Classfile /Users/mw/Projects/slang-braindump/.jar/jar8/assemble/slang-braindump/assemble/content/shapeless/HMap.class
  Last modified May 29, 2022; size 43127 bytes
  SHA-256 checksum 08b6cdd19e21eaeaed88569751bc12b6733770471c5a034fe26d648aa9a26fcc
  Compiled from "hmap.scala"
public class shapeless.HMap<R extends java.lang.Object> extends java.lang.Object implements shapeless.Poly1
  minor version: 0
  major version: 52
  flags: (0x0021) ACC_PUBLIC, ACC_SUPER
  this_class: #2                          // shapeless/HMap
  super_class: #5                         // java/lang/Object
  interfaces: 1, fields: 4, methods: 46, attributes: 7
Constant pool:
    #1 = Utf8               shapeless/HMap
    #2 = Class              #1            // shapeless/HMap
    #3 = Utf8               <R:Ljava/lang/Object;>Ljava/lang/Object;Lshapeless/Poly1;
    #4 = Utf8               java/lang/Object
    #5 = Class              #4            // java/lang/Object
    #6 = Utf8               shapeless/Poly1
    #7 = Class              #6            // shapeless/Poly1
    #8 = Utf8               hmap.scala
    #9 = Utf8               Lscala/reflect/ScalaSignature;
   #10 = Utf8               bytes
   #11 = Utf8               \u0006\u0005\u0005\re\u0001B\b\u0011\u0001MA\u0001b\b\u0001\u0003\u0002\u0003\u0006I\u0001\t\u0005\u0006]\u0001!\ta\f\u0005\u0006}\u0001!\ta\u0010\u0005\u0006!\u0002!\t!\u0015\u0005\u0006?\u0002!\t\u0001\u0019\u0005\u0006K\u0002!\u0019AZ\u0004\u0007\u007fBA\t!!\u0001\u0007\r=\u0001\u0002\u0012AA\u0002\u0011\u0019q\u0003\u0002\"\u0001\u0002\u0016!9\u0011q\u0003\u0005\u0005\u0002\u0005e\u0001bBA\u0017\u0011\u0011\u0005\u0011q\u0006\u0005\b\u0003[AA\u0011AA \u0011%\t\t\u0006CI\u0001\n\u0003\t\u0019\u0006C\u0005\u0002t!\t\t\u0011\"\u0003\u0002v\t!\u0001*T1q\u0015\u0005\t\u0012!C:iCB,G.Z:t\u0007\u0001)\"\u0001F\u001a\u0014\u0007\u0001)2\u0004\u0005\u0002\u001735\tqCC\u0001\u0019\u0003\u0015\u00198-\u00197b\u0013\tQrC\u0001\u0004B]f\u0014VM\u001a\t\u00039ui\u0011\u0001E\u0005\u0003=A\u0011Q\u0001U8msF\n!\"\u001e8eKJd\u00170\u001b8h!\u0011\t\u0003fK\u0016\u000f\u0005\t2\u0003CA\u0012\u0018\u001b\u0005!#BA\u0013\u0013\u0003\u0019a$o\\8u}%\u0011qeF\u0001\u0007!J,G-\u001a4\n\u0005%R#aA\'ba*\u0011qe\u0006\t\u0003-1J!!L\f\u0003\u0007\u0005s\u00170\u0001\u0004=S:LGO\u0010\u000b\u0003au\u00022\u0001\b\u00012!\t\u00114\u0007\u0004\u0001\u0005\u000bQ\u0002!\u0019A\u001b\u0003\u0003I+2A\u000e\u001e=#\t94\u0006\u0005\u0002\u0017q%\u0011\u0011h\u0006\u0002\b\u001d>$\b.\u001b8h\t\u0015Y4G1\u00017\u0005\u0005yF!B\u001e4\u0005\u00041\u0004bB\u0010\u0003!\u0003\u0005\r\u0001I\u0001\u0004O\u0016$Xc\u0001!M\rR\u0011\u0011I\u0014\u000b\u0003\u0005\"\u00032AF\"F\u0013\t!uC\u0001\u0004PaRLwN\u001c\t\u0003e\u0019#QaR\u0002C\u0002Y\u0012\u0011A\u0016\u0005\u0006\u0013\u000e\u0001\u001dAS\u0001\u0003KZ\u0004BAM\u001aL\u000bB\u0011!\u0007\u0014\u0003\u0006\u001b\u000e\u0011\rA\u000e\u0002\u0002\u0017\")qj\u0001a\u0001\u0017\u0006\t1.A\u0003%a2,8/F\u0002S/f#\"a\u0015.\u0015\u0005A\"\u0006\"B%\u0005\u0001\b)\u0006\u0003\u0002\u001a4-b\u0003\"AM,\u0005\u000b5#!\u0019\u0001\u001c\u0011\u0005IJF!B$\u0005\u0005\u00041\u0004\"B.\u0005\u0001\u0004a\u0016AA6w!\u00111RL\u0016-\n\u0005y;\"A\u0002+va2,\'\'\u0001\u0004%[&tWo]\u000b\u0003C\u0012$\"\u0001\r2\t\u000b=+\u0001\u0019A2\u0011\u0005I\"G!B\'\u0006\u0005\u00041\u0014aB2bg\u0016\u0014V\r\\\u000b\u0004OjdHC\u00015~!\u0015IW\u000f_=|\u001d\tQ\u0017O\u0004\u0002l]:\u0011A\u0004\\\u0005\u0003[B\tq\u0001]1dW\u0006<W-\u0003\u0002pa\u0006!\u0001o\u001c7z\u0015\ti\u0007#\u0003\u0002sg\u0006)1)Y:fc%\u0011A\u000f\u0005\u0002\u0006\u0007\u0006\u001cXm]\u0005\u0003m^\u00141!Q;y\u0015\t\u00118/D\u0001\u0001!\t\u0011$\u0010B\u0003N\r\t\u0007a\u0007\u0005\u00023y\u0012)qI\u0002b\u0001m!)\u0011J\u0002a\u0002}B!!gM=|\u0003\u0011AU*\u00199\u0011\u0005qA1\u0003\u0002\u0005\u0016\u0003\u000b\u0001B!a\u0002\u0002\u00125\u0011\u0011\u0011\u0002\u0006\u0005\u0003\u0017\ti!\u0001\u0002j_*\u0011\u0011qB\u0001\u0005U\u00064\u0018-\u0003\u0003\u0002\u0014\u0005%!\u0001D*fe&\fG.\u001b>bE2,GCAA\u0001\u0003\u0015\t\u0007\u000f\u001d7z+\u0011\tY\"!\n\u0016\u0005\u0005u\u0001#\u0002\u000f\u0002 \u0005\r\u0012bAA\u0011!\tY\u0001*T1q\u0005VLG\u000eZ3s!\r\u0011\u0014Q\u0005\u0003\u0007i)\u0011\r!a\n\u0016\u000bY\nI#a\u000b\u0005\rm\n)C1\u00017\t\u0019Y\u0014Q\u0005b\u0001m\u0005)Q-\u001c9usV!\u0011\u0011GA\u001c+\t\t\u0019\u0004\u0005\u0003\u001d\u0001\u0005U\u0002c\u0001\u001a\u00028\u00111Ag\u0003b\u0001\u0003s)RANA\u001e\u0003{!aaOA\u001c\u0005\u00041DAB\u001e\u00028\t\u0007a\'\u0006\u0003\u0002B\u0005\u001dC\u0003BA\"\u0003\u001f\u0002B\u0001\b\u0001\u0002FA\u0019!\'a\u0012\u0005\rQb!\u0019AA%+\u00151\u00141JA\'\t\u0019Y\u0014q\tb\u0001m\u001111(a\u0012C\u0002YBQa\b\u0007A\u0002\u0001\n1\u0004\n7fgNLg.\u001b;%OJ,\u0017\r^3sI\u0011,g-Y;mi\u0012\nT\u0003BA+\u0003W*\"!a\u0016+\u0007\u0001\nIf\u000b\u0002\u0002\\A!\u0011QLA4\u001b\t\tyF\u0003\u0003\u0002b\u0005\r\u0014!C;oG\",7m[3e\u0015\r\t)gF\u0001\u000bC:tw\u000e^1uS>t\u0017\u0002BA5\u0003?\u0012\u0011#\u001e8dQ\u0016\u001c7.\u001a3WCJL\u0017M\\2f\t\u0019!TB1\u0001\u0002nU)a\'a\u001c\u0002r\u001111(a\u001bC\u0002Y\"aaOA6\u0005\u00041\u0014\u0001D<sSR,\'+\u001a9mC\u000e,GCAA<!\u0011\tI(a \u000e\u0005\u0005m$\u0002BA?\u0003\u001b\tA\u0001\\1oO&!\u0011\u0011QA>\u0005\u0019y%M[3di\u0002
   #12 = Utf8               java/lang/invoke/MethodHandles$Lookup
   #13 = Class              #12           // java/lang/invoke/MethodHandles$Lookup
   #14 = Utf8               java/lang/invoke/MethodHandles
   #15 = Class              #14           // java/lang/invoke/MethodHandles
   #16 = Utf8               Lookup
   #17 = Utf8               shapeless/Cases$Case1$
   #18 = Class              #17           // shapeless/Cases$Case1$
   #19 = Utf8               shapeless/Cases
   #20 = Class              #19           // shapeless/Cases
   #21 = Utf8               Case1$
   #22 = Utf8               shapeless/Poly$CaseBuilder
   #23 = Class              #22           // shapeless/Poly$CaseBuilder
   #24 = Utf8               shapeless/Poly
   #25 = Class              #24           // shapeless/Poly
   #26 = Utf8               CaseBuilder
   #27 = Utf8               shapeless/Poly$CaseBuilder$
   #28 = Class              #27           // shapeless/Poly$CaseBuilder$
   #29 = Utf8               CaseBuilder$
   #30 = Utf8               shapeless/Poly$ProductCase$
   #31 = Class              #30           // shapeless/Poly$ProductCase$
   #32 = Utf8               ProductCase$
   #33 = Utf8               shapeless/Poly1$Case$
   #34 = Class              #33           // shapeless/Poly1$Case$
   #35 = Utf8               Case$
   #36 = Utf8               shapeless/Poly1$CaseBuilder
   #37 = Class              #36           // shapeless/Poly1$CaseBuilder
   #38 = Utf8               shapeless/PolyDefns$Case
   #39 = Class              #38           // shapeless/PolyDefns$Case
   #40 = Utf8               shapeless/PolyDefns
   #41 = Class              #40           // shapeless/PolyDefns
   #42 = Utf8               Case
   #43 = Utf8               shapeless/PolyDefns$Compose
   #44 = Class              #43           // shapeless/PolyDefns$Compose
   #45 = Utf8               Compose
   #46 = Utf8               shapeless/PolyDefns$RotateLeft
   #47 = Class              #46           // shapeless/PolyDefns$RotateLeft
   #48 = Utf8               RotateLeft
   #49 = Utf8               shapeless/PolyDefns$RotateRight
   #50 = Class              #49           // shapeless/PolyDefns$RotateRight
   #51 = Utf8               RotateRight
   #52 = Utf8               underlying
   #53 = Utf8               Lscala/collection/immutable/Map;
   #54 = Utf8               Lscala/collection/immutable/Map<Ljava/lang/Object;Ljava/lang/Object;>;
   #55 = Utf8               Case$module
   #56 = Utf8               Lshapeless/Poly1$Case$;
   #57 = Utf8               ProductCase$module
   #58 = Utf8               Lshapeless/Poly$ProductCase$;
   #59 = Utf8               CaseBuilder$module
   #60 = Utf8               Lshapeless/Poly$CaseBuilder$;
   #61 = Utf8               $lessinit$greater$default$1
   #62 = Utf8               ()Lscala/collection/immutable/Map;
   #63 = Utf8               <R:Ljava/lang/Object;>()Lscala/collection/immutable/Map<Ljava/lang/Object;Ljava/lang/Object;>;
   #64 = Utf8               shapeless/HMap$
   #65 = Class              #64           // shapeless/HMap$
   #66 = Utf8               MODULE$
   #67 = Utf8               Lshapeless/HMap$;
   #68 = NameAndType        #66:#67       // MODULE$:Lshapeless/HMap$;
   #69 = Fieldref           #65.#68       // shapeless/HMap$.MODULE$:Lshapeless/HMap$;
   #70 = NameAndType        #61:#62       // $lessinit$greater$default$1:()Lscala/collection/immutable/Map;
   #71 = Methodref          #65.#70       // shapeless/HMap$.$lessinit$greater$default$1:()Lscala/collection/immutable/Map;
   #72 = Utf8               empty
   #73 = Utf8               (Lscala/collection/immutable/Map;)Lshapeless/HMap;
   #74 = Utf8               <R:Ljava/lang/Object;>(Lscala/collection/immutable/Map<Ljava/lang/Object;Ljava/lang/Object;>;)Lshapeless/HMap<TR;>;
   #75 = NameAndType        #72:#73       // empty:(Lscala/collection/immutable/Map;)Lshapeless/HMap;
   #76 = Methodref          #65.#75       // shapeless/HMap$.empty:(Lscala/collection/immutable/Map;)Lshapeless/HMap;
   #77 = Utf8               ()Lshapeless/HMap;
   #78 = Utf8               <R:Ljava/lang/Object;>()Lshapeless/HMap<TR;>;
   #79 = NameAndType        #72:#77       // empty:()Lshapeless/HMap;
   #80 = Methodref          #65.#79       // shapeless/HMap$.empty:()Lshapeless/HMap;
   #81 = Utf8               at
   #82 = Utf8               ()Lshapeless/Poly1$CaseBuilder;
   #83 = Utf8               <A:Ljava/lang/Object;>()Lshapeless/Poly1$CaseBuilder<TA;>;
   #84 = Utf8               at$
   #85 = Utf8               (Lshapeless/Poly1;)Lshapeless/Poly1$CaseBuilder;
   #86 = NameAndType        #84:#85       // at$:(Lshapeless/Poly1;)Lshapeless/Poly1$CaseBuilder;
   #87 = InterfaceMethodref #7.#86        // shapeless/Poly1.at$:(Lshapeless/Poly1;)Lshapeless/Poly1$CaseBuilder;
   #88 = Utf8               this
   #89 = Utf8               Lshapeless/HMap;
   #90 = Utf8               compose
   #91 = Utf8               (Lshapeless/Poly;)Lshapeless/PolyDefns$Compose;
   #92 = Utf8               (Lshapeless/Poly;)Lshapeless/PolyDefns$Compose<Lshapeless/Poly;Lshapeless/Poly;>;
   #93 = Utf8               f
   #94 = Utf8               compose$
   #95 = Utf8               (Lshapeless/Poly;Lshapeless/Poly;)Lshapeless/PolyDefns$Compose;
   #96 = NameAndType        #94:#95       // compose$:(Lshapeless/Poly;Lshapeless/Poly;)Lshapeless/PolyDefns$Compose;
   #97 = InterfaceMethodref #25.#96       // shapeless/Poly.compose$:(Lshapeless/Poly;Lshapeless/Poly;)Lshapeless/PolyDefns$Compose;
   #98 = Utf8               Lshapeless/Poly;
   #99 = Utf8               andThen
  #100 = Utf8               andThen$
  #101 = NameAndType        #100:#95      // andThen$:(Lshapeless/Poly;Lshapeless/Poly;)Lshapeless/PolyDefns$Compose;
  #102 = InterfaceMethodref #25.#101      // shapeless/Poly.andThen$:(Lshapeless/Poly;Lshapeless/Poly;)Lshapeless/PolyDefns$Compose;
  #103 = Utf8               rotateLeft
  #104 = Utf8               ()Lshapeless/PolyDefns$RotateLeft;
  #105 = Utf8               <N::Lshapeless/Nat;>()Lshapeless/PolyDefns$RotateLeft<Lshapeless/Poly;TN;>;
  #106 = Utf8               rotateLeft$
  #107 = Utf8               (Lshapeless/Poly;)Lshapeless/PolyDefns$RotateLeft;
  #108 = NameAndType        #106:#107     // rotateLeft$:(Lshapeless/Poly;)Lshapeless/PolyDefns$RotateLeft;
  #109 = InterfaceMethodref #25.#108      // shapeless/Poly.rotateLeft$:(Lshapeless/Poly;)Lshapeless/PolyDefns$RotateLeft;
  #110 = Utf8               rotateRight
  #111 = Utf8               ()Lshapeless/PolyDefns$RotateRight;
  #112 = Utf8               <N::Lshapeless/Nat;>()Lshapeless/PolyDefns$RotateRight<Lshapeless/Poly;TN;>;
  #113 = Utf8               rotateRight$
  #114 = Utf8               (Lshapeless/Poly;)Lshapeless/PolyDefns$RotateRight;
  #115 = NameAndType        #113:#114     // rotateRight$:(Lshapeless/Poly;)Lshapeless/PolyDefns$RotateRight;
  #116 = InterfaceMethodref #25.#115      // shapeless/Poly.rotateRight$:(Lshapeless/Poly;)Lshapeless/PolyDefns$RotateRight;
  #117 = Utf8               use
  #118 = Utf8               (Ljava/lang/Object;Lshapeless/Poly$CaseBuilder;)Lshapeless/PolyDefns$Case;
  #119 = Utf8               <T:Ljava/lang/Object;L::Lshapeless/HList;R:Ljava/lang/Object;>(TT;Lshapeless/Poly$CaseBuilder<TT;TL;TR;>;)Lshapeless/PolyDefns$Case<Lshapeless/Poly;TL;>;
  #120 = Utf8               t
  #121 = Utf8               cb
  #122 = Utf8               use$
  #123 = Utf8               (Lshapeless/Poly;Ljava/lang/Object;Lshapeless/Poly$CaseBuilder;)Lshapeless/PolyDefns$Case;
  #124 = NameAndType        #122:#123     // use$:(Lshapeless/Poly;Ljava/lang/Object;Lshapeless/Poly$CaseBuilder;)Lshapeless/PolyDefns$Case;
  #125 = InterfaceMethodref #25.#124      // shapeless/Poly.use$:(Lshapeless/Poly;Ljava/lang/Object;Lshapeless/Poly$CaseBuilder;)Lshapeless/PolyDefns$Case;
  #126 = Utf8               Ljava/lang/Object;
  #127 = Utf8               Lshapeless/Poly$CaseBuilder;
  #128 = Utf8               caseAt
  #129 = Utf8               (Lshapeless/PolyDefns$Case;)Lshapeless/PolyDefns$Case;
  #130 = Utf8               <L::Lshapeless/HList;>(Lshapeless/PolyDefns$Case<Lshapeless/Poly;TL;>;)Lshapeless/PolyDefns$Case<Lshapeless/Poly;TL;>;
  #131 = Utf8               c
  #132 = Utf8               caseAt$
  #133 = Utf8               (Lshapeless/Poly;Lshapeless/PolyDefns$Case;)Lshapeless/PolyDefns$Case;
  #134 = NameAndType        #132:#133     // caseAt$:(Lshapeless/Poly;Lshapeless/PolyDefns$Case;)Lshapeless/PolyDefns$Case;
  #135 = InterfaceMethodref #25.#134      // shapeless/Poly.caseAt$:(Lshapeless/Poly;Lshapeless/PolyDefns$Case;)Lshapeless/PolyDefns$Case;
  #136 = Utf8               Lshapeless/PolyDefns$Case;
  #137 = Utf8               apply
  #138 = Utf8               (Lshapeless/PolyDefns$Case;)Ljava/lang/Object;
  #139 = Utf8               <R:Ljava/lang/Object;>(Lshapeless/PolyDefns$Case<Lshapeless/Poly;Lshapeless/HNil;>;)TR;
  #140 = Utf8               apply$
  #141 = Utf8               (Lshapeless/Poly;Lshapeless/PolyDefns$Case;)Ljava/lang/Object;
  #142 = NameAndType        #140:#141     // apply$:(Lshapeless/Poly;Lshapeless/PolyDefns$Case;)Ljava/lang/Object;
  #143 = InterfaceMethodref #25.#142      // shapeless/Poly.apply$:(Lshapeless/Poly;Lshapeless/PolyDefns$Case;)Ljava/lang/Object;
  #144 = Utf8               (Ljava/lang/Object;Lshapeless/PolyDefns$Case;)Ljava/lang/Object;
  #145 = Utf8               <A:Ljava/lang/Object;>(TA;Lshapeless/PolyDefns$Case<Lshapeless/PolyApply;Lshapeless/$colon$colon<TA;Lshapeless/HNil;>;>;)Ljava/lang/Object;
  #146 = Utf8               a
  #147 = Utf8               cse
  #148 = Utf8               shapeless/PolyApply
  #149 = Class              #148          // shapeless/PolyApply
  #150 = Utf8               (Lshapeless/PolyApply;Ljava/lang/Object;Lshapeless/PolyDefns$Case;)Ljava/lang/Object;
  #151 = NameAndType        #140:#150     // apply$:(Lshapeless/PolyApply;Ljava/lang/Object;Lshapeless/PolyDefns$Case;)Ljava/lang/Object;
  #152 = InterfaceMethodref #149.#151     // shapeless/PolyApply.apply$:(Lshapeless/PolyApply;Ljava/lang/Object;Lshapeless/PolyDefns$Case;)Ljava/lang/Object;
  #153 = Utf8               (Ljava/lang/Object;Ljava/lang/Object;Lshapeless/PolyDefns$Case;)Ljava/lang/Object;
  #154 = Utf8               <A:Ljava/lang/Object;B:Ljava/lang/Object;>(TA;TB;Lshapeless/PolyDefns$Case<Lshapeless/PolyApply;Lshapeless/$colon$colon<TA;Lshapeless/$colon$colon<TB;Lshapeless/HNil;>;>;>;)Ljava/lang/Object;
  #155 = Utf8               b
  #156 = Utf8               (Lshapeless/PolyApply;Ljava/lang/Object;Ljava/lang/Object;Lshapeless/PolyDefns$Case;)Ljava/lang/Object;
  #157 = NameAndType        #140:#156     // apply$:(Lshapeless/PolyApply;Ljava/lang/Object;Ljava/lang/Object;Lshapeless/PolyDefns$Case;)Ljava/lang/Object;
  #158 = InterfaceMethodref #149.#157     // shapeless/PolyApply.apply$:(Lshapeless/PolyApply;Ljava/lang/Object;Ljava/lang/Object;Lshapeless/PolyDefns$Case;)Ljava/lang/Object;
  #159 = Utf8               (Ljava/lang/Object;Ljava/lang/Object;Ljava/lang/Object;Lshapeless/PolyDefns$Case;)Ljava/lang/Object;
  #160 = Utf8               <A:Ljava/lang/Object;B:Ljava/lang/Object;C:Ljava/lang/Object;>(TA;TB;TC;Lshapeless/PolyDefns$Case<Lshapeless/PolyApply;Lshapeless/$colon$colon<TA;Lshapeless/$colon$colon<TB;Lshapeless/$colon$colon<TC;Lshapeless/HNil;>;>;>;>;)Ljava/lang/Object;
  #161 = Utf8               (Lshapeless/PolyApply;Ljava/lang/Object;Ljava/lang/Object;Ljava/lang/Object;Lshapeless/PolyDefns$Case;)Ljava/lang/Object;
  #162 = NameAndType        #140:#161     // apply$:(Lshapeless/PolyApply;Ljava/lang/Object;Ljava/lang/Object;Ljava/lang/Object;Lshapeless/PolyDefns$Case;)Ljava/lang/Object;
  #163 = InterfaceMethodref #149.#162     // shapeless/PolyApply.apply$:(Lshapeless/PolyApply;Ljava/lang/Object;Ljava/lang/Object;Ljava/lang/Object;Lshapeless/PolyDefns$Case;)Ljava/lang/Object;
  #164 = Utf8               (Ljava/lang/Object;Ljava/lang/Object;Ljava/lang/Object;Ljava/lang/Object;Lshapeless/PolyDefns$Case;)Ljava/lang/Object;
  #165 = Utf8               <A:Ljava/lang/Object;B:Ljava/lang/Object;C:Ljava/lang/Object;D:Ljava/lang/Object;>(TA;TB;TC;TD;Lshapeless/PolyDefns$Case<Lshapeless/PolyApply;Lshapeless/$colon$colon<TA;Lshapeless/$colon$colon<TB;Lshapeless/$colon$colon<TC;Lshapeless/$colon$colon<TD;Lshapeless/HNil;>;>;>;>;>;)Ljava/lang/Object;
  #166 = Utf8               d
  #167 = Utf8               (Lshapeless/PolyApply;Ljava/lang/Object;Ljava/lang/Object;Ljava/lang/Object;Ljava/lang/Object;Lshapeless/PolyDefns$Case;)Ljava/lang/Object;
  #168 = NameAndType        #140:#167     // apply$:(Lshapeless/PolyApply;Ljava/lang/Object;Ljava/lang/Object;Ljava/lang/Object;Ljava/lang/Object;Lshapeless/PolyDefns$Case;)Ljava/lang/Object;
  #169 = InterfaceMethodref #149.#168     // shapeless/PolyApply.apply$:(Lshapeless/PolyApply;Ljava/lang/Object;Ljava/lang/Object;Ljava/lang/Object;Ljava/lang/Object;Lshapeless/PolyDefns$Case;)Ljava/lang/Object;
  #170 = Utf8               (Ljava/lang/Object;Ljava/lang/Object;Ljava/lang/Object;Ljava/lang/Object;Ljava/lang/Object;Lshapeless/PolyDefns$Case;)Ljava/lang/Object;
  #171 = Utf8               <A:Ljava/lang/Object;B:Ljava/lang/Object;C:Ljava/lang/Object;D:Ljava/lang/Object;E:Ljava/lang/Object;>(TA;TB;TC;TD;TE;Lshapeless/PolyDefns$Case<Lshapeless/PolyApply;Lshapeless/$colon$colon<TA;Lshapeless/$colon$colon<TB;Lshapeless/$colon$colon<TC;Lshapeless/$colon$colon<TD;Lshapeless/$colon$colon<TE;Lshapeless/HNil;>;>;>;>;>;>;)Ljava/lang/Object;
  #172 = Utf8               e
  #173 = Utf8               (Lshapeless/PolyApply;Ljava/lang/Object;Ljava/lang/Object;Ljava/lang/Object;Ljava/lang/Object;Ljava/lang/Object;Lshapeless/PolyDefns$Case;)Ljava/lang/Object;
  #174 = NameAndType        #140:#173     // apply$:(Lshapeless/PolyApply;Ljava/lang/Object;Ljava/lang/Object;Ljava/lang/Object;Ljava/lang/Object;Ljava/lang/Object;Lshapeless/PolyDefns$Case;)Ljava/lang/Object;
  #175 = InterfaceMethodref #149.#174     // shapeless/PolyApply.apply$:(Lshapeless/PolyApply;Ljava/lang/Object;Ljava/lang/Object;Ljava/lang/Object;Ljava/lang/Object;Ljava/lang/Object;Lshapeless/PolyDefns$Case;)Ljava/lang/Object;
  #176 = Utf8               (Ljava/lang/Object;Ljava/lang/Object;Ljava/lang/Object;Ljava/lang/Object;Ljava/lang/Object;Ljava/lang/Object;Lshapeless/PolyDefns$Case;)Ljava/lang/Object;
  #177 = Utf8               <A:Ljava/lang/Object;B:Ljava/lang/Object;C:Ljava/lang/Object;D:Ljava/lang/Object;E:Ljava/lang/Object;F:Ljava/lang/Object;>(TA;TB;TC;TD;TE;TF;Lshapeless/PolyDefns$Case<Lshapeless/PolyApply;Lshapeless/$colon$colon<TA;Lshapeless/$colon$colon<TB;Lshapeless/$colon$colon<TC;Lshapeless/$colon$colon<TD;Lshapeless/$colon$colon<TE;Lshapeless/$colon$colon<TF;Lshapeless/HNil;>;>;>;>;>;>;>;)Ljava/lang/Object;
  #178 = Utf8               (Lshapeless/PolyApply;Ljava/lang/Object;Ljava/lang/Object;Ljava/lang/Object;Ljava/lang/Object;Ljava/lang/Object;Ljava/lang/Object;Lshapeless/PolyDefns$Case;)Ljava/lang/Object;
  #179 = NameAndType        #140:#178     // apply$:(Lshapeless/PolyApply;Ljava/lang/Object;Ljava/lang/Object;Ljava/lang/Object;Ljava/lang/Object;Ljava/lang/Object;Ljava/lang/Object;Lshapeless/PolyDefns$Case;)Ljava/lang/Object;
  #180 = InterfaceMethodref #149.#179     // shapeless/PolyApply.apply$:(Lshapeless/PolyApply;Ljava/lang/Object;Ljava/lang/Object;Ljava/lang/Object;Ljava/lang/Object;Ljava/lang/Object;Ljava/lang/Object;Lshapeless/PolyDefns$Case;)Ljava/lang/Object;
  #181 = Utf8               (Ljava/lang/Object;Ljava/lang/Object;Ljava/lang/Object;Ljava/lang/Object;Ljava/lang/Object;Ljava/lang/Object;Ljava/lang/Object;Lshapeless/PolyDefns$Case;)Ljava/lang/Object;
  #182 = Utf8               <A:Ljava/lang/Object;B:Ljava/lang/Object;C:Ljava/lang/Object;D:Ljava/lang/Object;E:Ljava/lang/Object;F:Ljava/lang/Object;G:Ljava/lang/Object;>(TA;TB;TC;TD;TE;TF;TG;Lshapeless/PolyDefns$Case<Lshapeless/PolyApply;Lshapeless/$colon$colon<TA;Lshapeless/$colon$colon<TB;Lshapeless/$colon$colon<TC;Lshapeless/$colon$colon<TD;Lshapeless/$colon$colon<TE;Lshapeless/$colon$colon<TF;Lshapeless/$colon$colon<TG;Lshapeless/HNil;>;>;>;>;>;>;>;>;)Ljava/lang/Object;
  #183 = Utf8               g
  #184 = Utf8               (Lshapeless/PolyApply;Ljava/lang/Object;Ljava/lang/Object;Ljava/lang/Object;Ljava/lang/Object;Ljava/lang/Object;Ljava/lang/Object;Ljava/lang/Object;Lshapeless/PolyDefns$Case;)Ljava/lang/Object;
  #185 = NameAndType        #140:#184     // apply$:(Lshapeless/PolyApply;Ljava/lang/Object;Ljava/lang/Object;Ljava/lang/Object;Ljava/lang/Object;Ljava/lang/Object;Ljava/lang/Object;Ljava/lang/Object;Lshapeless/PolyDefns$Case;)Ljava/lang/Object;
  #186 = InterfaceMethodref #149.#185     // shapeless/PolyApply.apply$:(Lshapeless/PolyApply;Ljava/lang/Object;Ljava/lang/Object;Ljava/lang/Object;Ljava/lang/Object;Ljava/lang/Object;Ljava/lang/Object;Ljava/lang/Object;Lshapeless/PolyDefns$Case;)Ljava/lang/Object;
  #187 = Utf8               (Ljava/lang/Object;Ljava/lang/Object;Ljava/lang/Object;Ljava/lang/Object;Ljava/lang/Object;Ljava/lang/Object;Ljava/lang/Object;Ljava/lang/Object;Lshapeless/PolyDefns$Case;)Ljava/lang/Object;
  #188 = Utf8               <A:Ljava/lang/Object;B:Ljava/lang/Object;C:Ljava/lang/Object;D:Ljava/lang/Object;E:Ljava/lang/Object;F:Ljava/lang/Object;G:Ljava/lang/Object;H:Ljava/lang/Object;>(TA;TB;TC;TD;TE;TF;TG;TH;Lshapeless/PolyDefns$Case<Lshapeless/PolyApply;Lshapeless/$colon$colon<TA;Lshapeless/$colon$colon<TB;Lshapeless/$colon$colon<TC;Lshapeless/$colon$colon<TD;Lshapeless/$colon$colon<TE;Lshapeless/$colon$colon<TF;Lshapeless/$colon$colon<TG;Lshapeless/$colon$colon<TH;Lshapeless/HNil;>;>;>;>;>;>;>;>;>;)Ljava/lang/Object;
  #189 = Utf8               h
  #190 = Utf8               (Lshapeless/PolyApply;Ljava/lang/Object;Ljava/lang/Object;Ljava/lang/Object;Ljava/lang/Object;Ljava/lang/Object;Ljava/lang/Object;Ljava/lang/Object;Ljava/lang/Object;Lshapeless/PolyDefns$Case;)Ljava/lang/Object;
  #191 = NameAndType        #140:#190     // apply$:(Lshapeless/PolyApply;Ljava/lang/Object;Ljava/lang/Object;Ljava/lang/Object;Ljava/lang/Object;Ljava/lang/Object;Ljava/lang/Object;Ljava/lang/Object;Ljava/lang/Object;Lshapeless/PolyDefns$Case;)Ljava/lang/Object;
  #192 = InterfaceMethodref #149.#191     // shapeless/PolyApply.apply$:(Lshapeless/PolyApply;Ljava/lang/Object;Ljava/lang/Object;Ljava/lang/Object;Ljava/lang/Object;Ljava/lang/Object;Ljava/lang/Object;Ljava/lang/Object;Ljava/lang/Object;Lshapeless/PolyDefns$Case;)Ljava/lang/Object;
  #193 = Utf8               (Ljava/lang/Object;Ljava/lang/Object;Ljava/lang/Object;Ljava/lang/Object;Ljava/lang/Object;Ljava/lang/Object;Ljava/lang/Object;Ljava/lang/Object;Ljava/lang/Object;Lshapeless/PolyDefns$Case;)Ljava/lang/Object;
  #194 = Utf8               <A:Ljava/lang/Object;B:Ljava/lang/Object;C:Ljava/lang/Object;D:Ljava/lang/Object;E:Ljava/lang/Object;F:Ljava/lang/Object;G:Ljava/lang/Object;H:Ljava/lang/Object;I:Ljava/lang/Object;>(TA;TB;TC;TD;TE;TF;TG;TH;TI;Lshapeless/PolyDefns$Case<Lshapeless/PolyApply;Lshapeless/$colon$colon<TA;Lshapeless/$colon$colon<TB;Lshapeless/$colon$colon<TC;Lshapeless/$colon$colon<TD;Lshapeless/$colon$colon<TE;Lshapeless/$colon$colon<TF;Lshapeless/$colon$colon<TG;Lshapeless/$colon$colon<TH;Lshapeless/$colon$colon<TI;Lshapeless/HNil;>;>;>;>;>;>;>;>;>;>;)Ljava/lang/Object;
  #195 = Utf8               i
  #196 = Utf8               (Lshapeless/PolyApply;Ljava/lang/Object;Ljava/lang/Object;Ljava/lang/Object;Ljava/lang/Object;Ljava/lang/Object;Ljava/lang/Object;Ljava/lang/Object;Ljava/lang/Object;Ljava/lang/Object;Lshapeless/PolyDefns$Case;)Ljava/lang/Object;
  #197 = NameAndType        #140:#196     // apply$:(Lshapeless/PolyApply;Ljava/lang/Object;Ljava/lang/Object;Ljava/lang/Object;Ljava/lang/Object;Ljava/lang/Object;Ljava/lang/Object;Ljava/lang/Object;Ljava/lang/Object;Ljava/lang/Object;Lshapeless/PolyDefns$Case;)Ljava/lang/Object;
  #198 = InterfaceMethodref #149.#197     // shapeless/PolyApply.apply$:(Lshapeless/PolyApply;Ljava/lang/Object;Ljava/lang/Object;Ljava/lang/Object;Ljava/lang/Object;Ljava/lang/Object;Ljava/lang/Object;Ljava/lang/Object;Ljava/lang/Object;Ljava/lang/Object;Lshapeless/PolyDefns$Case;)Ljava/lang/Object;
  #199 = Utf8               (Ljava/lang/Object;Ljava/lang/Object;Ljava/lang/Object;Ljava/lang/Object;Ljava/lang/Object;Ljava/lang/Object;Ljava/lang/Object;Ljava/lang/Object;Ljava/lang/Object;Ljava/lang/Object;Lshapeless/PolyDefns$Case;)Ljava/lang/Object;
  #200 = Utf8               <A:Ljava/lang/Object;B:Ljava/lang/Object;C:Ljava/lang/Object;D:Ljava/lang/Object;E:Ljava/lang/Object;F:Ljava/lang/Object;G:Ljava/lang/Object;H:Ljava/lang/Object;I:Ljava/lang/Object;J:Ljava/lang/Object;>(TA;TB;TC;TD;TE;TF;TG;TH;TI;TJ;Lshapeless/PolyDefns$Case<Lshapeless/PolyApply;Lshapeless/$colon$colon<TA;Lshapeless/$colon$colon<TB;Lshapeless/$colon$colon<TC;Lshapeless/$colon$colon<TD;Lshapeless/$colon$colon<TE;Lshapeless/$colon$colon<TF;Lshapeless/$colon$colon<TG;Lshapeless/$colon$colon<TH;Lshapeless/$colon$colon<TI;Lshapeless/$colon$colon<TJ;Lshapeless/HNil;>;>;>;>;>;>;>;>;>;>;>;)Ljava/lang/Object;
  #201 = Utf8               j
  #202 = Utf8               (Lshapeless/PolyApply;Ljava/lang/Object;Ljava/lang/Object;Ljava/lang/Object;Ljava/lang/Object;Ljava/lang/Object;Ljava/lang/Object;Ljava/lang/Object;Ljava/lang/Object;Ljava/lang/Object;Ljava/lang/Object;Lshapeless/PolyDefns$Case;)Ljava/lang/Object;
  #203 = NameAndType        #140:#202     // apply$:(Lshapeless/PolyApply;Ljava/lang/Object;Ljava/lang/Object;Ljava/lang/Object;Ljava/lang/Object;Ljava/lang/Object;Ljava/lang/Object;Ljava/lang/Object;Ljava/lang/Object;Ljava/lang/Object;Ljava/lang/Object;Lshapeless/PolyDefns$Case;)Ljava/lang/Object;
  #204 = InterfaceMethodref #149.#203     // shapeless/PolyApply.apply$:(Lshapeless/PolyApply;Ljava/lang/Object;Ljava/lang/Object;Ljava/lang/Object;Ljava/lang/Object;Ljava/lang/Object;Ljava/lang/Object;Ljava/lang/Object;Ljava/lang/Object;Ljava/lang/Object;Ljava/lang/Object;Lshapeless/PolyDefns$Case;)Ljava/lang/Object;
  #205 = Utf8               (Ljava/lang/Object;Ljava/lang/Object;Ljava/lang/Object;Ljava/lang/Object;Ljava/lang/Object;Ljava/lang/Object;Ljava/lang/Object;Ljava/lang/Object;Ljava/lang/Object;Ljava/lang/Object;Ljava/lang/Object;Lshapeless/PolyDefns$Case;)Ljava/lang/Object;
  #206 = Utf8               <A:Ljava/lang/Object;B:Ljava/lang/Object;C:Ljava/lang/Object;D:Ljava/lang/Object;E:Ljava/lang/Object;F:Ljava/lang/Object;G:Ljava/lang/Object;H:Ljava/lang/Object;I:Ljava/lang/Object;J:Ljava/lang/Object;K:Ljava/lang/Object;>(TA;TB;TC;TD;TE;TF;TG;TH;TI;TJ;TK;Lshapeless/PolyDefns$Case<Lshapeless/PolyApply;Lshapeless/$colon$colon<TA;Lshapeless/$colon$colon<TB;Lshapeless/$colon$colon<TC;Lshapeless/$colon$colon<TD;Lshapeless/$colon$colon<TE;Lshapeless/$colon$colon<TF;Lshapeless/$colon$colon<TG;Lshapeless/$colon$colon<TH;Lshapeless/$colon$colon<TI;Lshapeless/$colon$colon<TJ;Lshapeless/$colon$colon<TK;Lshapeless/HNil;>;>;>;>;>;>;>;>;>;>;>;>;)Ljava/lang/Object;
  #207 = Utf8               k
  #208 = Utf8               (Lshapeless/PolyApply;Ljava/lang/Object;Ljava/lang/Object;Ljava/lang/Object;Ljava/lang/Object;Ljava/lang/Object;Ljava/lang/Object;Ljava/lang/Object;Ljava/lang/Object;Ljava/lang/Object;Ljava/lang/Object;Ljava/lang/Object;Lshapeless/PolyDefns$Case;)Ljava/lang/Object;
  #209 = NameAndType        #140:#208     // apply$:(Lshapeless/PolyApply;Ljava/lang/Object;Ljava/lang/Object;Ljava/lang/Object;Ljava/lang/Object;Ljava/lang/Object;Ljava/lang/Object;Ljava/lang/Object;Ljava/lang/Object;Ljava/lang/Object;Ljava/lang/Object;Ljava/lang/Object;Lshapeless/PolyDefns$Case;)Ljava/lang/Object;
  #210 = InterfaceMethodref #149.#209     // shapeless/PolyApply.apply$:(Lshapeless/PolyApply;Ljava/lang/Object;Ljava/lang/Object;Ljava/lang/Object;Ljava/lang/Object;Ljava/lang/Object;Ljava/lang/Object;Ljava/lang/Object;Ljava/lang/Object;Ljava/lang/Object;Ljava/lang/Object;Ljava/lang/Object;Lshapeless/PolyDefns$Case;)Ljava/lang/Object;
  #211 = Utf8               (Ljava/lang/Object;Ljava/lang/Object;Ljava/lang/Object;Ljava/lang/Object;Ljava/lang/Object;Ljava/lang/Object;Ljava/lang/Object;Ljava/lang/Object;Ljava/lang/Object;Ljava/lang/Object;Ljava/lang/Object;Ljava/lang/Object;Lshapeless/PolyDefns$Case;)Ljava/lang/Object;
  #212 = Utf8               <A:Ljava/lang/Object;B:Ljava/lang/Object;C:Ljava/lang/Object;D:Ljava/lang/Object;E:Ljava/lang/Object;F:Ljava/lang/Object;G:Ljava/lang/Object;H:Ljava/lang/Object;I:Ljava/lang/Object;J:Ljava/lang/Object;K:Ljava/lang/Object;L:Ljava/lang/Object;>(TA;TB;TC;TD;TE;TF;TG;TH;TI;TJ;TK;TL;Lshapeless/PolyDefns$Case<Lshapeless/PolyApply;Lshapeless/$colon$colon<TA;Lshapeless/$colon$colon<TB;Lshapeless/$colon$colon<TC;Lshapeless/$colon$colon<TD;Lshapeless/$colon$colon<TE;Lshapeless/$colon$colon<TF;Lshapeless/$colon$colon<TG;Lshapeless/$colon$colon<TH;Lshapeless/$colon$colon<TI;Lshapeless/$colon$colon<TJ;Lshapeless/$colon$colon<TK;Lshapeless/$colon$colon<TL;Lshapeless/HNil;>;>;>;>;>;>;>;>;>;>;>;>;>;)Ljava/lang/Object;
  #213 = Utf8               l
  #214 = Utf8               (Lshapeless/PolyApply;Ljava/lang/Object;Ljava/lang/Object;Ljava/lang/Object;Ljava/lang/Object;Ljava/lang/Object;Ljava/lang/Object;Ljava/lang/Object;Ljava/lang/Object;Ljava/lang/Object;Ljava/lang/Object;Ljava/lang/Object;Ljava/lang/Object;Lshapeless/PolyDefns$Case;)Ljava/lang/Object;
  #215 = NameAndType        #140:#214     // apply$:(Lshapeless/PolyApply;Ljava/lang/Object;Ljava/lang/Object;Ljava/lang/Object;Ljava/lang/Object;Ljava/lang/Object;Ljava/lang/Object;Ljava/lang/Object;Ljava/lang/Object;Ljava/lang/Object;Ljava/lang/Object;Ljava/lang/Object;Ljava/lang/Object;Lshapeless/PolyDefns$Case;)Ljava/lang/Object;
  #216 = InterfaceMethodref #149.#215     // shapeless/PolyApply.apply$:(Lshapeless/PolyApply;Ljava/lang/Object;Ljava/lang/Object;Ljava/lang/Object;Ljava/lang/Object;Ljava/lang/Object;Ljava/lang/Object;Ljava/lang/Object;Ljava/lang/Object;Ljava/lang/Object;Ljava/lang/Object;Ljava/lang/Object;Ljava/lang/Object;Lshapeless/PolyDefns$Case;)Ljava/lang/Object;
  #217 = Utf8               (Ljava/lang/Object;Ljava/lang/Object;Ljava/lang/Object;Ljava/lang/Object;Ljava/lang/Object;Ljava/lang/Object;Ljava/lang/Object;Ljava/lang/Object;Ljava/lang/Object;Ljava/lang/Object;Ljava/lang/Object;Ljava/lang/Object;Ljava/lang/Object;Lshapeless/PolyDefns$Case;)Ljava/lang/Object;
  #218 = Utf8               <A:Ljava/lang/Object;B:Ljava/lang/Object;C:Ljava/lang/Object;D:Ljava/lang/Object;E:Ljava/lang/Object;F:Ljava/lang/Object;G:Ljava/lang/Object;H:Ljava/lang/Object;I:Ljava/lang/Object;J:Ljava/lang/Object;K:Ljava/lang/Object;L:Ljava/lang/Object;M:Ljava/lang/Object;>(TA;TB;TC;TD;TE;TF;TG;TH;TI;TJ;TK;TL;TM;Lshapeless/PolyDefns$Case<Lshapeless/PolyApply;Lshapeless/$colon$colon<TA;Lshapeless/$colon$colon<TB;Lshapeless/$colon$colon<TC;Lshapeless/$colon$colon<TD;Lshapeless/$colon$colon<TE;Lshapeless/$colon$colon<TF;Lshapeless/$colon$colon<TG;Lshapeless/$colon$colon<TH;Lshapeless/$colon$colon<TI;Lshapeless/$colon$colon<TJ;Lshapeless/$colon$colon<TK;Lshapeless/$colon$colon<TL;Lshapeless/$colon$colon<TM;Lshapeless/HNil;>;>;>;>;>;>;>;>;>;>;>;>;>;>;)Ljava/lang/Object;
  #219 = Utf8               m
  #220 = Utf8               (Lshapeless/PolyApply;Ljava/lang/Object;Ljava/lang/Object;Ljava/lang/Object;Ljava/lang/Object;Ljava/lang/Object;Ljava/lang/Object;Ljava/lang/Object;Ljava/lang/Object;Ljava/lang/Object;Ljava/lang/Object;Ljava/lang/Object;Ljava/lang/Object;Ljava/lang/Object;Lshapeless/PolyDefns$Case;)Ljava/lang/Object;
  #221 = NameAndType        #140:#220     // apply$:(Lshapeless/PolyApply;Ljava/lang/Object;Ljava/lang/Object;Ljava/lang/Object;Ljava/lang/Object;Ljava/lang/Object;Ljava/lang/Object;Ljava/lang/Object;Ljava/lang/Object;Ljava/lang/Object;Ljava/lang/Object;Ljava/lang/Object;Ljava/lang/Object;Ljava/lang/Object;Lshapeless/PolyDefns$Case;)Ljava/lang/Object;
  #222 = InterfaceMethodref #149.#221     // shapeless/PolyApply.apply$:(Lshapeless/PolyApply;Ljava/lang/Object;Ljava/lang/Object;Ljava/lang/Object;Ljava/lang/Object;Ljava/lang/Object;Ljava/lang/Object;Ljava/lang/Object;Ljava/lang/Object;Ljava/lang/Object;Ljava/lang/Object;Ljava/lang/Object;Ljava/lang/Object;Ljava/lang/Object;Lshapeless/PolyDefns$Case;)Ljava/lang/Object;
  #223 = Utf8               (Ljava/lang/Object;Ljava/lang/Object;Ljava/lang/Object;Ljava/lang/Object;Ljava/lang/Object;Ljava/lang/Object;Ljava/lang/Object;Ljava/lang/Object;Ljava/lang/Object;Ljava/lang/Object;Ljava/lang/Object;Ljava/lang/Object;Ljava/lang/Object;Ljava/lang/Object;Lshapeless/PolyDefns$Case;)Ljava/lang/Object;
  #224 = Utf8               <A:Ljava/lang/Object;B:Ljava/lang/Object;C:Ljava/lang/Object;D:Ljava/lang/Object;E:Ljava/lang/Object;F:Ljava/lang/Object;G:Ljava/lang/Object;H:Ljava/lang/Object;I:Ljava/lang/Object;J:Ljava/lang/Object;K:Ljava/lang/Object;L:Ljava/lang/Object;M:Ljava/lang/Object;N:Ljava/lang/Object;>(TA;TB;TC;TD;TE;TF;TG;TH;TI;TJ;TK;TL;TM;TN;Lshapeless/PolyDefns$Case<Lshapeless/PolyApply;Lshapeless/$colon$colon<TA;Lshapeless/$colon$colon<TB;Lshapeless/$colon$colon<TC;Lshapeless/$colon$colon<TD;Lshapeless/$colon$colon<TE;Lshapeless/$colon$colon<TF;Lshapeless/$colon$colon<TG;Lshapeless/$colon$colon<TH;Lshapeless/$colon$colon<TI;Lshapeless/$colon$colon<TJ;Lshapeless/$colon$colon<TK;Lshapeless/$colon$colon<TL;Lshapeless/$colon$colon<TM;Lshapeless/$colon$colon<TN;Lshapeless/HNil;>;>;>;>;>;>;>;>;>;>;>;>;>;>;>;)Ljava/lang/Object;
  #225 = Utf8               n
  #226 = Utf8               (Lshapeless/PolyApply;Ljava/lang/Object;Ljava/lang/Object;Ljava/lang/Object;Ljava/lang/Object;Ljava/lang/Object;Ljava/lang/Object;Ljava/lang/Object;Ljava/lang/Object;Ljava/lang/Object;Ljava/lang/Object;Ljava/lang/Object;Ljava/lang/Object;Ljava/lang/Object;Ljava/lang/Object;Lshapeless/PolyDefns$Case;)Ljava/lang/Object;
  #227 = NameAndType        #140:#226     // apply$:(Lshapeless/PolyApply;Ljava/lang/Object;Ljava/lang/Object;Ljava/lang/Object;Ljava/lang/Object;Ljava/lang/Object;Ljava/lang/Object;Ljava/lang/Object;Ljava/lang/Object;Ljava/lang/Object;Ljava/lang/Object;Ljava/lang/Object;Ljava/lang/Object;Ljava/lang/Object;Ljava/lang/Object;Lshapeless/PolyDefns$Case;)Ljava/lang/Object;
  #228 = InterfaceMethodref #149.#227     // shapeless/PolyApply.apply$:(Lshapeless/PolyApply;Ljava/lang/Object;Ljava/lang/Object;Ljava/lang/Object;Ljava/lang/Object;Ljava/lang/Object;Ljava/lang/Object;Ljava/lang/Object;Ljava/lang/Object;Ljava/lang/Object;Ljava/lang/Object;Ljava/lang/Object;Ljava/lang/Object;Ljava/lang/Object;Ljava/lang/Object;Lshapeless/PolyDefns$Case;)Ljava/lang/Object;
  #229 = Utf8               (Ljava/lang/Object;Ljava/lang/Object;Ljava/lang/Object;Ljava/lang/Object;Ljava/lang/Object;Ljava/lang/Object;Ljava/lang/Object;Ljava/lang/Object;Ljava/lang/Object;Ljava/lang/Object;Ljava/lang/Object;Ljava/lang/Object;Ljava/lang/Object;Ljava/lang/Object;Ljava/lang/Object;Lshapeless/PolyDefns$Case;)Ljava/lang/Object;
  #230 = Utf8               <A:Ljava/lang/Object;B:Ljava/lang/Object;C:Ljava/lang/Object;D:Ljava/lang/Object;E:Ljava/lang/Object;F:Ljava/lang/Object;G:Ljava/lang/Object;H:Ljava/lang/Object;I:Ljava/lang/Object;J:Ljava/lang/Object;K:Ljava/lang/Object;L:Ljava/lang/Object;M:Ljava/lang/Object;N:Ljava/lang/Object;O:Ljava/lang/Object;>(TA;TB;TC;TD;TE;TF;TG;TH;TI;TJ;TK;TL;TM;TN;TO;Lshapeless/PolyDefns$Case<Lshapeless/PolyApply;Lshapeless/$colon$colon<TA;Lshapeless/$colon$colon<TB;Lshapeless/$colon$colon<TC;Lshapeless/$colon$colon<TD;Lshapeless/$colon$colon<TE;Lshapeless/$colon$colon<TF;Lshapeless/$colon$colon<TG;Lshapeless/$colon$colon<TH;Lshapeless/$colon$colon<TI;Lshapeless/$colon$colon<TJ;Lshapeless/$colon$colon<TK;Lshapeless/$colon$colon<TL;Lshapeless/$colon$colon<TM;Lshapeless/$colon$colon<TN;Lshapeless/$colon$colon<TO;Lshapeless/HNil;>;>;>;>;>;>;>;>;>;>;>;>;>;>;>;>;)Ljava/lang/Object;
  #231 = Utf8               o
  #232 = Utf8               (Lshapeless/PolyApply;Ljava/lang/Object;Ljava/lang/Object;Ljava/lang/Object;Ljava/lang/Object;Ljava/lang/Object;Ljava/lang/Object;Ljava/lang/Object;Ljava/lang/Object;Ljava/lang/Object;Ljava/lang/Object;Ljava/lang/Object;Ljava/lang/Object;Ljava/lang/Object;Ljava/lang/Object;Ljava/lang/Object;Lshapeless/PolyDefns$Case;)Ljava/lang/Object;
  #233 = NameAndType        #140:#232     // apply$:(Lshapeless/PolyApply;Ljava/lang/Object;Ljava/lang/Object;Ljava/lang/Object;Ljava/lang/Object;Ljava/lang/Object;Ljava/lang/Object;Ljava/lang/Object;Ljava/lang/Object;Ljava/lang/Object;Ljava/lang/Object;Ljava/lang/Object;Ljava/lang/Object;Ljava/lang/Object;Ljava/lang/Object;Ljava/lang/Object;Lshapeless/PolyDefns$Case;)Ljava/lang/Object;
  #234 = InterfaceMethodref #149.#233     // shapeless/PolyApply.apply$:(Lshapeless/PolyApply;Ljava/lang/Object;Ljava/lang/Object;Ljava/lang/Object;Ljava/lang/Object;Ljava/lang/Object;Ljava/lang/Object;Ljava/lang/Object;Ljava/lang/Object;Ljava/lang/Object;Ljava/lang/Object;Ljava/lang/Object;Ljava/lang/Object;Ljava/lang/Object;Ljava/lang/Object;Ljava/lang/Object;Lshapeless/PolyDefns$Case;)Ljava/lang/Object;
  #235 = Utf8               (Ljava/lang/Object;Ljava/lang/Object;Ljava/lang/Object;Ljava/lang/Object;Ljava/lang/Object;Ljava/lang/Object;Ljava/lang/Object;Ljava/lang/Object;Ljava/lang/Object;Ljava/lang/Object;Ljava/lang/Object;Ljava/lang/Object;Ljava/lang/Object;Ljava/lang/Object;Ljava/lang/Object;Ljava/lang/Object;Lshapeless/PolyDefns$Case;)Ljava/lang/Object;
  #236 = Utf8               <A:Ljava/lang/Object;B:Ljava/lang/Object;C:Ljava/lang/Object;D:Ljava/lang/Object;E:Ljava/lang/Object;F:Ljava/lang/Object;G:Ljava/lang/Object;H:Ljava/lang/Object;I:Ljava/lang/Object;J:Ljava/lang/Object;K:Ljava/lang/Object;L:Ljava/lang/Object;M:Ljava/lang/Object;N:Ljava/lang/Object;O:Ljava/lang/Object;P:Ljava/lang/Object;>(TA;TB;TC;TD;TE;TF;TG;TH;TI;TJ;TK;TL;TM;TN;TO;TP;Lshapeless/PolyDefns$Case<Lshapeless/PolyApply;Lshapeless/$colon$colon<TA;Lshapeless/$colon$colon<TB;Lshapeless/$colon$colon<TC;Lshapeless/$colon$colon<TD;Lshapeless/$colon$colon<TE;Lshapeless/$colon$colon<TF;Lshapeless/$colon$colon<TG;Lshapeless/$colon$colon<TH;Lshapeless/$colon$colon<TI;Lshapeless/$colon$colon<TJ;Lshapeless/$colon$colon<TK;Lshapeless/$colon$colon<TL;Lshapeless/$colon$colon<TM;Lshapeless/$colon$colon<TN;Lshapeless/$colon$colon<TO;Lshapeless/$colon$colon<TP;Lshapeless/HNil;>;>;>;>;>;>;>;>;>;>;>;>;>;>;>;>;>;)Ljava/lang/Object;
  #237 = Utf8               p
  #238 = Utf8               (Lshapeless/PolyApply;Ljava/lang/Object;Ljava/lang/Object;Ljava/lang/Object;Ljava/lang/Object;Ljava/lang/Object;Ljava/lang/Object;Ljava/lang/Object;Ljava/lang/Object;Ljava/lang/Object;Ljava/lang/Object;Ljava/lang/Object;Ljava/lang/Object;Ljava/lang/Object;Ljava/lang/Object;Ljava/lang/Object;Ljava/lang/Object;Lshapeless/PolyDefns$Case;)Ljava/lang/Object;
  #239 = NameAndType        #140:#238     // apply$:(Lshapeless/PolyApply;Ljava/lang/Object;Ljava/lang/Object;Ljava/lang/Object;Ljava/lang/Object;Ljava/lang/Object;Ljava/lang/Object;Ljava/lang/Object;Ljava/lang/Object;Ljava/lang/Object;Ljava/lang/Object;Ljava/lang/Object;Ljava/lang/Object;Ljava/lang/Object;Ljava/lang/Object;Ljava/lang/Object;Ljava/lang/Object;Lshapeless/PolyDefns$Case;)Ljava/lang/Object;
  #240 = InterfaceMethodref #149.#239     // shapeless/PolyApply.apply$:(Lshapeless/PolyApply;Ljava/lang/Object;Ljava/lang/Object;Ljava/lang/Object;Ljava/lang/Object;Ljava/lang/Object;Ljava/lang/Object;Ljava/lang/Object;Ljava/lang/Object;Ljava/lang/Object;Ljava/lang/Object;Ljava/lang/Object;Ljava/lang/Object;Ljava/lang/Object;Ljava/lang/Object;Ljava/lang/Object;Ljava/lang/Object;Lshapeless/PolyDefns$Case;)Ljava/lang/Object;
  #241 = Utf8               (Ljava/lang/Object;Ljava/lang/Object;Ljava/lang/Object;Ljava/lang/Object;Ljava/lang/Object;Ljava/lang/Object;Ljava/lang/Object;Ljava/lang/Object;Ljava/lang/Object;Ljava/lang/Object;Ljava/lang/Object;Ljava/lang/Object;Ljava/lang/Object;Ljava/lang/Object;Ljava/lang/Object;Ljava/lang/Object;Ljava/lang/Object;Lshapeless/PolyDefns$Case;)Ljava/lang/Object;
  #242 = Utf8               <A:Ljava/lang/Object;B:Ljava/lang/Object;C:Ljava/lang/Object;D:Ljava/lang/Object;E:Ljava/lang/Object;F:Ljava/lang/Object;G:Ljava/lang/Object;H:Ljava/lang/Object;I:Ljava/lang/Object;J:Ljava/lang/Object;K:Ljava/lang/Object;L:Ljava/lang/Object;M:Ljava/lang/Object;N:Ljava/lang/Object;O:Ljava/lang/Object;P:Ljava/lang/Object;Q:Ljava/lang/Object;>(TA;TB;TC;TD;TE;TF;TG;TH;TI;TJ;TK;TL;TM;TN;TO;TP;TQ;Lshapeless/PolyDefns$Case<Lshapeless/PolyApply;Lshapeless/$colon$colon<TA;Lshapeless/$colon$colon<TB;Lshapeless/$colon$colon<TC;Lshapeless/$colon$colon<TD;Lshapeless/$colon$colon<TE;Lshapeless/$colon$colon<TF;Lshapeless/$colon$colon<TG;Lshapeless/$colon$colon<TH;Lshapeless/$colon$colon<TI;Lshapeless/$colon$colon<TJ;Lshapeless/$colon$colon<TK;Lshapeless/$colon$colon<TL;Lshapeless/$colon$colon<TM;Lshapeless/$colon$colon<TN;Lshapeless/$colon$colon<TO;Lshapeless/$colon$colon<TP;Lshapeless/$colon$colon<TQ;Lshapeless/HNil;>;>;>;>;>;>;>;>;>;>;>;>;>;>;>;>;>;>;)Ljava/lang/Object;
  #243 = Utf8               q
  #244 = Utf8               (Lshapeless/PolyApply;Ljava/lang/Object;Ljava/lang/Object;Ljava/lang/Object;Ljava/lang/Object;Ljava/lang/Object;Ljava/lang/Object;Ljava/lang/Object;Ljava/lang/Object;Ljava/lang/Object;Ljava/lang/Object;Ljava/lang/Object;Ljava/lang/Object;Ljava/lang/Object;Ljava/lang/Object;Ljava/lang/Object;Ljava/lang/Object;Ljava/lang/Object;Lshapeless/PolyDefns$Case;)Ljava/lang/Object;
  #245 = NameAndType        #140:#244     // apply$:(Lshapeless/PolyApply;Ljava/lang/Object;Ljava/lang/Object;Ljava/lang/Object;Ljava/lang/Object;Ljava/lang/Object;Ljava/lang/Object;Ljava/lang/Object;Ljava/lang/Object;Ljava/lang/Object;Ljava/lang/Object;Ljava/lang/Object;Ljava/lang/Object;Ljava/lang/Object;Ljava/lang/Object;Ljava/lang/Object;Ljava/lang/Object;Ljava/lang/Object;Lshapeless/PolyDefns$Case;)Ljava/lang/Object;
  #246 = InterfaceMethodref #149.#245     // shapeless/PolyApply.apply$:(Lshapeless/PolyApply;Ljava/lang/Object;Ljava/lang/Object;Ljava/lang/Object;Ljava/lang/Object;Ljava/lang/Object;Ljava/lang/Object;Ljava/lang/Object;Ljava/lang/Object;Ljava/lang/Object;Ljava/lang/Object;Ljava/lang/Object;Ljava/lang/Object;Ljava/lang/Object;Ljava/lang/Object;Ljava/lang/Object;Ljava/lang/Object;Ljava/lang/Object;Lshapeless/PolyDefns$Case;)Ljava/lang/Object;
  #247 = Utf8               (Ljava/lang/Object;Ljava/lang/Object;Ljava/lang/Object;Ljava/lang/Object;Ljava/lang/Object;Ljava/lang/Object;Ljava/lang/Object;Ljava/lang/Object;Ljava/lang/Object;Ljava/lang/Object;Ljava/lang/Object;Ljava/lang/Object;Ljava/lang/Object;Ljava/lang/Object;Ljava/lang/Object;Ljava/lang/Object;Ljava/lang/Object;Ljava/lang/Object;Lshapeless/PolyDefns$Case;)Ljava/lang/Object;
  #248 = Utf8               <A:Ljava/lang/Object;B:Ljava/lang/Object;C:Ljava/lang/Object;D:Ljava/lang/Object;E:Ljava/lang/Object;F:Ljava/lang/Object;G:Ljava/lang/Object;H:Ljava/lang/Object;I:Ljava/lang/Object;J:Ljava/lang/Object;K:Ljava/lang/Object;L:Ljava/lang/Object;M:Ljava/lang/Object;N:Ljava/lang/Object;O:Ljava/lang/Object;P:Ljava/lang/Object;Q:Ljava/lang/Object;R:Ljava/lang/Object;>(TA;TB;TC;TD;TE;TF;TG;TH;TI;TJ;TK;TL;TM;TN;TO;TP;TQ;TR;Lshapeless/PolyDefns$Case<Lshapeless/PolyApply;Lshapeless/$colon$colon<TA;Lshapeless/$colon$colon<TB;Lshapeless/$colon$colon<TC;Lshapeless/$colon$colon<TD;Lshapeless/$colon$colon<TE;Lshapeless/$colon$colon<TF;Lshapeless/$colon$colon<TG;Lshapeless/$colon$colon<TH;Lshapeless/$colon$colon<TI;Lshapeless/$colon$colon<TJ;Lshapeless/$colon$colon<TK;Lshapeless/$colon$colon<TL;Lshapeless/$colon$colon<TM;Lshapeless/$colon$colon<TN;Lshapeless/$colon$colon<TO;Lshapeless/$colon$colon<TP;Lshapeless/$colon$colon<TQ;Lshapeless/$colon$colon<TR;Lshapeless/HNil;>;>;>;>;>;>;>;>;>;>;>;>;>;>;>;>;>;>;>;)Ljava/lang/Object;
  #249 = Utf8               r
  #250 = Utf8               (Lshapeless/PolyApply;Ljava/lang/Object;Ljava/lang/Object;Ljava/lang/Object;Ljava/lang/Object;Ljava/lang/Object;Ljava/lang/Object;Ljava/lang/Object;Ljava/lang/Object;Ljava/lang/Object;Ljava/lang/Object;Ljava/lang/Object;Ljava/lang/Object;Ljava/lang/Object;Ljava/lang/Object;Ljava/lang/Object;Ljava/lang/Object;Ljava/lang/Object;Ljava/lang/Object;Lshapeless/PolyDefns$Case;)Ljava/lang/Object;
  #251 = NameAndType        #140:#250     // apply$:(Lshapeless/PolyApply;Ljava/lang/Object;Ljava/lang/Object;Ljava/lang/Object;Ljava/lang/Object;Ljava/lang/Object;Ljava/lang/Object;Ljava/lang/Object;Ljava/lang/Object;Ljava/lang/Object;Ljava/lang/Object;Ljava/lang/Object;Ljava/lang/Object;Ljava/lang/Object;Ljava/lang/Object;Ljava/lang/Object;Ljava/lang/Object;Ljava/lang/Object;Ljava/lang/Object;Lshapeless/PolyDefns$Case;)Ljava/lang/Object;
  #252 = InterfaceMethodref #149.#251     // shapeless/PolyApply.apply$:(Lshapeless/PolyApply;Ljava/lang/Object;Ljava/lang/Object;Ljava/lang/Object;Ljava/lang/Object;Ljava/lang/Object;Ljava/lang/Object;Ljava/lang/Object;Ljava/lang/Object;Ljava/lang/Object;Ljava/lang/Object;Ljava/lang/Object;Ljava/lang/Object;Ljava/lang/Object;Ljava/lang/Object;Ljava/lang/Object;Ljava/lang/Object;Ljava/lang/Object;Ljava/lang/Object;Lshapeless/PolyDefns$Case;)Ljava/lang/Object;
  #253 = Utf8               (Ljava/lang/Object;Ljava/lang/Object;Ljava/lang/Object;Ljava/lang/Object;Ljava/lang/Object;Ljava/lang/Object;Ljava/lang/Object;Ljava/lang/Object;Ljava/lang/Object;Ljava/lang/Object;Ljava/lang/Object;Ljava/lang/Object;Ljava/lang/Object;Ljava/lang/Object;Ljava/lang/Object;Ljava/lang/Object;Ljava/lang/Object;Ljava/lang/Object;Ljava/lang/Object;Lshapeless/PolyDefns$Case;)Ljava/lang/Object;
  #254 = Utf8               <A:Ljava/lang/Object;B:Ljava/lang/Object;C:Ljava/lang/Object;D:Ljava/lang/Object;E:Ljava/lang/Object;F:Ljava/lang/Object;G:Ljava/lang/Object;H:Ljava/lang/Object;I:Ljava/lang/Object;J:Ljava/lang/Object;K:Ljava/lang/Object;L:Ljava/lang/Object;M:Ljava/lang/Object;N:Ljava/lang/Object;O:Ljava/lang/Object;P:Ljava/lang/Object;Q:Ljava/lang/Object;R:Ljava/lang/Object;S:Ljava/lang/Object;>(TA;TB;TC;TD;TE;TF;TG;TH;TI;TJ;TK;TL;TM;TN;TO;TP;TQ;TR;TS;Lshapeless/PolyDefns$Case<Lshapeless/PolyApply;Lshapeless/$colon$colon<TA;Lshapeless/$colon$colon<TB;Lshapeless/$colon$colon<TC;Lshapeless/$colon$colon<TD;Lshapeless/$colon$colon<TE;Lshapeless/$colon$colon<TF;Lshapeless/$colon$colon<TG;Lshapeless/$colon$colon<TH;Lshapeless/$colon$colon<TI;Lshapeless/$colon$colon<TJ;Lshapeless/$colon$colon<TK;Lshapeless/$colon$colon<TL;Lshapeless/$colon$colon<TM;Lshapeless/$colon$colon<TN;Lshapeless/$colon$colon<TO;Lshapeless/$colon$colon<TP;Lshapeless/$colon$colon<TQ;Lshapeless/$colon$colon<TR;Lshapeless/$colon$colon<TS;Lshapeless/HNil;>;>;>;>;>;>;>;>;>;>;>;>;>;>;>;>;>;>;>;>;)Ljava/lang/Object;
  #255 = Utf8               s
  #256 = Utf8               (Lshapeless/PolyApply;Ljava/lang/Object;Ljava/lang/Object;Ljava/lang/Object;Ljava/lang/Object;Ljava/lang/Object;Ljava/lang/Object;Ljava/lang/Object;Ljava/lang/Object;Ljava/lang/Object;Ljava/lang/Object;Ljava/lang/Object;Ljava/lang/Object;Ljava/lang/Object;Ljava/lang/Object;Ljava/lang/Object;Ljava/lang/Object;Ljava/lang/Object;Ljava/lang/Object;Ljava/lang/Object;Lshapeless/PolyDefns$Case;)Ljava/lang/Object;
  #257 = NameAndType        #140:#256     // apply$:(Lshapeless/PolyApply;Ljava/lang/Object;Ljava/lang/Object;Ljava/lang/Object;Ljava/lang/Object;Ljava/lang/Object;Ljava/lang/Object;Ljava/lang/Object;Ljava/lang/Object;Ljava/lang/Object;Ljava/lang/Object;Ljava/lang/Object;Ljava/lang/Object;Ljava/lang/Object;Ljava/lang/Object;Ljava/lang/Object;Ljava/lang/Object;Ljava/lang/Object;Ljava/lang/Object;Ljava/lang/Object;Lshapeless/PolyDefns$Case;)Ljava/lang/Object;
  #258 = InterfaceMethodref #149.#257     // shapeless/PolyApply.apply$:(Lshapeless/PolyApply;Ljava/lang/Object;Ljava/lang/Object;Ljava/lang/Object;Ljava/lang/Object;Ljava/lang/Object;Ljava/lang/Object;Ljava/lang/Object;Ljava/lang/Object;Ljava/lang/Object;Ljava/lang/Object;Ljava/lang/Object;Ljava/lang/Object;Ljava/lang/Object;Ljava/lang/Object;Ljava/lang/Object;Ljava/lang/Object;Ljava/lang/Object;Ljava/lang/Object;Ljava/lang/Object;Lshapeless/PolyDefns$Case;)Ljava/lang/Object;
  #259 = Utf8               (Ljava/lang/Object;Ljava/lang/Object;Ljava/lang/Object;Ljava/lang/Object;Ljava/lang/Object;Ljava/lang/Object;Ljava/lang/Object;Ljava/lang/Object;Ljava/lang/Object;Ljava/lang/Object;Ljava/lang/Object;Ljava/lang/Object;Ljava/lang/Object;Ljava/lang/Object;Ljava/lang/Object;Ljava/lang/Object;Ljava/lang/Object;Ljava/lang/Object;Ljava/lang/Object;Ljava/lang/Object;Lshapeless/PolyDefns$Case;)Ljava/lang/Object;
  #260 = Utf8               <A:Ljava/lang/Object;B:Ljava/lang/Object;C:Ljava/lang/Object;D:Ljava/lang/Object;E:Ljava/lang/Object;F:Ljava/lang/Object;G:Ljava/lang/Object;H:Ljava/lang/Object;I:Ljava/lang/Object;J:Ljava/lang/Object;K:Ljava/lang/Object;L:Ljava/lang/Object;M:Ljava/lang/Object;N:Ljava/lang/Object;O:Ljava/lang/Object;P:Ljava/lang/Object;Q:Ljava/lang/Object;R:Ljava/lang/Object;S:Ljava/lang/Object;T:Ljava/lang/Object;>(TA;TB;TC;TD;TE;TF;TG;TH;TI;TJ;TK;TL;TM;TN;TO;TP;TQ;TR;TS;TT;Lshapeless/PolyDefns$Case<Lshapeless/PolyApply;Lshapeless/$colon$colon<TA;Lshapeless/$colon$colon<TB;Lshapeless/$colon$colon<TC;Lshapeless/$colon$colon<TD;Lshapeless/$colon$colon<TE;Lshapeless/$colon$colon<TF;Lshapeless/$colon$colon<TG;Lshapeless/$colon$colon<TH;Lshapeless/$colon$colon<TI;Lshapeless/$colon$colon<TJ;Lshapeless/$colon$colon<TK;Lshapeless/$colon$colon<TL;Lshapeless/$colon$colon<TM;Lshapeless/$colon$colon<TN;Lshapeless/$colon$colon<TO;Lshapeless/$colon$colon<TP;Lshapeless/$colon$colon<TQ;Lshapeless/$colon$colon<TR;Lshapeless/$colon$colon<TS;Lshapeless/$colon$colon<TT;Lshapeless/HNil;>;>;>;>;>;>;>;>;>;>;>;>;>;>;>;>;>;>;>;>;>;)Ljava/lang/Object;
  #261 = Utf8               (Lshapeless/PolyApply;Ljava/lang/Object;Ljava/lang/Object;Ljava/lang/Object;Ljava/lang/Object;Ljava/lang/Object;Ljava/lang/Object;Ljava/lang/Object;Ljava/lang/Object;Ljava/lang/Object;Ljava/lang/Object;Ljava/lang/Object;Ljava/lang/Object;Ljava/lang/Object;Ljava/lang/Object;Ljava/lang/Object;Ljava/lang/Object;Ljava/lang/Object;Ljava/lang/Object;Ljava/lang/Object;Ljava/lang/Object;Lshapeless/PolyDefns$Case;)Ljava/lang/Object;
  #262 = NameAndType        #140:#261     // apply$:(Lshapeless/PolyApply;Ljava/lang/Object;Ljava/lang/Object;Ljava/lang/Object;Ljava/lang/Object;Ljava/lang/Object;Ljava/lang/Object;Ljava/lang/Object;Ljava/lang/Object;Ljava/lang/Object;Ljava/lang/Object;Ljava/lang/Object;Ljava/lang/Object;Ljava/lang/Object;Ljava/lang/Object;Ljava/lang/Object;Ljava/lang/Object;Ljava/lang/Object;Ljava/lang/Object;Ljava/lang/Object;Ljava/lang/Object;Lshapeless/PolyDefns$Case;)Ljava/lang/Object;
  #263 = InterfaceMethodref #149.#262     // shapeless/PolyApply.apply$:(Lshapeless/PolyApply;Ljava/lang/Object;Ljava/lang/Object;Ljava/lang/Object;Ljava/lang/Object;Ljava/lang/Object;Ljava/lang/Object;Ljava/lang/Object;Ljava/lang/Object;Ljava/lang/Object;Ljava/lang/Object;Ljava/lang/Object;Ljava/lang/Object;Ljava/lang/Object;Ljava/lang/Object;Ljava/lang/Object;Ljava/lang/Object;Ljava/lang/Object;Ljava/lang/Object;Ljava/lang/Object;Ljava/lang/Object;Lshapeless/PolyDefns$Case;)Ljava/lang/Object;
  #264 = Utf8               (Ljava/lang/Object;Ljava/lang/Object;Ljava/lang/Object;Ljava/lang/Object;Ljava/lang/Object;Ljava/lang/Object;Ljava/lang/Object;Ljava/lang/Object;Ljava/lang/Object;Ljava/lang/Object;Ljava/lang/Object;Ljava/lang/Object;Ljava/lang/Object;Ljava/lang/Object;Ljava/lang/Object;Ljava/lang/Object;Ljava/lang/Object;Ljava/lang/Object;Ljava/lang/Object;Ljava/lang/Object;Ljava/lang/Object;Lshapeless/PolyDefns$Case;)Ljava/lang/Object;
  #265 = Utf8               <A:Ljava/lang/Object;B:Ljava/lang/Object;C:Ljava/lang/Object;D:Ljava/lang/Object;E:Ljava/lang/Object;F:Ljava/lang/Object;G:Ljava/lang/Object;H:Ljava/lang/Object;I:Ljava/lang/Object;J:Ljava/lang/Object;K:Ljava/lang/Object;L:Ljava/lang/Object;M:Ljava/lang/Object;N:Ljava/lang/Object;O:Ljava/lang/Object;P:Ljava/lang/Object;Q:Ljava/lang/Object;R:Ljava/lang/Object;S:Ljava/lang/Object;T:Ljava/lang/Object;U:Ljava/lang/Object;>(TA;TB;TC;TD;TE;TF;TG;TH;TI;TJ;TK;TL;TM;TN;TO;TP;TQ;TR;TS;TT;TU;Lshapeless/PolyDefns$Case<Lshapeless/PolyApply;Lshapeless/$colon$colon<TA;Lshapeless/$colon$colon<TB;Lshapeless/$colon$colon<TC;Lshapeless/$colon$colon<TD;Lshapeless/$colon$colon<TE;Lshapeless/$colon$colon<TF;Lshapeless/$colon$colon<TG;Lshapeless/$colon$colon<TH;Lshapeless/$colon$colon<TI;Lshapeless/$colon$colon<TJ;Lshapeless/$colon$colon<TK;Lshapeless/$colon$colon<TL;Lshapeless/$colon$colon<TM;Lshapeless/$colon$colon<TN;Lshapeless/$colon$colon<TO;Lshapeless/$colon$colon<TP;Lshapeless/$colon$colon<TQ;Lshapeless/$colon$colon<TR;Lshapeless/$colon$colon<TS;Lshapeless/$colon$colon<TT;Lshapeless/$colon$colon<TU;Lshapeless/HNil;>;>;>;>;>;>;>;>;>;>;>;>;>;>;>;>;>;>;>;>;>;>;)Ljava/lang/Object;
  #266 = Utf8               u
  #267 = Utf8               (Lshapeless/PolyApply;Ljava/lang/Object;Ljava/lang/Object;Ljava/lang/Object;Ljava/lang/Object;Ljava/lang/Object;Ljava/lang/Object;Ljava/lang/Object;Ljava/lang/Object;Ljava/lang/Object;Ljava/lang/Object;Ljava/lang/Object;Ljava/lang/Object;Ljava/lang/Object;Ljava/lang/Object;Ljava/lang/Object;Ljava/lang/Object;Ljava/lang/Object;Ljava/lang/Object;Ljava/lang/Object;Ljava/lang/Object;Ljava/lang/Object;Lshapeless/PolyDefns$Case;)Ljava/lang/Object;
  #268 = NameAndType        #140:#267     // apply$:(Lshapeless/PolyApply;Ljava/lang/Object;Ljava/lang/Object;Ljava/lang/Object;Ljava/lang/Object;Ljava/lang/Object;Ljava/lang/Object;Ljava/lang/Object;Ljava/lang/Object;Ljava/lang/Object;Ljava/lang/Object;Ljava/lang/Object;Ljava/lang/Object;Ljava/lang/Object;Ljava/lang/Object;Ljava/lang/Object;Ljava/lang/Object;Ljava/lang/Object;Ljava/lang/Object;Ljava/lang/Object;Ljava/lang/Object;Ljava/lang/Object;Lshapeless/PolyDefns$Case;)Ljava/lang/Object;
  #269 = InterfaceMethodref #149.#268     // shapeless/PolyApply.apply$:(Lshapeless/PolyApply;Ljava/lang/Object;Ljava/lang/Object;Ljava/lang/Object;Ljava/lang/Object;Ljava/lang/Object;Ljava/lang/Object;Ljava/lang/Object;Ljava/lang/Object;Ljava/lang/Object;Ljava/lang/Object;Ljava/lang/Object;Ljava/lang/Object;Ljava/lang/Object;Ljava/lang/Object;Ljava/lang/Object;Ljava/lang/Object;Ljava/lang/Object;Ljava/lang/Object;Ljava/lang/Object;Ljava/lang/Object;Ljava/lang/Object;Lshapeless/PolyDefns$Case;)Ljava/lang/Object;
  #270 = Utf8               (Ljava/lang/Object;Ljava/lang/Object;Ljava/lang/Object;Ljava/lang/Object;Ljava/lang/Object;Ljava/lang/Object;Ljava/lang/Object;Ljava/lang/Object;Ljava/lang/Object;Ljava/lang/Object;Ljava/lang/Object;Ljava/lang/Object;Ljava/lang/Object;Ljava/lang/Object;Ljava/lang/Object;Ljava/lang/Object;Ljava/lang/Object;Ljava/lang/Object;Ljava/lang/Object;Ljava/lang/Object;Ljava/lang/Object;Ljava/lang/Object;Lshapeless/PolyDefns$Case;)Ljava/lang/Object;
  #271 = Utf8               <A:Ljava/lang/Object;B:Ljava/lang/Object;C:Ljava/lang/Object;D:Ljava/lang/Object;E:Ljava/lang/Object;F:Ljava/lang/Object;G:Ljava/lang/Object;H:Ljava/lang/Object;I:Ljava/lang/Object;J:Ljava/lang/Object;K:Ljava/lang/Object;L:Ljava/lang/Object;M:Ljava/lang/Object;N:Ljava/lang/Object;O:Ljava/lang/Object;P:Ljava/lang/Object;Q:Ljava/lang/Object;R:Ljava/lang/Object;S:Ljava/lang/Object;T:Ljava/lang/Object;U:Ljava/lang/Object;V:Ljava/lang/Object;>(TA;TB;TC;TD;TE;TF;TG;TH;TI;TJ;TK;TL;TM;TN;TO;TP;TQ;TR;TS;TT;TU;TV;Lshapeless/PolyDefns$Case<Lshapeless/PolyApply;Lshapeless/$colon$colon<TA;Lshapeless/$colon$colon<TB;Lshapeless/$colon$colon<TC;Lshapeless/$colon$colon<TD;Lshapeless/$colon$colon<TE;Lshapeless/$colon$colon<TF;Lshapeless/$colon$colon<TG;Lshapeless/$colon$colon<TH;Lshapeless/$colon$colon<TI;Lshapeless/$colon$colon<TJ;Lshapeless/$colon$colon<TK;Lshapeless/$colon$colon<TL;Lshapeless/$colon$colon<TM;Lshapeless/$colon$colon<TN;Lshapeless/$colon$colon<TO;Lshapeless/$colon$colon<TP;Lshapeless/$colon$colon<TQ;Lshapeless/$colon$colon<TR;Lshapeless/$colon$colon<TS;Lshapeless/$colon$colon<TT;Lshapeless/$colon$colon<TU;Lshapeless/$colon$colon<TV;Lshapeless/HNil;>;>;>;>;>;>;>;>;>;>;>;>;>;>;>;>;>;>;>;>;>;>;>;)Ljava/lang/Object;
  #272 = Utf8               v
  #273 = Utf8               (Lshapeless/PolyApply;Ljava/lang/Object;Ljava/lang/Object;Ljava/lang/Object;Ljava/lang/Object;Ljava/lang/Object;Ljava/lang/Object;Ljava/lang/Object;Ljava/lang/Object;Ljava/lang/Object;Ljava/lang/Object;Ljava/lang/Object;Ljava/lang/Object;Ljava/lang/Object;Ljava/lang/Object;Ljava/lang/Object;Ljava/lang/Object;Ljava/lang/Object;Ljava/lang/Object;Ljava/lang/Object;Ljava/lang/Object;Ljava/lang/Object;Ljava/lang/Object;Lshapeless/PolyDefns$Case;)Ljava/lang/Object;
  #274 = NameAndType        #140:#273     // apply$:(Lshapeless/PolyApply;Ljava/lang/Object;Ljava/lang/Object;Ljava/lang/Object;Ljava/lang/Object;Ljava/lang/Object;Ljava/lang/Object;Ljava/lang/Object;Ljava/lang/Object;Ljava/lang/Object;Ljava/lang/Object;Ljava/lang/Object;Ljava/lang/Object;Ljava/lang/Object;Ljava/lang/Object;Ljava/lang/Object;Ljava/lang/Object;Ljava/lang/Object;Ljava/lang/Object;Ljava/lang/Object;Ljava/lang/Object;Ljava/lang/Object;Ljava/lang/Object;Lshapeless/PolyDefns$Case;)Ljava/lang/Object;
  #275 = InterfaceMethodref #149.#274     // shapeless/PolyApply.apply$:(Lshapeless/PolyApply;Ljava/lang/Object;Ljava/lang/Object;Ljava/lang/Object;Ljava/lang/Object;Ljava/lang/Object;Ljava/lang/Object;Ljava/lang/Object;Ljava/lang/Object;Ljava/lang/Object;Ljava/lang/Object;Ljava/lang/Object;Ljava/lang/Object;Ljava/lang/Object;Ljava/lang/Object;Ljava/lang/Object;Ljava/lang/Object;Ljava/lang/Object;Ljava/lang/Object;Ljava/lang/Object;Ljava/lang/Object;Ljava/lang/Object;Ljava/lang/Object;Lshapeless/PolyDefns$Case;)Ljava/lang/Object;
  #276 = Utf8               ()Lshapeless/Poly1$Case$;
  #277 = NameAndType        #55:#56       // Case$module:Lshapeless/Poly1$Case$;
  #278 = Fieldref           #2.#277       // shapeless/HMap.Case$module:Lshapeless/Poly1$Case$;
  #279 = Utf8               Case$lzycompute$1
  #280 = Utf8               ()V
  #281 = NameAndType        #279:#280     // Case$lzycompute$1:()V
  #282 = Methodref          #2.#281       // shapeless/HMap.Case$lzycompute$1:()V
  #283 = Utf8               ProductCase
  #284 = Utf8               ()Lshapeless/Poly$ProductCase$;
  #285 = NameAndType        #57:#58       // ProductCase$module:Lshapeless/Poly$ProductCase$;
  #286 = Fieldref           #2.#285       // shapeless/HMap.ProductCase$module:Lshapeless/Poly$ProductCase$;
  #287 = Utf8               ProductCase$lzycompute$1
  #288 = NameAndType        #287:#280     // ProductCase$lzycompute$1:()V
  #289 = Methodref          #2.#288       // shapeless/HMap.ProductCase$lzycompute$1:()V
  #290 = Utf8               ()Lshapeless/Poly$CaseBuilder$;
  #291 = NameAndType        #59:#60       // CaseBuilder$module:Lshapeless/Poly$CaseBuilder$;
  #292 = Fieldref           #2.#291       // shapeless/HMap.CaseBuilder$module:Lshapeless/Poly$CaseBuilder$;
  #293 = Utf8               CaseBuilder$lzycompute$1
  #294 = NameAndType        #293:#280     // CaseBuilder$lzycompute$1:()V
  #295 = Methodref          #2.#294       // shapeless/HMap.CaseBuilder$lzycompute$1:()V
  #296 = Utf8               get
  #297 = Utf8               (Ljava/lang/Object;Ljava/lang/Object;)Lscala/Option;
  #298 = Utf8               <K:Ljava/lang/Object;V:Ljava/lang/Object;>(TK;TR;)Lscala/Option<TV;>;
  #299 = Utf8               ev
  #300 = NameAndType        #52:#53       // underlying:Lscala/collection/immutable/Map;
  #301 = Fieldref           #2.#300       // shapeless/HMap.underlying:Lscala/collection/immutable/Map;
  #302 = Utf8               scala/collection/immutable/Map
  #303 = Class              #302          // scala/collection/immutable/Map
  #304 = Utf8               (Ljava/lang/Object;)Lscala/Option;
  #305 = NameAndType        #296:#304     // get:(Ljava/lang/Object;)Lscala/Option;
  #306 = InterfaceMethodref #303.#305     // scala/collection/immutable/Map.get:(Ljava/lang/Object;)Lscala/Option;
  #307 = Utf8               $plus
  #308 = Utf8               (Lscala/Tuple2;Ljava/lang/Object;)Lshapeless/HMap;
  #309 = Utf8               <K:Ljava/lang/Object;V:Ljava/lang/Object;>(Lscala/Tuple2<TK;TV;>;TR;)Lshapeless/HMap<TR;>;
  #310 = Utf8               kv
  #311 = Utf8               (Lscala/Tuple2;)Lscala/collection/immutable/MapOps;
  #312 = NameAndType        #307:#311     // $plus:(Lscala/Tuple2;)Lscala/collection/immutable/MapOps;
  #313 = InterfaceMethodref #303.#312     // scala/collection/immutable/Map.$plus:(Lscala/Tuple2;)Lscala/collection/immutable/MapOps;
  #314 = Utf8               <init>
  #315 = Utf8               (Lscala/collection/immutable/Map;)V
  #316 = NameAndType        #314:#315     // "<init>":(Lscala/collection/immutable/Map;)V
  #317 = Methodref          #2.#316       // shapeless/HMap."<init>":(Lscala/collection/immutable/Map;)V
  #318 = Utf8               Lscala/Tuple2;
  #319 = Utf8               $minus
  #320 = Utf8               (Ljava/lang/Object;)Lshapeless/HMap;
  #321 = Utf8               <K:Ljava/lang/Object;>(TK;)Lshapeless/HMap<TR;>;
  #322 = Utf8               (Ljava/lang/Object;)Lscala/collection/immutable/MapOps;
  #323 = NameAndType        #319:#322     // $minus:(Ljava/lang/Object;)Lscala/collection/immutable/MapOps;
  #324 = InterfaceMethodref #303.#323     // scala/collection/immutable/Map.$minus:(Ljava/lang/Object;)Lscala/collection/immutable/MapOps;
  #325 = Utf8               caseRel
  #326 = Utf8               (Ljava/lang/Object;)Lshapeless/PolyDefns$Case;
  #327 = Utf8               <K:Ljava/lang/Object;V:Ljava/lang/Object;>(TR;)Lshapeless/PolyDefns$Case<Lshapeless/HMap<TR;>;Lshapeless/$colon$colon<TK;Lshapeless/HNil;>;>;
  #328 = Utf8               shapeless/package$
  #329 = Class              #328          // shapeless/package$
  #330 = Utf8               Lshapeless/package$;
  #331 = NameAndType        #66:#330      // MODULE$:Lshapeless/package$;
  #332 = Fieldref           #329.#331     // shapeless/package$.MODULE$:Lshapeless/package$;
  #333 = Utf8               poly
  #334 = Utf8               ()Lshapeless/PolyDefns$;
  #335 = NameAndType        #333:#334     // poly:()Lshapeless/PolyDefns$;
  #336 = Methodref          #329.#335     // shapeless/package$.poly:()Lshapeless/PolyDefns$;
  #337 = Utf8               shapeless/PolyDefns$
  #338 = Class              #337          // shapeless/PolyDefns$
  #339 = Utf8               Case1
  #340 = Utf8               ()Lshapeless/Cases$Case1$;
  #341 = NameAndType        #339:#340     // Case1:()Lshapeless/Cases$Case1$;
  #342 = Methodref          #338.#341     // shapeless/PolyDefns$.Case1:()Lshapeless/Cases$Case1$;
  #343 = Utf8               (Ljava/lang/Object;)Ljava/lang/Object;
  #344 = MethodType         #343          //  (Ljava/lang/Object;)Ljava/lang/Object;
  #345 = Utf8               $anonfun$caseRel$1
  #346 = Utf8               (Lshapeless/HMap;Ljava/lang/Object;Ljava/lang/Object;)Ljava/lang/Object;
  #347 = NameAndType        #345:#346     // $anonfun$caseRel$1:(Lshapeless/HMap;Ljava/lang/Object;Ljava/lang/Object;)Ljava/lang/Object;
  #348 = Methodref          #2.#347       // shapeless/HMap.$anonfun$caseRel$1:(Lshapeless/HMap;Ljava/lang/Object;Ljava/lang/Object;)Ljava/lang/Object;
  #349 = MethodHandle       6:#348        // REF_invokeStatic shapeless/HMap.$anonfun$caseRel$1:(Lshapeless/HMap;Ljava/lang/Object;Ljava/lang/Object;)Ljava/lang/Object;
  #350 = Integer            1
  #351 = Utf8               java/lang/invoke/LambdaMetafactory
  #352 = Class              #351          // java/lang/invoke/LambdaMetafactory
  #353 = Utf8               altMetafactory
  #354 = Utf8               (Ljava/lang/invoke/MethodHandles$Lookup;Ljava/lang/String;Ljava/lang/invoke/MethodType;[Ljava/lang/Object;)Ljava/lang/invoke/CallSite;
  #355 = NameAndType        #353:#354     // altMetafactory:(Ljava/lang/invoke/MethodHandles$Lookup;Ljava/lang/String;Ljava/lang/invoke/MethodType;[Ljava/lang/Object;)Ljava/lang/invoke/CallSite;
  #356 = Methodref          #352.#355     // java/lang/invoke/LambdaMetafactory.altMetafactory:(Ljava/lang/invoke/MethodHandles$Lookup;Ljava/lang/String;Ljava/lang/invoke/MethodType;[Ljava/lang/Object;)Ljava/lang/invoke/CallSite;
  #357 = MethodHandle       6:#356        // REF_invokeStatic java/lang/invoke/LambdaMetafactory.altMetafactory:(Ljava/lang/invoke/MethodHandles$Lookup;Ljava/lang/String;Ljava/lang/invoke/MethodType;[Ljava/lang/Object;)Ljava/lang/invoke/CallSite;
  #358 = Utf8               (Lshapeless/HMap;Ljava/lang/Object;)Lscala/Function1;
  #359 = NameAndType        #137:#358     // apply:(Lshapeless/HMap;Ljava/lang/Object;)Lscala/Function1;
  #360 = InvokeDynamic      #0:#359       // #0:apply:(Lshapeless/HMap;Ljava/lang/Object;)Lscala/Function1;
  #361 = Utf8               (Lscala/Function1;)Lshapeless/PolyDefns$Case;
  #362 = NameAndType        #137:#361     // apply:(Lscala/Function1;)Lshapeless/PolyDefns$Case;
  #363 = Methodref          #18.#362      // shapeless/Cases$Case1$.apply:(Lscala/Function1;)Lshapeless/PolyDefns$Case;
  #364 = Utf8               (Lshapeless/Poly1;)V
  #365 = NameAndType        #314:#364     // "<init>":(Lshapeless/Poly1;)V
  #366 = Methodref          #34.#365      // shapeless/Poly1$Case$."<init>":(Lshapeless/Poly1;)V
  #367 = Utf8               java/lang/Throwable
  #368 = Class              #367          // java/lang/Throwable
  #369 = Utf8               (Lshapeless/Poly;)V
  #370 = NameAndType        #314:#369     // "<init>":(Lshapeless/Poly;)V
  #371 = Methodref          #31.#370      // shapeless/Poly$ProductCase$."<init>":(Lshapeless/Poly;)V
  #372 = Methodref          #28.#370      // shapeless/Poly$CaseBuilder$."<init>":(Lshapeless/Poly;)V
  #373 = Utf8               $this
  #374 = Utf8               ev$1
  #375 = Utf8               x$1
  #376 = NameAndType        #296:#297     // get:(Ljava/lang/Object;Ljava/lang/Object;)Lscala/Option;
  #377 = Methodref          #2.#376       // shapeless/HMap.get:(Ljava/lang/Object;Ljava/lang/Object;)Lscala/Option;
  #378 = Utf8               scala/Option
  #379 = Class              #378          // scala/Option
  #380 = Utf8               ()Ljava/lang/Object;
  #381 = NameAndType        #296:#380     // get:()Ljava/lang/Object;
  #382 = Methodref          #379.#381     // scala/Option.get:()Ljava/lang/Object;
  #383 = Utf8               (Lscala/collection/immutable/Map<Ljava/lang/Object;Ljava/lang/Object;>;)V
  #384 = NameAndType        #314:#280     // "<init>":()V
  #385 = Methodref          #5.#384       // java/lang/Object."<init>":()V
  #386 = Utf8               $init$
  #387 = Utf8               (Lshapeless/PolyApply;)V
  #388 = NameAndType        #386:#387     // $init$:(Lshapeless/PolyApply;)V
  #389 = InterfaceMethodref #149.#388     // shapeless/PolyApply.$init$:(Lshapeless/PolyApply;)V
  #390 = NameAndType        #386:#369     // $init$:(Lshapeless/Poly;)V
  #391 = InterfaceMethodref #25.#390      // shapeless/Poly.$init$:(Lshapeless/Poly;)V
  #392 = NameAndType        #386:#364     // $init$:(Lshapeless/Poly1;)V
  #393 = InterfaceMethodref #7.#392       // shapeless/Poly1.$init$:(Lshapeless/Poly1;)V
  #394 = Utf8               $deserializeLambda$
  #395 = Utf8               (Ljava/lang/invoke/SerializedLambda;)Ljava/lang/Object;
  #396 = Utf8               scala/runtime/LambdaDeserialize
  #397 = Class              #396          // scala/runtime/LambdaDeserialize
  #398 = Utf8               bootstrap
  #399 = Utf8               (Ljava/lang/invoke/MethodHandles$Lookup;Ljava/lang/String;Ljava/lang/invoke/MethodType;[Ljava/lang/invoke/MethodHandle;)Ljava/lang/invoke/CallSite;
  #400 = NameAndType        #398:#399     // bootstrap:(Ljava/lang/invoke/MethodHandles$Lookup;Ljava/lang/String;Ljava/lang/invoke/MethodType;[Ljava/lang/invoke/MethodHandle;)Ljava/lang/invoke/CallSite;
  #401 = Methodref          #397.#400     // scala/runtime/LambdaDeserialize.bootstrap:(Ljava/lang/invoke/MethodHandles$Lookup;Ljava/lang/String;Ljava/lang/invoke/MethodType;[Ljava/lang/invoke/MethodHandle;)Ljava/lang/invoke/CallSite;
  #402 = MethodHandle       6:#401        // REF_invokeStatic scala/runtime/LambdaDeserialize.bootstrap:(Ljava/lang/invoke/MethodHandles$Lookup;Ljava/lang/String;Ljava/lang/invoke/MethodType;[Ljava/lang/invoke/MethodHandle;)Ljava/lang/invoke/CallSite;
  #403 = Utf8               lambdaDeserialize
  #404 = NameAndType        #403:#395     // lambdaDeserialize:(Ljava/lang/invoke/SerializedLambda;)Ljava/lang/Object;
  #405 = InvokeDynamic      #1:#404       // #1:lambdaDeserialize:(Ljava/lang/invoke/SerializedLambda;)Ljava/lang/Object;
  #406 = Utf8               Signature
  #407 = Utf8               Code
  #408 = Utf8               MethodParameters
  #409 = Utf8               LineNumberTable
  #410 = Utf8               LocalVariableTable
  #411 = Utf8               StackMapTable
  #412 = Utf8               InnerClasses
  #413 = Utf8               SourceFile
  #414 = Utf8               RuntimeVisibleAnnotations
  #415 = Utf8               BootstrapMethods
  #416 = Utf8               ScalaInlineInfo
  #417 = Utf8               ScalaSig
{
  private final scala.collection.immutable.Map<java.lang.Object, java.lang.Object> underlying;
    descriptor: Lscala/collection/immutable/Map;
    flags: (0x0012) ACC_PRIVATE, ACC_FINAL
    Signature: #54                          // Lscala/collection/immutable/Map<Ljava/lang/Object;Ljava/lang/Object;>;

  private volatile shapeless.Poly1$Case$ Case$module;
    descriptor: Lshapeless/Poly1$Case$;
    flags: (0x0042) ACC_PRIVATE, ACC_VOLATILE

  private volatile shapeless.Poly$ProductCase$ ProductCase$module;
    descriptor: Lshapeless/Poly$ProductCase$;
    flags: (0x0042) ACC_PRIVATE, ACC_VOLATILE

  private volatile shapeless.Poly$CaseBuilder$ CaseBuilder$module;
    descriptor: Lshapeless/Poly$CaseBuilder$;
    flags: (0x0042) ACC_PRIVATE, ACC_VOLATILE

  public static <R extends java.lang.Object> scala.collection.immutable.Map<java.lang.Object, java.lang.Object> $lessinit$greater$default$1();
    descriptor: ()Lscala/collection/immutable/Map;
    flags: (0x0009) ACC_PUBLIC, ACC_STATIC
    Code:
      stack=1, locals=0, args_size=0
         0: getstatic     #69                 // Field shapeless/HMap$.MODULE$:Lshapeless/HMap$;
         3: invokevirtual #71                 // Method shapeless/HMap$.$lessinit$greater$default$1:()Lscala/collection/immutable/Map;
         6: areturn
    Signature: #63                          // <R:Ljava/lang/Object;>()Lscala/collection/immutable/Map<Ljava/lang/Object;Ljava/lang/Object;>;

  public static <R extends java.lang.Object> shapeless.HMap<R> empty(scala.collection.immutable.Map<java.lang.Object, java.lang.Object>);
    descriptor: (Lscala/collection/immutable/Map;)Lshapeless/HMap;
    flags: (0x0009) ACC_PUBLIC, ACC_STATIC
    Code:
      stack=2, locals=1, args_size=1
         0: getstatic     #69                 // Field shapeless/HMap$.MODULE$:Lshapeless/HMap$;
         3: aload_0
         4: invokevirtual #76                 // Method shapeless/HMap$.empty:(Lscala/collection/immutable/Map;)Lshapeless/HMap;
         7: areturn
    Signature: #74                          // <R:Ljava/lang/Object;>(Lscala/collection/immutable/Map<Ljava/lang/Object;Ljava/lang/Object;>;)Lshapeless/HMap<TR;>;
    MethodParameters:
      Name                           Flags
      underlying                     final

  public static <R extends java.lang.Object> shapeless.HMap<R> empty();
    descriptor: ()Lshapeless/HMap;
    flags: (0x0009) ACC_PUBLIC, ACC_STATIC
    Code:
      stack=1, locals=0, args_size=0
         0: getstatic     #69                 // Field shapeless/HMap$.MODULE$:Lshapeless/HMap$;
         3: invokevirtual #80                 // Method shapeless/HMap$.empty:()Lshapeless/HMap;
         6: areturn
    Signature: #78                          // <R:Ljava/lang/Object;>()Lshapeless/HMap<TR;>;

  public <A extends java.lang.Object> shapeless.Poly1$CaseBuilder<A> at();
    descriptor: ()Lshapeless/Poly1$CaseBuilder;
    flags: (0x0001) ACC_PUBLIC
    Code:
      stack=1, locals=1, args_size=1
         0: aload_0
         1: invokestatic  #87                 // InterfaceMethod shapeless/Poly1.at$:(Lshapeless/Poly1;)Lshapeless/Poly1$CaseBuilder;
         4: areturn
      LineNumberTable:
        line 28: 0
      LocalVariableTable:
        Start  Length  Slot  Name   Signature
            0       5     0  this   Lshapeless/HMap;
    Signature: #83                          // <A:Ljava/lang/Object;>()Lshapeless/Poly1$CaseBuilder<TA;>;

  public shapeless.PolyDefns$Compose<shapeless.Poly, shapeless.Poly> compose(shapeless.Poly);
    descriptor: (Lshapeless/Poly;)Lshapeless/PolyDefns$Compose;
    flags: (0x0001) ACC_PUBLIC
    Code:
      stack=2, locals=2, args_size=2
         0: aload_0
         1: aload_1
         2: invokestatic  #97                 // InterfaceMethod shapeless/Poly.compose$:(Lshapeless/Poly;Lshapeless/Poly;)Lshapeless/PolyDefns$Compose;
         5: areturn
      LineNumberTable:
        line 28: 0
      LocalVariableTable:
        Start  Length  Slot  Name   Signature
            0       6     0  this   Lshapeless/HMap;
            0       6     1     f   Lshapeless/Poly;
    Signature: #92                          // (Lshapeless/Poly;)Lshapeless/PolyDefns$Compose<Lshapeless/Poly;Lshapeless/Poly;>;
    MethodParameters:
      Name                           Flags
      f                              final

  public shapeless.PolyDefns$Compose<shapeless.Poly, shapeless.Poly> andThen(shapeless.Poly);
    descriptor: (Lshapeless/Poly;)Lshapeless/PolyDefns$Compose;
    flags: (0x0001) ACC_PUBLIC
    Code:
      stack=2, locals=2, args_size=2
         0: aload_0
         1: aload_1
         2: invokestatic  #102                // InterfaceMethod shapeless/Poly.andThen$:(Lshapeless/Poly;Lshapeless/Poly;)Lshapeless/PolyDefns$Compose;
         5: areturn
      LineNumberTable:
        line 28: 0
      LocalVariableTable:
        Start  Length  Slot  Name   Signature
            0       6     0  this   Lshapeless/HMap;
            0       6     1     f   Lshapeless/Poly;
    Signature: #92                          // (Lshapeless/Poly;)Lshapeless/PolyDefns$Compose<Lshapeless/Poly;Lshapeless/Poly;>;
    MethodParameters:
      Name                           Flags
      f                              final

  public <N extends shapeless.Nat> shapeless.PolyDefns$RotateLeft<shapeless.Poly, N> rotateLeft();
    descriptor: ()Lshapeless/PolyDefns$RotateLeft;
    flags: (0x0001) ACC_PUBLIC
    Code:
      stack=1, locals=1, args_size=1
         0: aload_0
         1: invokestatic  #109                // InterfaceMethod shapeless/Poly.rotateLeft$:(Lshapeless/Poly;)Lshapeless/PolyDefns$RotateLeft;
         4: areturn
      LineNumberTable:
        line 28: 0
      LocalVariableTable:
        Start  Length  Slot  Name   Signature
            0       5     0  this   Lshapeless/HMap;
    Signature: #105                         // <N::Lshapeless/Nat;>()Lshapeless/PolyDefns$RotateLeft<Lshapeless/Poly;TN;>;

  public <N extends shapeless.Nat> shapeless.PolyDefns$RotateRight<shapeless.Poly, N> rotateRight();
    descriptor: ()Lshapeless/PolyDefns$RotateRight;
    flags: (0x0001) ACC_PUBLIC
    Code:
      stack=1, locals=1, args_size=1
         0: aload_0
         1: invokestatic  #116                // InterfaceMethod shapeless/Poly.rotateRight$:(Lshapeless/Poly;)Lshapeless/PolyDefns$RotateRight;
         4: areturn
      LineNumberTable:
        line 28: 0
      LocalVariableTable:
        Start  Length  Slot  Name   Signature
            0       5     0  this   Lshapeless/HMap;
    Signature: #112                         // <N::Lshapeless/Nat;>()Lshapeless/PolyDefns$RotateRight<Lshapeless/Poly;TN;>;

  public <T extends java.lang.Object, L extends shapeless.HList, R extends java.lang.Object> shapeless.PolyDefns$Case<shapeless.Poly, L> use(T, shapeless.Poly$CaseBuilder<T, L, R>);
    descriptor: (Ljava/lang/Object;Lshapeless/Poly$CaseBuilder;)Lshapeless/PolyDefns$Case;
    flags: (0x0001) ACC_PUBLIC
    Code:
      stack=3, locals=3, args_size=3
         0: aload_0
         1: aload_1
         2: aload_2
         3: invokestatic  #125                // InterfaceMethod shapeless/Poly.use$:(Lshapeless/Poly;Ljava/lang/Object;Lshapeless/Poly$CaseBuilder;)Lshapeless/PolyDefns$Case;
         6: areturn
      LineNumberTable:
        line 28: 0
      LocalVariableTable:
        Start  Length  Slot  Name   Signature
            0       7     0  this   Lshapeless/HMap;
            0       7     1     t   Ljava/lang/Object;
            0       7     2    cb   Lshapeless/Poly$CaseBuilder;
    Signature: #119                         // <T:Ljava/lang/Object;L::Lshapeless/HList;R:Ljava/lang/Object;>(TT;Lshapeless/Poly$CaseBuilder<TT;TL;TR;>;)Lshapeless/PolyDefns$Case<Lshapeless/Poly;TL;>;
    MethodParameters:
      Name                           Flags
      t                              final
      cb                             final

  public <L extends shapeless.HList> shapeless.PolyDefns$Case<shapeless.Poly, L> caseAt(shapeless.PolyDefns$Case<shapeless.Poly, L>);
    descriptor: (Lshapeless/PolyDefns$Case;)Lshapeless/PolyDefns$Case;
    flags: (0x0001) ACC_PUBLIC
    Code:
      stack=2, locals=2, args_size=2
         0: aload_0
         1: aload_1
         2: invokestatic  #135                // InterfaceMethod shapeless/Poly.caseAt$:(Lshapeless/Poly;Lshapeless/PolyDefns$Case;)Lshapeless/PolyDefns$Case;
         5: areturn
      LineNumberTable:
        line 28: 0
      LocalVariableTable:
        Start  Length  Slot  Name   Signature
            0       6     0  this   Lshapeless/HMap;
            0       6     1     c   Lshapeless/PolyDefns$Case;
    Signature: #130                         // <L::Lshapeless/HList;>(Lshapeless/PolyDefns$Case<Lshapeless/Poly;TL;>;)Lshapeless/PolyDefns$Case<Lshapeless/Poly;TL;>;
    MethodParameters:
      Name                           Flags
      c                              final

  public <R extends java.lang.Object> R apply(shapeless.PolyDefns$Case<shapeless.Poly, shapeless.HNil>);
    descriptor: (Lshapeless/PolyDefns$Case;)Ljava/lang/Object;
    flags: (0x0001) ACC_PUBLIC
    Code:
      stack=2, locals=2, args_size=2
         0: aload_0
         1: aload_1
         2: invokestatic  #143                // InterfaceMethod shapeless/Poly.apply$:(Lshapeless/Poly;Lshapeless/PolyDefns$Case;)Ljava/lang/Object;
         5: areturn
      LineNumberTable:
        line 28: 0
      LocalVariableTable:
        Start  Length  Slot  Name   Signature
            0       6     0  this   Lshapeless/HMap;
            0       6     1     c   Lshapeless/PolyDefns$Case;
    Signature: #139                         // <R:Ljava/lang/Object;>(Lshapeless/PolyDefns$Case<Lshapeless/Poly;Lshapeless/HNil;>;)TR;
    MethodParameters:
      Name                           Flags
      c                              final

  public <A extends java.lang.Object> java.lang.Object apply(A, shapeless.PolyDefns$Case<shapeless.PolyApply, shapeless.$colon$colon<A, shapeless.HNil>>);
    descriptor: (Ljava/lang/Object;Lshapeless/PolyDefns$Case;)Ljava/lang/Object;
    flags: (0x0001) ACC_PUBLIC
    Code:
      stack=3, locals=3, args_size=3
         0: aload_0
         1: aload_1
         2: aload_2
         3: invokestatic  #152                // InterfaceMethod shapeless/PolyApply.apply$:(Lshapeless/PolyApply;Ljava/lang/Object;Lshapeless/PolyDefns$Case;)Ljava/lang/Object;
         6: areturn
      LineNumberTable:
        line 28: 0
      LocalVariableTable:
        Start  Length  Slot  Name   Signature
            0       7     0  this   Lshapeless/HMap;
            0       7     1     a   Ljava/lang/Object;
            0       7     2   cse   Lshapeless/PolyDefns$Case;
    Signature: #145                         // <A:Ljava/lang/Object;>(TA;Lshapeless/PolyDefns$Case<Lshapeless/PolyApply;Lshapeless/$colon$colon<TA;Lshapeless/HNil;>;>;)Ljava/lang/Object;
    MethodParameters:
      Name                           Flags
      a                              final
      cse                            final

  public <A extends java.lang.Object, B extends java.lang.Object> java.lang.Object apply(A, B, shapeless.PolyDefns$Case<shapeless.PolyApply, shapeless.$colon$colon<A, shapeless.$colon$colon<B, shapeless.HNil>>>);
    descriptor: (Ljava/lang/Object;Ljava/lang/Object;Lshapeless/PolyDefns$Case;)Ljava/lang/Object;
    flags: (0x0001) ACC_PUBLIC
    Code:
      stack=4, locals=4, args_size=4
         0: aload_0
         1: aload_1
         2: aload_2
         3: aload_3
         4: invokestatic  #158                // InterfaceMethod shapeless/PolyApply.apply$:(Lshapeless/PolyApply;Ljava/lang/Object;Ljava/lang/Object;Lshapeless/PolyDefns$Case;)Ljava/lang/Object;
         7: areturn
      LineNumberTable:
        line 28: 0
      LocalVariableTable:
        Start  Length  Slot  Name   Signature
            0       8     0  this   Lshapeless/HMap;
            0       8     1     a   Ljava/lang/Object;
            0       8     2     b   Ljava/lang/Object;
            0       8     3   cse   Lshapeless/PolyDefns$Case;
    Signature: #154                         // <A:Ljava/lang/Object;B:Ljava/lang/Object;>(TA;TB;Lshapeless/PolyDefns$Case<Lshapeless/PolyApply;Lshapeless/$colon$colon<TA;Lshapeless/$colon$colon<TB;Lshapeless/HNil;>;>;>;)Ljava/lang/Object;
    MethodParameters:
      Name                           Flags
      a                              final
      b                              final
      cse                            final

  public <A extends java.lang.Object, B extends java.lang.Object, C extends java.lang.Object> java.lang.Object apply(A, B, C, shapeless.PolyDefns$Case<shapeless.PolyApply, shapeless.$colon$colon<A, shapeless.$colon$colon<B, shapeless.$colon$colon<C, shapeless.HNil>>>>);
    descriptor: (Ljava/lang/Object;Ljava/lang/Object;Ljava/lang/Object;Lshapeless/PolyDefns$Case;)Ljava/lang/Object;
    flags: (0x0001) ACC_PUBLIC
    Code:
      stack=5, locals=5, args_size=5
         0: aload_0
         1: aload_1
         2: aload_2
         3: aload_3
         4: aload         4
         6: invokestatic  #163                // InterfaceMethod shapeless/PolyApply.apply$:(Lshapeless/PolyApply;Ljava/lang/Object;Ljava/lang/Object;Ljava/lang/Object;Lshapeless/PolyDefns$Case;)Ljava/lang/Object;
         9: areturn
      LineNumberTable:
        line 28: 0
      LocalVariableTable:
        Start  Length  Slot  Name   Signature
            0      10     0  this   Lshapeless/HMap;
            0      10     1     a   Ljava/lang/Object;
            0      10     2     b   Ljava/lang/Object;
            0      10     3     c   Ljava/lang/Object;
            0      10     4   cse   Lshapeless/PolyDefns$Case;
    Signature: #160                         // <A:Ljava/lang/Object;B:Ljava/lang/Object;C:Ljava/lang/Object;>(TA;TB;TC;Lshapeless/PolyDefns$Case<Lshapeless/PolyApply;Lshapeless/$colon$colon<TA;Lshapeless/$colon$colon<TB;Lshapeless/$colon$colon<TC;Lshapeless/HNil;>;>;>;>;)Ljava/lang/Object;
    MethodParameters:
      Name                           Flags
      a                              final
      b                              final
      c                              final
      cse                            final

  public <A extends java.lang.Object, B extends java.lang.Object, C extends java.lang.Object, D extends java.lang.Object> java.lang.Object apply(A, B, C, D, shapeless.PolyDefns$Case<shapeless.PolyApply, shapeless.$colon$colon<A, shapeless.$colon$colon<B, shapeless.$colon$colon<C, shapeless.$colon$colon<D, shapeless.HNil>>>>>);
    descriptor: (Ljava/lang/Object;Ljava/lang/Object;Ljava/lang/Object;Ljava/lang/Object;Lshapeless/PolyDefns$Case;)Ljava/lang/Object;
    flags: (0x0001) ACC_PUBLIC
    Code:
      stack=6, locals=6, args_size=6
         0: aload_0
         1: aload_1
         2: aload_2
         3: aload_3
         4: aload         4
         6: aload         5
         8: invokestatic  #169                // InterfaceMethod shapeless/PolyApply.apply$:(Lshapeless/PolyApply;Ljava/lang/Object;Ljava/lang/Object;Ljava/lang/Object;Ljava/lang/Object;Lshapeless/PolyDefns$Case;)Ljava/lang/Object;
        11: areturn
      LineNumberTable:
        line 28: 0
      LocalVariableTable:
        Start  Length  Slot  Name   Signature
            0      12     0  this   Lshapeless/HMap;
            0      12     1     a   Ljava/lang/Object;
            0      12     2     b   Ljava/lang/Object;
            0      12     3     c   Ljava/lang/Object;
            0      12     4     d   Ljava/lang/Object;
            0      12     5   cse   Lshapeless/PolyDefns$Case;
    Signature: #165                         // <A:Ljava/lang/Object;B:Ljava/lang/Object;C:Ljava/lang/Object;D:Ljava/lang/Object;>(TA;TB;TC;TD;Lshapeless/PolyDefns$Case<Lshapeless/PolyApply;Lshapeless/$colon$colon<TA;Lshapeless/$colon$colon<TB;Lshapeless/$colon$colon<TC;Lshapeless/$colon$colon<TD;Lshapeless/HNil;>;>;>;>;>;)Ljava/lang/Object;
    MethodParameters:
      Name                           Flags
      a                              final
      b                              final
      c                              final
      d                              final
      cse                            final

  public <A extends java.lang.Object, B extends java.lang.Object, C extends java.lang.Object, D extends java.lang.Object, E extends java.lang.Object> java.lang.Object apply(A, B, C, D, E, shapeless.PolyDefns$Case<shapeless.PolyApply, shapeless.$colon$colon<A, shapeless.$colon$colon<B, shapeless.$colon$colon<C, shapeless.$colon$colon<D, shapeless.$colon$colon<E, shapeless.HNil>>>>>>);
    descriptor: (Ljava/lang/Object;Ljava/lang/Object;Ljava/lang/Object;Ljava/lang/Object;Ljava/lang/Object;Lshapeless/PolyDefns$Case;)Ljava/lang/Object;
    flags: (0x0001) ACC_PUBLIC
    Code:
      stack=7, locals=7, args_size=7
         0: aload_0
         1: aload_1
         2: aload_2
         3: aload_3
         4: aload         4
         6: aload         5
         8: aload         6
        10: invokestatic  #175                // InterfaceMethod shapeless/PolyApply.apply$:(Lshapeless/PolyApply;Ljava/lang/Object;Ljava/lang/Object;Ljava/lang/Object;Ljava/lang/Object;Ljava/lang/Object;Lshapeless/PolyDefns$Case;)Ljava/lang/Object;
        13: areturn
      LineNumberTable:
        line 28: 0
      LocalVariableTable:
        Start  Length  Slot  Name   Signature
            0      14     0  this   Lshapeless/HMap;
            0      14     1     a   Ljava/lang/Object;
            0      14     2     b   Ljava/lang/Object;
            0      14     3     c   Ljava/lang/Object;
            0      14     4     d   Ljava/lang/Object;
            0      14     5     e   Ljava/lang/Object;
            0      14     6   cse   Lshapeless/PolyDefns$Case;
    Signature: #171                         // <A:Ljava/lang/Object;B:Ljava/lang/Object;C:Ljava/lang/Object;D:Ljava/lang/Object;E:Ljava/lang/Object;>(TA;TB;TC;TD;TE;Lshapeless/PolyDefns$Case<Lshapeless/PolyApply;Lshapeless/$colon$colon<TA;Lshapeless/$colon$colon<TB;Lshapeless/$colon$colon<TC;Lshapeless/$colon$colon<TD;Lshapeless/$colon$colon<TE;Lshapeless/HNil;>;>;>;>;>;>;)Ljava/lang/Object;
    MethodParameters:
      Name                           Flags
      a                              final
      b                              final
      c                              final
      d                              final
      e                              final
      cse                            final

  public <A extends java.lang.Object, B extends java.lang.Object, C extends java.lang.Object, D extends java.lang.Object, E extends java.lang.Object, F extends java.lang.Object> java.lang.Object apply(A, B, C, D, E, F, shapeless.PolyDefns$Case<shapeless.PolyApply, shapeless.$colon$colon<A, shapeless.$colon$colon<B, shapeless.$colon$colon<C, shapeless.$colon$colon<D, shapeless.$colon$colon<E, shapeless.$colon$colon<F, shapeless.HNil>>>>>>>);
    descriptor: (Ljava/lang/Object;Ljava/lang/Object;Ljava/lang/Object;Ljava/lang/Object;Ljava/lang/Object;Ljava/lang/Object;Lshapeless/PolyDefns$Case;)Ljava/lang/Object;
    flags: (0x0001) ACC_PUBLIC
    Code:
      stack=8, locals=8, args_size=8
         0: aload_0
         1: aload_1
         2: aload_2
         3: aload_3
         4: aload         4
         6: aload         5
         8: aload         6
        10: aload         7
        12: invokestatic  #180                // InterfaceMethod shapeless/PolyApply.apply$:(Lshapeless/PolyApply;Ljava/lang/Object;Ljava/lang/Object;Ljava/lang/Object;Ljava/lang/Object;Ljava/lang/Object;Ljava/lang/Object;Lshapeless/PolyDefns$Case;)Ljava/lang/Object;
        15: areturn
      LineNumberTable:
        line 28: 0
      LocalVariableTable:
        Start  Length  Slot  Name   Signature
            0      16     0  this   Lshapeless/HMap;
            0      16     1     a   Ljava/lang/Object;
            0      16     2     b   Ljava/lang/Object;
            0      16     3     c   Ljava/lang/Object;
            0      16     4     d   Ljava/lang/Object;
            0      16     5     e   Ljava/lang/Object;
            0      16     6     f   Ljava/lang/Object;
            0      16     7   cse   Lshapeless/PolyDefns$Case;
    Signature: #177                         // <A:Ljava/lang/Object;B:Ljava/lang/Object;C:Ljava/lang/Object;D:Ljava/lang/Object;E:Ljava/lang/Object;F:Ljava/lang/Object;>(TA;TB;TC;TD;TE;TF;Lshapeless/PolyDefns$Case<Lshapeless/PolyApply;Lshapeless/$colon$colon<TA;Lshapeless/$colon$colon<TB;Lshapeless/$colon$colon<TC;Lshapeless/$colon$colon<TD;Lshapeless/$colon$colon<TE;Lshapeless/$colon$colon<TF;Lshapeless/HNil;>;>;>;>;>;>;>;)Ljava/lang/Object;
    MethodParameters:
      Name                           Flags
      a                              final
      b                              final
      c                              final
      d                              final
      e                              final
      f                              final
      cse                            final

  public <A extends java.lang.Object, B extends java.lang.Object, C extends java.lang.Object, D extends java.lang.Object, E extends java.lang.Object, F extends java.lang.Object, G extends java.lang.Object> java.lang.Object apply(A, B, C, D, E, F, G, shapeless.PolyDefns$Case<shapeless.PolyApply, shapeless.$colon$colon<A, shapeless.$colon$colon<B, shapeless.$colon$colon<C, shapeless.$colon$colon<D, shapeless.$colon$colon<E, shapeless.$colon$colon<F, shapeless.$colon$colon<G, shapeless.HNil>>>>>>>>);
    descriptor: (Ljava/lang/Object;Ljava/lang/Object;Ljava/lang/Object;Ljava/lang/Object;Ljava/lang/Object;Ljava/lang/Object;Ljava/lang/Object;Lshapeless/PolyDefns$Case;)Ljava/lang/Object;
    flags: (0x0001) ACC_PUBLIC
    Code:
      stack=9, locals=9, args_size=9
         0: aload_0
         1: aload_1
         2: aload_2
         3: aload_3
         4: aload         4
         6: aload         5
         8: aload         6
        10: aload         7
        12: aload         8
        14: invokestatic  #186                // InterfaceMethod shapeless/PolyApply.apply$:(Lshapeless/PolyApply;Ljava/lang/Object;Ljava/lang/Object;Ljava/lang/Object;Ljava/lang/Object;Ljava/lang/Object;Ljava/lang/Object;Ljava/lang/Object;Lshapeless/PolyDefns$Case;)Ljava/lang/Object;
        17: areturn
      LineNumberTable:
        line 28: 0
      LocalVariableTable:
        Start  Length  Slot  Name   Signature
            0      18     0  this   Lshapeless/HMap;
            0      18     1     a   Ljava/lang/Object;
            0      18     2     b   Ljava/lang/Object;
            0      18     3     c   Ljava/lang/Object;
            0      18     4     d   Ljava/lang/Object;
            0      18     5     e   Ljava/lang/Object;
            0      18     6     f   Ljava/lang/Object;
            0      18     7     g   Ljava/lang/Object;
            0      18     8   cse   Lshapeless/PolyDefns$Case;
    Signature: #182                         // <A:Ljava/lang/Object;B:Ljava/lang/Object;C:Ljava/lang/Object;D:Ljava/lang/Object;E:Ljava/lang/Object;F:Ljava/lang/Object;G:Ljava/lang/Object;>(TA;TB;TC;TD;TE;TF;TG;Lshapeless/PolyDefns$Case<Lshapeless/PolyApply;Lshapeless/$colon$colon<TA;Lshapeless/$colon$colon<TB;Lshapeless/$colon$colon<TC;Lshapeless/$colon$colon<TD;Lshapeless/$colon$colon<TE;Lshapeless/$colon$colon<TF;Lshapeless/$colon$colon<TG;Lshapeless/HNil;>;>;>;>;>;>;>;>;)Ljava/lang/Object;
    MethodParameters:
      Name                           Flags
      a                              final
      b                              final
      c                              final
      d                              final
      e                              final
      f                              final
      g                              final
      cse                            final

  public <A extends java.lang.Object, B extends java.lang.Object, C extends java.lang.Object, D extends java.lang.Object, E extends java.lang.Object, F extends java.lang.Object, G extends java.lang.Object, H extends java.lang.Object> java.lang.Object apply(A, B, C, D, E, F, G, H, shapeless.PolyDefns$Case<shapeless.PolyApply, shapeless.$colon$colon<A, shapeless.$colon$colon<B, shapeless.$colon$colon<C, shapeless.$colon$colon<D, shapeless.$colon$colon<E, shapeless.$colon$colon<F, shapeless.$colon$colon<G, shapeless.$colon$colon<H, shapeless.HNil>>>>>>>>>);
    descriptor: (Ljava/lang/Object;Ljava/lang/Object;Ljava/lang/Object;Ljava/lang/Object;Ljava/lang/Object;Ljava/lang/Object;Ljava/lang/Object;Ljava/lang/Object;Lshapeless/PolyDefns$Case;)Ljava/lang/Object;
    flags: (0x0001) ACC_PUBLIC
    Code:
      stack=10, locals=10, args_size=10
         0: aload_0
         1: aload_1
         2: aload_2
         3: aload_3
         4: aload         4
         6: aload         5
         8: aload         6
        10: aload         7
        12: aload         8
        14: aload         9
        16: invokestatic  #192                // InterfaceMethod shapeless/PolyApply.apply$:(Lshapeless/PolyApply;Ljava/lang/Object;Ljava/lang/Object;Ljava/lang/Object;Ljava/lang/Object;Ljava/lang/Object;Ljava/lang/Object;Ljava/lang/Object;Ljava/lang/Object;Lshapeless/PolyDefns$Case;)Ljava/lang/Object;
        19: areturn
      LineNumberTable:
        line 28: 0
      LocalVariableTable:
        Start  Length  Slot  Name   Signature
            0      20     0  this   Lshapeless/HMap;
            0      20     1     a   Ljava/lang/Object;
            0      20     2     b   Ljava/lang/Object;
            0      20     3     c   Ljava/lang/Object;
            0      20     4     d   Ljava/lang/Object;
            0      20     5     e   Ljava/lang/Object;
            0      20     6     f   Ljava/lang/Object;
            0      20     7     g   Ljava/lang/Object;
            0      20     8     h   Ljava/lang/Object;
            0      20     9   cse   Lshapeless/PolyDefns$Case;
    Signature: #188                         // <A:Ljava/lang/Object;B:Ljava/lang/Object;C:Ljava/lang/Object;D:Ljava/lang/Object;E:Ljava/lang/Object;F:Ljava/lang/Object;G:Ljava/lang/Object;H:Ljava/lang/Object;>(TA;TB;TC;TD;TE;TF;TG;TH;Lshapeless/PolyDefns$Case<Lshapeless/PolyApply;Lshapeless/$colon$colon<TA;Lshapeless/$colon$colon<TB;Lshapeless/$colon$colon<TC;Lshapeless/$colon$colon<TD;Lshapeless/$colon$colon<TE;Lshapeless/$colon$colon<TF;Lshapeless/$colon$colon<TG;Lshapeless/$colon$colon<TH;Lshapeless/HNil;>;>;>;>;>;>;>;>;>;)Ljava/lang/Object;
    MethodParameters:
      Name                           Flags
      a                              final
      b                              final
      c                              final
      d                              final
      e                              final
      f                              final
      g                              final
      h                              final
      cse                            final

  public <A extends java.lang.Object, B extends java.lang.Object, C extends java.lang.Object, D extends java.lang.Object, E extends java.lang.Object, F extends java.lang.Object, G extends java.lang.Object, H extends java.lang.Object, I extends java.lang.Object> java.lang.Object apply(A, B, C, D, E, F, G, H, I, shapeless.PolyDefns$Case<shapeless.PolyApply, shapeless.$colon$colon<A, shapeless.$colon$colon<B, shapeless.$colon$colon<C, shapeless.$colon$colon<D, shapeless.$colon$colon<E, shapeless.$colon$colon<F, shapeless.$colon$colon<G, shapeless.$colon$colon<H, shapeless.$colon$colon<I, shapeless.HNil>>>>>>>>>>);
    descriptor: (Ljava/lang/Object;Ljava/lang/Object;Ljava/lang/Object;Ljava/lang/Object;Ljava/lang/Object;Ljava/lang/Object;Ljava/lang/Object;Ljava/lang/Object;Ljava/lang/Object;Lshapeless/PolyDefns$Case;)Ljava/lang/Object;
    flags: (0x0001) ACC_PUBLIC
    Code:
      stack=11, locals=11, args_size=11
         0: aload_0
         1: aload_1
         2: aload_2
         3: aload_3
         4: aload         4
         6: aload         5
         8: aload         6
        10: aload         7
        12: aload         8
        14: aload         9
        16: aload         10
        18: invokestatic  #198                // InterfaceMethod shapeless/PolyApply.apply$:(Lshapeless/PolyApply;Ljava/lang/Object;Ljava/lang/Object;Ljava/lang/Object;Ljava/lang/Object;Ljava/lang/Object;Ljava/lang/Object;Ljava/lang/Object;Ljava/lang/Object;Ljava/lang/Object;Lshapeless/PolyDefns$Case;)Ljava/lang/Object;
        21: areturn
      LineNumberTable:
        line 28: 0
      LocalVariableTable:
        Start  Length  Slot  Name   Signature
            0      22     0  this   Lshapeless/HMap;
            0      22     1     a   Ljava/lang/Object;
            0      22     2     b   Ljava/lang/Object;
            0      22     3     c   Ljava/lang/Object;
            0      22     4     d   Ljava/lang/Object;
            0      22     5     e   Ljava/lang/Object;
            0      22     6     f   Ljava/lang/Object;
            0      22     7     g   Ljava/lang/Object;
            0      22     8     h   Ljava/lang/Object;
            0      22     9     i   Ljava/lang/Object;
            0      22    10   cse   Lshapeless/PolyDefns$Case;
    Signature: #194                         // <A:Ljava/lang/Object;B:Ljava/lang/Object;C:Ljava/lang/Object;D:Ljava/lang/Object;E:Ljava/lang/Object;F:Ljava/lang/Object;G:Ljava/lang/Object;H:Ljava/lang/Object;I:Ljava/lang/Object;>(TA;TB;TC;TD;TE;TF;TG;TH;TI;Lshapeless/PolyDefns$Case<Lshapeless/PolyApply;Lshapeless/$colon$colon<TA;Lshapeless/$colon$colon<TB;Lshapeless/$colon$colon<TC;Lshapeless/$colon$colon<TD;Lshapeless/$colon$colon<TE;Lshapeless/$colon$colon<TF;Lshapeless/$colon$colon<TG;Lshapeless/$colon$colon<TH;Lshapeless/$colon$colon<TI;Lshapeless/HNil;>;>;>;>;>;>;>;>;>;>;)Ljava/lang/Object;
    MethodParameters:
      Name                           Flags
      a                              final
      b                              final
      c                              final
      d                              final
      e                              final
      f                              final
      g                              final
      h                              final
      i                              final
      cse                            final

  public <A extends java.lang.Object, B extends java.lang.Object, C extends java.lang.Object, D extends java.lang.Object, E extends java.lang.Object, F extends java.lang.Object, G extends java.lang.Object, H extends java.lang.Object, I extends java.lang.Object, J extends java.lang.Object> java.lang.Object apply(A, B, C, D, E, F, G, H, I, J, shapeless.PolyDefns$Case<shapeless.PolyApply, shapeless.$colon$colon<A, shapeless.$colon$colon<B, shapeless.$colon$colon<C, shapeless.$colon$colon<D, shapeless.$colon$colon<E, shapeless.$colon$colon<F, shapeless.$colon$colon<G, shapeless.$colon$colon<H, shapeless.$colon$colon<I, shapeless.$colon$colon<J, shapeless.HNil>>>>>>>>>>>);
    descriptor: (Ljava/lang/Object;Ljava/lang/Object;Ljava/lang/Object;Ljava/lang/Object;Ljava/lang/Object;Ljava/lang/Object;Ljava/lang/Object;Ljava/lang/Object;Ljava/lang/Object;Ljava/lang/Object;Lshapeless/PolyDefns$Case;)Ljava/lang/Object;
    flags: (0x0001) ACC_PUBLIC
    Code:
      stack=12, locals=12, args_size=12
         0: aload_0
         1: aload_1
         2: aload_2
         3: aload_3
         4: aload         4
         6: aload         5
         8: aload         6
        10: aload         7
        12: aload         8
        14: aload         9
        16: aload         10
        18: aload         11
        20: invokestatic  #204                // InterfaceMethod shapeless/PolyApply.apply$:(Lshapeless/PolyApply;Ljava/lang/Object;Ljava/lang/Object;Ljava/lang/Object;Ljava/lang/Object;Ljava/lang/Object;Ljava/lang/Object;Ljava/lang/Object;Ljava/lang/Object;Ljava/lang/Object;Ljava/lang/Object;Lshapeless/PolyDefns$Case;)Ljava/lang/Object;
        23: areturn
      LineNumberTable:
        line 28: 0
      LocalVariableTable:
        Start  Length  Slot  Name   Signature
            0      24     0  this   Lshapeless/HMap;
            0      24     1     a   Ljava/lang/Object;
            0      24     2     b   Ljava/lang/Object;
            0      24     3     c   Ljava/lang/Object;
            0      24     4     d   Ljava/lang/Object;
            0      24     5     e   Ljava/lang/Object;
            0      24     6     f   Ljava/lang/Object;
            0      24     7     g   Ljava/lang/Object;
            0      24     8     h   Ljava/lang/Object;
            0      24     9     i   Ljava/lang/Object;
            0      24    10     j   Ljava/lang/Object;
            0      24    11   cse   Lshapeless/PolyDefns$Case;
    Signature: #200                         // <A:Ljava/lang/Object;B:Ljava/lang/Object;C:Ljava/lang/Object;D:Ljava/lang/Object;E:Ljava/lang/Object;F:Ljava/lang/Object;G:Ljava/lang/Object;H:Ljava/lang/Object;I:Ljava/lang/Object;J:Ljava/lang/Object;>(TA;TB;TC;TD;TE;TF;TG;TH;TI;TJ;Lshapeless/PolyDefns$Case<Lshapeless/PolyApply;Lshapeless/$colon$colon<TA;Lshapeless/$colon$colon<TB;Lshapeless/$colon$colon<TC;Lshapeless/$colon$colon<TD;Lshapeless/$colon$colon<TE;Lshapeless/$colon$colon<TF;Lshapeless/$colon$colon<TG;Lshapeless/$colon$colon<TH;Lshapeless/$colon$colon<TI;Lshapeless/$colon$colon<TJ;Lshapeless/HNil;>;>;>;>;>;>;>;>;>;>;>;)Ljava/lang/Object;
    MethodParameters:
      Name                           Flags
      a                              final
      b                              final
      c                              final
      d                              final
      e                              final
      f                              final
      g                              final
      h                              final
      i                              final
      j                              final
      cse                            final

  public <A extends java.lang.Object, B extends java.lang.Object, C extends java.lang.Object, D extends java.lang.Object, E extends java.lang.Object, F extends java.lang.Object, G extends java.lang.Object, H extends java.lang.Object, I extends java.lang.Object, J extends java.lang.Object, K extends java.lang.Object> java.lang.Object apply(A, B, C, D, E, F, G, H, I, J, K, shapeless.PolyDefns$Case<shapeless.PolyApply, shapeless.$colon$colon<A, shapeless.$colon$colon<B, shapeless.$colon$colon<C, shapeless.$colon$colon<D, shapeless.$colon$colon<E, shapeless.$colon$colon<F, shapeless.$colon$colon<G, shapeless.$colon$colon<H, shapeless.$colon$colon<I, shapeless.$colon$colon<J, shapeless.$colon$colon<K, shapeless.HNil>>>>>>>>>>>>);
    descriptor: (Ljava/lang/Object;Ljava/lang/Object;Ljava/lang/Object;Ljava/lang/Object;Ljava/lang/Object;Ljava/lang/Object;Ljava/lang/Object;Ljava/lang/Object;Ljava/lang/Object;Ljava/lang/Object;Ljava/lang/Object;Lshapeless/PolyDefns$Case;)Ljava/lang/Object;
    flags: (0x0001) ACC_PUBLIC
    Code:
      stack=13, locals=13, args_size=13
         0: aload_0
         1: aload_1
         2: aload_2
         3: aload_3
         4: aload         4
         6: aload         5
         8: aload         6
        10: aload         7
        12: aload         8
        14: aload         9
        16: aload         10
        18: aload         11
        20: aload         12
        22: invokestatic  #210                // InterfaceMethod shapeless/PolyApply.apply$:(Lshapeless/PolyApply;Ljava/lang/Object;Ljava/lang/Object;Ljava/lang/Object;Ljava/lang/Object;Ljava/lang/Object;Ljava/lang/Object;Ljava/lang/Object;Ljava/lang/Object;Ljava/lang/Object;Ljava/lang/Object;Ljava/lang/Object;Lshapeless/PolyDefns$Case;)Ljava/lang/Object;
        25: areturn
      LineNumberTable:
        line 28: 0
      LocalVariableTable:
        Start  Length  Slot  Name   Signature
            0      26     0  this   Lshapeless/HMap;
            0      26     1     a   Ljava/lang/Object;
            0      26     2     b   Ljava/lang/Object;
            0      26     3     c   Ljava/lang/Object;
            0      26     4     d   Ljava/lang/Object;
            0      26     5     e   Ljava/lang/Object;
            0      26     6     f   Ljava/lang/Object;
            0      26     7     g   Ljava/lang/Object;
            0      26     8     h   Ljava/lang/Object;
            0      26     9     i   Ljava/lang/Object;
            0      26    10     j   Ljava/lang/Object;
            0      26    11     k   Ljava/lang/Object;
            0      26    12   cse   Lshapeless/PolyDefns$Case;
    Signature: #206                         // <A:Ljava/lang/Object;B:Ljava/lang/Object;C:Ljava/lang/Object;D:Ljava/lang/Object;E:Ljava/lang/Object;F:Ljava/lang/Object;G:Ljava/lang/Object;H:Ljava/lang/Object;I:Ljava/lang/Object;J:Ljava/lang/Object;K:Ljava/lang/Object;>(TA;TB;TC;TD;TE;TF;TG;TH;TI;TJ;TK;Lshapeless/PolyDefns$Case<Lshapeless/PolyApply;Lshapeless/$colon$colon<TA;Lshapeless/$colon$colon<TB;Lshapeless/$colon$colon<TC;Lshapeless/$colon$colon<TD;Lshapeless/$colon$colon<TE;Lshapeless/$colon$colon<TF;Lshapeless/$colon$colon<TG;Lshapeless/$colon$colon<TH;Lshapeless/$colon$colon<TI;Lshapeless/$colon$colon<TJ;Lshapeless/$colon$colon<TK;Lshapeless/HNil;>;>;>;>;>;>;>;>;>;>;>;>;)Ljava/lang/Object;
    MethodParameters:
      Name                           Flags
      a                              final
      b                              final
      c                              final
      d                              final
      e                              final
      f                              final
      g                              final
      h                              final
      i                              final
      j                              final
      k                              final
      cse                            final

  public <A extends java.lang.Object, B extends java.lang.Object, C extends java.lang.Object, D extends java.lang.Object, E extends java.lang.Object, F extends java.lang.Object, G extends java.lang.Object, H extends java.lang.Object, I extends java.lang.Object, J extends java.lang.Object, K extends java.lang.Object, L extends java.lang.Object> java.lang.Object apply(A, B, C, D, E, F, G, H, I, J, K, L, shapeless.PolyDefns$Case<shapeless.PolyApply, shapeless.$colon$colon<A, shapeless.$colon$colon<B, shapeless.$colon$colon<C, shapeless.$colon$colon<D, shapeless.$colon$colon<E, shapeless.$colon$colon<F, shapeless.$colon$colon<G, shapeless.$colon$colon<H, shapeless.$colon$colon<I, shapeless.$colon$colon<J, shapeless.$colon$colon<K, shapeless.$colon$colon<L, shapeless.HNil>>>>>>>>>>>>>);
    descriptor: (Ljava/lang/Object;Ljava/lang/Object;Ljava/lang/Object;Ljava/lang/Object;Ljava/lang/Object;Ljava/lang/Object;Ljava/lang/Object;Ljava/lang/Object;Ljava/lang/Object;Ljava/lang/Object;Ljava/lang/Object;Ljava/lang/Object;Lshapeless/PolyDefns$Case;)Ljava/lang/Object;
    flags: (0x0001) ACC_PUBLIC
    Code:
      stack=14, locals=14, args_size=14
         0: aload_0
         1: aload_1
         2: aload_2
         3: aload_3
         4: aload         4
         6: aload         5
         8: aload         6
        10: aload         7
        12: aload         8
        14: aload         9
        16: aload         10
        18: aload         11
        20: aload         12
        22: aload         13
        24: invokestatic  #216                // InterfaceMethod shapeless/PolyApply.apply$:(Lshapeless/PolyApply;Ljava/lang/Object;Ljava/lang/Object;Ljava/lang/Object;Ljava/lang/Object;Ljava/lang/Object;Ljava/lang/Object;Ljava/lang/Object;Ljava/lang/Object;Ljava/lang/Object;Ljava/lang/Object;Ljava/lang/Object;Ljava/lang/Object;Lshapeless/PolyDefns$Case;)Ljava/lang/Object;
        27: areturn
      LineNumberTable:
        line 28: 0
      LocalVariableTable:
        Start  Length  Slot  Name   Signature
            0      28     0  this   Lshapeless/HMap;
            0      28     1     a   Ljava/lang/Object;
            0      28     2     b   Ljava/lang/Object;
            0      28     3     c   Ljava/lang/Object;
            0      28     4     d   Ljava/lang/Object;
            0      28     5     e   Ljava/lang/Object;
            0      28     6     f   Ljava/lang/Object;
            0      28     7     g   Ljava/lang/Object;
            0      28     8     h   Ljava/lang/Object;
            0      28     9     i   Ljava/lang/Object;
            0      28    10     j   Ljava/lang/Object;
            0      28    11     k   Ljava/lang/Object;
            0      28    12     l   Ljava/lang/Object;
            0      28    13   cse   Lshapeless/PolyDefns$Case;
    Signature: #212                         // <A:Ljava/lang/Object;B:Ljava/lang/Object;C:Ljava/lang/Object;D:Ljava/lang/Object;E:Ljava/lang/Object;F:Ljava/lang/Object;G:Ljava/lang/Object;H:Ljava/lang/Object;I:Ljava/lang/Object;J:Ljava/lang/Object;K:Ljava/lang/Object;L:Ljava/lang/Object;>(TA;TB;TC;TD;TE;TF;TG;TH;TI;TJ;TK;TL;Lshapeless/PolyDefns$Case<Lshapeless/PolyApply;Lshapeless/$colon$colon<TA;Lshapeless/$colon$colon<TB;Lshapeless/$colon$colon<TC;Lshapeless/$colon$colon<TD;Lshapeless/$colon$colon<TE;Lshapeless/$colon$colon<TF;Lshapeless/$colon$colon<TG;Lshapeless/$colon$colon<TH;Lshapeless/$colon$colon<TI;Lshapeless/$colon$colon<TJ;Lshapeless/$colon$colon<TK;Lshapeless/$colon$colon<TL;Lshapeless/HNil;>;>;>;>;>;>;>;>;>;>;>;>;>;)Ljava/lang/Object;
    MethodParameters:
      Name                           Flags
      a                              final
      b                              final
      c                              final
      d                              final
      e                              final
      f                              final
      g                              final
      h                              final
      i                              final
      j                              final
      k                              final
      l                              final
      cse                            final

  public <A extends java.lang.Object, B extends java.lang.Object, C extends java.lang.Object, D extends java.lang.Object, E extends java.lang.Object, F extends java.lang.Object, G extends java.lang.Object, H extends java.lang.Object, I extends java.lang.Object, J extends java.lang.Object, K extends java.lang.Object, L extends java.lang.Object, M extends java.lang.Object> java.lang.Object apply(A, B, C, D, E, F, G, H, I, J, K, L, M, shapeless.PolyDefns$Case<shapeless.PolyApply, shapeless.$colon$colon<A, shapeless.$colon$colon<B, shapeless.$colon$colon<C, shapeless.$colon$colon<D, shapeless.$colon$colon<E, shapeless.$colon$colon<F, shapeless.$colon$colon<G, shapeless.$colon$colon<H, shapeless.$colon$colon<I, shapeless.$colon$colon<J, shapeless.$colon$colon<K, shapeless.$colon$colon<L, shapeless.$colon$colon<M, shapeless.HNil>>>>>>>>>>>>>>);
    descriptor: (Ljava/lang/Object;Ljava/lang/Object;Ljava/lang/Object;Ljava/lang/Object;Ljava/lang/Object;Ljava/lang/Object;Ljava/lang/Object;Ljava/lang/Object;Ljava/lang/Object;Ljava/lang/Object;Ljava/lang/Object;Ljava/lang/Object;Ljava/lang/Object;Lshapeless/PolyDefns$Case;)Ljava/lang/Object;
    flags: (0x0001) ACC_PUBLIC
    Code:
      stack=15, locals=15, args_size=15
         0: aload_0
         1: aload_1
         2: aload_2
         3: aload_3
         4: aload         4
         6: aload         5
         8: aload         6
        10: aload         7
        12: aload         8
        14: aload         9
        16: aload         10
        18: aload         11
        20: aload         12
        22: aload         13
        24: aload         14
        26: invokestatic  #222                // InterfaceMethod shapeless/PolyApply.apply$:(Lshapeless/PolyApply;Ljava/lang/Object;Ljava/lang/Object;Ljava/lang/Object;Ljava/lang/Object;Ljava/lang/Object;Ljava/lang/Object;Ljava/lang/Object;Ljava/lang/Object;Ljava/lang/Object;Ljava/lang/Object;Ljava/lang/Object;Ljava/lang/Object;Ljava/lang/Object;Lshapeless/PolyDefns$Case;)Ljava/lang/Object;
        29: areturn
      LineNumberTable:
        line 28: 0
      LocalVariableTable:
        Start  Length  Slot  Name   Signature
            0      30     0  this   Lshapeless/HMap;
            0      30     1     a   Ljava/lang/Object;
            0      30     2     b   Ljava/lang/Object;
            0      30     3     c   Ljava/lang/Object;
            0      30     4     d   Ljava/lang/Object;
            0      30     5     e   Ljava/lang/Object;
            0      30     6     f   Ljava/lang/Object;
            0      30     7     g   Ljava/lang/Object;
            0      30     8     h   Ljava/lang/Object;
            0      30     9     i   Ljava/lang/Object;
            0      30    10     j   Ljava/lang/Object;
            0      30    11     k   Ljava/lang/Object;
            0      30    12     l   Ljava/lang/Object;
            0      30    13     m   Ljava/lang/Object;
            0      30    14   cse   Lshapeless/PolyDefns$Case;
    Signature: #218                         // <A:Ljava/lang/Object;B:Ljava/lang/Object;C:Ljava/lang/Object;D:Ljava/lang/Object;E:Ljava/lang/Object;F:Ljava/lang/Object;G:Ljava/lang/Object;H:Ljava/lang/Object;I:Ljava/lang/Object;J:Ljava/lang/Object;K:Ljava/lang/Object;L:Ljava/lang/Object;M:Ljava/lang/Object;>(TA;TB;TC;TD;TE;TF;TG;TH;TI;TJ;TK;TL;TM;Lshapeless/PolyDefns$Case<Lshapeless/PolyApply;Lshapeless/$colon$colon<TA;Lshapeless/$colon$colon<TB;Lshapeless/$colon$colon<TC;Lshapeless/$colon$colon<TD;Lshapeless/$colon$colon<TE;Lshapeless/$colon$colon<TF;Lshapeless/$colon$colon<TG;Lshapeless/$colon$colon<TH;Lshapeless/$colon$colon<TI;Lshapeless/$colon$colon<TJ;Lshapeless/$colon$colon<TK;Lshapeless/$colon$colon<TL;Lshapeless/$colon$colon<TM;Lshapeless/HNil;>;>;>;>;>;>;>;>;>;>;>;>;>;>;)Ljava/lang/Object;
    MethodParameters:
      Name                           Flags
      a                              final
      b                              final
      c                              final
      d                              final
      e                              final
      f                              final
      g                              final
      h                              final
      i                              final
      j                              final
      k                              final
      l                              final
      m                              final
      cse                            final

  public <A extends java.lang.Object, B extends java.lang.Object, C extends java.lang.Object, D extends java.lang.Object, E extends java.lang.Object, F extends java.lang.Object, G extends java.lang.Object, H extends java.lang.Object, I extends java.lang.Object, J extends java.lang.Object, K extends java.lang.Object, L extends java.lang.Object, M extends java.lang.Object, N extends java.lang.Object> java.lang.Object apply(A, B, C, D, E, F, G, H, I, J, K, L, M, N, shapeless.PolyDefns$Case<shapeless.PolyApply, shapeless.$colon$colon<A, shapeless.$colon$colon<B, shapeless.$colon$colon<C, shapeless.$colon$colon<D, shapeless.$colon$colon<E, shapeless.$colon$colon<F, shapeless.$colon$colon<G, shapeless.$colon$colon<H, shapeless.$colon$colon<I, shapeless.$colon$colon<J, shapeless.$colon$colon<K, shapeless.$colon$colon<L, shapeless.$colon$colon<M, shapeless.$colon$colon<N, shapeless.HNil>>>>>>>>>>>>>>>);
    descriptor: (Ljava/lang/Object;Ljava/lang/Object;Ljava/lang/Object;Ljava/lang/Object;Ljava/lang/Object;Ljava/lang/Object;Ljava/lang/Object;Ljava/lang/Object;Ljava/lang/Object;Ljava/lang/Object;Ljava/lang/Object;Ljava/lang/Object;Ljava/lang/Object;Ljava/lang/Object;Lshapeless/PolyDefns$Case;)Ljava/lang/Object;
    flags: (0x0001) ACC_PUBLIC
    Code:
      stack=16, locals=16, args_size=16
         0: aload_0
         1: aload_1
         2: aload_2
         3: aload_3
         4: aload         4
         6: aload         5
         8: aload         6
        10: aload         7
        12: aload         8
        14: aload         9
        16: aload         10
        18: aload         11
        20: aload         12
        22: aload         13
        24: aload         14
        26: aload         15
        28: invokestatic  #228                // InterfaceMethod shapeless/PolyApply.apply$:(Lshapeless/PolyApply;Ljava/lang/Object;Ljava/lang/Object;Ljava/lang/Object;Ljava/lang/Object;Ljava/lang/Object;Ljava/lang/Object;Ljava/lang/Object;Ljava/lang/Object;Ljava/lang/Object;Ljava/lang/Object;Ljava/lang/Object;Ljava/lang/Object;Ljava/lang/Object;Ljava/lang/Object;Lshapeless/PolyDefns$Case;)Ljava/lang/Object;
        31: areturn
      LineNumberTable:
        line 28: 0
      LocalVariableTable:
        Start  Length  Slot  Name   Signature
            0      32     0  this   Lshapeless/HMap;
            0      32     1     a   Ljava/lang/Object;
            0      32     2     b   Ljava/lang/Object;
            0      32     3     c   Ljava/lang/Object;
            0      32     4     d   Ljava/lang/Object;
            0      32     5     e   Ljava/lang/Object;
            0      32     6     f   Ljava/lang/Object;
            0      32     7     g   Ljava/lang/Object;
            0      32     8     h   Ljava/lang/Object;
            0      32     9     i   Ljava/lang/Object;
            0      32    10     j   Ljava/lang/Object;
            0      32    11     k   Ljava/lang/Object;
            0      32    12     l   Ljava/lang/Object;
            0      32    13     m   Ljava/lang/Object;
            0      32    14     n   Ljava/lang/Object;
            0      32    15   cse   Lshapeless/PolyDefns$Case;
    Signature: #224                         // <A:Ljava/lang/Object;B:Ljava/lang/Object;C:Ljava/lang/Object;D:Ljava/lang/Object;E:Ljava/lang/Object;F:Ljava/lang/Object;G:Ljava/lang/Object;H:Ljava/lang/Object;I:Ljava/lang/Object;J:Ljava/lang/Object;K:Ljava/lang/Object;L:Ljava/lang/Object;M:Ljava/lang/Object;N:Ljava/lang/Object;>(TA;TB;TC;TD;TE;TF;TG;TH;TI;TJ;TK;TL;TM;TN;Lshapeless/PolyDefns$Case<Lshapeless/PolyApply;Lshapeless/$colon$colon<TA;Lshapeless/$colon$colon<TB;Lshapeless/$colon$colon<TC;Lshapeless/$colon$colon<TD;Lshapeless/$colon$colon<TE;Lshapeless/$colon$colon<TF;Lshapeless/$colon$colon<TG;Lshapeless/$colon$colon<TH;Lshapeless/$colon$colon<TI;Lshapeless/$colon$colon<TJ;Lshapeless/$colon$colon<TK;Lshapeless/$colon$colon<TL;Lshapeless/$colon$colon<TM;Lshapeless/$colon$colon<TN;Lshapeless/HNil;>;>;>;>;>;>;>;>;>;>;>;>;>;>;>;)Ljava/lang/Object;
    MethodParameters:
      Name                           Flags
      a                              final
      b                              final
      c                              final
      d                              final
      e                              final
      f                              final
      g                              final
      h                              final
      i                              final
      j                              final
      k                              final
      l                              final
      m                              final
      n                              final
      cse                            final

  public <A extends java.lang.Object, B extends java.lang.Object, C extends java.lang.Object, D extends java.lang.Object, E extends java.lang.Object, F extends java.lang.Object, G extends java.lang.Object, H extends java.lang.Object, I extends java.lang.Object, J extends java.lang.Object, K extends java.lang.Object, L extends java.lang.Object, M extends java.lang.Object, N extends java.lang.Object, O extends java.lang.Object> java.lang.Object apply(A, B, C, D, E, F, G, H, I, J, K, L, M, N, O, shapeless.PolyDefns$Case<shapeless.PolyApply, shapeless.$colon$colon<A, shapeless.$colon$colon<B, shapeless.$colon$colon<C, shapeless.$colon$colon<D, shapeless.$colon$colon<E, shapeless.$colon$colon<F, shapeless.$colon$colon<G, shapeless.$colon$colon<H, shapeless.$colon$colon<I, shapeless.$colon$colon<J, shapeless.$colon$colon<K, shapeless.$colon$colon<L, shapeless.$colon$colon<M, shapeless.$colon$colon<N, shapeless.$colon$colon<O, shapeless.HNil>>>>>>>>>>>>>>>>);
    descriptor: (Ljava/lang/Object;Ljava/lang/Object;Ljava/lang/Object;Ljava/lang/Object;Ljava/lang/Object;Ljava/lang/Object;Ljava/lang/Object;Ljava/lang/Object;Ljava/lang/Object;Ljava/lang/Object;Ljava/lang/Object;Ljava/lang/Object;Ljava/lang/Object;Ljava/lang/Object;Ljava/lang/Object;Lshapeless/PolyDefns$Case;)Ljava/lang/Object;
    flags: (0x0001) ACC_PUBLIC
    Code:
      stack=17, locals=17, args_size=17
         0: aload_0
         1: aload_1
         2: aload_2
         3: aload_3
         4: aload         4
         6: aload         5
         8: aload         6
        10: aload         7
        12: aload         8
        14: aload         9
        16: aload         10
        18: aload         11
        20: aload         12
        22: aload         13
        24: aload         14
        26: aload         15
        28: aload         16
        30: invokestatic  #234                // InterfaceMethod shapeless/PolyApply.apply$:(Lshapeless/PolyApply;Ljava/lang/Object;Ljava/lang/Object;Ljava/lang/Object;Ljava/lang/Object;Ljava/lang/Object;Ljava/lang/Object;Ljava/lang/Object;Ljava/lang/Object;Ljava/lang/Object;Ljava/lang/Object;Ljava/lang/Object;Ljava/lang/Object;Ljava/lang/Object;Ljava/lang/Object;Ljava/lang/Object;Lshapeless/PolyDefns$Case;)Ljava/lang/Object;
        33: areturn
      LineNumberTable:
        line 28: 0
      LocalVariableTable:
        Start  Length  Slot  Name   Signature
            0      34     0  this   Lshapeless/HMap;
            0      34     1     a   Ljava/lang/Object;
            0      34     2     b   Ljava/lang/Object;
            0      34     3     c   Ljava/lang/Object;
            0      34     4     d   Ljava/lang/Object;
            0      34     5     e   Ljava/lang/Object;
            0      34     6     f   Ljava/lang/Object;
            0      34     7     g   Ljava/lang/Object;
            0      34     8     h   Ljava/lang/Object;
            0      34     9     i   Ljava/lang/Object;
            0      34    10     j   Ljava/lang/Object;
            0      34    11     k   Ljava/lang/Object;
            0      34    12     l   Ljava/lang/Object;
            0      34    13     m   Ljava/lang/Object;
            0      34    14     n   Ljava/lang/Object;
            0      34    15     o   Ljava/lang/Object;
            0      34    16   cse   Lshapeless/PolyDefns$Case;
    Signature: #230                         // <A:Ljava/lang/Object;B:Ljava/lang/Object;C:Ljava/lang/Object;D:Ljava/lang/Object;E:Ljava/lang/Object;F:Ljava/lang/Object;G:Ljava/lang/Object;H:Ljava/lang/Object;I:Ljava/lang/Object;J:Ljava/lang/Object;K:Ljava/lang/Object;L:Ljava/lang/Object;M:Ljava/lang/Object;N:Ljava/lang/Object;O:Ljava/lang/Object;>(TA;TB;TC;TD;TE;TF;TG;TH;TI;TJ;TK;TL;TM;TN;TO;Lshapeless/PolyDefns$Case<Lshapeless/PolyApply;Lshapeless/$colon$colon<TA;Lshapeless/$colon$colon<TB;Lshapeless/$colon$colon<TC;Lshapeless/$colon$colon<TD;Lshapeless/$colon$colon<TE;Lshapeless/$colon$colon<TF;Lshapeless/$colon$colon<TG;Lshapeless/$colon$colon<TH;Lshapeless/$colon$colon<TI;Lshapeless/$colon$colon<TJ;Lshapeless/$colon$colon<TK;Lshapeless/$colon$colon<TL;Lshapeless/$colon$colon<TM;Lshapeless/$colon$colon<TN;Lshapeless/$colon$colon<TO;Lshapeless/HNil;>;>;>;>;>;>;>;>;>;>;>;>;>;>;>;>;)Ljava/lang/Object;
    MethodParameters:
      Name                           Flags
      a                              final
      b                              final
      c                              final
      d                              final
      e                              final
      f                              final
      g                              final
      h                              final
      i                              final
      j                              final
      k                              final
      l                              final
      m                              final
      n                              final
      o                              final
      cse                            final

  public <A extends java.lang.Object, B extends java.lang.Object, C extends java.lang.Object, D extends java.lang.Object, E extends java.lang.Object, F extends java.lang.Object, G extends java.lang.Object, H extends java.lang.Object, I extends java.lang.Object, J extends java.lang.Object, K extends java.lang.Object, L extends java.lang.Object, M extends java.lang.Object, N extends java.lang.Object, O extends java.lang.Object, P extends java.lang.Object> java.lang.Object apply(A, B, C, D, E, F, G, H, I, J, K, L, M, N, O, P, shapeless.PolyDefns$Case<shapeless.PolyApply, shapeless.$colon$colon<A, shapeless.$colon$colon<B, shapeless.$colon$colon<C, shapeless.$colon$colon<D, shapeless.$colon$colon<E, shapeless.$colon$colon<F, shapeless.$colon$colon<G, shapeless.$colon$colon<H, shapeless.$colon$colon<I, shapeless.$colon$colon<J, shapeless.$colon$colon<K, shapeless.$colon$colon<L, shapeless.$colon$colon<M, shapeless.$colon$colon<N, shapeless.$colon$colon<O, shapeless.$colon$colon<P, shapeless.HNil>>>>>>>>>>>>>>>>>);
    descriptor: (Ljava/lang/Object;Ljava/lang/Object;Ljava/lang/Object;Ljava/lang/Object;Ljava/lang/Object;Ljava/lang/Object;Ljava/lang/Object;Ljava/lang/Object;Ljava/lang/Object;Ljava/lang/Object;Ljava/lang/Object;Ljava/lang/Object;Ljava/lang/Object;Ljava/lang/Object;Ljava/lang/Object;Ljava/lang/Object;Lshapeless/PolyDefns$Case;)Ljava/lang/Object;
    flags: (0x0001) ACC_PUBLIC
    Code:
      stack=18, locals=18, args_size=18
         0: aload_0
         1: aload_1
         2: aload_2
         3: aload_3
         4: aload         4
         6: aload         5
         8: aload         6
        10: aload         7
        12: aload         8
        14: aload         9
        16: aload         10
        18: aload         11
        20: aload         12
        22: aload         13
        24: aload         14
        26: aload         15
        28: aload         16
        30: aload         17
        32: invokestatic  #240                // InterfaceMethod shapeless/PolyApply.apply$:(Lshapeless/PolyApply;Ljava/lang/Object;Ljava/lang/Object;Ljava/lang/Object;Ljava/lang/Object;Ljava/lang/Object;Ljava/lang/Object;Ljava/lang/Object;Ljava/lang/Object;Ljava/lang/Object;Ljava/lang/Object;Ljava/lang/Object;Ljava/lang/Object;Ljava/lang/Object;Ljava/lang/Object;Ljava/lang/Object;Ljava/lang/Object;Lshapeless/PolyDefns$Case;)Ljava/lang/Object;
        35: areturn
      LineNumberTable:
        line 28: 0
      LocalVariableTable:
        Start  Length  Slot  Name   Signature
            0      36     0  this   Lshapeless/HMap;
            0      36     1     a   Ljava/lang/Object;
            0      36     2     b   Ljava/lang/Object;
            0      36     3     c   Ljava/lang/Object;
            0      36     4     d   Ljava/lang/Object;
            0      36     5     e   Ljava/lang/Object;
            0      36     6     f   Ljava/lang/Object;
            0      36     7     g   Ljava/lang/Object;
            0      36     8     h   Ljava/lang/Object;
            0      36     9     i   Ljava/lang/Object;
            0      36    10     j   Ljava/lang/Object;
            0      36    11     k   Ljava/lang/Object;
            0      36    12     l   Ljava/lang/Object;
            0      36    13     m   Ljava/lang/Object;
            0      36    14     n   Ljava/lang/Object;
            0      36    15     o   Ljava/lang/Object;
            0      36    16     p   Ljava/lang/Object;
            0      36    17   cse   Lshapeless/PolyDefns$Case;
    Signature: #236                         // <A:Ljava/lang/Object;B:Ljava/lang/Object;C:Ljava/lang/Object;D:Ljava/lang/Object;E:Ljava/lang/Object;F:Ljava/lang/Object;G:Ljava/lang/Object;H:Ljava/lang/Object;I:Ljava/lang/Object;J:Ljava/lang/Object;K:Ljava/lang/Object;L:Ljava/lang/Object;M:Ljava/lang/Object;N:Ljava/lang/Object;O:Ljava/lang/Object;P:Ljava/lang/Object;>(TA;TB;TC;TD;TE;TF;TG;TH;TI;TJ;TK;TL;TM;TN;TO;TP;Lshapeless/PolyDefns$Case<Lshapeless/PolyApply;Lshapeless/$colon$colon<TA;Lshapeless/$colon$colon<TB;Lshapeless/$colon$colon<TC;Lshapeless/$colon$colon<TD;Lshapeless/$colon$colon<TE;Lshapeless/$colon$colon<TF;Lshapeless/$colon$colon<TG;Lshapeless/$colon$colon<TH;Lshapeless/$colon$colon<TI;Lshapeless/$colon$colon<TJ;Lshapeless/$colon$colon<TK;Lshapeless/$colon$colon<TL;Lshapeless/$colon$colon<TM;Lshapeless/$colon$colon<TN;Lshapeless/$colon$colon<TO;Lshapeless/$colon$colon<TP;Lshapeless/HNil;>;>;>;>;>;>;>;>;>;>;>;>;>;>;>;>;>;)Ljava/lang/Object;
    MethodParameters:
      Name                           Flags
      a                              final
      b                              final
      c                              final
      d                              final
      e                              final
      f                              final
      g                              final
      h                              final
      i                              final
      j                              final
      k                              final
      l                              final
      m                              final
      n                              final
      o                              final
      p                              final
      cse                            final

  public <A extends java.lang.Object, B extends java.lang.Object, C extends java.lang.Object, D extends java.lang.Object, E extends java.lang.Object, F extends java.lang.Object, G extends java.lang.Object, H extends java.lang.Object, I extends java.lang.Object, J extends java.lang.Object, K extends java.lang.Object, L extends java.lang.Object, M extends java.lang.Object, N extends java.lang.Object, O extends java.lang.Object, P extends java.lang.Object, Q extends java.lang.Object> java.lang.Object apply(A, B, C, D, E, F, G, H, I, J, K, L, M, N, O, P, Q, shapeless.PolyDefns$Case<shapeless.PolyApply, shapeless.$colon$colon<A, shapeless.$colon$colon<B, shapeless.$colon$colon<C, shapeless.$colon$colon<D, shapeless.$colon$colon<E, shapeless.$colon$colon<F, shapeless.$colon$colon<G, shapeless.$colon$colon<H, shapeless.$colon$colon<I, shapeless.$colon$colon<J, shapeless.$colon$colon<K, shapeless.$colon$colon<L, shapeless.$colon$colon<M, shapeless.$colon$colon<N, shapeless.$colon$colon<O, shapeless.$colon$colon<P, shapeless.$colon$colon<Q, shapeless.HNil>>>>>>>>>>>>>>>>>>);
    descriptor: (Ljava/lang/Object;Ljava/lang/Object;Ljava/lang/Object;Ljava/lang/Object;Ljava/lang/Object;Ljava/lang/Object;Ljava/lang/Object;Ljava/lang/Object;Ljava/lang/Object;Ljava/lang/Object;Ljava/lang/Object;Ljava/lang/Object;Ljava/lang/Object;Ljava/lang/Object;Ljava/lang/Object;Ljava/lang/Object;Ljava/lang/Object;Lshapeless/PolyDefns$Case;)Ljava/lang/Object;
    flags: (0x0001) ACC_PUBLIC
    Code:
      stack=19, locals=19, args_size=19
         0: aload_0
         1: aload_1
         2: aload_2
         3: aload_3
         4: aload         4
         6: aload         5
         8: aload         6
        10: aload         7
        12: aload         8
        14: aload         9
        16: aload         10
        18: aload         11
        20: aload         12
        22: aload         13
        24: aload         14
        26: aload         15
        28: aload         16
        30: aload         17
        32: aload         18
        34: invokestatic  #246                // InterfaceMethod shapeless/PolyApply.apply$:(Lshapeless/PolyApply;Ljava/lang/Object;Ljava/lang/Object;Ljava/lang/Object;Ljava/lang/Object;Ljava/lang/Object;Ljava/lang/Object;Ljava/lang/Object;Ljava/lang/Object;Ljava/lang/Object;Ljava/lang/Object;Ljava/lang/Object;Ljava/lang/Object;Ljava/lang/Object;Ljava/lang/Object;Ljava/lang/Object;Ljava/lang/Object;Ljava/lang/Object;Lshapeless/PolyDefns$Case;)Ljava/lang/Object;
        37: areturn
      LineNumberTable:
        line 28: 0
      LocalVariableTable:
        Start  Length  Slot  Name   Signature
            0      38     0  this   Lshapeless/HMap;
            0      38     1     a   Ljava/lang/Object;
            0      38     2     b   Ljava/lang/Object;
            0      38     3     c   Ljava/lang/Object;
            0      38     4     d   Ljava/lang/Object;
            0      38     5     e   Ljava/lang/Object;
            0      38     6     f   Ljava/lang/Object;
            0      38     7     g   Ljava/lang/Object;
            0      38     8     h   Ljava/lang/Object;
            0      38     9     i   Ljava/lang/Object;
            0      38    10     j   Ljava/lang/Object;
            0      38    11     k   Ljava/lang/Object;
            0      38    12     l   Ljava/lang/Object;
            0      38    13     m   Ljava/lang/Object;
            0      38    14     n   Ljava/lang/Object;
            0      38    15     o   Ljava/lang/Object;
            0      38    16     p   Ljava/lang/Object;
            0      38    17     q   Ljava/lang/Object;
            0      38    18   cse   Lshapeless/PolyDefns$Case;
    Signature: #242                         // <A:Ljava/lang/Object;B:Ljava/lang/Object;C:Ljava/lang/Object;D:Ljava/lang/Object;E:Ljava/lang/Object;F:Ljava/lang/Object;G:Ljava/lang/Object;H:Ljava/lang/Object;I:Ljava/lang/Object;J:Ljava/lang/Object;K:Ljava/lang/Object;L:Ljava/lang/Object;M:Ljava/lang/Object;N:Ljava/lang/Object;O:Ljava/lang/Object;P:Ljava/lang/Object;Q:Ljava/lang/Object;>(TA;TB;TC;TD;TE;TF;TG;TH;TI;TJ;TK;TL;TM;TN;TO;TP;TQ;Lshapeless/PolyDefns$Case<Lshapeless/PolyApply;Lshapeless/$colon$colon<TA;Lshapeless/$colon$colon<TB;Lshapeless/$colon$colon<TC;Lshapeless/$colon$colon<TD;Lshapeless/$colon$colon<TE;Lshapeless/$colon$colon<TF;Lshapeless/$colon$colon<TG;Lshapeless/$colon$colon<TH;Lshapeless/$colon$colon<TI;Lshapeless/$colon$colon<TJ;Lshapeless/$colon$colon<TK;Lshapeless/$colon$colon<TL;Lshapeless/$colon$colon<TM;Lshapeless/$colon$colon<TN;Lshapeless/$colon$colon<TO;Lshapeless/$colon$colon<TP;Lshapeless/$colon$colon<TQ;Lshapeless/HNil;>;>;>;>;>;>;>;>;>;>;>;>;>;>;>;>;>;>;)Ljava/lang/Object;
    MethodParameters:
      Name                           Flags
      a                              final
      b                              final
      c                              final
      d                              final
      e                              final
      f                              final
      g                              final
      h                              final
      i                              final
      j                              final
      k                              final
      l                              final
      m                              final
      n                              final
      o                              final
      p                              final
      q                              final
      cse                            final

  public <A extends java.lang.Object, B extends java.lang.Object, C extends java.lang.Object, D extends java.lang.Object, E extends java.lang.Object, F extends java.lang.Object, G extends java.lang.Object, H extends java.lang.Object, I extends java.lang.Object, J extends java.lang.Object, K extends java.lang.Object, L extends java.lang.Object, M extends java.lang.Object, N extends java.lang.Object, O extends java.lang.Object, P extends java.lang.Object, Q extends java.lang.Object, R extends java.lang.Object> java.lang.Object apply(A, B, C, D, E, F, G, H, I, J, K, L, M, N, O, P, Q, R, shapeless.PolyDefns$Case<shapeless.PolyApply, shapeless.$colon$colon<A, shapeless.$colon$colon<B, shapeless.$colon$colon<C, shapeless.$colon$colon<D, shapeless.$colon$colon<E, shapeless.$colon$colon<F, shapeless.$colon$colon<G, shapeless.$colon$colon<H, shapeless.$colon$colon<I, shapeless.$colon$colon<J, shapeless.$colon$colon<K, shapeless.$colon$colon<L, shapeless.$colon$colon<M, shapeless.$colon$colon<N, shapeless.$colon$colon<O, shapeless.$colon$colon<P, shapeless.$colon$colon<Q, shapeless.$colon$colon<R, shapeless.HNil>>>>>>>>>>>>>>>>>>>);
    descriptor: (Ljava/lang/Object;Ljava/lang/Object;Ljava/lang/Object;Ljava/lang/Object;Ljava/lang/Object;Ljava/lang/Object;Ljava/lang/Object;Ljava/lang/Object;Ljava/lang/Object;Ljava/lang/Object;Ljava/lang/Object;Ljava/lang/Object;Ljava/lang/Object;Ljava/lang/Object;Ljava/lang/Object;Ljava/lang/Object;Ljava/lang/Object;Ljava/lang/Object;Lshapeless/PolyDefns$Case;)Ljava/lang/Object;
    flags: (0x0001) ACC_PUBLIC
    Code:
      stack=20, locals=20, args_size=20
         0: aload_0
         1: aload_1
         2: aload_2
         3: aload_3
         4: aload         4
         6: aload         5
         8: aload         6
        10: aload         7
        12: aload         8
        14: aload         9
        16: aload         10
        18: aload         11
        20: aload         12
        22: aload         13
        24: aload         14
        26: aload         15
        28: aload         16
        30: aload         17
        32: aload         18
        34: aload         19
        36: invokestatic  #252                // InterfaceMethod shapeless/PolyApply.apply$:(Lshapeless/PolyApply;Ljava/lang/Object;Ljava/lang/Object;Ljava/lang/Object;Ljava/lang/Object;Ljava/lang/Object;Ljava/lang/Object;Ljava/lang/Object;Ljava/lang/Object;Ljava/lang/Object;Ljava/lang/Object;Ljava/lang/Object;Ljava/lang/Object;Ljava/lang/Object;Ljava/lang/Object;Ljava/lang/Object;Ljava/lang/Object;Ljava/lang/Object;Ljava/lang/Object;Lshapeless/PolyDefns$Case;)Ljava/lang/Object;
        39: areturn
      LineNumberTable:
        line 28: 0
      LocalVariableTable:
        Start  Length  Slot  Name   Signature
            0      40     0  this   Lshapeless/HMap;
            0      40     1     a   Ljava/lang/Object;
            0      40     2     b   Ljava/lang/Object;
            0      40     3     c   Ljava/lang/Object;
            0      40     4     d   Ljava/lang/Object;
            0      40     5     e   Ljava/lang/Object;
            0      40     6     f   Ljava/lang/Object;
            0      40     7     g   Ljava/lang/Object;
            0      40     8     h   Ljava/lang/Object;
            0      40     9     i   Ljava/lang/Object;
            0      40    10     j   Ljava/lang/Object;
            0      40    11     k   Ljava/lang/Object;
            0      40    12     l   Ljava/lang/Object;
            0      40    13     m   Ljava/lang/Object;
            0      40    14     n   Ljava/lang/Object;
            0      40    15     o   Ljava/lang/Object;
            0      40    16     p   Ljava/lang/Object;
            0      40    17     q   Ljava/lang/Object;
            0      40    18     r   Ljava/lang/Object;
            0      40    19   cse   Lshapeless/PolyDefns$Case;
    Signature: #248                         // <A:Ljava/lang/Object;B:Ljava/lang/Object;C:Ljava/lang/Object;D:Ljava/lang/Object;E:Ljava/lang/Object;F:Ljava/lang/Object;G:Ljava/lang/Object;H:Ljava/lang/Object;I:Ljava/lang/Object;J:Ljava/lang/Object;K:Ljava/lang/Object;L:Ljava/lang/Object;M:Ljava/lang/Object;N:Ljava/lang/Object;O:Ljava/lang/Object;P:Ljava/lang/Object;Q:Ljava/lang/Object;R:Ljava/lang/Object;>(TA;TB;TC;TD;TE;TF;TG;TH;TI;TJ;TK;TL;TM;TN;TO;TP;TQ;TR;Lshapeless/PolyDefns$Case<Lshapeless/PolyApply;Lshapeless/$colon$colon<TA;Lshapeless/$colon$colon<TB;Lshapeless/$colon$colon<TC;Lshapeless/$colon$colon<TD;Lshapeless/$colon$colon<TE;Lshapeless/$colon$colon<TF;Lshapeless/$colon$colon<TG;Lshapeless/$colon$colon<TH;Lshapeless/$colon$colon<TI;Lshapeless/$colon$colon<TJ;Lshapeless/$colon$colon<TK;Lshapeless/$colon$colon<TL;Lshapeless/$colon$colon<TM;Lshapeless/$colon$colon<TN;Lshapeless/$colon$colon<TO;Lshapeless/$colon$colon<TP;Lshapeless/$colon$colon<TQ;Lshapeless/$colon$colon<TR;Lshapeless/HNil;>;>;>;>;>;>;>;>;>;>;>;>;>;>;>;>;>;>;>;)Ljava/lang/Object;
    MethodParameters:
      Name                           Flags
      a                              final
      b                              final
      c                              final
      d                              final
      e                              final
      f                              final
      g                              final
      h                              final
      i                              final
      j                              final
      k                              final
      l                              final
      m                              final
      n                              final
      o                              final
      p                              final
      q                              final
      r                              final
      cse                            final

  public <A extends java.lang.Object, B extends java.lang.Object, C extends java.lang.Object, D extends java.lang.Object, E extends java.lang.Object, F extends java.lang.Object, G extends java.lang.Object, H extends java.lang.Object, I extends java.lang.Object, J extends java.lang.Object, K extends java.lang.Object, L extends java.lang.Object, M extends java.lang.Object, N extends java.lang.Object, O extends java.lang.Object, P extends java.lang.Object, Q extends java.lang.Object, R extends java.lang.Object, S extends java.lang.Object> java.lang.Object apply(A, B, C, D, E, F, G, H, I, J, K, L, M, N, O, P, Q, R, S, shapeless.PolyDefns$Case<shapeless.PolyApply, shapeless.$colon$colon<A, shapeless.$colon$colon<B, shapeless.$colon$colon<C, shapeless.$colon$colon<D, shapeless.$colon$colon<E, shapeless.$colon$colon<F, shapeless.$colon$colon<G, shapeless.$colon$colon<H, shapeless.$colon$colon<I, shapeless.$colon$colon<J, shapeless.$colon$colon<K, shapeless.$colon$colon<L, shapeless.$colon$colon<M, shapeless.$colon$colon<N, shapeless.$colon$colon<O, shapeless.$colon$colon<P, shapeless.$colon$colon<Q, shapeless.$colon$colon<R, shapeless.$colon$colon<S, shapeless.HNil>>>>>>>>>>>>>>>>>>>>);
    descriptor: (Ljava/lang/Object;Ljava/lang/Object;Ljava/lang/Object;Ljava/lang/Object;Ljava/lang/Object;Ljava/lang/Object;Ljava/lang/Object;Ljava/lang/Object;Ljava/lang/Object;Ljava/lang/Object;Ljava/lang/Object;Ljava/lang/Object;Ljava/lang/Object;Ljava/lang/Object;Ljava/lang/Object;Ljava/lang/Object;Ljava/lang/Object;Ljava/lang/Object;Ljava/lang/Object;Lshapeless/PolyDefns$Case;)Ljava/lang/Object;
    flags: (0x0001) ACC_PUBLIC
    Code:
      stack=21, locals=21, args_size=21
         0: aload_0
         1: aload_1
         2: aload_2
         3: aload_3
         4: aload         4
         6: aload         5
         8: aload         6
        10: aload         7
        12: aload         8
        14: aload         9
        16: aload         10
        18: aload         11
        20: aload         12
        22: aload         13
        24: aload         14
        26: aload         15
        28: aload         16
        30: aload         17
        32: aload         18
        34: aload         19
        36: aload         20
        38: invokestatic  #258                // InterfaceMethod shapeless/PolyApply.apply$:(Lshapeless/PolyApply;Ljava/lang/Object;Ljava/lang/Object;Ljava/lang/Object;Ljava/lang/Object;Ljava/lang/Object;Ljava/lang/Object;Ljava/lang/Object;Ljava/lang/Object;Ljava/lang/Object;Ljava/lang/Object;Ljava/lang/Object;Ljava/lang/Object;Ljava/lang/Object;Ljava/lang/Object;Ljava/lang/Object;Ljava/lang/Object;Ljava/lang/Object;Ljava/lang/Object;Ljava/lang/Object;Lshapeless/PolyDefns$Case;)Ljava/lang/Object;
        41: areturn
      LineNumberTable:
        line 28: 0
      LocalVariableTable:
        Start  Length  Slot  Name   Signature
            0      42     0  this   Lshapeless/HMap;
            0      42     1     a   Ljava/lang/Object;
            0      42     2     b   Ljava/lang/Object;
            0      42     3     c   Ljava/lang/Object;
            0      42     4     d   Ljava/lang/Object;
            0      42     5     e   Ljava/lang/Object;
            0      42     6     f   Ljava/lang/Object;
            0      42     7     g   Ljava/lang/Object;
            0      42     8     h   Ljava/lang/Object;
            0      42     9     i   Ljava/lang/Object;
            0      42    10     j   Ljava/lang/Object;
            0      42    11     k   Ljava/lang/Object;
            0      42    12     l   Ljava/lang/Object;
            0      42    13     m   Ljava/lang/Object;
            0      42    14     n   Ljava/lang/Object;
            0      42    15     o   Ljava/lang/Object;
            0      42    16     p   Ljava/lang/Object;
            0      42    17     q   Ljava/lang/Object;
            0      42    18     r   Ljava/lang/Object;
            0      42    19     s   Ljava/lang/Object;
            0      42    20   cse   Lshapeless/PolyDefns$Case;
    Signature: #254                         // <A:Ljava/lang/Object;B:Ljava/lang/Object;C:Ljava/lang/Object;D:Ljava/lang/Object;E:Ljava/lang/Object;F:Ljava/lang/Object;G:Ljava/lang/Object;H:Ljava/lang/Object;I:Ljava/lang/Object;J:Ljava/lang/Object;K:Ljava/lang/Object;L:Ljava/lang/Object;M:Ljava/lang/Object;N:Ljava/lang/Object;O:Ljava/lang/Object;P:Ljava/lang/Object;Q:Ljava/lang/Object;R:Ljava/lang/Object;S:Ljava/lang/Object;>(TA;TB;TC;TD;TE;TF;TG;TH;TI;TJ;TK;TL;TM;TN;TO;TP;TQ;TR;TS;Lshapeless/PolyDefns$Case<Lshapeless/PolyApply;Lshapeless/$colon$colon<TA;Lshapeless/$colon$colon<TB;Lshapeless/$colon$colon<TC;Lshapeless/$colon$colon<TD;Lshapeless/$colon$colon<TE;Lshapeless/$colon$colon<TF;Lshapeless/$colon$colon<TG;Lshapeless/$colon$colon<TH;Lshapeless/$colon$colon<TI;Lshapeless/$colon$colon<TJ;Lshapeless/$colon$colon<TK;Lshapeless/$colon$colon<TL;Lshapeless/$colon$colon<TM;Lshapeless/$colon$colon<TN;Lshapeless/$colon$colon<TO;Lshapeless/$colon$colon<TP;Lshapeless/$colon$colon<TQ;Lshapeless/$colon$colon<TR;Lshapeless/$colon$colon<TS;Lshapeless/HNil;>;>;>;>;>;>;>;>;>;>;>;>;>;>;>;>;>;>;>;>;)Ljava/lang/Object;
    MethodParameters:
      Name                           Flags
      a                              final
      b                              final
      c                              final
      d                              final
      e                              final
      f                              final
      g                              final
      h                              final
      i                              final
      j                              final
      k                              final
      l                              final
      m                              final
      n                              final
      o                              final
      p                              final
      q                              final
      r                              final
      s                              final
      cse                            final

  public <A extends java.lang.Object, B extends java.lang.Object, C extends java.lang.Object, D extends java.lang.Object, E extends java.lang.Object, F extends java.lang.Object, G extends java.lang.Object, H extends java.lang.Object, I extends java.lang.Object, J extends java.lang.Object, K extends java.lang.Object, L extends java.lang.Object, M extends java.lang.Object, N extends java.lang.Object, O extends java.lang.Object, P extends java.lang.Object, Q extends java.lang.Object, R extends java.lang.Object, S extends java.lang.Object, T extends java.lang.Object> java.lang.Object apply(A, B, C, D, E, F, G, H, I, J, K, L, M, N, O, P, Q, R, S, T, shapeless.PolyDefns$Case<shapeless.PolyApply, shapeless.$colon$colon<A, shapeless.$colon$colon<B, shapeless.$colon$colon<C, shapeless.$colon$colon<D, shapeless.$colon$colon<E, shapeless.$colon$colon<F, shapeless.$colon$colon<G, shapeless.$colon$colon<H, shapeless.$colon$colon<I, shapeless.$colon$colon<J, shapeless.$colon$colon<K, shapeless.$colon$colon<L, shapeless.$colon$colon<M, shapeless.$colon$colon<N, shapeless.$colon$colon<O, shapeless.$colon$colon<P, shapeless.$colon$colon<Q, shapeless.$colon$colon<R, shapeless.$colon$colon<S, shapeless.$colon$colon<T, shapeless.HNil>>>>>>>>>>>>>>>>>>>>>);
    descriptor: (Ljava/lang/Object;Ljava/lang/Object;Ljava/lang/Object;Ljava/lang/Object;Ljava/lang/Object;Ljava/lang/Object;Ljava/lang/Object;Ljava/lang/Object;Ljava/lang/Object;Ljava/lang/Object;Ljava/lang/Object;Ljava/lang/Object;Ljava/lang/Object;Ljava/lang/Object;Ljava/lang/Object;Ljava/lang/Object;Ljava/lang/Object;Ljava/lang/Object;Ljava/lang/Object;Ljava/lang/Object;Lshapeless/PolyDefns$Case;)Ljava/lang/Object;
    flags: (0x0001) ACC_PUBLIC
    Code:
      stack=22, locals=22, args_size=22
         0: aload_0
         1: aload_1
         2: aload_2
         3: aload_3
         4: aload         4
         6: aload         5
         8: aload         6
        10: aload         7
        12: aload         8
        14: aload         9
        16: aload         10
        18: aload         11
        20: aload         12
        22: aload         13
        24: aload         14
        26: aload         15
        28: aload         16
        30: aload         17
        32: aload         18
        34: aload         19
        36: aload         20
        38: aload         21
        40: invokestatic  #263                // InterfaceMethod shapeless/PolyApply.apply$:(Lshapeless/PolyApply;Ljava/lang/Object;Ljava/lang/Object;Ljava/lang/Object;Ljava/lang/Object;Ljava/lang/Object;Ljava/lang/Object;Ljava/lang/Object;Ljava/lang/Object;Ljava/lang/Object;Ljava/lang/Object;Ljava/lang/Object;Ljava/lang/Object;Ljava/lang/Object;Ljava/lang/Object;Ljava/lang/Object;Ljava/lang/Object;Ljava/lang/Object;Ljava/lang/Object;Ljava/lang/Object;Ljava/lang/Object;Lshapeless/PolyDefns$Case;)Ljava/lang/Object;
        43: areturn
      LineNumberTable:
        line 28: 0
      LocalVariableTable:
        Start  Length  Slot  Name   Signature
            0      44     0  this   Lshapeless/HMap;
            0      44     1     a   Ljava/lang/Object;
            0      44     2     b   Ljava/lang/Object;
            0      44     3     c   Ljava/lang/Object;
            0      44     4     d   Ljava/lang/Object;
            0      44     5     e   Ljava/lang/Object;
            0      44     6     f   Ljava/lang/Object;
            0      44     7     g   Ljava/lang/Object;
            0      44     8     h   Ljava/lang/Object;
            0      44     9     i   Ljava/lang/Object;
            0      44    10     j   Ljava/lang/Object;
            0      44    11     k   Ljava/lang/Object;
            0      44    12     l   Ljava/lang/Object;
            0      44    13     m   Ljava/lang/Object;
            0      44    14     n   Ljava/lang/Object;
            0      44    15     o   Ljava/lang/Object;
            0      44    16     p   Ljava/lang/Object;
            0      44    17     q   Ljava/lang/Object;
            0      44    18     r   Ljava/lang/Object;
            0      44    19     s   Ljava/lang/Object;
            0      44    20     t   Ljava/lang/Object;
            0      44    21   cse   Lshapeless/PolyDefns$Case;
    Signature: #260                         // <A:Ljava/lang/Object;B:Ljava/lang/Object;C:Ljava/lang/Object;D:Ljava/lang/Object;E:Ljava/lang/Object;F:Ljava/lang/Object;G:Ljava/lang/Object;H:Ljava/lang/Object;I:Ljava/lang/Object;J:Ljava/lang/Object;K:Ljava/lang/Object;L:Ljava/lang/Object;M:Ljava/lang/Object;N:Ljava/lang/Object;O:Ljava/lang/Object;P:Ljava/lang/Object;Q:Ljava/lang/Object;R:Ljava/lang/Object;S:Ljava/lang/Object;T:Ljava/lang/Object;>(TA;TB;TC;TD;TE;TF;TG;TH;TI;TJ;TK;TL;TM;TN;TO;TP;TQ;TR;TS;TT;Lshapeless/PolyDefns$Case<Lshapeless/PolyApply;Lshapeless/$colon$colon<TA;Lshapeless/$colon$colon<TB;Lshapeless/$colon$colon<TC;Lshapeless/$colon$colon<TD;Lshapeless/$colon$colon<TE;Lshapeless/$colon$colon<TF;Lshapeless/$colon$colon<TG;Lshapeless/$colon$colon<TH;Lshapeless/$colon$colon<TI;Lshapeless/$colon$colon<TJ;Lshapeless/$colon$colon<TK;Lshapeless/$colon$colon<TL;Lshapeless/$colon$colon<TM;Lshapeless/$colon$colon<TN;Lshapeless/$colon$colon<TO;Lshapeless/$colon$colon<TP;Lshapeless/$colon$colon<TQ;Lshapeless/$colon$colon<TR;Lshapeless/$colon$colon<TS;Lshapeless/$colon$colon<TT;Lshapeless/HNil;>;>;>;>;>;>;>;>;>;>;>;>;>;>;>;>;>;>;>;>;>;)Ljava/lang/Object;
    MethodParameters:
      Name                           Flags
      a                              final
      b                              final
      c                              final
      d                              final
      e                              final
      f                              final
      g                              final
      h                              final
      i                              final
      j                              final
      k                              final
      l                              final
      m                              final
      n                              final
      o                              final
      p                              final
      q                              final
      r                              final
      s                              final
      t                              final
      cse                            final

  public <A extends java.lang.Object, B extends java.lang.Object, C extends java.lang.Object, D extends java.lang.Object, E extends java.lang.Object, F extends java.lang.Object, G extends java.lang.Object, H extends java.lang.Object, I extends java.lang.Object, J extends java.lang.Object, K extends java.lang.Object, L extends java.lang.Object, M extends java.lang.Object, N extends java.lang.Object, O extends java.lang.Object, P extends java.lang.Object, Q extends java.lang.Object, R extends java.lang.Object, S extends java.lang.Object, T extends java.lang.Object, U extends java.lang.Object> java.lang.Object apply(A, B, C, D, E, F, G, H, I, J, K, L, M, N, O, P, Q, R, S, T, U, shapeless.PolyDefns$Case<shapeless.PolyApply, shapeless.$colon$colon<A, shapeless.$colon$colon<B, shapeless.$colon$colon<C, shapeless.$colon$colon<D, shapeless.$colon$colon<E, shapeless.$colon$colon<F, shapeless.$colon$colon<G, shapeless.$colon$colon<H, shapeless.$colon$colon<I, shapeless.$colon$colon<J, shapeless.$colon$colon<K, shapeless.$colon$colon<L, shapeless.$colon$colon<M, shapeless.$colon$colon<N, shapeless.$colon$colon<O, shapeless.$colon$colon<P, shapeless.$colon$colon<Q, shapeless.$colon$colon<R, shapeless.$colon$colon<S, shapeless.$colon$colon<T, shapeless.$colon$colon<U, shapeless.HNil>>>>>>>>>>>>>>>>>>>>>>);
    descriptor: (Ljava/lang/Object;Ljava/lang/Object;Ljava/lang/Object;Ljava/lang/Object;Ljava/lang/Object;Ljava/lang/Object;Ljava/lang/Object;Ljava/lang/Object;Ljava/lang/Object;Ljava/lang/Object;Ljava/lang/Object;Ljava/lang/Object;Ljava/lang/Object;Ljava/lang/Object;Ljava/lang/Object;Ljava/lang/Object;Ljava/lang/Object;Ljava/lang/Object;Ljava/lang/Object;Ljava/lang/Object;Ljava/lang/Object;Lshapeless/PolyDefns$Case;)Ljava/lang/Object;
    flags: (0x0001) ACC_PUBLIC
    Code:
      stack=23, locals=23, args_size=23
         0: aload_0
         1: aload_1
         2: aload_2
         3: aload_3
         4: aload         4
         6: aload         5
         8: aload         6
        10: aload         7
        12: aload         8
        14: aload         9
        16: aload         10
        18: aload         11
        20: aload         12
        22: aload         13
        24: aload         14
        26: aload         15
        28: aload         16
        30: aload         17
        32: aload         18
        34: aload         19
        36: aload         20
        38: aload         21
        40: aload         22
        42: invokestatic  #269                // InterfaceMethod shapeless/PolyApply.apply$:(Lshapeless/PolyApply;Ljava/lang/Object;Ljava/lang/Object;Ljava/lang/Object;Ljava/lang/Object;Ljava/lang/Object;Ljava/lang/Object;Ljava/lang/Object;Ljava/lang/Object;Ljava/lang/Object;Ljava/lang/Object;Ljava/lang/Object;Ljava/lang/Object;Ljava/lang/Object;Ljava/lang/Object;Ljava/lang/Object;Ljava/lang/Object;Ljava/lang/Object;Ljava/lang/Object;Ljava/lang/Object;Ljava/lang/Object;Ljava/lang/Object;Lshapeless/PolyDefns$Case;)Ljava/lang/Object;
        45: areturn
      LineNumberTable:
        line 28: 0
      LocalVariableTable:
        Start  Length  Slot  Name   Signature
            0      46     0  this   Lshapeless/HMap;
            0      46     1     a   Ljava/lang/Object;
            0      46     2     b   Ljava/lang/Object;
            0      46     3     c   Ljava/lang/Object;
            0      46     4     d   Ljava/lang/Object;
            0      46     5     e   Ljava/lang/Object;
            0      46     6     f   Ljava/lang/Object;
            0      46     7     g   Ljava/lang/Object;
            0      46     8     h   Ljava/lang/Object;
            0      46     9     i   Ljava/lang/Object;
            0      46    10     j   Ljava/lang/Object;
            0      46    11     k   Ljava/lang/Object;
            0      46    12     l   Ljava/lang/Object;
            0      46    13     m   Ljava/lang/Object;
            0      46    14     n   Ljava/lang/Object;
            0      46    15     o   Ljava/lang/Object;
            0      46    16     p   Ljava/lang/Object;
            0      46    17     q   Ljava/lang/Object;
            0      46    18     r   Ljava/lang/Object;
            0      46    19     s   Ljava/lang/Object;
            0      46    20     t   Ljava/lang/Object;
            0      46    21     u   Ljava/lang/Object;
            0      46    22   cse   Lshapeless/PolyDefns$Case;
    Signature: #265                         // <A:Ljava/lang/Object;B:Ljava/lang/Object;C:Ljava/lang/Object;D:Ljava/lang/Object;E:Ljava/lang/Object;F:Ljava/lang/Object;G:Ljava/lang/Object;H:Ljava/lang/Object;I:Ljava/lang/Object;J:Ljava/lang/Object;K:Ljava/lang/Object;L:Ljava/lang/Object;M:Ljava/lang/Object;N:Ljava/lang/Object;O:Ljava/lang/Object;P:Ljava/lang/Object;Q:Ljava/lang/Object;R:Ljava/lang/Object;S:Ljava/lang/Object;T:Ljava/lang/Object;U:Ljava/lang/Object;>(TA;TB;TC;TD;TE;TF;TG;TH;TI;TJ;TK;TL;TM;TN;TO;TP;TQ;TR;TS;TT;TU;Lshapeless/PolyDefns$Case<Lshapeless/PolyApply;Lshapeless/$colon$colon<TA;Lshapeless/$colon$colon<TB;Lshapeless/$colon$colon<TC;Lshapeless/$colon$colon<TD;Lshapeless/$colon$colon<TE;Lshapeless/$colon$colon<TF;Lshapeless/$colon$colon<TG;Lshapeless/$colon$colon<TH;Lshapeless/$colon$colon<TI;Lshapeless/$colon$colon<TJ;Lshapeless/$colon$colon<TK;Lshapeless/$colon$colon<TL;Lshapeless/$colon$colon<TM;Lshapeless/$colon$colon<TN;Lshapeless/$colon$colon<TO;Lshapeless/$colon$colon<TP;Lshapeless/$colon$colon<TQ;Lshapeless/$colon$colon<TR;Lshapeless/$colon$colon<TS;Lshapeless/$colon$colon<TT;Lshapeless/$colon$colon<TU;Lshapeless/HNil;>;>;>;>;>;>;>;>;>;>;>;>;>;>;>;>;>;>;>;>;>;>;)Ljava/lang/Object;
    MethodParameters:
      Name                           Flags
      a                              final
      b                              final
      c                              final
      d                              final
      e                              final
      f                              final
      g                              final
      h                              final
      i                              final
      j                              final
      k                              final
      l                              final
      m                              final
      n                              final
      o                              final
      p                              final
      q                              final
      r                              final
      s                              final
      t                              final
      u                              final
      cse                            final

  public <A extends java.lang.Object, B extends java.lang.Object, C extends java.lang.Object, D extends java.lang.Object, E extends java.lang.Object, F extends java.lang.Object, G extends java.lang.Object, H extends java.lang.Object, I extends java.lang.Object, J extends java.lang.Object, K extends java.lang.Object, L extends java.lang.Object, M extends java.lang.Object, N extends java.lang.Object, O extends java.lang.Object, P extends java.lang.Object, Q extends java.lang.Object, R extends java.lang.Object, S extends java.lang.Object, T extends java.lang.Object, U extends java.lang.Object, V extends java.lang.Object> java.lang.Object apply(A, B, C, D, E, F, G, H, I, J, K, L, M, N, O, P, Q, R, S, T, U, V, shapeless.PolyDefns$Case<shapeless.PolyApply, shapeless.$colon$colon<A, shapeless.$colon$colon<B, shapeless.$colon$colon<C, shapeless.$colon$colon<D, shapeless.$colon$colon<E, shapeless.$colon$colon<F, shapeless.$colon$colon<G, shapeless.$colon$colon<H, shapeless.$colon$colon<I, shapeless.$colon$colon<J, shapeless.$colon$colon<K, shapeless.$colon$colon<L, shapeless.$colon$colon<M, shapeless.$colon$colon<N, shapeless.$colon$colon<O, shapeless.$colon$colon<P, shapeless.$colon$colon<Q, shapeless.$colon$colon<R, shapeless.$colon$colon<S, shapeless.$colon$colon<T, shapeless.$colon$colon<U, shapeless.$colon$colon<V, shapeless.HNil>>>>>>>>>>>>>>>>>>>>>>>);
    descriptor: (Ljava/lang/Object;Ljava/lang/Object;Ljava/lang/Object;Ljava/lang/Object;Ljava/lang/Object;Ljava/lang/Object;Ljava/lang/Object;Ljava/lang/Object;Ljava/lang/Object;Ljava/lang/Object;Ljava/lang/Object;Ljava/lang/Object;Ljava/lang/Object;Ljava/lang/Object;Ljava/lang/Object;Ljava/lang/Object;Ljava/lang/Object;Ljava/lang/Object;Ljava/lang/Object;Ljava/lang/Object;Ljava/lang/Object;Ljava/lang/Object;Lshapeless/PolyDefns$Case;)Ljava/lang/Object;
    flags: (0x0001) ACC_PUBLIC
    Code:
      stack=24, locals=24, args_size=24
         0: aload_0
         1: aload_1
         2: aload_2
         3: aload_3
         4: aload         4
         6: aload         5
         8: aload         6
        10: aload         7
        12: aload         8
        14: aload         9
        16: aload         10
        18: aload         11
        20: aload         12
        22: aload         13
        24: aload         14
        26: aload         15
        28: aload         16
        30: aload         17
        32: aload         18
        34: aload         19
        36: aload         20
        38: aload         21
        40: aload         22
        42: aload         23
        44: invokestatic  #275                // InterfaceMethod shapeless/PolyApply.apply$:(Lshapeless/PolyApply;Ljava/lang/Object;Ljava/lang/Object;Ljava/lang/Object;Ljava/lang/Object;Ljava/lang/Object;Ljava/lang/Object;Ljava/lang/Object;Ljava/lang/Object;Ljava/lang/Object;Ljava/lang/Object;Ljava/lang/Object;Ljava/lang/Object;Ljava/lang/Object;Ljava/lang/Object;Ljava/lang/Object;Ljava/lang/Object;Ljava/lang/Object;Ljava/lang/Object;Ljava/lang/Object;Ljava/lang/Object;Ljava/lang/Object;Ljava/lang/Object;Lshapeless/PolyDefns$Case;)Ljava/lang/Object;
        47: areturn
      LineNumberTable:
        line 28: 0
      LocalVariableTable:
        Start  Length  Slot  Name   Signature
            0      48     0  this   Lshapeless/HMap;
            0      48     1     a   Ljava/lang/Object;
            0      48     2     b   Ljava/lang/Object;
            0      48     3     c   Ljava/lang/Object;
            0      48     4     d   Ljava/lang/Object;
            0      48     5     e   Ljava/lang/Object;
            0      48     6     f   Ljava/lang/Object;
            0      48     7     g   Ljava/lang/Object;
            0      48     8     h   Ljava/lang/Object;
            0      48     9     i   Ljava/lang/Object;
            0      48    10     j   Ljava/lang/Object;
            0      48    11     k   Ljava/lang/Object;
            0      48    12     l   Ljava/lang/Object;
            0      48    13     m   Ljava/lang/Object;
            0      48    14     n   Ljava/lang/Object;
            0      48    15     o   Ljava/lang/Object;
            0      48    16     p   Ljava/lang/Object;
            0      48    17     q   Ljava/lang/Object;
            0      48    18     r   Ljava/lang/Object;
            0      48    19     s   Ljava/lang/Object;
            0      48    20     t   Ljava/lang/Object;
            0      48    21     u   Ljava/lang/Object;
            0      48    22     v   Ljava/lang/Object;
            0      48    23   cse   Lshapeless/PolyDefns$Case;
    Signature: #271                         // <A:Ljava/lang/Object;B:Ljava/lang/Object;C:Ljava/lang/Object;D:Ljava/lang/Object;E:Ljava/lang/Object;F:Ljava/lang/Object;G:Ljava/lang/Object;H:Ljava/lang/Object;I:Ljava/lang/Object;J:Ljava/lang/Object;K:Ljava/lang/Object;L:Ljava/lang/Object;M:Ljava/lang/Object;N:Ljava/lang/Object;O:Ljava/lang/Object;P:Ljava/lang/Object;Q:Ljava/lang/Object;R:Ljava/lang/Object;S:Ljava/lang/Object;T:Ljava/lang/Object;U:Ljava/lang/Object;V:Ljava/lang/Object;>(TA;TB;TC;TD;TE;TF;TG;TH;TI;TJ;TK;TL;TM;TN;TO;TP;TQ;TR;TS;TT;TU;TV;Lshapeless/PolyDefns$Case<Lshapeless/PolyApply;Lshapeless/$colon$colon<TA;Lshapeless/$colon$colon<TB;Lshapeless/$colon$colon<TC;Lshapeless/$colon$colon<TD;Lshapeless/$colon$colon<TE;Lshapeless/$colon$colon<TF;Lshapeless/$colon$colon<TG;Lshapeless/$colon$colon<TH;Lshapeless/$colon$colon<TI;Lshapeless/$colon$colon<TJ;Lshapeless/$colon$colon<TK;Lshapeless/$colon$colon<TL;Lshapeless/$colon$colon<TM;Lshapeless/$colon$colon<TN;Lshapeless/$colon$colon<TO;Lshapeless/$colon$colon<TP;Lshapeless/$colon$colon<TQ;Lshapeless/$colon$colon<TR;Lshapeless/$colon$colon<TS;Lshapeless/$colon$colon<TT;Lshapeless/$colon$colon<TU;Lshapeless/$colon$colon<TV;Lshapeless/HNil;>;>;>;>;>;>;>;>;>;>;>;>;>;>;>;>;>;>;>;>;>;>;>;)Ljava/lang/Object;
    MethodParameters:
      Name                           Flags
      a                              final
      b                              final
      c                              final
      d                              final
      e                              final
      f                              final
      g                              final
      h                              final
      i                              final
      j                              final
      k                              final
      l                              final
      m                              final
      n                              final
      o                              final
      p                              final
      q                              final
      r                              final
      s                              final
      t                              final
      u                              final
      v                              final
      cse                            final

  public shapeless.Poly1$Case$ Case();
    descriptor: ()Lshapeless/Poly1$Case$;
    flags: (0x0001) ACC_PUBLIC
    Code:
      stack=1, locals=1, args_size=1
         0: aload_0
         1: getfield      #278                // Field Case$module:Lshapeless/Poly1$Case$;
         4: ifnonnull     11
         7: aload_0
         8: invokespecial #282                // Method Case$lzycompute$1:()V
        11: aload_0
        12: getfield      #278                // Field Case$module:Lshapeless/Poly1$Case$;
        15: areturn
      StackMapTable: number_of_entries = 1
        frame_type = 11 /* same */
      LineNumberTable:
        line 28: 0
      LocalVariableTable:
        Start  Length  Slot  Name   Signature
            0      16     0  this   Lshapeless/HMap;

  public shapeless.Poly$ProductCase$ ProductCase();
    descriptor: ()Lshapeless/Poly$ProductCase$;
    flags: (0x0001) ACC_PUBLIC
    Code:
      stack=1, locals=1, args_size=1
         0: aload_0
         1: getfield      #286                // Field ProductCase$module:Lshapeless/Poly$ProductCase$;
         4: ifnonnull     11
         7: aload_0
         8: invokespecial #289                // Method ProductCase$lzycompute$1:()V
        11: aload_0
        12: getfield      #286                // Field ProductCase$module:Lshapeless/Poly$ProductCase$;
        15: areturn
      StackMapTable: number_of_entries = 1
        frame_type = 11 /* same */
      LineNumberTable:
        line 28: 0
      LocalVariableTable:
        Start  Length  Slot  Name   Signature
            0      16     0  this   Lshapeless/HMap;

  public shapeless.Poly$CaseBuilder$ CaseBuilder();
    descriptor: ()Lshapeless/Poly$CaseBuilder$;
    flags: (0x0001) ACC_PUBLIC
    Code:
      stack=1, locals=1, args_size=1
         0: aload_0
         1: getfield      #292                // Field CaseBuilder$module:Lshapeless/Poly$CaseBuilder$;
         4: ifnonnull     11
         7: aload_0
         8: invokespecial #295                // Method CaseBuilder$lzycompute$1:()V
        11: aload_0
        12: getfield      #292                // Field CaseBuilder$module:Lshapeless/Poly$CaseBuilder$;
        15: areturn
      StackMapTable: number_of_entries = 1
        frame_type = 11 /* same */
      LineNumberTable:
        line 28: 0
      LocalVariableTable:
        Start  Length  Slot  Name   Signature
            0      16     0  this   Lshapeless/HMap;

  public <K extends java.lang.Object, V extends java.lang.Object> scala.Option<V> get(K, R);
    descriptor: (Ljava/lang/Object;Ljava/lang/Object;)Lscala/Option;
    flags: (0x0001) ACC_PUBLIC
    Code:
      stack=2, locals=3, args_size=3
         0: aload_0
         1: getfield      #301                // Field underlying:Lscala/collection/immutable/Map;
         4: aload_1
         5: invokeinterface #306,  2          // InterfaceMethod scala/collection/immutable/Map.get:(Ljava/lang/Object;)Lscala/Option;
        10: areturn
      LineNumberTable:
        line 29: 0
      LocalVariableTable:
        Start  Length  Slot  Name   Signature
            0      11     0  this   Lshapeless/HMap;
            0      11     1     k   Ljava/lang/Object;
            0      11     2    ev   Ljava/lang/Object;
    Signature: #298                         // <K:Ljava/lang/Object;V:Ljava/lang/Object;>(TK;TR;)Lscala/Option<TV;>;
    MethodParameters:
      Name                           Flags
      k                              final
      ev                             final

  public <K extends java.lang.Object, V extends java.lang.Object> shapeless.HMap<R> $plus(scala.Tuple2<K, V>, R);
    descriptor: (Lscala/Tuple2;Ljava/lang/Object;)Lshapeless/HMap;
    flags: (0x0001) ACC_PUBLIC
    Code:
      stack=4, locals=3, args_size=3
         0: new           #2                  // class shapeless/HMap
         3: dup
         4: aload_0
         5: getfield      #301                // Field underlying:Lscala/collection/immutable/Map;
         8: aload_1
         9: invokeinterface #313,  2          // InterfaceMethod scala/collection/immutable/Map.$plus:(Lscala/Tuple2;)Lscala/collection/immutable/MapOps;
        14: checkcast     #303                // class scala/collection/immutable/Map
        17: invokespecial #317                // Method "<init>":(Lscala/collection/immutable/Map;)V
        20: areturn
      LineNumberTable:
        line 31: 0
      LocalVariableTable:
        Start  Length  Slot  Name   Signature
            0      21     0  this   Lshapeless/HMap;
            0      21     1    kv   Lscala/Tuple2;
            0      21     2    ev   Ljava/lang/Object;
    Signature: #309                         // <K:Ljava/lang/Object;V:Ljava/lang/Object;>(Lscala/Tuple2<TK;TV;>;TR;)Lshapeless/HMap<TR;>;
    MethodParameters:
      Name                           Flags
      kv                             final
      ev                             final

  public <K extends java.lang.Object> shapeless.HMap<R> $minus(K);
    descriptor: (Ljava/lang/Object;)Lshapeless/HMap;
    flags: (0x0001) ACC_PUBLIC
    Code:
      stack=4, locals=2, args_size=2
         0: new           #2                  // class shapeless/HMap
         3: dup
         4: aload_0
         5: getfield      #301                // Field underlying:Lscala/collection/immutable/Map;
         8: aload_1
         9: invokeinterface #324,  2          // InterfaceMethod scala/collection/immutable/Map.$minus:(Ljava/lang/Object;)Lscala/collection/immutable/MapOps;
        14: checkcast     #303                // class scala/collection/immutable/Map
        17: invokespecial #317                // Method "<init>":(Lscala/collection/immutable/Map;)V
        20: areturn
      LineNumberTable:
        line 32: 0
      LocalVariableTable:
        Start  Length  Slot  Name   Signature
            0      21     0  this   Lshapeless/HMap;
            0      21     1     k   Ljava/lang/Object;
    Signature: #321                         // <K:Ljava/lang/Object;>(TK;)Lshapeless/HMap<TR;>;
    MethodParameters:
      Name                           Flags
      k                              final

  public <K extends java.lang.Object, V extends java.lang.Object> shapeless.PolyDefns$Case<shapeless.HMap<R>, shapeless.$colon$colon<K, shapeless.HNil>> caseRel(R);
    descriptor: (Ljava/lang/Object;)Lshapeless/PolyDefns$Case;
    flags: (0x0001) ACC_PUBLIC
    Code:
      stack=3, locals=2, args_size=2
         0: getstatic     #332                // Field shapeless/package$.MODULE$:Lshapeless/package$;
         3: invokevirtual #336                // Method shapeless/package$.poly:()Lshapeless/PolyDefns$;
         6: invokevirtual #342                // Method shapeless/PolyDefns$.Case1:()Lshapeless/Cases$Case1$;
         9: aload_0
        10: aload_1
        11: invokedynamic #360,  0            // InvokeDynamic #0:apply:(Lshapeless/HMap;Ljava/lang/Object;)Lscala/Function1;
        16: invokevirtual #363                // Method shapeless/Cases$Case1$.apply:(Lscala/Function1;)Lshapeless/PolyDefns$Case;
        19: areturn
      LineNumberTable:
        line 34: 0
      LocalVariableTable:
        Start  Length  Slot  Name   Signature
            0      20     0  this   Lshapeless/HMap;
            0      20     1    ev   Ljava/lang/Object;
    Signature: #327                         // <K:Ljava/lang/Object;V:Ljava/lang/Object;>(TR;)Lshapeless/PolyDefns$Case<Lshapeless/HMap<TR;>;Lshapeless/$colon$colon<TK;Lshapeless/HNil;>;>;
    MethodParameters:
      Name                           Flags
      ev                             final

  private final void Case$lzycompute$1();
    descriptor: ()V
    flags: (0x0012) ACC_PRIVATE, ACC_FINAL
    Code:
      stack=4, locals=2, args_size=1
         0: aload_0
         1: dup
         2: astore_1
         3: monitorenter
         4: aload_0
         5: getfield      #278                // Field Case$module:Lshapeless/Poly1$Case$;
         8: ifnonnull     23
        11: aload_0
        12: new           #34                 // class shapeless/Poly1$Case$
        15: dup
        16: aload_0
        17: invokespecial #366                // Method shapeless/Poly1$Case$."<init>":(Lshapeless/Poly1;)V
        20: putfield      #278                // Field Case$module:Lshapeless/Poly1$Case$;
        23: aload_1
        24: monitorexit
        25: goto          31
        28: aload_1
        29: monitorexit
        30: athrow
        31: return
      Exception table:
         from    to  target type
             4    23    28   any
      StackMapTable: number_of_entries = 3
        frame_type = 252 /* append */
          offset_delta = 23
          locals = [ class shapeless/HMap ]
        frame_type = 68 /* same_locals_1_stack_item */
          stack = [ class java/lang/Throwable ]
        frame_type = 2 /* same */
      LineNumberTable:
        line 28: 0
      LocalVariableTable:
        Start  Length  Slot  Name   Signature
            0      32     0  this   Lshapeless/HMap;

  private final void ProductCase$lzycompute$1();
    descriptor: ()V
    flags: (0x0012) ACC_PRIVATE, ACC_FINAL
    Code:
      stack=4, locals=2, args_size=1
         0: aload_0
         1: dup
         2: astore_1
         3: monitorenter
         4: aload_0
         5: getfield      #286                // Field ProductCase$module:Lshapeless/Poly$ProductCase$;
         8: ifnonnull     23
        11: aload_0
        12: new           #31                 // class shapeless/Poly$ProductCase$
        15: dup
        16: aload_0
        17: invokespecial #371                // Method shapeless/Poly$ProductCase$."<init>":(Lshapeless/Poly;)V
        20: putfield      #286                // Field ProductCase$module:Lshapeless/Poly$ProductCase$;
        23: aload_1
        24: monitorexit
        25: goto          31
        28: aload_1
        29: monitorexit
        30: athrow
        31: return
      Exception table:
         from    to  target type
             4    23    28   any
      StackMapTable: number_of_entries = 3
        frame_type = 252 /* append */
          offset_delta = 23
          locals = [ class shapeless/HMap ]
        frame_type = 68 /* same_locals_1_stack_item */
          stack = [ class java/lang/Throwable ]
        frame_type = 2 /* same */
      LineNumberTable:
        line 28: 0
      LocalVariableTable:
        Start  Length  Slot  Name   Signature
            0      32     0  this   Lshapeless/HMap;

  private final void CaseBuilder$lzycompute$1();
    descriptor: ()V
    flags: (0x0012) ACC_PRIVATE, ACC_FINAL
    Code:
      stack=4, locals=2, args_size=1
         0: aload_0
         1: dup
         2: astore_1
         3: monitorenter
         4: aload_0
         5: getfield      #292                // Field CaseBuilder$module:Lshapeless/Poly$CaseBuilder$;
         8: ifnonnull     23
        11: aload_0
        12: new           #28                 // class shapeless/Poly$CaseBuilder$
        15: dup
        16: aload_0
        17: invokespecial #372                // Method shapeless/Poly$CaseBuilder$."<init>":(Lshapeless/Poly;)V
        20: putfield      #292                // Field CaseBuilder$module:Lshapeless/Poly$CaseBuilder$;
        23: aload_1
        24: monitorexit
        25: goto          31
        28: aload_1
        29: monitorexit
        30: athrow
        31: return
      Exception table:
         from    to  target type
             4    23    28   any
      StackMapTable: number_of_entries = 3
        frame_type = 252 /* append */
          offset_delta = 23
          locals = [ class shapeless/HMap ]
        frame_type = 68 /* same_locals_1_stack_item */
          stack = [ class java/lang/Throwable ]
        frame_type = 2 /* same */
      LineNumberTable:
        line 28: 0
      LocalVariableTable:
        Start  Length  Slot  Name   Signature
            0      32     0  this   Lshapeless/HMap;

  public static final java.lang.Object $anonfun$caseRel$1(shapeless.HMap, java.lang.Object, java.lang.Object);
    descriptor: (Lshapeless/HMap;Ljava/lang/Object;Ljava/lang/Object;)Ljava/lang/Object;
    flags: (0x1019) ACC_PUBLIC, ACC_STATIC, ACC_FINAL, ACC_SYNTHETIC
    Code:
      stack=3, locals=3, args_size=3
         0: aload_0
         1: aload_2
         2: aload_1
         3: invokevirtual #377                // Method get:(Ljava/lang/Object;Ljava/lang/Object;)Lscala/Option;
         6: invokevirtual #382                // Method scala/Option.get:()Ljava/lang/Object;
         9: areturn
      LineNumberTable:
        line 34: 0
      LocalVariableTable:
        Start  Length  Slot  Name   Signature
            0      10     0 $this   Lshapeless/HMap;
            0      10     1  ev$1   Ljava/lang/Object;
            0      10     2   x$1   Ljava/lang/Object;
    MethodParameters:
      Name                           Flags
      $this                          final synthetic
      ev$1                           final
      x$1                            final

  public shapeless.HMap(scala.collection.immutable.Map<java.lang.Object, java.lang.Object>);
    descriptor: (Lscala/collection/immutable/Map;)V
    flags: (0x0001) ACC_PUBLIC
    Code:
      stack=2, locals=2, args_size=2
         0: aload_0
         1: aload_1
         2: putfield      #301                // Field underlying:Lscala/collection/immutable/Map;
         5: aload_0
         6: invokespecial #385                // Method java/lang/Object."<init>":()V
         9: aload_0
        10: invokestatic  #389                // InterfaceMethod shapeless/PolyApply.$init$:(Lshapeless/PolyApply;)V
        13: aload_0
        14: invokestatic  #391                // InterfaceMethod shapeless/Poly.$init$:(Lshapeless/Poly;)V
        17: aload_0
        18: invokestatic  #393                // InterfaceMethod shapeless/Poly1.$init$:(Lshapeless/Poly1;)V
        21: return
      LineNumberTable:
        line 28: 0
      LocalVariableTable:
        Start  Length  Slot  Name   Signature
            0      22     0  this   Lshapeless/HMap;
            0      22     1 underlying   Lscala/collection/immutable/Map;
    Signature: #383                         // (Lscala/collection/immutable/Map<Ljava/lang/Object;Ljava/lang/Object;>;)V
    MethodParameters:
      Name                           Flags
      underlying                     final

  private static java.lang.Object $deserializeLambda$(java.lang.invoke.SerializedLambda);
    descriptor: (Ljava/lang/invoke/SerializedLambda;)Ljava/lang/Object;
    flags: (0x100a) ACC_PRIVATE, ACC_STATIC, ACC_SYNTHETIC
    Code:
      stack=1, locals=1, args_size=1
         0: aload_0
         1: invokedynamic #405,  0            // InvokeDynamic #1:lambdaDeserialize:(Ljava/lang/invoke/SerializedLambda;)Ljava/lang/Object;
         6: areturn
}
InnerClasses:
  public static final #16= #13 of #15;    // Lookup=class java/lang/invoke/MethodHandles$Lookup of class java/lang/invoke/MethodHandles
  public #21= #18 of #20;                 // Case1$=class shapeless/Cases$Case1$ of class shapeless/Cases
  public #26= #23 of #25;                 // CaseBuilder=class shapeless/Poly$CaseBuilder of class shapeless/Poly
  public #29= #28 of #25;                 // CaseBuilder$=class shapeless/Poly$CaseBuilder$ of class shapeless/Poly
  public #32= #31 of #25;                 // ProductCase$=class shapeless/Poly$ProductCase$ of class shapeless/Poly
  public #35= #34 of #7;                  // Case$=class shapeless/Poly1$Case$ of class shapeless/Poly1
  public #26= #37 of #7;                  // CaseBuilder=class shapeless/Poly1$CaseBuilder of class shapeless/Poly1
  public static abstract #42= #39 of #41; // Case=class shapeless/PolyDefns$Case of class shapeless/PolyDefns
  public static #45= #44 of #41;          // Compose=class shapeless/PolyDefns$Compose of class shapeless/PolyDefns
  public static #48= #47 of #41;          // RotateLeft=class shapeless/PolyDefns$RotateLeft of class shapeless/PolyDefns
  public static #51= #50 of #41;          // RotateRight=class shapeless/PolyDefns$RotateRight of class shapeless/PolyDefns
Signature: #3                           // <R:Ljava/lang/Object;>Ljava/lang/Object;Lshapeless/Poly1;
SourceFile: "hmap.scala"
RuntimeVisibleAnnotations:
  0: #9(#10=s#11)
    scala.reflect.ScalaSignature(
      bytes="\u0006\u0005\u0005\re\u0001B\b\u0011\u0001MA\u0001b\b\u0001\u0003\u0002\u0003\u0006I\u0001\t\u0005\u0006]\u0001!\ta\f\u0005\u0006}\u0001!\ta\u0010\u0005\u0006!\u0002!\t!\u0015\u0005\u0006?\u0002!\t\u0001\u0019\u0005\u0006K\u0002!\u0019AZ\u0004\u0007\u007fBA\t!!\u0001\u0007\r=\u0001\u0002\u0012AA\u0002\u0011\u0019q\u0003\u0002\"\u0001\u0002\u0016!9\u0011q\u0003\u0005\u0005\u0002\u0005e\u0001bBA\u0017\u0011\u0011\u0005\u0011q\u0006\u0005\b\u0003[AA\u0011AA \u0011%\t\t\u0006CI\u0001\n\u0003\t\u0019\u0006C\u0005\u0002t!\t\t\u0011\"\u0003\u0002v\t!\u0001*T1q\u0015\u0005\t\u0012!C:iCB,G.Z:t\u0007\u0001)\"\u0001F\u001a\u0014\u0007\u0001)2\u0004\u0005\u0002\u001735\tqCC\u0001\u0019\u0003\u0015\u00198-\u00197b\u0013\tQrC\u0001\u0004B]f\u0014VM\u001a\t\u00039ui\u0011\u0001E\u0005\u0003=A\u0011Q\u0001U8msF\n!\"\u001e8eKJd\u00170\u001b8h!\u0011\t\u0003fK\u0016\u000f\u0005\t2\u0003CA\u0012\u0018\u001b\u0005!#BA\u0013\u0013\u0003\u0019a$o\\8u}%\u0011qeF\u0001\u0007!J,G-\u001a4\n\u0005%R#aA\'ba*\u0011qe\u0006\t\u0003-1J!!L\f\u0003\u0007\u0005s\u00170\u0001\u0004=S:LGO\u0010\u000b\u0003au\u00022\u0001\b\u00012!\t\u00114\u0007\u0004\u0001\u0005\u000bQ\u0002!\u0019A\u001b\u0003\u0003I+2A\u000e\u001e=#\t94\u0006\u0005\u0002\u0017q%\u0011\u0011h\u0006\u0002\b\u001d>$\b.\u001b8h\t\u0015Y4G1\u00017\u0005\u0005yF!B\u001e4\u0005\u00041\u0004bB\u0010\u0003!\u0003\u0005\r\u0001I\u0001\u0004O\u0016$Xc\u0001!M\rR\u0011\u0011I\u0014\u000b\u0003\u0005\"\u00032AF\"F\u0013\t!uC\u0001\u0004PaRLwN\u001c\t\u0003e\u0019#QaR\u0002C\u0002Y\u0012\u0011A\u0016\u0005\u0006\u0013\u000e\u0001\u001dAS\u0001\u0003KZ\u0004BAM\u001aL\u000bB\u0011!\u0007\u0014\u0003\u0006\u001b\u000e\u0011\rA\u000e\u0002\u0002\u0017\")qj\u0001a\u0001\u0017\u0006\t1.A\u0003%a2,8/F\u0002S/f#\"a\u0015.\u0015\u0005A\"\u0006\"B%\u0005\u0001\b)\u0006\u0003\u0002\u001a4-b\u0003\"AM,\u0005\u000b5#!\u0019\u0001\u001c\u0011\u0005IJF!B$\u0005\u0005\u00041\u0004\"B.\u0005\u0001\u0004a\u0016AA6w!\u00111RL\u0016-\n\u0005y;\"A\u0002+va2,\'\'\u0001\u0004%[&tWo]\u000b\u0003C\u0012$\"\u0001\r2\t\u000b=+\u0001\u0019A2\u0011\u0005I\"G!B\'\u0006\u0005\u00041\u0014aB2bg\u0016\u0014V\r\\\u000b\u0004OjdHC\u00015~!\u0015IW\u000f_=|\u001d\tQ\u0017O\u0004\u0002l]:\u0011A\u0004\\\u0005\u0003[B\tq\u0001]1dW\u0006<W-\u0003\u0002pa\u0006!\u0001o\u001c7z\u0015\ti\u0007#\u0003\u0002sg\u0006)1)Y:fc%\u0011A\u000f\u0005\u0002\u0006\u0007\u0006\u001cXm]\u0005\u0003m^\u00141!Q;y\u0015\t\u00118/D\u0001\u0001!\t\u0011$\u0010B\u0003N\r\t\u0007a\u0007\u0005\u00023y\u0012)qI\u0002b\u0001m!)\u0011J\u0002a\u0002}B!!gM=|\u0003\u0011AU*\u00199\u0011\u0005qA1\u0003\u0002\u0005\u0016\u0003\u000b\u0001B!a\u0002\u0002\u00125\u0011\u0011\u0011\u0002\u0006\u0005\u0003\u0017\ti!\u0001\u0002j_*\u0011\u0011qB\u0001\u0005U\u00064\u0018-\u0003\u0003\u0002\u0014\u0005%!\u0001D*fe&\fG.\u001b>bE2,GCAA\u0001\u0003\u0015\t\u0007\u000f\u001d7z+\u0011\tY\"!\n\u0016\u0005\u0005u\u0001#\u0002\u000f\u0002 \u0005\r\u0012bAA\u0011!\tY\u0001*T1q\u0005VLG\u000eZ3s!\r\u0011\u0014Q\u0005\u0003\u0007i)\u0011\r!a\n\u0016\u000bY\nI#a\u000b\u0005\rm\n)C1\u00017\t\u0019Y\u0014Q\u0005b\u0001m\u0005)Q-\u001c9usV!\u0011\u0011GA\u001c+\t\t\u0019\u0004\u0005\u0003\u001d\u0001\u0005U\u0002c\u0001\u001a\u00028\u00111Ag\u0003b\u0001\u0003s)RANA\u001e\u0003{!aaOA\u001c\u0005\u00041DAB\u001e\u00028\t\u0007a\'\u0006\u0003\u0002B\u0005\u001dC\u0003BA\"\u0003\u001f\u0002B\u0001\b\u0001\u0002FA\u0019!\'a\u0012\u0005\rQb!\u0019AA%+\u00151\u00141JA\'\t\u0019Y\u0014q\tb\u0001m\u001111(a\u0012C\u0002YBQa\b\u0007A\u0002\u0001\n1\u0004\n7fgNLg.\u001b;%OJ,\u0017\r^3sI\u0011,g-Y;mi\u0012\nT\u0003BA+\u0003W*\"!a\u0016+\u0007\u0001\nIf\u000b\u0002\u0002\\A!\u0011QLA4\u001b\t\tyF\u0003\u0003\u0002b\u0005\r\u0014!C;oG\",7m[3e\u0015\r\t)gF\u0001\u000bC:tw\u000e^1uS>t\u0017\u0002BA5\u0003?\u0012\u0011#\u001e8dQ\u0016\u001c7.\u001a3WCJL\u0017M\\2f\t\u0019!TB1\u0001\u0002nU)a\'a\u001c\u0002r\u001111(a\u001bC\u0002Y\"aaOA6\u0005\u00041\u0014\u0001D<sSR,\'+\u001a9mC\u000e,GCAA<!\u0011\tI(a \u000e\u0005\u0005m$\u0002BA?\u0003\u001b\tA\u0001\\1oO&!\u0011\u0011QA>\u0005\u0019y%M[3di\u0002"
    )
BootstrapMethods:
  0: #357 REF_invokeStatic java/lang/invoke/LambdaMetafactory.altMetafactory:(Ljava/lang/invoke/MethodHandles$Lookup;Ljava/lang/String;Ljava/lang/invoke/MethodType;[Ljava/lang/Object;)Ljava/lang/invoke/CallSite;
    Method arguments:
      #344 (Ljava/lang/Object;)Ljava/lang/Object;
      #349 REF_invokeStatic shapeless/HMap.$anonfun$caseRel$1:(Lshapeless/HMap;Ljava/lang/Object;Ljava/lang/Object;)Ljava/lang/Object;
      #344 (Ljava/lang/Object;)Ljava/lang/Object;
      #350 1
  1: #402 REF_invokeStatic scala/runtime/LambdaDeserialize.bootstrap:(Ljava/lang/invoke/MethodHandles$Lookup;Ljava/lang/String;Ljava/lang/invoke/MethodType;[Ljava/lang/invoke/MethodHandle;)Ljava/lang/invoke/CallSite;
    Method arguments:
      #349 REF_invokeStatic shapeless/HMap.$anonfun$caseRel$1:(Lshapeless/HMap;Ljava/lang/Object;Ljava/lang/Object;)Ljava/lang/Object;
  ScalaInlineInfo: length = 0xD6 (unknown attribute)
   01 00 00 2A 01 59 01 5A 01 01 3F 01 40 00 01 33
   01 34 00 01 3A 01 3B 00 01 17 01 18 01 00 2A 01
   14 01 01 25 01 18 01 00 1A 01 22 01 01 1F 01 18
   01 01 1B 01 1C 01 00 63 00 5B 00 00 89 01 0E 00
   00 89 01 08 00 00 89 01 03 00 00 89 00 FD 00 00
   89 00 F7 00 00 89 00 F1 00 00 89 00 EB 00 00 89
   00 E5 00 00 89 00 DF 00 00 89 00 D9 00 00 89 00
   D3 00 00 89 00 CD 00 00 89 00 C7 00 00 89 00 C1
   00 00 89 00 BB 00 00 89 00 B5 00 00 89 00 B0 00
   00 89 00 AA 00 00 89 00 A4 00 00 89 00 9F 00 00
   89 00 99 00 00 89 00 90 00 00 89 00 8A 00 00 51
   00 52 00 00 80 00 81 00 01 45 01 46 00 00 5A 00
   5B 00 01 28 01 29 00 00 67 00 68 00 00 6E 00 6F
   00 00 75 00 76 00
  ScalaSig: length = 0x3 (unknown attribute)
   05 02 00
