Classfile /Users/mw/Projects/slang-braindump/.jar/jar8/assemble/slang-braindump/assemble/content/shapeless/InferProduct$.class
  Last modified May 29, 2022; size 1697 bytes
  SHA-256 checksum 2992117c53dfedf4c65a304a9b0785947bcc6f5d4648b3b60b22acb15d50f464
  Compiled from "lenses.scala"
public final class shapeless.InferProduct$ implements java.io.Serializable
  minor version: 0
  major version: 52
  flags: (0x0031) ACC_PUBLIC, ACC_FINAL, ACC_SUPER
  this_class: #2                          // shapeless/InferProduct$
  super_class: #4                         // java/lang/Object
  interfaces: 1, fields: 1, methods: 5, attributes: 4
Constant pool:
   #1 = Utf8               shapeless/InferProduct$
   #2 = Class              #1             // shapeless/InferProduct$
   #3 = Utf8               java/lang/Object
   #4 = Class              #3             // java/lang/Object
   #5 = Utf8               java/io/Serializable
   #6 = Class              #5             // java/io/Serializable
   #7 = Utf8               lenses.scala
   #8 = Utf8               shapeless/InferProduct$$anon$21
   #9 = Class              #8             // shapeless/InferProduct$$anon$21
  #10 = Utf8               shapeless/InferProduct$$anon$22
  #11 = Class              #10            // shapeless/InferProduct$$anon$22
  #12 = Utf8               MODULE$
  #13 = Utf8               Lshapeless/InferProduct$;
  #14 = Utf8               <clinit>
  #15 = Utf8               ()V
  #16 = Utf8               <init>
  #17 = NameAndType        #16:#15        // "<init>":()V
  #18 = Methodref          #2.#17         // shapeless/InferProduct$."<init>":()V
  #19 = NameAndType        #12:#13        // MODULE$:Lshapeless/InferProduct$;
  #20 = Fieldref           #2.#19         // shapeless/InferProduct$.MODULE$:Lshapeless/InferProduct$;
  #21 = Utf8               inferProduct1
  #22 = Utf8               (Lshapeless/LabelledGeneric;Lshapeless/ops/record/Selector;)Lshapeless/InferProduct;
  #23 = Utf8               <P:Ljava/lang/Object;R::Lshapeless/HList;T::Lshapeless/Coproduct;K:Ljava/lang/Object;>(Lshapeless/LabelledGeneric<TP;>;Lshapeless/ops/record/Selector<TR;TK;>;)Lshapeless/InferProduct<Lshapeless/$colon$plus$colon<TP;TT;>;TK;>;
  #24 = Utf8               gen
  #25 = Utf8               sel
  #26 = Methodref          #9.#17         // shapeless/InferProduct$$anon$21."<init>":()V
  #27 = Utf8               this
  #28 = Utf8               Lshapeless/LabelledGeneric;
  #29 = Utf8               Lshapeless/ops/record/Selector;
  #30 = Utf8               inferProduct2
  #31 = Utf8               (Lshapeless/InferProduct;)Lshapeless/InferProduct;
  #32 = Utf8               <H:Ljava/lang/Object;T::Lshapeless/Coproduct;K:Ljava/lang/Object;P:Ljava/lang/Object;>(Lshapeless/InferProduct<TT;TK;>;)Lshapeless/InferProduct<Lshapeless/$colon$plus$colon<TH;TT;>;TK;>;
  #33 = Utf8               it
  #34 = Methodref          #11.#17        // shapeless/InferProduct$$anon$22."<init>":()V
  #35 = Utf8               Lshapeless/InferProduct;
  #36 = Utf8               writeReplace
  #37 = Utf8               ()Ljava/lang/Object;
  #38 = Utf8               scala/runtime/ModuleSerializationProxy
  #39 = Class              #38            // scala/runtime/ModuleSerializationProxy
  #40 = Utf8               (Ljava/lang/Class;)V
  #41 = NameAndType        #16:#40        // "<init>":(Ljava/lang/Class;)V
  #42 = Methodref          #39.#41        // scala/runtime/ModuleSerializationProxy."<init>":(Ljava/lang/Class;)V
  #43 = Methodref          #4.#17         // java/lang/Object."<init>":()V
  #44 = Utf8               Code
  #45 = Utf8               LineNumberTable
  #46 = Utf8               LocalVariableTable
  #47 = Utf8               Signature
  #48 = Utf8               MethodParameters
  #49 = Utf8               InnerClasses
  #50 = Utf8               SourceFile
  #51 = Utf8               ScalaInlineInfo
  #52 = Utf8               Scala
{
  public static final shapeless.InferProduct$ MODULE$;
    descriptor: Lshapeless/InferProduct$;
    flags: (0x0019) ACC_PUBLIC, ACC_STATIC, ACC_FINAL

  public static {};
    descriptor: ()V
    flags: (0x0009) ACC_PUBLIC, ACC_STATIC
    Code:
      stack=2, locals=0, args_size=0
         0: new           #2                  // class shapeless/InferProduct$
         3: dup
         4: invokespecial #18                 // Method "<init>":()V
         7: putstatic     #20                 // Field MODULE$:Lshapeless/InferProduct$;
        10: return
      LineNumberTable:
        line 291: 0

  public <P extends java.lang.Object, R extends shapeless.HList, T extends shapeless.Coproduct, K extends java.lang.Object> shapeless.InferProduct<shapeless.$colon$plus$colon<P, T>, K> inferProduct1(shapeless.LabelledGeneric<P>, shapeless.ops.record.Selector<R, K>);
    descriptor: (Lshapeless/LabelledGeneric;Lshapeless/ops/record/Selector;)Lshapeless/InferProduct;
    flags: (0x0001) ACC_PUBLIC
    Code:
      stack=2, locals=3, args_size=3
         0: new           #9                  // class shapeless/InferProduct$$anon$21
         3: dup
         4: invokespecial #26                 // Method shapeless/InferProduct$$anon$21."<init>":()V
         7: areturn
      LineNumberTable:
        line 296: 0
      LocalVariableTable:
        Start  Length  Slot  Name   Signature
            0       8     0  this   Lshapeless/InferProduct$;
            0       8     1   gen   Lshapeless/LabelledGeneric;
            0       8     2   sel   Lshapeless/ops/record/Selector;
    Signature: #23                          // <P:Ljava/lang/Object;R::Lshapeless/HList;T::Lshapeless/Coproduct;K:Ljava/lang/Object;>(Lshapeless/LabelledGeneric<TP;>;Lshapeless/ops/record/Selector<TR;TK;>;)Lshapeless/InferProduct<Lshapeless/$colon$plus$colon<TP;TT;>;TK;>;
    MethodParameters:
      Name                           Flags
      gen                            final
      sel                            final

  public <H extends java.lang.Object, T extends shapeless.Coproduct, K extends java.lang.Object, P extends java.lang.Object> shapeless.InferProduct<shapeless.$colon$plus$colon<H, T>, K> inferProduct2(shapeless.InferProduct<T, K>);
    descriptor: (Lshapeless/InferProduct;)Lshapeless/InferProduct;
    flags: (0x0001) ACC_PUBLIC
    Code:
      stack=2, locals=2, args_size=2
         0: new           #11                 // class shapeless/InferProduct$$anon$22
         3: dup
         4: invokespecial #34                 // Method shapeless/InferProduct$$anon$22."<init>":()V
         7: areturn
      LineNumberTable:
        line 301: 0
      LocalVariableTable:
        Start  Length  Slot  Name   Signature
            0       8     0  this   Lshapeless/InferProduct$;
            0       8     1    it   Lshapeless/InferProduct;
    Signature: #32                          // <H:Ljava/lang/Object;T::Lshapeless/Coproduct;K:Ljava/lang/Object;P:Ljava/lang/Object;>(Lshapeless/InferProduct<TT;TK;>;)Lshapeless/InferProduct<Lshapeless/$colon$plus$colon<TH;TT;>;TK;>;
    MethodParameters:
      Name                           Flags
      it                             final

  private java.lang.Object writeReplace();
    descriptor: ()Ljava/lang/Object;
    flags: (0x0002) ACC_PRIVATE
    Code:
      stack=3, locals=1, args_size=1
         0: new           #39                 // class scala/runtime/ModuleSerializationProxy
         3: dup
         4: ldc           #2                  // class shapeless/InferProduct$
         6: invokespecial #42                 // Method scala/runtime/ModuleSerializationProxy."<init>":(Ljava/lang/Class;)V
         9: areturn
      LineNumberTable:
        line 291: 0
      LocalVariableTable:
        Start  Length  Slot  Name   Signature
            0      10     0  this   Lshapeless/InferProduct$;

  private shapeless.InferProduct$();
    descriptor: ()V
    flags: (0x0002) ACC_PRIVATE
    Code:
      stack=1, locals=1, args_size=1
         0: aload_0
         1: invokespecial #43                 // Method java/lang/Object."<init>":()V
         4: return
      LineNumberTable:
        line 306: 0
        line 291: 4
      LocalVariableTable:
        Start  Length  Slot  Name   Signature
            0       5     0  this   Lshapeless/InferProduct$;
}
InnerClasses:
  public final #9;                        // class shapeless/InferProduct$$anon$21
  public final #11;                       // class shapeless/InferProduct$$anon$22
SourceFile: "lenses.scala"
  ScalaInlineInfo: length = 0x18 (unknown attribute)
   01 01 00 04 00 10 00 0F 01 00 15 00 16 01 00 1E
   00 1F 01 00 24 00 25 01
  Scala: length = 0x0 (unknown attribute)

