Classfile /Users/mw/Projects/slang-braindump/.jar/jar8/assemble/slang-braindump/assemble/content/shapeless/IsDistinctConstraint$.class
  Last modified May 29, 2022; size 1797 bytes
  SHA-256 checksum 61456515f5dfe3be6e8cf7c6c857ae60ef5029dc65681bc533d904977fa7b7f3
  Compiled from "hlistconstraints.scala"
public final class shapeless.IsDistinctConstraint$ implements java.io.Serializable
  minor version: 0
  major version: 52
  flags: (0x0031) ACC_PUBLIC, ACC_FINAL, ACC_SUPER
  this_class: #2                          // shapeless/IsDistinctConstraint$
  super_class: #4                         // java/lang/Object
  interfaces: 1, fields: 1, methods: 6, attributes: 4
Constant pool:
   #1 = Utf8               shapeless/IsDistinctConstraint$
   #2 = Class              #1             // shapeless/IsDistinctConstraint$
   #3 = Utf8               java/lang/Object
   #4 = Class              #3             // java/lang/Object
   #5 = Utf8               java/io/Serializable
   #6 = Class              #5             // java/io/Serializable
   #7 = Utf8               hlistconstraints.scala
   #8 = Utf8               shapeless/IsDistinctConstraint$$anon$16
   #9 = Class              #8             // shapeless/IsDistinctConstraint$$anon$16
  #10 = Utf8               shapeless/IsDistinctConstraint$$anon$17
  #11 = Class              #10            // shapeless/IsDistinctConstraint$$anon$17
  #12 = Utf8               MODULE$
  #13 = Utf8               Lshapeless/IsDistinctConstraint$;
  #14 = Utf8               <clinit>
  #15 = Utf8               ()V
  #16 = Utf8               <init>
  #17 = NameAndType        #16:#15        // "<init>":()V
  #18 = Methodref          #2.#17         // shapeless/IsDistinctConstraint$."<init>":()V
  #19 = NameAndType        #12:#13        // MODULE$:Lshapeless/IsDistinctConstraint$;
  #20 = Fieldref           #2.#19         // shapeless/IsDistinctConstraint$.MODULE$:Lshapeless/IsDistinctConstraint$;
  #21 = Utf8               apply
  #22 = Utf8               (Lshapeless/IsDistinctConstraint;)Lshapeless/IsDistinctConstraint;
  #23 = Utf8               <L::Lshapeless/HList;>(Lshapeless/IsDistinctConstraint<TL;>;)Lshapeless/IsDistinctConstraint<TL;>;
  #24 = Utf8               idc
  #25 = Utf8               this
  #26 = Utf8               Lshapeless/IsDistinctConstraint;
  #27 = Utf8               hnilIsDistinct
  #28 = Utf8               ()Lshapeless/IsDistinctConstraint;
  #29 = Utf8               ()Lshapeless/IsDistinctConstraint<Lshapeless/HNil;>;
  #30 = Methodref          #9.#17         // shapeless/IsDistinctConstraint$$anon$16."<init>":()V
  #31 = Utf8               hlistIsDistinct
  #32 = Utf8               (Lshapeless/IsDistinctConstraint;Lshapeless/NotContainsConstraint;)Lshapeless/IsDistinctConstraint;
  #33 = Utf8               <H:Ljava/lang/Object;T::Lshapeless/HList;>(Lshapeless/IsDistinctConstraint<TT;>;Lshapeless/NotContainsConstraint<TT;TH;>;)Lshapeless/IsDistinctConstraint<Lshapeless/$colon$colon<TH;TT;>;>;
  #34 = Utf8               d
  #35 = Utf8               nc
  #36 = Methodref          #11.#17        // shapeless/IsDistinctConstraint$$anon$17."<init>":()V
  #37 = Utf8               Lshapeless/NotContainsConstraint;
  #38 = Utf8               writeReplace
  #39 = Utf8               ()Ljava/lang/Object;
  #40 = Utf8               scala/runtime/ModuleSerializationProxy
  #41 = Class              #40            // scala/runtime/ModuleSerializationProxy
  #42 = Utf8               (Ljava/lang/Class;)V
  #43 = NameAndType        #16:#42        // "<init>":(Ljava/lang/Class;)V
  #44 = Methodref          #41.#43        // scala/runtime/ModuleSerializationProxy."<init>":(Ljava/lang/Class;)V
  #45 = Methodref          #4.#17         // java/lang/Object."<init>":()V
  #46 = Utf8               Code
  #47 = Utf8               LineNumberTable
  #48 = Utf8               LocalVariableTable
  #49 = Utf8               Signature
  #50 = Utf8               MethodParameters
  #51 = Utf8               InnerClasses
  #52 = Utf8               SourceFile
  #53 = Utf8               ScalaInlineInfo
  #54 = Utf8               Scala
{
  public static final shapeless.IsDistinctConstraint$ MODULE$;
    descriptor: Lshapeless/IsDistinctConstraint$;
    flags: (0x0019) ACC_PUBLIC, ACC_STATIC, ACC_FINAL

  public static {};
    descriptor: ()V
    flags: (0x0009) ACC_PUBLIC, ACC_STATIC
    Code:
      stack=2, locals=0, args_size=0
         0: new           #2                  // class shapeless/IsDistinctConstraint$
         3: dup
         4: invokespecial #18                 // Method "<init>":()V
         7: putstatic     #20                 // Field MODULE$:Lshapeless/IsDistinctConstraint$;
        10: return
      LineNumberTable:
        line 150: 0

  public <L extends shapeless.HList> shapeless.IsDistinctConstraint<L> apply(shapeless.IsDistinctConstraint<L>);
    descriptor: (Lshapeless/IsDistinctConstraint;)Lshapeless/IsDistinctConstraint;
    flags: (0x0001) ACC_PUBLIC
    Code:
      stack=1, locals=2, args_size=2
         0: aload_1
         1: areturn
      LineNumberTable:
        line 152: 0
      LocalVariableTable:
        Start  Length  Slot  Name   Signature
            0       2     0  this   Lshapeless/IsDistinctConstraint$;
            0       2     1   idc   Lshapeless/IsDistinctConstraint;
    Signature: #23                          // <L::Lshapeless/HList;>(Lshapeless/IsDistinctConstraint<TL;>;)Lshapeless/IsDistinctConstraint<TL;>;
    MethodParameters:
      Name                           Flags
      idc                            final

  public shapeless.IsDistinctConstraint<shapeless.HNil> hnilIsDistinct();
    descriptor: ()Lshapeless/IsDistinctConstraint;
    flags: (0x0001) ACC_PUBLIC
    Code:
      stack=2, locals=1, args_size=1
         0: new           #9                  // class shapeless/IsDistinctConstraint$$anon$16
         3: dup
         4: invokespecial #30                 // Method shapeless/IsDistinctConstraint$$anon$16."<init>":()V
         7: areturn
      LineNumberTable:
        line 154: 0
      LocalVariableTable:
        Start  Length  Slot  Name   Signature
            0       8     0  this   Lshapeless/IsDistinctConstraint$;
    Signature: #29                          // ()Lshapeless/IsDistinctConstraint<Lshapeless/HNil;>;

  public <H extends java.lang.Object, T extends shapeless.HList> shapeless.IsDistinctConstraint<shapeless.$colon$colon<H, T>> hlistIsDistinct(shapeless.IsDistinctConstraint<T>, shapeless.NotContainsConstraint<T, H>);
    descriptor: (Lshapeless/IsDistinctConstraint;Lshapeless/NotContainsConstraint;)Lshapeless/IsDistinctConstraint;
    flags: (0x0001) ACC_PUBLIC
    Code:
      stack=2, locals=3, args_size=3
         0: new           #11                 // class shapeless/IsDistinctConstraint$$anon$17
         3: dup
         4: invokespecial #36                 // Method shapeless/IsDistinctConstraint$$anon$17."<init>":()V
         7: areturn
      LineNumberTable:
        line 157: 0
      LocalVariableTable:
        Start  Length  Slot  Name   Signature
            0       8     0  this   Lshapeless/IsDistinctConstraint$;
            0       8     1     d   Lshapeless/IsDistinctConstraint;
            0       8     2    nc   Lshapeless/NotContainsConstraint;
    Signature: #33                          // <H:Ljava/lang/Object;T::Lshapeless/HList;>(Lshapeless/IsDistinctConstraint<TT;>;Lshapeless/NotContainsConstraint<TT;TH;>;)Lshapeless/IsDistinctConstraint<Lshapeless/$colon$colon<TH;TT;>;>;
    MethodParameters:
      Name                           Flags
      d                              final
      nc                             final

  private java.lang.Object writeReplace();
    descriptor: ()Ljava/lang/Object;
    flags: (0x0002) ACC_PRIVATE
    Code:
      stack=3, locals=1, args_size=1
         0: new           #41                 // class scala/runtime/ModuleSerializationProxy
         3: dup
         4: ldc           #2                  // class shapeless/IsDistinctConstraint$
         6: invokespecial #44                 // Method scala/runtime/ModuleSerializationProxy."<init>":(Ljava/lang/Class;)V
         9: areturn
      LineNumberTable:
        line 150: 0
      LocalVariableTable:
        Start  Length  Slot  Name   Signature
            0      10     0  this   Lshapeless/IsDistinctConstraint$;

  private shapeless.IsDistinctConstraint$();
    descriptor: ()V
    flags: (0x0002) ACC_PRIVATE
    Code:
      stack=1, locals=1, args_size=1
         0: aload_0
         1: invokespecial #45                 // Method java/lang/Object."<init>":()V
         4: return
      LineNumberTable:
        line 158: 0
        line 150: 4
      LocalVariableTable:
        Start  Length  Slot  Name   Signature
            0       5     0  this   Lshapeless/IsDistinctConstraint$;
}
InnerClasses:
  public final #9;                        // class shapeless/IsDistinctConstraint$$anon$16
  public final #11;                       // class shapeless/IsDistinctConstraint$$anon$17
SourceFile: "hlistconstraints.scala"
  ScalaInlineInfo: length = 0x1D (unknown attribute)
   01 01 00 05 00 10 00 0F 01 00 15 00 16 01 00 1F
   00 20 01 00 1B 00 1C 01 00 26 00 27 01
  Scala: length = 0x0 (unknown attribute)

