Classfile /Users/mw/Projects/slang-braindump/.jar/jar8/assemble/slang-braindump/assemble/content/shapeless/IsHCons1.class
  Last modified May 29, 2022; size 6337 bytes
  SHA-256 checksum f330c1568ffd1ae22b1042749f80542aea914d71328344235ccb0f859b2901fa
  Compiled from "generic1.scala"
public interface shapeless.IsHCons1<L extends java.lang.Object, FH extends java.lang.Object, FT extends java.lang.Object> extends java.io.Serializable
  minor version: 0
  major version: 52
  flags: (0x0601) ACC_PUBLIC, ACC_INTERFACE, ACC_ABSTRACT
  this_class: #2                          // shapeless/IsHCons1
  super_class: #5                         // java/lang/Object
  interfaces: 1, fields: 0, methods: 9, attributes: 5
Constant pool:
   #1 = Utf8               shapeless/IsHCons1
   #2 = Class              #1             // shapeless/IsHCons1
   #3 = Utf8               <L:Ljava/lang/Object;FH:Ljava/lang/Object;FT:Ljava/lang/Object;>Ljava/lang/Object;Ljava/io/Serializable;
   #4 = Utf8               java/lang/Object
   #5 = Class              #4             // java/lang/Object
   #6 = Utf8               java/io/Serializable
   #7 = Class              #6             // java/io/Serializable
   #8 = Utf8               generic1.scala
   #9 = Utf8               Lscala/reflect/ScalaSignature;
  #10 = Utf8               bytes
  #11 = Utf8               \u0006\u0005\u0011\u0015gaB\n\u0015!\u0003\r\ta\u0006\u0005\u0006W\u0001!\t\u0001\f\u0003\u0006a\u0001\u0011\t!\r\u0003\u0006w\u0001\u0011\t\u0001\u0010\u0005\t\u0007\u0002A)\u0019!C\u0001\t\"Aq\n\u0001EC\u0002\u0013\u0005\u0001\u000bC\u0003Z\u0001\u0019\u0005!\fC\u0003l\u0001\u0019\u0005A\u000eC\u0003w\u0001\u0019\u0005A\tC\u0003x\u0001\u0019\u0005\u0001kB\u0003y)!\u0005\u0011PB\u0003\u0014)!\u0005!\u0010C\u0004\u0002\f-!\t!!\u0004\u0006\r\u0005=1\u0002AA\t\u0011!\t\tg\u0003B\u0005\u0004\u0005\r\u0004\u0002\u0003BG\u0017\t%\u0019Aa$\t\u0011\r\u00153B!C\u0002\u0007\u000fB\u0001b!@\f\u0005\u0013\r1q \u0005\n\tk[\u0011\u0011!C\u0005\to\u0013\u0001\"S:I\u0007>t7/\r\u0006\u0002+\u0005I1\u000f[1qK2,7o]\u0002\u0001+\u0011ARl\u0012*\u0014\u0007\u0001Ir\u0004\u0005\u0002\u001b;5\t1DC\u0001\u001d\u0003\u0015\u00198-\u00197b\u0013\tq2D\u0001\u0004B]f\u0014VM\u001a\t\u0003A!r!!\t\u0014\u000f\u0005\t*S\"A\u0012\u000b\u0005\u00112\u0012A\u0002\u001fs_>$h(C\u0001\u001d\u0013\t93$A\u0004qC\u000e\\\u0017mZ3\n\u0005%R#\u0001D*fe&\fG.\u001b>bE2,\'BA\u0014\u001c\u0003\u0019!\u0013N\\5uIQ\tQ\u0006\u0005\u0002\u001b]%\u0011qf\u0007\u0002\u0005+:LGOA\u0001I+\t\u0011\u0014(\u0005\u00024mA\u0011!\u0004N\u0005\u0003km\u0011qAT8uQ&tw\r\u0005\u0002\u001bo%\u0011\u0001h\u0007\u0002\u0004\u0003:LH!\u0002\u001e\u0003\u0005\u0004\u0011$!A0\u0003\u0003Q+\"!\u0010\"\u0012\u0005Mr\u0004CA A\u001b\u0005!\u0012BA!\u0015\u0005\u0015AE*[:u\t\u0015Q4A1\u00013\u0003\t1\u0007.F\u0001F!\r1u)\u0014\u0007\u0001\t\u0015A\u0005A1\u0001J\u0005\t1\u0005*\u0006\u00023\u0015\u0012)!h\u0012b\u0001\u0017V\u0011!\u0007\u0014\u0003\u0006u)\u0013\rA\r\t\u0003\u001d\ni\u0011\u0001A\u0001\u0003MR,\u0012!\u0015\t\u0004\rJCF!B*\u0001\u0005\u0004!&A\u0001$U+\t\u0011T\u000bB\u0003;%\n\u0007a+\u0006\u00023/\u0012)!(\u0016b\u0001eA\u0011ajA\u0001\u0005a\u0006\u001c7.\u0006\u0002\\ER\u0011A\f\u001a\t\u0004\rv\u000bG!\u00020\u0001\u0005\u0004y&!\u0001\'\u0016\u0005I\u0002G!\u0002\u001e^\u0005\u0004\u0011\u0004C\u0001$c\t\u0015\u0019gA1\u00013\u0005\u0005\t\u0005\"B3\u0007\u0001\u00041\u0017!A;\u0011\ti9\u0017N[\u0005\u0003Qn\u0011a\u0001V;qY\u0016\u0014\u0004c\u0001(\u0003CB\u0019ajA1\u0002\rUt\u0007/Y2l+\ti\u0017\u000f\u0006\u0002ogB!!dZ8s!\rq%\u0001\u001d\t\u0003\rF$QaY\u0004C\u0002I\u00022AT\u0002q\u0011\u0015!x\u00011\u0001v\u0003\u0005\u0001\bc\u0001$^a\u0006)Qn\u001b$iQ\u0006)Qn\u001b$ui\u0006A\u0011j\u001d%D_:\u001c\u0018\u0007\u0005\u0002@\u0017M!1\"G>\u007f!\tyD0\u0003\u0002~)\tI\u0011j\u001d%D_:\u001c\u0018\u0007\r\t\u0004\u007f\u0006%QBAA\u0001\u0015\u0011\t\u0019!!\u0002\u0002\u0005%|\'BAA\u0004\u0003\u0011Q\u0017M^1\n\u0007%\n\t!\u0001\u0004=S:LGO\u0010\u000b\u0002s\n\u0019\u0011)\u001e=\u0016\u0019\u0005M\u0011QDA\u0013\u0003c\t\t%!\u0016\u0013\t\u0005U\u0011\u0011\u0004\u0004\u0007\u0003/Y\u0001!a\u0005\u0003\u0019q\u0012XMZ5oK6,g\u000e\u001e \u0011\u0011}\u0002\u00111DA\u0012\u0003_\u00012ARA\u000f\t\u0019qVB1\u0001\u0002 U\u0019!\'!\t\u0005\ri\niB1\u00013!\r1\u0015Q\u0005\u0003\u0007\u00116\u0011\r!a\n\u0016\u0007I\nI\u0003B\u0004;\u0003K\u0011\r!a\u000b\u0016\u0007I\ni\u0003\u0002\u0004;\u0003S\u0011\rA\r\t\u0004\r\u0006EBAB*\u000e\u0005\u0004\t\u0019$F\u00023\u0003k!qAOA\u0019\u0005\u0004\t9$F\u00023\u0003s!aAOA\u001b\u0005\u0004\u0011TA\u0002\u0019\u0002\u0016\u0001\ni$\u0006\u0003\u0002@\u0005-\u0003#\u0002$\u0002B\u0005%CaBA\"\u001b\t\u0007\u0011Q\t\u0002\u0003\u0011B*2AMA$\t\u0019Q\u0014\u0011\tb\u0001eA\u0019a)a\u0013\u0005\u000f\u00055\u00131\bb\u0001e\t\tA/\u0002\u0004<\u0003+\u0001\u0013\u0011K\u000b\u0005\u0003\'\ny\u0006E\u0003G\u0003+\ni\u0006B\u0004\u0002X5\u0011\r!!\u0017\u0003\u0005Q\u0003TcA\u001f\u0002\\\u00111!(!\u0016C\u0002I\u00022ARA0\t\u001d\ti%a\u0014C\u0002I\n1\"\\6Jg\"\u001buN\\:2aUQ\u0011QMA6\u0003k\n\u0019+!.\u0016\u0005\u0005\u001d\u0004\u0003C \u0001\u0003S\n\t(a-\u0011\u0007\u0019\u000bY\u0007\u0002\u0004_\u001d\t\u0007\u0011QN\u000b\u0004e\u0005=DA\u0002\u001e\u0002l\t\u0007!\'\u0006\u0003\u0002t\u0005\u001d\u0005c\u0002$\u0002v\u0005\u0015\u0015\u0011\u0017\u0003\u0007\u0011:\u0011\r!a\u001e\u0016\u000bI\nI(a \u0005\u000fi\n)H1\u0001\u0002|U\u0019!\'! \u0005\ri\nIH1\u00013\t\u001dQ\u0014Q\u000fb\u0001\u0003\u0003+2AMAB\t\u0019Q\u0014q\u0010b\u0001eA\u0019a)a\"\u0005\u0011\u00055\u0013\u0011\u0012b\u0001\u0003[Cq!a#\u0002\u000e\u0002\tY+\u0001\u0006=Y>\u001c\u0017\r\u001c\u0011Ox{*q!a$\u0002\u0012\u0002\t)J\u0001\u0002Ox\u001b1\u0011qC\u0006\u0001\u0003\'\u00132!!%\u001a+\u0011\t9*a\'\u0011\u000f\u0019\u000b)(!\'\u0002\"B\u0019a)a\'\u0005\u0011\u00055\u0013Q\u0012b\u0001\u0003;+2AMAP\t\u0019Q\u00141\u0014b\u0001eA\u0019a)a)\u0005\u000f\u0005\u0015fB1\u0001\u0002(\n\tQ+F\u00023\u0003S#aAOAR\u0005\u0004\u00114\u0002A\u000b\u0004e\u0005=FA\u0002\u001e\u0002\b\n\u0007!\u0007E\u0002G\u0003G\u00032ARA[\t\u0019\u0019fB1\u0001\u00028V\u0019!\'!/\u0005\u000fi\n)L1\u0001\u0002<V\u0019!\'!0\u0005\ri\nIL1\u00013Q\u0015q\u0011\u0011YAk!\u0011\t\u0019-!5\u000e\u0005\u0005\u0015\'\u0002BAd\u0003\u0013\f\u0001\"\u001b8uKJt\u0017\r\u001c\u0006\u0005\u0003\u0017\fi-\u0001\u0004nC\u000e\u0014xn\u001d\u0006\u0004\u0003\u001f\\\u0012a\u0002:fM2,7\r^\u0005\u0005\u0003\'\f)MA\u0005nC\u000e\u0014x.S7qYFZa$a+\u0002X\n\r$q\rBEcEy\u00121VAm\u0003;\fy/a@\u0003\u0010\t\u0005\"1G\u0019\u0007I\u0005-f#a7\u0002\u000b5\f7M]82\u000fY\tY+a8\u0002hF*Q%!9\u0002d>\u0011\u00111]\u0011\u0003\u0003K\f1\"\\1de>,enZ5oKF*Q%!;\u0002l>\u0011\u00111^\u0011\u0003\u0003[\fQE^\u001c/a\u0001B\u0013.\u001c9mK6,g\u000e^3eA%t\u0007eU2bY\u0006\u0004#GL\u00192]AjS\nO\u00152\u000fY\tY+!=\u0002zF*Q%a=\u0002v>\u0011\u0011Q_\u0011\u0003\u0003o\f\u0001\"[:Ck:$G.Z\u0019\u0006K\u0005m\u0018Q`\b\u0003\u0003{L\u0012!A\u0019\b-\u0005-&\u0011\u0001B\u0005c\u0015)#1\u0001B\u0003\u001f\t\u0011)!\t\u0002\u0003\b\u0005Q\u0011n\u001d\"mC\u000e\\\'m\u001c=2\u000b\u0015\u0012YA!\u0004\u0010\u0005\t5\u0011$\u0001\u00012\u000fY\tYK!\u0005\u0003\u001aE*QEa\u0005\u0003\u0016=\u0011!QC\u0011\u0003\u0005/\t\u0011b\u00197bgNt\u0015-\\32\u000b\u0015\u0012YB!\b\u0010\u0005\tu\u0011E\u0001B\u0010\u0003a\u0019\b.\u00199fY\u0016\u001c8OL%t\u0011\u000e{gn]\u0019NC\u000e\u0014xn]\u0019\b-\u0005-&1\u0005B\u0016c\u0015)#Q\u0005B\u0014\u001f\t\u00119#\t\u0002\u0003*\u0005QQ.\u001a;i_\u0012t\u0015-\\32\u000b\u0015\u0012iCa\f\u0010\u0005\t=\u0012E\u0001B\u0019\u00039i7.S:I\u0007>t7/M%na2\ftAFAV\u0005k\u0011i$M\u0003&\u0005o\u0011Id\u0004\u0002\u0003:\u0005\u0012!1H\u0001\ng&<g.\u0019;ve\u0016\ftaHAV\u0005\u007f\u0011i%M\u0004%\u0003W\u0013\tEa\u0011\n\t\t\r#QI\u0001\u0005\u0019&\u001cHO\u0003\u0003\u0003H\t%\u0013!C5n[V$\u0018M\u00197f\u0015\r\u0011YeG\u0001\u000bG>dG.Z2uS>t\u0017gC\u0010\u0002,\n=#\u0011\u000bB,\u0005;\nt\u0001JAV\u0005\u0003\u0012\u0019%M\u0003&\u0005\'\u0012)f\u0004\u0002\u0003Vu\t\u0001!M\u0003&\u00053\u0012Yf\u0004\u0002\u0003\\u\t\u0011!M\u0003&\u0005?\u0012\tg\u0004\u0002\u0003bu\t!!M\u0002\'\u0005K\u00022ARA6c\r1#\u0011N\u000b\u0005\u0005W\u0012y\u0007E\u0004G\u0003k\u0012i\'!)\u0011\u0007\u0019\u0013y\u0007\u0002\u0005\u0002N\tE$\u0019\u0001BC\u0011\u001d\tYIa\u001d\u0001\u0003W+q!a$\u0003v\u0001\u0011IH\u0002\u0004\u0002\u0018-\u0001!q\u000f\n\u0004\u0005kJR\u0003\u0002B>\u0005\u007f\u0002rARA;\u0005{\n\t\u000bE\u0002G\u0005\u007f\"\u0001\"!\u0014\u0003t\t\u0007!\u0011Q\u000b\u0004e\t\rEA\u0002\u001e\u0003\u0000\t\u0007!\'F\u00023\u0005\u000f#aA\u000fB8\u0005\u0004\u0011\u0014g\u0001\u0014\u0003\fB\u0019a)!.\u0002\u00175\\\u0017j\u001d%D_:\u001c\u0018\'M\u000b\u000b\u0005#\u00139J!)\u00034\neWC\u0001BJ!!y\u0004A!&\u0003\u001e\n]\u0007c\u0001$\u0003\u0018\u00121al\u0004b\u0001\u00053+2A\rBN\t\u0019Q$q\u0013b\u0001eU!!q\u0014B^!\u001d1%\u0011\u0015BY\u0005s#a\u0001S\bC\u0002\t\rV#\u0002\u001a\u0003&\n-Fa\u0002\u001e\u0003\"\n\u0007!qU\u000b\u0004e\t%FA\u0002\u001e\u0003&\n\u0007!\u0007B\u0004;\u0005C\u0013\rA!,\u0016\u0007I\u0012y\u000b\u0002\u0004;\u0005W\u0013\rA\r\t\u0004\r\nMFaBAS\u001f\t\u0007!QW\u000b\u0004e\t]FA\u0002\u001e\u00034\n\u0007!\u0007E\u0002G\u0005w#\u0001\"!\u0014\u0003>\n\u0007!1\u001b\u0005\b\u0003\u0017\u0013y\fAAV\u000b\u001d\tyI!1\u0001\u0005\u000b4a!a\u0006\f\u0001\t\r\'c\u0001Ba3U!!q\u0019Bg!\u001d1%\u0011\u0015Be\u0005\u0017\u00042A\u0012BZ!\r1%Q\u001a\u0003\t\u0003\u001b\u0012yL1\u0001\u0003PV\u0019!G!5\u0005\ri\u0012iM1\u00013+\r\u0011$Q\u001b\u0003\u0007u\tm&\u0019\u0001\u001a\u0011\u0007\u0019\u0013I\u000e\u0002\u0004T\u001f\t\u0007!1\\\u000b\u0004e\tuGa\u0002\u001e\u0003Z\n\u0007!q\\\u000b\u0004e\t\u0005HA\u0002\u001e\u0003^\n\u0007!\u0007K\u0003\u0010\u0003\u0003\u0014)/M\u0006\u001f\u0003W\u00139oa\u0007\u0004 \r\u0005\u0013\'E\u0010\u0002,\n%(1\u001eBy\u0005o\u0014ipa\u0001\u0004\nE2A%a+\u0017\u00037\ftAFAV\u0005[\u0014y/M\u0003&\u0003C\f\u0019/M\u0003&\u0003S\fY/M\u0004\u0017\u0003W\u0013\u0019P!>2\u000b\u0015\n\u00190!>2\u000b\u0015\nY0!@2\u000fY\tYK!?\u0003|F*QEa\u0001\u0003\u0006E*QEa\u0003\u0003\u000eE:a#a+\u0003\u0000\u000e\u0005\u0011\'B\u0013\u0003\u0014\tU\u0011\'B\u0013\u0003\u001c\tu\u0011g\u0002\f\u0002,\u000e\u00151qA\u0019\u0006K\t\u0015\"qE\u0019\u0006K\t5\"qF\u0019\b-\u0005-61BB\u0007c\u0015)#q\u0007B\u001dc\u001dy\u00121VB\b\u0007#\tt\u0001JAV\u0005\u0003\u0012\u0019%M\u0006 \u0003W\u001b\u0019b!\u0006\u0004\u0018\re\u0011g\u0002\u0013\u0002,\n\u0005#1I\u0019\u0006K\tM#QK\u0019\u0006K\te#1L\u0019\u0006K\t}#\u0011M\u0019\u0004M\ru\u0001c\u0001$\u0003\u0018F\u001aae!\t\u0016\t\r\r2q\u0005\t\b\r\n\u0005&\u0011ZB\u0013!\r15q\u0005\u0003\t\u0003\u001b\u001aIC1\u0001\u0004>!9\u00111RB\u0016\u0001\u0005-VaBAH\u0007[\u00011\u0011\u0007\u0004\u0007\u0003/Y\u0001aa\f\u0013\u0007\r5\u0012$\u0006\u0003\u00044\r]\u0002c\u0002$\u0003\"\n%7Q\u0007\t\u0004\r\u000e]B\u0001CA\'\u0007W\u0011\ra!\u000f\u0016\u0007I\u001aY\u0004\u0002\u0004;\u0007o\u0011\rAM\u000b\u0004e\r}BA\u0002\u001e\u0004(\t\u0007!\'M\u0002\'\u0007\u0007\u00022A\u0012Bm\u0003-i7.S:I\u0007>t7/\r\u001a\u0016\u0015\r%3qJB,\u0007K\u001ay)\u0006\u0002\u0004LAAq\bAB\'\u0007+\u001a\t\u0007E\u0002G\u0007\u001f\"aA\u0018\tC\u0002\rESc\u0001\u001a\u0004T\u00111!ha\u0014C\u0002I\u00022ARB,\t\u0019A\u0005C1\u0001\u0004ZU\u0019!ga\u0017\u0005\u000fi\u001a9F1\u0001\u0004^U\u0019!ga\u0018\u0005\ri\u001aYF1\u00013+\u0011\u0019\u0019ga\u001e\u0011\u000f\u0019\u001b)g!\u001e\u0004\u001a\u001211\u000b\u0005b\u0001\u0007O*RAMB5\u0007_\"qAOB3\u0005\u0004\u0019Y\'F\u00023\u0007[\"aAOB5\u0005\u0004\u0011Da\u0002\u001e\u0004f\t\u00071\u0011O\u000b\u0004e\rMDA\u0002\u001e\u0004p\t\u0007!\u0007E\u0002G\u0007o\"\u0001\"!\u0014\u0004z\t\u00071Q\u0013\u0005\b\u0003\u0017\u001bY\bAAV\u000b\u001d\tyi! \u0001\u0007\u00033a!a\u0006\f\u0001\r}$cAB?3U!11QBD!\u001d15QMBC\u0007\u001b\u00032ARBD\t!\tiea\u001fC\u0002\r%Uc\u0001\u001a\u0004\f\u00121!ha\"C\u0002I\u00022ARBH\t\u001d\t)\u000b\u0005b\u0001\u0007#+2AMBJ\t\u0019Q4q\u0012b\u0001eU\u0019!ga&\u0005\ri\u001a9H1\u00013!\r15q\u0012\u0015\u0006!\u0005\u00057QT\u0019\f=\u0005-6qTBj\u0007/\u001cY.M\t \u0003W\u001b\tka)\u0004*\u000e=6QWB^\u0007\u0003\fd\u0001JAV-\u0005m\u0017g\u0002\f\u0002,\u000e\u00156qU\u0019\u0006K\u0005\u0005\u00181]\u0019\u0006K\u0005%\u00181^\u0019\b-\u0005-61VBWc\u0015)\u00131_A{c\u0015)\u00131`A\u007fc\u001d1\u00121VBY\u0007g\u000bT!\nB\u0002\u0005\u000b\tT!\nB\u0006\u0005\u001b\ttAFAV\u0007o\u001bI,M\u0003&\u0005\'\u0011)\"M\u0003&\u00057\u0011i\"M\u0004\u0017\u0003W\u001bila02\u000b\u0015\u0012)Ca\n2\u000b\u0015\u0012iCa\f2\u000fY\tYka1\u0004FF*QEa\u000e\u0003:E:q$a+\u0004H\u000e%\u0017g\u0002\u0013\u0002,\n\u0005#1I\u0019\f?\u0005-61ZBg\u0007\u001f\u001c\t.M\u0004%\u0003W\u0013\tEa\u00112\u000b\u0015\u0012\u0019F!\u00162\u000b\u0015\u0012IFa\u00172\u000b\u0015\u0012yF!\u00192\u0007\u0019\u001a)\u000eE\u0002G\u0007\u001f\n4AJBm!\r15qK\u0019\u0004M\ruW\u0003BBp\u0007G\u0004rARB3\u0007C\u001ci\tE\u0002G\u0007G$\u0001\"!\u0014\u0004f\n\u00071\u0011 \u0005\b\u0003\u0017\u001b9\u000fAAV\u000b\u001d\tyi!;\u0001\u0007[4a!a\u0006\f\u0001\r-(cABu3U!1q^Bz!\u001d15QMBy\u0007\u001b\u00032ARBz\t!\tiea:C\u0002\rUXc\u0001\u001a\u0004x\u00121!ha=C\u0002I*2AMB~\t\u0019Q41\u001db\u0001e\u0005YQn[%t\u0011\u000e{gn]\u00194+)!\t\u0001b\u0002\u0005\u0010\u0011uAqF\u000b\u0003\t\u0007\u0001\u0002b\u0010\u0001\u0005\u0006\u00115A\u0011\u0004\t\u0004\r\u0012\u001dAA\u00020\u0012\u0005\u0004!I!F\u00023\t\u0017!aA\u000fC\u0004\u0005\u0004\u0011\u0004c\u0001$\u0005\u0010\u00111\u0001*\u0005b\u0001\t#)2A\rC\n\t\u001dQDq\u0002b\u0001\t+)2A\rC\f\t\u0019QD1\u0003b\u0001eU!A1\u0004C\u001c!\u001d1EQ\u0004C\u0017\tk!aaU\tC\u0002\u0011}Q#\u0002\u001a\u0005\"\u0011\u001dBa\u0002\u001e\u0005\u001e\t\u0007A1E\u000b\u0004e\u0011\u0015BA\u0002\u001e\u0005\"\t\u0007!\u0007B\u0004;\t;\u0011\r\u0001\"\u000b\u0016\u0007I\"Y\u0003\u0002\u0004;\tO\u0011\rA\r\t\u0004\r\u0012=BaBAS#\t\u0007A\u0011G\u000b\u0004e\u0011MBA\u0002\u001e\u00050\t\u0007!\u0007E\u0002G\to!\u0001\"!\u0014\u0005:\t\u0007Aq\n\u0005\b\u0003\u0017#Y\u0004AAV\u000b\u001d\ty\t\"\u0010\u0001\t\u00032a!a\u0006\f\u0001\u0011}\"c\u0001C\u001f3U!A1\tC%!\u001d1EQ\u0004C#\t\u000f\u00022A\u0012C\u0018!\r1E\u0011\n\u0003\t\u0003\u001b\"YD1\u0001\u0005LU\u0019!\u0007\"\u0014\u0005\ri\"IE1\u00013+\r\u0011D\u0011\u000b\u0003\u0007u\u0011]\"\u0019\u0001\u001a)\u000bE\t\t\r\"\u00162\u0017y\tY\u000bb\u0016\u0005\f\u0012=E1S\u0019\u0012?\u0005-F\u0011\fC.\tC\"9\u0007\"\u001c\u0005t\u0011e\u0014G\u0002\u0013\u0002,Z\tY.M\u0004\u0017\u0003W#i\u0006b\u00182\u000b\u0015\n\t/a92\u000b\u0015\nI/a;2\u000fY\tY\u000bb\u0019\u0005fE*Q%a=\u0002vF*Q%a?\u0002~F:a#a+\u0005j\u0011-\u0014\'B\u0013\u0003\u0004\t\u0015\u0011\'B\u0013\u0003\f\t5\u0011g\u0002\f\u0002,\u0012=D\u0011O\u0019\u0006K\tM!QC\u0019\u0006K\tm!QD\u0019\b-\u0005-FQ\u000fC<c\u0015)#Q\u0005B\u0014c\u0015)#Q\u0006B\u0018c\u001d1\u00121\u0016C>\t{\nT!\nB\u001c\u0005s\ttaHAV\t\u007f\"\t)M\u0004%\u0003W\u0013\tEa\u00112\u0017}\tY\u000bb!\u0005\u0006\u0012\u001dE\u0011R\u0019\bI\u0005-&\u0011\tB\"c\u0015)#1\u000bB+c\u0015)#\u0011\fB.c\u0015)#q\fB1c\r1CQ\u0012\t\u0004\r\u0012\u001d\u0011g\u0001\u0014\u0005\u0012B\u0019a\tb\u00042\u0007\u0019\")*\u0006\u0003\u0005\u0018\u0012m\u0005c\u0002$\u0005\u001e\u0011\u0015C\u0011\u0014\t\u0004\r\u0012mE\u0001CA\'\t;\u0013\r\u0001\"-\t\u000f\u0005-Eq\u0014\u0001\u0002,\u00169\u0011q\u0012CQ\u0001\u0011\u0015fABA\f\u0017\u0001!\u0019KE\u0002\u0005\"f)B\u0001b*\u0005,B9a\t\"\b\u0005F\u0011%\u0006c\u0001$\u0005,\u0012A\u0011Q\nCP\u0005\u0004!i+F\u00023\t_#aA\u000fCV\u0005\u0004\u0011Tc\u0001\u001a\u00054\u00121!\bb\'C\u0002I\nAb\u001e:ji\u0016\u0014V\r\u001d7bG\u0016$\"\u0001\"/\u0011\t\u0011mF\u0011Y\u0007\u0003\t{SA\u0001b0\u0002\u0006\u0005!A.\u00198h\u0013\u0011!\u0019\r\"0\u0003\r=\u0013\'.Z2u\u0001
  #12 = Utf8               fh$
  #13 = Utf8               (Lshapeless/IsHCons1;)Ljava/lang/Object;
  #14 = Utf8               $this
  #15 = Utf8               fh
  #16 = Utf8               ()Ljava/lang/Object;
  #17 = NameAndType        #15:#16        // fh:()Ljava/lang/Object;
  #18 = InterfaceMethodref #2.#17         // shapeless/IsHCons1.fh:()Ljava/lang/Object;
  #19 = Utf8               Lshapeless/IsHCons1;
  #20 = Utf8               ()TFH;
  #21 = Utf8               mkFhh
  #22 = NameAndType        #21:#16        // mkFhh:()Ljava/lang/Object;
  #23 = InterfaceMethodref #2.#22         // shapeless/IsHCons1.mkFhh:()Ljava/lang/Object;
  #24 = Utf8               this
  #25 = Utf8               ft$
  #26 = Utf8               ft
  #27 = NameAndType        #26:#16        // ft:()Ljava/lang/Object;
  #28 = InterfaceMethodref #2.#27         // shapeless/IsHCons1.ft:()Ljava/lang/Object;
  #29 = Utf8               ()TFT;
  #30 = Utf8               mkFtt
  #31 = NameAndType        #30:#16        // mkFtt:()Ljava/lang/Object;
  #32 = InterfaceMethodref #2.#31         // shapeless/IsHCons1.mkFtt:()Ljava/lang/Object;
  #33 = Utf8               pack
  #34 = Utf8               (Lscala/Tuple2;)Ljava/lang/Object;
  #35 = Utf8               <A:Ljava/lang/Object;>(Lscala/Tuple2<Ljava/lang/Object;Lshapeless/HList;>;)TL;
  #36 = Utf8               u
  #37 = Utf8               unpack
  #38 = Utf8               (Ljava/lang/Object;)Lscala/Tuple2;
  #39 = Utf8               <A:Ljava/lang/Object;>(TL;)Lscala/Tuple2<Ljava/lang/Object;Lshapeless/HList;>;
  #40 = Utf8               p
  #41 = Utf8               $init$
  #42 = Utf8               (Lshapeless/IsHCons1;)V
  #43 = Utf8               Code
  #44 = Utf8               LineNumberTable
  #45 = Utf8               LocalVariableTable
  #46 = Utf8               MethodParameters
  #47 = Utf8               Signature
  #48 = Utf8               SourceFile
  #49 = Utf8               RuntimeVisibleAnnotations
  #50 = Utf8               ScalaInlineInfo
  #51 = Utf8               ScalaSig
{
  public static java.lang.Object fh$(shapeless.IsHCons1);
    descriptor: (Lshapeless/IsHCons1;)Ljava/lang/Object;
    flags: (0x1009) ACC_PUBLIC, ACC_STATIC, ACC_SYNTHETIC
    Code:
      stack=1, locals=1, args_size=1
         0: aload_0
         1: invokespecial #18                 // InterfaceMethod fh:()Ljava/lang/Object;
         4: areturn
      LineNumberTable:
        line 52: 0
      LocalVariableTable:
        Start  Length  Slot  Name   Signature
            0       5     0 $this   Lshapeless/IsHCons1;
    MethodParameters:
      Name                           Flags
      $this                          final synthetic

  public default FH fh();
    descriptor: ()Ljava/lang/Object;
    flags: (0x0001) ACC_PUBLIC
    Code:
      stack=1, locals=1, args_size=1
         0: aload_0
         1: invokeinterface #23,  1           // InterfaceMethod mkFhh:()Ljava/lang/Object;
         6: areturn
      LineNumberTable:
        line 52: 0
      LocalVariableTable:
        Start  Length  Slot  Name   Signature
            0       7     0  this   Lshapeless/IsHCons1;
    Signature: #20                          // ()TFH;

  public static java.lang.Object ft$(shapeless.IsHCons1);
    descriptor: (Lshapeless/IsHCons1;)Ljava/lang/Object;
    flags: (0x1009) ACC_PUBLIC, ACC_STATIC, ACC_SYNTHETIC
    Code:
      stack=1, locals=1, args_size=1
         0: aload_0
         1: invokespecial #28                 // InterfaceMethod ft:()Ljava/lang/Object;
         4: areturn
      LineNumberTable:
        line 53: 0
      LocalVariableTable:
        Start  Length  Slot  Name   Signature
            0       5     0 $this   Lshapeless/IsHCons1;
    MethodParameters:
      Name                           Flags
      $this                          final synthetic

  public default FT ft();
    descriptor: ()Ljava/lang/Object;
    flags: (0x0001) ACC_PUBLIC
    Code:
      stack=1, locals=1, args_size=1
         0: aload_0
         1: invokeinterface #32,  1           // InterfaceMethod mkFtt:()Ljava/lang/Object;
         6: areturn
      LineNumberTable:
        line 53: 0
      LocalVariableTable:
        Start  Length  Slot  Name   Signature
            0       7     0  this   Lshapeless/IsHCons1;
    Signature: #29                          // ()TFT;

  public abstract <A extends java.lang.Object> L pack(scala.Tuple2<java.lang.Object, shapeless.HList>);
    descriptor: (Lscala/Tuple2;)Ljava/lang/Object;
    flags: (0x0401) ACC_PUBLIC, ACC_ABSTRACT
    Signature: #35                          // <A:Ljava/lang/Object;>(Lscala/Tuple2<Ljava/lang/Object;Lshapeless/HList;>;)TL;
    MethodParameters:
      Name                           Flags
      u                              final

  public abstract <A extends java.lang.Object> scala.Tuple2<java.lang.Object, shapeless.HList> unpack(L);
    descriptor: (Ljava/lang/Object;)Lscala/Tuple2;
    flags: (0x0401) ACC_PUBLIC, ACC_ABSTRACT
    Signature: #39                          // <A:Ljava/lang/Object;>(TL;)Lscala/Tuple2<Ljava/lang/Object;Lshapeless/HList;>;
    MethodParameters:
      Name                           Flags
      p                              final

  public abstract FH mkFhh();
    descriptor: ()Ljava/lang/Object;
    flags: (0x0401) ACC_PUBLIC, ACC_ABSTRACT
    Signature: #20                          // ()TFH;

  public abstract FT mkFtt();
    descriptor: ()Ljava/lang/Object;
    flags: (0x0401) ACC_PUBLIC, ACC_ABSTRACT
    Signature: #29                          // ()TFT;

  public static void $init$(shapeless.IsHCons1);
    descriptor: (Lshapeless/IsHCons1;)V
    flags: (0x0009) ACC_PUBLIC, ACC_STATIC
    Code:
      stack=0, locals=1, args_size=1
         0: return
      LineNumberTable:
        line 48: 0
      LocalVariableTable:
        Start  Length  Slot  Name   Signature
            0       1     0 $this   Lshapeless/IsHCons1;
    MethodParameters:
      Name                           Flags
      $this                          final synthetic
}
Signature: #3                           // <L:Ljava/lang/Object;FH:Ljava/lang/Object;FT:Ljava/lang/Object;>Ljava/lang/Object;Ljava/io/Serializable;
SourceFile: "generic1.scala"
RuntimeVisibleAnnotations:
  0: #9(#10=s#11)
    scala.reflect.ScalaSignature(
      bytes="\u0006\u0005\u0011\u0015gaB\n\u0015!\u0003\r\ta\u0006\u0005\u0006W\u0001!\t\u0001\f\u0003\u0006a\u0001\u0011\t!\r\u0003\u0006w\u0001\u0011\t\u0001\u0010\u0005\t\u0007\u0002A)\u0019!C\u0001\t\"Aq\n\u0001EC\u0002\u0013\u0005\u0001\u000bC\u0003Z\u0001\u0019\u0005!\fC\u0003l\u0001\u0019\u0005A\u000eC\u0003w\u0001\u0019\u0005A\tC\u0003x\u0001\u0019\u0005\u0001kB\u0003y)!\u0005\u0011PB\u0003\u0014)!\u0005!\u0010C\u0004\u0002\f-!\t!!\u0004\u0006\r\u0005=1\u0002AA\t\u0011!\t\tg\u0003B\u0005\u0004\u0005\r\u0004\u0002\u0003BG\u0017\t%\u0019Aa$\t\u0011\r\u00153B!C\u0002\u0007\u000fB\u0001b!@\f\u0005\u0013\r1q \u0005\n\tk[\u0011\u0011!C\u0005\to\u0013\u0001\"S:I\u0007>t7/\r\u0006\u0002+\u0005I1\u000f[1qK2,7o]\u0002\u0001+\u0011ARl\u0012*\u0014\u0007\u0001Ir\u0004\u0005\u0002\u001b;5\t1DC\u0001\u001d\u0003\u0015\u00198-\u00197b\u0013\tq2D\u0001\u0004B]f\u0014VM\u001a\t\u0003A!r!!\t\u0014\u000f\u0005\t*S\"A\u0012\u000b\u0005\u00112\u0012A\u0002\u001fs_>$h(C\u0001\u001d\u0013\t93$A\u0004qC\u000e\\\u0017mZ3\n\u0005%R#\u0001D*fe&\fG.\u001b>bE2,\'BA\u0014\u001c\u0003\u0019!\u0013N\\5uIQ\tQ\u0006\u0005\u0002\u001b]%\u0011qf\u0007\u0002\u0005+:LGOA\u0001I+\t\u0011\u0014(\u0005\u00024mA\u0011!\u0004N\u0005\u0003km\u0011qAT8uQ&tw\r\u0005\u0002\u001bo%\u0011\u0001h\u0007\u0002\u0004\u0003:LH!\u0002\u001e\u0003\u0005\u0004\u0011$!A0\u0003\u0003Q+\"!\u0010\"\u0012\u0005Mr\u0004CA A\u001b\u0005!\u0012BA!\u0015\u0005\u0015AE*[:u\t\u0015Q4A1\u00013\u0003\t1\u0007.F\u0001F!\r1u)\u0014\u0007\u0001\t\u0015A\u0005A1\u0001J\u0005\t1\u0005*\u0006\u00023\u0015\u0012)!h\u0012b\u0001\u0017V\u0011!\u0007\u0014\u0003\u0006u)\u0013\rA\r\t\u0003\u001d\ni\u0011\u0001A\u0001\u0003MR,\u0012!\u0015\t\u0004\rJCF!B*\u0001\u0005\u0004!&A\u0001$U+\t\u0011T\u000bB\u0003;%\n\u0007a+\u0006\u00023/\u0012)!(\u0016b\u0001eA\u0011ajA\u0001\u0005a\u0006\u001c7.\u0006\u0002\\ER\u0011A\f\u001a\t\u0004\rv\u000bG!\u00020\u0001\u0005\u0004y&!\u0001\'\u0016\u0005I\u0002G!\u0002\u001e^\u0005\u0004\u0011\u0004C\u0001$c\t\u0015\u0019gA1\u00013\u0005\u0005\t\u0005\"B3\u0007\u0001\u00041\u0017!A;\u0011\ti9\u0017N[\u0005\u0003Qn\u0011a\u0001V;qY\u0016\u0014\u0004c\u0001(\u0003CB\u0019ajA1\u0002\rUt\u0007/Y2l+\ti\u0017\u000f\u0006\u0002ogB!!dZ8s!\rq%\u0001\u001d\t\u0003\rF$QaY\u0004C\u0002I\u00022AT\u0002q\u0011\u0015!x\u00011\u0001v\u0003\u0005\u0001\bc\u0001$^a\u0006)Qn\u001b$iQ\u0006)Qn\u001b$ui\u0006A\u0011j\u001d%D_:\u001c\u0018\u0007\u0005\u0002@\u0017M!1\"G>\u007f!\tyD0\u0003\u0002~)\tI\u0011j\u001d%D_:\u001c\u0018\u0007\r\t\u0004\u007f\u0006%QBAA\u0001\u0015\u0011\t\u0019!!\u0002\u0002\u0005%|\'BAA\u0004\u0003\u0011Q\u0017M^1\n\u0007%\n\t!\u0001\u0004=S:LGO\u0010\u000b\u0002s\n\u0019\u0011)\u001e=\u0016\u0019\u0005M\u0011QDA\u0013\u0003c\t\t%!\u0016\u0013\t\u0005U\u0011\u0011\u0004\u0004\u0007\u0003/Y\u0001!a\u0005\u0003\u0019q\u0012XMZ5oK6,g\u000e\u001e \u0011\u0011}\u0002\u00111DA\u0012\u0003_\u00012ARA\u000f\t\u0019qVB1\u0001\u0002 U\u0019!\'!\t\u0005\ri\niB1\u00013!\r1\u0015Q\u0005\u0003\u0007\u00116\u0011\r!a\n\u0016\u0007I\nI\u0003B\u0004;\u0003K\u0011\r!a\u000b\u0016\u0007I\ni\u0003\u0002\u0004;\u0003S\u0011\rA\r\t\u0004\r\u0006EBAB*\u000e\u0005\u0004\t\u0019$F\u00023\u0003k!qAOA\u0019\u0005\u0004\t9$F\u00023\u0003s!aAOA\u001b\u0005\u0004\u0011TA\u0002\u0019\u0002\u0016\u0001\ni$\u0006\u0003\u0002@\u0005-\u0003#\u0002$\u0002B\u0005%CaBA\"\u001b\t\u0007\u0011Q\t\u0002\u0003\u0011B*2AMA$\t\u0019Q\u0014\u0011\tb\u0001eA\u0019a)a\u0013\u0005\u000f\u00055\u00131\bb\u0001e\t\tA/\u0002\u0004<\u0003+\u0001\u0013\u0011K\u000b\u0005\u0003\'\ny\u0006E\u0003G\u0003+\ni\u0006B\u0004\u0002X5\u0011\r!!\u0017\u0003\u0005Q\u0003TcA\u001f\u0002\\\u00111!(!\u0016C\u0002I\u00022ARA0\t\u001d\ti%a\u0014C\u0002I\n1\"\\6Jg\"\u001buN\\:2aUQ\u0011QMA6\u0003k\n\u0019+!.\u0016\u0005\u0005\u001d\u0004\u0003C \u0001\u0003S\n\t(a-\u0011\u0007\u0019\u000bY\u0007\u0002\u0004_\u001d\t\u0007\u0011QN\u000b\u0004e\u0005=DA\u0002\u001e\u0002l\t\u0007!\'\u0006\u0003\u0002t\u0005\u001d\u0005c\u0002$\u0002v\u0005\u0015\u0015\u0011\u0017\u0003\u0007\u0011:\u0011\r!a\u001e\u0016\u000bI\nI(a \u0005\u000fi\n)H1\u0001\u0002|U\u0019!\'! \u0005\ri\nIH1\u00013\t\u001dQ\u0014Q\u000fb\u0001\u0003\u0003+2AMAB\t\u0019Q\u0014q\u0010b\u0001eA\u0019a)a\"\u0005\u0011\u00055\u0013\u0011\u0012b\u0001\u0003[Cq!a#\u0002\u000e\u0002\tY+\u0001\u0006=Y>\u001c\u0017\r\u001c\u0011Ox{*q!a$\u0002\u0012\u0002\t)J\u0001\u0002Ox\u001b1\u0011qC\u0006\u0001\u0003\'\u00132!!%\u001a+\u0011\t9*a\'\u0011\u000f\u0019\u000b)(!\'\u0002\"B\u0019a)a\'\u0005\u0011\u00055\u0013Q\u0012b\u0001\u0003;+2AMAP\t\u0019Q\u00141\u0014b\u0001eA\u0019a)a)\u0005\u000f\u0005\u0015fB1\u0001\u0002(\n\tQ+F\u00023\u0003S#aAOAR\u0005\u0004\u00114\u0002A\u000b\u0004e\u0005=FA\u0002\u001e\u0002\b\n\u0007!\u0007E\u0002G\u0003G\u00032ARA[\t\u0019\u0019fB1\u0001\u00028V\u0019!\'!/\u0005\u000fi\n)L1\u0001\u0002<V\u0019!\'!0\u0005\ri\nIL1\u00013Q\u0015q\u0011\u0011YAk!\u0011\t\u0019-!5\u000e\u0005\u0005\u0015\'\u0002BAd\u0003\u0013\f\u0001\"\u001b8uKJt\u0017\r\u001c\u0006\u0005\u0003\u0017\fi-\u0001\u0004nC\u000e\u0014xn\u001d\u0006\u0004\u0003\u001f\\\u0012a\u0002:fM2,7\r^\u0005\u0005\u0003\'\f)MA\u0005nC\u000e\u0014x.S7qYFZa$a+\u0002X\n\r$q\rBEcEy\u00121VAm\u0003;\fy/a@\u0003\u0010\t\u0005\"1G\u0019\u0007I\u0005-f#a7\u0002\u000b5\f7M]82\u000fY\tY+a8\u0002hF*Q%!9\u0002d>\u0011\u00111]\u0011\u0003\u0003K\f1\"\\1de>,enZ5oKF*Q%!;\u0002l>\u0011\u00111^\u0011\u0003\u0003[\fQE^\u001c/a\u0001B\u0013.\u001c9mK6,g\u000e^3eA%t\u0007eU2bY\u0006\u0004#GL\u00192]AjS\nO\u00152\u000fY\tY+!=\u0002zF*Q%a=\u0002v>\u0011\u0011Q_\u0011\u0003\u0003o\f\u0001\"[:Ck:$G.Z\u0019\u0006K\u0005m\u0018Q`\b\u0003\u0003{L\u0012!A\u0019\b-\u0005-&\u0011\u0001B\u0005c\u0015)#1\u0001B\u0003\u001f\t\u0011)!\t\u0002\u0003\b\u0005Q\u0011n\u001d\"mC\u000e\\\'m\u001c=2\u000b\u0015\u0012YA!\u0004\u0010\u0005\t5\u0011$\u0001\u00012\u000fY\tYK!\u0005\u0003\u001aE*QEa\u0005\u0003\u0016=\u0011!QC\u0011\u0003\u0005/\t\u0011b\u00197bgNt\u0015-\\32\u000b\u0015\u0012YB!\b\u0010\u0005\tu\u0011E\u0001B\u0010\u0003a\u0019\b.\u00199fY\u0016\u001c8OL%t\u0011\u000e{gn]\u0019NC\u000e\u0014xn]\u0019\b-\u0005-&1\u0005B\u0016c\u0015)#Q\u0005B\u0014\u001f\t\u00119#\t\u0002\u0003*\u0005QQ.\u001a;i_\u0012t\u0015-\\32\u000b\u0015\u0012iCa\f\u0010\u0005\t=\u0012E\u0001B\u0019\u00039i7.S:I\u0007>t7/M%na2\ftAFAV\u0005k\u0011i$M\u0003&\u0005o\u0011Id\u0004\u0002\u0003:\u0005\u0012!1H\u0001\ng&<g.\u0019;ve\u0016\ftaHAV\u0005\u007f\u0011i%M\u0004%\u0003W\u0013\tEa\u0011\n\t\t\r#QI\u0001\u0005\u0019&\u001cHO\u0003\u0003\u0003H\t%\u0013!C5n[V$\u0018M\u00197f\u0015\r\u0011YeG\u0001\u000bG>dG.Z2uS>t\u0017gC\u0010\u0002,\n=#\u0011\u000bB,\u0005;\nt\u0001JAV\u0005\u0003\u0012\u0019%M\u0003&\u0005\'\u0012)f\u0004\u0002\u0003Vu\t\u0001!M\u0003&\u00053\u0012Yf\u0004\u0002\u0003\\u\t\u0011!M\u0003&\u0005?\u0012\tg\u0004\u0002\u0003bu\t!!M\u0002\'\u0005K\u00022ARA6c\r1#\u0011N\u000b\u0005\u0005W\u0012y\u0007E\u0004G\u0003k\u0012i\'!)\u0011\u0007\u0019\u0013y\u0007\u0002\u0005\u0002N\tE$\u0019\u0001BC\u0011\u001d\tYIa\u001d\u0001\u0003W+q!a$\u0003v\u0001\u0011IH\u0002\u0004\u0002\u0018-\u0001!q\u000f\n\u0004\u0005kJR\u0003\u0002B>\u0005\u007f\u0002rARA;\u0005{\n\t\u000bE\u0002G\u0005\u007f\"\u0001\"!\u0014\u0003t\t\u0007!\u0011Q\u000b\u0004e\t\rEA\u0002\u001e\u0003\u0000\t\u0007!\'F\u00023\u0005\u000f#aA\u000fB8\u0005\u0004\u0011\u0014g\u0001\u0014\u0003\fB\u0019a)!.\u0002\u00175\\\u0017j\u001d%D_:\u001c\u0018\'M\u000b\u000b\u0005#\u00139J!)\u00034\neWC\u0001BJ!!y\u0004A!&\u0003\u001e\n]\u0007c\u0001$\u0003\u0018\u00121al\u0004b\u0001\u00053+2A\rBN\t\u0019Q$q\u0013b\u0001eU!!q\u0014B^!\u001d1%\u0011\u0015BY\u0005s#a\u0001S\bC\u0002\t\rV#\u0002\u001a\u0003&\n-Fa\u0002\u001e\u0003\"\n\u0007!qU\u000b\u0004e\t%FA\u0002\u001e\u0003&\n\u0007!\u0007B\u0004;\u0005C\u0013\rA!,\u0016\u0007I\u0012y\u000b\u0002\u0004;\u0005W\u0013\rA\r\t\u0004\r\nMFaBAS\u001f\t\u0007!QW\u000b\u0004e\t]FA\u0002\u001e\u00034\n\u0007!\u0007E\u0002G\u0005w#\u0001\"!\u0014\u0003>\n\u0007!1\u001b\u0005\b\u0003\u0017\u0013y\fAAV\u000b\u001d\tyI!1\u0001\u0005\u000b4a!a\u0006\f\u0001\t\r\'c\u0001Ba3U!!q\u0019Bg!\u001d1%\u0011\u0015Be\u0005\u0017\u00042A\u0012BZ!\r1%Q\u001a\u0003\t\u0003\u001b\u0012yL1\u0001\u0003PV\u0019!G!5\u0005\ri\u0012iM1\u00013+\r\u0011$Q\u001b\u0003\u0007u\tm&\u0019\u0001\u001a\u0011\u0007\u0019\u0013I\u000e\u0002\u0004T\u001f\t\u0007!1\\\u000b\u0004e\tuGa\u0002\u001e\u0003Z\n\u0007!q\\\u000b\u0004e\t\u0005HA\u0002\u001e\u0003^\n\u0007!\u0007K\u0003\u0010\u0003\u0003\u0014)/M\u0006\u001f\u0003W\u00139oa\u0007\u0004 \r\u0005\u0013\'E\u0010\u0002,\n%(1\u001eBy\u0005o\u0014ipa\u0001\u0004\nE2A%a+\u0017\u00037\ftAFAV\u0005[\u0014y/M\u0003&\u0003C\f\u0019/M\u0003&\u0003S\fY/M\u0004\u0017\u0003W\u0013\u0019P!>2\u000b\u0015\n\u00190!>2\u000b\u0015\nY0!@2\u000fY\tYK!?\u0003|F*QEa\u0001\u0003\u0006E*QEa\u0003\u0003\u000eE:a#a+\u0003\u0000\u000e\u0005\u0011\'B\u0013\u0003\u0014\tU\u0011\'B\u0013\u0003\u001c\tu\u0011g\u0002\f\u0002,\u000e\u00151qA\u0019\u0006K\t\u0015\"qE\u0019\u0006K\t5\"qF\u0019\b-\u0005-61BB\u0007c\u0015)#q\u0007B\u001dc\u001dy\u00121VB\b\u0007#\tt\u0001JAV\u0005\u0003\u0012\u0019%M\u0006 \u0003W\u001b\u0019b!\u0006\u0004\u0018\re\u0011g\u0002\u0013\u0002,\n\u0005#1I\u0019\u0006K\tM#QK\u0019\u0006K\te#1L\u0019\u0006K\t}#\u0011M\u0019\u0004M\ru\u0001c\u0001$\u0003\u0018F\u001aae!\t\u0016\t\r\r2q\u0005\t\b\r\n\u0005&\u0011ZB\u0013!\r15q\u0005\u0003\t\u0003\u001b\u001aIC1\u0001\u0004>!9\u00111RB\u0016\u0001\u0005-VaBAH\u0007[\u00011\u0011\u0007\u0004\u0007\u0003/Y\u0001aa\f\u0013\u0007\r5\u0012$\u0006\u0003\u00044\r]\u0002c\u0002$\u0003\"\n%7Q\u0007\t\u0004\r\u000e]B\u0001CA\'\u0007W\u0011\ra!\u000f\u0016\u0007I\u001aY\u0004\u0002\u0004;\u0007o\u0011\rAM\u000b\u0004e\r}BA\u0002\u001e\u0004(\t\u0007!\'M\u0002\'\u0007\u0007\u00022A\u0012Bm\u0003-i7.S:I\u0007>t7/\r\u001a\u0016\u0015\r%3qJB,\u0007K\u001ay)\u0006\u0002\u0004LAAq\bAB\'\u0007+\u001a\t\u0007E\u0002G\u0007\u001f\"aA\u0018\tC\u0002\rESc\u0001\u001a\u0004T\u00111!ha\u0014C\u0002I\u00022ARB,\t\u0019A\u0005C1\u0001\u0004ZU\u0019!ga\u0017\u0005\u000fi\u001a9F1\u0001\u0004^U\u0019!ga\u0018\u0005\ri\u001aYF1\u00013+\u0011\u0019\u0019ga\u001e\u0011\u000f\u0019\u001b)g!\u001e\u0004\u001a\u001211\u000b\u0005b\u0001\u0007O*RAMB5\u0007_\"qAOB3\u0005\u0004\u0019Y\'F\u00023\u0007[\"aAOB5\u0005\u0004\u0011Da\u0002\u001e\u0004f\t\u00071\u0011O\u000b\u0004e\rMDA\u0002\u001e\u0004p\t\u0007!\u0007E\u0002G\u0007o\"\u0001\"!\u0014\u0004z\t\u00071Q\u0013\u0005\b\u0003\u0017\u001bY\bAAV\u000b\u001d\tyi! \u0001\u0007\u00033a!a\u0006\f\u0001\r}$cAB?3U!11QBD!\u001d15QMBC\u0007\u001b\u00032ARBD\t!\tiea\u001fC\u0002\r%Uc\u0001\u001a\u0004\f\u00121!ha\"C\u0002I\u00022ARBH\t\u001d\t)\u000b\u0005b\u0001\u0007#+2AMBJ\t\u0019Q4q\u0012b\u0001eU\u0019!ga&\u0005\ri\u001a9H1\u00013!\r15q\u0012\u0015\u0006!\u0005\u00057QT\u0019\f=\u0005-6qTBj\u0007/\u001cY.M\t \u0003W\u001b\tka)\u0004*\u000e=6QWB^\u0007\u0003\fd\u0001JAV-\u0005m\u0017g\u0002\f\u0002,\u000e\u00156qU\u0019\u0006K\u0005\u0005\u00181]\u0019\u0006K\u0005%\u00181^\u0019\b-\u0005-61VBWc\u0015)\u00131_A{c\u0015)\u00131`A\u007fc\u001d1\u00121VBY\u0007g\u000bT!\nB\u0002\u0005\u000b\tT!\nB\u0006\u0005\u001b\ttAFAV\u0007o\u001bI,M\u0003&\u0005\'\u0011)\"M\u0003&\u00057\u0011i\"M\u0004\u0017\u0003W\u001bila02\u000b\u0015\u0012)Ca\n2\u000b\u0015\u0012iCa\f2\u000fY\tYka1\u0004FF*QEa\u000e\u0003:E:q$a+\u0004H\u000e%\u0017g\u0002\u0013\u0002,\n\u0005#1I\u0019\f?\u0005-61ZBg\u0007\u001f\u001c\t.M\u0004%\u0003W\u0013\tEa\u00112\u000b\u0015\u0012\u0019F!\u00162\u000b\u0015\u0012IFa\u00172\u000b\u0015\u0012yF!\u00192\u0007\u0019\u001a)\u000eE\u0002G\u0007\u001f\n4AJBm!\r15qK\u0019\u0004M\ruW\u0003BBp\u0007G\u0004rARB3\u0007C\u001ci\tE\u0002G\u0007G$\u0001\"!\u0014\u0004f\n\u00071\u0011 \u0005\b\u0003\u0017\u001b9\u000fAAV\u000b\u001d\tyi!;\u0001\u0007[4a!a\u0006\f\u0001\r-(cABu3U!1q^Bz!\u001d15QMBy\u0007\u001b\u00032ARBz\t!\tiea:C\u0002\rUXc\u0001\u001a\u0004x\u00121!ha=C\u0002I*2AMB~\t\u0019Q41\u001db\u0001e\u0005YQn[%t\u0011\u000e{gn]\u00194+)!\t\u0001b\u0002\u0005\u0010\u0011uAqF\u000b\u0003\t\u0007\u0001\u0002b\u0010\u0001\u0005\u0006\u00115A\u0011\u0004\t\u0004\r\u0012\u001dAA\u00020\u0012\u0005\u0004!I!F\u00023\t\u0017!aA\u000fC\u0004\u0005\u0004\u0011\u0004c\u0001$\u0005\u0010\u00111\u0001*\u0005b\u0001\t#)2A\rC\n\t\u001dQDq\u0002b\u0001\t+)2A\rC\f\t\u0019QD1\u0003b\u0001eU!A1\u0004C\u001c!\u001d1EQ\u0004C\u0017\tk!aaU\tC\u0002\u0011}Q#\u0002\u001a\u0005\"\u0011\u001dBa\u0002\u001e\u0005\u001e\t\u0007A1E\u000b\u0004e\u0011\u0015BA\u0002\u001e\u0005\"\t\u0007!\u0007B\u0004;\t;\u0011\r\u0001\"\u000b\u0016\u0007I\"Y\u0003\u0002\u0004;\tO\u0011\rA\r\t\u0004\r\u0012=BaBAS#\t\u0007A\u0011G\u000b\u0004e\u0011MBA\u0002\u001e\u00050\t\u0007!\u0007E\u0002G\to!\u0001\"!\u0014\u0005:\t\u0007Aq\n\u0005\b\u0003\u0017#Y\u0004AAV\u000b\u001d\ty\t\"\u0010\u0001\t\u00032a!a\u0006\f\u0001\u0011}\"c\u0001C\u001f3U!A1\tC%!\u001d1EQ\u0004C#\t\u000f\u00022A\u0012C\u0018!\r1E\u0011\n\u0003\t\u0003\u001b\"YD1\u0001\u0005LU\u0019!\u0007\"\u0014\u0005\ri\"IE1\u00013+\r\u0011D\u0011\u000b\u0003\u0007u\u0011]\"\u0019\u0001\u001a)\u000bE\t\t\r\"\u00162\u0017y\tY\u000bb\u0016\u0005\f\u0012=E1S\u0019\u0012?\u0005-F\u0011\fC.\tC\"9\u0007\"\u001c\u0005t\u0011e\u0014G\u0002\u0013\u0002,Z\tY.M\u0004\u0017\u0003W#i\u0006b\u00182\u000b\u0015\n\t/a92\u000b\u0015\nI/a;2\u000fY\tY\u000bb\u0019\u0005fE*Q%a=\u0002vF*Q%a?\u0002~F:a#a+\u0005j\u0011-\u0014\'B\u0013\u0003\u0004\t\u0015\u0011\'B\u0013\u0003\f\t5\u0011g\u0002\f\u0002,\u0012=D\u0011O\u0019\u0006K\tM!QC\u0019\u0006K\tm!QD\u0019\b-\u0005-FQ\u000fC<c\u0015)#Q\u0005B\u0014c\u0015)#Q\u0006B\u0018c\u001d1\u00121\u0016C>\t{\nT!\nB\u001c\u0005s\ttaHAV\t\u007f\"\t)M\u0004%\u0003W\u0013\tEa\u00112\u0017}\tY\u000bb!\u0005\u0006\u0012\u001dE\u0011R\u0019\bI\u0005-&\u0011\tB\"c\u0015)#1\u000bB+c\u0015)#\u0011\fB.c\u0015)#q\fB1c\r1CQ\u0012\t\u0004\r\u0012\u001d\u0011g\u0001\u0014\u0005\u0012B\u0019a\tb\u00042\u0007\u0019\")*\u0006\u0003\u0005\u0018\u0012m\u0005c\u0002$\u0005\u001e\u0011\u0015C\u0011\u0014\t\u0004\r\u0012mE\u0001CA\'\t;\u0013\r\u0001\"-\t\u000f\u0005-Eq\u0014\u0001\u0002,\u00169\u0011q\u0012CQ\u0001\u0011\u0015fABA\f\u0017\u0001!\u0019KE\u0002\u0005\"f)B\u0001b*\u0005,B9a\t\"\b\u0005F\u0011%\u0006c\u0001$\u0005,\u0012A\u0011Q\nCP\u0005\u0004!i+F\u00023\t_#aA\u000fCV\u0005\u0004\u0011Tc\u0001\u001a\u00054\u00121!\bb\'C\u0002I\nAb\u001e:ji\u0016\u0014V\r\u001d7bG\u0016$\"\u0001\"/\u0011\t\u0011mF\u0011Y\u0007\u0003\t{SA\u0001b0\u0002\u0006\u0005!A.\u00198h\u0013\u0011!\u0019\r\"0\u0003\r=\u0013\'.Z2u\u0001"
    )
  ScalaInlineInfo: length = 0x31 (unknown attribute)
   01 00 00 09 00 29 00 2A 01 00 0C 00 0D 01 00 0F
   00 10 00 00 19 00 0D 01 00 1A 00 10 00 00 15 00
   10 00 00 1E 00 10 00 00 21 00 22 00 00 25 00 26
   00
  ScalaSig: length = 0x3 (unknown attribute)
   05 02 00
