Classfile /Users/mw/Projects/slang-braindump/.jar/jar8/assemble/slang-braindump/assemble/content/shapeless/LabelledGeneric$.class
  Last modified May 29, 2022; size 2765 bytes
  SHA-256 checksum 168a53c3010d164242ab088b3233db149d4674895041a5ae4b9e499bec05fc5a
  Compiled from "generic.scala"
public final class shapeless.LabelledGeneric$ implements java.io.Serializable
  minor version: 0
  major version: 52
  flags: (0x0031) ACC_PUBLIC, ACC_FINAL, ACC_SUPER
  this_class: #2                          // shapeless/LabelledGeneric$
  super_class: #4                         // java/lang/Object
  interfaces: 1, fields: 1, methods: 6, attributes: 4
Constant pool:
   #1 = Utf8               shapeless/LabelledGeneric$
   #2 = Class              #1             // shapeless/LabelledGeneric$
   #3 = Utf8               java/lang/Object
   #4 = Class              #3             // java/lang/Object
   #5 = Utf8               java/io/Serializable
   #6 = Class              #5             // java/io/Serializable
   #7 = Utf8               generic.scala
   #8 = Utf8               shapeless/LabelledGeneric$$anon$1
   #9 = Class              #8             // shapeless/LabelledGeneric$$anon$1
  #10 = Utf8               shapeless/LabelledGeneric$$anon$2
  #11 = Class              #10            // shapeless/LabelledGeneric$$anon$2
  #12 = Utf8               shapeless/ops/coproduct$ZipWithKeys
  #13 = Class              #12            // shapeless/ops/coproduct$ZipWithKeys
  #14 = Utf8               shapeless/ops/coproduct
  #15 = Class              #14            // shapeless/ops/coproduct
  #16 = Utf8               ZipWithKeys
  #17 = Utf8               shapeless/ops/hlist$ZipWithKeys
  #18 = Class              #17            // shapeless/ops/hlist$ZipWithKeys
  #19 = Utf8               shapeless/ops/hlist
  #20 = Class              #19            // shapeless/ops/hlist
  #21 = Utf8               MODULE$
  #22 = Utf8               Lshapeless/LabelledGeneric$;
  #23 = Utf8               <clinit>
  #24 = Utf8               ()V
  #25 = Utf8               <init>
  #26 = NameAndType        #25:#24        // "<init>":()V
  #27 = Methodref          #2.#26         // shapeless/LabelledGeneric$."<init>":()V
  #28 = NameAndType        #21:#22        // MODULE$:Lshapeless/LabelledGeneric$;
  #29 = Fieldref           #2.#28         // shapeless/LabelledGeneric$.MODULE$:Lshapeless/LabelledGeneric$;
  #30 = Utf8               apply
  #31 = Utf8               (Lshapeless/LabelledGeneric;)Lshapeless/LabelledGeneric;
  #32 = Utf8               <T:Ljava/lang/Object;>(Lshapeless/LabelledGeneric<TT;>;)Lshapeless/LabelledGeneric<TT;>;
  #33 = Utf8               lgen
  #34 = Utf8               this
  #35 = Utf8               Lshapeless/LabelledGeneric;
  #36 = Utf8               materializeProduct
  #37 = Utf8               (Lshapeless/DefaultSymbolicLabelling;Lshapeless/Generic;Lshapeless/ops/hlist$ZipWithKeys;Lscala/$less$colon$less;)Lshapeless/LabelledGeneric;
  #38 = Utf8               <T:Ljava/lang/Object;K::Lshapeless/HList;V::Lshapeless/HList;R::Lshapeless/HList;>(Lshapeless/DefaultSymbolicLabelling<TT;>;Lshapeless/Generic<TT;>;Lshapeless/ops/hlist$ZipWithKeys<TK;TV;>;Lscala/$less$colon$less<TR;TV;>;)Lshapeless/LabelledGeneric<TT;>;
  #39 = Utf8               lab
  #40 = Utf8               gen
  #41 = Utf8               zip
  #42 = Utf8               ev
  #43 = Utf8               (Lshapeless/ops/hlist$ZipWithKeys;Lshapeless/Generic;Lscala/$less$colon$less;)V
  #44 = NameAndType        #25:#43        // "<init>":(Lshapeless/ops/hlist$ZipWithKeys;Lshapeless/Generic;Lscala/$less$colon$less;)V
  #45 = Methodref          #9.#44         // shapeless/LabelledGeneric$$anon$1."<init>":(Lshapeless/ops/hlist$ZipWithKeys;Lshapeless/Generic;Lscala/$less$colon$less;)V
  #46 = Utf8               Lshapeless/DefaultSymbolicLabelling;
  #47 = Utf8               Lshapeless/Generic;
  #48 = Utf8               Lshapeless/ops/hlist$ZipWithKeys;
  #49 = Utf8               Lscala/$less$colon$less;
  #50 = Utf8               materializeCoproduct
  #51 = Utf8               (Lshapeless/DefaultSymbolicLabelling;Lshapeless/Generic;Lshapeless/ops/coproduct$ZipWithKeys;Lscala/$less$colon$less;)Lshapeless/LabelledGeneric;
  #52 = Utf8               <T:Ljava/lang/Object;K::Lshapeless/HList;V::Lshapeless/Coproduct;R::Lshapeless/Coproduct;>(Lshapeless/DefaultSymbolicLabelling<TT;>;Lshapeless/Generic<TT;>;Lshapeless/ops/coproduct$ZipWithKeys<TK;TV;>;Lscala/$less$colon$less<TR;TV;>;)Lshapeless/LabelledGeneric<TT;>;
  #53 = Utf8               (Lshapeless/ops/coproduct$ZipWithKeys;Lshapeless/Generic;Lscala/$less$colon$less;)V
  #54 = NameAndType        #25:#53        // "<init>":(Lshapeless/ops/coproduct$ZipWithKeys;Lshapeless/Generic;Lscala/$less$colon$less;)V
  #55 = Methodref          #11.#54        // shapeless/LabelledGeneric$$anon$2."<init>":(Lshapeless/ops/coproduct$ZipWithKeys;Lshapeless/Generic;Lscala/$less$colon$less;)V
  #56 = Utf8               Lshapeless/ops/coproduct$ZipWithKeys;
  #57 = Utf8               writeReplace
  #58 = Utf8               ()Ljava/lang/Object;
  #59 = Utf8               scala/runtime/ModuleSerializationProxy
  #60 = Class              #59            // scala/runtime/ModuleSerializationProxy
  #61 = Utf8               (Ljava/lang/Class;)V
  #62 = NameAndType        #25:#61        // "<init>":(Ljava/lang/Class;)V
  #63 = Methodref          #60.#62        // scala/runtime/ModuleSerializationProxy."<init>":(Ljava/lang/Class;)V
  #64 = Methodref          #4.#26         // java/lang/Object."<init>":()V
  #65 = Utf8               Code
  #66 = Utf8               LineNumberTable
  #67 = Utf8               LocalVariableTable
  #68 = Utf8               Signature
  #69 = Utf8               MethodParameters
  #70 = Utf8               InnerClasses
  #71 = Utf8               SourceFile
  #72 = Utf8               ScalaInlineInfo
  #73 = Utf8               Scala
{
  public static final shapeless.LabelledGeneric$ MODULE$;
    descriptor: Lshapeless/LabelledGeneric$;
    flags: (0x0019) ACC_PUBLIC, ACC_STATIC, ACC_FINAL

  public static {};
    descriptor: ()V
    flags: (0x0009) ACC_PUBLIC, ACC_STATIC
    Code:
      stack=2, locals=0, args_size=0
         0: new           #2                  // class shapeless/LabelledGeneric$
         3: dup
         4: invokespecial #27                 // Method "<init>":()V
         7: putstatic     #29                 // Field MODULE$:Lshapeless/LabelledGeneric$;
        10: return
      LineNumberTable:
        line 205: 0

  public <T extends java.lang.Object> shapeless.LabelledGeneric<T> apply(shapeless.LabelledGeneric<T>);
    descriptor: (Lshapeless/LabelledGeneric;)Lshapeless/LabelledGeneric;
    flags: (0x0001) ACC_PUBLIC
    Code:
      stack=1, locals=2, args_size=2
         0: aload_1
         1: areturn
      LineNumberTable:
        line 216: 0
      LocalVariableTable:
        Start  Length  Slot  Name   Signature
            0       2     0  this   Lshapeless/LabelledGeneric$;
            0       2     1  lgen   Lshapeless/LabelledGeneric;
    Signature: #32                          // <T:Ljava/lang/Object;>(Lshapeless/LabelledGeneric<TT;>;)Lshapeless/LabelledGeneric<TT;>;
    MethodParameters:
      Name                           Flags
      lgen                           final

  public <T extends java.lang.Object, K extends shapeless.HList, V extends shapeless.HList, R extends shapeless.HList> shapeless.LabelledGeneric<T> materializeProduct(shapeless.DefaultSymbolicLabelling<T>, shapeless.Generic<T>, shapeless.ops.hlist$ZipWithKeys<K, V>, scala.$less$colon$less<R, V>);
    descriptor: (Lshapeless/DefaultSymbolicLabelling;Lshapeless/Generic;Lshapeless/ops/hlist$ZipWithKeys;Lscala/$less$colon$less;)Lshapeless/LabelledGeneric;
    flags: (0x0001) ACC_PUBLIC
    Code:
      stack=5, locals=5, args_size=5
         0: new           #9                  // class shapeless/LabelledGeneric$$anon$1
         3: dup
         4: aload_3
         5: aload_2
         6: aload         4
         8: invokespecial #45                 // Method shapeless/LabelledGeneric$$anon$1."<init>":(Lshapeless/ops/hlist$ZipWithKeys;Lshapeless/Generic;Lscala/$less$colon$less;)V
        11: areturn
      LineNumberTable:
        line 226: 0
      LocalVariableTable:
        Start  Length  Slot  Name   Signature
            0      12     0  this   Lshapeless/LabelledGeneric$;
            0      12     1   lab   Lshapeless/DefaultSymbolicLabelling;
            0      12     2   gen   Lshapeless/Generic;
            0      12     3   zip   Lshapeless/ops/hlist$ZipWithKeys;
            0      12     4    ev   Lscala/$less$colon$less;
    Signature: #38                          // <T:Ljava/lang/Object;K::Lshapeless/HList;V::Lshapeless/HList;R::Lshapeless/HList;>(Lshapeless/DefaultSymbolicLabelling<TT;>;Lshapeless/Generic<TT;>;Lshapeless/ops/hlist$ZipWithKeys<TK;TV;>;Lscala/$less$colon$less<TR;TV;>;)Lshapeless/LabelledGeneric<TT;>;
    MethodParameters:
      Name                           Flags
      lab                            final
      gen                            final
      zip                            final
      ev                             final

  public <T extends java.lang.Object, K extends shapeless.HList, V extends shapeless.Coproduct, R extends shapeless.Coproduct> shapeless.LabelledGeneric<T> materializeCoproduct(shapeless.DefaultSymbolicLabelling<T>, shapeless.Generic<T>, shapeless.ops.coproduct$ZipWithKeys<K, V>, scala.$less$colon$less<R, V>);
    descriptor: (Lshapeless/DefaultSymbolicLabelling;Lshapeless/Generic;Lshapeless/ops/coproduct$ZipWithKeys;Lscala/$less$colon$less;)Lshapeless/LabelledGeneric;
    flags: (0x0001) ACC_PUBLIC
    Code:
      stack=5, locals=5, args_size=5
         0: new           #11                 // class shapeless/LabelledGeneric$$anon$2
         3: dup
         4: aload_3
         5: aload_2
         6: aload         4
         8: invokespecial #55                 // Method shapeless/LabelledGeneric$$anon$2."<init>":(Lshapeless/ops/coproduct$ZipWithKeys;Lshapeless/Generic;Lscala/$less$colon$less;)V
        11: areturn
      LineNumberTable:
        line 240: 0
      LocalVariableTable:
        Start  Length  Slot  Name   Signature
            0      12     0  this   Lshapeless/LabelledGeneric$;
            0      12     1   lab   Lshapeless/DefaultSymbolicLabelling;
            0      12     2   gen   Lshapeless/Generic;
            0      12     3   zip   Lshapeless/ops/coproduct$ZipWithKeys;
            0      12     4    ev   Lscala/$less$colon$less;
    Signature: #52                          // <T:Ljava/lang/Object;K::Lshapeless/HList;V::Lshapeless/Coproduct;R::Lshapeless/Coproduct;>(Lshapeless/DefaultSymbolicLabelling<TT;>;Lshapeless/Generic<TT;>;Lshapeless/ops/coproduct$ZipWithKeys<TK;TV;>;Lscala/$less$colon$less<TR;TV;>;)Lshapeless/LabelledGeneric<TT;>;
    MethodParameters:
      Name                           Flags
      lab                            final
      gen                            final
      zip                            final
      ev                             final

  private java.lang.Object writeReplace();
    descriptor: ()Ljava/lang/Object;
    flags: (0x0002) ACC_PRIVATE
    Code:
      stack=3, locals=1, args_size=1
         0: new           #60                 // class scala/runtime/ModuleSerializationProxy
         3: dup
         4: ldc           #2                  // class shapeless/LabelledGeneric$
         6: invokespecial #63                 // Method scala/runtime/ModuleSerializationProxy."<init>":(Ljava/lang/Class;)V
         9: areturn
      LineNumberTable:
        line 205: 0
      LocalVariableTable:
        Start  Length  Slot  Name   Signature
            0      10     0  this   Lshapeless/LabelledGeneric$;

  private shapeless.LabelledGeneric$();
    descriptor: ()V
    flags: (0x0002) ACC_PRIVATE
    Code:
      stack=1, locals=1, args_size=1
         0: aload_0
         1: invokespecial #64                 // Method java/lang/Object."<init>":()V
         4: return
      LineNumberTable:
        line 247: 0
        line 205: 4
      LocalVariableTable:
        Start  Length  Slot  Name   Signature
            0       5     0  this   Lshapeless/LabelledGeneric$;
}
InnerClasses:
  public final #9;                        // class shapeless/LabelledGeneric$$anon$1
  public final #11;                       // class shapeless/LabelledGeneric$$anon$2
  public static #16= #13 of #15;          // ZipWithKeys=class shapeless/ops/coproduct$ZipWithKeys of class shapeless/ops/coproduct
  public static #16= #18 of #20;          // ZipWithKeys=class shapeless/ops/hlist$ZipWithKeys of class shapeless/ops/hlist
SourceFile: "generic.scala"
  ScalaInlineInfo: length = 0x1D (unknown attribute)
   01 01 00 05 00 19 00 18 01 00 1E 00 1F 01 00 32
   00 33 01 00 24 00 25 01 00 39 00 3A 01
  Scala: length = 0x0 (unknown attribute)

