Classfile /Users/mw/Projects/slang-braindump/.jar/jar8/assemble/slang-braindump/assemble/content/shapeless/labelled$.class
  Last modified May 29, 2022; size 728 bytes
  SHA-256 checksum 224a6e86d2139a72a6a712bcaaaa02a4c95e012d2d5d64ad27c4571ce1ccb421
  Compiled from "labelled.scala"
public final class shapeless.labelled$
  minor version: 0
  major version: 52
  flags: (0x0031) ACC_PUBLIC, ACC_FINAL, ACC_SUPER
  this_class: #2                          // shapeless/labelled$
  super_class: #4                         // java/lang/Object
  interfaces: 0, fields: 1, methods: 3, attributes: 4
Constant pool:
   #1 = Utf8               shapeless/labelled$
   #2 = Class              #1             // shapeless/labelled$
   #3 = Utf8               java/lang/Object
   #4 = Class              #3             // java/lang/Object
   #5 = Utf8               labelled.scala
   #6 = Utf8               shapeless/labelled$FieldBuilder
   #7 = Class              #6             // shapeless/labelled$FieldBuilder
   #8 = Utf8               shapeless/labelled
   #9 = Class              #8             // shapeless/labelled
  #10 = Utf8               FieldBuilder
  #11 = Utf8               MODULE$
  #12 = Utf8               Lshapeless/labelled$;
  #13 = Utf8               <clinit>
  #14 = Utf8               ()V
  #15 = Utf8               <init>
  #16 = NameAndType        #15:#14        // "<init>":()V
  #17 = Methodref          #2.#16         // shapeless/labelled$."<init>":()V
  #18 = NameAndType        #11:#12        // MODULE$:Lshapeless/labelled$;
  #19 = Fieldref           #2.#18         // shapeless/labelled$.MODULE$:Lshapeless/labelled$;
  #20 = Utf8               field
  #21 = Utf8               ()Lshapeless/labelled$FieldBuilder;
  #22 = Utf8               <K:Ljava/lang/Object;>()Lshapeless/labelled$FieldBuilder<TK;>;
  #23 = Methodref          #7.#16         // shapeless/labelled$FieldBuilder."<init>":()V
  #24 = Utf8               this
  #25 = Methodref          #4.#16         // java/lang/Object."<init>":()V
  #26 = Utf8               Code
  #27 = Utf8               LineNumberTable
  #28 = Utf8               LocalVariableTable
  #29 = Utf8               Signature
  #30 = Utf8               InnerClasses
  #31 = Utf8               SourceFile
  #32 = Utf8               ScalaInlineInfo
  #33 = Utf8               Scala
{
  public static final shapeless.labelled$ MODULE$;
    descriptor: Lshapeless/labelled$;
    flags: (0x0019) ACC_PUBLIC, ACC_STATIC, ACC_FINAL

  public static {};
    descriptor: ()V
    flags: (0x0009) ACC_PUBLIC, ACC_STATIC
    Code:
      stack=2, locals=0, args_size=0
         0: new           #2                  // class shapeless/labelled$
         3: dup
         4: invokespecial #17                 // Method "<init>":()V
         7: putstatic     #19                 // Field MODULE$:Lshapeless/labelled$;
        10: return
      LineNumberTable:
        line 23: 0

  public <K extends java.lang.Object> shapeless.labelled$FieldBuilder<K> field();
    descriptor: ()Lshapeless/labelled$FieldBuilder;
    flags: (0x0001) ACC_PUBLIC
    Code:
      stack=2, locals=1, args_size=1
         0: new           #7                  // class shapeless/labelled$FieldBuilder
         3: dup
         4: invokespecial #23                 // Method shapeless/labelled$FieldBuilder."<init>":()V
         7: areturn
      LineNumberTable:
        line 33: 0
      LocalVariableTable:
        Start  Length  Slot  Name   Signature
            0       8     0  this   Lshapeless/labelled$;
    Signature: #22                          // <K:Ljava/lang/Object;>()Lshapeless/labelled$FieldBuilder<TK;>;

  private shapeless.labelled$();
    descriptor: ()V
    flags: (0x0002) ACC_PRIVATE
    Code:
      stack=1, locals=1, args_size=1
         0: aload_0
         1: invokespecial #25                 // Method java/lang/Object."<init>":()V
         4: return
      LineNumberTable:
        line 40: 0
        line 23: 4
      LocalVariableTable:
        Start  Length  Slot  Name   Signature
            0       5     0  this   Lshapeless/labelled$;
}
InnerClasses:
  public static #10= #7 of #9;            // FieldBuilder=class shapeless/labelled$FieldBuilder of class shapeless/labelled
SourceFile: "labelled.scala"
  ScalaInlineInfo: length = 0xE (unknown attribute)
   01 01 00 02 00 0F 00 0E 01 00 14 00 15 01
  Scala: length = 0x0 (unknown attribute)

