Classfile /Users/mw/Projects/slang-braindump/.jar/jar8/assemble/slang-braindump/assemble/content/shapeless/LabelledGeneric$$anon$2.class
  Last modified May 29, 2022; size 1913 bytes
  SHA-256 checksum f29564952146e7949a4303891f85a9363a82503093df68310a4e990b547a074e
  Compiled from "generic.scala"
public final class shapeless.LabelledGeneric$$anon$2 extends java.lang.Object implements shapeless.LabelledGeneric<T>
  minor version: 0
  major version: 52
  flags: (0x0031) ACC_PUBLIC, ACC_FINAL, ACC_SUPER
  this_class: #2                          // shapeless/LabelledGeneric$$anon$2
  super_class: #5                         // java/lang/Object
  interfaces: 1, fields: 3, methods: 5, attributes: 6
Constant pool:
   #1 = Utf8               shapeless/LabelledGeneric$$anon$2
   #2 = Class              #1             // shapeless/LabelledGeneric$$anon$2
   #3 = Utf8               Ljava/lang/Object;Lshapeless/LabelledGeneric<TT;>;
   #4 = Utf8               java/lang/Object
   #5 = Class              #4             // java/lang/Object
   #6 = Utf8               shapeless/LabelledGeneric
   #7 = Class              #6             // shapeless/LabelledGeneric
   #8 = Utf8               generic.scala
   #9 = Utf8               shapeless/LabelledGeneric$
  #10 = Class              #9             // shapeless/LabelledGeneric$
  #11 = Utf8               materializeCoproduct
  #12 = Utf8               (Lshapeless/DefaultSymbolicLabelling;Lshapeless/Generic;Lshapeless/ops/coproduct$ZipWithKeys;Lscala/$less$colon$less;)Lshapeless/LabelledGeneric;
  #13 = NameAndType        #11:#12        // materializeCoproduct:(Lshapeless/DefaultSymbolicLabelling;Lshapeless/Generic;Lshapeless/ops/coproduct$ZipWithKeys;Lscala/$less$colon$less;)Lshapeless/LabelledGeneric;
  #14 = Utf8               shapeless/ops/coproduct$ZipWithKeys
  #15 = Class              #14            // shapeless/ops/coproduct$ZipWithKeys
  #16 = Utf8               shapeless/ops/coproduct
  #17 = Class              #16            // shapeless/ops/coproduct
  #18 = Utf8               ZipWithKeys
  #19 = Utf8               zip$2
  #20 = Utf8               Lshapeless/ops/coproduct$ZipWithKeys;
  #21 = Utf8               gen$2
  #22 = Utf8               Lshapeless/Generic;
  #23 = Utf8               ev$2
  #24 = Utf8               Lscala/$less$colon$less;
  #25 = Utf8               to
  #26 = Utf8               (Ljava/lang/Object;)Lshapeless/Coproduct;
  #27 = Utf8               (TT;)TR;
  #28 = Utf8               t
  #29 = NameAndType        #19:#20        // zip$2:Lshapeless/ops/coproduct$ZipWithKeys;
  #30 = Fieldref           #2.#29         // shapeless/LabelledGeneric$$anon$2.zip$2:Lshapeless/ops/coproduct$ZipWithKeys;
  #31 = NameAndType        #21:#22        // gen$2:Lshapeless/Generic;
  #32 = Fieldref           #2.#31         // shapeless/LabelledGeneric$$anon$2.gen$2:Lshapeless/Generic;
  #33 = Utf8               shapeless/Generic
  #34 = Class              #33            // shapeless/Generic
  #35 = Utf8               (Ljava/lang/Object;)Ljava/lang/Object;
  #36 = NameAndType        #25:#35        // to:(Ljava/lang/Object;)Ljava/lang/Object;
  #37 = InterfaceMethodref #34.#36        // shapeless/Generic.to:(Ljava/lang/Object;)Ljava/lang/Object;
  #38 = Utf8               apply
  #39 = NameAndType        #38:#35        // apply:(Ljava/lang/Object;)Ljava/lang/Object;
  #40 = InterfaceMethodref #15.#39        // shapeless/ops/coproduct$ZipWithKeys.apply:(Ljava/lang/Object;)Ljava/lang/Object;
  #41 = Utf8               shapeless/Coproduct
  #42 = Class              #41            // shapeless/Coproduct
  #43 = Utf8               this
  #44 = Utf8               Lshapeless/LabelledGeneric$$anon$2;
  #45 = Utf8               Ljava/lang/Object;
  #46 = Utf8               from
  #47 = Utf8               (Lshapeless/Coproduct;)Ljava/lang/Object;
  #48 = Utf8               (TR;)TT;
  #49 = Utf8               r
  #50 = NameAndType        #23:#24        // ev$2:Lscala/$less$colon$less;
  #51 = Fieldref           #2.#50         // shapeless/LabelledGeneric$$anon$2.ev$2:Lscala/$less$colon$less;
  #52 = Utf8               scala/$less$colon$less
  #53 = Class              #52            // scala/$less$colon$less
  #54 = Methodref          #53.#39        // scala/$less$colon$less.apply:(Ljava/lang/Object;)Ljava/lang/Object;
  #55 = NameAndType        #46:#35        // from:(Ljava/lang/Object;)Ljava/lang/Object;
  #56 = InterfaceMethodref #34.#55        // shapeless/Generic.from:(Ljava/lang/Object;)Ljava/lang/Object;
  #57 = Utf8               Lshapeless/Coproduct;
  #58 = NameAndType        #46:#47        // from:(Lshapeless/Coproduct;)Ljava/lang/Object;
  #59 = Methodref          #2.#58         // shapeless/LabelledGeneric$$anon$2.from:(Lshapeless/Coproduct;)Ljava/lang/Object;
  #60 = NameAndType        #25:#26        // to:(Ljava/lang/Object;)Lshapeless/Coproduct;
  #61 = Methodref          #2.#60         // shapeless/LabelledGeneric$$anon$2.to:(Ljava/lang/Object;)Lshapeless/Coproduct;
  #62 = Utf8               <init>
  #63 = Utf8               (Lshapeless/ops/coproduct$ZipWithKeys;Lshapeless/Generic;Lscala/$less$colon$less;)V
  #64 = Utf8               ()V
  #65 = NameAndType        #62:#64        // "<init>":()V
  #66 = Methodref          #5.#65         // java/lang/Object."<init>":()V
  #67 = Utf8               Code
  #68 = Utf8               LineNumberTable
  #69 = Utf8               LocalVariableTable
  #70 = Utf8               Signature
  #71 = Utf8               MethodParameters
  #72 = Utf8               InnerClasses
  #73 = Utf8               EnclosingMethod
  #74 = Utf8               SourceFile
  #75 = Utf8               ScalaInlineInfo
  #76 = Utf8               Scala
{
  private final shapeless.ops.coproduct$ZipWithKeys zip$2;
    descriptor: Lshapeless/ops/coproduct$ZipWithKeys;
    flags: (0x0012) ACC_PRIVATE, ACC_FINAL

  private final shapeless.Generic gen$2;
    descriptor: Lshapeless/Generic;
    flags: (0x0012) ACC_PRIVATE, ACC_FINAL

  private final scala.$less$colon$less ev$2;
    descriptor: Lscala/$less$colon$less;
    flags: (0x0012) ACC_PRIVATE, ACC_FINAL

  public R to(T);
    descriptor: (Ljava/lang/Object;)Lshapeless/Coproduct;
    flags: (0x0001) ACC_PUBLIC
    Code:
      stack=3, locals=2, args_size=2
         0: aload_0
         1: getfield      #30                 // Field zip$2:Lshapeless/ops/coproduct$ZipWithKeys;
         4: aload_0
         5: getfield      #32                 // Field gen$2:Lshapeless/Generic;
         8: aload_1
         9: invokeinterface #37,  2           // InterfaceMethod shapeless/Generic.to:(Ljava/lang/Object;)Ljava/lang/Object;
        14: invokeinterface #40,  2           // InterfaceMethod shapeless/ops/coproduct$ZipWithKeys.apply:(Ljava/lang/Object;)Ljava/lang/Object;
        19: checkcast     #42                 // class shapeless/Coproduct
        22: areturn
      LineNumberTable:
        line 242: 0
      LocalVariableTable:
        Start  Length  Slot  Name   Signature
            0      23     0  this   Lshapeless/LabelledGeneric$$anon$2;
            0      23     1     t   Ljava/lang/Object;
    Signature: #27                          // (TT;)TR;
    MethodParameters:
      Name                           Flags
      t                              final

  public T from(R);
    descriptor: (Lshapeless/Coproduct;)Ljava/lang/Object;
    flags: (0x0001) ACC_PUBLIC
    Code:
      stack=3, locals=2, args_size=2
         0: aload_0
         1: getfield      #32                 // Field gen$2:Lshapeless/Generic;
         4: aload_0
         5: getfield      #51                 // Field ev$2:Lscala/$less$colon$less;
         8: aload_1
         9: invokevirtual #54                 // Method scala/$less$colon$less.apply:(Ljava/lang/Object;)Ljava/lang/Object;
        12: invokeinterface #56,  2           // InterfaceMethod shapeless/Generic.from:(Ljava/lang/Object;)Ljava/lang/Object;
        17: areturn
      LineNumberTable:
        line 243: 0
      LocalVariableTable:
        Start  Length  Slot  Name   Signature
            0      18     0  this   Lshapeless/LabelledGeneric$$anon$2;
            0      18     1     r   Lshapeless/Coproduct;
    Signature: #48                          // (TR;)TT;
    MethodParameters:
      Name                           Flags
      r                              final

  public java.lang.Object from(java.lang.Object);
    descriptor: (Ljava/lang/Object;)Ljava/lang/Object;
    flags: (0x1041) ACC_PUBLIC, ACC_BRIDGE, ACC_SYNTHETIC
    Code:
      stack=2, locals=2, args_size=2
         0: aload_0
         1: aload_1
         2: checkcast     #42                 // class shapeless/Coproduct
         5: invokevirtual #59                 // Method from:(Lshapeless/Coproduct;)Ljava/lang/Object;
         8: areturn
      LineNumberTable:
        line 240: 0
      LocalVariableTable:
        Start  Length  Slot  Name   Signature
            0       9     0  this   Lshapeless/LabelledGeneric$$anon$2;
            0       9     1     r   Ljava/lang/Object;
    MethodParameters:
      Name                           Flags
      r                              final

  public java.lang.Object to(java.lang.Object);
    descriptor: (Ljava/lang/Object;)Ljava/lang/Object;
    flags: (0x1041) ACC_PUBLIC, ACC_BRIDGE, ACC_SYNTHETIC
    Code:
      stack=2, locals=2, args_size=2
         0: aload_0
         1: aload_1
         2: invokevirtual #61                 // Method to:(Ljava/lang/Object;)Lshapeless/Coproduct;
         5: areturn
      LineNumberTable:
        line 240: 0
      LocalVariableTable:
        Start  Length  Slot  Name   Signature
            0       6     0  this   Lshapeless/LabelledGeneric$$anon$2;
            0       6     1     t   Ljava/lang/Object;
    MethodParameters:
      Name                           Flags
      t                              final

  public shapeless.LabelledGeneric$$anon$2(shapeless.ops.coproduct$ZipWithKeys, shapeless.Generic, scala.$less$colon$less);
    descriptor: (Lshapeless/ops/coproduct$ZipWithKeys;Lshapeless/Generic;Lscala/$less$colon$less;)V
    flags: (0x0001) ACC_PUBLIC
    Code:
      stack=2, locals=4, args_size=4
         0: aload_0
         1: aload_1
         2: putfield      #30                 // Field zip$2:Lshapeless/ops/coproduct$ZipWithKeys;
         5: aload_0
         6: aload_2
         7: putfield      #32                 // Field gen$2:Lshapeless/Generic;
        10: aload_0
        11: aload_3
        12: putfield      #51                 // Field ev$2:Lscala/$less$colon$less;
        15: aload_0
        16: invokespecial #66                 // Method java/lang/Object."<init>":()V
        19: return
      LineNumberTable:
        line 237: 0
        line 236: 5
        line 238: 10
        line 240: 15
      LocalVariableTable:
        Start  Length  Slot  Name   Signature
            0      20     0  this   Lshapeless/LabelledGeneric$$anon$2;
            0      20     1 zip$2   Lshapeless/ops/coproduct$ZipWithKeys;
            0      20     2 gen$2   Lshapeless/Generic;
            0      20     3  ev$2   Lscala/$less$colon$less;
    MethodParameters:
      Name                           Flags
      zip$2                          final
      gen$2                          final
      ev$2                           final
}
InnerClasses:
  public final #2;                        // class shapeless/LabelledGeneric$$anon$2
  public static #18= #15 of #17;          // ZipWithKeys=class shapeless/ops/coproduct$ZipWithKeys of class shapeless/ops/coproduct
EnclosingMethod: #10.#13                // shapeless.LabelledGeneric$.materializeCoproduct
Signature: #3                           // Ljava/lang/Object;Lshapeless/LabelledGeneric<TT;>;
SourceFile: "generic.scala"
  ScalaInlineInfo: length = 0x1D (unknown attribute)
   01 01 00 05 00 3E 00 3F 01 00 2E 00 23 01 00 2E
   00 2F 01 00 19 00 23 01 00 19 00 1A 01
  Scala: length = 0x0 (unknown attribute)

