Classfile /Users/mw/Projects/slang-braindump/.jar/jar8/assemble/slang-braindump/assemble/content/shapeless/LazyMacrosCompat.class
  Last modified May 29, 2022; size 7703 bytes
  SHA-256 checksum 28b4c5fb7ccd74e0fe767574ec4b59d83bcbfa3ebb175b22ccd7fe05ad5279ff
  Compiled from "lazymacros.scala"
public interface shapeless.LazyMacrosCompat
  minor version: 0
  major version: 52
  flags: (0x0601) ACC_PUBLIC, ACC_INTERFACE, ACC_ABSTRACT
  this_class: #2                          // shapeless/LazyMacrosCompat
  super_class: #4                         // java/lang/Object
  interfaces: 0, fields: 0, methods: 11, attributes: 6
Constant pool:
    #1 = Utf8               shapeless/LazyMacrosCompat
    #2 = Class              #1            // shapeless/LazyMacrosCompat
    #3 = Utf8               java/lang/Object
    #4 = Class              #3            // java/lang/Object
    #5 = Utf8               lazymacros.scala
    #6 = Utf8               Lscala/reflect/ScalaSignature;
    #7 = Utf8               bytes
    #8 = Utf8               \u0006\u0005y2q\u0001B\u0003\u0011\u0002\u0007\u0005\u0001\u0002C\u0003\u0010\u0001\u0011\u0005\u0001\u0003C\u0003\u0015\u0001\u0011\u0005Q\u0003C\u0003#\u0001\u0011\u00051E\u0001\tMCjLX*Y2s_N\u001cu.\u001c9bi*\ta!A\u0005tQ\u0006\u0004X\r\\3tg\u000e\u00011C\u0001\u0001\n!\tQQ\"D\u0001\f\u0015\u0005a\u0011!B:dC2\f\u0017B\u0001\b\f\u0005\u0019\te.\u001f*fM\u00061A%\u001b8ji\u0012\"\u0012!\u0005\t\u0003\u0015II!aE\u0006\u0003\tUs\u0017\u000e^\u0001\u0006I\u000e\u0014VM\u001a\u000b\u0003-\u0001\u00022AC\f\u001a\u0013\tA2B\u0001\u0004PaRLwN\u001c\t\u00035y\u0001\"a\u0007\u000f\u000e\u0003\u0015I!!H\u0003\u0003\u00151\u000b\'0_\'bGJ|7/\u0003\u0002 9\t\tB)\u001a:jm\u0006$\u0018n\u001c8D_:$X\r\u001f;\t\u000b\u0005\u0012\u0001\u0019\u0001\u000e\u0002\u00051l\u0017A\u00043fe&4X-\u00138ti\u0006t7-\u001a\u000b\u0003I%\"2!\n\u001b:!\t1CF\u0004\u0002(U9\u0011\u0001&\u000b\u0007\u0001\u0011\u0015\t3\u00011\u0001\u001b\u0013\tYC$A\u0001d\u0013\ticF\u0001\u0003Ue\u0016,\u0017BA\u00181\u0005\u001d\tE.[1tKNT!!\r\u001a\u0002\r5\f7M]8t\u0015\t\u00194\"A\u0004sK\u001adWm\u0019;\t\u000bU\u001a\u0001\u0019\u0001\u001c\u0002\u0007Q\u0004X\r\u0005\u0002\'o%\u0011\u0001H\f\u0002\u0005)f\u0004X\rC\u0003;\u0007\u0001\u00071(\u0001\u0004nW&s7\u000f\u001e\t\u0006\u0015q*c\'J\u0005\u0003{-\u0011\u0011BR;oGRLwN\u001c\u001a
    #9 = Utf8               java/lang/invoke/MethodHandles$Lookup
   #10 = Class              #9            // java/lang/invoke/MethodHandles$Lookup
   #11 = Utf8               java/lang/invoke/MethodHandles
   #12 = Class              #11           // java/lang/invoke/MethodHandles
   #13 = Utf8               Lookup
   #14 = Utf8               scala/reflect/api/Trees$TreeApi
   #15 = Class              #14           // scala/reflect/api/Trees$TreeApi
   #16 = Utf8               scala/reflect/api/Trees
   #17 = Class              #16           // scala/reflect/api/Trees
   #18 = Utf8               TreeApi
   #19 = Utf8               scala/reflect/api/Types$TypeApi
   #20 = Class              #19           // scala/reflect/api/Types$TypeApi
   #21 = Utf8               scala/reflect/api/Types
   #22 = Class              #21           // scala/reflect/api/Types
   #23 = Utf8               TypeApi
   #24 = Utf8               scala/reflect/macros/Internals$ContextInternalApi
   #25 = Class              #24           // scala/reflect/macros/Internals$ContextInternalApi
   #26 = Utf8               scala/reflect/macros/Internals
   #27 = Class              #26           // scala/reflect/macros/Internals
   #28 = Utf8               ContextInternalApi
   #29 = Utf8               shapeless/LazyMacros$DerivationContext
   #30 = Class              #29           // shapeless/LazyMacros$DerivationContext
   #31 = Utf8               shapeless/LazyMacros
   #32 = Class              #31           // shapeless/LazyMacros
   #33 = Utf8               DerivationContext
   #34 = Utf8               shapeless/LazyMacros$DerivationContext$State$
   #35 = Class              #34           // shapeless/LazyMacros$DerivationContext$State$
   #36 = Utf8               State$
   #37 = Utf8               dcRef$
   #38 = Utf8               (Lshapeless/LazyMacrosCompat;Lshapeless/LazyMacros;)Lscala/Option;
   #39 = Utf8               $this
   #40 = Utf8               lm
   #41 = Utf8               dcRef
   #42 = Utf8               (Lshapeless/LazyMacros;)Lscala/Option;
   #43 = NameAndType        #41:#42       // dcRef:(Lshapeless/LazyMacros;)Lscala/Option;
   #44 = InterfaceMethodref #2.#43        // shapeless/LazyMacrosCompat.dcRef:(Lshapeless/LazyMacros;)Lscala/Option;
   #45 = Utf8               Lshapeless/LazyMacrosCompat;
   #46 = Utf8               Lshapeless/LazyMacros;
   #47 = Utf8               (Lshapeless/LazyMacros;)Lscala/Option<Lshapeless/LazyMacros$DerivationContext;>;
   #48 = Utf8               c
   #49 = Utf8               ()Lscala/reflect/macros/whitebox/Context;
   #50 = NameAndType        #48:#49       // c:()Lscala/reflect/macros/whitebox/Context;
   #51 = Methodref          #32.#50       // shapeless/LazyMacros.c:()Lscala/reflect/macros/whitebox/Context;
   #52 = Utf8               scala/reflect/macros/whitebox/Context
   #53 = Class              #52           // scala/reflect/macros/whitebox/Context
   #54 = Utf8               openMacros
   #55 = Utf8               ()Lscala/collection/immutable/List;
   #56 = NameAndType        #54:#55       // openMacros:()Lscala/collection/immutable/List;
   #57 = InterfaceMethodref #53.#56       // scala/reflect/macros/whitebox/Context.openMacros:()Lscala/collection/immutable/List;
   #58 = Utf8               (Ljava/lang/Object;)Ljava/lang/Object;
   #59 = MethodType         #58           //  (Ljava/lang/Object;)Ljava/lang/Object;
   #60 = Utf8               $anonfun$dcRef$1$adapted
   #61 = Utf8               (Lshapeless/LazyMacros;Lscala/reflect/macros/whitebox/Context;)Ljava/lang/Object;
   #62 = NameAndType        #60:#61       // $anonfun$dcRef$1$adapted:(Lshapeless/LazyMacros;Lscala/reflect/macros/whitebox/Context;)Ljava/lang/Object;
   #63 = InterfaceMethodref #2.#62        // shapeless/LazyMacrosCompat.$anonfun$dcRef$1$adapted:(Lshapeless/LazyMacros;Lscala/reflect/macros/whitebox/Context;)Ljava/lang/Object;
   #64 = MethodHandle       6:#63         // REF_invokeStatic shapeless/LazyMacrosCompat.$anonfun$dcRef$1$adapted:(Lshapeless/LazyMacros;Lscala/reflect/macros/whitebox/Context;)Ljava/lang/Object;
   #65 = Utf8               (Lscala/reflect/macros/whitebox/Context;)Ljava/lang/Object;
   #66 = MethodType         #65           //  (Lscala/reflect/macros/whitebox/Context;)Ljava/lang/Object;
   #67 = Integer            5
   #68 = Integer            1
   #69 = Utf8               java/lang/invoke/LambdaMetafactory
   #70 = Class              #69           // java/lang/invoke/LambdaMetafactory
   #71 = Utf8               altMetafactory
   #72 = Utf8               (Ljava/lang/invoke/MethodHandles$Lookup;Ljava/lang/String;Ljava/lang/invoke/MethodType;[Ljava/lang/Object;)Ljava/lang/invoke/CallSite;
   #73 = NameAndType        #71:#72       // altMetafactory:(Ljava/lang/invoke/MethodHandles$Lookup;Ljava/lang/String;Ljava/lang/invoke/MethodType;[Ljava/lang/Object;)Ljava/lang/invoke/CallSite;
   #74 = Methodref          #70.#73       // java/lang/invoke/LambdaMetafactory.altMetafactory:(Ljava/lang/invoke/MethodHandles$Lookup;Ljava/lang/String;Ljava/lang/invoke/MethodType;[Ljava/lang/Object;)Ljava/lang/invoke/CallSite;
   #75 = MethodHandle       6:#74         // REF_invokeStatic java/lang/invoke/LambdaMetafactory.altMetafactory:(Ljava/lang/invoke/MethodHandles$Lookup;Ljava/lang/String;Ljava/lang/invoke/MethodType;[Ljava/lang/Object;)Ljava/lang/invoke/CallSite;
   #76 = Utf8               apply
   #77 = Utf8               (Lshapeless/LazyMacros;)Lscala/Function1;
   #78 = NameAndType        #76:#77       // apply:(Lshapeless/LazyMacros;)Lscala/Function1;
   #79 = InvokeDynamic      #0:#78        // #0:apply:(Lshapeless/LazyMacros;)Lscala/Function1;
   #80 = Utf8               scala/collection/immutable/List
   #81 = Class              #80           // scala/collection/immutable/List
   #82 = Utf8               takeWhile
   #83 = Utf8               (Lscala/Function1;)Lscala/collection/immutable/List;
   #84 = NameAndType        #82:#83       // takeWhile:(Lscala/Function1;)Lscala/collection/immutable/List;
   #85 = Methodref          #81.#84       // scala/collection/immutable/List.takeWhile:(Lscala/Function1;)Lscala/collection/immutable/List;
   #86 = Utf8               $anonfun$dcRef$2$adapted
   #87 = NameAndType        #86:#65       // $anonfun$dcRef$2$adapted:(Lscala/reflect/macros/whitebox/Context;)Ljava/lang/Object;
   #88 = InterfaceMethodref #2.#87        // shapeless/LazyMacrosCompat.$anonfun$dcRef$2$adapted:(Lscala/reflect/macros/whitebox/Context;)Ljava/lang/Object;
   #89 = MethodHandle       6:#88         // REF_invokeStatic shapeless/LazyMacrosCompat.$anonfun$dcRef$2$adapted:(Lscala/reflect/macros/whitebox/Context;)Ljava/lang/Object;
   #90 = Utf8               ()Lscala/Function1;
   #91 = NameAndType        #76:#90       // apply:()Lscala/Function1;
   #92 = InvokeDynamic      #1:#91        // #1:apply:()Lscala/Function1;
   #93 = Utf8               find
   #94 = Utf8               (Lscala/Function1;)Lscala/Option;
   #95 = NameAndType        #93:#94       // find:(Lscala/Function1;)Lscala/Option;
   #96 = Methodref          #81.#95       // scala/collection/immutable/List.find:(Lscala/Function1;)Lscala/Option;
   #97 = Utf8               $anonfun$dcRef$3
   #98 = Utf8               (Lscala/reflect/macros/whitebox/Context;)Lscala/Option;
   #99 = NameAndType        #97:#98       // $anonfun$dcRef$3:(Lscala/reflect/macros/whitebox/Context;)Lscala/Option;
  #100 = InterfaceMethodref #2.#99        // shapeless/LazyMacrosCompat.$anonfun$dcRef$3:(Lscala/reflect/macros/whitebox/Context;)Lscala/Option;
  #101 = MethodHandle       6:#100        // REF_invokeStatic shapeless/LazyMacrosCompat.$anonfun$dcRef$3:(Lscala/reflect/macros/whitebox/Context;)Lscala/Option;
  #102 = MethodType         #98           //  (Lscala/reflect/macros/whitebox/Context;)Lscala/Option;
  #103 = InvokeDynamic      #2:#91        // #2:apply:()Lscala/Function1;
  #104 = Utf8               scala/Option
  #105 = Class              #104          // scala/Option
  #106 = Utf8               flatMap
  #107 = NameAndType        #106:#94      // flatMap:(Lscala/Function1;)Lscala/Option;
  #108 = Methodref          #105.#107     // scala/Option.flatMap:(Lscala/Function1;)Lscala/Option;
  #109 = Utf8               this
  #110 = Utf8               deriveInstance$
  #111 = Utf8               (Lshapeless/LazyMacrosCompat;Lshapeless/LazyMacros;Lscala/reflect/api/Types$TypeApi;Lscala/Function2;)Lscala/reflect/api/Trees$TreeApi;
  #112 = Utf8               tpe
  #113 = Utf8               mkInst
  #114 = Utf8               deriveInstance
  #115 = Utf8               (Lshapeless/LazyMacros;Lscala/reflect/api/Types$TypeApi;Lscala/Function2;)Lscala/reflect/api/Trees$TreeApi;
  #116 = NameAndType        #114:#115     // deriveInstance:(Lshapeless/LazyMacros;Lscala/reflect/api/Types$TypeApi;Lscala/Function2;)Lscala/reflect/api/Trees$TreeApi;
  #117 = InterfaceMethodref #2.#116       // shapeless/LazyMacrosCompat.deriveInstance:(Lshapeless/LazyMacros;Lscala/reflect/api/Types$TypeApi;Lscala/Function2;)Lscala/reflect/api/Trees$TreeApi;
  #118 = Utf8               Lscala/reflect/api/Types$TypeApi;
  #119 = Utf8               Lscala/Function2;
  #120 = Utf8               (Lshapeless/LazyMacros;Lscala/reflect/api/Types$TypeApi;Lscala/Function2<Lscala/reflect/api/Trees$TreeApi;Lscala/reflect/api/Types$TypeApi;Lscala/reflect/api/Trees$TreeApi;>;)Lscala/reflect/api/Trees$TreeApi;
  #121 = Utf8               scala/None$
  #122 = Class              #121          // scala/None$
  #123 = Utf8               MODULE$
  #124 = Utf8               Lscala/None$;
  #125 = NameAndType        #123:#124     // MODULE$:Lscala/None$;
  #126 = Fieldref           #122.#125     // scala/None$.MODULE$:Lscala/None$;
  #127 = Utf8               equals
  #128 = Utf8               (Ljava/lang/Object;)Z
  #129 = NameAndType        #127:#128     // equals:(Ljava/lang/Object;)Z
  #130 = Methodref          #4.#129       // java/lang/Object.equals:(Ljava/lang/Object;)Z
  #131 = Utf8               resetAnnotation
  #132 = Utf8               ()V
  #133 = NameAndType        #131:#132     // resetAnnotation:()V
  #134 = Methodref          #32.#133      // shapeless/LazyMacros.resetAnnotation:()V
  #135 = Utf8               <init>
  #136 = Utf8               (Lshapeless/LazyMacros;)V
  #137 = NameAndType        #135:#136     // "<init>":(Lshapeless/LazyMacros;)V
  #138 = Methodref          #30.#137      // shapeless/LazyMacros$DerivationContext."<init>":(Lshapeless/LazyMacros;)V
  #139 = Utf8               internal
  #140 = Utf8               ()Lscala/reflect/macros/Internals$ContextInternalApi;
  #141 = NameAndType        #139:#140     // internal:()Lscala/reflect/macros/Internals$ContextInternalApi;
  #142 = InterfaceMethodref #53.#141      // scala/reflect/macros/whitebox/Context.internal:()Lscala/reflect/macros/Internals$ContextInternalApi;
  #143 = Utf8               macroApplication
  #144 = Utf8               ()Lscala/reflect/api/Trees$TreeApi;
  #145 = NameAndType        #143:#144     // macroApplication:()Lscala/reflect/api/Trees$TreeApi;
  #146 = InterfaceMethodref #53.#145      // scala/reflect/macros/whitebox/Context.macroApplication:()Lscala/reflect/api/Trees$TreeApi;
  #147 = Utf8               scala/reflect/ClassTag$
  #148 = Class              #147          // scala/reflect/ClassTag$
  #149 = Utf8               Lscala/reflect/ClassTag$;
  #150 = NameAndType        #123:#149     // MODULE$:Lscala/reflect/ClassTag$;
  #151 = Fieldref           #148.#150     // scala/reflect/ClassTag$.MODULE$:Lscala/reflect/ClassTag$;
  #152 = Utf8               (Ljava/lang/Class;)Lscala/reflect/ClassTag;
  #153 = NameAndType        #76:#152      // apply:(Ljava/lang/Class;)Lscala/reflect/ClassTag;
  #154 = Methodref          #148.#153     // scala/reflect/ClassTag$.apply:(Ljava/lang/Class;)Lscala/reflect/ClassTag;
  #155 = Utf8               updateAttachment
  #156 = Utf8               (Lscala/reflect/api/Trees$TreeApi;Ljava/lang/Object;Lscala/reflect/ClassTag;)Lscala/reflect/api/Trees$TreeApi;
  #157 = NameAndType        #155:#156     // updateAttachment:(Lscala/reflect/api/Trees$TreeApi;Ljava/lang/Object;Lscala/reflect/ClassTag;)Lscala/reflect/api/Trees$TreeApi;
  #158 = InterfaceMethodref #25.#157      // scala/reflect/macros/Internals$ContextInternalApi.updateAttachment:(Lscala/reflect/api/Trees$TreeApi;Ljava/lang/Object;Lscala/reflect/ClassTag;)Lscala/reflect/api/Trees$TreeApi;
  #159 = Utf8               scala/Tuple2
  #160 = Class              #159          // scala/Tuple2
  #161 = Utf8               scala/runtime/BoxesRunTime
  #162 = Class              #161          // scala/runtime/BoxesRunTime
  #163 = Utf8               boxToBoolean
  #164 = Utf8               (Z)Ljava/lang/Boolean;
  #165 = NameAndType        #163:#164     // boxToBoolean:(Z)Ljava/lang/Boolean;
  #166 = Methodref          #162.#165     // scala/runtime/BoxesRunTime.boxToBoolean:(Z)Ljava/lang/Boolean;
  #167 = Utf8               (Ljava/lang/Object;Ljava/lang/Object;)V
  #168 = NameAndType        #135:#167     // "<init>":(Ljava/lang/Object;Ljava/lang/Object;)V
  #169 = Methodref          #160.#168     // scala/Tuple2."<init>":(Ljava/lang/Object;Ljava/lang/Object;)V
  #170 = Utf8               scala/Some
  #171 = Class              #170          // scala/Some
  #172 = Utf8               value
  #173 = Utf8               ()Ljava/lang/Object;
  #174 = NameAndType        #172:#173     // value:()Ljava/lang/Object;
  #175 = Methodref          #171.#174     // scala/Some.value:()Ljava/lang/Object;
  #176 = Utf8               scala/MatchError
  #177 = Class              #176          // scala/MatchError
  #178 = Utf8               (Ljava/lang/Object;)V
  #179 = NameAndType        #135:#178     // "<init>":(Ljava/lang/Object;)V
  #180 = Methodref          #177.#179     // scala/MatchError."<init>":(Ljava/lang/Object;)V
  #181 = Utf8               _1
  #182 = NameAndType        #181:#173     // _1:()Ljava/lang/Object;
  #183 = Methodref          #160.#182     // scala/Tuple2._1:()Ljava/lang/Object;
  #184 = Utf8               _2$mcZ$sp
  #185 = Utf8               ()Z
  #186 = NameAndType        #184:#185     // _2$mcZ$sp:()Z
  #187 = Methodref          #160.#186     // scala/Tuple2._2$mcZ$sp:()Z
  #188 = Utf8               universe
  #189 = Utf8               ()Lscala/reflect/macros/Universe;
  #190 = NameAndType        #188:#189     // universe:()Lscala/reflect/macros/Universe;
  #191 = InterfaceMethodref #53.#190      // scala/reflect/macros/whitebox/Context.universe:()Lscala/reflect/macros/Universe;
  #192 = Utf8               scala/tools/nsc/Global
  #193 = Class              #192          // scala/tools/nsc/Global
  #194 = Utf8               analyzer
  #195 = Utf8               ()Lscala/tools/nsc/typechecker/Analyzer;
  #196 = NameAndType        #194:#195     // analyzer:()Lscala/tools/nsc/typechecker/Analyzer;
  #197 = Methodref          #193.#196     // scala/tools/nsc/Global.analyzer:()Lscala/tools/nsc/typechecker/Analyzer;
  #198 = Utf8               scala/tools/nsc/typechecker/Analyzer
  #199 = Class              #198          // scala/tools/nsc/typechecker/Analyzer
  #200 = Utf8               resetImplicits
  #201 = NameAndType        #200:#132     // resetImplicits:()V
  #202 = InterfaceMethodref #199.#201     // scala/tools/nsc/typechecker/Analyzer.resetImplicits:()V
  #203 = Utf8               State
  #204 = Utf8               ()Lshapeless/LazyMacros$DerivationContext$State$;
  #205 = NameAndType        #203:#204     // State:()Lshapeless/LazyMacros$DerivationContext$State$;
  #206 = Methodref          #30.#205      // shapeless/LazyMacros$DerivationContext.State:()Lshapeless/LazyMacros$DerivationContext$State$;
  #207 = Utf8               (Lscala/reflect/api/Types$TypeApi;ZLscala/Function2;)Lscala/reflect/api/Trees$TreeApi;
  #208 = NameAndType        #114:#207     // deriveInstance:(Lscala/reflect/api/Types$TypeApi;ZLscala/Function2;)Lscala/reflect/api/Trees$TreeApi;
  #209 = Methodref          #35.#208      // shapeless/LazyMacros$DerivationContext$State$.deriveInstance:(Lscala/reflect/api/Types$TypeApi;ZLscala/Function2;)Lscala/reflect/api/Trees$TreeApi;
  #210 = Utf8               removeAttachment
  #211 = Utf8               (Lscala/reflect/api/Trees$TreeApi;Lscala/reflect/ClassTag;)Lscala/reflect/api/Trees$TreeApi;
  #212 = NameAndType        #210:#211     // removeAttachment:(Lscala/reflect/api/Trees$TreeApi;Lscala/reflect/ClassTag;)Lscala/reflect/api/Trees$TreeApi;
  #213 = InterfaceMethodref #25.#212      // scala/reflect/macros/Internals$ContextInternalApi.removeAttachment:(Lscala/reflect/api/Trees$TreeApi;Lscala/reflect/ClassTag;)Lscala/reflect/api/Trees$TreeApi;
  #214 = Utf8               dc
  #215 = Utf8               Lshapeless/LazyMacros$DerivationContext;
  #216 = Utf8               root
  #217 = Utf8               Z
  #218 = Utf8               scala/Function2
  #219 = Class              #218          // scala/Function2
  #220 = Utf8               java/lang/Throwable
  #221 = Class              #220          // java/lang/Throwable
  #222 = Utf8               $anonfun$dcRef$1
  #223 = Utf8               (Lshapeless/LazyMacros;Lscala/reflect/macros/whitebox/Context;)Z
  #224 = Utf8               lm$1
  #225 = Utf8               x$1
  #226 = Utf8               enclosingPosition
  #227 = Utf8               ()Lscala/reflect/api/Position;
  #228 = NameAndType        #226:#227     // enclosingPosition:()Lscala/reflect/api/Position;
  #229 = InterfaceMethodref #53.#228      // scala/reflect/macros/whitebox/Context.enclosingPosition:()Lscala/reflect/api/Position;
  #230 = Utf8               Lscala/reflect/macros/whitebox/Context;
  #231 = Utf8               scala/reflect/api/Position
  #232 = Class              #231          // scala/reflect/api/Position
  #233 = Utf8               $anonfun$dcRef$2
  #234 = Utf8               (Lscala/reflect/macros/whitebox/Context;)Z
  #235 = Utf8               attachments
  #236 = Utf8               (Lscala/reflect/api/Trees$TreeApi;)Lscala/reflect/macros/Attachments;
  #237 = NameAndType        #235:#236     // attachments:(Lscala/reflect/api/Trees$TreeApi;)Lscala/reflect/macros/Attachments;
  #238 = InterfaceMethodref #25.#237      // scala/reflect/macros/Internals$ContextInternalApi.attachments:(Lscala/reflect/api/Trees$TreeApi;)Lscala/reflect/macros/Attachments;
  #239 = Utf8               scala/reflect/macros/Attachments
  #240 = Class              #239          // scala/reflect/macros/Attachments
  #241 = Utf8               contains
  #242 = Utf8               (Lscala/reflect/ClassTag;)Z
  #243 = NameAndType        #241:#242     // contains:(Lscala/reflect/ClassTag;)Z
  #244 = Methodref          #240.#243     // scala/reflect/macros/Attachments.contains:(Lscala/reflect/ClassTag;)Z
  #245 = Utf8               get
  #246 = Utf8               (Lscala/reflect/ClassTag;)Lscala/Option;
  #247 = NameAndType        #245:#246     // get:(Lscala/reflect/ClassTag;)Lscala/Option;
  #248 = Methodref          #240.#247     // scala/reflect/macros/Attachments.get:(Lscala/reflect/ClassTag;)Lscala/Option;
  #249 = Utf8               $init$
  #250 = Utf8               (Lshapeless/LazyMacrosCompat;)V
  #251 = NameAndType        #222:#223     // $anonfun$dcRef$1:(Lshapeless/LazyMacros;Lscala/reflect/macros/whitebox/Context;)Z
  #252 = InterfaceMethodref #2.#251       // shapeless/LazyMacrosCompat.$anonfun$dcRef$1:(Lshapeless/LazyMacros;Lscala/reflect/macros/whitebox/Context;)Z
  #253 = NameAndType        #233:#234     // $anonfun$dcRef$2:(Lscala/reflect/macros/whitebox/Context;)Z
  #254 = InterfaceMethodref #2.#253       // shapeless/LazyMacrosCompat.$anonfun$dcRef$2:(Lscala/reflect/macros/whitebox/Context;)Z
  #255 = Utf8               $deserializeLambda$
  #256 = Utf8               (Ljava/lang/invoke/SerializedLambda;)Ljava/lang/Object;
  #257 = Utf8               scala/runtime/LambdaDeserialize
  #258 = Class              #257          // scala/runtime/LambdaDeserialize
  #259 = Utf8               bootstrap
  #260 = Utf8               (Ljava/lang/invoke/MethodHandles$Lookup;Ljava/lang/String;Ljava/lang/invoke/MethodType;[Ljava/lang/invoke/MethodHandle;)Ljava/lang/invoke/CallSite;
  #261 = NameAndType        #259:#260     // bootstrap:(Ljava/lang/invoke/MethodHandles$Lookup;Ljava/lang/String;Ljava/lang/invoke/MethodType;[Ljava/lang/invoke/MethodHandle;)Ljava/lang/invoke/CallSite;
  #262 = Methodref          #258.#261     // scala/runtime/LambdaDeserialize.bootstrap:(Ljava/lang/invoke/MethodHandles$Lookup;Ljava/lang/String;Ljava/lang/invoke/MethodType;[Ljava/lang/invoke/MethodHandle;)Ljava/lang/invoke/CallSite;
  #263 = MethodHandle       6:#262        // REF_invokeStatic scala/runtime/LambdaDeserialize.bootstrap:(Ljava/lang/invoke/MethodHandles$Lookup;Ljava/lang/String;Ljava/lang/invoke/MethodType;[Ljava/lang/invoke/MethodHandle;)Ljava/lang/invoke/CallSite;
  #264 = Utf8               lambdaDeserialize
  #265 = NameAndType        #264:#256     // lambdaDeserialize:(Ljava/lang/invoke/SerializedLambda;)Ljava/lang/Object;
  #266 = InvokeDynamic      #3:#265       // #3:lambdaDeserialize:(Ljava/lang/invoke/SerializedLambda;)Ljava/lang/Object;
  #267 = Utf8               Code
  #268 = Utf8               LineNumberTable
  #269 = Utf8               LocalVariableTable
  #270 = Utf8               MethodParameters
  #271 = Utf8               Signature
  #272 = Utf8               StackMapTable
  #273 = Utf8               InnerClasses
  #274 = Utf8               SourceFile
  #275 = Utf8               RuntimeVisibleAnnotations
  #276 = Utf8               BootstrapMethods
  #277 = Utf8               ScalaInlineInfo
  #278 = Utf8               ScalaSig
{
  public static scala.Option dcRef$(shapeless.LazyMacrosCompat, shapeless.LazyMacros);
    descriptor: (Lshapeless/LazyMacrosCompat;Lshapeless/LazyMacros;)Lscala/Option;
    flags: (0x1009) ACC_PUBLIC, ACC_STATIC, ACC_SYNTHETIC
    Code:
      stack=2, locals=2, args_size=2
         0: aload_0
         1: aload_1
         2: invokespecial #44                 // InterfaceMethod dcRef:(Lshapeless/LazyMacros;)Lscala/Option;
         5: areturn
      LineNumberTable:
        line 22: 0
      LocalVariableTable:
        Start  Length  Slot  Name   Signature
            0       6     0 $this   Lshapeless/LazyMacrosCompat;
            0       6     1    lm   Lshapeless/LazyMacros;
    MethodParameters:
      Name                           Flags
      $this                          final synthetic
      lm                             final

  public default scala.Option<shapeless.LazyMacros$DerivationContext> dcRef(shapeless.LazyMacros);
    descriptor: (Lshapeless/LazyMacros;)Lscala/Option;
    flags: (0x0001) ACC_PUBLIC
    Code:
      stack=2, locals=2, args_size=2
         0: aload_1
         1: invokevirtual #51                 // Method shapeless/LazyMacros.c:()Lscala/reflect/macros/whitebox/Context;
         4: invokeinterface #57,  1           // InterfaceMethod scala/reflect/macros/whitebox/Context.openMacros:()Lscala/collection/immutable/List;
         9: aload_1
        10: invokedynamic #79,  0             // InvokeDynamic #0:apply:(Lshapeless/LazyMacros;)Lscala/Function1;
        15: invokevirtual #85                 // Method scala/collection/immutable/List.takeWhile:(Lscala/Function1;)Lscala/collection/immutable/List;
        18: invokedynamic #92,  0             // InvokeDynamic #1:apply:()Lscala/Function1;
        23: invokevirtual #96                 // Method scala/collection/immutable/List.find:(Lscala/Function1;)Lscala/Option;
        26: invokedynamic #103,  0            // InvokeDynamic #2:apply:()Lscala/Function1;
        31: invokevirtual #108                // Method scala/Option.flatMap:(Lscala/Function1;)Lscala/Option;
        34: areturn
      LineNumberTable:
        line 27: 0
        line 29: 18
        line 30: 26
      LocalVariableTable:
        Start  Length  Slot  Name   Signature
            0      35     0  this   Lshapeless/LazyMacrosCompat;
            0      35     1    lm   Lshapeless/LazyMacros;
    Signature: #47                          // (Lshapeless/LazyMacros;)Lscala/Option<Lshapeless/LazyMacros$DerivationContext;>;
    MethodParameters:
      Name                           Flags
      lm                             final

  public static scala.reflect.api.Trees$TreeApi deriveInstance$(shapeless.LazyMacrosCompat, shapeless.LazyMacros, scala.reflect.api.Types$TypeApi, scala.Function2);
    descriptor: (Lshapeless/LazyMacrosCompat;Lshapeless/LazyMacros;Lscala/reflect/api/Types$TypeApi;Lscala/Function2;)Lscala/reflect/api/Trees$TreeApi;
    flags: (0x1009) ACC_PUBLIC, ACC_STATIC, ACC_SYNTHETIC
    Code:
      stack=4, locals=4, args_size=4
         0: aload_0
         1: aload_1
         2: aload_2
         3: aload_3
         4: invokespecial #117                // InterfaceMethod deriveInstance:(Lshapeless/LazyMacros;Lscala/reflect/api/Types$TypeApi;Lscala/Function2;)Lscala/reflect/api/Trees$TreeApi;
         7: areturn
      LineNumberTable:
        line 33: 0
      LocalVariableTable:
        Start  Length  Slot  Name   Signature
            0       8     0 $this   Lshapeless/LazyMacrosCompat;
            0       8     1    lm   Lshapeless/LazyMacros;
            0       8     2   tpe   Lscala/reflect/api/Types$TypeApi;
            0       8     3 mkInst   Lscala/Function2;
    MethodParameters:
      Name                           Flags
      $this                          final synthetic
      lm                             final
      tpe                            final
      mkInst                         final

  public default scala.reflect.api.Trees$TreeApi deriveInstance(shapeless.LazyMacros, scala.reflect.api.Types$TypeApi, scala.Function2<scala.reflect.api.Trees$TreeApi, scala.reflect.api.Types$TypeApi, scala.reflect.api.Trees$TreeApi>);
    descriptor: (Lshapeless/LazyMacros;Lscala/reflect/api/Types$TypeApi;Lscala/Function2;)Lscala/reflect/api/Trees$TreeApi;
    flags: (0x0001) ACC_PUBLIC
    Code:
      stack=5, locals=19, args_size=4
         0: aload_2
         1: astore        6
         3: aload_3
         4: astore        7
         6: aload_0
         7: aload_1
         8: invokeinterface #44,  2           // InterfaceMethod dcRef:(Lshapeless/LazyMacros;)Lscala/Option;
        13: astore        10
        15: getstatic     #126                // Field scala/None$.MODULE$:Lscala/None$;
        18: aload         10
        20: invokevirtual #130                // Method java/lang/Object.equals:(Ljava/lang/Object;)Z
        23: ifeq          92
        26: aload_1
        27: invokevirtual #134                // Method shapeless/LazyMacros.resetAnnotation:()V
        30: new           #30                 // class shapeless/LazyMacros$DerivationContext
        33: dup
        34: aload_1
        35: invokespecial #138                // Method shapeless/LazyMacros$DerivationContext."<init>":(Lshapeless/LazyMacros;)V
        38: astore        11
        40: aload_1
        41: invokevirtual #51                 // Method shapeless/LazyMacros.c:()Lscala/reflect/macros/whitebox/Context;
        44: invokeinterface #142,  1          // InterfaceMethod scala/reflect/macros/whitebox/Context.internal:()Lscala/reflect/macros/Internals$ContextInternalApi;
        49: aload_1
        50: invokevirtual #51                 // Method shapeless/LazyMacros.c:()Lscala/reflect/macros/whitebox/Context;
        53: invokeinterface #146,  1          // InterfaceMethod scala/reflect/macros/whitebox/Context.macroApplication:()Lscala/reflect/api/Trees$TreeApi;
        58: aload         11
        60: getstatic     #151                // Field scala/reflect/ClassTag$.MODULE$:Lscala/reflect/ClassTag$;
        63: ldc           #30                 // class shapeless/LazyMacros$DerivationContext
        65: invokevirtual #154                // Method scala/reflect/ClassTag$.apply:(Ljava/lang/Class;)Lscala/reflect/ClassTag;
        68: invokeinterface #158,  4          // InterfaceMethod scala/reflect/macros/Internals$ContextInternalApi.updateAttachment:(Lscala/reflect/api/Trees$TreeApi;Ljava/lang/Object;Lscala/reflect/ClassTag;)Lscala/reflect/api/Trees$TreeApi;
        73: pop
        74: new           #160                // class scala/Tuple2
        77: dup
        78: aload         11
        80: iconst_1
        81: invokestatic  #166                // Method scala/runtime/BoxesRunTime.boxToBoolean:(Z)Ljava/lang/Boolean;
        84: invokespecial #169                // Method scala/Tuple2."<init>":(Ljava/lang/Object;Ljava/lang/Object;)V
        87: astore        5
        89: goto          151
        92: goto          95
        95: aload         10
        97: instanceof    #171                // class scala/Some
       100: ifeq          138
       103: aload         10
       105: checkcast     #171                // class scala/Some
       108: astore        12
       110: aload         12
       112: invokevirtual #175                // Method scala/Some.value:()Ljava/lang/Object;
       115: checkcast     #30                 // class shapeless/LazyMacros$DerivationContext
       118: astore        13
       120: new           #160                // class scala/Tuple2
       123: dup
       124: aload         13
       126: iconst_0
       127: invokestatic  #166                // Method scala/runtime/BoxesRunTime.boxToBoolean:(Z)Ljava/lang/Boolean;
       130: invokespecial #169                // Method scala/Tuple2."<init>":(Ljava/lang/Object;Ljava/lang/Object;)V
       133: astore        5
       135: goto          151
       138: goto          141
       141: new           #177                // class scala/MatchError
       144: dup
       145: aload         10
       147: invokespecial #180                // Method scala/MatchError."<init>":(Ljava/lang/Object;)V
       150: athrow
       151: aload         5
       153: astore        9
       155: aload         9
       157: ifnull        196
       160: aload         9
       162: invokevirtual #183                // Method scala/Tuple2._1:()Ljava/lang/Object;
       165: checkcast     #30                 // class shapeless/LazyMacros$DerivationContext
       168: astore        14
       170: aload         9
       172: invokevirtual #187                // Method scala/Tuple2._2$mcZ$sp:()Z
       175: istore        15
       177: new           #160                // class scala/Tuple2
       180: dup
       181: aload         14
       183: iload         15
       185: invokestatic  #166                // Method scala/runtime/BoxesRunTime.boxToBoolean:(Z)Ljava/lang/Boolean;
       188: invokespecial #169                // Method scala/Tuple2."<init>":(Ljava/lang/Object;Ljava/lang/Object;)V
       191: astore        4
       193: goto          209
       196: goto          199
       199: new           #177                // class scala/MatchError
       202: dup
       203: aload         9
       205: invokespecial #180                // Method scala/MatchError."<init>":(Ljava/lang/Object;)V
       208: athrow
       209: aload         4
       211: astore        8
       213: aload         8
       215: invokevirtual #183                // Method scala/Tuple2._1:()Ljava/lang/Object;
       218: checkcast     #30                 // class shapeless/LazyMacros$DerivationContext
       221: astore        16
       223: aload         8
       225: invokevirtual #187                // Method scala/Tuple2._2$mcZ$sp:()Z
       228: istore        17
       230: iload         17
       232: ifeq          258
       235: aload_1
       236: invokevirtual #51                 // Method shapeless/LazyMacros.c:()Lscala/reflect/macros/whitebox/Context;
       239: invokeinterface #191,  1          // InterfaceMethod scala/reflect/macros/whitebox/Context.universe:()Lscala/reflect/macros/Universe;
       244: checkcast     #193                // class scala/tools/nsc/Global
       247: invokevirtual #197                // Method scala/tools/nsc/Global.analyzer:()Lscala/tools/nsc/typechecker/Analyzer;
       250: invokeinterface #202,  1          // InterfaceMethod scala/tools/nsc/typechecker/Analyzer.resetImplicits:()V
       255: goto          258
       258: aload         16
       260: invokevirtual #206                // Method shapeless/LazyMacros$DerivationContext.State:()Lshapeless/LazyMacros$DerivationContext$State$;
       263: aload         6
       265: iload         17
       267: aload         7
       269: invokevirtual #209                // Method shapeless/LazyMacros$DerivationContext$State$.deriveInstance:(Lscala/reflect/api/Types$TypeApi;ZLscala/Function2;)Lscala/reflect/api/Trees$TreeApi;
       272: goto          320
       275: astore        18
       277: iload         17
       279: ifeq          317
       282: aload_1
       283: invokevirtual #51                 // Method shapeless/LazyMacros.c:()Lscala/reflect/macros/whitebox/Context;
       286: invokeinterface #142,  1          // InterfaceMethod scala/reflect/macros/whitebox/Context.internal:()Lscala/reflect/macros/Internals$ContextInternalApi;
       291: aload_1
       292: invokevirtual #51                 // Method shapeless/LazyMacros.c:()Lscala/reflect/macros/whitebox/Context;
       295: invokeinterface #146,  1          // InterfaceMethod scala/reflect/macros/whitebox/Context.macroApplication:()Lscala/reflect/api/Trees$TreeApi;
       300: getstatic     #151                // Field scala/reflect/ClassTag$.MODULE$:Lscala/reflect/ClassTag$;
       303: ldc           #30                 // class shapeless/LazyMacros$DerivationContext
       305: invokevirtual #154                // Method scala/reflect/ClassTag$.apply:(Ljava/lang/Class;)Lscala/reflect/ClassTag;
       308: invokeinterface #213,  3          // InterfaceMethod scala/reflect/macros/Internals$ContextInternalApi.removeAttachment:(Lscala/reflect/api/Trees$TreeApi;Lscala/reflect/ClassTag;)Lscala/reflect/api/Trees$TreeApi;
       313: pop
       314: goto          317
       317: aload         18
       319: athrow
       320: iload         17
       322: ifeq          360
       325: aload_1
       326: invokevirtual #51                 // Method shapeless/LazyMacros.c:()Lscala/reflect/macros/whitebox/Context;
       329: invokeinterface #142,  1          // InterfaceMethod scala/reflect/macros/whitebox/Context.internal:()Lscala/reflect/macros/Internals$ContextInternalApi;
       334: aload_1
       335: invokevirtual #51                 // Method shapeless/LazyMacros.c:()Lscala/reflect/macros/whitebox/Context;
       338: invokeinterface #146,  1          // InterfaceMethod scala/reflect/macros/whitebox/Context.macroApplication:()Lscala/reflect/api/Trees$TreeApi;
       343: getstatic     #151                // Field scala/reflect/ClassTag$.MODULE$:Lscala/reflect/ClassTag$;
       346: ldc           #30                 // class shapeless/LazyMacros$DerivationContext
       348: invokevirtual #154                // Method scala/reflect/ClassTag$.apply:(Ljava/lang/Class;)Lscala/reflect/ClassTag;
       351: invokeinterface #213,  3          // InterfaceMethod scala/reflect/macros/Internals$ContextInternalApi.removeAttachment:(Lscala/reflect/api/Trees$TreeApi;Lscala/reflect/ClassTag;)Lscala/reflect/api/Trees$TreeApi;
       356: pop
       357: goto          360
       360: areturn
      Exception table:
         from    to  target type
           258   275   275   any
      StackMapTable: number_of_entries = 13
        frame_type = 255 /* full_frame */
          offset_delta = 92
          locals = [ class shapeless/LazyMacrosCompat, class shapeless/LazyMacros, class scala/reflect/api/Types$TypeApi, class scala/Function2, top, top, class scala/reflect/api/Types$TypeApi, class scala/Function2, top, top, class scala/Option ]
          stack = []
        frame_type = 2 /* same */
        frame_type = 42 /* same */
        frame_type = 2 /* same */
        frame_type = 255 /* full_frame */
          offset_delta = 9
          locals = [ class shapeless/LazyMacrosCompat, class shapeless/LazyMacros, class scala/reflect/api/Types$TypeApi, class scala/Function2, top, class scala/Tuple2, class scala/reflect/api/Types$TypeApi, class scala/Function2, top, top, class scala/Option ]
          stack = []
        frame_type = 255 /* full_frame */
          offset_delta = 44
          locals = [ class shapeless/LazyMacrosCompat, class shapeless/LazyMacros, class scala/reflect/api/Types$TypeApi, class scala/Function2, top, class scala/Tuple2, class scala/reflect/api/Types$TypeApi, class scala/Function2, top, class scala/Tuple2, class scala/Option ]
          stack = []
        frame_type = 2 /* same */
        frame_type = 255 /* full_frame */
          offset_delta = 9
          locals = [ class shapeless/LazyMacrosCompat, class shapeless/LazyMacros, class scala/reflect/api/Types$TypeApi, class scala/Function2, class scala/Tuple2, class scala/Tuple2, class scala/reflect/api/Types$TypeApi, class scala/Function2, top, class scala/Tuple2, class scala/Option, top, top, top, class shapeless/LazyMacros$DerivationContext, int ]
          stack = []
        frame_type = 255 /* full_frame */
          offset_delta = 48
          locals = [ class shapeless/LazyMacrosCompat, class shapeless/LazyMacros, class scala/reflect/api/Types$TypeApi, class scala/Function2, class scala/Tuple2, class scala/Tuple2, class scala/reflect/api/Types$TypeApi, class scala/Function2, class scala/Tuple2, class scala/Tuple2, class scala/Option, top, top, top, class shapeless/LazyMacros$DerivationContext, int, class shapeless/LazyMacros$DerivationContext, int ]
          stack = []
        frame_type = 80 /* same_locals_1_stack_item */
          stack = [ class java/lang/Throwable ]
        frame_type = 252 /* append */
          offset_delta = 41
          locals = [ class java/lang/Throwable ]
        frame_type = 255 /* full_frame */
          offset_delta = 2
          locals = [ class shapeless/LazyMacrosCompat, class shapeless/LazyMacros, class scala/reflect/api/Types$TypeApi, class scala/Function2, class scala/Tuple2, class scala/Tuple2, class scala/reflect/api/Types$TypeApi, class scala/Function2, class scala/Tuple2, class scala/Tuple2, class scala/Option, top, top, top, class shapeless/LazyMacros$DerivationContext, int, class shapeless/LazyMacros$DerivationContext, int ]
          stack = [ class scala/reflect/api/Trees$TreeApi ]
        frame_type = 103 /* same_locals_1_stack_item */
          stack = [ class scala/reflect/api/Trees$TreeApi ]
      LineNumberTable:
        line 33: 0
        line 35: 6
        line 36: 15
        line 37: 26
        line 38: 30
        line 39: 40
        line 40: 74
        line 36: 92
        line 41: 95
        line 42: 120
        line 41: 138
        line 35: 141
        line 34: 155
        line 35: 199
        line 34: 213
        line 45: 230
        line 47: 235
        line 50: 258
        line 52: 277
        line 53: 282
        line 52: 317
        line 53: 325
        line 52: 360
      LocalVariableTable:
        Start  Length  Slot  Name   Signature
           38      49    11    dc   Lshapeless/LazyMacros$DerivationContext;
          118      20    13    dc   Lshapeless/LazyMacros$DerivationContext;
          168      28    14    dc   Lshapeless/LazyMacros$DerivationContext;
          175      21    15  root   Z
          221     139    16    dc   Lshapeless/LazyMacros$DerivationContext;
          228     132    17  root   Z
            0     361     0  this   Lshapeless/LazyMacrosCompat;
            0     361     1    lm   Lshapeless/LazyMacros;
            0     361     2   tpe   Lscala/reflect/api/Types$TypeApi;
            0     361     3 mkInst   Lscala/Function2;
    Signature: #120                         // (Lshapeless/LazyMacros;Lscala/reflect/api/Types$TypeApi;Lscala/Function2<Lscala/reflect/api/Trees$TreeApi;Lscala/reflect/api/Types$TypeApi;Lscala/reflect/api/Trees$TreeApi;>;)Lscala/reflect/api/Trees$TreeApi;
    MethodParameters:
      Name                           Flags
      lm                             final
      tpe                            final
      mkInst                         final

  public static boolean $anonfun$dcRef$1(shapeless.LazyMacros, scala.reflect.macros.whitebox.Context);
    descriptor: (Lshapeless/LazyMacros;Lscala/reflect/macros/whitebox/Context;)Z
    flags: (0x1009) ACC_PUBLIC, ACC_STATIC, ACC_SYNTHETIC
    Code:
      stack=2, locals=3, args_size=2
         0: aload_1
         1: invokeinterface #229,  1          // InterfaceMethod scala/reflect/macros/whitebox/Context.enclosingPosition:()Lscala/reflect/api/Position;
         6: aload_0
         7: invokevirtual #51                 // Method shapeless/LazyMacros.c:()Lscala/reflect/macros/whitebox/Context;
        10: invokeinterface #229,  1          // InterfaceMethod scala/reflect/macros/whitebox/Context.enclosingPosition:()Lscala/reflect/api/Position;
        15: astore_2
        16: dup
        17: ifnonnull     28
        20: pop
        21: aload_2
        22: ifnull        35
        25: goto          39
        28: aload_2
        29: invokevirtual #130                // Method java/lang/Object.equals:(Ljava/lang/Object;)Z
        32: ifeq          39
        35: iconst_1
        36: goto          40
        39: iconst_0
        40: ireturn
      StackMapTable: number_of_entries = 4
        frame_type = 255 /* full_frame */
          offset_delta = 28
          locals = [ class shapeless/LazyMacros, class scala/reflect/macros/whitebox/Context, class scala/reflect/api/Position ]
          stack = [ class scala/reflect/api/Position ]
        frame_type = 6 /* same */
        frame_type = 3 /* same */
        frame_type = 64 /* same_locals_1_stack_item */
          stack = [ int ]
      LineNumberTable:
        line 27: 0
      LocalVariableTable:
        Start  Length  Slot  Name   Signature
            0      41     0  lm$1   Lshapeless/LazyMacros;
            0      41     1   x$1   Lscala/reflect/macros/whitebox/Context;
    MethodParameters:
      Name                           Flags
      lm$1                           final
      x$1                            final

  public static boolean $anonfun$dcRef$2(scala.reflect.macros.whitebox.Context);
    descriptor: (Lscala/reflect/macros/whitebox/Context;)Z
    flags: (0x1009) ACC_PUBLIC, ACC_STATIC, ACC_SYNTHETIC
    Code:
      stack=3, locals=1, args_size=1
         0: aload_0
         1: invokeinterface #142,  1          // InterfaceMethod scala/reflect/macros/whitebox/Context.internal:()Lscala/reflect/macros/Internals$ContextInternalApi;
         6: aload_0
         7: invokeinterface #146,  1          // InterfaceMethod scala/reflect/macros/whitebox/Context.macroApplication:()Lscala/reflect/api/Trees$TreeApi;
        12: invokeinterface #238,  2          // InterfaceMethod scala/reflect/macros/Internals$ContextInternalApi.attachments:(Lscala/reflect/api/Trees$TreeApi;)Lscala/reflect/macros/Attachments;
        17: getstatic     #151                // Field scala/reflect/ClassTag$.MODULE$:Lscala/reflect/ClassTag$;
        20: ldc           #30                 // class shapeless/LazyMacros$DerivationContext
        22: invokevirtual #154                // Method scala/reflect/ClassTag$.apply:(Ljava/lang/Class;)Lscala/reflect/ClassTag;
        25: invokevirtual #244                // Method scala/reflect/macros/Attachments.contains:(Lscala/reflect/ClassTag;)Z
        28: ireturn
      LineNumberTable:
        line 29: 0
      LocalVariableTable:
        Start  Length  Slot  Name   Signature
            0      29     0     c   Lscala/reflect/macros/whitebox/Context;
    MethodParameters:
      Name                           Flags
      c                              final

  public static scala.Option $anonfun$dcRef$3(scala.reflect.macros.whitebox.Context);
    descriptor: (Lscala/reflect/macros/whitebox/Context;)Lscala/Option;
    flags: (0x1009) ACC_PUBLIC, ACC_STATIC, ACC_SYNTHETIC
    Code:
      stack=3, locals=1, args_size=1
         0: aload_0
         1: invokeinterface #142,  1          // InterfaceMethod scala/reflect/macros/whitebox/Context.internal:()Lscala/reflect/macros/Internals$ContextInternalApi;
         6: aload_0
         7: invokeinterface #146,  1          // InterfaceMethod scala/reflect/macros/whitebox/Context.macroApplication:()Lscala/reflect/api/Trees$TreeApi;
        12: invokeinterface #238,  2          // InterfaceMethod scala/reflect/macros/Internals$ContextInternalApi.attachments:(Lscala/reflect/api/Trees$TreeApi;)Lscala/reflect/macros/Attachments;
        17: getstatic     #151                // Field scala/reflect/ClassTag$.MODULE$:Lscala/reflect/ClassTag$;
        20: ldc           #30                 // class shapeless/LazyMacros$DerivationContext
        22: invokevirtual #154                // Method scala/reflect/ClassTag$.apply:(Ljava/lang/Class;)Lscala/reflect/ClassTag;
        25: invokevirtual #248                // Method scala/reflect/macros/Attachments.get:(Lscala/reflect/ClassTag;)Lscala/Option;
        28: areturn
      LineNumberTable:
        line 30: 0
      LocalVariableTable:
        Start  Length  Slot  Name   Signature
            0      29     0     c   Lscala/reflect/macros/whitebox/Context;
    MethodParameters:
      Name                           Flags
      c                              final

  public static void $init$(shapeless.LazyMacrosCompat);
    descriptor: (Lshapeless/LazyMacrosCompat;)V
    flags: (0x0009) ACC_PUBLIC, ACC_STATIC
    Code:
      stack=0, locals=1, args_size=1
         0: return
      LineNumberTable:
        line 21: 0
      LocalVariableTable:
        Start  Length  Slot  Name   Signature
            0       1     0 $this   Lshapeless/LazyMacrosCompat;
    MethodParameters:
      Name                           Flags
      $this                          final synthetic

  public static java.lang.Object $anonfun$dcRef$1$adapted(shapeless.LazyMacros, scala.reflect.macros.whitebox.Context);
    descriptor: (Lshapeless/LazyMacros;Lscala/reflect/macros/whitebox/Context;)Ljava/lang/Object;
    flags: (0x1009) ACC_PUBLIC, ACC_STATIC, ACC_SYNTHETIC
    Code:
      stack=2, locals=2, args_size=2
         0: aload_0
         1: aload_1
         2: invokestatic  #252                // InterfaceMethod $anonfun$dcRef$1:(Lshapeless/LazyMacros;Lscala/reflect/macros/whitebox/Context;)Z
         5: invokestatic  #166                // Method scala/runtime/BoxesRunTime.boxToBoolean:(Z)Ljava/lang/Boolean;
         8: areturn
      LineNumberTable:
        line 27: 0
      LocalVariableTable:
        Start  Length  Slot  Name   Signature
            0       9     0  lm$1   Lshapeless/LazyMacros;
            0       9     1   x$1   Lscala/reflect/macros/whitebox/Context;
    MethodParameters:
      Name                           Flags
      lm$1                           final
      x$1                            final

  public static java.lang.Object $anonfun$dcRef$2$adapted(scala.reflect.macros.whitebox.Context);
    descriptor: (Lscala/reflect/macros/whitebox/Context;)Ljava/lang/Object;
    flags: (0x1009) ACC_PUBLIC, ACC_STATIC, ACC_SYNTHETIC
    Code:
      stack=1, locals=1, args_size=1
         0: aload_0
         1: invokestatic  #254                // InterfaceMethod $anonfun$dcRef$2:(Lscala/reflect/macros/whitebox/Context;)Z
         4: invokestatic  #166                // Method scala/runtime/BoxesRunTime.boxToBoolean:(Z)Ljava/lang/Boolean;
         7: areturn
      LineNumberTable:
        line 29: 0
      LocalVariableTable:
        Start  Length  Slot  Name   Signature
            0       8     0     c   Lscala/reflect/macros/whitebox/Context;
    MethodParameters:
      Name                           Flags
      c                              final

  private static java.lang.Object $deserializeLambda$(java.lang.invoke.SerializedLambda);
    descriptor: (Ljava/lang/invoke/SerializedLambda;)Ljava/lang/Object;
    flags: (0x100a) ACC_PRIVATE, ACC_STATIC, ACC_SYNTHETIC
    Code:
      stack=1, locals=1, args_size=1
         0: aload_0
         1: invokedynamic #266,  0            // InvokeDynamic #3:lambdaDeserialize:(Ljava/lang/invoke/SerializedLambda;)Ljava/lang/Object;
         6: areturn
}
InnerClasses:
  public static final #13= #10 of #12;    // Lookup=class java/lang/invoke/MethodHandles$Lookup of class java/lang/invoke/MethodHandles
  public #18= #15 of #17;                 // TreeApi=class scala/reflect/api/Trees$TreeApi of class scala/reflect/api/Trees
  public abstract #23= #20 of #22;        // TypeApi=class scala/reflect/api/Types$TypeApi of class scala/reflect/api/Types
  public #28= #25 of #27;                 // ContextInternalApi=class scala/reflect/macros/Internals$ContextInternalApi of class scala/reflect/macros/Internals
  public #33= #30 of #32;                 // DerivationContext=class shapeless/LazyMacros$DerivationContext of class shapeless/LazyMacros
  public #36= #35 of #30;                 // State$=class shapeless/LazyMacros$DerivationContext$State$ of class shapeless/LazyMacros$DerivationContext
SourceFile: "lazymacros.scala"
RuntimeVisibleAnnotations:
  0: #6(#7=s#8)
    scala.reflect.ScalaSignature(
      bytes="\u0006\u0005y2q\u0001B\u0003\u0011\u0002\u0007\u0005\u0001\u0002C\u0003\u0010\u0001\u0011\u0005\u0001\u0003C\u0003\u0015\u0001\u0011\u0005Q\u0003C\u0003#\u0001\u0011\u00051E\u0001\tMCjLX*Y2s_N\u001cu.\u001c9bi*\ta!A\u0005tQ\u0006\u0004X\r\\3tg\u000e\u00011C\u0001\u0001\n!\tQQ\"D\u0001\f\u0015\u0005a\u0011!B:dC2\f\u0017B\u0001\b\f\u0005\u0019\te.\u001f*fM\u00061A%\u001b8ji\u0012\"\u0012!\u0005\t\u0003\u0015II!aE\u0006\u0003\tUs\u0017\u000e^\u0001\u0006I\u000e\u0014VM\u001a\u000b\u0003-\u0001\u00022AC\f\u001a\u0013\tA2B\u0001\u0004PaRLwN\u001c\t\u00035y\u0001\"a\u0007\u000f\u000e\u0003\u0015I!!H\u0003\u0003\u00151\u000b\'0_\'bGJ|7/\u0003\u0002 9\t\tB)\u001a:jm\u0006$\u0018n\u001c8D_:$X\r\u001f;\t\u000b\u0005\u0012\u0001\u0019\u0001\u000e\u0002\u00051l\u0017A\u00043fe&4X-\u00138ti\u0006t7-\u001a\u000b\u0003I%\"2!\n\u001b:!\t1CF\u0004\u0002(U9\u0011\u0001&\u000b\u0007\u0001\u0011\u0015\t3\u00011\u0001\u001b\u0013\tYC$A\u0001d\u0013\ticF\u0001\u0003Ue\u0016,\u0017BA\u00181\u0005\u001d\tE.[1tKNT!!\r\u001a\u0002\r5\f7M]8t\u0015\t\u00194\"A\u0004sK\u001adWm\u0019;\t\u000bU\u001a\u0001\u0019\u0001\u001c\u0002\u0007Q\u0004X\r\u0005\u0002\'o%\u0011\u0001H\f\u0002\u0005)f\u0004X\rC\u0003;\u0007\u0001\u00071(\u0001\u0004nW&s7\u000f\u001e\t\u0006\u0015q*c\'J\u0005\u0003{-\u0011\u0011BR;oGRLwN\u001c\u001a"
    )
BootstrapMethods:
  0: #75 REF_invokeStatic java/lang/invoke/LambdaMetafactory.altMetafactory:(Ljava/lang/invoke/MethodHandles$Lookup;Ljava/lang/String;Ljava/lang/invoke/MethodType;[Ljava/lang/Object;)Ljava/lang/invoke/CallSite;
    Method arguments:
      #59 (Ljava/lang/Object;)Ljava/lang/Object;
      #64 REF_invokeStatic shapeless/LazyMacrosCompat.$anonfun$dcRef$1$adapted:(Lshapeless/LazyMacros;Lscala/reflect/macros/whitebox/Context;)Ljava/lang/Object;
      #66 (Lscala/reflect/macros/whitebox/Context;)Ljava/lang/Object;
      #67 5
      #68 1
      #66 (Lscala/reflect/macros/whitebox/Context;)Ljava/lang/Object;
  1: #75 REF_invokeStatic java/lang/invoke/LambdaMetafactory.altMetafactory:(Ljava/lang/invoke/MethodHandles$Lookup;Ljava/lang/String;Ljava/lang/invoke/MethodType;[Ljava/lang/Object;)Ljava/lang/invoke/CallSite;
    Method arguments:
      #59 (Ljava/lang/Object;)Ljava/lang/Object;
      #89 REF_invokeStatic shapeless/LazyMacrosCompat.$anonfun$dcRef$2$adapted:(Lscala/reflect/macros/whitebox/Context;)Ljava/lang/Object;
      #66 (Lscala/reflect/macros/whitebox/Context;)Ljava/lang/Object;
      #67 5
      #68 1
      #66 (Lscala/reflect/macros/whitebox/Context;)Ljava/lang/Object;
  2: #75 REF_invokeStatic java/lang/invoke/LambdaMetafactory.altMetafactory:(Ljava/lang/invoke/MethodHandles$Lookup;Ljava/lang/String;Ljava/lang/invoke/MethodType;[Ljava/lang/Object;)Ljava/lang/invoke/CallSite;
    Method arguments:
      #59 (Ljava/lang/Object;)Ljava/lang/Object;
      #101 REF_invokeStatic shapeless/LazyMacrosCompat.$anonfun$dcRef$3:(Lscala/reflect/macros/whitebox/Context;)Lscala/Option;
      #102 (Lscala/reflect/macros/whitebox/Context;)Lscala/Option;
      #67 5
      #68 1
      #102 (Lscala/reflect/macros/whitebox/Context;)Lscala/Option;
  3: #263 REF_invokeStatic scala/runtime/LambdaDeserialize.bootstrap:(Ljava/lang/invoke/MethodHandles$Lookup;Ljava/lang/String;Ljava/lang/invoke/MethodType;[Ljava/lang/invoke/MethodHandle;)Ljava/lang/invoke/CallSite;
    Method arguments:
      #64 REF_invokeStatic shapeless/LazyMacrosCompat.$anonfun$dcRef$1$adapted:(Lshapeless/LazyMacros;Lscala/reflect/macros/whitebox/Context;)Ljava/lang/Object;
      #89 REF_invokeStatic shapeless/LazyMacrosCompat.$anonfun$dcRef$2$adapted:(Lscala/reflect/macros/whitebox/Context;)Ljava/lang/Object;
      #101 REF_invokeStatic shapeless/LazyMacrosCompat.$anonfun$dcRef$3:(Lscala/reflect/macros/whitebox/Context;)Lscala/Option;
  ScalaInlineInfo: length = 0x36 (unknown attribute)
   01 00 00 0A 00 3C 00 3D 01 00 DE 00 DF 01 00 56
   00 41 01 00 E9 00 EA 01 00 61 00 62 01 00 F9 00
   FA 01 00 25 00 26 01 00 29 00 2A 00 00 6E 00 6F
   01 00 72 00 73 00
  ScalaSig: length = 0x3 (unknown attribute)
   05 02 00
