Classfile /Users/mw/Projects/slang-braindump/.jar/jar8/assemble/slang-braindump/assemble/content/shapeless/LazyMacros$DerivationContext$State.class
  Last modified May 29, 2022; size 15685 bytes
  SHA-256 checksum cf87ada98695acf4a71a5a365b87287fd925b5e879c1a8f6167a52cdeef2c771
  Compiled from "lazy.scala"
public class shapeless.LazyMacros$DerivationContext$State implements scala.Product,java.io.Serializable
  minor version: 0
  major version: 52
  flags: (0x0021) ACC_PUBLIC, ACC_SUPER
  this_class: #2                          // shapeless/LazyMacros$DerivationContext$State
  super_class: #4                         // java/lang/Object
  interfaces: 2, fields: 5, methods: 33, attributes: 5
Constant pool:
    #1 = Utf8               shapeless/LazyMacros$DerivationContext$State
    #2 = Class              #1            // shapeless/LazyMacros$DerivationContext$State
    #3 = Utf8               java/lang/Object
    #4 = Class              #3            // java/lang/Object
    #5 = Utf8               scala/Product
    #6 = Class              #5            // scala/Product
    #7 = Utf8               java/io/Serializable
    #8 = Class              #7            // java/io/Serializable
    #9 = Utf8               lazy.scala
   #10 = Utf8               java/lang/invoke/MethodHandles$Lookup
   #11 = Class              #10           // java/lang/invoke/MethodHandles$Lookup
   #12 = Utf8               java/lang/invoke/MethodHandles
   #13 = Class              #12           // java/lang/invoke/MethodHandles
   #14 = Utf8               Lookup
   #15 = Utf8               scala/reflect/api/Names$TermNameApi
   #16 = Class              #15           // scala/reflect/api/Names$TermNameApi
   #17 = Utf8               scala/reflect/api/Names
   #18 = Class              #17           // scala/reflect/api/Names
   #19 = Utf8               TermNameApi
   #20 = Utf8               scala/reflect/api/Symbols$SymbolApi
   #21 = Class              #20           // scala/reflect/api/Symbols$SymbolApi
   #22 = Utf8               scala/reflect/api/Symbols
   #23 = Class              #22           // scala/reflect/api/Symbols
   #24 = Utf8               SymbolApi
   #25 = Utf8               scala/reflect/api/Trees$TreeApi
   #26 = Class              #25           // scala/reflect/api/Trees$TreeApi
   #27 = Utf8               scala/reflect/api/Trees
   #28 = Class              #27           // scala/reflect/api/Trees
   #29 = Utf8               TreeApi
   #30 = Utf8               scala/reflect/api/Types$TypeApi
   #31 = Class              #30           // scala/reflect/api/Types$TypeApi
   #32 = Utf8               scala/reflect/api/Types
   #33 = Class              #32           // scala/reflect/api/Types
   #34 = Utf8               TypeApi
   #35 = Utf8               scala/reflect/macros/Internals$ContextInternalApi
   #36 = Class              #35           // scala/reflect/macros/Internals$ContextInternalApi
   #37 = Utf8               scala/reflect/macros/Internals
   #38 = Class              #37           // scala/reflect/macros/Internals
   #39 = Utf8               ContextInternalApi
   #40 = Utf8               shapeless/LazyMacros$DerivationContext
   #41 = Class              #40           // shapeless/LazyMacros$DerivationContext
   #42 = Utf8               shapeless/LazyMacros
   #43 = Class              #42           // shapeless/LazyMacros
   #44 = Utf8               DerivationContext
   #45 = Utf8               State
   #46 = Utf8               shapeless/LazyMacros$LazyDefinitions
   #47 = Class              #46           // shapeless/LazyMacros$LazyDefinitions
   #48 = Utf8               LazyDefinitions
   #49 = Utf8               shapeless/LazyMacros$LazyDefinitions$Instance
   #50 = Class              #49           // shapeless/LazyMacros$LazyDefinitions$Instance
   #51 = Utf8               Instance
   #52 = Utf8               shapeless/LazyMacros$LazyDefinitions$Instance$
   #53 = Class              #52           // shapeless/LazyMacros$LazyDefinitions$Instance$
   #54 = Utf8               Instance$
   #55 = Utf8               shapeless/LazyMacros$LazyDefinitions$TypeWrapper
   #56 = Class              #55           // shapeless/LazyMacros$LazyDefinitions$TypeWrapper
   #57 = Utf8               TypeWrapper
   #58 = Utf8               shapeless/LazyMacros$LazyDefinitions$TypeWrapper$
   #59 = Class              #58           // shapeless/LazyMacros$LazyDefinitions$TypeWrapper$
   #60 = Utf8               TypeWrapper$
   #61 = Utf8               name
   #62 = Utf8               Ljava/lang/String;
   #63 = Utf8               dict
   #64 = Utf8               Lscala/collection/immutable/ListMap;
   #65 = Utf8               Lscala/collection/immutable/ListMap<Lshapeless/LazyMacros$LazyDefinitions$TypeWrapper;Lshapeless/LazyMacros$LazyDefinitions$Instance;>;
   #66 = Utf8               open
   #67 = Utf8               Lscala/collection/immutable/List;
   #68 = Utf8               Lscala/collection/immutable/List<Lshapeless/LazyMacros$LazyDefinitions$Instance;>;
   #69 = Utf8               prevent
   #70 = Utf8               Lscala/collection/immutable/List<Lshapeless/LazyMacros$LazyDefinitions$TypeWrapper;>;
   #71 = Utf8               $outer
   #72 = Utf8               Lshapeless/LazyMacros$DerivationContext;
   #73 = Utf8               productElementNames
   #74 = Utf8               ()Lscala/collection/Iterator;
   #75 = Utf8               ()Lscala/collection/Iterator<Ljava/lang/String;>;
   #76 = Utf8               productElementNames$
   #77 = Utf8               (Lscala/Product;)Lscala/collection/Iterator;
   #78 = NameAndType        #76:#77       // productElementNames$:(Lscala/Product;)Lscala/collection/Iterator;
   #79 = InterfaceMethodref #6.#78        // scala/Product.productElementNames$:(Lscala/Product;)Lscala/collection/Iterator;
   #80 = Utf8               this
   #81 = Utf8               Lshapeless/LazyMacros$DerivationContext$State;
   #82 = Utf8               ()Ljava/lang/String;
   #83 = NameAndType        #61:#62       // name:Ljava/lang/String;
   #84 = Fieldref           #2.#83        // shapeless/LazyMacros$DerivationContext$State.name:Ljava/lang/String;
   #85 = Utf8               ()Lscala/collection/immutable/ListMap;
   #86 = Utf8               ()Lscala/collection/immutable/ListMap<Lshapeless/LazyMacros$LazyDefinitions$TypeWrapper;Lshapeless/LazyMacros$LazyDefinitions$Instance;>;
   #87 = NameAndType        #63:#64       // dict:Lscala/collection/immutable/ListMap;
   #88 = Fieldref           #2.#87        // shapeless/LazyMacros$DerivationContext$State.dict:Lscala/collection/immutable/ListMap;
   #89 = Utf8               ()Lscala/collection/immutable/List;
   #90 = Utf8               ()Lscala/collection/immutable/List<Lshapeless/LazyMacros$LazyDefinitions$Instance;>;
   #91 = NameAndType        #66:#67       // open:Lscala/collection/immutable/List;
   #92 = Fieldref           #2.#91        // shapeless/LazyMacros$DerivationContext$State.open:Lscala/collection/immutable/List;
   #93 = Utf8               ()Lscala/collection/immutable/List<Lshapeless/LazyMacros$LazyDefinitions$TypeWrapper;>;
   #94 = NameAndType        #69:#67       // prevent:Lscala/collection/immutable/List;
   #95 = Fieldref           #2.#94        // shapeless/LazyMacros$DerivationContext$State.prevent:Lscala/collection/immutable/List;
   #96 = Utf8               addDependency
   #97 = Utf8               (Lscala/reflect/api/Types$TypeApi;)Lshapeless/LazyMacros$DerivationContext$State;
   #98 = Utf8               tpe
   #99 = NameAndType        #66:#89       // open:()Lscala/collection/immutable/List;
  #100 = Methodref          #2.#99        // shapeless/LazyMacros$DerivationContext$State.open:()Lscala/collection/immutable/List;
  #101 = Utf8               scala/collection/immutable/Nil$
  #102 = Class              #101          // scala/collection/immutable/Nil$
  #103 = Utf8               MODULE$
  #104 = Utf8               Lscala/collection/immutable/Nil$;
  #105 = NameAndType        #103:#104     // MODULE$:Lscala/collection/immutable/Nil$;
  #106 = Fieldref           #102.#105     // scala/collection/immutable/Nil$.MODULE$:Lscala/collection/immutable/Nil$;
  #107 = Utf8               equals
  #108 = Utf8               (Ljava/lang/Object;)Z
  #109 = NameAndType        #107:#108     // equals:(Ljava/lang/Object;)Z
  #110 = Methodref          #4.#109       // java/lang/Object.equals:(Ljava/lang/Object;)Z
  #111 = Utf8               scala/collection/immutable/$colon$colon
  #112 = Class              #111          // scala/collection/immutable/$colon$colon
  #113 = Utf8               head
  #114 = Utf8               ()Ljava/lang/Object;
  #115 = NameAndType        #113:#114     // head:()Ljava/lang/Object;
  #116 = Methodref          #112.#115     // scala/collection/immutable/$colon$colon.head:()Ljava/lang/Object;
  #117 = Utf8               next$access$1
  #118 = NameAndType        #117:#89      // next$access$1:()Lscala/collection/immutable/List;
  #119 = Methodref          #112.#118     // scala/collection/immutable/$colon$colon.next$access$1:()Lscala/collection/immutable/List;
  #120 = Utf8               instTpe
  #121 = Utf8               ()Lscala/reflect/api/Types$TypeApi;
  #122 = NameAndType        #120:#121     // instTpe:()Lscala/reflect/api/Types$TypeApi;
  #123 = Methodref          #50.#122      // shapeless/LazyMacros$LazyDefinitions$Instance.instTpe:()Lscala/reflect/api/Types$TypeApi;
  #124 = Utf8               $eq$colon$eq
  #125 = Utf8               (Lscala/reflect/api/Types$TypeApi;)Z
  #126 = NameAndType        #124:#125     // $eq$colon$eq:(Lscala/reflect/api/Types$TypeApi;)Z
  #127 = Methodref          #31.#126      // scala/reflect/api/Types$TypeApi.$eq$colon$eq:(Lscala/reflect/api/Types$TypeApi;)Z
  #128 = Utf8               dependsOn
  #129 = NameAndType        #128:#89      // dependsOn:()Lscala/collection/immutable/List;
  #130 = Methodref          #50.#129      // shapeless/LazyMacros$LazyDefinitions$Instance.dependsOn:()Lscala/collection/immutable/List;
  #131 = Utf8               (Ljava/lang/Object;)Ljava/lang/Object;
  #132 = MethodType         #131          //  (Ljava/lang/Object;)Ljava/lang/Object;
  #133 = Utf8               $anonfun$addDependency$1$adapted
  #134 = Utf8               (Lscala/reflect/api/Types$TypeApi;Lscala/reflect/api/Types$TypeApi;)Ljava/lang/Object;
  #135 = NameAndType        #133:#134     // $anonfun$addDependency$1$adapted:(Lscala/reflect/api/Types$TypeApi;Lscala/reflect/api/Types$TypeApi;)Ljava/lang/Object;
  #136 = Methodref          #2.#135       // shapeless/LazyMacros$DerivationContext$State.$anonfun$addDependency$1$adapted:(Lscala/reflect/api/Types$TypeApi;Lscala/reflect/api/Types$TypeApi;)Ljava/lang/Object;
  #137 = MethodHandle       6:#136        // REF_invokeStatic shapeless/LazyMacros$DerivationContext$State.$anonfun$addDependency$1$adapted:(Lscala/reflect/api/Types$TypeApi;Lscala/reflect/api/Types$TypeApi;)Ljava/lang/Object;
  #138 = Utf8               (Lscala/reflect/api/Types$TypeApi;)Ljava/lang/Object;
  #139 = MethodType         #138          //  (Lscala/reflect/api/Types$TypeApi;)Ljava/lang/Object;
  #140 = Integer            5
  #141 = Integer            1
  #142 = Utf8               java/lang/invoke/LambdaMetafactory
  #143 = Class              #142          // java/lang/invoke/LambdaMetafactory
  #144 = Utf8               altMetafactory
  #145 = Utf8               (Ljava/lang/invoke/MethodHandles$Lookup;Ljava/lang/String;Ljava/lang/invoke/MethodType;[Ljava/lang/Object;)Ljava/lang/invoke/CallSite;
  #146 = NameAndType        #144:#145     // altMetafactory:(Ljava/lang/invoke/MethodHandles$Lookup;Ljava/lang/String;Ljava/lang/invoke/MethodType;[Ljava/lang/Object;)Ljava/lang/invoke/CallSite;
  #147 = Methodref          #143.#146     // java/lang/invoke/LambdaMetafactory.altMetafactory:(Ljava/lang/invoke/MethodHandles$Lookup;Ljava/lang/String;Ljava/lang/invoke/MethodType;[Ljava/lang/Object;)Ljava/lang/invoke/CallSite;
  #148 = MethodHandle       6:#147        // REF_invokeStatic java/lang/invoke/LambdaMetafactory.altMetafactory:(Ljava/lang/invoke/MethodHandles$Lookup;Ljava/lang/String;Ljava/lang/invoke/MethodType;[Ljava/lang/Object;)Ljava/lang/invoke/CallSite;
  #149 = Utf8               apply
  #150 = Utf8               (Lscala/reflect/api/Types$TypeApi;)Lscala/Function1;
  #151 = NameAndType        #149:#150     // apply:(Lscala/reflect/api/Types$TypeApi;)Lscala/Function1;
  #152 = InvokeDynamic      #0:#151       // #0:apply:(Lscala/reflect/api/Types$TypeApi;)Lscala/Function1;
  #153 = Utf8               scala/collection/immutable/List
  #154 = Class              #153          // scala/collection/immutable/List
  #155 = Utf8               exists
  #156 = Utf8               (Lscala/Function1;)Z
  #157 = NameAndType        #155:#156     // exists:(Lscala/Function1;)Z
  #158 = Methodref          #154.#157     // scala/collection/immutable/List.exists:(Lscala/Function1;)Z
  #159 = Utf8               $colon$colon
  #160 = Utf8               (Ljava/lang/Object;)Lscala/collection/immutable/List;
  #161 = NameAndType        #159:#160     // $colon$colon:(Ljava/lang/Object;)Lscala/collection/immutable/List;
  #162 = Methodref          #154.#161     // scala/collection/immutable/List.$colon$colon:(Ljava/lang/Object;)Lscala/collection/immutable/List;
  #163 = Utf8               copy$default$1
  #164 = NameAndType        #163:#121     // copy$default$1:()Lscala/reflect/api/Types$TypeApi;
  #165 = Methodref          #50.#164      // shapeless/LazyMacros$LazyDefinitions$Instance.copy$default$1:()Lscala/reflect/api/Types$TypeApi;
  #166 = Utf8               copy$default$2
  #167 = Utf8               ()Lscala/reflect/api/Names$TermNameApi;
  #168 = NameAndType        #166:#167     // copy$default$2:()Lscala/reflect/api/Names$TermNameApi;
  #169 = Methodref          #50.#168      // shapeless/LazyMacros$LazyDefinitions$Instance.copy$default$2:()Lscala/reflect/api/Names$TermNameApi;
  #170 = Utf8               copy$default$3
  #171 = Utf8               ()Lscala/reflect/api/Symbols$SymbolApi;
  #172 = NameAndType        #170:#171     // copy$default$3:()Lscala/reflect/api/Symbols$SymbolApi;
  #173 = Methodref          #50.#172      // shapeless/LazyMacros$LazyDefinitions$Instance.copy$default$3:()Lscala/reflect/api/Symbols$SymbolApi;
  #174 = Utf8               copy$default$4
  #175 = Utf8               ()Lscala/Option;
  #176 = NameAndType        #174:#175     // copy$default$4:()Lscala/Option;
  #177 = Methodref          #50.#176      // shapeless/LazyMacros$LazyDefinitions$Instance.copy$default$4:()Lscala/Option;
  #178 = Utf8               copy$default$5
  #179 = NameAndType        #178:#121     // copy$default$5:()Lscala/reflect/api/Types$TypeApi;
  #180 = Methodref          #50.#179      // shapeless/LazyMacros$LazyDefinitions$Instance.copy$default$5:()Lscala/reflect/api/Types$TypeApi;
  #181 = Utf8               copy
  #182 = Utf8               (Lscala/reflect/api/Types$TypeApi;Lscala/reflect/api/Names$TermNameApi;Lscala/reflect/api/Symbols$SymbolApi;Lscala/Option;Lscala/reflect/api/Types$TypeApi;Lscala/collection/immutable/List;)Lshapeless/LazyMacros$LazyDefinitions$Instance;
  #183 = NameAndType        #181:#182     // copy:(Lscala/reflect/api/Types$TypeApi;Lscala/reflect/api/Names$TermNameApi;Lscala/reflect/api/Symbols$SymbolApi;Lscala/Option;Lscala/reflect/api/Types$TypeApi;Lscala/collection/immutable/List;)Lshapeless/LazyMacros$LazyDefinitions$Instance;
  #184 = Methodref          #50.#183      // shapeless/LazyMacros$LazyDefinitions$Instance.copy:(Lscala/reflect/api/Types$TypeApi;Lscala/reflect/api/Names$TermNameApi;Lscala/reflect/api/Symbols$SymbolApi;Lscala/Option;Lscala/reflect/api/Types$TypeApi;Lscala/collection/immutable/List;)Lshapeless/LazyMacros$LazyDefinitions$Instance;
  #185 = Utf8               scala/MatchError
  #186 = Class              #185          // scala/MatchError
  #187 = Utf8               <init>
  #188 = Utf8               (Ljava/lang/Object;)V
  #189 = NameAndType        #187:#188     // "<init>":(Ljava/lang/Object;)V
  #190 = Methodref          #186.#189     // scala/MatchError."<init>":(Ljava/lang/Object;)V
  #191 = NameAndType        #163:#82      // copy$default$1:()Ljava/lang/String;
  #192 = Methodref          #2.#191       // shapeless/LazyMacros$DerivationContext$State.copy$default$1:()Ljava/lang/String;
  #193 = NameAndType        #166:#85      // copy$default$2:()Lscala/collection/immutable/ListMap;
  #194 = Methodref          #2.#193       // shapeless/LazyMacros$DerivationContext$State.copy$default$2:()Lscala/collection/immutable/ListMap;
  #195 = NameAndType        #174:#89      // copy$default$4:()Lscala/collection/immutable/List;
  #196 = Methodref          #2.#195       // shapeless/LazyMacros$DerivationContext$State.copy$default$4:()Lscala/collection/immutable/List;
  #197 = Utf8               (Ljava/lang/String;Lscala/collection/immutable/ListMap;Lscala/collection/immutable/List;Lscala/collection/immutable/List;)Lshapeless/LazyMacros$DerivationContext$State;
  #198 = NameAndType        #181:#197     // copy:(Ljava/lang/String;Lscala/collection/immutable/ListMap;Lscala/collection/immutable/List;Lscala/collection/immutable/List;)Lshapeless/LazyMacros$DerivationContext$State;
  #199 = Methodref          #2.#198       // shapeless/LazyMacros$DerivationContext$State.copy:(Ljava/lang/String;Lscala/collection/immutable/ListMap;Lscala/collection/immutable/List;Lscala/collection/immutable/List;)Lshapeless/LazyMacros$DerivationContext$State;
  #200 = Utf8               x$1
  #201 = Utf8               x$2
  #202 = Utf8               Lscala/reflect/api/Types$TypeApi;
  #203 = Utf8               x$3
  #204 = Utf8               Lscala/reflect/api/Names$TermNameApi;
  #205 = Utf8               x$4
  #206 = Utf8               Lscala/reflect/api/Symbols$SymbolApi;
  #207 = Utf8               x$5
  #208 = Utf8               Lscala/Option;
  #209 = Utf8               x$6
  #210 = Utf8               h
  #211 = Utf8               Lshapeless/LazyMacros$LazyDefinitions$Instance;
  #212 = Utf8               t
  #213 = Utf8               x$7
  #214 = Utf8               x$8
  #215 = Utf8               x$9
  #216 = Utf8               x$10
  #217 = Utf8               open0
  #218 = Utf8               update
  #219 = Utf8               (Lshapeless/LazyMacros$LazyDefinitions$Instance;)Lshapeless/LazyMacros$DerivationContext$State;
  #220 = Utf8               inst
  #221 = NameAndType        #63:#85       // dict:()Lscala/collection/immutable/ListMap;
  #222 = Methodref          #2.#221       // shapeless/LazyMacros$DerivationContext$State.dict:()Lscala/collection/immutable/ListMap;
  #223 = Utf8               shapeless$LazyMacros$DerivationContext$State$$$outer
  #224 = Utf8               ()Lshapeless/LazyMacros$DerivationContext;
  #225 = NameAndType        #223:#224     // shapeless$LazyMacros$DerivationContext$State$$$outer:()Lshapeless/LazyMacros$DerivationContext;
  #226 = Methodref          #2.#225       // shapeless/LazyMacros$DerivationContext$State.shapeless$LazyMacros$DerivationContext$State$$$outer:()Lshapeless/LazyMacros$DerivationContext;
  #227 = Utf8               ()Lshapeless/LazyMacros$LazyDefinitions$TypeWrapper$;
  #228 = NameAndType        #57:#227      // TypeWrapper:()Lshapeless/LazyMacros$LazyDefinitions$TypeWrapper$;
  #229 = Methodref          #41.#228      // shapeless/LazyMacros$DerivationContext.TypeWrapper:()Lshapeless/LazyMacros$LazyDefinitions$TypeWrapper$;
  #230 = Utf8               (Lscala/reflect/api/Types$TypeApi;)Lshapeless/LazyMacros$LazyDefinitions$TypeWrapper;
  #231 = NameAndType        #149:#230     // apply:(Lscala/reflect/api/Types$TypeApi;)Lshapeless/LazyMacros$LazyDefinitions$TypeWrapper;
  #232 = Methodref          #59.#231      // shapeless/LazyMacros$LazyDefinitions$TypeWrapper$.apply:(Lscala/reflect/api/Types$TypeApi;)Lshapeless/LazyMacros$LazyDefinitions$TypeWrapper;
  #233 = Utf8               scala/collection/immutable/ListMap
  #234 = Class              #233          // scala/collection/immutable/ListMap
  #235 = Utf8               updated
  #236 = Utf8               (Ljava/lang/Object;Ljava/lang/Object;)Lscala/collection/immutable/ListMap;
  #237 = NameAndType        #235:#236     // updated:(Ljava/lang/Object;Ljava/lang/Object;)Lscala/collection/immutable/ListMap;
  #238 = Methodref          #234.#237     // scala/collection/immutable/ListMap.updated:(Ljava/lang/Object;Ljava/lang/Object;)Lscala/collection/immutable/ListMap;
  #239 = NameAndType        #170:#89      // copy$default$3:()Lscala/collection/immutable/List;
  #240 = Methodref          #2.#239       // shapeless/LazyMacros$DerivationContext$State.copy$default$3:()Lscala/collection/immutable/List;
  #241 = Utf8               openInst
  #242 = Utf8               (Lscala/reflect/api/Types$TypeApi;)Lscala/Tuple2;
  #243 = Utf8               (Lscala/reflect/api/Types$TypeApi;)Lscala/Tuple2<Lshapeless/LazyMacros$DerivationContext$State;Lshapeless/LazyMacros$LazyDefinitions$Instance;>;
  #244 = Utf8               ()Lshapeless/LazyMacros$LazyDefinitions$Instance$;
  #245 = NameAndType        #51:#244      // Instance:()Lshapeless/LazyMacros$LazyDefinitions$Instance$;
  #246 = Methodref          #41.#245      // shapeless/LazyMacros$DerivationContext.Instance:()Lshapeless/LazyMacros$LazyDefinitions$Instance$;
  #247 = Utf8               (Lscala/reflect/api/Types$TypeApi;)Lshapeless/LazyMacros$LazyDefinitions$Instance;
  #248 = NameAndType        #149:#247     // apply:(Lscala/reflect/api/Types$TypeApi;)Lshapeless/LazyMacros$LazyDefinitions$Instance;
  #249 = Methodref          #53.#248      // shapeless/LazyMacros$LazyDefinitions$Instance$.apply:(Lscala/reflect/api/Types$TypeApi;)Lshapeless/LazyMacros$LazyDefinitions$Instance;
  #250 = NameAndType        #96:#97       // addDependency:(Lscala/reflect/api/Types$TypeApi;)Lshapeless/LazyMacros$DerivationContext$State;
  #251 = Methodref          #2.#250       // shapeless/LazyMacros$DerivationContext$State.addDependency:(Lscala/reflect/api/Types$TypeApi;)Lshapeless/LazyMacros$DerivationContext$State;
  #252 = Utf8               scala/Tuple2
  #253 = Class              #252          // scala/Tuple2
  #254 = NameAndType        #218:#219     // update:(Lshapeless/LazyMacros$LazyDefinitions$Instance;)Lshapeless/LazyMacros$DerivationContext$State;
  #255 = Methodref          #2.#254       // shapeless/LazyMacros$DerivationContext$State.update:(Lshapeless/LazyMacros$LazyDefinitions$Instance;)Lshapeless/LazyMacros$DerivationContext$State;
  #256 = Utf8               (Ljava/lang/Object;Ljava/lang/Object;)V
  #257 = NameAndType        #187:#256     // "<init>":(Ljava/lang/Object;Ljava/lang/Object;)V
  #258 = Methodref          #253.#257     // scala/Tuple2."<init>":(Ljava/lang/Object;Ljava/lang/Object;)V
  #259 = Utf8               state0
  #260 = Utf8               closeInst
  #261 = Utf8               (Lscala/reflect/api/Types$TypeApi;Lscala/reflect/api/Trees$TreeApi;Lscala/reflect/api/Types$TypeApi;)Lscala/Tuple2;
  #262 = Utf8               (Lscala/reflect/api/Types$TypeApi;Lscala/reflect/api/Trees$TreeApi;Lscala/reflect/api/Types$TypeApi;)Lscala/Tuple2<Lshapeless/LazyMacros$DerivationContext$State;Lshapeless/LazyMacros$LazyDefinitions$Instance;>;
  #263 = Utf8               tree
  #264 = Utf8               actualTpe
  #265 = Utf8               scala/Predef$
  #266 = Class              #265          // scala/Predef$
  #267 = Utf8               Lscala/Predef$;
  #268 = NameAndType        #103:#267     // MODULE$:Lscala/Predef$;
  #269 = Fieldref           #266.#268     // scala/Predef$.MODULE$:Lscala/Predef$;
  #270 = Utf8               nonEmpty
  #271 = Utf8               ()Z
  #272 = NameAndType        #270:#271     // nonEmpty:()Z
  #273 = Methodref          #154.#272     // scala/collection/immutable/List.nonEmpty:()Z
  #274 = Utf8               assert
  #275 = Utf8               (Z)V
  #276 = NameAndType        #274:#275     // assert:(Z)V
  #277 = Methodref          #266.#276     // scala/Predef$.assert:(Z)V
  #278 = Methodref          #154.#115     // scala/collection/immutable/List.head:()Ljava/lang/Object;
  #279 = Utf8               shapeless$LazyMacros$DerivationContext$$$outer
  #280 = Utf8               ()Lshapeless/LazyMacros;
  #281 = NameAndType        #279:#280     // shapeless$LazyMacros$DerivationContext$$$outer:()Lshapeless/LazyMacros;
  #282 = Methodref          #41.#281      // shapeless/LazyMacros$DerivationContext.shapeless$LazyMacros$DerivationContext$$$outer:()Lshapeless/LazyMacros;
  #283 = Utf8               c
  #284 = Utf8               ()Lscala/reflect/macros/whitebox/Context;
  #285 = NameAndType        #283:#284     // c:()Lscala/reflect/macros/whitebox/Context;
  #286 = Methodref          #43.#285      // shapeless/LazyMacros.c:()Lscala/reflect/macros/whitebox/Context;
  #287 = Utf8               scala/reflect/macros/whitebox/Context
  #288 = Class              #287          // scala/reflect/macros/whitebox/Context
  #289 = Utf8               internal
  #290 = Utf8               ()Lscala/reflect/macros/Internals$ContextInternalApi;
  #291 = NameAndType        #289:#290     // internal:()Lscala/reflect/macros/Internals$ContextInternalApi;
  #292 = InterfaceMethodref #288.#291     // scala/reflect/macros/whitebox/Context.internal:()Lscala/reflect/macros/Internals$ContextInternalApi;
  #293 = Utf8               symbol
  #294 = NameAndType        #293:#171     // symbol:()Lscala/reflect/api/Symbols$SymbolApi;
  #295 = Methodref          #50.#294      // shapeless/LazyMacros$LazyDefinitions$Instance.symbol:()Lscala/reflect/api/Symbols$SymbolApi;
  #296 = Utf8               setInfo
  #297 = Utf8               (Lscala/reflect/api/Symbols$SymbolApi;Lscala/reflect/api/Types$TypeApi;)Lscala/reflect/api/Symbols$SymbolApi;
  #298 = NameAndType        #296:#297     // setInfo:(Lscala/reflect/api/Symbols$SymbolApi;Lscala/reflect/api/Types$TypeApi;)Lscala/reflect/api/Symbols$SymbolApi;
  #299 = InterfaceMethodref #36.#298      // scala/reflect/macros/Internals$ContextInternalApi.setInfo:(Lscala/reflect/api/Symbols$SymbolApi;Lscala/reflect/api/Types$TypeApi;)Lscala/reflect/api/Symbols$SymbolApi;
  #300 = Utf8               scala/Some
  #301 = Class              #300          // scala/Some
  #302 = Methodref          #301.#189     // scala/Some."<init>":(Ljava/lang/Object;)V
  #303 = Utf8               copy$default$6
  #304 = NameAndType        #303:#89      // copy$default$6:()Lscala/collection/immutable/List;
  #305 = Methodref          #50.#304      // shapeless/LazyMacros$LazyDefinitions$Instance.copy$default$6:()Lscala/collection/immutable/List;
  #306 = Utf8               tail
  #307 = NameAndType        #306:#114     // tail:()Ljava/lang/Object;
  #308 = Methodref          #154.#307     // scala/collection/immutable/List.tail:()Ljava/lang/Object;
  #309 = Utf8               Lscala/Some;
  #310 = Utf8               instance
  #311 = Utf8               sym
  #312 = Utf8               instance0
  #313 = Utf8               Lscala/reflect/api/Trees$TreeApi;
  #314 = Utf8               lookup
  #315 = Utf8               (Lscala/reflect/api/Types$TypeApi;)Lscala/util/Either;
  #316 = Utf8               (Lscala/reflect/api/Types$TypeApi;)Lscala/util/Either<Lshapeless/LazyMacros$DerivationContext$State;Lscala/Tuple2<Lshapeless/LazyMacros$DerivationContext$State;Lshapeless/LazyMacros$LazyDefinitions$Instance;>;>;
  #317 = Utf8               get
  #318 = Utf8               (Ljava/lang/Object;)Lscala/Option;
  #319 = NameAndType        #317:#318     // get:(Ljava/lang/Object;)Lscala/Option;
  #320 = Methodref          #234.#319     // scala/collection/immutable/ListMap.get:(Ljava/lang/Object;)Lscala/Option;
  #321 = Utf8               value
  #322 = NameAndType        #321:#114     // value:()Ljava/lang/Object;
  #323 = Methodref          #301.#322     // scala/Some.value:()Ljava/lang/Object;
  #324 = Utf8               scala/package$
  #325 = Class              #324          // scala/package$
  #326 = Utf8               Lscala/package$;
  #327 = NameAndType        #103:#326     // MODULE$:Lscala/package$;
  #328 = Fieldref           #325.#327     // scala/package$.MODULE$:Lscala/package$;
  #329 = Utf8               Right
  #330 = Utf8               ()Lscala/util/Right$;
  #331 = NameAndType        #329:#330     // Right:()Lscala/util/Right$;
  #332 = Methodref          #325.#331     // scala/package$.Right:()Lscala/util/Right$;
  #333 = Utf8               scala/util/Right$
  #334 = Class              #333          // scala/util/Right$
  #335 = Utf8               (Ljava/lang/Object;)Lscala/util/Right;
  #336 = NameAndType        #149:#335     // apply:(Ljava/lang/Object;)Lscala/util/Right;
  #337 = Methodref          #334.#336     // scala/util/Right$.apply:(Ljava/lang/Object;)Lscala/util/Right;
  #338 = Utf8               scala/None$
  #339 = Class              #338          // scala/None$
  #340 = Utf8               Lscala/None$;
  #341 = NameAndType        #103:#340     // MODULE$:Lscala/None$;
  #342 = Fieldref           #339.#341     // scala/None$.MODULE$:Lscala/None$;
  #343 = Utf8               Left
  #344 = Utf8               ()Lscala/util/Left$;
  #345 = NameAndType        #343:#344     // Left:()Lscala/util/Left$;
  #346 = Methodref          #325.#345     // scala/package$.Left:()Lscala/util/Left$;
  #347 = NameAndType        #241:#242     // openInst:(Lscala/reflect/api/Types$TypeApi;)Lscala/Tuple2;
  #348 = Methodref          #2.#347       // shapeless/LazyMacros$DerivationContext$State.openInst:(Lscala/reflect/api/Types$TypeApi;)Lscala/Tuple2;
  #349 = Utf8               _1
  #350 = NameAndType        #349:#114     // _1:()Ljava/lang/Object;
  #351 = Methodref          #253.#350     // scala/Tuple2._1:()Ljava/lang/Object;
  #352 = Utf8               scala/util/Left$
  #353 = Class              #352          // scala/util/Left$
  #354 = Utf8               (Ljava/lang/Object;)Lscala/util/Left;
  #355 = NameAndType        #149:#354     // apply:(Ljava/lang/Object;)Lscala/util/Left;
  #356 = Methodref          #353.#355     // scala/util/Left$.apply:(Ljava/lang/Object;)Lscala/util/Left;
  #357 = Utf8               i
  #358 = Utf8               scala/Option
  #359 = Class              #358          // scala/Option
  #360 = Utf8               scala/util/Either
  #361 = Class              #360          // scala/util/Either
  #362 = Utf8               (Lscala/reflect/api/Types$TypeApi;)Lscala/collection/immutable/List;
  #363 = Utf8               (Lscala/reflect/api/Types$TypeApi;)Lscala/collection/immutable/List<Lshapeless/LazyMacros$LazyDefinitions$Instance;>;
  #364 = Utf8               (Ljava/lang/Object;Lscala/collection/immutable/List;)V
  #365 = NameAndType        #187:#364     // "<init>":(Ljava/lang/Object;Lscala/collection/immutable/List;)V
  #366 = Methodref          #112.#365     // scala/collection/immutable/$colon$colon."<init>":(Ljava/lang/Object;Lscala/collection/immutable/List;)V
  #367 = Utf8               helper$1
  #368 = Utf8               (Lscala/collection/immutable/List;Lscala/collection/immutable/List;)Lscala/collection/immutable/List;
  #369 = NameAndType        #367:#368     // helper$1:(Lscala/collection/immutable/List;Lscala/collection/immutable/List;)Lscala/collection/immutable/List;
  #370 = Methodref          #2.#369       // shapeless/LazyMacros$DerivationContext$State.helper$1:(Lscala/collection/immutable/List;Lscala/collection/immutable/List;)Lscala/collection/immutable/List;
  #371 = Utf8               (Ljava/lang/String;Lscala/collection/immutable/ListMap<Lshapeless/LazyMacros$LazyDefinitions$TypeWrapper;Lshapeless/LazyMacros$LazyDefinitions$Instance;>;Lscala/collection/immutable/List<Lshapeless/LazyMacros$LazyDefinitions$Instance;>;Lscala/collection/immutable/List<Lshapeless/LazyMacros$LazyDefinitions$TypeWrapper;>;)Lshapeless/LazyMacros$DerivationContext$State;
  #372 = Utf8               (Lshapeless/LazyMacros$DerivationContext;Ljava/lang/String;Lscala/collection/immutable/ListMap;Lscala/collection/immutable/List;Lscala/collection/immutable/List;)V
  #373 = NameAndType        #187:#372     // "<init>":(Lshapeless/LazyMacros$DerivationContext;Ljava/lang/String;Lscala/collection/immutable/ListMap;Lscala/collection/immutable/List;Lscala/collection/immutable/List;)V
  #374 = Methodref          #2.#373       // shapeless/LazyMacros$DerivationContext$State."<init>":(Lshapeless/LazyMacros$DerivationContext;Ljava/lang/String;Lscala/collection/immutable/ListMap;Lscala/collection/immutable/List;Lscala/collection/immutable/List;)V
  #375 = NameAndType        #61:#82       // name:()Ljava/lang/String;
  #376 = Methodref          #2.#375       // shapeless/LazyMacros$DerivationContext$State.name:()Ljava/lang/String;
  #377 = NameAndType        #69:#89       // prevent:()Lscala/collection/immutable/List;
  #378 = Methodref          #2.#377       // shapeless/LazyMacros$DerivationContext$State.prevent:()Lscala/collection/immutable/List;
  #379 = Utf8               productPrefix
  #380 = String             #45           // State
  #381 = Utf8               productArity
  #382 = Utf8               ()I
  #383 = Utf8               productElement
  #384 = Utf8               (I)Ljava/lang/Object;
  #385 = Utf8               scala/runtime/Statics
  #386 = Class              #385          // scala/runtime/Statics
  #387 = Utf8               ioobe
  #388 = NameAndType        #387:#384     // ioobe:(I)Ljava/lang/Object;
  #389 = Methodref          #386.#388     // scala/runtime/Statics.ioobe:(I)Ljava/lang/Object;
  #390 = Utf8               I
  #391 = Utf8               productIterator
  #392 = Utf8               ()Lscala/collection/Iterator<Ljava/lang/Object;>;
  #393 = Utf8               scala/runtime/ScalaRunTime$
  #394 = Class              #393          // scala/runtime/ScalaRunTime$
  #395 = Utf8               Lscala/runtime/ScalaRunTime$;
  #396 = NameAndType        #103:#395     // MODULE$:Lscala/runtime/ScalaRunTime$;
  #397 = Fieldref           #394.#396     // scala/runtime/ScalaRunTime$.MODULE$:Lscala/runtime/ScalaRunTime$;
  #398 = Utf8               typedProductIterator
  #399 = NameAndType        #398:#77      // typedProductIterator:(Lscala/Product;)Lscala/collection/Iterator;
  #400 = Methodref          #394.#399     // scala/runtime/ScalaRunTime$.typedProductIterator:(Lscala/Product;)Lscala/collection/Iterator;
  #401 = Utf8               canEqual
  #402 = Utf8               Ljava/lang/Object;
  #403 = Utf8               productElementName
  #404 = Utf8               (I)Ljava/lang/String;
  #405 = String             #61           // name
  #406 = String             #63           // dict
  #407 = String             #66           // open
  #408 = String             #69           // prevent
  #409 = Utf8               java/lang/String
  #410 = Class              #409          // java/lang/String
  #411 = Utf8               hashCode
  #412 = Utf8               _hashCode
  #413 = Utf8               (Lscala/Product;)I
  #414 = NameAndType        #412:#413     // _hashCode:(Lscala/Product;)I
  #415 = Methodref          #394.#414     // scala/runtime/ScalaRunTime$._hashCode:(Lscala/Product;)I
  #416 = Utf8               toString
  #417 = Utf8               _toString
  #418 = Utf8               (Lscala/Product;)Ljava/lang/String;
  #419 = NameAndType        #417:#418     // _toString:(Lscala/Product;)Ljava/lang/String;
  #420 = Methodref          #394.#419     // scala/runtime/ScalaRunTime$._toString:(Lscala/Product;)Ljava/lang/String;
  #421 = NameAndType        #401:#108     // canEqual:(Ljava/lang/Object;)Z
  #422 = Methodref          #2.#421       // shapeless/LazyMacros$DerivationContext$State.canEqual:(Ljava/lang/Object;)Z
  #423 = NameAndType        #71:#72       // $outer:Lshapeless/LazyMacros$DerivationContext;
  #424 = Fieldref           #2.#423       // shapeless/LazyMacros$DerivationContext$State.$outer:Lshapeless/LazyMacros$DerivationContext;
  #425 = Utf8               $anonfun$addDependency$1
  #426 = Utf8               (Lscala/reflect/api/Types$TypeApi;Lscala/reflect/api/Types$TypeApi;)Z
  #427 = Utf8               tpe$2
  #428 = Utf8               $anonfun$dependsOn$1
  #429 = Utf8               (Lscala/reflect/api/Types$TypeApi;Lshapeless/LazyMacros$LazyDefinitions$Instance;)Z
  #430 = Utf8               h$1
  #431 = Utf8               tpes
  #432 = Utf8               acc
  #433 = Utf8               $anonfun$dependsOn$1$adapted
  #434 = Utf8               (Lscala/reflect/api/Types$TypeApi;Lshapeless/LazyMacros$LazyDefinitions$Instance;)Ljava/lang/Object;
  #435 = NameAndType        #433:#434     // $anonfun$dependsOn$1$adapted:(Lscala/reflect/api/Types$TypeApi;Lshapeless/LazyMacros$LazyDefinitions$Instance;)Ljava/lang/Object;
  #436 = Methodref          #2.#435       // shapeless/LazyMacros$DerivationContext$State.$anonfun$dependsOn$1$adapted:(Lscala/reflect/api/Types$TypeApi;Lshapeless/LazyMacros$LazyDefinitions$Instance;)Ljava/lang/Object;
  #437 = MethodHandle       6:#436        // REF_invokeStatic shapeless/LazyMacros$DerivationContext$State.$anonfun$dependsOn$1$adapted:(Lscala/reflect/api/Types$TypeApi;Lshapeless/LazyMacros$LazyDefinitions$Instance;)Ljava/lang/Object;
  #438 = Utf8               (Lshapeless/LazyMacros$LazyDefinitions$Instance;)Ljava/lang/Object;
  #439 = MethodType         #438          //  (Lshapeless/LazyMacros$LazyDefinitions$Instance;)Ljava/lang/Object;
  #440 = InvokeDynamic      #1:#151       // #1:apply:(Lscala/reflect/api/Types$TypeApi;)Lscala/Function1;
  #441 = NameAndType        #149:#131     // apply:(Ljava/lang/Object;)Ljava/lang/Object;
  #442 = Methodref          #234.#441     // scala/collection/immutable/ListMap.apply:(Ljava/lang/Object;)Ljava/lang/Object;
  #443 = Utf8               t0
  #444 = Utf8               (Ljava/lang/String;Lscala/collection/immutable/ListMap<Lshapeless/LazyMacros$LazyDefinitions$TypeWrapper;Lshapeless/LazyMacros$LazyDefinitions$Instance;>;Lscala/collection/immutable/List<Lshapeless/LazyMacros$LazyDefinitions$Instance;>;Lscala/collection/immutable/List<Lshapeless/LazyMacros$LazyDefinitions$TypeWrapper;>;)V
  #445 = Utf8               ()V
  #446 = NameAndType        #187:#445     // "<init>":()V
  #447 = Methodref          #4.#446       // java/lang/Object."<init>":()V
  #448 = Utf8               $init$
  #449 = Utf8               (Lscala/Product;)V
  #450 = NameAndType        #448:#449     // $init$:(Lscala/Product;)V
  #451 = InterfaceMethodref #6.#450       // scala/Product.$init$:(Lscala/Product;)V
  #452 = NameAndType        #425:#426     // $anonfun$addDependency$1:(Lscala/reflect/api/Types$TypeApi;Lscala/reflect/api/Types$TypeApi;)Z
  #453 = Methodref          #2.#452       // shapeless/LazyMacros$DerivationContext$State.$anonfun$addDependency$1:(Lscala/reflect/api/Types$TypeApi;Lscala/reflect/api/Types$TypeApi;)Z
  #454 = Utf8               scala/runtime/BoxesRunTime
  #455 = Class              #454          // scala/runtime/BoxesRunTime
  #456 = Utf8               boxToBoolean
  #457 = Utf8               (Z)Ljava/lang/Boolean;
  #458 = NameAndType        #456:#457     // boxToBoolean:(Z)Ljava/lang/Boolean;
  #459 = Methodref          #455.#458     // scala/runtime/BoxesRunTime.boxToBoolean:(Z)Ljava/lang/Boolean;
  #460 = NameAndType        #428:#429     // $anonfun$dependsOn$1:(Lscala/reflect/api/Types$TypeApi;Lshapeless/LazyMacros$LazyDefinitions$Instance;)Z
  #461 = Methodref          #2.#460       // shapeless/LazyMacros$DerivationContext$State.$anonfun$dependsOn$1:(Lscala/reflect/api/Types$TypeApi;Lshapeless/LazyMacros$LazyDefinitions$Instance;)Z
  #462 = Utf8               $deserializeLambda$
  #463 = Utf8               (Ljava/lang/invoke/SerializedLambda;)Ljava/lang/Object;
  #464 = Utf8               scala/runtime/LambdaDeserialize
  #465 = Class              #464          // scala/runtime/LambdaDeserialize
  #466 = Utf8               bootstrap
  #467 = Utf8               (Ljava/lang/invoke/MethodHandles$Lookup;Ljava/lang/String;Ljava/lang/invoke/MethodType;[Ljava/lang/invoke/MethodHandle;)Ljava/lang/invoke/CallSite;
  #468 = NameAndType        #466:#467     // bootstrap:(Ljava/lang/invoke/MethodHandles$Lookup;Ljava/lang/String;Ljava/lang/invoke/MethodType;[Ljava/lang/invoke/MethodHandle;)Ljava/lang/invoke/CallSite;
  #469 = Methodref          #465.#468     // scala/runtime/LambdaDeserialize.bootstrap:(Ljava/lang/invoke/MethodHandles$Lookup;Ljava/lang/String;Ljava/lang/invoke/MethodType;[Ljava/lang/invoke/MethodHandle;)Ljava/lang/invoke/CallSite;
  #470 = MethodHandle       6:#469        // REF_invokeStatic scala/runtime/LambdaDeserialize.bootstrap:(Ljava/lang/invoke/MethodHandles$Lookup;Ljava/lang/String;Ljava/lang/invoke/MethodType;[Ljava/lang/invoke/MethodHandle;)Ljava/lang/invoke/CallSite;
  #471 = Utf8               lambdaDeserialize
  #472 = NameAndType        #471:#463     // lambdaDeserialize:(Ljava/lang/invoke/SerializedLambda;)Ljava/lang/Object;
  #473 = InvokeDynamic      #2:#472       // #2:lambdaDeserialize:(Ljava/lang/invoke/SerializedLambda;)Ljava/lang/Object;
  #474 = Utf8               Signature
  #475 = Utf8               Code
  #476 = Utf8               LineNumberTable
  #477 = Utf8               LocalVariableTable
  #478 = Utf8               StackMapTable
  #479 = Utf8               MethodParameters
  #480 = Utf8               InnerClasses
  #481 = Utf8               SourceFile
  #482 = Utf8               BootstrapMethods
  #483 = Utf8               ScalaInlineInfo
  #484 = Utf8               Scala
{
  private final java.lang.String name;
    descriptor: Ljava/lang/String;
    flags: (0x0012) ACC_PRIVATE, ACC_FINAL

  private final scala.collection.immutable.ListMap<shapeless.LazyMacros$LazyDefinitions$TypeWrapper, shapeless.LazyMacros$LazyDefinitions$Instance> dict;
    descriptor: Lscala/collection/immutable/ListMap;
    flags: (0x0012) ACC_PRIVATE, ACC_FINAL
    Signature: #65                          // Lscala/collection/immutable/ListMap<Lshapeless/LazyMacros$LazyDefinitions$TypeWrapper;Lshapeless/LazyMacros$LazyDefinitions$Instance;>;

  private final scala.collection.immutable.List<shapeless.LazyMacros$LazyDefinitions$Instance> open;
    descriptor: Lscala/collection/immutable/List;
    flags: (0x0012) ACC_PRIVATE, ACC_FINAL
    Signature: #68                          // Lscala/collection/immutable/List<Lshapeless/LazyMacros$LazyDefinitions$Instance;>;

  private final scala.collection.immutable.List<shapeless.LazyMacros$LazyDefinitions$TypeWrapper> prevent;
    descriptor: Lscala/collection/immutable/List;
    flags: (0x0012) ACC_PRIVATE, ACC_FINAL
    Signature: #70                          // Lscala/collection/immutable/List<Lshapeless/LazyMacros$LazyDefinitions$TypeWrapper;>;

  public final shapeless.LazyMacros$DerivationContext $outer;
    descriptor: Lshapeless/LazyMacros$DerivationContext;
    flags: (0x1011) ACC_PUBLIC, ACC_FINAL, ACC_SYNTHETIC

  public scala.collection.Iterator<java.lang.String> productElementNames();
    descriptor: ()Lscala/collection/Iterator;
    flags: (0x0001) ACC_PUBLIC
    Code:
      stack=1, locals=1, args_size=1
         0: aload_0
         1: invokestatic  #79                 // InterfaceMethod scala/Product.productElementNames$:(Lscala/Product;)Lscala/collection/Iterator;
         4: areturn
      LineNumberTable:
        line 345: 0
      LocalVariableTable:
        Start  Length  Slot  Name   Signature
            0       5     0  this   Lshapeless/LazyMacros$DerivationContext$State;
    Signature: #75                          // ()Lscala/collection/Iterator<Ljava/lang/String;>;

  public java.lang.String name();
    descriptor: ()Ljava/lang/String;
    flags: (0x0001) ACC_PUBLIC
    Code:
      stack=1, locals=1, args_size=1
         0: aload_0
         1: getfield      #84                 // Field name:Ljava/lang/String;
         4: areturn
      LineNumberTable:
        line 346: 0
      LocalVariableTable:
        Start  Length  Slot  Name   Signature
            0       5     0  this   Lshapeless/LazyMacros$DerivationContext$State;

  public scala.collection.immutable.ListMap<shapeless.LazyMacros$LazyDefinitions$TypeWrapper, shapeless.LazyMacros$LazyDefinitions$Instance> dict();
    descriptor: ()Lscala/collection/immutable/ListMap;
    flags: (0x0001) ACC_PUBLIC
    Code:
      stack=1, locals=1, args_size=1
         0: aload_0
         1: getfield      #88                 // Field dict:Lscala/collection/immutable/ListMap;
         4: areturn
      LineNumberTable:
        line 347: 0
      LocalVariableTable:
        Start  Length  Slot  Name   Signature
            0       5     0  this   Lshapeless/LazyMacros$DerivationContext$State;
    Signature: #86                          // ()Lscala/collection/immutable/ListMap<Lshapeless/LazyMacros$LazyDefinitions$TypeWrapper;Lshapeless/LazyMacros$LazyDefinitions$Instance;>;

  public scala.collection.immutable.List<shapeless.LazyMacros$LazyDefinitions$Instance> open();
    descriptor: ()Lscala/collection/immutable/List;
    flags: (0x0001) ACC_PUBLIC
    Code:
      stack=1, locals=1, args_size=1
         0: aload_0
         1: getfield      #92                 // Field open:Lscala/collection/immutable/List;
         4: areturn
      LineNumberTable:
        line 348: 0
      LocalVariableTable:
        Start  Length  Slot  Name   Signature
            0       5     0  this   Lshapeless/LazyMacros$DerivationContext$State;
    Signature: #90                          // ()Lscala/collection/immutable/List<Lshapeless/LazyMacros$LazyDefinitions$Instance;>;

  public scala.collection.immutable.List<shapeless.LazyMacros$LazyDefinitions$TypeWrapper> prevent();
    descriptor: ()Lscala/collection/immutable/List;
    flags: (0x0001) ACC_PUBLIC
    Code:
      stack=1, locals=1, args_size=1
         0: aload_0
         1: getfield      #95                 // Field prevent:Lscala/collection/immutable/List;
         4: areturn
      LineNumberTable:
        line 350: 0
      LocalVariableTable:
        Start  Length  Slot  Name   Signature
            0       5     0  this   Lshapeless/LazyMacros$DerivationContext$State;
    Signature: #93                          // ()Lscala/collection/immutable/List<Lshapeless/LazyMacros$LazyDefinitions$TypeWrapper;>;

  public shapeless.LazyMacros$DerivationContext$State addDependency(scala.reflect.api.Types$TypeApi);
    descriptor: (Lscala/reflect/api/Types$TypeApi;)Lshapeless/LazyMacros$DerivationContext$State;
    flags: (0x0001) ACC_PUBLIC
    Code:
      stack=7, locals=20, args_size=2
         0: aload_0
         1: invokevirtual #100                // Method open:()Lscala/collection/immutable/List;
         4: astore        4
         6: getstatic     #106                // Field scala/collection/immutable/Nil$.MODULE$:Lscala/collection/immutable/Nil$;
         9: aload         4
        11: invokevirtual #110                // Method java/lang/Object.equals:(Ljava/lang/Object;)Z
        14: ifeq          24
        17: getstatic     #106                // Field scala/collection/immutable/Nil$.MODULE$:Lscala/collection/immutable/Nil$;
        20: astore_2
        21: goto          189
        24: goto          27
        27: aload         4
        29: instanceof    #112                // class scala/collection/immutable/$colon$colon
        32: ifeq          176
        35: aload         4
        37: checkcast     #112                // class scala/collection/immutable/$colon$colon
        40: astore        5
        42: aload         5
        44: invokevirtual #116                // Method scala/collection/immutable/$colon$colon.head:()Ljava/lang/Object;
        47: checkcast     #50                 // class shapeless/LazyMacros$LazyDefinitions$Instance
        50: astore        6
        52: aload         5
        54: invokevirtual #119                // Method scala/collection/immutable/$colon$colon.next$access$1:()Lscala/collection/immutable/List;
        57: astore        7
        59: aload         6
        61: invokevirtual #123                // Method shapeless/LazyMacros$LazyDefinitions$Instance.instTpe:()Lscala/reflect/api/Types$TypeApi;
        64: aload_1
        65: invokevirtual #127                // Method scala/reflect/api/Types$TypeApi.$eq$colon$eq:(Lscala/reflect/api/Types$TypeApi;)Z
        68: ifne          88
        71: aload         6
        73: invokevirtual #130                // Method shapeless/LazyMacros$LazyDefinitions$Instance.dependsOn:()Lscala/collection/immutable/List;
        76: aload_1
        77: invokedynamic #152,  0            // InvokeDynamic #0:apply:(Lscala/reflect/api/Types$TypeApi;)Lscala/Function1;
        82: invokevirtual #158                // Method scala/collection/immutable/List.exists:(Lscala/Function1;)Z
        85: ifeq          96
        88: aload         6
        90: invokevirtual #130                // Method shapeless/LazyMacros$LazyDefinitions$Instance.dependsOn:()Lscala/collection/immutable/List;
        93: goto          109
        96: aload_1
        97: astore        10
        99: aload         6
       101: invokevirtual #130                // Method shapeless/LazyMacros$LazyDefinitions$Instance.dependsOn:()Lscala/collection/immutable/List;
       104: aload         10
       106: invokevirtual #162                // Method scala/collection/immutable/List.$colon$colon:(Ljava/lang/Object;)Lscala/collection/immutable/List;
       109: astore        9
       111: aload         6
       113: invokevirtual #165                // Method shapeless/LazyMacros$LazyDefinitions$Instance.copy$default$1:()Lscala/reflect/api/Types$TypeApi;
       116: astore        11
       118: aload         6
       120: invokevirtual #169                // Method shapeless/LazyMacros$LazyDefinitions$Instance.copy$default$2:()Lscala/reflect/api/Names$TermNameApi;
       123: astore        12
       125: aload         6
       127: invokevirtual #173                // Method shapeless/LazyMacros$LazyDefinitions$Instance.copy$default$3:()Lscala/reflect/api/Symbols$SymbolApi;
       130: astore        13
       132: aload         6
       134: invokevirtual #177                // Method shapeless/LazyMacros$LazyDefinitions$Instance.copy$default$4:()Lscala/Option;
       137: astore        14
       139: aload         6
       141: invokevirtual #180                // Method shapeless/LazyMacros$LazyDefinitions$Instance.copy$default$5:()Lscala/reflect/api/Types$TypeApi;
       144: astore        15
       146: aload         6
       148: aload         11
       150: aload         12
       152: aload         13
       154: aload         14
       156: aload         15
       158: aload         9
       160: invokevirtual #184                // Method shapeless/LazyMacros$LazyDefinitions$Instance.copy:(Lscala/reflect/api/Types$TypeApi;Lscala/reflect/api/Names$TermNameApi;Lscala/reflect/api/Symbols$SymbolApi;Lscala/Option;Lscala/reflect/api/Types$TypeApi;Lscala/collection/immutable/List;)Lshapeless/LazyMacros$LazyDefinitions$Instance;
       163: astore        8
       165: aload         7
       167: aload         8
       169: invokevirtual #162                // Method scala/collection/immutable/List.$colon$colon:(Ljava/lang/Object;)Lscala/collection/immutable/List;
       172: astore_2
       173: goto          189
       176: goto          179
       179: new           #186                // class scala/MatchError
       182: dup
       183: aload         4
       185: invokespecial #190                // Method scala/MatchError."<init>":(Ljava/lang/Object;)V
       188: athrow
       189: aload_2
       190: astore_3
       191: aload_3
       192: astore        16
       194: aload_0
       195: invokevirtual #192                // Method copy$default$1:()Ljava/lang/String;
       198: astore        17
       200: aload_0
       201: invokevirtual #194                // Method copy$default$2:()Lscala/collection/immutable/ListMap;
       204: astore        18
       206: aload_0
       207: invokevirtual #196                // Method copy$default$4:()Lscala/collection/immutable/List;
       210: astore        19
       212: aload_0
       213: aload         17
       215: aload         18
       217: aload         16
       219: aload         19
       221: invokevirtual #199                // Method copy:(Ljava/lang/String;Lscala/collection/immutable/ListMap;Lscala/collection/immutable/List;Lscala/collection/immutable/List;)Lshapeless/LazyMacros$DerivationContext$State;
       224: areturn
      StackMapTable: number_of_entries = 8
        frame_type = 254 /* append */
          offset_delta = 24
          locals = [ top, top, class scala/collection/immutable/List ]
        frame_type = 2 /* same */
        frame_type = 254 /* append */
          offset_delta = 60
          locals = [ class scala/collection/immutable/$colon$colon, class shapeless/LazyMacros$LazyDefinitions$Instance, class scala/collection/immutable/List ]
        frame_type = 7 /* same */
        frame_type = 76 /* same_locals_1_stack_item */
          stack = [ class scala/collection/immutable/List ]
        frame_type = 248 /* chop */
          offset_delta = 66
        frame_type = 2 /* same */
        frame_type = 255 /* full_frame */
          offset_delta = 9
          locals = [ class shapeless/LazyMacros$DerivationContext$State, class scala/reflect/api/Types$TypeApi, class scala/collection/immutable/List, top, class scala/collection/immutable/List ]
          stack = []
      LineNumberTable:
        line 354: 0
        line 355: 6
        line 356: 27
        line 354: 179
        line 358: 191
      LocalVariableTable:
        Start  Length  Slot  Name   Signature
          109      54     9   x$1   Lscala/collection/immutable/List;
          116      47    11   x$2   Lscala/reflect/api/Types$TypeApi;
          123      40    12   x$3   Lscala/reflect/api/Names$TermNameApi;
          130      33    13   x$4   Lscala/reflect/api/Symbols$SymbolApi;
          137      26    14   x$5   Lscala/Option;
          144      19    15   x$6   Lscala/reflect/api/Types$TypeApi;
           50     126     6     h   Lshapeless/LazyMacros$LazyDefinitions$Instance;
           57     119     7     t   Lscala/collection/immutable/List;
          192      32    16   x$7   Lscala/collection/immutable/List;
          198      26    17   x$8   Ljava/lang/String;
          204      20    18   x$9   Lscala/collection/immutable/ListMap;
          210      14    19  x$10   Lscala/collection/immutable/List;
          190      34     3 open0   Lscala/collection/immutable/List;
            0     225     0  this   Lshapeless/LazyMacros$DerivationContext$State;
            0     225     1   tpe   Lscala/reflect/api/Types$TypeApi;
    MethodParameters:
      Name                           Flags
      tpe                            final

  private shapeless.LazyMacros$DerivationContext$State update(shapeless.LazyMacros$LazyDefinitions$Instance);
    descriptor: (Lshapeless/LazyMacros$LazyDefinitions$Instance;)Lshapeless/LazyMacros$DerivationContext$State;
    flags: (0x0002) ACC_PRIVATE
    Code:
      stack=5, locals=6, args_size=2
         0: aload_0
         1: invokevirtual #222                // Method dict:()Lscala/collection/immutable/ListMap;
         4: aload_0
         5: invokevirtual #226                // Method shapeless$LazyMacros$DerivationContext$State$$$outer:()Lshapeless/LazyMacros$DerivationContext;
         8: invokevirtual #229                // Method shapeless/LazyMacros$DerivationContext.TypeWrapper:()Lshapeless/LazyMacros$LazyDefinitions$TypeWrapper$;
        11: aload_1
        12: invokevirtual #123                // Method shapeless/LazyMacros$LazyDefinitions$Instance.instTpe:()Lscala/reflect/api/Types$TypeApi;
        15: invokevirtual #232                // Method shapeless/LazyMacros$LazyDefinitions$TypeWrapper$.apply:(Lscala/reflect/api/Types$TypeApi;)Lshapeless/LazyMacros$LazyDefinitions$TypeWrapper;
        18: aload_1
        19: invokevirtual #238                // Method scala/collection/immutable/ListMap.updated:(Ljava/lang/Object;Ljava/lang/Object;)Lscala/collection/immutable/ListMap;
        22: astore_2
        23: aload_0
        24: invokevirtual #192                // Method copy$default$1:()Ljava/lang/String;
        27: astore_3
        28: aload_0
        29: invokevirtual #240                // Method copy$default$3:()Lscala/collection/immutable/List;
        32: astore        4
        34: aload_0
        35: invokevirtual #196                // Method copy$default$4:()Lscala/collection/immutable/List;
        38: astore        5
        40: aload_0
        41: aload_3
        42: aload_2
        43: aload         4
        45: aload         5
        47: invokevirtual #199                // Method copy:(Ljava/lang/String;Lscala/collection/immutable/ListMap;Lscala/collection/immutable/List;Lscala/collection/immutable/List;)Lshapeless/LazyMacros$DerivationContext$State;
        50: areturn
      LineNumberTable:
        line 362: 0
      LocalVariableTable:
        Start  Length  Slot  Name   Signature
           22      28     2   x$1   Lscala/collection/immutable/ListMap;
           27      23     3   x$2   Ljava/lang/String;
           32      18     4   x$3   Lscala/collection/immutable/List;
           38      12     5   x$4   Lscala/collection/immutable/List;
            0      51     0  this   Lshapeless/LazyMacros$DerivationContext$State;
            0      51     1  inst   Lshapeless/LazyMacros$LazyDefinitions$Instance;
    MethodParameters:
      Name                           Flags
      inst                           final

  public scala.Tuple2<shapeless.LazyMacros$DerivationContext$State, shapeless.LazyMacros$LazyDefinitions$Instance> openInst(scala.reflect.api.Types$TypeApi);
    descriptor: (Lscala/reflect/api/Types$TypeApi;)Lscala/Tuple2;
    flags: (0x0001) ACC_PUBLIC
    Code:
      stack=7, locals=9, args_size=2
         0: aload_0
         1: invokevirtual #226                // Method shapeless$LazyMacros$DerivationContext$State$$$outer:()Lshapeless/LazyMacros$DerivationContext;
         4: invokevirtual #246                // Method shapeless/LazyMacros$DerivationContext.Instance:()Lshapeless/LazyMacros$LazyDefinitions$Instance$;
         7: aload_1
         8: invokevirtual #249                // Method shapeless/LazyMacros$LazyDefinitions$Instance$.apply:(Lscala/reflect/api/Types$TypeApi;)Lshapeless/LazyMacros$LazyDefinitions$Instance;
        11: astore_2
        12: aload_0
        13: aload_1
        14: invokevirtual #251                // Method addDependency:(Lscala/reflect/api/Types$TypeApi;)Lshapeless/LazyMacros$DerivationContext$State;
        17: astore_3
        18: new           #253                // class scala/Tuple2
        21: dup
        22: aload_2
        23: astore        5
        25: aload_3
        26: invokevirtual #100                // Method open:()Lscala/collection/immutable/List;
        29: aload         5
        31: invokevirtual #162                // Method scala/collection/immutable/List.$colon$colon:(Ljava/lang/Object;)Lscala/collection/immutable/List;
        34: astore        4
        36: aload_3
        37: invokevirtual #192                // Method copy$default$1:()Ljava/lang/String;
        40: astore        6
        42: aload_3
        43: invokevirtual #194                // Method copy$default$2:()Lscala/collection/immutable/ListMap;
        46: astore        7
        48: aload_3
        49: invokevirtual #196                // Method copy$default$4:()Lscala/collection/immutable/List;
        52: astore        8
        54: aload_3
        55: aload         6
        57: aload         7
        59: aload         4
        61: aload         8
        63: invokevirtual #199                // Method copy:(Ljava/lang/String;Lscala/collection/immutable/ListMap;Lscala/collection/immutable/List;Lscala/collection/immutable/List;)Lshapeless/LazyMacros$DerivationContext$State;
        66: aload_2
        67: invokespecial #255                // Method update:(Lshapeless/LazyMacros$LazyDefinitions$Instance;)Lshapeless/LazyMacros$DerivationContext$State;
        70: aload_2
        71: invokespecial #258                // Method scala/Tuple2."<init>":(Ljava/lang/Object;Ljava/lang/Object;)V
        74: areturn
      LineNumberTable:
        line 365: 0
        line 366: 12
        line 367: 18
      LocalVariableTable:
        Start  Length  Slot  Name   Signature
           34      32     4   x$1   Lscala/collection/immutable/List;
           40      26     6   x$2   Ljava/lang/String;
           46      20     7   x$3   Lscala/collection/immutable/ListMap;
           52      14     8   x$4   Lscala/collection/immutable/List;
           11      63     2  inst   Lshapeless/LazyMacros$LazyDefinitions$Instance;
           17      57     3 state0   Lshapeless/LazyMacros$DerivationContext$State;
            0      75     0  this   Lshapeless/LazyMacros$DerivationContext$State;
            0      75     1   tpe   Lscala/reflect/api/Types$TypeApi;
    Signature: #243                         // (Lscala/reflect/api/Types$TypeApi;)Lscala/Tuple2<Lshapeless/LazyMacros$DerivationContext$State;Lshapeless/LazyMacros$LazyDefinitions$Instance;>;
    MethodParameters:
      Name                           Flags
      tpe                            final

  public scala.Tuple2<shapeless.LazyMacros$DerivationContext$State, shapeless.LazyMacros$LazyDefinitions$Instance> closeInst(scala.reflect.api.Types$TypeApi, scala.reflect.api.Trees$TreeApi, scala.reflect.api.Types$TypeApi);
    descriptor: (Lscala/reflect/api/Types$TypeApi;Lscala/reflect/api/Trees$TreeApi;Lscala/reflect/api/Types$TypeApi;)Lscala/Tuple2;
    flags: (0x0001) ACC_PUBLIC
    Code:
      stack=7, locals=17, args_size=4
         0: getstatic     #269                // Field scala/Predef$.MODULE$:Lscala/Predef$;
         3: aload_0
         4: invokevirtual #100                // Method open:()Lscala/collection/immutable/List;
         7: invokevirtual #273                // Method scala/collection/immutable/List.nonEmpty:()Z
        10: invokevirtual #277                // Method scala/Predef$.assert:(Z)V
        13: getstatic     #269                // Field scala/Predef$.MODULE$:Lscala/Predef$;
        16: aload_0
        17: invokevirtual #100                // Method open:()Lscala/collection/immutable/List;
        20: invokevirtual #278                // Method scala/collection/immutable/List.head:()Ljava/lang/Object;
        23: checkcast     #50                 // class shapeless/LazyMacros$LazyDefinitions$Instance
        26: invokevirtual #123                // Method shapeless/LazyMacros$LazyDefinitions$Instance.instTpe:()Lscala/reflect/api/Types$TypeApi;
        29: aload_1
        30: invokevirtual #127                // Method scala/reflect/api/Types$TypeApi.$eq$colon$eq:(Lscala/reflect/api/Types$TypeApi;)Z
        33: invokevirtual #277                // Method scala/Predef$.assert:(Z)V
        36: aload_0
        37: invokevirtual #100                // Method open:()Lscala/collection/immutable/List;
        40: invokevirtual #278                // Method scala/collection/immutable/List.head:()Ljava/lang/Object;
        43: checkcast     #50                 // class shapeless/LazyMacros$LazyDefinitions$Instance
        46: astore        4
        48: aload_0
        49: invokevirtual #226                // Method shapeless$LazyMacros$DerivationContext$State$$$outer:()Lshapeless/LazyMacros$DerivationContext;
        52: invokevirtual #282                // Method shapeless/LazyMacros$DerivationContext.shapeless$LazyMacros$DerivationContext$$$outer:()Lshapeless/LazyMacros;
        55: invokevirtual #286                // Method shapeless/LazyMacros.c:()Lscala/reflect/macros/whitebox/Context;
        58: invokeinterface #292,  1          // InterfaceMethod scala/reflect/macros/whitebox/Context.internal:()Lscala/reflect/macros/Internals$ContextInternalApi;
        63: aload         4
        65: invokevirtual #295                // Method shapeless/LazyMacros$LazyDefinitions$Instance.symbol:()Lscala/reflect/api/Symbols$SymbolApi;
        68: aload_3
        69: invokeinterface #299,  3          // InterfaceMethod scala/reflect/macros/Internals$ContextInternalApi.setInfo:(Lscala/reflect/api/Symbols$SymbolApi;Lscala/reflect/api/Types$TypeApi;)Lscala/reflect/api/Symbols$SymbolApi;
        74: astore        5
        76: new           #301                // class scala/Some
        79: dup
        80: aload_2
        81: invokespecial #302                // Method scala/Some."<init>":(Ljava/lang/Object;)V
        84: astore        7
        86: aload_3
        87: astore        8
        89: aload         5
        91: astore        9
        93: aload         4
        95: invokevirtual #165                // Method shapeless/LazyMacros$LazyDefinitions$Instance.copy$default$1:()Lscala/reflect/api/Types$TypeApi;
        98: astore        10
       100: aload         4
       102: invokevirtual #169                // Method shapeless/LazyMacros$LazyDefinitions$Instance.copy$default$2:()Lscala/reflect/api/Names$TermNameApi;
       105: astore        11
       107: aload         4
       109: invokevirtual #305                // Method shapeless/LazyMacros$LazyDefinitions$Instance.copy$default$6:()Lscala/collection/immutable/List;
       112: astore        12
       114: aload         4
       116: aload         10
       118: aload         11
       120: aload         9
       122: aload         7
       124: aload         8
       126: aload         12
       128: invokevirtual #184                // Method shapeless/LazyMacros$LazyDefinitions$Instance.copy:(Lscala/reflect/api/Types$TypeApi;Lscala/reflect/api/Names$TermNameApi;Lscala/reflect/api/Symbols$SymbolApi;Lscala/Option;Lscala/reflect/api/Types$TypeApi;Lscala/collection/immutable/List;)Lshapeless/LazyMacros$LazyDefinitions$Instance;
       131: astore        6
       133: new           #253                // class scala/Tuple2
       136: dup
       137: aload_0
       138: invokevirtual #100                // Method open:()Lscala/collection/immutable/List;
       141: invokevirtual #308                // Method scala/collection/immutable/List.tail:()Ljava/lang/Object;
       144: checkcast     #154                // class scala/collection/immutable/List
       147: astore        13
       149: aload_0
       150: invokevirtual #192                // Method copy$default$1:()Ljava/lang/String;
       153: astore        14
       155: aload_0
       156: invokevirtual #194                // Method copy$default$2:()Lscala/collection/immutable/ListMap;
       159: astore        15
       161: aload_0
       162: invokevirtual #196                // Method copy$default$4:()Lscala/collection/immutable/List;
       165: astore        16
       167: aload_0
       168: aload         14
       170: aload         15
       172: aload         13
       174: aload         16
       176: invokevirtual #199                // Method copy:(Ljava/lang/String;Lscala/collection/immutable/ListMap;Lscala/collection/immutable/List;Lscala/collection/immutable/List;)Lshapeless/LazyMacros$DerivationContext$State;
       179: aload         6
       181: invokespecial #255                // Method update:(Lshapeless/LazyMacros$LazyDefinitions$Instance;)Lshapeless/LazyMacros$DerivationContext$State;
       184: aload         6
       186: invokespecial #258                // Method scala/Tuple2."<init>":(Ljava/lang/Object;Ljava/lang/Object;)V
       189: areturn
      LineNumberTable:
        line 371: 0
        line 372: 13
        line 373: 36
        line 374: 48
        line 375: 76
        line 376: 133
      LocalVariableTable:
        Start  Length  Slot  Name   Signature
           84      47     7   x$1   Lscala/Some;
           87      44     8   x$2   Lscala/reflect/api/Types$TypeApi;
           91      40     9   x$3   Lscala/reflect/api/Symbols$SymbolApi;
           98      33    10   x$4   Lscala/reflect/api/Types$TypeApi;
          105      26    11   x$5   Lscala/reflect/api/Names$TermNameApi;
          112      19    12   x$6   Lscala/collection/immutable/List;
          147      32    13   x$7   Lscala/collection/immutable/List;
          153      26    14   x$8   Ljava/lang/String;
          159      20    15   x$9   Lscala/collection/immutable/ListMap;
          165      14    16  x$10   Lscala/collection/immutable/List;
           46     143     4 instance   Lshapeless/LazyMacros$LazyDefinitions$Instance;
           74     115     5   sym   Lscala/reflect/api/Symbols$SymbolApi;
          131      58     6 instance0   Lshapeless/LazyMacros$LazyDefinitions$Instance;
            0     190     0  this   Lshapeless/LazyMacros$DerivationContext$State;
            0     190     1   tpe   Lscala/reflect/api/Types$TypeApi;
            0     190     2  tree   Lscala/reflect/api/Trees$TreeApi;
            0     190     3 actualTpe   Lscala/reflect/api/Types$TypeApi;
    Signature: #262                         // (Lscala/reflect/api/Types$TypeApi;Lscala/reflect/api/Trees$TreeApi;Lscala/reflect/api/Types$TypeApi;)Lscala/Tuple2<Lshapeless/LazyMacros$DerivationContext$State;Lshapeless/LazyMacros$LazyDefinitions$Instance;>;
    MethodParameters:
      Name                           Flags
      tpe                            final
      tree                           final
      actualTpe                      final

  public scala.util.Either<shapeless.LazyMacros$DerivationContext$State, scala.Tuple2<shapeless.LazyMacros$DerivationContext$State, shapeless.LazyMacros$LazyDefinitions$Instance>> lookup(scala.reflect.api.Types$TypeApi);
    descriptor: (Lscala/reflect/api/Types$TypeApi;)Lscala/util/Either;
    flags: (0x0001) ACC_PUBLIC
    Code:
      stack=5, locals=6, args_size=2
         0: aload_0
         1: invokevirtual #222                // Method dict:()Lscala/collection/immutable/ListMap;
         4: aload_0
         5: invokevirtual #226                // Method shapeless$LazyMacros$DerivationContext$State$$$outer:()Lshapeless/LazyMacros$DerivationContext;
         8: invokevirtual #229                // Method shapeless/LazyMacros$DerivationContext.TypeWrapper:()Lshapeless/LazyMacros$LazyDefinitions$TypeWrapper$;
        11: aload_1
        12: invokevirtual #232                // Method shapeless/LazyMacros$LazyDefinitions$TypeWrapper$.apply:(Lscala/reflect/api/Types$TypeApi;)Lshapeless/LazyMacros$LazyDefinitions$TypeWrapper;
        15: invokevirtual #320                // Method scala/collection/immutable/ListMap.get:(Ljava/lang/Object;)Lscala/Option;
        18: astore_3
        19: aload_3
        20: instanceof    #301                // class scala/Some
        23: ifeq          69
        26: aload_3
        27: checkcast     #301                // class scala/Some
        30: astore        4
        32: aload         4
        34: invokevirtual #323                // Method scala/Some.value:()Ljava/lang/Object;
        37: checkcast     #50                 // class shapeless/LazyMacros$LazyDefinitions$Instance
        40: astore        5
        42: getstatic     #328                // Field scala/package$.MODULE$:Lscala/package$;
        45: invokevirtual #332                // Method scala/package$.Right:()Lscala/util/Right$;
        48: new           #253                // class scala/Tuple2
        51: dup
        52: aload_0
        53: aload_1
        54: invokevirtual #251                // Method addDependency:(Lscala/reflect/api/Types$TypeApi;)Lshapeless/LazyMacros$DerivationContext$State;
        57: aload         5
        59: invokespecial #258                // Method scala/Tuple2."<init>":(Ljava/lang/Object;Ljava/lang/Object;)V
        62: invokevirtual #337                // Method scala/util/Right$.apply:(Ljava/lang/Object;)Lscala/util/Right;
        65: astore_2
        66: goto          115
        69: goto          72
        72: getstatic     #342                // Field scala/None$.MODULE$:Lscala/None$;
        75: aload_3
        76: invokevirtual #110                // Method java/lang/Object.equals:(Ljava/lang/Object;)Z
        79: ifeq          103
        82: getstatic     #328                // Field scala/package$.MODULE$:Lscala/package$;
        85: invokevirtual #346                // Method scala/package$.Left:()Lscala/util/Left$;
        88: aload_0
        89: aload_1
        90: invokevirtual #348                // Method openInst:(Lscala/reflect/api/Types$TypeApi;)Lscala/Tuple2;
        93: invokevirtual #351                // Method scala/Tuple2._1:()Ljava/lang/Object;
        96: invokevirtual #356                // Method scala/util/Left$.apply:(Ljava/lang/Object;)Lscala/util/Left;
        99: astore_2
       100: goto          115
       103: goto          106
       106: new           #186                // class scala/MatchError
       109: dup
       110: aload_3
       111: invokespecial #190                // Method scala/MatchError."<init>":(Ljava/lang/Object;)V
       114: athrow
       115: aload_2
       116: areturn
      StackMapTable: number_of_entries = 5
        frame_type = 253 /* append */
          offset_delta = 69
          locals = [ top, class scala/Option ]
        frame_type = 2 /* same */
        frame_type = 30 /* same */
        frame_type = 2 /* same */
        frame_type = 255 /* full_frame */
          offset_delta = 8
          locals = [ class shapeless/LazyMacros$DerivationContext$State, class scala/reflect/api/Types$TypeApi, class scala/util/Either, class scala/Option ]
          stack = []
      LineNumberTable:
        line 380: 0
        line 381: 19
        line 382: 72
        line 380: 106
      LocalVariableTable:
        Start  Length  Slot  Name   Signature
           40      29     5     i   Lshapeless/LazyMacros$LazyDefinitions$Instance;
            0     117     0  this   Lshapeless/LazyMacros$DerivationContext$State;
            0     117     1 instTpe   Lscala/reflect/api/Types$TypeApi;
    Signature: #316                         // (Lscala/reflect/api/Types$TypeApi;)Lscala/util/Either<Lshapeless/LazyMacros$DerivationContext$State;Lscala/Tuple2<Lshapeless/LazyMacros$DerivationContext$State;Lshapeless/LazyMacros$LazyDefinitions$Instance;>;>;
    MethodParameters:
      Name                           Flags
      instTpe                        final

  public scala.collection.immutable.List<shapeless.LazyMacros$LazyDefinitions$Instance> dependsOn(scala.reflect.api.Types$TypeApi);
    descriptor: (Lscala/reflect/api/Types$TypeApi;)Lscala/collection/immutable/List;
    flags: (0x0001) ACC_PUBLIC
    Code:
      stack=7, locals=2, args_size=2
         0: aload_0
         1: new           #112                // class scala/collection/immutable/$colon$colon
         4: dup
         5: new           #112                // class scala/collection/immutable/$colon$colon
         8: dup
         9: aload_1
        10: getstatic     #106                // Field scala/collection/immutable/Nil$.MODULE$:Lscala/collection/immutable/Nil$;
        13: invokespecial #366                // Method scala/collection/immutable/$colon$colon."<init>":(Ljava/lang/Object;Lscala/collection/immutable/List;)V
        16: checkcast     #154                // class scala/collection/immutable/List
        19: getstatic     #106                // Field scala/collection/immutable/Nil$.MODULE$:Lscala/collection/immutable/Nil$;
        22: invokespecial #366                // Method scala/collection/immutable/$colon$colon."<init>":(Ljava/lang/Object;Lscala/collection/immutable/List;)V
        25: checkcast     #154                // class scala/collection/immutable/List
        28: getstatic     #106                // Field scala/collection/immutable/Nil$.MODULE$:Lscala/collection/immutable/Nil$;
        31: invokespecial #370                // Method helper$1:(Lscala/collection/immutable/List;Lscala/collection/immutable/List;)Lscala/collection/immutable/List;
        34: areturn
      LineNumberTable:
        line 402: 0
      LocalVariableTable:
        Start  Length  Slot  Name   Signature
            0      35     0  this   Lshapeless/LazyMacros$DerivationContext$State;
            0      35     1   tpe   Lscala/reflect/api/Types$TypeApi;
    Signature: #363                         // (Lscala/reflect/api/Types$TypeApi;)Lscala/collection/immutable/List<Lshapeless/LazyMacros$LazyDefinitions$Instance;>;
    MethodParameters:
      Name                           Flags
      tpe                            final

  public shapeless.LazyMacros$DerivationContext$State copy(java.lang.String, scala.collection.immutable.ListMap<shapeless.LazyMacros$LazyDefinitions$TypeWrapper, shapeless.LazyMacros$LazyDefinitions$Instance>, scala.collection.immutable.List<shapeless.LazyMacros$LazyDefinitions$Instance>, scala.collection.immutable.List<shapeless.LazyMacros$LazyDefinitions$TypeWrapper>);
    descriptor: (Ljava/lang/String;Lscala/collection/immutable/ListMap;Lscala/collection/immutable/List;Lscala/collection/immutable/List;)Lshapeless/LazyMacros$DerivationContext$State;
    flags: (0x0001) ACC_PUBLIC
    Code:
      stack=7, locals=5, args_size=5
         0: new           #2                  // class shapeless/LazyMacros$DerivationContext$State
         3: dup
         4: aload_0
         5: invokevirtual #226                // Method shapeless$LazyMacros$DerivationContext$State$$$outer:()Lshapeless/LazyMacros$DerivationContext;
         8: aload_1
         9: aload_2
        10: aload_3
        11: aload         4
        13: invokespecial #374                // Method "<init>":(Lshapeless/LazyMacros$DerivationContext;Ljava/lang/String;Lscala/collection/immutable/ListMap;Lscala/collection/immutable/List;Lscala/collection/immutable/List;)V
        16: areturn
      LineNumberTable:
        line 345: 0
        line 346: 8
        line 347: 9
        line 348: 10
        line 350: 11
      LocalVariableTable:
        Start  Length  Slot  Name   Signature
            0      17     0  this   Lshapeless/LazyMacros$DerivationContext$State;
            0      17     1  name   Ljava/lang/String;
            0      17     2  dict   Lscala/collection/immutable/ListMap;
            0      17     3  open   Lscala/collection/immutable/List;
            0      17     4 prevent   Lscala/collection/immutable/List;
    Signature: #371                         // (Ljava/lang/String;Lscala/collection/immutable/ListMap<Lshapeless/LazyMacros$LazyDefinitions$TypeWrapper;Lshapeless/LazyMacros$LazyDefinitions$Instance;>;Lscala/collection/immutable/List<Lshapeless/LazyMacros$LazyDefinitions$Instance;>;Lscala/collection/immutable/List<Lshapeless/LazyMacros$LazyDefinitions$TypeWrapper;>;)Lshapeless/LazyMacros$DerivationContext$State;
    MethodParameters:
      Name                           Flags
      name                           final
      dict                           final
      open                           final
      prevent                        final

  public java.lang.String copy$default$1();
    descriptor: ()Ljava/lang/String;
    flags: (0x0001) ACC_PUBLIC
    Code:
      stack=1, locals=1, args_size=1
         0: aload_0
         1: invokevirtual #376                // Method name:()Ljava/lang/String;
         4: areturn
      LineNumberTable:
        line 346: 0
      LocalVariableTable:
        Start  Length  Slot  Name   Signature
            0       5     0  this   Lshapeless/LazyMacros$DerivationContext$State;

  public scala.collection.immutable.ListMap<shapeless.LazyMacros$LazyDefinitions$TypeWrapper, shapeless.LazyMacros$LazyDefinitions$Instance> copy$default$2();
    descriptor: ()Lscala/collection/immutable/ListMap;
    flags: (0x0001) ACC_PUBLIC
    Code:
      stack=1, locals=1, args_size=1
         0: aload_0
         1: invokevirtual #222                // Method dict:()Lscala/collection/immutable/ListMap;
         4: areturn
      LineNumberTable:
        line 347: 0
      LocalVariableTable:
        Start  Length  Slot  Name   Signature
            0       5     0  this   Lshapeless/LazyMacros$DerivationContext$State;
    Signature: #86                          // ()Lscala/collection/immutable/ListMap<Lshapeless/LazyMacros$LazyDefinitions$TypeWrapper;Lshapeless/LazyMacros$LazyDefinitions$Instance;>;

  public scala.collection.immutable.List<shapeless.LazyMacros$LazyDefinitions$Instance> copy$default$3();
    descriptor: ()Lscala/collection/immutable/List;
    flags: (0x0001) ACC_PUBLIC
    Code:
      stack=1, locals=1, args_size=1
         0: aload_0
         1: invokevirtual #100                // Method open:()Lscala/collection/immutable/List;
         4: areturn
      LineNumberTable:
        line 348: 0
      LocalVariableTable:
        Start  Length  Slot  Name   Signature
            0       5     0  this   Lshapeless/LazyMacros$DerivationContext$State;
    Signature: #90                          // ()Lscala/collection/immutable/List<Lshapeless/LazyMacros$LazyDefinitions$Instance;>;

  public scala.collection.immutable.List<shapeless.LazyMacros$LazyDefinitions$TypeWrapper> copy$default$4();
    descriptor: ()Lscala/collection/immutable/List;
    flags: (0x0001) ACC_PUBLIC
    Code:
      stack=1, locals=1, args_size=1
         0: aload_0
         1: invokevirtual #378                // Method prevent:()Lscala/collection/immutable/List;
         4: areturn
      LineNumberTable:
        line 350: 0
      LocalVariableTable:
        Start  Length  Slot  Name   Signature
            0       5     0  this   Lshapeless/LazyMacros$DerivationContext$State;
    Signature: #93                          // ()Lscala/collection/immutable/List<Lshapeless/LazyMacros$LazyDefinitions$TypeWrapper;>;

  public java.lang.String productPrefix();
    descriptor: ()Ljava/lang/String;
    flags: (0x0001) ACC_PUBLIC
    Code:
      stack=1, locals=1, args_size=1
         0: ldc_w         #380                // String State
         3: areturn
      LineNumberTable:
        line 345: 0
      LocalVariableTable:
        Start  Length  Slot  Name   Signature
            0       4     0  this   Lshapeless/LazyMacros$DerivationContext$State;

  public int productArity();
    descriptor: ()I
    flags: (0x0001) ACC_PUBLIC
    Code:
      stack=1, locals=1, args_size=1
         0: iconst_4
         1: ireturn
      LineNumberTable:
        line 345: 0
      LocalVariableTable:
        Start  Length  Slot  Name   Signature
            0       2     0  this   Lshapeless/LazyMacros$DerivationContext$State;

  public java.lang.Object productElement(int);
    descriptor: (I)Ljava/lang/Object;
    flags: (0x0001) ACC_PUBLIC
    Code:
      stack=1, locals=3, args_size=2
         0: iload_1
         1: istore_2
         2: iload_2
         3: tableswitch   { // 0 to 3
                       0: 32
                       1: 39
                       2: 46
                       3: 53
                 default: 60
            }
        32: aload_0
        33: invokevirtual #376                // Method name:()Ljava/lang/String;
        36: goto          67
        39: aload_0
        40: invokevirtual #222                // Method dict:()Lscala/collection/immutable/ListMap;
        43: goto          67
        46: aload_0
        47: invokevirtual #100                // Method open:()Lscala/collection/immutable/List;
        50: goto          67
        53: aload_0
        54: invokevirtual #378                // Method prevent:()Lscala/collection/immutable/List;
        57: goto          67
        60: iload_1
        61: invokestatic  #389                // Method scala/runtime/Statics.ioobe:(I)Ljava/lang/Object;
        64: goto          67
        67: areturn
      StackMapTable: number_of_entries = 6
        frame_type = 252 /* append */
          offset_delta = 32
          locals = [ int ]
        frame_type = 6 /* same */
        frame_type = 6 /* same */
        frame_type = 6 /* same */
        frame_type = 6 /* same */
        frame_type = 70 /* same_locals_1_stack_item */
          stack = [ class java/lang/Object ]
      LineNumberTable:
        line 345: 0
      LocalVariableTable:
        Start  Length  Slot  Name   Signature
            0      68     0  this   Lshapeless/LazyMacros$DerivationContext$State;
            0      68     1   x$1   I
    MethodParameters:
      Name                           Flags
      x$1                            final

  public scala.collection.Iterator<java.lang.Object> productIterator();
    descriptor: ()Lscala/collection/Iterator;
    flags: (0x0001) ACC_PUBLIC
    Code:
      stack=2, locals=1, args_size=1
         0: getstatic     #397                // Field scala/runtime/ScalaRunTime$.MODULE$:Lscala/runtime/ScalaRunTime$;
         3: aload_0
         4: invokevirtual #400                // Method scala/runtime/ScalaRunTime$.typedProductIterator:(Lscala/Product;)Lscala/collection/Iterator;
         7: areturn
      LineNumberTable:
        line 345: 0
      LocalVariableTable:
        Start  Length  Slot  Name   Signature
            0       8     0  this   Lshapeless/LazyMacros$DerivationContext$State;
    Signature: #392                         // ()Lscala/collection/Iterator<Ljava/lang/Object;>;

  public boolean canEqual(java.lang.Object);
    descriptor: (Ljava/lang/Object;)Z
    flags: (0x0001) ACC_PUBLIC
    Code:
      stack=1, locals=2, args_size=2
         0: aload_1
         1: instanceof    #2                  // class shapeless/LazyMacros$DerivationContext$State
         4: ireturn
      LineNumberTable:
        line 345: 0
      LocalVariableTable:
        Start  Length  Slot  Name   Signature
            0       5     0  this   Lshapeless/LazyMacros$DerivationContext$State;
            0       5     1   x$1   Ljava/lang/Object;
    MethodParameters:
      Name                           Flags
      x$1                            final

  public java.lang.String productElementName(int);
    descriptor: (I)Ljava/lang/String;
    flags: (0x0001) ACC_PUBLIC
    Code:
      stack=1, locals=3, args_size=2
         0: iload_1
         1: istore_2
         2: iload_2
         3: tableswitch   { // 0 to 3
                       0: 32
                       1: 38
                       2: 44
                       3: 50
                 default: 56
            }
        32: ldc_w         #405                // String name
        35: goto          66
        38: ldc_w         #406                // String dict
        41: goto          66
        44: ldc_w         #407                // String open
        47: goto          66
        50: ldc_w         #408                // String prevent
        53: goto          66
        56: iload_1
        57: invokestatic  #389                // Method scala/runtime/Statics.ioobe:(I)Ljava/lang/Object;
        60: checkcast     #410                // class java/lang/String
        63: goto          66
        66: areturn
      StackMapTable: number_of_entries = 6
        frame_type = 252 /* append */
          offset_delta = 32
          locals = [ int ]
        frame_type = 5 /* same */
        frame_type = 5 /* same */
        frame_type = 5 /* same */
        frame_type = 5 /* same */
        frame_type = 73 /* same_locals_1_stack_item */
          stack = [ class java/lang/String ]
      LineNumberTable:
        line 345: 0
      LocalVariableTable:
        Start  Length  Slot  Name   Signature
            0      67     0  this   Lshapeless/LazyMacros$DerivationContext$State;
            0      67     1   x$1   I
    MethodParameters:
      Name                           Flags
      x$1                            final

  public int hashCode();
    descriptor: ()I
    flags: (0x0001) ACC_PUBLIC
    Code:
      stack=2, locals=1, args_size=1
         0: getstatic     #397                // Field scala/runtime/ScalaRunTime$.MODULE$:Lscala/runtime/ScalaRunTime$;
         3: aload_0
         4: invokevirtual #415                // Method scala/runtime/ScalaRunTime$._hashCode:(Lscala/Product;)I
         7: ireturn
      LineNumberTable:
        line 345: 0
      LocalVariableTable:
        Start  Length  Slot  Name   Signature
            0       8     0  this   Lshapeless/LazyMacros$DerivationContext$State;

  public java.lang.String toString();
    descriptor: ()Ljava/lang/String;
    flags: (0x0001) ACC_PUBLIC
    Code:
      stack=2, locals=1, args_size=1
         0: getstatic     #397                // Field scala/runtime/ScalaRunTime$.MODULE$:Lscala/runtime/ScalaRunTime$;
         3: aload_0
         4: invokevirtual #420                // Method scala/runtime/ScalaRunTime$._toString:(Lscala/Product;)Ljava/lang/String;
         7: areturn
      LineNumberTable:
        line 345: 0
      LocalVariableTable:
        Start  Length  Slot  Name   Signature
            0       8     0  this   Lshapeless/LazyMacros$DerivationContext$State;

  public boolean equals(java.lang.Object);
    descriptor: (Ljava/lang/Object;)Z
    flags: (0x0001) ACC_PUBLIC
    Code:
      stack=2, locals=9, args_size=2
         0: aload_0
         1: aload_1
         2: if_acmpeq     196
         5: aload_1
         6: astore_3
         7: aload_3
         8: instanceof    #2                  // class shapeless/LazyMacros$DerivationContext$State
        11: ifeq          33
        14: aload_3
        15: checkcast     #2                  // class shapeless/LazyMacros$DerivationContext$State
        18: invokevirtual #226                // Method shapeless$LazyMacros$DerivationContext$State$$$outer:()Lshapeless/LazyMacros$DerivationContext;
        21: aload_0
        22: invokevirtual #226                // Method shapeless$LazyMacros$DerivationContext$State$$$outer:()Lshapeless/LazyMacros$DerivationContext;
        25: if_acmpne     33
        28: iconst_1
        29: istore_2
        30: goto          41
        33: goto          36
        36: iconst_0
        37: istore_2
        38: goto          41
        41: iload_2
        42: ifeq          200
        45: aload_1
        46: checkcast     #2                  // class shapeless/LazyMacros$DerivationContext$State
        49: astore        4
        51: aload_0
        52: invokevirtual #376                // Method name:()Ljava/lang/String;
        55: aload         4
        57: invokevirtual #376                // Method name:()Ljava/lang/String;
        60: astore        5
        62: dup
        63: ifnonnull     75
        66: pop
        67: aload         5
        69: ifnull        83
        72: goto          192
        75: aload         5
        77: invokevirtual #110                // Method java/lang/Object.equals:(Ljava/lang/Object;)Z
        80: ifeq          192
        83: aload_0
        84: invokevirtual #222                // Method dict:()Lscala/collection/immutable/ListMap;
        87: aload         4
        89: invokevirtual #222                // Method dict:()Lscala/collection/immutable/ListMap;
        92: astore        6
        94: dup
        95: ifnonnull     107
        98: pop
        99: aload         6
       101: ifnull        115
       104: goto          192
       107: aload         6
       109: invokevirtual #110                // Method java/lang/Object.equals:(Ljava/lang/Object;)Z
       112: ifeq          192
       115: aload_0
       116: invokevirtual #100                // Method open:()Lscala/collection/immutable/List;
       119: aload         4
       121: invokevirtual #100                // Method open:()Lscala/collection/immutable/List;
       124: astore        7
       126: dup
       127: ifnonnull     139
       130: pop
       131: aload         7
       133: ifnull        147
       136: goto          192
       139: aload         7
       141: invokevirtual #110                // Method java/lang/Object.equals:(Ljava/lang/Object;)Z
       144: ifeq          192
       147: aload_0
       148: invokevirtual #378                // Method prevent:()Lscala/collection/immutable/List;
       151: aload         4
       153: invokevirtual #378                // Method prevent:()Lscala/collection/immutable/List;
       156: astore        8
       158: dup
       159: ifnonnull     171
       162: pop
       163: aload         8
       165: ifnull        179
       168: goto          192
       171: aload         8
       173: invokevirtual #110                // Method java/lang/Object.equals:(Ljava/lang/Object;)Z
       176: ifeq          192
       179: aload         4
       181: aload_0
       182: invokevirtual #422                // Method canEqual:(Ljava/lang/Object;)Z
       185: ifeq          192
       188: iconst_1
       189: goto          193
       192: iconst_0
       193: ifeq          200
       196: iconst_1
       197: goto          201
       200: iconst_0
       201: ireturn
      StackMapTable: number_of_entries = 16
        frame_type = 253 /* append */
          offset_delta = 33
          locals = [ top, class java/lang/Object ]
        frame_type = 2 /* same */
        frame_type = 255 /* full_frame */
          offset_delta = 4
          locals = [ class shapeless/LazyMacros$DerivationContext$State, class java/lang/Object, int, class java/lang/Object ]
          stack = []
        frame_type = 255 /* full_frame */
          offset_delta = 33
          locals = [ class shapeless/LazyMacros$DerivationContext$State, class java/lang/Object, int, class java/lang/Object, class shapeless/LazyMacros$DerivationContext$State, class java/lang/String ]
          stack = [ class java/lang/String ]
        frame_type = 7 /* same */
        frame_type = 255 /* full_frame */
          offset_delta = 23
          locals = [ class shapeless/LazyMacros$DerivationContext$State, class java/lang/Object, int, class java/lang/Object, class shapeless/LazyMacros$DerivationContext$State, class java/lang/String, class scala/collection/immutable/ListMap ]
          stack = [ class scala/collection/immutable/ListMap ]
        frame_type = 7 /* same */
        frame_type = 255 /* full_frame */
          offset_delta = 23
          locals = [ class shapeless/LazyMacros$DerivationContext$State, class java/lang/Object, int, class java/lang/Object, class shapeless/LazyMacros$DerivationContext$State, class java/lang/String, class scala/collection/immutable/ListMap, class scala/collection/immutable/List ]
          stack = [ class scala/collection/immutable/List ]
        frame_type = 7 /* same */
        frame_type = 255 /* full_frame */
          offset_delta = 23
          locals = [ class shapeless/LazyMacros$DerivationContext$State, class java/lang/Object, int, class java/lang/Object, class shapeless/LazyMacros$DerivationContext$State, class java/lang/String, class scala/collection/immutable/ListMap, class scala/collection/immutable/List, class scala/collection/immutable/List ]
          stack = [ class scala/collection/immutable/List ]
        frame_type = 7 /* same */
        frame_type = 248 /* chop */
          offset_delta = 12
        frame_type = 64 /* same_locals_1_stack_item */
          stack = [ int ]
        frame_type = 255 /* full_frame */
          offset_delta = 2
          locals = [ class shapeless/LazyMacros$DerivationContext$State, class java/lang/Object ]
          stack = []
        frame_type = 253 /* append */
          offset_delta = 3
          locals = [ int, class java/lang/Object ]
        frame_type = 255 /* full_frame */
          offset_delta = 0
          locals = [ class shapeless/LazyMacros$DerivationContext$State, class java/lang/Object ]
          stack = [ int ]
      LineNumberTable:
        line 345: 0
      LocalVariableTable:
        Start  Length  Slot  Name   Signature
            0     202     0  this   Lshapeless/LazyMacros$DerivationContext$State;
            0     202     1   x$1   Ljava/lang/Object;
    MethodParameters:
      Name                           Flags
      x$1                            final

  public shapeless.LazyMacros$DerivationContext shapeless$LazyMacros$DerivationContext$State$$$outer();
    descriptor: ()Lshapeless/LazyMacros$DerivationContext;
    flags: (0x1001) ACC_PUBLIC, ACC_SYNTHETIC
    Code:
      stack=1, locals=1, args_size=1
         0: aload_0
         1: getfield      #424                // Field $outer:Lshapeless/LazyMacros$DerivationContext;
         4: areturn
      LineNumberTable:
        line 345: 0
      LocalVariableTable:
        Start  Length  Slot  Name   Signature
            0       5     0  this   Lshapeless/LazyMacros$DerivationContext$State;

  public static final boolean $anonfun$addDependency$1(scala.reflect.api.Types$TypeApi, scala.reflect.api.Types$TypeApi);
    descriptor: (Lscala/reflect/api/Types$TypeApi;Lscala/reflect/api/Types$TypeApi;)Z
    flags: (0x1019) ACC_PUBLIC, ACC_STATIC, ACC_FINAL, ACC_SYNTHETIC
    Code:
      stack=2, locals=2, args_size=2
         0: aload_1
         1: aload_0
         2: invokevirtual #127                // Method scala/reflect/api/Types$TypeApi.$eq$colon$eq:(Lscala/reflect/api/Types$TypeApi;)Z
         5: ireturn
      LineNumberTable:
        line 356: 0
      LocalVariableTable:
        Start  Length  Slot  Name   Signature
            0       6     0 tpe$2   Lscala/reflect/api/Types$TypeApi;
            0       6     1   x$7   Lscala/reflect/api/Types$TypeApi;
    MethodParameters:
      Name                           Flags
      tpe$2                          final
      x$7                            final

  public static final boolean $anonfun$dependsOn$1(scala.reflect.api.Types$TypeApi, shapeless.LazyMacros$LazyDefinitions$Instance);
    descriptor: (Lscala/reflect/api/Types$TypeApi;Lshapeless/LazyMacros$LazyDefinitions$Instance;)Z
    flags: (0x1019) ACC_PUBLIC, ACC_STATIC, ACC_FINAL, ACC_SYNTHETIC
    Code:
      stack=2, locals=2, args_size=2
         0: aload_1
         1: invokevirtual #123                // Method shapeless/LazyMacros$LazyDefinitions$Instance.instTpe:()Lscala/reflect/api/Types$TypeApi;
         4: aload_0
         5: invokevirtual #127                // Method scala/reflect/api/Types$TypeApi.$eq$colon$eq:(Lscala/reflect/api/Types$TypeApi;)Z
         8: ireturn
      LineNumberTable:
        line 394: 0
      LocalVariableTable:
        Start  Length  Slot  Name   Signature
            0       9     0   h$1   Lscala/reflect/api/Types$TypeApi;
            0       9     1   x$8   Lshapeless/LazyMacros$LazyDefinitions$Instance;
    MethodParameters:
      Name                           Flags
      h$1                            final
      x$8                            final

  private final scala.collection.immutable.List helper$1(scala.collection.immutable.List, scala.collection.immutable.List);
    descriptor: (Lscala/collection/immutable/List;Lscala/collection/immutable/List;)Lscala/collection/immutable/List;
    flags: (0x0012) ACC_PRIVATE, ACC_FINAL
    Code:
      stack=3, locals=20, args_size=3
         0: iconst_0
         1: istore        5
         3: aconst_null
         4: astore        6
         6: aload_1
         7: astore        7
         9: getstatic     #106                // Field scala/collection/immutable/Nil$.MODULE$:Lscala/collection/immutable/Nil$;
        12: aload         7
        14: invokevirtual #110                // Method java/lang/Object.equals:(Ljava/lang/Object;)Z
        17: ifeq          26
        20: aload_2
        21: astore        4
        23: goto          252
        26: goto          29
        29: aload         7
        31: instanceof    #112                // class scala/collection/immutable/$colon$colon
        34: ifeq          86
        37: iconst_1
        38: istore        5
        40: aload         7
        42: checkcast     #112                // class scala/collection/immutable/$colon$colon
        45: astore        6
        47: aload         6
        49: invokevirtual #116                // Method scala/collection/immutable/$colon$colon.head:()Ljava/lang/Object;
        52: checkcast     #154                // class scala/collection/immutable/List
        55: astore        8
        57: aload         6
        59: invokevirtual #119                // Method scala/collection/immutable/$colon$colon.next$access$1:()Lscala/collection/immutable/List;
        62: astore        9
        64: getstatic     #106                // Field scala/collection/immutable/Nil$.MODULE$:Lscala/collection/immutable/Nil$;
        67: aload         8
        69: invokevirtual #110                // Method java/lang/Object.equals:(Ljava/lang/Object;)Z
        72: ifeq          83
        75: aload         9
        77: aload_2
        78: astore_2
        79: astore_1
        80: goto          0
        83: goto          89
        86: goto          89
        89: iload         5
        91: ifeq          239
        94: aload         6
        96: invokevirtual #116                // Method scala/collection/immutable/$colon$colon.head:()Ljava/lang/Object;
        99: checkcast     #154                // class scala/collection/immutable/List
       102: astore        10
       104: aload         6
       106: invokevirtual #119                // Method scala/collection/immutable/$colon$colon.next$access$1:()Lscala/collection/immutable/List;
       109: astore        11
       111: aload         10
       113: instanceof    #112                // class scala/collection/immutable/$colon$colon
       116: ifeq          236
       119: aload         10
       121: checkcast     #112                // class scala/collection/immutable/$colon$colon
       124: astore        12
       126: aload         12
       128: invokevirtual #116                // Method scala/collection/immutable/$colon$colon.head:()Ljava/lang/Object;
       131: checkcast     #31                 // class scala/reflect/api/Types$TypeApi
       134: astore        13
       136: aload         12
       138: invokevirtual #119                // Method scala/collection/immutable/$colon$colon.next$access$1:()Lscala/collection/immutable/List;
       141: astore        14
       143: aload_2
       144: aload         13
       146: invokedynamic #440,  0            // InvokeDynamic #1:apply:(Lscala/reflect/api/Types$TypeApi;)Lscala/Function1;
       151: invokevirtual #158                // Method scala/collection/immutable/List.exists:(Lscala/Function1;)Z
       154: ifeq          174
       157: aload         14
       159: astore        15
       161: aload         11
       163: aload         15
       165: invokevirtual #162                // Method scala/collection/immutable/List.$colon$colon:(Ljava/lang/Object;)Lscala/collection/immutable/List;
       168: aload_2
       169: astore_2
       170: astore_1
       171: goto          0
       174: aload_0
       175: invokevirtual #222                // Method dict:()Lscala/collection/immutable/ListMap;
       178: aload_0
       179: invokevirtual #226                // Method shapeless$LazyMacros$DerivationContext$State$$$outer:()Lshapeless/LazyMacros$DerivationContext;
       182: invokevirtual #229                // Method shapeless/LazyMacros$DerivationContext.TypeWrapper:()Lshapeless/LazyMacros$LazyDefinitions$TypeWrapper$;
       185: aload         13
       187: invokevirtual #232                // Method shapeless/LazyMacros$LazyDefinitions$TypeWrapper$.apply:(Lscala/reflect/api/Types$TypeApi;)Lshapeless/LazyMacros$LazyDefinitions$TypeWrapper;
       190: invokevirtual #442                // Method scala/collection/immutable/ListMap.apply:(Ljava/lang/Object;)Ljava/lang/Object;
       193: checkcast     #50                 // class shapeless/LazyMacros$LazyDefinitions$Instance
       196: astore        16
       198: aload         16
       200: invokevirtual #130                // Method shapeless/LazyMacros$LazyDefinitions$Instance.dependsOn:()Lscala/collection/immutable/List;
       203: astore        17
       205: aload         14
       207: astore        18
       209: aload         11
       211: aload         18
       213: invokevirtual #162                // Method scala/collection/immutable/List.$colon$colon:(Ljava/lang/Object;)Lscala/collection/immutable/List;
       216: aload         17
       218: invokevirtual #162                // Method scala/collection/immutable/List.$colon$colon:(Ljava/lang/Object;)Lscala/collection/immutable/List;
       221: aload         16
       223: astore        19
       225: aload_2
       226: aload         19
       228: invokevirtual #162                // Method scala/collection/immutable/List.$colon$colon:(Ljava/lang/Object;)Lscala/collection/immutable/List;
       231: astore_2
       232: astore_1
       233: goto          0
       236: goto          242
       239: goto          242
       242: new           #186                // class scala/MatchError
       245: dup
       246: aload         7
       248: invokespecial #190                // Method scala/MatchError."<init>":(Ljava/lang/Object;)V
       251: athrow
       252: aload         4
       254: areturn
      StackMapTable: number_of_entries = 11
        frame_type = 0 /* same */
        frame_type = 255 /* full_frame */
          offset_delta = 25
          locals = [ class shapeless/LazyMacros$DerivationContext$State, class scala/collection/immutable/List, class scala/collection/immutable/List, top, top, int, null, class scala/collection/immutable/List ]
          stack = []
        frame_type = 2 /* same */
        frame_type = 255 /* full_frame */
          offset_delta = 53
          locals = [ class shapeless/LazyMacros$DerivationContext$State, class scala/collection/immutable/List, class scala/collection/immutable/List, top, top, int, class scala/collection/immutable/$colon$colon, class scala/collection/immutable/List, class scala/collection/immutable/List, class scala/collection/immutable/List ]
          stack = []
        frame_type = 255 /* full_frame */
          offset_delta = 2
          locals = [ class shapeless/LazyMacros$DerivationContext$State, class scala/collection/immutable/List, class scala/collection/immutable/List, top, top, int, null, class scala/collection/immutable/List ]
          stack = []
        frame_type = 255 /* full_frame */
          offset_delta = 2
          locals = [ class shapeless/LazyMacros$DerivationContext$State, class scala/collection/immutable/List, class scala/collection/immutable/List, top, top, int, class scala/collection/immutable/$colon$colon, class scala/collection/immutable/List ]
          stack = []
        frame_type = 255 /* full_frame */
          offset_delta = 84
          locals = [ class shapeless/LazyMacros$DerivationContext$State, class scala/collection/immutable/List, class scala/collection/immutable/List, top, top, int, class scala/collection/immutable/$colon$colon, class scala/collection/immutable/List, top, top, class scala/collection/immutable/List, class scala/collection/immutable/List, class scala/collection/immutable/$colon$colon, class scala/reflect/api/Types$TypeApi, class scala/collection/immutable/List ]
          stack = []
        frame_type = 248 /* chop */
          offset_delta = 61
        frame_type = 255 /* full_frame */
          offset_delta = 2
          locals = [ class shapeless/LazyMacros$DerivationContext$State, class scala/collection/immutable/List, class scala/collection/immutable/List, top, top, int, class scala/collection/immutable/$colon$colon, class scala/collection/immutable/List ]
          stack = []
        frame_type = 2 /* same */
        frame_type = 255 /* full_frame */
          offset_delta = 9
          locals = [ class shapeless/LazyMacros$DerivationContext$State, class scala/collection/immutable/List, class scala/collection/immutable/List, top, class scala/collection/immutable/List, int, null, class scala/collection/immutable/List ]
          stack = []
      LineNumberTable:
        line 389: 0
        line 390: 9
        line 391: 29
        line 392: 75
        line 391: 83
        line 393: 89
        line 394: 143
        line 395: 157
        line 397: 174
        line 398: 198
        line 393: 236
        line 389: 242
      LocalVariableTable:
        Start  Length  Slot  Name   Signature
           62      24     9     t   Lscala/collection/immutable/List;
          196      40    16  inst   Lshapeless/LazyMacros$LazyDefinitions$Instance;
          134     102    13     h   Lscala/reflect/api/Types$TypeApi;
          141      95    14    t0   Lscala/collection/immutable/List;
          109     130    11     t   Lscala/collection/immutable/List;
            0     255     0  this   Lshapeless/LazyMacros$DerivationContext$State;
            0     255     1  tpes   Lscala/collection/immutable/List;
            0     255     2   acc   Lscala/collection/immutable/List;
    MethodParameters:
      Name                           Flags
      tpes                           final
      acc                            final

  public shapeless.LazyMacros$DerivationContext$State(java.lang.String, scala.collection.immutable.ListMap<shapeless.LazyMacros$LazyDefinitions$TypeWrapper, shapeless.LazyMacros$LazyDefinitions$Instance>, scala.collection.immutable.List<shapeless.LazyMacros$LazyDefinitions$Instance>, scala.collection.immutable.List<shapeless.LazyMacros$LazyDefinitions$TypeWrapper>);
    descriptor: (Lshapeless/LazyMacros$DerivationContext;Ljava/lang/String;Lscala/collection/immutable/ListMap;Lscala/collection/immutable/List;Lscala/collection/immutable/List;)V
    flags: (0x0001) ACC_PUBLIC
    Code:
      stack=2, locals=6, args_size=6
         0: aload_0
         1: aload_2
         2: putfield      #84                 // Field name:Ljava/lang/String;
         5: aload_0
         6: aload_3
         7: putfield      #88                 // Field dict:Lscala/collection/immutable/ListMap;
        10: aload_0
        11: aload         4
        13: putfield      #92                 // Field open:Lscala/collection/immutable/List;
        16: aload_0
        17: aload         5
        19: putfield      #95                 // Field prevent:Lscala/collection/immutable/List;
        22: aload_1
        23: ifnonnull     28
        26: aconst_null
        27: athrow
        28: aload_0
        29: aload_1
        30: putfield      #424                // Field $outer:Lshapeless/LazyMacros$DerivationContext;
        33: aload_0
        34: invokespecial #447                // Method java/lang/Object."<init>":()V
        37: aload_0
        38: invokestatic  #451                // InterfaceMethod scala/Product.$init$:(Lscala/Product;)V
        41: return
      StackMapTable: number_of_entries = 1
        frame_type = 28 /* same */
      LineNumberTable:
        line 346: 0
        line 347: 5
        line 348: 10
        line 350: 16
        line 345: 22
      LocalVariableTable:
        Start  Length  Slot  Name   Signature
            0      42     0  this   Lshapeless/LazyMacros$DerivationContext$State;
            0      42     1 $outer   Lshapeless/LazyMacros$DerivationContext;
            0      42     2  name   Ljava/lang/String;
            0      42     3  dict   Lscala/collection/immutable/ListMap;
            0      42     4  open   Lscala/collection/immutable/List;
            0      42     5 prevent   Lscala/collection/immutable/List;
    Signature: #444                         // (Ljava/lang/String;Lscala/collection/immutable/ListMap<Lshapeless/LazyMacros$LazyDefinitions$TypeWrapper;Lshapeless/LazyMacros$LazyDefinitions$Instance;>;Lscala/collection/immutable/List<Lshapeless/LazyMacros$LazyDefinitions$Instance;>;Lscala/collection/immutable/List<Lshapeless/LazyMacros$LazyDefinitions$TypeWrapper;>;)V
    MethodParameters:
      Name                           Flags
      $outer                         final synthetic
      name                           final
      dict                           final
      open                           final
      prevent                        final

  public static final java.lang.Object $anonfun$addDependency$1$adapted(scala.reflect.api.Types$TypeApi, scala.reflect.api.Types$TypeApi);
    descriptor: (Lscala/reflect/api/Types$TypeApi;Lscala/reflect/api/Types$TypeApi;)Ljava/lang/Object;
    flags: (0x1019) ACC_PUBLIC, ACC_STATIC, ACC_FINAL, ACC_SYNTHETIC
    Code:
      stack=2, locals=2, args_size=2
         0: aload_0
         1: aload_1
         2: invokestatic  #453                // Method $anonfun$addDependency$1:(Lscala/reflect/api/Types$TypeApi;Lscala/reflect/api/Types$TypeApi;)Z
         5: invokestatic  #459                // Method scala/runtime/BoxesRunTime.boxToBoolean:(Z)Ljava/lang/Boolean;
         8: areturn
      LineNumberTable:
        line 356: 0
      LocalVariableTable:
        Start  Length  Slot  Name   Signature
            0       9     0 tpe$2   Lscala/reflect/api/Types$TypeApi;
            0       9     1   x$7   Lscala/reflect/api/Types$TypeApi;
    MethodParameters:
      Name                           Flags
      tpe$2                          final
      x$7                            final

  public static final java.lang.Object $anonfun$dependsOn$1$adapted(scala.reflect.api.Types$TypeApi, shapeless.LazyMacros$LazyDefinitions$Instance);
    descriptor: (Lscala/reflect/api/Types$TypeApi;Lshapeless/LazyMacros$LazyDefinitions$Instance;)Ljava/lang/Object;
    flags: (0x1019) ACC_PUBLIC, ACC_STATIC, ACC_FINAL, ACC_SYNTHETIC
    Code:
      stack=2, locals=2, args_size=2
         0: aload_0
         1: aload_1
         2: invokestatic  #461                // Method $anonfun$dependsOn$1:(Lscala/reflect/api/Types$TypeApi;Lshapeless/LazyMacros$LazyDefinitions$Instance;)Z
         5: invokestatic  #459                // Method scala/runtime/BoxesRunTime.boxToBoolean:(Z)Ljava/lang/Boolean;
         8: areturn
      LineNumberTable:
        line 394: 0
      LocalVariableTable:
        Start  Length  Slot  Name   Signature
            0       9     0   h$1   Lscala/reflect/api/Types$TypeApi;
            0       9     1   x$8   Lshapeless/LazyMacros$LazyDefinitions$Instance;
    MethodParameters:
      Name                           Flags
      h$1                            final
      x$8                            final

  private static java.lang.Object $deserializeLambda$(java.lang.invoke.SerializedLambda);
    descriptor: (Ljava/lang/invoke/SerializedLambda;)Ljava/lang/Object;
    flags: (0x100a) ACC_PRIVATE, ACC_STATIC, ACC_SYNTHETIC
    Code:
      stack=1, locals=1, args_size=1
         0: aload_0
         1: invokedynamic #473,  0            // InvokeDynamic #2:lambdaDeserialize:(Ljava/lang/invoke/SerializedLambda;)Ljava/lang/Object;
         6: areturn
}
InnerClasses:
  public static final #14= #11 of #13;    // Lookup=class java/lang/invoke/MethodHandles$Lookup of class java/lang/invoke/MethodHandles
  public #19= #16 of #18;                 // TermNameApi=class scala/reflect/api/Names$TermNameApi of class scala/reflect/api/Names
  public #24= #21 of #23;                 // SymbolApi=class scala/reflect/api/Symbols$SymbolApi of class scala/reflect/api/Symbols
  public #29= #26 of #28;                 // TreeApi=class scala/reflect/api/Trees$TreeApi of class scala/reflect/api/Trees
  public abstract #34= #31 of #33;        // TypeApi=class scala/reflect/api/Types$TypeApi of class scala/reflect/api/Types
  public #39= #36 of #38;                 // ContextInternalApi=class scala/reflect/macros/Internals$ContextInternalApi of class scala/reflect/macros/Internals
  public #44= #41 of #43;                 // DerivationContext=class shapeless/LazyMacros$DerivationContext of class shapeless/LazyMacros
  public #45= #2 of #41;                  // State=class shapeless/LazyMacros$DerivationContext$State of class shapeless/LazyMacros$DerivationContext
  public #48= #47 of #43;                 // LazyDefinitions=class shapeless/LazyMacros$LazyDefinitions of class shapeless/LazyMacros
  public #51= #50 of #47;                 // Instance=class shapeless/LazyMacros$LazyDefinitions$Instance of class shapeless/LazyMacros$LazyDefinitions
  public #54= #53 of #47;                 // Instance$=class shapeless/LazyMacros$LazyDefinitions$Instance$ of class shapeless/LazyMacros$LazyDefinitions
  public #57= #56 of #47;                 // TypeWrapper=class shapeless/LazyMacros$LazyDefinitions$TypeWrapper of class shapeless/LazyMacros$LazyDefinitions
  public #60= #59 of #47;                 // TypeWrapper$=class shapeless/LazyMacros$LazyDefinitions$TypeWrapper$ of class shapeless/LazyMacros$LazyDefinitions
SourceFile: "lazy.scala"
BootstrapMethods:
  0: #148 REF_invokeStatic java/lang/invoke/LambdaMetafactory.altMetafactory:(Ljava/lang/invoke/MethodHandles$Lookup;Ljava/lang/String;Ljava/lang/invoke/MethodType;[Ljava/lang/Object;)Ljava/lang/invoke/CallSite;
    Method arguments:
      #132 (Ljava/lang/Object;)Ljava/lang/Object;
      #137 REF_invokeStatic shapeless/LazyMacros$DerivationContext$State.$anonfun$addDependency$1$adapted:(Lscala/reflect/api/Types$TypeApi;Lscala/reflect/api/Types$TypeApi;)Ljava/lang/Object;
      #139 (Lscala/reflect/api/Types$TypeApi;)Ljava/lang/Object;
      #140 5
      #141 1
      #139 (Lscala/reflect/api/Types$TypeApi;)Ljava/lang/Object;
  1: #148 REF_invokeStatic java/lang/invoke/LambdaMetafactory.altMetafactory:(Ljava/lang/invoke/MethodHandles$Lookup;Ljava/lang/String;Ljava/lang/invoke/MethodType;[Ljava/lang/Object;)Ljava/lang/invoke/CallSite;
    Method arguments:
      #132 (Ljava/lang/Object;)Ljava/lang/Object;
      #437 REF_invokeStatic shapeless/LazyMacros$DerivationContext$State.$anonfun$dependsOn$1$adapted:(Lscala/reflect/api/Types$TypeApi;Lshapeless/LazyMacros$LazyDefinitions$Instance;)Ljava/lang/Object;
      #439 (Lshapeless/LazyMacros$LazyDefinitions$Instance;)Ljava/lang/Object;
      #140 5
      #141 1
      #439 (Lshapeless/LazyMacros$LazyDefinitions$Instance;)Ljava/lang/Object;
  2: #470 REF_invokeStatic scala/runtime/LambdaDeserialize.bootstrap:(Ljava/lang/invoke/MethodHandles$Lookup;Ljava/lang/String;Ljava/lang/invoke/MethodType;[Ljava/lang/invoke/MethodHandle;)Ljava/lang/invoke/CallSite;
    Method arguments:
      #137 REF_invokeStatic shapeless/LazyMacros$DerivationContext$State.$anonfun$addDependency$1$adapted:(Lscala/reflect/api/Types$TypeApi;Lscala/reflect/api/Types$TypeApi;)Ljava/lang/Object;
      #437 REF_invokeStatic shapeless/LazyMacros$DerivationContext$State.$anonfun$dependsOn$1$adapted:(Lscala/reflect/api/Types$TypeApi;Lshapeless/LazyMacros$LazyDefinitions$Instance;)Ljava/lang/Object;
  ScalaInlineInfo: length = 0xA4 (unknown attribute)
   01 00 00 20 00 85 00 86 01 01 A9 01 AA 01 01 B1
   01 B2 01 01 AC 01 AD 01 00 BB 01 74 00 00 60 00
   61 00 01 91 00 6C 00 01 04 01 05 00 00 A3 00 52
   00 00 A6 00 55 00 00 AA 00 59 00 00 AE 00 59 00
   00 B5 00 C5 00 00 80 01 6A 00 00 3F 00 55 00 00
   6B 00 6C 00 01 9B 01 7E 00 01 6F 01 70 01 01 3A
   01 3B 00 00 3D 00 52 00 00 42 00 59 00 00 F1 00
   F2 00 00 45 00 59 00 01 7D 01 7E 00 01 7F 01 80
   00 01 93 01 94 00 00 49 00 4A 00 01 87 00 4A 00
   01 7B 00 52 00 00 DF 00 E0 00 01 A0 00 52 00 00
   DA 00 DB 01
  Scala: length = 0x0 (unknown attribute)

