Classfile /Users/mw/Projects/slang-braindump/.jar/jar8/assemble/slang-braindump/assemble/content/shapeless/LowPriorityTypes$LowPriorityFor$.class
  Last modified May 29, 2022; size 5400 bytes
  SHA-256 checksum cffe84817f5fb9a3d62bb253675df8d7c3ead40be44e614344dabbb404cbf1ef
  Compiled from "lowpriority.scala"
public class shapeless.LowPriorityTypes$LowPriorityFor$
  minor version: 0
  major version: 52
  flags: (0x0021) ACC_PUBLIC, ACC_SUPER
  this_class: #2                          // shapeless/LowPriorityTypes$LowPriorityFor$
  super_class: #4                         // java/lang/Object
  interfaces: 0, fields: 1, methods: 2, attributes: 4
Constant pool:
    #1 = Utf8               shapeless/LowPriorityTypes$LowPriorityFor$
    #2 = Class              #1            // shapeless/LowPriorityTypes$LowPriorityFor$
    #3 = Utf8               java/lang/Object
    #4 = Class              #3            // java/lang/Object
    #5 = Utf8               lowpriority.scala
    #6 = Utf8               scala/collection/SeqFactory$UnapplySeqWrapper
    #7 = Class              #6            // scala/collection/SeqFactory$UnapplySeqWrapper
    #8 = Utf8               scala/collection/SeqFactory
    #9 = Class              #8            // scala/collection/SeqFactory
   #10 = Utf8               UnapplySeqWrapper
   #11 = Utf8               scala/collection/SeqFactory$UnapplySeqWrapper$
   #12 = Class              #11           // scala/collection/SeqFactory$UnapplySeqWrapper$
   #13 = Utf8               UnapplySeqWrapper$
   #14 = Utf8               scala/reflect/api/Constants$ConstantApi
   #15 = Class              #14           // scala/reflect/api/Constants$ConstantApi
   #16 = Utf8               scala/reflect/api/Constants
   #17 = Class              #16           // scala/reflect/api/Constants
   #18 = Utf8               ConstantApi
   #19 = Utf8               scala/reflect/api/Constants$ConstantExtractor
   #20 = Class              #19           // scala/reflect/api/Constants$ConstantExtractor
   #21 = Utf8               ConstantExtractor
   #22 = Utf8               scala/reflect/api/Symbols$SymbolApi
   #23 = Class              #22           // scala/reflect/api/Symbols$SymbolApi
   #24 = Utf8               scala/reflect/api/Symbols
   #25 = Class              #24           // scala/reflect/api/Symbols
   #26 = Utf8               SymbolApi
   #27 = Utf8               scala/reflect/api/Symbols$TypeSymbolApi
   #28 = Class              #27           // scala/reflect/api/Symbols$TypeSymbolApi
   #29 = Utf8               TypeSymbolApi
   #30 = Utf8               scala/reflect/api/Types$ConstantTypeApi
   #31 = Class              #30           // scala/reflect/api/Types$ConstantTypeApi
   #32 = Utf8               scala/reflect/api/Types
   #33 = Class              #32           // scala/reflect/api/Types
   #34 = Utf8               ConstantTypeApi
   #35 = Utf8               scala/reflect/api/Types$ConstantTypeExtractor
   #36 = Class              #35           // scala/reflect/api/Types$ConstantTypeExtractor
   #37 = Utf8               ConstantTypeExtractor
   #38 = Utf8               scala/reflect/api/Types$TypeApi
   #39 = Class              #38           // scala/reflect/api/Types$TypeApi
   #40 = Utf8               TypeApi
   #41 = Utf8               scala/reflect/api/Types$TypeRefApi
   #42 = Class              #41           // scala/reflect/api/Types$TypeRefApi
   #43 = Utf8               TypeRefApi
   #44 = Utf8               scala/reflect/api/Types$TypeRefExtractor
   #45 = Class              #44           // scala/reflect/api/Types$TypeRefExtractor
   #46 = Utf8               TypeRefExtractor
   #47 = Utf8               shapeless/LowPriorityTypes
   #48 = Class              #47           // shapeless/LowPriorityTypes
   #49 = Utf8               LowPriorityFor$
   #50 = Utf8               $outer
   #51 = Utf8               Lshapeless/LowPriorityTypes;
   #52 = Utf8               unapply
   #53 = Utf8               (Lscala/reflect/api/Types$TypeApi;)Lscala/Option;
   #54 = Utf8               (Lscala/reflect/api/Types$TypeApi;)Lscala/Option<Lscala/Tuple2<Ljava/lang/String;Lscala/reflect/api/Types$TypeApi;>;>;
   #55 = Utf8               tpe
   #56 = Utf8               dealias
   #57 = Utf8               ()Lscala/reflect/api/Types$TypeApi;
   #58 = NameAndType        #56:#57       // dealias:()Lscala/reflect/api/Types$TypeApi;
   #59 = Methodref          #39.#58       // scala/reflect/api/Types$TypeApi.dealias:()Lscala/reflect/api/Types$TypeApi;
   #60 = NameAndType        #50:#51       // $outer:Lshapeless/LowPriorityTypes;
   #61 = Fieldref           #2.#60        // shapeless/LowPriorityTypes$LowPriorityFor$.$outer:Lshapeless/LowPriorityTypes;
   #62 = Utf8               c
   #63 = Utf8               ()Lscala/reflect/macros/whitebox/Context;
   #64 = NameAndType        #62:#63       // c:()Lscala/reflect/macros/whitebox/Context;
   #65 = InterfaceMethodref #48.#64       // shapeless/LowPriorityTypes.c:()Lscala/reflect/macros/whitebox/Context;
   #66 = Utf8               scala/reflect/macros/whitebox/Context
   #67 = Class              #66           // scala/reflect/macros/whitebox/Context
   #68 = Utf8               universe
   #69 = Utf8               ()Lscala/reflect/macros/Universe;
   #70 = NameAndType        #68:#69       // universe:()Lscala/reflect/macros/Universe;
   #71 = InterfaceMethodref #67.#70       // scala/reflect/macros/whitebox/Context.universe:()Lscala/reflect/macros/Universe;
   #72 = Utf8               scala/reflect/macros/Universe
   #73 = Class              #72           // scala/reflect/macros/Universe
   #74 = Utf8               TypeRefTag
   #75 = Utf8               ()Lscala/reflect/ClassTag;
   #76 = NameAndType        #74:#75       // TypeRefTag:()Lscala/reflect/ClassTag;
   #77 = Methodref          #73.#76       // scala/reflect/macros/Universe.TypeRefTag:()Lscala/reflect/ClassTag;
   #78 = Utf8               scala/reflect/ClassTag
   #79 = Class              #78           // scala/reflect/ClassTag
   #80 = Utf8               (Ljava/lang/Object;)Lscala/Option;
   #81 = NameAndType        #52:#80       // unapply:(Ljava/lang/Object;)Lscala/Option;
   #82 = InterfaceMethodref #79.#81       // scala/reflect/ClassTag.unapply:(Ljava/lang/Object;)Lscala/Option;
   #83 = Utf8               scala/Option
   #84 = Class              #83           // scala/Option
   #85 = Utf8               isEmpty
   #86 = Utf8               ()Z
   #87 = NameAndType        #85:#86       // isEmpty:()Z
   #88 = Methodref          #84.#87       // scala/Option.isEmpty:()Z
   #89 = Utf8               get
   #90 = Utf8               ()Ljava/lang/Object;
   #91 = NameAndType        #89:#90       // get:()Ljava/lang/Object;
   #92 = Methodref          #84.#91       // scala/Option.get:()Ljava/lang/Object;
   #93 = Utf8               TypeRef
   #94 = Utf8               ()Lscala/reflect/api/Types$TypeRefExtractor;
   #95 = NameAndType        #93:#94       // TypeRef:()Lscala/reflect/api/Types$TypeRefExtractor;
   #96 = Methodref          #73.#95       // scala/reflect/macros/Universe.TypeRef:()Lscala/reflect/api/Types$TypeRefExtractor;
   #97 = Utf8               (Lscala/reflect/api/Types$TypeRefApi;)Lscala/Option;
   #98 = NameAndType        #52:#97       // unapply:(Lscala/reflect/api/Types$TypeRefApi;)Lscala/Option;
   #99 = Methodref          #45.#98       // scala/reflect/api/Types$TypeRefExtractor.unapply:(Lscala/reflect/api/Types$TypeRefApi;)Lscala/Option;
  #100 = Utf8               scala/Tuple3
  #101 = Class              #100          // scala/Tuple3
  #102 = Utf8               _2
  #103 = NameAndType        #102:#90      // _2:()Ljava/lang/Object;
  #104 = Methodref          #101.#103     // scala/Tuple3._2:()Ljava/lang/Object;
  #105 = Utf8               _3
  #106 = NameAndType        #105:#90      // _3:()Ljava/lang/Object;
  #107 = Methodref          #101.#106     // scala/Tuple3._3:()Ljava/lang/Object;
  #108 = Utf8               scala/collection/immutable/List
  #109 = Class              #108          // scala/collection/immutable/List
  #110 = Utf8               scala/collection/immutable/List$
  #111 = Class              #110          // scala/collection/immutable/List$
  #112 = Utf8               MODULE$
  #113 = Utf8               Lscala/collection/immutable/List$;
  #114 = NameAndType        #112:#113     // MODULE$:Lscala/collection/immutable/List$;
  #115 = Fieldref           #111.#114     // scala/collection/immutable/List$.MODULE$:Lscala/collection/immutable/List$;
  #116 = Utf8               unapplySeq
  #117 = Utf8               (Lscala/collection/SeqOps;)Lscala/collection/SeqOps;
  #118 = NameAndType        #116:#117     // unapplySeq:(Lscala/collection/SeqOps;)Lscala/collection/SeqOps;
  #119 = Methodref          #111.#118     // scala/collection/immutable/List$.unapplySeq:(Lscala/collection/SeqOps;)Lscala/collection/SeqOps;
  #120 = Utf8               Lscala/collection/SeqFactory$UnapplySeqWrapper$;
  #121 = NameAndType        #112:#120     // MODULE$:Lscala/collection/SeqFactory$UnapplySeqWrapper$;
  #122 = Fieldref           #12.#121      // scala/collection/SeqFactory$UnapplySeqWrapper$.MODULE$:Lscala/collection/SeqFactory$UnapplySeqWrapper$;
  #123 = Utf8               isEmpty$extension
  #124 = Utf8               (Lscala/collection/SeqOps;)Z
  #125 = NameAndType        #123:#124     // isEmpty$extension:(Lscala/collection/SeqOps;)Z
  #126 = Methodref          #12.#125      // scala/collection/SeqFactory$UnapplySeqWrapper$.isEmpty$extension:(Lscala/collection/SeqOps;)Z
  #127 = Utf8               get$extension
  #128 = NameAndType        #127:#117     // get$extension:(Lscala/collection/SeqOps;)Lscala/collection/SeqOps;
  #129 = Methodref          #12.#128      // scala/collection/SeqFactory$UnapplySeqWrapper$.get$extension:(Lscala/collection/SeqOps;)Lscala/collection/SeqOps;
  #130 = Utf8               <init>
  #131 = Utf8               (Lscala/collection/SeqOps;)V
  #132 = NameAndType        #130:#131     // "<init>":(Lscala/collection/SeqOps;)V
  #133 = Methodref          #7.#132       // scala/collection/SeqFactory$UnapplySeqWrapper."<init>":(Lscala/collection/SeqOps;)V
  #134 = Utf8               lengthCompare$extension
  #135 = Utf8               (Lscala/collection/SeqOps;I)I
  #136 = NameAndType        #134:#135     // lengthCompare$extension:(Lscala/collection/SeqOps;I)I
  #137 = Methodref          #12.#136      // scala/collection/SeqFactory$UnapplySeqWrapper$.lengthCompare$extension:(Lscala/collection/SeqOps;I)I
  #138 = Utf8               apply$extension
  #139 = Utf8               (Lscala/collection/SeqOps;I)Ljava/lang/Object;
  #140 = NameAndType        #138:#139     // apply$extension:(Lscala/collection/SeqOps;I)Ljava/lang/Object;
  #141 = Methodref          #12.#140      // scala/collection/SeqFactory$UnapplySeqWrapper$.apply$extension:(Lscala/collection/SeqOps;I)Ljava/lang/Object;
  #142 = Utf8               asType
  #143 = Utf8               ()Lscala/reflect/api/Symbols$TypeSymbolApi;
  #144 = NameAndType        #142:#143     // asType:()Lscala/reflect/api/Symbols$TypeSymbolApi;
  #145 = InterfaceMethodref #23.#144      // scala/reflect/api/Symbols$SymbolApi.asType:()Lscala/reflect/api/Symbols$TypeSymbolApi;
  #146 = Utf8               toType
  #147 = NameAndType        #146:#57      // toType:()Lscala/reflect/api/Types$TypeApi;
  #148 = InterfaceMethodref #28.#147      // scala/reflect/api/Symbols$TypeSymbolApi.toType:()Lscala/reflect/api/Types$TypeApi;
  #149 = Utf8               typeConstructor
  #150 = NameAndType        #149:#57      // typeConstructor:()Lscala/reflect/api/Types$TypeApi;
  #151 = Methodref          #39.#150      // scala/reflect/api/Types$TypeApi.typeConstructor:()Lscala/reflect/api/Types$TypeApi;
  #152 = Utf8               lowPriorityForTpe
  #153 = NameAndType        #152:#57      // lowPriorityForTpe:()Lscala/reflect/api/Types$TypeApi;
  #154 = InterfaceMethodref #48.#153      // shapeless/LowPriorityTypes.lowPriorityForTpe:()Lscala/reflect/api/Types$TypeApi;
  #155 = Utf8               $eq$colon$eq
  #156 = Utf8               (Lscala/reflect/api/Types$TypeApi;)Z
  #157 = NameAndType        #155:#156     // $eq$colon$eq:(Lscala/reflect/api/Types$TypeApi;)Z
  #158 = Methodref          #39.#157      // scala/reflect/api/Types$TypeApi.$eq$colon$eq:(Lscala/reflect/api/Types$TypeApi;)Z
  #159 = Utf8               scala/Some
  #160 = Class              #159          // scala/Some
  #161 = Utf8               scala/Tuple2
  #162 = Class              #161          // scala/Tuple2
  #163 = Utf8
  #164 = String             #163          //
  #165 = Utf8               (Ljava/lang/Object;Ljava/lang/Object;)V
  #166 = NameAndType        #130:#165     // "<init>":(Ljava/lang/Object;Ljava/lang/Object;)V
  #167 = Methodref          #162.#166     // scala/Tuple2."<init>":(Ljava/lang/Object;Ljava/lang/Object;)V
  #168 = Utf8               (Ljava/lang/Object;)V
  #169 = NameAndType        #130:#168     // "<init>":(Ljava/lang/Object;)V
  #170 = Methodref          #160.#169     // scala/Some."<init>":(Ljava/lang/Object;)V
  #171 = Utf8               ConstantTypeTag
  #172 = NameAndType        #171:#75      // ConstantTypeTag:()Lscala/reflect/ClassTag;
  #173 = Methodref          #73.#172      // scala/reflect/macros/Universe.ConstantTypeTag:()Lscala/reflect/ClassTag;
  #174 = Utf8               ConstantType
  #175 = Utf8               ()Lscala/reflect/api/Types$ConstantTypeExtractor;
  #176 = NameAndType        #174:#175     // ConstantType:()Lscala/reflect/api/Types$ConstantTypeExtractor;
  #177 = Methodref          #73.#176      // scala/reflect/macros/Universe.ConstantType:()Lscala/reflect/api/Types$ConstantTypeExtractor;
  #178 = Utf8               (Lscala/reflect/api/Types$ConstantTypeApi;)Lscala/Option;
  #179 = NameAndType        #52:#178      // unapply:(Lscala/reflect/api/Types$ConstantTypeApi;)Lscala/Option;
  #180 = Methodref          #36.#179      // scala/reflect/api/Types$ConstantTypeExtractor.unapply:(Lscala/reflect/api/Types$ConstantTypeApi;)Lscala/Option;
  #181 = Utf8               ConstantTag
  #182 = NameAndType        #181:#75      // ConstantTag:()Lscala/reflect/ClassTag;
  #183 = Methodref          #73.#182      // scala/reflect/macros/Universe.ConstantTag:()Lscala/reflect/ClassTag;
  #184 = Utf8               Constant
  #185 = Utf8               ()Lscala/reflect/api/Constants$ConstantExtractor;
  #186 = NameAndType        #184:#185     // Constant:()Lscala/reflect/api/Constants$ConstantExtractor;
  #187 = Methodref          #73.#186      // scala/reflect/macros/Universe.Constant:()Lscala/reflect/api/Constants$ConstantExtractor;
  #188 = Utf8               (Lscala/reflect/api/Constants$ConstantApi;)Lscala/Option;
  #189 = NameAndType        #52:#188      // unapply:(Lscala/reflect/api/Constants$ConstantApi;)Lscala/Option;
  #190 = Methodref          #20.#189      // scala/reflect/api/Constants$ConstantExtractor.unapply:(Lscala/reflect/api/Constants$ConstantApi;)Lscala/Option;
  #191 = Utf8               java/lang/String
  #192 = Class              #191          // java/lang/String
  #193 = Utf8               lowPriorityForIgnoringTpe
  #194 = NameAndType        #193:#57      // lowPriorityForIgnoringTpe:()Lscala/reflect/api/Types$TypeApi;
  #195 = InterfaceMethodref #48.#194      // shapeless/LowPriorityTypes.lowPriorityForIgnoringTpe:()Lscala/reflect/api/Types$TypeApi;
  #196 = Utf8               scala/collection/StringOps$
  #197 = Class              #196          // scala/collection/StringOps$
  #198 = Utf8               Lscala/collection/StringOps$;
  #199 = NameAndType        #112:#198     // MODULE$:Lscala/collection/StringOps$;
  #200 = Fieldref           #197.#199     // scala/collection/StringOps$.MODULE$:Lscala/collection/StringOps$;
  #201 = Utf8               scala/Predef$
  #202 = Class              #201          // scala/Predef$
  #203 = Utf8               Lscala/Predef$;
  #204 = NameAndType        #112:#203     // MODULE$:Lscala/Predef$;
  #205 = Fieldref           #202.#204     // scala/Predef$.MODULE$:Lscala/Predef$;
  #206 = Utf8               augmentString
  #207 = Utf8               (Ljava/lang/String;)Ljava/lang/String;
  #208 = NameAndType        #206:#207     // augmentString:(Ljava/lang/String;)Ljava/lang/String;
  #209 = Methodref          #202.#208     // scala/Predef$.augmentString:(Ljava/lang/String;)Ljava/lang/String;
  #210 = Utf8               nonEmpty$extension
  #211 = Utf8               (Ljava/lang/String;)Z
  #212 = NameAndType        #210:#211     // nonEmpty$extension:(Ljava/lang/String;)Z
  #213 = Methodref          #197.#212     // scala/collection/StringOps$.nonEmpty$extension:(Ljava/lang/String;)Z
  #214 = Utf8               scala/None$
  #215 = Class              #214          // scala/None$
  #216 = Utf8               Lscala/None$;
  #217 = NameAndType        #112:#216     // MODULE$:Lscala/None$;
  #218 = Fieldref           #215.#217     // scala/None$.MODULE$:Lscala/None$;
  #219 = Utf8               highTpe
  #220 = Utf8               Lscala/reflect/api/Types$TypeApi;
  #221 = Utf8               cpdTpe
  #222 = Utf8               Lscala/reflect/api/Symbols$SymbolApi;
  #223 = Utf8               ignored
  #224 = Utf8               Ljava/lang/Object;
  #225 = Utf8               tTpe
  #226 = Utf8               this
  #227 = Utf8               Lshapeless/LowPriorityTypes$LowPriorityFor$;
  #228 = Utf8               scala/collection/SeqOps
  #229 = Class              #228          // scala/collection/SeqOps
  #230 = Utf8               (Lshapeless/LowPriorityTypes;)V
  #231 = Utf8               ()V
  #232 = NameAndType        #130:#231     // "<init>":()V
  #233 = Methodref          #4.#232       // java/lang/Object."<init>":()V
  #234 = Utf8               Code
  #235 = Utf8               StackMapTable
  #236 = Utf8               LineNumberTable
  #237 = Utf8               LocalVariableTable
  #238 = Utf8               Signature
  #239 = Utf8               MethodParameters
  #240 = Utf8               InnerClasses
  #241 = Utf8               SourceFile
  #242 = Utf8               ScalaInlineInfo
  #243 = Utf8               Scala
{
  private final shapeless.LowPriorityTypes $outer;
    descriptor: Lshapeless/LowPriorityTypes;
    flags: (0x1012) ACC_PRIVATE, ACC_FINAL, ACC_SYNTHETIC

  public scala.Option<scala.Tuple2<java.lang.String, scala.reflect.api.Types$TypeApi>> unapply(scala.reflect.api.Types$TypeApi);
    descriptor: (Lscala/reflect/api/Types$TypeApi;)Lscala/Option;
    flags: (0x0001) ACC_PUBLIC
    Code:
      stack=6, locals=28, args_size=2
         0: aload_1
         1: invokevirtual #59                 // Method scala/reflect/api/Types$TypeApi.dealias:()Lscala/reflect/api/Types$TypeApi;
         4: astore_3
         5: aload_3
         6: ifnull        274
         9: aload_0
        10: getfield      #61                 // Field $outer:Lshapeless/LowPriorityTypes;
        13: invokeinterface #65,  1           // InterfaceMethod shapeless/LowPriorityTypes.c:()Lscala/reflect/macros/whitebox/Context;
        18: invokeinterface #71,  1           // InterfaceMethod scala/reflect/macros/whitebox/Context.universe:()Lscala/reflect/macros/Universe;
        23: invokevirtual #77                 // Method scala/reflect/macros/Universe.TypeRefTag:()Lscala/reflect/ClassTag;
        26: aload_3
        27: invokeinterface #82,  2           // InterfaceMethod scala/reflect/ClassTag.unapply:(Ljava/lang/Object;)Lscala/Option;
        32: astore        4
        34: aload         4
        36: invokevirtual #88                 // Method scala/Option.isEmpty:()Z
        39: ifne          271
        42: aload         4
        44: invokevirtual #92                 // Method scala/Option.get:()Ljava/lang/Object;
        47: checkcast     #42                 // class scala/reflect/api/Types$TypeRefApi
        50: astore        5
        52: aload         5
        54: ifnull        268
        57: aload_0
        58: getfield      #61                 // Field $outer:Lshapeless/LowPriorityTypes;
        61: invokeinterface #65,  1           // InterfaceMethod shapeless/LowPriorityTypes.c:()Lscala/reflect/macros/whitebox/Context;
        66: invokeinterface #71,  1           // InterfaceMethod scala/reflect/macros/whitebox/Context.universe:()Lscala/reflect/macros/Universe;
        71: invokevirtual #96                 // Method scala/reflect/macros/Universe.TypeRef:()Lscala/reflect/api/Types$TypeRefExtractor;
        74: aload         5
        76: invokevirtual #99                 // Method scala/reflect/api/Types$TypeRefExtractor.unapply:(Lscala/reflect/api/Types$TypeRefApi;)Lscala/Option;
        79: astore        6
        81: aload         6
        83: invokevirtual #88                 // Method scala/Option.isEmpty:()Z
        86: ifne          265
        89: aload         6
        91: invokevirtual #92                 // Method scala/Option.get:()Ljava/lang/Object;
        94: checkcast     #101                // class scala/Tuple3
        97: invokevirtual #104                // Method scala/Tuple3._2:()Ljava/lang/Object;
       100: checkcast     #23                 // class scala/reflect/api/Symbols$SymbolApi
       103: astore        7
       105: aload         6
       107: invokevirtual #92                 // Method scala/Option.get:()Ljava/lang/Object;
       110: checkcast     #101                // class scala/Tuple3
       113: invokevirtual #107                // Method scala/Tuple3._3:()Ljava/lang/Object;
       116: checkcast     #109                // class scala/collection/immutable/List
       119: astore        8
       121: aload         8
       123: ifnull        262
       126: getstatic     #115                // Field scala/collection/immutable/List$.MODULE$:Lscala/collection/immutable/List$;
       129: aload         8
       131: invokevirtual #119                // Method scala/collection/immutable/List$.unapplySeq:(Lscala/collection/SeqOps;)Lscala/collection/SeqOps;
       134: astore        9
       136: getstatic     #122                // Field scala/collection/SeqFactory$UnapplySeqWrapper$.MODULE$:Lscala/collection/SeqFactory$UnapplySeqWrapper$;
       139: aload         9
       141: invokevirtual #126                // Method scala/collection/SeqFactory$UnapplySeqWrapper$.isEmpty$extension:(Lscala/collection/SeqOps;)Z
       144: ifne          259
       147: new           #7                  // class scala/collection/SeqFactory$UnapplySeqWrapper
       150: dup
       151: getstatic     #122                // Field scala/collection/SeqFactory$UnapplySeqWrapper$.MODULE$:Lscala/collection/SeqFactory$UnapplySeqWrapper$;
       154: aload         9
       156: invokevirtual #129                // Method scala/collection/SeqFactory$UnapplySeqWrapper$.get$extension:(Lscala/collection/SeqOps;)Lscala/collection/SeqOps;
       159: invokespecial #133                // Method scala/collection/SeqFactory$UnapplySeqWrapper."<init>":(Lscala/collection/SeqOps;)V
       162: ifnull        259
       165: getstatic     #122                // Field scala/collection/SeqFactory$UnapplySeqWrapper$.MODULE$:Lscala/collection/SeqFactory$UnapplySeqWrapper$;
       168: getstatic     #122                // Field scala/collection/SeqFactory$UnapplySeqWrapper$.MODULE$:Lscala/collection/SeqFactory$UnapplySeqWrapper$;
       171: aload         9
       173: invokevirtual #129                // Method scala/collection/SeqFactory$UnapplySeqWrapper$.get$extension:(Lscala/collection/SeqOps;)Lscala/collection/SeqOps;
       176: iconst_1
       177: invokevirtual #137                // Method scala/collection/SeqFactory$UnapplySeqWrapper$.lengthCompare$extension:(Lscala/collection/SeqOps;I)I
       180: iconst_0
       181: if_icmpne     259
       184: getstatic     #122                // Field scala/collection/SeqFactory$UnapplySeqWrapper$.MODULE$:Lscala/collection/SeqFactory$UnapplySeqWrapper$;
       187: getstatic     #122                // Field scala/collection/SeqFactory$UnapplySeqWrapper$.MODULE$:Lscala/collection/SeqFactory$UnapplySeqWrapper$;
       190: aload         9
       192: invokevirtual #129                // Method scala/collection/SeqFactory$UnapplySeqWrapper$.get$extension:(Lscala/collection/SeqOps;)Lscala/collection/SeqOps;
       195: iconst_0
       196: invokevirtual #141                // Method scala/collection/SeqFactory$UnapplySeqWrapper$.apply$extension:(Lscala/collection/SeqOps;I)Ljava/lang/Object;
       199: checkcast     #39                 // class scala/reflect/api/Types$TypeApi
       202: astore        10
       204: aload         7
       206: invokeinterface #145,  1          // InterfaceMethod scala/reflect/api/Symbols$SymbolApi.asType:()Lscala/reflect/api/Symbols$TypeSymbolApi;
       211: invokeinterface #148,  1          // InterfaceMethod scala/reflect/api/Symbols$TypeSymbolApi.toType:()Lscala/reflect/api/Types$TypeApi;
       216: invokevirtual #151                // Method scala/reflect/api/Types$TypeApi.typeConstructor:()Lscala/reflect/api/Types$TypeApi;
       219: aload_0
       220: getfield      #61                 // Field $outer:Lshapeless/LowPriorityTypes;
       223: invokeinterface #154,  1          // InterfaceMethod shapeless/LowPriorityTypes.lowPriorityForTpe:()Lscala/reflect/api/Types$TypeApi;
       228: invokevirtual #158                // Method scala/reflect/api/Types$TypeApi.$eq$colon$eq:(Lscala/reflect/api/Types$TypeApi;)Z
       231: ifeq          256
       234: new           #160                // class scala/Some
       237: dup
       238: new           #162                // class scala/Tuple2
       241: dup
       242: ldc           #164                // String
       244: aload         10
       246: invokespecial #167                // Method scala/Tuple2."<init>":(Ljava/lang/Object;Ljava/lang/Object;)V
       249: invokespecial #170                // Method scala/Some."<init>":(Ljava/lang/Object;)V
       252: astore_2
       253: goto          824
       256: goto          277
       259: goto          277
       262: goto          277
       265: goto          277
       268: goto          277
       271: goto          277
       274: goto          277
       277: aload_3
       278: ifnull        814
       281: aload_0
       282: getfield      #61                 // Field $outer:Lshapeless/LowPriorityTypes;
       285: invokeinterface #65,  1           // InterfaceMethod shapeless/LowPriorityTypes.c:()Lscala/reflect/macros/whitebox/Context;
       290: invokeinterface #71,  1           // InterfaceMethod scala/reflect/macros/whitebox/Context.universe:()Lscala/reflect/macros/Universe;
       295: invokevirtual #77                 // Method scala/reflect/macros/Universe.TypeRefTag:()Lscala/reflect/ClassTag;
       298: aload_3
       299: invokeinterface #82,  2           // InterfaceMethod scala/reflect/ClassTag.unapply:(Ljava/lang/Object;)Lscala/Option;
       304: astore        11
       306: aload         11
       308: invokevirtual #88                 // Method scala/Option.isEmpty:()Z
       311: ifne          811
       314: aload         11
       316: invokevirtual #92                 // Method scala/Option.get:()Ljava/lang/Object;
       319: checkcast     #42                 // class scala/reflect/api/Types$TypeRefApi
       322: astore        12
       324: aload         12
       326: ifnull        808
       329: aload_0
       330: getfield      #61                 // Field $outer:Lshapeless/LowPriorityTypes;
       333: invokeinterface #65,  1           // InterfaceMethod shapeless/LowPriorityTypes.c:()Lscala/reflect/macros/whitebox/Context;
       338: invokeinterface #71,  1           // InterfaceMethod scala/reflect/macros/whitebox/Context.universe:()Lscala/reflect/macros/Universe;
       343: invokevirtual #96                 // Method scala/reflect/macros/Universe.TypeRef:()Lscala/reflect/api/Types$TypeRefExtractor;
       346: aload         12
       348: invokevirtual #99                 // Method scala/reflect/api/Types$TypeRefExtractor.unapply:(Lscala/reflect/api/Types$TypeRefApi;)Lscala/Option;
       351: astore        13
       353: aload         13
       355: invokevirtual #88                 // Method scala/Option.isEmpty:()Z
       358: ifne          805
       361: aload         13
       363: invokevirtual #92                 // Method scala/Option.get:()Ljava/lang/Object;
       366: checkcast     #101                // class scala/Tuple3
       369: invokevirtual #104                // Method scala/Tuple3._2:()Ljava/lang/Object;
       372: checkcast     #23                 // class scala/reflect/api/Symbols$SymbolApi
       375: astore        14
       377: aload         13
       379: invokevirtual #92                 // Method scala/Option.get:()Ljava/lang/Object;
       382: checkcast     #101                // class scala/Tuple3
       385: invokevirtual #107                // Method scala/Tuple3._3:()Ljava/lang/Object;
       388: checkcast     #109                // class scala/collection/immutable/List
       391: astore        15
       393: aload         15
       395: ifnull        802
       398: getstatic     #115                // Field scala/collection/immutable/List$.MODULE$:Lscala/collection/immutable/List$;
       401: aload         15
       403: invokevirtual #119                // Method scala/collection/immutable/List$.unapplySeq:(Lscala/collection/SeqOps;)Lscala/collection/SeqOps;
       406: astore        16
       408: getstatic     #122                // Field scala/collection/SeqFactory$UnapplySeqWrapper$.MODULE$:Lscala/collection/SeqFactory$UnapplySeqWrapper$;
       411: aload         16
       413: invokevirtual #126                // Method scala/collection/SeqFactory$UnapplySeqWrapper$.isEmpty$extension:(Lscala/collection/SeqOps;)Z
       416: ifne          799
       419: new           #7                  // class scala/collection/SeqFactory$UnapplySeqWrapper
       422: dup
       423: getstatic     #122                // Field scala/collection/SeqFactory$UnapplySeqWrapper$.MODULE$:Lscala/collection/SeqFactory$UnapplySeqWrapper$;
       426: aload         16
       428: invokevirtual #129                // Method scala/collection/SeqFactory$UnapplySeqWrapper$.get$extension:(Lscala/collection/SeqOps;)Lscala/collection/SeqOps;
       431: invokespecial #133                // Method scala/collection/SeqFactory$UnapplySeqWrapper."<init>":(Lscala/collection/SeqOps;)V
       434: ifnull        799
       437: getstatic     #122                // Field scala/collection/SeqFactory$UnapplySeqWrapper$.MODULE$:Lscala/collection/SeqFactory$UnapplySeqWrapper$;
       440: getstatic     #122                // Field scala/collection/SeqFactory$UnapplySeqWrapper$.MODULE$:Lscala/collection/SeqFactory$UnapplySeqWrapper$;
       443: aload         16
       445: invokevirtual #129                // Method scala/collection/SeqFactory$UnapplySeqWrapper$.get$extension:(Lscala/collection/SeqOps;)Lscala/collection/SeqOps;
       448: iconst_2
       449: invokevirtual #137                // Method scala/collection/SeqFactory$UnapplySeqWrapper$.lengthCompare$extension:(Lscala/collection/SeqOps;I)I
       452: iconst_0
       453: if_icmpne     799
       456: getstatic     #122                // Field scala/collection/SeqFactory$UnapplySeqWrapper$.MODULE$:Lscala/collection/SeqFactory$UnapplySeqWrapper$;
       459: getstatic     #122                // Field scala/collection/SeqFactory$UnapplySeqWrapper$.MODULE$:Lscala/collection/SeqFactory$UnapplySeqWrapper$;
       462: aload         16
       464: invokevirtual #129                // Method scala/collection/SeqFactory$UnapplySeqWrapper$.get$extension:(Lscala/collection/SeqOps;)Lscala/collection/SeqOps;
       467: iconst_0
       468: invokevirtual #141                // Method scala/collection/SeqFactory$UnapplySeqWrapper$.apply$extension:(Lscala/collection/SeqOps;I)Ljava/lang/Object;
       471: checkcast     #39                 // class scala/reflect/api/Types$TypeApi
       474: astore        17
       476: getstatic     #122                // Field scala/collection/SeqFactory$UnapplySeqWrapper$.MODULE$:Lscala/collection/SeqFactory$UnapplySeqWrapper$;
       479: getstatic     #122                // Field scala/collection/SeqFactory$UnapplySeqWrapper$.MODULE$:Lscala/collection/SeqFactory$UnapplySeqWrapper$;
       482: aload         16
       484: invokevirtual #129                // Method scala/collection/SeqFactory$UnapplySeqWrapper$.get$extension:(Lscala/collection/SeqOps;)Lscala/collection/SeqOps;
       487: iconst_1
       488: invokevirtual #141                // Method scala/collection/SeqFactory$UnapplySeqWrapper$.apply$extension:(Lscala/collection/SeqOps;I)Ljava/lang/Object;
       491: checkcast     #39                 // class scala/reflect/api/Types$TypeApi
       494: astore        18
       496: aload         17
       498: ifnull        796
       501: aload_0
       502: getfield      #61                 // Field $outer:Lshapeless/LowPriorityTypes;
       505: invokeinterface #65,  1           // InterfaceMethod shapeless/LowPriorityTypes.c:()Lscala/reflect/macros/whitebox/Context;
       510: invokeinterface #71,  1           // InterfaceMethod scala/reflect/macros/whitebox/Context.universe:()Lscala/reflect/macros/Universe;
       515: invokevirtual #173                // Method scala/reflect/macros/Universe.ConstantTypeTag:()Lscala/reflect/ClassTag;
       518: aload         17
       520: invokeinterface #82,  2           // InterfaceMethod scala/reflect/ClassTag.unapply:(Ljava/lang/Object;)Lscala/Option;
       525: astore        19
       527: aload         19
       529: invokevirtual #88                 // Method scala/Option.isEmpty:()Z
       532: ifne          793
       535: aload         19
       537: invokevirtual #92                 // Method scala/Option.get:()Ljava/lang/Object;
       540: checkcast     #31                 // class scala/reflect/api/Types$ConstantTypeApi
       543: astore        20
       545: aload         20
       547: ifnull        790
       550: aload_0
       551: getfield      #61                 // Field $outer:Lshapeless/LowPriorityTypes;
       554: invokeinterface #65,  1           // InterfaceMethod shapeless/LowPriorityTypes.c:()Lscala/reflect/macros/whitebox/Context;
       559: invokeinterface #71,  1           // InterfaceMethod scala/reflect/macros/whitebox/Context.universe:()Lscala/reflect/macros/Universe;
       564: invokevirtual #177                // Method scala/reflect/macros/Universe.ConstantType:()Lscala/reflect/api/Types$ConstantTypeExtractor;
       567: aload         20
       569: invokevirtual #180                // Method scala/reflect/api/Types$ConstantTypeExtractor.unapply:(Lscala/reflect/api/Types$ConstantTypeApi;)Lscala/Option;
       572: astore        21
       574: aload         21
       576: invokevirtual #88                 // Method scala/Option.isEmpty:()Z
       579: ifne          787
       582: aload         21
       584: invokevirtual #92                 // Method scala/Option.get:()Ljava/lang/Object;
       587: checkcast     #15                 // class scala/reflect/api/Constants$ConstantApi
       590: astore        22
       592: aload         22
       594: ifnull        784
       597: aload_0
       598: getfield      #61                 // Field $outer:Lshapeless/LowPriorityTypes;
       601: invokeinterface #65,  1           // InterfaceMethod shapeless/LowPriorityTypes.c:()Lscala/reflect/macros/whitebox/Context;
       606: invokeinterface #71,  1           // InterfaceMethod scala/reflect/macros/whitebox/Context.universe:()Lscala/reflect/macros/Universe;
       611: invokevirtual #183                // Method scala/reflect/macros/Universe.ConstantTag:()Lscala/reflect/ClassTag;
       614: aload         22
       616: invokeinterface #82,  2           // InterfaceMethod scala/reflect/ClassTag.unapply:(Ljava/lang/Object;)Lscala/Option;
       621: astore        23
       623: aload         23
       625: invokevirtual #88                 // Method scala/Option.isEmpty:()Z
       628: ifne          781
       631: aload         23
       633: invokevirtual #92                 // Method scala/Option.get:()Ljava/lang/Object;
       636: checkcast     #15                 // class scala/reflect/api/Constants$ConstantApi
       639: astore        24
       641: aload         24
       643: ifnull        778
       646: aload_0
       647: getfield      #61                 // Field $outer:Lshapeless/LowPriorityTypes;
       650: invokeinterface #65,  1           // InterfaceMethod shapeless/LowPriorityTypes.c:()Lscala/reflect/macros/whitebox/Context;
       655: invokeinterface #71,  1           // InterfaceMethod scala/reflect/macros/whitebox/Context.universe:()Lscala/reflect/macros/Universe;
       660: invokevirtual #187                // Method scala/reflect/macros/Universe.Constant:()Lscala/reflect/api/Constants$ConstantExtractor;
       663: aload         24
       665: invokevirtual #190                // Method scala/reflect/api/Constants$ConstantExtractor.unapply:(Lscala/reflect/api/Constants$ConstantApi;)Lscala/Option;
       668: astore        25
       670: aload         25
       672: invokevirtual #88                 // Method scala/Option.isEmpty:()Z
       675: ifne          775
       678: aload         25
       680: invokevirtual #92                 // Method scala/Option.get:()Ljava/lang/Object;
       683: astore        26
       685: aload         26
       687: instanceof    #192                // class java/lang/String
       690: ifeq          772
       693: aload         26
       695: checkcast     #192                // class java/lang/String
       698: astore        27
       700: aload         14
       702: invokeinterface #145,  1          // InterfaceMethod scala/reflect/api/Symbols$SymbolApi.asType:()Lscala/reflect/api/Symbols$TypeSymbolApi;
       707: invokeinterface #148,  1          // InterfaceMethod scala/reflect/api/Symbols$TypeSymbolApi.toType:()Lscala/reflect/api/Types$TypeApi;
       712: invokevirtual #151                // Method scala/reflect/api/Types$TypeApi.typeConstructor:()Lscala/reflect/api/Types$TypeApi;
       715: aload_0
       716: getfield      #61                 // Field $outer:Lshapeless/LowPriorityTypes;
       719: invokeinterface #195,  1          // InterfaceMethod shapeless/LowPriorityTypes.lowPriorityForIgnoringTpe:()Lscala/reflect/api/Types$TypeApi;
       724: invokevirtual #158                // Method scala/reflect/api/Types$TypeApi.$eq$colon$eq:(Lscala/reflect/api/Types$TypeApi;)Z
       727: ifeq          769
       730: getstatic     #200                // Field scala/collection/StringOps$.MODULE$:Lscala/collection/StringOps$;
       733: getstatic     #205                // Field scala/Predef$.MODULE$:Lscala/Predef$;
       736: aload         27
       738: invokevirtual #209                // Method scala/Predef$.augmentString:(Ljava/lang/String;)Ljava/lang/String;
       741: invokevirtual #213                // Method scala/collection/StringOps$.nonEmpty$extension:(Ljava/lang/String;)Z
       744: ifeq          769
       747: new           #160                // class scala/Some
       750: dup
       751: new           #162                // class scala/Tuple2
       754: dup
       755: aload         27
       757: aload         18
       759: invokespecial #167                // Method scala/Tuple2."<init>":(Ljava/lang/Object;Ljava/lang/Object;)V
       762: invokespecial #170                // Method scala/Some."<init>":(Ljava/lang/Object;)V
       765: astore_2
       766: goto          824
       769: goto          817
       772: goto          817
       775: goto          817
       778: goto          817
       781: goto          817
       784: goto          817
       787: goto          817
       790: goto          817
       793: goto          817
       796: goto          817
       799: goto          817
       802: goto          817
       805: goto          817
       808: goto          817
       811: goto          817
       814: goto          817
       817: getstatic     #218                // Field scala/None$.MODULE$:Lscala/None$;
       820: astore_2
       821: goto          824
       824: aload_2
       825: areturn
      StackMapTable: number_of_entries = 26
        frame_type = 255 /* full_frame */
          offset_delta = 256
          locals = [ class shapeless/LowPriorityTypes$LowPriorityFor$, class scala/reflect/api/Types$TypeApi, top, class scala/reflect/api/Types$TypeApi, class scala/Option, class scala/reflect/api/Types$TypeRefApi, class scala/Option, class scala/reflect/api/Symbols$SymbolApi, class scala/collection/immutable/List, class scala/collection/SeqOps, class scala/reflect/api/Types$TypeApi ]
          stack = []
        frame_type = 250 /* chop */
          offset_delta = 2
        frame_type = 250 /* chop */
          offset_delta = 2
        frame_type = 249 /* chop */
          offset_delta = 2
        frame_type = 250 /* chop */
          offset_delta = 2
        frame_type = 250 /* chop */
          offset_delta = 2
        frame_type = 250 /* chop */
          offset_delta = 2
        frame_type = 2 /* same */
        frame_type = 255 /* full_frame */
          offset_delta = 491
          locals = [ class shapeless/LowPriorityTypes$LowPriorityFor$, class scala/reflect/api/Types$TypeApi, top, class scala/reflect/api/Types$TypeApi, top, top, top, top, top, top, top, class scala/Option, class scala/reflect/api/Types$TypeRefApi, class scala/Option, class scala/reflect/api/Symbols$SymbolApi, class scala/collection/immutable/List, class scala/collection/SeqOps, class scala/reflect/api/Types$TypeApi, class scala/reflect/api/Types$TypeApi, class scala/Option, class scala/reflect/api/Types$ConstantTypeApi, class scala/Option, class scala/reflect/api/Constants$ConstantApi, class scala/Option, class scala/reflect/api/Constants$ConstantApi, class scala/Option, class java/lang/Object, class java/lang/String ]
          stack = []
        frame_type = 250 /* chop */
          offset_delta = 2
        frame_type = 250 /* chop */
          offset_delta = 2
        frame_type = 250 /* chop */
          offset_delta = 2
        frame_type = 250 /* chop */
          offset_delta = 2
        frame_type = 250 /* chop */
          offset_delta = 2
        frame_type = 250 /* chop */
          offset_delta = 2
        frame_type = 250 /* chop */
          offset_delta = 2
        frame_type = 250 /* chop */
          offset_delta = 2
        frame_type = 250 /* chop */
          offset_delta = 2
        frame_type = 249 /* chop */
          offset_delta = 2
        frame_type = 250 /* chop */
          offset_delta = 2
        frame_type = 249 /* chop */
          offset_delta = 2
        frame_type = 250 /* chop */
          offset_delta = 2
        frame_type = 250 /* chop */
          offset_delta = 2
        frame_type = 255 /* full_frame */
          offset_delta = 2
          locals = [ class shapeless/LowPriorityTypes$LowPriorityFor$, class scala/reflect/api/Types$TypeApi, top, class scala/reflect/api/Types$TypeApi ]
          stack = []
        frame_type = 2 /* same */
        frame_type = 255 /* full_frame */
          offset_delta = 6
          locals = [ class shapeless/LowPriorityTypes$LowPriorityFor$, class scala/reflect/api/Types$TypeApi, class scala/Option, class scala/reflect/api/Types$TypeApi ]
          stack = []
      LineNumberTable:
        line 122: 0
        line 123: 5
        line 122: 42
        line 123: 52
        line 122: 89
        line 122: 105
        line 123: 121
        line 124: 204
        line 125: 234
        line 123: 256
        line 126: 277
        line 122: 314
        line 126: 324
        line 122: 361
        line 122: 377
        line 126: 393
        line 122: 535
        line 126: 545
        line 122: 582
        line 126: 592
        line 122: 631
        line 126: 641
        line 122: 678
        line 126: 685
        line 127: 700
        line 128: 733
        line 129: 747
        line 126: 769
        line 131: 817
        line 122: 824
      LocalVariableTable:
        Start  Length  Slot  Name   Signature
          202      57    10 highTpe   Lscala/reflect/api/Types$TypeApi;
          103     162     7 cpdTpe   Lscala/reflect/api/Symbols$SymbolApi;
          683      92    26 ignored   Ljava/lang/Object;
          494     305    18  tTpe   Lscala/reflect/api/Types$TypeApi;
          375     430    14 cpdTpe   Lscala/reflect/api/Symbols$SymbolApi;
            0     826     0  this   Lshapeless/LowPriorityTypes$LowPriorityFor$;
            0     826     1   tpe   Lscala/reflect/api/Types$TypeApi;
    Signature: #54                          // (Lscala/reflect/api/Types$TypeApi;)Lscala/Option<Lscala/Tuple2<Ljava/lang/String;Lscala/reflect/api/Types$TypeApi;>;>;
    MethodParameters:
      Name                           Flags
      tpe                            final

  public shapeless.LowPriorityTypes$LowPriorityFor$(shapeless.LowPriorityTypes);
    descriptor: (Lshapeless/LowPriorityTypes;)V
    flags: (0x0001) ACC_PUBLIC
    Code:
      stack=2, locals=2, args_size=2
         0: aload_1
         1: ifnonnull     6
         4: aconst_null
         5: athrow
         6: aload_0
         7: aload_1
         8: putfield      #61                 // Field $outer:Lshapeless/LowPriorityTypes;
        11: aload_0
        12: invokespecial #233                // Method java/lang/Object."<init>":()V
        15: return
      StackMapTable: number_of_entries = 1
        frame_type = 6 /* same */
      LineNumberTable:
        line 120: 0
        line 135: 11
        line 120: 15
      LocalVariableTable:
        Start  Length  Slot  Name   Signature
            0      16     0  this   Lshapeless/LowPriorityTypes$LowPriorityFor$;
            0      16     1 $outer   Lshapeless/LowPriorityTypes;
    MethodParameters:
      Name                           Flags
      $outer                         final synthetic
}
InnerClasses:
  public static final #10= #7 of #9;      // UnapplySeqWrapper=class scala/collection/SeqFactory$UnapplySeqWrapper of class scala/collection/SeqFactory
  public static #13= #12 of #9;           // UnapplySeqWrapper$=class scala/collection/SeqFactory$UnapplySeqWrapper$ of class scala/collection/SeqFactory
  public abstract #18= #15 of #17;        // ConstantApi=class scala/reflect/api/Constants$ConstantApi of class scala/reflect/api/Constants
  public abstract #21= #20 of #17;        // ConstantExtractor=class scala/reflect/api/Constants$ConstantExtractor of class scala/reflect/api/Constants
  public #26= #23 of #25;                 // SymbolApi=class scala/reflect/api/Symbols$SymbolApi of class scala/reflect/api/Symbols
  public #29= #28 of #25;                 // TypeSymbolApi=class scala/reflect/api/Symbols$TypeSymbolApi of class scala/reflect/api/Symbols
  public #34= #31 of #33;                 // ConstantTypeApi=class scala/reflect/api/Types$ConstantTypeApi of class scala/reflect/api/Types
  public abstract #37= #36 of #33;        // ConstantTypeExtractor=class scala/reflect/api/Types$ConstantTypeExtractor of class scala/reflect/api/Types
  public abstract #40= #39 of #33;        // TypeApi=class scala/reflect/api/Types$TypeApi of class scala/reflect/api/Types
  public #43= #42 of #33;                 // TypeRefApi=class scala/reflect/api/Types$TypeRefApi of class scala/reflect/api/Types
  public abstract #46= #45 of #33;        // TypeRefExtractor=class scala/reflect/api/Types$TypeRefExtractor of class scala/reflect/api/Types
  public #49= #2 of #48;                  // LowPriorityFor$=class shapeless/LowPriorityTypes$LowPriorityFor$ of class shapeless/LowPriorityTypes
SourceFile: "lowpriority.scala"
  ScalaInlineInfo: length = 0xE (unknown attribute)
   01 01 00 02 00 82 00 E6 01 00 34 00 35 01
  Scala: length = 0x0 (unknown attribute)

