Classfile /Users/mw/Projects/slang-braindump/.jar/jar8/assemble/slang-braindump/assemble/content/shapeless/LowPriorityMkSelectDynamicOptic$$anon$23.class
  Last modified May 29, 2022; size 1780 bytes
  SHA-256 checksum 1eaa8811a9b73f006b7f08f35b78b4ccea0d5c090096bbff01bf52ef3a7093e7
  Compiled from "lenses.scala"
public final class shapeless.LowPriorityMkSelectDynamicOptic$$anon$23 extends java.lang.Object implements shapeless.MkSelectDynamicOptic<R, A, K, scala.runtime.Nothing$>
  minor version: 0
  major version: 52
  flags: (0x0031) ACC_PUBLIC, ACC_FINAL, ACC_SUPER
  this_class: #2                          // shapeless/LowPriorityMkSelectDynamicOptic$$anon$23
  super_class: #5                         // java/lang/Object
  interfaces: 1, fields: 3, methods: 2, attributes: 6
Constant pool:
   #1 = Utf8               shapeless/LowPriorityMkSelectDynamicOptic$$anon$23
   #2 = Class              #1             // shapeless/LowPriorityMkSelectDynamicOptic$$anon$23
   #3 = Utf8               Ljava/lang/Object;Lshapeless/MkSelectDynamicOptic<TR;TA;TK;Lscala/runtime/Nothing$;>;
   #4 = Utf8               java/lang/Object
   #5 = Class              #4             // java/lang/Object
   #6 = Utf8               shapeless/MkSelectDynamicOptic
   #7 = Class              #6             // shapeless/MkSelectDynamicOptic
   #8 = Utf8               lenses.scala
   #9 = Utf8               shapeless/LowPriorityMkSelectDynamicOptic
  #10 = Class              #9             // shapeless/LowPriorityMkSelectDynamicOptic
  #11 = Utf8               mkInferCtorSelField
  #12 = Utf8               (Lshapeless/Generic;Lshapeless/InferProduct;Lshapeless/MkCtorPrism;Lshapeless/MkFieldLens;Lshapeless/OpticComposer;)Lshapeless/MkSelectDynamicOptic;
  #13 = NameAndType        #11:#12        // mkInferCtorSelField:(Lshapeless/Generic;Lshapeless/InferProduct;Lshapeless/MkCtorPrism;Lshapeless/MkFieldLens;Lshapeless/OpticComposer;)Lshapeless/MkSelectDynamicOptic;
  #14 = Utf8               compose$1
  #15 = Utf8               Lshapeless/OpticComposer;
  #16 = Utf8               mkPSel$1
  #17 = Utf8               Lshapeless/MkFieldLens;
  #18 = Utf8               mkCSel$1
  #19 = Utf8               Lshapeless/MkCtorPrism;
  #20 = Utf8               apply
  #21 = Utf8               (Ljava/lang/Object;)Ljava/lang/Object;
  #22 = Utf8               (TR;)Ljava/lang/Object;
  #23 = Utf8               r
  #24 = NameAndType        #14:#15        // compose$1:Lshapeless/OpticComposer;
  #25 = Fieldref           #2.#24         // shapeless/LowPriorityMkSelectDynamicOptic$$anon$23.compose$1:Lshapeless/OpticComposer;
  #26 = NameAndType        #16:#17        // mkPSel$1:Lshapeless/MkFieldLens;
  #27 = Fieldref           #2.#26         // shapeless/LowPriorityMkSelectDynamicOptic$$anon$23.mkPSel$1:Lshapeless/MkFieldLens;
  #28 = Utf8               shapeless/MkFieldLens
  #29 = Class              #28            // shapeless/MkFieldLens
  #30 = Utf8               ()Lshapeless/Lens;
  #31 = NameAndType        #20:#30        // apply:()Lshapeless/Lens;
  #32 = InterfaceMethodref #29.#31        // shapeless/MkFieldLens.apply:()Lshapeless/Lens;
  #33 = NameAndType        #18:#19        // mkCSel$1:Lshapeless/MkCtorPrism;
  #34 = Fieldref           #2.#33         // shapeless/LowPriorityMkSelectDynamicOptic$$anon$23.mkCSel$1:Lshapeless/MkCtorPrism;
  #35 = Utf8               shapeless/MkCtorPrism
  #36 = Class              #35            // shapeless/MkCtorPrism
  #37 = Utf8               ()Lshapeless/Prism;
  #38 = NameAndType        #20:#37        // apply:()Lshapeless/Prism;
  #39 = InterfaceMethodref #36.#38        // shapeless/MkCtorPrism.apply:()Lshapeless/Prism;
  #40 = Utf8               shapeless/Lens
  #41 = Class              #40            // shapeless/Lens
  #42 = Utf8               compose
  #43 = Utf8               (Lshapeless/Prism;)Lshapeless/Prism;
  #44 = NameAndType        #42:#43        // compose:(Lshapeless/Prism;)Lshapeless/Prism;
  #45 = InterfaceMethodref #41.#44        // shapeless/Lens.compose:(Lshapeless/Prism;)Lshapeless/Prism;
  #46 = Utf8               shapeless/OpticComposer
  #47 = Class              #46            // shapeless/OpticComposer
  #48 = Utf8               (Ljava/lang/Object;Ljava/lang/Object;)Ljava/lang/Object;
  #49 = NameAndType        #20:#48        // apply:(Ljava/lang/Object;Ljava/lang/Object;)Ljava/lang/Object;
  #50 = InterfaceMethodref #47.#49        // shapeless/OpticComposer.apply:(Ljava/lang/Object;Ljava/lang/Object;)Ljava/lang/Object;
  #51 = Utf8               this
  #52 = Utf8               Lshapeless/LowPriorityMkSelectDynamicOptic$$anon$23;
  #53 = Utf8               Ljava/lang/Object;
  #54 = Utf8               <init>
  #55 = Utf8               (Lshapeless/LowPriorityMkSelectDynamicOptic;Lshapeless/OpticComposer;Lshapeless/MkFieldLens;Lshapeless/MkCtorPrism;)V
  #56 = Utf8               $outer
  #57 = Utf8               ()V
  #58 = NameAndType        #54:#57        // "<init>":()V
  #59 = Methodref          #5.#58         // java/lang/Object."<init>":()V
  #60 = Utf8               Lshapeless/LowPriorityMkSelectDynamicOptic;
  #61 = Utf8               Code
  #62 = Utf8               LineNumberTable
  #63 = Utf8               LocalVariableTable
  #64 = Utf8               Signature
  #65 = Utf8               MethodParameters
  #66 = Utf8               InnerClasses
  #67 = Utf8               EnclosingMethod
  #68 = Utf8               SourceFile
  #69 = Utf8               ScalaInlineInfo
  #70 = Utf8               Scala
{
  private final shapeless.OpticComposer compose$1;
    descriptor: Lshapeless/OpticComposer;
    flags: (0x0012) ACC_PRIVATE, ACC_FINAL

  private final shapeless.MkFieldLens mkPSel$1;
    descriptor: Lshapeless/MkFieldLens;
    flags: (0x0012) ACC_PRIVATE, ACC_FINAL

  private final shapeless.MkCtorPrism mkCSel$1;
    descriptor: Lshapeless/MkCtorPrism;
    flags: (0x0012) ACC_PRIVATE, ACC_FINAL

  public java.lang.Object apply(R);
    descriptor: (Ljava/lang/Object;)Ljava/lang/Object;
    flags: (0x0001) ACC_PUBLIC
    Code:
      stack=3, locals=2, args_size=2
         0: aload_0
         1: getfield      #25                 // Field compose$1:Lshapeless/OpticComposer;
         4: aload_0
         5: getfield      #27                 // Field mkPSel$1:Lshapeless/MkFieldLens;
         8: invokeinterface #32,  1           // InterfaceMethod shapeless/MkFieldLens.apply:()Lshapeless/Lens;
        13: aload_0
        14: getfield      #34                 // Field mkCSel$1:Lshapeless/MkCtorPrism;
        17: invokeinterface #39,  1           // InterfaceMethod shapeless/MkCtorPrism.apply:()Lshapeless/Prism;
        22: invokeinterface #45,  2           // InterfaceMethod shapeless/Lens.compose:(Lshapeless/Prism;)Lshapeless/Prism;
        27: aload_1
        28: invokeinterface #50,  3           // InterfaceMethod shapeless/OpticComposer.apply:(Ljava/lang/Object;Ljava/lang/Object;)Ljava/lang/Object;
        33: areturn
      LineNumberTable:
        line 324: 0
      LocalVariableTable:
        Start  Length  Slot  Name   Signature
            0      34     0  this   Lshapeless/LowPriorityMkSelectDynamicOptic$$anon$23;
            0      34     1     r   Ljava/lang/Object;
    Signature: #22                          // (TR;)Ljava/lang/Object;
    MethodParameters:
      Name                           Flags
      r                              final

  public shapeless.LowPriorityMkSelectDynamicOptic$$anon$23(shapeless.LowPriorityMkSelectDynamicOptic, shapeless.OpticComposer, shapeless.MkFieldLens, shapeless.MkCtorPrism);
    descriptor: (Lshapeless/LowPriorityMkSelectDynamicOptic;Lshapeless/OpticComposer;Lshapeless/MkFieldLens;Lshapeless/MkCtorPrism;)V
    flags: (0x0001) ACC_PUBLIC
    Code:
      stack=2, locals=5, args_size=5
         0: aload_0
         1: aload_2
         2: putfield      #25                 // Field compose$1:Lshapeless/OpticComposer;
         5: aload_0
         6: aload_3
         7: putfield      #27                 // Field mkPSel$1:Lshapeless/MkFieldLens;
        10: aload_0
        11: aload         4
        13: putfield      #34                 // Field mkCSel$1:Lshapeless/MkCtorPrism;
        16: aload_0
        17: invokespecial #59                 // Method java/lang/Object."<init>":()V
        20: return
      LineNumberTable:
        line 320: 0
        line 319: 5
        line 318: 10
        line 322: 16
      LocalVariableTable:
        Start  Length  Slot  Name   Signature
            0      21     0  this   Lshapeless/LowPriorityMkSelectDynamicOptic$$anon$23;
            0      21     1 $outer   Lshapeless/LowPriorityMkSelectDynamicOptic;
            0      21     2 compose$1   Lshapeless/OpticComposer;
            0      21     3 mkPSel$1   Lshapeless/MkFieldLens;
            0      21     4 mkCSel$1   Lshapeless/MkCtorPrism;
    MethodParameters:
      Name                           Flags
      $outer                         final synthetic
      compose$1                      final
      mkPSel$1                       final
      mkCSel$1                       final
}
InnerClasses:
  public final #2;                        // class shapeless/LowPriorityMkSelectDynamicOptic$$anon$23
EnclosingMethod: #10.#13                // shapeless.LowPriorityMkSelectDynamicOptic.mkInferCtorSelField
Signature: #3                           // Ljava/lang/Object;Lshapeless/MkSelectDynamicOptic<TR;TA;TK;Lscala/runtime/Nothing$;>;
SourceFile: "lenses.scala"
  ScalaInlineInfo: length = 0xE (unknown attribute)
   01 01 00 02 00 36 00 37 01 00 14 00 15 01
  Scala: length = 0x0 (unknown attribute)

