Classfile /Users/mw/Projects/slang-braindump/.jar/jar8/assemble/slang-braindump/assemble/content/shapeless/LPLens.class
  Last modified May 29, 2022; size 2083 bytes
  SHA-256 checksum 9265730509da830c6605463e707e43566c83f124d44a0b21a48bbcb5d9d02653
  Compiled from "lenses.scala"
public interface shapeless.LPLens<S extends java.lang.Object, A extends java.lang.Object> extends scala.Dynamic, java.io.Serializable
  minor version: 0
  major version: 52
  flags: (0x0601) ACC_PUBLIC, ACC_INTERFACE, ACC_ABSTRACT
  this_class: #2                          // shapeless/LPLens
  super_class: #5                         // java/lang/Object
  interfaces: 2, fields: 0, methods: 3, attributes: 5
Constant pool:
   #1 = Utf8               shapeless/LPLens
   #2 = Class              #1             // shapeless/LPLens
   #3 = Utf8               <S:Ljava/lang/Object;A:Ljava/lang/Object;>Ljava/lang/Object;Lscala/Dynamic;Ljava/io/Serializable;
   #4 = Utf8               java/lang/Object
   #5 = Class              #4             // java/lang/Object
   #6 = Utf8               scala/Dynamic
   #7 = Class              #6             // scala/Dynamic
   #8 = Utf8               java/io/Serializable
   #9 = Class              #8             // java/io/Serializable
  #10 = Utf8               lenses.scala
  #11 = Utf8               Lscala/reflect/ScalaSignature;
  #12 = Utf8               bytes
  #13 = Utf8               \u0006\u0005}3\u0001b\u0001\u0003\u0011\u0002\u0007\u0005q\u0001\r\u0005\u0006=\u0001!\ta\b\u0005\u0006G\u0001!\t\u0001\n\u0002\u0007\u0019BcUM\\:\u000b\u0003\u0015\t\u0011b\u001d5ba\u0016dWm]:\u0004\u0001U\u0019\u0001\u0002\u000e \u0014\t\u0001IqB\u0005\t\u0003\u00155i\u0011a\u0003\u0006\u0002\u0019\u0005)1oY1mC&\u0011ab\u0003\u0002\u0007\u0003:L(+\u001a4\u0011\u0005)\u0001\u0012BA\t\f\u0005\u001d!\u0015P\\1nS\u000e\u0004\"aE\u000e\u000f\u0005QIbBA\u000b\u0019\u001b\u00051\"BA\f\u0007\u0003\u0019a$o\\8u}%\tA\"\u0003\u0002\u001b\u0017\u00059\u0001/Y2lC\u001e,\u0017B\u0001\u000f\u001e\u00051\u0019VM]5bY&T\u0018M\u00197f\u0015\tQ2\"\u0001\u0004%S:LG\u000f\n\u000b\u0002AA\u0011!\"I\u0005\u0003E-\u0011A!\u00168ji\u0006i1/\u001a7fGR$\u0015P\\1nS\u000e,\"!\n,\u0015\u0005\u0019ZEcA\u0014+5B\u0011\u0001\u0006\u0017\b\u0003S)b\u0001\u0001C\u0003,\u0005\u0001\u000fA&\u0001\u0004nW2+gn\u001d\t\u0007[9\u0002T\bQ+\u000e\u0003\u0011I!a\f\u0003\u0003)5[7+\u001a7fGR$\u0015P\\1nS\u000e|\u0005\u000f^5d!\u0011i\u0013gM\u001f\n\u0005I\"!\u0001\u0002\'f]N\u0004\"!\u000b\u001b\u0005\u000bU\u0002!\u0019\u0001\u001c\u0003\u0003M\u000b\"a\u000e\u001e\u0011\u0005)A\u0014BA\u001d\f\u0005\u001dqu\u000e\u001e5j]\u001e\u0004\"AC\u001e\n\u0005qZ!aA!osB\u0011\u0011F\u0010\u0003\u0006\u007f\u0001\u0011\rA\u000e\u0002\u0002\u0003B!\u0011\tR$K\u001d\ti#)\u0003\u0002D\t\u0005\u0019A/Y4\n\u0005\u00153%A\u0002\u0013bi\u0012\nGO\u0003\u0002D\tA\u0011!\u0002S\u0005\u0003\u0013.\u0011aaU=nE>dgBA\u0015L\u0011\u0015a%\u00011\u0001N\u0003\u0005Y\u0007C\u0001(S\u001d\ty\u0005\u000b\u0005\u0002\u0016\u0017%\u0011\u0011kC\u0001\u0007!J,G-\u001a4\n\u0005M#&AB*ue&twM\u0003\u0002R\u0017A\u0011\u0011F\u0016\u0003\u0006/\n\u0011\rA\u000e\u0002\u0002\u0005&\u0011\u0011L\f\u0002\u0004\u001fV$\b\"B.\u0003\u0001\ba\u0016!\u00023v[6L\bC\u0001\u0006^\u0013\tq6BA\u0007Ek6l\u00170S7qY&\u001c\u0017\u000e\u001e
  #14 = Utf8               selectDynamic$
  #15 = Utf8               (Lshapeless/LPLens;Ljava/lang/String;Lshapeless/MkSelectDynamicOptic;Lscala/DummyImplicit;)Ljava/lang/Object;
  #16 = Utf8               $this
  #17 = Utf8               k
  #18 = Utf8               mkLens
  #19 = Utf8               dummy
  #20 = Utf8               selectDynamic
  #21 = Utf8               (Ljava/lang/String;Lshapeless/MkSelectDynamicOptic;Lscala/DummyImplicit;)Ljava/lang/Object;
  #22 = NameAndType        #20:#21        // selectDynamic:(Ljava/lang/String;Lshapeless/MkSelectDynamicOptic;Lscala/DummyImplicit;)Ljava/lang/Object;
  #23 = InterfaceMethodref #2.#22         // shapeless/LPLens.selectDynamic:(Ljava/lang/String;Lshapeless/MkSelectDynamicOptic;Lscala/DummyImplicit;)Ljava/lang/Object;
  #24 = Utf8               Lshapeless/LPLens;
  #25 = Utf8               Ljava/lang/String;
  #26 = Utf8               Lshapeless/MkSelectDynamicOptic;
  #27 = Utf8               Lscala/DummyImplicit;
  #28 = Utf8               <B:Ljava/lang/Object;>(Ljava/lang/String;Lshapeless/MkSelectDynamicOptic<Lshapeless/Lens<TS;TA;>;TA;Lscala/Symbol;TB;>;Lscala/DummyImplicit;)Ljava/lang/Object;
  #29 = Utf8               shapeless/MkSelectDynamicOptic
  #30 = Class              #29            // shapeless/MkSelectDynamicOptic
  #31 = Utf8               apply
  #32 = Utf8               (Ljava/lang/Object;)Ljava/lang/Object;
  #33 = NameAndType        #31:#32        // apply:(Ljava/lang/Object;)Ljava/lang/Object;
  #34 = InterfaceMethodref #30.#33        // shapeless/MkSelectDynamicOptic.apply:(Ljava/lang/Object;)Ljava/lang/Object;
  #35 = Utf8               this
  #36 = Utf8               $init$
  #37 = Utf8               (Lshapeless/LPLens;)V
  #38 = Utf8               Code
  #39 = Utf8               LineNumberTable
  #40 = Utf8               LocalVariableTable
  #41 = Utf8               MethodParameters
  #42 = Utf8               Signature
  #43 = Utf8               SourceFile
  #44 = Utf8               RuntimeVisibleAnnotations
  #45 = Utf8               ScalaInlineInfo
  #46 = Utf8               ScalaSig
{
  public static java.lang.Object selectDynamic$(shapeless.LPLens, java.lang.String, shapeless.MkSelectDynamicOptic, scala.DummyImplicit);
    descriptor: (Lshapeless/LPLens;Ljava/lang/String;Lshapeless/MkSelectDynamicOptic;Lscala/DummyImplicit;)Ljava/lang/Object;
    flags: (0x1009) ACC_PUBLIC, ACC_STATIC, ACC_SYNTHETIC
    Code:
      stack=4, locals=4, args_size=4
         0: aload_0
         1: aload_1
         2: aload_2
         3: aload_3
         4: invokespecial #23                 // InterfaceMethod selectDynamic:(Ljava/lang/String;Lshapeless/MkSelectDynamicOptic;Lscala/DummyImplicit;)Ljava/lang/Object;
         7: areturn
      LineNumberTable:
        line 65: 0
      LocalVariableTable:
        Start  Length  Slot  Name   Signature
            0       8     0 $this   Lshapeless/LPLens;
            0       8     1     k   Ljava/lang/String;
            0       8     2 mkLens   Lshapeless/MkSelectDynamicOptic;
            0       8     3 dummy   Lscala/DummyImplicit;
    MethodParameters:
      Name                           Flags
      $this                          final synthetic
      k                              final
      mkLens                         final
      dummy                          final

  public default <B extends java.lang.Object> java.lang.Object selectDynamic(java.lang.String, shapeless.MkSelectDynamicOptic<shapeless.Lens<S, A>, A, scala.Symbol, B>, scala.DummyImplicit);
    descriptor: (Ljava/lang/String;Lshapeless/MkSelectDynamicOptic;Lscala/DummyImplicit;)Ljava/lang/Object;
    flags: (0x0001) ACC_PUBLIC
    Code:
      stack=2, locals=5, args_size=4
         0: aload_2
         1: astore        4
         3: aload         4
         5: aload_0
         6: invokeinterface #34,  2           // InterfaceMethod shapeless/MkSelectDynamicOptic.apply:(Ljava/lang/Object;)Ljava/lang/Object;
        11: areturn
      LineNumberTable:
        line 66: 0
      LocalVariableTable:
        Start  Length  Slot  Name   Signature
            0      12     0  this   Lshapeless/LPLens;
            0      12     1     k   Ljava/lang/String;
            0      12     2 mkLens   Lshapeless/MkSelectDynamicOptic;
            0      12     3 dummy   Lscala/DummyImplicit;
    Signature: #28                          // <B:Ljava/lang/Object;>(Ljava/lang/String;Lshapeless/MkSelectDynamicOptic<Lshapeless/Lens<TS;TA;>;TA;Lscala/Symbol;TB;>;Lscala/DummyImplicit;)Ljava/lang/Object;
    MethodParameters:
      Name                           Flags
      k                              final
      mkLens                         final
      dummy                          final

  public static void $init$(shapeless.LPLens);
    descriptor: (Lshapeless/LPLens;)V
    flags: (0x0009) ACC_PUBLIC, ACC_STATIC
    Code:
      stack=0, locals=1, args_size=1
         0: return
      LineNumberTable:
        line 64: 0
      LocalVariableTable:
        Start  Length  Slot  Name   Signature
            0       1     0 $this   Lshapeless/LPLens;
    MethodParameters:
      Name                           Flags
      $this                          final synthetic
}
Signature: #3                           // <S:Ljava/lang/Object;A:Ljava/lang/Object;>Ljava/lang/Object;Lscala/Dynamic;Ljava/io/Serializable;
SourceFile: "lenses.scala"
RuntimeVisibleAnnotations:
  0: #11(#12=s#13)
    scala.reflect.ScalaSignature(
      bytes="\u0006\u0005}3\u0001b\u0001\u0003\u0011\u0002\u0007\u0005q\u0001\r\u0005\u0006=\u0001!\ta\b\u0005\u0006G\u0001!\t\u0001\n\u0002\u0007\u0019BcUM\\:\u000b\u0003\u0015\t\u0011b\u001d5ba\u0016dWm]:\u0004\u0001U\u0019\u0001\u0002\u000e \u0014\t\u0001IqB\u0005\t\u0003\u00155i\u0011a\u0003\u0006\u0002\u0019\u0005)1oY1mC&\u0011ab\u0003\u0002\u0007\u0003:L(+\u001a4\u0011\u0005)\u0001\u0012BA\t\f\u0005\u001d!\u0015P\\1nS\u000e\u0004\"aE\u000e\u000f\u0005QIbBA\u000b\u0019\u001b\u00051\"BA\f\u0007\u0003\u0019a$o\\8u}%\tA\"\u0003\u0002\u001b\u0017\u00059\u0001/Y2lC\u001e,\u0017B\u0001\u000f\u001e\u00051\u0019VM]5bY&T\u0018M\u00197f\u0015\tQ2\"\u0001\u0004%S:LG\u000f\n\u000b\u0002AA\u0011!\"I\u0005\u0003E-\u0011A!\u00168ji\u0006i1/\u001a7fGR$\u0015P\\1nS\u000e,\"!\n,\u0015\u0005\u0019ZEcA\u0014+5B\u0011\u0001\u0006\u0017\b\u0003S)b\u0001\u0001C\u0003,\u0005\u0001\u000fA&\u0001\u0004nW2+gn\u001d\t\u0007[9\u0002T\bQ+\u000e\u0003\u0011I!a\f\u0003\u0003)5[7+\u001a7fGR$\u0015P\\1nS\u000e|\u0005\u000f^5d!\u0011i\u0013gM\u001f\n\u0005I\"!\u0001\u0002\'f]N\u0004\"!\u000b\u001b\u0005\u000bU\u0002!\u0019\u0001\u001c\u0003\u0003M\u000b\"a\u000e\u001e\u0011\u0005)A\u0014BA\u001d\f\u0005\u001dqu\u000e\u001e5j]\u001e\u0004\"AC\u001e\n\u0005qZ!aA!osB\u0011\u0011F\u0010\u0003\u0006\u007f\u0001\u0011\rA\u000e\u0002\u0002\u0003B!\u0011\tR$K\u001d\ti#)\u0003\u0002D\t\u0005\u0019A/Y4\n\u0005\u00153%A\u0002\u0013bi\u0012\nGO\u0003\u0002D\tA\u0011!\u0002S\u0005\u0003\u0013.\u0011aaU=nE>dgBA\u0015L\u0011\u0015a%\u00011\u0001N\u0003\u0005Y\u0007C\u0001(S\u001d\ty\u0005\u000b\u0005\u0002\u0016\u0017%\u0011\u0011kC\u0001\u0007!J,G-\u001a4\n\u0005M#&AB*ue&twM\u0003\u0002R\u0017A\u0011\u0011F\u0016\u0003\u0006/\n\u0011\rA\u000e\u0002\u0002\u0005&\u0011\u0011L\f\u0002\u0004\u001fV$\b\"B.\u0003\u0001\ba\u0016!\u00023v[6L\bC\u0001\u0006^\u0013\tq6BA\u0007Ek6l\u00170S7qY&\u001c\u0017\u000e\u001e"
    )
  ScalaInlineInfo: length = 0x13 (unknown attribute)
   01 00 00 03 00 24 00 25 01 00 0E 00 0F 01 00 14
   00 15 00
  ScalaSig: length = 0x3 (unknown attribute)
   05 02 00
