Classfile /Users/mw/Projects/slang-braindump/.jar/jar8/assemble/slang-braindump/assemble/content/shapeless/LPPrism.class
  Last modified May 29, 2022; size 2093 bytes
  SHA-256 checksum d9ce6e8abab9a48df9b650ec7b7fb31b4b742742d5fb0eb80975bba21876d155
  Compiled from "lenses.scala"
public interface shapeless.LPPrism<S extends java.lang.Object, A extends java.lang.Object> extends scala.Dynamic, java.io.Serializable
  minor version: 0
  major version: 52
  flags: (0x0601) ACC_PUBLIC, ACC_INTERFACE, ACC_ABSTRACT
  this_class: #2                          // shapeless/LPPrism
  super_class: #5                         // java/lang/Object
  interfaces: 2, fields: 0, methods: 3, attributes: 5
Constant pool:
   #1 = Utf8               shapeless/LPPrism
   #2 = Class              #1             // shapeless/LPPrism
   #3 = Utf8               <S:Ljava/lang/Object;A:Ljava/lang/Object;>Ljava/lang/Object;Lscala/Dynamic;Ljava/io/Serializable;
   #4 = Utf8               java/lang/Object
   #5 = Class              #4             // java/lang/Object
   #6 = Utf8               scala/Dynamic
   #7 = Class              #6             // scala/Dynamic
   #8 = Utf8               java/io/Serializable
   #9 = Class              #8             // java/io/Serializable
  #10 = Utf8               lenses.scala
  #11 = Utf8               Lscala/reflect/ScalaSignature;
  #12 = Utf8               bytes
  #13 = Utf8               \u0006\u0005}3\u0001b\u0001\u0003\u0011\u0002\u0007\u0005q\u0001\r\u0005\u0006=\u0001!\ta\b\u0005\u0006G\u0001!\t\u0001\n\u0002\b\u0019B\u0003&/[:n\u0015\u0005)\u0011!C:iCB,G.Z:t\u0007\u0001)2\u0001\u0003\u001b?\'\u0011\u0001\u0011b\u0004\n\u0011\u0005)iQ\"A\u0006\u000b\u00031\tQa]2bY\u0006L!AD\u0006\u0003\r\u0005s\u0017PU3g!\tQ\u0001#\u0003\u0002\u0012\u0017\t9A)\u001f8b[&\u001c\u0007CA\n\u001c\u001d\t!\u0012D\u0004\u0002\u001615\taC\u0003\u0002\u0018\r\u00051AH]8pizJ\u0011\u0001D\u0005\u00035-\tq\u0001]1dW\u0006<W-\u0003\u0002\u001d;\ta1+\u001a:jC2L\'0\u00192mK*\u0011!dC\u0001\u0007I%t\u0017\u000e\u001e\u0013\u0015\u0003\u0001\u0002\"AC\u0011\n\u0005\tZ!\u0001B+oSR\fQb]3mK\u000e$H)\u001f8b[&\u001cWCA\u0013W)\t13\nF\u0002(Ui\u0003\"\u0001\u000b-\u000f\u0005%RC\u0002\u0001\u0005\u0006W\t\u0001\u001d\u0001L\u0001\b[.\u0004&/[:n!\u0019ic\u0006M\u001fA+6\tA!\u0003\u00020\t\t!Rj[*fY\u0016\u001cG\u000fR=oC6L7m\u00149uS\u000e\u0004B!L\u00194{%\u0011!\u0007\u0002\u0002\u0006!JL7/\u001c\t\u0003SQ\"Q!\u000e\u0001C\u0002Y\u0012\u0011aU\t\u0003oi\u0002\"A\u0003\u001d\n\u0005eZ!a\u0002(pi\"Lgn\u001a\t\u0003\u0015mJ!\u0001P\u0006\u0003\u0007\u0005s\u0017\u0010\u0005\u0002*}\u0011)q\b\u0001b\u0001m\t\t\u0011\t\u0005\u0003B\t\u001eSeBA\u0017C\u0013\t\u0019E!A\u0002uC\u001eL!!\u0012$\u0003\r\u0011\nG\u000fJ1u\u0015\t\u0019E\u0001\u0005\u0002\u000b\u0011&\u0011\u0011j\u0003\u0002\u0007\'fl\'m\u001c7\u000f\u0005%Z\u0005\"\u0002\'\u0003\u0001\u0004i\u0015!A6\u0011\u00059\u0013fBA(Q!\t)2\"\u0003\u0002R\u0017\u00051\u0001K]3eK\u001aL!a\u0015+\u0003\rM#(/\u001b8h\u0015\t\t6\u0002\u0005\u0002*-\u0012)qK\u0001b\u0001m\t\t!)\u0003\u0002Z]\t\u0019q*\u001e;\t\u000bm\u0013\u00019\u0001/\u0002\u000b\u0011,X.\\=\u0011\u0005)i\u0016B\u00010\f\u00055!U/\\7z\u00136\u0004H.[2ji\u0002
  #14 = Utf8               selectDynamic$
  #15 = Utf8               (Lshapeless/LPPrism;Ljava/lang/String;Lshapeless/MkSelectDynamicOptic;Lscala/DummyImplicit;)Ljava/lang/Object;
  #16 = Utf8               $this
  #17 = Utf8               k
  #18 = Utf8               mkPrism
  #19 = Utf8               dummy
  #20 = Utf8               selectDynamic
  #21 = Utf8               (Ljava/lang/String;Lshapeless/MkSelectDynamicOptic;Lscala/DummyImplicit;)Ljava/lang/Object;
  #22 = NameAndType        #20:#21        // selectDynamic:(Ljava/lang/String;Lshapeless/MkSelectDynamicOptic;Lscala/DummyImplicit;)Ljava/lang/Object;
  #23 = InterfaceMethodref #2.#22         // shapeless/LPPrism.selectDynamic:(Ljava/lang/String;Lshapeless/MkSelectDynamicOptic;Lscala/DummyImplicit;)Ljava/lang/Object;
  #24 = Utf8               Lshapeless/LPPrism;
  #25 = Utf8               Ljava/lang/String;
  #26 = Utf8               Lshapeless/MkSelectDynamicOptic;
  #27 = Utf8               Lscala/DummyImplicit;
  #28 = Utf8               <B:Ljava/lang/Object;>(Ljava/lang/String;Lshapeless/MkSelectDynamicOptic<Lshapeless/Prism<TS;TA;>;TA;Lscala/Symbol;TB;>;Lscala/DummyImplicit;)Ljava/lang/Object;
  #29 = Utf8               shapeless/MkSelectDynamicOptic
  #30 = Class              #29            // shapeless/MkSelectDynamicOptic
  #31 = Utf8               apply
  #32 = Utf8               (Ljava/lang/Object;)Ljava/lang/Object;
  #33 = NameAndType        #31:#32        // apply:(Ljava/lang/Object;)Ljava/lang/Object;
  #34 = InterfaceMethodref #30.#33        // shapeless/MkSelectDynamicOptic.apply:(Ljava/lang/Object;)Ljava/lang/Object;
  #35 = Utf8               this
  #36 = Utf8               $init$
  #37 = Utf8               (Lshapeless/LPPrism;)V
  #38 = Utf8               Code
  #39 = Utf8               LineNumberTable
  #40 = Utf8               LocalVariableTable
  #41 = Utf8               MethodParameters
  #42 = Utf8               Signature
  #43 = Utf8               SourceFile
  #44 = Utf8               RuntimeVisibleAnnotations
  #45 = Utf8               ScalaInlineInfo
  #46 = Utf8               ScalaSig
{
  public static java.lang.Object selectDynamic$(shapeless.LPPrism, java.lang.String, shapeless.MkSelectDynamicOptic, scala.DummyImplicit);
    descriptor: (Lshapeless/LPPrism;Ljava/lang/String;Lshapeless/MkSelectDynamicOptic;Lscala/DummyImplicit;)Ljava/lang/Object;
    flags: (0x1009) ACC_PUBLIC, ACC_STATIC, ACC_SYNTHETIC
    Code:
      stack=4, locals=4, args_size=4
         0: aload_0
         1: aload_1
         2: aload_2
         3: aload_3
         4: invokespecial #23                 // InterfaceMethod selectDynamic:(Ljava/lang/String;Lshapeless/MkSelectDynamicOptic;Lscala/DummyImplicit;)Ljava/lang/Object;
         7: areturn
      LineNumberTable:
        line 109: 0
      LocalVariableTable:
        Start  Length  Slot  Name   Signature
            0       8     0 $this   Lshapeless/LPPrism;
            0       8     1     k   Ljava/lang/String;
            0       8     2 mkPrism   Lshapeless/MkSelectDynamicOptic;
            0       8     3 dummy   Lscala/DummyImplicit;
    MethodParameters:
      Name                           Flags
      $this                          final synthetic
      k                              final
      mkPrism                        final
      dummy                          final

  public default <B extends java.lang.Object> java.lang.Object selectDynamic(java.lang.String, shapeless.MkSelectDynamicOptic<shapeless.Prism<S, A>, A, scala.Symbol, B>, scala.DummyImplicit);
    descriptor: (Ljava/lang/String;Lshapeless/MkSelectDynamicOptic;Lscala/DummyImplicit;)Ljava/lang/Object;
    flags: (0x0001) ACC_PUBLIC
    Code:
      stack=2, locals=5, args_size=4
         0: aload_2
         1: astore        4
         3: aload         4
         5: aload_0
         6: invokeinterface #34,  2           // InterfaceMethod shapeless/MkSelectDynamicOptic.apply:(Ljava/lang/Object;)Ljava/lang/Object;
        11: areturn
      LineNumberTable:
        line 110: 0
      LocalVariableTable:
        Start  Length  Slot  Name   Signature
            0      12     0  this   Lshapeless/LPPrism;
            0      12     1     k   Ljava/lang/String;
            0      12     2 mkPrism   Lshapeless/MkSelectDynamicOptic;
            0      12     3 dummy   Lscala/DummyImplicit;
    Signature: #28                          // <B:Ljava/lang/Object;>(Ljava/lang/String;Lshapeless/MkSelectDynamicOptic<Lshapeless/Prism<TS;TA;>;TA;Lscala/Symbol;TB;>;Lscala/DummyImplicit;)Ljava/lang/Object;
    MethodParameters:
      Name                           Flags
      k                              final
      mkPrism                        final
      dummy                          final

  public static void $init$(shapeless.LPPrism);
    descriptor: (Lshapeless/LPPrism;)V
    flags: (0x0009) ACC_PUBLIC, ACC_STATIC
    Code:
      stack=0, locals=1, args_size=1
         0: return
      LineNumberTable:
        line 108: 0
      LocalVariableTable:
        Start  Length  Slot  Name   Signature
            0       1     0 $this   Lshapeless/LPPrism;
    MethodParameters:
      Name                           Flags
      $this                          final synthetic
}
Signature: #3                           // <S:Ljava/lang/Object;A:Ljava/lang/Object;>Ljava/lang/Object;Lscala/Dynamic;Ljava/io/Serializable;
SourceFile: "lenses.scala"
RuntimeVisibleAnnotations:
  0: #11(#12=s#13)
    scala.reflect.ScalaSignature(
      bytes="\u0006\u0005}3\u0001b\u0001\u0003\u0011\u0002\u0007\u0005q\u0001\r\u0005\u0006=\u0001!\ta\b\u0005\u0006G\u0001!\t\u0001\n\u0002\b\u0019B\u0003&/[:n\u0015\u0005)\u0011!C:iCB,G.Z:t\u0007\u0001)2\u0001\u0003\u001b?\'\u0011\u0001\u0011b\u0004\n\u0011\u0005)iQ\"A\u0006\u000b\u00031\tQa]2bY\u0006L!AD\u0006\u0003\r\u0005s\u0017PU3g!\tQ\u0001#\u0003\u0002\u0012\u0017\t9A)\u001f8b[&\u001c\u0007CA\n\u001c\u001d\t!\u0012D\u0004\u0002\u001615\taC\u0003\u0002\u0018\r\u00051AH]8pizJ\u0011\u0001D\u0005\u00035-\tq\u0001]1dW\u0006<W-\u0003\u0002\u001d;\ta1+\u001a:jC2L\'0\u00192mK*\u0011!dC\u0001\u0007I%t\u0017\u000e\u001e\u0013\u0015\u0003\u0001\u0002\"AC\u0011\n\u0005\tZ!\u0001B+oSR\fQb]3mK\u000e$H)\u001f8b[&\u001cWCA\u0013W)\t13\nF\u0002(Ui\u0003\"\u0001\u000b-\u000f\u0005%RC\u0002\u0001\u0005\u0006W\t\u0001\u001d\u0001L\u0001\b[.\u0004&/[:n!\u0019ic\u0006M\u001fA+6\tA!\u0003\u00020\t\t!Rj[*fY\u0016\u001cG\u000fR=oC6L7m\u00149uS\u000e\u0004B!L\u00194{%\u0011!\u0007\u0002\u0002\u0006!JL7/\u001c\t\u0003SQ\"Q!\u000e\u0001C\u0002Y\u0012\u0011aU\t\u0003oi\u0002\"A\u0003\u001d\n\u0005eZ!a\u0002(pi\"Lgn\u001a\t\u0003\u0015mJ!\u0001P\u0006\u0003\u0007\u0005s\u0017\u0010\u0005\u0002*}\u0011)q\b\u0001b\u0001m\t\t\u0011\t\u0005\u0003B\t\u001eSeBA\u0017C\u0013\t\u0019E!A\u0002uC\u001eL!!\u0012$\u0003\r\u0011\nG\u000fJ1u\u0015\t\u0019E\u0001\u0005\u0002\u000b\u0011&\u0011\u0011j\u0003\u0002\u0007\'fl\'m\u001c7\u000f\u0005%Z\u0005\"\u0002\'\u0003\u0001\u0004i\u0015!A6\u0011\u00059\u0013fBA(Q!\t)2\"\u0003\u0002R\u0017\u00051\u0001K]3eK\u001aL!a\u0015+\u0003\rM#(/\u001b8h\u0015\t\t6\u0002\u0005\u0002*-\u0012)qK\u0001b\u0001m\t\t!)\u0003\u0002Z]\t\u0019q*\u001e;\t\u000bm\u0013\u00019\u0001/\u0002\u000b\u0011,X.\\=\u0011\u0005)i\u0016B\u00010\f\u00055!U/\\7z\u00136\u0004H.[2ji\u0002"
    )
  ScalaInlineInfo: length = 0x13 (unknown attribute)
   01 00 00 03 00 24 00 25 01 00 0E 00 0F 01 00 14
   00 15 00
  ScalaSig: length = 0x3 (unknown attribute)
   05 02 00
