Classfile /Users/mw/Projects/slang-braindump/.jar/jar8/assemble/slang-braindump/assemble/content/shapeless/Lub$$anon$4.class
  Last modified May 29, 2022; size 825 bytes
  SHA-256 checksum 6267d1f02a6aa838e6588bcbce1db633bd2dccfcff0223e15976d783c57e19b1
  Compiled from "typeoperators.scala"
public final class shapeless.Lub$$anon$4 extends java.lang.Object implements shapeless.Lub<T, T, T>
  minor version: 0
  major version: 52
  flags: (0x0031) ACC_PUBLIC, ACC_FINAL, ACC_SUPER
  this_class: #2                          // shapeless/Lub$$anon$4
  super_class: #5                         // java/lang/Object
  interfaces: 1, fields: 0, methods: 3, attributes: 6
Constant pool:
   #1 = Utf8               shapeless/Lub$$anon$4
   #2 = Class              #1             // shapeless/Lub$$anon$4
   #3 = Utf8               Ljava/lang/Object;Lshapeless/Lub<TT;TT;TT;>;
   #4 = Utf8               java/lang/Object
   #5 = Class              #4             // java/lang/Object
   #6 = Utf8               shapeless/Lub
   #7 = Class              #6             // shapeless/Lub
   #8 = Utf8               typeoperators.scala
   #9 = Utf8               shapeless/Lub$
  #10 = Class              #9             // shapeless/Lub$
  #11 = Utf8               lub
  #12 = Utf8               ()Lshapeless/Lub;
  #13 = NameAndType        #11:#12        // lub:()Lshapeless/Lub;
  #14 = Utf8               left
  #15 = Utf8               (Ljava/lang/Object;)Ljava/lang/Object;
  #16 = Utf8               (TT;)TT;
  #17 = Utf8               a
  #18 = Utf8               this
  #19 = Utf8               Lshapeless/Lub$$anon$4;
  #20 = Utf8               Ljava/lang/Object;
  #21 = Utf8               right
  #22 = Utf8               b
  #23 = Utf8               <init>
  #24 = Utf8               ()V
  #25 = NameAndType        #23:#24        // "<init>":()V
  #26 = Methodref          #5.#25         // java/lang/Object."<init>":()V
  #27 = Utf8               Code
  #28 = Utf8               LineNumberTable
  #29 = Utf8               LocalVariableTable
  #30 = Utf8               Signature
  #31 = Utf8               MethodParameters
  #32 = Utf8               InnerClasses
  #33 = Utf8               EnclosingMethod
  #34 = Utf8               SourceFile
  #35 = Utf8               ScalaInlineInfo
  #36 = Utf8               Scala
{
  public T left(T);
    descriptor: (Ljava/lang/Object;)Ljava/lang/Object;
    flags: (0x0001) ACC_PUBLIC
    Code:
      stack=1, locals=2, args_size=2
         0: aload_1
         1: areturn
      LineNumberTable:
        line 200: 0
      LocalVariableTable:
        Start  Length  Slot  Name   Signature
            0       2     0  this   Lshapeless/Lub$$anon$4;
            0       2     1     a   Ljava/lang/Object;
    Signature: #16                          // (TT;)TT;
    MethodParameters:
      Name                           Flags
      a                              final

  public T right(T);
    descriptor: (Ljava/lang/Object;)Ljava/lang/Object;
    flags: (0x0001) ACC_PUBLIC
    Code:
      stack=1, locals=2, args_size=2
         0: aload_1
         1: areturn
      LineNumberTable:
        line 201: 0
      LocalVariableTable:
        Start  Length  Slot  Name   Signature
            0       2     0  this   Lshapeless/Lub$$anon$4;
            0       2     1     b   Ljava/lang/Object;
    Signature: #16                          // (TT;)TT;
    MethodParameters:
      Name                           Flags
      b                              final

  public shapeless.Lub$$anon$4();
    descriptor: ()V
    flags: (0x0001) ACC_PUBLIC
    Code:
      stack=1, locals=1, args_size=1
         0: aload_0
         1: invokespecial #26                 // Method java/lang/Object."<init>":()V
         4: return
      LineNumberTable:
        line 199: 0
      LocalVariableTable:
        Start  Length  Slot  Name   Signature
            0       5     0  this   Lshapeless/Lub$$anon$4;
}
InnerClasses:
  public final #2;                        // class shapeless/Lub$$anon$4
EnclosingMethod: #10.#13                // shapeless.Lub$.lub
Signature: #3                           // Ljava/lang/Object;Lshapeless/Lub<TT;TT;TT;>;
SourceFile: "typeoperators.scala"
  ScalaInlineInfo: length = 0x13 (unknown attribute)
   01 01 00 03 00 17 00 18 01 00 0E 00 0F 01 00 15
   00 0F 01
  Scala: length = 0x0 (unknown attribute)

