Classfile /Users/mw/Projects/slang-braindump/.jar/jar8/assemble/slang-braindump/assemble/content/shapeless/MkCoproductSelectPrism$$anon$35$$anon$36.class
  Last modified May 29, 2022; size 5201 bytes
  SHA-256 checksum 225a0fb379cce3b83157edc87bf18f2baf4f95923967a59d9edf626931b92cea
  Compiled from "lenses.scala"
public final class shapeless.MkCoproductSelectPrism$$anon$35$$anon$36 extends java.lang.Object implements shapeless.Prism<C, T>
  minor version: 0
  major version: 52
  flags: (0x0031) ACC_PUBLIC, ACC_FINAL, ACC_SUPER
  this_class: #2                          // shapeless/MkCoproductSelectPrism$$anon$35$$anon$36
  super_class: #5                         // java/lang/Object
  interfaces: 1, fields: 1, methods: 14, attributes: 6
Constant pool:
    #1 = Utf8               shapeless/MkCoproductSelectPrism$$anon$35$$anon$36
    #2 = Class              #1            // shapeless/MkCoproductSelectPrism$$anon$35$$anon$36
    #3 = Utf8               Ljava/lang/Object;Lshapeless/Prism<TC;TT;>;
    #4 = Utf8               java/lang/Object
    #5 = Class              #4            // java/lang/Object
    #6 = Utf8               shapeless/Prism
    #7 = Class              #6            // shapeless/Prism
    #8 = Utf8               lenses.scala
    #9 = Utf8               shapeless/MkCoproductSelectPrism$$anon$35
   #10 = Class              #9            // shapeless/MkCoproductSelectPrism$$anon$35
   #11 = Utf8               apply
   #12 = Utf8               ()Lshapeless/Prism;
   #13 = NameAndType        #11:#12       // apply:()Lshapeless/Prism;
   #14 = Utf8               shapeless/ops/coproduct$Inject
   #15 = Class              #14           // shapeless/ops/coproduct$Inject
   #16 = Utf8               shapeless/ops/coproduct
   #17 = Class              #16           // shapeless/ops/coproduct
   #18 = Utf8               Inject
   #19 = Utf8               shapeless/ops/coproduct$Selector
   #20 = Class              #19           // shapeless/ops/coproduct$Selector
   #21 = Utf8               Selector
   #22 = Utf8               $outer
   #23 = Utf8               Lshapeless/MkCoproductSelectPrism$$anon$35;
   #24 = Utf8               modify
   #25 = Utf8               (Ljava/lang/Object;Lscala/Function1;)Ljava/lang/Object;
   #26 = Utf8               s
   #27 = Utf8               f
   #28 = Utf8               modify$
   #29 = Utf8               (Lshapeless/Prism;Ljava/lang/Object;Lscala/Function1;)Ljava/lang/Object;
   #30 = NameAndType        #28:#29       // modify$:(Lshapeless/Prism;Ljava/lang/Object;Lscala/Function1;)Ljava/lang/Object;
   #31 = InterfaceMethodref #7.#30        // shapeless/Prism.modify$:(Lshapeless/Prism;Ljava/lang/Object;Lscala/Function1;)Ljava/lang/Object;
   #32 = Utf8               this
   #33 = Utf8               Lshapeless/MkCoproductSelectPrism$$anon$35$$anon$36;
   #34 = Utf8               Ljava/lang/Object;
   #35 = Utf8               Lscala/Function1;
   #36 = Utf8               compose
   #37 = Utf8               (Lshapeless/Lens;)Lshapeless/Prism;
   #38 = Utf8               <T:Ljava/lang/Object;>(Lshapeless/Lens<TT;TC;>;)Lshapeless/Prism<TT;TT;>;
   #39 = Utf8               g
   #40 = Utf8               compose$
   #41 = Utf8               (Lshapeless/Prism;Lshapeless/Lens;)Lshapeless/Prism;
   #42 = NameAndType        #40:#41       // compose$:(Lshapeless/Prism;Lshapeless/Lens;)Lshapeless/Prism;
   #43 = InterfaceMethodref #7.#42        // shapeless/Prism.compose$:(Lshapeless/Prism;Lshapeless/Lens;)Lshapeless/Prism;
   #44 = Utf8               Lshapeless/Lens;
   #45 = Utf8               (Lshapeless/Prism;)Lshapeless/Prism;
   #46 = Utf8               <T:Ljava/lang/Object;>(Lshapeless/Prism<TT;TC;>;)Lshapeless/Prism<TT;TT;>;
   #47 = Utf8               (Lshapeless/Prism;Lshapeless/Prism;)Lshapeless/Prism;
   #48 = NameAndType        #40:#47       // compose$:(Lshapeless/Prism;Lshapeless/Prism;)Lshapeless/Prism;
   #49 = InterfaceMethodref #7.#48        // shapeless/Prism.compose$:(Lshapeless/Prism;Lshapeless/Prism;)Lshapeless/Prism;
   #50 = Utf8               Lshapeless/Prism;
   #51 = Utf8               selectDynamic
   #52 = Utf8               (Ljava/lang/String;Lshapeless/MkSelectDynamicOptic;)Ljava/lang/Object;
   #53 = Utf8               (Ljava/lang/String;Lshapeless/MkSelectDynamicOptic<Lshapeless/Prism<TC;TT;>;TT;Lscala/Symbol;Lscala/runtime/Nothing$;>;)Ljava/lang/Object;
   #54 = Utf8               k
   #55 = Utf8               mkPrism
   #56 = Utf8               selectDynamic$
   #57 = Utf8               (Lshapeless/Prism;Ljava/lang/String;Lshapeless/MkSelectDynamicOptic;)Ljava/lang/Object;
   #58 = NameAndType        #56:#57       // selectDynamic$:(Lshapeless/Prism;Ljava/lang/String;Lshapeless/MkSelectDynamicOptic;)Ljava/lang/Object;
   #59 = InterfaceMethodref #7.#58        // shapeless/Prism.selectDynamic$:(Lshapeless/Prism;Ljava/lang/String;Lshapeless/MkSelectDynamicOptic;)Ljava/lang/Object;
   #60 = Utf8               Ljava/lang/String;
   #61 = Utf8               Lshapeless/MkSelectDynamicOptic;
   #62 = Utf8               (Lshapeless/MkCtorPrism;)Lshapeless/Prism;
   #63 = Utf8               <B:Ljava/lang/Object;>(Lshapeless/MkCtorPrism<TT;TB;>;)Lshapeless/Prism<TC;TB;>;
   #64 = Utf8               apply$
   #65 = Utf8               (Lshapeless/Prism;Lshapeless/MkCtorPrism;)Lshapeless/Prism;
   #66 = NameAndType        #64:#65       // apply$:(Lshapeless/Prism;Lshapeless/MkCtorPrism;)Lshapeless/Prism;
   #67 = InterfaceMethodref #7.#66        // shapeless/Prism.apply$:(Lshapeless/Prism;Lshapeless/MkCtorPrism;)Lshapeless/Prism;
   #68 = Utf8               Lshapeless/MkCtorPrism;
   #69 = Utf8               unapply
   #70 = Utf8               (Ljava/lang/Object;)Lscala/Option;
   #71 = Utf8               unapply$
   #72 = Utf8               (Lshapeless/Prism;Ljava/lang/Object;)Lscala/Option;
   #73 = NameAndType        #71:#72       // unapply$:(Lshapeless/Prism;Ljava/lang/Object;)Lscala/Option;
   #74 = InterfaceMethodref #7.#73        // shapeless/Prism.unapply$:(Lshapeless/Prism;Ljava/lang/Object;)Lscala/Option;
   #75 = Utf8               $tilde
   #76 = Utf8               (Lshapeless/Lens;)Lshapeless/ProductPrismBuilder;
   #77 = Utf8               <B:Ljava/lang/Object;>(Lshapeless/Lens<TC;TB;>;)Lshapeless/ProductPrismBuilder<TC;Lscala/Tuple2<TT;TB;>;>;
   #78 = Utf8               other
   #79 = Utf8               $tilde$
   #80 = Utf8               (Lshapeless/Prism;Lshapeless/Lens;)Lshapeless/ProductPrismBuilder;
   #81 = NameAndType        #79:#80       // $tilde$:(Lshapeless/Prism;Lshapeless/Lens;)Lshapeless/ProductPrismBuilder;
   #82 = InterfaceMethodref #7.#81        // shapeless/Prism.$tilde$:(Lshapeless/Prism;Lshapeless/Lens;)Lshapeless/ProductPrismBuilder;
   #83 = Utf8               (Lshapeless/Prism;)Lshapeless/ProductPrismBuilder;
   #84 = Utf8               <B:Ljava/lang/Object;>(Lshapeless/Prism<TC;TB;>;)Lshapeless/ProductPrismBuilder<TC;Lscala/Tuple2<TT;TB;>;>;
   #85 = Utf8               (Lshapeless/Prism;Lshapeless/Prism;)Lshapeless/ProductPrismBuilder;
   #86 = NameAndType        #79:#85       // $tilde$:(Lshapeless/Prism;Lshapeless/Prism;)Lshapeless/ProductPrismBuilder;
   #87 = InterfaceMethodref #7.#86        // shapeless/Prism.$tilde$:(Lshapeless/Prism;Lshapeless/Prism;)Lshapeless/ProductPrismBuilder;
   #88 = Utf8               (Ljava/lang/String;Lshapeless/MkSelectDynamicOptic;Lscala/DummyImplicit;)Ljava/lang/Object;
   #89 = Utf8               <B:Ljava/lang/Object;>(Ljava/lang/String;Lshapeless/MkSelectDynamicOptic<Lshapeless/Prism<TC;TT;>;TT;Lscala/Symbol;TB;>;Lscala/DummyImplicit;)Ljava/lang/Object;
   #90 = Utf8               dummy
   #91 = Utf8               shapeless/LPPrism
   #92 = Class              #91           // shapeless/LPPrism
   #93 = Utf8               (Lshapeless/LPPrism;Ljava/lang/String;Lshapeless/MkSelectDynamicOptic;Lscala/DummyImplicit;)Ljava/lang/Object;
   #94 = NameAndType        #56:#93       // selectDynamic$:(Lshapeless/LPPrism;Ljava/lang/String;Lshapeless/MkSelectDynamicOptic;Lscala/DummyImplicit;)Ljava/lang/Object;
   #95 = InterfaceMethodref #92.#94       // shapeless/LPPrism.selectDynamic$:(Lshapeless/LPPrism;Ljava/lang/String;Lshapeless/MkSelectDynamicOptic;Lscala/DummyImplicit;)Ljava/lang/Object;
   #96 = Utf8               Lscala/DummyImplicit;
   #97 = Utf8               get
   #98 = Utf8               (Lshapeless/Coproduct;)Lscala/Option;
   #99 = Utf8               (TC;)Lscala/Option<TT;>;
  #100 = Utf8               c
  #101 = NameAndType        #22:#23       // $outer:Lshapeless/MkCoproductSelectPrism$$anon$35;
  #102 = Fieldref           #2.#101       // shapeless/MkCoproductSelectPrism$$anon$35$$anon$36.$outer:Lshapeless/MkCoproductSelectPrism$$anon$35;
  #103 = Utf8               selector$2
  #104 = Utf8               Lshapeless/ops/coproduct$Selector;
  #105 = NameAndType        #103:#104     // selector$2:Lshapeless/ops/coproduct$Selector;
  #106 = Fieldref           #10.#105      // shapeless/MkCoproductSelectPrism$$anon$35.selector$2:Lshapeless/ops/coproduct$Selector;
  #107 = NameAndType        #11:#98       // apply:(Lshapeless/Coproduct;)Lscala/Option;
  #108 = InterfaceMethodref #20.#107      // shapeless/ops/coproduct$Selector.apply:(Lshapeless/Coproduct;)Lscala/Option;
  #109 = Utf8               Lshapeless/Coproduct;
  #110 = Utf8               set
  #111 = Utf8               (Lshapeless/Coproduct;Ljava/lang/Object;)Lshapeless/Coproduct;
  #112 = Utf8               (TC;TT;)TC;
  #113 = Utf8               t
  #114 = Utf8               injector$1
  #115 = Utf8               Lshapeless/ops/coproduct$Inject;
  #116 = NameAndType        #114:#115     // injector$1:Lshapeless/ops/coproduct$Inject;
  #117 = Fieldref           #10.#116      // shapeless/MkCoproductSelectPrism$$anon$35.injector$1:Lshapeless/ops/coproduct$Inject;
  #118 = Utf8               (Ljava/lang/Object;)Lshapeless/Coproduct;
  #119 = NameAndType        #11:#118      // apply:(Ljava/lang/Object;)Lshapeless/Coproduct;
  #120 = InterfaceMethodref #15.#119      // shapeless/ops/coproduct$Inject.apply:(Ljava/lang/Object;)Lshapeless/Coproduct;
  #121 = Utf8               (Ljava/lang/Object;Ljava/lang/Object;)Ljava/lang/Object;
  #122 = Utf8               a
  #123 = Utf8               shapeless/Coproduct
  #124 = Class              #123          // shapeless/Coproduct
  #125 = NameAndType        #110:#111     // set:(Lshapeless/Coproduct;Ljava/lang/Object;)Lshapeless/Coproduct;
  #126 = Methodref          #2.#125       // shapeless/MkCoproductSelectPrism$$anon$35$$anon$36.set:(Lshapeless/Coproduct;Ljava/lang/Object;)Lshapeless/Coproduct;
  #127 = NameAndType        #97:#98       // get:(Lshapeless/Coproduct;)Lscala/Option;
  #128 = Methodref          #2.#127       // shapeless/MkCoproductSelectPrism$$anon$35$$anon$36.get:(Lshapeless/Coproduct;)Lscala/Option;
  #129 = Utf8               <init>
  #130 = Utf8               (Lshapeless/MkCoproductSelectPrism$$anon$35;)V
  #131 = Utf8               ()V
  #132 = NameAndType        #129:#131     // "<init>":()V
  #133 = Methodref          #5.#132       // java/lang/Object."<init>":()V
  #134 = Utf8               $init$
  #135 = Utf8               (Lshapeless/LPPrism;)V
  #136 = NameAndType        #134:#135     // $init$:(Lshapeless/LPPrism;)V
  #137 = InterfaceMethodref #92.#136      // shapeless/LPPrism.$init$:(Lshapeless/LPPrism;)V
  #138 = Utf8               (Lshapeless/Prism;)V
  #139 = NameAndType        #134:#138     // $init$:(Lshapeless/Prism;)V
  #140 = InterfaceMethodref #7.#139       // shapeless/Prism.$init$:(Lshapeless/Prism;)V
  #141 = Utf8               Code
  #142 = Utf8               LineNumberTable
  #143 = Utf8               LocalVariableTable
  #144 = Utf8               MethodParameters
  #145 = Utf8               Signature
  #146 = Utf8               StackMapTable
  #147 = Utf8               InnerClasses
  #148 = Utf8               EnclosingMethod
  #149 = Utf8               SourceFile
  #150 = Utf8               ScalaInlineInfo
  #151 = Utf8               Scala
{
  private final shapeless.MkCoproductSelectPrism$$anon$35 $outer;
    descriptor: Lshapeless/MkCoproductSelectPrism$$anon$35;
    flags: (0x1012) ACC_PRIVATE, ACC_FINAL, ACC_SYNTHETIC

  public java.lang.Object modify(java.lang.Object, scala.Function1);
    descriptor: (Ljava/lang/Object;Lscala/Function1;)Ljava/lang/Object;
    flags: (0x0001) ACC_PUBLIC
    Code:
      stack=3, locals=3, args_size=3
         0: aload_0
         1: aload_1
         2: aload_2
         3: invokestatic  #31                 // InterfaceMethod shapeless/Prism.modify$:(Lshapeless/Prism;Ljava/lang/Object;Lscala/Function1;)Ljava/lang/Object;
         6: areturn
      LineNumberTable:
        line 444: 0
      LocalVariableTable:
        Start  Length  Slot  Name   Signature
            0       7     0  this   Lshapeless/MkCoproductSelectPrism$$anon$35$$anon$36;
            0       7     1     s   Ljava/lang/Object;
            0       7     2     f   Lscala/Function1;
    MethodParameters:
      Name                           Flags
      s                              final
      f                              final

  public <T extends java.lang.Object> shapeless.Prism<T, T> compose(shapeless.Lens<T, C>);
    descriptor: (Lshapeless/Lens;)Lshapeless/Prism;
    flags: (0x0001) ACC_PUBLIC
    Code:
      stack=2, locals=2, args_size=2
         0: aload_0
         1: aload_1
         2: invokestatic  #43                 // InterfaceMethod shapeless/Prism.compose$:(Lshapeless/Prism;Lshapeless/Lens;)Lshapeless/Prism;
         5: areturn
      LineNumberTable:
        line 444: 0
      LocalVariableTable:
        Start  Length  Slot  Name   Signature
            0       6     0  this   Lshapeless/MkCoproductSelectPrism$$anon$35$$anon$36;
            0       6     1     g   Lshapeless/Lens;
    Signature: #38                          // <T:Ljava/lang/Object;>(Lshapeless/Lens<TT;TC;>;)Lshapeless/Prism<TT;TT;>;
    MethodParameters:
      Name                           Flags
      g                              final

  public <T extends java.lang.Object> shapeless.Prism<T, T> compose(shapeless.Prism<T, C>);
    descriptor: (Lshapeless/Prism;)Lshapeless/Prism;
    flags: (0x0001) ACC_PUBLIC
    Code:
      stack=2, locals=2, args_size=2
         0: aload_0
         1: aload_1
         2: invokestatic  #49                 // InterfaceMethod shapeless/Prism.compose$:(Lshapeless/Prism;Lshapeless/Prism;)Lshapeless/Prism;
         5: areturn
      LineNumberTable:
        line 444: 0
      LocalVariableTable:
        Start  Length  Slot  Name   Signature
            0       6     0  this   Lshapeless/MkCoproductSelectPrism$$anon$35$$anon$36;
            0       6     1     g   Lshapeless/Prism;
    Signature: #46                          // <T:Ljava/lang/Object;>(Lshapeless/Prism<TT;TC;>;)Lshapeless/Prism<TT;TT;>;
    MethodParameters:
      Name                           Flags
      g                              final

  public java.lang.Object selectDynamic(java.lang.String, shapeless.MkSelectDynamicOptic<shapeless.Prism<C, T>, T, scala.Symbol, scala.runtime.Nothing$>);
    descriptor: (Ljava/lang/String;Lshapeless/MkSelectDynamicOptic;)Ljava/lang/Object;
    flags: (0x0001) ACC_PUBLIC
    Code:
      stack=3, locals=3, args_size=3
         0: aload_0
         1: aload_1
         2: aload_2
         3: invokestatic  #59                 // InterfaceMethod shapeless/Prism.selectDynamic$:(Lshapeless/Prism;Ljava/lang/String;Lshapeless/MkSelectDynamicOptic;)Ljava/lang/Object;
         6: areturn
      LineNumberTable:
        line 444: 0
      LocalVariableTable:
        Start  Length  Slot  Name   Signature
            0       7     0  this   Lshapeless/MkCoproductSelectPrism$$anon$35$$anon$36;
            0       7     1     k   Ljava/lang/String;
            0       7     2 mkPrism   Lshapeless/MkSelectDynamicOptic;
    Signature: #53                          // (Ljava/lang/String;Lshapeless/MkSelectDynamicOptic<Lshapeless/Prism<TC;TT;>;TT;Lscala/Symbol;Lscala/runtime/Nothing$;>;)Ljava/lang/Object;
    MethodParameters:
      Name                           Flags
      k                              final
      mkPrism                        final

  public <B extends java.lang.Object> shapeless.Prism<C, B> apply(shapeless.MkCtorPrism<T, B>);
    descriptor: (Lshapeless/MkCtorPrism;)Lshapeless/Prism;
    flags: (0x0001) ACC_PUBLIC
    Code:
      stack=2, locals=2, args_size=2
         0: aload_0
         1: aload_1
         2: invokestatic  #67                 // InterfaceMethod shapeless/Prism.apply$:(Lshapeless/Prism;Lshapeless/MkCtorPrism;)Lshapeless/Prism;
         5: areturn
      LineNumberTable:
        line 444: 0
      LocalVariableTable:
        Start  Length  Slot  Name   Signature
            0       6     0  this   Lshapeless/MkCoproductSelectPrism$$anon$35$$anon$36;
            0       6     1 mkPrism   Lshapeless/MkCtorPrism;
    Signature: #63                          // <B:Ljava/lang/Object;>(Lshapeless/MkCtorPrism<TT;TB;>;)Lshapeless/Prism<TC;TB;>;
    MethodParameters:
      Name                           Flags
      mkPrism                        final

  public scala.Option unapply(java.lang.Object);
    descriptor: (Ljava/lang/Object;)Lscala/Option;
    flags: (0x0001) ACC_PUBLIC
    Code:
      stack=2, locals=2, args_size=2
         0: aload_0
         1: aload_1
         2: invokestatic  #74                 // InterfaceMethod shapeless/Prism.unapply$:(Lshapeless/Prism;Ljava/lang/Object;)Lscala/Option;
         5: areturn
      LineNumberTable:
        line 444: 0
      LocalVariableTable:
        Start  Length  Slot  Name   Signature
            0       6     0  this   Lshapeless/MkCoproductSelectPrism$$anon$35$$anon$36;
            0       6     1     s   Ljava/lang/Object;
    MethodParameters:
      Name                           Flags
      s                              final

  public <B extends java.lang.Object> shapeless.ProductPrismBuilder<C, scala.Tuple2<T, B>> $tilde(shapeless.Lens<C, B>);
    descriptor: (Lshapeless/Lens;)Lshapeless/ProductPrismBuilder;
    flags: (0x0001) ACC_PUBLIC
    Code:
      stack=2, locals=2, args_size=2
         0: aload_0
         1: aload_1
         2: invokestatic  #82                 // InterfaceMethod shapeless/Prism.$tilde$:(Lshapeless/Prism;Lshapeless/Lens;)Lshapeless/ProductPrismBuilder;
         5: areturn
      LineNumberTable:
        line 444: 0
      LocalVariableTable:
        Start  Length  Slot  Name   Signature
            0       6     0  this   Lshapeless/MkCoproductSelectPrism$$anon$35$$anon$36;
            0       6     1 other   Lshapeless/Lens;
    Signature: #77                          // <B:Ljava/lang/Object;>(Lshapeless/Lens<TC;TB;>;)Lshapeless/ProductPrismBuilder<TC;Lscala/Tuple2<TT;TB;>;>;
    MethodParameters:
      Name                           Flags
      other                          final

  public <B extends java.lang.Object> shapeless.ProductPrismBuilder<C, scala.Tuple2<T, B>> $tilde(shapeless.Prism<C, B>);
    descriptor: (Lshapeless/Prism;)Lshapeless/ProductPrismBuilder;
    flags: (0x0001) ACC_PUBLIC
    Code:
      stack=2, locals=2, args_size=2
         0: aload_0
         1: aload_1
         2: invokestatic  #87                 // InterfaceMethod shapeless/Prism.$tilde$:(Lshapeless/Prism;Lshapeless/Prism;)Lshapeless/ProductPrismBuilder;
         5: areturn
      LineNumberTable:
        line 444: 0
      LocalVariableTable:
        Start  Length  Slot  Name   Signature
            0       6     0  this   Lshapeless/MkCoproductSelectPrism$$anon$35$$anon$36;
            0       6     1 other   Lshapeless/Prism;
    Signature: #84                          // <B:Ljava/lang/Object;>(Lshapeless/Prism<TC;TB;>;)Lshapeless/ProductPrismBuilder<TC;Lscala/Tuple2<TT;TB;>;>;
    MethodParameters:
      Name                           Flags
      other                          final

  public <B extends java.lang.Object> java.lang.Object selectDynamic(java.lang.String, shapeless.MkSelectDynamicOptic<shapeless.Prism<C, T>, T, scala.Symbol, B>, scala.DummyImplicit);
    descriptor: (Ljava/lang/String;Lshapeless/MkSelectDynamicOptic;Lscala/DummyImplicit;)Ljava/lang/Object;
    flags: (0x0001) ACC_PUBLIC
    Code:
      stack=4, locals=4, args_size=4
         0: aload_0
         1: aload_1
         2: aload_2
         3: aload_3
         4: invokestatic  #95                 // InterfaceMethod shapeless/LPPrism.selectDynamic$:(Lshapeless/LPPrism;Ljava/lang/String;Lshapeless/MkSelectDynamicOptic;Lscala/DummyImplicit;)Ljava/lang/Object;
         7: areturn
      LineNumberTable:
        line 444: 0
      LocalVariableTable:
        Start  Length  Slot  Name   Signature
            0       8     0  this   Lshapeless/MkCoproductSelectPrism$$anon$35$$anon$36;
            0       8     1     k   Ljava/lang/String;
            0       8     2 mkPrism   Lshapeless/MkSelectDynamicOptic;
            0       8     3 dummy   Lscala/DummyImplicit;
    Signature: #89                          // <B:Ljava/lang/Object;>(Ljava/lang/String;Lshapeless/MkSelectDynamicOptic<Lshapeless/Prism<TC;TT;>;TT;Lscala/Symbol;TB;>;Lscala/DummyImplicit;)Ljava/lang/Object;
    MethodParameters:
      Name                           Flags
      k                              final
      mkPrism                        final
      dummy                          final

  public scala.Option<T> get(C);
    descriptor: (Lshapeless/Coproduct;)Lscala/Option;
    flags: (0x0001) ACC_PUBLIC
    Code:
      stack=2, locals=2, args_size=2
         0: aload_0
         1: getfield      #102                // Field $outer:Lshapeless/MkCoproductSelectPrism$$anon$35;
         4: getfield      #106                // Field shapeless/MkCoproductSelectPrism$$anon$35.selector$2:Lshapeless/ops/coproduct$Selector;
         7: aload_1
         8: invokeinterface #108,  2          // InterfaceMethod shapeless/ops/coproduct$Selector.apply:(Lshapeless/Coproduct;)Lscala/Option;
        13: areturn
      LineNumberTable:
        line 445: 0
      LocalVariableTable:
        Start  Length  Slot  Name   Signature
            0      14     0  this   Lshapeless/MkCoproductSelectPrism$$anon$35$$anon$36;
            0      14     1     c   Lshapeless/Coproduct;
    Signature: #99                          // (TC;)Lscala/Option<TT;>;
    MethodParameters:
      Name                           Flags
      c                              final

  public C set(C, T);
    descriptor: (Lshapeless/Coproduct;Ljava/lang/Object;)Lshapeless/Coproduct;
    flags: (0x0001) ACC_PUBLIC
    Code:
      stack=2, locals=3, args_size=3
         0: aload_0
         1: getfield      #102                // Field $outer:Lshapeless/MkCoproductSelectPrism$$anon$35;
         4: getfield      #117                // Field shapeless/MkCoproductSelectPrism$$anon$35.injector$1:Lshapeless/ops/coproduct$Inject;
         7: aload_2
         8: invokeinterface #120,  2          // InterfaceMethod shapeless/ops/coproduct$Inject.apply:(Ljava/lang/Object;)Lshapeless/Coproduct;
        13: areturn
      LineNumberTable:
        line 446: 0
      LocalVariableTable:
        Start  Length  Slot  Name   Signature
            0      14     0  this   Lshapeless/MkCoproductSelectPrism$$anon$35$$anon$36;
            0      14     1     c   Lshapeless/Coproduct;
            0      14     2     t   Ljava/lang/Object;
    Signature: #112                         // (TC;TT;)TC;
    MethodParameters:
      Name                           Flags
      c                              final
      t                              final

  public java.lang.Object set(java.lang.Object, java.lang.Object);
    descriptor: (Ljava/lang/Object;Ljava/lang/Object;)Ljava/lang/Object;
    flags: (0x1041) ACC_PUBLIC, ACC_BRIDGE, ACC_SYNTHETIC
    Code:
      stack=3, locals=3, args_size=3
         0: aload_0
         1: aload_1
         2: checkcast     #124                // class shapeless/Coproduct
         5: aload_2
         6: invokevirtual #126                // Method set:(Lshapeless/Coproduct;Ljava/lang/Object;)Lshapeless/Coproduct;
         9: areturn
      LineNumberTable:
        line 444: 0
      LocalVariableTable:
        Start  Length  Slot  Name   Signature
            0      10     0  this   Lshapeless/MkCoproductSelectPrism$$anon$35$$anon$36;
            0      10     1     s   Ljava/lang/Object;
            0      10     2     a   Ljava/lang/Object;
    MethodParameters:
      Name                           Flags
      s                              final
      a                              final

  public scala.Option get(java.lang.Object);
    descriptor: (Ljava/lang/Object;)Lscala/Option;
    flags: (0x1041) ACC_PUBLIC, ACC_BRIDGE, ACC_SYNTHETIC
    Code:
      stack=2, locals=2, args_size=2
         0: aload_0
         1: aload_1
         2: checkcast     #124                // class shapeless/Coproduct
         5: invokevirtual #128                // Method get:(Lshapeless/Coproduct;)Lscala/Option;
         8: areturn
      LineNumberTable:
        line 444: 0
      LocalVariableTable:
        Start  Length  Slot  Name   Signature
            0       9     0  this   Lshapeless/MkCoproductSelectPrism$$anon$35$$anon$36;
            0       9     1     s   Ljava/lang/Object;
    MethodParameters:
      Name                           Flags
      s                              final

  public shapeless.MkCoproductSelectPrism$$anon$35$$anon$36(shapeless.MkCoproductSelectPrism$$anon$35);
    descriptor: (Lshapeless/MkCoproductSelectPrism$$anon$35;)V
    flags: (0x0001) ACC_PUBLIC
    Code:
      stack=2, locals=2, args_size=2
         0: aload_1
         1: ifnonnull     6
         4: aconst_null
         5: athrow
         6: aload_0
         7: aload_1
         8: putfield      #102                // Field $outer:Lshapeless/MkCoproductSelectPrism$$anon$35;
        11: aload_0
        12: invokespecial #133                // Method java/lang/Object."<init>":()V
        15: aload_0
        16: invokestatic  #137                // InterfaceMethod shapeless/LPPrism.$init$:(Lshapeless/LPPrism;)V
        19: aload_0
        20: invokestatic  #140                // InterfaceMethod shapeless/Prism.$init$:(Lshapeless/Prism;)V
        23: return
      StackMapTable: number_of_entries = 1
        frame_type = 6 /* same */
      LineNumberTable:
        line 444: 0
      LocalVariableTable:
        Start  Length  Slot  Name   Signature
            0      24     0  this   Lshapeless/MkCoproductSelectPrism$$anon$35$$anon$36;
            0      24     1 $outer   Lshapeless/MkCoproductSelectPrism$$anon$35;
    MethodParameters:
      Name                           Flags
      $outer                         final synthetic
}
InnerClasses:
  public final #10;                       // class shapeless/MkCoproductSelectPrism$$anon$35
  public final #2;                        // class shapeless/MkCoproductSelectPrism$$anon$35$$anon$36
  public static #18= #15 of #17;          // Inject=class shapeless/ops/coproduct$Inject of class shapeless/ops/coproduct
  public static #21= #20 of #17;          // Selector=class shapeless/ops/coproduct$Selector of class shapeless/ops/coproduct
EnclosingMethod: #10.#13                // shapeless.MkCoproductSelectPrism$$anon$35.apply
Signature: #3                           // Ljava/lang/Object;Lshapeless/Prism<TC;TT;>;
SourceFile: "lenses.scala"
  ScalaInlineInfo: length = 0x4A (unknown attribute)
   01 01 00 0E 00 4B 00 4C 01 00 4B 00 53 01 00 81
   00 82 01 00 0B 00 3E 01 00 24 00 25 01 00 24 00
   2D 01 00 61 00 46 01 00 61 00 62 01 00 18 00 19
   01 00 33 00 34 01 00 33 00 58 01 00 6E 00 79 01
   00 6E 00 6F 01 00 45 00 46 01
  Scala: length = 0x0 (unknown attribute)

