Classfile /Users/mw/Projects/slang-braindump/.jar/jar8/assemble/slang-braindump/assemble/content/shapeless/Nat$.class
  Last modified May 29, 2022; size 21535 bytes
  SHA-256 checksum 3710fd5f3acba2da1f6e1907f3e439f5b794d3db2c74e149c99240be538a9973
  Compiled from "nat.scala"
public final class shapeless.Nat$ implements shapeless.Nats
  minor version: 0
  major version: 52
  flags: (0x0031) ACC_PUBLIC, ACC_FINAL, ACC_SUPER
  this_class: #2                          // shapeless/Nat$
  super_class: #4                         // java/lang/Object
  interfaces: 1, fields: 24, methods: 50, attributes: 4
Constant pool:
    #1 = Utf8               shapeless/Nat$
    #2 = Class              #1            // shapeless/Nat$
    #3 = Utf8               java/lang/Object
    #4 = Class              #3            // java/lang/Object
    #5 = Utf8               shapeless/Nats
    #6 = Class              #5            // shapeless/Nats
    #7 = Utf8               nat.scala
    #8 = Utf8               shapeless/ops/nat$ToInt
    #9 = Class              #8            // shapeless/ops/nat$ToInt
   #10 = Utf8               shapeless/ops/nat
   #11 = Class              #10           // shapeless/ops/nat
   #12 = Utf8               ToInt
   #13 = Utf8               MODULE$
   #14 = Utf8               Lshapeless/Nat$;
   #15 = Utf8               _0
   #16 = Utf8               Lshapeless/_0;
   #17 = Utf8               _1
   #18 = Utf8               Lshapeless/Succ;
   #19 = Utf8               Lshapeless/Succ<Lshapeless/_0;>;
   #20 = Utf8               _2
   #21 = Utf8               Lshapeless/Succ<Lshapeless/Succ<Lshapeless/_0;>;>;
   #22 = Utf8               _3
   #23 = Utf8               Lshapeless/Succ<Lshapeless/Succ<Lshapeless/Succ<Lshapeless/_0;>;>;>;
   #24 = Utf8               _4
   #25 = Utf8               Lshapeless/Succ<Lshapeless/Succ<Lshapeless/Succ<Lshapeless/Succ<Lshapeless/_0;>;>;>;>;
   #26 = Utf8               _5
   #27 = Utf8               Lshapeless/Succ<Lshapeless/Succ<Lshapeless/Succ<Lshapeless/Succ<Lshapeless/Succ<Lshapeless/_0;>;>;>;>;>;
   #28 = Utf8               _6
   #29 = Utf8               Lshapeless/Succ<Lshapeless/Succ<Lshapeless/Succ<Lshapeless/Succ<Lshapeless/Succ<Lshapeless/Succ<Lshapeless/_0;>;>;>;>;>;>;
   #30 = Utf8               _7
   #31 = Utf8               Lshapeless/Succ<Lshapeless/Succ<Lshapeless/Succ<Lshapeless/Succ<Lshapeless/Succ<Lshapeless/Succ<Lshapeless/Succ<Lshapeless/_0;>;>;>;>;>;>;>;
   #32 = Utf8               _8
   #33 = Utf8               Lshapeless/Succ<Lshapeless/Succ<Lshapeless/Succ<Lshapeless/Succ<Lshapeless/Succ<Lshapeless/Succ<Lshapeless/Succ<Lshapeless/Succ<Lshapeless/_0;>;>;>;>;>;>;>;>;
   #34 = Utf8               _9
   #35 = Utf8               Lshapeless/Succ<Lshapeless/Succ<Lshapeless/Succ<Lshapeless/Succ<Lshapeless/Succ<Lshapeless/Succ<Lshapeless/Succ<Lshapeless/Succ<Lshapeless/Succ<Lshapeless/_0;>;>;>;>;>;>;>;>;>;
   #36 = Utf8               _10
   #37 = Utf8               Lshapeless/Succ<Lshapeless/Succ<Lshapeless/Succ<Lshapeless/Succ<Lshapeless/Succ<Lshapeless/Succ<Lshapeless/Succ<Lshapeless/Succ<Lshapeless/Succ<Lshapeless/Succ<Lshapeless/_0;>;>;>;>;>;>;>;>;>;>;
   #38 = Utf8               _11
   #39 = Utf8               Lshapeless/Succ<Lshapeless/Succ<Lshapeless/Succ<Lshapeless/Succ<Lshapeless/Succ<Lshapeless/Succ<Lshapeless/Succ<Lshapeless/Succ<Lshapeless/Succ<Lshapeless/Succ<Lshapeless/Succ<Lshapeless/_0;>;>;>;>;>;>;>;>;>;>;>;
   #40 = Utf8               _12
   #41 = Utf8               Lshapeless/Succ<Lshapeless/Succ<Lshapeless/Succ<Lshapeless/Succ<Lshapeless/Succ<Lshapeless/Succ<Lshapeless/Succ<Lshapeless/Succ<Lshapeless/Succ<Lshapeless/Succ<Lshapeless/Succ<Lshapeless/Succ<Lshapeless/_0;>;>;>;>;>;>;>;>;>;>;>;>;
   #42 = Utf8               _13
   #43 = Utf8               Lshapeless/Succ<Lshapeless/Succ<Lshapeless/Succ<Lshapeless/Succ<Lshapeless/Succ<Lshapeless/Succ<Lshapeless/Succ<Lshapeless/Succ<Lshapeless/Succ<Lshapeless/Succ<Lshapeless/Succ<Lshapeless/Succ<Lshapeless/Succ<Lshapeless/_0;>;>;>;>;>;>;>;>;>;>;>;>;>;
   #44 = Utf8               _14
   #45 = Utf8               Lshapeless/Succ<Lshapeless/Succ<Lshapeless/Succ<Lshapeless/Succ<Lshapeless/Succ<Lshapeless/Succ<Lshapeless/Succ<Lshapeless/Succ<Lshapeless/Succ<Lshapeless/Succ<Lshapeless/Succ<Lshapeless/Succ<Lshapeless/Succ<Lshapeless/Succ<Lshapeless/_0;>;>;>;>;>;>;>;>;>;>;>;>;>;>;
   #46 = Utf8               _15
   #47 = Utf8               Lshapeless/Succ<Lshapeless/Succ<Lshapeless/Succ<Lshapeless/Succ<Lshapeless/Succ<Lshapeless/Succ<Lshapeless/Succ<Lshapeless/Succ<Lshapeless/Succ<Lshapeless/Succ<Lshapeless/Succ<Lshapeless/Succ<Lshapeless/Succ<Lshapeless/Succ<Lshapeless/Succ<Lshapeless/_0;>;>;>;>;>;>;>;>;>;>;>;>;>;>;>;
   #48 = Utf8               _16
   #49 = Utf8               Lshapeless/Succ<Lshapeless/Succ<Lshapeless/Succ<Lshapeless/Succ<Lshapeless/Succ<Lshapeless/Succ<Lshapeless/Succ<Lshapeless/Succ<Lshapeless/Succ<Lshapeless/Succ<Lshapeless/Succ<Lshapeless/Succ<Lshapeless/Succ<Lshapeless/Succ<Lshapeless/Succ<Lshapeless/Succ<Lshapeless/_0;>;>;>;>;>;>;>;>;>;>;>;>;>;>;>;>;
   #50 = Utf8               _17
   #51 = Utf8               Lshapeless/Succ<Lshapeless/Succ<Lshapeless/Succ<Lshapeless/Succ<Lshapeless/Succ<Lshapeless/Succ<Lshapeless/Succ<Lshapeless/Succ<Lshapeless/Succ<Lshapeless/Succ<Lshapeless/Succ<Lshapeless/Succ<Lshapeless/Succ<Lshapeless/Succ<Lshapeless/Succ<Lshapeless/Succ<Lshapeless/Succ<Lshapeless/_0;>;>;>;>;>;>;>;>;>;>;>;>;>;>;>;>;>;
   #52 = Utf8               _18
   #53 = Utf8               Lshapeless/Succ<Lshapeless/Succ<Lshapeless/Succ<Lshapeless/Succ<Lshapeless/Succ<Lshapeless/Succ<Lshapeless/Succ<Lshapeless/Succ<Lshapeless/Succ<Lshapeless/Succ<Lshapeless/Succ<Lshapeless/Succ<Lshapeless/Succ<Lshapeless/Succ<Lshapeless/Succ<Lshapeless/Succ<Lshapeless/Succ<Lshapeless/Succ<Lshapeless/_0;>;>;>;>;>;>;>;>;>;>;>;>;>;>;>;>;>;>;
   #54 = Utf8               _19
   #55 = Utf8               Lshapeless/Succ<Lshapeless/Succ<Lshapeless/Succ<Lshapeless/Succ<Lshapeless/Succ<Lshapeless/Succ<Lshapeless/Succ<Lshapeless/Succ<Lshapeless/Succ<Lshapeless/Succ<Lshapeless/Succ<Lshapeless/Succ<Lshapeless/Succ<Lshapeless/Succ<Lshapeless/Succ<Lshapeless/Succ<Lshapeless/Succ<Lshapeless/Succ<Lshapeless/Succ<Lshapeless/_0;>;>;>;>;>;>;>;>;>;>;>;>;>;>;>;>;>;>;>;
   #56 = Utf8               _20
   #57 = Utf8               Lshapeless/Succ<Lshapeless/Succ<Lshapeless/Succ<Lshapeless/Succ<Lshapeless/Succ<Lshapeless/Succ<Lshapeless/Succ<Lshapeless/Succ<Lshapeless/Succ<Lshapeless/Succ<Lshapeless/Succ<Lshapeless/Succ<Lshapeless/Succ<Lshapeless/Succ<Lshapeless/Succ<Lshapeless/Succ<Lshapeless/Succ<Lshapeless/Succ<Lshapeless/Succ<Lshapeless/Succ<Lshapeless/_0;>;>;>;>;>;>;>;>;>;>;>;>;>;>;>;>;>;>;>;>;
   #58 = Utf8               _21
   #59 = Utf8               Lshapeless/Succ<Lshapeless/Succ<Lshapeless/Succ<Lshapeless/Succ<Lshapeless/Succ<Lshapeless/Succ<Lshapeless/Succ<Lshapeless/Succ<Lshapeless/Succ<Lshapeless/Succ<Lshapeless/Succ<Lshapeless/Succ<Lshapeless/Succ<Lshapeless/Succ<Lshapeless/Succ<Lshapeless/Succ<Lshapeless/Succ<Lshapeless/Succ<Lshapeless/Succ<Lshapeless/Succ<Lshapeless/Succ<Lshapeless/_0;>;>;>;>;>;>;>;>;>;>;>;>;>;>;>;>;>;>;>;>;>;
   #60 = Utf8               _22
   #61 = Utf8               Lshapeless/Succ<Lshapeless/Succ<Lshapeless/Succ<Lshapeless/Succ<Lshapeless/Succ<Lshapeless/Succ<Lshapeless/Succ<Lshapeless/Succ<Lshapeless/Succ<Lshapeless/Succ<Lshapeless/Succ<Lshapeless/Succ<Lshapeless/Succ<Lshapeless/Succ<Lshapeless/Succ<Lshapeless/Succ<Lshapeless/Succ<Lshapeless/Succ<Lshapeless/Succ<Lshapeless/Succ<Lshapeless/Succ<Lshapeless/Succ<Lshapeless/_0;>;>;>;>;>;>;>;>;>;>;>;>;>;>;>;>;>;>;>;>;>;>;
   #62 = Utf8               <clinit>
   #63 = Utf8               ()V
   #64 = Utf8               <init>
   #65 = NameAndType        #64:#63       // "<init>":()V
   #66 = Methodref          #2.#65        // shapeless/Nat$."<init>":()V
   #67 = NameAndType        #13:#14       // MODULE$:Lshapeless/Nat$;
   #68 = Fieldref           #2.#67        // shapeless/Nat$.MODULE$:Lshapeless/Nat$;
   #69 = Utf8               $init$
   #70 = Utf8               (Lshapeless/Nats;)V
   #71 = NameAndType        #69:#70       // $init$:(Lshapeless/Nats;)V
   #72 = InterfaceMethodref #6.#71        // shapeless/Nats.$init$:(Lshapeless/Nats;)V
   #73 = Utf8               shapeless/_0
   #74 = Class              #73           // shapeless/_0
   #75 = Methodref          #74.#65       // shapeless/_0."<init>":()V
   #76 = NameAndType        #15:#16       // _0:Lshapeless/_0;
   #77 = Fieldref           #2.#76        // shapeless/Nat$._0:Lshapeless/_0;
   #78 = Utf8               ()Lshapeless/Succ;
   #79 = Utf8               ()Lshapeless/Succ<Lshapeless/_0;>;
   #80 = NameAndType        #17:#18       // _1:Lshapeless/Succ;
   #81 = Fieldref           #2.#80        // shapeless/Nat$._1:Lshapeless/Succ;
   #82 = Utf8               this
   #83 = Utf8               ()Lshapeless/Succ<Lshapeless/Succ<Lshapeless/_0;>;>;
   #84 = NameAndType        #20:#18       // _2:Lshapeless/Succ;
   #85 = Fieldref           #2.#84        // shapeless/Nat$._2:Lshapeless/Succ;
   #86 = Utf8               ()Lshapeless/Succ<Lshapeless/Succ<Lshapeless/Succ<Lshapeless/_0;>;>;>;
   #87 = NameAndType        #22:#18       // _3:Lshapeless/Succ;
   #88 = Fieldref           #2.#87        // shapeless/Nat$._3:Lshapeless/Succ;
   #89 = Utf8               ()Lshapeless/Succ<Lshapeless/Succ<Lshapeless/Succ<Lshapeless/Succ<Lshapeless/_0;>;>;>;>;
   #90 = NameAndType        #24:#18       // _4:Lshapeless/Succ;
   #91 = Fieldref           #2.#90        // shapeless/Nat$._4:Lshapeless/Succ;
   #92 = Utf8               ()Lshapeless/Succ<Lshapeless/Succ<Lshapeless/Succ<Lshapeless/Succ<Lshapeless/Succ<Lshapeless/_0;>;>;>;>;>;
   #93 = NameAndType        #26:#18       // _5:Lshapeless/Succ;
   #94 = Fieldref           #2.#93        // shapeless/Nat$._5:Lshapeless/Succ;
   #95 = Utf8               ()Lshapeless/Succ<Lshapeless/Succ<Lshapeless/Succ<Lshapeless/Succ<Lshapeless/Succ<Lshapeless/Succ<Lshapeless/_0;>;>;>;>;>;>;
   #96 = NameAndType        #28:#18       // _6:Lshapeless/Succ;
   #97 = Fieldref           #2.#96        // shapeless/Nat$._6:Lshapeless/Succ;
   #98 = Utf8               ()Lshapeless/Succ<Lshapeless/Succ<Lshapeless/Succ<Lshapeless/Succ<Lshapeless/Succ<Lshapeless/Succ<Lshapeless/Succ<Lshapeless/_0;>;>;>;>;>;>;>;
   #99 = NameAndType        #30:#18       // _7:Lshapeless/Succ;
  #100 = Fieldref           #2.#99        // shapeless/Nat$._7:Lshapeless/Succ;
  #101 = Utf8               ()Lshapeless/Succ<Lshapeless/Succ<Lshapeless/Succ<Lshapeless/Succ<Lshapeless/Succ<Lshapeless/Succ<Lshapeless/Succ<Lshapeless/Succ<Lshapeless/_0;>;>;>;>;>;>;>;>;
  #102 = NameAndType        #32:#18       // _8:Lshapeless/Succ;
  #103 = Fieldref           #2.#102       // shapeless/Nat$._8:Lshapeless/Succ;
  #104 = Utf8               ()Lshapeless/Succ<Lshapeless/Succ<Lshapeless/Succ<Lshapeless/Succ<Lshapeless/Succ<Lshapeless/Succ<Lshapeless/Succ<Lshapeless/Succ<Lshapeless/Succ<Lshapeless/_0;>;>;>;>;>;>;>;>;>;
  #105 = NameAndType        #34:#18       // _9:Lshapeless/Succ;
  #106 = Fieldref           #2.#105       // shapeless/Nat$._9:Lshapeless/Succ;
  #107 = Utf8               ()Lshapeless/Succ<Lshapeless/Succ<Lshapeless/Succ<Lshapeless/Succ<Lshapeless/Succ<Lshapeless/Succ<Lshapeless/Succ<Lshapeless/Succ<Lshapeless/Succ<Lshapeless/Succ<Lshapeless/_0;>;>;>;>;>;>;>;>;>;>;
  #108 = NameAndType        #36:#18       // _10:Lshapeless/Succ;
  #109 = Fieldref           #2.#108       // shapeless/Nat$._10:Lshapeless/Succ;
  #110 = Utf8               ()Lshapeless/Succ<Lshapeless/Succ<Lshapeless/Succ<Lshapeless/Succ<Lshapeless/Succ<Lshapeless/Succ<Lshapeless/Succ<Lshapeless/Succ<Lshapeless/Succ<Lshapeless/Succ<Lshapeless/Succ<Lshapeless/_0;>;>;>;>;>;>;>;>;>;>;>;
  #111 = NameAndType        #38:#18       // _11:Lshapeless/Succ;
  #112 = Fieldref           #2.#111       // shapeless/Nat$._11:Lshapeless/Succ;
  #113 = Utf8               ()Lshapeless/Succ<Lshapeless/Succ<Lshapeless/Succ<Lshapeless/Succ<Lshapeless/Succ<Lshapeless/Succ<Lshapeless/Succ<Lshapeless/Succ<Lshapeless/Succ<Lshapeless/Succ<Lshapeless/Succ<Lshapeless/Succ<Lshapeless/_0;>;>;>;>;>;>;>;>;>;>;>;>;
  #114 = NameAndType        #40:#18       // _12:Lshapeless/Succ;
  #115 = Fieldref           #2.#114       // shapeless/Nat$._12:Lshapeless/Succ;
  #116 = Utf8               ()Lshapeless/Succ<Lshapeless/Succ<Lshapeless/Succ<Lshapeless/Succ<Lshapeless/Succ<Lshapeless/Succ<Lshapeless/Succ<Lshapeless/Succ<Lshapeless/Succ<Lshapeless/Succ<Lshapeless/Succ<Lshapeless/Succ<Lshapeless/Succ<Lshapeless/_0;>;>;>;>;>;>;>;>;>;>;>;>;>;
  #117 = NameAndType        #42:#18       // _13:Lshapeless/Succ;
  #118 = Fieldref           #2.#117       // shapeless/Nat$._13:Lshapeless/Succ;
  #119 = Utf8               ()Lshapeless/Succ<Lshapeless/Succ<Lshapeless/Succ<Lshapeless/Succ<Lshapeless/Succ<Lshapeless/Succ<Lshapeless/Succ<Lshapeless/Succ<Lshapeless/Succ<Lshapeless/Succ<Lshapeless/Succ<Lshapeless/Succ<Lshapeless/Succ<Lshapeless/Succ<Lshapeless/_0;>;>;>;>;>;>;>;>;>;>;>;>;>;>;
  #120 = NameAndType        #44:#18       // _14:Lshapeless/Succ;
  #121 = Fieldref           #2.#120       // shapeless/Nat$._14:Lshapeless/Succ;
  #122 = Utf8               ()Lshapeless/Succ<Lshapeless/Succ<Lshapeless/Succ<Lshapeless/Succ<Lshapeless/Succ<Lshapeless/Succ<Lshapeless/Succ<Lshapeless/Succ<Lshapeless/Succ<Lshapeless/Succ<Lshapeless/Succ<Lshapeless/Succ<Lshapeless/Succ<Lshapeless/Succ<Lshapeless/Succ<Lshapeless/_0;>;>;>;>;>;>;>;>;>;>;>;>;>;>;>;
  #123 = NameAndType        #46:#18       // _15:Lshapeless/Succ;
  #124 = Fieldref           #2.#123       // shapeless/Nat$._15:Lshapeless/Succ;
  #125 = Utf8               ()Lshapeless/Succ<Lshapeless/Succ<Lshapeless/Succ<Lshapeless/Succ<Lshapeless/Succ<Lshapeless/Succ<Lshapeless/Succ<Lshapeless/Succ<Lshapeless/Succ<Lshapeless/Succ<Lshapeless/Succ<Lshapeless/Succ<Lshapeless/Succ<Lshapeless/Succ<Lshapeless/Succ<Lshapeless/Succ<Lshapeless/_0;>;>;>;>;>;>;>;>;>;>;>;>;>;>;>;>;
  #126 = NameAndType        #48:#18       // _16:Lshapeless/Succ;
  #127 = Fieldref           #2.#126       // shapeless/Nat$._16:Lshapeless/Succ;
  #128 = Utf8               ()Lshapeless/Succ<Lshapeless/Succ<Lshapeless/Succ<Lshapeless/Succ<Lshapeless/Succ<Lshapeless/Succ<Lshapeless/Succ<Lshapeless/Succ<Lshapeless/Succ<Lshapeless/Succ<Lshapeless/Succ<Lshapeless/Succ<Lshapeless/Succ<Lshapeless/Succ<Lshapeless/Succ<Lshapeless/Succ<Lshapeless/Succ<Lshapeless/_0;>;>;>;>;>;>;>;>;>;>;>;>;>;>;>;>;>;
  #129 = NameAndType        #50:#18       // _17:Lshapeless/Succ;
  #130 = Fieldref           #2.#129       // shapeless/Nat$._17:Lshapeless/Succ;
  #131 = Utf8               ()Lshapeless/Succ<Lshapeless/Succ<Lshapeless/Succ<Lshapeless/Succ<Lshapeless/Succ<Lshapeless/Succ<Lshapeless/Succ<Lshapeless/Succ<Lshapeless/Succ<Lshapeless/Succ<Lshapeless/Succ<Lshapeless/Succ<Lshapeless/Succ<Lshapeless/Succ<Lshapeless/Succ<Lshapeless/Succ<Lshapeless/Succ<Lshapeless/Succ<Lshapeless/_0;>;>;>;>;>;>;>;>;>;>;>;>;>;>;>;>;>;>;
  #132 = NameAndType        #52:#18       // _18:Lshapeless/Succ;
  #133 = Fieldref           #2.#132       // shapeless/Nat$._18:Lshapeless/Succ;
  #134 = Utf8               ()Lshapeless/Succ<Lshapeless/Succ<Lshapeless/Succ<Lshapeless/Succ<Lshapeless/Succ<Lshapeless/Succ<Lshapeless/Succ<Lshapeless/Succ<Lshapeless/Succ<Lshapeless/Succ<Lshapeless/Succ<Lshapeless/Succ<Lshapeless/Succ<Lshapeless/Succ<Lshapeless/Succ<Lshapeless/Succ<Lshapeless/Succ<Lshapeless/Succ<Lshapeless/Succ<Lshapeless/_0;>;>;>;>;>;>;>;>;>;>;>;>;>;>;>;>;>;>;>;
  #135 = NameAndType        #54:#18       // _19:Lshapeless/Succ;
  #136 = Fieldref           #2.#135       // shapeless/Nat$._19:Lshapeless/Succ;
  #137 = Utf8               ()Lshapeless/Succ<Lshapeless/Succ<Lshapeless/Succ<Lshapeless/Succ<Lshapeless/Succ<Lshapeless/Succ<Lshapeless/Succ<Lshapeless/Succ<Lshapeless/Succ<Lshapeless/Succ<Lshapeless/Succ<Lshapeless/Succ<Lshapeless/Succ<Lshapeless/Succ<Lshapeless/Succ<Lshapeless/Succ<Lshapeless/Succ<Lshapeless/Succ<Lshapeless/Succ<Lshapeless/Succ<Lshapeless/_0;>;>;>;>;>;>;>;>;>;>;>;>;>;>;>;>;>;>;>;>;
  #138 = NameAndType        #56:#18       // _20:Lshapeless/Succ;
  #139 = Fieldref           #2.#138       // shapeless/Nat$._20:Lshapeless/Succ;
  #140 = Utf8               ()Lshapeless/Succ<Lshapeless/Succ<Lshapeless/Succ<Lshapeless/Succ<Lshapeless/Succ<Lshapeless/Succ<Lshapeless/Succ<Lshapeless/Succ<Lshapeless/Succ<Lshapeless/Succ<Lshapeless/Succ<Lshapeless/Succ<Lshapeless/Succ<Lshapeless/Succ<Lshapeless/Succ<Lshapeless/Succ<Lshapeless/Succ<Lshapeless/Succ<Lshapeless/Succ<Lshapeless/Succ<Lshapeless/Succ<Lshapeless/_0;>;>;>;>;>;>;>;>;>;>;>;>;>;>;>;>;>;>;>;>;>;
  #141 = NameAndType        #58:#18       // _21:Lshapeless/Succ;
  #142 = Fieldref           #2.#141       // shapeless/Nat$._21:Lshapeless/Succ;
  #143 = Utf8               ()Lshapeless/Succ<Lshapeless/Succ<Lshapeless/Succ<Lshapeless/Succ<Lshapeless/Succ<Lshapeless/Succ<Lshapeless/Succ<Lshapeless/Succ<Lshapeless/Succ<Lshapeless/Succ<Lshapeless/Succ<Lshapeless/Succ<Lshapeless/Succ<Lshapeless/Succ<Lshapeless/Succ<Lshapeless/Succ<Lshapeless/Succ<Lshapeless/Succ<Lshapeless/Succ<Lshapeless/Succ<Lshapeless/Succ<Lshapeless/Succ<Lshapeless/_0;>;>;>;>;>;>;>;>;>;>;>;>;>;>;>;>;>;>;>;>;>;>;
  #144 = NameAndType        #60:#18       // _22:Lshapeless/Succ;
  #145 = Fieldref           #2.#144       // shapeless/Nat$._22:Lshapeless/Succ;
  #146 = Utf8               shapeless$Nats$_setter_$_1_$eq
  #147 = Utf8               (Lshapeless/Succ;)V
  #148 = Utf8               (Lshapeless/Succ<Lshapeless/_0;>;)V
  #149 = Utf8               x$1
  #150 = Utf8               shapeless$Nats$_setter_$_2_$eq
  #151 = Utf8               (Lshapeless/Succ<Lshapeless/Succ<Lshapeless/_0;>;>;)V
  #152 = Utf8               shapeless$Nats$_setter_$_3_$eq
  #153 = Utf8               (Lshapeless/Succ<Lshapeless/Succ<Lshapeless/Succ<Lshapeless/_0;>;>;>;)V
  #154 = Utf8               shapeless$Nats$_setter_$_4_$eq
  #155 = Utf8               (Lshapeless/Succ<Lshapeless/Succ<Lshapeless/Succ<Lshapeless/Succ<Lshapeless/_0;>;>;>;>;)V
  #156 = Utf8               shapeless$Nats$_setter_$_5_$eq
  #157 = Utf8               (Lshapeless/Succ<Lshapeless/Succ<Lshapeless/Succ<Lshapeless/Succ<Lshapeless/Succ<Lshapeless/_0;>;>;>;>;>;)V
  #158 = Utf8               shapeless$Nats$_setter_$_6_$eq
  #159 = Utf8               (Lshapeless/Succ<Lshapeless/Succ<Lshapeless/Succ<Lshapeless/Succ<Lshapeless/Succ<Lshapeless/Succ<Lshapeless/_0;>;>;>;>;>;>;)V
  #160 = Utf8               shapeless$Nats$_setter_$_7_$eq
  #161 = Utf8               (Lshapeless/Succ<Lshapeless/Succ<Lshapeless/Succ<Lshapeless/Succ<Lshapeless/Succ<Lshapeless/Succ<Lshapeless/Succ<Lshapeless/_0;>;>;>;>;>;>;>;)V
  #162 = Utf8               shapeless$Nats$_setter_$_8_$eq
  #163 = Utf8               (Lshapeless/Succ<Lshapeless/Succ<Lshapeless/Succ<Lshapeless/Succ<Lshapeless/Succ<Lshapeless/Succ<Lshapeless/Succ<Lshapeless/Succ<Lshapeless/_0;>;>;>;>;>;>;>;>;)V
  #164 = Utf8               shapeless$Nats$_setter_$_9_$eq
  #165 = Utf8               (Lshapeless/Succ<Lshapeless/Succ<Lshapeless/Succ<Lshapeless/Succ<Lshapeless/Succ<Lshapeless/Succ<Lshapeless/Succ<Lshapeless/Succ<Lshapeless/Succ<Lshapeless/_0;>;>;>;>;>;>;>;>;>;)V
  #166 = Utf8               shapeless$Nats$_setter_$_10_$eq
  #167 = Utf8               (Lshapeless/Succ<Lshapeless/Succ<Lshapeless/Succ<Lshapeless/Succ<Lshapeless/Succ<Lshapeless/Succ<Lshapeless/Succ<Lshapeless/Succ<Lshapeless/Succ<Lshapeless/Succ<Lshapeless/_0;>;>;>;>;>;>;>;>;>;>;)V
  #168 = Utf8               shapeless$Nats$_setter_$_11_$eq
  #169 = Utf8               (Lshapeless/Succ<Lshapeless/Succ<Lshapeless/Succ<Lshapeless/Succ<Lshapeless/Succ<Lshapeless/Succ<Lshapeless/Succ<Lshapeless/Succ<Lshapeless/Succ<Lshapeless/Succ<Lshapeless/Succ<Lshapeless/_0;>;>;>;>;>;>;>;>;>;>;>;)V
  #170 = Utf8               shapeless$Nats$_setter_$_12_$eq
  #171 = Utf8               (Lshapeless/Succ<Lshapeless/Succ<Lshapeless/Succ<Lshapeless/Succ<Lshapeless/Succ<Lshapeless/Succ<Lshapeless/Succ<Lshapeless/Succ<Lshapeless/Succ<Lshapeless/Succ<Lshapeless/Succ<Lshapeless/Succ<Lshapeless/_0;>;>;>;>;>;>;>;>;>;>;>;>;)V
  #172 = Utf8               shapeless$Nats$_setter_$_13_$eq
  #173 = Utf8               (Lshapeless/Succ<Lshapeless/Succ<Lshapeless/Succ<Lshapeless/Succ<Lshapeless/Succ<Lshapeless/Succ<Lshapeless/Succ<Lshapeless/Succ<Lshapeless/Succ<Lshapeless/Succ<Lshapeless/Succ<Lshapeless/Succ<Lshapeless/Succ<Lshapeless/_0;>;>;>;>;>;>;>;>;>;>;>;>;>;)V
  #174 = Utf8               shapeless$Nats$_setter_$_14_$eq
  #175 = Utf8               (Lshapeless/Succ<Lshapeless/Succ<Lshapeless/Succ<Lshapeless/Succ<Lshapeless/Succ<Lshapeless/Succ<Lshapeless/Succ<Lshapeless/Succ<Lshapeless/Succ<Lshapeless/Succ<Lshapeless/Succ<Lshapeless/Succ<Lshapeless/Succ<Lshapeless/Succ<Lshapeless/_0;>;>;>;>;>;>;>;>;>;>;>;>;>;>;)V
  #176 = Utf8               shapeless$Nats$_setter_$_15_$eq
  #177 = Utf8               (Lshapeless/Succ<Lshapeless/Succ<Lshapeless/Succ<Lshapeless/Succ<Lshapeless/Succ<Lshapeless/Succ<Lshapeless/Succ<Lshapeless/Succ<Lshapeless/Succ<Lshapeless/Succ<Lshapeless/Succ<Lshapeless/Succ<Lshapeless/Succ<Lshapeless/Succ<Lshapeless/Succ<Lshapeless/_0;>;>;>;>;>;>;>;>;>;>;>;>;>;>;>;)V
  #178 = Utf8               shapeless$Nats$_setter_$_16_$eq
  #179 = Utf8               (Lshapeless/Succ<Lshapeless/Succ<Lshapeless/Succ<Lshapeless/Succ<Lshapeless/Succ<Lshapeless/Succ<Lshapeless/Succ<Lshapeless/Succ<Lshapeless/Succ<Lshapeless/Succ<Lshapeless/Succ<Lshapeless/Succ<Lshapeless/Succ<Lshapeless/Succ<Lshapeless/Succ<Lshapeless/Succ<Lshapeless/_0;>;>;>;>;>;>;>;>;>;>;>;>;>;>;>;>;)V
  #180 = Utf8               shapeless$Nats$_setter_$_17_$eq
  #181 = Utf8               (Lshapeless/Succ<Lshapeless/Succ<Lshapeless/Succ<Lshapeless/Succ<Lshapeless/Succ<Lshapeless/Succ<Lshapeless/Succ<Lshapeless/Succ<Lshapeless/Succ<Lshapeless/Succ<Lshapeless/Succ<Lshapeless/Succ<Lshapeless/Succ<Lshapeless/Succ<Lshapeless/Succ<Lshapeless/Succ<Lshapeless/Succ<Lshapeless/_0;>;>;>;>;>;>;>;>;>;>;>;>;>;>;>;>;>;)V
  #182 = Utf8               shapeless$Nats$_setter_$_18_$eq
  #183 = Utf8               (Lshapeless/Succ<Lshapeless/Succ<Lshapeless/Succ<Lshapeless/Succ<Lshapeless/Succ<Lshapeless/Succ<Lshapeless/Succ<Lshapeless/Succ<Lshapeless/Succ<Lshapeless/Succ<Lshapeless/Succ<Lshapeless/Succ<Lshapeless/Succ<Lshapeless/Succ<Lshapeless/Succ<Lshapeless/Succ<Lshapeless/Succ<Lshapeless/Succ<Lshapeless/_0;>;>;>;>;>;>;>;>;>;>;>;>;>;>;>;>;>;>;)V
  #184 = Utf8               shapeless$Nats$_setter_$_19_$eq
  #185 = Utf8               (Lshapeless/Succ<Lshapeless/Succ<Lshapeless/Succ<Lshapeless/Succ<Lshapeless/Succ<Lshapeless/Succ<Lshapeless/Succ<Lshapeless/Succ<Lshapeless/Succ<Lshapeless/Succ<Lshapeless/Succ<Lshapeless/Succ<Lshapeless/Succ<Lshapeless/Succ<Lshapeless/Succ<Lshapeless/Succ<Lshapeless/Succ<Lshapeless/Succ<Lshapeless/Succ<Lshapeless/_0;>;>;>;>;>;>;>;>;>;>;>;>;>;>;>;>;>;>;>;)V
  #186 = Utf8               shapeless$Nats$_setter_$_20_$eq
  #187 = Utf8               (Lshapeless/Succ<Lshapeless/Succ<Lshapeless/Succ<Lshapeless/Succ<Lshapeless/Succ<Lshapeless/Succ<Lshapeless/Succ<Lshapeless/Succ<Lshapeless/Succ<Lshapeless/Succ<Lshapeless/Succ<Lshapeless/Succ<Lshapeless/Succ<Lshapeless/Succ<Lshapeless/Succ<Lshapeless/Succ<Lshapeless/Succ<Lshapeless/Succ<Lshapeless/Succ<Lshapeless/Succ<Lshapeless/_0;>;>;>;>;>;>;>;>;>;>;>;>;>;>;>;>;>;>;>;>;)V
  #188 = Utf8               shapeless$Nats$_setter_$_21_$eq
  #189 = Utf8               (Lshapeless/Succ<Lshapeless/Succ<Lshapeless/Succ<Lshapeless/Succ<Lshapeless/Succ<Lshapeless/Succ<Lshapeless/Succ<Lshapeless/Succ<Lshapeless/Succ<Lshapeless/Succ<Lshapeless/Succ<Lshapeless/Succ<Lshapeless/Succ<Lshapeless/Succ<Lshapeless/Succ<Lshapeless/Succ<Lshapeless/Succ<Lshapeless/Succ<Lshapeless/Succ<Lshapeless/Succ<Lshapeless/Succ<Lshapeless/_0;>;>;>;>;>;>;>;>;>;>;>;>;>;>;>;>;>;>;>;>;>;)V
  #190 = Utf8               shapeless$Nats$_setter_$_22_$eq
  #191 = Utf8               (Lshapeless/Succ<Lshapeless/Succ<Lshapeless/Succ<Lshapeless/Succ<Lshapeless/Succ<Lshapeless/Succ<Lshapeless/Succ<Lshapeless/Succ<Lshapeless/Succ<Lshapeless/Succ<Lshapeless/Succ<Lshapeless/Succ<Lshapeless/Succ<Lshapeless/Succ<Lshapeless/Succ<Lshapeless/Succ<Lshapeless/Succ<Lshapeless/Succ<Lshapeless/Succ<Lshapeless/Succ<Lshapeless/Succ<Lshapeless/Succ<Lshapeless/_0;>;>;>;>;>;>;>;>;>;>;>;>;>;>;>;>;>;>;>;>;>;>;)V
  #192 = Utf8               ()Lshapeless/_0;
  #193 = Utf8               toInt
  #194 = Utf8               (Lshapeless/ops/nat$ToInt;)I
  #195 = Utf8               <N::Lshapeless/Nat;>(Lshapeless/ops/nat$ToInt<TN;>;)I
  #196 = Utf8               toIntN
  #197 = Utf8               apply
  #198 = Utf8               ()I
  #199 = NameAndType        #197:#198     // apply:()I
  #200 = InterfaceMethodref #9.#199       // shapeless/ops/nat$ToInt.apply:()I
  #201 = Utf8               Lshapeless/ops/nat$ToInt;
  #202 = Utf8               (Lshapeless/Nat;Lshapeless/ops/nat$ToInt;)I
  #203 = Utf8               (Lshapeless/Nat;Lshapeless/ops/nat$ToInt<Lshapeless/Nat;>;)I
  #204 = Utf8               n
  #205 = Utf8               Lshapeless/Nat;
  #206 = Utf8               natOps
  #207 = Utf8               (Lshapeless/Nat;)Lshapeless/Nat;
  #208 = Utf8               <N::Lshapeless/Nat;>(TN;)TN;
  #209 = Methodref          #4.#65        // java/lang/Object."<init>":()V
  #210 = Utf8               Signature
  #211 = Utf8               Code
  #212 = Utf8               LineNumberTable
  #213 = Utf8               LocalVariableTable
  #214 = Utf8               MethodParameters
  #215 = Utf8               InnerClasses
  #216 = Utf8               SourceFile
  #217 = Utf8               ScalaInlineInfo
  #218 = Utf8               (I)Lshapeless/Nat;
  #219 = Utf8               Scala
{
  public static final shapeless.Nat$ MODULE$;
    descriptor: Lshapeless/Nat$;
    flags: (0x0019) ACC_PUBLIC, ACC_STATIC, ACC_FINAL

  private static final shapeless._0 _0;
    descriptor: Lshapeless/_0;
    flags: (0x001a) ACC_PRIVATE, ACC_STATIC, ACC_FINAL

  private static shapeless.Succ<shapeless._0> _1;
    descriptor: Lshapeless/Succ;
    flags: (0x000a) ACC_PRIVATE, ACC_STATIC
    Signature: #19                          // Lshapeless/Succ<Lshapeless/_0;>;

  private static shapeless.Succ<shapeless.Succ<shapeless._0>> _2;
    descriptor: Lshapeless/Succ;
    flags: (0x000a) ACC_PRIVATE, ACC_STATIC
    Signature: #21                          // Lshapeless/Succ<Lshapeless/Succ<Lshapeless/_0;>;>;

  private static shapeless.Succ<shapeless.Succ<shapeless.Succ<shapeless._0>>> _3;
    descriptor: Lshapeless/Succ;
    flags: (0x000a) ACC_PRIVATE, ACC_STATIC
    Signature: #23                          // Lshapeless/Succ<Lshapeless/Succ<Lshapeless/Succ<Lshapeless/_0;>;>;>;

  private static shapeless.Succ<shapeless.Succ<shapeless.Succ<shapeless.Succ<shapeless._0>>>> _4;
    descriptor: Lshapeless/Succ;
    flags: (0x000a) ACC_PRIVATE, ACC_STATIC
    Signature: #25                          // Lshapeless/Succ<Lshapeless/Succ<Lshapeless/Succ<Lshapeless/Succ<Lshapeless/_0;>;>;>;>;

  private static shapeless.Succ<shapeless.Succ<shapeless.Succ<shapeless.Succ<shapeless.Succ<shapeless._0>>>>> _5;
    descriptor: Lshapeless/Succ;
    flags: (0x000a) ACC_PRIVATE, ACC_STATIC
    Signature: #27                          // Lshapeless/Succ<Lshapeless/Succ<Lshapeless/Succ<Lshapeless/Succ<Lshapeless/Succ<Lshapeless/_0;>;>;>;>;>;

  private static shapeless.Succ<shapeless.Succ<shapeless.Succ<shapeless.Succ<shapeless.Succ<shapeless.Succ<shapeless._0>>>>>> _6;
    descriptor: Lshapeless/Succ;
    flags: (0x000a) ACC_PRIVATE, ACC_STATIC
    Signature: #29                          // Lshapeless/Succ<Lshapeless/Succ<Lshapeless/Succ<Lshapeless/Succ<Lshapeless/Succ<Lshapeless/Succ<Lshapeless/_0;>;>;>;>;>;>;

  private static shapeless.Succ<shapeless.Succ<shapeless.Succ<shapeless.Succ<shapeless.Succ<shapeless.Succ<shapeless.Succ<shapeless._0>>>>>>> _7;
    descriptor: Lshapeless/Succ;
    flags: (0x000a) ACC_PRIVATE, ACC_STATIC
    Signature: #31                          // Lshapeless/Succ<Lshapeless/Succ<Lshapeless/Succ<Lshapeless/Succ<Lshapeless/Succ<Lshapeless/Succ<Lshapeless/Succ<Lshapeless/_0;>;>;>;>;>;>;>;

  private static shapeless.Succ<shapeless.Succ<shapeless.Succ<shapeless.Succ<shapeless.Succ<shapeless.Succ<shapeless.Succ<shapeless.Succ<shapeless._0>>>>>>>> _8;
    descriptor: Lshapeless/Succ;
    flags: (0x000a) ACC_PRIVATE, ACC_STATIC
    Signature: #33                          // Lshapeless/Succ<Lshapeless/Succ<Lshapeless/Succ<Lshapeless/Succ<Lshapeless/Succ<Lshapeless/Succ<Lshapeless/Succ<Lshapeless/Succ<Lshapeless/_0;>;>;>;>;>;>;>;>;

  private static shapeless.Succ<shapeless.Succ<shapeless.Succ<shapeless.Succ<shapeless.Succ<shapeless.Succ<shapeless.Succ<shapeless.Succ<shapeless.Succ<shapeless._0>>>>>>>>> _9;
    descriptor: Lshapeless/Succ;
    flags: (0x000a) ACC_PRIVATE, ACC_STATIC
    Signature: #35                          // Lshapeless/Succ<Lshapeless/Succ<Lshapeless/Succ<Lshapeless/Succ<Lshapeless/Succ<Lshapeless/Succ<Lshapeless/Succ<Lshapeless/Succ<Lshapeless/Succ<Lshapeless/_0;>;>;>;>;>;>;>;>;>;

  private static shapeless.Succ<shapeless.Succ<shapeless.Succ<shapeless.Succ<shapeless.Succ<shapeless.Succ<shapeless.Succ<shapeless.Succ<shapeless.Succ<shapeless.Succ<shapeless._0>>>>>>>>>> _10;
    descriptor: Lshapeless/Succ;
    flags: (0x000a) ACC_PRIVATE, ACC_STATIC
    Signature: #37                          // Lshapeless/Succ<Lshapeless/Succ<Lshapeless/Succ<Lshapeless/Succ<Lshapeless/Succ<Lshapeless/Succ<Lshapeless/Succ<Lshapeless/Succ<Lshapeless/Succ<Lshapeless/Succ<Lshapeless/_0;>;>;>;>;>;>;>;>;>;>;

  private static shapeless.Succ<shapeless.Succ<shapeless.Succ<shapeless.Succ<shapeless.Succ<shapeless.Succ<shapeless.Succ<shapeless.Succ<shapeless.Succ<shapeless.Succ<shapeless.Succ<shapeless._0>>>>>>>>>>> _11;
    descriptor: Lshapeless/Succ;
    flags: (0x000a) ACC_PRIVATE, ACC_STATIC
    Signature: #39                          // Lshapeless/Succ<Lshapeless/Succ<Lshapeless/Succ<Lshapeless/Succ<Lshapeless/Succ<Lshapeless/Succ<Lshapeless/Succ<Lshapeless/Succ<Lshapeless/Succ<Lshapeless/Succ<Lshapeless/Succ<Lshapeless/_0;>;>;>;>;>;>;>;>;>;>;>;

  private static shapeless.Succ<shapeless.Succ<shapeless.Succ<shapeless.Succ<shapeless.Succ<shapeless.Succ<shapeless.Succ<shapeless.Succ<shapeless.Succ<shapeless.Succ<shapeless.Succ<shapeless.Succ<shapeless._0>>>>>>>>>>>> _12;
    descriptor: Lshapeless/Succ;
    flags: (0x000a) ACC_PRIVATE, ACC_STATIC
    Signature: #41                          // Lshapeless/Succ<Lshapeless/Succ<Lshapeless/Succ<Lshapeless/Succ<Lshapeless/Succ<Lshapeless/Succ<Lshapeless/Succ<Lshapeless/Succ<Lshapeless/Succ<Lshapeless/Succ<Lshapeless/Succ<Lshapeless/Succ<Lshapeless/_0;>;>;>;>;>;>;>;>;>;>;>;>;

  private static shapeless.Succ<shapeless.Succ<shapeless.Succ<shapeless.Succ<shapeless.Succ<shapeless.Succ<shapeless.Succ<shapeless.Succ<shapeless.Succ<shapeless.Succ<shapeless.Succ<shapeless.Succ<shapeless.Succ<shapeless._0>>>>>>>>>>>>> _13;
    descriptor: Lshapeless/Succ;
    flags: (0x000a) ACC_PRIVATE, ACC_STATIC
    Signature: #43                          // Lshapeless/Succ<Lshapeless/Succ<Lshapeless/Succ<Lshapeless/Succ<Lshapeless/Succ<Lshapeless/Succ<Lshapeless/Succ<Lshapeless/Succ<Lshapeless/Succ<Lshapeless/Succ<Lshapeless/Succ<Lshapeless/Succ<Lshapeless/Succ<Lshapeless/_0;>;>;>;>;>;>;>;>;>;>;>;>;>;

  private static shapeless.Succ<shapeless.Succ<shapeless.Succ<shapeless.Succ<shapeless.Succ<shapeless.Succ<shapeless.Succ<shapeless.Succ<shapeless.Succ<shapeless.Succ<shapeless.Succ<shapeless.Succ<shapeless.Succ<shapeless.Succ<shapeless._0>>>>>>>>>>>>>> _14;
    descriptor: Lshapeless/Succ;
    flags: (0x000a) ACC_PRIVATE, ACC_STATIC
    Signature: #45                          // Lshapeless/Succ<Lshapeless/Succ<Lshapeless/Succ<Lshapeless/Succ<Lshapeless/Succ<Lshapeless/Succ<Lshapeless/Succ<Lshapeless/Succ<Lshapeless/Succ<Lshapeless/Succ<Lshapeless/Succ<Lshapeless/Succ<Lshapeless/Succ<Lshapeless/Succ<Lshapeless/_0;>;>;>;>;>;>;>;>;>;>;>;>;>;>;

  private static shapeless.Succ<shapeless.Succ<shapeless.Succ<shapeless.Succ<shapeless.Succ<shapeless.Succ<shapeless.Succ<shapeless.Succ<shapeless.Succ<shapeless.Succ<shapeless.Succ<shapeless.Succ<shapeless.Succ<shapeless.Succ<shapeless.Succ<shapeless._0>>>>>>>>>>>>>>> _15;
    descriptor: Lshapeless/Succ;
    flags: (0x000a) ACC_PRIVATE, ACC_STATIC
    Signature: #47                          // Lshapeless/Succ<Lshapeless/Succ<Lshapeless/Succ<Lshapeless/Succ<Lshapeless/Succ<Lshapeless/Succ<Lshapeless/Succ<Lshapeless/Succ<Lshapeless/Succ<Lshapeless/Succ<Lshapeless/Succ<Lshapeless/Succ<Lshapeless/Succ<Lshapeless/Succ<Lshapeless/Succ<Lshapeless/_0;>;>;>;>;>;>;>;>;>;>;>;>;>;>;>;

  private static shapeless.Succ<shapeless.Succ<shapeless.Succ<shapeless.Succ<shapeless.Succ<shapeless.Succ<shapeless.Succ<shapeless.Succ<shapeless.Succ<shapeless.Succ<shapeless.Succ<shapeless.Succ<shapeless.Succ<shapeless.Succ<shapeless.Succ<shapeless.Succ<shapeless._0>>>>>>>>>>>>>>>> _16;
    descriptor: Lshapeless/Succ;
    flags: (0x000a) ACC_PRIVATE, ACC_STATIC
    Signature: #49                          // Lshapeless/Succ<Lshapeless/Succ<Lshapeless/Succ<Lshapeless/Succ<Lshapeless/Succ<Lshapeless/Succ<Lshapeless/Succ<Lshapeless/Succ<Lshapeless/Succ<Lshapeless/Succ<Lshapeless/Succ<Lshapeless/Succ<Lshapeless/Succ<Lshapeless/Succ<Lshapeless/Succ<Lshapeless/Succ<Lshapeless/_0;>;>;>;>;>;>;>;>;>;>;>;>;>;>;>;>;

  private static shapeless.Succ<shapeless.Succ<shapeless.Succ<shapeless.Succ<shapeless.Succ<shapeless.Succ<shapeless.Succ<shapeless.Succ<shapeless.Succ<shapeless.Succ<shapeless.Succ<shapeless.Succ<shapeless.Succ<shapeless.Succ<shapeless.Succ<shapeless.Succ<shapeless.Succ<shapeless._0>>>>>>>>>>>>>>>>> _17;
    descriptor: Lshapeless/Succ;
    flags: (0x000a) ACC_PRIVATE, ACC_STATIC
    Signature: #51                          // Lshapeless/Succ<Lshapeless/Succ<Lshapeless/Succ<Lshapeless/Succ<Lshapeless/Succ<Lshapeless/Succ<Lshapeless/Succ<Lshapeless/Succ<Lshapeless/Succ<Lshapeless/Succ<Lshapeless/Succ<Lshapeless/Succ<Lshapeless/Succ<Lshapeless/Succ<Lshapeless/Succ<Lshapeless/Succ<Lshapeless/Succ<Lshapeless/_0;>;>;>;>;>;>;>;>;>;>;>;>;>;>;>;>;>;

  private static shapeless.Succ<shapeless.Succ<shapeless.Succ<shapeless.Succ<shapeless.Succ<shapeless.Succ<shapeless.Succ<shapeless.Succ<shapeless.Succ<shapeless.Succ<shapeless.Succ<shapeless.Succ<shapeless.Succ<shapeless.Succ<shapeless.Succ<shapeless.Succ<shapeless.Succ<shapeless.Succ<shapeless._0>>>>>>>>>>>>>>>>>> _18;
    descriptor: Lshapeless/Succ;
    flags: (0x000a) ACC_PRIVATE, ACC_STATIC
    Signature: #53                          // Lshapeless/Succ<Lshapeless/Succ<Lshapeless/Succ<Lshapeless/Succ<Lshapeless/Succ<Lshapeless/Succ<Lshapeless/Succ<Lshapeless/Succ<Lshapeless/Succ<Lshapeless/Succ<Lshapeless/Succ<Lshapeless/Succ<Lshapeless/Succ<Lshapeless/Succ<Lshapeless/Succ<Lshapeless/Succ<Lshapeless/Succ<Lshapeless/Succ<Lshapeless/_0;>;>;>;>;>;>;>;>;>;>;>;>;>;>;>;>;>;>;

  private static shapeless.Succ<shapeless.Succ<shapeless.Succ<shapeless.Succ<shapeless.Succ<shapeless.Succ<shapeless.Succ<shapeless.Succ<shapeless.Succ<shapeless.Succ<shapeless.Succ<shapeless.Succ<shapeless.Succ<shapeless.Succ<shapeless.Succ<shapeless.Succ<shapeless.Succ<shapeless.Succ<shapeless.Succ<shapeless._0>>>>>>>>>>>>>>>>>>> _19;
    descriptor: Lshapeless/Succ;
    flags: (0x000a) ACC_PRIVATE, ACC_STATIC
    Signature: #55                          // Lshapeless/Succ<Lshapeless/Succ<Lshapeless/Succ<Lshapeless/Succ<Lshapeless/Succ<Lshapeless/Succ<Lshapeless/Succ<Lshapeless/Succ<Lshapeless/Succ<Lshapeless/Succ<Lshapeless/Succ<Lshapeless/Succ<Lshapeless/Succ<Lshapeless/Succ<Lshapeless/Succ<Lshapeless/Succ<Lshapeless/Succ<Lshapeless/Succ<Lshapeless/Succ<Lshapeless/_0;>;>;>;>;>;>;>;>;>;>;>;>;>;>;>;>;>;>;>;

  private static shapeless.Succ<shapeless.Succ<shapeless.Succ<shapeless.Succ<shapeless.Succ<shapeless.Succ<shapeless.Succ<shapeless.Succ<shapeless.Succ<shapeless.Succ<shapeless.Succ<shapeless.Succ<shapeless.Succ<shapeless.Succ<shapeless.Succ<shapeless.Succ<shapeless.Succ<shapeless.Succ<shapeless.Succ<shapeless.Succ<shapeless._0>>>>>>>>>>>>>>>>>>>> _20;
    descriptor: Lshapeless/Succ;
    flags: (0x000a) ACC_PRIVATE, ACC_STATIC
    Signature: #57                          // Lshapeless/Succ<Lshapeless/Succ<Lshapeless/Succ<Lshapeless/Succ<Lshapeless/Succ<Lshapeless/Succ<Lshapeless/Succ<Lshapeless/Succ<Lshapeless/Succ<Lshapeless/Succ<Lshapeless/Succ<Lshapeless/Succ<Lshapeless/Succ<Lshapeless/Succ<Lshapeless/Succ<Lshapeless/Succ<Lshapeless/Succ<Lshapeless/Succ<Lshapeless/Succ<Lshapeless/Succ<Lshapeless/_0;>;>;>;>;>;>;>;>;>;>;>;>;>;>;>;>;>;>;>;>;

  private static shapeless.Succ<shapeless.Succ<shapeless.Succ<shapeless.Succ<shapeless.Succ<shapeless.Succ<shapeless.Succ<shapeless.Succ<shapeless.Succ<shapeless.Succ<shapeless.Succ<shapeless.Succ<shapeless.Succ<shapeless.Succ<shapeless.Succ<shapeless.Succ<shapeless.Succ<shapeless.Succ<shapeless.Succ<shapeless.Succ<shapeless.Succ<shapeless._0>>>>>>>>>>>>>>>>>>>>> _21;
    descriptor: Lshapeless/Succ;
    flags: (0x000a) ACC_PRIVATE, ACC_STATIC
    Signature: #59                          // Lshapeless/Succ<Lshapeless/Succ<Lshapeless/Succ<Lshapeless/Succ<Lshapeless/Succ<Lshapeless/Succ<Lshapeless/Succ<Lshapeless/Succ<Lshapeless/Succ<Lshapeless/Succ<Lshapeless/Succ<Lshapeless/Succ<Lshapeless/Succ<Lshapeless/Succ<Lshapeless/Succ<Lshapeless/Succ<Lshapeless/Succ<Lshapeless/Succ<Lshapeless/Succ<Lshapeless/Succ<Lshapeless/Succ<Lshapeless/_0;>;>;>;>;>;>;>;>;>;>;>;>;>;>;>;>;>;>;>;>;>;

  private static shapeless.Succ<shapeless.Succ<shapeless.Succ<shapeless.Succ<shapeless.Succ<shapeless.Succ<shapeless.Succ<shapeless.Succ<shapeless.Succ<shapeless.Succ<shapeless.Succ<shapeless.Succ<shapeless.Succ<shapeless.Succ<shapeless.Succ<shapeless.Succ<shapeless.Succ<shapeless.Succ<shapeless.Succ<shapeless.Succ<shapeless.Succ<shapeless.Succ<shapeless._0>>>>>>>>>>>>>>>>>>>>>> _22;
    descriptor: Lshapeless/Succ;
    flags: (0x000a) ACC_PRIVATE, ACC_STATIC
    Signature: #61                          // Lshapeless/Succ<Lshapeless/Succ<Lshapeless/Succ<Lshapeless/Succ<Lshapeless/Succ<Lshapeless/Succ<Lshapeless/Succ<Lshapeless/Succ<Lshapeless/Succ<Lshapeless/Succ<Lshapeless/Succ<Lshapeless/Succ<Lshapeless/Succ<Lshapeless/Succ<Lshapeless/Succ<Lshapeless/Succ<Lshapeless/Succ<Lshapeless/Succ<Lshapeless/Succ<Lshapeless/Succ<Lshapeless/Succ<Lshapeless/Succ<Lshapeless/_0;>;>;>;>;>;>;>;>;>;>;>;>;>;>;>;>;>;>;>;>;>;>;

  public static {};
    descriptor: ()V
    flags: (0x0009) ACC_PUBLIC, ACC_STATIC
    Code:
      stack=2, locals=0, args_size=0
         0: new           #2                  // class shapeless/Nat$
         3: dup
         4: invokespecial #66                 // Method "<init>":()V
         7: putstatic     #68                 // Field MODULE$:Lshapeless/Nat$;
        10: getstatic     #68                 // Field MODULE$:Lshapeless/Nat$;
        13: invokestatic  #72                 // InterfaceMethod shapeless/Nats.$init$:(Lshapeless/Nats;)V
        16: new           #74                 // class shapeless/_0
        19: dup
        20: invokespecial #75                 // Method shapeless/_0."<init>":()V
        23: putstatic     #77                 // Field _0:Lshapeless/_0;
        26: return
      LineNumberTable:
        line 56: 0
        line 64: 16
        line 56: 26

  public shapeless.Succ<shapeless._0> _1();
    descriptor: ()Lshapeless/Succ;
    flags: (0x0001) ACC_PUBLIC
    Code:
      stack=1, locals=1, args_size=1
         0: getstatic     #81                 // Field _1:Lshapeless/Succ;
         3: areturn
      LineNumberTable:
        line 56: 0
      LocalVariableTable:
        Start  Length  Slot  Name   Signature
            0       4     0  this   Lshapeless/Nat$;
    Signature: #79                          // ()Lshapeless/Succ<Lshapeless/_0;>;

  public shapeless.Succ<shapeless.Succ<shapeless._0>> _2();
    descriptor: ()Lshapeless/Succ;
    flags: (0x0001) ACC_PUBLIC
    Code:
      stack=1, locals=1, args_size=1
         0: getstatic     #85                 // Field _2:Lshapeless/Succ;
         3: areturn
      LineNumberTable:
        line 56: 0
      LocalVariableTable:
        Start  Length  Slot  Name   Signature
            0       4     0  this   Lshapeless/Nat$;
    Signature: #83                          // ()Lshapeless/Succ<Lshapeless/Succ<Lshapeless/_0;>;>;

  public shapeless.Succ<shapeless.Succ<shapeless.Succ<shapeless._0>>> _3();
    descriptor: ()Lshapeless/Succ;
    flags: (0x0001) ACC_PUBLIC
    Code:
      stack=1, locals=1, args_size=1
         0: getstatic     #88                 // Field _3:Lshapeless/Succ;
         3: areturn
      LineNumberTable:
        line 56: 0
      LocalVariableTable:
        Start  Length  Slot  Name   Signature
            0       4     0  this   Lshapeless/Nat$;
    Signature: #86                          // ()Lshapeless/Succ<Lshapeless/Succ<Lshapeless/Succ<Lshapeless/_0;>;>;>;

  public shapeless.Succ<shapeless.Succ<shapeless.Succ<shapeless.Succ<shapeless._0>>>> _4();
    descriptor: ()Lshapeless/Succ;
    flags: (0x0001) ACC_PUBLIC
    Code:
      stack=1, locals=1, args_size=1
         0: getstatic     #91                 // Field _4:Lshapeless/Succ;
         3: areturn
      LineNumberTable:
        line 56: 0
      LocalVariableTable:
        Start  Length  Slot  Name   Signature
            0       4     0  this   Lshapeless/Nat$;
    Signature: #89                          // ()Lshapeless/Succ<Lshapeless/Succ<Lshapeless/Succ<Lshapeless/Succ<Lshapeless/_0;>;>;>;>;

  public shapeless.Succ<shapeless.Succ<shapeless.Succ<shapeless.Succ<shapeless.Succ<shapeless._0>>>>> _5();
    descriptor: ()Lshapeless/Succ;
    flags: (0x0001) ACC_PUBLIC
    Code:
      stack=1, locals=1, args_size=1
         0: getstatic     #94                 // Field _5:Lshapeless/Succ;
         3: areturn
      LineNumberTable:
        line 56: 0
      LocalVariableTable:
        Start  Length  Slot  Name   Signature
            0       4     0  this   Lshapeless/Nat$;
    Signature: #92                          // ()Lshapeless/Succ<Lshapeless/Succ<Lshapeless/Succ<Lshapeless/Succ<Lshapeless/Succ<Lshapeless/_0;>;>;>;>;>;

  public shapeless.Succ<shapeless.Succ<shapeless.Succ<shapeless.Succ<shapeless.Succ<shapeless.Succ<shapeless._0>>>>>> _6();
    descriptor: ()Lshapeless/Succ;
    flags: (0x0001) ACC_PUBLIC
    Code:
      stack=1, locals=1, args_size=1
         0: getstatic     #97                 // Field _6:Lshapeless/Succ;
         3: areturn
      LineNumberTable:
        line 56: 0
      LocalVariableTable:
        Start  Length  Slot  Name   Signature
            0       4     0  this   Lshapeless/Nat$;
    Signature: #95                          // ()Lshapeless/Succ<Lshapeless/Succ<Lshapeless/Succ<Lshapeless/Succ<Lshapeless/Succ<Lshapeless/Succ<Lshapeless/_0;>;>;>;>;>;>;

  public shapeless.Succ<shapeless.Succ<shapeless.Succ<shapeless.Succ<shapeless.Succ<shapeless.Succ<shapeless.Succ<shapeless._0>>>>>>> _7();
    descriptor: ()Lshapeless/Succ;
    flags: (0x0001) ACC_PUBLIC
    Code:
      stack=1, locals=1, args_size=1
         0: getstatic     #100                // Field _7:Lshapeless/Succ;
         3: areturn
      LineNumberTable:
        line 56: 0
      LocalVariableTable:
        Start  Length  Slot  Name   Signature
            0       4     0  this   Lshapeless/Nat$;
    Signature: #98                          // ()Lshapeless/Succ<Lshapeless/Succ<Lshapeless/Succ<Lshapeless/Succ<Lshapeless/Succ<Lshapeless/Succ<Lshapeless/Succ<Lshapeless/_0;>;>;>;>;>;>;>;

  public shapeless.Succ<shapeless.Succ<shapeless.Succ<shapeless.Succ<shapeless.Succ<shapeless.Succ<shapeless.Succ<shapeless.Succ<shapeless._0>>>>>>>> _8();
    descriptor: ()Lshapeless/Succ;
    flags: (0x0001) ACC_PUBLIC
    Code:
      stack=1, locals=1, args_size=1
         0: getstatic     #103                // Field _8:Lshapeless/Succ;
         3: areturn
      LineNumberTable:
        line 56: 0
      LocalVariableTable:
        Start  Length  Slot  Name   Signature
            0       4     0  this   Lshapeless/Nat$;
    Signature: #101                         // ()Lshapeless/Succ<Lshapeless/Succ<Lshapeless/Succ<Lshapeless/Succ<Lshapeless/Succ<Lshapeless/Succ<Lshapeless/Succ<Lshapeless/Succ<Lshapeless/_0;>;>;>;>;>;>;>;>;

  public shapeless.Succ<shapeless.Succ<shapeless.Succ<shapeless.Succ<shapeless.Succ<shapeless.Succ<shapeless.Succ<shapeless.Succ<shapeless.Succ<shapeless._0>>>>>>>>> _9();
    descriptor: ()Lshapeless/Succ;
    flags: (0x0001) ACC_PUBLIC
    Code:
      stack=1, locals=1, args_size=1
         0: getstatic     #106                // Field _9:Lshapeless/Succ;
         3: areturn
      LineNumberTable:
        line 56: 0
      LocalVariableTable:
        Start  Length  Slot  Name   Signature
            0       4     0  this   Lshapeless/Nat$;
    Signature: #104                         // ()Lshapeless/Succ<Lshapeless/Succ<Lshapeless/Succ<Lshapeless/Succ<Lshapeless/Succ<Lshapeless/Succ<Lshapeless/Succ<Lshapeless/Succ<Lshapeless/Succ<Lshapeless/_0;>;>;>;>;>;>;>;>;>;

  public shapeless.Succ<shapeless.Succ<shapeless.Succ<shapeless.Succ<shapeless.Succ<shapeless.Succ<shapeless.Succ<shapeless.Succ<shapeless.Succ<shapeless.Succ<shapeless._0>>>>>>>>>> _10();
    descriptor: ()Lshapeless/Succ;
    flags: (0x0001) ACC_PUBLIC
    Code:
      stack=1, locals=1, args_size=1
         0: getstatic     #109                // Field _10:Lshapeless/Succ;
         3: areturn
      LineNumberTable:
        line 56: 0
      LocalVariableTable:
        Start  Length  Slot  Name   Signature
            0       4     0  this   Lshapeless/Nat$;
    Signature: #107                         // ()Lshapeless/Succ<Lshapeless/Succ<Lshapeless/Succ<Lshapeless/Succ<Lshapeless/Succ<Lshapeless/Succ<Lshapeless/Succ<Lshapeless/Succ<Lshapeless/Succ<Lshapeless/Succ<Lshapeless/_0;>;>;>;>;>;>;>;>;>;>;

  public shapeless.Succ<shapeless.Succ<shapeless.Succ<shapeless.Succ<shapeless.Succ<shapeless.Succ<shapeless.Succ<shapeless.Succ<shapeless.Succ<shapeless.Succ<shapeless.Succ<shapeless._0>>>>>>>>>>> _11();
    descriptor: ()Lshapeless/Succ;
    flags: (0x0001) ACC_PUBLIC
    Code:
      stack=1, locals=1, args_size=1
         0: getstatic     #112                // Field _11:Lshapeless/Succ;
         3: areturn
      LineNumberTable:
        line 56: 0
      LocalVariableTable:
        Start  Length  Slot  Name   Signature
            0       4     0  this   Lshapeless/Nat$;
    Signature: #110                         // ()Lshapeless/Succ<Lshapeless/Succ<Lshapeless/Succ<Lshapeless/Succ<Lshapeless/Succ<Lshapeless/Succ<Lshapeless/Succ<Lshapeless/Succ<Lshapeless/Succ<Lshapeless/Succ<Lshapeless/Succ<Lshapeless/_0;>;>;>;>;>;>;>;>;>;>;>;

  public shapeless.Succ<shapeless.Succ<shapeless.Succ<shapeless.Succ<shapeless.Succ<shapeless.Succ<shapeless.Succ<shapeless.Succ<shapeless.Succ<shapeless.Succ<shapeless.Succ<shapeless.Succ<shapeless._0>>>>>>>>>>>> _12();
    descriptor: ()Lshapeless/Succ;
    flags: (0x0001) ACC_PUBLIC
    Code:
      stack=1, locals=1, args_size=1
         0: getstatic     #115                // Field _12:Lshapeless/Succ;
         3: areturn
      LineNumberTable:
        line 56: 0
      LocalVariableTable:
        Start  Length  Slot  Name   Signature
            0       4     0  this   Lshapeless/Nat$;
    Signature: #113                         // ()Lshapeless/Succ<Lshapeless/Succ<Lshapeless/Succ<Lshapeless/Succ<Lshapeless/Succ<Lshapeless/Succ<Lshapeless/Succ<Lshapeless/Succ<Lshapeless/Succ<Lshapeless/Succ<Lshapeless/Succ<Lshapeless/Succ<Lshapeless/_0;>;>;>;>;>;>;>;>;>;>;>;>;

  public shapeless.Succ<shapeless.Succ<shapeless.Succ<shapeless.Succ<shapeless.Succ<shapeless.Succ<shapeless.Succ<shapeless.Succ<shapeless.Succ<shapeless.Succ<shapeless.Succ<shapeless.Succ<shapeless.Succ<shapeless._0>>>>>>>>>>>>> _13();
    descriptor: ()Lshapeless/Succ;
    flags: (0x0001) ACC_PUBLIC
    Code:
      stack=1, locals=1, args_size=1
         0: getstatic     #118                // Field _13:Lshapeless/Succ;
         3: areturn
      LineNumberTable:
        line 56: 0
      LocalVariableTable:
        Start  Length  Slot  Name   Signature
            0       4     0  this   Lshapeless/Nat$;
    Signature: #116                         // ()Lshapeless/Succ<Lshapeless/Succ<Lshapeless/Succ<Lshapeless/Succ<Lshapeless/Succ<Lshapeless/Succ<Lshapeless/Succ<Lshapeless/Succ<Lshapeless/Succ<Lshapeless/Succ<Lshapeless/Succ<Lshapeless/Succ<Lshapeless/Succ<Lshapeless/_0;>;>;>;>;>;>;>;>;>;>;>;>;>;

  public shapeless.Succ<shapeless.Succ<shapeless.Succ<shapeless.Succ<shapeless.Succ<shapeless.Succ<shapeless.Succ<shapeless.Succ<shapeless.Succ<shapeless.Succ<shapeless.Succ<shapeless.Succ<shapeless.Succ<shapeless.Succ<shapeless._0>>>>>>>>>>>>>> _14();
    descriptor: ()Lshapeless/Succ;
    flags: (0x0001) ACC_PUBLIC
    Code:
      stack=1, locals=1, args_size=1
         0: getstatic     #121                // Field _14:Lshapeless/Succ;
         3: areturn
      LineNumberTable:
        line 56: 0
      LocalVariableTable:
        Start  Length  Slot  Name   Signature
            0       4     0  this   Lshapeless/Nat$;
    Signature: #119                         // ()Lshapeless/Succ<Lshapeless/Succ<Lshapeless/Succ<Lshapeless/Succ<Lshapeless/Succ<Lshapeless/Succ<Lshapeless/Succ<Lshapeless/Succ<Lshapeless/Succ<Lshapeless/Succ<Lshapeless/Succ<Lshapeless/Succ<Lshapeless/Succ<Lshapeless/Succ<Lshapeless/_0;>;>;>;>;>;>;>;>;>;>;>;>;>;>;

  public shapeless.Succ<shapeless.Succ<shapeless.Succ<shapeless.Succ<shapeless.Succ<shapeless.Succ<shapeless.Succ<shapeless.Succ<shapeless.Succ<shapeless.Succ<shapeless.Succ<shapeless.Succ<shapeless.Succ<shapeless.Succ<shapeless.Succ<shapeless._0>>>>>>>>>>>>>>> _15();
    descriptor: ()Lshapeless/Succ;
    flags: (0x0001) ACC_PUBLIC
    Code:
      stack=1, locals=1, args_size=1
         0: getstatic     #124                // Field _15:Lshapeless/Succ;
         3: areturn
      LineNumberTable:
        line 56: 0
      LocalVariableTable:
        Start  Length  Slot  Name   Signature
            0       4     0  this   Lshapeless/Nat$;
    Signature: #122                         // ()Lshapeless/Succ<Lshapeless/Succ<Lshapeless/Succ<Lshapeless/Succ<Lshapeless/Succ<Lshapeless/Succ<Lshapeless/Succ<Lshapeless/Succ<Lshapeless/Succ<Lshapeless/Succ<Lshapeless/Succ<Lshapeless/Succ<Lshapeless/Succ<Lshapeless/Succ<Lshapeless/Succ<Lshapeless/_0;>;>;>;>;>;>;>;>;>;>;>;>;>;>;>;

  public shapeless.Succ<shapeless.Succ<shapeless.Succ<shapeless.Succ<shapeless.Succ<shapeless.Succ<shapeless.Succ<shapeless.Succ<shapeless.Succ<shapeless.Succ<shapeless.Succ<shapeless.Succ<shapeless.Succ<shapeless.Succ<shapeless.Succ<shapeless.Succ<shapeless._0>>>>>>>>>>>>>>>> _16();
    descriptor: ()Lshapeless/Succ;
    flags: (0x0001) ACC_PUBLIC
    Code:
      stack=1, locals=1, args_size=1
         0: getstatic     #127                // Field _16:Lshapeless/Succ;
         3: areturn
      LineNumberTable:
        line 56: 0
      LocalVariableTable:
        Start  Length  Slot  Name   Signature
            0       4     0  this   Lshapeless/Nat$;
    Signature: #125                         // ()Lshapeless/Succ<Lshapeless/Succ<Lshapeless/Succ<Lshapeless/Succ<Lshapeless/Succ<Lshapeless/Succ<Lshapeless/Succ<Lshapeless/Succ<Lshapeless/Succ<Lshapeless/Succ<Lshapeless/Succ<Lshapeless/Succ<Lshapeless/Succ<Lshapeless/Succ<Lshapeless/Succ<Lshapeless/Succ<Lshapeless/_0;>;>;>;>;>;>;>;>;>;>;>;>;>;>;>;>;

  public shapeless.Succ<shapeless.Succ<shapeless.Succ<shapeless.Succ<shapeless.Succ<shapeless.Succ<shapeless.Succ<shapeless.Succ<shapeless.Succ<shapeless.Succ<shapeless.Succ<shapeless.Succ<shapeless.Succ<shapeless.Succ<shapeless.Succ<shapeless.Succ<shapeless.Succ<shapeless._0>>>>>>>>>>>>>>>>> _17();
    descriptor: ()Lshapeless/Succ;
    flags: (0x0001) ACC_PUBLIC
    Code:
      stack=1, locals=1, args_size=1
         0: getstatic     #130                // Field _17:Lshapeless/Succ;
         3: areturn
      LineNumberTable:
        line 56: 0
      LocalVariableTable:
        Start  Length  Slot  Name   Signature
            0       4     0  this   Lshapeless/Nat$;
    Signature: #128                         // ()Lshapeless/Succ<Lshapeless/Succ<Lshapeless/Succ<Lshapeless/Succ<Lshapeless/Succ<Lshapeless/Succ<Lshapeless/Succ<Lshapeless/Succ<Lshapeless/Succ<Lshapeless/Succ<Lshapeless/Succ<Lshapeless/Succ<Lshapeless/Succ<Lshapeless/Succ<Lshapeless/Succ<Lshapeless/Succ<Lshapeless/Succ<Lshapeless/_0;>;>;>;>;>;>;>;>;>;>;>;>;>;>;>;>;>;

  public shapeless.Succ<shapeless.Succ<shapeless.Succ<shapeless.Succ<shapeless.Succ<shapeless.Succ<shapeless.Succ<shapeless.Succ<shapeless.Succ<shapeless.Succ<shapeless.Succ<shapeless.Succ<shapeless.Succ<shapeless.Succ<shapeless.Succ<shapeless.Succ<shapeless.Succ<shapeless.Succ<shapeless._0>>>>>>>>>>>>>>>>>> _18();
    descriptor: ()Lshapeless/Succ;
    flags: (0x0001) ACC_PUBLIC
    Code:
      stack=1, locals=1, args_size=1
         0: getstatic     #133                // Field _18:Lshapeless/Succ;
         3: areturn
      LineNumberTable:
        line 56: 0
      LocalVariableTable:
        Start  Length  Slot  Name   Signature
            0       4     0  this   Lshapeless/Nat$;
    Signature: #131                         // ()Lshapeless/Succ<Lshapeless/Succ<Lshapeless/Succ<Lshapeless/Succ<Lshapeless/Succ<Lshapeless/Succ<Lshapeless/Succ<Lshapeless/Succ<Lshapeless/Succ<Lshapeless/Succ<Lshapeless/Succ<Lshapeless/Succ<Lshapeless/Succ<Lshapeless/Succ<Lshapeless/Succ<Lshapeless/Succ<Lshapeless/Succ<Lshapeless/Succ<Lshapeless/_0;>;>;>;>;>;>;>;>;>;>;>;>;>;>;>;>;>;>;

  public shapeless.Succ<shapeless.Succ<shapeless.Succ<shapeless.Succ<shapeless.Succ<shapeless.Succ<shapeless.Succ<shapeless.Succ<shapeless.Succ<shapeless.Succ<shapeless.Succ<shapeless.Succ<shapeless.Succ<shapeless.Succ<shapeless.Succ<shapeless.Succ<shapeless.Succ<shapeless.Succ<shapeless.Succ<shapeless._0>>>>>>>>>>>>>>>>>>> _19();
    descriptor: ()Lshapeless/Succ;
    flags: (0x0001) ACC_PUBLIC
    Code:
      stack=1, locals=1, args_size=1
         0: getstatic     #136                // Field _19:Lshapeless/Succ;
         3: areturn
      LineNumberTable:
        line 56: 0
      LocalVariableTable:
        Start  Length  Slot  Name   Signature
            0       4     0  this   Lshapeless/Nat$;
    Signature: #134                         // ()Lshapeless/Succ<Lshapeless/Succ<Lshapeless/Succ<Lshapeless/Succ<Lshapeless/Succ<Lshapeless/Succ<Lshapeless/Succ<Lshapeless/Succ<Lshapeless/Succ<Lshapeless/Succ<Lshapeless/Succ<Lshapeless/Succ<Lshapeless/Succ<Lshapeless/Succ<Lshapeless/Succ<Lshapeless/Succ<Lshapeless/Succ<Lshapeless/Succ<Lshapeless/Succ<Lshapeless/_0;>;>;>;>;>;>;>;>;>;>;>;>;>;>;>;>;>;>;>;

  public shapeless.Succ<shapeless.Succ<shapeless.Succ<shapeless.Succ<shapeless.Succ<shapeless.Succ<shapeless.Succ<shapeless.Succ<shapeless.Succ<shapeless.Succ<shapeless.Succ<shapeless.Succ<shapeless.Succ<shapeless.Succ<shapeless.Succ<shapeless.Succ<shapeless.Succ<shapeless.Succ<shapeless.Succ<shapeless.Succ<shapeless._0>>>>>>>>>>>>>>>>>>>> _20();
    descriptor: ()Lshapeless/Succ;
    flags: (0x0001) ACC_PUBLIC
    Code:
      stack=1, locals=1, args_size=1
         0: getstatic     #139                // Field _20:Lshapeless/Succ;
         3: areturn
      LineNumberTable:
        line 56: 0
      LocalVariableTable:
        Start  Length  Slot  Name   Signature
            0       4     0  this   Lshapeless/Nat$;
    Signature: #137                         // ()Lshapeless/Succ<Lshapeless/Succ<Lshapeless/Succ<Lshapeless/Succ<Lshapeless/Succ<Lshapeless/Succ<Lshapeless/Succ<Lshapeless/Succ<Lshapeless/Succ<Lshapeless/Succ<Lshapeless/Succ<Lshapeless/Succ<Lshapeless/Succ<Lshapeless/Succ<Lshapeless/Succ<Lshapeless/Succ<Lshapeless/Succ<Lshapeless/Succ<Lshapeless/Succ<Lshapeless/Succ<Lshapeless/_0;>;>;>;>;>;>;>;>;>;>;>;>;>;>;>;>;>;>;>;>;

  public shapeless.Succ<shapeless.Succ<shapeless.Succ<shapeless.Succ<shapeless.Succ<shapeless.Succ<shapeless.Succ<shapeless.Succ<shapeless.Succ<shapeless.Succ<shapeless.Succ<shapeless.Succ<shapeless.Succ<shapeless.Succ<shapeless.Succ<shapeless.Succ<shapeless.Succ<shapeless.Succ<shapeless.Succ<shapeless.Succ<shapeless.Succ<shapeless._0>>>>>>>>>>>>>>>>>>>>> _21();
    descriptor: ()Lshapeless/Succ;
    flags: (0x0001) ACC_PUBLIC
    Code:
      stack=1, locals=1, args_size=1
         0: getstatic     #142                // Field _21:Lshapeless/Succ;
         3: areturn
      LineNumberTable:
        line 56: 0
      LocalVariableTable:
        Start  Length  Slot  Name   Signature
            0       4     0  this   Lshapeless/Nat$;
    Signature: #140                         // ()Lshapeless/Succ<Lshapeless/Succ<Lshapeless/Succ<Lshapeless/Succ<Lshapeless/Succ<Lshapeless/Succ<Lshapeless/Succ<Lshapeless/Succ<Lshapeless/Succ<Lshapeless/Succ<Lshapeless/Succ<Lshapeless/Succ<Lshapeless/Succ<Lshapeless/Succ<Lshapeless/Succ<Lshapeless/Succ<Lshapeless/Succ<Lshapeless/Succ<Lshapeless/Succ<Lshapeless/Succ<Lshapeless/Succ<Lshapeless/_0;>;>;>;>;>;>;>;>;>;>;>;>;>;>;>;>;>;>;>;>;>;

  public shapeless.Succ<shapeless.Succ<shapeless.Succ<shapeless.Succ<shapeless.Succ<shapeless.Succ<shapeless.Succ<shapeless.Succ<shapeless.Succ<shapeless.Succ<shapeless.Succ<shapeless.Succ<shapeless.Succ<shapeless.Succ<shapeless.Succ<shapeless.Succ<shapeless.Succ<shapeless.Succ<shapeless.Succ<shapeless.Succ<shapeless.Succ<shapeless.Succ<shapeless._0>>>>>>>>>>>>>>>>>>>>>> _22();
    descriptor: ()Lshapeless/Succ;
    flags: (0x0001) ACC_PUBLIC
    Code:
      stack=1, locals=1, args_size=1
         0: getstatic     #145                // Field _22:Lshapeless/Succ;
         3: areturn
      LineNumberTable:
        line 56: 0
      LocalVariableTable:
        Start  Length  Slot  Name   Signature
            0       4     0  this   Lshapeless/Nat$;
    Signature: #143                         // ()Lshapeless/Succ<Lshapeless/Succ<Lshapeless/Succ<Lshapeless/Succ<Lshapeless/Succ<Lshapeless/Succ<Lshapeless/Succ<Lshapeless/Succ<Lshapeless/Succ<Lshapeless/Succ<Lshapeless/Succ<Lshapeless/Succ<Lshapeless/Succ<Lshapeless/Succ<Lshapeless/Succ<Lshapeless/Succ<Lshapeless/Succ<Lshapeless/Succ<Lshapeless/Succ<Lshapeless/Succ<Lshapeless/Succ<Lshapeless/Succ<Lshapeless/_0;>;>;>;>;>;>;>;>;>;>;>;>;>;>;>;>;>;>;>;>;>;>;

  public void shapeless$Nats$_setter_$_1_$eq(shapeless.Succ<shapeless._0>);
    descriptor: (Lshapeless/Succ;)V
    flags: (0x0001) ACC_PUBLIC
    Code:
      stack=1, locals=2, args_size=2
         0: aload_1
         1: putstatic     #81                 // Field _1:Lshapeless/Succ;
         4: return
      LineNumberTable:
        line 56: 0
      LocalVariableTable:
        Start  Length  Slot  Name   Signature
            0       5     0  this   Lshapeless/Nat$;
            0       5     1   x$1   Lshapeless/Succ;
    Signature: #148                         // (Lshapeless/Succ<Lshapeless/_0;>;)V
    MethodParameters:
      Name                           Flags
      x$1                            final

  public void shapeless$Nats$_setter_$_2_$eq(shapeless.Succ<shapeless.Succ<shapeless._0>>);
    descriptor: (Lshapeless/Succ;)V
    flags: (0x0001) ACC_PUBLIC
    Code:
      stack=1, locals=2, args_size=2
         0: aload_1
         1: putstatic     #85                 // Field _2:Lshapeless/Succ;
         4: return
      LineNumberTable:
        line 56: 0
      LocalVariableTable:
        Start  Length  Slot  Name   Signature
            0       5     0  this   Lshapeless/Nat$;
            0       5     1   x$1   Lshapeless/Succ;
    Signature: #151                         // (Lshapeless/Succ<Lshapeless/Succ<Lshapeless/_0;>;>;)V
    MethodParameters:
      Name                           Flags
      x$1                            final

  public void shapeless$Nats$_setter_$_3_$eq(shapeless.Succ<shapeless.Succ<shapeless.Succ<shapeless._0>>>);
    descriptor: (Lshapeless/Succ;)V
    flags: (0x0001) ACC_PUBLIC
    Code:
      stack=1, locals=2, args_size=2
         0: aload_1
         1: putstatic     #88                 // Field _3:Lshapeless/Succ;
         4: return
      LineNumberTable:
        line 56: 0
      LocalVariableTable:
        Start  Length  Slot  Name   Signature
            0       5     0  this   Lshapeless/Nat$;
            0       5     1   x$1   Lshapeless/Succ;
    Signature: #153                         // (Lshapeless/Succ<Lshapeless/Succ<Lshapeless/Succ<Lshapeless/_0;>;>;>;)V
    MethodParameters:
      Name                           Flags
      x$1                            final

  public void shapeless$Nats$_setter_$_4_$eq(shapeless.Succ<shapeless.Succ<shapeless.Succ<shapeless.Succ<shapeless._0>>>>);
    descriptor: (Lshapeless/Succ;)V
    flags: (0x0001) ACC_PUBLIC
    Code:
      stack=1, locals=2, args_size=2
         0: aload_1
         1: putstatic     #91                 // Field _4:Lshapeless/Succ;
         4: return
      LineNumberTable:
        line 56: 0
      LocalVariableTable:
        Start  Length  Slot  Name   Signature
            0       5     0  this   Lshapeless/Nat$;
            0       5     1   x$1   Lshapeless/Succ;
    Signature: #155                         // (Lshapeless/Succ<Lshapeless/Succ<Lshapeless/Succ<Lshapeless/Succ<Lshapeless/_0;>;>;>;>;)V
    MethodParameters:
      Name                           Flags
      x$1                            final

  public void shapeless$Nats$_setter_$_5_$eq(shapeless.Succ<shapeless.Succ<shapeless.Succ<shapeless.Succ<shapeless.Succ<shapeless._0>>>>>);
    descriptor: (Lshapeless/Succ;)V
    flags: (0x0001) ACC_PUBLIC
    Code:
      stack=1, locals=2, args_size=2
         0: aload_1
         1: putstatic     #94                 // Field _5:Lshapeless/Succ;
         4: return
      LineNumberTable:
        line 56: 0
      LocalVariableTable:
        Start  Length  Slot  Name   Signature
            0       5     0  this   Lshapeless/Nat$;
            0       5     1   x$1   Lshapeless/Succ;
    Signature: #157                         // (Lshapeless/Succ<Lshapeless/Succ<Lshapeless/Succ<Lshapeless/Succ<Lshapeless/Succ<Lshapeless/_0;>;>;>;>;>;)V
    MethodParameters:
      Name                           Flags
      x$1                            final

  public void shapeless$Nats$_setter_$_6_$eq(shapeless.Succ<shapeless.Succ<shapeless.Succ<shapeless.Succ<shapeless.Succ<shapeless.Succ<shapeless._0>>>>>>);
    descriptor: (Lshapeless/Succ;)V
    flags: (0x0001) ACC_PUBLIC
    Code:
      stack=1, locals=2, args_size=2
         0: aload_1
         1: putstatic     #97                 // Field _6:Lshapeless/Succ;
         4: return
      LineNumberTable:
        line 56: 0
      LocalVariableTable:
        Start  Length  Slot  Name   Signature
            0       5     0  this   Lshapeless/Nat$;
            0       5     1   x$1   Lshapeless/Succ;
    Signature: #159                         // (Lshapeless/Succ<Lshapeless/Succ<Lshapeless/Succ<Lshapeless/Succ<Lshapeless/Succ<Lshapeless/Succ<Lshapeless/_0;>;>;>;>;>;>;)V
    MethodParameters:
      Name                           Flags
      x$1                            final

  public void shapeless$Nats$_setter_$_7_$eq(shapeless.Succ<shapeless.Succ<shapeless.Succ<shapeless.Succ<shapeless.Succ<shapeless.Succ<shapeless.Succ<shapeless._0>>>>>>>);
    descriptor: (Lshapeless/Succ;)V
    flags: (0x0001) ACC_PUBLIC
    Code:
      stack=1, locals=2, args_size=2
         0: aload_1
         1: putstatic     #100                // Field _7:Lshapeless/Succ;
         4: return
      LineNumberTable:
        line 56: 0
      LocalVariableTable:
        Start  Length  Slot  Name   Signature
            0       5     0  this   Lshapeless/Nat$;
            0       5     1   x$1   Lshapeless/Succ;
    Signature: #161                         // (Lshapeless/Succ<Lshapeless/Succ<Lshapeless/Succ<Lshapeless/Succ<Lshapeless/Succ<Lshapeless/Succ<Lshapeless/Succ<Lshapeless/_0;>;>;>;>;>;>;>;)V
    MethodParameters:
      Name                           Flags
      x$1                            final

  public void shapeless$Nats$_setter_$_8_$eq(shapeless.Succ<shapeless.Succ<shapeless.Succ<shapeless.Succ<shapeless.Succ<shapeless.Succ<shapeless.Succ<shapeless.Succ<shapeless._0>>>>>>>>);
    descriptor: (Lshapeless/Succ;)V
    flags: (0x0001) ACC_PUBLIC
    Code:
      stack=1, locals=2, args_size=2
         0: aload_1
         1: putstatic     #103                // Field _8:Lshapeless/Succ;
         4: return
      LineNumberTable:
        line 56: 0
      LocalVariableTable:
        Start  Length  Slot  Name   Signature
            0       5     0  this   Lshapeless/Nat$;
            0       5     1   x$1   Lshapeless/Succ;
    Signature: #163                         // (Lshapeless/Succ<Lshapeless/Succ<Lshapeless/Succ<Lshapeless/Succ<Lshapeless/Succ<Lshapeless/Succ<Lshapeless/Succ<Lshapeless/Succ<Lshapeless/_0;>;>;>;>;>;>;>;>;)V
    MethodParameters:
      Name                           Flags
      x$1                            final

  public void shapeless$Nats$_setter_$_9_$eq(shapeless.Succ<shapeless.Succ<shapeless.Succ<shapeless.Succ<shapeless.Succ<shapeless.Succ<shapeless.Succ<shapeless.Succ<shapeless.Succ<shapeless._0>>>>>>>>>);
    descriptor: (Lshapeless/Succ;)V
    flags: (0x0001) ACC_PUBLIC
    Code:
      stack=1, locals=2, args_size=2
         0: aload_1
         1: putstatic     #106                // Field _9:Lshapeless/Succ;
         4: return
      LineNumberTable:
        line 56: 0
      LocalVariableTable:
        Start  Length  Slot  Name   Signature
            0       5     0  this   Lshapeless/Nat$;
            0       5     1   x$1   Lshapeless/Succ;
    Signature: #165                         // (Lshapeless/Succ<Lshapeless/Succ<Lshapeless/Succ<Lshapeless/Succ<Lshapeless/Succ<Lshapeless/Succ<Lshapeless/Succ<Lshapeless/Succ<Lshapeless/Succ<Lshapeless/_0;>;>;>;>;>;>;>;>;>;)V
    MethodParameters:
      Name                           Flags
      x$1                            final

  public void shapeless$Nats$_setter_$_10_$eq(shapeless.Succ<shapeless.Succ<shapeless.Succ<shapeless.Succ<shapeless.Succ<shapeless.Succ<shapeless.Succ<shapeless.Succ<shapeless.Succ<shapeless.Succ<shapeless._0>>>>>>>>>>);
    descriptor: (Lshapeless/Succ;)V
    flags: (0x0001) ACC_PUBLIC
    Code:
      stack=1, locals=2, args_size=2
         0: aload_1
         1: putstatic     #109                // Field _10:Lshapeless/Succ;
         4: return
      LineNumberTable:
        line 56: 0
      LocalVariableTable:
        Start  Length  Slot  Name   Signature
            0       5     0  this   Lshapeless/Nat$;
            0       5     1   x$1   Lshapeless/Succ;
    Signature: #167                         // (Lshapeless/Succ<Lshapeless/Succ<Lshapeless/Succ<Lshapeless/Succ<Lshapeless/Succ<Lshapeless/Succ<Lshapeless/Succ<Lshapeless/Succ<Lshapeless/Succ<Lshapeless/Succ<Lshapeless/_0;>;>;>;>;>;>;>;>;>;>;)V
    MethodParameters:
      Name                           Flags
      x$1                            final

  public void shapeless$Nats$_setter_$_11_$eq(shapeless.Succ<shapeless.Succ<shapeless.Succ<shapeless.Succ<shapeless.Succ<shapeless.Succ<shapeless.Succ<shapeless.Succ<shapeless.Succ<shapeless.Succ<shapeless.Succ<shapeless._0>>>>>>>>>>>);
    descriptor: (Lshapeless/Succ;)V
    flags: (0x0001) ACC_PUBLIC
    Code:
      stack=1, locals=2, args_size=2
         0: aload_1
         1: putstatic     #112                // Field _11:Lshapeless/Succ;
         4: return
      LineNumberTable:
        line 56: 0
      LocalVariableTable:
        Start  Length  Slot  Name   Signature
            0       5     0  this   Lshapeless/Nat$;
            0       5     1   x$1   Lshapeless/Succ;
    Signature: #169                         // (Lshapeless/Succ<Lshapeless/Succ<Lshapeless/Succ<Lshapeless/Succ<Lshapeless/Succ<Lshapeless/Succ<Lshapeless/Succ<Lshapeless/Succ<Lshapeless/Succ<Lshapeless/Succ<Lshapeless/Succ<Lshapeless/_0;>;>;>;>;>;>;>;>;>;>;>;)V
    MethodParameters:
      Name                           Flags
      x$1                            final

  public void shapeless$Nats$_setter_$_12_$eq(shapeless.Succ<shapeless.Succ<shapeless.Succ<shapeless.Succ<shapeless.Succ<shapeless.Succ<shapeless.Succ<shapeless.Succ<shapeless.Succ<shapeless.Succ<shapeless.Succ<shapeless.Succ<shapeless._0>>>>>>>>>>>>);
    descriptor: (Lshapeless/Succ;)V
    flags: (0x0001) ACC_PUBLIC
    Code:
      stack=1, locals=2, args_size=2
         0: aload_1
         1: putstatic     #115                // Field _12:Lshapeless/Succ;
         4: return
      LineNumberTable:
        line 56: 0
      LocalVariableTable:
        Start  Length  Slot  Name   Signature
            0       5     0  this   Lshapeless/Nat$;
            0       5     1   x$1   Lshapeless/Succ;
    Signature: #171                         // (Lshapeless/Succ<Lshapeless/Succ<Lshapeless/Succ<Lshapeless/Succ<Lshapeless/Succ<Lshapeless/Succ<Lshapeless/Succ<Lshapeless/Succ<Lshapeless/Succ<Lshapeless/Succ<Lshapeless/Succ<Lshapeless/Succ<Lshapeless/_0;>;>;>;>;>;>;>;>;>;>;>;>;)V
    MethodParameters:
      Name                           Flags
      x$1                            final

  public void shapeless$Nats$_setter_$_13_$eq(shapeless.Succ<shapeless.Succ<shapeless.Succ<shapeless.Succ<shapeless.Succ<shapeless.Succ<shapeless.Succ<shapeless.Succ<shapeless.Succ<shapeless.Succ<shapeless.Succ<shapeless.Succ<shapeless.Succ<shapeless._0>>>>>>>>>>>>>);
    descriptor: (Lshapeless/Succ;)V
    flags: (0x0001) ACC_PUBLIC
    Code:
      stack=1, locals=2, args_size=2
         0: aload_1
         1: putstatic     #118                // Field _13:Lshapeless/Succ;
         4: return
      LineNumberTable:
        line 56: 0
      LocalVariableTable:
        Start  Length  Slot  Name   Signature
            0       5     0  this   Lshapeless/Nat$;
            0       5     1   x$1   Lshapeless/Succ;
    Signature: #173                         // (Lshapeless/Succ<Lshapeless/Succ<Lshapeless/Succ<Lshapeless/Succ<Lshapeless/Succ<Lshapeless/Succ<Lshapeless/Succ<Lshapeless/Succ<Lshapeless/Succ<Lshapeless/Succ<Lshapeless/Succ<Lshapeless/Succ<Lshapeless/Succ<Lshapeless/_0;>;>;>;>;>;>;>;>;>;>;>;>;>;)V
    MethodParameters:
      Name                           Flags
      x$1                            final

  public void shapeless$Nats$_setter_$_14_$eq(shapeless.Succ<shapeless.Succ<shapeless.Succ<shapeless.Succ<shapeless.Succ<shapeless.Succ<shapeless.Succ<shapeless.Succ<shapeless.Succ<shapeless.Succ<shapeless.Succ<shapeless.Succ<shapeless.Succ<shapeless.Succ<shapeless._0>>>>>>>>>>>>>>);
    descriptor: (Lshapeless/Succ;)V
    flags: (0x0001) ACC_PUBLIC
    Code:
      stack=1, locals=2, args_size=2
         0: aload_1
         1: putstatic     #121                // Field _14:Lshapeless/Succ;
         4: return
      LineNumberTable:
        line 56: 0
      LocalVariableTable:
        Start  Length  Slot  Name   Signature
            0       5     0  this   Lshapeless/Nat$;
            0       5     1   x$1   Lshapeless/Succ;
    Signature: #175                         // (Lshapeless/Succ<Lshapeless/Succ<Lshapeless/Succ<Lshapeless/Succ<Lshapeless/Succ<Lshapeless/Succ<Lshapeless/Succ<Lshapeless/Succ<Lshapeless/Succ<Lshapeless/Succ<Lshapeless/Succ<Lshapeless/Succ<Lshapeless/Succ<Lshapeless/Succ<Lshapeless/_0;>;>;>;>;>;>;>;>;>;>;>;>;>;>;)V
    MethodParameters:
      Name                           Flags
      x$1                            final

  public void shapeless$Nats$_setter_$_15_$eq(shapeless.Succ<shapeless.Succ<shapeless.Succ<shapeless.Succ<shapeless.Succ<shapeless.Succ<shapeless.Succ<shapeless.Succ<shapeless.Succ<shapeless.Succ<shapeless.Succ<shapeless.Succ<shapeless.Succ<shapeless.Succ<shapeless.Succ<shapeless._0>>>>>>>>>>>>>>>);
    descriptor: (Lshapeless/Succ;)V
    flags: (0x0001) ACC_PUBLIC
    Code:
      stack=1, locals=2, args_size=2
         0: aload_1
         1: putstatic     #124                // Field _15:Lshapeless/Succ;
         4: return
      LineNumberTable:
        line 56: 0
      LocalVariableTable:
        Start  Length  Slot  Name   Signature
            0       5     0  this   Lshapeless/Nat$;
            0       5     1   x$1   Lshapeless/Succ;
    Signature: #177                         // (Lshapeless/Succ<Lshapeless/Succ<Lshapeless/Succ<Lshapeless/Succ<Lshapeless/Succ<Lshapeless/Succ<Lshapeless/Succ<Lshapeless/Succ<Lshapeless/Succ<Lshapeless/Succ<Lshapeless/Succ<Lshapeless/Succ<Lshapeless/Succ<Lshapeless/Succ<Lshapeless/Succ<Lshapeless/_0;>;>;>;>;>;>;>;>;>;>;>;>;>;>;>;)V
    MethodParameters:
      Name                           Flags
      x$1                            final

  public void shapeless$Nats$_setter_$_16_$eq(shapeless.Succ<shapeless.Succ<shapeless.Succ<shapeless.Succ<shapeless.Succ<shapeless.Succ<shapeless.Succ<shapeless.Succ<shapeless.Succ<shapeless.Succ<shapeless.Succ<shapeless.Succ<shapeless.Succ<shapeless.Succ<shapeless.Succ<shapeless.Succ<shapeless._0>>>>>>>>>>>>>>>>);
    descriptor: (Lshapeless/Succ;)V
    flags: (0x0001) ACC_PUBLIC
    Code:
      stack=1, locals=2, args_size=2
         0: aload_1
         1: putstatic     #127                // Field _16:Lshapeless/Succ;
         4: return
      LineNumberTable:
        line 56: 0
      LocalVariableTable:
        Start  Length  Slot  Name   Signature
            0       5     0  this   Lshapeless/Nat$;
            0       5     1   x$1   Lshapeless/Succ;
    Signature: #179                         // (Lshapeless/Succ<Lshapeless/Succ<Lshapeless/Succ<Lshapeless/Succ<Lshapeless/Succ<Lshapeless/Succ<Lshapeless/Succ<Lshapeless/Succ<Lshapeless/Succ<Lshapeless/Succ<Lshapeless/Succ<Lshapeless/Succ<Lshapeless/Succ<Lshapeless/Succ<Lshapeless/Succ<Lshapeless/Succ<Lshapeless/_0;>;>;>;>;>;>;>;>;>;>;>;>;>;>;>;>;)V
    MethodParameters:
      Name                           Flags
      x$1                            final

  public void shapeless$Nats$_setter_$_17_$eq(shapeless.Succ<shapeless.Succ<shapeless.Succ<shapeless.Succ<shapeless.Succ<shapeless.Succ<shapeless.Succ<shapeless.Succ<shapeless.Succ<shapeless.Succ<shapeless.Succ<shapeless.Succ<shapeless.Succ<shapeless.Succ<shapeless.Succ<shapeless.Succ<shapeless.Succ<shapeless._0>>>>>>>>>>>>>>>>>);
    descriptor: (Lshapeless/Succ;)V
    flags: (0x0001) ACC_PUBLIC
    Code:
      stack=1, locals=2, args_size=2
         0: aload_1
         1: putstatic     #130                // Field _17:Lshapeless/Succ;
         4: return
      LineNumberTable:
        line 56: 0
      LocalVariableTable:
        Start  Length  Slot  Name   Signature
            0       5     0  this   Lshapeless/Nat$;
            0       5     1   x$1   Lshapeless/Succ;
    Signature: #181                         // (Lshapeless/Succ<Lshapeless/Succ<Lshapeless/Succ<Lshapeless/Succ<Lshapeless/Succ<Lshapeless/Succ<Lshapeless/Succ<Lshapeless/Succ<Lshapeless/Succ<Lshapeless/Succ<Lshapeless/Succ<Lshapeless/Succ<Lshapeless/Succ<Lshapeless/Succ<Lshapeless/Succ<Lshapeless/Succ<Lshapeless/Succ<Lshapeless/_0;>;>;>;>;>;>;>;>;>;>;>;>;>;>;>;>;>;)V
    MethodParameters:
      Name                           Flags
      x$1                            final

  public void shapeless$Nats$_setter_$_18_$eq(shapeless.Succ<shapeless.Succ<shapeless.Succ<shapeless.Succ<shapeless.Succ<shapeless.Succ<shapeless.Succ<shapeless.Succ<shapeless.Succ<shapeless.Succ<shapeless.Succ<shapeless.Succ<shapeless.Succ<shapeless.Succ<shapeless.Succ<shapeless.Succ<shapeless.Succ<shapeless.Succ<shapeless._0>>>>>>>>>>>>>>>>>>);
    descriptor: (Lshapeless/Succ;)V
    flags: (0x0001) ACC_PUBLIC
    Code:
      stack=1, locals=2, args_size=2
         0: aload_1
         1: putstatic     #133                // Field _18:Lshapeless/Succ;
         4: return
      LineNumberTable:
        line 56: 0
      LocalVariableTable:
        Start  Length  Slot  Name   Signature
            0       5     0  this   Lshapeless/Nat$;
            0       5     1   x$1   Lshapeless/Succ;
    Signature: #183                         // (Lshapeless/Succ<Lshapeless/Succ<Lshapeless/Succ<Lshapeless/Succ<Lshapeless/Succ<Lshapeless/Succ<Lshapeless/Succ<Lshapeless/Succ<Lshapeless/Succ<Lshapeless/Succ<Lshapeless/Succ<Lshapeless/Succ<Lshapeless/Succ<Lshapeless/Succ<Lshapeless/Succ<Lshapeless/Succ<Lshapeless/Succ<Lshapeless/Succ<Lshapeless/_0;>;>;>;>;>;>;>;>;>;>;>;>;>;>;>;>;>;>;)V
    MethodParameters:
      Name                           Flags
      x$1                            final

  public void shapeless$Nats$_setter_$_19_$eq(shapeless.Succ<shapeless.Succ<shapeless.Succ<shapeless.Succ<shapeless.Succ<shapeless.Succ<shapeless.Succ<shapeless.Succ<shapeless.Succ<shapeless.Succ<shapeless.Succ<shapeless.Succ<shapeless.Succ<shapeless.Succ<shapeless.Succ<shapeless.Succ<shapeless.Succ<shapeless.Succ<shapeless.Succ<shapeless._0>>>>>>>>>>>>>>>>>>>);
    descriptor: (Lshapeless/Succ;)V
    flags: (0x0001) ACC_PUBLIC
    Code:
      stack=1, locals=2, args_size=2
         0: aload_1
         1: putstatic     #136                // Field _19:Lshapeless/Succ;
         4: return
      LineNumberTable:
        line 56: 0
      LocalVariableTable:
        Start  Length  Slot  Name   Signature
            0       5     0  this   Lshapeless/Nat$;
            0       5     1   x$1   Lshapeless/Succ;
    Signature: #185                         // (Lshapeless/Succ<Lshapeless/Succ<Lshapeless/Succ<Lshapeless/Succ<Lshapeless/Succ<Lshapeless/Succ<Lshapeless/Succ<Lshapeless/Succ<Lshapeless/Succ<Lshapeless/Succ<Lshapeless/Succ<Lshapeless/Succ<Lshapeless/Succ<Lshapeless/Succ<Lshapeless/Succ<Lshapeless/Succ<Lshapeless/Succ<Lshapeless/Succ<Lshapeless/Succ<Lshapeless/_0;>;>;>;>;>;>;>;>;>;>;>;>;>;>;>;>;>;>;>;)V
    MethodParameters:
      Name                           Flags
      x$1                            final

  public void shapeless$Nats$_setter_$_20_$eq(shapeless.Succ<shapeless.Succ<shapeless.Succ<shapeless.Succ<shapeless.Succ<shapeless.Succ<shapeless.Succ<shapeless.Succ<shapeless.Succ<shapeless.Succ<shapeless.Succ<shapeless.Succ<shapeless.Succ<shapeless.Succ<shapeless.Succ<shapeless.Succ<shapeless.Succ<shapeless.Succ<shapeless.Succ<shapeless.Succ<shapeless._0>>>>>>>>>>>>>>>>>>>>);
    descriptor: (Lshapeless/Succ;)V
    flags: (0x0001) ACC_PUBLIC
    Code:
      stack=1, locals=2, args_size=2
         0: aload_1
         1: putstatic     #139                // Field _20:Lshapeless/Succ;
         4: return
      LineNumberTable:
        line 56: 0
      LocalVariableTable:
        Start  Length  Slot  Name   Signature
            0       5     0  this   Lshapeless/Nat$;
            0       5     1   x$1   Lshapeless/Succ;
    Signature: #187                         // (Lshapeless/Succ<Lshapeless/Succ<Lshapeless/Succ<Lshapeless/Succ<Lshapeless/Succ<Lshapeless/Succ<Lshapeless/Succ<Lshapeless/Succ<Lshapeless/Succ<Lshapeless/Succ<Lshapeless/Succ<Lshapeless/Succ<Lshapeless/Succ<Lshapeless/Succ<Lshapeless/Succ<Lshapeless/Succ<Lshapeless/Succ<Lshapeless/Succ<Lshapeless/Succ<Lshapeless/Succ<Lshapeless/_0;>;>;>;>;>;>;>;>;>;>;>;>;>;>;>;>;>;>;>;>;)V
    MethodParameters:
      Name                           Flags
      x$1                            final

  public void shapeless$Nats$_setter_$_21_$eq(shapeless.Succ<shapeless.Succ<shapeless.Succ<shapeless.Succ<shapeless.Succ<shapeless.Succ<shapeless.Succ<shapeless.Succ<shapeless.Succ<shapeless.Succ<shapeless.Succ<shapeless.Succ<shapeless.Succ<shapeless.Succ<shapeless.Succ<shapeless.Succ<shapeless.Succ<shapeless.Succ<shapeless.Succ<shapeless.Succ<shapeless.Succ<shapeless._0>>>>>>>>>>>>>>>>>>>>>);
    descriptor: (Lshapeless/Succ;)V
    flags: (0x0001) ACC_PUBLIC
    Code:
      stack=1, locals=2, args_size=2
         0: aload_1
         1: putstatic     #142                // Field _21:Lshapeless/Succ;
         4: return
      LineNumberTable:
        line 56: 0
      LocalVariableTable:
        Start  Length  Slot  Name   Signature
            0       5     0  this   Lshapeless/Nat$;
            0       5     1   x$1   Lshapeless/Succ;
    Signature: #189                         // (Lshapeless/Succ<Lshapeless/Succ<Lshapeless/Succ<Lshapeless/Succ<Lshapeless/Succ<Lshapeless/Succ<Lshapeless/Succ<Lshapeless/Succ<Lshapeless/Succ<Lshapeless/Succ<Lshapeless/Succ<Lshapeless/Succ<Lshapeless/Succ<Lshapeless/Succ<Lshapeless/Succ<Lshapeless/Succ<Lshapeless/Succ<Lshapeless/Succ<Lshapeless/Succ<Lshapeless/Succ<Lshapeless/Succ<Lshapeless/_0;>;>;>;>;>;>;>;>;>;>;>;>;>;>;>;>;>;>;>;>;>;)V
    MethodParameters:
      Name                           Flags
      x$1                            final

  public void shapeless$Nats$_setter_$_22_$eq(shapeless.Succ<shapeless.Succ<shapeless.Succ<shapeless.Succ<shapeless.Succ<shapeless.Succ<shapeless.Succ<shapeless.Succ<shapeless.Succ<shapeless.Succ<shapeless.Succ<shapeless.Succ<shapeless.Succ<shapeless.Succ<shapeless.Succ<shapeless.Succ<shapeless.Succ<shapeless.Succ<shapeless.Succ<shapeless.Succ<shapeless.Succ<shapeless.Succ<shapeless._0>>>>>>>>>>>>>>>>>>>>>>);
    descriptor: (Lshapeless/Succ;)V
    flags: (0x0001) ACC_PUBLIC
    Code:
      stack=1, locals=2, args_size=2
         0: aload_1
         1: putstatic     #145                // Field _22:Lshapeless/Succ;
         4: return
      LineNumberTable:
        line 56: 0
      LocalVariableTable:
        Start  Length  Slot  Name   Signature
            0       5     0  this   Lshapeless/Nat$;
            0       5     1   x$1   Lshapeless/Succ;
    Signature: #191                         // (Lshapeless/Succ<Lshapeless/Succ<Lshapeless/Succ<Lshapeless/Succ<Lshapeless/Succ<Lshapeless/Succ<Lshapeless/Succ<Lshapeless/Succ<Lshapeless/Succ<Lshapeless/Succ<Lshapeless/Succ<Lshapeless/Succ<Lshapeless/Succ<Lshapeless/Succ<Lshapeless/Succ<Lshapeless/Succ<Lshapeless/Succ<Lshapeless/Succ<Lshapeless/Succ<Lshapeless/Succ<Lshapeless/Succ<Lshapeless/Succ<Lshapeless/_0;>;>;>;>;>;>;>;>;>;>;>;>;>;>;>;>;>;>;>;>;>;>;)V
    MethodParameters:
      Name                           Flags
      x$1                            final

  public shapeless._0 _0();
    descriptor: ()Lshapeless/_0;
    flags: (0x0001) ACC_PUBLIC
    Code:
      stack=1, locals=1, args_size=1
         0: getstatic     #77                 // Field _0:Lshapeless/_0;
         3: areturn
      LineNumberTable:
        line 64: 0
      LocalVariableTable:
        Start  Length  Slot  Name   Signature
            0       4     0  this   Lshapeless/Nat$;

  public <N extends shapeless.Nat> int toInt(shapeless.ops.nat$ToInt<N>);
    descriptor: (Lshapeless/ops/nat$ToInt;)I
    flags: (0x0001) ACC_PUBLIC
    Code:
      stack=1, locals=2, args_size=2
         0: aload_1
         1: invokeinterface #200,  1          // InterfaceMethod shapeless/ops/nat$ToInt.apply:()I
         6: ireturn
      LineNumberTable:
        line 66: 0
      LocalVariableTable:
        Start  Length  Slot  Name   Signature
            0       7     0  this   Lshapeless/Nat$;
            0       7     1 toIntN   Lshapeless/ops/nat$ToInt;
    Signature: #195                         // <N::Lshapeless/Nat;>(Lshapeless/ops/nat$ToInt<TN;>;)I
    MethodParameters:
      Name                           Flags
      toIntN                         final

  public int toInt(shapeless.Nat, shapeless.ops.nat$ToInt<shapeless.Nat>);
    descriptor: (Lshapeless/Nat;Lshapeless/ops/nat$ToInt;)I
    flags: (0x0001) ACC_PUBLIC
    Code:
      stack=1, locals=4, args_size=3
         0: aload_2
         1: astore_3
         2: aload_3
         3: invokeinterface #200,  1          // InterfaceMethod shapeless/ops/nat$ToInt.apply:()I
         8: ireturn
      LineNumberTable:
        line 68: 0
      LocalVariableTable:
        Start  Length  Slot  Name   Signature
            0       9     0  this   Lshapeless/Nat$;
            0       9     1     n   Lshapeless/Nat;
            0       9     2 toIntN   Lshapeless/ops/nat$ToInt;
    Signature: #203                         // (Lshapeless/Nat;Lshapeless/ops/nat$ToInt<Lshapeless/Nat;>;)I
    MethodParameters:
      Name                           Flags
      n                              final
      toIntN                         final

  public <N extends shapeless.Nat> N natOps(N);
    descriptor: (Lshapeless/Nat;)Lshapeless/Nat;
    flags: (0x0001) ACC_PUBLIC
    Code:
      stack=1, locals=2, args_size=2
         0: aload_1
         1: areturn
      LineNumberTable:
        line 70: 0
      LocalVariableTable:
        Start  Length  Slot  Name   Signature
            0       2     0  this   Lshapeless/Nat$;
            0       2     1     n   Lshapeless/Nat;
    Signature: #208                         // <N::Lshapeless/Nat;>(TN;)TN;
    MethodParameters:
      Name                           Flags
      n                              final

  private shapeless.Nat$();
    descriptor: ()V
    flags: (0x0002) ACC_PRIVATE
    Code:
      stack=1, locals=1, args_size=1
         0: aload_0
         1: invokespecial #209                // Method java/lang/Object."<init>":()V
         4: return
      LineNumberTable:
        line 56: 0
      LocalVariableTable:
        Start  Length  Slot  Name   Signature
            0       5     0  this   Lshapeless/Nat$;
}
InnerClasses:
  public static #12= #9 of #11;           // ToInt=class shapeless/ops/nat$ToInt of class shapeless/ops/nat
SourceFile: "nat.scala"
  ScalaInlineInfo: length = 0xFE (unknown attribute)
   01 01 00 32 00 40 00 3F 01 00 0F 00 C0 01 00 11
   00 4E 01 00 24 00 4E 01 00 26 00 4E 01 00 28 00
   4E 01 00 2A 00 4E 01 00 2C 00 4E 01 00 2E 00 4E
   01 00 30 00 4E 01 00 32 00 4E 01 00 34 00 4E 01
   00 36 00 4E 01 00 14 00 4E 01 00 38 00 4E 01 00
   3A 00 4E 01 00 3C 00 4E 01 00 16 00 4E 01 00 18
   00 4E 01 00 1A 00 4E 01 00 1C 00 4E 01 00 1E 00
   4E 01 00 20 00 4E 01 00 22 00 4E 01 00 C5 00 DA
   01 00 CE 00 CF 01 00 A6 00 93 01 00 A8 00 93 01
   00 AA 00 93 01 00 AC 00 93 01 00 AE 00 93 01 00
   B0 00 93 01 00 B2 00 93 01 00 B4 00 93 01 00 B6
   00 93 01 00 B8 00 93 01 00 92 00 93 01 00 BA 00
   93 01 00 BC 00 93 01 00 BE 00 93 01 00 96 00 93
   01 00 98 00 93 01 00 9A 00 93 01 00 9C 00 93 01
   00 9E 00 93 01 00 A0 00 93 01 00 A2 00 93 01 00
   A4 00 93 01 00 C1 00 CA 01 00 C1 00 C2 01
  Scala: length = 0x0 (unknown attribute)

