Classfile /Users/mw/Projects/slang-braindump/.jar/jar8/assemble/slang-braindump/assemble/content/shapeless/NatMacroDefns.class
  Last modified May 29, 2022; size 6724 bytes
  SHA-256 checksum 55d13e85e5492c688ed77b7765050755333fc1f28dfeaf07e94a2b2ea1ac8f4a
  Compiled from "nat.scala"
public interface shapeless.NatMacroDefns
  minor version: 0
  major version: 52
  flags: (0x0601) ACC_PUBLIC, ACC_INTERFACE, ACC_ABSTRACT
  this_class: #2                          // shapeless/NatMacroDefns
  super_class: #4                         // java/lang/Object
  interfaces: 0, fields: 0, methods: 11, attributes: 5
Constant pool:
    #1 = Utf8               shapeless/NatMacroDefns
    #2 = Class              #1            // shapeless/NatMacroDefns
    #3 = Utf8               java/lang/Object
    #4 = Class              #3            // java/lang/Object
    #5 = Utf8               nat.scala
    #6 = Utf8               Lscala/reflect/ScalaSignature;
    #7 = Utf8               bytes
    #8 = Utf8               \u0006\u0005M3qAC\u0006\u0011\u0002\u0007\u0005a\u0002C\u0003\u0016\u0001\u0011\u0005a\u0003C\u0004\u001b\u0001\t\u0007i\u0011A\u000e\b\u000b\u0019\u0002\u0001\u0012A\u0014\u0007\u000b%\u0002\u0001\u0012\u0001\u0016\t\u000b-\"A\u0011\u0001\u0017\t\u000b5\"A\u0011\u0001\u0018\t\u000b\u0015\u0003A\u0011\u0001$\t\u000b!\u0003A\u0011A%\t\u000bA\u0003A\u0011A)\u0003\u001b9\u000bG/T1de>$UM\u001a8t\u0015\u0005a\u0011!C:iCB,G.Z:t\u0007\u0001\u0019\"\u0001A\b\u0011\u0005A\u0019R\"A\t\u000b\u0003I\tQa]2bY\u0006L!\u0001F\t\u0003\r\u0005s\u0017PU3g\u0003\u0019!\u0013N\\5uIQ\tq\u0003\u0005\u0002\u00111%\u0011\u0011$\u0005\u0002\u0005+:LG/A\u0001d+\u0005a\u0002CA\u000f%\u001b\u0005q\"BA\u0010!\u0003!9\b.\u001b;fE>D(BA\u0011#\u0003\u0019i\u0017m\u0019:pg*\u00111%E\u0001\be\u00164G.Z2u\u0013\t)cDA\u0004D_:$X\r\u001f;\u0002\u00159\u000bG\u000fT5uKJ\fG\u000e\u0005\u0002)\t5\t\u0001A\u0001\u0006OCRd\u0015\u000e^3sC2\u001c\"\u0001B\b\u0002\rqJg.\u001b;?)\u00059\u0013aB;oCB\u0004H.\u001f\u000b\u0003_U\u00022\u0001\u0005\u00193\u0013\t\t\u0014C\u0001\u0004PaRLwN\u001c\t\u0003!MJ!\u0001N\t\u0003\u0007%sG\u000fC\u00037\r\u0001\u0007q\'A\u0001j!\tAtH\u0004\u0002:u9\u0011\u0001FA\u0005\u0003wq\n\u0001\"\u001e8jm\u0016\u00148/Z\u0005\u0003KuR!A\u0010\u0011\u0002\u0011\td\u0017mY6c_bL!\u0001Q!\u0003\tQ\u0013X-Z\u0005\u0003\u0005\u000e\u0013Q\u0001\u0016:fKNT!\u0001\u0012\u0012\u0002\u0007\u0005\u0004\u0018.\u0001\u0005nW:\u000bG\u000f\u00169u)\t9t\tC\u00037\u000f\u0001\u0007!\'\u0001\u0005nW:\u000bG\u000f\u00169f)\tQu\n\u0005\u00029\u0017&\u0011A*\u0014\u0002\u0005)f\u0004X-\u0003\u0002O\u0007\n)A+\u001f9fg\")a\u0007\u0003a\u0001e\u0005QQn\u001b(biZ\u000bG.^3\u0015\u0005]\u0012\u0006\"\u0002\u001c\n\u0001\u0004\u0011\u0004
    #9 = Utf8               scala/reflect/api/Internals$InternalApi
   #10 = Class              #9            // scala/reflect/api/Internals$InternalApi
   #11 = Utf8               scala/reflect/api/Internals
   #12 = Class              #11           // scala/reflect/api/Internals
   #13 = Utf8               InternalApi
   #14 = Utf8               scala/reflect/api/Internals$ReificationSupportApi
   #15 = Class              #14           // scala/reflect/api/Internals$ReificationSupportApi
   #16 = Utf8               ReificationSupportApi
   #17 = Utf8               scala/reflect/api/Internals$ReificationSupportApi$SyntacticNewExtractor
   #18 = Class              #17           // scala/reflect/api/Internals$ReificationSupportApi$SyntacticNewExtractor
   #19 = Utf8               SyntacticNewExtractor
   #20 = Utf8               scala/reflect/api/Symbols$SymbolApi
   #21 = Class              #20           // scala/reflect/api/Symbols$SymbolApi
   #22 = Utf8               scala/reflect/api/Symbols
   #23 = Class              #22           // scala/reflect/api/Symbols
   #24 = Utf8               SymbolApi
   #25 = Utf8               scala/reflect/api/Trees$AppliedTypeTreeApi
   #26 = Class              #25           // scala/reflect/api/Trees$AppliedTypeTreeApi
   #27 = Utf8               scala/reflect/api/Trees
   #28 = Class              #27           // scala/reflect/api/Trees
   #29 = Utf8               AppliedTypeTreeApi
   #30 = Utf8               scala/reflect/api/Trees$AppliedTypeTreeExtractor
   #31 = Class              #30           // scala/reflect/api/Trees$AppliedTypeTreeExtractor
   #32 = Utf8               AppliedTypeTreeExtractor
   #33 = Utf8               scala/reflect/api/Trees$IdentApi
   #34 = Class              #33           // scala/reflect/api/Trees$IdentApi
   #35 = Utf8               IdentApi
   #36 = Utf8               scala/reflect/api/Trees$TreeApi
   #37 = Class              #36           // scala/reflect/api/Trees$TreeApi
   #38 = Utf8               TreeApi
   #39 = Utf8               scala/reflect/api/Trees$ValDefApi
   #40 = Class              #39           // scala/reflect/api/Trees$ValDefApi
   #41 = Utf8               ValDefApi
   #42 = Utf8               scala/reflect/api/TypeTags$TypeTag
   #43 = Class              #42           // scala/reflect/api/TypeTags$TypeTag
   #44 = Utf8               scala/reflect/api/TypeTags
   #45 = Class              #44           // scala/reflect/api/TypeTags
   #46 = Utf8               TypeTag
   #47 = Utf8               scala/reflect/api/TypeTags$TypeTag$
   #48 = Class              #47           // scala/reflect/api/TypeTags$TypeTag$
   #49 = Utf8               TypeTag$
   #50 = Utf8               scala/reflect/api/Types$TypeApi
   #51 = Class              #50           // scala/reflect/api/Types$TypeApi
   #52 = Utf8               scala/reflect/api/Types
   #53 = Class              #52           // scala/reflect/api/Types
   #54 = Utf8               TypeApi
   #55 = Utf8               shapeless/NatMacroDefns$$typecreator1$1
   #56 = Class              #55           // shapeless/NatMacroDefns$$typecreator1$1
   #57 = Utf8               $typecreator1$1
   #58 = Utf8               shapeless/NatMacroDefns$$typecreator1$2
   #59 = Class              #58           // shapeless/NatMacroDefns$$typecreator1$2
   #60 = Utf8               $typecreator1$2
   #61 = Utf8               shapeless/NatMacroDefns$$typecreator2$1
   #62 = Class              #61           // shapeless/NatMacroDefns$$typecreator2$1
   #63 = Utf8               $typecreator2$1
   #64 = Utf8               shapeless/NatMacroDefns$$typecreator2$2
   #65 = Class              #64           // shapeless/NatMacroDefns$$typecreator2$2
   #66 = Utf8               $typecreator2$2
   #67 = Utf8               shapeless/NatMacroDefns$NatLiteral$
   #68 = Class              #67           // shapeless/NatMacroDefns$NatLiteral$
   #69 = Utf8               NatLiteral$
   #70 = Utf8               NatLiteral
   #71 = Utf8               ()Lshapeless/NatMacroDefns$NatLiteral$;
   #72 = Utf8               c
   #73 = Utf8               ()Lscala/reflect/macros/whitebox/Context;
   #74 = Utf8               mkNatTpt$
   #75 = Utf8               (Lshapeless/NatMacroDefns;I)Lscala/reflect/api/Trees$TreeApi;
   #76 = Utf8               $this
   #77 = Utf8               i
   #78 = Utf8               mkNatTpt
   #79 = Utf8               (I)Lscala/reflect/api/Trees$TreeApi;
   #80 = NameAndType        #78:#79       // mkNatTpt:(I)Lscala/reflect/api/Trees$TreeApi;
   #81 = InterfaceMethodref #2.#80        // shapeless/NatMacroDefns.mkNatTpt:(I)Lscala/reflect/api/Trees$TreeApi;
   #82 = Utf8               Lshapeless/NatMacroDefns;
   #83 = Utf8               I
   #84 = NameAndType        #72:#73       // c:()Lscala/reflect/macros/whitebox/Context;
   #85 = InterfaceMethodref #2.#84        // shapeless/NatMacroDefns.c:()Lscala/reflect/macros/whitebox/Context;
   #86 = Utf8               scala/reflect/macros/whitebox/Context
   #87 = Class              #86           // scala/reflect/macros/whitebox/Context
   #88 = Utf8               universe
   #89 = Utf8               ()Lscala/reflect/macros/Universe;
   #90 = NameAndType        #88:#89       // universe:()Lscala/reflect/macros/Universe;
   #91 = InterfaceMethodref #87.#90       // scala/reflect/macros/whitebox/Context.universe:()Lscala/reflect/macros/Universe;
   #92 = Utf8               scala/reflect/macros/Universe
   #93 = Class              #92           // scala/reflect/macros/Universe
   #94 = Utf8               rootMirror
   #95 = Utf8               ()Lscala/reflect/api/Mirror;
   #96 = NameAndType        #94:#95       // rootMirror:()Lscala/reflect/api/Mirror;
   #97 = Methodref          #93.#96       // scala/reflect/macros/Universe.rootMirror:()Lscala/reflect/api/Mirror;
   #98 = Utf8               ()Lscala/reflect/api/TypeTags$TypeTag$;
   #99 = NameAndType        #46:#98       // TypeTag:()Lscala/reflect/api/TypeTags$TypeTag$;
  #100 = Methodref          #93.#99       // scala/reflect/macros/Universe.TypeTag:()Lscala/reflect/api/TypeTags$TypeTag$;
  #101 = Utf8               <init>
  #102 = Utf8               (Lshapeless/NatMacroDefns;)V
  #103 = NameAndType        #101:#102     // "<init>":(Lshapeless/NatMacroDefns;)V
  #104 = Methodref          #56.#103      // shapeless/NatMacroDefns$$typecreator1$1."<init>":(Lshapeless/NatMacroDefns;)V
  #105 = Utf8               apply
  #106 = Utf8               (Lscala/reflect/api/Mirror;Lscala/reflect/api/TypeCreator;)Lscala/reflect/api/TypeTags$TypeTag;
  #107 = NameAndType        #105:#106     // apply:(Lscala/reflect/api/Mirror;Lscala/reflect/api/TypeCreator;)Lscala/reflect/api/TypeTags$TypeTag;
  #108 = Methodref          #48.#107      // scala/reflect/api/TypeTags$TypeTag$.apply:(Lscala/reflect/api/Mirror;Lscala/reflect/api/TypeCreator;)Lscala/reflect/api/TypeTags$TypeTag;
  #109 = Utf8               typeOf
  #110 = Utf8               (Lscala/reflect/api/TypeTags$TypeTag;)Lscala/reflect/api/Types$TypeApi;
  #111 = NameAndType        #109:#110     // typeOf:(Lscala/reflect/api/TypeTags$TypeTag;)Lscala/reflect/api/Types$TypeApi;
  #112 = Methodref          #93.#111      // scala/reflect/macros/Universe.typeOf:(Lscala/reflect/api/TypeTags$TypeTag;)Lscala/reflect/api/Types$TypeApi;
  #113 = Utf8               typeConstructor
  #114 = Utf8               ()Lscala/reflect/api/Types$TypeApi;
  #115 = NameAndType        #113:#114     // typeConstructor:()Lscala/reflect/api/Types$TypeApi;
  #116 = Methodref          #51.#115      // scala/reflect/api/Types$TypeApi.typeConstructor:()Lscala/reflect/api/Types$TypeApi;
  #117 = Utf8               typeSymbol
  #118 = Utf8               ()Lscala/reflect/api/Symbols$SymbolApi;
  #119 = NameAndType        #117:#118     // typeSymbol:()Lscala/reflect/api/Symbols$SymbolApi;
  #120 = Methodref          #51.#119      // scala/reflect/api/Types$TypeApi.typeSymbol:()Lscala/reflect/api/Symbols$SymbolApi;
  #121 = Methodref          #62.#103      // shapeless/NatMacroDefns$$typecreator2$1."<init>":(Lshapeless/NatMacroDefns;)V
  #122 = Utf8               Ident
  #123 = Utf8               (Lscala/reflect/api/Symbols$SymbolApi;)Lscala/reflect/api/Trees$IdentApi;
  #124 = NameAndType        #122:#123     // Ident:(Lscala/reflect/api/Symbols$SymbolApi;)Lscala/reflect/api/Trees$IdentApi;
  #125 = Methodref          #93.#124      // scala/reflect/macros/Universe.Ident:(Lscala/reflect/api/Symbols$SymbolApi;)Lscala/reflect/api/Trees$IdentApi;
  #126 = Utf8               loop$1
  #127 = Utf8               (ILscala/reflect/api/Trees$TreeApi;Lscala/reflect/api/Symbols$SymbolApi;)Lscala/reflect/api/Trees$TreeApi;
  #128 = NameAndType        #126:#127     // loop$1:(ILscala/reflect/api/Trees$TreeApi;Lscala/reflect/api/Symbols$SymbolApi;)Lscala/reflect/api/Trees$TreeApi;
  #129 = InterfaceMethodref #2.#128       // shapeless/NatMacroDefns.loop$1:(ILscala/reflect/api/Trees$TreeApi;Lscala/reflect/api/Symbols$SymbolApi;)Lscala/reflect/api/Trees$TreeApi;
  #130 = Utf8               $u
  #131 = Utf8               Lscala/reflect/macros/Universe;
  #132 = Utf8               $m
  #133 = Utf8               Lscala/reflect/api/Mirror;
  #134 = Utf8               succSym
  #135 = Utf8               Lscala/reflect/api/Symbols$SymbolApi;
  #136 = Utf8               _0Sym
  #137 = Utf8               this
  #138 = Utf8               mkNatTpe$
  #139 = Utf8               (Lshapeless/NatMacroDefns;I)Lscala/reflect/api/Types$TypeApi;
  #140 = Utf8               mkNatTpe
  #141 = Utf8               (I)Lscala/reflect/api/Types$TypeApi;
  #142 = NameAndType        #140:#141     // mkNatTpe:(I)Lscala/reflect/api/Types$TypeApi;
  #143 = InterfaceMethodref #2.#142       // shapeless/NatMacroDefns.mkNatTpe:(I)Lscala/reflect/api/Types$TypeApi;
  #144 = Methodref          #59.#103      // shapeless/NatMacroDefns$$typecreator1$2."<init>":(Lshapeless/NatMacroDefns;)V
  #145 = Methodref          #65.#103      // shapeless/NatMacroDefns$$typecreator2$2."<init>":(Lshapeless/NatMacroDefns;)V
  #146 = Utf8               loop$2
  #147 = Utf8               (ILscala/reflect/api/Types$TypeApi;Lscala/reflect/api/Types$TypeApi;)Lscala/reflect/api/Types$TypeApi;
  #148 = NameAndType        #146:#147     // loop$2:(ILscala/reflect/api/Types$TypeApi;Lscala/reflect/api/Types$TypeApi;)Lscala/reflect/api/Types$TypeApi;
  #149 = InterfaceMethodref #2.#148       // shapeless/NatMacroDefns.loop$2:(ILscala/reflect/api/Types$TypeApi;Lscala/reflect/api/Types$TypeApi;)Lscala/reflect/api/Types$TypeApi;
  #150 = Utf8               succTpe
  #151 = Utf8               Lscala/reflect/api/Types$TypeApi;
  #152 = Utf8               _0Tpe
  #153 = Utf8               mkNatValue$
  #154 = Utf8               mkNatValue
  #155 = NameAndType        #154:#79      // mkNatValue:(I)Lscala/reflect/api/Trees$TreeApi;
  #156 = InterfaceMethodref #2.#155       // shapeless/NatMacroDefns.mkNatValue:(I)Lscala/reflect/api/Trees$TreeApi;
  #157 = Utf8               internal
  #158 = Utf8               ()Lscala/reflect/api/Internals$InternalApi;
  #159 = NameAndType        #157:#158     // internal:()Lscala/reflect/api/Internals$InternalApi;
  #160 = Methodref          #93.#159      // scala/reflect/macros/Universe.internal:()Lscala/reflect/api/Internals$InternalApi;
  #161 = Utf8               reificationSupport
  #162 = Utf8               ()Lscala/reflect/api/Internals$ReificationSupportApi;
  #163 = NameAndType        #161:#162     // reificationSupport:()Lscala/reflect/api/Internals$ReificationSupportApi;
  #164 = InterfaceMethodref #10.#163      // scala/reflect/api/Internals$InternalApi.reificationSupport:()Lscala/reflect/api/Internals$ReificationSupportApi;
  #165 = Utf8               SyntacticNew
  #166 = Utf8               ()Lscala/reflect/api/Internals$ReificationSupportApi$SyntacticNewExtractor;
  #167 = NameAndType        #165:#166     // SyntacticNew:()Lscala/reflect/api/Internals$ReificationSupportApi$SyntacticNewExtractor;
  #168 = InterfaceMethodref #15.#167      // scala/reflect/api/Internals$ReificationSupportApi.SyntacticNew:()Lscala/reflect/api/Internals$ReificationSupportApi$SyntacticNewExtractor;
  #169 = Utf8               scala/collection/immutable/Nil$
  #170 = Class              #169          // scala/collection/immutable/Nil$
  #171 = Utf8               MODULE$
  #172 = Utf8               Lscala/collection/immutable/Nil$;
  #173 = NameAndType        #171:#172     // MODULE$:Lscala/collection/immutable/Nil$;
  #174 = Fieldref           #170.#173     // scala/collection/immutable/Nil$.MODULE$:Lscala/collection/immutable/Nil$;
  #175 = Utf8               scala/collection/immutable/$colon$colon
  #176 = Class              #175          // scala/collection/immutable/$colon$colon
  #177 = Utf8               (Ljava/lang/Object;Lscala/collection/immutable/List;)V
  #178 = NameAndType        #101:#177     // "<init>":(Ljava/lang/Object;Lscala/collection/immutable/List;)V
  #179 = Methodref          #176.#178     // scala/collection/immutable/$colon$colon."<init>":(Ljava/lang/Object;Lscala/collection/immutable/List;)V
  #180 = Utf8               scala/collection/immutable/List
  #181 = Class              #180          // scala/collection/immutable/List
  #182 = Utf8               noSelfType
  #183 = Utf8               ()Lscala/reflect/api/Trees$ValDefApi;
  #184 = NameAndType        #182:#183     // noSelfType:()Lscala/reflect/api/Trees$ValDefApi;
  #185 = Methodref          #93.#184      // scala/reflect/macros/Universe.noSelfType:()Lscala/reflect/api/Trees$ValDefApi;
  #186 = Utf8               (Lscala/collection/immutable/List;Lscala/collection/immutable/List;Lscala/reflect/api/Trees$TreeApi;Lscala/collection/immutable/List;)Lscala/reflect/api/Trees$TreeApi;
  #187 = NameAndType        #105:#186     // apply:(Lscala/collection/immutable/List;Lscala/collection/immutable/List;Lscala/reflect/api/Trees$TreeApi;Lscala/collection/immutable/List;)Lscala/reflect/api/Trees$TreeApi;
  #188 = InterfaceMethodref #18.#187      // scala/reflect/api/Internals$ReificationSupportApi$SyntacticNewExtractor.apply:(Lscala/collection/immutable/List;Lscala/collection/immutable/List;Lscala/reflect/api/Trees$TreeApi;Lscala/collection/immutable/List;)Lscala/reflect/api/Trees$TreeApi;
  #189 = Utf8               acc
  #190 = Utf8               succSym$1
  #191 = Utf8               AppliedTypeTree
  #192 = Utf8               ()Lscala/reflect/api/Trees$AppliedTypeTreeExtractor;
  #193 = NameAndType        #191:#192     // AppliedTypeTree:()Lscala/reflect/api/Trees$AppliedTypeTreeExtractor;
  #194 = Methodref          #93.#193      // scala/reflect/macros/Universe.AppliedTypeTree:()Lscala/reflect/api/Trees$AppliedTypeTreeExtractor;
  #195 = Utf8               (Lscala/reflect/api/Trees$TreeApi;Lscala/collection/immutable/List;)Lscala/reflect/api/Trees$AppliedTypeTreeApi;
  #196 = NameAndType        #105:#195     // apply:(Lscala/reflect/api/Trees$TreeApi;Lscala/collection/immutable/List;)Lscala/reflect/api/Trees$AppliedTypeTreeApi;
  #197 = Methodref          #31.#196      // scala/reflect/api/Trees$AppliedTypeTreeExtractor.apply:(Lscala/reflect/api/Trees$TreeApi;Lscala/collection/immutable/List;)Lscala/reflect/api/Trees$AppliedTypeTreeApi;
  #198 = Utf8               Lscala/reflect/api/Trees$TreeApi;
  #199 = Utf8               succTpe$1
  #200 = Utf8               scala/runtime/ScalaRunTime$
  #201 = Class              #200          // scala/runtime/ScalaRunTime$
  #202 = Utf8               Lscala/runtime/ScalaRunTime$;
  #203 = NameAndType        #171:#202     // MODULE$:Lscala/runtime/ScalaRunTime$;
  #204 = Fieldref           #201.#203     // scala/runtime/ScalaRunTime$.MODULE$:Lscala/runtime/ScalaRunTime$;
  #205 = Utf8               [Ljava/lang/Object;
  #206 = Class              #205          // "[Ljava/lang/Object;"
  #207 = Utf8               wrapRefArray
  #208 = Utf8               ([Ljava/lang/Object;)Lscala/collection/immutable/ArraySeq;
  #209 = NameAndType        #207:#208     // wrapRefArray:([Ljava/lang/Object;)Lscala/collection/immutable/ArraySeq;
  #210 = Methodref          #201.#209     // scala/runtime/ScalaRunTime$.wrapRefArray:([Ljava/lang/Object;)Lscala/collection/immutable/ArraySeq;
  #211 = Utf8               appliedType
  #212 = Utf8               (Lscala/reflect/api/Types$TypeApi;Lscala/collection/immutable/Seq;)Lscala/reflect/api/Types$TypeApi;
  #213 = NameAndType        #211:#212     // appliedType:(Lscala/reflect/api/Types$TypeApi;Lscala/collection/immutable/Seq;)Lscala/reflect/api/Types$TypeApi;
  #214 = Methodref          #93.#213      // scala/reflect/macros/Universe.appliedType:(Lscala/reflect/api/Types$TypeApi;Lscala/collection/immutable/Seq;)Lscala/reflect/api/Types$TypeApi;
  #215 = Utf8               $init$
  #216 = Utf8               Code
  #217 = Utf8               LineNumberTable
  #218 = Utf8               LocalVariableTable
  #219 = Utf8               MethodParameters
  #220 = Utf8               StackMapTable
  #221 = Utf8               InnerClasses
  #222 = Utf8               SourceFile
  #223 = Utf8               RuntimeVisibleAnnotations
  #224 = Utf8               ScalaInlineInfo
  #225 = Utf8               ScalaSig
{
  public abstract shapeless.NatMacroDefns$NatLiteral$ NatLiteral();
    descriptor: ()Lshapeless/NatMacroDefns$NatLiteral$;
    flags: (0x0401) ACC_PUBLIC, ACC_ABSTRACT

  public abstract scala.reflect.macros.whitebox.Context c();
    descriptor: ()Lscala/reflect/macros/whitebox/Context;
    flags: (0x0401) ACC_PUBLIC, ACC_ABSTRACT

  public static scala.reflect.api.Trees$TreeApi mkNatTpt$(shapeless.NatMacroDefns, int);
    descriptor: (Lshapeless/NatMacroDefns;I)Lscala/reflect/api/Trees$TreeApi;
    flags: (0x1009) ACC_PUBLIC, ACC_STATIC, ACC_SYNTHETIC
    Code:
      stack=2, locals=2, args_size=2
         0: aload_0
         1: iload_1
         2: invokespecial #81                 // InterfaceMethod mkNatTpt:(I)Lscala/reflect/api/Trees$TreeApi;
         5: areturn
      LineNumberTable:
        line 98: 0
      LocalVariableTable:
        Start  Length  Slot  Name   Signature
            0       6     0 $this   Lshapeless/NatMacroDefns;
            0       6     1     i   I
    MethodParameters:
      Name                           Flags
      $this                          final synthetic
      i                              final

  public default scala.reflect.api.Trees$TreeApi mkNatTpt(int);
    descriptor: (I)Lscala/reflect/api/Trees$TreeApi;
    flags: (0x0001) ACC_PUBLIC
    Code:
      stack=6, locals=8, args_size=2
         0: aload_0
         1: invokeinterface #85,  1           // InterfaceMethod c:()Lscala/reflect/macros/whitebox/Context;
         6: invokeinterface #91,  1           // InterfaceMethod scala/reflect/macros/whitebox/Context.universe:()Lscala/reflect/macros/Universe;
        11: aload_0
        12: invokeinterface #85,  1           // InterfaceMethod c:()Lscala/reflect/macros/whitebox/Context;
        17: invokeinterface #91,  1           // InterfaceMethod scala/reflect/macros/whitebox/Context.universe:()Lscala/reflect/macros/Universe;
        22: astore_3
        23: aload_0
        24: invokeinterface #85,  1           // InterfaceMethod c:()Lscala/reflect/macros/whitebox/Context;
        29: invokeinterface #91,  1           // InterfaceMethod scala/reflect/macros/whitebox/Context.universe:()Lscala/reflect/macros/Universe;
        34: invokevirtual #97                 // Method scala/reflect/macros/Universe.rootMirror:()Lscala/reflect/api/Mirror;
        37: astore        4
        39: aload_3
        40: invokevirtual #100                // Method scala/reflect/macros/Universe.TypeTag:()Lscala/reflect/api/TypeTags$TypeTag$;
        43: aload         4
        45: new           #56                 // class shapeless/NatMacroDefns$$typecreator1$1
        48: dup
        49: aconst_null
        50: invokespecial #104                // Method shapeless/NatMacroDefns$$typecreator1$1."<init>":(Lshapeless/NatMacroDefns;)V
        53: invokevirtual #108                // Method scala/reflect/api/TypeTags$TypeTag$.apply:(Lscala/reflect/api/Mirror;Lscala/reflect/api/TypeCreator;)Lscala/reflect/api/TypeTags$TypeTag;
        56: invokevirtual #112                // Method scala/reflect/macros/Universe.typeOf:(Lscala/reflect/api/TypeTags$TypeTag;)Lscala/reflect/api/Types$TypeApi;
        59: invokevirtual #116                // Method scala/reflect/api/Types$TypeApi.typeConstructor:()Lscala/reflect/api/Types$TypeApi;
        62: invokevirtual #120                // Method scala/reflect/api/Types$TypeApi.typeSymbol:()Lscala/reflect/api/Symbols$SymbolApi;
        65: astore_2
        66: aload_0
        67: invokeinterface #85,  1           // InterfaceMethod c:()Lscala/reflect/macros/whitebox/Context;
        72: invokeinterface #91,  1           // InterfaceMethod scala/reflect/macros/whitebox/Context.universe:()Lscala/reflect/macros/Universe;
        77: aload_0
        78: invokeinterface #85,  1           // InterfaceMethod c:()Lscala/reflect/macros/whitebox/Context;
        83: invokeinterface #91,  1           // InterfaceMethod scala/reflect/macros/whitebox/Context.universe:()Lscala/reflect/macros/Universe;
        88: astore        6
        90: aload_0
        91: invokeinterface #85,  1           // InterfaceMethod c:()Lscala/reflect/macros/whitebox/Context;
        96: invokeinterface #91,  1           // InterfaceMethod scala/reflect/macros/whitebox/Context.universe:()Lscala/reflect/macros/Universe;
       101: invokevirtual #97                 // Method scala/reflect/macros/Universe.rootMirror:()Lscala/reflect/api/Mirror;
       104: astore        7
       106: aload         6
       108: invokevirtual #100                // Method scala/reflect/macros/Universe.TypeTag:()Lscala/reflect/api/TypeTags$TypeTag$;
       111: aload         7
       113: new           #62                 // class shapeless/NatMacroDefns$$typecreator2$1
       116: dup
       117: aconst_null
       118: invokespecial #121                // Method shapeless/NatMacroDefns$$typecreator2$1."<init>":(Lshapeless/NatMacroDefns;)V
       121: invokevirtual #108                // Method scala/reflect/api/TypeTags$TypeTag$.apply:(Lscala/reflect/api/Mirror;Lscala/reflect/api/TypeCreator;)Lscala/reflect/api/TypeTags$TypeTag;
       124: invokevirtual #112                // Method scala/reflect/macros/Universe.typeOf:(Lscala/reflect/api/TypeTags$TypeTag;)Lscala/reflect/api/Types$TypeApi;
       127: invokevirtual #120                // Method scala/reflect/api/Types$TypeApi.typeSymbol:()Lscala/reflect/api/Symbols$SymbolApi;
       130: astore        5
       132: aload_0
       133: iload_1
       134: aload_0
       135: invokeinterface #85,  1           // InterfaceMethod c:()Lscala/reflect/macros/whitebox/Context;
       140: invokeinterface #91,  1           // InterfaceMethod scala/reflect/macros/whitebox/Context.universe:()Lscala/reflect/macros/Universe;
       145: aload         5
       147: invokevirtual #125                // Method scala/reflect/macros/Universe.Ident:(Lscala/reflect/api/Symbols$SymbolApi;)Lscala/reflect/api/Trees$IdentApi;
       150: aload_2
       151: invokespecial #129                // InterfaceMethod loop$1:(ILscala/reflect/api/Trees$TreeApi;Lscala/reflect/api/Symbols$SymbolApi;)Lscala/reflect/api/Trees$TreeApi;
       154: areturn
      LineNumberTable:
        line 99: 0
        line 100: 66
        line 108: 132
      LocalVariableTable:
        Start  Length  Slot  Name   Signature
           22      34     3    $u   Lscala/reflect/macros/Universe;
           37      19     4    $m   Lscala/reflect/api/Mirror;
           88      36     6    $u   Lscala/reflect/macros/Universe;
          104      20     7    $m   Lscala/reflect/api/Mirror;
           65      89     2 succSym   Lscala/reflect/api/Symbols$SymbolApi;
          130      24     5 _0Sym   Lscala/reflect/api/Symbols$SymbolApi;
            0     155     0  this   Lshapeless/NatMacroDefns;
            0     155     1     i   I
    MethodParameters:
      Name                           Flags
      i                              final

  public static scala.reflect.api.Types$TypeApi mkNatTpe$(shapeless.NatMacroDefns, int);
    descriptor: (Lshapeless/NatMacroDefns;I)Lscala/reflect/api/Types$TypeApi;
    flags: (0x1009) ACC_PUBLIC, ACC_STATIC, ACC_SYNTHETIC
    Code:
      stack=2, locals=2, args_size=2
         0: aload_0
         1: iload_1
         2: invokespecial #143                // InterfaceMethod mkNatTpe:(I)Lscala/reflect/api/Types$TypeApi;
         5: areturn
      LineNumberTable:
        line 111: 0
      LocalVariableTable:
        Start  Length  Slot  Name   Signature
            0       6     0 $this   Lshapeless/NatMacroDefns;
            0       6     1     i   I
    MethodParameters:
      Name                           Flags
      $this                          final synthetic
      i                              final

  public default scala.reflect.api.Types$TypeApi mkNatTpe(int);
    descriptor: (I)Lscala/reflect/api/Types$TypeApi;
    flags: (0x0001) ACC_PUBLIC
    Code:
      stack=6, locals=8, args_size=2
         0: aload_0
         1: invokeinterface #85,  1           // InterfaceMethod c:()Lscala/reflect/macros/whitebox/Context;
         6: invokeinterface #91,  1           // InterfaceMethod scala/reflect/macros/whitebox/Context.universe:()Lscala/reflect/macros/Universe;
        11: aload_0
        12: invokeinterface #85,  1           // InterfaceMethod c:()Lscala/reflect/macros/whitebox/Context;
        17: invokeinterface #91,  1           // InterfaceMethod scala/reflect/macros/whitebox/Context.universe:()Lscala/reflect/macros/Universe;
        22: astore_3
        23: aload_0
        24: invokeinterface #85,  1           // InterfaceMethod c:()Lscala/reflect/macros/whitebox/Context;
        29: invokeinterface #91,  1           // InterfaceMethod scala/reflect/macros/whitebox/Context.universe:()Lscala/reflect/macros/Universe;
        34: invokevirtual #97                 // Method scala/reflect/macros/Universe.rootMirror:()Lscala/reflect/api/Mirror;
        37: astore        4
        39: aload_3
        40: invokevirtual #100                // Method scala/reflect/macros/Universe.TypeTag:()Lscala/reflect/api/TypeTags$TypeTag$;
        43: aload         4
        45: new           #59                 // class shapeless/NatMacroDefns$$typecreator1$2
        48: dup
        49: aconst_null
        50: invokespecial #144                // Method shapeless/NatMacroDefns$$typecreator1$2."<init>":(Lshapeless/NatMacroDefns;)V
        53: invokevirtual #108                // Method scala/reflect/api/TypeTags$TypeTag$.apply:(Lscala/reflect/api/Mirror;Lscala/reflect/api/TypeCreator;)Lscala/reflect/api/TypeTags$TypeTag;
        56: invokevirtual #112                // Method scala/reflect/macros/Universe.typeOf:(Lscala/reflect/api/TypeTags$TypeTag;)Lscala/reflect/api/Types$TypeApi;
        59: invokevirtual #116                // Method scala/reflect/api/Types$TypeApi.typeConstructor:()Lscala/reflect/api/Types$TypeApi;
        62: astore_2
        63: aload_0
        64: invokeinterface #85,  1           // InterfaceMethod c:()Lscala/reflect/macros/whitebox/Context;
        69: invokeinterface #91,  1           // InterfaceMethod scala/reflect/macros/whitebox/Context.universe:()Lscala/reflect/macros/Universe;
        74: aload_0
        75: invokeinterface #85,  1           // InterfaceMethod c:()Lscala/reflect/macros/whitebox/Context;
        80: invokeinterface #91,  1           // InterfaceMethod scala/reflect/macros/whitebox/Context.universe:()Lscala/reflect/macros/Universe;
        85: astore        6
        87: aload_0
        88: invokeinterface #85,  1           // InterfaceMethod c:()Lscala/reflect/macros/whitebox/Context;
        93: invokeinterface #91,  1           // InterfaceMethod scala/reflect/macros/whitebox/Context.universe:()Lscala/reflect/macros/Universe;
        98: invokevirtual #97                 // Method scala/reflect/macros/Universe.rootMirror:()Lscala/reflect/api/Mirror;
       101: astore        7
       103: aload         6
       105: invokevirtual #100                // Method scala/reflect/macros/Universe.TypeTag:()Lscala/reflect/api/TypeTags$TypeTag$;
       108: aload         7
       110: new           #65                 // class shapeless/NatMacroDefns$$typecreator2$2
       113: dup
       114: aconst_null
       115: invokespecial #145                // Method shapeless/NatMacroDefns$$typecreator2$2."<init>":(Lshapeless/NatMacroDefns;)V
       118: invokevirtual #108                // Method scala/reflect/api/TypeTags$TypeTag$.apply:(Lscala/reflect/api/Mirror;Lscala/reflect/api/TypeCreator;)Lscala/reflect/api/TypeTags$TypeTag;
       121: invokevirtual #112                // Method scala/reflect/macros/Universe.typeOf:(Lscala/reflect/api/TypeTags$TypeTag;)Lscala/reflect/api/Types$TypeApi;
       124: astore        5
       126: aload_0
       127: iload_1
       128: aload         5
       130: aload_2
       131: invokespecial #149                // InterfaceMethod loop$2:(ILscala/reflect/api/Types$TypeApi;Lscala/reflect/api/Types$TypeApi;)Lscala/reflect/api/Types$TypeApi;
       134: areturn
      LineNumberTable:
        line 112: 0
        line 113: 63
        line 121: 126
      LocalVariableTable:
        Start  Length  Slot  Name   Signature
           22      34     3    $u   Lscala/reflect/macros/Universe;
           37      19     4    $m   Lscala/reflect/api/Mirror;
           85      36     6    $u   Lscala/reflect/macros/Universe;
          101      20     7    $m   Lscala/reflect/api/Mirror;
           62      72     2 succTpe   Lscala/reflect/api/Types$TypeApi;
          124      10     5 _0Tpe   Lscala/reflect/api/Types$TypeApi;
            0     135     0  this   Lshapeless/NatMacroDefns;
            0     135     1     i   I
    MethodParameters:
      Name                           Flags
      i                              final

  public static scala.reflect.api.Trees$TreeApi mkNatValue$(shapeless.NatMacroDefns, int);
    descriptor: (Lshapeless/NatMacroDefns;I)Lscala/reflect/api/Trees$TreeApi;
    flags: (0x1009) ACC_PUBLIC, ACC_STATIC, ACC_SYNTHETIC
    Code:
      stack=2, locals=2, args_size=2
         0: aload_0
         1: iload_1
         2: invokespecial #156                // InterfaceMethod mkNatValue:(I)Lscala/reflect/api/Trees$TreeApi;
         5: areturn
      LineNumberTable:
        line 124: 0
      LocalVariableTable:
        Start  Length  Slot  Name   Signature
            0       6     0 $this   Lshapeless/NatMacroDefns;
            0       6     1     i   I
    MethodParameters:
      Name                           Flags
      $this                          final synthetic
      i                              final

  public default scala.reflect.api.Trees$TreeApi mkNatValue(int);
    descriptor: (I)Lscala/reflect/api/Trees$TreeApi;
    flags: (0x0001) ACC_PUBLIC
    Code:
      stack=6, locals=2, args_size=2
         0: aload_0
         1: invokeinterface #85,  1           // InterfaceMethod c:()Lscala/reflect/macros/whitebox/Context;
         6: invokeinterface #91,  1           // InterfaceMethod scala/reflect/macros/whitebox/Context.universe:()Lscala/reflect/macros/Universe;
        11: invokevirtual #160                // Method scala/reflect/macros/Universe.internal:()Lscala/reflect/api/Internals$InternalApi;
        14: invokeinterface #164,  1          // InterfaceMethod scala/reflect/api/Internals$InternalApi.reificationSupport:()Lscala/reflect/api/Internals$ReificationSupportApi;
        19: invokeinterface #168,  1          // InterfaceMethod scala/reflect/api/Internals$ReificationSupportApi.SyntacticNew:()Lscala/reflect/api/Internals$ReificationSupportApi$SyntacticNewExtractor;
        24: getstatic     #174                // Field scala/collection/immutable/Nil$.MODULE$:Lscala/collection/immutable/Nil$;
        27: new           #176                // class scala/collection/immutable/$colon$colon
        30: dup
        31: aload_0
        32: iload_1
        33: invokeinterface #81,  2           // InterfaceMethod mkNatTpt:(I)Lscala/reflect/api/Trees$TreeApi;
        38: getstatic     #174                // Field scala/collection/immutable/Nil$.MODULE$:Lscala/collection/immutable/Nil$;
        41: invokespecial #179                // Method scala/collection/immutable/$colon$colon."<init>":(Ljava/lang/Object;Lscala/collection/immutable/List;)V
        44: checkcast     #181                // class scala/collection/immutable/List
        47: aload_0
        48: invokeinterface #85,  1           // InterfaceMethod c:()Lscala/reflect/macros/whitebox/Context;
        53: invokeinterface #91,  1           // InterfaceMethod scala/reflect/macros/whitebox/Context.universe:()Lscala/reflect/macros/Universe;
        58: invokevirtual #185                // Method scala/reflect/macros/Universe.noSelfType:()Lscala/reflect/api/Trees$ValDefApi;
        61: getstatic     #174                // Field scala/collection/immutable/Nil$.MODULE$:Lscala/collection/immutable/Nil$;
        64: invokeinterface #188,  5          // InterfaceMethod scala/reflect/api/Internals$ReificationSupportApi$SyntacticNewExtractor.apply:(Lscala/collection/immutable/List;Lscala/collection/immutable/List;Lscala/reflect/api/Trees$TreeApi;Lscala/collection/immutable/List;)Lscala/reflect/api/Trees$TreeApi;
        69: areturn
      LineNumberTable:
        line 125: 0
      LocalVariableTable:
        Start  Length  Slot  Name   Signature
            0      70     0  this   Lshapeless/NatMacroDefns;
            0      70     1     i   I
    MethodParameters:
      Name                           Flags
      i                              final

  private scala.reflect.api.Trees$TreeApi loop$1(int, scala.reflect.api.Trees$TreeApi, scala.reflect.api.Symbols$SymbolApi);
    descriptor: (ILscala/reflect/api/Trees$TreeApi;Lscala/reflect/api/Symbols$SymbolApi;)Lscala/reflect/api/Trees$TreeApi;
    flags: (0x0002) ACC_PRIVATE
    Code:
      stack=7, locals=4, args_size=4
         0: iload_1
         1: iconst_0
         2: if_icmpne     9
         5: aload_2
         6: goto          63
         9: iload_1
        10: iconst_1
        11: isub
        12: aload_0
        13: invokeinterface #85,  1           // InterfaceMethod c:()Lscala/reflect/macros/whitebox/Context;
        18: invokeinterface #91,  1           // InterfaceMethod scala/reflect/macros/whitebox/Context.universe:()Lscala/reflect/macros/Universe;
        23: invokevirtual #194                // Method scala/reflect/macros/Universe.AppliedTypeTree:()Lscala/reflect/api/Trees$AppliedTypeTreeExtractor;
        26: aload_0
        27: invokeinterface #85,  1           // InterfaceMethod c:()Lscala/reflect/macros/whitebox/Context;
        32: invokeinterface #91,  1           // InterfaceMethod scala/reflect/macros/whitebox/Context.universe:()Lscala/reflect/macros/Universe;
        37: aload_3
        38: invokevirtual #125                // Method scala/reflect/macros/Universe.Ident:(Lscala/reflect/api/Symbols$SymbolApi;)Lscala/reflect/api/Trees$IdentApi;
        41: new           #176                // class scala/collection/immutable/$colon$colon
        44: dup
        45: aload_2
        46: getstatic     #174                // Field scala/collection/immutable/Nil$.MODULE$:Lscala/collection/immutable/Nil$;
        49: invokespecial #179                // Method scala/collection/immutable/$colon$colon."<init>":(Ljava/lang/Object;Lscala/collection/immutable/List;)V
        52: checkcast     #181                // class scala/collection/immutable/List
        55: invokevirtual #197                // Method scala/reflect/api/Trees$AppliedTypeTreeExtractor.apply:(Lscala/reflect/api/Trees$TreeApi;Lscala/collection/immutable/List;)Lscala/reflect/api/Trees$AppliedTypeTreeApi;
        58: astore_2
        59: istore_1
        60: goto          0
        63: areturn
      StackMapTable: number_of_entries = 3
        frame_type = 0 /* same */
        frame_type = 8 /* same */
        frame_type = 117 /* same_locals_1_stack_item */
          stack = [ class scala/reflect/api/Trees$TreeApi ]
      LineNumberTable:
        line 104: 0
        line 105: 9
      LocalVariableTable:
        Start  Length  Slot  Name   Signature
            0      64     0  this   Lshapeless/NatMacroDefns;
            0      64     1     i   I
            0      64     2   acc   Lscala/reflect/api/Trees$TreeApi;
            0      64     3 succSym$1   Lscala/reflect/api/Symbols$SymbolApi;
    MethodParameters:
      Name                           Flags
      i                              final
      acc                            final
      succSym$1                      final

  private scala.reflect.api.Types$TypeApi loop$2(int, scala.reflect.api.Types$TypeApi, scala.reflect.api.Types$TypeApi);
    descriptor: (ILscala/reflect/api/Types$TypeApi;Lscala/reflect/api/Types$TypeApi;)Lscala/reflect/api/Types$TypeApi;
    flags: (0x0002) ACC_PRIVATE
    Code:
      stack=8, locals=4, args_size=4
         0: iload_1
         1: iconst_0
         2: if_icmpne     9
         5: aload_2
         6: goto          49
         9: iload_1
        10: iconst_1
        11: isub
        12: aload_0
        13: invokeinterface #85,  1           // InterfaceMethod c:()Lscala/reflect/macros/whitebox/Context;
        18: invokeinterface #91,  1           // InterfaceMethod scala/reflect/macros/whitebox/Context.universe:()Lscala/reflect/macros/Universe;
        23: aload_3
        24: getstatic     #204                // Field scala/runtime/ScalaRunTime$.MODULE$:Lscala/runtime/ScalaRunTime$;
        27: iconst_1
        28: anewarray     #51                 // class scala/reflect/api/Types$TypeApi
        31: dup
        32: iconst_0
        33: aload_2
        34: aastore
        35: checkcast     #206                // class "[Ljava/lang/Object;"
        38: invokevirtual #210                // Method scala/runtime/ScalaRunTime$.wrapRefArray:([Ljava/lang/Object;)Lscala/collection/immutable/ArraySeq;
        41: invokevirtual #214                // Method scala/reflect/macros/Universe.appliedType:(Lscala/reflect/api/Types$TypeApi;Lscala/collection/immutable/Seq;)Lscala/reflect/api/Types$TypeApi;
        44: astore_2
        45: istore_1
        46: goto          0
        49: areturn
      StackMapTable: number_of_entries = 3
        frame_type = 0 /* same */
        frame_type = 8 /* same */
        frame_type = 103 /* same_locals_1_stack_item */
          stack = [ class scala/reflect/api/Types$TypeApi ]
      LineNumberTable:
        line 117: 0
        line 118: 9
      LocalVariableTable:
        Start  Length  Slot  Name   Signature
            0      50     0  this   Lshapeless/NatMacroDefns;
            0      50     1     i   I
            0      50     2   acc   Lscala/reflect/api/Types$TypeApi;
            0      50     3 succTpe$1   Lscala/reflect/api/Types$TypeApi;
    MethodParameters:
      Name                           Flags
      i                              final
      acc                            final
      succTpe$1                      final

  public static void $init$(shapeless.NatMacroDefns);
    descriptor: (Lshapeless/NatMacroDefns;)V
    flags: (0x0009) ACC_PUBLIC, ACC_STATIC
    Code:
      stack=0, locals=1, args_size=1
         0: return
      LineNumberTable:
        line 86: 0
      LocalVariableTable:
        Start  Length  Slot  Name   Signature
            0       1     0 $this   Lshapeless/NatMacroDefns;
    MethodParameters:
      Name                           Flags
      $this                          final synthetic
}
InnerClasses:
  public #13= #10 of #12;                 // InternalApi=class scala/reflect/api/Internals$InternalApi of class scala/reflect/api/Internals
  public #16= #15 of #12;                 // ReificationSupportApi=class scala/reflect/api/Internals$ReificationSupportApi of class scala/reflect/api/Internals
  public #19= #18 of #15;                 // SyntacticNewExtractor=class scala/reflect/api/Internals$ReificationSupportApi$SyntacticNewExtractor of class scala/reflect/api/Internals$ReificationSupportApi
  public #24= #21 of #23;                 // SymbolApi=class scala/reflect/api/Symbols$SymbolApi of class scala/reflect/api/Symbols
  public #29= #26 of #28;                 // AppliedTypeTreeApi=class scala/reflect/api/Trees$AppliedTypeTreeApi of class scala/reflect/api/Trees
  public abstract #32= #31 of #28;        // AppliedTypeTreeExtractor=class scala/reflect/api/Trees$AppliedTypeTreeExtractor of class scala/reflect/api/Trees
  public #35= #34 of #28;                 // IdentApi=class scala/reflect/api/Trees$IdentApi of class scala/reflect/api/Trees
  public #38= #37 of #28;                 // TreeApi=class scala/reflect/api/Trees$TreeApi of class scala/reflect/api/Trees
  public #41= #40 of #28;                 // ValDefApi=class scala/reflect/api/Trees$ValDefApi of class scala/reflect/api/Trees
  public #46= #43 of #45;                 // TypeTag=class scala/reflect/api/TypeTags$TypeTag of class scala/reflect/api/TypeTags
  public #49= #48 of #45;                 // TypeTag$=class scala/reflect/api/TypeTags$TypeTag$ of class scala/reflect/api/TypeTags
  public abstract #54= #51 of #53;        // TypeApi=class scala/reflect/api/Types$TypeApi of class scala/reflect/api/Types
  public final #57= #56;                  // $typecreator1$1=class shapeless/NatMacroDefns$$typecreator1$1
  public final #60= #59;                  // $typecreator1$2=class shapeless/NatMacroDefns$$typecreator1$2
  public final #63= #62;                  // $typecreator2$1=class shapeless/NatMacroDefns$$typecreator2$1
  public final #66= #65;                  // $typecreator2$2=class shapeless/NatMacroDefns$$typecreator2$2
  public #69= #68 of #2;                  // NatLiteral$=class shapeless/NatMacroDefns$NatLiteral$ of class shapeless/NatMacroDefns
SourceFile: "nat.scala"
RuntimeVisibleAnnotations:
  0: #6(#7=s#8)
    scala.reflect.ScalaSignature(
      bytes="\u0006\u0005M3qAC\u0006\u0011\u0002\u0007\u0005a\u0002C\u0003\u0016\u0001\u0011\u0005a\u0003C\u0004\u001b\u0001\t\u0007i\u0011A\u000e\b\u000b\u0019\u0002\u0001\u0012A\u0014\u0007\u000b%\u0002\u0001\u0012\u0001\u0016\t\u000b-\"A\u0011\u0001\u0017\t\u000b5\"A\u0011\u0001\u0018\t\u000b\u0015\u0003A\u0011\u0001$\t\u000b!\u0003A\u0011A%\t\u000bA\u0003A\u0011A)\u0003\u001b9\u000bG/T1de>$UM\u001a8t\u0015\u0005a\u0011!C:iCB,G.Z:t\u0007\u0001\u0019\"\u0001A\b\u0011\u0005A\u0019R\"A\t\u000b\u0003I\tQa]2bY\u0006L!\u0001F\t\u0003\r\u0005s\u0017PU3g\u0003\u0019!\u0013N\\5uIQ\tq\u0003\u0005\u0002\u00111%\u0011\u0011$\u0005\u0002\u0005+:LG/A\u0001d+\u0005a\u0002CA\u000f%\u001b\u0005q\"BA\u0010!\u0003!9\b.\u001b;fE>D(BA\u0011#\u0003\u0019i\u0017m\u0019:pg*\u00111%E\u0001\be\u00164G.Z2u\u0013\t)cDA\u0004D_:$X\r\u001f;\u0002\u00159\u000bG\u000fT5uKJ\fG\u000e\u0005\u0002)\t5\t\u0001A\u0001\u0006OCRd\u0015\u000e^3sC2\u001c\"\u0001B\b\u0002\rqJg.\u001b;?)\u00059\u0013aB;oCB\u0004H.\u001f\u000b\u0003_U\u00022\u0001\u0005\u00193\u0013\t\t\u0014C\u0001\u0004PaRLwN\u001c\t\u0003!MJ!\u0001N\t\u0003\u0007%sG\u000fC\u00037\r\u0001\u0007q\'A\u0001j!\tAtH\u0004\u0002:u9\u0011\u0001FA\u0005\u0003wq\n\u0001\"\u001e8jm\u0016\u00148/Z\u0005\u0003KuR!A\u0010\u0011\u0002\u0011\td\u0017mY6c_bL!\u0001Q!\u0003\tQ\u0013X-Z\u0005\u0003\u0005\u000e\u0013Q\u0001\u0016:fKNT!\u0001\u0012\u0012\u0002\u0007\u0005\u0004\u0018.\u0001\u0005nW:\u000bG\u000f\u00169u)\t9t\tC\u00037\u000f\u0001\u0007!\'\u0001\u0005nW:\u000bG\u000f\u00169f)\tQu\n\u0005\u00029\u0017&\u0011A*\u0014\u0002\u0005)f\u0004X-\u0003\u0002O\u0007\n)A+\u001f9fg\")a\u0007\u0003a\u0001e\u0005QQn\u001b(biZ\u000bG.^3\u0015\u0005]\u0012\u0006\"\u0002\u001c\n\u0001\u0004\u0011\u0004"
    )
  ScalaInlineInfo: length = 0x3B (unknown attribute)
   01 00 00 0B 00 D7 00 66 01 00 46 00 47 00 00 48
   00 49 00 00 7E 00 7F 01 00 92 00 93 01 00 8A 00
   8B 01 00 8C 00 8D 00 00 4A 00 4B 01 00 4E 00 4F
   00 00 99 00 4B 01 00 9A 00 4F 00
  ScalaSig: length = 0x3 (unknown attribute)
   05 02 00
