Classfile /Users/mw/Projects/slang-braindump/.jar/jar8/assemble/slang-braindump/assemble/content/shapeless/package.class
  Last modified May 29, 2022; size 6278 bytes
  SHA-256 checksum 4753b09e0318eaf5d25ad2d3999900ace2f569307d44b7258c28de790f17d8cc
  Compiled from "package.scala"
public final class shapeless.package
  minor version: 0
  major version: 52
  flags: (0x0031) ACC_PUBLIC, ACC_FINAL, ACC_SUPER
  this_class: #2                          // shapeless/package
  super_class: #4                         // java/lang/Object
  interfaces: 0, fields: 0, methods: 16, attributes: 4
Constant pool:
    #1 = Utf8               shapeless/package
    #2 = Class              #1            // shapeless/package
    #3 = Utf8               java/lang/Object
    #4 = Class              #3            // java/lang/Object
    #5 = Utf8               package.scala
    #6 = Utf8               Lscala/reflect/ScalaSignature;
    #7 = Utf8               bytes
    #8 = Utf8               \u0006\u0005\r\u0015w!B\u001b7\u0011\u0003Id!B\u001e7\u0011\u0003a\u0004\"\u0002$\u0002\t\u00039\u0005\"\u0002%\u0002\t\u0003IU\u0001B\'\u0002\u00019+AaV\u0001\u00011\u0016!1-\u0001\u0001e\u000b\u0011Q\u0017\u0001A6\u0006\tE\f\u0001A]\u0003\u0005u\u0006\u000110\u0002\u0004\u0002\n\u0005\u0001\u00111\u0002\u0004\n\u0003[\t\u0001\u0013aI\u0001\u0003_Aq!!\u0015\u0002\t\u0007\t\u0019\u0006C\u0004\u0002b\u0005!\u0019!a\u0019\t\u000f\u00055\u0014\u0001b\u0001\u0002p\u0019I\u0011\u0011P\u0001\u0011\u0002G\u0005\u00111\u0010\u0005\b\u0003+\u000bA1AAL\u0011\u001d\t)+\u0001C\u0002\u0003OCq!a.\u0002\t\u0007\tI,\u0002\u0004\u0002J\u0006\u0001\u00111Z\u0003\u0007\u0003?\f\u0001!!9\u0006\r\u0005U\u0018\u0001AA|\u0011%\u0011\u0019#\u0001b\u0001\n\u0003\u0011)\u0003\u0003\u0005\u0003.\u0005\u0001\u000b\u0011\u0002B\u0014\u0011%\u0011y#\u0001b\u0001\n\u0003\u0011)\u0003\u0003\u0005\u00032\u0005\u0001\u000b\u0011\u0002B\u0014\u0011%\u0011\u0019$\u0001b\u0001\n\u0003\u0011)\u0003\u0003\u0005\u00036\u0005\u0001\u000b\u0011\u0002B\u0014\u0011%\u00119$\u0001b\u0001\n\u0003\u0011I\u0004\u0003\u0005\u0003B\u0005\u0001\u000b\u0011\u0002B\u001e\u0011%\u0011\u0019%\u0001b\u0001\n\u0003\u0011)\u0005\u0003\u0005\u0003N\u0005\u0001\u000b\u0011\u0002B$\u0011%\u0011y%\u0001b\u0001\n\u0003\u0011\t\u0006\u0003\u0005\u0003Z\u0005\u0001\u000b\u0011\u0002B*\u0011%\u0011Y&\u0001b\u0001\n\u0003\u0011i\u0006\u0003\u0005\u0003f\u0005\u0001\u000b\u0011\u0002B0\r%\u00119\'\u0001I\u0001$\u0003\u0011I\u0007\u0002\u0004\u0003l\u0011\u0012\ta\u0015\u0005\b\u0005[\"c\u0011\u0001B8\r%\u0011)(\u0001I\u0001$\u0003\u00119\b\u0002\u0004\u0003l\u001d\u0012\ta\u0015\u0005\b\u0005[:c\u0011\u0001B>\r%\u0011I)\u0001I\u0001$\u0003\u0011Y\t\u0002\u0004\u0003l)\u0012\ta\u0015\u0005\b\u0005[Rc\u0011\u0001BH\u000b\u0019\u0011\u0019+\u0001\u0001\u0003&\u001a1!\u0011[\u0001\u0001\u0005\'DaA\u0012\u0018\u0005\u0002\t]\u0007b\u0002B7]\u0011\u0005!q\u001c\u0005\b\u0005[\fA\u0011\u0001Bx\u000b\u0019\u0011i0\u0001\u0001\u0003\u0000\"91\u0011C\u0001\u0005\u0002\rM\u0001\u0002CB\u0010\u0003\t%\ta!\t\u0002\u000fA\f7m[1hK*\tq\'A\u0005tQ\u0006\u0004X\r\\3tg\u000e\u0001\u0001C\u0001\u001e\u0002\u001b\u00051$a\u00029bG.\fw-Z\n\u0004\u0003u\u001a\u0005C\u0001 B\u001b\u0005y$\"\u0001!\u0002\u000bM\u001c\u0017\r\\1\n\u0005\t{$AB!osJ+g\r\u0005\u0002;\t&\u0011QI\u000e\u0002\u0016\'\u000e\fG.\u0019,feNLwN\\*qK\u000eLg-[2t\u0003\u0019a\u0014N\\5u}Q\t\u0011(\u0001\u0006v]\u0016D\b/Z2uK\u0012,\u0012A\u0013\t\u0003}-K!\u0001T \u0003\u000f9{G\u000f[5oO\n\u0011\u0011\nZ\u000b\u0003\u001fF\u0003\"\u0001U)\r\u0001\u00111!\u000b\u0002CC\u0002M\u0013\u0011\u0001V\t\u0003\u0015R\u0003\"AP+\n\u0005Y{$aA!os\n)1i\u001c8tiV\u0011\u0011\f\u0019\n\u00035v2AaW\u0001\u00013\naAH]3gS:,W.\u001a8u}\u0015!QL\u0017\u0001_\u0005\tq=8\u0006\u0002`EB\u0011\u0001\u000b\u0019\u0003\u0006C\u0016\u0011\ra\u0015\u0002\u0002\u0007\u0012)!\u000b\u0018b\u0001\'\n1A%\u001e\u00191\u0003\u000e+\"!Z5\u0011\ty2\u0007NS\u0005\u0003O~\u0012\u0011BR;oGRLwN\\\u0019\u0011\u0005AKG!\u0002*\u0007\u0005\u0004\u0019&\u0001\u0004\u0013vaA\n5\tJ;1a\u0005\u001bUC\u00017q!\rigA\\\u0007\u0002\u0003A\u0019QNB8\u0011\u0005A\u0003H!\u0002*\b\u0005\u0004\u0019&A\u0002\u0013veI\u0012t\'F\u0002tmb\u00142\u0001^;x\r\u0011Y\u0016\u0001A:\u0011\u0005A3H!\u0002*\t\u0005\u0004\u0019\u0006C\u0001)y\t\u0015I\bB1\u0001T\u0005\u0005)&A\u0002\u0013veI\u0012\u0004(F\u0003}\u0003\u0003\t9\u0001E\u0002n\ru\u0004R!\u001c\u0005\u007f\u0003\u0007\u00012!\u001c\u0004\u0000!\r\u0001\u0016\u0011\u0001\u0003\u0006%&\u0011\ra\u0015\t\u0005[\u001a\t)\u0001E\u0002Q\u0003\u000f!Q!_\u0005C\u0002M\u0013a\u0002\n2be\u0012*(G\r\u001a9I\t\f\'/\u0006\u0004\u0002\u000e\u0005\u001d\u00121\u0006\n\u0004\u0003\u001fid!B.\u0002\u0001\u00055QAB/\u0002\u0010\u0001\t\u0019\"\u0006\u0003\u0002\u0016\u0005}\u0001c\u0002 \u0002\u0018\u0005m\u00111E\u0005\u0004\u00033y$\u0001\u0005\u0013mKN\u001cHeY8m_:$C.Z:t!\u0011iw!!\b\u0011\u0007A\u000by\u0002B\u0004\u0002\"\u0005E!\u0019A*\u0003\u0003a\u0003b!\\\u0005\u0002&\u0005%\u0002c\u0001)\u0002(\u0011)!K\u0003b\u0001\'B\u0019\u0001+a\u000b\u0005\u000beT!\u0019A*\u0003#\u0011*\u0017\u000fJ2pY>tGEY1oO\u0012*\u0017/\u0006\u0004\u00022\u0005%\u0013QJ\n\u0005\u0017u\n\u0019\u0004\u0005\u0003\u00026\u0005\rc\u0002BA\u001c\u0003\u0003rA!!\u000f\u0002@5\u0011\u00111\b\u0006\u0004\u0003{A\u0014A\u0002\u001fs_>$h(C\u0001A\u0013\t)t(\u0003\u0003\u0002F\u0005\u001d#\u0001D*fe&\fG.\u001b>bE2,\'BA\u001b@\t\u0019\tYe\u0003b\u0001\'\n\t\u0011\t\u0002\u0004\u0002P-\u0011\ra\u0015\u0002\u0002\u0005\u0006\u0019a.Z9\u0016\r\u0005U\u00131LA0+\t\t9\u0006\u0005\u0004n\u0017\u0005e\u0013Q\f\t\u0004!\u0006mCABA&\u0019\t\u00071\u000bE\u0002Q\u0003?\"a!a\u0014\r\u0005\u0004\u0019\u0016!\u00038fc\u0006k\'-[42+\u0011\t)\'a\u001b\u0016\u0005\u0005\u001d\u0004CB7\f\u0003S\nI\u0007E\u0002Q\u0003W\"a!a\u0013\u000e\u0005\u0004\u0019\u0016!\u00038fc\u0006k\'-[43+\u0011\t\t(a\u001e\u0016\u0005\u0005M\u0004CB7\f\u0003k\n)\bE\u0002Q\u0003o\"a!a\u0013\u000f\u0005\u0004\u0019&!\u0006\u0013mKN\u001cHeY8m_:$#-\u00198hI1,7o]\u000b\u0007\u0003{\ny(!!\u0014\t=i\u00141\u0007\u0003\u0007\u0003\u0017z!\u0019A*\u0005\r\u0005=sB1\u0001TQ\u0015y\u0011QQAI!\u0011\t9)!$\u000e\u0005\u0005%%bAAF\u007f\u0005Q\u0011M\u001c8pi\u0006$\u0018n\u001c8\n\t\u0005=\u0015\u0011\u0012\u0002\u0011S6\u0004H.[2ji:{GOR8v]\u0012\f#!a%\u0002E\u0011Z\u0018) \u0011nkN$\bE\\8uA\t,\u0007%\u0019\u0011tk\n$\u0018\u0010]3!_\u001a\u0004Ce\u001f\"~\u0003\u0011q7/\u001e2\u0016\r\u0005e\u0015qTAR+\t\tY\n\u0005\u0004n\u001f\u0005u\u0015\u0011\u0015\t\u0004!\u0006}EABA&!\t\u00071\u000bE\u0002Q\u0003G#a!a\u0014\u0011\u0005\u0004\u0019\u0016A\u00038tk\n\fUNY5hcU1\u0011\u0011VAX\u0003g+\"!a+\u0011\r5|\u0011QVAY!\r\u0001\u0016q\u0016\u0003\u0007\u0003\u0017\n\"\u0019A*\u0011\u0007A\u000b\u0019\fB\u0004\u0002PE\u0011\r!!.\u0012\u0007\u00055F+\u0001\u0006ogV\u0014\u0017)\u001c2jOJ*b!a/\u0002B\u0006\u0015WCAA_!\u0019iw\"a0\u0002DB\u0019\u0001+!1\u0005\r\u0005-#C1\u0001T!\r\u0001\u0016Q\u0019\u0003\b\u0003\u001f\u0012\"\u0019AAd#\r\ty\f\u0016\u0002\u000fI\t\f\'\u000fJ;1a\u0005\u001bEEY1s+\u0011\ti-!8\u0013\u0007\u0005=WHB\u0003\\\u0003\u0001\ti-\u0002\u0004^\u0003\u001f\u0004\u00111[\u000b\u0005\u0003+\fI\u000e\u0005\u0004n\u001f\u0005]\u00171\u001c\t\u0004!\u0006eGAB=\u0002R\n\u00071\u000bE\u0002Q\u0003;$QAU\nC\u0002M\u0013a\u0001J;3eA\u001aT\u0003BAr\u0003O\u0004D!!:\u0002tB)\u0001+a:\u0002r\u00129\u0011\u0011\u001e\u000bC\u0002\u0005-(!\u0001)\u0016\u0007M\u000bi\u000fB\u0004\u0002p\u0006\u001d(\u0019A*\u0003\u0003}\u00032\u0001UAz\t%\u0011F#!A\u0001\u0002\u000b\u00051K\u0001\u0004%kJ\u0012\u0004\u0007M\u000b\u0005\u0003s\u0014\u0019\u0001\u0005\u0003n\r\u0005m\b\u0003B7\u0015\u0003{,B!a@\u0003\fA)aH\u001aB\u0001\u0015B)\u0001Ka\u0001\u0003\n\u00119\u0011\u0011^\u000bC\u0002\t\u0015QcA*\u0003\b\u00119\u0011q\u001eB\u0002\u0005\u0004\u0019\u0006c\u0001)\u0003\f\u00119\u0011\u0011\u0005B\u0007\u0005\u0004\u0019\u0006b\u0002B\b\u0005#\u0001!\u0011E\u0001\u000by1|7-\u00197!\u001dpvTAB/\u0003\u0014\u0001\u00119BB\u0003\\\u0003\u0001\u0011)BE\u0002\u0003\u0014u*BA!\u0007\u0003 A!QN\u0002B\u000e!\u0015\u0001&1\u0001B\u000f!\r\u0001&q\u0004\u0003\b\u0003C\u0011\tB1\u0001T\u0017\u0001\tQa\u001c9uS\u000e,\"Aa\n\u000f\u0007i\u0012I#C\u0002\u0003,Y\n!b\u00149uS\u000e$UM\u001a8t\u0003\u0019y\u0007\u000f^5dA\u0005!A.\u001a8t\u0003\u0015aWM\\:!\u0003\u0015\u0001(/[:n\u0003\u0019\u0001(/[:nA\u0005\u0019A%\u001e9\u0016\u0005\tmbb\u0001\u001e\u0003>%\u0019!q\b\u001c\u0002\tA\u000bG\u000f[\u0001\u0005IU\u0004\b%A\u0002oCR,\"Aa\u0012\u000f\u0007i\u0012I%C\u0002\u0003LY\n1AT1u\u0003\u0011q\u0017\r\u001e\u0011\u0002\u0007\u0019Lg.\u0006\u0002\u0003T9\u0019!H!\u0016\n\u0007\t]c\'A\u0002GS:\fAAZ5oA\u0005!\u0001o\u001c7z+\t\u0011yFD\u0002;\u0005CJ1Aa\u00197\u0003%\u0001v\u000e\\=EK\u001at7/A\u0003q_2L\bE\u0001\u0004EKB4e\u000eM\n\u0003Iu\u00121aT;u\u0003\u0015\t\u0007\u000f\u001d7z)\t\u0011\t\bE\u0002\u0003t\u0015j\u0011\u0001\n\u0002\u0007\t\u0016\u0004hI\\\u0019\u0016\t\te$qQ\n\u0003Ou\"BA! \u0003\u0002B\u0019!q\u0010\u0015\u000e\u0003\u001dBqAa!*\u0001\u0004\u0011))A\u0001u!\r\u0001&q\u0011\u0003\u0006%\u001e\u0012\ra\u0015\u0002\u0007\t\u0016\u0004hI\u001c\u001a\u0016\r\t5%\u0011\u0014BQ\'\tQS\b\u0006\u0004\u0003\u0012\nU%1\u0014\t\u0004\u0005\'[S\"\u0001\u0016\t\u000f\t\rE\u00061\u0001\u0003\u0018B\u0019\u0001K!\'\u0005\u000bIS#\u0019A*\t\u000f\tuE\u00061\u0001\u0003 \u0006\tQ\u000fE\u0002Q\u0005C#Q!\u001f\u0016C\u0002M\u0013!\"\u0012<fef$\b.\u001b8h+!\u00119Ka/\u0003J\n=\u0007\u0003\u0003BU\u0005W\u0013\u0019L!4\u000f\u00055\u0014\u0013\u0002\u0002BW\u0005_\u0013QaQ1tKFJ1A!-7\u0005\u0015\u0019\u0015m]3t!\u001dQ$Q\u0017B]\u0005\u000fL1Aa.7\u00055)e/\u001a:zi\"LgnZ!vqB\u0019\u0001Ka/\u0005\u000f\tuVF1\u0001\u0003@\n\ta)E\u0002K\u0005\u0003\u00042A\u000fBb\u0013\r\u0011)M\u000e\u0002\u0005!>d\u0017\u0010E\u0002Q\u0005\u0013$qAa3.\u0005\u0004\u0011yLA\u0001L!\r\u0001&q\u001a\u0003\u0006%6\u0012\ra\u0015\u0002\u0010\u0003B\u0004H._#wKJLH\u000f[5oOV!!Q\u001bBo\'\tqS\b\u0006\u0002\u0003ZB!QN\fBn!\r\u0001&Q\u001c\u0003\b\u0005{s#\u0019\u0001B`)\u0011\u0011\tO!;\u0013\t\t\r(Q\u001d\u0004\u00067:\u0002!\u0011\u001d\t\bu\tU&1\u001cBt\u001d\r\u0001&\u0011\u001e\u0005\b\u0005W\u0004\u0004\u0019\u0001Ba\u0003\u0005Y\u0017AC3wKJLH\u000f[5oOR!!\u0011\u001fB}%\u0011\u0011\u0019P!>\u0007\u000bm\u000b\u0001A!=\u0011\t5t#q\u001f\b\u0004!\ne\bb\u0002B~c\u0001\u0007!\u0011Y\u0001\u0002M\nQQI^3ss^DWM]3\u0016\r\r\u000511BB\b!!\u0011IKa+\u0004\u0004\r5\u0001#\u0002\u001e\u0004\u0006\r%\u0011bAB\u0004m\tiQI^3ss^DWM]3Bkb\u00042\u0001UB\u0006\t\u001d\u0011iL\rb\u0001\u0005\u007f\u00032\u0001UB\b\t\u0015\u0011&G1\u0001T\u0003))g/\u001a:zo\",\'/\u001a\u000b\u0005\u0007+\u0019iB\u0005\u0003\u0004\u0018\rea!B.\u0002\u0001\rU\u0001#\u0002\u001e\u0004\u0006\rmab\u0001)\u0004\u001e!9!1`\u001aA\u0002\t\u0005\u0017AD2bG\",G-S7qY&\u001c\u0017\u000e^\u000b\u0005\u0007G\u00199#\u0006\u0002\u0004&A\u0019\u0001ka\n\u0005\u000bI#$\u0019A*)\u000bQ\u001aYca\u0010\u0011\t\r521H\u0007\u0003\u0007_QAa!\r\u00044\u0005A\u0011N\u001c;fe:\fGN\u0003\u0003\u00046\r]\u0012AB7bGJ|7OC\u0002\u0004:}\nqA]3gY\u0016\u001cG/\u0003\u0003\u0004>\r=\"!C7bGJ|\u0017*\u001c9mc\u001dq\"\u0011EB!\u0007\u0003\f\u0014c\bB\u0011\u0007\u0007\u001a9e!\u0017\u0004j\re41RBOc\u0019!#\u0011\u0005\u001d\u0004F\u0005)Q.Y2s_F:aC!\t\u0004J\rE\u0013\'B\u0013\u0004L\r5sBAB\'C\t\u0019y%A\u0006nC\u000e\u0014x.\u00128hS:,\u0017\'B\u0013\u0004T\rUsBAB+C\t\u00199&A\u0013wo9\u0002\u0004\u0005K5na2,W.\u001a8uK\u0012\u0004\u0013N\u001c\u0011TG\u0006d\u0017\r\t\u001a/cEr\u0003\'L\'9SE:aC!\t\u0004\\\r\r\u0014\'B\u0013\u0004^\r}sBAB0C\t\u0019\t\'\u0001\u0005jg\n+h\u000e\u001a7fc\u0015)3QMB4\u001f\t\u00199\'G\u0001\u0002c\u001d1\"\u0011EB6\u0007g\nT!JB7\u0007_z!aa\u001c\"\u0005\rE\u0014AC5t\u00052\f7m\u001b2pqF*Qe!\u001e\u0004x=\u00111qO\r\u0002\u0001E:aC!\t\u0004|\r\r\u0015\'B\u0013\u0004~\r}tBAB@C\t\u0019\t)A\u0005dY\u0006\u001c8OT1nKF*Qe!\"\u0004\b>\u00111qQ\u0011\u0003\u0007\u0013\u000bad\u001d5ba\u0016dWm]:/\u0007\u0006\u001c\u0007.\u001a3J[Bd\u0017nY5u\u001b\u0006\u001c\'o\\:2\u000fY\u0011\tc!$\u0004\u0016F*Qea$\u0004\u0012>\u00111\u0011S\u0011\u0003\u0007\'\u000b!\"\\3uQ>$g*Y7fc\u0015)3qSBM\u001f\t\u0019I*\t\u0002\u0004\u001c\u0006\u00112-Y2iK\u0012LU\u000e\u001d7jG&$\u0018*\u001c9mc\u001d1\"\u0011EBP\u0007O\u000bT!JBQ\u0007G{!aa)\"\u0005\r\u0015\u0016!C:jO:\fG/\u001e:fc\u001dy\"\u0011EBU\u0007o\u000bt\u0001\nB\u0011\u0007W\u001bi+\u0003\u0003\u0004.\u000e=\u0016\u0001\u0002\'jgRTAa!-\u00044\u0006I\u0011.\\7vi\u0006\u0014G.\u001a\u0006\u0004\u0007k{\u0014AC2pY2,7\r^5p]F:qD!\t\u0004:\u000em\u0016g\u0002\u0013\u0003\"\r-6QV\u0019\u0006K\ru6qX\b\u0003\u0007\u007fk\u0012\u0001A\u0019\u0004M\r\r\u0007c\u0001)\u0004(\u0001
    #9 = Utf8               shapeless/package$$eq$colon$bang$eq
   #10 = Class              #9            // shapeless/package$$eq$colon$bang$eq
   #11 = Utf8               $eq$colon$bang$eq
   #12 = Utf8               shapeless/package$$less$colon$bang$less
   #13 = Class              #12           // shapeless/package$$less$colon$bang$less
   #14 = Utf8               $less$colon$bang$less
   #15 = Utf8               shapeless/package$ApplyEverything
   #16 = Class              #15           // shapeless/package$ApplyEverything
   #17 = Utf8               ApplyEverything
   #18 = Utf8               shapeless/package$DepFn0
   #19 = Class              #18           // shapeless/package$DepFn0
   #20 = Utf8               DepFn0
   #21 = Utf8               shapeless/package$DepFn1
   #22 = Class              #21           // shapeless/package$DepFn1
   #23 = Utf8               DepFn1
   #24 = Utf8               shapeless/package$DepFn2
   #25 = Class              #24           // shapeless/package$DepFn2
   #26 = Utf8               DepFn2
   #27 = Utf8               everywhere
   #28 = Utf8               (Lshapeless/Poly;)Lshapeless/EverywhereAux;
   #29 = Utf8               (Lshapeless/Poly;)Lshapeless/EverywhereAux<Lshapeless/Poly;>;
   #30 = Utf8               f
   #31 = Utf8               shapeless/package$
   #32 = Class              #31           // shapeless/package$
   #33 = Utf8               MODULE$
   #34 = Utf8               Lshapeless/package$;
   #35 = NameAndType        #33:#34       // MODULE$:Lshapeless/package$;
   #36 = Fieldref           #32.#35       // shapeless/package$.MODULE$:Lshapeless/package$;
   #37 = NameAndType        #27:#28       // everywhere:(Lshapeless/Poly;)Lshapeless/EverywhereAux;
   #38 = Methodref          #32.#37       // shapeless/package$.everywhere:(Lshapeless/Poly;)Lshapeless/EverywhereAux;
   #39 = Utf8               everything
   #40 = Utf8               (Lshapeless/Poly;)Lshapeless/package$ApplyEverything;
   #41 = Utf8               (Lshapeless/Poly;)Lshapeless/package$ApplyEverything<Lshapeless/Poly;>;
   #42 = NameAndType        #39:#40       // everything:(Lshapeless/Poly;)Lshapeless/package$ApplyEverything;
   #43 = Methodref          #32.#42       // shapeless/package$.everything:(Lshapeless/Poly;)Lshapeless/package$ApplyEverything;
   #44 = Utf8               poly
   #45 = Utf8               ()Lshapeless/PolyDefns$;
   #46 = NameAndType        #44:#45       // poly:()Lshapeless/PolyDefns$;
   #47 = Methodref          #32.#46       // shapeless/package$.poly:()Lshapeless/PolyDefns$;
   #48 = Utf8               fin
   #49 = Utf8               ()Lshapeless/Fin$;
   #50 = NameAndType        #48:#49       // fin:()Lshapeless/Fin$;
   #51 = Methodref          #32.#50       // shapeless/package$.fin:()Lshapeless/Fin$;
   #52 = Utf8               nat
   #53 = Utf8               ()Lshapeless/Nat$;
   #54 = NameAndType        #52:#53       // nat:()Lshapeless/Nat$;
   #55 = Methodref          #32.#54       // shapeless/package$.nat:()Lshapeless/Nat$;
   #56 = Utf8               $up
   #57 = Utf8               ()Lshapeless/Path$;
   #58 = NameAndType        #56:#57       // $up:()Lshapeless/Path$;
   #59 = Methodref          #32.#58       // shapeless/package$.$up:()Lshapeless/Path$;
   #60 = Utf8               prism
   #61 = Utf8               ()Lshapeless/OpticDefns$;
   #62 = NameAndType        #60:#61       // prism:()Lshapeless/OpticDefns$;
   #63 = Methodref          #32.#62       // shapeless/package$.prism:()Lshapeless/OpticDefns$;
   #64 = Utf8               lens
   #65 = NameAndType        #64:#61       // lens:()Lshapeless/OpticDefns$;
   #66 = Methodref          #32.#65       // shapeless/package$.lens:()Lshapeless/OpticDefns$;
   #67 = Utf8               optic
   #68 = NameAndType        #67:#61       // optic:()Lshapeless/OpticDefns$;
   #69 = Methodref          #32.#68       // shapeless/package$.optic:()Lshapeless/OpticDefns$;
   #70 = Utf8               nsubAmbig2
   #71 = Utf8               ()Lshapeless/package$$less$colon$bang$less;
   #72 = Utf8               <A:Ljava/lang/Object;B:Ljava/lang/Object;>()Lshapeless/package$$less$colon$bang$less<TA;TB;>;
   #73 = NameAndType        #70:#71       // nsubAmbig2:()Lshapeless/package$$less$colon$bang$less;
   #74 = Methodref          #32.#73       // shapeless/package$.nsubAmbig2:()Lshapeless/package$$less$colon$bang$less;
   #75 = Utf8               nsubAmbig1
   #76 = NameAndType        #75:#71       // nsubAmbig1:()Lshapeless/package$$less$colon$bang$less;
   #77 = Methodref          #32.#76       // shapeless/package$.nsubAmbig1:()Lshapeless/package$$less$colon$bang$less;
   #78 = Utf8               nsub
   #79 = NameAndType        #78:#71       // nsub:()Lshapeless/package$$less$colon$bang$less;
   #80 = Methodref          #32.#79       // shapeless/package$.nsub:()Lshapeless/package$$less$colon$bang$less;
   #81 = Utf8               neqAmbig2
   #82 = Utf8               ()Lshapeless/package$$eq$colon$bang$eq;
   #83 = Utf8               <A:Ljava/lang/Object;>()Lshapeless/package$$eq$colon$bang$eq<TA;TA;>;
   #84 = NameAndType        #81:#82       // neqAmbig2:()Lshapeless/package$$eq$colon$bang$eq;
   #85 = Methodref          #32.#84       // shapeless/package$.neqAmbig2:()Lshapeless/package$$eq$colon$bang$eq;
   #86 = Utf8               neqAmbig1
   #87 = NameAndType        #86:#82       // neqAmbig1:()Lshapeless/package$$eq$colon$bang$eq;
   #88 = Methodref          #32.#87       // shapeless/package$.neqAmbig1:()Lshapeless/package$$eq$colon$bang$eq;
   #89 = Utf8               neq
   #90 = Utf8               <A:Ljava/lang/Object;B:Ljava/lang/Object;>()Lshapeless/package$$eq$colon$bang$eq<TA;TB;>;
   #91 = NameAndType        #89:#82       // neq:()Lshapeless/package$$eq$colon$bang$eq;
   #92 = Methodref          #32.#91       // shapeless/package$.neq:()Lshapeless/package$$eq$colon$bang$eq;
   #93 = Utf8               unexpected
   #94 = Utf8               ()Lscala/runtime/Nothing$;
   #95 = NameAndType        #93:#94       // unexpected:()Lscala/runtime/Nothing$;
   #96 = Methodref          #32.#95       // shapeless/package$.unexpected:()Lscala/runtime/Nothing$;
   #97 = Utf8               Code
   #98 = Utf8               Signature
   #99 = Utf8               MethodParameters
  #100 = Utf8               InnerClasses
  #101 = Utf8               SourceFile
  #102 = Utf8               RuntimeVisibleAnnotations
  #103 = Utf8               ScalaSig
{
  public static shapeless.EverywhereAux<shapeless.Poly> everywhere(shapeless.Poly);
    descriptor: (Lshapeless/Poly;)Lshapeless/EverywhereAux;
    flags: (0x0009) ACC_PUBLIC, ACC_STATIC
    Code:
      stack=2, locals=1, args_size=1
         0: getstatic     #36                 // Field shapeless/package$.MODULE$:Lshapeless/package$;
         3: aload_0
         4: invokevirtual #38                 // Method shapeless/package$.everywhere:(Lshapeless/Poly;)Lshapeless/EverywhereAux;
         7: areturn
    Signature: #29                          // (Lshapeless/Poly;)Lshapeless/EverywhereAux<Lshapeless/Poly;>;
    MethodParameters:
      Name                           Flags
      f                              final

  public static shapeless.package$ApplyEverything<shapeless.Poly> everything(shapeless.Poly);
    descriptor: (Lshapeless/Poly;)Lshapeless/package$ApplyEverything;
    flags: (0x0009) ACC_PUBLIC, ACC_STATIC
    Code:
      stack=2, locals=1, args_size=1
         0: getstatic     #36                 // Field shapeless/package$.MODULE$:Lshapeless/package$;
         3: aload_0
         4: invokevirtual #43                 // Method shapeless/package$.everything:(Lshapeless/Poly;)Lshapeless/package$ApplyEverything;
         7: areturn
    Signature: #41                          // (Lshapeless/Poly;)Lshapeless/package$ApplyEverything<Lshapeless/Poly;>;
    MethodParameters:
      Name                           Flags
      f                              final

  public static shapeless.PolyDefns$ poly();
    descriptor: ()Lshapeless/PolyDefns$;
    flags: (0x0009) ACC_PUBLIC, ACC_STATIC
    Code:
      stack=1, locals=0, args_size=0
         0: getstatic     #36                 // Field shapeless/package$.MODULE$:Lshapeless/package$;
         3: invokevirtual #47                 // Method shapeless/package$.poly:()Lshapeless/PolyDefns$;
         6: areturn

  public static shapeless.Fin$ fin();
    descriptor: ()Lshapeless/Fin$;
    flags: (0x0009) ACC_PUBLIC, ACC_STATIC
    Code:
      stack=1, locals=0, args_size=0
         0: getstatic     #36                 // Field shapeless/package$.MODULE$:Lshapeless/package$;
         3: invokevirtual #51                 // Method shapeless/package$.fin:()Lshapeless/Fin$;
         6: areturn

  public static shapeless.Nat$ nat();
    descriptor: ()Lshapeless/Nat$;
    flags: (0x0009) ACC_PUBLIC, ACC_STATIC
    Code:
      stack=1, locals=0, args_size=0
         0: getstatic     #36                 // Field shapeless/package$.MODULE$:Lshapeless/package$;
         3: invokevirtual #55                 // Method shapeless/package$.nat:()Lshapeless/Nat$;
         6: areturn

  public static shapeless.Path$ $up();
    descriptor: ()Lshapeless/Path$;
    flags: (0x0009) ACC_PUBLIC, ACC_STATIC
    Code:
      stack=1, locals=0, args_size=0
         0: getstatic     #36                 // Field shapeless/package$.MODULE$:Lshapeless/package$;
         3: invokevirtual #59                 // Method shapeless/package$.$up:()Lshapeless/Path$;
         6: areturn

  public static shapeless.OpticDefns$ prism();
    descriptor: ()Lshapeless/OpticDefns$;
    flags: (0x0009) ACC_PUBLIC, ACC_STATIC
    Code:
      stack=1, locals=0, args_size=0
         0: getstatic     #36                 // Field shapeless/package$.MODULE$:Lshapeless/package$;
         3: invokevirtual #63                 // Method shapeless/package$.prism:()Lshapeless/OpticDefns$;
         6: areturn

  public static shapeless.OpticDefns$ lens();
    descriptor: ()Lshapeless/OpticDefns$;
    flags: (0x0009) ACC_PUBLIC, ACC_STATIC
    Code:
      stack=1, locals=0, args_size=0
         0: getstatic     #36                 // Field shapeless/package$.MODULE$:Lshapeless/package$;
         3: invokevirtual #66                 // Method shapeless/package$.lens:()Lshapeless/OpticDefns$;
         6: areturn

  public static shapeless.OpticDefns$ optic();
    descriptor: ()Lshapeless/OpticDefns$;
    flags: (0x0009) ACC_PUBLIC, ACC_STATIC
    Code:
      stack=1, locals=0, args_size=0
         0: getstatic     #36                 // Field shapeless/package$.MODULE$:Lshapeless/package$;
         3: invokevirtual #69                 // Method shapeless/package$.optic:()Lshapeless/OpticDefns$;
         6: areturn

  public static <A extends java.lang.Object, B extends java.lang.Object> shapeless.package$$less$colon$bang$less<A, B> nsubAmbig2();
    descriptor: ()Lshapeless/package$$less$colon$bang$less;
    flags: (0x0009) ACC_PUBLIC, ACC_STATIC
    Code:
      stack=1, locals=0, args_size=0
         0: getstatic     #36                 // Field shapeless/package$.MODULE$:Lshapeless/package$;
         3: invokevirtual #74                 // Method shapeless/package$.nsubAmbig2:()Lshapeless/package$$less$colon$bang$less;
         6: areturn
    Signature: #72                          // <A:Ljava/lang/Object;B:Ljava/lang/Object;>()Lshapeless/package$$less$colon$bang$less<TA;TB;>;

  public static <A extends java.lang.Object, B extends java.lang.Object> shapeless.package$$less$colon$bang$less<A, B> nsubAmbig1();
    descriptor: ()Lshapeless/package$$less$colon$bang$less;
    flags: (0x0009) ACC_PUBLIC, ACC_STATIC
    Code:
      stack=1, locals=0, args_size=0
         0: getstatic     #36                 // Field shapeless/package$.MODULE$:Lshapeless/package$;
         3: invokevirtual #77                 // Method shapeless/package$.nsubAmbig1:()Lshapeless/package$$less$colon$bang$less;
         6: areturn
    Signature: #72                          // <A:Ljava/lang/Object;B:Ljava/lang/Object;>()Lshapeless/package$$less$colon$bang$less<TA;TB;>;

  public static <A extends java.lang.Object, B extends java.lang.Object> shapeless.package$$less$colon$bang$less<A, B> nsub();
    descriptor: ()Lshapeless/package$$less$colon$bang$less;
    flags: (0x0009) ACC_PUBLIC, ACC_STATIC
    Code:
      stack=1, locals=0, args_size=0
         0: getstatic     #36                 // Field shapeless/package$.MODULE$:Lshapeless/package$;
         3: invokevirtual #80                 // Method shapeless/package$.nsub:()Lshapeless/package$$less$colon$bang$less;
         6: areturn
    Signature: #72                          // <A:Ljava/lang/Object;B:Ljava/lang/Object;>()Lshapeless/package$$less$colon$bang$less<TA;TB;>;

  public static <A extends java.lang.Object> shapeless.package$$eq$colon$bang$eq<A, A> neqAmbig2();
    descriptor: ()Lshapeless/package$$eq$colon$bang$eq;
    flags: (0x0009) ACC_PUBLIC, ACC_STATIC
    Code:
      stack=1, locals=0, args_size=0
         0: getstatic     #36                 // Field shapeless/package$.MODULE$:Lshapeless/package$;
         3: invokevirtual #85                 // Method shapeless/package$.neqAmbig2:()Lshapeless/package$$eq$colon$bang$eq;
         6: areturn
    Signature: #83                          // <A:Ljava/lang/Object;>()Lshapeless/package$$eq$colon$bang$eq<TA;TA;>;

  public static <A extends java.lang.Object> shapeless.package$$eq$colon$bang$eq<A, A> neqAmbig1();
    descriptor: ()Lshapeless/package$$eq$colon$bang$eq;
    flags: (0x0009) ACC_PUBLIC, ACC_STATIC
    Code:
      stack=1, locals=0, args_size=0
         0: getstatic     #36                 // Field shapeless/package$.MODULE$:Lshapeless/package$;
         3: invokevirtual #88                 // Method shapeless/package$.neqAmbig1:()Lshapeless/package$$eq$colon$bang$eq;
         6: areturn
    Signature: #83                          // <A:Ljava/lang/Object;>()Lshapeless/package$$eq$colon$bang$eq<TA;TA;>;

  public static <A extends java.lang.Object, B extends java.lang.Object> shapeless.package$$eq$colon$bang$eq<A, B> neq();
    descriptor: ()Lshapeless/package$$eq$colon$bang$eq;
    flags: (0x0009) ACC_PUBLIC, ACC_STATIC
    Code:
      stack=1, locals=0, args_size=0
         0: getstatic     #36                 // Field shapeless/package$.MODULE$:Lshapeless/package$;
         3: invokevirtual #92                 // Method shapeless/package$.neq:()Lshapeless/package$$eq$colon$bang$eq;
         6: areturn
    Signature: #90                          // <A:Ljava/lang/Object;B:Ljava/lang/Object;>()Lshapeless/package$$eq$colon$bang$eq<TA;TB;>;

  public static scala.runtime.Nothing$ unexpected();
    descriptor: ()Lscala/runtime/Nothing$;
    flags: (0x0009) ACC_PUBLIC, ACC_STATIC
    Code:
      stack=1, locals=0, args_size=0
         0: getstatic     #36                 // Field shapeless/package$.MODULE$:Lshapeless/package$;
         3: invokevirtual #96                 // Method shapeless/package$.unexpected:()Lscala/runtime/Nothing$;
         6: areturn
}
InnerClasses:
  public static #11= #10 of #2;           // $eq$colon$bang$eq=class shapeless/package$$eq$colon$bang$eq of class shapeless/package
  public static #14= #13 of #2;           // $less$colon$bang$less=class shapeless/package$$less$colon$bang$less of class shapeless/package
  public static #17= #16 of #2;           // ApplyEverything=class shapeless/package$ApplyEverything of class shapeless/package
  public static #20= #19 of #2;           // DepFn0=class shapeless/package$DepFn0 of class shapeless/package
  public static #23= #22 of #2;           // DepFn1=class shapeless/package$DepFn1 of class shapeless/package
  public static #26= #25 of #2;           // DepFn2=class shapeless/package$DepFn2 of class shapeless/package
SourceFile: "package.scala"
RuntimeVisibleAnnotations:
  0: #6(#7=s#8)
    scala.reflect.ScalaSignature(
      bytes="\u0006\u0005\r\u0015w!B\u001b7\u0011\u0003Id!B\u001e7\u0011\u0003a\u0004\"\u0002$\u0002\t\u00039\u0005\"\u0002%\u0002\t\u0003IU\u0001B\'\u0002\u00019+AaV\u0001\u00011\u0016!1-\u0001\u0001e\u000b\u0011Q\u0017\u0001A6\u0006\tE\f\u0001A]\u0003\u0005u\u0006\u000110\u0002\u0004\u0002\n\u0005\u0001\u00111\u0002\u0004\n\u0003[\t\u0001\u0013aI\u0001\u0003_Aq!!\u0015\u0002\t\u0007\t\u0019\u0006C\u0004\u0002b\u0005!\u0019!a\u0019\t\u000f\u00055\u0014\u0001b\u0001\u0002p\u0019I\u0011\u0011P\u0001\u0011\u0002G\u0005\u00111\u0010\u0005\b\u0003+\u000bA1AAL\u0011\u001d\t)+\u0001C\u0002\u0003OCq!a.\u0002\t\u0007\tI,\u0002\u0004\u0002J\u0006\u0001\u00111Z\u0003\u0007\u0003?\f\u0001!!9\u0006\r\u0005U\u0018\u0001AA|\u0011%\u0011\u0019#\u0001b\u0001\n\u0003\u0011)\u0003\u0003\u0005\u0003.\u0005\u0001\u000b\u0011\u0002B\u0014\u0011%\u0011y#\u0001b\u0001\n\u0003\u0011)\u0003\u0003\u0005\u00032\u0005\u0001\u000b\u0011\u0002B\u0014\u0011%\u0011\u0019$\u0001b\u0001\n\u0003\u0011)\u0003\u0003\u0005\u00036\u0005\u0001\u000b\u0011\u0002B\u0014\u0011%\u00119$\u0001b\u0001\n\u0003\u0011I\u0004\u0003\u0005\u0003B\u0005\u0001\u000b\u0011\u0002B\u001e\u0011%\u0011\u0019%\u0001b\u0001\n\u0003\u0011)\u0005\u0003\u0005\u0003N\u0005\u0001\u000b\u0011\u0002B$\u0011%\u0011y%\u0001b\u0001\n\u0003\u0011\t\u0006\u0003\u0005\u0003Z\u0005\u0001\u000b\u0011\u0002B*\u0011%\u0011Y&\u0001b\u0001\n\u0003\u0011i\u0006\u0003\u0005\u0003f\u0005\u0001\u000b\u0011\u0002B0\r%\u00119\'\u0001I\u0001$\u0003\u0011I\u0007\u0002\u0004\u0003l\u0011\u0012\ta\u0015\u0005\b\u0005[\"c\u0011\u0001B8\r%\u0011)(\u0001I\u0001$\u0003\u00119\b\u0002\u0004\u0003l\u001d\u0012\ta\u0015\u0005\b\u0005[:c\u0011\u0001B>\r%\u0011I)\u0001I\u0001$\u0003\u0011Y\t\u0002\u0004\u0003l)\u0012\ta\u0015\u0005\b\u0005[Rc\u0011\u0001BH\u000b\u0019\u0011\u0019+\u0001\u0001\u0003&\u001a1!\u0011[\u0001\u0001\u0005\'DaA\u0012\u0018\u0005\u0002\t]\u0007b\u0002B7]\u0011\u0005!q\u001c\u0005\b\u0005[\fA\u0011\u0001Bx\u000b\u0019\u0011i0\u0001\u0001\u0003\u0000\"91\u0011C\u0001\u0005\u0002\rM\u0001\u0002CB\u0010\u0003\t%\ta!\t\u0002\u000fA\f7m[1hK*\tq\'A\u0005tQ\u0006\u0004X\r\\3tg\u000e\u0001\u0001C\u0001\u001e\u0002\u001b\u00051$a\u00029bG.\fw-Z\n\u0004\u0003u\u001a\u0005C\u0001 B\u001b\u0005y$\"\u0001!\u0002\u000bM\u001c\u0017\r\\1\n\u0005\t{$AB!osJ+g\r\u0005\u0002;\t&\u0011QI\u000e\u0002\u0016\'\u000e\fG.\u0019,feNLwN\\*qK\u000eLg-[2t\u0003\u0019a\u0014N\\5u}Q\t\u0011(\u0001\u0006v]\u0016D\b/Z2uK\u0012,\u0012A\u0013\t\u0003}-K!\u0001T \u0003\u000f9{G\u000f[5oO\n\u0011\u0011\nZ\u000b\u0003\u001fF\u0003\"\u0001U)\r\u0001\u00111!\u000b\u0002CC\u0002M\u0013\u0011\u0001V\t\u0003\u0015R\u0003\"AP+\n\u0005Y{$aA!os\n)1i\u001c8tiV\u0011\u0011\f\u0019\n\u00035v2AaW\u0001\u00013\naAH]3gS:,W.\u001a8u}\u0015!QL\u0017\u0001_\u0005\tq=8\u0006\u0002`EB\u0011\u0001\u000b\u0019\u0003\u0006C\u0016\u0011\ra\u0015\u0002\u0002\u0007\u0012)!\u000b\u0018b\u0001\'\n1A%\u001e\u00191\u0003\u000e+\"!Z5\u0011\ty2\u0007NS\u0005\u0003O~\u0012\u0011BR;oGRLwN\\\u0019\u0011\u0005AKG!\u0002*\u0007\u0005\u0004\u0019&\u0001\u0004\u0013vaA\n5\tJ;1a\u0005\u001bUC\u00017q!\rigA\\\u0007\u0002\u0003A\u0019QNB8\u0011\u0005A\u0003H!\u0002*\b\u0005\u0004\u0019&A\u0002\u0013veI\u0012t\'F\u0002tmb\u00142\u0001^;x\r\u0011Y\u0016\u0001A:\u0011\u0005A3H!\u0002*\t\u0005\u0004\u0019\u0006C\u0001)y\t\u0015I\bB1\u0001T\u0005\u0005)&A\u0002\u0013veI\u0012\u0004(F\u0003}\u0003\u0003\t9\u0001E\u0002n\ru\u0004R!\u001c\u0005\u007f\u0003\u0007\u00012!\u001c\u0004\u0000!\r\u0001\u0016\u0011\u0001\u0003\u0006%&\u0011\ra\u0015\t\u0005[\u001a\t)\u0001E\u0002Q\u0003\u000f!Q!_\u0005C\u0002M\u0013a\u0002\n2be\u0012*(G\r\u001a9I\t\f\'/\u0006\u0004\u0002\u000e\u0005\u001d\u00121\u0006\n\u0004\u0003\u001fid!B.\u0002\u0001\u00055QAB/\u0002\u0010\u0001\t\u0019\"\u0006\u0003\u0002\u0016\u0005}\u0001c\u0002 \u0002\u0018\u0005m\u00111E\u0005\u0004\u00033y$\u0001\u0005\u0013mKN\u001cHeY8m_:$C.Z:t!\u0011iw!!\b\u0011\u0007A\u000by\u0002B\u0004\u0002\"\u0005E!\u0019A*\u0003\u0003a\u0003b!\\\u0005\u0002&\u0005%\u0002c\u0001)\u0002(\u0011)!K\u0003b\u0001\'B\u0019\u0001+a\u000b\u0005\u000beT!\u0019A*\u0003#\u0011*\u0017\u000fJ2pY>tGEY1oO\u0012*\u0017/\u0006\u0004\u00022\u0005%\u0013QJ\n\u0005\u0017u\n\u0019\u0004\u0005\u0003\u00026\u0005\rc\u0002BA\u001c\u0003\u0003rA!!\u000f\u0002@5\u0011\u00111\b\u0006\u0004\u0003{A\u0014A\u0002\u001fs_>$h(C\u0001A\u0013\t)t(\u0003\u0003\u0002F\u0005\u001d#\u0001D*fe&\fG.\u001b>bE2,\'BA\u001b@\t\u0019\tYe\u0003b\u0001\'\n\t\u0011\t\u0002\u0004\u0002P-\u0011\ra\u0015\u0002\u0002\u0005\u0006\u0019a.Z9\u0016\r\u0005U\u00131LA0+\t\t9\u0006\u0005\u0004n\u0017\u0005e\u0013Q\f\t\u0004!\u0006mCABA&\u0019\t\u00071\u000bE\u0002Q\u0003?\"a!a\u0014\r\u0005\u0004\u0019\u0016!\u00038fc\u0006k\'-[42+\u0011\t)\'a\u001b\u0016\u0005\u0005\u001d\u0004CB7\f\u0003S\nI\u0007E\u0002Q\u0003W\"a!a\u0013\u000e\u0005\u0004\u0019\u0016!\u00038fc\u0006k\'-[43+\u0011\t\t(a\u001e\u0016\u0005\u0005M\u0004CB7\f\u0003k\n)\bE\u0002Q\u0003o\"a!a\u0013\u000f\u0005\u0004\u0019&!\u0006\u0013mKN\u001cHeY8m_:$#-\u00198hI1,7o]\u000b\u0007\u0003{\ny(!!\u0014\t=i\u00141\u0007\u0003\u0007\u0003\u0017z!\u0019A*\u0005\r\u0005=sB1\u0001TQ\u0015y\u0011QQAI!\u0011\t9)!$\u000e\u0005\u0005%%bAAF\u007f\u0005Q\u0011M\u001c8pi\u0006$\u0018n\u001c8\n\t\u0005=\u0015\u0011\u0012\u0002\u0011S6\u0004H.[2ji:{GOR8v]\u0012\f#!a%\u0002E\u0011Z\u0018) \u0011nkN$\bE\\8uA\t,\u0007%\u0019\u0011tk\n$\u0018\u0010]3!_\u001a\u0004Ce\u001f\"~\u0003\u0011q7/\u001e2\u0016\r\u0005e\u0015qTAR+\t\tY\n\u0005\u0004n\u001f\u0005u\u0015\u0011\u0015\t\u0004!\u0006}EABA&!\t\u00071\u000bE\u0002Q\u0003G#a!a\u0014\u0011\u0005\u0004\u0019\u0016A\u00038tk\n\fUNY5hcU1\u0011\u0011VAX\u0003g+\"!a+\u0011\r5|\u0011QVAY!\r\u0001\u0016q\u0016\u0003\u0007\u0003\u0017\n\"\u0019A*\u0011\u0007A\u000b\u0019\fB\u0004\u0002PE\u0011\r!!.\u0012\u0007\u00055F+\u0001\u0006ogV\u0014\u0017)\u001c2jOJ*b!a/\u0002B\u0006\u0015WCAA_!\u0019iw\"a0\u0002DB\u0019\u0001+!1\u0005\r\u0005-#C1\u0001T!\r\u0001\u0016Q\u0019\u0003\b\u0003\u001f\u0012\"\u0019AAd#\r\ty\f\u0016\u0002\u000fI\t\f\'\u000fJ;1a\u0005\u001bEEY1s+\u0011\ti-!8\u0013\u0007\u0005=WHB\u0003\\\u0003\u0001\ti-\u0002\u0004^\u0003\u001f\u0004\u00111[\u000b\u0005\u0003+\fI\u000e\u0005\u0004n\u001f\u0005]\u00171\u001c\t\u0004!\u0006eGAB=\u0002R\n\u00071\u000bE\u0002Q\u0003;$QAU\nC\u0002M\u0013a\u0001J;3eA\u001aT\u0003BAr\u0003O\u0004D!!:\u0002tB)\u0001+a:\u0002r\u00129\u0011\u0011\u001e\u000bC\u0002\u0005-(!\u0001)\u0016\u0007M\u000bi\u000fB\u0004\u0002p\u0006\u001d(\u0019A*\u0003\u0003}\u00032\u0001UAz\t%\u0011F#!A\u0001\u0002\u000b\u00051K\u0001\u0004%kJ\u0012\u0004\u0007M\u000b\u0005\u0003s\u0014\u0019\u0001\u0005\u0003n\r\u0005m\b\u0003B7\u0015\u0003{,B!a@\u0003\fA)aH\u001aB\u0001\u0015B)\u0001Ka\u0001\u0003\n\u00119\u0011\u0011^\u000bC\u0002\t\u0015QcA*\u0003\b\u00119\u0011q\u001eB\u0002\u0005\u0004\u0019\u0006c\u0001)\u0003\f\u00119\u0011\u0011\u0005B\u0007\u0005\u0004\u0019\u0006b\u0002B\b\u0005#\u0001!\u0011E\u0001\u000by1|7-\u00197!\u001dpvTAB/\u0003\u0014\u0001\u00119BB\u0003\\\u0003\u0001\u0011)BE\u0002\u0003\u0014u*BA!\u0007\u0003 A!QN\u0002B\u000e!\u0015\u0001&1\u0001B\u000f!\r\u0001&q\u0004\u0003\b\u0003C\u0011\tB1\u0001T\u0017\u0001\tQa\u001c9uS\u000e,\"Aa\n\u000f\u0007i\u0012I#C\u0002\u0003,Y\n!b\u00149uS\u000e$UM\u001a8t\u0003\u0019y\u0007\u000f^5dA\u0005!A.\u001a8t\u0003\u0015aWM\\:!\u0003\u0015\u0001(/[:n\u0003\u0019\u0001(/[:nA\u0005\u0019A%\u001e9\u0016\u0005\tmbb\u0001\u001e\u0003>%\u0019!q\b\u001c\u0002\tA\u000bG\u000f[\u0001\u0005IU\u0004\b%A\u0002oCR,\"Aa\u0012\u000f\u0007i\u0012I%C\u0002\u0003LY\n1AT1u\u0003\u0011q\u0017\r\u001e\u0011\u0002\u0007\u0019Lg.\u0006\u0002\u0003T9\u0019!H!\u0016\n\u0007\t]c\'A\u0002GS:\fAAZ5oA\u0005!\u0001o\u001c7z+\t\u0011yFD\u0002;\u0005CJ1Aa\u00197\u0003%\u0001v\u000e\\=EK\u001at7/A\u0003q_2L\bE\u0001\u0004EKB4e\u000eM\n\u0003Iu\u00121aT;u\u0003\u0015\t\u0007\u000f\u001d7z)\t\u0011\t\bE\u0002\u0003t\u0015j\u0011\u0001\n\u0002\u0007\t\u0016\u0004hI\\\u0019\u0016\t\te$qQ\n\u0003Ou\"BA! \u0003\u0002B\u0019!q\u0010\u0015\u000e\u0003\u001dBqAa!*\u0001\u0004\u0011))A\u0001u!\r\u0001&q\u0011\u0003\u0006%\u001e\u0012\ra\u0015\u0002\u0007\t\u0016\u0004hI\u001c\u001a\u0016\r\t5%\u0011\u0014BQ\'\tQS\b\u0006\u0004\u0003\u0012\nU%1\u0014\t\u0004\u0005\'[S\"\u0001\u0016\t\u000f\t\rE\u00061\u0001\u0003\u0018B\u0019\u0001K!\'\u0005\u000bIS#\u0019A*\t\u000f\tuE\u00061\u0001\u0003 \u0006\tQ\u000fE\u0002Q\u0005C#Q!\u001f\u0016C\u0002M\u0013!\"\u0012<fef$\b.\u001b8h+!\u00119Ka/\u0003J\n=\u0007\u0003\u0003BU\u0005W\u0013\u0019L!4\u000f\u00055\u0014\u0013\u0002\u0002BW\u0005_\u0013QaQ1tKFJ1A!-7\u0005\u0015\u0019\u0015m]3t!\u001dQ$Q\u0017B]\u0005\u000fL1Aa.7\u00055)e/\u001a:zi\"LgnZ!vqB\u0019\u0001Ka/\u0005\u000f\tuVF1\u0001\u0003@\n\ta)E\u0002K\u0005\u0003\u00042A\u000fBb\u0013\r\u0011)M\u000e\u0002\u0005!>d\u0017\u0010E\u0002Q\u0005\u0013$qAa3.\u0005\u0004\u0011yLA\u0001L!\r\u0001&q\u001a\u0003\u0006%6\u0012\ra\u0015\u0002\u0010\u0003B\u0004H._#wKJLH\u000f[5oOV!!Q\u001bBo\'\tqS\b\u0006\u0002\u0003ZB!QN\fBn!\r\u0001&Q\u001c\u0003\b\u0005{s#\u0019\u0001B`)\u0011\u0011\tO!;\u0013\t\t\r(Q\u001d\u0004\u00067:\u0002!\u0011\u001d\t\bu\tU&1\u001cBt\u001d\r\u0001&\u0011\u001e\u0005\b\u0005W\u0004\u0004\u0019\u0001Ba\u0003\u0005Y\u0017AC3wKJLH\u000f[5oOR!!\u0011\u001fB}%\u0011\u0011\u0019P!>\u0007\u000bm\u000b\u0001A!=\u0011\t5t#q\u001f\b\u0004!\ne\bb\u0002B~c\u0001\u0007!\u0011Y\u0001\u0002M\nQQI^3ss^DWM]3\u0016\r\r\u000511BB\b!!\u0011IKa+\u0004\u0004\r5\u0001#\u0002\u001e\u0004\u0006\r%\u0011bAB\u0004m\tiQI^3ss^DWM]3Bkb\u00042\u0001UB\u0006\t\u001d\u0011iL\rb\u0001\u0005\u007f\u00032\u0001UB\b\t\u0015\u0011&G1\u0001T\u0003))g/\u001a:zo\",\'/\u001a\u000b\u0005\u0007+\u0019iB\u0005\u0003\u0004\u0018\rea!B.\u0002\u0001\rU\u0001#\u0002\u001e\u0004\u0006\rmab\u0001)\u0004\u001e!9!1`\u001aA\u0002\t\u0005\u0017AD2bG\",G-S7qY&\u001c\u0017\u000e^\u000b\u0005\u0007G\u00199#\u0006\u0002\u0004&A\u0019\u0001ka\n\u0005\u000bI#$\u0019A*)\u000bQ\u001aYca\u0010\u0011\t\r521H\u0007\u0003\u0007_QAa!\r\u00044\u0005A\u0011N\u001c;fe:\fGN\u0003\u0003\u00046\r]\u0012AB7bGJ|7OC\u0002\u0004:}\nqA]3gY\u0016\u001cG/\u0003\u0003\u0004>\r=\"!C7bGJ|\u0017*\u001c9mc\u001dq\"\u0011EB!\u0007\u0003\f\u0014c\bB\u0011\u0007\u0007\u001a9e!\u0017\u0004j\re41RBOc\u0019!#\u0011\u0005\u001d\u0004F\u0005)Q.Y2s_F:aC!\t\u0004J\rE\u0013\'B\u0013\u0004L\r5sBAB\'C\t\u0019y%A\u0006nC\u000e\u0014x.\u00128hS:,\u0017\'B\u0013\u0004T\rUsBAB+C\t\u00199&A\u0013wo9\u0002\u0004\u0005K5na2,W.\u001a8uK\u0012\u0004\u0013N\u001c\u0011TG\u0006d\u0017\r\t\u001a/cEr\u0003\'L\'9SE:aC!\t\u0004\\\r\r\u0014\'B\u0013\u0004^\r}sBAB0C\t\u0019\t\'\u0001\u0005jg\n+h\u000e\u001a7fc\u0015)3QMB4\u001f\t\u00199\'G\u0001\u0002c\u001d1\"\u0011EB6\u0007g\nT!JB7\u0007_z!aa\u001c\"\u0005\rE\u0014AC5t\u00052\f7m\u001b2pqF*Qe!\u001e\u0004x=\u00111qO\r\u0002\u0001E:aC!\t\u0004|\r\r\u0015\'B\u0013\u0004~\r}tBAB@C\t\u0019\t)A\u0005dY\u0006\u001c8OT1nKF*Qe!\"\u0004\b>\u00111qQ\u0011\u0003\u0007\u0013\u000bad\u001d5ba\u0016dWm]:/\u0007\u0006\u001c\u0007.\u001a3J[Bd\u0017nY5u\u001b\u0006\u001c\'o\\:2\u000fY\u0011\tc!$\u0004\u0016F*Qea$\u0004\u0012>\u00111\u0011S\u0011\u0003\u0007\'\u000b!\"\\3uQ>$g*Y7fc\u0015)3qSBM\u001f\t\u0019I*\t\u0002\u0004\u001c\u0006\u00112-Y2iK\u0012LU\u000e\u001d7jG&$\u0018*\u001c9mc\u001d1\"\u0011EBP\u0007O\u000bT!JBQ\u0007G{!aa)\"\u0005\r\u0015\u0016!C:jO:\fG/\u001e:fc\u001dy\"\u0011EBU\u0007o\u000bt\u0001\nB\u0011\u0007W\u001bi+\u0003\u0003\u0004.\u000e=\u0016\u0001\u0002\'jgRTAa!-\u00044\u0006I\u0011.\\7vi\u0006\u0014G.\u001a\u0006\u0004\u0007k{\u0014AC2pY2,7\r^5p]F:qD!\t\u0004:\u000em\u0016g\u0002\u0013\u0003\"\r-6QV\u0019\u0006K\ru6qX\b\u0003\u0007\u007fk\u0012\u0001A\u0019\u0004M\r\r\u0007c\u0001)\u0004(\u0001"
    )
  ScalaSig: length = 0x3 (unknown attribute)
   05 02 00
