Classfile /Users/mw/Projects/slang-braindump/.jar/jar8/assemble/slang-braindump/assemble/content/shapeless/Path.class
  Last modified May 29, 2022; size 2400 bytes
  SHA-256 checksum 6344962537fdff69e6c29cc88f02ac7ce31914e0b16597f16e226a620c5ec14c
  Compiled from "lenses.scala"
public interface shapeless.Path<T extends shapeless.HList> extends shapeless.LPPath<T>
  minor version: 0
  major version: 52
  flags: (0x0601) ACC_PUBLIC, ACC_INTERFACE, ACC_ABSTRACT
  this_class: #2                          // shapeless/Path
  super_class: #5                         // java/lang/Object
  interfaces: 1, fields: 0, methods: 5, attributes: 6
Constant pool:
   #1 = Utf8               shapeless/Path
   #2 = Class              #1             // shapeless/Path
   #3 = Utf8               <T::Lshapeless/HList;>Ljava/lang/Object;Lshapeless/LPPath<TT;>;
   #4 = Utf8               java/lang/Object
   #5 = Class              #4             // java/lang/Object
   #6 = Utf8               shapeless/LPPath
   #7 = Class              #6             // shapeless/LPPath
   #8 = Utf8               lenses.scala
   #9 = Utf8               Lscala/reflect/ScalaSignature;
  #10 = Utf8               bytes
  #11 = Utf8               \u0006\u0005}4qa\u0003\u0007\u0011\u0002\u0007\u0005q\u0002C\u0003\'\u0001\u0011\u0005q%\u0002\u0003,\u0001\u0001aS\u0001B\u0017\u0001\u0001m)AA\f\u0001\u0001_\u0015!Q\t\u0001\u0001G\u0011\u0015q\u0005\u0001\"\u0001P\u0011\u0015Y\u0006\u0001\"\u0001]\u000f\u00151H\u0002#\u0001x\r\u0015YA\u0002#\u0001y\u0011\u0015i\u0018\u0002\"\u0001\u007f\u0005\u0011\u0001\u0016\r\u001e5\u000b\u00035\t\u0011b\u001d5ba\u0016dWm]:\u0004\u0001U\u0011\u0001#H\n\u0004\u0001E9\u0002C\u0001\n\u0016\u001b\u0005\u0019\"\"\u0001\u000b\u0002\u000bM\u001c\u0017\r\\1\n\u0005Y\u0019\"AB!osJ+g\rE\u0002\u00193mi\u0011\u0001D\u0005\u000351\u0011a\u0001\u0014)QCRD\u0007C\u0001\u000f\u001e\u0019\u0001!QA\b\u0001C\u0002}\u0011\u0011\u0001V\t\u0003A\r\u0002\"AE\u0011\n\u0005\t\u001a\"a\u0002(pi\"Lgn\u001a\t\u00031\u0011J!!\n\u0007\u0003\u000b!c\u0015n\u001d;\u0002\r\u0011Jg.\u001b;%)\u0005A\u0003C\u0001\n*\u0013\tQ3C\u0001\u0003V]&$(!\u0001)\u0011\u0007a\u00011DA\u0001M\u0005\u0011aUM\\:\u0016\u0007AJ4\tE\u00032iar\u0004I\u0004\u0002\u0019e%\u00111\u0007D\u0001\f\u001b.\u0004\u0016\r\u001e5PaRL7-\u0003\u00026m\t!\u0011)\u001e=2\u0013\t9DB\u0001\fM_^\u0004&/[8sSRLXj\u001b)bi\"|\u0005\u000f^5d!\ta\u0012\bB\u0003\u001f\t\t\u0007!(\u0005\u0002!wA\u0011!\u0003P\u0005\u0003{M\u00111!\u00118z!\ty4!D\u0001\u0001!\u0011A\u0012\t\u000f\"\n\u00059b\u0001C\u0001\u000fD\t\u0015!EA1\u0001;\u0005\u0005)%!\u0002)sSNlWcA$J\u001bB)\u0011\u0007\u000e%?\u0015B\u0011A$\u0013\u0003\u0006=\u0015\u0011\rA\u000f\t\u00051-CE*\u0003\u0002F\u0019A\u0011A$\u0014\u0003\u0006\t\u0016\u0011\rAO\u0001\u0006CB\u0004H._\u000b\u0003!f+\u0012!\u0015\t\u00041\u0001\u0011\u0006\u0003\u0002\rT+nI!\u0001\u0016\u0007\u0003\u0019\u0011\u001aw\u000e\\8oI\r|Gn\u001c8\u0011\u0007a1\u0006,\u0003\u0002X\u0019\tA1i\\:fY\u0016\u001cG\u000f\u0005\u0002\u001d3\u0012)!L\u0002b\u0001u\t\t\u0001*A\u0007tK2,7\r\u001e#z]\u0006l\u0017n\u0019\u000b\u0003;\u001e$\"AX1\u0011\u0007a\u0001q\f\u0005\u0002ai:\u0011A$\u0019\u0005\u0006E\u001e\u0001\u001daY\u0001\bg\u0016<W.\u001a8u!\u0015ABM\u001a\u0011\u001c\u0013\t)GBA\u0004TK\u001elWM\u001c;\u000f\u0005q9\u0007\"\u00025\b\u0001\u0004I\u0017!\u00015\u0011\u0005)\fhBA6p!\ta7#D\u0001n\u0015\tqg\"\u0001\u0004=e>|GOP\u0005\u0003aN\ta\u0001\u0015:fI\u00164\u0017B\u0001:t\u0005\u0019\u0019FO]5oO*\u0011\u0001oE\u0005\u0003k\u0012\u00141aT;u\u0003\u0011\u0001\u0016\r\u001e5\u0011\u0005aI1cA\u0005\u0012sB\u0019\u0001\u0004\u0001>\u0011\u0005aY\u0018B\u0001?\r\u0005\u0011Ae*\u001b7\u0002\rqJg.\u001b;?)\u00059\b
  #12 = Utf8               shapeless/Path$$anon$45
  #13 = Class              #12            // shapeless/Path$$anon$45
  #14 = Utf8               shapeless/Path$$anon$46
  #15 = Class              #14            // shapeless/Path$$anon$46
  #16 = Utf8               apply$
  #17 = Utf8               (Lshapeless/Path;)Lshapeless/Path;
  #18 = Utf8               $this
  #19 = Utf8               apply
  #20 = Utf8               ()Lshapeless/Path;
  #21 = NameAndType        #19:#20        // apply:()Lshapeless/Path;
  #22 = InterfaceMethodref #2.#21         // shapeless/Path.apply:()Lshapeless/Path;
  #23 = Utf8               Lshapeless/Path;
  #24 = Utf8               <H:Ljava/lang/Object;>()Lshapeless/Path<Lshapeless/$colon$colon<Lshapeless/Coselect<TH;>;TT;>;>;
  #25 = Utf8               <init>
  #26 = Utf8               (Lshapeless/Path;)V
  #27 = NameAndType        #25:#26        // "<init>":(Lshapeless/Path;)V
  #28 = Methodref          #13.#27        // shapeless/Path$$anon$45."<init>":(Lshapeless/Path;)V
  #29 = Utf8               this
  #30 = Utf8               selectDynamic$
  #31 = Utf8               (Lshapeless/Path;Ljava/lang/String;Lshapeless/Segment;)Lshapeless/Path;
  #32 = Utf8               h
  #33 = Utf8               segment
  #34 = Utf8               selectDynamic
  #35 = Utf8               (Ljava/lang/String;Lshapeless/Segment;)Lshapeless/Path;
  #36 = NameAndType        #34:#35        // selectDynamic:(Ljava/lang/String;Lshapeless/Segment;)Lshapeless/Path;
  #37 = InterfaceMethodref #2.#36         // shapeless/Path.selectDynamic:(Ljava/lang/String;Lshapeless/Segment;)Lshapeless/Path;
  #38 = Utf8               Ljava/lang/String;
  #39 = Utf8               Lshapeless/Segment;
  #40 = Utf8               (Ljava/lang/String;Lshapeless/Segment<+Ljava/lang/String;Lscala/runtime/Nothing$;TT;>;)Lshapeless/Path<Lshapeless/HList;>;
  #41 = Methodref          #15.#27        // shapeless/Path$$anon$46."<init>":(Lshapeless/Path;)V
  #42 = Utf8               $init$
  #43 = Utf8               Code
  #44 = Utf8               LineNumberTable
  #45 = Utf8               LocalVariableTable
  #46 = Utf8               MethodParameters
  #47 = Utf8               Signature
  #48 = Utf8               InnerClasses
  #49 = Utf8               SourceFile
  #50 = Utf8               RuntimeVisibleAnnotations
  #51 = Utf8               ScalaInlineInfo
  #52 = Utf8               ScalaSig
{
  public static shapeless.Path apply$(shapeless.Path);
    descriptor: (Lshapeless/Path;)Lshapeless/Path;
    flags: (0x1009) ACC_PUBLIC, ACC_STATIC, ACC_SYNTHETIC
    Code:
      stack=1, locals=1, args_size=1
         0: aload_0
         1: invokespecial #22                 // InterfaceMethod apply:()Lshapeless/Path;
         4: areturn
      LineNumberTable:
        line 559: 0
      LocalVariableTable:
        Start  Length  Slot  Name   Signature
            0       5     0 $this   Lshapeless/Path;
    MethodParameters:
      Name                           Flags
      $this                          final synthetic

  public default <H extends java.lang.Object> shapeless.Path<shapeless.$colon$colon<shapeless.Coselect<H>, T>> apply();
    descriptor: ()Lshapeless/Path;
    flags: (0x0001) ACC_PUBLIC
    Code:
      stack=3, locals=1, args_size=1
         0: new           #13                 // class shapeless/Path$$anon$45
         3: dup
         4: aconst_null
         5: invokespecial #28                 // Method shapeless/Path$$anon$45."<init>":(Lshapeless/Path;)V
         8: areturn
      LineNumberTable:
        line 559: 0
      LocalVariableTable:
        Start  Length  Slot  Name   Signature
            0       9     0  this   Lshapeless/Path;
    Signature: #24                          // <H:Ljava/lang/Object;>()Lshapeless/Path<Lshapeless/$colon$colon<Lshapeless/Coselect<TH;>;TT;>;>;

  public static shapeless.Path selectDynamic$(shapeless.Path, java.lang.String, shapeless.Segment);
    descriptor: (Lshapeless/Path;Ljava/lang/String;Lshapeless/Segment;)Lshapeless/Path;
    flags: (0x1009) ACC_PUBLIC, ACC_STATIC, ACC_SYNTHETIC
    Code:
      stack=3, locals=3, args_size=3
         0: aload_0
         1: aload_1
         2: aload_2
         3: invokespecial #37                 // InterfaceMethod selectDynamic:(Ljava/lang/String;Lshapeless/Segment;)Lshapeless/Path;
         6: areturn
      LineNumberTable:
        line 561: 0
      LocalVariableTable:
        Start  Length  Slot  Name   Signature
            0       7     0 $this   Lshapeless/Path;
            0       7     1     h   Ljava/lang/String;
            0       7     2 segment   Lshapeless/Segment;
    MethodParameters:
      Name                           Flags
      $this                          final synthetic
      h                              final
      segment                        final

  public default shapeless.Path<shapeless.HList> selectDynamic(java.lang.String, shapeless.Segment<? extends java.lang.String, scala.runtime.Nothing$, T>);
    descriptor: (Ljava/lang/String;Lshapeless/Segment;)Lshapeless/Path;
    flags: (0x0001) ACC_PUBLIC
    Code:
      stack=3, locals=4, args_size=3
         0: aload_2
         1: astore_3
         2: new           #15                 // class shapeless/Path$$anon$46
         5: dup
         6: aconst_null
         7: invokespecial #41                 // Method shapeless/Path$$anon$46."<init>":(Lshapeless/Path;)V
        10: areturn
      LineNumberTable:
        line 561: 0
        line 562: 2
      LocalVariableTable:
        Start  Length  Slot  Name   Signature
            0      11     0  this   Lshapeless/Path;
            0      11     1     h   Ljava/lang/String;
            0      11     2 segment   Lshapeless/Segment;
    Signature: #40                          // (Ljava/lang/String;Lshapeless/Segment<+Ljava/lang/String;Lscala/runtime/Nothing$;TT;>;)Lshapeless/Path<Lshapeless/HList;>;
    MethodParameters:
      Name                           Flags
      h                              final
      segment                        final

  public static void $init$(shapeless.Path);
    descriptor: (Lshapeless/Path;)V
    flags: (0x0009) ACC_PUBLIC, ACC_STATIC
    Code:
      stack=0, locals=1, args_size=1
         0: return
      LineNumberTable:
        line 552: 0
      LocalVariableTable:
        Start  Length  Slot  Name   Signature
            0       1     0 $this   Lshapeless/Path;
    MethodParameters:
      Name                           Flags
      $this                          final synthetic
}
InnerClasses:
  public final #13;                       // class shapeless/Path$$anon$45
  public final #15;                       // class shapeless/Path$$anon$46
Signature: #3                           // <T::Lshapeless/HList;>Ljava/lang/Object;Lshapeless/LPPath<TT;>;
SourceFile: "lenses.scala"
RuntimeVisibleAnnotations:
  0: #9(#10=s#11)
    scala.reflect.ScalaSignature(
      bytes="\u0006\u0005}4qa\u0003\u0007\u0011\u0002\u0007\u0005q\u0002C\u0003\'\u0001\u0011\u0005q%\u0002\u0003,\u0001\u0001aS\u0001B\u0017\u0001\u0001m)AA\f\u0001\u0001_\u0015!Q\t\u0001\u0001G\u0011\u0015q\u0005\u0001\"\u0001P\u0011\u0015Y\u0006\u0001\"\u0001]\u000f\u00151H\u0002#\u0001x\r\u0015YA\u0002#\u0001y\u0011\u0015i\u0018\u0002\"\u0001\u007f\u0005\u0011\u0001\u0016\r\u001e5\u000b\u00035\t\u0011b\u001d5ba\u0016dWm]:\u0004\u0001U\u0011\u0001#H\n\u0004\u0001E9\u0002C\u0001\n\u0016\u001b\u0005\u0019\"\"\u0001\u000b\u0002\u000bM\u001c\u0017\r\\1\n\u0005Y\u0019\"AB!osJ+g\rE\u0002\u00193mi\u0011\u0001D\u0005\u000351\u0011a\u0001\u0014)QCRD\u0007C\u0001\u000f\u001e\u0019\u0001!QA\b\u0001C\u0002}\u0011\u0011\u0001V\t\u0003A\r\u0002\"AE\u0011\n\u0005\t\u001a\"a\u0002(pi\"Lgn\u001a\t\u00031\u0011J!!\n\u0007\u0003\u000b!c\u0015n\u001d;\u0002\r\u0011Jg.\u001b;%)\u0005A\u0003C\u0001\n*\u0013\tQ3C\u0001\u0003V]&$(!\u0001)\u0011\u0007a\u00011DA\u0001M\u0005\u0011aUM\\:\u0016\u0007AJ4\tE\u00032iar\u0004I\u0004\u0002\u0019e%\u00111\u0007D\u0001\f\u001b.\u0004\u0016\r\u001e5PaRL7-\u0003\u00026m\t!\u0011)\u001e=2\u0013\t9DB\u0001\fM_^\u0004&/[8sSRLXj\u001b)bi\"|\u0005\u000f^5d!\ta\u0012\bB\u0003\u001f\t\t\u0007!(\u0005\u0002!wA\u0011!\u0003P\u0005\u0003{M\u00111!\u00118z!\ty4!D\u0001\u0001!\u0011A\u0012\t\u000f\"\n\u00059b\u0001C\u0001\u000fD\t\u0015!EA1\u0001;\u0005\u0005)%!\u0002)sSNlWcA$J\u001bB)\u0011\u0007\u000e%?\u0015B\u0011A$\u0013\u0003\u0006=\u0015\u0011\rA\u000f\t\u00051-CE*\u0003\u0002F\u0019A\u0011A$\u0014\u0003\u0006\t\u0016\u0011\rAO\u0001\u0006CB\u0004H._\u000b\u0003!f+\u0012!\u0015\t\u00041\u0001\u0011\u0006\u0003\u0002\rT+nI!\u0001\u0016\u0007\u0003\u0019\u0011\u001aw\u000e\\8oI\r|Gn\u001c8\u0011\u0007a1\u0006,\u0003\u0002X\u0019\tA1i\\:fY\u0016\u001cG\u000f\u0005\u0002\u001d3\u0012)!L\u0002b\u0001u\t\t\u0001*A\u0007tK2,7\r\u001e#z]\u0006l\u0017n\u0019\u000b\u0003;\u001e$\"AX1\u0011\u0007a\u0001q\f\u0005\u0002ai:\u0011A$\u0019\u0005\u0006E\u001e\u0001\u001daY\u0001\bg\u0016<W.\u001a8u!\u0015ABM\u001a\u0011\u001c\u0013\t)GBA\u0004TK\u001elWM\u001c;\u000f\u0005q9\u0007\"\u00025\b\u0001\u0004I\u0017!\u00015\u0011\u0005)\fhBA6p!\ta7#D\u0001n\u0015\tqg\"\u0001\u0004=e>|GOP\u0005\u0003aN\ta\u0001\u0015:fI\u00164\u0017B\u0001:t\u0005\u0019\u0019FO]5oO*\u0011\u0001oE\u0005\u0003k\u0012\u00141aT;u\u0003\u0011\u0001\u0016\r\u001e5\u0011\u0005aI1cA\u0005\u0012sB\u0019\u0001\u0004\u0001>\u0011\u0005aY\u0018B\u0001?\r\u0005\u0011Ae*\u001b7\u0002\rqJg.\u001b;?)\u00059\b"
    )
  ScalaInlineInfo: length = 0x1D (unknown attribute)
   01 00 00 05 00 2A 00 1A 01 00 10 00 11 01 00 13
   00 14 00 00 1E 00 1F 01 00 22 00 23 00
  ScalaSig: length = 0x3 (unknown attribute)
   05 02 00
