Classfile /Users/mw/Projects/slang-braindump/.jar/jar8/assemble/slang-braindump/assemble/content/shapeless/Poly.class
  Last modified May 29, 2022; size 25815 bytes
  SHA-256 checksum 8ff3bdff036be1a31bf608363ed99dac0a0a5d6cfab958e903deab31c3b96083
  Compiled from "poly.scala"
public interface shapeless.Poly extends shapeless.PolyApply,java.io.Serializable
  minor version: 0
  major version: 52
  flags: (0x0601) ACC_PUBLIC, ACC_INTERFACE, ACC_ABSTRACT
  this_class: #2                          // shapeless/Poly
  super_class: #4                         // java/lang/Object
  interfaces: 2, fields: 0, methods: 40, attributes: 5
Constant pool:
    #1 = Utf8               shapeless/Poly
    #2 = Class              #1            // shapeless/Poly
    #3 = Utf8               java/lang/Object
    #4 = Class              #3            // java/lang/Object
    #5 = Utf8               shapeless/PolyApply
    #6 = Class              #5            // shapeless/PolyApply
    #7 = Utf8               java/io/Serializable
    #8 = Class              #7            // java/io/Serializable
    #9 = Utf8               poly.scala
   #10 = Utf8               Lscala/reflect/ScalaSignature;
   #11 = Utf8               bytes
   #12 = Utf8               \u0006\u0005\tMca\u0002\u0010 !\u0003\r\tA\t\u0005\u0006s\u0001!\tA\u000f\u0005\u0006}\u0001!\ta\u0010\u0005\u0006#\u0002!\tA\u0015\u0005\u0006-\u0002!\ta\u0016\u0005\u0006M\u0002!\taZ\u0003\u0005]\u0002\u0001qnB\u0003{\u0001!\u00051PB\u0003o\u0001!\u0005A\u0010C\u0003~\u0011\u0011\u0005a0B\u0003\u0000\u0011\u0001\t\t!\u0002\u0004\u0002\"!\u0001\u00111\u0005\u0005\b\u0003wAA\u0011AA\u001f\u0011\u001d\ti\u0006\u0001C\u0001\u0003?2\u0011\"a\u001e\u0001!\u0003\r\n!!\u001f\t\u000f\u0005mbB\"\u0001\u0002~\u0019I\u0011q\u0013\u0001\u0011\u0002\u0007\u0005\u0011\u0011\u0014\u0005\u0006sA!\tA\u000f\u0005\b\u00037\u0003B1AAO\u000f\u001d\t9\u000b\u0001E\u0001\u0003S3q!a\u001e\u0001\u0011\u0003\tY\u000b\u0003\u0004~)\u0011\u0005\u0011Q\u0018\u0005\b\u0003\u007f#B1AAa\u0011\u001d\u0011\t\u0001\u0001C\u0001\u0005\u0007Aq!a\u000f\u0001\t\u0003\u0011\tbB\u0004\u0003\u001e}A\tAa\b\u0007\ryy\u0002\u0012\u0001B\u0011\u0011\u0019i(\u0004\"\u0001\u0003*!9!1\u0006\u000e\u0005\u0004\t5\u0002\"\u0003B\"5\u0005\u0005I\u0011\u0002B#\u0005\u0011\u0001v\u000e\\=\u000b\u0003\u0001\n\u0011b\u001d5ba\u0016dWm]:\u0004\u0001M!\u0001aI\u0015.!\t!s%D\u0001&\u0015\u00051\u0013!B:dC2\f\u0017B\u0001\u0015&\u0005\u0019\te.\u001f*fMB\u0011!fK\u0007\u0002?%\u0011Af\b\u0002\n!>d\u00170\u00119qYf\u0004\"A\f\u001c\u000f\u0005=\"dB\u0001\u00194\u001b\u0005\t$B\u0001\u001a\"\u0003\u0019a$o\\8u}%\ta%\u0003\u00026K\u00059\u0001/Y2lC\u001e,\u0017BA\u001c9\u00051\u0019VM]5bY&T\u0018M\u00197f\u0015\t)T%\u0001\u0004%S:LG\u000f\n\u000b\u0002wA\u0011A\u0005P\u0005\u0003{\u0015\u0012A!\u00168ji\u000691m\\7q_N,GC\u0001!O!\u0011\tui\u0013\'\u000f\u0005\t#eB\u0001\u0016D\u0013\t)t$\u0003\u0002F\r\u0006!\u0001o\u001c7z\u0015\t)t$\u0003\u0002I\u0013\n91i\\7q_N,\'B\u0001& \u0003%\u0001v\u000e\\=EK\u001at7/D\u0001\u0001\u001d\tie\n\u0004\u0001\t\u000b=\u0013\u0001\u0019\u0001)\u0002\u0003\u0019\u0004\"A\u000b\u0001\u0002\u000f\u0005tG\r\u00165f]R\u00111+\u0016\t\u0005\u0003\u001e#6J\u0004\u0002N+\")qj\u0001a\u0001!\u0006Q!o\u001c;bi\u0016dUM\u001a;\u0016\u0005akV#A-\u0011\t\u0005S6\nX\u0005\u00037&\u0013!BU8uCR,G*\u001a4u!\tiU\fB\u0003_\t\t\u0007qLA\u0001O#\t\u00017\r\u0005\u0002%C&\u0011!-\n\u0002\b\u001d>$\b.\u001b8h!\tQC-\u0003\u0002f?\t\u0019a*\u0019;\u0002\u0017I|G/\u0019;f%&<\u0007\u000e^\u000b\u0003Q6,\u0012!\u001b\t\u0005\u0003*\\E.\u0003\u0002l\u0013\nY!k\u001c;bi\u0016\u0014\u0016n\u001a5u!\tiU\u000eB\u0003_\u000b\t\u0007qLA\u0006Qe>$Wo\u0019;DCN,WC\u00019u!\u0011\t\u0015oS:\n\u0005IL%\u0001B\"bg\u0016\u0004\"!\u0014;\u0005\u000bU4!\u0019\u0001<\u0003\u00031\u000b\"\u0001Y<\u0011\u0005)B\u0018BA= \u0005\u0015AE*[:u\u0003-\u0001&o\u001c3vGR\u001c\u0015m]3\u0011\u0005-C1c\u0001\u0005$[\u00051A(\u001b8jiz\"\u0012a\u001f\u0002\u0004\u0003VDXCBA\u0002\u0003\u001b\t)B\u0005\u0003\u0002\u0006\u0005%aABA\u0004\u0011\u0001\t\u0019A\u0001\u0007=e\u00164\u0017N\\3nK:$h\b\u0005\u0003L\r\u0005-\u0001cA\'\u0002\u000e\u0011)QO\u0003b\u0001m\u00169\u0011\u0011CA\u0003A\u0005M!A\u0002*fgVdG\u000fE\u0002N\u0003+!q!a\u0006\u000b\u0005\u0004\tIBA\u0004SKN,H\u000e\u001e\u0019\u0012\u0007\u0001\fY\u0002E\u0002%\u0003;I1!a\b&\u0005\r\te.\u001f\u0002\u0004\u0011>lW\u0003BA\u0013\u0003c\u0001r!a\n\u000b\u0003S\ty#D\u0001\t!\u001dQ\u00131FA\u0018\u0003kI1!!\f \u00051!3m\u001c7p]\u0012\u001aw\u000e\\8o!\ri\u0015\u0011\u0007\u0003\b\u0003gY!\u0019AA\r\u0005\u0005!\u0006c\u0001\u0016\u00028%\u0019\u0011\u0011H\u0010\u0003\t!s\u0015\u000e\\\u0001\u0006CB\u0004H._\u000b\u0007\u0003\u007f\tI%a\u0014\u0015\t\u0005\u0005\u00131\u000b\n\u0005\u0003\u0007\n)E\u0002\u0004\u0002\b1\u0001\u0011\u0011\t\t\u0005\u0017\u001a\t9\u0005E\u0002N\u0003\u0013\"Q!\u001e\u0007C\u0002Y,q!!\u0005\u0002D\u0001\ti\u0005E\u0002N\u0003\u001f\"q!!\u0015\r\u0005\u0004\tIBA\u0001S\u0011\u001d\t)\u0006\u0004a\u0001\u0003/\n\u0011A\u001e\t\bI\u0005e\u0013qIA\'\u0013\r\tY&\n\u0002\n\rVt7\r^5p]F\n1!^:f+!\t\t\'a%\u0002l\u0005=D\u0003BA2\u0003+#B!!\u001a\u0002rA9\u0011q\r\u0006\u0002j\u00055dBA&\b!\ri\u00151\u000e\u0003\u0006k6\u0011\rA\u001e\t\u0004\u001b\u0006=DaBA)\u001b\t\u0007\u0011\u0011\u0004\u0005\b\u0003gj\u00019AA;\u0003\t\u0019\'\r\u0005\u0005L\u001d\u0005E\u0015\u0011NA7\u0005-\u0019\u0015m]3Ck&dG-\u001a:\u0016\u0011\u0005m\u0014qRAB\u0003\u000f\u001b2AD\u0012.)\u0011\ty(!#\u0011\u000f\u0005\u001d$\"!!\u0002\u0006B\u0019Q*a!\u0005\u000bUt!\u0019\u0001<\u0011\u00075\u000b9\tB\u0004\u0002R9\u0011\r!!\u0007\t\u000f\u0005-u\u00021\u0001\u0002\u000e\u0006\tA\u000fE\u0002N\u0003\u001f#q!a\r\u000f\u0005\u0004\tI\u0002E\u0002N\u0003\'#q!a\r\u000e\u0005\u0004\tI\u0002C\u0004\u0002\f6\u0001\r!!%\u0003-1{w\u000f\u0015:j_JLG/_\"bg\u0016\u0014U/\u001b7eKJ\u001c\"\u0001E\u0012\u0002!Y\fG.^3DCN,\')^5mI\u0016\u0014X\u0003BAP\u0003K+\"!!)\u0011\u0011-s\u00111UA\u001b\u0003G\u00032!TAS\t\u001d\t\u0019D\u0005b\u0001\u00033\t1bQ1tK\n+\u0018\u000e\u001c3feB\u00111\nF\n\u0007)\r\ni+a,\u0011\u0005-\u0003\u0002\u0003BAY\u0003wk!!a-\u000b\t\u0005U\u0016qW\u0001\u0003S>T!!!/\u0002\t)\fg/Y\u0005\u0004o\u0005MFCAAU\u000351gnQ1tK\n+\u0018\u000e\u001c3feVQ\u00111YAe\u0003#\f9.a7\u0015\t\u0005\u0015\u0017Q\u001c\t\t\u0017:\t9-!4\u0002ZB\u0019Q*!3\u0005\u000f\u0005-gC1\u0001\u0002\u001a\t\ta\tE\u0004+\u0003W\ty-!6\u0011\u00075\u000b\t\u000eB\u0004\u0002TZ\u0011\r!!\u0007\u0003\u0003!\u00032!TAl\t\u0019\t\u0019D\u0006b\u0001mB\u0019Q*a7\u0005\u000f\u0005EaC1\u0001\u0002\u001a!9\u0011q\u001c\fA\u0004\u0005\u0005\u0018\u0001\u00024oiB\u0004\u0002\"a9\u0002z\u0006\u001d\u0017q \b\u0005\u0003K\f\u0019P\u0004\u0003\u0002h\u00065hb\u0001\u0016\u0002j&\u0019\u00111^\u0010\u0002\u0007=\u00048/\u0003\u0003\u0002p\u0006E\u0018\u0001\u00034v]\u000e$\u0018n\u001c8\u000b\u0007\u0005-x$\u0003\u0003\u0002v\u0006]\u0018a\u0003$o)>\u0004&o\u001c3vGRTA!a<\u0002r&\u0019q0a?\n\t\u0005u\u0018\u0011\u001f\u0002\u0015\r:$v\u000e\u0015:pIV\u001cG/\u00138ti\u0006t7-Z:\u0011\u000f\u0011\nI&!4\u0002Z\u000611-Y:f\u0003R,BA!\u0002\u0003\fQ!!q\u0001B\u0007!\u0011YeA!\u0003\u0011\u00075\u0013Y\u0001B\u0003v/\t\u0007a\u000fC\u0004\u0003\u0010]\u0001\u001dAa\u0002\u0002\u0003\r,BAa\u0005\u0003\u0018Q!!Q\u0003B\r!\ri%q\u0003\u0003\b\u0003#B\"\u0019AA\r\u0011\u001d\u0011y\u0001\u0007a\u0002\u00057\u0001r!a\u001a\u000b\u0003k\u0011)\"\u0001\u0003Q_2L\bC\u0001\u0016\u001b\'\u0019Q2Ea\t\u00020B\u0019!F!\n\n\u0007\t\u001drD\u0001\u0005Q_2L\u0018J\\:u)\t\u0011y\"A\u0003j]N$\b\u0007\u0006\u0003\u00030\tuB\u0003\u0002B\u0019\u0005k\u0001BAa\r\u0003B9\u0019QJ!\u000e\t\u000f\t]B\u0004q\u0001\u0003:\u0005\u00191m]3\u0011\u000b\tmb!!\u000e\u000f\u00075\u0013i\u0004\u0003\u0004\u0003@q\u0001\r\u0001U\u0001\u0002a&\u0019\u0011\u0011C9\u0002\u0019]\u0014\u0018\u000e^3SKBd\u0017mY3\u0015\u0005\t\u001d\u0003\u0003\u0002B%\u0005\u001fj!Aa\u0013\u000b\t\t5\u0013qW\u0001\u0005Y\u0006tw-\u0003\u0003\u0003R\t-#AB(cU\u0016\u001cG\u000f
   #13 = Utf8               shapeless/Poly$CaseBuilder
   #14 = Class              #13           // shapeless/Poly$CaseBuilder
   #15 = Utf8               CaseBuilder
   #16 = Utf8               shapeless/Poly$CaseBuilder$
   #17 = Class              #16           // shapeless/Poly$CaseBuilder$
   #18 = Utf8               CaseBuilder$
   #19 = Utf8               shapeless/Poly$LowPriorityCaseBuilder
   #20 = Class              #19           // shapeless/Poly$LowPriorityCaseBuilder
   #21 = Utf8               LowPriorityCaseBuilder
   #22 = Utf8               shapeless/Poly$ProductCase$
   #23 = Class              #22           // shapeless/Poly$ProductCase$
   #24 = Utf8               ProductCase$
   #25 = Utf8               shapeless/PolyDefns$Case
   #26 = Class              #25           // shapeless/PolyDefns$Case
   #27 = Utf8               shapeless/PolyDefns
   #28 = Class              #27           // shapeless/PolyDefns
   #29 = Utf8               Case
   #30 = Utf8               shapeless/PolyDefns$Compose
   #31 = Class              #30           // shapeless/PolyDefns$Compose
   #32 = Utf8               Compose
   #33 = Utf8               shapeless/PolyDefns$RotateLeft
   #34 = Class              #33           // shapeless/PolyDefns$RotateLeft
   #35 = Utf8               RotateLeft
   #36 = Utf8               shapeless/PolyDefns$RotateRight
   #37 = Class              #36           // shapeless/PolyDefns$RotateRight
   #38 = Utf8               RotateRight
   #39 = Utf8               inst0
   #40 = Utf8               (Lshapeless/Poly;Lshapeless/PolyDefns$Case;)Ljava/lang/Object;
   #41 = Utf8               (Lshapeless/Poly;Lshapeless/PolyDefns$Case<+Lshapeless/Poly;Lshapeless/HNil;>;)Ljava/lang/Object;
   #42 = Utf8               p
   #43 = Utf8               cse
   #44 = Utf8               shapeless/Poly$
   #45 = Class              #44           // shapeless/Poly$
   #46 = Utf8               MODULE$
   #47 = Utf8               Lshapeless/Poly$;
   #48 = NameAndType        #46:#47       // MODULE$:Lshapeless/Poly$;
   #49 = Fieldref           #45.#48       // shapeless/Poly$.MODULE$:Lshapeless/Poly$;
   #50 = NameAndType        #39:#40       // inst0:(Lshapeless/Poly;Lshapeless/PolyDefns$Case;)Ljava/lang/Object;
   #51 = Methodref          #45.#50       // shapeless/Poly$.inst0:(Lshapeless/Poly;Lshapeless/PolyDefns$Case;)Ljava/lang/Object;
   #52 = Utf8               inst22
   #53 = Utf8               (Lshapeless/Poly;Lshapeless/PolyDefns$Case;)Lscala/Function22;
   #54 = Utf8               <A:Ljava/lang/Object;B:Ljava/lang/Object;C:Ljava/lang/Object;D:Ljava/lang/Object;E:Ljava/lang/Object;F:Ljava/lang/Object;G:Ljava/lang/Object;H:Ljava/lang/Object;I:Ljava/lang/Object;J:Ljava/lang/Object;K:Ljava/lang/Object;L:Ljava/lang/Object;M:Ljava/lang/Object;N:Ljava/lang/Object;O:Ljava/lang/Object;P:Ljava/lang/Object;Q:Ljava/lang/Object;R:Ljava/lang/Object;S:Ljava/lang/Object;T:Ljava/lang/Object;U:Ljava/lang/Object;V:Ljava/lang/Object;>(Lshapeless/Poly;Lshapeless/PolyDefns$Case<+Lshapeless/Poly;Lshapeless/$colon$colon<TA;Lshapeless/$colon$colon<TB;Lshapeless/$colon$colon<TC;Lshapeless/$colon$colon<TD;Lshapeless/$colon$colon<TE;Lshapeless/$colon$colon<TF;Lshapeless/$colon$colon<TG;Lshapeless/$colon$colon<TH;Lshapeless/$colon$colon<TI;Lshapeless/$colon$colon<TJ;Lshapeless/$colon$colon<TK;Lshapeless/$colon$colon<TL;Lshapeless/$colon$colon<TM;Lshapeless/$colon$colon<TN;Lshapeless/$colon$colon<TO;Lshapeless/$colon$colon<TP;Lshapeless/$colon$colon<TQ;Lshapeless/$colon$colon<TR;Lshapeless/$colon$colon<TS;Lshapeless/$colon$colon<TT;Lshapeless/$colon$colon<TU;Lshapeless/$colon$colon<TV;Lshapeless/HNil;>;>;>;>;>;>;>;>;>;>;>;>;>;>;>;>;>;>;>;>;>;>;>;)Lscala/Function22<TA;TB;TC;TD;TE;TF;TG;TH;TI;TJ;TK;TL;TM;TN;TO;TP;TQ;TR;TS;TT;TU;TV;Ljava/lang/Object;>;
   #55 = Utf8               fn
   #56 = NameAndType        #52:#53       // inst22:(Lshapeless/Poly;Lshapeless/PolyDefns$Case;)Lscala/Function22;
   #57 = Methodref          #45.#56       // shapeless/Poly$.inst22:(Lshapeless/Poly;Lshapeless/PolyDefns$Case;)Lscala/Function22;
   #58 = Utf8               inst21
   #59 = Utf8               (Lshapeless/Poly;Lshapeless/PolyDefns$Case;)Lscala/Function21;
   #60 = Utf8               <A:Ljava/lang/Object;B:Ljava/lang/Object;C:Ljava/lang/Object;D:Ljava/lang/Object;E:Ljava/lang/Object;F:Ljava/lang/Object;G:Ljava/lang/Object;H:Ljava/lang/Object;I:Ljava/lang/Object;J:Ljava/lang/Object;K:Ljava/lang/Object;L:Ljava/lang/Object;M:Ljava/lang/Object;N:Ljava/lang/Object;O:Ljava/lang/Object;P:Ljava/lang/Object;Q:Ljava/lang/Object;R:Ljava/lang/Object;S:Ljava/lang/Object;T:Ljava/lang/Object;U:Ljava/lang/Object;>(Lshapeless/Poly;Lshapeless/PolyDefns$Case<+Lshapeless/Poly;Lshapeless/$colon$colon<TA;Lshapeless/$colon$colon<TB;Lshapeless/$colon$colon<TC;Lshapeless/$colon$colon<TD;Lshapeless/$colon$colon<TE;Lshapeless/$colon$colon<TF;Lshapeless/$colon$colon<TG;Lshapeless/$colon$colon<TH;Lshapeless/$colon$colon<TI;Lshapeless/$colon$colon<TJ;Lshapeless/$colon$colon<TK;Lshapeless/$colon$colon<TL;Lshapeless/$colon$colon<TM;Lshapeless/$colon$colon<TN;Lshapeless/$colon$colon<TO;Lshapeless/$colon$colon<TP;Lshapeless/$colon$colon<TQ;Lshapeless/$colon$colon<TR;Lshapeless/$colon$colon<TS;Lshapeless/$colon$colon<TT;Lshapeless/$colon$colon<TU;Lshapeless/HNil;>;>;>;>;>;>;>;>;>;>;>;>;>;>;>;>;>;>;>;>;>;>;)Lscala/Function21<TA;TB;TC;TD;TE;TF;TG;TH;TI;TJ;TK;TL;TM;TN;TO;TP;TQ;TR;TS;TT;TU;Ljava/lang/Object;>;
   #61 = NameAndType        #58:#59       // inst21:(Lshapeless/Poly;Lshapeless/PolyDefns$Case;)Lscala/Function21;
   #62 = Methodref          #45.#61       // shapeless/Poly$.inst21:(Lshapeless/Poly;Lshapeless/PolyDefns$Case;)Lscala/Function21;
   #63 = Utf8               inst20
   #64 = Utf8               (Lshapeless/Poly;Lshapeless/PolyDefns$Case;)Lscala/Function20;
   #65 = Utf8               <A:Ljava/lang/Object;B:Ljava/lang/Object;C:Ljava/lang/Object;D:Ljava/lang/Object;E:Ljava/lang/Object;F:Ljava/lang/Object;G:Ljava/lang/Object;H:Ljava/lang/Object;I:Ljava/lang/Object;J:Ljava/lang/Object;K:Ljava/lang/Object;L:Ljava/lang/Object;M:Ljava/lang/Object;N:Ljava/lang/Object;O:Ljava/lang/Object;P:Ljava/lang/Object;Q:Ljava/lang/Object;R:Ljava/lang/Object;S:Ljava/lang/Object;T:Ljava/lang/Object;>(Lshapeless/Poly;Lshapeless/PolyDefns$Case<+Lshapeless/Poly;Lshapeless/$colon$colon<TA;Lshapeless/$colon$colon<TB;Lshapeless/$colon$colon<TC;Lshapeless/$colon$colon<TD;Lshapeless/$colon$colon<TE;Lshapeless/$colon$colon<TF;Lshapeless/$colon$colon<TG;Lshapeless/$colon$colon<TH;Lshapeless/$colon$colon<TI;Lshapeless/$colon$colon<TJ;Lshapeless/$colon$colon<TK;Lshapeless/$colon$colon<TL;Lshapeless/$colon$colon<TM;Lshapeless/$colon$colon<TN;Lshapeless/$colon$colon<TO;Lshapeless/$colon$colon<TP;Lshapeless/$colon$colon<TQ;Lshapeless/$colon$colon<TR;Lshapeless/$colon$colon<TS;Lshapeless/$colon$colon<TT;Lshapeless/HNil;>;>;>;>;>;>;>;>;>;>;>;>;>;>;>;>;>;>;>;>;>;)Lscala/Function20<TA;TB;TC;TD;TE;TF;TG;TH;TI;TJ;TK;TL;TM;TN;TO;TP;TQ;TR;TS;TT;Ljava/lang/Object;>;
   #66 = NameAndType        #63:#64       // inst20:(Lshapeless/Poly;Lshapeless/PolyDefns$Case;)Lscala/Function20;
   #67 = Methodref          #45.#66       // shapeless/Poly$.inst20:(Lshapeless/Poly;Lshapeless/PolyDefns$Case;)Lscala/Function20;
   #68 = Utf8               inst19
   #69 = Utf8               (Lshapeless/Poly;Lshapeless/PolyDefns$Case;)Lscala/Function19;
   #70 = Utf8               <A:Ljava/lang/Object;B:Ljava/lang/Object;C:Ljava/lang/Object;D:Ljava/lang/Object;E:Ljava/lang/Object;F:Ljava/lang/Object;G:Ljava/lang/Object;H:Ljava/lang/Object;I:Ljava/lang/Object;J:Ljava/lang/Object;K:Ljava/lang/Object;L:Ljava/lang/Object;M:Ljava/lang/Object;N:Ljava/lang/Object;O:Ljava/lang/Object;P:Ljava/lang/Object;Q:Ljava/lang/Object;R:Ljava/lang/Object;S:Ljava/lang/Object;>(Lshapeless/Poly;Lshapeless/PolyDefns$Case<+Lshapeless/Poly;Lshapeless/$colon$colon<TA;Lshapeless/$colon$colon<TB;Lshapeless/$colon$colon<TC;Lshapeless/$colon$colon<TD;Lshapeless/$colon$colon<TE;Lshapeless/$colon$colon<TF;Lshapeless/$colon$colon<TG;Lshapeless/$colon$colon<TH;Lshapeless/$colon$colon<TI;Lshapeless/$colon$colon<TJ;Lshapeless/$colon$colon<TK;Lshapeless/$colon$colon<TL;Lshapeless/$colon$colon<TM;Lshapeless/$colon$colon<TN;Lshapeless/$colon$colon<TO;Lshapeless/$colon$colon<TP;Lshapeless/$colon$colon<TQ;Lshapeless/$colon$colon<TR;Lshapeless/$colon$colon<TS;Lshapeless/HNil;>;>;>;>;>;>;>;>;>;>;>;>;>;>;>;>;>;>;>;>;)Lscala/Function19<TA;TB;TC;TD;TE;TF;TG;TH;TI;TJ;TK;TL;TM;TN;TO;TP;TQ;TR;TS;Ljava/lang/Object;>;
   #71 = NameAndType        #68:#69       // inst19:(Lshapeless/Poly;Lshapeless/PolyDefns$Case;)Lscala/Function19;
   #72 = Methodref          #45.#71       // shapeless/Poly$.inst19:(Lshapeless/Poly;Lshapeless/PolyDefns$Case;)Lscala/Function19;
   #73 = Utf8               inst18
   #74 = Utf8               (Lshapeless/Poly;Lshapeless/PolyDefns$Case;)Lscala/Function18;
   #75 = Utf8               <A:Ljava/lang/Object;B:Ljava/lang/Object;C:Ljava/lang/Object;D:Ljava/lang/Object;E:Ljava/lang/Object;F:Ljava/lang/Object;G:Ljava/lang/Object;H:Ljava/lang/Object;I:Ljava/lang/Object;J:Ljava/lang/Object;K:Ljava/lang/Object;L:Ljava/lang/Object;M:Ljava/lang/Object;N:Ljava/lang/Object;O:Ljava/lang/Object;P:Ljava/lang/Object;Q:Ljava/lang/Object;R:Ljava/lang/Object;>(Lshapeless/Poly;Lshapeless/PolyDefns$Case<+Lshapeless/Poly;Lshapeless/$colon$colon<TA;Lshapeless/$colon$colon<TB;Lshapeless/$colon$colon<TC;Lshapeless/$colon$colon<TD;Lshapeless/$colon$colon<TE;Lshapeless/$colon$colon<TF;Lshapeless/$colon$colon<TG;Lshapeless/$colon$colon<TH;Lshapeless/$colon$colon<TI;Lshapeless/$colon$colon<TJ;Lshapeless/$colon$colon<TK;Lshapeless/$colon$colon<TL;Lshapeless/$colon$colon<TM;Lshapeless/$colon$colon<TN;Lshapeless/$colon$colon<TO;Lshapeless/$colon$colon<TP;Lshapeless/$colon$colon<TQ;Lshapeless/$colon$colon<TR;Lshapeless/HNil;>;>;>;>;>;>;>;>;>;>;>;>;>;>;>;>;>;>;>;)Lscala/Function18<TA;TB;TC;TD;TE;TF;TG;TH;TI;TJ;TK;TL;TM;TN;TO;TP;TQ;TR;Ljava/lang/Object;>;
   #76 = NameAndType        #73:#74       // inst18:(Lshapeless/Poly;Lshapeless/PolyDefns$Case;)Lscala/Function18;
   #77 = Methodref          #45.#76       // shapeless/Poly$.inst18:(Lshapeless/Poly;Lshapeless/PolyDefns$Case;)Lscala/Function18;
   #78 = Utf8               inst17
   #79 = Utf8               (Lshapeless/Poly;Lshapeless/PolyDefns$Case;)Lscala/Function17;
   #80 = Utf8               <A:Ljava/lang/Object;B:Ljava/lang/Object;C:Ljava/lang/Object;D:Ljava/lang/Object;E:Ljava/lang/Object;F:Ljava/lang/Object;G:Ljava/lang/Object;H:Ljava/lang/Object;I:Ljava/lang/Object;J:Ljava/lang/Object;K:Ljava/lang/Object;L:Ljava/lang/Object;M:Ljava/lang/Object;N:Ljava/lang/Object;O:Ljava/lang/Object;P:Ljava/lang/Object;Q:Ljava/lang/Object;>(Lshapeless/Poly;Lshapeless/PolyDefns$Case<+Lshapeless/Poly;Lshapeless/$colon$colon<TA;Lshapeless/$colon$colon<TB;Lshapeless/$colon$colon<TC;Lshapeless/$colon$colon<TD;Lshapeless/$colon$colon<TE;Lshapeless/$colon$colon<TF;Lshapeless/$colon$colon<TG;Lshapeless/$colon$colon<TH;Lshapeless/$colon$colon<TI;Lshapeless/$colon$colon<TJ;Lshapeless/$colon$colon<TK;Lshapeless/$colon$colon<TL;Lshapeless/$colon$colon<TM;Lshapeless/$colon$colon<TN;Lshapeless/$colon$colon<TO;Lshapeless/$colon$colon<TP;Lshapeless/$colon$colon<TQ;Lshapeless/HNil;>;>;>;>;>;>;>;>;>;>;>;>;>;>;>;>;>;>;)Lscala/Function17<TA;TB;TC;TD;TE;TF;TG;TH;TI;TJ;TK;TL;TM;TN;TO;TP;TQ;Ljava/lang/Object;>;
   #81 = NameAndType        #78:#79       // inst17:(Lshapeless/Poly;Lshapeless/PolyDefns$Case;)Lscala/Function17;
   #82 = Methodref          #45.#81       // shapeless/Poly$.inst17:(Lshapeless/Poly;Lshapeless/PolyDefns$Case;)Lscala/Function17;
   #83 = Utf8               inst16
   #84 = Utf8               (Lshapeless/Poly;Lshapeless/PolyDefns$Case;)Lscala/Function16;
   #85 = Utf8               <A:Ljava/lang/Object;B:Ljava/lang/Object;C:Ljava/lang/Object;D:Ljava/lang/Object;E:Ljava/lang/Object;F:Ljava/lang/Object;G:Ljava/lang/Object;H:Ljava/lang/Object;I:Ljava/lang/Object;J:Ljava/lang/Object;K:Ljava/lang/Object;L:Ljava/lang/Object;M:Ljava/lang/Object;N:Ljava/lang/Object;O:Ljava/lang/Object;P:Ljava/lang/Object;>(Lshapeless/Poly;Lshapeless/PolyDefns$Case<+Lshapeless/Poly;Lshapeless/$colon$colon<TA;Lshapeless/$colon$colon<TB;Lshapeless/$colon$colon<TC;Lshapeless/$colon$colon<TD;Lshapeless/$colon$colon<TE;Lshapeless/$colon$colon<TF;Lshapeless/$colon$colon<TG;Lshapeless/$colon$colon<TH;Lshapeless/$colon$colon<TI;Lshapeless/$colon$colon<TJ;Lshapeless/$colon$colon<TK;Lshapeless/$colon$colon<TL;Lshapeless/$colon$colon<TM;Lshapeless/$colon$colon<TN;Lshapeless/$colon$colon<TO;Lshapeless/$colon$colon<TP;Lshapeless/HNil;>;>;>;>;>;>;>;>;>;>;>;>;>;>;>;>;>;)Lscala/Function16<TA;TB;TC;TD;TE;TF;TG;TH;TI;TJ;TK;TL;TM;TN;TO;TP;Ljava/lang/Object;>;
   #86 = NameAndType        #83:#84       // inst16:(Lshapeless/Poly;Lshapeless/PolyDefns$Case;)Lscala/Function16;
   #87 = Methodref          #45.#86       // shapeless/Poly$.inst16:(Lshapeless/Poly;Lshapeless/PolyDefns$Case;)Lscala/Function16;
   #88 = Utf8               inst15
   #89 = Utf8               (Lshapeless/Poly;Lshapeless/PolyDefns$Case;)Lscala/Function15;
   #90 = Utf8               <A:Ljava/lang/Object;B:Ljava/lang/Object;C:Ljava/lang/Object;D:Ljava/lang/Object;E:Ljava/lang/Object;F:Ljava/lang/Object;G:Ljava/lang/Object;H:Ljava/lang/Object;I:Ljava/lang/Object;J:Ljava/lang/Object;K:Ljava/lang/Object;L:Ljava/lang/Object;M:Ljava/lang/Object;N:Ljava/lang/Object;O:Ljava/lang/Object;>(Lshapeless/Poly;Lshapeless/PolyDefns$Case<+Lshapeless/Poly;Lshapeless/$colon$colon<TA;Lshapeless/$colon$colon<TB;Lshapeless/$colon$colon<TC;Lshapeless/$colon$colon<TD;Lshapeless/$colon$colon<TE;Lshapeless/$colon$colon<TF;Lshapeless/$colon$colon<TG;Lshapeless/$colon$colon<TH;Lshapeless/$colon$colon<TI;Lshapeless/$colon$colon<TJ;Lshapeless/$colon$colon<TK;Lshapeless/$colon$colon<TL;Lshapeless/$colon$colon<TM;Lshapeless/$colon$colon<TN;Lshapeless/$colon$colon<TO;Lshapeless/HNil;>;>;>;>;>;>;>;>;>;>;>;>;>;>;>;>;)Lscala/Function15<TA;TB;TC;TD;TE;TF;TG;TH;TI;TJ;TK;TL;TM;TN;TO;Ljava/lang/Object;>;
   #91 = NameAndType        #88:#89       // inst15:(Lshapeless/Poly;Lshapeless/PolyDefns$Case;)Lscala/Function15;
   #92 = Methodref          #45.#91       // shapeless/Poly$.inst15:(Lshapeless/Poly;Lshapeless/PolyDefns$Case;)Lscala/Function15;
   #93 = Utf8               inst14
   #94 = Utf8               (Lshapeless/Poly;Lshapeless/PolyDefns$Case;)Lscala/Function14;
   #95 = Utf8               <A:Ljava/lang/Object;B:Ljava/lang/Object;C:Ljava/lang/Object;D:Ljava/lang/Object;E:Ljava/lang/Object;F:Ljava/lang/Object;G:Ljava/lang/Object;H:Ljava/lang/Object;I:Ljava/lang/Object;J:Ljava/lang/Object;K:Ljava/lang/Object;L:Ljava/lang/Object;M:Ljava/lang/Object;N:Ljava/lang/Object;>(Lshapeless/Poly;Lshapeless/PolyDefns$Case<+Lshapeless/Poly;Lshapeless/$colon$colon<TA;Lshapeless/$colon$colon<TB;Lshapeless/$colon$colon<TC;Lshapeless/$colon$colon<TD;Lshapeless/$colon$colon<TE;Lshapeless/$colon$colon<TF;Lshapeless/$colon$colon<TG;Lshapeless/$colon$colon<TH;Lshapeless/$colon$colon<TI;Lshapeless/$colon$colon<TJ;Lshapeless/$colon$colon<TK;Lshapeless/$colon$colon<TL;Lshapeless/$colon$colon<TM;Lshapeless/$colon$colon<TN;Lshapeless/HNil;>;>;>;>;>;>;>;>;>;>;>;>;>;>;>;)Lscala/Function14<TA;TB;TC;TD;TE;TF;TG;TH;TI;TJ;TK;TL;TM;TN;Ljava/lang/Object;>;
   #96 = NameAndType        #93:#94       // inst14:(Lshapeless/Poly;Lshapeless/PolyDefns$Case;)Lscala/Function14;
   #97 = Methodref          #45.#96       // shapeless/Poly$.inst14:(Lshapeless/Poly;Lshapeless/PolyDefns$Case;)Lscala/Function14;
   #98 = Utf8               inst13
   #99 = Utf8               (Lshapeless/Poly;Lshapeless/PolyDefns$Case;)Lscala/Function13;
  #100 = Utf8               <A:Ljava/lang/Object;B:Ljava/lang/Object;C:Ljava/lang/Object;D:Ljava/lang/Object;E:Ljava/lang/Object;F:Ljava/lang/Object;G:Ljava/lang/Object;H:Ljava/lang/Object;I:Ljava/lang/Object;J:Ljava/lang/Object;K:Ljava/lang/Object;L:Ljava/lang/Object;M:Ljava/lang/Object;>(Lshapeless/Poly;Lshapeless/PolyDefns$Case<+Lshapeless/Poly;Lshapeless/$colon$colon<TA;Lshapeless/$colon$colon<TB;Lshapeless/$colon$colon<TC;Lshapeless/$colon$colon<TD;Lshapeless/$colon$colon<TE;Lshapeless/$colon$colon<TF;Lshapeless/$colon$colon<TG;Lshapeless/$colon$colon<TH;Lshapeless/$colon$colon<TI;Lshapeless/$colon$colon<TJ;Lshapeless/$colon$colon<TK;Lshapeless/$colon$colon<TL;Lshapeless/$colon$colon<TM;Lshapeless/HNil;>;>;>;>;>;>;>;>;>;>;>;>;>;>;)Lscala/Function13<TA;TB;TC;TD;TE;TF;TG;TH;TI;TJ;TK;TL;TM;Ljava/lang/Object;>;
  #101 = NameAndType        #98:#99       // inst13:(Lshapeless/Poly;Lshapeless/PolyDefns$Case;)Lscala/Function13;
  #102 = Methodref          #45.#101      // shapeless/Poly$.inst13:(Lshapeless/Poly;Lshapeless/PolyDefns$Case;)Lscala/Function13;
  #103 = Utf8               inst12
  #104 = Utf8               (Lshapeless/Poly;Lshapeless/PolyDefns$Case;)Lscala/Function12;
  #105 = Utf8               <A:Ljava/lang/Object;B:Ljava/lang/Object;C:Ljava/lang/Object;D:Ljava/lang/Object;E:Ljava/lang/Object;F:Ljava/lang/Object;G:Ljava/lang/Object;H:Ljava/lang/Object;I:Ljava/lang/Object;J:Ljava/lang/Object;K:Ljava/lang/Object;L:Ljava/lang/Object;>(Lshapeless/Poly;Lshapeless/PolyDefns$Case<+Lshapeless/Poly;Lshapeless/$colon$colon<TA;Lshapeless/$colon$colon<TB;Lshapeless/$colon$colon<TC;Lshapeless/$colon$colon<TD;Lshapeless/$colon$colon<TE;Lshapeless/$colon$colon<TF;Lshapeless/$colon$colon<TG;Lshapeless/$colon$colon<TH;Lshapeless/$colon$colon<TI;Lshapeless/$colon$colon<TJ;Lshapeless/$colon$colon<TK;Lshapeless/$colon$colon<TL;Lshapeless/HNil;>;>;>;>;>;>;>;>;>;>;>;>;>;)Lscala/Function12<TA;TB;TC;TD;TE;TF;TG;TH;TI;TJ;TK;TL;Ljava/lang/Object;>;
  #106 = NameAndType        #103:#104     // inst12:(Lshapeless/Poly;Lshapeless/PolyDefns$Case;)Lscala/Function12;
  #107 = Methodref          #45.#106      // shapeless/Poly$.inst12:(Lshapeless/Poly;Lshapeless/PolyDefns$Case;)Lscala/Function12;
  #108 = Utf8               inst11
  #109 = Utf8               (Lshapeless/Poly;Lshapeless/PolyDefns$Case;)Lscala/Function11;
  #110 = Utf8               <A:Ljava/lang/Object;B:Ljava/lang/Object;C:Ljava/lang/Object;D:Ljava/lang/Object;E:Ljava/lang/Object;F:Ljava/lang/Object;G:Ljava/lang/Object;H:Ljava/lang/Object;I:Ljava/lang/Object;J:Ljava/lang/Object;K:Ljava/lang/Object;>(Lshapeless/Poly;Lshapeless/PolyDefns$Case<+Lshapeless/Poly;Lshapeless/$colon$colon<TA;Lshapeless/$colon$colon<TB;Lshapeless/$colon$colon<TC;Lshapeless/$colon$colon<TD;Lshapeless/$colon$colon<TE;Lshapeless/$colon$colon<TF;Lshapeless/$colon$colon<TG;Lshapeless/$colon$colon<TH;Lshapeless/$colon$colon<TI;Lshapeless/$colon$colon<TJ;Lshapeless/$colon$colon<TK;Lshapeless/HNil;>;>;>;>;>;>;>;>;>;>;>;>;)Lscala/Function11<TA;TB;TC;TD;TE;TF;TG;TH;TI;TJ;TK;Ljava/lang/Object;>;
  #111 = NameAndType        #108:#109     // inst11:(Lshapeless/Poly;Lshapeless/PolyDefns$Case;)Lscala/Function11;
  #112 = Methodref          #45.#111      // shapeless/Poly$.inst11:(Lshapeless/Poly;Lshapeless/PolyDefns$Case;)Lscala/Function11;
  #113 = Utf8               inst10
  #114 = Utf8               (Lshapeless/Poly;Lshapeless/PolyDefns$Case;)Lscala/Function10;
  #115 = Utf8               <A:Ljava/lang/Object;B:Ljava/lang/Object;C:Ljava/lang/Object;D:Ljava/lang/Object;E:Ljava/lang/Object;F:Ljava/lang/Object;G:Ljava/lang/Object;H:Ljava/lang/Object;I:Ljava/lang/Object;J:Ljava/lang/Object;>(Lshapeless/Poly;Lshapeless/PolyDefns$Case<+Lshapeless/Poly;Lshapeless/$colon$colon<TA;Lshapeless/$colon$colon<TB;Lshapeless/$colon$colon<TC;Lshapeless/$colon$colon<TD;Lshapeless/$colon$colon<TE;Lshapeless/$colon$colon<TF;Lshapeless/$colon$colon<TG;Lshapeless/$colon$colon<TH;Lshapeless/$colon$colon<TI;Lshapeless/$colon$colon<TJ;Lshapeless/HNil;>;>;>;>;>;>;>;>;>;>;>;)Lscala/Function10<TA;TB;TC;TD;TE;TF;TG;TH;TI;TJ;Ljava/lang/Object;>;
  #116 = NameAndType        #113:#114     // inst10:(Lshapeless/Poly;Lshapeless/PolyDefns$Case;)Lscala/Function10;
  #117 = Methodref          #45.#116      // shapeless/Poly$.inst10:(Lshapeless/Poly;Lshapeless/PolyDefns$Case;)Lscala/Function10;
  #118 = Utf8               inst9
  #119 = Utf8               (Lshapeless/Poly;Lshapeless/PolyDefns$Case;)Lscala/Function9;
  #120 = Utf8               <A:Ljava/lang/Object;B:Ljava/lang/Object;C:Ljava/lang/Object;D:Ljava/lang/Object;E:Ljava/lang/Object;F:Ljava/lang/Object;G:Ljava/lang/Object;H:Ljava/lang/Object;I:Ljava/lang/Object;>(Lshapeless/Poly;Lshapeless/PolyDefns$Case<+Lshapeless/Poly;Lshapeless/$colon$colon<TA;Lshapeless/$colon$colon<TB;Lshapeless/$colon$colon<TC;Lshapeless/$colon$colon<TD;Lshapeless/$colon$colon<TE;Lshapeless/$colon$colon<TF;Lshapeless/$colon$colon<TG;Lshapeless/$colon$colon<TH;Lshapeless/$colon$colon<TI;Lshapeless/HNil;>;>;>;>;>;>;>;>;>;>;)Lscala/Function9<TA;TB;TC;TD;TE;TF;TG;TH;TI;Ljava/lang/Object;>;
  #121 = NameAndType        #118:#119     // inst9:(Lshapeless/Poly;Lshapeless/PolyDefns$Case;)Lscala/Function9;
  #122 = Methodref          #45.#121      // shapeless/Poly$.inst9:(Lshapeless/Poly;Lshapeless/PolyDefns$Case;)Lscala/Function9;
  #123 = Utf8               inst8
  #124 = Utf8               (Lshapeless/Poly;Lshapeless/PolyDefns$Case;)Lscala/Function8;
  #125 = Utf8               <A:Ljava/lang/Object;B:Ljava/lang/Object;C:Ljava/lang/Object;D:Ljava/lang/Object;E:Ljava/lang/Object;F:Ljava/lang/Object;G:Ljava/lang/Object;H:Ljava/lang/Object;>(Lshapeless/Poly;Lshapeless/PolyDefns$Case<+Lshapeless/Poly;Lshapeless/$colon$colon<TA;Lshapeless/$colon$colon<TB;Lshapeless/$colon$colon<TC;Lshapeless/$colon$colon<TD;Lshapeless/$colon$colon<TE;Lshapeless/$colon$colon<TF;Lshapeless/$colon$colon<TG;Lshapeless/$colon$colon<TH;Lshapeless/HNil;>;>;>;>;>;>;>;>;>;)Lscala/Function8<TA;TB;TC;TD;TE;TF;TG;TH;Ljava/lang/Object;>;
  #126 = NameAndType        #123:#124     // inst8:(Lshapeless/Poly;Lshapeless/PolyDefns$Case;)Lscala/Function8;
  #127 = Methodref          #45.#126      // shapeless/Poly$.inst8:(Lshapeless/Poly;Lshapeless/PolyDefns$Case;)Lscala/Function8;
  #128 = Utf8               inst7
  #129 = Utf8               (Lshapeless/Poly;Lshapeless/PolyDefns$Case;)Lscala/Function7;
  #130 = Utf8               <A:Ljava/lang/Object;B:Ljava/lang/Object;C:Ljava/lang/Object;D:Ljava/lang/Object;E:Ljava/lang/Object;F:Ljava/lang/Object;G:Ljava/lang/Object;>(Lshapeless/Poly;Lshapeless/PolyDefns$Case<+Lshapeless/Poly;Lshapeless/$colon$colon<TA;Lshapeless/$colon$colon<TB;Lshapeless/$colon$colon<TC;Lshapeless/$colon$colon<TD;Lshapeless/$colon$colon<TE;Lshapeless/$colon$colon<TF;Lshapeless/$colon$colon<TG;Lshapeless/HNil;>;>;>;>;>;>;>;>;)Lscala/Function7<TA;TB;TC;TD;TE;TF;TG;Ljava/lang/Object;>;
  #131 = NameAndType        #128:#129     // inst7:(Lshapeless/Poly;Lshapeless/PolyDefns$Case;)Lscala/Function7;
  #132 = Methodref          #45.#131      // shapeless/Poly$.inst7:(Lshapeless/Poly;Lshapeless/PolyDefns$Case;)Lscala/Function7;
  #133 = Utf8               inst6
  #134 = Utf8               (Lshapeless/Poly;Lshapeless/PolyDefns$Case;)Lscala/Function6;
  #135 = Utf8               <A:Ljava/lang/Object;B:Ljava/lang/Object;C:Ljava/lang/Object;D:Ljava/lang/Object;E:Ljava/lang/Object;F:Ljava/lang/Object;>(Lshapeless/Poly;Lshapeless/PolyDefns$Case<+Lshapeless/Poly;Lshapeless/$colon$colon<TA;Lshapeless/$colon$colon<TB;Lshapeless/$colon$colon<TC;Lshapeless/$colon$colon<TD;Lshapeless/$colon$colon<TE;Lshapeless/$colon$colon<TF;Lshapeless/HNil;>;>;>;>;>;>;>;)Lscala/Function6<TA;TB;TC;TD;TE;TF;Ljava/lang/Object;>;
  #136 = NameAndType        #133:#134     // inst6:(Lshapeless/Poly;Lshapeless/PolyDefns$Case;)Lscala/Function6;
  #137 = Methodref          #45.#136      // shapeless/Poly$.inst6:(Lshapeless/Poly;Lshapeless/PolyDefns$Case;)Lscala/Function6;
  #138 = Utf8               inst5
  #139 = Utf8               (Lshapeless/Poly;Lshapeless/PolyDefns$Case;)Lscala/Function5;
  #140 = Utf8               <A:Ljava/lang/Object;B:Ljava/lang/Object;C:Ljava/lang/Object;D:Ljava/lang/Object;E:Ljava/lang/Object;>(Lshapeless/Poly;Lshapeless/PolyDefns$Case<+Lshapeless/Poly;Lshapeless/$colon$colon<TA;Lshapeless/$colon$colon<TB;Lshapeless/$colon$colon<TC;Lshapeless/$colon$colon<TD;Lshapeless/$colon$colon<TE;Lshapeless/HNil;>;>;>;>;>;>;)Lscala/Function5<TA;TB;TC;TD;TE;Ljava/lang/Object;>;
  #141 = NameAndType        #138:#139     // inst5:(Lshapeless/Poly;Lshapeless/PolyDefns$Case;)Lscala/Function5;
  #142 = Methodref          #45.#141      // shapeless/Poly$.inst5:(Lshapeless/Poly;Lshapeless/PolyDefns$Case;)Lscala/Function5;
  #143 = Utf8               inst4
  #144 = Utf8               (Lshapeless/Poly;Lshapeless/PolyDefns$Case;)Lscala/Function4;
  #145 = Utf8               <A:Ljava/lang/Object;B:Ljava/lang/Object;C:Ljava/lang/Object;D:Ljava/lang/Object;>(Lshapeless/Poly;Lshapeless/PolyDefns$Case<+Lshapeless/Poly;Lshapeless/$colon$colon<TA;Lshapeless/$colon$colon<TB;Lshapeless/$colon$colon<TC;Lshapeless/$colon$colon<TD;Lshapeless/HNil;>;>;>;>;>;)Lscala/Function4<TA;TB;TC;TD;Ljava/lang/Object;>;
  #146 = NameAndType        #143:#144     // inst4:(Lshapeless/Poly;Lshapeless/PolyDefns$Case;)Lscala/Function4;
  #147 = Methodref          #45.#146      // shapeless/Poly$.inst4:(Lshapeless/Poly;Lshapeless/PolyDefns$Case;)Lscala/Function4;
  #148 = Utf8               inst3
  #149 = Utf8               (Lshapeless/Poly;Lshapeless/PolyDefns$Case;)Lscala/Function3;
  #150 = Utf8               <A:Ljava/lang/Object;B:Ljava/lang/Object;C:Ljava/lang/Object;>(Lshapeless/Poly;Lshapeless/PolyDefns$Case<+Lshapeless/Poly;Lshapeless/$colon$colon<TA;Lshapeless/$colon$colon<TB;Lshapeless/$colon$colon<TC;Lshapeless/HNil;>;>;>;>;)Lscala/Function3<TA;TB;TC;Ljava/lang/Object;>;
  #151 = NameAndType        #148:#149     // inst3:(Lshapeless/Poly;Lshapeless/PolyDefns$Case;)Lscala/Function3;
  #152 = Methodref          #45.#151      // shapeless/Poly$.inst3:(Lshapeless/Poly;Lshapeless/PolyDefns$Case;)Lscala/Function3;
  #153 = Utf8               inst2
  #154 = Utf8               (Lshapeless/Poly;Lshapeless/PolyDefns$Case;)Lscala/Function2;
  #155 = Utf8               <A:Ljava/lang/Object;B:Ljava/lang/Object;>(Lshapeless/Poly;Lshapeless/PolyDefns$Case<+Lshapeless/Poly;Lshapeless/$colon$colon<TA;Lshapeless/$colon$colon<TB;Lshapeless/HNil;>;>;>;)Lscala/Function2<TA;TB;Ljava/lang/Object;>;
  #156 = NameAndType        #153:#154     // inst2:(Lshapeless/Poly;Lshapeless/PolyDefns$Case;)Lscala/Function2;
  #157 = Methodref          #45.#156      // shapeless/Poly$.inst2:(Lshapeless/Poly;Lshapeless/PolyDefns$Case;)Lscala/Function2;
  #158 = Utf8               inst1
  #159 = Utf8               (Lshapeless/Poly;Lshapeless/PolyDefns$Case;)Lscala/Function1;
  #160 = Utf8               <A:Ljava/lang/Object;>(Lshapeless/Poly;Lshapeless/PolyDefns$Case<+Lshapeless/Poly;Lshapeless/$colon$colon<TA;Lshapeless/HNil;>;>;)Lscala/Function1<TA;Ljava/lang/Object;>;
  #161 = NameAndType        #158:#159     // inst1:(Lshapeless/Poly;Lshapeless/PolyDefns$Case;)Lscala/Function1;
  #162 = Methodref          #45.#161      // shapeless/Poly$.inst1:(Lshapeless/Poly;Lshapeless/PolyDefns$Case;)Lscala/Function1;
  #163 = Utf8               ProductCase
  #164 = Utf8               ()Lshapeless/Poly$ProductCase$;
  #165 = Utf8               ()Lshapeless/Poly$CaseBuilder$;
  #166 = Utf8               compose$
  #167 = Utf8               (Lshapeless/Poly;Lshapeless/Poly;)Lshapeless/PolyDefns$Compose;
  #168 = Utf8               $this
  #169 = Utf8               f
  #170 = Utf8               compose
  #171 = Utf8               (Lshapeless/Poly;)Lshapeless/PolyDefns$Compose;
  #172 = NameAndType        #170:#171     // compose:(Lshapeless/Poly;)Lshapeless/PolyDefns$Compose;
  #173 = InterfaceMethodref #2.#172       // shapeless/Poly.compose:(Lshapeless/Poly;)Lshapeless/PolyDefns$Compose;
  #174 = Utf8               Lshapeless/Poly;
  #175 = Utf8               (Lshapeless/Poly;)Lshapeless/PolyDefns$Compose<Lshapeless/Poly;Lshapeless/Poly;>;
  #176 = Utf8               <init>
  #177 = Utf8               (Ljava/lang/Object;Ljava/lang/Object;)V
  #178 = NameAndType        #176:#177     // "<init>":(Ljava/lang/Object;Ljava/lang/Object;)V
  #179 = Methodref          #31.#178      // shapeless/PolyDefns$Compose."<init>":(Ljava/lang/Object;Ljava/lang/Object;)V
  #180 = Utf8               this
  #181 = Utf8               andThen$
  #182 = Utf8               andThen
  #183 = NameAndType        #182:#171     // andThen:(Lshapeless/Poly;)Lshapeless/PolyDefns$Compose;
  #184 = InterfaceMethodref #2.#183       // shapeless/Poly.andThen:(Lshapeless/Poly;)Lshapeless/PolyDefns$Compose;
  #185 = Utf8               rotateLeft$
  #186 = Utf8               (Lshapeless/Poly;)Lshapeless/PolyDefns$RotateLeft;
  #187 = Utf8               rotateLeft
  #188 = Utf8               ()Lshapeless/PolyDefns$RotateLeft;
  #189 = NameAndType        #187:#188     // rotateLeft:()Lshapeless/PolyDefns$RotateLeft;
  #190 = InterfaceMethodref #2.#189       // shapeless/Poly.rotateLeft:()Lshapeless/PolyDefns$RotateLeft;
  #191 = Utf8               <N::Lshapeless/Nat;>()Lshapeless/PolyDefns$RotateLeft<Lshapeless/Poly;TN;>;
  #192 = Utf8               (Ljava/lang/Object;)V
  #193 = NameAndType        #176:#192     // "<init>":(Ljava/lang/Object;)V
  #194 = Methodref          #34.#193      // shapeless/PolyDefns$RotateLeft."<init>":(Ljava/lang/Object;)V
  #195 = Utf8               rotateRight$
  #196 = Utf8               (Lshapeless/Poly;)Lshapeless/PolyDefns$RotateRight;
  #197 = Utf8               rotateRight
  #198 = Utf8               ()Lshapeless/PolyDefns$RotateRight;
  #199 = NameAndType        #197:#198     // rotateRight:()Lshapeless/PolyDefns$RotateRight;
  #200 = InterfaceMethodref #2.#199       // shapeless/Poly.rotateRight:()Lshapeless/PolyDefns$RotateRight;
  #201 = Utf8               <N::Lshapeless/Nat;>()Lshapeless/PolyDefns$RotateRight<Lshapeless/Poly;TN;>;
  #202 = Methodref          #37.#193      // shapeless/PolyDefns$RotateRight."<init>":(Ljava/lang/Object;)V
  #203 = Utf8               use$
  #204 = Utf8               (Lshapeless/Poly;Ljava/lang/Object;Lshapeless/Poly$CaseBuilder;)Lshapeless/PolyDefns$Case;
  #205 = Utf8               t
  #206 = Utf8               cb
  #207 = Utf8               use
  #208 = Utf8               (Ljava/lang/Object;Lshapeless/Poly$CaseBuilder;)Lshapeless/PolyDefns$Case;
  #209 = NameAndType        #207:#208     // use:(Ljava/lang/Object;Lshapeless/Poly$CaseBuilder;)Lshapeless/PolyDefns$Case;
  #210 = InterfaceMethodref #2.#209       // shapeless/Poly.use:(Ljava/lang/Object;Lshapeless/Poly$CaseBuilder;)Lshapeless/PolyDefns$Case;
  #211 = Utf8               Ljava/lang/Object;
  #212 = Utf8               Lshapeless/Poly$CaseBuilder;
  #213 = Utf8               <T:Ljava/lang/Object;L::Lshapeless/HList;R:Ljava/lang/Object;>(TT;Lshapeless/Poly$CaseBuilder<TT;TL;TR;>;)Lshapeless/PolyDefns$Case<Lshapeless/Poly;TL;>;
  #214 = Utf8               apply
  #215 = Utf8               (Ljava/lang/Object;)Lshapeless/PolyDefns$Case;
  #216 = NameAndType        #214:#215     // apply:(Ljava/lang/Object;)Lshapeless/PolyDefns$Case;
  #217 = InterfaceMethodref #14.#216      // shapeless/Poly$CaseBuilder.apply:(Ljava/lang/Object;)Lshapeless/PolyDefns$Case;
  #218 = Utf8               caseAt$
  #219 = Utf8               (Lshapeless/Poly;Lshapeless/PolyDefns$Case;)Lshapeless/PolyDefns$Case;
  #220 = Utf8               c
  #221 = Utf8               caseAt
  #222 = Utf8               (Lshapeless/PolyDefns$Case;)Lshapeless/PolyDefns$Case;
  #223 = NameAndType        #221:#222     // caseAt:(Lshapeless/PolyDefns$Case;)Lshapeless/PolyDefns$Case;
  #224 = InterfaceMethodref #2.#223       // shapeless/Poly.caseAt:(Lshapeless/PolyDefns$Case;)Lshapeless/PolyDefns$Case;
  #225 = Utf8               Lshapeless/PolyDefns$Case;
  #226 = Utf8               <L::Lshapeless/HList;>(Lshapeless/PolyDefns$Case<Lshapeless/Poly;TL;>;)Lshapeless/PolyDefns$Case<Lshapeless/Poly;TL;>;
  #227 = Utf8               apply$
  #228 = Utf8               (Lshapeless/PolyDefns$Case;)Ljava/lang/Object;
  #229 = NameAndType        #214:#228     // apply:(Lshapeless/PolyDefns$Case;)Ljava/lang/Object;
  #230 = InterfaceMethodref #2.#229       // shapeless/Poly.apply:(Lshapeless/PolyDefns$Case;)Ljava/lang/Object;
  #231 = Utf8               <R:Ljava/lang/Object;>(Lshapeless/PolyDefns$Case<Lshapeless/Poly;Lshapeless/HNil;>;)TR;
  #232 = Utf8               scala/$less$colon$less$
  #233 = Class              #232          // scala/$less$colon$less$
  #234 = Utf8               Lscala/$less$colon$less$;
  #235 = NameAndType        #46:#234      // MODULE$:Lscala/$less$colon$less$;
  #236 = Fieldref           #233.#235     // scala/$less$colon$less$.MODULE$:Lscala/$less$colon$less$;
  #237 = Utf8               refl
  #238 = Utf8               ()Lscala/$eq$colon$eq;
  #239 = NameAndType        #237:#238     // refl:()Lscala/$eq$colon$eq;
  #240 = Methodref          #233.#239     // scala/$less$colon$less$.refl:()Lscala/$eq$colon$eq;
  #241 = Utf8               (Lscala/$eq$colon$eq;)Ljava/lang/Object;
  #242 = NameAndType        #214:#241     // apply:(Lscala/$eq$colon$eq;)Ljava/lang/Object;
  #243 = Methodref          #26.#242      // shapeless/PolyDefns$Case.apply:(Lscala/$eq$colon$eq;)Ljava/lang/Object;
  #244 = Utf8               $init$
  #245 = Utf8               (Lshapeless/Poly;)V
  #246 = Utf8               Code
  #247 = Utf8               Signature
  #248 = Utf8               MethodParameters
  #249 = Utf8               LineNumberTable
  #250 = Utf8               LocalVariableTable
  #251 = Utf8               InnerClasses
  #252 = Utf8               SourceFile
  #253 = Utf8               RuntimeVisibleAnnotations
  #254 = Utf8               ScalaInlineInfo
  #255 = Utf8               ScalaSig
{
  public static java.lang.Object inst0(shapeless.Poly, shapeless.PolyDefns$Case<? extends shapeless.Poly, shapeless.HNil>);
    descriptor: (Lshapeless/Poly;Lshapeless/PolyDefns$Case;)Ljava/lang/Object;
    flags: (0x0009) ACC_PUBLIC, ACC_STATIC
    Code:
      stack=3, locals=2, args_size=2
         0: getstatic     #49                 // Field shapeless/Poly$.MODULE$:Lshapeless/Poly$;
         3: aload_0
         4: aload_1
         5: invokevirtual #51                 // Method shapeless/Poly$.inst0:(Lshapeless/Poly;Lshapeless/PolyDefns$Case;)Ljava/lang/Object;
         8: areturn
    Signature: #41                          // (Lshapeless/Poly;Lshapeless/PolyDefns$Case<+Lshapeless/Poly;Lshapeless/HNil;>;)Ljava/lang/Object;
    MethodParameters:
      Name                           Flags
      p                              final
      cse                            final

  public static <A extends java.lang.Object, B extends java.lang.Object, C extends java.lang.Object, D extends java.lang.Object, E extends java.lang.Object, F extends java.lang.Object, G extends java.lang.Object, H extends java.lang.Object, I extends java.lang.Object, J extends java.lang.Object, K extends java.lang.Object, L extends java.lang.Object, M extends java.lang.Object, N extends java.lang.Object, O extends java.lang.Object, P extends java.lang.Object, Q extends java.lang.Object, R extends java.lang.Object, S extends java.lang.Object, T extends java.lang.Object, U extends java.lang.Object, V extends java.lang.Object> scala.Function22<A, B, C, D, E, F, G, H, I, J, K, L, M, N, O, P, Q, R, S, T, U, V, java.lang.Object> inst22(shapeless.Poly, shapeless.PolyDefns$Case<? extends shapeless.Poly, shapeless.$colon$colon<A, shapeless.$colon$colon<B, shapeless.$colon$colon<C, shapeless.$colon$colon<D, shapeless.$colon$colon<E, shapeless.$colon$colon<F, shapeless.$colon$colon<G, shapeless.$colon$colon<H, shapeless.$colon$colon<I, shapeless.$colon$colon<J, shapeless.$colon$colon<K, shapeless.$colon$colon<L, shapeless.$colon$colon<M, shapeless.$colon$colon<N, shapeless.$colon$colon<O, shapeless.$colon$colon<P, shapeless.$colon$colon<Q, shapeless.$colon$colon<R, shapeless.$colon$colon<S, shapeless.$colon$colon<T, shapeless.$colon$colon<U, shapeless.$colon$colon<V, shapeless.HNil>>>>>>>>>>>>>>>>>>>>>>>);
    descriptor: (Lshapeless/Poly;Lshapeless/PolyDefns$Case;)Lscala/Function22;
    flags: (0x0009) ACC_PUBLIC, ACC_STATIC
    Code:
      stack=3, locals=2, args_size=2
         0: getstatic     #49                 // Field shapeless/Poly$.MODULE$:Lshapeless/Poly$;
         3: aload_0
         4: aload_1
         5: invokevirtual #57                 // Method shapeless/Poly$.inst22:(Lshapeless/Poly;Lshapeless/PolyDefns$Case;)Lscala/Function22;
         8: areturn
    Signature: #54                          // <A:Ljava/lang/Object;B:Ljava/lang/Object;C:Ljava/lang/Object;D:Ljava/lang/Object;E:Ljava/lang/Object;F:Ljava/lang/Object;G:Ljava/lang/Object;H:Ljava/lang/Object;I:Ljava/lang/Object;J:Ljava/lang/Object;K:Ljava/lang/Object;L:Ljava/lang/Object;M:Ljava/lang/Object;N:Ljava/lang/Object;O:Ljava/lang/Object;P:Ljava/lang/Object;Q:Ljava/lang/Object;R:Ljava/lang/Object;S:Ljava/lang/Object;T:Ljava/lang/Object;U:Ljava/lang/Object;V:Ljava/lang/Object;>(Lshapeless/Poly;Lshapeless/PolyDefns$Case<+Lshapeless/Poly;Lshapeless/$colon$colon<TA;Lshapeless/$colon$colon<TB;Lshapeless/$colon$colon<TC;Lshapeless/$colon$colon<TD;Lshapeless/$colon$colon<TE;Lshapeless/$colon$colon<TF;Lshapeless/$colon$colon<TG;Lshapeless/$colon$colon<TH;Lshapeless/$colon$colon<TI;Lshapeless/$colon$colon<TJ;Lshapeless/$colon$colon<TK;Lshapeless/$colon$colon<TL;Lshapeless/$colon$colon<TM;Lshapeless/$colon$colon<TN;Lshapeless/$colon$colon<TO;Lshapeless/$colon$colon<TP;Lshapeless/$colon$colon<TQ;Lshapeless/$colon$colon<TR;Lshapeless/$colon$colon<TS;Lshapeless/$colon$colon<TT;Lshapeless/$colon$colon<TU;Lshapeless/$colon$colon<TV;Lshapeless/HNil;>;>;>;>;>;>;>;>;>;>;>;>;>;>;>;>;>;>;>;>;>;>;>;)Lscala/Function22<TA;TB;TC;TD;TE;TF;TG;TH;TI;TJ;TK;TL;TM;TN;TO;TP;TQ;TR;TS;TT;TU;TV;Ljava/lang/Object;>;
    MethodParameters:
      Name                           Flags
      fn                             final
      cse                            final

  public static <A extends java.lang.Object, B extends java.lang.Object, C extends java.lang.Object, D extends java.lang.Object, E extends java.lang.Object, F extends java.lang.Object, G extends java.lang.Object, H extends java.lang.Object, I extends java.lang.Object, J extends java.lang.Object, K extends java.lang.Object, L extends java.lang.Object, M extends java.lang.Object, N extends java.lang.Object, O extends java.lang.Object, P extends java.lang.Object, Q extends java.lang.Object, R extends java.lang.Object, S extends java.lang.Object, T extends java.lang.Object, U extends java.lang.Object> scala.Function21<A, B, C, D, E, F, G, H, I, J, K, L, M, N, O, P, Q, R, S, T, U, java.lang.Object> inst21(shapeless.Poly, shapeless.PolyDefns$Case<? extends shapeless.Poly, shapeless.$colon$colon<A, shapeless.$colon$colon<B, shapeless.$colon$colon<C, shapeless.$colon$colon<D, shapeless.$colon$colon<E, shapeless.$colon$colon<F, shapeless.$colon$colon<G, shapeless.$colon$colon<H, shapeless.$colon$colon<I, shapeless.$colon$colon<J, shapeless.$colon$colon<K, shapeless.$colon$colon<L, shapeless.$colon$colon<M, shapeless.$colon$colon<N, shapeless.$colon$colon<O, shapeless.$colon$colon<P, shapeless.$colon$colon<Q, shapeless.$colon$colon<R, shapeless.$colon$colon<S, shapeless.$colon$colon<T, shapeless.$colon$colon<U, shapeless.HNil>>>>>>>>>>>>>>>>>>>>>>);
    descriptor: (Lshapeless/Poly;Lshapeless/PolyDefns$Case;)Lscala/Function21;
    flags: (0x0009) ACC_PUBLIC, ACC_STATIC
    Code:
      stack=3, locals=2, args_size=2
         0: getstatic     #49                 // Field shapeless/Poly$.MODULE$:Lshapeless/Poly$;
         3: aload_0
         4: aload_1
         5: invokevirtual #62                 // Method shapeless/Poly$.inst21:(Lshapeless/Poly;Lshapeless/PolyDefns$Case;)Lscala/Function21;
         8: areturn
    Signature: #60                          // <A:Ljava/lang/Object;B:Ljava/lang/Object;C:Ljava/lang/Object;D:Ljava/lang/Object;E:Ljava/lang/Object;F:Ljava/lang/Object;G:Ljava/lang/Object;H:Ljava/lang/Object;I:Ljava/lang/Object;J:Ljava/lang/Object;K:Ljava/lang/Object;L:Ljava/lang/Object;M:Ljava/lang/Object;N:Ljava/lang/Object;O:Ljava/lang/Object;P:Ljava/lang/Object;Q:Ljava/lang/Object;R:Ljava/lang/Object;S:Ljava/lang/Object;T:Ljava/lang/Object;U:Ljava/lang/Object;>(Lshapeless/Poly;Lshapeless/PolyDefns$Case<+Lshapeless/Poly;Lshapeless/$colon$colon<TA;Lshapeless/$colon$colon<TB;Lshapeless/$colon$colon<TC;Lshapeless/$colon$colon<TD;Lshapeless/$colon$colon<TE;Lshapeless/$colon$colon<TF;Lshapeless/$colon$colon<TG;Lshapeless/$colon$colon<TH;Lshapeless/$colon$colon<TI;Lshapeless/$colon$colon<TJ;Lshapeless/$colon$colon<TK;Lshapeless/$colon$colon<TL;Lshapeless/$colon$colon<TM;Lshapeless/$colon$colon<TN;Lshapeless/$colon$colon<TO;Lshapeless/$colon$colon<TP;Lshapeless/$colon$colon<TQ;Lshapeless/$colon$colon<TR;Lshapeless/$colon$colon<TS;Lshapeless/$colon$colon<TT;Lshapeless/$colon$colon<TU;Lshapeless/HNil;>;>;>;>;>;>;>;>;>;>;>;>;>;>;>;>;>;>;>;>;>;>;)Lscala/Function21<TA;TB;TC;TD;TE;TF;TG;TH;TI;TJ;TK;TL;TM;TN;TO;TP;TQ;TR;TS;TT;TU;Ljava/lang/Object;>;
    MethodParameters:
      Name                           Flags
      fn                             final
      cse                            final

  public static <A extends java.lang.Object, B extends java.lang.Object, C extends java.lang.Object, D extends java.lang.Object, E extends java.lang.Object, F extends java.lang.Object, G extends java.lang.Object, H extends java.lang.Object, I extends java.lang.Object, J extends java.lang.Object, K extends java.lang.Object, L extends java.lang.Object, M extends java.lang.Object, N extends java.lang.Object, O extends java.lang.Object, P extends java.lang.Object, Q extends java.lang.Object, R extends java.lang.Object, S extends java.lang.Object, T extends java.lang.Object> scala.Function20<A, B, C, D, E, F, G, H, I, J, K, L, M, N, O, P, Q, R, S, T, java.lang.Object> inst20(shapeless.Poly, shapeless.PolyDefns$Case<? extends shapeless.Poly, shapeless.$colon$colon<A, shapeless.$colon$colon<B, shapeless.$colon$colon<C, shapeless.$colon$colon<D, shapeless.$colon$colon<E, shapeless.$colon$colon<F, shapeless.$colon$colon<G, shapeless.$colon$colon<H, shapeless.$colon$colon<I, shapeless.$colon$colon<J, shapeless.$colon$colon<K, shapeless.$colon$colon<L, shapeless.$colon$colon<M, shapeless.$colon$colon<N, shapeless.$colon$colon<O, shapeless.$colon$colon<P, shapeless.$colon$colon<Q, shapeless.$colon$colon<R, shapeless.$colon$colon<S, shapeless.$colon$colon<T, shapeless.HNil>>>>>>>>>>>>>>>>>>>>>);
    descriptor: (Lshapeless/Poly;Lshapeless/PolyDefns$Case;)Lscala/Function20;
    flags: (0x0009) ACC_PUBLIC, ACC_STATIC
    Code:
      stack=3, locals=2, args_size=2
         0: getstatic     #49                 // Field shapeless/Poly$.MODULE$:Lshapeless/Poly$;
         3: aload_0
         4: aload_1
         5: invokevirtual #67                 // Method shapeless/Poly$.inst20:(Lshapeless/Poly;Lshapeless/PolyDefns$Case;)Lscala/Function20;
         8: areturn
    Signature: #65                          // <A:Ljava/lang/Object;B:Ljava/lang/Object;C:Ljava/lang/Object;D:Ljava/lang/Object;E:Ljava/lang/Object;F:Ljava/lang/Object;G:Ljava/lang/Object;H:Ljava/lang/Object;I:Ljava/lang/Object;J:Ljava/lang/Object;K:Ljava/lang/Object;L:Ljava/lang/Object;M:Ljava/lang/Object;N:Ljava/lang/Object;O:Ljava/lang/Object;P:Ljava/lang/Object;Q:Ljava/lang/Object;R:Ljava/lang/Object;S:Ljava/lang/Object;T:Ljava/lang/Object;>(Lshapeless/Poly;Lshapeless/PolyDefns$Case<+Lshapeless/Poly;Lshapeless/$colon$colon<TA;Lshapeless/$colon$colon<TB;Lshapeless/$colon$colon<TC;Lshapeless/$colon$colon<TD;Lshapeless/$colon$colon<TE;Lshapeless/$colon$colon<TF;Lshapeless/$colon$colon<TG;Lshapeless/$colon$colon<TH;Lshapeless/$colon$colon<TI;Lshapeless/$colon$colon<TJ;Lshapeless/$colon$colon<TK;Lshapeless/$colon$colon<TL;Lshapeless/$colon$colon<TM;Lshapeless/$colon$colon<TN;Lshapeless/$colon$colon<TO;Lshapeless/$colon$colon<TP;Lshapeless/$colon$colon<TQ;Lshapeless/$colon$colon<TR;Lshapeless/$colon$colon<TS;Lshapeless/$colon$colon<TT;Lshapeless/HNil;>;>;>;>;>;>;>;>;>;>;>;>;>;>;>;>;>;>;>;>;>;)Lscala/Function20<TA;TB;TC;TD;TE;TF;TG;TH;TI;TJ;TK;TL;TM;TN;TO;TP;TQ;TR;TS;TT;Ljava/lang/Object;>;
    MethodParameters:
      Name                           Flags
      fn                             final
      cse                            final

  public static <A extends java.lang.Object, B extends java.lang.Object, C extends java.lang.Object, D extends java.lang.Object, E extends java.lang.Object, F extends java.lang.Object, G extends java.lang.Object, H extends java.lang.Object, I extends java.lang.Object, J extends java.lang.Object, K extends java.lang.Object, L extends java.lang.Object, M extends java.lang.Object, N extends java.lang.Object, O extends java.lang.Object, P extends java.lang.Object, Q extends java.lang.Object, R extends java.lang.Object, S extends java.lang.Object> scala.Function19<A, B, C, D, E, F, G, H, I, J, K, L, M, N, O, P, Q, R, S, java.lang.Object> inst19(shapeless.Poly, shapeless.PolyDefns$Case<? extends shapeless.Poly, shapeless.$colon$colon<A, shapeless.$colon$colon<B, shapeless.$colon$colon<C, shapeless.$colon$colon<D, shapeless.$colon$colon<E, shapeless.$colon$colon<F, shapeless.$colon$colon<G, shapeless.$colon$colon<H, shapeless.$colon$colon<I, shapeless.$colon$colon<J, shapeless.$colon$colon<K, shapeless.$colon$colon<L, shapeless.$colon$colon<M, shapeless.$colon$colon<N, shapeless.$colon$colon<O, shapeless.$colon$colon<P, shapeless.$colon$colon<Q, shapeless.$colon$colon<R, shapeless.$colon$colon<S, shapeless.HNil>>>>>>>>>>>>>>>>>>>>);
    descriptor: (Lshapeless/Poly;Lshapeless/PolyDefns$Case;)Lscala/Function19;
    flags: (0x0009) ACC_PUBLIC, ACC_STATIC
    Code:
      stack=3, locals=2, args_size=2
         0: getstatic     #49                 // Field shapeless/Poly$.MODULE$:Lshapeless/Poly$;
         3: aload_0
         4: aload_1
         5: invokevirtual #72                 // Method shapeless/Poly$.inst19:(Lshapeless/Poly;Lshapeless/PolyDefns$Case;)Lscala/Function19;
         8: areturn
    Signature: #70                          // <A:Ljava/lang/Object;B:Ljava/lang/Object;C:Ljava/lang/Object;D:Ljava/lang/Object;E:Ljava/lang/Object;F:Ljava/lang/Object;G:Ljava/lang/Object;H:Ljava/lang/Object;I:Ljava/lang/Object;J:Ljava/lang/Object;K:Ljava/lang/Object;L:Ljava/lang/Object;M:Ljava/lang/Object;N:Ljava/lang/Object;O:Ljava/lang/Object;P:Ljava/lang/Object;Q:Ljava/lang/Object;R:Ljava/lang/Object;S:Ljava/lang/Object;>(Lshapeless/Poly;Lshapeless/PolyDefns$Case<+Lshapeless/Poly;Lshapeless/$colon$colon<TA;Lshapeless/$colon$colon<TB;Lshapeless/$colon$colon<TC;Lshapeless/$colon$colon<TD;Lshapeless/$colon$colon<TE;Lshapeless/$colon$colon<TF;Lshapeless/$colon$colon<TG;Lshapeless/$colon$colon<TH;Lshapeless/$colon$colon<TI;Lshapeless/$colon$colon<TJ;Lshapeless/$colon$colon<TK;Lshapeless/$colon$colon<TL;Lshapeless/$colon$colon<TM;Lshapeless/$colon$colon<TN;Lshapeless/$colon$colon<TO;Lshapeless/$colon$colon<TP;Lshapeless/$colon$colon<TQ;Lshapeless/$colon$colon<TR;Lshapeless/$colon$colon<TS;Lshapeless/HNil;>;>;>;>;>;>;>;>;>;>;>;>;>;>;>;>;>;>;>;>;)Lscala/Function19<TA;TB;TC;TD;TE;TF;TG;TH;TI;TJ;TK;TL;TM;TN;TO;TP;TQ;TR;TS;Ljava/lang/Object;>;
    MethodParameters:
      Name                           Flags
      fn                             final
      cse                            final

  public static <A extends java.lang.Object, B extends java.lang.Object, C extends java.lang.Object, D extends java.lang.Object, E extends java.lang.Object, F extends java.lang.Object, G extends java.lang.Object, H extends java.lang.Object, I extends java.lang.Object, J extends java.lang.Object, K extends java.lang.Object, L extends java.lang.Object, M extends java.lang.Object, N extends java.lang.Object, O extends java.lang.Object, P extends java.lang.Object, Q extends java.lang.Object, R extends java.lang.Object> scala.Function18<A, B, C, D, E, F, G, H, I, J, K, L, M, N, O, P, Q, R, java.lang.Object> inst18(shapeless.Poly, shapeless.PolyDefns$Case<? extends shapeless.Poly, shapeless.$colon$colon<A, shapeless.$colon$colon<B, shapeless.$colon$colon<C, shapeless.$colon$colon<D, shapeless.$colon$colon<E, shapeless.$colon$colon<F, shapeless.$colon$colon<G, shapeless.$colon$colon<H, shapeless.$colon$colon<I, shapeless.$colon$colon<J, shapeless.$colon$colon<K, shapeless.$colon$colon<L, shapeless.$colon$colon<M, shapeless.$colon$colon<N, shapeless.$colon$colon<O, shapeless.$colon$colon<P, shapeless.$colon$colon<Q, shapeless.$colon$colon<R, shapeless.HNil>>>>>>>>>>>>>>>>>>>);
    descriptor: (Lshapeless/Poly;Lshapeless/PolyDefns$Case;)Lscala/Function18;
    flags: (0x0009) ACC_PUBLIC, ACC_STATIC
    Code:
      stack=3, locals=2, args_size=2
         0: getstatic     #49                 // Field shapeless/Poly$.MODULE$:Lshapeless/Poly$;
         3: aload_0
         4: aload_1
         5: invokevirtual #77                 // Method shapeless/Poly$.inst18:(Lshapeless/Poly;Lshapeless/PolyDefns$Case;)Lscala/Function18;
         8: areturn
    Signature: #75                          // <A:Ljava/lang/Object;B:Ljava/lang/Object;C:Ljava/lang/Object;D:Ljava/lang/Object;E:Ljava/lang/Object;F:Ljava/lang/Object;G:Ljava/lang/Object;H:Ljava/lang/Object;I:Ljava/lang/Object;J:Ljava/lang/Object;K:Ljava/lang/Object;L:Ljava/lang/Object;M:Ljava/lang/Object;N:Ljava/lang/Object;O:Ljava/lang/Object;P:Ljava/lang/Object;Q:Ljava/lang/Object;R:Ljava/lang/Object;>(Lshapeless/Poly;Lshapeless/PolyDefns$Case<+Lshapeless/Poly;Lshapeless/$colon$colon<TA;Lshapeless/$colon$colon<TB;Lshapeless/$colon$colon<TC;Lshapeless/$colon$colon<TD;Lshapeless/$colon$colon<TE;Lshapeless/$colon$colon<TF;Lshapeless/$colon$colon<TG;Lshapeless/$colon$colon<TH;Lshapeless/$colon$colon<TI;Lshapeless/$colon$colon<TJ;Lshapeless/$colon$colon<TK;Lshapeless/$colon$colon<TL;Lshapeless/$colon$colon<TM;Lshapeless/$colon$colon<TN;Lshapeless/$colon$colon<TO;Lshapeless/$colon$colon<TP;Lshapeless/$colon$colon<TQ;Lshapeless/$colon$colon<TR;Lshapeless/HNil;>;>;>;>;>;>;>;>;>;>;>;>;>;>;>;>;>;>;>;)Lscala/Function18<TA;TB;TC;TD;TE;TF;TG;TH;TI;TJ;TK;TL;TM;TN;TO;TP;TQ;TR;Ljava/lang/Object;>;
    MethodParameters:
      Name                           Flags
      fn                             final
      cse                            final

  public static <A extends java.lang.Object, B extends java.lang.Object, C extends java.lang.Object, D extends java.lang.Object, E extends java.lang.Object, F extends java.lang.Object, G extends java.lang.Object, H extends java.lang.Object, I extends java.lang.Object, J extends java.lang.Object, K extends java.lang.Object, L extends java.lang.Object, M extends java.lang.Object, N extends java.lang.Object, O extends java.lang.Object, P extends java.lang.Object, Q extends java.lang.Object> scala.Function17<A, B, C, D, E, F, G, H, I, J, K, L, M, N, O, P, Q, java.lang.Object> inst17(shapeless.Poly, shapeless.PolyDefns$Case<? extends shapeless.Poly, shapeless.$colon$colon<A, shapeless.$colon$colon<B, shapeless.$colon$colon<C, shapeless.$colon$colon<D, shapeless.$colon$colon<E, shapeless.$colon$colon<F, shapeless.$colon$colon<G, shapeless.$colon$colon<H, shapeless.$colon$colon<I, shapeless.$colon$colon<J, shapeless.$colon$colon<K, shapeless.$colon$colon<L, shapeless.$colon$colon<M, shapeless.$colon$colon<N, shapeless.$colon$colon<O, shapeless.$colon$colon<P, shapeless.$colon$colon<Q, shapeless.HNil>>>>>>>>>>>>>>>>>>);
    descriptor: (Lshapeless/Poly;Lshapeless/PolyDefns$Case;)Lscala/Function17;
    flags: (0x0009) ACC_PUBLIC, ACC_STATIC
    Code:
      stack=3, locals=2, args_size=2
         0: getstatic     #49                 // Field shapeless/Poly$.MODULE$:Lshapeless/Poly$;
         3: aload_0
         4: aload_1
         5: invokevirtual #82                 // Method shapeless/Poly$.inst17:(Lshapeless/Poly;Lshapeless/PolyDefns$Case;)Lscala/Function17;
         8: areturn
    Signature: #80                          // <A:Ljava/lang/Object;B:Ljava/lang/Object;C:Ljava/lang/Object;D:Ljava/lang/Object;E:Ljava/lang/Object;F:Ljava/lang/Object;G:Ljava/lang/Object;H:Ljava/lang/Object;I:Ljava/lang/Object;J:Ljava/lang/Object;K:Ljava/lang/Object;L:Ljava/lang/Object;M:Ljava/lang/Object;N:Ljava/lang/Object;O:Ljava/lang/Object;P:Ljava/lang/Object;Q:Ljava/lang/Object;>(Lshapeless/Poly;Lshapeless/PolyDefns$Case<+Lshapeless/Poly;Lshapeless/$colon$colon<TA;Lshapeless/$colon$colon<TB;Lshapeless/$colon$colon<TC;Lshapeless/$colon$colon<TD;Lshapeless/$colon$colon<TE;Lshapeless/$colon$colon<TF;Lshapeless/$colon$colon<TG;Lshapeless/$colon$colon<TH;Lshapeless/$colon$colon<TI;Lshapeless/$colon$colon<TJ;Lshapeless/$colon$colon<TK;Lshapeless/$colon$colon<TL;Lshapeless/$colon$colon<TM;Lshapeless/$colon$colon<TN;Lshapeless/$colon$colon<TO;Lshapeless/$colon$colon<TP;Lshapeless/$colon$colon<TQ;Lshapeless/HNil;>;>;>;>;>;>;>;>;>;>;>;>;>;>;>;>;>;>;)Lscala/Function17<TA;TB;TC;TD;TE;TF;TG;TH;TI;TJ;TK;TL;TM;TN;TO;TP;TQ;Ljava/lang/Object;>;
    MethodParameters:
      Name                           Flags
      fn                             final
      cse                            final

  public static <A extends java.lang.Object, B extends java.lang.Object, C extends java.lang.Object, D extends java.lang.Object, E extends java.lang.Object, F extends java.lang.Object, G extends java.lang.Object, H extends java.lang.Object, I extends java.lang.Object, J extends java.lang.Object, K extends java.lang.Object, L extends java.lang.Object, M extends java.lang.Object, N extends java.lang.Object, O extends java.lang.Object, P extends java.lang.Object> scala.Function16<A, B, C, D, E, F, G, H, I, J, K, L, M, N, O, P, java.lang.Object> inst16(shapeless.Poly, shapeless.PolyDefns$Case<? extends shapeless.Poly, shapeless.$colon$colon<A, shapeless.$colon$colon<B, shapeless.$colon$colon<C, shapeless.$colon$colon<D, shapeless.$colon$colon<E, shapeless.$colon$colon<F, shapeless.$colon$colon<G, shapeless.$colon$colon<H, shapeless.$colon$colon<I, shapeless.$colon$colon<J, shapeless.$colon$colon<K, shapeless.$colon$colon<L, shapeless.$colon$colon<M, shapeless.$colon$colon<N, shapeless.$colon$colon<O, shapeless.$colon$colon<P, shapeless.HNil>>>>>>>>>>>>>>>>>);
    descriptor: (Lshapeless/Poly;Lshapeless/PolyDefns$Case;)Lscala/Function16;
    flags: (0x0009) ACC_PUBLIC, ACC_STATIC
    Code:
      stack=3, locals=2, args_size=2
         0: getstatic     #49                 // Field shapeless/Poly$.MODULE$:Lshapeless/Poly$;
         3: aload_0
         4: aload_1
         5: invokevirtual #87                 // Method shapeless/Poly$.inst16:(Lshapeless/Poly;Lshapeless/PolyDefns$Case;)Lscala/Function16;
         8: areturn
    Signature: #85                          // <A:Ljava/lang/Object;B:Ljava/lang/Object;C:Ljava/lang/Object;D:Ljava/lang/Object;E:Ljava/lang/Object;F:Ljava/lang/Object;G:Ljava/lang/Object;H:Ljava/lang/Object;I:Ljava/lang/Object;J:Ljava/lang/Object;K:Ljava/lang/Object;L:Ljava/lang/Object;M:Ljava/lang/Object;N:Ljava/lang/Object;O:Ljava/lang/Object;P:Ljava/lang/Object;>(Lshapeless/Poly;Lshapeless/PolyDefns$Case<+Lshapeless/Poly;Lshapeless/$colon$colon<TA;Lshapeless/$colon$colon<TB;Lshapeless/$colon$colon<TC;Lshapeless/$colon$colon<TD;Lshapeless/$colon$colon<TE;Lshapeless/$colon$colon<TF;Lshapeless/$colon$colon<TG;Lshapeless/$colon$colon<TH;Lshapeless/$colon$colon<TI;Lshapeless/$colon$colon<TJ;Lshapeless/$colon$colon<TK;Lshapeless/$colon$colon<TL;Lshapeless/$colon$colon<TM;Lshapeless/$colon$colon<TN;Lshapeless/$colon$colon<TO;Lshapeless/$colon$colon<TP;Lshapeless/HNil;>;>;>;>;>;>;>;>;>;>;>;>;>;>;>;>;>;)Lscala/Function16<TA;TB;TC;TD;TE;TF;TG;TH;TI;TJ;TK;TL;TM;TN;TO;TP;Ljava/lang/Object;>;
    MethodParameters:
      Name                           Flags
      fn                             final
      cse                            final

  public static <A extends java.lang.Object, B extends java.lang.Object, C extends java.lang.Object, D extends java.lang.Object, E extends java.lang.Object, F extends java.lang.Object, G extends java.lang.Object, H extends java.lang.Object, I extends java.lang.Object, J extends java.lang.Object, K extends java.lang.Object, L extends java.lang.Object, M extends java.lang.Object, N extends java.lang.Object, O extends java.lang.Object> scala.Function15<A, B, C, D, E, F, G, H, I, J, K, L, M, N, O, java.lang.Object> inst15(shapeless.Poly, shapeless.PolyDefns$Case<? extends shapeless.Poly, shapeless.$colon$colon<A, shapeless.$colon$colon<B, shapeless.$colon$colon<C, shapeless.$colon$colon<D, shapeless.$colon$colon<E, shapeless.$colon$colon<F, shapeless.$colon$colon<G, shapeless.$colon$colon<H, shapeless.$colon$colon<I, shapeless.$colon$colon<J, shapeless.$colon$colon<K, shapeless.$colon$colon<L, shapeless.$colon$colon<M, shapeless.$colon$colon<N, shapeless.$colon$colon<O, shapeless.HNil>>>>>>>>>>>>>>>>);
    descriptor: (Lshapeless/Poly;Lshapeless/PolyDefns$Case;)Lscala/Function15;
    flags: (0x0009) ACC_PUBLIC, ACC_STATIC
    Code:
      stack=3, locals=2, args_size=2
         0: getstatic     #49                 // Field shapeless/Poly$.MODULE$:Lshapeless/Poly$;
         3: aload_0
         4: aload_1
         5: invokevirtual #92                 // Method shapeless/Poly$.inst15:(Lshapeless/Poly;Lshapeless/PolyDefns$Case;)Lscala/Function15;
         8: areturn
    Signature: #90                          // <A:Ljava/lang/Object;B:Ljava/lang/Object;C:Ljava/lang/Object;D:Ljava/lang/Object;E:Ljava/lang/Object;F:Ljava/lang/Object;G:Ljava/lang/Object;H:Ljava/lang/Object;I:Ljava/lang/Object;J:Ljava/lang/Object;K:Ljava/lang/Object;L:Ljava/lang/Object;M:Ljava/lang/Object;N:Ljava/lang/Object;O:Ljava/lang/Object;>(Lshapeless/Poly;Lshapeless/PolyDefns$Case<+Lshapeless/Poly;Lshapeless/$colon$colon<TA;Lshapeless/$colon$colon<TB;Lshapeless/$colon$colon<TC;Lshapeless/$colon$colon<TD;Lshapeless/$colon$colon<TE;Lshapeless/$colon$colon<TF;Lshapeless/$colon$colon<TG;Lshapeless/$colon$colon<TH;Lshapeless/$colon$colon<TI;Lshapeless/$colon$colon<TJ;Lshapeless/$colon$colon<TK;Lshapeless/$colon$colon<TL;Lshapeless/$colon$colon<TM;Lshapeless/$colon$colon<TN;Lshapeless/$colon$colon<TO;Lshapeless/HNil;>;>;>;>;>;>;>;>;>;>;>;>;>;>;>;>;)Lscala/Function15<TA;TB;TC;TD;TE;TF;TG;TH;TI;TJ;TK;TL;TM;TN;TO;Ljava/lang/Object;>;
    MethodParameters:
      Name                           Flags
      fn                             final
      cse                            final

  public static <A extends java.lang.Object, B extends java.lang.Object, C extends java.lang.Object, D extends java.lang.Object, E extends java.lang.Object, F extends java.lang.Object, G extends java.lang.Object, H extends java.lang.Object, I extends java.lang.Object, J extends java.lang.Object, K extends java.lang.Object, L extends java.lang.Object, M extends java.lang.Object, N extends java.lang.Object> scala.Function14<A, B, C, D, E, F, G, H, I, J, K, L, M, N, java.lang.Object> inst14(shapeless.Poly, shapeless.PolyDefns$Case<? extends shapeless.Poly, shapeless.$colon$colon<A, shapeless.$colon$colon<B, shapeless.$colon$colon<C, shapeless.$colon$colon<D, shapeless.$colon$colon<E, shapeless.$colon$colon<F, shapeless.$colon$colon<G, shapeless.$colon$colon<H, shapeless.$colon$colon<I, shapeless.$colon$colon<J, shapeless.$colon$colon<K, shapeless.$colon$colon<L, shapeless.$colon$colon<M, shapeless.$colon$colon<N, shapeless.HNil>>>>>>>>>>>>>>>);
    descriptor: (Lshapeless/Poly;Lshapeless/PolyDefns$Case;)Lscala/Function14;
    flags: (0x0009) ACC_PUBLIC, ACC_STATIC
    Code:
      stack=3, locals=2, args_size=2
         0: getstatic     #49                 // Field shapeless/Poly$.MODULE$:Lshapeless/Poly$;
         3: aload_0
         4: aload_1
         5: invokevirtual #97                 // Method shapeless/Poly$.inst14:(Lshapeless/Poly;Lshapeless/PolyDefns$Case;)Lscala/Function14;
         8: areturn
    Signature: #95                          // <A:Ljava/lang/Object;B:Ljava/lang/Object;C:Ljava/lang/Object;D:Ljava/lang/Object;E:Ljava/lang/Object;F:Ljava/lang/Object;G:Ljava/lang/Object;H:Ljava/lang/Object;I:Ljava/lang/Object;J:Ljava/lang/Object;K:Ljava/lang/Object;L:Ljava/lang/Object;M:Ljava/lang/Object;N:Ljava/lang/Object;>(Lshapeless/Poly;Lshapeless/PolyDefns$Case<+Lshapeless/Poly;Lshapeless/$colon$colon<TA;Lshapeless/$colon$colon<TB;Lshapeless/$colon$colon<TC;Lshapeless/$colon$colon<TD;Lshapeless/$colon$colon<TE;Lshapeless/$colon$colon<TF;Lshapeless/$colon$colon<TG;Lshapeless/$colon$colon<TH;Lshapeless/$colon$colon<TI;Lshapeless/$colon$colon<TJ;Lshapeless/$colon$colon<TK;Lshapeless/$colon$colon<TL;Lshapeless/$colon$colon<TM;Lshapeless/$colon$colon<TN;Lshapeless/HNil;>;>;>;>;>;>;>;>;>;>;>;>;>;>;>;)Lscala/Function14<TA;TB;TC;TD;TE;TF;TG;TH;TI;TJ;TK;TL;TM;TN;Ljava/lang/Object;>;
    MethodParameters:
      Name                           Flags
      fn                             final
      cse                            final

  public static <A extends java.lang.Object, B extends java.lang.Object, C extends java.lang.Object, D extends java.lang.Object, E extends java.lang.Object, F extends java.lang.Object, G extends java.lang.Object, H extends java.lang.Object, I extends java.lang.Object, J extends java.lang.Object, K extends java.lang.Object, L extends java.lang.Object, M extends java.lang.Object> scala.Function13<A, B, C, D, E, F, G, H, I, J, K, L, M, java.lang.Object> inst13(shapeless.Poly, shapeless.PolyDefns$Case<? extends shapeless.Poly, shapeless.$colon$colon<A, shapeless.$colon$colon<B, shapeless.$colon$colon<C, shapeless.$colon$colon<D, shapeless.$colon$colon<E, shapeless.$colon$colon<F, shapeless.$colon$colon<G, shapeless.$colon$colon<H, shapeless.$colon$colon<I, shapeless.$colon$colon<J, shapeless.$colon$colon<K, shapeless.$colon$colon<L, shapeless.$colon$colon<M, shapeless.HNil>>>>>>>>>>>>>>);
    descriptor: (Lshapeless/Poly;Lshapeless/PolyDefns$Case;)Lscala/Function13;
    flags: (0x0009) ACC_PUBLIC, ACC_STATIC
    Code:
      stack=3, locals=2, args_size=2
         0: getstatic     #49                 // Field shapeless/Poly$.MODULE$:Lshapeless/Poly$;
         3: aload_0
         4: aload_1
         5: invokevirtual #102                // Method shapeless/Poly$.inst13:(Lshapeless/Poly;Lshapeless/PolyDefns$Case;)Lscala/Function13;
         8: areturn
    Signature: #100                         // <A:Ljava/lang/Object;B:Ljava/lang/Object;C:Ljava/lang/Object;D:Ljava/lang/Object;E:Ljava/lang/Object;F:Ljava/lang/Object;G:Ljava/lang/Object;H:Ljava/lang/Object;I:Ljava/lang/Object;J:Ljava/lang/Object;K:Ljava/lang/Object;L:Ljava/lang/Object;M:Ljava/lang/Object;>(Lshapeless/Poly;Lshapeless/PolyDefns$Case<+Lshapeless/Poly;Lshapeless/$colon$colon<TA;Lshapeless/$colon$colon<TB;Lshapeless/$colon$colon<TC;Lshapeless/$colon$colon<TD;Lshapeless/$colon$colon<TE;Lshapeless/$colon$colon<TF;Lshapeless/$colon$colon<TG;Lshapeless/$colon$colon<TH;Lshapeless/$colon$colon<TI;Lshapeless/$colon$colon<TJ;Lshapeless/$colon$colon<TK;Lshapeless/$colon$colon<TL;Lshapeless/$colon$colon<TM;Lshapeless/HNil;>;>;>;>;>;>;>;>;>;>;>;>;>;>;)Lscala/Function13<TA;TB;TC;TD;TE;TF;TG;TH;TI;TJ;TK;TL;TM;Ljava/lang/Object;>;
    MethodParameters:
      Name                           Flags
      fn                             final
      cse                            final

  public static <A extends java.lang.Object, B extends java.lang.Object, C extends java.lang.Object, D extends java.lang.Object, E extends java.lang.Object, F extends java.lang.Object, G extends java.lang.Object, H extends java.lang.Object, I extends java.lang.Object, J extends java.lang.Object, K extends java.lang.Object, L extends java.lang.Object> scala.Function12<A, B, C, D, E, F, G, H, I, J, K, L, java.lang.Object> inst12(shapeless.Poly, shapeless.PolyDefns$Case<? extends shapeless.Poly, shapeless.$colon$colon<A, shapeless.$colon$colon<B, shapeless.$colon$colon<C, shapeless.$colon$colon<D, shapeless.$colon$colon<E, shapeless.$colon$colon<F, shapeless.$colon$colon<G, shapeless.$colon$colon<H, shapeless.$colon$colon<I, shapeless.$colon$colon<J, shapeless.$colon$colon<K, shapeless.$colon$colon<L, shapeless.HNil>>>>>>>>>>>>>);
    descriptor: (Lshapeless/Poly;Lshapeless/PolyDefns$Case;)Lscala/Function12;
    flags: (0x0009) ACC_PUBLIC, ACC_STATIC
    Code:
      stack=3, locals=2, args_size=2
         0: getstatic     #49                 // Field shapeless/Poly$.MODULE$:Lshapeless/Poly$;
         3: aload_0
         4: aload_1
         5: invokevirtual #107                // Method shapeless/Poly$.inst12:(Lshapeless/Poly;Lshapeless/PolyDefns$Case;)Lscala/Function12;
         8: areturn
    Signature: #105                         // <A:Ljava/lang/Object;B:Ljava/lang/Object;C:Ljava/lang/Object;D:Ljava/lang/Object;E:Ljava/lang/Object;F:Ljava/lang/Object;G:Ljava/lang/Object;H:Ljava/lang/Object;I:Ljava/lang/Object;J:Ljava/lang/Object;K:Ljava/lang/Object;L:Ljava/lang/Object;>(Lshapeless/Poly;Lshapeless/PolyDefns$Case<+Lshapeless/Poly;Lshapeless/$colon$colon<TA;Lshapeless/$colon$colon<TB;Lshapeless/$colon$colon<TC;Lshapeless/$colon$colon<TD;Lshapeless/$colon$colon<TE;Lshapeless/$colon$colon<TF;Lshapeless/$colon$colon<TG;Lshapeless/$colon$colon<TH;Lshapeless/$colon$colon<TI;Lshapeless/$colon$colon<TJ;Lshapeless/$colon$colon<TK;Lshapeless/$colon$colon<TL;Lshapeless/HNil;>;>;>;>;>;>;>;>;>;>;>;>;>;)Lscala/Function12<TA;TB;TC;TD;TE;TF;TG;TH;TI;TJ;TK;TL;Ljava/lang/Object;>;
    MethodParameters:
      Name                           Flags
      fn                             final
      cse                            final

  public static <A extends java.lang.Object, B extends java.lang.Object, C extends java.lang.Object, D extends java.lang.Object, E extends java.lang.Object, F extends java.lang.Object, G extends java.lang.Object, H extends java.lang.Object, I extends java.lang.Object, J extends java.lang.Object, K extends java.lang.Object> scala.Function11<A, B, C, D, E, F, G, H, I, J, K, java.lang.Object> inst11(shapeless.Poly, shapeless.PolyDefns$Case<? extends shapeless.Poly, shapeless.$colon$colon<A, shapeless.$colon$colon<B, shapeless.$colon$colon<C, shapeless.$colon$colon<D, shapeless.$colon$colon<E, shapeless.$colon$colon<F, shapeless.$colon$colon<G, shapeless.$colon$colon<H, shapeless.$colon$colon<I, shapeless.$colon$colon<J, shapeless.$colon$colon<K, shapeless.HNil>>>>>>>>>>>>);
    descriptor: (Lshapeless/Poly;Lshapeless/PolyDefns$Case;)Lscala/Function11;
    flags: (0x0009) ACC_PUBLIC, ACC_STATIC
    Code:
      stack=3, locals=2, args_size=2
         0: getstatic     #49                 // Field shapeless/Poly$.MODULE$:Lshapeless/Poly$;
         3: aload_0
         4: aload_1
         5: invokevirtual #112                // Method shapeless/Poly$.inst11:(Lshapeless/Poly;Lshapeless/PolyDefns$Case;)Lscala/Function11;
         8: areturn
    Signature: #110                         // <A:Ljava/lang/Object;B:Ljava/lang/Object;C:Ljava/lang/Object;D:Ljava/lang/Object;E:Ljava/lang/Object;F:Ljava/lang/Object;G:Ljava/lang/Object;H:Ljava/lang/Object;I:Ljava/lang/Object;J:Ljava/lang/Object;K:Ljava/lang/Object;>(Lshapeless/Poly;Lshapeless/PolyDefns$Case<+Lshapeless/Poly;Lshapeless/$colon$colon<TA;Lshapeless/$colon$colon<TB;Lshapeless/$colon$colon<TC;Lshapeless/$colon$colon<TD;Lshapeless/$colon$colon<TE;Lshapeless/$colon$colon<TF;Lshapeless/$colon$colon<TG;Lshapeless/$colon$colon<TH;Lshapeless/$colon$colon<TI;Lshapeless/$colon$colon<TJ;Lshapeless/$colon$colon<TK;Lshapeless/HNil;>;>;>;>;>;>;>;>;>;>;>;>;)Lscala/Function11<TA;TB;TC;TD;TE;TF;TG;TH;TI;TJ;TK;Ljava/lang/Object;>;
    MethodParameters:
      Name                           Flags
      fn                             final
      cse                            final

  public static <A extends java.lang.Object, B extends java.lang.Object, C extends java.lang.Object, D extends java.lang.Object, E extends java.lang.Object, F extends java.lang.Object, G extends java.lang.Object, H extends java.lang.Object, I extends java.lang.Object, J extends java.lang.Object> scala.Function10<A, B, C, D, E, F, G, H, I, J, java.lang.Object> inst10(shapeless.Poly, shapeless.PolyDefns$Case<? extends shapeless.Poly, shapeless.$colon$colon<A, shapeless.$colon$colon<B, shapeless.$colon$colon<C, shapeless.$colon$colon<D, shapeless.$colon$colon<E, shapeless.$colon$colon<F, shapeless.$colon$colon<G, shapeless.$colon$colon<H, shapeless.$colon$colon<I, shapeless.$colon$colon<J, shapeless.HNil>>>>>>>>>>>);
    descriptor: (Lshapeless/Poly;Lshapeless/PolyDefns$Case;)Lscala/Function10;
    flags: (0x0009) ACC_PUBLIC, ACC_STATIC
    Code:
      stack=3, locals=2, args_size=2
         0: getstatic     #49                 // Field shapeless/Poly$.MODULE$:Lshapeless/Poly$;
         3: aload_0
         4: aload_1
         5: invokevirtual #117                // Method shapeless/Poly$.inst10:(Lshapeless/Poly;Lshapeless/PolyDefns$Case;)Lscala/Function10;
         8: areturn
    Signature: #115                         // <A:Ljava/lang/Object;B:Ljava/lang/Object;C:Ljava/lang/Object;D:Ljava/lang/Object;E:Ljava/lang/Object;F:Ljava/lang/Object;G:Ljava/lang/Object;H:Ljava/lang/Object;I:Ljava/lang/Object;J:Ljava/lang/Object;>(Lshapeless/Poly;Lshapeless/PolyDefns$Case<+Lshapeless/Poly;Lshapeless/$colon$colon<TA;Lshapeless/$colon$colon<TB;Lshapeless/$colon$colon<TC;Lshapeless/$colon$colon<TD;Lshapeless/$colon$colon<TE;Lshapeless/$colon$colon<TF;Lshapeless/$colon$colon<TG;Lshapeless/$colon$colon<TH;Lshapeless/$colon$colon<TI;Lshapeless/$colon$colon<TJ;Lshapeless/HNil;>;>;>;>;>;>;>;>;>;>;>;)Lscala/Function10<TA;TB;TC;TD;TE;TF;TG;TH;TI;TJ;Ljava/lang/Object;>;
    MethodParameters:
      Name                           Flags
      fn                             final
      cse                            final

  public static <A extends java.lang.Object, B extends java.lang.Object, C extends java.lang.Object, D extends java.lang.Object, E extends java.lang.Object, F extends java.lang.Object, G extends java.lang.Object, H extends java.lang.Object, I extends java.lang.Object> scala.Function9<A, B, C, D, E, F, G, H, I, java.lang.Object> inst9(shapeless.Poly, shapeless.PolyDefns$Case<? extends shapeless.Poly, shapeless.$colon$colon<A, shapeless.$colon$colon<B, shapeless.$colon$colon<C, shapeless.$colon$colon<D, shapeless.$colon$colon<E, shapeless.$colon$colon<F, shapeless.$colon$colon<G, shapeless.$colon$colon<H, shapeless.$colon$colon<I, shapeless.HNil>>>>>>>>>>);
    descriptor: (Lshapeless/Poly;Lshapeless/PolyDefns$Case;)Lscala/Function9;
    flags: (0x0009) ACC_PUBLIC, ACC_STATIC
    Code:
      stack=3, locals=2, args_size=2
         0: getstatic     #49                 // Field shapeless/Poly$.MODULE$:Lshapeless/Poly$;
         3: aload_0
         4: aload_1
         5: invokevirtual #122                // Method shapeless/Poly$.inst9:(Lshapeless/Poly;Lshapeless/PolyDefns$Case;)Lscala/Function9;
         8: areturn
    Signature: #120                         // <A:Ljava/lang/Object;B:Ljava/lang/Object;C:Ljava/lang/Object;D:Ljava/lang/Object;E:Ljava/lang/Object;F:Ljava/lang/Object;G:Ljava/lang/Object;H:Ljava/lang/Object;I:Ljava/lang/Object;>(Lshapeless/Poly;Lshapeless/PolyDefns$Case<+Lshapeless/Poly;Lshapeless/$colon$colon<TA;Lshapeless/$colon$colon<TB;Lshapeless/$colon$colon<TC;Lshapeless/$colon$colon<TD;Lshapeless/$colon$colon<TE;Lshapeless/$colon$colon<TF;Lshapeless/$colon$colon<TG;Lshapeless/$colon$colon<TH;Lshapeless/$colon$colon<TI;Lshapeless/HNil;>;>;>;>;>;>;>;>;>;>;)Lscala/Function9<TA;TB;TC;TD;TE;TF;TG;TH;TI;Ljava/lang/Object;>;
    MethodParameters:
      Name                           Flags
      fn                             final
      cse                            final

  public static <A extends java.lang.Object, B extends java.lang.Object, C extends java.lang.Object, D extends java.lang.Object, E extends java.lang.Object, F extends java.lang.Object, G extends java.lang.Object, H extends java.lang.Object> scala.Function8<A, B, C, D, E, F, G, H, java.lang.Object> inst8(shapeless.Poly, shapeless.PolyDefns$Case<? extends shapeless.Poly, shapeless.$colon$colon<A, shapeless.$colon$colon<B, shapeless.$colon$colon<C, shapeless.$colon$colon<D, shapeless.$colon$colon<E, shapeless.$colon$colon<F, shapeless.$colon$colon<G, shapeless.$colon$colon<H, shapeless.HNil>>>>>>>>>);
    descriptor: (Lshapeless/Poly;Lshapeless/PolyDefns$Case;)Lscala/Function8;
    flags: (0x0009) ACC_PUBLIC, ACC_STATIC
    Code:
      stack=3, locals=2, args_size=2
         0: getstatic     #49                 // Field shapeless/Poly$.MODULE$:Lshapeless/Poly$;
         3: aload_0
         4: aload_1
         5: invokevirtual #127                // Method shapeless/Poly$.inst8:(Lshapeless/Poly;Lshapeless/PolyDefns$Case;)Lscala/Function8;
         8: areturn
    Signature: #125                         // <A:Ljava/lang/Object;B:Ljava/lang/Object;C:Ljava/lang/Object;D:Ljava/lang/Object;E:Ljava/lang/Object;F:Ljava/lang/Object;G:Ljava/lang/Object;H:Ljava/lang/Object;>(Lshapeless/Poly;Lshapeless/PolyDefns$Case<+Lshapeless/Poly;Lshapeless/$colon$colon<TA;Lshapeless/$colon$colon<TB;Lshapeless/$colon$colon<TC;Lshapeless/$colon$colon<TD;Lshapeless/$colon$colon<TE;Lshapeless/$colon$colon<TF;Lshapeless/$colon$colon<TG;Lshapeless/$colon$colon<TH;Lshapeless/HNil;>;>;>;>;>;>;>;>;>;)Lscala/Function8<TA;TB;TC;TD;TE;TF;TG;TH;Ljava/lang/Object;>;
    MethodParameters:
      Name                           Flags
      fn                             final
      cse                            final

  public static <A extends java.lang.Object, B extends java.lang.Object, C extends java.lang.Object, D extends java.lang.Object, E extends java.lang.Object, F extends java.lang.Object, G extends java.lang.Object> scala.Function7<A, B, C, D, E, F, G, java.lang.Object> inst7(shapeless.Poly, shapeless.PolyDefns$Case<? extends shapeless.Poly, shapeless.$colon$colon<A, shapeless.$colon$colon<B, shapeless.$colon$colon<C, shapeless.$colon$colon<D, shapeless.$colon$colon<E, shapeless.$colon$colon<F, shapeless.$colon$colon<G, shapeless.HNil>>>>>>>>);
    descriptor: (Lshapeless/Poly;Lshapeless/PolyDefns$Case;)Lscala/Function7;
    flags: (0x0009) ACC_PUBLIC, ACC_STATIC
    Code:
      stack=3, locals=2, args_size=2
         0: getstatic     #49                 // Field shapeless/Poly$.MODULE$:Lshapeless/Poly$;
         3: aload_0
         4: aload_1
         5: invokevirtual #132                // Method shapeless/Poly$.inst7:(Lshapeless/Poly;Lshapeless/PolyDefns$Case;)Lscala/Function7;
         8: areturn
    Signature: #130                         // <A:Ljava/lang/Object;B:Ljava/lang/Object;C:Ljava/lang/Object;D:Ljava/lang/Object;E:Ljava/lang/Object;F:Ljava/lang/Object;G:Ljava/lang/Object;>(Lshapeless/Poly;Lshapeless/PolyDefns$Case<+Lshapeless/Poly;Lshapeless/$colon$colon<TA;Lshapeless/$colon$colon<TB;Lshapeless/$colon$colon<TC;Lshapeless/$colon$colon<TD;Lshapeless/$colon$colon<TE;Lshapeless/$colon$colon<TF;Lshapeless/$colon$colon<TG;Lshapeless/HNil;>;>;>;>;>;>;>;>;)Lscala/Function7<TA;TB;TC;TD;TE;TF;TG;Ljava/lang/Object;>;
    MethodParameters:
      Name                           Flags
      fn                             final
      cse                            final

  public static <A extends java.lang.Object, B extends java.lang.Object, C extends java.lang.Object, D extends java.lang.Object, E extends java.lang.Object, F extends java.lang.Object> scala.Function6<A, B, C, D, E, F, java.lang.Object> inst6(shapeless.Poly, shapeless.PolyDefns$Case<? extends shapeless.Poly, shapeless.$colon$colon<A, shapeless.$colon$colon<B, shapeless.$colon$colon<C, shapeless.$colon$colon<D, shapeless.$colon$colon<E, shapeless.$colon$colon<F, shapeless.HNil>>>>>>>);
    descriptor: (Lshapeless/Poly;Lshapeless/PolyDefns$Case;)Lscala/Function6;
    flags: (0x0009) ACC_PUBLIC, ACC_STATIC
    Code:
      stack=3, locals=2, args_size=2
         0: getstatic     #49                 // Field shapeless/Poly$.MODULE$:Lshapeless/Poly$;
         3: aload_0
         4: aload_1
         5: invokevirtual #137                // Method shapeless/Poly$.inst6:(Lshapeless/Poly;Lshapeless/PolyDefns$Case;)Lscala/Function6;
         8: areturn
    Signature: #135                         // <A:Ljava/lang/Object;B:Ljava/lang/Object;C:Ljava/lang/Object;D:Ljava/lang/Object;E:Ljava/lang/Object;F:Ljava/lang/Object;>(Lshapeless/Poly;Lshapeless/PolyDefns$Case<+Lshapeless/Poly;Lshapeless/$colon$colon<TA;Lshapeless/$colon$colon<TB;Lshapeless/$colon$colon<TC;Lshapeless/$colon$colon<TD;Lshapeless/$colon$colon<TE;Lshapeless/$colon$colon<TF;Lshapeless/HNil;>;>;>;>;>;>;>;)Lscala/Function6<TA;TB;TC;TD;TE;TF;Ljava/lang/Object;>;
    MethodParameters:
      Name                           Flags
      fn                             final
      cse                            final

  public static <A extends java.lang.Object, B extends java.lang.Object, C extends java.lang.Object, D extends java.lang.Object, E extends java.lang.Object> scala.Function5<A, B, C, D, E, java.lang.Object> inst5(shapeless.Poly, shapeless.PolyDefns$Case<? extends shapeless.Poly, shapeless.$colon$colon<A, shapeless.$colon$colon<B, shapeless.$colon$colon<C, shapeless.$colon$colon<D, shapeless.$colon$colon<E, shapeless.HNil>>>>>>);
    descriptor: (Lshapeless/Poly;Lshapeless/PolyDefns$Case;)Lscala/Function5;
    flags: (0x0009) ACC_PUBLIC, ACC_STATIC
    Code:
      stack=3, locals=2, args_size=2
         0: getstatic     #49                 // Field shapeless/Poly$.MODULE$:Lshapeless/Poly$;
         3: aload_0
         4: aload_1
         5: invokevirtual #142                // Method shapeless/Poly$.inst5:(Lshapeless/Poly;Lshapeless/PolyDefns$Case;)Lscala/Function5;
         8: areturn
    Signature: #140                         // <A:Ljava/lang/Object;B:Ljava/lang/Object;C:Ljava/lang/Object;D:Ljava/lang/Object;E:Ljava/lang/Object;>(Lshapeless/Poly;Lshapeless/PolyDefns$Case<+Lshapeless/Poly;Lshapeless/$colon$colon<TA;Lshapeless/$colon$colon<TB;Lshapeless/$colon$colon<TC;Lshapeless/$colon$colon<TD;Lshapeless/$colon$colon<TE;Lshapeless/HNil;>;>;>;>;>;>;)Lscala/Function5<TA;TB;TC;TD;TE;Ljava/lang/Object;>;
    MethodParameters:
      Name                           Flags
      fn                             final
      cse                            final

  public static <A extends java.lang.Object, B extends java.lang.Object, C extends java.lang.Object, D extends java.lang.Object> scala.Function4<A, B, C, D, java.lang.Object> inst4(shapeless.Poly, shapeless.PolyDefns$Case<? extends shapeless.Poly, shapeless.$colon$colon<A, shapeless.$colon$colon<B, shapeless.$colon$colon<C, shapeless.$colon$colon<D, shapeless.HNil>>>>>);
    descriptor: (Lshapeless/Poly;Lshapeless/PolyDefns$Case;)Lscala/Function4;
    flags: (0x0009) ACC_PUBLIC, ACC_STATIC
    Code:
      stack=3, locals=2, args_size=2
         0: getstatic     #49                 // Field shapeless/Poly$.MODULE$:Lshapeless/Poly$;
         3: aload_0
         4: aload_1
         5: invokevirtual #147                // Method shapeless/Poly$.inst4:(Lshapeless/Poly;Lshapeless/PolyDefns$Case;)Lscala/Function4;
         8: areturn
    Signature: #145                         // <A:Ljava/lang/Object;B:Ljava/lang/Object;C:Ljava/lang/Object;D:Ljava/lang/Object;>(Lshapeless/Poly;Lshapeless/PolyDefns$Case<+Lshapeless/Poly;Lshapeless/$colon$colon<TA;Lshapeless/$colon$colon<TB;Lshapeless/$colon$colon<TC;Lshapeless/$colon$colon<TD;Lshapeless/HNil;>;>;>;>;>;)Lscala/Function4<TA;TB;TC;TD;Ljava/lang/Object;>;
    MethodParameters:
      Name                           Flags
      fn                             final
      cse                            final

  public static <A extends java.lang.Object, B extends java.lang.Object, C extends java.lang.Object> scala.Function3<A, B, C, java.lang.Object> inst3(shapeless.Poly, shapeless.PolyDefns$Case<? extends shapeless.Poly, shapeless.$colon$colon<A, shapeless.$colon$colon<B, shapeless.$colon$colon<C, shapeless.HNil>>>>);
    descriptor: (Lshapeless/Poly;Lshapeless/PolyDefns$Case;)Lscala/Function3;
    flags: (0x0009) ACC_PUBLIC, ACC_STATIC
    Code:
      stack=3, locals=2, args_size=2
         0: getstatic     #49                 // Field shapeless/Poly$.MODULE$:Lshapeless/Poly$;
         3: aload_0
         4: aload_1
         5: invokevirtual #152                // Method shapeless/Poly$.inst3:(Lshapeless/Poly;Lshapeless/PolyDefns$Case;)Lscala/Function3;
         8: areturn
    Signature: #150                         // <A:Ljava/lang/Object;B:Ljava/lang/Object;C:Ljava/lang/Object;>(Lshapeless/Poly;Lshapeless/PolyDefns$Case<+Lshapeless/Poly;Lshapeless/$colon$colon<TA;Lshapeless/$colon$colon<TB;Lshapeless/$colon$colon<TC;Lshapeless/HNil;>;>;>;>;)Lscala/Function3<TA;TB;TC;Ljava/lang/Object;>;
    MethodParameters:
      Name                           Flags
      fn                             final
      cse                            final

  public static <A extends java.lang.Object, B extends java.lang.Object> scala.Function2<A, B, java.lang.Object> inst2(shapeless.Poly, shapeless.PolyDefns$Case<? extends shapeless.Poly, shapeless.$colon$colon<A, shapeless.$colon$colon<B, shapeless.HNil>>>);
    descriptor: (Lshapeless/Poly;Lshapeless/PolyDefns$Case;)Lscala/Function2;
    flags: (0x0009) ACC_PUBLIC, ACC_STATIC
    Code:
      stack=3, locals=2, args_size=2
         0: getstatic     #49                 // Field shapeless/Poly$.MODULE$:Lshapeless/Poly$;
         3: aload_0
         4: aload_1
         5: invokevirtual #157                // Method shapeless/Poly$.inst2:(Lshapeless/Poly;Lshapeless/PolyDefns$Case;)Lscala/Function2;
         8: areturn
    Signature: #155                         // <A:Ljava/lang/Object;B:Ljava/lang/Object;>(Lshapeless/Poly;Lshapeless/PolyDefns$Case<+Lshapeless/Poly;Lshapeless/$colon$colon<TA;Lshapeless/$colon$colon<TB;Lshapeless/HNil;>;>;>;)Lscala/Function2<TA;TB;Ljava/lang/Object;>;
    MethodParameters:
      Name                           Flags
      fn                             final
      cse                            final

  public static <A extends java.lang.Object> scala.Function1<A, java.lang.Object> inst1(shapeless.Poly, shapeless.PolyDefns$Case<? extends shapeless.Poly, shapeless.$colon$colon<A, shapeless.HNil>>);
    descriptor: (Lshapeless/Poly;Lshapeless/PolyDefns$Case;)Lscala/Function1;
    flags: (0x0009) ACC_PUBLIC, ACC_STATIC
    Code:
      stack=3, locals=2, args_size=2
         0: getstatic     #49                 // Field shapeless/Poly$.MODULE$:Lshapeless/Poly$;
         3: aload_0
         4: aload_1
         5: invokevirtual #162                // Method shapeless/Poly$.inst1:(Lshapeless/Poly;Lshapeless/PolyDefns$Case;)Lscala/Function1;
         8: areturn
    Signature: #160                         // <A:Ljava/lang/Object;>(Lshapeless/Poly;Lshapeless/PolyDefns$Case<+Lshapeless/Poly;Lshapeless/$colon$colon<TA;Lshapeless/HNil;>;>;)Lscala/Function1<TA;Ljava/lang/Object;>;
    MethodParameters:
      Name                           Flags
      fn                             final
      cse                            final

  public abstract shapeless.Poly$ProductCase$ ProductCase();
    descriptor: ()Lshapeless/Poly$ProductCase$;
    flags: (0x0401) ACC_PUBLIC, ACC_ABSTRACT

  public abstract shapeless.Poly$CaseBuilder$ CaseBuilder();
    descriptor: ()Lshapeless/Poly$CaseBuilder$;
    flags: (0x0401) ACC_PUBLIC, ACC_ABSTRACT

  public static shapeless.PolyDefns$Compose compose$(shapeless.Poly, shapeless.Poly);
    descriptor: (Lshapeless/Poly;Lshapeless/Poly;)Lshapeless/PolyDefns$Compose;
    flags: (0x1009) ACC_PUBLIC, ACC_STATIC, ACC_SYNTHETIC
    Code:
      stack=2, locals=2, args_size=2
         0: aload_0
         1: aload_1
         2: invokespecial #173                // InterfaceMethod compose:(Lshapeless/Poly;)Lshapeless/PolyDefns$Compose;
         5: areturn
      LineNumberTable:
        line 191: 0
      LocalVariableTable:
        Start  Length  Slot  Name   Signature
            0       6     0 $this   Lshapeless/Poly;
            0       6     1     f   Lshapeless/Poly;
    MethodParameters:
      Name                           Flags
      $this                          final synthetic
      f                              final

  public default shapeless.PolyDefns$Compose<shapeless.Poly, shapeless.Poly> compose(shapeless.Poly);
    descriptor: (Lshapeless/Poly;)Lshapeless/PolyDefns$Compose;
    flags: (0x0001) ACC_PUBLIC
    Code:
      stack=4, locals=2, args_size=2
         0: new           #31                 // class shapeless/PolyDefns$Compose
         3: dup
         4: aload_0
         5: aload_1
         6: invokespecial #179                // Method shapeless/PolyDefns$Compose."<init>":(Ljava/lang/Object;Ljava/lang/Object;)V
         9: areturn
      LineNumberTable:
        line 191: 0
      LocalVariableTable:
        Start  Length  Slot  Name   Signature
            0      10     0  this   Lshapeless/Poly;
            0      10     1     f   Lshapeless/Poly;
    Signature: #175                         // (Lshapeless/Poly;)Lshapeless/PolyDefns$Compose<Lshapeless/Poly;Lshapeless/Poly;>;
    MethodParameters:
      Name                           Flags
      f                              final

  public static shapeless.PolyDefns$Compose andThen$(shapeless.Poly, shapeless.Poly);
    descriptor: (Lshapeless/Poly;Lshapeless/Poly;)Lshapeless/PolyDefns$Compose;
    flags: (0x1009) ACC_PUBLIC, ACC_STATIC, ACC_SYNTHETIC
    Code:
      stack=2, locals=2, args_size=2
         0: aload_0
         1: aload_1
         2: invokespecial #184                // InterfaceMethod andThen:(Lshapeless/Poly;)Lshapeless/PolyDefns$Compose;
         5: areturn
      LineNumberTable:
        line 193: 0
      LocalVariableTable:
        Start  Length  Slot  Name   Signature
            0       6     0 $this   Lshapeless/Poly;
            0       6     1     f   Lshapeless/Poly;
    MethodParameters:
      Name                           Flags
      $this                          final synthetic
      f                              final

  public default shapeless.PolyDefns$Compose<shapeless.Poly, shapeless.Poly> andThen(shapeless.Poly);
    descriptor: (Lshapeless/Poly;)Lshapeless/PolyDefns$Compose;
    flags: (0x0001) ACC_PUBLIC
    Code:
      stack=4, locals=2, args_size=2
         0: new           #31                 // class shapeless/PolyDefns$Compose
         3: dup
         4: aload_1
         5: aload_0
         6: invokespecial #179                // Method shapeless/PolyDefns$Compose."<init>":(Ljava/lang/Object;Ljava/lang/Object;)V
         9: areturn
      LineNumberTable:
        line 193: 0
      LocalVariableTable:
        Start  Length  Slot  Name   Signature
            0      10     0  this   Lshapeless/Poly;
            0      10     1     f   Lshapeless/Poly;
    Signature: #175                         // (Lshapeless/Poly;)Lshapeless/PolyDefns$Compose<Lshapeless/Poly;Lshapeless/Poly;>;
    MethodParameters:
      Name                           Flags
      f                              final

  public static shapeless.PolyDefns$RotateLeft rotateLeft$(shapeless.Poly);
    descriptor: (Lshapeless/Poly;)Lshapeless/PolyDefns$RotateLeft;
    flags: (0x1009) ACC_PUBLIC, ACC_STATIC, ACC_SYNTHETIC
    Code:
      stack=1, locals=1, args_size=1
         0: aload_0
         1: invokespecial #190                // InterfaceMethod rotateLeft:()Lshapeless/PolyDefns$RotateLeft;
         4: areturn
      LineNumberTable:
        line 195: 0
      LocalVariableTable:
        Start  Length  Slot  Name   Signature
            0       5     0 $this   Lshapeless/Poly;
    MethodParameters:
      Name                           Flags
      $this                          final synthetic

  public default <N extends shapeless.Nat> shapeless.PolyDefns$RotateLeft<shapeless.Poly, N> rotateLeft();
    descriptor: ()Lshapeless/PolyDefns$RotateLeft;
    flags: (0x0001) ACC_PUBLIC
    Code:
      stack=3, locals=1, args_size=1
         0: new           #34                 // class shapeless/PolyDefns$RotateLeft
         3: dup
         4: aload_0
         5: invokespecial #194                // Method shapeless/PolyDefns$RotateLeft."<init>":(Ljava/lang/Object;)V
         8: areturn
      LineNumberTable:
        line 195: 0
      LocalVariableTable:
        Start  Length  Slot  Name   Signature
            0       9     0  this   Lshapeless/Poly;
    Signature: #191                         // <N::Lshapeless/Nat;>()Lshapeless/PolyDefns$RotateLeft<Lshapeless/Poly;TN;>;

  public static shapeless.PolyDefns$RotateRight rotateRight$(shapeless.Poly);
    descriptor: (Lshapeless/Poly;)Lshapeless/PolyDefns$RotateRight;
    flags: (0x1009) ACC_PUBLIC, ACC_STATIC, ACC_SYNTHETIC
    Code:
      stack=1, locals=1, args_size=1
         0: aload_0
         1: invokespecial #200                // InterfaceMethod rotateRight:()Lshapeless/PolyDefns$RotateRight;
         4: areturn
      LineNumberTable:
        line 197: 0
      LocalVariableTable:
        Start  Length  Slot  Name   Signature
            0       5     0 $this   Lshapeless/Poly;
    MethodParameters:
      Name                           Flags
      $this                          final synthetic

  public default <N extends shapeless.Nat> shapeless.PolyDefns$RotateRight<shapeless.Poly, N> rotateRight();
    descriptor: ()Lshapeless/PolyDefns$RotateRight;
    flags: (0x0001) ACC_PUBLIC
    Code:
      stack=3, locals=1, args_size=1
         0: new           #37                 // class shapeless/PolyDefns$RotateRight
         3: dup
         4: aload_0
         5: invokespecial #202                // Method shapeless/PolyDefns$RotateRight."<init>":(Ljava/lang/Object;)V
         8: areturn
      LineNumberTable:
        line 197: 0
      LocalVariableTable:
        Start  Length  Slot  Name   Signature
            0       9     0  this   Lshapeless/Poly;
    Signature: #201                         // <N::Lshapeless/Nat;>()Lshapeless/PolyDefns$RotateRight<Lshapeless/Poly;TN;>;

  public static shapeless.PolyDefns$Case use$(shapeless.Poly, java.lang.Object, shapeless.Poly$CaseBuilder);
    descriptor: (Lshapeless/Poly;Ljava/lang/Object;Lshapeless/Poly$CaseBuilder;)Lshapeless/PolyDefns$Case;
    flags: (0x1009) ACC_PUBLIC, ACC_STATIC, ACC_SYNTHETIC
    Code:
      stack=3, locals=3, args_size=3
         0: aload_0
         1: aload_1
         2: aload_2
         3: invokespecial #210                // InterfaceMethod use:(Ljava/lang/Object;Lshapeless/Poly$CaseBuilder;)Lshapeless/PolyDefns$Case;
         6: areturn
      LineNumberTable:
        line 214: 0
      LocalVariableTable:
        Start  Length  Slot  Name   Signature
            0       7     0 $this   Lshapeless/Poly;
            0       7     1     t   Ljava/lang/Object;
            0       7     2    cb   Lshapeless/Poly$CaseBuilder;
    MethodParameters:
      Name                           Flags
      $this                          final synthetic
      t                              final
      cb                             final

  public default <T extends java.lang.Object, L extends shapeless.HList, R extends java.lang.Object> shapeless.PolyDefns$Case<shapeless.Poly, L> use(T, shapeless.Poly$CaseBuilder<T, L, R>);
    descriptor: (Ljava/lang/Object;Lshapeless/Poly$CaseBuilder;)Lshapeless/PolyDefns$Case;
    flags: (0x0001) ACC_PUBLIC
    Code:
      stack=2, locals=3, args_size=3
         0: aload_2
         1: aload_1
         2: invokeinterface #217,  2          // InterfaceMethod shapeless/Poly$CaseBuilder.apply:(Ljava/lang/Object;)Lshapeless/PolyDefns$Case;
         7: areturn
      LineNumberTable:
        line 214: 0
      LocalVariableTable:
        Start  Length  Slot  Name   Signature
            0       8     0  this   Lshapeless/Poly;
            0       8     1     t   Ljava/lang/Object;
            0       8     2    cb   Lshapeless/Poly$CaseBuilder;
    Signature: #213                         // <T:Ljava/lang/Object;L::Lshapeless/HList;R:Ljava/lang/Object;>(TT;Lshapeless/Poly$CaseBuilder<TT;TL;TR;>;)Lshapeless/PolyDefns$Case<Lshapeless/Poly;TL;>;
    MethodParameters:
      Name                           Flags
      t                              final
      cb                             final

  public static shapeless.PolyDefns$Case caseAt$(shapeless.Poly, shapeless.PolyDefns$Case);
    descriptor: (Lshapeless/Poly;Lshapeless/PolyDefns$Case;)Lshapeless/PolyDefns$Case;
    flags: (0x1009) ACC_PUBLIC, ACC_STATIC, ACC_SYNTHETIC
    Code:
      stack=2, locals=2, args_size=2
         0: aload_0
         1: aload_1
         2: invokespecial #224                // InterfaceMethod caseAt:(Lshapeless/PolyDefns$Case;)Lshapeless/PolyDefns$Case;
         5: areturn
      LineNumberTable:
        line 236: 0
      LocalVariableTable:
        Start  Length  Slot  Name   Signature
            0       6     0 $this   Lshapeless/Poly;
            0       6     1     c   Lshapeless/PolyDefns$Case;
    MethodParameters:
      Name                           Flags
      $this                          final synthetic
      c                              final

  public default <L extends shapeless.HList> shapeless.PolyDefns$Case<shapeless.Poly, L> caseAt(shapeless.PolyDefns$Case<shapeless.Poly, L>);
    descriptor: (Lshapeless/PolyDefns$Case;)Lshapeless/PolyDefns$Case;
    flags: (0x0001) ACC_PUBLIC
    Code:
      stack=1, locals=2, args_size=2
         0: aload_1
         1: areturn
      LineNumberTable:
        line 236: 0
      LocalVariableTable:
        Start  Length  Slot  Name   Signature
            0       2     0  this   Lshapeless/Poly;
            0       2     1     c   Lshapeless/PolyDefns$Case;
    Signature: #226                         // <L::Lshapeless/HList;>(Lshapeless/PolyDefns$Case<Lshapeless/Poly;TL;>;)Lshapeless/PolyDefns$Case<Lshapeless/Poly;TL;>;
    MethodParameters:
      Name                           Flags
      c                              final

  public static java.lang.Object apply$(shapeless.Poly, shapeless.PolyDefns$Case);
    descriptor: (Lshapeless/Poly;Lshapeless/PolyDefns$Case;)Ljava/lang/Object;
    flags: (0x1009) ACC_PUBLIC, ACC_STATIC, ACC_SYNTHETIC
    Code:
      stack=2, locals=2, args_size=2
         0: aload_0
         1: aload_1
         2: invokespecial #230                // InterfaceMethod apply:(Lshapeless/PolyDefns$Case;)Ljava/lang/Object;
         5: areturn
      LineNumberTable:
        line 238: 0
      LocalVariableTable:
        Start  Length  Slot  Name   Signature
            0       6     0 $this   Lshapeless/Poly;
            0       6     1     c   Lshapeless/PolyDefns$Case;
    MethodParameters:
      Name                           Flags
      $this                          final synthetic
      c                              final

  public default <R extends java.lang.Object> R apply(shapeless.PolyDefns$Case<shapeless.Poly, shapeless.HNil>);
    descriptor: (Lshapeless/PolyDefns$Case;)Ljava/lang/Object;
    flags: (0x0001) ACC_PUBLIC
    Code:
      stack=2, locals=2, args_size=2
         0: aload_1
         1: getstatic     #236                // Field scala/$less$colon$less$.MODULE$:Lscala/$less$colon$less$;
         4: invokevirtual #240                // Method scala/$less$colon$less$.refl:()Lscala/$eq$colon$eq;
         7: invokevirtual #243                // Method shapeless/PolyDefns$Case.apply:(Lscala/$eq$colon$eq;)Ljava/lang/Object;
        10: areturn
      LineNumberTable:
        line 238: 0
      LocalVariableTable:
        Start  Length  Slot  Name   Signature
            0      11     0  this   Lshapeless/Poly;
            0      11     1     c   Lshapeless/PolyDefns$Case;
    Signature: #231                         // <R:Ljava/lang/Object;>(Lshapeless/PolyDefns$Case<Lshapeless/Poly;Lshapeless/HNil;>;)TR;
    MethodParameters:
      Name                           Flags
      c                              final

  public static void $init$(shapeless.Poly);
    descriptor: (Lshapeless/Poly;)V
    flags: (0x0009) ACC_PUBLIC, ACC_STATIC
    Code:
      stack=0, locals=1, args_size=1
         0: return
      LineNumberTable:
        line 188: 0
      LocalVariableTable:
        Start  Length  Slot  Name   Signature
            0       1     0 $this   Lshapeless/Poly;
    MethodParameters:
      Name                           Flags
      $this                          final synthetic
}
InnerClasses:
  public #15= #14 of #2;                  // CaseBuilder=class shapeless/Poly$CaseBuilder of class shapeless/Poly
  public #18= #17 of #2;                  // CaseBuilder$=class shapeless/Poly$CaseBuilder$ of class shapeless/Poly
  public #21= #20 of #2;                  // LowPriorityCaseBuilder=class shapeless/Poly$LowPriorityCaseBuilder of class shapeless/Poly
  public #24= #23 of #2;                  // ProductCase$=class shapeless/Poly$ProductCase$ of class shapeless/Poly
  public static abstract #29= #26 of #28; // Case=class shapeless/PolyDefns$Case of class shapeless/PolyDefns
  public static #32= #31 of #28;          // Compose=class shapeless/PolyDefns$Compose of class shapeless/PolyDefns
  public static #35= #34 of #28;          // RotateLeft=class shapeless/PolyDefns$RotateLeft of class shapeless/PolyDefns
  public static #38= #37 of #28;          // RotateRight=class shapeless/PolyDefns$RotateRight of class shapeless/PolyDefns
SourceFile: "poly.scala"
RuntimeVisibleAnnotations:
  0: #10(#11=s#12)
    scala.reflect.ScalaSignature(
      bytes="\u0006\u0005\tMca\u0002\u0010 !\u0003\r\tA\t\u0005\u0006s\u0001!\tA\u000f\u0005\u0006}\u0001!\ta\u0010\u0005\u0006#\u0002!\tA\u0015\u0005\u0006-\u0002!\ta\u0016\u0005\u0006M\u0002!\taZ\u0003\u0005]\u0002\u0001qnB\u0003{\u0001!\u00051PB\u0003o\u0001!\u0005A\u0010C\u0003~\u0011\u0011\u0005a0B\u0003\u0000\u0011\u0001\t\t!\u0002\u0004\u0002\"!\u0001\u00111\u0005\u0005\b\u0003wAA\u0011AA\u001f\u0011\u001d\ti\u0006\u0001C\u0001\u0003?2\u0011\"a\u001e\u0001!\u0003\r\n!!\u001f\t\u000f\u0005mbB\"\u0001\u0002~\u0019I\u0011q\u0013\u0001\u0011\u0002\u0007\u0005\u0011\u0011\u0014\u0005\u0006sA!\tA\u000f\u0005\b\u00037\u0003B1AAO\u000f\u001d\t9\u000b\u0001E\u0001\u0003S3q!a\u001e\u0001\u0011\u0003\tY\u000b\u0003\u0004~)\u0011\u0005\u0011Q\u0018\u0005\b\u0003\u007f#B1AAa\u0011\u001d\u0011\t\u0001\u0001C\u0001\u0005\u0007Aq!a\u000f\u0001\t\u0003\u0011\tbB\u0004\u0003\u001e}A\tAa\b\u0007\ryy\u0002\u0012\u0001B\u0011\u0011\u0019i(\u0004\"\u0001\u0003*!9!1\u0006\u000e\u0005\u0004\t5\u0002\"\u0003B\"5\u0005\u0005I\u0011\u0002B#\u0005\u0011\u0001v\u000e\\=\u000b\u0003\u0001\n\u0011b\u001d5ba\u0016dWm]:\u0004\u0001M!\u0001aI\u0015.!\t!s%D\u0001&\u0015\u00051\u0013!B:dC2\f\u0017B\u0001\u0015&\u0005\u0019\te.\u001f*fMB\u0011!fK\u0007\u0002?%\u0011Af\b\u0002\n!>d\u00170\u00119qYf\u0004\"A\f\u001c\u000f\u0005=\"dB\u0001\u00194\u001b\u0005\t$B\u0001\u001a\"\u0003\u0019a$o\\8u}%\ta%\u0003\u00026K\u00059\u0001/Y2lC\u001e,\u0017BA\u001c9\u00051\u0019VM]5bY&T\u0018M\u00197f\u0015\t)T%\u0001\u0004%S:LG\u000f\n\u000b\u0002wA\u0011A\u0005P\u0005\u0003{\u0015\u0012A!\u00168ji\u000691m\\7q_N,GC\u0001!O!\u0011\tui\u0013\'\u000f\u0005\t#eB\u0001\u0016D\u0013\t)t$\u0003\u0002F\r\u0006!\u0001o\u001c7z\u0015\t)t$\u0003\u0002I\u0013\n91i\\7q_N,\'B\u0001& \u0003%\u0001v\u000e\\=EK\u001at7/D\u0001\u0001\u001d\tie\n\u0004\u0001\t\u000b=\u0013\u0001\u0019\u0001)\u0002\u0003\u0019\u0004\"A\u000b\u0001\u0002\u000f\u0005tG\r\u00165f]R\u00111+\u0016\t\u0005\u0003\u001e#6J\u0004\u0002N+\")qj\u0001a\u0001!\u0006Q!o\u001c;bi\u0016dUM\u001a;\u0016\u0005akV#A-\u0011\t\u0005S6\nX\u0005\u00037&\u0013!BU8uCR,G*\u001a4u!\tiU\fB\u0003_\t\t\u0007qLA\u0001O#\t\u00017\r\u0005\u0002%C&\u0011!-\n\u0002\b\u001d>$\b.\u001b8h!\tQC-\u0003\u0002f?\t\u0019a*\u0019;\u0002\u0017I|G/\u0019;f%&<\u0007\u000e^\u000b\u0003Q6,\u0012!\u001b\t\u0005\u0003*\\E.\u0003\u0002l\u0013\nY!k\u001c;bi\u0016\u0014\u0016n\u001a5u!\tiU\u000eB\u0003_\u000b\t\u0007qLA\u0006Qe>$Wo\u0019;DCN,WC\u00019u!\u0011\t\u0015oS:\n\u0005IL%\u0001B\"bg\u0016\u0004\"!\u0014;\u0005\u000bU4!\u0019\u0001<\u0003\u00031\u000b\"\u0001Y<\u0011\u0005)B\u0018BA= \u0005\u0015AE*[:u\u0003-\u0001&o\u001c3vGR\u001c\u0015m]3\u0011\u0005-C1c\u0001\u0005$[\u00051A(\u001b8jiz\"\u0012a\u001f\u0002\u0004\u0003VDXCBA\u0002\u0003\u001b\t)B\u0005\u0003\u0002\u0006\u0005%aABA\u0004\u0011\u0001\t\u0019A\u0001\u0007=e\u00164\u0017N\\3nK:$h\b\u0005\u0003L\r\u0005-\u0001cA\'\u0002\u000e\u0011)QO\u0003b\u0001m\u00169\u0011\u0011CA\u0003A\u0005M!A\u0002*fgVdG\u000fE\u0002N\u0003+!q!a\u0006\u000b\u0005\u0004\tIBA\u0004SKN,H\u000e\u001e\u0019\u0012\u0007\u0001\fY\u0002E\u0002%\u0003;I1!a\b&\u0005\r\te.\u001f\u0002\u0004\u0011>lW\u0003BA\u0013\u0003c\u0001r!a\n\u000b\u0003S\ty#D\u0001\t!\u001dQ\u00131FA\u0018\u0003kI1!!\f \u00051!3m\u001c7p]\u0012\u001aw\u000e\\8o!\ri\u0015\u0011\u0007\u0003\b\u0003gY!\u0019AA\r\u0005\u0005!\u0006c\u0001\u0016\u00028%\u0019\u0011\u0011H\u0010\u0003\t!s\u0015\u000e\\\u0001\u0006CB\u0004H._\u000b\u0007\u0003\u007f\tI%a\u0014\u0015\t\u0005\u0005\u00131\u000b\n\u0005\u0003\u0007\n)E\u0002\u0004\u0002\b1\u0001\u0011\u0011\t\t\u0005\u0017\u001a\t9\u0005E\u0002N\u0003\u0013\"Q!\u001e\u0007C\u0002Y,q!!\u0005\u0002D\u0001\ti\u0005E\u0002N\u0003\u001f\"q!!\u0015\r\u0005\u0004\tIBA\u0001S\u0011\u001d\t)\u0006\u0004a\u0001\u0003/\n\u0011A\u001e\t\bI\u0005e\u0013qIA\'\u0013\r\tY&\n\u0002\n\rVt7\r^5p]F\n1!^:f+!\t\t\'a%\u0002l\u0005=D\u0003BA2\u0003+#B!!\u001a\u0002rA9\u0011q\r\u0006\u0002j\u00055dBA&\b!\ri\u00151\u000e\u0003\u0006k6\u0011\rA\u001e\t\u0004\u001b\u0006=DaBA)\u001b\t\u0007\u0011\u0011\u0004\u0005\b\u0003gj\u00019AA;\u0003\t\u0019\'\r\u0005\u0005L\u001d\u0005E\u0015\u0011NA7\u0005-\u0019\u0015m]3Ck&dG-\u001a:\u0016\u0011\u0005m\u0014qRAB\u0003\u000f\u001b2AD\u0012.)\u0011\ty(!#\u0011\u000f\u0005\u001d$\"!!\u0002\u0006B\u0019Q*a!\u0005\u000bUt!\u0019\u0001<\u0011\u00075\u000b9\tB\u0004\u0002R9\u0011\r!!\u0007\t\u000f\u0005-u\u00021\u0001\u0002\u000e\u0006\tA\u000fE\u0002N\u0003\u001f#q!a\r\u000f\u0005\u0004\tI\u0002E\u0002N\u0003\'#q!a\r\u000e\u0005\u0004\tI\u0002C\u0004\u0002\f6\u0001\r!!%\u0003-1{w\u000f\u0015:j_JLG/_\"bg\u0016\u0014U/\u001b7eKJ\u001c\"\u0001E\u0012\u0002!Y\fG.^3DCN,\')^5mI\u0016\u0014X\u0003BAP\u0003K+\"!!)\u0011\u0011-s\u00111UA\u001b\u0003G\u00032!TAS\t\u001d\t\u0019D\u0005b\u0001\u00033\t1bQ1tK\n+\u0018\u000e\u001c3feB\u00111\nF\n\u0007)\r\ni+a,\u0011\u0005-\u0003\u0002\u0003BAY\u0003wk!!a-\u000b\t\u0005U\u0016qW\u0001\u0003S>T!!!/\u0002\t)\fg/Y\u0005\u0004o\u0005MFCAAU\u000351gnQ1tK\n+\u0018\u000e\u001c3feVQ\u00111YAe\u0003#\f9.a7\u0015\t\u0005\u0015\u0017Q\u001c\t\t\u0017:\t9-!4\u0002ZB\u0019Q*!3\u0005\u000f\u0005-gC1\u0001\u0002\u001a\t\ta\tE\u0004+\u0003W\ty-!6\u0011\u00075\u000b\t\u000eB\u0004\u0002TZ\u0011\r!!\u0007\u0003\u0003!\u00032!TAl\t\u0019\t\u0019D\u0006b\u0001mB\u0019Q*a7\u0005\u000f\u0005EaC1\u0001\u0002\u001a!9\u0011q\u001c\fA\u0004\u0005\u0005\u0018\u0001\u00024oiB\u0004\u0002\"a9\u0002z\u0006\u001d\u0017q \b\u0005\u0003K\f\u0019P\u0004\u0003\u0002h\u00065hb\u0001\u0016\u0002j&\u0019\u00111^\u0010\u0002\u0007=\u00048/\u0003\u0003\u0002p\u0006E\u0018\u0001\u00034v]\u000e$\u0018n\u001c8\u000b\u0007\u0005-x$\u0003\u0003\u0002v\u0006]\u0018a\u0003$o)>\u0004&o\u001c3vGRTA!a<\u0002r&\u0019q0a?\n\t\u0005u\u0018\u0011\u001f\u0002\u0015\r:$v\u000e\u0015:pIV\u001cG/\u00138ti\u0006t7-Z:\u0011\u000f\u0011\nI&!4\u0002Z\u000611-Y:f\u0003R,BA!\u0002\u0003\fQ!!q\u0001B\u0007!\u0011YeA!\u0003\u0011\u00075\u0013Y\u0001B\u0003v/\t\u0007a\u000fC\u0004\u0003\u0010]\u0001\u001dAa\u0002\u0002\u0003\r,BAa\u0005\u0003\u0018Q!!Q\u0003B\r!\ri%q\u0003\u0003\b\u0003#B\"\u0019AA\r\u0011\u001d\u0011y\u0001\u0007a\u0002\u00057\u0001r!a\u001a\u000b\u0003k\u0011)\"\u0001\u0003Q_2L\bC\u0001\u0016\u001b\'\u0019Q2Ea\t\u00020B\u0019!F!\n\n\u0007\t\u001drD\u0001\u0005Q_2L\u0018J\\:u)\t\u0011y\"A\u0003j]N$\b\u0007\u0006\u0003\u00030\tuB\u0003\u0002B\u0019\u0005k\u0001BAa\r\u0003B9\u0019QJ!\u000e\t\u000f\t]B\u0004q\u0001\u0003:\u0005\u00191m]3\u0011\u000b\tmb!!\u000e\u000f\u00075\u0013i\u0004\u0003\u0004\u0003@q\u0001\r\u0001U\u0001\u0002a&\u0019\u0011\u0011C9\u0002\u0019]\u0014\u0018\u000e^3SKBd\u0017mY3\u0015\u0005\t\u001d\u0003\u0003\u0002B%\u0005\u001fj!Aa\u0013\u000b\t\t5\u0013qW\u0001\u0005Y\u0006tw-\u0003\u0003\u0003R\t-#AB(cU\u0016\u001cG\u000f"
    )
  ScalaInlineInfo: length = 0x59 (unknown attribute)
   01 00 00 11 00 F4 00 F5 01 00 0F 00 A5 00 00 A3
   00 A4 00 00 B5 00 A7 01 00 B6 00 AB 00 00 E3 00
   28 01 00 D6 00 E4 00 00 DA 00 DB 01 00 DD 00 DE
   00 00 A6 00 A7 01 00 AA 00 AB 00 00 B9 00 BA 01
   00 BB 00 BC 00 00 C3 00 C4 01 00 C5 00 C6 00 00
   CB 00 CC 01 00 CF 00 D0 00
  ScalaSig: length = 0x3 (unknown attribute)
   05 02 00
