Classfile /Users/mw/Projects/slang-braindump/.jar/jar8/assemble/slang-braindump/assemble/content/shapeless/Poly3.class
  Last modified May 29, 2022; size 2439 bytes
  SHA-256 checksum 78972263b128c5d6467cac773f0c86df426f4c16cb40a0b93291c8f2cb70bda0
  Compiled from "polyntraits.scala"
public interface shapeless.Poly3 extends shapeless.Poly
  minor version: 0
  major version: 52
  flags: (0x0601) ACC_PUBLIC, ACC_INTERFACE, ACC_ABSTRACT
  this_class: #2                          // shapeless/Poly3
  super_class: #4                         // java/lang/Object
  interfaces: 1, fields: 0, methods: 6, attributes: 5
Constant pool:
   #1 = Utf8               shapeless/Poly3
   #2 = Class              #1             // shapeless/Poly3
   #3 = Utf8               java/lang/Object
   #4 = Class              #3             // java/lang/Object
   #5 = Utf8               shapeless/Poly
   #6 = Class              #5             // shapeless/Poly
   #7 = Utf8               polyntraits.scala
   #8 = Utf8               Lscala/reflect/ScalaSignature;
   #9 = Utf8               bytes
  #10 = Utf8               \u0006\u0005\u0005UcaB\t\u0013!\u0003\r\t!\u0006\u0005\u0006A\u0001!\t!I\u0003\u0005K\u0001\u0001aeB\u0003M\u0001!\u0005QJB\u0003&\u0001!\u0005a\nC\u0003P\t\u0011\u0005\u0001+\u0002\u0003R\t\u0001\u0011f\u0001B3\u0001\u0001\u0019DQaT\u0004\u0005\u0002!DQ\u0001]\u0004\u0005\u0002EDaa \u0001\u0005\u0002\u0005\u0005qaBA\n%!\u0005\u0011Q\u0003\u0004\u0007#IA\t!a\u0006\t\r=cA\u0011AA\u001c\u0011%\tI\u0004\u0004b\u0001\n\u0003\tY\u0004\u0003\u0005\u0002D1\u0001\u000b\u0011BA\u001f\u0011%\t)\u0005DA\u0001\n\u0013\t9EA\u0003Q_2L8GC\u0001\u0014\u0003%\u0019\b.\u00199fY\u0016\u001c8o\u0001\u0001\u0014\u0007\u00011B\u0004\u0005\u0002\u001855\t\u0001DC\u0001\u001a\u0003\u0015\u00198-\u00197b\u0013\tY\u0002D\u0001\u0004B]f\u0014VM\u001a\t\u0003;yi\u0011AE\u0005\u0003?I\u0011A\u0001U8ms\u00061A%\u001b8ji\u0012\"\u0012A\t\t\u0003/\rJ!\u0001\n\r\u0003\tUs\u0017\u000e\u001e\u0002\u0005\u0007\u0006\u001cX-\u0006\u0003(q\r;\u0005\u0003\u0002\u00150eMr!!\u000b\u0017\u000f\u0005uQ\u0013BA\u0016\u0013\u0003\u001d\u0001\u0018mY6bO\u0016L!!\f\u0018\u0002\tA|G.\u001f\u0006\u0003WII!!\n\u0019\u000b\u0005E\u0012\u0012!\u0003)pYf$UM\u001a8t\u001b\u0005\u0001\u0001\u0003B\u000f5m\u0005K!!\u000e\n\u0003\u0019\u0011\u001aw\u000e\\8oI\r|Gn\u001c8\u0011\u0005]BD\u0002\u0001\u0003\u0006s\t\u0011\rA\u000f\u0002\u0002\u0003F\u00111H\u0010\t\u0003/qJ!!\u0010\r\u0003\u000f9{G\u000f[5oOB\u0011qcP\u0005\u0003\u0001b\u00111!\u00118z!\u0011iBGQ#\u0011\u0005]\u001aE!\u0002#\u0003\u0005\u0004Q$!\u0001\"\u0011\tu!d)\u0013\t\u0003o\u001d#Q\u0001\u0013\u0002C\u0002i\u0012\u0011a\u0011\t\u0003;)K!a\u0013\n\u0003\t!s\u0015\u000e\\\u0001\u0005\u0007\u0006\u001cX\r\u0005\u00023\tM\u0011AAF\u0001\u0007y%t\u0017\u000e\u001e \u0015\u00035\u00131!Q;y+\u0015\u0019\u0016\fX0d%\t!fK\u0002\u0003V\t\u0001\u0019&\u0001\u0004\u001fsK\u001aLg.Z7f]Rt\u0004\u0003\u0002\u00150e]\u0003B!\b\u001bY5B\u0011q\'\u0017\u0003\u0006s\u0019\u0011\rA\u000f\t\u0005;QZV\f\u0005\u000289\u0012)AI\u0002b\u0001uA!Q\u0004\u000e0J!\t9t\fB\u0003I\r\t\u0007!(\u0002\u0003b)\u0002\u0012\'A\u0002*fgVdG\u000f\u0005\u00028G\u0012)AM\u0002b\u0001u\t9!+Z:vYR\u0004$aC\"bg\u0016\u0014U/\u001b7eKJ,BaZ6n_N\u0011qA\u0006\u000b\u0002SB)!g\u00026m]B\u0011qg\u001b\u0003\u0006s\u001d\u0011\rA\u000f\t\u0003o5$Q\u0001R\u0004C\u0002i\u0002\"aN8\u0005\u000b!;!\u0019\u0001\u001e\u0002\u000b\u0005\u0004\b\u000f\\=\u0016\u0005IDHCA:{%\t!XO\u0002\u0003V\u0013\u0001\u0019\b#\u0002\u001a\u0003U2tW\u0001B1u\u0001]\u0004\"a\u000e=\u0005\u000beL!\u0019\u0001\u001e\u0003\u0007I+7\u000fC\u0003|\u0013\u0001\u0007A0\u0001\u0002g]B1q# 6m]^L!A \r\u0003\u0013\u0019+hn\u0019;j_:\u001c\u0014AA1u+!\t\u0019!!\u0003\u0002\u000e\u0005EQCAA\u0003!!\u0011t!a\u0002\u0002\f\u0005=\u0001cA\u001c\u0002\n\u0011)\u0011H\u0003b\u0001uA\u0019q\'!\u0004\u0005\u000b\u0011S!\u0019\u0001\u001e\u0011\u0007]\n\t\u0002B\u0003I\u0015\t\u0007!(A\u0003Q_2L8\u0007\u0005\u0002\u001e\u0019M1ABFA\r\u0003O\u0001R!a\u0007\u0002\"%s1!HA\u000f\u0013\r\tyBE\u0001\u000e!>d\u0017P\u0014\"vS2$WM]:\n\t\u0005\r\u0012Q\u0005\u0002\r!>d\u0017p\r\"vS2$WM\u001d\u0006\u0004\u0003?\u0011\u0002\u0003BA\u0015\u0003gi!!a\u000b\u000b\t\u00055\u0012qF\u0001\u0003S>T!!!\r\u0002\t)\fg/Y\u0005\u0005\u0003k\tYC\u0001\u0007TKJL\u0017\r\\5{C\ndW\r\u0006\u0002\u0002\u0016\u0005Ia-\u001e8di&|gn]\u000b\u0003\u0003{q1!HA \u0013\r\t\tEE\u0001\u0005\u0011:KG.\u0001\u0006gk:\u001cG/[8og\u0002\nAb\u001e:ji\u0016\u0014V\r\u001d7bG\u0016$\"!!\u0013\u0011\t\u0005-\u0013\u0011K\u0007\u0003\u0003\u001bRA!a\u0014\u00020\u0005!A.\u00198h\u0013\u0011\t\u0019&!\u0014\u0003\r=\u0013\'.Z2u\u0001
  #11 = Utf8               shapeless/Poly3$Case$
  #12 = Class              #11            // shapeless/Poly3$Case$
  #13 = Utf8               Case$
  #14 = Utf8               shapeless/Poly3$CaseBuilder
  #15 = Class              #14            // shapeless/Poly3$CaseBuilder
  #16 = Utf8               CaseBuilder
  #17 = Utf8               functions
  #18 = Utf8               ()Lshapeless/HNil$;
  #19 = Utf8               shapeless/Poly3$
  #20 = Class              #19            // shapeless/Poly3$
  #21 = Utf8               MODULE$
  #22 = Utf8               Lshapeless/Poly3$;
  #23 = NameAndType        #21:#22        // MODULE$:Lshapeless/Poly3$;
  #24 = Fieldref           #20.#23        // shapeless/Poly3$.MODULE$:Lshapeless/Poly3$;
  #25 = NameAndType        #17:#18        // functions:()Lshapeless/HNil$;
  #26 = Methodref          #20.#25        // shapeless/Poly3$.functions:()Lshapeless/HNil$;
  #27 = Utf8               build
  #28 = Utf8               ()Lshapeless/Poly3;
  #29 = NameAndType        #27:#28        // build:()Lshapeless/Poly3;
  #30 = Methodref          #20.#29        // shapeless/Poly3$.build:()Lshapeless/Poly3;
  #31 = Utf8               Case
  #32 = Utf8               ()Lshapeless/Poly3$Case$;
  #33 = Utf8               at$
  #34 = Utf8               (Lshapeless/Poly3;)Lshapeless/Poly3$CaseBuilder;
  #35 = Utf8               $this
  #36 = Utf8               at
  #37 = Utf8               ()Lshapeless/Poly3$CaseBuilder;
  #38 = NameAndType        #36:#37        // at:()Lshapeless/Poly3$CaseBuilder;
  #39 = InterfaceMethodref #2.#38         // shapeless/Poly3.at:()Lshapeless/Poly3$CaseBuilder;
  #40 = Utf8               Lshapeless/Poly3;
  #41 = Utf8               <A:Ljava/lang/Object;B:Ljava/lang/Object;C:Ljava/lang/Object;>()Lshapeless/Poly3$CaseBuilder<TA;TB;TC;>;
  #42 = Utf8               <init>
  #43 = Utf8               (Lshapeless/Poly3;)V
  #44 = NameAndType        #42:#43        // "<init>":(Lshapeless/Poly3;)V
  #45 = Methodref          #15.#44        // shapeless/Poly3$CaseBuilder."<init>":(Lshapeless/Poly3;)V
  #46 = Utf8               this
  #47 = Utf8               $init$
  #48 = Utf8               Code
  #49 = Utf8               LineNumberTable
  #50 = Utf8               LocalVariableTable
  #51 = Utf8               MethodParameters
  #52 = Utf8               Signature
  #53 = Utf8               InnerClasses
  #54 = Utf8               SourceFile
  #55 = Utf8               RuntimeVisibleAnnotations
  #56 = Utf8               ScalaInlineInfo
  #57 = Utf8               ScalaSig
{
  public static shapeless.HNil$ functions();
    descriptor: ()Lshapeless/HNil$;
    flags: (0x0009) ACC_PUBLIC, ACC_STATIC
    Code:
      stack=1, locals=0, args_size=0
         0: getstatic     #24                 // Field shapeless/Poly3$.MODULE$:Lshapeless/Poly3$;
         3: invokevirtual #26                 // Method shapeless/Poly3$.functions:()Lshapeless/HNil$;
         6: areturn

  public static shapeless.Poly3 build();
    descriptor: ()Lshapeless/Poly3;
    flags: (0x0009) ACC_PUBLIC, ACC_STATIC
    Code:
      stack=1, locals=0, args_size=0
         0: getstatic     #24                 // Field shapeless/Poly3$.MODULE$:Lshapeless/Poly3$;
         3: invokevirtual #30                 // Method shapeless/Poly3$.build:()Lshapeless/Poly3;
         6: areturn

  public abstract shapeless.Poly3$Case$ Case();
    descriptor: ()Lshapeless/Poly3$Case$;
    flags: (0x0401) ACC_PUBLIC, ACC_ABSTRACT

  public static shapeless.Poly3$CaseBuilder at$(shapeless.Poly3);
    descriptor: (Lshapeless/Poly3;)Lshapeless/Poly3$CaseBuilder;
    flags: (0x1009) ACC_PUBLIC, ACC_STATIC, ACC_SYNTHETIC
    Code:
      stack=1, locals=1, args_size=1
         0: aload_0
         1: invokespecial #39                 // InterfaceMethod at:()Lshapeless/Poly3$CaseBuilder;
         4: areturn
      LineNumberTable:
        line 92: 0
      LocalVariableTable:
        Start  Length  Slot  Name   Signature
            0       5     0 $this   Lshapeless/Poly3;
    MethodParameters:
      Name                           Flags
      $this                          final synthetic

  public default <A extends java.lang.Object, B extends java.lang.Object, C extends java.lang.Object> shapeless.Poly3$CaseBuilder<A, B, C> at();
    descriptor: ()Lshapeless/Poly3$CaseBuilder;
    flags: (0x0001) ACC_PUBLIC
    Code:
      stack=3, locals=1, args_size=1
         0: new           #15                 // class shapeless/Poly3$CaseBuilder
         3: dup
         4: aload_0
         5: invokespecial #45                 // Method shapeless/Poly3$CaseBuilder."<init>":(Lshapeless/Poly3;)V
         8: areturn
      LineNumberTable:
        line 93: 0
      LocalVariableTable:
        Start  Length  Slot  Name   Signature
            0       9     0  this   Lshapeless/Poly3;
    Signature: #41                          // <A:Ljava/lang/Object;B:Ljava/lang/Object;C:Ljava/lang/Object;>()Lshapeless/Poly3$CaseBuilder<TA;TB;TC;>;

  public static void $init$(shapeless.Poly3);
    descriptor: (Lshapeless/Poly3;)V
    flags: (0x0009) ACC_PUBLIC, ACC_STATIC
    Code:
      stack=0, locals=1, args_size=1
         0: return
      LineNumberTable:
        line 74: 0
      LocalVariableTable:
        Start  Length  Slot  Name   Signature
            0       1     0 $this   Lshapeless/Poly3;
    MethodParameters:
      Name                           Flags
      $this                          final synthetic
}
InnerClasses:
  public #13= #12 of #2;                  // Case$=class shapeless/Poly3$Case$ of class shapeless/Poly3
  public #16= #15 of #2;                  // CaseBuilder=class shapeless/Poly3$CaseBuilder of class shapeless/Poly3
SourceFile: "polyntraits.scala"
RuntimeVisibleAnnotations:
  0: #8(#9=s#10)
    scala.reflect.ScalaSignature(
      bytes="\u0006\u0005\u0005UcaB\t\u0013!\u0003\r\t!\u0006\u0005\u0006A\u0001!\t!I\u0003\u0005K\u0001\u0001aeB\u0003M\u0001!\u0005QJB\u0003&\u0001!\u0005a\nC\u0003P\t\u0011\u0005\u0001+\u0002\u0003R\t\u0001\u0011f\u0001B3\u0001\u0001\u0019DQaT\u0004\u0005\u0002!DQ\u0001]\u0004\u0005\u0002EDaa \u0001\u0005\u0002\u0005\u0005qaBA\n%!\u0005\u0011Q\u0003\u0004\u0007#IA\t!a\u0006\t\r=cA\u0011AA\u001c\u0011%\tI\u0004\u0004b\u0001\n\u0003\tY\u0004\u0003\u0005\u0002D1\u0001\u000b\u0011BA\u001f\u0011%\t)\u0005DA\u0001\n\u0013\t9EA\u0003Q_2L8GC\u0001\u0014\u0003%\u0019\b.\u00199fY\u0016\u001c8o\u0001\u0001\u0014\u0007\u00011B\u0004\u0005\u0002\u001855\t\u0001DC\u0001\u001a\u0003\u0015\u00198-\u00197b\u0013\tY\u0002D\u0001\u0004B]f\u0014VM\u001a\t\u0003;yi\u0011AE\u0005\u0003?I\u0011A\u0001U8ms\u00061A%\u001b8ji\u0012\"\u0012A\t\t\u0003/\rJ!\u0001\n\r\u0003\tUs\u0017\u000e\u001e\u0002\u0005\u0007\u0006\u001cX-\u0006\u0003(q\r;\u0005\u0003\u0002\u00150eMr!!\u000b\u0017\u000f\u0005uQ\u0013BA\u0016\u0013\u0003\u001d\u0001\u0018mY6bO\u0016L!!\f\u0018\u0002\tA|G.\u001f\u0006\u0003WII!!\n\u0019\u000b\u0005E\u0012\u0012!\u0003)pYf$UM\u001a8t\u001b\u0005\u0001\u0001\u0003B\u000f5m\u0005K!!\u000e\n\u0003\u0019\u0011\u001aw\u000e\\8oI\r|Gn\u001c8\u0011\u0005]BD\u0002\u0001\u0003\u0006s\t\u0011\rA\u000f\u0002\u0002\u0003F\u00111H\u0010\t\u0003/qJ!!\u0010\r\u0003\u000f9{G\u000f[5oOB\u0011qcP\u0005\u0003\u0001b\u00111!\u00118z!\u0011iBGQ#\u0011\u0005]\u001aE!\u0002#\u0003\u0005\u0004Q$!\u0001\"\u0011\tu!d)\u0013\t\u0003o\u001d#Q\u0001\u0013\u0002C\u0002i\u0012\u0011a\u0011\t\u0003;)K!a\u0013\n\u0003\t!s\u0015\u000e\\\u0001\u0005\u0007\u0006\u001cX\r\u0005\u00023\tM\u0011AAF\u0001\u0007y%t\u0017\u000e\u001e \u0015\u00035\u00131!Q;y+\u0015\u0019\u0016\fX0d%\t!fK\u0002\u0003V\t\u0001\u0019&\u0001\u0004\u001fsK\u001aLg.Z7f]Rt\u0004\u0003\u0002\u00150e]\u0003B!\b\u001bY5B\u0011q\'\u0017\u0003\u0006s\u0019\u0011\rA\u000f\t\u0005;QZV\f\u0005\u000289\u0012)AI\u0002b\u0001uA!Q\u0004\u000e0J!\t9t\fB\u0003I\r\t\u0007!(\u0002\u0003b)\u0002\u0012\'A\u0002*fgVdG\u000f\u0005\u00028G\u0012)AM\u0002b\u0001u\t9!+Z:vYR\u0004$aC\"bg\u0016\u0014U/\u001b7eKJ,BaZ6n_N\u0011qA\u0006\u000b\u0002SB)!g\u00026m]B\u0011qg\u001b\u0003\u0006s\u001d\u0011\rA\u000f\t\u0003o5$Q\u0001R\u0004C\u0002i\u0002\"aN8\u0005\u000b!;!\u0019\u0001\u001e\u0002\u000b\u0005\u0004\b\u000f\\=\u0016\u0005IDHCA:{%\t!XO\u0002\u0003V\u0013\u0001\u0019\b#\u0002\u001a\u0003U2tW\u0001B1u\u0001]\u0004\"a\u000e=\u0005\u000beL!\u0019\u0001\u001e\u0003\u0007I+7\u000fC\u0003|\u0013\u0001\u0007A0\u0001\u0002g]B1q# 6m]^L!A \r\u0003\u0013\u0019+hn\u0019;j_:\u001c\u0014AA1u+!\t\u0019!!\u0003\u0002\u000e\u0005EQCAA\u0003!!\u0011t!a\u0002\u0002\f\u0005=\u0001cA\u001c\u0002\n\u0011)\u0011H\u0003b\u0001uA\u0019q\'!\u0004\u0005\u000b\u0011S!\u0019\u0001\u001e\u0011\u0007]\n\t\u0002B\u0003I\u0015\t\u0007!(A\u0003Q_2L8\u0007\u0005\u0002\u001e\u0019M1ABFA\r\u0003O\u0001R!a\u0007\u0002\"%s1!HA\u000f\u0013\r\tyBE\u0001\u000e!>d\u0017P\u0014\"vS2$WM]:\n\t\u0005\r\u0012Q\u0005\u0002\r!>d\u0017p\r\"vS2$WM\u001d\u0006\u0004\u0003?\u0011\u0002\u0003BA\u0015\u0003gi!!a\u000b\u000b\t\u00055\u0012qF\u0001\u0003S>T!!!\r\u0002\t)\fg/Y\u0005\u0005\u0003k\tYC\u0001\u0007TKJL\u0017\r\\5{C\ndW\r\u0006\u0002\u0002\u0016\u0005Ia-\u001e8di&|gn]\u000b\u0003\u0003{q1!HA \u0013\r\t\tEE\u0001\u0005\u0011:KG.\u0001\u0006gk:\u001cG/[8og\u0002\nAb\u001e:ji\u0016\u0014V\r\u001d7bG\u0016$\"!!\u0013\u0011\t\u0005-\u0013\u0011K\u0007\u0003\u0003\u001bRA!a\u0014\u00020\u0005!A.\u00198h\u0013\u0011\t\u0019&!\u0014\u0003\r=\u0013\'.Z2u\u0001"
    )
  ScalaInlineInfo: length = 0x18 (unknown attribute)
   01 00 00 04 00 2F 00 2B 01 00 1F 00 20 00 00 21
   00 22 01 00 24 00 25 00
  ScalaSig: length = 0x3 (unknown attribute)
   05 02 00
