Classfile /Users/mw/Projects/slang-braindump/.jar/jar8/assemble/slang-braindump/assemble/content/shapeless/PolyDefns$RotateRight$.class
  Last modified May 29, 2022; size 1734 bytes
  SHA-256 checksum bab4881c1eac3fad7d5ada2c2605916547ebe27c934f3f130b9c15270d6479db
  Compiled from "poly.scala"
public class shapeless.PolyDefns$RotateRight$ implements java.io.Serializable
  minor version: 0
  major version: 52
  flags: (0x0021) ACC_PUBLIC, ACC_SUPER
  this_class: #2                          // shapeless/PolyDefns$RotateRight$
  super_class: #4                         // java/lang/Object
  interfaces: 1, fields: 1, methods: 4, attributes: 4
Constant pool:
   #1 = Utf8               shapeless/PolyDefns$RotateRight$
   #2 = Class              #1             // shapeless/PolyDefns$RotateRight$
   #3 = Utf8               java/lang/Object
   #4 = Class              #3             // java/lang/Object
   #5 = Utf8               java/io/Serializable
   #6 = Class              #5             // java/io/Serializable
   #7 = Utf8               poly.scala
   #8 = Utf8               shapeless/PolyDefns$Case
   #9 = Class              #8             // shapeless/PolyDefns$Case
  #10 = Utf8               shapeless/PolyDefns
  #11 = Class              #10            // shapeless/PolyDefns
  #12 = Utf8               Case
  #13 = Utf8               shapeless/PolyDefns$RotateRight
  #14 = Class              #13            // shapeless/PolyDefns$RotateRight
  #15 = Utf8               RotateRight
  #16 = Utf8               RotateRight$
  #17 = Utf8               shapeless/PolyDefns$RotateRight$$anon$5
  #18 = Class              #17            // shapeless/PolyDefns$RotateRight$$anon$5
  #19 = Utf8               shapeless/ops/hlist$RotateLeft
  #20 = Class              #19            // shapeless/ops/hlist$RotateLeft
  #21 = Utf8               shapeless/ops/hlist
  #22 = Class              #21            // shapeless/ops/hlist
  #23 = Utf8               RotateLeft
  #24 = Utf8               MODULE$
  #25 = Utf8               Lshapeless/PolyDefns$RotateRight$;
  #26 = Utf8               <clinit>
  #27 = Utf8               ()V
  #28 = Utf8               <init>
  #29 = NameAndType        #28:#27        // "<init>":()V
  #30 = Methodref          #2.#29         // shapeless/PolyDefns$RotateRight$."<init>":()V
  #31 = NameAndType        #24:#25        // MODULE$:Lshapeless/PolyDefns$RotateRight$;
  #32 = Fieldref           #2.#31         // shapeless/PolyDefns$RotateRight$.MODULE$:Lshapeless/PolyDefns$RotateRight$;
  #33 = Utf8               rotateLeftCase
  #34 = Utf8               (Lshapeless/Unpack2;Lshapeless/PolyDefns$Case;Lshapeless/ops/hlist$RotateLeft;)Lshapeless/PolyDefns$Case;
  #35 = Utf8               <C:Ljava/lang/Object;P::Lshapeless/Poly;N::Lshapeless/Nat;L::Lshapeless/HList;LOut:Ljava/lang/Object;RL::Lshapeless/HList;>(Lshapeless/Unpack2<TC;Lshapeless/PolyDefns$RotateRight;TP;TN;>;Lshapeless/PolyDefns$Case<TP;TL;>;Lshapeless/ops/hlist$RotateLeft<TRL;TN;>;)Lshapeless/PolyDefns$Case<TC;TRL;>;
  #36 = Utf8               unpack
  #37 = Utf8               cP
  #38 = Utf8               rotateLeft
  #39 = Utf8               (Lshapeless/PolyDefns$Case;Lshapeless/ops/hlist$RotateLeft;)V
  #40 = NameAndType        #28:#39        // "<init>":(Lshapeless/PolyDefns$Case;Lshapeless/ops/hlist$RotateLeft;)V
  #41 = Methodref          #18.#40        // shapeless/PolyDefns$RotateRight$$anon$5."<init>":(Lshapeless/PolyDefns$Case;Lshapeless/ops/hlist$RotateLeft;)V
  #42 = Utf8               this
  #43 = Utf8               Lshapeless/Unpack2;
  #44 = Utf8               Lshapeless/PolyDefns$Case;
  #45 = Utf8               Lshapeless/ops/hlist$RotateLeft;
  #46 = Utf8               writeReplace
  #47 = Utf8               ()Ljava/lang/Object;
  #48 = Utf8               scala/runtime/ModuleSerializationProxy
  #49 = Class              #48            // scala/runtime/ModuleSerializationProxy
  #50 = Utf8               (Ljava/lang/Class;)V
  #51 = NameAndType        #28:#50        // "<init>":(Ljava/lang/Class;)V
  #52 = Methodref          #49.#51        // scala/runtime/ModuleSerializationProxy."<init>":(Ljava/lang/Class;)V
  #53 = Methodref          #4.#29         // java/lang/Object."<init>":()V
  #54 = Utf8               Code
  #55 = Utf8               LineNumberTable
  #56 = Utf8               LocalVariableTable
  #57 = Utf8               Signature
  #58 = Utf8               MethodParameters
  #59 = Utf8               InnerClasses
  #60 = Utf8               SourceFile
  #61 = Utf8               ScalaInlineInfo
  #62 = Utf8               Scala
{
  public static final shapeless.PolyDefns$RotateRight$ MODULE$;
    descriptor: Lshapeless/PolyDefns$RotateRight$;
    flags: (0x0019) ACC_PUBLIC, ACC_STATIC, ACC_FINAL

  public static {};
    descriptor: ()V
    flags: (0x0009) ACC_PUBLIC, ACC_STATIC
    Code:
      stack=2, locals=0, args_size=0
         0: new           #2                  // class shapeless/PolyDefns$RotateRight$
         3: dup
         4: invokespecial #30                 // Method "<init>":()V
         7: putstatic     #32                 // Field MODULE$:Lshapeless/PolyDefns$RotateRight$;
        10: return
      LineNumberTable:
        line 106: 0

  public <C extends java.lang.Object, P extends shapeless.Poly, N extends shapeless.Nat, L extends shapeless.HList, LOut extends java.lang.Object, RL extends shapeless.HList> shapeless.PolyDefns$Case<C, RL> rotateLeftCase(shapeless.Unpack2<C, shapeless.PolyDefns$RotateRight, P, N>, shapeless.PolyDefns$Case<P, L>, shapeless.ops.hlist$RotateLeft<RL, N>);
    descriptor: (Lshapeless/Unpack2;Lshapeless/PolyDefns$Case;Lshapeless/ops/hlist$RotateLeft;)Lshapeless/PolyDefns$Case;
    flags: (0x0001) ACC_PUBLIC
    Code:
      stack=4, locals=4, args_size=4
         0: new           #18                 // class shapeless/PolyDefns$RotateRight$$anon$5
         3: dup
         4: aload_2
         5: aload_3
         6: invokespecial #41                 // Method shapeless/PolyDefns$RotateRight$$anon$5."<init>":(Lshapeless/PolyDefns$Case;Lshapeless/ops/hlist$RotateLeft;)V
         9: areturn
      LineNumberTable:
        line 109: 0
      LocalVariableTable:
        Start  Length  Slot  Name   Signature
            0      10     0  this   Lshapeless/PolyDefns$RotateRight$;
            0      10     1 unpack   Lshapeless/Unpack2;
            0      10     2    cP   Lshapeless/PolyDefns$Case;
            0      10     3 rotateLeft   Lshapeless/ops/hlist$RotateLeft;
    Signature: #35                          // <C:Ljava/lang/Object;P::Lshapeless/Poly;N::Lshapeless/Nat;L::Lshapeless/HList;LOut:Ljava/lang/Object;RL::Lshapeless/HList;>(Lshapeless/Unpack2<TC;Lshapeless/PolyDefns$RotateRight;TP;TN;>;Lshapeless/PolyDefns$Case<TP;TL;>;Lshapeless/ops/hlist$RotateLeft<TRL;TN;>;)Lshapeless/PolyDefns$Case<TC;TRL;>;
    MethodParameters:
      Name                           Flags
      unpack                         final
      cP                             final
      rotateLeft                     final

  private java.lang.Object writeReplace();
    descriptor: ()Ljava/lang/Object;
    flags: (0x0002) ACC_PRIVATE
    Code:
      stack=3, locals=1, args_size=1
         0: new           #49                 // class scala/runtime/ModuleSerializationProxy
         3: dup
         4: ldc           #2                  // class shapeless/PolyDefns$RotateRight$
         6: invokespecial #52                 // Method scala/runtime/ModuleSerializationProxy."<init>":(Ljava/lang/Class;)V
         9: areturn
      LineNumberTable:
        line 106: 0
      LocalVariableTable:
        Start  Length  Slot  Name   Signature
            0      10     0  this   Lshapeless/PolyDefns$RotateRight$;

  public shapeless.PolyDefns$RotateRight$();
    descriptor: ()V
    flags: (0x0001) ACC_PUBLIC
    Code:
      stack=1, locals=1, args_size=1
         0: aload_0
         1: invokespecial #53                 // Method java/lang/Object."<init>":()V
         4: return
      LineNumberTable:
        line 119: 0
        line 106: 4
      LocalVariableTable:
        Start  Length  Slot  Name   Signature
            0       5     0  this   Lshapeless/PolyDefns$RotateRight$;
}
InnerClasses:
  public static abstract #12= #9 of #11;  // Case=class shapeless/PolyDefns$Case of class shapeless/PolyDefns
  public static #15= #14 of #11;          // RotateRight=class shapeless/PolyDefns$RotateRight of class shapeless/PolyDefns
  public static #16= #2 of #11;           // RotateRight$=class shapeless/PolyDefns$RotateRight$ of class shapeless/PolyDefns
  public final #18;                       // class shapeless/PolyDefns$RotateRight$$anon$5
  public static #23= #20 of #22;          // RotateLeft=class shapeless/ops/hlist$RotateLeft of class shapeless/ops/hlist
SourceFile: "poly.scala"
  ScalaInlineInfo: length = 0x13 (unknown attribute)
   01 01 00 03 00 1C 00 1B 01 00 21 00 22 01 00 2E
   00 2F 01
  Scala: length = 0x0 (unknown attribute)

