Classfile /Users/mw/Projects/slang-braindump/.jar/jar8/assemble/slang-braindump/assemble/content/shapeless/Poly13.class
  Last modified May 29, 2022; size 3653 bytes
  SHA-256 checksum c2420d08191267b89571d3871217164f159ca11676292dcb7b47dcad98c97855
  Compiled from "polyntraits.scala"
public interface shapeless.Poly13 extends shapeless.Poly
  minor version: 0
  major version: 52
  flags: (0x0601) ACC_PUBLIC, ACC_INTERFACE, ACC_ABSTRACT
  this_class: #2                          // shapeless/Poly13
  super_class: #4                         // java/lang/Object
  interfaces: 1, fields: 0, methods: 6, attributes: 5
Constant pool:
   #1 = Utf8               shapeless/Poly13
   #2 = Class              #1             // shapeless/Poly13
   #3 = Utf8               java/lang/Object
   #4 = Class              #3             // java/lang/Object
   #5 = Utf8               shapeless/Poly
   #6 = Class              #5             // shapeless/Poly
   #7 = Utf8               polyntraits.scala
   #8 = Utf8               Lscala/reflect/ScalaSignature;
   #9 = Utf8               bytes
  #10 = Utf8               \u0006\u0005\tEbaB\t\u0013!\u0003\r\t!\u0006\u0005\u0006A\u0001!\t!I\u0003\u0005K\u0001\u0001aeB\u0003u\u0001!\u0005QOB\u0003&\u0001!\u0005a\u000fC\u0003x\t\u0011\u0005\u00010\u0002\u0003z\t\u0001QhABA,\u0001\u0001\tI\u0006\u0003\u0004x\u000f\u0011\u0005\u0011Q\f\u0005\b\u0003+;A\u0011AAL\u0011\u001d\t\u0019\f\u0001C\u0001\u0003k;q!a<\u0013\u0011\u0003\t\tP\u0002\u0004\u0012%!\u0005\u00111\u001f\u0005\u0007o2!\tAa\u0005\t\u0013\tUAB1A\u0005\u0002\t]\u0001\u0002\u0003B\u0010\u0019\u0001\u0006IA!\u0007\t\u0013\t\u0005B\"!A\u0005\n\t\r\"A\u0002)pYf\f4GC\u0001\u0014\u0003%\u0019\b.\u00199fY\u0016\u001c8o\u0001\u0001\u0014\u0007\u00011B\u0004\u0005\u0002\u001855\t\u0001DC\u0001\u001a\u0003\u0015\u00198-\u00197b\u0013\tY\u0002D\u0001\u0004B]f\u0014VM\u001a\t\u0003;yi\u0011AE\u0005\u0003?I\u0011A\u0001U8ms\u00061A%\u001b8ji\u0012\"\u0012A\t\t\u0003/\rJ!\u0001\n\r\u0003\tUs\u0017\u000e\u001e\u0002\u0005\u0007\u0006\u001cX-\u0006\b(q\r;5jT*X7~\u001bwm[8\u0011\t!z#g\r\b\u0003S1r!!\b\u0016\n\u0005-\u0012\u0012a\u00029bG.\fw-Z\u0005\u0003[9\nA\u0001]8ms*\u00111FE\u0005\u0003KAR!!\r\n\u0002\u0013A{G.\u001f#fM:\u001cX\"\u0001\u0001\u0011\tu!d\'Q\u0005\u0003kI\u0011A\u0002J2pY>tGeY8m_:\u0004\"a\u000e\u001d\r\u0001\u0011)\u0011H\u0001b\u0001u\t\t\u0011)\u0005\u0002<}A\u0011q\u0003P\u0005\u0003{a\u0011qAT8uQ&tw\r\u0005\u0002\u0018\u007f%\u0011\u0001\t\u0007\u0002\u0004\u0003:L\b\u0003B\u000f5\u0005\u0016\u0003\"aN\"\u0005\u000b\u0011\u0013!\u0019\u0001\u001e\u0003\u0003\t\u0003B!\b\u001bG\u0013B\u0011qg\u0012\u0003\u0006\u0011\n\u0011\rA\u000f\u0002\u0002\u0007B!Q\u0004\u000e&N!\t94\nB\u0003M\u0005\t\u0007!HA\u0001E!\u0011iBGT)\u0011\u0005]zE!\u0002)\u0003\u0005\u0004Q$!A#\u0011\tu!$+\u0016\t\u0003oM#Q\u0001\u0016\u0002C\u0002i\u0012\u0011A\u0012\t\u0005;Q2\u0016\f\u0005\u00028/\u0012)\u0001L\u0001b\u0001u\t\tq\t\u0005\u0003\u001eiik\u0006CA\u001c\\\t\u0015a&A1\u0001;\u0005\u0005A\u0005\u0003B\u000f5=\u0006\u0004\"aN0\u0005\u000b\u0001\u0014!\u0019\u0001\u001e\u0003\u0003%\u0003B!\b\u001bcKB\u0011qg\u0019\u0003\u0006I\n\u0011\rA\u000f\u0002\u0002\u0015B!Q\u0004\u000e4j!\t9t\rB\u0003i\u0005\t\u0007!HA\u0001L!\u0011iBG[7\u0011\u0005]ZG!\u00027\u0003\u0005\u0004Q$!\u0001\'\u0011\tu!d.\u001d\t\u0003o=$Q\u0001\u001d\u0002C\u0002i\u0012\u0011!\u0014\t\u0003;IL!a\u001d\n\u0003\t!s\u0015\u000e\\\u0001\u0005\u0007\u0006\u001cX\r\u0005\u00023\tM\u0011AAF\u0001\u0007y%t\u0017\u000e\u001e \u0015\u0003U\u00141!Q;y+uY\u00181AA\u0005\u0003\u001f\t)\"a\u0007\u0002\"\u0005\u001d\u0012QFA\u001a\u0003s\ty$!\u0012\u0002L\u0005M#C\u0001?\u007f\r\u0011iH\u0001A>\u0003\u0019q\u0012XMZ5oK6,g\u000e\u001e \u0011\t!z#g \t\u0007;Q\n\t!!\u0002\u0011\u0007]\n\u0019\u0001B\u0003:\r\t\u0007!\b\u0005\u0004\u001ei\u0005\u001d\u00111\u0002\t\u0004o\u0005%A!\u0002#\u0007\u0005\u0004Q\u0004CB\u000f5\u0003\u001b\t\t\u0002E\u00028\u0003\u001f!Q\u0001\u0013\u0004C\u0002i\u0002b!\b\u001b\u0002\u0014\u0005]\u0001cA\u001c\u0002\u0016\u0011)AJ\u0002b\u0001uA1Q\u0004NA\r\u0003;\u00012aNA\u000e\t\u0015\u0001fA1\u0001;!\u0019iB\'a\b\u0002$A\u0019q\'!\t\u0005\u000bQ3!\u0019\u0001\u001e\u0011\ru!\u0014QEA\u0015!\r9\u0014q\u0005\u0003\u00061\u001a\u0011\rA\u000f\t\u0007;Q\nY#a\f\u0011\u0007]\ni\u0003B\u0003]\r\t\u0007!\b\u0005\u0004\u001ei\u0005E\u0012Q\u0007\t\u0004o\u0005MB!\u00021\u0007\u0005\u0004Q\u0004CB\u000f5\u0003o\tY\u0004E\u00028\u0003s!Q\u0001\u001a\u0004C\u0002i\u0002b!\b\u001b\u0002>\u0005\u0005\u0003cA\u001c\u0002@\u0011)\u0001N\u0002b\u0001uA1Q\u0004NA\"\u0003\u000f\u00022aNA#\t\u0015agA1\u0001;!\u0015iB\'!\u0013r!\r9\u00141\n\u0003\u0006a\u001a\u0011\rAO\u0003\u0007\u0003\u001fb\b%!\u0015\u0003\rI+7/\u001e7u!\r9\u00141\u000b\u0003\u0007\u0003+2!\u0019\u0001\u001e\u0003\u000fI+7/\u001e7ua\tY1)Y:f\u0005VLG\u000eZ3s+q\tY&a\u0019\u0002h\u0005-\u0014qNA:\u0003o\nY(a \u0002\u0004\u0006\u001d\u00151RAH\u0003\'\u001b\"a\u0002\f\u0015\u0005\u0005}\u0003\u0003\b\u001a\b\u0003C\n)\'!\u001b\u0002n\u0005E\u0014QOA=\u0003{\n\t)!\"\u0002\n\u00065\u0015\u0011\u0013\t\u0004o\u0005\rD!B\u001d\b\u0005\u0004Q\u0004cA\u001c\u0002h\u0011)Ai\u0002b\u0001uA\u0019q\'a\u001b\u0005\u000b!;!\u0019\u0001\u001e\u0011\u0007]\ny\u0007B\u0003M\u000f\t\u0007!\bE\u00028\u0003g\"Q\u0001U\u0004C\u0002i\u00022aNA<\t\u0015!vA1\u0001;!\r9\u00141\u0010\u0003\u00061\u001e\u0011\rA\u000f\t\u0004o\u0005}D!\u0002/\b\u0005\u0004Q\u0004cA\u001c\u0002\u0004\u0012)\u0001m\u0002b\u0001uA\u0019q\'a\"\u0005\u000b\u0011<!\u0019\u0001\u001e\u0011\u0007]\nY\tB\u0003i\u000f\t\u0007!\bE\u00028\u0003\u001f#Q\u0001\\\u0004C\u0002i\u00022aNAJ\t\u0015\u0001xA1\u0001;\u0003\u0015\t\u0007\u000f\u001d7z+\u0011\tI*!*\u0015\t\u0005m\u0015\u0011\u0016\n\u0005\u0003;\u000byJB\u0003~\u0013\u0001\tY\n\u0005\u000f3\u0005\u0005\u0005\u0014QMA5\u0003[\n\t(!\u001e\u0002z\u0005u\u0014\u0011QAC\u0003\u0013\u000bi)!%\u0006\u000f\u0005=\u0013Q\u0014\u0001\u0002$B\u0019q\'!*\u0005\r\u0005\u001d\u0016B1\u0001;\u0005\r\u0011Vm\u001d\u0005\b\u0003WK\u0001\u0019AAW\u0003\t1g\u000eE\u0010\u0018\u0003_\u000b\t\'!\u001a\u0002j\u00055\u0014\u0011OA;\u0003s\ni(!!\u0002\u0006\u0006%\u0015QRAI\u0003GK1!!-\u0019\u0005)1UO\\2uS>t\u0017gM\u0001\u0003CR,B$a.\u0002>\u0006\u0005\u0017QYAe\u0003\u001b\f\t.!6\u0002Z\u0006u\u0017\u0011]As\u0003S\fi/\u0006\u0002\u0002:Ba\"gBA^\u0003\u007f\u000b\u0019-a2\u0002L\u0006=\u00171[Al\u00037\fy.a9\u0002h\u0006-\bcA\u001c\u0002>\u0012)\u0011H\u0003b\u0001uA\u0019q\'!1\u0005\u000b\u0011S!\u0019\u0001\u001e\u0011\u0007]\n)\rB\u0003I\u0015\t\u0007!\bE\u00028\u0003\u0013$Q\u0001\u0014\u0006C\u0002i\u00022aNAg\t\u0015\u0001&B1\u0001;!\r9\u0014\u0011\u001b\u0003\u0006)*\u0011\rA\u000f\t\u0004o\u0005UG!\u0002-\u000b\u0005\u0004Q\u0004cA\u001c\u0002Z\u0012)AL\u0003b\u0001uA\u0019q\'!8\u0005\u000b\u0001T!\u0019\u0001\u001e\u0011\u0007]\n\t\u000fB\u0003e\u0015\t\u0007!\bE\u00028\u0003K$Q\u0001\u001b\u0006C\u0002i\u00022aNAu\t\u0015a\'B1\u0001;!\r9\u0014Q\u001e\u0003\u0006a*\u0011\rAO\u0001\u0007!>d\u00170M\u001a\u0011\u0005ua1C\u0002\u0007\u0017\u0003k\u0014\u0019\u0001E\u0003\u0002x\u0006u\u0018OD\u0002\u001e\u0003sL1!a?\u0013\u00035\u0001v\u000e\\=O\u0005VLG\u000eZ3sg&!\u0011q B\u0001\u00055\u0001v\u000e\\=2g\t+\u0018\u000e\u001c3fe*\u0019\u00111 \n\u0011\t\t\u0015!qB\u0007\u0003\u0005\u000fQAA!\u0003\u0003\f\u0005\u0011\u0011n\u001c\u0006\u0003\u0005\u001b\tAA[1wC&!!\u0011\u0003B\u0004\u00051\u0019VM]5bY&T\u0018M\u00197f)\t\t\t0A\u0005gk:\u001cG/[8ogV\u0011!\u0011\u0004\b\u0004;\tm\u0011b\u0001B\u000f%\u0005!\u0001JT5m\u0003)1WO\\2uS>t7\u000fI\u0001\roJLG/\u001a*fa2\f7-\u001a\u000b\u0003\u0005K\u0001BAa\n\u0003.5\u0011!\u0011\u0006\u0006\u0005\u0005W\u0011Y!\u0001\u0003mC:<\u0017\u0002\u0002B\u0018\u0005S\u0011aa\u00142kK\u000e$\b
  #11 = Utf8               shapeless/Poly13$Case$
  #12 = Class              #11            // shapeless/Poly13$Case$
  #13 = Utf8               Case$
  #14 = Utf8               shapeless/Poly13$CaseBuilder
  #15 = Class              #14            // shapeless/Poly13$CaseBuilder
  #16 = Utf8               CaseBuilder
  #17 = Utf8               functions
  #18 = Utf8               ()Lshapeless/HNil$;
  #19 = Utf8               shapeless/Poly13$
  #20 = Class              #19            // shapeless/Poly13$
  #21 = Utf8               MODULE$
  #22 = Utf8               Lshapeless/Poly13$;
  #23 = NameAndType        #21:#22        // MODULE$:Lshapeless/Poly13$;
  #24 = Fieldref           #20.#23        // shapeless/Poly13$.MODULE$:Lshapeless/Poly13$;
  #25 = NameAndType        #17:#18        // functions:()Lshapeless/HNil$;
  #26 = Methodref          #20.#25        // shapeless/Poly13$.functions:()Lshapeless/HNil$;
  #27 = Utf8               build
  #28 = Utf8               ()Lshapeless/Poly13;
  #29 = NameAndType        #27:#28        // build:()Lshapeless/Poly13;
  #30 = Methodref          #20.#29        // shapeless/Poly13$.build:()Lshapeless/Poly13;
  #31 = Utf8               Case
  #32 = Utf8               ()Lshapeless/Poly13$Case$;
  #33 = Utf8               at$
  #34 = Utf8               (Lshapeless/Poly13;)Lshapeless/Poly13$CaseBuilder;
  #35 = Utf8               $this
  #36 = Utf8               at
  #37 = Utf8               ()Lshapeless/Poly13$CaseBuilder;
  #38 = NameAndType        #36:#37        // at:()Lshapeless/Poly13$CaseBuilder;
  #39 = InterfaceMethodref #2.#38         // shapeless/Poly13.at:()Lshapeless/Poly13$CaseBuilder;
  #40 = Utf8               Lshapeless/Poly13;
  #41 = Utf8               <A:Ljava/lang/Object;B:Ljava/lang/Object;C:Ljava/lang/Object;D:Ljava/lang/Object;E:Ljava/lang/Object;F:Ljava/lang/Object;G:Ljava/lang/Object;H:Ljava/lang/Object;I:Ljava/lang/Object;J:Ljava/lang/Object;K:Ljava/lang/Object;L:Ljava/lang/Object;M:Ljava/lang/Object;>()Lshapeless/Poly13$CaseBuilder<TA;TB;TC;TD;TE;TF;TG;TH;TI;TJ;TK;TL;TM;>;
  #42 = Utf8               <init>
  #43 = Utf8               (Lshapeless/Poly13;)V
  #44 = NameAndType        #42:#43        // "<init>":(Lshapeless/Poly13;)V
  #45 = Methodref          #15.#44        // shapeless/Poly13$CaseBuilder."<init>":(Lshapeless/Poly13;)V
  #46 = Utf8               this
  #47 = Utf8               $init$
  #48 = Utf8               Code
  #49 = Utf8               LineNumberTable
  #50 = Utf8               LocalVariableTable
  #51 = Utf8               MethodParameters
  #52 = Utf8               Signature
  #53 = Utf8               InnerClasses
  #54 = Utf8               SourceFile
  #55 = Utf8               RuntimeVisibleAnnotations
  #56 = Utf8               ScalaInlineInfo
  #57 = Utf8               ScalaSig
{
  public static shapeless.HNil$ functions();
    descriptor: ()Lshapeless/HNil$;
    flags: (0x0009) ACC_PUBLIC, ACC_STATIC
    Code:
      stack=1, locals=0, args_size=0
         0: getstatic     #24                 // Field shapeless/Poly13$.MODULE$:Lshapeless/Poly13$;
         3: invokevirtual #26                 // Method shapeless/Poly13$.functions:()Lshapeless/HNil$;
         6: areturn

  public static shapeless.Poly13 build();
    descriptor: ()Lshapeless/Poly13;
    flags: (0x0009) ACC_PUBLIC, ACC_STATIC
    Code:
      stack=1, locals=0, args_size=0
         0: getstatic     #24                 // Field shapeless/Poly13$.MODULE$:Lshapeless/Poly13$;
         3: invokevirtual #30                 // Method shapeless/Poly13$.build:()Lshapeless/Poly13;
         6: areturn

  public abstract shapeless.Poly13$Case$ Case();
    descriptor: ()Lshapeless/Poly13$Case$;
    flags: (0x0401) ACC_PUBLIC, ACC_ABSTRACT

  public static shapeless.Poly13$CaseBuilder at$(shapeless.Poly13);
    descriptor: (Lshapeless/Poly13;)Lshapeless/Poly13$CaseBuilder;
    flags: (0x1009) ACC_PUBLIC, ACC_STATIC, ACC_SYNTHETIC
    Code:
      stack=1, locals=1, args_size=1
         0: aload_0
         1: invokespecial #39                 // InterfaceMethod at:()Lshapeless/Poly13$CaseBuilder;
         4: areturn
      LineNumberTable:
        line 352: 0
      LocalVariableTable:
        Start  Length  Slot  Name   Signature
            0       5     0 $this   Lshapeless/Poly13;
    MethodParameters:
      Name                           Flags
      $this                          final synthetic

  public default <A extends java.lang.Object, B extends java.lang.Object, C extends java.lang.Object, D extends java.lang.Object, E extends java.lang.Object, F extends java.lang.Object, G extends java.lang.Object, H extends java.lang.Object, I extends java.lang.Object, J extends java.lang.Object, K extends java.lang.Object, L extends java.lang.Object, M extends java.lang.Object> shapeless.Poly13$CaseBuilder<A, B, C, D, E, F, G, H, I, J, K, L, M> at();
    descriptor: ()Lshapeless/Poly13$CaseBuilder;
    flags: (0x0001) ACC_PUBLIC
    Code:
      stack=3, locals=1, args_size=1
         0: new           #15                 // class shapeless/Poly13$CaseBuilder
         3: dup
         4: aload_0
         5: invokespecial #45                 // Method shapeless/Poly13$CaseBuilder."<init>":(Lshapeless/Poly13;)V
         8: areturn
      LineNumberTable:
        line 353: 0
      LocalVariableTable:
        Start  Length  Slot  Name   Signature
            0       9     0  this   Lshapeless/Poly13;
    Signature: #41                          // <A:Ljava/lang/Object;B:Ljava/lang/Object;C:Ljava/lang/Object;D:Ljava/lang/Object;E:Ljava/lang/Object;F:Ljava/lang/Object;G:Ljava/lang/Object;H:Ljava/lang/Object;I:Ljava/lang/Object;J:Ljava/lang/Object;K:Ljava/lang/Object;L:Ljava/lang/Object;M:Ljava/lang/Object;>()Lshapeless/Poly13$CaseBuilder<TA;TB;TC;TD;TE;TF;TG;TH;TI;TJ;TK;TL;TM;>;

  public static void $init$(shapeless.Poly13);
    descriptor: (Lshapeless/Poly13;)V
    flags: (0x0009) ACC_PUBLIC, ACC_STATIC
    Code:
      stack=0, locals=1, args_size=1
         0: return
      LineNumberTable:
        line 334: 0
      LocalVariableTable:
        Start  Length  Slot  Name   Signature
            0       1     0 $this   Lshapeless/Poly13;
    MethodParameters:
      Name                           Flags
      $this                          final synthetic
}
InnerClasses:
  public #13= #12 of #2;                  // Case$=class shapeless/Poly13$Case$ of class shapeless/Poly13
  public #16= #15 of #2;                  // CaseBuilder=class shapeless/Poly13$CaseBuilder of class shapeless/Poly13
SourceFile: "polyntraits.scala"
RuntimeVisibleAnnotations:
  0: #8(#9=s#10)
    scala.reflect.ScalaSignature(
      bytes="\u0006\u0005\tEbaB\t\u0013!\u0003\r\t!\u0006\u0005\u0006A\u0001!\t!I\u0003\u0005K\u0001\u0001aeB\u0003u\u0001!\u0005QOB\u0003&\u0001!\u0005a\u000fC\u0003x\t\u0011\u0005\u00010\u0002\u0003z\t\u0001QhABA,\u0001\u0001\tI\u0006\u0003\u0004x\u000f\u0011\u0005\u0011Q\f\u0005\b\u0003+;A\u0011AAL\u0011\u001d\t\u0019\f\u0001C\u0001\u0003k;q!a<\u0013\u0011\u0003\t\tP\u0002\u0004\u0012%!\u0005\u00111\u001f\u0005\u0007o2!\tAa\u0005\t\u0013\tUAB1A\u0005\u0002\t]\u0001\u0002\u0003B\u0010\u0019\u0001\u0006IA!\u0007\t\u0013\t\u0005B\"!A\u0005\n\t\r\"A\u0002)pYf\f4GC\u0001\u0014\u0003%\u0019\b.\u00199fY\u0016\u001c8o\u0001\u0001\u0014\u0007\u00011B\u0004\u0005\u0002\u001855\t\u0001DC\u0001\u001a\u0003\u0015\u00198-\u00197b\u0013\tY\u0002D\u0001\u0004B]f\u0014VM\u001a\t\u0003;yi\u0011AE\u0005\u0003?I\u0011A\u0001U8ms\u00061A%\u001b8ji\u0012\"\u0012A\t\t\u0003/\rJ!\u0001\n\r\u0003\tUs\u0017\u000e\u001e\u0002\u0005\u0007\u0006\u001cX-\u0006\b(q\r;5jT*X7~\u001bwm[8\u0011\t!z#g\r\b\u0003S1r!!\b\u0016\n\u0005-\u0012\u0012a\u00029bG.\fw-Z\u0005\u0003[9\nA\u0001]8ms*\u00111FE\u0005\u0003KAR!!\r\n\u0002\u0013A{G.\u001f#fM:\u001cX\"\u0001\u0001\u0011\tu!d\'Q\u0005\u0003kI\u0011A\u0002J2pY>tGeY8m_:\u0004\"a\u000e\u001d\r\u0001\u0011)\u0011H\u0001b\u0001u\t\t\u0011)\u0005\u0002<}A\u0011q\u0003P\u0005\u0003{a\u0011qAT8uQ&tw\r\u0005\u0002\u0018\u007f%\u0011\u0001\t\u0007\u0002\u0004\u0003:L\b\u0003B\u000f5\u0005\u0016\u0003\"aN\"\u0005\u000b\u0011\u0013!\u0019\u0001\u001e\u0003\u0003\t\u0003B!\b\u001bG\u0013B\u0011qg\u0012\u0003\u0006\u0011\n\u0011\rA\u000f\u0002\u0002\u0007B!Q\u0004\u000e&N!\t94\nB\u0003M\u0005\t\u0007!HA\u0001E!\u0011iBGT)\u0011\u0005]zE!\u0002)\u0003\u0005\u0004Q$!A#\u0011\tu!$+\u0016\t\u0003oM#Q\u0001\u0016\u0002C\u0002i\u0012\u0011A\u0012\t\u0005;Q2\u0016\f\u0005\u00028/\u0012)\u0001L\u0001b\u0001u\t\tq\t\u0005\u0003\u001eiik\u0006CA\u001c\\\t\u0015a&A1\u0001;\u0005\u0005A\u0005\u0003B\u000f5=\u0006\u0004\"aN0\u0005\u000b\u0001\u0014!\u0019\u0001\u001e\u0003\u0003%\u0003B!\b\u001bcKB\u0011qg\u0019\u0003\u0006I\n\u0011\rA\u000f\u0002\u0002\u0015B!Q\u0004\u000e4j!\t9t\rB\u0003i\u0005\t\u0007!HA\u0001L!\u0011iBG[7\u0011\u0005]ZG!\u00027\u0003\u0005\u0004Q$!\u0001\'\u0011\tu!d.\u001d\t\u0003o=$Q\u0001\u001d\u0002C\u0002i\u0012\u0011!\u0014\t\u0003;IL!a\u001d\n\u0003\t!s\u0015\u000e\\\u0001\u0005\u0007\u0006\u001cX\r\u0005\u00023\tM\u0011AAF\u0001\u0007y%t\u0017\u000e\u001e \u0015\u0003U\u00141!Q;y+uY\u00181AA\u0005\u0003\u001f\t)\"a\u0007\u0002\"\u0005\u001d\u0012QFA\u001a\u0003s\ty$!\u0012\u0002L\u0005M#C\u0001?\u007f\r\u0011iH\u0001A>\u0003\u0019q\u0012XMZ5oK6,g\u000e\u001e \u0011\t!z#g \t\u0007;Q\n\t!!\u0002\u0011\u0007]\n\u0019\u0001B\u0003:\r\t\u0007!\b\u0005\u0004\u001ei\u0005\u001d\u00111\u0002\t\u0004o\u0005%A!\u0002#\u0007\u0005\u0004Q\u0004CB\u000f5\u0003\u001b\t\t\u0002E\u00028\u0003\u001f!Q\u0001\u0013\u0004C\u0002i\u0002b!\b\u001b\u0002\u0014\u0005]\u0001cA\u001c\u0002\u0016\u0011)AJ\u0002b\u0001uA1Q\u0004NA\r\u0003;\u00012aNA\u000e\t\u0015\u0001fA1\u0001;!\u0019iB\'a\b\u0002$A\u0019q\'!\t\u0005\u000bQ3!\u0019\u0001\u001e\u0011\ru!\u0014QEA\u0015!\r9\u0014q\u0005\u0003\u00061\u001a\u0011\rA\u000f\t\u0007;Q\nY#a\f\u0011\u0007]\ni\u0003B\u0003]\r\t\u0007!\b\u0005\u0004\u001ei\u0005E\u0012Q\u0007\t\u0004o\u0005MB!\u00021\u0007\u0005\u0004Q\u0004CB\u000f5\u0003o\tY\u0004E\u00028\u0003s!Q\u0001\u001a\u0004C\u0002i\u0002b!\b\u001b\u0002>\u0005\u0005\u0003cA\u001c\u0002@\u0011)\u0001N\u0002b\u0001uA1Q\u0004NA\"\u0003\u000f\u00022aNA#\t\u0015agA1\u0001;!\u0015iB\'!\u0013r!\r9\u00141\n\u0003\u0006a\u001a\u0011\rAO\u0003\u0007\u0003\u001fb\b%!\u0015\u0003\rI+7/\u001e7u!\r9\u00141\u000b\u0003\u0007\u0003+2!\u0019\u0001\u001e\u0003\u000fI+7/\u001e7ua\tY1)Y:f\u0005VLG\u000eZ3s+q\tY&a\u0019\u0002h\u0005-\u0014qNA:\u0003o\nY(a \u0002\u0004\u0006\u001d\u00151RAH\u0003\'\u001b\"a\u0002\f\u0015\u0005\u0005}\u0003\u0003\b\u001a\b\u0003C\n)\'!\u001b\u0002n\u0005E\u0014QOA=\u0003{\n\t)!\"\u0002\n\u00065\u0015\u0011\u0013\t\u0004o\u0005\rD!B\u001d\b\u0005\u0004Q\u0004cA\u001c\u0002h\u0011)Ai\u0002b\u0001uA\u0019q\'a\u001b\u0005\u000b!;!\u0019\u0001\u001e\u0011\u0007]\ny\u0007B\u0003M\u000f\t\u0007!\bE\u00028\u0003g\"Q\u0001U\u0004C\u0002i\u00022aNA<\t\u0015!vA1\u0001;!\r9\u00141\u0010\u0003\u00061\u001e\u0011\rA\u000f\t\u0004o\u0005}D!\u0002/\b\u0005\u0004Q\u0004cA\u001c\u0002\u0004\u0012)\u0001m\u0002b\u0001uA\u0019q\'a\"\u0005\u000b\u0011<!\u0019\u0001\u001e\u0011\u0007]\nY\tB\u0003i\u000f\t\u0007!\bE\u00028\u0003\u001f#Q\u0001\\\u0004C\u0002i\u00022aNAJ\t\u0015\u0001xA1\u0001;\u0003\u0015\t\u0007\u000f\u001d7z+\u0011\tI*!*\u0015\t\u0005m\u0015\u0011\u0016\n\u0005\u0003;\u000byJB\u0003~\u0013\u0001\tY\n\u0005\u000f3\u0005\u0005\u0005\u0014QMA5\u0003[\n\t(!\u001e\u0002z\u0005u\u0014\u0011QAC\u0003\u0013\u000bi)!%\u0006\u000f\u0005=\u0013Q\u0014\u0001\u0002$B\u0019q\'!*\u0005\r\u0005\u001d\u0016B1\u0001;\u0005\r\u0011Vm\u001d\u0005\b\u0003WK\u0001\u0019AAW\u0003\t1g\u000eE\u0010\u0018\u0003_\u000b\t\'!\u001a\u0002j\u00055\u0014\u0011OA;\u0003s\ni(!!\u0002\u0006\u0006%\u0015QRAI\u0003GK1!!-\u0019\u0005)1UO\\2uS>t\u0017gM\u0001\u0003CR,B$a.\u0002>\u0006\u0005\u0017QYAe\u0003\u001b\f\t.!6\u0002Z\u0006u\u0017\u0011]As\u0003S\fi/\u0006\u0002\u0002:Ba\"gBA^\u0003\u007f\u000b\u0019-a2\u0002L\u0006=\u00171[Al\u00037\fy.a9\u0002h\u0006-\bcA\u001c\u0002>\u0012)\u0011H\u0003b\u0001uA\u0019q\'!1\u0005\u000b\u0011S!\u0019\u0001\u001e\u0011\u0007]\n)\rB\u0003I\u0015\t\u0007!\bE\u00028\u0003\u0013$Q\u0001\u0014\u0006C\u0002i\u00022aNAg\t\u0015\u0001&B1\u0001;!\r9\u0014\u0011\u001b\u0003\u0006)*\u0011\rA\u000f\t\u0004o\u0005UG!\u0002-\u000b\u0005\u0004Q\u0004cA\u001c\u0002Z\u0012)AL\u0003b\u0001uA\u0019q\'!8\u0005\u000b\u0001T!\u0019\u0001\u001e\u0011\u0007]\n\t\u000fB\u0003e\u0015\t\u0007!\bE\u00028\u0003K$Q\u0001\u001b\u0006C\u0002i\u00022aNAu\t\u0015a\'B1\u0001;!\r9\u0014Q\u001e\u0003\u0006a*\u0011\rAO\u0001\u0007!>d\u00170M\u001a\u0011\u0005ua1C\u0002\u0007\u0017\u0003k\u0014\u0019\u0001E\u0003\u0002x\u0006u\u0018OD\u0002\u001e\u0003sL1!a?\u0013\u00035\u0001v\u000e\\=O\u0005VLG\u000eZ3sg&!\u0011q B\u0001\u00055\u0001v\u000e\\=2g\t+\u0018\u000e\u001c3fe*\u0019\u00111 \n\u0011\t\t\u0015!qB\u0007\u0003\u0005\u000fQAA!\u0003\u0003\f\u0005\u0011\u0011n\u001c\u0006\u0003\u0005\u001b\tAA[1wC&!!\u0011\u0003B\u0004\u00051\u0019VM]5bY&T\u0018M\u00197f)\t\t\t0A\u0005gk:\u001cG/[8ogV\u0011!\u0011\u0004\b\u0004;\tm\u0011b\u0001B\u000f%\u0005!\u0001JT5m\u0003)1WO\\2uS>t7\u000fI\u0001\roJLG/\u001a*fa2\f7-\u001a\u000b\u0003\u0005K\u0001BAa\n\u0003.5\u0011!\u0011\u0006\u0006\u0005\u0005W\u0011Y!\u0001\u0003mC:<\u0017\u0002\u0002B\u0018\u0005S\u0011aa\u00142kK\u000e$\b"
    )
  ScalaInlineInfo: length = 0x18 (unknown attribute)
   01 00 00 04 00 2F 00 2B 01 00 1F 00 20 00 00 21
   00 22 01 00 24 00 25 00
  ScalaSig: length = 0x3 (unknown attribute)
   05 02 00
