Classfile /Users/mw/Projects/slang-braindump/.jar/jar8/assemble/slang-braindump/assemble/content/shapeless/Poly17.class
  Last modified May 29, 2022; size 4137 bytes
  SHA-256 checksum c67fb6bd96174ad8956b419b487e631b9a92d7e4a03ec949b5916f6a948241b9
  Compiled from "polyntraits.scala"
public interface shapeless.Poly17 extends shapeless.Poly
  minor version: 0
  major version: 52
  flags: (0x0601) ACC_PUBLIC, ACC_INTERFACE, ACC_ABSTRACT
  this_class: #2                          // shapeless/Poly17
  super_class: #4                         // java/lang/Object
  interfaces: 1, fields: 0, methods: 6, attributes: 5
Constant pool:
   #1 = Utf8               shapeless/Poly17
   #2 = Class              #1             // shapeless/Poly17
   #3 = Utf8               java/lang/Object
   #4 = Class              #3             // java/lang/Object
   #5 = Utf8               shapeless/Poly
   #6 = Class              #5             // shapeless/Poly
   #7 = Utf8               polyntraits.scala
   #8 = Utf8               Lscala/reflect/ScalaSignature;
   #9 = Utf8               bytes
  #10 = Utf8               \u0006\u0005\t%eaB\t\u0013!\u0003\r\t!\u0006\u0005\u0006A\u0001!\t!I\u0003\u0005K\u0001\u0001aeB\u0004\u0002\n\u0001A\t!a\u0003\u0007\r\u0015\u0002\u0001\u0012AA\u0007\u0011\u001d\ty\u0001\u0002C\u0001\u0003#)a!a\u0005\u0005\u0001\u0005UaABAH\u0001\u0001\t\t\nC\u0004\u0002\u0010\u001d!\t!!&\t\u000f\u0005uw\u0001\"\u0001\u0002`\"9\u00111 \u0001\u0005\u0002\u0005uxa\u0002B$%!\u0005!\u0011\n\u0004\u0007#IA\tAa\u0013\t\u000f\u0005=A\u0002\"\u0001\u0003l!I!Q\u000e\u0007C\u0002\u0013\u0005!q\u000e\u0005\t\u0005ob\u0001\u0015!\u0003\u0003r!I!\u0011\u0010\u0007\u0002\u0002\u0013%!1\u0010\u0002\u0007!>d\u00170M\u001c\u000b\u0003M\t\u0011b\u001d5ba\u0016dWm]:\u0004\u0001M\u0019\u0001A\u0006\u000f\u0011\u0005]QR\"\u0001\r\u000b\u0003e\tQa]2bY\u0006L!a\u0007\r\u0003\r\u0005s\u0017PU3g!\tib$D\u0001\u0013\u0013\ty\"C\u0001\u0003Q_2L\u0018A\u0002\u0013j]&$H\u0005F\u0001#!\t92%\u0003\u0002%1\t!QK\\5u\u0005\u0011\u0019\u0015m]3\u0016%\u001dB4iR&P\'^[vlY4l_N<8p \t\u0005Q=\u00124G\u0004\u0002*Y9\u0011QDK\u0005\u0003WI\tq\u0001]1dW\u0006<W-\u0003\u0002.]\u0005!\u0001o\u001c7z\u0015\tY##\u0003\u0002&a)\u0011\u0011GE\u0001\n!>d\u0017\u0010R3g]Nl\u0011\u0001\u0001\t\u0005;Q2\u0014)\u0003\u00026%\taAeY8m_:$3m\u001c7p]B\u0011q\u0007\u000f\u0007\u0001\t\u0015I$A1\u0001;\u0005\u0005\t\u0015CA\u001e?!\t9B(\u0003\u0002>1\t9aj\u001c;iS:<\u0007CA\f@\u0013\t\u0001\u0005DA\u0002B]f\u0004B!\b\u001bC\u000bB\u0011qg\u0011\u0003\u0006\t\n\u0011\rA\u000f\u0002\u0002\u0005B!Q\u0004\u000e$J!\t9t\tB\u0003I\u0005\t\u0007!HA\u0001D!\u0011iBGS\'\u0011\u0005]ZE!\u0002\'\u0003\u0005\u0004Q$!\u0001#\u0011\tu!d*\u0015\t\u0003o=#Q\u0001\u0015\u0002C\u0002i\u0012\u0011!\u0012\t\u0005;Q\u0012V\u000b\u0005\u00028\'\u0012)AK\u0001b\u0001u\t\ta\t\u0005\u0003\u001eiYK\u0006CA\u001cX\t\u0015A&A1\u0001;\u0005\u00059\u0005\u0003B\u000f55v\u0003\"aN.\u0005\u000bq\u0013!\u0019\u0001\u001e\u0003\u0003!\u0003B!\b\u001b_CB\u0011qg\u0018\u0003\u0006A\n\u0011\rA\u000f\u0002\u0002\u0013B!Q\u0004\u000e2f!\t94\rB\u0003e\u0005\t\u0007!HA\u0001K!\u0011iBGZ5\u0011\u0005]:G!\u00025\u0003\u0005\u0004Q$!A&\u0011\tu!$.\u001c\t\u0003o-$Q\u0001\u001c\u0002C\u0002i\u0012\u0011\u0001\u0014\t\u0005;Qr\u0017\u000f\u0005\u00028_\u0012)\u0001O\u0001b\u0001u\t\tQ\n\u0005\u0003\u001eiI,\bCA\u001ct\t\u0015!(A1\u0001;\u0005\u0005q\u0005\u0003B\u000f5mf\u0004\"aN<\u0005\u000ba\u0014!\u0019\u0001\u001e\u0003\u0003=\u0003B!\b\u001b{{B\u0011qg\u001f\u0003\u0006y\n\u0011\rA\u000f\u0002\u0002!B)Q\u0004\u000e@\u0002\u0004A\u0011qg \u0003\u0007\u0003\u0003\u0011!\u0019\u0001\u001e\u0003\u0003E\u00032!HA\u0003\u0013\r\t9A\u0005\u0002\u0005\u0011:KG.\u0001\u0003DCN,\u0007C\u0001\u001a\u0005\'\t!a#\u0001\u0004=S:LGO\u0010\u000b\u0003\u0003\u0017\u00111!Q;y+\u0019\n9\"a\t\u0002*\u0005=\u0012QGA\u001e\u0003\u0003\n9%!\u0014\u0002T\u0005e\u0013qLA3\u0003W\n\t(a\u001e\u0002~\u0005\r\u00151\u0012\n\u0005\u00033\tiB\u0002\u0004\u0002\u001c\u0011\u0001\u0011q\u0003\u0002\ryI,g-\u001b8f[\u0016tGO\u0010\t\u0006Q=\u0012\u0014q\u0004\t\u0007;Q\n\t#!\n\u0011\u0007]\n\u0019\u0003B\u0003:\r\t\u0007!\b\u0005\u0004\u001ei\u0005\u001d\u00121\u0006\t\u0004o\u0005%B!\u0002#\u0007\u0005\u0004Q\u0004CB\u000f5\u0003[\t\t\u0004E\u00028\u0003_!Q\u0001\u0013\u0004C\u0002i\u0002b!\b\u001b\u00024\u0005]\u0002cA\u001c\u00026\u0011)AJ\u0002b\u0001uA1Q\u0004NA\u001d\u0003{\u00012aNA\u001e\t\u0015\u0001fA1\u0001;!\u0019iB\'a\u0010\u0002DA\u0019q\'!\u0011\u0005\u000bQ3!\u0019\u0001\u001e\u0011\ru!\u0014QIA%!\r9\u0014q\t\u0003\u00061\u001a\u0011\rA\u000f\t\u0007;Q\nY%a\u0014\u0011\u0007]\ni\u0005B\u0003]\r\t\u0007!\b\u0005\u0004\u001ei\u0005E\u0013Q\u000b\t\u0004o\u0005MC!\u00021\u0007\u0005\u0004Q\u0004CB\u000f5\u0003/\nY\u0006E\u00028\u00033\"Q\u0001\u001a\u0004C\u0002i\u0002b!\b\u001b\u0002^\u0005\u0005\u0004cA\u001c\u0002`\u0011)\u0001N\u0002b\u0001uA1Q\u0004NA2\u0003O\u00022aNA3\t\u0015agA1\u0001;!\u0019iB\'!\u001b\u0002nA\u0019q\'a\u001b\u0005\u000bA4!\u0019\u0001\u001e\u0011\ru!\u0014qNA:!\r9\u0014\u0011\u000f\u0003\u0006i\u001a\u0011\rA\u000f\t\u0007;Q\n)(!\u001f\u0011\u0007]\n9\bB\u0003y\r\t\u0007!\b\u0005\u0004\u001ei\u0005m\u0014q\u0010\t\u0004o\u0005uD!\u0002?\u0007\u0005\u0004Q\u0004CB\u000f5\u0003\u0003\u000b\u0019\u0001E\u00028\u0003\u0007#a!!\u0001\u0007\u0005\u0004QTaBAD\u00033\u0001\u0013\u0011\u0012\u0002\u0007%\u0016\u001cX\u000f\u001c;\u0011\u0007]\nY\t\u0002\u0004\u0002\u000e\u001a\u0011\rA\u000f\u0002\b%\u0016\u001cX\u000f\u001c;1\u0005-\u0019\u0015m]3Ck&dG-\u001a:\u0016I\u0005M\u00151TAP\u0003G\u000b9+a+\u00020\u0006M\u0016qWA^\u0003\u007f\u000b\u0019-a2\u0002L\u0006=\u00171[Al\u00037\u001c\"a\u0002\f\u0015\u0005\u0005]\u0005\u0003\n\u001a\b\u00033\u000bi*!)\u0002&\u0006%\u0016QVAY\u0003k\u000bI,!0\u0002B\u0006\u0015\u0017\u0011ZAg\u0003#\f).!7\u0011\u0007]\nY\nB\u0003:\u000f\t\u0007!\bE\u00028\u0003?#Q\u0001R\u0004C\u0002i\u00022aNAR\t\u0015AuA1\u0001;!\r9\u0014q\u0015\u0003\u0006\u0019\u001e\u0011\rA\u000f\t\u0004o\u0005-F!\u0002)\b\u0005\u0004Q\u0004cA\u001c\u00020\u0012)Ak\u0002b\u0001uA\u0019q\'a-\u0005\u000ba;!\u0019\u0001\u001e\u0011\u0007]\n9\fB\u0003]\u000f\t\u0007!\bE\u00028\u0003w#Q\u0001Y\u0004C\u0002i\u00022aNA`\t\u0015!wA1\u0001;!\r9\u00141\u0019\u0003\u0006Q\u001e\u0011\rA\u000f\t\u0004o\u0005\u001dG!\u00027\b\u0005\u0004Q\u0004cA\u001c\u0002L\u0012)\u0001o\u0002b\u0001uA\u0019q\'a4\u0005\u000bQ<!\u0019\u0001\u001e\u0011\u0007]\n\u0019\u000eB\u0003y\u000f\t\u0007!\bE\u00028\u0003/$Q\u0001`\u0004C\u0002i\u00022aNAn\t\u0019\t\ta\u0002b\u0001u\u0005)\u0011\r\u001d9msV!\u0011\u0011]Aw)\u0011\t\u0019/!=\u0013\t\u0005\u0015\u0018q\u001d\u0004\u0007\u00037I\u0001!a9\u0011II\u0012\u0011\u0011TAO\u0003C\u000b)+!+\u0002.\u0006E\u0016QWA]\u0003{\u000b\t-!2\u0002J\u00065\u0017\u0011[Ak\u00033,q!a\"\u0002f\u0002\tY\u000fE\u00028\u0003[$a!a<\n\u0005\u0004Q$a\u0001*fg\"9\u00111_\u0005A\u0002\u0005U\u0018A\u00014o!\u001d:\u0012q_AM\u0003;\u000b\t+!*\u0002*\u00065\u0016\u0011WA[\u0003s\u000bi,!1\u0002F\u0006%\u0017QZAi\u0003+\fI.a;\n\u0007\u0005e\bD\u0001\u0006Gk:\u001cG/[8oc]\n!!\u0019;\u0016I\u0005}(Q\u0001B\u0005\u0005\u001b\u0011\tB!\u0006\u0003\u001a\tu!\u0011\u0005B\u0013\u0005S\u0011iC!\r\u00036\te\"Q\bB!\u0005\u000b*\"A!\u0001\u0011II:!1\u0001B\u0004\u0005\u0017\u0011yAa\u0005\u0003\u0018\tm!q\u0004B\u0012\u0005O\u0011YCa\f\u00034\t]\"1\bB \u0005\u0007\u00022a\u000eB\u0003\t\u0015I$B1\u0001;!\r9$\u0011\u0002\u0003\u0006\t*\u0011\rA\u000f\t\u0004o\t5A!\u0002%\u000b\u0005\u0004Q\u0004cA\u001c\u0003\u0012\u0011)AJ\u0003b\u0001uA\u0019qG!\u0006\u0005\u000bAS!\u0019\u0001\u001e\u0011\u0007]\u0012I\u0002B\u0003U\u0015\t\u0007!\bE\u00028\u0005;!Q\u0001\u0017\u0006C\u0002i\u00022a\u000eB\u0011\t\u0015a&B1\u0001;!\r9$Q\u0005\u0003\u0006A*\u0011\rA\u000f\t\u0004o\t%B!\u00023\u000b\u0005\u0004Q\u0004cA\u001c\u0003.\u0011)\u0001N\u0003b\u0001uA\u0019qG!\r\u0005\u000b1T!\u0019\u0001\u001e\u0011\u0007]\u0012)\u0004B\u0003q\u0015\t\u0007!\bE\u00028\u0005s!Q\u0001\u001e\u0006C\u0002i\u00022a\u000eB\u001f\t\u0015A(B1\u0001;!\r9$\u0011\t\u0003\u0006y*\u0011\rA\u000f\t\u0004o\t\u0015CABA\u0001\u0015\t\u0007!(\u0001\u0004Q_2L\u0018g\u000e\t\u0003;1\u0019b\u0001\u0004\f\u0003N\tm\u0003C\u0002B(\u0005+\n\u0019AD\u0002\u001e\u0005#J1Aa\u0015\u0013\u00035\u0001v\u000e\\=O\u0005VLG\u000eZ3sg&!!q\u000bB-\u00055\u0001v\u000e\\=2o\t+\u0018\u000e\u001c3fe*\u0019!1\u000b\n\u0011\t\tu#qM\u0007\u0003\u0005?RAA!\u0019\u0003d\u0005\u0011\u0011n\u001c\u0006\u0003\u0005K\nAA[1wC&!!\u0011\u000eB0\u00051\u0019VM]5bY&T\u0018M\u00197f)\t\u0011I%A\u0005gk:\u001cG/[8ogV\u0011!\u0011\u000f\b\u0004;\tM\u0014b\u0001B;%\u0005!\u0001JT5m\u0003)1WO\\2uS>t7\u000fI\u0001\roJLG/\u001a*fa2\f7-\u001a\u000b\u0003\u0005{\u0002BAa \u0003\u00066\u0011!\u0011\u0011\u0006\u0005\u0005\u0007\u0013\u0019\'\u0001\u0003mC:<\u0017\u0002\u0002BD\u0005\u0003\u0013aa\u00142kK\u000e$\b
  #11 = Utf8               shapeless/Poly17$Case$
  #12 = Class              #11            // shapeless/Poly17$Case$
  #13 = Utf8               Case$
  #14 = Utf8               shapeless/Poly17$CaseBuilder
  #15 = Class              #14            // shapeless/Poly17$CaseBuilder
  #16 = Utf8               CaseBuilder
  #17 = Utf8               functions
  #18 = Utf8               ()Lshapeless/HNil$;
  #19 = Utf8               shapeless/Poly17$
  #20 = Class              #19            // shapeless/Poly17$
  #21 = Utf8               MODULE$
  #22 = Utf8               Lshapeless/Poly17$;
  #23 = NameAndType        #21:#22        // MODULE$:Lshapeless/Poly17$;
  #24 = Fieldref           #20.#23        // shapeless/Poly17$.MODULE$:Lshapeless/Poly17$;
  #25 = NameAndType        #17:#18        // functions:()Lshapeless/HNil$;
  #26 = Methodref          #20.#25        // shapeless/Poly17$.functions:()Lshapeless/HNil$;
  #27 = Utf8               build
  #28 = Utf8               ()Lshapeless/Poly17;
  #29 = NameAndType        #27:#28        // build:()Lshapeless/Poly17;
  #30 = Methodref          #20.#29        // shapeless/Poly17$.build:()Lshapeless/Poly17;
  #31 = Utf8               Case
  #32 = Utf8               ()Lshapeless/Poly17$Case$;
  #33 = Utf8               at$
  #34 = Utf8               (Lshapeless/Poly17;)Lshapeless/Poly17$CaseBuilder;
  #35 = Utf8               $this
  #36 = Utf8               at
  #37 = Utf8               ()Lshapeless/Poly17$CaseBuilder;
  #38 = NameAndType        #36:#37        // at:()Lshapeless/Poly17$CaseBuilder;
  #39 = InterfaceMethodref #2.#38         // shapeless/Poly17.at:()Lshapeless/Poly17$CaseBuilder;
  #40 = Utf8               Lshapeless/Poly17;
  #41 = Utf8               <A:Ljava/lang/Object;B:Ljava/lang/Object;C:Ljava/lang/Object;D:Ljava/lang/Object;E:Ljava/lang/Object;F:Ljava/lang/Object;G:Ljava/lang/Object;H:Ljava/lang/Object;I:Ljava/lang/Object;J:Ljava/lang/Object;K:Ljava/lang/Object;L:Ljava/lang/Object;M:Ljava/lang/Object;N:Ljava/lang/Object;O:Ljava/lang/Object;P:Ljava/lang/Object;Q:Ljava/lang/Object;>()Lshapeless/Poly17$CaseBuilder<TA;TB;TC;TD;TE;TF;TG;TH;TI;TJ;TK;TL;TM;TN;TO;TP;TQ;>;
  #42 = Utf8               <init>
  #43 = Utf8               (Lshapeless/Poly17;)V
  #44 = NameAndType        #42:#43        // "<init>":(Lshapeless/Poly17;)V
  #45 = Methodref          #15.#44        // shapeless/Poly17$CaseBuilder."<init>":(Lshapeless/Poly17;)V
  #46 = Utf8               this
  #47 = Utf8               $init$
  #48 = Utf8               Code
  #49 = Utf8               LineNumberTable
  #50 = Utf8               LocalVariableTable
  #51 = Utf8               MethodParameters
  #52 = Utf8               Signature
  #53 = Utf8               InnerClasses
  #54 = Utf8               SourceFile
  #55 = Utf8               RuntimeVisibleAnnotations
  #56 = Utf8               ScalaInlineInfo
  #57 = Utf8               ScalaSig
{
  public static shapeless.HNil$ functions();
    descriptor: ()Lshapeless/HNil$;
    flags: (0x0009) ACC_PUBLIC, ACC_STATIC
    Code:
      stack=1, locals=0, args_size=0
         0: getstatic     #24                 // Field shapeless/Poly17$.MODULE$:Lshapeless/Poly17$;
         3: invokevirtual #26                 // Method shapeless/Poly17$.functions:()Lshapeless/HNil$;
         6: areturn

  public static shapeless.Poly17 build();
    descriptor: ()Lshapeless/Poly17;
    flags: (0x0009) ACC_PUBLIC, ACC_STATIC
    Code:
      stack=1, locals=0, args_size=0
         0: getstatic     #24                 // Field shapeless/Poly17$.MODULE$:Lshapeless/Poly17$;
         3: invokevirtual #30                 // Method shapeless/Poly17$.build:()Lshapeless/Poly17;
         6: areturn

  public abstract shapeless.Poly17$Case$ Case();
    descriptor: ()Lshapeless/Poly17$Case$;
    flags: (0x0401) ACC_PUBLIC, ACC_ABSTRACT

  public static shapeless.Poly17$CaseBuilder at$(shapeless.Poly17);
    descriptor: (Lshapeless/Poly17;)Lshapeless/Poly17$CaseBuilder;
    flags: (0x1009) ACC_PUBLIC, ACC_STATIC, ACC_SYNTHETIC
    Code:
      stack=1, locals=1, args_size=1
         0: aload_0
         1: invokespecial #39                 // InterfaceMethod at:()Lshapeless/Poly17$CaseBuilder;
         4: areturn
      LineNumberTable:
        line 456: 0
      LocalVariableTable:
        Start  Length  Slot  Name   Signature
            0       5     0 $this   Lshapeless/Poly17;
    MethodParameters:
      Name                           Flags
      $this                          final synthetic

  public default <A extends java.lang.Object, B extends java.lang.Object, C extends java.lang.Object, D extends java.lang.Object, E extends java.lang.Object, F extends java.lang.Object, G extends java.lang.Object, H extends java.lang.Object, I extends java.lang.Object, J extends java.lang.Object, K extends java.lang.Object, L extends java.lang.Object, M extends java.lang.Object, N extends java.lang.Object, O extends java.lang.Object, P extends java.lang.Object, Q extends java.lang.Object> shapeless.Poly17$CaseBuilder<A, B, C, D, E, F, G, H, I, J, K, L, M, N, O, P, Q> at();
    descriptor: ()Lshapeless/Poly17$CaseBuilder;
    flags: (0x0001) ACC_PUBLIC
    Code:
      stack=3, locals=1, args_size=1
         0: new           #15                 // class shapeless/Poly17$CaseBuilder
         3: dup
         4: aload_0
         5: invokespecial #45                 // Method shapeless/Poly17$CaseBuilder."<init>":(Lshapeless/Poly17;)V
         8: areturn
      LineNumberTable:
        line 457: 0
      LocalVariableTable:
        Start  Length  Slot  Name   Signature
            0       9     0  this   Lshapeless/Poly17;
    Signature: #41                          // <A:Ljava/lang/Object;B:Ljava/lang/Object;C:Ljava/lang/Object;D:Ljava/lang/Object;E:Ljava/lang/Object;F:Ljava/lang/Object;G:Ljava/lang/Object;H:Ljava/lang/Object;I:Ljava/lang/Object;J:Ljava/lang/Object;K:Ljava/lang/Object;L:Ljava/lang/Object;M:Ljava/lang/Object;N:Ljava/lang/Object;O:Ljava/lang/Object;P:Ljava/lang/Object;Q:Ljava/lang/Object;>()Lshapeless/Poly17$CaseBuilder<TA;TB;TC;TD;TE;TF;TG;TH;TI;TJ;TK;TL;TM;TN;TO;TP;TQ;>;

  public static void $init$(shapeless.Poly17);
    descriptor: (Lshapeless/Poly17;)V
    flags: (0x0009) ACC_PUBLIC, ACC_STATIC
    Code:
      stack=0, locals=1, args_size=1
         0: return
      LineNumberTable:
        line 438: 0
      LocalVariableTable:
        Start  Length  Slot  Name   Signature
            0       1     0 $this   Lshapeless/Poly17;
    MethodParameters:
      Name                           Flags
      $this                          final synthetic
}
InnerClasses:
  public #13= #12 of #2;                  // Case$=class shapeless/Poly17$Case$ of class shapeless/Poly17
  public #16= #15 of #2;                  // CaseBuilder=class shapeless/Poly17$CaseBuilder of class shapeless/Poly17
SourceFile: "polyntraits.scala"
RuntimeVisibleAnnotations:
  0: #8(#9=s#10)
    scala.reflect.ScalaSignature(
      bytes="\u0006\u0005\t%eaB\t\u0013!\u0003\r\t!\u0006\u0005\u0006A\u0001!\t!I\u0003\u0005K\u0001\u0001aeB\u0004\u0002\n\u0001A\t!a\u0003\u0007\r\u0015\u0002\u0001\u0012AA\u0007\u0011\u001d\ty\u0001\u0002C\u0001\u0003#)a!a\u0005\u0005\u0001\u0005UaABAH\u0001\u0001\t\t\nC\u0004\u0002\u0010\u001d!\t!!&\t\u000f\u0005uw\u0001\"\u0001\u0002`\"9\u00111 \u0001\u0005\u0002\u0005uxa\u0002B$%!\u0005!\u0011\n\u0004\u0007#IA\tAa\u0013\t\u000f\u0005=A\u0002\"\u0001\u0003l!I!Q\u000e\u0007C\u0002\u0013\u0005!q\u000e\u0005\t\u0005ob\u0001\u0015!\u0003\u0003r!I!\u0011\u0010\u0007\u0002\u0002\u0013%!1\u0010\u0002\u0007!>d\u00170M\u001c\u000b\u0003M\t\u0011b\u001d5ba\u0016dWm]:\u0004\u0001M\u0019\u0001A\u0006\u000f\u0011\u0005]QR\"\u0001\r\u000b\u0003e\tQa]2bY\u0006L!a\u0007\r\u0003\r\u0005s\u0017PU3g!\tib$D\u0001\u0013\u0013\ty\"C\u0001\u0003Q_2L\u0018A\u0002\u0013j]&$H\u0005F\u0001#!\t92%\u0003\u0002%1\t!QK\\5u\u0005\u0011\u0019\u0015m]3\u0016%\u001dB4iR&P\'^[vlY4l_N<8p \t\u0005Q=\u00124G\u0004\u0002*Y9\u0011QDK\u0005\u0003WI\tq\u0001]1dW\u0006<W-\u0003\u0002.]\u0005!\u0001o\u001c7z\u0015\tY##\u0003\u0002&a)\u0011\u0011GE\u0001\n!>d\u0017\u0010R3g]Nl\u0011\u0001\u0001\t\u0005;Q2\u0014)\u0003\u00026%\taAeY8m_:$3m\u001c7p]B\u0011q\u0007\u000f\u0007\u0001\t\u0015I$A1\u0001;\u0005\u0005\t\u0015CA\u001e?!\t9B(\u0003\u0002>1\t9aj\u001c;iS:<\u0007CA\f@\u0013\t\u0001\u0005DA\u0002B]f\u0004B!\b\u001bC\u000bB\u0011qg\u0011\u0003\u0006\t\n\u0011\rA\u000f\u0002\u0002\u0005B!Q\u0004\u000e$J!\t9t\tB\u0003I\u0005\t\u0007!HA\u0001D!\u0011iBGS\'\u0011\u0005]ZE!\u0002\'\u0003\u0005\u0004Q$!\u0001#\u0011\tu!d*\u0015\t\u0003o=#Q\u0001\u0015\u0002C\u0002i\u0012\u0011!\u0012\t\u0005;Q\u0012V\u000b\u0005\u00028\'\u0012)AK\u0001b\u0001u\t\ta\t\u0005\u0003\u001eiYK\u0006CA\u001cX\t\u0015A&A1\u0001;\u0005\u00059\u0005\u0003B\u000f55v\u0003\"aN.\u0005\u000bq\u0013!\u0019\u0001\u001e\u0003\u0003!\u0003B!\b\u001b_CB\u0011qg\u0018\u0003\u0006A\n\u0011\rA\u000f\u0002\u0002\u0013B!Q\u0004\u000e2f!\t94\rB\u0003e\u0005\t\u0007!HA\u0001K!\u0011iBGZ5\u0011\u0005]:G!\u00025\u0003\u0005\u0004Q$!A&\u0011\tu!$.\u001c\t\u0003o-$Q\u0001\u001c\u0002C\u0002i\u0012\u0011\u0001\u0014\t\u0005;Qr\u0017\u000f\u0005\u00028_\u0012)\u0001O\u0001b\u0001u\t\tQ\n\u0005\u0003\u001eiI,\bCA\u001ct\t\u0015!(A1\u0001;\u0005\u0005q\u0005\u0003B\u000f5mf\u0004\"aN<\u0005\u000ba\u0014!\u0019\u0001\u001e\u0003\u0003=\u0003B!\b\u001b{{B\u0011qg\u001f\u0003\u0006y\n\u0011\rA\u000f\u0002\u0002!B)Q\u0004\u000e@\u0002\u0004A\u0011qg \u0003\u0007\u0003\u0003\u0011!\u0019\u0001\u001e\u0003\u0003E\u00032!HA\u0003\u0013\r\t9A\u0005\u0002\u0005\u0011:KG.\u0001\u0003DCN,\u0007C\u0001\u001a\u0005\'\t!a#\u0001\u0004=S:LGO\u0010\u000b\u0003\u0003\u0017\u00111!Q;y+\u0019\n9\"a\t\u0002*\u0005=\u0012QGA\u001e\u0003\u0003\n9%!\u0014\u0002T\u0005e\u0013qLA3\u0003W\n\t(a\u001e\u0002~\u0005\r\u00151\u0012\n\u0005\u00033\tiB\u0002\u0004\u0002\u001c\u0011\u0001\u0011q\u0003\u0002\ryI,g-\u001b8f[\u0016tGO\u0010\t\u0006Q=\u0012\u0014q\u0004\t\u0007;Q\n\t#!\n\u0011\u0007]\n\u0019\u0003B\u0003:\r\t\u0007!\b\u0005\u0004\u001ei\u0005\u001d\u00121\u0006\t\u0004o\u0005%B!\u0002#\u0007\u0005\u0004Q\u0004CB\u000f5\u0003[\t\t\u0004E\u00028\u0003_!Q\u0001\u0013\u0004C\u0002i\u0002b!\b\u001b\u00024\u0005]\u0002cA\u001c\u00026\u0011)AJ\u0002b\u0001uA1Q\u0004NA\u001d\u0003{\u00012aNA\u001e\t\u0015\u0001fA1\u0001;!\u0019iB\'a\u0010\u0002DA\u0019q\'!\u0011\u0005\u000bQ3!\u0019\u0001\u001e\u0011\ru!\u0014QIA%!\r9\u0014q\t\u0003\u00061\u001a\u0011\rA\u000f\t\u0007;Q\nY%a\u0014\u0011\u0007]\ni\u0005B\u0003]\r\t\u0007!\b\u0005\u0004\u001ei\u0005E\u0013Q\u000b\t\u0004o\u0005MC!\u00021\u0007\u0005\u0004Q\u0004CB\u000f5\u0003/\nY\u0006E\u00028\u00033\"Q\u0001\u001a\u0004C\u0002i\u0002b!\b\u001b\u0002^\u0005\u0005\u0004cA\u001c\u0002`\u0011)\u0001N\u0002b\u0001uA1Q\u0004NA2\u0003O\u00022aNA3\t\u0015agA1\u0001;!\u0019iB\'!\u001b\u0002nA\u0019q\'a\u001b\u0005\u000bA4!\u0019\u0001\u001e\u0011\ru!\u0014qNA:!\r9\u0014\u0011\u000f\u0003\u0006i\u001a\u0011\rA\u000f\t\u0007;Q\n)(!\u001f\u0011\u0007]\n9\bB\u0003y\r\t\u0007!\b\u0005\u0004\u001ei\u0005m\u0014q\u0010\t\u0004o\u0005uD!\u0002?\u0007\u0005\u0004Q\u0004CB\u000f5\u0003\u0003\u000b\u0019\u0001E\u00028\u0003\u0007#a!!\u0001\u0007\u0005\u0004QTaBAD\u00033\u0001\u0013\u0011\u0012\u0002\u0007%\u0016\u001cX\u000f\u001c;\u0011\u0007]\nY\t\u0002\u0004\u0002\u000e\u001a\u0011\rA\u000f\u0002\b%\u0016\u001cX\u000f\u001c;1\u0005-\u0019\u0015m]3Ck&dG-\u001a:\u0016I\u0005M\u00151TAP\u0003G\u000b9+a+\u00020\u0006M\u0016qWA^\u0003\u007f\u000b\u0019-a2\u0002L\u0006=\u00171[Al\u00037\u001c\"a\u0002\f\u0015\u0005\u0005]\u0005\u0003\n\u001a\b\u00033\u000bi*!)\u0002&\u0006%\u0016QVAY\u0003k\u000bI,!0\u0002B\u0006\u0015\u0017\u0011ZAg\u0003#\f).!7\u0011\u0007]\nY\nB\u0003:\u000f\t\u0007!\bE\u00028\u0003?#Q\u0001R\u0004C\u0002i\u00022aNAR\t\u0015AuA1\u0001;!\r9\u0014q\u0015\u0003\u0006\u0019\u001e\u0011\rA\u000f\t\u0004o\u0005-F!\u0002)\b\u0005\u0004Q\u0004cA\u001c\u00020\u0012)Ak\u0002b\u0001uA\u0019q\'a-\u0005\u000ba;!\u0019\u0001\u001e\u0011\u0007]\n9\fB\u0003]\u000f\t\u0007!\bE\u00028\u0003w#Q\u0001Y\u0004C\u0002i\u00022aNA`\t\u0015!wA1\u0001;!\r9\u00141\u0019\u0003\u0006Q\u001e\u0011\rA\u000f\t\u0004o\u0005\u001dG!\u00027\b\u0005\u0004Q\u0004cA\u001c\u0002L\u0012)\u0001o\u0002b\u0001uA\u0019q\'a4\u0005\u000bQ<!\u0019\u0001\u001e\u0011\u0007]\n\u0019\u000eB\u0003y\u000f\t\u0007!\bE\u00028\u0003/$Q\u0001`\u0004C\u0002i\u00022aNAn\t\u0019\t\ta\u0002b\u0001u\u0005)\u0011\r\u001d9msV!\u0011\u0011]Aw)\u0011\t\u0019/!=\u0013\t\u0005\u0015\u0018q\u001d\u0004\u0007\u00037I\u0001!a9\u0011II\u0012\u0011\u0011TAO\u0003C\u000b)+!+\u0002.\u0006E\u0016QWA]\u0003{\u000b\t-!2\u0002J\u00065\u0017\u0011[Ak\u00033,q!a\"\u0002f\u0002\tY\u000fE\u00028\u0003[$a!a<\n\u0005\u0004Q$a\u0001*fg\"9\u00111_\u0005A\u0002\u0005U\u0018A\u00014o!\u001d:\u0012q_AM\u0003;\u000b\t+!*\u0002*\u00065\u0016\u0011WA[\u0003s\u000bi,!1\u0002F\u0006%\u0017QZAi\u0003+\fI.a;\n\u0007\u0005e\bD\u0001\u0006Gk:\u001cG/[8oc]\n!!\u0019;\u0016I\u0005}(Q\u0001B\u0005\u0005\u001b\u0011\tB!\u0006\u0003\u001a\tu!\u0011\u0005B\u0013\u0005S\u0011iC!\r\u00036\te\"Q\bB!\u0005\u000b*\"A!\u0001\u0011II:!1\u0001B\u0004\u0005\u0017\u0011yAa\u0005\u0003\u0018\tm!q\u0004B\u0012\u0005O\u0011YCa\f\u00034\t]\"1\bB \u0005\u0007\u00022a\u000eB\u0003\t\u0015I$B1\u0001;!\r9$\u0011\u0002\u0003\u0006\t*\u0011\rA\u000f\t\u0004o\t5A!\u0002%\u000b\u0005\u0004Q\u0004cA\u001c\u0003\u0012\u0011)AJ\u0003b\u0001uA\u0019qG!\u0006\u0005\u000bAS!\u0019\u0001\u001e\u0011\u0007]\u0012I\u0002B\u0003U\u0015\t\u0007!\bE\u00028\u0005;!Q\u0001\u0017\u0006C\u0002i\u00022a\u000eB\u0011\t\u0015a&B1\u0001;!\r9$Q\u0005\u0003\u0006A*\u0011\rA\u000f\t\u0004o\t%B!\u00023\u000b\u0005\u0004Q\u0004cA\u001c\u0003.\u0011)\u0001N\u0003b\u0001uA\u0019qG!\r\u0005\u000b1T!\u0019\u0001\u001e\u0011\u0007]\u0012)\u0004B\u0003q\u0015\t\u0007!\bE\u00028\u0005s!Q\u0001\u001e\u0006C\u0002i\u00022a\u000eB\u001f\t\u0015A(B1\u0001;!\r9$\u0011\t\u0003\u0006y*\u0011\rA\u000f\t\u0004o\t\u0015CABA\u0001\u0015\t\u0007!(\u0001\u0004Q_2L\u0018g\u000e\t\u0003;1\u0019b\u0001\u0004\f\u0003N\tm\u0003C\u0002B(\u0005+\n\u0019AD\u0002\u001e\u0005#J1Aa\u0015\u0013\u00035\u0001v\u000e\\=O\u0005VLG\u000eZ3sg&!!q\u000bB-\u00055\u0001v\u000e\\=2o\t+\u0018\u000e\u001c3fe*\u0019!1\u000b\n\u0011\t\tu#qM\u0007\u0003\u0005?RAA!\u0019\u0003d\u0005\u0011\u0011n\u001c\u0006\u0003\u0005K\nAA[1wC&!!\u0011\u000eB0\u00051\u0019VM]5bY&T\u0018M\u00197f)\t\u0011I%A\u0005gk:\u001cG/[8ogV\u0011!\u0011\u000f\b\u0004;\tM\u0014b\u0001B;%\u0005!\u0001JT5m\u0003)1WO\\2uS>t7\u000fI\u0001\roJLG/\u001a*fa2\f7-\u001a\u000b\u0003\u0005{\u0002BAa \u0003\u00066\u0011!\u0011\u0011\u0006\u0005\u0005\u0007\u0013\u0019\'\u0001\u0003mC:<\u0017\u0002\u0002BD\u0005\u0003\u0013aa\u00142kK\u000e$\b"
    )
  ScalaInlineInfo: length = 0x18 (unknown attribute)
   01 00 00 04 00 2F 00 2B 01 00 1F 00 20 00 00 21
   00 22 01 00 24 00 25 00
  ScalaSig: length = 0x3 (unknown attribute)
   05 02 00
