Classfile /Users/mw/Projects/slang-braindump/.jar/jar8/assemble/slang-braindump/assemble/content/shapeless/Poly$.class
  Last modified May 29, 2022; size 23513 bytes
  SHA-256 checksum 573be493b350587ea57b5fdb4fedc16528126db685709477c7efc9c8d889c55b
  Compiled from "poly.scala"
public final class shapeless.Poly$ implements shapeless.PolyInst,java.io.Serializable
  minor version: 0
  major version: 52
  flags: (0x0031) ACC_PUBLIC, ACC_FINAL, ACC_SUPER
  this_class: #2                          // shapeless/Poly$
  super_class: #4                         // java/lang/Object
  interfaces: 2, fields: 1, methods: 26, attributes: 4
Constant pool:
    #1 = Utf8               shapeless/Poly$
    #2 = Class              #1            // shapeless/Poly$
    #3 = Utf8               java/lang/Object
    #4 = Class              #3            // java/lang/Object
    #5 = Utf8               shapeless/PolyInst
    #6 = Class              #5            // shapeless/PolyInst
    #7 = Utf8               java/io/Serializable
    #8 = Class              #7            // java/io/Serializable
    #9 = Utf8               poly.scala
   #10 = Utf8               shapeless/PolyDefns$Case
   #11 = Class              #10           // shapeless/PolyDefns$Case
   #12 = Utf8               shapeless/PolyDefns
   #13 = Class              #12           // shapeless/PolyDefns
   #14 = Utf8               Case
   #15 = Utf8               MODULE$
   #16 = Utf8               Lshapeless/Poly$;
   #17 = Utf8               <clinit>
   #18 = Utf8               ()V
   #19 = Utf8               <init>
   #20 = NameAndType        #19:#18       // "<init>":()V
   #21 = Methodref          #2.#20        // shapeless/Poly$."<init>":()V
   #22 = NameAndType        #15:#16       // MODULE$:Lshapeless/Poly$;
   #23 = Fieldref           #2.#22        // shapeless/Poly$.MODULE$:Lshapeless/Poly$;
   #24 = Utf8               $init$
   #25 = Utf8               (Lshapeless/PolyInst;)V
   #26 = NameAndType        #24:#25       // $init$:(Lshapeless/PolyInst;)V
   #27 = InterfaceMethodref #6.#26        // shapeless/PolyInst.$init$:(Lshapeless/PolyInst;)V
   #28 = Utf8               inst1
   #29 = Utf8               (Lshapeless/Poly;Lshapeless/PolyDefns$Case;)Lscala/Function1;
   #30 = Utf8               <A:Ljava/lang/Object;>(Lshapeless/Poly;Lshapeless/PolyDefns$Case<+Lshapeless/Poly;Lshapeless/$colon$colon<TA;Lshapeless/HNil;>;>;)Lscala/Function1<TA;Ljava/lang/Object;>;
   #31 = Utf8               fn
   #32 = Utf8               cse
   #33 = Utf8               inst1$
   #34 = Utf8               (Lshapeless/PolyInst;Lshapeless/Poly;Lshapeless/PolyDefns$Case;)Lscala/Function1;
   #35 = NameAndType        #33:#34       // inst1$:(Lshapeless/PolyInst;Lshapeless/Poly;Lshapeless/PolyDefns$Case;)Lscala/Function1;
   #36 = InterfaceMethodref #6.#35        // shapeless/PolyInst.inst1$:(Lshapeless/PolyInst;Lshapeless/Poly;Lshapeless/PolyDefns$Case;)Lscala/Function1;
   #37 = Utf8               this
   #38 = Utf8               Lshapeless/Poly;
   #39 = Utf8               Lshapeless/PolyDefns$Case;
   #40 = Utf8               inst2
   #41 = Utf8               (Lshapeless/Poly;Lshapeless/PolyDefns$Case;)Lscala/Function2;
   #42 = Utf8               <A:Ljava/lang/Object;B:Ljava/lang/Object;>(Lshapeless/Poly;Lshapeless/PolyDefns$Case<+Lshapeless/Poly;Lshapeless/$colon$colon<TA;Lshapeless/$colon$colon<TB;Lshapeless/HNil;>;>;>;)Lscala/Function2<TA;TB;Ljava/lang/Object;>;
   #43 = Utf8               inst2$
   #44 = Utf8               (Lshapeless/PolyInst;Lshapeless/Poly;Lshapeless/PolyDefns$Case;)Lscala/Function2;
   #45 = NameAndType        #43:#44       // inst2$:(Lshapeless/PolyInst;Lshapeless/Poly;Lshapeless/PolyDefns$Case;)Lscala/Function2;
   #46 = InterfaceMethodref #6.#45        // shapeless/PolyInst.inst2$:(Lshapeless/PolyInst;Lshapeless/Poly;Lshapeless/PolyDefns$Case;)Lscala/Function2;
   #47 = Utf8               inst3
   #48 = Utf8               (Lshapeless/Poly;Lshapeless/PolyDefns$Case;)Lscala/Function3;
   #49 = Utf8               <A:Ljava/lang/Object;B:Ljava/lang/Object;C:Ljava/lang/Object;>(Lshapeless/Poly;Lshapeless/PolyDefns$Case<+Lshapeless/Poly;Lshapeless/$colon$colon<TA;Lshapeless/$colon$colon<TB;Lshapeless/$colon$colon<TC;Lshapeless/HNil;>;>;>;>;)Lscala/Function3<TA;TB;TC;Ljava/lang/Object;>;
   #50 = Utf8               inst3$
   #51 = Utf8               (Lshapeless/PolyInst;Lshapeless/Poly;Lshapeless/PolyDefns$Case;)Lscala/Function3;
   #52 = NameAndType        #50:#51       // inst3$:(Lshapeless/PolyInst;Lshapeless/Poly;Lshapeless/PolyDefns$Case;)Lscala/Function3;
   #53 = InterfaceMethodref #6.#52        // shapeless/PolyInst.inst3$:(Lshapeless/PolyInst;Lshapeless/Poly;Lshapeless/PolyDefns$Case;)Lscala/Function3;
   #54 = Utf8               inst4
   #55 = Utf8               (Lshapeless/Poly;Lshapeless/PolyDefns$Case;)Lscala/Function4;
   #56 = Utf8               <A:Ljava/lang/Object;B:Ljava/lang/Object;C:Ljava/lang/Object;D:Ljava/lang/Object;>(Lshapeless/Poly;Lshapeless/PolyDefns$Case<+Lshapeless/Poly;Lshapeless/$colon$colon<TA;Lshapeless/$colon$colon<TB;Lshapeless/$colon$colon<TC;Lshapeless/$colon$colon<TD;Lshapeless/HNil;>;>;>;>;>;)Lscala/Function4<TA;TB;TC;TD;Ljava/lang/Object;>;
   #57 = Utf8               inst4$
   #58 = Utf8               (Lshapeless/PolyInst;Lshapeless/Poly;Lshapeless/PolyDefns$Case;)Lscala/Function4;
   #59 = NameAndType        #57:#58       // inst4$:(Lshapeless/PolyInst;Lshapeless/Poly;Lshapeless/PolyDefns$Case;)Lscala/Function4;
   #60 = InterfaceMethodref #6.#59        // shapeless/PolyInst.inst4$:(Lshapeless/PolyInst;Lshapeless/Poly;Lshapeless/PolyDefns$Case;)Lscala/Function4;
   #61 = Utf8               inst5
   #62 = Utf8               (Lshapeless/Poly;Lshapeless/PolyDefns$Case;)Lscala/Function5;
   #63 = Utf8               <A:Ljava/lang/Object;B:Ljava/lang/Object;C:Ljava/lang/Object;D:Ljava/lang/Object;E:Ljava/lang/Object;>(Lshapeless/Poly;Lshapeless/PolyDefns$Case<+Lshapeless/Poly;Lshapeless/$colon$colon<TA;Lshapeless/$colon$colon<TB;Lshapeless/$colon$colon<TC;Lshapeless/$colon$colon<TD;Lshapeless/$colon$colon<TE;Lshapeless/HNil;>;>;>;>;>;>;)Lscala/Function5<TA;TB;TC;TD;TE;Ljava/lang/Object;>;
   #64 = Utf8               inst5$
   #65 = Utf8               (Lshapeless/PolyInst;Lshapeless/Poly;Lshapeless/PolyDefns$Case;)Lscala/Function5;
   #66 = NameAndType        #64:#65       // inst5$:(Lshapeless/PolyInst;Lshapeless/Poly;Lshapeless/PolyDefns$Case;)Lscala/Function5;
   #67 = InterfaceMethodref #6.#66        // shapeless/PolyInst.inst5$:(Lshapeless/PolyInst;Lshapeless/Poly;Lshapeless/PolyDefns$Case;)Lscala/Function5;
   #68 = Utf8               inst6
   #69 = Utf8               (Lshapeless/Poly;Lshapeless/PolyDefns$Case;)Lscala/Function6;
   #70 = Utf8               <A:Ljava/lang/Object;B:Ljava/lang/Object;C:Ljava/lang/Object;D:Ljava/lang/Object;E:Ljava/lang/Object;F:Ljava/lang/Object;>(Lshapeless/Poly;Lshapeless/PolyDefns$Case<+Lshapeless/Poly;Lshapeless/$colon$colon<TA;Lshapeless/$colon$colon<TB;Lshapeless/$colon$colon<TC;Lshapeless/$colon$colon<TD;Lshapeless/$colon$colon<TE;Lshapeless/$colon$colon<TF;Lshapeless/HNil;>;>;>;>;>;>;>;)Lscala/Function6<TA;TB;TC;TD;TE;TF;Ljava/lang/Object;>;
   #71 = Utf8               inst6$
   #72 = Utf8               (Lshapeless/PolyInst;Lshapeless/Poly;Lshapeless/PolyDefns$Case;)Lscala/Function6;
   #73 = NameAndType        #71:#72       // inst6$:(Lshapeless/PolyInst;Lshapeless/Poly;Lshapeless/PolyDefns$Case;)Lscala/Function6;
   #74 = InterfaceMethodref #6.#73        // shapeless/PolyInst.inst6$:(Lshapeless/PolyInst;Lshapeless/Poly;Lshapeless/PolyDefns$Case;)Lscala/Function6;
   #75 = Utf8               inst7
   #76 = Utf8               (Lshapeless/Poly;Lshapeless/PolyDefns$Case;)Lscala/Function7;
   #77 = Utf8               <A:Ljava/lang/Object;B:Ljava/lang/Object;C:Ljava/lang/Object;D:Ljava/lang/Object;E:Ljava/lang/Object;F:Ljava/lang/Object;G:Ljava/lang/Object;>(Lshapeless/Poly;Lshapeless/PolyDefns$Case<+Lshapeless/Poly;Lshapeless/$colon$colon<TA;Lshapeless/$colon$colon<TB;Lshapeless/$colon$colon<TC;Lshapeless/$colon$colon<TD;Lshapeless/$colon$colon<TE;Lshapeless/$colon$colon<TF;Lshapeless/$colon$colon<TG;Lshapeless/HNil;>;>;>;>;>;>;>;>;)Lscala/Function7<TA;TB;TC;TD;TE;TF;TG;Ljava/lang/Object;>;
   #78 = Utf8               inst7$
   #79 = Utf8               (Lshapeless/PolyInst;Lshapeless/Poly;Lshapeless/PolyDefns$Case;)Lscala/Function7;
   #80 = NameAndType        #78:#79       // inst7$:(Lshapeless/PolyInst;Lshapeless/Poly;Lshapeless/PolyDefns$Case;)Lscala/Function7;
   #81 = InterfaceMethodref #6.#80        // shapeless/PolyInst.inst7$:(Lshapeless/PolyInst;Lshapeless/Poly;Lshapeless/PolyDefns$Case;)Lscala/Function7;
   #82 = Utf8               inst8
   #83 = Utf8               (Lshapeless/Poly;Lshapeless/PolyDefns$Case;)Lscala/Function8;
   #84 = Utf8               <A:Ljava/lang/Object;B:Ljava/lang/Object;C:Ljava/lang/Object;D:Ljava/lang/Object;E:Ljava/lang/Object;F:Ljava/lang/Object;G:Ljava/lang/Object;H:Ljava/lang/Object;>(Lshapeless/Poly;Lshapeless/PolyDefns$Case<+Lshapeless/Poly;Lshapeless/$colon$colon<TA;Lshapeless/$colon$colon<TB;Lshapeless/$colon$colon<TC;Lshapeless/$colon$colon<TD;Lshapeless/$colon$colon<TE;Lshapeless/$colon$colon<TF;Lshapeless/$colon$colon<TG;Lshapeless/$colon$colon<TH;Lshapeless/HNil;>;>;>;>;>;>;>;>;>;)Lscala/Function8<TA;TB;TC;TD;TE;TF;TG;TH;Ljava/lang/Object;>;
   #85 = Utf8               inst8$
   #86 = Utf8               (Lshapeless/PolyInst;Lshapeless/Poly;Lshapeless/PolyDefns$Case;)Lscala/Function8;
   #87 = NameAndType        #85:#86       // inst8$:(Lshapeless/PolyInst;Lshapeless/Poly;Lshapeless/PolyDefns$Case;)Lscala/Function8;
   #88 = InterfaceMethodref #6.#87        // shapeless/PolyInst.inst8$:(Lshapeless/PolyInst;Lshapeless/Poly;Lshapeless/PolyDefns$Case;)Lscala/Function8;
   #89 = Utf8               inst9
   #90 = Utf8               (Lshapeless/Poly;Lshapeless/PolyDefns$Case;)Lscala/Function9;
   #91 = Utf8               <A:Ljava/lang/Object;B:Ljava/lang/Object;C:Ljava/lang/Object;D:Ljava/lang/Object;E:Ljava/lang/Object;F:Ljava/lang/Object;G:Ljava/lang/Object;H:Ljava/lang/Object;I:Ljava/lang/Object;>(Lshapeless/Poly;Lshapeless/PolyDefns$Case<+Lshapeless/Poly;Lshapeless/$colon$colon<TA;Lshapeless/$colon$colon<TB;Lshapeless/$colon$colon<TC;Lshapeless/$colon$colon<TD;Lshapeless/$colon$colon<TE;Lshapeless/$colon$colon<TF;Lshapeless/$colon$colon<TG;Lshapeless/$colon$colon<TH;Lshapeless/$colon$colon<TI;Lshapeless/HNil;>;>;>;>;>;>;>;>;>;>;)Lscala/Function9<TA;TB;TC;TD;TE;TF;TG;TH;TI;Ljava/lang/Object;>;
   #92 = Utf8               inst9$
   #93 = Utf8               (Lshapeless/PolyInst;Lshapeless/Poly;Lshapeless/PolyDefns$Case;)Lscala/Function9;
   #94 = NameAndType        #92:#93       // inst9$:(Lshapeless/PolyInst;Lshapeless/Poly;Lshapeless/PolyDefns$Case;)Lscala/Function9;
   #95 = InterfaceMethodref #6.#94        // shapeless/PolyInst.inst9$:(Lshapeless/PolyInst;Lshapeless/Poly;Lshapeless/PolyDefns$Case;)Lscala/Function9;
   #96 = Utf8               inst10
   #97 = Utf8               (Lshapeless/Poly;Lshapeless/PolyDefns$Case;)Lscala/Function10;
   #98 = Utf8               <A:Ljava/lang/Object;B:Ljava/lang/Object;C:Ljava/lang/Object;D:Ljava/lang/Object;E:Ljava/lang/Object;F:Ljava/lang/Object;G:Ljava/lang/Object;H:Ljava/lang/Object;I:Ljava/lang/Object;J:Ljava/lang/Object;>(Lshapeless/Poly;Lshapeless/PolyDefns$Case<+Lshapeless/Poly;Lshapeless/$colon$colon<TA;Lshapeless/$colon$colon<TB;Lshapeless/$colon$colon<TC;Lshapeless/$colon$colon<TD;Lshapeless/$colon$colon<TE;Lshapeless/$colon$colon<TF;Lshapeless/$colon$colon<TG;Lshapeless/$colon$colon<TH;Lshapeless/$colon$colon<TI;Lshapeless/$colon$colon<TJ;Lshapeless/HNil;>;>;>;>;>;>;>;>;>;>;>;)Lscala/Function10<TA;TB;TC;TD;TE;TF;TG;TH;TI;TJ;Ljava/lang/Object;>;
   #99 = Utf8               inst10$
  #100 = Utf8               (Lshapeless/PolyInst;Lshapeless/Poly;Lshapeless/PolyDefns$Case;)Lscala/Function10;
  #101 = NameAndType        #99:#100      // inst10$:(Lshapeless/PolyInst;Lshapeless/Poly;Lshapeless/PolyDefns$Case;)Lscala/Function10;
  #102 = InterfaceMethodref #6.#101       // shapeless/PolyInst.inst10$:(Lshapeless/PolyInst;Lshapeless/Poly;Lshapeless/PolyDefns$Case;)Lscala/Function10;
  #103 = Utf8               inst11
  #104 = Utf8               (Lshapeless/Poly;Lshapeless/PolyDefns$Case;)Lscala/Function11;
  #105 = Utf8               <A:Ljava/lang/Object;B:Ljava/lang/Object;C:Ljava/lang/Object;D:Ljava/lang/Object;E:Ljava/lang/Object;F:Ljava/lang/Object;G:Ljava/lang/Object;H:Ljava/lang/Object;I:Ljava/lang/Object;J:Ljava/lang/Object;K:Ljava/lang/Object;>(Lshapeless/Poly;Lshapeless/PolyDefns$Case<+Lshapeless/Poly;Lshapeless/$colon$colon<TA;Lshapeless/$colon$colon<TB;Lshapeless/$colon$colon<TC;Lshapeless/$colon$colon<TD;Lshapeless/$colon$colon<TE;Lshapeless/$colon$colon<TF;Lshapeless/$colon$colon<TG;Lshapeless/$colon$colon<TH;Lshapeless/$colon$colon<TI;Lshapeless/$colon$colon<TJ;Lshapeless/$colon$colon<TK;Lshapeless/HNil;>;>;>;>;>;>;>;>;>;>;>;>;)Lscala/Function11<TA;TB;TC;TD;TE;TF;TG;TH;TI;TJ;TK;Ljava/lang/Object;>;
  #106 = Utf8               inst11$
  #107 = Utf8               (Lshapeless/PolyInst;Lshapeless/Poly;Lshapeless/PolyDefns$Case;)Lscala/Function11;
  #108 = NameAndType        #106:#107     // inst11$:(Lshapeless/PolyInst;Lshapeless/Poly;Lshapeless/PolyDefns$Case;)Lscala/Function11;
  #109 = InterfaceMethodref #6.#108       // shapeless/PolyInst.inst11$:(Lshapeless/PolyInst;Lshapeless/Poly;Lshapeless/PolyDefns$Case;)Lscala/Function11;
  #110 = Utf8               inst12
  #111 = Utf8               (Lshapeless/Poly;Lshapeless/PolyDefns$Case;)Lscala/Function12;
  #112 = Utf8               <A:Ljava/lang/Object;B:Ljava/lang/Object;C:Ljava/lang/Object;D:Ljava/lang/Object;E:Ljava/lang/Object;F:Ljava/lang/Object;G:Ljava/lang/Object;H:Ljava/lang/Object;I:Ljava/lang/Object;J:Ljava/lang/Object;K:Ljava/lang/Object;L:Ljava/lang/Object;>(Lshapeless/Poly;Lshapeless/PolyDefns$Case<+Lshapeless/Poly;Lshapeless/$colon$colon<TA;Lshapeless/$colon$colon<TB;Lshapeless/$colon$colon<TC;Lshapeless/$colon$colon<TD;Lshapeless/$colon$colon<TE;Lshapeless/$colon$colon<TF;Lshapeless/$colon$colon<TG;Lshapeless/$colon$colon<TH;Lshapeless/$colon$colon<TI;Lshapeless/$colon$colon<TJ;Lshapeless/$colon$colon<TK;Lshapeless/$colon$colon<TL;Lshapeless/HNil;>;>;>;>;>;>;>;>;>;>;>;>;>;)Lscala/Function12<TA;TB;TC;TD;TE;TF;TG;TH;TI;TJ;TK;TL;Ljava/lang/Object;>;
  #113 = Utf8               inst12$
  #114 = Utf8               (Lshapeless/PolyInst;Lshapeless/Poly;Lshapeless/PolyDefns$Case;)Lscala/Function12;
  #115 = NameAndType        #113:#114     // inst12$:(Lshapeless/PolyInst;Lshapeless/Poly;Lshapeless/PolyDefns$Case;)Lscala/Function12;
  #116 = InterfaceMethodref #6.#115       // shapeless/PolyInst.inst12$:(Lshapeless/PolyInst;Lshapeless/Poly;Lshapeless/PolyDefns$Case;)Lscala/Function12;
  #117 = Utf8               inst13
  #118 = Utf8               (Lshapeless/Poly;Lshapeless/PolyDefns$Case;)Lscala/Function13;
  #119 = Utf8               <A:Ljava/lang/Object;B:Ljava/lang/Object;C:Ljava/lang/Object;D:Ljava/lang/Object;E:Ljava/lang/Object;F:Ljava/lang/Object;G:Ljava/lang/Object;H:Ljava/lang/Object;I:Ljava/lang/Object;J:Ljava/lang/Object;K:Ljava/lang/Object;L:Ljava/lang/Object;M:Ljava/lang/Object;>(Lshapeless/Poly;Lshapeless/PolyDefns$Case<+Lshapeless/Poly;Lshapeless/$colon$colon<TA;Lshapeless/$colon$colon<TB;Lshapeless/$colon$colon<TC;Lshapeless/$colon$colon<TD;Lshapeless/$colon$colon<TE;Lshapeless/$colon$colon<TF;Lshapeless/$colon$colon<TG;Lshapeless/$colon$colon<TH;Lshapeless/$colon$colon<TI;Lshapeless/$colon$colon<TJ;Lshapeless/$colon$colon<TK;Lshapeless/$colon$colon<TL;Lshapeless/$colon$colon<TM;Lshapeless/HNil;>;>;>;>;>;>;>;>;>;>;>;>;>;>;)Lscala/Function13<TA;TB;TC;TD;TE;TF;TG;TH;TI;TJ;TK;TL;TM;Ljava/lang/Object;>;
  #120 = Utf8               inst13$
  #121 = Utf8               (Lshapeless/PolyInst;Lshapeless/Poly;Lshapeless/PolyDefns$Case;)Lscala/Function13;
  #122 = NameAndType        #120:#121     // inst13$:(Lshapeless/PolyInst;Lshapeless/Poly;Lshapeless/PolyDefns$Case;)Lscala/Function13;
  #123 = InterfaceMethodref #6.#122       // shapeless/PolyInst.inst13$:(Lshapeless/PolyInst;Lshapeless/Poly;Lshapeless/PolyDefns$Case;)Lscala/Function13;
  #124 = Utf8               inst14
  #125 = Utf8               (Lshapeless/Poly;Lshapeless/PolyDefns$Case;)Lscala/Function14;
  #126 = Utf8               <A:Ljava/lang/Object;B:Ljava/lang/Object;C:Ljava/lang/Object;D:Ljava/lang/Object;E:Ljava/lang/Object;F:Ljava/lang/Object;G:Ljava/lang/Object;H:Ljava/lang/Object;I:Ljava/lang/Object;J:Ljava/lang/Object;K:Ljava/lang/Object;L:Ljava/lang/Object;M:Ljava/lang/Object;N:Ljava/lang/Object;>(Lshapeless/Poly;Lshapeless/PolyDefns$Case<+Lshapeless/Poly;Lshapeless/$colon$colon<TA;Lshapeless/$colon$colon<TB;Lshapeless/$colon$colon<TC;Lshapeless/$colon$colon<TD;Lshapeless/$colon$colon<TE;Lshapeless/$colon$colon<TF;Lshapeless/$colon$colon<TG;Lshapeless/$colon$colon<TH;Lshapeless/$colon$colon<TI;Lshapeless/$colon$colon<TJ;Lshapeless/$colon$colon<TK;Lshapeless/$colon$colon<TL;Lshapeless/$colon$colon<TM;Lshapeless/$colon$colon<TN;Lshapeless/HNil;>;>;>;>;>;>;>;>;>;>;>;>;>;>;>;)Lscala/Function14<TA;TB;TC;TD;TE;TF;TG;TH;TI;TJ;TK;TL;TM;TN;Ljava/lang/Object;>;
  #127 = Utf8               inst14$
  #128 = Utf8               (Lshapeless/PolyInst;Lshapeless/Poly;Lshapeless/PolyDefns$Case;)Lscala/Function14;
  #129 = NameAndType        #127:#128     // inst14$:(Lshapeless/PolyInst;Lshapeless/Poly;Lshapeless/PolyDefns$Case;)Lscala/Function14;
  #130 = InterfaceMethodref #6.#129       // shapeless/PolyInst.inst14$:(Lshapeless/PolyInst;Lshapeless/Poly;Lshapeless/PolyDefns$Case;)Lscala/Function14;
  #131 = Utf8               inst15
  #132 = Utf8               (Lshapeless/Poly;Lshapeless/PolyDefns$Case;)Lscala/Function15;
  #133 = Utf8               <A:Ljava/lang/Object;B:Ljava/lang/Object;C:Ljava/lang/Object;D:Ljava/lang/Object;E:Ljava/lang/Object;F:Ljava/lang/Object;G:Ljava/lang/Object;H:Ljava/lang/Object;I:Ljava/lang/Object;J:Ljava/lang/Object;K:Ljava/lang/Object;L:Ljava/lang/Object;M:Ljava/lang/Object;N:Ljava/lang/Object;O:Ljava/lang/Object;>(Lshapeless/Poly;Lshapeless/PolyDefns$Case<+Lshapeless/Poly;Lshapeless/$colon$colon<TA;Lshapeless/$colon$colon<TB;Lshapeless/$colon$colon<TC;Lshapeless/$colon$colon<TD;Lshapeless/$colon$colon<TE;Lshapeless/$colon$colon<TF;Lshapeless/$colon$colon<TG;Lshapeless/$colon$colon<TH;Lshapeless/$colon$colon<TI;Lshapeless/$colon$colon<TJ;Lshapeless/$colon$colon<TK;Lshapeless/$colon$colon<TL;Lshapeless/$colon$colon<TM;Lshapeless/$colon$colon<TN;Lshapeless/$colon$colon<TO;Lshapeless/HNil;>;>;>;>;>;>;>;>;>;>;>;>;>;>;>;>;)Lscala/Function15<TA;TB;TC;TD;TE;TF;TG;TH;TI;TJ;TK;TL;TM;TN;TO;Ljava/lang/Object;>;
  #134 = Utf8               inst15$
  #135 = Utf8               (Lshapeless/PolyInst;Lshapeless/Poly;Lshapeless/PolyDefns$Case;)Lscala/Function15;
  #136 = NameAndType        #134:#135     // inst15$:(Lshapeless/PolyInst;Lshapeless/Poly;Lshapeless/PolyDefns$Case;)Lscala/Function15;
  #137 = InterfaceMethodref #6.#136       // shapeless/PolyInst.inst15$:(Lshapeless/PolyInst;Lshapeless/Poly;Lshapeless/PolyDefns$Case;)Lscala/Function15;
  #138 = Utf8               inst16
  #139 = Utf8               (Lshapeless/Poly;Lshapeless/PolyDefns$Case;)Lscala/Function16;
  #140 = Utf8               <A:Ljava/lang/Object;B:Ljava/lang/Object;C:Ljava/lang/Object;D:Ljava/lang/Object;E:Ljava/lang/Object;F:Ljava/lang/Object;G:Ljava/lang/Object;H:Ljava/lang/Object;I:Ljava/lang/Object;J:Ljava/lang/Object;K:Ljava/lang/Object;L:Ljava/lang/Object;M:Ljava/lang/Object;N:Ljava/lang/Object;O:Ljava/lang/Object;P:Ljava/lang/Object;>(Lshapeless/Poly;Lshapeless/PolyDefns$Case<+Lshapeless/Poly;Lshapeless/$colon$colon<TA;Lshapeless/$colon$colon<TB;Lshapeless/$colon$colon<TC;Lshapeless/$colon$colon<TD;Lshapeless/$colon$colon<TE;Lshapeless/$colon$colon<TF;Lshapeless/$colon$colon<TG;Lshapeless/$colon$colon<TH;Lshapeless/$colon$colon<TI;Lshapeless/$colon$colon<TJ;Lshapeless/$colon$colon<TK;Lshapeless/$colon$colon<TL;Lshapeless/$colon$colon<TM;Lshapeless/$colon$colon<TN;Lshapeless/$colon$colon<TO;Lshapeless/$colon$colon<TP;Lshapeless/HNil;>;>;>;>;>;>;>;>;>;>;>;>;>;>;>;>;>;)Lscala/Function16<TA;TB;TC;TD;TE;TF;TG;TH;TI;TJ;TK;TL;TM;TN;TO;TP;Ljava/lang/Object;>;
  #141 = Utf8               inst16$
  #142 = Utf8               (Lshapeless/PolyInst;Lshapeless/Poly;Lshapeless/PolyDefns$Case;)Lscala/Function16;
  #143 = NameAndType        #141:#142     // inst16$:(Lshapeless/PolyInst;Lshapeless/Poly;Lshapeless/PolyDefns$Case;)Lscala/Function16;
  #144 = InterfaceMethodref #6.#143       // shapeless/PolyInst.inst16$:(Lshapeless/PolyInst;Lshapeless/Poly;Lshapeless/PolyDefns$Case;)Lscala/Function16;
  #145 = Utf8               inst17
  #146 = Utf8               (Lshapeless/Poly;Lshapeless/PolyDefns$Case;)Lscala/Function17;
  #147 = Utf8               <A:Ljava/lang/Object;B:Ljava/lang/Object;C:Ljava/lang/Object;D:Ljava/lang/Object;E:Ljava/lang/Object;F:Ljava/lang/Object;G:Ljava/lang/Object;H:Ljava/lang/Object;I:Ljava/lang/Object;J:Ljava/lang/Object;K:Ljava/lang/Object;L:Ljava/lang/Object;M:Ljava/lang/Object;N:Ljava/lang/Object;O:Ljava/lang/Object;P:Ljava/lang/Object;Q:Ljava/lang/Object;>(Lshapeless/Poly;Lshapeless/PolyDefns$Case<+Lshapeless/Poly;Lshapeless/$colon$colon<TA;Lshapeless/$colon$colon<TB;Lshapeless/$colon$colon<TC;Lshapeless/$colon$colon<TD;Lshapeless/$colon$colon<TE;Lshapeless/$colon$colon<TF;Lshapeless/$colon$colon<TG;Lshapeless/$colon$colon<TH;Lshapeless/$colon$colon<TI;Lshapeless/$colon$colon<TJ;Lshapeless/$colon$colon<TK;Lshapeless/$colon$colon<TL;Lshapeless/$colon$colon<TM;Lshapeless/$colon$colon<TN;Lshapeless/$colon$colon<TO;Lshapeless/$colon$colon<TP;Lshapeless/$colon$colon<TQ;Lshapeless/HNil;>;>;>;>;>;>;>;>;>;>;>;>;>;>;>;>;>;>;)Lscala/Function17<TA;TB;TC;TD;TE;TF;TG;TH;TI;TJ;TK;TL;TM;TN;TO;TP;TQ;Ljava/lang/Object;>;
  #148 = Utf8               inst17$
  #149 = Utf8               (Lshapeless/PolyInst;Lshapeless/Poly;Lshapeless/PolyDefns$Case;)Lscala/Function17;
  #150 = NameAndType        #148:#149     // inst17$:(Lshapeless/PolyInst;Lshapeless/Poly;Lshapeless/PolyDefns$Case;)Lscala/Function17;
  #151 = InterfaceMethodref #6.#150       // shapeless/PolyInst.inst17$:(Lshapeless/PolyInst;Lshapeless/Poly;Lshapeless/PolyDefns$Case;)Lscala/Function17;
  #152 = Utf8               inst18
  #153 = Utf8               (Lshapeless/Poly;Lshapeless/PolyDefns$Case;)Lscala/Function18;
  #154 = Utf8               <A:Ljava/lang/Object;B:Ljava/lang/Object;C:Ljava/lang/Object;D:Ljava/lang/Object;E:Ljava/lang/Object;F:Ljava/lang/Object;G:Ljava/lang/Object;H:Ljava/lang/Object;I:Ljava/lang/Object;J:Ljava/lang/Object;K:Ljava/lang/Object;L:Ljava/lang/Object;M:Ljava/lang/Object;N:Ljava/lang/Object;O:Ljava/lang/Object;P:Ljava/lang/Object;Q:Ljava/lang/Object;R:Ljava/lang/Object;>(Lshapeless/Poly;Lshapeless/PolyDefns$Case<+Lshapeless/Poly;Lshapeless/$colon$colon<TA;Lshapeless/$colon$colon<TB;Lshapeless/$colon$colon<TC;Lshapeless/$colon$colon<TD;Lshapeless/$colon$colon<TE;Lshapeless/$colon$colon<TF;Lshapeless/$colon$colon<TG;Lshapeless/$colon$colon<TH;Lshapeless/$colon$colon<TI;Lshapeless/$colon$colon<TJ;Lshapeless/$colon$colon<TK;Lshapeless/$colon$colon<TL;Lshapeless/$colon$colon<TM;Lshapeless/$colon$colon<TN;Lshapeless/$colon$colon<TO;Lshapeless/$colon$colon<TP;Lshapeless/$colon$colon<TQ;Lshapeless/$colon$colon<TR;Lshapeless/HNil;>;>;>;>;>;>;>;>;>;>;>;>;>;>;>;>;>;>;>;)Lscala/Function18<TA;TB;TC;TD;TE;TF;TG;TH;TI;TJ;TK;TL;TM;TN;TO;TP;TQ;TR;Ljava/lang/Object;>;
  #155 = Utf8               inst18$
  #156 = Utf8               (Lshapeless/PolyInst;Lshapeless/Poly;Lshapeless/PolyDefns$Case;)Lscala/Function18;
  #157 = NameAndType        #155:#156     // inst18$:(Lshapeless/PolyInst;Lshapeless/Poly;Lshapeless/PolyDefns$Case;)Lscala/Function18;
  #158 = InterfaceMethodref #6.#157       // shapeless/PolyInst.inst18$:(Lshapeless/PolyInst;Lshapeless/Poly;Lshapeless/PolyDefns$Case;)Lscala/Function18;
  #159 = Utf8               inst19
  #160 = Utf8               (Lshapeless/Poly;Lshapeless/PolyDefns$Case;)Lscala/Function19;
  #161 = Utf8               <A:Ljava/lang/Object;B:Ljava/lang/Object;C:Ljava/lang/Object;D:Ljava/lang/Object;E:Ljava/lang/Object;F:Ljava/lang/Object;G:Ljava/lang/Object;H:Ljava/lang/Object;I:Ljava/lang/Object;J:Ljava/lang/Object;K:Ljava/lang/Object;L:Ljava/lang/Object;M:Ljava/lang/Object;N:Ljava/lang/Object;O:Ljava/lang/Object;P:Ljava/lang/Object;Q:Ljava/lang/Object;R:Ljava/lang/Object;S:Ljava/lang/Object;>(Lshapeless/Poly;Lshapeless/PolyDefns$Case<+Lshapeless/Poly;Lshapeless/$colon$colon<TA;Lshapeless/$colon$colon<TB;Lshapeless/$colon$colon<TC;Lshapeless/$colon$colon<TD;Lshapeless/$colon$colon<TE;Lshapeless/$colon$colon<TF;Lshapeless/$colon$colon<TG;Lshapeless/$colon$colon<TH;Lshapeless/$colon$colon<TI;Lshapeless/$colon$colon<TJ;Lshapeless/$colon$colon<TK;Lshapeless/$colon$colon<TL;Lshapeless/$colon$colon<TM;Lshapeless/$colon$colon<TN;Lshapeless/$colon$colon<TO;Lshapeless/$colon$colon<TP;Lshapeless/$colon$colon<TQ;Lshapeless/$colon$colon<TR;Lshapeless/$colon$colon<TS;Lshapeless/HNil;>;>;>;>;>;>;>;>;>;>;>;>;>;>;>;>;>;>;>;>;)Lscala/Function19<TA;TB;TC;TD;TE;TF;TG;TH;TI;TJ;TK;TL;TM;TN;TO;TP;TQ;TR;TS;Ljava/lang/Object;>;
  #162 = Utf8               inst19$
  #163 = Utf8               (Lshapeless/PolyInst;Lshapeless/Poly;Lshapeless/PolyDefns$Case;)Lscala/Function19;
  #164 = NameAndType        #162:#163     // inst19$:(Lshapeless/PolyInst;Lshapeless/Poly;Lshapeless/PolyDefns$Case;)Lscala/Function19;
  #165 = InterfaceMethodref #6.#164       // shapeless/PolyInst.inst19$:(Lshapeless/PolyInst;Lshapeless/Poly;Lshapeless/PolyDefns$Case;)Lscala/Function19;
  #166 = Utf8               inst20
  #167 = Utf8               (Lshapeless/Poly;Lshapeless/PolyDefns$Case;)Lscala/Function20;
  #168 = Utf8               <A:Ljava/lang/Object;B:Ljava/lang/Object;C:Ljava/lang/Object;D:Ljava/lang/Object;E:Ljava/lang/Object;F:Ljava/lang/Object;G:Ljava/lang/Object;H:Ljava/lang/Object;I:Ljava/lang/Object;J:Ljava/lang/Object;K:Ljava/lang/Object;L:Ljava/lang/Object;M:Ljava/lang/Object;N:Ljava/lang/Object;O:Ljava/lang/Object;P:Ljava/lang/Object;Q:Ljava/lang/Object;R:Ljava/lang/Object;S:Ljava/lang/Object;T:Ljava/lang/Object;>(Lshapeless/Poly;Lshapeless/PolyDefns$Case<+Lshapeless/Poly;Lshapeless/$colon$colon<TA;Lshapeless/$colon$colon<TB;Lshapeless/$colon$colon<TC;Lshapeless/$colon$colon<TD;Lshapeless/$colon$colon<TE;Lshapeless/$colon$colon<TF;Lshapeless/$colon$colon<TG;Lshapeless/$colon$colon<TH;Lshapeless/$colon$colon<TI;Lshapeless/$colon$colon<TJ;Lshapeless/$colon$colon<TK;Lshapeless/$colon$colon<TL;Lshapeless/$colon$colon<TM;Lshapeless/$colon$colon<TN;Lshapeless/$colon$colon<TO;Lshapeless/$colon$colon<TP;Lshapeless/$colon$colon<TQ;Lshapeless/$colon$colon<TR;Lshapeless/$colon$colon<TS;Lshapeless/$colon$colon<TT;Lshapeless/HNil;>;>;>;>;>;>;>;>;>;>;>;>;>;>;>;>;>;>;>;>;>;)Lscala/Function20<TA;TB;TC;TD;TE;TF;TG;TH;TI;TJ;TK;TL;TM;TN;TO;TP;TQ;TR;TS;TT;Ljava/lang/Object;>;
  #169 = Utf8               inst20$
  #170 = Utf8               (Lshapeless/PolyInst;Lshapeless/Poly;Lshapeless/PolyDefns$Case;)Lscala/Function20;
  #171 = NameAndType        #169:#170     // inst20$:(Lshapeless/PolyInst;Lshapeless/Poly;Lshapeless/PolyDefns$Case;)Lscala/Function20;
  #172 = InterfaceMethodref #6.#171       // shapeless/PolyInst.inst20$:(Lshapeless/PolyInst;Lshapeless/Poly;Lshapeless/PolyDefns$Case;)Lscala/Function20;
  #173 = Utf8               inst21
  #174 = Utf8               (Lshapeless/Poly;Lshapeless/PolyDefns$Case;)Lscala/Function21;
  #175 = Utf8               <A:Ljava/lang/Object;B:Ljava/lang/Object;C:Ljava/lang/Object;D:Ljava/lang/Object;E:Ljava/lang/Object;F:Ljava/lang/Object;G:Ljava/lang/Object;H:Ljava/lang/Object;I:Ljava/lang/Object;J:Ljava/lang/Object;K:Ljava/lang/Object;L:Ljava/lang/Object;M:Ljava/lang/Object;N:Ljava/lang/Object;O:Ljava/lang/Object;P:Ljava/lang/Object;Q:Ljava/lang/Object;R:Ljava/lang/Object;S:Ljava/lang/Object;T:Ljava/lang/Object;U:Ljava/lang/Object;>(Lshapeless/Poly;Lshapeless/PolyDefns$Case<+Lshapeless/Poly;Lshapeless/$colon$colon<TA;Lshapeless/$colon$colon<TB;Lshapeless/$colon$colon<TC;Lshapeless/$colon$colon<TD;Lshapeless/$colon$colon<TE;Lshapeless/$colon$colon<TF;Lshapeless/$colon$colon<TG;Lshapeless/$colon$colon<TH;Lshapeless/$colon$colon<TI;Lshapeless/$colon$colon<TJ;Lshapeless/$colon$colon<TK;Lshapeless/$colon$colon<TL;Lshapeless/$colon$colon<TM;Lshapeless/$colon$colon<TN;Lshapeless/$colon$colon<TO;Lshapeless/$colon$colon<TP;Lshapeless/$colon$colon<TQ;Lshapeless/$colon$colon<TR;Lshapeless/$colon$colon<TS;Lshapeless/$colon$colon<TT;Lshapeless/$colon$colon<TU;Lshapeless/HNil;>;>;>;>;>;>;>;>;>;>;>;>;>;>;>;>;>;>;>;>;>;>;)Lscala/Function21<TA;TB;TC;TD;TE;TF;TG;TH;TI;TJ;TK;TL;TM;TN;TO;TP;TQ;TR;TS;TT;TU;Ljava/lang/Object;>;
  #176 = Utf8               inst21$
  #177 = Utf8               (Lshapeless/PolyInst;Lshapeless/Poly;Lshapeless/PolyDefns$Case;)Lscala/Function21;
  #178 = NameAndType        #176:#177     // inst21$:(Lshapeless/PolyInst;Lshapeless/Poly;Lshapeless/PolyDefns$Case;)Lscala/Function21;
  #179 = InterfaceMethodref #6.#178       // shapeless/PolyInst.inst21$:(Lshapeless/PolyInst;Lshapeless/Poly;Lshapeless/PolyDefns$Case;)Lscala/Function21;
  #180 = Utf8               inst22
  #181 = Utf8               (Lshapeless/Poly;Lshapeless/PolyDefns$Case;)Lscala/Function22;
  #182 = Utf8               <A:Ljava/lang/Object;B:Ljava/lang/Object;C:Ljava/lang/Object;D:Ljava/lang/Object;E:Ljava/lang/Object;F:Ljava/lang/Object;G:Ljava/lang/Object;H:Ljava/lang/Object;I:Ljava/lang/Object;J:Ljava/lang/Object;K:Ljava/lang/Object;L:Ljava/lang/Object;M:Ljava/lang/Object;N:Ljava/lang/Object;O:Ljava/lang/Object;P:Ljava/lang/Object;Q:Ljava/lang/Object;R:Ljava/lang/Object;S:Ljava/lang/Object;T:Ljava/lang/Object;U:Ljava/lang/Object;V:Ljava/lang/Object;>(Lshapeless/Poly;Lshapeless/PolyDefns$Case<+Lshapeless/Poly;Lshapeless/$colon$colon<TA;Lshapeless/$colon$colon<TB;Lshapeless/$colon$colon<TC;Lshapeless/$colon$colon<TD;Lshapeless/$colon$colon<TE;Lshapeless/$colon$colon<TF;Lshapeless/$colon$colon<TG;Lshapeless/$colon$colon<TH;Lshapeless/$colon$colon<TI;Lshapeless/$colon$colon<TJ;Lshapeless/$colon$colon<TK;Lshapeless/$colon$colon<TL;Lshapeless/$colon$colon<TM;Lshapeless/$colon$colon<TN;Lshapeless/$colon$colon<TO;Lshapeless/$colon$colon<TP;Lshapeless/$colon$colon<TQ;Lshapeless/$colon$colon<TR;Lshapeless/$colon$colon<TS;Lshapeless/$colon$colon<TT;Lshapeless/$colon$colon<TU;Lshapeless/$colon$colon<TV;Lshapeless/HNil;>;>;>;>;>;>;>;>;>;>;>;>;>;>;>;>;>;>;>;>;>;>;>;)Lscala/Function22<TA;TB;TC;TD;TE;TF;TG;TH;TI;TJ;TK;TL;TM;TN;TO;TP;TQ;TR;TS;TT;TU;TV;Ljava/lang/Object;>;
  #183 = Utf8               inst22$
  #184 = Utf8               (Lshapeless/PolyInst;Lshapeless/Poly;Lshapeless/PolyDefns$Case;)Lscala/Function22;
  #185 = NameAndType        #183:#184     // inst22$:(Lshapeless/PolyInst;Lshapeless/Poly;Lshapeless/PolyDefns$Case;)Lscala/Function22;
  #186 = InterfaceMethodref #6.#185       // shapeless/PolyInst.inst22$:(Lshapeless/PolyInst;Lshapeless/Poly;Lshapeless/PolyDefns$Case;)Lscala/Function22;
  #187 = Utf8               inst0
  #188 = Utf8               (Lshapeless/Poly;Lshapeless/PolyDefns$Case;)Ljava/lang/Object;
  #189 = Utf8               (Lshapeless/Poly;Lshapeless/PolyDefns$Case<+Lshapeless/Poly;Lshapeless/HNil;>;)Ljava/lang/Object;
  #190 = Utf8               p
  #191 = Utf8               scala/$less$colon$less$
  #192 = Class              #191          // scala/$less$colon$less$
  #193 = Utf8               Lscala/$less$colon$less$;
  #194 = NameAndType        #15:#193      // MODULE$:Lscala/$less$colon$less$;
  #195 = Fieldref           #192.#194     // scala/$less$colon$less$.MODULE$:Lscala/$less$colon$less$;
  #196 = Utf8               refl
  #197 = Utf8               ()Lscala/$eq$colon$eq;
  #198 = NameAndType        #196:#197     // refl:()Lscala/$eq$colon$eq;
  #199 = Methodref          #192.#198     // scala/$less$colon$less$.refl:()Lscala/$eq$colon$eq;
  #200 = Utf8               apply
  #201 = Utf8               (Lscala/$eq$colon$eq;)Ljava/lang/Object;
  #202 = NameAndType        #200:#201     // apply:(Lscala/$eq$colon$eq;)Ljava/lang/Object;
  #203 = Methodref          #11.#202      // shapeless/PolyDefns$Case.apply:(Lscala/$eq$colon$eq;)Ljava/lang/Object;
  #204 = Utf8               writeReplace
  #205 = Utf8               ()Ljava/lang/Object;
  #206 = Utf8               scala/runtime/ModuleSerializationProxy
  #207 = Class              #206          // scala/runtime/ModuleSerializationProxy
  #208 = Utf8               (Ljava/lang/Class;)V
  #209 = NameAndType        #19:#208      // "<init>":(Ljava/lang/Class;)V
  #210 = Methodref          #207.#209     // scala/runtime/ModuleSerializationProxy."<init>":(Ljava/lang/Class;)V
  #211 = Methodref          #4.#20        // java/lang/Object."<init>":()V
  #212 = Utf8               Code
  #213 = Utf8               LineNumberTable
  #214 = Utf8               LocalVariableTable
  #215 = Utf8               Signature
  #216 = Utf8               MethodParameters
  #217 = Utf8               InnerClasses
  #218 = Utf8               SourceFile
  #219 = Utf8               ScalaInlineInfo
  #220 = Utf8               Scala
{
  public static final shapeless.Poly$ MODULE$;
    descriptor: Lshapeless/Poly$;
    flags: (0x0019) ACC_PUBLIC, ACC_STATIC, ACC_FINAL

  public static {};
    descriptor: ()V
    flags: (0x0009) ACC_PUBLIC, ACC_STATIC
    Code:
      stack=2, locals=0, args_size=0
         0: new           #2                  // class shapeless/Poly$
         3: dup
         4: invokespecial #21                 // Method "<init>":()V
         7: putstatic     #23                 // Field MODULE$:Lshapeless/Poly$;
        10: getstatic     #23                 // Field MODULE$:Lshapeless/Poly$;
        13: invokestatic  #27                 // InterfaceMethod shapeless/PolyInst.$init$:(Lshapeless/PolyInst;)V
        16: return
      LineNumberTable:
        line 247: 0

  public <A extends java.lang.Object> scala.Function1<A, java.lang.Object> inst1(shapeless.Poly, shapeless.PolyDefns$Case<? extends shapeless.Poly, shapeless.$colon$colon<A, shapeless.HNil>>);
    descriptor: (Lshapeless/Poly;Lshapeless/PolyDefns$Case;)Lscala/Function1;
    flags: (0x0001) ACC_PUBLIC
    Code:
      stack=3, locals=3, args_size=3
         0: aload_0
         1: aload_1
         2: aload_2
         3: invokestatic  #36                 // InterfaceMethod shapeless/PolyInst.inst1$:(Lshapeless/PolyInst;Lshapeless/Poly;Lshapeless/PolyDefns$Case;)Lscala/Function1;
         6: areturn
      LineNumberTable:
        line 247: 0
      LocalVariableTable:
        Start  Length  Slot  Name   Signature
            0       7     0  this   Lshapeless/Poly$;
            0       7     1    fn   Lshapeless/Poly;
            0       7     2   cse   Lshapeless/PolyDefns$Case;
    Signature: #30                          // <A:Ljava/lang/Object;>(Lshapeless/Poly;Lshapeless/PolyDefns$Case<+Lshapeless/Poly;Lshapeless/$colon$colon<TA;Lshapeless/HNil;>;>;)Lscala/Function1<TA;Ljava/lang/Object;>;
    MethodParameters:
      Name                           Flags
      fn                             final
      cse                            final

  public <A extends java.lang.Object, B extends java.lang.Object> scala.Function2<A, B, java.lang.Object> inst2(shapeless.Poly, shapeless.PolyDefns$Case<? extends shapeless.Poly, shapeless.$colon$colon<A, shapeless.$colon$colon<B, shapeless.HNil>>>);
    descriptor: (Lshapeless/Poly;Lshapeless/PolyDefns$Case;)Lscala/Function2;
    flags: (0x0001) ACC_PUBLIC
    Code:
      stack=3, locals=3, args_size=3
         0: aload_0
         1: aload_1
         2: aload_2
         3: invokestatic  #46                 // InterfaceMethod shapeless/PolyInst.inst2$:(Lshapeless/PolyInst;Lshapeless/Poly;Lshapeless/PolyDefns$Case;)Lscala/Function2;
         6: areturn
      LineNumberTable:
        line 247: 0
      LocalVariableTable:
        Start  Length  Slot  Name   Signature
            0       7     0  this   Lshapeless/Poly$;
            0       7     1    fn   Lshapeless/Poly;
            0       7     2   cse   Lshapeless/PolyDefns$Case;
    Signature: #42                          // <A:Ljava/lang/Object;B:Ljava/lang/Object;>(Lshapeless/Poly;Lshapeless/PolyDefns$Case<+Lshapeless/Poly;Lshapeless/$colon$colon<TA;Lshapeless/$colon$colon<TB;Lshapeless/HNil;>;>;>;)Lscala/Function2<TA;TB;Ljava/lang/Object;>;
    MethodParameters:
      Name                           Flags
      fn                             final
      cse                            final

  public <A extends java.lang.Object, B extends java.lang.Object, C extends java.lang.Object> scala.Function3<A, B, C, java.lang.Object> inst3(shapeless.Poly, shapeless.PolyDefns$Case<? extends shapeless.Poly, shapeless.$colon$colon<A, shapeless.$colon$colon<B, shapeless.$colon$colon<C, shapeless.HNil>>>>);
    descriptor: (Lshapeless/Poly;Lshapeless/PolyDefns$Case;)Lscala/Function3;
    flags: (0x0001) ACC_PUBLIC
    Code:
      stack=3, locals=3, args_size=3
         0: aload_0
         1: aload_1
         2: aload_2
         3: invokestatic  #53                 // InterfaceMethod shapeless/PolyInst.inst3$:(Lshapeless/PolyInst;Lshapeless/Poly;Lshapeless/PolyDefns$Case;)Lscala/Function3;
         6: areturn
      LineNumberTable:
        line 247: 0
      LocalVariableTable:
        Start  Length  Slot  Name   Signature
            0       7     0  this   Lshapeless/Poly$;
            0       7     1    fn   Lshapeless/Poly;
            0       7     2   cse   Lshapeless/PolyDefns$Case;
    Signature: #49                          // <A:Ljava/lang/Object;B:Ljava/lang/Object;C:Ljava/lang/Object;>(Lshapeless/Poly;Lshapeless/PolyDefns$Case<+Lshapeless/Poly;Lshapeless/$colon$colon<TA;Lshapeless/$colon$colon<TB;Lshapeless/$colon$colon<TC;Lshapeless/HNil;>;>;>;>;)Lscala/Function3<TA;TB;TC;Ljava/lang/Object;>;
    MethodParameters:
      Name                           Flags
      fn                             final
      cse                            final

  public <A extends java.lang.Object, B extends java.lang.Object, C extends java.lang.Object, D extends java.lang.Object> scala.Function4<A, B, C, D, java.lang.Object> inst4(shapeless.Poly, shapeless.PolyDefns$Case<? extends shapeless.Poly, shapeless.$colon$colon<A, shapeless.$colon$colon<B, shapeless.$colon$colon<C, shapeless.$colon$colon<D, shapeless.HNil>>>>>);
    descriptor: (Lshapeless/Poly;Lshapeless/PolyDefns$Case;)Lscala/Function4;
    flags: (0x0001) ACC_PUBLIC
    Code:
      stack=3, locals=3, args_size=3
         0: aload_0
         1: aload_1
         2: aload_2
         3: invokestatic  #60                 // InterfaceMethod shapeless/PolyInst.inst4$:(Lshapeless/PolyInst;Lshapeless/Poly;Lshapeless/PolyDefns$Case;)Lscala/Function4;
         6: areturn
      LineNumberTable:
        line 247: 0
      LocalVariableTable:
        Start  Length  Slot  Name   Signature
            0       7     0  this   Lshapeless/Poly$;
            0       7     1    fn   Lshapeless/Poly;
            0       7     2   cse   Lshapeless/PolyDefns$Case;
    Signature: #56                          // <A:Ljava/lang/Object;B:Ljava/lang/Object;C:Ljava/lang/Object;D:Ljava/lang/Object;>(Lshapeless/Poly;Lshapeless/PolyDefns$Case<+Lshapeless/Poly;Lshapeless/$colon$colon<TA;Lshapeless/$colon$colon<TB;Lshapeless/$colon$colon<TC;Lshapeless/$colon$colon<TD;Lshapeless/HNil;>;>;>;>;>;)Lscala/Function4<TA;TB;TC;TD;Ljava/lang/Object;>;
    MethodParameters:
      Name                           Flags
      fn                             final
      cse                            final

  public <A extends java.lang.Object, B extends java.lang.Object, C extends java.lang.Object, D extends java.lang.Object, E extends java.lang.Object> scala.Function5<A, B, C, D, E, java.lang.Object> inst5(shapeless.Poly, shapeless.PolyDefns$Case<? extends shapeless.Poly, shapeless.$colon$colon<A, shapeless.$colon$colon<B, shapeless.$colon$colon<C, shapeless.$colon$colon<D, shapeless.$colon$colon<E, shapeless.HNil>>>>>>);
    descriptor: (Lshapeless/Poly;Lshapeless/PolyDefns$Case;)Lscala/Function5;
    flags: (0x0001) ACC_PUBLIC
    Code:
      stack=3, locals=3, args_size=3
         0: aload_0
         1: aload_1
         2: aload_2
         3: invokestatic  #67                 // InterfaceMethod shapeless/PolyInst.inst5$:(Lshapeless/PolyInst;Lshapeless/Poly;Lshapeless/PolyDefns$Case;)Lscala/Function5;
         6: areturn
      LineNumberTable:
        line 247: 0
      LocalVariableTable:
        Start  Length  Slot  Name   Signature
            0       7     0  this   Lshapeless/Poly$;
            0       7     1    fn   Lshapeless/Poly;
            0       7     2   cse   Lshapeless/PolyDefns$Case;
    Signature: #63                          // <A:Ljava/lang/Object;B:Ljava/lang/Object;C:Ljava/lang/Object;D:Ljava/lang/Object;E:Ljava/lang/Object;>(Lshapeless/Poly;Lshapeless/PolyDefns$Case<+Lshapeless/Poly;Lshapeless/$colon$colon<TA;Lshapeless/$colon$colon<TB;Lshapeless/$colon$colon<TC;Lshapeless/$colon$colon<TD;Lshapeless/$colon$colon<TE;Lshapeless/HNil;>;>;>;>;>;>;)Lscala/Function5<TA;TB;TC;TD;TE;Ljava/lang/Object;>;
    MethodParameters:
      Name                           Flags
      fn                             final
      cse                            final

  public <A extends java.lang.Object, B extends java.lang.Object, C extends java.lang.Object, D extends java.lang.Object, E extends java.lang.Object, F extends java.lang.Object> scala.Function6<A, B, C, D, E, F, java.lang.Object> inst6(shapeless.Poly, shapeless.PolyDefns$Case<? extends shapeless.Poly, shapeless.$colon$colon<A, shapeless.$colon$colon<B, shapeless.$colon$colon<C, shapeless.$colon$colon<D, shapeless.$colon$colon<E, shapeless.$colon$colon<F, shapeless.HNil>>>>>>>);
    descriptor: (Lshapeless/Poly;Lshapeless/PolyDefns$Case;)Lscala/Function6;
    flags: (0x0001) ACC_PUBLIC
    Code:
      stack=3, locals=3, args_size=3
         0: aload_0
         1: aload_1
         2: aload_2
         3: invokestatic  #74                 // InterfaceMethod shapeless/PolyInst.inst6$:(Lshapeless/PolyInst;Lshapeless/Poly;Lshapeless/PolyDefns$Case;)Lscala/Function6;
         6: areturn
      LineNumberTable:
        line 247: 0
      LocalVariableTable:
        Start  Length  Slot  Name   Signature
            0       7     0  this   Lshapeless/Poly$;
            0       7     1    fn   Lshapeless/Poly;
            0       7     2   cse   Lshapeless/PolyDefns$Case;
    Signature: #70                          // <A:Ljava/lang/Object;B:Ljava/lang/Object;C:Ljava/lang/Object;D:Ljava/lang/Object;E:Ljava/lang/Object;F:Ljava/lang/Object;>(Lshapeless/Poly;Lshapeless/PolyDefns$Case<+Lshapeless/Poly;Lshapeless/$colon$colon<TA;Lshapeless/$colon$colon<TB;Lshapeless/$colon$colon<TC;Lshapeless/$colon$colon<TD;Lshapeless/$colon$colon<TE;Lshapeless/$colon$colon<TF;Lshapeless/HNil;>;>;>;>;>;>;>;)Lscala/Function6<TA;TB;TC;TD;TE;TF;Ljava/lang/Object;>;
    MethodParameters:
      Name                           Flags
      fn                             final
      cse                            final

  public <A extends java.lang.Object, B extends java.lang.Object, C extends java.lang.Object, D extends java.lang.Object, E extends java.lang.Object, F extends java.lang.Object, G extends java.lang.Object> scala.Function7<A, B, C, D, E, F, G, java.lang.Object> inst7(shapeless.Poly, shapeless.PolyDefns$Case<? extends shapeless.Poly, shapeless.$colon$colon<A, shapeless.$colon$colon<B, shapeless.$colon$colon<C, shapeless.$colon$colon<D, shapeless.$colon$colon<E, shapeless.$colon$colon<F, shapeless.$colon$colon<G, shapeless.HNil>>>>>>>>);
    descriptor: (Lshapeless/Poly;Lshapeless/PolyDefns$Case;)Lscala/Function7;
    flags: (0x0001) ACC_PUBLIC
    Code:
      stack=3, locals=3, args_size=3
         0: aload_0
         1: aload_1
         2: aload_2
         3: invokestatic  #81                 // InterfaceMethod shapeless/PolyInst.inst7$:(Lshapeless/PolyInst;Lshapeless/Poly;Lshapeless/PolyDefns$Case;)Lscala/Function7;
         6: areturn
      LineNumberTable:
        line 247: 0
      LocalVariableTable:
        Start  Length  Slot  Name   Signature
            0       7     0  this   Lshapeless/Poly$;
            0       7     1    fn   Lshapeless/Poly;
            0       7     2   cse   Lshapeless/PolyDefns$Case;
    Signature: #77                          // <A:Ljava/lang/Object;B:Ljava/lang/Object;C:Ljava/lang/Object;D:Ljava/lang/Object;E:Ljava/lang/Object;F:Ljava/lang/Object;G:Ljava/lang/Object;>(Lshapeless/Poly;Lshapeless/PolyDefns$Case<+Lshapeless/Poly;Lshapeless/$colon$colon<TA;Lshapeless/$colon$colon<TB;Lshapeless/$colon$colon<TC;Lshapeless/$colon$colon<TD;Lshapeless/$colon$colon<TE;Lshapeless/$colon$colon<TF;Lshapeless/$colon$colon<TG;Lshapeless/HNil;>;>;>;>;>;>;>;>;)Lscala/Function7<TA;TB;TC;TD;TE;TF;TG;Ljava/lang/Object;>;
    MethodParameters:
      Name                           Flags
      fn                             final
      cse                            final

  public <A extends java.lang.Object, B extends java.lang.Object, C extends java.lang.Object, D extends java.lang.Object, E extends java.lang.Object, F extends java.lang.Object, G extends java.lang.Object, H extends java.lang.Object> scala.Function8<A, B, C, D, E, F, G, H, java.lang.Object> inst8(shapeless.Poly, shapeless.PolyDefns$Case<? extends shapeless.Poly, shapeless.$colon$colon<A, shapeless.$colon$colon<B, shapeless.$colon$colon<C, shapeless.$colon$colon<D, shapeless.$colon$colon<E, shapeless.$colon$colon<F, shapeless.$colon$colon<G, shapeless.$colon$colon<H, shapeless.HNil>>>>>>>>>);
    descriptor: (Lshapeless/Poly;Lshapeless/PolyDefns$Case;)Lscala/Function8;
    flags: (0x0001) ACC_PUBLIC
    Code:
      stack=3, locals=3, args_size=3
         0: aload_0
         1: aload_1
         2: aload_2
         3: invokestatic  #88                 // InterfaceMethod shapeless/PolyInst.inst8$:(Lshapeless/PolyInst;Lshapeless/Poly;Lshapeless/PolyDefns$Case;)Lscala/Function8;
         6: areturn
      LineNumberTable:
        line 247: 0
      LocalVariableTable:
        Start  Length  Slot  Name   Signature
            0       7     0  this   Lshapeless/Poly$;
            0       7     1    fn   Lshapeless/Poly;
            0       7     2   cse   Lshapeless/PolyDefns$Case;
    Signature: #84                          // <A:Ljava/lang/Object;B:Ljava/lang/Object;C:Ljava/lang/Object;D:Ljava/lang/Object;E:Ljava/lang/Object;F:Ljava/lang/Object;G:Ljava/lang/Object;H:Ljava/lang/Object;>(Lshapeless/Poly;Lshapeless/PolyDefns$Case<+Lshapeless/Poly;Lshapeless/$colon$colon<TA;Lshapeless/$colon$colon<TB;Lshapeless/$colon$colon<TC;Lshapeless/$colon$colon<TD;Lshapeless/$colon$colon<TE;Lshapeless/$colon$colon<TF;Lshapeless/$colon$colon<TG;Lshapeless/$colon$colon<TH;Lshapeless/HNil;>;>;>;>;>;>;>;>;>;)Lscala/Function8<TA;TB;TC;TD;TE;TF;TG;TH;Ljava/lang/Object;>;
    MethodParameters:
      Name                           Flags
      fn                             final
      cse                            final

  public <A extends java.lang.Object, B extends java.lang.Object, C extends java.lang.Object, D extends java.lang.Object, E extends java.lang.Object, F extends java.lang.Object, G extends java.lang.Object, H extends java.lang.Object, I extends java.lang.Object> scala.Function9<A, B, C, D, E, F, G, H, I, java.lang.Object> inst9(shapeless.Poly, shapeless.PolyDefns$Case<? extends shapeless.Poly, shapeless.$colon$colon<A, shapeless.$colon$colon<B, shapeless.$colon$colon<C, shapeless.$colon$colon<D, shapeless.$colon$colon<E, shapeless.$colon$colon<F, shapeless.$colon$colon<G, shapeless.$colon$colon<H, shapeless.$colon$colon<I, shapeless.HNil>>>>>>>>>>);
    descriptor: (Lshapeless/Poly;Lshapeless/PolyDefns$Case;)Lscala/Function9;
    flags: (0x0001) ACC_PUBLIC
    Code:
      stack=3, locals=3, args_size=3
         0: aload_0
         1: aload_1
         2: aload_2
         3: invokestatic  #95                 // InterfaceMethod shapeless/PolyInst.inst9$:(Lshapeless/PolyInst;Lshapeless/Poly;Lshapeless/PolyDefns$Case;)Lscala/Function9;
         6: areturn
      LineNumberTable:
        line 247: 0
      LocalVariableTable:
        Start  Length  Slot  Name   Signature
            0       7     0  this   Lshapeless/Poly$;
            0       7     1    fn   Lshapeless/Poly;
            0       7     2   cse   Lshapeless/PolyDefns$Case;
    Signature: #91                          // <A:Ljava/lang/Object;B:Ljava/lang/Object;C:Ljava/lang/Object;D:Ljava/lang/Object;E:Ljava/lang/Object;F:Ljava/lang/Object;G:Ljava/lang/Object;H:Ljava/lang/Object;I:Ljava/lang/Object;>(Lshapeless/Poly;Lshapeless/PolyDefns$Case<+Lshapeless/Poly;Lshapeless/$colon$colon<TA;Lshapeless/$colon$colon<TB;Lshapeless/$colon$colon<TC;Lshapeless/$colon$colon<TD;Lshapeless/$colon$colon<TE;Lshapeless/$colon$colon<TF;Lshapeless/$colon$colon<TG;Lshapeless/$colon$colon<TH;Lshapeless/$colon$colon<TI;Lshapeless/HNil;>;>;>;>;>;>;>;>;>;>;)Lscala/Function9<TA;TB;TC;TD;TE;TF;TG;TH;TI;Ljava/lang/Object;>;
    MethodParameters:
      Name                           Flags
      fn                             final
      cse                            final

  public <A extends java.lang.Object, B extends java.lang.Object, C extends java.lang.Object, D extends java.lang.Object, E extends java.lang.Object, F extends java.lang.Object, G extends java.lang.Object, H extends java.lang.Object, I extends java.lang.Object, J extends java.lang.Object> scala.Function10<A, B, C, D, E, F, G, H, I, J, java.lang.Object> inst10(shapeless.Poly, shapeless.PolyDefns$Case<? extends shapeless.Poly, shapeless.$colon$colon<A, shapeless.$colon$colon<B, shapeless.$colon$colon<C, shapeless.$colon$colon<D, shapeless.$colon$colon<E, shapeless.$colon$colon<F, shapeless.$colon$colon<G, shapeless.$colon$colon<H, shapeless.$colon$colon<I, shapeless.$colon$colon<J, shapeless.HNil>>>>>>>>>>>);
    descriptor: (Lshapeless/Poly;Lshapeless/PolyDefns$Case;)Lscala/Function10;
    flags: (0x0001) ACC_PUBLIC
    Code:
      stack=3, locals=3, args_size=3
         0: aload_0
         1: aload_1
         2: aload_2
         3: invokestatic  #102                // InterfaceMethod shapeless/PolyInst.inst10$:(Lshapeless/PolyInst;Lshapeless/Poly;Lshapeless/PolyDefns$Case;)Lscala/Function10;
         6: areturn
      LineNumberTable:
        line 247: 0
      LocalVariableTable:
        Start  Length  Slot  Name   Signature
            0       7     0  this   Lshapeless/Poly$;
            0       7     1    fn   Lshapeless/Poly;
            0       7     2   cse   Lshapeless/PolyDefns$Case;
    Signature: #98                          // <A:Ljava/lang/Object;B:Ljava/lang/Object;C:Ljava/lang/Object;D:Ljava/lang/Object;E:Ljava/lang/Object;F:Ljava/lang/Object;G:Ljava/lang/Object;H:Ljava/lang/Object;I:Ljava/lang/Object;J:Ljava/lang/Object;>(Lshapeless/Poly;Lshapeless/PolyDefns$Case<+Lshapeless/Poly;Lshapeless/$colon$colon<TA;Lshapeless/$colon$colon<TB;Lshapeless/$colon$colon<TC;Lshapeless/$colon$colon<TD;Lshapeless/$colon$colon<TE;Lshapeless/$colon$colon<TF;Lshapeless/$colon$colon<TG;Lshapeless/$colon$colon<TH;Lshapeless/$colon$colon<TI;Lshapeless/$colon$colon<TJ;Lshapeless/HNil;>;>;>;>;>;>;>;>;>;>;>;)Lscala/Function10<TA;TB;TC;TD;TE;TF;TG;TH;TI;TJ;Ljava/lang/Object;>;
    MethodParameters:
      Name                           Flags
      fn                             final
      cse                            final

  public <A extends java.lang.Object, B extends java.lang.Object, C extends java.lang.Object, D extends java.lang.Object, E extends java.lang.Object, F extends java.lang.Object, G extends java.lang.Object, H extends java.lang.Object, I extends java.lang.Object, J extends java.lang.Object, K extends java.lang.Object> scala.Function11<A, B, C, D, E, F, G, H, I, J, K, java.lang.Object> inst11(shapeless.Poly, shapeless.PolyDefns$Case<? extends shapeless.Poly, shapeless.$colon$colon<A, shapeless.$colon$colon<B, shapeless.$colon$colon<C, shapeless.$colon$colon<D, shapeless.$colon$colon<E, shapeless.$colon$colon<F, shapeless.$colon$colon<G, shapeless.$colon$colon<H, shapeless.$colon$colon<I, shapeless.$colon$colon<J, shapeless.$colon$colon<K, shapeless.HNil>>>>>>>>>>>>);
    descriptor: (Lshapeless/Poly;Lshapeless/PolyDefns$Case;)Lscala/Function11;
    flags: (0x0001) ACC_PUBLIC
    Code:
      stack=3, locals=3, args_size=3
         0: aload_0
         1: aload_1
         2: aload_2
         3: invokestatic  #109                // InterfaceMethod shapeless/PolyInst.inst11$:(Lshapeless/PolyInst;Lshapeless/Poly;Lshapeless/PolyDefns$Case;)Lscala/Function11;
         6: areturn
      LineNumberTable:
        line 247: 0
      LocalVariableTable:
        Start  Length  Slot  Name   Signature
            0       7     0  this   Lshapeless/Poly$;
            0       7     1    fn   Lshapeless/Poly;
            0       7     2   cse   Lshapeless/PolyDefns$Case;
    Signature: #105                         // <A:Ljava/lang/Object;B:Ljava/lang/Object;C:Ljava/lang/Object;D:Ljava/lang/Object;E:Ljava/lang/Object;F:Ljava/lang/Object;G:Ljava/lang/Object;H:Ljava/lang/Object;I:Ljava/lang/Object;J:Ljava/lang/Object;K:Ljava/lang/Object;>(Lshapeless/Poly;Lshapeless/PolyDefns$Case<+Lshapeless/Poly;Lshapeless/$colon$colon<TA;Lshapeless/$colon$colon<TB;Lshapeless/$colon$colon<TC;Lshapeless/$colon$colon<TD;Lshapeless/$colon$colon<TE;Lshapeless/$colon$colon<TF;Lshapeless/$colon$colon<TG;Lshapeless/$colon$colon<TH;Lshapeless/$colon$colon<TI;Lshapeless/$colon$colon<TJ;Lshapeless/$colon$colon<TK;Lshapeless/HNil;>;>;>;>;>;>;>;>;>;>;>;>;)Lscala/Function11<TA;TB;TC;TD;TE;TF;TG;TH;TI;TJ;TK;Ljava/lang/Object;>;
    MethodParameters:
      Name                           Flags
      fn                             final
      cse                            final

  public <A extends java.lang.Object, B extends java.lang.Object, C extends java.lang.Object, D extends java.lang.Object, E extends java.lang.Object, F extends java.lang.Object, G extends java.lang.Object, H extends java.lang.Object, I extends java.lang.Object, J extends java.lang.Object, K extends java.lang.Object, L extends java.lang.Object> scala.Function12<A, B, C, D, E, F, G, H, I, J, K, L, java.lang.Object> inst12(shapeless.Poly, shapeless.PolyDefns$Case<? extends shapeless.Poly, shapeless.$colon$colon<A, shapeless.$colon$colon<B, shapeless.$colon$colon<C, shapeless.$colon$colon<D, shapeless.$colon$colon<E, shapeless.$colon$colon<F, shapeless.$colon$colon<G, shapeless.$colon$colon<H, shapeless.$colon$colon<I, shapeless.$colon$colon<J, shapeless.$colon$colon<K, shapeless.$colon$colon<L, shapeless.HNil>>>>>>>>>>>>>);
    descriptor: (Lshapeless/Poly;Lshapeless/PolyDefns$Case;)Lscala/Function12;
    flags: (0x0001) ACC_PUBLIC
    Code:
      stack=3, locals=3, args_size=3
         0: aload_0
         1: aload_1
         2: aload_2
         3: invokestatic  #116                // InterfaceMethod shapeless/PolyInst.inst12$:(Lshapeless/PolyInst;Lshapeless/Poly;Lshapeless/PolyDefns$Case;)Lscala/Function12;
         6: areturn
      LineNumberTable:
        line 247: 0
      LocalVariableTable:
        Start  Length  Slot  Name   Signature
            0       7     0  this   Lshapeless/Poly$;
            0       7     1    fn   Lshapeless/Poly;
            0       7     2   cse   Lshapeless/PolyDefns$Case;
    Signature: #112                         // <A:Ljava/lang/Object;B:Ljava/lang/Object;C:Ljava/lang/Object;D:Ljava/lang/Object;E:Ljava/lang/Object;F:Ljava/lang/Object;G:Ljava/lang/Object;H:Ljava/lang/Object;I:Ljava/lang/Object;J:Ljava/lang/Object;K:Ljava/lang/Object;L:Ljava/lang/Object;>(Lshapeless/Poly;Lshapeless/PolyDefns$Case<+Lshapeless/Poly;Lshapeless/$colon$colon<TA;Lshapeless/$colon$colon<TB;Lshapeless/$colon$colon<TC;Lshapeless/$colon$colon<TD;Lshapeless/$colon$colon<TE;Lshapeless/$colon$colon<TF;Lshapeless/$colon$colon<TG;Lshapeless/$colon$colon<TH;Lshapeless/$colon$colon<TI;Lshapeless/$colon$colon<TJ;Lshapeless/$colon$colon<TK;Lshapeless/$colon$colon<TL;Lshapeless/HNil;>;>;>;>;>;>;>;>;>;>;>;>;>;)Lscala/Function12<TA;TB;TC;TD;TE;TF;TG;TH;TI;TJ;TK;TL;Ljava/lang/Object;>;
    MethodParameters:
      Name                           Flags
      fn                             final
      cse                            final

  public <A extends java.lang.Object, B extends java.lang.Object, C extends java.lang.Object, D extends java.lang.Object, E extends java.lang.Object, F extends java.lang.Object, G extends java.lang.Object, H extends java.lang.Object, I extends java.lang.Object, J extends java.lang.Object, K extends java.lang.Object, L extends java.lang.Object, M extends java.lang.Object> scala.Function13<A, B, C, D, E, F, G, H, I, J, K, L, M, java.lang.Object> inst13(shapeless.Poly, shapeless.PolyDefns$Case<? extends shapeless.Poly, shapeless.$colon$colon<A, shapeless.$colon$colon<B, shapeless.$colon$colon<C, shapeless.$colon$colon<D, shapeless.$colon$colon<E, shapeless.$colon$colon<F, shapeless.$colon$colon<G, shapeless.$colon$colon<H, shapeless.$colon$colon<I, shapeless.$colon$colon<J, shapeless.$colon$colon<K, shapeless.$colon$colon<L, shapeless.$colon$colon<M, shapeless.HNil>>>>>>>>>>>>>>);
    descriptor: (Lshapeless/Poly;Lshapeless/PolyDefns$Case;)Lscala/Function13;
    flags: (0x0001) ACC_PUBLIC
    Code:
      stack=3, locals=3, args_size=3
         0: aload_0
         1: aload_1
         2: aload_2
         3: invokestatic  #123                // InterfaceMethod shapeless/PolyInst.inst13$:(Lshapeless/PolyInst;Lshapeless/Poly;Lshapeless/PolyDefns$Case;)Lscala/Function13;
         6: areturn
      LineNumberTable:
        line 247: 0
      LocalVariableTable:
        Start  Length  Slot  Name   Signature
            0       7     0  this   Lshapeless/Poly$;
            0       7     1    fn   Lshapeless/Poly;
            0       7     2   cse   Lshapeless/PolyDefns$Case;
    Signature: #119                         // <A:Ljava/lang/Object;B:Ljava/lang/Object;C:Ljava/lang/Object;D:Ljava/lang/Object;E:Ljava/lang/Object;F:Ljava/lang/Object;G:Ljava/lang/Object;H:Ljava/lang/Object;I:Ljava/lang/Object;J:Ljava/lang/Object;K:Ljava/lang/Object;L:Ljava/lang/Object;M:Ljava/lang/Object;>(Lshapeless/Poly;Lshapeless/PolyDefns$Case<+Lshapeless/Poly;Lshapeless/$colon$colon<TA;Lshapeless/$colon$colon<TB;Lshapeless/$colon$colon<TC;Lshapeless/$colon$colon<TD;Lshapeless/$colon$colon<TE;Lshapeless/$colon$colon<TF;Lshapeless/$colon$colon<TG;Lshapeless/$colon$colon<TH;Lshapeless/$colon$colon<TI;Lshapeless/$colon$colon<TJ;Lshapeless/$colon$colon<TK;Lshapeless/$colon$colon<TL;Lshapeless/$colon$colon<TM;Lshapeless/HNil;>;>;>;>;>;>;>;>;>;>;>;>;>;>;)Lscala/Function13<TA;TB;TC;TD;TE;TF;TG;TH;TI;TJ;TK;TL;TM;Ljava/lang/Object;>;
    MethodParameters:
      Name                           Flags
      fn                             final
      cse                            final

  public <A extends java.lang.Object, B extends java.lang.Object, C extends java.lang.Object, D extends java.lang.Object, E extends java.lang.Object, F extends java.lang.Object, G extends java.lang.Object, H extends java.lang.Object, I extends java.lang.Object, J extends java.lang.Object, K extends java.lang.Object, L extends java.lang.Object, M extends java.lang.Object, N extends java.lang.Object> scala.Function14<A, B, C, D, E, F, G, H, I, J, K, L, M, N, java.lang.Object> inst14(shapeless.Poly, shapeless.PolyDefns$Case<? extends shapeless.Poly, shapeless.$colon$colon<A, shapeless.$colon$colon<B, shapeless.$colon$colon<C, shapeless.$colon$colon<D, shapeless.$colon$colon<E, shapeless.$colon$colon<F, shapeless.$colon$colon<G, shapeless.$colon$colon<H, shapeless.$colon$colon<I, shapeless.$colon$colon<J, shapeless.$colon$colon<K, shapeless.$colon$colon<L, shapeless.$colon$colon<M, shapeless.$colon$colon<N, shapeless.HNil>>>>>>>>>>>>>>>);
    descriptor: (Lshapeless/Poly;Lshapeless/PolyDefns$Case;)Lscala/Function14;
    flags: (0x0001) ACC_PUBLIC
    Code:
      stack=3, locals=3, args_size=3
         0: aload_0
         1: aload_1
         2: aload_2
         3: invokestatic  #130                // InterfaceMethod shapeless/PolyInst.inst14$:(Lshapeless/PolyInst;Lshapeless/Poly;Lshapeless/PolyDefns$Case;)Lscala/Function14;
         6: areturn
      LineNumberTable:
        line 247: 0
      LocalVariableTable:
        Start  Length  Slot  Name   Signature
            0       7     0  this   Lshapeless/Poly$;
            0       7     1    fn   Lshapeless/Poly;
            0       7     2   cse   Lshapeless/PolyDefns$Case;
    Signature: #126                         // <A:Ljava/lang/Object;B:Ljava/lang/Object;C:Ljava/lang/Object;D:Ljava/lang/Object;E:Ljava/lang/Object;F:Ljava/lang/Object;G:Ljava/lang/Object;H:Ljava/lang/Object;I:Ljava/lang/Object;J:Ljava/lang/Object;K:Ljava/lang/Object;L:Ljava/lang/Object;M:Ljava/lang/Object;N:Ljava/lang/Object;>(Lshapeless/Poly;Lshapeless/PolyDefns$Case<+Lshapeless/Poly;Lshapeless/$colon$colon<TA;Lshapeless/$colon$colon<TB;Lshapeless/$colon$colon<TC;Lshapeless/$colon$colon<TD;Lshapeless/$colon$colon<TE;Lshapeless/$colon$colon<TF;Lshapeless/$colon$colon<TG;Lshapeless/$colon$colon<TH;Lshapeless/$colon$colon<TI;Lshapeless/$colon$colon<TJ;Lshapeless/$colon$colon<TK;Lshapeless/$colon$colon<TL;Lshapeless/$colon$colon<TM;Lshapeless/$colon$colon<TN;Lshapeless/HNil;>;>;>;>;>;>;>;>;>;>;>;>;>;>;>;)Lscala/Function14<TA;TB;TC;TD;TE;TF;TG;TH;TI;TJ;TK;TL;TM;TN;Ljava/lang/Object;>;
    MethodParameters:
      Name                           Flags
      fn                             final
      cse                            final

  public <A extends java.lang.Object, B extends java.lang.Object, C extends java.lang.Object, D extends java.lang.Object, E extends java.lang.Object, F extends java.lang.Object, G extends java.lang.Object, H extends java.lang.Object, I extends java.lang.Object, J extends java.lang.Object, K extends java.lang.Object, L extends java.lang.Object, M extends java.lang.Object, N extends java.lang.Object, O extends java.lang.Object> scala.Function15<A, B, C, D, E, F, G, H, I, J, K, L, M, N, O, java.lang.Object> inst15(shapeless.Poly, shapeless.PolyDefns$Case<? extends shapeless.Poly, shapeless.$colon$colon<A, shapeless.$colon$colon<B, shapeless.$colon$colon<C, shapeless.$colon$colon<D, shapeless.$colon$colon<E, shapeless.$colon$colon<F, shapeless.$colon$colon<G, shapeless.$colon$colon<H, shapeless.$colon$colon<I, shapeless.$colon$colon<J, shapeless.$colon$colon<K, shapeless.$colon$colon<L, shapeless.$colon$colon<M, shapeless.$colon$colon<N, shapeless.$colon$colon<O, shapeless.HNil>>>>>>>>>>>>>>>>);
    descriptor: (Lshapeless/Poly;Lshapeless/PolyDefns$Case;)Lscala/Function15;
    flags: (0x0001) ACC_PUBLIC
    Code:
      stack=3, locals=3, args_size=3
         0: aload_0
         1: aload_1
         2: aload_2
         3: invokestatic  #137                // InterfaceMethod shapeless/PolyInst.inst15$:(Lshapeless/PolyInst;Lshapeless/Poly;Lshapeless/PolyDefns$Case;)Lscala/Function15;
         6: areturn
      LineNumberTable:
        line 247: 0
      LocalVariableTable:
        Start  Length  Slot  Name   Signature
            0       7     0  this   Lshapeless/Poly$;
            0       7     1    fn   Lshapeless/Poly;
            0       7     2   cse   Lshapeless/PolyDefns$Case;
    Signature: #133                         // <A:Ljava/lang/Object;B:Ljava/lang/Object;C:Ljava/lang/Object;D:Ljava/lang/Object;E:Ljava/lang/Object;F:Ljava/lang/Object;G:Ljava/lang/Object;H:Ljava/lang/Object;I:Ljava/lang/Object;J:Ljava/lang/Object;K:Ljava/lang/Object;L:Ljava/lang/Object;M:Ljava/lang/Object;N:Ljava/lang/Object;O:Ljava/lang/Object;>(Lshapeless/Poly;Lshapeless/PolyDefns$Case<+Lshapeless/Poly;Lshapeless/$colon$colon<TA;Lshapeless/$colon$colon<TB;Lshapeless/$colon$colon<TC;Lshapeless/$colon$colon<TD;Lshapeless/$colon$colon<TE;Lshapeless/$colon$colon<TF;Lshapeless/$colon$colon<TG;Lshapeless/$colon$colon<TH;Lshapeless/$colon$colon<TI;Lshapeless/$colon$colon<TJ;Lshapeless/$colon$colon<TK;Lshapeless/$colon$colon<TL;Lshapeless/$colon$colon<TM;Lshapeless/$colon$colon<TN;Lshapeless/$colon$colon<TO;Lshapeless/HNil;>;>;>;>;>;>;>;>;>;>;>;>;>;>;>;>;)Lscala/Function15<TA;TB;TC;TD;TE;TF;TG;TH;TI;TJ;TK;TL;TM;TN;TO;Ljava/lang/Object;>;
    MethodParameters:
      Name                           Flags
      fn                             final
      cse                            final

  public <A extends java.lang.Object, B extends java.lang.Object, C extends java.lang.Object, D extends java.lang.Object, E extends java.lang.Object, F extends java.lang.Object, G extends java.lang.Object, H extends java.lang.Object, I extends java.lang.Object, J extends java.lang.Object, K extends java.lang.Object, L extends java.lang.Object, M extends java.lang.Object, N extends java.lang.Object, O extends java.lang.Object, P extends java.lang.Object> scala.Function16<A, B, C, D, E, F, G, H, I, J, K, L, M, N, O, P, java.lang.Object> inst16(shapeless.Poly, shapeless.PolyDefns$Case<? extends shapeless.Poly, shapeless.$colon$colon<A, shapeless.$colon$colon<B, shapeless.$colon$colon<C, shapeless.$colon$colon<D, shapeless.$colon$colon<E, shapeless.$colon$colon<F, shapeless.$colon$colon<G, shapeless.$colon$colon<H, shapeless.$colon$colon<I, shapeless.$colon$colon<J, shapeless.$colon$colon<K, shapeless.$colon$colon<L, shapeless.$colon$colon<M, shapeless.$colon$colon<N, shapeless.$colon$colon<O, shapeless.$colon$colon<P, shapeless.HNil>>>>>>>>>>>>>>>>>);
    descriptor: (Lshapeless/Poly;Lshapeless/PolyDefns$Case;)Lscala/Function16;
    flags: (0x0001) ACC_PUBLIC
    Code:
      stack=3, locals=3, args_size=3
         0: aload_0
         1: aload_1
         2: aload_2
         3: invokestatic  #144                // InterfaceMethod shapeless/PolyInst.inst16$:(Lshapeless/PolyInst;Lshapeless/Poly;Lshapeless/PolyDefns$Case;)Lscala/Function16;
         6: areturn
      LineNumberTable:
        line 247: 0
      LocalVariableTable:
        Start  Length  Slot  Name   Signature
            0       7     0  this   Lshapeless/Poly$;
            0       7     1    fn   Lshapeless/Poly;
            0       7     2   cse   Lshapeless/PolyDefns$Case;
    Signature: #140                         // <A:Ljava/lang/Object;B:Ljava/lang/Object;C:Ljava/lang/Object;D:Ljava/lang/Object;E:Ljava/lang/Object;F:Ljava/lang/Object;G:Ljava/lang/Object;H:Ljava/lang/Object;I:Ljava/lang/Object;J:Ljava/lang/Object;K:Ljava/lang/Object;L:Ljava/lang/Object;M:Ljava/lang/Object;N:Ljava/lang/Object;O:Ljava/lang/Object;P:Ljava/lang/Object;>(Lshapeless/Poly;Lshapeless/PolyDefns$Case<+Lshapeless/Poly;Lshapeless/$colon$colon<TA;Lshapeless/$colon$colon<TB;Lshapeless/$colon$colon<TC;Lshapeless/$colon$colon<TD;Lshapeless/$colon$colon<TE;Lshapeless/$colon$colon<TF;Lshapeless/$colon$colon<TG;Lshapeless/$colon$colon<TH;Lshapeless/$colon$colon<TI;Lshapeless/$colon$colon<TJ;Lshapeless/$colon$colon<TK;Lshapeless/$colon$colon<TL;Lshapeless/$colon$colon<TM;Lshapeless/$colon$colon<TN;Lshapeless/$colon$colon<TO;Lshapeless/$colon$colon<TP;Lshapeless/HNil;>;>;>;>;>;>;>;>;>;>;>;>;>;>;>;>;>;)Lscala/Function16<TA;TB;TC;TD;TE;TF;TG;TH;TI;TJ;TK;TL;TM;TN;TO;TP;Ljava/lang/Object;>;
    MethodParameters:
      Name                           Flags
      fn                             final
      cse                            final

  public <A extends java.lang.Object, B extends java.lang.Object, C extends java.lang.Object, D extends java.lang.Object, E extends java.lang.Object, F extends java.lang.Object, G extends java.lang.Object, H extends java.lang.Object, I extends java.lang.Object, J extends java.lang.Object, K extends java.lang.Object, L extends java.lang.Object, M extends java.lang.Object, N extends java.lang.Object, O extends java.lang.Object, P extends java.lang.Object, Q extends java.lang.Object> scala.Function17<A, B, C, D, E, F, G, H, I, J, K, L, M, N, O, P, Q, java.lang.Object> inst17(shapeless.Poly, shapeless.PolyDefns$Case<? extends shapeless.Poly, shapeless.$colon$colon<A, shapeless.$colon$colon<B, shapeless.$colon$colon<C, shapeless.$colon$colon<D, shapeless.$colon$colon<E, shapeless.$colon$colon<F, shapeless.$colon$colon<G, shapeless.$colon$colon<H, shapeless.$colon$colon<I, shapeless.$colon$colon<J, shapeless.$colon$colon<K, shapeless.$colon$colon<L, shapeless.$colon$colon<M, shapeless.$colon$colon<N, shapeless.$colon$colon<O, shapeless.$colon$colon<P, shapeless.$colon$colon<Q, shapeless.HNil>>>>>>>>>>>>>>>>>>);
    descriptor: (Lshapeless/Poly;Lshapeless/PolyDefns$Case;)Lscala/Function17;
    flags: (0x0001) ACC_PUBLIC
    Code:
      stack=3, locals=3, args_size=3
         0: aload_0
         1: aload_1
         2: aload_2
         3: invokestatic  #151                // InterfaceMethod shapeless/PolyInst.inst17$:(Lshapeless/PolyInst;Lshapeless/Poly;Lshapeless/PolyDefns$Case;)Lscala/Function17;
         6: areturn
      LineNumberTable:
        line 247: 0
      LocalVariableTable:
        Start  Length  Slot  Name   Signature
            0       7     0  this   Lshapeless/Poly$;
            0       7     1    fn   Lshapeless/Poly;
            0       7     2   cse   Lshapeless/PolyDefns$Case;
    Signature: #147                         // <A:Ljava/lang/Object;B:Ljava/lang/Object;C:Ljava/lang/Object;D:Ljava/lang/Object;E:Ljava/lang/Object;F:Ljava/lang/Object;G:Ljava/lang/Object;H:Ljava/lang/Object;I:Ljava/lang/Object;J:Ljava/lang/Object;K:Ljava/lang/Object;L:Ljava/lang/Object;M:Ljava/lang/Object;N:Ljava/lang/Object;O:Ljava/lang/Object;P:Ljava/lang/Object;Q:Ljava/lang/Object;>(Lshapeless/Poly;Lshapeless/PolyDefns$Case<+Lshapeless/Poly;Lshapeless/$colon$colon<TA;Lshapeless/$colon$colon<TB;Lshapeless/$colon$colon<TC;Lshapeless/$colon$colon<TD;Lshapeless/$colon$colon<TE;Lshapeless/$colon$colon<TF;Lshapeless/$colon$colon<TG;Lshapeless/$colon$colon<TH;Lshapeless/$colon$colon<TI;Lshapeless/$colon$colon<TJ;Lshapeless/$colon$colon<TK;Lshapeless/$colon$colon<TL;Lshapeless/$colon$colon<TM;Lshapeless/$colon$colon<TN;Lshapeless/$colon$colon<TO;Lshapeless/$colon$colon<TP;Lshapeless/$colon$colon<TQ;Lshapeless/HNil;>;>;>;>;>;>;>;>;>;>;>;>;>;>;>;>;>;>;)Lscala/Function17<TA;TB;TC;TD;TE;TF;TG;TH;TI;TJ;TK;TL;TM;TN;TO;TP;TQ;Ljava/lang/Object;>;
    MethodParameters:
      Name                           Flags
      fn                             final
      cse                            final

  public <A extends java.lang.Object, B extends java.lang.Object, C extends java.lang.Object, D extends java.lang.Object, E extends java.lang.Object, F extends java.lang.Object, G extends java.lang.Object, H extends java.lang.Object, I extends java.lang.Object, J extends java.lang.Object, K extends java.lang.Object, L extends java.lang.Object, M extends java.lang.Object, N extends java.lang.Object, O extends java.lang.Object, P extends java.lang.Object, Q extends java.lang.Object, R extends java.lang.Object> scala.Function18<A, B, C, D, E, F, G, H, I, J, K, L, M, N, O, P, Q, R, java.lang.Object> inst18(shapeless.Poly, shapeless.PolyDefns$Case<? extends shapeless.Poly, shapeless.$colon$colon<A, shapeless.$colon$colon<B, shapeless.$colon$colon<C, shapeless.$colon$colon<D, shapeless.$colon$colon<E, shapeless.$colon$colon<F, shapeless.$colon$colon<G, shapeless.$colon$colon<H, shapeless.$colon$colon<I, shapeless.$colon$colon<J, shapeless.$colon$colon<K, shapeless.$colon$colon<L, shapeless.$colon$colon<M, shapeless.$colon$colon<N, shapeless.$colon$colon<O, shapeless.$colon$colon<P, shapeless.$colon$colon<Q, shapeless.$colon$colon<R, shapeless.HNil>>>>>>>>>>>>>>>>>>>);
    descriptor: (Lshapeless/Poly;Lshapeless/PolyDefns$Case;)Lscala/Function18;
    flags: (0x0001) ACC_PUBLIC
    Code:
      stack=3, locals=3, args_size=3
         0: aload_0
         1: aload_1
         2: aload_2
         3: invokestatic  #158                // InterfaceMethod shapeless/PolyInst.inst18$:(Lshapeless/PolyInst;Lshapeless/Poly;Lshapeless/PolyDefns$Case;)Lscala/Function18;
         6: areturn
      LineNumberTable:
        line 247: 0
      LocalVariableTable:
        Start  Length  Slot  Name   Signature
            0       7     0  this   Lshapeless/Poly$;
            0       7     1    fn   Lshapeless/Poly;
            0       7     2   cse   Lshapeless/PolyDefns$Case;
    Signature: #154                         // <A:Ljava/lang/Object;B:Ljava/lang/Object;C:Ljava/lang/Object;D:Ljava/lang/Object;E:Ljava/lang/Object;F:Ljava/lang/Object;G:Ljava/lang/Object;H:Ljava/lang/Object;I:Ljava/lang/Object;J:Ljava/lang/Object;K:Ljava/lang/Object;L:Ljava/lang/Object;M:Ljava/lang/Object;N:Ljava/lang/Object;O:Ljava/lang/Object;P:Ljava/lang/Object;Q:Ljava/lang/Object;R:Ljava/lang/Object;>(Lshapeless/Poly;Lshapeless/PolyDefns$Case<+Lshapeless/Poly;Lshapeless/$colon$colon<TA;Lshapeless/$colon$colon<TB;Lshapeless/$colon$colon<TC;Lshapeless/$colon$colon<TD;Lshapeless/$colon$colon<TE;Lshapeless/$colon$colon<TF;Lshapeless/$colon$colon<TG;Lshapeless/$colon$colon<TH;Lshapeless/$colon$colon<TI;Lshapeless/$colon$colon<TJ;Lshapeless/$colon$colon<TK;Lshapeless/$colon$colon<TL;Lshapeless/$colon$colon<TM;Lshapeless/$colon$colon<TN;Lshapeless/$colon$colon<TO;Lshapeless/$colon$colon<TP;Lshapeless/$colon$colon<TQ;Lshapeless/$colon$colon<TR;Lshapeless/HNil;>;>;>;>;>;>;>;>;>;>;>;>;>;>;>;>;>;>;>;)Lscala/Function18<TA;TB;TC;TD;TE;TF;TG;TH;TI;TJ;TK;TL;TM;TN;TO;TP;TQ;TR;Ljava/lang/Object;>;
    MethodParameters:
      Name                           Flags
      fn                             final
      cse                            final

  public <A extends java.lang.Object, B extends java.lang.Object, C extends java.lang.Object, D extends java.lang.Object, E extends java.lang.Object, F extends java.lang.Object, G extends java.lang.Object, H extends java.lang.Object, I extends java.lang.Object, J extends java.lang.Object, K extends java.lang.Object, L extends java.lang.Object, M extends java.lang.Object, N extends java.lang.Object, O extends java.lang.Object, P extends java.lang.Object, Q extends java.lang.Object, R extends java.lang.Object, S extends java.lang.Object> scala.Function19<A, B, C, D, E, F, G, H, I, J, K, L, M, N, O, P, Q, R, S, java.lang.Object> inst19(shapeless.Poly, shapeless.PolyDefns$Case<? extends shapeless.Poly, shapeless.$colon$colon<A, shapeless.$colon$colon<B, shapeless.$colon$colon<C, shapeless.$colon$colon<D, shapeless.$colon$colon<E, shapeless.$colon$colon<F, shapeless.$colon$colon<G, shapeless.$colon$colon<H, shapeless.$colon$colon<I, shapeless.$colon$colon<J, shapeless.$colon$colon<K, shapeless.$colon$colon<L, shapeless.$colon$colon<M, shapeless.$colon$colon<N, shapeless.$colon$colon<O, shapeless.$colon$colon<P, shapeless.$colon$colon<Q, shapeless.$colon$colon<R, shapeless.$colon$colon<S, shapeless.HNil>>>>>>>>>>>>>>>>>>>>);
    descriptor: (Lshapeless/Poly;Lshapeless/PolyDefns$Case;)Lscala/Function19;
    flags: (0x0001) ACC_PUBLIC
    Code:
      stack=3, locals=3, args_size=3
         0: aload_0
         1: aload_1
         2: aload_2
         3: invokestatic  #165                // InterfaceMethod shapeless/PolyInst.inst19$:(Lshapeless/PolyInst;Lshapeless/Poly;Lshapeless/PolyDefns$Case;)Lscala/Function19;
         6: areturn
      LineNumberTable:
        line 247: 0
      LocalVariableTable:
        Start  Length  Slot  Name   Signature
            0       7     0  this   Lshapeless/Poly$;
            0       7     1    fn   Lshapeless/Poly;
            0       7     2   cse   Lshapeless/PolyDefns$Case;
    Signature: #161                         // <A:Ljava/lang/Object;B:Ljava/lang/Object;C:Ljava/lang/Object;D:Ljava/lang/Object;E:Ljava/lang/Object;F:Ljava/lang/Object;G:Ljava/lang/Object;H:Ljava/lang/Object;I:Ljava/lang/Object;J:Ljava/lang/Object;K:Ljava/lang/Object;L:Ljava/lang/Object;M:Ljava/lang/Object;N:Ljava/lang/Object;O:Ljava/lang/Object;P:Ljava/lang/Object;Q:Ljava/lang/Object;R:Ljava/lang/Object;S:Ljava/lang/Object;>(Lshapeless/Poly;Lshapeless/PolyDefns$Case<+Lshapeless/Poly;Lshapeless/$colon$colon<TA;Lshapeless/$colon$colon<TB;Lshapeless/$colon$colon<TC;Lshapeless/$colon$colon<TD;Lshapeless/$colon$colon<TE;Lshapeless/$colon$colon<TF;Lshapeless/$colon$colon<TG;Lshapeless/$colon$colon<TH;Lshapeless/$colon$colon<TI;Lshapeless/$colon$colon<TJ;Lshapeless/$colon$colon<TK;Lshapeless/$colon$colon<TL;Lshapeless/$colon$colon<TM;Lshapeless/$colon$colon<TN;Lshapeless/$colon$colon<TO;Lshapeless/$colon$colon<TP;Lshapeless/$colon$colon<TQ;Lshapeless/$colon$colon<TR;Lshapeless/$colon$colon<TS;Lshapeless/HNil;>;>;>;>;>;>;>;>;>;>;>;>;>;>;>;>;>;>;>;>;)Lscala/Function19<TA;TB;TC;TD;TE;TF;TG;TH;TI;TJ;TK;TL;TM;TN;TO;TP;TQ;TR;TS;Ljava/lang/Object;>;
    MethodParameters:
      Name                           Flags
      fn                             final
      cse                            final

  public <A extends java.lang.Object, B extends java.lang.Object, C extends java.lang.Object, D extends java.lang.Object, E extends java.lang.Object, F extends java.lang.Object, G extends java.lang.Object, H extends java.lang.Object, I extends java.lang.Object, J extends java.lang.Object, K extends java.lang.Object, L extends java.lang.Object, M extends java.lang.Object, N extends java.lang.Object, O extends java.lang.Object, P extends java.lang.Object, Q extends java.lang.Object, R extends java.lang.Object, S extends java.lang.Object, T extends java.lang.Object> scala.Function20<A, B, C, D, E, F, G, H, I, J, K, L, M, N, O, P, Q, R, S, T, java.lang.Object> inst20(shapeless.Poly, shapeless.PolyDefns$Case<? extends shapeless.Poly, shapeless.$colon$colon<A, shapeless.$colon$colon<B, shapeless.$colon$colon<C, shapeless.$colon$colon<D, shapeless.$colon$colon<E, shapeless.$colon$colon<F, shapeless.$colon$colon<G, shapeless.$colon$colon<H, shapeless.$colon$colon<I, shapeless.$colon$colon<J, shapeless.$colon$colon<K, shapeless.$colon$colon<L, shapeless.$colon$colon<M, shapeless.$colon$colon<N, shapeless.$colon$colon<O, shapeless.$colon$colon<P, shapeless.$colon$colon<Q, shapeless.$colon$colon<R, shapeless.$colon$colon<S, shapeless.$colon$colon<T, shapeless.HNil>>>>>>>>>>>>>>>>>>>>>);
    descriptor: (Lshapeless/Poly;Lshapeless/PolyDefns$Case;)Lscala/Function20;
    flags: (0x0001) ACC_PUBLIC
    Code:
      stack=3, locals=3, args_size=3
         0: aload_0
         1: aload_1
         2: aload_2
         3: invokestatic  #172                // InterfaceMethod shapeless/PolyInst.inst20$:(Lshapeless/PolyInst;Lshapeless/Poly;Lshapeless/PolyDefns$Case;)Lscala/Function20;
         6: areturn
      LineNumberTable:
        line 247: 0
      LocalVariableTable:
        Start  Length  Slot  Name   Signature
            0       7     0  this   Lshapeless/Poly$;
            0       7     1    fn   Lshapeless/Poly;
            0       7     2   cse   Lshapeless/PolyDefns$Case;
    Signature: #168                         // <A:Ljava/lang/Object;B:Ljava/lang/Object;C:Ljava/lang/Object;D:Ljava/lang/Object;E:Ljava/lang/Object;F:Ljava/lang/Object;G:Ljava/lang/Object;H:Ljava/lang/Object;I:Ljava/lang/Object;J:Ljava/lang/Object;K:Ljava/lang/Object;L:Ljava/lang/Object;M:Ljava/lang/Object;N:Ljava/lang/Object;O:Ljava/lang/Object;P:Ljava/lang/Object;Q:Ljava/lang/Object;R:Ljava/lang/Object;S:Ljava/lang/Object;T:Ljava/lang/Object;>(Lshapeless/Poly;Lshapeless/PolyDefns$Case<+Lshapeless/Poly;Lshapeless/$colon$colon<TA;Lshapeless/$colon$colon<TB;Lshapeless/$colon$colon<TC;Lshapeless/$colon$colon<TD;Lshapeless/$colon$colon<TE;Lshapeless/$colon$colon<TF;Lshapeless/$colon$colon<TG;Lshapeless/$colon$colon<TH;Lshapeless/$colon$colon<TI;Lshapeless/$colon$colon<TJ;Lshapeless/$colon$colon<TK;Lshapeless/$colon$colon<TL;Lshapeless/$colon$colon<TM;Lshapeless/$colon$colon<TN;Lshapeless/$colon$colon<TO;Lshapeless/$colon$colon<TP;Lshapeless/$colon$colon<TQ;Lshapeless/$colon$colon<TR;Lshapeless/$colon$colon<TS;Lshapeless/$colon$colon<TT;Lshapeless/HNil;>;>;>;>;>;>;>;>;>;>;>;>;>;>;>;>;>;>;>;>;>;)Lscala/Function20<TA;TB;TC;TD;TE;TF;TG;TH;TI;TJ;TK;TL;TM;TN;TO;TP;TQ;TR;TS;TT;Ljava/lang/Object;>;
    MethodParameters:
      Name                           Flags
      fn                             final
      cse                            final

  public <A extends java.lang.Object, B extends java.lang.Object, C extends java.lang.Object, D extends java.lang.Object, E extends java.lang.Object, F extends java.lang.Object, G extends java.lang.Object, H extends java.lang.Object, I extends java.lang.Object, J extends java.lang.Object, K extends java.lang.Object, L extends java.lang.Object, M extends java.lang.Object, N extends java.lang.Object, O extends java.lang.Object, P extends java.lang.Object, Q extends java.lang.Object, R extends java.lang.Object, S extends java.lang.Object, T extends java.lang.Object, U extends java.lang.Object> scala.Function21<A, B, C, D, E, F, G, H, I, J, K, L, M, N, O, P, Q, R, S, T, U, java.lang.Object> inst21(shapeless.Poly, shapeless.PolyDefns$Case<? extends shapeless.Poly, shapeless.$colon$colon<A, shapeless.$colon$colon<B, shapeless.$colon$colon<C, shapeless.$colon$colon<D, shapeless.$colon$colon<E, shapeless.$colon$colon<F, shapeless.$colon$colon<G, shapeless.$colon$colon<H, shapeless.$colon$colon<I, shapeless.$colon$colon<J, shapeless.$colon$colon<K, shapeless.$colon$colon<L, shapeless.$colon$colon<M, shapeless.$colon$colon<N, shapeless.$colon$colon<O, shapeless.$colon$colon<P, shapeless.$colon$colon<Q, shapeless.$colon$colon<R, shapeless.$colon$colon<S, shapeless.$colon$colon<T, shapeless.$colon$colon<U, shapeless.HNil>>>>>>>>>>>>>>>>>>>>>>);
    descriptor: (Lshapeless/Poly;Lshapeless/PolyDefns$Case;)Lscala/Function21;
    flags: (0x0001) ACC_PUBLIC
    Code:
      stack=3, locals=3, args_size=3
         0: aload_0
         1: aload_1
         2: aload_2
         3: invokestatic  #179                // InterfaceMethod shapeless/PolyInst.inst21$:(Lshapeless/PolyInst;Lshapeless/Poly;Lshapeless/PolyDefns$Case;)Lscala/Function21;
         6: areturn
      LineNumberTable:
        line 247: 0
      LocalVariableTable:
        Start  Length  Slot  Name   Signature
            0       7     0  this   Lshapeless/Poly$;
            0       7     1    fn   Lshapeless/Poly;
            0       7     2   cse   Lshapeless/PolyDefns$Case;
    Signature: #175                         // <A:Ljava/lang/Object;B:Ljava/lang/Object;C:Ljava/lang/Object;D:Ljava/lang/Object;E:Ljava/lang/Object;F:Ljava/lang/Object;G:Ljava/lang/Object;H:Ljava/lang/Object;I:Ljava/lang/Object;J:Ljava/lang/Object;K:Ljava/lang/Object;L:Ljava/lang/Object;M:Ljava/lang/Object;N:Ljava/lang/Object;O:Ljava/lang/Object;P:Ljava/lang/Object;Q:Ljava/lang/Object;R:Ljava/lang/Object;S:Ljava/lang/Object;T:Ljava/lang/Object;U:Ljava/lang/Object;>(Lshapeless/Poly;Lshapeless/PolyDefns$Case<+Lshapeless/Poly;Lshapeless/$colon$colon<TA;Lshapeless/$colon$colon<TB;Lshapeless/$colon$colon<TC;Lshapeless/$colon$colon<TD;Lshapeless/$colon$colon<TE;Lshapeless/$colon$colon<TF;Lshapeless/$colon$colon<TG;Lshapeless/$colon$colon<TH;Lshapeless/$colon$colon<TI;Lshapeless/$colon$colon<TJ;Lshapeless/$colon$colon<TK;Lshapeless/$colon$colon<TL;Lshapeless/$colon$colon<TM;Lshapeless/$colon$colon<TN;Lshapeless/$colon$colon<TO;Lshapeless/$colon$colon<TP;Lshapeless/$colon$colon<TQ;Lshapeless/$colon$colon<TR;Lshapeless/$colon$colon<TS;Lshapeless/$colon$colon<TT;Lshapeless/$colon$colon<TU;Lshapeless/HNil;>;>;>;>;>;>;>;>;>;>;>;>;>;>;>;>;>;>;>;>;>;>;)Lscala/Function21<TA;TB;TC;TD;TE;TF;TG;TH;TI;TJ;TK;TL;TM;TN;TO;TP;TQ;TR;TS;TT;TU;Ljava/lang/Object;>;
    MethodParameters:
      Name                           Flags
      fn                             final
      cse                            final

  public <A extends java.lang.Object, B extends java.lang.Object, C extends java.lang.Object, D extends java.lang.Object, E extends java.lang.Object, F extends java.lang.Object, G extends java.lang.Object, H extends java.lang.Object, I extends java.lang.Object, J extends java.lang.Object, K extends java.lang.Object, L extends java.lang.Object, M extends java.lang.Object, N extends java.lang.Object, O extends java.lang.Object, P extends java.lang.Object, Q extends java.lang.Object, R extends java.lang.Object, S extends java.lang.Object, T extends java.lang.Object, U extends java.lang.Object, V extends java.lang.Object> scala.Function22<A, B, C, D, E, F, G, H, I, J, K, L, M, N, O, P, Q, R, S, T, U, V, java.lang.Object> inst22(shapeless.Poly, shapeless.PolyDefns$Case<? extends shapeless.Poly, shapeless.$colon$colon<A, shapeless.$colon$colon<B, shapeless.$colon$colon<C, shapeless.$colon$colon<D, shapeless.$colon$colon<E, shapeless.$colon$colon<F, shapeless.$colon$colon<G, shapeless.$colon$colon<H, shapeless.$colon$colon<I, shapeless.$colon$colon<J, shapeless.$colon$colon<K, shapeless.$colon$colon<L, shapeless.$colon$colon<M, shapeless.$colon$colon<N, shapeless.$colon$colon<O, shapeless.$colon$colon<P, shapeless.$colon$colon<Q, shapeless.$colon$colon<R, shapeless.$colon$colon<S, shapeless.$colon$colon<T, shapeless.$colon$colon<U, shapeless.$colon$colon<V, shapeless.HNil>>>>>>>>>>>>>>>>>>>>>>>);
    descriptor: (Lshapeless/Poly;Lshapeless/PolyDefns$Case;)Lscala/Function22;
    flags: (0x0001) ACC_PUBLIC
    Code:
      stack=3, locals=3, args_size=3
         0: aload_0
         1: aload_1
         2: aload_2
         3: invokestatic  #186                // InterfaceMethod shapeless/PolyInst.inst22$:(Lshapeless/PolyInst;Lshapeless/Poly;Lshapeless/PolyDefns$Case;)Lscala/Function22;
         6: areturn
      LineNumberTable:
        line 247: 0
      LocalVariableTable:
        Start  Length  Slot  Name   Signature
            0       7     0  this   Lshapeless/Poly$;
            0       7     1    fn   Lshapeless/Poly;
            0       7     2   cse   Lshapeless/PolyDefns$Case;
    Signature: #182                         // <A:Ljava/lang/Object;B:Ljava/lang/Object;C:Ljava/lang/Object;D:Ljava/lang/Object;E:Ljava/lang/Object;F:Ljava/lang/Object;G:Ljava/lang/Object;H:Ljava/lang/Object;I:Ljava/lang/Object;J:Ljava/lang/Object;K:Ljava/lang/Object;L:Ljava/lang/Object;M:Ljava/lang/Object;N:Ljava/lang/Object;O:Ljava/lang/Object;P:Ljava/lang/Object;Q:Ljava/lang/Object;R:Ljava/lang/Object;S:Ljava/lang/Object;T:Ljava/lang/Object;U:Ljava/lang/Object;V:Ljava/lang/Object;>(Lshapeless/Poly;Lshapeless/PolyDefns$Case<+Lshapeless/Poly;Lshapeless/$colon$colon<TA;Lshapeless/$colon$colon<TB;Lshapeless/$colon$colon<TC;Lshapeless/$colon$colon<TD;Lshapeless/$colon$colon<TE;Lshapeless/$colon$colon<TF;Lshapeless/$colon$colon<TG;Lshapeless/$colon$colon<TH;Lshapeless/$colon$colon<TI;Lshapeless/$colon$colon<TJ;Lshapeless/$colon$colon<TK;Lshapeless/$colon$colon<TL;Lshapeless/$colon$colon<TM;Lshapeless/$colon$colon<TN;Lshapeless/$colon$colon<TO;Lshapeless/$colon$colon<TP;Lshapeless/$colon$colon<TQ;Lshapeless/$colon$colon<TR;Lshapeless/$colon$colon<TS;Lshapeless/$colon$colon<TT;Lshapeless/$colon$colon<TU;Lshapeless/$colon$colon<TV;Lshapeless/HNil;>;>;>;>;>;>;>;>;>;>;>;>;>;>;>;>;>;>;>;>;>;>;>;)Lscala/Function22<TA;TB;TC;TD;TE;TF;TG;TH;TI;TJ;TK;TL;TM;TN;TO;TP;TQ;TR;TS;TT;TU;TV;Ljava/lang/Object;>;
    MethodParameters:
      Name                           Flags
      fn                             final
      cse                            final

  public java.lang.Object inst0(shapeless.Poly, shapeless.PolyDefns$Case<? extends shapeless.Poly, shapeless.HNil>);
    descriptor: (Lshapeless/Poly;Lshapeless/PolyDefns$Case;)Ljava/lang/Object;
    flags: (0x0001) ACC_PUBLIC
    Code:
      stack=2, locals=4, args_size=3
         0: aload_2
         1: astore_3
         2: aload_3
         3: getstatic     #195                // Field scala/$less$colon$less$.MODULE$:Lscala/$less$colon$less$;
         6: invokevirtual #199                // Method scala/$less$colon$less$.refl:()Lscala/$eq$colon$eq;
         9: invokevirtual #203                // Method shapeless/PolyDefns$Case.apply:(Lscala/$eq$colon$eq;)Ljava/lang/Object;
        12: areturn
      LineNumberTable:
        line 248: 0
      LocalVariableTable:
        Start  Length  Slot  Name   Signature
            0      13     0  this   Lshapeless/Poly$;
            0      13     1     p   Lshapeless/Poly;
            0      13     2   cse   Lshapeless/PolyDefns$Case;
    Signature: #189                         // (Lshapeless/Poly;Lshapeless/PolyDefns$Case<+Lshapeless/Poly;Lshapeless/HNil;>;)Ljava/lang/Object;
    MethodParameters:
      Name                           Flags
      p                              final
      cse                            final

  private java.lang.Object writeReplace();
    descriptor: ()Ljava/lang/Object;
    flags: (0x0002) ACC_PRIVATE
    Code:
      stack=3, locals=1, args_size=1
         0: new           #207                // class scala/runtime/ModuleSerializationProxy
         3: dup
         4: ldc           #2                  // class shapeless/Poly$
         6: invokespecial #210                // Method scala/runtime/ModuleSerializationProxy."<init>":(Ljava/lang/Class;)V
         9: areturn
      LineNumberTable:
        line 247: 0
      LocalVariableTable:
        Start  Length  Slot  Name   Signature
            0      10     0  this   Lshapeless/Poly$;

  private shapeless.Poly$();
    descriptor: ()V
    flags: (0x0002) ACC_PRIVATE
    Code:
      stack=1, locals=1, args_size=1
         0: aload_0
         1: invokespecial #211                // Method java/lang/Object."<init>":()V
         4: return
      LineNumberTable:
        line 247: 0
      LocalVariableTable:
        Start  Length  Slot  Name   Signature
            0       5     0  this   Lshapeless/Poly$;
}
InnerClasses:
  public static abstract #14= #11 of #13; // Case=class shapeless/PolyDefns$Case of class shapeless/PolyDefns
SourceFile: "poly.scala"
  ScalaInlineInfo: length = 0x81 (unknown attribute)
   01 01 00 19 00 13 00 12 01 00 BB 00 BC 01 00 1C
   00 1D 01 00 60 00 61 01 00 67 00 68 01 00 6E 00
   6F 01 00 75 00 76 01 00 7C 00 7D 01 00 83 00 84
   01 00 8A 00 8B 01 00 91 00 92 01 00 98 00 99 01
   00 9F 00 A0 01 00 28 00 29 01 00 A6 00 A7 01 00
   AD 00 AE 01 00 B4 00 B5 01 00 2F 00 30 01 00 36
   00 37 01 00 3D 00 3E 01 00 44 00 45 01 00 4B 00
   4C 01 00 52 00 53 01 00 59 00 5A 01 00 CC 00 CD
   01
  Scala: length = 0x0 (unknown attribute)

