Classfile /Users/mw/Projects/slang-braindump/.jar/jar8/assemble/slang-braindump/assemble/content/shapeless/Poly4.class
  Last modified May 29, 2022; size 2554 bytes
  SHA-256 checksum f8ed94f5f99565220bbd7f84b970bc94b8412f4aa334543268bd2199f92982f3
  Compiled from "polyntraits.scala"
public interface shapeless.Poly4 extends shapeless.Poly
  minor version: 0
  major version: 52
  flags: (0x0601) ACC_PUBLIC, ACC_INTERFACE, ACC_ABSTRACT
  this_class: #2                          // shapeless/Poly4
  super_class: #4                         // java/lang/Object
  interfaces: 1, fields: 0, methods: 6, attributes: 5
Constant pool:
   #1 = Utf8               shapeless/Poly4
   #2 = Class              #1             // shapeless/Poly4
   #3 = Utf8               java/lang/Object
   #4 = Class              #3             // java/lang/Object
   #5 = Utf8               shapeless/Poly
   #6 = Class              #5             // shapeless/Poly
   #7 = Utf8               polyntraits.scala
   #8 = Utf8               Lscala/reflect/ScalaSignature;
   #9 = Utf8               bytes
  #10 = Utf8               \u0006\u0005\u0005-daB\t\u0013!\u0003\r\t!\u0006\u0005\u0006A\u0001!\t!I\u0003\u0005K\u0001\u0001aeB\u0003Q\u0001!\u0005\u0011KB\u0003&\u0001!\u0005!\u000bC\u0003T\t\u0011\u0005A+\u0002\u0003V\t\u00011f\u0001\u00027\u0001\u00015DQaU\u0004\u0005\u0002=DQ!_\u0004\u0005\u0002iDq!!\u0005\u0001\t\u0003\t\u0019bB\u0004\u0002*IA\t!a\u000b\u0007\rE\u0011\u0002\u0012AA\u0017\u0011\u0019\u0019F\u0002\"\u0001\u0002N!I\u0011q\n\u0007C\u0002\u0013\u0005\u0011\u0011\u000b\u0005\t\u00033b\u0001\u0015!\u0003\u0002T!I\u00111\f\u0007\u0002\u0002\u0013%\u0011Q\f\u0002\u0006!>d\u0017\u0010\u000e\u0006\u0002\'\u0005I1\u000f[1qK2,7o]\u0002\u0001\'\r\u0001a\u0003\b\t\u0003/ii\u0011\u0001\u0007\u0006\u00023\u0005)1oY1mC&\u00111\u0004\u0007\u0002\u0007\u0003:L(+\u001a4\u0011\u0005uqR\"\u0001\n\n\u0005}\u0011\"\u0001\u0002)pYf\fa\u0001J5oSR$C#\u0001\u0012\u0011\u0005]\u0019\u0013B\u0001\u0013\u0019\u0005\u0011)f.\u001b;\u0003\t\r\u000b7/Z\u000b\u0006Oa\u001aui\u0013\t\u0005Q=\u00124G\u0004\u0002*Y9\u0011QDK\u0005\u0003WI\tq\u0001]1dW\u0006<W-\u0003\u0002.]\u0005!\u0001o\u001c7z\u0015\tY##\u0003\u0002&a)\u0011\u0011GE\u0001\n!>d\u0017\u0010R3g]Nl\u0011\u0001\u0001\t\u0005;Q2\u0014)\u0003\u00026%\taAeY8m_:$3m\u001c7p]B\u0011q\u0007\u000f\u0007\u0001\t\u0015I$A1\u0001;\u0005\u0005\t\u0015CA\u001e?!\t9B(\u0003\u0002>1\t9aj\u001c;iS:<\u0007CA\f@\u0013\t\u0001\u0005DA\u0002B]f\u0004B!\b\u001bC\u000bB\u0011qg\u0011\u0003\u0006\t\n\u0011\rA\u000f\u0002\u0002\u0005B!Q\u0004\u000e$J!\t9t\tB\u0003I\u0005\t\u0007!HA\u0001D!\u0011iBGS\'\u0011\u0005]ZE!\u0002\'\u0003\u0005\u0004Q$!\u0001#\u0011\u0005uq\u0015BA(\u0013\u0005\u0011Ae*\u001b7\u0002\t\r\u000b7/\u001a\t\u0003e\u0011\u0019\"\u0001\u0002\f\u0002\rqJg.\u001b;?)\u0005\t&aA!vqV1q+\u00181dM*\u0014\"\u0001\u0017.\u0007\te#\u0001a\u0016\u0002\ryI,g-\u001b8f[\u0016tGO\u0010\t\u0005Q=\u00124\f\u0005\u0003\u001eiqs\u0006CA\u001c^\t\u0015IdA1\u0001;!\u0011iBgX1\u0011\u0005]\u0002G!\u0002#\u0007\u0005\u0004Q\u0004\u0003B\u000f5E\u0012\u0004\"aN2\u0005\u000b!3!\u0019\u0001\u001e\u0011\tu!T-\u0014\t\u0003o\u0019$Q\u0001\u0014\u0004C\u0002i*A\u0001\u001b-!S\n1!+Z:vYR\u0004\"a\u000e6\u0005\u000b-4!\u0019\u0001\u001e\u0003\u000fI+7/\u001e7ua\tY1)Y:f\u0005VLG\u000eZ3s+\u0015q\'\u000f\u001e<y\'\t9a\u0003F\u0001q!\u0019\u0011t!]:voB\u0011qG\u001d\u0003\u0006s\u001d\u0011\rA\u000f\t\u0003oQ$Q\u0001R\u0004C\u0002i\u0002\"a\u000e<\u0005\u000b!;!\u0019\u0001\u001e\u0011\u0005]BH!\u0002\'\b\u0005\u0004Q\u0014!B1qa2LXcA>\u0002\u0004Q\u0019A0a\u0002\u0013\u0005uth\u0001B-\n\u0001q\u0004bA\r\u0002rgV<X!\u00025~\u0001\u0005\u0005\u0001cA\u001c\u0002\u0004\u00111\u0011QA\u0005C\u0002i\u00121AU3t\u0011\u001d\tI!\u0003a\u0001\u0003\u0017\t!A\u001a8\u0011\u0013]\ti!]:vo\u0006\u0005\u0011bAA\b1\tIa)\u001e8di&|g\u000eN\u0001\u0003CR,\"\"!\u0006\u0002\u001c\u0005}\u00111EA\u0014+\t\t9\u0002\u0005\u00063\u000f\u0005e\u0011QDA\u0011\u0003K\u00012aNA\u000e\t\u0015I$B1\u0001;!\r9\u0014q\u0004\u0003\u0006\t*\u0011\rA\u000f\t\u0004o\u0005\rB!\u0002%\u000b\u0005\u0004Q\u0004cA\u001c\u0002(\u0011)AJ\u0003b\u0001u\u0005)\u0001k\u001c7ziA\u0011Q\u0004D\n\u0007\u0019Y\ty#!\u0010\u0011\u000b\u0005E\u0012qG\'\u000f\u0007u\t\u0019$C\u0002\u00026I\tQ\u0002U8ms:\u0013U/\u001b7eKJ\u001c\u0018\u0002BA\u001d\u0003w\u0011A\u0002U8msR\u0012U/\u001b7eKJT1!!\u000e\u0013!\u0011\ty$!\u0013\u000e\u0005\u0005\u0005#\u0002BA\"\u0003\u000b\n!![8\u000b\u0005\u0005\u001d\u0013\u0001\u00026bm\u0006LA!a\u0013\u0002B\ta1+\u001a:jC2L\'0\u00192mKR\u0011\u00111F\u0001\nMVt7\r^5p]N,\"!a\u0015\u000f\u0007u\t)&C\u0002\u0002XI\tA\u0001\u0013(jY\u0006Qa-\u001e8di&|gn\u001d\u0011\u0002\u0019]\u0014\u0018\u000e^3SKBd\u0017mY3\u0015\u0005\u0005}\u0003\u0003BA1\u0003Oj!!a\u0019\u000b\t\u0005\u0015\u0014QI\u0001\u0005Y\u0006tw-\u0003\u0003\u0002j\u0005\r$AB(cU\u0016\u001cG\u000f
  #11 = Utf8               shapeless/Poly4$Case$
  #12 = Class              #11            // shapeless/Poly4$Case$
  #13 = Utf8               Case$
  #14 = Utf8               shapeless/Poly4$CaseBuilder
  #15 = Class              #14            // shapeless/Poly4$CaseBuilder
  #16 = Utf8               CaseBuilder
  #17 = Utf8               functions
  #18 = Utf8               ()Lshapeless/HNil$;
  #19 = Utf8               shapeless/Poly4$
  #20 = Class              #19            // shapeless/Poly4$
  #21 = Utf8               MODULE$
  #22 = Utf8               Lshapeless/Poly4$;
  #23 = NameAndType        #21:#22        // MODULE$:Lshapeless/Poly4$;
  #24 = Fieldref           #20.#23        // shapeless/Poly4$.MODULE$:Lshapeless/Poly4$;
  #25 = NameAndType        #17:#18        // functions:()Lshapeless/HNil$;
  #26 = Methodref          #20.#25        // shapeless/Poly4$.functions:()Lshapeless/HNil$;
  #27 = Utf8               build
  #28 = Utf8               ()Lshapeless/Poly4;
  #29 = NameAndType        #27:#28        // build:()Lshapeless/Poly4;
  #30 = Methodref          #20.#29        // shapeless/Poly4$.build:()Lshapeless/Poly4;
  #31 = Utf8               Case
  #32 = Utf8               ()Lshapeless/Poly4$Case$;
  #33 = Utf8               at$
  #34 = Utf8               (Lshapeless/Poly4;)Lshapeless/Poly4$CaseBuilder;
  #35 = Utf8               $this
  #36 = Utf8               at
  #37 = Utf8               ()Lshapeless/Poly4$CaseBuilder;
  #38 = NameAndType        #36:#37        // at:()Lshapeless/Poly4$CaseBuilder;
  #39 = InterfaceMethodref #2.#38         // shapeless/Poly4.at:()Lshapeless/Poly4$CaseBuilder;
  #40 = Utf8               Lshapeless/Poly4;
  #41 = Utf8               <A:Ljava/lang/Object;B:Ljava/lang/Object;C:Ljava/lang/Object;D:Ljava/lang/Object;>()Lshapeless/Poly4$CaseBuilder<TA;TB;TC;TD;>;
  #42 = Utf8               <init>
  #43 = Utf8               (Lshapeless/Poly4;)V
  #44 = NameAndType        #42:#43        // "<init>":(Lshapeless/Poly4;)V
  #45 = Methodref          #15.#44        // shapeless/Poly4$CaseBuilder."<init>":(Lshapeless/Poly4;)V
  #46 = Utf8               this
  #47 = Utf8               $init$
  #48 = Utf8               Code
  #49 = Utf8               LineNumberTable
  #50 = Utf8               LocalVariableTable
  #51 = Utf8               MethodParameters
  #52 = Utf8               Signature
  #53 = Utf8               InnerClasses
  #54 = Utf8               SourceFile
  #55 = Utf8               RuntimeVisibleAnnotations
  #56 = Utf8               ScalaInlineInfo
  #57 = Utf8               ScalaSig
{
  public static shapeless.HNil$ functions();
    descriptor: ()Lshapeless/HNil$;
    flags: (0x0009) ACC_PUBLIC, ACC_STATIC
    Code:
      stack=1, locals=0, args_size=0
         0: getstatic     #24                 // Field shapeless/Poly4$.MODULE$:Lshapeless/Poly4$;
         3: invokevirtual #26                 // Method shapeless/Poly4$.functions:()Lshapeless/HNil$;
         6: areturn

  public static shapeless.Poly4 build();
    descriptor: ()Lshapeless/Poly4;
    flags: (0x0009) ACC_PUBLIC, ACC_STATIC
    Code:
      stack=1, locals=0, args_size=0
         0: getstatic     #24                 // Field shapeless/Poly4$.MODULE$:Lshapeless/Poly4$;
         3: invokevirtual #30                 // Method shapeless/Poly4$.build:()Lshapeless/Poly4;
         6: areturn

  public abstract shapeless.Poly4$Case$ Case();
    descriptor: ()Lshapeless/Poly4$Case$;
    flags: (0x0401) ACC_PUBLIC, ACC_ABSTRACT

  public static shapeless.Poly4$CaseBuilder at$(shapeless.Poly4);
    descriptor: (Lshapeless/Poly4;)Lshapeless/Poly4$CaseBuilder;
    flags: (0x1009) ACC_PUBLIC, ACC_STATIC, ACC_SYNTHETIC
    Code:
      stack=1, locals=1, args_size=1
         0: aload_0
         1: invokespecial #39                 // InterfaceMethod at:()Lshapeless/Poly4$CaseBuilder;
         4: areturn
      LineNumberTable:
        line 118: 0
      LocalVariableTable:
        Start  Length  Slot  Name   Signature
            0       5     0 $this   Lshapeless/Poly4;
    MethodParameters:
      Name                           Flags
      $this                          final synthetic

  public default <A extends java.lang.Object, B extends java.lang.Object, C extends java.lang.Object, D extends java.lang.Object> shapeless.Poly4$CaseBuilder<A, B, C, D> at();
    descriptor: ()Lshapeless/Poly4$CaseBuilder;
    flags: (0x0001) ACC_PUBLIC
    Code:
      stack=3, locals=1, args_size=1
         0: new           #15                 // class shapeless/Poly4$CaseBuilder
         3: dup
         4: aload_0
         5: invokespecial #45                 // Method shapeless/Poly4$CaseBuilder."<init>":(Lshapeless/Poly4;)V
         8: areturn
      LineNumberTable:
        line 119: 0
      LocalVariableTable:
        Start  Length  Slot  Name   Signature
            0       9     0  this   Lshapeless/Poly4;
    Signature: #41                          // <A:Ljava/lang/Object;B:Ljava/lang/Object;C:Ljava/lang/Object;D:Ljava/lang/Object;>()Lshapeless/Poly4$CaseBuilder<TA;TB;TC;TD;>;

  public static void $init$(shapeless.Poly4);
    descriptor: (Lshapeless/Poly4;)V
    flags: (0x0009) ACC_PUBLIC, ACC_STATIC
    Code:
      stack=0, locals=1, args_size=1
         0: return
      LineNumberTable:
        line 100: 0
      LocalVariableTable:
        Start  Length  Slot  Name   Signature
            0       1     0 $this   Lshapeless/Poly4;
    MethodParameters:
      Name                           Flags
      $this                          final synthetic
}
InnerClasses:
  public #13= #12 of #2;                  // Case$=class shapeless/Poly4$Case$ of class shapeless/Poly4
  public #16= #15 of #2;                  // CaseBuilder=class shapeless/Poly4$CaseBuilder of class shapeless/Poly4
SourceFile: "polyntraits.scala"
RuntimeVisibleAnnotations:
  0: #8(#9=s#10)
    scala.reflect.ScalaSignature(
      bytes="\u0006\u0005\u0005-daB\t\u0013!\u0003\r\t!\u0006\u0005\u0006A\u0001!\t!I\u0003\u0005K\u0001\u0001aeB\u0003Q\u0001!\u0005\u0011KB\u0003&\u0001!\u0005!\u000bC\u0003T\t\u0011\u0005A+\u0002\u0003V\t\u00011f\u0001\u00027\u0001\u00015DQaU\u0004\u0005\u0002=DQ!_\u0004\u0005\u0002iDq!!\u0005\u0001\t\u0003\t\u0019bB\u0004\u0002*IA\t!a\u000b\u0007\rE\u0011\u0002\u0012AA\u0017\u0011\u0019\u0019F\u0002\"\u0001\u0002N!I\u0011q\n\u0007C\u0002\u0013\u0005\u0011\u0011\u000b\u0005\t\u00033b\u0001\u0015!\u0003\u0002T!I\u00111\f\u0007\u0002\u0002\u0013%\u0011Q\f\u0002\u0006!>d\u0017\u0010\u000e\u0006\u0002\'\u0005I1\u000f[1qK2,7o]\u0002\u0001\'\r\u0001a\u0003\b\t\u0003/ii\u0011\u0001\u0007\u0006\u00023\u0005)1oY1mC&\u00111\u0004\u0007\u0002\u0007\u0003:L(+\u001a4\u0011\u0005uqR\"\u0001\n\n\u0005}\u0011\"\u0001\u0002)pYf\fa\u0001J5oSR$C#\u0001\u0012\u0011\u0005]\u0019\u0013B\u0001\u0013\u0019\u0005\u0011)f.\u001b;\u0003\t\r\u000b7/Z\u000b\u0006Oa\u001aui\u0013\t\u0005Q=\u00124G\u0004\u0002*Y9\u0011QDK\u0005\u0003WI\tq\u0001]1dW\u0006<W-\u0003\u0002.]\u0005!\u0001o\u001c7z\u0015\tY##\u0003\u0002&a)\u0011\u0011GE\u0001\n!>d\u0017\u0010R3g]Nl\u0011\u0001\u0001\t\u0005;Q2\u0014)\u0003\u00026%\taAeY8m_:$3m\u001c7p]B\u0011q\u0007\u000f\u0007\u0001\t\u0015I$A1\u0001;\u0005\u0005\t\u0015CA\u001e?!\t9B(\u0003\u0002>1\t9aj\u001c;iS:<\u0007CA\f@\u0013\t\u0001\u0005DA\u0002B]f\u0004B!\b\u001bC\u000bB\u0011qg\u0011\u0003\u0006\t\n\u0011\rA\u000f\u0002\u0002\u0005B!Q\u0004\u000e$J!\t9t\tB\u0003I\u0005\t\u0007!HA\u0001D!\u0011iBGS\'\u0011\u0005]ZE!\u0002\'\u0003\u0005\u0004Q$!\u0001#\u0011\u0005uq\u0015BA(\u0013\u0005\u0011Ae*\u001b7\u0002\t\r\u000b7/\u001a\t\u0003e\u0011\u0019\"\u0001\u0002\f\u0002\rqJg.\u001b;?)\u0005\t&aA!vqV1q+\u00181dM*\u0014\"\u0001\u0017.\u0007\te#\u0001a\u0016\u0002\ryI,g-\u001b8f[\u0016tGO\u0010\t\u0005Q=\u00124\f\u0005\u0003\u001eiqs\u0006CA\u001c^\t\u0015IdA1\u0001;!\u0011iBgX1\u0011\u0005]\u0002G!\u0002#\u0007\u0005\u0004Q\u0004\u0003B\u000f5E\u0012\u0004\"aN2\u0005\u000b!3!\u0019\u0001\u001e\u0011\tu!T-\u0014\t\u0003o\u0019$Q\u0001\u0014\u0004C\u0002i*A\u0001\u001b-!S\n1!+Z:vYR\u0004\"a\u000e6\u0005\u000b-4!\u0019\u0001\u001e\u0003\u000fI+7/\u001e7ua\tY1)Y:f\u0005VLG\u000eZ3s+\u0015q\'\u000f\u001e<y\'\t9a\u0003F\u0001q!\u0019\u0011t!]:voB\u0011qG\u001d\u0003\u0006s\u001d\u0011\rA\u000f\t\u0003oQ$Q\u0001R\u0004C\u0002i\u0002\"a\u000e<\u0005\u000b!;!\u0019\u0001\u001e\u0011\u0005]BH!\u0002\'\b\u0005\u0004Q\u0014!B1qa2LXcA>\u0002\u0004Q\u0019A0a\u0002\u0013\u0005uth\u0001B-\n\u0001q\u0004bA\r\u0002rgV<X!\u00025~\u0001\u0005\u0005\u0001cA\u001c\u0002\u0004\u00111\u0011QA\u0005C\u0002i\u00121AU3t\u0011\u001d\tI!\u0003a\u0001\u0003\u0017\t!A\u001a8\u0011\u0013]\ti!]:vo\u0006\u0005\u0011bAA\b1\tIa)\u001e8di&|g\u000eN\u0001\u0003CR,\"\"!\u0006\u0002\u001c\u0005}\u00111EA\u0014+\t\t9\u0002\u0005\u00063\u000f\u0005e\u0011QDA\u0011\u0003K\u00012aNA\u000e\t\u0015I$B1\u0001;!\r9\u0014q\u0004\u0003\u0006\t*\u0011\rA\u000f\t\u0004o\u0005\rB!\u0002%\u000b\u0005\u0004Q\u0004cA\u001c\u0002(\u0011)AJ\u0003b\u0001u\u0005)\u0001k\u001c7ziA\u0011Q\u0004D\n\u0007\u0019Y\ty#!\u0010\u0011\u000b\u0005E\u0012qG\'\u000f\u0007u\t\u0019$C\u0002\u00026I\tQ\u0002U8ms:\u0013U/\u001b7eKJ\u001c\u0018\u0002BA\u001d\u0003w\u0011A\u0002U8msR\u0012U/\u001b7eKJT1!!\u000e\u0013!\u0011\ty$!\u0013\u000e\u0005\u0005\u0005#\u0002BA\"\u0003\u000b\n!![8\u000b\u0005\u0005\u001d\u0013\u0001\u00026bm\u0006LA!a\u0013\u0002B\ta1+\u001a:jC2L\'0\u00192mKR\u0011\u00111F\u0001\nMVt7\r^5p]N,\"!a\u0015\u000f\u0007u\t)&C\u0002\u0002XI\tA\u0001\u0013(jY\u0006Qa-\u001e8di&|gn\u001d\u0011\u0002\u0019]\u0014\u0018\u000e^3SKBd\u0017mY3\u0015\u0005\u0005}\u0003\u0003BA1\u0003Oj!!a\u0019\u000b\t\u0005\u0015\u0014QI\u0001\u0005Y\u0006tw-\u0003\u0003\u0002j\u0005\r$AB(cU\u0016\u001cG\u000f"
    )
  ScalaInlineInfo: length = 0x18 (unknown attribute)
   01 00 00 04 00 2F 00 2B 01 00 1F 00 20 00 00 21
   00 22 01 00 24 00 25 00
  ScalaSig: length = 0x3 (unknown attribute)
   05 02 00
