Classfile /Users/mw/Projects/slang-braindump/.jar/jar8/assemble/slang-braindump/assemble/content/shapeless/PolyNBuilders$Poly22Builder$AtAux$$anon$85.class
  Last modified May 29, 2022; size 3209 bytes
  SHA-256 checksum ffb0c33d9dae131592b133c045aa08b7592b1849e3b88fd0f2759ecfea23ddf3
  Compiled from "polynbuilders.scala"
public final class shapeless.PolyNBuilders$Poly22Builder$AtAux$$anon$85 extends java.lang.Object implements shapeless.PolyNBuilders$Poly22Builder<shapeless.$colon$colon<scala.Function22<A, B, C, D, E, F, G, H, I, J, K, L, M, N, O, P, Q, R, S, T, U, V, Out>, HL>>
  minor version: 0
  major version: 52
  flags: (0x0031) ACC_PUBLIC, ACC_FINAL, ACC_SUPER
  this_class: #2                          // shapeless/PolyNBuilders$Poly22Builder$AtAux$$anon$85
  super_class: #5                         // java/lang/Object
  interfaces: 1, fields: 1, methods: 5, attributes: 6
Constant pool:
   #1 = Utf8               shapeless/PolyNBuilders$Poly22Builder$AtAux$$anon$85
   #2 = Class              #1             // shapeless/PolyNBuilders$Poly22Builder$AtAux$$anon$85
   #3 = Utf8               Ljava/lang/Object;Lshapeless/PolyNBuilders$Poly22Builder<Lshapeless/$colon$colon<Lscala/Function22<TA;TB;TC;TD;TE;TF;TG;TH;TI;TJ;TK;TL;TM;TN;TO;TP;TQ;TR;TS;TT;TU;TV;TOut;>;THL;>;>;
   #4 = Utf8               java/lang/Object
   #5 = Class              #4             // java/lang/Object
   #6 = Utf8               shapeless/PolyNBuilders$Poly22Builder
   #7 = Class              #6             // shapeless/PolyNBuilders$Poly22Builder
   #8 = Utf8               polynbuilders.scala
   #9 = Utf8               shapeless/PolyNBuilders$Poly22Builder$AtAux
  #10 = Class              #9             // shapeless/PolyNBuilders$Poly22Builder$AtAux
  #11 = Utf8               apply
  #12 = Utf8               (Lscala/Function22;)Lshapeless/PolyNBuilders$Poly22Builder;
  #13 = NameAndType        #11:#12        // apply:(Lscala/Function22;)Lshapeless/PolyNBuilders$Poly22Builder;
  #14 = Utf8               shapeless/PolyNBuilders
  #15 = Class              #14            // shapeless/PolyNBuilders
  #16 = Utf8               Poly22Builder
  #17 = Utf8               AtAux
  #18 = Utf8               functions
  #19 = Utf8               Lshapeless/$colon$colon;
  #20 = Utf8               Lshapeless/$colon$colon<Lscala/Function22<TA;TB;TC;TD;TE;TF;TG;TH;TI;TJ;TK;TL;TM;TN;TO;TP;TQ;TR;TS;TT;TU;TV;TOut;>;THL;>;
  #21 = Utf8               at
  #22 = Utf8               ()Lshapeless/PolyNBuilders$Poly22Builder$AtAux;
  #23 = Utf8               <A$:Ljava/lang/Object;B$:Ljava/lang/Object;C$:Ljava/lang/Object;D$:Ljava/lang/Object;E$:Ljava/lang/Object;F$:Ljava/lang/Object;G$:Ljava/lang/Object;H$:Ljava/lang/Object;I$:Ljava/lang/Object;J$:Ljava/lang/Object;K$:Ljava/lang/Object;L$:Ljava/lang/Object;M$:Ljava/lang/Object;N$:Ljava/lang/Object;O$:Ljava/lang/Object;P$:Ljava/lang/Object;Q$:Ljava/lang/Object;R$:Ljava/lang/Object;S$:Ljava/lang/Object;T$:Ljava/lang/Object;U$:Ljava/lang/Object;V$:Ljava/lang/Object;>()Lshapeless/PolyNBuilders$Poly22Builder<Lshapeless/$colon$colon<Lscala/Function22<TA;TB;TC;TD;TE;TF;TG;TH;TI;TJ;TK;TL;TM;TN;TO;TP;TQ;TR;TS;TT;TU;TV;TOut;>;THL;>;>.AtAux<TA$;TB$;TC$;TD$;TE$;TF$;TG$;TH$;TI$;TJ$;TK$;TL$;TM$;TN$;TO$;TP$;TQ$;TR$;TS$;TT$;TU$;TV$;>;
  #24 = Utf8               at$
  #25 = Utf8               (Lshapeless/PolyNBuilders$Poly22Builder;)Lshapeless/PolyNBuilders$Poly22Builder$AtAux;
  #26 = NameAndType        #24:#25        // at$:(Lshapeless/PolyNBuilders$Poly22Builder;)Lshapeless/PolyNBuilders$Poly22Builder$AtAux;
  #27 = InterfaceMethodref #7.#26         // shapeless/PolyNBuilders$Poly22Builder.at$:(Lshapeless/PolyNBuilders$Poly22Builder;)Lshapeless/PolyNBuilders$Poly22Builder$AtAux;
  #28 = Utf8               this
  #29 = Utf8               Lshapeless/PolyNBuilders$Poly22Builder$AtAux$$anon$85;
  #30 = Utf8               build
  #31 = Utf8               ()Lshapeless/Poly22;
  #32 = Utf8               build$
  #33 = Utf8               (Lshapeless/PolyNBuilders$Poly22Builder;)Lshapeless/Poly22;
  #34 = NameAndType        #32:#33        // build$:(Lshapeless/PolyNBuilders$Poly22Builder;)Lshapeless/Poly22;
  #35 = InterfaceMethodref #7.#34         // shapeless/PolyNBuilders$Poly22Builder.build$:(Lshapeless/PolyNBuilders$Poly22Builder;)Lshapeless/Poly22;
  #36 = Utf8               ()Lshapeless/$colon$colon;
  #37 = Utf8               ()Lshapeless/$colon$colon<Lscala/Function22<TA;TB;TC;TD;TE;TF;TG;TH;TI;TJ;TK;TL;TM;TN;TO;TP;TQ;TR;TS;TT;TU;TV;TOut;>;THL;>;
  #38 = NameAndType        #18:#19        // functions:Lshapeless/$colon$colon;
  #39 = Fieldref           #2.#38         // shapeless/PolyNBuilders$Poly22Builder$AtAux$$anon$85.functions:Lshapeless/$colon$colon;
  #40 = Utf8               ()Lshapeless/HList;
  #41 = NameAndType        #18:#36        // functions:()Lshapeless/$colon$colon;
  #42 = Methodref          #2.#41         // shapeless/PolyNBuilders$Poly22Builder$AtAux$$anon$85.functions:()Lshapeless/$colon$colon;
  #43 = Utf8               <init>
  #44 = Utf8               (Lshapeless/PolyNBuilders$Poly22Builder$AtAux;Lscala/Function22;)V
  #45 = Utf8               $outer
  #46 = Utf8               λ$22
  #47 = Utf8               ()V
  #48 = NameAndType        #43:#47        // "<init>":()V
  #49 = Methodref          #5.#48         // java/lang/Object."<init>":()V
  #50 = Utf8               $init$
  #51 = Utf8               (Lshapeless/PolyNBuilders$Poly22Builder;)V
  #52 = NameAndType        #50:#51        // $init$:(Lshapeless/PolyNBuilders$Poly22Builder;)V
  #53 = InterfaceMethodref #7.#52         // shapeless/PolyNBuilders$Poly22Builder.$init$:(Lshapeless/PolyNBuilders$Poly22Builder;)V
  #54 = Utf8               shapeless/HList$
  #55 = Class              #54            // shapeless/HList$
  #56 = Utf8               MODULE$
  #57 = Utf8               Lshapeless/HList$;
  #58 = NameAndType        #56:#57        // MODULE$:Lshapeless/HList$;
  #59 = Fieldref           #55.#58        // shapeless/HList$.MODULE$:Lshapeless/HList$;
  #60 = Utf8               shapeless$PolyNBuilders$Poly22Builder$AtAux$$$outer
  #61 = Utf8               ()Lshapeless/PolyNBuilders$Poly22Builder;
  #62 = NameAndType        #60:#61        // shapeless$PolyNBuilders$Poly22Builder$AtAux$$$outer:()Lshapeless/PolyNBuilders$Poly22Builder;
  #63 = Methodref          #10.#62        // shapeless/PolyNBuilders$Poly22Builder$AtAux.shapeless$PolyNBuilders$Poly22Builder$AtAux$$$outer:()Lshapeless/PolyNBuilders$Poly22Builder;
  #64 = NameAndType        #18:#40        // functions:()Lshapeless/HList;
  #65 = InterfaceMethodref #7.#64         // shapeless/PolyNBuilders$Poly22Builder.functions:()Lshapeless/HList;
  #66 = Utf8               hlistOps
  #67 = Utf8               (Lshapeless/HList;)Lshapeless/syntax/HListOps;
  #68 = NameAndType        #66:#67        // hlistOps:(Lshapeless/HList;)Lshapeless/syntax/HListOps;
  #69 = Methodref          #55.#68        // shapeless/HList$.hlistOps:(Lshapeless/HList;)Lshapeless/syntax/HListOps;
  #70 = Utf8               shapeless/syntax/HListOps
  #71 = Class              #70            // shapeless/syntax/HListOps
  #72 = Utf8               $colon$colon
  #73 = Utf8               (Ljava/lang/Object;)Lshapeless/$colon$colon;
  #74 = NameAndType        #72:#73        // $colon$colon:(Ljava/lang/Object;)Lshapeless/$colon$colon;
  #75 = Methodref          #71.#74        // shapeless/syntax/HListOps.$colon$colon:(Ljava/lang/Object;)Lshapeless/$colon$colon;
  #76 = Utf8               Lshapeless/PolyNBuilders$Poly22Builder$AtAux;
  #77 = Utf8               Lscala/Function22;
  #78 = Utf8               Signature
  #79 = Utf8               Code
  #80 = Utf8               LineNumberTable
  #81 = Utf8               LocalVariableTable
  #82 = Utf8               MethodParameters
  #83 = Utf8               InnerClasses
  #84 = Utf8               EnclosingMethod
  #85 = Utf8               SourceFile
  #86 = Utf8               ScalaInlineInfo
  #87 = Utf8               Scala
{
  private final shapeless.$colon$colon<scala.Function22<A, B, C, D, E, F, G, H, I, J, K, L, M, N, O, P, Q, R, S, T, U, V, Out>, HL> functions;
    descriptor: Lshapeless/$colon$colon;
    flags: (0x0012) ACC_PRIVATE, ACC_FINAL
    Signature: #20                          // Lshapeless/$colon$colon<Lscala/Function22<TA;TB;TC;TD;TE;TF;TG;TH;TI;TJ;TK;TL;TM;TN;TO;TP;TQ;TR;TS;TT;TU;TV;TOut;>;THL;>;

  public <A$ extends java.lang.Object, B$ extends java.lang.Object, C$ extends java.lang.Object, D$ extends java.lang.Object, E$ extends java.lang.Object, F$ extends java.lang.Object, G$ extends java.lang.Object, H$ extends java.lang.Object, I$ extends java.lang.Object, J$ extends java.lang.Object, K$ extends java.lang.Object, L$ extends java.lang.Object, M$ extends java.lang.Object, N$ extends java.lang.Object, O$ extends java.lang.Object, P$ extends java.lang.Object, Q$ extends java.lang.Object, R$ extends java.lang.Object, S$ extends java.lang.Object, T$ extends java.lang.Object, U$ extends java.lang.Object, V$ extends java.lang.Object> shapeless.PolyNBuilders$Poly22Builder<shapeless.$colon$colon<scala.Function22<A, B, C, D, E, F, G, H, I, J, K, L, M, N, O, P, Q, R, S, T, U, V, Out>, HL>>.AtAux<A$, B$, C$, D$, E$, F$, G$, H$, I$, J$, K$, L$, M$, N$, O$, P$, Q$, R$, S$, T$, U$, V$> at();
    descriptor: ()Lshapeless/PolyNBuilders$Poly22Builder$AtAux;
    flags: (0x0001) ACC_PUBLIC
    Code:
      stack=1, locals=1, args_size=1
         0: aload_0
         1: invokestatic  #27                 // InterfaceMethod shapeless/PolyNBuilders$Poly22Builder.at$:(Lshapeless/PolyNBuilders$Poly22Builder;)Lshapeless/PolyNBuilders$Poly22Builder$AtAux;
         4: areturn
      LineNumberTable:
        line 895: 0
      LocalVariableTable:
        Start  Length  Slot  Name   Signature
            0       5     0  this   Lshapeless/PolyNBuilders$Poly22Builder$AtAux$$anon$85;
    Signature: #23                          // <A$:Ljava/lang/Object;B$:Ljava/lang/Object;C$:Ljava/lang/Object;D$:Ljava/lang/Object;E$:Ljava/lang/Object;F$:Ljava/lang/Object;G$:Ljava/lang/Object;H$:Ljava/lang/Object;I$:Ljava/lang/Object;J$:Ljava/lang/Object;K$:Ljava/lang/Object;L$:Ljava/lang/Object;M$:Ljava/lang/Object;N$:Ljava/lang/Object;O$:Ljava/lang/Object;P$:Ljava/lang/Object;Q$:Ljava/lang/Object;R$:Ljava/lang/Object;S$:Ljava/lang/Object;T$:Ljava/lang/Object;U$:Ljava/lang/Object;V$:Ljava/lang/Object;>()Lshapeless/PolyNBuilders$Poly22Builder<Lshapeless/$colon$colon<Lscala/Function22<TA;TB;TC;TD;TE;TF;TG;TH;TI;TJ;TK;TL;TM;TN;TO;TP;TQ;TR;TS;TT;TU;TV;TOut;>;THL;>;>.AtAux<TA$;TB$;TC$;TD$;TE$;TF$;TG$;TH$;TI$;TJ$;TK$;TL$;TM$;TN$;TO$;TP$;TQ$;TR$;TS$;TT$;TU$;TV$;>;

  public shapeless.Poly22 build();
    descriptor: ()Lshapeless/Poly22;
    flags: (0x0001) ACC_PUBLIC
    Code:
      stack=1, locals=1, args_size=1
         0: aload_0
         1: invokestatic  #35                 // InterfaceMethod shapeless/PolyNBuilders$Poly22Builder.build$:(Lshapeless/PolyNBuilders$Poly22Builder;)Lshapeless/Poly22;
         4: areturn
      LineNumberTable:
        line 895: 0
      LocalVariableTable:
        Start  Length  Slot  Name   Signature
            0       5     0  this   Lshapeless/PolyNBuilders$Poly22Builder$AtAux$$anon$85;

  public shapeless.$colon$colon<scala.Function22<A, B, C, D, E, F, G, H, I, J, K, L, M, N, O, P, Q, R, S, T, U, V, Out>, HL> functions();
    descriptor: ()Lshapeless/$colon$colon;
    flags: (0x0001) ACC_PUBLIC
    Code:
      stack=1, locals=1, args_size=1
         0: aload_0
         1: getfield      #39                 // Field functions:Lshapeless/$colon$colon;
         4: areturn
      LineNumberTable:
        line 896: 0
      LocalVariableTable:
        Start  Length  Slot  Name   Signature
            0       5     0  this   Lshapeless/PolyNBuilders$Poly22Builder$AtAux$$anon$85;
    Signature: #37                          // ()Lshapeless/$colon$colon<Lscala/Function22<TA;TB;TC;TD;TE;TF;TG;TH;TI;TJ;TK;TL;TM;TN;TO;TP;TQ;TR;TS;TT;TU;TV;TOut;>;THL;>;

  public shapeless.HList functions();
    descriptor: ()Lshapeless/HList;
    flags: (0x1041) ACC_PUBLIC, ACC_BRIDGE, ACC_SYNTHETIC
    Code:
      stack=1, locals=1, args_size=1
         0: aload_0
         1: invokevirtual #42                 // Method functions:()Lshapeless/$colon$colon;
         4: areturn
      LineNumberTable:
        line 895: 0
      LocalVariableTable:
        Start  Length  Slot  Name   Signature
            0       5     0  this   Lshapeless/PolyNBuilders$Poly22Builder$AtAux$$anon$85;

  public shapeless.PolyNBuilders$Poly22Builder$AtAux$$anon$85(shapeless.PolyNBuilders$Poly22Builder$AtAux, scala.Function22);
    descriptor: (Lshapeless/PolyNBuilders$Poly22Builder$AtAux;Lscala/Function22;)V
    flags: (0x0001) ACC_PUBLIC
    Code:
      stack=3, locals=4, args_size=3
         0: aload_0
         1: invokespecial #49                 // Method java/lang/Object."<init>":()V
         4: aload_0
         5: invokestatic  #53                 // InterfaceMethod shapeless/PolyNBuilders$Poly22Builder.$init$:(Lshapeless/PolyNBuilders$Poly22Builder;)V
         8: aload_0
         9: aload_2
        10: astore_3
        11: getstatic     #59                 // Field shapeless/HList$.MODULE$:Lshapeless/HList$;
        14: aload_1
        15: invokevirtual #63                 // Method shapeless/PolyNBuilders$Poly22Builder$AtAux.shapeless$PolyNBuilders$Poly22Builder$AtAux$$$outer:()Lshapeless/PolyNBuilders$Poly22Builder;
        18: invokeinterface #65,  1           // InterfaceMethod shapeless/PolyNBuilders$Poly22Builder.functions:()Lshapeless/HList;
        23: invokevirtual #69                 // Method shapeless/HList$.hlistOps:(Lshapeless/HList;)Lshapeless/syntax/HListOps;
        26: aload_3
        27: invokevirtual #75                 // Method shapeless/syntax/HListOps.$colon$colon:(Ljava/lang/Object;)Lshapeless/$colon$colon;
        30: putfield      #39                 // Field functions:Lshapeless/$colon$colon;
        33: return
      LineNumberTable:
        line 895: 0
        line 896: 8
        line 895: 33
      LocalVariableTable:
        Start  Length  Slot  Name   Signature
            0      34     0  this   Lshapeless/PolyNBuilders$Poly22Builder$AtAux$$anon$85;
            0      34     1 $outer   Lshapeless/PolyNBuilders$Poly22Builder$AtAux;
            0      34     2  λ$22   Lscala/Function22;
    MethodParameters:
      Name                           Flags
      $outer                         final synthetic
      λ$22                           final
}
InnerClasses:
  public static #16= #7 of #15;           // Poly22Builder=class shapeless/PolyNBuilders$Poly22Builder of class shapeless/PolyNBuilders
  public #17= #10 of #7;                  // AtAux=class shapeless/PolyNBuilders$Poly22Builder$AtAux of class shapeless/PolyNBuilders$Poly22Builder
  public final #2;                        // class shapeless/PolyNBuilders$Poly22Builder$AtAux$$anon$85
EnclosingMethod: #10.#13                // shapeless.PolyNBuilders$Poly22Builder$AtAux.apply
Signature: #3                           // Ljava/lang/Object;Lshapeless/PolyNBuilders$Poly22Builder<Lshapeless/$colon$colon<Lscala/Function22<TA;TB;TC;TD;TE;TF;TG;TH;TI;TJ;TK;TL;TM;TN;TO;TP;TQ;TR;TS;TT;TU;TV;TOut;>;THL;>;>;
SourceFile: "polynbuilders.scala"
  ScalaInlineInfo: length = 0x1D (unknown attribute)
   01 01 00 05 00 2B 00 2C 01 00 15 00 16 01 00 1E
   00 1F 01 00 12 00 24 01 00 12 00 28 01
  Scala: length = 0x0 (unknown attribute)

