Classfile /Users/mw/Projects/slang-braindump/.jar/jar8/assemble/slang-braindump/assemble/content/shapeless/Poly11.class
  Last modified May 29, 2022; size 3416 bytes
  SHA-256 checksum 649280e2a46ab79e870aafa32ba58d06c58c33cf4ca7cff0e183af74abd49259
  Compiled from "polyntraits.scala"
public interface shapeless.Poly11 extends shapeless.Poly
  minor version: 0
  major version: 52
  flags: (0x0601) ACC_PUBLIC, ACC_INTERFACE, ACC_ABSTRACT
  this_class: #2                          // shapeless/Poly11
  super_class: #4                         // java/lang/Object
  interfaces: 1, fields: 0, methods: 6, attributes: 5
Constant pool:
   #1 = Utf8               shapeless/Poly11
   #2 = Class              #1             // shapeless/Poly11
   #3 = Utf8               java/lang/Object
   #4 = Class              #3             // java/lang/Object
   #5 = Utf8               shapeless/Poly
   #6 = Class              #5             // shapeless/Poly
   #7 = Utf8               polyntraits.scala
   #8 = Utf8               Lscala/reflect/ScalaSignature;
   #9 = Utf8               bytes
  #10 = Utf8               \u0006\u0005\t\u0015aaB\t\u0013!\u0003\r\t!\u0006\u0005\u0006A\u0001!\t!I\u0003\u0005K\u0001\u0001aeB\u0003m\u0001!\u0005QNB\u0003&\u0001!\u0005a\u000eC\u0003p\t\u0011\u0005\u0001/\u0002\u0003r\t\u0001\u0011hABA\u001e\u0001\u0001\ti\u0004\u0003\u0004p\u000f\u0011\u0005\u0011\u0011\t\u0005\b\u0003c:A\u0011AA:\u0011\u001d\ty\t\u0001C\u0001\u0003#;q!a1\u0013\u0011\u0003\t)M\u0002\u0004\u0012%!\u0005\u0011q\u0019\u0005\u0007_2!\t!a:\t\u0013\u0005%HB1A\u0005\u0002\u0005-\b\u0002CAz\u0019\u0001\u0006I!!<\t\u0013\u0005UH\"!A\u0005\n\u0005](A\u0002)pYf\f\u0014GC\u0001\u0014\u0003%\u0019\b.\u00199fY\u0016\u001c8o\u0001\u0001\u0014\u0007\u00011B\u0004\u0005\u0002\u001855\t\u0001DC\u0001\u001a\u0003\u0015\u00198-\u00197b\u0013\tY\u0002D\u0001\u0004B]f\u0014VM\u001a\t\u0003;yi\u0011AE\u0005\u0003?I\u0011A\u0001U8ms\u00061A%\u001b8ji\u0012\"\u0012A\t\t\u0003/\rJ!\u0001\n\r\u0003\tUs\u0017\u000e\u001e\u0002\u0005\u0007\u0006\u001cX-\u0006\u0007(q\r;5jT*X7~\u001bw\r\u0005\u0003)_I\u001adBA\u0015-\u001d\ti\"&\u0003\u0002,%\u00059\u0001/Y2lC\u001e,\u0017BA\u0017/\u0003\u0011\u0001x\u000e\\=\u000b\u0005-\u0012\u0012BA\u00131\u0015\t\t$#A\u0005Q_2LH)\u001a4og6\t\u0001\u0001\u0005\u0003\u001eiY\n\u0015BA\u001b\u0013\u00051!3m\u001c7p]\u0012\u001aw\u000e\\8o!\t9\u0004\b\u0004\u0001\u0005\u000be\u0012!\u0019\u0001\u001e\u0003\u0003\u0005\u000b\"a\u000f \u0011\u0005]a\u0014BA\u001f\u0019\u0005\u001dqu\u000e\u001e5j]\u001e\u0004\"aF \n\u0005\u0001C\"aA!osB!Q\u0004\u000e\"F!\t94\tB\u0003E\u0005\t\u0007!HA\u0001C!\u0011iBGR%\u0011\u0005]:E!\u0002%\u0003\u0005\u0004Q$!A\"\u0011\tu!$*\u0014\t\u0003o-#Q\u0001\u0014\u0002C\u0002i\u0012\u0011\u0001\u0012\t\u0005;Qr\u0015\u000b\u0005\u00028\u001f\u0012)\u0001K\u0001b\u0001u\t\tQ\t\u0005\u0003\u001eiI+\u0006CA\u001cT\t\u0015!&A1\u0001;\u0005\u00051\u0005\u0003B\u000f5-f\u0003\"aN,\u0005\u000ba\u0013!\u0019\u0001\u001e\u0003\u0003\u001d\u0003B!\b\u001b[;B\u0011qg\u0017\u0003\u00069\n\u0011\rA\u000f\u0002\u0002\u0011B!Q\u0004\u000e0b!\t9t\fB\u0003a\u0005\t\u0007!HA\u0001J!\u0011iBGY3\u0011\u0005]\u001aG!\u00023\u0003\u0005\u0004Q$!\u0001&\u0011\tu!d-\u001b\t\u0003o\u001d$Q\u0001\u001b\u0002C\u0002i\u0012\u0011a\u0013\t\u0003;)L!a\u001b\n\u0003\t!s\u0015\u000e\\\u0001\u0005\u0007\u0006\u001cX\r\u0005\u00023\tM\u0011AAF\u0001\u0007y%t\u0017\u000e\u001e \u0015\u00035\u00141!Q;y+Y\u0019\u0018\u0010`@\u0002\u0006\u0005-\u0011\u0011CA\f\u0003;\t\u0019#!\u000b\u00020\u0005]\"C\u0001;w\r\u0011)H\u0001A:\u0003\u0019q\u0012XMZ5oK6,g\u000e\u001e \u0011\t!z#g\u001e\t\u0005;QB(\u0010\u0005\u00028s\u0012)\u0011H\u0002b\u0001uA!Q\u0004N>~!\t9D\u0010B\u0003E\r\t\u0007!\bE\u0003\u001eiy\f\t\u0001\u0005\u00028\u007f\u0012)\u0001J\u0002b\u0001uA1Q\u0004NA\u0002\u0003\u000f\u00012aNA\u0003\t\u0015aeA1\u0001;!\u0019iB\'!\u0003\u0002\u000eA\u0019q\'a\u0003\u0005\u000bA3!\u0019\u0001\u001e\u0011\ru!\u0014qBA\n!\r9\u0014\u0011\u0003\u0003\u0006)\u001a\u0011\rA\u000f\t\u0007;Q\n)\"!\u0007\u0011\u0007]\n9\u0002B\u0003Y\r\t\u0007!\b\u0005\u0004\u001ei\u0005m\u0011q\u0004\t\u0004o\u0005uA!\u0002/\u0007\u0005\u0004Q\u0004CB\u000f5\u0003C\t)\u0003E\u00028\u0003G!Q\u0001\u0019\u0004C\u0002i\u0002b!\b\u001b\u0002(\u0005-\u0002cA\u001c\u0002*\u0011)AM\u0002b\u0001uA)Q\u0004NA\u0017SB\u0019q\'a\f\u0005\u000b!4!\u0019\u0001\u001e\u0006\r\u0005MB\u000fIA\u001b\u0005\u0019\u0011Vm];miB\u0019q\'a\u000e\u0005\r\u0005ebA1\u0001;\u0005\u001d\u0011Vm];miB\u00121bQ1tK\n+\u0018\u000e\u001c3feVA\u0012qHA$\u0003\u0017\ny%a\u0015\u0002X\u0005m\u0013qLA2\u0003O\nY\'a\u001c\u0014\u0005\u001d1BCAA\"!a\u0011t!!\u0012\u0002J\u00055\u0013\u0011KA+\u00033\ni&!\u0019\u0002f\u0005%\u0014Q\u000e\t\u0004o\u0005\u001dC!B\u001d\b\u0005\u0004Q\u0004cA\u001c\u0002L\u0011)Ai\u0002b\u0001uA\u0019q\'a\u0014\u0005\u000b!;!\u0019\u0001\u001e\u0011\u0007]\n\u0019\u0006B\u0003M\u000f\t\u0007!\bE\u00028\u0003/\"Q\u0001U\u0004C\u0002i\u00022aNA.\t\u0015!vA1\u0001;!\r9\u0014q\f\u0003\u00061\u001e\u0011\rA\u000f\t\u0004o\u0005\rD!\u0002/\b\u0005\u0004Q\u0004cA\u001c\u0002h\u0011)\u0001m\u0002b\u0001uA\u0019q\'a\u001b\u0005\u000b\u0011<!\u0019\u0001\u001e\u0011\u0007]\ny\u0007B\u0003i\u000f\t\u0007!(A\u0003baBd\u00170\u0006\u0003\u0002v\u0005\u0005E\u0003BA<\u0003\u000b\u0013B!!\u001f\u0002|\u0019)Q/\u0003\u0001\u0002xAA\"GAA#\u0003\u0013\ni%!\u0015\u0002V\u0005e\u0013QLA1\u0003K\nI\'!\u001c\u0006\u000f\u0005M\u0012\u0011\u0010\u0001\u0002\u0000A\u0019q\'!!\u0005\r\u0005\r\u0015B1\u0001;\u0005\r\u0011Vm\u001d\u0005\b\u0003\u000fK\u0001\u0019AAE\u0003\t1g\u000eE\u000e\u0018\u0003\u0017\u000b)%!\u0013\u0002N\u0005E\u0013QKA-\u0003;\n\t\'!\u001a\u0002j\u00055\u0014qP\u0005\u0004\u0003\u001bC\"A\u0003$v]\u000e$\u0018n\u001c82c\u0005\u0011\u0011\r^\u000b\u0019\u0003\'\u000bI*!(\u0002\"\u0006\u0015\u0016\u0011VAW\u0003c\u000b),!/\u0002>\u0006\u0005WCAAK!a\u0011t!a&\u0002\u001c\u0006}\u00151UAT\u0003W\u000by+a-\u00028\u0006m\u0016q\u0018\t\u0004o\u0005eE!B\u001d\u000b\u0005\u0004Q\u0004cA\u001c\u0002\u001e\u0012)AI\u0003b\u0001uA\u0019q\'!)\u0005\u000b!S!\u0019\u0001\u001e\u0011\u0007]\n)\u000bB\u0003M\u0015\t\u0007!\bE\u00028\u0003S#Q\u0001\u0015\u0006C\u0002i\u00022aNAW\t\u0015!&B1\u0001;!\r9\u0014\u0011\u0017\u0003\u00061*\u0011\rA\u000f\t\u0004o\u0005UF!\u0002/\u000b\u0005\u0004Q\u0004cA\u001c\u0002:\u0012)\u0001M\u0003b\u0001uA\u0019q\'!0\u0005\u000b\u0011T!\u0019\u0001\u001e\u0011\u0007]\n\t\rB\u0003i\u0015\t\u0007!(\u0001\u0004Q_2L\u0018\'\r\t\u0003;1\u0019b\u0001\u0004\f\u0002J\u0006]\u0007#BAf\u0003#LgbA\u000f\u0002N&\u0019\u0011q\u001a\n\u0002\u001bA{G.\u001f(Ck&dG-\u001a:t\u0013\u0011\t\u0019.!6\u0003\u001bA{G._\u00192\u0005VLG\u000eZ3s\u0015\r\tyM\u0005\t\u0005\u00033\f\u0019/\u0004\u0002\u0002\\*!\u0011Q\\Ap\u0003\tIwN\u0003\u0002\u0002b\u0006!!.\u0019<b\u0013\u0011\t)/a7\u0003\u0019M+\'/[1mSj\f\'\r\\3\u0015\u0005\u0005\u0015\u0017!\u00034v]\u000e$\u0018n\u001c8t+\t\tiOD\u0002\u001e\u0003_L1!!=\u0013\u0003\u0011Ae*\u001b7\u0002\u0015\u0019,hn\u0019;j_:\u001c\b%\u0001\u0007xe&$XMU3qY\u0006\u001cW\r\u0006\u0002\u0002zB!\u00111 B\u0001\u001b\t\tiP\u0003\u0003\u0002\u0000\u0006}\u0017\u0001\u00027b]\u001eLAAa\u0001\u0002~\n1qJ\u00196fGR\u0004
  #11 = Utf8               shapeless/Poly11$Case$
  #12 = Class              #11            // shapeless/Poly11$Case$
  #13 = Utf8               Case$
  #14 = Utf8               shapeless/Poly11$CaseBuilder
  #15 = Class              #14            // shapeless/Poly11$CaseBuilder
  #16 = Utf8               CaseBuilder
  #17 = Utf8               functions
  #18 = Utf8               ()Lshapeless/HNil$;
  #19 = Utf8               shapeless/Poly11$
  #20 = Class              #19            // shapeless/Poly11$
  #21 = Utf8               MODULE$
  #22 = Utf8               Lshapeless/Poly11$;
  #23 = NameAndType        #21:#22        // MODULE$:Lshapeless/Poly11$;
  #24 = Fieldref           #20.#23        // shapeless/Poly11$.MODULE$:Lshapeless/Poly11$;
  #25 = NameAndType        #17:#18        // functions:()Lshapeless/HNil$;
  #26 = Methodref          #20.#25        // shapeless/Poly11$.functions:()Lshapeless/HNil$;
  #27 = Utf8               build
  #28 = Utf8               ()Lshapeless/Poly11;
  #29 = NameAndType        #27:#28        // build:()Lshapeless/Poly11;
  #30 = Methodref          #20.#29        // shapeless/Poly11$.build:()Lshapeless/Poly11;
  #31 = Utf8               Case
  #32 = Utf8               ()Lshapeless/Poly11$Case$;
  #33 = Utf8               at$
  #34 = Utf8               (Lshapeless/Poly11;)Lshapeless/Poly11$CaseBuilder;
  #35 = Utf8               $this
  #36 = Utf8               at
  #37 = Utf8               ()Lshapeless/Poly11$CaseBuilder;
  #38 = NameAndType        #36:#37        // at:()Lshapeless/Poly11$CaseBuilder;
  #39 = InterfaceMethodref #2.#38         // shapeless/Poly11.at:()Lshapeless/Poly11$CaseBuilder;
  #40 = Utf8               Lshapeless/Poly11;
  #41 = Utf8               <A:Ljava/lang/Object;B:Ljava/lang/Object;C:Ljava/lang/Object;D:Ljava/lang/Object;E:Ljava/lang/Object;F:Ljava/lang/Object;G:Ljava/lang/Object;H:Ljava/lang/Object;I:Ljava/lang/Object;J:Ljava/lang/Object;K:Ljava/lang/Object;>()Lshapeless/Poly11$CaseBuilder<TA;TB;TC;TD;TE;TF;TG;TH;TI;TJ;TK;>;
  #42 = Utf8               <init>
  #43 = Utf8               (Lshapeless/Poly11;)V
  #44 = NameAndType        #42:#43        // "<init>":(Lshapeless/Poly11;)V
  #45 = Methodref          #15.#44        // shapeless/Poly11$CaseBuilder."<init>":(Lshapeless/Poly11;)V
  #46 = Utf8               this
  #47 = Utf8               $init$
  #48 = Utf8               Code
  #49 = Utf8               LineNumberTable
  #50 = Utf8               LocalVariableTable
  #51 = Utf8               MethodParameters
  #52 = Utf8               Signature
  #53 = Utf8               InnerClasses
  #54 = Utf8               SourceFile
  #55 = Utf8               RuntimeVisibleAnnotations
  #56 = Utf8               ScalaInlineInfo
  #57 = Utf8               ScalaSig
{
  public static shapeless.HNil$ functions();
    descriptor: ()Lshapeless/HNil$;
    flags: (0x0009) ACC_PUBLIC, ACC_STATIC
    Code:
      stack=1, locals=0, args_size=0
         0: getstatic     #24                 // Field shapeless/Poly11$.MODULE$:Lshapeless/Poly11$;
         3: invokevirtual #26                 // Method shapeless/Poly11$.functions:()Lshapeless/HNil$;
         6: areturn

  public static shapeless.Poly11 build();
    descriptor: ()Lshapeless/Poly11;
    flags: (0x0009) ACC_PUBLIC, ACC_STATIC
    Code:
      stack=1, locals=0, args_size=0
         0: getstatic     #24                 // Field shapeless/Poly11$.MODULE$:Lshapeless/Poly11$;
         3: invokevirtual #30                 // Method shapeless/Poly11$.build:()Lshapeless/Poly11;
         6: areturn

  public abstract shapeless.Poly11$Case$ Case();
    descriptor: ()Lshapeless/Poly11$Case$;
    flags: (0x0401) ACC_PUBLIC, ACC_ABSTRACT

  public static shapeless.Poly11$CaseBuilder at$(shapeless.Poly11);
    descriptor: (Lshapeless/Poly11;)Lshapeless/Poly11$CaseBuilder;
    flags: (0x1009) ACC_PUBLIC, ACC_STATIC, ACC_SYNTHETIC
    Code:
      stack=1, locals=1, args_size=1
         0: aload_0
         1: invokespecial #39                 // InterfaceMethod at:()Lshapeless/Poly11$CaseBuilder;
         4: areturn
      LineNumberTable:
        line 300: 0
      LocalVariableTable:
        Start  Length  Slot  Name   Signature
            0       5     0 $this   Lshapeless/Poly11;
    MethodParameters:
      Name                           Flags
      $this                          final synthetic

  public default <A extends java.lang.Object, B extends java.lang.Object, C extends java.lang.Object, D extends java.lang.Object, E extends java.lang.Object, F extends java.lang.Object, G extends java.lang.Object, H extends java.lang.Object, I extends java.lang.Object, J extends java.lang.Object, K extends java.lang.Object> shapeless.Poly11$CaseBuilder<A, B, C, D, E, F, G, H, I, J, K> at();
    descriptor: ()Lshapeless/Poly11$CaseBuilder;
    flags: (0x0001) ACC_PUBLIC
    Code:
      stack=3, locals=1, args_size=1
         0: new           #15                 // class shapeless/Poly11$CaseBuilder
         3: dup
         4: aload_0
         5: invokespecial #45                 // Method shapeless/Poly11$CaseBuilder."<init>":(Lshapeless/Poly11;)V
         8: areturn
      LineNumberTable:
        line 301: 0
      LocalVariableTable:
        Start  Length  Slot  Name   Signature
            0       9     0  this   Lshapeless/Poly11;
    Signature: #41                          // <A:Ljava/lang/Object;B:Ljava/lang/Object;C:Ljava/lang/Object;D:Ljava/lang/Object;E:Ljava/lang/Object;F:Ljava/lang/Object;G:Ljava/lang/Object;H:Ljava/lang/Object;I:Ljava/lang/Object;J:Ljava/lang/Object;K:Ljava/lang/Object;>()Lshapeless/Poly11$CaseBuilder<TA;TB;TC;TD;TE;TF;TG;TH;TI;TJ;TK;>;

  public static void $init$(shapeless.Poly11);
    descriptor: (Lshapeless/Poly11;)V
    flags: (0x0009) ACC_PUBLIC, ACC_STATIC
    Code:
      stack=0, locals=1, args_size=1
         0: return
      LineNumberTable:
        line 282: 0
      LocalVariableTable:
        Start  Length  Slot  Name   Signature
            0       1     0 $this   Lshapeless/Poly11;
    MethodParameters:
      Name                           Flags
      $this                          final synthetic
}
InnerClasses:
  public #13= #12 of #2;                  // Case$=class shapeless/Poly11$Case$ of class shapeless/Poly11
  public #16= #15 of #2;                  // CaseBuilder=class shapeless/Poly11$CaseBuilder of class shapeless/Poly11
SourceFile: "polyntraits.scala"
RuntimeVisibleAnnotations:
  0: #8(#9=s#10)
    scala.reflect.ScalaSignature(
      bytes="\u0006\u0005\t\u0015aaB\t\u0013!\u0003\r\t!\u0006\u0005\u0006A\u0001!\t!I\u0003\u0005K\u0001\u0001aeB\u0003m\u0001!\u0005QNB\u0003&\u0001!\u0005a\u000eC\u0003p\t\u0011\u0005\u0001/\u0002\u0003r\t\u0001\u0011hABA\u001e\u0001\u0001\ti\u0004\u0003\u0004p\u000f\u0011\u0005\u0011\u0011\t\u0005\b\u0003c:A\u0011AA:\u0011\u001d\ty\t\u0001C\u0001\u0003#;q!a1\u0013\u0011\u0003\t)M\u0002\u0004\u0012%!\u0005\u0011q\u0019\u0005\u0007_2!\t!a:\t\u0013\u0005%HB1A\u0005\u0002\u0005-\b\u0002CAz\u0019\u0001\u0006I!!<\t\u0013\u0005UH\"!A\u0005\n\u0005](A\u0002)pYf\f\u0014GC\u0001\u0014\u0003%\u0019\b.\u00199fY\u0016\u001c8o\u0001\u0001\u0014\u0007\u00011B\u0004\u0005\u0002\u001855\t\u0001DC\u0001\u001a\u0003\u0015\u00198-\u00197b\u0013\tY\u0002D\u0001\u0004B]f\u0014VM\u001a\t\u0003;yi\u0011AE\u0005\u0003?I\u0011A\u0001U8ms\u00061A%\u001b8ji\u0012\"\u0012A\t\t\u0003/\rJ!\u0001\n\r\u0003\tUs\u0017\u000e\u001e\u0002\u0005\u0007\u0006\u001cX-\u0006\u0007(q\r;5jT*X7~\u001bw\r\u0005\u0003)_I\u001adBA\u0015-\u001d\ti\"&\u0003\u0002,%\u00059\u0001/Y2lC\u001e,\u0017BA\u0017/\u0003\u0011\u0001x\u000e\\=\u000b\u0005-\u0012\u0012BA\u00131\u0015\t\t$#A\u0005Q_2LH)\u001a4og6\t\u0001\u0001\u0005\u0003\u001eiY\n\u0015BA\u001b\u0013\u00051!3m\u001c7p]\u0012\u001aw\u000e\\8o!\t9\u0004\b\u0004\u0001\u0005\u000be\u0012!\u0019\u0001\u001e\u0003\u0003\u0005\u000b\"a\u000f \u0011\u0005]a\u0014BA\u001f\u0019\u0005\u001dqu\u000e\u001e5j]\u001e\u0004\"aF \n\u0005\u0001C\"aA!osB!Q\u0004\u000e\"F!\t94\tB\u0003E\u0005\t\u0007!HA\u0001C!\u0011iBGR%\u0011\u0005]:E!\u0002%\u0003\u0005\u0004Q$!A\"\u0011\tu!$*\u0014\t\u0003o-#Q\u0001\u0014\u0002C\u0002i\u0012\u0011\u0001\u0012\t\u0005;Qr\u0015\u000b\u0005\u00028\u001f\u0012)\u0001K\u0001b\u0001u\t\tQ\t\u0005\u0003\u001eiI+\u0006CA\u001cT\t\u0015!&A1\u0001;\u0005\u00051\u0005\u0003B\u000f5-f\u0003\"aN,\u0005\u000ba\u0013!\u0019\u0001\u001e\u0003\u0003\u001d\u0003B!\b\u001b[;B\u0011qg\u0017\u0003\u00069\n\u0011\rA\u000f\u0002\u0002\u0011B!Q\u0004\u000e0b!\t9t\fB\u0003a\u0005\t\u0007!HA\u0001J!\u0011iBGY3\u0011\u0005]\u001aG!\u00023\u0003\u0005\u0004Q$!\u0001&\u0011\tu!d-\u001b\t\u0003o\u001d$Q\u0001\u001b\u0002C\u0002i\u0012\u0011a\u0013\t\u0003;)L!a\u001b\n\u0003\t!s\u0015\u000e\\\u0001\u0005\u0007\u0006\u001cX\r\u0005\u00023\tM\u0011AAF\u0001\u0007y%t\u0017\u000e\u001e \u0015\u00035\u00141!Q;y+Y\u0019\u0018\u0010`@\u0002\u0006\u0005-\u0011\u0011CA\f\u0003;\t\u0019#!\u000b\u00020\u0005]\"C\u0001;w\r\u0011)H\u0001A:\u0003\u0019q\u0012XMZ5oK6,g\u000e\u001e \u0011\t!z#g\u001e\t\u0005;QB(\u0010\u0005\u00028s\u0012)\u0011H\u0002b\u0001uA!Q\u0004N>~!\t9D\u0010B\u0003E\r\t\u0007!\bE\u0003\u001eiy\f\t\u0001\u0005\u00028\u007f\u0012)\u0001J\u0002b\u0001uA1Q\u0004NA\u0002\u0003\u000f\u00012aNA\u0003\t\u0015aeA1\u0001;!\u0019iB\'!\u0003\u0002\u000eA\u0019q\'a\u0003\u0005\u000bA3!\u0019\u0001\u001e\u0011\ru!\u0014qBA\n!\r9\u0014\u0011\u0003\u0003\u0006)\u001a\u0011\rA\u000f\t\u0007;Q\n)\"!\u0007\u0011\u0007]\n9\u0002B\u0003Y\r\t\u0007!\b\u0005\u0004\u001ei\u0005m\u0011q\u0004\t\u0004o\u0005uA!\u0002/\u0007\u0005\u0004Q\u0004CB\u000f5\u0003C\t)\u0003E\u00028\u0003G!Q\u0001\u0019\u0004C\u0002i\u0002b!\b\u001b\u0002(\u0005-\u0002cA\u001c\u0002*\u0011)AM\u0002b\u0001uA)Q\u0004NA\u0017SB\u0019q\'a\f\u0005\u000b!4!\u0019\u0001\u001e\u0006\r\u0005MB\u000fIA\u001b\u0005\u0019\u0011Vm];miB\u0019q\'a\u000e\u0005\r\u0005ebA1\u0001;\u0005\u001d\u0011Vm];miB\u00121bQ1tK\n+\u0018\u000e\u001c3feVA\u0012qHA$\u0003\u0017\ny%a\u0015\u0002X\u0005m\u0013qLA2\u0003O\nY\'a\u001c\u0014\u0005\u001d1BCAA\"!a\u0011t!!\u0012\u0002J\u00055\u0013\u0011KA+\u00033\ni&!\u0019\u0002f\u0005%\u0014Q\u000e\t\u0004o\u0005\u001dC!B\u001d\b\u0005\u0004Q\u0004cA\u001c\u0002L\u0011)Ai\u0002b\u0001uA\u0019q\'a\u0014\u0005\u000b!;!\u0019\u0001\u001e\u0011\u0007]\n\u0019\u0006B\u0003M\u000f\t\u0007!\bE\u00028\u0003/\"Q\u0001U\u0004C\u0002i\u00022aNA.\t\u0015!vA1\u0001;!\r9\u0014q\f\u0003\u00061\u001e\u0011\rA\u000f\t\u0004o\u0005\rD!\u0002/\b\u0005\u0004Q\u0004cA\u001c\u0002h\u0011)\u0001m\u0002b\u0001uA\u0019q\'a\u001b\u0005\u000b\u0011<!\u0019\u0001\u001e\u0011\u0007]\ny\u0007B\u0003i\u000f\t\u0007!(A\u0003baBd\u00170\u0006\u0003\u0002v\u0005\u0005E\u0003BA<\u0003\u000b\u0013B!!\u001f\u0002|\u0019)Q/\u0003\u0001\u0002xAA\"GAA#\u0003\u0013\ni%!\u0015\u0002V\u0005e\u0013QLA1\u0003K\nI\'!\u001c\u0006\u000f\u0005M\u0012\u0011\u0010\u0001\u0002\u0000A\u0019q\'!!\u0005\r\u0005\r\u0015B1\u0001;\u0005\r\u0011Vm\u001d\u0005\b\u0003\u000fK\u0001\u0019AAE\u0003\t1g\u000eE\u000e\u0018\u0003\u0017\u000b)%!\u0013\u0002N\u0005E\u0013QKA-\u0003;\n\t\'!\u001a\u0002j\u00055\u0014qP\u0005\u0004\u0003\u001bC\"A\u0003$v]\u000e$\u0018n\u001c82c\u0005\u0011\u0011\r^\u000b\u0019\u0003\'\u000bI*!(\u0002\"\u0006\u0015\u0016\u0011VAW\u0003c\u000b),!/\u0002>\u0006\u0005WCAAK!a\u0011t!a&\u0002\u001c\u0006}\u00151UAT\u0003W\u000by+a-\u00028\u0006m\u0016q\u0018\t\u0004o\u0005eE!B\u001d\u000b\u0005\u0004Q\u0004cA\u001c\u0002\u001e\u0012)AI\u0003b\u0001uA\u0019q\'!)\u0005\u000b!S!\u0019\u0001\u001e\u0011\u0007]\n)\u000bB\u0003M\u0015\t\u0007!\bE\u00028\u0003S#Q\u0001\u0015\u0006C\u0002i\u00022aNAW\t\u0015!&B1\u0001;!\r9\u0014\u0011\u0017\u0003\u00061*\u0011\rA\u000f\t\u0004o\u0005UF!\u0002/\u000b\u0005\u0004Q\u0004cA\u001c\u0002:\u0012)\u0001M\u0003b\u0001uA\u0019q\'!0\u0005\u000b\u0011T!\u0019\u0001\u001e\u0011\u0007]\n\t\rB\u0003i\u0015\t\u0007!(\u0001\u0004Q_2L\u0018\'\r\t\u0003;1\u0019b\u0001\u0004\f\u0002J\u0006]\u0007#BAf\u0003#LgbA\u000f\u0002N&\u0019\u0011q\u001a\n\u0002\u001bA{G.\u001f(Ck&dG-\u001a:t\u0013\u0011\t\u0019.!6\u0003\u001bA{G._\u00192\u0005VLG\u000eZ3s\u0015\r\tyM\u0005\t\u0005\u00033\f\u0019/\u0004\u0002\u0002\\*!\u0011Q\\Ap\u0003\tIwN\u0003\u0002\u0002b\u0006!!.\u0019<b\u0013\u0011\t)/a7\u0003\u0019M+\'/[1mSj\f\'\r\\3\u0015\u0005\u0005\u0015\u0017!\u00034v]\u000e$\u0018n\u001c8t+\t\tiOD\u0002\u001e\u0003_L1!!=\u0013\u0003\u0011Ae*\u001b7\u0002\u0015\u0019,hn\u0019;j_:\u001c\b%\u0001\u0007xe&$XMU3qY\u0006\u001cW\r\u0006\u0002\u0002zB!\u00111 B\u0001\u001b\t\tiP\u0003\u0003\u0002\u0000\u0006}\u0017\u0001\u00027b]\u001eLAAa\u0001\u0002~\n1qJ\u00196fGR\u0004"
    )
  ScalaInlineInfo: length = 0x18 (unknown attribute)
   01 00 00 04 00 2F 00 2B 01 00 1F 00 20 00 00 21
   00 22 01 00 24 00 25 00
  ScalaSig: length = 0x3 (unknown attribute)
   05 02 00
