Classfile /Users/mw/Projects/slang-braindump/.jar/jar8/assemble/slang-braindump/assemble/content/shapeless/ProductISOFacet$ProductISOOps.class
  Last modified May 29, 2022; size 1662 bytes
  SHA-256 checksum 324ca7851f13bc54f753d2574808b14968718b77b80bced5338ab1ec7b268bf9
  Compiled from "alacarte.scala"
public interface shapeless.ProductISOFacet$ProductISOOps
  minor version: 0
  major version: 52
  flags: (0x0601) ACC_PUBLIC, ACC_INTERFACE, ACC_ABSTRACT
  this_class: #2                          // shapeless/ProductISOFacet$ProductISOOps
  super_class: #4                         // java/lang/Object
  interfaces: 0, fields: 0, methods: 8, attributes: 4
Constant pool:
   #1 = Utf8               shapeless/ProductISOFacet$ProductISOOps
   #2 = Class              #1             // shapeless/ProductISOFacet$ProductISOOps
   #3 = Utf8               java/lang/Object
   #4 = Class              #3             // java/lang/Object
   #5 = Utf8               alacarte.scala
   #6 = Utf8               shapeless/ProductISOFacet
   #7 = Class              #6             // shapeless/ProductISOFacet
   #8 = Utf8               ProductISOOps
   #9 = Utf8               gen
  #10 = Utf8               ()Lshapeless/Generic;
  #11 = Utf8               ()Lshapeless/Generic<Ljava/lang/Object;>;
  #12 = Utf8               pgen
  #13 = Utf8               ()Lshapeless/Generic<Lscala/Product;>;
  #14 = Utf8               toProduct$
  #15 = Utf8               (Lshapeless/ProductISOFacet$ProductISOOps;Ljava/lang/Object;)Lscala/Product;
  #16 = Utf8               $this
  #17 = Utf8               c
  #18 = Utf8               toProduct
  #19 = Utf8               (Ljava/lang/Object;)Lscala/Product;
  #20 = NameAndType        #18:#19        // toProduct:(Ljava/lang/Object;)Lscala/Product;
  #21 = InterfaceMethodref #2.#20         // shapeless/ProductISOFacet$ProductISOOps.toProduct:(Ljava/lang/Object;)Lscala/Product;
  #22 = Utf8               Lshapeless/ProductISOFacet$ProductISOOps;
  #23 = Utf8               Ljava/lang/Object;
  #24 = NameAndType        #12:#10        // pgen:()Lshapeless/Generic;
  #25 = InterfaceMethodref #2.#24         // shapeless/ProductISOFacet$ProductISOOps.pgen:()Lshapeless/Generic;
  #26 = NameAndType        #9:#10         // gen:()Lshapeless/Generic;
  #27 = InterfaceMethodref #2.#26         // shapeless/ProductISOFacet$ProductISOOps.gen:()Lshapeless/Generic;
  #28 = Utf8               shapeless/Generic
  #29 = Class              #28            // shapeless/Generic
  #30 = Utf8               to
  #31 = Utf8               (Ljava/lang/Object;)Ljava/lang/Object;
  #32 = NameAndType        #30:#31        // to:(Ljava/lang/Object;)Ljava/lang/Object;
  #33 = InterfaceMethodref #29.#32        // shapeless/Generic.to:(Ljava/lang/Object;)Ljava/lang/Object;
  #34 = Utf8               from
  #35 = NameAndType        #34:#31        // from:(Ljava/lang/Object;)Ljava/lang/Object;
  #36 = InterfaceMethodref #29.#35        // shapeless/Generic.from:(Ljava/lang/Object;)Ljava/lang/Object;
  #37 = Utf8               scala/Product
  #38 = Class              #37            // scala/Product
  #39 = Utf8               this
  #40 = Utf8               fromProduct$
  #41 = Utf8               (Lshapeless/ProductISOFacet$ProductISOOps;Lscala/Product;)Ljava/lang/Object;
  #42 = Utf8               p
  #43 = Utf8               fromProduct
  #44 = Utf8               (Lscala/Product;)Ljava/lang/Object;
  #45 = NameAndType        #43:#44        // fromProduct:(Lscala/Product;)Ljava/lang/Object;
  #46 = InterfaceMethodref #2.#45         // shapeless/ProductISOFacet$ProductISOOps.fromProduct:(Lscala/Product;)Ljava/lang/Object;
  #47 = Utf8               Lscala/Product;
  #48 = Utf8               shapeless$ProductISOFacet$ProductISOOps$$$outer
  #49 = Utf8               ()Lshapeless/ProductISOFacet;
  #50 = Utf8               $init$
  #51 = Utf8               (Lshapeless/ProductISOFacet$ProductISOOps;)V
  #52 = Utf8               Signature
  #53 = Utf8               Code
  #54 = Utf8               LineNumberTable
  #55 = Utf8               LocalVariableTable
  #56 = Utf8               MethodParameters
  #57 = Utf8               InnerClasses
  #58 = Utf8               SourceFile
  #59 = Utf8               ScalaInlineInfo
  #60 = Utf8               Scala
{
  public abstract shapeless.Generic<java.lang.Object> gen();
    descriptor: ()Lshapeless/Generic;
    flags: (0x0401) ACC_PUBLIC, ACC_ABSTRACT
    Signature: #11                          // ()Lshapeless/Generic<Ljava/lang/Object;>;

  public abstract shapeless.Generic<scala.Product> pgen();
    descriptor: ()Lshapeless/Generic;
    flags: (0x0401) ACC_PUBLIC, ACC_ABSTRACT
    Signature: #13                          // ()Lshapeless/Generic<Lscala/Product;>;

  public static scala.Product toProduct$(shapeless.ProductISOFacet$ProductISOOps, java.lang.Object);
    descriptor: (Lshapeless/ProductISOFacet$ProductISOOps;Ljava/lang/Object;)Lscala/Product;
    flags: (0x1009) ACC_PUBLIC, ACC_STATIC, ACC_SYNTHETIC
    Code:
      stack=2, locals=2, args_size=2
         0: aload_0
         1: aload_1
         2: invokespecial #21                 // InterfaceMethod toProduct:(Ljava/lang/Object;)Lscala/Product;
         5: areturn
      LineNumberTable:
        line 37: 0
      LocalVariableTable:
        Start  Length  Slot  Name   Signature
            0       6     0 $this   Lshapeless/ProductISOFacet$ProductISOOps;
            0       6     1     c   Ljava/lang/Object;
    MethodParameters:
      Name                           Flags
      $this                          final synthetic
      c                              final

  public default scala.Product toProduct(java.lang.Object);
    descriptor: (Ljava/lang/Object;)Lscala/Product;
    flags: (0x0001) ACC_PUBLIC
    Code:
      stack=3, locals=2, args_size=2
         0: aload_0
         1: invokeinterface #25,  1           // InterfaceMethod pgen:()Lshapeless/Generic;
         6: aload_0
         7: invokeinterface #27,  1           // InterfaceMethod gen:()Lshapeless/Generic;
        12: aload_1
        13: invokeinterface #33,  2           // InterfaceMethod shapeless/Generic.to:(Ljava/lang/Object;)Ljava/lang/Object;
        18: invokeinterface #36,  2           // InterfaceMethod shapeless/Generic.from:(Ljava/lang/Object;)Ljava/lang/Object;
        23: checkcast     #38                 // class scala/Product
        26: areturn
      LineNumberTable:
        line 37: 0
      LocalVariableTable:
        Start  Length  Slot  Name   Signature
            0      27     0  this   Lshapeless/ProductISOFacet$ProductISOOps;
            0      27     1     c   Ljava/lang/Object;
    MethodParameters:
      Name                           Flags
      c                              final

  public static java.lang.Object fromProduct$(shapeless.ProductISOFacet$ProductISOOps, scala.Product);
    descriptor: (Lshapeless/ProductISOFacet$ProductISOOps;Lscala/Product;)Ljava/lang/Object;
    flags: (0x1009) ACC_PUBLIC, ACC_STATIC, ACC_SYNTHETIC
    Code:
      stack=2, locals=2, args_size=2
         0: aload_0
         1: aload_1
         2: invokespecial #46                 // InterfaceMethod fromProduct:(Lscala/Product;)Ljava/lang/Object;
         5: areturn
      LineNumberTable:
        line 38: 0
      LocalVariableTable:
        Start  Length  Slot  Name   Signature
            0       6     0 $this   Lshapeless/ProductISOFacet$ProductISOOps;
            0       6     1     p   Lscala/Product;
    MethodParameters:
      Name                           Flags
      $this                          final synthetic
      p                              final

  public default java.lang.Object fromProduct(scala.Product);
    descriptor: (Lscala/Product;)Ljava/lang/Object;
    flags: (0x0001) ACC_PUBLIC
    Code:
      stack=3, locals=2, args_size=2
         0: aload_0
         1: invokeinterface #27,  1           // InterfaceMethod gen:()Lshapeless/Generic;
         6: aload_0
         7: invokeinterface #25,  1           // InterfaceMethod pgen:()Lshapeless/Generic;
        12: aload_1
        13: invokeinterface #33,  2           // InterfaceMethod shapeless/Generic.to:(Ljava/lang/Object;)Ljava/lang/Object;
        18: invokeinterface #36,  2           // InterfaceMethod shapeless/Generic.from:(Ljava/lang/Object;)Ljava/lang/Object;
        23: areturn
      LineNumberTable:
        line 38: 0
      LocalVariableTable:
        Start  Length  Slot  Name   Signature
            0      24     0  this   Lshapeless/ProductISOFacet$ProductISOOps;
            0      24     1     p   Lscala/Product;
    MethodParameters:
      Name                           Flags
      p                              final

  public abstract shapeless.ProductISOFacet shapeless$ProductISOFacet$ProductISOOps$$$outer();
    descriptor: ()Lshapeless/ProductISOFacet;
    flags: (0x1401) ACC_PUBLIC, ACC_ABSTRACT, ACC_SYNTHETIC

  public static void $init$(shapeless.ProductISOFacet$ProductISOOps);
    descriptor: (Lshapeless/ProductISOFacet$ProductISOOps;)V
    flags: (0x0009) ACC_PUBLIC, ACC_STATIC
    Code:
      stack=0, locals=1, args_size=1
         0: return
      LineNumberTable:
        line 31: 0
      LocalVariableTable:
        Start  Length  Slot  Name   Signature
            0       1     0 $this   Lshapeless/ProductISOFacet$ProductISOOps;
    MethodParameters:
      Name                           Flags
      $this                          final synthetic
}
InnerClasses:
  public #8= #2 of #7;                    // ProductISOOps=class shapeless/ProductISOFacet$ProductISOOps of class shapeless/ProductISOFacet
SourceFile: "alacarte.scala"
  ScalaInlineInfo: length = 0x2C (unknown attribute)
   01 00 00 08 00 32 00 33 01 00 28 00 29 01 00 2B
   00 2C 00 00 09 00 0A 00 00 0C 00 0A 00 00 30 00
   31 00 00 0E 00 0F 01 00 12 00 13 00
  Scala: length = 0x0 (unknown attribute)

