Classfile /Users/mw/Projects/slang-braindump/.jar/jar8/assemble/slang-braindump/assemble/content/shapeless/RecordMacros$$treecreator2$1.class
  Last modified May 29, 2022; size 2466 bytes
  SHA-256 checksum 59d0bee106d3a054dc39066f1c1dedd399476bd5c40c5cc74c09b1e06d2d61ad
  Compiled from "records.scala"
public final class shapeless.RecordMacros$$treecreator2$1 extends scala.reflect.api.TreeCreator
  minor version: 0
  major version: 52
  flags: (0x0031) ACC_PUBLIC, ACC_FINAL, ACC_SUPER
  this_class: #2                          // shapeless/RecordMacros$$treecreator2$1
  super_class: #4                         // scala/reflect/api/TreeCreator
  interfaces: 0, fields: 0, methods: 2, attributes: 5
Constant pool:
    #1 = Utf8               shapeless/RecordMacros$$treecreator2$1
    #2 = Class              #1            // shapeless/RecordMacros$$treecreator2$1
    #3 = Utf8               scala/reflect/api/TreeCreator
    #4 = Class              #3            // scala/reflect/api/TreeCreator
    #5 = Utf8               records.scala
    #6 = Utf8               shapeless/RecordMacros
    #7 = Class              #6            // shapeless/RecordMacros
    #8 = Utf8               scala/reflect/api/Internals$InternalApi
    #9 = Class              #8            // scala/reflect/api/Internals$InternalApi
   #10 = Utf8               scala/reflect/api/Internals
   #11 = Class              #10           // scala/reflect/api/Internals
   #12 = Utf8               InternalApi
   #13 = Utf8               scala/reflect/api/Internals$ReificationSupportApi
   #14 = Class              #13           // scala/reflect/api/Internals$ReificationSupportApi
   #15 = Utf8               ReificationSupportApi
   #16 = Utf8               scala/reflect/api/Symbols$ClassSymbolApi
   #17 = Class              #16           // scala/reflect/api/Symbols$ClassSymbolApi
   #18 = Utf8               scala/reflect/api/Symbols
   #19 = Class              #18           // scala/reflect/api/Symbols
   #20 = Utf8               ClassSymbolApi
   #21 = Utf8               scala/reflect/api/Symbols$ModuleSymbolApi
   #22 = Class              #21           // scala/reflect/api/Symbols$ModuleSymbolApi
   #23 = Utf8               ModuleSymbolApi
   #24 = Utf8               scala/reflect/api/Symbols$SymbolApi
   #25 = Class              #24           // scala/reflect/api/Symbols$SymbolApi
   #26 = Utf8               SymbolApi
   #27 = Utf8               scala/reflect/api/Trees$IdentApi
   #28 = Class              #27           // scala/reflect/api/Trees$IdentApi
   #29 = Utf8               scala/reflect/api/Trees
   #30 = Class              #29           // scala/reflect/api/Trees
   #31 = Utf8               IdentApi
   #32 = Utf8               scala/reflect/api/Trees$TreeApi
   #33 = Class              #32           // scala/reflect/api/Trees$TreeApi
   #34 = Utf8               TreeApi
   #35 = Utf8               scala/reflect/api/Trees$TypedApi
   #36 = Class              #35           // scala/reflect/api/Trees$TypedApi
   #37 = Utf8               TypedApi
   #38 = Utf8               scala/reflect/api/Trees$TypedExtractor
   #39 = Class              #38           // scala/reflect/api/Trees$TypedExtractor
   #40 = Utf8               TypedExtractor
   #41 = Utf8               $treecreator2$1
   #42 = Utf8               apply
   #43 = Utf8               (Lscala/reflect/api/Mirror;)Lscala/reflect/api/Trees$TreeApi;
   #44 = Utf8               <U:Lscala/reflect/api/Universe;:Ljava/lang/Object;>(Lscala/reflect/api/Mirror<TU;>;)Lscala/reflect/api/Trees$TreeApi;
   #45 = Utf8               $m$untyped
   #46 = Utf8               scala/reflect/api/Mirror
   #47 = Class              #46           // scala/reflect/api/Mirror
   #48 = Utf8               universe
   #49 = Utf8               ()Lscala/reflect/api/Universe;
   #50 = NameAndType        #48:#49       // universe:()Lscala/reflect/api/Universe;
   #51 = Methodref          #47.#50       // scala/reflect/api/Mirror.universe:()Lscala/reflect/api/Universe;
   #52 = Utf8               scala/reflect/api/Universe
   #53 = Class              #52           // scala/reflect/api/Universe
   #54 = Utf8               Typed
   #55 = Utf8               ()Lscala/reflect/api/Trees$TypedExtractor;
   #56 = NameAndType        #54:#55       // Typed:()Lscala/reflect/api/Trees$TypedExtractor;
   #57 = Methodref          #53.#56       // scala/reflect/api/Universe.Typed:()Lscala/reflect/api/Trees$TypedExtractor;
   #58 = Utf8               internal
   #59 = Utf8               ()Lscala/reflect/api/Internals$InternalApi;
   #60 = NameAndType        #58:#59       // internal:()Lscala/reflect/api/Internals$InternalApi;
   #61 = Methodref          #53.#60       // scala/reflect/api/Universe.internal:()Lscala/reflect/api/Internals$InternalApi;
   #62 = Utf8               reificationSupport
   #63 = Utf8               ()Lscala/reflect/api/Internals$ReificationSupportApi;
   #64 = NameAndType        #62:#63       // reificationSupport:()Lscala/reflect/api/Internals$ReificationSupportApi;
   #65 = InterfaceMethodref #9.#64        // scala/reflect/api/Internals$InternalApi.reificationSupport:()Lscala/reflect/api/Internals$ReificationSupportApi;
   #66 = Utf8               shapeless.HNil
   #67 = String             #66           // shapeless.HNil
   #68 = Utf8               staticModule
   #69 = Utf8               (Ljava/lang/String;)Lscala/reflect/api/Symbols$ModuleSymbolApi;
   #70 = NameAndType        #68:#69       // staticModule:(Ljava/lang/String;)Lscala/reflect/api/Symbols$ModuleSymbolApi;
   #71 = Methodref          #47.#70       // scala/reflect/api/Mirror.staticModule:(Ljava/lang/String;)Lscala/reflect/api/Symbols$ModuleSymbolApi;
   #72 = Utf8               mkIdent
   #73 = Utf8               (Lscala/reflect/api/Symbols$SymbolApi;)Lscala/reflect/api/Trees$IdentApi;
   #74 = NameAndType        #72:#73       // mkIdent:(Lscala/reflect/api/Symbols$SymbolApi;)Lscala/reflect/api/Trees$IdentApi;
   #75 = InterfaceMethodref #14.#74       // scala/reflect/api/Internals$ReificationSupportApi.mkIdent:(Lscala/reflect/api/Symbols$SymbolApi;)Lscala/reflect/api/Trees$IdentApi;
   #76 = Utf8               staticClass
   #77 = Utf8               (Ljava/lang/String;)Lscala/reflect/api/Symbols$ClassSymbolApi;
   #78 = NameAndType        #76:#77       // staticClass:(Ljava/lang/String;)Lscala/reflect/api/Symbols$ClassSymbolApi;
   #79 = Methodref          #47.#78       // scala/reflect/api/Mirror.staticClass:(Ljava/lang/String;)Lscala/reflect/api/Symbols$ClassSymbolApi;
   #80 = Utf8               (Lscala/reflect/api/Trees$TreeApi;Lscala/reflect/api/Trees$TreeApi;)Lscala/reflect/api/Trees$TypedApi;
   #81 = NameAndType        #42:#80       // apply:(Lscala/reflect/api/Trees$TreeApi;Lscala/reflect/api/Trees$TreeApi;)Lscala/reflect/api/Trees$TypedApi;
   #82 = Methodref          #39.#81       // scala/reflect/api/Trees$TypedExtractor.apply:(Lscala/reflect/api/Trees$TreeApi;Lscala/reflect/api/Trees$TreeApi;)Lscala/reflect/api/Trees$TypedApi;
   #83 = Utf8               $u
   #84 = Utf8               Lscala/reflect/api/Universe;
   #85 = Utf8               $m
   #86 = Utf8               Lscala/reflect/api/Mirror;
   #87 = Utf8               this
   #88 = Utf8               Lshapeless/RecordMacros$$treecreator2$1;
   #89 = Utf8               <init>
   #90 = Utf8               (Lshapeless/RecordMacros;)V
   #91 = Utf8               $outer
   #92 = Utf8               ()V
   #93 = NameAndType        #89:#92       // "<init>":()V
   #94 = Methodref          #4.#93        // scala/reflect/api/TreeCreator."<init>":()V
   #95 = Utf8               Lshapeless/RecordMacros;
   #96 = Utf8               Code
   #97 = Utf8               LineNumberTable
   #98 = Utf8               LocalVariableTable
   #99 = Utf8               Signature
  #100 = Utf8               MethodParameters
  #101 = Utf8               InnerClasses
  #102 = Utf8               EnclosingMethod
  #103 = Utf8               SourceFile
  #104 = Utf8               ScalaInlineInfo
  #105 = Utf8               Scala
{
  public <U extends scala.reflect.api.Universe & java.lang.Object> scala.reflect.api.Trees$TreeApi apply(scala.reflect.api.Mirror<U>);
    descriptor: (Lscala/reflect/api/Mirror;)Lscala/reflect/api/Trees$TreeApi;
    flags: (0x0001) ACC_PUBLIC
    Code:
      stack=5, locals=4, args_size=2
         0: aload_1
         1: invokevirtual #51                 // Method scala/reflect/api/Mirror.universe:()Lscala/reflect/api/Universe;
         4: astore_2
         5: aload_1
         6: astore_3
         7: aload_2
         8: invokevirtual #57                 // Method scala/reflect/api/Universe.Typed:()Lscala/reflect/api/Trees$TypedExtractor;
        11: aload_2
        12: invokevirtual #61                 // Method scala/reflect/api/Universe.internal:()Lscala/reflect/api/Internals$InternalApi;
        15: invokeinterface #65,  1           // InterfaceMethod scala/reflect/api/Internals$InternalApi.reificationSupport:()Lscala/reflect/api/Internals$ReificationSupportApi;
        20: aload_3
        21: ldc           #67                 // String shapeless.HNil
        23: invokevirtual #71                 // Method scala/reflect/api/Mirror.staticModule:(Ljava/lang/String;)Lscala/reflect/api/Symbols$ModuleSymbolApi;
        26: invokeinterface #75,  2           // InterfaceMethod scala/reflect/api/Internals$ReificationSupportApi.mkIdent:(Lscala/reflect/api/Symbols$SymbolApi;)Lscala/reflect/api/Trees$IdentApi;
        31: aload_2
        32: invokevirtual #61                 // Method scala/reflect/api/Universe.internal:()Lscala/reflect/api/Internals$InternalApi;
        35: invokeinterface #65,  1           // InterfaceMethod scala/reflect/api/Internals$InternalApi.reificationSupport:()Lscala/reflect/api/Internals$ReificationSupportApi;
        40: aload_3
        41: ldc           #67                 // String shapeless.HNil
        43: invokevirtual #79                 // Method scala/reflect/api/Mirror.staticClass:(Ljava/lang/String;)Lscala/reflect/api/Symbols$ClassSymbolApi;
        46: invokeinterface #75,  2           // InterfaceMethod scala/reflect/api/Internals$ReificationSupportApi.mkIdent:(Lscala/reflect/api/Symbols$SymbolApi;)Lscala/reflect/api/Trees$IdentApi;
        51: invokevirtual #82                 // Method scala/reflect/api/Trees$TypedExtractor.apply:(Lscala/reflect/api/Trees$TreeApi;Lscala/reflect/api/Trees$TreeApi;)Lscala/reflect/api/Trees$TypedApi;
        54: areturn
      LineNumberTable:
        line 121: 0
      LocalVariableTable:
        Start  Length  Slot  Name   Signature
            4      50     2    $u   Lscala/reflect/api/Universe;
            6      48     3    $m   Lscala/reflect/api/Mirror;
            0      55     0  this   Lshapeless/RecordMacros$$treecreator2$1;
            0      55     1 $m$untyped   Lscala/reflect/api/Mirror;
    Signature: #44                          // <U:Lscala/reflect/api/Universe;:Ljava/lang/Object;>(Lscala/reflect/api/Mirror<TU;>;)Lscala/reflect/api/Trees$TreeApi;
    MethodParameters:
      Name                           Flags
      $m$untyped                     final

  public shapeless.RecordMacros$$treecreator2$1(shapeless.RecordMacros);
    descriptor: (Lshapeless/RecordMacros;)V
    flags: (0x0001) ACC_PUBLIC
    Code:
      stack=1, locals=2, args_size=2
         0: aload_0
         1: invokespecial #94                 // Method scala/reflect/api/TreeCreator."<init>":()V
         4: return
      LineNumberTable:
        line 121: 0
      LocalVariableTable:
        Start  Length  Slot  Name   Signature
            0       5     0  this   Lshapeless/RecordMacros$$treecreator2$1;
            0       5     1 $outer   Lshapeless/RecordMacros;
    MethodParameters:
      Name                           Flags
      $outer                         final synthetic
}
InnerClasses:
  public #12= #9 of #11;                  // InternalApi=class scala/reflect/api/Internals$InternalApi of class scala/reflect/api/Internals
  public #15= #14 of #11;                 // ReificationSupportApi=class scala/reflect/api/Internals$ReificationSupportApi of class scala/reflect/api/Internals
  public #20= #17 of #19;                 // ClassSymbolApi=class scala/reflect/api/Symbols$ClassSymbolApi of class scala/reflect/api/Symbols
  public #23= #22 of #19;                 // ModuleSymbolApi=class scala/reflect/api/Symbols$ModuleSymbolApi of class scala/reflect/api/Symbols
  public #26= #25 of #19;                 // SymbolApi=class scala/reflect/api/Symbols$SymbolApi of class scala/reflect/api/Symbols
  public #31= #28 of #30;                 // IdentApi=class scala/reflect/api/Trees$IdentApi of class scala/reflect/api/Trees
  public #34= #33 of #30;                 // TreeApi=class scala/reflect/api/Trees$TreeApi of class scala/reflect/api/Trees
  public #37= #36 of #30;                 // TypedApi=class scala/reflect/api/Trees$TypedApi of class scala/reflect/api/Trees
  public abstract #40= #39 of #30;        // TypedExtractor=class scala/reflect/api/Trees$TypedExtractor of class scala/reflect/api/Trees
  public final #41= #2;                   // $treecreator2$1=class shapeless/RecordMacros$$treecreator2$1
EnclosingMethod: #7.#0                  // shapeless.RecordMacros
SourceFile: "records.scala"
  ScalaInlineInfo: length = 0xE (unknown attribute)
   01 01 00 02 00 59 00 5A 01 00 2A 00 2B 01
  Scala: length = 0x0 (unknown attribute)

