Classfile /Users/mw/Projects/slang-braindump/.jar/jar8/assemble/slang-braindump/assemble/content/shapeless/record$Record$.class
  Last modified May 29, 2022; size 684 bytes
  SHA-256 checksum 7eb0f5409a378f3a31fb2e55ad5f53b10db6ea7a728c2609e3ccfa715e8d8716
  Compiled from "records.scala"
public class shapeless.record$Record$ implements scala.Dynamic
  minor version: 0
  major version: 52
  flags: (0x0021) ACC_PUBLIC, ACC_SUPER
  this_class: #2                          // shapeless/record$Record$
  super_class: #4                         // java/lang/Object
  interfaces: 1, fields: 1, methods: 2, attributes: 4
Constant pool:
   #1 = Utf8               shapeless/record$Record$
   #2 = Class              #1             // shapeless/record$Record$
   #3 = Utf8               java/lang/Object
   #4 = Class              #3             // java/lang/Object
   #5 = Utf8               scala/Dynamic
   #6 = Class              #5             // scala/Dynamic
   #7 = Utf8               records.scala
   #8 = Utf8               shapeless/record
   #9 = Class              #8             // shapeless/record
  #10 = Utf8               Record$
  #11 = Utf8               MODULE$
  #12 = Utf8               Lshapeless/record$Record$;
  #13 = Utf8               <clinit>
  #14 = Utf8               ()V
  #15 = Utf8               <init>
  #16 = NameAndType        #15:#14        // "<init>":()V
  #17 = Methodref          #2.#16         // shapeless/record$Record$."<init>":()V
  #18 = NameAndType        #11:#12        // MODULE$:Lshapeless/record$Record$;
  #19 = Fieldref           #2.#18         // shapeless/record$Record$.MODULE$:Lshapeless/record$Record$;
  #20 = Methodref          #4.#16         // java/lang/Object."<init>":()V
  #21 = Utf8               this
  #22 = Utf8               Code
  #23 = Utf8               LineNumberTable
  #24 = Utf8               LocalVariableTable
  #25 = Utf8               InnerClasses
  #26 = Utf8               SourceFile
  #27 = Utf8               ScalaInlineInfo
  #28 = Utf8               applyDynamic
  #29 = Utf8               (Ljava/lang/String;Lscala/collection/immutable/Seq;)Lshapeless/HList;
  #30 = Utf8               applyDynamicNamed
  #31 = Utf8               selectDynamic
  #32 = Utf8               (Ljava/lang/String;)Ljava/lang/Object;
  #33 = Utf8               Scala
{
  public static final shapeless.record$Record$ MODULE$;
    descriptor: Lshapeless/record$Record$;
    flags: (0x0019) ACC_PUBLIC, ACC_STATIC, ACC_FINAL

  public static {};
    descriptor: ()V
    flags: (0x0009) ACC_PUBLIC, ACC_STATIC
    Code:
      stack=2, locals=0, args_size=0
         0: new           #2                  // class shapeless/record$Record$
         3: dup
         4: invokespecial #17                 // Method "<init>":()V
         7: putstatic     #19                 // Field MODULE$:Lshapeless/record$Record$;
        10: return
      LineNumberTable:
        line 58: 0

  public shapeless.record$Record$();
    descriptor: ()V
    flags: (0x0001) ACC_PUBLIC
    Code:
      stack=1, locals=1, args_size=1
         0: aload_0
         1: invokespecial #20                 // Method java/lang/Object."<init>":()V
         4: return
      LineNumberTable:
        line 58: 0
      LocalVariableTable:
        Start  Length  Slot  Name   Signature
            0       5     0  this   Lshapeless/record$Record$;
}
InnerClasses:
  public static #10= #2 of #9;            // Record$=class shapeless/record$Record$ of class shapeless/record
SourceFile: "records.scala"
  ScalaInlineInfo: length = 0x18 (unknown attribute)
   01 01 00 04 00 0F 00 0E 01 00 1C 00 1D 01 00 1E
   00 1D 01 00 1F 00 20 01
  Scala: length = 0x0 (unknown attribute)

