Classfile /Users/mw/Projects/slang-braindump/.jar/jar8/assemble/slang-braindump/assemble/content/shapeless/ScalaVersionSpecifics$macrocompat$bundle.class
  Last modified May 29, 2022; size 932 bytes
  SHA-256 checksum 2616a2a170af5c375aca9fc4aab9a8e1eb4c8346222d1dd6c996602f694c0a87
  Compiled from "versionspecifics.scala"
public class shapeless.ScalaVersionSpecifics$macrocompat$bundle extends scala.annotation.Annotation
  minor version: 0
  major version: 52
  flags: (0x0021) ACC_PUBLIC, ACC_SUPER
  this_class: #2                          // shapeless/ScalaVersionSpecifics$macrocompat$bundle
  super_class: #4                         // scala/annotation/Annotation
  interfaces: 0, fields: 1, methods: 2, attributes: 4
Constant pool:
   #1 = Utf8               shapeless/ScalaVersionSpecifics$macrocompat$bundle
   #2 = Class              #1             // shapeless/ScalaVersionSpecifics$macrocompat$bundle
   #3 = Utf8               scala/annotation/Annotation
   #4 = Class              #3             // scala/annotation/Annotation
   #5 = Utf8               versionspecifics.scala
   #6 = Utf8               shapeless/ScalaVersionSpecifics$macrocompat$
   #7 = Class              #6             // shapeless/ScalaVersionSpecifics$macrocompat$
   #8 = Utf8               shapeless/ScalaVersionSpecifics
   #9 = Class              #8             // shapeless/ScalaVersionSpecifics
  #10 = Utf8               macrocompat$
  #11 = Utf8               bundle
  #12 = Utf8               $outer
  #13 = Utf8               Lshapeless/ScalaVersionSpecifics$macrocompat$;
  #14 = Utf8               shapeless$ScalaVersionSpecifics$macrocompat$bundle$$$outer
  #15 = Utf8               ()Lshapeless/ScalaVersionSpecifics$macrocompat$;
  #16 = NameAndType        #12:#13        // $outer:Lshapeless/ScalaVersionSpecifics$macrocompat$;
  #17 = Fieldref           #2.#16         // shapeless/ScalaVersionSpecifics$macrocompat$bundle.$outer:Lshapeless/ScalaVersionSpecifics$macrocompat$;
  #18 = Utf8               this
  #19 = Utf8               Lshapeless/ScalaVersionSpecifics$macrocompat$bundle;
  #20 = Utf8               <init>
  #21 = Utf8               (Lshapeless/ScalaVersionSpecifics$macrocompat$;)V
  #22 = Utf8               ()V
  #23 = NameAndType        #20:#22        // "<init>":()V
  #24 = Methodref          #4.#23         // scala/annotation/Annotation."<init>":()V
  #25 = Utf8               Code
  #26 = Utf8               LineNumberTable
  #27 = Utf8               LocalVariableTable
  #28 = Utf8               StackMapTable
  #29 = Utf8               MethodParameters
  #30 = Utf8               InnerClasses
  #31 = Utf8               SourceFile
  #32 = Utf8               ScalaInlineInfo
  #33 = Utf8               Scala
{
  public final shapeless.ScalaVersionSpecifics$macrocompat$ $outer;
    descriptor: Lshapeless/ScalaVersionSpecifics$macrocompat$;
    flags: (0x1011) ACC_PUBLIC, ACC_FINAL, ACC_SYNTHETIC

  public shapeless.ScalaVersionSpecifics$macrocompat$ shapeless$ScalaVersionSpecifics$macrocompat$bundle$$$outer();
    descriptor: ()Lshapeless/ScalaVersionSpecifics$macrocompat$;
    flags: (0x1001) ACC_PUBLIC, ACC_SYNTHETIC
    Code:
      stack=1, locals=1, args_size=1
         0: aload_0
         1: getfield      #17                 // Field $outer:Lshapeless/ScalaVersionSpecifics$macrocompat$;
         4: areturn
      LineNumberTable:
        line 36: 0
      LocalVariableTable:
        Start  Length  Slot  Name   Signature
            0       5     0  this   Lshapeless/ScalaVersionSpecifics$macrocompat$bundle;

  public shapeless.ScalaVersionSpecifics$macrocompat$bundle(shapeless.ScalaVersionSpecifics$macrocompat$);
    descriptor: (Lshapeless/ScalaVersionSpecifics$macrocompat$;)V
    flags: (0x0001) ACC_PUBLIC
    Code:
      stack=2, locals=2, args_size=2
         0: aload_1
         1: ifnonnull     6
         4: aconst_null
         5: athrow
         6: aload_0
         7: aload_1
         8: putfield      #17                 // Field $outer:Lshapeless/ScalaVersionSpecifics$macrocompat$;
        11: aload_0
        12: invokespecial #24                 // Method scala/annotation/Annotation."<init>":()V
        15: return
      StackMapTable: number_of_entries = 1
        frame_type = 6 /* same */
      LineNumberTable:
        line 36: 0
      LocalVariableTable:
        Start  Length  Slot  Name   Signature
            0      16     0  this   Lshapeless/ScalaVersionSpecifics$macrocompat$bundle;
            0      16     1 $outer   Lshapeless/ScalaVersionSpecifics$macrocompat$;
    MethodParameters:
      Name                           Flags
      $outer                         final synthetic
}
InnerClasses:
  public #10= #7 of #9;                   // macrocompat$=class shapeless/ScalaVersionSpecifics$macrocompat$ of class shapeless/ScalaVersionSpecifics
  public #11= #2 of #7;                   // bundle=class shapeless/ScalaVersionSpecifics$macrocompat$bundle of class shapeless/ScalaVersionSpecifics$macrocompat$
SourceFile: "versionspecifics.scala"
  ScalaInlineInfo: length = 0xE (unknown attribute)
   01 00 00 02 00 14 00 15 00 00 0E 00 0F 00
  Scala: length = 0x0 (unknown attribute)

