Classfile /Users/mw/Projects/slang-braindump/.jar/jar8/assemble/slang-braindump/assemble/content/shapeless/Sized.class
  Last modified May 29, 2022; size 4225 bytes
  SHA-256 checksum fec90cd67c5ace5f3155970b88c7492f105ca4f1c8339902a95e17e9bba60cfe
  Compiled from "sized.scala"
public final class shapeless.Sized<Repr extends java.lang.Object, L extends shapeless.Nat> extends java.lang.Object
  minor version: 0
  major version: 52
  flags: (0x0031) ACC_PUBLIC, ACC_FINAL, ACC_SUPER
  this_class: #2                          // shapeless/Sized
  super_class: #5                         // java/lang/Object
  interfaces: 0, fields: 1, methods: 11, attributes: 5
Constant pool:
   #1 = Utf8               shapeless/Sized
   #2 = Class              #1             // shapeless/Sized
   #3 = Utf8               <Repr:Ljava/lang/Object;L::Lshapeless/Nat;>Ljava/lang/Object;
   #4 = Utf8               java/lang/Object
   #5 = Class              #4             // java/lang/Object
   #6 = Utf8               sized.scala
   #7 = Utf8               Lscala/reflect/ScalaSignature;
   #8 = Utf8               bytes
   #9 = Utf8               \u0006\u0005\u0005Ed\u0001B\b\u0011\u0005MA\u0001b\u0007\u0001\u0003\u0006\u0004%\t\u0001\b\u0005\tQ\u0001\u0011\t\u0011)A\u0005;!)\u0011\u0006\u0001C\u0005U!)Q\u0007\u0001C!m!)q\b\u0001C!\u0001\")a\t\u0001C!\u000f\u001e)1\n\u0005E\u0001\u0019\u001a)q\u0002\u0005E\u0001\u001b\")\u0011\u0006\u0003C\u0001#\")!\u000b\u0003C\u0002\'\")\u0011\u0010\u0003C\u0001u\"1\u0011\u0010\u0003C\u0001\u0003\u0017Aq!!\u0010\t\t\u0003\ty\u0004C\u0004\u0002X!!\t!!\u0017\u0003\u000bMK\'0\u001a3\u000b\u0003E\t\u0011b\u001d5ba\u0016dWm]:\u0004\u0001U\u0019Ac\b\u0018\u0014\u0005\u0001)\u0002C\u0001\f\u001a\u001b\u00059\"\"\u0001\r\u0002\u000bM\u001c\u0017\r\\1\n\u0005i9\"AB!osJ+g-A\u0004v]NL\'0\u001a3\u0016\u0003u\u0001\"AH\u0010\r\u0001\u00111\u0001\u0005\u0001CC\u0002\u0005\u0012AAU3qeF\u0011!%\n\t\u0003-\rJ!\u0001J\f\u0003\u000f9{G\u000f[5oOB\u0011aCJ\u0005\u0003O]\u00111!\u00118z\u0003!)hn]5{K\u0012\u0004\u0013A\u0002\u001fj]&$h\b\u0006\u0002,iA!A\u0006A\u000f.\u001b\u0005\u0001\u0002C\u0001\u0010/\t\u0015y\u0003A1\u00011\u0005\u0005a\u0015C\u0001\u00122!\ta#\'\u0003\u00024!\t\u0019a*\u0019;\t\u000bm\u0019\u0001\u0019A\u000f\u0002\u0011Q|7\u000b\u001e:j]\u001e$\u0012a\u000e\t\u0003quj\u0011!\u000f\u0006\u0003um\nA\u0001\\1oO*\tA(\u0001\u0003kCZ\f\u0017B\u0001 :\u0005\u0019\u0019FO]5oO\u00061Q-];bYN$\"!\u0011#\u0011\u0005Y\u0011\u0015BA\"\u0018\u0005\u001d\u0011un\u001c7fC:DQ!R\u0003A\u0002\u0015\nQa\u001c;iKJ\f\u0001\u0002[1tQ\u000e{G-\u001a\u000b\u0002\u0011B\u0011a#S\u0005\u0003\u0015^\u00111!\u00138u\u0003\u0015\u0019\u0016N_3e!\ta\u0003bE\u0002\t+9\u0003\"\u0001L(\n\u0005A\u0003\"\u0001\u0005\'poB\u0013\u0018n\u001c:jif\u001c\u0016N_3e)\u0005a\u0015\u0001C:ju\u0016$w\n]:\u0016\u0007Q3\u0007\u000f\u0006\u0002VmR\u0019akW9\u0011\u000b1:\u0016,Z8\n\u0005a\u0003\"\u0001C*ju\u0016$w\n]:\u0011\u0005i;gB\u0001\u0010\\\u0011\u0015a&\u0002q\u0001^\u0003\rIG\u000f\u001c\t\u0004=\u0006,gB\u0001\u0017`\u0013\t\u0001\u0007#A\u0004qC\u000e\\\u0017mZ3\n\u0005\t\u001c\'!E%t%\u0016<W\u000f\\1s\u0013R,\'/\u00192mK&\u0011A\r\u0005\u0002\u0016\'\u000e\fG.\u0019,feNLwN\\*qK\u000eLg-[2t!\tqb\rB\u0003!\u0015\t\u0007\u0011%\u0003\u0002iS\n\t\u0011)\u0003\u0002kW\nq\u0011j]%uKJ\f\'\r\\3P]\u000e,\'B\u00017n\u0003\u001d9WM\\3sS\u000eT!A\\\f\u0002\u0015\r|G\u000e\\3di&|g\u000e\u0005\u0002\u001fa\u0012)qF\u0003b\u0001a!)!O\u0003a\u0002g\u0006\u0011QM\u001e\t\u0004YQ,\u0017BA;\u0011\u0005I\tE\rZ5uSZ,7i\u001c7mK\u000e$\u0018n\u001c8\t\u000b]T\u0001\u0019\u0001=\u0002\u0003M\u0004B\u0001\f\u0001f_\u0006)\u0011\r\u001d9msV\u001910!\u0001\u0016\u0003q\u00042\u0001L?\u0000\u0013\tq\bC\u0001\u0007TSj,GMQ;jY\u0012,\'\u000fE\u0002\u001f\u0003\u0003!q!a\u0001\f\u0005\u0004\t)A\u0001\u0002D\u0007V\u0019\u0011%a\u0002\u0005\u000f\u0005%\u0011\u0011\u0001b\u0001C\t\tq,\u0006\u0003\u0002\u000e\u0005UACAA\b)!\t\t\"!\t\u0002.\u0005e\u0002C\u0002\u0017\u0001\u0003\'\tY\u0002\u0005\u0003\u001f\u0003+\u0011CaBA\u0002\u0019\t\u0007\u0011qC\u000b\u0004C\u0005eAaBA\u0005\u0003+\u0011\r!\t\t\u0004Y\u0005u\u0011bAA\u0010!\t\u0011q\f\r\u0005\b\u0003Ga\u00019AA\u0013\u0003\r!\u0017n\u001d\t\u0006Y\u0005\u001d\u00121F\u0005\u0004\u0003S\u0001\"a\u0005#fM\u0006,H\u000e\u001e+p\u0013:$W\r_3e\'\u0016\f\bc\u0001\u0010\u0002\u0016!9\u0011q\u0006\u0007A\u0004\u0005E\u0012aA2cMB9\u00111GA\u001bE\u0005MQ\"A7\n\u0007\u0005]RNA\u0004GC\u000e$xN]=\t\rId\u00019AA\u001e!\u0011aC/a\u0005\u0002\t]\u0014\u0018\r]\u000b\u0007\u0003\u0003\nI%!\u0014\u0015\t\u0005\r\u00131\u000b\u000b\u0005\u0003\u000b\ny\u0005\u0005\u0004-\u0001\u0005\u001d\u00131\n\t\u0004=\u0005%C!\u0002\u0011\u000e\u0005\u0004\t\u0003c\u0001\u0010\u0002N\u0011)q&\u0004b\u0001a!1!/\u0004a\u0002\u0003#\u0002B\u0001\f;\u0002H!9\u0011QK\u0007A\u0002\u0005\u001d\u0013!\u0001:\u0002\u0015Ut\u0017\r\u001d9msN+\u0017/\u0006\u0004\u0002\\\u0005\u0015\u0014q\u000e\u000b\u0005\u0003;\n9\u0007E\u0003\u0017\u0003?\n\u0019\'C\u0002\u0002b]\u0011AaU8nKB\u0019a$!\u001a\u0005\u000b\u0001r!\u0019A\u0011\t\u000f\u0005%d\u00021\u0001\u0002l\u0005\t\u0001\u0010\u0005\u0004-\u0001\u0005\r\u0014Q\u000e\t\u0004=\u0005=D!B\u0018\u000f\u0005\u0004\u0001\u0004
  #10 = Utf8               unsized
  #11 = Utf8               Ljava/lang/Object;
  #12 = Utf8               TRepr;
  #13 = Utf8               unapplySeq
  #14 = Utf8               (Lshapeless/Sized;)Lscala/Some;
  #15 = Utf8               <Repr:Ljava/lang/Object;L::Lshapeless/Nat;>(Lshapeless/Sized<TRepr;TL;>;)Lscala/Some<TRepr;>;
  #16 = Utf8               x
  #17 = Utf8               shapeless/Sized$
  #18 = Class              #17            // shapeless/Sized$
  #19 = Utf8               MODULE$
  #20 = Utf8               Lshapeless/Sized$;
  #21 = NameAndType        #19:#20        // MODULE$:Lshapeless/Sized$;
  #22 = Fieldref           #18.#21        // shapeless/Sized$.MODULE$:Lshapeless/Sized$;
  #23 = NameAndType        #13:#14        // unapplySeq:(Lshapeless/Sized;)Lscala/Some;
  #24 = Methodref          #18.#23        // shapeless/Sized$.unapplySeq:(Lshapeless/Sized;)Lscala/Some;
  #25 = Utf8               wrap
  #26 = Utf8               (Ljava/lang/Object;Lshapeless/AdditiveCollection;)Lshapeless/Sized;
  #27 = Utf8               <Repr:Ljava/lang/Object;L::Lshapeless/Nat;>(TRepr;Lshapeless/AdditiveCollection<TRepr;>;)Lshapeless/Sized<TRepr;TL;>;
  #28 = Utf8               r
  #29 = Utf8               ev
  #30 = NameAndType        #25:#26        // wrap:(Ljava/lang/Object;Lshapeless/AdditiveCollection;)Lshapeless/Sized;
  #31 = Methodref          #18.#30        // shapeless/Sized$.wrap:(Ljava/lang/Object;Lshapeless/AdditiveCollection;)Lshapeless/Sized;
  #32 = Utf8               apply
  #33 = Utf8               (Lshapeless/DefaultToIndexedSeq;Lscala/collection/Factory;Lshapeless/AdditiveCollection;)Lshapeless/Sized;
  #34 = Utf8               <CC:Ljava/lang/Object;>(Lshapeless/DefaultToIndexedSeq<TCC;>;Lscala/collection/Factory<Lscala/runtime/Nothing$;TCC;>;Lshapeless/AdditiveCollection<TCC;>;)Lshapeless/Sized<TCC;Lshapeless/_0;>;
  #35 = Utf8               dis
  #36 = Utf8               cbf
  #37 = NameAndType        #32:#33        // apply:(Lshapeless/DefaultToIndexedSeq;Lscala/collection/Factory;Lshapeless/AdditiveCollection;)Lshapeless/Sized;
  #38 = Methodref          #18.#37        // shapeless/Sized$.apply:(Lshapeless/DefaultToIndexedSeq;Lscala/collection/Factory;Lshapeless/AdditiveCollection;)Lshapeless/Sized;
  #39 = Utf8               ()Lshapeless/SizedBuilder;
  #40 = Utf8               <CC:Ljava/lang/Object;>()Lshapeless/SizedBuilder<TCC;>;
  #41 = NameAndType        #32:#39        // apply:()Lshapeless/SizedBuilder;
  #42 = Methodref          #18.#41        // shapeless/Sized$.apply:()Lshapeless/SizedBuilder;
  #43 = Utf8               sizedOps
  #44 = Utf8               (Lshapeless/Sized;Lscala/collection/generic/IsIterable;Lshapeless/AdditiveCollection;)Lshapeless/SizedOps;
  #45 = Utf8               <Repr:Ljava/lang/Object;L::Lshapeless/Nat;>(Lshapeless/Sized<TRepr;TL;>;Lscala/collection/generic/IsIterable<TRepr;>;Lshapeless/AdditiveCollection<TRepr;>;)Lshapeless/SizedOps<Ljava/lang/Object;TRepr;TL;>;
  #46 = Utf8               s
  #47 = Utf8               itl
  #48 = NameAndType        #43:#44        // sizedOps:(Lshapeless/Sized;Lscala/collection/generic/IsIterable;Lshapeless/AdditiveCollection;)Lshapeless/SizedOps;
  #49 = Methodref          #18.#48        // shapeless/Sized$.sizedOps:(Lshapeless/Sized;Lscala/collection/generic/IsIterable;Lshapeless/AdditiveCollection;)Lshapeless/SizedOps;
  #50 = Utf8               sizedToRepr
  #51 = Utf8               (Lshapeless/Sized;)Ljava/lang/Object;
  #52 = Utf8               <Repr:Ljava/lang/Object;>(Lshapeless/Sized<TRepr;*>;)TRepr;
  #53 = NameAndType        #50:#51        // sizedToRepr:(Lshapeless/Sized;)Ljava/lang/Object;
  #54 = Methodref          #18.#53        // shapeless/Sized$.sizedToRepr:(Lshapeless/Sized;)Ljava/lang/Object;
  #55 = Utf8               ()Ljava/lang/Object;
  #56 = Utf8               ()TRepr;
  #57 = NameAndType        #10:#11        // unsized:Ljava/lang/Object;
  #58 = Fieldref           #2.#57         // shapeless/Sized.unsized:Ljava/lang/Object;
  #59 = Utf8               this
  #60 = Utf8               Lshapeless/Sized;
  #61 = Utf8               toString
  #62 = Utf8               ()Ljava/lang/String;
  #63 = NameAndType        #10:#55        // unsized:()Ljava/lang/Object;
  #64 = Methodref          #2.#63         // shapeless/Sized.unsized:()Ljava/lang/Object;
  #65 = NameAndType        #61:#62        // toString:()Ljava/lang/String;
  #66 = Methodref          #5.#65         // java/lang/Object.toString:()Ljava/lang/String;
  #67 = Utf8               equals
  #68 = Utf8               (Ljava/lang/Object;)Z
  #69 = Utf8               other
  #70 = NameAndType        #67:#68        // equals:(Ljava/lang/Object;)Z
  #71 = Methodref          #5.#70         // java/lang/Object.equals:(Ljava/lang/Object;)Z
  #72 = Utf8               hashCode
  #73 = Utf8               ()I
  #74 = NameAndType        #72:#73        // hashCode:()I
  #75 = Methodref          #5.#74         // java/lang/Object.hashCode:()I
  #76 = Utf8               <init>
  #77 = Utf8               (Ljava/lang/Object;)V
  #78 = Utf8               (TRepr;)V
  #79 = Utf8               ()V
  #80 = NameAndType        #76:#79        // "<init>":()V
  #81 = Methodref          #5.#80         // java/lang/Object."<init>":()V
  #82 = Utf8               Signature
  #83 = Utf8               Code
  #84 = Utf8               MethodParameters
  #85 = Utf8               LineNumberTable
  #86 = Utf8               LocalVariableTable
  #87 = Utf8               StackMapTable
  #88 = Utf8               SourceFile
  #89 = Utf8               RuntimeVisibleAnnotations
  #90 = Utf8               ScalaInlineInfo
  #91 = Utf8               ScalaSig
{
  private final Repr unsized;
    descriptor: Ljava/lang/Object;
    flags: (0x0012) ACC_PRIVATE, ACC_FINAL
    Signature: #12                          // TRepr;

  public static <Repr extends java.lang.Object, L extends shapeless.Nat> scala.Some<Repr> unapplySeq(shapeless.Sized<Repr, L>);
    descriptor: (Lshapeless/Sized;)Lscala/Some;
    flags: (0x0009) ACC_PUBLIC, ACC_STATIC
    Code:
      stack=2, locals=1, args_size=1
         0: getstatic     #22                 // Field shapeless/Sized$.MODULE$:Lshapeless/Sized$;
         3: aload_0
         4: invokevirtual #24                 // Method shapeless/Sized$.unapplySeq:(Lshapeless/Sized;)Lscala/Some;
         7: areturn
    Signature: #15                          // <Repr:Ljava/lang/Object;L::Lshapeless/Nat;>(Lshapeless/Sized<TRepr;TL;>;)Lscala/Some<TRepr;>;
    MethodParameters:
      Name                           Flags
      x                              final

  public static <Repr extends java.lang.Object, L extends shapeless.Nat> shapeless.Sized<Repr, L> wrap(Repr, shapeless.AdditiveCollection<Repr>);
    descriptor: (Ljava/lang/Object;Lshapeless/AdditiveCollection;)Lshapeless/Sized;
    flags: (0x0009) ACC_PUBLIC, ACC_STATIC
    Code:
      stack=3, locals=2, args_size=2
         0: getstatic     #22                 // Field shapeless/Sized$.MODULE$:Lshapeless/Sized$;
         3: aload_0
         4: aload_1
         5: invokevirtual #31                 // Method shapeless/Sized$.wrap:(Ljava/lang/Object;Lshapeless/AdditiveCollection;)Lshapeless/Sized;
         8: areturn
    Signature: #27                          // <Repr:Ljava/lang/Object;L::Lshapeless/Nat;>(TRepr;Lshapeless/AdditiveCollection<TRepr;>;)Lshapeless/Sized<TRepr;TL;>;
    MethodParameters:
      Name                           Flags
      r                              final
      ev                             final

  public static <CC extends java.lang.Object> shapeless.Sized<CC, shapeless._0> apply(shapeless.DefaultToIndexedSeq<CC>, scala.collection.Factory<scala.runtime.Nothing$, CC>, shapeless.AdditiveCollection<CC>);
    descriptor: (Lshapeless/DefaultToIndexedSeq;Lscala/collection/Factory;Lshapeless/AdditiveCollection;)Lshapeless/Sized;
    flags: (0x0009) ACC_PUBLIC, ACC_STATIC
    Code:
      stack=4, locals=3, args_size=3
         0: getstatic     #22                 // Field shapeless/Sized$.MODULE$:Lshapeless/Sized$;
         3: aload_0
         4: aload_1
         5: aload_2
         6: invokevirtual #38                 // Method shapeless/Sized$.apply:(Lshapeless/DefaultToIndexedSeq;Lscala/collection/Factory;Lshapeless/AdditiveCollection;)Lshapeless/Sized;
         9: areturn
    Signature: #34                          // <CC:Ljava/lang/Object;>(Lshapeless/DefaultToIndexedSeq<TCC;>;Lscala/collection/Factory<Lscala/runtime/Nothing$;TCC;>;Lshapeless/AdditiveCollection<TCC;>;)Lshapeless/Sized<TCC;Lshapeless/_0;>;
    MethodParameters:
      Name                           Flags
      dis                            final
      cbf                            final
      ev                             final

  public static <CC extends java.lang.Object> shapeless.SizedBuilder<CC> apply();
    descriptor: ()Lshapeless/SizedBuilder;
    flags: (0x0009) ACC_PUBLIC, ACC_STATIC
    Code:
      stack=1, locals=0, args_size=0
         0: getstatic     #22                 // Field shapeless/Sized$.MODULE$:Lshapeless/Sized$;
         3: invokevirtual #42                 // Method shapeless/Sized$.apply:()Lshapeless/SizedBuilder;
         6: areturn
    Signature: #40                          // <CC:Ljava/lang/Object;>()Lshapeless/SizedBuilder<TCC;>;

  public static <Repr extends java.lang.Object, L extends shapeless.Nat> shapeless.SizedOps<java.lang.Object, Repr, L> sizedOps(shapeless.Sized<Repr, L>, scala.collection.generic.IsIterable<Repr>, shapeless.AdditiveCollection<Repr>);
    descriptor: (Lshapeless/Sized;Lscala/collection/generic/IsIterable;Lshapeless/AdditiveCollection;)Lshapeless/SizedOps;
    flags: (0x0009) ACC_PUBLIC, ACC_STATIC
    Code:
      stack=4, locals=3, args_size=3
         0: getstatic     #22                 // Field shapeless/Sized$.MODULE$:Lshapeless/Sized$;
         3: aload_0
         4: aload_1
         5: aload_2
         6: invokevirtual #49                 // Method shapeless/Sized$.sizedOps:(Lshapeless/Sized;Lscala/collection/generic/IsIterable;Lshapeless/AdditiveCollection;)Lshapeless/SizedOps;
         9: areturn
    Signature: #45                          // <Repr:Ljava/lang/Object;L::Lshapeless/Nat;>(Lshapeless/Sized<TRepr;TL;>;Lscala/collection/generic/IsIterable<TRepr;>;Lshapeless/AdditiveCollection<TRepr;>;)Lshapeless/SizedOps<Ljava/lang/Object;TRepr;TL;>;
    MethodParameters:
      Name                           Flags
      s                              final
      itl                            final
      ev                             final

  public static <Repr extends java.lang.Object> Repr sizedToRepr(shapeless.Sized<Repr, ?>);
    descriptor: (Lshapeless/Sized;)Ljava/lang/Object;
    flags: (0x0009) ACC_PUBLIC, ACC_STATIC
    Code:
      stack=2, locals=1, args_size=1
         0: getstatic     #22                 // Field shapeless/Sized$.MODULE$:Lshapeless/Sized$;
         3: aload_0
         4: invokevirtual #54                 // Method shapeless/Sized$.sizedToRepr:(Lshapeless/Sized;)Ljava/lang/Object;
         7: areturn
    Signature: #52                          // <Repr:Ljava/lang/Object;>(Lshapeless/Sized<TRepr;*>;)TRepr;
    MethodParameters:
      Name                           Flags
      s                              final

  public Repr unsized();
    descriptor: ()Ljava/lang/Object;
    flags: (0x0001) ACC_PUBLIC
    Code:
      stack=1, locals=1, args_size=1
         0: aload_0
         1: getfield      #58                 // Field unsized:Ljava/lang/Object;
         4: areturn
      LineNumberTable:
        line 28: 0
      LocalVariableTable:
        Start  Length  Slot  Name   Signature
            0       5     0  this   Lshapeless/Sized;
    Signature: #56                          // ()TRepr;

  public java.lang.String toString();
    descriptor: ()Ljava/lang/String;
    flags: (0x0001) ACC_PUBLIC
    Code:
      stack=1, locals=1, args_size=1
         0: aload_0
         1: invokevirtual #64                 // Method unsized:()Ljava/lang/Object;
         4: invokevirtual #66                 // Method java/lang/Object.toString:()Ljava/lang/String;
         7: areturn
      LineNumberTable:
        line 30: 0
      LocalVariableTable:
        Start  Length  Slot  Name   Signature
            0       8     0  this   Lshapeless/Sized;

  public boolean equals(java.lang.Object);
    descriptor: (Ljava/lang/Object;)Z
    flags: (0x0001) ACC_PUBLIC
    Code:
      stack=2, locals=5, args_size=2
         0: aload_1
         1: astore_3
         2: aload_3
         3: instanceof    #2                  // class shapeless/Sized
         6: ifeq          31
         9: aload_3
        10: checkcast     #2                  // class shapeless/Sized
        13: astore        4
        15: aload_0
        16: invokevirtual #64                 // Method unsized:()Ljava/lang/Object;
        19: aload         4
        21: invokevirtual #64                 // Method unsized:()Ljava/lang/Object;
        24: invokevirtual #71                 // Method java/lang/Object.equals:(Ljava/lang/Object;)Z
        27: istore_2
        28: goto          39
        31: goto          34
        34: iconst_0
        35: istore_2
        36: goto          39
        39: iload_2
        40: ireturn
      StackMapTable: number_of_entries = 3
        frame_type = 253 /* append */
          offset_delta = 31
          locals = [ top, class java/lang/Object ]
        frame_type = 2 /* same */
        frame_type = 255 /* full_frame */
          offset_delta = 4
          locals = [ class shapeless/Sized, class java/lang/Object, int, class java/lang/Object ]
          stack = []
      LineNumberTable:
        line 33: 0
        line 34: 2
        line 35: 34
        line 33: 39
      LocalVariableTable:
        Start  Length  Slot  Name   Signature
            0      41     0  this   Lshapeless/Sized;
            0      41     1 other   Ljava/lang/Object;
    MethodParameters:
      Name                           Flags
      other                          final

  public int hashCode();
    descriptor: ()I
    flags: (0x0001) ACC_PUBLIC
    Code:
      stack=1, locals=1, args_size=1
         0: aload_0
         1: invokevirtual #64                 // Method unsized:()Ljava/lang/Object;
         4: invokevirtual #75                 // Method java/lang/Object.hashCode:()I
         7: ireturn
      LineNumberTable:
        line 38: 0
      LocalVariableTable:
        Start  Length  Slot  Name   Signature
            0       8     0  this   Lshapeless/Sized;

  public shapeless.Sized(Repr);
    descriptor: (Ljava/lang/Object;)V
    flags: (0x0001) ACC_PUBLIC
    Code:
      stack=2, locals=2, args_size=2
         0: aload_0
         1: aload_1
         2: putfield      #58                 // Field unsized:Ljava/lang/Object;
         5: aload_0
         6: invokespecial #81                 // Method java/lang/Object."<init>":()V
         9: return
      LineNumberTable:
        line 28: 0
        line 49: 5
        line 28: 9
      LocalVariableTable:
        Start  Length  Slot  Name   Signature
            0      10     0  this   Lshapeless/Sized;
            0      10     1 unsized   Ljava/lang/Object;
    Signature: #78                          // (TRepr;)V
    MethodParameters:
      Name                           Flags
      unsized                        final
}
Signature: #3                           // <Repr:Ljava/lang/Object;L::Lshapeless/Nat;>Ljava/lang/Object;
SourceFile: "sized.scala"
RuntimeVisibleAnnotations:
  0: #7(#8=s#9)
    scala.reflect.ScalaSignature(
      bytes="\u0006\u0005\u0005Ed\u0001B\b\u0011\u0005MA\u0001b\u0007\u0001\u0003\u0006\u0004%\t\u0001\b\u0005\tQ\u0001\u0011\t\u0011)A\u0005;!)\u0011\u0006\u0001C\u0005U!)Q\u0007\u0001C!m!)q\b\u0001C!\u0001\")a\t\u0001C!\u000f\u001e)1\n\u0005E\u0001\u0019\u001a)q\u0002\u0005E\u0001\u001b\")\u0011\u0006\u0003C\u0001#\")!\u000b\u0003C\u0002\'\")\u0011\u0010\u0003C\u0001u\"1\u0011\u0010\u0003C\u0001\u0003\u0017Aq!!\u0010\t\t\u0003\ty\u0004C\u0004\u0002X!!\t!!\u0017\u0003\u000bMK\'0\u001a3\u000b\u0003E\t\u0011b\u001d5ba\u0016dWm]:\u0004\u0001U\u0019Ac\b\u0018\u0014\u0005\u0001)\u0002C\u0001\f\u001a\u001b\u00059\"\"\u0001\r\u0002\u000bM\u001c\u0017\r\\1\n\u0005i9\"AB!osJ+g-A\u0004v]NL\'0\u001a3\u0016\u0003u\u0001\"AH\u0010\r\u0001\u00111\u0001\u0005\u0001CC\u0002\u0005\u0012AAU3qeF\u0011!%\n\t\u0003-\rJ!\u0001J\f\u0003\u000f9{G\u000f[5oOB\u0011aCJ\u0005\u0003O]\u00111!\u00118z\u0003!)hn]5{K\u0012\u0004\u0013A\u0002\u001fj]&$h\b\u0006\u0002,iA!A\u0006A\u000f.\u001b\u0005\u0001\u0002C\u0001\u0010/\t\u0015y\u0003A1\u00011\u0005\u0005a\u0015C\u0001\u00122!\ta#\'\u0003\u00024!\t\u0019a*\u0019;\t\u000bm\u0019\u0001\u0019A\u000f\u0002\u0011Q|7\u000b\u001e:j]\u001e$\u0012a\u000e\t\u0003quj\u0011!\u000f\u0006\u0003um\nA\u0001\\1oO*\tA(\u0001\u0003kCZ\f\u0017B\u0001 :\u0005\u0019\u0019FO]5oO\u00061Q-];bYN$\"!\u0011#\u0011\u0005Y\u0011\u0015BA\"\u0018\u0005\u001d\u0011un\u001c7fC:DQ!R\u0003A\u0002\u0015\nQa\u001c;iKJ\f\u0001\u0002[1tQ\u000e{G-\u001a\u000b\u0002\u0011B\u0011a#S\u0005\u0003\u0015^\u00111!\u00138u\u0003\u0015\u0019\u0016N_3e!\ta\u0003bE\u0002\t+9\u0003\"\u0001L(\n\u0005A\u0003\"\u0001\u0005\'poB\u0013\u0018n\u001c:jif\u001c\u0016N_3e)\u0005a\u0015\u0001C:ju\u0016$w\n]:\u0016\u0007Q3\u0007\u000f\u0006\u0002VmR\u0019akW9\u0011\u000b1:\u0016,Z8\n\u0005a\u0003\"\u0001C*ju\u0016$w\n]:\u0011\u0005i;gB\u0001\u0010\\\u0011\u0015a&\u0002q\u0001^\u0003\rIG\u000f\u001c\t\u0004=\u0006,gB\u0001\u0017`\u0013\t\u0001\u0007#A\u0004qC\u000e\\\u0017mZ3\n\u0005\t\u001c\'!E%t%\u0016<W\u000f\\1s\u0013R,\'/\u00192mK&\u0011A\r\u0005\u0002\u0016\'\u000e\fG.\u0019,feNLwN\\*qK\u000eLg-[2t!\tqb\rB\u0003!\u0015\t\u0007\u0011%\u0003\u0002iS\n\t\u0011)\u0003\u0002kW\nq\u0011j]%uKJ\f\'\r\\3P]\u000e,\'B\u00017n\u0003\u001d9WM\\3sS\u000eT!A\\\f\u0002\u0015\r|G\u000e\\3di&|g\u000e\u0005\u0002\u001fa\u0012)qF\u0003b\u0001a!)!O\u0003a\u0002g\u0006\u0011QM\u001e\t\u0004YQ,\u0017BA;\u0011\u0005I\tE\rZ5uSZ,7i\u001c7mK\u000e$\u0018n\u001c8\t\u000b]T\u0001\u0019\u0001=\u0002\u0003M\u0004B\u0001\f\u0001f_\u0006)\u0011\r\u001d9msV\u001910!\u0001\u0016\u0003q\u00042\u0001L?\u0000\u0013\tq\bC\u0001\u0007TSj,GMQ;jY\u0012,\'\u000fE\u0002\u001f\u0003\u0003!q!a\u0001\f\u0005\u0004\t)A\u0001\u0002D\u0007V\u0019\u0011%a\u0002\u0005\u000f\u0005%\u0011\u0011\u0001b\u0001C\t\tq,\u0006\u0003\u0002\u000e\u0005UACAA\b)!\t\t\"!\t\u0002.\u0005e\u0002C\u0002\u0017\u0001\u0003\'\tY\u0002\u0005\u0003\u001f\u0003+\u0011CaBA\u0002\u0019\t\u0007\u0011qC\u000b\u0004C\u0005eAaBA\u0005\u0003+\u0011\r!\t\t\u0004Y\u0005u\u0011bAA\u0010!\t\u0011q\f\r\u0005\b\u0003Ga\u00019AA\u0013\u0003\r!\u0017n\u001d\t\u0006Y\u0005\u001d\u00121F\u0005\u0004\u0003S\u0001\"a\u0005#fM\u0006,H\u000e\u001e+p\u0013:$W\r_3e\'\u0016\f\bc\u0001\u0010\u0002\u0016!9\u0011q\u0006\u0007A\u0004\u0005E\u0012aA2cMB9\u00111GA\u001bE\u0005MQ\"A7\n\u0007\u0005]RNA\u0004GC\u000e$xN]=\t\rId\u00019AA\u001e!\u0011aC/a\u0005\u0002\t]\u0014\u0018\r]\u000b\u0007\u0003\u0003\nI%!\u0014\u0015\t\u0005\r\u00131\u000b\u000b\u0005\u0003\u000b\ny\u0005\u0005\u0004-\u0001\u0005\u001d\u00131\n\t\u0004=\u0005%C!\u0002\u0011\u000e\u0005\u0004\t\u0003c\u0001\u0010\u0002N\u0011)q&\u0004b\u0001a!1!/\u0004a\u0002\u0003#\u0002B\u0001\f;\u0002H!9\u0011QK\u0007A\u0002\u0005\u001d\u0013!\u0001:\u0002\u0015Ut\u0017\r\u001d9msN+\u0017/\u0006\u0004\u0002\\\u0005\u0015\u0014q\u000e\u000b\u0005\u0003;\n9\u0007E\u0003\u0017\u0003?\n\u0019\'C\u0002\u0002b]\u0011AaU8nKB\u0019a$!\u001a\u0005\u000b\u0001r!\u0019A\u0011\t\u000f\u0005%d\u00021\u0001\u0002l\u0005\t\u0001\u0010\u0005\u0004-\u0001\u0005\r\u0014Q\u000e\t\u0004=\u0005=D!B\u0018\u000f\u0005\u0004\u0001\u0004"
    )
  ScalaInlineInfo: length = 0x1D (unknown attribute)
   01 01 00 05 00 4C 00 4D 01 00 43 00 44 01 00 48
   00 49 01 00 3D 00 3E 01 00 0A 00 37 01
  ScalaSig: length = 0x3 (unknown attribute)
   05 02 00
