Classfile /Users/mw/Projects/slang-braindump/.jar/jar8/assemble/slang-braindump/assemble/content/shapeless/Strict$$anon$2.class
  Last modified May 29, 2022; size 1383 bytes
  SHA-256 checksum 02a4f416bba31bc1b741e42538d7bddd361723cf7b0f4933d83c04408093637e
  Compiled from "lazy.scala"
public final class shapeless.Strict$$anon$2 extends java.lang.Object implements shapeless.Strict<T>
  minor version: 0
  major version: 52
  flags: (0x0031) ACC_PUBLIC, ACC_FINAL, ACC_SUPER
  this_class: #2                          // shapeless/Strict$$anon$2
  super_class: #5                         // java/lang/Object
  interfaces: 1, fields: 1, methods: 4, attributes: 6
Constant pool:
   #1 = Utf8               shapeless/Strict$$anon$2
   #2 = Class              #1             // shapeless/Strict$$anon$2
   #3 = Utf8               Ljava/lang/Object;Lshapeless/Strict<TT;>;
   #4 = Utf8               java/lang/Object
   #5 = Class              #4             // java/lang/Object
   #6 = Utf8               shapeless/Strict
   #7 = Class              #6             // shapeless/Strict
   #8 = Utf8               lazy.scala
   #9 = Utf8               shapeless/Strict$
  #10 = Class              #9             // shapeless/Strict$
  #11 = Utf8               apply
  #12 = Utf8               (Ljava/lang/Object;)Lshapeless/Strict;
  #13 = NameAndType        #11:#12        // apply:(Ljava/lang/Object;)Lshapeless/Strict;
  #14 = Utf8               value
  #15 = Utf8               Ljava/lang/Object;
  #16 = Utf8               TT;
  #17 = Utf8               map
  #18 = Utf8               (Lscala/Function1;)Lshapeless/Strict;
  #19 = Utf8               <U:Ljava/lang/Object;>(Lscala/Function1<TT;TU;>;)Lshapeless/Strict<TU;>;
  #20 = Utf8               f
  #21 = Utf8               map$
  #22 = Utf8               (Lshapeless/Strict;Lscala/Function1;)Lshapeless/Strict;
  #23 = NameAndType        #21:#22        // map$:(Lshapeless/Strict;Lscala/Function1;)Lshapeless/Strict;
  #24 = InterfaceMethodref #7.#23         // shapeless/Strict.map$:(Lshapeless/Strict;Lscala/Function1;)Lshapeless/Strict;
  #25 = Utf8               this
  #26 = Utf8               Lshapeless/Strict$$anon$2;
  #27 = Utf8               Lscala/Function1;
  #28 = Utf8               flatMap
  #29 = Utf8               <U:Ljava/lang/Object;>(Lscala/Function1<TT;Lshapeless/Strict<TU;>;>;)Lshapeless/Strict<TU;>;
  #30 = Utf8               flatMap$
  #31 = NameAndType        #30:#22        // flatMap$:(Lshapeless/Strict;Lscala/Function1;)Lshapeless/Strict;
  #32 = InterfaceMethodref #7.#31         // shapeless/Strict.flatMap$:(Lshapeless/Strict;Lscala/Function1;)Lshapeless/Strict;
  #33 = Utf8               ()Ljava/lang/Object;
  #34 = Utf8               ()TT;
  #35 = NameAndType        #14:#15        // value:Ljava/lang/Object;
  #36 = Fieldref           #2.#35         // shapeless/Strict$$anon$2.value:Ljava/lang/Object;
  #37 = Utf8               <init>
  #38 = Utf8               (Ljava/lang/Object;)V
  #39 = Utf8               t$2
  #40 = Utf8               ()V
  #41 = NameAndType        #37:#40        // "<init>":()V
  #42 = Methodref          #5.#41         // java/lang/Object."<init>":()V
  #43 = Utf8               $init$
  #44 = Utf8               (Lshapeless/Strict;)V
  #45 = NameAndType        #43:#44        // $init$:(Lshapeless/Strict;)V
  #46 = InterfaceMethodref #7.#45         // shapeless/Strict.$init$:(Lshapeless/Strict;)V
  #47 = Utf8               Signature
  #48 = Utf8               Code
  #49 = Utf8               LineNumberTable
  #50 = Utf8               LocalVariableTable
  #51 = Utf8               MethodParameters
  #52 = Utf8               InnerClasses
  #53 = Utf8               EnclosingMethod
  #54 = Utf8               SourceFile
  #55 = Utf8               ScalaInlineInfo
  #56 = Utf8               Scala
{
  private final T value;
    descriptor: Ljava/lang/Object;
    flags: (0x0012) ACC_PRIVATE, ACC_FINAL
    Signature: #16                          // TT;

  public <U extends java.lang.Object> shapeless.Strict<U> map(scala.Function1<T, U>);
    descriptor: (Lscala/Function1;)Lshapeless/Strict;
    flags: (0x0001) ACC_PUBLIC
    Code:
      stack=2, locals=2, args_size=2
         0: aload_0
         1: aload_1
         2: invokestatic  #24                 // InterfaceMethod shapeless/Strict.map$:(Lshapeless/Strict;Lscala/Function1;)Lshapeless/Strict;
         5: areturn
      LineNumberTable:
        line 162: 0
      LocalVariableTable:
        Start  Length  Slot  Name   Signature
            0       6     0  this   Lshapeless/Strict$$anon$2;
            0       6     1     f   Lscala/Function1;
    Signature: #19                          // <U:Ljava/lang/Object;>(Lscala/Function1<TT;TU;>;)Lshapeless/Strict<TU;>;
    MethodParameters:
      Name                           Flags
      f                              final

  public <U extends java.lang.Object> shapeless.Strict<U> flatMap(scala.Function1<T, shapeless.Strict<U>>);
    descriptor: (Lscala/Function1;)Lshapeless/Strict;
    flags: (0x0001) ACC_PUBLIC
    Code:
      stack=2, locals=2, args_size=2
         0: aload_0
         1: aload_1
         2: invokestatic  #32                 // InterfaceMethod shapeless/Strict.flatMap$:(Lshapeless/Strict;Lscala/Function1;)Lshapeless/Strict;
         5: areturn
      LineNumberTable:
        line 162: 0
      LocalVariableTable:
        Start  Length  Slot  Name   Signature
            0       6     0  this   Lshapeless/Strict$$anon$2;
            0       6     1     f   Lscala/Function1;
    Signature: #29                          // <U:Ljava/lang/Object;>(Lscala/Function1<TT;Lshapeless/Strict<TU;>;>;)Lshapeless/Strict<TU;>;
    MethodParameters:
      Name                           Flags
      f                              final

  public T value();
    descriptor: ()Ljava/lang/Object;
    flags: (0x0001) ACC_PUBLIC
    Code:
      stack=1, locals=1, args_size=1
         0: aload_0
         1: getfield      #36                 // Field value:Ljava/lang/Object;
         4: areturn
      LineNumberTable:
        line 163: 0
      LocalVariableTable:
        Start  Length  Slot  Name   Signature
            0       5     0  this   Lshapeless/Strict$$anon$2;
    Signature: #34                          // ()TT;

  public shapeless.Strict$$anon$2(java.lang.Object);
    descriptor: (Ljava/lang/Object;)V
    flags: (0x0001) ACC_PUBLIC
    Code:
      stack=2, locals=2, args_size=2
         0: aload_0
         1: invokespecial #42                 // Method java/lang/Object."<init>":()V
         4: aload_0
         5: invokestatic  #46                 // InterfaceMethod shapeless/Strict.$init$:(Lshapeless/Strict;)V
         8: aload_0
         9: aload_1
        10: putfield      #36                 // Field value:Ljava/lang/Object;
        13: return
      LineNumberTable:
        line 162: 0
        line 163: 8
        line 162: 13
      LocalVariableTable:
        Start  Length  Slot  Name   Signature
            0      14     0  this   Lshapeless/Strict$$anon$2;
            0      14     1   t$2   Ljava/lang/Object;
    MethodParameters:
      Name                           Flags
      t$2                            final
}
InnerClasses:
  public final #2;                        // class shapeless/Strict$$anon$2
EnclosingMethod: #10.#13                // shapeless.Strict$.apply
Signature: #3                           // Ljava/lang/Object;Lshapeless/Strict<TT;>;
SourceFile: "lazy.scala"
  ScalaInlineInfo: length = 0x18 (unknown attribute)
   01 01 00 04 00 25 00 26 01 00 1C 00 12 01 00 11
   00 12 01 00 0E 00 21 01
  Scala: length = 0x0 (unknown attribute)

