Classfile /Users/mw/Projects/slang-braindump/.jar/jar8/assemble/slang-braindump/assemble/content/shapeless/Strict$.class
  Last modified May 29, 2022; size 1320 bytes
  SHA-256 checksum 747e15cccd21ddfb885353a7bb40212575b48ed065452934c34e3bcad3d8c133
  Compiled from "lazy.scala"
public final class shapeless.Strict$ implements java.io.Serializable
  minor version: 0
  major version: 52
  flags: (0x0031) ACC_PUBLIC, ACC_FINAL, ACC_SUPER
  this_class: #2                          // shapeless/Strict$
  super_class: #4                         // java/lang/Object
  interfaces: 1, fields: 1, methods: 5, attributes: 4
Constant pool:
   #1 = Utf8               shapeless/Strict$
   #2 = Class              #1             // shapeless/Strict$
   #3 = Utf8               java/lang/Object
   #4 = Class              #3             // java/lang/Object
   #5 = Utf8               java/io/Serializable
   #6 = Class              #5             // java/io/Serializable
   #7 = Utf8               lazy.scala
   #8 = Utf8               shapeless/Strict$$anon$2
   #9 = Class              #8             // shapeless/Strict$$anon$2
  #10 = Utf8               MODULE$
  #11 = Utf8               Lshapeless/Strict$;
  #12 = Utf8               <clinit>
  #13 = Utf8               ()V
  #14 = Utf8               <init>
  #15 = NameAndType        #14:#13        // "<init>":()V
  #16 = Methodref          #2.#15         // shapeless/Strict$."<init>":()V
  #17 = NameAndType        #10:#11        // MODULE$:Lshapeless/Strict$;
  #18 = Fieldref           #2.#17         // shapeless/Strict$.MODULE$:Lshapeless/Strict$;
  #19 = Utf8               apply
  #20 = Utf8               (Ljava/lang/Object;)Lshapeless/Strict;
  #21 = Utf8               <T:Ljava/lang/Object;>(TT;)Lshapeless/Strict<TT;>;
  #22 = Utf8               t
  #23 = Utf8               (Ljava/lang/Object;)V
  #24 = NameAndType        #14:#23        // "<init>":(Ljava/lang/Object;)V
  #25 = Methodref          #9.#24         // shapeless/Strict$$anon$2."<init>":(Ljava/lang/Object;)V
  #26 = Utf8               this
  #27 = Utf8               Ljava/lang/Object;
  #28 = Utf8               unapply
  #29 = Utf8               (Lshapeless/Strict;)Lscala/Option;
  #30 = Utf8               <T:Ljava/lang/Object;>(Lshapeless/Strict<TT;>;)Lscala/Option<TT;>;
  #31 = Utf8               lt
  #32 = Utf8               scala/Some
  #33 = Class              #32            // scala/Some
  #34 = Utf8               shapeless/Strict
  #35 = Class              #34            // shapeless/Strict
  #36 = Utf8               value
  #37 = Utf8               ()Ljava/lang/Object;
  #38 = NameAndType        #36:#37        // value:()Ljava/lang/Object;
  #39 = InterfaceMethodref #35.#38        // shapeless/Strict.value:()Ljava/lang/Object;
  #40 = Methodref          #33.#24        // scala/Some."<init>":(Ljava/lang/Object;)V
  #41 = Utf8               Lshapeless/Strict;
  #42 = Utf8               writeReplace
  #43 = Utf8               scala/runtime/ModuleSerializationProxy
  #44 = Class              #43            // scala/runtime/ModuleSerializationProxy
  #45 = Utf8               (Ljava/lang/Class;)V
  #46 = NameAndType        #14:#45        // "<init>":(Ljava/lang/Class;)V
  #47 = Methodref          #44.#46        // scala/runtime/ModuleSerializationProxy."<init>":(Ljava/lang/Class;)V
  #48 = Methodref          #4.#15         // java/lang/Object."<init>":()V
  #49 = Utf8               Code
  #50 = Utf8               LineNumberTable
  #51 = Utf8               LocalVariableTable
  #52 = Utf8               Signature
  #53 = Utf8               MethodParameters
  #54 = Utf8               InnerClasses
  #55 = Utf8               SourceFile
  #56 = Utf8               ScalaInlineInfo
  #57 = Utf8               mkStrict
  #58 = Utf8               ()Lshapeless/Strict;
  #59 = Utf8               Scala
{
  public static final shapeless.Strict$ MODULE$;
    descriptor: Lshapeless/Strict$;
    flags: (0x0019) ACC_PUBLIC, ACC_STATIC, ACC_FINAL

  public static {};
    descriptor: ()V
    flags: (0x0009) ACC_PUBLIC, ACC_STATIC
    Code:
      stack=2, locals=0, args_size=0
         0: new           #2                  // class shapeless/Strict$
         3: dup
         4: invokespecial #16                 // Method "<init>":()V
         7: putstatic     #18                 // Field MODULE$:Lshapeless/Strict$;
        10: return
      LineNumberTable:
        line 160: 0

  public <T extends java.lang.Object> shapeless.Strict<T> apply(T);
    descriptor: (Ljava/lang/Object;)Lshapeless/Strict;
    flags: (0x0001) ACC_PUBLIC
    Code:
      stack=3, locals=2, args_size=2
         0: new           #9                  // class shapeless/Strict$$anon$2
         3: dup
         4: aload_1
         5: invokespecial #25                 // Method shapeless/Strict$$anon$2."<init>":(Ljava/lang/Object;)V
         8: areturn
      LineNumberTable:
        line 162: 0
      LocalVariableTable:
        Start  Length  Slot  Name   Signature
            0       9     0  this   Lshapeless/Strict$;
            0       9     1     t   Ljava/lang/Object;
    Signature: #21                          // <T:Ljava/lang/Object;>(TT;)Lshapeless/Strict<TT;>;
    MethodParameters:
      Name                           Flags
      t                              final

  public <T extends java.lang.Object> scala.Option<T> unapply(shapeless.Strict<T>);
    descriptor: (Lshapeless/Strict;)Lscala/Option;
    flags: (0x0001) ACC_PUBLIC
    Code:
      stack=3, locals=2, args_size=2
         0: new           #33                 // class scala/Some
         3: dup
         4: aload_1
         5: invokeinterface #39,  1           // InterfaceMethod shapeless/Strict.value:()Ljava/lang/Object;
        10: invokespecial #40                 // Method scala/Some."<init>":(Ljava/lang/Object;)V
        13: areturn
      LineNumberTable:
        line 166: 0
      LocalVariableTable:
        Start  Length  Slot  Name   Signature
            0      14     0  this   Lshapeless/Strict$;
            0      14     1    lt   Lshapeless/Strict;
    Signature: #30                          // <T:Ljava/lang/Object;>(Lshapeless/Strict<TT;>;)Lscala/Option<TT;>;
    MethodParameters:
      Name                           Flags
      lt                             final

  private java.lang.Object writeReplace();
    descriptor: ()Ljava/lang/Object;
    flags: (0x0002) ACC_PRIVATE
    Code:
      stack=3, locals=1, args_size=1
         0: new           #44                 // class scala/runtime/ModuleSerializationProxy
         3: dup
         4: ldc           #2                  // class shapeless/Strict$
         6: invokespecial #47                 // Method scala/runtime/ModuleSerializationProxy."<init>":(Ljava/lang/Class;)V
         9: areturn
      LineNumberTable:
        line 160: 0
      LocalVariableTable:
        Start  Length  Slot  Name   Signature
            0      10     0  this   Lshapeless/Strict$;

  private shapeless.Strict$();
    descriptor: ()V
    flags: (0x0002) ACC_PRIVATE
    Code:
      stack=1, locals=1, args_size=1
         0: aload_0
         1: invokespecial #48                 // Method java/lang/Object."<init>":()V
         4: return
      LineNumberTable:
        line 171: 0
        line 160: 4
      LocalVariableTable:
        Start  Length  Slot  Name   Signature
            0       5     0  this   Lshapeless/Strict$;
}
InnerClasses:
  public final #9;                        // class shapeless/Strict$$anon$2
SourceFile: "lazy.scala"
  ScalaInlineInfo: length = 0x1D (unknown attribute)
   01 01 00 05 00 0E 00 0D 01 00 13 00 14 01 00 39
   00 3A 01 00 1C 00 1D 01 00 2A 00 25 01
  Scala: length = 0x0 (unknown attribute)

