Classfile /Users/mw/Projects/slang-braindump/.jar/jar8/assemble/slang-braindump/assemble/content/shapeless/Succ$.class
  Last modified May 29, 2022; size 1160 bytes
  SHA-256 checksum 037fddff424c5cc6f775591343a64a1234eca80f76682aa8f62833138b3c7d5f
  Compiled from "nat.scala"
public final class shapeless.Succ$ implements java.io.Serializable
  minor version: 0
  major version: 52
  flags: (0x0031) ACC_PUBLIC, ACC_FINAL, ACC_SUPER
  this_class: #2                          // shapeless/Succ$
  super_class: #4                         // java/lang/Object
  interfaces: 1, fields: 1, methods: 6, attributes: 3
Constant pool:
   #1 = Utf8               shapeless/Succ$
   #2 = Class              #1             // shapeless/Succ$
   #3 = Utf8               java/lang/Object
   #4 = Class              #3             // java/lang/Object
   #5 = Utf8               java/io/Serializable
   #6 = Class              #5             // java/io/Serializable
   #7 = Utf8               nat.scala
   #8 = Utf8               MODULE$
   #9 = Utf8               Lshapeless/Succ$;
  #10 = Utf8               <clinit>
  #11 = Utf8               ()V
  #12 = Utf8               <init>
  #13 = NameAndType        #12:#11        // "<init>":()V
  #14 = Methodref          #2.#13         // shapeless/Succ$."<init>":()V
  #15 = NameAndType        #8:#9          // MODULE$:Lshapeless/Succ$;
  #16 = Fieldref           #2.#15         // shapeless/Succ$.MODULE$:Lshapeless/Succ$;
  #17 = Utf8               toString
  #18 = Utf8               ()Ljava/lang/String;
  #19 = Utf8               Succ
  #20 = String             #19            // Succ
  #21 = Utf8               this
  #22 = Utf8               apply
  #23 = Utf8               ()Lshapeless/Succ;
  #24 = Utf8               <P::Lshapeless/Nat;>()Lshapeless/Succ<TP;>;
  #25 = Utf8               shapeless/Succ
  #26 = Class              #25            // shapeless/Succ
  #27 = Methodref          #26.#13        // shapeless/Succ."<init>":()V
  #28 = Utf8               unapply
  #29 = Utf8               (Lshapeless/Succ;)Z
  #30 = Utf8               <P::Lshapeless/Nat;>(Lshapeless/Succ<TP;>;)Z
  #31 = Utf8               x$0
  #32 = Utf8               Lshapeless/Succ;
  #33 = Utf8               writeReplace
  #34 = Utf8               ()Ljava/lang/Object;
  #35 = Utf8               scala/runtime/ModuleSerializationProxy
  #36 = Class              #35            // scala/runtime/ModuleSerializationProxy
  #37 = Utf8               (Ljava/lang/Class;)V
  #38 = NameAndType        #12:#37        // "<init>":(Ljava/lang/Class;)V
  #39 = Methodref          #36.#38        // scala/runtime/ModuleSerializationProxy."<init>":(Ljava/lang/Class;)V
  #40 = Methodref          #4.#13         // java/lang/Object."<init>":()V
  #41 = Utf8               Code
  #42 = Utf8               LineNumberTable
  #43 = Utf8               LocalVariableTable
  #44 = Utf8               Signature
  #45 = Utf8               StackMapTable
  #46 = Utf8               MethodParameters
  #47 = Utf8               SourceFile
  #48 = Utf8               ScalaInlineInfo
  #49 = Utf8               Scala
{
  public static final shapeless.Succ$ MODULE$;
    descriptor: Lshapeless/Succ$;
    flags: (0x0019) ACC_PUBLIC, ACC_STATIC, ACC_FINAL

  public static {};
    descriptor: ()V
    flags: (0x0009) ACC_PUBLIC, ACC_STATIC
    Code:
      stack=2, locals=0, args_size=0
         0: new           #2                  // class shapeless/Succ$
         3: dup
         4: invokespecial #14                 // Method "<init>":()V
         7: putstatic     #16                 // Field MODULE$:Lshapeless/Succ$;
        10: return
      LineNumberTable:
        line 38: 0

  public final java.lang.String toString();
    descriptor: ()Ljava/lang/String;
    flags: (0x0011) ACC_PUBLIC, ACC_FINAL
    Code:
      stack=1, locals=1, args_size=1
         0: ldc           #20                 // String Succ
         2: areturn
      LineNumberTable:
        line 38: 0
      LocalVariableTable:
        Start  Length  Slot  Name   Signature
            0       3     0  this   Lshapeless/Succ$;

  public <P extends shapeless.Nat> shapeless.Succ<P> apply();
    descriptor: ()Lshapeless/Succ;
    flags: (0x0001) ACC_PUBLIC
    Code:
      stack=2, locals=1, args_size=1
         0: new           #26                 // class shapeless/Succ
         3: dup
         4: invokespecial #27                 // Method shapeless/Succ."<init>":()V
         7: areturn
      LineNumberTable:
        line 38: 0
      LocalVariableTable:
        Start  Length  Slot  Name   Signature
            0       8     0  this   Lshapeless/Succ$;
    Signature: #24                          // <P::Lshapeless/Nat;>()Lshapeless/Succ<TP;>;

  public <P extends shapeless.Nat> boolean unapply(shapeless.Succ<P>);
    descriptor: (Lshapeless/Succ;)Z
    flags: (0x0001) ACC_PUBLIC
    Code:
      stack=1, locals=2, args_size=2
         0: aload_1
         1: ifnonnull     8
         4: iconst_0
         5: goto          9
         8: iconst_1
         9: ireturn
      StackMapTable: number_of_entries = 2
        frame_type = 8 /* same */
        frame_type = 64 /* same_locals_1_stack_item */
          stack = [ int ]
      LineNumberTable:
        line 38: 0
      LocalVariableTable:
        Start  Length  Slot  Name   Signature
            0      10     0  this   Lshapeless/Succ$;
            0      10     1   x$0   Lshapeless/Succ;
    Signature: #30                          // <P::Lshapeless/Nat;>(Lshapeless/Succ<TP;>;)Z
    MethodParameters:
      Name                           Flags
      x$0                            final

  private java.lang.Object writeReplace();
    descriptor: ()Ljava/lang/Object;
    flags: (0x0002) ACC_PRIVATE
    Code:
      stack=3, locals=1, args_size=1
         0: new           #36                 // class scala/runtime/ModuleSerializationProxy
         3: dup
         4: ldc           #2                  // class shapeless/Succ$
         6: invokespecial #39                 // Method scala/runtime/ModuleSerializationProxy."<init>":(Ljava/lang/Class;)V
         9: areturn
      LineNumberTable:
        line 38: 0
      LocalVariableTable:
        Start  Length  Slot  Name   Signature
            0      10     0  this   Lshapeless/Succ$;

  private shapeless.Succ$();
    descriptor: ()V
    flags: (0x0002) ACC_PRIVATE
    Code:
      stack=1, locals=1, args_size=1
         0: aload_0
         1: invokespecial #40                 // Method java/lang/Object."<init>":()V
         4: return
      LineNumberTable:
        line 38: 0
      LocalVariableTable:
        Start  Length  Slot  Name   Signature
            0       5     0  this   Lshapeless/Succ$;
}
SourceFile: "nat.scala"
  ScalaInlineInfo: length = 0x1D (unknown attribute)
   01 01 00 05 00 0C 00 0B 01 00 16 00 17 01 00 11
   00 12 01 00 1C 00 1D 01 00 21 00 22 01
  Scala: length = 0x0 (unknown attribute)

