Classfile /Users/mw/Projects/slang-braindump/.jar/jar8/assemble/slang-braindump/assemble/content/shapeless/Tuple.class
  Last modified May 29, 2022; size 1548 bytes
  SHA-256 checksum b6b081eedc473ead6de15acfe1024ffddd368850cc2caf08220d93b0abdbb01a
  Compiled from "tuples.scala"
public final class shapeless.Tuple
  minor version: 0
  major version: 52
  flags: (0x0031) ACC_PUBLIC, ACC_FINAL, ACC_SUPER
  this_class: #2                          // shapeless/Tuple
  super_class: #4                         // java/lang/Object
  interfaces: 0, fields: 0, methods: 2, attributes: 4
Constant pool:
   #1 = Utf8               shapeless/Tuple
   #2 = Class              #1             // shapeless/Tuple
   #3 = Utf8               java/lang/Object
   #4 = Class              #3             // java/lang/Object
   #5 = Utf8               tuples.scala
   #6 = Utf8               Lscala/reflect/ScalaSignature;
   #7 = Utf8               bytes
   #8 = Utf8               \u0006\u0005i;Q!\u0002\u0004\t\u0002%1Qa\u0003\u0004\t\u00021AQaE\u0001\u0005\u0002QAQ!F\u0001\u0005\u0002YAQ!F\u0001\u0005\u0002\u0011\u000bQ\u0001V;qY\u0016T\u0011aB\u0001\ng\"\f\u0007/\u001a7fgN\u001c\u0001\u0001\u0005\u0002\u000b\u00035\taAA\u0003UkBdWm\u0005\u0002\u0002\u001bA\u0011a\"E\u0007\u0002\u001f)\t\u0001#A\u0003tG\u0006d\u0017-\u0003\u0002\u0013\u001f\t1\u0011I\\=SK\u001a\fa\u0001P5oSRtD#A\u0005\u0002\t\u0019LG\u000e\\\u000b\u0003/M\"\"\u0001G\u0016\u0015\u0005e\u0011EC\u0001\u000e\u001e!\tYBH\u0004\u0002\u001d;1\u0001\u0001\"B\u000b\u0004\u0001\bq\u0002\u0003B\u0010\'SIr!\u0001I\u0012\u000f\u0005)\t\u0013B\u0001\u0012\u0007\u0003\ry\u0007o]\u0005\u0003I\u0015\nQ\u0001^;qY\u0016T!A\t\u0004\n\u0005\u001dB#\u0001\u0002$jY2T!\u0001J\u0013\u0011\u0005)\u0002dB\u0001\u000f,\u0011\u0015a3\u00011\u0001.\u0003\u0005q\u0007C\u0001\u0006/\u0013\tycAA\u0002OCRL!!\r\u0018\u0003\u00039\u0003\"\u0001H\u001a\u0005\u000bQ\u001a!\u0019A\u001b\u0003\u0003\u0005\u000b\"AN\u001d\u0011\u000599\u0014B\u0001\u001d\u0010\u0005\u001dqu\u000e\u001e5j]\u001e\u0004\"A\u0004\u001e\n\u0005mz!aA!os&\u0011QH\u0010\u0002\u0004\u001fV$\u0018BA A\u0005\u0019!U\r\u001d$oc)\u0011\u0011IB\u0001\ba\u0006\u001c7.Y4f\u0011\u0015\u00195\u00011\u00013\u0003\u0011)G.Z7\u0016\u0005\u0015CFc\u0001$R+R\u0011q)\u0017\u000b\u0003\u0011*\u0003\"!\u0013\u001f\u000f\u0005qQ\u0005\"B\u000b\u0005\u0001\bY\u0005\u0003B\u0010\'\u0019^\u0003BAD\'P\'&\u0011aj\u0004\u0002\u0007)V\u0004H.\u001a\u001a\u0011\u0005A\u0003dB\u0001\u000fR\u0011\u0015\u0011F\u00011\u0001.\u0003\tq\u0017\u0007\u0005\u0002Ua9\u0011A$\u0016\u0005\u0006-\u0012\u0001\r!L\u0001\u0003]J\u0002\"\u0001\b-\u0005\u000bQ\"!\u0019A\u001b\t\u000b\r#\u0001\u0019A,
   #9 = Utf8               shapeless/ops/tuple$Fill
  #10 = Class              #9             // shapeless/ops/tuple$Fill
  #11 = Utf8               shapeless/ops/tuple
  #12 = Class              #11            // shapeless/ops/tuple
  #13 = Utf8               Fill
  #14 = Utf8               fill
  #15 = Utf8               (Lshapeless/Nat;Lshapeless/Nat;Ljava/lang/Object;Lshapeless/ops/tuple$Fill;)Ljava/lang/Object;
  #16 = Utf8               <A:Ljava/lang/Object;>(Lshapeless/Nat;Lshapeless/Nat;TA;Lshapeless/ops/tuple$Fill<Lscala/Tuple2<Lshapeless/Nat;Lshapeless/Nat;>;TA;>;)Ljava/lang/Object;
  #17 = Utf8               n1
  #18 = Utf8               n2
  #19 = Utf8               elem
  #20 = Utf8               shapeless/Tuple$
  #21 = Class              #20            // shapeless/Tuple$
  #22 = Utf8               MODULE$
  #23 = Utf8               Lshapeless/Tuple$;
  #24 = NameAndType        #22:#23        // MODULE$:Lshapeless/Tuple$;
  #25 = Fieldref           #21.#24        // shapeless/Tuple$.MODULE$:Lshapeless/Tuple$;
  #26 = NameAndType        #14:#15        // fill:(Lshapeless/Nat;Lshapeless/Nat;Ljava/lang/Object;Lshapeless/ops/tuple$Fill;)Ljava/lang/Object;
  #27 = Methodref          #21.#26        // shapeless/Tuple$.fill:(Lshapeless/Nat;Lshapeless/Nat;Ljava/lang/Object;Lshapeless/ops/tuple$Fill;)Ljava/lang/Object;
  #28 = Utf8               (Lshapeless/Nat;Ljava/lang/Object;Lshapeless/ops/tuple$Fill;)Ljava/lang/Object;
  #29 = Utf8               <A:Ljava/lang/Object;>(Lshapeless/Nat;TA;Lshapeless/ops/tuple$Fill<Lshapeless/Nat;TA;>;)Ljava/lang/Object;
  #30 = Utf8               n
  #31 = NameAndType        #14:#28        // fill:(Lshapeless/Nat;Ljava/lang/Object;Lshapeless/ops/tuple$Fill;)Ljava/lang/Object;
  #32 = Methodref          #21.#31        // shapeless/Tuple$.fill:(Lshapeless/Nat;Ljava/lang/Object;Lshapeless/ops/tuple$Fill;)Ljava/lang/Object;
  #33 = Utf8               Code
  #34 = Utf8               Signature
  #35 = Utf8               MethodParameters
  #36 = Utf8               InnerClasses
  #37 = Utf8               SourceFile
  #38 = Utf8               RuntimeVisibleAnnotations
  #39 = Utf8               ScalaSig
{
  public static <A extends java.lang.Object> java.lang.Object fill(shapeless.Nat, shapeless.Nat, A, shapeless.ops.tuple$Fill<scala.Tuple2<shapeless.Nat, shapeless.Nat>, A>);
    descriptor: (Lshapeless/Nat;Lshapeless/Nat;Ljava/lang/Object;Lshapeless/ops/tuple$Fill;)Ljava/lang/Object;
    flags: (0x0009) ACC_PUBLIC, ACC_STATIC
    Code:
      stack=5, locals=4, args_size=4
         0: getstatic     #25                 // Field shapeless/Tuple$.MODULE$:Lshapeless/Tuple$;
         3: aload_0
         4: aload_1
         5: aload_2
         6: aload_3
         7: invokevirtual #27                 // Method shapeless/Tuple$.fill:(Lshapeless/Nat;Lshapeless/Nat;Ljava/lang/Object;Lshapeless/ops/tuple$Fill;)Ljava/lang/Object;
        10: areturn
    Signature: #16                          // <A:Ljava/lang/Object;>(Lshapeless/Nat;Lshapeless/Nat;TA;Lshapeless/ops/tuple$Fill<Lscala/Tuple2<Lshapeless/Nat;Lshapeless/Nat;>;TA;>;)Ljava/lang/Object;
    MethodParameters:
      Name                           Flags
      n1                             final
      n2                             final
      elem                           final
      fill                           final

  public static <A extends java.lang.Object> java.lang.Object fill(shapeless.Nat, A, shapeless.ops.tuple$Fill<shapeless.Nat, A>);
    descriptor: (Lshapeless/Nat;Ljava/lang/Object;Lshapeless/ops/tuple$Fill;)Ljava/lang/Object;
    flags: (0x0009) ACC_PUBLIC, ACC_STATIC
    Code:
      stack=4, locals=3, args_size=3
         0: getstatic     #25                 // Field shapeless/Tuple$.MODULE$:Lshapeless/Tuple$;
         3: aload_0
         4: aload_1
         5: aload_2
         6: invokevirtual #32                 // Method shapeless/Tuple$.fill:(Lshapeless/Nat;Ljava/lang/Object;Lshapeless/ops/tuple$Fill;)Ljava/lang/Object;
         9: areturn
    Signature: #29                          // <A:Ljava/lang/Object;>(Lshapeless/Nat;TA;Lshapeless/ops/tuple$Fill<Lshapeless/Nat;TA;>;)Ljava/lang/Object;
    MethodParameters:
      Name                           Flags
      n                              final
      elem                           final
      fill                           final
}
InnerClasses:
  public static #13= #10 of #12;          // Fill=class shapeless/ops/tuple$Fill of class shapeless/ops/tuple
SourceFile: "tuples.scala"
RuntimeVisibleAnnotations:
  0: #6(#7=s#8)
    scala.reflect.ScalaSignature(
      bytes="\u0006\u0005i;Q!\u0002\u0004\t\u0002%1Qa\u0003\u0004\t\u00021AQaE\u0001\u0005\u0002QAQ!F\u0001\u0005\u0002YAQ!F\u0001\u0005\u0002\u0011\u000bQ\u0001V;qY\u0016T\u0011aB\u0001\ng\"\f\u0007/\u001a7fgN\u001c\u0001\u0001\u0005\u0002\u000b\u00035\taAA\u0003UkBdWm\u0005\u0002\u0002\u001bA\u0011a\"E\u0007\u0002\u001f)\t\u0001#A\u0003tG\u0006d\u0017-\u0003\u0002\u0013\u001f\t1\u0011I\\=SK\u001a\fa\u0001P5oSRtD#A\u0005\u0002\t\u0019LG\u000e\\\u000b\u0003/M\"\"\u0001G\u0016\u0015\u0005e\u0011EC\u0001\u000e\u001e!\tYBH\u0004\u0002\u001d;1\u0001\u0001\"B\u000b\u0004\u0001\bq\u0002\u0003B\u0010\'SIr!\u0001I\u0012\u000f\u0005)\t\u0013B\u0001\u0012\u0007\u0003\ry\u0007o]\u0005\u0003I\u0015\nQ\u0001^;qY\u0016T!A\t\u0004\n\u0005\u001dB#\u0001\u0002$jY2T!\u0001J\u0013\u0011\u0005)\u0002dB\u0001\u000f,\u0011\u0015a3\u00011\u0001.\u0003\u0005q\u0007C\u0001\u0006/\u0013\tycAA\u0002OCRL!!\r\u0018\u0003\u00039\u0003\"\u0001H\u001a\u0005\u000bQ\u001a!\u0019A\u001b\u0003\u0003\u0005\u000b\"AN\u001d\u0011\u000599\u0014B\u0001\u001d\u0010\u0005\u001dqu\u000e\u001e5j]\u001e\u0004\"A\u0004\u001e\n\u0005mz!aA!os&\u0011QH\u0010\u0002\u0004\u001fV$\u0018BA A\u0005\u0019!U\r\u001d$oc)\u0011\u0011IB\u0001\ba\u0006\u001c7.Y4f\u0011\u0015\u00195\u00011\u00013\u0003\u0011)G.Z7\u0016\u0005\u0015CFc\u0001$R+R\u0011q)\u0017\u000b\u0003\u0011*\u0003\"!\u0013\u001f\u000f\u0005qQ\u0005\"B\u000b\u0005\u0001\bY\u0005\u0003B\u0010\'\u0019^\u0003BAD\'P\'&\u0011aj\u0004\u0002\u0007)V\u0004H.\u001a\u001a\u0011\u0005A\u0003dB\u0001\u000fR\u0011\u0015\u0011F\u00011\u0001.\u0003\tq\u0017\u0007\u0005\u0002Ua9\u0011A$\u0016\u0005\u0006-\u0012\u0001\r!L\u0001\u0003]J\u0002\"\u0001\b-\u0005\u000bQ\"!\u0019A\u001b\t\u000b\r#\u0001\u0019A,"
    )
  ScalaSig: length = 0x3 (unknown attribute)
   05 02 00
