Classfile /Users/mw/Projects/slang-braindump/.jar/jar8/assemble/slang-braindump/assemble/content/shapeless/Typeable$ValueTypeable.class
  Last modified May 29, 2022; size 4131 bytes
  SHA-256 checksum 90af1a60a5e203d387d70a88da4d028262c1d973cad28a82706a91bacaf3c027
  Compiled from "typeable.scala"
public class shapeless.Typeable$ValueTypeable<T extends java.lang.Object, B extends java.lang.Object> extends java.lang.Object implements shapeless.Typeable<T>, scala.Product
  minor version: 0
  major version: 52
  flags: (0x0021) ACC_PUBLIC, ACC_SUPER
  this_class: #2                          // shapeless/Typeable$ValueTypeable
  super_class: #5                         // java/lang/Object
  interfaces: 2, fields: 2, methods: 17, attributes: 5
Constant pool:
    #1 = Utf8               shapeless/Typeable$ValueTypeable
    #2 = Class              #1            // shapeless/Typeable$ValueTypeable
    #3 = Utf8               <T:Ljava/lang/Object;B:Ljava/lang/Object;>Ljava/lang/Object;Lshapeless/Typeable<TT;>;Lscala/Product;
    #4 = Utf8               java/lang/Object
    #5 = Class              #4            // java/lang/Object
    #6 = Utf8               shapeless/Typeable
    #7 = Class              #6            // shapeless/Typeable
    #8 = Utf8               scala/Product
    #9 = Class              #8            // scala/Product
   #10 = Utf8               typeable.scala
   #11 = Utf8               ValueTypeable
   #12 = Utf8               cB
   #13 = Utf8               Ljava/lang/Class;
   #14 = Utf8               Ljava/lang/Class<TB;>;
   #15 = Utf8               describe
   #16 = Utf8               Ljava/lang/String;
   #17 = Utf8               productElementNames
   #18 = Utf8               ()Lscala/collection/Iterator;
   #19 = Utf8               ()Lscala/collection/Iterator<Ljava/lang/String;>;
   #20 = Utf8               productElementNames$
   #21 = Utf8               (Lscala/Product;)Lscala/collection/Iterator;
   #22 = NameAndType        #20:#21       // productElementNames$:(Lscala/Product;)Lscala/collection/Iterator;
   #23 = InterfaceMethodref #9.#22        // scala/Product.productElementNames$:(Lscala/Product;)Lscala/collection/Iterator;
   #24 = Utf8               this
   #25 = Utf8               Lshapeless/Typeable$ValueTypeable;
   #26 = Utf8               toString
   #27 = Utf8               ()Ljava/lang/String;
   #28 = Utf8               toString$
   #29 = Utf8               (Lshapeless/Typeable;)Ljava/lang/String;
   #30 = NameAndType        #28:#29       // toString$:(Lshapeless/Typeable;)Ljava/lang/String;
   #31 = InterfaceMethodref #7.#30        // shapeless/Typeable.toString$:(Lshapeless/Typeable;)Ljava/lang/String;
   #32 = Utf8               ()Ljava/lang/Class;
   #33 = Utf8               ()Ljava/lang/Class<TB;>;
   #34 = NameAndType        #12:#13       // cB:Ljava/lang/Class;
   #35 = Fieldref           #2.#34        // shapeless/Typeable$ValueTypeable.cB:Ljava/lang/Class;
   #36 = NameAndType        #15:#16       // describe:Ljava/lang/String;
   #37 = Fieldref           #2.#36        // shapeless/Typeable$ValueTypeable.describe:Ljava/lang/String;
   #38 = Utf8               cast
   #39 = Utf8               (Ljava/lang/Object;)Lscala/Option;
   #40 = Utf8               (Ljava/lang/Object;)Lscala/Option<TT;>;
   #41 = Utf8               t
   #42 = NameAndType        #12:#32       // cB:()Ljava/lang/Class;
   #43 = Methodref          #2.#42        // shapeless/Typeable$ValueTypeable.cB:()Ljava/lang/Class;
   #44 = Utf8               java/lang/Class
   #45 = Class              #44           // java/lang/Class
   #46 = Utf8               isInstance
   #47 = Utf8               (Ljava/lang/Object;)Z
   #48 = NameAndType        #46:#47       // isInstance:(Ljava/lang/Object;)Z
   #49 = Methodref          #45.#48       // java/lang/Class.isInstance:(Ljava/lang/Object;)Z
   #50 = Utf8               scala/Some
   #51 = Class              #50           // scala/Some
   #52 = Utf8               <init>
   #53 = Utf8               (Ljava/lang/Object;)V
   #54 = NameAndType        #52:#53       // "<init>":(Ljava/lang/Object;)V
   #55 = Methodref          #51.#54       // scala/Some."<init>":(Ljava/lang/Object;)V
   #56 = Utf8               scala/None$
   #57 = Class              #56           // scala/None$
   #58 = Utf8               MODULE$
   #59 = Utf8               Lscala/None$;
   #60 = NameAndType        #58:#59       // MODULE$:Lscala/None$;
   #61 = Fieldref           #57.#60       // scala/None$.MODULE$:Lscala/None$;
   #62 = Utf8               Ljava/lang/Object;
   #63 = Utf8               scala/Option
   #64 = Class              #63           // scala/Option
   #65 = Utf8               copy
   #66 = Utf8               (Ljava/lang/Class;Ljava/lang/String;)Lshapeless/Typeable$ValueTypeable;
   #67 = Utf8               <T:Ljava/lang/Object;B:Ljava/lang/Object;>(Ljava/lang/Class<TB;>;Ljava/lang/String;)Lshapeless/Typeable$ValueTypeable<TT;TB;>;
   #68 = Utf8               (Ljava/lang/Class;Ljava/lang/String;)V
   #69 = NameAndType        #52:#68       // "<init>":(Ljava/lang/Class;Ljava/lang/String;)V
   #70 = Methodref          #2.#69        // shapeless/Typeable$ValueTypeable."<init>":(Ljava/lang/Class;Ljava/lang/String;)V
   #71 = Utf8               copy$default$1
   #72 = Utf8               <T:Ljava/lang/Object;B:Ljava/lang/Object;>()Ljava/lang/Class<TB;>;
   #73 = Utf8               copy$default$2
   #74 = Utf8               <T:Ljava/lang/Object;B:Ljava/lang/Object;>()Ljava/lang/String;
   #75 = NameAndType        #15:#27       // describe:()Ljava/lang/String;
   #76 = Methodref          #2.#75        // shapeless/Typeable$ValueTypeable.describe:()Ljava/lang/String;
   #77 = Utf8               productPrefix
   #78 = String             #11           // ValueTypeable
   #79 = Utf8               productArity
   #80 = Utf8               ()I
   #81 = Utf8               productElement
   #82 = Utf8               (I)Ljava/lang/Object;
   #83 = Utf8               x$1
   #84 = Utf8               scala/runtime/Statics
   #85 = Class              #84           // scala/runtime/Statics
   #86 = Utf8               ioobe
   #87 = NameAndType        #86:#82       // ioobe:(I)Ljava/lang/Object;
   #88 = Methodref          #85.#87       // scala/runtime/Statics.ioobe:(I)Ljava/lang/Object;
   #89 = Utf8               I
   #90 = Utf8               productIterator
   #91 = Utf8               ()Lscala/collection/Iterator<Ljava/lang/Object;>;
   #92 = Utf8               scala/runtime/ScalaRunTime$
   #93 = Class              #92           // scala/runtime/ScalaRunTime$
   #94 = Utf8               Lscala/runtime/ScalaRunTime$;
   #95 = NameAndType        #58:#94       // MODULE$:Lscala/runtime/ScalaRunTime$;
   #96 = Fieldref           #93.#95       // scala/runtime/ScalaRunTime$.MODULE$:Lscala/runtime/ScalaRunTime$;
   #97 = Utf8               typedProductIterator
   #98 = NameAndType        #97:#21       // typedProductIterator:(Lscala/Product;)Lscala/collection/Iterator;
   #99 = Methodref          #93.#98       // scala/runtime/ScalaRunTime$.typedProductIterator:(Lscala/Product;)Lscala/collection/Iterator;
  #100 = Utf8               canEqual
  #101 = Utf8               productElementName
  #102 = Utf8               (I)Ljava/lang/String;
  #103 = String             #12           // cB
  #104 = String             #15           // describe
  #105 = Utf8               java/lang/String
  #106 = Class              #105          // java/lang/String
  #107 = Utf8               hashCode
  #108 = Utf8               _hashCode
  #109 = Utf8               (Lscala/Product;)I
  #110 = NameAndType        #108:#109     // _hashCode:(Lscala/Product;)I
  #111 = Methodref          #93.#110      // scala/runtime/ScalaRunTime$._hashCode:(Lscala/Product;)I
  #112 = Utf8               equals
  #113 = NameAndType        #112:#47      // equals:(Ljava/lang/Object;)Z
  #114 = Methodref          #5.#113       // java/lang/Object.equals:(Ljava/lang/Object;)Z
  #115 = NameAndType        #100:#47      // canEqual:(Ljava/lang/Object;)Z
  #116 = Methodref          #2.#115       // shapeless/Typeable$ValueTypeable.canEqual:(Ljava/lang/Object;)Z
  #117 = Utf8               (Ljava/lang/Class<TB;>;Ljava/lang/String;)V
  #118 = Utf8               ()V
  #119 = NameAndType        #52:#118      // "<init>":()V
  #120 = Methodref          #5.#119       // java/lang/Object."<init>":()V
  #121 = Utf8               $init$
  #122 = Utf8               (Lshapeless/Typeable;)V
  #123 = NameAndType        #121:#122     // $init$:(Lshapeless/Typeable;)V
  #124 = InterfaceMethodref #7.#123       // shapeless/Typeable.$init$:(Lshapeless/Typeable;)V
  #125 = Utf8               (Lscala/Product;)V
  #126 = NameAndType        #121:#125     // $init$:(Lscala/Product;)V
  #127 = InterfaceMethodref #9.#126       // scala/Product.$init$:(Lscala/Product;)V
  #128 = Utf8               Signature
  #129 = Utf8               Code
  #130 = Utf8               LineNumberTable
  #131 = Utf8               LocalVariableTable
  #132 = Utf8               StackMapTable
  #133 = Utf8               MethodParameters
  #134 = Utf8               InnerClasses
  #135 = Utf8               SourceFile
  #136 = Utf8               ScalaInlineInfo
  #137 = Utf8               Scala
{
  private final java.lang.Class<B> cB;
    descriptor: Ljava/lang/Class;
    flags: (0x0012) ACC_PRIVATE, ACC_FINAL
    Signature: #14                          // Ljava/lang/Class<TB;>;

  private final java.lang.String describe;
    descriptor: Ljava/lang/String;
    flags: (0x0012) ACC_PRIVATE, ACC_FINAL

  public scala.collection.Iterator<java.lang.String> productElementNames();
    descriptor: ()Lscala/collection/Iterator;
    flags: (0x0001) ACC_PUBLIC
    Code:
      stack=1, locals=1, args_size=1
         0: aload_0
         1: invokestatic  #23                 // InterfaceMethod scala/Product.productElementNames$:(Lscala/Product;)Lscala/collection/Iterator;
         4: areturn
      LineNumberTable:
        line 52: 0
      LocalVariableTable:
        Start  Length  Slot  Name   Signature
            0       5     0  this   Lshapeless/Typeable$ValueTypeable;
    Signature: #19                          // ()Lscala/collection/Iterator<Ljava/lang/String;>;

  public java.lang.String toString();
    descriptor: ()Ljava/lang/String;
    flags: (0x0001) ACC_PUBLIC
    Code:
      stack=1, locals=1, args_size=1
         0: aload_0
         1: invokestatic  #31                 // InterfaceMethod shapeless/Typeable.toString$:(Lshapeless/Typeable;)Ljava/lang/String;
         4: areturn
      LineNumberTable:
        line 52: 0
      LocalVariableTable:
        Start  Length  Slot  Name   Signature
            0       5     0  this   Lshapeless/Typeable$ValueTypeable;

  public java.lang.Class<B> cB();
    descriptor: ()Ljava/lang/Class;
    flags: (0x0001) ACC_PUBLIC
    Code:
      stack=1, locals=1, args_size=1
         0: aload_0
         1: getfield      #35                 // Field cB:Ljava/lang/Class;
         4: areturn
      LineNumberTable:
        line 52: 0
      LocalVariableTable:
        Start  Length  Slot  Name   Signature
            0       5     0  this   Lshapeless/Typeable$ValueTypeable;
    Signature: #33                          // ()Ljava/lang/Class<TB;>;

  public java.lang.String describe();
    descriptor: ()Ljava/lang/String;
    flags: (0x0001) ACC_PUBLIC
    Code:
      stack=1, locals=1, args_size=1
         0: aload_0
         1: getfield      #37                 // Field describe:Ljava/lang/String;
         4: areturn
      LineNumberTable:
        line 52: 0
      LocalVariableTable:
        Start  Length  Slot  Name   Signature
            0       5     0  this   Lshapeless/Typeable$ValueTypeable;

  public scala.Option<T> cast(java.lang.Object);
    descriptor: (Ljava/lang/Object;)Lscala/Option;
    flags: (0x0001) ACC_PUBLIC
    Code:
      stack=3, locals=2, args_size=2
         0: aload_1
         1: ifnull        26
         4: aload_0
         5: invokevirtual #43                 // Method cB:()Ljava/lang/Class;
         8: aload_1
         9: invokevirtual #49                 // Method java/lang/Class.isInstance:(Ljava/lang/Object;)Z
        12: ifeq          26
        15: new           #51                 // class scala/Some
        18: dup
        19: aload_1
        20: invokespecial #55                 // Method scala/Some."<init>":(Ljava/lang/Object;)V
        23: goto          29
        26: getstatic     #61                 // Field scala/None$.MODULE$:Lscala/None$;
        29: areturn
      StackMapTable: number_of_entries = 2
        frame_type = 26 /* same */
        frame_type = 66 /* same_locals_1_stack_item */
          stack = [ class scala/Option ]
      LineNumberTable:
        line 54: 0
      LocalVariableTable:
        Start  Length  Slot  Name   Signature
            0      30     0  this   Lshapeless/Typeable$ValueTypeable;
            0      30     1     t   Ljava/lang/Object;
    Signature: #40                          // (Ljava/lang/Object;)Lscala/Option<TT;>;
    MethodParameters:
      Name                           Flags
      t                              final

  public <T extends java.lang.Object, B extends java.lang.Object> shapeless.Typeable$ValueTypeable<T, B> copy(java.lang.Class<B>, java.lang.String);
    descriptor: (Ljava/lang/Class;Ljava/lang/String;)Lshapeless/Typeable$ValueTypeable;
    flags: (0x0001) ACC_PUBLIC
    Code:
      stack=4, locals=3, args_size=3
         0: new           #2                  // class shapeless/Typeable$ValueTypeable
         3: dup
         4: aload_1
         5: aload_2
         6: invokespecial #70                 // Method "<init>":(Ljava/lang/Class;Ljava/lang/String;)V
         9: areturn
      LineNumberTable:
        line 52: 0
      LocalVariableTable:
        Start  Length  Slot  Name   Signature
            0      10     0  this   Lshapeless/Typeable$ValueTypeable;
            0      10     1    cB   Ljava/lang/Class;
            0      10     2 describe   Ljava/lang/String;
    Signature: #67                          // <T:Ljava/lang/Object;B:Ljava/lang/Object;>(Ljava/lang/Class<TB;>;Ljava/lang/String;)Lshapeless/Typeable$ValueTypeable<TT;TB;>;
    MethodParameters:
      Name                           Flags
      cB                             final
      describe                       final

  public <T extends java.lang.Object, B extends java.lang.Object> java.lang.Class<B> copy$default$1();
    descriptor: ()Ljava/lang/Class;
    flags: (0x0001) ACC_PUBLIC
    Code:
      stack=1, locals=1, args_size=1
         0: aload_0
         1: invokevirtual #43                 // Method cB:()Ljava/lang/Class;
         4: areturn
      LineNumberTable:
        line 52: 0
      LocalVariableTable:
        Start  Length  Slot  Name   Signature
            0       5     0  this   Lshapeless/Typeable$ValueTypeable;
    Signature: #72                          // <T:Ljava/lang/Object;B:Ljava/lang/Object;>()Ljava/lang/Class<TB;>;

  public <T extends java.lang.Object, B extends java.lang.Object> java.lang.String copy$default$2();
    descriptor: ()Ljava/lang/String;
    flags: (0x0001) ACC_PUBLIC
    Code:
      stack=1, locals=1, args_size=1
         0: aload_0
         1: invokevirtual #76                 // Method describe:()Ljava/lang/String;
         4: areturn
      LineNumberTable:
        line 52: 0
      LocalVariableTable:
        Start  Length  Slot  Name   Signature
            0       5     0  this   Lshapeless/Typeable$ValueTypeable;
    Signature: #74                          // <T:Ljava/lang/Object;B:Ljava/lang/Object;>()Ljava/lang/String;

  public java.lang.String productPrefix();
    descriptor: ()Ljava/lang/String;
    flags: (0x0001) ACC_PUBLIC
    Code:
      stack=1, locals=1, args_size=1
         0: ldc           #78                 // String ValueTypeable
         2: areturn
      LineNumberTable:
        line 52: 0
      LocalVariableTable:
        Start  Length  Slot  Name   Signature
            0       3     0  this   Lshapeless/Typeable$ValueTypeable;

  public int productArity();
    descriptor: ()I
    flags: (0x0001) ACC_PUBLIC
    Code:
      stack=1, locals=1, args_size=1
         0: iconst_2
         1: ireturn
      LineNumberTable:
        line 52: 0
      LocalVariableTable:
        Start  Length  Slot  Name   Signature
            0       2     0  this   Lshapeless/Typeable$ValueTypeable;

  public java.lang.Object productElement(int);
    descriptor: (I)Ljava/lang/Object;
    flags: (0x0001) ACC_PUBLIC
    Code:
      stack=1, locals=3, args_size=2
         0: iload_1
         1: istore_2
         2: iload_2
         3: tableswitch   { // 0 to 1
                       0: 24
                       1: 31
                 default: 38
            }
        24: aload_0
        25: invokevirtual #43                 // Method cB:()Ljava/lang/Class;
        28: goto          45
        31: aload_0
        32: invokevirtual #76                 // Method describe:()Ljava/lang/String;
        35: goto          45
        38: iload_1
        39: invokestatic  #88                 // Method scala/runtime/Statics.ioobe:(I)Ljava/lang/Object;
        42: goto          45
        45: areturn
      StackMapTable: number_of_entries = 4
        frame_type = 252 /* append */
          offset_delta = 24
          locals = [ int ]
        frame_type = 6 /* same */
        frame_type = 6 /* same */
        frame_type = 70 /* same_locals_1_stack_item */
          stack = [ class java/lang/Object ]
      LineNumberTable:
        line 52: 0
      LocalVariableTable:
        Start  Length  Slot  Name   Signature
            0      46     0  this   Lshapeless/Typeable$ValueTypeable;
            0      46     1   x$1   I
    MethodParameters:
      Name                           Flags
      x$1                            final

  public scala.collection.Iterator<java.lang.Object> productIterator();
    descriptor: ()Lscala/collection/Iterator;
    flags: (0x0001) ACC_PUBLIC
    Code:
      stack=2, locals=1, args_size=1
         0: getstatic     #96                 // Field scala/runtime/ScalaRunTime$.MODULE$:Lscala/runtime/ScalaRunTime$;
         3: aload_0
         4: invokevirtual #99                 // Method scala/runtime/ScalaRunTime$.typedProductIterator:(Lscala/Product;)Lscala/collection/Iterator;
         7: areturn
      LineNumberTable:
        line 52: 0
      LocalVariableTable:
        Start  Length  Slot  Name   Signature
            0       8     0  this   Lshapeless/Typeable$ValueTypeable;
    Signature: #91                          // ()Lscala/collection/Iterator<Ljava/lang/Object;>;

  public boolean canEqual(java.lang.Object);
    descriptor: (Ljava/lang/Object;)Z
    flags: (0x0001) ACC_PUBLIC
    Code:
      stack=1, locals=2, args_size=2
         0: aload_1
         1: instanceof    #2                  // class shapeless/Typeable$ValueTypeable
         4: ireturn
      LineNumberTable:
        line 52: 0
      LocalVariableTable:
        Start  Length  Slot  Name   Signature
            0       5     0  this   Lshapeless/Typeable$ValueTypeable;
            0       5     1   x$1   Ljava/lang/Object;
    MethodParameters:
      Name                           Flags
      x$1                            final

  public java.lang.String productElementName(int);
    descriptor: (I)Ljava/lang/String;
    flags: (0x0001) ACC_PUBLIC
    Code:
      stack=1, locals=3, args_size=2
         0: iload_1
         1: istore_2
         2: iload_2
         3: tableswitch   { // 0 to 1
                       0: 24
                       1: 29
                 default: 34
            }
        24: ldc           #103                // String cB
        26: goto          44
        29: ldc           #104                // String describe
        31: goto          44
        34: iload_1
        35: invokestatic  #88                 // Method scala/runtime/Statics.ioobe:(I)Ljava/lang/Object;
        38: checkcast     #106                // class java/lang/String
        41: goto          44
        44: areturn
      StackMapTable: number_of_entries = 4
        frame_type = 252 /* append */
          offset_delta = 24
          locals = [ int ]
        frame_type = 4 /* same */
        frame_type = 4 /* same */
        frame_type = 73 /* same_locals_1_stack_item */
          stack = [ class java/lang/String ]
      LineNumberTable:
        line 52: 0
      LocalVariableTable:
        Start  Length  Slot  Name   Signature
            0      45     0  this   Lshapeless/Typeable$ValueTypeable;
            0      45     1   x$1   I
    MethodParameters:
      Name                           Flags
      x$1                            final

  public int hashCode();
    descriptor: ()I
    flags: (0x0001) ACC_PUBLIC
    Code:
      stack=2, locals=1, args_size=1
         0: getstatic     #96                 // Field scala/runtime/ScalaRunTime$.MODULE$:Lscala/runtime/ScalaRunTime$;
         3: aload_0
         4: invokevirtual #111                // Method scala/runtime/ScalaRunTime$._hashCode:(Lscala/Product;)I
         7: ireturn
      LineNumberTable:
        line 52: 0
      LocalVariableTable:
        Start  Length  Slot  Name   Signature
            0       8     0  this   Lshapeless/Typeable$ValueTypeable;

  public boolean equals(java.lang.Object);
    descriptor: (Ljava/lang/Object;)Z
    flags: (0x0001) ACC_PUBLIC
    Code:
      stack=2, locals=7, args_size=2
         0: aload_0
         1: aload_1
         2: if_acmpeq     118
         5: aload_1
         6: astore_3
         7: aload_3
         8: instanceof    #2                  // class shapeless/Typeable$ValueTypeable
        11: ifeq          19
        14: iconst_1
        15: istore_2
        16: goto          27
        19: goto          22
        22: iconst_0
        23: istore_2
        24: goto          27
        27: iload_2
        28: ifeq          122
        31: aload_1
        32: checkcast     #2                  // class shapeless/Typeable$ValueTypeable
        35: astore        4
        37: aload_0
        38: invokevirtual #43                 // Method cB:()Ljava/lang/Class;
        41: aload         4
        43: invokevirtual #43                 // Method cB:()Ljava/lang/Class;
        46: astore        5
        48: dup
        49: ifnonnull     61
        52: pop
        53: aload         5
        55: ifnull        69
        58: goto          114
        61: aload         5
        63: invokevirtual #114                // Method java/lang/Object.equals:(Ljava/lang/Object;)Z
        66: ifeq          114
        69: aload_0
        70: invokevirtual #76                 // Method describe:()Ljava/lang/String;
        73: aload         4
        75: invokevirtual #76                 // Method describe:()Ljava/lang/String;
        78: astore        6
        80: dup
        81: ifnonnull     93
        84: pop
        85: aload         6
        87: ifnull        101
        90: goto          114
        93: aload         6
        95: invokevirtual #114                // Method java/lang/Object.equals:(Ljava/lang/Object;)Z
        98: ifeq          114
       101: aload         4
       103: aload_0
       104: invokevirtual #116                // Method canEqual:(Ljava/lang/Object;)Z
       107: ifeq          114
       110: iconst_1
       111: goto          115
       114: iconst_0
       115: ifeq          122
       118: iconst_1
       119: goto          123
       122: iconst_0
       123: ireturn
      StackMapTable: number_of_entries = 12
        frame_type = 253 /* append */
          offset_delta = 19
          locals = [ top, class java/lang/Object ]
        frame_type = 2 /* same */
        frame_type = 255 /* full_frame */
          offset_delta = 4
          locals = [ class shapeless/Typeable$ValueTypeable, class java/lang/Object, int, class java/lang/Object ]
          stack = []
        frame_type = 255 /* full_frame */
          offset_delta = 33
          locals = [ class shapeless/Typeable$ValueTypeable, class java/lang/Object, int, class java/lang/Object, class shapeless/Typeable$ValueTypeable, class java/lang/Class ]
          stack = [ class java/lang/Class ]
        frame_type = 7 /* same */
        frame_type = 255 /* full_frame */
          offset_delta = 23
          locals = [ class shapeless/Typeable$ValueTypeable, class java/lang/Object, int, class java/lang/Object, class shapeless/Typeable$ValueTypeable, class java/lang/Class, class java/lang/String ]
          stack = [ class java/lang/String ]
        frame_type = 7 /* same */
        frame_type = 250 /* chop */
          offset_delta = 12
        frame_type = 64 /* same_locals_1_stack_item */
          stack = [ int ]
        frame_type = 255 /* full_frame */
          offset_delta = 2
          locals = [ class shapeless/Typeable$ValueTypeable, class java/lang/Object ]
          stack = []
        frame_type = 253 /* append */
          offset_delta = 3
          locals = [ int, class java/lang/Object ]
        frame_type = 255 /* full_frame */
          offset_delta = 0
          locals = [ class shapeless/Typeable$ValueTypeable, class java/lang/Object ]
          stack = [ int ]
      LineNumberTable:
        line 52: 0
      LocalVariableTable:
        Start  Length  Slot  Name   Signature
            0     124     0  this   Lshapeless/Typeable$ValueTypeable;
            0     124     1   x$1   Ljava/lang/Object;
    MethodParameters:
      Name                           Flags
      x$1                            final

  public shapeless.Typeable$ValueTypeable(java.lang.Class<B>, java.lang.String);
    descriptor: (Ljava/lang/Class;Ljava/lang/String;)V
    flags: (0x0001) ACC_PUBLIC
    Code:
      stack=2, locals=3, args_size=3
         0: aload_0
         1: aload_1
         2: putfield      #35                 // Field cB:Ljava/lang/Class;
         5: aload_0
         6: aload_2
         7: putfield      #37                 // Field describe:Ljava/lang/String;
        10: aload_0
        11: invokespecial #120                // Method java/lang/Object."<init>":()V
        14: aload_0
        15: invokestatic  #124                // InterfaceMethod shapeless/Typeable.$init$:(Lshapeless/Typeable;)V
        18: aload_0
        19: invokestatic  #127                // InterfaceMethod scala/Product.$init$:(Lscala/Product;)V
        22: return
      LineNumberTable:
        line 52: 0
      LocalVariableTable:
        Start  Length  Slot  Name   Signature
            0      23     0  this   Lshapeless/Typeable$ValueTypeable;
            0      23     1    cB   Ljava/lang/Class;
            0      23     2 describe   Ljava/lang/String;
    Signature: #117                         // (Ljava/lang/Class<TB;>;Ljava/lang/String;)V
    MethodParameters:
      Name                           Flags
      cB                             final
      describe                       final
}
InnerClasses:
  public static #11= #2 of #7;            // ValueTypeable=class shapeless/Typeable$ValueTypeable of class shapeless/Typeable
Signature: #3                           // <T:Ljava/lang/Object;B:Ljava/lang/Object;>Ljava/lang/Object;Lshapeless/Typeable<TT;>;Lscala/Product;
SourceFile: "typeable.scala"
  ScalaInlineInfo: length = 0x59 (unknown attribute)
   01 00 00 11 00 34 00 44 00 00 0C 00 20 00 00 64
   00 2F 00 00 26 00 27 00 00 47 00 20 00 00 49 00
   1B 00 00 41 00 42 00 00 0F 00 1B 00 00 70 00 2F
   00 00 6B 00 50 00 00 4F 00 50 00 00 51 00 52 00
   00 65 00 66 00 00 11 00 12 00 00 5A 00 12 00 00
   4D 00 1B 00 00 1A 00 1B 00
  Scala: length = 0x0 (unknown attribute)

