Classfile /Users/mw/Projects/slang-braindump/.jar/jar8/assemble/slang-braindump/assemble/content/shapeless/Typeable$$anon$6.class
  Last modified May 29, 2022; size 2069 bytes
  SHA-256 checksum f9af1fc133389855ba748f431d430f5a18c93b6b5647fdf9798dc7defd7aeb2e
  Compiled from "typeable.scala"
public final class shapeless.Typeable$$anon$6 extends java.lang.Object implements shapeless.Typeable<T>
  minor version: 0
  major version: 52
  flags: (0x0031) ACC_PUBLIC, ACC_FINAL, ACC_SUPER
  this_class: #2                          // shapeless/Typeable$$anon$6
  super_class: #5                         // java/lang/Object
  interfaces: 1, fields: 3, methods: 5, attributes: 6
Constant pool:
    #1 = Utf8               shapeless/Typeable$$anon$6
    #2 = Class              #1            // shapeless/Typeable$$anon$6
    #3 = Utf8               Ljava/lang/Object;Lshapeless/Typeable<TT;>;
    #4 = Utf8               java/lang/Object
    #5 = Class              #4            // java/lang/Object
    #6 = Utf8               shapeless/Typeable
    #7 = Class              #6            // shapeless/Typeable
    #8 = Utf8               typeable.scala
    #9 = Utf8               shapeless/Typeable$
   #10 = Class              #9            // shapeless/Typeable$
   #11 = Utf8               referenceSingletonTypeable
   #12 = Utf8               (Ljava/lang/Object;Ljava/lang/String;Z)Lshapeless/Typeable;
   #13 = NameAndType        #11:#12       // referenceSingletonTypeable:(Ljava/lang/Object;Ljava/lang/String;Z)Lshapeless/Typeable;
   #14 = Utf8               value$2
   #15 = Utf8               Ljava/lang/Object;
   #16 = Utf8               name$3
   #17 = Utf8               Ljava/lang/String;
   #18 = Utf8               serializable$1
   #19 = Utf8               Z
   #20 = Utf8               toString
   #21 = Utf8               ()Ljava/lang/String;
   #22 = Utf8               toString$
   #23 = Utf8               (Lshapeless/Typeable;)Ljava/lang/String;
   #24 = NameAndType        #22:#23       // toString$:(Lshapeless/Typeable;)Ljava/lang/String;
   #25 = InterfaceMethodref #7.#24        // shapeless/Typeable.toString$:(Lshapeless/Typeable;)Ljava/lang/String;
   #26 = Utf8               this
   #27 = Utf8               Lshapeless/Typeable$$anon$6;
   #28 = Utf8               cast
   #29 = Utf8               (Ljava/lang/Object;)Lscala/Option;
   #30 = Utf8               (Ljava/lang/Object;)Lscala/Option<TT;>;
   #31 = Utf8               t
   #32 = NameAndType        #14:#15       // value$2:Ljava/lang/Object;
   #33 = Fieldref           #2.#32        // shapeless/Typeable$$anon$6.value$2:Ljava/lang/Object;
   #34 = Utf8               scala/Some
   #35 = Class              #34           // scala/Some
   #36 = Utf8               <init>
   #37 = Utf8               (Ljava/lang/Object;)V
   #38 = NameAndType        #36:#37       // "<init>":(Ljava/lang/Object;)V
   #39 = Methodref          #35.#38       // scala/Some."<init>":(Ljava/lang/Object;)V
   #40 = Utf8               scala/None$
   #41 = Class              #40           // scala/None$
   #42 = Utf8               MODULE$
   #43 = Utf8               Lscala/None$;
   #44 = NameAndType        #42:#43       // MODULE$:Lscala/None$;
   #45 = Fieldref           #41.#44       // scala/None$.MODULE$:Lscala/None$;
   #46 = Utf8               scala/Option
   #47 = Class              #46           // scala/Option
   #48 = Utf8               describe
   #49 = Utf8               java/lang/StringBuilder
   #50 = Class              #49           // java/lang/StringBuilder
   #51 = Integer            5
   #52 = Utf8               (I)V
   #53 = NameAndType        #36:#52       // "<init>":(I)V
   #54 = Methodref          #50.#53       // java/lang/StringBuilder."<init>":(I)V
   #55 = NameAndType        #16:#17       // name$3:Ljava/lang/String;
   #56 = Fieldref           #2.#55        // shapeless/Typeable$$anon$6.name$3:Ljava/lang/String;
   #57 = Utf8               append
   #58 = Utf8               (Ljava/lang/String;)Ljava/lang/StringBuilder;
   #59 = NameAndType        #57:#58       // append:(Ljava/lang/String;)Ljava/lang/StringBuilder;
   #60 = Methodref          #50.#59       // java/lang/StringBuilder.append:(Ljava/lang/String;)Ljava/lang/StringBuilder;
   #61 = Utf8               .type
   #62 = String             #61           // .type
   #63 = NameAndType        #20:#21       // toString:()Ljava/lang/String;
   #64 = Methodref          #50.#63       // java/lang/StringBuilder.toString:()Ljava/lang/String;
   #65 = Utf8               writeObject
   #66 = Utf8               (Ljava/io/ObjectOutputStream;)V
   #67 = Utf8               java/io/IOException
   #68 = Class              #67           // java/io/IOException
   #69 = Utf8               out
   #70 = NameAndType        #18:#19       // serializable$1:Z
   #71 = Fieldref           #2.#70        // shapeless/Typeable$$anon$6.serializable$1:Z
   #72 = Utf8               java/io/ObjectOutputStream
   #73 = Class              #72           // java/io/ObjectOutputStream
   #74 = Utf8               defaultWriteObject
   #75 = Utf8               ()V
   #76 = NameAndType        #74:#75       // defaultWriteObject:()V
   #77 = Methodref          #73.#76       // java/io/ObjectOutputStream.defaultWriteObject:()V
   #78 = Utf8               java/io/NotSerializableException
   #79 = Class              #78           // java/io/NotSerializableException
   #80 = String             #11           // referenceSingletonTypeable
   #81 = Utf8               (Ljava/lang/String;)V
   #82 = NameAndType        #36:#81       // "<init>":(Ljava/lang/String;)V
   #83 = Methodref          #79.#82       // java/io/NotSerializableException."<init>":(Ljava/lang/String;)V
   #84 = Utf8               Ljava/io/ObjectOutputStream;
   #85 = Utf8               (Ljava/lang/Object;Ljava/lang/String;Z)V
   #86 = NameAndType        #36:#75       // "<init>":()V
   #87 = Methodref          #5.#86        // java/lang/Object."<init>":()V
   #88 = Utf8               $init$
   #89 = Utf8               (Lshapeless/Typeable;)V
   #90 = NameAndType        #88:#89       // $init$:(Lshapeless/Typeable;)V
   #91 = InterfaceMethodref #7.#90        // shapeless/Typeable.$init$:(Lshapeless/Typeable;)V
   #92 = Utf8               Code
   #93 = Utf8               LineNumberTable
   #94 = Utf8               LocalVariableTable
   #95 = Utf8               StackMapTable
   #96 = Utf8               Signature
   #97 = Utf8               MethodParameters
   #98 = Utf8               Exceptions
   #99 = Utf8               InnerClasses
  #100 = Utf8               EnclosingMethod
  #101 = Utf8               SourceFile
  #102 = Utf8               ScalaInlineInfo
  #103 = Utf8               Scala
{
  private final java.lang.Object value$2;
    descriptor: Ljava/lang/Object;
    flags: (0x0012) ACC_PRIVATE, ACC_FINAL

  private final java.lang.String name$3;
    descriptor: Ljava/lang/String;
    flags: (0x0012) ACC_PRIVATE, ACC_FINAL

  private final boolean serializable$1;
    descriptor: Z
    flags: (0x0012) ACC_PRIVATE, ACC_FINAL

  public java.lang.String toString();
    descriptor: ()Ljava/lang/String;
    flags: (0x0001) ACC_PUBLIC
    Code:
      stack=1, locals=1, args_size=1
         0: aload_0
         1: invokestatic  #25                 // InterfaceMethod shapeless/Typeable.toString$:(Lshapeless/Typeable;)Ljava/lang/String;
         4: areturn
      LineNumberTable:
        line 149: 0
      LocalVariableTable:
        Start  Length  Slot  Name   Signature
            0       5     0  this   Lshapeless/Typeable$$anon$6;

  public scala.Option<T> cast(java.lang.Object);
    descriptor: (Ljava/lang/Object;)Lscala/Option;
    flags: (0x0001) ACC_PUBLIC
    Code:
      stack=3, locals=2, args_size=2
         0: aload_1
         1: aload_0
         2: getfield      #33                 // Field value$2:Ljava/lang/Object;
         5: if_acmpne     22
         8: new           #35                 // class scala/Some
        11: dup
        12: aload_0
        13: getfield      #33                 // Field value$2:Ljava/lang/Object;
        16: invokespecial #39                 // Method scala/Some."<init>":(Ljava/lang/Object;)V
        19: goto          25
        22: getstatic     #45                 // Field scala/None$.MODULE$:Lscala/None$;
        25: areturn
      StackMapTable: number_of_entries = 2
        frame_type = 22 /* same */
        frame_type = 66 /* same_locals_1_stack_item */
          stack = [ class scala/Option ]
      LineNumberTable:
        line 152: 0
      LocalVariableTable:
        Start  Length  Slot  Name   Signature
            0      26     0  this   Lshapeless/Typeable$$anon$6;
            0      26     1     t   Ljava/lang/Object;
    Signature: #30                          // (Ljava/lang/Object;)Lscala/Option<TT;>;
    MethodParameters:
      Name                           Flags
      t                              final

  public java.lang.String describe();
    descriptor: ()Ljava/lang/String;
    flags: (0x0001) ACC_PUBLIC
    Code:
      stack=3, locals=1, args_size=1
         0: new           #50                 // class java/lang/StringBuilder
         3: dup
         4: ldc           #51                 // int 5
         6: invokespecial #54                 // Method java/lang/StringBuilder."<init>":(I)V
         9: aload_0
        10: getfield      #56                 // Field name$3:Ljava/lang/String;
        13: invokevirtual #60                 // Method java/lang/StringBuilder.append:(Ljava/lang/String;)Ljava/lang/StringBuilder;
        16: ldc           #62                 // String .type
        18: invokevirtual #60                 // Method java/lang/StringBuilder.append:(Ljava/lang/String;)Ljava/lang/StringBuilder;
        21: invokevirtual #64                 // Method java/lang/StringBuilder.toString:()Ljava/lang/String;
        24: areturn
      LineNumberTable:
        line 154: 0
      LocalVariableTable:
        Start  Length  Slot  Name   Signature
            0      25     0  this   Lshapeless/Typeable$$anon$6;

  private void writeObject(java.io.ObjectOutputStream) throws java.io.IOException;
    descriptor: (Ljava/io/ObjectOutputStream;)V
    flags: (0x0002) ACC_PRIVATE
    Code:
      stack=3, locals=2, args_size=2
         0: aload_0
         1: getfield      #71                 // Field serializable$1:Z
         4: ifeq          14
         7: aload_1
         8: invokevirtual #77                 // Method java/io/ObjectOutputStream.defaultWriteObject:()V
        11: goto          24
        14: new           #79                 // class java/io/NotSerializableException
        17: dup
        18: ldc           #80                 // String referenceSingletonTypeable
        20: invokespecial #83                 // Method java/io/NotSerializableException."<init>":(Ljava/lang/String;)V
        23: athrow
        24: return
      StackMapTable: number_of_entries = 2
        frame_type = 14 /* same */
        frame_type = 9 /* same */
      LineNumberTable:
        line 158: 0
        line 159: 14
      LocalVariableTable:
        Start  Length  Slot  Name   Signature
            0      25     0  this   Lshapeless/Typeable$$anon$6;
            0      25     1   out   Ljava/io/ObjectOutputStream;
    Exceptions:
      throws java.io.IOException
    MethodParameters:
      Name                           Flags
      out                            final

  public shapeless.Typeable$$anon$6(java.lang.Object, java.lang.String, boolean);
    descriptor: (Ljava/lang/Object;Ljava/lang/String;Z)V
    flags: (0x0001) ACC_PUBLIC
    Code:
      stack=2, locals=4, args_size=4
         0: aload_0
         1: aload_1
         2: putfield      #33                 // Field value$2:Ljava/lang/Object;
         5: aload_0
         6: aload_2
         7: putfield      #56                 // Field name$3:Ljava/lang/String;
        10: aload_0
        11: iload_3
        12: putfield      #71                 // Field serializable$1:Z
        15: aload_0
        16: invokespecial #87                 // Method java/lang/Object."<init>":()V
        19: aload_0
        20: invokestatic  #91                 // InterfaceMethod shapeless/Typeable.$init$:(Lshapeless/Typeable;)V
        23: return
      LineNumberTable:
        line 148: 0
        line 149: 15
      LocalVariableTable:
        Start  Length  Slot  Name   Signature
            0      24     0  this   Lshapeless/Typeable$$anon$6;
            0      24     1 value$2   Ljava/lang/Object;
            0      24     2 name$3   Ljava/lang/String;
            0      24     3 serializable$1   Z
    MethodParameters:
      Name                           Flags
      value$2                        final
      name$3                         final
      serializable$1                 final
}
InnerClasses:
  public final #2;                        // class shapeless/Typeable$$anon$6
EnclosingMethod: #10.#13                // shapeless.Typeable$.referenceSingletonTypeable
Signature: #3                           // Ljava/lang/Object;Lshapeless/Typeable<TT;>;
SourceFile: "typeable.scala"
  ScalaInlineInfo: length = 0x1D (unknown attribute)
   01 01 00 05 00 24 00 55 01 00 1C 00 1D 01 00 30
   00 15 01 00 14 00 15 01 00 41 00 42 01
  Scala: length = 0x0 (unknown attribute)

