Classfile /Users/mw/Projects/slang-braindump/.jar/jar8/assemble/slang-braindump/assemble/content/shapeless/TypeCase.class
  Last modified May 29, 2022; size 1283 bytes
  SHA-256 checksum 2b1b86f362f897395d1a5168e8c5206186c29034d7f1477098b6c90ae24bba49
  Compiled from "typeable.scala"
public interface shapeless.TypeCase<T extends java.lang.Object> extends java.io.Serializable
  minor version: 0
  major version: 52
  flags: (0x0601) ACC_PUBLIC, ACC_INTERFACE, ACC_ABSTRACT
  this_class: #2                          // shapeless/TypeCase
  super_class: #5                         // java/lang/Object
  interfaces: 1, fields: 0, methods: 2, attributes: 5
Constant pool:
   #1 = Utf8               shapeless/TypeCase
   #2 = Class              #1             // shapeless/TypeCase
   #3 = Utf8               <T:Ljava/lang/Object;>Ljava/lang/Object;Ljava/io/Serializable;
   #4 = Utf8               java/lang/Object
   #5 = Class              #4             // java/lang/Object
   #6 = Utf8               java/io/Serializable
   #7 = Class              #6             // java/io/Serializable
   #8 = Utf8               typeable.scala
   #9 = Utf8               Lscala/reflect/ScalaSignature;
  #10 = Utf8               bytes
  #11 = Utf8               \u0006\u0005E3qa\u0002\u0005\u0011\u0002G\u00051\u0002C\u0003 \u0001\u0019\u0005\u0001eB\u00032\u0011!\u0005!GB\u0003\b\u0011!\u0005A\u0007C\u0003=\u0007\u0011\u0005Q\bC\u0003?\u0007\u0011\u0005q\bC\u0004J\u0007\u0005\u0005I\u0011\u0002&\u0003\u0011QK\b/Z\"bg\u0016T\u0011!C\u0001\ng\"\f\u0007/\u001a7fgN\u001c\u0001!\u0006\u0002\rMM\u0019\u0001!D\n\u0011\u00059\tR\"A\b\u000b\u0003A\tQa]2bY\u0006L!AE\b\u0003\r\u0005s\u0017PU3g!\t!BD\u0004\u0002\u001659\u0011a#G\u0007\u0002/)\u0011\u0001DC\u0001\u0007yI|w\u000e\u001e \n\u0003AI!aG\b\u0002\u000fA\f7m[1hK&\u0011QD\b\u0002\r\'\u0016\u0014\u0018.\u00197ju\u0006\u0014G.\u001a\u0006\u00037=\tq!\u001e8baBd\u0017\u0010\u0006\u0002\"_A\u0019aB\t\u0013\n\u0005\rz!AB(qi&|g\u000e\u0005\u0002&M1\u0001A!B\u0014\u0001\u0005\u0004A#!\u0001+\u0012\u0005%b\u0003C\u0001\b+\u0013\tYsBA\u0004O_RD\u0017N\\4\u0011\u00059i\u0013B\u0001\u0018\u0010\u0005\r\te.\u001f\u0005\u0006a\u0005\u0001\r\u0001L\u0001\u0002i\u0006AA+\u001f9f\u0007\u0006\u001cX\r\u0005\u00024\u00075\t\u0001bE\u0002\u0004\u001bU\u0002\"AN\u001e\u000e\u0003]R!\u0001O\u001d\u0002\u0005%|\'\"\u0001\u001e\u0002\t)\fg/Y\u0005\u0003;]\na\u0001P5oSRtD#\u0001\u001a\u0002\u000b\u0005\u0004\b\u000f\\=\u0016\u0005\u0001\u001bECA!E!\r\u0019\u0004A\u0011\t\u0003K\r#QaJ\u0003C\u0002!BQ!R\u0003A\u0004\u0019\u000b!\u0001\u001e;\u0011\u0007M:%)\u0003\u0002I\u0011\tAA+\u001f9fC\ndW-\u0001\u0007xe&$XMU3qY\u0006\u001cW\rF\u0001L!\tau*D\u0001N\u0015\tq\u0015(\u0001\u0003mC:<\u0017B\u0001)N\u0005\u0019y%M[3di\u0002
  #12 = Utf8               apply
  #13 = Utf8               (Lshapeless/Typeable;)Lshapeless/TypeCase;
  #14 = Utf8               <T:Ljava/lang/Object;>(Lshapeless/Typeable<TT;>;)Lshapeless/TypeCase<TT;>;
  #15 = Utf8               tt
  #16 = Utf8               shapeless/TypeCase$
  #17 = Class              #16            // shapeless/TypeCase$
  #18 = Utf8               MODULE$
  #19 = Utf8               Lshapeless/TypeCase$;
  #20 = NameAndType        #18:#19        // MODULE$:Lshapeless/TypeCase$;
  #21 = Fieldref           #17.#20        // shapeless/TypeCase$.MODULE$:Lshapeless/TypeCase$;
  #22 = NameAndType        #12:#13        // apply:(Lshapeless/Typeable;)Lshapeless/TypeCase;
  #23 = Methodref          #17.#22        // shapeless/TypeCase$.apply:(Lshapeless/Typeable;)Lshapeless/TypeCase;
  #24 = Utf8               unapply
  #25 = Utf8               (Ljava/lang/Object;)Lscala/Option;
  #26 = Utf8               (Ljava/lang/Object;)Lscala/Option<TT;>;
  #27 = Utf8               t
  #28 = Utf8               Code
  #29 = Utf8               Signature
  #30 = Utf8               MethodParameters
  #31 = Utf8               SourceFile
  #32 = Utf8               RuntimeVisibleAnnotations
  #33 = Utf8               ScalaInlineInfo
  #34 = Utf8               ScalaSig
{
  public static <T extends java.lang.Object> shapeless.TypeCase<T> apply(shapeless.Typeable<T>);
    descriptor: (Lshapeless/Typeable;)Lshapeless/TypeCase;
    flags: (0x0009) ACC_PUBLIC, ACC_STATIC
    Code:
      stack=2, locals=1, args_size=1
         0: getstatic     #21                 // Field shapeless/TypeCase$.MODULE$:Lshapeless/TypeCase$;
         3: aload_0
         4: invokevirtual #23                 // Method shapeless/TypeCase$.apply:(Lshapeless/Typeable;)Lshapeless/TypeCase;
         7: areturn
    Signature: #14                          // <T:Ljava/lang/Object;>(Lshapeless/Typeable<TT;>;)Lshapeless/TypeCase<TT;>;
    MethodParameters:
      Name                           Flags
      tt                             final

  public abstract scala.Option<T> unapply(java.lang.Object);
    descriptor: (Ljava/lang/Object;)Lscala/Option;
    flags: (0x0401) ACC_PUBLIC, ACC_ABSTRACT
    Signature: #26                          // (Ljava/lang/Object;)Lscala/Option<TT;>;
    MethodParameters:
      Name                           Flags
      t                              final
}
Signature: #3                           // <T:Ljava/lang/Object;>Ljava/lang/Object;Ljava/io/Serializable;
SourceFile: "typeable.scala"
RuntimeVisibleAnnotations:
  0: #9(#10=s#11)
    scala.reflect.ScalaSignature(
      bytes="\u0006\u0005E3qa\u0002\u0005\u0011\u0002G\u00051\u0002C\u0003 \u0001\u0019\u0005\u0001eB\u00032\u0011!\u0005!GB\u0003\b\u0011!\u0005A\u0007C\u0003=\u0007\u0011\u0005Q\bC\u0003?\u0007\u0011\u0005q\bC\u0004J\u0007\u0005\u0005I\u0011\u0002&\u0003\u0011QK\b/Z\"bg\u0016T\u0011!C\u0001\ng\"\f\u0007/\u001a7fgN\u001c\u0001!\u0006\u0002\rMM\u0019\u0001!D\n\u0011\u00059\tR\"A\b\u000b\u0003A\tQa]2bY\u0006L!AE\b\u0003\r\u0005s\u0017PU3g!\t!BD\u0004\u0002\u001659\u0011a#G\u0007\u0002/)\u0011\u0001DC\u0001\u0007yI|w\u000e\u001e \n\u0003AI!aG\b\u0002\u000fA\f7m[1hK&\u0011QD\b\u0002\r\'\u0016\u0014\u0018.\u00197ju\u0006\u0014G.\u001a\u0006\u00037=\tq!\u001e8baBd\u0017\u0010\u0006\u0002\"_A\u0019aB\t\u0013\n\u0005\rz!AB(qi&|g\u000e\u0005\u0002&M1\u0001A!B\u0014\u0001\u0005\u0004A#!\u0001+\u0012\u0005%b\u0003C\u0001\b+\u0013\tYsBA\u0004O_RD\u0017N\\4\u0011\u00059i\u0013B\u0001\u0018\u0010\u0005\r\te.\u001f\u0005\u0006a\u0005\u0001\r\u0001L\u0001\u0002i\u0006AA+\u001f9f\u0007\u0006\u001cX\r\u0005\u00024\u00075\t\u0001bE\u0002\u0004\u001bU\u0002\"AN\u001e\u000e\u0003]R!\u0001O\u001d\u0002\u0005%|\'\"\u0001\u001e\u0002\t)\fg/Y\u0005\u0003;]\na\u0001P5oSRtD#\u0001\u001a\u0002\u000b\u0005\u0004\b\u000f\\=\u0016\u0005\u0001\u001bECA!E!\r\u0019\u0004A\u0011\t\u0003K\r#QaJ\u0003C\u0002!BQ!R\u0003A\u0004\u0019\u000b!\u0001\u001e;\u0011\u0007M:%)\u0003\u0002I\u0011\tAA+\u001f9fC\ndW-\u0001\u0007xe&$XMU3qY\u0006\u001cW\rF\u0001L!\tau*D\u0001N\u0015\tq\u0015(\u0001\u0003mC:<\u0017B\u0001)N\u0005\u0019y%M[3di\u0002"
    )
  ScalaInlineInfo: length = 0x9 (unknown attribute)
   01 00 00 01 00 18 00 19 00
  ScalaSig: length = 0x3 (unknown attribute)
   05 02 00
