Classfile /Users/mw/Projects/slang-braindump/.jar/jar8/assemble/slang-braindump/assemble/content/shapeless/UnaryTCConstraint$.class
  Last modified May 29, 2022; size 2799 bytes
  SHA-256 checksum 14d26e81474f1181fa313ff0b71eba36a914f54e4dfae6f52a2f807460915968
  Compiled from "hlistconstraints.scala"
public final class shapeless.UnaryTCConstraint$ implements shapeless.LowPriorityUnaryTCConstraint,java.io.Serializable
  minor version: 0
  major version: 52
  flags: (0x0031) ACC_PUBLIC, ACC_FINAL, ACC_SUPER
  this_class: #2                          // shapeless/UnaryTCConstraint$
  super_class: #4                         // java/lang/Object
  interfaces: 2, fields: 1, methods: 9, attributes: 4
Constant pool:
   #1 = Utf8               shapeless/UnaryTCConstraint$
   #2 = Class              #1             // shapeless/UnaryTCConstraint$
   #3 = Utf8               java/lang/Object
   #4 = Class              #3             // java/lang/Object
   #5 = Utf8               shapeless/LowPriorityUnaryTCConstraint
   #6 = Class              #5             // shapeless/LowPriorityUnaryTCConstraint
   #7 = Utf8               java/io/Serializable
   #8 = Class              #7             // java/io/Serializable
   #9 = Utf8               hlistconstraints.scala
  #10 = Utf8               shapeless/UnaryTCConstraint$$anon$4
  #11 = Class              #10            // shapeless/UnaryTCConstraint$$anon$4
  #12 = Utf8               shapeless/UnaryTCConstraint$$anon$5
  #13 = Class              #12            // shapeless/UnaryTCConstraint$$anon$5
  #14 = Utf8               MODULE$
  #15 = Utf8               Lshapeless/UnaryTCConstraint$;
  #16 = Utf8               <clinit>
  #17 = Utf8               ()V
  #18 = Utf8               <init>
  #19 = NameAndType        #18:#17        // "<init>":()V
  #20 = Methodref          #2.#19         // shapeless/UnaryTCConstraint$."<init>":()V
  #21 = NameAndType        #14:#15        // MODULE$:Lshapeless/UnaryTCConstraint$;
  #22 = Fieldref           #2.#21         // shapeless/UnaryTCConstraint$.MODULE$:Lshapeless/UnaryTCConstraint$;
  #23 = Utf8               shapeless/LowPriorityUnaryTCConstraint0
  #24 = Class              #23            // shapeless/LowPriorityUnaryTCConstraint0
  #25 = Utf8               $init$
  #26 = Utf8               (Lshapeless/LowPriorityUnaryTCConstraint0;)V
  #27 = NameAndType        #25:#26        // $init$:(Lshapeless/LowPriorityUnaryTCConstraint0;)V
  #28 = InterfaceMethodref #24.#27        // shapeless/LowPriorityUnaryTCConstraint0.$init$:(Lshapeless/LowPriorityUnaryTCConstraint0;)V
  #29 = Utf8               (Lshapeless/LowPriorityUnaryTCConstraint;)V
  #30 = NameAndType        #25:#29        // $init$:(Lshapeless/LowPriorityUnaryTCConstraint;)V
  #31 = InterfaceMethodref #6.#30         // shapeless/LowPriorityUnaryTCConstraint.$init$:(Lshapeless/LowPriorityUnaryTCConstraint;)V
  #32 = Utf8               hnilUnaryTC
  #33 = Utf8               ()Lshapeless/UnaryTCConstraint;
  #34 = Utf8               <TC:Ljava/lang/Object;>()Lshapeless/UnaryTCConstraint<Lshapeless/HNil;TTC;>;
  #35 = Utf8               hnilUnaryTC$
  #36 = Utf8               (Lshapeless/LowPriorityUnaryTCConstraint;)Lshapeless/UnaryTCConstraint;
  #37 = NameAndType        #35:#36        // hnilUnaryTC$:(Lshapeless/LowPriorityUnaryTCConstraint;)Lshapeless/UnaryTCConstraint;
  #38 = InterfaceMethodref #6.#37         // shapeless/LowPriorityUnaryTCConstraint.hnilUnaryTC$:(Lshapeless/LowPriorityUnaryTCConstraint;)Lshapeless/UnaryTCConstraint;
  #39 = Utf8               this
  #40 = Utf8               hlistConstUnaryTC
  #41 = Utf8               (Lshapeless/UnaryTCConstraint;)Lshapeless/UnaryTCConstraint;
  #42 = Utf8               <H:Ljava/lang/Object;T::Lshapeless/HList;>(Lshapeless/UnaryTCConstraint<TT;*>;)Lshapeless/UnaryTCConstraint<Lshapeless/$colon$colon<TH;TT;>;*>;
  #43 = Utf8               utct
  #44 = Utf8               hlistConstUnaryTC$
  #45 = Utf8               (Lshapeless/LowPriorityUnaryTCConstraint;Lshapeless/UnaryTCConstraint;)Lshapeless/UnaryTCConstraint;
  #46 = NameAndType        #44:#45        // hlistConstUnaryTC$:(Lshapeless/LowPriorityUnaryTCConstraint;Lshapeless/UnaryTCConstraint;)Lshapeless/UnaryTCConstraint;
  #47 = InterfaceMethodref #6.#46         // shapeless/LowPriorityUnaryTCConstraint.hlistConstUnaryTC$:(Lshapeless/LowPriorityUnaryTCConstraint;Lshapeless/UnaryTCConstraint;)Lshapeless/UnaryTCConstraint;
  #48 = Utf8               Lshapeless/UnaryTCConstraint;
  #49 = Utf8               hlistIdUnaryTC
  #50 = Utf8               <L::Lshapeless/HList;>()Lshapeless/UnaryTCConstraint<TL;Ljava/lang/Object;>;
  #51 = Utf8               hlistIdUnaryTC$
  #52 = Utf8               (Lshapeless/LowPriorityUnaryTCConstraint0;)Lshapeless/UnaryTCConstraint;
  #53 = NameAndType        #51:#52        // hlistIdUnaryTC$:(Lshapeless/LowPriorityUnaryTCConstraint0;)Lshapeless/UnaryTCConstraint;
  #54 = InterfaceMethodref #24.#53        // shapeless/LowPriorityUnaryTCConstraint0.hlistIdUnaryTC$:(Lshapeless/LowPriorityUnaryTCConstraint0;)Lshapeless/UnaryTCConstraint;
  #55 = Utf8               apply
  #56 = Utf8               <L::Lshapeless/HList;TC:Ljava/lang/Object;>(Lshapeless/UnaryTCConstraint<TL;TTC;>;)Lshapeless/UnaryTCConstraint<TL;TTC;>;
  #57 = Utf8               utcc
  #58 = Utf8               hnilConstUnaryTC
  #59 = Utf8               <H:Ljava/lang/Object;>()Lshapeless/UnaryTCConstraint<Lshapeless/HNil;*>;
  #60 = Methodref          #11.#19        // shapeless/UnaryTCConstraint$$anon$4."<init>":()V
  #61 = Utf8               hlistUnaryTC
  #62 = Utf8               <H:Ljava/lang/Object;T::Lshapeless/HList;TC:Ljava/lang/Object;>(Lshapeless/UnaryTCConstraint<TT;TTC;>;)Lshapeless/UnaryTCConstraint<Lshapeless/$colon$colon<TTC;TT;>;TTC;>;
  #63 = Methodref          #13.#19        // shapeless/UnaryTCConstraint$$anon$5."<init>":()V
  #64 = Utf8               writeReplace
  #65 = Utf8               ()Ljava/lang/Object;
  #66 = Utf8               scala/runtime/ModuleSerializationProxy
  #67 = Class              #66            // scala/runtime/ModuleSerializationProxy
  #68 = Utf8               (Ljava/lang/Class;)V
  #69 = NameAndType        #18:#68        // "<init>":(Ljava/lang/Class;)V
  #70 = Methodref          #67.#69        // scala/runtime/ModuleSerializationProxy."<init>":(Ljava/lang/Class;)V
  #71 = Methodref          #4.#19         // java/lang/Object."<init>":()V
  #72 = Utf8               Code
  #73 = Utf8               LineNumberTable
  #74 = Utf8               LocalVariableTable
  #75 = Utf8               Signature
  #76 = Utf8               MethodParameters
  #77 = Utf8               InnerClasses
  #78 = Utf8               SourceFile
  #79 = Utf8               ScalaInlineInfo
  #80 = Utf8               Scala
{
  public static final shapeless.UnaryTCConstraint$ MODULE$;
    descriptor: Lshapeless/UnaryTCConstraint$;
    flags: (0x0019) ACC_PUBLIC, ACC_STATIC, ACC_FINAL

  public static {};
    descriptor: ()V
    flags: (0x0009) ACC_PUBLIC, ACC_STATIC
    Code:
      stack=2, locals=0, args_size=0
         0: new           #2                  // class shapeless/UnaryTCConstraint$
         3: dup
         4: invokespecial #20                 // Method "<init>":()V
         7: putstatic     #22                 // Field MODULE$:Lshapeless/UnaryTCConstraint$;
        10: getstatic     #22                 // Field MODULE$:Lshapeless/UnaryTCConstraint$;
        13: invokestatic  #28                 // InterfaceMethod shapeless/LowPriorityUnaryTCConstraint0.$init$:(Lshapeless/LowPriorityUnaryTCConstraint0;)V
        16: getstatic     #22                 // Field MODULE$:Lshapeless/UnaryTCConstraint$;
        19: invokestatic  #31                 // InterfaceMethod shapeless/LowPriorityUnaryTCConstraint.$init$:(Lshapeless/LowPriorityUnaryTCConstraint;)V
        22: return
      LineNumberTable:
        line 40: 0

  public <TC extends java.lang.Object> shapeless.UnaryTCConstraint<shapeless.HNil, TC> hnilUnaryTC();
    descriptor: ()Lshapeless/UnaryTCConstraint;
    flags: (0x0001) ACC_PUBLIC
    Code:
      stack=1, locals=1, args_size=1
         0: aload_0
         1: invokestatic  #38                 // InterfaceMethod shapeless/LowPriorityUnaryTCConstraint.hnilUnaryTC$:(Lshapeless/LowPriorityUnaryTCConstraint;)Lshapeless/UnaryTCConstraint;
         4: areturn
      LineNumberTable:
        line 40: 0
      LocalVariableTable:
        Start  Length  Slot  Name   Signature
            0       5     0  this   Lshapeless/UnaryTCConstraint$;
    Signature: #34                          // <TC:Ljava/lang/Object;>()Lshapeless/UnaryTCConstraint<Lshapeless/HNil;TTC;>;

  public <H extends java.lang.Object, T extends shapeless.HList> shapeless.UnaryTCConstraint<shapeless.$colon$colon<H, T>, ?> hlistConstUnaryTC(shapeless.UnaryTCConstraint<T, ?>);
    descriptor: (Lshapeless/UnaryTCConstraint;)Lshapeless/UnaryTCConstraint;
    flags: (0x0001) ACC_PUBLIC
    Code:
      stack=2, locals=2, args_size=2
         0: aload_0
         1: aload_1
         2: invokestatic  #47                 // InterfaceMethod shapeless/LowPriorityUnaryTCConstraint.hlistConstUnaryTC$:(Lshapeless/LowPriorityUnaryTCConstraint;Lshapeless/UnaryTCConstraint;)Lshapeless/UnaryTCConstraint;
         5: areturn
      LineNumberTable:
        line 40: 0
      LocalVariableTable:
        Start  Length  Slot  Name   Signature
            0       6     0  this   Lshapeless/UnaryTCConstraint$;
            0       6     1  utct   Lshapeless/UnaryTCConstraint;
    Signature: #42                          // <H:Ljava/lang/Object;T::Lshapeless/HList;>(Lshapeless/UnaryTCConstraint<TT;*>;)Lshapeless/UnaryTCConstraint<Lshapeless/$colon$colon<TH;TT;>;*>;
    MethodParameters:
      Name                           Flags
      utct                           final

  public <L extends shapeless.HList> shapeless.UnaryTCConstraint<L, java.lang.Object> hlistIdUnaryTC();
    descriptor: ()Lshapeless/UnaryTCConstraint;
    flags: (0x0001) ACC_PUBLIC
    Code:
      stack=1, locals=1, args_size=1
         0: aload_0
         1: invokestatic  #54                 // InterfaceMethod shapeless/LowPriorityUnaryTCConstraint0.hlistIdUnaryTC$:(Lshapeless/LowPriorityUnaryTCConstraint0;)Lshapeless/UnaryTCConstraint;
         4: areturn
      LineNumberTable:
        line 40: 0
      LocalVariableTable:
        Start  Length  Slot  Name   Signature
            0       5     0  this   Lshapeless/UnaryTCConstraint$;
    Signature: #50                          // <L::Lshapeless/HList;>()Lshapeless/UnaryTCConstraint<TL;Ljava/lang/Object;>;

  public <L extends shapeless.HList, TC extends java.lang.Object> shapeless.UnaryTCConstraint<L, TC> apply(shapeless.UnaryTCConstraint<L, TC>);
    descriptor: (Lshapeless/UnaryTCConstraint;)Lshapeless/UnaryTCConstraint;
    flags: (0x0001) ACC_PUBLIC
    Code:
      stack=1, locals=2, args_size=2
         0: aload_1
         1: areturn
      LineNumberTable:
        line 41: 0
      LocalVariableTable:
        Start  Length  Slot  Name   Signature
            0       2     0  this   Lshapeless/UnaryTCConstraint$;
            0       2     1  utcc   Lshapeless/UnaryTCConstraint;
    Signature: #56                          // <L::Lshapeless/HList;TC:Ljava/lang/Object;>(Lshapeless/UnaryTCConstraint<TL;TTC;>;)Lshapeless/UnaryTCConstraint<TL;TTC;>;
    MethodParameters:
      Name                           Flags
      utcc                           final

  public <H extends java.lang.Object> shapeless.UnaryTCConstraint<shapeless.HNil, ?> hnilConstUnaryTC();
    descriptor: ()Lshapeless/UnaryTCConstraint;
    flags: (0x0001) ACC_PUBLIC
    Code:
      stack=2, locals=1, args_size=1
         0: new           #11                 // class shapeless/UnaryTCConstraint$$anon$4
         3: dup
         4: invokespecial #60                 // Method shapeless/UnaryTCConstraint$$anon$4."<init>":()V
         7: areturn
      LineNumberTable:
        line 47: 0
      LocalVariableTable:
        Start  Length  Slot  Name   Signature
            0       8     0  this   Lshapeless/UnaryTCConstraint$;
    Signature: #59                          // <H:Ljava/lang/Object;>()Lshapeless/UnaryTCConstraint<Lshapeless/HNil;*>;

  public <H extends java.lang.Object, T extends shapeless.HList, TC extends java.lang.Object> shapeless.UnaryTCConstraint<shapeless.$colon$colon<TC, T>, TC> hlistUnaryTC(shapeless.UnaryTCConstraint<T, TC>);
    descriptor: (Lshapeless/UnaryTCConstraint;)Lshapeless/UnaryTCConstraint;
    flags: (0x0001) ACC_PUBLIC
    Code:
      stack=2, locals=2, args_size=2
         0: new           #13                 // class shapeless/UnaryTCConstraint$$anon$5
         3: dup
         4: invokespecial #63                 // Method shapeless/UnaryTCConstraint$$anon$5."<init>":()V
         7: areturn
      LineNumberTable:
        line 50: 0
      LocalVariableTable:
        Start  Length  Slot  Name   Signature
            0       8     0  this   Lshapeless/UnaryTCConstraint$;
            0       8     1  utct   Lshapeless/UnaryTCConstraint;
    Signature: #62                          // <H:Ljava/lang/Object;T::Lshapeless/HList;TC:Ljava/lang/Object;>(Lshapeless/UnaryTCConstraint<TT;TTC;>;)Lshapeless/UnaryTCConstraint<Lshapeless/$colon$colon<TTC;TT;>;TTC;>;
    MethodParameters:
      Name                           Flags
      utct                           final

  private java.lang.Object writeReplace();
    descriptor: ()Ljava/lang/Object;
    flags: (0x0002) ACC_PRIVATE
    Code:
      stack=3, locals=1, args_size=1
         0: new           #67                 // class scala/runtime/ModuleSerializationProxy
         3: dup
         4: ldc           #2                  // class shapeless/UnaryTCConstraint$
         6: invokespecial #70                 // Method scala/runtime/ModuleSerializationProxy."<init>":(Ljava/lang/Class;)V
         9: areturn
      LineNumberTable:
        line 40: 0
      LocalVariableTable:
        Start  Length  Slot  Name   Signature
            0      10     0  this   Lshapeless/UnaryTCConstraint$;

  private shapeless.UnaryTCConstraint$();
    descriptor: ()V
    flags: (0x0002) ACC_PRIVATE
    Code:
      stack=1, locals=1, args_size=1
         0: aload_0
         1: invokespecial #71                 // Method java/lang/Object."<init>":()V
         4: return
      LineNumberTable:
        line 40: 0
      LocalVariableTable:
        Start  Length  Slot  Name   Signature
            0       5     0  this   Lshapeless/UnaryTCConstraint$;
}
InnerClasses:
  public final #11;                       // class shapeless/UnaryTCConstraint$$anon$4
  public final #13;                       // class shapeless/UnaryTCConstraint$$anon$5
SourceFile: "hlistconstraints.scala"
  ScalaInlineInfo: length = 0x2C (unknown attribute)
   01 01 00 08 00 12 00 11 01 00 37 00 29 01 00 28
   00 29 01 00 31 00 21 01 00 3D 00 29 01 00 3A 00
   21 01 00 20 00 21 01 00 40 00 41 01
  Scala: length = 0x0 (unknown attribute)

