Classfile /Users/mw/Projects/slang-braindump/.jar/jar8/assemble/slang-braindump/assemble/content/shapeless/Unpack22.class
  Last modified May 29, 2022; size 2907 bytes
  SHA-256 checksum 37e1b6dcd3c561ed02805cccb8bc63052229068fae49843cfb24305e0ac558d8
  Compiled from "unpack.scala"
public interface shapeless.Unpack22<PP extends java.lang.Object, FF extends java.lang.Object, A extends java.lang.Object, B extends java.lang.Object, C extends java.lang.Object, D extends java.lang.Object, E extends java.lang.Object, F extends java.lang.Object, G extends java.lang.Object, H extends java.lang.Object, I extends java.lang.Object, J extends java.lang.Object, K extends java.lang.Object, L extends java.lang.Object, M extends java.lang.Object, N extends java.lang.Object, O extends java.lang.Object, P extends java.lang.Object, Q extends java.lang.Object, R extends java.lang.Object, S extends java.lang.Object, T extends java.lang.Object, U extends java.lang.Object, V extends java.lang.Object>
  minor version: 0
  major version: 52
  flags: (0x0601) ACC_PUBLIC, ACC_INTERFACE, ACC_ABSTRACT
  this_class: #2                          // shapeless/Unpack22
  super_class: #5                         // java/lang/Object
  interfaces: 0, fields: 0, methods: 1, attributes: 5
Constant pool:
   #1 = Utf8               shapeless/Unpack22
   #2 = Class              #1             // shapeless/Unpack22
   #3 = Utf8               <PP:Ljava/lang/Object;FF:Ljava/lang/Object;A:Ljava/lang/Object;B:Ljava/lang/Object;C:Ljava/lang/Object;D:Ljava/lang/Object;E:Ljava/lang/Object;F:Ljava/lang/Object;G:Ljava/lang/Object;H:Ljava/lang/Object;I:Ljava/lang/Object;J:Ljava/lang/Object;K:Ljava/lang/Object;L:Ljava/lang/Object;M:Ljava/lang/Object;N:Ljava/lang/Object;O:Ljava/lang/Object;P:Ljava/lang/Object;Q:Ljava/lang/Object;R:Ljava/lang/Object;S:Ljava/lang/Object;T:Ljava/lang/Object;U:Ljava/lang/Object;V:Ljava/lang/Object;>Ljava/lang/Object;
   #4 = Utf8               java/lang/Object
   #5 = Class              #4             // java/lang/Object
   #6 = Utf8               unpack.scala
   #7 = Utf8               Lscala/reflect/ScalaSignature;
   #8 = Utf8               bytes
   #9 = Utf8               \u0006\u0005\u0005\rdaB\u0003\u0007!\u0003\r\n!C\u0004\u0006A\u001aA\t!\u0019\u0004\u0006\u000b\u0019A\ta\u0019\u0005\u0006I\n!\t!\u001a\u0005\u0006M\n!\u0019a\u001a\u0002\t+:\u0004\u0018mY63e)\tq!A\u0005tQ\u0006\u0004X\r\\3tg\u000e\u0001Q#\u0007\u0006\u00125Q2\u0004H\u000f\u001f?\u0001\n#e\t\u0013&M\u001dB\u0013FK\u0016-[9z\u001b\"\u0001A\u0006\u0011\u00051yQ\"A\u0007\u000b\u00039\tQa]2bY\u0006L!\u0001E\u0007\u0003\r\u0005s\u0017PU3g\t\u0019\u0011\u0002\u0001#b\u0001\'\t\u0011\u0001\u000bU\t\u0003)]\u0001\"\u0001D\u000b\n\u0005Yi!a\u0002(pi\"Lgn\u001a\t\u0003\u0019aI!!G\u0007\u0003\u0007\u0005s\u0017\u0010B\u0003\u001c\u0001\t\u0007AD\u0001\u0002G\rV92#H\u0010!C\t\u001aC%\n\u0014(Q%R3\u0006L\u0017/_A\n$g\r\u0003\u0006=i\u0011\ra\u0005\u0002\u0002?\u0012)aD\u0007b\u0001\'\u0011)aD\u0007b\u0001\'\u0011)aD\u0007b\u0001\'\u0011)aD\u0007b\u0001\'\u0011)aD\u0007b\u0001\'\u0011)aD\u0007b\u0001\'\u0011)aD\u0007b\u0001\'\u0011)aD\u0007b\u0001\'\u0011)aD\u0007b\u0001\'\u0011)aD\u0007b\u0001\'\u0011)aD\u0007b\u0001\'\u0011)aD\u0007b\u0001\'\u0011)aD\u0007b\u0001\'\u0011)aD\u0007b\u0001\'\u0011)aD\u0007b\u0001\'\u0011)aD\u0007b\u0001\'\u0011)aD\u0007b\u0001\'\u0011)aD\u0007b\u0001\'\u0011)aD\u0007b\u0001\'\u0011)aD\u0007b\u0001\'\u0011)aD\u0007b\u0001\'\u0011)Q\u0007\u0001b\u0001\'\t\t\u0011\tB\u00038\u0001\t\u00071CA\u0001C\t\u0015I\u0004A1\u0001\u0014\u0005\u0005\u0019E!B\u001e\u0001\u0005\u0004\u0019\"!\u0001#\u0005\u000bu\u0002!\u0019A\n\u0003\u0003\u0015#Qa\u0010\u0001C\u0002M\u0011\u0011A\u0012\u0003\u0006\u0003\u0002\u0011\ra\u0005\u0002\u0002\u000f\u0012)1\t\u0001b\u0001\'\t\t\u0001\nB\u0003F\u0001\t\u00071CA\u0001J\t\u00159\u0005A1\u0001\u0014\u0005\u0005QE!B%\u0001\u0005\u0004\u0019\"!A&\u0005\u000b-\u0003!\u0019A\n\u0003\u00031#Q!\u0014\u0001C\u0002M\u0011\u0011!\u0014\u0003\u0006\u001f\u0002\u0011\ra\u0005\u0002\u0002\u001d\u0012)\u0011\u000b\u0001b\u0001\'\t\tq\nB\u0003T\u0001\t\u00071CA\u0001Q\t\u0015)\u0006A1\u0001\u0014\u0005\u0005\tF!B,\u0001\u0005\u0004\u0019\"!\u0001*\u0005\u000be\u0003!\u0019A\n\u0003\u0003M#Qa\u0017\u0001C\u0002M\u0011\u0011\u0001\u0016\u0003\u0006;\u0002\u0011\ra\u0005\u0002\u0002+\u0012)q\f\u0001b\u0001\'\t\ta+\u0001\u0005V]B\f7m\u001b\u001a3!\t\u0011\'!D\u0001\u0007\'\t\u00111\"\u0001\u0004=S:LGO\u0010\u000b\u0002C\u00061QO\u001c9bG.,b\u0006\u001b7\u0002\f\u0005=\u00111CA\f\u00037\ty\"a\t\u0002(\u0005-\u0012qFA\u001a\u0003o\tY$a\u0010\u0002D\u0005\u001d\u00131JA(\u0003\'\n9&a\u0017\u0002`U\t\u0011\u000eE\u0019c\u0001)\f\t\'!\u0003\u0002\u000e\u0005E\u0011QCA\r\u0003;\t\t#!\n\u0002*\u00055\u0012\u0011GA\u001b\u0003s\ti$!\u0011\u0002F\u0005%\u0013QJA)\u0003+\nI&!\u0018\u0011]-d\u0017\u0011BA\u0007\u0003#\t)\"!\u0007\u0002\u001e\u0005\u0005\u0012QEA\u0015\u0003[\t\t$!\u000e\u0002:\u0005u\u0012\u0011IA#\u0003\u0013\ni%!\u0015\u0002V\u0005e\u0013Q\f\u0007\u0001\t\u0015YBA1\u0001n+m\u0019bn\u001c9reN$XO^<ysj\\H0 @\u0000\u0003\u0003\t\u0019!!\u0002\u0002\b\u0011)a\u0004\u001cb\u0001\'\u0011)a\u0004\u001cb\u0001\'\u0011)a\u0004\u001cb\u0001\'\u0011)a\u0004\u001cb\u0001\'\u0011)a\u0004\u001cb\u0001\'\u0011)a\u0004\u001cb\u0001\'\u0011)a\u0004\u001cb\u0001\'\u0011)a\u0004\u001cb\u0001\'\u0011)a\u0004\u001cb\u0001\'\u0011)a\u0004\u001cb\u0001\'\u0011)a\u0004\u001cb\u0001\'\u0011)a\u0004\u001cb\u0001\'\u0011)a\u0004\u001cb\u0001\'\u0011)a\u0004\u001cb\u0001\'\u0011)a\u0004\u001cb\u0001\'\u0011)a\u0004\u001cb\u0001\'\u0011)a\u0004\u001cb\u0001\'\u0011)a\u0004\u001cb\u0001\'\u0011)a\u0004\u001cb\u0001\'\u0011)a\u0004\u001cb\u0001\'\u0011)a\u0004\u001cb\u0001\'\u0011)a\u0004\u001cb\u0001\'A\u00191.a\u0003\u0005\u000bU\"!\u0019A\n\u0011\u0007-\fy\u0001B\u00038\t\t\u00071\u0003E\u0002l\u0003\'!Q!\u000f\u0003C\u0002M\u00012a[A\f\t\u0015YDA1\u0001\u0014!\rY\u00171\u0004\u0003\u0006{\u0011\u0011\ra\u0005\t\u0004W\u0006}A!B \u0005\u0005\u0004\u0019\u0002cA6\u0002$\u0011)\u0011\t\u0002b\u0001\'A\u00191.a\n\u0005\u000b\r#!\u0019A\n\u0011\u0007-\fY\u0003B\u0003F\t\t\u00071\u0003E\u0002l\u0003_!Qa\u0012\u0003C\u0002M\u00012a[A\u001a\t\u0015IEA1\u0001\u0014!\rY\u0017q\u0007\u0003\u0006\u0017\u0012\u0011\ra\u0005\t\u0004W\u0006mB!B\'\u0005\u0005\u0004\u0019\u0002cA6\u0002@\u0011)q\n\u0002b\u0001\'A\u00191.a\u0011\u0005\u000bE#!\u0019A\n\u0011\u0007-\f9\u0005B\u0003T\t\t\u00071\u0003E\u0002l\u0003\u0017\"Q!\u0016\u0003C\u0002M\u00012a[A(\t\u00159FA1\u0001\u0014!\rY\u00171\u000b\u0003\u00063\u0012\u0011\ra\u0005\t\u0004W\u0006]C!B.\u0005\u0005\u0004\u0019\u0002cA6\u0002\\\u0011)Q\f\u0002b\u0001\'A\u00191.a\u0018\u0005\u000b}#!\u0019A\n\u0011\u0005-d\u0007
  #10 = Utf8               unpack
  #11 = Utf8               ()Lshapeless/Unpack22;
  #12 = Utf8               <FF:Ljava/lang/Object;A:Ljava/lang/Object;B:Ljava/lang/Object;C:Ljava/lang/Object;D:Ljava/lang/Object;E:Ljava/lang/Object;F:Ljava/lang/Object;G:Ljava/lang/Object;H:Ljava/lang/Object;I:Ljava/lang/Object;J:Ljava/lang/Object;K:Ljava/lang/Object;L:Ljava/lang/Object;M:Ljava/lang/Object;N:Ljava/lang/Object;O:Ljava/lang/Object;P:Ljava/lang/Object;Q:Ljava/lang/Object;R:Ljava/lang/Object;S:Ljava/lang/Object;T:Ljava/lang/Object;U:Ljava/lang/Object;V:Ljava/lang/Object;>()Lshapeless/Unpack22<TFF;TFF;TA;TB;TC;TD;TE;TF;TG;TH;TI;TJ;TK;TL;TM;TN;TO;TP;TQ;TR;TS;TT;TU;TV;>;
  #13 = Utf8               shapeless/Unpack22$
  #14 = Class              #13            // shapeless/Unpack22$
  #15 = Utf8               MODULE$
  #16 = Utf8               Lshapeless/Unpack22$;
  #17 = NameAndType        #15:#16        // MODULE$:Lshapeless/Unpack22$;
  #18 = Fieldref           #14.#17        // shapeless/Unpack22$.MODULE$:Lshapeless/Unpack22$;
  #19 = NameAndType        #10:#11        // unpack:()Lshapeless/Unpack22;
  #20 = Methodref          #14.#19        // shapeless/Unpack22$.unpack:()Lshapeless/Unpack22;
  #21 = Utf8               Code
  #22 = Utf8               Signature
  #23 = Utf8               SourceFile
  #24 = Utf8               RuntimeVisibleAnnotations
  #25 = Utf8               ScalaInlineInfo
  #26 = Utf8               ScalaSig
{
  public static <FF extends java.lang.Object, A extends java.lang.Object, B extends java.lang.Object, C extends java.lang.Object, D extends java.lang.Object, E extends java.lang.Object, F extends java.lang.Object, G extends java.lang.Object, H extends java.lang.Object, I extends java.lang.Object, J extends java.lang.Object, K extends java.lang.Object, L extends java.lang.Object, M extends java.lang.Object, N extends java.lang.Object, O extends java.lang.Object, P extends java.lang.Object, Q extends java.lang.Object, R extends java.lang.Object, S extends java.lang.Object, T extends java.lang.Object, U extends java.lang.Object, V extends java.lang.Object> shapeless.Unpack22<FF, FF, A, B, C, D, E, F, G, H, I, J, K, L, M, N, O, P, Q, R, S, T, U, V> unpack();
    descriptor: ()Lshapeless/Unpack22;
    flags: (0x0009) ACC_PUBLIC, ACC_STATIC
    Code:
      stack=1, locals=0, args_size=0
         0: getstatic     #18                 // Field shapeless/Unpack22$.MODULE$:Lshapeless/Unpack22$;
         3: invokevirtual #20                 // Method shapeless/Unpack22$.unpack:()Lshapeless/Unpack22;
         6: areturn
    Signature: #12                          // <FF:Ljava/lang/Object;A:Ljava/lang/Object;B:Ljava/lang/Object;C:Ljava/lang/Object;D:Ljava/lang/Object;E:Ljava/lang/Object;F:Ljava/lang/Object;G:Ljava/lang/Object;H:Ljava/lang/Object;I:Ljava/lang/Object;J:Ljava/lang/Object;K:Ljava/lang/Object;L:Ljava/lang/Object;M:Ljava/lang/Object;N:Ljava/lang/Object;O:Ljava/lang/Object;P:Ljava/lang/Object;Q:Ljava/lang/Object;R:Ljava/lang/Object;S:Ljava/lang/Object;T:Ljava/lang/Object;U:Ljava/lang/Object;V:Ljava/lang/Object;>()Lshapeless/Unpack22<TFF;TFF;TA;TB;TC;TD;TE;TF;TG;TH;TI;TJ;TK;TL;TM;TN;TO;TP;TQ;TR;TS;TT;TU;TV;>;
}
Signature: #3                           // <PP:Ljava/lang/Object;FF:Ljava/lang/Object;A:Ljava/lang/Object;B:Ljava/lang/Object;C:Ljava/lang/Object;D:Ljava/lang/Object;E:Ljava/lang/Object;F:Ljava/lang/Object;G:Ljava/lang/Object;H:Ljava/lang/Object;I:Ljava/lang/Object;J:Ljava/lang/Object;K:Ljava/lang/Object;L:Ljava/lang/Object;M:Ljava/lang/Object;N:Ljava/lang/Object;O:Ljava/lang/Object;P:Ljava/lang/Object;Q:Ljava/lang/Object;R:Ljava/lang/Object;S:Ljava/lang/Object;T:Ljava/lang/Object;U:Ljava/lang/Object;V:Ljava/lang/Object;>Ljava/lang/Object;
SourceFile: "unpack.scala"
RuntimeVisibleAnnotations:
  0: #7(#8=s#9)
    scala.reflect.ScalaSignature(
      bytes="\u0006\u0005\u0005\rdaB\u0003\u0007!\u0003\r\n!C\u0004\u0006A\u001aA\t!\u0019\u0004\u0006\u000b\u0019A\ta\u0019\u0005\u0006I\n!\t!\u001a\u0005\u0006M\n!\u0019a\u001a\u0002\t+:\u0004\u0018mY63e)\tq!A\u0005tQ\u0006\u0004X\r\\3tg\u000e\u0001Q#\u0007\u0006\u00125Q2\u0004H\u000f\u001f?\u0001\n#e\t\u0013&M\u001dB\u0013FK\u0016-[9z\u001b\"\u0001A\u0006\u0011\u00051yQ\"A\u0007\u000b\u00039\tQa]2bY\u0006L!\u0001E\u0007\u0003\r\u0005s\u0017PU3g\t\u0019\u0011\u0002\u0001#b\u0001\'\t\u0011\u0001\u000bU\t\u0003)]\u0001\"\u0001D\u000b\n\u0005Yi!a\u0002(pi\"Lgn\u001a\t\u0003\u0019aI!!G\u0007\u0003\u0007\u0005s\u0017\u0010B\u0003\u001c\u0001\t\u0007AD\u0001\u0002G\rV92#H\u0010!C\t\u001aC%\n\u0014(Q%R3\u0006L\u0017/_A\n$g\r\u0003\u0006=i\u0011\ra\u0005\u0002\u0002?\u0012)aD\u0007b\u0001\'\u0011)aD\u0007b\u0001\'\u0011)aD\u0007b\u0001\'\u0011)aD\u0007b\u0001\'\u0011)aD\u0007b\u0001\'\u0011)aD\u0007b\u0001\'\u0011)aD\u0007b\u0001\'\u0011)aD\u0007b\u0001\'\u0011)aD\u0007b\u0001\'\u0011)aD\u0007b\u0001\'\u0011)aD\u0007b\u0001\'\u0011)aD\u0007b\u0001\'\u0011)aD\u0007b\u0001\'\u0011)aD\u0007b\u0001\'\u0011)aD\u0007b\u0001\'\u0011)aD\u0007b\u0001\'\u0011)aD\u0007b\u0001\'\u0011)aD\u0007b\u0001\'\u0011)aD\u0007b\u0001\'\u0011)aD\u0007b\u0001\'\u0011)aD\u0007b\u0001\'\u0011)Q\u0007\u0001b\u0001\'\t\t\u0011\tB\u00038\u0001\t\u00071CA\u0001C\t\u0015I\u0004A1\u0001\u0014\u0005\u0005\u0019E!B\u001e\u0001\u0005\u0004\u0019\"!\u0001#\u0005\u000bu\u0002!\u0019A\n\u0003\u0003\u0015#Qa\u0010\u0001C\u0002M\u0011\u0011A\u0012\u0003\u0006\u0003\u0002\u0011\ra\u0005\u0002\u0002\u000f\u0012)1\t\u0001b\u0001\'\t\t\u0001\nB\u0003F\u0001\t\u00071CA\u0001J\t\u00159\u0005A1\u0001\u0014\u0005\u0005QE!B%\u0001\u0005\u0004\u0019\"!A&\u0005\u000b-\u0003!\u0019A\n\u0003\u00031#Q!\u0014\u0001C\u0002M\u0011\u0011!\u0014\u0003\u0006\u001f\u0002\u0011\ra\u0005\u0002\u0002\u001d\u0012)\u0011\u000b\u0001b\u0001\'\t\tq\nB\u0003T\u0001\t\u00071CA\u0001Q\t\u0015)\u0006A1\u0001\u0014\u0005\u0005\tF!B,\u0001\u0005\u0004\u0019\"!\u0001*\u0005\u000be\u0003!\u0019A\n\u0003\u0003M#Qa\u0017\u0001C\u0002M\u0011\u0011\u0001\u0016\u0003\u0006;\u0002\u0011\ra\u0005\u0002\u0002+\u0012)q\f\u0001b\u0001\'\t\ta+\u0001\u0005V]B\f7m\u001b\u001a3!\t\u0011\'!D\u0001\u0007\'\t\u00111\"\u0001\u0004=S:LGO\u0010\u000b\u0002C\u00061QO\u001c9bG.,b\u0006\u001b7\u0002\f\u0005=\u00111CA\f\u00037\ty\"a\t\u0002(\u0005-\u0012qFA\u001a\u0003o\tY$a\u0010\u0002D\u0005\u001d\u00131JA(\u0003\'\n9&a\u0017\u0002`U\t\u0011\u000eE\u0019c\u0001)\f\t\'!\u0003\u0002\u000e\u0005E\u0011QCA\r\u0003;\t\t#!\n\u0002*\u00055\u0012\u0011GA\u001b\u0003s\ti$!\u0011\u0002F\u0005%\u0013QJA)\u0003+\nI&!\u0018\u0011]-d\u0017\u0011BA\u0007\u0003#\t)\"!\u0007\u0002\u001e\u0005\u0005\u0012QEA\u0015\u0003[\t\t$!\u000e\u0002:\u0005u\u0012\u0011IA#\u0003\u0013\ni%!\u0015\u0002V\u0005e\u0013Q\f\u0007\u0001\t\u0015YBA1\u0001n+m\u0019bn\u001c9reN$XO^<ysj\\H0 @\u0000\u0003\u0003\t\u0019!!\u0002\u0002\b\u0011)a\u0004\u001cb\u0001\'\u0011)a\u0004\u001cb\u0001\'\u0011)a\u0004\u001cb\u0001\'\u0011)a\u0004\u001cb\u0001\'\u0011)a\u0004\u001cb\u0001\'\u0011)a\u0004\u001cb\u0001\'\u0011)a\u0004\u001cb\u0001\'\u0011)a\u0004\u001cb\u0001\'\u0011)a\u0004\u001cb\u0001\'\u0011)a\u0004\u001cb\u0001\'\u0011)a\u0004\u001cb\u0001\'\u0011)a\u0004\u001cb\u0001\'\u0011)a\u0004\u001cb\u0001\'\u0011)a\u0004\u001cb\u0001\'\u0011)a\u0004\u001cb\u0001\'\u0011)a\u0004\u001cb\u0001\'\u0011)a\u0004\u001cb\u0001\'\u0011)a\u0004\u001cb\u0001\'\u0011)a\u0004\u001cb\u0001\'\u0011)a\u0004\u001cb\u0001\'\u0011)a\u0004\u001cb\u0001\'\u0011)a\u0004\u001cb\u0001\'A\u00191.a\u0003\u0005\u000bU\"!\u0019A\n\u0011\u0007-\fy\u0001B\u00038\t\t\u00071\u0003E\u0002l\u0003\'!Q!\u000f\u0003C\u0002M\u00012a[A\f\t\u0015YDA1\u0001\u0014!\rY\u00171\u0004\u0003\u0006{\u0011\u0011\ra\u0005\t\u0004W\u0006}A!B \u0005\u0005\u0004\u0019\u0002cA6\u0002$\u0011)\u0011\t\u0002b\u0001\'A\u00191.a\n\u0005\u000b\r#!\u0019A\n\u0011\u0007-\fY\u0003B\u0003F\t\t\u00071\u0003E\u0002l\u0003_!Qa\u0012\u0003C\u0002M\u00012a[A\u001a\t\u0015IEA1\u0001\u0014!\rY\u0017q\u0007\u0003\u0006\u0017\u0012\u0011\ra\u0005\t\u0004W\u0006mB!B\'\u0005\u0005\u0004\u0019\u0002cA6\u0002@\u0011)q\n\u0002b\u0001\'A\u00191.a\u0011\u0005\u000bE#!\u0019A\n\u0011\u0007-\f9\u0005B\u0003T\t\t\u00071\u0003E\u0002l\u0003\u0017\"Q!\u0016\u0003C\u0002M\u00012a[A(\t\u00159FA1\u0001\u0014!\rY\u00171\u000b\u0003\u00063\u0012\u0011\ra\u0005\t\u0004W\u0006]C!B.\u0005\u0005\u0004\u0019\u0002cA6\u0002\\\u0011)Q\f\u0002b\u0001\'A\u00191.a\u0018\u0005\u000b}#!\u0019A\n\u0011\u0005-d\u0007"
    )
  ScalaInlineInfo: length = 0x4 (unknown attribute)
   01 00 00 00
  ScalaSig: length = 0x3 (unknown attribute)
   05 02 00
