Classfile /Users/mw/Projects/slang-braindump/.jar/jar8/assemble/slang-braindump/assemble/content/shapeless/Unpack6.class
  Last modified May 29, 2022; size 1354 bytes
  SHA-256 checksum f14221e9c1ec381cc122065a68fad193055702dd58370376e83d95ff1307961d
  Compiled from "unpack.scala"
public interface shapeless.Unpack6<PP extends java.lang.Object, FF extends java.lang.Object, A extends java.lang.Object, B extends java.lang.Object, C extends java.lang.Object, D extends java.lang.Object, E extends java.lang.Object, F extends java.lang.Object>
  minor version: 0
  major version: 52
  flags: (0x0601) ACC_PUBLIC, ACC_INTERFACE, ACC_ABSTRACT
  this_class: #2                          // shapeless/Unpack6
  super_class: #5                         // java/lang/Object
  interfaces: 0, fields: 0, methods: 1, attributes: 5
Constant pool:
   #1 = Utf8               shapeless/Unpack6
   #2 = Class              #1             // shapeless/Unpack6
   #3 = Utf8               <PP:Ljava/lang/Object;FF:Ljava/lang/Object;A:Ljava/lang/Object;B:Ljava/lang/Object;C:Ljava/lang/Object;D:Ljava/lang/Object;E:Ljava/lang/Object;F:Ljava/lang/Object;>Ljava/lang/Object;
   #4 = Utf8               java/lang/Object
   #5 = Class              #4             // java/lang/Object
   #6 = Utf8               unpack.scala
   #7 = Utf8               Lscala/reflect/ScalaSignature;
   #8 = Utf8               bytes
   #9 = Utf8               \u0006\u0005E3q!\u0002\u0004\u0011\u0002G\u0005\u0011bB\u00031\r!\u0005\u0011GB\u0003\u0006\r!\u00051\u0007C\u00035\u0005\u0011\u0005Q\u0007C\u00037\u0005\u0011\rqGA\u0004V]B\f7m\u001b\u001c\u000b\u0003\u001d\t\u0011b\u001d5ba\u0016dWm]:\u0004\u0001UI!\"\u0005\u000e%M!RCFL\n\u0003\u0001-\u0001\"\u0001D\b\u000e\u00035Q\u0011AD\u0001\u0006g\u000e\fG.Y\u0005\u0003!5\u0011a!\u00118z%\u00164GA\u0002\n\u0001\u0011\u000b\u00071C\u0001\u0002Q!F\u0011Ac\u0006\t\u0003\u0019UI!AF\u0007\u0003\u000f9{G\u000f[5oOB\u0011A\u0002G\u0005\u000335\u00111!\u00118z\t\u0015Y\u0002A1\u0001\u001d\u0005\t1e)F\u0004\u0014;}\u0001\u0013EI\u0012\u0005\u000byQ\"\u0019A\n\u0003\u0003}#QA\b\u000eC\u0002M!QA\b\u000eC\u0002M!QA\b\u000eC\u0002M!QA\b\u000eC\u0002M!QA\b\u000eC\u0002M!Q!\n\u0001C\u0002M\u0011\u0011!\u0011\u0003\u0006O\u0001\u0011\ra\u0005\u0002\u0002\u0005\u0012)\u0011\u0006\u0001b\u0001\'\t\t1\tB\u0003,\u0001\t\u00071CA\u0001E\t\u0015i\u0003A1\u0001\u0014\u0005\u0005)E!B\u0018\u0001\u0005\u0004\u0019\"!\u0001$\u0002\u000fUs\u0007/Y2lmA\u0011!GA\u0007\u0002\rM\u0011!aC\u0001\u0007y%t\u0017\u000e\u001e \u0015\u0003E\na!\u001e8qC\u000e\\W\u0003\u0003\u001d=\u000b\u001eK5*T(\u0016\u0003e\u0002\"B\r\u0001;!\u00123\u0005J\u0013\'O!!YD\b\u0012$I\u00152sE\u0002\u0001\u0003\u00067\u0011\u0011\r!P\u000b\b\'yz\u0004)\u0011\"D\t\u0015qBH1\u0001\u0014\t\u0015qBH1\u0001\u0014\t\u0015qBH1\u0001\u0014\t\u0015qBH1\u0001\u0014\t\u0015qBH1\u0001\u0014\t\u0015qBH1\u0001\u0014!\tYT\tB\u0003&\t\t\u00071\u0003\u0005\u0002<\u000f\u0012)q\u0005\u0002b\u0001\'A\u00111(\u0013\u0003\u0006S\u0011\u0011\ra\u0005\t\u0003w-#Qa\u000b\u0003C\u0002M\u0001\"aO\'\u0005\u000b5\"!\u0019A\n\u0011\u0005mzE!B\u0018\u0005\u0005\u0004\u0019\u0002CA\u001e=\u0001
  #10 = Utf8               unpack
  #11 = Utf8               ()Lshapeless/Unpack6;
  #12 = Utf8               <FF:Ljava/lang/Object;A:Ljava/lang/Object;B:Ljava/lang/Object;C:Ljava/lang/Object;D:Ljava/lang/Object;E:Ljava/lang/Object;F:Ljava/lang/Object;>()Lshapeless/Unpack6<TFF;TFF;TA;TB;TC;TD;TE;TF;>;
  #13 = Utf8               shapeless/Unpack6$
  #14 = Class              #13            // shapeless/Unpack6$
  #15 = Utf8               MODULE$
  #16 = Utf8               Lshapeless/Unpack6$;
  #17 = NameAndType        #15:#16        // MODULE$:Lshapeless/Unpack6$;
  #18 = Fieldref           #14.#17        // shapeless/Unpack6$.MODULE$:Lshapeless/Unpack6$;
  #19 = NameAndType        #10:#11        // unpack:()Lshapeless/Unpack6;
  #20 = Methodref          #14.#19        // shapeless/Unpack6$.unpack:()Lshapeless/Unpack6;
  #21 = Utf8               Code
  #22 = Utf8               Signature
  #23 = Utf8               SourceFile
  #24 = Utf8               RuntimeVisibleAnnotations
  #25 = Utf8               ScalaInlineInfo
  #26 = Utf8               ScalaSig
{
  public static <FF extends java.lang.Object, A extends java.lang.Object, B extends java.lang.Object, C extends java.lang.Object, D extends java.lang.Object, E extends java.lang.Object, F extends java.lang.Object> shapeless.Unpack6<FF, FF, A, B, C, D, E, F> unpack();
    descriptor: ()Lshapeless/Unpack6;
    flags: (0x0009) ACC_PUBLIC, ACC_STATIC
    Code:
      stack=1, locals=0, args_size=0
         0: getstatic     #18                 // Field shapeless/Unpack6$.MODULE$:Lshapeless/Unpack6$;
         3: invokevirtual #20                 // Method shapeless/Unpack6$.unpack:()Lshapeless/Unpack6;
         6: areturn
    Signature: #12                          // <FF:Ljava/lang/Object;A:Ljava/lang/Object;B:Ljava/lang/Object;C:Ljava/lang/Object;D:Ljava/lang/Object;E:Ljava/lang/Object;F:Ljava/lang/Object;>()Lshapeless/Unpack6<TFF;TFF;TA;TB;TC;TD;TE;TF;>;
}
Signature: #3                           // <PP:Ljava/lang/Object;FF:Ljava/lang/Object;A:Ljava/lang/Object;B:Ljava/lang/Object;C:Ljava/lang/Object;D:Ljava/lang/Object;E:Ljava/lang/Object;F:Ljava/lang/Object;>Ljava/lang/Object;
SourceFile: "unpack.scala"
RuntimeVisibleAnnotations:
  0: #7(#8=s#9)
    scala.reflect.ScalaSignature(
      bytes="\u0006\u0005E3q!\u0002\u0004\u0011\u0002G\u0005\u0011bB\u00031\r!\u0005\u0011GB\u0003\u0006\r!\u00051\u0007C\u00035\u0005\u0011\u0005Q\u0007C\u00037\u0005\u0011\rqGA\u0004V]B\f7m\u001b\u001c\u000b\u0003\u001d\t\u0011b\u001d5ba\u0016dWm]:\u0004\u0001UI!\"\u0005\u000e%M!RCFL\n\u0003\u0001-\u0001\"\u0001D\b\u000e\u00035Q\u0011AD\u0001\u0006g\u000e\fG.Y\u0005\u0003!5\u0011a!\u00118z%\u00164GA\u0002\n\u0001\u0011\u000b\u00071C\u0001\u0002Q!F\u0011Ac\u0006\t\u0003\u0019UI!AF\u0007\u0003\u000f9{G\u000f[5oOB\u0011A\u0002G\u0005\u000335\u00111!\u00118z\t\u0015Y\u0002A1\u0001\u001d\u0005\t1e)F\u0004\u0014;}\u0001\u0013EI\u0012\u0005\u000byQ\"\u0019A\n\u0003\u0003}#QA\b\u000eC\u0002M!QA\b\u000eC\u0002M!QA\b\u000eC\u0002M!QA\b\u000eC\u0002M!QA\b\u000eC\u0002M!Q!\n\u0001C\u0002M\u0011\u0011!\u0011\u0003\u0006O\u0001\u0011\ra\u0005\u0002\u0002\u0005\u0012)\u0011\u0006\u0001b\u0001\'\t\t1\tB\u0003,\u0001\t\u00071CA\u0001E\t\u0015i\u0003A1\u0001\u0014\u0005\u0005)E!B\u0018\u0001\u0005\u0004\u0019\"!\u0001$\u0002\u000fUs\u0007/Y2lmA\u0011!GA\u0007\u0002\rM\u0011!aC\u0001\u0007y%t\u0017\u000e\u001e \u0015\u0003E\na!\u001e8qC\u000e\\W\u0003\u0003\u001d=\u000b\u001eK5*T(\u0016\u0003e\u0002\"B\r\u0001;!\u00123\u0005J\u0013\'O!!YD\b\u0012$I\u00152sE\u0002\u0001\u0003\u00067\u0011\u0011\r!P\u000b\b\'yz\u0004)\u0011\"D\t\u0015qBH1\u0001\u0014\t\u0015qBH1\u0001\u0014\t\u0015qBH1\u0001\u0014\t\u0015qBH1\u0001\u0014\t\u0015qBH1\u0001\u0014\t\u0015qBH1\u0001\u0014!\tYT\tB\u0003&\t\t\u00071\u0003\u0005\u0002<\u000f\u0012)q\u0005\u0002b\u0001\'A\u00111(\u0013\u0003\u0006S\u0011\u0011\ra\u0005\t\u0003w-#Qa\u000b\u0003C\u0002M\u0001\"aO\'\u0005\u000b5\"!\u0019A\n\u0011\u0005mzE!B\u0018\u0005\u0005\u0004\u0019\u0002CA\u001e=\u0001"
    )
  ScalaInlineInfo: length = 0x4 (unknown attribute)
   01 00 00 00
  ScalaSig: length = 0x3 (unknown attribute)
   05 02 00
