Classfile /Users/mw/Projects/slang-braindump/.jar/jar8/assemble/slang-braindump/assemble/content/shapeless/Unpack14.class
  Last modified May 29, 2022; size 2082 bytes
  SHA-256 checksum 029013090f357bdf8a48f1f61f5d4ad1330a95cbcabf905517e4205f27e4c93e
  Compiled from "unpack.scala"
public interface shapeless.Unpack14<PP extends java.lang.Object, FF extends java.lang.Object, A extends java.lang.Object, B extends java.lang.Object, C extends java.lang.Object, D extends java.lang.Object, E extends java.lang.Object, F extends java.lang.Object, G extends java.lang.Object, H extends java.lang.Object, I extends java.lang.Object, J extends java.lang.Object, K extends java.lang.Object, L extends java.lang.Object, M extends java.lang.Object, N extends java.lang.Object>
  minor version: 0
  major version: 52
  flags: (0x0601) ACC_PUBLIC, ACC_INTERFACE, ACC_ABSTRACT
  this_class: #2                          // shapeless/Unpack14
  super_class: #5                         // java/lang/Object
  interfaces: 0, fields: 0, methods: 1, attributes: 5
Constant pool:
   #1 = Utf8               shapeless/Unpack14
   #2 = Class              #1             // shapeless/Unpack14
   #3 = Utf8               <PP:Ljava/lang/Object;FF:Ljava/lang/Object;A:Ljava/lang/Object;B:Ljava/lang/Object;C:Ljava/lang/Object;D:Ljava/lang/Object;E:Ljava/lang/Object;F:Ljava/lang/Object;G:Ljava/lang/Object;H:Ljava/lang/Object;I:Ljava/lang/Object;J:Ljava/lang/Object;K:Ljava/lang/Object;L:Ljava/lang/Object;M:Ljava/lang/Object;N:Ljava/lang/Object;>Ljava/lang/Object;
   #4 = Utf8               java/lang/Object
   #5 = Class              #4             // java/lang/Object
   #6 = Utf8               unpack.scala
   #7 = Utf8               Lscala/reflect/ScalaSignature;
   #8 = Utf8               bytes
   #9 = Utf8               \u0006\u0005\u0005\raaB\u0003\u0007!\u0003\r\n!C\u0004\u0006\u0011\u001aA\t!\u0013\u0004\u0006\u000b\u0019A\ta\u0013\u0005\u0006\u0019\n!\t!\u0014\u0005\u0006\u001d\n!\u0019a\u0014\u0002\t+:\u0004\u0018mY62i)\tq!A\u0005tQ\u0006\u0004X\r\\3tg\u000e\u0001Q#\u0005\u0006\u001251r\u0003G\r\u001b7qibd\b\u0011\"E\rN\u0011\u0001a\u0003\t\u0003\u0019=i\u0011!\u0004\u0006\u0002\u001d\u0005)1oY1mC&\u0011\u0001#\u0004\u0002\u0007\u0003:L(+\u001a4\u0005\rI\u0001\u0001R1\u0001\u0014\u0005\t\u0001\u0006+\u0005\u0002\u0015/A\u0011A\"F\u0005\u0003-5\u0011qAT8uQ&tw\r\u0005\u0002\r1%\u0011\u0011$\u0004\u0002\u0004\u0003:LH!B\u000e\u0001\u0005\u0004a\"A\u0001$G+=\u0019Rd\b\u0011\"E\r\"SEJ\u0014)S)ZC!\u0002\u0010\u001b\u0005\u0004\u0019\"!A0\u0005\u000byQ\"\u0019A\n\u0005\u000byQ\"\u0019A\n\u0005\u000byQ\"\u0019A\n\u0005\u000byQ\"\u0019A\n\u0005\u000byQ\"\u0019A\n\u0005\u000byQ\"\u0019A\n\u0005\u000byQ\"\u0019A\n\u0005\u000byQ\"\u0019A\n\u0005\u000byQ\"\u0019A\n\u0005\u000byQ\"\u0019A\n\u0005\u000byQ\"\u0019A\n\u0005\u000byQ\"\u0019A\n\u0005\u000byQ\"\u0019A\n\u0005\u000b5\u0002!\u0019A\n\u0003\u0003\u0005#Qa\f\u0001C\u0002M\u0011\u0011A\u0011\u0003\u0006c\u0001\u0011\ra\u0005\u0002\u0002\u0007\u0012)1\u0007\u0001b\u0001\'\t\tA\tB\u00036\u0001\t\u00071CA\u0001F\t\u00159\u0004A1\u0001\u0014\u0005\u00051E!B\u001d\u0001\u0005\u0004\u0019\"!A$\u0005\u000bm\u0002!\u0019A\n\u0003\u0003!#Q!\u0010\u0001C\u0002M\u0011\u0011!\u0013\u0003\u0006\u007f\u0001\u0011\ra\u0005\u0002\u0002\u0015\u0012)\u0011\t\u0001b\u0001\'\t\t1\nB\u0003D\u0001\t\u00071CA\u0001M\t\u0015)\u0005A1\u0001\u0014\u0005\u0005iE!B$\u0001\u0005\u0004\u0019\"!\u0001(\u0002\u0011Us\u0007/Y2lcQ\u0002\"A\u0013\u0002\u000e\u0003\u0019\u0019\"AA\u0006\u0002\rqJg.\u001b;?)\u0005I\u0015AB;oa\u0006\u001c7.\u0006\tQ)\u0016<\u0017n[7pcN,x/_>~\u007fV\t\u0011\u000bE\nK\u0001I\u000b\t\u0001\u001a4iU2t\u0007O\u001d;wqjdh\u0010\u0005\tT)\u00124\u0007N\u001b7oaJ$h\u000f\u001f>}}2\u0001A!B\u000e\u0005\u0005\u0004)VcD\nW/bK&l\u0017/^=~\u0003\u0017MY2\u0005\u000by!&\u0019A\n\u0005\u000by!&\u0019A\n\u0005\u000by!&\u0019A\n\u0005\u000by!&\u0019A\n\u0005\u000by!&\u0019A\n\u0005\u000by!&\u0019A\n\u0005\u000by!&\u0019A\n\u0005\u000by!&\u0019A\n\u0005\u000by!&\u0019A\n\u0005\u000by!&\u0019A\n\u0005\u000by!&\u0019A\n\u0005\u000by!&\u0019A\n\u0005\u000by!&\u0019A\n\u0005\u000by!&\u0019A\n\u0011\u0005M+G!B\u0017\u0005\u0005\u0004\u0019\u0002CA*h\t\u0015yCA1\u0001\u0014!\t\u0019\u0016\u000eB\u00032\t\t\u00071\u0003\u0005\u0002TW\u0012)1\u0007\u0002b\u0001\'A\u00111+\u001c\u0003\u0006k\u0011\u0011\ra\u0005\t\u0003\'>$Qa\u000e\u0003C\u0002M\u0001\"aU9\u0005\u000be\"!\u0019A\n\u0011\u0005M\u001bH!B\u001e\u0005\u0005\u0004\u0019\u0002CA*v\t\u0015iDA1\u0001\u0014!\t\u0019v\u000fB\u0003@\t\t\u00071\u0003\u0005\u0002Ts\u0012)\u0011\t\u0002b\u0001\'A\u00111k\u001f\u0003\u0006\u0007\u0012\u0011\ra\u0005\t\u0003\'v$Q!\u0012\u0003C\u0002M\u0001\"aU@\u0005\u000b\u001d#!\u0019A\n\u0011\u0005M#\u0006
  #10 = Utf8               unpack
  #11 = Utf8               ()Lshapeless/Unpack14;
  #12 = Utf8               <FF:Ljava/lang/Object;A:Ljava/lang/Object;B:Ljava/lang/Object;C:Ljava/lang/Object;D:Ljava/lang/Object;E:Ljava/lang/Object;F:Ljava/lang/Object;G:Ljava/lang/Object;H:Ljava/lang/Object;I:Ljava/lang/Object;J:Ljava/lang/Object;K:Ljava/lang/Object;L:Ljava/lang/Object;M:Ljava/lang/Object;N:Ljava/lang/Object;>()Lshapeless/Unpack14<TFF;TFF;TA;TB;TC;TD;TE;TF;TG;TH;TI;TJ;TK;TL;TM;TN;>;
  #13 = Utf8               shapeless/Unpack14$
  #14 = Class              #13            // shapeless/Unpack14$
  #15 = Utf8               MODULE$
  #16 = Utf8               Lshapeless/Unpack14$;
  #17 = NameAndType        #15:#16        // MODULE$:Lshapeless/Unpack14$;
  #18 = Fieldref           #14.#17        // shapeless/Unpack14$.MODULE$:Lshapeless/Unpack14$;
  #19 = NameAndType        #10:#11        // unpack:()Lshapeless/Unpack14;
  #20 = Methodref          #14.#19        // shapeless/Unpack14$.unpack:()Lshapeless/Unpack14;
  #21 = Utf8               Code
  #22 = Utf8               Signature
  #23 = Utf8               SourceFile
  #24 = Utf8               RuntimeVisibleAnnotations
  #25 = Utf8               ScalaInlineInfo
  #26 = Utf8               ScalaSig
{
  public static <FF extends java.lang.Object, A extends java.lang.Object, B extends java.lang.Object, C extends java.lang.Object, D extends java.lang.Object, E extends java.lang.Object, F extends java.lang.Object, G extends java.lang.Object, H extends java.lang.Object, I extends java.lang.Object, J extends java.lang.Object, K extends java.lang.Object, L extends java.lang.Object, M extends java.lang.Object, N extends java.lang.Object> shapeless.Unpack14<FF, FF, A, B, C, D, E, F, G, H, I, J, K, L, M, N> unpack();
    descriptor: ()Lshapeless/Unpack14;
    flags: (0x0009) ACC_PUBLIC, ACC_STATIC
    Code:
      stack=1, locals=0, args_size=0
         0: getstatic     #18                 // Field shapeless/Unpack14$.MODULE$:Lshapeless/Unpack14$;
         3: invokevirtual #20                 // Method shapeless/Unpack14$.unpack:()Lshapeless/Unpack14;
         6: areturn
    Signature: #12                          // <FF:Ljava/lang/Object;A:Ljava/lang/Object;B:Ljava/lang/Object;C:Ljava/lang/Object;D:Ljava/lang/Object;E:Ljava/lang/Object;F:Ljava/lang/Object;G:Ljava/lang/Object;H:Ljava/lang/Object;I:Ljava/lang/Object;J:Ljava/lang/Object;K:Ljava/lang/Object;L:Ljava/lang/Object;M:Ljava/lang/Object;N:Ljava/lang/Object;>()Lshapeless/Unpack14<TFF;TFF;TA;TB;TC;TD;TE;TF;TG;TH;TI;TJ;TK;TL;TM;TN;>;
}
Signature: #3                           // <PP:Ljava/lang/Object;FF:Ljava/lang/Object;A:Ljava/lang/Object;B:Ljava/lang/Object;C:Ljava/lang/Object;D:Ljava/lang/Object;E:Ljava/lang/Object;F:Ljava/lang/Object;G:Ljava/lang/Object;H:Ljava/lang/Object;I:Ljava/lang/Object;J:Ljava/lang/Object;K:Ljava/lang/Object;L:Ljava/lang/Object;M:Ljava/lang/Object;N:Ljava/lang/Object;>Ljava/lang/Object;
SourceFile: "unpack.scala"
RuntimeVisibleAnnotations:
  0: #7(#8=s#9)
    scala.reflect.ScalaSignature(
      bytes="\u0006\u0005\u0005\raaB\u0003\u0007!\u0003\r\n!C\u0004\u0006\u0011\u001aA\t!\u0013\u0004\u0006\u000b\u0019A\ta\u0013\u0005\u0006\u0019\n!\t!\u0014\u0005\u0006\u001d\n!\u0019a\u0014\u0002\t+:\u0004\u0018mY62i)\tq!A\u0005tQ\u0006\u0004X\r\\3tg\u000e\u0001Q#\u0005\u0006\u001251r\u0003G\r\u001b7qibd\b\u0011\"E\rN\u0011\u0001a\u0003\t\u0003\u0019=i\u0011!\u0004\u0006\u0002\u001d\u0005)1oY1mC&\u0011\u0001#\u0004\u0002\u0007\u0003:L(+\u001a4\u0005\rI\u0001\u0001R1\u0001\u0014\u0005\t\u0001\u0006+\u0005\u0002\u0015/A\u0011A\"F\u0005\u0003-5\u0011qAT8uQ&tw\r\u0005\u0002\r1%\u0011\u0011$\u0004\u0002\u0004\u0003:LH!B\u000e\u0001\u0005\u0004a\"A\u0001$G+=\u0019Rd\b\u0011\"E\r\"SEJ\u0014)S)ZC!\u0002\u0010\u001b\u0005\u0004\u0019\"!A0\u0005\u000byQ\"\u0019A\n\u0005\u000byQ\"\u0019A\n\u0005\u000byQ\"\u0019A\n\u0005\u000byQ\"\u0019A\n\u0005\u000byQ\"\u0019A\n\u0005\u000byQ\"\u0019A\n\u0005\u000byQ\"\u0019A\n\u0005\u000byQ\"\u0019A\n\u0005\u000byQ\"\u0019A\n\u0005\u000byQ\"\u0019A\n\u0005\u000byQ\"\u0019A\n\u0005\u000byQ\"\u0019A\n\u0005\u000byQ\"\u0019A\n\u0005\u000b5\u0002!\u0019A\n\u0003\u0003\u0005#Qa\f\u0001C\u0002M\u0011\u0011A\u0011\u0003\u0006c\u0001\u0011\ra\u0005\u0002\u0002\u0007\u0012)1\u0007\u0001b\u0001\'\t\tA\tB\u00036\u0001\t\u00071CA\u0001F\t\u00159\u0004A1\u0001\u0014\u0005\u00051E!B\u001d\u0001\u0005\u0004\u0019\"!A$\u0005\u000bm\u0002!\u0019A\n\u0003\u0003!#Q!\u0010\u0001C\u0002M\u0011\u0011!\u0013\u0003\u0006\u007f\u0001\u0011\ra\u0005\u0002\u0002\u0015\u0012)\u0011\t\u0001b\u0001\'\t\t1\nB\u0003D\u0001\t\u00071CA\u0001M\t\u0015)\u0005A1\u0001\u0014\u0005\u0005iE!B$\u0001\u0005\u0004\u0019\"!\u0001(\u0002\u0011Us\u0007/Y2lcQ\u0002\"A\u0013\u0002\u000e\u0003\u0019\u0019\"AA\u0006\u0002\rqJg.\u001b;?)\u0005I\u0015AB;oa\u0006\u001c7.\u0006\tQ)\u0016<\u0017n[7pcN,x/_>~\u007fV\t\u0011\u000bE\nK\u0001I\u000b\t\u0001\u001a4iU2t\u0007O\u001d;wqjdh\u0010\u0005\tT)\u00124\u0007N\u001b7oaJ$h\u000f\u001f>}}2\u0001A!B\u000e\u0005\u0005\u0004)VcD\nW/bK&l\u0017/^=~\u0003\u0017MY2\u0005\u000by!&\u0019A\n\u0005\u000by!&\u0019A\n\u0005\u000by!&\u0019A\n\u0005\u000by!&\u0019A\n\u0005\u000by!&\u0019A\n\u0005\u000by!&\u0019A\n\u0005\u000by!&\u0019A\n\u0005\u000by!&\u0019A\n\u0005\u000by!&\u0019A\n\u0005\u000by!&\u0019A\n\u0005\u000by!&\u0019A\n\u0005\u000by!&\u0019A\n\u0005\u000by!&\u0019A\n\u0005\u000by!&\u0019A\n\u0011\u0005M+G!B\u0017\u0005\u0005\u0004\u0019\u0002CA*h\t\u0015yCA1\u0001\u0014!\t\u0019\u0016\u000eB\u00032\t\t\u00071\u0003\u0005\u0002TW\u0012)1\u0007\u0002b\u0001\'A\u00111+\u001c\u0003\u0006k\u0011\u0011\ra\u0005\t\u0003\'>$Qa\u000e\u0003C\u0002M\u0001\"aU9\u0005\u000be\"!\u0019A\n\u0011\u0005M\u001bH!B\u001e\u0005\u0005\u0004\u0019\u0002CA*v\t\u0015iDA1\u0001\u0014!\t\u0019v\u000fB\u0003@\t\t\u00071\u0003\u0005\u0002Ts\u0012)\u0011\t\u0002b\u0001\'A\u00111k\u001f\u0003\u0006\u0007\u0012\u0011\ra\u0005\t\u0003\'v$Q!\u0012\u0003C\u0002M\u0001\"aU@\u0005\u000b\u001d#!\u0019A\n\u0011\u0005M#\u0006"
    )
  ScalaInlineInfo: length = 0x4 (unknown attribute)
   01 00 00 00
  ScalaSig: length = 0x3 (unknown attribute)
   05 02 00
