Classfile /Users/mw/Projects/slang-braindump/.jar/jar8/assemble/slang-braindump/assemble/content/shapeless/Unpack5.class
  Last modified May 29, 2022; size 1264 bytes
  SHA-256 checksum a523932c050bf0b01cdf5ba3b5be006a82b270b1a6af5d9e72b48c174f3f0d0f
  Compiled from "unpack.scala"
public interface shapeless.Unpack5<PP extends java.lang.Object, FF extends java.lang.Object, A extends java.lang.Object, B extends java.lang.Object, C extends java.lang.Object, D extends java.lang.Object, E extends java.lang.Object>
  minor version: 0
  major version: 52
  flags: (0x0601) ACC_PUBLIC, ACC_INTERFACE, ACC_ABSTRACT
  this_class: #2                          // shapeless/Unpack5
  super_class: #5                         // java/lang/Object
  interfaces: 0, fields: 0, methods: 1, attributes: 5
Constant pool:
   #1 = Utf8               shapeless/Unpack5
   #2 = Class              #1             // shapeless/Unpack5
   #3 = Utf8               <PP:Ljava/lang/Object;FF:Ljava/lang/Object;A:Ljava/lang/Object;B:Ljava/lang/Object;C:Ljava/lang/Object;D:Ljava/lang/Object;E:Ljava/lang/Object;>Ljava/lang/Object;
   #4 = Utf8               java/lang/Object
   #5 = Class              #4             // java/lang/Object
   #6 = Utf8               unpack.scala
   #7 = Utf8               Lscala/reflect/ScalaSignature;
   #8 = Utf8               bytes
   #9 = Utf8               \u0006\u0005-3q!\u0002\u0004\u0011\u0002G\u0005\u0011bB\u0003.\r!\u0005aFB\u0003\u0006\r!\u0005\u0001\u0007C\u00032\u0005\u0011\u0005!\u0007C\u00034\u0005\u0011\rAGA\u0004V]B\f7m[\u001b\u000b\u0003\u001d\t\u0011b\u001d5ba\u0016dWm]:\u0004\u0001UA!\"\u0005\u000e$K\u001dJ3f\u0005\u0002\u0001\u0017A\u0011AbD\u0007\u0002\u001b)\ta\"A\u0003tG\u0006d\u0017-\u0003\u0002\u0011\u001b\t1\u0011I\\=SK\u001a$aA\u0005\u0001\t\u0006\u0004\u0019\"A\u0001)Q#\t!r\u0003\u0005\u0002\r+%\u0011a#\u0004\u0002\b\u001d>$\b.\u001b8h!\ta\u0001$\u0003\u0002\u001a\u001b\t\u0019\u0011I\\=\u0005\u000bm\u0001!\u0019\u0001\u000f\u0003\u0005\u00193UCB\n\u001e?\u0001\n#\u0005B\u0003\u001f5\t\u00071CA\u0001`\t\u0015q\"D1\u0001\u0014\t\u0015q\"D1\u0001\u0014\t\u0015q\"D1\u0001\u0014\t\u0015q\"D1\u0001\u0014\t\u0015!\u0003A1\u0001\u0014\u0005\u0005\tE!\u0002\u0014\u0001\u0005\u0004\u0019\"!\u0001\"\u0005\u000b!\u0002!\u0019A\n\u0003\u0003\r#QA\u000b\u0001C\u0002M\u0011\u0011\u0001\u0012\u0003\u0006Y\u0001\u0011\ra\u0005\u0002\u0002\u000b\u00069QK\u001c9bG.,\u0004CA\u0018\u0003\u001b\u000511C\u0001\u0002\f\u0003\u0019a\u0014N\\5u}Q\ta&\u0001\u0004v]B\f7m[\u000b\bke\n5)R$J+\u00051\u0004#C\u0018\u0001o)\u0003%\t\u0012$I!\u001dA\u0014\b\u0011\"E\r\"c\u0001\u0001B\u0003\u001c\t\t\u0007!(\u0006\u0004\u0014wqjdh\u0010\u0003\u0006=e\u0012\ra\u0005\u0003\u0006=e\u0012\ra\u0005\u0003\u0006=e\u0012\ra\u0005\u0003\u0006=e\u0012\ra\u0005\u0003\u0006=e\u0012\ra\u0005\t\u0003q\u0005#Q\u0001\n\u0003C\u0002M\u0001\"\u0001O\"\u0005\u000b\u0019\"!\u0019A\n\u0011\u0005a*E!\u0002\u0015\u0005\u0005\u0004\u0019\u0002C\u0001\u001dH\t\u0015QCA1\u0001\u0014!\tA\u0014\nB\u0003-\t\t\u00071\u0003\u0005\u00029s\u0001
  #10 = Utf8               unpack
  #11 = Utf8               ()Lshapeless/Unpack5;
  #12 = Utf8               <FF:Ljava/lang/Object;A:Ljava/lang/Object;B:Ljava/lang/Object;C:Ljava/lang/Object;D:Ljava/lang/Object;E:Ljava/lang/Object;>()Lshapeless/Unpack5<TFF;TFF;TA;TB;TC;TD;TE;>;
  #13 = Utf8               shapeless/Unpack5$
  #14 = Class              #13            // shapeless/Unpack5$
  #15 = Utf8               MODULE$
  #16 = Utf8               Lshapeless/Unpack5$;
  #17 = NameAndType        #15:#16        // MODULE$:Lshapeless/Unpack5$;
  #18 = Fieldref           #14.#17        // shapeless/Unpack5$.MODULE$:Lshapeless/Unpack5$;
  #19 = NameAndType        #10:#11        // unpack:()Lshapeless/Unpack5;
  #20 = Methodref          #14.#19        // shapeless/Unpack5$.unpack:()Lshapeless/Unpack5;
  #21 = Utf8               Code
  #22 = Utf8               Signature
  #23 = Utf8               SourceFile
  #24 = Utf8               RuntimeVisibleAnnotations
  #25 = Utf8               ScalaInlineInfo
  #26 = Utf8               ScalaSig
{
  public static <FF extends java.lang.Object, A extends java.lang.Object, B extends java.lang.Object, C extends java.lang.Object, D extends java.lang.Object, E extends java.lang.Object> shapeless.Unpack5<FF, FF, A, B, C, D, E> unpack();
    descriptor: ()Lshapeless/Unpack5;
    flags: (0x0009) ACC_PUBLIC, ACC_STATIC
    Code:
      stack=1, locals=0, args_size=0
         0: getstatic     #18                 // Field shapeless/Unpack5$.MODULE$:Lshapeless/Unpack5$;
         3: invokevirtual #20                 // Method shapeless/Unpack5$.unpack:()Lshapeless/Unpack5;
         6: areturn
    Signature: #12                          // <FF:Ljava/lang/Object;A:Ljava/lang/Object;B:Ljava/lang/Object;C:Ljava/lang/Object;D:Ljava/lang/Object;E:Ljava/lang/Object;>()Lshapeless/Unpack5<TFF;TFF;TA;TB;TC;TD;TE;>;
}
Signature: #3                           // <PP:Ljava/lang/Object;FF:Ljava/lang/Object;A:Ljava/lang/Object;B:Ljava/lang/Object;C:Ljava/lang/Object;D:Ljava/lang/Object;E:Ljava/lang/Object;>Ljava/lang/Object;
SourceFile: "unpack.scala"
RuntimeVisibleAnnotations:
  0: #7(#8=s#9)
    scala.reflect.ScalaSignature(
      bytes="\u0006\u0005-3q!\u0002\u0004\u0011\u0002G\u0005\u0011bB\u0003.\r!\u0005aFB\u0003\u0006\r!\u0005\u0001\u0007C\u00032\u0005\u0011\u0005!\u0007C\u00034\u0005\u0011\rAGA\u0004V]B\f7m[\u001b\u000b\u0003\u001d\t\u0011b\u001d5ba\u0016dWm]:\u0004\u0001UA!\"\u0005\u000e$K\u001dJ3f\u0005\u0002\u0001\u0017A\u0011AbD\u0007\u0002\u001b)\ta\"A\u0003tG\u0006d\u0017-\u0003\u0002\u0011\u001b\t1\u0011I\\=SK\u001a$aA\u0005\u0001\t\u0006\u0004\u0019\"A\u0001)Q#\t!r\u0003\u0005\u0002\r+%\u0011a#\u0004\u0002\b\u001d>$\b.\u001b8h!\ta\u0001$\u0003\u0002\u001a\u001b\t\u0019\u0011I\\=\u0005\u000bm\u0001!\u0019\u0001\u000f\u0003\u0005\u00193UCB\n\u001e?\u0001\n#\u0005B\u0003\u001f5\t\u00071CA\u0001`\t\u0015q\"D1\u0001\u0014\t\u0015q\"D1\u0001\u0014\t\u0015q\"D1\u0001\u0014\t\u0015q\"D1\u0001\u0014\t\u0015!\u0003A1\u0001\u0014\u0005\u0005\tE!\u0002\u0014\u0001\u0005\u0004\u0019\"!\u0001\"\u0005\u000b!\u0002!\u0019A\n\u0003\u0003\r#QA\u000b\u0001C\u0002M\u0011\u0011\u0001\u0012\u0003\u0006Y\u0001\u0011\ra\u0005\u0002\u0002\u000b\u00069QK\u001c9bG.,\u0004CA\u0018\u0003\u001b\u000511C\u0001\u0002\f\u0003\u0019a\u0014N\\5u}Q\ta&\u0001\u0004v]B\f7m[\u000b\bke\n5)R$J+\u00051\u0004#C\u0018\u0001o)\u0003%\t\u0012$I!\u001dA\u0014\b\u0011\"E\r\"c\u0001\u0001B\u0003\u001c\t\t\u0007!(\u0006\u0004\u0014wqjdh\u0010\u0003\u0006=e\u0012\ra\u0005\u0003\u0006=e\u0012\ra\u0005\u0003\u0006=e\u0012\ra\u0005\u0003\u0006=e\u0012\ra\u0005\u0003\u0006=e\u0012\ra\u0005\t\u0003q\u0005#Q\u0001\n\u0003C\u0002M\u0001\"\u0001O\"\u0005\u000b\u0019\"!\u0019A\n\u0011\u0005a*E!\u0002\u0015\u0005\u0005\u0004\u0019\u0002C\u0001\u001dH\t\u0015QCA1\u0001\u0014!\tA\u0014\nB\u0003-\t\t\u00071\u0003\u0005\u00029s\u0001"
    )
  ScalaInlineInfo: length = 0x4 (unknown attribute)
   01 00 00 00
  ScalaSig: length = 0x3 (unknown attribute)
   05 02 00
