Classfile /Users/mw/Projects/slang-braindump/.jar/jar8/assemble/slang-braindump/assemble/content/shapeless/UnwrappedInstances$AnyValHelper$.class
  Last modified May 29, 2022; size 1473 bytes
  SHA-256 checksum 49b487f3b5d2d5914b4a6b659c6df61ca6cdedc58423291b2679428ebf297664
  Compiled from "unwrapped.scala"
public class shapeless.UnwrappedInstances$AnyValHelper$ implements java.io.Serializable
  minor version: 0
  major version: 52
  flags: (0x0021) ACC_PUBLIC, ACC_SUPER
  this_class: #2                          // shapeless/UnwrappedInstances$AnyValHelper$
  super_class: #4                         // java/lang/Object
  interfaces: 1, fields: 1, methods: 3, attributes: 4
Constant pool:
   #1 = Utf8               shapeless/UnwrappedInstances$AnyValHelper$
   #2 = Class              #1             // shapeless/UnwrappedInstances$AnyValHelper$
   #3 = Utf8               java/lang/Object
   #4 = Class              #3             // java/lang/Object
   #5 = Utf8               java/io/Serializable
   #6 = Class              #5             // java/io/Serializable
   #7 = Utf8               unwrapped.scala
   #8 = Utf8               shapeless/UnwrappedInstances$AnyValHelper
   #9 = Class              #8             // shapeless/UnwrappedInstances$AnyValHelper
  #10 = Utf8               shapeless/UnwrappedInstances
  #11 = Class              #10            // shapeless/UnwrappedInstances
  #12 = Utf8               AnyValHelper
  #13 = Utf8               AnyValHelper$
  #14 = Utf8               shapeless/UnwrappedInstances$AnyValHelper$$anon$2
  #15 = Class              #14            // shapeless/UnwrappedInstances$AnyValHelper$$anon$2
  #16 = Utf8               SizeOneHListHelper
  #17 = Utf8               Lshapeless/UnwrappedInstances$AnyValHelper;
  #18 = Utf8               Lshapeless/UnwrappedInstances$AnyValHelper<Lshapeless/$colon$colon<Ljava/lang/Object;Lshapeless/HNil;>;>;
  #19 = Utf8               sizeOneHListHelper
  #20 = Utf8               ()Lshapeless/UnwrappedInstances$AnyValHelper;
  #21 = Utf8               <T:Ljava/lang/Object;>()Lshapeless/UnwrappedInstances$AnyValHelper<Lshapeless/$colon$colon<TT;Lshapeless/HNil;>;>;
  #22 = NameAndType        #16:#20        // SizeOneHListHelper:()Lshapeless/UnwrappedInstances$AnyValHelper;
  #23 = Methodref          #2.#22         // shapeless/UnwrappedInstances$AnyValHelper$.SizeOneHListHelper:()Lshapeless/UnwrappedInstances$AnyValHelper;
  #24 = Utf8               this
  #25 = Utf8               Lshapeless/UnwrappedInstances$AnyValHelper$;
  #26 = Utf8               ()Lshapeless/UnwrappedInstances$AnyValHelper<Lshapeless/$colon$colon<Ljava/lang/Object;Lshapeless/HNil;>;>;
  #27 = NameAndType        #16:#17        // SizeOneHListHelper:Lshapeless/UnwrappedInstances$AnyValHelper;
  #28 = Fieldref           #2.#27         // shapeless/UnwrappedInstances$AnyValHelper$.SizeOneHListHelper:Lshapeless/UnwrappedInstances$AnyValHelper;
  #29 = Utf8               <init>
  #30 = Utf8               (Lshapeless/UnwrappedInstances;)V
  #31 = Utf8               $outer
  #32 = Utf8               ()V
  #33 = NameAndType        #29:#32        // "<init>":()V
  #34 = Methodref          #4.#33         // java/lang/Object."<init>":()V
  #35 = Utf8               (Lshapeless/UnwrappedInstances$AnyValHelper$;)V
  #36 = NameAndType        #29:#35        // "<init>":(Lshapeless/UnwrappedInstances$AnyValHelper$;)V
  #37 = Methodref          #15.#36        // shapeless/UnwrappedInstances$AnyValHelper$$anon$2."<init>":(Lshapeless/UnwrappedInstances$AnyValHelper$;)V
  #38 = Utf8               Lshapeless/UnwrappedInstances;
  #39 = Utf8               Signature
  #40 = Utf8               Code
  #41 = Utf8               LineNumberTable
  #42 = Utf8               LocalVariableTable
  #43 = Utf8               MethodParameters
  #44 = Utf8               InnerClasses
  #45 = Utf8               SourceFile
  #46 = Utf8               ScalaInlineInfo
  #47 = Utf8               Scala
{
  private final shapeless.UnwrappedInstances$AnyValHelper<shapeless.$colon$colon<java.lang.Object, shapeless.HNil>> SizeOneHListHelper;
    descriptor: Lshapeless/UnwrappedInstances$AnyValHelper;
    flags: (0x0012) ACC_PRIVATE, ACC_FINAL
    Signature: #18                          // Lshapeless/UnwrappedInstances$AnyValHelper<Lshapeless/$colon$colon<Ljava/lang/Object;Lshapeless/HNil;>;>;

  public <T extends java.lang.Object> shapeless.UnwrappedInstances$AnyValHelper<shapeless.$colon$colon<T, shapeless.HNil>> sizeOneHListHelper();
    descriptor: ()Lshapeless/UnwrappedInstances$AnyValHelper;
    flags: (0x0001) ACC_PUBLIC
    Code:
      stack=1, locals=1, args_size=1
         0: aload_0
         1: invokevirtual #23                 // Method SizeOneHListHelper:()Lshapeless/UnwrappedInstances$AnyValHelper;
         4: areturn
      LineNumberTable:
        line 51: 0
      LocalVariableTable:
        Start  Length  Slot  Name   Signature
            0       5     0  this   Lshapeless/UnwrappedInstances$AnyValHelper$;
    Signature: #21                          // <T:Ljava/lang/Object;>()Lshapeless/UnwrappedInstances$AnyValHelper<Lshapeless/$colon$colon<TT;Lshapeless/HNil;>;>;

  public shapeless.UnwrappedInstances$AnyValHelper<shapeless.$colon$colon<java.lang.Object, shapeless.HNil>> SizeOneHListHelper();
    descriptor: ()Lshapeless/UnwrappedInstances$AnyValHelper;
    flags: (0x0001) ACC_PUBLIC
    Code:
      stack=1, locals=1, args_size=1
         0: aload_0
         1: getfield      #28                 // Field SizeOneHListHelper:Lshapeless/UnwrappedInstances$AnyValHelper;
         4: areturn
      LineNumberTable:
        line 52: 0
      LocalVariableTable:
        Start  Length  Slot  Name   Signature
            0       5     0  this   Lshapeless/UnwrappedInstances$AnyValHelper$;
    Signature: #26                          // ()Lshapeless/UnwrappedInstances$AnyValHelper<Lshapeless/$colon$colon<Ljava/lang/Object;Lshapeless/HNil;>;>;

  public shapeless.UnwrappedInstances$AnyValHelper$(shapeless.UnwrappedInstances);
    descriptor: (Lshapeless/UnwrappedInstances;)V
    flags: (0x0001) ACC_PUBLIC
    Code:
      stack=4, locals=2, args_size=2
         0: aload_0
         1: invokespecial #34                 // Method java/lang/Object."<init>":()V
         4: aload_0
         5: new           #15                 // class shapeless/UnwrappedInstances$AnyValHelper$$anon$2
         8: dup
         9: aconst_null
        10: invokespecial #37                 // Method shapeless/UnwrappedInstances$AnyValHelper$$anon$2."<init>":(Lshapeless/UnwrappedInstances$AnyValHelper$;)V
        13: putfield      #28                 // Field SizeOneHListHelper:Lshapeless/UnwrappedInstances$AnyValHelper;
        16: return
      LineNumberTable:
        line 59: 0
        line 52: 4
        line 48: 16
      LocalVariableTable:
        Start  Length  Slot  Name   Signature
            0      17     0  this   Lshapeless/UnwrappedInstances$AnyValHelper$;
            0      17     1 $outer   Lshapeless/UnwrappedInstances;
    MethodParameters:
      Name                           Flags
      $outer                         final synthetic
}
InnerClasses:
  public #12= #9 of #11;                  // AnyValHelper=class shapeless/UnwrappedInstances$AnyValHelper of class shapeless/UnwrappedInstances
  public #13= #2 of #11;                  // AnyValHelper$=class shapeless/UnwrappedInstances$AnyValHelper$ of class shapeless/UnwrappedInstances
  public final #15;                       // class shapeless/UnwrappedInstances$AnyValHelper$$anon$2
SourceFile: "unwrapped.scala"
  ScalaInlineInfo: length = 0x13 (unknown attribute)
   01 01 00 03 00 1D 00 1E 01 00 10 00 14 01 00 13
   00 14 01
  Scala: length = 0x0 (unknown attribute)

