Classfile /Users/mw/Projects/slang-braindump/.jar/jar8/assemble/slang-braindump/assemble/content/shapeless/Witness.class
  Last modified May 29, 2022; size 2956 bytes
  SHA-256 checksum dfb5b03b49ac7cee56811992c3d9794b4f2fbd2b8783583e7ac00c4f5b73e423
  Compiled from "singletons.scala"
public interface shapeless.Witness extends java.io.Serializable
  minor version: 0
  major version: 52
  flags: (0x0601) ACC_PUBLIC, ACC_INTERFACE, ACC_ABSTRACT
  this_class: #2                          // shapeless/Witness
  super_class: #4                         // java/lang/Object
  interfaces: 1, fields: 0, methods: 4, attributes: 4
Constant pool:
   #1 = Utf8               shapeless/Witness
   #2 = Class              #1             // shapeless/Witness
   #3 = Utf8               java/lang/Object
   #4 = Class              #3             // java/lang/Object
   #5 = Utf8               java/io/Serializable
   #6 = Class              #5             // java/io/Serializable
   #7 = Utf8               singletons.scala
   #8 = Utf8               Lscala/reflect/ScalaSignature;
   #9 = Utf8               bytes
  #10 = Utf8               \u0006\u0005\t\u0015ca\u0002\t\u0012!\u0003\r\n\u0001\u0006\u0003\u0006O\u0001\u0011\t\u0001\u000b\u0005\b_\u0001\u0011\rQ\"\u00011\u000f\u00151\u0014\u0003#\u00018\r\u0015\u0001\u0012\u0003#\u0001:\u0011\u0015!E\u0001\"\u0001F\u000b\u00111E\u0001A$\u0006\tA#\u0001!\u0015\u0005\u00073\u0012\u0011I1\u0001.\t\u000fe#!\u0011b\u0001\u0002`!9\u0011\u0011\u0016\u0003\u0005\u0002\u0005-\u0006\"CA^\t\t\u0007I1AA_\u0011!\t9\r\u0002Q\u0001\n\u0005}\u0006bBAe\t\u0011\r\u00111\u001a\u0005\t\u0003K$!\u0011\"\u0001\u0002h\"I!Q\u0007\u0003\u0002\u0002\u0013%!q\u0007\u0002\b/&$h.Z:t\u0015\u0005\u0011\u0012!C:iCB,G.Z:t\u0007\u0001\u00192\u0001A\u000b\u001c!\t1\u0012$D\u0001\u0018\u0015\u0005A\u0012!B:dC2\f\u0017B\u0001\u000e\u0018\u0005\u0019\te.\u001f*fMB\u0011A\u0004\n\b\u0003;\tr!AH\u0011\u000e\u0003}Q!\u0001I\n\u0002\rq\u0012xn\u001c;?\u0013\u0005A\u0012BA\u0012\u0018\u0003\u001d\u0001\u0018mY6bO\u0016L!!\n\u0014\u0003\u0019M+\'/[1mSj\f\'\r\\3\u000b\u0005\r:\"!\u0001+\u0012\u0005%b\u0003C\u0001\f+\u0013\tYsCA\u0004O_RD\u0017N\\4\u0011\u0005Yi\u0013B\u0001\u0018\u0018\u0005\r\te._\u0001\u0006m\u0006dW/Z\u000b\u0002cI\u0011!\u0007\u000e\u0004\u0005g\u0001\u0001\u0011G\u0001\u0007=e\u00164\u0017N\\3nK:$h\b\u0005\u00026\u00035\t\u0001!A\u0004XSRtWm]:\u0011\u0005a\"Q\"A\t\u0014\t\u0011)\"(\u0010\t\u0003-mJ!\u0001P\f\u0003\u000f\u0011Kh.Y7jGB\u0011ahQ\u0007\u0002\u007f)\u0011\u0001)Q\u0001\u0003S>T\u0011AQ\u0001\u0005U\u00064\u0018-\u0003\u0002&\u007f\u00051A(\u001b8jiz\"\u0012a\u000e\u0002\u0004\u0003VDXC\u0001%O%\tI%J\u0002\u00034\t\u0001A\u0005C\u0001\u001d\u0001\u000b\u00119\u0013\n\t\'\u0011\u00055sE\u0002\u0001\u0003\u0006\u001f\u001a\u0011\r\u0001\u000b\u0002\u0003)B\u0012!\u0001\u0014;\u0016\u0005I;&CA*K\r\u0011\u0019D\u0001\u0001*\u0005\u000b\u001d\u001a&\u0011I+\u0012\u0005%2\u0006CA\'X\t\u0015AvA1\u0001)\u0005\raUOY\u0001\u0006CB\u0004H._\u000b\u00037~+\u0012\u0001\u0018\t\u0004;\u001aqfB\u0001\u001d\u0004!\tiu\fB\u0003(\u0011\t\u0007\u0001\u0006K\u0002\tC.\u0004\"AY5\u000e\u0003\rT!\u0001Z3\u0002\u0011%tG/\u001a:oC2T!AZ4\u0002\r5\f7M]8t\u0015\tAw#A\u0004sK\u001adWm\u0019;\n\u0005)\u001c\'!C7bGJ|\u0017*\u001c9mc\u0015qB.\\A.\u0017\u0001\tTb\b7oaf\f\u0019!a\u0005\u0002&\u0005]\u0012\u0007\u0002\u0013m\'=\fQ!\\1de>\fDA\u00067rkF\u001aQE]:\u0010\u0003M\f\u0013\u0001^\u0001\f[\u0006\u001c\'o\\#oO&tW-M\u0002&m^|\u0011a^\u0011\u0002q\u0006)co\u000e\u00181A!JW\u000e\u001d7f[\u0016tG/\u001a3!S:\u00043kY1mC\u0002\u0012d&M\u0019/a5j\u0005(K\u0019\u0005-1Th0M\u0002&wr|\u0011\u0001`\u0011\u0002{\u0006A\u0011n\u001d\"v]\u0012dW-\r\u0003&\u007f\u0006\u0005qBAA\u00013\u0005\t\u0011G\u0002\fm\u0003\u000b\ti!M\u0003&\u0003\u000f\tIa\u0004\u0002\u0002\n\u0005\u0012\u00111B\u0001\u000bSN\u0014E.Y2lE>D\u0018\'B\u0013\u0002\u0010\u0005EqBAA\t3\u0005\u0001\u0011G\u0002\fm\u0003+\ti\"M\u0003&\u0003/\tIb\u0004\u0002\u0002\u001a\u0005\u0012\u00111D\u0001\nG2\f7o\u001d(b[\u0016\fT!JA\u0010\u0003Cy!!!\t\"\u0005\u0005\r\u0012!H:iCB,G.Z:t]MKgn\u001a7fi>tG+\u001f9f\u001b\u0006\u001c\'o\\:2\rYa\u0017qEA\u0018c\u0015)\u0013\u0011FA\u0016\u001f\t\tY#\t\u0002\u0002.\u0005QQ.\u001a;i_\u0012t\u0015-\\32\u000b\u0015\n\t$a\r\u0010\u0005\u0005M\u0012EAA\u001b\u0003=i\u0017\r^3sS\u0006d\u0017N_3J[Bd\u0017G\u0002\fm\u0003s\t\t%M\u0003&\u0003w\tid\u0004\u0002\u0002>\u0005\u0012\u0011qH\u0001\ng&<g.\u0019;ve\u0016\fda\b7\u0002D\u0005E\u0013G\u0002\u0013m\u0003\u000b\n9%\u0003\u0003\u0002H\u0005%\u0013\u0001\u0002\'jgRTA!a\u0013\u0002N\u0005I\u0011.\\7vi\u0006\u0014G.\u001a\u0006\u0004\u0003\u001f:\u0012AC2pY2,7\r^5p]F2q\u0004\\A*\u0003+\nd\u0001\n7\u0002F\u0005\u001d\u0013\'B\u0013\u0002X\u0005esBAA-;\u0005\u0001\u0011g\u0001\u0014\u0002^A\u0011QjX\u000b\u0005\u0003C\n9\u0007\u0006\u0003\u0002d\u0005%\u0004\u0003B/\b\u0003K\u00022!TA4\t\u00159\u0013B1\u0001)\u0011\u001d\tY\'\u0003a\u0001\u0003K\n\u0011\u0001\u001e\u0015\u0005\u0013\u0005\fy\'\r\t Y\u0006E\u00141OA=\u0003\u007f\n))a#\u0002\u0018F\"A\u0005\\\npc\u00191B.!\u001e\u0002xE\u001aQE]:2\u0007\u00152x/\r\u0004\u0017Y\u0006m\u0014QP\u0019\u0004Kmd\u0018\u0007B\u0013\u0000\u0003\u0003\tdA\u00067\u0002\u0002\u0006\r\u0015\'B\u0013\u0002\b\u0005%\u0011\'B\u0013\u0002\u0010\u0005E\u0011G\u0002\fm\u0003\u000f\u000bI)M\u0003&\u0003/\tI\"M\u0003&\u0003?\t\t#\r\u0004\u0017Y\u00065\u0015qR\u0019\u0006K\u0005%\u00121F\u0019\u0006K\u0005E\u00151S\b\u0003\u0003\'\u000b#!!&\u0002\u0017\r|gN^3si&k\u0007\u000f\\\u0019\u0007-1\fI*a\'2\u000b\u0015\nY$!\u00102\r}a\u0017QTAPc\u0019!C.!\u0012\u0002HE2q\u0004\\AQ\u0003G\u000bd\u0001\n7\u0002F\u0005\u001d\u0013\'B\u0013\u0002&\u0006\u001dvBAAT;\u0005i !C7l/&$h.Z:t+\u0011\ti+!.\u0015\t\u0005=\u0016q\u0017\t\u0006\u0003c3\u00111W\u0007\u0002\tA\u0019Q*!.\u0005\u000b=S!\u0019\u0001\u0015\t\u000f\u0005e&\u00021\u0001\u00024\u00061a/\u00197vKB\n\u0001b^5u]\u0016\u001c8\u000fM\u000b\u0003\u0003\u007f\u0003B!\u0018\u0004\u0002BB\u0019\u0001(a1\n\u0007\u0005\u0015\u0017C\u0001\u0002`a\u0005Iq/\u001b;oKN\u001c\b\u0007I\u0001\to&$h.Z:t\u001dV!\u0011QZAm+\t\ty\r\u0005\u0003^\r\u0005E\u0007#\u0002\u001d\u0002T\u0006]\u0017bAAk#\t!1+^2d!\ri\u0015\u0011\u001c\u0003\b\u00037l!\u0019AAo\u0005\u0005\u0001\u0016cA\u0015\u0002`B\u0019\u0001(!9\n\u0007\u0005\r\u0018CA\u0002OCR\fQb]3mK\u000e$H)\u001f8b[&\u001cGc\u0001\u0017\u0002j\"9\u00111\u001e\bA\u0002\u00055\u0018a\u0003;qKN+G.Z2u_J\u0004B!a<\u0002x:!\u0011\u0011_Az!\tqr#C\u0002\u0002v^\ta\u0001\u0015:fI\u00164\u0017\u0002BA}\u0003w\u0014aa\u0015;sS:<\'bAA{/!\"a\"YA\u0000cAyBN!\u0001\u0003\u0004\t%!q\u0002B\u000b\u00057\u00119#\r\u0003%YNy\u0017G\u0002\fm\u0005\u000b\u00119!M\u0002&eN\f4!\n<xc\u00191BNa\u0003\u0003\u000eE\u001aQe\u001f?2\t\u0015z\u0018\u0011A\u0019\u0007-1\u0014\tBa\u00052\u000b\u0015\n9!!\u00032\u000b\u0015\ny!!\u00052\rYa\'q\u0003B\rc\u0015)\u0013qCA\rc\u0015)\u0013qDA\u0011c\u00191BN!\b\u0003 E*Q%!\u000b\u0002,E*QE!\t\u0003$=\u0011!1E\u0011\u0003\u0005K\tqb^5u]\u0016\u001c8\u000fV=qK&k\u0007\u000f\\\u0019\u0007-1\u0014ICa\u000b2\u000b\u0015\nY$!\u00102\r}a\'Q\u0006B\u0018c\u0019!C.!\u0012\u0002HE2q\u0004\u001cB\u0019\u0005g\td\u0001\n7\u0002F\u0005\u001d\u0013\'B\u0013\u0002&\u0006\u001d\u0016\u0001D<sSR,\'+\u001a9mC\u000e,GC\u0001B\u001d!\u0011\u0011YD!\u0011\u000e\u0005\tu\"b\u0001B \u0003\u0006!A.\u00198h\u0013\u0011\u0011\u0019E!\u0010\u0003\r=\u0013\'.Z2u\u0001
  #11 = Utf8               witnessN
  #12 = Utf8               ()Lshapeless/Witness;
  #13 = Utf8               <P::Lshapeless/Nat;>()Lshapeless/Witness;
  #14 = Utf8               shapeless/Witness$
  #15 = Class              #14            // shapeless/Witness$
  #16 = Utf8               MODULE$
  #17 = Utf8               Lshapeless/Witness$;
  #18 = NameAndType        #16:#17        // MODULE$:Lshapeless/Witness$;
  #19 = Fieldref           #15.#18        // shapeless/Witness$.MODULE$:Lshapeless/Witness$;
  #20 = NameAndType        #11:#12        // witnessN:()Lshapeless/Witness;
  #21 = Methodref          #15.#20        // shapeless/Witness$.witnessN:()Lshapeless/Witness;
  #22 = Utf8               witness0
  #23 = NameAndType        #22:#12        // witness0:()Lshapeless/Witness;
  #24 = Methodref          #15.#23        // shapeless/Witness$.witness0:()Lshapeless/Witness;
  #25 = Utf8               mkWitness
  #26 = Utf8               (Ljava/lang/Object;)Lshapeless/Witness;
  #27 = Utf8               <T0:Ljava/lang/Object;>(TT0;)Lshapeless/Witness;
  #28 = Utf8               value0
  #29 = NameAndType        #25:#26        // mkWitness:(Ljava/lang/Object;)Lshapeless/Witness;
  #30 = Methodref          #15.#29        // shapeless/Witness$.mkWitness:(Ljava/lang/Object;)Lshapeless/Witness;
  #31 = Utf8               value
  #32 = Utf8               ()Ljava/lang/Object;
  #33 = Utf8               Code
  #34 = Utf8               Signature
  #35 = Utf8               MethodParameters
  #36 = Utf8               SourceFile
  #37 = Utf8               RuntimeVisibleAnnotations
  #38 = Utf8               ScalaInlineInfo
  #39 = Utf8               ScalaSig
{
  public static <P extends shapeless.Nat> shapeless.Witness witnessN();
    descriptor: ()Lshapeless/Witness;
    flags: (0x0009) ACC_PUBLIC, ACC_STATIC
    Code:
      stack=1, locals=0, args_size=0
         0: getstatic     #19                 // Field shapeless/Witness$.MODULE$:Lshapeless/Witness$;
         3: invokevirtual #21                 // Method shapeless/Witness$.witnessN:()Lshapeless/Witness;
         6: areturn
    Signature: #13                          // <P::Lshapeless/Nat;>()Lshapeless/Witness;

  public static shapeless.Witness witness0();
    descriptor: ()Lshapeless/Witness;
    flags: (0x0009) ACC_PUBLIC, ACC_STATIC
    Code:
      stack=1, locals=0, args_size=0
         0: getstatic     #19                 // Field shapeless/Witness$.MODULE$:Lshapeless/Witness$;
         3: invokevirtual #24                 // Method shapeless/Witness$.witness0:()Lshapeless/Witness;
         6: areturn

  public static <T0 extends java.lang.Object> shapeless.Witness mkWitness(T0);
    descriptor: (Ljava/lang/Object;)Lshapeless/Witness;
    flags: (0x0009) ACC_PUBLIC, ACC_STATIC
    Code:
      stack=2, locals=1, args_size=1
         0: getstatic     #19                 // Field shapeless/Witness$.MODULE$:Lshapeless/Witness$;
         3: aload_0
         4: invokevirtual #30                 // Method shapeless/Witness$.mkWitness:(Ljava/lang/Object;)Lshapeless/Witness;
         7: areturn
    Signature: #27                          // <T0:Ljava/lang/Object;>(TT0;)Lshapeless/Witness;
    MethodParameters:
      Name                           Flags
      value0                         final

  public abstract java.lang.Object value();
    descriptor: ()Ljava/lang/Object;
    flags: (0x0401) ACC_PUBLIC, ACC_ABSTRACT
}
SourceFile: "singletons.scala"
RuntimeVisibleAnnotations:
  0: #8(#9=s#10)
    scala.reflect.ScalaSignature(
      bytes="\u0006\u0005\t\u0015ca\u0002\t\u0012!\u0003\r\n\u0001\u0006\u0003\u0006O\u0001\u0011\t\u0001\u000b\u0005\b_\u0001\u0011\rQ\"\u00011\u000f\u00151\u0014\u0003#\u00018\r\u0015\u0001\u0012\u0003#\u0001:\u0011\u0015!E\u0001\"\u0001F\u000b\u00111E\u0001A$\u0006\tA#\u0001!\u0015\u0005\u00073\u0012\u0011I1\u0001.\t\u000fe#!\u0011b\u0001\u0002`!9\u0011\u0011\u0016\u0003\u0005\u0002\u0005-\u0006\"CA^\t\t\u0007I1AA_\u0011!\t9\r\u0002Q\u0001\n\u0005}\u0006bBAe\t\u0011\r\u00111\u001a\u0005\t\u0003K$!\u0011\"\u0001\u0002h\"I!Q\u0007\u0003\u0002\u0002\u0013%!q\u0007\u0002\b/&$h.Z:t\u0015\u0005\u0011\u0012!C:iCB,G.Z:t\u0007\u0001\u00192\u0001A\u000b\u001c!\t1\u0012$D\u0001\u0018\u0015\u0005A\u0012!B:dC2\f\u0017B\u0001\u000e\u0018\u0005\u0019\te.\u001f*fMB\u0011A\u0004\n\b\u0003;\tr!AH\u0011\u000e\u0003}Q!\u0001I\n\u0002\rq\u0012xn\u001c;?\u0013\u0005A\u0012BA\u0012\u0018\u0003\u001d\u0001\u0018mY6bO\u0016L!!\n\u0014\u0003\u0019M+\'/[1mSj\f\'\r\\3\u000b\u0005\r:\"!\u0001+\u0012\u0005%b\u0003C\u0001\f+\u0013\tYsCA\u0004O_RD\u0017N\\4\u0011\u0005Yi\u0013B\u0001\u0018\u0018\u0005\r\te._\u0001\u0006m\u0006dW/Z\u000b\u0002cI\u0011!\u0007\u000e\u0004\u0005g\u0001\u0001\u0011G\u0001\u0007=e\u00164\u0017N\\3nK:$h\b\u0005\u00026\u00035\t\u0001!A\u0004XSRtWm]:\u0011\u0005a\"Q\"A\t\u0014\t\u0011)\"(\u0010\t\u0003-mJ!\u0001P\f\u0003\u000f\u0011Kh.Y7jGB\u0011ahQ\u0007\u0002\u007f)\u0011\u0001)Q\u0001\u0003S>T\u0011AQ\u0001\u0005U\u00064\u0018-\u0003\u0002&\u007f\u00051A(\u001b8jiz\"\u0012a\u000e\u0002\u0004\u0003VDXC\u0001%O%\tI%J\u0002\u00034\t\u0001A\u0005C\u0001\u001d\u0001\u000b\u00119\u0013\n\t\'\u0011\u00055sE\u0002\u0001\u0003\u0006\u001f\u001a\u0011\r\u0001\u000b\u0002\u0003)B\u0012!\u0001\u0014;\u0016\u0005I;&CA*K\r\u0011\u0019D\u0001\u0001*\u0005\u000b\u001d\u001a&\u0011I+\u0012\u0005%2\u0006CA\'X\t\u0015AvA1\u0001)\u0005\raUOY\u0001\u0006CB\u0004H._\u000b\u00037~+\u0012\u0001\u0018\t\u0004;\u001aqfB\u0001\u001d\u0004!\tiu\fB\u0003(\u0011\t\u0007\u0001\u0006K\u0002\tC.\u0004\"AY5\u000e\u0003\rT!\u0001Z3\u0002\u0011%tG/\u001a:oC2T!AZ4\u0002\r5\f7M]8t\u0015\tAw#A\u0004sK\u001adWm\u0019;\n\u0005)\u001c\'!C7bGJ|\u0017*\u001c9mc\u0015qB.\\A.\u0017\u0001\tTb\b7oaf\f\u0019!a\u0005\u0002&\u0005]\u0012\u0007\u0002\u0013m\'=\fQ!\\1de>\fDA\u00067rkF\u001aQE]:\u0010\u0003M\f\u0013\u0001^\u0001\f[\u0006\u001c\'o\\#oO&tW-M\u0002&m^|\u0011a^\u0011\u0002q\u0006)co\u000e\u00181A!JW\u000e\u001d7f[\u0016tG/\u001a3!S:\u00043kY1mC\u0002\u0012d&M\u0019/a5j\u0005(K\u0019\u0005-1Th0M\u0002&wr|\u0011\u0001`\u0011\u0002{\u0006A\u0011n\u001d\"v]\u0012dW-\r\u0003&\u007f\u0006\u0005qBAA\u00013\u0005\t\u0011G\u0002\fm\u0003\u000b\ti!M\u0003&\u0003\u000f\tIa\u0004\u0002\u0002\n\u0005\u0012\u00111B\u0001\u000bSN\u0014E.Y2lE>D\u0018\'B\u0013\u0002\u0010\u0005EqBAA\t3\u0005\u0001\u0011G\u0002\fm\u0003+\ti\"M\u0003&\u0003/\tIb\u0004\u0002\u0002\u001a\u0005\u0012\u00111D\u0001\nG2\f7o\u001d(b[\u0016\fT!JA\u0010\u0003Cy!!!\t\"\u0005\u0005\r\u0012!H:iCB,G.Z:t]MKgn\u001a7fi>tG+\u001f9f\u001b\u0006\u001c\'o\\:2\rYa\u0017qEA\u0018c\u0015)\u0013\u0011FA\u0016\u001f\t\tY#\t\u0002\u0002.\u0005QQ.\u001a;i_\u0012t\u0015-\\32\u000b\u0015\n\t$a\r\u0010\u0005\u0005M\u0012EAA\u001b\u0003=i\u0017\r^3sS\u0006d\u0017N_3J[Bd\u0017G\u0002\fm\u0003s\t\t%M\u0003&\u0003w\tid\u0004\u0002\u0002>\u0005\u0012\u0011qH\u0001\ng&<g.\u0019;ve\u0016\fda\b7\u0002D\u0005E\u0013G\u0002\u0013m\u0003\u000b\n9%\u0003\u0003\u0002H\u0005%\u0013\u0001\u0002\'jgRTA!a\u0013\u0002N\u0005I\u0011.\\7vi\u0006\u0014G.\u001a\u0006\u0004\u0003\u001f:\u0012AC2pY2,7\r^5p]F2q\u0004\\A*\u0003+\nd\u0001\n7\u0002F\u0005\u001d\u0013\'B\u0013\u0002X\u0005esBAA-;\u0005\u0001\u0011g\u0001\u0014\u0002^A\u0011QjX\u000b\u0005\u0003C\n9\u0007\u0006\u0003\u0002d\u0005%\u0004\u0003B/\b\u0003K\u00022!TA4\t\u00159\u0013B1\u0001)\u0011\u001d\tY\'\u0003a\u0001\u0003K\n\u0011\u0001\u001e\u0015\u0005\u0013\u0005\fy\'\r\t Y\u0006E\u00141OA=\u0003\u007f\n))a#\u0002\u0018F\"A\u0005\\\npc\u00191B.!\u001e\u0002xE\u001aQE]:2\u0007\u00152x/\r\u0004\u0017Y\u0006m\u0014QP\u0019\u0004Kmd\u0018\u0007B\u0013\u0000\u0003\u0003\tdA\u00067\u0002\u0002\u0006\r\u0015\'B\u0013\u0002\b\u0005%\u0011\'B\u0013\u0002\u0010\u0005E\u0011G\u0002\fm\u0003\u000f\u000bI)M\u0003&\u0003/\tI\"M\u0003&\u0003?\t\t#\r\u0004\u0017Y\u00065\u0015qR\u0019\u0006K\u0005%\u00121F\u0019\u0006K\u0005E\u00151S\b\u0003\u0003\'\u000b#!!&\u0002\u0017\r|gN^3si&k\u0007\u000f\\\u0019\u0007-1\fI*a\'2\u000b\u0015\nY$!\u00102\r}a\u0017QTAPc\u0019!C.!\u0012\u0002HE2q\u0004\\AQ\u0003G\u000bd\u0001\n7\u0002F\u0005\u001d\u0013\'B\u0013\u0002&\u0006\u001dvBAAT;\u0005i !C7l/&$h.Z:t+\u0011\ti+!.\u0015\t\u0005=\u0016q\u0017\t\u0006\u0003c3\u00111W\u0007\u0002\tA\u0019Q*!.\u0005\u000b=S!\u0019\u0001\u0015\t\u000f\u0005e&\u00021\u0001\u00024\u00061a/\u00197vKB\n\u0001b^5u]\u0016\u001c8\u000fM\u000b\u0003\u0003\u007f\u0003B!\u0018\u0004\u0002BB\u0019\u0001(a1\n\u0007\u0005\u0015\u0017C\u0001\u0002`a\u0005Iq/\u001b;oKN\u001c\b\u0007I\u0001\to&$h.Z:t\u001dV!\u0011QZAm+\t\ty\r\u0005\u0003^\r\u0005E\u0007#\u0002\u001d\u0002T\u0006]\u0017bAAk#\t!1+^2d!\ri\u0015\u0011\u001c\u0003\b\u00037l!\u0019AAo\u0005\u0005\u0001\u0016cA\u0015\u0002`B\u0019\u0001(!9\n\u0007\u0005\r\u0018CA\u0002OCR\fQb]3mK\u000e$H)\u001f8b[&\u001cGc\u0001\u0017\u0002j\"9\u00111\u001e\bA\u0002\u00055\u0018a\u0003;qKN+G.Z2u_J\u0004B!a<\u0002x:!\u0011\u0011_Az!\tqr#C\u0002\u0002v^\ta\u0001\u0015:fI\u00164\u0017\u0002BA}\u0003w\u0014aa\u0015;sS:<\'bAA{/!\"a\"YA\u0000cAyBN!\u0001\u0003\u0004\t%!q\u0002B\u000b\u00057\u00119#\r\u0003%YNy\u0017G\u0002\fm\u0005\u000b\u00119!M\u0002&eN\f4!\n<xc\u00191BNa\u0003\u0003\u000eE\u001aQe\u001f?2\t\u0015z\u0018\u0011A\u0019\u0007-1\u0014\tBa\u00052\u000b\u0015\n9!!\u00032\u000b\u0015\ny!!\u00052\rYa\'q\u0003B\rc\u0015)\u0013qCA\rc\u0015)\u0013qDA\u0011c\u00191BN!\b\u0003 E*Q%!\u000b\u0002,E*QE!\t\u0003$=\u0011!1E\u0011\u0003\u0005K\tqb^5u]\u0016\u001c8\u000fV=qK&k\u0007\u000f\\\u0019\u0007-1\u0014ICa\u000b2\u000b\u0015\nY$!\u00102\r}a\'Q\u0006B\u0018c\u0019!C.!\u0012\u0002HE2q\u0004\u001cB\u0019\u0005g\td\u0001\n7\u0002F\u0005\u001d\u0013\'B\u0013\u0002&\u0006\u001d\u0016\u0001D<sSR,\'+\u001a9mC\u000e,GC\u0001B\u001d!\u0011\u0011YD!\u0011\u000e\u0005\tu\"b\u0001B \u0003\u0006!A.\u00198h\u0013\u0011\u0011\u0019E!\u0010\u0003\r=\u0013\'.Z2u\u0001"
    )
  ScalaInlineInfo: length = 0x9 (unknown attribute)
   01 00 00 01 00 1F 00 20 00
  ScalaSig: length = 0x3 (unknown attribute)
   05 02 00
