Classfile /Users/mw/Projects/slang-braindump/.jar/jar11/assemble/slang-braindump/assemble/content/coursier/cache/loggers/RefreshInfo$CheckUpdateInfo$.class
  Last modified May 29, 2022; size 1337 bytes
  SHA-256 checksum e68b3dd76e9e91de3b42d6547914d03137df311695725fdc358d1bf0d48a317e
  Compiled from "RefreshInfo.scala"
public class coursier.cache.loggers.RefreshInfo$CheckUpdateInfo$ implements java.io.Serializable
  minor version: 0
  major version: 52
  flags: (0x0021) ACC_PUBLIC, ACC_SUPER
  this_class: #2                          // coursier/cache/loggers/RefreshInfo$CheckUpdateInfo$
  super_class: #4                         // java/lang/Object
  interfaces: 1, fields: 1, methods: 4, attributes: 4
Constant pool:
   #1 = Utf8               coursier/cache/loggers/RefreshInfo$CheckUpdateInfo$
   #2 = Class              #1             // coursier/cache/loggers/RefreshInfo$CheckUpdateInfo$
   #3 = Utf8               java/lang/Object
   #4 = Class              #3             // java/lang/Object
   #5 = Utf8               java/io/Serializable
   #6 = Class              #5             // java/io/Serializable
   #7 = Utf8               RefreshInfo.scala
   #8 = Utf8               coursier/cache/loggers/RefreshInfo$CheckUpdateInfo
   #9 = Class              #8             // coursier/cache/loggers/RefreshInfo$CheckUpdateInfo
  #10 = Utf8               coursier/cache/loggers/RefreshInfo
  #11 = Class              #10            // coursier/cache/loggers/RefreshInfo
  #12 = Utf8               CheckUpdateInfo
  #13 = Utf8
  #14 = Utf8               MODULE$
  #15 = Utf8               Lcoursier/cache/loggers/RefreshInfo$CheckUpdateInfo$;
  #16 = Utf8               <clinit>
  #17 = Utf8               ()V
  #18 = Utf8               <init>
  #19 = NameAndType        #18:#17        // "<init>":()V
  #20 = Methodref          #2.#19         // coursier/cache/loggers/RefreshInfo$CheckUpdateInfo$."<init>":()V
  #21 = NameAndType        #14:#15        // MODULE$:Lcoursier/cache/loggers/RefreshInfo$CheckUpdateInfo$;
  #22 = Fieldref           #2.#21         // coursier/cache/loggers/RefreshInfo$CheckUpdateInfo$.MODULE$:Lcoursier/cache/loggers/RefreshInfo$CheckUpdateInfo$;
  #23 = Utf8               apply
  #24 = Utf8               (Lscala/Option;Lscala/Option;Z)Lcoursier/cache/loggers/RefreshInfo$CheckUpdateInfo;
  #25 = Utf8               (Lscala/Option<Ljava/lang/Object;>;Lscala/Option<Ljava/lang/Object;>;Z)Lcoursier/cache/loggers/RefreshInfo$CheckUpdateInfo;
  #26 = Utf8               currentTimeOpt
  #27 = Utf8               remoteTimeOpt
  #28 = Utf8               isDone
  #29 = Utf8               (Lscala/Option;Lscala/Option;Z)V
  #30 = NameAndType        #18:#29        // "<init>":(Lscala/Option;Lscala/Option;Z)V
  #31 = Methodref          #9.#30         // coursier/cache/loggers/RefreshInfo$CheckUpdateInfo."<init>":(Lscala/Option;Lscala/Option;Z)V
  #32 = Utf8               this
  #33 = Utf8               Lscala/Option;
  #34 = Utf8               Z
  #35 = Utf8               writeReplace
  #36 = Utf8               ()Ljava/lang/Object;
  #37 = Utf8               scala/runtime/ModuleSerializationProxy
  #38 = Class              #37            // scala/runtime/ModuleSerializationProxy
  #39 = Utf8               (Ljava/lang/Class;)V
  #40 = NameAndType        #18:#39        // "<init>":(Ljava/lang/Class;)V
  #41 = Methodref          #38.#40        // scala/runtime/ModuleSerializationProxy."<init>":(Ljava/lang/Class;)V
  #42 = Methodref          #4.#19         // java/lang/Object."<init>":()V
  #43 = Utf8               Code
  #44 = Utf8               LineNumberTable
  #45 = Utf8               LocalVariableTable
  #46 = Utf8               Signature
  #47 = Utf8               MethodParameters
  #48 = Utf8               InnerClasses
  #49 = Utf8               SourceFile
  #50 = Utf8               ScalaInlineInfo
  #51 = Utf8               Scala
{
  public static final coursier.cache.loggers.RefreshInfo$CheckUpdateInfo$ MODULE$;
    descriptor: Lcoursier/cache/loggers/RefreshInfo$CheckUpdateInfo$;
    flags: (0x0019) ACC_PUBLIC, ACC_STATIC, ACC_FINAL

  public static {};
    descriptor: ()V
    flags: (0x0009) ACC_PUBLIC, ACC_STATIC
    Code:
      stack=2, locals=0, args_size=0
         0: new           #2                  // class coursier/cache/loggers/RefreshInfo$CheckUpdateInfo$
         3: dup
         4: invokespecial #20                 // Method "<init>":()V
         7: putstatic     #22                 // Field MODULE$:Lcoursier/cache/loggers/RefreshInfo$CheckUpdateInfo$;
        10: return
      LineNumberTable:
        line 32: 0

  public coursier.cache.loggers.RefreshInfo$CheckUpdateInfo apply(scala.Option<java.lang.Object>, scala.Option<java.lang.Object>, boolean);
    descriptor: (Lscala/Option;Lscala/Option;Z)Lcoursier/cache/loggers/RefreshInfo$CheckUpdateInfo;
    flags: (0x0001) ACC_PUBLIC
    Code:
      stack=5, locals=4, args_size=4
         0: new           #9                  // class coursier/cache/loggers/RefreshInfo$CheckUpdateInfo
         3: dup
         4: aload_1
         5: aload_2
         6: iload_3
         7: invokespecial #31                 // Method coursier/cache/loggers/RefreshInfo$CheckUpdateInfo."<init>":(Lscala/Option;Lscala/Option;Z)V
        10: areturn
      LineNumberTable:
        line 32: 0
      LocalVariableTable:
        Start  Length  Slot  Name   Signature
            0      11     0  this   Lcoursier/cache/loggers/RefreshInfo$CheckUpdateInfo$;
            0      11     1 currentTimeOpt   Lscala/Option;
            0      11     2 remoteTimeOpt   Lscala/Option;
            0      11     3 isDone   Z
    Signature: #25                          // (Lscala/Option<Ljava/lang/Object;>;Lscala/Option<Ljava/lang/Object;>;Z)Lcoursier/cache/loggers/RefreshInfo$CheckUpdateInfo;
    MethodParameters:
      Name                           Flags
      currentTimeOpt                 final
      remoteTimeOpt                  final
      isDone                         final

  private java.lang.Object writeReplace();
    descriptor: ()Ljava/lang/Object;
    flags: (0x0002) ACC_PRIVATE
    Code:
      stack=3, locals=1, args_size=1
         0: new           #38                 // class scala/runtime/ModuleSerializationProxy
         3: dup
         4: ldc           #2                  // class coursier/cache/loggers/RefreshInfo$CheckUpdateInfo$
         6: invokespecial #41                 // Method scala/runtime/ModuleSerializationProxy."<init>":(Ljava/lang/Class;)V
         9: areturn
      LineNumberTable:
        line 32: 0
      LocalVariableTable:
        Start  Length  Slot  Name   Signature
            0      10     0  this   Lcoursier/cache/loggers/RefreshInfo$CheckUpdateInfo$;

  public coursier.cache.loggers.RefreshInfo$CheckUpdateInfo$();
    descriptor: ()V
    flags: (0x0001) ACC_PUBLIC
    Code:
      stack=1, locals=1, args_size=1
         0: aload_0
         1: invokespecial #42                 // Method java/lang/Object."<init>":()V
         4: return
      LineNumberTable:
        line 32: 0
      LocalVariableTable:
        Start  Length  Slot  Name   Signature
            0       5     0  this   Lcoursier/cache/loggers/RefreshInfo$CheckUpdateInfo$;
}
InnerClasses:
  public static final #12= #9 of #11;     // CheckUpdateInfo=class coursier/cache/loggers/RefreshInfo$CheckUpdateInfo of class coursier/cache/loggers/RefreshInfo
  public static #13= #2 of #11;           // =class coursier/cache/loggers/RefreshInfo$CheckUpdateInfo$ of class coursier/cache/loggers/RefreshInfo
SourceFile: "RefreshInfo.scala"
  ScalaInlineInfo: length = 0x13 (unknown attribute)
   01 01 00 03 00 12 00 11 01 00 17 00 18 01 00 23
   00 24 01
  Scala: length = 0x0 (unknown attribute)

