Classfile /Users/mw/Projects/slang-braindump/.jar/jar11/assemble/slang-braindump/assemble/content/coursier/cache/loggers/RefreshInfo$DownloadInfo.class
  Last modified May 29, 2022; size 6917 bytes
  SHA-256 checksum 102a2e2ab5cf34ad448a0971da14b30f52820979e097a77f202cae1c0b574148
  Compiled from "RefreshInfo.scala"
public final class coursier.cache.loggers.RefreshInfo$DownloadInfo extends coursier.cache.loggers.RefreshInfo
  minor version: 0
  major version: 52
  flags: (0x0031) ACC_PUBLIC, ACC_FINAL, ACC_SUPER
  this_class: #2                          // coursier/cache/loggers/RefreshInfo$DownloadInfo
  super_class: #4                         // coursier/cache/loggers/RefreshInfo
  interfaces: 0, fields: 6, methods: 26, attributes: 5
Constant pool:
    #1 = Utf8               coursier/cache/loggers/RefreshInfo$DownloadInfo
    #2 = Class              #1            // coursier/cache/loggers/RefreshInfo$DownloadInfo
    #3 = Utf8               coursier/cache/loggers/RefreshInfo
    #4 = Class              #3            // coursier/cache/loggers/RefreshInfo
    #5 = Utf8               RefreshInfo.scala
    #6 = Utf8               DownloadInfo
    #7 = Utf8               java/lang/invoke/MethodHandles$Lookup
    #8 = Class              #7            // java/lang/invoke/MethodHandles$Lookup
    #9 = Utf8               java/lang/invoke/MethodHandles
   #10 = Class              #9            // java/lang/invoke/MethodHandles
   #11 = Utf8               Lookup
   #12 = Utf8               downloaded
   #13 = Utf8               J
   #14 = Utf8               previouslyDownloaded
   #15 = Utf8               length
   #16 = Utf8               Lscala/Option;
   #17 = Utf8               Lscala/Option<Ljava/lang/Object;>;
   #18 = Utf8               startTime
   #19 = Utf8               updateCheck
   #20 = Utf8               Z
   #21 = Utf8               watching
   #22 = Utf8               ()J
   #23 = NameAndType        #12:#13       // downloaded:J
   #24 = Fieldref           #2.#23        // coursier/cache/loggers/RefreshInfo$DownloadInfo.downloaded:J
   #25 = Utf8               this
   #26 = Utf8               Lcoursier/cache/loggers/RefreshInfo$DownloadInfo;
   #27 = NameAndType        #14:#13       // previouslyDownloaded:J
   #28 = Fieldref           #2.#27        // coursier/cache/loggers/RefreshInfo$DownloadInfo.previouslyDownloaded:J
   #29 = Utf8               ()Lscala/Option;
   #30 = Utf8               ()Lscala/Option<Ljava/lang/Object;>;
   #31 = NameAndType        #15:#16       // length:Lscala/Option;
   #32 = Fieldref           #2.#31        // coursier/cache/loggers/RefreshInfo$DownloadInfo.length:Lscala/Option;
   #33 = NameAndType        #18:#13       // startTime:J
   #34 = Fieldref           #2.#33        // coursier/cache/loggers/RefreshInfo$DownloadInfo.startTime:J
   #35 = Utf8               ()Z
   #36 = NameAndType        #19:#20       // updateCheck:Z
   #37 = Fieldref           #2.#36        // coursier/cache/loggers/RefreshInfo$DownloadInfo.updateCheck:Z
   #38 = NameAndType        #21:#20       // watching:Z
   #39 = Fieldref           #2.#38        // coursier/cache/loggers/RefreshInfo$DownloadInfo.watching:Z
   #40 = Utf8               fraction
   #41 = NameAndType        #15:#29       // length:()Lscala/Option;
   #42 = Methodref          #2.#41        // coursier/cache/loggers/RefreshInfo$DownloadInfo.length:()Lscala/Option;
   #43 = Utf8               (J)D
   #44 = MethodType         #43           //  (J)D
   #45 = Utf8               $anonfun$fraction$1
   #46 = Utf8               (Lcoursier/cache/loggers/RefreshInfo$DownloadInfo;J)D
   #47 = NameAndType        #45:#46       // $anonfun$fraction$1:(Lcoursier/cache/loggers/RefreshInfo$DownloadInfo;J)D
   #48 = Methodref          #2.#47        // coursier/cache/loggers/RefreshInfo$DownloadInfo.$anonfun$fraction$1:(Lcoursier/cache/loggers/RefreshInfo$DownloadInfo;J)D
   #49 = MethodHandle       6:#48         // REF_invokeStatic coursier/cache/loggers/RefreshInfo$DownloadInfo.$anonfun$fraction$1:(Lcoursier/cache/loggers/RefreshInfo$DownloadInfo;J)D
   #50 = Integer            1
   #51 = Utf8               java/lang/invoke/LambdaMetafactory
   #52 = Class              #51           // java/lang/invoke/LambdaMetafactory
   #53 = Utf8               altMetafactory
   #54 = Utf8               (Ljava/lang/invoke/MethodHandles$Lookup;Ljava/lang/String;Ljava/lang/invoke/MethodType;[Ljava/lang/Object;)Ljava/lang/invoke/CallSite;
   #55 = NameAndType        #53:#54       // altMetafactory:(Ljava/lang/invoke/MethodHandles$Lookup;Ljava/lang/String;Ljava/lang/invoke/MethodType;[Ljava/lang/Object;)Ljava/lang/invoke/CallSite;
   #56 = Methodref          #52.#55       // java/lang/invoke/LambdaMetafactory.altMetafactory:(Ljava/lang/invoke/MethodHandles$Lookup;Ljava/lang/String;Ljava/lang/invoke/MethodType;[Ljava/lang/Object;)Ljava/lang/invoke/CallSite;
   #57 = MethodHandle       6:#56         // REF_invokeStatic java/lang/invoke/LambdaMetafactory.altMetafactory:(Ljava/lang/invoke/MethodHandles$Lookup;Ljava/lang/String;Ljava/lang/invoke/MethodType;[Ljava/lang/Object;)Ljava/lang/invoke/CallSite;
   #58 = Utf8               apply$mcDJ$sp
   #59 = Utf8               (Lcoursier/cache/loggers/RefreshInfo$DownloadInfo;)Lscala/runtime/java8/JFunction1$mcDJ$sp;
   #60 = NameAndType        #58:#59       // apply$mcDJ$sp:(Lcoursier/cache/loggers/RefreshInfo$DownloadInfo;)Lscala/runtime/java8/JFunction1$mcDJ$sp;
   #61 = InvokeDynamic      #0:#60        // #0:apply$mcDJ$sp:(Lcoursier/cache/loggers/RefreshInfo$DownloadInfo;)Lscala/runtime/java8/JFunction1$mcDJ$sp;
   #62 = Utf8               scala/Option
   #63 = Class              #62           // scala/Option
   #64 = Utf8               map
   #65 = Utf8               (Lscala/Function1;)Lscala/Option;
   #66 = NameAndType        #64:#65       // map:(Lscala/Function1;)Lscala/Option;
   #67 = Methodref          #63.#66       // scala/Option.map:(Lscala/Function1;)Lscala/Option;
   #68 = Utf8               rate
   #69 = Utf8               java/lang/System
   #70 = Class              #69           // java/lang/System
   #71 = Utf8               currentTimeMillis
   #72 = NameAndType        #71:#22       // currentTimeMillis:()J
   #73 = Methodref          #70.#72       // java/lang/System.currentTimeMillis:()J
   #74 = NameAndType        #18:#22       // startTime:()J
   #75 = Methodref          #2.#74        // coursier/cache/loggers/RefreshInfo$DownloadInfo.startTime:()J
   #76 = Utf8               scala/Some
   #77 = Class              #76           // scala/Some
   #78 = NameAndType        #12:#22       // downloaded:()J
   #79 = Methodref          #2.#78        // coursier/cache/loggers/RefreshInfo$DownloadInfo.downloaded:()J
   #80 = NameAndType        #14:#22       // previouslyDownloaded:()J
   #81 = Methodref          #2.#80        // coursier/cache/loggers/RefreshInfo$DownloadInfo.previouslyDownloaded:()J
   #82 = Double             1000.0d
   #84 = Utf8               scala/runtime/BoxesRunTime
   #85 = Class              #84           // scala/runtime/BoxesRunTime
   #86 = Utf8               boxToDouble
   #87 = Utf8               (D)Ljava/lang/Double;
   #88 = NameAndType        #86:#87       // boxToDouble:(D)Ljava/lang/Double;
   #89 = Methodref          #85.#88       // scala/runtime/BoxesRunTime.boxToDouble:(D)Ljava/lang/Double;
   #90 = Utf8               <init>
   #91 = Utf8               (Ljava/lang/Object;)V
   #92 = NameAndType        #90:#91       // "<init>":(Ljava/lang/Object;)V
   #93 = Methodref          #77.#92       // scala/Some."<init>":(Ljava/lang/Object;)V
   #94 = Utf8               scala/None$
   #95 = Class              #94           // scala/None$
   #96 = Utf8               MODULE$
   #97 = Utf8               Lscala/None$;
   #98 = NameAndType        #96:#97       // MODULE$:Lscala/None$;
   #99 = Fieldref           #95.#98       // scala/None$.MODULE$:Lscala/None$;
  #100 = Utf8               currentTime
  #101 = Utf8               withDownloaded
  #102 = Utf8               (J)Lcoursier/cache/loggers/RefreshInfo$DownloadInfo;
  #103 = NameAndType        #19:#35       // updateCheck:()Z
  #104 = Methodref          #2.#103       // coursier/cache/loggers/RefreshInfo$DownloadInfo.updateCheck:()Z
  #105 = NameAndType        #21:#35       // watching:()Z
  #106 = Methodref          #2.#105       // coursier/cache/loggers/RefreshInfo$DownloadInfo.watching:()Z
  #107 = Utf8               (JJLscala/Option;JZZ)V
  #108 = NameAndType        #90:#107      // "<init>":(JJLscala/Option;JZZ)V
  #109 = Methodref          #2.#108       // coursier/cache/loggers/RefreshInfo$DownloadInfo."<init>":(JJLscala/Option;JZZ)V
  #110 = Utf8               withPreviouslyDownloaded
  #111 = Utf8               withLength
  #112 = Utf8               (Lscala/Option;)Lcoursier/cache/loggers/RefreshInfo$DownloadInfo;
  #113 = Utf8               (Lscala/Option<Ljava/lang/Object;>;)Lcoursier/cache/loggers/RefreshInfo$DownloadInfo;
  #114 = Utf8               withStartTime
  #115 = Utf8               withUpdateCheck
  #116 = Utf8               (Z)Lcoursier/cache/loggers/RefreshInfo$DownloadInfo;
  #117 = Utf8               withWatching
  #118 = Utf8               toString
  #119 = Utf8               ()Ljava/lang/String;
  #120 = Utf8               java/lang/StringBuilder
  #121 = Class              #120          // java/lang/StringBuilder
  #122 = Utf8               DownloadInfo(
  #123 = String             #122          // DownloadInfo(
  #124 = Utf8               (Ljava/lang/String;)V
  #125 = NameAndType        #90:#124      // "<init>":(Ljava/lang/String;)V
  #126 = Methodref          #121.#125     // java/lang/StringBuilder."<init>":(Ljava/lang/String;)V
  #127 = Utf8               java/lang/String
  #128 = Class              #127          // java/lang/String
  #129 = Utf8               valueOf
  #130 = Utf8               (J)Ljava/lang/String;
  #131 = NameAndType        #129:#130     // valueOf:(J)Ljava/lang/String;
  #132 = Methodref          #128.#131     // java/lang/String.valueOf:(J)Ljava/lang/String;
  #133 = Utf8               append
  #134 = Utf8               (Ljava/lang/String;)Ljava/lang/StringBuilder;
  #135 = NameAndType        #133:#134     // append:(Ljava/lang/String;)Ljava/lang/StringBuilder;
  #136 = Methodref          #121.#135     // java/lang/StringBuilder.append:(Ljava/lang/String;)Ljava/lang/StringBuilder;
  #137 = Utf8               ,
  #138 = String             #137          // ,
  #139 = Utf8               (Ljava/lang/Object;)Ljava/lang/String;
  #140 = NameAndType        #129:#139     // valueOf:(Ljava/lang/Object;)Ljava/lang/String;
  #141 = Methodref          #128.#140     // java/lang/String.valueOf:(Ljava/lang/Object;)Ljava/lang/String;
  #142 = Utf8               (Z)Ljava/lang/String;
  #143 = NameAndType        #129:#142     // valueOf:(Z)Ljava/lang/String;
  #144 = Methodref          #128.#143     // java/lang/String.valueOf:(Z)Ljava/lang/String;
  #145 = Utf8               )
  #146 = String             #145          // )
  #147 = NameAndType        #118:#119     // toString:()Ljava/lang/String;
  #148 = Methodref          #121.#147     // java/lang/StringBuilder.toString:()Ljava/lang/String;
  #149 = Utf8               b
  #150 = Utf8               Ljava/lang/StringBuilder;
  #151 = Utf8               canEqual
  #152 = Utf8               (Ljava/lang/Object;)Z
  #153 = Utf8               obj
  #154 = Utf8               Ljava/lang/Object;
  #155 = Utf8               equals
  #156 = NameAndType        #151:#152     // canEqual:(Ljava/lang/Object;)Z
  #157 = Methodref          #2.#156       // coursier/cache/loggers/RefreshInfo$DownloadInfo.canEqual:(Ljava/lang/Object;)Z
  #158 = Utf8               java/lang/Object
  #159 = Class              #158          // java/lang/Object
  #160 = NameAndType        #155:#152     // equals:(Ljava/lang/Object;)Z
  #161 = Methodref          #159.#160     // java/lang/Object.equals:(Ljava/lang/Object;)Z
  #162 = Utf8               other
  #163 = Utf8               hashCode
  #164 = Utf8               ()I
  #165 = String             #6            // DownloadInfo
  #166 = Utf8               scala/runtime/Statics
  #167 = Class              #166          // scala/runtime/Statics
  #168 = Utf8               anyHash
  #169 = Utf8               (Ljava/lang/Object;)I
  #170 = NameAndType        #168:#169     // anyHash:(Ljava/lang/Object;)I
  #171 = Methodref          #167.#170     // scala/runtime/Statics.anyHash:(Ljava/lang/Object;)I
  #172 = Utf8               longHash
  #173 = Utf8               (J)I
  #174 = NameAndType        #172:#173     // longHash:(J)I
  #175 = Methodref          #167.#174     // scala/runtime/Statics.longHash:(J)I
  #176 = Utf8               code
  #177 = Utf8               I
  #178 = Utf8               tuple
  #179 = Utf8               ()Lscala/Tuple6;
  #180 = Utf8               ()Lscala/Tuple6<Ljava/lang/Object;Ljava/lang/Object;Lscala/Option<Ljava/lang/Object;>;Ljava/lang/Object;Ljava/lang/Object;Ljava/lang/Object;>;
  #181 = Utf8               scala/Tuple6
  #182 = Class              #181          // scala/Tuple6
  #183 = Utf8               boxToLong
  #184 = Utf8               (J)Ljava/lang/Long;
  #185 = NameAndType        #183:#184     // boxToLong:(J)Ljava/lang/Long;
  #186 = Methodref          #85.#185      // scala/runtime/BoxesRunTime.boxToLong:(J)Ljava/lang/Long;
  #187 = Utf8               boxToBoolean
  #188 = Utf8               (Z)Ljava/lang/Boolean;
  #189 = NameAndType        #187:#188     // boxToBoolean:(Z)Ljava/lang/Boolean;
  #190 = Methodref          #85.#189      // scala/runtime/BoxesRunTime.boxToBoolean:(Z)Ljava/lang/Boolean;
  #191 = Utf8               (Ljava/lang/Object;Ljava/lang/Object;Ljava/lang/Object;Ljava/lang/Object;Ljava/lang/Object;Ljava/lang/Object;)V
  #192 = NameAndType        #90:#191      // "<init>":(Ljava/lang/Object;Ljava/lang/Object;Ljava/lang/Object;Ljava/lang/Object;Ljava/lang/Object;Ljava/lang/Object;)V
  #193 = Methodref          #182.#192     // scala/Tuple6."<init>":(Ljava/lang/Object;Ljava/lang/Object;Ljava/lang/Object;Ljava/lang/Object;Ljava/lang/Object;Ljava/lang/Object;)V
  #194 = Utf8               productPrefix
  #195 = Utf8               productArity
  #196 = Utf8               productElement
  #197 = Utf8               (I)Ljava/lang/Object;
  #198 = Utf8               n
  #199 = Utf8               java/lang/IndexOutOfBoundsException
  #200 = Class              #199          // java/lang/IndexOutOfBoundsException
  #201 = Utf8               boxToInteger
  #202 = Utf8               (I)Ljava/lang/Integer;
  #203 = NameAndType        #201:#202     // boxToInteger:(I)Ljava/lang/Integer;
  #204 = Methodref          #85.#203      // scala/runtime/BoxesRunTime.boxToInteger:(I)Ljava/lang/Integer;
  #205 = Methodref          #159.#147     // java/lang/Object.toString:()Ljava/lang/String;
  #206 = Methodref          #200.#125     // java/lang/IndexOutOfBoundsException."<init>":(Ljava/lang/String;)V
  #207 = Utf8               productElementName
  #208 = Utf8               (I)Ljava/lang/String;
  #209 = String             #12           // downloaded
  #210 = String             #14           // previouslyDownloaded
  #211 = String             #15           // length
  #212 = String             #18           // startTime
  #213 = String             #19           // updateCheck
  #214 = String             #21           // watching
  #215 = Utf8               $this
  #216 = Utf8               x$1
  #217 = Utf8               (JJLscala/Option<Ljava/lang/Object;>;JZZ)V
  #218 = Utf8               ()V
  #219 = NameAndType        #90:#218      // "<init>":()V
  #220 = Methodref          #4.#219       // coursier/cache/loggers/RefreshInfo."<init>":()V
  #221 = Utf8               $deserializeLambda$
  #222 = Utf8               (Ljava/lang/invoke/SerializedLambda;)Ljava/lang/Object;
  #223 = Utf8               scala/runtime/LambdaDeserialize
  #224 = Class              #223          // scala/runtime/LambdaDeserialize
  #225 = Utf8               bootstrap
  #226 = Utf8               (Ljava/lang/invoke/MethodHandles$Lookup;Ljava/lang/String;Ljava/lang/invoke/MethodType;[Ljava/lang/invoke/MethodHandle;)Ljava/lang/invoke/CallSite;
  #227 = NameAndType        #225:#226     // bootstrap:(Ljava/lang/invoke/MethodHandles$Lookup;Ljava/lang/String;Ljava/lang/invoke/MethodType;[Ljava/lang/invoke/MethodHandle;)Ljava/lang/invoke/CallSite;
  #228 = Methodref          #224.#227     // scala/runtime/LambdaDeserialize.bootstrap:(Ljava/lang/invoke/MethodHandles$Lookup;Ljava/lang/String;Ljava/lang/invoke/MethodType;[Ljava/lang/invoke/MethodHandle;)Ljava/lang/invoke/CallSite;
  #229 = MethodHandle       6:#228        // REF_invokeStatic scala/runtime/LambdaDeserialize.bootstrap:(Ljava/lang/invoke/MethodHandles$Lookup;Ljava/lang/String;Ljava/lang/invoke/MethodType;[Ljava/lang/invoke/MethodHandle;)Ljava/lang/invoke/CallSite;
  #230 = Utf8               lambdaDeserialize
  #231 = NameAndType        #230:#222     // lambdaDeserialize:(Ljava/lang/invoke/SerializedLambda;)Ljava/lang/Object;
  #232 = InvokeDynamic      #1:#231       // #1:lambdaDeserialize:(Ljava/lang/invoke/SerializedLambda;)Ljava/lang/Object;
  #233 = Utf8               Signature
  #234 = Utf8               Code
  #235 = Utf8               LineNumberTable
  #236 = Utf8               LocalVariableTable
  #237 = Utf8               StackMapTable
  #238 = Utf8               MethodParameters
  #239 = Utf8               InnerClasses
  #240 = Utf8               SourceFile
  #241 = Utf8               BootstrapMethods
  #242 = Utf8               ScalaInlineInfo
  #243 = Utf8               Scala
{
  private final long downloaded;
    descriptor: J
    flags: (0x0012) ACC_PRIVATE, ACC_FINAL

  private final long previouslyDownloaded;
    descriptor: J
    flags: (0x0012) ACC_PRIVATE, ACC_FINAL

  private final scala.Option<java.lang.Object> length;
    descriptor: Lscala/Option;
    flags: (0x0012) ACC_PRIVATE, ACC_FINAL
    Signature: #17                          // Lscala/Option<Ljava/lang/Object;>;

  private final long startTime;
    descriptor: J
    flags: (0x0012) ACC_PRIVATE, ACC_FINAL

  private final boolean updateCheck;
    descriptor: Z
    flags: (0x0012) ACC_PRIVATE, ACC_FINAL

  private final boolean watching;
    descriptor: Z
    flags: (0x0012) ACC_PRIVATE, ACC_FINAL

  public long downloaded();
    descriptor: ()J
    flags: (0x0001) ACC_PUBLIC
    Code:
      stack=2, locals=1, args_size=1
         0: aload_0
         1: getfield      #24                 // Field downloaded:J
         4: lreturn
      LineNumberTable:
        line 12: 0
      LocalVariableTable:
        Start  Length  Slot  Name   Signature
            0       5     0  this   Lcoursier/cache/loggers/RefreshInfo$DownloadInfo;

  public long previouslyDownloaded();
    descriptor: ()J
    flags: (0x0001) ACC_PUBLIC
    Code:
      stack=2, locals=1, args_size=1
         0: aload_0
         1: getfield      #28                 // Field previouslyDownloaded:J
         4: lreturn
      LineNumberTable:
        line 12: 0
      LocalVariableTable:
        Start  Length  Slot  Name   Signature
            0       5     0  this   Lcoursier/cache/loggers/RefreshInfo$DownloadInfo;

  public scala.Option<java.lang.Object> length();
    descriptor: ()Lscala/Option;
    flags: (0x0001) ACC_PUBLIC
    Code:
      stack=1, locals=1, args_size=1
         0: aload_0
         1: getfield      #32                 // Field length:Lscala/Option;
         4: areturn
      LineNumberTable:
        line 12: 0
      LocalVariableTable:
        Start  Length  Slot  Name   Signature
            0       5     0  this   Lcoursier/cache/loggers/RefreshInfo$DownloadInfo;
    Signature: #30                          // ()Lscala/Option<Ljava/lang/Object;>;

  public long startTime();
    descriptor: ()J
    flags: (0x0001) ACC_PUBLIC
    Code:
      stack=2, locals=1, args_size=1
         0: aload_0
         1: getfield      #34                 // Field startTime:J
         4: lreturn
      LineNumberTable:
        line 12: 0
      LocalVariableTable:
        Start  Length  Slot  Name   Signature
            0       5     0  this   Lcoursier/cache/loggers/RefreshInfo$DownloadInfo;

  public boolean updateCheck();
    descriptor: ()Z
    flags: (0x0001) ACC_PUBLIC
    Code:
      stack=1, locals=1, args_size=1
         0: aload_0
         1: getfield      #37                 // Field updateCheck:Z
         4: ireturn
      LineNumberTable:
        line 12: 0
      LocalVariableTable:
        Start  Length  Slot  Name   Signature
            0       5     0  this   Lcoursier/cache/loggers/RefreshInfo$DownloadInfo;

  public boolean watching();
    descriptor: ()Z
    flags: (0x0001) ACC_PUBLIC
    Code:
      stack=1, locals=1, args_size=1
         0: aload_0
         1: getfield      #39                 // Field watching:Z
         4: ireturn
      LineNumberTable:
        line 12: 0
      LocalVariableTable:
        Start  Length  Slot  Name   Signature
            0       5     0  this   Lcoursier/cache/loggers/RefreshInfo$DownloadInfo;

  public scala.Option<java.lang.Object> fraction();
    descriptor: ()Lscala/Option;
    flags: (0x0001) ACC_PUBLIC
    Code:
      stack=2, locals=1, args_size=1
         0: aload_0
         1: invokevirtual #42                 // Method length:()Lscala/Option;
         4: aload_0
         5: invokedynamic #61,  0             // InvokeDynamic #0:apply$mcDJ$sp:(Lcoursier/cache/loggers/RefreshInfo$DownloadInfo;)Lscala/runtime/java8/JFunction1$mcDJ$sp;
        10: invokevirtual #67                 // Method scala/Option.map:(Lscala/Function1;)Lscala/Option;
        13: areturn
      LineNumberTable:
        line 21: 0
      LocalVariableTable:
        Start  Length  Slot  Name   Signature
            0      14     0  this   Lcoursier/cache/loggers/RefreshInfo$DownloadInfo;
    Signature: #30                          // ()Lscala/Option<Ljava/lang/Object;>;

  public scala.Option<java.lang.Object> rate();
    descriptor: ()Lscala/Option;
    flags: (0x0001) ACC_PUBLIC
    Code:
      stack=8, locals=3, args_size=1
         0: invokestatic  #73                 // Method java/lang/System.currentTimeMillis:()J
         3: lstore_1
         4: lload_1
         5: aload_0
         6: invokevirtual #75                 // Method startTime:()J
         9: lcmp
        10: ifle          50
        13: new           #77                 // class scala/Some
        16: dup
        17: aload_0
        18: invokevirtual #79                 // Method downloaded:()J
        21: aload_0
        22: invokevirtual #81                 // Method previouslyDownloaded:()J
        25: lsub
        26: l2d
        27: invokestatic  #73                 // Method java/lang/System.currentTimeMillis:()J
        30: aload_0
        31: invokevirtual #75                 // Method startTime:()J
        34: lsub
        35: l2d
        36: ddiv
        37: ldc2_w        #82                 // double 1000.0d
        40: dmul
        41: invokestatic  #89                 // Method scala/runtime/BoxesRunTime.boxToDouble:(D)Ljava/lang/Double;
        44: invokespecial #93                 // Method scala/Some."<init>":(Ljava/lang/Object;)V
        47: goto          53
        50: getstatic     #99                 // Field scala/None$.MODULE$:Lscala/None$;
        53: areturn
      StackMapTable: number_of_entries = 2
        frame_type = 252 /* append */
          offset_delta = 50
          locals = [ long ]
        frame_type = 66 /* same_locals_1_stack_item */
          stack = [ class scala/Option ]
      LineNumberTable:
        line 24: 0
        line 25: 4
        line 26: 13
        line 28: 50
      LocalVariableTable:
        Start  Length  Slot  Name   Signature
            4      49     1 currentTime   J
            0      54     0  this   Lcoursier/cache/loggers/RefreshInfo$DownloadInfo;
    Signature: #30                          // ()Lscala/Option<Ljava/lang/Object;>;

  public coursier.cache.loggers.RefreshInfo$DownloadInfo withDownloaded(long);
    descriptor: (J)Lcoursier/cache/loggers/RefreshInfo$DownloadInfo;
    flags: (0x0001) ACC_PUBLIC
    Code:
      stack=11, locals=3, args_size=2
         0: new           #2                  // class coursier/cache/loggers/RefreshInfo$DownloadInfo
         3: dup
         4: lload_1
         5: aload_0
         6: invokevirtual #81                 // Method previouslyDownloaded:()J
         9: aload_0
        10: invokevirtual #42                 // Method length:()Lscala/Option;
        13: aload_0
        14: invokevirtual #75                 // Method startTime:()J
        17: aload_0
        18: invokevirtual #104                // Method updateCheck:()Z
        21: aload_0
        22: invokevirtual #106                // Method watching:()Z
        25: invokespecial #109                // Method "<init>":(JJLscala/Option;JZZ)V
        28: areturn
      LineNumberTable:
        line 12: 0
      LocalVariableTable:
        Start  Length  Slot  Name   Signature
            0      29     0  this   Lcoursier/cache/loggers/RefreshInfo$DownloadInfo;
            0      29     1 downloaded   J
    MethodParameters:
      Name                           Flags
      downloaded                     final

  public coursier.cache.loggers.RefreshInfo$DownloadInfo withPreviouslyDownloaded(long);
    descriptor: (J)Lcoursier/cache/loggers/RefreshInfo$DownloadInfo;
    flags: (0x0001) ACC_PUBLIC
    Code:
      stack=11, locals=3, args_size=2
         0: new           #2                  // class coursier/cache/loggers/RefreshInfo$DownloadInfo
         3: dup
         4: aload_0
         5: invokevirtual #79                 // Method downloaded:()J
         8: lload_1
         9: aload_0
        10: invokevirtual #42                 // Method length:()Lscala/Option;
        13: aload_0
        14: invokevirtual #75                 // Method startTime:()J
        17: aload_0
        18: invokevirtual #104                // Method updateCheck:()Z
        21: aload_0
        22: invokevirtual #106                // Method watching:()Z
        25: invokespecial #109                // Method "<init>":(JJLscala/Option;JZZ)V
        28: areturn
      LineNumberTable:
        line 12: 0
      LocalVariableTable:
        Start  Length  Slot  Name   Signature
            0      29     0  this   Lcoursier/cache/loggers/RefreshInfo$DownloadInfo;
            0      29     1 previouslyDownloaded   J
    MethodParameters:
      Name                           Flags
      previouslyDownloaded           final

  public coursier.cache.loggers.RefreshInfo$DownloadInfo withLength(scala.Option<java.lang.Object>);
    descriptor: (Lscala/Option;)Lcoursier/cache/loggers/RefreshInfo$DownloadInfo;
    flags: (0x0001) ACC_PUBLIC
    Code:
      stack=11, locals=2, args_size=2
         0: new           #2                  // class coursier/cache/loggers/RefreshInfo$DownloadInfo
         3: dup
         4: aload_0
         5: invokevirtual #79                 // Method downloaded:()J
         8: aload_0
         9: invokevirtual #81                 // Method previouslyDownloaded:()J
        12: aload_1
        13: aload_0
        14: invokevirtual #75                 // Method startTime:()J
        17: aload_0
        18: invokevirtual #104                // Method updateCheck:()Z
        21: aload_0
        22: invokevirtual #106                // Method watching:()Z
        25: invokespecial #109                // Method "<init>":(JJLscala/Option;JZZ)V
        28: areturn
      LineNumberTable:
        line 12: 0
      LocalVariableTable:
        Start  Length  Slot  Name   Signature
            0      29     0  this   Lcoursier/cache/loggers/RefreshInfo$DownloadInfo;
            0      29     1 length   Lscala/Option;
    Signature: #113                         // (Lscala/Option<Ljava/lang/Object;>;)Lcoursier/cache/loggers/RefreshInfo$DownloadInfo;
    MethodParameters:
      Name                           Flags
      length                         final

  public coursier.cache.loggers.RefreshInfo$DownloadInfo withStartTime(long);
    descriptor: (J)Lcoursier/cache/loggers/RefreshInfo$DownloadInfo;
    flags: (0x0001) ACC_PUBLIC
    Code:
      stack=11, locals=3, args_size=2
         0: new           #2                  // class coursier/cache/loggers/RefreshInfo$DownloadInfo
         3: dup
         4: aload_0
         5: invokevirtual #79                 // Method downloaded:()J
         8: aload_0
         9: invokevirtual #81                 // Method previouslyDownloaded:()J
        12: aload_0
        13: invokevirtual #42                 // Method length:()Lscala/Option;
        16: lload_1
        17: aload_0
        18: invokevirtual #104                // Method updateCheck:()Z
        21: aload_0
        22: invokevirtual #106                // Method watching:()Z
        25: invokespecial #109                // Method "<init>":(JJLscala/Option;JZZ)V
        28: areturn
      LineNumberTable:
        line 12: 0
      LocalVariableTable:
        Start  Length  Slot  Name   Signature
            0      29     0  this   Lcoursier/cache/loggers/RefreshInfo$DownloadInfo;
            0      29     1 startTime   J
    MethodParameters:
      Name                           Flags
      startTime                      final

  public coursier.cache.loggers.RefreshInfo$DownloadInfo withUpdateCheck(boolean);
    descriptor: (Z)Lcoursier/cache/loggers/RefreshInfo$DownloadInfo;
    flags: (0x0001) ACC_PUBLIC
    Code:
      stack=11, locals=2, args_size=2
         0: new           #2                  // class coursier/cache/loggers/RefreshInfo$DownloadInfo
         3: dup
         4: aload_0
         5: invokevirtual #79                 // Method downloaded:()J
         8: aload_0
         9: invokevirtual #81                 // Method previouslyDownloaded:()J
        12: aload_0
        13: invokevirtual #42                 // Method length:()Lscala/Option;
        16: aload_0
        17: invokevirtual #75                 // Method startTime:()J
        20: iload_1
        21: aload_0
        22: invokevirtual #106                // Method watching:()Z
        25: invokespecial #109                // Method "<init>":(JJLscala/Option;JZZ)V
        28: areturn
      LineNumberTable:
        line 12: 0
      LocalVariableTable:
        Start  Length  Slot  Name   Signature
            0      29     0  this   Lcoursier/cache/loggers/RefreshInfo$DownloadInfo;
            0      29     1 updateCheck   Z
    MethodParameters:
      Name                           Flags
      updateCheck                    final

  public coursier.cache.loggers.RefreshInfo$DownloadInfo withWatching(boolean);
    descriptor: (Z)Lcoursier/cache/loggers/RefreshInfo$DownloadInfo;
    flags: (0x0001) ACC_PUBLIC
    Code:
      stack=11, locals=2, args_size=2
         0: new           #2                  // class coursier/cache/loggers/RefreshInfo$DownloadInfo
         3: dup
         4: aload_0
         5: invokevirtual #79                 // Method downloaded:()J
         8: aload_0
         9: invokevirtual #81                 // Method previouslyDownloaded:()J
        12: aload_0
        13: invokevirtual #42                 // Method length:()Lscala/Option;
        16: aload_0
        17: invokevirtual #75                 // Method startTime:()J
        20: aload_0
        21: invokevirtual #104                // Method updateCheck:()Z
        24: iload_1
        25: invokespecial #109                // Method "<init>":(JJLscala/Option;JZZ)V
        28: areturn
      LineNumberTable:
        line 12: 0
      LocalVariableTable:
        Start  Length  Slot  Name   Signature
            0      29     0  this   Lcoursier/cache/loggers/RefreshInfo$DownloadInfo;
            0      29     1 watching   Z
    MethodParameters:
      Name                           Flags
      watching                       final

  public java.lang.String toString();
    descriptor: ()Ljava/lang/String;
    flags: (0x0001) ACC_PUBLIC
    Code:
      stack=3, locals=2, args_size=1
         0: new           #121                // class java/lang/StringBuilder
         3: dup
         4: ldc           #123                // String DownloadInfo(
         6: invokespecial #126                // Method java/lang/StringBuilder."<init>":(Ljava/lang/String;)V
         9: astore_1
        10: aload_1
        11: aload_0
        12: invokevirtual #79                 // Method downloaded:()J
        15: invokestatic  #132                // Method java/lang/String.valueOf:(J)Ljava/lang/String;
        18: invokevirtual #136                // Method java/lang/StringBuilder.append:(Ljava/lang/String;)Ljava/lang/StringBuilder;
        21: pop
        22: aload_1
        23: ldc           #138                // String ,
        25: invokevirtual #136                // Method java/lang/StringBuilder.append:(Ljava/lang/String;)Ljava/lang/StringBuilder;
        28: pop
        29: aload_1
        30: aload_0
        31: invokevirtual #81                 // Method previouslyDownloaded:()J
        34: invokestatic  #132                // Method java/lang/String.valueOf:(J)Ljava/lang/String;
        37: invokevirtual #136                // Method java/lang/StringBuilder.append:(Ljava/lang/String;)Ljava/lang/StringBuilder;
        40: pop
        41: aload_1
        42: ldc           #138                // String ,
        44: invokevirtual #136                // Method java/lang/StringBuilder.append:(Ljava/lang/String;)Ljava/lang/StringBuilder;
        47: pop
        48: aload_1
        49: aload_0
        50: invokevirtual #42                 // Method length:()Lscala/Option;
        53: invokestatic  #141                // Method java/lang/String.valueOf:(Ljava/lang/Object;)Ljava/lang/String;
        56: invokevirtual #136                // Method java/lang/StringBuilder.append:(Ljava/lang/String;)Ljava/lang/StringBuilder;
        59: pop
        60: aload_1
        61: ldc           #138                // String ,
        63: invokevirtual #136                // Method java/lang/StringBuilder.append:(Ljava/lang/String;)Ljava/lang/StringBuilder;
        66: pop
        67: aload_1
        68: aload_0
        69: invokevirtual #75                 // Method startTime:()J
        72: invokestatic  #132                // Method java/lang/String.valueOf:(J)Ljava/lang/String;
        75: invokevirtual #136                // Method java/lang/StringBuilder.append:(Ljava/lang/String;)Ljava/lang/StringBuilder;
        78: pop
        79: aload_1
        80: ldc           #138                // String ,
        82: invokevirtual #136                // Method java/lang/StringBuilder.append:(Ljava/lang/String;)Ljava/lang/StringBuilder;
        85: pop
        86: aload_1
        87: aload_0
        88: invokevirtual #104                // Method updateCheck:()Z
        91: invokestatic  #144                // Method java/lang/String.valueOf:(Z)Ljava/lang/String;
        94: invokevirtual #136                // Method java/lang/StringBuilder.append:(Ljava/lang/String;)Ljava/lang/StringBuilder;
        97: pop
        98: aload_1
        99: ldc           #138                // String ,
       101: invokevirtual #136                // Method java/lang/StringBuilder.append:(Ljava/lang/String;)Ljava/lang/StringBuilder;
       104: pop
       105: aload_1
       106: aload_0
       107: invokevirtual #106                // Method watching:()Z
       110: invokestatic  #144                // Method java/lang/String.valueOf:(Z)Ljava/lang/String;
       113: invokevirtual #136                // Method java/lang/StringBuilder.append:(Ljava/lang/String;)Ljava/lang/StringBuilder;
       116: pop
       117: aload_1
       118: ldc           #146                // String )
       120: invokevirtual #136                // Method java/lang/StringBuilder.append:(Ljava/lang/String;)Ljava/lang/StringBuilder;
       123: pop
       124: aload_1
       125: invokevirtual #148                // Method java/lang/StringBuilder.toString:()Ljava/lang/String;
       128: areturn
      LineNumberTable:
        line 12: 0
      LocalVariableTable:
        Start  Length  Slot  Name   Signature
           10     118     1     b   Ljava/lang/StringBuilder;
            0     129     0  this   Lcoursier/cache/loggers/RefreshInfo$DownloadInfo;

  public boolean canEqual(java.lang.Object);
    descriptor: (Ljava/lang/Object;)Z
    flags: (0x0001) ACC_PUBLIC
    Code:
      stack=1, locals=2, args_size=2
         0: aload_1
         1: ifnull        15
         4: aload_1
         5: instanceof    #2                  // class coursier/cache/loggers/RefreshInfo$DownloadInfo
         8: ifeq          15
        11: iconst_1
        12: goto          16
        15: iconst_0
        16: ireturn
      StackMapTable: number_of_entries = 2
        frame_type = 15 /* same */
        frame_type = 64 /* same_locals_1_stack_item */
          stack = [ int ]
      LineNumberTable:
        line 12: 0
      LocalVariableTable:
        Start  Length  Slot  Name   Signature
            0      17     0  this   Lcoursier/cache/loggers/RefreshInfo$DownloadInfo;
            0      17     1   obj   Ljava/lang/Object;
    MethodParameters:
      Name                           Flags
      obj                            final

  public boolean equals(java.lang.Object);
    descriptor: (Ljava/lang/Object;)Z
    flags: (0x0001) ACC_PUBLIC
    Code:
      stack=4, locals=4, args_size=2
         0: aload_0
         1: aload_1
         2: if_acmpeq     116
         5: aload_0
         6: aload_1
         7: invokevirtual #157                // Method canEqual:(Ljava/lang/Object;)Z
        10: ifeq          120
        13: aload_1
        14: checkcast     #2                  // class coursier/cache/loggers/RefreshInfo$DownloadInfo
        17: astore_2
        18: iconst_1
        19: ifeq          112
        22: aload_0
        23: invokevirtual #79                 // Method downloaded:()J
        26: aload_2
        27: invokevirtual #79                 // Method downloaded:()J
        30: lcmp
        31: ifne          112
        34: aload_0
        35: invokevirtual #81                 // Method previouslyDownloaded:()J
        38: aload_2
        39: invokevirtual #81                 // Method previouslyDownloaded:()J
        42: lcmp
        43: ifne          112
        46: aload_0
        47: invokevirtual #42                 // Method length:()Lscala/Option;
        50: aload_2
        51: invokevirtual #42                 // Method length:()Lscala/Option;
        54: astore_3
        55: dup
        56: ifnonnull     67
        59: pop
        60: aload_3
        61: ifnull        74
        64: goto          112
        67: aload_3
        68: invokevirtual #161                // Method java/lang/Object.equals:(Ljava/lang/Object;)Z
        71: ifeq          112
        74: aload_0
        75: invokevirtual #75                 // Method startTime:()J
        78: aload_2
        79: invokevirtual #75                 // Method startTime:()J
        82: lcmp
        83: ifne          112
        86: aload_0
        87: invokevirtual #104                // Method updateCheck:()Z
        90: aload_2
        91: invokevirtual #104                // Method updateCheck:()Z
        94: if_icmpne     112
        97: aload_0
        98: invokevirtual #106                // Method watching:()Z
       101: aload_2
       102: invokevirtual #106                // Method watching:()Z
       105: if_icmpne     112
       108: iconst_1
       109: goto          113
       112: iconst_0
       113: ifeq          120
       116: iconst_1
       117: goto          121
       120: iconst_0
       121: ireturn
      StackMapTable: number_of_entries = 7
        frame_type = 255 /* full_frame */
          offset_delta = 67
          locals = [ class coursier/cache/loggers/RefreshInfo$DownloadInfo, class java/lang/Object, class coursier/cache/loggers/RefreshInfo$DownloadInfo, class scala/Option ]
          stack = [ class scala/Option ]
        frame_type = 6 /* same */
        frame_type = 250 /* chop */
          offset_delta = 37
        frame_type = 64 /* same_locals_1_stack_item */
          stack = [ int ]
        frame_type = 250 /* chop */
          offset_delta = 2
        frame_type = 3 /* same */
        frame_type = 64 /* same_locals_1_stack_item */
          stack = [ int ]
      LineNumberTable:
        line 12: 0
      LocalVariableTable:
        Start  Length  Slot  Name   Signature
           18      95     2 other   Lcoursier/cache/loggers/RefreshInfo$DownloadInfo;
            0     122     0  this   Lcoursier/cache/loggers/RefreshInfo$DownloadInfo;
            0     122     1   obj   Ljava/lang/Object;
    MethodParameters:
      Name                           Flags
      obj                            final

  public int hashCode();
    descriptor: ()I
    flags: (0x0001) ACC_PUBLIC
    Code:
      stack=3, locals=2, args_size=1
         0: bipush        17
         2: ldc           #165                // String DownloadInfo
         4: invokestatic  #171                // Method scala/runtime/Statics.anyHash:(Ljava/lang/Object;)I
         7: iadd
         8: istore_1
         9: bipush        37
        11: iload_1
        12: imul
        13: aload_0
        14: invokevirtual #79                 // Method downloaded:()J
        17: invokestatic  #175                // Method scala/runtime/Statics.longHash:(J)I
        20: iadd
        21: istore_1
        22: bipush        37
        24: iload_1
        25: imul
        26: aload_0
        27: invokevirtual #81                 // Method previouslyDownloaded:()J
        30: invokestatic  #175                // Method scala/runtime/Statics.longHash:(J)I
        33: iadd
        34: istore_1
        35: bipush        37
        37: iload_1
        38: imul
        39: aload_0
        40: invokevirtual #42                 // Method length:()Lscala/Option;
        43: invokestatic  #171                // Method scala/runtime/Statics.anyHash:(Ljava/lang/Object;)I
        46: iadd
        47: istore_1
        48: bipush        37
        50: iload_1
        51: imul
        52: aload_0
        53: invokevirtual #75                 // Method startTime:()J
        56: invokestatic  #175                // Method scala/runtime/Statics.longHash:(J)I
        59: iadd
        60: istore_1
        61: bipush        37
        63: iload_1
        64: imul
        65: aload_0
        66: invokevirtual #104                // Method updateCheck:()Z
        69: ifeq          78
        72: sipush        1231
        75: goto          81
        78: sipush        1237
        81: iadd
        82: istore_1
        83: bipush        37
        85: iload_1
        86: imul
        87: aload_0
        88: invokevirtual #106                // Method watching:()Z
        91: ifeq          100
        94: sipush        1231
        97: goto          103
       100: sipush        1237
       103: iadd
       104: istore_1
       105: bipush        37
       107: iload_1
       108: imul
       109: ireturn
      StackMapTable: number_of_entries = 4
        frame_type = 255 /* full_frame */
          offset_delta = 78
          locals = [ class coursier/cache/loggers/RefreshInfo$DownloadInfo, int ]
          stack = [ int ]
        frame_type = 255 /* full_frame */
          offset_delta = 2
          locals = [ class coursier/cache/loggers/RefreshInfo$DownloadInfo, int ]
          stack = [ int, int ]
        frame_type = 82 /* same_locals_1_stack_item */
          stack = [ int ]
        frame_type = 255 /* full_frame */
          offset_delta = 2
          locals = [ class coursier/cache/loggers/RefreshInfo$DownloadInfo, int ]
          stack = [ int, int ]
      LineNumberTable:
        line 12: 0
      LocalVariableTable:
        Start  Length  Slot  Name   Signature
            9     100     1  code   I
            0     110     0  this   Lcoursier/cache/loggers/RefreshInfo$DownloadInfo;

  private scala.Tuple6<java.lang.Object, java.lang.Object, scala.Option<java.lang.Object>, java.lang.Object, java.lang.Object, java.lang.Object> tuple();
    descriptor: ()Lscala/Tuple6;
    flags: (0x0002) ACC_PRIVATE
    Code:
      stack=8, locals=1, args_size=1
         0: new           #182                // class scala/Tuple6
         3: dup
         4: aload_0
         5: invokevirtual #79                 // Method downloaded:()J
         8: invokestatic  #186                // Method scala/runtime/BoxesRunTime.boxToLong:(J)Ljava/lang/Long;
        11: aload_0
        12: invokevirtual #81                 // Method previouslyDownloaded:()J
        15: invokestatic  #186                // Method scala/runtime/BoxesRunTime.boxToLong:(J)Ljava/lang/Long;
        18: aload_0
        19: invokevirtual #42                 // Method length:()Lscala/Option;
        22: aload_0
        23: invokevirtual #75                 // Method startTime:()J
        26: invokestatic  #186                // Method scala/runtime/BoxesRunTime.boxToLong:(J)Ljava/lang/Long;
        29: aload_0
        30: invokevirtual #104                // Method updateCheck:()Z
        33: invokestatic  #190                // Method scala/runtime/BoxesRunTime.boxToBoolean:(Z)Ljava/lang/Boolean;
        36: aload_0
        37: invokevirtual #106                // Method watching:()Z
        40: invokestatic  #190                // Method scala/runtime/BoxesRunTime.boxToBoolean:(Z)Ljava/lang/Boolean;
        43: invokespecial #193                // Method scala/Tuple6."<init>":(Ljava/lang/Object;Ljava/lang/Object;Ljava/lang/Object;Ljava/lang/Object;Ljava/lang/Object;Ljava/lang/Object;)V
        46: areturn
      LineNumberTable:
        line 12: 0
      LocalVariableTable:
        Start  Length  Slot  Name   Signature
            0      47     0  this   Lcoursier/cache/loggers/RefreshInfo$DownloadInfo;
    Signature: #180                         // ()Lscala/Tuple6<Ljava/lang/Object;Ljava/lang/Object;Lscala/Option<Ljava/lang/Object;>;Ljava/lang/Object;Ljava/lang/Object;Ljava/lang/Object;>;

  public java.lang.String productPrefix();
    descriptor: ()Ljava/lang/String;
    flags: (0x0001) ACC_PUBLIC
    Code:
      stack=1, locals=1, args_size=1
         0: ldc           #165                // String DownloadInfo
         2: areturn
      LineNumberTable:
        line 12: 0
      LocalVariableTable:
        Start  Length  Slot  Name   Signature
            0       3     0  this   Lcoursier/cache/loggers/RefreshInfo$DownloadInfo;

  public int productArity();
    descriptor: ()I
    flags: (0x0001) ACC_PUBLIC
    Code:
      stack=1, locals=1, args_size=1
         0: bipush        6
         2: ireturn
      LineNumberTable:
        line 12: 0
      LocalVariableTable:
        Start  Length  Slot  Name   Signature
            0       3     0  this   Lcoursier/cache/loggers/RefreshInfo$DownloadInfo;

  public java.lang.Object productElement(int);
    descriptor: (I)Ljava/lang/Object;
    flags: (0x0001) ACC_PUBLIC
    Code:
      stack=3, locals=3, args_size=2
         0: iload_1
         1: istore_2
         2: iload_2
         3: tableswitch   { // 0 to 5
                       0: 40
                       1: 50
                       2: 60
                       3: 67
                       4: 77
                       5: 87
                 default: 97
            }
        40: aload_0
        41: invokevirtual #79                 // Method downloaded:()J
        44: invokestatic  #186                // Method scala/runtime/BoxesRunTime.boxToLong:(J)Ljava/lang/Long;
        47: goto          112
        50: aload_0
        51: invokevirtual #81                 // Method previouslyDownloaded:()J
        54: invokestatic  #186                // Method scala/runtime/BoxesRunTime.boxToLong:(J)Ljava/lang/Long;
        57: goto          112
        60: aload_0
        61: invokevirtual #42                 // Method length:()Lscala/Option;
        64: goto          112
        67: aload_0
        68: invokevirtual #75                 // Method startTime:()J
        71: invokestatic  #186                // Method scala/runtime/BoxesRunTime.boxToLong:(J)Ljava/lang/Long;
        74: goto          112
        77: aload_0
        78: invokevirtual #104                // Method updateCheck:()Z
        81: invokestatic  #190                // Method scala/runtime/BoxesRunTime.boxToBoolean:(Z)Ljava/lang/Boolean;
        84: goto          112
        87: aload_0
        88: invokevirtual #106                // Method watching:()Z
        91: invokestatic  #190                // Method scala/runtime/BoxesRunTime.boxToBoolean:(Z)Ljava/lang/Boolean;
        94: goto          112
        97: new           #200                // class java/lang/IndexOutOfBoundsException
       100: dup
       101: iload_2
       102: invokestatic  #204                // Method scala/runtime/BoxesRunTime.boxToInteger:(I)Ljava/lang/Integer;
       105: invokevirtual #205                // Method java/lang/Object.toString:()Ljava/lang/String;
       108: invokespecial #206                // Method java/lang/IndexOutOfBoundsException."<init>":(Ljava/lang/String;)V
       111: athrow
       112: areturn
      StackMapTable: number_of_entries = 8
        frame_type = 252 /* append */
          offset_delta = 40
          locals = [ int ]
        frame_type = 9 /* same */
        frame_type = 9 /* same */
        frame_type = 6 /* same */
        frame_type = 9 /* same */
        frame_type = 9 /* same */
        frame_type = 9 /* same */
        frame_type = 78 /* same_locals_1_stack_item */
          stack = [ class java/lang/Object ]
      LineNumberTable:
        line 12: 0
      LocalVariableTable:
        Start  Length  Slot  Name   Signature
            0     113     0  this   Lcoursier/cache/loggers/RefreshInfo$DownloadInfo;
            0     113     1     n   I
    MethodParameters:
      Name                           Flags
      n                              final

  public java.lang.String productElementName(int);
    descriptor: (I)Ljava/lang/String;
    flags: (0x0001) ACC_PUBLIC
    Code:
      stack=3, locals=3, args_size=2
         0: iload_1
         1: istore_2
         2: iload_2
         3: tableswitch   { // 0 to 5
                       0: 40
                       1: 45
                       2: 50
                       3: 55
                       4: 60
                       5: 65
                 default: 70
            }
        40: ldc           #209                // String downloaded
        42: goto          85
        45: ldc           #210                // String previouslyDownloaded
        47: goto          85
        50: ldc           #211                // String length
        52: goto          85
        55: ldc           #212                // String startTime
        57: goto          85
        60: ldc           #213                // String updateCheck
        62: goto          85
        65: ldc           #214                // String watching
        67: goto          85
        70: new           #200                // class java/lang/IndexOutOfBoundsException
        73: dup
        74: iload_2
        75: invokestatic  #204                // Method scala/runtime/BoxesRunTime.boxToInteger:(I)Ljava/lang/Integer;
        78: invokevirtual #205                // Method java/lang/Object.toString:()Ljava/lang/String;
        81: invokespecial #206                // Method java/lang/IndexOutOfBoundsException."<init>":(Ljava/lang/String;)V
        84: athrow
        85: areturn
      StackMapTable: number_of_entries = 8
        frame_type = 252 /* append */
          offset_delta = 40
          locals = [ int ]
        frame_type = 4 /* same */
        frame_type = 4 /* same */
        frame_type = 4 /* same */
        frame_type = 4 /* same */
        frame_type = 4 /* same */
        frame_type = 4 /* same */
        frame_type = 78 /* same_locals_1_stack_item */
          stack = [ class java/lang/String ]
      LineNumberTable:
        line 12: 0
      LocalVariableTable:
        Start  Length  Slot  Name   Signature
            0      86     0  this   Lcoursier/cache/loggers/RefreshInfo$DownloadInfo;
            0      86     1     n   I
    MethodParameters:
      Name                           Flags
      n                              final

  public static final double $anonfun$fraction$1(coursier.cache.loggers.RefreshInfo$DownloadInfo, long);
    descriptor: (Lcoursier/cache/loggers/RefreshInfo$DownloadInfo;J)D
    flags: (0x1019) ACC_PUBLIC, ACC_STATIC, ACC_FINAL, ACC_SYNTHETIC
    Code:
      stack=4, locals=3, args_size=2
         0: aload_0
         1: invokevirtual #79                 // Method downloaded:()J
         4: l2d
         5: lload_1
         6: l2d
         7: ddiv
         8: dreturn
      LineNumberTable:
        line 21: 0
      LocalVariableTable:
        Start  Length  Slot  Name   Signature
            0       9     0 $this   Lcoursier/cache/loggers/RefreshInfo$DownloadInfo;
            0       9     1   x$1   J
    MethodParameters:
      Name                           Flags
      $this                          final synthetic
      x$1                            final

  public coursier.cache.loggers.RefreshInfo$DownloadInfo(long, long, scala.Option<java.lang.Object>, long, boolean, boolean);
    descriptor: (JJLscala/Option;JZZ)V
    flags: (0x0001) ACC_PUBLIC
    Code:
      stack=3, locals=10, args_size=7
         0: aload_0
         1: lload_1
         2: putfield      #24                 // Field downloaded:J
         5: aload_0
         6: lload_3
         7: putfield      #28                 // Field previouslyDownloaded:J
        10: aload_0
        11: aload         5
        13: putfield      #32                 // Field length:Lscala/Option;
        16: aload_0
        17: lload         6
        19: putfield      #34                 // Field startTime:J
        22: aload_0
        23: iload         8
        25: putfield      #37                 // Field updateCheck:Z
        28: aload_0
        29: iload         9
        31: putfield      #39                 // Field watching:Z
        34: aload_0
        35: invokespecial #220                // Method coursier/cache/loggers/RefreshInfo."<init>":()V
        38: return
      LineNumberTable:
        line 12: 0
        line 19: 34
        line 12: 38
      LocalVariableTable:
        Start  Length  Slot  Name   Signature
            0      39     0  this   Lcoursier/cache/loggers/RefreshInfo$DownloadInfo;
            0      39     1 downloaded   J
            0      39     3 previouslyDownloaded   J
            0      39     5 length   Lscala/Option;
            0      39     6 startTime   J
            0      39     8 updateCheck   Z
            0      39     9 watching   Z
    Signature: #217                         // (JJLscala/Option<Ljava/lang/Object;>;JZZ)V
    MethodParameters:
      Name                           Flags
      downloaded                     final
      previouslyDownloaded           final
      length                         final
      startTime                      final
      updateCheck                    final
      watching                       final

  private static java.lang.Object $deserializeLambda$(java.lang.invoke.SerializedLambda);
    descriptor: (Ljava/lang/invoke/SerializedLambda;)Ljava/lang/Object;
    flags: (0x100a) ACC_PRIVATE, ACC_STATIC, ACC_SYNTHETIC
    Code:
      stack=1, locals=1, args_size=1
         0: aload_0
         1: invokedynamic #232,  0            // InvokeDynamic #1:lambdaDeserialize:(Ljava/lang/invoke/SerializedLambda;)Ljava/lang/Object;
         6: areturn
}
InnerClasses:
  public static final #6= #2 of #4;       // DownloadInfo=class coursier/cache/loggers/RefreshInfo$DownloadInfo of class coursier/cache/loggers/RefreshInfo
  public static final #11= #8 of #10;     // Lookup=class java/lang/invoke/MethodHandles$Lookup of class java/lang/invoke/MethodHandles
SourceFile: "RefreshInfo.scala"
BootstrapMethods:
  0: #57 REF_invokeStatic java/lang/invoke/LambdaMetafactory.altMetafactory:(Ljava/lang/invoke/MethodHandles$Lookup;Ljava/lang/String;Ljava/lang/invoke/MethodType;[Ljava/lang/Object;)Ljava/lang/invoke/CallSite;
    Method arguments:
      #44 (J)D
      #49 REF_invokeStatic coursier/cache/loggers/RefreshInfo$DownloadInfo.$anonfun$fraction$1:(Lcoursier/cache/loggers/RefreshInfo$DownloadInfo;J)D
      #44 (J)D
      #50 1
  1: #229 REF_invokeStatic scala/runtime/LambdaDeserialize.bootstrap:(Ljava/lang/invoke/MethodHandles$Lookup;Ljava/lang/String;Ljava/lang/invoke/MethodType;[Ljava/lang/invoke/MethodHandle;)Ljava/lang/invoke/CallSite;
    Method arguments:
      #49 REF_invokeStatic coursier/cache/loggers/RefreshInfo$DownloadInfo.$anonfun$fraction$1:(Lcoursier/cache/loggers/RefreshInfo$DownloadInfo;J)D
  ScalaInlineInfo: length = 0x81 (unknown attribute)
   01 01 00 19 00 2D 00 2E 01 00 5A 00 6B 01 00 97
   00 98 01 00 0C 00 16 01 00 9B 00 98 01 00 28 00
   1D 01 00 A3 00 A4 01 00 0F 00 1D 01 00 0E 00 16
   01 00 C3 00 A4 01 00 C4 00 C5 01 00 CF 00 D0 01
   00 C2 00 77 01 00 44 00 1D 01 00 12 00 16 01 00
   76 00 77 01 00 B2 00 B3 01 00 13 00 23 01 00 15
   00 23 01 00 65 00 66 01 00 6F 00 70 01 00 6E 00
   66 01 00 72 00 66 01 00 73 00 74 01 00 75 00 74
   01
  Scala: length = 0x0 (unknown attribute)

