Classfile /Users/mw/Projects/slang-braindump/.jar/jar11/assemble/slang-braindump/assemble/content/coursier/cache/loggers/RefreshDisplay.class
  Last modified May 29, 2022; size 3507 bytes
  SHA-256 checksum 0a753e015b89c0bca7886b863c00c4a3e31e6cb8b8fb9bf5da20f4bea9824deb
  Compiled from "RefreshDisplay.scala"
public interface coursier.cache.loggers.RefreshDisplay
  minor version: 0
  major version: 52
  flags: (0x0601) ACC_PUBLIC, ACC_INTERFACE, ACC_ABSTRACT
  this_class: #2                          // coursier/cache/loggers/RefreshDisplay
  super_class: #4                         // java/lang/Object
  interfaces: 0, fields: 0, methods: 12, attributes: 4
Constant pool:
   #1 = Utf8               coursier/cache/loggers/RefreshDisplay
   #2 = Class              #1             // coursier/cache/loggers/RefreshDisplay
   #3 = Utf8               java/lang/Object
   #4 = Class              #3             // java/lang/Object
   #5 = Utf8               RefreshDisplay.scala
   #6 = Utf8               Lscala/reflect/ScalaSignature;
   #7 = Utf8               bytes
   #8 = Utf8               \u0006\u0005y4q!\u0004\b\u0011\u0002\u0007\u0005Q\u0003C\u0003\u001d\u0001\u0011\u0005Q\u0004C\u0003\"\u0001\u0011\u0005!\u0005C\u0003A\u0001\u0011\u0005\u0011\tC\u0003F\u0001\u0011\u0005a\tC\u0003M\u0001\u0019\u0005Q\nC\u0003e\u0001\u0011\u0005Q\rC\u0003h\u0001\u0019\u0005\u0001nB\u0003r\u001d!\u0005!OB\u0003\u000e\u001d!\u00051\u000fC\u0003u\u0013\u0011\u0005Q\u000f\u0003\u0005w\u0013!\u0015\r\u0011\"\u0003x\u0011\u0015A\u0018\u0002\"\u0001z\u00059\u0011VM\u001a:fg\"$\u0015n\u001d9mCfT!a\u0004\t\u0002\u000f1|wmZ3sg*\u0011\u0011CE\u0001\u0006G\u0006\u001c\u0007.\u001a\u0006\u0002\'\u0005A1m\\;sg&,\'o\u0001\u0001\u0014\u0005\u00011\u0002CA\f\u001b\u001b\u0005A\"\"A\r\u0002\u000bM\u001c\u0017\r\\1\n\u0005mA\"AB!osJ+g-\u0001\u0004%S:LG\u000f\n\u000b\u0002=A\u0011qcH\u0005\u0003Aa\u0011A!\u00168ji\u0006Aa.Z<F]R\u0014\u0018\u0010\u0006\u0003\u001fG5R\u0004\"\u0002\u0013\u0003\u0001\u0004)\u0013aA8viB\u0011aeK\u0007\u0002O)\u0011\u0001&K\u0001\u0003S>T\u0011AK\u0001\u0005U\u00064\u0018-\u0003\u0002-O\t1qK]5uKJDQA\f\u0002A\u0002=\n1!\u001e:m!\t\u0001tG\u0004\u00022kA\u0011!\u0007G\u0007\u0002g)\u0011A\u0007F\u0001\u0007yI|w\u000e\u001e \n\u0005YB\u0012A\u0002)sK\u0012,g-\u0003\u00029s\t11\u000b\u001e:j]\u001eT!A\u000e\r\t\u000bm\u0012\u0001\u0019\u0001\u001f\u0002\t%tgm\u001c\t\u0003{yj\u0011AD\u0005\u0003\u007f9\u00111BU3ge\u0016\u001c\b.\u00138g_\u0006Y!/Z7pm\u0016,e\u000e\u001e:z)\u0011q\"i\u0011#\t\u000b\u0011\u001a\u0001\u0019A\u0013\t\u000b9\u001a\u0001\u0019A\u0018\t\u000bm\u001a\u0001\u0019\u0001\u001f\u0002\u0011ML\'0\u001a%j]R$\"AH$\t\u000b!#\u0001\u0019A%\u0002\u00039\u0004\"a\u0006&\n\u0005-C\"aA%oi\u00061Q\u000f\u001d3bi\u0016$RA\b(P;~CQ\u0001J\u0003A\u0002\u0015BQ\u0001U\u0003A\u0002E\u000bA\u0001Z8oKB\u0019!k\u0016.\u000f\u0005M+fB\u0001\u001aU\u0013\u0005I\u0012B\u0001,\u0019\u0003\u001d\u0001\u0018mY6bO\u0016L!\u0001W-\u0003\u0007M+\u0017O\u0003\u0002W1A!qcW\u0018=\u0013\ta\u0006D\u0001\u0004UkBdWM\r\u0005\u0006=\u0016\u0001\r!U\u0001\nI><h\u000e\\8bINDQ\u0001Y\u0003A\u0002\u0005\fqa\u00195b]\u001e,G\r\u0005\u0002\u0018E&\u00111\r\u0007\u0002\b\u0005>|G.Z1o\u0003\u0011\u0019Ho\u001c9\u0015\u0005y1\u0007\"\u0002\u0013\u0007\u0001\u0004)\u0013a\u0004:fMJ,7\u000f[%oi\u0016\u0014h/\u00197\u0016\u0003%\u0004\"A[8\u000e\u0003-T!\u0001\\7\u0002\u0011\u0011,(/\u0019;j_:T!A\u001c\r\u0002\u0015\r|gnY;se\u0016tG/\u0003\u0002qW\nAA)\u001e:bi&|g.\u0001\bSK\u001a\u0014Xm\u001d5ESN\u0004H.Y=\u0011\u0005uJ1CA\u0005\u0017\u0003\u0019a\u0014N\\5u}Q\t!/A\u0005jg^Kg\u000eZ8xgV\t\u0011-A\u0005ueVt7-\u0019;fIR\u0019qF\u001f?\t\u000bmd\u0001\u0019A\u0018\u0002\u0003MDQ! \u0007A\u0002%\u000bQa^5ei\"\u0004
   #9 = Utf8               truncated
  #10 = Utf8               (Ljava/lang/String;I)Ljava/lang/String;
  #11 = Utf8               s
  #12 = Utf8               width
  #13 = Utf8               coursier/cache/loggers/RefreshDisplay$
  #14 = Class              #13            // coursier/cache/loggers/RefreshDisplay$
  #15 = Utf8               MODULE$
  #16 = Utf8               Lcoursier/cache/loggers/RefreshDisplay$;
  #17 = NameAndType        #15:#16        // MODULE$:Lcoursier/cache/loggers/RefreshDisplay$;
  #18 = Fieldref           #14.#17        // coursier/cache/loggers/RefreshDisplay$.MODULE$:Lcoursier/cache/loggers/RefreshDisplay$;
  #19 = NameAndType        #9:#10         // truncated:(Ljava/lang/String;I)Ljava/lang/String;
  #20 = Methodref          #14.#19        // coursier/cache/loggers/RefreshDisplay$.truncated:(Ljava/lang/String;I)Ljava/lang/String;
  #21 = Utf8               newEntry$
  #22 = Utf8               (Lcoursier/cache/loggers/RefreshDisplay;Ljava/io/Writer;Ljava/lang/String;Lcoursier/cache/loggers/RefreshInfo;)V
  #23 = Utf8               $this
  #24 = Utf8               out
  #25 = Utf8               url
  #26 = Utf8               info
  #27 = Utf8               newEntry
  #28 = Utf8               (Ljava/io/Writer;Ljava/lang/String;Lcoursier/cache/loggers/RefreshInfo;)V
  #29 = NameAndType        #27:#28        // newEntry:(Ljava/io/Writer;Ljava/lang/String;Lcoursier/cache/loggers/RefreshInfo;)V
  #30 = InterfaceMethodref #2.#29         // coursier/cache/loggers/RefreshDisplay.newEntry:(Ljava/io/Writer;Ljava/lang/String;Lcoursier/cache/loggers/RefreshInfo;)V
  #31 = Utf8               Lcoursier/cache/loggers/RefreshDisplay;
  #32 = Utf8               Ljava/io/Writer;
  #33 = Utf8               Ljava/lang/String;
  #34 = Utf8               Lcoursier/cache/loggers/RefreshInfo;
  #35 = Utf8               this
  #36 = Utf8               removeEntry$
  #37 = Utf8               removeEntry
  #38 = NameAndType        #37:#28        // removeEntry:(Ljava/io/Writer;Ljava/lang/String;Lcoursier/cache/loggers/RefreshInfo;)V
  #39 = InterfaceMethodref #2.#38         // coursier/cache/loggers/RefreshDisplay.removeEntry:(Ljava/io/Writer;Ljava/lang/String;Lcoursier/cache/loggers/RefreshInfo;)V
  #40 = Utf8               sizeHint$
  #41 = Utf8               (Lcoursier/cache/loggers/RefreshDisplay;I)V
  #42 = Utf8               n
  #43 = Utf8               sizeHint
  #44 = Utf8               (I)V
  #45 = NameAndType        #43:#44        // sizeHint:(I)V
  #46 = InterfaceMethodref #2.#45         // coursier/cache/loggers/RefreshDisplay.sizeHint:(I)V
  #47 = Utf8               I
  #48 = Utf8               update
  #49 = Utf8               (Ljava/io/Writer;Lscala/collection/immutable/Seq;Lscala/collection/immutable/Seq;Z)V
  #50 = Utf8               (Ljava/io/Writer;Lscala/collection/immutable/Seq<Lscala/Tuple2<Ljava/lang/String;Lcoursier/cache/loggers/RefreshInfo;>;>;Lscala/collection/immutable/Seq<Lscala/Tuple2<Ljava/lang/String;Lcoursier/cache/loggers/RefreshInfo;>;>;Z)V
  #51 = Utf8               done
  #52 = Utf8               downloads
  #53 = Utf8               changed
  #54 = Utf8               stop$
  #55 = Utf8               (Lcoursier/cache/loggers/RefreshDisplay;Ljava/io/Writer;)V
  #56 = Utf8               stop
  #57 = Utf8               (Ljava/io/Writer;)V
  #58 = NameAndType        #56:#57        // stop:(Ljava/io/Writer;)V
  #59 = InterfaceMethodref #2.#58         // coursier/cache/loggers/RefreshDisplay.stop:(Ljava/io/Writer;)V
  #60 = Utf8               refreshInterval
  #61 = Utf8               ()Lscala/concurrent/duration/Duration;
  #62 = Utf8               $init$
  #63 = Utf8               (Lcoursier/cache/loggers/RefreshDisplay;)V
  #64 = Utf8               Code
  #65 = Utf8               MethodParameters
  #66 = Utf8               LineNumberTable
  #67 = Utf8               LocalVariableTable
  #68 = Utf8               Signature
  #69 = Utf8               SourceFile
  #70 = Utf8               RuntimeVisibleAnnotations
  #71 = Utf8               ScalaInlineInfo
  #72 = Utf8               ScalaSig
{
  public static java.lang.String truncated(java.lang.String, int);
    descriptor: (Ljava/lang/String;I)Ljava/lang/String;
    flags: (0x0009) ACC_PUBLIC, ACC_STATIC
    Code:
      stack=3, locals=2, args_size=2
         0: getstatic     #18                 // Field coursier/cache/loggers/RefreshDisplay$.MODULE$:Lcoursier/cache/loggers/RefreshDisplay$;
         3: aload_0
         4: iload_1
         5: invokevirtual #20                 // Method coursier/cache/loggers/RefreshDisplay$.truncated:(Ljava/lang/String;I)Ljava/lang/String;
         8: areturn
    MethodParameters:
      Name                           Flags
      s                              final
      width                          final

  public static void newEntry$(coursier.cache.loggers.RefreshDisplay, java.io.Writer, java.lang.String, coursier.cache.loggers.RefreshInfo);
    descriptor: (Lcoursier/cache/loggers/RefreshDisplay;Ljava/io/Writer;Ljava/lang/String;Lcoursier/cache/loggers/RefreshInfo;)V
    flags: (0x1009) ACC_PUBLIC, ACC_STATIC, ACC_SYNTHETIC
    Code:
      stack=4, locals=4, args_size=4
         0: aload_0
         1: aload_1
         2: aload_2
         3: aload_3
         4: invokespecial #30                 // InterfaceMethod newEntry:(Ljava/io/Writer;Ljava/lang/String;Lcoursier/cache/loggers/RefreshInfo;)V
         7: return
      LineNumberTable:
        line 12: 0
      LocalVariableTable:
        Start  Length  Slot  Name   Signature
            0       8     0 $this   Lcoursier/cache/loggers/RefreshDisplay;
            0       8     1   out   Ljava/io/Writer;
            0       8     2   url   Ljava/lang/String;
            0       8     3  info   Lcoursier/cache/loggers/RefreshInfo;
    MethodParameters:
      Name                           Flags
      $this                          final synthetic
      out                            final
      url                            final
      info                           final

  public default void newEntry(java.io.Writer, java.lang.String, coursier.cache.loggers.RefreshInfo);
    descriptor: (Ljava/io/Writer;Ljava/lang/String;Lcoursier/cache/loggers/RefreshInfo;)V
    flags: (0x0001) ACC_PUBLIC
    Code:
      stack=0, locals=4, args_size=4
         0: return
      LineNumberTable:
        line 12: 0
      LocalVariableTable:
        Start  Length  Slot  Name   Signature
            0       1     0  this   Lcoursier/cache/loggers/RefreshDisplay;
            0       1     1   out   Ljava/io/Writer;
            0       1     2   url   Ljava/lang/String;
            0       1     3  info   Lcoursier/cache/loggers/RefreshInfo;
    MethodParameters:
      Name                           Flags
      out                            final
      url                            final
      info                           final

  public static void removeEntry$(coursier.cache.loggers.RefreshDisplay, java.io.Writer, java.lang.String, coursier.cache.loggers.RefreshInfo);
    descriptor: (Lcoursier/cache/loggers/RefreshDisplay;Ljava/io/Writer;Ljava/lang/String;Lcoursier/cache/loggers/RefreshInfo;)V
    flags: (0x1009) ACC_PUBLIC, ACC_STATIC, ACC_SYNTHETIC
    Code:
      stack=4, locals=4, args_size=4
         0: aload_0
         1: aload_1
         2: aload_2
         3: aload_3
         4: invokespecial #39                 // InterfaceMethod removeEntry:(Ljava/io/Writer;Ljava/lang/String;Lcoursier/cache/loggers/RefreshInfo;)V
         7: return
      LineNumberTable:
        line 13: 0
      LocalVariableTable:
        Start  Length  Slot  Name   Signature
            0       8     0 $this   Lcoursier/cache/loggers/RefreshDisplay;
            0       8     1   out   Ljava/io/Writer;
            0       8     2   url   Ljava/lang/String;
            0       8     3  info   Lcoursier/cache/loggers/RefreshInfo;
    MethodParameters:
      Name                           Flags
      $this                          final synthetic
      out                            final
      url                            final
      info                           final

  public default void removeEntry(java.io.Writer, java.lang.String, coursier.cache.loggers.RefreshInfo);
    descriptor: (Ljava/io/Writer;Ljava/lang/String;Lcoursier/cache/loggers/RefreshInfo;)V
    flags: (0x0001) ACC_PUBLIC
    Code:
      stack=0, locals=4, args_size=4
         0: return
      LineNumberTable:
        line 13: 0
      LocalVariableTable:
        Start  Length  Slot  Name   Signature
            0       1     0  this   Lcoursier/cache/loggers/RefreshDisplay;
            0       1     1   out   Ljava/io/Writer;
            0       1     2   url   Ljava/lang/String;
            0       1     3  info   Lcoursier/cache/loggers/RefreshInfo;
    MethodParameters:
      Name                           Flags
      out                            final
      url                            final
      info                           final

  public static void sizeHint$(coursier.cache.loggers.RefreshDisplay, int);
    descriptor: (Lcoursier/cache/loggers/RefreshDisplay;I)V
    flags: (0x1009) ACC_PUBLIC, ACC_STATIC, ACC_SYNTHETIC
    Code:
      stack=2, locals=2, args_size=2
         0: aload_0
         1: iload_1
         2: invokespecial #46                 // InterfaceMethod sizeHint:(I)V
         5: return
      LineNumberTable:
        line 15: 0
      LocalVariableTable:
        Start  Length  Slot  Name   Signature
            0       6     0 $this   Lcoursier/cache/loggers/RefreshDisplay;
            0       6     1     n   I
    MethodParameters:
      Name                           Flags
      $this                          final synthetic
      n                              final

  public default void sizeHint(int);
    descriptor: (I)V
    flags: (0x0001) ACC_PUBLIC
    Code:
      stack=0, locals=2, args_size=2
         0: return
      LineNumberTable:
        line 15: 0
      LocalVariableTable:
        Start  Length  Slot  Name   Signature
            0       1     0  this   Lcoursier/cache/loggers/RefreshDisplay;
            0       1     1     n   I
    MethodParameters:
      Name                           Flags
      n                              final

  public abstract void update(java.io.Writer, scala.collection.immutable.Seq<scala.Tuple2<java.lang.String, coursier.cache.loggers.RefreshInfo>>, scala.collection.immutable.Seq<scala.Tuple2<java.lang.String, coursier.cache.loggers.RefreshInfo>>, boolean);
    descriptor: (Ljava/io/Writer;Lscala/collection/immutable/Seq;Lscala/collection/immutable/Seq;Z)V
    flags: (0x0401) ACC_PUBLIC, ACC_ABSTRACT
    Signature: #50                          // (Ljava/io/Writer;Lscala/collection/immutable/Seq<Lscala/Tuple2<Ljava/lang/String;Lcoursier/cache/loggers/RefreshInfo;>;>;Lscala/collection/immutable/Seq<Lscala/Tuple2<Ljava/lang/String;Lcoursier/cache/loggers/RefreshInfo;>;>;Z)V
    MethodParameters:
      Name                           Flags
      out                            final
      done                           final
      downloads                      final
      changed                        final

  public static void stop$(coursier.cache.loggers.RefreshDisplay, java.io.Writer);
    descriptor: (Lcoursier/cache/loggers/RefreshDisplay;Ljava/io/Writer;)V
    flags: (0x1009) ACC_PUBLIC, ACC_STATIC, ACC_SYNTHETIC
    Code:
      stack=2, locals=2, args_size=2
         0: aload_0
         1: aload_1
         2: invokespecial #59                 // InterfaceMethod stop:(Ljava/io/Writer;)V
         5: return
      LineNumberTable:
        line 22: 0
      LocalVariableTable:
        Start  Length  Slot  Name   Signature
            0       6     0 $this   Lcoursier/cache/loggers/RefreshDisplay;
            0       6     1   out   Ljava/io/Writer;
    MethodParameters:
      Name                           Flags
      $this                          final synthetic
      out                            final

  public default void stop(java.io.Writer);
    descriptor: (Ljava/io/Writer;)V
    flags: (0x0001) ACC_PUBLIC
    Code:
      stack=0, locals=2, args_size=2
         0: return
      LineNumberTable:
        line 22: 0
      LocalVariableTable:
        Start  Length  Slot  Name   Signature
            0       1     0  this   Lcoursier/cache/loggers/RefreshDisplay;
            0       1     1   out   Ljava/io/Writer;
    MethodParameters:
      Name                           Flags
      out                            final

  public abstract scala.concurrent.duration.Duration refreshInterval();
    descriptor: ()Lscala/concurrent/duration/Duration;
    flags: (0x0401) ACC_PUBLIC, ACC_ABSTRACT

  public static void $init$(coursier.cache.loggers.RefreshDisplay);
    descriptor: (Lcoursier/cache/loggers/RefreshDisplay;)V
    flags: (0x0009) ACC_PUBLIC, ACC_STATIC
    Code:
      stack=0, locals=1, args_size=1
         0: return
      LineNumberTable:
        line 8: 0
      LocalVariableTable:
        Start  Length  Slot  Name   Signature
            0       1     0 $this   Lcoursier/cache/loggers/RefreshDisplay;
    MethodParameters:
      Name                           Flags
      $this                          final synthetic
}
SourceFile: "RefreshDisplay.scala"
RuntimeVisibleAnnotations:
  0: #6(#7=s#8)
    scala.reflect.ScalaSignature(
      bytes="\u0006\u0005y4q!\u0004\b\u0011\u0002\u0007\u0005Q\u0003C\u0003\u001d\u0001\u0011\u0005Q\u0004C\u0003\"\u0001\u0011\u0005!\u0005C\u0003A\u0001\u0011\u0005\u0011\tC\u0003F\u0001\u0011\u0005a\tC\u0003M\u0001\u0019\u0005Q\nC\u0003e\u0001\u0011\u0005Q\rC\u0003h\u0001\u0019\u0005\u0001nB\u0003r\u001d!\u0005!OB\u0003\u000e\u001d!\u00051\u000fC\u0003u\u0013\u0011\u0005Q\u000f\u0003\u0005w\u0013!\u0015\r\u0011\"\u0003x\u0011\u0015A\u0018\u0002\"\u0001z\u00059\u0011VM\u001a:fg\"$\u0015n\u001d9mCfT!a\u0004\t\u0002\u000f1|wmZ3sg*\u0011\u0011CE\u0001\u0006G\u0006\u001c\u0007.\u001a\u0006\u0002\'\u0005A1m\\;sg&,\'o\u0001\u0001\u0014\u0005\u00011\u0002CA\f\u001b\u001b\u0005A\"\"A\r\u0002\u000bM\u001c\u0017\r\\1\n\u0005mA\"AB!osJ+g-\u0001\u0004%S:LG\u000f\n\u000b\u0002=A\u0011qcH\u0005\u0003Aa\u0011A!\u00168ji\u0006Aa.Z<F]R\u0014\u0018\u0010\u0006\u0003\u001fG5R\u0004\"\u0002\u0013\u0003\u0001\u0004)\u0013aA8viB\u0011aeK\u0007\u0002O)\u0011\u0001&K\u0001\u0003S>T\u0011AK\u0001\u0005U\u00064\u0018-\u0003\u0002-O\t1qK]5uKJDQA\f\u0002A\u0002=\n1!\u001e:m!\t\u0001tG\u0004\u00022kA\u0011!\u0007G\u0007\u0002g)\u0011A\u0007F\u0001\u0007yI|w\u000e\u001e \n\u0005YB\u0012A\u0002)sK\u0012,g-\u0003\u00029s\t11\u000b\u001e:j]\u001eT!A\u000e\r\t\u000bm\u0012\u0001\u0019\u0001\u001f\u0002\t%tgm\u001c\t\u0003{yj\u0011AD\u0005\u0003\u007f9\u00111BU3ge\u0016\u001c\b.\u00138g_\u0006Y!/Z7pm\u0016,e\u000e\u001e:z)\u0011q\"i\u0011#\t\u000b\u0011\u001a\u0001\u0019A\u0013\t\u000b9\u001a\u0001\u0019A\u0018\t\u000bm\u001a\u0001\u0019\u0001\u001f\u0002\u0011ML\'0\u001a%j]R$\"AH$\t\u000b!#\u0001\u0019A%\u0002\u00039\u0004\"a\u0006&\n\u0005-C\"aA%oi\u00061Q\u000f\u001d3bi\u0016$RA\b(P;~CQ\u0001J\u0003A\u0002\u0015BQ\u0001U\u0003A\u0002E\u000bA\u0001Z8oKB\u0019!k\u0016.\u000f\u0005M+fB\u0001\u001aU\u0013\u0005I\u0012B\u0001,\u0019\u0003\u001d\u0001\u0018mY6bO\u0016L!\u0001W-\u0003\u0007M+\u0017O\u0003\u0002W1A!qcW\u0018=\u0013\ta\u0006D\u0001\u0004UkBdWM\r\u0005\u0006=\u0016\u0001\r!U\u0001\nI><h\u000e\\8bINDQ\u0001Y\u0003A\u0002\u0005\fqa\u00195b]\u001e,G\r\u0005\u0002\u0018E&\u00111\r\u0007\u0002\b\u0005>|G.Z1o\u0003\u0011\u0019Ho\u001c9\u0015\u0005y1\u0007\"\u0002\u0013\u0007\u0001\u0004)\u0013a\u0004:fMJ,7\u000f[%oi\u0016\u0014h/\u00197\u0016\u0003%\u0004\"A[8\u000e\u0003-T!\u0001\\7\u0002\u0011\u0011,(/\u0019;j_:T!A\u001c\r\u0002\u0015\r|gnY;se\u0016tG/\u0003\u0002qW\nAA)\u001e:bi&|g.\u0001\bSK\u001a\u0014Xm\u001d5ESN\u0004H.Y=\u0011\u0005uJ1CA\u0005\u0017\u0003\u0019a\u0014N\\5u}Q\t!/A\u0005jg^Kg\u000eZ8xgV\t\u0011-A\u0005ueVt7-\u0019;fIR\u0019qF\u001f?\t\u000bmd\u0001\u0019A\u0018\u0002\u0003MDQ! \u0007A\u0002%\u000bQa^5ei\"\u0004"
    )
  ScalaInlineInfo: length = 0x3B (unknown attribute)
   01 00 00 0B 00 3E 00 3F 01 00 1B 00 1C 00 00 15
   00 16 01 00 3C 00 3D 00 00 25 00 1C 00 00 24 00
   16 01 00 2B 00 2C 00 00 28 00 29 01 00 38 00 39
   00 00 36 00 37 01 00 30 00 31 00
  ScalaSig: length = 0x3 (unknown attribute)
   05 02 00
