Classfile /Users/mw/Projects/slang-braindump/.jar/jar11/assemble/slang-braindump/assemble/content/coursier/cache/loggers/RefreshInfo.class
  Last modified May 29, 2022; size 4452 bytes
  SHA-256 checksum 2767e9f0f65dc8df712354438132f04e4daf00e2e42082477fcdfb8a6046c883
  Compiled from "RefreshInfo.scala"
public abstract class coursier.cache.loggers.RefreshInfo implements scala.Product,java.io.Serializable
  minor version: 0
  major version: 52
  flags: (0x0421) ACC_PUBLIC, ACC_SUPER, ACC_ABSTRACT
  this_class: #2                          // coursier/cache/loggers/RefreshInfo
  super_class: #4                         // java/lang/Object
  interfaces: 2, fields: 0, methods: 7, attributes: 5
Constant pool:
   #1 = Utf8               coursier/cache/loggers/RefreshInfo
   #2 = Class              #1             // coursier/cache/loggers/RefreshInfo
   #3 = Utf8               java/lang/Object
   #4 = Class              #3             // java/lang/Object
   #5 = Utf8               scala/Product
   #6 = Class              #5             // scala/Product
   #7 = Utf8               java/io/Serializable
   #8 = Class              #7             // java/io/Serializable
   #9 = Utf8               RefreshInfo.scala
  #10 = Utf8               Lscala/reflect/ScalaSignature;
  #11 = Utf8               bytes
  #12 = Utf8               \u0006\u0005\tEb!B$I\u0003Cy\u0005\"B3\u0001\t\u00031\u0007\"B5\u0001\r\u0003Q\u0007\"B9\u0001\r\u0003\u0011xa\u0002B\u0018\u0011\"\u0005\u00111\u0001\u0004\u0006\u000f\"C\t\u0001\u001f\u0005\u0007K\u0016!\t!!\u0001\u0007\r\u0005\u0015QAAA\u0004\u0011)\tIa\u0002BC\u0002\u0013\u0005\u00111\u0002\u0005\u000b\u0003\'9!\u0011!Q\u0001\n\u00055\u0001BCA\u000b\u000f\t\u0015\r\u0011\"\u0001\u0002\f!Q\u0011qC\u0004\u0003\u0002\u0003\u0006I!!\u0004\t\u0015\u0005eqA!b\u0001\n\u0003\tY\u0002\u0003\u0006\u0002 \u001d\u0011\t\u0011)A\u0005\u0003;A!\"!\t\b\u0005\u000b\u0007I\u0011AA\u0006\u0011)\t\u0019c\u0002B\u0001B\u0003%\u0011Q\u0002\u0005\n\u0003K9!Q1A\u0005\u0002ID\u0011\"a\n\b\u0005\u0003\u0005\u000b\u0011B:\t\u0011E<!Q1A\u0005\u0002ID\u0011\"!\u000b\b\u0005\u0003\u0005\u000b\u0011B:\t\r\u0015<A\u0011AA\u0016\u0011\u0015Iw\u0001\"\u0001k\u0011\u001d\tid\u0002C\u0001\u0003\u007fAq!!\u0011\b\t\u0003\t\u0019\u0005C\u0004\u0002H\u001d!\t!!\u0013\t\u000f\u00055s\u0001\"\u0001\u0002P!9\u00111K\u0004\u0005\u0002\u0005U\u0003bBA-\u000f\u0011\u0005\u00111\f\u0005\b\u0003?:A\u0011AA1\u0011\u001d\t)g\u0002C!\u0003OBq!!\u001e\b\t\u0003\n9\bC\u0004\u0002\u0004\u001e!\t%!\"\t\u000f\u0005%u\u0001\"\u0011\u0002\f\"9\u00111S\u0004\u0005\n\u0005U\u0005bBAO\u000f\u0011\u0005\u0013q\u0014\u0005\b\u0003C;A\u0011IAR\u0011\u001d\t)k\u0002C!\u0003OCq!!,\b\t\u0003\nykB\u0004\u00024\u0016A\t!!.\u0007\u000f\u0005\u0015Q\u0001#\u0001\u00028\"1Qm\nC\u0001\u0003sCq!a/(\t\u0003\ti\fC\u0005\u0002L\u001e\n\t\u0011\"\u0003\u0002N\u001a)q/\u0002\u0002\u0002n\"Q\u00111]\u0016\u0003\u0006\u0004%\t!a\u0007\t\u0015\u0005=8F!A!\u0002\u0013\ti\u0002\u0003\u0006\u0002h.\u0012)\u0019!C\u0001\u00037A!\"!=,\u0005\u0003\u0005\u000b\u0011BA\u000f\u0011%\tYo\u000bBC\u0002\u0013\u0005!\u000fC\u0005\u0002t.\u0012\t\u0011)A\u0005g\"1Qm\u000bC\u0001\u0003kDQ!]\u0016\u0005\u0002IDa![\u0016\u0005\u0002\u0005u\bb\u0002B\u0003W\u0011\u0005!q\u0001\u0005\b\u0005\u0017YC\u0011\u0001B\u0007\u0011\u001d\u0011\tb\u000bC\u0001\u0005\'Aq!!\u001a,\t\u0003\n9\u0007C\u0004\u0002v-\"\tEa\u0006\t\u000f\u0005\r5\u0006\"\u0011\u0003\u001c!9\u0011\u0011R\u0016\u0005B\u0005-\u0005bBAJW\u0011%!q\u0004\u0005\b\u0003;[C\u0011IAP\u0011\u001d\t\tk\u000bC!\u0003GCq!!*,\t\u0003\u00129\u0003C\u0004\u0002..\"\tEa\u000b\b\u000f\u0005UW\u0001#\u0001\u0002X\u001a1q/\u0002E\u0001\u00033Da!\u001a\"\u0005\u0002\u0005m\u0007bBA^\u0005\u0012\u0005\u0011Q\u001c\u0005\n\u0003\u0017\u0014\u0015\u0011!C\u0005\u0003\u001bD\u0011\"a3\u0006\u0003\u0003%I!!4\u0003\u0017I+gM]3tQ&sgm\u001c\u0006\u0003\u0013*\u000bq\u0001\\8hO\u0016\u00148O\u0003\u0002L\u0019\u0006)1-Y2iK*\tQ*\u0001\u0005d_V\u00148/[3s\u0007\u0001\u0019B\u0001\u0001)W3B\u0011\u0011\u000bV\u0007\u0002%*\t1+A\u0003tG\u0006d\u0017-\u0003\u0002V%\n1\u0011I\\=SK\u001a\u0004\"!U,\n\u0005a\u0013&a\u0002)s_\u0012,8\r\u001e\t\u00035\nt!a\u00171\u000f\u0005q{V\"A/\u000b\u0005ys\u0015A\u0002\u001fs_>$h(C\u0001T\u0013\t\t\'+A\u0004qC\u000e\\\u0017mZ3\n\u0005\r$\'\u0001D*fe&\fG.\u001b>bE2,\'BA1S\u0003\u0019a\u0014N\\5u}Q\tq\r\u0005\u0002i\u00015\t\u0001*\u0001\u0005ge\u0006\u001cG/[8o+\u0005Y\u0007cA)m]&\u0011QN\u0015\u0002\u0007\u001fB$\u0018n\u001c8\u0011\u0005E{\u0017B\u00019S\u0005\u0019!u.\u001e2mK\u0006Aq/\u0019;dQ&tw-F\u0001t!\t\tF/\u0003\u0002v%\n9!i\\8mK\u0006t\u0017f\u0001\u0001,\u000f\ty1\t[3dWV\u0003H-\u0019;f\u0013:4wnE\u0002\u0006!f\u0004\"A_@\u000e\u0003mT!\u0001`?\u0002\u0005%|\'\"\u0001@\u0002\t)\fg/Y\u0005\u0003Gn$\"!a\u0001\u0011\u0005!,!\u0001\u0004#po:dw.\u00193J]\u001a|7\u0003B\u0004h-f\u000b!\u0002Z8x]2|\u0017\rZ3e+\t\ti\u0001E\u0002R\u0003\u001fI1!!\u0005S\u0005\u0011auN\\4\u0002\u0017\u0011|wO\u001c7pC\u0012,G\rI\u0001\u0015aJ,g/[8vg2LHi\\<oY>\fG-\u001a3\u0002+A\u0014XM^5pkNd\u0017\u0010R8x]2|\u0017\rZ3eA\u00051A.\u001a8hi\",\"!!\b\u0011\tEc\u0017QB\u0001\bY\u0016tw\r\u001e5!\u0003%\u0019H/\u0019:u)&lW-\u0001\u0006ti\u0006\u0014H\u000fV5nK\u0002\n1\"\u001e9eCR,7\t[3dW\u0006aQ\u000f\u001d3bi\u0016\u001c\u0005.Z2lA\u0005Iq/\u0019;dQ&tw\r\t\u000b\u000f\u0003[\t\t$a\r\u00026\u0005]\u0012\u0011HA\u001e!\r\tycB\u0007\u0002\u000b!9\u0011\u0011\u0002\u000bA\u0002\u00055\u0001bBA\u000b)\u0001\u0007\u0011Q\u0002\u0005\b\u00033!\u0002\u0019AA\u000f\u0011\u001d\t\t\u0003\u0006a\u0001\u0003\u001bAa!!\n\u0015\u0001\u0004\u0019\b\"B9\u0015\u0001\u0004\u0019\u0018\u0001\u0002:bi\u0016$\u0012a[\u0001\u000fo&$\b\u000eR8x]2|\u0017\rZ3e)\u0011\ti#!\u0012\t\u000f\u0005%q\u00031\u0001\u0002\u000e\u0005Ar/\u001b;i!J,g/[8vg2LHi\\<oY>\fG-\u001a3\u0015\t\u00055\u00121\n\u0005\b\u0003+A\u0002\u0019AA\u0007\u0003)9\u0018\u000e\u001e5MK:<G\u000f\u001b\u000b\u0005\u0003[\t\t\u0006C\u0004\u0002\u001ae\u0001\r!!\b\u0002\u001b]LG\u000f[*uCJ$H+[7f)\u0011\ti#a\u0016\t\u000f\u0005\u0005\"\u00041\u0001\u0002\u000e\u0005yq/\u001b;i+B$\u0017\r^3DQ\u0016\u001c7\u000e\u0006\u0003\u0002.\u0005u\u0003BBA\u00137\u0001\u00071/\u0001\u0007xSRDw+\u0019;dQ&tw\r\u0006\u0003\u0002.\u0005\r\u0004\"B9\u001d\u0001\u0004\u0019\u0018\u0001\u0003;p\'R\u0014\u0018N\\4\u0015\u0005\u0005%\u0004\u0003BA6\u0003cj!!!\u001c\u000b\u0007\u0005=T0\u0001\u0003mC:<\u0017\u0002BA:\u0003[\u0012aa\u0015;sS:<\u0017\u0001C2b]\u0016\u000bX/\u00197\u0015\u0007M\fI\bC\u0004\u0002|y\u0001\r!! \u0002\u0007=\u0014\'\u000eE\u0002R\u0003\u007fJ1!!!S\u0005\r\te._\u0001\u0007KF,\u0018\r\\:\u0015\u0007M\f9\tC\u0004\u0002|}\u0001\r!! \u0002\u0011!\f7\u000f[\"pI\u0016$\"!!$\u0011\u0007E\u000by)C\u0002\u0002\u0012J\u00131!\u00138u\u0003\u0015!X\u000f\u001d7f+\t\t9\nE\u0007R\u00033\u000bi!!\u0004\u0002\u001e\u000551o]\u0005\u0004\u00037\u0013&A\u0002+va2,g\'A\u0007qe>$Wo\u0019;Qe\u00164\u0017\u000e_\u000b\u0003\u0003S\nA\u0002\u001d:pIV\u001cG/\u0011:jif,\"!!$\u0002\u001dA\u0014x\u000eZ;di\u0016cW-\\3oiR!\u0011QPAU\u0011\u001d\tY\u000b\na\u0001\u0003\u001b\u000b\u0011A\\\u0001\u0013aJ|G-^2u\u000b2,W.\u001a8u\u001d\u0006lW\r\u0006\u0003\u0002j\u0005E\u0006bBAVK\u0001\u0007\u0011QR\u0001\r\t><h\u000e\\8bI&sgm\u001c\t\u0004\u0003_93cA\u0014QsR\u0011\u0011QW\u0001\u0006CB\u0004H.\u001f\u000b\u000f\u0003[\ty,!1\u0002D\u0006\u0015\u0017qYAe\u0011\u001d\tI!\u000ba\u0001\u0003\u001bAq!!\u0006*\u0001\u0004\ti\u0001C\u0004\u0002\u001a%\u0002\r!!\b\t\u000f\u0005\u0005\u0012\u00061\u0001\u0002\u000e!1\u0011QE\u0015A\u0002MDQ!]\u0015A\u0002M\fAb\u001e:ji\u0016\u0014V\r\u001d7bG\u0016$\"!a4\u0011\t\u0005-\u0014\u0011[\u0005\u0005\u0003\'\fiG\u0001\u0004PE*,7\r^\u0001\u0010\u0007\",7m[+qI\u0006$X-\u00138g_B\u0019\u0011q\u0006\"\u0014\u0007\t\u0003\u0016\u0010\u0006\u0002\u0002XRA\u0011q\\Aq\u0003K\fI\u000fE\u0002\u00020-Bq!a9E\u0001\u0004\ti\"\u0001\bdkJ\u0014XM\u001c;US6,w\n\u001d;\t\u000f\u0005\u001dH\t1\u0001\u0002\u001e\u0005i!/Z7pi\u0016$\u0016.\\3PaRDa!a;E\u0001\u0004\u0019\u0018AB5t\t>tWm\u0005\u0003,OZK\u0016aD2veJ,g\u000e\u001e+j[\u0016|\u0005\u000f\u001e\u0011\u0002\u001dI,Wn\u001c;f)&lWm\u00149uA\u00059\u0011n\u001d#p]\u0016\u0004C\u0003CAp\u0003o\fI0a?\t\u000f\u0005\r(\u00071\u0001\u0002\u001e!9\u0011q\u001d\u001aA\u0002\u0005u\u0001BBAve\u0001\u00071/\u0006\u0002\u0002\u0000B\u0019\u0011K!\u0001\u000b\u0007\t\r!+\u0001\u0003O_:,\u0017AE<ji\"\u001cUO\u001d:f]R$\u0016.\\3PaR$B!a8\u0003\n!9\u00111]\u001bA\u0002\u0005u\u0011!E<ji\"\u0014V-\\8uKRKW.Z(qiR!\u0011q\u001cB\b\u0011\u001d\t9O\u000ea\u0001\u0003;\t!b^5uQ&\u001bHi\u001c8f)\u0011\tyN!\u0006\t\r\u0005-x\u00071\u0001t)\r\u0019(\u0011\u0004\u0005\b\u0003wJ\u0004\u0019AA?)\r\u0019(Q\u0004\u0005\b\u0003wR\u0004\u0019AA?+\t\u0011\t\u0003\u0005\u0005R\u0005G\ti\"!\bt\u0013\r\u0011)C\u0015\u0002\u0007)V\u0004H.Z\u001a\u0015\t\u0005u$\u0011\u0006\u0005\b\u0003W{\u0004\u0019AAG)\u0011\tIG!\f\t\u000f\u0005-\u0006\t1\u0001\u0002\u000e\u0006Y!+\u001a4sKND\u0017J\u001c4p\u0001
  #13 = Utf8               coursier/cache/loggers/RefreshInfo$CheckUpdateInfo
  #14 = Class              #13            // coursier/cache/loggers/RefreshInfo$CheckUpdateInfo
  #15 = Utf8               CheckUpdateInfo
  #16 = Utf8               coursier/cache/loggers/RefreshInfo$CheckUpdateInfo$
  #17 = Class              #16            // coursier/cache/loggers/RefreshInfo$CheckUpdateInfo$
  #18 = Utf8
  #19 = Utf8               coursier/cache/loggers/RefreshInfo$DownloadInfo
  #20 = Class              #19            // coursier/cache/loggers/RefreshInfo$DownloadInfo
  #21 = Utf8               DownloadInfo
  #22 = Utf8               coursier/cache/loggers/RefreshInfo$DownloadInfo$
  #23 = Class              #22            // coursier/cache/loggers/RefreshInfo$DownloadInfo$
  #24 = Utf8               productIterator
  #25 = Utf8               ()Lscala/collection/Iterator;
  #26 = Utf8               ()Lscala/collection/Iterator<Ljava/lang/Object;>;
  #27 = Utf8               productIterator$
  #28 = Utf8               (Lscala/Product;)Lscala/collection/Iterator;
  #29 = NameAndType        #27:#28        // productIterator$:(Lscala/Product;)Lscala/collection/Iterator;
  #30 = InterfaceMethodref #6.#29         // scala/Product.productIterator$:(Lscala/Product;)Lscala/collection/Iterator;
  #31 = Utf8               this
  #32 = Utf8               Lcoursier/cache/loggers/RefreshInfo;
  #33 = Utf8               productPrefix
  #34 = Utf8               ()Ljava/lang/String;
  #35 = Utf8               productPrefix$
  #36 = Utf8               (Lscala/Product;)Ljava/lang/String;
  #37 = NameAndType        #35:#36        // productPrefix$:(Lscala/Product;)Ljava/lang/String;
  #38 = InterfaceMethodref #6.#37         // scala/Product.productPrefix$:(Lscala/Product;)Ljava/lang/String;
  #39 = Utf8               productElementName
  #40 = Utf8               (I)Ljava/lang/String;
  #41 = Utf8               n
  #42 = Utf8               productElementName$
  #43 = Utf8               (Lscala/Product;I)Ljava/lang/String;
  #44 = NameAndType        #42:#43        // productElementName$:(Lscala/Product;I)Ljava/lang/String;
  #45 = InterfaceMethodref #6.#44         // scala/Product.productElementName$:(Lscala/Product;I)Ljava/lang/String;
  #46 = Utf8               I
  #47 = Utf8               productElementNames
  #48 = Utf8               ()Lscala/collection/Iterator<Ljava/lang/String;>;
  #49 = Utf8               productElementNames$
  #50 = NameAndType        #49:#28        // productElementNames$:(Lscala/Product;)Lscala/collection/Iterator;
  #51 = InterfaceMethodref #6.#50         // scala/Product.productElementNames$:(Lscala/Product;)Lscala/collection/Iterator;
  #52 = Utf8               fraction
  #53 = Utf8               ()Lscala/Option;
  #54 = Utf8               ()Lscala/Option<Ljava/lang/Object;>;
  #55 = Utf8               watching
  #56 = Utf8               ()Z
  #57 = Utf8               <init>
  #58 = Utf8               ()V
  #59 = NameAndType        #57:#58        // "<init>":()V
  #60 = Methodref          #4.#59         // java/lang/Object."<init>":()V
  #61 = Utf8               $init$
  #62 = Utf8               (Lscala/Product;)V
  #63 = NameAndType        #61:#62        // $init$:(Lscala/Product;)V
  #64 = InterfaceMethodref #6.#63         // scala/Product.$init$:(Lscala/Product;)V
  #65 = Utf8               Code
  #66 = Utf8               LineNumberTable
  #67 = Utf8               LocalVariableTable
  #68 = Utf8               Signature
  #69 = Utf8               MethodParameters
  #70 = Utf8               InnerClasses
  #71 = Utf8               SourceFile
  #72 = Utf8               RuntimeVisibleAnnotations
  #73 = Utf8               ScalaInlineInfo
  #74 = Utf8               ScalaSig
{
  public scala.collection.Iterator<java.lang.Object> productIterator();
    descriptor: ()Lscala/collection/Iterator;
    flags: (0x0001) ACC_PUBLIC
    Code:
      stack=1, locals=1, args_size=1
         0: aload_0
         1: invokestatic  #30                 // InterfaceMethod scala/Product.productIterator$:(Lscala/Product;)Lscala/collection/Iterator;
         4: areturn
      LineNumberTable:
        line 5: 0
      LocalVariableTable:
        Start  Length  Slot  Name   Signature
            0       5     0  this   Lcoursier/cache/loggers/RefreshInfo;
    Signature: #26                          // ()Lscala/collection/Iterator<Ljava/lang/Object;>;

  public java.lang.String productPrefix();
    descriptor: ()Ljava/lang/String;
    flags: (0x0001) ACC_PUBLIC
    Code:
      stack=1, locals=1, args_size=1
         0: aload_0
         1: invokestatic  #38                 // InterfaceMethod scala/Product.productPrefix$:(Lscala/Product;)Ljava/lang/String;
         4: areturn
      LineNumberTable:
        line 5: 0
      LocalVariableTable:
        Start  Length  Slot  Name   Signature
            0       5     0  this   Lcoursier/cache/loggers/RefreshInfo;

  public java.lang.String productElementName(int);
    descriptor: (I)Ljava/lang/String;
    flags: (0x0001) ACC_PUBLIC
    Code:
      stack=2, locals=2, args_size=2
         0: aload_0
         1: iload_1
         2: invokestatic  #45                 // InterfaceMethod scala/Product.productElementName$:(Lscala/Product;I)Ljava/lang/String;
         5: areturn
      LineNumberTable:
        line 5: 0
      LocalVariableTable:
        Start  Length  Slot  Name   Signature
            0       6     0  this   Lcoursier/cache/loggers/RefreshInfo;
            0       6     1     n   I
    MethodParameters:
      Name                           Flags
      n                              final

  public scala.collection.Iterator<java.lang.String> productElementNames();
    descriptor: ()Lscala/collection/Iterator;
    flags: (0x0001) ACC_PUBLIC
    Code:
      stack=1, locals=1, args_size=1
         0: aload_0
         1: invokestatic  #51                 // InterfaceMethod scala/Product.productElementNames$:(Lscala/Product;)Lscala/collection/Iterator;
         4: areturn
      LineNumberTable:
        line 5: 0
      LocalVariableTable:
        Start  Length  Slot  Name   Signature
            0       5     0  this   Lcoursier/cache/loggers/RefreshInfo;
    Signature: #48                          // ()Lscala/collection/Iterator<Ljava/lang/String;>;

  public abstract scala.Option<java.lang.Object> fraction();
    descriptor: ()Lscala/Option;
    flags: (0x0401) ACC_PUBLIC, ACC_ABSTRACT
    Signature: #54                          // ()Lscala/Option<Ljava/lang/Object;>;

  public abstract boolean watching();
    descriptor: ()Z
    flags: (0x0401) ACC_PUBLIC, ACC_ABSTRACT

  public coursier.cache.loggers.RefreshInfo();
    descriptor: ()V
    flags: (0x0001) ACC_PUBLIC
    Code:
      stack=1, locals=1, args_size=1
         0: aload_0
         1: invokespecial #60                 // Method java/lang/Object."<init>":()V
         4: aload_0
         5: invokestatic  #64                 // InterfaceMethod scala/Product.$init$:(Lscala/Product;)V
         8: return
      LineNumberTable:
        line 5: 0
      LocalVariableTable:
        Start  Length  Slot  Name   Signature
            0       9     0  this   Lcoursier/cache/loggers/RefreshInfo;
}
InnerClasses:
  public static final #15= #14 of #2;     // CheckUpdateInfo=class coursier/cache/loggers/RefreshInfo$CheckUpdateInfo of class coursier/cache/loggers/RefreshInfo
  public static #18= #17 of #2;           // =class coursier/cache/loggers/RefreshInfo$CheckUpdateInfo$ of class coursier/cache/loggers/RefreshInfo
  public static final #21= #20 of #2;     // DownloadInfo=class coursier/cache/loggers/RefreshInfo$DownloadInfo of class coursier/cache/loggers/RefreshInfo
  public static #18= #23 of #2;           // =class coursier/cache/loggers/RefreshInfo$DownloadInfo$ of class coursier/cache/loggers/RefreshInfo
SourceFile: "RefreshInfo.scala"
RuntimeVisibleAnnotations:
  0: #10(#11=s#12)
    scala.reflect.ScalaSignature(
      bytes="\u0006\u0005\tEb!B$I\u0003Cy\u0005\"B3\u0001\t\u00031\u0007\"B5\u0001\r\u0003Q\u0007\"B9\u0001\r\u0003\u0011xa\u0002B\u0018\u0011\"\u0005\u00111\u0001\u0004\u0006\u000f\"C\t\u0001\u001f\u0005\u0007K\u0016!\t!!\u0001\u0007\r\u0005\u0015QAAA\u0004\u0011)\tIa\u0002BC\u0002\u0013\u0005\u00111\u0002\u0005\u000b\u0003\'9!\u0011!Q\u0001\n\u00055\u0001BCA\u000b\u000f\t\u0015\r\u0011\"\u0001\u0002\f!Q\u0011qC\u0004\u0003\u0002\u0003\u0006I!!\u0004\t\u0015\u0005eqA!b\u0001\n\u0003\tY\u0002\u0003\u0006\u0002 \u001d\u0011\t\u0011)A\u0005\u0003;A!\"!\t\b\u0005\u000b\u0007I\u0011AA\u0006\u0011)\t\u0019c\u0002B\u0001B\u0003%\u0011Q\u0002\u0005\n\u0003K9!Q1A\u0005\u0002ID\u0011\"a\n\b\u0005\u0003\u0005\u000b\u0011B:\t\u0011E<!Q1A\u0005\u0002ID\u0011\"!\u000b\b\u0005\u0003\u0005\u000b\u0011B:\t\r\u0015<A\u0011AA\u0016\u0011\u0015Iw\u0001\"\u0001k\u0011\u001d\tid\u0002C\u0001\u0003\u007fAq!!\u0011\b\t\u0003\t\u0019\u0005C\u0004\u0002H\u001d!\t!!\u0013\t\u000f\u00055s\u0001\"\u0001\u0002P!9\u00111K\u0004\u0005\u0002\u0005U\u0003bBA-\u000f\u0011\u0005\u00111\f\u0005\b\u0003?:A\u0011AA1\u0011\u001d\t)g\u0002C!\u0003OBq!!\u001e\b\t\u0003\n9\bC\u0004\u0002\u0004\u001e!\t%!\"\t\u000f\u0005%u\u0001\"\u0011\u0002\f\"9\u00111S\u0004\u0005\n\u0005U\u0005bBAO\u000f\u0011\u0005\u0013q\u0014\u0005\b\u0003C;A\u0011IAR\u0011\u001d\t)k\u0002C!\u0003OCq!!,\b\t\u0003\nykB\u0004\u00024\u0016A\t!!.\u0007\u000f\u0005\u0015Q\u0001#\u0001\u00028\"1Qm\nC\u0001\u0003sCq!a/(\t\u0003\ti\fC\u0005\u0002L\u001e\n\t\u0011\"\u0003\u0002N\u001a)q/\u0002\u0002\u0002n\"Q\u00111]\u0016\u0003\u0006\u0004%\t!a\u0007\t\u0015\u0005=8F!A!\u0002\u0013\ti\u0002\u0003\u0006\u0002h.\u0012)\u0019!C\u0001\u00037A!\"!=,\u0005\u0003\u0005\u000b\u0011BA\u000f\u0011%\tYo\u000bBC\u0002\u0013\u0005!\u000fC\u0005\u0002t.\u0012\t\u0011)A\u0005g\"1Qm\u000bC\u0001\u0003kDQ!]\u0016\u0005\u0002IDa![\u0016\u0005\u0002\u0005u\bb\u0002B\u0003W\u0011\u0005!q\u0001\u0005\b\u0005\u0017YC\u0011\u0001B\u0007\u0011\u001d\u0011\tb\u000bC\u0001\u0005\'Aq!!\u001a,\t\u0003\n9\u0007C\u0004\u0002v-\"\tEa\u0006\t\u000f\u0005\r5\u0006\"\u0011\u0003\u001c!9\u0011\u0011R\u0016\u0005B\u0005-\u0005bBAJW\u0011%!q\u0004\u0005\b\u0003;[C\u0011IAP\u0011\u001d\t\tk\u000bC!\u0003GCq!!*,\t\u0003\u00129\u0003C\u0004\u0002..\"\tEa\u000b\b\u000f\u0005UW\u0001#\u0001\u0002X\u001a1q/\u0002E\u0001\u00033Da!\u001a\"\u0005\u0002\u0005m\u0007bBA^\u0005\u0012\u0005\u0011Q\u001c\u0005\n\u0003\u0017\u0014\u0015\u0011!C\u0005\u0003\u001bD\u0011\"a3\u0006\u0003\u0003%I!!4\u0003\u0017I+gM]3tQ&sgm\u001c\u0006\u0003\u0013*\u000bq\u0001\\8hO\u0016\u00148O\u0003\u0002L\u0019\u0006)1-Y2iK*\tQ*\u0001\u0005d_V\u00148/[3s\u0007\u0001\u0019B\u0001\u0001)W3B\u0011\u0011\u000bV\u0007\u0002%*\t1+A\u0003tG\u0006d\u0017-\u0003\u0002V%\n1\u0011I\\=SK\u001a\u0004\"!U,\n\u0005a\u0013&a\u0002)s_\u0012,8\r\u001e\t\u00035\nt!a\u00171\u000f\u0005q{V\"A/\u000b\u0005ys\u0015A\u0002\u001fs_>$h(C\u0001T\u0013\t\t\'+A\u0004qC\u000e\\\u0017mZ3\n\u0005\r$\'\u0001D*fe&\fG.\u001b>bE2,\'BA1S\u0003\u0019a\u0014N\\5u}Q\tq\r\u0005\u0002i\u00015\t\u0001*\u0001\u0005ge\u0006\u001cG/[8o+\u0005Y\u0007cA)m]&\u0011QN\u0015\u0002\u0007\u001fB$\u0018n\u001c8\u0011\u0005E{\u0017B\u00019S\u0005\u0019!u.\u001e2mK\u0006Aq/\u0019;dQ&tw-F\u0001t!\t\tF/\u0003\u0002v%\n9!i\\8mK\u0006t\u0017f\u0001\u0001,\u000f\ty1\t[3dWV\u0003H-\u0019;f\u0013:4wnE\u0002\u0006!f\u0004\"A_@\u000e\u0003mT!\u0001`?\u0002\u0005%|\'\"\u0001@\u0002\t)\fg/Y\u0005\u0003Gn$\"!a\u0001\u0011\u0005!,!\u0001\u0004#po:dw.\u00193J]\u001a|7\u0003B\u0004h-f\u000b!\u0002Z8x]2|\u0017\rZ3e+\t\ti\u0001E\u0002R\u0003\u001fI1!!\u0005S\u0005\u0011auN\\4\u0002\u0017\u0011|wO\u001c7pC\u0012,G\rI\u0001\u0015aJ,g/[8vg2LHi\\<oY>\fG-\u001a3\u0002+A\u0014XM^5pkNd\u0017\u0010R8x]2|\u0017\rZ3eA\u00051A.\u001a8hi\",\"!!\b\u0011\tEc\u0017QB\u0001\bY\u0016tw\r\u001e5!\u0003%\u0019H/\u0019:u)&lW-\u0001\u0006ti\u0006\u0014H\u000fV5nK\u0002\n1\"\u001e9eCR,7\t[3dW\u0006aQ\u000f\u001d3bi\u0016\u001c\u0005.Z2lA\u0005Iq/\u0019;dQ&tw\r\t\u000b\u000f\u0003[\t\t$a\r\u00026\u0005]\u0012\u0011HA\u001e!\r\tycB\u0007\u0002\u000b!9\u0011\u0011\u0002\u000bA\u0002\u00055\u0001bBA\u000b)\u0001\u0007\u0011Q\u0002\u0005\b\u00033!\u0002\u0019AA\u000f\u0011\u001d\t\t\u0003\u0006a\u0001\u0003\u001bAa!!\n\u0015\u0001\u0004\u0019\b\"B9\u0015\u0001\u0004\u0019\u0018\u0001\u0002:bi\u0016$\u0012a[\u0001\u000fo&$\b\u000eR8x]2|\u0017\rZ3e)\u0011\ti#!\u0012\t\u000f\u0005%q\u00031\u0001\u0002\u000e\u0005Ar/\u001b;i!J,g/[8vg2LHi\\<oY>\fG-\u001a3\u0015\t\u00055\u00121\n\u0005\b\u0003+A\u0002\u0019AA\u0007\u0003)9\u0018\u000e\u001e5MK:<G\u000f\u001b\u000b\u0005\u0003[\t\t\u0006C\u0004\u0002\u001ae\u0001\r!!\b\u0002\u001b]LG\u000f[*uCJ$H+[7f)\u0011\ti#a\u0016\t\u000f\u0005\u0005\"\u00041\u0001\u0002\u000e\u0005yq/\u001b;i+B$\u0017\r^3DQ\u0016\u001c7\u000e\u0006\u0003\u0002.\u0005u\u0003BBA\u00137\u0001\u00071/\u0001\u0007xSRDw+\u0019;dQ&tw\r\u0006\u0003\u0002.\u0005\r\u0004\"B9\u001d\u0001\u0004\u0019\u0018\u0001\u0003;p\'R\u0014\u0018N\\4\u0015\u0005\u0005%\u0004\u0003BA6\u0003cj!!!\u001c\u000b\u0007\u0005=T0\u0001\u0003mC:<\u0017\u0002BA:\u0003[\u0012aa\u0015;sS:<\u0017\u0001C2b]\u0016\u000bX/\u00197\u0015\u0007M\fI\bC\u0004\u0002|y\u0001\r!! \u0002\u0007=\u0014\'\u000eE\u0002R\u0003\u007fJ1!!!S\u0005\r\te._\u0001\u0007KF,\u0018\r\\:\u0015\u0007M\f9\tC\u0004\u0002|}\u0001\r!! \u0002\u0011!\f7\u000f[\"pI\u0016$\"!!$\u0011\u0007E\u000by)C\u0002\u0002\u0012J\u00131!\u00138u\u0003\u0015!X\u000f\u001d7f+\t\t9\nE\u0007R\u00033\u000bi!!\u0004\u0002\u001e\u000551o]\u0005\u0004\u00037\u0013&A\u0002+va2,g\'A\u0007qe>$Wo\u0019;Qe\u00164\u0017\u000e_\u000b\u0003\u0003S\nA\u0002\u001d:pIV\u001cG/\u0011:jif,\"!!$\u0002\u001dA\u0014x\u000eZ;di\u0016cW-\\3oiR!\u0011QPAU\u0011\u001d\tY\u000b\na\u0001\u0003\u001b\u000b\u0011A\\\u0001\u0013aJ|G-^2u\u000b2,W.\u001a8u\u001d\u0006lW\r\u0006\u0003\u0002j\u0005E\u0006bBAVK\u0001\u0007\u0011QR\u0001\r\t><h\u000e\\8bI&sgm\u001c\t\u0004\u0003_93cA\u0014QsR\u0011\u0011QW\u0001\u0006CB\u0004H.\u001f\u000b\u000f\u0003[\ty,!1\u0002D\u0006\u0015\u0017qYAe\u0011\u001d\tI!\u000ba\u0001\u0003\u001bAq!!\u0006*\u0001\u0004\ti\u0001C\u0004\u0002\u001a%\u0002\r!!\b\t\u000f\u0005\u0005\u0012\u00061\u0001\u0002\u000e!1\u0011QE\u0015A\u0002MDQ!]\u0015A\u0002M\fAb\u001e:ji\u0016\u0014V\r\u001d7bG\u0016$\"!a4\u0011\t\u0005-\u0014\u0011[\u0005\u0005\u0003\'\fiG\u0001\u0004PE*,7\r^\u0001\u0010\u0007\",7m[+qI\u0006$X-\u00138g_B\u0019\u0011q\u0006\"\u0014\u0007\t\u0003\u0016\u0010\u0006\u0002\u0002XRA\u0011q\\Aq\u0003K\fI\u000fE\u0002\u00020-Bq!a9E\u0001\u0004\ti\"\u0001\bdkJ\u0014XM\u001c;US6,w\n\u001d;\t\u000f\u0005\u001dH\t1\u0001\u0002\u001e\u0005i!/Z7pi\u0016$\u0016.\\3PaRDa!a;E\u0001\u0004\u0019\u0018AB5t\t>tWm\u0005\u0003,OZK\u0016aD2veJ,g\u000e\u001e+j[\u0016|\u0005\u000f\u001e\u0011\u0002\u001dI,Wn\u001c;f)&lWm\u00149uA\u00059\u0011n\u001d#p]\u0016\u0004C\u0003CAp\u0003o\fI0a?\t\u000f\u0005\r(\u00071\u0001\u0002\u001e!9\u0011q\u001d\u001aA\u0002\u0005u\u0001BBAve\u0001\u00071/\u0006\u0002\u0002\u0000B\u0019\u0011K!\u0001\u000b\u0007\t\r!+\u0001\u0003O_:,\u0017AE<ji\"\u001cUO\u001d:f]R$\u0016.\\3PaR$B!a8\u0003\n!9\u00111]\u001bA\u0002\u0005u\u0011!E<ji\"\u0014V-\\8uKRKW.Z(qiR!\u0011q\u001cB\b\u0011\u001d\t9O\u000ea\u0001\u0003;\t!b^5uQ&\u001bHi\u001c8f)\u0011\tyN!\u0006\t\r\u0005-x\u00071\u0001t)\r\u0019(\u0011\u0004\u0005\b\u0003wJ\u0004\u0019AA?)\r\u0019(Q\u0004\u0005\b\u0003wR\u0004\u0019AA?+\t\u0011\t\u0003\u0005\u0005R\u0005G\ti\"!\bt\u0013\r\u0011)C\u0015\u0002\u0007)V\u0004H.Z\u001a\u0015\t\u0005u$\u0011\u0006\u0005\b\u0003W{\u0004\u0019AAG)\u0011\tIG!\f\t\u000f\u0005-\u0006\t1\u0001\u0002\u000e\u0006Y!+\u001a4sKND\u0017J\u001c4p\u0001"
    )
  ScalaInlineInfo: length = 0x27 (unknown attribute)
   01 00 00 07 00 3A 00 3B 01 00 35 00 36 00 00 28
   00 29 00 00 30 00 1A 01 00 19 00 1A 01 00 22 00
   23 00 00 38 00 39 00
  ScalaSig: length = 0x3 (unknown attribute)
   05 02 00
