Classfile /Users/mw/Projects/slang-braindump/.jar/jar8/assemble/slang-braindump/assemble/content/concurrentrefhashmap/ConcurrentReferenceHashMap$WriteThroughEntry.class
  Last modified May 29, 2022; size 1193 bytes
  SHA-256 checksum a1db7d564ddeca4af2a1344a75cffd67d310b715a0a3547e21b27ea0fc69d7dc
  Compiled from "ConcurrentReferenceHashMap.java"
final class concurrentrefhashmap.ConcurrentReferenceHashMap$WriteThroughEntry extends concurrentrefhashmap.ConcurrentReferenceHashMap$SimpleEntry<K, V>
  minor version: 0
  major version: 52
  flags: (0x0030) ACC_FINAL, ACC_SUPER
  this_class: #8                          // concurrentrefhashmap/ConcurrentReferenceHashMap$WriteThroughEntry
  super_class: #9                         // concurrentrefhashmap/ConcurrentReferenceHashMap$SimpleEntry
  interfaces: 0, fields: 2, methods: 2, attributes: 3
Constant pool:
   #1 = Fieldref           #8.#32         // concurrentrefhashmap/ConcurrentReferenceHashMap$WriteThroughEntry.this$0:Lconcurrentrefhashmap/ConcurrentReferenceHashMap;
   #2 = Methodref          #9.#33         // concurrentrefhashmap/ConcurrentReferenceHashMap$SimpleEntry."<init>":(Ljava/lang/Object;Ljava/lang/Object;)V
   #3 = Class              #34            // java/lang/NullPointerException
   #4 = Methodref          #3.#35         // java/lang/NullPointerException."<init>":()V
   #5 = Methodref          #9.#36         // concurrentrefhashmap/ConcurrentReferenceHashMap$SimpleEntry.setValue:(Ljava/lang/Object;)Ljava/lang/Object;
   #6 = Methodref          #8.#37         // concurrentrefhashmap/ConcurrentReferenceHashMap$WriteThroughEntry.getKey:()Ljava/lang/Object;
   #7 = Methodref          #38.#39        // concurrentrefhashmap/ConcurrentReferenceHashMap.put:(Ljava/lang/Object;Ljava/lang/Object;)Ljava/lang/Object;
   #8 = Class              #40            // concurrentrefhashmap/ConcurrentReferenceHashMap$WriteThroughEntry
   #9 = Class              #42            // concurrentrefhashmap/ConcurrentReferenceHashMap$SimpleEntry
  #10 = Utf8               serialVersionUID
  #11 = Utf8               J
  #12 = Utf8               ConstantValue
  #13 = Long               -7900634345345313646l
  #15 = Utf8               this$0
  #16 = Utf8               Lconcurrentrefhashmap/ConcurrentReferenceHashMap;
  #17 = Utf8               <init>
  #18 = Utf8               (Lconcurrentrefhashmap/ConcurrentReferenceHashMap;Ljava/lang/Object;Ljava/lang/Object;)V
  #19 = Utf8               Code
  #20 = Utf8               LineNumberTable
  #21 = Utf8               Signature
  #22 = Utf8               (TK;TV;)V
  #23 = Utf8               setValue
  #24 = Utf8               (Ljava/lang/Object;)Ljava/lang/Object;
  #25 = Utf8               StackMapTable
  #26 = Utf8               (TV;)TV;
  #27 = Utf8               SimpleEntry
  #28 = Utf8               InnerClasses
  #29 = Utf8               Lconcurrentrefhashmap/ConcurrentReferenceHashMap$SimpleEntry<TK;TV;>;
  #30 = Utf8               SourceFile
  #31 = Utf8               ConcurrentReferenceHashMap.java
  #32 = NameAndType        #15:#16        // this$0:Lconcurrentrefhashmap/ConcurrentReferenceHashMap;
  #33 = NameAndType        #17:#43        // "<init>":(Ljava/lang/Object;Ljava/lang/Object;)V
  #34 = Utf8               java/lang/NullPointerException
  #35 = NameAndType        #17:#44        // "<init>":()V
  #36 = NameAndType        #23:#24        // setValue:(Ljava/lang/Object;)Ljava/lang/Object;
  #37 = NameAndType        #45:#46        // getKey:()Ljava/lang/Object;
  #38 = Class              #47            // concurrentrefhashmap/ConcurrentReferenceHashMap
  #39 = NameAndType        #48:#49        // put:(Ljava/lang/Object;Ljava/lang/Object;)Ljava/lang/Object;
  #40 = Utf8               concurrentrefhashmap/ConcurrentReferenceHashMap$WriteThroughEntry
  #41 = Utf8               WriteThroughEntry
  #42 = Utf8               concurrentrefhashmap/ConcurrentReferenceHashMap$SimpleEntry
  #43 = Utf8               (Ljava/lang/Object;Ljava/lang/Object;)V
  #44 = Utf8               ()V
  #45 = Utf8               getKey
  #46 = Utf8               ()Ljava/lang/Object;
  #47 = Utf8               concurrentrefhashmap/ConcurrentReferenceHashMap
  #48 = Utf8               put
  #49 = Utf8               (Ljava/lang/Object;Ljava/lang/Object;)Ljava/lang/Object;
{
  private static final long serialVersionUID;
    descriptor: J
    flags: (0x001a) ACC_PRIVATE, ACC_STATIC, ACC_FINAL
    ConstantValue: long -7900634345345313646l

  final concurrentrefhashmap.ConcurrentReferenceHashMap this$0;
    descriptor: Lconcurrentrefhashmap/ConcurrentReferenceHashMap;
    flags: (0x1010) ACC_FINAL, ACC_SYNTHETIC

  concurrentrefhashmap.ConcurrentReferenceHashMap$WriteThroughEntry(K, V);
    descriptor: (Lconcurrentrefhashmap/ConcurrentReferenceHashMap;Ljava/lang/Object;Ljava/lang/Object;)V
    flags: (0x0000)
    Code:
      stack=3, locals=4, args_size=4
         0: aload_0
         1: aload_1
         2: putfield      #1                  // Field this$0:Lconcurrentrefhashmap/ConcurrentReferenceHashMap;
         5: aload_0
         6: aload_2
         7: aload_3
         8: invokespecial #2                  // Method concurrentrefhashmap/ConcurrentReferenceHashMap$SimpleEntry."<init>":(Ljava/lang/Object;Ljava/lang/Object;)V
        11: return
      LineNumberTable:
        line 1726: 0
        line 1727: 5
        line 1728: 11
    Signature: #22                          // (TK;TV;)V

  public V setValue(V);
    descriptor: (Ljava/lang/Object;)Ljava/lang/Object;
    flags: (0x0001) ACC_PUBLIC
    Code:
      stack=3, locals=3, args_size=2
         0: aload_1
         1: ifnonnull     12
         4: new           #3                  // class java/lang/NullPointerException
         7: dup
         8: invokespecial #4                  // Method java/lang/NullPointerException."<init>":()V
        11: athrow
        12: aload_0
        13: aload_1
        14: invokespecial #5                  // Method concurrentrefhashmap/ConcurrentReferenceHashMap$SimpleEntry.setValue:(Ljava/lang/Object;)Ljava/lang/Object;
        17: astore_2
        18: aload_0
        19: getfield      #1                  // Field this$0:Lconcurrentrefhashmap/ConcurrentReferenceHashMap;
        22: aload_0
        23: invokevirtual #6                  // Method getKey:()Ljava/lang/Object;
        26: aload_1
        27: invokevirtual #7                  // Method concurrentrefhashmap/ConcurrentReferenceHashMap.put:(Ljava/lang/Object;Ljava/lang/Object;)Ljava/lang/Object;
        30: pop
        31: aload_2
        32: areturn
      LineNumberTable:
        line 1741: 0
        line 1742: 4
        line 1744: 12
        line 1745: 18
        line 1746: 31
      StackMapTable: number_of_entries = 1
        frame_type = 12 /* same */
    Signature: #26                          // (TV;)TV;
}
Signature: #29                          // Lconcurrentrefhashmap/ConcurrentReferenceHashMap$SimpleEntry<TK;TV;>;
SourceFile: "ConcurrentReferenceHashMap.java"
InnerClasses:
  static #27= #9 of #38;                  // SimpleEntry=class concurrentrefhashmap/ConcurrentReferenceHashMap$SimpleEntry of class concurrentrefhashmap/ConcurrentReferenceHashMap
  final #41= #8 of #38;                   // WriteThroughEntry=class concurrentrefhashmap/ConcurrentReferenceHashMap$WriteThroughEntry of class concurrentrefhashmap/ConcurrentReferenceHashMap
