Classfile /Users/mw/Projects/slang-braindump/.jar/jar8/assemble/slang-braindump/assemble/content/concurrentrefhashmap/ConcurrentReferenceHashMap$ValueIterator.class
  Last modified May 29, 2022; size 1110 bytes
  SHA-256 checksum db1e8ba6d0c23c88f5add924d13f08055317eeb50a8b34713337c41613c866a5
  Compiled from "ConcurrentReferenceHashMap.java"
final class concurrentrefhashmap.ConcurrentReferenceHashMap$ValueIterator extends concurrentrefhashmap.ConcurrentReferenceHashMap<K, V>.HashIterator implements java.util.Iterator<V>, java.util.Enumeration<V>
  minor version: 0
  major version: 52
  flags: (0x0030) ACC_FINAL, ACC_SUPER
  this_class: #5                          // concurrentrefhashmap/ConcurrentReferenceHashMap$ValueIterator
  super_class: #6                         // concurrentrefhashmap/ConcurrentReferenceHashMap$HashIterator
  interfaces: 2, fields: 1, methods: 3, attributes: 3
Constant pool:
   #1 = Fieldref           #5.#25         // concurrentrefhashmap/ConcurrentReferenceHashMap$ValueIterator.this$0:Lconcurrentrefhashmap/ConcurrentReferenceHashMap;
   #2 = Methodref          #6.#26         // concurrentrefhashmap/ConcurrentReferenceHashMap$HashIterator."<init>":(Lconcurrentrefhashmap/ConcurrentReferenceHashMap;)V
   #3 = Methodref          #6.#27         // concurrentrefhashmap/ConcurrentReferenceHashMap$HashIterator.nextEntry:()Lconcurrentrefhashmap/ConcurrentReferenceHashMap$HashEntry;
   #4 = Methodref          #28.#29        // concurrentrefhashmap/ConcurrentReferenceHashMap$HashEntry.value:()Ljava/lang/Object;
   #5 = Class              #31            // concurrentrefhashmap/ConcurrentReferenceHashMap$ValueIterator
   #6 = Class              #33            // concurrentrefhashmap/ConcurrentReferenceHashMap$HashIterator
   #7 = Class              #34            // java/util/Iterator
   #8 = Class              #35            // java/util/Enumeration
   #9 = Utf8               this$0
  #10 = Utf8               Lconcurrentrefhashmap/ConcurrentReferenceHashMap;
  #11 = Utf8               <init>
  #12 = Utf8               (Lconcurrentrefhashmap/ConcurrentReferenceHashMap;)V
  #13 = Utf8               Code
  #14 = Utf8               LineNumberTable
  #15 = Utf8               next
  #16 = Utf8               ()Ljava/lang/Object;
  #17 = Utf8               Signature
  #18 = Utf8               ()TV;
  #19 = Utf8               nextElement
  #20 = Utf8               HashIterator
  #21 = Utf8               InnerClasses
  #22 = Utf8               Lconcurrentrefhashmap/ConcurrentReferenceHashMap<TK;TV;>.HashIterator;Ljava/util/Iterator<TV;>;Ljava/util/Enumeration<TV;>;
  #23 = Utf8               SourceFile
  #24 = Utf8               ConcurrentReferenceHashMap.java
  #25 = NameAndType        #9:#10         // this$0:Lconcurrentrefhashmap/ConcurrentReferenceHashMap;
  #26 = NameAndType        #11:#12        // "<init>":(Lconcurrentrefhashmap/ConcurrentReferenceHashMap;)V
  #27 = NameAndType        #36:#38        // nextEntry:()Lconcurrentrefhashmap/ConcurrentReferenceHashMap$HashEntry;
  #28 = Class              #39            // concurrentrefhashmap/ConcurrentReferenceHashMap$HashEntry
  #29 = NameAndType        #40:#16        // value:()Ljava/lang/Object;
  #30 = Class              #41            // concurrentrefhashmap/ConcurrentReferenceHashMap
  #31 = Utf8               concurrentrefhashmap/ConcurrentReferenceHashMap$ValueIterator
  #32 = Utf8               ValueIterator
  #33 = Utf8               concurrentrefhashmap/ConcurrentReferenceHashMap$HashIterator
  #34 = Utf8               java/util/Iterator
  #35 = Utf8               java/util/Enumeration
  #36 = Utf8               nextEntry
  #37 = Utf8               HashEntry
  #38 = Utf8               ()Lconcurrentrefhashmap/ConcurrentReferenceHashMap$HashEntry;
  #39 = Utf8               concurrentrefhashmap/ConcurrentReferenceHashMap$HashEntry
  #40 = Utf8               value
  #41 = Utf8               concurrentrefhashmap/ConcurrentReferenceHashMap
{
  final concurrentrefhashmap.ConcurrentReferenceHashMap this$0;
    descriptor: Lconcurrentrefhashmap/ConcurrentReferenceHashMap;
    flags: (0x1010) ACC_FINAL, ACC_SYNTHETIC

  concurrentrefhashmap.ConcurrentReferenceHashMap$ValueIterator(concurrentrefhashmap.ConcurrentReferenceHashMap);
    descriptor: (Lconcurrentrefhashmap/ConcurrentReferenceHashMap;)V
    flags: (0x0000)
    Code:
      stack=2, locals=2, args_size=2
         0: aload_0
         1: aload_1
         2: putfield      #1                  // Field this$0:Lconcurrentrefhashmap/ConcurrentReferenceHashMap;
         5: aload_0
         6: aload_1
         7: invokespecial #2                  // Method concurrentrefhashmap/ConcurrentReferenceHashMap$HashIterator."<init>":(Lconcurrentrefhashmap/ConcurrentReferenceHashMap;)V
        10: return
      LineNumberTable:
        line 1642: 0

  public V next();
    descriptor: ()Ljava/lang/Object;
    flags: (0x0001) ACC_PUBLIC
    Code:
      stack=1, locals=1, args_size=1
         0: aload_0
         1: invokespecial #3                  // Method concurrentrefhashmap/ConcurrentReferenceHashMap$HashIterator.nextEntry:()Lconcurrentrefhashmap/ConcurrentReferenceHashMap$HashEntry;
         4: invokevirtual #4                  // Method concurrentrefhashmap/ConcurrentReferenceHashMap$HashEntry.value:()Ljava/lang/Object;
         7: areturn
      LineNumberTable:
        line 1647: 0
    Signature: #18                          // ()TV;

  public V nextElement();
    descriptor: ()Ljava/lang/Object;
    flags: (0x0001) ACC_PUBLIC
    Code:
      stack=1, locals=1, args_size=1
         0: aload_0
         1: invokespecial #3                  // Method concurrentrefhashmap/ConcurrentReferenceHashMap$HashIterator.nextEntry:()Lconcurrentrefhashmap/ConcurrentReferenceHashMap$HashEntry;
         4: invokevirtual #4                  // Method concurrentrefhashmap/ConcurrentReferenceHashMap$HashEntry.value:()Ljava/lang/Object;
         7: areturn
      LineNumberTable:
        line 1652: 0
    Signature: #18                          // ()TV;
}
Signature: #22                          // Lconcurrentrefhashmap/ConcurrentReferenceHashMap<TK;TV;>.HashIterator;Ljava/util/Iterator<TV;>;Ljava/util/Enumeration<TV;>;
SourceFile: "ConcurrentReferenceHashMap.java"
InnerClasses:
  abstract #20= #6 of #30;                // HashIterator=class concurrentrefhashmap/ConcurrentReferenceHashMap$HashIterator of class concurrentrefhashmap/ConcurrentReferenceHashMap
  final #32= #5 of #30;                   // ValueIterator=class concurrentrefhashmap/ConcurrentReferenceHashMap$ValueIterator of class concurrentrefhashmap/ConcurrentReferenceHashMap
  static final #37= #28 of #30;           // HashEntry=class concurrentrefhashmap/ConcurrentReferenceHashMap$HashEntry of class concurrentrefhashmap/ConcurrentReferenceHashMap
