Classfile /Users/mw/Projects/slang-braindump/.jar/jar8/assemble/slang-braindump/assemble/content/concurrentrefhashmap/ConcurrentReferenceHashMap$ReferenceType.class
  Last modified May 29, 2022; size 1259 bytes
  SHA-256 checksum 0cb466fe28b59e77fcf77ade449a8621cf0746a8ac8f234df5a645baa21c9ded
  Compiled from "ConcurrentReferenceHashMap.java"
public final class concurrentrefhashmap.ConcurrentReferenceHashMap$ReferenceType extends java.lang.Enum<concurrentrefhashmap.ConcurrentReferenceHashMap$ReferenceType>
  minor version: 0
  major version: 52
  flags: (0x4031) ACC_PUBLIC, ACC_FINAL, ACC_SUPER, ACC_ENUM
  this_class: #4                          // concurrentrefhashmap/ConcurrentReferenceHashMap$ReferenceType
  super_class: #14                        // java/lang/Enum
  interfaces: 0, fields: 4, methods: 4, attributes: 3
Constant pool:
   #1 = Fieldref           #4.#37         // concurrentrefhashmap/ConcurrentReferenceHashMap$ReferenceType.$VALUES:[Lconcurrentrefhashmap/ConcurrentReferenceHashMap$ReferenceType;
   #2 = Methodref          #38.#39        // "[Lconcurrentrefhashmap/ConcurrentReferenceHashMap$ReferenceType;".clone:()Ljava/lang/Object;
   #3 = Class              #22            // "[Lconcurrentrefhashmap/ConcurrentReferenceHashMap$ReferenceType;"
   #4 = Class              #41            // concurrentrefhashmap/ConcurrentReferenceHashMap$ReferenceType
   #5 = Methodref          #14.#42        // java/lang/Enum.valueOf:(Ljava/lang/Class;Ljava/lang/String;)Ljava/lang/Enum;
   #6 = Methodref          #14.#43        // java/lang/Enum."<init>":(Ljava/lang/String;I)V
   #7 = String             #15            // STRONG
   #8 = Methodref          #4.#43         // concurrentrefhashmap/ConcurrentReferenceHashMap$ReferenceType."<init>":(Ljava/lang/String;I)V
   #9 = Fieldref           #4.#44         // concurrentrefhashmap/ConcurrentReferenceHashMap$ReferenceType.STRONG:Lconcurrentrefhashmap/ConcurrentReferenceHashMap$ReferenceType;
  #10 = String             #19            // WEAK
  #11 = Fieldref           #4.#45         // concurrentrefhashmap/ConcurrentReferenceHashMap$ReferenceType.WEAK:Lconcurrentrefhashmap/ConcurrentReferenceHashMap$ReferenceType;
  #12 = String             #20            // SOFT
  #13 = Fieldref           #4.#46         // concurrentrefhashmap/ConcurrentReferenceHashMap$ReferenceType.SOFT:Lconcurrentrefhashmap/ConcurrentReferenceHashMap$ReferenceType;
  #14 = Class              #47            // java/lang/Enum
  #15 = Utf8               STRONG
  #16 = Utf8               ReferenceType
  #17 = Utf8               InnerClasses
  #18 = Utf8               Lconcurrentrefhashmap/ConcurrentReferenceHashMap$ReferenceType;
  #19 = Utf8               WEAK
  #20 = Utf8               SOFT
  #21 = Utf8               $VALUES
  #22 = Utf8               [Lconcurrentrefhashmap/ConcurrentReferenceHashMap$ReferenceType;
  #23 = Utf8               values
  #24 = Utf8               ()[Lconcurrentrefhashmap/ConcurrentReferenceHashMap$ReferenceType;
  #25 = Utf8               Code
  #26 = Utf8               LineNumberTable
  #27 = Utf8               valueOf
  #28 = Utf8               (Ljava/lang/String;)Lconcurrentrefhashmap/ConcurrentReferenceHashMap$ReferenceType;
  #29 = Utf8               <init>
  #30 = Utf8               (Ljava/lang/String;I)V
  #31 = Utf8               Signature
  #32 = Utf8               ()V
  #33 = Utf8               <clinit>
  #34 = Utf8               Ljava/lang/Enum<Lconcurrentrefhashmap/ConcurrentReferenceHashMap$ReferenceType;>;
  #35 = Utf8               SourceFile
  #36 = Utf8               ConcurrentReferenceHashMap.java
  #37 = NameAndType        #21:#22        // $VALUES:[Lconcurrentrefhashmap/ConcurrentReferenceHashMap$ReferenceType;
  #38 = Class              #22            // "[Lconcurrentrefhashmap/ConcurrentReferenceHashMap$ReferenceType;"
  #39 = NameAndType        #48:#49        // clone:()Ljava/lang/Object;
  #40 = Class              #50            // concurrentrefhashmap/ConcurrentReferenceHashMap
  #41 = Utf8               concurrentrefhashmap/ConcurrentReferenceHashMap$ReferenceType
  #42 = NameAndType        #27:#51        // valueOf:(Ljava/lang/Class;Ljava/lang/String;)Ljava/lang/Enum;
  #43 = NameAndType        #29:#30        // "<init>":(Ljava/lang/String;I)V
  #44 = NameAndType        #15:#18        // STRONG:Lconcurrentrefhashmap/ConcurrentReferenceHashMap$ReferenceType;
  #45 = NameAndType        #19:#18        // WEAK:Lconcurrentrefhashmap/ConcurrentReferenceHashMap$ReferenceType;
  #46 = NameAndType        #20:#18        // SOFT:Lconcurrentrefhashmap/ConcurrentReferenceHashMap$ReferenceType;
  #47 = Utf8               java/lang/Enum
  #48 = Utf8               clone
  #49 = Utf8               ()Ljava/lang/Object;
  #50 = Utf8               concurrentrefhashmap/ConcurrentReferenceHashMap
  #51 = Utf8               (Ljava/lang/Class;Ljava/lang/String;)Ljava/lang/Enum;
{
  public static final concurrentrefhashmap.ConcurrentReferenceHashMap$ReferenceType STRONG;
    descriptor: Lconcurrentrefhashmap/ConcurrentReferenceHashMap$ReferenceType;
    flags: (0x4019) ACC_PUBLIC, ACC_STATIC, ACC_FINAL, ACC_ENUM

  public static final concurrentrefhashmap.ConcurrentReferenceHashMap$ReferenceType WEAK;
    descriptor: Lconcurrentrefhashmap/ConcurrentReferenceHashMap$ReferenceType;
    flags: (0x4019) ACC_PUBLIC, ACC_STATIC, ACC_FINAL, ACC_ENUM

  public static final concurrentrefhashmap.ConcurrentReferenceHashMap$ReferenceType SOFT;
    descriptor: Lconcurrentrefhashmap/ConcurrentReferenceHashMap$ReferenceType;
    flags: (0x4019) ACC_PUBLIC, ACC_STATIC, ACC_FINAL, ACC_ENUM

  private static final concurrentrefhashmap.ConcurrentReferenceHashMap$ReferenceType[] $VALUES;
    descriptor: [Lconcurrentrefhashmap/ConcurrentReferenceHashMap$ReferenceType;
    flags: (0x101a) ACC_PRIVATE, ACC_STATIC, ACC_FINAL, ACC_SYNTHETIC

  public static concurrentrefhashmap.ConcurrentReferenceHashMap$ReferenceType[] values();
    descriptor: ()[Lconcurrentrefhashmap/ConcurrentReferenceHashMap$ReferenceType;
    flags: (0x0009) ACC_PUBLIC, ACC_STATIC
    Code:
      stack=1, locals=0, args_size=0
         0: getstatic     #1                  // Field $VALUES:[Lconcurrentrefhashmap/ConcurrentReferenceHashMap$ReferenceType;
         3: invokevirtual #2                  // Method "[Lconcurrentrefhashmap/ConcurrentReferenceHashMap$ReferenceType;".clone:()Ljava/lang/Object;
         6: checkcast     #3                  // class "[Lconcurrentrefhashmap/ConcurrentReferenceHashMap$ReferenceType;"
         9: areturn
      LineNumberTable:
        line 147: 0

  public static concurrentrefhashmap.ConcurrentReferenceHashMap$ReferenceType valueOf(java.lang.String);
    descriptor: (Ljava/lang/String;)Lconcurrentrefhashmap/ConcurrentReferenceHashMap$ReferenceType;
    flags: (0x0009) ACC_PUBLIC, ACC_STATIC
    Code:
      stack=2, locals=1, args_size=1
         0: ldc           #4                  // class concurrentrefhashmap/ConcurrentReferenceHashMap$ReferenceType
         2: aload_0
         3: invokestatic  #5                  // Method java/lang/Enum.valueOf:(Ljava/lang/Class;Ljava/lang/String;)Ljava/lang/Enum;
         6: checkcast     #4                  // class concurrentrefhashmap/ConcurrentReferenceHashMap$ReferenceType
         9: areturn
      LineNumberTable:
        line 147: 0

  private concurrentrefhashmap.ConcurrentReferenceHashMap$ReferenceType();
    descriptor: (Ljava/lang/String;I)V
    flags: (0x0002) ACC_PRIVATE
    Code:
      stack=3, locals=3, args_size=3
         0: aload_0
         1: aload_1
         2: iload_2
         3: invokespecial #6                  // Method java/lang/Enum."<init>":(Ljava/lang/String;I)V
         6: return
      LineNumberTable:
        line 147: 0
    Signature: #32                          // ()V

  static {};
    descriptor: ()V
    flags: (0x0008) ACC_STATIC
    Code:
      stack=4, locals=0, args_size=0
         0: new           #4                  // class concurrentrefhashmap/ConcurrentReferenceHashMap$ReferenceType
         3: dup
         4: ldc           #7                  // String STRONG
         6: iconst_0
         7: invokespecial #8                  // Method "<init>":(Ljava/lang/String;I)V
        10: putstatic     #9                  // Field STRONG:Lconcurrentrefhashmap/ConcurrentReferenceHashMap$ReferenceType;
        13: new           #4                  // class concurrentrefhashmap/ConcurrentReferenceHashMap$ReferenceType
        16: dup
        17: ldc           #10                 // String WEAK
        19: iconst_1
        20: invokespecial #8                  // Method "<init>":(Ljava/lang/String;I)V
        23: putstatic     #11                 // Field WEAK:Lconcurrentrefhashmap/ConcurrentReferenceHashMap$ReferenceType;
        26: new           #4                  // class concurrentrefhashmap/ConcurrentReferenceHashMap$ReferenceType
        29: dup
        30: ldc           #12                 // String SOFT
        32: iconst_2
        33: invokespecial #8                  // Method "<init>":(Ljava/lang/String;I)V
        36: putstatic     #13                 // Field SOFT:Lconcurrentrefhashmap/ConcurrentReferenceHashMap$ReferenceType;
        39: iconst_3
        40: anewarray     #4                  // class concurrentrefhashmap/ConcurrentReferenceHashMap$ReferenceType
        43: dup
        44: iconst_0
        45: getstatic     #9                  // Field STRONG:Lconcurrentrefhashmap/ConcurrentReferenceHashMap$ReferenceType;
        48: aastore
        49: dup
        50: iconst_1
        51: getstatic     #11                 // Field WEAK:Lconcurrentrefhashmap/ConcurrentReferenceHashMap$ReferenceType;
        54: aastore
        55: dup
        56: iconst_2
        57: getstatic     #13                 // Field SOFT:Lconcurrentrefhashmap/ConcurrentReferenceHashMap$ReferenceType;
        60: aastore
        61: putstatic     #1                  // Field $VALUES:[Lconcurrentrefhashmap/ConcurrentReferenceHashMap$ReferenceType;
        64: return
      LineNumberTable:
        line 151: 0
        line 155: 13
        line 159: 26
        line 147: 39
}
Signature: #34                          // Ljava/lang/Enum<Lconcurrentrefhashmap/ConcurrentReferenceHashMap$ReferenceType;>;
SourceFile: "ConcurrentReferenceHashMap.java"
InnerClasses:
  public static final #16= #4 of #40;     // ReferenceType=class concurrentrefhashmap/ConcurrentReferenceHashMap$ReferenceType of class concurrentrefhashmap/ConcurrentReferenceHashMap
