Classfile /Users/mw/Projects/slang-braindump/.jar/jar8/assemble/slang-braindump/assemble/content/concurrentrefhashmap/ConcurrentReferenceHashMap$WeakValueReference.class
  Last modified May 29, 2022; size 1048 bytes
  SHA-256 checksum 385541727f348554a44e286003a914752381b44c2815aae7f260a00847a58796
  Compiled from "ConcurrentReferenceHashMap.java"
final class concurrentrefhashmap.ConcurrentReferenceHashMap$WeakValueReference<V extends java.lang.Object> extends java.lang.ref.WeakReference<V> implements concurrentrefhashmap.ConcurrentReferenceHashMap$KeyReference
  minor version: 0
  major version: 52
  flags: (0x0030) ACC_FINAL, ACC_SUPER
  this_class: #4                          // concurrentrefhashmap/ConcurrentReferenceHashMap$WeakValueReference
  super_class: #5                         // java/lang/ref/WeakReference
  interfaces: 1, fields: 2, methods: 3, attributes: 3
Constant pool:
   #1 = Methodref          #5.#25         // java/lang/ref/WeakReference."<init>":(Ljava/lang/Object;Ljava/lang/ref/ReferenceQueue;)V
   #2 = Fieldref           #4.#26         // concurrentrefhashmap/ConcurrentReferenceHashMap$WeakValueReference.keyRef:Ljava/lang/Object;
   #3 = Fieldref           #4.#27         // concurrentrefhashmap/ConcurrentReferenceHashMap$WeakValueReference.hash:I
   #4 = Class              #29            // concurrentrefhashmap/ConcurrentReferenceHashMap$WeakValueReference
   #5 = Class              #31            // java/lang/ref/WeakReference
   #6 = Class              #32            // concurrentrefhashmap/ConcurrentReferenceHashMap$KeyReference
   #7 = Utf8               keyRef
   #8 = Utf8               Ljava/lang/Object;
   #9 = Utf8               hash
  #10 = Utf8               I
  #11 = Utf8               <init>
  #12 = Utf8               (Ljava/lang/Object;Ljava/lang/Object;ILjava/lang/ref/ReferenceQueue;)V
  #13 = Utf8               Code
  #14 = Utf8               LineNumberTable
  #15 = Utf8               Signature
  #16 = Utf8               (TV;Ljava/lang/Object;ILjava/lang/ref/ReferenceQueue<Ljava/lang/Object;>;)V
  #17 = Utf8               keyHash
  #18 = Utf8               ()I
  #19 = Utf8               ()Ljava/lang/Object;
  #20 = Utf8               KeyReference
  #21 = Utf8               InnerClasses
  #22 = Utf8               <V:Ljava/lang/Object;>Ljava/lang/ref/WeakReference<TV;>;Lconcurrentrefhashmap/ConcurrentReferenceHashMap$KeyReference;
  #23 = Utf8               SourceFile
  #24 = Utf8               ConcurrentReferenceHashMap.java
  #25 = NameAndType        #11:#33        // "<init>":(Ljava/lang/Object;Ljava/lang/ref/ReferenceQueue;)V
  #26 = NameAndType        #7:#8          // keyRef:Ljava/lang/Object;
  #27 = NameAndType        #9:#10         // hash:I
  #28 = Class              #34            // concurrentrefhashmap/ConcurrentReferenceHashMap
  #29 = Utf8               concurrentrefhashmap/ConcurrentReferenceHashMap$WeakValueReference
  #30 = Utf8               WeakValueReference
  #31 = Utf8               java/lang/ref/WeakReference
  #32 = Utf8               concurrentrefhashmap/ConcurrentReferenceHashMap$KeyReference
  #33 = Utf8               (Ljava/lang/Object;Ljava/lang/ref/ReferenceQueue;)V
  #34 = Utf8               concurrentrefhashmap/ConcurrentReferenceHashMap
{
  final java.lang.Object keyRef;
    descriptor: Ljava/lang/Object;
    flags: (0x0010) ACC_FINAL

  final int hash;
    descriptor: I
    flags: (0x0010) ACC_FINAL

  concurrentrefhashmap.ConcurrentReferenceHashMap$WeakValueReference(V, java.lang.Object, int, java.lang.ref.ReferenceQueue<java.lang.Object>);
    descriptor: (Ljava/lang/Object;Ljava/lang/Object;ILjava/lang/ref/ReferenceQueue;)V
    flags: (0x0000)
    Code:
      stack=3, locals=5, args_size=5
         0: aload_0
         1: aload_1
         2: aload         4
         4: invokespecial #1                  // Method java/lang/ref/WeakReference."<init>":(Ljava/lang/Object;Ljava/lang/ref/ReferenceQueue;)V
         7: aload_0
         8: aload_2
         9: putfield      #2                  // Field keyRef:Ljava/lang/Object;
        12: aload_0
        13: iload_3
        14: putfield      #3                  // Field hash:I
        17: return
      LineNumberTable:
        line 341: 0
        line 342: 7
        line 343: 12
        line 344: 17
    Signature: #16                          // (TV;Ljava/lang/Object;ILjava/lang/ref/ReferenceQueue<Ljava/lang/Object;>;)V

  public final int keyHash();
    descriptor: ()I
    flags: (0x0011) ACC_PUBLIC, ACC_FINAL
    Code:
      stack=1, locals=1, args_size=1
         0: aload_0
         1: getfield      #3                  // Field hash:I
         4: ireturn
      LineNumberTable:
        line 348: 0

  public final java.lang.Object keyRef();
    descriptor: ()Ljava/lang/Object;
    flags: (0x0011) ACC_PUBLIC, ACC_FINAL
    Code:
      stack=1, locals=1, args_size=1
         0: aload_0
         1: getfield      #2                  // Field keyRef:Ljava/lang/Object;
         4: areturn
      LineNumberTable:
        line 353: 0
}
Signature: #22                          // <V:Ljava/lang/Object;>Ljava/lang/ref/WeakReference<TV;>;Lconcurrentrefhashmap/ConcurrentReferenceHashMap$KeyReference;
SourceFile: "ConcurrentReferenceHashMap.java"
InnerClasses:
  static #20= #6 of #28;                  // KeyReference=class concurrentrefhashmap/ConcurrentReferenceHashMap$KeyReference of class concurrentrefhashmap/ConcurrentReferenceHashMap
  static final #30= #4 of #28;            // WeakValueReference=class concurrentrefhashmap/ConcurrentReferenceHashMap$WeakValueReference of class concurrentrefhashmap/ConcurrentReferenceHashMap
