Classfile /Users/mw/Projects/slang-braindump/.jar/jar11/assemble/slang-braindump/assemble/content/scala/util/ChainingOps.class
  Last modified May 29, 2022; size 3420 bytes
  SHA-256 checksum 34b9b27b0fe2ed0e0bd1b9bf331d48d2cd4e60ef55536983266191d964ee0bb0
  Compiled from "ChainingOps.scala"
public final class scala.util.ChainingOps<A extends java.lang.Object> extends java.lang.Object
  minor version: 0
  major version: 52
  flags: (0x0031) ACC_PUBLIC, ACC_FINAL, ACC_SUPER
  this_class: #2                          // scala/util/ChainingOps
  super_class: #5                         // java/lang/Object
  interfaces: 0, fields: 1, methods: 10, attributes: 5
Constant pool:
   #1 = Utf8               scala/util/ChainingOps
   #2 = Class              #1             // scala/util/ChainingOps
   #3 = Utf8               <A:Ljava/lang/Object;>Ljava/lang/Object;
   #4 = Utf8               java/lang/Object
   #5 = Class              #4             // java/lang/Object
   #6 = Utf8               ChainingOps.scala
   #7 = Utf8               Lscala/reflect/ScalaSignature;
   #8 = Utf8               bytes
   #9 = Utf8               \u0006\u0005y4Aa\u0004\t\u0003+!a1\u0004\u0001C\u0001\u0002\u000b\u0015)\u0019!C\u00059!I\u0001\u0006\u0001B\u0003\u0002\u0003\u0006I!\b\u0005\u0006S\u0001!\tA\u000b\u0005\u0006_\u0001!\t\u0001\r\u0005\u0006u\u0001!\ta\u000f\u0005\b\u0005\u0002\t\t\u0011\"\u0011D\u0011\u001d9\u0005!!A\u0005B!;qA\u0014\t\u0002\u0002#\u0005qJB\u0004\u0010!\u0005\u0005\t\u0012\u0001)\t\u000b%JA\u0011\u0001+\t\u000bUKAQ\u0001,\t\u000b\tLAQA2\t\u000f9L\u0011\u0011!C\u0003_\"9Q/CA\u0001\n\u000b1(aC\"iC&t\u0017N\\4PaNT!!\u0005\n\u0002\tU$\u0018\u000e\u001c\u0006\u0002\'\u0005)1oY1mC\u000e\u0001QC\u0001\f \'\t\u0001q\u0003\u0005\u0002\u001935\t!#\u0003\u0002\u001b%\t1\u0011I\\=WC2\fAd]2bY\u0006$S\u000f^5mI\rC\u0017-\u001b8j]\u001e|\u0005o\u001d\u0013%g\u0016dg-F\u0001\u001e!\tqr\u0004\u0004\u0001\u0005\u000b\u0001\u0002!\u0019A\u0011\u0003\u0003\u0005\u000b\"AI\u0013\u0011\u0005a\u0019\u0013B\u0001\u0013\u0013\u0005\u001dqu\u000e\u001e5j]\u001e\u0004\"\u0001\u0007\u0014\n\u0005\u001d\u0012\"aA!os\u0006i2oY1mC\u0012*H/\u001b7%\u0007\"\f\u0017N\\5oO>\u00038\u000f\n\u0013tK24\u0007%\u0001\u0004=S:LGO\u0010\u000b\u0003W5\u00022\u0001\f\u0001\u001e\u001b\u0005\u0001\u0002\"\u0002\u0018\u0004\u0001\u0004i\u0012\u0001B:fY\u001a\f1\u0001^1q+\t\t\u0004\b\u0006\u0002\u001ee!)1\u0007\u0002a\u0001i\u0005\ta\r\u0005\u0003\u0019ku9\u0014B\u0001\u001c\u0013\u0005%1UO\\2uS>t\u0017\u0007\u0005\u0002\u001fq\u0011)\u0011\b\u0002b\u0001C\t\tQ+\u0001\u0003qSB,WC\u0001\u001f?)\ti\u0004\t\u0005\u0002\u001f}\u0011)q(\u0002b\u0001C\t\t!\tC\u00034\u000b\u0001\u0007\u0011\t\u0005\u0003\u0019kui\u0014\u0001\u00035bg\"\u001cu\u000eZ3\u0015\u0003\u0011\u0003\"\u0001G#\n\u0005\u0019\u0013\"aA%oi\u00061Q-];bYN$\"!\u0013\'\u0011\u0005aQ\u0015BA&\u0013\u0005\u001d\u0011un\u001c7fC:Dq!T\u0004\u0002\u0002\u0003\u0007Q%A\u0002yIE\n1b\u00115bS:LgnZ(qgB\u0011A&C\n\u0003\u0013E\u0003\"\u0001\u0007*\n\u0005M\u0013\"AB!osJ+g\rF\u0001P\u00035!\u0018\r\u001d\u0013fqR,gn]5p]V\u0019qK\u0018.\u0015\u0005a{FCA-\\!\tq\"\fB\u0003!\u0017\t\u0007\u0011\u0005C\u00034\u0017\u0001\u0007A\f\u0005\u0003\u0019kek\u0006C\u0001\u0010_\t\u0015I4B1\u0001\"\u0011\u0015\u00017\u00021\u0001b\u0003\u0015!C\u000f[5t!\ra\u0003!W\u0001\u000fa&\u0004X\rJ3yi\u0016t7/[8o+\r!wm\u001b\u000b\u0003K2$\"A\u001a5\u0011\u0005y9G!B \r\u0005\u0004\t\u0003\"B\u001a\r\u0001\u0004I\u0007\u0003\u0002\r6U\u001a\u0004\"AH6\u0005\u000b\u0001b!\u0019A\u0011\t\u000b\u0001d\u0001\u0019A7\u0011\u00071\u0002!.\u0001\niCND7i\u001c3fI\u0015DH/\u001a8tS>tWC\u00019u)\t\u0019\u0015\u000fC\u0003a\u001b\u0001\u0007!\u000fE\u0002-\u0001M\u0004\"A\b;\u0005\u000b\u0001j!\u0019A\u0011\u0002!\u0015\fX/\u00197tI\u0015DH/\u001a8tS>tWCA<~)\tA(\u0010\u0006\u0002Js\"9QJDA\u0001\u0002\u0004)\u0003\"\u00021\u000f\u0001\u0004Y\bc\u0001\u0017\u0001yB\u0011a$ \u0003\u0006A9\u0011\r!\t
  #10 = Utf8               scala$util$ChainingOps$$self
  #11 = Utf8               Ljava/lang/Object;
  #12 = Utf8               TA;
  #13 = Utf8               equals$extension
  #14 = Utf8               (Ljava/lang/Object;Ljava/lang/Object;)Z
  #15 = Utf8               <A:Ljava/lang/Object;>(TA;Ljava/lang/Object;)Z
  #16 = Utf8               $this
  #17 = Utf8               x$1
  #18 = Utf8               scala/util/ChainingOps$
  #19 = Class              #18            // scala/util/ChainingOps$
  #20 = Utf8               MODULE$
  #21 = Utf8               Lscala/util/ChainingOps$;
  #22 = NameAndType        #20:#21        // MODULE$:Lscala/util/ChainingOps$;
  #23 = Fieldref           #19.#22        // scala/util/ChainingOps$.MODULE$:Lscala/util/ChainingOps$;
  #24 = NameAndType        #13:#14        // equals$extension:(Ljava/lang/Object;Ljava/lang/Object;)Z
  #25 = Methodref          #19.#24        // scala/util/ChainingOps$.equals$extension:(Ljava/lang/Object;Ljava/lang/Object;)Z
  #26 = Utf8               hashCode$extension
  #27 = Utf8               (Ljava/lang/Object;)I
  #28 = Utf8               <A:Ljava/lang/Object;>(TA;)I
  #29 = Utf8               hashCode
  #30 = Utf8               ()I
  #31 = NameAndType        #29:#30        // hashCode:()I
  #32 = Methodref          #5.#31         // java/lang/Object.hashCode:()I
  #33 = Utf8               pipe$extension
  #34 = Utf8               (Ljava/lang/Object;Lscala/Function1;)Ljava/lang/Object;
  #35 = Utf8               <B:Ljava/lang/Object;A:Ljava/lang/Object;>(TA;Lscala/Function1<TA;TB;>;)TB;
  #36 = Utf8               f
  #37 = Utf8               scala/Function1
  #38 = Class              #37            // scala/Function1
  #39 = Utf8               apply
  #40 = Utf8               (Ljava/lang/Object;)Ljava/lang/Object;
  #41 = NameAndType        #39:#40        // apply:(Ljava/lang/Object;)Ljava/lang/Object;
  #42 = InterfaceMethodref #38.#41        // scala/Function1.apply:(Ljava/lang/Object;)Ljava/lang/Object;
  #43 = Utf8               Lscala/Function1;
  #44 = Utf8               tap$extension
  #45 = Utf8               <U:Ljava/lang/Object;A:Ljava/lang/Object;>(TA;Lscala/Function1<TA;TU;>;)TA;
  #46 = Utf8               ()Ljava/lang/Object;
  #47 = Utf8               ()TA;
  #48 = NameAndType        #10:#11        // scala$util$ChainingOps$$self:Ljava/lang/Object;
  #49 = Fieldref           #2.#48         // scala/util/ChainingOps.scala$util$ChainingOps$$self:Ljava/lang/Object;
  #50 = Utf8               this
  #51 = Utf8               Lscala/util/ChainingOps;
  #52 = Utf8               tap
  #53 = Utf8               (Lscala/Function1;)Ljava/lang/Object;
  #54 = Utf8               <U:Ljava/lang/Object;>(Lscala/Function1<TA;TU;>;)TA;
  #55 = NameAndType        #10:#46        // scala$util$ChainingOps$$self:()Ljava/lang/Object;
  #56 = Methodref          #2.#55         // scala/util/ChainingOps.scala$util$ChainingOps$$self:()Ljava/lang/Object;
  #57 = Utf8               tap$extension_$this
  #58 = Utf8               pipe
  #59 = Utf8               <B:Ljava/lang/Object;>(Lscala/Function1<TA;TB;>;)TB;
  #60 = Utf8               pipe$extension_$this
  #61 = Utf8               equals
  #62 = Utf8               (Ljava/lang/Object;)Z
  #63 = Utf8               <init>
  #64 = Utf8               (Ljava/lang/Object;)V
  #65 = Utf8               (TA;)V
  #66 = Utf8               self
  #67 = Utf8               ()V
  #68 = NameAndType        #63:#67        // "<init>":()V
  #69 = Methodref          #5.#68         // java/lang/Object."<init>":()V
  #70 = Utf8               Signature
  #71 = Utf8               Code
  #72 = Utf8               LocalVariableTable
  #73 = Utf8               MethodParameters
  #74 = Utf8               LineNumberTable
  #75 = Utf8               SourceFile
  #76 = Utf8               RuntimeVisibleAnnotations
  #77 = Utf8               ScalaInlineInfo
  #78 = Utf8               ScalaSig
{
  private final A scala$util$ChainingOps$$self;
    descriptor: Ljava/lang/Object;
    flags: (0x0012) ACC_PRIVATE, ACC_FINAL
    Signature: #12                          // TA;

  public static <A extends java.lang.Object> boolean equals$extension(A, java.lang.Object);
    descriptor: (Ljava/lang/Object;Ljava/lang/Object;)Z
    flags: (0x0009) ACC_PUBLIC, ACC_STATIC
    Code:
      stack=3, locals=2, args_size=2
         0: getstatic     #23                 // Field scala/util/ChainingOps$.MODULE$:Lscala/util/ChainingOps$;
         3: aload_0
         4: aload_1
         5: invokevirtual #25                 // Method scala/util/ChainingOps$.equals$extension:(Ljava/lang/Object;Ljava/lang/Object;)Z
         8: ireturn
      LocalVariableTable:
        Start  Length  Slot  Name   Signature
            0       9     0 $this   Ljava/lang/Object;
            0       9     1   x$1   Ljava/lang/Object;
    Signature: #15                          // <A:Ljava/lang/Object;>(TA;Ljava/lang/Object;)Z
    MethodParameters:
      Name                           Flags
      $this                          final
      x$1                            final

  public static <A extends java.lang.Object> int hashCode$extension(A);
    descriptor: (Ljava/lang/Object;)I
    flags: (0x0009) ACC_PUBLIC, ACC_STATIC
    Code:
      stack=1, locals=1, args_size=1
         0: getstatic     #23                 // Field scala/util/ChainingOps$.MODULE$:Lscala/util/ChainingOps$;
         3: pop
         4: aload_0
         5: invokevirtual #32                 // Method java/lang/Object.hashCode:()I
         8: ireturn
      LineNumberTable:
        line 24: 4
      LocalVariableTable:
        Start  Length  Slot  Name   Signature
            0       9     0 $this   Ljava/lang/Object;
    Signature: #28                          // <A:Ljava/lang/Object;>(TA;)I
    MethodParameters:
      Name                           Flags
      $this                          final

  public static <B extends java.lang.Object, A extends java.lang.Object> B pipe$extension(A, scala.Function1<A, B>);
    descriptor: (Ljava/lang/Object;Lscala/Function1;)Ljava/lang/Object;
    flags: (0x0009) ACC_PUBLIC, ACC_STATIC
    Code:
      stack=2, locals=2, args_size=2
         0: getstatic     #23                 // Field scala/util/ChainingOps$.MODULE$:Lscala/util/ChainingOps$;
         3: pop
         4: aload_1
         5: aload_0
         6: invokeinterface #42,  2           // InterfaceMethod scala/Function1.apply:(Ljava/lang/Object;)Ljava/lang/Object;
        11: areturn
      LineNumberTable:
        line 64: 4
      LocalVariableTable:
        Start  Length  Slot  Name   Signature
            0      12     0 $this   Ljava/lang/Object;
            0      12     1     f   Lscala/Function1;
    Signature: #35                          // <B:Ljava/lang/Object;A:Ljava/lang/Object;>(TA;Lscala/Function1<TA;TB;>;)TB;
    MethodParameters:
      Name                           Flags
      $this                          final
      f                              final

  public static <U extends java.lang.Object, A extends java.lang.Object> A tap$extension(A, scala.Function1<A, U>);
    descriptor: (Ljava/lang/Object;Lscala/Function1;)Ljava/lang/Object;
    flags: (0x0009) ACC_PUBLIC, ACC_STATIC
    Code:
      stack=2, locals=2, args_size=2
         0: getstatic     #23                 // Field scala/util/ChainingOps$.MODULE$:Lscala/util/ChainingOps$;
         3: pop
         4: aload_1
         5: aload_0
         6: invokeinterface #42,  2           // InterfaceMethod scala/Function1.apply:(Ljava/lang/Object;)Ljava/lang/Object;
        11: pop
        12: aload_0
        13: areturn
      LineNumberTable:
        line 40: 4
      LocalVariableTable:
        Start  Length  Slot  Name   Signature
            0      14     0 $this   Ljava/lang/Object;
            0      14     1     f   Lscala/Function1;
    Signature: #45                          // <U:Ljava/lang/Object;A:Ljava/lang/Object;>(TA;Lscala/Function1<TA;TU;>;)TA;
    MethodParameters:
      Name                           Flags
      $this                          final
      f                              final

  public A scala$util$ChainingOps$$self();
    descriptor: ()Ljava/lang/Object;
    flags: (0x0001) ACC_PUBLIC
    Code:
      stack=1, locals=1, args_size=1
         0: aload_0
         1: getfield      #49                 // Field scala$util$ChainingOps$$self:Ljava/lang/Object;
         4: areturn
      LineNumberTable:
        line 24: 0
      LocalVariableTable:
        Start  Length  Slot  Name   Signature
            0       5     0  this   Lscala/util/ChainingOps;
    Signature: #47                          // ()TA;

  public <U extends java.lang.Object> A tap(scala.Function1<A, U>);
    descriptor: (Lscala/Function1;)Ljava/lang/Object;
    flags: (0x0001) ACC_PUBLIC
    Code:
      stack=2, locals=3, args_size=2
         0: getstatic     #23                 // Field scala/util/ChainingOps$.MODULE$:Lscala/util/ChainingOps$;
         3: pop
         4: aload_0
         5: invokevirtual #56                 // Method scala$util$ChainingOps$$self:()Ljava/lang/Object;
         8: astore_2
         9: aload_1
        10: aload_2
        11: invokeinterface #42,  2           // InterfaceMethod scala/Function1.apply:(Ljava/lang/Object;)Ljava/lang/Object;
        16: pop
        17: aload_2
        18: areturn
      LineNumberTable:
        line 39: 0
        line 40: 9
        line 39: 17
      LocalVariableTable:
        Start  Length  Slot  Name   Signature
            0      19     0  this   Lscala/util/ChainingOps;
            0      19     1     f   Lscala/Function1;
            9       8     2 tap$extension_$this   Ljava/lang/Object;
    Signature: #54                          // <U:Ljava/lang/Object;>(Lscala/Function1<TA;TU;>;)TA;
    MethodParameters:
      Name                           Flags
      f                              final

  public <B extends java.lang.Object> B pipe(scala.Function1<A, B>);
    descriptor: (Lscala/Function1;)Ljava/lang/Object;
    flags: (0x0001) ACC_PUBLIC
    Code:
      stack=2, locals=3, args_size=2
         0: getstatic     #23                 // Field scala/util/ChainingOps$.MODULE$:Lscala/util/ChainingOps$;
         3: pop
         4: aload_0
         5: invokevirtual #56                 // Method scala$util$ChainingOps$$self:()Ljava/lang/Object;
         8: astore_2
         9: aload_1
        10: aload_2
        11: invokeinterface #42,  2           // InterfaceMethod scala/Function1.apply:(Ljava/lang/Object;)Ljava/lang/Object;
        16: areturn
      LineNumberTable:
        line 64: 0
        line 64: 9
        line 64: 16
      LocalVariableTable:
        Start  Length  Slot  Name   Signature
            0      17     0  this   Lscala/util/ChainingOps;
            0      17     1     f   Lscala/Function1;
            9       7     2 pipe$extension_$this   Ljava/lang/Object;
    Signature: #59                          // <B:Ljava/lang/Object;>(Lscala/Function1<TA;TB;>;)TB;
    MethodParameters:
      Name                           Flags
      f                              final

  public int hashCode();
    descriptor: ()I
    flags: (0x0001) ACC_PUBLIC
    Code:
      stack=1, locals=1, args_size=1
         0: getstatic     #23                 // Field scala/util/ChainingOps$.MODULE$:Lscala/util/ChainingOps$;
         3: pop
         4: aload_0
         5: invokevirtual #56                 // Method scala$util$ChainingOps$$self:()Ljava/lang/Object;
         8: invokevirtual #32                 // Method java/lang/Object.hashCode:()I
        11: ireturn
      LineNumberTable:
        line 24: 0
        line 24: 8
        line 24: 11
      LocalVariableTable:
        Start  Length  Slot  Name   Signature
            0      12     0  this   Lscala/util/ChainingOps;

  public boolean equals(java.lang.Object);
    descriptor: (Ljava/lang/Object;)Z
    flags: (0x0001) ACC_PUBLIC
    Code:
      stack=3, locals=2, args_size=2
         0: getstatic     #23                 // Field scala/util/ChainingOps$.MODULE$:Lscala/util/ChainingOps$;
         3: aload_0
         4: invokevirtual #56                 // Method scala$util$ChainingOps$$self:()Ljava/lang/Object;
         7: aload_1
         8: invokevirtual #25                 // Method scala/util/ChainingOps$.equals$extension:(Ljava/lang/Object;Ljava/lang/Object;)Z
        11: ireturn
      LineNumberTable:
        line 24: 0
      LocalVariableTable:
        Start  Length  Slot  Name   Signature
            0      12     0  this   Lscala/util/ChainingOps;
            0      12     1   x$1   Ljava/lang/Object;
    MethodParameters:
      Name                           Flags
      x$1                            final

  public scala.util.ChainingOps(A);
    descriptor: (Ljava/lang/Object;)V
    flags: (0x0001) ACC_PUBLIC
    Code:
      stack=2, locals=2, args_size=2
         0: aload_0
         1: aload_1
         2: putfield      #49                 // Field scala$util$ChainingOps$$self:Ljava/lang/Object;
         5: aload_0
         6: invokespecial #69                 // Method java/lang/Object."<init>":()V
         9: return
      LineNumberTable:
        line 24: 0
      LocalVariableTable:
        Start  Length  Slot  Name   Signature
            0      10     0  this   Lscala/util/ChainingOps;
            0      10     1  self   Ljava/lang/Object;
    Signature: #65                          // (TA;)V
    MethodParameters:
      Name                           Flags
      self                           final
}
Signature: #3                           // <A:Ljava/lang/Object;>Ljava/lang/Object;
SourceFile: "ChainingOps.scala"
RuntimeVisibleAnnotations:
  0: #7(#8=s#9)
    scala.reflect.ScalaSignature(
      bytes="\u0006\u0005y4Aa\u0004\t\u0003+!a1\u0004\u0001C\u0001\u0002\u000b\u0015)\u0019!C\u00059!I\u0001\u0006\u0001B\u0003\u0002\u0003\u0006I!\b\u0005\u0006S\u0001!\tA\u000b\u0005\u0006_\u0001!\t\u0001\r\u0005\u0006u\u0001!\ta\u000f\u0005\b\u0005\u0002\t\t\u0011\"\u0011D\u0011\u001d9\u0005!!A\u0005B!;qA\u0014\t\u0002\u0002#\u0005qJB\u0004\u0010!\u0005\u0005\t\u0012\u0001)\t\u000b%JA\u0011\u0001+\t\u000bUKAQ\u0001,\t\u000b\tLAQA2\t\u000f9L\u0011\u0011!C\u0003_\"9Q/CA\u0001\n\u000b1(aC\"iC&t\u0017N\\4PaNT!!\u0005\n\u0002\tU$\u0018\u000e\u001c\u0006\u0002\'\u0005)1oY1mC\u000e\u0001QC\u0001\f \'\t\u0001q\u0003\u0005\u0002\u001935\t!#\u0003\u0002\u001b%\t1\u0011I\\=WC2\fAd]2bY\u0006$S\u000f^5mI\rC\u0017-\u001b8j]\u001e|\u0005o\u001d\u0013%g\u0016dg-F\u0001\u001e!\tqr\u0004\u0004\u0001\u0005\u000b\u0001\u0002!\u0019A\u0011\u0003\u0003\u0005\u000b\"AI\u0013\u0011\u0005a\u0019\u0013B\u0001\u0013\u0013\u0005\u001dqu\u000e\u001e5j]\u001e\u0004\"\u0001\u0007\u0014\n\u0005\u001d\u0012\"aA!os\u0006i2oY1mC\u0012*H/\u001b7%\u0007\"\f\u0017N\\5oO>\u00038\u000f\n\u0013tK24\u0007%\u0001\u0004=S:LGO\u0010\u000b\u0003W5\u00022\u0001\f\u0001\u001e\u001b\u0005\u0001\u0002\"\u0002\u0018\u0004\u0001\u0004i\u0012\u0001B:fY\u001a\f1\u0001^1q+\t\t\u0004\b\u0006\u0002\u001ee!)1\u0007\u0002a\u0001i\u0005\ta\r\u0005\u0003\u0019ku9\u0014B\u0001\u001c\u0013\u0005%1UO\\2uS>t\u0017\u0007\u0005\u0002\u001fq\u0011)\u0011\b\u0002b\u0001C\t\tQ+\u0001\u0003qSB,WC\u0001\u001f?)\ti\u0004\t\u0005\u0002\u001f}\u0011)q(\u0002b\u0001C\t\t!\tC\u00034\u000b\u0001\u0007\u0011\t\u0005\u0003\u0019kui\u0014\u0001\u00035bg\"\u001cu\u000eZ3\u0015\u0003\u0011\u0003\"\u0001G#\n\u0005\u0019\u0013\"aA%oi\u00061Q-];bYN$\"!\u0013\'\u0011\u0005aQ\u0015BA&\u0013\u0005\u001d\u0011un\u001c7fC:Dq!T\u0004\u0002\u0002\u0003\u0007Q%A\u0002yIE\n1b\u00115bS:LgnZ(qgB\u0011A&C\n\u0003\u0013E\u0003\"\u0001\u0007*\n\u0005M\u0013\"AB!osJ+g\rF\u0001P\u00035!\u0018\r\u001d\u0013fqR,gn]5p]V\u0019qK\u0018.\u0015\u0005a{FCA-\\!\tq\"\fB\u0003!\u0017\t\u0007\u0011\u0005C\u00034\u0017\u0001\u0007A\f\u0005\u0003\u0019kek\u0006C\u0001\u0010_\t\u0015I4B1\u0001\"\u0011\u0015\u00017\u00021\u0001b\u0003\u0015!C\u000f[5t!\ra\u0003!W\u0001\u000fa&\u0004X\rJ3yi\u0016t7/[8o+\r!wm\u001b\u000b\u0003K2$\"A\u001a5\u0011\u0005y9G!B \r\u0005\u0004\t\u0003\"B\u001a\r\u0001\u0004I\u0007\u0003\u0002\r6U\u001a\u0004\"AH6\u0005\u000b\u0001b!\u0019A\u0011\t\u000b\u0001d\u0001\u0019A7\u0011\u00071\u0002!.\u0001\niCND7i\u001c3fI\u0015DH/\u001a8tS>tWC\u00019u)\t\u0019\u0015\u000fC\u0003a\u001b\u0001\u0007!\u000fE\u0002-\u0001M\u0004\"A\b;\u0005\u000b\u0001j!\u0019A\u0011\u0002!\u0015\fX/\u00197tI\u0015DH/\u001a8tS>tWCA<~)\tA(\u0010\u0006\u0002Js\"9QJDA\u0001\u0002\u0004)\u0003\"\u00021\u000f\u0001\u0004Y\bc\u0001\u0017\u0001yB\u0011a$ \u0003\u0006A9\u0011\r!\t"
    )
  ScalaInlineInfo: length = 0x22 (unknown attribute)
   01 01 00 06 00 3F 00 40 01 00 3D 00 3E 01 00 1D
   00 1E 01 00 3A 00 35 01 00 0A 00 2E 01 00 34 00
   35 01
  ScalaSig: length = 0x3 (unknown attribute)
   05 02 00
