Classfile /Users/mw/Projects/slang-braindump/.jar/jar11/assemble/slang-braindump/assemble/content/scala/util/Either$MergeableEither.class
  Last modified May 29, 2022; size 1501 bytes
  SHA-256 checksum 6ccd79863619ff8d00d1be4d32307b44f09f9f47f866012c352e006b14dcfe92
  Compiled from "Either.scala"
public final class scala.util.Either$MergeableEither<A extends java.lang.Object> extends java.lang.Object
  minor version: 0
  major version: 52
  flags: (0x0031) ACC_PUBLIC, ACC_FINAL, ACC_SUPER
  this_class: #2                          // scala/util/Either$MergeableEither
  super_class: #5                         // java/lang/Object
  interfaces: 0, fields: 1, methods: 5, attributes: 5
Constant pool:
   #1 = Utf8               scala/util/Either$MergeableEither
   #2 = Class              #1             // scala/util/Either$MergeableEither
   #3 = Utf8               <A:Ljava/lang/Object;>Ljava/lang/Object;
   #4 = Utf8               java/lang/Object
   #5 = Class              #4             // java/lang/Object
   #6 = Utf8               Either.scala
   #7 = Utf8               scala/util/Either
   #8 = Class              #7             // scala/util/Either
   #9 = Utf8               MergeableEither
  #10 = Utf8               scala/util/Either$MergeableEither$
  #11 = Class              #10            // scala/util/Either$MergeableEither$
  #12 = Utf8               MergeableEither$
  #13 = Utf8               scala$util$Either$MergeableEither$$x
  #14 = Utf8               Lscala/util/Either;
  #15 = Utf8               Lscala/util/Either<TA;TA;>;
  #16 = Utf8               ()Lscala/util/Either;
  #17 = Utf8               ()Lscala/util/Either<TA;TA;>;
  #18 = NameAndType        #13:#14        // scala$util$Either$MergeableEither$$x:Lscala/util/Either;
  #19 = Fieldref           #2.#18         // scala/util/Either$MergeableEither.scala$util$Either$MergeableEither$$x:Lscala/util/Either;
  #20 = Utf8               this
  #21 = Utf8               Lscala/util/Either$MergeableEither;
  #22 = Utf8               merge
  #23 = Utf8               ()Ljava/lang/Object;
  #24 = Utf8               ()TA;
  #25 = Utf8               MODULE$
  #26 = Utf8               Lscala/util/Either$MergeableEither$;
  #27 = NameAndType        #25:#26        // MODULE$:Lscala/util/Either$MergeableEither$;
  #28 = Fieldref           #11.#27        // scala/util/Either$MergeableEither$.MODULE$:Lscala/util/Either$MergeableEither$;
  #29 = NameAndType        #13:#16        // scala$util$Either$MergeableEither$$x:()Lscala/util/Either;
  #30 = Methodref          #2.#29         // scala/util/Either$MergeableEither.scala$util$Either$MergeableEither$$x:()Lscala/util/Either;
  #31 = Utf8               merge$extension
  #32 = Utf8               (Lscala/util/Either;)Ljava/lang/Object;
  #33 = NameAndType        #31:#32        // merge$extension:(Lscala/util/Either;)Ljava/lang/Object;
  #34 = Methodref          #11.#33        // scala/util/Either$MergeableEither$.merge$extension:(Lscala/util/Either;)Ljava/lang/Object;
  #35 = Utf8               hashCode
  #36 = Utf8               ()I
  #37 = NameAndType        #35:#36        // hashCode:()I
  #38 = Methodref          #8.#37         // scala/util/Either.hashCode:()I
  #39 = Utf8               equals
  #40 = Utf8               (Ljava/lang/Object;)Z
  #41 = Utf8               x$1
  #42 = Utf8               equals$extension
  #43 = Utf8               (Lscala/util/Either;Ljava/lang/Object;)Z
  #44 = NameAndType        #42:#43        // equals$extension:(Lscala/util/Either;Ljava/lang/Object;)Z
  #45 = Methodref          #11.#44        // scala/util/Either$MergeableEither$.equals$extension:(Lscala/util/Either;Ljava/lang/Object;)Z
  #46 = Utf8               Ljava/lang/Object;
  #47 = Utf8               <init>
  #48 = Utf8               (Lscala/util/Either;)V
  #49 = Utf8               (Lscala/util/Either<TA;TA;>;)V
  #50 = Utf8               x
  #51 = Utf8               ()V
  #52 = NameAndType        #47:#51        // "<init>":()V
  #53 = Methodref          #5.#52         // java/lang/Object."<init>":()V
  #54 = Utf8               Signature
  #55 = Utf8               Code
  #56 = Utf8               LineNumberTable
  #57 = Utf8               LocalVariableTable
  #58 = Utf8               MethodParameters
  #59 = Utf8               InnerClasses
  #60 = Utf8               SourceFile
  #61 = Utf8               ScalaInlineInfo
  #62 = Utf8               Scala
{
  private final scala.util.Either<A, A> scala$util$Either$MergeableEither$$x;
    descriptor: Lscala/util/Either;
    flags: (0x0012) ACC_PRIVATE, ACC_FINAL
    Signature: #15                          // Lscala/util/Either<TA;TA;>;

  public scala.util.Either<A, A> scala$util$Either$MergeableEither$$x();
    descriptor: ()Lscala/util/Either;
    flags: (0x0001) ACC_PUBLIC
    Code:
      stack=1, locals=1, args_size=1
         0: aload_0
         1: getfield      #19                 // Field scala$util$Either$MergeableEither$$x:Lscala/util/Either;
         4: areturn
      LineNumberTable:
        line 512: 0
      LocalVariableTable:
        Start  Length  Slot  Name   Signature
            0       5     0  this   Lscala/util/Either$MergeableEither;
    Signature: #17                          // ()Lscala/util/Either<TA;TA;>;

  public A merge();
    descriptor: ()Ljava/lang/Object;
    flags: (0x0001) ACC_PUBLIC
    Code:
      stack=2, locals=1, args_size=1
         0: getstatic     #28                 // Field scala/util/Either$MergeableEither$.MODULE$:Lscala/util/Either$MergeableEither$;
         3: aload_0
         4: invokevirtual #30                 // Method scala$util$Either$MergeableEither$$x:()Lscala/util/Either;
         7: invokevirtual #34                 // Method scala/util/Either$MergeableEither$.merge$extension:(Lscala/util/Either;)Ljava/lang/Object;
        10: areturn
      LineNumberTable:
        line 513: 0
      LocalVariableTable:
        Start  Length  Slot  Name   Signature
            0      11     0  this   Lscala/util/Either$MergeableEither;
    Signature: #24                          // ()TA;

  public int hashCode();
    descriptor: ()I
    flags: (0x0001) ACC_PUBLIC
    Code:
      stack=1, locals=1, args_size=1
         0: getstatic     #28                 // Field scala/util/Either$MergeableEither$.MODULE$:Lscala/util/Either$MergeableEither$;
         3: pop
         4: aload_0
         5: invokevirtual #30                 // Method scala$util$Either$MergeableEither$$x:()Lscala/util/Either;
         8: invokevirtual #38                 // Method scala/util/Either.hashCode:()I
        11: ireturn
      LineNumberTable:
        line 512: 0
        line 512: 8
        line 512: 11
      LocalVariableTable:
        Start  Length  Slot  Name   Signature
            0      12     0  this   Lscala/util/Either$MergeableEither;

  public boolean equals(java.lang.Object);
    descriptor: (Ljava/lang/Object;)Z
    flags: (0x0001) ACC_PUBLIC
    Code:
      stack=3, locals=2, args_size=2
         0: getstatic     #28                 // Field scala/util/Either$MergeableEither$.MODULE$:Lscala/util/Either$MergeableEither$;
         3: aload_0
         4: invokevirtual #30                 // Method scala$util$Either$MergeableEither$$x:()Lscala/util/Either;
         7: aload_1
         8: invokevirtual #45                 // Method scala/util/Either$MergeableEither$.equals$extension:(Lscala/util/Either;Ljava/lang/Object;)Z
        11: ireturn
      LineNumberTable:
        line 512: 0
      LocalVariableTable:
        Start  Length  Slot  Name   Signature
            0      12     0  this   Lscala/util/Either$MergeableEither;
            0      12     1   x$1   Ljava/lang/Object;
    MethodParameters:
      Name                           Flags
      x$1                            final

  public scala.util.Either$MergeableEither(scala.util.Either<A, A>);
    descriptor: (Lscala/util/Either;)V
    flags: (0x0001) ACC_PUBLIC
    Code:
      stack=2, locals=2, args_size=2
         0: aload_0
         1: aload_1
         2: putfield      #19                 // Field scala$util$Either$MergeableEither$$x:Lscala/util/Either;
         5: aload_0
         6: invokespecial #53                 // Method java/lang/Object."<init>":()V
         9: return
      LineNumberTable:
        line 512: 0
      LocalVariableTable:
        Start  Length  Slot  Name   Signature
            0      10     0  this   Lscala/util/Either$MergeableEither;
            0      10     1     x   Lscala/util/Either;
    Signature: #49                          // (Lscala/util/Either<TA;TA;>;)V
    MethodParameters:
      Name                           Flags
      x                              final
}
InnerClasses:
  public static final #9= #2 of #8;       // MergeableEither=class scala/util/Either$MergeableEither of class scala/util/Either
  public static #12= #11 of #8;           // MergeableEither$=class scala/util/Either$MergeableEither$ of class scala/util/Either
Signature: #3                           // <A:Ljava/lang/Object;>Ljava/lang/Object;
SourceFile: "Either.scala"
  ScalaInlineInfo: length = 0x1D (unknown attribute)
   01 01 00 05 00 2F 00 30 01 00 27 00 28 01 00 23
   00 24 01 00 16 00 17 01 00 0D 00 10 01
  Scala: length = 0x0 (unknown attribute)

