Classfile /Users/mw/Projects/slang-braindump/.jar/jar11/assemble/slang-braindump/assemble/content/scala/util/Left$.class
  Last modified May 29, 2022; size 1435 bytes
  SHA-256 checksum e30a082479cf84738d3ad8c5ce1437fd0377cddd00b782a1696e49c990a19c9c
  Compiled from "Either.scala"
public final class scala.util.Left$ implements java.io.Serializable
  minor version: 0
  major version: 52
  flags: (0x0031) ACC_PUBLIC, ACC_FINAL, ACC_SUPER
  this_class: #2                          // scala/util/Left$
  super_class: #4                         // java/lang/Object
  interfaces: 1, fields: 1, methods: 6, attributes: 3
Constant pool:
   #1 = Utf8               scala/util/Left$
   #2 = Class              #1             // scala/util/Left$
   #3 = Utf8               java/lang/Object
   #4 = Class              #3             // java/lang/Object
   #5 = Utf8               java/io/Serializable
   #6 = Class              #5             // java/io/Serializable
   #7 = Utf8               Either.scala
   #8 = Utf8               MODULE$
   #9 = Utf8               Lscala/util/Left$;
  #10 = Utf8               <clinit>
  #11 = Utf8               ()V
  #12 = Utf8               <init>
  #13 = NameAndType        #12:#11        // "<init>":()V
  #14 = Methodref          #2.#13         // scala/util/Left$."<init>":()V
  #15 = NameAndType        #8:#9          // MODULE$:Lscala/util/Left$;
  #16 = Fieldref           #2.#15         // scala/util/Left$.MODULE$:Lscala/util/Left$;
  #17 = Utf8               toString
  #18 = Utf8               ()Ljava/lang/String;
  #19 = Utf8               Left
  #20 = String             #19            // Left
  #21 = Utf8               this
  #22 = Utf8               apply
  #23 = Utf8               (Ljava/lang/Object;)Lscala/util/Left;
  #24 = Utf8               <A:Ljava/lang/Object;B:Ljava/lang/Object;>(TA;)Lscala/util/Left<TA;TB;>;
  #25 = Utf8               value
  #26 = Utf8               scala/util/Left
  #27 = Class              #26            // scala/util/Left
  #28 = Utf8               (Ljava/lang/Object;)V
  #29 = NameAndType        #12:#28        // "<init>":(Ljava/lang/Object;)V
  #30 = Methodref          #27.#29        // scala/util/Left."<init>":(Ljava/lang/Object;)V
  #31 = Utf8               Ljava/lang/Object;
  #32 = Utf8               unapply
  #33 = Utf8               (Lscala/util/Left;)Lscala/Option;
  #34 = Utf8               <A:Ljava/lang/Object;B:Ljava/lang/Object;>(Lscala/util/Left<TA;TB;>;)Lscala/Option<TA;>;
  #35 = Utf8               x$0
  #36 = Utf8               scala/None$
  #37 = Class              #36            // scala/None$
  #38 = Utf8               Lscala/None$;
  #39 = NameAndType        #8:#38         // MODULE$:Lscala/None$;
  #40 = Fieldref           #37.#39        // scala/None$.MODULE$:Lscala/None$;
  #41 = Utf8               scala/Some
  #42 = Class              #41            // scala/Some
  #43 = Utf8               ()Ljava/lang/Object;
  #44 = NameAndType        #25:#43        // value:()Ljava/lang/Object;
  #45 = Methodref          #27.#44        // scala/util/Left.value:()Ljava/lang/Object;
  #46 = Methodref          #42.#29        // scala/Some."<init>":(Ljava/lang/Object;)V
  #47 = Utf8               Lscala/util/Left;
  #48 = Utf8               writeReplace
  #49 = Utf8               scala/runtime/ModuleSerializationProxy
  #50 = Class              #49            // scala/runtime/ModuleSerializationProxy
  #51 = Utf8               (Ljava/lang/Class;)V
  #52 = NameAndType        #12:#51        // "<init>":(Ljava/lang/Class;)V
  #53 = Methodref          #50.#52        // scala/runtime/ModuleSerializationProxy."<init>":(Ljava/lang/Class;)V
  #54 = Methodref          #4.#13         // java/lang/Object."<init>":()V
  #55 = Utf8               Code
  #56 = Utf8               LineNumberTable
  #57 = Utf8               LocalVariableTable
  #58 = Utf8               Signature
  #59 = Utf8               MethodParameters
  #60 = Utf8               StackMapTable
  #61 = Utf8               SourceFile
  #62 = Utf8               ScalaInlineInfo
  #63 = Utf8               Scala
{
  public static final scala.util.Left$ MODULE$;
    descriptor: Lscala/util/Left$;
    flags: (0x0019) ACC_PUBLIC, ACC_STATIC, ACC_FINAL

  public static {};
    descriptor: ()V
    flags: (0x0009) ACC_PUBLIC, ACC_STATIC
    Code:
      stack=2, locals=0, args_size=0
         0: new           #2                  // class scala/util/Left$
         3: dup
         4: invokespecial #14                 // Method "<init>":()V
         7: putstatic     #16                 // Field MODULE$:Lscala/util/Left$;
        10: return
      LineNumberTable:
        line 454: 0

  public final java.lang.String toString();
    descriptor: ()Ljava/lang/String;
    flags: (0x0011) ACC_PUBLIC, ACC_FINAL
    Code:
      stack=1, locals=1, args_size=1
         0: ldc           #20                 // String Left
         2: areturn
      LineNumberTable:
        line 454: 0
      LocalVariableTable:
        Start  Length  Slot  Name   Signature
            0       3     0  this   Lscala/util/Left$;

  public <A extends java.lang.Object, B extends java.lang.Object> scala.util.Left<A, B> apply(A);
    descriptor: (Ljava/lang/Object;)Lscala/util/Left;
    flags: (0x0001) ACC_PUBLIC
    Code:
      stack=3, locals=2, args_size=2
         0: new           #27                 // class scala/util/Left
         3: dup
         4: aload_1
         5: invokespecial #30                 // Method scala/util/Left."<init>":(Ljava/lang/Object;)V
         8: areturn
      LineNumberTable:
        line 454: 0
      LocalVariableTable:
        Start  Length  Slot  Name   Signature
            0       9     0  this   Lscala/util/Left$;
            0       9     1 value   Ljava/lang/Object;
    Signature: #24                          // <A:Ljava/lang/Object;B:Ljava/lang/Object;>(TA;)Lscala/util/Left<TA;TB;>;
    MethodParameters:
      Name                           Flags
      value                          final

  public <A extends java.lang.Object, B extends java.lang.Object> scala.Option<A> unapply(scala.util.Left<A, B>);
    descriptor: (Lscala/util/Left;)Lscala/Option;
    flags: (0x0001) ACC_PUBLIC
    Code:
      stack=3, locals=2, args_size=2
         0: aload_1
         1: ifnonnull     8
         4: getstatic     #40                 // Field scala/None$.MODULE$:Lscala/None$;
         7: areturn
         8: new           #42                 // class scala/Some
        11: dup
        12: aload_1
        13: invokevirtual #45                 // Method scala/util/Left.value:()Ljava/lang/Object;
        16: invokespecial #46                 // Method scala/Some."<init>":(Ljava/lang/Object;)V
        19: areturn
      StackMapTable: number_of_entries = 1
        frame_type = 8 /* same */
      LineNumberTable:
        line 454: 0
      LocalVariableTable:
        Start  Length  Slot  Name   Signature
            0      20     0  this   Lscala/util/Left$;
            0      20     1   x$0   Lscala/util/Left;
    Signature: #34                          // <A:Ljava/lang/Object;B:Ljava/lang/Object;>(Lscala/util/Left<TA;TB;>;)Lscala/Option<TA;>;
    MethodParameters:
      Name                           Flags
      x$0                            final

  private java.lang.Object writeReplace();
    descriptor: ()Ljava/lang/Object;
    flags: (0x0002) ACC_PRIVATE
    Code:
      stack=3, locals=1, args_size=1
         0: new           #50                 // class scala/runtime/ModuleSerializationProxy
         3: dup
         4: ldc           #2                  // class scala/util/Left$
         6: invokespecial #53                 // Method scala/runtime/ModuleSerializationProxy."<init>":(Ljava/lang/Class;)V
         9: areturn
      LineNumberTable:
        line 454: 0
      LocalVariableTable:
        Start  Length  Slot  Name   Signature
            0      10     0  this   Lscala/util/Left$;

  private scala.util.Left$();
    descriptor: ()V
    flags: (0x0002) ACC_PRIVATE
    Code:
      stack=1, locals=1, args_size=1
         0: aload_0
         1: invokespecial #54                 // Method java/lang/Object."<init>":()V
         4: return
      LineNumberTable:
        line 454: 0
      LocalVariableTable:
        Start  Length  Slot  Name   Signature
            0       5     0  this   Lscala/util/Left$;
}
SourceFile: "Either.scala"
  ScalaInlineInfo: length = 0x1D (unknown attribute)
   01 01 00 05 00 0C 00 0B 01 00 16 00 17 01 00 11
   00 12 01 00 20 00 21 01 00 30 00 2B 01
  Scala: length = 0x0 (unknown attribute)

