Classfile /Users/mw/Projects/slang-braindump/.jar/jar11/assemble/slang-braindump/assemble/content/scala/util/package$chaining$.class
  Last modified May 29, 2022; size 884 bytes
  SHA-256 checksum f09b776bd39c1057ed45d6483866fbad25833c41f872688396cc104fb12220f5
  Compiled from "package.scala"
public class scala.util.package$chaining$ implements scala.util.ChainingSyntax
  minor version: 0
  major version: 52
  flags: (0x0021) ACC_PUBLIC, ACC_SUPER
  this_class: #2                          // scala/util/package$chaining$
  super_class: #4                         // java/lang/Object
  interfaces: 1, fields: 1, methods: 3, attributes: 4
Constant pool:
   #1 = Utf8               scala/util/package$chaining$
   #2 = Class              #1             // scala/util/package$chaining$
   #3 = Utf8               java/lang/Object
   #4 = Class              #3             // java/lang/Object
   #5 = Utf8               scala/util/ChainingSyntax
   #6 = Class              #5             // scala/util/ChainingSyntax
   #7 = Utf8               package.scala
   #8 = Utf8               scala/util/package
   #9 = Class              #8             // scala/util/package
  #10 = Utf8               chaining$
  #11 = Utf8               MODULE$
  #12 = Utf8               Lscala/util/package$chaining$;
  #13 = Utf8               <clinit>
  #14 = Utf8               ()V
  #15 = Utf8               <init>
  #16 = NameAndType        #15:#14        // "<init>":()V
  #17 = Methodref          #2.#16         // scala/util/package$chaining$."<init>":()V
  #18 = NameAndType        #11:#12        // MODULE$:Lscala/util/package$chaining$;
  #19 = Fieldref           #2.#18         // scala/util/package$chaining$.MODULE$:Lscala/util/package$chaining$;
  #20 = Utf8               scalaUtilChainingOps
  #21 = Utf8               (Ljava/lang/Object;)Ljava/lang/Object;
  #22 = Utf8               <A:Ljava/lang/Object;>(TA;)TA;
  #23 = Utf8               a
  #24 = Utf8               scalaUtilChainingOps$
  #25 = Utf8               (Lscala/util/ChainingSyntax;Ljava/lang/Object;)Ljava/lang/Object;
  #26 = NameAndType        #24:#25        // scalaUtilChainingOps$:(Lscala/util/ChainingSyntax;Ljava/lang/Object;)Ljava/lang/Object;
  #27 = InterfaceMethodref #6.#26         // scala/util/ChainingSyntax.scalaUtilChainingOps$:(Lscala/util/ChainingSyntax;Ljava/lang/Object;)Ljava/lang/Object;
  #28 = Utf8               this
  #29 = Utf8               Ljava/lang/Object;
  #30 = Methodref          #4.#16         // java/lang/Object."<init>":()V
  #31 = Utf8               Code
  #32 = Utf8               LineNumberTable
  #33 = Utf8               LocalVariableTable
  #34 = Utf8               Signature
  #35 = Utf8               MethodParameters
  #36 = Utf8               InnerClasses
  #37 = Utf8               SourceFile
  #38 = Utf8               ScalaInlineInfo
  #39 = Utf8               Scala
{
  public static final scala.util.package$chaining$ MODULE$;
    descriptor: Lscala/util/package$chaining$;
    flags: (0x0019) ACC_PUBLIC, ACC_STATIC, ACC_FINAL

  public static {};
    descriptor: ()V
    flags: (0x0009) ACC_PUBLIC, ACC_STATIC
    Code:
      stack=2, locals=0, args_size=0
         0: new           #2                  // class scala/util/package$chaining$
         3: dup
         4: invokespecial #17                 // Method "<init>":()V
         7: putstatic     #19                 // Field MODULE$:Lscala/util/package$chaining$;
        10: getstatic     #19                 // Field MODULE$:Lscala/util/package$chaining$;
        13: pop
        14: return
      LineNumberTable:
        line 19: 0

  public final <A extends java.lang.Object> A scalaUtilChainingOps(A);
    descriptor: (Ljava/lang/Object;)Ljava/lang/Object;
    flags: (0x0011) ACC_PUBLIC, ACC_FINAL
    Code:
      stack=2, locals=2, args_size=2
         0: aload_0
         1: aload_1
         2: invokestatic  #27                 // InterfaceMethod scala/util/ChainingSyntax.scalaUtilChainingOps$:(Lscala/util/ChainingSyntax;Ljava/lang/Object;)Ljava/lang/Object;
         5: areturn
      LineNumberTable:
        line 19: 0
      LocalVariableTable:
        Start  Length  Slot  Name   Signature
            0       6     0  this   Lscala/util/package$chaining$;
            0       6     1     a   Ljava/lang/Object;
    Signature: #22                          // <A:Ljava/lang/Object;>(TA;)TA;
    MethodParameters:
      Name                           Flags
      a                              final

  public scala.util.package$chaining$();
    descriptor: ()V
    flags: (0x0001) ACC_PUBLIC
    Code:
      stack=1, locals=1, args_size=1
         0: aload_0
         1: invokespecial #30                 // Method java/lang/Object."<init>":()V
         4: return
      LineNumberTable:
        line 19: 0
      LocalVariableTable:
        Start  Length  Slot  Name   Signature
            0       5     0  this   Lscala/util/package$chaining$;
}
InnerClasses:
  public static #10= #2 of #9;            // chaining$=class scala/util/package$chaining$ of class scala/util/package
SourceFile: "package.scala"
  ScalaInlineInfo: length = 0xE (unknown attribute)
   01 01 00 02 00 0F 00 0E 01 00 14 00 15 05
  Scala: length = 0x0 (unknown attribute)

