Classfile /Users/mw/Projects/slang-braindump/.jar/jar11/assemble/slang-braindump/assemble/content/scala/util/PropertiesTrait.class
  Last modified May 29, 2022; size 26464 bytes
  SHA-256 checksum fc2db9f2a153d39ff180d46a8478eaaf2d626687dfc466c46ac03ac9340a0ea6
  Compiled from "Properties.scala"
public interface scala.util.PropertiesTrait
  minor version: 0
  major version: 52
  flags: (0x0601) ACC_PUBLIC, ACC_INTERFACE, ACC_ABSTRACT
  this_class: #2                          // scala/util/PropertiesTrait
  super_class: #4                         // java/lang/Object
  interfaces: 0, fields: 0, methods: 142, attributes: 6
Constant pool:
    #1 = Utf8               scala/util/PropertiesTrait
    #2 = Class              #1            // scala/util/PropertiesTrait
    #3 = Utf8               java/lang/Object
    #4 = Class              #3            // java/lang/Object
    #5 = Utf8               Properties.scala
    #6 = Utf8               Lscala/reflect/ScalaSignature;
    #7 = Utf8               bytes
    #8 = Utf8               \u0006\u0005\u0005eh\u0001C\u001f?!\u0003\r\t\u0001\u0011\"\t\u000b\u001d\u0003A\u0011A%\t\u000b5\u0003a\u0011\u0003(\t\u000bi\u0003a\u0011C.\t\u000f-\u0004!\u0019!C\tY\"AA\u000f\u0001EC\u0002\u0013EQ\u000fC\u0003|\u0001\u0011%A\u0010C\u0004\u0002\n\u0001!\t!a\u0003\t\u000f\u0005]\u0001\u0001\"\u0001\u0002\u001a!9\u0011\u0011\u0005\u0001\u0005\u0002\u0005\r\u0002bBA\u0017\u0001\u0011\u0005\u0011q\u0006\u0005\b\u0003g\u0001A\u0011AA\u001b\u0011\u001d\tI\u0004\u0001C\u0001\u0003wAq!!\u0012\u0001\t\u0003\t9\u0005C\u0004\u0002L\u0001!\t!!\u0014\t\u000f\u0005M\u0003\u0001\"\u0001\u0002V!9\u0011\u0011\f\u0001\u0005\u0002\u0005m\u0003bBA1\u0001\u0011\u0005\u00111\r\u0005\b\u0003O\u0002A\u0011AA5\u0011\u001d\t\u0019\b\u0001C\u0001\u0003kBq!a\u001f\u0001\t\u0003\ti\bC\u0004\u0002\u0002\u0002!\t!a!\t\u0013\u0005\u001d\u0005A1A\u0005\u0002\u0005%\u0005\"CAF\u0001\t\u0007I\u0011AAE\u0011\u0019\ti\t\u0001C\u0001\u001d\"A\u0011q\u0012\u0001C\u0002\u0013\u0005A\u000e\u0003\u0005\u0002\u0012\u0002\u0011\r\u0011\"\u0001O\u0011\u0019\t\u0019\n\u0001C\u0001\u001d\"1\u0011Q\u0013\u0001\u0005\u00029Ca!a&\u0001\t\u0003a\u0007BBAM\u0001\u0011\u0005A\u000e\u0003\u0004\u0002\u001c\u0002!\t\u0001\u001c\u0005\u0007\u0003;\u0003A\u0011\u00017\t\r\u0005}\u0005\u0001\"\u0001m\u0011\u0019\t\t\u000b\u0001C\u0001Y\"1\u00111\u0015\u0001\u0005\u00021Da!!*\u0001\t\u0003a\u0007BBAT\u0001\u0011\u0005A\u000e\u0003\u0004\u0002*\u0002!\t\u0001\u001c\u0005\u0007\u0003W\u0003A\u0011\u00017\t\r\u00055\u0006\u0001\"\u0001m\u0011\u0019\ty\u000b\u0001C\u0001Y\"1\u0011\u0011\u0017\u0001\u0005\u00021Da!a-\u0001\t\u0003a\u0007BBA[\u0001\u0011\u0005A\u000e\u0003\u0004\u00028\u0002!\t\u0001\u001c\u0005\u0007\u0003s\u0003A\u0011\u00017\t\r\u0005m\u0006\u0001\"\u0001m\u0011\u001d\ti\f\u0001C\u0001\u0003\u007fCq!!1\u0001\t\u0003\ty\fC\u0004\u0002D\u0002!\t!a0\t\u0011\u0005\u0015\u0007\u0001\"\u0001A\u0003\u007fC\u0001\"a2\u0001\t\u0003\u0001\u0015q\u0018\u0005\u0007\u0003\u0013\u0004A\u0011\u00017\t\u0011\u0005-\u0007\u0001\"\u0001A\u0003\u001bDa!a5\u0001\t\u0003q\u0005BBAk\u0001\u0011\u0005A\u000e\u0003\u0004\u0002X\u0002!\t\u0001\u001c\u0005\b\u00033\u0004A\u0011AAn\u0011\u001d\tI\u000e\u0001C\u0001\u0003CDq!a;\u0001\t\u0003\tiOA\bQe>\u0004XM\u001d;jKN$&/Y5u\u0015\ty\u0004)\u0001\u0003vi&d\'\"A!\u0002\u000bM\u001c\u0017\r\\1\u0014\u0005\u0001\u0019\u0005C\u0001#F\u001b\u0005\u0001\u0015B\u0001$A\u0005\u0019\te.\u001f*fM\u00061A%\u001b8ji\u0012\u001a\u0001\u0001F\u0001K!\t!5*\u0003\u0002M\u0001\n!QK\\5u\u00031\u0001(o\u001c9DCR,wm\u001c:z+\u0005y\u0005C\u0001)X\u001d\t\tV\u000b\u0005\u0002S\u00016\t1K\u0003\u0002U\u0011\u00061AH]8pizJ!A\u0016!\u0002\rA\u0013X\rZ3g\u0013\tA\u0016L\u0001\u0004TiJLgn\u001a\u0006\u0003-\u0002\u000ba\u0002]5dW*\u000b\'OQ1tK\u0012|e.F\u0001]a\ti&\rE\u0002Q=\u0002L!aX-\u0003\u000b\rc\u0017m]:\u0011\u0005\u0005\u0014G\u0002\u0001\u0003\nG\u000e\t\t\u0011!A\u0003\u0002\u0011\u00141a\u0018\u00133#\t)\u0007\u000e\u0005\u0002EM&\u0011q\r\u0011\u0002\b\u001d>$\b.\u001b8h!\t!\u0015.\u0003\u0002k\u0001\n\u0019\u0011I\\=\u0002\u0019A\u0014x\u000e\u001d$jY\u0016t\u0017-\\3\u0016\u00035\u0004\"A\\:\u000e\u0003=T!\u0001]9\u0002\t1\fgn\u001a\u0006\u0002e\u0006!!.\u0019<b\u0013\tAv.\u0001\u0006tG\u0006d\u0017\r\u0015:paN,\u0012A\u001e\t\u0003ofl\u0011\u0001\u001f\u0006\u0003\u007fEL!A\u001f=\u0003\u0015A\u0013x\u000e]3si&,7/\u0001\brk&,G\u000f\\=ESN\u0004xn]3\u0015\t)k\u0018Q\u0001\u0005\u0007}\u001a!\t\u0019A@\u0002\r\u0005\u001cG/[8o!\u0011!\u0015\u0011\u0001&\n\u0007\u0005\r\u0001I\u0001\u0005=Eft\u0017-\\3?\u0011\u001d\t9A\u0002CA\u0002}\f\u0001\u0002Z5ta>\u001c\u0018\r\\\u0001\naJ|\u0007/S:TKR$B!!\u0004\u0002\u0014A\u0019A)a\u0004\n\u0007\u0005E\u0001IA\u0004C_>dW-\u00198\t\r\u0005Uq\u00011\u0001P\u0003\u0011q\u0017-\\3\u0002\u0017A\u0014x\u000e]%t\'\u0016$Hk\u001c\u000b\u0007\u0003\u001b\tY\"!\b\t\r\u0005U\u0001\u00021\u0001P\u0011\u0019\ty\u0002\u0003a\u0001\u001f\u0006)a/\u00197vK\u0006Q\u0001O]8q\u001fJ,En]3\u0015\u000b5\f)#a\n\t\r\u0005U\u0011\u00021\u0001P\u0011!\tI#\u0003CA\u0002\u0005-\u0012aA1miB!A)!\u0001P\u0003-\u0001(o\u001c9Pe\u0016k\u0007\u000f^=\u0015\u00075\f\t\u0004\u0003\u0004\u0002\u0016)\u0001\raT\u0001\u000baJ|\u0007o\u0014:Ok2dGcA7\u00028!1\u0011QC\u0006A\u0002=\u000b!\u0002\u001d:pa>\u0013hj\u001c8f)\u0011\ti$a\u0011\u0011\t\u0011\u000by$\\\u0005\u0004\u0003\u0003\u0002%AB(qi&|g\u000e\u0003\u0004\u0002\u00161\u0001\raT\u0001\faJ|\u0007o\u0014:GC2\u001cX\r\u0006\u0003\u0002\u000e\u0005%\u0003BBA\u000b\u001b\u0001\u0007q*A\u0004tKR\u0004&o\u001c9\u0015\u000b5\fy%!\u0015\t\r\u0005Ua\u00021\u0001P\u0011\u0019\tyB\u0004a\u0001\u001f\u0006I1\r\\3beB\u0013x\u000e\u001d\u000b\u0004[\u0006]\u0003BBA\u000b\u001f\u0001\u0007q*A\u0005f]Z|%/\u00127tKR)Q.!\u0018\u0002`!1\u0011Q\u0003\tA\u0002=C\u0001\"!\u000b\u0011\t\u0003\u0007\u00111F\u0001\nK:4xJ\u001d(p]\u0016$B!!\u0010\u0002f!1\u0011QC\tA\u0002=\u000b\u0011\"\u001a8w\u001fJ\u001cv.\\3\u0015\r\u0005u\u00121NA7\u0011\u0019\t)B\u0005a\u0001\u001f\"A\u0011\u0011\u0006\n\u0005\u0002\u0004\ty\u0007E\u0003E\u0003\u0003\t\t\b\u0005\u0003E\u0003\u007fy\u0015aD:dC2\f\u0007K]8q\u001fJ,En]3\u0015\u000b=\u000b9(!\u001f\t\r\u0005U1\u00031\u0001P\u0011!\tIc\u0005CA\u0002\u0005-\u0012\u0001E:dC2\f\u0007K]8q\u001fJ,U\u000e\u001d;z)\ry\u0015q\u0010\u0005\u0007\u0003+!\u0002\u0019A(\u0002\u001fM\u001c\u0017\r\\1Qe>\u0004xJ\u001d(p]\u0016$B!!\u001d\u0002\u0006\"1\u0011QC\u000bA\u0002=\u000baB]3mK\u0006\u001cXMV3sg&|g.\u0006\u0002\u0002r\u0005\u0011B-\u001a<fY>\u0004X.\u001a8u-\u0016\u00148/[8o\u0003M1XM]:j_:tU/\u001c2feN#(/\u001b8h\u000351XM]:j_:\u001cFO]5oO\u0006y1m\u001c9ze&<\u0007\u000e^*ue&tw-\u0001\bt_V\u00148-Z#oG>$\u0017N\\4\u0002\u0019M|WO]2f%\u0016\fG-\u001a:\u0002\u001d\u0015t7m\u001c3j]\u001e\u001cFO]5oO\u0006iA.\u001b8f\'\u0016\u0004\u0018M]1u_J\fQB[1wC\u000ec\u0017m]:QCRD\u0017\u0001\u00036bm\u0006Du.\\3\u0002\u0015)\fg/\u0019,f]\u0012|\'/A\u0006kCZ\fg+\u001a:tS>t\u0017A\u00036bm\u00064V.\u00138g_\u0006Q!.\u0019<b-6t\u0015-\\3\u0002\u0019)\fg/\u0019,n-\u0016tGm\u001c:\u0002\u001b)\fg/\u0019,n-\u0016\u00148/[8o\u0003=Q\u0017M^1Ta\u0016\u001cg+\u001a:tS>t\u0017A\u00046bm\u0006\u001c\u0006/Z2WK:$wN]\u0001\rU\u00064\u0018m\u00159fG:\u000bW.Z\u0001\u0007_Nt\u0015-\\3\u0002\u0013M\u001c\u0017\r\\1I_6,\u0017A\u0002;na\u0012K\'/A\u0004vg\u0016\u0014H)\u001b:\u0002\u0011U\u001cXM\u001d%p[\u0016\f\u0001\"^:fe:\u000bW.Z\u0001\u0006SN<\u0016N\\\u000b\u0003\u0003\u001b\tQ![:NC\u000e\fq![:MS:,\b0A\u0004jg\u00063\u0018.\u00198\u0002)\r|Gn\u001c:fI>+H\u000f];u\u000b:\f\'\r\\3e\u0003\u001dQGm\u001b%p[\u0016\f!B^3sg&|gNR8s)\ry\u0015q\u001a\u0005\u0007\u0003#4\u0004\u0019A(\u0002\u000f\r|W.\\1oI\u0006Qa/\u001a:tS>tWj]4\u0002\u0011M\u001c\u0017\r\\1D[\u0012\f\u0011b]2bY\u0006\u001c7)\u001c3\u0002\u001b%\u001c(*\u0019<b\u0003RdU-Y:u)\u0011\ti!!8\t\r\u0005}\'\b1\u0001P\u0003\u001d1XM]:j_:$B!!\u0004\u0002d\"9\u0011q\\\u001eA\u0002\u0005\u0015\bc\u0001#\u0002h&\u0019\u0011\u0011\u001e!\u0003\u0007%sG/\u0001\u0003nC&tGc\u0001&\u0002p\"9\u0011\u0011\u001f\u001fA\u0002\u0005M\u0018\u0001B1sON\u0004B\u0001RA{\u001f&\u0019\u0011q\u001f!\u0003\u000b\u0005\u0013(/Y=
    #9 = Utf8               java/lang/invoke/MethodHandles$Lookup
   #10 = Class              #9            // java/lang/invoke/MethodHandles$Lookup
   #11 = Utf8               java/lang/invoke/MethodHandles
   #12 = Class              #11           // java/lang/invoke/MethodHandles
   #13 = Utf8               Lookup
   #14 = Utf8               scala/Option$WithFilter
   #15 = Class              #14           // scala/Option$WithFilter
   #16 = Utf8               scala/Option
   #17 = Class              #16           // scala/Option
   #18 = Utf8               WithFilter
   #19 = Utf8               scala$util$PropertiesTrait$_setter_$propFilename_$eq
   #20 = Utf8               (Ljava/lang/String;)V
   #21 = Utf8               x$1
   #22 = Utf8               scala$util$PropertiesTrait$_setter_$releaseVersion_$eq
   #23 = Utf8               (Lscala/Option;)V
   #24 = Utf8               (Lscala/Option<Ljava/lang/String;>;)V
   #25 = Utf8               scala$util$PropertiesTrait$_setter_$developmentVersion_$eq
   #26 = Utf8               scala$util$PropertiesTrait$_setter_$versionString_$eq
   #27 = Utf8               scala$util$PropertiesTrait$_setter_$copyrightString_$eq
   #28 = Utf8               propCategory
   #29 = Utf8               ()Ljava/lang/String;
   #30 = Utf8               pickJarBasedOn
   #31 = Utf8               ()Ljava/lang/Class;
   #32 = Utf8               ()Ljava/lang/Class<*>;
   #33 = Utf8               propFilename
   #34 = Utf8               scalaProps$
   #35 = Utf8               (Lscala/util/PropertiesTrait;)Ljava/util/Properties;
   #36 = Utf8               $this
   #37 = Utf8               scalaProps
   #38 = Utf8               ()Ljava/util/Properties;
   #39 = NameAndType        #37:#38       // scalaProps:()Ljava/util/Properties;
   #40 = InterfaceMethodref #2.#39        // scala/util/PropertiesTrait.scalaProps:()Ljava/util/Properties;
   #41 = Utf8               Lscala/util/PropertiesTrait;
   #42 = Utf8               java/io/IOException
   #43 = Class              #42           // java/io/IOException
   #44 = Utf8               java/util/Properties
   #45 = Class              #44           // java/util/Properties
   #46 = Utf8               <init>
   #47 = Utf8               ()V
   #48 = NameAndType        #46:#47       // "<init>":()V
   #49 = Methodref          #45.#48       // java/util/Properties."<init>":()V
   #50 = NameAndType        #30:#31       // pickJarBasedOn:()Ljava/lang/Class;
   #51 = InterfaceMethodref #2.#50        // scala/util/PropertiesTrait.pickJarBasedOn:()Ljava/lang/Class;
   #52 = NameAndType        #33:#29       // propFilename:()Ljava/lang/String;
   #53 = InterfaceMethodref #2.#52        // scala/util/PropertiesTrait.propFilename:()Ljava/lang/String;
   #54 = Utf8               java/lang/Class
   #55 = Class              #54           // java/lang/Class
   #56 = Utf8               getResourceAsStream
   #57 = Utf8               (Ljava/lang/String;)Ljava/io/InputStream;
   #58 = NameAndType        #56:#57       // getResourceAsStream:(Ljava/lang/String;)Ljava/io/InputStream;
   #59 = Methodref          #55.#58       // java/lang/Class.getResourceAsStream:(Ljava/lang/String;)Ljava/io/InputStream;
   #60 = Utf8               load
   #61 = Utf8               (Ljava/io/InputStream;)V
   #62 = NameAndType        #60:#61       // load:(Ljava/io/InputStream;)V
   #63 = Methodref          #45.#62       // java/util/Properties.load:(Ljava/io/InputStream;)V
   #64 = Utf8               java/io/InputStream
   #65 = Class              #64           // java/io/InputStream
   #66 = Utf8               close
   #67 = NameAndType        #66:#47       // close:()V
   #68 = Methodref          #65.#67       // java/io/InputStream.close:()V
   #69 = Utf8               props
   #70 = Utf8               Ljava/util/Properties;
   #71 = Utf8               stream
   #72 = Utf8               Ljava/io/InputStream;
   #73 = Utf8               this
   #74 = Utf8               java/lang/Throwable
   #75 = Class              #74           // java/lang/Throwable
   #76 = Utf8               quietlyDispose
   #77 = Utf8               (Lscala/Function0;Lscala/Function0;)V
   #78 = Utf8               (Lscala/Function0<Lscala/runtime/BoxedUnit;>;Lscala/Function0<Lscala/runtime/BoxedUnit;>;)V
   #79 = Utf8               action
   #80 = Utf8               disposal
   #81 = Utf8               scala/Function0
   #82 = Class              #81           // scala/Function0
   #83 = Utf8               apply$mcV$sp
   #84 = NameAndType        #83:#47       // apply$mcV$sp:()V
   #85 = InterfaceMethodref #82.#84       // scala/Function0.apply$mcV$sp:()V
   #86 = Utf8               Lscala/Function0;
   #87 = Utf8               propIsSet$
   #88 = Utf8               (Lscala/util/PropertiesTrait;Ljava/lang/String;)Z
   #89 = Utf8               name
   #90 = Utf8               propIsSet
   #91 = Utf8               (Ljava/lang/String;)Z
   #92 = NameAndType        #90:#91       // propIsSet:(Ljava/lang/String;)Z
   #93 = InterfaceMethodref #2.#92        // scala/util/PropertiesTrait.propIsSet:(Ljava/lang/String;)Z
   #94 = Utf8               Ljava/lang/String;
   #95 = Utf8               java/lang/System
   #96 = Class              #95           // java/lang/System
   #97 = Utf8               getProperty
   #98 = Utf8               (Ljava/lang/String;)Ljava/lang/String;
   #99 = NameAndType        #97:#98       // getProperty:(Ljava/lang/String;)Ljava/lang/String;
  #100 = Methodref          #96.#99       // java/lang/System.getProperty:(Ljava/lang/String;)Ljava/lang/String;
  #101 = Utf8               propIsSetTo$
  #102 = Utf8               (Lscala/util/PropertiesTrait;Ljava/lang/String;Ljava/lang/String;)Z
  #103 = Utf8               value
  #104 = Utf8               propIsSetTo
  #105 = Utf8               (Ljava/lang/String;Ljava/lang/String;)Z
  #106 = NameAndType        #104:#105     // propIsSetTo:(Ljava/lang/String;Ljava/lang/String;)Z
  #107 = InterfaceMethodref #2.#106       // scala/util/PropertiesTrait.propIsSetTo:(Ljava/lang/String;Ljava/lang/String;)Z
  #108 = Utf8               propOrNull
  #109 = NameAndType        #108:#98      // propOrNull:(Ljava/lang/String;)Ljava/lang/String;
  #110 = InterfaceMethodref #2.#109       // scala/util/PropertiesTrait.propOrNull:(Ljava/lang/String;)Ljava/lang/String;
  #111 = Utf8               equals
  #112 = Utf8               (Ljava/lang/Object;)Z
  #113 = NameAndType        #111:#112     // equals:(Ljava/lang/Object;)Z
  #114 = Methodref          #4.#113       // java/lang/Object.equals:(Ljava/lang/Object;)Z
  #115 = Utf8               java/lang/String
  #116 = Class              #115          // java/lang/String
  #117 = Utf8               propOrElse$
  #118 = Utf8               (Lscala/util/PropertiesTrait;Ljava/lang/String;Lscala/Function0;)Ljava/lang/String;
  #119 = Utf8               alt
  #120 = Utf8               propOrElse
  #121 = Utf8               (Ljava/lang/String;Lscala/Function0;)Ljava/lang/String;
  #122 = NameAndType        #120:#121     // propOrElse:(Ljava/lang/String;Lscala/Function0;)Ljava/lang/String;
  #123 = InterfaceMethodref #2.#122       // scala/util/PropertiesTrait.propOrElse:(Ljava/lang/String;Lscala/Function0;)Ljava/lang/String;
  #124 = Utf8               (Ljava/lang/String;Lscala/Function0<Ljava/lang/String;>;)Ljava/lang/String;
  #125 = Utf8               scala/Option$
  #126 = Class              #125          // scala/Option$
  #127 = Utf8               MODULE$
  #128 = Utf8               Lscala/Option$;
  #129 = NameAndType        #127:#128     // MODULE$:Lscala/Option$;
  #130 = Fieldref           #126.#129     // scala/Option$.MODULE$:Lscala/Option$;
  #131 = Utf8               apply
  #132 = Utf8               (Ljava/lang/Object;)Lscala/Option;
  #133 = NameAndType        #131:#132     // apply:(Ljava/lang/Object;)Lscala/Option;
  #134 = Methodref          #126.#133     // scala/Option$.apply:(Ljava/lang/Object;)Lscala/Option;
  #135 = Utf8               isEmpty
  #136 = Utf8               ()Z
  #137 = NameAndType        #135:#136     // isEmpty:()Z
  #138 = Methodref          #17.#137      // scala/Option.isEmpty:()Z
  #139 = Utf8               ()Ljava/lang/Object;
  #140 = NameAndType        #131:#139     // apply:()Ljava/lang/Object;
  #141 = InterfaceMethodref #82.#140      // scala/Function0.apply:()Ljava/lang/Object;
  #142 = Utf8               get
  #143 = NameAndType        #142:#139     // get:()Ljava/lang/Object;
  #144 = Methodref          #17.#143      // scala/Option.get:()Ljava/lang/Object;
  #145 = Utf8               getOrElse_this
  #146 = Utf8               Lscala/Option;
  #147 = Utf8               propOrEmpty$
  #148 = Utf8               (Lscala/util/PropertiesTrait;Ljava/lang/String;)Ljava/lang/String;
  #149 = Utf8               propOrEmpty
  #150 = NameAndType        #149:#98      // propOrEmpty:(Ljava/lang/String;)Ljava/lang/String;
  #151 = InterfaceMethodref #2.#150       // scala/util/PropertiesTrait.propOrEmpty:(Ljava/lang/String;)Ljava/lang/String;
  #152 = MethodType         #139          //  ()Ljava/lang/Object;
  #153 = Utf8               $anonfun$propOrEmpty$1
  #154 = NameAndType        #153:#29      // $anonfun$propOrEmpty$1:()Ljava/lang/String;
  #155 = InterfaceMethodref #2.#154       // scala/util/PropertiesTrait.$anonfun$propOrEmpty$1:()Ljava/lang/String;
  #156 = MethodHandle       6:#155        // REF_invokeStatic scala/util/PropertiesTrait.$anonfun$propOrEmpty$1:()Ljava/lang/String;
  #157 = MethodType         #29           //  ()Ljava/lang/String;
  #158 = Integer            5
  #159 = Integer            1
  #160 = Utf8               java/lang/invoke/LambdaMetafactory
  #161 = Class              #160          // java/lang/invoke/LambdaMetafactory
  #162 = Utf8               altMetafactory
  #163 = Utf8               (Ljava/lang/invoke/MethodHandles$Lookup;Ljava/lang/String;Ljava/lang/invoke/MethodType;[Ljava/lang/Object;)Ljava/lang/invoke/CallSite;
  #164 = NameAndType        #162:#163     // altMetafactory:(Ljava/lang/invoke/MethodHandles$Lookup;Ljava/lang/String;Ljava/lang/invoke/MethodType;[Ljava/lang/Object;)Ljava/lang/invoke/CallSite;
  #165 = Methodref          #161.#164     // java/lang/invoke/LambdaMetafactory.altMetafactory:(Ljava/lang/invoke/MethodHandles$Lookup;Ljava/lang/String;Ljava/lang/invoke/MethodType;[Ljava/lang/Object;)Ljava/lang/invoke/CallSite;
  #166 = MethodHandle       6:#165        // REF_invokeStatic java/lang/invoke/LambdaMetafactory.altMetafactory:(Ljava/lang/invoke/MethodHandles$Lookup;Ljava/lang/String;Ljava/lang/invoke/MethodType;[Ljava/lang/Object;)Ljava/lang/invoke/CallSite;
  #167 = Utf8               ()Lscala/Function0;
  #168 = NameAndType        #131:#167     // apply:()Lscala/Function0;
  #169 = InvokeDynamic      #0:#168       // #0:apply:()Lscala/Function0;
  #170 = Utf8               propOrNull$
  #171 = Utf8               $anonfun$propOrNull$1
  #172 = Utf8               ()Lscala/runtime/Null$;
  #173 = NameAndType        #171:#172     // $anonfun$propOrNull$1:()Lscala/runtime/Null$;
  #174 = InterfaceMethodref #2.#173       // scala/util/PropertiesTrait.$anonfun$propOrNull$1:()Lscala/runtime/Null$;
  #175 = MethodHandle       6:#174        // REF_invokeStatic scala/util/PropertiesTrait.$anonfun$propOrNull$1:()Lscala/runtime/Null$;
  #176 = MethodType         #172          //  ()Lscala/runtime/Null$;
  #177 = InvokeDynamic      #1:#168       // #1:apply:()Lscala/Function0;
  #178 = Utf8               propOrNone$
  #179 = Utf8               (Lscala/util/PropertiesTrait;Ljava/lang/String;)Lscala/Option;
  #180 = Utf8               propOrNone
  #181 = Utf8               (Ljava/lang/String;)Lscala/Option;
  #182 = NameAndType        #180:#181     // propOrNone:(Ljava/lang/String;)Lscala/Option;
  #183 = InterfaceMethodref #2.#182       // scala/util/PropertiesTrait.propOrNone:(Ljava/lang/String;)Lscala/Option;
  #184 = Utf8               (Ljava/lang/String;)Lscala/Option<Ljava/lang/String;>;
  #185 = Utf8               propOrFalse$
  #186 = Utf8               propOrFalse
  #187 = NameAndType        #186:#91      // propOrFalse:(Ljava/lang/String;)Z
  #188 = InterfaceMethodref #2.#187       // scala/util/PropertiesTrait.propOrFalse:(Ljava/lang/String;)Z
  #189 = Utf8               $anonfun$propOrFalse$1
  #190 = NameAndType        #189:#91      // $anonfun$propOrFalse$1:(Ljava/lang/String;)Z
  #191 = InterfaceMethodref #2.#190       // scala/util/PropertiesTrait.$anonfun$propOrFalse$1:(Ljava/lang/String;)Z
  #192 = Utf8               exists_this
  #193 = Utf8               setProp$
  #194 = Utf8               (Lscala/util/PropertiesTrait;Ljava/lang/String;Ljava/lang/String;)Ljava/lang/String;
  #195 = Utf8               setProp
  #196 = Utf8               (Ljava/lang/String;Ljava/lang/String;)Ljava/lang/String;
  #197 = NameAndType        #195:#196     // setProp:(Ljava/lang/String;Ljava/lang/String;)Ljava/lang/String;
  #198 = InterfaceMethodref #2.#197       // scala/util/PropertiesTrait.setProp:(Ljava/lang/String;Ljava/lang/String;)Ljava/lang/String;
  #199 = Utf8               setProperty
  #200 = NameAndType        #199:#196     // setProperty:(Ljava/lang/String;Ljava/lang/String;)Ljava/lang/String;
  #201 = Methodref          #96.#200      // java/lang/System.setProperty:(Ljava/lang/String;Ljava/lang/String;)Ljava/lang/String;
  #202 = Utf8               clearProp$
  #203 = Utf8               clearProp
  #204 = NameAndType        #203:#98      // clearProp:(Ljava/lang/String;)Ljava/lang/String;
  #205 = InterfaceMethodref #2.#204       // scala/util/PropertiesTrait.clearProp:(Ljava/lang/String;)Ljava/lang/String;
  #206 = Utf8               clearProperty
  #207 = NameAndType        #206:#98      // clearProperty:(Ljava/lang/String;)Ljava/lang/String;
  #208 = Methodref          #96.#207      // java/lang/System.clearProperty:(Ljava/lang/String;)Ljava/lang/String;
  #209 = Utf8               envOrElse$
  #210 = Utf8               envOrElse
  #211 = NameAndType        #210:#121     // envOrElse:(Ljava/lang/String;Lscala/Function0;)Ljava/lang/String;
  #212 = InterfaceMethodref #2.#211       // scala/util/PropertiesTrait.envOrElse:(Ljava/lang/String;Lscala/Function0;)Ljava/lang/String;
  #213 = Utf8               getenv
  #214 = NameAndType        #213:#98      // getenv:(Ljava/lang/String;)Ljava/lang/String;
  #215 = Methodref          #96.#214      // java/lang/System.getenv:(Ljava/lang/String;)Ljava/lang/String;
  #216 = Utf8               envOrNone$
  #217 = Utf8               envOrNone
  #218 = NameAndType        #217:#181     // envOrNone:(Ljava/lang/String;)Lscala/Option;
  #219 = InterfaceMethodref #2.#218       // scala/util/PropertiesTrait.envOrNone:(Ljava/lang/String;)Lscala/Option;
  #220 = Utf8               envOrSome$
  #221 = Utf8               (Lscala/util/PropertiesTrait;Ljava/lang/String;Lscala/Function0;)Lscala/Option;
  #222 = Utf8               envOrSome
  #223 = Utf8               (Ljava/lang/String;Lscala/Function0;)Lscala/Option;
  #224 = NameAndType        #222:#223     // envOrSome:(Ljava/lang/String;Lscala/Function0;)Lscala/Option;
  #225 = InterfaceMethodref #2.#224       // scala/util/PropertiesTrait.envOrSome:(Ljava/lang/String;Lscala/Function0;)Lscala/Option;
  #226 = Utf8               (Ljava/lang/String;Lscala/Function0<Lscala/Option<Ljava/lang/String;>;>;)Lscala/Option<Ljava/lang/String;>;
  #227 = Utf8               orElse_this
  #228 = Utf8               scalaPropOrElse$
  #229 = Utf8               scalaPropOrElse
  #230 = NameAndType        #229:#121     // scalaPropOrElse:(Ljava/lang/String;Lscala/Function0;)Ljava/lang/String;
  #231 = InterfaceMethodref #2.#230       // scala/util/PropertiesTrait.scalaPropOrElse:(Ljava/lang/String;Lscala/Function0;)Ljava/lang/String;
  #232 = Utf8               scalaPropOrNone
  #233 = NameAndType        #232:#181     // scalaPropOrNone:(Ljava/lang/String;)Lscala/Option;
  #234 = InterfaceMethodref #2.#233       // scala/util/PropertiesTrait.scalaPropOrNone:(Ljava/lang/String;)Lscala/Option;
  #235 = Utf8               scalaPropOrEmpty$
  #236 = Utf8               scalaPropOrEmpty
  #237 = NameAndType        #236:#98      // scalaPropOrEmpty:(Ljava/lang/String;)Ljava/lang/String;
  #238 = InterfaceMethodref #2.#237       // scala/util/PropertiesTrait.scalaPropOrEmpty:(Ljava/lang/String;)Ljava/lang/String;
  #239 = Utf8               $anonfun$scalaPropOrEmpty$1
  #240 = NameAndType        #239:#29      // $anonfun$scalaPropOrEmpty$1:()Ljava/lang/String;
  #241 = InterfaceMethodref #2.#240       // scala/util/PropertiesTrait.$anonfun$scalaPropOrEmpty$1:()Ljava/lang/String;
  #242 = MethodHandle       6:#241        // REF_invokeStatic scala/util/PropertiesTrait.$anonfun$scalaPropOrEmpty$1:()Ljava/lang/String;
  #243 = InvokeDynamic      #2:#168       // #2:apply:()Lscala/Function0;
  #244 = Utf8               scalaPropOrNone$
  #245 = Methodref          #45.#99       // java/util/Properties.getProperty:(Ljava/lang/String;)Ljava/lang/String;
  #246 = Utf8               $anonfun$scalaPropOrNone$1
  #247 = NameAndType        #246:#179     // $anonfun$scalaPropOrNone$1:(Lscala/util/PropertiesTrait;Ljava/lang/String;)Lscala/Option;
  #248 = InterfaceMethodref #2.#247       // scala/util/PropertiesTrait.$anonfun$scalaPropOrNone$1:(Lscala/util/PropertiesTrait;Ljava/lang/String;)Lscala/Option;
  #249 = Utf8               releaseVersion
  #250 = Utf8               ()Lscala/Option;
  #251 = Utf8               ()Lscala/Option<Ljava/lang/String;>;
  #252 = Utf8               developmentVersion
  #253 = Utf8               versionNumberString$
  #254 = Utf8               (Lscala/util/PropertiesTrait;)Ljava/lang/String;
  #255 = Utf8               versionNumberString
  #256 = NameAndType        #255:#29      // versionNumberString:()Ljava/lang/String;
  #257 = InterfaceMethodref #2.#256       // scala/util/PropertiesTrait.versionNumberString:()Ljava/lang/String;
  #258 = Utf8               version.number
  #259 = String             #258          // version.number
  #260 = Utf8               versionString
  #261 = Utf8               copyrightString
  #262 = Utf8               sourceEncoding$
  #263 = Utf8               sourceEncoding
  #264 = NameAndType        #263:#29      // sourceEncoding:()Ljava/lang/String;
  #265 = InterfaceMethodref #2.#264       // scala/util/PropertiesTrait.sourceEncoding:()Ljava/lang/String;
  #266 = Utf8               file.encoding
  #267 = String             #266          // file.encoding
  #268 = Utf8               $anonfun$sourceEncoding$1
  #269 = NameAndType        #268:#29      // $anonfun$sourceEncoding$1:()Ljava/lang/String;
  #270 = InterfaceMethodref #2.#269       // scala/util/PropertiesTrait.$anonfun$sourceEncoding$1:()Ljava/lang/String;
  #271 = MethodHandle       6:#270        // REF_invokeStatic scala/util/PropertiesTrait.$anonfun$sourceEncoding$1:()Ljava/lang/String;
  #272 = InvokeDynamic      #3:#168       // #3:apply:()Lscala/Function0;
  #273 = Utf8               sourceReader$
  #274 = Utf8               sourceReader
  #275 = NameAndType        #274:#29      // sourceReader:()Ljava/lang/String;
  #276 = InterfaceMethodref #2.#275       // scala/util/PropertiesTrait.sourceReader:()Ljava/lang/String;
  #277 = Utf8               source.reader
  #278 = String             #277          // source.reader
  #279 = Utf8               $anonfun$sourceReader$1
  #280 = NameAndType        #279:#29      // $anonfun$sourceReader$1:()Ljava/lang/String;
  #281 = InterfaceMethodref #2.#280       // scala/util/PropertiesTrait.$anonfun$sourceReader$1:()Ljava/lang/String;
  #282 = MethodHandle       6:#281        // REF_invokeStatic scala/util/PropertiesTrait.$anonfun$sourceReader$1:()Ljava/lang/String;
  #283 = InvokeDynamic      #4:#168       // #4:apply:()Lscala/Function0;
  #284 = Utf8               encodingString$
  #285 = Utf8               encodingString
  #286 = NameAndType        #285:#29      // encodingString:()Ljava/lang/String;
  #287 = InterfaceMethodref #2.#286       // scala/util/PropertiesTrait.encodingString:()Ljava/lang/String;
  #288 = Utf8               $anonfun$encodingString$1
  #289 = NameAndType        #288:#29      // $anonfun$encodingString$1:()Ljava/lang/String;
  #290 = InterfaceMethodref #2.#289       // scala/util/PropertiesTrait.$anonfun$encodingString$1:()Ljava/lang/String;
  #291 = MethodHandle       6:#290        // REF_invokeStatic scala/util/PropertiesTrait.$anonfun$encodingString$1:()Ljava/lang/String;
  #292 = InvokeDynamic      #5:#168       // #5:apply:()Lscala/Function0;
  #293 = Utf8               lineSeparator$
  #294 = Utf8               lineSeparator
  #295 = NameAndType        #294:#29      // lineSeparator:()Ljava/lang/String;
  #296 = InterfaceMethodref #2.#295       // scala/util/PropertiesTrait.lineSeparator:()Ljava/lang/String;
  #297 = Methodref          #96.#295      // java/lang/System.lineSeparator:()Ljava/lang/String;
  #298 = Utf8               javaClassPath$
  #299 = Utf8               javaClassPath
  #300 = NameAndType        #299:#29      // javaClassPath:()Ljava/lang/String;
  #301 = InterfaceMethodref #2.#300       // scala/util/PropertiesTrait.javaClassPath:()Ljava/lang/String;
  #302 = Utf8               java.class.path
  #303 = String             #302          // java.class.path
  #304 = Utf8               javaHome$
  #305 = Utf8               javaHome
  #306 = NameAndType        #305:#29      // javaHome:()Ljava/lang/String;
  #307 = InterfaceMethodref #2.#306       // scala/util/PropertiesTrait.javaHome:()Ljava/lang/String;
  #308 = Utf8               java.home
  #309 = String             #308          // java.home
  #310 = Utf8               javaVendor$
  #311 = Utf8               javaVendor
  #312 = NameAndType        #311:#29      // javaVendor:()Ljava/lang/String;
  #313 = InterfaceMethodref #2.#312       // scala/util/PropertiesTrait.javaVendor:()Ljava/lang/String;
  #314 = Utf8               java.vendor
  #315 = String             #314          // java.vendor
  #316 = Utf8               javaVersion$
  #317 = Utf8               javaVersion
  #318 = NameAndType        #317:#29      // javaVersion:()Ljava/lang/String;
  #319 = InterfaceMethodref #2.#318       // scala/util/PropertiesTrait.javaVersion:()Ljava/lang/String;
  #320 = Utf8               java.version
  #321 = String             #320          // java.version
  #322 = Utf8               javaVmInfo$
  #323 = Utf8               javaVmInfo
  #324 = NameAndType        #323:#29      // javaVmInfo:()Ljava/lang/String;
  #325 = InterfaceMethodref #2.#324       // scala/util/PropertiesTrait.javaVmInfo:()Ljava/lang/String;
  #326 = Utf8               java.vm.info
  #327 = String             #326          // java.vm.info
  #328 = Utf8               javaVmName$
  #329 = Utf8               javaVmName
  #330 = NameAndType        #329:#29      // javaVmName:()Ljava/lang/String;
  #331 = InterfaceMethodref #2.#330       // scala/util/PropertiesTrait.javaVmName:()Ljava/lang/String;
  #332 = Utf8               java.vm.name
  #333 = String             #332          // java.vm.name
  #334 = Utf8               javaVmVendor$
  #335 = Utf8               javaVmVendor
  #336 = NameAndType        #335:#29      // javaVmVendor:()Ljava/lang/String;
  #337 = InterfaceMethodref #2.#336       // scala/util/PropertiesTrait.javaVmVendor:()Ljava/lang/String;
  #338 = Utf8               java.vm.vendor
  #339 = String             #338          // java.vm.vendor
  #340 = Utf8               javaVmVersion$
  #341 = Utf8               javaVmVersion
  #342 = NameAndType        #341:#29      // javaVmVersion:()Ljava/lang/String;
  #343 = InterfaceMethodref #2.#342       // scala/util/PropertiesTrait.javaVmVersion:()Ljava/lang/String;
  #344 = Utf8               java.vm.version
  #345 = String             #344          // java.vm.version
  #346 = Utf8               javaSpecVersion$
  #347 = Utf8               javaSpecVersion
  #348 = NameAndType        #347:#29      // javaSpecVersion:()Ljava/lang/String;
  #349 = InterfaceMethodref #2.#348       // scala/util/PropertiesTrait.javaSpecVersion:()Ljava/lang/String;
  #350 = Utf8               java.specification.version
  #351 = String             #350          // java.specification.version
  #352 = Utf8               javaSpecVendor$
  #353 = Utf8               javaSpecVendor
  #354 = NameAndType        #353:#29      // javaSpecVendor:()Ljava/lang/String;
  #355 = InterfaceMethodref #2.#354       // scala/util/PropertiesTrait.javaSpecVendor:()Ljava/lang/String;
  #356 = Utf8               java.specification.vendor
  #357 = String             #356          // java.specification.vendor
  #358 = Utf8               javaSpecName$
  #359 = Utf8               javaSpecName
  #360 = NameAndType        #359:#29      // javaSpecName:()Ljava/lang/String;
  #361 = InterfaceMethodref #2.#360       // scala/util/PropertiesTrait.javaSpecName:()Ljava/lang/String;
  #362 = Utf8               java.specification.name
  #363 = String             #362          // java.specification.name
  #364 = Utf8               osName$
  #365 = Utf8               osName
  #366 = NameAndType        #365:#29      // osName:()Ljava/lang/String;
  #367 = InterfaceMethodref #2.#366       // scala/util/PropertiesTrait.osName:()Ljava/lang/String;
  #368 = Utf8               os.name
  #369 = String             #368          // os.name
  #370 = Utf8               scalaHome$
  #371 = Utf8               scalaHome
  #372 = NameAndType        #371:#29      // scalaHome:()Ljava/lang/String;
  #373 = InterfaceMethodref #2.#372       // scala/util/PropertiesTrait.scalaHome:()Ljava/lang/String;
  #374 = Utf8               scala.home
  #375 = String             #374          // scala.home
  #376 = Utf8               tmpDir$
  #377 = Utf8               tmpDir
  #378 = NameAndType        #377:#29      // tmpDir:()Ljava/lang/String;
  #379 = InterfaceMethodref #2.#378       // scala/util/PropertiesTrait.tmpDir:()Ljava/lang/String;
  #380 = Utf8               java.io.tmpdir
  #381 = String             #380          // java.io.tmpdir
  #382 = Utf8               userDir$
  #383 = Utf8               userDir
  #384 = NameAndType        #383:#29      // userDir:()Ljava/lang/String;
  #385 = InterfaceMethodref #2.#384       // scala/util/PropertiesTrait.userDir:()Ljava/lang/String;
  #386 = Utf8               user.dir
  #387 = String             #386          // user.dir
  #388 = Utf8               userHome$
  #389 = Utf8               userHome
  #390 = NameAndType        #389:#29      // userHome:()Ljava/lang/String;
  #391 = InterfaceMethodref #2.#390       // scala/util/PropertiesTrait.userHome:()Ljava/lang/String;
  #392 = Utf8               user.home
  #393 = String             #392          // user.home
  #394 = Utf8               userName$
  #395 = Utf8               userName
  #396 = NameAndType        #395:#29      // userName:()Ljava/lang/String;
  #397 = InterfaceMethodref #2.#396       // scala/util/PropertiesTrait.userName:()Ljava/lang/String;
  #398 = Utf8               user.name
  #399 = String             #398          // user.name
  #400 = Utf8               isWin$
  #401 = Utf8               (Lscala/util/PropertiesTrait;)Z
  #402 = Utf8               isWin
  #403 = NameAndType        #402:#136     // isWin:()Z
  #404 = InterfaceMethodref #2.#403       // scala/util/PropertiesTrait.isWin:()Z
  #405 = Utf8               Windows
  #406 = String             #405          // Windows
  #407 = Utf8               startsWith
  #408 = NameAndType        #407:#91      // startsWith:(Ljava/lang/String;)Z
  #409 = Methodref          #116.#408     // java/lang/String.startsWith:(Ljava/lang/String;)Z
  #410 = Utf8               isMac$
  #411 = Utf8               isMac
  #412 = NameAndType        #411:#136     // isMac:()Z
  #413 = InterfaceMethodref #2.#412       // scala/util/PropertiesTrait.isMac:()Z
  #414 = Utf8               Mac OS X
  #415 = String             #414          // Mac OS X
  #416 = Utf8               isLinux$
  #417 = Utf8               isLinux
  #418 = NameAndType        #417:#136     // isLinux:()Z
  #419 = InterfaceMethodref #2.#418       // scala/util/PropertiesTrait.isLinux:()Z
  #420 = Utf8               Linux
  #421 = String             #420          // Linux
  #422 = Utf8               isAvian$
  #423 = Utf8               isAvian
  #424 = NameAndType        #423:#136     // isAvian:()Z
  #425 = InterfaceMethodref #2.#424       // scala/util/PropertiesTrait.isAvian:()Z
  #426 = Utf8               Avian
  #427 = String             #426          // Avian
  #428 = Utf8               contains
  #429 = Utf8               (Ljava/lang/CharSequence;)Z
  #430 = NameAndType        #428:#429     // contains:(Ljava/lang/CharSequence;)Z
  #431 = Methodref          #116.#430     // java/lang/String.contains:(Ljava/lang/CharSequence;)Z
  #432 = Utf8               coloredOutputEnabled$
  #433 = Utf8               coloredOutputEnabled
  #434 = NameAndType        #433:#136     // coloredOutputEnabled:()Z
  #435 = InterfaceMethodref #2.#434       // scala/util/PropertiesTrait.coloredOutputEnabled:()Z
  #436 = Utf8               scala.color
  #437 = String             #436          // scala.color
  #438 = Utf8               $anonfun$coloredOutputEnabled$1
  #439 = NameAndType        #438:#29      // $anonfun$coloredOutputEnabled$1:()Ljava/lang/String;
  #440 = InterfaceMethodref #2.#439       // scala/util/PropertiesTrait.$anonfun$coloredOutputEnabled$1:()Ljava/lang/String;
  #441 = MethodHandle       6:#440        // REF_invokeStatic scala/util/PropertiesTrait.$anonfun$coloredOutputEnabled$1:()Ljava/lang/String;
  #442 = InvokeDynamic      #6:#168       // #6:apply:()Lscala/Function0;
  #443 = Utf8               hashCode
  #444 = Utf8               ()I
  #445 = NameAndType        #443:#444     // hashCode:()I
  #446 = Methodref          #116.#445     // java/lang/String.hashCode:()I
  #447 = Utf8               auto
  #448 = String             #447          // auto
  #449 = Methodref          #116.#113     // java/lang/String.equals:(Ljava/lang/Object;)Z
  #450 = Utf8               console
  #451 = Utf8               ()Ljava/io/Console;
  #452 = NameAndType        #450:#451     // console:()Ljava/io/Console;
  #453 = Methodref          #96.#452      // java/lang/System.console:()Ljava/io/Console;
  #454 = Utf8
  #455 = String             #454          //
  #456 = Utf8               true
  #457 = String             #456          // true
  #458 = Utf8               equalsIgnoreCase
  #459 = NameAndType        #458:#91      // equalsIgnoreCase:(Ljava/lang/String;)Z
  #460 = Methodref          #116.#459     // java/lang/String.equalsIgnoreCase:(Ljava/lang/String;)Z
  #461 = Utf8               jdkHome$
  #462 = Utf8               jdkHome
  #463 = NameAndType        #462:#29      // jdkHome:()Ljava/lang/String;
  #464 = InterfaceMethodref #2.#463       // scala/util/PropertiesTrait.jdkHome:()Ljava/lang/String;
  #465 = Utf8               JDK_HOME
  #466 = String             #465          // JDK_HOME
  #467 = Utf8               $anonfun$jdkHome$1
  #468 = NameAndType        #467:#254     // $anonfun$jdkHome$1:(Lscala/util/PropertiesTrait;)Ljava/lang/String;
  #469 = InterfaceMethodref #2.#468       // scala/util/PropertiesTrait.$anonfun$jdkHome$1:(Lscala/util/PropertiesTrait;)Ljava/lang/String;
  #470 = MethodHandle       6:#469        // REF_invokeStatic scala/util/PropertiesTrait.$anonfun$jdkHome$1:(Lscala/util/PropertiesTrait;)Ljava/lang/String;
  #471 = Utf8               (Lscala/util/PropertiesTrait;)Lscala/Function0;
  #472 = NameAndType        #131:#471     // apply:(Lscala/util/PropertiesTrait;)Lscala/Function0;
  #473 = InvokeDynamic      #7:#472       // #7:apply:(Lscala/util/PropertiesTrait;)Lscala/Function0;
  #474 = Utf8               versionFor$
  #475 = Utf8               command
  #476 = Utf8               versionFor
  #477 = NameAndType        #476:#98      // versionFor:(Ljava/lang/String;)Ljava/lang/String;
  #478 = InterfaceMethodref #2.#477       // scala/util/PropertiesTrait.versionFor:(Ljava/lang/String;)Ljava/lang/String;
  #479 = Utf8               java/lang/StringBuilder
  #480 = Class              #479          // java/lang/StringBuilder
  #481 = Integer            11
  #482 = Utf8               (I)V
  #483 = NameAndType        #46:#482      // "<init>":(I)V
  #484 = Methodref          #480.#483     // java/lang/StringBuilder."<init>":(I)V
  #485 = Utf8               Scala
  #486 = String             #485          // Scala
  #487 = Utf8               append
  #488 = Utf8               (Ljava/lang/String;)Ljava/lang/StringBuilder;
  #489 = NameAndType        #487:#488     // append:(Ljava/lang/String;)Ljava/lang/StringBuilder;
  #490 = Methodref          #480.#489     // java/lang/StringBuilder.append:(Ljava/lang/String;)Ljava/lang/StringBuilder;
  #491 = Utf8
  #492 = String             #491          //
  #493 = NameAndType        #260:#29      // versionString:()Ljava/lang/String;
  #494 = InterfaceMethodref #2.#493       // scala/util/PropertiesTrait.versionString:()Ljava/lang/String;
  #495 = Utf8                --
  #496 = String             #495          //  --
  #497 = NameAndType        #261:#29      // copyrightString:()Ljava/lang/String;
  #498 = InterfaceMethodref #2.#497       // scala/util/PropertiesTrait.copyrightString:()Ljava/lang/String;
  #499 = Utf8               toString
  #500 = NameAndType        #499:#29      // toString:()Ljava/lang/String;
  #501 = Methodref          #480.#500     // java/lang/StringBuilder.toString:()Ljava/lang/String;
  #502 = Utf8               versionMsg$
  #503 = Utf8               versionMsg
  #504 = NameAndType        #503:#29      // versionMsg:()Ljava/lang/String;
  #505 = InterfaceMethodref #2.#504       // scala/util/PropertiesTrait.versionMsg:()Ljava/lang/String;
  #506 = NameAndType        #28:#29       // propCategory:()Ljava/lang/String;
  #507 = InterfaceMethodref #2.#506       // scala/util/PropertiesTrait.propCategory:()Ljava/lang/String;
  #508 = Utf8               scalaCmd$
  #509 = Utf8               scalaCmd
  #510 = NameAndType        #509:#29      // scalaCmd:()Ljava/lang/String;
  #511 = InterfaceMethodref #2.#510       // scala/util/PropertiesTrait.scalaCmd:()Ljava/lang/String;
  #512 = Utf8               scala.bat
  #513 = String             #512          // scala.bat
  #514 = Utf8               scala
  #515 = String             #514          // scala
  #516 = Utf8               scalacCmd$
  #517 = Utf8               scalacCmd
  #518 = NameAndType        #517:#29      // scalacCmd:()Ljava/lang/String;
  #519 = InterfaceMethodref #2.#518       // scala/util/PropertiesTrait.scalacCmd:()Ljava/lang/String;
  #520 = Utf8               scalac.bat
  #521 = String             #520          // scalac.bat
  #522 = Utf8               scalac
  #523 = String             #522          // scalac
  #524 = Utf8               isJavaAtLeast$
  #525 = Utf8               version
  #526 = Utf8               isJavaAtLeast
  #527 = NameAndType        #526:#91      // isJavaAtLeast:(Ljava/lang/String;)Z
  #528 = InterfaceMethodref #2.#527       // scala/util/PropertiesTrait.isJavaAtLeast:(Ljava/lang/String;)Z
  #529 = Utf8               compareVersions$1
  #530 = Utf8               (Ljava/lang/String;Ljava/lang/String;I)I
  #531 = NameAndType        #529:#530     // compareVersions$1:(Ljava/lang/String;Ljava/lang/String;I)I
  #532 = InterfaceMethodref #2.#531       // scala/util/PropertiesTrait.compareVersions$1:(Ljava/lang/String;Ljava/lang/String;I)I
  #533 = Utf8               java/lang/NumberFormatException
  #534 = Class              #533          // java/lang/NumberFormatException
  #535 = Integer            15
  #536 = Utf8               Not a version:
  #537 = String             #536          // Not a version:
  #538 = NameAndType        #46:#20       // "<init>":(Ljava/lang/String;)V
  #539 = Methodref          #534.#538     // java/lang/NumberFormatException."<init>":(Ljava/lang/String;)V
  #540 = Utf8               (Lscala/util/PropertiesTrait;I)Z
  #541 = Utf8               (I)Z
  #542 = NameAndType        #526:#541     // isJavaAtLeast:(I)Z
  #543 = InterfaceMethodref #2.#542       // scala/util/PropertiesTrait.isJavaAtLeast:(I)Z
  #544 = Utf8               I
  #545 = Utf8               scala/math/package$
  #546 = Class              #545          // scala/math/package$
  #547 = Utf8               Lscala/math/package$;
  #548 = NameAndType        #127:#547     // MODULE$:Lscala/math/package$;
  #549 = Fieldref           #546.#548     // scala/math/package$.MODULE$:Lscala/math/package$;
  #550 = Utf8               java/lang/Math
  #551 = Class              #550          // java/lang/Math
  #552 = Utf8               max
  #553 = Utf8               (II)I
  #554 = NameAndType        #552:#553     // max:(II)I
  #555 = Methodref          #551.#554     // java/lang/Math.max:(II)I
  #556 = Utf8               java/lang/Integer
  #557 = Class              #556          // java/lang/Integer
  #558 = Utf8               (I)Ljava/lang/String;
  #559 = NameAndType        #499:#558     // toString:(I)Ljava/lang/String;
  #560 = Methodref          #557.#559     // java/lang/Integer.toString:(I)Ljava/lang/String;
  #561 = Utf8               max_y
  #562 = Utf8               main$
  #563 = Utf8               (Lscala/util/PropertiesTrait;[Ljava/lang/String;)V
  #564 = Utf8               args
  #565 = Utf8               main
  #566 = Utf8               ([Ljava/lang/String;)V
  #567 = NameAndType        #565:#566     // main:([Ljava/lang/String;)V
  #568 = InterfaceMethodref #2.#567       // scala/util/PropertiesTrait.main:([Ljava/lang/String;)V
  #569 = Utf8               [Ljava/lang/String;
  #570 = Utf8               java/io/PrintWriter
  #571 = Class              #570          // java/io/PrintWriter
  #572 = Utf8               scala/Console$
  #573 = Class              #572          // scala/Console$
  #574 = Utf8               Lscala/Console$;
  #575 = NameAndType        #127:#574     // MODULE$:Lscala/Console$;
  #576 = Fieldref           #573.#575     // scala/Console$.MODULE$:Lscala/Console$;
  #577 = Utf8               err
  #578 = Utf8               ()Ljava/io/PrintStream;
  #579 = NameAndType        #577:#578     // err:()Ljava/io/PrintStream;
  #580 = Methodref          #573.#579     // scala/Console$.err:()Ljava/io/PrintStream;
  #581 = Utf8               (Ljava/io/OutputStream;Z)V
  #582 = NameAndType        #46:#581      // "<init>":(Ljava/io/OutputStream;Z)V
  #583 = Methodref          #571.#582     // java/io/PrintWriter."<init>":(Ljava/io/OutputStream;Z)V
  #584 = Utf8               println
  #585 = NameAndType        #584:#20      // println:(Ljava/lang/String;)V
  #586 = Methodref          #571.#585     // java/io/PrintWriter.println:(Ljava/lang/String;)V
  #587 = Utf8               $anonfun$scalaProps$1
  #588 = Utf8               (Ljava/util/Properties;Ljava/io/InputStream;)V
  #589 = Utf8               props$1
  #590 = Utf8               stream$1
  #591 = Utf8               $anonfun$scalaProps$2
  #592 = Utf8               x
  #593 = Utf8               scala/package$
  #594 = Class              #593          // scala/package$
  #595 = Utf8               Lscala/package$;
  #596 = NameAndType        #127:#595     // MODULE$:Lscala/package$;
  #597 = Fieldref           #594.#596     // scala/package$.MODULE$:Lscala/package$;
  #598 = Utf8               List
  #599 = Utf8               ()Lscala/collection/immutable/List$;
  #600 = NameAndType        #598:#599     // List:()Lscala/collection/immutable/List$;
  #601 = Methodref          #594.#600     // scala/package$.List:()Lscala/collection/immutable/List$;
  #602 = Utf8               scala/runtime/ScalaRunTime$
  #603 = Class              #602          // scala/runtime/ScalaRunTime$
  #604 = Utf8               Lscala/runtime/ScalaRunTime$;
  #605 = NameAndType        #127:#604     // MODULE$:Lscala/runtime/ScalaRunTime$;
  #606 = Fieldref           #603.#605     // scala/runtime/ScalaRunTime$.MODULE$:Lscala/runtime/ScalaRunTime$;
  #607 = Utf8               yes
  #608 = String             #607          // yes
  #609 = Utf8               on
  #610 = String             #609          // on
  #611 = Utf8               wrapRefArray
  #612 = Utf8               ([Ljava/lang/Object;)Lscala/collection/immutable/ArraySeq;
  #613 = NameAndType        #611:#612     // wrapRefArray:([Ljava/lang/Object;)Lscala/collection/immutable/ArraySeq;
  #614 = Methodref          #603.#613     // scala/runtime/ScalaRunTime$.wrapRefArray:([Ljava/lang/Object;)Lscala/collection/immutable/ArraySeq;
  #615 = Utf8               scala/collection/immutable/Nil$
  #616 = Class              #615          // scala/collection/immutable/Nil$
  #617 = Utf8               Lscala/collection/immutable/Nil$;
  #618 = NameAndType        #127:#617     // MODULE$:Lscala/collection/immutable/Nil$;
  #619 = Fieldref           #616.#618     // scala/collection/immutable/Nil$.MODULE$:Lscala/collection/immutable/Nil$;
  #620 = Utf8               prependedAll
  #621 = Utf8               (Lscala/collection/IterableOnce;)Lscala/collection/immutable/List;
  #622 = NameAndType        #620:#621     // prependedAll:(Lscala/collection/IterableOnce;)Lscala/collection/immutable/List;
  #623 = Methodref          #616.#622     // scala/collection/immutable/Nil$.prependedAll:(Lscala/collection/IterableOnce;)Lscala/collection/immutable/List;
  #624 = Utf8               toLowerCase
  #625 = NameAndType        #624:#29      // toLowerCase:()Ljava/lang/String;
  #626 = Methodref          #116.#625     // java/lang/String.toLowerCase:()Ljava/lang/String;
  #627 = Utf8               scala/collection/immutable/List
  #628 = Class              #627          // scala/collection/immutable/List
  #629 = NameAndType        #428:#112     // contains:(Ljava/lang/Object;)Z
  #630 = Methodref          #628.#629     // scala/collection/immutable/List.contains:(Ljava/lang/Object;)Z
  #631 = Utf8               apply_elems
  #632 = Utf8               Lscala/collection/immutable/Seq;
  #633 = Utf8               scala/collection/immutable/ArraySeq
  #634 = Class              #633          // scala/collection/immutable/ArraySeq
  #635 = Utf8               name$1
  #636 = Integer            6
  #637 = Utf8               scala.
  #638 = String             #637          // scala.
  #639 = Utf8               $anonfun$releaseVersion$1
  #640 = Utf8               v
  #641 = Utf8               -SNAPSHOT
  #642 = String             #641          // -SNAPSHOT
  #643 = Utf8               endsWith
  #644 = NameAndType        #643:#91      // endsWith:(Ljava/lang/String;)Z
  #645 = Methodref          #116.#644     // java/lang/String.endsWith:(Ljava/lang/String;)Z
  #646 = Utf8               $anonfun$releaseVersion$2
  #647 = Utf8               $anonfun$developmentVersion$1
  #648 = Utf8               $anonfun$developmentVersion$3
  #649 = Utf8               ov
  #650 = Utf8               $anonfun$developmentVersion$2
  #651 = Utf8               scala/None$
  #652 = Class              #651          // scala/None$
  #653 = Utf8               Lscala/None$;
  #654 = NameAndType        #127:#653     // MODULE$:Lscala/None$;
  #655 = Fieldref           #652.#654     // scala/None$.MODULE$:Lscala/None$;
  #656 = Utf8               scala/Some
  #657 = Class              #656          // scala/Some
  #658 = Utf8               (Ljava/lang/Object;)V
  #659 = NameAndType        #46:#658      // "<init>":(Ljava/lang/Object;)V
  #660 = Methodref          #657.#659     // scala/Some."<init>":(Ljava/lang/Object;)V
  #661 = Utf8               map_this
  #662 = Utf8               $anonfun$versionString$1
  #663 = Utf8               (unknown)
  #664 = String             #663          // (unknown)
  #665 = Utf8               $anonfun$copyrightString$1
  #666 = Utf8               Copyright 2002-2021, LAMP/EPFL and Lightbend, Inc.
  #667 = String             #666          // Copyright 2002-2021, LAMP/EPFL and Lightbend, Inc.
  #668 = Utf8               UTF-8
  #669 = String             #668          // UTF-8
  #670 = Utf8               scala.tools.nsc.io.SourceReader
  #671 = String             #670          // scala.tools.nsc.io.SourceReader
  #672 = Utf8               $anonfun$jdkHome$2
  #673 = Utf8               JAVA_HOME
  #674 = String             #673          // JAVA_HOME
  #675 = NameAndType        #672:#254     // $anonfun$jdkHome$2:(Lscala/util/PropertiesTrait;)Ljava/lang/String;
  #676 = InterfaceMethodref #2.#675       // scala/util/PropertiesTrait.$anonfun$jdkHome$2:(Lscala/util/PropertiesTrait;)Ljava/lang/String;
  #677 = MethodHandle       6:#676        // REF_invokeStatic scala/util/PropertiesTrait.$anonfun$jdkHome$2:(Lscala/util/PropertiesTrait;)Ljava/lang/String;
  #678 = InvokeDynamic      #8:#472       // #8:apply:(Lscala/util/PropertiesTrait;)Lscala/Function0;
  #679 = Utf8               versionOf$1
  #680 = Utf8               (Ljava/lang/String;I)Lscala/Tuple2;
  #681 = Utf8               s
  #682 = Utf8               depth
  #683 = Utf8               indexOf
  #684 = Utf8               (I)I
  #685 = NameAndType        #683:#684     // indexOf:(I)I
  #686 = Methodref          #116.#685     // java/lang/String.indexOf:(I)I
  #687 = Utf8               scala/Tuple2
  #688 = Class              #687          // scala/Tuple2
  #689 = Utf8               valueOf
  #690 = Utf8               (I)Ljava/lang/Integer;
  #691 = NameAndType        #689:#690     // valueOf:(I)Ljava/lang/Integer;
  #692 = Methodref          #557.#691     // java/lang/Integer.valueOf:(I)Ljava/lang/Integer;
  #693 = Utf8               substring
  #694 = NameAndType        #693:#558     // substring:(I)Ljava/lang/String;
  #695 = Methodref          #116.#694     // java/lang/String.substring:(I)Ljava/lang/String;
  #696 = Utf8               (Ljava/lang/Object;Ljava/lang/Object;)V
  #697 = NameAndType        #46:#696      // "<init>":(Ljava/lang/Object;Ljava/lang/Object;)V
  #698 = Methodref          #688.#697     // scala/Tuple2."<init>":(Ljava/lang/Object;Ljava/lang/Object;)V
  #699 = Utf8               charAt
  #700 = Utf8               (I)C
  #701 = NameAndType        #699:#700     // charAt:(I)C
  #702 = Methodref          #116.#701     // java/lang/String.charAt:(I)C
  #703 = NameAndType        #679:#680     // versionOf$1:(Ljava/lang/String;I)Lscala/Tuple2;
  #704 = InterfaceMethodref #2.#703       // scala/util/PropertiesTrait.versionOf$1:(Ljava/lang/String;I)Lscala/Tuple2;
  #705 = Utf8               _1$mcI$sp
  #706 = NameAndType        #705:#444     // _1$mcI$sp:()I
  #707 = Methodref          #688.#706     // scala/Tuple2._1$mcI$sp:()I
  #708 = Utf8               _2
  #709 = NameAndType        #708:#139     // _2:()Ljava/lang/Object;
  #710 = Methodref          #688.#709     // scala/Tuple2._2:()Ljava/lang/Object;
  #711 = Utf8               scala/MatchError
  #712 = Class              #711          // scala/MatchError
  #713 = Methodref          #712.#659     // scala/MatchError."<init>":(Ljava/lang/Object;)V
  #714 = Methodref          #116.#137     // java/lang/String.isEmpty:()Z
  #715 = Utf8               parseInt
  #716 = Utf8               (Ljava/lang/String;)I
  #717 = NameAndType        #715:#716     // parseInt:(Ljava/lang/String;)I
  #718 = Methodref          #557.#717     // java/lang/Integer.parseInt:(Ljava/lang/String;)I
  #719 = Utf8               (II)Ljava/lang/String;
  #720 = NameAndType        #693:#719     // substring:(II)Ljava/lang/String;
  #721 = Methodref          #116.#720     // java/lang/String.substring:(II)Ljava/lang/String;
  #722 = Utf8               r
  #723 = Utf8               r0
  #724 = Utf8               n
  #725 = Utf8               toInt$extension_$this
  #726 = Utf8               sn
  #727 = Utf8               srest
  #728 = Utf8               vn
  #729 = Utf8               vrest
  #730 = Utf8               $init$
  #731 = Utf8               (Lscala/util/PropertiesTrait;)V
  #732 = Integer            12
  #733 = Utf8               /
  #734 = String             #733          // /
  #735 = Utf8               .properties
  #736 = String             #735          // .properties
  #737 = NameAndType        #19:#20       // scala$util$PropertiesTrait$_setter_$propFilename_$eq:(Ljava/lang/String;)V
  #738 = InterfaceMethodref #2.#737       // scala/util/PropertiesTrait.scala$util$PropertiesTrait$_setter_$propFilename_$eq:(Ljava/lang/String;)V
  #739 = Utf8               maven.version.number
  #740 = String             #739          // maven.version.number
  #741 = Utf8               (Ljava/lang/Object;)Ljava/lang/Object;
  #742 = MethodType         #741          //  (Ljava/lang/Object;)Ljava/lang/Object;
  #743 = Utf8               $anonfun$releaseVersion$1$adapted
  #744 = Utf8               (Ljava/lang/String;)Ljava/lang/Object;
  #745 = NameAndType        #743:#744     // $anonfun$releaseVersion$1$adapted:(Ljava/lang/String;)Ljava/lang/Object;
  #746 = InterfaceMethodref #2.#745       // scala/util/PropertiesTrait.$anonfun$releaseVersion$1$adapted:(Ljava/lang/String;)Ljava/lang/Object;
  #747 = MethodHandle       6:#746        // REF_invokeStatic scala/util/PropertiesTrait.$anonfun$releaseVersion$1$adapted:(Ljava/lang/String;)Ljava/lang/Object;
  #748 = MethodType         #744          //  (Ljava/lang/String;)Ljava/lang/Object;
  #749 = Utf8               ()Lscala/Function1;
  #750 = NameAndType        #131:#749     // apply:()Lscala/Function1;
  #751 = InvokeDynamic      #9:#750       // #9:apply:()Lscala/Function1;
  #752 = Utf8               (Lscala/Option;Lscala/Function1;)V
  #753 = NameAndType        #46:#752      // "<init>":(Lscala/Option;Lscala/Function1;)V
  #754 = Methodref          #15.#753      // scala/Option$WithFilter."<init>":(Lscala/Option;Lscala/Function1;)V
  #755 = NameAndType        #646:#98      // $anonfun$releaseVersion$2:(Ljava/lang/String;)Ljava/lang/String;
  #756 = InterfaceMethodref #2.#755       // scala/util/PropertiesTrait.$anonfun$releaseVersion$2:(Ljava/lang/String;)Ljava/lang/String;
  #757 = MethodHandle       6:#756        // REF_invokeStatic scala/util/PropertiesTrait.$anonfun$releaseVersion$2:(Ljava/lang/String;)Ljava/lang/String;
  #758 = MethodType         #98           //  (Ljava/lang/String;)Ljava/lang/String;
  #759 = InvokeDynamic      #10:#750      // #10:apply:()Lscala/Function1;
  #760 = Utf8               map
  #761 = Utf8               (Lscala/Function1;)Lscala/Option;
  #762 = NameAndType        #760:#761     // map:(Lscala/Function1;)Lscala/Option;
  #763 = Methodref          #15.#762      // scala/Option$WithFilter.map:(Lscala/Function1;)Lscala/Option;
  #764 = NameAndType        #22:#23       // scala$util$PropertiesTrait$_setter_$releaseVersion_$eq:(Lscala/Option;)V
  #765 = InterfaceMethodref #2.#764       // scala/util/PropertiesTrait.scala$util$PropertiesTrait$_setter_$releaseVersion_$eq:(Lscala/Option;)V
  #766 = Utf8               $anonfun$developmentVersion$1$adapted
  #767 = NameAndType        #766:#744     // $anonfun$developmentVersion$1$adapted:(Ljava/lang/String;)Ljava/lang/Object;
  #768 = InterfaceMethodref #2.#767       // scala/util/PropertiesTrait.$anonfun$developmentVersion$1$adapted:(Ljava/lang/String;)Ljava/lang/Object;
  #769 = MethodHandle       6:#768        // REF_invokeStatic scala/util/PropertiesTrait.$anonfun$developmentVersion$1$adapted:(Ljava/lang/String;)Ljava/lang/Object;
  #770 = InvokeDynamic      #11:#750      // #11:apply:()Lscala/Function1;
  #771 = NameAndType        #650:#179     // $anonfun$developmentVersion$2:(Lscala/util/PropertiesTrait;Ljava/lang/String;)Lscala/Option;
  #772 = InterfaceMethodref #2.#771       // scala/util/PropertiesTrait.$anonfun$developmentVersion$2:(Lscala/util/PropertiesTrait;Ljava/lang/String;)Lscala/Option;
  #773 = MethodHandle       6:#772        // REF_invokeStatic scala/util/PropertiesTrait.$anonfun$developmentVersion$2:(Lscala/util/PropertiesTrait;Ljava/lang/String;)Lscala/Option;
  #774 = MethodType         #181          //  (Ljava/lang/String;)Lscala/Option;
  #775 = Utf8               (Lscala/util/PropertiesTrait;)Lscala/Function1;
  #776 = NameAndType        #131:#775     // apply:(Lscala/util/PropertiesTrait;)Lscala/Function1;
  #777 = InvokeDynamic      #12:#776      // #12:apply:(Lscala/util/PropertiesTrait;)Lscala/Function1;
  #778 = Utf8               flatMap
  #779 = NameAndType        #778:#761     // flatMap:(Lscala/Function1;)Lscala/Option;
  #780 = Methodref          #15.#779      // scala/Option$WithFilter.flatMap:(Lscala/Function1;)Lscala/Option;
  #781 = NameAndType        #25:#23       // scala$util$PropertiesTrait$_setter_$developmentVersion_$eq:(Lscala/Option;)V
  #782 = InterfaceMethodref #2.#781       // scala/util/PropertiesTrait.scala$util$PropertiesTrait$_setter_$developmentVersion_$eq:(Lscala/Option;)V
  #783 = Integer            8
  #784 = Utf8               version
  #785 = String             #784          // version
  #786 = NameAndType        #662:#29      // $anonfun$versionString$1:()Ljava/lang/String;
  #787 = InterfaceMethodref #2.#786       // scala/util/PropertiesTrait.$anonfun$versionString$1:()Ljava/lang/String;
  #788 = MethodHandle       6:#787        // REF_invokeStatic scala/util/PropertiesTrait.$anonfun$versionString$1:()Ljava/lang/String;
  #789 = InvokeDynamic      #13:#168      // #13:apply:()Lscala/Function0;
  #790 = NameAndType        #26:#20       // scala$util$PropertiesTrait$_setter_$versionString_$eq:(Ljava/lang/String;)V
  #791 = InterfaceMethodref #2.#790       // scala/util/PropertiesTrait.scala$util$PropertiesTrait$_setter_$versionString_$eq:(Ljava/lang/String;)V
  #792 = Utf8               copyright.string
  #793 = String             #792          // copyright.string
  #794 = NameAndType        #665:#29      // $anonfun$copyrightString$1:()Ljava/lang/String;
  #795 = InterfaceMethodref #2.#794       // scala/util/PropertiesTrait.$anonfun$copyrightString$1:()Ljava/lang/String;
  #796 = MethodHandle       6:#795        // REF_invokeStatic scala/util/PropertiesTrait.$anonfun$copyrightString$1:()Ljava/lang/String;
  #797 = InvokeDynamic      #14:#168      // #14:apply:()Lscala/Function0;
  #798 = NameAndType        #27:#20       // scala$util$PropertiesTrait$_setter_$copyrightString_$eq:(Ljava/lang/String;)V
  #799 = InterfaceMethodref #2.#798       // scala/util/PropertiesTrait.scala$util$PropertiesTrait$_setter_$copyrightString_$eq:(Ljava/lang/String;)V
  #800 = Utf8               withFilter_this
  #801 = Utf8               withFilter_p
  #802 = Utf8               Lscala/Function1;
  #803 = Utf8               scala/Function1
  #804 = Class              #803          // scala/Function1
  #805 = Utf8               $anonfun$propOrFalse$1$adapted
  #806 = Utf8               scala/runtime/BoxesRunTime
  #807 = Class              #806          // scala/runtime/BoxesRunTime
  #808 = Utf8               boxToBoolean
  #809 = Utf8               (Z)Ljava/lang/Boolean;
  #810 = NameAndType        #808:#809     // boxToBoolean:(Z)Ljava/lang/Boolean;
  #811 = Methodref          #807.#810     // scala/runtime/BoxesRunTime.boxToBoolean:(Z)Ljava/lang/Boolean;
  #812 = NameAndType        #639:#91      // $anonfun$releaseVersion$1:(Ljava/lang/String;)Z
  #813 = InterfaceMethodref #2.#812       // scala/util/PropertiesTrait.$anonfun$releaseVersion$1:(Ljava/lang/String;)Z
  #814 = NameAndType        #647:#91      // $anonfun$developmentVersion$1:(Ljava/lang/String;)Z
  #815 = InterfaceMethodref #2.#814       // scala/util/PropertiesTrait.$anonfun$developmentVersion$1:(Ljava/lang/String;)Z
  #816 = Utf8               $deserializeLambda$
  #817 = Utf8               (Ljava/lang/invoke/SerializedLambda;)Ljava/lang/Object;
  #818 = Utf8               scala/runtime/LambdaDeserialize
  #819 = Class              #818          // scala/runtime/LambdaDeserialize
  #820 = Utf8               bootstrap
  #821 = Utf8               (Ljava/lang/invoke/MethodHandles$Lookup;Ljava/lang/String;Ljava/lang/invoke/MethodType;[Ljava/lang/invoke/MethodHandle;)Ljava/lang/invoke/CallSite;
  #822 = NameAndType        #820:#821     // bootstrap:(Ljava/lang/invoke/MethodHandles$Lookup;Ljava/lang/String;Ljava/lang/invoke/MethodType;[Ljava/lang/invoke/MethodHandle;)Ljava/lang/invoke/CallSite;
  #823 = Methodref          #819.#822     // scala/runtime/LambdaDeserialize.bootstrap:(Ljava/lang/invoke/MethodHandles$Lookup;Ljava/lang/String;Ljava/lang/invoke/MethodType;[Ljava/lang/invoke/MethodHandle;)Ljava/lang/invoke/CallSite;
  #824 = MethodHandle       6:#823        // REF_invokeStatic scala/runtime/LambdaDeserialize.bootstrap:(Ljava/lang/invoke/MethodHandles$Lookup;Ljava/lang/String;Ljava/lang/invoke/MethodType;[Ljava/lang/invoke/MethodHandle;)Ljava/lang/invoke/CallSite;
  #825 = Utf8               lambdaDeserialize
  #826 = NameAndType        #825:#817     // lambdaDeserialize:(Ljava/lang/invoke/SerializedLambda;)Ljava/lang/Object;
  #827 = InvokeDynamic      #15:#826      // #15:lambdaDeserialize:(Ljava/lang/invoke/SerializedLambda;)Ljava/lang/Object;
  #828 = Utf8               MethodParameters
  #829 = Utf8               Signature
  #830 = Utf8               Code
  #831 = Utf8               LineNumberTable
  #832 = Utf8               LocalVariableTable
  #833 = Utf8               StackMapTable
  #834 = Utf8               InnerClasses
  #835 = Utf8               SourceFile
  #836 = Utf8               RuntimeVisibleAnnotations
  #837 = Utf8               BootstrapMethods
  #838 = Utf8               ScalaInlineInfo
  #839 = Utf8               ScalaSig
{
  public abstract void scala$util$PropertiesTrait$_setter_$propFilename_$eq(java.lang.String);
    descriptor: (Ljava/lang/String;)V
    flags: (0x0401) ACC_PUBLIC, ACC_ABSTRACT
    MethodParameters:
      Name                           Flags
      x$1                            final

  public abstract void scala$util$PropertiesTrait$_setter_$releaseVersion_$eq(scala.Option<java.lang.String>);
    descriptor: (Lscala/Option;)V
    flags: (0x0401) ACC_PUBLIC, ACC_ABSTRACT
    Signature: #24                          // (Lscala/Option<Ljava/lang/String;>;)V
    MethodParameters:
      Name                           Flags
      x$1                            final

  public abstract void scala$util$PropertiesTrait$_setter_$developmentVersion_$eq(scala.Option<java.lang.String>);
    descriptor: (Lscala/Option;)V
    flags: (0x0401) ACC_PUBLIC, ACC_ABSTRACT
    Signature: #24                          // (Lscala/Option<Ljava/lang/String;>;)V
    MethodParameters:
      Name                           Flags
      x$1                            final

  public abstract void scala$util$PropertiesTrait$_setter_$versionString_$eq(java.lang.String);
    descriptor: (Ljava/lang/String;)V
    flags: (0x0401) ACC_PUBLIC, ACC_ABSTRACT
    MethodParameters:
      Name                           Flags
      x$1                            final

  public abstract void scala$util$PropertiesTrait$_setter_$copyrightString_$eq(java.lang.String);
    descriptor: (Ljava/lang/String;)V
    flags: (0x0401) ACC_PUBLIC, ACC_ABSTRACT
    MethodParameters:
      Name                           Flags
      x$1                            final

  public abstract java.lang.String propCategory();
    descriptor: ()Ljava/lang/String;
    flags: (0x0401) ACC_PUBLIC, ACC_ABSTRACT

  public abstract java.lang.Class<?> pickJarBasedOn();
    descriptor: ()Ljava/lang/Class;
    flags: (0x0401) ACC_PUBLIC, ACC_ABSTRACT
    Signature: #32                          // ()Ljava/lang/Class<*>;

  public abstract java.lang.String propFilename();
    descriptor: ()Ljava/lang/String;
    flags: (0x0401) ACC_PUBLIC, ACC_ABSTRACT

  public static java.util.Properties scalaProps$(scala.util.PropertiesTrait);
    descriptor: (Lscala/util/PropertiesTrait;)Ljava/util/Properties;
    flags: (0x1009) ACC_PUBLIC, ACC_STATIC, ACC_SYNTHETIC
    Code:
      stack=1, locals=1, args_size=1
         0: aload_0
         1: invokespecial #40                 // InterfaceMethod scalaProps:()Ljava/util/Properties;
         4: areturn
      LineNumberTable:
        line 38: 0
      LocalVariableTable:
        Start  Length  Slot  Name   Signature
            0       5     0 $this   Lscala/util/PropertiesTrait;
    MethodParameters:
      Name                           Flags
      $this                          final synthetic

  public default java.util.Properties scalaProps();
    descriptor: ()Ljava/util/Properties;
    flags: (0x0001) ACC_PUBLIC
    Code:
      stack=2, locals=4, args_size=1
         0: new           #45                 // class java/util/Properties
         3: dup
         4: invokespecial #49                 // Method java/util/Properties."<init>":()V
         7: astore_1
         8: aload_0
         9: invokeinterface #51,  1           // InterfaceMethod pickJarBasedOn:()Ljava/lang/Class;
        14: aload_0
        15: invokeinterface #53,  1           // InterfaceMethod propFilename:()Ljava/lang/String;
        20: invokevirtual #59                 // Method java/lang/Class.getResourceAsStream:(Ljava/lang/String;)Ljava/io/InputStream;
        23: astore_2
        24: aload_2
        25: ifnull        55
        28: aload_1
        29: aload_2
        30: invokevirtual #63                 // Method java/util/Properties.load:(Ljava/io/InputStream;)V
        33: goto          47
        36: astore_3
        37: aload_2
        38: invokevirtual #68                 // Method java/io/InputStream.close:()V
        41: goto          45
        44: pop
        45: aload_3
        46: athrow
        47: aload_2
        48: invokevirtual #68                 // Method java/io/InputStream.close:()V
        51: goto          55
        54: pop
        55: aload_1
        56: areturn
      Exception table:
         from    to  target type
            28    36    36   any
            37    44    44   Class java/io/IOException
            47    54    54   Class java/io/IOException
      StackMapTable: number_of_entries = 6
        frame_type = 255 /* full_frame */
          offset_delta = 36
          locals = [ class scala/util/PropertiesTrait, class java/util/Properties, class java/io/InputStream ]
          stack = [ class java/lang/Throwable ]
        frame_type = 255 /* full_frame */
          offset_delta = 7
          locals = [ class scala/util/PropertiesTrait, class java/util/Properties, class java/io/InputStream, class java/lang/Throwable ]
          stack = [ class java/io/IOException ]
        frame_type = 0 /* same */
        frame_type = 250 /* chop */
          offset_delta = 1
        frame_type = 70 /* same_locals_1_stack_item */
          stack = [ class java/io/IOException ]
        frame_type = 0 /* same */
      LineNumberTable:
        line 39: 0
        line 40: 8
        line 41: 24
        line 42: 28
        line 48: 36
        line 42: 37
        line 50: 44
        line 51: 45
        line 42: 47
        line 50: 54
        line 44: 55
      LocalVariableTable:
        Start  Length  Slot  Name   Signature
            8      48     1 props   Ljava/util/Properties;
           24      32     2 stream   Ljava/io/InputStream;
            0      57     0  this   Lscala/util/PropertiesTrait;

  private void quietlyDispose(scala.Function0<scala.runtime.BoxedUnit>, scala.Function0<scala.runtime.BoxedUnit>);
    descriptor: (Lscala/Function0;Lscala/Function0;)V
    flags: (0x0002) ACC_PRIVATE
    Code:
      stack=1, locals=4, args_size=3
         0: aload_1
         1: invokeinterface #85,  1           // InterfaceMethod scala/Function0.apply$mcV$sp:()V
         6: goto          22
         9: astore_3
        10: aload_2
        11: invokeinterface #85,  1           // InterfaceMethod scala/Function0.apply$mcV$sp:()V
        16: goto          20
        19: pop
        20: aload_3
        21: athrow
        22: aload_2
        23: invokeinterface #85,  1           // InterfaceMethod scala/Function0.apply$mcV$sp:()V
        28: return
        29: pop
        30: return
      Exception table:
         from    to  target type
             0     9     9   any
            10    16    19   Class java/io/IOException
            22    28    29   Class java/io/IOException
      StackMapTable: number_of_entries = 5
        frame_type = 73 /* same_locals_1_stack_item */
          stack = [ class java/lang/Throwable ]
        frame_type = 255 /* full_frame */
          offset_delta = 9
          locals = [ class scala/util/PropertiesTrait, class scala/Function0, class scala/Function0, class java/lang/Throwable ]
          stack = [ class java/io/IOException ]
        frame_type = 0 /* same */
        frame_type = 250 /* chop */
          offset_delta = 1
        frame_type = 70 /* same_locals_1_stack_item */
          stack = [ class java/io/IOException ]
      LineNumberTable:
        line 48: 0
        line 50: 10
        line 51: 20
        line 50: 22
        line 51: 30
      LocalVariableTable:
        Start  Length  Slot  Name   Signature
            0      31     0  this   Lscala/util/PropertiesTrait;
            0      31     1 action   Lscala/Function0;
            0      31     2 disposal   Lscala/Function0;
    Signature: #78                          // (Lscala/Function0<Lscala/runtime/BoxedUnit;>;Lscala/Function0<Lscala/runtime/BoxedUnit;>;)V
    MethodParameters:
      Name                           Flags
      action                         final
      disposal                       final

  public static boolean propIsSet$(scala.util.PropertiesTrait, java.lang.String);
    descriptor: (Lscala/util/PropertiesTrait;Ljava/lang/String;)Z
    flags: (0x1009) ACC_PUBLIC, ACC_STATIC, ACC_SYNTHETIC
    Code:
      stack=2, locals=2, args_size=2
         0: aload_0
         1: aload_1
         2: invokespecial #93                 // InterfaceMethod propIsSet:(Ljava/lang/String;)Z
         5: ireturn
      LineNumberTable:
        line 54: 0
      LocalVariableTable:
        Start  Length  Slot  Name   Signature
            0       6     0 $this   Lscala/util/PropertiesTrait;
            0       6     1  name   Ljava/lang/String;
    MethodParameters:
      Name                           Flags
      $this                          final synthetic
      name                           final

  public default boolean propIsSet(java.lang.String);
    descriptor: (Ljava/lang/String;)Z
    flags: (0x0001) ACC_PUBLIC
    Code:
      stack=1, locals=2, args_size=2
         0: aload_1
         1: invokestatic  #100                // Method java/lang/System.getProperty:(Ljava/lang/String;)Ljava/lang/String;
         4: ifnull        9
         7: iconst_1
         8: ireturn
         9: iconst_0
        10: ireturn
      StackMapTable: number_of_entries = 1
        frame_type = 9 /* same */
      LineNumberTable:
        line 54: 0
      LocalVariableTable:
        Start  Length  Slot  Name   Signature
            0      11     0  this   Lscala/util/PropertiesTrait;
            0      11     1  name   Ljava/lang/String;
    MethodParameters:
      Name                           Flags
      name                           final

  public static boolean propIsSetTo$(scala.util.PropertiesTrait, java.lang.String, java.lang.String);
    descriptor: (Lscala/util/PropertiesTrait;Ljava/lang/String;Ljava/lang/String;)Z
    flags: (0x1009) ACC_PUBLIC, ACC_STATIC, ACC_SYNTHETIC
    Code:
      stack=3, locals=3, args_size=3
         0: aload_0
         1: aload_1
         2: aload_2
         3: invokespecial #107                // InterfaceMethod propIsSetTo:(Ljava/lang/String;Ljava/lang/String;)Z
         6: ireturn
      LineNumberTable:
        line 55: 0
      LocalVariableTable:
        Start  Length  Slot  Name   Signature
            0       7     0 $this   Lscala/util/PropertiesTrait;
            0       7     1  name   Ljava/lang/String;
            0       7     2 value   Ljava/lang/String;
    MethodParameters:
      Name                           Flags
      $this                          final synthetic
      name                           final
      value                          final

  public default boolean propIsSetTo(java.lang.String, java.lang.String);
    descriptor: (Ljava/lang/String;Ljava/lang/String;)Z
    flags: (0x0001) ACC_PUBLIC
    Code:
      stack=2, locals=3, args_size=3
         0: aload_0
         1: aload_1
         2: invokeinterface #110,  2          // InterfaceMethod propOrNull:(Ljava/lang/String;)Ljava/lang/String;
         7: dup
         8: ifnonnull     19
        11: pop
        12: aload_2
        13: ifnull        26
        16: goto          28
        19: aload_2
        20: invokevirtual #114                // Method java/lang/Object.equals:(Ljava/lang/Object;)Z
        23: ifeq          28
        26: iconst_1
        27: ireturn
        28: iconst_0
        29: ireturn
      StackMapTable: number_of_entries = 3
        frame_type = 83 /* same_locals_1_stack_item */
          stack = [ class java/lang/String ]
        frame_type = 6 /* same */
        frame_type = 1 /* same */
      LineNumberTable:
        line 55: 0
      LocalVariableTable:
        Start  Length  Slot  Name   Signature
            0      30     0  this   Lscala/util/PropertiesTrait;
            0      30     1  name   Ljava/lang/String;
            0      30     2 value   Ljava/lang/String;
    MethodParameters:
      Name                           Flags
      name                           final
      value                          final

  public static java.lang.String propOrElse$(scala.util.PropertiesTrait, java.lang.String, scala.Function0);
    descriptor: (Lscala/util/PropertiesTrait;Ljava/lang/String;Lscala/Function0;)Ljava/lang/String;
    flags: (0x1009) ACC_PUBLIC, ACC_STATIC, ACC_SYNTHETIC
    Code:
      stack=3, locals=3, args_size=3
         0: aload_0
         1: aload_1
         2: aload_2
         3: invokespecial #123                // InterfaceMethod propOrElse:(Ljava/lang/String;Lscala/Function0;)Ljava/lang/String;
         6: areturn
      LineNumberTable:
        line 56: 0
      LocalVariableTable:
        Start  Length  Slot  Name   Signature
            0       7     0 $this   Lscala/util/PropertiesTrait;
            0       7     1  name   Ljava/lang/String;
            0       7     2   alt   Lscala/Function0;
    MethodParameters:
      Name                           Flags
      $this                          final synthetic
      name                           final
      alt                            final

  public default java.lang.String propOrElse(java.lang.String, scala.Function0<java.lang.String>);
    descriptor: (Ljava/lang/String;Lscala/Function0;)Ljava/lang/String;
    flags: (0x0001) ACC_PUBLIC
    Code:
      stack=2, locals=4, args_size=3
         0: getstatic     #130                // Field scala/Option$.MODULE$:Lscala/Option$;
         3: aload_1
         4: invokestatic  #100                // Method java/lang/System.getProperty:(Ljava/lang/String;)Ljava/lang/String;
         7: invokevirtual #134                // Method scala/Option$.apply:(Ljava/lang/Object;)Lscala/Option;
        10: dup
        11: ifnonnull     16
        14: aconst_null
        15: athrow
        16: astore_3
        17: aload_3
        18: invokevirtual #138                // Method scala/Option.isEmpty:()Z
        21: ifeq          33
        24: aload_2
        25: invokeinterface #141,  1          // InterfaceMethod scala/Function0.apply:()Ljava/lang/Object;
        30: goto          37
        33: aload_3
        34: invokevirtual #144                // Method scala/Option.get:()Ljava/lang/Object;
        37: checkcast     #116                // class java/lang/String
        40: areturn
      StackMapTable: number_of_entries = 3
        frame_type = 80 /* same_locals_1_stack_item */
          stack = [ class scala/Option ]
        frame_type = 252 /* append */
          offset_delta = 16
          locals = [ class scala/Option ]
        frame_type = 67 /* same_locals_1_stack_item */
          stack = [ class java/lang/Object ]
      LineNumberTable:
        line 56: 0
      LocalVariableTable:
        Start  Length  Slot  Name   Signature
            0      41     0  this   Lscala/util/PropertiesTrait;
            0      41     1  name   Ljava/lang/String;
            0      41     2   alt   Lscala/Function0;
           17      20     3 getOrElse_this   Lscala/Option;
    Signature: #124                         // (Ljava/lang/String;Lscala/Function0<Ljava/lang/String;>;)Ljava/lang/String;
    MethodParameters:
      Name                           Flags
      name                           final
      alt                            final

  public static java.lang.String propOrEmpty$(scala.util.PropertiesTrait, java.lang.String);
    descriptor: (Lscala/util/PropertiesTrait;Ljava/lang/String;)Ljava/lang/String;
    flags: (0x1009) ACC_PUBLIC, ACC_STATIC, ACC_SYNTHETIC
    Code:
      stack=2, locals=2, args_size=2
         0: aload_0
         1: aload_1
         2: invokespecial #151                // InterfaceMethod propOrEmpty:(Ljava/lang/String;)Ljava/lang/String;
         5: areturn
      LineNumberTable:
        line 57: 0
      LocalVariableTable:
        Start  Length  Slot  Name   Signature
            0       6     0 $this   Lscala/util/PropertiesTrait;
            0       6     1  name   Ljava/lang/String;
    MethodParameters:
      Name                           Flags
      $this                          final synthetic
      name                           final

  public default java.lang.String propOrEmpty(java.lang.String);
    descriptor: (Ljava/lang/String;)Ljava/lang/String;
    flags: (0x0001) ACC_PUBLIC
    Code:
      stack=3, locals=2, args_size=2
         0: aload_0
         1: aload_1
         2: invokedynamic #169,  0            // InvokeDynamic #0:apply:()Lscala/Function0;
         7: invokeinterface #123,  3          // InterfaceMethod propOrElse:(Ljava/lang/String;Lscala/Function0;)Ljava/lang/String;
        12: areturn
      LineNumberTable:
        line 57: 0
      LocalVariableTable:
        Start  Length  Slot  Name   Signature
            0      13     0  this   Lscala/util/PropertiesTrait;
            0      13     1  name   Ljava/lang/String;
    MethodParameters:
      Name                           Flags
      name                           final

  public static java.lang.String propOrNull$(scala.util.PropertiesTrait, java.lang.String);
    descriptor: (Lscala/util/PropertiesTrait;Ljava/lang/String;)Ljava/lang/String;
    flags: (0x1009) ACC_PUBLIC, ACC_STATIC, ACC_SYNTHETIC
    Code:
      stack=2, locals=2, args_size=2
         0: aload_0
         1: aload_1
         2: invokespecial #110                // InterfaceMethod propOrNull:(Ljava/lang/String;)Ljava/lang/String;
         5: areturn
      LineNumberTable:
        line 58: 0
      LocalVariableTable:
        Start  Length  Slot  Name   Signature
            0       6     0 $this   Lscala/util/PropertiesTrait;
            0       6     1  name   Ljava/lang/String;
    MethodParameters:
      Name                           Flags
      $this                          final synthetic
      name                           final

  public default java.lang.String propOrNull(java.lang.String);
    descriptor: (Ljava/lang/String;)Ljava/lang/String;
    flags: (0x0001) ACC_PUBLIC
    Code:
      stack=3, locals=2, args_size=2
         0: aload_0
         1: aload_1
         2: invokedynamic #177,  0            // InvokeDynamic #1:apply:()Lscala/Function0;
         7: invokeinterface #123,  3          // InterfaceMethod propOrElse:(Ljava/lang/String;Lscala/Function0;)Ljava/lang/String;
        12: areturn
      LineNumberTable:
        line 58: 0
      LocalVariableTable:
        Start  Length  Slot  Name   Signature
            0      13     0  this   Lscala/util/PropertiesTrait;
            0      13     1  name   Ljava/lang/String;
    MethodParameters:
      Name                           Flags
      name                           final

  public static scala.Option propOrNone$(scala.util.PropertiesTrait, java.lang.String);
    descriptor: (Lscala/util/PropertiesTrait;Ljava/lang/String;)Lscala/Option;
    flags: (0x1009) ACC_PUBLIC, ACC_STATIC, ACC_SYNTHETIC
    Code:
      stack=2, locals=2, args_size=2
         0: aload_0
         1: aload_1
         2: invokespecial #183                // InterfaceMethod propOrNone:(Ljava/lang/String;)Lscala/Option;
         5: areturn
      LineNumberTable:
        line 59: 0
      LocalVariableTable:
        Start  Length  Slot  Name   Signature
            0       6     0 $this   Lscala/util/PropertiesTrait;
            0       6     1  name   Ljava/lang/String;
    MethodParameters:
      Name                           Flags
      $this                          final synthetic
      name                           final

  public default scala.Option<java.lang.String> propOrNone(java.lang.String);
    descriptor: (Ljava/lang/String;)Lscala/Option;
    flags: (0x0001) ACC_PUBLIC
    Code:
      stack=3, locals=2, args_size=2
         0: getstatic     #130                // Field scala/Option$.MODULE$:Lscala/Option$;
         3: aload_0
         4: aload_1
         5: invokeinterface #110,  2          // InterfaceMethod propOrNull:(Ljava/lang/String;)Ljava/lang/String;
        10: invokevirtual #134                // Method scala/Option$.apply:(Ljava/lang/Object;)Lscala/Option;
        13: areturn
      LineNumberTable:
        line 59: 0
      LocalVariableTable:
        Start  Length  Slot  Name   Signature
            0      14     0  this   Lscala/util/PropertiesTrait;
            0      14     1  name   Ljava/lang/String;
    Signature: #184                         // (Ljava/lang/String;)Lscala/Option<Ljava/lang/String;>;
    MethodParameters:
      Name                           Flags
      name                           final

  public static boolean propOrFalse$(scala.util.PropertiesTrait, java.lang.String);
    descriptor: (Lscala/util/PropertiesTrait;Ljava/lang/String;)Z
    flags: (0x1009) ACC_PUBLIC, ACC_STATIC, ACC_SYNTHETIC
    Code:
      stack=2, locals=2, args_size=2
         0: aload_0
         1: aload_1
         2: invokespecial #188                // InterfaceMethod propOrFalse:(Ljava/lang/String;)Z
         5: ireturn
      LineNumberTable:
        line 60: 0
      LocalVariableTable:
        Start  Length  Slot  Name   Signature
            0       6     0 $this   Lscala/util/PropertiesTrait;
            0       6     1  name   Ljava/lang/String;
    MethodParameters:
      Name                           Flags
      $this                          final synthetic
      name                           final

  public default boolean propOrFalse(java.lang.String);
    descriptor: (Ljava/lang/String;)Z
    flags: (0x0001) ACC_PUBLIC
    Code:
      stack=2, locals=3, args_size=2
         0: aload_0
         1: aload_1
         2: invokeinterface #183,  2          // InterfaceMethod propOrNone:(Ljava/lang/String;)Lscala/Option;
         7: dup
         8: ifnonnull     13
        11: aconst_null
        12: athrow
        13: astore_2
        14: aload_2
        15: invokevirtual #138                // Method scala/Option.isEmpty:()Z
        18: ifne          36
        21: aload_2
        22: invokevirtual #144                // Method scala/Option.get:()Ljava/lang/Object;
        25: checkcast     #116                // class java/lang/String
        28: invokestatic  #191                // InterfaceMethod $anonfun$propOrFalse$1:(Ljava/lang/String;)Z
        31: ifeq          36
        34: iconst_1
        35: ireturn
        36: iconst_0
        37: ireturn
      StackMapTable: number_of_entries = 2
        frame_type = 77 /* same_locals_1_stack_item */
          stack = [ class scala/Option ]
        frame_type = 252 /* append */
          offset_delta = 22
          locals = [ class scala/Option ]
      LineNumberTable:
        line 60: 0
        line 60: 28
        line 60: 31
      LocalVariableTable:
        Start  Length  Slot  Name   Signature
            0      38     0  this   Lscala/util/PropertiesTrait;
            0      38     1  name   Ljava/lang/String;
           14      23     2 exists_this   Lscala/Option;
    MethodParameters:
      Name                           Flags
      name                           final

  public static java.lang.String setProp$(scala.util.PropertiesTrait, java.lang.String, java.lang.String);
    descriptor: (Lscala/util/PropertiesTrait;Ljava/lang/String;Ljava/lang/String;)Ljava/lang/String;
    flags: (0x1009) ACC_PUBLIC, ACC_STATIC, ACC_SYNTHETIC
    Code:
      stack=3, locals=3, args_size=3
         0: aload_0
         1: aload_1
         2: aload_2
         3: invokespecial #198                // InterfaceMethod setProp:(Ljava/lang/String;Ljava/lang/String;)Ljava/lang/String;
         6: areturn
      LineNumberTable:
        line 61: 0
      LocalVariableTable:
        Start  Length  Slot  Name   Signature
            0       7     0 $this   Lscala/util/PropertiesTrait;
            0       7     1  name   Ljava/lang/String;
            0       7     2 value   Ljava/lang/String;
    MethodParameters:
      Name                           Flags
      $this                          final synthetic
      name                           final
      value                          final

  public default java.lang.String setProp(java.lang.String, java.lang.String);
    descriptor: (Ljava/lang/String;Ljava/lang/String;)Ljava/lang/String;
    flags: (0x0001) ACC_PUBLIC
    Code:
      stack=2, locals=3, args_size=3
         0: aload_1
         1: aload_2
         2: invokestatic  #201                // Method java/lang/System.setProperty:(Ljava/lang/String;Ljava/lang/String;)Ljava/lang/String;
         5: areturn
      LineNumberTable:
        line 61: 0
      LocalVariableTable:
        Start  Length  Slot  Name   Signature
            0       6     0  this   Lscala/util/PropertiesTrait;
            0       6     1  name   Ljava/lang/String;
            0       6     2 value   Ljava/lang/String;
    MethodParameters:
      Name                           Flags
      name                           final
      value                          final

  public static java.lang.String clearProp$(scala.util.PropertiesTrait, java.lang.String);
    descriptor: (Lscala/util/PropertiesTrait;Ljava/lang/String;)Ljava/lang/String;
    flags: (0x1009) ACC_PUBLIC, ACC_STATIC, ACC_SYNTHETIC
    Code:
      stack=2, locals=2, args_size=2
         0: aload_0
         1: aload_1
         2: invokespecial #205                // InterfaceMethod clearProp:(Ljava/lang/String;)Ljava/lang/String;
         5: areturn
      LineNumberTable:
        line 62: 0
      LocalVariableTable:
        Start  Length  Slot  Name   Signature
            0       6     0 $this   Lscala/util/PropertiesTrait;
            0       6     1  name   Ljava/lang/String;
    MethodParameters:
      Name                           Flags
      $this                          final synthetic
      name                           final

  public default java.lang.String clearProp(java.lang.String);
    descriptor: (Ljava/lang/String;)Ljava/lang/String;
    flags: (0x0001) ACC_PUBLIC
    Code:
      stack=1, locals=2, args_size=2
         0: aload_1
         1: invokestatic  #208                // Method java/lang/System.clearProperty:(Ljava/lang/String;)Ljava/lang/String;
         4: areturn
      LineNumberTable:
        line 62: 0
      LocalVariableTable:
        Start  Length  Slot  Name   Signature
            0       5     0  this   Lscala/util/PropertiesTrait;
            0       5     1  name   Ljava/lang/String;
    MethodParameters:
      Name                           Flags
      name                           final

  public static java.lang.String envOrElse$(scala.util.PropertiesTrait, java.lang.String, scala.Function0);
    descriptor: (Lscala/util/PropertiesTrait;Ljava/lang/String;Lscala/Function0;)Ljava/lang/String;
    flags: (0x1009) ACC_PUBLIC, ACC_STATIC, ACC_SYNTHETIC
    Code:
      stack=3, locals=3, args_size=3
         0: aload_0
         1: aload_1
         2: aload_2
         3: invokespecial #212                // InterfaceMethod envOrElse:(Ljava/lang/String;Lscala/Function0;)Ljava/lang/String;
         6: areturn
      LineNumberTable:
        line 64: 0
      LocalVariableTable:
        Start  Length  Slot  Name   Signature
            0       7     0 $this   Lscala/util/PropertiesTrait;
            0       7     1  name   Ljava/lang/String;
            0       7     2   alt   Lscala/Function0;
    MethodParameters:
      Name                           Flags
      $this                          final synthetic
      name                           final
      alt                            final

  public default java.lang.String envOrElse(java.lang.String, scala.Function0<java.lang.String>);
    descriptor: (Ljava/lang/String;Lscala/Function0;)Ljava/lang/String;
    flags: (0x0001) ACC_PUBLIC
    Code:
      stack=2, locals=4, args_size=3
         0: getstatic     #130                // Field scala/Option$.MODULE$:Lscala/Option$;
         3: aload_1
         4: invokestatic  #215                // Method java/lang/System.getenv:(Ljava/lang/String;)Ljava/lang/String;
         7: invokevirtual #134                // Method scala/Option$.apply:(Ljava/lang/Object;)Lscala/Option;
        10: dup
        11: ifnonnull     16
        14: aconst_null
        15: athrow
        16: astore_3
        17: aload_3
        18: invokevirtual #138                // Method scala/Option.isEmpty:()Z
        21: ifeq          33
        24: aload_2
        25: invokeinterface #141,  1          // InterfaceMethod scala/Function0.apply:()Ljava/lang/Object;
        30: goto          37
        33: aload_3
        34: invokevirtual #144                // Method scala/Option.get:()Ljava/lang/Object;
        37: checkcast     #116                // class java/lang/String
        40: areturn
      StackMapTable: number_of_entries = 3
        frame_type = 80 /* same_locals_1_stack_item */
          stack = [ class scala/Option ]
        frame_type = 252 /* append */
          offset_delta = 16
          locals = [ class scala/Option ]
        frame_type = 67 /* same_locals_1_stack_item */
          stack = [ class java/lang/Object ]
      LineNumberTable:
        line 64: 0
      LocalVariableTable:
        Start  Length  Slot  Name   Signature
            0      41     0  this   Lscala/util/PropertiesTrait;
            0      41     1  name   Ljava/lang/String;
            0      41     2   alt   Lscala/Function0;
           17      20     3 getOrElse_this   Lscala/Option;
    Signature: #124                         // (Ljava/lang/String;Lscala/Function0<Ljava/lang/String;>;)Ljava/lang/String;
    MethodParameters:
      Name                           Flags
      name                           final
      alt                            final

  public static scala.Option envOrNone$(scala.util.PropertiesTrait, java.lang.String);
    descriptor: (Lscala/util/PropertiesTrait;Ljava/lang/String;)Lscala/Option;
    flags: (0x1009) ACC_PUBLIC, ACC_STATIC, ACC_SYNTHETIC
    Code:
      stack=2, locals=2, args_size=2
         0: aload_0
         1: aload_1
         2: invokespecial #219                // InterfaceMethod envOrNone:(Ljava/lang/String;)Lscala/Option;
         5: areturn
      LineNumberTable:
        line 65: 0
      LocalVariableTable:
        Start  Length  Slot  Name   Signature
            0       6     0 $this   Lscala/util/PropertiesTrait;
            0       6     1  name   Ljava/lang/String;
    MethodParameters:
      Name                           Flags
      $this                          final synthetic
      name                           final

  public default scala.Option<java.lang.String> envOrNone(java.lang.String);
    descriptor: (Ljava/lang/String;)Lscala/Option;
    flags: (0x0001) ACC_PUBLIC
    Code:
      stack=2, locals=2, args_size=2
         0: getstatic     #130                // Field scala/Option$.MODULE$:Lscala/Option$;
         3: aload_1
         4: invokestatic  #215                // Method java/lang/System.getenv:(Ljava/lang/String;)Ljava/lang/String;
         7: invokevirtual #134                // Method scala/Option$.apply:(Ljava/lang/Object;)Lscala/Option;
        10: areturn
      LineNumberTable:
        line 65: 0
      LocalVariableTable:
        Start  Length  Slot  Name   Signature
            0      11     0  this   Lscala/util/PropertiesTrait;
            0      11     1  name   Ljava/lang/String;
    Signature: #184                         // (Ljava/lang/String;)Lscala/Option<Ljava/lang/String;>;
    MethodParameters:
      Name                           Flags
      name                           final

  public static scala.Option envOrSome$(scala.util.PropertiesTrait, java.lang.String, scala.Function0);
    descriptor: (Lscala/util/PropertiesTrait;Ljava/lang/String;Lscala/Function0;)Lscala/Option;
    flags: (0x1009) ACC_PUBLIC, ACC_STATIC, ACC_SYNTHETIC
    Code:
      stack=3, locals=3, args_size=3
         0: aload_0
         1: aload_1
         2: aload_2
         3: invokespecial #225                // InterfaceMethod envOrSome:(Ljava/lang/String;Lscala/Function0;)Lscala/Option;
         6: areturn
      LineNumberTable:
        line 67: 0
      LocalVariableTable:
        Start  Length  Slot  Name   Signature
            0       7     0 $this   Lscala/util/PropertiesTrait;
            0       7     1  name   Ljava/lang/String;
            0       7     2   alt   Lscala/Function0;
    MethodParameters:
      Name                           Flags
      $this                          final synthetic
      name                           final
      alt                            final

  public default scala.Option<java.lang.String> envOrSome(java.lang.String, scala.Function0<scala.Option<java.lang.String>>);
    descriptor: (Ljava/lang/String;Lscala/Function0;)Lscala/Option;
    flags: (0x0001) ACC_PUBLIC
    Code:
      stack=2, locals=4, args_size=3
         0: aload_0
         1: aload_1
         2: invokeinterface #219,  2          // InterfaceMethod envOrNone:(Ljava/lang/String;)Lscala/Option;
         7: dup
         8: ifnonnull     13
        11: aconst_null
        12: athrow
        13: astore_3
        14: aload_3
        15: invokevirtual #138                // Method scala/Option.isEmpty:()Z
        18: ifeq          31
        21: aload_2
        22: invokeinterface #141,  1          // InterfaceMethod scala/Function0.apply:()Ljava/lang/Object;
        27: checkcast     #17                 // class scala/Option
        30: areturn
        31: aload_3
        32: areturn
      StackMapTable: number_of_entries = 2
        frame_type = 77 /* same_locals_1_stack_item */
          stack = [ class scala/Option ]
        frame_type = 252 /* append */
          offset_delta = 17
          locals = [ class scala/Option ]
      LineNumberTable:
        line 67: 0
      LocalVariableTable:
        Start  Length  Slot  Name   Signature
            0      33     0  this   Lscala/util/PropertiesTrait;
            0      33     1  name   Ljava/lang/String;
            0      33     2   alt   Lscala/Function0;
           14      18     3 orElse_this   Lscala/Option;
    Signature: #226                         // (Ljava/lang/String;Lscala/Function0<Lscala/Option<Ljava/lang/String;>;>;)Lscala/Option<Ljava/lang/String;>;
    MethodParameters:
      Name                           Flags
      name                           final
      alt                            final

  public static java.lang.String scalaPropOrElse$(scala.util.PropertiesTrait, java.lang.String, scala.Function0);
    descriptor: (Lscala/util/PropertiesTrait;Ljava/lang/String;Lscala/Function0;)Ljava/lang/String;
    flags: (0x1009) ACC_PUBLIC, ACC_STATIC, ACC_SYNTHETIC
    Code:
      stack=3, locals=3, args_size=3
         0: aload_0
         1: aload_1
         2: aload_2
         3: invokespecial #231                // InterfaceMethod scalaPropOrElse:(Ljava/lang/String;Lscala/Function0;)Ljava/lang/String;
         6: areturn
      LineNumberTable:
        line 70: 0
      LocalVariableTable:
        Start  Length  Slot  Name   Signature
            0       7     0 $this   Lscala/util/PropertiesTrait;
            0       7     1  name   Ljava/lang/String;
            0       7     2   alt   Lscala/Function0;
    MethodParameters:
      Name                           Flags
      $this                          final synthetic
      name                           final
      alt                            final

  public default java.lang.String scalaPropOrElse(java.lang.String, scala.Function0<java.lang.String>);
    descriptor: (Ljava/lang/String;Lscala/Function0;)Ljava/lang/String;
    flags: (0x0001) ACC_PUBLIC
    Code:
      stack=2, locals=4, args_size=3
         0: aload_0
         1: aload_1
         2: invokeinterface #234,  2          // InterfaceMethod scalaPropOrNone:(Ljava/lang/String;)Lscala/Option;
         7: dup
         8: ifnonnull     13
        11: aconst_null
        12: athrow
        13: astore_3
        14: aload_3
        15: invokevirtual #138                // Method scala/Option.isEmpty:()Z
        18: ifeq          30
        21: aload_2
        22: invokeinterface #141,  1          // InterfaceMethod scala/Function0.apply:()Ljava/lang/Object;
        27: goto          34
        30: aload_3
        31: invokevirtual #144                // Method scala/Option.get:()Ljava/lang/Object;
        34: checkcast     #116                // class java/lang/String
        37: areturn
      StackMapTable: number_of_entries = 3
        frame_type = 77 /* same_locals_1_stack_item */
          stack = [ class scala/Option ]
        frame_type = 252 /* append */
          offset_delta = 16
          locals = [ class scala/Option ]
        frame_type = 67 /* same_locals_1_stack_item */
          stack = [ class java/lang/Object ]
      LineNumberTable:
        line 70: 0
      LocalVariableTable:
        Start  Length  Slot  Name   Signature
            0      38     0  this   Lscala/util/PropertiesTrait;
            0      38     1  name   Ljava/lang/String;
            0      38     2   alt   Lscala/Function0;
           14      20     3 getOrElse_this   Lscala/Option;
    Signature: #124                         // (Ljava/lang/String;Lscala/Function0<Ljava/lang/String;>;)Ljava/lang/String;
    MethodParameters:
      Name                           Flags
      name                           final
      alt                            final

  public static java.lang.String scalaPropOrEmpty$(scala.util.PropertiesTrait, java.lang.String);
    descriptor: (Lscala/util/PropertiesTrait;Ljava/lang/String;)Ljava/lang/String;
    flags: (0x1009) ACC_PUBLIC, ACC_STATIC, ACC_SYNTHETIC
    Code:
      stack=2, locals=2, args_size=2
         0: aload_0
         1: aload_1
         2: invokespecial #238                // InterfaceMethod scalaPropOrEmpty:(Ljava/lang/String;)Ljava/lang/String;
         5: areturn
      LineNumberTable:
        line 71: 0
      LocalVariableTable:
        Start  Length  Slot  Name   Signature
            0       6     0 $this   Lscala/util/PropertiesTrait;
            0       6     1  name   Ljava/lang/String;
    MethodParameters:
      Name                           Flags
      $this                          final synthetic
      name                           final

  public default java.lang.String scalaPropOrEmpty(java.lang.String);
    descriptor: (Ljava/lang/String;)Ljava/lang/String;
    flags: (0x0001) ACC_PUBLIC
    Code:
      stack=3, locals=2, args_size=2
         0: aload_0
         1: aload_1
         2: invokedynamic #243,  0            // InvokeDynamic #2:apply:()Lscala/Function0;
         7: invokeinterface #231,  3          // InterfaceMethod scalaPropOrElse:(Ljava/lang/String;Lscala/Function0;)Ljava/lang/String;
        12: areturn
      LineNumberTable:
        line 71: 0
      LocalVariableTable:
        Start  Length  Slot  Name   Signature
            0      13     0  this   Lscala/util/PropertiesTrait;
            0      13     1  name   Ljava/lang/String;
    MethodParameters:
      Name                           Flags
      name                           final

  public static scala.Option scalaPropOrNone$(scala.util.PropertiesTrait, java.lang.String);
    descriptor: (Lscala/util/PropertiesTrait;Ljava/lang/String;)Lscala/Option;
    flags: (0x1009) ACC_PUBLIC, ACC_STATIC, ACC_SYNTHETIC
    Code:
      stack=2, locals=2, args_size=2
         0: aload_0
         1: aload_1
         2: invokespecial #234                // InterfaceMethod scalaPropOrNone:(Ljava/lang/String;)Lscala/Option;
         5: areturn
      LineNumberTable:
        line 72: 0
      LocalVariableTable:
        Start  Length  Slot  Name   Signature
            0       6     0 $this   Lscala/util/PropertiesTrait;
            0       6     1  name   Ljava/lang/String;
    MethodParameters:
      Name                           Flags
      $this                          final synthetic
      name                           final

  public default scala.Option<java.lang.String> scalaPropOrNone(java.lang.String);
    descriptor: (Ljava/lang/String;)Lscala/Option;
    flags: (0x0001) ACC_PUBLIC
    Code:
      stack=3, locals=3, args_size=2
         0: getstatic     #130                // Field scala/Option$.MODULE$:Lscala/Option$;
         3: aload_0
         4: invokeinterface #40,  1           // InterfaceMethod scalaProps:()Ljava/util/Properties;
         9: aload_1
        10: invokevirtual #245                // Method java/util/Properties.getProperty:(Ljava/lang/String;)Ljava/lang/String;
        13: invokevirtual #134                // Method scala/Option$.apply:(Ljava/lang/Object;)Lscala/Option;
        16: dup
        17: ifnonnull     22
        20: aconst_null
        21: athrow
        22: astore_2
        23: aload_2
        24: invokevirtual #138                // Method scala/Option.isEmpty:()Z
        27: ifeq          36
        30: aload_0
        31: aload_1
        32: invokestatic  #248                // InterfaceMethod $anonfun$scalaPropOrNone$1:(Lscala/util/PropertiesTrait;Ljava/lang/String;)Lscala/Option;
        35: areturn
        36: aload_2
        37: areturn
      StackMapTable: number_of_entries = 2
        frame_type = 86 /* same_locals_1_stack_item */
          stack = [ class scala/Option ]
        frame_type = 252 /* append */
          offset_delta = 13
          locals = [ class scala/Option ]
      LineNumberTable:
        line 72: 0
      LocalVariableTable:
        Start  Length  Slot  Name   Signature
            0      38     0  this   Lscala/util/PropertiesTrait;
            0      38     1  name   Ljava/lang/String;
           23      14     2 orElse_this   Lscala/Option;
    Signature: #184                         // (Ljava/lang/String;)Lscala/Option<Ljava/lang/String;>;
    MethodParameters:
      Name                           Flags
      name                           final

  public abstract scala.Option<java.lang.String> releaseVersion();
    descriptor: ()Lscala/Option;
    flags: (0x0401) ACC_PUBLIC, ACC_ABSTRACT
    Signature: #251                         // ()Lscala/Option<Ljava/lang/String;>;

  public abstract scala.Option<java.lang.String> developmentVersion();
    descriptor: ()Lscala/Option;
    flags: (0x0401) ACC_PUBLIC, ACC_ABSTRACT
    Signature: #251                         // ()Lscala/Option<Ljava/lang/String;>;

  public static java.lang.String versionNumberString$(scala.util.PropertiesTrait);
    descriptor: (Lscala/util/PropertiesTrait;)Ljava/lang/String;
    flags: (0x1009) ACC_PUBLIC, ACC_STATIC, ACC_SYNTHETIC
    Code:
      stack=1, locals=1, args_size=1
         0: aload_0
         1: invokespecial #257                // InterfaceMethod versionNumberString:()Ljava/lang/String;
         4: areturn
      LineNumberTable:
        line 106: 0
      LocalVariableTable:
        Start  Length  Slot  Name   Signature
            0       5     0 $this   Lscala/util/PropertiesTrait;
    MethodParameters:
      Name                           Flags
      $this                          final synthetic

  public default java.lang.String versionNumberString();
    descriptor: ()Ljava/lang/String;
    flags: (0x0001) ACC_PUBLIC
    Code:
      stack=2, locals=1, args_size=1
         0: aload_0
         1: ldc_w         #259                // String version.number
         4: invokeinterface #238,  2          // InterfaceMethod scalaPropOrEmpty:(Ljava/lang/String;)Ljava/lang/String;
         9: areturn
      LineNumberTable:
        line 106: 0
      LocalVariableTable:
        Start  Length  Slot  Name   Signature
            0      10     0  this   Lscala/util/PropertiesTrait;

  public abstract java.lang.String versionString();
    descriptor: ()Ljava/lang/String;
    flags: (0x0401) ACC_PUBLIC, ACC_ABSTRACT

  public abstract java.lang.String copyrightString();
    descriptor: ()Ljava/lang/String;
    flags: (0x0401) ACC_PUBLIC, ACC_ABSTRACT

  public static java.lang.String sourceEncoding$(scala.util.PropertiesTrait);
    descriptor: (Lscala/util/PropertiesTrait;)Ljava/lang/String;
    flags: (0x1009) ACC_PUBLIC, ACC_STATIC, ACC_SYNTHETIC
    Code:
      stack=1, locals=1, args_size=1
         0: aload_0
         1: invokespecial #265                // InterfaceMethod sourceEncoding:()Ljava/lang/String;
         4: areturn
      LineNumberTable:
        line 117: 0
      LocalVariableTable:
        Start  Length  Slot  Name   Signature
            0       5     0 $this   Lscala/util/PropertiesTrait;
    MethodParameters:
      Name                           Flags
      $this                          final synthetic

  public default java.lang.String sourceEncoding();
    descriptor: ()Ljava/lang/String;
    flags: (0x0001) ACC_PUBLIC
    Code:
      stack=3, locals=1, args_size=1
         0: aload_0
         1: ldc_w         #267                // String file.encoding
         4: invokedynamic #272,  0            // InvokeDynamic #3:apply:()Lscala/Function0;
         9: invokeinterface #231,  3          // InterfaceMethod scalaPropOrElse:(Ljava/lang/String;Lscala/Function0;)Ljava/lang/String;
        14: areturn
      LineNumberTable:
        line 117: 0
      LocalVariableTable:
        Start  Length  Slot  Name   Signature
            0      15     0  this   Lscala/util/PropertiesTrait;

  public static java.lang.String sourceReader$(scala.util.PropertiesTrait);
    descriptor: (Lscala/util/PropertiesTrait;)Ljava/lang/String;
    flags: (0x1009) ACC_PUBLIC, ACC_STATIC, ACC_SYNTHETIC
    Code:
      stack=1, locals=1, args_size=1
         0: aload_0
         1: invokespecial #276                // InterfaceMethod sourceReader:()Ljava/lang/String;
         4: areturn
      LineNumberTable:
        line 118: 0
      LocalVariableTable:
        Start  Length  Slot  Name   Signature
            0       5     0 $this   Lscala/util/PropertiesTrait;
    MethodParameters:
      Name                           Flags
      $this                          final synthetic

  public default java.lang.String sourceReader();
    descriptor: ()Ljava/lang/String;
    flags: (0x0001) ACC_PUBLIC
    Code:
      stack=3, locals=1, args_size=1
         0: aload_0
         1: ldc_w         #278                // String source.reader
         4: invokedynamic #283,  0            // InvokeDynamic #4:apply:()Lscala/Function0;
         9: invokeinterface #231,  3          // InterfaceMethod scalaPropOrElse:(Ljava/lang/String;Lscala/Function0;)Ljava/lang/String;
        14: areturn
      LineNumberTable:
        line 118: 0
      LocalVariableTable:
        Start  Length  Slot  Name   Signature
            0      15     0  this   Lscala/util/PropertiesTrait;

  public static java.lang.String encodingString$(scala.util.PropertiesTrait);
    descriptor: (Lscala/util/PropertiesTrait;)Ljava/lang/String;
    flags: (0x1009) ACC_PUBLIC, ACC_STATIC, ACC_SYNTHETIC
    Code:
      stack=1, locals=1, args_size=1
         0: aload_0
         1: invokespecial #287                // InterfaceMethod encodingString:()Ljava/lang/String;
         4: areturn
      LineNumberTable:
        line 123: 0
      LocalVariableTable:
        Start  Length  Slot  Name   Signature
            0       5     0 $this   Lscala/util/PropertiesTrait;
    MethodParameters:
      Name                           Flags
      $this                          final synthetic

  public default java.lang.String encodingString();
    descriptor: ()Ljava/lang/String;
    flags: (0x0001) ACC_PUBLIC
    Code:
      stack=3, locals=1, args_size=1
         0: aload_0
         1: ldc_w         #267                // String file.encoding
         4: invokedynamic #292,  0            // InvokeDynamic #5:apply:()Lscala/Function0;
         9: invokeinterface #123,  3          // InterfaceMethod propOrElse:(Ljava/lang/String;Lscala/Function0;)Ljava/lang/String;
        14: areturn
      LineNumberTable:
        line 123: 0
      LocalVariableTable:
        Start  Length  Slot  Name   Signature
            0      15     0  this   Lscala/util/PropertiesTrait;

  public static java.lang.String lineSeparator$(scala.util.PropertiesTrait);
    descriptor: (Lscala/util/PropertiesTrait;)Ljava/lang/String;
    flags: (0x1009) ACC_PUBLIC, ACC_STATIC, ACC_SYNTHETIC
    Code:
      stack=1, locals=1, args_size=1
         0: aload_0
         1: invokespecial #296                // InterfaceMethod lineSeparator:()Ljava/lang/String;
         4: areturn
      LineNumberTable:
        line 127: 0
      LocalVariableTable:
        Start  Length  Slot  Name   Signature
            0       5     0 $this   Lscala/util/PropertiesTrait;
    MethodParameters:
      Name                           Flags
      $this                          final synthetic

  public default java.lang.String lineSeparator();
    descriptor: ()Ljava/lang/String;
    flags: (0x0001) ACC_PUBLIC
    Code:
      stack=1, locals=1, args_size=1
         0: invokestatic  #297                // Method java/lang/System.lineSeparator:()Ljava/lang/String;
         3: areturn
      LineNumberTable:
        line 127: 0
      LocalVariableTable:
        Start  Length  Slot  Name   Signature
            0       4     0  this   Lscala/util/PropertiesTrait;

  public static java.lang.String javaClassPath$(scala.util.PropertiesTrait);
    descriptor: (Lscala/util/PropertiesTrait;)Ljava/lang/String;
    flags: (0x1009) ACC_PUBLIC, ACC_STATIC, ACC_SYNTHETIC
    Code:
      stack=1, locals=1, args_size=1
         0: aload_0
         1: invokespecial #301                // InterfaceMethod javaClassPath:()Ljava/lang/String;
         4: areturn
      LineNumberTable:
        line 130: 0
      LocalVariableTable:
        Start  Length  Slot  Name   Signature
            0       5     0 $this   Lscala/util/PropertiesTrait;
    MethodParameters:
      Name                           Flags
      $this                          final synthetic

  public default java.lang.String javaClassPath();
    descriptor: ()Ljava/lang/String;
    flags: (0x0001) ACC_PUBLIC
    Code:
      stack=2, locals=1, args_size=1
         0: aload_0
         1: ldc_w         #303                // String java.class.path
         4: invokeinterface #151,  2          // InterfaceMethod propOrEmpty:(Ljava/lang/String;)Ljava/lang/String;
         9: areturn
      LineNumberTable:
        line 130: 0
      LocalVariableTable:
        Start  Length  Slot  Name   Signature
            0      10     0  this   Lscala/util/PropertiesTrait;

  public static java.lang.String javaHome$(scala.util.PropertiesTrait);
    descriptor: (Lscala/util/PropertiesTrait;)Ljava/lang/String;
    flags: (0x1009) ACC_PUBLIC, ACC_STATIC, ACC_SYNTHETIC
    Code:
      stack=1, locals=1, args_size=1
         0: aload_0
         1: invokespecial #307                // InterfaceMethod javaHome:()Ljava/lang/String;
         4: areturn
      LineNumberTable:
        line 131: 0
      LocalVariableTable:
        Start  Length  Slot  Name   Signature
            0       5     0 $this   Lscala/util/PropertiesTrait;
    MethodParameters:
      Name                           Flags
      $this                          final synthetic

  public default java.lang.String javaHome();
    descriptor: ()Ljava/lang/String;
    flags: (0x0001) ACC_PUBLIC
    Code:
      stack=2, locals=1, args_size=1
         0: aload_0
         1: ldc_w         #309                // String java.home
         4: invokeinterface #151,  2          // InterfaceMethod propOrEmpty:(Ljava/lang/String;)Ljava/lang/String;
         9: areturn
      LineNumberTable:
        line 131: 0
      LocalVariableTable:
        Start  Length  Slot  Name   Signature
            0      10     0  this   Lscala/util/PropertiesTrait;

  public static java.lang.String javaVendor$(scala.util.PropertiesTrait);
    descriptor: (Lscala/util/PropertiesTrait;)Ljava/lang/String;
    flags: (0x1009) ACC_PUBLIC, ACC_STATIC, ACC_SYNTHETIC
    Code:
      stack=1, locals=1, args_size=1
         0: aload_0
         1: invokespecial #313                // InterfaceMethod javaVendor:()Ljava/lang/String;
         4: areturn
      LineNumberTable:
        line 132: 0
      LocalVariableTable:
        Start  Length  Slot  Name   Signature
            0       5     0 $this   Lscala/util/PropertiesTrait;
    MethodParameters:
      Name                           Flags
      $this                          final synthetic

  public default java.lang.String javaVendor();
    descriptor: ()Ljava/lang/String;
    flags: (0x0001) ACC_PUBLIC
    Code:
      stack=2, locals=1, args_size=1
         0: aload_0
         1: ldc_w         #315                // String java.vendor
         4: invokeinterface #151,  2          // InterfaceMethod propOrEmpty:(Ljava/lang/String;)Ljava/lang/String;
         9: areturn
      LineNumberTable:
        line 132: 0
      LocalVariableTable:
        Start  Length  Slot  Name   Signature
            0      10     0  this   Lscala/util/PropertiesTrait;

  public static java.lang.String javaVersion$(scala.util.PropertiesTrait);
    descriptor: (Lscala/util/PropertiesTrait;)Ljava/lang/String;
    flags: (0x1009) ACC_PUBLIC, ACC_STATIC, ACC_SYNTHETIC
    Code:
      stack=1, locals=1, args_size=1
         0: aload_0
         1: invokespecial #319                // InterfaceMethod javaVersion:()Ljava/lang/String;
         4: areturn
      LineNumberTable:
        line 133: 0
      LocalVariableTable:
        Start  Length  Slot  Name   Signature
            0       5     0 $this   Lscala/util/PropertiesTrait;
    MethodParameters:
      Name                           Flags
      $this                          final synthetic

  public default java.lang.String javaVersion();
    descriptor: ()Ljava/lang/String;
    flags: (0x0001) ACC_PUBLIC
    Code:
      stack=2, locals=1, args_size=1
         0: aload_0
         1: ldc_w         #321                // String java.version
         4: invokeinterface #151,  2          // InterfaceMethod propOrEmpty:(Ljava/lang/String;)Ljava/lang/String;
         9: areturn
      LineNumberTable:
        line 133: 0
      LocalVariableTable:
        Start  Length  Slot  Name   Signature
            0      10     0  this   Lscala/util/PropertiesTrait;

  public static java.lang.String javaVmInfo$(scala.util.PropertiesTrait);
    descriptor: (Lscala/util/PropertiesTrait;)Ljava/lang/String;
    flags: (0x1009) ACC_PUBLIC, ACC_STATIC, ACC_SYNTHETIC
    Code:
      stack=1, locals=1, args_size=1
         0: aload_0
         1: invokespecial #325                // InterfaceMethod javaVmInfo:()Ljava/lang/String;
         4: areturn
      LineNumberTable:
        line 134: 0
      LocalVariableTable:
        Start  Length  Slot  Name   Signature
            0       5     0 $this   Lscala/util/PropertiesTrait;
    MethodParameters:
      Name                           Flags
      $this                          final synthetic

  public default java.lang.String javaVmInfo();
    descriptor: ()Ljava/lang/String;
    flags: (0x0001) ACC_PUBLIC
    Code:
      stack=2, locals=1, args_size=1
         0: aload_0
         1: ldc_w         #327                // String java.vm.info
         4: invokeinterface #151,  2          // InterfaceMethod propOrEmpty:(Ljava/lang/String;)Ljava/lang/String;
         9: areturn
      LineNumberTable:
        line 134: 0
      LocalVariableTable:
        Start  Length  Slot  Name   Signature
            0      10     0  this   Lscala/util/PropertiesTrait;

  public static java.lang.String javaVmName$(scala.util.PropertiesTrait);
    descriptor: (Lscala/util/PropertiesTrait;)Ljava/lang/String;
    flags: (0x1009) ACC_PUBLIC, ACC_STATIC, ACC_SYNTHETIC
    Code:
      stack=1, locals=1, args_size=1
         0: aload_0
         1: invokespecial #331                // InterfaceMethod javaVmName:()Ljava/lang/String;
         4: areturn
      LineNumberTable:
        line 135: 0
      LocalVariableTable:
        Start  Length  Slot  Name   Signature
            0       5     0 $this   Lscala/util/PropertiesTrait;
    MethodParameters:
      Name                           Flags
      $this                          final synthetic

  public default java.lang.String javaVmName();
    descriptor: ()Ljava/lang/String;
    flags: (0x0001) ACC_PUBLIC
    Code:
      stack=2, locals=1, args_size=1
         0: aload_0
         1: ldc_w         #333                // String java.vm.name
         4: invokeinterface #151,  2          // InterfaceMethod propOrEmpty:(Ljava/lang/String;)Ljava/lang/String;
         9: areturn
      LineNumberTable:
        line 135: 0
      LocalVariableTable:
        Start  Length  Slot  Name   Signature
            0      10     0  this   Lscala/util/PropertiesTrait;

  public static java.lang.String javaVmVendor$(scala.util.PropertiesTrait);
    descriptor: (Lscala/util/PropertiesTrait;)Ljava/lang/String;
    flags: (0x1009) ACC_PUBLIC, ACC_STATIC, ACC_SYNTHETIC
    Code:
      stack=1, locals=1, args_size=1
         0: aload_0
         1: invokespecial #337                // InterfaceMethod javaVmVendor:()Ljava/lang/String;
         4: areturn
      LineNumberTable:
        line 136: 0
      LocalVariableTable:
        Start  Length  Slot  Name   Signature
            0       5     0 $this   Lscala/util/PropertiesTrait;
    MethodParameters:
      Name                           Flags
      $this                          final synthetic

  public default java.lang.String javaVmVendor();
    descriptor: ()Ljava/lang/String;
    flags: (0x0001) ACC_PUBLIC
    Code:
      stack=2, locals=1, args_size=1
         0: aload_0
         1: ldc_w         #339                // String java.vm.vendor
         4: invokeinterface #151,  2          // InterfaceMethod propOrEmpty:(Ljava/lang/String;)Ljava/lang/String;
         9: areturn
      LineNumberTable:
        line 136: 0
      LocalVariableTable:
        Start  Length  Slot  Name   Signature
            0      10     0  this   Lscala/util/PropertiesTrait;

  public static java.lang.String javaVmVersion$(scala.util.PropertiesTrait);
    descriptor: (Lscala/util/PropertiesTrait;)Ljava/lang/String;
    flags: (0x1009) ACC_PUBLIC, ACC_STATIC, ACC_SYNTHETIC
    Code:
      stack=1, locals=1, args_size=1
         0: aload_0
         1: invokespecial #343                // InterfaceMethod javaVmVersion:()Ljava/lang/String;
         4: areturn
      LineNumberTable:
        line 137: 0
      LocalVariableTable:
        Start  Length  Slot  Name   Signature
            0       5     0 $this   Lscala/util/PropertiesTrait;
    MethodParameters:
      Name                           Flags
      $this                          final synthetic

  public default java.lang.String javaVmVersion();
    descriptor: ()Ljava/lang/String;
    flags: (0x0001) ACC_PUBLIC
    Code:
      stack=2, locals=1, args_size=1
         0: aload_0
         1: ldc_w         #345                // String java.vm.version
         4: invokeinterface #151,  2          // InterfaceMethod propOrEmpty:(Ljava/lang/String;)Ljava/lang/String;
         9: areturn
      LineNumberTable:
        line 137: 0
      LocalVariableTable:
        Start  Length  Slot  Name   Signature
            0      10     0  this   Lscala/util/PropertiesTrait;

  public static java.lang.String javaSpecVersion$(scala.util.PropertiesTrait);
    descriptor: (Lscala/util/PropertiesTrait;)Ljava/lang/String;
    flags: (0x1009) ACC_PUBLIC, ACC_STATIC, ACC_SYNTHETIC
    Code:
      stack=1, locals=1, args_size=1
         0: aload_0
         1: invokespecial #349                // InterfaceMethod javaSpecVersion:()Ljava/lang/String;
         4: areturn
      LineNumberTable:
        line 138: 0
      LocalVariableTable:
        Start  Length  Slot  Name   Signature
            0       5     0 $this   Lscala/util/PropertiesTrait;
    MethodParameters:
      Name                           Flags
      $this                          final synthetic

  public default java.lang.String javaSpecVersion();
    descriptor: ()Ljava/lang/String;
    flags: (0x0001) ACC_PUBLIC
    Code:
      stack=2, locals=1, args_size=1
         0: aload_0
         1: ldc_w         #351                // String java.specification.version
         4: invokeinterface #151,  2          // InterfaceMethod propOrEmpty:(Ljava/lang/String;)Ljava/lang/String;
         9: areturn
      LineNumberTable:
        line 138: 0
      LocalVariableTable:
        Start  Length  Slot  Name   Signature
            0      10     0  this   Lscala/util/PropertiesTrait;

  public static java.lang.String javaSpecVendor$(scala.util.PropertiesTrait);
    descriptor: (Lscala/util/PropertiesTrait;)Ljava/lang/String;
    flags: (0x1009) ACC_PUBLIC, ACC_STATIC, ACC_SYNTHETIC
    Code:
      stack=1, locals=1, args_size=1
         0: aload_0
         1: invokespecial #355                // InterfaceMethod javaSpecVendor:()Ljava/lang/String;
         4: areturn
      LineNumberTable:
        line 139: 0
      LocalVariableTable:
        Start  Length  Slot  Name   Signature
            0       5     0 $this   Lscala/util/PropertiesTrait;
    MethodParameters:
      Name                           Flags
      $this                          final synthetic

  public default java.lang.String javaSpecVendor();
    descriptor: ()Ljava/lang/String;
    flags: (0x0001) ACC_PUBLIC
    Code:
      stack=2, locals=1, args_size=1
         0: aload_0
         1: ldc_w         #357                // String java.specification.vendor
         4: invokeinterface #151,  2          // InterfaceMethod propOrEmpty:(Ljava/lang/String;)Ljava/lang/String;
         9: areturn
      LineNumberTable:
        line 139: 0
      LocalVariableTable:
        Start  Length  Slot  Name   Signature
            0      10     0  this   Lscala/util/PropertiesTrait;

  public static java.lang.String javaSpecName$(scala.util.PropertiesTrait);
    descriptor: (Lscala/util/PropertiesTrait;)Ljava/lang/String;
    flags: (0x1009) ACC_PUBLIC, ACC_STATIC, ACC_SYNTHETIC
    Code:
      stack=1, locals=1, args_size=1
         0: aload_0
         1: invokespecial #361                // InterfaceMethod javaSpecName:()Ljava/lang/String;
         4: areturn
      LineNumberTable:
        line 140: 0
      LocalVariableTable:
        Start  Length  Slot  Name   Signature
            0       5     0 $this   Lscala/util/PropertiesTrait;
    MethodParameters:
      Name                           Flags
      $this                          final synthetic

  public default java.lang.String javaSpecName();
    descriptor: ()Ljava/lang/String;
    flags: (0x0001) ACC_PUBLIC
    Code:
      stack=2, locals=1, args_size=1
         0: aload_0
         1: ldc_w         #363                // String java.specification.name
         4: invokeinterface #151,  2          // InterfaceMethod propOrEmpty:(Ljava/lang/String;)Ljava/lang/String;
         9: areturn
      LineNumberTable:
        line 140: 0
      LocalVariableTable:
        Start  Length  Slot  Name   Signature
            0      10     0  this   Lscala/util/PropertiesTrait;

  public static java.lang.String osName$(scala.util.PropertiesTrait);
    descriptor: (Lscala/util/PropertiesTrait;)Ljava/lang/String;
    flags: (0x1009) ACC_PUBLIC, ACC_STATIC, ACC_SYNTHETIC
    Code:
      stack=1, locals=1, args_size=1
         0: aload_0
         1: invokespecial #367                // InterfaceMethod osName:()Ljava/lang/String;
         4: areturn
      LineNumberTable:
        line 141: 0
      LocalVariableTable:
        Start  Length  Slot  Name   Signature
            0       5     0 $this   Lscala/util/PropertiesTrait;
    MethodParameters:
      Name                           Flags
      $this                          final synthetic

  public default java.lang.String osName();
    descriptor: ()Ljava/lang/String;
    flags: (0x0001) ACC_PUBLIC
    Code:
      stack=2, locals=1, args_size=1
         0: aload_0
         1: ldc_w         #369                // String os.name
         4: invokeinterface #151,  2          // InterfaceMethod propOrEmpty:(Ljava/lang/String;)Ljava/lang/String;
         9: areturn
      LineNumberTable:
        line 141: 0
      LocalVariableTable:
        Start  Length  Slot  Name   Signature
            0      10     0  this   Lscala/util/PropertiesTrait;

  public static java.lang.String scalaHome$(scala.util.PropertiesTrait);
    descriptor: (Lscala/util/PropertiesTrait;)Ljava/lang/String;
    flags: (0x1009) ACC_PUBLIC, ACC_STATIC, ACC_SYNTHETIC
    Code:
      stack=1, locals=1, args_size=1
         0: aload_0
         1: invokespecial #373                // InterfaceMethod scalaHome:()Ljava/lang/String;
         4: areturn
      LineNumberTable:
        line 142: 0
      LocalVariableTable:
        Start  Length  Slot  Name   Signature
            0       5     0 $this   Lscala/util/PropertiesTrait;
    MethodParameters:
      Name                           Flags
      $this                          final synthetic

  public default java.lang.String scalaHome();
    descriptor: ()Ljava/lang/String;
    flags: (0x0001) ACC_PUBLIC
    Code:
      stack=2, locals=1, args_size=1
         0: aload_0
         1: ldc_w         #375                // String scala.home
         4: invokeinterface #151,  2          // InterfaceMethod propOrEmpty:(Ljava/lang/String;)Ljava/lang/String;
         9: areturn
      LineNumberTable:
        line 142: 0
      LocalVariableTable:
        Start  Length  Slot  Name   Signature
            0      10     0  this   Lscala/util/PropertiesTrait;

  public static java.lang.String tmpDir$(scala.util.PropertiesTrait);
    descriptor: (Lscala/util/PropertiesTrait;)Ljava/lang/String;
    flags: (0x1009) ACC_PUBLIC, ACC_STATIC, ACC_SYNTHETIC
    Code:
      stack=1, locals=1, args_size=1
         0: aload_0
         1: invokespecial #379                // InterfaceMethod tmpDir:()Ljava/lang/String;
         4: areturn
      LineNumberTable:
        line 143: 0
      LocalVariableTable:
        Start  Length  Slot  Name   Signature
            0       5     0 $this   Lscala/util/PropertiesTrait;
    MethodParameters:
      Name                           Flags
      $this                          final synthetic

  public default java.lang.String tmpDir();
    descriptor: ()Ljava/lang/String;
    flags: (0x0001) ACC_PUBLIC
    Code:
      stack=2, locals=1, args_size=1
         0: aload_0
         1: ldc_w         #381                // String java.io.tmpdir
         4: invokeinterface #151,  2          // InterfaceMethod propOrEmpty:(Ljava/lang/String;)Ljava/lang/String;
         9: areturn
      LineNumberTable:
        line 143: 0
      LocalVariableTable:
        Start  Length  Slot  Name   Signature
            0      10     0  this   Lscala/util/PropertiesTrait;

  public static java.lang.String userDir$(scala.util.PropertiesTrait);
    descriptor: (Lscala/util/PropertiesTrait;)Ljava/lang/String;
    flags: (0x1009) ACC_PUBLIC, ACC_STATIC, ACC_SYNTHETIC
    Code:
      stack=1, locals=1, args_size=1
         0: aload_0
         1: invokespecial #385                // InterfaceMethod userDir:()Ljava/lang/String;
         4: areturn
      LineNumberTable:
        line 144: 0
      LocalVariableTable:
        Start  Length  Slot  Name   Signature
            0       5     0 $this   Lscala/util/PropertiesTrait;
    MethodParameters:
      Name                           Flags
      $this                          final synthetic

  public default java.lang.String userDir();
    descriptor: ()Ljava/lang/String;
    flags: (0x0001) ACC_PUBLIC
    Code:
      stack=2, locals=1, args_size=1
         0: aload_0
         1: ldc_w         #387                // String user.dir
         4: invokeinterface #151,  2          // InterfaceMethod propOrEmpty:(Ljava/lang/String;)Ljava/lang/String;
         9: areturn
      LineNumberTable:
        line 144: 0
      LocalVariableTable:
        Start  Length  Slot  Name   Signature
            0      10     0  this   Lscala/util/PropertiesTrait;

  public static java.lang.String userHome$(scala.util.PropertiesTrait);
    descriptor: (Lscala/util/PropertiesTrait;)Ljava/lang/String;
    flags: (0x1009) ACC_PUBLIC, ACC_STATIC, ACC_SYNTHETIC
    Code:
      stack=1, locals=1, args_size=1
         0: aload_0
         1: invokespecial #391                // InterfaceMethod userHome:()Ljava/lang/String;
         4: areturn
      LineNumberTable:
        line 145: 0
      LocalVariableTable:
        Start  Length  Slot  Name   Signature
            0       5     0 $this   Lscala/util/PropertiesTrait;
    MethodParameters:
      Name                           Flags
      $this                          final synthetic

  public default java.lang.String userHome();
    descriptor: ()Ljava/lang/String;
    flags: (0x0001) ACC_PUBLIC
    Code:
      stack=2, locals=1, args_size=1
         0: aload_0
         1: ldc_w         #393                // String user.home
         4: invokeinterface #151,  2          // InterfaceMethod propOrEmpty:(Ljava/lang/String;)Ljava/lang/String;
         9: areturn
      LineNumberTable:
        line 145: 0
      LocalVariableTable:
        Start  Length  Slot  Name   Signature
            0      10     0  this   Lscala/util/PropertiesTrait;

  public static java.lang.String userName$(scala.util.PropertiesTrait);
    descriptor: (Lscala/util/PropertiesTrait;)Ljava/lang/String;
    flags: (0x1009) ACC_PUBLIC, ACC_STATIC, ACC_SYNTHETIC
    Code:
      stack=1, locals=1, args_size=1
         0: aload_0
         1: invokespecial #397                // InterfaceMethod userName:()Ljava/lang/String;
         4: areturn
      LineNumberTable:
        line 146: 0
      LocalVariableTable:
        Start  Length  Slot  Name   Signature
            0       5     0 $this   Lscala/util/PropertiesTrait;
    MethodParameters:
      Name                           Flags
      $this                          final synthetic

  public default java.lang.String userName();
    descriptor: ()Ljava/lang/String;
    flags: (0x0001) ACC_PUBLIC
    Code:
      stack=2, locals=1, args_size=1
         0: aload_0
         1: ldc_w         #399                // String user.name
         4: invokeinterface #151,  2          // InterfaceMethod propOrEmpty:(Ljava/lang/String;)Ljava/lang/String;
         9: areturn
      LineNumberTable:
        line 146: 0
      LocalVariableTable:
        Start  Length  Slot  Name   Signature
            0      10     0  this   Lscala/util/PropertiesTrait;

  public static boolean isWin$(scala.util.PropertiesTrait);
    descriptor: (Lscala/util/PropertiesTrait;)Z
    flags: (0x1009) ACC_PUBLIC, ACC_STATIC, ACC_SYNTHETIC
    Code:
      stack=1, locals=1, args_size=1
         0: aload_0
         1: invokespecial #404                // InterfaceMethod isWin:()Z
         4: ireturn
      LineNumberTable:
        line 150: 0
      LocalVariableTable:
        Start  Length  Slot  Name   Signature
            0       5     0 $this   Lscala/util/PropertiesTrait;
    MethodParameters:
      Name                           Flags
      $this                          final synthetic

  public default boolean isWin();
    descriptor: ()Z
    flags: (0x0001) ACC_PUBLIC
    Code:
      stack=2, locals=1, args_size=1
         0: aload_0
         1: invokeinterface #367,  1          // InterfaceMethod osName:()Ljava/lang/String;
         6: ldc_w         #406                // String Windows
         9: invokevirtual #409                // Method java/lang/String.startsWith:(Ljava/lang/String;)Z
        12: ireturn
      LineNumberTable:
        line 150: 0
      LocalVariableTable:
        Start  Length  Slot  Name   Signature
            0      13     0  this   Lscala/util/PropertiesTrait;

  public static boolean isMac$(scala.util.PropertiesTrait);
    descriptor: (Lscala/util/PropertiesTrait;)Z
    flags: (0x1009) ACC_PUBLIC, ACC_STATIC, ACC_SYNTHETIC
    Code:
      stack=1, locals=1, args_size=1
         0: aload_0
         1: invokespecial #413                // InterfaceMethod isMac:()Z
         4: ireturn
      LineNumberTable:
        line 154: 0
      LocalVariableTable:
        Start  Length  Slot  Name   Signature
            0       5     0 $this   Lscala/util/PropertiesTrait;
    MethodParameters:
      Name                           Flags
      $this                          final synthetic

  public default boolean isMac();
    descriptor: ()Z
    flags: (0x0001) ACC_PUBLIC
    Code:
      stack=2, locals=1, args_size=1
         0: aload_0
         1: invokeinterface #367,  1          // InterfaceMethod osName:()Ljava/lang/String;
         6: ldc_w         #415                // String Mac OS X
         9: invokevirtual #409                // Method java/lang/String.startsWith:(Ljava/lang/String;)Z
        12: ireturn
      LineNumberTable:
        line 154: 0
      LocalVariableTable:
        Start  Length  Slot  Name   Signature
            0      13     0  this   Lscala/util/PropertiesTrait;

  public static boolean isLinux$(scala.util.PropertiesTrait);
    descriptor: (Lscala/util/PropertiesTrait;)Z
    flags: (0x1009) ACC_PUBLIC, ACC_STATIC, ACC_SYNTHETIC
    Code:
      stack=1, locals=1, args_size=1
         0: aload_0
         1: invokespecial #419                // InterfaceMethod isLinux:()Z
         4: ireturn
      LineNumberTable:
        line 156: 0
      LocalVariableTable:
        Start  Length  Slot  Name   Signature
            0       5     0 $this   Lscala/util/PropertiesTrait;
    MethodParameters:
      Name                           Flags
      $this                          final synthetic

  public default boolean isLinux();
    descriptor: ()Z
    flags: (0x0001) ACC_PUBLIC
    Code:
      stack=2, locals=1, args_size=1
         0: aload_0
         1: invokeinterface #367,  1          // InterfaceMethod osName:()Ljava/lang/String;
         6: ldc_w         #421                // String Linux
         9: invokevirtual #409                // Method java/lang/String.startsWith:(Ljava/lang/String;)Z
        12: ireturn
      LineNumberTable:
        line 156: 0
      LocalVariableTable:
        Start  Length  Slot  Name   Signature
            0      13     0  this   Lscala/util/PropertiesTrait;

  public static boolean isAvian$(scala.util.PropertiesTrait);
    descriptor: (Lscala/util/PropertiesTrait;)Z
    flags: (0x1009) ACC_PUBLIC, ACC_STATIC, ACC_SYNTHETIC
    Code:
      stack=1, locals=1, args_size=1
         0: aload_0
         1: invokespecial #425                // InterfaceMethod isAvian:()Z
         4: ireturn
      LineNumberTable:
        line 159: 0
      LocalVariableTable:
        Start  Length  Slot  Name   Signature
            0       5     0 $this   Lscala/util/PropertiesTrait;
    MethodParameters:
      Name                           Flags
      $this                          final synthetic

  public default boolean isAvian();
    descriptor: ()Z
    flags: (0x0001) ACC_PUBLIC
    Code:
      stack=2, locals=1, args_size=1
         0: aload_0
         1: invokeinterface #331,  1          // InterfaceMethod javaVmName:()Ljava/lang/String;
         6: ldc_w         #427                // String Avian
         9: invokevirtual #431                // Method java/lang/String.contains:(Ljava/lang/CharSequence;)Z
        12: ireturn
      LineNumberTable:
        line 159: 0
      LocalVariableTable:
        Start  Length  Slot  Name   Signature
            0      13     0  this   Lscala/util/PropertiesTrait;

  public static boolean coloredOutputEnabled$(scala.util.PropertiesTrait);
    descriptor: (Lscala/util/PropertiesTrait;)Z
    flags: (0x1009) ACC_PUBLIC, ACC_STATIC, ACC_SYNTHETIC
    Code:
      stack=1, locals=1, args_size=1
         0: aload_0
         1: invokespecial #435                // InterfaceMethod coloredOutputEnabled:()Z
         4: ireturn
      LineNumberTable:
        line 161: 0
      LocalVariableTable:
        Start  Length  Slot  Name   Signature
            0       5     0 $this   Lscala/util/PropertiesTrait;
    MethodParameters:
      Name                           Flags
      $this                          final synthetic

  public default boolean coloredOutputEnabled();
    descriptor: ()Z
    flags: (0x0001) ACC_PUBLIC
    Code:
      stack=3, locals=4, args_size=1
         0: aload_0
         1: ldc_w         #437                // String scala.color
         4: invokedynamic #442,  0            // InvokeDynamic #6:apply:()Lscala/Function0;
         9: invokeinterface #123,  3          // InterfaceMethod propOrElse:(Ljava/lang/String;Lscala/Function0;)Ljava/lang/String;
        14: astore_2
        15: aload_2
        16: ifnonnull     23
        19: iconst_0
        20: goto          27
        23: aload_2
        24: invokevirtual #446                // Method java/lang/String.hashCode:()I
        27: tableswitch   { // 3005871 to 3005871
                 3005871: 44
                 default: 78
            }
        44: ldc_w         #448                // String auto
        47: aload_2
        48: invokevirtual #449                // Method java/lang/String.equals:(Ljava/lang/Object;)Z
        51: ifeq          78
        54: invokestatic  #453                // Method java/lang/System.console:()Ljava/io/Console;
        57: ifnull        73
        60: aload_0
        61: invokeinterface #404,  1          // InterfaceMethod isWin:()Z
        66: ifne          73
        69: iconst_1
        70: goto          74
        73: iconst_0
        74: istore_1
        75: goto          114
        78: aload_2
        79: ldc_w         #455                // String
        82: astore_3
        83: dup
        84: ifnonnull     91
        87: pop
        88: goto          98
        91: aload_3
        92: invokevirtual #114                // Method java/lang/Object.equals:(Ljava/lang/Object;)Z
        95: ifne          108
        98: ldc_w         #457                // String true
       101: aload_2
       102: invokevirtual #460                // Method java/lang/String.equalsIgnoreCase:(Ljava/lang/String;)Z
       105: ifeq          112
       108: iconst_1
       109: goto          113
       112: iconst_0
       113: istore_1
       114: iload_1
       115: ireturn
      StackMapTable: number_of_entries = 12
        frame_type = 253 /* append */
          offset_delta = 23
          locals = [ top, class java/lang/String ]
        frame_type = 67 /* same_locals_1_stack_item */
          stack = [ int ]
        frame_type = 16 /* same */
        frame_type = 28 /* same */
        frame_type = 64 /* same_locals_1_stack_item */
          stack = [ int ]
        frame_type = 3 /* same */
        frame_type = 255 /* full_frame */
          offset_delta = 12
          locals = [ class scala/util/PropertiesTrait, top, class java/lang/String, class java/lang/String ]
          stack = [ class java/lang/String ]
        frame_type = 6 /* same */
        frame_type = 9 /* same */
        frame_type = 3 /* same */
        frame_type = 64 /* same_locals_1_stack_item */
          stack = [ int ]
        frame_type = 255 /* full_frame */
          offset_delta = 0
          locals = [ class scala/util/PropertiesTrait, int, class java/lang/String ]
          stack = []
      LineNumberTable:
        line 161: 0
        line 162: 44
        line 163: 78
        line 161: 114
      LocalVariableTable:
        Start  Length  Slot  Name   Signature
            0     116     0  this   Lscala/util/PropertiesTrait;

  public static java.lang.String jdkHome$(scala.util.PropertiesTrait);
    descriptor: (Lscala/util/PropertiesTrait;)Ljava/lang/String;
    flags: (0x1009) ACC_PUBLIC, ACC_STATIC, ACC_SYNTHETIC
    Code:
      stack=1, locals=1, args_size=1
         0: aload_0
         1: invokespecial #464                // InterfaceMethod jdkHome:()Ljava/lang/String;
         4: areturn
      LineNumberTable:
        line 169: 0
      LocalVariableTable:
        Start  Length  Slot  Name   Signature
            0       5     0 $this   Lscala/util/PropertiesTrait;
    MethodParameters:
      Name                           Flags
      $this                          final synthetic

  public default java.lang.String jdkHome();
    descriptor: ()Ljava/lang/String;
    flags: (0x0001) ACC_PUBLIC
    Code:
      stack=3, locals=1, args_size=1
         0: aload_0
         1: ldc_w         #466                // String JDK_HOME
         4: aload_0
         5: invokedynamic #473,  0            // InvokeDynamic #7:apply:(Lscala/util/PropertiesTrait;)Lscala/Function0;
        10: invokeinterface #212,  3          // InterfaceMethod envOrElse:(Ljava/lang/String;Lscala/Function0;)Ljava/lang/String;
        15: areturn
      LineNumberTable:
        line 169: 0
      LocalVariableTable:
        Start  Length  Slot  Name   Signature
            0      16     0  this   Lscala/util/PropertiesTrait;

  public static java.lang.String versionFor$(scala.util.PropertiesTrait, java.lang.String);
    descriptor: (Lscala/util/PropertiesTrait;Ljava/lang/String;)Ljava/lang/String;
    flags: (0x1009) ACC_PUBLIC, ACC_STATIC, ACC_SYNTHETIC
    Code:
      stack=2, locals=2, args_size=2
         0: aload_0
         1: aload_1
         2: invokespecial #478                // InterfaceMethod versionFor:(Ljava/lang/String;)Ljava/lang/String;
         5: areturn
      LineNumberTable:
        line 171: 0
      LocalVariableTable:
        Start  Length  Slot  Name   Signature
            0       6     0 $this   Lscala/util/PropertiesTrait;
            0       6     1 command   Ljava/lang/String;
    MethodParameters:
      Name                           Flags
      $this                          final synthetic
      command                        final

  public default java.lang.String versionFor(java.lang.String);
    descriptor: (Ljava/lang/String;)Ljava/lang/String;
    flags: (0x0001) ACC_PUBLIC
    Code:
      stack=3, locals=2, args_size=2
         0: new           #480                // class java/lang/StringBuilder
         3: dup
         4: ldc_w         #481                // int 11
         7: invokespecial #484                // Method java/lang/StringBuilder."<init>":(I)V
        10: ldc_w         #486                // String Scala
        13: invokevirtual #490                // Method java/lang/StringBuilder.append:(Ljava/lang/String;)Ljava/lang/StringBuilder;
        16: aload_1
        17: invokevirtual #490                // Method java/lang/StringBuilder.append:(Ljava/lang/String;)Ljava/lang/StringBuilder;
        20: ldc_w         #492                // String
        23: invokevirtual #490                // Method java/lang/StringBuilder.append:(Ljava/lang/String;)Ljava/lang/StringBuilder;
        26: aload_0
        27: invokeinterface #494,  1          // InterfaceMethod versionString:()Ljava/lang/String;
        32: invokevirtual #490                // Method java/lang/StringBuilder.append:(Ljava/lang/String;)Ljava/lang/StringBuilder;
        35: ldc_w         #496                // String  --
        38: invokevirtual #490                // Method java/lang/StringBuilder.append:(Ljava/lang/String;)Ljava/lang/StringBuilder;
        41: aload_0
        42: invokeinterface #498,  1          // InterfaceMethod copyrightString:()Ljava/lang/String;
        47: invokevirtual #490                // Method java/lang/StringBuilder.append:(Ljava/lang/String;)Ljava/lang/StringBuilder;
        50: invokevirtual #501                // Method java/lang/StringBuilder.toString:()Ljava/lang/String;
        53: areturn
      LineNumberTable:
        line 171: 0
      LocalVariableTable:
        Start  Length  Slot  Name   Signature
            0      54     0  this   Lscala/util/PropertiesTrait;
            0      54     1 command   Ljava/lang/String;
    MethodParameters:
      Name                           Flags
      command                        final

  public static java.lang.String versionMsg$(scala.util.PropertiesTrait);
    descriptor: (Lscala/util/PropertiesTrait;)Ljava/lang/String;
    flags: (0x1009) ACC_PUBLIC, ACC_STATIC, ACC_SYNTHETIC
    Code:
      stack=1, locals=1, args_size=1
         0: aload_0
         1: invokespecial #505                // InterfaceMethod versionMsg:()Ljava/lang/String;
         4: areturn
      LineNumberTable:
        line 173: 0
      LocalVariableTable:
        Start  Length  Slot  Name   Signature
            0       5     0 $this   Lscala/util/PropertiesTrait;
    MethodParameters:
      Name                           Flags
      $this                          final synthetic

  public default java.lang.String versionMsg();
    descriptor: ()Ljava/lang/String;
    flags: (0x0001) ACC_PUBLIC
    Code:
      stack=2, locals=1, args_size=1
         0: aload_0
         1: aload_0
         2: invokeinterface #507,  1          // InterfaceMethod propCategory:()Ljava/lang/String;
         7: invokeinterface #478,  2          // InterfaceMethod versionFor:(Ljava/lang/String;)Ljava/lang/String;
        12: areturn
      LineNumberTable:
        line 173: 0
      LocalVariableTable:
        Start  Length  Slot  Name   Signature
            0      13     0  this   Lscala/util/PropertiesTrait;

  public static java.lang.String scalaCmd$(scala.util.PropertiesTrait);
    descriptor: (Lscala/util/PropertiesTrait;)Ljava/lang/String;
    flags: (0x1009) ACC_PUBLIC, ACC_STATIC, ACC_SYNTHETIC
    Code:
      stack=1, locals=1, args_size=1
         0: aload_0
         1: invokespecial #511                // InterfaceMethod scalaCmd:()Ljava/lang/String;
         4: areturn
      LineNumberTable:
        line 174: 0
      LocalVariableTable:
        Start  Length  Slot  Name   Signature
            0       5     0 $this   Lscala/util/PropertiesTrait;
    MethodParameters:
      Name                           Flags
      $this                          final synthetic

  public default java.lang.String scalaCmd();
    descriptor: ()Ljava/lang/String;
    flags: (0x0001) ACC_PUBLIC
    Code:
      stack=1, locals=1, args_size=1
         0: aload_0
         1: invokeinterface #404,  1          // InterfaceMethod isWin:()Z
         6: ifeq          13
         9: ldc_w         #513                // String scala.bat
        12: areturn
        13: ldc_w         #515                // String scala
        16: areturn
      StackMapTable: number_of_entries = 1
        frame_type = 13 /* same */
      LineNumberTable:
        line 174: 0
      LocalVariableTable:
        Start  Length  Slot  Name   Signature
            0      17     0  this   Lscala/util/PropertiesTrait;

  public static java.lang.String scalacCmd$(scala.util.PropertiesTrait);
    descriptor: (Lscala/util/PropertiesTrait;)Ljava/lang/String;
    flags: (0x1009) ACC_PUBLIC, ACC_STATIC, ACC_SYNTHETIC
    Code:
      stack=1, locals=1, args_size=1
         0: aload_0
         1: invokespecial #519                // InterfaceMethod scalacCmd:()Ljava/lang/String;
         4: areturn
      LineNumberTable:
        line 175: 0
      LocalVariableTable:
        Start  Length  Slot  Name   Signature
            0       5     0 $this   Lscala/util/PropertiesTrait;
    MethodParameters:
      Name                           Flags
      $this                          final synthetic

  public default java.lang.String scalacCmd();
    descriptor: ()Ljava/lang/String;
    flags: (0x0001) ACC_PUBLIC
    Code:
      stack=1, locals=1, args_size=1
         0: aload_0
         1: invokeinterface #404,  1          // InterfaceMethod isWin:()Z
         6: ifeq          13
         9: ldc_w         #521                // String scalac.bat
        12: areturn
        13: ldc_w         #523                // String scalac
        16: areturn
      StackMapTable: number_of_entries = 1
        frame_type = 13 /* same */
      LineNumberTable:
        line 175: 0
      LocalVariableTable:
        Start  Length  Slot  Name   Signature
            0      17     0  this   Lscala/util/PropertiesTrait;

  public static boolean isJavaAtLeast$(scala.util.PropertiesTrait, java.lang.String);
    descriptor: (Lscala/util/PropertiesTrait;Ljava/lang/String;)Z
    flags: (0x1009) ACC_PUBLIC, ACC_STATIC, ACC_SYNTHETIC
    Code:
      stack=2, locals=2, args_size=2
         0: aload_0
         1: aload_1
         2: invokespecial #528                // InterfaceMethod isJavaAtLeast:(Ljava/lang/String;)Z
         5: ireturn
      LineNumberTable:
        line 193: 0
      LocalVariableTable:
        Start  Length  Slot  Name   Signature
            0       6     0 $this   Lscala/util/PropertiesTrait;
            0       6     1 version   Ljava/lang/String;
    MethodParameters:
      Name                           Flags
      $this                          final synthetic
      version                        final

  public default boolean isJavaAtLeast(java.lang.String);
    descriptor: (Ljava/lang/String;)Z
    flags: (0x0001) ACC_PUBLIC
    Code:
      stack=5, locals=3, args_size=2
         0: aload_0
         1: aload_0
         2: invokeinterface #349,  1          // InterfaceMethod javaSpecVersion:()Ljava/lang/String;
         7: aload_1
         8: iconst_0
         9: invokespecial #532                // InterfaceMethod compareVersions$1:(Ljava/lang/String;Ljava/lang/String;I)I
        12: istore_2
        13: iload_2
        14: tableswitch   { // -2 to -2
                      -2: 32
                 default: 63
            }
        32: new           #534                // class java/lang/NumberFormatException
        35: dup
        36: new           #480                // class java/lang/StringBuilder
        39: dup
        40: ldc_w         #535                // int 15
        43: invokespecial #484                // Method java/lang/StringBuilder."<init>":(I)V
        46: ldc_w         #537                // String Not a version:
        49: invokevirtual #490                // Method java/lang/StringBuilder.append:(Ljava/lang/String;)Ljava/lang/StringBuilder;
        52: aload_1
        53: invokevirtual #490                // Method java/lang/StringBuilder.append:(Ljava/lang/String;)Ljava/lang/StringBuilder;
        56: invokevirtual #501                // Method java/lang/StringBuilder.toString:()Ljava/lang/String;
        59: invokespecial #539                // Method java/lang/NumberFormatException."<init>":(Ljava/lang/String;)V
        62: athrow
        63: iload_2
        64: iconst_0
        65: if_icmplt     70
        68: iconst_1
        69: ireturn
        70: iconst_0
        71: ireturn
      StackMapTable: number_of_entries = 3
        frame_type = 252 /* append */
          offset_delta = 32
          locals = [ int ]
        frame_type = 30 /* same */
        frame_type = 6 /* same */
      LineNumberTable:
        line 223: 0
        line 224: 32
        line 225: 63
      LocalVariableTable:
        Start  Length  Slot  Name   Signature
            0      72     0  this   Lscala/util/PropertiesTrait;
            0      72     1 version   Ljava/lang/String;
    MethodParameters:
      Name                           Flags
      version                        final

  public static boolean isJavaAtLeast$(scala.util.PropertiesTrait, int);
    descriptor: (Lscala/util/PropertiesTrait;I)Z
    flags: (0x1009) ACC_PUBLIC, ACC_STATIC, ACC_SYNTHETIC
    Code:
      stack=2, locals=2, args_size=2
         0: aload_0
         1: iload_1
         2: invokespecial #543                // InterfaceMethod isJavaAtLeast:(I)Z
         5: ireturn
      LineNumberTable:
        line 232: 0
      LocalVariableTable:
        Start  Length  Slot  Name   Signature
            0       6     0 $this   Lscala/util/PropertiesTrait;
            0       6     1 version   I
    MethodParameters:
      Name                           Flags
      $this                          final synthetic
      version                        final

  public default boolean isJavaAtLeast(int);
    descriptor: (I)Z
    flags: (0x0001) ACC_PUBLIC
    Code:
      stack=3, locals=3, args_size=2
         0: aload_0
         1: getstatic     #549                // Field scala/math/package$.MODULE$:Lscala/math/package$;
         4: pop
         5: iconst_0
         6: istore_2
         7: iload_1
         8: iload_2
         9: invokestatic  #555                // Method java/lang/Math.max:(II)I
        12: invokestatic  #560                // Method java/lang/Integer.toString:(I)Ljava/lang/String;
        15: invokeinterface #528,  2          // InterfaceMethod isJavaAtLeast:(Ljava/lang/String;)Z
        20: ireturn
      LineNumberTable:
        line 232: 0
      LocalVariableTable:
        Start  Length  Slot  Name   Signature
            0      21     0  this   Lscala/util/PropertiesTrait;
            0      21     1 version   I
            7       5     2 max_y   I
    MethodParameters:
      Name                           Flags
      version                        final

  public static void main$(scala.util.PropertiesTrait, java.lang.String[]);
    descriptor: (Lscala/util/PropertiesTrait;[Ljava/lang/String;)V
    flags: (0x1009) ACC_PUBLIC, ACC_STATIC, ACC_SYNTHETIC
    Code:
      stack=2, locals=2, args_size=2
         0: aload_0
         1: aload_1
         2: invokespecial #568                // InterfaceMethod main:([Ljava/lang/String;)V
         5: return
      LineNumberTable:
        line 235: 0
      LocalVariableTable:
        Start  Length  Slot  Name   Signature
            0       6     0 $this   Lscala/util/PropertiesTrait;
            0       6     1  args   [Ljava/lang/String;
    MethodParameters:
      Name                           Flags
      $this                          final synthetic
      args                           final

  public default void main(java.lang.String[]);
    descriptor: ([Ljava/lang/String;)V
    flags: (0x0001) ACC_PUBLIC
    Code:
      stack=4, locals=2, args_size=2
         0: new           #571                // class java/io/PrintWriter
         3: dup
         4: getstatic     #576                // Field scala/Console$.MODULE$:Lscala/Console$;
         7: invokevirtual #580                // Method scala/Console$.err:()Ljava/io/PrintStream;
        10: iconst_1
        11: invokespecial #583                // Method java/io/PrintWriter."<init>":(Ljava/io/OutputStream;Z)V
        14: aload_0
        15: invokeinterface #505,  1          // InterfaceMethod versionMsg:()Ljava/lang/String;
        20: invokevirtual #586                // Method java/io/PrintWriter.println:(Ljava/lang/String;)V
        23: return
      LineNumberTable:
        line 236: 0
        line 237: 14
      LocalVariableTable:
        Start  Length  Slot  Name   Signature
            0      24     0  this   Lscala/util/PropertiesTrait;
            0      24     1  args   [Ljava/lang/String;
    MethodParameters:
      Name                           Flags
      args                           final

  public static void $anonfun$scalaProps$1(java.util.Properties, java.io.InputStream);
    descriptor: (Ljava/util/Properties;Ljava/io/InputStream;)V
    flags: (0x1009) ACC_PUBLIC, ACC_STATIC, ACC_SYNTHETIC
    Code:
      stack=2, locals=2, args_size=2
         0: aload_0
         1: aload_1
         2: invokevirtual #63                 // Method java/util/Properties.load:(Ljava/io/InputStream;)V
         5: return
      LineNumberTable:
        line 42: 0
      LocalVariableTable:
        Start  Length  Slot  Name   Signature
            0       6     0 props$1   Ljava/util/Properties;
            0       6     1 stream$1   Ljava/io/InputStream;
    MethodParameters:
      Name                           Flags
      props$1                        final
      stream$1                       final

  public static void $anonfun$scalaProps$2(java.io.InputStream);
    descriptor: (Ljava/io/InputStream;)V
    flags: (0x1009) ACC_PUBLIC, ACC_STATIC, ACC_SYNTHETIC
    Code:
      stack=1, locals=1, args_size=1
         0: aload_0
         1: invokevirtual #68                 // Method java/io/InputStream.close:()V
         4: return
      LineNumberTable:
        line 42: 0
      LocalVariableTable:
        Start  Length  Slot  Name   Signature
            0       5     0 stream$1   Ljava/io/InputStream;
    MethodParameters:
      Name                           Flags
      stream$1                       final

  public static java.lang.String $anonfun$propOrEmpty$1();
    descriptor: ()Ljava/lang/String;
    flags: (0x1009) ACC_PUBLIC, ACC_STATIC, ACC_SYNTHETIC
    Code:
      stack=1, locals=0, args_size=0
         0: ldc_w         #455                // String
         3: areturn
      LineNumberTable:
        line 57: 0

  public static scala.runtime.Null$ $anonfun$propOrNull$1();
    descriptor: ()Lscala/runtime/Null$;
    flags: (0x1009) ACC_PUBLIC, ACC_STATIC, ACC_SYNTHETIC
    Code:
      stack=1, locals=0, args_size=0
         0: aconst_null
         1: areturn
      LineNumberTable:
        line 58: 0

  public static boolean $anonfun$propOrFalse$1(java.lang.String);
    descriptor: (Ljava/lang/String;)Z
    flags: (0x1009) ACC_PUBLIC, ACC_STATIC, ACC_SYNTHETIC
    Code:
      stack=6, locals=2, args_size=1
         0: getstatic     #597                // Field scala/package$.MODULE$:Lscala/package$;
         3: invokevirtual #601                // Method scala/package$.List:()Lscala/collection/immutable/List$;
         6: getstatic     #606                // Field scala/runtime/ScalaRunTime$.MODULE$:Lscala/runtime/ScalaRunTime$;
         9: iconst_3
        10: anewarray     #116                // class java/lang/String
        13: dup
        14: iconst_0
        15: ldc_w         #608                // String yes
        18: aastore
        19: dup
        20: iconst_1
        21: ldc_w         #610                // String on
        24: aastore
        25: dup
        26: iconst_2
        27: ldc_w         #457                // String true
        30: aastore
        31: invokevirtual #614                // Method scala/runtime/ScalaRunTime$.wrapRefArray:([Ljava/lang/Object;)Lscala/collection/immutable/ArraySeq;
        34: astore_1
        35: ifnonnull     40
        38: aconst_null
        39: athrow
        40: getstatic     #619                // Field scala/collection/immutable/Nil$.MODULE$:Lscala/collection/immutable/Nil$;
        43: aload_1
        44: invokevirtual #623                // Method scala/collection/immutable/Nil$.prependedAll:(Lscala/collection/IterableOnce;)Lscala/collection/immutable/List;
        47: aconst_null
        48: astore_1
        49: aload_0
        50: invokevirtual #626                // Method java/lang/String.toLowerCase:()Ljava/lang/String;
        53: invokevirtual #630                // Method scala/collection/immutable/List.contains:(Ljava/lang/Object;)Z
        56: ireturn
      StackMapTable: number_of_entries = 1
        frame_type = 252 /* append */
          offset_delta = 40
          locals = [ class scala/collection/immutable/ArraySeq ]
      LineNumberTable:
        line 60: 0
      LocalVariableTable:
        Start  Length  Slot  Name   Signature
            0      57     0     x   Ljava/lang/String;
           40       7     1 apply_elems   Lscala/collection/immutable/Seq;
    MethodParameters:
      Name                           Flags
      x                              final

  public static java.lang.String $anonfun$scalaPropOrEmpty$1();
    descriptor: ()Ljava/lang/String;
    flags: (0x1009) ACC_PUBLIC, ACC_STATIC, ACC_SYNTHETIC
    Code:
      stack=1, locals=0, args_size=0
         0: ldc_w         #455                // String
         3: areturn
      LineNumberTable:
        line 71: 0

  public static scala.Option $anonfun$scalaPropOrNone$1(scala.util.PropertiesTrait, java.lang.String);
    descriptor: (Lscala/util/PropertiesTrait;Ljava/lang/String;)Lscala/Option;
    flags: (0x1009) ACC_PUBLIC, ACC_STATIC, ACC_SYNTHETIC
    Code:
      stack=4, locals=2, args_size=2
         0: aload_0
         1: new           #480                // class java/lang/StringBuilder
         4: dup
         5: ldc_w         #636                // int 6
         8: invokespecial #484                // Method java/lang/StringBuilder."<init>":(I)V
        11: ldc_w         #638                // String scala.
        14: invokevirtual #490                // Method java/lang/StringBuilder.append:(Ljava/lang/String;)Ljava/lang/StringBuilder;
        17: aload_1
        18: invokevirtual #490                // Method java/lang/StringBuilder.append:(Ljava/lang/String;)Ljava/lang/StringBuilder;
        21: invokevirtual #501                // Method java/lang/StringBuilder.toString:()Ljava/lang/String;
        24: invokeinterface #183,  2          // InterfaceMethod propOrNone:(Ljava/lang/String;)Lscala/Option;
        29: areturn
      LineNumberTable:
        line 72: 0
      LocalVariableTable:
        Start  Length  Slot  Name   Signature
            0      30     0 $this   Lscala/util/PropertiesTrait;
            0      30     1 name$1   Ljava/lang/String;
    MethodParameters:
      Name                           Flags
      $this                          final synthetic
      name$1                         final

  public static boolean $anonfun$releaseVersion$1(java.lang.String);
    descriptor: (Ljava/lang/String;)Z
    flags: (0x1009) ACC_PUBLIC, ACC_STATIC, ACC_SYNTHETIC
    Code:
      stack=2, locals=1, args_size=1
         0: aload_0
         1: ldc_w         #642                // String -SNAPSHOT
         4: invokevirtual #645                // Method java/lang/String.endsWith:(Ljava/lang/String;)Z
         7: ifne          12
        10: iconst_1
        11: ireturn
        12: iconst_0
        13: ireturn
      StackMapTable: number_of_entries = 1
        frame_type = 12 /* same */
      LineNumberTable:
        line 85: 0
      LocalVariableTable:
        Start  Length  Slot  Name   Signature
            0      14     0     v   Ljava/lang/String;
    MethodParameters:
      Name                           Flags
      v                              final

  public static java.lang.String $anonfun$releaseVersion$2(java.lang.String);
    descriptor: (Ljava/lang/String;)Ljava/lang/String;
    flags: (0x1009) ACC_PUBLIC, ACC_STATIC, ACC_SYNTHETIC
    Code:
      stack=1, locals=1, args_size=1
         0: aload_0
         1: areturn
      LineNumberTable:
        line 86: 0
      LocalVariableTable:
        Start  Length  Slot  Name   Signature
            0       2     0     v   Ljava/lang/String;
    MethodParameters:
      Name                           Flags
      v                              final

  public static boolean $anonfun$developmentVersion$1(java.lang.String);
    descriptor: (Ljava/lang/String;)Z
    flags: (0x1009) ACC_PUBLIC, ACC_STATIC, ACC_SYNTHETIC
    Code:
      stack=2, locals=1, args_size=1
         0: aload_0
         1: ldc_w         #642                // String -SNAPSHOT
         4: invokevirtual #645                // Method java/lang/String.endsWith:(Ljava/lang/String;)Z
         7: ireturn
      LineNumberTable:
        line 99: 0
      LocalVariableTable:
        Start  Length  Slot  Name   Signature
            0       8     0     v   Ljava/lang/String;
    MethodParameters:
      Name                           Flags
      v                              final

  public static java.lang.String $anonfun$developmentVersion$3(java.lang.String);
    descriptor: (Ljava/lang/String;)Ljava/lang/String;
    flags: (0x1009) ACC_PUBLIC, ACC_STATIC, ACC_SYNTHETIC
    Code:
      stack=1, locals=1, args_size=1
         0: aload_0
         1: areturn
      LineNumberTable:
        line 101: 0
      LocalVariableTable:
        Start  Length  Slot  Name   Signature
            0       2     0    ov   Ljava/lang/String;
    MethodParameters:
      Name                           Flags
      ov                             final

  public static scala.Option $anonfun$developmentVersion$2(scala.util.PropertiesTrait, java.lang.String);
    descriptor: (Lscala/util/PropertiesTrait;Ljava/lang/String;)Lscala/Option;
    flags: (0x1009) ACC_PUBLIC, ACC_STATIC, ACC_SYNTHETIC
    Code:
      stack=3, locals=3, args_size=2
         0: aload_0
         1: ldc_w         #259                // String version.number
         4: invokeinterface #234,  2          // InterfaceMethod scalaPropOrNone:(Ljava/lang/String;)Lscala/Option;
         9: dup
        10: ifnonnull     15
        13: aconst_null
        14: athrow
        15: astore_2
        16: aload_2
        17: invokevirtual #138                // Method scala/Option.isEmpty:()Z
        20: ifeq          27
        23: getstatic     #655                // Field scala/None$.MODULE$:Lscala/None$;
        26: areturn
        27: new           #657                // class scala/Some
        30: dup
        31: aload_2
        32: invokevirtual #144                // Method scala/Option.get:()Ljava/lang/Object;
        35: checkcast     #116                // class java/lang/String
        38: invokespecial #660                // Method scala/Some."<init>":(Ljava/lang/Object;)V
        41: areturn
      StackMapTable: number_of_entries = 2
        frame_type = 79 /* same_locals_1_stack_item */
          stack = [ class scala/Option ]
        frame_type = 252 /* append */
          offset_delta = 11
          locals = [ class scala/Option ]
      LineNumberTable:
        line 100: 0
        line 100: 38
      LocalVariableTable:
        Start  Length  Slot  Name   Signature
            0      42     0 $this   Lscala/util/PropertiesTrait;
            0      42     1     v   Ljava/lang/String;
           16      25     2 map_this   Lscala/Option;
    MethodParameters:
      Name                           Flags
      $this                          final synthetic
      v                              final

  public static java.lang.String $anonfun$versionString$1();
    descriptor: ()Ljava/lang/String;
    flags: (0x1009) ACC_PUBLIC, ACC_STATIC, ACC_SYNTHETIC
    Code:
      stack=1, locals=0, args_size=0
         0: ldc_w         #664                // String (unknown)
         3: areturn
      LineNumberTable:
        line 111: 0

  public static java.lang.String $anonfun$copyrightString$1();
    descriptor: ()Ljava/lang/String;
    flags: (0x1009) ACC_PUBLIC, ACC_STATIC, ACC_SYNTHETIC
    Code:
      stack=1, locals=0, args_size=0
         0: ldc_w         #667                // String Copyright 2002-2021, LAMP/EPFL and Lightbend, Inc.
         3: areturn
      LineNumberTable:
        line 112: 0

  public static java.lang.String $anonfun$sourceEncoding$1();
    descriptor: ()Ljava/lang/String;
    flags: (0x1009) ACC_PUBLIC, ACC_STATIC, ACC_SYNTHETIC
    Code:
      stack=1, locals=0, args_size=0
         0: ldc_w         #669                // String UTF-8
         3: areturn
      LineNumberTable:
        line 117: 0

  public static java.lang.String $anonfun$sourceReader$1();
    descriptor: ()Ljava/lang/String;
    flags: (0x1009) ACC_PUBLIC, ACC_STATIC, ACC_SYNTHETIC
    Code:
      stack=1, locals=0, args_size=0
         0: ldc_w         #671                // String scala.tools.nsc.io.SourceReader
         3: areturn
      LineNumberTable:
        line 118: 0

  public static java.lang.String $anonfun$encodingString$1();
    descriptor: ()Ljava/lang/String;
    flags: (0x1009) ACC_PUBLIC, ACC_STATIC, ACC_SYNTHETIC
    Code:
      stack=1, locals=0, args_size=0
         0: ldc_w         #669                // String UTF-8
         3: areturn
      LineNumberTable:
        line 123: 0

  public static java.lang.String $anonfun$coloredOutputEnabled$1();
    descriptor: ()Ljava/lang/String;
    flags: (0x1009) ACC_PUBLIC, ACC_STATIC, ACC_SYNTHETIC
    Code:
      stack=1, locals=0, args_size=0
         0: ldc_w         #448                // String auto
         3: areturn
      LineNumberTable:
        line 161: 0

  public static java.lang.String $anonfun$jdkHome$2(scala.util.PropertiesTrait);
    descriptor: (Lscala/util/PropertiesTrait;)Ljava/lang/String;
    flags: (0x1009) ACC_PUBLIC, ACC_STATIC, ACC_SYNTHETIC
    Code:
      stack=1, locals=1, args_size=1
         0: aload_0
         1: invokeinterface #307,  1          // InterfaceMethod javaHome:()Ljava/lang/String;
         6: areturn
      LineNumberTable:
        line 169: 0
      LocalVariableTable:
        Start  Length  Slot  Name   Signature
            0       7     0 $this   Lscala/util/PropertiesTrait;
    MethodParameters:
      Name                           Flags
      $this                          final synthetic

  public static java.lang.String $anonfun$jdkHome$1(scala.util.PropertiesTrait);
    descriptor: (Lscala/util/PropertiesTrait;)Ljava/lang/String;
    flags: (0x1009) ACC_PUBLIC, ACC_STATIC, ACC_SYNTHETIC
    Code:
      stack=3, locals=1, args_size=1
         0: aload_0
         1: ldc_w         #674                // String JAVA_HOME
         4: aload_0
         5: invokedynamic #678,  0            // InvokeDynamic #8:apply:(Lscala/util/PropertiesTrait;)Lscala/Function0;
        10: invokeinterface #212,  3          // InterfaceMethod envOrElse:(Ljava/lang/String;Lscala/Function0;)Ljava/lang/String;
        15: areturn
      LineNumberTable:
        line 169: 0
      LocalVariableTable:
        Start  Length  Slot  Name   Signature
            0      16     0 $this   Lscala/util/PropertiesTrait;
    MethodParameters:
      Name                           Flags
      $this                          final synthetic

  private static scala.Tuple2 versionOf$1(java.lang.String, int);
    descriptor: (Ljava/lang/String;I)Lscala/Tuple2;
    flags: (0x000a) ACC_PRIVATE, ACC_STATIC
    Code:
      stack=5, locals=12, args_size=2
         0: aload_0
         1: bipush        46
         3: invokevirtual #686                // Method java/lang/String.indexOf:(I)I
         6: istore_2
         7: iload_2
         8: tableswitch   { // -1 to 1
                      -1: 154
                       0: 36
                       1: 54
                 default: 197
            }
        36: new           #688                // class scala/Tuple2
        39: dup
        40: bipush        -2
        42: invokestatic  #692                // Method java/lang/Integer.valueOf:(I)Ljava/lang/Integer;
        45: aload_0
        46: iconst_1
        47: invokevirtual #695                // Method java/lang/String.substring:(I)Ljava/lang/String;
        50: invokespecial #698                // Method scala/Tuple2."<init>":(Ljava/lang/Object;Ljava/lang/Object;)V
        53: areturn
        54: iload_1
        55: iconst_0
        56: if_icmpne     197
        59: aload_0
        60: iconst_0
        61: invokevirtual #702                // Method java/lang/String.charAt:(I)C
        64: bipush        49
        66: if_icmpne     197
        69: aload_0
        70: iconst_2
        71: invokevirtual #695                // Method java/lang/String.substring:(I)Ljava/lang/String;
        74: astore_3
        75: aload_3
        76: iconst_1
        77: invokestatic  #704                // InterfaceMethod versionOf$1:(Ljava/lang/String;I)Lscala/Tuple2;
        80: astore        4
        82: aload         4
        84: ifnull        107
        87: aload         4
        89: invokevirtual #707                // Method scala/Tuple2._1$mcI$sp:()I
        92: istore        5
        94: aload         4
        96: invokevirtual #710                // Method scala/Tuple2._2:()Ljava/lang/Object;
        99: checkcast     #116                // class java/lang/String
       102: astore        6
       104: goto          116
       107: new           #712                // class scala/MatchError
       110: dup
       111: aconst_null
       112: invokespecial #713                // Method scala/MatchError."<init>":(Ljava/lang/Object;)V
       115: athrow
       116: iload         5
       118: bipush        8
       120: if_icmpgt     130
       123: aload_3
       124: invokevirtual #714                // Method java/lang/String.isEmpty:()Z
       127: ifeq          135
       130: bipush        -2
       132: goto          137
       135: iload         5
       137: istore        7
       139: new           #688                // class scala/Tuple2
       142: dup
       143: iload         7
       145: invokestatic  #692                // Method java/lang/Integer.valueOf:(I)Ljava/lang/Integer;
       148: aload         6
       150: invokespecial #698                // Method scala/Tuple2."<init>":(Ljava/lang/Object;Ljava/lang/Object;)V
       153: areturn
       154: aload_0
       155: invokevirtual #714                // Method java/lang/String.isEmpty:()Z
       158: ifne          168
       161: aload_0
       162: invokestatic  #718                // Method java/lang/Integer.parseInt:(Ljava/lang/String;)I
       165: goto          179
       168: iload_1
       169: iconst_0
       170: if_icmpne     178
       173: bipush        -2
       175: goto          179
       178: iconst_0
       179: istore        8
       181: new           #688                // class scala/Tuple2
       184: dup
       185: iload         8
       187: invokestatic  #692                // Method java/lang/Integer.valueOf:(I)Ljava/lang/Integer;
       190: ldc_w         #455                // String
       193: invokespecial #698                // Method scala/Tuple2."<init>":(Ljava/lang/Object;Ljava/lang/Object;)V
       196: areturn
       197: aload_0
       198: iload_2
       199: iconst_1
       200: iadd
       201: invokevirtual #695                // Method java/lang/String.substring:(I)Ljava/lang/String;
       204: astore        9
       206: iload_1
       207: iconst_2
       208: if_icmpge     224
       211: aload         9
       213: invokevirtual #714                // Method java/lang/String.isEmpty:()Z
       216: ifeq          224
       219: bipush        -2
       221: goto          240
       224: aload_0
       225: iconst_0
       226: iload_2
       227: invokevirtual #721                // Method java/lang/String.substring:(II)Ljava/lang/String;
       230: astore        11
       232: aload         11
       234: invokestatic  #718                // Method java/lang/Integer.parseInt:(Ljava/lang/String;)I
       237: aconst_null
       238: astore        11
       240: istore        10
       242: new           #688                // class scala/Tuple2
       245: dup
       246: iload         10
       248: invokestatic  #692                // Method java/lang/Integer.valueOf:(I)Ljava/lang/Integer;
       251: aload         9
       253: invokespecial #698                // Method scala/Tuple2."<init>":(Ljava/lang/Object;Ljava/lang/Object;)V
       256: areturn
      StackMapTable: number_of_entries = 14
        frame_type = 252 /* append */
          offset_delta = 36
          locals = [ int ]
        frame_type = 17 /* same */
        frame_type = 253 /* append */
          offset_delta = 52
          locals = [ class java/lang/String, class scala/Tuple2 ]
        frame_type = 253 /* append */
          offset_delta = 8
          locals = [ int, class java/lang/String ]
        frame_type = 13 /* same */
        frame_type = 4 /* same */
        frame_type = 65 /* same_locals_1_stack_item */
          stack = [ int ]
        frame_type = 255 /* full_frame */
          offset_delta = 16
          locals = [ class java/lang/String, int, int ]
          stack = []
        frame_type = 13 /* same */
        frame_type = 9 /* same */
        frame_type = 64 /* same_locals_1_stack_item */
          stack = [ int ]
        frame_type = 17 /* same */
        frame_type = 255 /* full_frame */
          offset_delta = 26
          locals = [ class java/lang/String, int, int, top, top, top, top, top, top, class java/lang/String ]
          stack = []
        frame_type = 79 /* same_locals_1_stack_item */
          stack = [ int ]
      LineNumberTable:
        line 195: 0
        line 197: 36
        line 198: 54
        line 199: 69
        line 200: 75
        line 201: 116
        line 202: 139
        line 204: 154
        line 205: 181
        line 207: 197
        line 208: 206
        line 209: 242
      LocalVariableTable:
        Start  Length  Slot  Name   Signature
           94      13     5     v   I
          104       3     6     r   Ljava/lang/String;
           75      78     3    r0   Ljava/lang/String;
          139      14     7     n   I
          181      15     8     n   I
          206      50     9     r   Ljava/lang/String;
          242      14    10     n   I
            0     257     0     s   Ljava/lang/String;
            0     257     1 depth   I
          232       5    11 toInt$extension_$this   Ljava/lang/String;
    MethodParameters:
      Name                           Flags
      s                              final
      depth                          final

  private int compareVersions$1(java.lang.String, java.lang.String, int);
    descriptor: (Ljava/lang/String;Ljava/lang/String;I)I
    flags: (0x0002) ACC_PRIVATE
    Code:
      stack=4, locals=10, args_size=4
         0: iload_3
         1: iconst_3
         2: if_icmplt     7
         5: iconst_0
         6: ireturn
         7: aload_1
         8: iload_3
         9: invokestatic  #704                // InterfaceMethod versionOf$1:(Ljava/lang/String;I)Lscala/Tuple2;
        12: astore        4
        14: aload         4
        16: ifnull        39
        19: aload         4
        21: invokevirtual #707                // Method scala/Tuple2._1$mcI$sp:()I
        24: istore        5
        26: aload         4
        28: invokevirtual #710                // Method scala/Tuple2._2:()Ljava/lang/Object;
        31: checkcast     #116                // class java/lang/String
        34: astore        6
        36: goto          48
        39: new           #712                // class scala/MatchError
        42: dup
        43: aconst_null
        44: invokespecial #713                // Method scala/MatchError."<init>":(Ljava/lang/Object;)V
        47: athrow
        48: aload_2
        49: iload_3
        50: invokestatic  #704                // InterfaceMethod versionOf$1:(Ljava/lang/String;I)Lscala/Tuple2;
        53: astore        7
        55: aload         7
        57: ifnull        80
        60: aload         7
        62: invokevirtual #707                // Method scala/Tuple2._1$mcI$sp:()I
        65: istore        8
        67: aload         7
        69: invokevirtual #710                // Method scala/Tuple2._2:()Ljava/lang/Object;
        72: checkcast     #116                // class java/lang/String
        75: astore        9
        77: goto          89
        80: new           #712                // class scala/MatchError
        83: dup
        84: aconst_null
        85: invokespecial #713                // Method scala/MatchError."<init>":(Ljava/lang/Object;)V
        88: athrow
        89: iload         8
        91: iconst_0
        92: if_icmpge     98
        95: bipush        -2
        97: ireturn
        98: iload         5
       100: iload         8
       102: if_icmpge     107
       105: iconst_m1
       106: ireturn
       107: iload         5
       109: iload         8
       111: if_icmple     116
       114: iconst_1
       115: ireturn
       116: aload         6
       118: aload         9
       120: iload_3
       121: iconst_1
       122: iadd
       123: istore_3
       124: astore_2
       125: astore_1
       126: goto          0
      StackMapTable: number_of_entries = 9
        frame_type = 0 /* same */
        frame_type = 6 /* same */
        frame_type = 252 /* append */
          offset_delta = 31
          locals = [ class scala/Tuple2 ]
        frame_type = 253 /* append */
          offset_delta = 8
          locals = [ int, class java/lang/String ]
        frame_type = 252 /* append */
          offset_delta = 31
          locals = [ class scala/Tuple2 ]
        frame_type = 253 /* append */
          offset_delta = 8
          locals = [ int, class java/lang/String ]
        frame_type = 8 /* same */
        frame_type = 8 /* same */
        frame_type = 8 /* same */
      LineNumberTable:
        line 213: 0
        line 215: 7
        line 216: 48
        line 217: 89
        line 218: 98
        line 219: 107
        line 220: 116
      LocalVariableTable:
        Start  Length  Slot  Name   Signature
           26      13     5    sn   I
           36       3     6 srest   Ljava/lang/String;
           67      13     8    vn   I
           77       3     9 vrest   Ljava/lang/String;
            0     129     0  this   Lscala/util/PropertiesTrait;
            0     129     1     s   Ljava/lang/String;
            0     129     2     v   Ljava/lang/String;
            0     129     3 depth   I
    MethodParameters:
      Name                           Flags
      s                              final
      v                              final
      depth                          final

  public static void $init$(scala.util.PropertiesTrait);
    descriptor: (Lscala/util/PropertiesTrait;)V
    flags: (0x0009) ACC_PUBLIC, ACC_STATIC
    Code:
      stack=5, locals=5, args_size=1
         0: aload_0
         1: new           #480                // class java/lang/StringBuilder
         4: dup
         5: ldc_w         #732                // int 12
         8: invokespecial #484                // Method java/lang/StringBuilder."<init>":(I)V
        11: ldc_w         #734                // String /
        14: invokevirtual #490                // Method java/lang/StringBuilder.append:(Ljava/lang/String;)Ljava/lang/StringBuilder;
        17: aload_0
        18: invokeinterface #507,  1          // InterfaceMethod propCategory:()Ljava/lang/String;
        23: invokevirtual #490                // Method java/lang/StringBuilder.append:(Ljava/lang/String;)Ljava/lang/StringBuilder;
        26: ldc_w         #736                // String .properties
        29: invokevirtual #490                // Method java/lang/StringBuilder.append:(Ljava/lang/String;)Ljava/lang/StringBuilder;
        32: invokevirtual #501                // Method java/lang/StringBuilder.toString:()Ljava/lang/String;
        35: invokeinterface #738,  2          // InterfaceMethod scala$util$PropertiesTrait$_setter_$propFilename_$eq:(Ljava/lang/String;)V
        40: aload_0
        41: aload_0
        42: ldc_w         #740                // String maven.version.number
        45: invokeinterface #234,  2          // InterfaceMethod scalaPropOrNone:(Ljava/lang/String;)Lscala/Option;
        50: invokedynamic #751,  0            // InvokeDynamic #9:apply:()Lscala/Function1;
        55: astore_2
        56: dup
        57: ifnonnull     62
        60: aconst_null
        61: athrow
        62: astore_1
        63: new           #15                 // class scala/Option$WithFilter
        66: dup
        67: aload_1
        68: aload_2
        69: invokespecial #754                // Method scala/Option$WithFilter."<init>":(Lscala/Option;Lscala/Function1;)V
        72: aconst_null
        73: astore_1
        74: aconst_null
        75: astore_2
        76: invokedynamic #759,  0            // InvokeDynamic #10:apply:()Lscala/Function1;
        81: invokevirtual #763                // Method scala/Option$WithFilter.map:(Lscala/Function1;)Lscala/Option;
        84: invokeinterface #765,  2          // InterfaceMethod scala$util$PropertiesTrait$_setter_$releaseVersion_$eq:(Lscala/Option;)V
        89: aload_0
        90: aload_0
        91: ldc_w         #740                // String maven.version.number
        94: invokeinterface #234,  2          // InterfaceMethod scalaPropOrNone:(Ljava/lang/String;)Lscala/Option;
        99: invokedynamic #770,  0            // InvokeDynamic #11:apply:()Lscala/Function1;
       104: astore        4
       106: dup
       107: ifnonnull     112
       110: aconst_null
       111: athrow
       112: astore_3
       113: new           #15                 // class scala/Option$WithFilter
       116: dup
       117: aload_3
       118: aload         4
       120: invokespecial #754                // Method scala/Option$WithFilter."<init>":(Lscala/Option;Lscala/Function1;)V
       123: aconst_null
       124: astore_3
       125: aconst_null
       126: astore        4
       128: aload_0
       129: invokedynamic #777,  0            // InvokeDynamic #12:apply:(Lscala/util/PropertiesTrait;)Lscala/Function1;
       134: invokevirtual #780                // Method scala/Option$WithFilter.flatMap:(Lscala/Function1;)Lscala/Option;
       137: invokeinterface #782,  2          // InterfaceMethod scala$util$PropertiesTrait$_setter_$developmentVersion_$eq:(Lscala/Option;)V
       142: aload_0
       143: new           #480                // class java/lang/StringBuilder
       146: dup
       147: ldc_w         #783                // int 8
       150: invokespecial #484                // Method java/lang/StringBuilder."<init>":(I)V
       153: ldc_w         #785                // String version
       156: invokevirtual #490                // Method java/lang/StringBuilder.append:(Ljava/lang/String;)Ljava/lang/StringBuilder;
       159: aload_0
       160: ldc_w         #259                // String version.number
       163: invokedynamic #789,  0            // InvokeDynamic #13:apply:()Lscala/Function0;
       168: invokeinterface #231,  3          // InterfaceMethod scalaPropOrElse:(Ljava/lang/String;Lscala/Function0;)Ljava/lang/String;
       173: invokevirtual #490                // Method java/lang/StringBuilder.append:(Ljava/lang/String;)Ljava/lang/StringBuilder;
       176: invokevirtual #501                // Method java/lang/StringBuilder.toString:()Ljava/lang/String;
       179: invokeinterface #791,  2          // InterfaceMethod scala$util$PropertiesTrait$_setter_$versionString_$eq:(Ljava/lang/String;)V
       184: aload_0
       185: aload_0
       186: ldc_w         #793                // String copyright.string
       189: invokedynamic #797,  0            // InvokeDynamic #14:apply:()Lscala/Function0;
       194: invokeinterface #231,  3          // InterfaceMethod scalaPropOrElse:(Ljava/lang/String;Lscala/Function0;)Ljava/lang/String;
       199: invokeinterface #799,  2          // InterfaceMethod scala$util$PropertiesTrait$_setter_$copyrightString_$eq:(Ljava/lang/String;)V
       204: return
      StackMapTable: number_of_entries = 2
        frame_type = 255 /* full_frame */
          offset_delta = 62
          locals = [ class scala/util/PropertiesTrait, top, class scala/Function1 ]
          stack = [ class scala/util/PropertiesTrait, class scala/Option ]
        frame_type = 255 /* full_frame */
          offset_delta = 49
          locals = [ class scala/util/PropertiesTrait, null, null, top, class scala/Function1 ]
          stack = [ class scala/util/PropertiesTrait, class scala/Option ]
      LineNumberTable:
        line 35: 0
        line 82: 40
        line 84: 41
        line 96: 89
        line 98: 90
        line 111: 142
        line 112: 184
        line 30: 204
      LocalVariableTable:
        Start  Length  Slot  Name   Signature
            0     205     0 $this   Lscala/util/PropertiesTrait;
           63       9     1 withFilter_this   Lscala/Option;
           63       9     2 withFilter_p   Lscala/Function1;
          113      10     3 withFilter_this   Lscala/Option;
          113      10     4 withFilter_p   Lscala/Function1;
    MethodParameters:
      Name                           Flags
      $this                          final synthetic

  public static java.lang.Object $anonfun$propOrFalse$1$adapted(java.lang.String);
    descriptor: (Ljava/lang/String;)Ljava/lang/Object;
    flags: (0x1009) ACC_PUBLIC, ACC_STATIC, ACC_SYNTHETIC
    Code:
      stack=1, locals=1, args_size=1
         0: aload_0
         1: invokestatic  #191                // InterfaceMethod $anonfun$propOrFalse$1:(Ljava/lang/String;)Z
         4: invokestatic  #811                // Method scala/runtime/BoxesRunTime.boxToBoolean:(Z)Ljava/lang/Boolean;
         7: areturn
      LineNumberTable:
        line 60: 0
      LocalVariableTable:
        Start  Length  Slot  Name   Signature
            0       8     0     x   Ljava/lang/String;
    MethodParameters:
      Name                           Flags
      x                              final

  public static java.lang.Object $anonfun$releaseVersion$1$adapted(java.lang.String);
    descriptor: (Ljava/lang/String;)Ljava/lang/Object;
    flags: (0x1009) ACC_PUBLIC, ACC_STATIC, ACC_SYNTHETIC
    Code:
      stack=1, locals=1, args_size=1
         0: aload_0
         1: invokestatic  #813                // InterfaceMethod $anonfun$releaseVersion$1:(Ljava/lang/String;)Z
         4: invokestatic  #811                // Method scala/runtime/BoxesRunTime.boxToBoolean:(Z)Ljava/lang/Boolean;
         7: areturn
      LineNumberTable:
        line 84: 0
      LocalVariableTable:
        Start  Length  Slot  Name   Signature
            0       8     0     v   Ljava/lang/String;
    MethodParameters:
      Name                           Flags
      v                              final

  public static java.lang.Object $anonfun$developmentVersion$1$adapted(java.lang.String);
    descriptor: (Ljava/lang/String;)Ljava/lang/Object;
    flags: (0x1009) ACC_PUBLIC, ACC_STATIC, ACC_SYNTHETIC
    Code:
      stack=1, locals=1, args_size=1
         0: aload_0
         1: invokestatic  #815                // InterfaceMethod $anonfun$developmentVersion$1:(Ljava/lang/String;)Z
         4: invokestatic  #811                // Method scala/runtime/BoxesRunTime.boxToBoolean:(Z)Ljava/lang/Boolean;
         7: areturn
      LineNumberTable:
        line 98: 0
      LocalVariableTable:
        Start  Length  Slot  Name   Signature
            0       8     0     v   Ljava/lang/String;
    MethodParameters:
      Name                           Flags
      v                              final

  private static java.lang.Object $deserializeLambda$(java.lang.invoke.SerializedLambda);
    descriptor: (Ljava/lang/invoke/SerializedLambda;)Ljava/lang/Object;
    flags: (0x100a) ACC_PRIVATE, ACC_STATIC, ACC_SYNTHETIC
    Code:
      stack=1, locals=1, args_size=1
         0: aload_0
         1: invokedynamic #827,  0            // InvokeDynamic #15:lambdaDeserialize:(Ljava/lang/invoke/SerializedLambda;)Ljava/lang/Object;
         6: areturn
}
InnerClasses:
  public static final #13= #10 of #12;    // Lookup=class java/lang/invoke/MethodHandles$Lookup of class java/lang/invoke/MethodHandles
  public #18= #15 of #17;                 // WithFilter=class scala/Option$WithFilter of class scala/Option
SourceFile: "Properties.scala"
RuntimeVisibleAnnotations:
  0: #6(#7=s#8)
    scala.reflect.ScalaSignature(
      bytes="\u0006\u0005\u0005eh\u0001C\u001f?!\u0003\r\t\u0001\u0011\"\t\u000b\u001d\u0003A\u0011A%\t\u000b5\u0003a\u0011\u0003(\t\u000bi\u0003a\u0011C.\t\u000f-\u0004!\u0019!C\tY\"AA\u000f\u0001EC\u0002\u0013EQ\u000fC\u0003|\u0001\u0011%A\u0010C\u0004\u0002\n\u0001!\t!a\u0003\t\u000f\u0005]\u0001\u0001\"\u0001\u0002\u001a!9\u0011\u0011\u0005\u0001\u0005\u0002\u0005\r\u0002bBA\u0017\u0001\u0011\u0005\u0011q\u0006\u0005\b\u0003g\u0001A\u0011AA\u001b\u0011\u001d\tI\u0004\u0001C\u0001\u0003wAq!!\u0012\u0001\t\u0003\t9\u0005C\u0004\u0002L\u0001!\t!!\u0014\t\u000f\u0005M\u0003\u0001\"\u0001\u0002V!9\u0011\u0011\f\u0001\u0005\u0002\u0005m\u0003bBA1\u0001\u0011\u0005\u00111\r\u0005\b\u0003O\u0002A\u0011AA5\u0011\u001d\t\u0019\b\u0001C\u0001\u0003kBq!a\u001f\u0001\t\u0003\ti\bC\u0004\u0002\u0002\u0002!\t!a!\t\u0013\u0005\u001d\u0005A1A\u0005\u0002\u0005%\u0005\"CAF\u0001\t\u0007I\u0011AAE\u0011\u0019\ti\t\u0001C\u0001\u001d\"A\u0011q\u0012\u0001C\u0002\u0013\u0005A\u000e\u0003\u0005\u0002\u0012\u0002\u0011\r\u0011\"\u0001O\u0011\u0019\t\u0019\n\u0001C\u0001\u001d\"1\u0011Q\u0013\u0001\u0005\u00029Ca!a&\u0001\t\u0003a\u0007BBAM\u0001\u0011\u0005A\u000e\u0003\u0004\u0002\u001c\u0002!\t\u0001\u001c\u0005\u0007\u0003;\u0003A\u0011\u00017\t\r\u0005}\u0005\u0001\"\u0001m\u0011\u0019\t\t\u000b\u0001C\u0001Y\"1\u00111\u0015\u0001\u0005\u00021Da!!*\u0001\t\u0003a\u0007BBAT\u0001\u0011\u0005A\u000e\u0003\u0004\u0002*\u0002!\t\u0001\u001c\u0005\u0007\u0003W\u0003A\u0011\u00017\t\r\u00055\u0006\u0001\"\u0001m\u0011\u0019\ty\u000b\u0001C\u0001Y\"1\u0011\u0011\u0017\u0001\u0005\u00021Da!a-\u0001\t\u0003a\u0007BBA[\u0001\u0011\u0005A\u000e\u0003\u0004\u00028\u0002!\t\u0001\u001c\u0005\u0007\u0003s\u0003A\u0011\u00017\t\r\u0005m\u0006\u0001\"\u0001m\u0011\u001d\ti\f\u0001C\u0001\u0003\u007fCq!!1\u0001\t\u0003\ty\fC\u0004\u0002D\u0002!\t!a0\t\u0011\u0005\u0015\u0007\u0001\"\u0001A\u0003\u007fC\u0001\"a2\u0001\t\u0003\u0001\u0015q\u0018\u0005\u0007\u0003\u0013\u0004A\u0011\u00017\t\u0011\u0005-\u0007\u0001\"\u0001A\u0003\u001bDa!a5\u0001\t\u0003q\u0005BBAk\u0001\u0011\u0005A\u000e\u0003\u0004\u0002X\u0002!\t\u0001\u001c\u0005\b\u00033\u0004A\u0011AAn\u0011\u001d\tI\u000e\u0001C\u0001\u0003CDq!a;\u0001\t\u0003\tiOA\bQe>\u0004XM\u001d;jKN$&/Y5u\u0015\ty\u0004)\u0001\u0003vi&d\'\"A!\u0002\u000bM\u001c\u0017\r\\1\u0014\u0005\u0001\u0019\u0005C\u0001#F\u001b\u0005\u0001\u0015B\u0001$A\u0005\u0019\te.\u001f*fM\u00061A%\u001b8ji\u0012\u001a\u0001\u0001F\u0001K!\t!5*\u0003\u0002M\u0001\n!QK\\5u\u00031\u0001(o\u001c9DCR,wm\u001c:z+\u0005y\u0005C\u0001)X\u001d\t\tV\u000b\u0005\u0002S\u00016\t1K\u0003\u0002U\u0011\u00061AH]8pizJ!A\u0016!\u0002\rA\u0013X\rZ3g\u0013\tA\u0016L\u0001\u0004TiJLgn\u001a\u0006\u0003-\u0002\u000ba\u0002]5dW*\u000b\'OQ1tK\u0012|e.F\u0001]a\ti&\rE\u0002Q=\u0002L!aX-\u0003\u000b\rc\u0017m]:\u0011\u0005\u0005\u0014G\u0002\u0001\u0003\nG\u000e\t\t\u0011!A\u0003\u0002\u0011\u00141a\u0018\u00133#\t)\u0007\u000e\u0005\u0002EM&\u0011q\r\u0011\u0002\b\u001d>$\b.\u001b8h!\t!\u0015.\u0003\u0002k\u0001\n\u0019\u0011I\\=\u0002\u0019A\u0014x\u000e\u001d$jY\u0016t\u0017-\\3\u0016\u00035\u0004\"A\\:\u000e\u0003=T!\u0001]9\u0002\t1\fgn\u001a\u0006\u0002e\u0006!!.\u0019<b\u0013\tAv.\u0001\u0006tG\u0006d\u0017\r\u0015:paN,\u0012A\u001e\t\u0003ofl\u0011\u0001\u001f\u0006\u0003\u007fEL!A\u001f=\u0003\u0015A\u0013x\u000e]3si&,7/\u0001\brk&,G\u000f\\=ESN\u0004xn]3\u0015\t)k\u0018Q\u0001\u0005\u0007}\u001a!\t\u0019A@\u0002\r\u0005\u001cG/[8o!\u0011!\u0015\u0011\u0001&\n\u0007\u0005\r\u0001I\u0001\u0005=Eft\u0017-\\3?\u0011\u001d\t9A\u0002CA\u0002}\f\u0001\u0002Z5ta>\u001c\u0018\r\\\u0001\naJ|\u0007/S:TKR$B!!\u0004\u0002\u0014A\u0019A)a\u0004\n\u0007\u0005E\u0001IA\u0004C_>dW-\u00198\t\r\u0005Uq\u00011\u0001P\u0003\u0011q\u0017-\\3\u0002\u0017A\u0014x\u000e]%t\'\u0016$Hk\u001c\u000b\u0007\u0003\u001b\tY\"!\b\t\r\u0005U\u0001\u00021\u0001P\u0011\u0019\ty\u0002\u0003a\u0001\u001f\u0006)a/\u00197vK\u0006Q\u0001O]8q\u001fJ,En]3\u0015\u000b5\f)#a\n\t\r\u0005U\u0011\u00021\u0001P\u0011!\tI#\u0003CA\u0002\u0005-\u0012aA1miB!A)!\u0001P\u0003-\u0001(o\u001c9Pe\u0016k\u0007\u000f^=\u0015\u00075\f\t\u0004\u0003\u0004\u0002\u0016)\u0001\raT\u0001\u000baJ|\u0007o\u0014:Ok2dGcA7\u00028!1\u0011QC\u0006A\u0002=\u000b!\u0002\u001d:pa>\u0013hj\u001c8f)\u0011\ti$a\u0011\u0011\t\u0011\u000by$\\\u0005\u0004\u0003\u0003\u0002%AB(qi&|g\u000e\u0003\u0004\u0002\u00161\u0001\raT\u0001\faJ|\u0007o\u0014:GC2\u001cX\r\u0006\u0003\u0002\u000e\u0005%\u0003BBA\u000b\u001b\u0001\u0007q*A\u0004tKR\u0004&o\u001c9\u0015\u000b5\fy%!\u0015\t\r\u0005Ua\u00021\u0001P\u0011\u0019\tyB\u0004a\u0001\u001f\u0006I1\r\\3beB\u0013x\u000e\u001d\u000b\u0004[\u0006]\u0003BBA\u000b\u001f\u0001\u0007q*A\u0005f]Z|%/\u00127tKR)Q.!\u0018\u0002`!1\u0011Q\u0003\tA\u0002=C\u0001\"!\u000b\u0011\t\u0003\u0007\u00111F\u0001\nK:4xJ\u001d(p]\u0016$B!!\u0010\u0002f!1\u0011QC\tA\u0002=\u000b\u0011\"\u001a8w\u001fJ\u001cv.\\3\u0015\r\u0005u\u00121NA7\u0011\u0019\t)B\u0005a\u0001\u001f\"A\u0011\u0011\u0006\n\u0005\u0002\u0004\ty\u0007E\u0003E\u0003\u0003\t\t\b\u0005\u0003E\u0003\u007fy\u0015aD:dC2\f\u0007K]8q\u001fJ,En]3\u0015\u000b=\u000b9(!\u001f\t\r\u0005U1\u00031\u0001P\u0011!\tIc\u0005CA\u0002\u0005-\u0012\u0001E:dC2\f\u0007K]8q\u001fJ,U\u000e\u001d;z)\ry\u0015q\u0010\u0005\u0007\u0003+!\u0002\u0019A(\u0002\u001fM\u001c\u0017\r\\1Qe>\u0004xJ\u001d(p]\u0016$B!!\u001d\u0002\u0006\"1\u0011QC\u000bA\u0002=\u000baB]3mK\u0006\u001cXMV3sg&|g.\u0006\u0002\u0002r\u0005\u0011B-\u001a<fY>\u0004X.\u001a8u-\u0016\u00148/[8o\u0003M1XM]:j_:tU/\u001c2feN#(/\u001b8h\u000351XM]:j_:\u001cFO]5oO\u0006y1m\u001c9ze&<\u0007\u000e^*ue&tw-\u0001\bt_V\u00148-Z#oG>$\u0017N\\4\u0002\u0019M|WO]2f%\u0016\fG-\u001a:\u0002\u001d\u0015t7m\u001c3j]\u001e\u001cFO]5oO\u0006iA.\u001b8f\'\u0016\u0004\u0018M]1u_J\fQB[1wC\u000ec\u0017m]:QCRD\u0017\u0001\u00036bm\u0006Du.\\3\u0002\u0015)\fg/\u0019,f]\u0012|\'/A\u0006kCZ\fg+\u001a:tS>t\u0017A\u00036bm\u00064V.\u00138g_\u0006Q!.\u0019<b-6t\u0015-\\3\u0002\u0019)\fg/\u0019,n-\u0016tGm\u001c:\u0002\u001b)\fg/\u0019,n-\u0016\u00148/[8o\u0003=Q\u0017M^1Ta\u0016\u001cg+\u001a:tS>t\u0017A\u00046bm\u0006\u001c\u0006/Z2WK:$wN]\u0001\rU\u00064\u0018m\u00159fG:\u000bW.Z\u0001\u0007_Nt\u0015-\\3\u0002\u0013M\u001c\u0017\r\\1I_6,\u0017A\u0002;na\u0012K\'/A\u0004vg\u0016\u0014H)\u001b:\u0002\u0011U\u001cXM\u001d%p[\u0016\f\u0001\"^:fe:\u000bW.Z\u0001\u0006SN<\u0016N\\\u000b\u0003\u0003\u001b\tQ![:NC\u000e\fq![:MS:,\b0A\u0004jg\u00063\u0018.\u00198\u0002)\r|Gn\u001c:fI>+H\u000f];u\u000b:\f\'\r\\3e\u0003\u001dQGm\u001b%p[\u0016\f!B^3sg&|gNR8s)\ry\u0015q\u001a\u0005\u0007\u0003#4\u0004\u0019A(\u0002\u000f\r|W.\\1oI\u0006Qa/\u001a:tS>tWj]4\u0002\u0011M\u001c\u0017\r\\1D[\u0012\f\u0011b]2bY\u0006\u001c7)\u001c3\u0002\u001b%\u001c(*\u0019<b\u0003RdU-Y:u)\u0011\ti!!8\t\r\u0005}\'\b1\u0001P\u0003\u001d1XM]:j_:$B!!\u0004\u0002d\"9\u0011q\\\u001eA\u0002\u0005\u0015\bc\u0001#\u0002h&\u0019\u0011\u0011\u001e!\u0003\u0007%sG/\u0001\u0003nC&tGc\u0001&\u0002p\"9\u0011\u0011\u001f\u001fA\u0002\u0005M\u0018\u0001B1sON\u0004B\u0001RA{\u001f&\u0019\u0011q\u001f!\u0003\u000b\u0005\u0013(/Y="
    )
BootstrapMethods:
  0: #166 REF_invokeStatic java/lang/invoke/LambdaMetafactory.altMetafactory:(Ljava/lang/invoke/MethodHandles$Lookup;Ljava/lang/String;Ljava/lang/invoke/MethodType;[Ljava/lang/Object;)Ljava/lang/invoke/CallSite;
    Method arguments:
      #152 ()Ljava/lang/Object;
      #156 REF_invokeStatic scala/util/PropertiesTrait.$anonfun$propOrEmpty$1:()Ljava/lang/String;
      #157 ()Ljava/lang/String;
      #158 5
      #159 1
      #157 ()Ljava/lang/String;
  1: #166 REF_invokeStatic java/lang/invoke/LambdaMetafactory.altMetafactory:(Ljava/lang/invoke/MethodHandles$Lookup;Ljava/lang/String;Ljava/lang/invoke/MethodType;[Ljava/lang/Object;)Ljava/lang/invoke/CallSite;
    Method arguments:
      #152 ()Ljava/lang/Object;
      #175 REF_invokeStatic scala/util/PropertiesTrait.$anonfun$propOrNull$1:()Lscala/runtime/Null$;
      #176 ()Lscala/runtime/Null$;
      #158 5
      #159 1
      #176 ()Lscala/runtime/Null$;
  2: #166 REF_invokeStatic java/lang/invoke/LambdaMetafactory.altMetafactory:(Ljava/lang/invoke/MethodHandles$Lookup;Ljava/lang/String;Ljava/lang/invoke/MethodType;[Ljava/lang/Object;)Ljava/lang/invoke/CallSite;
    Method arguments:
      #152 ()Ljava/lang/Object;
      #242 REF_invokeStatic scala/util/PropertiesTrait.$anonfun$scalaPropOrEmpty$1:()Ljava/lang/String;
      #157 ()Ljava/lang/String;
      #158 5
      #159 1
      #157 ()Ljava/lang/String;
  3: #166 REF_invokeStatic java/lang/invoke/LambdaMetafactory.altMetafactory:(Ljava/lang/invoke/MethodHandles$Lookup;Ljava/lang/String;Ljava/lang/invoke/MethodType;[Ljava/lang/Object;)Ljava/lang/invoke/CallSite;
    Method arguments:
      #152 ()Ljava/lang/Object;
      #271 REF_invokeStatic scala/util/PropertiesTrait.$anonfun$sourceEncoding$1:()Ljava/lang/String;
      #157 ()Ljava/lang/String;
      #158 5
      #159 1
      #157 ()Ljava/lang/String;
  4: #166 REF_invokeStatic java/lang/invoke/LambdaMetafactory.altMetafactory:(Ljava/lang/invoke/MethodHandles$Lookup;Ljava/lang/String;Ljava/lang/invoke/MethodType;[Ljava/lang/Object;)Ljava/lang/invoke/CallSite;
    Method arguments:
      #152 ()Ljava/lang/Object;
      #282 REF_invokeStatic scala/util/PropertiesTrait.$anonfun$sourceReader$1:()Ljava/lang/String;
      #157 ()Ljava/lang/String;
      #158 5
      #159 1
      #157 ()Ljava/lang/String;
  5: #166 REF_invokeStatic java/lang/invoke/LambdaMetafactory.altMetafactory:(Ljava/lang/invoke/MethodHandles$Lookup;Ljava/lang/String;Ljava/lang/invoke/MethodType;[Ljava/lang/Object;)Ljava/lang/invoke/CallSite;
    Method arguments:
      #152 ()Ljava/lang/Object;
      #291 REF_invokeStatic scala/util/PropertiesTrait.$anonfun$encodingString$1:()Ljava/lang/String;
      #157 ()Ljava/lang/String;
      #158 5
      #159 1
      #157 ()Ljava/lang/String;
  6: #166 REF_invokeStatic java/lang/invoke/LambdaMetafactory.altMetafactory:(Ljava/lang/invoke/MethodHandles$Lookup;Ljava/lang/String;Ljava/lang/invoke/MethodType;[Ljava/lang/Object;)Ljava/lang/invoke/CallSite;
    Method arguments:
      #152 ()Ljava/lang/Object;
      #441 REF_invokeStatic scala/util/PropertiesTrait.$anonfun$coloredOutputEnabled$1:()Ljava/lang/String;
      #157 ()Ljava/lang/String;
      #158 5
      #159 1
      #157 ()Ljava/lang/String;
  7: #166 REF_invokeStatic java/lang/invoke/LambdaMetafactory.altMetafactory:(Ljava/lang/invoke/MethodHandles$Lookup;Ljava/lang/String;Ljava/lang/invoke/MethodType;[Ljava/lang/Object;)Ljava/lang/invoke/CallSite;
    Method arguments:
      #152 ()Ljava/lang/Object;
      #470 REF_invokeStatic scala/util/PropertiesTrait.$anonfun$jdkHome$1:(Lscala/util/PropertiesTrait;)Ljava/lang/String;
      #157 ()Ljava/lang/String;
      #158 5
      #159 1
      #157 ()Ljava/lang/String;
  8: #166 REF_invokeStatic java/lang/invoke/LambdaMetafactory.altMetafactory:(Ljava/lang/invoke/MethodHandles$Lookup;Ljava/lang/String;Ljava/lang/invoke/MethodType;[Ljava/lang/Object;)Ljava/lang/invoke/CallSite;
    Method arguments:
      #152 ()Ljava/lang/Object;
      #677 REF_invokeStatic scala/util/PropertiesTrait.$anonfun$jdkHome$2:(Lscala/util/PropertiesTrait;)Ljava/lang/String;
      #157 ()Ljava/lang/String;
      #158 5
      #159 1
      #157 ()Ljava/lang/String;
  9: #166 REF_invokeStatic java/lang/invoke/LambdaMetafactory.altMetafactory:(Ljava/lang/invoke/MethodHandles$Lookup;Ljava/lang/String;Ljava/lang/invoke/MethodType;[Ljava/lang/Object;)Ljava/lang/invoke/CallSite;
    Method arguments:
      #742 (Ljava/lang/Object;)Ljava/lang/Object;
      #747 REF_invokeStatic scala/util/PropertiesTrait.$anonfun$releaseVersion$1$adapted:(Ljava/lang/String;)Ljava/lang/Object;
      #748 (Ljava/lang/String;)Ljava/lang/Object;
      #158 5
      #159 1
      #748 (Ljava/lang/String;)Ljava/lang/Object;
  10: #166 REF_invokeStatic java/lang/invoke/LambdaMetafactory.altMetafactory:(Ljava/lang/invoke/MethodHandles$Lookup;Ljava/lang/String;Ljava/lang/invoke/MethodType;[Ljava/lang/Object;)Ljava/lang/invoke/CallSite;
    Method arguments:
      #742 (Ljava/lang/Object;)Ljava/lang/Object;
      #757 REF_invokeStatic scala/util/PropertiesTrait.$anonfun$releaseVersion$2:(Ljava/lang/String;)Ljava/lang/String;
      #758 (Ljava/lang/String;)Ljava/lang/String;
      #158 5
      #159 1
      #758 (Ljava/lang/String;)Ljava/lang/String;
  11: #166 REF_invokeStatic java/lang/invoke/LambdaMetafactory.altMetafactory:(Ljava/lang/invoke/MethodHandles$Lookup;Ljava/lang/String;Ljava/lang/invoke/MethodType;[Ljava/lang/Object;)Ljava/lang/invoke/CallSite;
    Method arguments:
      #742 (Ljava/lang/Object;)Ljava/lang/Object;
      #769 REF_invokeStatic scala/util/PropertiesTrait.$anonfun$developmentVersion$1$adapted:(Ljava/lang/String;)Ljava/lang/Object;
      #748 (Ljava/lang/String;)Ljava/lang/Object;
      #158 5
      #159 1
      #748 (Ljava/lang/String;)Ljava/lang/Object;
  12: #166 REF_invokeStatic java/lang/invoke/LambdaMetafactory.altMetafactory:(Ljava/lang/invoke/MethodHandles$Lookup;Ljava/lang/String;Ljava/lang/invoke/MethodType;[Ljava/lang/Object;)Ljava/lang/invoke/CallSite;
    Method arguments:
      #742 (Ljava/lang/Object;)Ljava/lang/Object;
      #773 REF_invokeStatic scala/util/PropertiesTrait.$anonfun$developmentVersion$2:(Lscala/util/PropertiesTrait;Ljava/lang/String;)Lscala/Option;
      #774 (Ljava/lang/String;)Lscala/Option;
      #158 5
      #159 1
      #774 (Ljava/lang/String;)Lscala/Option;
  13: #166 REF_invokeStatic java/lang/invoke/LambdaMetafactory.altMetafactory:(Ljava/lang/invoke/MethodHandles$Lookup;Ljava/lang/String;Ljava/lang/invoke/MethodType;[Ljava/lang/Object;)Ljava/lang/invoke/CallSite;
    Method arguments:
      #152 ()Ljava/lang/Object;
      #788 REF_invokeStatic scala/util/PropertiesTrait.$anonfun$versionString$1:()Ljava/lang/String;
      #157 ()Ljava/lang/String;
      #158 5
      #159 1
      #157 ()Ljava/lang/String;
  14: #166 REF_invokeStatic java/lang/invoke/LambdaMetafactory.altMetafactory:(Ljava/lang/invoke/MethodHandles$Lookup;Ljava/lang/String;Ljava/lang/invoke/MethodType;[Ljava/lang/Object;)Ljava/lang/invoke/CallSite;
    Method arguments:
      #152 ()Ljava/lang/Object;
      #796 REF_invokeStatic scala/util/PropertiesTrait.$anonfun$copyrightString$1:()Ljava/lang/String;
      #157 ()Ljava/lang/String;
      #158 5
      #159 1
      #157 ()Ljava/lang/String;
  15: #824 REF_invokeStatic scala/runtime/LambdaDeserialize.bootstrap:(Ljava/lang/invoke/MethodHandles$Lookup;Ljava/lang/String;Ljava/lang/invoke/MethodType;[Ljava/lang/invoke/MethodHandle;)Ljava/lang/invoke/CallSite;
    Method arguments:
      #441 REF_invokeStatic scala/util/PropertiesTrait.$anonfun$coloredOutputEnabled$1:()Ljava/lang/String;
      #796 REF_invokeStatic scala/util/PropertiesTrait.$anonfun$copyrightString$1:()Ljava/lang/String;
      #769 REF_invokeStatic scala/util/PropertiesTrait.$anonfun$developmentVersion$1$adapted:(Ljava/lang/String;)Ljava/lang/Object;
      #773 REF_invokeStatic scala/util/PropertiesTrait.$anonfun$developmentVersion$2:(Lscala/util/PropertiesTrait;Ljava/lang/String;)Lscala/Option;
      #291 REF_invokeStatic scala/util/PropertiesTrait.$anonfun$encodingString$1:()Ljava/lang/String;
      #470 REF_invokeStatic scala/util/PropertiesTrait.$anonfun$jdkHome$1:(Lscala/util/PropertiesTrait;)Ljava/lang/String;
      #677 REF_invokeStatic scala/util/PropertiesTrait.$anonfun$jdkHome$2:(Lscala/util/PropertiesTrait;)Ljava/lang/String;
      #156 REF_invokeStatic scala/util/PropertiesTrait.$anonfun$propOrEmpty$1:()Ljava/lang/String;
      #175 REF_invokeStatic scala/util/PropertiesTrait.$anonfun$propOrNull$1:()Lscala/runtime/Null$;
      #747 REF_invokeStatic scala/util/PropertiesTrait.$anonfun$releaseVersion$1$adapted:(Ljava/lang/String;)Ljava/lang/Object;
      #757 REF_invokeStatic scala/util/PropertiesTrait.$anonfun$releaseVersion$2:(Ljava/lang/String;)Ljava/lang/String;
      #242 REF_invokeStatic scala/util/PropertiesTrait.$anonfun$scalaPropOrEmpty$1:()Ljava/lang/String;
      #271 REF_invokeStatic scala/util/PropertiesTrait.$anonfun$sourceEncoding$1:()Ljava/lang/String;
      #282 REF_invokeStatic scala/util/PropertiesTrait.$anonfun$sourceReader$1:()Ljava/lang/String;
      #788 REF_invokeStatic scala/util/PropertiesTrait.$anonfun$versionString$1:()Ljava/lang/String;
  ScalaInlineInfo: length = 0x2C5 (unknown attribute)
   01 00 00 8D 01 B6 00 1D 01 02 99 00 1D 01 02 87
   00 5B 01 02 FE 02 E8 01 02 8A 00 B3 01 02 88 00
   62 01 01 20 00 1D 01 01 D3 00 FE 01 02 A0 00 FE
   01 00 99 00 1D 01 00 BD 00 5B 01 03 25 02 E8 01
   00 AB 00 AC 01 02 7F 00 5B 01 02 E7 02 E8 01 02
   86 00 62 01 00 EF 00 1D 01 00 F6 00 B3 01 02 4B
   02 4C 01 02 4F 00 3D 01 01 0C 00 1D 01 01 17 00
   1D 01 02 96 00 1D 01 02 DA 02 DB 01 00 CB 00 62
   00 00 CA 00 94 01 01 B1 00 88 00 01 B0 01 91 01
   02 11 02 12 01 01 05 00 1D 00 00 FC 00 FA 00 01
   1D 00 1D 00 01 1C 00 FE 01 00 D2 00 79 00 00 D1
   00 76 01 00 D9 00 B5 00 00 D8 00 B3 01 00 DE 00
   DF 00 00 DC 00 DD 01 01 A7 00 88 00 01 A6 01 91
   01 02 0E 02 1D 00 02 0E 00 5B 00 02 0C 02 1C 01
   02 0C 00 58 01 01 A1 00 88 00 01 A0 01 91 01 01
   9B 00 88 00 01 9A 01 91 01 01 92 00 88 00 01 90
   01 91 01 01 2B 00 1D 00 01 2A 00 FE 01 01 31 00
   1D 00 01 30 00 FE 01 01 67 00 1D 00 01 66 00 FE
   01 01 61 00 1D 00 01 60 00 FE 01 01 5B 00 1D 00
   01 5A 00 FE 01 01 37 00 1D 00 01 36 00 FE 01 01
   3D 00 1D 00 01 3C 00 FE 01 01 43 00 1D 00 01 42
   00 FE 01 01 49 00 1D 00 01 48 00 FE 01 01 4F 00
   1D 00 01 4E 00 FE 01 01 55 00 1D 00 01 54 00 FE
   01 01 CE 00 1D 00 01 CD 00 FE 01 01 26 00 1D 00
   01 25 00 FE 01 02 35 02 36 00 02 32 02 33 01 01
   6D 00 1D 00 01 6C 00 FE 01 00 1E 00 1F 00 00 1C
   00 1D 00 00 21 00 1D 00 00 5A 00 5B 00 00 57 00
   58 01 00 68 00 69 00 00 65 00 66 01 00 78 00 79
   00 00 75 00 76 01 00 95 00 62 00 00 93 00 94 01
   00 BA 00 5B 00 00 B9 00 58 01 00 B4 00 B5 00 00
   B2 00 B3 01 00 6C 00 62 00 00 AA 00 94 01 00 4C
   00 4D 01 00 F9 00 FA 00 00 1B 00 14 00 00 19 00
   17 00 00 13 00 14 00 00 16 00 17 00 00 1A 00 14
   00 01 FD 00 1D 00 01 FC 00 FE 01 01 73 00 1D 00
   01 72 00 FE 01 00 E5 00 79 00 00 E4 00 76 01 00
   EC 00 62 00 00 EB 00 94 01 00 E8 00 B5 00 00 F4
   00 B3 01 00 25 00 26 00 00 22 00 23 01 02 05 00
   1D 00 02 04 00 FE 01 00 C3 00 C4 00 00 C1 00 C2
   01 01 07 00 1D 00 01 06 00 FE 01 01 12 00 1D 00
   01 11 00 FE 01 01 79 00 1D 00 01 78 00 FE 01 01
   7F 00 1D 00 01 7E 00 FE 01 01 85 00 1D 00 01 84
   00 FE 01 01 8B 00 1D 00 01 8A 00 FE 01 01 DC 00
   62 00 01 DA 00 94 01 01 F7 00 1D 00 01 F6 00 FE
   01 00 FF 00 1D 00 00 FD 00 FE 01 02 A7 02 A8 01
   01 04 00 1D 00
  ScalaSig: length = 0x3 (unknown attribute)
   05 02 00
