Classfile /Users/mw/Projects/slang-braindump/.jar/jar11/assemble/slang-braindump/assemble/content/scala/util/Sorting.class
  Last modified May 29, 2022; size 4970 bytes
  SHA-256 checksum d47d2a4a54366025117dda4896c710bb813dc0471afadf65fa835d4271b7245d
  Compiled from "Sorting.scala"
public final class scala.util.Sorting
  minor version: 0
  major version: 52
  flags: (0x0031) ACC_PUBLIC, ACC_FINAL, ACC_SUPER
  this_class: #2                          // scala/util/Sorting
  super_class: #4                         // java/lang/Object
  interfaces: 0, fields: 0, methods: 11, attributes: 3
Constant pool:
   #1 = Utf8               scala/util/Sorting
   #2 = Class              #1             // scala/util/Sorting
   #3 = Utf8               java/lang/Object
   #4 = Class              #3             // java/lang/Object
   #5 = Utf8               Sorting.scala
   #6 = Utf8               Lscala/reflect/ScalaSignature;
   #7 = Utf8               bytes
   #8 = Utf8               \u0006\u0005\tEs!\u0002\r\u001a\u0011\u0003qb!\u0002\u0011\u001a\u0011\u0003\t\u0003\"\u0002\u0014\u0002\t\u00039\u0003\"\u0002\u0015\u0002\t\u0003I\u0003\"\u0002\u0015\u0002\t\u0003)\u0004\"\u0002\u0015\u0002\t\u0003Y\u0004bB!\u0002\u0005\u0004%iA\u0011\u0005\u0007\u000b\u0006\u0001\u000bQB\"\t\u000b!\nA\u0011\u0001$\t\u000fy\u000b!\u0019!C\u0007?\"1!-\u0001Q\u0001\u000e\u0001DQaY\u0001\u0005\n\u0011DQA^\u0001\u0005\n]D\u0011\"a\u0007\u0002#\u0003%I!!\b\t\u000f\u0005u\u0012\u0001\"\u0003\u0002@!q\u00111L\u0001\u0005\u0002\u0003\u0015\t\u0011!A\u0005\n\u0005u\u0003bBA5\u0003\u0011%\u00111\u000e\u0005\b\u0003\u0017\u000bA\u0011AAG\u0011\u001d\tY)\u0001C\u0001\u0003GCq!a#\u0002\t\u0003\tY\fC\u0004\u0002\f\u0006!\t!a5\t\u000f\u0005-\u0015\u0001\"\u0001\u0002h\"9\u00111R\u0001\u0005\u0002\t5\u0001bBAF\u0003\u0011\u0005!qE\u0001\b\'>\u0014H/\u001b8h\u0015\tQ2$\u0001\u0003vi&d\'\"\u0001\u000f\u0002\u000bM\u001c\u0017\r\\1\u0004\u0001A\u0011q$A\u0007\u00023\t91k\u001c:uS:<7CA\u0001#!\t\u0019C%D\u0001\u001c\u0013\t)3D\u0001\u0004B]f\u0014VMZ\u0001\u0007y%t\u0017\u000e\u001e \u0015\u0003y\t\u0011\"];jG.\u001cvN\u001d;\u0015\u0005)j\u0003CA\u0012,\u0013\ta3D\u0001\u0003V]&$\b\"\u0002\u0018\u0004\u0001\u0004y\u0013!A1\u0011\u0007\r\u0002$\'\u0003\u000227\t)\u0011I\u001d:bsB\u00111eM\u0005\u0003im\u0011a\u0001R8vE2,GC\u0001\u00167\u0011\u0015qC\u00011\u00018!\r\u0019\u0003\u0007\u000f\t\u0003GeJ!AO\u000e\u0003\u0007%sG\u000f\u0006\u0002+y!)a&\u0002a\u0001{A\u00191\u0005\r \u0011\u0005\rz\u0014B\u0001!\u001c\u0005\u00151En\\1u\u00039\t8o\u001c:u)\"\u0014Xm\u001d5pY\u0012,\u0012aQ\b\u0002\tv\t\u0001#A\brg>\u0014H\u000f\u00165sKNDw\u000e\u001c3!+\t95\u000b\u0006\u0002I9R\u0011!&\u0013\u0005\b\u0015\"\t\t\u0011q\u0001L\u0003))g/\u001b3f]\u000e,G%\r\t\u0004\u0019>\u000bV\"A\'\u000b\u00059[\u0012\u0001B7bi\"L!\u0001U\'\u0003\u0011=\u0013H-\u001a:j]\u001e\u0004\"AU*\r\u0001\u0011)A\u000b\u0003b\u0001+\n\t1*\u0005\u0002W3B\u00111eV\u0005\u00031n\u0011qAT8uQ&tw\r\u0005\u0002$5&\u00111l\u0007\u0002\u0004\u0003:L\b\"\u0002\u0018\t\u0001\u0004i\u0006cA\u00121#\u0006qQ.\u001a:hKRC\'/Z:i_2$W#\u00011\u0010\u0003\u0005l\u0012\u0001I\u0001\u0010[\u0016\u0014x-\u001a+ie\u0016\u001c\bn\u001c7eA\u0005i\u0011N\\:feRLwN\\*peR,\"!Z5\u0015\u000b)2w.]:\t\u000b9Z\u0001\u0019A4\u0011\u0007\r\u0002\u0004\u000e\u0005\u0002SS\u0012I!n\u0003Q\u0001\u0002\u0003\u0015\r!\u0016\u0002\u0002)\"\u0012\u0011\u000e\u001c\t\u0003G5L!A\\\u000e\u0003\u0017M\u0004XmY5bY&TX\r\u001a\u0005\u0006a.\u0001\r\u0001O\u0001\u0003SBBQA]\u0006A\u0002a\n!!\u001b(\t\u000bQ\\\u0001\u0019A;\u0002\u0007=\u0014H\rE\u0002M\u001f\"\f\u0011\"\\3sO\u0016\u001cvN\u001d;\u0016\u0007a\f9\u0001F\u0006z\u0003\u0017\ty!!\u0005\u0002\u0014\u0005]AC\u0001\u0016{\u0011\u001dYH\"!AA\u0004q\f!\"\u001a<jI\u0016t7-\u001a\u00133!\u0015i\u0018\u0011AA\u0003\u001b\u0005q(BA@\u001c\u0003\u001d\u0011XM\u001a7fGRL1!a\u0001\u007f\u0005!\u0019E.Y:t)\u0006<\u0007c\u0001*\u0002\b\u0011I!\u000e\u0004Q\u0001\u0002\u0003\u0015\r!\u0016\u0015\u0004\u0003\u000fa\u0007B\u0002\u0018\r\u0001\u0004\ti\u0001\u0005\u0003$a\u0005\u0015\u0001\"\u00029\r\u0001\u0004A\u0004\"\u0002:\r\u0001\u0004A\u0004B\u0002;\r\u0001\u0004\t)\u0002\u0005\u0003M\u001f\u0006\u0015\u0001\"CA\r\u0019A\u0005\t\u0019AA\u0007\u0003\u001d\u00198M]1uG\"\f1#\\3sO\u0016\u001cvN\u001d;%I\u00164\u0017-\u001e7uIU*B!a\b\u0002:U\u0011\u0011\u0011\u0005\u0016\u0005\u0003G\t9c\u0004\u0002\u0002&\t\u00021FAA\u0015!\u0011\tY#!\u000e\u000e\u0005\u00055\"\u0002BA\u0018\u0003c\t\u0011\"\u001e8dQ\u0016\u001c7.\u001a3\u000b\u0007\u0005M2$\u0001\u0006b]:|G/\u0019;j_:LA!a\u000e\u0002.\t\tRO\\2iK\u000e\\W\r\u001a,be&\fgnY3\u0005\u0013)l\u0001\u0015!A\u0001\u0006\u0004)\u0006fAA\u001dY\u0006YQ.\u001a:hKN{\'\u000f^3e+\u0011\t\t%!\u0013\u0015\u001b)\n\u0019%!\u0014\u0002P\u0005M\u0013QKA-\u0011\u0019qc\u00021\u0001\u0002FA!1\u0005MA$!\r\u0011\u0016\u0011\n\u0003\nU:\u0001\u000b\u0011!AC\u0002UC3!!\u0013m\u0011\u0015\u0001h\u00021\u00019\u0011\u0019\t\tF\u0004a\u0001q\u0005\u0011\u0011n\u0013\u0005\u0006e:\u0001\r\u0001\u000f\u0005\u0007i:\u0001\r!a\u0016\u0011\t1{\u0015q\t\u0005\b\u00033q\u0001\u0019AA#\u0003}\u00198-\u00197bIU$\u0018\u000e\u001c\u0013T_J$\u0018N\\4%I\t|w\u000e\\3b]N{\'\u000f\u001e\u000b\u0004U\u0005}\u0003B\u0002\u0018\u0010\u0001\u0004\t\t\u0007\u0005\u0003$a\u0005\r\u0004cA\u0012\u0002f%\u0019\u0011qM\u000e\u0003\u000f\t{w\u000e\\3b]\u0006!1o\u001c:u+\u0011\ti\'!\u001e\u0015\u0013)\ny\'a\u001e\u0002|\u0005}\u0004B\u0002\u0018\u0011\u0001\u0004\t\t\b\u0005\u0003$a\u0005M\u0004c\u0001*\u0002v\u0011)!\u000e\u0005b\u0001+\"1\u0011\u0011\u0010\tA\u0002a\nAA\u001a:p[\"1\u0011Q\u0010\tA\u0002a\nQ!\u001e8uS2Da\u0001\u001e\tA\u0002\u0005\u0005\u0005\u0003\u0002\'P\u0003gB3\u0001EAC!\r\u0019\u0013qQ\u0005\u0004\u0003\u0013[\"AB5oY&tW-\u0001\u0006ti\u0006\u0014G.Z*peR,B!a$\u0002\u001cR!\u0011\u0011SAO)\rQ\u00131\u0013\u0005\n\u0003+\u000b\u0012\u0011!a\u0002\u0003/\u000b!\"\u001a<jI\u0016t7-\u001a\u00134!\u0011au*!\'\u0011\u0007I\u000bY\nB\u0003U#\t\u0007Q\u000b\u0003\u0004/#\u0001\u0007\u0011q\u0014\t\u0005GA\nI\nK\u0002\u0012\u0003\u000b+B!!*\u00022RA\u0011qUAZ\u0003o\u000bI\fF\u0002+\u0003SC\u0011\"a+\u0013\u0003\u0003\u0005\u001d!!,\u0002\u0015\u00154\u0018\u000eZ3oG\u0016$C\u0007\u0005\u0003M\u001f\u0006=\u0006c\u0001*\u00022\u0012)AK\u0005b\u0001+\"1aF\u0005a\u0001\u0003k\u0003Ba\t\u0019\u00020\"1\u0011\u0011\u0010\nA\u0002aBa!! \u0013\u0001\u0004AT\u0003BA_\u0003\u000b$RAKA`\u0003\u000fDaAL\nA\u0002\u0005\u0005\u0007\u0003B\u00121\u0003\u0007\u00042AUAc\t\u0015!6C1\u0001V\u0011\u001d\tIm\u0005a\u0001\u0003\u0017\f\u0011A\u001a\t\nG\u00055\u00171YAb\u0003GJ1!a4\u001c\u0005%1UO\\2uS>t\'\u0007K\u0002\u0014\u0003\u000b+B!!6\u0002^RI!&a6\u0002`\u0006\r\u0018Q\u001d\u0005\u0007]Q\u0001\r!!7\u0011\t\r\u0002\u00141\u001c\t\u0004%\u0006uG!\u0002+\u0015\u0005\u0004)\u0006bBAe)\u0001\u0007\u0011\u0011\u001d\t\nG\u00055\u00171\\An\u0003GBa!!\u001f\u0015\u0001\u0004A\u0004BBA?)\u0001\u0007\u0001(\u0006\u0003\u0002j\u0006EH\u0003BAv\u0003\u007f$b!!<\u0002t\u0006e\b\u0003B\u00121\u0003_\u00042AUAy\t\u0015!VC1\u0001V\u0011%\t)0FA\u0001\u0002\b\t90\u0001\u0006fm&$WM\\2fIU\u0002R!`A\u0001\u0003_D\u0011\"a?\u0016\u0003\u0003\u0005\u001d!!@\u0002\u0015\u00154\u0018\u000eZ3oG\u0016$c\u0007\u0005\u0003M\u001f\u0006=\bB\u0002\u0018\u0016\u0001\u0004\u0011\t\u0001\u0005\u0004\u0003\u0004\t%\u0011q^\u0007\u0003\u0005\u000bQ1Aa\u0002\u001c\u0003)\u0019w\u000e\u001c7fGRLwN\\\u0005\u0005\u0005\u0017\u0011)AA\u0002TKF,BAa\u0004\u0003\u0018Q1!\u0011\u0003B\u0010\u0005G!BAa\u0005\u0003\u001aA!1\u0005\rB\u000b!\r\u0011&q\u0003\u0003\u0006)Z\u0011\r!\u0016\u0005\n\u000571\u0012\u0011!a\u0002\u0005;\t!\"\u001a<jI\u0016t7-\u001a\u00138!\u0015i\u0018\u0011\u0001B\u000b\u0011\u0019qc\u00031\u0001\u0003\"A1!1\u0001B\u0005\u0005+Aq!!3\u0017\u0001\u0004\u0011)\u0003E\u0005$\u0003\u001b\u0014)B!\u0006\u0002dU1!\u0011\u0006B\u0019\u0005\u0003\"bAa\u000b\u0003F\t%CC\u0002B\u0017\u0005g\u0011I\u0004\u0005\u0003$a\t=\u0002c\u0001*\u00032\u0011)Ak\u0006b\u0001+\"I!QG\f\u0002\u0002\u0003\u000f!qG\u0001\u000bKZLG-\u001a8dK\u0012B\u0004#B?\u0002\u0002\t=\u0002\"\u0003B\u001e/\u0005\u0005\t9\u0001B\u001f\u0003))g/\u001b3f]\u000e,G%\u000f\t\u0005\u0019>\u0013y\u0004E\u0002S\u0005\u0003\"aAa\u0011\u0018\u0005\u0004)&!A\'\t\r9:\u0002\u0019\u0001B$!\u0019\u0011\u0019A!\u0003\u00030!9\u0011\u0011Z\fA\u0002\t-\u0003cB\u0012\u0003N\t=\"qH\u0005\u0004\u0005\u001fZ\"!\u0003$v]\u000e$\u0018n\u001c82\u0001
   #9 = Utf8               stableSort
  #10 = Utf8               (Lscala/collection/Seq;Lscala/Function1;Lscala/reflect/ClassTag;Lscala/math/Ordering;)Ljava/lang/Object;
  #11 = Utf8               a
  #12 = Utf8               f
  #13 = Utf8               evidence$8
  #14 = Utf8               evidence$9
  #15 = Utf8               scala/util/Sorting$
  #16 = Class              #15            // scala/util/Sorting$
  #17 = Utf8               MODULE$
  #18 = Utf8               Lscala/util/Sorting$;
  #19 = NameAndType        #17:#18        // MODULE$:Lscala/util/Sorting$;
  #20 = Fieldref           #16.#19        // scala/util/Sorting$.MODULE$:Lscala/util/Sorting$;
  #21 = NameAndType        #9:#10         // stableSort:(Lscala/collection/Seq;Lscala/Function1;Lscala/reflect/ClassTag;Lscala/math/Ordering;)Ljava/lang/Object;
  #22 = Methodref          #16.#21        // scala/util/Sorting$.stableSort:(Lscala/collection/Seq;Lscala/Function1;Lscala/reflect/ClassTag;Lscala/math/Ordering;)Ljava/lang/Object;
  #23 = Utf8               Lscala/collection/Seq;
  #24 = Utf8               Lscala/Function1;
  #25 = Utf8               Lscala/reflect/ClassTag;
  #26 = Utf8               Lscala/math/Ordering;
  #27 = Utf8               (Lscala/collection/Seq;Lscala/Function2;Lscala/reflect/ClassTag;)Ljava/lang/Object;
  #28 = Utf8               evidence$7
  #29 = NameAndType        #9:#27         // stableSort:(Lscala/collection/Seq;Lscala/Function2;Lscala/reflect/ClassTag;)Ljava/lang/Object;
  #30 = Methodref          #16.#29        // scala/util/Sorting$.stableSort:(Lscala/collection/Seq;Lscala/Function2;Lscala/reflect/ClassTag;)Ljava/lang/Object;
  #31 = Utf8               Lscala/Function2;
  #32 = Utf8               (Lscala/collection/Seq;Lscala/reflect/ClassTag;Lscala/math/Ordering;)Ljava/lang/Object;
  #33 = Utf8               evidence$5
  #34 = Utf8               evidence$6
  #35 = NameAndType        #9:#32         // stableSort:(Lscala/collection/Seq;Lscala/reflect/ClassTag;Lscala/math/Ordering;)Ljava/lang/Object;
  #36 = Methodref          #16.#35        // scala/util/Sorting$.stableSort:(Lscala/collection/Seq;Lscala/reflect/ClassTag;Lscala/math/Ordering;)Ljava/lang/Object;
  #37 = Utf8               (Ljava/lang/Object;Lscala/Function2;II)V
  #38 = Utf8               <K:Ljava/lang/Object;>(Ljava/lang/Object;Lscala/Function2<TK;TK;Ljava/lang/Object;>;II)V
  #39 = Utf8               from
  #40 = Utf8               until
  #41 = NameAndType        #9:#37         // stableSort:(Ljava/lang/Object;Lscala/Function2;II)V
  #42 = Methodref          #16.#41        // scala/util/Sorting$.stableSort:(Ljava/lang/Object;Lscala/Function2;II)V
  #43 = Utf8               Ljava/lang/Object;
  #44 = Utf8               I
  #45 = Utf8               (Ljava/lang/Object;Lscala/Function2;)V
  #46 = Utf8               <K:Ljava/lang/Object;>(Ljava/lang/Object;Lscala/Function2<TK;TK;Ljava/lang/Object;>;)V
  #47 = NameAndType        #9:#45         // stableSort:(Ljava/lang/Object;Lscala/Function2;)V
  #48 = Methodref          #16.#47        // scala/util/Sorting$.stableSort:(Ljava/lang/Object;Lscala/Function2;)V
  #49 = Utf8               (Ljava/lang/Object;IILscala/math/Ordering;)V
  #50 = Utf8               <K:Ljava/lang/Object;>(Ljava/lang/Object;IILscala/math/Ordering<TK;>;)V
  #51 = Utf8               evidence$4
  #52 = NameAndType        #9:#49         // stableSort:(Ljava/lang/Object;IILscala/math/Ordering;)V
  #53 = Methodref          #16.#52        // scala/util/Sorting$.stableSort:(Ljava/lang/Object;IILscala/math/Ordering;)V
  #54 = Utf8               (Ljava/lang/Object;Lscala/math/Ordering;)V
  #55 = Utf8               <K:Ljava/lang/Object;>(Ljava/lang/Object;Lscala/math/Ordering<TK;>;)V
  #56 = Utf8               evidence$3
  #57 = NameAndType        #9:#54         // stableSort:(Ljava/lang/Object;Lscala/math/Ordering;)V
  #58 = Methodref          #16.#57        // scala/util/Sorting$.stableSort:(Ljava/lang/Object;Lscala/math/Ordering;)V
  #59 = Utf8               quickSort
  #60 = Utf8               evidence$1
  #61 = NameAndType        #59:#54        // quickSort:(Ljava/lang/Object;Lscala/math/Ordering;)V
  #62 = Methodref          #16.#61        // scala/util/Sorting$.quickSort:(Ljava/lang/Object;Lscala/math/Ordering;)V
  #63 = Utf8               ([F)V
  #64 = NameAndType        #59:#63        // quickSort:([F)V
  #65 = Methodref          #16.#64        // scala/util/Sorting$.quickSort:([F)V
  #66 = Utf8               [F
  #67 = Utf8               ([I)V
  #68 = NameAndType        #59:#67        // quickSort:([I)V
  #69 = Methodref          #16.#68        // scala/util/Sorting$.quickSort:([I)V
  #70 = Utf8               [I
  #71 = Utf8               ([D)V
  #72 = NameAndType        #59:#71        // quickSort:([D)V
  #73 = Methodref          #16.#72        // scala/util/Sorting$.quickSort:([D)V
  #74 = Utf8               [D
  #75 = Utf8               Code
  #76 = Utf8               LocalVariableTable
  #77 = Utf8               MethodParameters
  #78 = Utf8               Signature
  #79 = Utf8               SourceFile
  #80 = Utf8               RuntimeVisibleAnnotations
  #81 = Utf8               ScalaSig
{
  public static java.lang.Object stableSort(scala.collection.Seq, scala.Function1, scala.reflect.ClassTag, scala.math.Ordering);
    descriptor: (Lscala/collection/Seq;Lscala/Function1;Lscala/reflect/ClassTag;Lscala/math/Ordering;)Ljava/lang/Object;
    flags: (0x0009) ACC_PUBLIC, ACC_STATIC
    Code:
      stack=5, locals=4, args_size=4
         0: getstatic     #20                 // Field scala/util/Sorting$.MODULE$:Lscala/util/Sorting$;
         3: aload_0
         4: aload_1
         5: aload_2
         6: aload_3
         7: invokevirtual #22                 // Method scala/util/Sorting$.stableSort:(Lscala/collection/Seq;Lscala/Function1;Lscala/reflect/ClassTag;Lscala/math/Ordering;)Ljava/lang/Object;
        10: areturn
      LocalVariableTable:
        Start  Length  Slot  Name   Signature
            0      11     0     a   Lscala/collection/Seq;
            0      11     1     f   Lscala/Function1;
            0      11     2 evidence$8   Lscala/reflect/ClassTag;
            0      11     3 evidence$9   Lscala/math/Ordering;
    MethodParameters:
      Name                           Flags
      a                              final
      f                              final
      evidence$8                     final
      evidence$9                     final

  public static java.lang.Object stableSort(scala.collection.Seq, scala.Function2, scala.reflect.ClassTag);
    descriptor: (Lscala/collection/Seq;Lscala/Function2;Lscala/reflect/ClassTag;)Ljava/lang/Object;
    flags: (0x0009) ACC_PUBLIC, ACC_STATIC
    Code:
      stack=4, locals=3, args_size=3
         0: getstatic     #20                 // Field scala/util/Sorting$.MODULE$:Lscala/util/Sorting$;
         3: aload_0
         4: aload_1
         5: aload_2
         6: invokevirtual #30                 // Method scala/util/Sorting$.stableSort:(Lscala/collection/Seq;Lscala/Function2;Lscala/reflect/ClassTag;)Ljava/lang/Object;
         9: areturn
      LocalVariableTable:
        Start  Length  Slot  Name   Signature
            0      10     0     a   Lscala/collection/Seq;
            0      10     1     f   Lscala/Function2;
            0      10     2 evidence$7   Lscala/reflect/ClassTag;
    MethodParameters:
      Name                           Flags
      a                              final
      f                              final
      evidence$7                     final

  public static java.lang.Object stableSort(scala.collection.Seq, scala.reflect.ClassTag, scala.math.Ordering);
    descriptor: (Lscala/collection/Seq;Lscala/reflect/ClassTag;Lscala/math/Ordering;)Ljava/lang/Object;
    flags: (0x0009) ACC_PUBLIC, ACC_STATIC
    Code:
      stack=4, locals=3, args_size=3
         0: getstatic     #20                 // Field scala/util/Sorting$.MODULE$:Lscala/util/Sorting$;
         3: aload_0
         4: aload_1
         5: aload_2
         6: invokevirtual #36                 // Method scala/util/Sorting$.stableSort:(Lscala/collection/Seq;Lscala/reflect/ClassTag;Lscala/math/Ordering;)Ljava/lang/Object;
         9: areturn
      LocalVariableTable:
        Start  Length  Slot  Name   Signature
            0      10     0     a   Lscala/collection/Seq;
            0      10     1 evidence$5   Lscala/reflect/ClassTag;
            0      10     2 evidence$6   Lscala/math/Ordering;
    MethodParameters:
      Name                           Flags
      a                              final
      evidence$5                     final
      evidence$6                     final

  public static <K extends java.lang.Object> void stableSort(java.lang.Object, scala.Function2<K, K, java.lang.Object>, int, int);
    descriptor: (Ljava/lang/Object;Lscala/Function2;II)V
    flags: (0x0009) ACC_PUBLIC, ACC_STATIC
    Code:
      stack=5, locals=4, args_size=4
         0: getstatic     #20                 // Field scala/util/Sorting$.MODULE$:Lscala/util/Sorting$;
         3: aload_0
         4: aload_1
         5: iload_2
         6: iload_3
         7: invokevirtual #42                 // Method scala/util/Sorting$.stableSort:(Ljava/lang/Object;Lscala/Function2;II)V
        10: return
      LocalVariableTable:
        Start  Length  Slot  Name   Signature
            0      11     0     a   Ljava/lang/Object;
            0      11     1     f   Lscala/Function2;
            0      11     2  from   I
            0      11     3 until   I
    Signature: #38                          // <K:Ljava/lang/Object;>(Ljava/lang/Object;Lscala/Function2<TK;TK;Ljava/lang/Object;>;II)V
    MethodParameters:
      Name                           Flags
      a                              final
      f                              final
      from                           final
      until                          final

  public static <K extends java.lang.Object> void stableSort(java.lang.Object, scala.Function2<K, K, java.lang.Object>);
    descriptor: (Ljava/lang/Object;Lscala/Function2;)V
    flags: (0x0009) ACC_PUBLIC, ACC_STATIC
    Code:
      stack=3, locals=2, args_size=2
         0: getstatic     #20                 // Field scala/util/Sorting$.MODULE$:Lscala/util/Sorting$;
         3: aload_0
         4: aload_1
         5: invokevirtual #48                 // Method scala/util/Sorting$.stableSort:(Ljava/lang/Object;Lscala/Function2;)V
         8: return
      LocalVariableTable:
        Start  Length  Slot  Name   Signature
            0       9     0     a   Ljava/lang/Object;
            0       9     1     f   Lscala/Function2;
    Signature: #46                          // <K:Ljava/lang/Object;>(Ljava/lang/Object;Lscala/Function2<TK;TK;Ljava/lang/Object;>;)V
    MethodParameters:
      Name                           Flags
      a                              final
      f                              final

  public static <K extends java.lang.Object> void stableSort(java.lang.Object, int, int, scala.math.Ordering<K>);
    descriptor: (Ljava/lang/Object;IILscala/math/Ordering;)V
    flags: (0x0009) ACC_PUBLIC, ACC_STATIC
    Code:
      stack=5, locals=4, args_size=4
         0: getstatic     #20                 // Field scala/util/Sorting$.MODULE$:Lscala/util/Sorting$;
         3: aload_0
         4: iload_1
         5: iload_2
         6: aload_3
         7: invokevirtual #53                 // Method scala/util/Sorting$.stableSort:(Ljava/lang/Object;IILscala/math/Ordering;)V
        10: return
      LocalVariableTable:
        Start  Length  Slot  Name   Signature
            0      11     0     a   Ljava/lang/Object;
            0      11     1  from   I
            0      11     2 until   I
            0      11     3 evidence$4   Lscala/math/Ordering;
    Signature: #50                          // <K:Ljava/lang/Object;>(Ljava/lang/Object;IILscala/math/Ordering<TK;>;)V
    MethodParameters:
      Name                           Flags
      a                              final
      from                           final
      until                          final
      evidence$4                     final

  public static <K extends java.lang.Object> void stableSort(java.lang.Object, scala.math.Ordering<K>);
    descriptor: (Ljava/lang/Object;Lscala/math/Ordering;)V
    flags: (0x0009) ACC_PUBLIC, ACC_STATIC
    Code:
      stack=3, locals=2, args_size=2
         0: getstatic     #20                 // Field scala/util/Sorting$.MODULE$:Lscala/util/Sorting$;
         3: aload_0
         4: aload_1
         5: invokevirtual #58                 // Method scala/util/Sorting$.stableSort:(Ljava/lang/Object;Lscala/math/Ordering;)V
         8: return
      LocalVariableTable:
        Start  Length  Slot  Name   Signature
            0       9     0     a   Ljava/lang/Object;
            0       9     1 evidence$3   Lscala/math/Ordering;
    Signature: #55                          // <K:Ljava/lang/Object;>(Ljava/lang/Object;Lscala/math/Ordering<TK;>;)V
    MethodParameters:
      Name                           Flags
      a                              final
      evidence$3                     final

  public static <K extends java.lang.Object> void quickSort(java.lang.Object, scala.math.Ordering<K>);
    descriptor: (Ljava/lang/Object;Lscala/math/Ordering;)V
    flags: (0x0009) ACC_PUBLIC, ACC_STATIC
    Code:
      stack=3, locals=2, args_size=2
         0: getstatic     #20                 // Field scala/util/Sorting$.MODULE$:Lscala/util/Sorting$;
         3: aload_0
         4: aload_1
         5: invokevirtual #62                 // Method scala/util/Sorting$.quickSort:(Ljava/lang/Object;Lscala/math/Ordering;)V
         8: return
      LocalVariableTable:
        Start  Length  Slot  Name   Signature
            0       9     0     a   Ljava/lang/Object;
            0       9     1 evidence$1   Lscala/math/Ordering;
    Signature: #55                          // <K:Ljava/lang/Object;>(Ljava/lang/Object;Lscala/math/Ordering<TK;>;)V
    MethodParameters:
      Name                           Flags
      a                              final
      evidence$1                     final

  public static void quickSort(float[]);
    descriptor: ([F)V
    flags: (0x0009) ACC_PUBLIC, ACC_STATIC
    Code:
      stack=2, locals=1, args_size=1
         0: getstatic     #20                 // Field scala/util/Sorting$.MODULE$:Lscala/util/Sorting$;
         3: aload_0
         4: invokevirtual #65                 // Method scala/util/Sorting$.quickSort:([F)V
         7: return
      LocalVariableTable:
        Start  Length  Slot  Name   Signature
            0       8     0     a   [F
    MethodParameters:
      Name                           Flags
      a                              final

  public static void quickSort(int[]);
    descriptor: ([I)V
    flags: (0x0009) ACC_PUBLIC, ACC_STATIC
    Code:
      stack=2, locals=1, args_size=1
         0: getstatic     #20                 // Field scala/util/Sorting$.MODULE$:Lscala/util/Sorting$;
         3: aload_0
         4: invokevirtual #69                 // Method scala/util/Sorting$.quickSort:([I)V
         7: return
      LocalVariableTable:
        Start  Length  Slot  Name   Signature
            0       8     0     a   [I
    MethodParameters:
      Name                           Flags
      a                              final

  public static void quickSort(double[]);
    descriptor: ([D)V
    flags: (0x0009) ACC_PUBLIC, ACC_STATIC
    Code:
      stack=2, locals=1, args_size=1
         0: getstatic     #20                 // Field scala/util/Sorting$.MODULE$:Lscala/util/Sorting$;
         3: aload_0
         4: invokevirtual #73                 // Method scala/util/Sorting$.quickSort:([D)V
         7: return
      LocalVariableTable:
        Start  Length  Slot  Name   Signature
            0       8     0     a   [D
    MethodParameters:
      Name                           Flags
      a                              final
}
SourceFile: "Sorting.scala"
RuntimeVisibleAnnotations:
  0: #6(#7=s#8)
    scala.reflect.ScalaSignature(
      bytes="\u0006\u0005\tEs!\u0002\r\u001a\u0011\u0003qb!\u0002\u0011\u001a\u0011\u0003\t\u0003\"\u0002\u0014\u0002\t\u00039\u0003\"\u0002\u0015\u0002\t\u0003I\u0003\"\u0002\u0015\u0002\t\u0003)\u0004\"\u0002\u0015\u0002\t\u0003Y\u0004bB!\u0002\u0005\u0004%iA\u0011\u0005\u0007\u000b\u0006\u0001\u000bQB\"\t\u000b!\nA\u0011\u0001$\t\u000fy\u000b!\u0019!C\u0007?\"1!-\u0001Q\u0001\u000e\u0001DQaY\u0001\u0005\n\u0011DQA^\u0001\u0005\n]D\u0011\"a\u0007\u0002#\u0003%I!!\b\t\u000f\u0005u\u0012\u0001\"\u0003\u0002@!q\u00111L\u0001\u0005\u0002\u0003\u0015\t\u0011!A\u0005\n\u0005u\u0003bBA5\u0003\u0011%\u00111\u000e\u0005\b\u0003\u0017\u000bA\u0011AAG\u0011\u001d\tY)\u0001C\u0001\u0003GCq!a#\u0002\t\u0003\tY\fC\u0004\u0002\f\u0006!\t!a5\t\u000f\u0005-\u0015\u0001\"\u0001\u0002h\"9\u00111R\u0001\u0005\u0002\t5\u0001bBAF\u0003\u0011\u0005!qE\u0001\b\'>\u0014H/\u001b8h\u0015\tQ2$\u0001\u0003vi&d\'\"\u0001\u000f\u0002\u000bM\u001c\u0017\r\\1\u0004\u0001A\u0011q$A\u0007\u00023\t91k\u001c:uS:<7CA\u0001#!\t\u0019C%D\u0001\u001c\u0013\t)3D\u0001\u0004B]f\u0014VMZ\u0001\u0007y%t\u0017\u000e\u001e \u0015\u0003y\t\u0011\"];jG.\u001cvN\u001d;\u0015\u0005)j\u0003CA\u0012,\u0013\ta3D\u0001\u0003V]&$\b\"\u0002\u0018\u0004\u0001\u0004y\u0013!A1\u0011\u0007\r\u0002$\'\u0003\u000227\t)\u0011I\u001d:bsB\u00111eM\u0005\u0003im\u0011a\u0001R8vE2,GC\u0001\u00167\u0011\u0015qC\u00011\u00018!\r\u0019\u0003\u0007\u000f\t\u0003GeJ!AO\u000e\u0003\u0007%sG\u000f\u0006\u0002+y!)a&\u0002a\u0001{A\u00191\u0005\r \u0011\u0005\rz\u0014B\u0001!\u001c\u0005\u00151En\\1u\u00039\t8o\u001c:u)\"\u0014Xm\u001d5pY\u0012,\u0012aQ\b\u0002\tv\t\u0001#A\brg>\u0014H\u000f\u00165sKNDw\u000e\u001c3!+\t95\u000b\u0006\u0002I9R\u0011!&\u0013\u0005\b\u0015\"\t\t\u0011q\u0001L\u0003))g/\u001b3f]\u000e,G%\r\t\u0004\u0019>\u000bV\"A\'\u000b\u00059[\u0012\u0001B7bi\"L!\u0001U\'\u0003\u0011=\u0013H-\u001a:j]\u001e\u0004\"AU*\r\u0001\u0011)A\u000b\u0003b\u0001+\n\t1*\u0005\u0002W3B\u00111eV\u0005\u00031n\u0011qAT8uQ&tw\r\u0005\u0002$5&\u00111l\u0007\u0002\u0004\u0003:L\b\"\u0002\u0018\t\u0001\u0004i\u0006cA\u00121#\u0006qQ.\u001a:hKRC\'/Z:i_2$W#\u00011\u0010\u0003\u0005l\u0012\u0001I\u0001\u0010[\u0016\u0014x-\u001a+ie\u0016\u001c\bn\u001c7eA\u0005i\u0011N\\:feRLwN\\*peR,\"!Z5\u0015\u000b)2w.]:\t\u000b9Z\u0001\u0019A4\u0011\u0007\r\u0002\u0004\u000e\u0005\u0002SS\u0012I!n\u0003Q\u0001\u0002\u0003\u0015\r!\u0016\u0002\u0002)\"\u0012\u0011\u000e\u001c\t\u0003G5L!A\\\u000e\u0003\u0017M\u0004XmY5bY&TX\r\u001a\u0005\u0006a.\u0001\r\u0001O\u0001\u0003SBBQA]\u0006A\u0002a\n!!\u001b(\t\u000bQ\\\u0001\u0019A;\u0002\u0007=\u0014H\rE\u0002M\u001f\"\f\u0011\"\\3sO\u0016\u001cvN\u001d;\u0016\u0007a\f9\u0001F\u0006z\u0003\u0017\ty!!\u0005\u0002\u0014\u0005]AC\u0001\u0016{\u0011\u001dYH\"!AA\u0004q\f!\"\u001a<jI\u0016t7-\u001a\u00133!\u0015i\u0018\u0011AA\u0003\u001b\u0005q(BA@\u001c\u0003\u001d\u0011XM\u001a7fGRL1!a\u0001\u007f\u0005!\u0019E.Y:t)\u0006<\u0007c\u0001*\u0002\b\u0011I!\u000e\u0004Q\u0001\u0002\u0003\u0015\r!\u0016\u0015\u0004\u0003\u000fa\u0007B\u0002\u0018\r\u0001\u0004\ti\u0001\u0005\u0003$a\u0005\u0015\u0001\"\u00029\r\u0001\u0004A\u0004\"\u0002:\r\u0001\u0004A\u0004B\u0002;\r\u0001\u0004\t)\u0002\u0005\u0003M\u001f\u0006\u0015\u0001\"CA\r\u0019A\u0005\t\u0019AA\u0007\u0003\u001d\u00198M]1uG\"\f1#\\3sO\u0016\u001cvN\u001d;%I\u00164\u0017-\u001e7uIU*B!a\b\u0002:U\u0011\u0011\u0011\u0005\u0016\u0005\u0003G\t9c\u0004\u0002\u0002&\t\u00021FAA\u0015!\u0011\tY#!\u000e\u000e\u0005\u00055\"\u0002BA\u0018\u0003c\t\u0011\"\u001e8dQ\u0016\u001c7.\u001a3\u000b\u0007\u0005M2$\u0001\u0006b]:|G/\u0019;j_:LA!a\u000e\u0002.\t\tRO\\2iK\u000e\\W\r\u001a,be&\fgnY3\u0005\u0013)l\u0001\u0015!A\u0001\u0006\u0004)\u0006fAA\u001dY\u0006YQ.\u001a:hKN{\'\u000f^3e+\u0011\t\t%!\u0013\u0015\u001b)\n\u0019%!\u0014\u0002P\u0005M\u0013QKA-\u0011\u0019qc\u00021\u0001\u0002FA!1\u0005MA$!\r\u0011\u0016\u0011\n\u0003\nU:\u0001\u000b\u0011!AC\u0002UC3!!\u0013m\u0011\u0015\u0001h\u00021\u00019\u0011\u0019\t\tF\u0004a\u0001q\u0005\u0011\u0011n\u0013\u0005\u0006e:\u0001\r\u0001\u000f\u0005\u0007i:\u0001\r!a\u0016\u0011\t1{\u0015q\t\u0005\b\u00033q\u0001\u0019AA#\u0003}\u00198-\u00197bIU$\u0018\u000e\u001c\u0013T_J$\u0018N\\4%I\t|w\u000e\\3b]N{\'\u000f\u001e\u000b\u0004U\u0005}\u0003B\u0002\u0018\u0010\u0001\u0004\t\t\u0007\u0005\u0003$a\u0005\r\u0004cA\u0012\u0002f%\u0019\u0011qM\u000e\u0003\u000f\t{w\u000e\\3b]\u0006!1o\u001c:u+\u0011\ti\'!\u001e\u0015\u0013)\ny\'a\u001e\u0002|\u0005}\u0004B\u0002\u0018\u0011\u0001\u0004\t\t\b\u0005\u0003$a\u0005M\u0004c\u0001*\u0002v\u0011)!\u000e\u0005b\u0001+\"1\u0011\u0011\u0010\tA\u0002a\nAA\u001a:p[\"1\u0011Q\u0010\tA\u0002a\nQ!\u001e8uS2Da\u0001\u001e\tA\u0002\u0005\u0005\u0005\u0003\u0002\'P\u0003gB3\u0001EAC!\r\u0019\u0013qQ\u0005\u0004\u0003\u0013[\"AB5oY&tW-\u0001\u0006ti\u0006\u0014G.Z*peR,B!a$\u0002\u001cR!\u0011\u0011SAO)\rQ\u00131\u0013\u0005\n\u0003+\u000b\u0012\u0011!a\u0002\u0003/\u000b!\"\u001a<jI\u0016t7-\u001a\u00134!\u0011au*!\'\u0011\u0007I\u000bY\nB\u0003U#\t\u0007Q\u000b\u0003\u0004/#\u0001\u0007\u0011q\u0014\t\u0005GA\nI\nK\u0002\u0012\u0003\u000b+B!!*\u00022RA\u0011qUAZ\u0003o\u000bI\fF\u0002+\u0003SC\u0011\"a+\u0013\u0003\u0003\u0005\u001d!!,\u0002\u0015\u00154\u0018\u000eZ3oG\u0016$C\u0007\u0005\u0003M\u001f\u0006=\u0006c\u0001*\u00022\u0012)AK\u0005b\u0001+\"1aF\u0005a\u0001\u0003k\u0003Ba\t\u0019\u00020\"1\u0011\u0011\u0010\nA\u0002aBa!! \u0013\u0001\u0004AT\u0003BA_\u0003\u000b$RAKA`\u0003\u000fDaAL\nA\u0002\u0005\u0005\u0007\u0003B\u00121\u0003\u0007\u00042AUAc\t\u0015!6C1\u0001V\u0011\u001d\tIm\u0005a\u0001\u0003\u0017\f\u0011A\u001a\t\nG\u00055\u00171YAb\u0003GJ1!a4\u001c\u0005%1UO\\2uS>t\'\u0007K\u0002\u0014\u0003\u000b+B!!6\u0002^RI!&a6\u0002`\u0006\r\u0018Q\u001d\u0005\u0007]Q\u0001\r!!7\u0011\t\r\u0002\u00141\u001c\t\u0004%\u0006uG!\u0002+\u0015\u0005\u0004)\u0006bBAe)\u0001\u0007\u0011\u0011\u001d\t\nG\u00055\u00171\\An\u0003GBa!!\u001f\u0015\u0001\u0004A\u0004BBA?)\u0001\u0007\u0001(\u0006\u0003\u0002j\u0006EH\u0003BAv\u0003\u007f$b!!<\u0002t\u0006e\b\u0003B\u00121\u0003_\u00042AUAy\t\u0015!VC1\u0001V\u0011%\t)0FA\u0001\u0002\b\t90\u0001\u0006fm&$WM\\2fIU\u0002R!`A\u0001\u0003_D\u0011\"a?\u0016\u0003\u0003\u0005\u001d!!@\u0002\u0015\u00154\u0018\u000eZ3oG\u0016$c\u0007\u0005\u0003M\u001f\u0006=\bB\u0002\u0018\u0016\u0001\u0004\u0011\t\u0001\u0005\u0004\u0003\u0004\t%\u0011q^\u0007\u0003\u0005\u000bQ1Aa\u0002\u001c\u0003)\u0019w\u000e\u001c7fGRLwN\\\u0005\u0005\u0005\u0017\u0011)AA\u0002TKF,BAa\u0004\u0003\u0018Q1!\u0011\u0003B\u0010\u0005G!BAa\u0005\u0003\u001aA!1\u0005\rB\u000b!\r\u0011&q\u0003\u0003\u0006)Z\u0011\r!\u0016\u0005\n\u000571\u0012\u0011!a\u0002\u0005;\t!\"\u001a<jI\u0016t7-\u001a\u00138!\u0015i\u0018\u0011\u0001B\u000b\u0011\u0019qc\u00031\u0001\u0003\"A1!1\u0001B\u0005\u0005+Aq!!3\u0017\u0001\u0004\u0011)\u0003E\u0005$\u0003\u001b\u0014)B!\u0006\u0002dU1!\u0011\u0006B\u0019\u0005\u0003\"bAa\u000b\u0003F\t%CC\u0002B\u0017\u0005g\u0011I\u0004\u0005\u0003$a\t=\u0002c\u0001*\u00032\u0011)Ak\u0006b\u0001+\"I!QG\f\u0002\u0002\u0003\u000f!qG\u0001\u000bKZLG-\u001a8dK\u0012B\u0004#B?\u0002\u0002\t=\u0002\"\u0003B\u001e/\u0005\u0005\t9\u0001B\u001f\u0003))g/\u001b3f]\u000e,G%\u000f\t\u0005\u0019>\u0013y\u0004E\u0002S\u0005\u0003\"aAa\u0011\u0018\u0005\u0004)&!A\'\t\r9:\u0002\u0019\u0001B$!\u0019\u0011\u0019A!\u0003\u00030!9\u0011\u0011Z\fA\u0002\t-\u0003cB\u0012\u0003N\t=\"qH\u0005\u0004\u0005\u001fZ\"!\u0003$v]\u000e$\u0018n\u001c82\u0001"
    )
  ScalaSig: length = 0x3 (unknown attribute)
   05 02 00
