Classfile /Users/mw/Projects/slang-braindump/.jar/jar11/assemble/slang-braindump/assemble/content/scala/xml/dtd/ContentModel.class
  Last modified May 29, 2022; size 6388 bytes
  SHA-256 checksum 20626d116a4323353616319eedc28472554874f98db4fb3ea7e1338cfa8e9a14
  Compiled from "ContentModel.scala"
public abstract class scala.xml.dtd.ContentModel
  minor version: 0
  major version: 52
  flags: (0x0421) ACC_PUBLIC, ACC_SUPER, ACC_ABSTRACT
  this_class: #2                          // scala/xml/dtd/ContentModel
  super_class: #4                         // java/lang/Object
  interfaces: 0, fields: 0, methods: 15, attributes: 6
Constant pool:
    #1 = Utf8               scala/xml/dtd/ContentModel
    #2 = Class              #1            // scala/xml/dtd/ContentModel
    #3 = Utf8               java/lang/Object
    #4 = Class              #3            // java/lang/Object
    #5 = Utf8               ContentModel.scala
    #6 = Utf8               Lscala/reflect/ScalaSignature;
    #7 = Utf8               bytes
    #8 = Utf8               \u0006\u0005\tUr!\u0002\u0017.\u0011\u0003!d!\u0002\u001c.\u0011\u00039\u0004\"\u0002 \u0002\t\u0003yT\u0001\u0002!\u0002\u0001\u0005+a!a\u0011\u0002\u0001\u0005\u0015c!CA(\u0003A\u0005\u0019\u0013AA)\u000f\u001d\ti\'\u0001E\u0001\u0003_2q!a\u0014\u0002\u0011\u0003\t\t\b\u0003\u0004?\u000f\u0011\u0005\u0011Q\u000f\u0005\tw\u001e\u0011\r\u0011\"\u0011\u0002x!9\u0011\u0011P\u0004!\u0002\u0013\u0011e\u0001B\"\u0002\u0001\u0012C\u0001\u0002W\u0006\u0003\u0016\u0004%\t!\u0017\u0005\tE.\u0011\t\u0012)A\u00055\")ah\u0003C\u0001G\")Qm\u0003C!M\"9qmCA\u0001\n\u0003A\u0007b\u00026\f#\u0003%\ta\u001b\u0005\bm.\t\t\u0011\"\u0011x\u0011!y8\"!A\u0005\u0002\u0005\u0005\u0001\"CA\u0005\u0017\u0005\u0005I\u0011AA\u0006\u0011%\t9bCA\u0001\n\u0003\nI\u0002C\u0005\u0002(-\t\t\u0011\"\u0001\u0002*!I\u00111G\u0006\u0002\u0002\u0013\u0005\u0013Q\u0007\u0005\n\u0003sY\u0011\u0011!C!\u0003wA\u0011\"!\u0010\f\u0003\u0003%\t%a\u0010\b\u0013\u0005u\u0014!!A\t\u0002\u0005}d\u0001C\"\u0002\u0003\u0003E\t!!!\t\ryZB\u0011AAM\u0011!)7$!A\u0005F\u0005m\u0005\"CAO7\u0005\u0005I\u0011QAP\u0011%\t\u0019kGA\u0001\n\u0003\u000b)\u000bC\u0005\u00022n\t\t\u0011\"\u0003\u00024\"9\u00111X\u0001\u0005\u0002\u0005u\u0006bBAy\u0003\u0011\u0005\u00111\u001f\u0005\b\u0003o\fA\u0011AA}\u0011\u001d\ty-\u0001C\u0001\u0005\u000bAq!a4\u0002\t\u0013\u0011I\u0001C\u0004\u0002P\u0006!\tAa\n\t\u000f\u0005=\u0017\u0001\"\u0001\u00030\u00191a\'LA\u0011\u0003\u000bDaA\u0010\u0015\u0005\u0002\u00055\u0007\"B3)\t\u00032\u0007bBAhQ\u0019\u0005\u0011\u0011[\u0001\r\u0007>tG/\u001a8u\u001b>$W\r\u001c\u0006\u0003]=\n1\u0001\u001a;e\u0015\t\u0001\u0014\'A\u0002y[2T\u0011AM\u0001\u0006g\u000e\fG.Y\u0002\u0001!\t)\u0014!D\u0001.\u00051\u0019uN\u001c;f]Rlu\u000eZ3m\'\t\t\u0001\b\u0005\u0002:y5\t!H\u0003\u0002<[\u0005!\u0011.\u001c9m\u0013\ti$HA\u0004X_J$W\t\u001f9\u0002\rqJg.\u001b;?)\u0005!$aB0mC\n,G\u000e\u0016\t\u0003\u0005.i\u0011!\u0001\u0002\t\u000b2,WNT1nKN!1\"\u0012%M!\t\u0011e)\u0003\u0002Hy\t)A*\u00192fYB\u0011\u0011JS\u0007\u0002c%\u00111*\r\u0002\b!J|G-^2u!\tiUK\u0004\u0002O\':\u0011qJU\u0007\u0002!*\u0011\u0011kM\u0001\u0007yI|w\u000e\u001e \n\u0003IJ!\u0001V\u0019\u0002\u000fA\f7m[1hK&\u0011ak\u0016\u0002\r\'\u0016\u0014\u0018.\u00197ju\u0006\u0014G.\u001a\u0006\u0003)F\nAA\\1nKV\t!\f\u0005\u0002\\?:\u0011A,\u0018\t\u0003\u001fFJ!AX\u0019\u0002\rA\u0013X\rZ3g\u0013\t\u0001\u0017M\u0001\u0004TiJLgn\u001a\u0006\u0003=F\nQA\\1nK\u0002\"\"!\u00113\t\u000bas\u0001\u0019\u0001.\u0002\u0011Q|7\u000b\u001e:j]\u001e$\u0012AW\u0001\u0005G>\u0004\u0018\u0010\u0006\u0002BS\"9\u0001\f\u0005I\u0001\u0002\u0004Q\u0016AD2paf$C-\u001a4bk2$H%M\u000b\u0002Y*\u0012!,\\\u0016\u0002]B\u0011q\u000e^\u0007\u0002a*\u0011\u0011O]\u0001\nk:\u001c\u0007.Z2lK\u0012T!a]\u0019\u0002\u0015\u0005tgn\u001c;bi&|g.\u0003\u0002va\n\tRO\\2iK\u000e\\W\r\u001a,be&\fgnY3\u0002\u001bA\u0014x\u000eZ;diB\u0013XMZ5y+\u0005A\bCA=\u007f\u001b\u0005Q(BA>}\u0003\u0011a\u0017M\\4\u000b\u0003u\fAA[1wC&\u0011\u0001M_\u0001\raJ|G-^2u\u0003JLG/_\u000b\u0003\u0003\u0007\u00012!SA\u0003\u0013\r\t9!\r\u0002\u0004\u0013:$\u0018A\u00049s_\u0012,8\r^#mK6,g\u000e\u001e\u000b\u0005\u0003\u001b\t\u0019\u0002E\u0002J\u0003\u001fI1!!\u00052\u0005\r\te.\u001f\u0005\n\u0003+!\u0012\u0011!a\u0001\u0003\u0007\t1\u0001\u001f\u00132\u0003=\u0001(o\u001c3vGRLE/\u001a:bi>\u0014XCAA\u000e!\u0019\ti\"a\t\u0002\u000e5\u0011\u0011q\u0004\u0006\u0004\u0003C\t\u0014AC2pY2,7\r^5p]&!\u0011QEA\u0010\u0005!IE/\u001a:bi>\u0014\u0018\u0001C2b]\u0016\u000bX/\u00197\u0015\t\u0005-\u0012\u0011\u0007\t\u0004\u0013\u00065\u0012bAA\u0018c\t9!i\\8mK\u0006t\u0007\"CA\u000b-\u0005\u0005\t\u0019AA\u0007\u0003I\u0001(o\u001c3vGR,E.Z7f]Rt\u0015-\\3\u0015\u0007a\f9\u0004C\u0005\u0002\u0016]\t\t\u00111\u0001\u0002\u0004\u0005A\u0001.Y:i\u0007>$W\r\u0006\u0002\u0002\u0004\u00051Q-];bYN$B!a\u000b\u0002B!I\u0011QC\r\u0002\u0002\u0003\u0007\u0011Q\u0002\u0002\t?J,w-\u001a=q)B\u0019!)a\u0012\n\t\u0005%\u00131\n\u0002\u0007%\u0016<W\t\u001f9\n\u0007\u00055#H\u0001\u0003CCN,\'A\u0003+sC:\u001cH.\u0019;peN\u0019Q!a\u0015\u0011\u0007e\n)&C\u0002\u0002Xi\u0012abV8sI\n+\'O]=TKRD\u0017\u000eK\u0006\u0006\u00037\n\t\'a\u0019\u0002h\u0005%\u0004cA%\u0002^%\u0019\u0011qL\u0019\u0003\u0015\u0011,\u0007O]3dCR,G-A\u0004nKN\u001c\u0018mZ3\"\u0005\u0005\u0015\u0014!C!w_&$\u0017M\\2f\u0003\u0015\u0019\u0018N\\2fC\t\tY\'\u0001\u00033]E\u0002\u0014A\u0003+sC:\u001cH.\u0019;peB\u0011!iB\n\u0006\u000f\u0005M\u00131\u000f\t\u0003\u0005\u0016!\"!a\u001c\u0016\u0003\t\u000bQ\u0001\\1oO\u0002B3aBA.\u0003!)E.Z7OC6,\u0007C\u0001\"\u001c\'\u0015Y\u00121QAH!\u0019\t))a#[\u00036\u0011\u0011q\u0011\u0006\u0004\u0003\u0013\u000b\u0014a\u0002:v]RLW.Z\u0005\u0005\u0003\u001b\u000b9IA\tBEN$(/Y2u\rVt7\r^5p]F\u0002B!!%\u0002\u00186\u0011\u00111\u0013\u0006\u0004\u0003+c\u0018AA5p\u0013\r1\u00161\u0013\u000b\u0003\u0003\u007f\"\u0012\u0001_\u0001\u0006CB\u0004H.\u001f\u000b\u0004\u0003\u0006\u0005\u0006\"\u0002-\u001f\u0001\u0004Q\u0016aB;oCB\u0004H.\u001f\u000b\u0005\u0003O\u000bi\u000b\u0005\u0003J\u0003SS\u0016bAAVc\t1q\n\u001d;j_:D\u0001\"a, \u0003\u0003\u0005\r!Q\u0001\u0004q\u0012\u0002\u0014\u0001D<sSR,\'+\u001a9mC\u000e,GCAA[!\rI\u0018qW\u0005\u0004\u0003sS(AB(cU\u0016\u001cG/A\u0004jg6K\u00070\u001a3\u0015\t\u0005-\u0012q\u0018\u0005\b\u0003\u0003\f\u0003\u0019AAb\u0003\t\u0019W\u000e\u0005\u00026QM\u0019\u0001&a2\u0011\u0007%\u000bI-C\u0002\u0002LF\u0012a!\u00118z%\u00164GCAAb\u0003-\u0011W/\u001b7e\'R\u0014\u0018N\\4\u0015\t\u0005M\u00171\u001c\t\u0005\u0003+\f9N\u0004\u0002J\'&\u0019\u0011\u0011\\,\u0003\u001bM#(/\u001b8h\u0005VLG\u000eZ3s\u0011\u001d\tin\u000ba\u0001\u0003\'\f!a\u001d2*\u0013!\n\t/!:\u0002j\u00065(bAAr[\u0005\u0019\u0011IT-\n\u0007\u0005\u001dXFA\bE\r\u0006\u001buN\u001c;f]Rlu\u000eZ3m\u0015\r\tY/L\u0001\u0006\u000b6\u0003F+\u0017\u0006\u0004\u0003_l\u0013A\u0002)D\t\u0006#\u0016)\u0001\u0007d_:$\u0018-\u001b8t)\u0016DH\u000f\u0006\u0003\u0002,\u0005U\bbBAaE\u0001\u0007\u00111Y\u0001\nO\u0016$H*\u00192fYN$B!a?\u0003\u0002A!1,!@[\u0013\r\ty0\u0019\u0002\u0004\'\u0016$\bb\u0002B\u0002G\u0001\u0007\u0011QI\u0001\u0002eR\u0019!La\u0002\t\u000f\t\rA\u00051\u0001\u0002FQA!1\u0002B\t\u00057\u0011i\u0002E\u0002J\u0005\u001bI1Aa\u00042\u0005\u0011)f.\u001b;\t\u000f\tMQ\u00051\u0001\u0003\u0016\u0005\u0011!o\u001d\t\u0007\u0003;\u00119\"!\u0012\n\t\te\u0011q\u0004\u0002\u0004\'\u0016\f\bbBAoK\u0001\u0007\u00111\u001b\u0005\b\u0005?)\u0003\u0019\u0001B\u0011\u0003\r\u0019X\r\u001d\t\u0004\u0013\n\r\u0012b\u0001B\u0013c\t!1\t[1s)\u0019\t\u0019N!\u000b\u0003.!9!1\u0006\u0014A\u0002\u0005\r\u0017!A2\t\u000f\u0005ug\u00051\u0001\u0002TR1\u00111\u001bB\u0019\u0005gAqAa\u0001(\u0001\u0004\t)\u0005C\u0004\u0002^\u001e\u0002\r!a5
    #9 = Utf8               java/lang/invoke/MethodHandles$Lookup
   #10 = Class              #9            // java/lang/invoke/MethodHandles$Lookup
   #11 = Utf8               java/lang/invoke/MethodHandles
   #12 = Class              #11           // java/lang/invoke/MethodHandles
   #13 = Utf8               Lookup
   #14 = Utf8               scala/xml/dtd/ContentModel$ElemName
   #15 = Class              #14           // scala/xml/dtd/ContentModel$ElemName
   #16 = Utf8               ElemName
   #17 = Utf8               scala/xml/dtd/ContentModel$ElemName$
   #18 = Class              #17           // scala/xml/dtd/ContentModel$ElemName$
   #19 = Utf8               ElemName$
   #20 = Utf8               scala/xml/dtd/ContentModel$Translator
   #21 = Class              #20           // scala/xml/dtd/ContentModel$Translator
   #22 = Utf8               Translator
   #23 = Utf8               scala/xml/dtd/ContentModel$Translator$
   #24 = Class              #23           // scala/xml/dtd/ContentModel$Translator$
   #25 = Utf8               Translator$
   #26 = Utf8               scala/xml/dtd/impl/Base$Alt$
   #27 = Class              #26           // scala/xml/dtd/impl/Base$Alt$
   #28 = Utf8               scala/xml/dtd/impl/Base
   #29 = Class              #28           // scala/xml/dtd/impl/Base
   #30 = Utf8               Alt$
   #31 = Utf8               scala/xml/dtd/impl/Base$Eps$
   #32 = Class              #31           // scala/xml/dtd/impl/Base$Eps$
   #33 = Utf8               Eps$
   #34 = Utf8               scala/xml/dtd/impl/Base$RegExp
   #35 = Class              #34           // scala/xml/dtd/impl/Base$RegExp
   #36 = Utf8               RegExp
   #37 = Utf8               scala/xml/dtd/impl/Base$Sequ$
   #38 = Class              #37           // scala/xml/dtd/impl/Base$Sequ$
   #39 = Utf8               Sequ$
   #40 = Utf8               scala/xml/dtd/impl/Base$Star$
   #41 = Class              #40           // scala/xml/dtd/impl/Base$Star$
   #42 = Utf8               Star$
   #43 = Utf8               scala/xml/dtd/impl/WordExp$Letter$
   #44 = Class              #43           // scala/xml/dtd/impl/WordExp$Letter$
   #45 = Utf8               scala/xml/dtd/impl/WordExp
   #46 = Class              #45           // scala/xml/dtd/impl/WordExp
   #47 = Utf8               Letter$
   #48 = Utf8               scala/xml/dtd/impl/WordExp$Wildcard$
   #49 = Class              #48           // scala/xml/dtd/impl/WordExp$Wildcard$
   #50 = Utf8               Wildcard$
   #51 = Utf8               getLabels
   #52 = Utf8               (Lscala/xml/dtd/impl/Base$RegExp;)Lscala/collection/immutable/Set;
   #53 = Utf8               (Lscala/xml/dtd/impl/Base$RegExp;)Lscala/collection/immutable/Set<Ljava/lang/String;>;
   #54 = Utf8               r
   #55 = Utf8               scala/xml/dtd/ContentModel$
   #56 = Class              #55           // scala/xml/dtd/ContentModel$
   #57 = Utf8               MODULE$
   #58 = Utf8               Lscala/xml/dtd/ContentModel$;
   #59 = NameAndType        #57:#58       // MODULE$:Lscala/xml/dtd/ContentModel$;
   #60 = Fieldref           #56.#59       // scala/xml/dtd/ContentModel$.MODULE$:Lscala/xml/dtd/ContentModel$;
   #61 = NameAndType        #51:#52       // getLabels:(Lscala/xml/dtd/impl/Base$RegExp;)Lscala/collection/immutable/Set;
   #62 = Methodref          #56.#61       // scala/xml/dtd/ContentModel$.getLabels:(Lscala/xml/dtd/impl/Base$RegExp;)Lscala/collection/immutable/Set;
   #63 = Utf8               Lscala/xml/dtd/impl/Base$RegExp;
   #64 = Utf8               containsText
   #65 = Utf8               (Lscala/xml/dtd/ContentModel;)Z
   #66 = Utf8               cm
   #67 = NameAndType        #64:#65       // containsText:(Lscala/xml/dtd/ContentModel;)Z
   #68 = Methodref          #56.#67       // scala/xml/dtd/ContentModel$.containsText:(Lscala/xml/dtd/ContentModel;)Z
   #69 = Utf8               Lscala/xml/dtd/ContentModel;
   #70 = Utf8               isMixed
   #71 = NameAndType        #70:#65       // isMixed:(Lscala/xml/dtd/ContentModel;)Z
   #72 = Methodref          #56.#71       // scala/xml/dtd/ContentModel$.isMixed:(Lscala/xml/dtd/ContentModel;)Z
   #73 = Utf8               Wildcard
   #74 = Utf8               ()Lscala/xml/dtd/impl/WordExp$Wildcard$;
   #75 = NameAndType        #73:#74       // Wildcard:()Lscala/xml/dtd/impl/WordExp$Wildcard$;
   #76 = Methodref          #56.#75       // scala/xml/dtd/ContentModel$.Wildcard:()Lscala/xml/dtd/impl/WordExp$Wildcard$;
   #77 = Utf8               Letter
   #78 = Utf8               ()Lscala/xml/dtd/impl/WordExp$Letter$;
   #79 = NameAndType        #77:#78       // Letter:()Lscala/xml/dtd/impl/WordExp$Letter$;
   #80 = Methodref          #56.#79       // scala/xml/dtd/ContentModel$.Letter:()Lscala/xml/dtd/impl/WordExp$Letter$;
   #81 = Utf8               Eps
   #82 = Utf8               ()Lscala/xml/dtd/impl/Base$Eps$;
   #83 = NameAndType        #81:#82       // Eps:()Lscala/xml/dtd/impl/Base$Eps$;
   #84 = Methodref          #56.#83       // scala/xml/dtd/ContentModel$.Eps:()Lscala/xml/dtd/impl/Base$Eps$;
   #85 = Utf8               Star
   #86 = Utf8               ()Lscala/xml/dtd/impl/Base$Star$;
   #87 = NameAndType        #85:#86       // Star:()Lscala/xml/dtd/impl/Base$Star$;
   #88 = Methodref          #56.#87       // scala/xml/dtd/ContentModel$.Star:()Lscala/xml/dtd/impl/Base$Star$;
   #89 = Utf8               Sequ
   #90 = Utf8               ()Lscala/xml/dtd/impl/Base$Sequ$;
   #91 = NameAndType        #89:#90       // Sequ:()Lscala/xml/dtd/impl/Base$Sequ$;
   #92 = Methodref          #56.#91       // scala/xml/dtd/ContentModel$.Sequ:()Lscala/xml/dtd/impl/Base$Sequ$;
   #93 = Utf8               Alt
   #94 = Utf8               ()Lscala/xml/dtd/impl/Base$Alt$;
   #95 = NameAndType        #93:#94       // Alt:()Lscala/xml/dtd/impl/Base$Alt$;
   #96 = Methodref          #56.#95       // scala/xml/dtd/ContentModel$.Alt:()Lscala/xml/dtd/impl/Base$Alt$;
   #97 = Utf8               toString
   #98 = Utf8               ()Ljava/lang/String;
   #99 = Utf8               scala/xml/Utility$
  #100 = Class              #99           // scala/xml/Utility$
  #101 = Utf8               Lscala/xml/Utility$;
  #102 = NameAndType        #57:#101      // MODULE$:Lscala/xml/Utility$;
  #103 = Fieldref           #100.#102     // scala/xml/Utility$.MODULE$:Lscala/xml/Utility$;
  #104 = Utf8               (Ljava/lang/Object;)Ljava/lang/Object;
  #105 = MethodType         #104          //  (Ljava/lang/Object;)Ljava/lang/Object;
  #106 = Utf8               $anonfun$toString$1$adapted
  #107 = Utf8               (Lscala/xml/dtd/ContentModel;Lscala/collection/mutable/StringBuilder;)Ljava/lang/Object;
  #108 = NameAndType        #106:#107     // $anonfun$toString$1$adapted:(Lscala/xml/dtd/ContentModel;Lscala/collection/mutable/StringBuilder;)Ljava/lang/Object;
  #109 = Methodref          #2.#108       // scala/xml/dtd/ContentModel.$anonfun$toString$1$adapted:(Lscala/xml/dtd/ContentModel;Lscala/collection/mutable/StringBuilder;)Ljava/lang/Object;
  #110 = MethodHandle       6:#109        // REF_invokeStatic scala/xml/dtd/ContentModel.$anonfun$toString$1$adapted:(Lscala/xml/dtd/ContentModel;Lscala/collection/mutable/StringBuilder;)Ljava/lang/Object;
  #111 = Utf8               (Lscala/collection/mutable/StringBuilder;)Ljava/lang/Object;
  #112 = MethodType         #111          //  (Lscala/collection/mutable/StringBuilder;)Ljava/lang/Object;
  #113 = Integer            5
  #114 = Integer            1
  #115 = Utf8               java/lang/invoke/LambdaMetafactory
  #116 = Class              #115          // java/lang/invoke/LambdaMetafactory
  #117 = Utf8               altMetafactory
  #118 = Utf8               (Ljava/lang/invoke/MethodHandles$Lookup;Ljava/lang/String;Ljava/lang/invoke/MethodType;[Ljava/lang/Object;)Ljava/lang/invoke/CallSite;
  #119 = NameAndType        #117:#118     // altMetafactory:(Ljava/lang/invoke/MethodHandles$Lookup;Ljava/lang/String;Ljava/lang/invoke/MethodType;[Ljava/lang/Object;)Ljava/lang/invoke/CallSite;
  #120 = Methodref          #116.#119     // java/lang/invoke/LambdaMetafactory.altMetafactory:(Ljava/lang/invoke/MethodHandles$Lookup;Ljava/lang/String;Ljava/lang/invoke/MethodType;[Ljava/lang/Object;)Ljava/lang/invoke/CallSite;
  #121 = MethodHandle       6:#120        // REF_invokeStatic java/lang/invoke/LambdaMetafactory.altMetafactory:(Ljava/lang/invoke/MethodHandles$Lookup;Ljava/lang/String;Ljava/lang/invoke/MethodType;[Ljava/lang/Object;)Ljava/lang/invoke/CallSite;
  #122 = Utf8               apply
  #123 = Utf8               (Lscala/xml/dtd/ContentModel;)Lscala/Function1;
  #124 = NameAndType        #122:#123     // apply:(Lscala/xml/dtd/ContentModel;)Lscala/Function1;
  #125 = InvokeDynamic      #0:#124       // #0:apply:(Lscala/xml/dtd/ContentModel;)Lscala/Function1;
  #126 = Utf8               sbToString
  #127 = Utf8               (Lscala/Function1;)Ljava/lang/String;
  #128 = NameAndType        #126:#127     // sbToString:(Lscala/Function1;)Ljava/lang/String;
  #129 = Methodref          #100.#128     // scala/xml/Utility$.sbToString:(Lscala/Function1;)Ljava/lang/String;
  #130 = Utf8               this
  #131 = Utf8               buildString
  #132 = Utf8               (Lscala/collection/mutable/StringBuilder;)Lscala/collection/mutable/StringBuilder;
  #133 = Utf8               sb
  #134 = Utf8               $anonfun$toString$1
  #135 = Utf8               (Lscala/xml/dtd/ContentModel;Lscala/collection/mutable/StringBuilder;)V
  #136 = Utf8               $this
  #137 = NameAndType        #131:#132     // buildString:(Lscala/collection/mutable/StringBuilder;)Lscala/collection/mutable/StringBuilder;
  #138 = Methodref          #2.#137       // scala/xml/dtd/ContentModel.buildString:(Lscala/collection/mutable/StringBuilder;)Lscala/collection/mutable/StringBuilder;
  #139 = Utf8               Lscala/collection/mutable/StringBuilder;
  #140 = Utf8               <init>
  #141 = Utf8               ()V
  #142 = NameAndType        #140:#141     // "<init>":()V
  #143 = Methodref          #4.#142       // java/lang/Object."<init>":()V
  #144 = NameAndType        #134:#135     // $anonfun$toString$1:(Lscala/xml/dtd/ContentModel;Lscala/collection/mutable/StringBuilder;)V
  #145 = Methodref          #2.#144       // scala/xml/dtd/ContentModel.$anonfun$toString$1:(Lscala/xml/dtd/ContentModel;Lscala/collection/mutable/StringBuilder;)V
  #146 = Utf8               scala/runtime/BoxedUnit
  #147 = Class              #146          // scala/runtime/BoxedUnit
  #148 = Utf8               UNIT
  #149 = Utf8               Lscala/runtime/BoxedUnit;
  #150 = NameAndType        #148:#149     // UNIT:Lscala/runtime/BoxedUnit;
  #151 = Fieldref           #147.#150     // scala/runtime/BoxedUnit.UNIT:Lscala/runtime/BoxedUnit;
  #152 = Utf8               $deserializeLambda$
  #153 = Utf8               (Ljava/lang/invoke/SerializedLambda;)Ljava/lang/Object;
  #154 = Utf8               scala/runtime/LambdaDeserialize
  #155 = Class              #154          // scala/runtime/LambdaDeserialize
  #156 = Utf8               bootstrap
  #157 = Utf8               (Ljava/lang/invoke/MethodHandles$Lookup;Ljava/lang/String;Ljava/lang/invoke/MethodType;[Ljava/lang/invoke/MethodHandle;)Ljava/lang/invoke/CallSite;
  #158 = NameAndType        #156:#157     // bootstrap:(Ljava/lang/invoke/MethodHandles$Lookup;Ljava/lang/String;Ljava/lang/invoke/MethodType;[Ljava/lang/invoke/MethodHandle;)Ljava/lang/invoke/CallSite;
  #159 = Methodref          #155.#158     // scala/runtime/LambdaDeserialize.bootstrap:(Ljava/lang/invoke/MethodHandles$Lookup;Ljava/lang/String;Ljava/lang/invoke/MethodType;[Ljava/lang/invoke/MethodHandle;)Ljava/lang/invoke/CallSite;
  #160 = MethodHandle       6:#159        // REF_invokeStatic scala/runtime/LambdaDeserialize.bootstrap:(Ljava/lang/invoke/MethodHandles$Lookup;Ljava/lang/String;Ljava/lang/invoke/MethodType;[Ljava/lang/invoke/MethodHandle;)Ljava/lang/invoke/CallSite;
  #161 = Utf8               lambdaDeserialize
  #162 = NameAndType        #161:#153     // lambdaDeserialize:(Ljava/lang/invoke/SerializedLambda;)Ljava/lang/Object;
  #163 = InvokeDynamic      #1:#162       // #1:lambdaDeserialize:(Ljava/lang/invoke/SerializedLambda;)Ljava/lang/Object;
  #164 = Utf8               Code
  #165 = Utf8               LocalVariableTable
  #166 = Utf8               Signature
  #167 = Utf8               MethodParameters
  #168 = Utf8               LineNumberTable
  #169 = Utf8               InnerClasses
  #170 = Utf8               SourceFile
  #171 = Utf8               RuntimeVisibleAnnotations
  #172 = Utf8               BootstrapMethods
  #173 = Utf8               ScalaInlineInfo
  #174 = Utf8               ScalaSig
{
  public static scala.collection.immutable.Set<java.lang.String> getLabels(scala.xml.dtd.impl.Base$RegExp);
    descriptor: (Lscala/xml/dtd/impl/Base$RegExp;)Lscala/collection/immutable/Set;
    flags: (0x0009) ACC_PUBLIC, ACC_STATIC
    Code:
      stack=2, locals=1, args_size=1
         0: getstatic     #60                 // Field scala/xml/dtd/ContentModel$.MODULE$:Lscala/xml/dtd/ContentModel$;
         3: aload_0
         4: invokevirtual #62                 // Method scala/xml/dtd/ContentModel$.getLabels:(Lscala/xml/dtd/impl/Base$RegExp;)Lscala/collection/immutable/Set;
         7: areturn
      LocalVariableTable:
        Start  Length  Slot  Name   Signature
            0       8     0     r   Lscala/xml/dtd/impl/Base$RegExp;
    Signature: #53                          // (Lscala/xml/dtd/impl/Base$RegExp;)Lscala/collection/immutable/Set<Ljava/lang/String;>;
    MethodParameters:
      Name                           Flags
      r                              final

  public static boolean containsText(scala.xml.dtd.ContentModel);
    descriptor: (Lscala/xml/dtd/ContentModel;)Z
    flags: (0x0009) ACC_PUBLIC, ACC_STATIC
    Code:
      stack=2, locals=1, args_size=1
         0: getstatic     #60                 // Field scala/xml/dtd/ContentModel$.MODULE$:Lscala/xml/dtd/ContentModel$;
         3: aload_0
         4: invokevirtual #68                 // Method scala/xml/dtd/ContentModel$.containsText:(Lscala/xml/dtd/ContentModel;)Z
         7: ireturn
      LocalVariableTable:
        Start  Length  Slot  Name   Signature
            0       8     0    cm   Lscala/xml/dtd/ContentModel;
    MethodParameters:
      Name                           Flags
      cm                             final

  public static boolean isMixed(scala.xml.dtd.ContentModel);
    descriptor: (Lscala/xml/dtd/ContentModel;)Z
    flags: (0x0009) ACC_PUBLIC, ACC_STATIC
    Code:
      stack=2, locals=1, args_size=1
         0: getstatic     #60                 // Field scala/xml/dtd/ContentModel$.MODULE$:Lscala/xml/dtd/ContentModel$;
         3: aload_0
         4: invokevirtual #72                 // Method scala/xml/dtd/ContentModel$.isMixed:(Lscala/xml/dtd/ContentModel;)Z
         7: ireturn
      LocalVariableTable:
        Start  Length  Slot  Name   Signature
            0       8     0    cm   Lscala/xml/dtd/ContentModel;
    MethodParameters:
      Name                           Flags
      cm                             final

  public static scala.xml.dtd.impl.WordExp$Wildcard$ Wildcard();
    descriptor: ()Lscala/xml/dtd/impl/WordExp$Wildcard$;
    flags: (0x0009) ACC_PUBLIC, ACC_STATIC
    Code:
      stack=1, locals=0, args_size=0
         0: getstatic     #60                 // Field scala/xml/dtd/ContentModel$.MODULE$:Lscala/xml/dtd/ContentModel$;
         3: invokevirtual #76                 // Method scala/xml/dtd/ContentModel$.Wildcard:()Lscala/xml/dtd/impl/WordExp$Wildcard$;
         6: areturn

  public static scala.xml.dtd.impl.WordExp$Letter$ Letter();
    descriptor: ()Lscala/xml/dtd/impl/WordExp$Letter$;
    flags: (0x0009) ACC_PUBLIC, ACC_STATIC
    Code:
      stack=1, locals=0, args_size=0
         0: getstatic     #60                 // Field scala/xml/dtd/ContentModel$.MODULE$:Lscala/xml/dtd/ContentModel$;
         3: invokevirtual #80                 // Method scala/xml/dtd/ContentModel$.Letter:()Lscala/xml/dtd/impl/WordExp$Letter$;
         6: areturn

  public static scala.xml.dtd.impl.Base$Eps$ Eps();
    descriptor: ()Lscala/xml/dtd/impl/Base$Eps$;
    flags: (0x0009) ACC_PUBLIC, ACC_STATIC
    Code:
      stack=1, locals=0, args_size=0
         0: getstatic     #60                 // Field scala/xml/dtd/ContentModel$.MODULE$:Lscala/xml/dtd/ContentModel$;
         3: invokevirtual #84                 // Method scala/xml/dtd/ContentModel$.Eps:()Lscala/xml/dtd/impl/Base$Eps$;
         6: areturn

  public static scala.xml.dtd.impl.Base$Star$ Star();
    descriptor: ()Lscala/xml/dtd/impl/Base$Star$;
    flags: (0x0009) ACC_PUBLIC, ACC_STATIC
    Code:
      stack=1, locals=0, args_size=0
         0: getstatic     #60                 // Field scala/xml/dtd/ContentModel$.MODULE$:Lscala/xml/dtd/ContentModel$;
         3: invokevirtual #88                 // Method scala/xml/dtd/ContentModel$.Star:()Lscala/xml/dtd/impl/Base$Star$;
         6: areturn

  public static scala.xml.dtd.impl.Base$Sequ$ Sequ();
    descriptor: ()Lscala/xml/dtd/impl/Base$Sequ$;
    flags: (0x0009) ACC_PUBLIC, ACC_STATIC
    Code:
      stack=1, locals=0, args_size=0
         0: getstatic     #60                 // Field scala/xml/dtd/ContentModel$.MODULE$:Lscala/xml/dtd/ContentModel$;
         3: invokevirtual #92                 // Method scala/xml/dtd/ContentModel$.Sequ:()Lscala/xml/dtd/impl/Base$Sequ$;
         6: areturn

  public static scala.xml.dtd.impl.Base$Alt$ Alt();
    descriptor: ()Lscala/xml/dtd/impl/Base$Alt$;
    flags: (0x0009) ACC_PUBLIC, ACC_STATIC
    Code:
      stack=1, locals=0, args_size=0
         0: getstatic     #60                 // Field scala/xml/dtd/ContentModel$.MODULE$:Lscala/xml/dtd/ContentModel$;
         3: invokevirtual #96                 // Method scala/xml/dtd/ContentModel$.Alt:()Lscala/xml/dtd/impl/Base$Alt$;
         6: areturn

  public java.lang.String toString();
    descriptor: ()Ljava/lang/String;
    flags: (0x0001) ACC_PUBLIC
    Code:
      stack=2, locals=1, args_size=1
         0: getstatic     #103                // Field scala/xml/Utility$.MODULE$:Lscala/xml/Utility$;
         3: aload_0
         4: invokedynamic #125,  0            // InvokeDynamic #0:apply:(Lscala/xml/dtd/ContentModel;)Lscala/Function1;
         9: invokevirtual #129                // Method scala/xml/Utility$.sbToString:(Lscala/Function1;)Ljava/lang/String;
        12: areturn
      LineNumberTable:
        line 92: 0
      LocalVariableTable:
        Start  Length  Slot  Name   Signature
            0      13     0  this   Lscala/xml/dtd/ContentModel;

  public abstract scala.collection.mutable.StringBuilder buildString(scala.collection.mutable.StringBuilder);
    descriptor: (Lscala/collection/mutable/StringBuilder;)Lscala/collection/mutable/StringBuilder;
    flags: (0x0401) ACC_PUBLIC, ACC_ABSTRACT
    MethodParameters:
      Name                           Flags
      sb                             final

  public static final void $anonfun$toString$1(scala.xml.dtd.ContentModel, scala.collection.mutable.StringBuilder);
    descriptor: (Lscala/xml/dtd/ContentModel;Lscala/collection/mutable/StringBuilder;)V
    flags: (0x1019) ACC_PUBLIC, ACC_STATIC, ACC_FINAL, ACC_SYNTHETIC
    Code:
      stack=2, locals=2, args_size=2
         0: aload_0
         1: aload_1
         2: invokevirtual #138                // Method buildString:(Lscala/collection/mutable/StringBuilder;)Lscala/collection/mutable/StringBuilder;
         5: pop
         6: return
      LineNumberTable:
        line 92: 0
      LocalVariableTable:
        Start  Length  Slot  Name   Signature
            0       7     0 $this   Lscala/xml/dtd/ContentModel;
            0       7     1    sb   Lscala/collection/mutable/StringBuilder;
    MethodParameters:
      Name                           Flags
      $this                          final synthetic
      sb                             final

  public scala.xml.dtd.ContentModel();
    descriptor: ()V
    flags: (0x0001) ACC_PUBLIC
    Code:
      stack=1, locals=1, args_size=1
         0: aload_0
         1: invokespecial #143                // Method java/lang/Object."<init>":()V
         4: return
      LineNumberTable:
        line 96: 0
        line 91: 4
      LocalVariableTable:
        Start  Length  Slot  Name   Signature
            0       5     0  this   Lscala/xml/dtd/ContentModel;

  public static final java.lang.Object $anonfun$toString$1$adapted(scala.xml.dtd.ContentModel, scala.collection.mutable.StringBuilder);
    descriptor: (Lscala/xml/dtd/ContentModel;Lscala/collection/mutable/StringBuilder;)Ljava/lang/Object;
    flags: (0x1019) ACC_PUBLIC, ACC_STATIC, ACC_FINAL, ACC_SYNTHETIC
    Code:
      stack=2, locals=2, args_size=2
         0: aload_0
         1: aload_1
         2: invokestatic  #145                // Method $anonfun$toString$1:(Lscala/xml/dtd/ContentModel;Lscala/collection/mutable/StringBuilder;)V
         5: getstatic     #151                // Field scala/runtime/BoxedUnit.UNIT:Lscala/runtime/BoxedUnit;
         8: areturn
      LineNumberTable:
        line 92: 0
      LocalVariableTable:
        Start  Length  Slot  Name   Signature
            0       9     0 $this   Lscala/xml/dtd/ContentModel;
            0       9     1    sb   Lscala/collection/mutable/StringBuilder;
    MethodParameters:
      Name                           Flags
      $this                          final
      sb                             final

  private static java.lang.Object $deserializeLambda$(java.lang.invoke.SerializedLambda);
    descriptor: (Ljava/lang/invoke/SerializedLambda;)Ljava/lang/Object;
    flags: (0x100a) ACC_PRIVATE, ACC_STATIC, ACC_SYNTHETIC
    Code:
      stack=1, locals=1, args_size=1
         0: aload_0
         1: invokedynamic #163,  0            // InvokeDynamic #1:lambdaDeserialize:(Ljava/lang/invoke/SerializedLambda;)Ljava/lang/Object;
         6: areturn
}
InnerClasses:
  public static final #13= #10 of #12;    // Lookup=class java/lang/invoke/MethodHandles$Lookup of class java/lang/invoke/MethodHandles
  public static #16= #15 of #2;           // ElemName=class scala/xml/dtd/ContentModel$ElemName of class scala/xml/dtd/ContentModel
  public static #19= #18 of #2;           // ElemName$=class scala/xml/dtd/ContentModel$ElemName$ of class scala/xml/dtd/ContentModel
  public static #22= #21 of #2;           // Translator=class scala/xml/dtd/ContentModel$Translator of class scala/xml/dtd/ContentModel
  public static #25= #24 of #2;           // Translator$=class scala/xml/dtd/ContentModel$Translator$ of class scala/xml/dtd/ContentModel
  public #30= #27 of #29;                 // Alt$=class scala/xml/dtd/impl/Base$Alt$ of class scala/xml/dtd/impl/Base
  public #33= #32 of #29;                 // Eps$=class scala/xml/dtd/impl/Base$Eps$ of class scala/xml/dtd/impl/Base
  public abstract #36= #35 of #29;        // RegExp=class scala/xml/dtd/impl/Base$RegExp of class scala/xml/dtd/impl/Base
  public #39= #38 of #29;                 // Sequ$=class scala/xml/dtd/impl/Base$Sequ$ of class scala/xml/dtd/impl/Base
  public #42= #41 of #29;                 // Star$=class scala/xml/dtd/impl/Base$Star$ of class scala/xml/dtd/impl/Base
  public #47= #44 of #46;                 // Letter$=class scala/xml/dtd/impl/WordExp$Letter$ of class scala/xml/dtd/impl/WordExp
  public #50= #49 of #46;                 // Wildcard$=class scala/xml/dtd/impl/WordExp$Wildcard$ of class scala/xml/dtd/impl/WordExp
SourceFile: "ContentModel.scala"
RuntimeVisibleAnnotations:
  0: #6(#7=s#8)
    scala.reflect.ScalaSignature(
      bytes="\u0006\u0005\tUr!\u0002\u0017.\u0011\u0003!d!\u0002\u001c.\u0011\u00039\u0004\"\u0002 \u0002\t\u0003yT\u0001\u0002!\u0002\u0001\u0005+a!a\u0011\u0002\u0001\u0005\u0015c!CA(\u0003A\u0005\u0019\u0013AA)\u000f\u001d\ti\'\u0001E\u0001\u0003_2q!a\u0014\u0002\u0011\u0003\t\t\b\u0003\u0004?\u000f\u0011\u0005\u0011Q\u000f\u0005\tw\u001e\u0011\r\u0011\"\u0011\u0002x!9\u0011\u0011P\u0004!\u0002\u0013\u0011e\u0001B\"\u0002\u0001\u0012C\u0001\u0002W\u0006\u0003\u0016\u0004%\t!\u0017\u0005\tE.\u0011\t\u0012)A\u00055\")ah\u0003C\u0001G\")Qm\u0003C!M\"9qmCA\u0001\n\u0003A\u0007b\u00026\f#\u0003%\ta\u001b\u0005\bm.\t\t\u0011\"\u0011x\u0011!y8\"!A\u0005\u0002\u0005\u0005\u0001\"CA\u0005\u0017\u0005\u0005I\u0011AA\u0006\u0011%\t9bCA\u0001\n\u0003\nI\u0002C\u0005\u0002(-\t\t\u0011\"\u0001\u0002*!I\u00111G\u0006\u0002\u0002\u0013\u0005\u0013Q\u0007\u0005\n\u0003sY\u0011\u0011!C!\u0003wA\u0011\"!\u0010\f\u0003\u0003%\t%a\u0010\b\u0013\u0005u\u0014!!A\t\u0002\u0005}d\u0001C\"\u0002\u0003\u0003E\t!!!\t\ryZB\u0011AAM\u0011!)7$!A\u0005F\u0005m\u0005\"CAO7\u0005\u0005I\u0011QAP\u0011%\t\u0019kGA\u0001\n\u0003\u000b)\u000bC\u0005\u00022n\t\t\u0011\"\u0003\u00024\"9\u00111X\u0001\u0005\u0002\u0005u\u0006bBAy\u0003\u0011\u0005\u00111\u001f\u0005\b\u0003o\fA\u0011AA}\u0011\u001d\ty-\u0001C\u0001\u0005\u000bAq!a4\u0002\t\u0013\u0011I\u0001C\u0004\u0002P\u0006!\tAa\n\t\u000f\u0005=\u0017\u0001\"\u0001\u00030\u00191a\'LA\u0011\u0003\u000bDaA\u0010\u0015\u0005\u0002\u00055\u0007\"B3)\t\u00032\u0007bBAhQ\u0019\u0005\u0011\u0011[\u0001\r\u0007>tG/\u001a8u\u001b>$W\r\u001c\u0006\u0003]=\n1\u0001\u001a;e\u0015\t\u0001\u0014\'A\u0002y[2T\u0011AM\u0001\u0006g\u000e\fG.Y\u0002\u0001!\t)\u0014!D\u0001.\u00051\u0019uN\u001c;f]Rlu\u000eZ3m\'\t\t\u0001\b\u0005\u0002:y5\t!H\u0003\u0002<[\u0005!\u0011.\u001c9m\u0013\ti$HA\u0004X_J$W\t\u001f9\u0002\rqJg.\u001b;?)\u0005!$aB0mC\n,G\u000e\u0016\t\u0003\u0005.i\u0011!\u0001\u0002\t\u000b2,WNT1nKN!1\"\u0012%M!\t\u0011e)\u0003\u0002Hy\t)A*\u00192fYB\u0011\u0011JS\u0007\u0002c%\u00111*\r\u0002\b!J|G-^2u!\tiUK\u0004\u0002O\':\u0011qJU\u0007\u0002!*\u0011\u0011kM\u0001\u0007yI|w\u000e\u001e \n\u0003IJ!\u0001V\u0019\u0002\u000fA\f7m[1hK&\u0011ak\u0016\u0002\r\'\u0016\u0014\u0018.\u00197ju\u0006\u0014G.\u001a\u0006\u0003)F\nAA\\1nKV\t!\f\u0005\u0002\\?:\u0011A,\u0018\t\u0003\u001fFJ!AX\u0019\u0002\rA\u0013X\rZ3g\u0013\t\u0001\u0017M\u0001\u0004TiJLgn\u001a\u0006\u0003=F\nQA\\1nK\u0002\"\"!\u00113\t\u000bas\u0001\u0019\u0001.\u0002\u0011Q|7\u000b\u001e:j]\u001e$\u0012AW\u0001\u0005G>\u0004\u0018\u0010\u0006\u0002BS\"9\u0001\f\u0005I\u0001\u0002\u0004Q\u0016AD2paf$C-\u001a4bk2$H%M\u000b\u0002Y*\u0012!,\\\u0016\u0002]B\u0011q\u000e^\u0007\u0002a*\u0011\u0011O]\u0001\nk:\u001c\u0007.Z2lK\u0012T!a]\u0019\u0002\u0015\u0005tgn\u001c;bi&|g.\u0003\u0002va\n\tRO\\2iK\u000e\\W\r\u001a,be&\fgnY3\u0002\u001bA\u0014x\u000eZ;diB\u0013XMZ5y+\u0005A\bCA=\u007f\u001b\u0005Q(BA>}\u0003\u0011a\u0017M\\4\u000b\u0003u\fAA[1wC&\u0011\u0001M_\u0001\raJ|G-^2u\u0003JLG/_\u000b\u0003\u0003\u0007\u00012!SA\u0003\u0013\r\t9!\r\u0002\u0004\u0013:$\u0018A\u00049s_\u0012,8\r^#mK6,g\u000e\u001e\u000b\u0005\u0003\u001b\t\u0019\u0002E\u0002J\u0003\u001fI1!!\u00052\u0005\r\te.\u001f\u0005\n\u0003+!\u0012\u0011!a\u0001\u0003\u0007\t1\u0001\u001f\u00132\u0003=\u0001(o\u001c3vGRLE/\u001a:bi>\u0014XCAA\u000e!\u0019\ti\"a\t\u0002\u000e5\u0011\u0011q\u0004\u0006\u0004\u0003C\t\u0014AC2pY2,7\r^5p]&!\u0011QEA\u0010\u0005!IE/\u001a:bi>\u0014\u0018\u0001C2b]\u0016\u000bX/\u00197\u0015\t\u0005-\u0012\u0011\u0007\t\u0004\u0013\u00065\u0012bAA\u0018c\t9!i\\8mK\u0006t\u0007\"CA\u000b-\u0005\u0005\t\u0019AA\u0007\u0003I\u0001(o\u001c3vGR,E.Z7f]Rt\u0015-\\3\u0015\u0007a\f9\u0004C\u0005\u0002\u0016]\t\t\u00111\u0001\u0002\u0004\u0005A\u0001.Y:i\u0007>$W\r\u0006\u0002\u0002\u0004\u00051Q-];bYN$B!a\u000b\u0002B!I\u0011QC\r\u0002\u0002\u0003\u0007\u0011Q\u0002\u0002\t?J,w-\u001a=q)B\u0019!)a\u0012\n\t\u0005%\u00131\n\u0002\u0007%\u0016<W\t\u001f9\n\u0007\u00055#H\u0001\u0003CCN,\'A\u0003+sC:\u001cH.\u0019;peN\u0019Q!a\u0015\u0011\u0007e\n)&C\u0002\u0002Xi\u0012abV8sI\n+\'O]=TKRD\u0017\u000eK\u0006\u0006\u00037\n\t\'a\u0019\u0002h\u0005%\u0004cA%\u0002^%\u0019\u0011qL\u0019\u0003\u0015\u0011,\u0007O]3dCR,G-A\u0004nKN\u001c\u0018mZ3\"\u0005\u0005\u0015\u0014!C!w_&$\u0017M\\2f\u0003\u0015\u0019\u0018N\\2fC\t\tY\'\u0001\u00033]E\u0002\u0014A\u0003+sC:\u001cH.\u0019;peB\u0011!iB\n\u0006\u000f\u0005M\u00131\u000f\t\u0003\u0005\u0016!\"!a\u001c\u0016\u0003\t\u000bQ\u0001\\1oO\u0002B3aBA.\u0003!)E.Z7OC6,\u0007C\u0001\"\u001c\'\u0015Y\u00121QAH!\u0019\t))a#[\u00036\u0011\u0011q\u0011\u0006\u0004\u0003\u0013\u000b\u0014a\u0002:v]RLW.Z\u0005\u0005\u0003\u001b\u000b9IA\tBEN$(/Y2u\rVt7\r^5p]F\u0002B!!%\u0002\u00186\u0011\u00111\u0013\u0006\u0004\u0003+c\u0018AA5p\u0013\r1\u00161\u0013\u000b\u0003\u0003\u007f\"\u0012\u0001_\u0001\u0006CB\u0004H.\u001f\u000b\u0004\u0003\u0006\u0005\u0006\"\u0002-\u001f\u0001\u0004Q\u0016aB;oCB\u0004H.\u001f\u000b\u0005\u0003O\u000bi\u000b\u0005\u0003J\u0003SS\u0016bAAVc\t1q\n\u001d;j_:D\u0001\"a, \u0003\u0003\u0005\r!Q\u0001\u0004q\u0012\u0002\u0014\u0001D<sSR,\'+\u001a9mC\u000e,GCAA[!\rI\u0018qW\u0005\u0004\u0003sS(AB(cU\u0016\u001cG/A\u0004jg6K\u00070\u001a3\u0015\t\u0005-\u0012q\u0018\u0005\b\u0003\u0003\f\u0003\u0019AAb\u0003\t\u0019W\u000e\u0005\u00026QM\u0019\u0001&a2\u0011\u0007%\u000bI-C\u0002\u0002LF\u0012a!\u00118z%\u00164GCAAb\u0003-\u0011W/\u001b7e\'R\u0014\u0018N\\4\u0015\t\u0005M\u00171\u001c\t\u0005\u0003+\f9N\u0004\u0002J\'&\u0019\u0011\u0011\\,\u0003\u001bM#(/\u001b8h\u0005VLG\u000eZ3s\u0011\u001d\tin\u000ba\u0001\u0003\'\f!a\u001d2*\u0013!\n\t/!:\u0002j\u00065(bAAr[\u0005\u0019\u0011IT-\n\u0007\u0005\u001dXFA\bE\r\u0006\u001buN\u001c;f]Rlu\u000eZ3m\u0015\r\tY/L\u0001\u0006\u000b6\u0003F+\u0017\u0006\u0004\u0003_l\u0013A\u0002)D\t\u0006#\u0016)\u0001\u0007d_:$\u0018-\u001b8t)\u0016DH\u000f\u0006\u0003\u0002,\u0005U\bbBAaE\u0001\u0007\u00111Y\u0001\nO\u0016$H*\u00192fYN$B!a?\u0003\u0002A!1,!@[\u0013\r\ty0\u0019\u0002\u0004\'\u0016$\bb\u0002B\u0002G\u0001\u0007\u0011QI\u0001\u0002eR\u0019!La\u0002\t\u000f\t\rA\u00051\u0001\u0002FQA!1\u0002B\t\u00057\u0011i\u0002E\u0002J\u0005\u001bI1Aa\u00042\u0005\u0011)f.\u001b;\t\u000f\tMQ\u00051\u0001\u0003\u0016\u0005\u0011!o\u001d\t\u0007\u0003;\u00119\"!\u0012\n\t\te\u0011q\u0004\u0002\u0004\'\u0016\f\bbBAoK\u0001\u0007\u00111\u001b\u0005\b\u0005?)\u0003\u0019\u0001B\u0011\u0003\r\u0019X\r\u001d\t\u0004\u0013\n\r\u0012b\u0001B\u0013c\t!1\t[1s)\u0019\t\u0019N!\u000b\u0003.!9!1\u0006\u0014A\u0002\u0005\r\u0017!A2\t\u000f\u0005ug\u00051\u0001\u0002TR1\u00111\u001bB\u0019\u0005gAqAa\u0001(\u0001\u0004\t)\u0005C\u0004\u0002^\u001e\u0002\r!a5"
    )
BootstrapMethods:
  0: #121 REF_invokeStatic java/lang/invoke/LambdaMetafactory.altMetafactory:(Ljava/lang/invoke/MethodHandles$Lookup;Ljava/lang/String;Ljava/lang/invoke/MethodType;[Ljava/lang/Object;)Ljava/lang/invoke/CallSite;
    Method arguments:
      #105 (Ljava/lang/Object;)Ljava/lang/Object;
      #110 REF_invokeStatic scala/xml/dtd/ContentModel.$anonfun$toString$1$adapted:(Lscala/xml/dtd/ContentModel;Lscala/collection/mutable/StringBuilder;)Ljava/lang/Object;
      #112 (Lscala/collection/mutable/StringBuilder;)Ljava/lang/Object;
      #113 5
      #114 1
      #112 (Lscala/collection/mutable/StringBuilder;)Ljava/lang/Object;
  1: #160 REF_invokeStatic scala/runtime/LambdaDeserialize.bootstrap:(Ljava/lang/invoke/MethodHandles$Lookup;Ljava/lang/String;Ljava/lang/invoke/MethodType;[Ljava/lang/invoke/MethodHandle;)Ljava/lang/invoke/CallSite;
    Method arguments:
      #110 REF_invokeStatic scala/xml/dtd/ContentModel.$anonfun$toString$1$adapted:(Lscala/xml/dtd/ContentModel;Lscala/collection/mutable/StringBuilder;)Ljava/lang/Object;
  ScalaInlineInfo: length = 0x1D (unknown attribute)
   01 00 00 05 00 86 00 87 01 00 6A 00 6B 01 00 8C
   00 8D 00 00 83 00 84 00 00 61 00 62 00
  ScalaSig: length = 0x3 (unknown attribute)
   05 02 00
