Classfile /Users/mw/Projects/slang-braindump/.jar/jar11/assemble/slang-braindump/assemble/content/scala/xml/dtd/DefaultDecl.class
  Last modified May 29, 2022; size 964 bytes
  SHA-256 checksum 62edd5e0e85d2ca40e1283bd1a75fcff0be86bf22310b04399cc57829fc46961
  Compiled from "Decl.scala"
public abstract class scala.xml.dtd.DefaultDecl
  minor version: 0
  major version: 52
  flags: (0x0421) ACC_PUBLIC, ACC_SUPER, ACC_ABSTRACT
  this_class: #2                          // scala/xml/dtd/DefaultDecl
  super_class: #4                         // java/lang/Object
  interfaces: 0, fields: 0, methods: 3, attributes: 4
Constant pool:
   #1 = Utf8               scala/xml/dtd/DefaultDecl
   #2 = Class              #1             // scala/xml/dtd/DefaultDecl
   #3 = Utf8               java/lang/Object
   #4 = Class              #3             // java/lang/Object
   #5 = Utf8               Decl.scala
   #6 = Utf8               Lscala/reflect/ScalaSignature;
   #7 = Utf8               bytes
   #8 = Utf8               \u0006\u0005Q2Q\u0001B\u0003\u0002\"1AQ!\u0005\u0001\u0005\u0002IAQ!\u0006\u0001\u0007BYAQA\t\u0001\u0007\u0002\r\u00121\u0002R3gCVdG\u000fR3dY*\u0011aaB\u0001\u0004IR$\'B\u0001\u0005\n\u0003\rAX\u000e\u001c\u0006\u0002\u0015\u0005)1oY1mC\u000e\u00011C\u0001\u0001\u000e!\tqq\"D\u0001\n\u0013\t\u0001\u0012B\u0001\u0004B]f\u0014VMZ\u0001\u0007y%t\u0017\u000e\u001e \u0015\u0003M\u0001\"\u0001\u0006\u0001\u000e\u0003\u0015\t\u0001\u0002^8TiJLgn\u001a\u000b\u0002/A\u0011\u0001d\b\b\u00033u\u0001\"AG\u0005\u000e\u0003mQ!\u0001H\u0006\u0002\rq\u0012xn\u001c;?\u0013\tq\u0012\"\u0001\u0004Qe\u0016$WMZ\u0005\u0003A\u0005\u0012aa\u0015;sS:<\'B\u0001\u0010\n\u0003-\u0011W/\u001b7e\'R\u0014\u0018N\\4\u0015\u0005\u0011Z\u0003CA\u0013)\u001d\tqa%\u0003\u0002(\u0013\u00059\u0001/Y2lC\u001e,\u0017BA\u0015+\u00055\u0019FO]5oO\n+\u0018\u000e\u001c3fe*\u0011q%\u0003\u0005\u0006Y\r\u0001\r\u0001J\u0001\u0003g\nLC\u0001\u0001\u00181e%\u0011q&\u0002\u0002\b\t\u00163\u0015)\u0016\'U\u0015\t\tT!A\u0004J\u001bBc\u0015*\u0012#\u000b\u0005M*\u0011\u0001\u0003*F#VK%+\u0012#
   #9 = Utf8               toString
  #10 = Utf8               ()Ljava/lang/String;
  #11 = Utf8               buildString
  #12 = Utf8               (Lscala/collection/mutable/StringBuilder;)Lscala/collection/mutable/StringBuilder;
  #13 = Utf8               sb
  #14 = Utf8               <init>
  #15 = Utf8               ()V
  #16 = NameAndType        #14:#15        // "<init>":()V
  #17 = Methodref          #4.#16         // java/lang/Object."<init>":()V
  #18 = Utf8               this
  #19 = Utf8               Lscala/xml/dtd/DefaultDecl;
  #20 = Utf8               MethodParameters
  #21 = Utf8               Code
  #22 = Utf8               LineNumberTable
  #23 = Utf8               LocalVariableTable
  #24 = Utf8               SourceFile
  #25 = Utf8               RuntimeVisibleAnnotations
  #26 = Utf8               ScalaInlineInfo
  #27 = Utf8               ScalaSig
{
  public abstract java.lang.String toString();
    descriptor: ()Ljava/lang/String;
    flags: (0x0401) ACC_PUBLIC, ACC_ABSTRACT

  public abstract scala.collection.mutable.StringBuilder buildString(scala.collection.mutable.StringBuilder);
    descriptor: (Lscala/collection/mutable/StringBuilder;)Lscala/collection/mutable/StringBuilder;
    flags: (0x0401) ACC_PUBLIC, ACC_ABSTRACT
    MethodParameters:
      Name                           Flags
      sb                             final

  public scala.xml.dtd.DefaultDecl();
    descriptor: ()V
    flags: (0x0001) ACC_PUBLIC
    Code:
      stack=1, locals=1, args_size=1
         0: aload_0
         1: invokespecial #17                 // Method java/lang/Object."<init>":()V
         4: return
      LineNumberTable:
        line 157: 0
        line 152: 4
      LocalVariableTable:
        Start  Length  Slot  Name   Signature
            0       5     0  this   Lscala/xml/dtd/DefaultDecl;
}
SourceFile: "Decl.scala"
RuntimeVisibleAnnotations:
  0: #6(#7=s#8)
    scala.reflect.ScalaSignature(
      bytes="\u0006\u0005Q2Q\u0001B\u0003\u0002\"1AQ!\u0005\u0001\u0005\u0002IAQ!\u0006\u0001\u0007BYAQA\t\u0001\u0007\u0002\r\u00121\u0002R3gCVdG\u000fR3dY*\u0011aaB\u0001\u0004IR$\'B\u0001\u0005\n\u0003\rAX\u000e\u001c\u0006\u0002\u0015\u0005)1oY1mC\u000e\u00011C\u0001\u0001\u000e!\tqq\"D\u0001\n\u0013\t\u0001\u0012B\u0001\u0004B]f\u0014VMZ\u0001\u0007y%t\u0017\u000e\u001e \u0015\u0003M\u0001\"\u0001\u0006\u0001\u000e\u0003\u0015\t\u0001\u0002^8TiJLgn\u001a\u000b\u0002/A\u0011\u0001d\b\b\u00033u\u0001\"AG\u0005\u000e\u0003mQ!\u0001H\u0006\u0002\rq\u0012xn\u001c;?\u0013\tq\u0012\"\u0001\u0004Qe\u0016$WMZ\u0005\u0003A\u0005\u0012aa\u0015;sS:<\'B\u0001\u0010\n\u0003-\u0011W/\u001b7e\'R\u0014\u0018N\\4\u0015\u0005\u0011Z\u0003CA\u0013)\u001d\tqa%\u0003\u0002(\u0013\u00059\u0001/Y2lC\u001e,\u0017BA\u0015+\u00055\u0019FO]5oO\n+\u0018\u000e\u001c3fe*\u0011q%\u0003\u0005\u0006Y\r\u0001\r\u0001J\u0001\u0003g\nLC\u0001\u0001\u00181e%\u0011q&\u0002\u0002\b\t\u00163\u0015)\u0016\'U\u0015\t\tT!A\u0004J\u001bBc\u0015*\u0012#\u000b\u0005M*\u0011\u0001\u0003*F#VK%+\u0012#"
    )
  ScalaInlineInfo: length = 0x13 (unknown attribute)
   01 00 00 03 00 0E 00 0F 00 00 0B 00 0C 00 00 09
   00 0A 00
  ScalaSig: length = 0x3 (unknown attribute)
   05 02 00
