Classfile /Users/mw/Projects/slang-braindump/.jar/jar11/assemble/slang-braindump/assemble/content/scala/xml/dtd/ELEMENTS$.class
  Last modified May 29, 2022; size 1930 bytes
  SHA-256 checksum cb26c6f9384c0a7bf27439bd3b2dc93d3a361fa29ca03aaaf8247ec19bc0ce2b
  Compiled from "ContentModel.scala"
public final class scala.xml.dtd.ELEMENTS$ extends scala.runtime.AbstractFunction1<scala.xml.dtd.impl.Base$RegExp, scala.xml.dtd.ELEMENTS> implements java.io.Serializable
  minor version: 0
  major version: 52
  flags: (0x0031) ACC_PUBLIC, ACC_FINAL, ACC_SUPER
  this_class: #2                          // scala/xml/dtd/ELEMENTS$
  super_class: #5                         // scala/runtime/AbstractFunction1
  interfaces: 1, fields: 1, methods: 7, attributes: 5
Constant pool:
   #1 = Utf8               scala/xml/dtd/ELEMENTS$
   #2 = Class              #1             // scala/xml/dtd/ELEMENTS$
   #3 = Utf8               Lscala/runtime/AbstractFunction1<Lscala/xml/dtd/impl/Base$RegExp;Lscala/xml/dtd/ELEMENTS;>;Ljava/io/Serializable;
   #4 = Utf8               scala/runtime/AbstractFunction1
   #5 = Class              #4             // scala/runtime/AbstractFunction1
   #6 = Utf8               java/io/Serializable
   #7 = Class              #6             // java/io/Serializable
   #8 = Utf8               ContentModel.scala
   #9 = Utf8               scala/xml/dtd/impl/Base$RegExp
  #10 = Class              #9             // scala/xml/dtd/impl/Base$RegExp
  #11 = Utf8               scala/xml/dtd/impl/Base
  #12 = Class              #11            // scala/xml/dtd/impl/Base
  #13 = Utf8               RegExp
  #14 = Utf8               MODULE$
  #15 = Utf8               Lscala/xml/dtd/ELEMENTS$;
  #16 = Utf8               <clinit>
  #17 = Utf8               ()V
  #18 = Utf8               <init>
  #19 = NameAndType        #18:#17        // "<init>":()V
  #20 = Methodref          #2.#19         // scala/xml/dtd/ELEMENTS$."<init>":()V
  #21 = NameAndType        #14:#15        // MODULE$:Lscala/xml/dtd/ELEMENTS$;
  #22 = Fieldref           #2.#21         // scala/xml/dtd/ELEMENTS$.MODULE$:Lscala/xml/dtd/ELEMENTS$;
  #23 = Utf8               toString
  #24 = Utf8               ()Ljava/lang/String;
  #25 = Utf8               ELEMENTS
  #26 = String             #25            // ELEMENTS
  #27 = Utf8               this
  #28 = Utf8               apply
  #29 = Utf8               (Lscala/xml/dtd/impl/Base$RegExp;)Lscala/xml/dtd/ELEMENTS;
  #30 = Utf8               r
  #31 = Utf8               scala/xml/dtd/ELEMENTS
  #32 = Class              #31            // scala/xml/dtd/ELEMENTS
  #33 = Utf8               (Lscala/xml/dtd/impl/Base$RegExp;)V
  #34 = NameAndType        #18:#33        // "<init>":(Lscala/xml/dtd/impl/Base$RegExp;)V
  #35 = Methodref          #32.#34        // scala/xml/dtd/ELEMENTS."<init>":(Lscala/xml/dtd/impl/Base$RegExp;)V
  #36 = Utf8               Lscala/xml/dtd/impl/Base$RegExp;
  #37 = Utf8               unapply
  #38 = Utf8               (Lscala/xml/dtd/ELEMENTS;)Lscala/Option;
  #39 = Utf8               (Lscala/xml/dtd/ELEMENTS;)Lscala/Option<Lscala/xml/dtd/impl/Base$RegExp;>;
  #40 = Utf8               x$0
  #41 = Utf8               scala/None$
  #42 = Class              #41            // scala/None$
  #43 = Utf8               Lscala/None$;
  #44 = NameAndType        #14:#43        // MODULE$:Lscala/None$;
  #45 = Fieldref           #42.#44        // scala/None$.MODULE$:Lscala/None$;
  #46 = Utf8               scala/Some
  #47 = Class              #46            // scala/Some
  #48 = Utf8               ()Lscala/xml/dtd/impl/Base$RegExp;
  #49 = NameAndType        #30:#48        // r:()Lscala/xml/dtd/impl/Base$RegExp;
  #50 = Methodref          #32.#49        // scala/xml/dtd/ELEMENTS.r:()Lscala/xml/dtd/impl/Base$RegExp;
  #51 = Utf8               (Ljava/lang/Object;)V
  #52 = NameAndType        #18:#51        // "<init>":(Ljava/lang/Object;)V
  #53 = Methodref          #47.#52        // scala/Some."<init>":(Ljava/lang/Object;)V
  #54 = Utf8               Lscala/xml/dtd/ELEMENTS;
  #55 = Utf8               scala/Option
  #56 = Class              #55            // scala/Option
  #57 = Utf8               writeReplace
  #58 = Utf8               ()Ljava/lang/Object;
  #59 = Utf8               scala/runtime/ModuleSerializationProxy
  #60 = Class              #59            // scala/runtime/ModuleSerializationProxy
  #61 = Utf8               (Ljava/lang/Class;)V
  #62 = NameAndType        #18:#61        // "<init>":(Ljava/lang/Class;)V
  #63 = Methodref          #60.#62        // scala/runtime/ModuleSerializationProxy."<init>":(Ljava/lang/Class;)V
  #64 = Utf8               (Ljava/lang/Object;)Ljava/lang/Object;
  #65 = Utf8               v1
  #66 = NameAndType        #28:#29        // apply:(Lscala/xml/dtd/impl/Base$RegExp;)Lscala/xml/dtd/ELEMENTS;
  #67 = Methodref          #2.#66         // scala/xml/dtd/ELEMENTS$.apply:(Lscala/xml/dtd/impl/Base$RegExp;)Lscala/xml/dtd/ELEMENTS;
  #68 = Utf8               Ljava/lang/Object;
  #69 = Methodref          #5.#19         // scala/runtime/AbstractFunction1."<init>":()V
  #70 = Utf8               Code
  #71 = Utf8               LineNumberTable
  #72 = Utf8               LocalVariableTable
  #73 = Utf8               MethodParameters
  #74 = Utf8               StackMapTable
  #75 = Utf8               Signature
  #76 = Utf8               InnerClasses
  #77 = Utf8               SourceFile
  #78 = Utf8               ScalaInlineInfo
  #79 = Utf8               Scala
{
  public static final scala.xml.dtd.ELEMENTS$ MODULE$;
    descriptor: Lscala/xml/dtd/ELEMENTS$;
    flags: (0x0019) ACC_PUBLIC, ACC_STATIC, ACC_FINAL

  public static {};
    descriptor: ()V
    flags: (0x0009) ACC_PUBLIC, ACC_STATIC
    Code:
      stack=2, locals=0, args_size=0
         0: new           #2                  // class scala/xml/dtd/ELEMENTS$
         3: dup
         4: invokespecial #20                 // Method "<init>":()V
         7: putstatic     #22                 // Field MODULE$:Lscala/xml/dtd/ELEMENTS$;
        10: return
      LineNumberTable:
        line 129: 0

  public final java.lang.String toString();
    descriptor: ()Ljava/lang/String;
    flags: (0x0011) ACC_PUBLIC, ACC_FINAL
    Code:
      stack=1, locals=1, args_size=1
         0: ldc           #26                 // String ELEMENTS
         2: areturn
      LineNumberTable:
        line 129: 0
      LocalVariableTable:
        Start  Length  Slot  Name   Signature
            0       3     0  this   Lscala/xml/dtd/ELEMENTS$;

  public scala.xml.dtd.ELEMENTS apply(scala.xml.dtd.impl.Base$RegExp);
    descriptor: (Lscala/xml/dtd/impl/Base$RegExp;)Lscala/xml/dtd/ELEMENTS;
    flags: (0x0001) ACC_PUBLIC
    Code:
      stack=3, locals=2, args_size=2
         0: new           #32                 // class scala/xml/dtd/ELEMENTS
         3: dup
         4: aload_1
         5: invokespecial #35                 // Method scala/xml/dtd/ELEMENTS."<init>":(Lscala/xml/dtd/impl/Base$RegExp;)V
         8: areturn
      LineNumberTable:
        line 129: 0
      LocalVariableTable:
        Start  Length  Slot  Name   Signature
            0       9     0  this   Lscala/xml/dtd/ELEMENTS$;
            0       9     1     r   Lscala/xml/dtd/impl/Base$RegExp;
    MethodParameters:
      Name                           Flags
      r                              final

  public scala.Option<scala.xml.dtd.impl.Base$RegExp> unapply(scala.xml.dtd.ELEMENTS);
    descriptor: (Lscala/xml/dtd/ELEMENTS;)Lscala/Option;
    flags: (0x0001) ACC_PUBLIC
    Code:
      stack=3, locals=2, args_size=2
         0: aload_1
         1: ifnonnull     10
         4: getstatic     #45                 // Field scala/None$.MODULE$:Lscala/None$;
         7: goto          21
        10: new           #47                 // class scala/Some
        13: dup
        14: aload_1
        15: invokevirtual #50                 // Method scala/xml/dtd/ELEMENTS.r:()Lscala/xml/dtd/impl/Base$RegExp;
        18: invokespecial #53                 // Method scala/Some."<init>":(Ljava/lang/Object;)V
        21: areturn
      StackMapTable: number_of_entries = 2
        frame_type = 10 /* same */
        frame_type = 74 /* same_locals_1_stack_item */
          stack = [ class scala/Option ]
      LineNumberTable:
        line 129: 0
      LocalVariableTable:
        Start  Length  Slot  Name   Signature
            0      22     0  this   Lscala/xml/dtd/ELEMENTS$;
            0      22     1   x$0   Lscala/xml/dtd/ELEMENTS;
    Signature: #39                          // (Lscala/xml/dtd/ELEMENTS;)Lscala/Option<Lscala/xml/dtd/impl/Base$RegExp;>;
    MethodParameters:
      Name                           Flags
      x$0                            final

  private java.lang.Object writeReplace();
    descriptor: ()Ljava/lang/Object;
    flags: (0x0002) ACC_PRIVATE
    Code:
      stack=3, locals=1, args_size=1
         0: new           #60                 // class scala/runtime/ModuleSerializationProxy
         3: dup
         4: ldc           #2                  // class scala/xml/dtd/ELEMENTS$
         6: invokespecial #63                 // Method scala/runtime/ModuleSerializationProxy."<init>":(Ljava/lang/Class;)V
         9: areturn
      LineNumberTable:
        line 129: 0
      LocalVariableTable:
        Start  Length  Slot  Name   Signature
            0      10     0  this   Lscala/xml/dtd/ELEMENTS$;

  public java.lang.Object apply(java.lang.Object);
    descriptor: (Ljava/lang/Object;)Ljava/lang/Object;
    flags: (0x1041) ACC_PUBLIC, ACC_BRIDGE, ACC_SYNTHETIC
    Code:
      stack=2, locals=2, args_size=2
         0: aload_0
         1: aload_1
         2: checkcast     #10                 // class scala/xml/dtd/impl/Base$RegExp
         5: invokevirtual #67                 // Method apply:(Lscala/xml/dtd/impl/Base$RegExp;)Lscala/xml/dtd/ELEMENTS;
         8: areturn
      LineNumberTable:
        line 129: 0
      LocalVariableTable:
        Start  Length  Slot  Name   Signature
            0       9     0  this   Lscala/xml/dtd/ELEMENTS$;
            0       9     1    v1   Ljava/lang/Object;
    MethodParameters:
      Name                           Flags
      v1                             final

  private scala.xml.dtd.ELEMENTS$();
    descriptor: ()V
    flags: (0x0002) ACC_PRIVATE
    Code:
      stack=1, locals=1, args_size=1
         0: aload_0
         1: invokespecial #69                 // Method scala/runtime/AbstractFunction1."<init>":()V
         4: return
      LineNumberTable:
        line 129: 0
      LocalVariableTable:
        Start  Length  Slot  Name   Signature
            0       5     0  this   Lscala/xml/dtd/ELEMENTS$;
}
InnerClasses:
  public abstract #13= #10 of #12;        // RegExp=class scala/xml/dtd/impl/Base$RegExp of class scala/xml/dtd/impl/Base
Signature: #3                           // Lscala/runtime/AbstractFunction1<Lscala/xml/dtd/impl/Base$RegExp;Lscala/xml/dtd/ELEMENTS;>;Ljava/io/Serializable;
SourceFile: "ContentModel.scala"
  ScalaInlineInfo: length = 0x22 (unknown attribute)
   01 01 00 06 00 12 00 11 01 00 1C 00 40 01 00 1C
   00 1D 01 00 17 00 18 01 00 25 00 26 01 00 39 00
   3A 01
  Scala: length = 0x0 (unknown attribute)

