Classfile /Users/mw/Projects/slang-braindump/.jar/jar11/assemble/slang-braindump/assemble/content/scala/xml/dtd/ELEMENTS.class
  Last modified May 29, 2022; size 5533 bytes
  SHA-256 checksum e10cab669d7e2ad6f139b1bc7f62148123516dc517852170c604c1a1bb8ec67d
  Compiled from "ContentModel.scala"
public class scala.xml.dtd.ELEMENTS extends scala.xml.dtd.DFAContentModel implements scala.Product,java.io.Serializable
  minor version: 0
  major version: 52
  flags: (0x0021) ACC_PUBLIC, ACC_SUPER
  this_class: #2                          // scala/xml/dtd/ELEMENTS
  super_class: #4                         // scala/xml/dtd/DFAContentModel
  interfaces: 2, fields: 1, methods: 18, attributes: 5
Constant pool:
    #1 = Utf8               scala/xml/dtd/ELEMENTS
    #2 = Class              #1            // scala/xml/dtd/ELEMENTS
    #3 = Utf8               scala/xml/dtd/DFAContentModel
    #4 = Class              #3            // scala/xml/dtd/DFAContentModel
    #5 = Utf8               scala/Product
    #6 = Class              #5            // scala/Product
    #7 = Utf8               java/io/Serializable
    #8 = Class              #7            // java/io/Serializable
    #9 = Utf8               ContentModel.scala
   #10 = Utf8               Lscala/reflect/ScalaSignature;
   #11 = Utf8               bytes
   #12 = Utf8               \u0006\u0005\u0005=c\u0001\u0002\f\u0018\u0001zA\u0001b\r\u0001\u0003\u0016\u0004%\t\u0001\u000e\u0005\t\u007f\u0001\u0011\t\u0012)A\u0005k!)\u0001\t\u0001C\u0001\u0003\")A\t\u0001C!\u000b\"9A\nAA\u0001\n\u0003i\u0005bB(\u0001#\u0003%\t\u0001\u0015\u0005\b7\u0002\t\t\u0011\"\u0011]\u0011\u001d)\u0007!!A\u0005\u0002\u0019DqA\u001b\u0001\u0002\u0002\u0013\u00051\u000eC\u0004r\u0001\u0005\u0005I\u0011\t:\t\u000fe\u0004\u0011\u0011!C\u0001u\"Aq\u0010AA\u0001\n\u0003\n\t\u0001C\u0005\u0002\u0006\u0001\t\t\u0011\"\u0011\u0002\b!I\u0011\u0011\u0002\u0001\u0002\u0002\u0013\u0005\u00131B\u0004\n\u0003\u001f9\u0012\u0011!E\u0001\u0003#1\u0001BF\f\u0002\u0002#\u0005\u00111\u0003\u0005\u0007\u0001B!\t!a\u000b\t\u0013\u00055\u0002#!A\u0005F\u0005=\u0002\"CA\u0019!\u0005\u0005I\u0011QA\u001a\u0011%\t9\u0004EA\u0001\n\u0003\u000bI\u0004C\u0005\u0002FA\t\t\u0011\"\u0003\u0002H\tAQ\tT#N\u000b:#6K\u0003\u0002\u00193\u0005\u0019A\r\u001e3\u000b\u0005iY\u0012a\u0001=nY*\tA$A\u0003tG\u0006d\u0017m\u0001\u0001\u0014\t\u0001y2e\n\t\u0003A\u0005j\u0011aF\u0005\u0003E]\u0011q\u0002\u0012$B\u0007>tG/\u001a8u\u001b>$W\r\u001c\t\u0003I\u0015j\u0011aG\u0005\u0003Mm\u0011q\u0001\u0015:pIV\u001cG\u000f\u0005\u0002)a9\u0011\u0011F\f\b\u0003U5j\u0011a\u000b\u0006\u0003Yu\ta\u0001\u0010:p_Rt\u0014\"\u0001\u000f\n\u0005=Z\u0012a\u00029bG.\fw-Z\u0005\u0003cI\u0012AbU3sS\u0006d\u0017N_1cY\u0016T!aL\u000e\u0002\u0003I,\u0012!\u000e\t\u0003mer!\u0001I\u001c\n\u0005a:\u0012\u0001D\"p]R,g\u000e^\'pI\u0016d\u0017B\u0001\u001e<\u0005\u0019\u0011VmZ#ya&\u0011A(\u0010\u0002\u0005\u0005\u0006\u001cXM\u0003\u0002?/\u0005!\u0011.\u001c9m\u0003\t\u0011\b%\u0001\u0004=S:LGO\u0010\u000b\u0003\u0005\u000e\u0003\"\u0001\t\u0001\t\u000bM\u001a\u0001\u0019A\u001b\u0002\u0017\t,\u0018\u000e\u001c3TiJLgn\u001a\u000b\u0003\r*\u0003\"a\u0012%\u000f\u0005\u0011r\u0013BA%3\u00055\u0019FO]5oO\n+\u0018\u000e\u001c3fe\")1\n\u0002a\u0001\r\u0006\u00111OY\u0001\u0005G>\u0004\u0018\u0010\u0006\u0002C\u001d\"91\'\u0002I\u0001\u0002\u0004)\u0014AD2paf$C-\u001a4bk2$H%M\u000b\u0002#*\u0012QGU\u0016\u0002\'B\u0011A+W\u0007\u0002+*\u0011akV\u0001\nk:\u001c\u0007.Z2lK\u0012T!\u0001W\u000e\u0002\u0015\u0005tgn\u001c;bi&|g.\u0003\u0002[+\n\tRO\\2iK\u000e\\W\r\u001a,be&\fgnY3\u0002\u001bA\u0014x\u000eZ;diB\u0013XMZ5y+\u0005i\u0006C\u00010d\u001b\u0005y&B\u00011b\u0003\u0011a\u0017M\\4\u000b\u0003\t\fAA[1wC&\u0011Am\u0018\u0002\u0007\'R\u0014\u0018N\\4\u0002\u0019A\u0014x\u000eZ;di\u0006\u0013\u0018\u000e^=\u0016\u0003\u001d\u0004\"\u0001\n5\n\u0005%\\\"aA%oi\u0006q\u0001O]8ek\u000e$X\t\\3nK:$HC\u00017p!\t!S.\u0003\u0002o7\t\u0019\u0011I\\=\t\u000fAL\u0011\u0011!a\u0001O\u0006\u0019\u0001\u0010J\u0019\u0002\u001fA\u0014x\u000eZ;di&#XM]1u_J,\u0012a\u001d\t\u0004i^dW\"A;\u000b\u0005Y\\\u0012AC2pY2,7\r^5p]&\u0011\u00010\u001e\u0002\t\u0013R,\'/\u0019;pe\u0006A1-\u00198FcV\fG\u000e\u0006\u0002|}B\u0011A\u0005`\u0005\u0003{n\u0011qAQ8pY\u0016\fg\u000eC\u0004q\u0017\u0005\u0005\t\u0019\u00017\u0002%A\u0014x\u000eZ;di\u0016cW-\\3oi:\u000bW.\u001a\u000b\u0004;\u0006\r\u0001b\u00029\r\u0003\u0003\u0005\raZ\u0001\tQ\u0006\u001c\bnQ8eKR\tq-\u0001\u0004fcV\fGn\u001d\u000b\u0004w\u00065\u0001b\u00029\u000f\u0003\u0003\u0005\r\u0001\\\u0001\t\u000b2+U*\u0012(U\'B\u0011\u0001\u0005E\n\u0006!\u0005U\u0011\u0011\u0005\t\u0007\u0003/\ti\"\u000e\"\u000e\u0005\u0005e!bAA\u000e7\u00059!/\u001e8uS6,\u0017\u0002BA\u0010\u00033\u0011\u0011#\u00112tiJ\f7\r\u001e$v]\u000e$\u0018n\u001c82!\u0011\t\u0019#!\u000b\u000e\u0005\u0005\u0015\"bAA\u0014C\u0006\u0011\u0011n\\\u0005\u0004c\u0005\u0015BCAA\t\u0003!!xn\u0015;sS:<G#A/\u0002\u000b\u0005\u0004\b\u000f\\=\u0015\u0007\t\u000b)\u0004C\u00034\'\u0001\u0007Q\'A\u0004v]\u0006\u0004\b\u000f\\=\u0015\t\u0005m\u0012\u0011\t\t\u0005I\u0005uR\'C\u0002\u0002@m\u0011aa\u00149uS>t\u0007\u0002CA\")\u0005\u0005\t\u0019\u0001\"\u0002\u0007a$\u0003\'\u0001\u0007xe&$XMU3qY\u0006\u001cW\r\u0006\u0002\u0002JA\u0019a,a\u0013\n\u0007\u00055sL\u0001\u0004PE*,7\r\u001e
   #13 = Utf8               scala/xml/dtd/impl/Base$RegExp
   #14 = Class              #13           // scala/xml/dtd/impl/Base$RegExp
   #15 = Utf8               scala/xml/dtd/impl/Base
   #16 = Class              #15           // scala/xml/dtd/impl/Base
   #17 = Utf8               RegExp
   #18 = Utf8               r
   #19 = Utf8               Lscala/xml/dtd/impl/Base$RegExp;
   #20 = Utf8               unapply
   #21 = Utf8               (Lscala/xml/dtd/ELEMENTS;)Lscala/Option;
   #22 = Utf8               (Lscala/xml/dtd/ELEMENTS;)Lscala/Option<Lscala/xml/dtd/impl/Base$RegExp;>;
   #23 = Utf8               x$0
   #24 = Utf8               scala/xml/dtd/ELEMENTS$
   #25 = Class              #24           // scala/xml/dtd/ELEMENTS$
   #26 = Utf8               MODULE$
   #27 = Utf8               Lscala/xml/dtd/ELEMENTS$;
   #28 = NameAndType        #26:#27       // MODULE$:Lscala/xml/dtd/ELEMENTS$;
   #29 = Fieldref           #25.#28       // scala/xml/dtd/ELEMENTS$.MODULE$:Lscala/xml/dtd/ELEMENTS$;
   #30 = NameAndType        #20:#21       // unapply:(Lscala/xml/dtd/ELEMENTS;)Lscala/Option;
   #31 = Methodref          #25.#30       // scala/xml/dtd/ELEMENTS$.unapply:(Lscala/xml/dtd/ELEMENTS;)Lscala/Option;
   #32 = Utf8               Lscala/xml/dtd/ELEMENTS;
   #33 = Utf8               apply
   #34 = Utf8               (Lscala/xml/dtd/impl/Base$RegExp;)Lscala/xml/dtd/ELEMENTS;
   #35 = NameAndType        #33:#34       // apply:(Lscala/xml/dtd/impl/Base$RegExp;)Lscala/xml/dtd/ELEMENTS;
   #36 = Methodref          #25.#35       // scala/xml/dtd/ELEMENTS$.apply:(Lscala/xml/dtd/impl/Base$RegExp;)Lscala/xml/dtd/ELEMENTS;
   #37 = Utf8               andThen
   #38 = Utf8               (Lscala/Function1;)Lscala/Function1;
   #39 = Utf8               <A$:Ljava/lang/Object;>(Lscala/Function1<Lscala/xml/dtd/ELEMENTS;TA$;>;)Lscala/Function1<Lscala/xml/dtd/impl/Base$RegExp;TA$;>;
   #40 = Utf8               g
   #41 = NameAndType        #37:#38       // andThen:(Lscala/Function1;)Lscala/Function1;
   #42 = Methodref          #25.#41       // scala/xml/dtd/ELEMENTS$.andThen:(Lscala/Function1;)Lscala/Function1;
   #43 = Utf8               Lscala/Function1;
   #44 = Utf8               compose
   #45 = Utf8               <A$:Ljava/lang/Object;>(Lscala/Function1<TA$;Lscala/xml/dtd/impl/Base$RegExp;>;)Lscala/Function1<TA$;Lscala/xml/dtd/ELEMENTS;>;
   #46 = NameAndType        #44:#38       // compose:(Lscala/Function1;)Lscala/Function1;
   #47 = Methodref          #25.#46       // scala/xml/dtd/ELEMENTS$.compose:(Lscala/Function1;)Lscala/Function1;
   #48 = Utf8               productElementNames
   #49 = Utf8               ()Lscala/collection/Iterator;
   #50 = Utf8               ()Lscala/collection/Iterator<Ljava/lang/String;>;
   #51 = Utf8               productElementNames$
   #52 = Utf8               (Lscala/Product;)Lscala/collection/Iterator;
   #53 = NameAndType        #51:#52       // productElementNames$:(Lscala/Product;)Lscala/collection/Iterator;
   #54 = InterfaceMethodref #6.#53        // scala/Product.productElementNames$:(Lscala/Product;)Lscala/collection/Iterator;
   #55 = Utf8               this
   #56 = Utf8               ()Lscala/xml/dtd/impl/Base$RegExp;
   #57 = NameAndType        #18:#19       // r:Lscala/xml/dtd/impl/Base$RegExp;
   #58 = Fieldref           #2.#57        // scala/xml/dtd/ELEMENTS.r:Lscala/xml/dtd/impl/Base$RegExp;
   #59 = Utf8               buildString
   #60 = Utf8               (Lscala/collection/mutable/StringBuilder;)Lscala/collection/mutable/StringBuilder;
   #61 = Utf8               sb
   #62 = Utf8               scala/xml/dtd/ContentModel$
   #63 = Class              #62           // scala/xml/dtd/ContentModel$
   #64 = Utf8               Lscala/xml/dtd/ContentModel$;
   #65 = NameAndType        #26:#64       // MODULE$:Lscala/xml/dtd/ContentModel$;
   #66 = Fieldref           #63.#65       // scala/xml/dtd/ContentModel$.MODULE$:Lscala/xml/dtd/ContentModel$;
   #67 = NameAndType        #18:#56       // r:()Lscala/xml/dtd/impl/Base$RegExp;
   #68 = Methodref          #2.#67        // scala/xml/dtd/ELEMENTS.r:()Lscala/xml/dtd/impl/Base$RegExp;
   #69 = Utf8               (Lscala/xml/dtd/impl/Base$RegExp;Lscala/collection/mutable/StringBuilder;)Lscala/collection/mutable/StringBuilder;
   #70 = NameAndType        #59:#69       // buildString:(Lscala/xml/dtd/impl/Base$RegExp;Lscala/collection/mutable/StringBuilder;)Lscala/collection/mutable/StringBuilder;
   #71 = Methodref          #63.#70       // scala/xml/dtd/ContentModel$.buildString:(Lscala/xml/dtd/impl/Base$RegExp;Lscala/collection/mutable/StringBuilder;)Lscala/collection/mutable/StringBuilder;
   #72 = Utf8               Lscala/collection/mutable/StringBuilder;
   #73 = Utf8               copy
   #74 = Utf8               <init>
   #75 = Utf8               (Lscala/xml/dtd/impl/Base$RegExp;)V
   #76 = NameAndType        #74:#75       // "<init>":(Lscala/xml/dtd/impl/Base$RegExp;)V
   #77 = Methodref          #2.#76        // scala/xml/dtd/ELEMENTS."<init>":(Lscala/xml/dtd/impl/Base$RegExp;)V
   #78 = Utf8               copy$default$1
   #79 = Utf8               productPrefix
   #80 = Utf8               ()Ljava/lang/String;
   #81 = Utf8               ELEMENTS
   #82 = String             #81           // ELEMENTS
   #83 = Utf8               productArity
   #84 = Utf8               ()I
   #85 = Utf8               productElement
   #86 = Utf8               (I)Ljava/lang/Object;
   #87 = Utf8               x$1
   #88 = Utf8               scala/runtime/Statics
   #89 = Class              #88           // scala/runtime/Statics
   #90 = Utf8               ioobe
   #91 = NameAndType        #90:#86       // ioobe:(I)Ljava/lang/Object;
   #92 = Methodref          #89.#91       // scala/runtime/Statics.ioobe:(I)Ljava/lang/Object;
   #93 = Utf8               I
   #94 = Utf8               java/lang/Object
   #95 = Class              #94           // java/lang/Object
   #96 = Utf8               productIterator
   #97 = Utf8               ()Lscala/collection/Iterator<Ljava/lang/Object;>;
   #98 = Utf8               scala/runtime/ScalaRunTime$
   #99 = Class              #98           // scala/runtime/ScalaRunTime$
  #100 = Utf8               Lscala/runtime/ScalaRunTime$;
  #101 = NameAndType        #26:#100      // MODULE$:Lscala/runtime/ScalaRunTime$;
  #102 = Fieldref           #99.#101      // scala/runtime/ScalaRunTime$.MODULE$:Lscala/runtime/ScalaRunTime$;
  #103 = Utf8               typedProductIterator
  #104 = NameAndType        #103:#52      // typedProductIterator:(Lscala/Product;)Lscala/collection/Iterator;
  #105 = Methodref          #99.#104      // scala/runtime/ScalaRunTime$.typedProductIterator:(Lscala/Product;)Lscala/collection/Iterator;
  #106 = Utf8               canEqual
  #107 = Utf8               (Ljava/lang/Object;)Z
  #108 = Utf8               Ljava/lang/Object;
  #109 = Utf8               productElementName
  #110 = Utf8               (I)Ljava/lang/String;
  #111 = String             #18           // r
  #112 = Utf8               java/lang/String
  #113 = Class              #112          // java/lang/String
  #114 = Utf8               hashCode
  #115 = Utf8               _hashCode
  #116 = Utf8               (Lscala/Product;)I
  #117 = NameAndType        #115:#116     // _hashCode:(Lscala/Product;)I
  #118 = Methodref          #99.#117      // scala/runtime/ScalaRunTime$._hashCode:(Lscala/Product;)I
  #119 = Utf8               equals
  #120 = NameAndType        #119:#107     // equals:(Ljava/lang/Object;)Z
  #121 = Methodref          #95.#120      // java/lang/Object.equals:(Ljava/lang/Object;)Z
  #122 = NameAndType        #106:#107     // canEqual:(Ljava/lang/Object;)Z
  #123 = Methodref          #2.#122       // scala/xml/dtd/ELEMENTS.canEqual:(Ljava/lang/Object;)Z
  #124 = Utf8               ()V
  #125 = NameAndType        #74:#124      // "<init>":()V
  #126 = Methodref          #4.#125       // scala/xml/dtd/DFAContentModel."<init>":()V
  #127 = Utf8               $init$
  #128 = Utf8               (Lscala/Product;)V
  #129 = NameAndType        #127:#128     // $init$:(Lscala/Product;)V
  #130 = InterfaceMethodref #6.#129       // scala/Product.$init$:(Lscala/Product;)V
  #131 = Utf8               Code
  #132 = Utf8               LocalVariableTable
  #133 = Utf8               Signature
  #134 = Utf8               MethodParameters
  #135 = Utf8               LineNumberTable
  #136 = Utf8               StackMapTable
  #137 = Utf8               InnerClasses
  #138 = Utf8               SourceFile
  #139 = Utf8               RuntimeVisibleAnnotations
  #140 = Utf8               ScalaInlineInfo
  #141 = Utf8               ScalaSig
{
  private final scala.xml.dtd.impl.Base$RegExp r;
    descriptor: Lscala/xml/dtd/impl/Base$RegExp;
    flags: (0x0012) ACC_PRIVATE, ACC_FINAL

  public static scala.Option<scala.xml.dtd.impl.Base$RegExp> unapply(scala.xml.dtd.ELEMENTS);
    descriptor: (Lscala/xml/dtd/ELEMENTS;)Lscala/Option;
    flags: (0x0009) ACC_PUBLIC, ACC_STATIC
    Code:
      stack=2, locals=1, args_size=1
         0: getstatic     #29                 // Field scala/xml/dtd/ELEMENTS$.MODULE$:Lscala/xml/dtd/ELEMENTS$;
         3: aload_0
         4: invokevirtual #31                 // Method scala/xml/dtd/ELEMENTS$.unapply:(Lscala/xml/dtd/ELEMENTS;)Lscala/Option;
         7: areturn
      LocalVariableTable:
        Start  Length  Slot  Name   Signature
            0       8     0   x$0   Lscala/xml/dtd/ELEMENTS;
    Signature: #22                          // (Lscala/xml/dtd/ELEMENTS;)Lscala/Option<Lscala/xml/dtd/impl/Base$RegExp;>;
    MethodParameters:
      Name                           Flags
      x$0                            final

  public static scala.xml.dtd.ELEMENTS apply(scala.xml.dtd.impl.Base$RegExp);
    descriptor: (Lscala/xml/dtd/impl/Base$RegExp;)Lscala/xml/dtd/ELEMENTS;
    flags: (0x0009) ACC_PUBLIC, ACC_STATIC
    Code:
      stack=2, locals=1, args_size=1
         0: getstatic     #29                 // Field scala/xml/dtd/ELEMENTS$.MODULE$:Lscala/xml/dtd/ELEMENTS$;
         3: aload_0
         4: invokevirtual #36                 // Method scala/xml/dtd/ELEMENTS$.apply:(Lscala/xml/dtd/impl/Base$RegExp;)Lscala/xml/dtd/ELEMENTS;
         7: areturn
      LocalVariableTable:
        Start  Length  Slot  Name   Signature
            0       8     0     r   Lscala/xml/dtd/impl/Base$RegExp;
    MethodParameters:
      Name                           Flags
      r                              final

  public static <A$ extends java.lang.Object> scala.Function1<scala.xml.dtd.impl.Base$RegExp, A$> andThen(scala.Function1<scala.xml.dtd.ELEMENTS, A$>);
    descriptor: (Lscala/Function1;)Lscala/Function1;
    flags: (0x0009) ACC_PUBLIC, ACC_STATIC
    Code:
      stack=2, locals=1, args_size=1
         0: getstatic     #29                 // Field scala/xml/dtd/ELEMENTS$.MODULE$:Lscala/xml/dtd/ELEMENTS$;
         3: aload_0
         4: invokevirtual #42                 // Method scala/xml/dtd/ELEMENTS$.andThen:(Lscala/Function1;)Lscala/Function1;
         7: areturn
      LocalVariableTable:
        Start  Length  Slot  Name   Signature
            0       8     0     g   Lscala/Function1;
    Signature: #39                          // <A$:Ljava/lang/Object;>(Lscala/Function1<Lscala/xml/dtd/ELEMENTS;TA$;>;)Lscala/Function1<Lscala/xml/dtd/impl/Base$RegExp;TA$;>;
    MethodParameters:
      Name                           Flags
      g                              final

  public static <A$ extends java.lang.Object> scala.Function1<A$, scala.xml.dtd.ELEMENTS> compose(scala.Function1<A$, scala.xml.dtd.impl.Base$RegExp>);
    descriptor: (Lscala/Function1;)Lscala/Function1;
    flags: (0x0009) ACC_PUBLIC, ACC_STATIC
    Code:
      stack=2, locals=1, args_size=1
         0: getstatic     #29                 // Field scala/xml/dtd/ELEMENTS$.MODULE$:Lscala/xml/dtd/ELEMENTS$;
         3: aload_0
         4: invokevirtual #47                 // Method scala/xml/dtd/ELEMENTS$.compose:(Lscala/Function1;)Lscala/Function1;
         7: areturn
      LocalVariableTable:
        Start  Length  Slot  Name   Signature
            0       8     0     g   Lscala/Function1;
    Signature: #45                          // <A$:Ljava/lang/Object;>(Lscala/Function1<TA$;Lscala/xml/dtd/impl/Base$RegExp;>;)Lscala/Function1<TA$;Lscala/xml/dtd/ELEMENTS;>;
    MethodParameters:
      Name                           Flags
      g                              final

  public scala.collection.Iterator<java.lang.String> productElementNames();
    descriptor: ()Lscala/collection/Iterator;
    flags: (0x0001) ACC_PUBLIC
    Code:
      stack=1, locals=1, args_size=1
         0: aload_0
         1: invokestatic  #54                 // InterfaceMethod scala/Product.productElementNames$:(Lscala/Product;)Lscala/collection/Iterator;
         4: areturn
      LineNumberTable:
        line 129: 0
      LocalVariableTable:
        Start  Length  Slot  Name   Signature
            0       5     0  this   Lscala/xml/dtd/ELEMENTS;
    Signature: #50                          // ()Lscala/collection/Iterator<Ljava/lang/String;>;

  public scala.xml.dtd.impl.Base$RegExp r();
    descriptor: ()Lscala/xml/dtd/impl/Base$RegExp;
    flags: (0x0001) ACC_PUBLIC
    Code:
      stack=1, locals=1, args_size=1
         0: aload_0
         1: getfield      #58                 // Field r:Lscala/xml/dtd/impl/Base$RegExp;
         4: areturn
      LineNumberTable:
        line 129: 0
      LocalVariableTable:
        Start  Length  Slot  Name   Signature
            0       5     0  this   Lscala/xml/dtd/ELEMENTS;

  public scala.collection.mutable.StringBuilder buildString(scala.collection.mutable.StringBuilder);
    descriptor: (Lscala/collection/mutable/StringBuilder;)Lscala/collection/mutable/StringBuilder;
    flags: (0x0001) ACC_PUBLIC
    Code:
      stack=3, locals=2, args_size=2
         0: getstatic     #66                 // Field scala/xml/dtd/ContentModel$.MODULE$:Lscala/xml/dtd/ContentModel$;
         3: aload_0
         4: invokevirtual #68                 // Method r:()Lscala/xml/dtd/impl/Base$RegExp;
         7: aload_1
         8: invokevirtual #71                 // Method scala/xml/dtd/ContentModel$.buildString:(Lscala/xml/dtd/impl/Base$RegExp;Lscala/collection/mutable/StringBuilder;)Lscala/collection/mutable/StringBuilder;
        11: areturn
      LineNumberTable:
        line 131: 0
      LocalVariableTable:
        Start  Length  Slot  Name   Signature
            0      12     0  this   Lscala/xml/dtd/ELEMENTS;
            0      12     1    sb   Lscala/collection/mutable/StringBuilder;
    MethodParameters:
      Name                           Flags
      sb                             final

  public scala.xml.dtd.ELEMENTS copy(scala.xml.dtd.impl.Base$RegExp);
    descriptor: (Lscala/xml/dtd/impl/Base$RegExp;)Lscala/xml/dtd/ELEMENTS;
    flags: (0x0001) ACC_PUBLIC
    Code:
      stack=3, locals=2, args_size=2
         0: new           #2                  // class scala/xml/dtd/ELEMENTS
         3: dup
         4: aload_1
         5: invokespecial #77                 // Method "<init>":(Lscala/xml/dtd/impl/Base$RegExp;)V
         8: areturn
      LineNumberTable:
        line 129: 0
      LocalVariableTable:
        Start  Length  Slot  Name   Signature
            0       9     0  this   Lscala/xml/dtd/ELEMENTS;
            0       9     1     r   Lscala/xml/dtd/impl/Base$RegExp;
    MethodParameters:
      Name                           Flags
      r                              final

  public scala.xml.dtd.impl.Base$RegExp copy$default$1();
    descriptor: ()Lscala/xml/dtd/impl/Base$RegExp;
    flags: (0x0001) ACC_PUBLIC
    Code:
      stack=1, locals=1, args_size=1
         0: aload_0
         1: invokevirtual #68                 // Method r:()Lscala/xml/dtd/impl/Base$RegExp;
         4: areturn
      LineNumberTable:
        line 129: 0
      LocalVariableTable:
        Start  Length  Slot  Name   Signature
            0       5     0  this   Lscala/xml/dtd/ELEMENTS;

  public java.lang.String productPrefix();
    descriptor: ()Ljava/lang/String;
    flags: (0x0001) ACC_PUBLIC
    Code:
      stack=1, locals=1, args_size=1
         0: ldc           #82                 // String ELEMENTS
         2: areturn
      LineNumberTable:
        line 129: 0
      LocalVariableTable:
        Start  Length  Slot  Name   Signature
            0       3     0  this   Lscala/xml/dtd/ELEMENTS;

  public int productArity();
    descriptor: ()I
    flags: (0x0001) ACC_PUBLIC
    Code:
      stack=1, locals=1, args_size=1
         0: iconst_1
         1: ireturn
      LineNumberTable:
        line 129: 0
      LocalVariableTable:
        Start  Length  Slot  Name   Signature
            0       2     0  this   Lscala/xml/dtd/ELEMENTS;

  public java.lang.Object productElement(int);
    descriptor: (I)Ljava/lang/Object;
    flags: (0x0001) ACC_PUBLIC
    Code:
      stack=1, locals=3, args_size=2
         0: iload_1
         1: istore_2
         2: iload_2
         3: tableswitch   { // 0 to 0
                       0: 20
                 default: 27
            }
        20: aload_0
        21: invokevirtual #68                 // Method r:()Lscala/xml/dtd/impl/Base$RegExp;
        24: goto          34
        27: iload_1
        28: invokestatic  #92                 // Method scala/runtime/Statics.ioobe:(I)Ljava/lang/Object;
        31: goto          34
        34: areturn
      StackMapTable: number_of_entries = 3
        frame_type = 252 /* append */
          offset_delta = 20
          locals = [ int ]
        frame_type = 6 /* same */
        frame_type = 70 /* same_locals_1_stack_item */
          stack = [ class java/lang/Object ]
      LineNumberTable:
        line 129: 0
      LocalVariableTable:
        Start  Length  Slot  Name   Signature
            0      35     0  this   Lscala/xml/dtd/ELEMENTS;
            0      35     1   x$1   I
    MethodParameters:
      Name                           Flags
      x$1                            final

  public scala.collection.Iterator<java.lang.Object> productIterator();
    descriptor: ()Lscala/collection/Iterator;
    flags: (0x0001) ACC_PUBLIC
    Code:
      stack=2, locals=1, args_size=1
         0: getstatic     #102                // Field scala/runtime/ScalaRunTime$.MODULE$:Lscala/runtime/ScalaRunTime$;
         3: aload_0
         4: invokevirtual #105                // Method scala/runtime/ScalaRunTime$.typedProductIterator:(Lscala/Product;)Lscala/collection/Iterator;
         7: areturn
      LineNumberTable:
        line 129: 0
      LocalVariableTable:
        Start  Length  Slot  Name   Signature
            0       8     0  this   Lscala/xml/dtd/ELEMENTS;
    Signature: #97                          // ()Lscala/collection/Iterator<Ljava/lang/Object;>;

  public boolean canEqual(java.lang.Object);
    descriptor: (Ljava/lang/Object;)Z
    flags: (0x0001) ACC_PUBLIC
    Code:
      stack=1, locals=2, args_size=2
         0: aload_1
         1: instanceof    #2                  // class scala/xml/dtd/ELEMENTS
         4: ireturn
      LineNumberTable:
        line 129: 0
      LocalVariableTable:
        Start  Length  Slot  Name   Signature
            0       5     0  this   Lscala/xml/dtd/ELEMENTS;
            0       5     1   x$1   Ljava/lang/Object;
    MethodParameters:
      Name                           Flags
      x$1                            final

  public java.lang.String productElementName(int);
    descriptor: (I)Ljava/lang/String;
    flags: (0x0001) ACC_PUBLIC
    Code:
      stack=1, locals=3, args_size=2
         0: iload_1
         1: istore_2
         2: iload_2
         3: tableswitch   { // 0 to 0
                       0: 20
                 default: 25
            }
        20: ldc           #111                // String r
        22: goto          35
        25: iload_1
        26: invokestatic  #92                 // Method scala/runtime/Statics.ioobe:(I)Ljava/lang/Object;
        29: checkcast     #113                // class java/lang/String
        32: goto          35
        35: areturn
      StackMapTable: number_of_entries = 3
        frame_type = 252 /* append */
          offset_delta = 20
          locals = [ int ]
        frame_type = 4 /* same */
        frame_type = 73 /* same_locals_1_stack_item */
          stack = [ class java/lang/String ]
      LineNumberTable:
        line 129: 0
      LocalVariableTable:
        Start  Length  Slot  Name   Signature
            0      36     0  this   Lscala/xml/dtd/ELEMENTS;
            0      36     1   x$1   I
    MethodParameters:
      Name                           Flags
      x$1                            final

  public int hashCode();
    descriptor: ()I
    flags: (0x0001) ACC_PUBLIC
    Code:
      stack=2, locals=1, args_size=1
         0: getstatic     #102                // Field scala/runtime/ScalaRunTime$.MODULE$:Lscala/runtime/ScalaRunTime$;
         3: aload_0
         4: invokevirtual #118                // Method scala/runtime/ScalaRunTime$._hashCode:(Lscala/Product;)I
         7: ireturn
      LineNumberTable:
        line 129: 0
      LocalVariableTable:
        Start  Length  Slot  Name   Signature
            0       8     0  this   Lscala/xml/dtd/ELEMENTS;

  public boolean equals(java.lang.Object);
    descriptor: (Ljava/lang/Object;)Z
    flags: (0x0001) ACC_PUBLIC
    Code:
      stack=2, locals=6, args_size=2
         0: aload_0
         1: aload_1
         2: if_acmpeq     86
         5: aload_1
         6: astore_3
         7: aload_3
         8: instanceof    #2                  // class scala/xml/dtd/ELEMENTS
        11: ifeq          19
        14: iconst_1
        15: istore_2
        16: goto          27
        19: goto          22
        22: iconst_0
        23: istore_2
        24: goto          27
        27: iload_2
        28: ifeq          90
        31: aload_1
        32: checkcast     #2                  // class scala/xml/dtd/ELEMENTS
        35: astore        4
        37: aload_0
        38: invokevirtual #68                 // Method r:()Lscala/xml/dtd/impl/Base$RegExp;
        41: aload         4
        43: invokevirtual #68                 // Method r:()Lscala/xml/dtd/impl/Base$RegExp;
        46: astore        5
        48: dup
        49: ifnonnull     61
        52: pop
        53: aload         5
        55: ifnull        69
        58: goto          82
        61: aload         5
        63: invokevirtual #121                // Method java/lang/Object.equals:(Ljava/lang/Object;)Z
        66: ifeq          82
        69: aload         4
        71: aload_0
        72: invokevirtual #123                // Method canEqual:(Ljava/lang/Object;)Z
        75: ifeq          82
        78: iconst_1
        79: goto          83
        82: iconst_0
        83: ifeq          90
        86: iconst_1
        87: goto          91
        90: iconst_0
        91: ireturn
      StackMapTable: number_of_entries = 10
        frame_type = 253 /* append */
          offset_delta = 19
          locals = [ top, class java/lang/Object ]
        frame_type = 2 /* same */
        frame_type = 255 /* full_frame */
          offset_delta = 4
          locals = [ class scala/xml/dtd/ELEMENTS, class java/lang/Object, int, class java/lang/Object ]
          stack = []
        frame_type = 255 /* full_frame */
          offset_delta = 33
          locals = [ class scala/xml/dtd/ELEMENTS, class java/lang/Object, int, class java/lang/Object, class scala/xml/dtd/ELEMENTS, class scala/xml/dtd/impl/Base$RegExp ]
          stack = [ class scala/xml/dtd/impl/Base$RegExp ]
        frame_type = 7 /* same */
        frame_type = 12 /* same */
        frame_type = 64 /* same_locals_1_stack_item */
          stack = [ int ]
        frame_type = 255 /* full_frame */
          offset_delta = 2
          locals = [ class scala/xml/dtd/ELEMENTS, class java/lang/Object ]
          stack = []
        frame_type = 253 /* append */
          offset_delta = 3
          locals = [ int, class java/lang/Object ]
        frame_type = 255 /* full_frame */
          offset_delta = 0
          locals = [ class scala/xml/dtd/ELEMENTS, class java/lang/Object ]
          stack = [ int ]
      LineNumberTable:
        line 129: 0
      LocalVariableTable:
        Start  Length  Slot  Name   Signature
            0      92     0  this   Lscala/xml/dtd/ELEMENTS;
            0      92     1   x$1   Ljava/lang/Object;
    MethodParameters:
      Name                           Flags
      x$1                            final

  public scala.xml.dtd.ELEMENTS(scala.xml.dtd.impl.Base$RegExp);
    descriptor: (Lscala/xml/dtd/impl/Base$RegExp;)V
    flags: (0x0001) ACC_PUBLIC
    Code:
      stack=2, locals=2, args_size=2
         0: aload_0
         1: aload_1
         2: putfield      #58                 // Field r:Lscala/xml/dtd/impl/Base$RegExp;
         5: aload_0
         6: invokespecial #126                // Method scala/xml/dtd/DFAContentModel."<init>":()V
         9: aload_0
        10: invokestatic  #130                // InterfaceMethod scala/Product.$init$:(Lscala/Product;)V
        13: return
      LineNumberTable:
        line 129: 0
      LocalVariableTable:
        Start  Length  Slot  Name   Signature
            0      14     0  this   Lscala/xml/dtd/ELEMENTS;
            0      14     1     r   Lscala/xml/dtd/impl/Base$RegExp;
    MethodParameters:
      Name                           Flags
      r                              final
}
InnerClasses:
  public abstract #17= #14 of #16;        // RegExp=class scala/xml/dtd/impl/Base$RegExp of class scala/xml/dtd/impl/Base
SourceFile: "ContentModel.scala"
RuntimeVisibleAnnotations:
  0: #10(#11=s#12)
    scala.reflect.ScalaSignature(
      bytes="\u0006\u0005\u0005=c\u0001\u0002\f\u0018\u0001zA\u0001b\r\u0001\u0003\u0016\u0004%\t\u0001\u000e\u0005\t\u007f\u0001\u0011\t\u0012)A\u0005k!)\u0001\t\u0001C\u0001\u0003\")A\t\u0001C!\u000b\"9A\nAA\u0001\n\u0003i\u0005bB(\u0001#\u0003%\t\u0001\u0015\u0005\b7\u0002\t\t\u0011\"\u0011]\u0011\u001d)\u0007!!A\u0005\u0002\u0019DqA\u001b\u0001\u0002\u0002\u0013\u00051\u000eC\u0004r\u0001\u0005\u0005I\u0011\t:\t\u000fe\u0004\u0011\u0011!C\u0001u\"Aq\u0010AA\u0001\n\u0003\n\t\u0001C\u0005\u0002\u0006\u0001\t\t\u0011\"\u0011\u0002\b!I\u0011\u0011\u0002\u0001\u0002\u0002\u0013\u0005\u00131B\u0004\n\u0003\u001f9\u0012\u0011!E\u0001\u0003#1\u0001BF\f\u0002\u0002#\u0005\u00111\u0003\u0005\u0007\u0001B!\t!a\u000b\t\u0013\u00055\u0002#!A\u0005F\u0005=\u0002\"CA\u0019!\u0005\u0005I\u0011QA\u001a\u0011%\t9\u0004EA\u0001\n\u0003\u000bI\u0004C\u0005\u0002FA\t\t\u0011\"\u0003\u0002H\tAQ\tT#N\u000b:#6K\u0003\u0002\u00193\u0005\u0019A\r\u001e3\u000b\u0005iY\u0012a\u0001=nY*\tA$A\u0003tG\u0006d\u0017m\u0001\u0001\u0014\t\u0001y2e\n\t\u0003A\u0005j\u0011aF\u0005\u0003E]\u0011q\u0002\u0012$B\u0007>tG/\u001a8u\u001b>$W\r\u001c\t\u0003I\u0015j\u0011aG\u0005\u0003Mm\u0011q\u0001\u0015:pIV\u001cG\u000f\u0005\u0002)a9\u0011\u0011F\f\b\u0003U5j\u0011a\u000b\u0006\u0003Yu\ta\u0001\u0010:p_Rt\u0014\"\u0001\u000f\n\u0005=Z\u0012a\u00029bG.\fw-Z\u0005\u0003cI\u0012AbU3sS\u0006d\u0017N_1cY\u0016T!aL\u000e\u0002\u0003I,\u0012!\u000e\t\u0003mer!\u0001I\u001c\n\u0005a:\u0012\u0001D\"p]R,g\u000e^\'pI\u0016d\u0017B\u0001\u001e<\u0005\u0019\u0011VmZ#ya&\u0011A(\u0010\u0002\u0005\u0005\u0006\u001cXM\u0003\u0002?/\u0005!\u0011.\u001c9m\u0003\t\u0011\b%\u0001\u0004=S:LGO\u0010\u000b\u0003\u0005\u000e\u0003\"\u0001\t\u0001\t\u000bM\u001a\u0001\u0019A\u001b\u0002\u0017\t,\u0018\u000e\u001c3TiJLgn\u001a\u000b\u0003\r*\u0003\"a\u0012%\u000f\u0005\u0011r\u0013BA%3\u00055\u0019FO]5oO\n+\u0018\u000e\u001c3fe\")1\n\u0002a\u0001\r\u0006\u00111OY\u0001\u0005G>\u0004\u0018\u0010\u0006\u0002C\u001d\"91\'\u0002I\u0001\u0002\u0004)\u0014AD2paf$C-\u001a4bk2$H%M\u000b\u0002#*\u0012QGU\u0016\u0002\'B\u0011A+W\u0007\u0002+*\u0011akV\u0001\nk:\u001c\u0007.Z2lK\u0012T!\u0001W\u000e\u0002\u0015\u0005tgn\u001c;bi&|g.\u0003\u0002[+\n\tRO\\2iK\u000e\\W\r\u001a,be&\fgnY3\u0002\u001bA\u0014x\u000eZ;diB\u0013XMZ5y+\u0005i\u0006C\u00010d\u001b\u0005y&B\u00011b\u0003\u0011a\u0017M\\4\u000b\u0003\t\fAA[1wC&\u0011Am\u0018\u0002\u0007\'R\u0014\u0018N\\4\u0002\u0019A\u0014x\u000eZ;di\u0006\u0013\u0018\u000e^=\u0016\u0003\u001d\u0004\"\u0001\n5\n\u0005%\\\"aA%oi\u0006q\u0001O]8ek\u000e$X\t\\3nK:$HC\u00017p!\t!S.\u0003\u0002o7\t\u0019\u0011I\\=\t\u000fAL\u0011\u0011!a\u0001O\u0006\u0019\u0001\u0010J\u0019\u0002\u001fA\u0014x\u000eZ;di&#XM]1u_J,\u0012a\u001d\t\u0004i^dW\"A;\u000b\u0005Y\\\u0012AC2pY2,7\r^5p]&\u0011\u00010\u001e\u0002\t\u0013R,\'/\u0019;pe\u0006A1-\u00198FcV\fG\u000e\u0006\u0002|}B\u0011A\u0005`\u0005\u0003{n\u0011qAQ8pY\u0016\fg\u000eC\u0004q\u0017\u0005\u0005\t\u0019\u00017\u0002%A\u0014x\u000eZ;di\u0016cW-\\3oi:\u000bW.\u001a\u000b\u0004;\u0006\r\u0001b\u00029\r\u0003\u0003\u0005\raZ\u0001\tQ\u0006\u001c\bnQ8eKR\tq-\u0001\u0004fcV\fGn\u001d\u000b\u0004w\u00065\u0001b\u00029\u000f\u0003\u0003\u0005\r\u0001\\\u0001\t\u000b2+U*\u0012(U\'B\u0011\u0001\u0005E\n\u0006!\u0005U\u0011\u0011\u0005\t\u0007\u0003/\ti\"\u000e\"\u000e\u0005\u0005e!bAA\u000e7\u00059!/\u001e8uS6,\u0017\u0002BA\u0010\u00033\u0011\u0011#\u00112tiJ\f7\r\u001e$v]\u000e$\u0018n\u001c82!\u0011\t\u0019#!\u000b\u000e\u0005\u0005\u0015\"bAA\u0014C\u0006\u0011\u0011n\\\u0005\u0004c\u0005\u0015BCAA\t\u0003!!xn\u0015;sS:<G#A/\u0002\u000b\u0005\u0004\b\u000f\\=\u0015\u0007\t\u000b)\u0004C\u00034\'\u0001\u0007Q\'A\u0004v]\u0006\u0004\b\u000f\\=\u0015\t\u0005m\u0012\u0011\t\t\u0005I\u0005uR\'C\u0002\u0002@m\u0011aa\u00149uS>t\u0007\u0002CA\")\u0005\u0005\t\u0019\u0001\"\u0002\u0007a$\u0003\'\u0001\u0007xe&$XMU3qY\u0006\u001cW\r\u0006\u0002\u0002JA\u0019a,a\u0013\n\u0007\u00055sL\u0001\u0004PE*,7\r\u001e"
    )
  ScalaInlineInfo: length = 0x4A (unknown attribute)
   01 00 00 0E 00 4A 00 4B 00 00 3B 00 3C 00 00 6A
   00 6B 00 00 49 00 22 00 00 4E 00 38 00 00 77 00
   6B 00 00 72 00 54 00 00 53 00 54 00 00 55 00 56
   00 00 6D 00 6E 00 00 30 00 31 00 00 60 00 31 00
   00 4F 00 50 00 00 12 00 38 00
  ScalaSig: length = 0x3 (unknown attribute)
   05 02 00
