Classfile /Users/mw/Projects/slang-braindump/.jar/jar11/assemble/slang-braindump/assemble/content/scala/xml/dtd/EntityDef.class
  Last modified May 29, 2022; size 806 bytes
  SHA-256 checksum 58eb798463082e2dc6bce5e1851c7f16335aebe438742877caa1a6fb6c15363d
  Compiled from "Decl.scala"
public abstract class scala.xml.dtd.EntityDef
  minor version: 0
  major version: 52
  flags: (0x0421) ACC_PUBLIC, ACC_SUPER, ACC_ABSTRACT
  this_class: #2                          // scala/xml/dtd/EntityDef
  super_class: #4                         // java/lang/Object
  interfaces: 0, fields: 0, methods: 2, attributes: 4
Constant pool:
   #1 = Utf8               scala/xml/dtd/EntityDef
   #2 = Class              #1             // scala/xml/dtd/EntityDef
   #3 = Utf8               java/lang/Object
   #4 = Class              #3             // java/lang/Object
   #5 = Utf8               Decl.scala
   #6 = Utf8               Lscala/reflect/ScalaSignature;
   #7 = Utf8               bytes
   #8 = Utf8               \u0006\u0005\u00112Qa\u0001\u0003\u0002\"-AQ\u0001\u0005\u0001\u0005\u0002EAQ\u0001\u0006\u0001\u0007\u0002U\u0011\u0011\"\u00128uSRLH)\u001a4\u000b\u0005\u00151\u0011a\u00013uI*\u0011q\u0001C\u0001\u0004q6d\'\"A\u0005\u0002\u000bM\u001c\u0017\r\\1\u0004\u0001M\u0011\u0001\u0001\u0004\t\u0003\u001b9i\u0011\u0001C\u0005\u0003\u001f!\u0011a!\u00118z%\u00164\u0017A\u0002\u001fj]&$h\bF\u0001\u0013!\t\u0019\u0002!D\u0001\u0005\u0003-\u0011W/\u001b7e\'R\u0014\u0018N\\4\u0015\u0005Yi\u0002CA\f\u001b\u001d\ti\u0001$\u0003\u0002\u001a\u0011\u00059\u0001/Y2lC\u001e,\u0017BA\u000e\u001d\u00055\u0019FO]5oO\n+\u0018\u000e\u001c3fe*\u0011\u0011\u0004\u0003\u0005\u0006=\t\u0001\rAF\u0001\u0003g\nL3\u0001\u0001\u0011#\u0013\t\tCA\u0001\u0004FqR$UMZ\u0005\u0003G\u0011\u0011a!\u00138u\t\u00164\u0007
   #9 = Utf8               buildString
  #10 = Utf8               (Lscala/collection/mutable/StringBuilder;)Lscala/collection/mutable/StringBuilder;
  #11 = Utf8               sb
  #12 = Utf8               <init>
  #13 = Utf8               ()V
  #14 = NameAndType        #12:#13        // "<init>":()V
  #15 = Methodref          #4.#14         // java/lang/Object."<init>":()V
  #16 = Utf8               this
  #17 = Utf8               Lscala/xml/dtd/EntityDef;
  #18 = Utf8               MethodParameters
  #19 = Utf8               Code
  #20 = Utf8               LineNumberTable
  #21 = Utf8               LocalVariableTable
  #22 = Utf8               SourceFile
  #23 = Utf8               RuntimeVisibleAnnotations
  #24 = Utf8               ScalaInlineInfo
  #25 = Utf8               ScalaSig
{
  public abstract scala.collection.mutable.StringBuilder buildString(scala.collection.mutable.StringBuilder);
    descriptor: (Lscala/collection/mutable/StringBuilder;)Lscala/collection/mutable/StringBuilder;
    flags: (0x0401) ACC_PUBLIC, ACC_ABSTRACT
    MethodParameters:
      Name                           Flags
      sb                             final

  public scala.xml.dtd.EntityDef();
    descriptor: ()V
    flags: (0x0001) ACC_PUBLIC
    Code:
      stack=1, locals=1, args_size=1
         0: aload_0
         1: invokespecial #15                 // Method java/lang/Object."<init>":()V
         4: return
      LineNumberTable:
        line 110: 0
        line 106: 4
      LocalVariableTable:
        Start  Length  Slot  Name   Signature
            0       5     0  this   Lscala/xml/dtd/EntityDef;
}
SourceFile: "Decl.scala"
RuntimeVisibleAnnotations:
  0: #6(#7=s#8)
    scala.reflect.ScalaSignature(
      bytes="\u0006\u0005\u00112Qa\u0001\u0003\u0002\"-AQ\u0001\u0005\u0001\u0005\u0002EAQ\u0001\u0006\u0001\u0007\u0002U\u0011\u0011\"\u00128uSRLH)\u001a4\u000b\u0005\u00151\u0011a\u00013uI*\u0011q\u0001C\u0001\u0004q6d\'\"A\u0005\u0002\u000bM\u001c\u0017\r\\1\u0004\u0001M\u0011\u0001\u0001\u0004\t\u0003\u001b9i\u0011\u0001C\u0005\u0003\u001f!\u0011a!\u00118z%\u00164\u0017A\u0002\u001fj]&$h\bF\u0001\u0013!\t\u0019\u0002!D\u0001\u0005\u0003-\u0011W/\u001b7e\'R\u0014\u0018N\\4\u0015\u0005Yi\u0002CA\f\u001b\u001d\ti\u0001$\u0003\u0002\u001a\u0011\u00059\u0001/Y2lC\u001e,\u0017BA\u000e\u001d\u00055\u0019FO]5oO\n+\u0018\u000e\u001c3fe*\u0011\u0011\u0004\u0003\u0005\u0006=\t\u0001\rAF\u0001\u0003g\nL3\u0001\u0001\u0011#\u0013\t\tCA\u0001\u0004FqR$UMZ\u0005\u0003G\u0011\u0011a!\u00138u\t\u00164\u0007"
    )
  ScalaInlineInfo: length = 0xE (unknown attribute)
   01 00 00 02 00 0C 00 0D 00 00 09 00 0A 00
  ScalaSig: length = 0x3 (unknown attribute)
   05 02 00
