Classfile /Users/mw/Projects/slang-braindump/.jar/jar11/assemble/slang-braindump/assemble/content/scala/xml/dtd/IMPLIED.class
  Last modified May 29, 2022; size 2255 bytes
  SHA-256 checksum 9ecf6a3aa4faeee79f737b493a382324d5c09569ff0ac202e0fe5b4b0774fd4f
  Compiled from "Decl.scala"
public final class scala.xml.dtd.IMPLIED
  minor version: 0
  major version: 52
  flags: (0x0031) ACC_PUBLIC, ACC_FINAL, ACC_SUPER
  this_class: #2                          // scala/xml/dtd/IMPLIED
  super_class: #4                         // java/lang/Object
  interfaces: 0, fields: 0, methods: 10, attributes: 3
Constant pool:
   #1 = Utf8               scala/xml/dtd/IMPLIED
   #2 = Class              #1             // scala/xml/dtd/IMPLIED
   #3 = Utf8               java/lang/Object
   #4 = Class              #3             // java/lang/Object
   #5 = Utf8               Decl.scala
   #6 = Utf8               Lscala/reflect/ScalaSignature;
   #7 = Utf8               bytes
   #8 = Utf8               \u0006\u00059<Q\u0001D\u0007\t\u0002R1QAF\u0007\t\u0002^AQaK\u0001\u0005\u00021BQ!L\u0001\u0005B9BQaN\u0001\u0005BaBqAR\u0001\u0002\u0002\u0013\u0005s\tC\u0004P\u0003\u0005\u0005I\u0011\u0001)\t\u000fQ\u000b\u0011\u0011!C\u0001+\"91,AA\u0001\n\u0003b\u0006bB1\u0002\u0003\u0003%\tA\u0019\u0005\bO\u0006\t\t\u0011\"\u0011i\u0011\u001dI\u0017!!A\u0005\n)\fq!S\'Q\u0019&+EI\u0003\u0002\u000f\u001f\u0005\u0019A\r\u001e3\u000b\u0005A\t\u0012a\u0001=nY*\t!#A\u0003tG\u0006d\u0017m\u0001\u0001\u0011\u0005U\tQ\"A\u0007\u0003\u000f%k\u0005\u000bT%F\tN!\u0011\u0001G\u000e !\t)\u0012$\u0003\u0002\u001b\u001b\tYA)\u001a4bk2$H)Z2m!\taR$D\u0001\u0012\u0013\tq\u0012CA\u0004Qe>$Wo\u0019;\u0011\u0005\u0001BcBA\u0011\'\u001d\t\u0011S%D\u0001$\u0015\t!3#\u0001\u0004=e>|GOP\u0005\u0002%%\u0011q%E\u0001\ba\u0006\u001c7.Y4f\u0013\tI#F\u0001\u0007TKJL\u0017\r\\5{C\ndWM\u0003\u0002(#\u00051A(\u001b8jiz\"\u0012\u0001F\u0001\ti>\u001cFO]5oOR\tq\u0006\u0005\u00021i9\u0011\u0011G\r\t\u0003EEI!aM\t\u0002\rA\u0013X\rZ3g\u0013\t)dG\u0001\u0004TiJLgn\u001a\u0006\u0003gE\t1BY;jY\u0012\u001cFO]5oOR\u0011\u0011(\u0011\t\u0003u}j\u0011a\u000f\u0006\u0003yu\nq!\\;uC\ndWM\u0003\u0002?#\u0005Q1m\u001c7mK\u000e$\u0018n\u001c8\n\u0005\u0001[$!D*ue&twMQ;jY\u0012,\'\u000fC\u0003C\t\u0001\u00071)\u0001\u0002tEB\u0011A)\u0012\b\u00039\u0019J!\u0001\u0011\u0016\u0002\u001bA\u0014x\u000eZ;diB\u0013XMZ5y+\u0005A\u0005CA%O\u001b\u0005Q%BA&M\u0003\u0011a\u0017M\\4\u000b\u00035\u000bAA[1wC&\u0011QGS\u0001\raJ|G-^2u\u0003JLG/_\u000b\u0002#B\u0011ADU\u0005\u0003\'F\u00111!\u00138u\u00039\u0001(o\u001c3vGR,E.Z7f]R$\"AV-\u0011\u0005q9\u0016B\u0001-\u0012\u0005\r\te.\u001f\u0005\b5\u001e\t\t\u00111\u0001R\u0003\rAH%M\u0001\u0010aJ|G-^2u\u0013R,\'/\u0019;peV\tQ\fE\u0002_?Zk\u0011!P\u0005\u0003Av\u0012\u0001\"\u0013;fe\u0006$xN]\u0001\tG\u0006tW)];bYR\u00111M\u001a\t\u00039\u0011L!!Z\t\u0003\u000f\t{w\u000e\\3b]\"9!,CA\u0001\u0002\u00041\u0016\u0001\u00035bg\"\u001cu\u000eZ3\u0015\u0003E\u000bAb\u001e:ji\u0016\u0014V\r\u001d7bG\u0016$\u0012a\u001b\t\u0003\u00132L!!\u001c&\u0003\r=\u0013\'.Z2u\u0001
   #9 = Utf8               hashCode
  #10 = Utf8               ()I
  #11 = Utf8               scala/xml/dtd/IMPLIED$
  #12 = Class              #11            // scala/xml/dtd/IMPLIED$
  #13 = Utf8               MODULE$
  #14 = Utf8               Lscala/xml/dtd/IMPLIED$;
  #15 = NameAndType        #13:#14        // MODULE$:Lscala/xml/dtd/IMPLIED$;
  #16 = Fieldref           #12.#15        // scala/xml/dtd/IMPLIED$.MODULE$:Lscala/xml/dtd/IMPLIED$;
  #17 = NameAndType        #9:#10         // hashCode:()I
  #18 = Methodref          #12.#17        // scala/xml/dtd/IMPLIED$.hashCode:()I
  #19 = Utf8               canEqual
  #20 = Utf8               (Ljava/lang/Object;)Z
  #21 = Utf8               x$1
  #22 = NameAndType        #19:#20        // canEqual:(Ljava/lang/Object;)Z
  #23 = Methodref          #12.#22        // scala/xml/dtd/IMPLIED$.canEqual:(Ljava/lang/Object;)Z
  #24 = Utf8               Ljava/lang/Object;
  #25 = Utf8               productIterator
  #26 = Utf8               ()Lscala/collection/Iterator;
  #27 = Utf8               ()Lscala/collection/Iterator<Ljava/lang/Object;>;
  #28 = NameAndType        #25:#26        // productIterator:()Lscala/collection/Iterator;
  #29 = Methodref          #12.#28        // scala/xml/dtd/IMPLIED$.productIterator:()Lscala/collection/Iterator;
  #30 = Utf8               productElement
  #31 = Utf8               (I)Ljava/lang/Object;
  #32 = NameAndType        #30:#31        // productElement:(I)Ljava/lang/Object;
  #33 = Methodref          #12.#32        // scala/xml/dtd/IMPLIED$.productElement:(I)Ljava/lang/Object;
  #34 = Utf8               I
  #35 = Utf8               productArity
  #36 = NameAndType        #35:#10        // productArity:()I
  #37 = Methodref          #12.#36        // scala/xml/dtd/IMPLIED$.productArity:()I
  #38 = Utf8               productPrefix
  #39 = Utf8               ()Ljava/lang/String;
  #40 = NameAndType        #38:#39        // productPrefix:()Ljava/lang/String;
  #41 = Methodref          #12.#40        // scala/xml/dtd/IMPLIED$.productPrefix:()Ljava/lang/String;
  #42 = Utf8               buildString
  #43 = Utf8               (Lscala/collection/mutable/StringBuilder;)Lscala/collection/mutable/StringBuilder;
  #44 = Utf8               sb
  #45 = NameAndType        #42:#43        // buildString:(Lscala/collection/mutable/StringBuilder;)Lscala/collection/mutable/StringBuilder;
  #46 = Methodref          #12.#45        // scala/xml/dtd/IMPLIED$.buildString:(Lscala/collection/mutable/StringBuilder;)Lscala/collection/mutable/StringBuilder;
  #47 = Utf8               Lscala/collection/mutable/StringBuilder;
  #48 = Utf8               toString
  #49 = NameAndType        #48:#39        // toString:()Ljava/lang/String;
  #50 = Methodref          #12.#49        // scala/xml/dtd/IMPLIED$.toString:()Ljava/lang/String;
  #51 = Utf8               productElementNames
  #52 = Utf8               ()Lscala/collection/Iterator<Ljava/lang/String;>;
  #53 = NameAndType        #51:#26        // productElementNames:()Lscala/collection/Iterator;
  #54 = Methodref          #12.#53        // scala/xml/dtd/IMPLIED$.productElementNames:()Lscala/collection/Iterator;
  #55 = Utf8               productElementName
  #56 = Utf8               (I)Ljava/lang/String;
  #57 = Utf8               n
  #58 = NameAndType        #55:#56        // productElementName:(I)Ljava/lang/String;
  #59 = Methodref          #12.#58        // scala/xml/dtd/IMPLIED$.productElementName:(I)Ljava/lang/String;
  #60 = Utf8               Code
  #61 = Utf8               LocalVariableTable
  #62 = Utf8               MethodParameters
  #63 = Utf8               Signature
  #64 = Utf8               SourceFile
  #65 = Utf8               RuntimeVisibleAnnotations
  #66 = Utf8               ScalaSig
{
  public static int hashCode();
    descriptor: ()I
    flags: (0x0009) ACC_PUBLIC, ACC_STATIC
    Code:
      stack=1, locals=0, args_size=0
         0: getstatic     #16                 // Field scala/xml/dtd/IMPLIED$.MODULE$:Lscala/xml/dtd/IMPLIED$;
         3: invokevirtual #18                 // Method scala/xml/dtd/IMPLIED$.hashCode:()I
         6: ireturn

  public static boolean canEqual(java.lang.Object);
    descriptor: (Ljava/lang/Object;)Z
    flags: (0x0009) ACC_PUBLIC, ACC_STATIC
    Code:
      stack=2, locals=1, args_size=1
         0: getstatic     #16                 // Field scala/xml/dtd/IMPLIED$.MODULE$:Lscala/xml/dtd/IMPLIED$;
         3: aload_0
         4: invokevirtual #23                 // Method scala/xml/dtd/IMPLIED$.canEqual:(Ljava/lang/Object;)Z
         7: ireturn
      LocalVariableTable:
        Start  Length  Slot  Name   Signature
            0       8     0   x$1   Ljava/lang/Object;
    MethodParameters:
      Name                           Flags
      x$1                            final

  public static scala.collection.Iterator<java.lang.Object> productIterator();
    descriptor: ()Lscala/collection/Iterator;
    flags: (0x0009) ACC_PUBLIC, ACC_STATIC
    Code:
      stack=1, locals=0, args_size=0
         0: getstatic     #16                 // Field scala/xml/dtd/IMPLIED$.MODULE$:Lscala/xml/dtd/IMPLIED$;
         3: invokevirtual #29                 // Method scala/xml/dtd/IMPLIED$.productIterator:()Lscala/collection/Iterator;
         6: areturn
    Signature: #27                          // ()Lscala/collection/Iterator<Ljava/lang/Object;>;

  public static java.lang.Object productElement(int);
    descriptor: (I)Ljava/lang/Object;
    flags: (0x0009) ACC_PUBLIC, ACC_STATIC
    Code:
      stack=2, locals=1, args_size=1
         0: getstatic     #16                 // Field scala/xml/dtd/IMPLIED$.MODULE$:Lscala/xml/dtd/IMPLIED$;
         3: iload_0
         4: invokevirtual #33                 // Method scala/xml/dtd/IMPLIED$.productElement:(I)Ljava/lang/Object;
         7: areturn
      LocalVariableTable:
        Start  Length  Slot  Name   Signature
            0       8     0   x$1   I
    MethodParameters:
      Name                           Flags
      x$1                            final

  public static int productArity();
    descriptor: ()I
    flags: (0x0009) ACC_PUBLIC, ACC_STATIC
    Code:
      stack=1, locals=0, args_size=0
         0: getstatic     #16                 // Field scala/xml/dtd/IMPLIED$.MODULE$:Lscala/xml/dtd/IMPLIED$;
         3: invokevirtual #37                 // Method scala/xml/dtd/IMPLIED$.productArity:()I
         6: ireturn

  public static java.lang.String productPrefix();
    descriptor: ()Ljava/lang/String;
    flags: (0x0009) ACC_PUBLIC, ACC_STATIC
    Code:
      stack=1, locals=0, args_size=0
         0: getstatic     #16                 // Field scala/xml/dtd/IMPLIED$.MODULE$:Lscala/xml/dtd/IMPLIED$;
         3: invokevirtual #41                 // Method scala/xml/dtd/IMPLIED$.productPrefix:()Ljava/lang/String;
         6: areturn

  public static scala.collection.mutable.StringBuilder buildString(scala.collection.mutable.StringBuilder);
    descriptor: (Lscala/collection/mutable/StringBuilder;)Lscala/collection/mutable/StringBuilder;
    flags: (0x0009) ACC_PUBLIC, ACC_STATIC
    Code:
      stack=2, locals=1, args_size=1
         0: getstatic     #16                 // Field scala/xml/dtd/IMPLIED$.MODULE$:Lscala/xml/dtd/IMPLIED$;
         3: aload_0
         4: invokevirtual #46                 // Method scala/xml/dtd/IMPLIED$.buildString:(Lscala/collection/mutable/StringBuilder;)Lscala/collection/mutable/StringBuilder;
         7: areturn
      LocalVariableTable:
        Start  Length  Slot  Name   Signature
            0       8     0    sb   Lscala/collection/mutable/StringBuilder;
    MethodParameters:
      Name                           Flags
      sb                             final

  public static java.lang.String toString();
    descriptor: ()Ljava/lang/String;
    flags: (0x0009) ACC_PUBLIC, ACC_STATIC
    Code:
      stack=1, locals=0, args_size=0
         0: getstatic     #16                 // Field scala/xml/dtd/IMPLIED$.MODULE$:Lscala/xml/dtd/IMPLIED$;
         3: invokevirtual #50                 // Method scala/xml/dtd/IMPLIED$.toString:()Ljava/lang/String;
         6: areturn

  public static scala.collection.Iterator<java.lang.String> productElementNames();
    descriptor: ()Lscala/collection/Iterator;
    flags: (0x0009) ACC_PUBLIC, ACC_STATIC
    Code:
      stack=1, locals=0, args_size=0
         0: getstatic     #16                 // Field scala/xml/dtd/IMPLIED$.MODULE$:Lscala/xml/dtd/IMPLIED$;
         3: invokevirtual #54                 // Method scala/xml/dtd/IMPLIED$.productElementNames:()Lscala/collection/Iterator;
         6: areturn
    Signature: #52                          // ()Lscala/collection/Iterator<Ljava/lang/String;>;

  public static java.lang.String productElementName(int);
    descriptor: (I)Ljava/lang/String;
    flags: (0x0009) ACC_PUBLIC, ACC_STATIC
    Code:
      stack=2, locals=1, args_size=1
         0: getstatic     #16                 // Field scala/xml/dtd/IMPLIED$.MODULE$:Lscala/xml/dtd/IMPLIED$;
         3: iload_0
         4: invokevirtual #59                 // Method scala/xml/dtd/IMPLIED$.productElementName:(I)Ljava/lang/String;
         7: areturn
      LocalVariableTable:
        Start  Length  Slot  Name   Signature
            0       8     0     n   I
    MethodParameters:
      Name                           Flags
      n                              final
}
SourceFile: "Decl.scala"
RuntimeVisibleAnnotations:
  0: #6(#7=s#8)
    scala.reflect.ScalaSignature(
      bytes="\u0006\u00059<Q\u0001D\u0007\t\u0002R1QAF\u0007\t\u0002^AQaK\u0001\u0005\u00021BQ!L\u0001\u0005B9BQaN\u0001\u0005BaBqAR\u0001\u0002\u0002\u0013\u0005s\tC\u0004P\u0003\u0005\u0005I\u0011\u0001)\t\u000fQ\u000b\u0011\u0011!C\u0001+\"91,AA\u0001\n\u0003b\u0006bB1\u0002\u0003\u0003%\tA\u0019\u0005\bO\u0006\t\t\u0011\"\u0011i\u0011\u001dI\u0017!!A\u0005\n)\fq!S\'Q\u0019&+EI\u0003\u0002\u000f\u001f\u0005\u0019A\r\u001e3\u000b\u0005A\t\u0012a\u0001=nY*\t!#A\u0003tG\u0006d\u0017m\u0001\u0001\u0011\u0005U\tQ\"A\u0007\u0003\u000f%k\u0005\u000bT%F\tN!\u0011\u0001G\u000e !\t)\u0012$\u0003\u0002\u001b\u001b\tYA)\u001a4bk2$H)Z2m!\taR$D\u0001\u0012\u0013\tq\u0012CA\u0004Qe>$Wo\u0019;\u0011\u0005\u0001BcBA\u0011\'\u001d\t\u0011S%D\u0001$\u0015\t!3#\u0001\u0004=e>|GOP\u0005\u0002%%\u0011q%E\u0001\ba\u0006\u001c7.Y4f\u0013\tI#F\u0001\u0007TKJL\u0017\r\\5{C\ndWM\u0003\u0002(#\u00051A(\u001b8jiz\"\u0012\u0001F\u0001\ti>\u001cFO]5oOR\tq\u0006\u0005\u00021i9\u0011\u0011G\r\t\u0003EEI!aM\t\u0002\rA\u0013X\rZ3g\u0013\t)dG\u0001\u0004TiJLgn\u001a\u0006\u0003gE\t1BY;jY\u0012\u001cFO]5oOR\u0011\u0011(\u0011\t\u0003u}j\u0011a\u000f\u0006\u0003yu\nq!\\;uC\ndWM\u0003\u0002?#\u0005Q1m\u001c7mK\u000e$\u0018n\u001c8\n\u0005\u0001[$!D*ue&twMQ;jY\u0012,\'\u000fC\u0003C\t\u0001\u00071)\u0001\u0002tEB\u0011A)\u0012\b\u00039\u0019J!\u0001\u0011\u0016\u0002\u001bA\u0014x\u000eZ;diB\u0013XMZ5y+\u0005A\u0005CA%O\u001b\u0005Q%BA&M\u0003\u0011a\u0017M\\4\u000b\u00035\u000bAA[1wC&\u0011QGS\u0001\raJ|G-^2u\u0003JLG/_\u000b\u0002#B\u0011ADU\u0005\u0003\'F\u00111!\u00138u\u00039\u0001(o\u001c3vGR,E.Z7f]R$\"AV-\u0011\u0005q9\u0016B\u0001-\u0012\u0005\r\te.\u001f\u0005\b5\u001e\t\t\u00111\u0001R\u0003\rAH%M\u0001\u0010aJ|G-^2u\u0013R,\'/\u0019;peV\tQ\fE\u0002_?Zk\u0011!P\u0005\u0003Av\u0012\u0001\"\u0013;fe\u0006$xN]\u0001\tG\u0006tW)];bYR\u00111M\u001a\t\u00039\u0011L!!Z\t\u0003\u000f\t{w\u000e\\3b]\"9!,CA\u0001\u0002\u00041\u0016\u0001\u00035bg\"\u001cu\u000eZ3\u0015\u0003E\u000bAb\u001e:ji\u0016\u0014V\r\u001d7bG\u0016$\u0012a\u001b\t\u0003\u00132L!!\u001c&\u0003\r=\u0013\'.Z2u\u0001"
    )
  ScalaSig: length = 0x3 (unknown attribute)
   05 02 00
