Classfile /Users/mw/Projects/slang-braindump/.jar/jar11/assemble/slang-braindump/assemble/content/scala/xml/dtd/NoExternalID$.class
  Last modified May 29, 2022; size 956 bytes
  SHA-256 checksum b9fa8e5c97ec339b8d241e4c8b692bea4639281532a2f79ae1ddbdbd83a4b9e2
  Compiled from "ExternalID.scala"
public final class scala.xml.dtd.NoExternalID$ extends scala.xml.dtd.ExternalID
  minor version: 0
  major version: 52
  flags: (0x0031) ACC_PUBLIC, ACC_FINAL, ACC_SUPER
  this_class: #2                          // scala/xml/dtd/NoExternalID$
  super_class: #4                         // scala/xml/dtd/ExternalID
  interfaces: 0, fields: 3, methods: 7, attributes: 3
Constant pool:
   #1 = Utf8               scala/xml/dtd/NoExternalID$
   #2 = Class              #1             // scala/xml/dtd/NoExternalID$
   #3 = Utf8               scala/xml/dtd/ExternalID
   #4 = Class              #3             // scala/xml/dtd/ExternalID
   #5 = Utf8               ExternalID.scala
   #6 = Utf8               MODULE$
   #7 = Utf8               Lscala/xml/dtd/NoExternalID$;
   #8 = Utf8               publicId
   #9 = Utf8               Lscala/runtime/Null$;
  #10 = Utf8               systemId
  #11 = Utf8               <clinit>
  #12 = Utf8               ()V
  #13 = Utf8               <init>
  #14 = NameAndType        #13:#12        // "<init>":()V
  #15 = Methodref          #2.#14         // scala/xml/dtd/NoExternalID$."<init>":()V
  #16 = NameAndType        #6:#7          // MODULE$:Lscala/xml/dtd/NoExternalID$;
  #17 = Fieldref           #2.#16         // scala/xml/dtd/NoExternalID$.MODULE$:Lscala/xml/dtd/NoExternalID$;
  #18 = NameAndType        #8:#9          // publicId:Lscala/runtime/Null$;
  #19 = Fieldref           #2.#18         // scala/xml/dtd/NoExternalID$.publicId:Lscala/runtime/Null$;
  #20 = NameAndType        #10:#9         // systemId:Lscala/runtime/Null$;
  #21 = Fieldref           #2.#20         // scala/xml/dtd/NoExternalID$.systemId:Lscala/runtime/Null$;
  #22 = Utf8               ()Lscala/runtime/Null$;
  #23 = Utf8               this
  #24 = Utf8               toString
  #25 = Utf8               ()Ljava/lang/String;
  #26 = Utf8
  #27 = String             #26            //
  #28 = NameAndType        #10:#22        // systemId:()Lscala/runtime/Null$;
  #29 = Methodref          #2.#28         // scala/xml/dtd/NoExternalID$.systemId:()Lscala/runtime/Null$;
  #30 = NameAndType        #8:#22         // publicId:()Lscala/runtime/Null$;
  #31 = Methodref          #2.#30         // scala/xml/dtd/NoExternalID$.publicId:()Lscala/runtime/Null$;
  #32 = Methodref          #4.#14         // scala/xml/dtd/ExternalID."<init>":()V
  #33 = Utf8               Code
  #34 = Utf8               LineNumberTable
  #35 = Utf8               LocalVariableTable
  #36 = Utf8               SourceFile
  #37 = Utf8               ScalaInlineInfo
  #38 = Utf8               Scala
{
  public static final scala.xml.dtd.NoExternalID$ MODULE$;
    descriptor: Lscala/xml/dtd/NoExternalID$;
    flags: (0x0019) ACC_PUBLIC, ACC_STATIC, ACC_FINAL

  private static final scala.runtime.Null$ publicId;
    descriptor: Lscala/runtime/Null$;
    flags: (0x001a) ACC_PRIVATE, ACC_STATIC, ACC_FINAL

  private static final scala.runtime.Null$ systemId;
    descriptor: Lscala/runtime/Null$;
    flags: (0x001a) ACC_PRIVATE, ACC_STATIC, ACC_FINAL

  public static {};
    descriptor: ()V
    flags: (0x0009) ACC_PUBLIC, ACC_STATIC
    Code:
      stack=2, locals=0, args_size=0
         0: new           #2                  // class scala/xml/dtd/NoExternalID$
         3: dup
         4: invokespecial #15                 // Method "<init>":()V
         7: putstatic     #17                 // Field MODULE$:Lscala/xml/dtd/NoExternalID$;
        10: aconst_null
        11: putstatic     #19                 // Field publicId:Lscala/runtime/Null$;
        14: aconst_null
        15: putstatic     #21                 // Field systemId:Lscala/runtime/Null$;
        18: return
      LineNumberTable:
        line 87: 0
        line 88: 10
        line 89: 14
        line 87: 18

  public scala.runtime.Null$ publicId();
    descriptor: ()Lscala/runtime/Null$;
    flags: (0x0001) ACC_PUBLIC
    Code:
      stack=1, locals=1, args_size=1
         0: getstatic     #19                 // Field publicId:Lscala/runtime/Null$;
         3: areturn
      LineNumberTable:
        line 88: 0
      LocalVariableTable:
        Start  Length  Slot  Name   Signature
            0       4     0  this   Lscala/xml/dtd/NoExternalID$;

  public scala.runtime.Null$ systemId();
    descriptor: ()Lscala/runtime/Null$;
    flags: (0x0001) ACC_PUBLIC
    Code:
      stack=1, locals=1, args_size=1
         0: getstatic     #21                 // Field systemId:Lscala/runtime/Null$;
         3: areturn
      LineNumberTable:
        line 89: 0
      LocalVariableTable:
        Start  Length  Slot  Name   Signature
            0       4     0  this   Lscala/xml/dtd/NoExternalID$;

  public java.lang.String toString();
    descriptor: ()Ljava/lang/String;
    flags: (0x0001) ACC_PUBLIC
    Code:
      stack=1, locals=1, args_size=1
         0: ldc           #27                 // String
         2: areturn
      LineNumberTable:
        line 91: 0
      LocalVariableTable:
        Start  Length  Slot  Name   Signature
            0       3     0  this   Lscala/xml/dtd/NoExternalID$;

  public java.lang.String systemId();
    descriptor: ()Ljava/lang/String;
    flags: (0x1041) ACC_PUBLIC, ACC_BRIDGE, ACC_SYNTHETIC
    Code:
      stack=1, locals=1, args_size=1
         0: aload_0
         1: invokevirtual #29                 // Method systemId:()Lscala/runtime/Null$;
         4: pop
         5: aconst_null
         6: areturn
      LineNumberTable:
        line 87: 0
      LocalVariableTable:
        Start  Length  Slot  Name   Signature
            0       7     0  this   Lscala/xml/dtd/NoExternalID$;

  public java.lang.String publicId();
    descriptor: ()Ljava/lang/String;
    flags: (0x1041) ACC_PUBLIC, ACC_BRIDGE, ACC_SYNTHETIC
    Code:
      stack=1, locals=1, args_size=1
         0: aload_0
         1: invokevirtual #31                 // Method publicId:()Lscala/runtime/Null$;
         4: pop
         5: aconst_null
         6: areturn
      LineNumberTable:
        line 87: 0
      LocalVariableTable:
        Start  Length  Slot  Name   Signature
            0       7     0  this   Lscala/xml/dtd/NoExternalID$;

  private scala.xml.dtd.NoExternalID$();
    descriptor: ()V
    flags: (0x0002) ACC_PRIVATE
    Code:
      stack=1, locals=1, args_size=1
         0: aload_0
         1: invokespecial #32                 // Method scala/xml/dtd/ExternalID."<init>":()V
         4: return
      LineNumberTable:
        line 87: 0
      LocalVariableTable:
        Start  Length  Slot  Name   Signature
            0       5     0  this   Lscala/xml/dtd/NoExternalID$;
}
SourceFile: "ExternalID.scala"
  ScalaInlineInfo: length = 0x22 (unknown attribute)
   01 01 00 06 00 0D 00 0C 01 00 08 00 19 01 00 08
   00 16 01 00 0A 00 19 01 00 0A 00 16 01 00 18 00
   19 01
  Scala: length = 0x0 (unknown attribute)

