Classfile /Users/mw/Projects/slang-braindump/.jar/jar11/assemble/slang-braindump/assemble/content/scala/xml/dtd/NotationDecl.class
  Last modified May 29, 2022; size 5912 bytes
  SHA-256 checksum a1e49811c1d4476e7dfbcb348dec9fa5cc87a62c8cea82e3be8782b2fd99a76b
  Compiled from "Decl.scala"
public class scala.xml.dtd.NotationDecl extends scala.xml.dtd.MarkupDecl implements scala.Product,java.io.Serializable
  minor version: 0
  major version: 52
  flags: (0x0021) ACC_PUBLIC, ACC_SUPER
  this_class: #2                          // scala/xml/dtd/NotationDecl
  super_class: #4                         // scala/xml/dtd/MarkupDecl
  interfaces: 2, fields: 2, methods: 20, attributes: 4
Constant pool:
    #1 = Utf8               scala/xml/dtd/NotationDecl
    #2 = Class              #1            // scala/xml/dtd/NotationDecl
    #3 = Utf8               scala/xml/dtd/MarkupDecl
    #4 = Class              #3            // scala/xml/dtd/MarkupDecl
    #5 = Utf8               scala/Product
    #6 = Class              #5            // scala/Product
    #7 = Utf8               java/io/Serializable
    #8 = Class              #7            // java/io/Serializable
    #9 = Utf8               Decl.scala
   #10 = Utf8               Lscala/reflect/ScalaSignature;
   #11 = Utf8               bytes
   #12 = Utf8               \u0006\u0005\u00055d\u0001B\r\u001b\u0001\u0006B\u0001B\u000e\u0001\u0003\u0016\u0004%\ta\u000e\u0005\t\u0001\u0002\u0011\t\u0012)A\u0005q!A\u0011\t\u0001BK\u0002\u0013\u0005!\t\u0003\u0005G\u0001\tE\t\u0015!\u0003D\u0011\u00159\u0005\u0001\"\u0001I\u0011\u0015a\u0005\u0001\"\u0011N\u0011\u001d!\u0006!!A\u0005\u0002UCq\u0001\u0017\u0001\u0012\u0002\u0013\u0005\u0011\fC\u0004e\u0001E\u0005I\u0011A3\t\u000f\u001d\u0004\u0011\u0011!C!Q\"9\u0001\u000fAA\u0001\n\u0003\t\bbB;\u0001\u0003\u0003%\tA\u001e\u0005\by\u0002\t\t\u0011\"\u0011~\u0011%\tI\u0001AA\u0001\n\u0003\tY\u0001C\u0005\u0002\u0016\u0001\t\t\u0011\"\u0011\u0002\u0018!I\u00111\u0004\u0001\u0002\u0002\u0013\u0005\u0013Q\u0004\u0005\n\u0003?\u0001\u0011\u0011!C!\u0003C9\u0011\"!\n\u001b\u0003\u0003E\t!a\n\u0007\u0011eQ\u0012\u0011!E\u0001\u0003SAaaR\n\u0005\u0002\u0005\u0005\u0003\"CA\"\'\u0005\u0005IQIA#\u0011%\t9eEA\u0001\n\u0003\u000bI\u0005C\u0005\u0002PM\t\t\u0011\"!\u0002R!I\u00111M\n\u0002\u0002\u0013%\u0011Q\r\u0002\r\u001d>$\u0018\r^5p]\u0012+7\r\u001c\u0006\u00037q\t1\u0001\u001a;e\u0015\tib$A\u0002y[2T\u0011aH\u0001\u0006g\u000e\fG.Y\u0002\u0001\'\u0011\u0001!E\n\u0016\u0011\u0005\r\"S\"\u0001\u000e\n\u0005\u0015R\"AC\'be.,\b\u000fR3dYB\u0011q\u0005K\u0007\u0002=%\u0011\u0011F\b\u0002\b!J|G-^2u!\tY3G\u0004\u0002-c9\u0011Q\u0006M\u0007\u0002])\u0011q\u0006I\u0001\u0007yI|w\u000e\u001e \n\u0003}I!A\r\u0010\u0002\u000fA\f7m[1hK&\u0011A\'\u000e\u0002\r\'\u0016\u0014\u0018.\u00197ju\u0006\u0014G.\u001a\u0006\u0003ey\tAA\\1nKV\t\u0001\b\u0005\u0002:{9\u0011!h\u000f\t\u0003[yI!\u0001\u0010\u0010\u0002\rA\u0013X\rZ3g\u0013\tqtH\u0001\u0004TiJLgn\u001a\u0006\u0003yy\tQA\\1nK\u0002\nQ!\u001a=u\u0013\u0012+\u0012a\u0011\t\u0003G\u0011K!!\u0012\u000e\u0003\u0015\u0015CH/\u001a:oC2LE)\u0001\u0004fqRLE\tI\u0001\u0007y%t\u0017\u000e\u001e \u0015\u0007%S5\n\u0005\u0002$\u0001!)a\'\u0002a\u0001q!)\u0011)\u0002a\u0001\u0007\u0006Y!-^5mIN#(/\u001b8h)\tq%\u000b\u0005\u0002P!:\u0011q%M\u0005\u0003#V\u0012Qb\u0015;sS:<\')^5mI\u0016\u0014\b\"B*\u0007\u0001\u0004q\u0015AA:c\u0003\u0011\u0019w\u000e]=\u0015\u0007%3v\u000bC\u00047\u000fA\u0005\t\u0019\u0001\u001d\t\u000f\u0005;\u0001\u0013!a\u0001\u0007\u0006q1m\u001c9zI\u0011,g-Y;mi\u0012\nT#\u0001.+\u0005aZ6&\u0001/\u0011\u0005u\u0013W\"\u00010\u000b\u0005}\u0003\u0017!C;oG\",7m[3e\u0015\t\tg$\u0001\u0006b]:|G/\u0019;j_:L!a\u00190\u0003#Ut7\r[3dW\u0016$g+\u0019:jC:\u001cW-\u0001\bd_BLH\u0005Z3gCVdG\u000f\n\u001a\u0016\u0003\u0019T#aQ.\u0002\u001bA\u0014x\u000eZ;diB\u0013XMZ5y+\u0005I\u0007C\u00016p\u001b\u0005Y\'B\u00017n\u0003\u0011a\u0017M\\4\u000b\u00039\fAA[1wC&\u0011ah[\u0001\raJ|G-^2u\u0003JLG/_\u000b\u0002eB\u0011qe]\u0005\u0003iz\u00111!\u00138u\u00039\u0001(o\u001c3vGR,E.Z7f]R$\"a\u001e>\u0011\u0005\u001dB\u0018BA=\u001f\u0005\r\te.\u001f\u0005\bw2\t\t\u00111\u0001s\u0003\rAH%M\u0001\u0010aJ|G-^2u\u0013R,\'/\u0019;peV\ta\u0010\u0005\u0003\u0000\u0003\u000b9XBAA\u0001\u0015\r\t\u0019AH\u0001\u000bG>dG.Z2uS>t\u0017\u0002BA\u0004\u0003\u0003\u0011\u0001\"\u0013;fe\u0006$xN]\u0001\tG\u0006tW)];bYR!\u0011QBA\n!\r9\u0013qB\u0005\u0004\u0003#q\"a\u0002\"p_2,\u0017M\u001c\u0005\bw:\t\t\u00111\u0001x\u0003I\u0001(o\u001c3vGR,E.Z7f]Rt\u0015-\\3\u0015\u0007%\fI\u0002C\u0004|\u001f\u0005\u0005\t\u0019\u0001:\u0002\u0011!\f7\u000f[\"pI\u0016$\u0012A]\u0001\u0007KF,\u0018\r\\:\u0015\t\u00055\u00111\u0005\u0005\bwF\t\t\u00111\u0001x\u00031qu\u000e^1uS>tG)Z2m!\t\u00193cE\u0003\u0014\u0003W\t9\u0004E\u0004\u0002.\u0005M\u0002hQ%\u000e\u0005\u0005=\"bAA\u0019=\u00059!/\u001e8uS6,\u0017\u0002BA\u001b\u0003_\u0011\u0011#\u00112tiJ\f7\r\u001e$v]\u000e$\u0018n\u001c83!\u0011\tI$a\u0010\u000e\u0005\u0005m\"bAA\u001f[\u0006\u0011\u0011n\\\u0005\u0004i\u0005mBCAA\u0014\u0003!!xn\u0015;sS:<G#A5\u0002\u000b\u0005\u0004\b\u000f\\=\u0015\u000b%\u000bY%!\u0014\t\u000bY2\u0002\u0019\u0001\u001d\t\u000b\u00053\u0002\u0019A\"\u0002\u000fUt\u0017\r\u001d9msR!\u00111KA0!\u00159\u0013QKA-\u0013\r\t9F\b\u0002\u0007\u001fB$\u0018n\u001c8\u0011\u000b\u001d\nY\u0006O\"\n\u0007\u0005ucD\u0001\u0004UkBdWM\r\u0005\t\u0003C:\u0012\u0011!a\u0001\u0013\u0006\u0019\u0001\u0010\n\u0019\u0002\u0019]\u0014\u0018\u000e^3SKBd\u0017mY3\u0015\u0005\u0005\u001d\u0004c\u00016\u0002j%\u0019\u00111N6\u0003\r=\u0013\'.Z2u\u0001
   #13 = Utf8               name
   #14 = Utf8               Ljava/lang/String;
   #15 = Utf8               extID
   #16 = Utf8               Lscala/xml/dtd/ExternalID;
   #17 = Utf8               unapply
   #18 = Utf8               (Lscala/xml/dtd/NotationDecl;)Lscala/Option;
   #19 = Utf8               (Lscala/xml/dtd/NotationDecl;)Lscala/Option<Lscala/Tuple2<Ljava/lang/String;Lscala/xml/dtd/ExternalID;>;>;
   #20 = Utf8               x$0
   #21 = Utf8               scala/xml/dtd/NotationDecl$
   #22 = Class              #21           // scala/xml/dtd/NotationDecl$
   #23 = Utf8               MODULE$
   #24 = Utf8               Lscala/xml/dtd/NotationDecl$;
   #25 = NameAndType        #23:#24       // MODULE$:Lscala/xml/dtd/NotationDecl$;
   #26 = Fieldref           #22.#25       // scala/xml/dtd/NotationDecl$.MODULE$:Lscala/xml/dtd/NotationDecl$;
   #27 = NameAndType        #17:#18       // unapply:(Lscala/xml/dtd/NotationDecl;)Lscala/Option;
   #28 = Methodref          #22.#27       // scala/xml/dtd/NotationDecl$.unapply:(Lscala/xml/dtd/NotationDecl;)Lscala/Option;
   #29 = Utf8               Lscala/xml/dtd/NotationDecl;
   #30 = Utf8               apply
   #31 = Utf8               (Ljava/lang/String;Lscala/xml/dtd/ExternalID;)Lscala/xml/dtd/NotationDecl;
   #32 = NameAndType        #30:#31       // apply:(Ljava/lang/String;Lscala/xml/dtd/ExternalID;)Lscala/xml/dtd/NotationDecl;
   #33 = Methodref          #22.#32       // scala/xml/dtd/NotationDecl$.apply:(Ljava/lang/String;Lscala/xml/dtd/ExternalID;)Lscala/xml/dtd/NotationDecl;
   #34 = Utf8               tupled
   #35 = Utf8               ()Lscala/Function1;
   #36 = Utf8               ()Lscala/Function1<Lscala/Tuple2<Ljava/lang/String;Lscala/xml/dtd/ExternalID;>;Lscala/xml/dtd/NotationDecl;>;
   #37 = NameAndType        #34:#35       // tupled:()Lscala/Function1;
   #38 = Methodref          #22.#37       // scala/xml/dtd/NotationDecl$.tupled:()Lscala/Function1;
   #39 = Utf8               curried
   #40 = Utf8               ()Lscala/Function1<Ljava/lang/String;Lscala/Function1<Lscala/xml/dtd/ExternalID;Lscala/xml/dtd/NotationDecl;>;>;
   #41 = NameAndType        #39:#35       // curried:()Lscala/Function1;
   #42 = Methodref          #22.#41       // scala/xml/dtd/NotationDecl$.curried:()Lscala/Function1;
   #43 = Utf8               productElementNames
   #44 = Utf8               ()Lscala/collection/Iterator;
   #45 = Utf8               ()Lscala/collection/Iterator<Ljava/lang/String;>;
   #46 = Utf8               productElementNames$
   #47 = Utf8               (Lscala/Product;)Lscala/collection/Iterator;
   #48 = NameAndType        #46:#47       // productElementNames$:(Lscala/Product;)Lscala/collection/Iterator;
   #49 = InterfaceMethodref #6.#48        // scala/Product.productElementNames$:(Lscala/Product;)Lscala/collection/Iterator;
   #50 = Utf8               this
   #51 = Utf8               ()Ljava/lang/String;
   #52 = NameAndType        #13:#14       // name:Ljava/lang/String;
   #53 = Fieldref           #2.#52        // scala/xml/dtd/NotationDecl.name:Ljava/lang/String;
   #54 = Utf8               ()Lscala/xml/dtd/ExternalID;
   #55 = NameAndType        #15:#16       // extID:Lscala/xml/dtd/ExternalID;
   #56 = Fieldref           #2.#55        // scala/xml/dtd/NotationDecl.extID:Lscala/xml/dtd/ExternalID;
   #57 = Utf8               buildString
   #58 = Utf8               (Lscala/collection/mutable/StringBuilder;)Lscala/collection/mutable/StringBuilder;
   #59 = Utf8               sb
   #60 = Utf8               <!NOTATION
   #61 = String             #60           // <!NOTATION
   #62 = Utf8               scala/collection/mutable/StringBuilder
   #63 = Class              #62           // scala/collection/mutable/StringBuilder
   #64 = Utf8               append
   #65 = Utf8               (Ljava/lang/String;)Lscala/collection/mutable/StringBuilder;
   #66 = NameAndType        #64:#65       // append:(Ljava/lang/String;)Lscala/collection/mutable/StringBuilder;
   #67 = Methodref          #63.#66       // scala/collection/mutable/StringBuilder.append:(Ljava/lang/String;)Lscala/collection/mutable/StringBuilder;
   #68 = NameAndType        #13:#51       // name:()Ljava/lang/String;
   #69 = Methodref          #2.#68        // scala/xml/dtd/NotationDecl.name:()Ljava/lang/String;
   #70 = Utf8               (C)Lscala/collection/mutable/StringBuilder;
   #71 = NameAndType        #64:#70       // append:(C)Lscala/collection/mutable/StringBuilder;
   #72 = Methodref          #63.#71       // scala/collection/mutable/StringBuilder.append:(C)Lscala/collection/mutable/StringBuilder;
   #73 = NameAndType        #15:#54       // extID:()Lscala/xml/dtd/ExternalID;
   #74 = Methodref          #2.#73        // scala/xml/dtd/NotationDecl.extID:()Lscala/xml/dtd/ExternalID;
   #75 = Utf8               scala/xml/dtd/ExternalID
   #76 = Class              #75           // scala/xml/dtd/ExternalID
   #77 = NameAndType        #57:#58       // buildString:(Lscala/collection/mutable/StringBuilder;)Lscala/collection/mutable/StringBuilder;
   #78 = Methodref          #76.#77       // scala/xml/dtd/ExternalID.buildString:(Lscala/collection/mutable/StringBuilder;)Lscala/collection/mutable/StringBuilder;
   #79 = Utf8               Lscala/collection/mutable/StringBuilder;
   #80 = Utf8               copy
   #81 = Utf8               <init>
   #82 = Utf8               (Ljava/lang/String;Lscala/xml/dtd/ExternalID;)V
   #83 = NameAndType        #81:#82       // "<init>":(Ljava/lang/String;Lscala/xml/dtd/ExternalID;)V
   #84 = Methodref          #2.#83        // scala/xml/dtd/NotationDecl."<init>":(Ljava/lang/String;Lscala/xml/dtd/ExternalID;)V
   #85 = Utf8               copy$default$1
   #86 = Utf8               copy$default$2
   #87 = Utf8               productPrefix
   #88 = Utf8               NotationDecl
   #89 = String             #88           // NotationDecl
   #90 = Utf8               productArity
   #91 = Utf8               ()I
   #92 = Utf8               productElement
   #93 = Utf8               (I)Ljava/lang/Object;
   #94 = Utf8               x$1
   #95 = Utf8               scala/runtime/Statics
   #96 = Class              #95           // scala/runtime/Statics
   #97 = Utf8               ioobe
   #98 = NameAndType        #97:#93       // ioobe:(I)Ljava/lang/Object;
   #99 = Methodref          #96.#98       // scala/runtime/Statics.ioobe:(I)Ljava/lang/Object;
  #100 = Utf8               I
  #101 = Utf8               java/lang/Object
  #102 = Class              #101          // java/lang/Object
  #103 = Utf8               productIterator
  #104 = Utf8               ()Lscala/collection/Iterator<Ljava/lang/Object;>;
  #105 = Utf8               scala/runtime/ScalaRunTime$
  #106 = Class              #105          // scala/runtime/ScalaRunTime$
  #107 = Utf8               Lscala/runtime/ScalaRunTime$;
  #108 = NameAndType        #23:#107      // MODULE$:Lscala/runtime/ScalaRunTime$;
  #109 = Fieldref           #106.#108     // scala/runtime/ScalaRunTime$.MODULE$:Lscala/runtime/ScalaRunTime$;
  #110 = Utf8               typedProductIterator
  #111 = NameAndType        #110:#47      // typedProductIterator:(Lscala/Product;)Lscala/collection/Iterator;
  #112 = Methodref          #106.#111     // scala/runtime/ScalaRunTime$.typedProductIterator:(Lscala/Product;)Lscala/collection/Iterator;
  #113 = Utf8               canEqual
  #114 = Utf8               (Ljava/lang/Object;)Z
  #115 = Utf8               Ljava/lang/Object;
  #116 = Utf8               productElementName
  #117 = Utf8               (I)Ljava/lang/String;
  #118 = String             #13           // name
  #119 = String             #15           // extID
  #120 = Utf8               java/lang/String
  #121 = Class              #120          // java/lang/String
  #122 = Utf8               hashCode
  #123 = Utf8               _hashCode
  #124 = Utf8               (Lscala/Product;)I
  #125 = NameAndType        #123:#124     // _hashCode:(Lscala/Product;)I
  #126 = Methodref          #106.#125     // scala/runtime/ScalaRunTime$._hashCode:(Lscala/Product;)I
  #127 = Utf8               equals
  #128 = NameAndType        #127:#114     // equals:(Ljava/lang/Object;)Z
  #129 = Methodref          #102.#128     // java/lang/Object.equals:(Ljava/lang/Object;)Z
  #130 = NameAndType        #113:#114     // canEqual:(Ljava/lang/Object;)Z
  #131 = Methodref          #2.#130       // scala/xml/dtd/NotationDecl.canEqual:(Ljava/lang/Object;)Z
  #132 = Utf8               ()V
  #133 = NameAndType        #81:#132      // "<init>":()V
  #134 = Methodref          #4.#133       // scala/xml/dtd/MarkupDecl."<init>":()V
  #135 = Utf8               $init$
  #136 = Utf8               (Lscala/Product;)V
  #137 = NameAndType        #135:#136     // $init$:(Lscala/Product;)V
  #138 = InterfaceMethodref #6.#137       // scala/Product.$init$:(Lscala/Product;)V
  #139 = Utf8               Code
  #140 = Utf8               LocalVariableTable
  #141 = Utf8               Signature
  #142 = Utf8               MethodParameters
  #143 = Utf8               LineNumberTable
  #144 = Utf8               StackMapTable
  #145 = Utf8               SourceFile
  #146 = Utf8               RuntimeVisibleAnnotations
  #147 = Utf8               ScalaInlineInfo
  #148 = Utf8               ScalaSig
{
  private final java.lang.String name;
    descriptor: Ljava/lang/String;
    flags: (0x0012) ACC_PRIVATE, ACC_FINAL

  private final scala.xml.dtd.ExternalID extID;
    descriptor: Lscala/xml/dtd/ExternalID;
    flags: (0x0012) ACC_PRIVATE, ACC_FINAL

  public static scala.Option<scala.Tuple2<java.lang.String, scala.xml.dtd.ExternalID>> unapply(scala.xml.dtd.NotationDecl);
    descriptor: (Lscala/xml/dtd/NotationDecl;)Lscala/Option;
    flags: (0x0009) ACC_PUBLIC, ACC_STATIC
    Code:
      stack=2, locals=1, args_size=1
         0: getstatic     #26                 // Field scala/xml/dtd/NotationDecl$.MODULE$:Lscala/xml/dtd/NotationDecl$;
         3: aload_0
         4: invokevirtual #28                 // Method scala/xml/dtd/NotationDecl$.unapply:(Lscala/xml/dtd/NotationDecl;)Lscala/Option;
         7: areturn
      LocalVariableTable:
        Start  Length  Slot  Name   Signature
            0       8     0   x$0   Lscala/xml/dtd/NotationDecl;
    Signature: #19                          // (Lscala/xml/dtd/NotationDecl;)Lscala/Option<Lscala/Tuple2<Ljava/lang/String;Lscala/xml/dtd/ExternalID;>;>;
    MethodParameters:
      Name                           Flags
      x$0                            final

  public static scala.xml.dtd.NotationDecl apply(java.lang.String, scala.xml.dtd.ExternalID);
    descriptor: (Ljava/lang/String;Lscala/xml/dtd/ExternalID;)Lscala/xml/dtd/NotationDecl;
    flags: (0x0009) ACC_PUBLIC, ACC_STATIC
    Code:
      stack=3, locals=2, args_size=2
         0: getstatic     #26                 // Field scala/xml/dtd/NotationDecl$.MODULE$:Lscala/xml/dtd/NotationDecl$;
         3: aload_0
         4: aload_1
         5: invokevirtual #33                 // Method scala/xml/dtd/NotationDecl$.apply:(Ljava/lang/String;Lscala/xml/dtd/ExternalID;)Lscala/xml/dtd/NotationDecl;
         8: areturn
      LocalVariableTable:
        Start  Length  Slot  Name   Signature
            0       9     0  name   Ljava/lang/String;
            0       9     1 extID   Lscala/xml/dtd/ExternalID;
    MethodParameters:
      Name                           Flags
      name                           final
      extID                          final

  public static scala.Function1<scala.Tuple2<java.lang.String, scala.xml.dtd.ExternalID>, scala.xml.dtd.NotationDecl> tupled();
    descriptor: ()Lscala/Function1;
    flags: (0x0009) ACC_PUBLIC, ACC_STATIC
    Code:
      stack=1, locals=0, args_size=0
         0: getstatic     #26                 // Field scala/xml/dtd/NotationDecl$.MODULE$:Lscala/xml/dtd/NotationDecl$;
         3: invokevirtual #38                 // Method scala/xml/dtd/NotationDecl$.tupled:()Lscala/Function1;
         6: areturn
    Signature: #36                          // ()Lscala/Function1<Lscala/Tuple2<Ljava/lang/String;Lscala/xml/dtd/ExternalID;>;Lscala/xml/dtd/NotationDecl;>;

  public static scala.Function1<java.lang.String, scala.Function1<scala.xml.dtd.ExternalID, scala.xml.dtd.NotationDecl>> curried();
    descriptor: ()Lscala/Function1;
    flags: (0x0009) ACC_PUBLIC, ACC_STATIC
    Code:
      stack=1, locals=0, args_size=0
         0: getstatic     #26                 // Field scala/xml/dtd/NotationDecl$.MODULE$:Lscala/xml/dtd/NotationDecl$;
         3: invokevirtual #42                 // Method scala/xml/dtd/NotationDecl$.curried:()Lscala/Function1;
         6: areturn
    Signature: #40                          // ()Lscala/Function1<Ljava/lang/String;Lscala/Function1<Lscala/xml/dtd/ExternalID;Lscala/xml/dtd/NotationDecl;>;>;

  public scala.collection.Iterator<java.lang.String> productElementNames();
    descriptor: ()Lscala/collection/Iterator;
    flags: (0x0001) ACC_PUBLIC
    Code:
      stack=1, locals=1, args_size=1
         0: aload_0
         1: invokestatic  #49                 // InterfaceMethod scala/Product.productElementNames$:(Lscala/Product;)Lscala/collection/Iterator;
         4: areturn
      LineNumberTable:
        line 99: 0
      LocalVariableTable:
        Start  Length  Slot  Name   Signature
            0       5     0  this   Lscala/xml/dtd/NotationDecl;
    Signature: #45                          // ()Lscala/collection/Iterator<Ljava/lang/String;>;

  public java.lang.String name();
    descriptor: ()Ljava/lang/String;
    flags: (0x0001) ACC_PUBLIC
    Code:
      stack=1, locals=1, args_size=1
         0: aload_0
         1: getfield      #53                 // Field name:Ljava/lang/String;
         4: areturn
      LineNumberTable:
        line 99: 0
      LocalVariableTable:
        Start  Length  Slot  Name   Signature
            0       5     0  this   Lscala/xml/dtd/NotationDecl;

  public scala.xml.dtd.ExternalID extID();
    descriptor: ()Lscala/xml/dtd/ExternalID;
    flags: (0x0001) ACC_PUBLIC
    Code:
      stack=1, locals=1, args_size=1
         0: aload_0
         1: getfield      #56                 // Field extID:Lscala/xml/dtd/ExternalID;
         4: areturn
      LineNumberTable:
        line 99: 0
      LocalVariableTable:
        Start  Length  Slot  Name   Signature
            0       5     0  this   Lscala/xml/dtd/NotationDecl;

  public scala.collection.mutable.StringBuilder buildString(scala.collection.mutable.StringBuilder);
    descriptor: (Lscala/collection/mutable/StringBuilder;)Lscala/collection/mutable/StringBuilder;
    flags: (0x0001) ACC_PUBLIC
    Code:
      stack=2, locals=2, args_size=2
         0: aload_1
         1: ldc           #61                 // String <!NOTATION
         3: invokevirtual #67                 // Method scala/collection/mutable/StringBuilder.append:(Ljava/lang/String;)Lscala/collection/mutable/StringBuilder;
         6: aload_0
         7: invokevirtual #69                 // Method name:()Ljava/lang/String;
        10: invokevirtual #67                 // Method scala/collection/mutable/StringBuilder.append:(Ljava/lang/String;)Lscala/collection/mutable/StringBuilder;
        13: bipush        32
        15: invokevirtual #72                 // Method scala/collection/mutable/StringBuilder.append:(C)Lscala/collection/mutable/StringBuilder;
        18: pop
        19: aload_0
        20: invokevirtual #74                 // Method extID:()Lscala/xml/dtd/ExternalID;
        23: aload_1
        24: invokevirtual #78                 // Method scala/xml/dtd/ExternalID.buildString:(Lscala/collection/mutable/StringBuilder;)Lscala/collection/mutable/StringBuilder;
        27: areturn
      LineNumberTable:
        line 101: 0
        line 102: 19
      LocalVariableTable:
        Start  Length  Slot  Name   Signature
            0      28     0  this   Lscala/xml/dtd/NotationDecl;
            0      28     1    sb   Lscala/collection/mutable/StringBuilder;
    MethodParameters:
      Name                           Flags
      sb                             final

  public scala.xml.dtd.NotationDecl copy(java.lang.String, scala.xml.dtd.ExternalID);
    descriptor: (Ljava/lang/String;Lscala/xml/dtd/ExternalID;)Lscala/xml/dtd/NotationDecl;
    flags: (0x0001) ACC_PUBLIC
    Code:
      stack=4, locals=3, args_size=3
         0: new           #2                  // class scala/xml/dtd/NotationDecl
         3: dup
         4: aload_1
         5: aload_2
         6: invokespecial #84                 // Method "<init>":(Ljava/lang/String;Lscala/xml/dtd/ExternalID;)V
         9: areturn
      LineNumberTable:
        line 99: 0
      LocalVariableTable:
        Start  Length  Slot  Name   Signature
            0      10     0  this   Lscala/xml/dtd/NotationDecl;
            0      10     1  name   Ljava/lang/String;
            0      10     2 extID   Lscala/xml/dtd/ExternalID;
    MethodParameters:
      Name                           Flags
      name                           final
      extID                          final

  public java.lang.String copy$default$1();
    descriptor: ()Ljava/lang/String;
    flags: (0x0001) ACC_PUBLIC
    Code:
      stack=1, locals=1, args_size=1
         0: aload_0
         1: invokevirtual #69                 // Method name:()Ljava/lang/String;
         4: areturn
      LineNumberTable:
        line 99: 0
      LocalVariableTable:
        Start  Length  Slot  Name   Signature
            0       5     0  this   Lscala/xml/dtd/NotationDecl;

  public scala.xml.dtd.ExternalID copy$default$2();
    descriptor: ()Lscala/xml/dtd/ExternalID;
    flags: (0x0001) ACC_PUBLIC
    Code:
      stack=1, locals=1, args_size=1
         0: aload_0
         1: invokevirtual #74                 // Method extID:()Lscala/xml/dtd/ExternalID;
         4: areturn
      LineNumberTable:
        line 99: 0
      LocalVariableTable:
        Start  Length  Slot  Name   Signature
            0       5     0  this   Lscala/xml/dtd/NotationDecl;

  public java.lang.String productPrefix();
    descriptor: ()Ljava/lang/String;
    flags: (0x0001) ACC_PUBLIC
    Code:
      stack=1, locals=1, args_size=1
         0: ldc           #89                 // String NotationDecl
         2: areturn
      LineNumberTable:
        line 99: 0
      LocalVariableTable:
        Start  Length  Slot  Name   Signature
            0       3     0  this   Lscala/xml/dtd/NotationDecl;

  public int productArity();
    descriptor: ()I
    flags: (0x0001) ACC_PUBLIC
    Code:
      stack=1, locals=1, args_size=1
         0: iconst_2
         1: ireturn
      LineNumberTable:
        line 99: 0
      LocalVariableTable:
        Start  Length  Slot  Name   Signature
            0       2     0  this   Lscala/xml/dtd/NotationDecl;

  public java.lang.Object productElement(int);
    descriptor: (I)Ljava/lang/Object;
    flags: (0x0001) ACC_PUBLIC
    Code:
      stack=1, locals=3, args_size=2
         0: iload_1
         1: istore_2
         2: iload_2
         3: tableswitch   { // 0 to 1
                       0: 24
                       1: 31
                 default: 38
            }
        24: aload_0
        25: invokevirtual #69                 // Method name:()Ljava/lang/String;
        28: goto          45
        31: aload_0
        32: invokevirtual #74                 // Method extID:()Lscala/xml/dtd/ExternalID;
        35: goto          45
        38: iload_1
        39: invokestatic  #99                 // Method scala/runtime/Statics.ioobe:(I)Ljava/lang/Object;
        42: goto          45
        45: areturn
      StackMapTable: number_of_entries = 4
        frame_type = 252 /* append */
          offset_delta = 24
          locals = [ int ]
        frame_type = 6 /* same */
        frame_type = 6 /* same */
        frame_type = 70 /* same_locals_1_stack_item */
          stack = [ class java/lang/Object ]
      LineNumberTable:
        line 99: 0
      LocalVariableTable:
        Start  Length  Slot  Name   Signature
            0      46     0  this   Lscala/xml/dtd/NotationDecl;
            0      46     1   x$1   I
    MethodParameters:
      Name                           Flags
      x$1                            final

  public scala.collection.Iterator<java.lang.Object> productIterator();
    descriptor: ()Lscala/collection/Iterator;
    flags: (0x0001) ACC_PUBLIC
    Code:
      stack=2, locals=1, args_size=1
         0: getstatic     #109                // Field scala/runtime/ScalaRunTime$.MODULE$:Lscala/runtime/ScalaRunTime$;
         3: aload_0
         4: invokevirtual #112                // Method scala/runtime/ScalaRunTime$.typedProductIterator:(Lscala/Product;)Lscala/collection/Iterator;
         7: areturn
      LineNumberTable:
        line 99: 0
      LocalVariableTable:
        Start  Length  Slot  Name   Signature
            0       8     0  this   Lscala/xml/dtd/NotationDecl;
    Signature: #104                         // ()Lscala/collection/Iterator<Ljava/lang/Object;>;

  public boolean canEqual(java.lang.Object);
    descriptor: (Ljava/lang/Object;)Z
    flags: (0x0001) ACC_PUBLIC
    Code:
      stack=1, locals=2, args_size=2
         0: aload_1
         1: instanceof    #2                  // class scala/xml/dtd/NotationDecl
         4: ireturn
      LineNumberTable:
        line 99: 0
      LocalVariableTable:
        Start  Length  Slot  Name   Signature
            0       5     0  this   Lscala/xml/dtd/NotationDecl;
            0       5     1   x$1   Ljava/lang/Object;
    MethodParameters:
      Name                           Flags
      x$1                            final

  public java.lang.String productElementName(int);
    descriptor: (I)Ljava/lang/String;
    flags: (0x0001) ACC_PUBLIC
    Code:
      stack=1, locals=3, args_size=2
         0: iload_1
         1: istore_2
         2: iload_2
         3: tableswitch   { // 0 to 1
                       0: 24
                       1: 29
                 default: 34
            }
        24: ldc           #118                // String name
        26: goto          44
        29: ldc           #119                // String extID
        31: goto          44
        34: iload_1
        35: invokestatic  #99                 // Method scala/runtime/Statics.ioobe:(I)Ljava/lang/Object;
        38: checkcast     #121                // class java/lang/String
        41: goto          44
        44: areturn
      StackMapTable: number_of_entries = 4
        frame_type = 252 /* append */
          offset_delta = 24
          locals = [ int ]
        frame_type = 4 /* same */
        frame_type = 4 /* same */
        frame_type = 73 /* same_locals_1_stack_item */
          stack = [ class java/lang/String ]
      LineNumberTable:
        line 99: 0
      LocalVariableTable:
        Start  Length  Slot  Name   Signature
            0      45     0  this   Lscala/xml/dtd/NotationDecl;
            0      45     1   x$1   I
    MethodParameters:
      Name                           Flags
      x$1                            final

  public int hashCode();
    descriptor: ()I
    flags: (0x0001) ACC_PUBLIC
    Code:
      stack=2, locals=1, args_size=1
         0: getstatic     #109                // Field scala/runtime/ScalaRunTime$.MODULE$:Lscala/runtime/ScalaRunTime$;
         3: aload_0
         4: invokevirtual #126                // Method scala/runtime/ScalaRunTime$._hashCode:(Lscala/Product;)I
         7: ireturn
      LineNumberTable:
        line 99: 0
      LocalVariableTable:
        Start  Length  Slot  Name   Signature
            0       8     0  this   Lscala/xml/dtd/NotationDecl;

  public boolean equals(java.lang.Object);
    descriptor: (Ljava/lang/Object;)Z
    flags: (0x0001) ACC_PUBLIC
    Code:
      stack=2, locals=7, args_size=2
         0: aload_0
         1: aload_1
         2: if_acmpeq     118
         5: aload_1
         6: astore_3
         7: aload_3
         8: instanceof    #2                  // class scala/xml/dtd/NotationDecl
        11: ifeq          19
        14: iconst_1
        15: istore_2
        16: goto          27
        19: goto          22
        22: iconst_0
        23: istore_2
        24: goto          27
        27: iload_2
        28: ifeq          122
        31: aload_1
        32: checkcast     #2                  // class scala/xml/dtd/NotationDecl
        35: astore        4
        37: aload_0
        38: invokevirtual #69                 // Method name:()Ljava/lang/String;
        41: aload         4
        43: invokevirtual #69                 // Method name:()Ljava/lang/String;
        46: astore        5
        48: dup
        49: ifnonnull     61
        52: pop
        53: aload         5
        55: ifnull        69
        58: goto          114
        61: aload         5
        63: invokevirtual #129                // Method java/lang/Object.equals:(Ljava/lang/Object;)Z
        66: ifeq          114
        69: aload_0
        70: invokevirtual #74                 // Method extID:()Lscala/xml/dtd/ExternalID;
        73: aload         4
        75: invokevirtual #74                 // Method extID:()Lscala/xml/dtd/ExternalID;
        78: astore        6
        80: dup
        81: ifnonnull     93
        84: pop
        85: aload         6
        87: ifnull        101
        90: goto          114
        93: aload         6
        95: invokevirtual #129                // Method java/lang/Object.equals:(Ljava/lang/Object;)Z
        98: ifeq          114
       101: aload         4
       103: aload_0
       104: invokevirtual #131                // Method canEqual:(Ljava/lang/Object;)Z
       107: ifeq          114
       110: iconst_1
       111: goto          115
       114: iconst_0
       115: ifeq          122
       118: iconst_1
       119: goto          123
       122: iconst_0
       123: ireturn
      StackMapTable: number_of_entries = 12
        frame_type = 253 /* append */
          offset_delta = 19
          locals = [ top, class java/lang/Object ]
        frame_type = 2 /* same */
        frame_type = 255 /* full_frame */
          offset_delta = 4
          locals = [ class scala/xml/dtd/NotationDecl, class java/lang/Object, int, class java/lang/Object ]
          stack = []
        frame_type = 255 /* full_frame */
          offset_delta = 33
          locals = [ class scala/xml/dtd/NotationDecl, class java/lang/Object, int, class java/lang/Object, class scala/xml/dtd/NotationDecl, class java/lang/String ]
          stack = [ class java/lang/String ]
        frame_type = 7 /* same */
        frame_type = 255 /* full_frame */
          offset_delta = 23
          locals = [ class scala/xml/dtd/NotationDecl, class java/lang/Object, int, class java/lang/Object, class scala/xml/dtd/NotationDecl, class java/lang/String, class scala/xml/dtd/ExternalID ]
          stack = [ class scala/xml/dtd/ExternalID ]
        frame_type = 7 /* same */
        frame_type = 250 /* chop */
          offset_delta = 12
        frame_type = 64 /* same_locals_1_stack_item */
          stack = [ int ]
        frame_type = 255 /* full_frame */
          offset_delta = 2
          locals = [ class scala/xml/dtd/NotationDecl, class java/lang/Object ]
          stack = []
        frame_type = 253 /* append */
          offset_delta = 3
          locals = [ int, class java/lang/Object ]
        frame_type = 255 /* full_frame */
          offset_delta = 0
          locals = [ class scala/xml/dtd/NotationDecl, class java/lang/Object ]
          stack = [ int ]
      LineNumberTable:
        line 99: 0
      LocalVariableTable:
        Start  Length  Slot  Name   Signature
            0     124     0  this   Lscala/xml/dtd/NotationDecl;
            0     124     1   x$1   Ljava/lang/Object;
    MethodParameters:
      Name                           Flags
      x$1                            final

  public scala.xml.dtd.NotationDecl(java.lang.String, scala.xml.dtd.ExternalID);
    descriptor: (Ljava/lang/String;Lscala/xml/dtd/ExternalID;)V
    flags: (0x0001) ACC_PUBLIC
    Code:
      stack=2, locals=3, args_size=3
         0: aload_0
         1: aload_1
         2: putfield      #53                 // Field name:Ljava/lang/String;
         5: aload_0
         6: aload_2
         7: putfield      #56                 // Field extID:Lscala/xml/dtd/ExternalID;
        10: aload_0
        11: invokespecial #134                // Method scala/xml/dtd/MarkupDecl."<init>":()V
        14: aload_0
        15: invokestatic  #138                // InterfaceMethod scala/Product.$init$:(Lscala/Product;)V
        18: return
      LineNumberTable:
        line 99: 0
      LocalVariableTable:
        Start  Length  Slot  Name   Signature
            0      19     0  this   Lscala/xml/dtd/NotationDecl;
            0      19     1  name   Ljava/lang/String;
            0      19     2 extID   Lscala/xml/dtd/ExternalID;
    MethodParameters:
      Name                           Flags
      name                           final
      extID                          final
}
SourceFile: "Decl.scala"
RuntimeVisibleAnnotations:
  0: #10(#11=s#12)
    scala.reflect.ScalaSignature(
      bytes="\u0006\u0005\u00055d\u0001B\r\u001b\u0001\u0006B\u0001B\u000e\u0001\u0003\u0016\u0004%\ta\u000e\u0005\t\u0001\u0002\u0011\t\u0012)A\u0005q!A\u0011\t\u0001BK\u0002\u0013\u0005!\t\u0003\u0005G\u0001\tE\t\u0015!\u0003D\u0011\u00159\u0005\u0001\"\u0001I\u0011\u0015a\u0005\u0001\"\u0011N\u0011\u001d!\u0006!!A\u0005\u0002UCq\u0001\u0017\u0001\u0012\u0002\u0013\u0005\u0011\fC\u0004e\u0001E\u0005I\u0011A3\t\u000f\u001d\u0004\u0011\u0011!C!Q\"9\u0001\u000fAA\u0001\n\u0003\t\bbB;\u0001\u0003\u0003%\tA\u001e\u0005\by\u0002\t\t\u0011\"\u0011~\u0011%\tI\u0001AA\u0001\n\u0003\tY\u0001C\u0005\u0002\u0016\u0001\t\t\u0011\"\u0011\u0002\u0018!I\u00111\u0004\u0001\u0002\u0002\u0013\u0005\u0013Q\u0004\u0005\n\u0003?\u0001\u0011\u0011!C!\u0003C9\u0011\"!\n\u001b\u0003\u0003E\t!a\n\u0007\u0011eQ\u0012\u0011!E\u0001\u0003SAaaR\n\u0005\u0002\u0005\u0005\u0003\"CA\"\'\u0005\u0005IQIA#\u0011%\t9eEA\u0001\n\u0003\u000bI\u0005C\u0005\u0002PM\t\t\u0011\"!\u0002R!I\u00111M\n\u0002\u0002\u0013%\u0011Q\r\u0002\r\u001d>$\u0018\r^5p]\u0012+7\r\u001c\u0006\u00037q\t1\u0001\u001a;e\u0015\tib$A\u0002y[2T\u0011aH\u0001\u0006g\u000e\fG.Y\u0002\u0001\'\u0011\u0001!E\n\u0016\u0011\u0005\r\"S\"\u0001\u000e\n\u0005\u0015R\"AC\'be.,\b\u000fR3dYB\u0011q\u0005K\u0007\u0002=%\u0011\u0011F\b\u0002\b!J|G-^2u!\tY3G\u0004\u0002-c9\u0011Q\u0006M\u0007\u0002])\u0011q\u0006I\u0001\u0007yI|w\u000e\u001e \n\u0003}I!A\r\u0010\u0002\u000fA\f7m[1hK&\u0011A\'\u000e\u0002\r\'\u0016\u0014\u0018.\u00197ju\u0006\u0014G.\u001a\u0006\u0003ey\tAA\\1nKV\t\u0001\b\u0005\u0002:{9\u0011!h\u000f\t\u0003[yI!\u0001\u0010\u0010\u0002\rA\u0013X\rZ3g\u0013\tqtH\u0001\u0004TiJLgn\u001a\u0006\u0003yy\tQA\\1nK\u0002\nQ!\u001a=u\u0013\u0012+\u0012a\u0011\t\u0003G\u0011K!!\u0012\u000e\u0003\u0015\u0015CH/\u001a:oC2LE)\u0001\u0004fqRLE\tI\u0001\u0007y%t\u0017\u000e\u001e \u0015\u0007%S5\n\u0005\u0002$\u0001!)a\'\u0002a\u0001q!)\u0011)\u0002a\u0001\u0007\u0006Y!-^5mIN#(/\u001b8h)\tq%\u000b\u0005\u0002P!:\u0011q%M\u0005\u0003#V\u0012Qb\u0015;sS:<\')^5mI\u0016\u0014\b\"B*\u0007\u0001\u0004q\u0015AA:c\u0003\u0011\u0019w\u000e]=\u0015\u0007%3v\u000bC\u00047\u000fA\u0005\t\u0019\u0001\u001d\t\u000f\u0005;\u0001\u0013!a\u0001\u0007\u0006q1m\u001c9zI\u0011,g-Y;mi\u0012\nT#\u0001.+\u0005aZ6&\u0001/\u0011\u0005u\u0013W\"\u00010\u000b\u0005}\u0003\u0017!C;oG\",7m[3e\u0015\t\tg$\u0001\u0006b]:|G/\u0019;j_:L!a\u00190\u0003#Ut7\r[3dW\u0016$g+\u0019:jC:\u001cW-\u0001\bd_BLH\u0005Z3gCVdG\u000f\n\u001a\u0016\u0003\u0019T#aQ.\u0002\u001bA\u0014x\u000eZ;diB\u0013XMZ5y+\u0005I\u0007C\u00016p\u001b\u0005Y\'B\u00017n\u0003\u0011a\u0017M\\4\u000b\u00039\fAA[1wC&\u0011ah[\u0001\raJ|G-^2u\u0003JLG/_\u000b\u0002eB\u0011qe]\u0005\u0003iz\u00111!\u00138u\u00039\u0001(o\u001c3vGR,E.Z7f]R$\"a\u001e>\u0011\u0005\u001dB\u0018BA=\u001f\u0005\r\te.\u001f\u0005\bw2\t\t\u00111\u0001s\u0003\rAH%M\u0001\u0010aJ|G-^2u\u0013R,\'/\u0019;peV\ta\u0010\u0005\u0003\u0000\u0003\u000b9XBAA\u0001\u0015\r\t\u0019AH\u0001\u000bG>dG.Z2uS>t\u0017\u0002BA\u0004\u0003\u0003\u0011\u0001\"\u0013;fe\u0006$xN]\u0001\tG\u0006tW)];bYR!\u0011QBA\n!\r9\u0013qB\u0005\u0004\u0003#q\"a\u0002\"p_2,\u0017M\u001c\u0005\bw:\t\t\u00111\u0001x\u0003I\u0001(o\u001c3vGR,E.Z7f]Rt\u0015-\\3\u0015\u0007%\fI\u0002C\u0004|\u001f\u0005\u0005\t\u0019\u0001:\u0002\u0011!\f7\u000f[\"pI\u0016$\u0012A]\u0001\u0007KF,\u0018\r\\:\u0015\t\u00055\u00111\u0005\u0005\bwF\t\t\u00111\u0001x\u00031qu\u000e^1uS>tG)Z2m!\t\u00193cE\u0003\u0014\u0003W\t9\u0004E\u0004\u0002.\u0005M\u0002hQ%\u000e\u0005\u0005=\"bAA\u0019=\u00059!/\u001e8uS6,\u0017\u0002BA\u001b\u0003_\u0011\u0011#\u00112tiJ\f7\r\u001e$v]\u000e$\u0018n\u001c83!\u0011\tI$a\u0010\u000e\u0005\u0005m\"bAA\u001f[\u0006\u0011\u0011n\\\u0005\u0004i\u0005mBCAA\u0014\u0003!!xn\u0015;sS:<G#A5\u0002\u000b\u0005\u0004\b\u000f\\=\u0015\u000b%\u000bY%!\u0014\t\u000bY2\u0002\u0019\u0001\u001d\t\u000b\u00053\u0002\u0019A\"\u0002\u000fUt\u0017\r\u001d9msR!\u00111KA0!\u00159\u0013QKA-\u0013\r\t9F\b\u0002\u0007\u001fB$\u0018n\u001c8\u0011\u000b\u001d\nY\u0006O\"\n\u0007\u0005ucD\u0001\u0004UkBdWM\r\u0005\t\u0003C:\u0012\u0011!a\u0001\u0013\u0006\u0019\u0001\u0010\n\u0019\u0002\u0019]\u0014\u0018\u000e^3SKBd\u0017mY3\u0015\u0005\u0005\u001d\u0004c\u00016\u0002j%\u0019\u00111N6\u0003\r=\u0013\'.Z2u\u0001"
    )
  ScalaInlineInfo: length = 0x54 (unknown attribute)
   01 00 00 10 00 51 00 52 00 00 39 00 3A 00 00 71
   00 72 00 00 50 00 1F 00 00 55 00 33 00 00 56 00
   36 00 00 7F 00 72 00 00 0F 00 36 00 00 7A 00 5B
   00 00 0D 00 33 00 00 5A 00 5B 00 00 5C 00 5D 00
   00 74 00 75 00 00 2B 00 2C 00 00 67 00 2C 00 00
   57 00 33 00
  ScalaSig: length = 0x3 (unknown attribute)
   05 02 00
