Classfile /Users/mw/Projects/slang-braindump/.jar/jar11/assemble/slang-braindump/assemble/content/scala/xml/dtd/PEReference.class
  Last modified May 29, 2022; size 5513 bytes
  SHA-256 checksum 1646f4b039ad90cf73c95ca1ae4532ad8a9949a32b9ef734ecde256bbd031ee8
  Compiled from "Decl.scala"
public class scala.xml.dtd.PEReference extends scala.xml.dtd.MarkupDecl implements scala.Product,java.io.Serializable
  minor version: 0
  major version: 52
  flags: (0x0021) ACC_PUBLIC, ACC_SUPER
  this_class: #2                          // scala/xml/dtd/PEReference
  super_class: #4                         // scala/xml/dtd/MarkupDecl
  interfaces: 2, fields: 1, methods: 18, attributes: 4
Constant pool:
    #1 = Utf8               scala/xml/dtd/PEReference
    #2 = Class              #1            // scala/xml/dtd/PEReference
    #3 = Utf8               scala/xml/dtd/MarkupDecl
    #4 = Class              #3            // scala/xml/dtd/MarkupDecl
    #5 = Utf8               scala/Product
    #6 = Class              #5            // scala/Product
    #7 = Utf8               java/io/Serializable
    #8 = Class              #7            // java/io/Serializable
    #9 = Utf8               Decl.scala
   #10 = Utf8               Lscala/reflect/ScalaSignature;
   #11 = Utf8               bytes
   #12 = Utf8               \u0006\u0005\u0005%c\u0001\u0002\f\u0018\u0001zA\u0001b\r\u0001\u0003\u0016\u0004%\t\u0001\u000e\u0005\t{\u0001\u0011\t\u0012)A\u0005k!)a\b\u0001C\u0001\u007f!)!\t\u0001C!\u0007\"9!\nAA\u0001\n\u0003Y\u0005bB\'\u0001#\u0003%\tA\u0014\u0005\b3\u0002\t\t\u0011\"\u0011[\u0011\u001d\u0011\u0007!!A\u0005\u0002\rDqa\u001a\u0001\u0002\u0002\u0013\u0005\u0001\u000eC\u0004o\u0001\u0005\u0005I\u0011I8\t\u000fY\u0004\u0011\u0011!C\u0001o\"9A\u0010AA\u0001\n\u0003j\b\u0002C@\u0001\u0003\u0003%\t%!\u0001\t\u0013\u0005\r\u0001!!A\u0005B\u0005\u0015q!CA\u0005/\u0005\u0005\t\u0012AA\u0006\r!1r#!A\t\u0002\u00055\u0001B\u0002 \u0011\t\u0003\t)\u0003C\u0005\u0002(A\t\t\u0011\"\u0012\u0002*!I\u00111\u0006\t\u0002\u0002\u0013\u0005\u0015Q\u0006\u0005\n\u0003c\u0001\u0012\u0011!CA\u0003gA\u0011\"a\u0010\u0011\u0003\u0003%I!!\u0011\u0003\u0017A+%+\u001a4fe\u0016t7-\u001a\u0006\u00031e\t1\u0001\u001a;e\u0015\tQ2$A\u0002y[2T\u0011\u0001H\u0001\u0006g\u000e\fG.Y\u0002\u0001\'\u0011\u0001qdI\u0014\u0011\u0005\u0001\nS\"A\f\n\u0005\t:\"AC\'be.,\b\u000fR3dYB\u0011A%J\u0007\u00027%\u0011ae\u0007\u0002\b!J|G-^2u!\tA\u0003G\u0004\u0002*]9\u0011!&L\u0007\u0002W)\u0011A&H\u0001\u0007yI|w\u000e\u001e \n\u0003qI!aL\u000e\u0002\u000fA\f7m[1hK&\u0011\u0011G\r\u0002\r\'\u0016\u0014\u0018.\u00197ju\u0006\u0014G.\u001a\u0006\u0003_m\t1!\u001a8u+\u0005)\u0004C\u0001\u001c;\u001d\t9\u0004\b\u0005\u0002+7%\u0011\u0011hG\u0001\u0007!J,G-\u001a4\n\u0005mb$AB*ue&twM\u0003\u0002:7\u0005!QM\u001c;!\u0003\u0019a\u0014N\\5u}Q\u0011\u0001)\u0011\t\u0003A\u0001AQaM\u0002A\u0002U\n1BY;jY\u0012\u001cFO]5oOR\u0011A\t\u0013\t\u0003\u000b\u001as!\u0001\n\u0018\n\u0005\u001d\u0013$!D*ue&twMQ;jY\u0012,\'\u000fC\u0003J\t\u0001\u0007A)\u0001\u0002tE\u0006!1m\u001c9z)\t\u0001E\nC\u00044\u000bA\u0005\t\u0019A\u001b\u0002\u001d\r|\u0007/\u001f\u0013eK\u001a\fW\u000f\u001c;%cU\tqJ\u000b\u00026!.\n\u0011\u000b\u0005\u0002S/6\t1K\u0003\u0002U+\u0006IQO\\2iK\u000e\\W\r\u001a\u0006\u0003-n\t!\"\u00198o_R\fG/[8o\u0013\tA6KA\tv]\u000eDWmY6fIZ\u000b\'/[1oG\u0016\fQ\u0002\u001d:pIV\u001cG\u000f\u0015:fM&DX#A.\u0011\u0005q\u000bW\"A/\u000b\u0005y{\u0016\u0001\u00027b]\u001eT\u0011\u0001Y\u0001\u0005U\u00064\u0018-\u0003\u0002<;\u0006a\u0001O]8ek\u000e$\u0018I]5usV\tA\r\u0005\u0002%K&\u0011am\u0007\u0002\u0004\u0013:$\u0018A\u00049s_\u0012,8\r^#mK6,g\u000e\u001e\u000b\u0003S2\u0004\"\u0001\n6\n\u0005-\\\"aA!os\"9Q.CA\u0001\u0002\u0004!\u0017a\u0001=%c\u0005y\u0001O]8ek\u000e$\u0018\n^3sCR|\'/F\u0001q!\r\tH/[\u0007\u0002e*\u00111oG\u0001\u000bG>dG.Z2uS>t\u0017BA;s\u0005!IE/\u001a:bi>\u0014\u0018\u0001C2b]\u0016\u000bX/\u00197\u0015\u0005a\\\bC\u0001\u0013z\u0013\tQ8DA\u0004C_>dW-\u00198\t\u000f5\\\u0011\u0011!a\u0001S\u0006\u0011\u0002O]8ek\u000e$X\t\\3nK:$h*Y7f)\tYf\u0010C\u0004n\u0019\u0005\u0005\t\u0019\u00013\u0002\u0011!\f7\u000f[\"pI\u0016$\u0012\u0001Z\u0001\u0007KF,\u0018\r\\:\u0015\u0007a\f9\u0001C\u0004n\u001d\u0005\u0005\t\u0019A5\u0002\u0017A+%+\u001a4fe\u0016t7-\u001a\t\u0003AA\u0019R\u0001EA\b\u00037\u0001b!!\u0005\u0002\u0018U\u0002UBAA\n\u0015\r\t)bG\u0001\beVtG/[7f\u0013\u0011\tI\"a\u0005\u0003#\u0005\u00137\u000f\u001e:bGR4UO\\2uS>t\u0017\u0007\u0005\u0003\u0002\u001e\u0005\rRBAA\u0010\u0015\r\t\tcX\u0001\u0003S>L1!MA\u0010)\t\tY!\u0001\u0005u_N#(/\u001b8h)\u0005Y\u0016!B1qa2LHc\u0001!\u00020!)1g\u0005a\u0001k\u00059QO\\1qa2LH\u0003BA\u001b\u0003w\u0001B\u0001JA\u001ck%\u0019\u0011\u0011H\u000e\u0003\r=\u0003H/[8o\u0011!\ti\u0004FA\u0001\u0002\u0004\u0001\u0015a\u0001=%a\u0005aqO]5uKJ+\u0007\u000f\\1dKR\u0011\u00111\t\t\u00049\u0006\u0015\u0013bAA$;\n1qJ\u00196fGR\u0004
   #13 = Utf8               ent
   #14 = Utf8               Ljava/lang/String;
   #15 = Utf8               unapply
   #16 = Utf8               (Lscala/xml/dtd/PEReference;)Lscala/Option;
   #17 = Utf8               (Lscala/xml/dtd/PEReference;)Lscala/Option<Ljava/lang/String;>;
   #18 = Utf8               x$0
   #19 = Utf8               scala/xml/dtd/PEReference$
   #20 = Class              #19           // scala/xml/dtd/PEReference$
   #21 = Utf8               MODULE$
   #22 = Utf8               Lscala/xml/dtd/PEReference$;
   #23 = NameAndType        #21:#22       // MODULE$:Lscala/xml/dtd/PEReference$;
   #24 = Fieldref           #20.#23       // scala/xml/dtd/PEReference$.MODULE$:Lscala/xml/dtd/PEReference$;
   #25 = NameAndType        #15:#16       // unapply:(Lscala/xml/dtd/PEReference;)Lscala/Option;
   #26 = Methodref          #20.#25       // scala/xml/dtd/PEReference$.unapply:(Lscala/xml/dtd/PEReference;)Lscala/Option;
   #27 = Utf8               Lscala/xml/dtd/PEReference;
   #28 = Utf8               apply
   #29 = Utf8               (Ljava/lang/String;)Lscala/xml/dtd/PEReference;
   #30 = NameAndType        #28:#29       // apply:(Ljava/lang/String;)Lscala/xml/dtd/PEReference;
   #31 = Methodref          #20.#30       // scala/xml/dtd/PEReference$.apply:(Ljava/lang/String;)Lscala/xml/dtd/PEReference;
   #32 = Utf8               andThen
   #33 = Utf8               (Lscala/Function1;)Lscala/Function1;
   #34 = Utf8               <A$:Ljava/lang/Object;>(Lscala/Function1<Lscala/xml/dtd/PEReference;TA$;>;)Lscala/Function1<Ljava/lang/String;TA$;>;
   #35 = Utf8               g
   #36 = NameAndType        #32:#33       // andThen:(Lscala/Function1;)Lscala/Function1;
   #37 = Methodref          #20.#36       // scala/xml/dtd/PEReference$.andThen:(Lscala/Function1;)Lscala/Function1;
   #38 = Utf8               Lscala/Function1;
   #39 = Utf8               compose
   #40 = Utf8               <A$:Ljava/lang/Object;>(Lscala/Function1<TA$;Ljava/lang/String;>;)Lscala/Function1<TA$;Lscala/xml/dtd/PEReference;>;
   #41 = NameAndType        #39:#33       // compose:(Lscala/Function1;)Lscala/Function1;
   #42 = Methodref          #20.#41       // scala/xml/dtd/PEReference$.compose:(Lscala/Function1;)Lscala/Function1;
   #43 = Utf8               productElementNames
   #44 = Utf8               ()Lscala/collection/Iterator;
   #45 = Utf8               ()Lscala/collection/Iterator<Ljava/lang/String;>;
   #46 = Utf8               productElementNames$
   #47 = Utf8               (Lscala/Product;)Lscala/collection/Iterator;
   #48 = NameAndType        #46:#47       // productElementNames$:(Lscala/Product;)Lscala/collection/Iterator;
   #49 = InterfaceMethodref #6.#48        // scala/Product.productElementNames$:(Lscala/Product;)Lscala/collection/Iterator;
   #50 = Utf8               this
   #51 = Utf8               ()Ljava/lang/String;
   #52 = NameAndType        #13:#14       // ent:Ljava/lang/String;
   #53 = Fieldref           #2.#52        // scala/xml/dtd/PEReference.ent:Ljava/lang/String;
   #54 = Utf8               buildString
   #55 = Utf8               (Lscala/collection/mutable/StringBuilder;)Lscala/collection/mutable/StringBuilder;
   #56 = Utf8               sb
   #57 = Utf8               scala/collection/mutable/StringBuilder
   #58 = Class              #57           // scala/collection/mutable/StringBuilder
   #59 = Utf8               append
   #60 = Utf8               (C)Lscala/collection/mutable/StringBuilder;
   #61 = NameAndType        #59:#60       // append:(C)Lscala/collection/mutable/StringBuilder;
   #62 = Methodref          #58.#61       // scala/collection/mutable/StringBuilder.append:(C)Lscala/collection/mutable/StringBuilder;
   #63 = NameAndType        #13:#51       // ent:()Ljava/lang/String;
   #64 = Methodref          #2.#63        // scala/xml/dtd/PEReference.ent:()Ljava/lang/String;
   #65 = Utf8               (Ljava/lang/String;)Lscala/collection/mutable/StringBuilder;
   #66 = NameAndType        #59:#65       // append:(Ljava/lang/String;)Lscala/collection/mutable/StringBuilder;
   #67 = Methodref          #58.#66       // scala/collection/mutable/StringBuilder.append:(Ljava/lang/String;)Lscala/collection/mutable/StringBuilder;
   #68 = Utf8               Lscala/collection/mutable/StringBuilder;
   #69 = Utf8               copy
   #70 = Utf8               <init>
   #71 = Utf8               (Ljava/lang/String;)V
   #72 = NameAndType        #70:#71       // "<init>":(Ljava/lang/String;)V
   #73 = Methodref          #2.#72        // scala/xml/dtd/PEReference."<init>":(Ljava/lang/String;)V
   #74 = Utf8               copy$default$1
   #75 = Utf8               productPrefix
   #76 = Utf8               PEReference
   #77 = String             #76           // PEReference
   #78 = Utf8               productArity
   #79 = Utf8               ()I
   #80 = Utf8               productElement
   #81 = Utf8               (I)Ljava/lang/Object;
   #82 = Utf8               x$1
   #83 = Utf8               scala/runtime/Statics
   #84 = Class              #83           // scala/runtime/Statics
   #85 = Utf8               ioobe
   #86 = NameAndType        #85:#81       // ioobe:(I)Ljava/lang/Object;
   #87 = Methodref          #84.#86       // scala/runtime/Statics.ioobe:(I)Ljava/lang/Object;
   #88 = Utf8               I
   #89 = Utf8               java/lang/Object
   #90 = Class              #89           // java/lang/Object
   #91 = Utf8               productIterator
   #92 = Utf8               ()Lscala/collection/Iterator<Ljava/lang/Object;>;
   #93 = Utf8               scala/runtime/ScalaRunTime$
   #94 = Class              #93           // scala/runtime/ScalaRunTime$
   #95 = Utf8               Lscala/runtime/ScalaRunTime$;
   #96 = NameAndType        #21:#95       // MODULE$:Lscala/runtime/ScalaRunTime$;
   #97 = Fieldref           #94.#96       // scala/runtime/ScalaRunTime$.MODULE$:Lscala/runtime/ScalaRunTime$;
   #98 = Utf8               typedProductIterator
   #99 = NameAndType        #98:#47       // typedProductIterator:(Lscala/Product;)Lscala/collection/Iterator;
  #100 = Methodref          #94.#99       // scala/runtime/ScalaRunTime$.typedProductIterator:(Lscala/Product;)Lscala/collection/Iterator;
  #101 = Utf8               canEqual
  #102 = Utf8               (Ljava/lang/Object;)Z
  #103 = Utf8               Ljava/lang/Object;
  #104 = Utf8               productElementName
  #105 = Utf8               (I)Ljava/lang/String;
  #106 = String             #13           // ent
  #107 = Utf8               java/lang/String
  #108 = Class              #107          // java/lang/String
  #109 = Utf8               hashCode
  #110 = Utf8               _hashCode
  #111 = Utf8               (Lscala/Product;)I
  #112 = NameAndType        #110:#111     // _hashCode:(Lscala/Product;)I
  #113 = Methodref          #94.#112      // scala/runtime/ScalaRunTime$._hashCode:(Lscala/Product;)I
  #114 = Utf8               equals
  #115 = NameAndType        #114:#102     // equals:(Ljava/lang/Object;)Z
  #116 = Methodref          #90.#115      // java/lang/Object.equals:(Ljava/lang/Object;)Z
  #117 = NameAndType        #101:#102     // canEqual:(Ljava/lang/Object;)Z
  #118 = Methodref          #2.#117       // scala/xml/dtd/PEReference.canEqual:(Ljava/lang/Object;)Z
  #119 = Utf8               ()V
  #120 = NameAndType        #70:#119      // "<init>":()V
  #121 = Methodref          #4.#120       // scala/xml/dtd/MarkupDecl."<init>":()V
  #122 = Utf8               $init$
  #123 = Utf8               (Lscala/Product;)V
  #124 = NameAndType        #122:#123     // $init$:(Lscala/Product;)V
  #125 = InterfaceMethodref #6.#124       // scala/Product.$init$:(Lscala/Product;)V
  #126 = Utf8               scala/xml/Utility$
  #127 = Class              #126          // scala/xml/Utility$
  #128 = Utf8               Lscala/xml/Utility$;
  #129 = NameAndType        #21:#128      // MODULE$:Lscala/xml/Utility$;
  #130 = Fieldref           #127.#129     // scala/xml/Utility$.MODULE$:Lscala/xml/Utility$;
  #131 = Utf8               isName
  #132 = Utf8               (Ljava/lang/String;)Z
  #133 = NameAndType        #131:#132     // isName:(Ljava/lang/String;)Z
  #134 = Methodref          #127.#133     // scala/xml/Utility$.isName:(Ljava/lang/String;)Z
  #135 = Utf8               java/lang/IllegalArgumentException
  #136 = Class              #135          // java/lang/IllegalArgumentException
  #137 = Utf8               ent must be an XML Name
  #138 = String             #137          // ent must be an XML Name
  #139 = Methodref          #136.#72      // java/lang/IllegalArgumentException."<init>":(Ljava/lang/String;)V
  #140 = Utf8               Code
  #141 = Utf8               LocalVariableTable
  #142 = Utf8               Signature
  #143 = Utf8               MethodParameters
  #144 = Utf8               LineNumberTable
  #145 = Utf8               StackMapTable
  #146 = Utf8               SourceFile
  #147 = Utf8               RuntimeVisibleAnnotations
  #148 = Utf8               ScalaInlineInfo
  #149 = Utf8               ScalaSig
{
  private final java.lang.String ent;
    descriptor: Ljava/lang/String;
    flags: (0x0012) ACC_PRIVATE, ACC_FINAL

  public static scala.Option<java.lang.String> unapply(scala.xml.dtd.PEReference);
    descriptor: (Lscala/xml/dtd/PEReference;)Lscala/Option;
    flags: (0x0009) ACC_PUBLIC, ACC_STATIC
    Code:
      stack=2, locals=1, args_size=1
         0: getstatic     #24                 // Field scala/xml/dtd/PEReference$.MODULE$:Lscala/xml/dtd/PEReference$;
         3: aload_0
         4: invokevirtual #26                 // Method scala/xml/dtd/PEReference$.unapply:(Lscala/xml/dtd/PEReference;)Lscala/Option;
         7: areturn
      LocalVariableTable:
        Start  Length  Slot  Name   Signature
            0       8     0   x$0   Lscala/xml/dtd/PEReference;
    Signature: #17                          // (Lscala/xml/dtd/PEReference;)Lscala/Option<Ljava/lang/String;>;
    MethodParameters:
      Name                           Flags
      x$0                            final

  public static scala.xml.dtd.PEReference apply(java.lang.String);
    descriptor: (Ljava/lang/String;)Lscala/xml/dtd/PEReference;
    flags: (0x0009) ACC_PUBLIC, ACC_STATIC
    Code:
      stack=2, locals=1, args_size=1
         0: getstatic     #24                 // Field scala/xml/dtd/PEReference$.MODULE$:Lscala/xml/dtd/PEReference$;
         3: aload_0
         4: invokevirtual #31                 // Method scala/xml/dtd/PEReference$.apply:(Ljava/lang/String;)Lscala/xml/dtd/PEReference;
         7: areturn
      LocalVariableTable:
        Start  Length  Slot  Name   Signature
            0       8     0   ent   Ljava/lang/String;
    MethodParameters:
      Name                           Flags
      ent                            final

  public static <A$ extends java.lang.Object> scala.Function1<java.lang.String, A$> andThen(scala.Function1<scala.xml.dtd.PEReference, A$>);
    descriptor: (Lscala/Function1;)Lscala/Function1;
    flags: (0x0009) ACC_PUBLIC, ACC_STATIC
    Code:
      stack=2, locals=1, args_size=1
         0: getstatic     #24                 // Field scala/xml/dtd/PEReference$.MODULE$:Lscala/xml/dtd/PEReference$;
         3: aload_0
         4: invokevirtual #37                 // Method scala/xml/dtd/PEReference$.andThen:(Lscala/Function1;)Lscala/Function1;
         7: areturn
      LocalVariableTable:
        Start  Length  Slot  Name   Signature
            0       8     0     g   Lscala/Function1;
    Signature: #34                          // <A$:Ljava/lang/Object;>(Lscala/Function1<Lscala/xml/dtd/PEReference;TA$;>;)Lscala/Function1<Ljava/lang/String;TA$;>;
    MethodParameters:
      Name                           Flags
      g                              final

  public static <A$ extends java.lang.Object> scala.Function1<A$, scala.xml.dtd.PEReference> compose(scala.Function1<A$, java.lang.String>);
    descriptor: (Lscala/Function1;)Lscala/Function1;
    flags: (0x0009) ACC_PUBLIC, ACC_STATIC
    Code:
      stack=2, locals=1, args_size=1
         0: getstatic     #24                 // Field scala/xml/dtd/PEReference$.MODULE$:Lscala/xml/dtd/PEReference$;
         3: aload_0
         4: invokevirtual #42                 // Method scala/xml/dtd/PEReference$.compose:(Lscala/Function1;)Lscala/Function1;
         7: areturn
      LocalVariableTable:
        Start  Length  Slot  Name   Signature
            0       8     0     g   Lscala/Function1;
    Signature: #40                          // <A$:Ljava/lang/Object;>(Lscala/Function1<TA$;Ljava/lang/String;>;)Lscala/Function1<TA$;Lscala/xml/dtd/PEReference;>;
    MethodParameters:
      Name                           Flags
      g                              final

  public scala.collection.Iterator<java.lang.String> productElementNames();
    descriptor: ()Lscala/collection/Iterator;
    flags: (0x0001) ACC_PUBLIC
    Code:
      stack=1, locals=1, args_size=1
         0: aload_0
         1: invokestatic  #49                 // InterfaceMethod scala/Product.productElementNames$:(Lscala/Product;)Lscala/collection/Iterator;
         4: areturn
      LineNumberTable:
        line 142: 0
      LocalVariableTable:
        Start  Length  Slot  Name   Signature
            0       5     0  this   Lscala/xml/dtd/PEReference;
    Signature: #45                          // ()Lscala/collection/Iterator<Ljava/lang/String;>;

  public java.lang.String ent();
    descriptor: ()Ljava/lang/String;
    flags: (0x0001) ACC_PUBLIC
    Code:
      stack=1, locals=1, args_size=1
         0: aload_0
         1: getfield      #53                 // Field ent:Ljava/lang/String;
         4: areturn
      LineNumberTable:
        line 142: 0
      LocalVariableTable:
        Start  Length  Slot  Name   Signature
            0       5     0  this   Lscala/xml/dtd/PEReference;

  public scala.collection.mutable.StringBuilder buildString(scala.collection.mutable.StringBuilder);
    descriptor: (Lscala/collection/mutable/StringBuilder;)Lscala/collection/mutable/StringBuilder;
    flags: (0x0001) ACC_PUBLIC
    Code:
      stack=2, locals=2, args_size=2
         0: aload_1
         1: bipush        37
         3: invokevirtual #62                 // Method scala/collection/mutable/StringBuilder.append:(C)Lscala/collection/mutable/StringBuilder;
         6: aload_0
         7: invokevirtual #64                 // Method ent:()Ljava/lang/String;
        10: invokevirtual #67                 // Method scala/collection/mutable/StringBuilder.append:(Ljava/lang/String;)Lscala/collection/mutable/StringBuilder;
        13: bipush        59
        15: invokevirtual #62                 // Method scala/collection/mutable/StringBuilder.append:(C)Lscala/collection/mutable/StringBuilder;
        18: areturn
      LineNumberTable:
        line 147: 0
      LocalVariableTable:
        Start  Length  Slot  Name   Signature
            0      19     0  this   Lscala/xml/dtd/PEReference;
            0      19     1    sb   Lscala/collection/mutable/StringBuilder;
    MethodParameters:
      Name                           Flags
      sb                             final

  public scala.xml.dtd.PEReference copy(java.lang.String);
    descriptor: (Ljava/lang/String;)Lscala/xml/dtd/PEReference;
    flags: (0x0001) ACC_PUBLIC
    Code:
      stack=3, locals=2, args_size=2
         0: new           #2                  // class scala/xml/dtd/PEReference
         3: dup
         4: aload_1
         5: invokespecial #73                 // Method "<init>":(Ljava/lang/String;)V
         8: areturn
      LineNumberTable:
        line 142: 0
      LocalVariableTable:
        Start  Length  Slot  Name   Signature
            0       9     0  this   Lscala/xml/dtd/PEReference;
            0       9     1   ent   Ljava/lang/String;
    MethodParameters:
      Name                           Flags
      ent                            final

  public java.lang.String copy$default$1();
    descriptor: ()Ljava/lang/String;
    flags: (0x0001) ACC_PUBLIC
    Code:
      stack=1, locals=1, args_size=1
         0: aload_0
         1: invokevirtual #64                 // Method ent:()Ljava/lang/String;
         4: areturn
      LineNumberTable:
        line 142: 0
      LocalVariableTable:
        Start  Length  Slot  Name   Signature
            0       5     0  this   Lscala/xml/dtd/PEReference;

  public java.lang.String productPrefix();
    descriptor: ()Ljava/lang/String;
    flags: (0x0001) ACC_PUBLIC
    Code:
      stack=1, locals=1, args_size=1
         0: ldc           #77                 // String PEReference
         2: areturn
      LineNumberTable:
        line 142: 0
      LocalVariableTable:
        Start  Length  Slot  Name   Signature
            0       3     0  this   Lscala/xml/dtd/PEReference;

  public int productArity();
    descriptor: ()I
    flags: (0x0001) ACC_PUBLIC
    Code:
      stack=1, locals=1, args_size=1
         0: iconst_1
         1: ireturn
      LineNumberTable:
        line 142: 0
      LocalVariableTable:
        Start  Length  Slot  Name   Signature
            0       2     0  this   Lscala/xml/dtd/PEReference;

  public java.lang.Object productElement(int);
    descriptor: (I)Ljava/lang/Object;
    flags: (0x0001) ACC_PUBLIC
    Code:
      stack=1, locals=3, args_size=2
         0: iload_1
         1: istore_2
         2: iload_2
         3: tableswitch   { // 0 to 0
                       0: 20
                 default: 27
            }
        20: aload_0
        21: invokevirtual #64                 // Method ent:()Ljava/lang/String;
        24: goto          34
        27: iload_1
        28: invokestatic  #87                 // Method scala/runtime/Statics.ioobe:(I)Ljava/lang/Object;
        31: goto          34
        34: areturn
      StackMapTable: number_of_entries = 3
        frame_type = 252 /* append */
          offset_delta = 20
          locals = [ int ]
        frame_type = 6 /* same */
        frame_type = 70 /* same_locals_1_stack_item */
          stack = [ class java/lang/Object ]
      LineNumberTable:
        line 142: 0
      LocalVariableTable:
        Start  Length  Slot  Name   Signature
            0      35     0  this   Lscala/xml/dtd/PEReference;
            0      35     1   x$1   I
    MethodParameters:
      Name                           Flags
      x$1                            final

  public scala.collection.Iterator<java.lang.Object> productIterator();
    descriptor: ()Lscala/collection/Iterator;
    flags: (0x0001) ACC_PUBLIC
    Code:
      stack=2, locals=1, args_size=1
         0: getstatic     #97                 // Field scala/runtime/ScalaRunTime$.MODULE$:Lscala/runtime/ScalaRunTime$;
         3: aload_0
         4: invokevirtual #100                // Method scala/runtime/ScalaRunTime$.typedProductIterator:(Lscala/Product;)Lscala/collection/Iterator;
         7: areturn
      LineNumberTable:
        line 142: 0
      LocalVariableTable:
        Start  Length  Slot  Name   Signature
            0       8     0  this   Lscala/xml/dtd/PEReference;
    Signature: #92                          // ()Lscala/collection/Iterator<Ljava/lang/Object;>;

  public boolean canEqual(java.lang.Object);
    descriptor: (Ljava/lang/Object;)Z
    flags: (0x0001) ACC_PUBLIC
    Code:
      stack=1, locals=2, args_size=2
         0: aload_1
         1: instanceof    #2                  // class scala/xml/dtd/PEReference
         4: ireturn
      LineNumberTable:
        line 142: 0
      LocalVariableTable:
        Start  Length  Slot  Name   Signature
            0       5     0  this   Lscala/xml/dtd/PEReference;
            0       5     1   x$1   Ljava/lang/Object;
    MethodParameters:
      Name                           Flags
      x$1                            final

  public java.lang.String productElementName(int);
    descriptor: (I)Ljava/lang/String;
    flags: (0x0001) ACC_PUBLIC
    Code:
      stack=1, locals=3, args_size=2
         0: iload_1
         1: istore_2
         2: iload_2
         3: tableswitch   { // 0 to 0
                       0: 20
                 default: 25
            }
        20: ldc           #106                // String ent
        22: goto          35
        25: iload_1
        26: invokestatic  #87                 // Method scala/runtime/Statics.ioobe:(I)Ljava/lang/Object;
        29: checkcast     #108                // class java/lang/String
        32: goto          35
        35: areturn
      StackMapTable: number_of_entries = 3
        frame_type = 252 /* append */
          offset_delta = 20
          locals = [ int ]
        frame_type = 4 /* same */
        frame_type = 73 /* same_locals_1_stack_item */
          stack = [ class java/lang/String ]
      LineNumberTable:
        line 142: 0
      LocalVariableTable:
        Start  Length  Slot  Name   Signature
            0      36     0  this   Lscala/xml/dtd/PEReference;
            0      36     1   x$1   I
    MethodParameters:
      Name                           Flags
      x$1                            final

  public int hashCode();
    descriptor: ()I
    flags: (0x0001) ACC_PUBLIC
    Code:
      stack=2, locals=1, args_size=1
         0: getstatic     #97                 // Field scala/runtime/ScalaRunTime$.MODULE$:Lscala/runtime/ScalaRunTime$;
         3: aload_0
         4: invokevirtual #113                // Method scala/runtime/ScalaRunTime$._hashCode:(Lscala/Product;)I
         7: ireturn
      LineNumberTable:
        line 142: 0
      LocalVariableTable:
        Start  Length  Slot  Name   Signature
            0       8     0  this   Lscala/xml/dtd/PEReference;

  public boolean equals(java.lang.Object);
    descriptor: (Ljava/lang/Object;)Z
    flags: (0x0001) ACC_PUBLIC
    Code:
      stack=2, locals=6, args_size=2
         0: aload_0
         1: aload_1
         2: if_acmpeq     86
         5: aload_1
         6: astore_3
         7: aload_3
         8: instanceof    #2                  // class scala/xml/dtd/PEReference
        11: ifeq          19
        14: iconst_1
        15: istore_2
        16: goto          27
        19: goto          22
        22: iconst_0
        23: istore_2
        24: goto          27
        27: iload_2
        28: ifeq          90
        31: aload_1
        32: checkcast     #2                  // class scala/xml/dtd/PEReference
        35: astore        4
        37: aload_0
        38: invokevirtual #64                 // Method ent:()Ljava/lang/String;
        41: aload         4
        43: invokevirtual #64                 // Method ent:()Ljava/lang/String;
        46: astore        5
        48: dup
        49: ifnonnull     61
        52: pop
        53: aload         5
        55: ifnull        69
        58: goto          82
        61: aload         5
        63: invokevirtual #116                // Method java/lang/Object.equals:(Ljava/lang/Object;)Z
        66: ifeq          82
        69: aload         4
        71: aload_0
        72: invokevirtual #118                // Method canEqual:(Ljava/lang/Object;)Z
        75: ifeq          82
        78: iconst_1
        79: goto          83
        82: iconst_0
        83: ifeq          90
        86: iconst_1
        87: goto          91
        90: iconst_0
        91: ireturn
      StackMapTable: number_of_entries = 10
        frame_type = 253 /* append */
          offset_delta = 19
          locals = [ top, class java/lang/Object ]
        frame_type = 2 /* same */
        frame_type = 255 /* full_frame */
          offset_delta = 4
          locals = [ class scala/xml/dtd/PEReference, class java/lang/Object, int, class java/lang/Object ]
          stack = []
        frame_type = 255 /* full_frame */
          offset_delta = 33
          locals = [ class scala/xml/dtd/PEReference, class java/lang/Object, int, class java/lang/Object, class scala/xml/dtd/PEReference, class java/lang/String ]
          stack = [ class java/lang/String ]
        frame_type = 7 /* same */
        frame_type = 12 /* same */
        frame_type = 64 /* same_locals_1_stack_item */
          stack = [ int ]
        frame_type = 255 /* full_frame */
          offset_delta = 2
          locals = [ class scala/xml/dtd/PEReference, class java/lang/Object ]
          stack = []
        frame_type = 253 /* append */
          offset_delta = 3
          locals = [ int, class java/lang/Object ]
        frame_type = 255 /* full_frame */
          offset_delta = 0
          locals = [ class scala/xml/dtd/PEReference, class java/lang/Object ]
          stack = [ int ]
      LineNumberTable:
        line 142: 0
      LocalVariableTable:
        Start  Length  Slot  Name   Signature
            0      92     0  this   Lscala/xml/dtd/PEReference;
            0      92     1   x$1   Ljava/lang/Object;
    MethodParameters:
      Name                           Flags
      x$1                            final

  public scala.xml.dtd.PEReference(java.lang.String);
    descriptor: (Ljava/lang/String;)V
    flags: (0x0001) ACC_PUBLIC
    Code:
      stack=3, locals=2, args_size=2
         0: aload_0
         1: aload_1
         2: putfield      #53                 // Field ent:Ljava/lang/String;
         5: aload_0
         6: invokespecial #121                // Method scala/xml/dtd/MarkupDecl."<init>":()V
         9: aload_0
        10: invokestatic  #125                // InterfaceMethod scala/Product.$init$:(Lscala/Product;)V
        13: getstatic     #130                // Field scala/xml/Utility$.MODULE$:Lscala/xml/Utility$;
        16: aload_1
        17: invokevirtual #134                // Method scala/xml/Utility$.isName:(Ljava/lang/String;)Z
        20: ifne          33
        23: new           #136                // class java/lang/IllegalArgumentException
        26: dup
        27: ldc           #138                // String ent must be an XML Name
        29: invokespecial #139                // Method java/lang/IllegalArgumentException."<init>":(Ljava/lang/String;)V
        32: athrow
        33: return
      StackMapTable: number_of_entries = 1
        frame_type = 255 /* full_frame */
          offset_delta = 33
          locals = [ class scala/xml/dtd/PEReference, class java/lang/String ]
          stack = []
      LineNumberTable:
        line 142: 0
        line 143: 13
        line 144: 23
        line 142: 33
      LocalVariableTable:
        Start  Length  Slot  Name   Signature
            0      34     0  this   Lscala/xml/dtd/PEReference;
            0      34     1   ent   Ljava/lang/String;
    MethodParameters:
      Name                           Flags
      ent                            final
}
SourceFile: "Decl.scala"
RuntimeVisibleAnnotations:
  0: #10(#11=s#12)
    scala.reflect.ScalaSignature(
      bytes="\u0006\u0005\u0005%c\u0001\u0002\f\u0018\u0001zA\u0001b\r\u0001\u0003\u0016\u0004%\t\u0001\u000e\u0005\t{\u0001\u0011\t\u0012)A\u0005k!)a\b\u0001C\u0001\u007f!)!\t\u0001C!\u0007\"9!\nAA\u0001\n\u0003Y\u0005bB\'\u0001#\u0003%\tA\u0014\u0005\b3\u0002\t\t\u0011\"\u0011[\u0011\u001d\u0011\u0007!!A\u0005\u0002\rDqa\u001a\u0001\u0002\u0002\u0013\u0005\u0001\u000eC\u0004o\u0001\u0005\u0005I\u0011I8\t\u000fY\u0004\u0011\u0011!C\u0001o\"9A\u0010AA\u0001\n\u0003j\b\u0002C@\u0001\u0003\u0003%\t%!\u0001\t\u0013\u0005\r\u0001!!A\u0005B\u0005\u0015q!CA\u0005/\u0005\u0005\t\u0012AA\u0006\r!1r#!A\t\u0002\u00055\u0001B\u0002 \u0011\t\u0003\t)\u0003C\u0005\u0002(A\t\t\u0011\"\u0012\u0002*!I\u00111\u0006\t\u0002\u0002\u0013\u0005\u0015Q\u0006\u0005\n\u0003c\u0001\u0012\u0011!CA\u0003gA\u0011\"a\u0010\u0011\u0003\u0003%I!!\u0011\u0003\u0017A+%+\u001a4fe\u0016t7-\u001a\u0006\u00031e\t1\u0001\u001a;e\u0015\tQ2$A\u0002y[2T\u0011\u0001H\u0001\u0006g\u000e\fG.Y\u0002\u0001\'\u0011\u0001qdI\u0014\u0011\u0005\u0001\nS\"A\f\n\u0005\t:\"AC\'be.,\b\u000fR3dYB\u0011A%J\u0007\u00027%\u0011ae\u0007\u0002\b!J|G-^2u!\tA\u0003G\u0004\u0002*]9\u0011!&L\u0007\u0002W)\u0011A&H\u0001\u0007yI|w\u000e\u001e \n\u0003qI!aL\u000e\u0002\u000fA\f7m[1hK&\u0011\u0011G\r\u0002\r\'\u0016\u0014\u0018.\u00197ju\u0006\u0014G.\u001a\u0006\u0003_m\t1!\u001a8u+\u0005)\u0004C\u0001\u001c;\u001d\t9\u0004\b\u0005\u0002+7%\u0011\u0011hG\u0001\u0007!J,G-\u001a4\n\u0005mb$AB*ue&twM\u0003\u0002:7\u0005!QM\u001c;!\u0003\u0019a\u0014N\\5u}Q\u0011\u0001)\u0011\t\u0003A\u0001AQaM\u0002A\u0002U\n1BY;jY\u0012\u001cFO]5oOR\u0011A\t\u0013\t\u0003\u000b\u001as!\u0001\n\u0018\n\u0005\u001d\u0013$!D*ue&twMQ;jY\u0012,\'\u000fC\u0003J\t\u0001\u0007A)\u0001\u0002tE\u0006!1m\u001c9z)\t\u0001E\nC\u00044\u000bA\u0005\t\u0019A\u001b\u0002\u001d\r|\u0007/\u001f\u0013eK\u001a\fW\u000f\u001c;%cU\tqJ\u000b\u00026!.\n\u0011\u000b\u0005\u0002S/6\t1K\u0003\u0002U+\u0006IQO\\2iK\u000e\\W\r\u001a\u0006\u0003-n\t!\"\u00198o_R\fG/[8o\u0013\tA6KA\tv]\u000eDWmY6fIZ\u000b\'/[1oG\u0016\fQ\u0002\u001d:pIV\u001cG\u000f\u0015:fM&DX#A.\u0011\u0005q\u000bW\"A/\u000b\u0005y{\u0016\u0001\u00027b]\u001eT\u0011\u0001Y\u0001\u0005U\u00064\u0018-\u0003\u0002<;\u0006a\u0001O]8ek\u000e$\u0018I]5usV\tA\r\u0005\u0002%K&\u0011am\u0007\u0002\u0004\u0013:$\u0018A\u00049s_\u0012,8\r^#mK6,g\u000e\u001e\u000b\u0003S2\u0004\"\u0001\n6\n\u0005-\\\"aA!os\"9Q.CA\u0001\u0002\u0004!\u0017a\u0001=%c\u0005y\u0001O]8ek\u000e$\u0018\n^3sCR|\'/F\u0001q!\r\tH/[\u0007\u0002e*\u00111oG\u0001\u000bG>dG.Z2uS>t\u0017BA;s\u0005!IE/\u001a:bi>\u0014\u0018\u0001C2b]\u0016\u000bX/\u00197\u0015\u0005a\\\bC\u0001\u0013z\u0013\tQ8DA\u0004C_>dW-\u00198\t\u000f5\\\u0011\u0011!a\u0001S\u0006\u0011\u0002O]8ek\u000e$X\t\\3nK:$h*Y7f)\tYf\u0010C\u0004n\u0019\u0005\u0005\t\u0019\u00013\u0002\u0011!\f7\u000f[\"pI\u0016$\u0012\u0001Z\u0001\u0007KF,\u0018\r\\:\u0015\u0007a\f9\u0001C\u0004n\u001d\u0005\u0005\t\u0019A5\u0002\u0017A+%+\u001a4fe\u0016t7-\u001a\t\u0003AA\u0019R\u0001EA\b\u00037\u0001b!!\u0005\u0002\u0018U\u0002UBAA\n\u0015\r\t)bG\u0001\beVtG/[7f\u0013\u0011\tI\"a\u0005\u0003#\u0005\u00137\u000f\u001e:bGR4UO\\2uS>t\u0017\u0007\u0005\u0003\u0002\u001e\u0005\rRBAA\u0010\u0015\r\t\tcX\u0001\u0003S>L1!MA\u0010)\t\tY!\u0001\u0005u_N#(/\u001b8h)\u0005Y\u0016!B1qa2LHc\u0001!\u00020!)1g\u0005a\u0001k\u00059QO\\1qa2LH\u0003BA\u001b\u0003w\u0001B\u0001JA\u001ck%\u0019\u0011\u0011H\u000e\u0003\r=\u0003H/[8o\u0011!\ti\u0004FA\u0001\u0002\u0004\u0001\u0015a\u0001=%a\u0005aqO]5uKJ+\u0007\u000f\\1dKR\u0011\u00111\t\t\u00049\u0006\u0015\u0013bAA$;\n1qJ\u00196fGR\u0004"
    )
  ScalaInlineInfo: length = 0x4A (unknown attribute)
   01 00 00 0E 00 46 00 47 00 00 36 00 37 00 00 65
   00 66 00 00 45 00 1D 00 00 4A 00 33 00 00 0D 00
   33 00 00 72 00 66 00 00 6D 00 4F 00 00 4E 00 4F
   00 00 50 00 51 00 00 68 00 69 00 00 2B 00 2C 00
   00 5B 00 2C 00 00 4B 00 33 00
  ScalaSig: length = 0x3 (unknown attribute)
   05 02 00
