Classfile /Users/mw/Projects/slang-braindump/.jar/jar8/assemble/slang-braindump/assemble/content/com/fasterxml/jackson/databind/ser/std/BeanSerializerBase.class
  Last modified May 29, 2022; size 32979 bytes
  SHA-256 checksum 92c6dd032ff3f4495f7f34af92a662afe093609fe0956d2679af093314cfddca
  Compiled from "BeanSerializerBase.java"
public abstract class com.fasterxml.jackson.databind.ser.std.BeanSerializerBase extends com.fasterxml.jackson.databind.ser.std.StdSerializer<java.lang.Object> implements com.fasterxml.jackson.databind.ser.ContextualSerializer, com.fasterxml.jackson.databind.ser.ResolvableSerializer, com.fasterxml.jackson.databind.jsonFormatVisitors.JsonFormatVisitable, com.fasterxml.jackson.databind.jsonschema.SchemaAware
  minor version: 0
  major version: 52
  flags: (0x0421) ACC_PUBLIC, ACC_SUPER, ACC_ABSTRACT
  this_class: #189                        // com/fasterxml/jackson/databind/ser/std/BeanSerializerBase
  super_class: #190                       // com/fasterxml/jackson/databind/ser/std/StdSerializer
  interfaces: 4, fields: 10, methods: 35, attributes: 3
Constant pool:
    #1 = Methodref          #190.#446     // com/fasterxml/jackson/databind/ser/std/StdSerializer."<init>":(Lcom/fasterxml/jackson/databind/JavaType;)V
    #2 = Fieldref           #189.#447     // com/fasterxml/jackson/databind/ser/std/BeanSerializerBase._beanType:Lcom/fasterxml/jackson/databind/JavaType;
    #3 = Fieldref           #189.#448     // com/fasterxml/jackson/databind/ser/std/BeanSerializerBase._props:[Lcom/fasterxml/jackson/databind/ser/BeanPropertyWriter;
    #4 = Fieldref           #189.#449     // com/fasterxml/jackson/databind/ser/std/BeanSerializerBase._filteredProps:[Lcom/fasterxml/jackson/databind/ser/BeanPropertyWriter;
    #5 = Fieldref           #189.#450     // com/fasterxml/jackson/databind/ser/std/BeanSerializerBase._typeId:Lcom/fasterxml/jackson/databind/introspect/AnnotatedMember;
    #6 = Fieldref           #189.#451     // com/fasterxml/jackson/databind/ser/std/BeanSerializerBase._anyGetterWriter:Lcom/fasterxml/jackson/databind/ser/AnyGetterWriter;
    #7 = Fieldref           #189.#452     // com/fasterxml/jackson/databind/ser/std/BeanSerializerBase._propertyFilterId:Ljava/lang/Object;
    #8 = Fieldref           #189.#453     // com/fasterxml/jackson/databind/ser/std/BeanSerializerBase._objectIdWriter:Lcom/fasterxml/jackson/databind/ser/impl/ObjectIdWriter;
    #9 = Fieldref           #189.#454     // com/fasterxml/jackson/databind/ser/std/BeanSerializerBase._serializationShape:Lcom/fasterxml/jackson/annotation/JsonFormat$Shape;
   #10 = Methodref          #455.#456     // com/fasterxml/jackson/databind/ser/BeanSerializerBuilder.getTypeId:()Lcom/fasterxml/jackson/databind/introspect/AnnotatedMember;
   #11 = Methodref          #455.#457     // com/fasterxml/jackson/databind/ser/BeanSerializerBuilder.getAnyGetter:()Lcom/fasterxml/jackson/databind/ser/AnyGetterWriter;
   #12 = Methodref          #455.#458     // com/fasterxml/jackson/databind/ser/BeanSerializerBuilder.getFilterId:()Ljava/lang/Object;
   #13 = Methodref          #455.#459     // com/fasterxml/jackson/databind/ser/BeanSerializerBuilder.getObjectIdWriter:()Lcom/fasterxml/jackson/databind/ser/impl/ObjectIdWriter;
   #14 = Methodref          #455.#460     // com/fasterxml/jackson/databind/ser/BeanSerializerBuilder.getBeanDescription:()Lcom/fasterxml/jackson/databind/BeanDescription;
   #15 = Methodref          #461.#462     // com/fasterxml/jackson/databind/BeanDescription.findExpectedFormat:(Lcom/fasterxml/jackson/annotation/JsonFormat$Value;)Lcom/fasterxml/jackson/annotation/JsonFormat$Value;
   #16 = Methodref          #223.#463     // com/fasterxml/jackson/annotation/JsonFormat$Value.getShape:()Lcom/fasterxml/jackson/annotation/JsonFormat$Shape;
   #17 = Fieldref           #189.#464     // com/fasterxml/jackson/databind/ser/std/BeanSerializerBase._handledType:Ljava/lang/Class;
   #18 = Methodref          #190.#465     // com/fasterxml/jackson/databind/ser/std/StdSerializer."<init>":(Ljava/lang/Class;)V
   #19 = Methodref          #189.#466     // com/fasterxml/jackson/databind/ser/std/BeanSerializerBase."<init>":(Lcom/fasterxml/jackson/databind/ser/std/BeanSerializerBase;Lcom/fasterxml/jackson/databind/ser/impl/ObjectIdWriter;Ljava/lang/Object;)V
   #20 = Methodref          #467.#468     // com/fasterxml/jackson/databind/util/ArrayBuilders.arrayToSet:([Ljava/lang/Object;)Ljava/util/HashSet;
   #21 = Methodref          #189.#469     // com/fasterxml/jackson/databind/ser/std/BeanSerializerBase."<init>":(Lcom/fasterxml/jackson/databind/ser/std/BeanSerializerBase;Ljava/util/Set;Ljava/util/Set;)V
   #22 = Class              #470          // java/util/ArrayList
   #23 = Methodref          #22.#471      // java/util/ArrayList."<init>":(I)V
   #24 = Methodref          #28.#472      // com/fasterxml/jackson/databind/ser/BeanPropertyWriter.getName:()Ljava/lang/String;
   #25 = Methodref          #473.#474     // com/fasterxml/jackson/databind/util/IgnorePropertiesUtil.shouldIgnore:(Ljava/lang/Object;Ljava/util/Collection;Ljava/util/Collection;)Z
   #26 = Methodref          #22.#475      // java/util/ArrayList.add:(Ljava/lang/Object;)Z
   #27 = Methodref          #22.#476      // java/util/ArrayList.size:()I
   #28 = Class              #477          // com/fasterxml/jackson/databind/ser/BeanPropertyWriter
   #29 = Methodref          #22.#478      // java/util/ArrayList.toArray:([Ljava/lang/Object;)[Ljava/lang/Object;
   #30 = Class              #200          // "[Lcom/fasterxml/jackson/databind/ser/BeanPropertyWriter;"
   #31 = Methodref          #189.#479     // com/fasterxml/jackson/databind/ser/std/BeanSerializerBase.withByNameInclusion:(Ljava/util/Set;Ljava/util/Set;)Lcom/fasterxml/jackson/databind/ser/std/BeanSerializerBase;
   #32 = Methodref          #189.#480     // com/fasterxml/jackson/databind/ser/std/BeanSerializerBase.withIgnorals:(Ljava/util/Set;)Lcom/fasterxml/jackson/databind/ser/std/BeanSerializerBase;
   #33 = Methodref          #189.#481     // com/fasterxml/jackson/databind/ser/std/BeanSerializerBase."<init>":(Lcom/fasterxml/jackson/databind/ser/std/BeanSerializerBase;[Lcom/fasterxml/jackson/databind/ser/BeanPropertyWriter;[Lcom/fasterxml/jackson/databind/ser/BeanPropertyWriter;)V
   #34 = Methodref          #189.#482     // com/fasterxml/jackson/databind/ser/std/BeanSerializerBase.rename:([Lcom/fasterxml/jackson/databind/ser/BeanPropertyWriter;Lcom/fasterxml/jackson/databind/util/NameTransformer;)[Lcom/fasterxml/jackson/databind/ser/BeanPropertyWriter;
   #35 = Fieldref           #483.#484     // com/fasterxml/jackson/databind/util/NameTransformer.NOP:Lcom/fasterxml/jackson/databind/util/NameTransformer;
   #36 = Methodref          #28.#485      // com/fasterxml/jackson/databind/ser/BeanPropertyWriter.rename:(Lcom/fasterxml/jackson/databind/util/NameTransformer;)Lcom/fasterxml/jackson/databind/ser/BeanPropertyWriter;
   #37 = Methodref          #28.#486      // com/fasterxml/jackson/databind/ser/BeanPropertyWriter.willSuppressNulls:()Z
   #38 = Methodref          #28.#487      // com/fasterxml/jackson/databind/ser/BeanPropertyWriter.hasNullSerializer:()Z
   #39 = Methodref          #488.#489     // com/fasterxml/jackson/databind/SerializerProvider.findNullValueSerializer:(Lcom/fasterxml/jackson/databind/BeanProperty;)Lcom/fasterxml/jackson/databind/JsonSerializer;
   #40 = Methodref          #28.#490      // com/fasterxml/jackson/databind/ser/BeanPropertyWriter.assignNullSerializer:(Lcom/fasterxml/jackson/databind/JsonSerializer;)V
   #41 = Methodref          #28.#491      // com/fasterxml/jackson/databind/ser/BeanPropertyWriter.hasSerializer:()Z
   #42 = Methodref          #189.#492     // com/fasterxml/jackson/databind/ser/std/BeanSerializerBase.findConvertingSerializer:(Lcom/fasterxml/jackson/databind/SerializerProvider;Lcom/fasterxml/jackson/databind/ser/BeanPropertyWriter;)Lcom/fasterxml/jackson/databind/JsonSerializer;
   #43 = Methodref          #28.#493      // com/fasterxml/jackson/databind/ser/BeanPropertyWriter.getSerializationType:()Lcom/fasterxml/jackson/databind/JavaType;
   #44 = Methodref          #28.#494      // com/fasterxml/jackson/databind/ser/BeanPropertyWriter.getType:()Lcom/fasterxml/jackson/databind/JavaType;
   #45 = Methodref          #495.#496     // com/fasterxml/jackson/databind/JavaType.isFinal:()Z
   #46 = Methodref          #495.#497     // com/fasterxml/jackson/databind/JavaType.isContainerType:()Z
   #47 = Methodref          #495.#498     // com/fasterxml/jackson/databind/JavaType.containedTypeCount:()I
   #48 = Methodref          #28.#499      // com/fasterxml/jackson/databind/ser/BeanPropertyWriter.setNonTrivialBaseType:(Lcom/fasterxml/jackson/databind/JavaType;)V
   #49 = Methodref          #488.#500     // com/fasterxml/jackson/databind/SerializerProvider.findValueSerializer:(Lcom/fasterxml/jackson/databind/JavaType;Lcom/fasterxml/jackson/databind/BeanProperty;)Lcom/fasterxml/jackson/databind/JsonSerializer;
   #50 = Methodref          #495.#501     // com/fasterxml/jackson/databind/JavaType.getContentType:()Lcom/fasterxml/jackson/databind/JavaType;
   #51 = Methodref          #495.#502     // com/fasterxml/jackson/databind/JavaType.getTypeHandler:()Ljava/lang/Object;
   #52 = Class              #503          // com/fasterxml/jackson/databind/jsontype/TypeSerializer
   #53 = Class              #504          // com/fasterxml/jackson/databind/ser/ContainerSerializer
   #54 = Methodref          #53.#505      // com/fasterxml/jackson/databind/ser/ContainerSerializer.withValueTypeSerializer:(Lcom/fasterxml/jackson/databind/jsontype/TypeSerializer;)Lcom/fasterxml/jackson/databind/ser/ContainerSerializer;
   #55 = Methodref          #28.#506      // com/fasterxml/jackson/databind/ser/BeanPropertyWriter.assignSerializer:(Lcom/fasterxml/jackson/databind/JsonSerializer;)V
   #56 = Methodref          #507.#508     // com/fasterxml/jackson/databind/ser/AnyGetterWriter.resolve:(Lcom/fasterxml/jackson/databind/SerializerProvider;)V
   #57 = Methodref          #488.#509     // com/fasterxml/jackson/databind/SerializerProvider.getAnnotationIntrospector:()Lcom/fasterxml/jackson/databind/AnnotationIntrospector;
   #58 = Methodref          #28.#510      // com/fasterxml/jackson/databind/ser/BeanPropertyWriter.getMember:()Lcom/fasterxml/jackson/databind/introspect/AnnotatedMember;
   #59 = Methodref          #511.#512     // com/fasterxml/jackson/databind/AnnotationIntrospector.findSerializationConverter:(Lcom/fasterxml/jackson/databind/introspect/Annotated;)Ljava/lang/Object;
   #60 = Methodref          #488.#513     // com/fasterxml/jackson/databind/SerializerProvider.converterInstance:(Lcom/fasterxml/jackson/databind/introspect/Annotated;Ljava/lang/Object;)Lcom/fasterxml/jackson/databind/util/Converter;
   #61 = Methodref          #488.#514     // com/fasterxml/jackson/databind/SerializerProvider.getTypeFactory:()Lcom/fasterxml/jackson/databind/type/TypeFactory;
   #62 = InterfaceMethodref #515.#516     // com/fasterxml/jackson/databind/util/Converter.getOutputType:(Lcom/fasterxml/jackson/databind/type/TypeFactory;)Lcom/fasterxml/jackson/databind/JavaType;
   #63 = Methodref          #495.#517     // com/fasterxml/jackson/databind/JavaType.isJavaLangObject:()Z
   #64 = Class              #518          // com/fasterxml/jackson/databind/ser/std/StdDelegatingSerializer
   #65 = Methodref          #64.#519      // com/fasterxml/jackson/databind/ser/std/StdDelegatingSerializer."<init>":(Lcom/fasterxml/jackson/databind/util/Converter;Lcom/fasterxml/jackson/databind/JavaType;Lcom/fasterxml/jackson/databind/JsonSerializer;)V
   #66 = InterfaceMethodref #520.#510     // com/fasterxml/jackson/databind/BeanProperty.getMember:()Lcom/fasterxml/jackson/databind/introspect/AnnotatedMember;
   #67 = Methodref          #488.#521     // com/fasterxml/jackson/databind/SerializerProvider.getConfig:()Lcom/fasterxml/jackson/databind/SerializationConfig;
   #68 = Methodref          #189.#522     // com/fasterxml/jackson/databind/ser/std/BeanSerializerBase.findFormatOverrides:(Lcom/fasterxml/jackson/databind/SerializerProvider;Lcom/fasterxml/jackson/databind/BeanProperty;Ljava/lang/Class;)Lcom/fasterxml/jackson/annotation/JsonFormat$Value;
   #69 = Methodref          #223.#523     // com/fasterxml/jackson/annotation/JsonFormat$Value.hasShape:()Z
   #70 = Fieldref           #214.#524     // com/fasterxml/jackson/annotation/JsonFormat$Shape.ANY:Lcom/fasterxml/jackson/annotation/JsonFormat$Shape;
   #71 = Methodref          #495.#525     // com/fasterxml/jackson/databind/JavaType.isEnumType:()Z
   #72 = Fieldref           #195.#526     // com/fasterxml/jackson/databind/ser/std/BeanSerializerBase$1.$SwitchMap$com$fasterxml$jackson$annotation$JsonFormat$Shape:[I
   #73 = Methodref          #214.#527     // com/fasterxml/jackson/annotation/JsonFormat$Shape.ordinal:()I
   #74 = Methodref          #528.#529     // com/fasterxml/jackson/databind/SerializationConfig.introspectClassAnnotations:(Lcom/fasterxml/jackson/databind/JavaType;)Lcom/fasterxml/jackson/databind/BeanDescription;
   #75 = Methodref          #495.#530     // com/fasterxml/jackson/databind/JavaType.getRawClass:()Ljava/lang/Class;
   #76 = Methodref          #531.#532     // com/fasterxml/jackson/databind/ser/std/EnumSerializer.construct:(Ljava/lang/Class;Lcom/fasterxml/jackson/databind/SerializationConfig;Lcom/fasterxml/jackson/databind/BeanDescription;Lcom/fasterxml/jackson/annotation/JsonFormat$Value;)Lcom/fasterxml/jackson/databind/ser/std/EnumSerializer;
   #77 = Methodref          #488.#533     // com/fasterxml/jackson/databind/SerializerProvider.handlePrimaryContextualization:(Lcom/fasterxml/jackson/databind/JsonSerializer;Lcom/fasterxml/jackson/databind/BeanProperty;)Lcom/fasterxml/jackson/databind/JsonSerializer;
   #78 = Fieldref           #214.#534     // com/fasterxml/jackson/annotation/JsonFormat$Shape.NATURAL:Lcom/fasterxml/jackson/annotation/JsonFormat$Shape;
   #79 = Methodref          #495.#535     // com/fasterxml/jackson/databind/JavaType.isMapLikeType:()Z
   #80 = Class              #536          // java/util/Map
   #81 = Methodref          #537.#538     // java/lang/Class.isAssignableFrom:(Ljava/lang/Class;)Z
   #82 = Class              #539          // java/util/Map$Entry
   #83 = Methodref          #495.#541     // com/fasterxml/jackson/databind/JavaType.findSuperType:(Ljava/lang/Class;)Lcom/fasterxml/jackson/databind/JavaType;
   #84 = Methodref          #495.#542     // com/fasterxml/jackson/databind/JavaType.containedTypeOrUnknown:(I)Lcom/fasterxml/jackson/databind/JavaType;
   #85 = Class              #543          // com/fasterxml/jackson/databind/ser/impl/MapEntrySerializer
   #86 = Methodref          #85.#544      // com/fasterxml/jackson/databind/ser/impl/MapEntrySerializer."<init>":(Lcom/fasterxml/jackson/databind/JavaType;Lcom/fasterxml/jackson/databind/JavaType;Lcom/fasterxml/jackson/databind/JavaType;ZLcom/fasterxml/jackson/databind/jsontype/TypeSerializer;Lcom/fasterxml/jackson/databind/BeanProperty;)V
   #87 = Methodref          #511.#545     // com/fasterxml/jackson/databind/AnnotationIntrospector.findPropertyIgnoralByName:(Lcom/fasterxml/jackson/databind/cfg/MapperConfig;Lcom/fasterxml/jackson/databind/introspect/Annotated;)Lcom/fasterxml/jackson/annotation/JsonIgnoreProperties$Value;
   #88 = Methodref          #546.#547     // com/fasterxml/jackson/annotation/JsonIgnoreProperties$Value.findIgnoredForSerialization:()Ljava/util/Set;
   #89 = Methodref          #511.#548     // com/fasterxml/jackson/databind/AnnotationIntrospector.findPropertyInclusionByName:(Lcom/fasterxml/jackson/databind/cfg/MapperConfig;Lcom/fasterxml/jackson/databind/introspect/Annotated;)Lcom/fasterxml/jackson/annotation/JsonIncludeProperties$Value;
   #90 = Methodref          #549.#550     // com/fasterxml/jackson/annotation/JsonIncludeProperties$Value.getIncluded:()Ljava/util/Set;
   #91 = Methodref          #511.#551     // com/fasterxml/jackson/databind/AnnotationIntrospector.findObjectIdInfo:(Lcom/fasterxml/jackson/databind/introspect/Annotated;)Lcom/fasterxml/jackson/databind/introspect/ObjectIdInfo;
   #92 = Methodref          #511.#552     // com/fasterxml/jackson/databind/AnnotationIntrospector.findObjectReferenceInfo:(Lcom/fasterxml/jackson/databind/introspect/Annotated;Lcom/fasterxml/jackson/databind/introspect/ObjectIdInfo;)Lcom/fasterxml/jackson/databind/introspect/ObjectIdInfo;
   #93 = Methodref          #553.#554     // com/fasterxml/jackson/databind/introspect/ObjectIdInfo.getAlwaysAsId:()Z
   #94 = Methodref          #555.#556     // com/fasterxml/jackson/databind/ser/impl/ObjectIdWriter.withAlwaysAsId:(Z)Lcom/fasterxml/jackson/databind/ser/impl/ObjectIdWriter;
   #95 = Methodref          #553.#557     // com/fasterxml/jackson/databind/introspect/ObjectIdInfo.getGeneratorType:()Ljava/lang/Class;
   #96 = Methodref          #488.#558     // com/fasterxml/jackson/databind/SerializerProvider.constructType:(Ljava/lang/reflect/Type;)Lcom/fasterxml/jackson/databind/JavaType;
   #97 = Class              #559          // com/fasterxml/jackson/annotation/ObjectIdGenerator
   #98 = Methodref          #560.#561     // com/fasterxml/jackson/databind/type/TypeFactory.findTypeParameters:(Lcom/fasterxml/jackson/databind/JavaType;Ljava/lang/Class;)[Lcom/fasterxml/jackson/databind/JavaType;
   #99 = Class              #563          // com/fasterxml/jackson/annotation/ObjectIdGenerators$PropertyGenerator
  #100 = Methodref          #553.#565     // com/fasterxml/jackson/databind/introspect/ObjectIdInfo.getPropertyName:()Lcom/fasterxml/jackson/databind/PropertyName;
  #101 = Methodref          #112.#566     // com/fasterxml/jackson/databind/PropertyName.getSimpleName:()Ljava/lang/String;
  #102 = String             #567          // Invalid Object Id definition for %s: cannot find property with name %s
  #103 = Class              #568          // java/lang/Object
  #104 = Methodref          #189.#569     // com/fasterxml/jackson/databind/ser/std/BeanSerializerBase.handledType:()Ljava/lang/Class;
  #105 = Methodref          #570.#571     // com/fasterxml/jackson/databind/util/ClassUtil.nameOf:(Ljava/lang/Class;)Ljava/lang/String;
  #106 = Methodref          #570.#572     // com/fasterxml/jackson/databind/util/ClassUtil.name:(Ljava/lang/String;)Ljava/lang/String;
  #107 = Methodref          #152.#573     // java/lang/String.format:(Ljava/lang/String;[Ljava/lang/Object;)Ljava/lang/String;
  #108 = Methodref          #488.#574     // com/fasterxml/jackson/databind/SerializerProvider.reportBadDefinition:(Lcom/fasterxml/jackson/databind/JavaType;Ljava/lang/String;)Ljava/lang/Object;
  #109 = Methodref          #152.#575     // java/lang/String.equals:(Ljava/lang/Object;)Z
  #110 = Class              #576          // com/fasterxml/jackson/databind/ser/impl/PropertyBasedObjectIdGenerator
  #111 = Methodref          #110.#577     // com/fasterxml/jackson/databind/ser/impl/PropertyBasedObjectIdGenerator."<init>":(Lcom/fasterxml/jackson/databind/introspect/ObjectIdInfo;Lcom/fasterxml/jackson/databind/ser/BeanPropertyWriter;)V
  #112 = Class              #578          // com/fasterxml/jackson/databind/PropertyName
  #113 = Methodref          #555.#579     // com/fasterxml/jackson/databind/ser/impl/ObjectIdWriter.construct:(Lcom/fasterxml/jackson/databind/JavaType;Lcom/fasterxml/jackson/databind/PropertyName;Lcom/fasterxml/jackson/annotation/ObjectIdGenerator;Z)Lcom/fasterxml/jackson/databind/ser/impl/ObjectIdWriter;
  #114 = Methodref          #488.#580     // com/fasterxml/jackson/databind/SerializerProvider.objectIdGeneratorInstance:(Lcom/fasterxml/jackson/databind/introspect/Annotated;Lcom/fasterxml/jackson/databind/introspect/ObjectIdInfo;)Lcom/fasterxml/jackson/annotation/ObjectIdGenerator;
  #115 = Methodref          #511.#581     // com/fasterxml/jackson/databind/AnnotationIntrospector.findFilterId:(Lcom/fasterxml/jackson/databind/introspect/Annotated;)Ljava/lang/Object;
  #116 = Methodref          #103.#575     // java/lang/Object.equals:(Ljava/lang/Object;)Z
  #117 = Methodref          #582.#583     // java/util/Arrays.copyOf:([Ljava/lang/Object;I)[Ljava/lang/Object;
  #118 = Methodref          #584.#585     // java/lang/System.arraycopy:(Ljava/lang/Object;ILjava/lang/Object;II)V
  #119 = Methodref          #189.#586     // com/fasterxml/jackson/databind/ser/std/BeanSerializerBase.withProperties:([Lcom/fasterxml/jackson/databind/ser/BeanPropertyWriter;[Lcom/fasterxml/jackson/databind/ser/BeanPropertyWriter;)Lcom/fasterxml/jackson/databind/ser/std/BeanSerializerBase;
  #120 = Fieldref           #555.#587     // com/fasterxml/jackson/databind/ser/impl/ObjectIdWriter.idType:Lcom/fasterxml/jackson/databind/JavaType;
  #121 = Methodref          #555.#588     // com/fasterxml/jackson/databind/ser/impl/ObjectIdWriter.withSerializer:(Lcom/fasterxml/jackson/databind/JsonSerializer;)Lcom/fasterxml/jackson/databind/ser/impl/ObjectIdWriter;
  #122 = Methodref          #189.#589     // com/fasterxml/jackson/databind/ser/std/BeanSerializerBase.withObjectIdWriter:(Lcom/fasterxml/jackson/databind/ser/impl/ObjectIdWriter;)Lcom/fasterxml/jackson/databind/ser/std/BeanSerializerBase;
  #123 = InterfaceMethodref #590.#591     // java/util/Set.isEmpty:()Z
  #124 = Methodref          #189.#592     // com/fasterxml/jackson/databind/ser/std/BeanSerializerBase.withFilterId:(Ljava/lang/Object;)Lcom/fasterxml/jackson/databind/ser/std/BeanSerializerBase;
  #125 = Fieldref           #214.#593     // com/fasterxml/jackson/annotation/JsonFormat$Shape.ARRAY:Lcom/fasterxml/jackson/annotation/JsonFormat$Shape;
  #126 = Methodref          #189.#594     // com/fasterxml/jackson/databind/ser/std/BeanSerializerBase.asArraySerializer:()Lcom/fasterxml/jackson/databind/ser/std/BeanSerializerBase;
  #127 = Methodref          #582.#595     // java/util/Arrays.asList:([Ljava/lang/Object;)Ljava/util/List;
  #128 = InterfaceMethodref #596.#597     // java/util/List.iterator:()Ljava/util/Iterator;
  #129 = Methodref          #189.#598     // com/fasterxml/jackson/databind/ser/std/BeanSerializerBase._serializeWithObjectId:(Ljava/lang/Object;Lcom/fasterxml/jackson/core/JsonGenerator;Lcom/fasterxml/jackson/databind/SerializerProvider;Lcom/fasterxml/jackson/databind/jsontype/TypeSerializer;)V
  #130 = Fieldref           #599.#600     // com/fasterxml/jackson/core/JsonToken.START_OBJECT:Lcom/fasterxml/jackson/core/JsonToken;
  #131 = Methodref          #189.#601     // com/fasterxml/jackson/databind/ser/std/BeanSerializerBase._typeIdDef:(Lcom/fasterxml/jackson/databind/jsontype/TypeSerializer;Ljava/lang/Object;Lcom/fasterxml/jackson/core/JsonToken;)Lcom/fasterxml/jackson/core/type/WritableTypeId;
  #132 = Methodref          #52.#602      // com/fasterxml/jackson/databind/jsontype/TypeSerializer.writeTypePrefix:(Lcom/fasterxml/jackson/core/JsonGenerator;Lcom/fasterxml/jackson/core/type/WritableTypeId;)Lcom/fasterxml/jackson/core/type/WritableTypeId;
  #133 = Methodref          #603.#604     // com/fasterxml/jackson/core/JsonGenerator.setCurrentValue:(Ljava/lang/Object;)V
  #134 = Methodref          #189.#605     // com/fasterxml/jackson/databind/ser/std/BeanSerializerBase.serializeFieldsFiltered:(Ljava/lang/Object;Lcom/fasterxml/jackson/core/JsonGenerator;Lcom/fasterxml/jackson/databind/SerializerProvider;)V
  #135 = Methodref          #189.#606     // com/fasterxml/jackson/databind/ser/std/BeanSerializerBase.serializeFields:(Ljava/lang/Object;Lcom/fasterxml/jackson/core/JsonGenerator;Lcom/fasterxml/jackson/databind/SerializerProvider;)V
  #136 = Methodref          #52.#607      // com/fasterxml/jackson/databind/jsontype/TypeSerializer.writeTypeSuffix:(Lcom/fasterxml/jackson/core/JsonGenerator;Lcom/fasterxml/jackson/core/type/WritableTypeId;)Lcom/fasterxml/jackson/core/type/WritableTypeId;
  #137 = Fieldref           #555.#608     // com/fasterxml/jackson/databind/ser/impl/ObjectIdWriter.generator:Lcom/fasterxml/jackson/annotation/ObjectIdGenerator;
  #138 = Methodref          #488.#609     // com/fasterxml/jackson/databind/SerializerProvider.findObjectId:(Ljava/lang/Object;Lcom/fasterxml/jackson/annotation/ObjectIdGenerator;)Lcom/fasterxml/jackson/databind/ser/impl/WritableObjectId;
  #139 = Methodref          #610.#611     // com/fasterxml/jackson/databind/ser/impl/WritableObjectId.writeAsId:(Lcom/fasterxml/jackson/core/JsonGenerator;Lcom/fasterxml/jackson/databind/SerializerProvider;Lcom/fasterxml/jackson/databind/ser/impl/ObjectIdWriter;)Z
  #140 = Methodref          #610.#612     // com/fasterxml/jackson/databind/ser/impl/WritableObjectId.generateId:(Ljava/lang/Object;)Ljava/lang/Object;
  #141 = Fieldref           #555.#613     // com/fasterxml/jackson/databind/ser/impl/ObjectIdWriter.alwaysAsId:Z
  #142 = Fieldref           #555.#614     // com/fasterxml/jackson/databind/ser/impl/ObjectIdWriter.serializer:Lcom/fasterxml/jackson/databind/JsonSerializer;
  #143 = Methodref          #615.#616     // com/fasterxml/jackson/databind/JsonSerializer.serialize:(Ljava/lang/Object;Lcom/fasterxml/jackson/core/JsonGenerator;Lcom/fasterxml/jackson/databind/SerializerProvider;)V
  #144 = Methodref          #603.#617     // com/fasterxml/jackson/core/JsonGenerator.writeStartObject:(Ljava/lang/Object;)V
  #145 = Methodref          #610.#618     // com/fasterxml/jackson/databind/ser/impl/WritableObjectId.writeAsField:(Lcom/fasterxml/jackson/core/JsonGenerator;Lcom/fasterxml/jackson/databind/SerializerProvider;Lcom/fasterxml/jackson/databind/ser/impl/ObjectIdWriter;)V
  #146 = Methodref          #603.#619     // com/fasterxml/jackson/core/JsonGenerator.writeEndObject:()V
  #147 = Methodref          #189.#620     // com/fasterxml/jackson/databind/ser/std/BeanSerializerBase._serializeObjectId:(Ljava/lang/Object;Lcom/fasterxml/jackson/core/JsonGenerator;Lcom/fasterxml/jackson/databind/SerializerProvider;Lcom/fasterxml/jackson/databind/jsontype/TypeSerializer;Lcom/fasterxml/jackson/databind/ser/impl/WritableObjectId;)V
  #148 = Methodref          #52.#621      // com/fasterxml/jackson/databind/jsontype/TypeSerializer.typeId:(Ljava/lang/Object;Lcom/fasterxml/jackson/core/JsonToken;)Lcom/fasterxml/jackson/core/type/WritableTypeId;
  #149 = Methodref          #622.#623     // com/fasterxml/jackson/databind/introspect/AnnotatedMember.getValue:(Ljava/lang/Object;)Ljava/lang/Object;
  #150 = String             #624          //
  #151 = Methodref          #52.#625      // com/fasterxml/jackson/databind/jsontype/TypeSerializer.typeId:(Ljava/lang/Object;Lcom/fasterxml/jackson/core/JsonToken;Ljava/lang/Object;)Lcom/fasterxml/jackson/core/type/WritableTypeId;
  #152 = Class              #626          // java/lang/String
  #153 = Methodref          #103.#627     // java/lang/Object.toString:()Ljava/lang/String;
  #154 = Methodref          #488.#628     // com/fasterxml/jackson/databind/SerializerProvider.getActiveView:()Ljava/lang/Class;
  #155 = Methodref          #28.#629      // com/fasterxml/jackson/databind/ser/BeanPropertyWriter.serializeAsField:(Ljava/lang/Object;Lcom/fasterxml/jackson/core/JsonGenerator;Lcom/fasterxml/jackson/databind/SerializerProvider;)V
  #156 = Methodref          #507.#630     // com/fasterxml/jackson/databind/ser/AnyGetterWriter.getAndSerialize:(Ljava/lang/Object;Lcom/fasterxml/jackson/core/JsonGenerator;Lcom/fasterxml/jackson/databind/SerializerProvider;)V
  #157 = Class              #631          // java/lang/Exception
  #158 = String             #632          // [anySetter]
  #159 = Methodref          #189.#633     // com/fasterxml/jackson/databind/ser/std/BeanSerializerBase.wrapAndThrow:(Lcom/fasterxml/jackson/databind/SerializerProvider;Ljava/lang/Throwable;Ljava/lang/Object;Ljava/lang/String;)V
  #160 = Class              #634          // java/lang/StackOverflowError
  #161 = Class              #635          // com/fasterxml/jackson/databind/JsonMappingException
  #162 = String             #636          // Infinite recursion (StackOverflowError)
  #163 = Methodref          #161.#637     // com/fasterxml/jackson/databind/JsonMappingException."<init>":(Ljava/io/Closeable;Ljava/lang/String;Ljava/lang/Throwable;)V
  #164 = Methodref          #638.#639     // com/fasterxml/jackson/databind/DatabindException.prependPath:(Ljava/lang/Object;Ljava/lang/String;)V
  #165 = Methodref          #189.#640     // com/fasterxml/jackson/databind/ser/std/BeanSerializerBase.findPropertyFilter:(Lcom/fasterxml/jackson/databind/SerializerProvider;Ljava/lang/Object;Ljava/lang/Object;)Lcom/fasterxml/jackson/databind/ser/PropertyFilter;
  #166 = InterfaceMethodref #641.#642     // com/fasterxml/jackson/databind/ser/PropertyFilter.serializeAsField:(Ljava/lang/Object;Lcom/fasterxml/jackson/core/JsonGenerator;Lcom/fasterxml/jackson/databind/SerializerProvider;Lcom/fasterxml/jackson/databind/ser/PropertyWriter;)V
  #167 = Methodref          #507.#643     // com/fasterxml/jackson/databind/ser/AnyGetterWriter.getAndFilter:(Ljava/lang/Object;Lcom/fasterxml/jackson/core/JsonGenerator;Lcom/fasterxml/jackson/databind/SerializerProvider;Lcom/fasterxml/jackson/databind/ser/PropertyFilter;)V
  #168 = String             #644          // object
  #169 = Methodref          #189.#645     // com/fasterxml/jackson/databind/ser/std/BeanSerializerBase.createSchemaNode:(Ljava/lang/String;Z)Lcom/fasterxml/jackson/databind/node/ObjectNode;
  #170 = Class              #646          // com/fasterxml/jackson/databind/jsonschema/JsonSerializableSchema
  #171 = Methodref          #537.#647     // java/lang/Class.getAnnotation:(Ljava/lang/Class;)Ljava/lang/annotation/Annotation;
  #172 = InterfaceMethodref #170.#648     // com/fasterxml/jackson/databind/jsonschema/JsonSerializableSchema.id:()Ljava/lang/String;
  #173 = Methodref          #152.#591     // java/lang/String.isEmpty:()Z
  #174 = String             #392          // id
  #175 = Methodref          #649.#650     // com/fasterxml/jackson/databind/node/ObjectNode.put:(Ljava/lang/String;Ljava/lang/String;)Lcom/fasterxml/jackson/databind/node/ObjectNode;
  #176 = Methodref          #649.#651     // com/fasterxml/jackson/databind/node/ObjectNode.objectNode:()Lcom/fasterxml/jackson/databind/node/ObjectNode;
  #177 = Methodref          #28.#652      // com/fasterxml/jackson/databind/ser/BeanPropertyWriter.depositSchemaProperty:(Lcom/fasterxml/jackson/databind/node/ObjectNode;Lcom/fasterxml/jackson/databind/SerializerProvider;)V
  #178 = InterfaceMethodref #641.#653     // com/fasterxml/jackson/databind/ser/PropertyFilter.depositSchemaProperty:(Lcom/fasterxml/jackson/databind/ser/PropertyWriter;Lcom/fasterxml/jackson/databind/node/ObjectNode;Lcom/fasterxml/jackson/databind/SerializerProvider;)V
  #179 = String             #231          // properties
  #180 = Methodref          #649.#654     // com/fasterxml/jackson/databind/node/ObjectNode.set:(Ljava/lang/String;Lcom/fasterxml/jackson/databind/JsonNode;)Lcom/fasterxml/jackson/databind/JsonNode;
  #181 = InterfaceMethodref #655.#656     // com/fasterxml/jackson/databind/jsonFormatVisitors/JsonFormatVisitorWrapper.expectObjectFormat:(Lcom/fasterxml/jackson/databind/JavaType;)Lcom/fasterxml/jackson/databind/jsonFormatVisitors/JsonObjectFormatVisitor;
  #182 = InterfaceMethodref #655.#657     // com/fasterxml/jackson/databind/jsonFormatVisitors/JsonFormatVisitorWrapper.getProvider:()Lcom/fasterxml/jackson/databind/SerializerProvider;
  #183 = InterfaceMethodref #641.#658     // com/fasterxml/jackson/databind/ser/PropertyFilter.depositSchemaProperty:(Lcom/fasterxml/jackson/databind/ser/PropertyWriter;Lcom/fasterxml/jackson/databind/jsonFormatVisitors/JsonObjectFormatVisitor;Lcom/fasterxml/jackson/databind/SerializerProvider;)V
  #184 = Methodref          #28.#659      // com/fasterxml/jackson/databind/ser/BeanPropertyWriter.depositSchemaProperty:(Lcom/fasterxml/jackson/databind/jsonFormatVisitors/JsonObjectFormatVisitor;Lcom/fasterxml/jackson/databind/SerializerProvider;)V
  #185 = String             #660          // #object-ref
  #186 = Methodref          #112.#661     // com/fasterxml/jackson/databind/PropertyName."<init>":(Ljava/lang/String;)V
  #187 = Fieldref           #189.#662     // com/fasterxml/jackson/databind/ser/std/BeanSerializerBase.NAME_FOR_OBJECT_REF:Lcom/fasterxml/jackson/databind/PropertyName;
  #188 = Fieldref           #189.#663     // com/fasterxml/jackson/databind/ser/std/BeanSerializerBase.NO_PROPS:[Lcom/fasterxml/jackson/databind/ser/BeanPropertyWriter;
  #189 = Class              #664          // com/fasterxml/jackson/databind/ser/std/BeanSerializerBase
  #190 = Class              #665          // com/fasterxml/jackson/databind/ser/std/StdSerializer
  #191 = Class              #666          // com/fasterxml/jackson/databind/ser/ContextualSerializer
  #192 = Class              #667          // com/fasterxml/jackson/databind/ser/ResolvableSerializer
  #193 = Class              #668          // com/fasterxml/jackson/databind/jsonFormatVisitors/JsonFormatVisitable
  #194 = Class              #669          // com/fasterxml/jackson/databind/jsonschema/SchemaAware
  #195 = Class              #670          // com/fasterxml/jackson/databind/ser/std/BeanSerializerBase$1
  #196 = Utf8               InnerClasses
  #197 = Utf8               NAME_FOR_OBJECT_REF
  #198 = Utf8               Lcom/fasterxml/jackson/databind/PropertyName;
  #199 = Utf8               NO_PROPS
  #200 = Utf8               [Lcom/fasterxml/jackson/databind/ser/BeanPropertyWriter;
  #201 = Utf8               _beanType
  #202 = Utf8               Lcom/fasterxml/jackson/databind/JavaType;
  #203 = Utf8               _props
  #204 = Utf8               _filteredProps
  #205 = Utf8               _anyGetterWriter
  #206 = Utf8               Lcom/fasterxml/jackson/databind/ser/AnyGetterWriter;
  #207 = Utf8               _propertyFilterId
  #208 = Utf8               Ljava/lang/Object;
  #209 = Utf8               _typeId
  #210 = Utf8               Lcom/fasterxml/jackson/databind/introspect/AnnotatedMember;
  #211 = Utf8               _objectIdWriter
  #212 = Utf8               Lcom/fasterxml/jackson/databind/ser/impl/ObjectIdWriter;
  #213 = Utf8               _serializationShape
  #214 = Class              #672          // com/fasterxml/jackson/annotation/JsonFormat$Shape
  #215 = Utf8               Shape
  #216 = Utf8               Lcom/fasterxml/jackson/annotation/JsonFormat$Shape;
  #217 = Utf8               <init>
  #218 = Utf8               (Lcom/fasterxml/jackson/databind/JavaType;Lcom/fasterxml/jackson/databind/ser/BeanSerializerBuilder;[Lcom/fasterxml/jackson/databind/ser/BeanPropertyWriter;[Lcom/fasterxml/jackson/databind/ser/BeanPropertyWriter;)V
  #219 = Utf8               Code
  #220 = Utf8               LineNumberTable
  #221 = Utf8               LocalVariableTable
  #222 = Utf8               format
  #223 = Class              #673          // com/fasterxml/jackson/annotation/JsonFormat$Value
  #224 = Utf8               Value
  #225 = Utf8               Lcom/fasterxml/jackson/annotation/JsonFormat$Value;
  #226 = Utf8               this
  #227 = Utf8               Lcom/fasterxml/jackson/databind/ser/std/BeanSerializerBase;
  #228 = Utf8               type
  #229 = Utf8               builder
  #230 = Utf8               Lcom/fasterxml/jackson/databind/ser/BeanSerializerBuilder;
  #231 = Utf8               properties
  #232 = Utf8               filteredProperties
  #233 = Utf8               StackMapTable
  #234 = Class              #664          // com/fasterxml/jackson/databind/ser/std/BeanSerializerBase
  #235 = Class              #674          // com/fasterxml/jackson/databind/JavaType
  #236 = Class              #675          // com/fasterxml/jackson/databind/ser/BeanSerializerBuilder
  #237 = Utf8               (Lcom/fasterxml/jackson/databind/ser/std/BeanSerializerBase;[Lcom/fasterxml/jackson/databind/ser/BeanPropertyWriter;[Lcom/fasterxml/jackson/databind/ser/BeanPropertyWriter;)V
  #238 = Utf8               src
  #239 = Utf8               (Lcom/fasterxml/jackson/databind/ser/std/BeanSerializerBase;Lcom/fasterxml/jackson/databind/ser/impl/ObjectIdWriter;)V
  #240 = Utf8               objectIdWriter
  #241 = Utf8               (Lcom/fasterxml/jackson/databind/ser/std/BeanSerializerBase;Lcom/fasterxml/jackson/databind/ser/impl/ObjectIdWriter;Ljava/lang/Object;)V
  #242 = Utf8               filterId
  #243 = Utf8               (Lcom/fasterxml/jackson/databind/ser/std/BeanSerializerBase;[Ljava/lang/String;)V
  #244 = Utf8               toIgnore
  #245 = Utf8               [Ljava/lang/String;
  #246 = Utf8               Deprecated
  #247 = Utf8               RuntimeVisibleAnnotations
  #248 = Utf8               Ljava/lang/Deprecated;
  #249 = Utf8               (Lcom/fasterxml/jackson/databind/ser/std/BeanSerializerBase;Ljava/util/Set;)V
  #250 = Utf8               Ljava/util/Set;
  #251 = Utf8               LocalVariableTypeTable
  #252 = Utf8               Ljava/util/Set<Ljava/lang/String;>;
  #253 = Utf8               Signature
  #254 = Utf8               (Lcom/fasterxml/jackson/databind/ser/std/BeanSerializerBase;Ljava/util/Set<Ljava/lang/String;>;)V
  #255 = Utf8               (Lcom/fasterxml/jackson/databind/ser/std/BeanSerializerBase;Ljava/util/Set;Ljava/util/Set;)V
  #256 = Utf8               bpw
  #257 = Utf8               Lcom/fasterxml/jackson/databind/ser/BeanPropertyWriter;
  #258 = Utf8               i
  #259 = Utf8               I
  #260 = Utf8               toInclude
  #261 = Utf8               propsIn
  #262 = Utf8               fpropsIn
  #263 = Utf8               len
  #264 = Utf8               propsOut
  #265 = Utf8               Ljava/util/ArrayList;
  #266 = Utf8               fpropsOut
  #267 = Utf8               Ljava/util/ArrayList<Lcom/fasterxml/jackson/databind/ser/BeanPropertyWriter;>;
  #268 = Class              #676          // java/util/Set
  #269 = Class              #470          // java/util/ArrayList
  #270 = Class              #477          // com/fasterxml/jackson/databind/ser/BeanPropertyWriter
  #271 = Utf8               (Lcom/fasterxml/jackson/databind/ser/std/BeanSerializerBase;Ljava/util/Set<Ljava/lang/String;>;Ljava/util/Set<Ljava/lang/String;>;)V
  #272 = Utf8               withObjectIdWriter
  #273 = Utf8               (Lcom/fasterxml/jackson/databind/ser/impl/ObjectIdWriter;)Lcom/fasterxml/jackson/databind/ser/std/BeanSerializerBase;
  #274 = Utf8               withIgnorals
  #275 = Utf8               (Ljava/util/Set;)Lcom/fasterxml/jackson/databind/ser/std/BeanSerializerBase;
  #276 = Utf8               (Ljava/util/Set<Ljava/lang/String;>;)Lcom/fasterxml/jackson/databind/ser/std/BeanSerializerBase;
  #277 = Utf8               withByNameInclusion
  #278 = Utf8               (Ljava/util/Set;Ljava/util/Set;)Lcom/fasterxml/jackson/databind/ser/std/BeanSerializerBase;
  #279 = Utf8               (Ljava/util/Set<Ljava/lang/String;>;Ljava/util/Set<Ljava/lang/String;>;)Lcom/fasterxml/jackson/databind/ser/std/BeanSerializerBase;
  #280 = Utf8               ([Ljava/lang/String;)Lcom/fasterxml/jackson/databind/ser/std/BeanSerializerBase;
  #281 = Utf8               asArraySerializer
  #282 = Utf8               ()Lcom/fasterxml/jackson/databind/ser/std/BeanSerializerBase;
  #283 = Utf8               withFilterId
  #284 = Utf8               (Ljava/lang/Object;)Lcom/fasterxml/jackson/databind/ser/std/BeanSerializerBase;
  #285 = Utf8               withProperties
  #286 = Utf8               ([Lcom/fasterxml/jackson/databind/ser/BeanPropertyWriter;[Lcom/fasterxml/jackson/databind/ser/BeanPropertyWriter;)Lcom/fasterxml/jackson/databind/ser/std/BeanSerializerBase;
  #287 = Utf8               (Lcom/fasterxml/jackson/databind/ser/std/BeanSerializerBase;)V
  #288 = Utf8               (Lcom/fasterxml/jackson/databind/ser/std/BeanSerializerBase;Lcom/fasterxml/jackson/databind/util/NameTransformer;)V
  #289 = Utf8               unwrapper
  #290 = Utf8               Lcom/fasterxml/jackson/databind/util/NameTransformer;
  #291 = Utf8               rename
  #292 = Utf8               ([Lcom/fasterxml/jackson/databind/ser/BeanPropertyWriter;Lcom/fasterxml/jackson/databind/util/NameTransformer;)[Lcom/fasterxml/jackson/databind/ser/BeanPropertyWriter;
  #293 = Utf8               props
  #294 = Utf8               transformer
  #295 = Utf8               result
  #296 = Utf8               resolve
  #297 = Utf8               (Lcom/fasterxml/jackson/databind/SerializerProvider;)V
  #298 = Utf8               w2
  #299 = Utf8               nullSer
  #300 = Utf8               Lcom/fasterxml/jackson/databind/JsonSerializer;
  #301 = Utf8               ser2
  #302 = Utf8               typeSer
  #303 = Utf8               Lcom/fasterxml/jackson/databind/jsontype/TypeSerializer;
  #304 = Utf8               prop
  #305 = Utf8               ser
  #306 = Utf8               provider
  #307 = Utf8               Lcom/fasterxml/jackson/databind/SerializerProvider;
  #308 = Utf8               filteredCount
  #309 = Utf8               Lcom/fasterxml/jackson/databind/JsonSerializer<Ljava/lang/Object;>;
  #310 = Class              #677          // com/fasterxml/jackson/databind/JsonSerializer
  #311 = Utf8               Exceptions
  #312 = Utf8               findConvertingSerializer
  #313 = Utf8               (Lcom/fasterxml/jackson/databind/SerializerProvider;Lcom/fasterxml/jackson/databind/ser/BeanPropertyWriter;)Lcom/fasterxml/jackson/databind/JsonSerializer;
  #314 = Utf8               conv
  #315 = Utf8               Lcom/fasterxml/jackson/databind/util/Converter;
  #316 = Utf8               delegateType
  #317 = Utf8               convDef
  #318 = Utf8               m
  #319 = Utf8               intr
  #320 = Utf8               Lcom/fasterxml/jackson/databind/AnnotationIntrospector;
  #321 = Utf8               Lcom/fasterxml/jackson/databind/util/Converter<Ljava/lang/Object;Ljava/lang/Object;>;
  #322 = Utf8               Lcom/fasterxml/jackson/databind/JsonSerializer<*>;
  #323 = Class              #678          // com/fasterxml/jackson/databind/SerializerProvider
  #324 = Class              #679          // com/fasterxml/jackson/databind/AnnotationIntrospector
  #325 = Class              #680          // com/fasterxml/jackson/databind/introspect/AnnotatedMember
  #326 = Class              #568          // java/lang/Object
  #327 = Class              #681          // com/fasterxml/jackson/databind/util/Converter
  #328 = Utf8               (Lcom/fasterxml/jackson/databind/SerializerProvider;Lcom/fasterxml/jackson/databind/ser/BeanPropertyWriter;)Lcom/fasterxml/jackson/databind/JsonSerializer<Ljava/lang/Object;>;
  #329 = Utf8               createContextual
  #330 = Utf8               (Lcom/fasterxml/jackson/databind/SerializerProvider;Lcom/fasterxml/jackson/databind/BeanProperty;)Lcom/fasterxml/jackson/databind/JsonSerializer;
  #331 = Utf8               desc
  #332 = Utf8               Lcom/fasterxml/jackson/databind/BeanDescription;
  #333 = Utf8               mapEntryType
  #334 = Utf8               kt
  #335 = Utf8               vt
  #336 = Utf8               propName
  #337 = Utf8               Ljava/lang/String;
  #338 = Utf8               idProp
  #339 = Utf8               gen
  #340 = Utf8               Lcom/fasterxml/jackson/annotation/ObjectIdGenerator;
  #341 = Utf8               implClass
  #342 = Utf8               Ljava/lang/Class;
  #343 = Utf8               idType
  #344 = Utf8               objectIdInfo
  #345 = Utf8               Lcom/fasterxml/jackson/databind/introspect/ObjectIdInfo;
  #346 = Utf8               newFiltered
  #347 = Utf8               newProps
  #348 = Utf8               property
  #349 = Utf8               Lcom/fasterxml/jackson/databind/BeanProperty;
  #350 = Utf8               accessor
  #351 = Utf8               config
  #352 = Utf8               Lcom/fasterxml/jackson/databind/SerializationConfig;
  #353 = Utf8               shape
  #354 = Utf8               oiw
  #355 = Utf8               idPropOrigIndex
  #356 = Utf8               ignoredProps
  #357 = Utf8               includedProps
  #358 = Utf8               newFilterId
  #359 = Utf8               contextual
  #360 = Utf8               Lcom/fasterxml/jackson/annotation/ObjectIdGenerator<*>;
  #361 = Utf8               Ljava/lang/Class<*>;
  #362 = Class              #682          // com/fasterxml/jackson/databind/BeanProperty
  #363 = Class              #683          // com/fasterxml/jackson/databind/SerializationConfig
  #364 = Class              #673          // com/fasterxml/jackson/annotation/JsonFormat$Value
  #365 = Class              #672          // com/fasterxml/jackson/annotation/JsonFormat$Shape
  #366 = Class              #684          // com/fasterxml/jackson/databind/ser/impl/ObjectIdWriter
  #367 = Class              #685          // com/fasterxml/jackson/databind/introspect/ObjectIdInfo
  #368 = Class              #686          // java/lang/Class
  #369 = Class              #626          // java/lang/String
  #370 = Utf8               (Lcom/fasterxml/jackson/databind/SerializerProvider;Lcom/fasterxml/jackson/databind/BeanProperty;)Lcom/fasterxml/jackson/databind/JsonSerializer<*>;
  #371 = Utf8               ()Ljava/util/Iterator;
  #372 = Utf8               ()Ljava/util/Iterator<Lcom/fasterxml/jackson/databind/ser/PropertyWriter;>;
  #373 = Utf8               usesObjectId
  #374 = Utf8               ()Z
  #375 = Utf8               serialize
  #376 = Utf8               (Ljava/lang/Object;Lcom/fasterxml/jackson/core/JsonGenerator;Lcom/fasterxml/jackson/databind/SerializerProvider;)V
  #377 = Class              #687          // java/io/IOException
  #378 = Utf8               serializeWithType
  #379 = Utf8               (Ljava/lang/Object;Lcom/fasterxml/jackson/core/JsonGenerator;Lcom/fasterxml/jackson/databind/SerializerProvider;Lcom/fasterxml/jackson/databind/jsontype/TypeSerializer;)V
  #380 = Utf8               bean
  #381 = Utf8               Lcom/fasterxml/jackson/core/JsonGenerator;
  #382 = Utf8               typeIdDef
  #383 = Utf8               Lcom/fasterxml/jackson/core/type/WritableTypeId;
  #384 = Class              #688          // com/fasterxml/jackson/core/type/WritableTypeId
  #385 = Utf8               _serializeWithObjectId
  #386 = Utf8               (Ljava/lang/Object;Lcom/fasterxml/jackson/core/JsonGenerator;Lcom/fasterxml/jackson/databind/SerializerProvider;Z)V
  #387 = Utf8               startEndObject
  #388 = Utf8               Z
  #389 = Utf8               w
  #390 = Utf8               objectId
  #391 = Utf8               Lcom/fasterxml/jackson/databind/ser/impl/WritableObjectId;
  #392 = Utf8               id
  #393 = Class              #689          // com/fasterxml/jackson/databind/ser/impl/WritableObjectId
  #394 = Utf8               _serializeObjectId
  #395 = Utf8               (Ljava/lang/Object;Lcom/fasterxml/jackson/core/JsonGenerator;Lcom/fasterxml/jackson/databind/SerializerProvider;Lcom/fasterxml/jackson/databind/jsontype/TypeSerializer;Lcom/fasterxml/jackson/databind/ser/impl/WritableObjectId;)V
  #396 = Utf8               g
  #397 = Utf8               _typeIdDef
  #398 = Utf8               (Lcom/fasterxml/jackson/databind/jsontype/TypeSerializer;Ljava/lang/Object;Lcom/fasterxml/jackson/core/JsonToken;)Lcom/fasterxml/jackson/core/type/WritableTypeId;
  #399 = Utf8               valueShape
  #400 = Utf8               Lcom/fasterxml/jackson/core/JsonToken;
  #401 = Utf8               typeId
  #402 = Utf8               _customTypeId
  #403 = Utf8               (Ljava/lang/Object;)Ljava/lang/String;
  #404 = Utf8               serializeFields
  #405 = Utf8               name
  #406 = Utf8               e
  #407 = Utf8               Ljava/lang/Exception;
  #408 = Utf8               mapE
  #409 = Utf8               Lcom/fasterxml/jackson/databind/DatabindException;
  #410 = Utf8               Ljava/lang/StackOverflowError;
  #411 = Class              #631          // java/lang/Exception
  #412 = Class              #690          // com/fasterxml/jackson/core/JsonGenerator
  #413 = Class              #634          // java/lang/StackOverflowError
  #414 = Class              #691          // com/fasterxml/jackson/databind/DatabindException
  #415 = Utf8               serializeFieldsFiltered
  #416 = Utf8               filter
  #417 = Utf8               Lcom/fasterxml/jackson/databind/ser/PropertyFilter;
  #418 = Class              #692          // com/fasterxml/jackson/databind/ser/PropertyFilter
  #419 = Utf8               getSchema
  #420 = Utf8               (Lcom/fasterxml/jackson/databind/SerializerProvider;Ljava/lang/reflect/Type;)Lcom/fasterxml/jackson/databind/JsonNode;
  #421 = Utf8               typeHint
  #422 = Utf8               Ljava/lang/reflect/Type;
  #423 = Utf8               o
  #424 = Utf8               Lcom/fasterxml/jackson/databind/node/ObjectNode;
  #425 = Utf8               ann
  #426 = Utf8               Lcom/fasterxml/jackson/databind/jsonschema/JsonSerializableSchema;
  #427 = Utf8               propertiesNode
  #428 = Class              #693          // com/fasterxml/jackson/databind/node/ObjectNode
  #429 = Class              #646          // com/fasterxml/jackson/databind/jsonschema/JsonSerializableSchema
  #430 = Utf8               acceptJsonFormatVisitor
  #431 = Utf8               (Lcom/fasterxml/jackson/databind/jsonFormatVisitors/JsonFormatVisitorWrapper;Lcom/fasterxml/jackson/databind/JavaType;)V
  #432 = Utf8               end
  #433 = Utf8               view
  #434 = Utf8               visitor
  #435 = Utf8               Lcom/fasterxml/jackson/databind/jsonFormatVisitors/JsonFormatVisitorWrapper;
  #436 = Utf8               objectVisitor
  #437 = Utf8               Lcom/fasterxml/jackson/databind/jsonFormatVisitors/JsonObjectFormatVisitor;
  #438 = Class              #694          // com/fasterxml/jackson/databind/jsonFormatVisitors/JsonObjectFormatVisitor
  #439 = Class              #695          // com/fasterxml/jackson/databind/jsonFormatVisitors/JsonFormatVisitorWrapper
  #440 = Utf8               (Ljava/lang/Object;)Lcom/fasterxml/jackson/databind/JsonSerializer;
  #441 = Utf8               <clinit>
  #442 = Utf8               ()V
  #443 = Utf8               Lcom/fasterxml/jackson/databind/ser/std/StdSerializer<Ljava/lang/Object;>;Lcom/fasterxml/jackson/databind/ser/ContextualSerializer;Lcom/fasterxml/jackson/databind/ser/ResolvableSerializer;Lcom/fasterxml/jackson/databind/jsonFormatVisitors/JsonFormatVisitable;Lcom/fasterxml/jackson/databind/jsonschema/SchemaAware;
  #444 = Utf8               SourceFile
  #445 = Utf8               BeanSerializerBase.java
  #446 = NameAndType        #217:#696     // "<init>":(Lcom/fasterxml/jackson/databind/JavaType;)V
  #447 = NameAndType        #201:#202     // _beanType:Lcom/fasterxml/jackson/databind/JavaType;
  #448 = NameAndType        #203:#200     // _props:[Lcom/fasterxml/jackson/databind/ser/BeanPropertyWriter;
  #449 = NameAndType        #204:#200     // _filteredProps:[Lcom/fasterxml/jackson/databind/ser/BeanPropertyWriter;
  #450 = NameAndType        #209:#210     // _typeId:Lcom/fasterxml/jackson/databind/introspect/AnnotatedMember;
  #451 = NameAndType        #205:#206     // _anyGetterWriter:Lcom/fasterxml/jackson/databind/ser/AnyGetterWriter;
  #452 = NameAndType        #207:#208     // _propertyFilterId:Ljava/lang/Object;
  #453 = NameAndType        #211:#212     // _objectIdWriter:Lcom/fasterxml/jackson/databind/ser/impl/ObjectIdWriter;
  #454 = NameAndType        #213:#216     // _serializationShape:Lcom/fasterxml/jackson/annotation/JsonFormat$Shape;
  #455 = Class              #675          // com/fasterxml/jackson/databind/ser/BeanSerializerBuilder
  #456 = NameAndType        #697:#698     // getTypeId:()Lcom/fasterxml/jackson/databind/introspect/AnnotatedMember;
  #457 = NameAndType        #699:#700     // getAnyGetter:()Lcom/fasterxml/jackson/databind/ser/AnyGetterWriter;
  #458 = NameAndType        #701:#702     // getFilterId:()Ljava/lang/Object;
  #459 = NameAndType        #703:#704     // getObjectIdWriter:()Lcom/fasterxml/jackson/databind/ser/impl/ObjectIdWriter;
  #460 = NameAndType        #705:#706     // getBeanDescription:()Lcom/fasterxml/jackson/databind/BeanDescription;
  #461 = Class              #707          // com/fasterxml/jackson/databind/BeanDescription
  #462 = NameAndType        #708:#709     // findExpectedFormat:(Lcom/fasterxml/jackson/annotation/JsonFormat$Value;)Lcom/fasterxml/jackson/annotation/JsonFormat$Value;
  #463 = NameAndType        #710:#711     // getShape:()Lcom/fasterxml/jackson/annotation/JsonFormat$Shape;
  #464 = NameAndType        #712:#342     // _handledType:Ljava/lang/Class;
  #465 = NameAndType        #217:#713     // "<init>":(Ljava/lang/Class;)V
  #466 = NameAndType        #217:#241     // "<init>":(Lcom/fasterxml/jackson/databind/ser/std/BeanSerializerBase;Lcom/fasterxml/jackson/databind/ser/impl/ObjectIdWriter;Ljava/lang/Object;)V
  #467 = Class              #714          // com/fasterxml/jackson/databind/util/ArrayBuilders
  #468 = NameAndType        #715:#716     // arrayToSet:([Ljava/lang/Object;)Ljava/util/HashSet;
  #469 = NameAndType        #217:#255     // "<init>":(Lcom/fasterxml/jackson/databind/ser/std/BeanSerializerBase;Ljava/util/Set;Ljava/util/Set;)V
  #470 = Utf8               java/util/ArrayList
  #471 = NameAndType        #217:#717     // "<init>":(I)V
  #472 = NameAndType        #718:#719     // getName:()Ljava/lang/String;
  #473 = Class              #720          // com/fasterxml/jackson/databind/util/IgnorePropertiesUtil
  #474 = NameAndType        #721:#722     // shouldIgnore:(Ljava/lang/Object;Ljava/util/Collection;Ljava/util/Collection;)Z
  #475 = NameAndType        #723:#724     // add:(Ljava/lang/Object;)Z
  #476 = NameAndType        #725:#726     // size:()I
  #477 = Utf8               com/fasterxml/jackson/databind/ser/BeanPropertyWriter
  #478 = NameAndType        #727:#728     // toArray:([Ljava/lang/Object;)[Ljava/lang/Object;
  #479 = NameAndType        #277:#278     // withByNameInclusion:(Ljava/util/Set;Ljava/util/Set;)Lcom/fasterxml/jackson/databind/ser/std/BeanSerializerBase;
  #480 = NameAndType        #274:#275     // withIgnorals:(Ljava/util/Set;)Lcom/fasterxml/jackson/databind/ser/std/BeanSerializerBase;
  #481 = NameAndType        #217:#237     // "<init>":(Lcom/fasterxml/jackson/databind/ser/std/BeanSerializerBase;[Lcom/fasterxml/jackson/databind/ser/BeanPropertyWriter;[Lcom/fasterxml/jackson/databind/ser/BeanPropertyWriter;)V
  #482 = NameAndType        #291:#292     // rename:([Lcom/fasterxml/jackson/databind/ser/BeanPropertyWriter;Lcom/fasterxml/jackson/databind/util/NameTransformer;)[Lcom/fasterxml/jackson/databind/ser/BeanPropertyWriter;
  #483 = Class              #729          // com/fasterxml/jackson/databind/util/NameTransformer
  #484 = NameAndType        #730:#290     // NOP:Lcom/fasterxml/jackson/databind/util/NameTransformer;
  #485 = NameAndType        #291:#731     // rename:(Lcom/fasterxml/jackson/databind/util/NameTransformer;)Lcom/fasterxml/jackson/databind/ser/BeanPropertyWriter;
  #486 = NameAndType        #732:#374     // willSuppressNulls:()Z
  #487 = NameAndType        #733:#374     // hasNullSerializer:()Z
  #488 = Class              #678          // com/fasterxml/jackson/databind/SerializerProvider
  #489 = NameAndType        #734:#735     // findNullValueSerializer:(Lcom/fasterxml/jackson/databind/BeanProperty;)Lcom/fasterxml/jackson/databind/JsonSerializer;
  #490 = NameAndType        #736:#737     // assignNullSerializer:(Lcom/fasterxml/jackson/databind/JsonSerializer;)V
  #491 = NameAndType        #738:#374     // hasSerializer:()Z
  #492 = NameAndType        #312:#313     // findConvertingSerializer:(Lcom/fasterxml/jackson/databind/SerializerProvider;Lcom/fasterxml/jackson/databind/ser/BeanPropertyWriter;)Lcom/fasterxml/jackson/databind/JsonSerializer;
  #493 = NameAndType        #739:#740     // getSerializationType:()Lcom/fasterxml/jackson/databind/JavaType;
  #494 = NameAndType        #741:#740     // getType:()Lcom/fasterxml/jackson/databind/JavaType;
  #495 = Class              #674          // com/fasterxml/jackson/databind/JavaType
  #496 = NameAndType        #742:#374     // isFinal:()Z
  #497 = NameAndType        #743:#374     // isContainerType:()Z
  #498 = NameAndType        #744:#726     // containedTypeCount:()I
  #499 = NameAndType        #745:#696     // setNonTrivialBaseType:(Lcom/fasterxml/jackson/databind/JavaType;)V
  #500 = NameAndType        #746:#747     // findValueSerializer:(Lcom/fasterxml/jackson/databind/JavaType;Lcom/fasterxml/jackson/databind/BeanProperty;)Lcom/fasterxml/jackson/databind/JsonSerializer;
  #501 = NameAndType        #748:#740     // getContentType:()Lcom/fasterxml/jackson/databind/JavaType;
  #502 = NameAndType        #749:#702     // getTypeHandler:()Ljava/lang/Object;
  #503 = Utf8               com/fasterxml/jackson/databind/jsontype/TypeSerializer
  #504 = Utf8               com/fasterxml/jackson/databind/ser/ContainerSerializer
  #505 = NameAndType        #750:#751     // withValueTypeSerializer:(Lcom/fasterxml/jackson/databind/jsontype/TypeSerializer;)Lcom/fasterxml/jackson/databind/ser/ContainerSerializer;
  #506 = NameAndType        #752:#737     // assignSerializer:(Lcom/fasterxml/jackson/databind/JsonSerializer;)V
  #507 = Class              #753          // com/fasterxml/jackson/databind/ser/AnyGetterWriter
  #508 = NameAndType        #296:#297     // resolve:(Lcom/fasterxml/jackson/databind/SerializerProvider;)V
  #509 = NameAndType        #754:#755     // getAnnotationIntrospector:()Lcom/fasterxml/jackson/databind/AnnotationIntrospector;
  #510 = NameAndType        #756:#698     // getMember:()Lcom/fasterxml/jackson/databind/introspect/AnnotatedMember;
  #511 = Class              #679          // com/fasterxml/jackson/databind/AnnotationIntrospector
  #512 = NameAndType        #757:#758     // findSerializationConverter:(Lcom/fasterxml/jackson/databind/introspect/Annotated;)Ljava/lang/Object;
  #513 = NameAndType        #759:#760     // converterInstance:(Lcom/fasterxml/jackson/databind/introspect/Annotated;Ljava/lang/Object;)Lcom/fasterxml/jackson/databind/util/Converter;
  #514 = NameAndType        #761:#762     // getTypeFactory:()Lcom/fasterxml/jackson/databind/type/TypeFactory;
  #515 = Class              #681          // com/fasterxml/jackson/databind/util/Converter
  #516 = NameAndType        #763:#764     // getOutputType:(Lcom/fasterxml/jackson/databind/type/TypeFactory;)Lcom/fasterxml/jackson/databind/JavaType;
  #517 = NameAndType        #765:#374     // isJavaLangObject:()Z
  #518 = Utf8               com/fasterxml/jackson/databind/ser/std/StdDelegatingSerializer
  #519 = NameAndType        #217:#766     // "<init>":(Lcom/fasterxml/jackson/databind/util/Converter;Lcom/fasterxml/jackson/databind/JavaType;Lcom/fasterxml/jackson/databind/JsonSerializer;)V
  #520 = Class              #682          // com/fasterxml/jackson/databind/BeanProperty
  #521 = NameAndType        #767:#768     // getConfig:()Lcom/fasterxml/jackson/databind/SerializationConfig;
  #522 = NameAndType        #769:#770     // findFormatOverrides:(Lcom/fasterxml/jackson/databind/SerializerProvider;Lcom/fasterxml/jackson/databind/BeanProperty;Ljava/lang/Class;)Lcom/fasterxml/jackson/annotation/JsonFormat$Value;
  #523 = NameAndType        #771:#374     // hasShape:()Z
  #524 = NameAndType        #772:#216     // ANY:Lcom/fasterxml/jackson/annotation/JsonFormat$Shape;
  #525 = NameAndType        #773:#374     // isEnumType:()Z
  #526 = NameAndType        #774:#775     // $SwitchMap$com$fasterxml$jackson$annotation$JsonFormat$Shape:[I
  #527 = NameAndType        #776:#726     // ordinal:()I
  #528 = Class              #683          // com/fasterxml/jackson/databind/SerializationConfig
  #529 = NameAndType        #777:#778     // introspectClassAnnotations:(Lcom/fasterxml/jackson/databind/JavaType;)Lcom/fasterxml/jackson/databind/BeanDescription;
  #530 = NameAndType        #779:#780     // getRawClass:()Ljava/lang/Class;
  #531 = Class              #781          // com/fasterxml/jackson/databind/ser/std/EnumSerializer
  #532 = NameAndType        #782:#783     // construct:(Ljava/lang/Class;Lcom/fasterxml/jackson/databind/SerializationConfig;Lcom/fasterxml/jackson/databind/BeanDescription;Lcom/fasterxml/jackson/annotation/JsonFormat$Value;)Lcom/fasterxml/jackson/databind/ser/std/EnumSerializer;
  #533 = NameAndType        #784:#785     // handlePrimaryContextualization:(Lcom/fasterxml/jackson/databind/JsonSerializer;Lcom/fasterxml/jackson/databind/BeanProperty;)Lcom/fasterxml/jackson/databind/JsonSerializer;
  #534 = NameAndType        #786:#216     // NATURAL:Lcom/fasterxml/jackson/annotation/JsonFormat$Shape;
  #535 = NameAndType        #787:#374     // isMapLikeType:()Z
  #536 = Utf8               java/util/Map
  #537 = Class              #686          // java/lang/Class
  #538 = NameAndType        #788:#789     // isAssignableFrom:(Ljava/lang/Class;)Z
  #539 = Utf8               java/util/Map$Entry
  #540 = Utf8               Entry
  #541 = NameAndType        #790:#791     // findSuperType:(Ljava/lang/Class;)Lcom/fasterxml/jackson/databind/JavaType;
  #542 = NameAndType        #792:#793     // containedTypeOrUnknown:(I)Lcom/fasterxml/jackson/databind/JavaType;
  #543 = Utf8               com/fasterxml/jackson/databind/ser/impl/MapEntrySerializer
  #544 = NameAndType        #217:#794     // "<init>":(Lcom/fasterxml/jackson/databind/JavaType;Lcom/fasterxml/jackson/databind/JavaType;Lcom/fasterxml/jackson/databind/JavaType;ZLcom/fasterxml/jackson/databind/jsontype/TypeSerializer;Lcom/fasterxml/jackson/databind/BeanProperty;)V
  #545 = NameAndType        #795:#796     // findPropertyIgnoralByName:(Lcom/fasterxml/jackson/databind/cfg/MapperConfig;Lcom/fasterxml/jackson/databind/introspect/Annotated;)Lcom/fasterxml/jackson/annotation/JsonIgnoreProperties$Value;
  #546 = Class              #798          // com/fasterxml/jackson/annotation/JsonIgnoreProperties$Value
  #547 = NameAndType        #799:#800     // findIgnoredForSerialization:()Ljava/util/Set;
  #548 = NameAndType        #801:#802     // findPropertyInclusionByName:(Lcom/fasterxml/jackson/databind/cfg/MapperConfig;Lcom/fasterxml/jackson/databind/introspect/Annotated;)Lcom/fasterxml/jackson/annotation/JsonIncludeProperties$Value;
  #549 = Class              #804          // com/fasterxml/jackson/annotation/JsonIncludeProperties$Value
  #550 = NameAndType        #805:#800     // getIncluded:()Ljava/util/Set;
  #551 = NameAndType        #806:#807     // findObjectIdInfo:(Lcom/fasterxml/jackson/databind/introspect/Annotated;)Lcom/fasterxml/jackson/databind/introspect/ObjectIdInfo;
  #552 = NameAndType        #808:#809     // findObjectReferenceInfo:(Lcom/fasterxml/jackson/databind/introspect/Annotated;Lcom/fasterxml/jackson/databind/introspect/ObjectIdInfo;)Lcom/fasterxml/jackson/databind/introspect/ObjectIdInfo;
  #553 = Class              #685          // com/fasterxml/jackson/databind/introspect/ObjectIdInfo
  #554 = NameAndType        #810:#374     // getAlwaysAsId:()Z
  #555 = Class              #684          // com/fasterxml/jackson/databind/ser/impl/ObjectIdWriter
  #556 = NameAndType        #811:#812     // withAlwaysAsId:(Z)Lcom/fasterxml/jackson/databind/ser/impl/ObjectIdWriter;
  #557 = NameAndType        #813:#780     // getGeneratorType:()Ljava/lang/Class;
  #558 = NameAndType        #814:#815     // constructType:(Ljava/lang/reflect/Type;)Lcom/fasterxml/jackson/databind/JavaType;
  #559 = Utf8               com/fasterxml/jackson/annotation/ObjectIdGenerator
  #560 = Class              #816          // com/fasterxml/jackson/databind/type/TypeFactory
  #561 = NameAndType        #817:#818     // findTypeParameters:(Lcom/fasterxml/jackson/databind/JavaType;Ljava/lang/Class;)[Lcom/fasterxml/jackson/databind/JavaType;
  #562 = Class              #819          // com/fasterxml/jackson/annotation/ObjectIdGenerators
  #563 = Utf8               com/fasterxml/jackson/annotation/ObjectIdGenerators$PropertyGenerator
  #564 = Utf8               PropertyGenerator
  #565 = NameAndType        #820:#821     // getPropertyName:()Lcom/fasterxml/jackson/databind/PropertyName;
  #566 = NameAndType        #822:#719     // getSimpleName:()Ljava/lang/String;
  #567 = Utf8               Invalid Object Id definition for %s: cannot find property with name %s
  #568 = Utf8               java/lang/Object
  #569 = NameAndType        #823:#780     // handledType:()Ljava/lang/Class;
  #570 = Class              #824          // com/fasterxml/jackson/databind/util/ClassUtil
  #571 = NameAndType        #825:#826     // nameOf:(Ljava/lang/Class;)Ljava/lang/String;
  #572 = NameAndType        #405:#827     // name:(Ljava/lang/String;)Ljava/lang/String;
  #573 = NameAndType        #222:#828     // format:(Ljava/lang/String;[Ljava/lang/Object;)Ljava/lang/String;
  #574 = NameAndType        #829:#830     // reportBadDefinition:(Lcom/fasterxml/jackson/databind/JavaType;Ljava/lang/String;)Ljava/lang/Object;
  #575 = NameAndType        #831:#724     // equals:(Ljava/lang/Object;)Z
  #576 = Utf8               com/fasterxml/jackson/databind/ser/impl/PropertyBasedObjectIdGenerator
  #577 = NameAndType        #217:#832     // "<init>":(Lcom/fasterxml/jackson/databind/introspect/ObjectIdInfo;Lcom/fasterxml/jackson/databind/ser/BeanPropertyWriter;)V
  #578 = Utf8               com/fasterxml/jackson/databind/PropertyName
  #579 = NameAndType        #782:#833     // construct:(Lcom/fasterxml/jackson/databind/JavaType;Lcom/fasterxml/jackson/databind/PropertyName;Lcom/fasterxml/jackson/annotation/ObjectIdGenerator;Z)Lcom/fasterxml/jackson/databind/ser/impl/ObjectIdWriter;
  #580 = NameAndType        #834:#835     // objectIdGeneratorInstance:(Lcom/fasterxml/jackson/databind/introspect/Annotated;Lcom/fasterxml/jackson/databind/introspect/ObjectIdInfo;)Lcom/fasterxml/jackson/annotation/ObjectIdGenerator;
  #581 = NameAndType        #836:#758     // findFilterId:(Lcom/fasterxml/jackson/databind/introspect/Annotated;)Ljava/lang/Object;
  #582 = Class              #837          // java/util/Arrays
  #583 = NameAndType        #838:#839     // copyOf:([Ljava/lang/Object;I)[Ljava/lang/Object;
  #584 = Class              #840          // java/lang/System
  #585 = NameAndType        #841:#842     // arraycopy:(Ljava/lang/Object;ILjava/lang/Object;II)V
  #586 = NameAndType        #285:#286     // withProperties:([Lcom/fasterxml/jackson/databind/ser/BeanPropertyWriter;[Lcom/fasterxml/jackson/databind/ser/BeanPropertyWriter;)Lcom/fasterxml/jackson/databind/ser/std/BeanSerializerBase;
  #587 = NameAndType        #343:#202     // idType:Lcom/fasterxml/jackson/databind/JavaType;
  #588 = NameAndType        #843:#844     // withSerializer:(Lcom/fasterxml/jackson/databind/JsonSerializer;)Lcom/fasterxml/jackson/databind/ser/impl/ObjectIdWriter;
  #589 = NameAndType        #272:#273     // withObjectIdWriter:(Lcom/fasterxml/jackson/databind/ser/impl/ObjectIdWriter;)Lcom/fasterxml/jackson/databind/ser/std/BeanSerializerBase;
  #590 = Class              #676          // java/util/Set
  #591 = NameAndType        #845:#374     // isEmpty:()Z
  #592 = NameAndType        #283:#284     // withFilterId:(Ljava/lang/Object;)Lcom/fasterxml/jackson/databind/ser/std/BeanSerializerBase;
  #593 = NameAndType        #846:#216     // ARRAY:Lcom/fasterxml/jackson/annotation/JsonFormat$Shape;
  #594 = NameAndType        #281:#282     // asArraySerializer:()Lcom/fasterxml/jackson/databind/ser/std/BeanSerializerBase;
  #595 = NameAndType        #847:#848     // asList:([Ljava/lang/Object;)Ljava/util/List;
  #596 = Class              #849          // java/util/List
  #597 = NameAndType        #850:#371     // iterator:()Ljava/util/Iterator;
  #598 = NameAndType        #385:#379     // _serializeWithObjectId:(Ljava/lang/Object;Lcom/fasterxml/jackson/core/JsonGenerator;Lcom/fasterxml/jackson/databind/SerializerProvider;Lcom/fasterxml/jackson/databind/jsontype/TypeSerializer;)V
  #599 = Class              #851          // com/fasterxml/jackson/core/JsonToken
  #600 = NameAndType        #852:#400     // START_OBJECT:Lcom/fasterxml/jackson/core/JsonToken;
  #601 = NameAndType        #397:#398     // _typeIdDef:(Lcom/fasterxml/jackson/databind/jsontype/TypeSerializer;Ljava/lang/Object;Lcom/fasterxml/jackson/core/JsonToken;)Lcom/fasterxml/jackson/core/type/WritableTypeId;
  #602 = NameAndType        #853:#854     // writeTypePrefix:(Lcom/fasterxml/jackson/core/JsonGenerator;Lcom/fasterxml/jackson/core/type/WritableTypeId;)Lcom/fasterxml/jackson/core/type/WritableTypeId;
  #603 = Class              #690          // com/fasterxml/jackson/core/JsonGenerator
  #604 = NameAndType        #855:#856     // setCurrentValue:(Ljava/lang/Object;)V
  #605 = NameAndType        #415:#376     // serializeFieldsFiltered:(Ljava/lang/Object;Lcom/fasterxml/jackson/core/JsonGenerator;Lcom/fasterxml/jackson/databind/SerializerProvider;)V
  #606 = NameAndType        #404:#376     // serializeFields:(Ljava/lang/Object;Lcom/fasterxml/jackson/core/JsonGenerator;Lcom/fasterxml/jackson/databind/SerializerProvider;)V
  #607 = NameAndType        #857:#854     // writeTypeSuffix:(Lcom/fasterxml/jackson/core/JsonGenerator;Lcom/fasterxml/jackson/core/type/WritableTypeId;)Lcom/fasterxml/jackson/core/type/WritableTypeId;
  #608 = NameAndType        #858:#340     // generator:Lcom/fasterxml/jackson/annotation/ObjectIdGenerator;
  #609 = NameAndType        #859:#860     // findObjectId:(Ljava/lang/Object;Lcom/fasterxml/jackson/annotation/ObjectIdGenerator;)Lcom/fasterxml/jackson/databind/ser/impl/WritableObjectId;
  #610 = Class              #689          // com/fasterxml/jackson/databind/ser/impl/WritableObjectId
  #611 = NameAndType        #861:#862     // writeAsId:(Lcom/fasterxml/jackson/core/JsonGenerator;Lcom/fasterxml/jackson/databind/SerializerProvider;Lcom/fasterxml/jackson/databind/ser/impl/ObjectIdWriter;)Z
  #612 = NameAndType        #863:#864     // generateId:(Ljava/lang/Object;)Ljava/lang/Object;
  #613 = NameAndType        #865:#388     // alwaysAsId:Z
  #614 = NameAndType        #866:#300     // serializer:Lcom/fasterxml/jackson/databind/JsonSerializer;
  #615 = Class              #677          // com/fasterxml/jackson/databind/JsonSerializer
  #616 = NameAndType        #375:#376     // serialize:(Ljava/lang/Object;Lcom/fasterxml/jackson/core/JsonGenerator;Lcom/fasterxml/jackson/databind/SerializerProvider;)V
  #617 = NameAndType        #867:#856     // writeStartObject:(Ljava/lang/Object;)V
  #618 = NameAndType        #868:#869     // writeAsField:(Lcom/fasterxml/jackson/core/JsonGenerator;Lcom/fasterxml/jackson/databind/SerializerProvider;Lcom/fasterxml/jackson/databind/ser/impl/ObjectIdWriter;)V
  #619 = NameAndType        #870:#442     // writeEndObject:()V
  #620 = NameAndType        #394:#395     // _serializeObjectId:(Ljava/lang/Object;Lcom/fasterxml/jackson/core/JsonGenerator;Lcom/fasterxml/jackson/databind/SerializerProvider;Lcom/fasterxml/jackson/databind/jsontype/TypeSerializer;Lcom/fasterxml/jackson/databind/ser/impl/WritableObjectId;)V
  #621 = NameAndType        #401:#871     // typeId:(Ljava/lang/Object;Lcom/fasterxml/jackson/core/JsonToken;)Lcom/fasterxml/jackson/core/type/WritableTypeId;
  #622 = Class              #680          // com/fasterxml/jackson/databind/introspect/AnnotatedMember
  #623 = NameAndType        #872:#864     // getValue:(Ljava/lang/Object;)Ljava/lang/Object;
  #624 = Utf8
  #625 = NameAndType        #401:#873     // typeId:(Ljava/lang/Object;Lcom/fasterxml/jackson/core/JsonToken;Ljava/lang/Object;)Lcom/fasterxml/jackson/core/type/WritableTypeId;
  #626 = Utf8               java/lang/String
  #627 = NameAndType        #874:#719     // toString:()Ljava/lang/String;
  #628 = NameAndType        #875:#780     // getActiveView:()Ljava/lang/Class;
  #629 = NameAndType        #876:#376     // serializeAsField:(Ljava/lang/Object;Lcom/fasterxml/jackson/core/JsonGenerator;Lcom/fasterxml/jackson/databind/SerializerProvider;)V
  #630 = NameAndType        #877:#376     // getAndSerialize:(Ljava/lang/Object;Lcom/fasterxml/jackson/core/JsonGenerator;Lcom/fasterxml/jackson/databind/SerializerProvider;)V
  #631 = Utf8               java/lang/Exception
  #632 = Utf8               [anySetter]
  #633 = NameAndType        #878:#879     // wrapAndThrow:(Lcom/fasterxml/jackson/databind/SerializerProvider;Ljava/lang/Throwable;Ljava/lang/Object;Ljava/lang/String;)V
  #634 = Utf8               java/lang/StackOverflowError
  #635 = Utf8               com/fasterxml/jackson/databind/JsonMappingException
  #636 = Utf8               Infinite recursion (StackOverflowError)
  #637 = NameAndType        #217:#880     // "<init>":(Ljava/io/Closeable;Ljava/lang/String;Ljava/lang/Throwable;)V
  #638 = Class              #691          // com/fasterxml/jackson/databind/DatabindException
  #639 = NameAndType        #881:#882     // prependPath:(Ljava/lang/Object;Ljava/lang/String;)V
  #640 = NameAndType        #883:#884     // findPropertyFilter:(Lcom/fasterxml/jackson/databind/SerializerProvider;Ljava/lang/Object;Ljava/lang/Object;)Lcom/fasterxml/jackson/databind/ser/PropertyFilter;
  #641 = Class              #692          // com/fasterxml/jackson/databind/ser/PropertyFilter
  #642 = NameAndType        #876:#885     // serializeAsField:(Ljava/lang/Object;Lcom/fasterxml/jackson/core/JsonGenerator;Lcom/fasterxml/jackson/databind/SerializerProvider;Lcom/fasterxml/jackson/databind/ser/PropertyWriter;)V
  #643 = NameAndType        #886:#887     // getAndFilter:(Ljava/lang/Object;Lcom/fasterxml/jackson/core/JsonGenerator;Lcom/fasterxml/jackson/databind/SerializerProvider;Lcom/fasterxml/jackson/databind/ser/PropertyFilter;)V
  #644 = Utf8               object
  #645 = NameAndType        #888:#889     // createSchemaNode:(Ljava/lang/String;Z)Lcom/fasterxml/jackson/databind/node/ObjectNode;
  #646 = Utf8               com/fasterxml/jackson/databind/jsonschema/JsonSerializableSchema
  #647 = NameAndType        #890:#891     // getAnnotation:(Ljava/lang/Class;)Ljava/lang/annotation/Annotation;
  #648 = NameAndType        #392:#719     // id:()Ljava/lang/String;
  #649 = Class              #693          // com/fasterxml/jackson/databind/node/ObjectNode
  #650 = NameAndType        #892:#893     // put:(Ljava/lang/String;Ljava/lang/String;)Lcom/fasterxml/jackson/databind/node/ObjectNode;
  #651 = NameAndType        #894:#895     // objectNode:()Lcom/fasterxml/jackson/databind/node/ObjectNode;
  #652 = NameAndType        #896:#897     // depositSchemaProperty:(Lcom/fasterxml/jackson/databind/node/ObjectNode;Lcom/fasterxml/jackson/databind/SerializerProvider;)V
  #653 = NameAndType        #896:#898     // depositSchemaProperty:(Lcom/fasterxml/jackson/databind/ser/PropertyWriter;Lcom/fasterxml/jackson/databind/node/ObjectNode;Lcom/fasterxml/jackson/databind/SerializerProvider;)V
  #654 = NameAndType        #899:#900     // set:(Ljava/lang/String;Lcom/fasterxml/jackson/databind/JsonNode;)Lcom/fasterxml/jackson/databind/JsonNode;
  #655 = Class              #695          // com/fasterxml/jackson/databind/jsonFormatVisitors/JsonFormatVisitorWrapper
  #656 = NameAndType        #901:#902     // expectObjectFormat:(Lcom/fasterxml/jackson/databind/JavaType;)Lcom/fasterxml/jackson/databind/jsonFormatVisitors/JsonObjectFormatVisitor;
  #657 = NameAndType        #903:#904     // getProvider:()Lcom/fasterxml/jackson/databind/SerializerProvider;
  #658 = NameAndType        #896:#905     // depositSchemaProperty:(Lcom/fasterxml/jackson/databind/ser/PropertyWriter;Lcom/fasterxml/jackson/databind/jsonFormatVisitors/JsonObjectFormatVisitor;Lcom/fasterxml/jackson/databind/SerializerProvider;)V
  #659 = NameAndType        #896:#906     // depositSchemaProperty:(Lcom/fasterxml/jackson/databind/jsonFormatVisitors/JsonObjectFormatVisitor;Lcom/fasterxml/jackson/databind/SerializerProvider;)V
  #660 = Utf8               #object-ref
  #661 = NameAndType        #217:#907     // "<init>":(Ljava/lang/String;)V
  #662 = NameAndType        #197:#198     // NAME_FOR_OBJECT_REF:Lcom/fasterxml/jackson/databind/PropertyName;
  #663 = NameAndType        #199:#200     // NO_PROPS:[Lcom/fasterxml/jackson/databind/ser/BeanPropertyWriter;
  #664 = Utf8               com/fasterxml/jackson/databind/ser/std/BeanSerializerBase
  #665 = Utf8               com/fasterxml/jackson/databind/ser/std/StdSerializer
  #666 = Utf8               com/fasterxml/jackson/databind/ser/ContextualSerializer
  #667 = Utf8               com/fasterxml/jackson/databind/ser/ResolvableSerializer
  #668 = Utf8               com/fasterxml/jackson/databind/jsonFormatVisitors/JsonFormatVisitable
  #669 = Utf8               com/fasterxml/jackson/databind/jsonschema/SchemaAware
  #670 = Utf8               com/fasterxml/jackson/databind/ser/std/BeanSerializerBase$1
  #671 = Class              #908          // com/fasterxml/jackson/annotation/JsonFormat
  #672 = Utf8               com/fasterxml/jackson/annotation/JsonFormat$Shape
  #673 = Utf8               com/fasterxml/jackson/annotation/JsonFormat$Value
  #674 = Utf8               com/fasterxml/jackson/databind/JavaType
  #675 = Utf8               com/fasterxml/jackson/databind/ser/BeanSerializerBuilder
  #676 = Utf8               java/util/Set
  #677 = Utf8               com/fasterxml/jackson/databind/JsonSerializer
  #678 = Utf8               com/fasterxml/jackson/databind/SerializerProvider
  #679 = Utf8               com/fasterxml/jackson/databind/AnnotationIntrospector
  #680 = Utf8               com/fasterxml/jackson/databind/introspect/AnnotatedMember
  #681 = Utf8               com/fasterxml/jackson/databind/util/Converter
  #682 = Utf8               com/fasterxml/jackson/databind/BeanProperty
  #683 = Utf8               com/fasterxml/jackson/databind/SerializationConfig
  #684 = Utf8               com/fasterxml/jackson/databind/ser/impl/ObjectIdWriter
  #685 = Utf8               com/fasterxml/jackson/databind/introspect/ObjectIdInfo
  #686 = Utf8               java/lang/Class
  #687 = Utf8               java/io/IOException
  #688 = Utf8               com/fasterxml/jackson/core/type/WritableTypeId
  #689 = Utf8               com/fasterxml/jackson/databind/ser/impl/WritableObjectId
  #690 = Utf8               com/fasterxml/jackson/core/JsonGenerator
  #691 = Utf8               com/fasterxml/jackson/databind/DatabindException
  #692 = Utf8               com/fasterxml/jackson/databind/ser/PropertyFilter
  #693 = Utf8               com/fasterxml/jackson/databind/node/ObjectNode
  #694 = Utf8               com/fasterxml/jackson/databind/jsonFormatVisitors/JsonObjectFormatVisitor
  #695 = Utf8               com/fasterxml/jackson/databind/jsonFormatVisitors/JsonFormatVisitorWrapper
  #696 = Utf8               (Lcom/fasterxml/jackson/databind/JavaType;)V
  #697 = Utf8               getTypeId
  #698 = Utf8               ()Lcom/fasterxml/jackson/databind/introspect/AnnotatedMember;
  #699 = Utf8               getAnyGetter
  #700 = Utf8               ()Lcom/fasterxml/jackson/databind/ser/AnyGetterWriter;
  #701 = Utf8               getFilterId
  #702 = Utf8               ()Ljava/lang/Object;
  #703 = Utf8               getObjectIdWriter
  #704 = Utf8               ()Lcom/fasterxml/jackson/databind/ser/impl/ObjectIdWriter;
  #705 = Utf8               getBeanDescription
  #706 = Utf8               ()Lcom/fasterxml/jackson/databind/BeanDescription;
  #707 = Utf8               com/fasterxml/jackson/databind/BeanDescription
  #708 = Utf8               findExpectedFormat
  #709 = Utf8               (Lcom/fasterxml/jackson/annotation/JsonFormat$Value;)Lcom/fasterxml/jackson/annotation/JsonFormat$Value;
  #710 = Utf8               getShape
  #711 = Utf8               ()Lcom/fasterxml/jackson/annotation/JsonFormat$Shape;
  #712 = Utf8               _handledType
  #713 = Utf8               (Ljava/lang/Class;)V
  #714 = Utf8               com/fasterxml/jackson/databind/util/ArrayBuilders
  #715 = Utf8               arrayToSet
  #716 = Utf8               ([Ljava/lang/Object;)Ljava/util/HashSet;
  #717 = Utf8               (I)V
  #718 = Utf8               getName
  #719 = Utf8               ()Ljava/lang/String;
  #720 = Utf8               com/fasterxml/jackson/databind/util/IgnorePropertiesUtil
  #721 = Utf8               shouldIgnore
  #722 = Utf8               (Ljava/lang/Object;Ljava/util/Collection;Ljava/util/Collection;)Z
  #723 = Utf8               add
  #724 = Utf8               (Ljava/lang/Object;)Z
  #725 = Utf8               size
  #726 = Utf8               ()I
  #727 = Utf8               toArray
  #728 = Utf8               ([Ljava/lang/Object;)[Ljava/lang/Object;
  #729 = Utf8               com/fasterxml/jackson/databind/util/NameTransformer
  #730 = Utf8               NOP
  #731 = Utf8               (Lcom/fasterxml/jackson/databind/util/NameTransformer;)Lcom/fasterxml/jackson/databind/ser/BeanPropertyWriter;
  #732 = Utf8               willSuppressNulls
  #733 = Utf8               hasNullSerializer
  #734 = Utf8               findNullValueSerializer
  #735 = Utf8               (Lcom/fasterxml/jackson/databind/BeanProperty;)Lcom/fasterxml/jackson/databind/JsonSerializer;
  #736 = Utf8               assignNullSerializer
  #737 = Utf8               (Lcom/fasterxml/jackson/databind/JsonSerializer;)V
  #738 = Utf8               hasSerializer
  #739 = Utf8               getSerializationType
  #740 = Utf8               ()Lcom/fasterxml/jackson/databind/JavaType;
  #741 = Utf8               getType
  #742 = Utf8               isFinal
  #743 = Utf8               isContainerType
  #744 = Utf8               containedTypeCount
  #745 = Utf8               setNonTrivialBaseType
  #746 = Utf8               findValueSerializer
  #747 = Utf8               (Lcom/fasterxml/jackson/databind/JavaType;Lcom/fasterxml/jackson/databind/BeanProperty;)Lcom/fasterxml/jackson/databind/JsonSerializer;
  #748 = Utf8               getContentType
  #749 = Utf8               getTypeHandler
  #750 = Utf8               withValueTypeSerializer
  #751 = Utf8               (Lcom/fasterxml/jackson/databind/jsontype/TypeSerializer;)Lcom/fasterxml/jackson/databind/ser/ContainerSerializer;
  #752 = Utf8               assignSerializer
  #753 = Utf8               com/fasterxml/jackson/databind/ser/AnyGetterWriter
  #754 = Utf8               getAnnotationIntrospector
  #755 = Utf8               ()Lcom/fasterxml/jackson/databind/AnnotationIntrospector;
  #756 = Utf8               getMember
  #757 = Utf8               findSerializationConverter
  #758 = Utf8               (Lcom/fasterxml/jackson/databind/introspect/Annotated;)Ljava/lang/Object;
  #759 = Utf8               converterInstance
  #760 = Utf8               (Lcom/fasterxml/jackson/databind/introspect/Annotated;Ljava/lang/Object;)Lcom/fasterxml/jackson/databind/util/Converter;
  #761 = Utf8               getTypeFactory
  #762 = Utf8               ()Lcom/fasterxml/jackson/databind/type/TypeFactory;
  #763 = Utf8               getOutputType
  #764 = Utf8               (Lcom/fasterxml/jackson/databind/type/TypeFactory;)Lcom/fasterxml/jackson/databind/JavaType;
  #765 = Utf8               isJavaLangObject
  #766 = Utf8               (Lcom/fasterxml/jackson/databind/util/Converter;Lcom/fasterxml/jackson/databind/JavaType;Lcom/fasterxml/jackson/databind/JsonSerializer;)V
  #767 = Utf8               getConfig
  #768 = Utf8               ()Lcom/fasterxml/jackson/databind/SerializationConfig;
  #769 = Utf8               findFormatOverrides
  #770 = Utf8               (Lcom/fasterxml/jackson/databind/SerializerProvider;Lcom/fasterxml/jackson/databind/BeanProperty;Ljava/lang/Class;)Lcom/fasterxml/jackson/annotation/JsonFormat$Value;
  #771 = Utf8               hasShape
  #772 = Utf8               ANY
  #773 = Utf8               isEnumType
  #774 = Utf8               $SwitchMap$com$fasterxml$jackson$annotation$JsonFormat$Shape
  #775 = Utf8               [I
  #776 = Utf8               ordinal
  #777 = Utf8               introspectClassAnnotations
  #778 = Utf8               (Lcom/fasterxml/jackson/databind/JavaType;)Lcom/fasterxml/jackson/databind/BeanDescription;
  #779 = Utf8               getRawClass
  #780 = Utf8               ()Ljava/lang/Class;
  #781 = Utf8               com/fasterxml/jackson/databind/ser/std/EnumSerializer
  #782 = Utf8               construct
  #783 = Utf8               (Ljava/lang/Class;Lcom/fasterxml/jackson/databind/SerializationConfig;Lcom/fasterxml/jackson/databind/BeanDescription;Lcom/fasterxml/jackson/annotation/JsonFormat$Value;)Lcom/fasterxml/jackson/databind/ser/std/EnumSerializer;
  #784 = Utf8               handlePrimaryContextualization
  #785 = Utf8               (Lcom/fasterxml/jackson/databind/JsonSerializer;Lcom/fasterxml/jackson/databind/BeanProperty;)Lcom/fasterxml/jackson/databind/JsonSerializer;
  #786 = Utf8               NATURAL
  #787 = Utf8               isMapLikeType
  #788 = Utf8               isAssignableFrom
  #789 = Utf8               (Ljava/lang/Class;)Z
  #790 = Utf8               findSuperType
  #791 = Utf8               (Ljava/lang/Class;)Lcom/fasterxml/jackson/databind/JavaType;
  #792 = Utf8               containedTypeOrUnknown
  #793 = Utf8               (I)Lcom/fasterxml/jackson/databind/JavaType;
  #794 = Utf8               (Lcom/fasterxml/jackson/databind/JavaType;Lcom/fasterxml/jackson/databind/JavaType;Lcom/fasterxml/jackson/databind/JavaType;ZLcom/fasterxml/jackson/databind/jsontype/TypeSerializer;Lcom/fasterxml/jackson/databind/BeanProperty;)V
  #795 = Utf8               findPropertyIgnoralByName
  #796 = Utf8               (Lcom/fasterxml/jackson/databind/cfg/MapperConfig;Lcom/fasterxml/jackson/databind/introspect/Annotated;)Lcom/fasterxml/jackson/annotation/JsonIgnoreProperties$Value;
  #797 = Class              #909          // com/fasterxml/jackson/annotation/JsonIgnoreProperties
  #798 = Utf8               com/fasterxml/jackson/annotation/JsonIgnoreProperties$Value
  #799 = Utf8               findIgnoredForSerialization
  #800 = Utf8               ()Ljava/util/Set;
  #801 = Utf8               findPropertyInclusionByName
  #802 = Utf8               (Lcom/fasterxml/jackson/databind/cfg/MapperConfig;Lcom/fasterxml/jackson/databind/introspect/Annotated;)Lcom/fasterxml/jackson/annotation/JsonIncludeProperties$Value;
  #803 = Class              #910          // com/fasterxml/jackson/annotation/JsonIncludeProperties
  #804 = Utf8               com/fasterxml/jackson/annotation/JsonIncludeProperties$Value
  #805 = Utf8               getIncluded
  #806 = Utf8               findObjectIdInfo
  #807 = Utf8               (Lcom/fasterxml/jackson/databind/introspect/Annotated;)Lcom/fasterxml/jackson/databind/introspect/ObjectIdInfo;
  #808 = Utf8               findObjectReferenceInfo
  #809 = Utf8               (Lcom/fasterxml/jackson/databind/introspect/Annotated;Lcom/fasterxml/jackson/databind/introspect/ObjectIdInfo;)Lcom/fasterxml/jackson/databind/introspect/ObjectIdInfo;
  #810 = Utf8               getAlwaysAsId
  #811 = Utf8               withAlwaysAsId
  #812 = Utf8               (Z)Lcom/fasterxml/jackson/databind/ser/impl/ObjectIdWriter;
  #813 = Utf8               getGeneratorType
  #814 = Utf8               constructType
  #815 = Utf8               (Ljava/lang/reflect/Type;)Lcom/fasterxml/jackson/databind/JavaType;
  #816 = Utf8               com/fasterxml/jackson/databind/type/TypeFactory
  #817 = Utf8               findTypeParameters
  #818 = Utf8               (Lcom/fasterxml/jackson/databind/JavaType;Ljava/lang/Class;)[Lcom/fasterxml/jackson/databind/JavaType;
  #819 = Utf8               com/fasterxml/jackson/annotation/ObjectIdGenerators
  #820 = Utf8               getPropertyName
  #821 = Utf8               ()Lcom/fasterxml/jackson/databind/PropertyName;
  #822 = Utf8               getSimpleName
  #823 = Utf8               handledType
  #824 = Utf8               com/fasterxml/jackson/databind/util/ClassUtil
  #825 = Utf8               nameOf
  #826 = Utf8               (Ljava/lang/Class;)Ljava/lang/String;
  #827 = Utf8               (Ljava/lang/String;)Ljava/lang/String;
  #828 = Utf8               (Ljava/lang/String;[Ljava/lang/Object;)Ljava/lang/String;
  #829 = Utf8               reportBadDefinition
  #830 = Utf8               (Lcom/fasterxml/jackson/databind/JavaType;Ljava/lang/String;)Ljava/lang/Object;
  #831 = Utf8               equals
  #832 = Utf8               (Lcom/fasterxml/jackson/databind/introspect/ObjectIdInfo;Lcom/fasterxml/jackson/databind/ser/BeanPropertyWriter;)V
  #833 = Utf8               (Lcom/fasterxml/jackson/databind/JavaType;Lcom/fasterxml/jackson/databind/PropertyName;Lcom/fasterxml/jackson/annotation/ObjectIdGenerator;Z)Lcom/fasterxml/jackson/databind/ser/impl/ObjectIdWriter;
  #834 = Utf8               objectIdGeneratorInstance
  #835 = Utf8               (Lcom/fasterxml/jackson/databind/introspect/Annotated;Lcom/fasterxml/jackson/databind/introspect/ObjectIdInfo;)Lcom/fasterxml/jackson/annotation/ObjectIdGenerator;
  #836 = Utf8               findFilterId
  #837 = Utf8               java/util/Arrays
  #838 = Utf8               copyOf
  #839 = Utf8               ([Ljava/lang/Object;I)[Ljava/lang/Object;
  #840 = Utf8               java/lang/System
  #841 = Utf8               arraycopy
  #842 = Utf8               (Ljava/lang/Object;ILjava/lang/Object;II)V
  #843 = Utf8               withSerializer
  #844 = Utf8               (Lcom/fasterxml/jackson/databind/JsonSerializer;)Lcom/fasterxml/jackson/databind/ser/impl/ObjectIdWriter;
  #845 = Utf8               isEmpty
  #846 = Utf8               ARRAY
  #847 = Utf8               asList
  #848 = Utf8               ([Ljava/lang/Object;)Ljava/util/List;
  #849 = Utf8               java/util/List
  #850 = Utf8               iterator
  #851 = Utf8               com/fasterxml/jackson/core/JsonToken
  #852 = Utf8               START_OBJECT
  #853 = Utf8               writeTypePrefix
  #854 = Utf8               (Lcom/fasterxml/jackson/core/JsonGenerator;Lcom/fasterxml/jackson/core/type/WritableTypeId;)Lcom/fasterxml/jackson/core/type/WritableTypeId;
  #855 = Utf8               setCurrentValue
  #856 = Utf8               (Ljava/lang/Object;)V
  #857 = Utf8               writeTypeSuffix
  #858 = Utf8               generator
  #859 = Utf8               findObjectId
  #860 = Utf8               (Ljava/lang/Object;Lcom/fasterxml/jackson/annotation/ObjectIdGenerator;)Lcom/fasterxml/jackson/databind/ser/impl/WritableObjectId;
  #861 = Utf8               writeAsId
  #862 = Utf8               (Lcom/fasterxml/jackson/core/JsonGenerator;Lcom/fasterxml/jackson/databind/SerializerProvider;Lcom/fasterxml/jackson/databind/ser/impl/ObjectIdWriter;)Z
  #863 = Utf8               generateId
  #864 = Utf8               (Ljava/lang/Object;)Ljava/lang/Object;
  #865 = Utf8               alwaysAsId
  #866 = Utf8               serializer
  #867 = Utf8               writeStartObject
  #868 = Utf8               writeAsField
  #869 = Utf8               (Lcom/fasterxml/jackson/core/JsonGenerator;Lcom/fasterxml/jackson/databind/SerializerProvider;Lcom/fasterxml/jackson/databind/ser/impl/ObjectIdWriter;)V
  #870 = Utf8               writeEndObject
  #871 = Utf8               (Ljava/lang/Object;Lcom/fasterxml/jackson/core/JsonToken;)Lcom/fasterxml/jackson/core/type/WritableTypeId;
  #872 = Utf8               getValue
  #873 = Utf8               (Ljava/lang/Object;Lcom/fasterxml/jackson/core/JsonToken;Ljava/lang/Object;)Lcom/fasterxml/jackson/core/type/WritableTypeId;
  #874 = Utf8               toString
  #875 = Utf8               getActiveView
  #876 = Utf8               serializeAsField
  #877 = Utf8               getAndSerialize
  #878 = Utf8               wrapAndThrow
  #879 = Utf8               (Lcom/fasterxml/jackson/databind/SerializerProvider;Ljava/lang/Throwable;Ljava/lang/Object;Ljava/lang/String;)V
  #880 = Utf8               (Ljava/io/Closeable;Ljava/lang/String;Ljava/lang/Throwable;)V
  #881 = Utf8               prependPath
  #882 = Utf8               (Ljava/lang/Object;Ljava/lang/String;)V
  #883 = Utf8               findPropertyFilter
  #884 = Utf8               (Lcom/fasterxml/jackson/databind/SerializerProvider;Ljava/lang/Object;Ljava/lang/Object;)Lcom/fasterxml/jackson/databind/ser/PropertyFilter;
  #885 = Utf8               (Ljava/lang/Object;Lcom/fasterxml/jackson/core/JsonGenerator;Lcom/fasterxml/jackson/databind/SerializerProvider;Lcom/fasterxml/jackson/databind/ser/PropertyWriter;)V
  #886 = Utf8               getAndFilter
  #887 = Utf8               (Ljava/lang/Object;Lcom/fasterxml/jackson/core/JsonGenerator;Lcom/fasterxml/jackson/databind/SerializerProvider;Lcom/fasterxml/jackson/databind/ser/PropertyFilter;)V
  #888 = Utf8               createSchemaNode
  #889 = Utf8               (Ljava/lang/String;Z)Lcom/fasterxml/jackson/databind/node/ObjectNode;
  #890 = Utf8               getAnnotation
  #891 = Utf8               (Ljava/lang/Class;)Ljava/lang/annotation/Annotation;
  #892 = Utf8               put
  #893 = Utf8               (Ljava/lang/String;Ljava/lang/String;)Lcom/fasterxml/jackson/databind/node/ObjectNode;
  #894 = Utf8               objectNode
  #895 = Utf8               ()Lcom/fasterxml/jackson/databind/node/ObjectNode;
  #896 = Utf8               depositSchemaProperty
  #897 = Utf8               (Lcom/fasterxml/jackson/databind/node/ObjectNode;Lcom/fasterxml/jackson/databind/SerializerProvider;)V
  #898 = Utf8               (Lcom/fasterxml/jackson/databind/ser/PropertyWriter;Lcom/fasterxml/jackson/databind/node/ObjectNode;Lcom/fasterxml/jackson/databind/SerializerProvider;)V
  #899 = Utf8               set
  #900 = Utf8               (Ljava/lang/String;Lcom/fasterxml/jackson/databind/JsonNode;)Lcom/fasterxml/jackson/databind/JsonNode;
  #901 = Utf8               expectObjectFormat
  #902 = Utf8               (Lcom/fasterxml/jackson/databind/JavaType;)Lcom/fasterxml/jackson/databind/jsonFormatVisitors/JsonObjectFormatVisitor;
  #903 = Utf8               getProvider
  #904 = Utf8               ()Lcom/fasterxml/jackson/databind/SerializerProvider;
  #905 = Utf8               (Lcom/fasterxml/jackson/databind/ser/PropertyWriter;Lcom/fasterxml/jackson/databind/jsonFormatVisitors/JsonObjectFormatVisitor;Lcom/fasterxml/jackson/databind/SerializerProvider;)V
  #906 = Utf8               (Lcom/fasterxml/jackson/databind/jsonFormatVisitors/JsonObjectFormatVisitor;Lcom/fasterxml/jackson/databind/SerializerProvider;)V
  #907 = Utf8               (Ljava/lang/String;)V
  #908 = Utf8               com/fasterxml/jackson/annotation/JsonFormat
  #909 = Utf8               com/fasterxml/jackson/annotation/JsonIgnoreProperties
  #910 = Utf8               com/fasterxml/jackson/annotation/JsonIncludeProperties
{
  protected static final com.fasterxml.jackson.databind.PropertyName NAME_FOR_OBJECT_REF;
    descriptor: Lcom/fasterxml/jackson/databind/PropertyName;
    flags: (0x001c) ACC_PROTECTED, ACC_STATIC, ACC_FINAL

  protected static final com.fasterxml.jackson.databind.ser.BeanPropertyWriter[] NO_PROPS;
    descriptor: [Lcom/fasterxml/jackson/databind/ser/BeanPropertyWriter;
    flags: (0x001c) ACC_PROTECTED, ACC_STATIC, ACC_FINAL

  protected final com.fasterxml.jackson.databind.JavaType _beanType;
    descriptor: Lcom/fasterxml/jackson/databind/JavaType;
    flags: (0x0014) ACC_PROTECTED, ACC_FINAL

  protected final com.fasterxml.jackson.databind.ser.BeanPropertyWriter[] _props;
    descriptor: [Lcom/fasterxml/jackson/databind/ser/BeanPropertyWriter;
    flags: (0x0014) ACC_PROTECTED, ACC_FINAL

  protected final com.fasterxml.jackson.databind.ser.BeanPropertyWriter[] _filteredProps;
    descriptor: [Lcom/fasterxml/jackson/databind/ser/BeanPropertyWriter;
    flags: (0x0014) ACC_PROTECTED, ACC_FINAL

  protected final com.fasterxml.jackson.databind.ser.AnyGetterWriter _anyGetterWriter;
    descriptor: Lcom/fasterxml/jackson/databind/ser/AnyGetterWriter;
    flags: (0x0014) ACC_PROTECTED, ACC_FINAL

  protected final java.lang.Object _propertyFilterId;
    descriptor: Ljava/lang/Object;
    flags: (0x0014) ACC_PROTECTED, ACC_FINAL

  protected final com.fasterxml.jackson.databind.introspect.AnnotatedMember _typeId;
    descriptor: Lcom/fasterxml/jackson/databind/introspect/AnnotatedMember;
    flags: (0x0014) ACC_PROTECTED, ACC_FINAL

  protected final com.fasterxml.jackson.databind.ser.impl.ObjectIdWriter _objectIdWriter;
    descriptor: Lcom/fasterxml/jackson/databind/ser/impl/ObjectIdWriter;
    flags: (0x0014) ACC_PROTECTED, ACC_FINAL

  protected final com.fasterxml.jackson.annotation.JsonFormat$Shape _serializationShape;
    descriptor: Lcom/fasterxml/jackson/annotation/JsonFormat$Shape;
    flags: (0x0014) ACC_PROTECTED, ACC_FINAL

  protected com.fasterxml.jackson.databind.ser.std.BeanSerializerBase(com.fasterxml.jackson.databind.JavaType, com.fasterxml.jackson.databind.ser.BeanSerializerBuilder, com.fasterxml.jackson.databind.ser.BeanPropertyWriter[], com.fasterxml.jackson.databind.ser.BeanPropertyWriter[]);
    descriptor: (Lcom/fasterxml/jackson/databind/JavaType;Lcom/fasterxml/jackson/databind/ser/BeanSerializerBuilder;[Lcom/fasterxml/jackson/databind/ser/BeanPropertyWriter;[Lcom/fasterxml/jackson/databind/ser/BeanPropertyWriter;)V
    flags: (0x0004) ACC_PROTECTED
    Code:
      stack=2, locals=6, args_size=5
         0: aload_0
         1: aload_1
         2: invokespecial #1                  // Method com/fasterxml/jackson/databind/ser/std/StdSerializer."<init>":(Lcom/fasterxml/jackson/databind/JavaType;)V
         5: aload_0
         6: aload_1
         7: putfield      #2                  // Field _beanType:Lcom/fasterxml/jackson/databind/JavaType;
        10: aload_0
        11: aload_3
        12: putfield      #3                  // Field _props:[Lcom/fasterxml/jackson/databind/ser/BeanPropertyWriter;
        15: aload_0
        16: aload         4
        18: putfield      #4                  // Field _filteredProps:[Lcom/fasterxml/jackson/databind/ser/BeanPropertyWriter;
        21: aload_2
        22: ifnonnull     53
        25: aload_0
        26: aconst_null
        27: putfield      #5                  // Field _typeId:Lcom/fasterxml/jackson/databind/introspect/AnnotatedMember;
        30: aload_0
        31: aconst_null
        32: putfield      #6                  // Field _anyGetterWriter:Lcom/fasterxml/jackson/databind/ser/AnyGetterWriter;
        35: aload_0
        36: aconst_null
        37: putfield      #7                  // Field _propertyFilterId:Ljava/lang/Object;
        40: aload_0
        41: aconst_null
        42: putfield      #8                  // Field _objectIdWriter:Lcom/fasterxml/jackson/databind/ser/impl/ObjectIdWriter;
        45: aload_0
        46: aconst_null
        47: putfield      #9                  // Field _serializationShape:Lcom/fasterxml/jackson/annotation/JsonFormat$Shape;
        50: goto          104
        53: aload_0
        54: aload_2
        55: invokevirtual #10                 // Method com/fasterxml/jackson/databind/ser/BeanSerializerBuilder.getTypeId:()Lcom/fasterxml/jackson/databind/introspect/AnnotatedMember;
        58: putfield      #5                  // Field _typeId:Lcom/fasterxml/jackson/databind/introspect/AnnotatedMember;
        61: aload_0
        62: aload_2
        63: invokevirtual #11                 // Method com/fasterxml/jackson/databind/ser/BeanSerializerBuilder.getAnyGetter:()Lcom/fasterxml/jackson/databind/ser/AnyGetterWriter;
        66: putfield      #6                  // Field _anyGetterWriter:Lcom/fasterxml/jackson/databind/ser/AnyGetterWriter;
        69: aload_0
        70: aload_2
        71: invokevirtual #12                 // Method com/fasterxml/jackson/databind/ser/BeanSerializerBuilder.getFilterId:()Ljava/lang/Object;
        74: putfield      #7                  // Field _propertyFilterId:Ljava/lang/Object;
        77: aload_0
        78: aload_2
        79: invokevirtual #13                 // Method com/fasterxml/jackson/databind/ser/BeanSerializerBuilder.getObjectIdWriter:()Lcom/fasterxml/jackson/databind/ser/impl/ObjectIdWriter;
        82: putfield      #8                  // Field _objectIdWriter:Lcom/fasterxml/jackson/databind/ser/impl/ObjectIdWriter;
        85: aload_2
        86: invokevirtual #14                 // Method com/fasterxml/jackson/databind/ser/BeanSerializerBuilder.getBeanDescription:()Lcom/fasterxml/jackson/databind/BeanDescription;
        89: aconst_null
        90: invokevirtual #15                 // Method com/fasterxml/jackson/databind/BeanDescription.findExpectedFormat:(Lcom/fasterxml/jackson/annotation/JsonFormat$Value;)Lcom/fasterxml/jackson/annotation/JsonFormat$Value;
        93: astore        5
        95: aload_0
        96: aload         5
        98: invokevirtual #16                 // Method com/fasterxml/jackson/annotation/JsonFormat$Value.getShape:()Lcom/fasterxml/jackson/annotation/JsonFormat$Shape;
       101: putfield      #9                  // Field _serializationShape:Lcom/fasterxml/jackson/annotation/JsonFormat$Shape;
       104: return
      LineNumberTable:
        line 116: 0
        line 117: 5
        line 118: 10
        line 119: 15
        line 120: 21
        line 123: 25
        line 124: 30
        line 125: 35
        line 126: 40
        line 127: 45
        line 129: 53
        line 130: 61
        line 131: 69
        line 132: 77
        line 133: 85
        line 134: 95
        line 136: 104
      LocalVariableTable:
        Start  Length  Slot  Name   Signature
           95       9     5 format   Lcom/fasterxml/jackson/annotation/JsonFormat$Value;
            0     105     0  this   Lcom/fasterxml/jackson/databind/ser/std/BeanSerializerBase;
            0     105     1  type   Lcom/fasterxml/jackson/databind/JavaType;
            0     105     2 builder   Lcom/fasterxml/jackson/databind/ser/BeanSerializerBuilder;
            0     105     3 properties   [Lcom/fasterxml/jackson/databind/ser/BeanPropertyWriter;
            0     105     4 filteredProperties   [Lcom/fasterxml/jackson/databind/ser/BeanPropertyWriter;
      StackMapTable: number_of_entries = 2
        frame_type = 255 /* full_frame */
          offset_delta = 53
          locals = [ class com/fasterxml/jackson/databind/ser/std/BeanSerializerBase, class com/fasterxml/jackson/databind/JavaType, class com/fasterxml/jackson/databind/ser/BeanSerializerBuilder, class "[Lcom/fasterxml/jackson/databind/ser/BeanPropertyWriter;", class "[Lcom/fasterxml/jackson/databind/ser/BeanPropertyWriter;" ]
          stack = []
        frame_type = 50 /* same */

  protected com.fasterxml.jackson.databind.ser.std.BeanSerializerBase(com.fasterxml.jackson.databind.ser.std.BeanSerializerBase, com.fasterxml.jackson.databind.ser.BeanPropertyWriter[], com.fasterxml.jackson.databind.ser.BeanPropertyWriter[]);
    descriptor: (Lcom/fasterxml/jackson/databind/ser/std/BeanSerializerBase;[Lcom/fasterxml/jackson/databind/ser/BeanPropertyWriter;[Lcom/fasterxml/jackson/databind/ser/BeanPropertyWriter;)V
    flags: (0x0004) ACC_PROTECTED
    Code:
      stack=2, locals=4, args_size=4
         0: aload_0
         1: aload_1
         2: getfield      #17                 // Field _handledType:Ljava/lang/Class;
         5: invokespecial #18                 // Method com/fasterxml/jackson/databind/ser/std/StdSerializer."<init>":(Ljava/lang/Class;)V
         8: aload_0
         9: aload_1
        10: getfield      #2                  // Field _beanType:Lcom/fasterxml/jackson/databind/JavaType;
        13: putfield      #2                  // Field _beanType:Lcom/fasterxml/jackson/databind/JavaType;
        16: aload_0
        17: aload_2
        18: putfield      #3                  // Field _props:[Lcom/fasterxml/jackson/databind/ser/BeanPropertyWriter;
        21: aload_0
        22: aload_3
        23: putfield      #4                  // Field _filteredProps:[Lcom/fasterxml/jackson/databind/ser/BeanPropertyWriter;
        26: aload_0
        27: aload_1
        28: getfield      #5                  // Field _typeId:Lcom/fasterxml/jackson/databind/introspect/AnnotatedMember;
        31: putfield      #5                  // Field _typeId:Lcom/fasterxml/jackson/databind/introspect/AnnotatedMember;
        34: aload_0
        35: aload_1
        36: getfield      #6                  // Field _anyGetterWriter:Lcom/fasterxml/jackson/databind/ser/AnyGetterWriter;
        39: putfield      #6                  // Field _anyGetterWriter:Lcom/fasterxml/jackson/databind/ser/AnyGetterWriter;
        42: aload_0
        43: aload_1
        44: getfield      #8                  // Field _objectIdWriter:Lcom/fasterxml/jackson/databind/ser/impl/ObjectIdWriter;
        47: putfield      #8                  // Field _objectIdWriter:Lcom/fasterxml/jackson/databind/ser/impl/ObjectIdWriter;
        50: aload_0
        51: aload_1
        52: getfield      #7                  // Field _propertyFilterId:Ljava/lang/Object;
        55: putfield      #7                  // Field _propertyFilterId:Ljava/lang/Object;
        58: aload_0
        59: aload_1
        60: getfield      #9                  // Field _serializationShape:Lcom/fasterxml/jackson/annotation/JsonFormat$Shape;
        63: putfield      #9                  // Field _serializationShape:Lcom/fasterxml/jackson/annotation/JsonFormat$Shape;
        66: return
      LineNumberTable:
        line 141: 0
        line 142: 8
        line 143: 16
        line 144: 21
        line 146: 26
        line 147: 34
        line 148: 42
        line 149: 50
        line 150: 58
        line 151: 66
      LocalVariableTable:
        Start  Length  Slot  Name   Signature
            0      67     0  this   Lcom/fasterxml/jackson/databind/ser/std/BeanSerializerBase;
            0      67     1   src   Lcom/fasterxml/jackson/databind/ser/std/BeanSerializerBase;
            0      67     2 properties   [Lcom/fasterxml/jackson/databind/ser/BeanPropertyWriter;
            0      67     3 filteredProperties   [Lcom/fasterxml/jackson/databind/ser/BeanPropertyWriter;

  protected com.fasterxml.jackson.databind.ser.std.BeanSerializerBase(com.fasterxml.jackson.databind.ser.std.BeanSerializerBase, com.fasterxml.jackson.databind.ser.impl.ObjectIdWriter);
    descriptor: (Lcom/fasterxml/jackson/databind/ser/std/BeanSerializerBase;Lcom/fasterxml/jackson/databind/ser/impl/ObjectIdWriter;)V
    flags: (0x0004) ACC_PROTECTED
    Code:
      stack=4, locals=3, args_size=3
         0: aload_0
         1: aload_1
         2: aload_2
         3: aload_1
         4: getfield      #7                  // Field _propertyFilterId:Ljava/lang/Object;
         7: invokespecial #19                 // Method "<init>":(Lcom/fasterxml/jackson/databind/ser/std/BeanSerializerBase;Lcom/fasterxml/jackson/databind/ser/impl/ObjectIdWriter;Ljava/lang/Object;)V
        10: return
      LineNumberTable:
        line 156: 0
        line 157: 10
      LocalVariableTable:
        Start  Length  Slot  Name   Signature
            0      11     0  this   Lcom/fasterxml/jackson/databind/ser/std/BeanSerializerBase;
            0      11     1   src   Lcom/fasterxml/jackson/databind/ser/std/BeanSerializerBase;
            0      11     2 objectIdWriter   Lcom/fasterxml/jackson/databind/ser/impl/ObjectIdWriter;

  protected com.fasterxml.jackson.databind.ser.std.BeanSerializerBase(com.fasterxml.jackson.databind.ser.std.BeanSerializerBase, com.fasterxml.jackson.databind.ser.impl.ObjectIdWriter, java.lang.Object);
    descriptor: (Lcom/fasterxml/jackson/databind/ser/std/BeanSerializerBase;Lcom/fasterxml/jackson/databind/ser/impl/ObjectIdWriter;Ljava/lang/Object;)V
    flags: (0x0004) ACC_PROTECTED
    Code:
      stack=2, locals=4, args_size=4
         0: aload_0
         1: aload_1
         2: getfield      #17                 // Field _handledType:Ljava/lang/Class;
         5: invokespecial #18                 // Method com/fasterxml/jackson/databind/ser/std/StdSerializer."<init>":(Ljava/lang/Class;)V
         8: aload_0
         9: aload_1
        10: getfield      #2                  // Field _beanType:Lcom/fasterxml/jackson/databind/JavaType;
        13: putfield      #2                  // Field _beanType:Lcom/fasterxml/jackson/databind/JavaType;
        16: aload_0
        17: aload_1
        18: getfield      #3                  // Field _props:[Lcom/fasterxml/jackson/databind/ser/BeanPropertyWriter;
        21: putfield      #3                  // Field _props:[Lcom/fasterxml/jackson/databind/ser/BeanPropertyWriter;
        24: aload_0
        25: aload_1
        26: getfield      #4                  // Field _filteredProps:[Lcom/fasterxml/jackson/databind/ser/BeanPropertyWriter;
        29: putfield      #4                  // Field _filteredProps:[Lcom/fasterxml/jackson/databind/ser/BeanPropertyWriter;
        32: aload_0
        33: aload_1
        34: getfield      #5                  // Field _typeId:Lcom/fasterxml/jackson/databind/introspect/AnnotatedMember;
        37: putfield      #5                  // Field _typeId:Lcom/fasterxml/jackson/databind/introspect/AnnotatedMember;
        40: aload_0
        41: aload_1
        42: getfield      #6                  // Field _anyGetterWriter:Lcom/fasterxml/jackson/databind/ser/AnyGetterWriter;
        45: putfield      #6                  // Field _anyGetterWriter:Lcom/fasterxml/jackson/databind/ser/AnyGetterWriter;
        48: aload_0
        49: aload_2
        50: putfield      #8                  // Field _objectIdWriter:Lcom/fasterxml/jackson/databind/ser/impl/ObjectIdWriter;
        53: aload_0
        54: aload_3
        55: putfield      #7                  // Field _propertyFilterId:Ljava/lang/Object;
        58: aload_0
        59: aload_1
        60: getfield      #9                  // Field _serializationShape:Lcom/fasterxml/jackson/annotation/JsonFormat$Shape;
        63: putfield      #9                  // Field _serializationShape:Lcom/fasterxml/jackson/annotation/JsonFormat$Shape;
        66: return
      LineNumberTable:
        line 165: 0
        line 166: 8
        line 167: 16
        line 168: 24
        line 170: 32
        line 171: 40
        line 172: 48
        line 173: 53
        line 174: 58
        line 175: 66
      LocalVariableTable:
        Start  Length  Slot  Name   Signature
            0      67     0  this   Lcom/fasterxml/jackson/databind/ser/std/BeanSerializerBase;
            0      67     1   src   Lcom/fasterxml/jackson/databind/ser/std/BeanSerializerBase;
            0      67     2 objectIdWriter   Lcom/fasterxml/jackson/databind/ser/impl/ObjectIdWriter;
            0      67     3 filterId   Ljava/lang/Object;

  protected com.fasterxml.jackson.databind.ser.std.BeanSerializerBase(com.fasterxml.jackson.databind.ser.std.BeanSerializerBase, java.lang.String[]);
    descriptor: (Lcom/fasterxml/jackson/databind/ser/std/BeanSerializerBase;[Ljava/lang/String;)V
    flags: (0x0004) ACC_PROTECTED
    Code:
      stack=4, locals=3, args_size=3
         0: aload_0
         1: aload_1
         2: aload_2
         3: invokestatic  #20                 // Method com/fasterxml/jackson/databind/util/ArrayBuilders.arrayToSet:([Ljava/lang/Object;)Ljava/util/HashSet;
         6: aconst_null
         7: invokespecial #21                 // Method "<init>":(Lcom/fasterxml/jackson/databind/ser/std/BeanSerializerBase;Ljava/util/Set;Ljava/util/Set;)V
        10: return
      LineNumberTable:
        line 180: 0
        line 181: 10
      LocalVariableTable:
        Start  Length  Slot  Name   Signature
            0      11     0  this   Lcom/fasterxml/jackson/databind/ser/std/BeanSerializerBase;
            0      11     1   src   Lcom/fasterxml/jackson/databind/ser/std/BeanSerializerBase;
            0      11     2 toIgnore   [Ljava/lang/String;
    Deprecated: true
    RuntimeVisibleAnnotations:
      0: #248()
        java.lang.Deprecated

  protected com.fasterxml.jackson.databind.ser.std.BeanSerializerBase(com.fasterxml.jackson.databind.ser.std.BeanSerializerBase, java.util.Set<java.lang.String>);
    descriptor: (Lcom/fasterxml/jackson/databind/ser/std/BeanSerializerBase;Ljava/util/Set;)V
    flags: (0x0004) ACC_PROTECTED
    Code:
      stack=4, locals=3, args_size=3
         0: aload_0
         1: aload_1
         2: aload_2
         3: aconst_null
         4: invokespecial #21                 // Method "<init>":(Lcom/fasterxml/jackson/databind/ser/std/BeanSerializerBase;Ljava/util/Set;Ljava/util/Set;)V
         7: return
      LineNumberTable:
        line 185: 0
        line 186: 7
      LocalVariableTable:
        Start  Length  Slot  Name   Signature
            0       8     0  this   Lcom/fasterxml/jackson/databind/ser/std/BeanSerializerBase;
            0       8     1   src   Lcom/fasterxml/jackson/databind/ser/std/BeanSerializerBase;
            0       8     2 toIgnore   Ljava/util/Set;
      LocalVariableTypeTable:
        Start  Length  Slot  Name   Signature
            0       8     2 toIgnore   Ljava/util/Set<Ljava/lang/String;>;
    Deprecated: true
    Signature: #254                         // (Lcom/fasterxml/jackson/databind/ser/std/BeanSerializerBase;Ljava/util/Set<Ljava/lang/String;>;)V
    RuntimeVisibleAnnotations:
      0: #248()
        java.lang.Deprecated

  protected com.fasterxml.jackson.databind.ser.std.BeanSerializerBase(com.fasterxml.jackson.databind.ser.std.BeanSerializerBase, java.util.Set<java.lang.String>, java.util.Set<java.lang.String>);
    descriptor: (Lcom/fasterxml/jackson/databind/ser/std/BeanSerializerBase;Ljava/util/Set;Ljava/util/Set;)V
    flags: (0x0004) ACC_PROTECTED
    Code:
      stack=3, locals=11, args_size=4
         0: aload_0
         1: aload_1
         2: getfield      #17                 // Field _handledType:Ljava/lang/Class;
         5: invokespecial #18                 // Method com/fasterxml/jackson/databind/ser/std/StdSerializer."<init>":(Ljava/lang/Class;)V
         8: aload_0
         9: aload_1
        10: getfield      #2                  // Field _beanType:Lcom/fasterxml/jackson/databind/JavaType;
        13: putfield      #2                  // Field _beanType:Lcom/fasterxml/jackson/databind/JavaType;
        16: aload_1
        17: getfield      #3                  // Field _props:[Lcom/fasterxml/jackson/databind/ser/BeanPropertyWriter;
        20: astore        4
        22: aload_1
        23: getfield      #4                  // Field _filteredProps:[Lcom/fasterxml/jackson/databind/ser/BeanPropertyWriter;
        26: astore        5
        28: aload         4
        30: arraylength
        31: istore        6
        33: new           #22                 // class java/util/ArrayList
        36: dup
        37: iload         6
        39: invokespecial #23                 // Method java/util/ArrayList."<init>":(I)V
        42: astore        7
        44: aload         5
        46: ifnonnull     53
        49: aconst_null
        50: goto          62
        53: new           #22                 // class java/util/ArrayList
        56: dup
        57: iload         6
        59: invokespecial #23                 // Method java/util/ArrayList."<init>":(I)V
        62: astore        8
        64: iconst_0
        65: istore        9
        67: iload         9
        69: iload         6
        71: if_icmpge     127
        74: aload         4
        76: iload         9
        78: aaload
        79: astore        10
        81: aload         10
        83: invokevirtual #24                 // Method com/fasterxml/jackson/databind/ser/BeanPropertyWriter.getName:()Ljava/lang/String;
        86: aload_2
        87: aload_3
        88: invokestatic  #25                 // Method com/fasterxml/jackson/databind/util/IgnorePropertiesUtil.shouldIgnore:(Ljava/lang/Object;Ljava/util/Collection;Ljava/util/Collection;)Z
        91: ifeq          97
        94: goto          121
        97: aload         7
        99: aload         10
       101: invokevirtual #26                 // Method java/util/ArrayList.add:(Ljava/lang/Object;)Z
       104: pop
       105: aload         5
       107: ifnull        121
       110: aload         8
       112: aload         5
       114: iload         9
       116: aaload
       117: invokevirtual #26                 // Method java/util/ArrayList.add:(Ljava/lang/Object;)Z
       120: pop
       121: iinc          9, 1
       124: goto          67
       127: aload_0
       128: aload         7
       130: aload         7
       132: invokevirtual #27                 // Method java/util/ArrayList.size:()I
       135: anewarray     #28                 // class com/fasterxml/jackson/databind/ser/BeanPropertyWriter
       138: invokevirtual #29                 // Method java/util/ArrayList.toArray:([Ljava/lang/Object;)[Ljava/lang/Object;
       141: checkcast     #30                 // class "[Lcom/fasterxml/jackson/databind/ser/BeanPropertyWriter;"
       144: putfield      #3                  // Field _props:[Lcom/fasterxml/jackson/databind/ser/BeanPropertyWriter;
       147: aload_0
       148: aload         8
       150: ifnonnull     157
       153: aconst_null
       154: goto          173
       157: aload         8
       159: aload         8
       161: invokevirtual #27                 // Method java/util/ArrayList.size:()I
       164: anewarray     #28                 // class com/fasterxml/jackson/databind/ser/BeanPropertyWriter
       167: invokevirtual #29                 // Method java/util/ArrayList.toArray:([Ljava/lang/Object;)[Ljava/lang/Object;
       170: checkcast     #30                 // class "[Lcom/fasterxml/jackson/databind/ser/BeanPropertyWriter;"
       173: putfield      #4                  // Field _filteredProps:[Lcom/fasterxml/jackson/databind/ser/BeanPropertyWriter;
       176: aload_0
       177: aload_1
       178: getfield      #5                  // Field _typeId:Lcom/fasterxml/jackson/databind/introspect/AnnotatedMember;
       181: putfield      #5                  // Field _typeId:Lcom/fasterxml/jackson/databind/introspect/AnnotatedMember;
       184: aload_0
       185: aload_1
       186: getfield      #6                  // Field _anyGetterWriter:Lcom/fasterxml/jackson/databind/ser/AnyGetterWriter;
       189: putfield      #6                  // Field _anyGetterWriter:Lcom/fasterxml/jackson/databind/ser/AnyGetterWriter;
       192: aload_0
       193: aload_1
       194: getfield      #8                  // Field _objectIdWriter:Lcom/fasterxml/jackson/databind/ser/impl/ObjectIdWriter;
       197: putfield      #8                  // Field _objectIdWriter:Lcom/fasterxml/jackson/databind/ser/impl/ObjectIdWriter;
       200: aload_0
       201: aload_1
       202: getfield      #7                  // Field _propertyFilterId:Ljava/lang/Object;
       205: putfield      #7                  // Field _propertyFilterId:Ljava/lang/Object;
       208: aload_0
       209: aload_1
       210: getfield      #9                  // Field _serializationShape:Lcom/fasterxml/jackson/annotation/JsonFormat$Shape;
       213: putfield      #9                  // Field _serializationShape:Lcom/fasterxml/jackson/annotation/JsonFormat$Shape;
       216: return
      LineNumberTable:
        line 190: 0
        line 192: 8
        line 193: 16
        line 194: 22
        line 195: 28
        line 197: 33
        line 198: 44
        line 200: 64
        line 201: 74
        line 203: 81
        line 204: 94
        line 206: 97
        line 207: 105
        line 208: 110
        line 200: 121
        line 211: 127
        line 212: 147
        line 214: 176
        line 215: 184
        line 216: 192
        line 217: 200
        line 218: 208
        line 219: 216
      LocalVariableTable:
        Start  Length  Slot  Name   Signature
           81      40    10   bpw   Lcom/fasterxml/jackson/databind/ser/BeanPropertyWriter;
           67      60     9     i   I
            0     217     0  this   Lcom/fasterxml/jackson/databind/ser/std/BeanSerializerBase;
            0     217     1   src   Lcom/fasterxml/jackson/databind/ser/std/BeanSerializerBase;
            0     217     2 toIgnore   Ljava/util/Set;
            0     217     3 toInclude   Ljava/util/Set;
           22     195     4 propsIn   [Lcom/fasterxml/jackson/databind/ser/BeanPropertyWriter;
           28     189     5 fpropsIn   [Lcom/fasterxml/jackson/databind/ser/BeanPropertyWriter;
           33     184     6   len   I
           44     173     7 propsOut   Ljava/util/ArrayList;
           64     153     8 fpropsOut   Ljava/util/ArrayList;
      LocalVariableTypeTable:
        Start  Length  Slot  Name   Signature
            0     217     2 toIgnore   Ljava/util/Set<Ljava/lang/String;>;
            0     217     3 toInclude   Ljava/util/Set<Ljava/lang/String;>;
           44     173     7 propsOut   Ljava/util/ArrayList<Lcom/fasterxml/jackson/databind/ser/BeanPropertyWriter;>;
           64     153     8 fpropsOut   Ljava/util/ArrayList<Lcom/fasterxml/jackson/databind/ser/BeanPropertyWriter;>;
      StackMapTable: number_of_entries = 8
        frame_type = 255 /* full_frame */
          offset_delta = 53
          locals = [ class com/fasterxml/jackson/databind/ser/std/BeanSerializerBase, class com/fasterxml/jackson/databind/ser/std/BeanSerializerBase, class java/util/Set, class java/util/Set, class "[Lcom/fasterxml/jackson/databind/ser/BeanPropertyWriter;", class "[Lcom/fasterxml/jackson/databind/ser/BeanPropertyWriter;", int, class java/util/ArrayList ]
          stack = []
        frame_type = 72 /* same_locals_1_stack_item */
          stack = [ class java/util/ArrayList ]
        frame_type = 253 /* append */
          offset_delta = 4
          locals = [ class java/util/ArrayList, int ]
        frame_type = 252 /* append */
          offset_delta = 29
          locals = [ class com/fasterxml/jackson/databind/ser/BeanPropertyWriter ]
        frame_type = 250 /* chop */
          offset_delta = 23
        frame_type = 250 /* chop */
          offset_delta = 5
        frame_type = 93 /* same_locals_1_stack_item */
          stack = [ class com/fasterxml/jackson/databind/ser/std/BeanSerializerBase ]
        frame_type = 255 /* full_frame */
          offset_delta = 15
          locals = [ class com/fasterxml/jackson/databind/ser/std/BeanSerializerBase, class com/fasterxml/jackson/databind/ser/std/BeanSerializerBase, class java/util/Set, class java/util/Set, class "[Lcom/fasterxml/jackson/databind/ser/BeanPropertyWriter;", class "[Lcom/fasterxml/jackson/databind/ser/BeanPropertyWriter;", int, class java/util/ArrayList, class java/util/ArrayList ]
          stack = [ class com/fasterxml/jackson/databind/ser/std/BeanSerializerBase, class "[Lcom/fasterxml/jackson/databind/ser/BeanPropertyWriter;" ]
    Signature: #271                         // (Lcom/fasterxml/jackson/databind/ser/std/BeanSerializerBase;Ljava/util/Set<Ljava/lang/String;>;Ljava/util/Set<Ljava/lang/String;>;)V

  public abstract com.fasterxml.jackson.databind.ser.std.BeanSerializerBase withObjectIdWriter(com.fasterxml.jackson.databind.ser.impl.ObjectIdWriter);
    descriptor: (Lcom/fasterxml/jackson/databind/ser/impl/ObjectIdWriter;)Lcom/fasterxml/jackson/databind/ser/std/BeanSerializerBase;
    flags: (0x0401) ACC_PUBLIC, ACC_ABSTRACT

  protected com.fasterxml.jackson.databind.ser.std.BeanSerializerBase withIgnorals(java.util.Set<java.lang.String>);
    descriptor: (Ljava/util/Set;)Lcom/fasterxml/jackson/databind/ser/std/BeanSerializerBase;
    flags: (0x0004) ACC_PROTECTED
    Code:
      stack=3, locals=2, args_size=2
         0: aload_0
         1: aload_1
         2: aconst_null
         3: invokevirtual #31                 // Method withByNameInclusion:(Ljava/util/Set;Ljava/util/Set;)Lcom/fasterxml/jackson/databind/ser/std/BeanSerializerBase;
         6: areturn
      LineNumberTable:
        line 238: 0
      LocalVariableTable:
        Start  Length  Slot  Name   Signature
            0       7     0  this   Lcom/fasterxml/jackson/databind/ser/std/BeanSerializerBase;
            0       7     1 toIgnore   Ljava/util/Set;
      LocalVariableTypeTable:
        Start  Length  Slot  Name   Signature
            0       7     1 toIgnore   Ljava/util/Set<Ljava/lang/String;>;
    Deprecated: true
    Signature: #276                         // (Ljava/util/Set<Ljava/lang/String;>;)Lcom/fasterxml/jackson/databind/ser/std/BeanSerializerBase;
    RuntimeVisibleAnnotations:
      0: #248()
        java.lang.Deprecated

  protected abstract com.fasterxml.jackson.databind.ser.std.BeanSerializerBase withByNameInclusion(java.util.Set<java.lang.String>, java.util.Set<java.lang.String>);
    descriptor: (Ljava/util/Set;Ljava/util/Set;)Lcom/fasterxml/jackson/databind/ser/std/BeanSerializerBase;
    flags: (0x0404) ACC_PROTECTED, ACC_ABSTRACT
    Signature: #279                         // (Ljava/util/Set<Ljava/lang/String;>;Ljava/util/Set<Ljava/lang/String;>;)Lcom/fasterxml/jackson/databind/ser/std/BeanSerializerBase;

  protected com.fasterxml.jackson.databind.ser.std.BeanSerializerBase withIgnorals(java.lang.String[]);
    descriptor: ([Ljava/lang/String;)Lcom/fasterxml/jackson/databind/ser/std/BeanSerializerBase;
    flags: (0x0004) ACC_PROTECTED
    Code:
      stack=2, locals=2, args_size=2
         0: aload_0
         1: aload_1
         2: invokestatic  #20                 // Method com/fasterxml/jackson/databind/util/ArrayBuilders.arrayToSet:([Ljava/lang/Object;)Ljava/util/HashSet;
         5: invokevirtual #32                 // Method withIgnorals:(Ljava/util/Set;)Lcom/fasterxml/jackson/databind/ser/std/BeanSerializerBase;
         8: areturn
      LineNumberTable:
        line 258: 0
      LocalVariableTable:
        Start  Length  Slot  Name   Signature
            0       9     0  this   Lcom/fasterxml/jackson/databind/ser/std/BeanSerializerBase;
            0       9     1 toIgnore   [Ljava/lang/String;
    Deprecated: true
    RuntimeVisibleAnnotations:
      0: #248()
        java.lang.Deprecated

  protected abstract com.fasterxml.jackson.databind.ser.std.BeanSerializerBase asArraySerializer();
    descriptor: ()Lcom/fasterxml/jackson/databind/ser/std/BeanSerializerBase;
    flags: (0x0404) ACC_PROTECTED, ACC_ABSTRACT

  public abstract com.fasterxml.jackson.databind.ser.std.BeanSerializerBase withFilterId(java.lang.Object);
    descriptor: (Ljava/lang/Object;)Lcom/fasterxml/jackson/databind/ser/std/BeanSerializerBase;
    flags: (0x0401) ACC_PUBLIC, ACC_ABSTRACT

  protected abstract com.fasterxml.jackson.databind.ser.std.BeanSerializerBase withProperties(com.fasterxml.jackson.databind.ser.BeanPropertyWriter[], com.fasterxml.jackson.databind.ser.BeanPropertyWriter[]);
    descriptor: ([Lcom/fasterxml/jackson/databind/ser/BeanPropertyWriter;[Lcom/fasterxml/jackson/databind/ser/BeanPropertyWriter;)Lcom/fasterxml/jackson/databind/ser/std/BeanSerializerBase;
    flags: (0x0404) ACC_PROTECTED, ACC_ABSTRACT

  protected com.fasterxml.jackson.databind.ser.std.BeanSerializerBase(com.fasterxml.jackson.databind.ser.std.BeanSerializerBase);
    descriptor: (Lcom/fasterxml/jackson/databind/ser/std/BeanSerializerBase;)V
    flags: (0x0004) ACC_PROTECTED
    Code:
      stack=4, locals=2, args_size=2
         0: aload_0
         1: aload_1
         2: aload_1
         3: getfield      #3                  // Field _props:[Lcom/fasterxml/jackson/databind/ser/BeanPropertyWriter;
         6: aload_1
         7: getfield      #4                  // Field _filteredProps:[Lcom/fasterxml/jackson/databind/ser/BeanPropertyWriter;
        10: invokespecial #33                 // Method "<init>":(Lcom/fasterxml/jackson/databind/ser/std/BeanSerializerBase;[Lcom/fasterxml/jackson/databind/ser/BeanPropertyWriter;[Lcom/fasterxml/jackson/databind/ser/BeanPropertyWriter;)V
        13: return
      LineNumberTable:
        line 296: 0
        line 297: 13
      LocalVariableTable:
        Start  Length  Slot  Name   Signature
            0      14     0  this   Lcom/fasterxml/jackson/databind/ser/std/BeanSerializerBase;
            0      14     1   src   Lcom/fasterxml/jackson/databind/ser/std/BeanSerializerBase;

  protected com.fasterxml.jackson.databind.ser.std.BeanSerializerBase(com.fasterxml.jackson.databind.ser.std.BeanSerializerBase, com.fasterxml.jackson.databind.util.NameTransformer);
    descriptor: (Lcom/fasterxml/jackson/databind/ser/std/BeanSerializerBase;Lcom/fasterxml/jackson/databind/util/NameTransformer;)V
    flags: (0x0004) ACC_PROTECTED
    Code:
      stack=5, locals=3, args_size=3
         0: aload_0
         1: aload_1
         2: aload_1
         3: getfield      #3                  // Field _props:[Lcom/fasterxml/jackson/databind/ser/BeanPropertyWriter;
         6: aload_2
         7: invokestatic  #34                 // Method rename:([Lcom/fasterxml/jackson/databind/ser/BeanPropertyWriter;Lcom/fasterxml/jackson/databind/util/NameTransformer;)[Lcom/fasterxml/jackson/databind/ser/BeanPropertyWriter;
        10: aload_1
        11: getfield      #4                  // Field _filteredProps:[Lcom/fasterxml/jackson/databind/ser/BeanPropertyWriter;
        14: aload_2
        15: invokestatic  #34                 // Method rename:([Lcom/fasterxml/jackson/databind/ser/BeanPropertyWriter;Lcom/fasterxml/jackson/databind/util/NameTransformer;)[Lcom/fasterxml/jackson/databind/ser/BeanPropertyWriter;
        18: invokespecial #33                 // Method "<init>":(Lcom/fasterxml/jackson/databind/ser/std/BeanSerializerBase;[Lcom/fasterxml/jackson/databind/ser/BeanPropertyWriter;[Lcom/fasterxml/jackson/databind/ser/BeanPropertyWriter;)V
        21: return
      LineNumberTable:
        line 304: 0
        line 305: 21
      LocalVariableTable:
        Start  Length  Slot  Name   Signature
            0      22     0  this   Lcom/fasterxml/jackson/databind/ser/std/BeanSerializerBase;
            0      22     1   src   Lcom/fasterxml/jackson/databind/ser/std/BeanSerializerBase;
            0      22     2 unwrapper   Lcom/fasterxml/jackson/databind/util/NameTransformer;

  private static final com.fasterxml.jackson.databind.ser.BeanPropertyWriter[] rename(com.fasterxml.jackson.databind.ser.BeanPropertyWriter[], com.fasterxml.jackson.databind.util.NameTransformer);
    descriptor: ([Lcom/fasterxml/jackson/databind/ser/BeanPropertyWriter;Lcom/fasterxml/jackson/databind/util/NameTransformer;)[Lcom/fasterxml/jackson/databind/ser/BeanPropertyWriter;
    flags: (0x001a) ACC_PRIVATE, ACC_STATIC, ACC_FINAL
    Code:
      stack=4, locals=6, args_size=2
         0: aload_0
         1: ifnull        20
         4: aload_0
         5: arraylength
         6: ifeq          20
         9: aload_1
        10: ifnull        20
        13: aload_1
        14: getstatic     #35                 // Field com/fasterxml/jackson/databind/util/NameTransformer.NOP:Lcom/fasterxml/jackson/databind/util/NameTransformer;
        17: if_acmpne     22
        20: aload_0
        21: areturn
        22: aload_0
        23: arraylength
        24: istore_2
        25: iload_2
        26: anewarray     #28                 // class com/fasterxml/jackson/databind/ser/BeanPropertyWriter
        29: astore_3
        30: iconst_0
        31: istore        4
        33: iload         4
        35: iload_2
        36: if_icmpge     66
        39: aload_0
        40: iload         4
        42: aaload
        43: astore        5
        45: aload         5
        47: ifnull        60
        50: aload_3
        51: iload         4
        53: aload         5
        55: aload_1
        56: invokevirtual #36                 // Method com/fasterxml/jackson/databind/ser/BeanPropertyWriter.rename:(Lcom/fasterxml/jackson/databind/util/NameTransformer;)Lcom/fasterxml/jackson/databind/ser/BeanPropertyWriter;
        59: aastore
        60: iinc          4, 1
        63: goto          33
        66: aload_3
        67: areturn
      LineNumberTable:
        line 310: 0
        line 311: 20
        line 313: 22
        line 314: 25
        line 315: 30
        line 316: 39
        line 317: 45
        line 318: 50
        line 315: 60
        line 321: 66
      LocalVariableTable:
        Start  Length  Slot  Name   Signature
           45      15     5   bpw   Lcom/fasterxml/jackson/databind/ser/BeanPropertyWriter;
           33      33     4     i   I
            0      68     0 props   [Lcom/fasterxml/jackson/databind/ser/BeanPropertyWriter;
            0      68     1 transformer   Lcom/fasterxml/jackson/databind/util/NameTransformer;
           25      43     2   len   I
           30      38     3 result   [Lcom/fasterxml/jackson/databind/ser/BeanPropertyWriter;
      StackMapTable: number_of_entries = 5
        frame_type = 20 /* same */
        frame_type = 1 /* same */
        frame_type = 254 /* append */
          offset_delta = 10
          locals = [ int, class "[Lcom/fasterxml/jackson/databind/ser/BeanPropertyWriter;", int ]
        frame_type = 26 /* same */
        frame_type = 250 /* chop */
          offset_delta = 5

  public void resolve(com.fasterxml.jackson.databind.SerializerProvider) throws com.fasterxml.jackson.databind.JsonMappingException;
    descriptor: (Lcom/fasterxml/jackson/databind/SerializerProvider;)V
    flags: (0x0001) ACC_PUBLIC
    Code:
      stack=3, locals=10, args_size=2
         0: aload_0
         1: getfield      #4                  // Field _filteredProps:[Lcom/fasterxml/jackson/databind/ser/BeanPropertyWriter;
         4: ifnonnull     11
         7: iconst_0
         8: goto          16
        11: aload_0
        12: getfield      #4                  // Field _filteredProps:[Lcom/fasterxml/jackson/databind/ser/BeanPropertyWriter;
        15: arraylength
        16: istore_2
        17: iconst_0
        18: istore_3
        19: aload_0
        20: getfield      #3                  // Field _props:[Lcom/fasterxml/jackson/databind/ser/BeanPropertyWriter;
        23: arraylength
        24: istore        4
        26: iload_3
        27: iload         4
        29: if_icmpge     280
        32: aload_0
        33: getfield      #3                  // Field _props:[Lcom/fasterxml/jackson/databind/ser/BeanPropertyWriter;
        36: iload_3
        37: aaload
        38: astore        5
        40: aload         5
        42: invokevirtual #37                 // Method com/fasterxml/jackson/databind/ser/BeanPropertyWriter.willSuppressNulls:()Z
        45: ifne          101
        48: aload         5
        50: invokevirtual #38                 // Method com/fasterxml/jackson/databind/ser/BeanPropertyWriter.hasNullSerializer:()Z
        53: ifne          101
        56: aload_1
        57: aload         5
        59: invokevirtual #39                 // Method com/fasterxml/jackson/databind/SerializerProvider.findNullValueSerializer:(Lcom/fasterxml/jackson/databind/BeanProperty;)Lcom/fasterxml/jackson/databind/JsonSerializer;
        62: astore        6
        64: aload         6
        66: ifnull        101
        69: aload         5
        71: aload         6
        73: invokevirtual #40                 // Method com/fasterxml/jackson/databind/ser/BeanPropertyWriter.assignNullSerializer:(Lcom/fasterxml/jackson/databind/JsonSerializer;)V
        76: iload_3
        77: iload_2
        78: if_icmpge     101
        81: aload_0
        82: getfield      #4                  // Field _filteredProps:[Lcom/fasterxml/jackson/databind/ser/BeanPropertyWriter;
        85: iload_3
        86: aaload
        87: astore        7
        89: aload         7
        91: ifnull        101
        94: aload         7
        96: aload         6
        98: invokevirtual #40                 // Method com/fasterxml/jackson/databind/ser/BeanPropertyWriter.assignNullSerializer:(Lcom/fasterxml/jackson/databind/JsonSerializer;)V
       101: aload         5
       103: invokevirtual #41                 // Method com/fasterxml/jackson/databind/ser/BeanPropertyWriter.hasSerializer:()Z
       106: ifeq          112
       109: goto          274
       112: aload_0
       113: aload_1
       114: aload         5
       116: invokevirtual #42                 // Method findConvertingSerializer:(Lcom/fasterxml/jackson/databind/SerializerProvider;Lcom/fasterxml/jackson/databind/ser/BeanPropertyWriter;)Lcom/fasterxml/jackson/databind/JsonSerializer;
       119: astore        6
       121: aload         6
       123: ifnonnull     239
       126: aload         5
       128: invokevirtual #43                 // Method com/fasterxml/jackson/databind/ser/BeanPropertyWriter.getSerializationType:()Lcom/fasterxml/jackson/databind/JavaType;
       131: astore        7
       133: aload         7
       135: ifnonnull     179
       138: aload         5
       140: invokevirtual #44                 // Method com/fasterxml/jackson/databind/ser/BeanPropertyWriter.getType:()Lcom/fasterxml/jackson/databind/JavaType;
       143: astore        7
       145: aload         7
       147: invokevirtual #45                 // Method com/fasterxml/jackson/databind/JavaType.isFinal:()Z
       150: ifne          179
       153: aload         7
       155: invokevirtual #46                 // Method com/fasterxml/jackson/databind/JavaType.isContainerType:()Z
       158: ifne          169
       161: aload         7
       163: invokevirtual #47                 // Method com/fasterxml/jackson/databind/JavaType.containedTypeCount:()I
       166: ifle          274
       169: aload         5
       171: aload         7
       173: invokevirtual #48                 // Method com/fasterxml/jackson/databind/ser/BeanPropertyWriter.setNonTrivialBaseType:(Lcom/fasterxml/jackson/databind/JavaType;)V
       176: goto          274
       179: aload_1
       180: aload         7
       182: aload         5
       184: invokevirtual #49                 // Method com/fasterxml/jackson/databind/SerializerProvider.findValueSerializer:(Lcom/fasterxml/jackson/databind/JavaType;Lcom/fasterxml/jackson/databind/BeanProperty;)Lcom/fasterxml/jackson/databind/JsonSerializer;
       187: astore        6
       189: aload         7
       191: invokevirtual #46                 // Method com/fasterxml/jackson/databind/JavaType.isContainerType:()Z
       194: ifeq          239
       197: aload         7
       199: invokevirtual #50                 // Method com/fasterxml/jackson/databind/JavaType.getContentType:()Lcom/fasterxml/jackson/databind/JavaType;
       202: invokevirtual #51                 // Method com/fasterxml/jackson/databind/JavaType.getTypeHandler:()Ljava/lang/Object;
       205: checkcast     #52                 // class com/fasterxml/jackson/databind/jsontype/TypeSerializer
       208: astore        8
       210: aload         8
       212: ifnull        239
       215: aload         6
       217: instanceof    #53                 // class com/fasterxml/jackson/databind/ser/ContainerSerializer
       220: ifeq          239
       223: aload         6
       225: checkcast     #53                 // class com/fasterxml/jackson/databind/ser/ContainerSerializer
       228: aload         8
       230: invokevirtual #54                 // Method com/fasterxml/jackson/databind/ser/ContainerSerializer.withValueTypeSerializer:(Lcom/fasterxml/jackson/databind/jsontype/TypeSerializer;)Lcom/fasterxml/jackson/databind/ser/ContainerSerializer;
       233: astore        9
       235: aload         9
       237: astore        6
       239: iload_3
       240: iload_2
       241: if_icmpge     267
       244: aload_0
       245: getfield      #4                  // Field _filteredProps:[Lcom/fasterxml/jackson/databind/ser/BeanPropertyWriter;
       248: iload_3
       249: aaload
       250: astore        7
       252: aload         7
       254: ifnull        267
       257: aload         7
       259: aload         6
       261: invokevirtual #55                 // Method com/fasterxml/jackson/databind/ser/BeanPropertyWriter.assignSerializer:(Lcom/fasterxml/jackson/databind/JsonSerializer;)V
       264: goto          274
       267: aload         5
       269: aload         6
       271: invokevirtual #55                 // Method com/fasterxml/jackson/databind/ser/BeanPropertyWriter.assignSerializer:(Lcom/fasterxml/jackson/databind/JsonSerializer;)V
       274: iinc          3, 1
       277: goto          26
       280: aload_0
       281: getfield      #6                  // Field _anyGetterWriter:Lcom/fasterxml/jackson/databind/ser/AnyGetterWriter;
       284: ifnull        295
       287: aload_0
       288: getfield      #6                  // Field _anyGetterWriter:Lcom/fasterxml/jackson/databind/ser/AnyGetterWriter;
       291: aload_1
       292: invokevirtual #56                 // Method com/fasterxml/jackson/databind/ser/AnyGetterWriter.resolve:(Lcom/fasterxml/jackson/databind/SerializerProvider;)V
       295: return
      LineNumberTable:
        line 338: 0
        line 339: 17
        line 340: 32
        line 342: 40
        line 343: 56
        line 344: 64
        line 345: 69
        line 347: 76
        line 348: 81
        line 349: 89
        line 350: 94
        line 356: 101
        line 357: 109
        line 360: 112
        line 361: 121
        line 363: 126
        line 367: 133
        line 368: 138
        line 369: 145
        line 370: 153
        line 371: 169
        line 376: 179
        line 379: 189
        line 380: 197
        line 381: 210
        line 383: 215
        line 386: 223
        line 387: 235
        line 393: 239
        line 394: 244
        line 395: 252
        line 396: 257
        line 400: 264
        line 403: 267
        line 339: 274
        line 407: 280
        line 409: 287
        line 411: 295
      LocalVariableTable:
        Start  Length  Slot  Name   Signature
           89      12     7    w2   Lcom/fasterxml/jackson/databind/ser/BeanPropertyWriter;
           64      37     6 nullSer   Lcom/fasterxml/jackson/databind/JsonSerializer;
          235       4     9  ser2   Lcom/fasterxml/jackson/databind/JsonSerializer;
          210      29     8 typeSer   Lcom/fasterxml/jackson/databind/jsontype/TypeSerializer;
          133     106     7  type   Lcom/fasterxml/jackson/databind/JavaType;
          252      15     7    w2   Lcom/fasterxml/jackson/databind/ser/BeanPropertyWriter;
           40     234     5  prop   Lcom/fasterxml/jackson/databind/ser/BeanPropertyWriter;
          121     153     6   ser   Lcom/fasterxml/jackson/databind/JsonSerializer;
           19     261     3     i   I
           26     254     4   len   I
            0     296     0  this   Lcom/fasterxml/jackson/databind/ser/std/BeanSerializerBase;
            0     296     1 provider   Lcom/fasterxml/jackson/databind/SerializerProvider;
           17     279     2 filteredCount   I
      LocalVariableTypeTable:
        Start  Length  Slot  Name   Signature
           64      37     6 nullSer   Lcom/fasterxml/jackson/databind/JsonSerializer<Ljava/lang/Object;>;
          235       4     9  ser2   Lcom/fasterxml/jackson/databind/JsonSerializer<Ljava/lang/Object;>;
          121     153     6   ser   Lcom/fasterxml/jackson/databind/JsonSerializer<Ljava/lang/Object;>;
      StackMapTable: number_of_entries = 12
        frame_type = 11 /* same */
        frame_type = 68 /* same_locals_1_stack_item */
          stack = [ int ]
        frame_type = 254 /* append */
          offset_delta = 9
          locals = [ int, int, int ]
        frame_type = 252 /* append */
          offset_delta = 74
          locals = [ class com/fasterxml/jackson/databind/ser/BeanPropertyWriter ]
        frame_type = 10 /* same */
        frame_type = 253 /* append */
          offset_delta = 56
          locals = [ class com/fasterxml/jackson/databind/JsonSerializer, class com/fasterxml/jackson/databind/JavaType ]
        frame_type = 9 /* same */
        frame_type = 250 /* chop */
          offset_delta = 59
        frame_type = 27 /* same */
        frame_type = 249 /* chop */
          offset_delta = 6
        frame_type = 249 /* chop */
          offset_delta = 5
        frame_type = 14 /* same */
    Exceptions:
      throws com.fasterxml.jackson.databind.JsonMappingException

  protected com.fasterxml.jackson.databind.JsonSerializer<java.lang.Object> findConvertingSerializer(com.fasterxml.jackson.databind.SerializerProvider, com.fasterxml.jackson.databind.ser.BeanPropertyWriter) throws com.fasterxml.jackson.databind.JsonMappingException;
    descriptor: (Lcom/fasterxml/jackson/databind/SerializerProvider;Lcom/fasterxml/jackson/databind/ser/BeanPropertyWriter;)Lcom/fasterxml/jackson/databind/JsonSerializer;
    flags: (0x0004) ACC_PROTECTED
    Code:
      stack=5, locals=9, args_size=3
         0: aload_1
         1: invokevirtual #57                 // Method com/fasterxml/jackson/databind/SerializerProvider.getAnnotationIntrospector:()Lcom/fasterxml/jackson/databind/AnnotationIntrospector;
         4: astore_3
         5: aload_3
         6: ifnull        93
         9: aload_2
        10: invokevirtual #58                 // Method com/fasterxml/jackson/databind/ser/BeanPropertyWriter.getMember:()Lcom/fasterxml/jackson/databind/introspect/AnnotatedMember;
        13: astore        4
        15: aload         4
        17: ifnull        93
        20: aload_3
        21: aload         4
        23: invokevirtual #59                 // Method com/fasterxml/jackson/databind/AnnotationIntrospector.findSerializationConverter:(Lcom/fasterxml/jackson/databind/introspect/Annotated;)Ljava/lang/Object;
        26: astore        5
        28: aload         5
        30: ifnull        93
        33: aload_1
        34: aload_2
        35: invokevirtual #58                 // Method com/fasterxml/jackson/databind/ser/BeanPropertyWriter.getMember:()Lcom/fasterxml/jackson/databind/introspect/AnnotatedMember;
        38: aload         5
        40: invokevirtual #60                 // Method com/fasterxml/jackson/databind/SerializerProvider.converterInstance:(Lcom/fasterxml/jackson/databind/introspect/Annotated;Ljava/lang/Object;)Lcom/fasterxml/jackson/databind/util/Converter;
        43: astore        6
        45: aload         6
        47: aload_1
        48: invokevirtual #61                 // Method com/fasterxml/jackson/databind/SerializerProvider.getTypeFactory:()Lcom/fasterxml/jackson/databind/type/TypeFactory;
        51: invokeinterface #62,  2           // InterfaceMethod com/fasterxml/jackson/databind/util/Converter.getOutputType:(Lcom/fasterxml/jackson/databind/type/TypeFactory;)Lcom/fasterxml/jackson/databind/JavaType;
        56: astore        7
        58: aload         7
        60: invokevirtual #63                 // Method com/fasterxml/jackson/databind/JavaType.isJavaLangObject:()Z
        63: ifeq          70
        66: aconst_null
        67: goto          77
        70: aload_1
        71: aload         7
        73: aload_2
        74: invokevirtual #49                 // Method com/fasterxml/jackson/databind/SerializerProvider.findValueSerializer:(Lcom/fasterxml/jackson/databind/JavaType;Lcom/fasterxml/jackson/databind/BeanProperty;)Lcom/fasterxml/jackson/databind/JsonSerializer;
        77: astore        8
        79: new           #64                 // class com/fasterxml/jackson/databind/ser/std/StdDelegatingSerializer
        82: dup
        83: aload         6
        85: aload         7
        87: aload         8
        89: invokespecial #65                 // Method com/fasterxml/jackson/databind/ser/std/StdDelegatingSerializer."<init>":(Lcom/fasterxml/jackson/databind/util/Converter;Lcom/fasterxml/jackson/databind/JavaType;Lcom/fasterxml/jackson/databind/JsonSerializer;)V
        92: areturn
        93: aconst_null
        94: areturn
      LineNumberTable:
        line 424: 0
        line 425: 5
        line 426: 9
        line 427: 15
        line 428: 20
        line 429: 28
        line 430: 33
        line 431: 45
        line 433: 58
        line 434: 74
        line 435: 79
        line 439: 93
      LocalVariableTable:
        Start  Length  Slot  Name   Signature
           45      48     6  conv   Lcom/fasterxml/jackson/databind/util/Converter;
           58      35     7 delegateType   Lcom/fasterxml/jackson/databind/JavaType;
           79      14     8   ser   Lcom/fasterxml/jackson/databind/JsonSerializer;
           28      65     5 convDef   Ljava/lang/Object;
           15      78     4     m   Lcom/fasterxml/jackson/databind/introspect/AnnotatedMember;
            0      95     0  this   Lcom/fasterxml/jackson/databind/ser/std/BeanSerializerBase;
            0      95     1 provider   Lcom/fasterxml/jackson/databind/SerializerProvider;
            0      95     2  prop   Lcom/fasterxml/jackson/databind/ser/BeanPropertyWriter;
            5      90     3  intr   Lcom/fasterxml/jackson/databind/AnnotationIntrospector;
      LocalVariableTypeTable:
        Start  Length  Slot  Name   Signature
           45      48     6  conv   Lcom/fasterxml/jackson/databind/util/Converter<Ljava/lang/Object;Ljava/lang/Object;>;
           79      14     8   ser   Lcom/fasterxml/jackson/databind/JsonSerializer<*>;
      StackMapTable: number_of_entries = 3
        frame_type = 255 /* full_frame */
          offset_delta = 70
          locals = [ class com/fasterxml/jackson/databind/ser/std/BeanSerializerBase, class com/fasterxml/jackson/databind/SerializerProvider, class com/fasterxml/jackson/databind/ser/BeanPropertyWriter, class com/fasterxml/jackson/databind/AnnotationIntrospector, class com/fasterxml/jackson/databind/introspect/AnnotatedMember, class java/lang/Object, class com/fasterxml/jackson/databind/util/Converter, class com/fasterxml/jackson/databind/JavaType ]
          stack = []
        frame_type = 70 /* same_locals_1_stack_item */
          stack = [ class com/fasterxml/jackson/databind/JsonSerializer ]
        frame_type = 255 /* full_frame */
          offset_delta = 15
          locals = [ class com/fasterxml/jackson/databind/ser/std/BeanSerializerBase, class com/fasterxml/jackson/databind/SerializerProvider, class com/fasterxml/jackson/databind/ser/BeanPropertyWriter, class com/fasterxml/jackson/databind/AnnotationIntrospector ]
          stack = []
    Exceptions:
      throws com.fasterxml.jackson.databind.JsonMappingException
    Signature: #328                         // (Lcom/fasterxml/jackson/databind/SerializerProvider;Lcom/fasterxml/jackson/databind/ser/BeanPropertyWriter;)Lcom/fasterxml/jackson/databind/JsonSerializer<Ljava/lang/Object;>;

  public com.fasterxml.jackson.databind.JsonSerializer<?> createContextual(com.fasterxml.jackson.databind.SerializerProvider, com.fasterxml.jackson.databind.BeanProperty) throws com.fasterxml.jackson.databind.JsonMappingException;
    descriptor: (Lcom/fasterxml/jackson/databind/SerializerProvider;Lcom/fasterxml/jackson/databind/BeanProperty;)Lcom/fasterxml/jackson/databind/JsonSerializer;
    flags: (0x0001) ACC_PUBLIC
    Code:
      stack=8, locals=22, args_size=3
         0: aload_1
         1: invokevirtual #57                 // Method com/fasterxml/jackson/databind/SerializerProvider.getAnnotationIntrospector:()Lcom/fasterxml/jackson/databind/AnnotationIntrospector;
         4: astore_3
         5: aload_2
         6: ifnull        13
         9: aload_3
        10: ifnonnull     17
        13: aconst_null
        14: goto          23
        17: aload_2
        18: invokeinterface #66,  1           // InterfaceMethod com/fasterxml/jackson/databind/BeanProperty.getMember:()Lcom/fasterxml/jackson/databind/introspect/AnnotatedMember;
        23: astore        4
        25: aload_1
        26: invokevirtual #67                 // Method com/fasterxml/jackson/databind/SerializerProvider.getConfig:()Lcom/fasterxml/jackson/databind/SerializationConfig;
        29: astore        5
        31: aload_0
        32: aload_1
        33: aload_2
        34: aload_0
        35: getfield      #17                 // Field _handledType:Ljava/lang/Class;
        38: invokevirtual #68                 // Method findFormatOverrides:(Lcom/fasterxml/jackson/databind/SerializerProvider;Lcom/fasterxml/jackson/databind/BeanProperty;Ljava/lang/Class;)Lcom/fasterxml/jackson/annotation/JsonFormat$Value;
        41: astore        6
        43: aconst_null
        44: astore        7
        46: aload         6
        48: ifnull        270
        51: aload         6
        53: invokevirtual #69                 // Method com/fasterxml/jackson/annotation/JsonFormat$Value.hasShape:()Z
        56: ifeq          270
        59: aload         6
        61: invokevirtual #16                 // Method com/fasterxml/jackson/annotation/JsonFormat$Value.getShape:()Lcom/fasterxml/jackson/annotation/JsonFormat$Shape;
        64: astore        7
        66: aload         7
        68: getstatic     #70                 // Field com/fasterxml/jackson/annotation/JsonFormat$Shape.ANY:Lcom/fasterxml/jackson/annotation/JsonFormat$Shape;
        71: if_acmpeq     270
        74: aload         7
        76: aload_0
        77: getfield      #9                  // Field _serializationShape:Lcom/fasterxml/jackson/annotation/JsonFormat$Shape;
        80: if_acmpeq     270
        83: aload_0
        84: getfield      #2                  // Field _beanType:Lcom/fasterxml/jackson/databind/JavaType;
        87: invokevirtual #71                 // Method com/fasterxml/jackson/databind/JavaType.isEnumType:()Z
        90: ifeq          170
        93: getstatic     #72                 // Field com/fasterxml/jackson/databind/ser/std/BeanSerializerBase$1.$SwitchMap$com$fasterxml$jackson$annotation$JsonFormat$Shape:[I
        96: aload         7
        98: invokevirtual #73                 // Method com/fasterxml/jackson/annotation/JsonFormat$Shape.ordinal:()I
       101: iaload
       102: tableswitch   { // 1 to 3
                       1: 128
                       2: 128
                       3: 128
                 default: 167
            }
       128: aload         5
       130: aload_0
       131: getfield      #2                  // Field _beanType:Lcom/fasterxml/jackson/databind/JavaType;
       134: invokevirtual #74                 // Method com/fasterxml/jackson/databind/SerializationConfig.introspectClassAnnotations:(Lcom/fasterxml/jackson/databind/JavaType;)Lcom/fasterxml/jackson/databind/BeanDescription;
       137: astore        8
       139: aload_0
       140: getfield      #2                  // Field _beanType:Lcom/fasterxml/jackson/databind/JavaType;
       143: invokevirtual #75                 // Method com/fasterxml/jackson/databind/JavaType.getRawClass:()Ljava/lang/Class;
       146: aload_1
       147: invokevirtual #67                 // Method com/fasterxml/jackson/databind/SerializerProvider.getConfig:()Lcom/fasterxml/jackson/databind/SerializationConfig;
       150: aload         8
       152: aload         6
       154: invokestatic  #76                 // Method com/fasterxml/jackson/databind/ser/std/EnumSerializer.construct:(Ljava/lang/Class;Lcom/fasterxml/jackson/databind/SerializationConfig;Lcom/fasterxml/jackson/databind/BeanDescription;Lcom/fasterxml/jackson/annotation/JsonFormat$Value;)Lcom/fasterxml/jackson/databind/ser/std/EnumSerializer;
       157: astore        9
       159: aload_1
       160: aload         9
       162: aload_2
       163: invokevirtual #77                 // Method com/fasterxml/jackson/databind/SerializerProvider.handlePrimaryContextualization:(Lcom/fasterxml/jackson/databind/JsonSerializer;Lcom/fasterxml/jackson/databind/BeanProperty;)Lcom/fasterxml/jackson/databind/JsonSerializer;
       166: areturn
       167: goto          270
       170: aload         7
       172: getstatic     #78                 // Field com/fasterxml/jackson/annotation/JsonFormat$Shape.NATURAL:Lcom/fasterxml/jackson/annotation/JsonFormat$Shape;
       175: if_acmpne     270
       178: aload_0
       179: getfield      #2                  // Field _beanType:Lcom/fasterxml/jackson/databind/JavaType;
       182: invokevirtual #79                 // Method com/fasterxml/jackson/databind/JavaType.isMapLikeType:()Z
       185: ifeq          203
       188: ldc           #80                 // class java/util/Map
       190: aload_0
       191: getfield      #17                 // Field _handledType:Ljava/lang/Class;
       194: invokevirtual #81                 // Method java/lang/Class.isAssignableFrom:(Ljava/lang/Class;)Z
       197: ifeq          203
       200: goto          270
       203: ldc           #82                 // class java/util/Map$Entry
       205: aload_0
       206: getfield      #17                 // Field _handledType:Ljava/lang/Class;
       209: invokevirtual #81                 // Method java/lang/Class.isAssignableFrom:(Ljava/lang/Class;)Z
       212: ifeq          270
       215: aload_0
       216: getfield      #2                  // Field _beanType:Lcom/fasterxml/jackson/databind/JavaType;
       219: ldc           #82                 // class java/util/Map$Entry
       221: invokevirtual #83                 // Method com/fasterxml/jackson/databind/JavaType.findSuperType:(Ljava/lang/Class;)Lcom/fasterxml/jackson/databind/JavaType;
       224: astore        8
       226: aload         8
       228: iconst_0
       229: invokevirtual #84                 // Method com/fasterxml/jackson/databind/JavaType.containedTypeOrUnknown:(I)Lcom/fasterxml/jackson/databind/JavaType;
       232: astore        9
       234: aload         8
       236: iconst_1
       237: invokevirtual #84                 // Method com/fasterxml/jackson/databind/JavaType.containedTypeOrUnknown:(I)Lcom/fasterxml/jackson/databind/JavaType;
       240: astore        10
       242: new           #85                 // class com/fasterxml/jackson/databind/ser/impl/MapEntrySerializer
       245: dup
       246: aload_0
       247: getfield      #2                  // Field _beanType:Lcom/fasterxml/jackson/databind/JavaType;
       250: aload         9
       252: aload         10
       254: iconst_0
       255: aconst_null
       256: aload_2
       257: invokespecial #86                 // Method com/fasterxml/jackson/databind/ser/impl/MapEntrySerializer."<init>":(Lcom/fasterxml/jackson/databind/JavaType;Lcom/fasterxml/jackson/databind/JavaType;Lcom/fasterxml/jackson/databind/JavaType;ZLcom/fasterxml/jackson/databind/jsontype/TypeSerializer;Lcom/fasterxml/jackson/databind/BeanProperty;)V
       260: astore        11
       262: aload_1
       263: aload         11
       265: aload_2
       266: invokevirtual #77                 // Method com/fasterxml/jackson/databind/SerializerProvider.handlePrimaryContextualization:(Lcom/fasterxml/jackson/databind/JsonSerializer;Lcom/fasterxml/jackson/databind/BeanProperty;)Lcom/fasterxml/jackson/databind/JsonSerializer;
       269: areturn
       270: aload_0
       271: getfield      #8                  // Field _objectIdWriter:Lcom/fasterxml/jackson/databind/ser/impl/ObjectIdWriter;
       274: astore        8
       276: iconst_0
       277: istore        9
       279: aconst_null
       280: astore        10
       282: aconst_null
       283: astore        11
       285: aconst_null
       286: astore        12
       288: aload         4
       290: ifnull        626
       293: aload_3
       294: aload         5
       296: aload         4
       298: invokevirtual #87                 // Method com/fasterxml/jackson/databind/AnnotationIntrospector.findPropertyIgnoralByName:(Lcom/fasterxml/jackson/databind/cfg/MapperConfig;Lcom/fasterxml/jackson/databind/introspect/Annotated;)Lcom/fasterxml/jackson/annotation/JsonIgnoreProperties$Value;
       301: invokevirtual #88                 // Method com/fasterxml/jackson/annotation/JsonIgnoreProperties$Value.findIgnoredForSerialization:()Ljava/util/Set;
       304: astore        10
       306: aload_3
       307: aload         5
       309: aload         4
       311: invokevirtual #89                 // Method com/fasterxml/jackson/databind/AnnotationIntrospector.findPropertyInclusionByName:(Lcom/fasterxml/jackson/databind/cfg/MapperConfig;Lcom/fasterxml/jackson/databind/introspect/Annotated;)Lcom/fasterxml/jackson/annotation/JsonIncludeProperties$Value;
       314: invokevirtual #90                 // Method com/fasterxml/jackson/annotation/JsonIncludeProperties$Value.getIncluded:()Ljava/util/Set;
       317: astore        11
       319: aload_3
       320: aload         4
       322: invokevirtual #91                 // Method com/fasterxml/jackson/databind/AnnotationIntrospector.findObjectIdInfo:(Lcom/fasterxml/jackson/databind/introspect/Annotated;)Lcom/fasterxml/jackson/databind/introspect/ObjectIdInfo;
       325: astore        13
       327: aload         13
       329: ifnonnull     368
       332: aload         8
       334: ifnull        590
       337: aload_3
       338: aload         4
       340: aconst_null
       341: invokevirtual #92                 // Method com/fasterxml/jackson/databind/AnnotationIntrospector.findObjectReferenceInfo:(Lcom/fasterxml/jackson/databind/introspect/Annotated;Lcom/fasterxml/jackson/databind/introspect/ObjectIdInfo;)Lcom/fasterxml/jackson/databind/introspect/ObjectIdInfo;
       344: astore        13
       346: aload         13
       348: ifnull        590
       351: aload_0
       352: getfield      #8                  // Field _objectIdWriter:Lcom/fasterxml/jackson/databind/ser/impl/ObjectIdWriter;
       355: aload         13
       357: invokevirtual #93                 // Method com/fasterxml/jackson/databind/introspect/ObjectIdInfo.getAlwaysAsId:()Z
       360: invokevirtual #94                 // Method com/fasterxml/jackson/databind/ser/impl/ObjectIdWriter.withAlwaysAsId:(Z)Lcom/fasterxml/jackson/databind/ser/impl/ObjectIdWriter;
       363: astore        8
       365: goto          590
       368: aload_3
       369: aload         4
       371: aload         13
       373: invokevirtual #92                 // Method com/fasterxml/jackson/databind/AnnotationIntrospector.findObjectReferenceInfo:(Lcom/fasterxml/jackson/databind/introspect/Annotated;Lcom/fasterxml/jackson/databind/introspect/ObjectIdInfo;)Lcom/fasterxml/jackson/databind/introspect/ObjectIdInfo;
       376: astore        13
       378: aload         13
       380: invokevirtual #95                 // Method com/fasterxml/jackson/databind/introspect/ObjectIdInfo.getGeneratorType:()Ljava/lang/Class;
       383: astore        14
       385: aload_1
       386: aload         14
       388: invokevirtual #96                 // Method com/fasterxml/jackson/databind/SerializerProvider.constructType:(Ljava/lang/reflect/Type;)Lcom/fasterxml/jackson/databind/JavaType;
       391: astore        15
       393: aload_1
       394: invokevirtual #61                 // Method com/fasterxml/jackson/databind/SerializerProvider.getTypeFactory:()Lcom/fasterxml/jackson/databind/type/TypeFactory;
       397: aload         15
       399: ldc           #97                 // class com/fasterxml/jackson/annotation/ObjectIdGenerator
       401: invokevirtual #98                 // Method com/fasterxml/jackson/databind/type/TypeFactory.findTypeParameters:(Lcom/fasterxml/jackson/databind/JavaType;Ljava/lang/Class;)[Lcom/fasterxml/jackson/databind/JavaType;
       404: iconst_0
       405: aaload
       406: astore        16
       408: aload         14
       410: ldc           #99                 // class com/fasterxml/jackson/annotation/ObjectIdGenerators$PropertyGenerator
       412: if_acmpne     561
       415: aload         13
       417: invokevirtual #100                // Method com/fasterxml/jackson/databind/introspect/ObjectIdInfo.getPropertyName:()Lcom/fasterxml/jackson/databind/PropertyName;
       420: invokevirtual #101                // Method com/fasterxml/jackson/databind/PropertyName.getSimpleName:()Ljava/lang/String;
       423: astore        17
       425: aconst_null
       426: astore        18
       428: iconst_0
       429: istore        19
       431: aload_0
       432: getfield      #3                  // Field _props:[Lcom/fasterxml/jackson/databind/ser/BeanPropertyWriter;
       435: arraylength
       436: istore        20
       438: iload         19
       440: iload         20
       442: if_icmpne     481
       445: aload_1
       446: aload_0
       447: getfield      #2                  // Field _beanType:Lcom/fasterxml/jackson/databind/JavaType;
       450: ldc           #102                // String Invalid Object Id definition for %s: cannot find property with name %s
       452: iconst_2
       453: anewarray     #103                // class java/lang/Object
       456: dup
       457: iconst_0
       458: aload_0
       459: invokevirtual #104                // Method handledType:()Ljava/lang/Class;
       462: invokestatic  #105                // Method com/fasterxml/jackson/databind/util/ClassUtil.nameOf:(Ljava/lang/Class;)Ljava/lang/String;
       465: aastore
       466: dup
       467: iconst_1
       468: aload         17
       470: invokestatic  #106                // Method com/fasterxml/jackson/databind/util/ClassUtil.name:(Ljava/lang/String;)Ljava/lang/String;
       473: aastore
       474: invokestatic  #107                // Method java/lang/String.format:(Ljava/lang/String;[Ljava/lang/Object;)Ljava/lang/String;
       477: invokevirtual #108                // Method com/fasterxml/jackson/databind/SerializerProvider.reportBadDefinition:(Lcom/fasterxml/jackson/databind/JavaType;Ljava/lang/String;)Ljava/lang/Object;
       480: pop
       481: aload_0
       482: getfield      #3                  // Field _props:[Lcom/fasterxml/jackson/databind/ser/BeanPropertyWriter;
       485: iload         19
       487: aaload
       488: astore        21
       490: aload         17
       492: aload         21
       494: invokevirtual #24                 // Method com/fasterxml/jackson/databind/ser/BeanPropertyWriter.getName:()Ljava/lang/String;
       497: invokevirtual #109                // Method java/lang/String.equals:(Ljava/lang/Object;)Z
       500: ifeq          514
       503: aload         21
       505: astore        18
       507: iload         19
       509: istore        9
       511: goto          520
       514: iinc          19, 1
       517: goto          438
       520: aload         18
       522: invokevirtual #44                 // Method com/fasterxml/jackson/databind/ser/BeanPropertyWriter.getType:()Lcom/fasterxml/jackson/databind/JavaType;
       525: astore        16
       527: new           #110                // class com/fasterxml/jackson/databind/ser/impl/PropertyBasedObjectIdGenerator
       530: dup
       531: aload         13
       533: aload         18
       535: invokespecial #111                // Method com/fasterxml/jackson/databind/ser/impl/PropertyBasedObjectIdGenerator."<init>":(Lcom/fasterxml/jackson/databind/introspect/ObjectIdInfo;Lcom/fasterxml/jackson/databind/ser/BeanPropertyWriter;)V
       538: astore        19
       540: aload         16
       542: aconst_null
       543: checkcast     #112                // class com/fasterxml/jackson/databind/PropertyName
       546: aload         19
       548: aload         13
       550: invokevirtual #93                 // Method com/fasterxml/jackson/databind/introspect/ObjectIdInfo.getAlwaysAsId:()Z
       553: invokestatic  #113                // Method com/fasterxml/jackson/databind/ser/impl/ObjectIdWriter.construct:(Lcom/fasterxml/jackson/databind/JavaType;Lcom/fasterxml/jackson/databind/PropertyName;Lcom/fasterxml/jackson/annotation/ObjectIdGenerator;Z)Lcom/fasterxml/jackson/databind/ser/impl/ObjectIdWriter;
       556: astore        8
       558: goto          590
       561: aload_1
       562: aload         4
       564: aload         13
       566: invokevirtual #114                // Method com/fasterxml/jackson/databind/SerializerProvider.objectIdGeneratorInstance:(Lcom/fasterxml/jackson/databind/introspect/Annotated;Lcom/fasterxml/jackson/databind/introspect/ObjectIdInfo;)Lcom/fasterxml/jackson/annotation/ObjectIdGenerator;
       569: astore        17
       571: aload         16
       573: aload         13
       575: invokevirtual #100                // Method com/fasterxml/jackson/databind/introspect/ObjectIdInfo.getPropertyName:()Lcom/fasterxml/jackson/databind/PropertyName;
       578: aload         17
       580: aload         13
       582: invokevirtual #93                 // Method com/fasterxml/jackson/databind/introspect/ObjectIdInfo.getAlwaysAsId:()Z
       585: invokestatic  #113                // Method com/fasterxml/jackson/databind/ser/impl/ObjectIdWriter.construct:(Lcom/fasterxml/jackson/databind/JavaType;Lcom/fasterxml/jackson/databind/PropertyName;Lcom/fasterxml/jackson/annotation/ObjectIdGenerator;Z)Lcom/fasterxml/jackson/databind/ser/impl/ObjectIdWriter;
       588: astore        8
       590: aload_3
       591: aload         4
       593: invokevirtual #115                // Method com/fasterxml/jackson/databind/AnnotationIntrospector.findFilterId:(Lcom/fasterxml/jackson/databind/introspect/Annotated;)Ljava/lang/Object;
       596: astore        14
       598: aload         14
       600: ifnull        626
       603: aload_0
       604: getfield      #7                  // Field _propertyFilterId:Ljava/lang/Object;
       607: ifnull        622
       610: aload         14
       612: aload_0
       613: getfield      #7                  // Field _propertyFilterId:Ljava/lang/Object;
       616: invokevirtual #116                // Method java/lang/Object.equals:(Ljava/lang/Object;)Z
       619: ifne          626
       622: aload         14
       624: astore        12
       626: aload_0
       627: astore        13
       629: iload         9
       631: ifle          740
       634: aload_0
       635: getfield      #3                  // Field _props:[Lcom/fasterxml/jackson/databind/ser/BeanPropertyWriter;
       638: aload_0
       639: getfield      #3                  // Field _props:[Lcom/fasterxml/jackson/databind/ser/BeanPropertyWriter;
       642: arraylength
       643: invokestatic  #117                // Method java/util/Arrays.copyOf:([Ljava/lang/Object;I)[Ljava/lang/Object;
       646: checkcast     #30                 // class "[Lcom/fasterxml/jackson/databind/ser/BeanPropertyWriter;"
       649: astore        14
       651: aload         14
       653: iload         9
       655: aaload
       656: astore        15
       658: aload         14
       660: iconst_0
       661: aload         14
       663: iconst_1
       664: iload         9
       666: invokestatic  #118                // Method java/lang/System.arraycopy:(Ljava/lang/Object;ILjava/lang/Object;II)V
       669: aload         14
       671: iconst_0
       672: aload         15
       674: aastore
       675: aload_0
       676: getfield      #4                  // Field _filteredProps:[Lcom/fasterxml/jackson/databind/ser/BeanPropertyWriter;
       679: ifnonnull     688
       682: aconst_null
       683: astore        16
       685: goto          729
       688: aload_0
       689: getfield      #4                  // Field _filteredProps:[Lcom/fasterxml/jackson/databind/ser/BeanPropertyWriter;
       692: aload_0
       693: getfield      #4                  // Field _filteredProps:[Lcom/fasterxml/jackson/databind/ser/BeanPropertyWriter;
       696: arraylength
       697: invokestatic  #117                // Method java/util/Arrays.copyOf:([Ljava/lang/Object;I)[Ljava/lang/Object;
       700: checkcast     #30                 // class "[Lcom/fasterxml/jackson/databind/ser/BeanPropertyWriter;"
       703: astore        16
       705: aload         16
       707: iload         9
       709: aaload
       710: astore        15
       712: aload         16
       714: iconst_0
       715: aload         16
       717: iconst_1
       718: iload         9
       720: invokestatic  #118                // Method java/lang/System.arraycopy:(Ljava/lang/Object;ILjava/lang/Object;II)V
       723: aload         16
       725: iconst_0
       726: aload         15
       728: aastore
       729: aload         13
       731: aload         14
       733: aload         16
       735: invokevirtual #119                // Method withProperties:([Lcom/fasterxml/jackson/databind/ser/BeanPropertyWriter;[Lcom/fasterxml/jackson/databind/ser/BeanPropertyWriter;)Lcom/fasterxml/jackson/databind/ser/std/BeanSerializerBase;
       738: astore        13
       740: aload         8
       742: ifnull        784
       745: aload_1
       746: aload         8
       748: getfield      #120                // Field com/fasterxml/jackson/databind/ser/impl/ObjectIdWriter.idType:Lcom/fasterxml/jackson/databind/JavaType;
       751: aload_2
       752: invokevirtual #49                 // Method com/fasterxml/jackson/databind/SerializerProvider.findValueSerializer:(Lcom/fasterxml/jackson/databind/JavaType;Lcom/fasterxml/jackson/databind/BeanProperty;)Lcom/fasterxml/jackson/databind/JsonSerializer;
       755: astore        14
       757: aload         8
       759: aload         14
       761: invokevirtual #121                // Method com/fasterxml/jackson/databind/ser/impl/ObjectIdWriter.withSerializer:(Lcom/fasterxml/jackson/databind/JsonSerializer;)Lcom/fasterxml/jackson/databind/ser/impl/ObjectIdWriter;
       764: astore        8
       766: aload         8
       768: aload_0
       769: getfield      #8                  // Field _objectIdWriter:Lcom/fasterxml/jackson/databind/ser/impl/ObjectIdWriter;
       772: if_acmpeq     784
       775: aload         13
       777: aload         8
       779: invokevirtual #122                // Method withObjectIdWriter:(Lcom/fasterxml/jackson/databind/ser/impl/ObjectIdWriter;)Lcom/fasterxml/jackson/databind/ser/std/BeanSerializerBase;
       782: astore        13
       784: aload         10
       786: ifnull        799
       789: aload         10
       791: invokeinterface #123,  1          // InterfaceMethod java/util/Set.isEmpty:()Z
       796: ifeq          804
       799: aload         11
       801: ifnull        815
       804: aload         13
       806: aload         10
       808: aload         11
       810: invokevirtual #31                 // Method withByNameInclusion:(Ljava/util/Set;Ljava/util/Set;)Lcom/fasterxml/jackson/databind/ser/std/BeanSerializerBase;
       813: astore        13
       815: aload         12
       817: ifnull        829
       820: aload         13
       822: aload         12
       824: invokevirtual #124                // Method withFilterId:(Ljava/lang/Object;)Lcom/fasterxml/jackson/databind/ser/std/BeanSerializerBase;
       827: astore        13
       829: aload         7
       831: ifnonnull     840
       834: aload_0
       835: getfield      #9                  // Field _serializationShape:Lcom/fasterxml/jackson/annotation/JsonFormat$Shape;
       838: astore        7
       840: aload         7
       842: getstatic     #125                // Field com/fasterxml/jackson/annotation/JsonFormat$Shape.ARRAY:Lcom/fasterxml/jackson/annotation/JsonFormat$Shape;
       845: if_acmpne     854
       848: aload         13
       850: invokevirtual #126                // Method asArraySerializer:()Lcom/fasterxml/jackson/databind/ser/std/BeanSerializerBase;
       853: areturn
       854: aload         13
       856: areturn
      LineNumberTable:
        line 448: 0
        line 449: 5
        line 450: 18
        line 451: 25
        line 455: 31
        line 456: 43
        line 457: 46
        line 458: 59
        line 460: 66
        line 461: 83
        line 462: 93
        line 468: 128
        line 469: 139
        line 470: 147
        line 469: 154
        line 471: 159
        line 474: 170
        line 475: 178
        line 477: 203
        line 478: 215
        line 480: 226
        line 481: 234
        line 485: 242
        line 487: 262
        line 493: 270
        line 497: 276
        line 498: 279
        line 499: 282
        line 500: 285
        line 503: 288
        line 504: 293
        line 505: 306
        line 506: 319
        line 507: 327
        line 509: 332
        line 510: 337
        line 511: 346
        line 512: 351
        line 520: 368
        line 521: 378
        line 522: 385
        line 523: 393
        line 525: 408
        line 526: 415
        line 527: 425
        line 529: 428
        line 530: 438
        line 531: 445
        line 533: 459
        line 531: 474
        line 535: 481
        line 536: 490
        line 537: 503
        line 540: 507
        line 541: 511
        line 529: 514
        line 544: 520
        line 545: 527
        line 546: 540
        line 547: 558
        line 548: 561
        line 549: 571
        line 550: 582
        line 549: 585
        line 554: 590
        line 555: 598
        line 557: 603
        line 558: 622
        line 563: 626
        line 566: 629
        line 567: 634
        line 568: 651
        line 569: 658
        line 570: 669
        line 572: 675
        line 573: 682
        line 575: 688
        line 576: 705
        line 577: 712
        line 578: 723
        line 580: 729
        line 583: 740
        line 584: 745
        line 585: 757
        line 586: 766
        line 587: 775
        line 592: 784
        line 594: 804
        line 596: 815
        line 597: 820
        line 600: 829
        line 601: 834
        line 604: 840
        line 605: 848
        line 607: 854
      LocalVariableTable:
        Start  Length  Slot  Name   Signature
          139      28     8  desc   Lcom/fasterxml/jackson/databind/BeanDescription;
          159       8     9   ser   Lcom/fasterxml/jackson/databind/JsonSerializer;
          226      44     8 mapEntryType   Lcom/fasterxml/jackson/databind/JavaType;
          234      36     9    kt   Lcom/fasterxml/jackson/databind/JavaType;
          242      28    10    vt   Lcom/fasterxml/jackson/databind/JavaType;
          262       8    11   ser   Lcom/fasterxml/jackson/databind/JsonSerializer;
          490      24    21  prop   Lcom/fasterxml/jackson/databind/ser/BeanPropertyWriter;
          431      89    19     i   I
          438      82    20   len   I
          425     133    17 propName   Ljava/lang/String;
          428     130    18 idProp   Lcom/fasterxml/jackson/databind/ser/BeanPropertyWriter;
          540      18    19   gen   Lcom/fasterxml/jackson/annotation/ObjectIdGenerator;
          571      19    17   gen   Lcom/fasterxml/jackson/annotation/ObjectIdGenerator;
          385     205    14 implClass   Ljava/lang/Class;
          393     197    15  type   Lcom/fasterxml/jackson/databind/JavaType;
          408     182    16 idType   Lcom/fasterxml/jackson/databind/JavaType;
          327     299    13 objectIdInfo   Lcom/fasterxml/jackson/databind/introspect/ObjectIdInfo;
          598      28    14 filterId   Ljava/lang/Object;
          685       3    16 newFiltered   [Lcom/fasterxml/jackson/databind/ser/BeanPropertyWriter;
          651      89    14 newProps   [Lcom/fasterxml/jackson/databind/ser/BeanPropertyWriter;
          658      82    15   bpw   Lcom/fasterxml/jackson/databind/ser/BeanPropertyWriter;
          705      35    16 newFiltered   [Lcom/fasterxml/jackson/databind/ser/BeanPropertyWriter;
          757      27    14   ser   Lcom/fasterxml/jackson/databind/JsonSerializer;
            0     857     0  this   Lcom/fasterxml/jackson/databind/ser/std/BeanSerializerBase;
            0     857     1 provider   Lcom/fasterxml/jackson/databind/SerializerProvider;
            0     857     2 property   Lcom/fasterxml/jackson/databind/BeanProperty;
            5     852     3  intr   Lcom/fasterxml/jackson/databind/AnnotationIntrospector;
           25     832     4 accessor   Lcom/fasterxml/jackson/databind/introspect/AnnotatedMember;
           31     826     5 config   Lcom/fasterxml/jackson/databind/SerializationConfig;
           43     814     6 format   Lcom/fasterxml/jackson/annotation/JsonFormat$Value;
           46     811     7 shape   Lcom/fasterxml/jackson/annotation/JsonFormat$Shape;
          276     581     8   oiw   Lcom/fasterxml/jackson/databind/ser/impl/ObjectIdWriter;
          279     578     9 idPropOrigIndex   I
          282     575    10 ignoredProps   Ljava/util/Set;
          285     572    11 includedProps   Ljava/util/Set;
          288     569    12 newFilterId   Ljava/lang/Object;
          629     228    13 contextual   Lcom/fasterxml/jackson/databind/ser/std/BeanSerializerBase;
      LocalVariableTypeTable:
        Start  Length  Slot  Name   Signature
          159       8     9   ser   Lcom/fasterxml/jackson/databind/JsonSerializer<*>;
          262       8    11   ser   Lcom/fasterxml/jackson/databind/JsonSerializer<*>;
          540      18    19   gen   Lcom/fasterxml/jackson/annotation/ObjectIdGenerator<*>;
          571      19    17   gen   Lcom/fasterxml/jackson/annotation/ObjectIdGenerator<*>;
          385     205    14 implClass   Ljava/lang/Class<*>;
          757      27    14   ser   Lcom/fasterxml/jackson/databind/JsonSerializer<*>;
          282     575    10 ignoredProps   Ljava/util/Set<Ljava/lang/String;>;
          285     572    11 includedProps   Ljava/util/Set<Ljava/lang/String;>;
      StackMapTable: number_of_entries = 27
        frame_type = 252 /* append */
          offset_delta = 13
          locals = [ class com/fasterxml/jackson/databind/AnnotationIntrospector ]
        frame_type = 3 /* same */
        frame_type = 69 /* same_locals_1_stack_item */
          stack = [ class com/fasterxml/jackson/databind/introspect/AnnotatedMember ]
        frame_type = 255 /* full_frame */
          offset_delta = 104
          locals = [ class com/fasterxml/jackson/databind/ser/std/BeanSerializerBase, class com/fasterxml/jackson/databind/SerializerProvider, class com/fasterxml/jackson/databind/BeanProperty, class com/fasterxml/jackson/databind/AnnotationIntrospector, class com/fasterxml/jackson/databind/introspect/AnnotatedMember, class com/fasterxml/jackson/databind/SerializationConfig, class com/fasterxml/jackson/annotation/JsonFormat$Value, class com/fasterxml/jackson/annotation/JsonFormat$Shape ]
          stack = []
        frame_type = 38 /* same */
        frame_type = 2 /* same */
        frame_type = 32 /* same */
        frame_type = 251 /* same_frame_extended */
          offset_delta = 66
        frame_type = 255 /* full_frame */
          offset_delta = 97
          locals = [ class com/fasterxml/jackson/databind/ser/std/BeanSerializerBase, class com/fasterxml/jackson/databind/SerializerProvider, class com/fasterxml/jackson/databind/BeanProperty, class com/fasterxml/jackson/databind/AnnotationIntrospector, class com/fasterxml/jackson/databind/introspect/AnnotatedMember, class com/fasterxml/jackson/databind/SerializationConfig, class com/fasterxml/jackson/annotation/JsonFormat$Value, class com/fasterxml/jackson/annotation/JsonFormat$Shape, class com/fasterxml/jackson/databind/ser/impl/ObjectIdWriter, int, class java/util/Set, class java/util/Set, class java/lang/Object, class com/fasterxml/jackson/databind/introspect/ObjectIdInfo ]
          stack = []
        frame_type = 255 /* full_frame */
          offset_delta = 69
          locals = [ class com/fasterxml/jackson/databind/ser/std/BeanSerializerBase, class com/fasterxml/jackson/databind/SerializerProvider, class com/fasterxml/jackson/databind/BeanProperty, class com/fasterxml/jackson/databind/AnnotationIntrospector, class com/fasterxml/jackson/databind/introspect/AnnotatedMember, class com/fasterxml/jackson/databind/SerializationConfig, class com/fasterxml/jackson/annotation/JsonFormat$Value, class com/fasterxml/jackson/annotation/JsonFormat$Shape, class com/fasterxml/jackson/databind/ser/impl/ObjectIdWriter, int, class java/util/Set, class java/util/Set, class java/lang/Object, class com/fasterxml/jackson/databind/introspect/ObjectIdInfo, class java/lang/Class, class com/fasterxml/jackson/databind/JavaType, class com/fasterxml/jackson/databind/JavaType, class java/lang/String, class com/fasterxml/jackson/databind/ser/BeanPropertyWriter, int, int ]
          stack = []
        frame_type = 42 /* same */
        frame_type = 32 /* same */
        frame_type = 249 /* chop */
          offset_delta = 5
        frame_type = 249 /* chop */
          offset_delta = 40
        frame_type = 248 /* chop */
          offset_delta = 28
        frame_type = 252 /* append */
          offset_delta = 31
          locals = [ class java/lang/Object ]
        frame_type = 249 /* chop */
          offset_delta = 3
        frame_type = 254 /* append */
          offset_delta = 61
          locals = [ class com/fasterxml/jackson/databind/ser/std/BeanSerializerBase, class "[Lcom/fasterxml/jackson/databind/ser/BeanPropertyWriter;", class com/fasterxml/jackson/databind/ser/BeanPropertyWriter ]
        frame_type = 252 /* append */
          offset_delta = 40
          locals = [ class "[Lcom/fasterxml/jackson/databind/ser/BeanPropertyWriter;" ]
        frame_type = 248 /* chop */
          offset_delta = 10
        frame_type = 43 /* same */
        frame_type = 14 /* same */
        frame_type = 4 /* same */
        frame_type = 10 /* same */
        frame_type = 13 /* same */
        frame_type = 10 /* same */
        frame_type = 13 /* same */
    Exceptions:
      throws com.fasterxml.jackson.databind.JsonMappingException
    Signature: #370                         // (Lcom/fasterxml/jackson/databind/SerializerProvider;Lcom/fasterxml/jackson/databind/BeanProperty;)Lcom/fasterxml/jackson/databind/JsonSerializer<*>;

  public java.util.Iterator<com.fasterxml.jackson.databind.ser.PropertyWriter> properties();
    descriptor: ()Ljava/util/Iterator;
    flags: (0x0001) ACC_PUBLIC
    Code:
      stack=1, locals=1, args_size=1
         0: aload_0
         1: getfield      #3                  // Field _props:[Lcom/fasterxml/jackson/databind/ser/BeanPropertyWriter;
         4: invokestatic  #127                // Method java/util/Arrays.asList:([Ljava/lang/Object;)Ljava/util/List;
         7: invokeinterface #128,  1          // InterfaceMethod java/util/List.iterator:()Ljava/util/Iterator;
        12: areturn
      LineNumberTable:
        line 618: 0
      LocalVariableTable:
        Start  Length  Slot  Name   Signature
            0      13     0  this   Lcom/fasterxml/jackson/databind/ser/std/BeanSerializerBase;
    Signature: #372                         // ()Ljava/util/Iterator<Lcom/fasterxml/jackson/databind/ser/PropertyWriter;>;

  public boolean usesObjectId();
    descriptor: ()Z
    flags: (0x0001) ACC_PUBLIC
    Code:
      stack=1, locals=1, args_size=1
         0: aload_0
         1: getfield      #8                  // Field _objectIdWriter:Lcom/fasterxml/jackson/databind/ser/impl/ObjectIdWriter;
         4: ifnull        11
         7: iconst_1
         8: goto          12
        11: iconst_0
        12: ireturn
      LineNumberTable:
        line 629: 0
      LocalVariableTable:
        Start  Length  Slot  Name   Signature
            0      13     0  this   Lcom/fasterxml/jackson/databind/ser/std/BeanSerializerBase;
      StackMapTable: number_of_entries = 2
        frame_type = 11 /* same */
        frame_type = 64 /* same_locals_1_stack_item */
          stack = [ int ]

  public abstract void serialize(java.lang.Object, com.fasterxml.jackson.core.JsonGenerator, com.fasterxml.jackson.databind.SerializerProvider) throws java.io.IOException;
    descriptor: (Ljava/lang/Object;Lcom/fasterxml/jackson/core/JsonGenerator;Lcom/fasterxml/jackson/databind/SerializerProvider;)V
    flags: (0x0401) ACC_PUBLIC, ACC_ABSTRACT
    Exceptions:
      throws java.io.IOException

  public void serializeWithType(java.lang.Object, com.fasterxml.jackson.core.JsonGenerator, com.fasterxml.jackson.databind.SerializerProvider, com.fasterxml.jackson.databind.jsontype.TypeSerializer) throws java.io.IOException;
    descriptor: (Ljava/lang/Object;Lcom/fasterxml/jackson/core/JsonGenerator;Lcom/fasterxml/jackson/databind/SerializerProvider;Lcom/fasterxml/jackson/databind/jsontype/TypeSerializer;)V
    flags: (0x0001) ACC_PUBLIC
    Code:
      stack=5, locals=6, args_size=5
         0: aload_0
         1: getfield      #8                  // Field _objectIdWriter:Lcom/fasterxml/jackson/databind/ser/impl/ObjectIdWriter;
         4: ifnull        17
         7: aload_0
         8: aload_1
         9: aload_2
        10: aload_3
        11: aload         4
        13: invokevirtual #129                // Method _serializeWithObjectId:(Ljava/lang/Object;Lcom/fasterxml/jackson/core/JsonGenerator;Lcom/fasterxml/jackson/databind/SerializerProvider;Lcom/fasterxml/jackson/databind/jsontype/TypeSerializer;)V
        16: return
        17: aload_0
        18: aload         4
        20: aload_1
        21: getstatic     #130                // Field com/fasterxml/jackson/core/JsonToken.START_OBJECT:Lcom/fasterxml/jackson/core/JsonToken;
        24: invokevirtual #131                // Method _typeIdDef:(Lcom/fasterxml/jackson/databind/jsontype/TypeSerializer;Ljava/lang/Object;Lcom/fasterxml/jackson/core/JsonToken;)Lcom/fasterxml/jackson/core/type/WritableTypeId;
        27: astore        5
        29: aload         4
        31: aload_2
        32: aload         5
        34: invokevirtual #132                // Method com/fasterxml/jackson/databind/jsontype/TypeSerializer.writeTypePrefix:(Lcom/fasterxml/jackson/core/JsonGenerator;Lcom/fasterxml/jackson/core/type/WritableTypeId;)Lcom/fasterxml/jackson/core/type/WritableTypeId;
        37: pop
        38: aload_2
        39: aload_1
        40: invokevirtual #133                // Method com/fasterxml/jackson/core/JsonGenerator.setCurrentValue:(Ljava/lang/Object;)V
        43: aload_0
        44: getfield      #7                  // Field _propertyFilterId:Ljava/lang/Object;
        47: ifnull        60
        50: aload_0
        51: aload_1
        52: aload_2
        53: aload_3
        54: invokevirtual #134                // Method serializeFieldsFiltered:(Ljava/lang/Object;Lcom/fasterxml/jackson/core/JsonGenerator;Lcom/fasterxml/jackson/databind/SerializerProvider;)V
        57: goto          67
        60: aload_0
        61: aload_1
        62: aload_2
        63: aload_3
        64: invokevirtual #135                // Method serializeFields:(Ljava/lang/Object;Lcom/fasterxml/jackson/core/JsonGenerator;Lcom/fasterxml/jackson/databind/SerializerProvider;)V
        67: aload         4
        69: aload_2
        70: aload         5
        72: invokevirtual #136                // Method com/fasterxml/jackson/databind/jsontype/TypeSerializer.writeTypeSuffix:(Lcom/fasterxml/jackson/core/JsonGenerator;Lcom/fasterxml/jackson/core/type/WritableTypeId;)Lcom/fasterxml/jackson/core/type/WritableTypeId;
        75: pop
        76: return
      LineNumberTable:
        line 643: 0
        line 647: 7
        line 648: 16
        line 651: 17
        line 652: 29
        line 653: 38
        line 654: 43
        line 655: 50
        line 657: 60
        line 659: 67
        line 660: 76
      LocalVariableTable:
        Start  Length  Slot  Name   Signature
            0      77     0  this   Lcom/fasterxml/jackson/databind/ser/std/BeanSerializerBase;
            0      77     1  bean   Ljava/lang/Object;
            0      77     2   gen   Lcom/fasterxml/jackson/core/JsonGenerator;
            0      77     3 provider   Lcom/fasterxml/jackson/databind/SerializerProvider;
            0      77     4 typeSer   Lcom/fasterxml/jackson/databind/jsontype/TypeSerializer;
           29      48     5 typeIdDef   Lcom/fasterxml/jackson/core/type/WritableTypeId;
      StackMapTable: number_of_entries = 3
        frame_type = 17 /* same */
        frame_type = 252 /* append */
          offset_delta = 42
          locals = [ class com/fasterxml/jackson/core/type/WritableTypeId ]
        frame_type = 6 /* same */
    Exceptions:
      throws java.io.IOException

  protected final void _serializeWithObjectId(java.lang.Object, com.fasterxml.jackson.core.JsonGenerator, com.fasterxml.jackson.databind.SerializerProvider, boolean) throws java.io.IOException;
    descriptor: (Ljava/lang/Object;Lcom/fasterxml/jackson/core/JsonGenerator;Lcom/fasterxml/jackson/databind/SerializerProvider;Z)V
    flags: (0x0014) ACC_PROTECTED, ACC_FINAL
    Code:
      stack=4, locals=8, args_size=5
         0: aload_0
         1: getfield      #8                  // Field _objectIdWriter:Lcom/fasterxml/jackson/databind/ser/impl/ObjectIdWriter;
         4: astore        5
         6: aload_3
         7: aload_1
         8: aload         5
        10: getfield      #137                // Field com/fasterxml/jackson/databind/ser/impl/ObjectIdWriter.generator:Lcom/fasterxml/jackson/annotation/ObjectIdGenerator;
        13: invokevirtual #138                // Method com/fasterxml/jackson/databind/SerializerProvider.findObjectId:(Ljava/lang/Object;Lcom/fasterxml/jackson/annotation/ObjectIdGenerator;)Lcom/fasterxml/jackson/databind/ser/impl/WritableObjectId;
        16: astore        6
        18: aload         6
        20: aload_2
        21: aload_3
        22: aload         5
        24: invokevirtual #139                // Method com/fasterxml/jackson/databind/ser/impl/WritableObjectId.writeAsId:(Lcom/fasterxml/jackson/core/JsonGenerator;Lcom/fasterxml/jackson/databind/SerializerProvider;Lcom/fasterxml/jackson/databind/ser/impl/ObjectIdWriter;)Z
        27: ifeq          31
        30: return
        31: aload         6
        33: aload_1
        34: invokevirtual #140                // Method com/fasterxml/jackson/databind/ser/impl/WritableObjectId.generateId:(Ljava/lang/Object;)Ljava/lang/Object;
        37: astore        7
        39: aload         5
        41: getfield      #141                // Field com/fasterxml/jackson/databind/ser/impl/ObjectIdWriter.alwaysAsId:Z
        44: ifeq          60
        47: aload         5
        49: getfield      #142                // Field com/fasterxml/jackson/databind/ser/impl/ObjectIdWriter.serializer:Lcom/fasterxml/jackson/databind/JsonSerializer;
        52: aload         7
        54: aload_2
        55: aload_3
        56: invokevirtual #143                // Method com/fasterxml/jackson/databind/JsonSerializer.serialize:(Ljava/lang/Object;Lcom/fasterxml/jackson/core/JsonGenerator;Lcom/fasterxml/jackson/databind/SerializerProvider;)V
        59: return
        60: iload         4
        62: ifeq          70
        65: aload_2
        66: aload_1
        67: invokevirtual #144                // Method com/fasterxml/jackson/core/JsonGenerator.writeStartObject:(Ljava/lang/Object;)V
        70: aload         6
        72: aload_2
        73: aload_3
        74: aload         5
        76: invokevirtual #145                // Method com/fasterxml/jackson/databind/ser/impl/WritableObjectId.writeAsField:(Lcom/fasterxml/jackson/core/JsonGenerator;Lcom/fasterxml/jackson/databind/SerializerProvider;Lcom/fasterxml/jackson/databind/ser/impl/ObjectIdWriter;)V
        79: aload_0
        80: getfield      #7                  // Field _propertyFilterId:Ljava/lang/Object;
        83: ifnull        96
        86: aload_0
        87: aload_1
        88: aload_2
        89: aload_3
        90: invokevirtual #134                // Method serializeFieldsFiltered:(Ljava/lang/Object;Lcom/fasterxml/jackson/core/JsonGenerator;Lcom/fasterxml/jackson/databind/SerializerProvider;)V
        93: goto          103
        96: aload_0
        97: aload_1
        98: aload_2
        99: aload_3
       100: invokevirtual #135                // Method serializeFields:(Ljava/lang/Object;Lcom/fasterxml/jackson/core/JsonGenerator;Lcom/fasterxml/jackson/databind/SerializerProvider;)V
       103: iload         4
       105: ifeq          112
       108: aload_2
       109: invokevirtual #146                // Method com/fasterxml/jackson/core/JsonGenerator.writeEndObject:()V
       112: return
      LineNumberTable:
        line 665: 0
        line 666: 6
        line 668: 18
        line 669: 30
        line 672: 31
        line 673: 39
        line 674: 47
        line 675: 59
        line 677: 60
        line 678: 65
        line 680: 70
        line 681: 79
        line 682: 86
        line 684: 96
        line 686: 103
        line 687: 108
        line 689: 112
      LocalVariableTable:
        Start  Length  Slot  Name   Signature
            0     113     0  this   Lcom/fasterxml/jackson/databind/ser/std/BeanSerializerBase;
            0     113     1  bean   Ljava/lang/Object;
            0     113     2   gen   Lcom/fasterxml/jackson/core/JsonGenerator;
            0     113     3 provider   Lcom/fasterxml/jackson/databind/SerializerProvider;
            0     113     4 startEndObject   Z
            6     107     5     w   Lcom/fasterxml/jackson/databind/ser/impl/ObjectIdWriter;
           18      95     6 objectId   Lcom/fasterxml/jackson/databind/ser/impl/WritableObjectId;
           39      74     7    id   Ljava/lang/Object;
      StackMapTable: number_of_entries = 6
        frame_type = 253 /* append */
          offset_delta = 31
          locals = [ class com/fasterxml/jackson/databind/ser/impl/ObjectIdWriter, class com/fasterxml/jackson/databind/ser/impl/WritableObjectId ]
        frame_type = 252 /* append */
          offset_delta = 28
          locals = [ class java/lang/Object ]
        frame_type = 9 /* same */
        frame_type = 25 /* same */
        frame_type = 6 /* same */
        frame_type = 8 /* same */
    Exceptions:
      throws java.io.IOException

  protected final void _serializeWithObjectId(java.lang.Object, com.fasterxml.jackson.core.JsonGenerator, com.fasterxml.jackson.databind.SerializerProvider, com.fasterxml.jackson.databind.jsontype.TypeSerializer) throws java.io.IOException;
    descriptor: (Ljava/lang/Object;Lcom/fasterxml/jackson/core/JsonGenerator;Lcom/fasterxml/jackson/databind/SerializerProvider;Lcom/fasterxml/jackson/databind/jsontype/TypeSerializer;)V
    flags: (0x0014) ACC_PROTECTED, ACC_FINAL
    Code:
      stack=6, locals=8, args_size=5
         0: aload_0
         1: getfield      #8                  // Field _objectIdWriter:Lcom/fasterxml/jackson/databind/ser/impl/ObjectIdWriter;
         4: astore        5
         6: aload_3
         7: aload_1
         8: aload         5
        10: getfield      #137                // Field com/fasterxml/jackson/databind/ser/impl/ObjectIdWriter.generator:Lcom/fasterxml/jackson/annotation/ObjectIdGenerator;
        13: invokevirtual #138                // Method com/fasterxml/jackson/databind/SerializerProvider.findObjectId:(Ljava/lang/Object;Lcom/fasterxml/jackson/annotation/ObjectIdGenerator;)Lcom/fasterxml/jackson/databind/ser/impl/WritableObjectId;
        16: astore        6
        18: aload         6
        20: aload_2
        21: aload_3
        22: aload         5
        24: invokevirtual #139                // Method com/fasterxml/jackson/databind/ser/impl/WritableObjectId.writeAsId:(Lcom/fasterxml/jackson/core/JsonGenerator;Lcom/fasterxml/jackson/databind/SerializerProvider;Lcom/fasterxml/jackson/databind/ser/impl/ObjectIdWriter;)Z
        27: ifeq          31
        30: return
        31: aload         6
        33: aload_1
        34: invokevirtual #140                // Method com/fasterxml/jackson/databind/ser/impl/WritableObjectId.generateId:(Ljava/lang/Object;)Ljava/lang/Object;
        37: astore        7
        39: aload         5
        41: getfield      #141                // Field com/fasterxml/jackson/databind/ser/impl/ObjectIdWriter.alwaysAsId:Z
        44: ifeq          60
        47: aload         5
        49: getfield      #142                // Field com/fasterxml/jackson/databind/ser/impl/ObjectIdWriter.serializer:Lcom/fasterxml/jackson/databind/JsonSerializer;
        52: aload         7
        54: aload_2
        55: aload_3
        56: invokevirtual #143                // Method com/fasterxml/jackson/databind/JsonSerializer.serialize:(Ljava/lang/Object;Lcom/fasterxml/jackson/core/JsonGenerator;Lcom/fasterxml/jackson/databind/SerializerProvider;)V
        59: return
        60: aload_0
        61: aload_1
        62: aload_2
        63: aload_3
        64: aload         4
        66: aload         6
        68: invokevirtual #147                // Method _serializeObjectId:(Ljava/lang/Object;Lcom/fasterxml/jackson/core/JsonGenerator;Lcom/fasterxml/jackson/databind/SerializerProvider;Lcom/fasterxml/jackson/databind/jsontype/TypeSerializer;Lcom/fasterxml/jackson/databind/ser/impl/WritableObjectId;)V
        71: return
      LineNumberTable:
        line 694: 0
        line 695: 6
        line 697: 18
        line 698: 30
        line 701: 31
        line 702: 39
        line 703: 47
        line 704: 59
        line 706: 60
        line 707: 71
      LocalVariableTable:
        Start  Length  Slot  Name   Signature
            0      72     0  this   Lcom/fasterxml/jackson/databind/ser/std/BeanSerializerBase;
            0      72     1  bean   Ljava/lang/Object;
            0      72     2   gen   Lcom/fasterxml/jackson/core/JsonGenerator;
            0      72     3 provider   Lcom/fasterxml/jackson/databind/SerializerProvider;
            0      72     4 typeSer   Lcom/fasterxml/jackson/databind/jsontype/TypeSerializer;
            6      66     5     w   Lcom/fasterxml/jackson/databind/ser/impl/ObjectIdWriter;
           18      54     6 objectId   Lcom/fasterxml/jackson/databind/ser/impl/WritableObjectId;
           39      33     7    id   Ljava/lang/Object;
      StackMapTable: number_of_entries = 2
        frame_type = 253 /* append */
          offset_delta = 31
          locals = [ class com/fasterxml/jackson/databind/ser/impl/ObjectIdWriter, class com/fasterxml/jackson/databind/ser/impl/WritableObjectId ]
        frame_type = 252 /* append */
          offset_delta = 28
          locals = [ class java/lang/Object ]
    Exceptions:
      throws java.io.IOException

  protected void _serializeObjectId(java.lang.Object, com.fasterxml.jackson.core.JsonGenerator, com.fasterxml.jackson.databind.SerializerProvider, com.fasterxml.jackson.databind.jsontype.TypeSerializer, com.fasterxml.jackson.databind.ser.impl.WritableObjectId) throws java.io.IOException;
    descriptor: (Ljava/lang/Object;Lcom/fasterxml/jackson/core/JsonGenerator;Lcom/fasterxml/jackson/databind/SerializerProvider;Lcom/fasterxml/jackson/databind/jsontype/TypeSerializer;Lcom/fasterxml/jackson/databind/ser/impl/WritableObjectId;)V
    flags: (0x0004) ACC_PROTECTED
    Code:
      stack=4, locals=8, args_size=6
         0: aload_0
         1: getfield      #8                  // Field _objectIdWriter:Lcom/fasterxml/jackson/databind/ser/impl/ObjectIdWriter;
         4: astore        6
         6: aload_0
         7: aload         4
         9: aload_1
        10: getstatic     #130                // Field com/fasterxml/jackson/core/JsonToken.START_OBJECT:Lcom/fasterxml/jackson/core/JsonToken;
        13: invokevirtual #131                // Method _typeIdDef:(Lcom/fasterxml/jackson/databind/jsontype/TypeSerializer;Ljava/lang/Object;Lcom/fasterxml/jackson/core/JsonToken;)Lcom/fasterxml/jackson/core/type/WritableTypeId;
        16: astore        7
        18: aload         4
        20: aload_2
        21: aload         7
        23: invokevirtual #132                // Method com/fasterxml/jackson/databind/jsontype/TypeSerializer.writeTypePrefix:(Lcom/fasterxml/jackson/core/JsonGenerator;Lcom/fasterxml/jackson/core/type/WritableTypeId;)Lcom/fasterxml/jackson/core/type/WritableTypeId;
        26: pop
        27: aload_2
        28: aload_1
        29: invokevirtual #133                // Method com/fasterxml/jackson/core/JsonGenerator.setCurrentValue:(Ljava/lang/Object;)V
        32: aload         5
        34: aload_2
        35: aload_3
        36: aload         6
        38: invokevirtual #145                // Method com/fasterxml/jackson/databind/ser/impl/WritableObjectId.writeAsField:(Lcom/fasterxml/jackson/core/JsonGenerator;Lcom/fasterxml/jackson/databind/SerializerProvider;Lcom/fasterxml/jackson/databind/ser/impl/ObjectIdWriter;)V
        41: aload_0
        42: getfield      #7                  // Field _propertyFilterId:Ljava/lang/Object;
        45: ifnull        58
        48: aload_0
        49: aload_1
        50: aload_2
        51: aload_3
        52: invokevirtual #134                // Method serializeFieldsFiltered:(Ljava/lang/Object;Lcom/fasterxml/jackson/core/JsonGenerator;Lcom/fasterxml/jackson/databind/SerializerProvider;)V
        55: goto          65
        58: aload_0
        59: aload_1
        60: aload_2
        61: aload_3
        62: invokevirtual #135                // Method serializeFields:(Ljava/lang/Object;Lcom/fasterxml/jackson/core/JsonGenerator;Lcom/fasterxml/jackson/databind/SerializerProvider;)V
        65: aload         4
        67: aload_2
        68: aload         7
        70: invokevirtual #136                // Method com/fasterxml/jackson/databind/jsontype/TypeSerializer.writeTypeSuffix:(Lcom/fasterxml/jackson/core/JsonGenerator;Lcom/fasterxml/jackson/core/type/WritableTypeId;)Lcom/fasterxml/jackson/core/type/WritableTypeId;
        73: pop
        74: return
      LineNumberTable:
        line 713: 0
        line 714: 6
        line 716: 18
        line 718: 27
        line 719: 32
        line 720: 41
        line 721: 48
        line 723: 58
        line 725: 65
        line 726: 74
      LocalVariableTable:
        Start  Length  Slot  Name   Signature
            0      75     0  this   Lcom/fasterxml/jackson/databind/ser/std/BeanSerializerBase;
            0      75     1  bean   Ljava/lang/Object;
            0      75     2     g   Lcom/fasterxml/jackson/core/JsonGenerator;
            0      75     3 provider   Lcom/fasterxml/jackson/databind/SerializerProvider;
            0      75     4 typeSer   Lcom/fasterxml/jackson/databind/jsontype/TypeSerializer;
            0      75     5 objectId   Lcom/fasterxml/jackson/databind/ser/impl/WritableObjectId;
            6      69     6     w   Lcom/fasterxml/jackson/databind/ser/impl/ObjectIdWriter;
           18      57     7 typeIdDef   Lcom/fasterxml/jackson/core/type/WritableTypeId;
      StackMapTable: number_of_entries = 2
        frame_type = 253 /* append */
          offset_delta = 58
          locals = [ class com/fasterxml/jackson/databind/ser/impl/ObjectIdWriter, class com/fasterxml/jackson/core/type/WritableTypeId ]
        frame_type = 6 /* same */
    Exceptions:
      throws java.io.IOException

  protected final com.fasterxml.jackson.core.type.WritableTypeId _typeIdDef(com.fasterxml.jackson.databind.jsontype.TypeSerializer, java.lang.Object, com.fasterxml.jackson.core.JsonToken);
    descriptor: (Lcom/fasterxml/jackson/databind/jsontype/TypeSerializer;Ljava/lang/Object;Lcom/fasterxml/jackson/core/JsonToken;)Lcom/fasterxml/jackson/core/type/WritableTypeId;
    flags: (0x0014) ACC_PROTECTED, ACC_FINAL
    Code:
      stack=4, locals=5, args_size=4
         0: aload_0
         1: getfield      #5                  // Field _typeId:Lcom/fasterxml/jackson/databind/introspect/AnnotatedMember;
         4: ifnonnull     14
         7: aload_1
         8: aload_2
         9: aload_3
        10: invokevirtual #148                // Method com/fasterxml/jackson/databind/jsontype/TypeSerializer.typeId:(Ljava/lang/Object;Lcom/fasterxml/jackson/core/JsonToken;)Lcom/fasterxml/jackson/core/type/WritableTypeId;
        13: areturn
        14: aload_0
        15: getfield      #5                  // Field _typeId:Lcom/fasterxml/jackson/databind/introspect/AnnotatedMember;
        18: aload_2
        19: invokevirtual #149                // Method com/fasterxml/jackson/databind/introspect/AnnotatedMember.getValue:(Ljava/lang/Object;)Ljava/lang/Object;
        22: astore        4
        24: aload         4
        26: ifnonnull     33
        29: ldc           #150                // String
        31: astore        4
        33: aload_1
        34: aload_2
        35: aload_3
        36: aload         4
        38: invokevirtual #151                // Method com/fasterxml/jackson/databind/jsontype/TypeSerializer.typeId:(Ljava/lang/Object;Lcom/fasterxml/jackson/core/JsonToken;Ljava/lang/Object;)Lcom/fasterxml/jackson/core/type/WritableTypeId;
        41: areturn
      LineNumberTable:
        line 733: 0
        line 734: 7
        line 736: 14
        line 737: 24
        line 739: 29
        line 741: 33
      LocalVariableTable:
        Start  Length  Slot  Name   Signature
            0      42     0  this   Lcom/fasterxml/jackson/databind/ser/std/BeanSerializerBase;
            0      42     1 typeSer   Lcom/fasterxml/jackson/databind/jsontype/TypeSerializer;
            0      42     2  bean   Ljava/lang/Object;
            0      42     3 valueShape   Lcom/fasterxml/jackson/core/JsonToken;
           24      18     4 typeId   Ljava/lang/Object;
      StackMapTable: number_of_entries = 2
        frame_type = 14 /* same */
        frame_type = 252 /* append */
          offset_delta = 18
          locals = [ class java/lang/Object ]

  protected final java.lang.String _customTypeId(java.lang.Object);
    descriptor: (Ljava/lang/Object;)Ljava/lang/String;
    flags: (0x0014) ACC_PROTECTED, ACC_FINAL
    Code:
      stack=2, locals=3, args_size=2
         0: aload_0
         1: getfield      #5                  // Field _typeId:Lcom/fasterxml/jackson/databind/introspect/AnnotatedMember;
         4: aload_1
         5: invokevirtual #149                // Method com/fasterxml/jackson/databind/introspect/AnnotatedMember.getValue:(Ljava/lang/Object;)Ljava/lang/Object;
         8: astore_2
         9: aload_2
        10: ifnonnull     16
        13: ldc           #150                // String
        15: areturn
        16: aload_2
        17: instanceof    #152                // class java/lang/String
        20: ifeq          30
        23: aload_2
        24: checkcast     #152                // class java/lang/String
        27: goto          34
        30: aload_2
        31: invokevirtual #153                // Method java/lang/Object.toString:()Ljava/lang/String;
        34: areturn
      LineNumberTable:
        line 747: 0
        line 748: 9
        line 749: 13
        line 751: 16
      LocalVariableTable:
        Start  Length  Slot  Name   Signature
            0      35     0  this   Lcom/fasterxml/jackson/databind/ser/std/BeanSerializerBase;
            0      35     1  bean   Ljava/lang/Object;
            9      26     2 typeId   Ljava/lang/Object;
      StackMapTable: number_of_entries = 3
        frame_type = 252 /* append */
          offset_delta = 16
          locals = [ class java/lang/Object ]
        frame_type = 13 /* same */
        frame_type = 67 /* same_locals_1_stack_item */
          stack = [ class java/lang/String ]
    Deprecated: true
    RuntimeVisibleAnnotations:
      0: #248()
        java.lang.Deprecated

  protected void serializeFields(java.lang.Object, com.fasterxml.jackson.core.JsonGenerator, com.fasterxml.jackson.databind.SerializerProvider) throws java.io.IOException;
    descriptor: (Ljava/lang/Object;Lcom/fasterxml/jackson/core/JsonGenerator;Lcom/fasterxml/jackson/databind/SerializerProvider;)V
    flags: (0x0004) ACC_PROTECTED
    Code:
      stack=5, locals=9, args_size=4
         0: aload_0
         1: getfield      #4                  // Field _filteredProps:[Lcom/fasterxml/jackson/databind/ser/BeanPropertyWriter;
         4: ifnull        23
         7: aload_3
         8: invokevirtual #154                // Method com/fasterxml/jackson/databind/SerializerProvider.getActiveView:()Ljava/lang/Class;
        11: ifnull        23
        14: aload_0
        15: getfield      #4                  // Field _filteredProps:[Lcom/fasterxml/jackson/databind/ser/BeanPropertyWriter;
        18: astore        4
        20: goto          29
        23: aload_0
        24: getfield      #3                  // Field _props:[Lcom/fasterxml/jackson/databind/ser/BeanPropertyWriter;
        27: astore        4
        29: iconst_0
        30: istore        5
        32: aload         4
        34: arraylength
        35: istore        6
        37: iload         5
        39: iload         6
        41: if_icmpge     70
        44: aload         4
        46: iload         5
        48: aaload
        49: astore        7
        51: aload         7
        53: ifnull        64
        56: aload         7
        58: aload_1
        59: aload_2
        60: aload_3
        61: invokevirtual #155                // Method com/fasterxml/jackson/databind/ser/BeanPropertyWriter.serializeAsField:(Ljava/lang/Object;Lcom/fasterxml/jackson/core/JsonGenerator;Lcom/fasterxml/jackson/databind/SerializerProvider;)V
        64: iinc          5, 1
        67: goto          37
        70: aload_0
        71: getfield      #6                  // Field _anyGetterWriter:Lcom/fasterxml/jackson/databind/ser/AnyGetterWriter;
        74: ifnull        87
        77: aload_0
        78: getfield      #6                  // Field _anyGetterWriter:Lcom/fasterxml/jackson/databind/ser/AnyGetterWriter;
        81: aload_1
        82: aload_2
        83: aload_3
        84: invokevirtual #156                // Method com/fasterxml/jackson/databind/ser/AnyGetterWriter.getAndSerialize:(Ljava/lang/Object;Lcom/fasterxml/jackson/core/JsonGenerator;Lcom/fasterxml/jackson/databind/SerializerProvider;)V
        87: goto          178
        90: astore        6
        92: iload         5
        94: aload         4
        96: arraylength
        97: if_icmpne     105
       100: ldc           #158                // String [anySetter]
       102: goto          113
       105: aload         4
       107: iload         5
       109: aaload
       110: invokevirtual #24                 // Method com/fasterxml/jackson/databind/ser/BeanPropertyWriter.getName:()Ljava/lang/String;
       113: astore        7
       115: aload_0
       116: aload_3
       117: aload         6
       119: aload_1
       120: aload         7
       122: invokevirtual #159                // Method wrapAndThrow:(Lcom/fasterxml/jackson/databind/SerializerProvider;Ljava/lang/Throwable;Ljava/lang/Object;Ljava/lang/String;)V
       125: goto          178
       128: astore        6
       130: new           #161                // class com/fasterxml/jackson/databind/JsonMappingException
       133: dup
       134: aload_2
       135: ldc           #162                // String Infinite recursion (StackOverflowError)
       137: aload         6
       139: invokespecial #163                // Method com/fasterxml/jackson/databind/JsonMappingException."<init>":(Ljava/io/Closeable;Ljava/lang/String;Ljava/lang/Throwable;)V
       142: astore        7
       144: iload         5
       146: aload         4
       148: arraylength
       149: if_icmpne     157
       152: ldc           #158                // String [anySetter]
       154: goto          165
       157: aload         4
       159: iload         5
       161: aaload
       162: invokevirtual #24                 // Method com/fasterxml/jackson/databind/ser/BeanPropertyWriter.getName:()Ljava/lang/String;
       165: astore        8
       167: aload         7
       169: aload_1
       170: aload         8
       172: invokevirtual #164                // Method com/fasterxml/jackson/databind/DatabindException.prependPath:(Ljava/lang/Object;Ljava/lang/String;)V
       175: aload         7
       177: athrow
       178: return
      Exception table:
         from    to  target type
            32    87    90   Class java/lang/Exception
            32    87   128   Class java/lang/StackOverflowError
      LineNumberTable:
        line 764: 0
        line 765: 14
        line 767: 23
        line 769: 29
        line 771: 32
        line 772: 44
        line 773: 51
        line 774: 56
        line 771: 64
        line 777: 70
        line 778: 77
        line 794: 87
        line 780: 90
        line 781: 92
        line 782: 115
        line 794: 125
        line 783: 128
        line 789: 130
        line 791: 144
        line 792: 167
        line 793: 175
        line 795: 178
      LocalVariableTable:
        Start  Length  Slot  Name   Signature
           20       3     4 props   [Lcom/fasterxml/jackson/databind/ser/BeanPropertyWriter;
           51      13     7  prop   Lcom/fasterxml/jackson/databind/ser/BeanPropertyWriter;
           37      33     6   len   I
          115      10     7  name   Ljava/lang/String;
           92      33     6     e   Ljava/lang/Exception;
          144      34     7  mapE   Lcom/fasterxml/jackson/databind/DatabindException;
          167      11     8  name   Ljava/lang/String;
          130      48     6     e   Ljava/lang/StackOverflowError;
            0     179     0  this   Lcom/fasterxml/jackson/databind/ser/std/BeanSerializerBase;
            0     179     1  bean   Ljava/lang/Object;
            0     179     2   gen   Lcom/fasterxml/jackson/core/JsonGenerator;
            0     179     3 provider   Lcom/fasterxml/jackson/databind/SerializerProvider;
           29     150     4 props   [Lcom/fasterxml/jackson/databind/ser/BeanPropertyWriter;
           32     147     5     i   I
      StackMapTable: number_of_entries = 13
        frame_type = 23 /* same */
        frame_type = 252 /* append */
          offset_delta = 5
          locals = [ class "[Lcom/fasterxml/jackson/databind/ser/BeanPropertyWriter;" ]
        frame_type = 253 /* append */
          offset_delta = 7
          locals = [ int, int ]
        frame_type = 26 /* same */
        frame_type = 250 /* chop */
          offset_delta = 5
        frame_type = 16 /* same */
        frame_type = 66 /* same_locals_1_stack_item */
          stack = [ class java/lang/Exception ]
        frame_type = 252 /* append */
          offset_delta = 14
          locals = [ class java/lang/Exception ]
        frame_type = 71 /* same_locals_1_stack_item */
          stack = [ class java/lang/String ]
        frame_type = 255 /* full_frame */
          offset_delta = 14
          locals = [ class com/fasterxml/jackson/databind/ser/std/BeanSerializerBase, class java/lang/Object, class com/fasterxml/jackson/core/JsonGenerator, class com/fasterxml/jackson/databind/SerializerProvider, class "[Lcom/fasterxml/jackson/databind/ser/BeanPropertyWriter;", int ]
          stack = [ class java/lang/StackOverflowError ]
        frame_type = 253 /* append */
          offset_delta = 28
          locals = [ class java/lang/StackOverflowError, class com/fasterxml/jackson/databind/DatabindException ]
        frame_type = 71 /* same_locals_1_stack_item */
          stack = [ class java/lang/String ]
        frame_type = 249 /* chop */
          offset_delta = 12
    Exceptions:
      throws java.io.IOException

  protected void serializeFieldsFiltered(java.lang.Object, com.fasterxml.jackson.core.JsonGenerator, com.fasterxml.jackson.databind.SerializerProvider) throws java.io.IOException;
    descriptor: (Ljava/lang/Object;Lcom/fasterxml/jackson/core/JsonGenerator;Lcom/fasterxml/jackson/databind/SerializerProvider;)V
    flags: (0x0004) ACC_PROTECTED
    Code:
      stack=5, locals=10, args_size=4
         0: aload_0
         1: getfield      #4                  // Field _filteredProps:[Lcom/fasterxml/jackson/databind/ser/BeanPropertyWriter;
         4: ifnull        23
         7: aload_3
         8: invokevirtual #154                // Method com/fasterxml/jackson/databind/SerializerProvider.getActiveView:()Ljava/lang/Class;
        11: ifnull        23
        14: aload_0
        15: getfield      #4                  // Field _filteredProps:[Lcom/fasterxml/jackson/databind/ser/BeanPropertyWriter;
        18: astore        4
        20: goto          29
        23: aload_0
        24: getfield      #3                  // Field _props:[Lcom/fasterxml/jackson/databind/ser/BeanPropertyWriter;
        27: astore        4
        29: aload_0
        30: aload_3
        31: aload_0
        32: getfield      #7                  // Field _propertyFilterId:Ljava/lang/Object;
        35: aload_1
        36: invokevirtual #165                // Method findPropertyFilter:(Lcom/fasterxml/jackson/databind/SerializerProvider;Ljava/lang/Object;Ljava/lang/Object;)Lcom/fasterxml/jackson/databind/ser/PropertyFilter;
        39: astore        5
        41: aload         5
        43: ifnonnull     54
        46: aload_0
        47: aload_1
        48: aload_2
        49: aload_3
        50: invokevirtual #135                // Method serializeFields:(Ljava/lang/Object;Lcom/fasterxml/jackson/core/JsonGenerator;Lcom/fasterxml/jackson/databind/SerializerProvider;)V
        53: return
        54: iconst_0
        55: istore        6
        57: aload         4
        59: arraylength
        60: istore        7
        62: iload         6
        64: iload         7
        66: if_icmpge     99
        69: aload         4
        71: iload         6
        73: aaload
        74: astore        8
        76: aload         8
        78: ifnull        93
        81: aload         5
        83: aload_1
        84: aload_2
        85: aload_3
        86: aload         8
        88: invokeinterface #166,  5          // InterfaceMethod com/fasterxml/jackson/databind/ser/PropertyFilter.serializeAsField:(Ljava/lang/Object;Lcom/fasterxml/jackson/core/JsonGenerator;Lcom/fasterxml/jackson/databind/SerializerProvider;Lcom/fasterxml/jackson/databind/ser/PropertyWriter;)V
        93: iinc          6, 1
        96: goto          62
        99: aload_0
       100: getfield      #6                  // Field _anyGetterWriter:Lcom/fasterxml/jackson/databind/ser/AnyGetterWriter;
       103: ifnull        118
       106: aload_0
       107: getfield      #6                  // Field _anyGetterWriter:Lcom/fasterxml/jackson/databind/ser/AnyGetterWriter;
       110: aload_1
       111: aload_2
       112: aload_3
       113: aload         5
       115: invokevirtual #167                // Method com/fasterxml/jackson/databind/ser/AnyGetterWriter.getAndFilter:(Ljava/lang/Object;Lcom/fasterxml/jackson/core/JsonGenerator;Lcom/fasterxml/jackson/databind/SerializerProvider;Lcom/fasterxml/jackson/databind/ser/PropertyFilter;)V
       118: goto          209
       121: astore        7
       123: iload         6
       125: aload         4
       127: arraylength
       128: if_icmpne     136
       131: ldc           #158                // String [anySetter]
       133: goto          144
       136: aload         4
       138: iload         6
       140: aaload
       141: invokevirtual #24                 // Method com/fasterxml/jackson/databind/ser/BeanPropertyWriter.getName:()Ljava/lang/String;
       144: astore        8
       146: aload_0
       147: aload_3
       148: aload         7
       150: aload_1
       151: aload         8
       153: invokevirtual #159                // Method wrapAndThrow:(Lcom/fasterxml/jackson/databind/SerializerProvider;Ljava/lang/Throwable;Ljava/lang/Object;Ljava/lang/String;)V
       156: goto          209
       159: astore        7
       161: new           #161                // class com/fasterxml/jackson/databind/JsonMappingException
       164: dup
       165: aload_2
       166: ldc           #162                // String Infinite recursion (StackOverflowError)
       168: aload         7
       170: invokespecial #163                // Method com/fasterxml/jackson/databind/JsonMappingException."<init>":(Ljava/io/Closeable;Ljava/lang/String;Ljava/lang/Throwable;)V
       173: astore        8
       175: iload         6
       177: aload         4
       179: arraylength
       180: if_icmpne     188
       183: ldc           #158                // String [anySetter]
       185: goto          196
       188: aload         4
       190: iload         6
       192: aaload
       193: invokevirtual #24                 // Method com/fasterxml/jackson/databind/ser/BeanPropertyWriter.getName:()Ljava/lang/String;
       196: astore        9
       198: aload         8
       200: aload_1
       201: aload         9
       203: invokevirtual #164                // Method com/fasterxml/jackson/databind/DatabindException.prependPath:(Ljava/lang/Object;Ljava/lang/String;)V
       206: aload         8
       208: athrow
       209: return
      Exception table:
         from    to  target type
            57   118   121   Class java/lang/Exception
            57   118   159   Class java/lang/StackOverflowError
      LineNumberTable:
        line 809: 0
        line 810: 14
        line 812: 23
        line 814: 29
        line 816: 41
        line 817: 46
        line 818: 53
        line 820: 54
        line 822: 57
        line 823: 69
        line 824: 76
        line 825: 81
        line 822: 93
        line 828: 99
        line 829: 106
        line 841: 118
        line 831: 121
        line 832: 123
        line 833: 146
        line 841: 156
        line 834: 159
        line 837: 161
        line 838: 175
        line 839: 198
        line 840: 206
        line 842: 209
      LocalVariableTable:
        Start  Length  Slot  Name   Signature
           20       3     4 props   [Lcom/fasterxml/jackson/databind/ser/BeanPropertyWriter;
           76      17     8  prop   Lcom/fasterxml/jackson/databind/ser/BeanPropertyWriter;
           62      37     7   len   I
          146      10     8  name   Ljava/lang/String;
          123      33     7     e   Ljava/lang/Exception;
          175      34     8  mapE   Lcom/fasterxml/jackson/databind/DatabindException;
          198      11     9  name   Ljava/lang/String;
          161      48     7     e   Ljava/lang/StackOverflowError;
            0     210     0  this   Lcom/fasterxml/jackson/databind/ser/std/BeanSerializerBase;
            0     210     1  bean   Ljava/lang/Object;
            0     210     2   gen   Lcom/fasterxml/jackson/core/JsonGenerator;
            0     210     3 provider   Lcom/fasterxml/jackson/databind/SerializerProvider;
           29     181     4 props   [Lcom/fasterxml/jackson/databind/ser/BeanPropertyWriter;
           41     169     5 filter   Lcom/fasterxml/jackson/databind/ser/PropertyFilter;
           57     153     6     i   I
      StackMapTable: number_of_entries = 14
        frame_type = 23 /* same */
        frame_type = 252 /* append */
          offset_delta = 5
          locals = [ class "[Lcom/fasterxml/jackson/databind/ser/BeanPropertyWriter;" ]
        frame_type = 252 /* append */
          offset_delta = 24
          locals = [ class com/fasterxml/jackson/databind/ser/PropertyFilter ]
        frame_type = 253 /* append */
          offset_delta = 7
          locals = [ int, int ]
        frame_type = 30 /* same */
        frame_type = 250 /* chop */
          offset_delta = 5
        frame_type = 18 /* same */
        frame_type = 66 /* same_locals_1_stack_item */
          stack = [ class java/lang/Exception ]
        frame_type = 252 /* append */
          offset_delta = 14
          locals = [ class java/lang/Exception ]
        frame_type = 71 /* same_locals_1_stack_item */
          stack = [ class java/lang/String ]
        frame_type = 255 /* full_frame */
          offset_delta = 14
          locals = [ class com/fasterxml/jackson/databind/ser/std/BeanSerializerBase, class java/lang/Object, class com/fasterxml/jackson/core/JsonGenerator, class com/fasterxml/jackson/databind/SerializerProvider, class "[Lcom/fasterxml/jackson/databind/ser/BeanPropertyWriter;", class com/fasterxml/jackson/databind/ser/PropertyFilter, int ]
          stack = [ class java/lang/StackOverflowError ]
        frame_type = 253 /* append */
          offset_delta = 28
          locals = [ class java/lang/StackOverflowError, class com/fasterxml/jackson/databind/DatabindException ]
        frame_type = 71 /* same_locals_1_stack_item */
          stack = [ class java/lang/String ]
        frame_type = 249 /* chop */
          offset_delta = 12
    Exceptions:
      throws java.io.IOException

  public com.fasterxml.jackson.databind.JsonNode getSchema(com.fasterxml.jackson.databind.SerializerProvider, java.lang.reflect.Type) throws com.fasterxml.jackson.databind.JsonMappingException;
    descriptor: (Lcom/fasterxml/jackson/databind/SerializerProvider;Ljava/lang/reflect/Type;)Lcom/fasterxml/jackson/databind/JsonNode;
    flags: (0x0001) ACC_PUBLIC
    Code:
      stack=4, locals=9, args_size=3
         0: aload_0
         1: ldc           #168                // String object
         3: iconst_1
         4: invokevirtual #169                // Method createSchemaNode:(Ljava/lang/String;Z)Lcom/fasterxml/jackson/databind/node/ObjectNode;
         7: astore_3
         8: aload_0
         9: getfield      #17                 // Field _handledType:Ljava/lang/Class;
        12: ldc           #170                // class com/fasterxml/jackson/databind/jsonschema/JsonSerializableSchema
        14: invokevirtual #171                // Method java/lang/Class.getAnnotation:(Ljava/lang/Class;)Ljava/lang/annotation/Annotation;
        17: checkcast     #170                // class com/fasterxml/jackson/databind/jsonschema/JsonSerializableSchema
        20: astore        4
        22: aload         4
        24: ifnull        58
        27: aload         4
        29: invokeinterface #172,  1          // InterfaceMethod com/fasterxml/jackson/databind/jsonschema/JsonSerializableSchema.id:()Ljava/lang/String;
        34: astore        5
        36: aload         5
        38: ifnull        58
        41: aload         5
        43: invokevirtual #173                // Method java/lang/String.isEmpty:()Z
        46: ifne          58
        49: aload_3
        50: ldc           #174                // String id
        52: aload         5
        54: invokevirtual #175                // Method com/fasterxml/jackson/databind/node/ObjectNode.put:(Ljava/lang/String;Ljava/lang/String;)Lcom/fasterxml/jackson/databind/node/ObjectNode;
        57: pop
        58: aload_3
        59: invokevirtual #176                // Method com/fasterxml/jackson/databind/node/ObjectNode.objectNode:()Lcom/fasterxml/jackson/databind/node/ObjectNode;
        62: astore        5
        64: aload_0
        65: getfield      #7                  // Field _propertyFilterId:Ljava/lang/Object;
        68: ifnull        86
        71: aload_0
        72: aload_1
        73: aload_0
        74: getfield      #7                  // Field _propertyFilterId:Ljava/lang/Object;
        77: aconst_null
        78: invokevirtual #165                // Method findPropertyFilter:(Lcom/fasterxml/jackson/databind/SerializerProvider;Ljava/lang/Object;Ljava/lang/Object;)Lcom/fasterxml/jackson/databind/ser/PropertyFilter;
        81: astore        6
        83: goto          89
        86: aconst_null
        87: astore        6
        89: iconst_0
        90: istore        7
        92: iload         7
        94: aload_0
        95: getfield      #3                  // Field _props:[Lcom/fasterxml/jackson/databind/ser/BeanPropertyWriter;
        98: arraylength
        99: if_icmpge     145
       102: aload_0
       103: getfield      #3                  // Field _props:[Lcom/fasterxml/jackson/databind/ser/BeanPropertyWriter;
       106: iload         7
       108: aaload
       109: astore        8
       111: aload         6
       113: ifnonnull     127
       116: aload         8
       118: aload         5
       120: aload_1
       121: invokevirtual #177                // Method com/fasterxml/jackson/databind/ser/BeanPropertyWriter.depositSchemaProperty:(Lcom/fasterxml/jackson/databind/node/ObjectNode;Lcom/fasterxml/jackson/databind/SerializerProvider;)V
       124: goto          139
       127: aload         6
       129: aload         8
       131: aload         5
       133: aload_1
       134: invokeinterface #178,  4          // InterfaceMethod com/fasterxml/jackson/databind/ser/PropertyFilter.depositSchemaProperty:(Lcom/fasterxml/jackson/databind/ser/PropertyWriter;Lcom/fasterxml/jackson/databind/node/ObjectNode;Lcom/fasterxml/jackson/databind/SerializerProvider;)V
       139: iinc          7, 1
       142: goto          92
       145: aload_3
       146: ldc           #179                // String properties
       148: aload         5
       150: invokevirtual #180                // Method com/fasterxml/jackson/databind/node/ObjectNode.set:(Ljava/lang/String;Lcom/fasterxml/jackson/databind/JsonNode;)Lcom/fasterxml/jackson/databind/JsonNode;
       153: pop
       154: aload_3
       155: areturn
      LineNumberTable:
        line 849: 0
        line 852: 8
        line 853: 22
        line 854: 27
        line 855: 36
        line 856: 49
        line 862: 58
        line 864: 64
        line 865: 71
        line 867: 86
        line 870: 89
        line 871: 102
        line 872: 111
        line 873: 116
        line 875: 127
        line 870: 139
        line 879: 145
        line 880: 154
      LocalVariableTable:
        Start  Length  Slot  Name   Signature
           36      22     5    id   Ljava/lang/String;
           83       3     6 filter   Lcom/fasterxml/jackson/databind/ser/PropertyFilter;
          111      28     8  prop   Lcom/fasterxml/jackson/databind/ser/BeanPropertyWriter;
           92      53     7     i   I
            0     156     0  this   Lcom/fasterxml/jackson/databind/ser/std/BeanSerializerBase;
            0     156     1 provider   Lcom/fasterxml/jackson/databind/SerializerProvider;
            0     156     2 typeHint   Ljava/lang/reflect/Type;
            8     148     3     o   Lcom/fasterxml/jackson/databind/node/ObjectNode;
           22     134     4   ann   Lcom/fasterxml/jackson/databind/jsonschema/JsonSerializableSchema;
           64      92     5 propertiesNode   Lcom/fasterxml/jackson/databind/node/ObjectNode;
           89      67     6 filter   Lcom/fasterxml/jackson/databind/ser/PropertyFilter;
      StackMapTable: number_of_entries = 7
        frame_type = 253 /* append */
          offset_delta = 58
          locals = [ class com/fasterxml/jackson/databind/node/ObjectNode, class com/fasterxml/jackson/databind/jsonschema/JsonSerializableSchema ]
        frame_type = 252 /* append */
          offset_delta = 27
          locals = [ class com/fasterxml/jackson/databind/node/ObjectNode ]
        frame_type = 252 /* append */
          offset_delta = 2
          locals = [ class com/fasterxml/jackson/databind/ser/PropertyFilter ]
        frame_type = 252 /* append */
          offset_delta = 2
          locals = [ int ]
        frame_type = 252 /* append */
          offset_delta = 34
          locals = [ class com/fasterxml/jackson/databind/ser/BeanPropertyWriter ]
        frame_type = 250 /* chop */
          offset_delta = 11
        frame_type = 250 /* chop */
          offset_delta = 5
    Exceptions:
      throws com.fasterxml.jackson.databind.JsonMappingException
    Deprecated: true
    RuntimeVisibleAnnotations:
      0: #248()
        java.lang.Deprecated

  public void acceptJsonFormatVisitor(com.fasterxml.jackson.databind.jsonFormatVisitors.JsonFormatVisitorWrapper, com.fasterxml.jackson.databind.JavaType) throws com.fasterxml.jackson.databind.JsonMappingException;
    descriptor: (Lcom/fasterxml/jackson/databind/jsonFormatVisitors/JsonFormatVisitorWrapper;Lcom/fasterxml/jackson/databind/JavaType;)V
    flags: (0x0001) ACC_PUBLIC
    Code:
      stack=4, locals=10, args_size=3
         0: aload_1
         1: ifnonnull     5
         4: return
         5: aload_1
         6: aload_2
         7: invokeinterface #181,  2          // InterfaceMethod com/fasterxml/jackson/databind/jsonFormatVisitors/JsonFormatVisitorWrapper.expectObjectFormat:(Lcom/fasterxml/jackson/databind/JavaType;)Lcom/fasterxml/jackson/databind/jsonFormatVisitors/JsonObjectFormatVisitor;
        12: astore_3
        13: aload_3
        14: ifnonnull     18
        17: return
        18: aload_1
        19: invokeinterface #182,  1          // InterfaceMethod com/fasterxml/jackson/databind/jsonFormatVisitors/JsonFormatVisitorWrapper.getProvider:()Lcom/fasterxml/jackson/databind/SerializerProvider;
        24: astore        4
        26: aload_0
        27: getfield      #7                  // Field _propertyFilterId:Ljava/lang/Object;
        30: ifnull        93
        33: aload_0
        34: aload_1
        35: invokeinterface #182,  1          // InterfaceMethod com/fasterxml/jackson/databind/jsonFormatVisitors/JsonFormatVisitorWrapper.getProvider:()Lcom/fasterxml/jackson/databind/SerializerProvider;
        40: aload_0
        41: getfield      #7                  // Field _propertyFilterId:Ljava/lang/Object;
        44: aconst_null
        45: invokevirtual #165                // Method findPropertyFilter:(Lcom/fasterxml/jackson/databind/SerializerProvider;Ljava/lang/Object;Ljava/lang/Object;)Lcom/fasterxml/jackson/databind/ser/PropertyFilter;
        48: astore        5
        50: iconst_0
        51: istore        6
        53: aload_0
        54: getfield      #3                  // Field _props:[Lcom/fasterxml/jackson/databind/ser/BeanPropertyWriter;
        57: arraylength
        58: istore        7
        60: iload         6
        62: iload         7
        64: if_icmpge     90
        67: aload         5
        69: aload_0
        70: getfield      #3                  // Field _props:[Lcom/fasterxml/jackson/databind/ser/BeanPropertyWriter;
        73: iload         6
        75: aaload
        76: aload_3
        77: aload         4
        79: invokeinterface #183,  4          // InterfaceMethod com/fasterxml/jackson/databind/ser/PropertyFilter.depositSchemaProperty:(Lcom/fasterxml/jackson/databind/ser/PropertyWriter;Lcom/fasterxml/jackson/databind/jsonFormatVisitors/JsonObjectFormatVisitor;Lcom/fasterxml/jackson/databind/SerializerProvider;)V
        84: iinc          6, 1
        87: goto          60
        90: goto          177
        93: aload_0
        94: getfield      #4                  // Field _filteredProps:[Lcom/fasterxml/jackson/databind/ser/BeanPropertyWriter;
        97: ifnull        105
       100: aload         4
       102: ifnonnull     109
       105: aconst_null
       106: goto          114
       109: aload         4
       111: invokevirtual #154                // Method com/fasterxml/jackson/databind/SerializerProvider.getActiveView:()Ljava/lang/Class;
       114: astore        5
       116: aload         5
       118: ifnull        130
       121: aload_0
       122: getfield      #4                  // Field _filteredProps:[Lcom/fasterxml/jackson/databind/ser/BeanPropertyWriter;
       125: astore        6
       127: goto          136
       130: aload_0
       131: getfield      #3                  // Field _props:[Lcom/fasterxml/jackson/databind/ser/BeanPropertyWriter;
       134: astore        6
       136: iconst_0
       137: istore        7
       139: aload         6
       141: arraylength
       142: istore        8
       144: iload         7
       146: iload         8
       148: if_icmpge     177
       151: aload         6
       153: iload         7
       155: aaload
       156: astore        9
       158: aload         9
       160: ifnull        171
       163: aload         9
       165: aload_3
       166: aload         4
       168: invokevirtual #184                // Method com/fasterxml/jackson/databind/ser/BeanPropertyWriter.depositSchemaProperty:(Lcom/fasterxml/jackson/databind/jsonFormatVisitors/JsonObjectFormatVisitor;Lcom/fasterxml/jackson/databind/SerializerProvider;)V
       171: iinc          7, 1
       174: goto          144
       177: return
      LineNumberTable:
        line 888: 0
        line 889: 4
        line 891: 5
        line 892: 13
        line 893: 17
        line 895: 18
        line 896: 26
        line 897: 33
        line 899: 50
        line 900: 67
        line 899: 84
        line 902: 90
        line 903: 93
        line 904: 111
        line 906: 116
        line 907: 121
        line 909: 130
        line 912: 136
        line 913: 151
        line 914: 158
        line 915: 163
        line 912: 171
        line 919: 177
      LocalVariableTable:
        Start  Length  Slot  Name   Signature
           53      37     6     i   I
           60      30     7   end   I
           50      40     5 filter   Lcom/fasterxml/jackson/databind/ser/PropertyFilter;
          127       3     6 props   [Lcom/fasterxml/jackson/databind/ser/BeanPropertyWriter;
          158      13     9  prop   Lcom/fasterxml/jackson/databind/ser/BeanPropertyWriter;
          139      38     7     i   I
          144      33     8   end   I
          116      61     5  view   Ljava/lang/Class;
          136      41     6 props   [Lcom/fasterxml/jackson/databind/ser/BeanPropertyWriter;
            0     178     0  this   Lcom/fasterxml/jackson/databind/ser/std/BeanSerializerBase;
            0     178     1 visitor   Lcom/fasterxml/jackson/databind/jsonFormatVisitors/JsonFormatVisitorWrapper;
            0     178     2 typeHint   Lcom/fasterxml/jackson/databind/JavaType;
           13     165     3 objectVisitor   Lcom/fasterxml/jackson/databind/jsonFormatVisitors/JsonObjectFormatVisitor;
           26     152     4 provider   Lcom/fasterxml/jackson/databind/SerializerProvider;
      LocalVariableTypeTable:
        Start  Length  Slot  Name   Signature
          116      61     5  view   Ljava/lang/Class<*>;
      StackMapTable: number_of_entries = 13
        frame_type = 5 /* same */
        frame_type = 252 /* append */
          offset_delta = 12
          locals = [ class com/fasterxml/jackson/databind/jsonFormatVisitors/JsonObjectFormatVisitor ]
        frame_type = 255 /* full_frame */
          offset_delta = 41
          locals = [ class com/fasterxml/jackson/databind/ser/std/BeanSerializerBase, class com/fasterxml/jackson/databind/jsonFormatVisitors/JsonFormatVisitorWrapper, class com/fasterxml/jackson/databind/JavaType, class com/fasterxml/jackson/databind/jsonFormatVisitors/JsonObjectFormatVisitor, class com/fasterxml/jackson/databind/SerializerProvider, class com/fasterxml/jackson/databind/ser/PropertyFilter, int, int ]
          stack = []
        frame_type = 248 /* chop */
          offset_delta = 29
        frame_type = 2 /* same */
        frame_type = 11 /* same */
        frame_type = 3 /* same */
        frame_type = 68 /* same_locals_1_stack_item */
          stack = [ class java/lang/Class ]
        frame_type = 252 /* append */
          offset_delta = 15
          locals = [ class java/lang/Class ]
        frame_type = 252 /* append */
          offset_delta = 5
          locals = [ class "[Lcom/fasterxml/jackson/databind/ser/BeanPropertyWriter;" ]
        frame_type = 253 /* append */
          offset_delta = 7
          locals = [ int, int ]
        frame_type = 26 /* same */
        frame_type = 255 /* full_frame */
          offset_delta = 5
          locals = [ class com/fasterxml/jackson/databind/ser/std/BeanSerializerBase, class com/fasterxml/jackson/databind/jsonFormatVisitors/JsonFormatVisitorWrapper, class com/fasterxml/jackson/databind/JavaType, class com/fasterxml/jackson/databind/jsonFormatVisitors/JsonObjectFormatVisitor, class com/fasterxml/jackson/databind/SerializerProvider ]
          stack = []
    Exceptions:
      throws com.fasterxml.jackson.databind.JsonMappingException

  public com.fasterxml.jackson.databind.JsonSerializer withFilterId(java.lang.Object);
    descriptor: (Ljava/lang/Object;)Lcom/fasterxml/jackson/databind/JsonSerializer;
    flags: (0x1041) ACC_PUBLIC, ACC_BRIDGE, ACC_SYNTHETIC
    Code:
      stack=2, locals=2, args_size=2
         0: aload_0
         1: aload_1
         2: invokevirtual #124                // Method withFilterId:(Ljava/lang/Object;)Lcom/fasterxml/jackson/databind/ser/std/BeanSerializerBase;
         5: areturn
      LineNumberTable:
        line 39: 0
      LocalVariableTable:
        Start  Length  Slot  Name   Signature
            0       6     0  this   Lcom/fasterxml/jackson/databind/ser/std/BeanSerializerBase;

  static {};
    descriptor: ()V
    flags: (0x0008) ACC_STATIC
    Code:
      stack=3, locals=0, args_size=0
         0: new           #112                // class com/fasterxml/jackson/databind/PropertyName
         3: dup
         4: ldc           #185                // String #object-ref
         6: invokespecial #186                // Method com/fasterxml/jackson/databind/PropertyName."<init>":(Ljava/lang/String;)V
         9: putstatic     #187                // Field NAME_FOR_OBJECT_REF:Lcom/fasterxml/jackson/databind/PropertyName;
        12: iconst_0
        13: anewarray     #28                 // class com/fasterxml/jackson/databind/ser/BeanPropertyWriter
        16: putstatic     #188                // Field NO_PROPS:[Lcom/fasterxml/jackson/databind/ser/BeanPropertyWriter;
        19: return
      LineNumberTable:
        line 45: 0
        line 47: 12
}
Signature: #443                         // Lcom/fasterxml/jackson/databind/ser/std/StdSerializer<Ljava/lang/Object;>;Lcom/fasterxml/jackson/databind/ser/ContextualSerializer;Lcom/fasterxml/jackson/databind/ser/ResolvableSerializer;Lcom/fasterxml/jackson/databind/jsonFormatVisitors/JsonFormatVisitable;Lcom/fasterxml/jackson/databind/jsonschema/SchemaAware;
SourceFile: "BeanSerializerBase.java"
InnerClasses:
  static #195;                            // class com/fasterxml/jackson/databind/ser/std/BeanSerializerBase$1
  public static final #215= #214 of #671; // Shape=class com/fasterxml/jackson/annotation/JsonFormat$Shape of class com/fasterxml/jackson/annotation/JsonFormat
  public static #224= #223 of #671;       // Value=class com/fasterxml/jackson/annotation/JsonFormat$Value of class com/fasterxml/jackson/annotation/JsonFormat
  public static #540= #82 of #80;         // Entry=class java/util/Map$Entry of class java/util/Map
  public static abstract #564= #99 of #562; // PropertyGenerator=class com/fasterxml/jackson/annotation/ObjectIdGenerators$PropertyGenerator of class com/fasterxml/jackson/annotation/ObjectIdGenerators
  public static #224= #546 of #797;       // Value=class com/fasterxml/jackson/annotation/JsonIgnoreProperties$Value of class com/fasterxml/jackson/annotation/JsonIgnoreProperties
  public static #224= #549 of #803;       // Value=class com/fasterxml/jackson/annotation/JsonIncludeProperties$Value of class com/fasterxml/jackson/annotation/JsonIncludeProperties
