Classfile /Users/mw/Projects/slang-braindump/.jar/jar8/assemble/slang-braindump/assemble/content/com/fasterxml/jackson/databind/ser/std/NumberSerializer.class
  Last modified May 29, 2022; size 6327 bytes
  SHA-256 checksum 17624cc72e904680b80552a3c3380287bff2f7ec8bfb2d5569ab74fe1d256912
  Compiled from "NumberSerializer.java"
public class com.fasterxml.jackson.databind.ser.std.NumberSerializer extends com.fasterxml.jackson.databind.ser.std.StdScalarSerializer<java.lang.Number> implements com.fasterxml.jackson.databind.ser.ContextualSerializer
  minor version: 0
  major version: 52
  flags: (0x0021) ACC_PUBLIC, ACC_SUPER
  this_class: #41                         // com/fasterxml/jackson/databind/ser/std/NumberSerializer
  super_class: #44                        // com/fasterxml/jackson/databind/ser/std/StdScalarSerializer
  interfaces: 1, fields: 3, methods: 8, attributes: 4
Constant pool:
    #1 = Methodref          #44.#118      // com/fasterxml/jackson/databind/ser/std/StdScalarSerializer."<init>":(Ljava/lang/Class;Z)V
    #2 = Class              #119          // java/math/BigInteger
    #3 = Fieldref           #41.#120      // com/fasterxml/jackson/databind/ser/std/NumberSerializer._isInt:Z
    #4 = Methodref          #41.#121      // com/fasterxml/jackson/databind/ser/std/NumberSerializer.handledType:()Ljava/lang/Class;
    #5 = Methodref          #41.#122      // com/fasterxml/jackson/databind/ser/std/NumberSerializer.findFormatOverrides:(Lcom/fasterxml/jackson/databind/SerializerProvider;Lcom/fasterxml/jackson/databind/BeanProperty;Ljava/lang/Class;)Lcom/fasterxml/jackson/annotation/JsonFormat$Value;
    #6 = Fieldref           #46.#123      // com/fasterxml/jackson/databind/ser/std/NumberSerializer$1.$SwitchMap$com$fasterxml$jackson$annotation$JsonFormat$Shape:[I
    #7 = Methodref          #80.#124      // com/fasterxml/jackson/annotation/JsonFormat$Value.getShape:()Lcom/fasterxml/jackson/annotation/JsonFormat$Shape;
    #8 = Methodref          #125.#126     // com/fasterxml/jackson/annotation/JsonFormat$Shape.ordinal:()I
    #9 = Class              #127          // java/math/BigDecimal
   #10 = Methodref          #41.#128      // com/fasterxml/jackson/databind/ser/std/NumberSerializer.bigDecimalAsStringSerializer:()Lcom/fasterxml/jackson/databind/JsonSerializer;
   #11 = Fieldref           #129.#130     // com/fasterxml/jackson/databind/ser/std/ToStringSerializer.instance:Lcom/fasterxml/jackson/databind/ser/std/ToStringSerializer;
   #12 = Methodref          #131.#132     // com/fasterxml/jackson/core/JsonGenerator.writeNumber:(Ljava/math/BigDecimal;)V
   #13 = Methodref          #131.#133     // com/fasterxml/jackson/core/JsonGenerator.writeNumber:(Ljava/math/BigInteger;)V
   #14 = Class              #134          // java/lang/Long
   #15 = Methodref          #39.#135      // java/lang/Number.longValue:()J
   #16 = Methodref          #131.#136     // com/fasterxml/jackson/core/JsonGenerator.writeNumber:(J)V
   #17 = Class              #137          // java/lang/Double
   #18 = Methodref          #39.#138      // java/lang/Number.doubleValue:()D
   #19 = Methodref          #131.#139     // com/fasterxml/jackson/core/JsonGenerator.writeNumber:(D)V
   #20 = Class              #140          // java/lang/Float
   #21 = Methodref          #39.#141      // java/lang/Number.floatValue:()F
   #22 = Methodref          #131.#142     // com/fasterxml/jackson/core/JsonGenerator.writeNumber:(F)V
   #23 = Class              #143          // java/lang/Integer
   #24 = Class              #144          // java/lang/Byte
   #25 = Class              #145          // java/lang/Short
   #26 = Methodref          #39.#146      // java/lang/Number.intValue:()I
   #27 = Methodref          #131.#147     // com/fasterxml/jackson/core/JsonGenerator.writeNumber:(I)V
   #28 = Methodref          #148.#149     // java/lang/Object.toString:()Ljava/lang/String;
   #29 = Methodref          #131.#150     // com/fasterxml/jackson/core/JsonGenerator.writeNumber:(Ljava/lang/String;)V
   #30 = String             #151          // integer
   #31 = String             #152          // number
   #32 = Methodref          #41.#153      // com/fasterxml/jackson/databind/ser/std/NumberSerializer.createSchemaNode:(Ljava/lang/String;Z)Lcom/fasterxml/jackson/databind/node/ObjectNode;
   #33 = Fieldref           #154.#155     // com/fasterxml/jackson/core/JsonParser$NumberType.BIG_INTEGER:Lcom/fasterxml/jackson/core/JsonParser$NumberType;
   #34 = Methodref          #41.#156      // com/fasterxml/jackson/databind/ser/std/NumberSerializer.visitIntFormat:(Lcom/fasterxml/jackson/databind/jsonFormatVisitors/JsonFormatVisitorWrapper;Lcom/fasterxml/jackson/databind/JavaType;Lcom/fasterxml/jackson/core/JsonParser$NumberType;)V
   #35 = Fieldref           #154.#157     // com/fasterxml/jackson/core/JsonParser$NumberType.BIG_DECIMAL:Lcom/fasterxml/jackson/core/JsonParser$NumberType;
   #36 = Methodref          #41.#158      // com/fasterxml/jackson/databind/ser/std/NumberSerializer.visitFloatFormat:(Lcom/fasterxml/jackson/databind/jsonFormatVisitors/JsonFormatVisitorWrapper;Lcom/fasterxml/jackson/databind/JavaType;Lcom/fasterxml/jackson/core/JsonParser$NumberType;)V
   #37 = InterfaceMethodref #159.#160     // com/fasterxml/jackson/databind/jsonFormatVisitors/JsonFormatVisitorWrapper.expectNumberFormat:(Lcom/fasterxml/jackson/databind/JavaType;)Lcom/fasterxml/jackson/databind/jsonFormatVisitors/JsonNumberFormatVisitor;
   #38 = Fieldref           #48.#161      // com/fasterxml/jackson/databind/ser/std/NumberSerializer$BigDecimalAsStringSerializer.BD_INSTANCE:Lcom/fasterxml/jackson/databind/ser/std/NumberSerializer$BigDecimalAsStringSerializer;
   #39 = Class              #162          // java/lang/Number
   #40 = Methodref          #41.#163      // com/fasterxml/jackson/databind/ser/std/NumberSerializer.serialize:(Ljava/lang/Number;Lcom/fasterxml/jackson/core/JsonGenerator;Lcom/fasterxml/jackson/databind/SerializerProvider;)V
   #41 = Class              #164          // com/fasterxml/jackson/databind/ser/std/NumberSerializer
   #42 = Methodref          #41.#165      // com/fasterxml/jackson/databind/ser/std/NumberSerializer."<init>":(Ljava/lang/Class;)V
   #43 = Fieldref           #41.#166      // com/fasterxml/jackson/databind/ser/std/NumberSerializer.instance:Lcom/fasterxml/jackson/databind/ser/std/NumberSerializer;
   #44 = Class              #167          // com/fasterxml/jackson/databind/ser/std/StdScalarSerializer
   #45 = Class              #168          // com/fasterxml/jackson/databind/ser/ContextualSerializer
   #46 = Class              #169          // com/fasterxml/jackson/databind/ser/std/NumberSerializer$1
   #47 = Utf8               InnerClasses
   #48 = Class              #170          // com/fasterxml/jackson/databind/ser/std/NumberSerializer$BigDecimalAsStringSerializer
   #49 = Utf8               BigDecimalAsStringSerializer
   #50 = Utf8               instance
   #51 = Utf8               Lcom/fasterxml/jackson/databind/ser/std/NumberSerializer;
   #52 = Utf8               MAX_BIG_DECIMAL_SCALE
   #53 = Utf8               I
   #54 = Utf8               ConstantValue
   #55 = Integer            9999
   #56 = Utf8               _isInt
   #57 = Utf8               Z
   #58 = Utf8               <init>
   #59 = Utf8               (Ljava/lang/Class;)V
   #60 = Utf8               Code
   #61 = Utf8               LineNumberTable
   #62 = Utf8               LocalVariableTable
   #63 = Utf8               this
   #64 = Utf8               rawType
   #65 = Utf8               Ljava/lang/Class;
   #66 = Utf8               LocalVariableTypeTable
   #67 = Utf8               Ljava/lang/Class<+Ljava/lang/Number;>;
   #68 = Utf8               StackMapTable
   #69 = Class              #164          // com/fasterxml/jackson/databind/ser/std/NumberSerializer
   #70 = Class              #171          // java/lang/Class
   #71 = Utf8               Signature
   #72 = Utf8               (Ljava/lang/Class<+Ljava/lang/Number;>;)V
   #73 = Utf8               createContextual
   #74 = Utf8               (Lcom/fasterxml/jackson/databind/SerializerProvider;Lcom/fasterxml/jackson/databind/BeanProperty;)Lcom/fasterxml/jackson/databind/JsonSerializer;
   #75 = Utf8               prov
   #76 = Utf8               Lcom/fasterxml/jackson/databind/SerializerProvider;
   #77 = Utf8               property
   #78 = Utf8               Lcom/fasterxml/jackson/databind/BeanProperty;
   #79 = Utf8               format
   #80 = Class              #173          // com/fasterxml/jackson/annotation/JsonFormat$Value
   #81 = Utf8               Value
   #82 = Utf8               Lcom/fasterxml/jackson/annotation/JsonFormat$Value;
   #83 = Class              #173          // com/fasterxml/jackson/annotation/JsonFormat$Value
   #84 = Utf8               Exceptions
   #85 = Class              #174          // com/fasterxml/jackson/databind/JsonMappingException
   #86 = Utf8               (Lcom/fasterxml/jackson/databind/SerializerProvider;Lcom/fasterxml/jackson/databind/BeanProperty;)Lcom/fasterxml/jackson/databind/JsonSerializer<*>;
   #87 = Utf8               serialize
   #88 = Utf8               (Ljava/lang/Number;Lcom/fasterxml/jackson/core/JsonGenerator;Lcom/fasterxml/jackson/databind/SerializerProvider;)V
   #89 = Utf8               value
   #90 = Utf8               Ljava/lang/Number;
   #91 = Utf8               g
   #92 = Utf8               Lcom/fasterxml/jackson/core/JsonGenerator;
   #93 = Utf8               provider
   #94 = Class              #175          // java/io/IOException
   #95 = Utf8               getSchema
   #96 = Utf8               (Lcom/fasterxml/jackson/databind/SerializerProvider;Ljava/lang/reflect/Type;)Lcom/fasterxml/jackson/databind/JsonNode;
   #97 = Utf8               typeHint
   #98 = Utf8               Ljava/lang/reflect/Type;
   #99 = Class              #176          // com/fasterxml/jackson/databind/SerializerProvider
  #100 = Class              #177          // java/lang/reflect/Type
  #101 = Class              #178          // java/lang/String
  #102 = Utf8               acceptJsonFormatVisitor
  #103 = Utf8               (Lcom/fasterxml/jackson/databind/jsonFormatVisitors/JsonFormatVisitorWrapper;Lcom/fasterxml/jackson/databind/JavaType;)V
  #104 = Utf8               visitor
  #105 = Utf8               Lcom/fasterxml/jackson/databind/jsonFormatVisitors/JsonFormatVisitorWrapper;
  #106 = Utf8               Lcom/fasterxml/jackson/databind/JavaType;
  #107 = Utf8               bigDecimalAsStringSerializer
  #108 = Utf8               ()Lcom/fasterxml/jackson/databind/JsonSerializer;
  #109 = Utf8               ()Lcom/fasterxml/jackson/databind/JsonSerializer<*>;
  #110 = Utf8               (Ljava/lang/Object;Lcom/fasterxml/jackson/core/JsonGenerator;Lcom/fasterxml/jackson/databind/SerializerProvider;)V
  #111 = Utf8               <clinit>
  #112 = Utf8               ()V
  #113 = Utf8               Lcom/fasterxml/jackson/databind/ser/std/StdScalarSerializer<Ljava/lang/Number;>;Lcom/fasterxml/jackson/databind/ser/ContextualSerializer;
  #114 = Utf8               SourceFile
  #115 = Utf8               NumberSerializer.java
  #116 = Utf8               RuntimeVisibleAnnotations
  #117 = Utf8               Lcom/fasterxml/jackson/databind/annotation/JacksonStdImpl;
  #118 = NameAndType        #58:#179      // "<init>":(Ljava/lang/Class;Z)V
  #119 = Utf8               java/math/BigInteger
  #120 = NameAndType        #56:#57       // _isInt:Z
  #121 = NameAndType        #180:#181     // handledType:()Ljava/lang/Class;
  #122 = NameAndType        #182:#183     // findFormatOverrides:(Lcom/fasterxml/jackson/databind/SerializerProvider;Lcom/fasterxml/jackson/databind/BeanProperty;Ljava/lang/Class;)Lcom/fasterxml/jackson/annotation/JsonFormat$Value;
  #123 = NameAndType        #184:#185     // $SwitchMap$com$fasterxml$jackson$annotation$JsonFormat$Shape:[I
  #124 = NameAndType        #186:#188     // getShape:()Lcom/fasterxml/jackson/annotation/JsonFormat$Shape;
  #125 = Class              #189          // com/fasterxml/jackson/annotation/JsonFormat$Shape
  #126 = NameAndType        #190:#191     // ordinal:()I
  #127 = Utf8               java/math/BigDecimal
  #128 = NameAndType        #107:#108     // bigDecimalAsStringSerializer:()Lcom/fasterxml/jackson/databind/JsonSerializer;
  #129 = Class              #192          // com/fasterxml/jackson/databind/ser/std/ToStringSerializer
  #130 = NameAndType        #50:#193      // instance:Lcom/fasterxml/jackson/databind/ser/std/ToStringSerializer;
  #131 = Class              #194          // com/fasterxml/jackson/core/JsonGenerator
  #132 = NameAndType        #195:#196     // writeNumber:(Ljava/math/BigDecimal;)V
  #133 = NameAndType        #195:#197     // writeNumber:(Ljava/math/BigInteger;)V
  #134 = Utf8               java/lang/Long
  #135 = NameAndType        #198:#199     // longValue:()J
  #136 = NameAndType        #195:#200     // writeNumber:(J)V
  #137 = Utf8               java/lang/Double
  #138 = NameAndType        #201:#202     // doubleValue:()D
  #139 = NameAndType        #195:#203     // writeNumber:(D)V
  #140 = Utf8               java/lang/Float
  #141 = NameAndType        #204:#205     // floatValue:()F
  #142 = NameAndType        #195:#206     // writeNumber:(F)V
  #143 = Utf8               java/lang/Integer
  #144 = Utf8               java/lang/Byte
  #145 = Utf8               java/lang/Short
  #146 = NameAndType        #207:#191     // intValue:()I
  #147 = NameAndType        #195:#208     // writeNumber:(I)V
  #148 = Class              #209          // java/lang/Object
  #149 = NameAndType        #210:#211     // toString:()Ljava/lang/String;
  #150 = NameAndType        #195:#212     // writeNumber:(Ljava/lang/String;)V
  #151 = Utf8               integer
  #152 = Utf8               number
  #153 = NameAndType        #213:#214     // createSchemaNode:(Ljava/lang/String;Z)Lcom/fasterxml/jackson/databind/node/ObjectNode;
  #154 = Class              #216          // com/fasterxml/jackson/core/JsonParser$NumberType
  #155 = NameAndType        #218:#219     // BIG_INTEGER:Lcom/fasterxml/jackson/core/JsonParser$NumberType;
  #156 = NameAndType        #220:#221     // visitIntFormat:(Lcom/fasterxml/jackson/databind/jsonFormatVisitors/JsonFormatVisitorWrapper;Lcom/fasterxml/jackson/databind/JavaType;Lcom/fasterxml/jackson/core/JsonParser$NumberType;)V
  #157 = NameAndType        #222:#219     // BIG_DECIMAL:Lcom/fasterxml/jackson/core/JsonParser$NumberType;
  #158 = NameAndType        #223:#221     // visitFloatFormat:(Lcom/fasterxml/jackson/databind/jsonFormatVisitors/JsonFormatVisitorWrapper;Lcom/fasterxml/jackson/databind/JavaType;Lcom/fasterxml/jackson/core/JsonParser$NumberType;)V
  #159 = Class              #224          // com/fasterxml/jackson/databind/jsonFormatVisitors/JsonFormatVisitorWrapper
  #160 = NameAndType        #225:#226     // expectNumberFormat:(Lcom/fasterxml/jackson/databind/JavaType;)Lcom/fasterxml/jackson/databind/jsonFormatVisitors/JsonNumberFormatVisitor;
  #161 = NameAndType        #227:#228     // BD_INSTANCE:Lcom/fasterxml/jackson/databind/ser/std/NumberSerializer$BigDecimalAsStringSerializer;
  #162 = Utf8               java/lang/Number
  #163 = NameAndType        #87:#88       // serialize:(Ljava/lang/Number;Lcom/fasterxml/jackson/core/JsonGenerator;Lcom/fasterxml/jackson/databind/SerializerProvider;)V
  #164 = Utf8               com/fasterxml/jackson/databind/ser/std/NumberSerializer
  #165 = NameAndType        #58:#59       // "<init>":(Ljava/lang/Class;)V
  #166 = NameAndType        #50:#51       // instance:Lcom/fasterxml/jackson/databind/ser/std/NumberSerializer;
  #167 = Utf8               com/fasterxml/jackson/databind/ser/std/StdScalarSerializer
  #168 = Utf8               com/fasterxml/jackson/databind/ser/ContextualSerializer
  #169 = Utf8               com/fasterxml/jackson/databind/ser/std/NumberSerializer$1
  #170 = Utf8               com/fasterxml/jackson/databind/ser/std/NumberSerializer$BigDecimalAsStringSerializer
  #171 = Utf8               java/lang/Class
  #172 = Class              #229          // com/fasterxml/jackson/annotation/JsonFormat
  #173 = Utf8               com/fasterxml/jackson/annotation/JsonFormat$Value
  #174 = Utf8               com/fasterxml/jackson/databind/JsonMappingException
  #175 = Utf8               java/io/IOException
  #176 = Utf8               com/fasterxml/jackson/databind/SerializerProvider
  #177 = Utf8               java/lang/reflect/Type
  #178 = Utf8               java/lang/String
  #179 = Utf8               (Ljava/lang/Class;Z)V
  #180 = Utf8               handledType
  #181 = Utf8               ()Ljava/lang/Class;
  #182 = Utf8               findFormatOverrides
  #183 = Utf8               (Lcom/fasterxml/jackson/databind/SerializerProvider;Lcom/fasterxml/jackson/databind/BeanProperty;Ljava/lang/Class;)Lcom/fasterxml/jackson/annotation/JsonFormat$Value;
  #184 = Utf8               $SwitchMap$com$fasterxml$jackson$annotation$JsonFormat$Shape
  #185 = Utf8               [I
  #186 = Utf8               getShape
  #187 = Utf8               Shape
  #188 = Utf8               ()Lcom/fasterxml/jackson/annotation/JsonFormat$Shape;
  #189 = Utf8               com/fasterxml/jackson/annotation/JsonFormat$Shape
  #190 = Utf8               ordinal
  #191 = Utf8               ()I
  #192 = Utf8               com/fasterxml/jackson/databind/ser/std/ToStringSerializer
  #193 = Utf8               Lcom/fasterxml/jackson/databind/ser/std/ToStringSerializer;
  #194 = Utf8               com/fasterxml/jackson/core/JsonGenerator
  #195 = Utf8               writeNumber
  #196 = Utf8               (Ljava/math/BigDecimal;)V
  #197 = Utf8               (Ljava/math/BigInteger;)V
  #198 = Utf8               longValue
  #199 = Utf8               ()J
  #200 = Utf8               (J)V
  #201 = Utf8               doubleValue
  #202 = Utf8               ()D
  #203 = Utf8               (D)V
  #204 = Utf8               floatValue
  #205 = Utf8               ()F
  #206 = Utf8               (F)V
  #207 = Utf8               intValue
  #208 = Utf8               (I)V
  #209 = Utf8               java/lang/Object
  #210 = Utf8               toString
  #211 = Utf8               ()Ljava/lang/String;
  #212 = Utf8               (Ljava/lang/String;)V
  #213 = Utf8               createSchemaNode
  #214 = Utf8               (Ljava/lang/String;Z)Lcom/fasterxml/jackson/databind/node/ObjectNode;
  #215 = Class              #230          // com/fasterxml/jackson/core/JsonParser
  #216 = Utf8               com/fasterxml/jackson/core/JsonParser$NumberType
  #217 = Utf8               NumberType
  #218 = Utf8               BIG_INTEGER
  #219 = Utf8               Lcom/fasterxml/jackson/core/JsonParser$NumberType;
  #220 = Utf8               visitIntFormat
  #221 = Utf8               (Lcom/fasterxml/jackson/databind/jsonFormatVisitors/JsonFormatVisitorWrapper;Lcom/fasterxml/jackson/databind/JavaType;Lcom/fasterxml/jackson/core/JsonParser$NumberType;)V
  #222 = Utf8               BIG_DECIMAL
  #223 = Utf8               visitFloatFormat
  #224 = Utf8               com/fasterxml/jackson/databind/jsonFormatVisitors/JsonFormatVisitorWrapper
  #225 = Utf8               expectNumberFormat
  #226 = Utf8               (Lcom/fasterxml/jackson/databind/JavaType;)Lcom/fasterxml/jackson/databind/jsonFormatVisitors/JsonNumberFormatVisitor;
  #227 = Utf8               BD_INSTANCE
  #228 = Utf8               Lcom/fasterxml/jackson/databind/ser/std/NumberSerializer$BigDecimalAsStringSerializer;
  #229 = Utf8               com/fasterxml/jackson/annotation/JsonFormat
  #230 = Utf8               com/fasterxml/jackson/core/JsonParser
{
  public static final com.fasterxml.jackson.databind.ser.std.NumberSerializer instance;
    descriptor: Lcom/fasterxml/jackson/databind/ser/std/NumberSerializer;
    flags: (0x0019) ACC_PUBLIC, ACC_STATIC, ACC_FINAL

  protected static final int MAX_BIG_DECIMAL_SCALE;
    descriptor: I
    flags: (0x001c) ACC_PROTECTED, ACC_STATIC, ACC_FINAL
    ConstantValue: int 9999

  protected final boolean _isInt;
    descriptor: Z
    flags: (0x0014) ACC_PROTECTED, ACC_FINAL

  public com.fasterxml.jackson.databind.ser.std.NumberSerializer(java.lang.Class<? extends java.lang.Number>);
    descriptor: (Ljava/lang/Class;)V
    flags: (0x0001) ACC_PUBLIC
    Code:
      stack=3, locals=2, args_size=2
         0: aload_0
         1: aload_1
         2: iconst_0
         3: invokespecial #1                  // Method com/fasterxml/jackson/databind/ser/std/StdScalarSerializer."<init>":(Ljava/lang/Class;Z)V
         6: aload_0
         7: aload_1
         8: ldc           #2                  // class java/math/BigInteger
        10: if_acmpne     17
        13: iconst_1
        14: goto          18
        17: iconst_0
        18: putfield      #3                  // Field _isInt:Z
        21: return
      LineNumberTable:
        line 45: 0
        line 47: 6
        line 48: 21
      LocalVariableTable:
        Start  Length  Slot  Name   Signature
            0      22     0  this   Lcom/fasterxml/jackson/databind/ser/std/NumberSerializer;
            0      22     1 rawType   Ljava/lang/Class;
      LocalVariableTypeTable:
        Start  Length  Slot  Name   Signature
            0      22     1 rawType   Ljava/lang/Class<+Ljava/lang/Number;>;
      StackMapTable: number_of_entries = 2
        frame_type = 255 /* full_frame */
          offset_delta = 17
          locals = [ class com/fasterxml/jackson/databind/ser/std/NumberSerializer, class java/lang/Class ]
          stack = [ class com/fasterxml/jackson/databind/ser/std/NumberSerializer ]
        frame_type = 255 /* full_frame */
          offset_delta = 0
          locals = [ class com/fasterxml/jackson/databind/ser/std/NumberSerializer, class java/lang/Class ]
          stack = [ class com/fasterxml/jackson/databind/ser/std/NumberSerializer, int ]
    Signature: #72                          // (Ljava/lang/Class<+Ljava/lang/Number;>;)V

  public com.fasterxml.jackson.databind.JsonSerializer<?> createContextual(com.fasterxml.jackson.databind.SerializerProvider, com.fasterxml.jackson.databind.BeanProperty) throws com.fasterxml.jackson.databind.JsonMappingException;
    descriptor: (Lcom/fasterxml/jackson/databind/SerializerProvider;Lcom/fasterxml/jackson/databind/BeanProperty;)Lcom/fasterxml/jackson/databind/JsonSerializer;
    flags: (0x0001) ACC_PUBLIC
    Code:
      stack=4, locals=4, args_size=3
         0: aload_0
         1: aload_1
         2: aload_2
         3: aload_0
         4: invokevirtual #4                  // Method handledType:()Ljava/lang/Class;
         7: invokevirtual #5                  // Method findFormatOverrides:(Lcom/fasterxml/jackson/databind/SerializerProvider;Lcom/fasterxml/jackson/databind/BeanProperty;Ljava/lang/Class;)Lcom/fasterxml/jackson/annotation/JsonFormat$Value;
        10: astore_3
        11: aload_3
        12: ifnull        61
        15: getstatic     #6                  // Field com/fasterxml/jackson/databind/ser/std/NumberSerializer$1.$SwitchMap$com$fasterxml$jackson$annotation$JsonFormat$Shape:[I
        18: aload_3
        19: invokevirtual #7                  // Method com/fasterxml/jackson/annotation/JsonFormat$Value.getShape:()Lcom/fasterxml/jackson/annotation/JsonFormat$Shape;
        22: invokevirtual #8                  // Method com/fasterxml/jackson/annotation/JsonFormat$Shape.ordinal:()I
        25: iaload
        26: lookupswitch  { // 1
                       1: 44
                 default: 61
            }
        44: aload_0
        45: invokevirtual #4                  // Method handledType:()Ljava/lang/Class;
        48: ldc           #9                  // class java/math/BigDecimal
        50: if_acmpne     57
        53: invokestatic  #10                 // Method bigDecimalAsStringSerializer:()Lcom/fasterxml/jackson/databind/JsonSerializer;
        56: areturn
        57: getstatic     #11                 // Field com/fasterxml/jackson/databind/ser/std/ToStringSerializer.instance:Lcom/fasterxml/jackson/databind/ser/std/ToStringSerializer;
        60: areturn
        61: aload_0
        62: areturn
      LineNumberTable:
        line 54: 0
        line 55: 11
        line 56: 15
        line 59: 44
        line 60: 53
        line 62: 57
        line 66: 61
      LocalVariableTable:
        Start  Length  Slot  Name   Signature
            0      63     0  this   Lcom/fasterxml/jackson/databind/ser/std/NumberSerializer;
            0      63     1  prov   Lcom/fasterxml/jackson/databind/SerializerProvider;
            0      63     2 property   Lcom/fasterxml/jackson/databind/BeanProperty;
           11      52     3 format   Lcom/fasterxml/jackson/annotation/JsonFormat$Value;
      StackMapTable: number_of_entries = 3
        frame_type = 252 /* append */
          offset_delta = 44
          locals = [ class com/fasterxml/jackson/annotation/JsonFormat$Value ]
        frame_type = 12 /* same */
        frame_type = 3 /* same */
    Exceptions:
      throws com.fasterxml.jackson.databind.JsonMappingException
    Signature: #86                          // (Lcom/fasterxml/jackson/databind/SerializerProvider;Lcom/fasterxml/jackson/databind/BeanProperty;)Lcom/fasterxml/jackson/databind/JsonSerializer<*>;

  public void serialize(java.lang.Number, com.fasterxml.jackson.core.JsonGenerator, com.fasterxml.jackson.databind.SerializerProvider) throws java.io.IOException;
    descriptor: (Ljava/lang/Number;Lcom/fasterxml/jackson/core/JsonGenerator;Lcom/fasterxml/jackson/databind/SerializerProvider;)V
    flags: (0x0001) ACC_PUBLIC
    Code:
      stack=3, locals=4, args_size=4
         0: aload_1
         1: instanceof    #9                  // class java/math/BigDecimal
         4: ifeq          18
         7: aload_2
         8: aload_1
         9: checkcast     #9                  // class java/math/BigDecimal
        12: invokevirtual #12                 // Method com/fasterxml/jackson/core/JsonGenerator.writeNumber:(Ljava/math/BigDecimal;)V
        15: goto          130
        18: aload_1
        19: instanceof    #2                  // class java/math/BigInteger
        22: ifeq          36
        25: aload_2
        26: aload_1
        27: checkcast     #2                  // class java/math/BigInteger
        30: invokevirtual #13                 // Method com/fasterxml/jackson/core/JsonGenerator.writeNumber:(Ljava/math/BigInteger;)V
        33: goto          130
        36: aload_1
        37: instanceof    #14                 // class java/lang/Long
        40: ifeq          54
        43: aload_2
        44: aload_1
        45: invokevirtual #15                 // Method java/lang/Number.longValue:()J
        48: invokevirtual #16                 // Method com/fasterxml/jackson/core/JsonGenerator.writeNumber:(J)V
        51: goto          130
        54: aload_1
        55: instanceof    #17                 // class java/lang/Double
        58: ifeq          72
        61: aload_2
        62: aload_1
        63: invokevirtual #18                 // Method java/lang/Number.doubleValue:()D
        66: invokevirtual #19                 // Method com/fasterxml/jackson/core/JsonGenerator.writeNumber:(D)V
        69: goto          130
        72: aload_1
        73: instanceof    #20                 // class java/lang/Float
        76: ifeq          90
        79: aload_2
        80: aload_1
        81: invokevirtual #21                 // Method java/lang/Number.floatValue:()F
        84: invokevirtual #22                 // Method com/fasterxml/jackson/core/JsonGenerator.writeNumber:(F)V
        87: goto          130
        90: aload_1
        91: instanceof    #23                 // class java/lang/Integer
        94: ifne          111
        97: aload_1
        98: instanceof    #24                 // class java/lang/Byte
       101: ifne          111
       104: aload_1
       105: instanceof    #25                 // class java/lang/Short
       108: ifeq          122
       111: aload_2
       112: aload_1
       113: invokevirtual #26                 // Method java/lang/Number.intValue:()I
       116: invokevirtual #27                 // Method com/fasterxml/jackson/core/JsonGenerator.writeNumber:(I)V
       119: goto          130
       122: aload_2
       123: aload_1
       124: invokevirtual #28                 // Method java/lang/Object.toString:()Ljava/lang/String;
       127: invokevirtual #29                 // Method com/fasterxml/jackson/core/JsonGenerator.writeNumber:(Ljava/lang/String;)V
       130: return
      LineNumberTable:
        line 73: 0
        line 74: 7
        line 75: 18
        line 76: 25
        line 80: 36
        line 81: 43
        line 82: 54
        line 83: 61
        line 84: 72
        line 85: 79
        line 86: 90
        line 87: 111
        line 90: 122
        line 92: 130
      LocalVariableTable:
        Start  Length  Slot  Name   Signature
            0     131     0  this   Lcom/fasterxml/jackson/databind/ser/std/NumberSerializer;
            0     131     1 value   Ljava/lang/Number;
            0     131     2     g   Lcom/fasterxml/jackson/core/JsonGenerator;
            0     131     3 provider   Lcom/fasterxml/jackson/databind/SerializerProvider;
      StackMapTable: number_of_entries = 8
        frame_type = 18 /* same */
        frame_type = 17 /* same */
        frame_type = 17 /* same */
        frame_type = 17 /* same */
        frame_type = 17 /* same */
        frame_type = 20 /* same */
        frame_type = 10 /* same */
        frame_type = 7 /* same */
    Exceptions:
      throws java.io.IOException

  public com.fasterxml.jackson.databind.JsonNode getSchema(com.fasterxml.jackson.databind.SerializerProvider, java.lang.reflect.Type);
    descriptor: (Lcom/fasterxml/jackson/databind/SerializerProvider;Ljava/lang/reflect/Type;)Lcom/fasterxml/jackson/databind/JsonNode;
    flags: (0x0001) ACC_PUBLIC
    Code:
      stack=3, locals=3, args_size=3
         0: aload_0
         1: aload_0
         2: getfield      #3                  // Field _isInt:Z
         5: ifeq          13
         8: ldc           #30                 // String integer
        10: goto          15
        13: ldc           #31                 // String number
        15: iconst_1
        16: invokevirtual #32                 // Method createSchemaNode:(Ljava/lang/String;Z)Lcom/fasterxml/jackson/databind/node/ObjectNode;
        19: areturn
      LineNumberTable:
        line 96: 0
      LocalVariableTable:
        Start  Length  Slot  Name   Signature
            0      20     0  this   Lcom/fasterxml/jackson/databind/ser/std/NumberSerializer;
            0      20     1 provider   Lcom/fasterxml/jackson/databind/SerializerProvider;
            0      20     2 typeHint   Ljava/lang/reflect/Type;
      StackMapTable: number_of_entries = 2
        frame_type = 77 /* same_locals_1_stack_item */
          stack = [ class com/fasterxml/jackson/databind/ser/std/NumberSerializer ]
        frame_type = 255 /* full_frame */
          offset_delta = 1
          locals = [ class com/fasterxml/jackson/databind/ser/std/NumberSerializer, class com/fasterxml/jackson/databind/SerializerProvider, class java/lang/reflect/Type ]
          stack = [ class com/fasterxml/jackson/databind/ser/std/NumberSerializer, class java/lang/String ]

  public void acceptJsonFormatVisitor(com.fasterxml.jackson.databind.jsonFormatVisitors.JsonFormatVisitorWrapper, com.fasterxml.jackson.databind.JavaType) throws com.fasterxml.jackson.databind.JsonMappingException;
    descriptor: (Lcom/fasterxml/jackson/databind/jsonFormatVisitors/JsonFormatVisitorWrapper;Lcom/fasterxml/jackson/databind/JavaType;)V
    flags: (0x0001) ACC_PUBLIC
    Code:
      stack=4, locals=3, args_size=3
         0: aload_0
         1: getfield      #3                  // Field _isInt:Z
         4: ifeq          19
         7: aload_0
         8: aload_1
         9: aload_2
        10: getstatic     #33                 // Field com/fasterxml/jackson/core/JsonParser$NumberType.BIG_INTEGER:Lcom/fasterxml/jackson/core/JsonParser$NumberType;
        13: invokevirtual #34                 // Method visitIntFormat:(Lcom/fasterxml/jackson/databind/jsonFormatVisitors/JsonFormatVisitorWrapper;Lcom/fasterxml/jackson/databind/JavaType;Lcom/fasterxml/jackson/core/JsonParser$NumberType;)V
        16: goto          48
        19: aload_0
        20: invokevirtual #4                  // Method handledType:()Ljava/lang/Class;
        23: ldc           #9                  // class java/math/BigDecimal
        25: if_acmpne     40
        28: aload_0
        29: aload_1
        30: aload_2
        31: getstatic     #35                 // Field com/fasterxml/jackson/core/JsonParser$NumberType.BIG_DECIMAL:Lcom/fasterxml/jackson/core/JsonParser$NumberType;
        34: invokevirtual #36                 // Method visitFloatFormat:(Lcom/fasterxml/jackson/databind/jsonFormatVisitors/JsonFormatVisitorWrapper;Lcom/fasterxml/jackson/databind/JavaType;Lcom/fasterxml/jackson/core/JsonParser$NumberType;)V
        37: goto          48
        40: aload_1
        41: aload_2
        42: invokeinterface #37,  2           // InterfaceMethod com/fasterxml/jackson/databind/jsonFormatVisitors/JsonFormatVisitorWrapper.expectNumberFormat:(Lcom/fasterxml/jackson/databind/JavaType;)Lcom/fasterxml/jackson/databind/jsonFormatVisitors/JsonNumberFormatVisitor;
        47: pop
        48: return
      LineNumberTable:
        line 102: 0
        line 103: 7
        line 105: 19
        line 106: 28
        line 109: 40
        line 112: 48
      LocalVariableTable:
        Start  Length  Slot  Name   Signature
            0      49     0  this   Lcom/fasterxml/jackson/databind/ser/std/NumberSerializer;
            0      49     1 visitor   Lcom/fasterxml/jackson/databind/jsonFormatVisitors/JsonFormatVisitorWrapper;
            0      49     2 typeHint   Lcom/fasterxml/jackson/databind/JavaType;
      StackMapTable: number_of_entries = 3
        frame_type = 19 /* same */
        frame_type = 20 /* same */
        frame_type = 7 /* same */
    Exceptions:
      throws com.fasterxml.jackson.databind.JsonMappingException

  public static com.fasterxml.jackson.databind.JsonSerializer<?> bigDecimalAsStringSerializer();
    descriptor: ()Lcom/fasterxml/jackson/databind/JsonSerializer;
    flags: (0x0009) ACC_PUBLIC, ACC_STATIC
    Code:
      stack=1, locals=0, args_size=0
         0: getstatic     #38                 // Field com/fasterxml/jackson/databind/ser/std/NumberSerializer$BigDecimalAsStringSerializer.BD_INSTANCE:Lcom/fasterxml/jackson/databind/ser/std/NumberSerializer$BigDecimalAsStringSerializer;
         3: areturn
      LineNumberTable:
        line 118: 0
    Signature: #109                         // ()Lcom/fasterxml/jackson/databind/JsonSerializer<*>;

  public void serialize(java.lang.Object, com.fasterxml.jackson.core.JsonGenerator, com.fasterxml.jackson.databind.SerializerProvider) throws java.io.IOException;
    descriptor: (Ljava/lang/Object;Lcom/fasterxml/jackson/core/JsonGenerator;Lcom/fasterxml/jackson/databind/SerializerProvider;)V
    flags: (0x1041) ACC_PUBLIC, ACC_BRIDGE, ACC_SYNTHETIC
    Code:
      stack=4, locals=4, args_size=4
         0: aload_0
         1: aload_1
         2: checkcast     #39                 // class java/lang/Number
         5: aload_2
         6: aload_3
         7: invokevirtual #40                 // Method serialize:(Ljava/lang/Number;Lcom/fasterxml/jackson/core/JsonGenerator;Lcom/fasterxml/jackson/databind/SerializerProvider;)V
        10: return
      LineNumberTable:
        line 23: 0
      LocalVariableTable:
        Start  Length  Slot  Name   Signature
            0      11     0  this   Lcom/fasterxml/jackson/databind/ser/std/NumberSerializer;
    Exceptions:
      throws java.io.IOException

  static {};
    descriptor: ()V
    flags: (0x0008) ACC_STATIC
    Code:
      stack=3, locals=0, args_size=0
         0: new           #41                 // class com/fasterxml/jackson/databind/ser/std/NumberSerializer
         3: dup
         4: ldc           #39                 // class java/lang/Number
         6: invokespecial #42                 // Method "<init>":(Ljava/lang/Class;)V
         9: putstatic     #43                 // Field instance:Lcom/fasterxml/jackson/databind/ser/std/NumberSerializer;
        12: return
      LineNumberTable:
        line 32: 0
}
Signature: #113                         // Lcom/fasterxml/jackson/databind/ser/std/StdScalarSerializer<Ljava/lang/Number;>;Lcom/fasterxml/jackson/databind/ser/ContextualSerializer;
SourceFile: "NumberSerializer.java"
RuntimeVisibleAnnotations:
  0: #117()
    com.fasterxml.jackson.databind.annotation.JacksonStdImpl
InnerClasses:
  static #46;                             // class com/fasterxml/jackson/databind/ser/std/NumberSerializer$1
  static final #49= #48 of #41;           // BigDecimalAsStringSerializer=class com/fasterxml/jackson/databind/ser/std/NumberSerializer$BigDecimalAsStringSerializer of class com/fasterxml/jackson/databind/ser/std/NumberSerializer
  public static #81= #80 of #172;         // Value=class com/fasterxml/jackson/annotation/JsonFormat$Value of class com/fasterxml/jackson/annotation/JsonFormat
  public static final #187= #125 of #172; // Shape=class com/fasterxml/jackson/annotation/JsonFormat$Shape of class com/fasterxml/jackson/annotation/JsonFormat
  public static final #217= #154 of #215; // NumberType=class com/fasterxml/jackson/core/JsonParser$NumberType of class com/fasterxml/jackson/core/JsonParser
