Classfile /Users/mw/Projects/slang-braindump/.jar/jar8/assemble/slang-braindump/assemble/content/com/fasterxml/jackson/databind/ser/std/StdKeySerializers$EnumKeySerializer.class
  Last modified May 29, 2022; size 2888 bytes
  SHA-256 checksum eacf1f508dbea38f54b168e2dd417b20a11bd1c98f2250ef3840a4e39ef73487
  Compiled from "StdKeySerializers.java"
public class com.fasterxml.jackson.databind.ser.std.StdKeySerializers$EnumKeySerializer extends com.fasterxml.jackson.databind.ser.std.StdSerializer<java.lang.Object>
  minor version: 0
  major version: 52
  flags: (0x0021) ACC_PUBLIC, ACC_SUPER
  this_class: #3                          // com/fasterxml/jackson/databind/ser/std/StdKeySerializers$EnumKeySerializer
  super_class: #15                        // com/fasterxml/jackson/databind/ser/std/StdSerializer
  interfaces: 0, fields: 1, methods: 3, attributes: 3
Constant pool:
    #1 = Methodref          #15.#56       // com/fasterxml/jackson/databind/ser/std/StdSerializer."<init>":(Ljava/lang/Class;Z)V
    #2 = Fieldref           #3.#57        // com/fasterxml/jackson/databind/ser/std/StdKeySerializers$EnumKeySerializer._values:Lcom/fasterxml/jackson/databind/util/EnumValues;
    #3 = Class              #59           // com/fasterxml/jackson/databind/ser/std/StdKeySerializers$EnumKeySerializer
    #4 = Methodref          #3.#60        // com/fasterxml/jackson/databind/ser/std/StdKeySerializers$EnumKeySerializer."<init>":(Ljava/lang/Class;Lcom/fasterxml/jackson/databind/util/EnumValues;)V
    #5 = Fieldref           #61.#62       // com/fasterxml/jackson/databind/SerializationFeature.WRITE_ENUMS_USING_TO_STRING:Lcom/fasterxml/jackson/databind/SerializationFeature;
    #6 = Methodref          #63.#64       // com/fasterxml/jackson/databind/SerializerProvider.isEnabled:(Lcom/fasterxml/jackson/databind/SerializationFeature;)Z
    #7 = Methodref          #65.#66       // java/lang/Object.toString:()Ljava/lang/String;
    #8 = Methodref          #67.#68       // com/fasterxml/jackson/core/JsonGenerator.writeFieldName:(Ljava/lang/String;)V
    #9 = Class              #69           // java/lang/Enum
   #10 = Fieldref           #61.#70       // com/fasterxml/jackson/databind/SerializationFeature.WRITE_ENUM_KEYS_USING_INDEX:Lcom/fasterxml/jackson/databind/SerializationFeature;
   #11 = Methodref          #9.#71        // java/lang/Enum.ordinal:()I
   #12 = Methodref          #72.#73       // java/lang/String.valueOf:(I)Ljava/lang/String;
   #13 = Methodref          #74.#75       // com/fasterxml/jackson/databind/util/EnumValues.serializedValueFor:(Ljava/lang/Enum;)Lcom/fasterxml/jackson/core/SerializableString;
   #14 = Methodref          #67.#76       // com/fasterxml/jackson/core/JsonGenerator.writeFieldName:(Lcom/fasterxml/jackson/core/SerializableString;)V
   #15 = Class              #77           // com/fasterxml/jackson/databind/ser/std/StdSerializer
   #16 = Utf8               _values
   #17 = Utf8               Lcom/fasterxml/jackson/databind/util/EnumValues;
   #18 = Utf8               <init>
   #19 = Utf8               (Ljava/lang/Class;Lcom/fasterxml/jackson/databind/util/EnumValues;)V
   #20 = Utf8               Code
   #21 = Utf8               LineNumberTable
   #22 = Utf8               LocalVariableTable
   #23 = Utf8               this
   #24 = Utf8               EnumKeySerializer
   #25 = Utf8               InnerClasses
   #26 = Utf8               Lcom/fasterxml/jackson/databind/ser/std/StdKeySerializers$EnumKeySerializer;
   #27 = Utf8               enumType
   #28 = Utf8               Ljava/lang/Class;
   #29 = Utf8               values
   #30 = Utf8               LocalVariableTypeTable
   #31 = Utf8               Ljava/lang/Class<*>;
   #32 = Utf8               Signature
   #33 = Utf8               (Ljava/lang/Class<*>;Lcom/fasterxml/jackson/databind/util/EnumValues;)V
   #34 = Utf8               construct
   #35 = Utf8               (Ljava/lang/Class;Lcom/fasterxml/jackson/databind/util/EnumValues;)Lcom/fasterxml/jackson/databind/ser/std/StdKeySerializers$EnumKeySerializer;
   #36 = Utf8               enumValues
   #37 = Utf8               (Ljava/lang/Class<*>;Lcom/fasterxml/jackson/databind/util/EnumValues;)Lcom/fasterxml/jackson/databind/ser/std/StdKeySerializers$EnumKeySerializer;
   #38 = Utf8               serialize
   #39 = Utf8               (Ljava/lang/Object;Lcom/fasterxml/jackson/core/JsonGenerator;Lcom/fasterxml/jackson/databind/SerializerProvider;)V
   #40 = Utf8               value
   #41 = Utf8               Ljava/lang/Object;
   #42 = Utf8               g
   #43 = Utf8               Lcom/fasterxml/jackson/core/JsonGenerator;
   #44 = Utf8               serializers
   #45 = Utf8               Lcom/fasterxml/jackson/databind/SerializerProvider;
   #46 = Utf8               en
   #47 = Utf8               Ljava/lang/Enum;
   #48 = Utf8               Ljava/lang/Enum<*>;
   #49 = Utf8               StackMapTable
   #50 = Class              #69           // java/lang/Enum
   #51 = Utf8               Exceptions
   #52 = Class              #78           // java/io/IOException
   #53 = Utf8               Lcom/fasterxml/jackson/databind/ser/std/StdSerializer<Ljava/lang/Object;>;
   #54 = Utf8               SourceFile
   #55 = Utf8               StdKeySerializers.java
   #56 = NameAndType        #18:#79       // "<init>":(Ljava/lang/Class;Z)V
   #57 = NameAndType        #16:#17       // _values:Lcom/fasterxml/jackson/databind/util/EnumValues;
   #58 = Class              #80           // com/fasterxml/jackson/databind/ser/std/StdKeySerializers
   #59 = Utf8               com/fasterxml/jackson/databind/ser/std/StdKeySerializers$EnumKeySerializer
   #60 = NameAndType        #18:#19       // "<init>":(Ljava/lang/Class;Lcom/fasterxml/jackson/databind/util/EnumValues;)V
   #61 = Class              #81           // com/fasterxml/jackson/databind/SerializationFeature
   #62 = NameAndType        #82:#83       // WRITE_ENUMS_USING_TO_STRING:Lcom/fasterxml/jackson/databind/SerializationFeature;
   #63 = Class              #84           // com/fasterxml/jackson/databind/SerializerProvider
   #64 = NameAndType        #85:#86       // isEnabled:(Lcom/fasterxml/jackson/databind/SerializationFeature;)Z
   #65 = Class              #87           // java/lang/Object
   #66 = NameAndType        #88:#89       // toString:()Ljava/lang/String;
   #67 = Class              #90           // com/fasterxml/jackson/core/JsonGenerator
   #68 = NameAndType        #91:#92       // writeFieldName:(Ljava/lang/String;)V
   #69 = Utf8               java/lang/Enum
   #70 = NameAndType        #93:#83       // WRITE_ENUM_KEYS_USING_INDEX:Lcom/fasterxml/jackson/databind/SerializationFeature;
   #71 = NameAndType        #94:#95       // ordinal:()I
   #72 = Class              #96           // java/lang/String
   #73 = NameAndType        #97:#98       // valueOf:(I)Ljava/lang/String;
   #74 = Class              #99           // com/fasterxml/jackson/databind/util/EnumValues
   #75 = NameAndType        #100:#101     // serializedValueFor:(Ljava/lang/Enum;)Lcom/fasterxml/jackson/core/SerializableString;
   #76 = NameAndType        #91:#102      // writeFieldName:(Lcom/fasterxml/jackson/core/SerializableString;)V
   #77 = Utf8               com/fasterxml/jackson/databind/ser/std/StdSerializer
   #78 = Utf8               java/io/IOException
   #79 = Utf8               (Ljava/lang/Class;Z)V
   #80 = Utf8               com/fasterxml/jackson/databind/ser/std/StdKeySerializers
   #81 = Utf8               com/fasterxml/jackson/databind/SerializationFeature
   #82 = Utf8               WRITE_ENUMS_USING_TO_STRING
   #83 = Utf8               Lcom/fasterxml/jackson/databind/SerializationFeature;
   #84 = Utf8               com/fasterxml/jackson/databind/SerializerProvider
   #85 = Utf8               isEnabled
   #86 = Utf8               (Lcom/fasterxml/jackson/databind/SerializationFeature;)Z
   #87 = Utf8               java/lang/Object
   #88 = Utf8               toString
   #89 = Utf8               ()Ljava/lang/String;
   #90 = Utf8               com/fasterxml/jackson/core/JsonGenerator
   #91 = Utf8               writeFieldName
   #92 = Utf8               (Ljava/lang/String;)V
   #93 = Utf8               WRITE_ENUM_KEYS_USING_INDEX
   #94 = Utf8               ordinal
   #95 = Utf8               ()I
   #96 = Utf8               java/lang/String
   #97 = Utf8               valueOf
   #98 = Utf8               (I)Ljava/lang/String;
   #99 = Utf8               com/fasterxml/jackson/databind/util/EnumValues
  #100 = Utf8               serializedValueFor
  #101 = Utf8               (Ljava/lang/Enum;)Lcom/fasterxml/jackson/core/SerializableString;
  #102 = Utf8               (Lcom/fasterxml/jackson/core/SerializableString;)V
{
  protected final com.fasterxml.jackson.databind.util.EnumValues _values;
    descriptor: Lcom/fasterxml/jackson/databind/util/EnumValues;
    flags: (0x0014) ACC_PROTECTED, ACC_FINAL

  protected com.fasterxml.jackson.databind.ser.std.StdKeySerializers$EnumKeySerializer(java.lang.Class<?>, com.fasterxml.jackson.databind.util.EnumValues);
    descriptor: (Ljava/lang/Class;Lcom/fasterxml/jackson/databind/util/EnumValues;)V
    flags: (0x0004) ACC_PROTECTED
    Code:
      stack=3, locals=3, args_size=3
         0: aload_0
         1: aload_1
         2: iconst_0
         3: invokespecial #1                  // Method com/fasterxml/jackson/databind/ser/std/StdSerializer."<init>":(Ljava/lang/Class;Z)V
         6: aload_0
         7: aload_2
         8: putfield      #2                  // Field _values:Lcom/fasterxml/jackson/databind/util/EnumValues;
        11: return
      LineNumberTable:
        line 280: 0
        line 281: 6
        line 282: 11
      LocalVariableTable:
        Start  Length  Slot  Name   Signature
            0      12     0  this   Lcom/fasterxml/jackson/databind/ser/std/StdKeySerializers$EnumKeySerializer;
            0      12     1 enumType   Ljava/lang/Class;
            0      12     2 values   Lcom/fasterxml/jackson/databind/util/EnumValues;
      LocalVariableTypeTable:
        Start  Length  Slot  Name   Signature
            0      12     1 enumType   Ljava/lang/Class<*>;
    Signature: #33                          // (Ljava/lang/Class<*>;Lcom/fasterxml/jackson/databind/util/EnumValues;)V

  public static com.fasterxml.jackson.databind.ser.std.StdKeySerializers$EnumKeySerializer construct(java.lang.Class<?>, com.fasterxml.jackson.databind.util.EnumValues);
    descriptor: (Ljava/lang/Class;Lcom/fasterxml/jackson/databind/util/EnumValues;)Lcom/fasterxml/jackson/databind/ser/std/StdKeySerializers$EnumKeySerializer;
    flags: (0x0009) ACC_PUBLIC, ACC_STATIC
    Code:
      stack=4, locals=2, args_size=2
         0: new           #3                  // class com/fasterxml/jackson/databind/ser/std/StdKeySerializers$EnumKeySerializer
         3: dup
         4: aload_0
         5: aload_1
         6: invokespecial #4                  // Method "<init>":(Ljava/lang/Class;Lcom/fasterxml/jackson/databind/util/EnumValues;)V
         9: areturn
      LineNumberTable:
        line 287: 0
      LocalVariableTable:
        Start  Length  Slot  Name   Signature
            0      10     0 enumType   Ljava/lang/Class;
            0      10     1 enumValues   Lcom/fasterxml/jackson/databind/util/EnumValues;
      LocalVariableTypeTable:
        Start  Length  Slot  Name   Signature
            0      10     0 enumType   Ljava/lang/Class<*>;
    Signature: #37                          // (Ljava/lang/Class<*>;Lcom/fasterxml/jackson/databind/util/EnumValues;)Lcom/fasterxml/jackson/databind/ser/std/StdKeySerializers$EnumKeySerializer;

  public void serialize(java.lang.Object, com.fasterxml.jackson.core.JsonGenerator, com.fasterxml.jackson.databind.SerializerProvider) throws java.io.IOException;
    descriptor: (Ljava/lang/Object;Lcom/fasterxml/jackson/core/JsonGenerator;Lcom/fasterxml/jackson/databind/SerializerProvider;)V
    flags: (0x0001) ACC_PUBLIC
    Code:
      stack=3, locals=5, args_size=4
         0: aload_3
         1: getstatic     #5                  // Field com/fasterxml/jackson/databind/SerializationFeature.WRITE_ENUMS_USING_TO_STRING:Lcom/fasterxml/jackson/databind/SerializationFeature;
         4: invokevirtual #6                  // Method com/fasterxml/jackson/databind/SerializerProvider.isEnabled:(Lcom/fasterxml/jackson/databind/SerializationFeature;)Z
         7: ifeq          19
        10: aload_2
        11: aload_1
        12: invokevirtual #7                  // Method java/lang/Object.toString:()Ljava/lang/String;
        15: invokevirtual #8                  // Method com/fasterxml/jackson/core/JsonGenerator.writeFieldName:(Ljava/lang/String;)V
        18: return
        19: aload_1
        20: checkcast     #9                  // class java/lang/Enum
        23: astore        4
        25: aload_3
        26: getstatic     #10                 // Field com/fasterxml/jackson/databind/SerializationFeature.WRITE_ENUM_KEYS_USING_INDEX:Lcom/fasterxml/jackson/databind/SerializationFeature;
        29: invokevirtual #6                  // Method com/fasterxml/jackson/databind/SerializerProvider.isEnabled:(Lcom/fasterxml/jackson/databind/SerializationFeature;)Z
        32: ifeq          48
        35: aload_2
        36: aload         4
        38: invokevirtual #11                 // Method java/lang/Enum.ordinal:()I
        41: invokestatic  #12                 // Method java/lang/String.valueOf:(I)Ljava/lang/String;
        44: invokevirtual #8                  // Method com/fasterxml/jackson/core/JsonGenerator.writeFieldName:(Ljava/lang/String;)V
        47: return
        48: aload_2
        49: aload_0
        50: getfield      #2                  // Field _values:Lcom/fasterxml/jackson/databind/util/EnumValues;
        53: aload         4
        55: invokevirtual #13                 // Method com/fasterxml/jackson/databind/util/EnumValues.serializedValueFor:(Ljava/lang/Enum;)Lcom/fasterxml/jackson/core/SerializableString;
        58: invokevirtual #14                 // Method com/fasterxml/jackson/core/JsonGenerator.writeFieldName:(Lcom/fasterxml/jackson/core/SerializableString;)V
        61: return
      LineNumberTable:
        line 294: 0
        line 295: 10
        line 296: 18
        line 298: 19
        line 300: 25
        line 301: 35
        line 302: 47
        line 304: 48
        line 305: 61
      LocalVariableTable:
        Start  Length  Slot  Name   Signature
            0      62     0  this   Lcom/fasterxml/jackson/databind/ser/std/StdKeySerializers$EnumKeySerializer;
            0      62     1 value   Ljava/lang/Object;
            0      62     2     g   Lcom/fasterxml/jackson/core/JsonGenerator;
            0      62     3 serializers   Lcom/fasterxml/jackson/databind/SerializerProvider;
           25      37     4    en   Ljava/lang/Enum;
      LocalVariableTypeTable:
        Start  Length  Slot  Name   Signature
           25      37     4    en   Ljava/lang/Enum<*>;
      StackMapTable: number_of_entries = 2
        frame_type = 19 /* same */
        frame_type = 252 /* append */
          offset_delta = 28
          locals = [ class java/lang/Enum ]
    Exceptions:
      throws java.io.IOException
}
Signature: #53                          // Lcom/fasterxml/jackson/databind/ser/std/StdSerializer<Ljava/lang/Object;>;
SourceFile: "StdKeySerializers.java"
InnerClasses:
  public static #24= #3 of #58;           // EnumKeySerializer=class com/fasterxml/jackson/databind/ser/std/StdKeySerializers$EnumKeySerializer of class com/fasterxml/jackson/databind/ser/std/StdKeySerializers
