Classfile /Users/mw/Projects/slang-braindump/.jar/jar11/assemble/slang-braindump/assemble/content/coursier/core/shaded/geny/Generator$.class
  Last modified May 29, 2022; size 1983 bytes
  SHA-256 checksum 1cca241a3a91df827f6cbf058db93493df5068838798241be39f46b246b77954
  Compiled from "Generator.scala"
public final class coursier.core.shaded.geny.Generator$
  minor version: 0
  major version: 52
  flags: (0x0031) ACC_PUBLIC, ACC_FINAL, ACC_SUPER
  this_class: #2                          // coursier/core/shaded/geny/Generator$
  super_class: #4                         // java/lang/Object
  interfaces: 0, fields: 1, methods: 5, attributes: 4
Constant pool:
   #1 = Utf8               coursier/core/shaded/geny/Generator$
   #2 = Class              #1             // coursier/core/shaded/geny/Generator$
   #3 = Utf8               java/lang/Object
   #4 = Class              #3             // java/lang/Object
   #5 = Utf8               Generator.scala
   #6 = Utf8               coursier/core/shaded/geny/Generator$$anon$1
   #7 = Class              #6             // coursier/core/shaded/geny/Generator$$anon$1
   #8 = Utf8               coursier/core/shaded/geny/Generator$SelfClosing
   #9 = Class              #8             // coursier/core/shaded/geny/Generator$SelfClosing
  #10 = Utf8               coursier/core/shaded/geny/Generator
  #11 = Class              #10            // coursier/core/shaded/geny/Generator
  #12 = Utf8               SelfClosing
  #13 = Utf8               MODULE$
  #14 = Utf8               Lcoursier/core/shaded/geny/Generator$;
  #15 = Utf8               <clinit>
  #16 = Utf8               ()V
  #17 = Utf8               <init>
  #18 = NameAndType        #17:#16        // "<init>":()V
  #19 = Methodref          #2.#18         // coursier/core/shaded/geny/Generator$."<init>":()V
  #20 = NameAndType        #13:#14        // MODULE$:Lcoursier/core/shaded/geny/Generator$;
  #21 = Fieldref           #2.#20         // coursier/core/shaded/geny/Generator$.MODULE$:Lcoursier/core/shaded/geny/Generator$;
  #22 = Utf8               apply
  #23 = Utf8               (Lscala/collection/immutable/Seq;)Lcoursier/core/shaded/geny/Generator;
  #24 = Utf8               <T:Ljava/lang/Object;>(Lscala/collection/immutable/Seq<TT;>;)Lcoursier/core/shaded/geny/Generator<TT;>;
  #25 = Utf8               xs
  #26 = Utf8               scala/Predef$
  #27 = Class              #26            // scala/Predef$
  #28 = Utf8               Lscala/Predef$;
  #29 = NameAndType        #13:#28        // MODULE$:Lscala/Predef$;
  #30 = Fieldref           #27.#29        // scala/Predef$.MODULE$:Lscala/Predef$;
  #31 = Utf8               $conforms
  #32 = Utf8               ()Lscala/Function1;
  #33 = NameAndType        #31:#32        // $conforms:()Lscala/Function1;
  #34 = Methodref          #27.#33        // scala/Predef$.$conforms:()Lscala/Function1;
  #35 = Utf8               from
  #36 = Utf8               (Ljava/lang/Object;Lscala/Function1;)Lcoursier/core/shaded/geny/Generator;
  #37 = NameAndType        #35:#36        // from:(Ljava/lang/Object;Lscala/Function1;)Lcoursier/core/shaded/geny/Generator;
  #38 = Methodref          #2.#37         // coursier/core/shaded/geny/Generator$.from:(Ljava/lang/Object;Lscala/Function1;)Lcoursier/core/shaded/geny/Generator;
  #39 = Utf8               this
  #40 = Utf8               Lscala/collection/immutable/Seq;
  #41 = Utf8               <M:Ljava/lang/Object;T:Ljava/lang/Object;>(TM;Lscala/Function1<TM;Lscala/collection/IterableOnce<TT;>;>;)Lcoursier/core/shaded/geny/Generator<TT;>;
  #42 = Utf8               t
  #43 = Utf8               convert
  #44 = Utf8               (Lscala/Function1;Ljava/lang/Object;)V
  #45 = NameAndType        #17:#44        // "<init>":(Lscala/Function1;Ljava/lang/Object;)V
  #46 = Methodref          #7.#45         // coursier/core/shaded/geny/Generator$$anon$1."<init>":(Lscala/Function1;Ljava/lang/Object;)V
  #47 = Utf8               Ljava/lang/Object;
  #48 = Utf8               Lscala/Function1;
  #49 = Utf8               selfClosing
  #50 = Utf8               (Lscala/Function0;)Lcoursier/core/shaded/geny/Generator;
  #51 = Utf8               <T:Ljava/lang/Object;>(Lscala/Function0<Lscala/Tuple2<Lscala/collection/Iterator<TT;>;Lscala/Function0<Lscala/runtime/BoxedUnit;>;>;>;)Lcoursier/core/shaded/geny/Generator<TT;>;
  #52 = Utf8               makeIterator
  #53 = Utf8               (Lscala/Function0;)V
  #54 = NameAndType        #17:#53        // "<init>":(Lscala/Function0;)V
  #55 = Methodref          #9.#54         // coursier/core/shaded/geny/Generator$SelfClosing."<init>":(Lscala/Function0;)V
  #56 = Utf8               Lscala/Function0;
  #57 = Methodref          #4.#18         // java/lang/Object."<init>":()V
  #58 = Utf8               Code
  #59 = Utf8               LineNumberTable
  #60 = Utf8               LocalVariableTable
  #61 = Utf8               Signature
  #62 = Utf8               MethodParameters
  #63 = Utf8               InnerClasses
  #64 = Utf8               SourceFile
  #65 = Utf8               ScalaInlineInfo
  #66 = Utf8               Scala
{
  public static final coursier.core.shaded.geny.Generator$ MODULE$;
    descriptor: Lcoursier/core/shaded/geny/Generator$;
    flags: (0x0019) ACC_PUBLIC, ACC_STATIC, ACC_FINAL

  public static {};
    descriptor: ()V
    flags: (0x0009) ACC_PUBLIC, ACC_STATIC
    Code:
      stack=2, locals=0, args_size=0
         0: new           #2                  // class coursier/core/shaded/geny/Generator$
         3: dup
         4: invokespecial #19                 // Method "<init>":()V
         7: putstatic     #21                 // Field MODULE$:Lcoursier/core/shaded/geny/Generator$;
        10: return
      LineNumberTable:
        line 199: 0

  public <T extends java.lang.Object> coursier.core.shaded.geny.Generator<T> apply(scala.collection.immutable.Seq<T>);
    descriptor: (Lscala/collection/immutable/Seq;)Lcoursier/core/shaded/geny/Generator;
    flags: (0x0001) ACC_PUBLIC
    Code:
      stack=3, locals=2, args_size=2
         0: aload_0
         1: aload_1
         2: getstatic     #30                 // Field scala/Predef$.MODULE$:Lscala/Predef$;
         5: invokevirtual #34                 // Method scala/Predef$.$conforms:()Lscala/Function1;
         8: invokevirtual #38                 // Method from:(Ljava/lang/Object;Lscala/Function1;)Lcoursier/core/shaded/geny/Generator;
        11: areturn
      LineNumberTable:
        line 205: 0
      LocalVariableTable:
        Start  Length  Slot  Name   Signature
            0      12     0  this   Lcoursier/core/shaded/geny/Generator$;
            0      12     1    xs   Lscala/collection/immutable/Seq;
    Signature: #24                          // <T:Ljava/lang/Object;>(Lscala/collection/immutable/Seq<TT;>;)Lcoursier/core/shaded/geny/Generator<TT;>;
    MethodParameters:
      Name                           Flags
      xs                             final

  public <M extends java.lang.Object, T extends java.lang.Object> coursier.core.shaded.geny.Generator<T> from(M, scala.Function1<M, scala.collection.IterableOnce<T>>);
    descriptor: (Ljava/lang/Object;Lscala/Function1;)Lcoursier/core/shaded/geny/Generator;
    flags: (0x0001) ACC_PUBLIC
    Code:
      stack=4, locals=3, args_size=3
         0: new           #7                  // class coursier/core/shaded/geny/Generator$$anon$1
         3: dup
         4: aload_2
         5: aload_1
         6: invokespecial #46                 // Method coursier/core/shaded/geny/Generator$$anon$1."<init>":(Lscala/Function1;Ljava/lang/Object;)V
         9: areturn
      LineNumberTable:
        line 207: 0
      LocalVariableTable:
        Start  Length  Slot  Name   Signature
            0      10     0  this   Lcoursier/core/shaded/geny/Generator$;
            0      10     1     t   Ljava/lang/Object;
            0      10     2 convert   Lscala/Function1;
    Signature: #41                          // <M:Ljava/lang/Object;T:Ljava/lang/Object;>(TM;Lscala/Function1<TM;Lscala/collection/IterableOnce<TT;>;>;)Lcoursier/core/shaded/geny/Generator<TT;>;
    MethodParameters:
      Name                           Flags
      t                              final
      convert                        final

  public <T extends java.lang.Object> coursier.core.shaded.geny.Generator<T> selfClosing(scala.Function0<scala.Tuple2<scala.collection.Iterator<T>, scala.Function0<scala.runtime.BoxedUnit>>>);
    descriptor: (Lscala/Function0;)Lcoursier/core/shaded/geny/Generator;
    flags: (0x0001) ACC_PUBLIC
    Code:
      stack=3, locals=2, args_size=2
         0: new           #9                  // class coursier/core/shaded/geny/Generator$SelfClosing
         3: dup
         4: aload_1
         5: invokespecial #55                 // Method coursier/core/shaded/geny/Generator$SelfClosing."<init>":(Lscala/Function0;)V
         8: areturn
      LineNumberTable:
        line 221: 0
      LocalVariableTable:
        Start  Length  Slot  Name   Signature
            0       9     0  this   Lcoursier/core/shaded/geny/Generator$;
            0       9     1 makeIterator   Lscala/Function0;
    Signature: #51                          // <T:Ljava/lang/Object;>(Lscala/Function0<Lscala/Tuple2<Lscala/collection/Iterator<TT;>;Lscala/Function0<Lscala/runtime/BoxedUnit;>;>;>;)Lcoursier/core/shaded/geny/Generator<TT;>;
    MethodParameters:
      Name                           Flags
      makeIterator                   final

  private coursier.core.shaded.geny.Generator$();
    descriptor: ()V
    flags: (0x0002) ACC_PRIVATE
    Code:
      stack=1, locals=1, args_size=1
         0: aload_0
         1: invokespecial #57                 // Method java/lang/Object."<init>":()V
         4: return
      LineNumberTable:
        line 354: 0
        line 199: 4
      LocalVariableTable:
        Start  Length  Slot  Name   Signature
            0       5     0  this   Lcoursier/core/shaded/geny/Generator$;
}
InnerClasses:
  public final #7;                        // class coursier/core/shaded/geny/Generator$$anon$1
  public static #12= #9 of #11;           // SelfClosing=class coursier/core/shaded/geny/Generator$SelfClosing of class coursier/core/shaded/geny/Generator
SourceFile: "Generator.scala"
  ScalaInlineInfo: length = 0x18 (unknown attribute)
   01 01 00 04 00 11 00 10 01 00 16 00 17 01 00 23
   00 24 01 00 31 00 32 01
  Scala: length = 0x0 (unknown attribute)

