Classfile /Users/mw/Projects/slang-braindump/.jar/jar11/assemble/slang-braindump/assemble/content/coursier/core/shaded/geny/Generator$End$.class
  Last modified May 29, 2022; size 597 bytes
  SHA-256 checksum 5a61e3f2fe29624f4999d8b85db8815e0577f6cbe548fc1d36f88725461de278
  Compiled from "Generator.scala"
public class coursier.core.shaded.geny.Generator$End$ implements coursier.core.shaded.geny.Generator$Action
  minor version: 0
  major version: 52
  flags: (0x0021) ACC_PUBLIC, ACC_SUPER
  this_class: #2                          // coursier/core/shaded/geny/Generator$End$
  super_class: #4                         // java/lang/Object
  interfaces: 1, fields: 1, methods: 2, attributes: 4
Constant pool:
   #1 = Utf8               coursier/core/shaded/geny/Generator$End$
   #2 = Class              #1             // coursier/core/shaded/geny/Generator$End$
   #3 = Utf8               java/lang/Object
   #4 = Class              #3             // java/lang/Object
   #5 = Utf8               coursier/core/shaded/geny/Generator$Action
   #6 = Class              #5             // coursier/core/shaded/geny/Generator$Action
   #7 = Utf8               Generator.scala
   #8 = Utf8               coursier/core/shaded/geny/Generator
   #9 = Class              #8             // coursier/core/shaded/geny/Generator
  #10 = Utf8               Action
  #11 = Utf8
  #12 = Utf8               MODULE$
  #13 = Utf8               Lcoursier/core/shaded/geny/Generator$End$;
  #14 = Utf8               <clinit>
  #15 = Utf8               ()V
  #16 = Utf8               <init>
  #17 = NameAndType        #16:#15        // "<init>":()V
  #18 = Methodref          #2.#17         // coursier/core/shaded/geny/Generator$End$."<init>":()V
  #19 = NameAndType        #12:#13        // MODULE$:Lcoursier/core/shaded/geny/Generator$End$;
  #20 = Fieldref           #2.#19         // coursier/core/shaded/geny/Generator$End$.MODULE$:Lcoursier/core/shaded/geny/Generator$End$;
  #21 = Methodref          #4.#17         // java/lang/Object."<init>":()V
  #22 = Utf8               this
  #23 = Utf8               Code
  #24 = Utf8               LineNumberTable
  #25 = Utf8               LocalVariableTable
  #26 = Utf8               InnerClasses
  #27 = Utf8               SourceFile
  #28 = Utf8               ScalaInlineInfo
  #29 = Utf8               Scala
{
  public static final coursier.core.shaded.geny.Generator$End$ MODULE$;
    descriptor: Lcoursier/core/shaded/geny/Generator$End$;
    flags: (0x0019) ACC_PUBLIC, ACC_STATIC, ACC_FINAL

  public static {};
    descriptor: ()V
    flags: (0x0009) ACC_PUBLIC, ACC_STATIC
    Code:
      stack=2, locals=0, args_size=0
         0: new           #2                  // class coursier/core/shaded/geny/Generator$End$
         3: dup
         4: invokespecial #18                 // Method "<init>":()V
         7: putstatic     #20                 // Field MODULE$:Lcoursier/core/shaded/geny/Generator$End$;
        10: return
      LineNumberTable:
        line 201: 0

  public coursier.core.shaded.geny.Generator$End$();
    descriptor: ()V
    flags: (0x0001) ACC_PUBLIC
    Code:
      stack=1, locals=1, args_size=1
         0: aload_0
         1: invokespecial #21                 // Method java/lang/Object."<init>":()V
         4: return
      LineNumberTable:
        line 201: 0
      LocalVariableTable:
        Start  Length  Slot  Name   Signature
            0       5     0  this   Lcoursier/core/shaded/geny/Generator$End$;
}
InnerClasses:
  public static #10= #6 of #9;            // Action=class coursier/core/shaded/geny/Generator$Action of class coursier/core/shaded/geny/Generator
  public static #11= #2 of #9;            // =class coursier/core/shaded/geny/Generator$End$ of class coursier/core/shaded/geny/Generator
SourceFile: "Generator.scala"
  ScalaInlineInfo: length = 0x9 (unknown attribute)
   01 01 00 01 00 10 00 0F 01
  Scala: length = 0x0 (unknown attribute)

