Classfile /Users/mw/Projects/slang-braindump/.jar/jar11/assemble/slang-braindump/assemble/content/coursier/core/shaded/geny/LowPriWritable.class
  Last modified May 29, 2022; size 1602 bytes
  SHA-256 checksum 7a8230bb3e03b5d069f3a5a2600b2cfb29e5c47b3937bca571e43120b6c9af5f
  Compiled from "Writable.scala"
public interface coursier.core.shaded.geny.LowPriWritable
  minor version: 0
  major version: 52
  flags: (0x0601) ACC_PUBLIC, ACC_INTERFACE, ACC_ABSTRACT
  this_class: #2                          // coursier/core/shaded/geny/LowPriWritable
  super_class: #4                         // java/lang/Object
  interfaces: 0, fields: 0, methods: 3, attributes: 4
Constant pool:
   #1 = Utf8               coursier/core/shaded/geny/LowPriWritable
   #2 = Class              #1             // coursier/core/shaded/geny/LowPriWritable
   #3 = Utf8               java/lang/Object
   #4 = Class              #3             // java/lang/Object
   #5 = Utf8               Writable.scala
   #6 = Utf8               Lscala/reflect/ScalaSignature;
   #7 = Utf8               bytes
   #8 = Utf8               \u0006\u0005A2qa\u0001\u0003\u0011\u0002\u0007\u0005q\u0001C\u0003\u000f\u0001\u0011\u0005q\u0002C\u0003\u0014\u0001\u0011\rAC\u0001\bM_^\u0004&/[,sSR\f\'\r\\3\u000b\u0003\u0015\tAaZ3os\u000e\u00011C\u0001\u0001\t!\tIA\"D\u0001\u000b\u0015\u0005Y\u0011!B:dC2\f\u0017BA\u0007\u000b\u0005\u0019\te.\u001f*fM\u00061A%\u001b8ji\u0012\"\u0012\u0001\u0005\t\u0003\u0013EI!A\u0005\u0006\u0003\tUs\u0017\u000e^\u0001\u0011e\u0016\fG-\u00192mK^\u0013\u0018\u000e^1cY\u0016,\"!\u0006\u0012\u0015\u0005YqCCA\f\u001c!\tA\u0012$D\u0001\u0005\u0013\tQBA\u0001\u0005Xe&$\u0018M\u00197f\u0011\u0015a\"\u0001q\u0001\u001e\u0003\u00051\u0007\u0003B\u0005\u001fA-J!a\b\u0006\u0003\u0013\u0019+hn\u0019;j_:\f\u0004CA\u0011#\u0019\u0001!Qa\t\u0002C\u0002\u0011\u0012\u0011\u0001V\t\u0003K!\u0002\"!\u0003\u0014\n\u0005\u001dR!a\u0002(pi\"Lgn\u001a\t\u0003\u0013%J!A\u000b\u0006\u0003\u0007\u0005s\u0017\u0010\u0005\u0002\u0019Y%\u0011Q\u0006\u0002\u0002\t%\u0016\fG-\u00192mK\")qF\u0001a\u0001A\u0005\tA\u000f
   #9 = Utf8               readableWritable$
  #10 = Utf8               (Lcoursier/core/shaded/geny/LowPriWritable;Ljava/lang/Object;Lscala/Function1;)Lcoursier/core/shaded/geny/Writable;
  #11 = Utf8               $this
  #12 = Utf8               t
  #13 = Utf8               f
  #14 = Utf8               readableWritable
  #15 = Utf8               (Ljava/lang/Object;Lscala/Function1;)Lcoursier/core/shaded/geny/Writable;
  #16 = NameAndType        #14:#15        // readableWritable:(Ljava/lang/Object;Lscala/Function1;)Lcoursier/core/shaded/geny/Writable;
  #17 = InterfaceMethodref #2.#16         // coursier/core/shaded/geny/LowPriWritable.readableWritable:(Ljava/lang/Object;Lscala/Function1;)Lcoursier/core/shaded/geny/Writable;
  #18 = Utf8               Lcoursier/core/shaded/geny/LowPriWritable;
  #19 = Utf8               Ljava/lang/Object;
  #20 = Utf8               Lscala/Function1;
  #21 = Utf8               <T:Ljava/lang/Object;>(TT;Lscala/Function1<TT;Lcoursier/core/shaded/geny/Readable;>;)Lcoursier/core/shaded/geny/Writable;
  #22 = Utf8               scala/Function1
  #23 = Class              #22            // scala/Function1
  #24 = Utf8               apply
  #25 = Utf8               (Ljava/lang/Object;)Ljava/lang/Object;
  #26 = NameAndType        #24:#25        // apply:(Ljava/lang/Object;)Ljava/lang/Object;
  #27 = InterfaceMethodref #23.#26        // scala/Function1.apply:(Ljava/lang/Object;)Ljava/lang/Object;
  #28 = Utf8               coursier/core/shaded/geny/Writable
  #29 = Class              #28            // coursier/core/shaded/geny/Writable
  #30 = Utf8               this
  #31 = Utf8               $init$
  #32 = Utf8               (Lcoursier/core/shaded/geny/LowPriWritable;)V
  #33 = Utf8               Code
  #34 = Utf8               LineNumberTable
  #35 = Utf8               LocalVariableTable
  #36 = Utf8               MethodParameters
  #37 = Utf8               Signature
  #38 = Utf8               SourceFile
  #39 = Utf8               RuntimeVisibleAnnotations
  #40 = Utf8               ScalaInlineInfo
  #41 = Utf8               ScalaSig
{
  public static coursier.core.shaded.geny.Writable readableWritable$(coursier.core.shaded.geny.LowPriWritable, java.lang.Object, scala.Function1);
    descriptor: (Lcoursier/core/shaded/geny/LowPriWritable;Ljava/lang/Object;Lscala/Function1;)Lcoursier/core/shaded/geny/Writable;
    flags: (0x1009) ACC_PUBLIC, ACC_STATIC, ACC_SYNTHETIC
    Code:
      stack=3, locals=3, args_size=3
         0: aload_0
         1: aload_1
         2: aload_2
         3: invokespecial #17                 // InterfaceMethod readableWritable:(Ljava/lang/Object;Lscala/Function1;)Lcoursier/core/shaded/geny/Writable;
         6: areturn
      LineNumberTable:
        line 47: 0
      LocalVariableTable:
        Start  Length  Slot  Name   Signature
            0       7     0 $this   Lcoursier/core/shaded/geny/LowPriWritable;
            0       7     1     t   Ljava/lang/Object;
            0       7     2     f   Lscala/Function1;
    MethodParameters:
      Name                           Flags
      $this                          final synthetic
      t                              final
      f                              final

  public default <T extends java.lang.Object> coursier.core.shaded.geny.Writable readableWritable(T, scala.Function1<T, coursier.core.shaded.geny.Readable>);
    descriptor: (Ljava/lang/Object;Lscala/Function1;)Lcoursier/core/shaded/geny/Writable;
    flags: (0x0001) ACC_PUBLIC
    Code:
      stack=2, locals=3, args_size=3
         0: aload_2
         1: aload_1
         2: invokeinterface #27,  2           // InterfaceMethod scala/Function1.apply:(Ljava/lang/Object;)Ljava/lang/Object;
         7: checkcast     #29                 // class coursier/core/shaded/geny/Writable
        10: areturn
      LineNumberTable:
        line 47: 0
      LocalVariableTable:
        Start  Length  Slot  Name   Signature
            0      11     0  this   Lcoursier/core/shaded/geny/LowPriWritable;
            0      11     1     t   Ljava/lang/Object;
            0      11     2     f   Lscala/Function1;
    Signature: #21                          // <T:Ljava/lang/Object;>(TT;Lscala/Function1<TT;Lcoursier/core/shaded/geny/Readable;>;)Lcoursier/core/shaded/geny/Writable;
    MethodParameters:
      Name                           Flags
      t                              final
      f                              final

  public static void $init$(coursier.core.shaded.geny.LowPriWritable);
    descriptor: (Lcoursier/core/shaded/geny/LowPriWritable;)V
    flags: (0x0009) ACC_PUBLIC, ACC_STATIC
    Code:
      stack=0, locals=1, args_size=1
         0: return
      LineNumberTable:
        line 46: 0
      LocalVariableTable:
        Start  Length  Slot  Name   Signature
            0       1     0 $this   Lcoursier/core/shaded/geny/LowPriWritable;
    MethodParameters:
      Name                           Flags
      $this                          final synthetic
}
SourceFile: "Writable.scala"
RuntimeVisibleAnnotations:
  0: #6(#7=s#8)
    scala.reflect.ScalaSignature(
      bytes="\u0006\u0005A2qa\u0001\u0003\u0011\u0002\u0007\u0005q\u0001C\u0003\u000f\u0001\u0011\u0005q\u0002C\u0003\u0014\u0001\u0011\rAC\u0001\bM_^\u0004&/[,sSR\f\'\r\\3\u000b\u0003\u0015\tAaZ3os\u000e\u00011C\u0001\u0001\t!\tIA\"D\u0001\u000b\u0015\u0005Y\u0011!B:dC2\f\u0017BA\u0007\u000b\u0005\u0019\te.\u001f*fM\u00061A%\u001b8ji\u0012\"\u0012\u0001\u0005\t\u0003\u0013EI!A\u0005\u0006\u0003\tUs\u0017\u000e^\u0001\u0011e\u0016\fG-\u00192mK^\u0013\u0018\u000e^1cY\u0016,\"!\u0006\u0012\u0015\u0005YqCCA\f\u001c!\tA\u0012$D\u0001\u0005\u0013\tQBA\u0001\u0005Xe&$\u0018M\u00197f\u0011\u0015a\"\u0001q\u0001\u001e\u0003\u00051\u0007\u0003B\u0005\u001fA-J!a\b\u0006\u0003\u0013\u0019+hn\u0019;j_:\f\u0004CA\u0011#\u0019\u0001!Qa\t\u0002C\u0002\u0011\u0012\u0011\u0001V\t\u0003K!\u0002\"!\u0003\u0014\n\u0005\u001dR!a\u0002(pi\"Lgn\u001a\t\u0003\u0013%J!A\u000b\u0006\u0003\u0007\u0005s\u0017\u0010\u0005\u0002\u0019Y%\u0011Q\u0006\u0002\u0002\t%\u0016\fG-\u00192mK\")qF\u0001a\u0001A\u0005\tA\u000f"
    )
  ScalaInlineInfo: length = 0x13 (unknown attribute)
   01 00 00 03 00 1F 00 20 01 00 09 00 0A 01 00 0E
   00 0F 00
  ScalaSig: length = 0x3 (unknown attribute)
   05 02 00
