Classfile /Users/mw/Projects/slang-braindump/.jar/jar11/assemble/slang-braindump/assemble/content/com/fasterxml/jackson/databind/JsonSerializer$None.class
  Last modified May 29, 2022; size 496 bytes
  SHA-256 checksum 777495be3debfac070acbd037e97dbb65f7d78f17bfe7a7df089306358d2fcad
  Compiled from "JsonSerializer.java"
public abstract class com.fasterxml.jackson.databind.JsonSerializer$None extends com.fasterxml.jackson.databind.JsonSerializer<java.lang.Object>
  minor version: 0
  major version: 52
  flags: (0x0421) ACC_PUBLIC, ACC_SUPER, ACC_ABSTRACT
  this_class: #2                          // com/fasterxml/jackson/databind/JsonSerializer$None
  super_class: #3                         // com/fasterxml/jackson/databind/JsonSerializer
  interfaces: 0, fields: 0, methods: 1, attributes: 3
Constant pool:
   #1 = Methodref          #3.#17         // com/fasterxml/jackson/databind/JsonSerializer."<init>":()V
   #2 = Class              #18            // com/fasterxml/jackson/databind/JsonSerializer$None
   #3 = Class              #19            // com/fasterxml/jackson/databind/JsonSerializer
   #4 = Utf8               <init>
   #5 = Utf8               ()V
   #6 = Utf8               Code
   #7 = Utf8               LineNumberTable
   #8 = Utf8               LocalVariableTable
   #9 = Utf8               this
  #10 = Utf8               None
  #11 = Utf8               InnerClasses
  #12 = Utf8               Lcom/fasterxml/jackson/databind/JsonSerializer$None;
  #13 = Utf8               Signature
  #14 = Utf8               Lcom/fasterxml/jackson/databind/JsonSerializer<Ljava/lang/Object;>;
  #15 = Utf8               SourceFile
  #16 = Utf8               JsonSerializer.java
  #17 = NameAndType        #4:#5          // "<init>":()V
  #18 = Utf8               com/fasterxml/jackson/databind/JsonSerializer$None
  #19 = Utf8               com/fasterxml/jackson/databind/JsonSerializer
{
  public com.fasterxml.jackson.databind.JsonSerializer$None();
    descriptor: ()V
    flags: (0x0001) ACC_PUBLIC
    Code:
      stack=1, locals=1, args_size=1
         0: aload_0
         1: invokespecial #1                  // Method com/fasterxml/jackson/databind/JsonSerializer."<init>":()V
         4: return
      LineNumberTable:
        line 292: 0
      LocalVariableTable:
        Start  Length  Slot  Name   Signature
            0       5     0  this   Lcom/fasterxml/jackson/databind/JsonSerializer$None;
}
Signature: #14                          // Lcom/fasterxml/jackson/databind/JsonSerializer<Ljava/lang/Object;>;
SourceFile: "JsonSerializer.java"
InnerClasses:
  public static abstract #10= #2 of #3;   // None=class com/fasterxml/jackson/databind/JsonSerializer$None of class com/fasterxml/jackson/databind/JsonSerializer
