Classfile /Users/mw/Projects/slang-braindump/.jar/jar11/assemble/slang-braindump/assemble/content/com/fasterxml/jackson/databind/PropertyNamingStrategies$LowerDotCaseStrategy.class
  Last modified May 29, 2022; size 893 bytes
  SHA-256 checksum 05435a5ff0f1b8debe62c4aed4e44244a8b80416d403384a3ad691b6fe75e978
  Compiled from "PropertyNamingStrategies.java"
public class com.fasterxml.jackson.databind.PropertyNamingStrategies$LowerDotCaseStrategy extends com.fasterxml.jackson.databind.PropertyNamingStrategies$NamingBase
  minor version: 0
  major version: 52
  flags: (0x0021) ACC_PUBLIC, ACC_SUPER
  this_class: #3                          // com/fasterxml/jackson/databind/PropertyNamingStrategies$LowerDotCaseStrategy
  super_class: #4                         // com/fasterxml/jackson/databind/PropertyNamingStrategies$NamingBase
  interfaces: 0, fields: 1, methods: 2, attributes: 2
Constant pool:
   #1 = Methodref          #4.#25         // com/fasterxml/jackson/databind/PropertyNamingStrategies$NamingBase."<init>":()V
   #2 = Methodref          #3.#26         // com/fasterxml/jackson/databind/PropertyNamingStrategies$LowerDotCaseStrategy.translateLowerCaseWithSeparator:(Ljava/lang/String;C)Ljava/lang/String;
   #3 = Class              #28            // com/fasterxml/jackson/databind/PropertyNamingStrategies$LowerDotCaseStrategy
   #4 = Class              #29            // com/fasterxml/jackson/databind/PropertyNamingStrategies$NamingBase
   #5 = Utf8               serialVersionUID
   #6 = Utf8               J
   #7 = Utf8               ConstantValue
   #8 = Long               2l
  #10 = Utf8               <init>
  #11 = Utf8               ()V
  #12 = Utf8               Code
  #13 = Utf8               LineNumberTable
  #14 = Utf8               LocalVariableTable
  #15 = Utf8               this
  #16 = Utf8               LowerDotCaseStrategy
  #17 = Utf8               InnerClasses
  #18 = Utf8               Lcom/fasterxml/jackson/databind/PropertyNamingStrategies$LowerDotCaseStrategy;
  #19 = Utf8               translate
  #20 = Utf8               (Ljava/lang/String;)Ljava/lang/String;
  #21 = Utf8               input
  #22 = Utf8               Ljava/lang/String;
  #23 = Utf8               SourceFile
  #24 = Utf8               PropertyNamingStrategies.java
  #25 = NameAndType        #10:#11        // "<init>":()V
  #26 = NameAndType        #31:#32        // translateLowerCaseWithSeparator:(Ljava/lang/String;C)Ljava/lang/String;
  #27 = Class              #33            // com/fasterxml/jackson/databind/PropertyNamingStrategies
  #28 = Utf8               com/fasterxml/jackson/databind/PropertyNamingStrategies$LowerDotCaseStrategy
  #29 = Utf8               com/fasterxml/jackson/databind/PropertyNamingStrategies$NamingBase
  #30 = Utf8               NamingBase
  #31 = Utf8               translateLowerCaseWithSeparator
  #32 = Utf8               (Ljava/lang/String;C)Ljava/lang/String;
  #33 = Utf8               com/fasterxml/jackson/databind/PropertyNamingStrategies
{
  private static final long serialVersionUID;
    descriptor: J
    flags: (0x001a) ACC_PRIVATE, ACC_STATIC, ACC_FINAL
    ConstantValue: long 2l

  public com.fasterxml.jackson.databind.PropertyNamingStrategies$LowerDotCaseStrategy();
    descriptor: ()V
    flags: (0x0001) ACC_PUBLIC
    Code:
      stack=1, locals=1, args_size=1
         0: aload_0
         1: invokespecial #1                  // Method com/fasterxml/jackson/databind/PropertyNamingStrategies$NamingBase."<init>":()V
         4: return
      LineNumberTable:
        line 373: 0
      LocalVariableTable:
        Start  Length  Slot  Name   Signature
            0       5     0  this   Lcom/fasterxml/jackson/databind/PropertyNamingStrategies$LowerDotCaseStrategy;

  public java.lang.String translate(java.lang.String);
    descriptor: (Ljava/lang/String;)Ljava/lang/String;
    flags: (0x0001) ACC_PUBLIC
    Code:
      stack=3, locals=2, args_size=2
         0: aload_0
         1: aload_1
         2: bipush        46
         4: invokevirtual #2                  // Method translateLowerCaseWithSeparator:(Ljava/lang/String;C)Ljava/lang/String;
         7: areturn
      LineNumberTable:
        line 378: 0
      LocalVariableTable:
        Start  Length  Slot  Name   Signature
            0       8     0  this   Lcom/fasterxml/jackson/databind/PropertyNamingStrategies$LowerDotCaseStrategy;
            0       8     1 input   Ljava/lang/String;
}
SourceFile: "PropertyNamingStrategies.java"
InnerClasses:
  public static #16= #3 of #27;           // LowerDotCaseStrategy=class com/fasterxml/jackson/databind/PropertyNamingStrategies$LowerDotCaseStrategy of class com/fasterxml/jackson/databind/PropertyNamingStrategies
  public static abstract #30= #4 of #27;  // NamingBase=class com/fasterxml/jackson/databind/PropertyNamingStrategies$NamingBase of class com/fasterxml/jackson/databind/PropertyNamingStrategies
