Classfile /Users/mw/Projects/slang-braindump/.jar/jar8/assemble/slang-braindump/assemble/content/com/fasterxml/jackson/core/base/ParserBase.class
  Last modified May 29, 2022; size 22746 bytes
  SHA-256 checksum d065c08cb48df2a97dcec8c6ec14c63c9e1ad9102776d903650d8ef9fffa60a1
  Compiled from "ParserBase.java"
public abstract class com.fasterxml.jackson.core.base.ParserBase extends com.fasterxml.jackson.core.base.ParserMinimalBase
  minor version: 0
  major version: 50
  flags: (0x0421) ACC_PUBLIC, ACC_SUPER, ACC_ABSTRACT
  this_class: #231                        // com/fasterxml/jackson/core/base/ParserBase
  super_class: #4                         // com/fasterxml/jackson/core/base/ParserMinimalBase
  interfaces: 0, fields: 28, methods: 69, attributes: 2
Constant pool:
    #1 = Methodref          #4.#471       // com/fasterxml/jackson/core/base/ParserMinimalBase."<init>":(I)V
    #2 = Fieldref           #231.#472     // com/fasterxml/jackson/core/base/ParserBase._currInputRow:I
    #3 = Fieldref           #231.#473     // com/fasterxml/jackson/core/base/ParserBase._tokenInputRow:I
    #4 = Class              #474          // com/fasterxml/jackson/core/base/ParserMinimalBase
    #5 = Fieldref           #231.#475     // com/fasterxml/jackson/core/base/ParserBase._numTypesValid:I
    #6 = Fieldref           #231.#476     // com/fasterxml/jackson/core/base/ParserBase._ioContext:Lcom/fasterxml/jackson/core/io/IOContext;
    #7 = Methodref          #477.#478     // com/fasterxml/jackson/core/io/IOContext.constructTextBuffer:()Lcom/fasterxml/jackson/core/util/TextBuffer;
    #8 = Fieldref           #231.#479     // com/fasterxml/jackson/core/base/ParserBase._textBuffer:Lcom/fasterxml/jackson/core/util/TextBuffer;
    #9 = Fieldref           #300.#480     // com/fasterxml/jackson/core/JsonParser$Feature.STRICT_DUPLICATE_DETECTION:Lcom/fasterxml/jackson/core/JsonParser$Feature;
   #10 = Methodref          #300.#481     // com/fasterxml/jackson/core/JsonParser$Feature.enabledIn:(I)Z
   #11 = Methodref          #482.#483     // com/fasterxml/jackson/core/json/DupDetector.rootDetector:(Lcom/fasterxml/jackson/core/JsonParser;)Lcom/fasterxml/jackson/core/json/DupDetector;
   #12 = Methodref          #484.#485     // com/fasterxml/jackson/core/json/JsonReadContext.createRootContext:(Lcom/fasterxml/jackson/core/json/DupDetector;)Lcom/fasterxml/jackson/core/json/JsonReadContext;
   #13 = Fieldref           #231.#486     // com/fasterxml/jackson/core/base/ParserBase._parsingContext:Lcom/fasterxml/jackson/core/json/JsonReadContext;
   #14 = Fieldref           #487.#488     // com/fasterxml/jackson/core/json/PackageVersion.VERSION:Lcom/fasterxml/jackson/core/Version;
   #15 = Methodref          #484.#489     // com/fasterxml/jackson/core/json/JsonReadContext.getCurrentValue:()Ljava/lang/Object;
   #16 = Methodref          #484.#490     // com/fasterxml/jackson/core/json/JsonReadContext.setCurrentValue:(Ljava/lang/Object;)V
   #17 = Fieldref           #231.#491     // com/fasterxml/jackson/core/base/ParserBase._features:I
   #18 = Methodref          #300.#492     // com/fasterxml/jackson/core/JsonParser$Feature.getMask:()I
   #19 = Methodref          #484.#493     // com/fasterxml/jackson/core/json/JsonReadContext.getDupDetector:()Lcom/fasterxml/jackson/core/json/DupDetector;
   #20 = Methodref          #484.#494     // com/fasterxml/jackson/core/json/JsonReadContext.withDupDetector:(Lcom/fasterxml/jackson/core/json/DupDetector;)Lcom/fasterxml/jackson/core/json/JsonReadContext;
   #21 = Methodref          #231.#495     // com/fasterxml/jackson/core/base/ParserBase._checkStdFeatureChanges:(II)V
   #22 = Fieldref           #231.#496     // com/fasterxml/jackson/core/base/ParserBase._currToken:Lcom/fasterxml/jackson/core/JsonToken;
   #23 = Fieldref           #497.#498     // com/fasterxml/jackson/core/JsonToken.START_OBJECT:Lcom/fasterxml/jackson/core/JsonToken;
   #24 = Fieldref           #497.#499     // com/fasterxml/jackson/core/JsonToken.START_ARRAY:Lcom/fasterxml/jackson/core/JsonToken;
   #25 = Methodref          #484.#500     // com/fasterxml/jackson/core/json/JsonReadContext.getParent:()Lcom/fasterxml/jackson/core/json/JsonReadContext;
   #26 = Methodref          #484.#501     // com/fasterxml/jackson/core/json/JsonReadContext.getCurrentName:()Ljava/lang/String;
   #27 = Methodref          #484.#502     // com/fasterxml/jackson/core/json/JsonReadContext.setCurrentName:(Ljava/lang/String;)V
   #28 = Class              #503          // java/io/IOException
   #29 = Class              #504          // java/lang/IllegalStateException
   #30 = Methodref          #29.#505      // java/lang/IllegalStateException."<init>":(Ljava/lang/Throwable;)V
   #31 = Fieldref           #231.#506     // com/fasterxml/jackson/core/base/ParserBase._closed:Z
   #32 = Fieldref           #231.#507     // com/fasterxml/jackson/core/base/ParserBase._inputPtr:I
   #33 = Fieldref           #231.#508     // com/fasterxml/jackson/core/base/ParserBase._inputEnd:I
   #34 = Methodref          #509.#510     // java/lang/Math.max:(II)I
   #35 = Methodref          #231.#511     // com/fasterxml/jackson/core/base/ParserBase._closeInput:()V
   #36 = Methodref          #231.#512     // com/fasterxml/jackson/core/base/ParserBase._releaseBuffers:()V
   #37 = Class              #513          // com/fasterxml/jackson/core/JsonLocation
   #38 = Methodref          #231.#514     // com/fasterxml/jackson/core/base/ParserBase._contentReference:()Lcom/fasterxml/jackson/core/io/ContentReference;
   #39 = Long               -1l
   #41 = Methodref          #231.#515     // com/fasterxml/jackson/core/base/ParserBase.getTokenCharacterOffset:()J
   #42 = Methodref          #231.#516     // com/fasterxml/jackson/core/base/ParserBase.getTokenLineNr:()I
   #43 = Methodref          #231.#517     // com/fasterxml/jackson/core/base/ParserBase.getTokenColumnNr:()I
   #44 = Methodref          #37.#518      // com/fasterxml/jackson/core/JsonLocation."<init>":(Lcom/fasterxml/jackson/core/io/ContentReference;JJII)V
   #45 = Fieldref           #231.#519     // com/fasterxml/jackson/core/base/ParserBase._currInputRowStart:I
   #46 = Fieldref           #231.#520     // com/fasterxml/jackson/core/base/ParserBase._currInputProcessed:J
   #47 = Fieldref           #497.#521     // com/fasterxml/jackson/core/JsonToken.VALUE_STRING:Lcom/fasterxml/jackson/core/JsonToken;
   #48 = Fieldref           #497.#522     // com/fasterxml/jackson/core/JsonToken.FIELD_NAME:Lcom/fasterxml/jackson/core/JsonToken;
   #49 = Fieldref           #231.#523     // com/fasterxml/jackson/core/base/ParserBase._nameCopied:Z
   #50 = Fieldref           #231.#524     // com/fasterxml/jackson/core/base/ParserBase._binaryValue:[B
   #51 = Class              #525          // java/lang/StringBuilder
   #52 = Methodref          #51.#526      // java/lang/StringBuilder."<init>":()V
   #53 = String             #527          // Current token (
   #54 = Methodref          #51.#528      // java/lang/StringBuilder.append:(Ljava/lang/String;)Ljava/lang/StringBuilder;
   #55 = Methodref          #51.#529      // java/lang/StringBuilder.append:(Ljava/lang/Object;)Ljava/lang/StringBuilder;
   #56 = String             #530          // ) not VALUE_STRING, can not access as binary
   #57 = Methodref          #51.#531      // java/lang/StringBuilder.toString:()Ljava/lang/String;
   #58 = Methodref          #231.#532     // com/fasterxml/jackson/core/base/ParserBase._reportError:(Ljava/lang/String;)V
   #59 = Methodref          #231.#533     // com/fasterxml/jackson/core/base/ParserBase._getByteArrayBuilder:()Lcom/fasterxml/jackson/core/util/ByteArrayBuilder;
   #60 = Methodref          #231.#534     // com/fasterxml/jackson/core/base/ParserBase.getText:()Ljava/lang/String;
   #61 = Methodref          #231.#535     // com/fasterxml/jackson/core/base/ParserBase._decodeBase64:(Ljava/lang/String;Lcom/fasterxml/jackson/core/util/ByteArrayBuilder;Lcom/fasterxml/jackson/core/Base64Variant;)V
   #62 = Methodref          #79.#536      // com/fasterxml/jackson/core/util/ByteArrayBuilder.toByteArray:()[B
   #63 = Fieldref           #231.#537     // com/fasterxml/jackson/core/base/ParserBase._tokenInputTotal:J
   #64 = Fieldref           #231.#538     // com/fasterxml/jackson/core/base/ParserBase._tokenInputCol:I
   #65 = Methodref          #539.#540     // com/fasterxml/jackson/core/util/TextBuffer.releaseBuffers:()V
   #66 = Fieldref           #231.#541     // com/fasterxml/jackson/core/base/ParserBase._nameCopyBuffer:[C
   #67 = Methodref          #477.#542     // com/fasterxml/jackson/core/io/IOContext.releaseNameCopyBuffer:([C)V
   #68 = Methodref          #484.#543     // com/fasterxml/jackson/core/json/JsonReadContext.inRoot:()Z
   #69 = Methodref          #484.#544     // com/fasterxml/jackson/core/json/JsonReadContext.inArray:()Z
   #70 = String             #545          // Array
   #71 = String             #546          // Object
   #72 = String             #547          // : expected close marker for %s (start marker at %s)
   #73 = Class              #548          // java/lang/Object
   #74 = Methodref          #484.#549     // com/fasterxml/jackson/core/json/JsonReadContext.startLocation:(Lcom/fasterxml/jackson/core/io/ContentReference;)Lcom/fasterxml/jackson/core/JsonLocation;
   #75 = Methodref          #550.#551     // java/lang/String.format:(Ljava/lang/String;[Ljava/lang/Object;)Ljava/lang/String;
   #76 = Methodref          #231.#552     // com/fasterxml/jackson/core/base/ParserBase._reportInvalidEOF:(Ljava/lang/String;Lcom/fasterxml/jackson/core/JsonToken;)V
   #77 = Methodref          #231.#553     // com/fasterxml/jackson/core/base/ParserBase._handleEOF:()V
   #78 = Fieldref           #231.#554     // com/fasterxml/jackson/core/base/ParserBase._byteArrayBuilder:Lcom/fasterxml/jackson/core/util/ByteArrayBuilder;
   #79 = Class              #555          // com/fasterxml/jackson/core/util/ByteArrayBuilder
   #80 = Methodref          #79.#526      // com/fasterxml/jackson/core/util/ByteArrayBuilder."<init>":()V
   #81 = Methodref          #79.#556      // com/fasterxml/jackson/core/util/ByteArrayBuilder.reset:()V
   #82 = Methodref          #231.#557     // com/fasterxml/jackson/core/base/ParserBase.resetInt:(ZI)Lcom/fasterxml/jackson/core/JsonToken;
   #83 = Methodref          #231.#558     // com/fasterxml/jackson/core/base/ParserBase.resetFloat:(ZIII)Lcom/fasterxml/jackson/core/JsonToken;
   #84 = Fieldref           #231.#559     // com/fasterxml/jackson/core/base/ParserBase._numberNegative:Z
   #85 = Fieldref           #231.#560     // com/fasterxml/jackson/core/base/ParserBase._intLength:I
   #86 = Fieldref           #231.#561     // com/fasterxml/jackson/core/base/ParserBase._fractLength:I
   #87 = Fieldref           #231.#562     // com/fasterxml/jackson/core/base/ParserBase._expLength:I
   #88 = Fieldref           #497.#563     // com/fasterxml/jackson/core/JsonToken.VALUE_NUMBER_INT:Lcom/fasterxml/jackson/core/JsonToken;
   #89 = Fieldref           #497.#564     // com/fasterxml/jackson/core/JsonToken.VALUE_NUMBER_FLOAT:Lcom/fasterxml/jackson/core/JsonToken;
   #90 = Methodref          #539.#565     // com/fasterxml/jackson/core/util/TextBuffer.resetWithString:(Ljava/lang/String;)V
   #91 = Fieldref           #231.#566     // com/fasterxml/jackson/core/base/ParserBase._numberDouble:D
   #92 = Methodref          #567.#568     // java/lang/Double.isNaN:(D)Z
   #93 = Methodref          #567.#569     // java/lang/Double.isInfinite:(D)Z
   #94 = Methodref          #231.#570     // com/fasterxml/jackson/core/base/ParserBase._parseNumericValue:(I)V
   #95 = Fieldref           #231.#571     // com/fasterxml/jackson/core/base/ParserBase._numberInt:I
   #96 = Methodref          #572.#573     // java/lang/Integer.valueOf:(I)Ljava/lang/Integer;
   #97 = Fieldref           #231.#574     // com/fasterxml/jackson/core/base/ParserBase._numberLong:J
   #98 = Methodref          #575.#576     // java/lang/Long.valueOf:(J)Ljava/lang/Long;
   #99 = Fieldref           #231.#577     // com/fasterxml/jackson/core/base/ParserBase._numberBigInt:Ljava/math/BigInteger;
  #100 = Methodref          #231.#578     // com/fasterxml/jackson/core/base/ParserBase._throwInternal:()V
  #101 = Fieldref           #231.#579     // com/fasterxml/jackson/core/base/ParserBase._numberBigDecimal:Ljava/math/BigDecimal;
  #102 = Methodref          #567.#580     // java/lang/Double.valueOf:(D)Ljava/lang/Double;
  #103 = Fieldref           #389.#581     // com/fasterxml/jackson/core/JsonParser$NumberType.INT:Lcom/fasterxml/jackson/core/JsonParser$NumberType;
  #104 = Fieldref           #389.#582     // com/fasterxml/jackson/core/JsonParser$NumberType.LONG:Lcom/fasterxml/jackson/core/JsonParser$NumberType;
  #105 = Fieldref           #389.#583     // com/fasterxml/jackson/core/JsonParser$NumberType.BIG_INTEGER:Lcom/fasterxml/jackson/core/JsonParser$NumberType;
  #106 = Fieldref           #389.#584     // com/fasterxml/jackson/core/JsonParser$NumberType.BIG_DECIMAL:Lcom/fasterxml/jackson/core/JsonParser$NumberType;
  #107 = Fieldref           #389.#585     // com/fasterxml/jackson/core/JsonParser$NumberType.DOUBLE:Lcom/fasterxml/jackson/core/JsonParser$NumberType;
  #108 = Methodref          #231.#586     // com/fasterxml/jackson/core/base/ParserBase._parseIntValue:()I
  #109 = Methodref          #231.#587     // com/fasterxml/jackson/core/base/ParserBase.convertNumberToInt:()V
  #110 = Methodref          #231.#588     // com/fasterxml/jackson/core/base/ParserBase.convertNumberToLong:()V
  #111 = Methodref          #231.#589     // com/fasterxml/jackson/core/base/ParserBase.convertNumberToBigInteger:()V
  #112 = Methodref          #231.#590     // com/fasterxml/jackson/core/base/ParserBase.getDoubleValue:()D
  #113 = Methodref          #231.#591     // com/fasterxml/jackson/core/base/ParserBase.convertNumberToDouble:()V
  #114 = Methodref          #231.#592     // com/fasterxml/jackson/core/base/ParserBase.convertNumberToBigDecimal:()V
  #115 = String             #593          // Internal error: _parseNumericValue called when parser instance closed
  #116 = Methodref          #539.#594     // com/fasterxml/jackson/core/util/TextBuffer.contentsAsInt:(Z)I
  #117 = Methodref          #539.#595     // com/fasterxml/jackson/core/util/TextBuffer.contentsAsLong:(Z)J
  #118 = Long               -2147483648l
  #120 = Long               2147483647l
  #122 = Methodref          #231.#596     // com/fasterxml/jackson/core/base/ParserBase._parseSlowInt:(I)V
  #123 = Methodref          #231.#597     // com/fasterxml/jackson/core/base/ParserBase._parseSlowFloat:(I)V
  #124 = String             #598          // Current token (%s) not numeric, can not use numeric value accessors
  #125 = Methodref          #231.#599     // com/fasterxml/jackson/core/base/ParserBase._reportError:(Ljava/lang/String;Ljava/lang/Object;)V
  #126 = Methodref          #539.#600     // com/fasterxml/jackson/core/util/TextBuffer.contentsAsDecimal:()Ljava/math/BigDecimal;
  #127 = Methodref          #539.#601     // com/fasterxml/jackson/core/util/TextBuffer.contentsAsDouble:()D
  #128 = Class              #602          // java/lang/NumberFormatException
  #129 = String             #603          // Malformed numeric value (
  #130 = Methodref          #539.#604     // com/fasterxml/jackson/core/util/TextBuffer.contentsAsString:()Ljava/lang/String;
  #131 = Methodref          #231.#605     // com/fasterxml/jackson/core/base/ParserBase._longNumberDesc:(Ljava/lang/String;)Ljava/lang/String;
  #132 = String             #606          // )
  #133 = Methodref          #231.#607     // com/fasterxml/jackson/core/base/ParserBase._wrapError:(Ljava/lang/String;Ljava/lang/Throwable;)V
  #134 = Methodref          #539.#608     // com/fasterxml/jackson/core/util/TextBuffer.getTextBuffer:()[C
  #135 = Methodref          #539.#609     // com/fasterxml/jackson/core/util/TextBuffer.getTextOffset:()I
  #136 = Methodref          #610.#611     // com/fasterxml/jackson/core/io/NumberInput.inLongRange:([CIIZ)Z
  #137 = Methodref          #575.#612     // java/lang/Long.parseLong:(Ljava/lang/String;)J
  #138 = Methodref          #231.#613     // com/fasterxml/jackson/core/base/ParserBase._reportTooLongIntegral:(ILjava/lang/String;)V
  #139 = Methodref          #610.#614     // com/fasterxml/jackson/core/io/NumberInput.parseDouble:(Ljava/lang/String;)D
  #140 = Class              #615          // java/math/BigInteger
  #141 = Methodref          #140.#616     // java/math/BigInteger."<init>":(Ljava/lang/String;)V
  #142 = Methodref          #231.#617     // com/fasterxml/jackson/core/base/ParserBase.reportOverflowInt:(Ljava/lang/String;)V
  #143 = Methodref          #231.#618     // com/fasterxml/jackson/core/base/ParserBase.reportOverflowLong:(Ljava/lang/String;)V
  #144 = Methodref          #231.#619     // com/fasterxml/jackson/core/base/ParserBase.currentToken:()Lcom/fasterxml/jackson/core/JsonToken;
  #145 = Methodref          #231.#620     // com/fasterxml/jackson/core/base/ParserBase.reportOverflowInt:(Ljava/lang/String;Lcom/fasterxml/jackson/core/JsonToken;)V
  #146 = Fieldref           #231.#621     // com/fasterxml/jackson/core/base/ParserBase.BI_MIN_INT:Ljava/math/BigInteger;
  #147 = Methodref          #140.#622     // java/math/BigInteger.compareTo:(Ljava/math/BigInteger;)I
  #148 = Fieldref           #231.#623     // com/fasterxml/jackson/core/base/ParserBase.BI_MAX_INT:Ljava/math/BigInteger;
  #149 = Methodref          #231.#624     // com/fasterxml/jackson/core/base/ParserBase.reportOverflowInt:()V
  #150 = Methodref          #140.#625     // java/math/BigInteger.intValue:()I
  #151 = Double             -2.147483648E9d
  #153 = Double             2.147483647E9d
  #155 = Fieldref           #231.#626     // com/fasterxml/jackson/core/base/ParserBase.BD_MIN_INT:Ljava/math/BigDecimal;
  #156 = Methodref          #176.#627     // java/math/BigDecimal.compareTo:(Ljava/math/BigDecimal;)I
  #157 = Fieldref           #231.#628     // com/fasterxml/jackson/core/base/ParserBase.BD_MAX_INT:Ljava/math/BigDecimal;
  #158 = Methodref          #176.#625     // java/math/BigDecimal.intValue:()I
  #159 = Fieldref           #231.#629     // com/fasterxml/jackson/core/base/ParserBase.BI_MIN_LONG:Ljava/math/BigInteger;
  #160 = Fieldref           #231.#630     // com/fasterxml/jackson/core/base/ParserBase.BI_MAX_LONG:Ljava/math/BigInteger;
  #161 = Methodref          #231.#631     // com/fasterxml/jackson/core/base/ParserBase.reportOverflowLong:()V
  #162 = Methodref          #140.#632     // java/math/BigInteger.longValue:()J
  #163 = Double             -9.223372036854776E18d
  #165 = Double             9.223372036854776E18d
  #167 = Fieldref           #231.#633     // com/fasterxml/jackson/core/base/ParserBase.BD_MIN_LONG:Ljava/math/BigDecimal;
  #168 = Fieldref           #231.#634     // com/fasterxml/jackson/core/base/ParserBase.BD_MAX_LONG:Ljava/math/BigDecimal;
  #169 = Methodref          #176.#632     // java/math/BigDecimal.longValue:()J
  #170 = Methodref          #176.#635     // java/math/BigDecimal.toBigInteger:()Ljava/math/BigInteger;
  #171 = Methodref          #140.#636     // java/math/BigInteger.valueOf:(J)Ljava/math/BigInteger;
  #172 = Methodref          #176.#637     // java/math/BigDecimal.valueOf:(D)Ljava/math/BigDecimal;
  #173 = Methodref          #176.#638     // java/math/BigDecimal.doubleValue:()D
  #174 = Methodref          #140.#638     // java/math/BigInteger.doubleValue:()D
  #175 = Methodref          #610.#639     // com/fasterxml/jackson/core/io/NumberInput.parseBigDecimal:(Ljava/lang/String;)Ljava/math/BigDecimal;
  #176 = Class              #640          // java/math/BigDecimal
  #177 = Methodref          #176.#641     // java/math/BigDecimal."<init>":(Ljava/math/BigInteger;)V
  #178 = Methodref          #176.#642     // java/math/BigDecimal.valueOf:(J)Ljava/math/BigDecimal;
  #179 = Methodref          #231.#643     // com/fasterxml/jackson/core/base/ParserBase.getParsingContext:()Lcom/fasterxml/jackson/core/json/JsonReadContext;
  #180 = String             #644          // Unexpected close marker \'%s\': expected \'%c\' (for %s starting at %s)
  #181 = Methodref          #645.#646     // java/lang/Character.valueOf:(C)Ljava/lang/Character;
  #182 = Methodref          #484.#647     // com/fasterxml/jackson/core/json/JsonReadContext.typeDesc:()Ljava/lang/String;
  #183 = Fieldref           #300.#648     // com/fasterxml/jackson/core/JsonParser$Feature.ALLOW_BACKSLASH_ESCAPING_ANY_CHARACTER:Lcom/fasterxml/jackson/core/JsonParser$Feature;
  #184 = Methodref          #231.#649     // com/fasterxml/jackson/core/base/ParserBase.isEnabled:(Lcom/fasterxml/jackson/core/JsonParser$Feature;)Z
  #185 = Fieldref           #300.#650     // com/fasterxml/jackson/core/JsonParser$Feature.ALLOW_SINGLE_QUOTES:Lcom/fasterxml/jackson/core/JsonParser$Feature;
  #186 = String             #651          // Unrecognized character escape
  #187 = Methodref          #231.#652     // com/fasterxml/jackson/core/base/ParserBase._getCharDesc:(I)Ljava/lang/String;
  #188 = Fieldref           #300.#653     // com/fasterxml/jackson/core/JsonParser$Feature.ALLOW_UNQUOTED_CONTROL_CHARS:Lcom/fasterxml/jackson/core/JsonParser$Feature;
  #189 = String             #654          // Illegal unquoted character (
  #190 = String             #655          // ): has to be escaped using backslash to be included in
  #191 = Methodref          #231.#656     // com/fasterxml/jackson/core/base/ParserBase._validJsonValueList:()Ljava/lang/String;
  #192 = Fieldref           #300.#657     // com/fasterxml/jackson/core/JsonParser$Feature.ALLOW_NON_NUMERIC_NUMBERS:Lcom/fasterxml/jackson/core/JsonParser$Feature;
  #193 = String             #658          // (JSON String, Number (or \'NaN\'/\'INF\'/\'+INF\'), Array, Object or token \'null\', \'true\' or \'false\')
  #194 = String             #659          // (JSON String, Number, Array, Object or token \'null\', \'true\' or \'false\')
  #195 = Class              #660          // java/lang/UnsupportedOperationException
  #196 = Methodref          #195.#526     // java/lang/UnsupportedOperationException."<init>":()V
  #197 = Methodref          #231.#661     // com/fasterxml/jackson/core/base/ParserBase.reportInvalidBase64Char:(Lcom/fasterxml/jackson/core/Base64Variant;II)Ljava/lang/IllegalArgumentException;
  #198 = Methodref          #231.#662     // com/fasterxml/jackson/core/base/ParserBase._decodeEscaped:()C
  #199 = Methodref          #200.#663     // com/fasterxml/jackson/core/Base64Variant.decodeBase64Char:(I)I
  #200 = Class              #664          // com/fasterxml/jackson/core/Base64Variant
  #201 = Methodref          #200.#665     // com/fasterxml/jackson/core/Base64Variant.decodeBase64Char:(C)I
  #202 = Methodref          #231.#666     // com/fasterxml/jackson/core/base/ParserBase.reportInvalidBase64Char:(Lcom/fasterxml/jackson/core/Base64Variant;IILjava/lang/String;)Ljava/lang/IllegalArgumentException;
  #203 = String             #667          // Illegal white space character (code 0x%s) as character #%d of 4-char base64 unit: can only used between units
  #204 = Methodref          #572.#668     // java/lang/Integer.toHexString:(I)Ljava/lang/String;
  #205 = Methodref          #200.#669     // com/fasterxml/jackson/core/Base64Variant.usesPaddingChar:(I)Z
  #206 = String             #670          // Unexpected padding character (\'
  #207 = Methodref          #200.#671     // com/fasterxml/jackson/core/Base64Variant.getPaddingChar:()C
  #208 = Methodref          #51.#672      // java/lang/StringBuilder.append:(C)Ljava/lang/StringBuilder;
  #209 = String             #673          // \') as character #
  #210 = Methodref          #51.#674      // java/lang/StringBuilder.append:(I)Ljava/lang/StringBuilder;
  #211 = String             #675          //  of 4-char base64 unit: padding only legal as 3rd or 4th character
  #212 = Methodref          #645.#676     // java/lang/Character.isDefined:(I)Z
  #213 = Methodref          #645.#677     // java/lang/Character.isISOControl:(I)Z
  #214 = String             #678          // Illegal character (code 0x
  #215 = String             #679          // ) in base64 content
  #216 = String             #680          // Illegal character \'
  #217 = String             #681          // \' (code 0x
  #218 = String             #682          // :
  #219 = Class              #683          // java/lang/IllegalArgumentException
  #220 = Methodref          #219.#616     // java/lang/IllegalArgumentException."<init>":(Ljava/lang/String;)V
  #221 = Methodref          #200.#684     // com/fasterxml/jackson/core/Base64Variant.missingPaddingMessage:()Ljava/lang/String;
  #222 = Fieldref           #300.#685     // com/fasterxml/jackson/core/JsonParser$Feature.INCLUDE_SOURCE_IN_LOCATION:Lcom/fasterxml/jackson/core/JsonParser$Feature;
  #223 = Methodref          #477.#686     // com/fasterxml/jackson/core/io/IOContext.contentReference:()Lcom/fasterxml/jackson/core/io/ContentReference;
  #224 = Methodref          #687.#688     // com/fasterxml/jackson/core/io/ContentReference.getRawContent:()Ljava/lang/Object;
  #225 = Methodref          #687.#689     // com/fasterxml/jackson/core/io/ContentReference.unknown:()Lcom/fasterxml/jackson/core/io/ContentReference;
  #226 = Methodref          #690.#691     // java/util/Arrays.copyOf:([II)[I
  #227 = Methodref          #231.#692     // com/fasterxml/jackson/core/base/ParserBase.loadMore:()Z
  #228 = Methodref          #231.#693     // com/fasterxml/jackson/core/base/ParserBase._reportInvalidEOF:()V
  #229 = Fieldref           #231.#694     // com/fasterxml/jackson/core/base/ParserBase.DEFAULT_READ_CAPABILITIES:Lcom/fasterxml/jackson/core/util/JacksonFeatureSet;
  #230 = Fieldref           #231.#695     // com/fasterxml/jackson/core/base/ParserBase.JSON_READ_CAPABILITIES:Lcom/fasterxml/jackson/core/util/JacksonFeatureSet;
  #231 = Class              #696          // com/fasterxml/jackson/core/base/ParserBase
  #232 = Utf8               JSON_READ_CAPABILITIES
  #233 = Utf8               Lcom/fasterxml/jackson/core/util/JacksonFeatureSet;
  #234 = Utf8               Signature
  #235 = Utf8               Lcom/fasterxml/jackson/core/util/JacksonFeatureSet<Lcom/fasterxml/jackson/core/StreamReadCapability;>;
  #236 = Utf8               _ioContext
  #237 = Utf8               Lcom/fasterxml/jackson/core/io/IOContext;
  #238 = Utf8               _closed
  #239 = Utf8               Z
  #240 = Utf8               _inputPtr
  #241 = Utf8               I
  #242 = Utf8               _inputEnd
  #243 = Utf8               _currInputProcessed
  #244 = Utf8               J
  #245 = Utf8               _currInputRow
  #246 = Utf8               _currInputRowStart
  #247 = Utf8               _tokenInputTotal
  #248 = Utf8               _tokenInputRow
  #249 = Utf8               _tokenInputCol
  #250 = Utf8               _parsingContext
  #251 = Utf8               Lcom/fasterxml/jackson/core/json/JsonReadContext;
  #252 = Utf8               _nextToken
  #253 = Utf8               Lcom/fasterxml/jackson/core/JsonToken;
  #254 = Utf8               _textBuffer
  #255 = Utf8               Lcom/fasterxml/jackson/core/util/TextBuffer;
  #256 = Utf8               _nameCopyBuffer
  #257 = Utf8               [C
  #258 = Utf8               _nameCopied
  #259 = Utf8               _byteArrayBuilder
  #260 = Utf8               Lcom/fasterxml/jackson/core/util/ByteArrayBuilder;
  #261 = Utf8               _binaryValue
  #262 = Utf8               [B
  #263 = Utf8               _numTypesValid
  #264 = Utf8               _numberInt
  #265 = Utf8               _numberLong
  #266 = Utf8               _numberDouble
  #267 = Utf8               D
  #268 = Utf8               _numberBigInt
  #269 = Utf8               Ljava/math/BigInteger;
  #270 = Utf8               _numberBigDecimal
  #271 = Utf8               Ljava/math/BigDecimal;
  #272 = Utf8               _numberNegative
  #273 = Utf8               _intLength
  #274 = Utf8               _fractLength
  #275 = Utf8               _expLength
  #276 = Utf8               <init>
  #277 = Utf8               (Lcom/fasterxml/jackson/core/io/IOContext;I)V
  #278 = Utf8               Code
  #279 = Utf8               LineNumberTable
  #280 = Utf8               LocalVariableTable
  #281 = Utf8               this
  #282 = Utf8               Lcom/fasterxml/jackson/core/base/ParserBase;
  #283 = Utf8               ctxt
  #284 = Utf8               features
  #285 = Utf8               dups
  #286 = Utf8               Lcom/fasterxml/jackson/core/json/DupDetector;
  #287 = Utf8               StackMapTable
  #288 = Class              #696          // com/fasterxml/jackson/core/base/ParserBase
  #289 = Class              #697          // com/fasterxml/jackson/core/io/IOContext
  #290 = Class              #698          // com/fasterxml/jackson/core/json/DupDetector
  #291 = Utf8               version
  #292 = Utf8               ()Lcom/fasterxml/jackson/core/Version;
  #293 = Utf8               getCurrentValue
  #294 = Utf8               ()Ljava/lang/Object;
  #295 = Utf8               setCurrentValue
  #296 = Utf8               (Ljava/lang/Object;)V
  #297 = Utf8               v
  #298 = Utf8               Ljava/lang/Object;
  #299 = Utf8               enable
  #300 = Class              #700          // com/fasterxml/jackson/core/JsonParser$Feature
  #301 = Utf8               Feature
  #302 = Utf8               InnerClasses
  #303 = Utf8               (Lcom/fasterxml/jackson/core/JsonParser$Feature;)Lcom/fasterxml/jackson/core/JsonParser;
  #304 = Utf8               f
  #305 = Utf8               Lcom/fasterxml/jackson/core/JsonParser$Feature;
  #306 = Utf8               disable
  #307 = Utf8               setFeatureMask
  #308 = Utf8               (I)Lcom/fasterxml/jackson/core/JsonParser;
  #309 = Utf8               newMask
  #310 = Utf8               changes
  #311 = Utf8               Deprecated
  #312 = Utf8               RuntimeVisibleAnnotations
  #313 = Utf8               Ljava/lang/Deprecated;
  #314 = Utf8               overrideStdFeatures
  #315 = Utf8               (II)Lcom/fasterxml/jackson/core/JsonParser;
  #316 = Utf8               values
  #317 = Utf8               mask
  #318 = Utf8               oldState
  #319 = Utf8               newState
  #320 = Utf8               changed
  #321 = Utf8               _checkStdFeatureChanges
  #322 = Utf8               (II)V
  #323 = Utf8               newFeatureFlags
  #324 = Utf8               changedFeatures
  #325 = Utf8               getCurrentName
  #326 = Utf8               ()Ljava/lang/String;
  #327 = Utf8               parent
  #328 = Utf8               Exceptions
  #329 = Utf8               overrideCurrentName
  #330 = Utf8               (Ljava/lang/String;)V
  #331 = Utf8               e
  #332 = Utf8               Ljava/io/IOException;
  #333 = Utf8               name
  #334 = Utf8               Ljava/lang/String;
  #335 = Class              #701          // com/fasterxml/jackson/core/json/JsonReadContext
  #336 = Class              #503          // java/io/IOException
  #337 = Utf8               close
  #338 = Utf8               ()V
  #339 = Class              #702          // java/lang/Throwable
  #340 = Utf8               isClosed
  #341 = Utf8               ()Z
  #342 = Utf8               getParsingContext
  #343 = Utf8               ()Lcom/fasterxml/jackson/core/json/JsonReadContext;
  #344 = Utf8               getTokenLocation
  #345 = Utf8               ()Lcom/fasterxml/jackson/core/JsonLocation;
  #346 = Utf8               getCurrentLocation
  #347 = Utf8               col
  #348 = Utf8               hasTextCharacters
  #349 = Utf8               getBinaryValue
  #350 = Utf8               (Lcom/fasterxml/jackson/core/Base64Variant;)[B
  #351 = Utf8               builder
  #352 = Utf8               variant
  #353 = Utf8               Lcom/fasterxml/jackson/core/Base64Variant;
  #354 = Utf8               getTokenCharacterOffset
  #355 = Utf8               ()J
  #356 = Utf8               getTokenLineNr
  #357 = Utf8               ()I
  #358 = Utf8               getTokenColumnNr
  #359 = Utf8               _closeInput
  #360 = Utf8               _releaseBuffers
  #361 = Utf8               buf
  #362 = Class              #257          // "[C"
  #363 = Utf8               _handleEOF
  #364 = Utf8               marker
  #365 = Class              #703          // java/lang/String
  #366 = Class              #704          // com/fasterxml/jackson/core/JsonParseException
  #367 = Utf8               _eofAsNextChar
  #368 = Utf8               _getByteArrayBuilder
  #369 = Utf8               ()Lcom/fasterxml/jackson/core/util/ByteArrayBuilder;
  #370 = Utf8               reset
  #371 = Utf8               (ZIII)Lcom/fasterxml/jackson/core/JsonToken;
  #372 = Utf8               negative
  #373 = Utf8               intLen
  #374 = Utf8               fractLen
  #375 = Utf8               expLen
  #376 = Utf8               resetInt
  #377 = Utf8               (ZI)Lcom/fasterxml/jackson/core/JsonToken;
  #378 = Utf8               resetFloat
  #379 = Utf8               resetAsNaN
  #380 = Utf8               (Ljava/lang/String;D)Lcom/fasterxml/jackson/core/JsonToken;
  #381 = Utf8               valueStr
  #382 = Utf8               value
  #383 = Utf8               isNaN
  #384 = Utf8               d
  #385 = Utf8               getNumberValue
  #386 = Utf8               ()Ljava/lang/Number;
  #387 = Utf8               getNumberValueExact
  #388 = Utf8               getNumberType
  #389 = Class              #705          // com/fasterxml/jackson/core/JsonParser$NumberType
  #390 = Utf8               NumberType
  #391 = Utf8               ()Lcom/fasterxml/jackson/core/JsonParser$NumberType;
  #392 = Utf8               getIntValue
  #393 = Utf8               getLongValue
  #394 = Utf8               getBigIntegerValue
  #395 = Utf8               ()Ljava/math/BigInteger;
  #396 = Utf8               getFloatValue
  #397 = Utf8               ()F
  #398 = Utf8               getDoubleValue
  #399 = Utf8               ()D
  #400 = Utf8               getDecimalValue
  #401 = Utf8               ()Ljava/math/BigDecimal;
  #402 = Utf8               _parseNumericValue
  #403 = Utf8               (I)V
  #404 = Utf8               i
  #405 = Utf8               l
  #406 = Utf8               len
  #407 = Utf8               expType
  #408 = Utf8               _parseIntValue
  #409 = Utf8               _parseSlowFloat
  #410 = Utf8               nex
  #411 = Utf8               Ljava/lang/NumberFormatException;
  #412 = Class              #602          // java/lang/NumberFormatException
  #413 = Utf8               _parseSlowInt
  #414 = Utf8               offset
  #415 = Utf8               numStr
  #416 = Utf8               _reportTooLongIntegral
  #417 = Utf8               (ILjava/lang/String;)V
  #418 = Utf8               rawNum
  #419 = Utf8               convertNumberToInt
  #420 = Utf8               result
  #421 = Utf8               convertNumberToLong
  #422 = Utf8               convertNumberToBigInteger
  #423 = Utf8               convertNumberToDouble
  #424 = Utf8               convertNumberToBigDecimal
  #425 = Utf8               _reportMismatchedEndMarker
  #426 = Utf8               (IC)V
  #427 = Utf8               actCh
  #428 = Utf8               expCh
  #429 = Utf8               C
  #430 = Utf8               _handleUnrecognizedCharacterEscape
  #431 = Utf8               (C)C
  #432 = Utf8               ch
  #433 = Class              #706          // com/fasterxml/jackson/core/JsonProcessingException
  #434 = Utf8               _throwUnquotedSpace
  #435 = Utf8               c
  #436 = Utf8               msg
  #437 = Utf8               ctxtDesc
  #438 = Utf8               _validJsonTokenList
  #439 = Utf8               _validJsonValueList
  #440 = Utf8               _decodeEscaped
  #441 = Utf8               ()C
  #442 = Utf8               _decodeBase64Escape
  #443 = Utf8               (Lcom/fasterxml/jackson/core/Base64Variant;II)I
  #444 = Utf8               b64variant
  #445 = Utf8               index
  #446 = Utf8               unescaped
  #447 = Utf8               bits
  #448 = Utf8               (Lcom/fasterxml/jackson/core/Base64Variant;CI)I
  #449 = Utf8               reportInvalidBase64Char
  #450 = Utf8               (Lcom/fasterxml/jackson/core/Base64Variant;II)Ljava/lang/IllegalArgumentException;
  #451 = Utf8               bindex
  #452 = Utf8               (Lcom/fasterxml/jackson/core/Base64Variant;IILjava/lang/String;)Ljava/lang/IllegalArgumentException;
  #453 = Utf8               base
  #454 = Utf8               _handleBase64MissingPadding
  #455 = Utf8               (Lcom/fasterxml/jackson/core/Base64Variant;)V
  #456 = Utf8               _getSourceReference
  #457 = Utf8               _contentReference
  #458 = Utf8               ()Lcom/fasterxml/jackson/core/io/ContentReference;
  #459 = Utf8               growArrayBy
  #460 = Utf8               ([II)[I
  #461 = Utf8               arr
  #462 = Utf8               [I
  #463 = Utf8               more
  #464 = Utf8               loadMoreGuaranteed
  #465 = Utf8               loadMore
  #466 = Utf8               _finishString
  #467 = Utf8               ()Lcom/fasterxml/jackson/core/JsonStreamContext;
  #468 = Utf8               <clinit>
  #469 = Utf8               SourceFile
  #470 = Utf8               ParserBase.java
  #471 = NameAndType        #276:#403     // "<init>":(I)V
  #472 = NameAndType        #245:#241     // _currInputRow:I
  #473 = NameAndType        #248:#241     // _tokenInputRow:I
  #474 = Utf8               com/fasterxml/jackson/core/base/ParserMinimalBase
  #475 = NameAndType        #263:#241     // _numTypesValid:I
  #476 = NameAndType        #236:#237     // _ioContext:Lcom/fasterxml/jackson/core/io/IOContext;
  #477 = Class              #697          // com/fasterxml/jackson/core/io/IOContext
  #478 = NameAndType        #707:#708     // constructTextBuffer:()Lcom/fasterxml/jackson/core/util/TextBuffer;
  #479 = NameAndType        #254:#255     // _textBuffer:Lcom/fasterxml/jackson/core/util/TextBuffer;
  #480 = NameAndType        #709:#305     // STRICT_DUPLICATE_DETECTION:Lcom/fasterxml/jackson/core/JsonParser$Feature;
  #481 = NameAndType        #710:#711     // enabledIn:(I)Z
  #482 = Class              #698          // com/fasterxml/jackson/core/json/DupDetector
  #483 = NameAndType        #712:#713     // rootDetector:(Lcom/fasterxml/jackson/core/JsonParser;)Lcom/fasterxml/jackson/core/json/DupDetector;
  #484 = Class              #701          // com/fasterxml/jackson/core/json/JsonReadContext
  #485 = NameAndType        #714:#715     // createRootContext:(Lcom/fasterxml/jackson/core/json/DupDetector;)Lcom/fasterxml/jackson/core/json/JsonReadContext;
  #486 = NameAndType        #250:#251     // _parsingContext:Lcom/fasterxml/jackson/core/json/JsonReadContext;
  #487 = Class              #716          // com/fasterxml/jackson/core/json/PackageVersion
  #488 = NameAndType        #717:#718     // VERSION:Lcom/fasterxml/jackson/core/Version;
  #489 = NameAndType        #293:#294     // getCurrentValue:()Ljava/lang/Object;
  #490 = NameAndType        #295:#296     // setCurrentValue:(Ljava/lang/Object;)V
  #491 = NameAndType        #719:#241     // _features:I
  #492 = NameAndType        #720:#357     // getMask:()I
  #493 = NameAndType        #721:#722     // getDupDetector:()Lcom/fasterxml/jackson/core/json/DupDetector;
  #494 = NameAndType        #723:#715     // withDupDetector:(Lcom/fasterxml/jackson/core/json/DupDetector;)Lcom/fasterxml/jackson/core/json/JsonReadContext;
  #495 = NameAndType        #321:#322     // _checkStdFeatureChanges:(II)V
  #496 = NameAndType        #724:#253     // _currToken:Lcom/fasterxml/jackson/core/JsonToken;
  #497 = Class              #725          // com/fasterxml/jackson/core/JsonToken
  #498 = NameAndType        #726:#253     // START_OBJECT:Lcom/fasterxml/jackson/core/JsonToken;
  #499 = NameAndType        #727:#253     // START_ARRAY:Lcom/fasterxml/jackson/core/JsonToken;
  #500 = NameAndType        #728:#343     // getParent:()Lcom/fasterxml/jackson/core/json/JsonReadContext;
  #501 = NameAndType        #325:#326     // getCurrentName:()Ljava/lang/String;
  #502 = NameAndType        #729:#330     // setCurrentName:(Ljava/lang/String;)V
  #503 = Utf8               java/io/IOException
  #504 = Utf8               java/lang/IllegalStateException
  #505 = NameAndType        #276:#730     // "<init>":(Ljava/lang/Throwable;)V
  #506 = NameAndType        #238:#239     // _closed:Z
  #507 = NameAndType        #240:#241     // _inputPtr:I
  #508 = NameAndType        #242:#241     // _inputEnd:I
  #509 = Class              #731          // java/lang/Math
  #510 = NameAndType        #732:#733     // max:(II)I
  #511 = NameAndType        #359:#338     // _closeInput:()V
  #512 = NameAndType        #360:#338     // _releaseBuffers:()V
  #513 = Utf8               com/fasterxml/jackson/core/JsonLocation
  #514 = NameAndType        #457:#458     // _contentReference:()Lcom/fasterxml/jackson/core/io/ContentReference;
  #515 = NameAndType        #354:#355     // getTokenCharacterOffset:()J
  #516 = NameAndType        #356:#357     // getTokenLineNr:()I
  #517 = NameAndType        #358:#357     // getTokenColumnNr:()I
  #518 = NameAndType        #276:#734     // "<init>":(Lcom/fasterxml/jackson/core/io/ContentReference;JJII)V
  #519 = NameAndType        #246:#241     // _currInputRowStart:I
  #520 = NameAndType        #243:#244     // _currInputProcessed:J
  #521 = NameAndType        #735:#253     // VALUE_STRING:Lcom/fasterxml/jackson/core/JsonToken;
  #522 = NameAndType        #736:#253     // FIELD_NAME:Lcom/fasterxml/jackson/core/JsonToken;
  #523 = NameAndType        #258:#239     // _nameCopied:Z
  #524 = NameAndType        #261:#262     // _binaryValue:[B
  #525 = Utf8               java/lang/StringBuilder
  #526 = NameAndType        #276:#338     // "<init>":()V
  #527 = Utf8               Current token (
  #528 = NameAndType        #737:#738     // append:(Ljava/lang/String;)Ljava/lang/StringBuilder;
  #529 = NameAndType        #737:#739     // append:(Ljava/lang/Object;)Ljava/lang/StringBuilder;
  #530 = Utf8               ) not VALUE_STRING, can not access as binary
  #531 = NameAndType        #740:#326     // toString:()Ljava/lang/String;
  #532 = NameAndType        #741:#330     // _reportError:(Ljava/lang/String;)V
  #533 = NameAndType        #368:#369     // _getByteArrayBuilder:()Lcom/fasterxml/jackson/core/util/ByteArrayBuilder;
  #534 = NameAndType        #742:#326     // getText:()Ljava/lang/String;
  #535 = NameAndType        #743:#744     // _decodeBase64:(Ljava/lang/String;Lcom/fasterxml/jackson/core/util/ByteArrayBuilder;Lcom/fasterxml/jackson/core/Base64Variant;)V
  #536 = NameAndType        #745:#746     // toByteArray:()[B
  #537 = NameAndType        #247:#244     // _tokenInputTotal:J
  #538 = NameAndType        #249:#241     // _tokenInputCol:I
  #539 = Class              #747          // com/fasterxml/jackson/core/util/TextBuffer
  #540 = NameAndType        #748:#338     // releaseBuffers:()V
  #541 = NameAndType        #256:#257     // _nameCopyBuffer:[C
  #542 = NameAndType        #749:#750     // releaseNameCopyBuffer:([C)V
  #543 = NameAndType        #751:#341     // inRoot:()Z
  #544 = NameAndType        #752:#341     // inArray:()Z
  #545 = Utf8               Array
  #546 = Utf8               Object
  #547 = Utf8               : expected close marker for %s (start marker at %s)
  #548 = Utf8               java/lang/Object
  #549 = NameAndType        #753:#754     // startLocation:(Lcom/fasterxml/jackson/core/io/ContentReference;)Lcom/fasterxml/jackson/core/JsonLocation;
  #550 = Class              #703          // java/lang/String
  #551 = NameAndType        #755:#756     // format:(Ljava/lang/String;[Ljava/lang/Object;)Ljava/lang/String;
  #552 = NameAndType        #757:#758     // _reportInvalidEOF:(Ljava/lang/String;Lcom/fasterxml/jackson/core/JsonToken;)V
  #553 = NameAndType        #363:#338     // _handleEOF:()V
  #554 = NameAndType        #259:#260     // _byteArrayBuilder:Lcom/fasterxml/jackson/core/util/ByteArrayBuilder;
  #555 = Utf8               com/fasterxml/jackson/core/util/ByteArrayBuilder
  #556 = NameAndType        #370:#338     // reset:()V
  #557 = NameAndType        #376:#377     // resetInt:(ZI)Lcom/fasterxml/jackson/core/JsonToken;
  #558 = NameAndType        #378:#371     // resetFloat:(ZIII)Lcom/fasterxml/jackson/core/JsonToken;
  #559 = NameAndType        #272:#239     // _numberNegative:Z
  #560 = NameAndType        #273:#241     // _intLength:I
  #561 = NameAndType        #274:#241     // _fractLength:I
  #562 = NameAndType        #275:#241     // _expLength:I
  #563 = NameAndType        #759:#253     // VALUE_NUMBER_INT:Lcom/fasterxml/jackson/core/JsonToken;
  #564 = NameAndType        #760:#253     // VALUE_NUMBER_FLOAT:Lcom/fasterxml/jackson/core/JsonToken;
  #565 = NameAndType        #761:#330     // resetWithString:(Ljava/lang/String;)V
  #566 = NameAndType        #266:#267     // _numberDouble:D
  #567 = Class              #762          // java/lang/Double
  #568 = NameAndType        #383:#763     // isNaN:(D)Z
  #569 = NameAndType        #764:#763     // isInfinite:(D)Z
  #570 = NameAndType        #402:#403     // _parseNumericValue:(I)V
  #571 = NameAndType        #264:#241     // _numberInt:I
  #572 = Class              #765          // java/lang/Integer
  #573 = NameAndType        #766:#767     // valueOf:(I)Ljava/lang/Integer;
  #574 = NameAndType        #265:#244     // _numberLong:J
  #575 = Class              #768          // java/lang/Long
  #576 = NameAndType        #766:#769     // valueOf:(J)Ljava/lang/Long;
  #577 = NameAndType        #268:#269     // _numberBigInt:Ljava/math/BigInteger;
  #578 = NameAndType        #770:#338     // _throwInternal:()V
  #579 = NameAndType        #270:#271     // _numberBigDecimal:Ljava/math/BigDecimal;
  #580 = NameAndType        #766:#771     // valueOf:(D)Ljava/lang/Double;
  #581 = NameAndType        #772:#773     // INT:Lcom/fasterxml/jackson/core/JsonParser$NumberType;
  #582 = NameAndType        #774:#773     // LONG:Lcom/fasterxml/jackson/core/JsonParser$NumberType;
  #583 = NameAndType        #775:#773     // BIG_INTEGER:Lcom/fasterxml/jackson/core/JsonParser$NumberType;
  #584 = NameAndType        #776:#773     // BIG_DECIMAL:Lcom/fasterxml/jackson/core/JsonParser$NumberType;
  #585 = NameAndType        #777:#773     // DOUBLE:Lcom/fasterxml/jackson/core/JsonParser$NumberType;
  #586 = NameAndType        #408:#357     // _parseIntValue:()I
  #587 = NameAndType        #419:#338     // convertNumberToInt:()V
  #588 = NameAndType        #421:#338     // convertNumberToLong:()V
  #589 = NameAndType        #422:#338     // convertNumberToBigInteger:()V
  #590 = NameAndType        #398:#399     // getDoubleValue:()D
  #591 = NameAndType        #423:#338     // convertNumberToDouble:()V
  #592 = NameAndType        #424:#338     // convertNumberToBigDecimal:()V
  #593 = Utf8               Internal error: _parseNumericValue called when parser instance closed
  #594 = NameAndType        #778:#779     // contentsAsInt:(Z)I
  #595 = NameAndType        #780:#781     // contentsAsLong:(Z)J
  #596 = NameAndType        #413:#403     // _parseSlowInt:(I)V
  #597 = NameAndType        #409:#403     // _parseSlowFloat:(I)V
  #598 = Utf8               Current token (%s) not numeric, can not use numeric value accessors
  #599 = NameAndType        #741:#782     // _reportError:(Ljava/lang/String;Ljava/lang/Object;)V
  #600 = NameAndType        #783:#401     // contentsAsDecimal:()Ljava/math/BigDecimal;
  #601 = NameAndType        #784:#399     // contentsAsDouble:()D
  #602 = Utf8               java/lang/NumberFormatException
  #603 = Utf8               Malformed numeric value (
  #604 = NameAndType        #785:#326     // contentsAsString:()Ljava/lang/String;
  #605 = NameAndType        #786:#787     // _longNumberDesc:(Ljava/lang/String;)Ljava/lang/String;
  #606 = Utf8               )
  #607 = NameAndType        #788:#789     // _wrapError:(Ljava/lang/String;Ljava/lang/Throwable;)V
  #608 = NameAndType        #790:#791     // getTextBuffer:()[C
  #609 = NameAndType        #792:#357     // getTextOffset:()I
  #610 = Class              #793          // com/fasterxml/jackson/core/io/NumberInput
  #611 = NameAndType        #794:#795     // inLongRange:([CIIZ)Z
  #612 = NameAndType        #796:#797     // parseLong:(Ljava/lang/String;)J
  #613 = NameAndType        #416:#417     // _reportTooLongIntegral:(ILjava/lang/String;)V
  #614 = NameAndType        #798:#799     // parseDouble:(Ljava/lang/String;)D
  #615 = Utf8               java/math/BigInteger
  #616 = NameAndType        #276:#330     // "<init>":(Ljava/lang/String;)V
  #617 = NameAndType        #800:#330     // reportOverflowInt:(Ljava/lang/String;)V
  #618 = NameAndType        #801:#330     // reportOverflowLong:(Ljava/lang/String;)V
  #619 = NameAndType        #802:#803     // currentToken:()Lcom/fasterxml/jackson/core/JsonToken;
  #620 = NameAndType        #800:#758     // reportOverflowInt:(Ljava/lang/String;Lcom/fasterxml/jackson/core/JsonToken;)V
  #621 = NameAndType        #804:#269     // BI_MIN_INT:Ljava/math/BigInteger;
  #622 = NameAndType        #805:#806     // compareTo:(Ljava/math/BigInteger;)I
  #623 = NameAndType        #807:#269     // BI_MAX_INT:Ljava/math/BigInteger;
  #624 = NameAndType        #800:#338     // reportOverflowInt:()V
  #625 = NameAndType        #808:#357     // intValue:()I
  #626 = NameAndType        #809:#271     // BD_MIN_INT:Ljava/math/BigDecimal;
  #627 = NameAndType        #805:#810     // compareTo:(Ljava/math/BigDecimal;)I
  #628 = NameAndType        #811:#271     // BD_MAX_INT:Ljava/math/BigDecimal;
  #629 = NameAndType        #812:#269     // BI_MIN_LONG:Ljava/math/BigInteger;
  #630 = NameAndType        #813:#269     // BI_MAX_LONG:Ljava/math/BigInteger;
  #631 = NameAndType        #801:#338     // reportOverflowLong:()V
  #632 = NameAndType        #814:#355     // longValue:()J
  #633 = NameAndType        #815:#271     // BD_MIN_LONG:Ljava/math/BigDecimal;
  #634 = NameAndType        #816:#271     // BD_MAX_LONG:Ljava/math/BigDecimal;
  #635 = NameAndType        #817:#395     // toBigInteger:()Ljava/math/BigInteger;
  #636 = NameAndType        #766:#818     // valueOf:(J)Ljava/math/BigInteger;
  #637 = NameAndType        #766:#819     // valueOf:(D)Ljava/math/BigDecimal;
  #638 = NameAndType        #820:#399     // doubleValue:()D
  #639 = NameAndType        #821:#822     // parseBigDecimal:(Ljava/lang/String;)Ljava/math/BigDecimal;
  #640 = Utf8               java/math/BigDecimal
  #641 = NameAndType        #276:#823     // "<init>":(Ljava/math/BigInteger;)V
  #642 = NameAndType        #766:#824     // valueOf:(J)Ljava/math/BigDecimal;
  #643 = NameAndType        #342:#343     // getParsingContext:()Lcom/fasterxml/jackson/core/json/JsonReadContext;
  #644 = Utf8               Unexpected close marker \'%s\': expected \'%c\' (for %s starting at %s)
  #645 = Class              #825          // java/lang/Character
  #646 = NameAndType        #766:#826     // valueOf:(C)Ljava/lang/Character;
  #647 = NameAndType        #827:#326     // typeDesc:()Ljava/lang/String;
  #648 = NameAndType        #828:#305     // ALLOW_BACKSLASH_ESCAPING_ANY_CHARACTER:Lcom/fasterxml/jackson/core/JsonParser$Feature;
  #649 = NameAndType        #829:#830     // isEnabled:(Lcom/fasterxml/jackson/core/JsonParser$Feature;)Z
  #650 = NameAndType        #831:#305     // ALLOW_SINGLE_QUOTES:Lcom/fasterxml/jackson/core/JsonParser$Feature;
  #651 = Utf8               Unrecognized character escape
  #652 = NameAndType        #832:#833     // _getCharDesc:(I)Ljava/lang/String;
  #653 = NameAndType        #834:#305     // ALLOW_UNQUOTED_CONTROL_CHARS:Lcom/fasterxml/jackson/core/JsonParser$Feature;
  #654 = Utf8               Illegal unquoted character (
  #655 = Utf8               ): has to be escaped using backslash to be included in
  #656 = NameAndType        #439:#326     // _validJsonValueList:()Ljava/lang/String;
  #657 = NameAndType        #835:#305     // ALLOW_NON_NUMERIC_NUMBERS:Lcom/fasterxml/jackson/core/JsonParser$Feature;
  #658 = Utf8               (JSON String, Number (or \'NaN\'/\'INF\'/\'+INF\'), Array, Object or token \'null\', \'true\' or \'false\')
  #659 = Utf8               (JSON String, Number, Array, Object or token \'null\', \'true\' or \'false\')
  #660 = Utf8               java/lang/UnsupportedOperationException
  #661 = NameAndType        #449:#450     // reportInvalidBase64Char:(Lcom/fasterxml/jackson/core/Base64Variant;II)Ljava/lang/IllegalArgumentException;
  #662 = NameAndType        #440:#441     // _decodeEscaped:()C
  #663 = NameAndType        #836:#837     // decodeBase64Char:(I)I
  #664 = Utf8               com/fasterxml/jackson/core/Base64Variant
  #665 = NameAndType        #836:#838     // decodeBase64Char:(C)I
  #666 = NameAndType        #449:#452     // reportInvalidBase64Char:(Lcom/fasterxml/jackson/core/Base64Variant;IILjava/lang/String;)Ljava/lang/IllegalArgumentException;
  #667 = Utf8               Illegal white space character (code 0x%s) as character #%d of 4-char base64 unit: can only used between units
  #668 = NameAndType        #839:#833     // toHexString:(I)Ljava/lang/String;
  #669 = NameAndType        #840:#711     // usesPaddingChar:(I)Z
  #670 = Utf8               Unexpected padding character (\'
  #671 = NameAndType        #841:#441     // getPaddingChar:()C
  #672 = NameAndType        #737:#842     // append:(C)Ljava/lang/StringBuilder;
  #673 = Utf8               \') as character #
  #674 = NameAndType        #737:#843     // append:(I)Ljava/lang/StringBuilder;
  #675 = Utf8                of 4-char base64 unit: padding only legal as 3rd or 4th character
  #676 = NameAndType        #844:#711     // isDefined:(I)Z
  #677 = NameAndType        #845:#711     // isISOControl:(I)Z
  #678 = Utf8               Illegal character (code 0x
  #679 = Utf8               ) in base64 content
  #680 = Utf8               Illegal character \'
  #681 = Utf8               \' (code 0x
  #682 = Utf8               :
  #683 = Utf8               java/lang/IllegalArgumentException
  #684 = NameAndType        #846:#326     // missingPaddingMessage:()Ljava/lang/String;
  #685 = NameAndType        #847:#305     // INCLUDE_SOURCE_IN_LOCATION:Lcom/fasterxml/jackson/core/JsonParser$Feature;
  #686 = NameAndType        #848:#458     // contentReference:()Lcom/fasterxml/jackson/core/io/ContentReference;
  #687 = Class              #849          // com/fasterxml/jackson/core/io/ContentReference
  #688 = NameAndType        #850:#294     // getRawContent:()Ljava/lang/Object;
  #689 = NameAndType        #851:#458     // unknown:()Lcom/fasterxml/jackson/core/io/ContentReference;
  #690 = Class              #852          // java/util/Arrays
  #691 = NameAndType        #853:#460     // copyOf:([II)[I
  #692 = NameAndType        #465:#341     // loadMore:()Z
  #693 = NameAndType        #757:#338     // _reportInvalidEOF:()V
  #694 = NameAndType        #854:#233     // DEFAULT_READ_CAPABILITIES:Lcom/fasterxml/jackson/core/util/JacksonFeatureSet;
  #695 = NameAndType        #232:#233     // JSON_READ_CAPABILITIES:Lcom/fasterxml/jackson/core/util/JacksonFeatureSet;
  #696 = Utf8               com/fasterxml/jackson/core/base/ParserBase
  #697 = Utf8               com/fasterxml/jackson/core/io/IOContext
  #698 = Utf8               com/fasterxml/jackson/core/json/DupDetector
  #699 = Class              #855          // com/fasterxml/jackson/core/JsonParser
  #700 = Utf8               com/fasterxml/jackson/core/JsonParser$Feature
  #701 = Utf8               com/fasterxml/jackson/core/json/JsonReadContext
  #702 = Utf8               java/lang/Throwable
  #703 = Utf8               java/lang/String
  #704 = Utf8               com/fasterxml/jackson/core/JsonParseException
  #705 = Utf8               com/fasterxml/jackson/core/JsonParser$NumberType
  #706 = Utf8               com/fasterxml/jackson/core/JsonProcessingException
  #707 = Utf8               constructTextBuffer
  #708 = Utf8               ()Lcom/fasterxml/jackson/core/util/TextBuffer;
  #709 = Utf8               STRICT_DUPLICATE_DETECTION
  #710 = Utf8               enabledIn
  #711 = Utf8               (I)Z
  #712 = Utf8               rootDetector
  #713 = Utf8               (Lcom/fasterxml/jackson/core/JsonParser;)Lcom/fasterxml/jackson/core/json/DupDetector;
  #714 = Utf8               createRootContext
  #715 = Utf8               (Lcom/fasterxml/jackson/core/json/DupDetector;)Lcom/fasterxml/jackson/core/json/JsonReadContext;
  #716 = Utf8               com/fasterxml/jackson/core/json/PackageVersion
  #717 = Utf8               VERSION
  #718 = Utf8               Lcom/fasterxml/jackson/core/Version;
  #719 = Utf8               _features
  #720 = Utf8               getMask
  #721 = Utf8               getDupDetector
  #722 = Utf8               ()Lcom/fasterxml/jackson/core/json/DupDetector;
  #723 = Utf8               withDupDetector
  #724 = Utf8               _currToken
  #725 = Utf8               com/fasterxml/jackson/core/JsonToken
  #726 = Utf8               START_OBJECT
  #727 = Utf8               START_ARRAY
  #728 = Utf8               getParent
  #729 = Utf8               setCurrentName
  #730 = Utf8               (Ljava/lang/Throwable;)V
  #731 = Utf8               java/lang/Math
  #732 = Utf8               max
  #733 = Utf8               (II)I
  #734 = Utf8               (Lcom/fasterxml/jackson/core/io/ContentReference;JJII)V
  #735 = Utf8               VALUE_STRING
  #736 = Utf8               FIELD_NAME
  #737 = Utf8               append
  #738 = Utf8               (Ljava/lang/String;)Ljava/lang/StringBuilder;
  #739 = Utf8               (Ljava/lang/Object;)Ljava/lang/StringBuilder;
  #740 = Utf8               toString
  #741 = Utf8               _reportError
  #742 = Utf8               getText
  #743 = Utf8               _decodeBase64
  #744 = Utf8               (Ljava/lang/String;Lcom/fasterxml/jackson/core/util/ByteArrayBuilder;Lcom/fasterxml/jackson/core/Base64Variant;)V
  #745 = Utf8               toByteArray
  #746 = Utf8               ()[B
  #747 = Utf8               com/fasterxml/jackson/core/util/TextBuffer
  #748 = Utf8               releaseBuffers
  #749 = Utf8               releaseNameCopyBuffer
  #750 = Utf8               ([C)V
  #751 = Utf8               inRoot
  #752 = Utf8               inArray
  #753 = Utf8               startLocation
  #754 = Utf8               (Lcom/fasterxml/jackson/core/io/ContentReference;)Lcom/fasterxml/jackson/core/JsonLocation;
  #755 = Utf8               format
  #756 = Utf8               (Ljava/lang/String;[Ljava/lang/Object;)Ljava/lang/String;
  #757 = Utf8               _reportInvalidEOF
  #758 = Utf8               (Ljava/lang/String;Lcom/fasterxml/jackson/core/JsonToken;)V
  #759 = Utf8               VALUE_NUMBER_INT
  #760 = Utf8               VALUE_NUMBER_FLOAT
  #761 = Utf8               resetWithString
  #762 = Utf8               java/lang/Double
  #763 = Utf8               (D)Z
  #764 = Utf8               isInfinite
  #765 = Utf8               java/lang/Integer
  #766 = Utf8               valueOf
  #767 = Utf8               (I)Ljava/lang/Integer;
  #768 = Utf8               java/lang/Long
  #769 = Utf8               (J)Ljava/lang/Long;
  #770 = Utf8               _throwInternal
  #771 = Utf8               (D)Ljava/lang/Double;
  #772 = Utf8               INT
  #773 = Utf8               Lcom/fasterxml/jackson/core/JsonParser$NumberType;
  #774 = Utf8               LONG
  #775 = Utf8               BIG_INTEGER
  #776 = Utf8               BIG_DECIMAL
  #777 = Utf8               DOUBLE
  #778 = Utf8               contentsAsInt
  #779 = Utf8               (Z)I
  #780 = Utf8               contentsAsLong
  #781 = Utf8               (Z)J
  #782 = Utf8               (Ljava/lang/String;Ljava/lang/Object;)V
  #783 = Utf8               contentsAsDecimal
  #784 = Utf8               contentsAsDouble
  #785 = Utf8               contentsAsString
  #786 = Utf8               _longNumberDesc
  #787 = Utf8               (Ljava/lang/String;)Ljava/lang/String;
  #788 = Utf8               _wrapError
  #789 = Utf8               (Ljava/lang/String;Ljava/lang/Throwable;)V
  #790 = Utf8               getTextBuffer
  #791 = Utf8               ()[C
  #792 = Utf8               getTextOffset
  #793 = Utf8               com/fasterxml/jackson/core/io/NumberInput
  #794 = Utf8               inLongRange
  #795 = Utf8               ([CIIZ)Z
  #796 = Utf8               parseLong
  #797 = Utf8               (Ljava/lang/String;)J
  #798 = Utf8               parseDouble
  #799 = Utf8               (Ljava/lang/String;)D
  #800 = Utf8               reportOverflowInt
  #801 = Utf8               reportOverflowLong
  #802 = Utf8               currentToken
  #803 = Utf8               ()Lcom/fasterxml/jackson/core/JsonToken;
  #804 = Utf8               BI_MIN_INT
  #805 = Utf8               compareTo
  #806 = Utf8               (Ljava/math/BigInteger;)I
  #807 = Utf8               BI_MAX_INT
  #808 = Utf8               intValue
  #809 = Utf8               BD_MIN_INT
  #810 = Utf8               (Ljava/math/BigDecimal;)I
  #811 = Utf8               BD_MAX_INT
  #812 = Utf8               BI_MIN_LONG
  #813 = Utf8               BI_MAX_LONG
  #814 = Utf8               longValue
  #815 = Utf8               BD_MIN_LONG
  #816 = Utf8               BD_MAX_LONG
  #817 = Utf8               toBigInteger
  #818 = Utf8               (J)Ljava/math/BigInteger;
  #819 = Utf8               (D)Ljava/math/BigDecimal;
  #820 = Utf8               doubleValue
  #821 = Utf8               parseBigDecimal
  #822 = Utf8               (Ljava/lang/String;)Ljava/math/BigDecimal;
  #823 = Utf8               (Ljava/math/BigInteger;)V
  #824 = Utf8               (J)Ljava/math/BigDecimal;
  #825 = Utf8               java/lang/Character
  #826 = Utf8               (C)Ljava/lang/Character;
  #827 = Utf8               typeDesc
  #828 = Utf8               ALLOW_BACKSLASH_ESCAPING_ANY_CHARACTER
  #829 = Utf8               isEnabled
  #830 = Utf8               (Lcom/fasterxml/jackson/core/JsonParser$Feature;)Z
  #831 = Utf8               ALLOW_SINGLE_QUOTES
  #832 = Utf8               _getCharDesc
  #833 = Utf8               (I)Ljava/lang/String;
  #834 = Utf8               ALLOW_UNQUOTED_CONTROL_CHARS
  #835 = Utf8               ALLOW_NON_NUMERIC_NUMBERS
  #836 = Utf8               decodeBase64Char
  #837 = Utf8               (I)I
  #838 = Utf8               (C)I
  #839 = Utf8               toHexString
  #840 = Utf8               usesPaddingChar
  #841 = Utf8               getPaddingChar
  #842 = Utf8               (C)Ljava/lang/StringBuilder;
  #843 = Utf8               (I)Ljava/lang/StringBuilder;
  #844 = Utf8               isDefined
  #845 = Utf8               isISOControl
  #846 = Utf8               missingPaddingMessage
  #847 = Utf8               INCLUDE_SOURCE_IN_LOCATION
  #848 = Utf8               contentReference
  #849 = Utf8               com/fasterxml/jackson/core/io/ContentReference
  #850 = Utf8               getRawContent
  #851 = Utf8               unknown
  #852 = Utf8               java/util/Arrays
  #853 = Utf8               copyOf
  #854 = Utf8               DEFAULT_READ_CAPABILITIES
  #855 = Utf8               com/fasterxml/jackson/core/JsonParser
{
  protected static final com.fasterxml.jackson.core.util.JacksonFeatureSet<com.fasterxml.jackson.core.StreamReadCapability> JSON_READ_CAPABILITIES;
    descriptor: Lcom/fasterxml/jackson/core/util/JacksonFeatureSet;
    flags: (0x001c) ACC_PROTECTED, ACC_STATIC, ACC_FINAL
    Signature: #235                         // Lcom/fasterxml/jackson/core/util/JacksonFeatureSet<Lcom/fasterxml/jackson/core/StreamReadCapability;>;

  protected final com.fasterxml.jackson.core.io.IOContext _ioContext;
    descriptor: Lcom/fasterxml/jackson/core/io/IOContext;
    flags: (0x0014) ACC_PROTECTED, ACC_FINAL

  protected boolean _closed;
    descriptor: Z
    flags: (0x0004) ACC_PROTECTED

  protected int _inputPtr;
    descriptor: I
    flags: (0x0004) ACC_PROTECTED

  protected int _inputEnd;
    descriptor: I
    flags: (0x0004) ACC_PROTECTED

  protected long _currInputProcessed;
    descriptor: J
    flags: (0x0004) ACC_PROTECTED

  protected int _currInputRow;
    descriptor: I
    flags: (0x0004) ACC_PROTECTED

  protected int _currInputRowStart;
    descriptor: I
    flags: (0x0004) ACC_PROTECTED

  protected long _tokenInputTotal;
    descriptor: J
    flags: (0x0004) ACC_PROTECTED

  protected int _tokenInputRow;
    descriptor: I
    flags: (0x0004) ACC_PROTECTED

  protected int _tokenInputCol;
    descriptor: I
    flags: (0x0004) ACC_PROTECTED

  protected com.fasterxml.jackson.core.json.JsonReadContext _parsingContext;
    descriptor: Lcom/fasterxml/jackson/core/json/JsonReadContext;
    flags: (0x0004) ACC_PROTECTED

  protected com.fasterxml.jackson.core.JsonToken _nextToken;
    descriptor: Lcom/fasterxml/jackson/core/JsonToken;
    flags: (0x0004) ACC_PROTECTED

  protected final com.fasterxml.jackson.core.util.TextBuffer _textBuffer;
    descriptor: Lcom/fasterxml/jackson/core/util/TextBuffer;
    flags: (0x0014) ACC_PROTECTED, ACC_FINAL

  protected char[] _nameCopyBuffer;
    descriptor: [C
    flags: (0x0004) ACC_PROTECTED

  protected boolean _nameCopied;
    descriptor: Z
    flags: (0x0004) ACC_PROTECTED

  protected com.fasterxml.jackson.core.util.ByteArrayBuilder _byteArrayBuilder;
    descriptor: Lcom/fasterxml/jackson/core/util/ByteArrayBuilder;
    flags: (0x0004) ACC_PROTECTED

  protected byte[] _binaryValue;
    descriptor: [B
    flags: (0x0004) ACC_PROTECTED

  protected int _numTypesValid;
    descriptor: I
    flags: (0x0004) ACC_PROTECTED

  protected int _numberInt;
    descriptor: I
    flags: (0x0004) ACC_PROTECTED

  protected long _numberLong;
    descriptor: J
    flags: (0x0004) ACC_PROTECTED

  protected double _numberDouble;
    descriptor: D
    flags: (0x0004) ACC_PROTECTED

  protected java.math.BigInteger _numberBigInt;
    descriptor: Ljava/math/BigInteger;
    flags: (0x0004) ACC_PROTECTED

  protected java.math.BigDecimal _numberBigDecimal;
    descriptor: Ljava/math/BigDecimal;
    flags: (0x0004) ACC_PROTECTED

  protected boolean _numberNegative;
    descriptor: Z
    flags: (0x0004) ACC_PROTECTED

  protected int _intLength;
    descriptor: I
    flags: (0x0004) ACC_PROTECTED

  protected int _fractLength;
    descriptor: I
    flags: (0x0004) ACC_PROTECTED

  protected int _expLength;
    descriptor: I
    flags: (0x0004) ACC_PROTECTED

  protected com.fasterxml.jackson.core.base.ParserBase(com.fasterxml.jackson.core.io.IOContext, int);
    descriptor: (Lcom/fasterxml/jackson/core/io/IOContext;I)V
    flags: (0x0004) ACC_PROTECTED
    Code:
      stack=2, locals=4, args_size=3
         0: aload_0
         1: iload_2
         2: invokespecial #1                  // Method com/fasterxml/jackson/core/base/ParserMinimalBase."<init>":(I)V
         5: aload_0
         6: iconst_1
         7: putfield      #2                  // Field _currInputRow:I
        10: aload_0
        11: iconst_1
        12: putfield      #3                  // Field _tokenInputRow:I
        15: aload_0
        16: iconst_0
        17: putfield      #5                  // Field _numTypesValid:I
        20: aload_0
        21: aload_1
        22: putfield      #6                  // Field _ioContext:Lcom/fasterxml/jackson/core/io/IOContext;
        25: aload_0
        26: aload_1
        27: invokevirtual #7                  // Method com/fasterxml/jackson/core/io/IOContext.constructTextBuffer:()Lcom/fasterxml/jackson/core/util/TextBuffer;
        30: putfield      #8                  // Field _textBuffer:Lcom/fasterxml/jackson/core/util/TextBuffer;
        33: getstatic     #9                  // Field com/fasterxml/jackson/core/JsonParser$Feature.STRICT_DUPLICATE_DETECTION:Lcom/fasterxml/jackson/core/JsonParser$Feature;
        36: iload_2
        37: invokevirtual #10                 // Method com/fasterxml/jackson/core/JsonParser$Feature.enabledIn:(I)Z
        40: ifeq          50
        43: aload_0
        44: invokestatic  #11                 // Method com/fasterxml/jackson/core/json/DupDetector.rootDetector:(Lcom/fasterxml/jackson/core/JsonParser;)Lcom/fasterxml/jackson/core/json/DupDetector;
        47: goto          51
        50: aconst_null
        51: astore_3
        52: aload_0
        53: aload_3
        54: invokestatic  #12                 // Method com/fasterxml/jackson/core/json/JsonReadContext.createRootContext:(Lcom/fasterxml/jackson/core/json/DupDetector;)Lcom/fasterxml/jackson/core/json/JsonReadContext;
        57: putfield      #13                 // Field _parsingContext:Lcom/fasterxml/jackson/core/json/JsonReadContext;
        60: return
      LineNumberTable:
        line 239: 0
        line 84: 5
        line 113: 10
        line 188: 15
        line 240: 20
        line 241: 25
        line 242: 33
        line 243: 44
        line 244: 52
        line 245: 60
      LocalVariableTable:
        Start  Length  Slot  Name   Signature
            0      61     0  this   Lcom/fasterxml/jackson/core/base/ParserBase;
            0      61     1  ctxt   Lcom/fasterxml/jackson/core/io/IOContext;
            0      61     2 features   I
           52       9     3  dups   Lcom/fasterxml/jackson/core/json/DupDetector;
      StackMapTable: number_of_entries = 2
        frame_type = 255 /* full_frame */
          offset_delta = 50
          locals = [ class com/fasterxml/jackson/core/base/ParserBase, class com/fasterxml/jackson/core/io/IOContext, int ]
          stack = []
        frame_type = 64 /* same_locals_1_stack_item */
          stack = [ class com/fasterxml/jackson/core/json/DupDetector ]

  public com.fasterxml.jackson.core.Version version();
    descriptor: ()Lcom/fasterxml/jackson/core/Version;
    flags: (0x0001) ACC_PUBLIC
    Code:
      stack=1, locals=1, args_size=1
         0: getstatic     #14                 // Field com/fasterxml/jackson/core/json/PackageVersion.VERSION:Lcom/fasterxml/jackson/core/Version;
         3: areturn
      LineNumberTable:
        line 247: 0
      LocalVariableTable:
        Start  Length  Slot  Name   Signature
            0       4     0  this   Lcom/fasterxml/jackson/core/base/ParserBase;

  public java.lang.Object getCurrentValue();
    descriptor: ()Ljava/lang/Object;
    flags: (0x0001) ACC_PUBLIC
    Code:
      stack=1, locals=1, args_size=1
         0: aload_0
         1: getfield      #13                 // Field _parsingContext:Lcom/fasterxml/jackson/core/json/JsonReadContext;
         4: invokevirtual #15                 // Method com/fasterxml/jackson/core/json/JsonReadContext.getCurrentValue:()Ljava/lang/Object;
         7: areturn
      LineNumberTable:
        line 251: 0
      LocalVariableTable:
        Start  Length  Slot  Name   Signature
            0       8     0  this   Lcom/fasterxml/jackson/core/base/ParserBase;

  public void setCurrentValue(java.lang.Object);
    descriptor: (Ljava/lang/Object;)V
    flags: (0x0001) ACC_PUBLIC
    Code:
      stack=2, locals=2, args_size=2
         0: aload_0
         1: getfield      #13                 // Field _parsingContext:Lcom/fasterxml/jackson/core/json/JsonReadContext;
         4: aload_1
         5: invokevirtual #16                 // Method com/fasterxml/jackson/core/json/JsonReadContext.setCurrentValue:(Ljava/lang/Object;)V
         8: return
      LineNumberTable:
        line 256: 0
        line 257: 8
      LocalVariableTable:
        Start  Length  Slot  Name   Signature
            0       9     0  this   Lcom/fasterxml/jackson/core/base/ParserBase;
            0       9     1     v   Ljava/lang/Object;

  public com.fasterxml.jackson.core.JsonParser enable(com.fasterxml.jackson.core.JsonParser$Feature);
    descriptor: (Lcom/fasterxml/jackson/core/JsonParser$Feature;)Lcom/fasterxml/jackson/core/JsonParser;
    flags: (0x0001) ACC_PUBLIC
    Code:
      stack=3, locals=2, args_size=2
         0: aload_0
         1: dup
         2: getfield      #17                 // Field _features:I
         5: aload_1
         6: invokevirtual #18                 // Method com/fasterxml/jackson/core/JsonParser$Feature.getMask:()I
         9: ior
        10: putfield      #17                 // Field _features:I
        13: aload_1
        14: getstatic     #9                  // Field com/fasterxml/jackson/core/JsonParser$Feature.STRICT_DUPLICATE_DETECTION:Lcom/fasterxml/jackson/core/JsonParser$Feature;
        17: if_acmpne     45
        20: aload_0
        21: getfield      #13                 // Field _parsingContext:Lcom/fasterxml/jackson/core/json/JsonReadContext;
        24: invokevirtual #19                 // Method com/fasterxml/jackson/core/json/JsonReadContext.getDupDetector:()Lcom/fasterxml/jackson/core/json/DupDetector;
        27: ifnonnull     45
        30: aload_0
        31: aload_0
        32: getfield      #13                 // Field _parsingContext:Lcom/fasterxml/jackson/core/json/JsonReadContext;
        35: aload_0
        36: invokestatic  #11                 // Method com/fasterxml/jackson/core/json/DupDetector.rootDetector:(Lcom/fasterxml/jackson/core/JsonParser;)Lcom/fasterxml/jackson/core/json/DupDetector;
        39: invokevirtual #20                 // Method com/fasterxml/jackson/core/json/JsonReadContext.withDupDetector:(Lcom/fasterxml/jackson/core/json/DupDetector;)Lcom/fasterxml/jackson/core/json/JsonReadContext;
        42: putfield      #13                 // Field _parsingContext:Lcom/fasterxml/jackson/core/json/JsonReadContext;
        45: aload_0
        46: areturn
      LineNumberTable:
        line 267: 0
        line 268: 13
        line 269: 20
        line 270: 30
        line 273: 45
      LocalVariableTable:
        Start  Length  Slot  Name   Signature
            0      47     0  this   Lcom/fasterxml/jackson/core/base/ParserBase;
            0      47     1     f   Lcom/fasterxml/jackson/core/JsonParser$Feature;
      StackMapTable: number_of_entries = 1
        frame_type = 45 /* same */

  public com.fasterxml.jackson.core.JsonParser disable(com.fasterxml.jackson.core.JsonParser$Feature);
    descriptor: (Lcom/fasterxml/jackson/core/JsonParser$Feature;)Lcom/fasterxml/jackson/core/JsonParser;
    flags: (0x0001) ACC_PUBLIC
    Code:
      stack=4, locals=2, args_size=2
         0: aload_0
         1: dup
         2: getfield      #17                 // Field _features:I
         5: aload_1
         6: invokevirtual #18                 // Method com/fasterxml/jackson/core/JsonParser$Feature.getMask:()I
         9: iconst_m1
        10: ixor
        11: iand
        12: putfield      #17                 // Field _features:I
        15: aload_1
        16: getstatic     #9                  // Field com/fasterxml/jackson/core/JsonParser$Feature.STRICT_DUPLICATE_DETECTION:Lcom/fasterxml/jackson/core/JsonParser$Feature;
        19: if_acmpne     34
        22: aload_0
        23: aload_0
        24: getfield      #13                 // Field _parsingContext:Lcom/fasterxml/jackson/core/json/JsonReadContext;
        27: aconst_null
        28: invokevirtual #20                 // Method com/fasterxml/jackson/core/json/JsonReadContext.withDupDetector:(Lcom/fasterxml/jackson/core/json/DupDetector;)Lcom/fasterxml/jackson/core/json/JsonReadContext;
        31: putfield      #13                 // Field _parsingContext:Lcom/fasterxml/jackson/core/json/JsonReadContext;
        34: aload_0
        35: areturn
      LineNumberTable:
        line 278: 0
        line 279: 15
        line 280: 22
        line 282: 34
      LocalVariableTable:
        Start  Length  Slot  Name   Signature
            0      36     0  this   Lcom/fasterxml/jackson/core/base/ParserBase;
            0      36     1     f   Lcom/fasterxml/jackson/core/JsonParser$Feature;
      StackMapTable: number_of_entries = 1
        frame_type = 34 /* same */

  public com.fasterxml.jackson.core.JsonParser setFeatureMask(int);
    descriptor: (I)Lcom/fasterxml/jackson/core/JsonParser;
    flags: (0x0001) ACC_PUBLIC
    Code:
      stack=3, locals=3, args_size=2
         0: aload_0
         1: getfield      #17                 // Field _features:I
         4: iload_1
         5: ixor
         6: istore_2
         7: iload_2
         8: ifeq          22
        11: aload_0
        12: iload_1
        13: putfield      #17                 // Field _features:I
        16: aload_0
        17: iload_1
        18: iload_2
        19: invokevirtual #21                 // Method _checkStdFeatureChanges:(II)V
        22: aload_0
        23: areturn
      LineNumberTable:
        line 288: 0
        line 289: 7
        line 290: 11
        line 291: 16
        line 293: 22
      LocalVariableTable:
        Start  Length  Slot  Name   Signature
            0      24     0  this   Lcom/fasterxml/jackson/core/base/ParserBase;
            0      24     1 newMask   I
            7      17     2 changes   I
      StackMapTable: number_of_entries = 1
        frame_type = 252 /* append */
          offset_delta = 22
          locals = [ int ]
    Deprecated: true
    RuntimeVisibleAnnotations:
      0: #313()
        java.lang.Deprecated

  public com.fasterxml.jackson.core.JsonParser overrideStdFeatures(int, int);
    descriptor: (II)Lcom/fasterxml/jackson/core/JsonParser;
    flags: (0x0001) ACC_PUBLIC
    Code:
      stack=3, locals=6, args_size=3
         0: aload_0
         1: getfield      #17                 // Field _features:I
         4: istore_3
         5: iload_3
         6: iload_2
         7: iconst_m1
         8: ixor
         9: iand
        10: iload_1
        11: iload_2
        12: iand
        13: ior
        14: istore        4
        16: iload_3
        17: iload         4
        19: ixor
        20: istore        5
        22: iload         5
        24: ifeq          41
        27: aload_0
        28: iload         4
        30: putfield      #17                 // Field _features:I
        33: aload_0
        34: iload         4
        36: iload         5
        38: invokevirtual #21                 // Method _checkStdFeatureChanges:(II)V
        41: aload_0
        42: areturn
      LineNumberTable:
        line 298: 0
        line 299: 5
        line 300: 16
        line 301: 22
        line 302: 27
        line 303: 33
        line 305: 41
      LocalVariableTable:
        Start  Length  Slot  Name   Signature
            0      43     0  this   Lcom/fasterxml/jackson/core/base/ParserBase;
            0      43     1 values   I
            0      43     2  mask   I
            5      38     3 oldState   I
           16      27     4 newState   I
           22      21     5 changed   I
      StackMapTable: number_of_entries = 1
        frame_type = 254 /* append */
          offset_delta = 41
          locals = [ int, int, int ]

  protected void _checkStdFeatureChanges(int, int);
    descriptor: (II)V
    flags: (0x0004) ACC_PROTECTED
    Code:
      stack=3, locals=4, args_size=3
         0: getstatic     #9                  // Field com/fasterxml/jackson/core/JsonParser$Feature.STRICT_DUPLICATE_DETECTION:Lcom/fasterxml/jackson/core/JsonParser$Feature;
         3: invokevirtual #18                 // Method com/fasterxml/jackson/core/JsonParser$Feature.getMask:()I
         6: istore_3
         7: iload_2
         8: iload_3
         9: iand
        10: ifeq          59
        13: iload_1
        14: iload_3
        15: iand
        16: ifeq          59
        19: aload_0
        20: getfield      #13                 // Field _parsingContext:Lcom/fasterxml/jackson/core/json/JsonReadContext;
        23: invokevirtual #19                 // Method com/fasterxml/jackson/core/json/JsonReadContext.getDupDetector:()Lcom/fasterxml/jackson/core/json/DupDetector;
        26: ifnonnull     47
        29: aload_0
        30: aload_0
        31: getfield      #13                 // Field _parsingContext:Lcom/fasterxml/jackson/core/json/JsonReadContext;
        34: aload_0
        35: invokestatic  #11                 // Method com/fasterxml/jackson/core/json/DupDetector.rootDetector:(Lcom/fasterxml/jackson/core/JsonParser;)Lcom/fasterxml/jackson/core/json/DupDetector;
        38: invokevirtual #20                 // Method com/fasterxml/jackson/core/json/JsonReadContext.withDupDetector:(Lcom/fasterxml/jackson/core/json/DupDetector;)Lcom/fasterxml/jackson/core/json/JsonReadContext;
        41: putfield      #13                 // Field _parsingContext:Lcom/fasterxml/jackson/core/json/JsonReadContext;
        44: goto          59
        47: aload_0
        48: aload_0
        49: getfield      #13                 // Field _parsingContext:Lcom/fasterxml/jackson/core/json/JsonReadContext;
        52: aconst_null
        53: invokevirtual #20                 // Method com/fasterxml/jackson/core/json/JsonReadContext.withDupDetector:(Lcom/fasterxml/jackson/core/json/DupDetector;)Lcom/fasterxml/jackson/core/json/JsonReadContext;
        56: putfield      #13                 // Field _parsingContext:Lcom/fasterxml/jackson/core/json/JsonReadContext;
        59: return
      LineNumberTable:
        line 319: 0
        line 321: 7
        line 322: 13
        line 323: 19
        line 324: 29
        line 326: 47
        line 330: 59
      LocalVariableTable:
        Start  Length  Slot  Name   Signature
            0      60     0  this   Lcom/fasterxml/jackson/core/base/ParserBase;
            0      60     1 newFeatureFlags   I
            0      60     2 changedFeatures   I
            7      53     3     f   I
      StackMapTable: number_of_entries = 2
        frame_type = 252 /* append */
          offset_delta = 47
          locals = [ int ]
        frame_type = 11 /* same */

  public java.lang.String getCurrentName() throws java.io.IOException;
    descriptor: ()Ljava/lang/String;
    flags: (0x0001) ACC_PUBLIC
    Code:
      stack=2, locals=2, args_size=1
         0: aload_0
         1: getfield      #22                 // Field _currToken:Lcom/fasterxml/jackson/core/JsonToken;
         4: getstatic     #23                 // Field com/fasterxml/jackson/core/JsonToken.START_OBJECT:Lcom/fasterxml/jackson/core/JsonToken;
         7: if_acmpeq     20
        10: aload_0
        11: getfield      #22                 // Field _currToken:Lcom/fasterxml/jackson/core/JsonToken;
        14: getstatic     #24                 // Field com/fasterxml/jackson/core/JsonToken.START_ARRAY:Lcom/fasterxml/jackson/core/JsonToken;
        17: if_acmpne     37
        20: aload_0
        21: getfield      #13                 // Field _parsingContext:Lcom/fasterxml/jackson/core/json/JsonReadContext;
        24: invokevirtual #25                 // Method com/fasterxml/jackson/core/json/JsonReadContext.getParent:()Lcom/fasterxml/jackson/core/json/JsonReadContext;
        27: astore_1
        28: aload_1
        29: ifnull        37
        32: aload_1
        33: invokevirtual #26                 // Method com/fasterxml/jackson/core/json/JsonReadContext.getCurrentName:()Ljava/lang/String;
        36: areturn
        37: aload_0
        38: getfield      #13                 // Field _parsingContext:Lcom/fasterxml/jackson/core/json/JsonReadContext;
        41: invokevirtual #26                 // Method com/fasterxml/jackson/core/json/JsonReadContext.getCurrentName:()Ljava/lang/String;
        44: areturn
      LineNumberTable:
        line 344: 0
        line 345: 20
        line 346: 28
        line 347: 32
        line 350: 37
      LocalVariableTable:
        Start  Length  Slot  Name   Signature
           28       9     1 parent   Lcom/fasterxml/jackson/core/json/JsonReadContext;
            0      45     0  this   Lcom/fasterxml/jackson/core/base/ParserBase;
      StackMapTable: number_of_entries = 2
        frame_type = 20 /* same */
        frame_type = 16 /* same */
    Exceptions:
      throws java.io.IOException

  public void overrideCurrentName(java.lang.String);
    descriptor: (Ljava/lang/String;)V
    flags: (0x0001) ACC_PUBLIC
    Code:
      stack=3, locals=4, args_size=2
         0: aload_0
         1: getfield      #13                 // Field _parsingContext:Lcom/fasterxml/jackson/core/json/JsonReadContext;
         4: astore_2
         5: aload_0
         6: getfield      #22                 // Field _currToken:Lcom/fasterxml/jackson/core/JsonToken;
         9: getstatic     #23                 // Field com/fasterxml/jackson/core/JsonToken.START_OBJECT:Lcom/fasterxml/jackson/core/JsonToken;
        12: if_acmpeq     25
        15: aload_0
        16: getfield      #22                 // Field _currToken:Lcom/fasterxml/jackson/core/JsonToken;
        19: getstatic     #24                 // Field com/fasterxml/jackson/core/JsonToken.START_ARRAY:Lcom/fasterxml/jackson/core/JsonToken;
        22: if_acmpne     30
        25: aload_2
        26: invokevirtual #25                 // Method com/fasterxml/jackson/core/json/JsonReadContext.getParent:()Lcom/fasterxml/jackson/core/json/JsonReadContext;
        29: astore_2
        30: aload_2
        31: aload_1
        32: invokevirtual #27                 // Method com/fasterxml/jackson/core/json/JsonReadContext.setCurrentName:(Ljava/lang/String;)V
        35: goto          48
        38: astore_3
        39: new           #29                 // class java/lang/IllegalStateException
        42: dup
        43: aload_3
        44: invokespecial #30                 // Method java/lang/IllegalStateException."<init>":(Ljava/lang/Throwable;)V
        47: athrow
        48: return
      Exception table:
         from    to  target type
            30    35    38   Class java/io/IOException
      LineNumberTable:
        line 355: 0
        line 356: 5
        line 357: 25
        line 362: 30
        line 365: 35
        line 363: 38
        line 364: 39
        line 366: 48
      LocalVariableTable:
        Start  Length  Slot  Name   Signature
           39       9     3     e   Ljava/io/IOException;
            0      49     0  this   Lcom/fasterxml/jackson/core/base/ParserBase;
            0      49     1  name   Ljava/lang/String;
            5      44     2  ctxt   Lcom/fasterxml/jackson/core/json/JsonReadContext;
      StackMapTable: number_of_entries = 4
        frame_type = 252 /* append */
          offset_delta = 25
          locals = [ class com/fasterxml/jackson/core/json/JsonReadContext ]
        frame_type = 4 /* same */
        frame_type = 71 /* same_locals_1_stack_item */
          stack = [ class java/io/IOException ]
        frame_type = 9 /* same */

  public void close() throws java.io.IOException;
    descriptor: ()V
    flags: (0x0001) ACC_PUBLIC
    Code:
      stack=3, locals=2, args_size=1
         0: aload_0
         1: getfield      #31                 // Field _closed:Z
         4: ifne          45
         7: aload_0
         8: aload_0
         9: getfield      #32                 // Field _inputPtr:I
        12: aload_0
        13: getfield      #33                 // Field _inputEnd:I
        16: invokestatic  #34                 // Method java/lang/Math.max:(II)I
        19: putfield      #32                 // Field _inputPtr:I
        22: aload_0
        23: iconst_1
        24: putfield      #31                 // Field _closed:Z
        27: aload_0
        28: invokevirtual #35                 // Method _closeInput:()V
        31: aload_0
        32: invokevirtual #36                 // Method _releaseBuffers:()V
        35: goto          45
        38: astore_1
        39: aload_0
        40: invokevirtual #36                 // Method _releaseBuffers:()V
        43: aload_1
        44: athrow
        45: return
      Exception table:
         from    to  target type
            27    31    38   any
      LineNumberTable:
        line 369: 0
        line 371: 7
        line 372: 22
        line 374: 27
        line 378: 31
        line 379: 35
        line 378: 38
        line 379: 43
        line 381: 45
      LocalVariableTable:
        Start  Length  Slot  Name   Signature
            0      46     0  this   Lcom/fasterxml/jackson/core/base/ParserBase;
      StackMapTable: number_of_entries = 2
        frame_type = 102 /* same_locals_1_stack_item */
          stack = [ class java/lang/Throwable ]
        frame_type = 6 /* same */
    Exceptions:
      throws java.io.IOException

  public boolean isClosed();
    descriptor: ()Z
    flags: (0x0001) ACC_PUBLIC
    Code:
      stack=1, locals=1, args_size=1
         0: aload_0
         1: getfield      #31                 // Field _closed:Z
         4: ireturn
      LineNumberTable:
        line 383: 0
      LocalVariableTable:
        Start  Length  Slot  Name   Signature
            0       5     0  this   Lcom/fasterxml/jackson/core/base/ParserBase;

  public com.fasterxml.jackson.core.json.JsonReadContext getParsingContext();
    descriptor: ()Lcom/fasterxml/jackson/core/json/JsonReadContext;
    flags: (0x0001) ACC_PUBLIC
    Code:
      stack=1, locals=1, args_size=1
         0: aload_0
         1: getfield      #13                 // Field _parsingContext:Lcom/fasterxml/jackson/core/json/JsonReadContext;
         4: areturn
      LineNumberTable:
        line 384: 0
      LocalVariableTable:
        Start  Length  Slot  Name   Signature
            0       5     0  this   Lcom/fasterxml/jackson/core/base/ParserBase;

  public com.fasterxml.jackson.core.JsonLocation getTokenLocation();
    descriptor: ()Lcom/fasterxml/jackson/core/JsonLocation;
    flags: (0x0001) ACC_PUBLIC
    Code:
      stack=9, locals=1, args_size=1
         0: new           #37                 // class com/fasterxml/jackson/core/JsonLocation
         3: dup
         4: aload_0
         5: invokevirtual #38                 // Method _contentReference:()Lcom/fasterxml/jackson/core/io/ContentReference;
         8: ldc2_w        #39                 // long -1l
        11: aload_0
        12: invokevirtual #41                 // Method getTokenCharacterOffset:()J
        15: aload_0
        16: invokevirtual #42                 // Method getTokenLineNr:()I
        19: aload_0
        20: invokevirtual #43                 // Method getTokenColumnNr:()I
        23: invokespecial #44                 // Method com/fasterxml/jackson/core/JsonLocation."<init>":(Lcom/fasterxml/jackson/core/io/ContentReference;JJII)V
        26: areturn
      LineNumberTable:
        line 393: 0
        line 394: 12
        line 395: 16
        line 396: 20
        line 393: 26
      LocalVariableTable:
        Start  Length  Slot  Name   Signature
            0      27     0  this   Lcom/fasterxml/jackson/core/base/ParserBase;

  public com.fasterxml.jackson.core.JsonLocation getCurrentLocation();
    descriptor: ()Lcom/fasterxml/jackson/core/JsonLocation;
    flags: (0x0001) ACC_PUBLIC
    Code:
      stack=9, locals=2, args_size=1
         0: aload_0
         1: getfield      #32                 // Field _inputPtr:I
         4: aload_0
         5: getfield      #45                 // Field _currInputRowStart:I
         8: isub
         9: iconst_1
        10: iadd
        11: istore_1
        12: new           #37                 // class com/fasterxml/jackson/core/JsonLocation
        15: dup
        16: aload_0
        17: invokevirtual #38                 // Method _contentReference:()Lcom/fasterxml/jackson/core/io/ContentReference;
        20: ldc2_w        #39                 // long -1l
        23: aload_0
        24: getfield      #46                 // Field _currInputProcessed:J
        27: aload_0
        28: getfield      #32                 // Field _inputPtr:I
        31: i2l
        32: ladd
        33: aload_0
        34: getfield      #2                  // Field _currInputRow:I
        37: iload_1
        38: invokespecial #44                 // Method com/fasterxml/jackson/core/JsonLocation."<init>":(Lcom/fasterxml/jackson/core/io/ContentReference;JJII)V
        41: areturn
      LineNumberTable:
        line 405: 0
        line 406: 12
      LocalVariableTable:
        Start  Length  Slot  Name   Signature
            0      42     0  this   Lcom/fasterxml/jackson/core/base/ParserBase;
           12      30     1   col   I

  public boolean hasTextCharacters();
    descriptor: ()Z
    flags: (0x0001) ACC_PUBLIC
    Code:
      stack=2, locals=1, args_size=1
         0: aload_0
         1: getfield      #22                 // Field _currToken:Lcom/fasterxml/jackson/core/JsonToken;
         4: getstatic     #47                 // Field com/fasterxml/jackson/core/JsonToken.VALUE_STRING:Lcom/fasterxml/jackson/core/JsonToken;
         7: if_acmpne     12
        10: iconst_1
        11: ireturn
        12: aload_0
        13: getfield      #22                 // Field _currToken:Lcom/fasterxml/jackson/core/JsonToken;
        16: getstatic     #48                 // Field com/fasterxml/jackson/core/JsonToken.FIELD_NAME:Lcom/fasterxml/jackson/core/JsonToken;
        19: if_acmpne     27
        22: aload_0
        23: getfield      #49                 // Field _nameCopied:Z
        26: ireturn
        27: iconst_0
        28: ireturn
      LineNumberTable:
        line 419: 0
        line 420: 12
        line 421: 27
      LocalVariableTable:
        Start  Length  Slot  Name   Signature
            0      29     0  this   Lcom/fasterxml/jackson/core/base/ParserBase;
      StackMapTable: number_of_entries = 2
        frame_type = 12 /* same */
        frame_type = 14 /* same */

  public byte[] getBinaryValue(com.fasterxml.jackson.core.Base64Variant) throws java.io.IOException;
    descriptor: (Lcom/fasterxml/jackson/core/Base64Variant;)[B
    flags: (0x0001) ACC_PUBLIC
    Code:
      stack=4, locals=3, args_size=2
         0: aload_0
         1: getfield      #50                 // Field _binaryValue:[B
         4: ifnonnull     71
         7: aload_0
         8: getfield      #22                 // Field _currToken:Lcom/fasterxml/jackson/core/JsonToken;
        11: getstatic     #47                 // Field com/fasterxml/jackson/core/JsonToken.VALUE_STRING:Lcom/fasterxml/jackson/core/JsonToken;
        14: if_acmpeq     48
        17: aload_0
        18: new           #51                 // class java/lang/StringBuilder
        21: dup
        22: invokespecial #52                 // Method java/lang/StringBuilder."<init>":()V
        25: ldc           #53                 // String Current token (
        27: invokevirtual #54                 // Method java/lang/StringBuilder.append:(Ljava/lang/String;)Ljava/lang/StringBuilder;
        30: aload_0
        31: getfield      #22                 // Field _currToken:Lcom/fasterxml/jackson/core/JsonToken;
        34: invokevirtual #55                 // Method java/lang/StringBuilder.append:(Ljava/lang/Object;)Ljava/lang/StringBuilder;
        37: ldc           #56                 // String ) not VALUE_STRING, can not access as binary
        39: invokevirtual #54                 // Method java/lang/StringBuilder.append:(Ljava/lang/String;)Ljava/lang/StringBuilder;
        42: invokevirtual #57                 // Method java/lang/StringBuilder.toString:()Ljava/lang/String;
        45: invokevirtual #58                 // Method _reportError:(Ljava/lang/String;)V
        48: aload_0
        49: invokevirtual #59                 // Method _getByteArrayBuilder:()Lcom/fasterxml/jackson/core/util/ByteArrayBuilder;
        52: astore_2
        53: aload_0
        54: aload_0
        55: invokevirtual #60                 // Method getText:()Ljava/lang/String;
        58: aload_2
        59: aload_1
        60: invokevirtual #61                 // Method _decodeBase64:(Ljava/lang/String;Lcom/fasterxml/jackson/core/util/ByteArrayBuilder;Lcom/fasterxml/jackson/core/Base64Variant;)V
        63: aload_0
        64: aload_2
        65: invokevirtual #62                 // Method com/fasterxml/jackson/core/util/ByteArrayBuilder.toByteArray:()[B
        68: putfield      #50                 // Field _binaryValue:[B
        71: aload_0
        72: getfield      #50                 // Field _binaryValue:[B
        75: areturn
      LineNumberTable:
        line 428: 0
        line 429: 7
        line 430: 17
        line 432: 48
        line 433: 53
        line 434: 63
        line 436: 71
      LocalVariableTable:
        Start  Length  Slot  Name   Signature
           53      18     2 builder   Lcom/fasterxml/jackson/core/util/ByteArrayBuilder;
            0      76     0  this   Lcom/fasterxml/jackson/core/base/ParserBase;
            0      76     1 variant   Lcom/fasterxml/jackson/core/Base64Variant;
      StackMapTable: number_of_entries = 2
        frame_type = 48 /* same */
        frame_type = 22 /* same */
    Exceptions:
      throws java.io.IOException

  public long getTokenCharacterOffset();
    descriptor: ()J
    flags: (0x0001) ACC_PUBLIC
    Code:
      stack=2, locals=1, args_size=1
         0: aload_0
         1: getfield      #63                 // Field _tokenInputTotal:J
         4: lreturn
      LineNumberTable:
        line 445: 0
      LocalVariableTable:
        Start  Length  Slot  Name   Signature
            0       5     0  this   Lcom/fasterxml/jackson/core/base/ParserBase;

  public int getTokenLineNr();
    descriptor: ()I
    flags: (0x0001) ACC_PUBLIC
    Code:
      stack=1, locals=1, args_size=1
         0: aload_0
         1: getfield      #3                  // Field _tokenInputRow:I
         4: ireturn
      LineNumberTable:
        line 446: 0
      LocalVariableTable:
        Start  Length  Slot  Name   Signature
            0       5     0  this   Lcom/fasterxml/jackson/core/base/ParserBase;

  public int getTokenColumnNr();
    descriptor: ()I
    flags: (0x0001) ACC_PUBLIC
    Code:
      stack=2, locals=2, args_size=1
         0: aload_0
         1: getfield      #64                 // Field _tokenInputCol:I
         4: istore_1
         5: iload_1
         6: ifge          13
         9: iload_1
        10: goto          16
        13: iload_1
        14: iconst_1
        15: iadd
        16: ireturn
      LineNumberTable:
        line 449: 0
        line 450: 5
      LocalVariableTable:
        Start  Length  Slot  Name   Signature
            0      17     0  this   Lcom/fasterxml/jackson/core/base/ParserBase;
            5      12     1   col   I
      StackMapTable: number_of_entries = 2
        frame_type = 252 /* append */
          offset_delta = 13
          locals = [ int ]
        frame_type = 66 /* same_locals_1_stack_item */
          stack = [ int ]

  protected abstract void _closeInput() throws java.io.IOException;
    descriptor: ()V
    flags: (0x0404) ACC_PROTECTED, ACC_ABSTRACT
    Exceptions:
      throws java.io.IOException

  protected void _releaseBuffers() throws java.io.IOException;
    descriptor: ()V
    flags: (0x0004) ACC_PROTECTED
    Code:
      stack=2, locals=2, args_size=1
         0: aload_0
         1: getfield      #8                  // Field _textBuffer:Lcom/fasterxml/jackson/core/util/TextBuffer;
         4: invokevirtual #65                 // Method com/fasterxml/jackson/core/util/TextBuffer.releaseBuffers:()V
         7: aload_0
         8: getfield      #66                 // Field _nameCopyBuffer:[C
        11: astore_1
        12: aload_1
        13: ifnull        29
        16: aload_0
        17: aconst_null
        18: putfield      #66                 // Field _nameCopyBuffer:[C
        21: aload_0
        22: getfield      #6                  // Field _ioContext:Lcom/fasterxml/jackson/core/io/IOContext;
        25: aload_1
        26: invokevirtual #67                 // Method com/fasterxml/jackson/core/io/IOContext.releaseNameCopyBuffer:([C)V
        29: return
      LineNumberTable:
        line 477: 0
        line 478: 7
        line 479: 12
        line 480: 16
        line 481: 21
        line 483: 29
      LocalVariableTable:
        Start  Length  Slot  Name   Signature
            0      30     0  this   Lcom/fasterxml/jackson/core/base/ParserBase;
           12      18     1   buf   [C
      StackMapTable: number_of_entries = 1
        frame_type = 252 /* append */
          offset_delta = 29
          locals = [ class "[C" ]
    Exceptions:
      throws java.io.IOException

  protected void _handleEOF() throws com.fasterxml.jackson.core.JsonParseException;
    descriptor: ()V
    flags: (0x0004) ACC_PROTECTED
    Code:
      stack=7, locals=2, args_size=1
         0: aload_0
         1: getfield      #13                 // Field _parsingContext:Lcom/fasterxml/jackson/core/json/JsonReadContext;
         4: invokevirtual #68                 // Method com/fasterxml/jackson/core/json/JsonReadContext.inRoot:()Z
         7: ifne          60
        10: aload_0
        11: getfield      #13                 // Field _parsingContext:Lcom/fasterxml/jackson/core/json/JsonReadContext;
        14: invokevirtual #69                 // Method com/fasterxml/jackson/core/json/JsonReadContext.inArray:()Z
        17: ifeq          25
        20: ldc           #70                 // String Array
        22: goto          27
        25: ldc           #71                 // String Object
        27: astore_1
        28: aload_0
        29: ldc           #72                 // String : expected close marker for %s (start marker at %s)
        31: iconst_2
        32: anewarray     #73                 // class java/lang/Object
        35: dup
        36: iconst_0
        37: aload_1
        38: aastore
        39: dup
        40: iconst_1
        41: aload_0
        42: getfield      #13                 // Field _parsingContext:Lcom/fasterxml/jackson/core/json/JsonReadContext;
        45: aload_0
        46: invokevirtual #38                 // Method _contentReference:()Lcom/fasterxml/jackson/core/io/ContentReference;
        49: invokevirtual #74                 // Method com/fasterxml/jackson/core/json/JsonReadContext.startLocation:(Lcom/fasterxml/jackson/core/io/ContentReference;)Lcom/fasterxml/jackson/core/JsonLocation;
        52: aastore
        53: invokestatic  #75                 // Method java/lang/String.format:(Ljava/lang/String;[Ljava/lang/Object;)Ljava/lang/String;
        56: aconst_null
        57: invokevirtual #76                 // Method _reportInvalidEOF:(Ljava/lang/String;Lcom/fasterxml/jackson/core/JsonToken;)V
        60: return
      LineNumberTable:
        line 492: 0
        line 493: 10
        line 494: 28
        line 497: 46
        line 494: 53
        line 500: 60
      LocalVariableTable:
        Start  Length  Slot  Name   Signature
           28      32     1 marker   Ljava/lang/String;
            0      61     0  this   Lcom/fasterxml/jackson/core/base/ParserBase;
      StackMapTable: number_of_entries = 3
        frame_type = 25 /* same */
        frame_type = 65 /* same_locals_1_stack_item */
          stack = [ class java/lang/String ]
        frame_type = 32 /* same */
    Exceptions:
      throws com.fasterxml.jackson.core.JsonParseException

  protected final int _eofAsNextChar() throws com.fasterxml.jackson.core.JsonParseException;
    descriptor: ()I
    flags: (0x0014) ACC_PROTECTED, ACC_FINAL
    Code:
      stack=1, locals=1, args_size=1
         0: aload_0
         1: invokevirtual #77                 // Method _handleEOF:()V
         4: iconst_m1
         5: ireturn
      LineNumberTable:
        line 511: 0
        line 512: 4
      LocalVariableTable:
        Start  Length  Slot  Name   Signature
            0       6     0  this   Lcom/fasterxml/jackson/core/base/ParserBase;
    Exceptions:
      throws com.fasterxml.jackson.core.JsonParseException

  public com.fasterxml.jackson.core.util.ByteArrayBuilder _getByteArrayBuilder();
    descriptor: ()Lcom/fasterxml/jackson/core/util/ByteArrayBuilder;
    flags: (0x0001) ACC_PUBLIC
    Code:
      stack=3, locals=1, args_size=1
         0: aload_0
         1: getfield      #78                 // Field _byteArrayBuilder:Lcom/fasterxml/jackson/core/util/ByteArrayBuilder;
         4: ifnonnull     21
         7: aload_0
         8: new           #79                 // class com/fasterxml/jackson/core/util/ByteArrayBuilder
        11: dup
        12: invokespecial #80                 // Method com/fasterxml/jackson/core/util/ByteArrayBuilder."<init>":()V
        15: putfield      #78                 // Field _byteArrayBuilder:Lcom/fasterxml/jackson/core/util/ByteArrayBuilder;
        18: goto          28
        21: aload_0
        22: getfield      #78                 // Field _byteArrayBuilder:Lcom/fasterxml/jackson/core/util/ByteArrayBuilder;
        25: invokevirtual #81                 // Method com/fasterxml/jackson/core/util/ByteArrayBuilder.reset:()V
        28: aload_0
        29: getfield      #78                 // Field _byteArrayBuilder:Lcom/fasterxml/jackson/core/util/ByteArrayBuilder;
        32: areturn
      LineNumberTable:
        line 523: 0
        line 524: 7
        line 526: 21
        line 528: 28
      LocalVariableTable:
        Start  Length  Slot  Name   Signature
            0      33     0  this   Lcom/fasterxml/jackson/core/base/ParserBase;
      StackMapTable: number_of_entries = 2
        frame_type = 21 /* same */
        frame_type = 6 /* same */

  protected final com.fasterxml.jackson.core.JsonToken reset(boolean, int, int, int);
    descriptor: (ZIII)Lcom/fasterxml/jackson/core/JsonToken;
    flags: (0x0014) ACC_PROTECTED, ACC_FINAL
    Code:
      stack=5, locals=5, args_size=5
         0: iload_3
         1: iconst_1
         2: if_icmpge     18
         5: iload         4
         7: iconst_1
         8: if_icmpge     18
        11: aload_0
        12: iload_1
        13: iload_2
        14: invokevirtual #82                 // Method resetInt:(ZI)Lcom/fasterxml/jackson/core/JsonToken;
        17: areturn
        18: aload_0
        19: iload_1
        20: iload_2
        21: iload_3
        22: iload         4
        24: invokevirtual #83                 // Method resetFloat:(ZIII)Lcom/fasterxml/jackson/core/JsonToken;
        27: areturn
      LineNumberTable:
        line 541: 0
        line 542: 11
        line 544: 18
      LocalVariableTable:
        Start  Length  Slot  Name   Signature
            0      28     0  this   Lcom/fasterxml/jackson/core/base/ParserBase;
            0      28     1 negative   Z
            0      28     2 intLen   I
            0      28     3 fractLen   I
            0      28     4 expLen   I
      StackMapTable: number_of_entries = 1
        frame_type = 18 /* same */

  protected final com.fasterxml.jackson.core.JsonToken resetInt(boolean, int);
    descriptor: (ZI)Lcom/fasterxml/jackson/core/JsonToken;
    flags: (0x0014) ACC_PROTECTED, ACC_FINAL
    Code:
      stack=2, locals=3, args_size=3
         0: aload_0
         1: iload_1
         2: putfield      #84                 // Field _numberNegative:Z
         5: aload_0
         6: iload_2
         7: putfield      #85                 // Field _intLength:I
        10: aload_0
        11: iconst_0
        12: putfield      #86                 // Field _fractLength:I
        15: aload_0
        16: iconst_0
        17: putfield      #87                 // Field _expLength:I
        20: aload_0
        21: iconst_0
        22: putfield      #5                  // Field _numTypesValid:I
        25: getstatic     #88                 // Field com/fasterxml/jackson/core/JsonToken.VALUE_NUMBER_INT:Lcom/fasterxml/jackson/core/JsonToken;
        28: areturn
      LineNumberTable:
        line 549: 0
        line 550: 5
        line 551: 10
        line 552: 15
        line 553: 20
        line 554: 25
      LocalVariableTable:
        Start  Length  Slot  Name   Signature
            0      29     0  this   Lcom/fasterxml/jackson/core/base/ParserBase;
            0      29     1 negative   Z
            0      29     2 intLen   I

  protected final com.fasterxml.jackson.core.JsonToken resetFloat(boolean, int, int, int);
    descriptor: (ZIII)Lcom/fasterxml/jackson/core/JsonToken;
    flags: (0x0014) ACC_PROTECTED, ACC_FINAL
    Code:
      stack=2, locals=5, args_size=5
         0: aload_0
         1: iload_1
         2: putfield      #84                 // Field _numberNegative:Z
         5: aload_0
         6: iload_2
         7: putfield      #85                 // Field _intLength:I
        10: aload_0
        11: iload_3
        12: putfield      #86                 // Field _fractLength:I
        15: aload_0
        16: iload         4
        18: putfield      #87                 // Field _expLength:I
        21: aload_0
        22: iconst_0
        23: putfield      #5                  // Field _numTypesValid:I
        26: getstatic     #89                 // Field com/fasterxml/jackson/core/JsonToken.VALUE_NUMBER_FLOAT:Lcom/fasterxml/jackson/core/JsonToken;
        29: areturn
      LineNumberTable:
        line 559: 0
        line 560: 5
        line 561: 10
        line 562: 15
        line 563: 21
        line 564: 26
      LocalVariableTable:
        Start  Length  Slot  Name   Signature
            0      30     0  this   Lcom/fasterxml/jackson/core/base/ParserBase;
            0      30     1 negative   Z
            0      30     2 intLen   I
            0      30     3 fractLen   I
            0      30     4 expLen   I

  protected final com.fasterxml.jackson.core.JsonToken resetAsNaN(java.lang.String, double);
    descriptor: (Ljava/lang/String;D)Lcom/fasterxml/jackson/core/JsonToken;
    flags: (0x0014) ACC_PROTECTED, ACC_FINAL
    Code:
      stack=3, locals=4, args_size=3
         0: aload_0
         1: getfield      #8                  // Field _textBuffer:Lcom/fasterxml/jackson/core/util/TextBuffer;
         4: aload_1
         5: invokevirtual #90                 // Method com/fasterxml/jackson/core/util/TextBuffer.resetWithString:(Ljava/lang/String;)V
         8: aload_0
         9: dload_2
        10: putfield      #91                 // Field _numberDouble:D
        13: aload_0
        14: bipush        8
        16: putfield      #5                  // Field _numTypesValid:I
        19: getstatic     #89                 // Field com/fasterxml/jackson/core/JsonToken.VALUE_NUMBER_FLOAT:Lcom/fasterxml/jackson/core/JsonToken;
        22: areturn
      LineNumberTable:
        line 569: 0
        line 570: 8
        line 571: 13
        line 572: 19
      LocalVariableTable:
        Start  Length  Slot  Name   Signature
            0      23     0  this   Lcom/fasterxml/jackson/core/base/ParserBase;
            0      23     1 valueStr   Ljava/lang/String;
            0      23     2 value   D

  public boolean isNaN();
    descriptor: ()Z
    flags: (0x0001) ACC_PUBLIC
    Code:
      stack=2, locals=3, args_size=1
         0: aload_0
         1: getfield      #22                 // Field _currToken:Lcom/fasterxml/jackson/core/JsonToken;
         4: getstatic     #89                 // Field com/fasterxml/jackson/core/JsonToken.VALUE_NUMBER_FLOAT:Lcom/fasterxml/jackson/core/JsonToken;
         7: if_acmpne     45
        10: aload_0
        11: getfield      #5                  // Field _numTypesValid:I
        14: bipush        8
        16: iand
        17: ifeq          45
        20: aload_0
        21: getfield      #91                 // Field _numberDouble:D
        24: dstore_1
        25: dload_1
        26: invokestatic  #92                 // Method java/lang/Double.isNaN:(D)Z
        29: ifne          39
        32: dload_1
        33: invokestatic  #93                 // Method java/lang/Double.isInfinite:(D)Z
        36: ifeq          43
        39: iconst_1
        40: goto          44
        43: iconst_0
        44: ireturn
        45: iconst_0
        46: ireturn
      LineNumberTable:
        line 577: 0
        line 578: 10
        line 580: 20
        line 581: 25
        line 584: 45
      LocalVariableTable:
        Start  Length  Slot  Name   Signature
           25      20     1     d   D
            0      47     0  this   Lcom/fasterxml/jackson/core/base/ParserBase;
      StackMapTable: number_of_entries = 4
        frame_type = 252 /* append */
          offset_delta = 39
          locals = [ double ]
        frame_type = 3 /* same */
        frame_type = 64 /* same_locals_1_stack_item */
          stack = [ int ]
        frame_type = 250 /* chop */
          offset_delta = 0

  public java.lang.Number getNumberValue() throws java.io.IOException;
    descriptor: ()Ljava/lang/Number;
    flags: (0x0001) ACC_PUBLIC
    Code:
      stack=2, locals=1, args_size=1
         0: aload_0
         1: getfield      #5                  // Field _numTypesValid:I
         4: ifne          12
         7: aload_0
         8: iconst_0
         9: invokevirtual #94                 // Method _parseNumericValue:(I)V
        12: aload_0
        13: getfield      #22                 // Field _currToken:Lcom/fasterxml/jackson/core/JsonToken;
        16: getstatic     #88                 // Field com/fasterxml/jackson/core/JsonToken.VALUE_NUMBER_INT:Lcom/fasterxml/jackson/core/JsonToken;
        19: if_acmpne     74
        22: aload_0
        23: getfield      #5                  // Field _numTypesValid:I
        26: iconst_1
        27: iand
        28: ifeq          39
        31: aload_0
        32: getfield      #95                 // Field _numberInt:I
        35: invokestatic  #96                 // Method java/lang/Integer.valueOf:(I)Ljava/lang/Integer;
        38: areturn
        39: aload_0
        40: getfield      #5                  // Field _numTypesValid:I
        43: iconst_2
        44: iand
        45: ifeq          56
        48: aload_0
        49: getfield      #97                 // Field _numberLong:J
        52: invokestatic  #98                 // Method java/lang/Long.valueOf:(J)Ljava/lang/Long;
        55: areturn
        56: aload_0
        57: getfield      #5                  // Field _numTypesValid:I
        60: iconst_4
        61: iand
        62: ifeq          70
        65: aload_0
        66: getfield      #99                 // Field _numberBigInt:Ljava/math/BigInteger;
        69: areturn
        70: aload_0
        71: invokevirtual #100                // Method _throwInternal:()V
        74: aload_0
        75: getfield      #5                  // Field _numTypesValid:I
        78: bipush        16
        80: iand
        81: ifeq          89
        84: aload_0
        85: getfield      #101                // Field _numberBigDecimal:Ljava/math/BigDecimal;
        88: areturn
        89: aload_0
        90: getfield      #5                  // Field _numTypesValid:I
        93: bipush        8
        95: iand
        96: ifne          103
        99: aload_0
       100: invokevirtual #100                // Method _throwInternal:()V
       103: aload_0
       104: getfield      #91                 // Field _numberDouble:D
       107: invokestatic  #102                // Method java/lang/Double.valueOf:(D)Ljava/lang/Double;
       110: areturn
      LineNumberTable:
        line 596: 0
        line 597: 7
        line 600: 12
        line 601: 22
        line 602: 31
        line 604: 39
        line 605: 48
        line 607: 56
        line 608: 65
        line 610: 70
        line 615: 74
        line 616: 84
        line 618: 89
        line 619: 99
        line 621: 103
      LocalVariableTable:
        Start  Length  Slot  Name   Signature
            0     111     0  this   Lcom/fasterxml/jackson/core/base/ParserBase;
      StackMapTable: number_of_entries = 7
        frame_type = 12 /* same */
        frame_type = 26 /* same */
        frame_type = 16 /* same */
        frame_type = 13 /* same */
        frame_type = 3 /* same */
        frame_type = 14 /* same */
        frame_type = 13 /* same */
    Exceptions:
      throws java.io.IOException

  public java.lang.Number getNumberValueExact() throws java.io.IOException;
    descriptor: ()Ljava/lang/Number;
    flags: (0x0001) ACC_PUBLIC
    Code:
      stack=2, locals=1, args_size=1
         0: aload_0
         1: getfield      #22                 // Field _currToken:Lcom/fasterxml/jackson/core/JsonToken;
         4: getstatic     #88                 // Field com/fasterxml/jackson/core/JsonToken.VALUE_NUMBER_INT:Lcom/fasterxml/jackson/core/JsonToken;
         7: if_acmpne     74
        10: aload_0
        11: getfield      #5                  // Field _numTypesValid:I
        14: ifne          22
        17: aload_0
        18: iconst_0
        19: invokevirtual #94                 // Method _parseNumericValue:(I)V
        22: aload_0
        23: getfield      #5                  // Field _numTypesValid:I
        26: iconst_1
        27: iand
        28: ifeq          39
        31: aload_0
        32: getfield      #95                 // Field _numberInt:I
        35: invokestatic  #96                 // Method java/lang/Integer.valueOf:(I)Ljava/lang/Integer;
        38: areturn
        39: aload_0
        40: getfield      #5                  // Field _numTypesValid:I
        43: iconst_2
        44: iand
        45: ifeq          56
        48: aload_0
        49: getfield      #97                 // Field _numberLong:J
        52: invokestatic  #98                 // Method java/lang/Long.valueOf:(J)Ljava/lang/Long;
        55: areturn
        56: aload_0
        57: getfield      #5                  // Field _numTypesValid:I
        60: iconst_4
        61: iand
        62: ifeq          70
        65: aload_0
        66: getfield      #99                 // Field _numberBigInt:Ljava/math/BigInteger;
        69: areturn
        70: aload_0
        71: invokevirtual #100                // Method _throwInternal:()V
        74: aload_0
        75: getfield      #5                  // Field _numTypesValid:I
        78: ifne          87
        81: aload_0
        82: bipush        16
        84: invokevirtual #94                 // Method _parseNumericValue:(I)V
        87: aload_0
        88: getfield      #5                  // Field _numTypesValid:I
        91: bipush        16
        93: iand
        94: ifeq          102
        97: aload_0
        98: getfield      #101                // Field _numberBigDecimal:Ljava/math/BigDecimal;
       101: areturn
       102: aload_0
       103: getfield      #5                  // Field _numTypesValid:I
       106: bipush        8
       108: iand
       109: ifne          116
       112: aload_0
       113: invokevirtual #100                // Method _throwInternal:()V
       116: aload_0
       117: getfield      #91                 // Field _numberDouble:D
       120: invokestatic  #102                // Method java/lang/Double.valueOf:(D)Ljava/lang/Double;
       123: areturn
      LineNumberTable:
        line 628: 0
        line 629: 10
        line 630: 17
        line 632: 22
        line 633: 31
        line 635: 39
        line 636: 48
        line 638: 56
        line 639: 65
        line 641: 70
        line 644: 74
        line 645: 81
        line 647: 87
        line 648: 97
        line 650: 102
        line 651: 112
        line 653: 116
      LocalVariableTable:
        Start  Length  Slot  Name   Signature
            0     124     0  this   Lcom/fasterxml/jackson/core/base/ParserBase;
      StackMapTable: number_of_entries = 8
        frame_type = 22 /* same */
        frame_type = 16 /* same */
        frame_type = 16 /* same */
        frame_type = 13 /* same */
        frame_type = 3 /* same */
        frame_type = 12 /* same */
        frame_type = 14 /* same */
        frame_type = 13 /* same */
    Exceptions:
      throws java.io.IOException

  public com.fasterxml.jackson.core.JsonParser$NumberType getNumberType() throws java.io.IOException;
    descriptor: ()Lcom/fasterxml/jackson/core/JsonParser$NumberType;
    flags: (0x0001) ACC_PUBLIC
    Code:
      stack=2, locals=1, args_size=1
         0: aload_0
         1: getfield      #5                  // Field _numTypesValid:I
         4: ifne          12
         7: aload_0
         8: iconst_0
         9: invokevirtual #94                 // Method _parseNumericValue:(I)V
        12: aload_0
        13: getfield      #22                 // Field _currToken:Lcom/fasterxml/jackson/core/JsonToken;
        16: getstatic     #88                 // Field com/fasterxml/jackson/core/JsonToken.VALUE_NUMBER_INT:Lcom/fasterxml/jackson/core/JsonToken;
        19: if_acmpne     52
        22: aload_0
        23: getfield      #5                  // Field _numTypesValid:I
        26: iconst_1
        27: iand
        28: ifeq          35
        31: getstatic     #103                // Field com/fasterxml/jackson/core/JsonParser$NumberType.INT:Lcom/fasterxml/jackson/core/JsonParser$NumberType;
        34: areturn
        35: aload_0
        36: getfield      #5                  // Field _numTypesValid:I
        39: iconst_2
        40: iand
        41: ifeq          48
        44: getstatic     #104                // Field com/fasterxml/jackson/core/JsonParser$NumberType.LONG:Lcom/fasterxml/jackson/core/JsonParser$NumberType;
        47: areturn
        48: getstatic     #105                // Field com/fasterxml/jackson/core/JsonParser$NumberType.BIG_INTEGER:Lcom/fasterxml/jackson/core/JsonParser$NumberType;
        51: areturn
        52: aload_0
        53: getfield      #5                  // Field _numTypesValid:I
        56: bipush        16
        58: iand
        59: ifeq          66
        62: getstatic     #106                // Field com/fasterxml/jackson/core/JsonParser$NumberType.BIG_DECIMAL:Lcom/fasterxml/jackson/core/JsonParser$NumberType;
        65: areturn
        66: getstatic     #107                // Field com/fasterxml/jackson/core/JsonParser$NumberType.DOUBLE:Lcom/fasterxml/jackson/core/JsonParser$NumberType;
        69: areturn
      LineNumberTable:
        line 659: 0
        line 660: 7
        line 662: 12
        line 663: 22
        line 664: 31
        line 666: 35
        line 667: 44
        line 669: 48
        line 678: 52
        line 679: 62
        line 681: 66
      LocalVariableTable:
        Start  Length  Slot  Name   Signature
            0      70     0  this   Lcom/fasterxml/jackson/core/base/ParserBase;
      StackMapTable: number_of_entries = 5
        frame_type = 12 /* same */
        frame_type = 22 /* same */
        frame_type = 12 /* same */
        frame_type = 3 /* same */
        frame_type = 13 /* same */
    Exceptions:
      throws java.io.IOException

  public int getIntValue() throws java.io.IOException;
    descriptor: ()I
    flags: (0x0001) ACC_PUBLIC
    Code:
      stack=2, locals=1, args_size=1
         0: aload_0
         1: getfield      #5                  // Field _numTypesValid:I
         4: iconst_1
         5: iand
         6: ifne          34
         9: aload_0
        10: getfield      #5                  // Field _numTypesValid:I
        13: ifne          21
        16: aload_0
        17: invokevirtual #108                // Method _parseIntValue:()I
        20: ireturn
        21: aload_0
        22: getfield      #5                  // Field _numTypesValid:I
        25: iconst_1
        26: iand
        27: ifne          34
        30: aload_0
        31: invokevirtual #109                // Method convertNumberToInt:()V
        34: aload_0
        35: getfield      #95                 // Field _numberInt:I
        38: ireturn
      LineNumberTable:
        line 687: 0
        line 688: 9
        line 689: 16
        line 691: 21
        line 692: 30
        line 695: 34
      LocalVariableTable:
        Start  Length  Slot  Name   Signature
            0      39     0  this   Lcom/fasterxml/jackson/core/base/ParserBase;
      StackMapTable: number_of_entries = 2
        frame_type = 21 /* same */
        frame_type = 12 /* same */
    Exceptions:
      throws java.io.IOException

  public long getLongValue() throws java.io.IOException;
    descriptor: ()J
    flags: (0x0001) ACC_PUBLIC
    Code:
      stack=2, locals=1, args_size=1
         0: aload_0
         1: getfield      #5                  // Field _numTypesValid:I
         4: iconst_2
         5: iand
         6: ifne          34
         9: aload_0
        10: getfield      #5                  // Field _numTypesValid:I
        13: ifne          21
        16: aload_0
        17: iconst_2
        18: invokevirtual #94                 // Method _parseNumericValue:(I)V
        21: aload_0
        22: getfield      #5                  // Field _numTypesValid:I
        25: iconst_2
        26: iand
        27: ifne          34
        30: aload_0
        31: invokevirtual #110                // Method convertNumberToLong:()V
        34: aload_0
        35: getfield      #97                 // Field _numberLong:J
        38: lreturn
      LineNumberTable:
        line 701: 0
        line 702: 9
        line 703: 16
        line 705: 21
        line 706: 30
        line 709: 34
      LocalVariableTable:
        Start  Length  Slot  Name   Signature
            0      39     0  this   Lcom/fasterxml/jackson/core/base/ParserBase;
      StackMapTable: number_of_entries = 2
        frame_type = 21 /* same */
        frame_type = 12 /* same */
    Exceptions:
      throws java.io.IOException

  public java.math.BigInteger getBigIntegerValue() throws java.io.IOException;
    descriptor: ()Ljava/math/BigInteger;
    flags: (0x0001) ACC_PUBLIC
    Code:
      stack=2, locals=1, args_size=1
         0: aload_0
         1: getfield      #5                  // Field _numTypesValid:I
         4: iconst_4
         5: iand
         6: ifne          34
         9: aload_0
        10: getfield      #5                  // Field _numTypesValid:I
        13: ifne          21
        16: aload_0
        17: iconst_4
        18: invokevirtual #94                 // Method _parseNumericValue:(I)V
        21: aload_0
        22: getfield      #5                  // Field _numTypesValid:I
        25: iconst_4
        26: iand
        27: ifne          34
        30: aload_0
        31: invokevirtual #111                // Method convertNumberToBigInteger:()V
        34: aload_0
        35: getfield      #99                 // Field _numberBigInt:Ljava/math/BigInteger;
        38: areturn
      LineNumberTable:
        line 715: 0
        line 716: 9
        line 717: 16
        line 719: 21
        line 720: 30
        line 723: 34
      LocalVariableTable:
        Start  Length  Slot  Name   Signature
            0      39     0  this   Lcom/fasterxml/jackson/core/base/ParserBase;
      StackMapTable: number_of_entries = 2
        frame_type = 21 /* same */
        frame_type = 12 /* same */
    Exceptions:
      throws java.io.IOException

  public float getFloatValue() throws java.io.IOException;
    descriptor: ()F
    flags: (0x0001) ACC_PUBLIC
    Code:
      stack=2, locals=3, args_size=1
         0: aload_0
         1: invokevirtual #112                // Method getDoubleValue:()D
         4: dstore_1
         5: dload_1
         6: d2f
         7: freturn
      LineNumberTable:
        line 729: 0
        line 738: 5
      LocalVariableTable:
        Start  Length  Slot  Name   Signature
            0       8     0  this   Lcom/fasterxml/jackson/core/base/ParserBase;
            5       3     1 value   D
    Exceptions:
      throws java.io.IOException

  public double getDoubleValue() throws java.io.IOException;
    descriptor: ()D
    flags: (0x0001) ACC_PUBLIC
    Code:
      stack=2, locals=1, args_size=1
         0: aload_0
         1: getfield      #5                  // Field _numTypesValid:I
         4: bipush        8
         6: iand
         7: ifne          37
        10: aload_0
        11: getfield      #5                  // Field _numTypesValid:I
        14: ifne          23
        17: aload_0
        18: bipush        8
        20: invokevirtual #94                 // Method _parseNumericValue:(I)V
        23: aload_0
        24: getfield      #5                  // Field _numTypesValid:I
        27: bipush        8
        29: iand
        30: ifne          37
        33: aload_0
        34: invokevirtual #113                // Method convertNumberToDouble:()V
        37: aload_0
        38: getfield      #91                 // Field _numberDouble:D
        41: dreturn
      LineNumberTable:
        line 744: 0
        line 745: 10
        line 746: 17
        line 748: 23
        line 749: 33
        line 752: 37
      LocalVariableTable:
        Start  Length  Slot  Name   Signature
            0      42     0  this   Lcom/fasterxml/jackson/core/base/ParserBase;
      StackMapTable: number_of_entries = 2
        frame_type = 23 /* same */
        frame_type = 13 /* same */
    Exceptions:
      throws java.io.IOException

  public java.math.BigDecimal getDecimalValue() throws java.io.IOException;
    descriptor: ()Ljava/math/BigDecimal;
    flags: (0x0001) ACC_PUBLIC
    Code:
      stack=2, locals=1, args_size=1
         0: aload_0
         1: getfield      #5                  // Field _numTypesValid:I
         4: bipush        16
         6: iand
         7: ifne          37
        10: aload_0
        11: getfield      #5                  // Field _numTypesValid:I
        14: ifne          23
        17: aload_0
        18: bipush        16
        20: invokevirtual #94                 // Method _parseNumericValue:(I)V
        23: aload_0
        24: getfield      #5                  // Field _numTypesValid:I
        27: bipush        16
        29: iand
        30: ifne          37
        33: aload_0
        34: invokevirtual #114                // Method convertNumberToBigDecimal:()V
        37: aload_0
        38: getfield      #101                // Field _numberBigDecimal:Ljava/math/BigDecimal;
        41: areturn
      LineNumberTable:
        line 758: 0
        line 759: 10
        line 760: 17
        line 762: 23
        line 763: 33
        line 766: 37
      LocalVariableTable:
        Start  Length  Slot  Name   Signature
            0      42     0  this   Lcom/fasterxml/jackson/core/base/ParserBase;
      StackMapTable: number_of_entries = 2
        frame_type = 23 /* same */
        frame_type = 13 /* same */
    Exceptions:
      throws java.io.IOException

  protected void _parseNumericValue(int) throws java.io.IOException;
    descriptor: (I)V
    flags: (0x0004) ACC_PROTECTED
    Code:
      stack=4, locals=5, args_size=2
         0: aload_0
         1: getfield      #31                 // Field _closed:Z
         4: ifeq          13
         7: aload_0
         8: ldc           #115                // String Internal error: _parseNumericValue called when parser instance closed
        10: invokevirtual #58                 // Method _reportError:(Ljava/lang/String;)V
        13: aload_0
        14: getfield      #22                 // Field _currToken:Lcom/fasterxml/jackson/core/JsonToken;
        17: getstatic     #88                 // Field com/fasterxml/jackson/core/JsonToken.VALUE_NUMBER_INT:Lcom/fasterxml/jackson/core/JsonToken;
        20: if_acmpne     145
        23: aload_0
        24: getfield      #85                 // Field _intLength:I
        27: istore_2
        28: iload_2
        29: bipush        9
        31: if_icmpgt     57
        34: aload_0
        35: getfield      #8                  // Field _textBuffer:Lcom/fasterxml/jackson/core/util/TextBuffer;
        38: aload_0
        39: getfield      #84                 // Field _numberNegative:Z
        42: invokevirtual #116                // Method com/fasterxml/jackson/core/util/TextBuffer.contentsAsInt:(Z)I
        45: istore_3
        46: aload_0
        47: iload_3
        48: putfield      #95                 // Field _numberInt:I
        51: aload_0
        52: iconst_1
        53: putfield      #5                  // Field _numTypesValid:I
        56: return
        57: iload_2
        58: bipush        18
        60: if_icmpgt     139
        63: aload_0
        64: getfield      #8                  // Field _textBuffer:Lcom/fasterxml/jackson/core/util/TextBuffer;
        67: aload_0
        68: getfield      #84                 // Field _numberNegative:Z
        71: invokevirtual #117                // Method com/fasterxml/jackson/core/util/TextBuffer.contentsAsLong:(Z)J
        74: lstore_3
        75: iload_2
        76: bipush        10
        78: if_icmpne     128
        81: aload_0
        82: getfield      #84                 // Field _numberNegative:Z
        85: ifeq          108
        88: lload_3
        89: ldc2_w        #118                // long -2147483648l
        92: lcmp
        93: iflt          128
        96: aload_0
        97: lload_3
        98: l2i
        99: putfield      #95                 // Field _numberInt:I
       102: aload_0
       103: iconst_1
       104: putfield      #5                  // Field _numTypesValid:I
       107: return
       108: lload_3
       109: ldc2_w        #120                // long 2147483647l
       112: lcmp
       113: ifgt          128
       116: aload_0
       117: lload_3
       118: l2i
       119: putfield      #95                 // Field _numberInt:I
       122: aload_0
       123: iconst_1
       124: putfield      #5                  // Field _numTypesValid:I
       127: return
       128: aload_0
       129: lload_3
       130: putfield      #97                 // Field _numberLong:J
       133: aload_0
       134: iconst_2
       135: putfield      #5                  // Field _numTypesValid:I
       138: return
       139: aload_0
       140: iload_1
       141: invokespecial #122                // Method _parseSlowInt:(I)V
       144: return
       145: aload_0
       146: getfield      #22                 // Field _currToken:Lcom/fasterxml/jackson/core/JsonToken;
       149: getstatic     #89                 // Field com/fasterxml/jackson/core/JsonToken.VALUE_NUMBER_FLOAT:Lcom/fasterxml/jackson/core/JsonToken;
       152: if_acmpne     161
       155: aload_0
       156: iload_1
       157: invokespecial #123                // Method _parseSlowFloat:(I)V
       160: return
       161: aload_0
       162: ldc           #124                // String Current token (%s) not numeric, can not use numeric value accessors
       164: aload_0
       165: getfield      #22                 // Field _currToken:Lcom/fasterxml/jackson/core/JsonToken;
       168: invokevirtual #125                // Method _reportError:(Ljava/lang/String;Ljava/lang/Object;)V
       171: return
      LineNumberTable:
        line 792: 0
        line 793: 7
        line 797: 13
        line 798: 23
        line 800: 28
        line 801: 34
        line 802: 46
        line 803: 51
        line 804: 56
        line 806: 57
        line 807: 63
        line 809: 75
        line 810: 81
        line 811: 88
        line 812: 96
        line 813: 102
        line 814: 107
        line 817: 108
        line 818: 116
        line 819: 122
        line 820: 127
        line 824: 128
        line 825: 133
        line 826: 138
        line 828: 139
        line 829: 144
        line 831: 145
        line 832: 155
        line 833: 160
        line 835: 161
        line 836: 171
      LocalVariableTable:
        Start  Length  Slot  Name   Signature
           46      11     3     i   I
           75      64     3     l   J
           28     117     2   len   I
            0     172     0  this   Lcom/fasterxml/jackson/core/base/ParserBase;
            0     172     1 expType   I
      StackMapTable: number_of_entries = 7
        frame_type = 13 /* same */
        frame_type = 252 /* append */
          offset_delta = 43
          locals = [ int ]
        frame_type = 252 /* append */
          offset_delta = 50
          locals = [ long ]
        frame_type = 19 /* same */
        frame_type = 250 /* chop */
          offset_delta = 10
        frame_type = 250 /* chop */
          offset_delta = 5
        frame_type = 15 /* same */
    Exceptions:
      throws java.io.IOException

  protected int _parseIntValue() throws java.io.IOException;
    descriptor: ()I
    flags: (0x0004) ACC_PROTECTED
    Code:
      stack=2, locals=2, args_size=1
         0: aload_0
         1: getfield      #31                 // Field _closed:Z
         4: ifeq          13
         7: aload_0
         8: ldc           #115                // String Internal error: _parseNumericValue called when parser instance closed
        10: invokevirtual #58                 // Method _reportError:(Ljava/lang/String;)V
        13: aload_0
        14: getfield      #22                 // Field _currToken:Lcom/fasterxml/jackson/core/JsonToken;
        17: getstatic     #88                 // Field com/fasterxml/jackson/core/JsonToken.VALUE_NUMBER_INT:Lcom/fasterxml/jackson/core/JsonToken;
        20: if_acmpne     56
        23: aload_0
        24: getfield      #85                 // Field _intLength:I
        27: bipush        9
        29: if_icmpgt     56
        32: aload_0
        33: getfield      #8                  // Field _textBuffer:Lcom/fasterxml/jackson/core/util/TextBuffer;
        36: aload_0
        37: getfield      #84                 // Field _numberNegative:Z
        40: invokevirtual #116                // Method com/fasterxml/jackson/core/util/TextBuffer.contentsAsInt:(Z)I
        43: istore_1
        44: aload_0
        45: iload_1
        46: putfield      #95                 // Field _numberInt:I
        49: aload_0
        50: iconst_1
        51: putfield      #5                  // Field _numTypesValid:I
        54: iload_1
        55: ireturn
        56: aload_0
        57: iconst_1
        58: invokevirtual #94                 // Method _parseNumericValue:(I)V
        61: aload_0
        62: getfield      #5                  // Field _numTypesValid:I
        65: iconst_1
        66: iand
        67: ifne          74
        70: aload_0
        71: invokevirtual #109                // Method convertNumberToInt:()V
        74: aload_0
        75: getfield      #95                 // Field _numberInt:I
        78: ireturn
      LineNumberTable:
        line 844: 0
        line 845: 7
        line 848: 13
        line 849: 23
        line 850: 32
        line 851: 44
        line 852: 49
        line 853: 54
        line 857: 56
        line 858: 61
        line 859: 70
        line 861: 74
      LocalVariableTable:
        Start  Length  Slot  Name   Signature
           44      12     1     i   I
            0      79     0  this   Lcom/fasterxml/jackson/core/base/ParserBase;
      StackMapTable: number_of_entries = 3
        frame_type = 13 /* same */
        frame_type = 42 /* same */
        frame_type = 17 /* same */
    Exceptions:
      throws java.io.IOException

  private void _parseSlowFloat(int) throws java.io.IOException;
    descriptor: (I)V
    flags: (0x0002) ACC_PRIVATE
    Code:
      stack=4, locals=3, args_size=2
         0: iload_1
         1: bipush        16
         3: if_icmpne     26
         6: aload_0
         7: aload_0
         8: getfield      #8                  // Field _textBuffer:Lcom/fasterxml/jackson/core/util/TextBuffer;
        11: invokevirtual #126                // Method com/fasterxml/jackson/core/util/TextBuffer.contentsAsDecimal:()Ljava/math/BigDecimal;
        14: putfield      #101                // Field _numberBigDecimal:Ljava/math/BigDecimal;
        17: aload_0
        18: bipush        16
        20: putfield      #5                  // Field _numTypesValid:I
        23: goto          43
        26: aload_0
        27: aload_0
        28: getfield      #8                  // Field _textBuffer:Lcom/fasterxml/jackson/core/util/TextBuffer;
        31: invokevirtual #127                // Method com/fasterxml/jackson/core/util/TextBuffer.contentsAsDouble:()D
        34: putfield      #91                 // Field _numberDouble:D
        37: aload_0
        38: bipush        8
        40: putfield      #5                  // Field _numTypesValid:I
        43: goto          86
        46: astore_2
        47: aload_0
        48: new           #51                 // class java/lang/StringBuilder
        51: dup
        52: invokespecial #52                 // Method java/lang/StringBuilder."<init>":()V
        55: ldc           #129                // String Malformed numeric value (
        57: invokevirtual #54                 // Method java/lang/StringBuilder.append:(Ljava/lang/String;)Ljava/lang/StringBuilder;
        60: aload_0
        61: aload_0
        62: getfield      #8                  // Field _textBuffer:Lcom/fasterxml/jackson/core/util/TextBuffer;
        65: invokevirtual #130                // Method com/fasterxml/jackson/core/util/TextBuffer.contentsAsString:()Ljava/lang/String;
        68: invokevirtual #131                // Method _longNumberDesc:(Ljava/lang/String;)Ljava/lang/String;
        71: invokevirtual #54                 // Method java/lang/StringBuilder.append:(Ljava/lang/String;)Ljava/lang/StringBuilder;
        74: ldc           #132                // String )
        76: invokevirtual #54                 // Method java/lang/StringBuilder.append:(Ljava/lang/String;)Ljava/lang/StringBuilder;
        79: invokevirtual #57                 // Method java/lang/StringBuilder.toString:()Ljava/lang/String;
        82: aload_2
        83: invokevirtual #133                // Method _wrapError:(Ljava/lang/String;Ljava/lang/Throwable;)V
        86: return
      Exception table:
         from    to  target type
             0    43    46   Class java/lang/NumberFormatException
      LineNumberTable:
        line 874: 0
        line 875: 6
        line 876: 17
        line 879: 26
        line 880: 37
        line 885: 43
        line 882: 46
        line 884: 47
        line 886: 86
      LocalVariableTable:
        Start  Length  Slot  Name   Signature
           47      39     2   nex   Ljava/lang/NumberFormatException;
            0      87     0  this   Lcom/fasterxml/jackson/core/base/ParserBase;
            0      87     1 expType   I
      StackMapTable: number_of_entries = 4
        frame_type = 26 /* same */
        frame_type = 16 /* same */
        frame_type = 66 /* same_locals_1_stack_item */
          stack = [ class java/lang/NumberFormatException ]
        frame_type = 39 /* same */
    Exceptions:
      throws java.io.IOException

  private void _parseSlowInt(int) throws java.io.IOException;
    descriptor: (I)V
    flags: (0x0002) ACC_PRIVATE
    Code:
      stack=4, locals=6, args_size=2
         0: aload_0
         1: getfield      #8                  // Field _textBuffer:Lcom/fasterxml/jackson/core/util/TextBuffer;
         4: invokevirtual #130                // Method com/fasterxml/jackson/core/util/TextBuffer.contentsAsString:()Ljava/lang/String;
         7: astore_2
         8: aload_0
         9: getfield      #85                 // Field _intLength:I
        12: istore_3
        13: aload_0
        14: getfield      #8                  // Field _textBuffer:Lcom/fasterxml/jackson/core/util/TextBuffer;
        17: invokevirtual #134                // Method com/fasterxml/jackson/core/util/TextBuffer.getTextBuffer:()[C
        20: astore        4
        22: aload_0
        23: getfield      #8                  // Field _textBuffer:Lcom/fasterxml/jackson/core/util/TextBuffer;
        26: invokevirtual #135                // Method com/fasterxml/jackson/core/util/TextBuffer.getTextOffset:()I
        29: istore        5
        31: aload_0
        32: getfield      #84                 // Field _numberNegative:Z
        35: ifeq          41
        38: iinc          5, 1
        41: aload         4
        43: iload         5
        45: iload_3
        46: aload_0
        47: getfield      #84                 // Field _numberNegative:Z
        50: invokestatic  #136                // Method com/fasterxml/jackson/core/io/NumberInput.inLongRange:([CIIZ)Z
        53: ifeq          72
        56: aload_0
        57: aload_2
        58: invokestatic  #137                // Method java/lang/Long.parseLong:(Ljava/lang/String;)J
        61: putfield      #97                 // Field _numberLong:J
        64: aload_0
        65: iconst_2
        66: putfield      #5                  // Field _numTypesValid:I
        69: goto          134
        72: iload_1
        73: iconst_1
        74: if_icmpeq     82
        77: iload_1
        78: iconst_2
        79: if_icmpne     88
        82: aload_0
        83: iload_1
        84: aload_2
        85: invokevirtual #138                // Method _reportTooLongIntegral:(ILjava/lang/String;)V
        88: iload_1
        89: bipush        8
        91: if_icmpeq     100
        94: iload_1
        95: bipush        32
        97: if_icmpne     117
       100: aload_0
       101: aload_2
       102: invokestatic  #139                // Method com/fasterxml/jackson/core/io/NumberInput.parseDouble:(Ljava/lang/String;)D
       105: putfield      #91                 // Field _numberDouble:D
       108: aload_0
       109: bipush        8
       111: putfield      #5                  // Field _numTypesValid:I
       114: goto          134
       117: aload_0
       118: new           #140                // class java/math/BigInteger
       121: dup
       122: aload_2
       123: invokespecial #141                // Method java/math/BigInteger."<init>":(Ljava/lang/String;)V
       126: putfield      #99                 // Field _numberBigInt:Ljava/math/BigInteger;
       129: aload_0
       130: iconst_4
       131: putfield      #5                  // Field _numTypesValid:I
       134: goto          171
       137: astore_3
       138: aload_0
       139: new           #51                 // class java/lang/StringBuilder
       142: dup
       143: invokespecial #52                 // Method java/lang/StringBuilder."<init>":()V
       146: ldc           #129                // String Malformed numeric value (
       148: invokevirtual #54                 // Method java/lang/StringBuilder.append:(Ljava/lang/String;)Ljava/lang/StringBuilder;
       151: aload_0
       152: aload_2
       153: invokevirtual #131                // Method _longNumberDesc:(Ljava/lang/String;)Ljava/lang/String;
       156: invokevirtual #54                 // Method java/lang/StringBuilder.append:(Ljava/lang/String;)Ljava/lang/StringBuilder;
       159: ldc           #132                // String )
       161: invokevirtual #54                 // Method java/lang/StringBuilder.append:(Ljava/lang/String;)Ljava/lang/StringBuilder;
       164: invokevirtual #57                 // Method java/lang/StringBuilder.toString:()Ljava/lang/String;
       167: aload_3
       168: invokevirtual #133                // Method _wrapError:(Ljava/lang/String;Ljava/lang/Throwable;)V
       171: return
      Exception table:
         from    to  target type
             8   134   137   Class java/lang/NumberFormatException
      LineNumberTable:
        line 890: 0
        line 892: 8
        line 893: 13
        line 894: 22
        line 895: 31
        line 896: 38
        line 899: 41
        line 901: 56
        line 902: 64
        line 905: 72
        line 906: 82
        line 908: 88
        line 909: 100
        line 910: 108
        line 913: 117
        line 914: 129
        line 920: 134
        line 917: 137
        line 919: 138
        line 921: 171
      LocalVariableTable:
        Start  Length  Slot  Name   Signature
           13     121     3   len   I
           22     112     4   buf   [C
           31     103     5 offset   I
          138      33     3   nex   Ljava/lang/NumberFormatException;
            0     172     0  this   Lcom/fasterxml/jackson/core/base/ParserBase;
            0     172     1 expType   I
            8     164     2 numStr   Ljava/lang/String;
      StackMapTable: number_of_entries = 9
        frame_type = 255 /* full_frame */
          offset_delta = 41
          locals = [ class com/fasterxml/jackson/core/base/ParserBase, int, class java/lang/String, int, class "[C", int ]
          stack = []
        frame_type = 30 /* same */
        frame_type = 9 /* same */
        frame_type = 5 /* same */
        frame_type = 11 /* same */
        frame_type = 16 /* same */
        frame_type = 248 /* chop */
          offset_delta = 16
        frame_type = 66 /* same_locals_1_stack_item */
          stack = [ class java/lang/NumberFormatException ]
        frame_type = 33 /* same */
    Exceptions:
      throws java.io.IOException

  protected void _reportTooLongIntegral(int, java.lang.String) throws java.io.IOException;
    descriptor: (ILjava/lang/String;)V
    flags: (0x0004) ACC_PROTECTED
    Code:
      stack=2, locals=3, args_size=3
         0: iload_1
         1: iconst_1
         2: if_icmpne     13
         5: aload_0
         6: aload_2
         7: invokevirtual #142                // Method reportOverflowInt:(Ljava/lang/String;)V
        10: goto          18
        13: aload_0
        14: aload_2
        15: invokevirtual #143                // Method reportOverflowLong:(Ljava/lang/String;)V
        18: return
      LineNumberTable:
        line 926: 0
        line 927: 5
        line 929: 13
        line 931: 18
      LocalVariableTable:
        Start  Length  Slot  Name   Signature
            0      19     0  this   Lcom/fasterxml/jackson/core/base/ParserBase;
            0      19     1 expType   I
            0      19     2 rawNum   Ljava/lang/String;
      StackMapTable: number_of_entries = 2
        frame_type = 13 /* same */
        frame_type = 4 /* same */
    Exceptions:
      throws java.io.IOException

  protected void convertNumberToInt() throws java.io.IOException;
    descriptor: ()V
    flags: (0x0004) ACC_PROTECTED
    Code:
      stack=4, locals=2, args_size=1
         0: aload_0
         1: getfield      #5                  // Field _numTypesValid:I
         4: iconst_2
         5: iand
         6: ifeq          45
         9: aload_0
        10: getfield      #97                 // Field _numberLong:J
        13: l2i
        14: istore_1
        15: iload_1
        16: i2l
        17: aload_0
        18: getfield      #97                 // Field _numberLong:J
        21: lcmp
        22: ifeq          37
        25: aload_0
        26: aload_0
        27: invokevirtual #60                 // Method getText:()Ljava/lang/String;
        30: aload_0
        31: invokevirtual #144                // Method currentToken:()Lcom/fasterxml/jackson/core/JsonToken;
        34: invokevirtual #145                // Method reportOverflowInt:(Ljava/lang/String;Lcom/fasterxml/jackson/core/JsonToken;)V
        37: aload_0
        38: iload_1
        39: putfield      #95                 // Field _numberInt:I
        42: goto          204
        45: aload_0
        46: getfield      #5                  // Field _numTypesValid:I
        49: iconst_4
        50: iand
        51: ifeq          98
        54: getstatic     #146                // Field BI_MIN_INT:Ljava/math/BigInteger;
        57: aload_0
        58: getfield      #99                 // Field _numberBigInt:Ljava/math/BigInteger;
        61: invokevirtual #147                // Method java/math/BigInteger.compareTo:(Ljava/math/BigInteger;)I
        64: ifgt          80
        67: getstatic     #148                // Field BI_MAX_INT:Ljava/math/BigInteger;
        70: aload_0
        71: getfield      #99                 // Field _numberBigInt:Ljava/math/BigInteger;
        74: invokevirtual #147                // Method java/math/BigInteger.compareTo:(Ljava/math/BigInteger;)I
        77: ifge          84
        80: aload_0
        81: invokevirtual #149                // Method reportOverflowInt:()V
        84: aload_0
        85: aload_0
        86: getfield      #99                 // Field _numberBigInt:Ljava/math/BigInteger;
        89: invokevirtual #150                // Method java/math/BigInteger.intValue:()I
        92: putfield      #95                 // Field _numberInt:I
        95: goto          204
        98: aload_0
        99: getfield      #5                  // Field _numTypesValid:I
       102: bipush        8
       104: iand
       105: ifeq          146
       108: aload_0
       109: getfield      #91                 // Field _numberDouble:D
       112: ldc2_w        #151                // double -2.147483648E9d
       115: dcmpg
       116: iflt          130
       119: aload_0
       120: getfield      #91                 // Field _numberDouble:D
       123: ldc2_w        #153                // double 2.147483647E9d
       126: dcmpl
       127: ifle          134
       130: aload_0
       131: invokevirtual #149                // Method reportOverflowInt:()V
       134: aload_0
       135: aload_0
       136: getfield      #91                 // Field _numberDouble:D
       139: d2i
       140: putfield      #95                 // Field _numberInt:I
       143: goto          204
       146: aload_0
       147: getfield      #5                  // Field _numTypesValid:I
       150: bipush        16
       152: iand
       153: ifeq          200
       156: getstatic     #155                // Field BD_MIN_INT:Ljava/math/BigDecimal;
       159: aload_0
       160: getfield      #101                // Field _numberBigDecimal:Ljava/math/BigDecimal;
       163: invokevirtual #156                // Method java/math/BigDecimal.compareTo:(Ljava/math/BigDecimal;)I
       166: ifgt          182
       169: getstatic     #157                // Field BD_MAX_INT:Ljava/math/BigDecimal;
       172: aload_0
       173: getfield      #101                // Field _numberBigDecimal:Ljava/math/BigDecimal;
       176: invokevirtual #156                // Method java/math/BigDecimal.compareTo:(Ljava/math/BigDecimal;)I
       179: ifge          186
       182: aload_0
       183: invokevirtual #149                // Method reportOverflowInt:()V
       186: aload_0
       187: aload_0
       188: getfield      #101                // Field _numberBigDecimal:Ljava/math/BigDecimal;
       191: invokevirtual #158                // Method java/math/BigDecimal.intValue:()I
       194: putfield      #95                 // Field _numberInt:I
       197: goto          204
       200: aload_0
       201: invokevirtual #100                // Method _throwInternal:()V
       204: aload_0
       205: dup
       206: getfield      #5                  // Field _numTypesValid:I
       209: iconst_1
       210: ior
       211: putfield      #5                  // Field _numTypesValid:I
       214: return
      LineNumberTable:
        line 942: 0
        line 944: 9
        line 945: 15
        line 946: 25
        line 948: 37
        line 949: 42
        line 950: 54
        line 951: 74
        line 952: 80
        line 954: 84
        line 955: 98
        line 957: 108
        line 958: 130
        line 960: 134
        line 961: 146
        line 962: 156
        line 963: 176
        line 964: 182
        line 966: 186
        line 968: 200
        line 970: 204
        line 971: 214
      LocalVariableTable:
        Start  Length  Slot  Name   Signature
           15      27     1 result   I
            0     215     0  this   Lcom/fasterxml/jackson/core/base/ParserBase;
      StackMapTable: number_of_entries = 12
        frame_type = 252 /* append */
          offset_delta = 37
          locals = [ int ]
        frame_type = 250 /* chop */
          offset_delta = 7
        frame_type = 34 /* same */
        frame_type = 3 /* same */
        frame_type = 13 /* same */
        frame_type = 31 /* same */
        frame_type = 3 /* same */
        frame_type = 11 /* same */
        frame_type = 35 /* same */
        frame_type = 3 /* same */
        frame_type = 13 /* same */
        frame_type = 3 /* same */
    Exceptions:
      throws java.io.IOException

  protected void convertNumberToLong() throws java.io.IOException;
    descriptor: ()V
    flags: (0x0004) ACC_PROTECTED
    Code:
      stack=4, locals=1, args_size=1
         0: aload_0
         1: getfield      #5                  // Field _numTypesValid:I
         4: iconst_1
         5: iand
         6: ifeq          21
         9: aload_0
        10: aload_0
        11: getfield      #95                 // Field _numberInt:I
        14: i2l
        15: putfield      #97                 // Field _numberLong:J
        18: goto          180
        21: aload_0
        22: getfield      #5                  // Field _numTypesValid:I
        25: iconst_4
        26: iand
        27: ifeq          74
        30: getstatic     #159                // Field BI_MIN_LONG:Ljava/math/BigInteger;
        33: aload_0
        34: getfield      #99                 // Field _numberBigInt:Ljava/math/BigInteger;
        37: invokevirtual #147                // Method java/math/BigInteger.compareTo:(Ljava/math/BigInteger;)I
        40: ifgt          56
        43: getstatic     #160                // Field BI_MAX_LONG:Ljava/math/BigInteger;
        46: aload_0
        47: getfield      #99                 // Field _numberBigInt:Ljava/math/BigInteger;
        50: invokevirtual #147                // Method java/math/BigInteger.compareTo:(Ljava/math/BigInteger;)I
        53: ifge          60
        56: aload_0
        57: invokevirtual #161                // Method reportOverflowLong:()V
        60: aload_0
        61: aload_0
        62: getfield      #99                 // Field _numberBigInt:Ljava/math/BigInteger;
        65: invokevirtual #162                // Method java/math/BigInteger.longValue:()J
        68: putfield      #97                 // Field _numberLong:J
        71: goto          180
        74: aload_0
        75: getfield      #5                  // Field _numTypesValid:I
        78: bipush        8
        80: iand
        81: ifeq          122
        84: aload_0
        85: getfield      #91                 // Field _numberDouble:D
        88: ldc2_w        #163                // double -9.223372036854776E18d
        91: dcmpg
        92: iflt          106
        95: aload_0
        96: getfield      #91                 // Field _numberDouble:D
        99: ldc2_w        #165                // double 9.223372036854776E18d
       102: dcmpl
       103: ifle          110
       106: aload_0
       107: invokevirtual #161                // Method reportOverflowLong:()V
       110: aload_0
       111: aload_0
       112: getfield      #91                 // Field _numberDouble:D
       115: d2l
       116: putfield      #97                 // Field _numberLong:J
       119: goto          180
       122: aload_0
       123: getfield      #5                  // Field _numTypesValid:I
       126: bipush        16
       128: iand
       129: ifeq          176
       132: getstatic     #167                // Field BD_MIN_LONG:Ljava/math/BigDecimal;
       135: aload_0
       136: getfield      #101                // Field _numberBigDecimal:Ljava/math/BigDecimal;
       139: invokevirtual #156                // Method java/math/BigDecimal.compareTo:(Ljava/math/BigDecimal;)I
       142: ifgt          158
       145: getstatic     #168                // Field BD_MAX_LONG:Ljava/math/BigDecimal;
       148: aload_0
       149: getfield      #101                // Field _numberBigDecimal:Ljava/math/BigDecimal;
       152: invokevirtual #156                // Method java/math/BigDecimal.compareTo:(Ljava/math/BigDecimal;)I
       155: ifge          162
       158: aload_0
       159: invokevirtual #161                // Method reportOverflowLong:()V
       162: aload_0
       163: aload_0
       164: getfield      #101                // Field _numberBigDecimal:Ljava/math/BigDecimal;
       167: invokevirtual #169                // Method java/math/BigDecimal.longValue:()J
       170: putfield      #97                 // Field _numberLong:J
       173: goto          180
       176: aload_0
       177: invokevirtual #100                // Method _throwInternal:()V
       180: aload_0
       181: dup
       182: getfield      #5                  // Field _numTypesValid:I
       185: iconst_2
       186: ior
       187: putfield      #5                  // Field _numTypesValid:I
       190: return
      LineNumberTable:
        line 975: 0
        line 976: 9
        line 977: 21
        line 978: 30
        line 979: 50
        line 980: 56
        line 982: 60
        line 983: 74
        line 985: 84
        line 986: 106
        line 988: 110
        line 989: 122
        line 990: 132
        line 991: 152
        line 992: 158
        line 994: 162
        line 996: 176
        line 998: 180
        line 999: 190
      LocalVariableTable:
        Start  Length  Slot  Name   Signature
            0     191     0  this   Lcom/fasterxml/jackson/core/base/ParserBase;
      StackMapTable: number_of_entries = 11
        frame_type = 21 /* same */
        frame_type = 34 /* same */
        frame_type = 3 /* same */
        frame_type = 13 /* same */
        frame_type = 31 /* same */
        frame_type = 3 /* same */
        frame_type = 11 /* same */
        frame_type = 35 /* same */
        frame_type = 3 /* same */
        frame_type = 13 /* same */
        frame_type = 3 /* same */
    Exceptions:
      throws java.io.IOException

  protected void convertNumberToBigInteger() throws java.io.IOException;
    descriptor: ()V
    flags: (0x0004) ACC_PROTECTED
    Code:
      stack=3, locals=1, args_size=1
         0: aload_0
         1: getfield      #5                  // Field _numTypesValid:I
         4: bipush        16
         6: iand
         7: ifeq          24
        10: aload_0
        11: aload_0
        12: getfield      #101                // Field _numberBigDecimal:Ljava/math/BigDecimal;
        15: invokevirtual #170                // Method java/math/BigDecimal.toBigInteger:()Ljava/math/BigInteger;
        18: putfield      #99                 // Field _numberBigInt:Ljava/math/BigInteger;
        21: goto          102
        24: aload_0
        25: getfield      #5                  // Field _numTypesValid:I
        28: iconst_2
        29: iand
        30: ifeq          47
        33: aload_0
        34: aload_0
        35: getfield      #97                 // Field _numberLong:J
        38: invokestatic  #171                // Method java/math/BigInteger.valueOf:(J)Ljava/math/BigInteger;
        41: putfield      #99                 // Field _numberBigInt:Ljava/math/BigInteger;
        44: goto          102
        47: aload_0
        48: getfield      #5                  // Field _numTypesValid:I
        51: iconst_1
        52: iand
        53: ifeq          71
        56: aload_0
        57: aload_0
        58: getfield      #95                 // Field _numberInt:I
        61: i2l
        62: invokestatic  #171                // Method java/math/BigInteger.valueOf:(J)Ljava/math/BigInteger;
        65: putfield      #99                 // Field _numberBigInt:Ljava/math/BigInteger;
        68: goto          102
        71: aload_0
        72: getfield      #5                  // Field _numTypesValid:I
        75: bipush        8
        77: iand
        78: ifeq          98
        81: aload_0
        82: aload_0
        83: getfield      #91                 // Field _numberDouble:D
        86: invokestatic  #172                // Method java/math/BigDecimal.valueOf:(D)Ljava/math/BigDecimal;
        89: invokevirtual #170                // Method java/math/BigDecimal.toBigInteger:()Ljava/math/BigInteger;
        92: putfield      #99                 // Field _numberBigInt:Ljava/math/BigInteger;
        95: goto          102
        98: aload_0
        99: invokevirtual #100                // Method _throwInternal:()V
       102: aload_0
       103: dup
       104: getfield      #5                  // Field _numTypesValid:I
       107: iconst_4
       108: ior
       109: putfield      #5                  // Field _numTypesValid:I
       112: return
      LineNumberTable:
        line 1003: 0
        line 1005: 10
        line 1006: 24
        line 1007: 33
        line 1008: 47
        line 1009: 56
        line 1010: 71
        line 1011: 81
        line 1013: 98
        line 1015: 102
        line 1016: 112
      LocalVariableTable:
        Start  Length  Slot  Name   Signature
            0     113     0  this   Lcom/fasterxml/jackson/core/base/ParserBase;
      StackMapTable: number_of_entries = 5
        frame_type = 24 /* same */
        frame_type = 22 /* same */
        frame_type = 23 /* same */
        frame_type = 26 /* same */
        frame_type = 3 /* same */
    Exceptions:
      throws java.io.IOException

  protected void convertNumberToDouble() throws java.io.IOException;
    descriptor: ()V
    flags: (0x0004) ACC_PROTECTED
    Code:
      stack=3, locals=1, args_size=1
         0: aload_0
         1: getfield      #5                  // Field _numTypesValid:I
         4: bipush        16
         6: iand
         7: ifeq          24
        10: aload_0
        11: aload_0
        12: getfield      #101                // Field _numberBigDecimal:Ljava/math/BigDecimal;
        15: invokevirtual #173                // Method java/math/BigDecimal.doubleValue:()D
        18: putfield      #91                 // Field _numberDouble:D
        21: goto          93
        24: aload_0
        25: getfield      #5                  // Field _numTypesValid:I
        28: iconst_4
        29: iand
        30: ifeq          47
        33: aload_0
        34: aload_0
        35: getfield      #99                 // Field _numberBigInt:Ljava/math/BigInteger;
        38: invokevirtual #174                // Method java/math/BigInteger.doubleValue:()D
        41: putfield      #91                 // Field _numberDouble:D
        44: goto          93
        47: aload_0
        48: getfield      #5                  // Field _numTypesValid:I
        51: iconst_2
        52: iand
        53: ifeq          68
        56: aload_0
        57: aload_0
        58: getfield      #97                 // Field _numberLong:J
        61: l2d
        62: putfield      #91                 // Field _numberDouble:D
        65: goto          93
        68: aload_0
        69: getfield      #5                  // Field _numTypesValid:I
        72: iconst_1
        73: iand
        74: ifeq          89
        77: aload_0
        78: aload_0
        79: getfield      #95                 // Field _numberInt:I
        82: i2d
        83: putfield      #91                 // Field _numberDouble:D
        86: goto          93
        89: aload_0
        90: invokevirtual #100                // Method _throwInternal:()V
        93: aload_0
        94: dup
        95: getfield      #5                  // Field _numTypesValid:I
        98: bipush        8
       100: ior
       101: putfield      #5                  // Field _numTypesValid:I
       104: return
      LineNumberTable:
        line 1026: 0
        line 1027: 10
        line 1028: 24
        line 1029: 33
        line 1030: 47
        line 1031: 56
        line 1032: 68
        line 1033: 77
        line 1035: 89
        line 1037: 93
        line 1038: 104
      LocalVariableTable:
        Start  Length  Slot  Name   Signature
            0     105     0  this   Lcom/fasterxml/jackson/core/base/ParserBase;
      StackMapTable: number_of_entries = 5
        frame_type = 24 /* same */
        frame_type = 22 /* same */
        frame_type = 20 /* same */
        frame_type = 20 /* same */
        frame_type = 3 /* same */
    Exceptions:
      throws java.io.IOException

  protected void convertNumberToBigDecimal() throws java.io.IOException;
    descriptor: ()V
    flags: (0x0004) ACC_PROTECTED
    Code:
      stack=4, locals=1, args_size=1
         0: aload_0
         1: getfield      #5                  // Field _numTypesValid:I
         4: bipush        8
         6: iand
         7: ifeq          24
        10: aload_0
        11: aload_0
        12: invokevirtual #60                 // Method getText:()Ljava/lang/String;
        15: invokestatic  #175                // Method com/fasterxml/jackson/core/io/NumberInput.parseBigDecimal:(Ljava/lang/String;)Ljava/math/BigDecimal;
        18: putfield      #101                // Field _numberBigDecimal:Ljava/math/BigDecimal;
        21: goto          102
        24: aload_0
        25: getfield      #5                  // Field _numTypesValid:I
        28: iconst_4
        29: iand
        30: ifeq          51
        33: aload_0
        34: new           #176                // class java/math/BigDecimal
        37: dup
        38: aload_0
        39: getfield      #99                 // Field _numberBigInt:Ljava/math/BigInteger;
        42: invokespecial #177                // Method java/math/BigDecimal."<init>":(Ljava/math/BigInteger;)V
        45: putfield      #101                // Field _numberBigDecimal:Ljava/math/BigDecimal;
        48: goto          102
        51: aload_0
        52: getfield      #5                  // Field _numTypesValid:I
        55: iconst_2
        56: iand
        57: ifeq          74
        60: aload_0
        61: aload_0
        62: getfield      #97                 // Field _numberLong:J
        65: invokestatic  #178                // Method java/math/BigDecimal.valueOf:(J)Ljava/math/BigDecimal;
        68: putfield      #101                // Field _numberBigDecimal:Ljava/math/BigDecimal;
        71: goto          102
        74: aload_0
        75: getfield      #5                  // Field _numTypesValid:I
        78: iconst_1
        79: iand
        80: ifeq          98
        83: aload_0
        84: aload_0
        85: getfield      #95                 // Field _numberInt:I
        88: i2l
        89: invokestatic  #178                // Method java/math/BigDecimal.valueOf:(J)Ljava/math/BigDecimal;
        92: putfield      #101                // Field _numberBigDecimal:Ljava/math/BigDecimal;
        95: goto          102
        98: aload_0
        99: invokevirtual #100                // Method _throwInternal:()V
       102: aload_0
       103: dup
       104: getfield      #5                  // Field _numTypesValid:I
       107: bipush        16
       109: ior
       110: putfield      #5                  // Field _numTypesValid:I
       113: return
      LineNumberTable:
        line 1048: 0
        line 1052: 10
        line 1053: 24
        line 1054: 33
        line 1055: 51
        line 1056: 60
        line 1057: 74
        line 1058: 83
        line 1060: 98
        line 1062: 102
        line 1063: 113
      LocalVariableTable:
        Start  Length  Slot  Name   Signature
            0     114     0  this   Lcom/fasterxml/jackson/core/base/ParserBase;
      StackMapTable: number_of_entries = 5
        frame_type = 24 /* same */
        frame_type = 26 /* same */
        frame_type = 22 /* same */
        frame_type = 23 /* same */
        frame_type = 3 /* same */
    Exceptions:
      throws java.io.IOException

  protected void _reportMismatchedEndMarker(int, char) throws com.fasterxml.jackson.core.JsonParseException;
    descriptor: (IC)V
    flags: (0x0004) ACC_PROTECTED
    Code:
      stack=7, locals=4, args_size=3
         0: aload_0
         1: invokevirtual #179                // Method getParsingContext:()Lcom/fasterxml/jackson/core/json/JsonReadContext;
         4: astore_3
         5: aload_0
         6: ldc           #180                // String Unexpected close marker \'%s\': expected \'%c\' (for %s starting at %s)
         8: iconst_4
         9: anewarray     #73                 // class java/lang/Object
        12: dup
        13: iconst_0
        14: iload_1
        15: i2c
        16: invokestatic  #181                // Method java/lang/Character.valueOf:(C)Ljava/lang/Character;
        19: aastore
        20: dup
        21: iconst_1
        22: iload_2
        23: invokestatic  #181                // Method java/lang/Character.valueOf:(C)Ljava/lang/Character;
        26: aastore
        27: dup
        28: iconst_2
        29: aload_3
        30: invokevirtual #182                // Method com/fasterxml/jackson/core/json/JsonReadContext.typeDesc:()Ljava/lang/String;
        33: aastore
        34: dup
        35: iconst_3
        36: aload_3
        37: aload_0
        38: invokevirtual #38                 // Method _contentReference:()Lcom/fasterxml/jackson/core/io/ContentReference;
        41: invokevirtual #74                 // Method com/fasterxml/jackson/core/json/JsonReadContext.startLocation:(Lcom/fasterxml/jackson/core/io/ContentReference;)Lcom/fasterxml/jackson/core/JsonLocation;
        44: aastore
        45: invokestatic  #75                 // Method java/lang/String.format:(Ljava/lang/String;[Ljava/lang/Object;)Ljava/lang/String;
        48: invokevirtual #58                 // Method _reportError:(Ljava/lang/String;)V
        51: return
      LineNumberTable:
        line 1072: 0
        line 1073: 5
        line 1075: 16
        line 1076: 38
        line 1073: 45
        line 1077: 51
      LocalVariableTable:
        Start  Length  Slot  Name   Signature
            0      52     0  this   Lcom/fasterxml/jackson/core/base/ParserBase;
            0      52     1 actCh   I
            0      52     2 expCh   C
            5      47     3  ctxt   Lcom/fasterxml/jackson/core/json/JsonReadContext;
    Exceptions:
      throws com.fasterxml.jackson.core.JsonParseException

  protected char _handleUnrecognizedCharacterEscape(char) throws com.fasterxml.jackson.core.JsonProcessingException;
    descriptor: (C)C
    flags: (0x0004) ACC_PROTECTED
    Code:
      stack=3, locals=2, args_size=2
         0: aload_0
         1: getstatic     #183                // Field com/fasterxml/jackson/core/JsonParser$Feature.ALLOW_BACKSLASH_ESCAPING_ANY_CHARACTER:Lcom/fasterxml/jackson/core/JsonParser$Feature;
         4: invokevirtual #184                // Method isEnabled:(Lcom/fasterxml/jackson/core/JsonParser$Feature;)Z
         7: ifeq          12
        10: iload_1
        11: ireturn
        12: iload_1
        13: bipush        39
        15: if_icmpne     30
        18: aload_0
        19: getstatic     #185                // Field com/fasterxml/jackson/core/JsonParser$Feature.ALLOW_SINGLE_QUOTES:Lcom/fasterxml/jackson/core/JsonParser$Feature;
        22: invokevirtual #184                // Method isEnabled:(Lcom/fasterxml/jackson/core/JsonParser$Feature;)Z
        25: ifeq          30
        28: iload_1
        29: ireturn
        30: aload_0
        31: new           #51                 // class java/lang/StringBuilder
        34: dup
        35: invokespecial #52                 // Method java/lang/StringBuilder."<init>":()V
        38: ldc           #186                // String Unrecognized character escape
        40: invokevirtual #54                 // Method java/lang/StringBuilder.append:(Ljava/lang/String;)Ljava/lang/StringBuilder;
        43: iload_1
        44: invokestatic  #187                // Method _getCharDesc:(I)Ljava/lang/String;
        47: invokevirtual #54                 // Method java/lang/StringBuilder.append:(Ljava/lang/String;)Ljava/lang/StringBuilder;
        50: invokevirtual #57                 // Method java/lang/StringBuilder.toString:()Ljava/lang/String;
        53: invokevirtual #58                 // Method _reportError:(Ljava/lang/String;)V
        56: iload_1
        57: ireturn
      LineNumberTable:
        line 1082: 0
        line 1083: 10
        line 1086: 12
        line 1087: 28
        line 1089: 30
        line 1090: 56
      LocalVariableTable:
        Start  Length  Slot  Name   Signature
            0      58     0  this   Lcom/fasterxml/jackson/core/base/ParserBase;
            0      58     1    ch   C
      StackMapTable: number_of_entries = 2
        frame_type = 12 /* same */
        frame_type = 17 /* same */
    Exceptions:
      throws com.fasterxml.jackson.core.JsonProcessingException

  protected void _throwUnquotedSpace(int, java.lang.String) throws com.fasterxml.jackson.core.JsonParseException;
    descriptor: (ILjava/lang/String;)V
    flags: (0x0004) ACC_PROTECTED
    Code:
      stack=2, locals=5, args_size=3
         0: aload_0
         1: getstatic     #188                // Field com/fasterxml/jackson/core/JsonParser$Feature.ALLOW_UNQUOTED_CONTROL_CHARS:Lcom/fasterxml/jackson/core/JsonParser$Feature;
         4: invokevirtual #184                // Method isEnabled:(Lcom/fasterxml/jackson/core/JsonParser$Feature;)Z
         7: ifeq          16
        10: iload_1
        11: bipush        32
        13: if_icmple     58
        16: iload_1
        17: i2c
        18: istore_3
        19: new           #51                 // class java/lang/StringBuilder
        22: dup
        23: invokespecial #52                 // Method java/lang/StringBuilder."<init>":()V
        26: ldc           #189                // String Illegal unquoted character (
        28: invokevirtual #54                 // Method java/lang/StringBuilder.append:(Ljava/lang/String;)Ljava/lang/StringBuilder;
        31: iload_3
        32: invokestatic  #187                // Method _getCharDesc:(I)Ljava/lang/String;
        35: invokevirtual #54                 // Method java/lang/StringBuilder.append:(Ljava/lang/String;)Ljava/lang/StringBuilder;
        38: ldc           #190                // String ): has to be escaped using backslash to be included in
        40: invokevirtual #54                 // Method java/lang/StringBuilder.append:(Ljava/lang/String;)Ljava/lang/StringBuilder;
        43: aload_2
        44: invokevirtual #54                 // Method java/lang/StringBuilder.append:(Ljava/lang/String;)Ljava/lang/StringBuilder;
        47: invokevirtual #57                 // Method java/lang/StringBuilder.toString:()Ljava/lang/String;
        50: astore        4
        52: aload_0
        53: aload         4
        55: invokevirtual #58                 // Method _reportError:(Ljava/lang/String;)V
        58: return
      LineNumberTable:
        line 1107: 0
        line 1108: 16
        line 1109: 19
        line 1110: 52
        line 1112: 58
      LocalVariableTable:
        Start  Length  Slot  Name   Signature
           19      39     3     c   C
           52       6     4   msg   Ljava/lang/String;
            0      59     0  this   Lcom/fasterxml/jackson/core/base/ParserBase;
            0      59     1     i   I
            0      59     2 ctxtDesc   Ljava/lang/String;
      StackMapTable: number_of_entries = 2
        frame_type = 16 /* same */
        frame_type = 41 /* same */
    Exceptions:
      throws com.fasterxml.jackson.core.JsonParseException

  protected java.lang.String _validJsonTokenList() throws java.io.IOException;
    descriptor: ()Ljava/lang/String;
    flags: (0x0004) ACC_PROTECTED
    Code:
      stack=1, locals=1, args_size=1
         0: aload_0
         1: invokevirtual #191                // Method _validJsonValueList:()Ljava/lang/String;
         4: areturn
      LineNumberTable:
        line 1124: 0
      LocalVariableTable:
        Start  Length  Slot  Name   Signature
            0       5     0  this   Lcom/fasterxml/jackson/core/base/ParserBase;
    Exceptions:
      throws java.io.IOException

  protected java.lang.String _validJsonValueList() throws java.io.IOException;
    descriptor: ()Ljava/lang/String;
    flags: (0x0004) ACC_PROTECTED
    Code:
      stack=2, locals=1, args_size=1
         0: aload_0
         1: getstatic     #192                // Field com/fasterxml/jackson/core/JsonParser$Feature.ALLOW_NON_NUMERIC_NUMBERS:Lcom/fasterxml/jackson/core/JsonParser$Feature;
         4: invokevirtual #184                // Method isEnabled:(Lcom/fasterxml/jackson/core/JsonParser$Feature;)Z
         7: ifeq          13
        10: ldc           #193                // String (JSON String, Number (or \'NaN\'/\'INF\'/\'+INF\'), Array, Object or token \'null\', \'true\' or \'false\')
        12: areturn
        13: ldc           #194                // String (JSON String, Number, Array, Object or token \'null\', \'true\' or \'false\')
        15: areturn
      LineNumberTable:
        line 1138: 0
        line 1139: 10
        line 1141: 13
      LocalVariableTable:
        Start  Length  Slot  Name   Signature
            0      16     0  this   Lcom/fasterxml/jackson/core/base/ParserBase;
      StackMapTable: number_of_entries = 1
        frame_type = 13 /* same */
    Exceptions:
      throws java.io.IOException

  protected char _decodeEscaped() throws java.io.IOException;
    descriptor: ()C
    flags: (0x0004) ACC_PROTECTED
    Code:
      stack=2, locals=1, args_size=1
         0: new           #195                // class java/lang/UnsupportedOperationException
         3: dup
         4: invokespecial #196                // Method java/lang/UnsupportedOperationException."<init>":()V
         7: athrow
      LineNumberTable:
        line 1160: 0
      LocalVariableTable:
        Start  Length  Slot  Name   Signature
            0       8     0  this   Lcom/fasterxml/jackson/core/base/ParserBase;
    Exceptions:
      throws java.io.IOException

  protected final int _decodeBase64Escape(com.fasterxml.jackson.core.Base64Variant, int, int) throws java.io.IOException;
    descriptor: (Lcom/fasterxml/jackson/core/Base64Variant;II)I
    flags: (0x0014) ACC_PROTECTED, ACC_FINAL
    Code:
      stack=4, locals=6, args_size=4
         0: iload_2
         1: bipush        92
         3: if_icmpeq     14
         6: aload_0
         7: aload_1
         8: iload_2
         9: iload_3
        10: invokevirtual #197                // Method reportInvalidBase64Char:(Lcom/fasterxml/jackson/core/Base64Variant;II)Ljava/lang/IllegalArgumentException;
        13: athrow
        14: aload_0
        15: invokevirtual #198                // Method _decodeEscaped:()C
        18: istore        4
        20: iload         4
        22: bipush        32
        24: if_icmpgt     33
        27: iload_3
        28: ifne          33
        31: iconst_m1
        32: ireturn
        33: aload_1
        34: iload         4
        36: invokevirtual #199                // Method com/fasterxml/jackson/core/Base64Variant.decodeBase64Char:(I)I
        39: istore        5
        41: iload         5
        43: ifge          62
        46: iload         5
        48: bipush        -2
        50: if_icmpeq     62
        53: aload_0
        54: aload_1
        55: iload         4
        57: iload_3
        58: invokevirtual #197                // Method reportInvalidBase64Char:(Lcom/fasterxml/jackson/core/Base64Variant;II)Ljava/lang/IllegalArgumentException;
        61: athrow
        62: iload         5
        64: ireturn
      LineNumberTable:
        line 1166: 0
        line 1167: 6
        line 1169: 14
        line 1171: 20
        line 1172: 27
        line 1173: 31
        line 1177: 33
        line 1178: 41
        line 1179: 46
        line 1180: 53
        line 1183: 62
      LocalVariableTable:
        Start  Length  Slot  Name   Signature
            0      65     0  this   Lcom/fasterxml/jackson/core/base/ParserBase;
            0      65     1 b64variant   Lcom/fasterxml/jackson/core/Base64Variant;
            0      65     2    ch   I
            0      65     3 index   I
           20      45     4 unescaped   I
           41      24     5  bits   I
      StackMapTable: number_of_entries = 3
        frame_type = 14 /* same */
        frame_type = 252 /* append */
          offset_delta = 18
          locals = [ int ]
        frame_type = 252 /* append */
          offset_delta = 28
          locals = [ int ]
    Exceptions:
      throws java.io.IOException

  protected final int _decodeBase64Escape(com.fasterxml.jackson.core.Base64Variant, char, int) throws java.io.IOException;
    descriptor: (Lcom/fasterxml/jackson/core/Base64Variant;CI)I
    flags: (0x0014) ACC_PROTECTED, ACC_FINAL
    Code:
      stack=4, locals=6, args_size=4
         0: iload_2
         1: bipush        92
         3: if_icmpeq     14
         6: aload_0
         7: aload_1
         8: iload_2
         9: iload_3
        10: invokevirtual #197                // Method reportInvalidBase64Char:(Lcom/fasterxml/jackson/core/Base64Variant;II)Ljava/lang/IllegalArgumentException;
        13: athrow
        14: aload_0
        15: invokevirtual #198                // Method _decodeEscaped:()C
        18: istore        4
        20: iload         4
        22: bipush        32
        24: if_icmpgt     33
        27: iload_3
        28: ifne          33
        31: iconst_m1
        32: ireturn
        33: aload_1
        34: iload         4
        36: invokevirtual #201                // Method com/fasterxml/jackson/core/Base64Variant.decodeBase64Char:(C)I
        39: istore        5
        41: iload         5
        43: ifge          67
        46: iload         5
        48: bipush        -2
        50: if_icmpne     58
        53: iload_3
        54: iconst_2
        55: if_icmpge     67
        58: aload_0
        59: aload_1
        60: iload         4
        62: iload_3
        63: invokevirtual #197                // Method reportInvalidBase64Char:(Lcom/fasterxml/jackson/core/Base64Variant;II)Ljava/lang/IllegalArgumentException;
        66: athrow
        67: iload         5
        69: ireturn
      LineNumberTable:
        line 1188: 0
        line 1189: 6
        line 1191: 14
        line 1193: 20
        line 1194: 27
        line 1195: 31
        line 1199: 33
        line 1200: 41
        line 1202: 46
        line 1203: 58
        line 1206: 67
      LocalVariableTable:
        Start  Length  Slot  Name   Signature
            0      70     0  this   Lcom/fasterxml/jackson/core/base/ParserBase;
            0      70     1 b64variant   Lcom/fasterxml/jackson/core/Base64Variant;
            0      70     2    ch   C
            0      70     3 index   I
           20      50     4 unescaped   C
           41      29     5  bits   I
      StackMapTable: number_of_entries = 4
        frame_type = 14 /* same */
        frame_type = 252 /* append */
          offset_delta = 18
          locals = [ int ]
        frame_type = 252 /* append */
          offset_delta = 24
          locals = [ int ]
        frame_type = 8 /* same */
    Exceptions:
      throws java.io.IOException

  protected java.lang.IllegalArgumentException reportInvalidBase64Char(com.fasterxml.jackson.core.Base64Variant, int, int) throws java.lang.IllegalArgumentException;
    descriptor: (Lcom/fasterxml/jackson/core/Base64Variant;II)Ljava/lang/IllegalArgumentException;
    flags: (0x0004) ACC_PROTECTED
    Code:
      stack=5, locals=4, args_size=4
         0: aload_0
         1: aload_1
         2: iload_2
         3: iload_3
         4: aconst_null
         5: invokevirtual #202                // Method reportInvalidBase64Char:(Lcom/fasterxml/jackson/core/Base64Variant;IILjava/lang/String;)Ljava/lang/IllegalArgumentException;
         8: areturn
      LineNumberTable:
        line 1210: 0
      LocalVariableTable:
        Start  Length  Slot  Name   Signature
            0       9     0  this   Lcom/fasterxml/jackson/core/base/ParserBase;
            0       9     1 b64variant   Lcom/fasterxml/jackson/core/Base64Variant;
            0       9     2    ch   I
            0       9     3 bindex   I
    Exceptions:
      throws java.lang.IllegalArgumentException

  protected java.lang.IllegalArgumentException reportInvalidBase64Char(com.fasterxml.jackson.core.Base64Variant, int, int, java.lang.String) throws java.lang.IllegalArgumentException;
    descriptor: (Lcom/fasterxml/jackson/core/Base64Variant;IILjava/lang/String;)Ljava/lang/IllegalArgumentException;
    flags: (0x0004) ACC_PROTECTED
    Code:
      stack=6, locals=6, args_size=5
         0: iload_2
         1: bipush        32
         3: if_icmpgt     36
         6: ldc           #203                // String Illegal white space character (code 0x%s) as character #%d of 4-char base64 unit: can only used between units
         8: iconst_2
         9: anewarray     #73                 // class java/lang/Object
        12: dup
        13: iconst_0
        14: iload_2
        15: invokestatic  #204                // Method java/lang/Integer.toHexString:(I)Ljava/lang/String;
        18: aastore
        19: dup
        20: iconst_1
        21: iload_3
        22: iconst_1
        23: iadd
        24: invokestatic  #96                 // Method java/lang/Integer.valueOf:(I)Ljava/lang/Integer;
        27: aastore
        28: invokestatic  #75                 // Method java/lang/String.format:(Ljava/lang/String;[Ljava/lang/Object;)Ljava/lang/String;
        31: astore        5
        33: goto          172
        36: aload_1
        37: iload_2
        38: invokevirtual #205                // Method com/fasterxml/jackson/core/Base64Variant.usesPaddingChar:(I)Z
        41: ifeq          87
        44: new           #51                 // class java/lang/StringBuilder
        47: dup
        48: invokespecial #52                 // Method java/lang/StringBuilder."<init>":()V
        51: ldc           #206                // String Unexpected padding character (\'
        53: invokevirtual #54                 // Method java/lang/StringBuilder.append:(Ljava/lang/String;)Ljava/lang/StringBuilder;
        56: aload_1
        57: invokevirtual #207                // Method com/fasterxml/jackson/core/Base64Variant.getPaddingChar:()C
        60: invokevirtual #208                // Method java/lang/StringBuilder.append:(C)Ljava/lang/StringBuilder;
        63: ldc           #209                // String \') as character #
        65: invokevirtual #54                 // Method java/lang/StringBuilder.append:(Ljava/lang/String;)Ljava/lang/StringBuilder;
        68: iload_3
        69: iconst_1
        70: iadd
        71: invokevirtual #210                // Method java/lang/StringBuilder.append:(I)Ljava/lang/StringBuilder;
        74: ldc           #211                // String  of 4-char base64 unit: padding only legal as 3rd or 4th character
        76: invokevirtual #54                 // Method java/lang/StringBuilder.append:(Ljava/lang/String;)Ljava/lang/StringBuilder;
        79: invokevirtual #57                 // Method java/lang/StringBuilder.toString:()Ljava/lang/String;
        82: astore        5
        84: goto          172
        87: iload_2
        88: invokestatic  #212                // Method java/lang/Character.isDefined:(I)Z
        91: ifeq          101
        94: iload_2
        95: invokestatic  #213                // Method java/lang/Character.isISOControl:(I)Z
        98: ifeq          133
       101: new           #51                 // class java/lang/StringBuilder
       104: dup
       105: invokespecial #52                 // Method java/lang/StringBuilder."<init>":()V
       108: ldc           #214                // String Illegal character (code 0x
       110: invokevirtual #54                 // Method java/lang/StringBuilder.append:(Ljava/lang/String;)Ljava/lang/StringBuilder;
       113: iload_2
       114: invokestatic  #204                // Method java/lang/Integer.toHexString:(I)Ljava/lang/String;
       117: invokevirtual #54                 // Method java/lang/StringBuilder.append:(Ljava/lang/String;)Ljava/lang/StringBuilder;
       120: ldc           #215                // String ) in base64 content
       122: invokevirtual #54                 // Method java/lang/StringBuilder.append:(Ljava/lang/String;)Ljava/lang/StringBuilder;
       125: invokevirtual #57                 // Method java/lang/StringBuilder.toString:()Ljava/lang/String;
       128: astore        5
       130: goto          172
       133: new           #51                 // class java/lang/StringBuilder
       136: dup
       137: invokespecial #52                 // Method java/lang/StringBuilder."<init>":()V
       140: ldc           #216                // String Illegal character \'
       142: invokevirtual #54                 // Method java/lang/StringBuilder.append:(Ljava/lang/String;)Ljava/lang/StringBuilder;
       145: iload_2
       146: i2c
       147: invokevirtual #208                // Method java/lang/StringBuilder.append:(C)Ljava/lang/StringBuilder;
       150: ldc           #217                // String \' (code 0x
       152: invokevirtual #54                 // Method java/lang/StringBuilder.append:(Ljava/lang/String;)Ljava/lang/StringBuilder;
       155: iload_2
       156: invokestatic  #204                // Method java/lang/Integer.toHexString:(I)Ljava/lang/String;
       159: invokevirtual #54                 // Method java/lang/StringBuilder.append:(Ljava/lang/String;)Ljava/lang/StringBuilder;
       162: ldc           #215                // String ) in base64 content
       164: invokevirtual #54                 // Method java/lang/StringBuilder.append:(Ljava/lang/String;)Ljava/lang/StringBuilder;
       167: invokevirtual #57                 // Method java/lang/StringBuilder.toString:()Ljava/lang/String;
       170: astore        5
       172: aload         4
       174: ifnull        204
       177: new           #51                 // class java/lang/StringBuilder
       180: dup
       181: invokespecial #52                 // Method java/lang/StringBuilder."<init>":()V
       184: aload         5
       186: invokevirtual #54                 // Method java/lang/StringBuilder.append:(Ljava/lang/String;)Ljava/lang/StringBuilder;
       189: ldc           #218                // String :
       191: invokevirtual #54                 // Method java/lang/StringBuilder.append:(Ljava/lang/String;)Ljava/lang/StringBuilder;
       194: aload         4
       196: invokevirtual #54                 // Method java/lang/StringBuilder.append:(Ljava/lang/String;)Ljava/lang/StringBuilder;
       199: invokevirtual #57                 // Method java/lang/StringBuilder.toString:()Ljava/lang/String;
       202: astore        5
       204: new           #219                // class java/lang/IllegalArgumentException
       207: dup
       208: aload         5
       210: invokespecial #220                // Method java/lang/IllegalArgumentException."<init>":(Ljava/lang/String;)V
       213: areturn
      LineNumberTable:
        line 1219: 0
        line 1220: 6
        line 1221: 15
        line 1220: 28
        line 1222: 36
        line 1223: 44
        line 1224: 87
        line 1226: 101
        line 1228: 133
        line 1230: 172
        line 1231: 177
        line 1233: 204
      LocalVariableTable:
        Start  Length  Slot  Name   Signature
           33       3     5  base   Ljava/lang/String;
           84       3     5  base   Ljava/lang/String;
          130       3     5  base   Ljava/lang/String;
            0     214     0  this   Lcom/fasterxml/jackson/core/base/ParserBase;
            0     214     1 b64variant   Lcom/fasterxml/jackson/core/Base64Variant;
            0     214     2    ch   I
            0     214     3 bindex   I
            0     214     4   msg   Ljava/lang/String;
          172      42     5  base   Ljava/lang/String;
      StackMapTable: number_of_entries = 6
        frame_type = 36 /* same */
        frame_type = 50 /* same */
        frame_type = 13 /* same */
        frame_type = 31 /* same */
        frame_type = 252 /* append */
          offset_delta = 38
          locals = [ class java/lang/String ]
        frame_type = 31 /* same */
    Exceptions:
      throws java.lang.IllegalArgumentException

  protected void _handleBase64MissingPadding(com.fasterxml.jackson.core.Base64Variant) throws java.io.IOException;
    descriptor: (Lcom/fasterxml/jackson/core/Base64Variant;)V
    flags: (0x0004) ACC_PROTECTED
    Code:
      stack=2, locals=2, args_size=2
         0: aload_0
         1: aload_1
         2: invokevirtual #221                // Method com/fasterxml/jackson/core/Base64Variant.missingPaddingMessage:()Ljava/lang/String;
         5: invokevirtual #58                 // Method _reportError:(Ljava/lang/String;)V
         8: return
      LineNumberTable:
        line 1239: 0
        line 1240: 8
      LocalVariableTable:
        Start  Length  Slot  Name   Signature
            0       9     0  this   Lcom/fasterxml/jackson/core/base/ParserBase;
            0       9     1 b64variant   Lcom/fasterxml/jackson/core/Base64Variant;
    Exceptions:
      throws java.io.IOException

  protected java.lang.Object _getSourceReference();
    descriptor: ()Ljava/lang/Object;
    flags: (0x0004) ACC_PROTECTED
    Code:
      stack=2, locals=1, args_size=1
         0: getstatic     #222                // Field com/fasterxml/jackson/core/JsonParser$Feature.INCLUDE_SOURCE_IN_LOCATION:Lcom/fasterxml/jackson/core/JsonParser$Feature;
         3: aload_0
         4: getfield      #17                 // Field _features:I
         7: invokevirtual #10                 // Method com/fasterxml/jackson/core/JsonParser$Feature.enabledIn:(I)Z
        10: ifeq          24
        13: aload_0
        14: getfield      #6                  // Field _ioContext:Lcom/fasterxml/jackson/core/io/IOContext;
        17: invokevirtual #223                // Method com/fasterxml/jackson/core/io/IOContext.contentReference:()Lcom/fasterxml/jackson/core/io/ContentReference;
        20: invokevirtual #224                // Method com/fasterxml/jackson/core/io/ContentReference.getRawContent:()Ljava/lang/Object;
        23: areturn
        24: aconst_null
        25: areturn
      LineNumberTable:
        line 1255: 0
        line 1256: 13
        line 1258: 24
      LocalVariableTable:
        Start  Length  Slot  Name   Signature
            0      26     0  this   Lcom/fasterxml/jackson/core/base/ParserBase;
      StackMapTable: number_of_entries = 1
        frame_type = 24 /* same */
    Deprecated: true
    RuntimeVisibleAnnotations:
      0: #313()
        java.lang.Deprecated

  protected com.fasterxml.jackson.core.io.ContentReference _contentReference();
    descriptor: ()Lcom/fasterxml/jackson/core/io/ContentReference;
    flags: (0x0004) ACC_PROTECTED
    Code:
      stack=2, locals=1, args_size=1
         0: getstatic     #222                // Field com/fasterxml/jackson/core/JsonParser$Feature.INCLUDE_SOURCE_IN_LOCATION:Lcom/fasterxml/jackson/core/JsonParser$Feature;
         3: aload_0
         4: getfield      #17                 // Field _features:I
         7: invokevirtual #10                 // Method com/fasterxml/jackson/core/JsonParser$Feature.enabledIn:(I)Z
        10: ifeq          21
        13: aload_0
        14: getfield      #6                  // Field _ioContext:Lcom/fasterxml/jackson/core/io/IOContext;
        17: invokevirtual #223                // Method com/fasterxml/jackson/core/io/IOContext.contentReference:()Lcom/fasterxml/jackson/core/io/ContentReference;
        20: areturn
        21: invokestatic  #225                // Method com/fasterxml/jackson/core/io/ContentReference.unknown:()Lcom/fasterxml/jackson/core/io/ContentReference;
        24: areturn
      LineNumberTable:
        line 1270: 0
        line 1271: 13
        line 1273: 21
      LocalVariableTable:
        Start  Length  Slot  Name   Signature
            0      25     0  this   Lcom/fasterxml/jackson/core/base/ParserBase;
      StackMapTable: number_of_entries = 1
        frame_type = 21 /* same */

  protected static int[] growArrayBy(int[], int);
    descriptor: ([II)[I
    flags: (0x000c) ACC_PROTECTED, ACC_STATIC
    Code:
      stack=3, locals=2, args_size=2
         0: aload_0
         1: ifnonnull     8
         4: iload_1
         5: newarray       int
         7: areturn
         8: aload_0
         9: aload_0
        10: arraylength
        11: iload_1
        12: iadd
        13: invokestatic  #226                // Method java/util/Arrays.copyOf:([II)[I
        16: areturn
      LineNumberTable:
        line 1278: 0
        line 1279: 4
        line 1281: 8
      LocalVariableTable:
        Start  Length  Slot  Name   Signature
            0      17     0   arr   [I
            0      17     1  more   I
      StackMapTable: number_of_entries = 1
        frame_type = 8 /* same */

  protected void loadMoreGuaranteed() throws java.io.IOException;
    descriptor: ()V
    flags: (0x0004) ACC_PROTECTED
    Code:
      stack=1, locals=1, args_size=1
         0: aload_0
         1: invokevirtual #227                // Method loadMore:()Z
         4: ifne          11
         7: aload_0
         8: invokevirtual #228                // Method _reportInvalidEOF:()V
        11: return
      LineNumberTable:
        line 1293: 0
        line 1294: 11
      LocalVariableTable:
        Start  Length  Slot  Name   Signature
            0      12     0  this   Lcom/fasterxml/jackson/core/base/ParserBase;
      StackMapTable: number_of_entries = 1
        frame_type = 11 /* same */
    Exceptions:
      throws java.io.IOException
    Deprecated: true
    RuntimeVisibleAnnotations:
      0: #313()
        java.lang.Deprecated

  protected boolean loadMore() throws java.io.IOException;
    descriptor: ()Z
    flags: (0x0004) ACC_PROTECTED
    Code:
      stack=1, locals=1, args_size=1
         0: iconst_0
         1: ireturn
      LineNumberTable:
        line 1297: 0
      LocalVariableTable:
        Start  Length  Slot  Name   Signature
            0       2     0  this   Lcom/fasterxml/jackson/core/base/ParserBase;
    Exceptions:
      throws java.io.IOException
    Deprecated: true
    RuntimeVisibleAnnotations:
      0: #313()
        java.lang.Deprecated

  protected void _finishString() throws java.io.IOException;
    descriptor: ()V
    flags: (0x0004) ACC_PROTECTED
    Code:
      stack=0, locals=1, args_size=1
         0: return
      LineNumberTable:
        line 1300: 0
      LocalVariableTable:
        Start  Length  Slot  Name   Signature
            0       1     0  this   Lcom/fasterxml/jackson/core/base/ParserBase;
    Exceptions:
      throws java.io.IOException

  public com.fasterxml.jackson.core.JsonStreamContext getParsingContext();
    descriptor: ()Lcom/fasterxml/jackson/core/JsonStreamContext;
    flags: (0x1041) ACC_PUBLIC, ACC_BRIDGE, ACC_SYNTHETIC
    Code:
      stack=1, locals=1, args_size=1
         0: aload_0
         1: invokevirtual #179                // Method getParsingContext:()Lcom/fasterxml/jackson/core/json/JsonReadContext;
         4: areturn
      LineNumberTable:
        line 24: 0
      LocalVariableTable:
        Start  Length  Slot  Name   Signature
            0       5     0  this   Lcom/fasterxml/jackson/core/base/ParserBase;

  static {};
    descriptor: ()V
    flags: (0x0008) ACC_STATIC
    Code:
      stack=1, locals=0, args_size=0
         0: getstatic     #229                // Field DEFAULT_READ_CAPABILITIES:Lcom/fasterxml/jackson/core/util/JacksonFeatureSet;
         3: putstatic     #230                // Field JSON_READ_CAPABILITIES:Lcom/fasterxml/jackson/core/util/JacksonFeatureSet;
         6: return
      LineNumberTable:
        line 28: 0
}
SourceFile: "ParserBase.java"
InnerClasses:
  public static final #301= #300 of #699; // Feature=class com/fasterxml/jackson/core/JsonParser$Feature of class com/fasterxml/jackson/core/JsonParser
  public static final #390= #389 of #699; // NumberType=class com/fasterxml/jackson/core/JsonParser$NumberType of class com/fasterxml/jackson/core/JsonParser
