Classfile /Users/mw/Projects/slang-braindump/.jar/jar11/assemble/slang-braindump/assemble/content/org/scalatest/exceptions/TableDrivenPropertyCheckFailedException.class
  Last modified May 29, 2022; size 8801 bytes
  SHA-256 checksum d8726c3c635388b08cccf2246cc6f8dfa3617a79caa3e6e95c6da1724246b0f6
  Compiled from "TableDrivenPropertyCheckFailedException.scala"
public class org.scalatest.exceptions.TableDrivenPropertyCheckFailedException extends org.scalatest.exceptions.PropertyCheckFailedException
  minor version: 0
  major version: 52
  flags: (0x0021) ACC_PUBLIC, ACC_SUPER
  this_class: #2                          // org/scalatest/exceptions/TableDrivenPropertyCheckFailedException
  super_class: #4                         // org/scalatest/exceptions/PropertyCheckFailedException
  interfaces: 0, fields: 4, methods: 13, attributes: 6
Constant pool:
    #1 = Utf8               org/scalatest/exceptions/TableDrivenPropertyCheckFailedException
    #2 = Class              #1            // org/scalatest/exceptions/TableDrivenPropertyCheckFailedException
    #3 = Utf8               org/scalatest/exceptions/PropertyCheckFailedException
    #4 = Class              #3            // org/scalatest/exceptions/PropertyCheckFailedException
    #5 = Utf8               TableDrivenPropertyCheckFailedException.scala
    #6 = Utf8               Lscala/reflect/ScalaSignature;
    #7 = Utf8               bytes
    #8 = Utf8               \u0006\u0005\u0005ea\u0001B\b\u0011\u0001]A\u0001\u0002\b\u0001\u0003\u0002\u0003\u0006I!\b\u0005\nc\u0001\u0011\t\u0011)A\u0005eyB\u0001b\u0010\u0001\u0003\u0002\u0003\u0006I\u0001\u0011\u0005\n\u001f\u0002\u0011\t\u0011)A\u0005!RC\u0011b\u0016\u0001\u0003\u0002\u0003\u0006IA\n-\t\u0013e\u0003!\u0011!Q\u0001\nik\u0006\u0002\u00030\u0001\u0005\u0003\u0005\u000b\u0011B0\t\u0011\u0001\u0004!Q1A\u0005\u0002\u0005D\u0001B\u0019\u0001\u0003\u0002\u0003\u0006I\u0001\u0014\u0005\u0006G\u0002!\t\u0001\u001a\u0005\u0006G\u0002!\tA\u001c\u0005\u0006G\u0002!\t\u0001\u001f\u0005\b\u0003\u000b\u0001A\u0011IA\u0004\u0011\u001d\t\t\u0002\u0001C!\u0003\'\u0011q\u0005V1cY\u0016$%/\u001b<f]B\u0013x\u000e]3sif\u001c\u0005.Z2l\r\u0006LG.\u001a3Fq\u000e,\u0007\u000f^5p]*\u0011\u0011CE\u0001\u000bKb\u001cW\r\u001d;j_:\u001c(BA\n\u0015\u0003%\u00198-\u00197bi\u0016\u001cHOC\u0001\u0016\u0003\ry\'oZ\u0002\u0001\'\t\u0001\u0001\u0004\u0005\u0002\u001a55\t\u0001#\u0003\u0002\u001c!\ta\u0002K]8qKJ$\u0018p\u00115fG.4\u0015-\u001b7fI\u0016C8-\u001a9uS>t\u0017AC7fgN\fw-\u001a$v]B!a$I\u0012\'\u001b\u0005y\"\"\u0001\u0011\u0002\u000bM\u001c\u0017\r\\1\n\u0005\tz\"!\u0003$v]\u000e$\u0018n\u001c82!\tIB%\u0003\u0002&!\t\u00192\u000b^1dW\u0012+\u0007\u000f\u001e5Fq\u000e,\u0007\u000f^5p]B\u0011qE\f\b\u0003Q1\u0002\"!K\u0010\u000e\u0003)R!a\u000b\f\u0002\rq\u0012xn\u001c;?\u0013\tis$\u0001\u0004Qe\u0016$WMZ\u0005\u0003_A\u0012aa\u0015;sS:<\'BA\u0017 \u0003\u0015\u0019\u0017-^:f!\rq2\'N\u0005\u0003i}\u0011aa\u00149uS>t\u0007C\u0001\u001c<\u001d\t9\u0014H\u0004\u0002*q%\t\u0001%\u0003\u0002;?\u00059\u0001/Y2lC\u001e,\u0017B\u0001\u001f>\u0005%!\u0006N]8xC\ndWM\u0003\u0002;?%\u0011\u0011\u0007J\u0001\u0013a>\u001cxJ]*uC\u000e\\G)\u001a9uQ\u001a+h\u000e\u0005\u00037\u0003\u000e[\u0015B\u0001\">\u0005\u0019)\u0015\u000e\u001e5feB\u0011A)S\u0007\u0002\u000b*\u0011aiR\u0001\u0007g>,(oY3\u000b\u0005!#\u0012!C:dC2\f7\r^5d\u0013\tQUI\u0001\u0005Q_NLG/[8o!\u0011q\u0012e\t\'\u0011\u0005yi\u0015B\u0001( \u0005\rIe\u000e^\u0001\ba\u0006LHn\\1e!\rq2\'\u0015\t\u0003=IK!aU\u0010\u0003\u0007\u0005s\u00170\u0003\u0002P+&\u0011a\u000b\u0005\u0002\u0014)\u0016\u001cHOR1jY\u0016$W\t_2faRLwN\\\u0001\u0013k:$WmY8sCR,G-T3tg\u0006<W-\u0003\u0002X5\u0005!\u0011M]4t!\r14,U\u0005\u00039v\u0012A\u0001T5ti&\u0011\u0011LG\u0001\f]\u0006lWm](g\u0003J<7\u000fE\u000277\u001a\n1A]8x+\u0005a\u0015\u0001\u0002:po\u0002\na\u0001P5oSRtD#C3gO\"L\'n\u001b7n!\tI\u0002\u0001C\u0003\u001d\u0015\u0001\u0007Q\u0004C\u00032\u0015\u0001\u0007!\u0007C\u0003@\u0015\u0001\u0007\u0001\tC\u0003P\u0015\u0001\u0007\u0001\u000bC\u0003X\u0015\u0001\u0007a\u0005C\u0003Z\u0015\u0001\u0007!\fC\u0003_\u0015\u0001\u0007q\fC\u0003a\u0015\u0001\u0007A\nF\u0005f_B\f8\u000f^;wo\")Ad\u0003a\u0001;!)\u0011g\u0003a\u0001e!)!o\u0003a\u0001\u0007\u0006\u0019\u0001o\\:\t\u000b=[\u0001\u0019\u0001)\t\u000b][\u0001\u0019\u0001\u0014\t\u000be[\u0001\u0019\u0001.\t\u000by[\u0001\u0019A0\t\u000b\u0001\\\u0001\u0019\u0001\'\u0015\u0017\u0015L(p_?\u007f\u007f\u0006\u0005\u00111\u0001\u0005\u000691\u0001\r!\b\u0005\u0006c1\u0001\rA\r\u0005\u0006y2\u0001\raS\u0001\u0018M\u0006LG.\u001a3D_\u0012,7\u000b^1dW\u0012+\u0007\u000f\u001e5Gk:DQa\u0014\u0007A\u0002ACQa\u0016\u0007A\u0002\u0019BQ!\u0017\u0007A\u0002iCQA\u0018\u0007A\u0002}CQ\u0001\u0019\u0007A\u00021\u000bQ\"\\8eS\u001aLX*Z:tC\u001e,GcA3\u0002\n!9\u00111B\u0007A\u0002\u00055\u0011a\u00014v]B1a$IA\b\u0003\u001f\u00012AH\u001a\'\u00035iw\u000eZ5gsB\u000b\u0017\u0010\\8bIR\u0019Q-!\u0006\t\u000f\u0005-a\u00021\u0001\u0002\u0018A!a$\t)Q\u0001
    #9 = Utf8               java/lang/invoke/MethodHandles$Lookup
   #10 = Class              #9            // java/lang/invoke/MethodHandles$Lookup
   #11 = Utf8               java/lang/invoke/MethodHandles
   #12 = Class              #11           // java/lang/invoke/MethodHandles
   #13 = Utf8               Lookup
   #14 = Utf8               messageFun
   #15 = Utf8               Lscala/Function1;
   #16 = Utf8               Lscala/Function1<Lorg/scalatest/exceptions/StackDepthException;Ljava/lang/String;>;
   #17 = Utf8               posOrStackDepthFun
   #18 = Utf8               Lscala/util/Either;
   #19 = Utf8               Lscala/util/Either<Lorg/scalactic/source/Position;Lscala/Function1<Lorg/scalatest/exceptions/StackDepthException;Ljava/lang/Object;>;>;
   #20 = Utf8               namesOfArgs
   #21 = Utf8               Lscala/collection/immutable/List;
   #22 = Utf8               Lscala/collection/immutable/List<Ljava/lang/String;>;
   #23 = Utf8               row
   #24 = Utf8               I
   #25 = Utf8               ()I
   #26 = NameAndType        #23:#24       // row:I
   #27 = Fieldref           #2.#26        // org/scalatest/exceptions/TableDrivenPropertyCheckFailedException.row:I
   #28 = Utf8               this
   #29 = Utf8               Lorg/scalatest/exceptions/TableDrivenPropertyCheckFailedException;
   #30 = Utf8               modifyMessage
   #31 = Utf8               (Lscala/Function1;)Lorg/scalatest/exceptions/TableDrivenPropertyCheckFailedException;
   #32 = Utf8               (Lscala/Function1<Lscala/Option<Ljava/lang/String;>;Lscala/Option<Ljava/lang/String;>;>;)Lorg/scalatest/exceptions/TableDrivenPropertyCheckFailedException;
   #33 = Utf8               fun
   #34 = Utf8               (Ljava/lang/Object;)Ljava/lang/Object;
   #35 = MethodType         #34           //  (Ljava/lang/Object;)Ljava/lang/Object;
   #36 = Utf8               $anonfun$modifyMessage$1
   #37 = Utf8               (Lorg/scalatest/exceptions/TableDrivenPropertyCheckFailedException;Lscala/Function1;Lorg/scalatest/exceptions/StackDepthException;)Ljava/lang/String;
   #38 = NameAndType        #36:#37       // $anonfun$modifyMessage$1:(Lorg/scalatest/exceptions/TableDrivenPropertyCheckFailedException;Lscala/Function1;Lorg/scalatest/exceptions/StackDepthException;)Ljava/lang/String;
   #39 = Methodref          #2.#38        // org/scalatest/exceptions/TableDrivenPropertyCheckFailedException.$anonfun$modifyMessage$1:(Lorg/scalatest/exceptions/TableDrivenPropertyCheckFailedException;Lscala/Function1;Lorg/scalatest/exceptions/StackDepthException;)Ljava/lang/String;
   #40 = MethodHandle       6:#39         // REF_invokeStatic org/scalatest/exceptions/TableDrivenPropertyCheckFailedException.$anonfun$modifyMessage$1:(Lorg/scalatest/exceptions/TableDrivenPropertyCheckFailedException;Lscala/Function1;Lorg/scalatest/exceptions/StackDepthException;)Ljava/lang/String;
   #41 = Utf8               (Lorg/scalatest/exceptions/StackDepthException;)Ljava/lang/String;
   #42 = MethodType         #41           //  (Lorg/scalatest/exceptions/StackDepthException;)Ljava/lang/String;
   #43 = Integer            5
   #44 = Integer            1
   #45 = Utf8               java/lang/invoke/LambdaMetafactory
   #46 = Class              #45           // java/lang/invoke/LambdaMetafactory
   #47 = Utf8               altMetafactory
   #48 = Utf8               (Ljava/lang/invoke/MethodHandles$Lookup;Ljava/lang/String;Ljava/lang/invoke/MethodType;[Ljava/lang/Object;)Ljava/lang/invoke/CallSite;
   #49 = NameAndType        #47:#48       // altMetafactory:(Ljava/lang/invoke/MethodHandles$Lookup;Ljava/lang/String;Ljava/lang/invoke/MethodType;[Ljava/lang/Object;)Ljava/lang/invoke/CallSite;
   #50 = Methodref          #46.#49       // java/lang/invoke/LambdaMetafactory.altMetafactory:(Ljava/lang/invoke/MethodHandles$Lookup;Ljava/lang/String;Ljava/lang/invoke/MethodType;[Ljava/lang/Object;)Ljava/lang/invoke/CallSite;
   #51 = MethodHandle       6:#50         // REF_invokeStatic java/lang/invoke/LambdaMetafactory.altMetafactory:(Ljava/lang/invoke/MethodHandles$Lookup;Ljava/lang/String;Ljava/lang/invoke/MethodType;[Ljava/lang/Object;)Ljava/lang/invoke/CallSite;
   #52 = Utf8               apply
   #53 = Utf8               (Lorg/scalatest/exceptions/TableDrivenPropertyCheckFailedException;Lscala/Function1;)Lscala/Function1;
   #54 = NameAndType        #52:#53       // apply:(Lorg/scalatest/exceptions/TableDrivenPropertyCheckFailedException;Lscala/Function1;)Lscala/Function1;
   #55 = InvokeDynamic      #0:#54        // #0:apply:(Lorg/scalatest/exceptions/TableDrivenPropertyCheckFailedException;Lscala/Function1;)Lscala/Function1;
   #56 = Utf8               org/scalatest/exceptions/StackDepthException
   #57 = Class              #56           // org/scalatest/exceptions/StackDepthException
   #58 = Utf8               cause
   #59 = Utf8               ()Lscala/Option;
   #60 = NameAndType        #58:#59       // cause:()Lscala/Option;
   #61 = Methodref          #57.#60       // org/scalatest/exceptions/StackDepthException.cause:()Lscala/Option;
   #62 = NameAndType        #17:#18       // posOrStackDepthFun:Lscala/util/Either;
   #63 = Fieldref           #2.#62        // org/scalatest/exceptions/TableDrivenPropertyCheckFailedException.posOrStackDepthFun:Lscala/util/Either;
   #64 = Utf8               org/scalatest/exceptions/TestFailedException
   #65 = Class              #64           // org/scalatest/exceptions/TestFailedException
   #66 = Utf8               payload
   #67 = NameAndType        #66:#59       // payload:()Lscala/Option;
   #68 = Methodref          #65.#67       // org/scalatest/exceptions/TestFailedException.payload:()Lscala/Option;
   #69 = Utf8               undecoratedMessage
   #70 = Utf8               ()Ljava/lang/String;
   #71 = NameAndType        #69:#70       // undecoratedMessage:()Ljava/lang/String;
   #72 = Methodref          #4.#71        // org/scalatest/exceptions/PropertyCheckFailedException.undecoratedMessage:()Ljava/lang/String;
   #73 = Utf8               args
   #74 = Utf8               ()Lscala/collection/immutable/List;
   #75 = NameAndType        #73:#74       // args:()Lscala/collection/immutable/List;
   #76 = Methodref          #4.#75        // org/scalatest/exceptions/PropertyCheckFailedException.args:()Lscala/collection/immutable/List;
   #77 = NameAndType        #20:#21       // namesOfArgs:Lscala/collection/immutable/List;
   #78 = Fieldref           #2.#77        // org/scalatest/exceptions/TableDrivenPropertyCheckFailedException.namesOfArgs:Lscala/collection/immutable/List;
   #79 = NameAndType        #23:#25       // row:()I
   #80 = Methodref          #2.#79        // org/scalatest/exceptions/TableDrivenPropertyCheckFailedException.row:()I
   #81 = Utf8               <init>
   #82 = Utf8               (Lscala/Function1;Lscala/Option;Lscala/util/Either;Lscala/Option;Ljava/lang/String;Lscala/collection/immutable/List;Lscala/collection/immutable/List;I)V
   #83 = NameAndType        #81:#82       // "<init>":(Lscala/Function1;Lscala/Option;Lscala/util/Either;Lscala/Option;Ljava/lang/String;Lscala/collection/immutable/List;Lscala/collection/immutable/List;I)V
   #84 = Methodref          #2.#83        // org/scalatest/exceptions/TableDrivenPropertyCheckFailedException."<init>":(Lscala/Function1;Lscala/Option;Lscala/util/Either;Lscala/Option;Ljava/lang/String;Lscala/collection/immutable/List;Lscala/collection/immutable/List;I)V
   #85 = Utf8               getStackTrace
   #86 = Utf8               ()[Ljava/lang/StackTraceElement;
   #87 = NameAndType        #85:#86       // getStackTrace:()[Ljava/lang/StackTraceElement;
   #88 = Methodref          #2.#87        // org/scalatest/exceptions/TableDrivenPropertyCheckFailedException.getStackTrace:()[Ljava/lang/StackTraceElement;
   #89 = Utf8               setStackTrace
   #90 = Utf8               ([Ljava/lang/StackTraceElement;)V
   #91 = NameAndType        #89:#90       // setStackTrace:([Ljava/lang/StackTraceElement;)V
   #92 = Methodref          #2.#91        // org/scalatest/exceptions/TableDrivenPropertyCheckFailedException.setStackTrace:([Ljava/lang/StackTraceElement;)V
   #93 = Utf8               mod
   #94 = Utf8               modifyPayload
   #95 = Utf8               (Lscala/Function1<Lscala/Option<Ljava/lang/Object;>;Lscala/Option<Ljava/lang/Object;>;>;)Lorg/scalatest/exceptions/TableDrivenPropertyCheckFailedException;
   #96 = NameAndType        #14:#15       // messageFun:Lscala/Function1;
   #97 = Fieldref           #2.#96        // org/scalatest/exceptions/TableDrivenPropertyCheckFailedException.messageFun:Lscala/Function1;
   #98 = Utf8               scala/Function1
   #99 = Class              #98           // scala/Function1
  #100 = NameAndType        #52:#34       // apply:(Ljava/lang/Object;)Ljava/lang/Object;
  #101 = InterfaceMethodref #99.#100      // scala/Function1.apply:(Ljava/lang/Object;)Ljava/lang/Object;
  #102 = Utf8               scala/Option
  #103 = Class              #102          // scala/Option
  #104 = Utf8               currentPayload
  #105 = Utf8               Lscala/Option;
  #106 = Utf8               (Lscala/Function1;)Ljava/lang/Throwable;
  #107 = NameAndType        #94:#31       // modifyPayload:(Lscala/Function1;)Lorg/scalatest/exceptions/TableDrivenPropertyCheckFailedException;
  #108 = Methodref          #2.#107       // org/scalatest/exceptions/TableDrivenPropertyCheckFailedException.modifyPayload:(Lscala/Function1;)Lorg/scalatest/exceptions/TableDrivenPropertyCheckFailedException;
  #109 = Utf8               (Lscala/Function1;)Lorg/scalatest/exceptions/TestFailedException;
  #110 = NameAndType        #30:#31       // modifyMessage:(Lscala/Function1;)Lorg/scalatest/exceptions/TableDrivenPropertyCheckFailedException;
  #111 = Methodref          #2.#110       // org/scalatest/exceptions/TableDrivenPropertyCheckFailedException.modifyMessage:(Lscala/Function1;)Lorg/scalatest/exceptions/TableDrivenPropertyCheckFailedException;
  #112 = Utf8               $anonfun$modifyMessage$2
  #113 = Utf8               (Lorg/scalatest/exceptions/TableDrivenPropertyCheckFailedException;)Ljava/lang/String;
  #114 = Utf8               $this
  #115 = Utf8               java/lang/String
  #116 = Class              #115          // java/lang/String
  #117 = Utf8               fun$1
  #118 = Utf8               sde
  #119 = Utf8               message
  #120 = NameAndType        #119:#59      // message:()Lscala/Option;
  #121 = Methodref          #2.#120       // org/scalatest/exceptions/TableDrivenPropertyCheckFailedException.message:()Lscala/Option;
  #122 = Utf8               ()Ljava/lang/Object;
  #123 = MethodType         #122          //  ()Ljava/lang/Object;
  #124 = NameAndType        #112:#113     // $anonfun$modifyMessage$2:(Lorg/scalatest/exceptions/TableDrivenPropertyCheckFailedException;)Ljava/lang/String;
  #125 = Methodref          #2.#124       // org/scalatest/exceptions/TableDrivenPropertyCheckFailedException.$anonfun$modifyMessage$2:(Lorg/scalatest/exceptions/TableDrivenPropertyCheckFailedException;)Ljava/lang/String;
  #126 = MethodHandle       6:#125        // REF_invokeStatic org/scalatest/exceptions/TableDrivenPropertyCheckFailedException.$anonfun$modifyMessage$2:(Lorg/scalatest/exceptions/TableDrivenPropertyCheckFailedException;)Ljava/lang/String;
  #127 = MethodType         #70           //  ()Ljava/lang/String;
  #128 = Utf8               (Lorg/scalatest/exceptions/TableDrivenPropertyCheckFailedException;)Lscala/Function0;
  #129 = NameAndType        #52:#128      // apply:(Lorg/scalatest/exceptions/TableDrivenPropertyCheckFailedException;)Lscala/Function0;
  #130 = InvokeDynamic      #1:#129       // #1:apply:(Lorg/scalatest/exceptions/TableDrivenPropertyCheckFailedException;)Lscala/Function0;
  #131 = Utf8               getOrElse
  #132 = Utf8               (Lscala/Function0;)Ljava/lang/Object;
  #133 = NameAndType        #131:#132     // getOrElse:(Lscala/Function0;)Ljava/lang/Object;
  #134 = Methodref          #103.#133     // scala/Option.getOrElse:(Lscala/Function0;)Ljava/lang/Object;
  #135 = Utf8               Lorg/scalatest/exceptions/StackDepthException;
  #136 = Utf8               (Lscala/Function1<Lorg/scalatest/exceptions/StackDepthException;Ljava/lang/String;>;Lscala/Option<Ljava/lang/Throwable;>;Lscala/util/Either<Lorg/scalactic/source/Position;Lscala/Function1<Lorg/scalatest/exceptions/StackDepthException;Ljava/lang/Object;>;>;Lscala/Option<Ljava/lang/Object;>;Ljava/lang/String;Lscala/collection/immutable/List<Ljava/lang/Object;>;Lscala/collection/immutable/List<Ljava/lang/String;>;I)V
  #137 = Utf8               scala/Some
  #138 = Class              #137          // scala/Some
  #139 = Utf8               (Ljava/lang/Object;)V
  #140 = NameAndType        #81:#139      // "<init>":(Ljava/lang/Object;)V
  #141 = Methodref          #138.#140     // scala/Some."<init>":(Ljava/lang/Object;)V
  #142 = Utf8               (Lscala/Function1;Lscala/Option;Lscala/util/Either;Lscala/Option;Ljava/lang/String;Lscala/collection/immutable/List;Lscala/Option;)V
  #143 = NameAndType        #81:#142      // "<init>":(Lscala/Function1;Lscala/Option;Lscala/util/Either;Lscala/Option;Ljava/lang/String;Lscala/collection/immutable/List;Lscala/Option;)V
  #144 = Methodref          #4.#143       // org/scalatest/exceptions/PropertyCheckFailedException."<init>":(Lscala/Function1;Lscala/Option;Lscala/util/Either;Lscala/Option;Ljava/lang/String;Lscala/collection/immutable/List;Lscala/Option;)V
  #145 = Utf8               Ljava/lang/String;
  #146 = Utf8               (Lscala/Function1;Lscala/Option;Lorg/scalactic/source/Position;Lscala/Option;Ljava/lang/String;Lscala/collection/immutable/List;Lscala/collection/immutable/List;I)V
  #147 = Utf8               (Lscala/Function1<Lorg/scalatest/exceptions/StackDepthException;Ljava/lang/String;>;Lscala/Option<Ljava/lang/Throwable;>;Lorg/scalactic/source/Position;Lscala/Option<Ljava/lang/Object;>;Ljava/lang/String;Lscala/collection/immutable/List<Ljava/lang/Object;>;Lscala/collection/immutable/List<Ljava/lang/String;>;I)V
  #148 = Utf8               pos
  #149 = Utf8               scala/package$
  #150 = Class              #149          // scala/package$
  #151 = Utf8               MODULE$
  #152 = Utf8               Lscala/package$;
  #153 = NameAndType        #151:#152     // MODULE$:Lscala/package$;
  #154 = Fieldref           #150.#153     // scala/package$.MODULE$:Lscala/package$;
  #155 = Utf8               Left
  #156 = Utf8               ()Lscala/util/Left$;
  #157 = NameAndType        #155:#156     // Left:()Lscala/util/Left$;
  #158 = Methodref          #150.#157     // scala/package$.Left:()Lscala/util/Left$;
  #159 = Utf8               scala/util/Left$
  #160 = Class              #159          // scala/util/Left$
  #161 = Utf8               (Ljava/lang/Object;)Lscala/util/Left;
  #162 = NameAndType        #52:#161      // apply:(Ljava/lang/Object;)Lscala/util/Left;
  #163 = Methodref          #160.#162     // scala/util/Left$.apply:(Ljava/lang/Object;)Lscala/util/Left;
  #164 = Utf8               Lorg/scalactic/source/Position;
  #165 = Utf8               (Lscala/Function1;Lscala/Option;Lscala/Function1;Lscala/Option;Ljava/lang/String;Lscala/collection/immutable/List;Lscala/collection/immutable/List;I)V
  #166 = Utf8               (Lscala/Function1<Lorg/scalatest/exceptions/StackDepthException;Ljava/lang/String;>;Lscala/Option<Ljava/lang/Throwable;>;Lscala/Function1<Lorg/scalatest/exceptions/StackDepthException;Ljava/lang/Object;>;Lscala/Option<Ljava/lang/Object;>;Ljava/lang/String;Lscala/collection/immutable/List<Ljava/lang/Object;>;Lscala/collection/immutable/List<Ljava/lang/String;>;I)V
  #167 = Utf8               failedCodeStackDepthFun
  #168 = Utf8               Right
  #169 = Utf8               ()Lscala/util/Right$;
  #170 = NameAndType        #168:#169     // Right:()Lscala/util/Right$;
  #171 = Methodref          #150.#170     // scala/package$.Right:()Lscala/util/Right$;
  #172 = Utf8               scala/util/Right$
  #173 = Class              #172          // scala/util/Right$
  #174 = Utf8               (Ljava/lang/Object;)Lscala/util/Right;
  #175 = NameAndType        #52:#174      // apply:(Ljava/lang/Object;)Lscala/util/Right;
  #176 = Methodref          #173.#175     // scala/util/Right$.apply:(Ljava/lang/Object;)Lscala/util/Right;
  #177 = Utf8               $deserializeLambda$
  #178 = Utf8               (Ljava/lang/invoke/SerializedLambda;)Ljava/lang/Object;
  #179 = Utf8               scala/runtime/LambdaDeserialize
  #180 = Class              #179          // scala/runtime/LambdaDeserialize
  #181 = Utf8               bootstrap
  #182 = Utf8               (Ljava/lang/invoke/MethodHandles$Lookup;Ljava/lang/String;Ljava/lang/invoke/MethodType;[Ljava/lang/invoke/MethodHandle;)Ljava/lang/invoke/CallSite;
  #183 = NameAndType        #181:#182     // bootstrap:(Ljava/lang/invoke/MethodHandles$Lookup;Ljava/lang/String;Ljava/lang/invoke/MethodType;[Ljava/lang/invoke/MethodHandle;)Ljava/lang/invoke/CallSite;
  #184 = Methodref          #180.#183     // scala/runtime/LambdaDeserialize.bootstrap:(Ljava/lang/invoke/MethodHandles$Lookup;Ljava/lang/String;Ljava/lang/invoke/MethodType;[Ljava/lang/invoke/MethodHandle;)Ljava/lang/invoke/CallSite;
  #185 = MethodHandle       6:#184        // REF_invokeStatic scala/runtime/LambdaDeserialize.bootstrap:(Ljava/lang/invoke/MethodHandles$Lookup;Ljava/lang/String;Ljava/lang/invoke/MethodType;[Ljava/lang/invoke/MethodHandle;)Ljava/lang/invoke/CallSite;
  #186 = Utf8               lambdaDeserialize
  #187 = NameAndType        #186:#178     // lambdaDeserialize:(Ljava/lang/invoke/SerializedLambda;)Ljava/lang/Object;
  #188 = InvokeDynamic      #2:#187       // #2:lambdaDeserialize:(Ljava/lang/invoke/SerializedLambda;)Ljava/lang/Object;
  #189 = Utf8               Signature
  #190 = Utf8               Code
  #191 = Utf8               LineNumberTable
  #192 = Utf8               LocalVariableTable
  #193 = Utf8               MethodParameters
  #194 = Utf8               InnerClasses
  #195 = Utf8               SourceFile
  #196 = Utf8               RuntimeVisibleAnnotations
  #197 = Utf8               BootstrapMethods
  #198 = Utf8               ScalaInlineInfo
  #199 = Utf8               ScalaSig
{
  private final scala.Function1<org.scalatest.exceptions.StackDepthException, java.lang.String> messageFun;
    descriptor: Lscala/Function1;
    flags: (0x0012) ACC_PRIVATE, ACC_FINAL
    Signature: #16                          // Lscala/Function1<Lorg/scalatest/exceptions/StackDepthException;Ljava/lang/String;>;

  private final scala.util.Either<org.scalactic.source.Position, scala.Function1<org.scalatest.exceptions.StackDepthException, java.lang.Object>> posOrStackDepthFun;
    descriptor: Lscala/util/Either;
    flags: (0x0012) ACC_PRIVATE, ACC_FINAL
    Signature: #19                          // Lscala/util/Either<Lorg/scalactic/source/Position;Lscala/Function1<Lorg/scalatest/exceptions/StackDepthException;Ljava/lang/Object;>;>;

  private final scala.collection.immutable.List<java.lang.String> namesOfArgs;
    descriptor: Lscala/collection/immutable/List;
    flags: (0x0012) ACC_PRIVATE, ACC_FINAL
    Signature: #22                          // Lscala/collection/immutable/List<Ljava/lang/String;>;

  private final int row;
    descriptor: I
    flags: (0x0012) ACC_PRIVATE, ACC_FINAL

  public int row();
    descriptor: ()I
    flags: (0x0001) ACC_PUBLIC
    Code:
      stack=1, locals=1, args_size=1
         0: aload_0
         1: getfield      #27                 // Field row:I
         4: ireturn
      LineNumberTable:
        line 50: 0
      LocalVariableTable:
        Start  Length  Slot  Name   Signature
            0       5     0  this   Lorg/scalatest/exceptions/TableDrivenPropertyCheckFailedException;

  public org.scalatest.exceptions.TableDrivenPropertyCheckFailedException modifyMessage(scala.Function1<scala.Option<java.lang.String>, scala.Option<java.lang.String>>);
    descriptor: (Lscala/Function1;)Lorg/scalatest/exceptions/TableDrivenPropertyCheckFailedException;
    flags: (0x0001) ACC_PUBLIC
    Code:
      stack=10, locals=3, args_size=2
         0: new           #2                  // class org/scalatest/exceptions/TableDrivenPropertyCheckFailedException
         3: dup
         4: aload_0
         5: aload_1
         6: invokedynamic #55,  0             // InvokeDynamic #0:apply:(Lorg/scalatest/exceptions/TableDrivenPropertyCheckFailedException;Lscala/Function1;)Lscala/Function1;
        11: aload_0
        12: invokespecial #61                 // Method org/scalatest/exceptions/StackDepthException.cause:()Lscala/Option;
        15: aload_0
        16: getfield      #63                 // Field posOrStackDepthFun:Lscala/util/Either;
        19: aload_0
        20: invokespecial #68                 // Method org/scalatest/exceptions/TestFailedException.payload:()Lscala/Option;
        23: aload_0
        24: invokespecial #72                 // Method org/scalatest/exceptions/PropertyCheckFailedException.undecoratedMessage:()Ljava/lang/String;
        27: aload_0
        28: invokespecial #76                 // Method org/scalatest/exceptions/PropertyCheckFailedException.args:()Lscala/collection/immutable/List;
        31: aload_0
        32: getfield      #78                 // Field namesOfArgs:Lscala/collection/immutable/List;
        35: aload_0
        36: invokevirtual #80                 // Method row:()I
        39: invokespecial #84                 // Method "<init>":(Lscala/Function1;Lscala/Option;Lscala/util/Either;Lscala/Option;Ljava/lang/String;Lscala/collection/immutable/List;Lscala/collection/immutable/List;I)V
        42: astore_2
        43: aload_2
        44: aload_0
        45: invokevirtual #88                 // Method getStackTrace:()[Ljava/lang/StackTraceElement;
        48: invokevirtual #92                 // Method setStackTrace:([Ljava/lang/StackTraceElement;)V
        51: aload_2
        52: areturn
      LineNumberTable:
        line 115: 0
        line 116: 4
        line 117: 11
        line 118: 15
        line 119: 19
        line 120: 23
        line 121: 27
        line 122: 31
        line 123: 35
        line 125: 43
        line 126: 51
      LocalVariableTable:
        Start  Length  Slot  Name   Signature
           43       9     2   mod   Lorg/scalatest/exceptions/TableDrivenPropertyCheckFailedException;
            0      53     0  this   Lorg/scalatest/exceptions/TableDrivenPropertyCheckFailedException;
            0      53     1   fun   Lscala/Function1;
    Signature: #32                          // (Lscala/Function1<Lscala/Option<Ljava/lang/String;>;Lscala/Option<Ljava/lang/String;>;>;)Lorg/scalatest/exceptions/TableDrivenPropertyCheckFailedException;
    MethodParameters:
      Name                           Flags
      fun                            final

  public org.scalatest.exceptions.TableDrivenPropertyCheckFailedException modifyPayload(scala.Function1<scala.Option<java.lang.Object>, scala.Option<java.lang.Object>>);
    descriptor: (Lscala/Function1;)Lorg/scalatest/exceptions/TableDrivenPropertyCheckFailedException;
    flags: (0x0001) ACC_PUBLIC
    Code:
      stack=10, locals=4, args_size=2
         0: aload_0
         1: invokespecial #68                 // Method org/scalatest/exceptions/TestFailedException.payload:()Lscala/Option;
         4: astore_2
         5: new           #2                  // class org/scalatest/exceptions/TableDrivenPropertyCheckFailedException
         8: dup
         9: aload_0
        10: getfield      #97                 // Field messageFun:Lscala/Function1;
        13: aload_0
        14: invokespecial #61                 // Method org/scalatest/exceptions/StackDepthException.cause:()Lscala/Option;
        17: aload_0
        18: getfield      #63                 // Field posOrStackDepthFun:Lscala/util/Either;
        21: aload_1
        22: aload_2
        23: invokeinterface #101,  2          // InterfaceMethod scala/Function1.apply:(Ljava/lang/Object;)Ljava/lang/Object;
        28: checkcast     #103                // class scala/Option
        31: aload_0
        32: invokespecial #72                 // Method org/scalatest/exceptions/PropertyCheckFailedException.undecoratedMessage:()Ljava/lang/String;
        35: aload_0
        36: invokespecial #76                 // Method org/scalatest/exceptions/PropertyCheckFailedException.args:()Lscala/collection/immutable/List;
        39: aload_0
        40: getfield      #78                 // Field namesOfArgs:Lscala/collection/immutable/List;
        43: aload_0
        44: invokevirtual #80                 // Method row:()I
        47: invokespecial #84                 // Method "<init>":(Lscala/Function1;Lscala/Option;Lscala/util/Either;Lscala/Option;Ljava/lang/String;Lscala/collection/immutable/List;Lscala/collection/immutable/List;I)V
        50: astore_3
        51: aload_3
        52: aload_0
        53: invokevirtual #88                 // Method getStackTrace:()[Ljava/lang/StackTraceElement;
        56: invokevirtual #92                 // Method setStackTrace:([Ljava/lang/StackTraceElement;)V
        59: aload_3
        60: areturn
      LineNumberTable:
        line 138: 0
        line 140: 5
        line 141: 9
        line 142: 13
        line 143: 17
        line 144: 21
        line 145: 31
        line 146: 35
        line 147: 39
        line 148: 43
        line 150: 51
        line 151: 59
      LocalVariableTable:
        Start  Length  Slot  Name   Signature
            5      55     2 currentPayload   Lscala/Option;
           51       9     3   mod   Lorg/scalatest/exceptions/TableDrivenPropertyCheckFailedException;
            0      61     0  this   Lorg/scalatest/exceptions/TableDrivenPropertyCheckFailedException;
            0      61     1   fun   Lscala/Function1;
    Signature: #95                          // (Lscala/Function1<Lscala/Option<Ljava/lang/Object;>;Lscala/Option<Ljava/lang/Object;>;>;)Lorg/scalatest/exceptions/TableDrivenPropertyCheckFailedException;
    MethodParameters:
      Name                           Flags
      fun                            final

  public java.lang.Throwable modifyPayload(scala.Function1);
    descriptor: (Lscala/Function1;)Ljava/lang/Throwable;
    flags: (0x1041) ACC_PUBLIC, ACC_BRIDGE, ACC_SYNTHETIC
    Code:
      stack=2, locals=2, args_size=2
         0: aload_0
         1: aload_1
         2: invokevirtual #108                // Method modifyPayload:(Lscala/Function1;)Lorg/scalatest/exceptions/TableDrivenPropertyCheckFailedException;
         5: areturn
      LineNumberTable:
        line 42: 0
      LocalVariableTable:
        Start  Length  Slot  Name   Signature
            0       6     0  this   Lorg/scalatest/exceptions/TableDrivenPropertyCheckFailedException;
            0       6     1   fun   Lscala/Function1;
    MethodParameters:
      Name                           Flags
      fun                            final

  public org.scalatest.exceptions.TestFailedException modifyPayload(scala.Function1);
    descriptor: (Lscala/Function1;)Lorg/scalatest/exceptions/TestFailedException;
    flags: (0x1041) ACC_PUBLIC, ACC_BRIDGE, ACC_SYNTHETIC
    Code:
      stack=2, locals=2, args_size=2
         0: aload_0
         1: aload_1
         2: invokevirtual #108                // Method modifyPayload:(Lscala/Function1;)Lorg/scalatest/exceptions/TableDrivenPropertyCheckFailedException;
         5: areturn
      LineNumberTable:
        line 42: 0
      LocalVariableTable:
        Start  Length  Slot  Name   Signature
            0       6     0  this   Lorg/scalatest/exceptions/TableDrivenPropertyCheckFailedException;
            0       6     1   fun   Lscala/Function1;
    MethodParameters:
      Name                           Flags
      fun                            final

  public java.lang.Throwable modifyMessage(scala.Function1);
    descriptor: (Lscala/Function1;)Ljava/lang/Throwable;
    flags: (0x1041) ACC_PUBLIC, ACC_BRIDGE, ACC_SYNTHETIC
    Code:
      stack=2, locals=2, args_size=2
         0: aload_0
         1: aload_1
         2: invokevirtual #111                // Method modifyMessage:(Lscala/Function1;)Lorg/scalatest/exceptions/TableDrivenPropertyCheckFailedException;
         5: areturn
      LineNumberTable:
        line 42: 0
      LocalVariableTable:
        Start  Length  Slot  Name   Signature
            0       6     0  this   Lorg/scalatest/exceptions/TableDrivenPropertyCheckFailedException;
            0       6     1   fun   Lscala/Function1;
    MethodParameters:
      Name                           Flags
      fun                            final

  public org.scalatest.exceptions.TestFailedException modifyMessage(scala.Function1);
    descriptor: (Lscala/Function1;)Lorg/scalatest/exceptions/TestFailedException;
    flags: (0x1041) ACC_PUBLIC, ACC_BRIDGE, ACC_SYNTHETIC
    Code:
      stack=2, locals=2, args_size=2
         0: aload_0
         1: aload_1
         2: invokevirtual #111                // Method modifyMessage:(Lscala/Function1;)Lorg/scalatest/exceptions/TableDrivenPropertyCheckFailedException;
         5: areturn
      LineNumberTable:
        line 42: 0
      LocalVariableTable:
        Start  Length  Slot  Name   Signature
            0       6     0  this   Lorg/scalatest/exceptions/TableDrivenPropertyCheckFailedException;
            0       6     1   fun   Lscala/Function1;
    MethodParameters:
      Name                           Flags
      fun                            final

  public static final java.lang.String $anonfun$modifyMessage$2(org.scalatest.exceptions.TableDrivenPropertyCheckFailedException);
    descriptor: (Lorg/scalatest/exceptions/TableDrivenPropertyCheckFailedException;)Ljava/lang/String;
    flags: (0x1019) ACC_PUBLIC, ACC_STATIC, ACC_FINAL, ACC_SYNTHETIC
    Code:
      stack=2, locals=1, args_size=1
         0: aload_0
         1: getfield      #97                 // Field messageFun:Lscala/Function1;
         4: aload_0
         5: invokeinterface #101,  2          // InterfaceMethod scala/Function1.apply:(Ljava/lang/Object;)Ljava/lang/Object;
        10: checkcast     #116                // class java/lang/String
        13: areturn
      LineNumberTable:
        line 116: 0
      LocalVariableTable:
        Start  Length  Slot  Name   Signature
            0      14     0 $this   Lorg/scalatest/exceptions/TableDrivenPropertyCheckFailedException;
    MethodParameters:
      Name                           Flags
      $this                          final synthetic

  public static final java.lang.String $anonfun$modifyMessage$1(org.scalatest.exceptions.TableDrivenPropertyCheckFailedException, scala.Function1, org.scalatest.exceptions.StackDepthException);
    descriptor: (Lorg/scalatest/exceptions/TableDrivenPropertyCheckFailedException;Lscala/Function1;Lorg/scalatest/exceptions/StackDepthException;)Ljava/lang/String;
    flags: (0x1019) ACC_PUBLIC, ACC_STATIC, ACC_FINAL, ACC_SYNTHETIC
    Code:
      stack=2, locals=3, args_size=3
         0: aload_1
         1: aload_0
         2: invokevirtual #121                // Method message:()Lscala/Option;
         5: invokeinterface #101,  2          // InterfaceMethod scala/Function1.apply:(Ljava/lang/Object;)Ljava/lang/Object;
        10: checkcast     #103                // class scala/Option
        13: aload_0
        14: invokedynamic #130,  0            // InvokeDynamic #1:apply:(Lorg/scalatest/exceptions/TableDrivenPropertyCheckFailedException;)Lscala/Function0;
        19: invokevirtual #134                // Method scala/Option.getOrElse:(Lscala/Function0;)Ljava/lang/Object;
        22: checkcast     #116                // class java/lang/String
        25: areturn
      LineNumberTable:
        line 116: 0
      LocalVariableTable:
        Start  Length  Slot  Name   Signature
            0      26     0 $this   Lorg/scalatest/exceptions/TableDrivenPropertyCheckFailedException;
            0      26     1 fun$1   Lscala/Function1;
            0      26     2   sde   Lorg/scalatest/exceptions/StackDepthException;
    MethodParameters:
      Name                           Flags
      $this                          final synthetic
      fun$1                          final
      sde                            final

  public org.scalatest.exceptions.TableDrivenPropertyCheckFailedException(scala.Function1<org.scalatest.exceptions.StackDepthException, java.lang.String>, scala.Option<java.lang.Throwable>, scala.util.Either<org.scalactic.source.Position, scala.Function1<org.scalatest.exceptions.StackDepthException, java.lang.Object>>, scala.Option<java.lang.Object>, java.lang.String, scala.collection.immutable.List<java.lang.Object>, scala.collection.immutable.List<java.lang.String>, int);
    descriptor: (Lscala/Function1;Lscala/Option;Lscala/util/Either;Lscala/Option;Ljava/lang/String;Lscala/collection/immutable/List;Lscala/collection/immutable/List;I)V
    flags: (0x0001) ACC_PUBLIC
    Code:
      stack=10, locals=9, args_size=9
         0: aload_0
         1: aload_1
         2: putfield      #97                 // Field messageFun:Lscala/Function1;
         5: aload_0
         6: aload_3
         7: putfield      #63                 // Field posOrStackDepthFun:Lscala/util/Either;
        10: aload_0
        11: aload         7
        13: putfield      #78                 // Field namesOfArgs:Lscala/collection/immutable/List;
        16: aload_0
        17: iload         8
        19: putfield      #27                 // Field row:I
        22: aload_0
        23: aload_1
        24: aload_2
        25: aload_3
        26: aload         4
        28: aload         5
        30: aload         6
        32: new           #138                // class scala/Some
        35: dup
        36: aload         7
        38: invokespecial #141                // Method scala/Some."<init>":(Ljava/lang/Object;)V
        41: invokespecial #144                // Method org/scalatest/exceptions/PropertyCheckFailedException."<init>":(Lscala/Function1;Lscala/Option;Lscala/util/Either;Lscala/Option;Ljava/lang/String;Lscala/collection/immutable/List;Lscala/Option;)V
        44: return
      LineNumberTable:
        line 43: 0
        line 45: 5
        line 49: 10
        line 50: 16
        line 51: 22
        line 52: 23
        line 42: 44
      LocalVariableTable:
        Start  Length  Slot  Name   Signature
            0      45     0  this   Lorg/scalatest/exceptions/TableDrivenPropertyCheckFailedException;
            0      45     1 messageFun   Lscala/Function1;
            0      45     2 cause   Lscala/Option;
            0      45     3 posOrStackDepthFun   Lscala/util/Either;
            0      45     4 payload   Lscala/Option;
            0      45     5 undecoratedMessage   Ljava/lang/String;
            0      45     6  args   Lscala/collection/immutable/List;
            0      45     7 namesOfArgs   Lscala/collection/immutable/List;
            0      45     8   row   I
    Signature: #136                         // (Lscala/Function1<Lorg/scalatest/exceptions/StackDepthException;Ljava/lang/String;>;Lscala/Option<Ljava/lang/Throwable;>;Lscala/util/Either<Lorg/scalactic/source/Position;Lscala/Function1<Lorg/scalatest/exceptions/StackDepthException;Ljava/lang/Object;>;>;Lscala/Option<Ljava/lang/Object;>;Ljava/lang/String;Lscala/collection/immutable/List<Ljava/lang/Object;>;Lscala/collection/immutable/List<Ljava/lang/String;>;I)V
    MethodParameters:
      Name                           Flags
      messageFun                     final
      cause                          final
      posOrStackDepthFun             final
      payload                        final
      undecoratedMessage             final
      args                           final
      namesOfArgs                    final
      row                            final

  public org.scalatest.exceptions.TableDrivenPropertyCheckFailedException(scala.Function1<org.scalatest.exceptions.StackDepthException, java.lang.String>, scala.Option<java.lang.Throwable>, org.scalactic.source.Position, scala.Option<java.lang.Object>, java.lang.String, scala.collection.immutable.List<java.lang.Object>, scala.collection.immutable.List<java.lang.String>, int);
    descriptor: (Lscala/Function1;Lscala/Option;Lorg/scalactic/source/Position;Lscala/Option;Ljava/lang/String;Lscala/collection/immutable/List;Lscala/collection/immutable/List;I)V
    flags: (0x0001) ACC_PUBLIC
    Code:
      stack=9, locals=9, args_size=9
         0: aload_0
         1: aload_1
         2: aload_2
         3: getstatic     #154                // Field scala/package$.MODULE$:Lscala/package$;
         6: invokevirtual #158                // Method scala/package$.Left:()Lscala/util/Left$;
         9: aload_3
        10: invokevirtual #163                // Method scala/util/Left$.apply:(Ljava/lang/Object;)Lscala/util/Left;
        13: aload         4
        15: aload         5
        17: aload         6
        19: aload         7
        21: iload         8
        23: invokespecial #84                 // Method "<init>":(Lscala/Function1;Lscala/Option;Lscala/util/Either;Lscala/Option;Ljava/lang/String;Lscala/collection/immutable/List;Lscala/collection/immutable/List;I)V
        26: return
      LineNumberTable:
        line 78: 0
      LocalVariableTable:
        Start  Length  Slot  Name   Signature
            0      27     0  this   Lorg/scalatest/exceptions/TableDrivenPropertyCheckFailedException;
            0      27     1 messageFun   Lscala/Function1;
            0      27     2 cause   Lscala/Option;
            0      27     3   pos   Lorg/scalactic/source/Position;
            0      27     4 payload   Lscala/Option;
            0      27     5 undecoratedMessage   Ljava/lang/String;
            0      27     6  args   Lscala/collection/immutable/List;
            0      27     7 namesOfArgs   Lscala/collection/immutable/List;
            0      27     8   row   I
    Signature: #147                         // (Lscala/Function1<Lorg/scalatest/exceptions/StackDepthException;Ljava/lang/String;>;Lscala/Option<Ljava/lang/Throwable;>;Lorg/scalactic/source/Position;Lscala/Option<Ljava/lang/Object;>;Ljava/lang/String;Lscala/collection/immutable/List<Ljava/lang/Object;>;Lscala/collection/immutable/List<Ljava/lang/String;>;I)V
    MethodParameters:
      Name                           Flags
      messageFun                     final
      cause                          final
      pos                            final
      payload                        final
      undecoratedMessage             final
      args                           final
      namesOfArgs                    final
      row                            final

  public org.scalatest.exceptions.TableDrivenPropertyCheckFailedException(scala.Function1<org.scalatest.exceptions.StackDepthException, java.lang.String>, scala.Option<java.lang.Throwable>, scala.Function1<org.scalatest.exceptions.StackDepthException, java.lang.Object>, scala.Option<java.lang.Object>, java.lang.String, scala.collection.immutable.List<java.lang.Object>, scala.collection.immutable.List<java.lang.String>, int);
    descriptor: (Lscala/Function1;Lscala/Option;Lscala/Function1;Lscala/Option;Ljava/lang/String;Lscala/collection/immutable/List;Lscala/collection/immutable/List;I)V
    flags: (0x0001) ACC_PUBLIC
    Code:
      stack=9, locals=9, args_size=9
         0: aload_0
         1: aload_1
         2: aload_2
         3: getstatic     #154                // Field scala/package$.MODULE$:Lscala/package$;
         6: invokevirtual #171                // Method scala/package$.Right:()Lscala/util/Right$;
         9: aload_3
        10: invokevirtual #176                // Method scala/util/Right$.apply:(Ljava/lang/Object;)Lscala/util/Right;
        13: aload         4
        15: aload         5
        17: aload         6
        19: aload         7
        21: iload         8
        23: invokespecial #84                 // Method "<init>":(Lscala/Function1;Lscala/Option;Lscala/util/Either;Lscala/Option;Ljava/lang/String;Lscala/collection/immutable/List;Lscala/collection/immutable/List;I)V
        26: return
      LineNumberTable:
        line 103: 0
      LocalVariableTable:
        Start  Length  Slot  Name   Signature
            0      27     0  this   Lorg/scalatest/exceptions/TableDrivenPropertyCheckFailedException;
            0      27     1 messageFun   Lscala/Function1;
            0      27     2 cause   Lscala/Option;
            0      27     3 failedCodeStackDepthFun   Lscala/Function1;
            0      27     4 payload   Lscala/Option;
            0      27     5 undecoratedMessage   Ljava/lang/String;
            0      27     6  args   Lscala/collection/immutable/List;
            0      27     7 namesOfArgs   Lscala/collection/immutable/List;
            0      27     8   row   I
    Signature: #166                         // (Lscala/Function1<Lorg/scalatest/exceptions/StackDepthException;Ljava/lang/String;>;Lscala/Option<Ljava/lang/Throwable;>;Lscala/Function1<Lorg/scalatest/exceptions/StackDepthException;Ljava/lang/Object;>;Lscala/Option<Ljava/lang/Object;>;Ljava/lang/String;Lscala/collection/immutable/List<Ljava/lang/Object;>;Lscala/collection/immutable/List<Ljava/lang/String;>;I)V
    MethodParameters:
      Name                           Flags
      messageFun                     final
      cause                          final
      failedCodeStackDepthFun        final
      payload                        final
      undecoratedMessage             final
      args                           final
      namesOfArgs                    final
      row                            final

  private static java.lang.Object $deserializeLambda$(java.lang.invoke.SerializedLambda);
    descriptor: (Ljava/lang/invoke/SerializedLambda;)Ljava/lang/Object;
    flags: (0x100a) ACC_PRIVATE, ACC_STATIC, ACC_SYNTHETIC
    Code:
      stack=1, locals=1, args_size=1
         0: aload_0
         1: invokedynamic #188,  0            // InvokeDynamic #2:lambdaDeserialize:(Ljava/lang/invoke/SerializedLambda;)Ljava/lang/Object;
         6: areturn
}
InnerClasses:
  public static final #13= #10 of #12;    // Lookup=class java/lang/invoke/MethodHandles$Lookup of class java/lang/invoke/MethodHandles
SourceFile: "TableDrivenPropertyCheckFailedException.scala"
RuntimeVisibleAnnotations:
  0: #6(#7=s#8)
    scala.reflect.ScalaSignature(
      bytes="\u0006\u0005\u0005ea\u0001B\b\u0011\u0001]A\u0001\u0002\b\u0001\u0003\u0002\u0003\u0006I!\b\u0005\nc\u0001\u0011\t\u0011)A\u0005eyB\u0001b\u0010\u0001\u0003\u0002\u0003\u0006I\u0001\u0011\u0005\n\u001f\u0002\u0011\t\u0011)A\u0005!RC\u0011b\u0016\u0001\u0003\u0002\u0003\u0006IA\n-\t\u0013e\u0003!\u0011!Q\u0001\nik\u0006\u0002\u00030\u0001\u0005\u0003\u0005\u000b\u0011B0\t\u0011\u0001\u0004!Q1A\u0005\u0002\u0005D\u0001B\u0019\u0001\u0003\u0002\u0003\u0006I\u0001\u0014\u0005\u0006G\u0002!\t\u0001\u001a\u0005\u0006G\u0002!\tA\u001c\u0005\u0006G\u0002!\t\u0001\u001f\u0005\b\u0003\u000b\u0001A\u0011IA\u0004\u0011\u001d\t\t\u0002\u0001C!\u0003\'\u0011q\u0005V1cY\u0016$%/\u001b<f]B\u0013x\u000e]3sif\u001c\u0005.Z2l\r\u0006LG.\u001a3Fq\u000e,\u0007\u000f^5p]*\u0011\u0011CE\u0001\u000bKb\u001cW\r\u001d;j_:\u001c(BA\n\u0015\u0003%\u00198-\u00197bi\u0016\u001cHOC\u0001\u0016\u0003\ry\'oZ\u0002\u0001\'\t\u0001\u0001\u0004\u0005\u0002\u001a55\t\u0001#\u0003\u0002\u001c!\ta\u0002K]8qKJ$\u0018p\u00115fG.4\u0015-\u001b7fI\u0016C8-\u001a9uS>t\u0017AC7fgN\fw-\u001a$v]B!a$I\u0012\'\u001b\u0005y\"\"\u0001\u0011\u0002\u000bM\u001c\u0017\r\\1\n\u0005\tz\"!\u0003$v]\u000e$\u0018n\u001c82!\tIB%\u0003\u0002&!\t\u00192\u000b^1dW\u0012+\u0007\u000f\u001e5Fq\u000e,\u0007\u000f^5p]B\u0011qE\f\b\u0003Q1\u0002\"!K\u0010\u000e\u0003)R!a\u000b\f\u0002\rq\u0012xn\u001c;?\u0013\tis$\u0001\u0004Qe\u0016$WMZ\u0005\u0003_A\u0012aa\u0015;sS:<\'BA\u0017 \u0003\u0015\u0019\u0017-^:f!\rq2\'N\u0005\u0003i}\u0011aa\u00149uS>t\u0007C\u0001\u001c<\u001d\t9\u0014H\u0004\u0002*q%\t\u0001%\u0003\u0002;?\u00059\u0001/Y2lC\u001e,\u0017B\u0001\u001f>\u0005%!\u0006N]8xC\ndWM\u0003\u0002;?%\u0011\u0011\u0007J\u0001\u0013a>\u001cxJ]*uC\u000e\\G)\u001a9uQ\u001a+h\u000e\u0005\u00037\u0003\u000e[\u0015B\u0001\">\u0005\u0019)\u0015\u000e\u001e5feB\u0011A)S\u0007\u0002\u000b*\u0011aiR\u0001\u0007g>,(oY3\u000b\u0005!#\u0012!C:dC2\f7\r^5d\u0013\tQUI\u0001\u0005Q_NLG/[8o!\u0011q\u0012e\t\'\u0011\u0005yi\u0015B\u0001( \u0005\rIe\u000e^\u0001\ba\u0006LHn\\1e!\rq2\'\u0015\t\u0003=IK!aU\u0010\u0003\u0007\u0005s\u00170\u0003\u0002P+&\u0011a\u000b\u0005\u0002\u0014)\u0016\u001cHOR1jY\u0016$W\t_2faRLwN\\\u0001\u0013k:$WmY8sCR,G-T3tg\u0006<W-\u0003\u0002X5\u0005!\u0011M]4t!\r14,U\u0005\u00039v\u0012A\u0001T5ti&\u0011\u0011LG\u0001\f]\u0006lWm](g\u0003J<7\u000fE\u000277\u001a\n1A]8x+\u0005a\u0015\u0001\u0002:po\u0002\na\u0001P5oSRtD#C3gO\"L\'n\u001b7n!\tI\u0002\u0001C\u0003\u001d\u0015\u0001\u0007Q\u0004C\u00032\u0015\u0001\u0007!\u0007C\u0003@\u0015\u0001\u0007\u0001\tC\u0003P\u0015\u0001\u0007\u0001\u000bC\u0003X\u0015\u0001\u0007a\u0005C\u0003Z\u0015\u0001\u0007!\fC\u0003_\u0015\u0001\u0007q\fC\u0003a\u0015\u0001\u0007A\nF\u0005f_B\f8\u000f^;wo\")Ad\u0003a\u0001;!)\u0011g\u0003a\u0001e!)!o\u0003a\u0001\u0007\u0006\u0019\u0001o\\:\t\u000b=[\u0001\u0019\u0001)\t\u000b][\u0001\u0019\u0001\u0014\t\u000be[\u0001\u0019\u0001.\t\u000by[\u0001\u0019A0\t\u000b\u0001\\\u0001\u0019\u0001\'\u0015\u0017\u0015L(p_?\u007f\u007f\u0006\u0005\u00111\u0001\u0005\u000691\u0001\r!\b\u0005\u0006c1\u0001\rA\r\u0005\u0006y2\u0001\raS\u0001\u0018M\u0006LG.\u001a3D_\u0012,7\u000b^1dW\u0012+\u0007\u000f\u001e5Gk:DQa\u0014\u0007A\u0002ACQa\u0016\u0007A\u0002\u0019BQ!\u0017\u0007A\u0002iCQA\u0018\u0007A\u0002}CQ\u0001\u0019\u0007A\u00021\u000bQ\"\\8eS\u001aLX*Z:tC\u001e,GcA3\u0002\n!9\u00111B\u0007A\u0002\u00055\u0011a\u00014v]B1a$IA\b\u0003\u001f\u00012AH\u001a\'\u00035iw\u000eZ5gsB\u000b\u0017\u0010\\8bIR\u0019Q-!\u0006\t\u000f\u0005-a\u00021\u0001\u0002\u0018A!a$\t)Q\u0001"
    )
BootstrapMethods:
  0: #51 REF_invokeStatic java/lang/invoke/LambdaMetafactory.altMetafactory:(Ljava/lang/invoke/MethodHandles$Lookup;Ljava/lang/String;Ljava/lang/invoke/MethodType;[Ljava/lang/Object;)Ljava/lang/invoke/CallSite;
    Method arguments:
      #35 (Ljava/lang/Object;)Ljava/lang/Object;
      #40 REF_invokeStatic org/scalatest/exceptions/TableDrivenPropertyCheckFailedException.$anonfun$modifyMessage$1:(Lorg/scalatest/exceptions/TableDrivenPropertyCheckFailedException;Lscala/Function1;Lorg/scalatest/exceptions/StackDepthException;)Ljava/lang/String;
      #42 (Lorg/scalatest/exceptions/StackDepthException;)Ljava/lang/String;
      #43 5
      #44 1
      #42 (Lorg/scalatest/exceptions/StackDepthException;)Ljava/lang/String;
  1: #51 REF_invokeStatic java/lang/invoke/LambdaMetafactory.altMetafactory:(Ljava/lang/invoke/MethodHandles$Lookup;Ljava/lang/String;Ljava/lang/invoke/MethodType;[Ljava/lang/Object;)Ljava/lang/invoke/CallSite;
    Method arguments:
      #123 ()Ljava/lang/Object;
      #126 REF_invokeStatic org/scalatest/exceptions/TableDrivenPropertyCheckFailedException.$anonfun$modifyMessage$2:(Lorg/scalatest/exceptions/TableDrivenPropertyCheckFailedException;)Ljava/lang/String;
      #127 ()Ljava/lang/String;
      #43 5
      #44 1
      #127 ()Ljava/lang/String;
  2: #185 REF_invokeStatic scala/runtime/LambdaDeserialize.bootstrap:(Ljava/lang/invoke/MethodHandles$Lookup;Ljava/lang/String;Ljava/lang/invoke/MethodType;[Ljava/lang/invoke/MethodHandle;)Ljava/lang/invoke/CallSite;
    Method arguments:
      #40 REF_invokeStatic org/scalatest/exceptions/TableDrivenPropertyCheckFailedException.$anonfun$modifyMessage$1:(Lorg/scalatest/exceptions/TableDrivenPropertyCheckFailedException;Lscala/Function1;Lorg/scalatest/exceptions/StackDepthException;)Ljava/lang/String;
      #126 REF_invokeStatic org/scalatest/exceptions/TableDrivenPropertyCheckFailedException.$anonfun$modifyMessage$2:(Lorg/scalatest/exceptions/TableDrivenPropertyCheckFailedException;)Ljava/lang/String;
  ScalaInlineInfo: length = 0x40 (unknown attribute)
   01 00 00 0C 00 24 00 25 01 00 70 00 71 01 00 51
   00 92 00 00 51 00 A5 00 00 51 00 52 00 00 1E 00
   6A 00 00 1E 00 1F 00 00 1E 00 6D 00 00 5E 00 6A
   00 00 5E 00 1F 00 00 5E 00 6D 00 00 17 00 19 00

  ScalaSig: length = 0x3 (unknown attribute)
   05 02 00
