Classfile /Users/mw/Projects/slang-braindump/.jar/jar11/assemble/slang-braindump/assemble/content/scala/sys/ShutdownHookThread.class
  Last modified May 29, 2022; size 1691 bytes
  SHA-256 checksum a91a9c54a8bd8008d13a6e99b4ad485c1eef7d4acd76eca6d9fe7c5b95b86e18
  Compiled from "ShutdownHookThread.scala"
public class scala.sys.ShutdownHookThread extends java.lang.Thread
  minor version: 0
  major version: 52
  flags: (0x0021) ACC_PUBLIC, ACC_SUPER
  this_class: #2                          // scala/sys/ShutdownHookThread
  super_class: #4                         // java/lang/Thread
  interfaces: 0, fields: 0, methods: 3, attributes: 4
Constant pool:
   #1 = Utf8               scala/sys/ShutdownHookThread
   #2 = Class              #1             // scala/sys/ShutdownHookThread
   #3 = Utf8               java/lang/Thread
   #4 = Class              #3             // java/lang/Thread
   #5 = Utf8               ShutdownHookThread.scala
   #6 = Utf8               Lscala/reflect/ScalaSignature;
   #7 = Utf8               bytes
   #8 = Utf8               \u0006\u000553Aa\u0003\u0007\u0001#!A!\u0004\u0001B\u0001B\u0003%1\u0004\u0003\u0005\u001f\u0001\t\u0005\t\u0015!\u0003 \u0011\u0015Q\u0003\u0001\"\u0003,\u0011\u0015\u0001\u0004\u0001\"\u00012\u000f\u00151D\u0002#\u00018\r\u0015YA\u0002#\u00019\u0011\u0015Qc\u0001\"\u0001=\u0011\u0019id\u0001)Q\u0005}!)\u0011I\u0002C\u0005\u0005\")1I\u0002C\u0001\t\n\u00112\u000b[;uI><h\u000eS8pWRC\'/Z1e\u0015\tia\"A\u0002tsNT\u0011aD\u0001\u0006g\u000e\fG.Y\u0002\u0001\'\t\u0001!\u0003\u0005\u0002\u001415\tAC\u0003\u0002\u0016-\u0005!A.\u00198h\u0015\u00059\u0012\u0001\u00026bm\u0006L!!\u0007\u000b\u0003\rQC\'/Z1e\u0003!\u0011XO\u001c8bE2,\u0007CA\n\u001d\u0013\tiBC\u0001\u0005Sk:t\u0017M\u00197f\u0003\u0011q\u0017-\\3\u0011\u0005\u0001:cBA\u0011&!\t\u0011c\"D\u0001$\u0015\t!\u0003#\u0001\u0004=e>|GOP\u0005\u0003M9\ta\u0001\u0015:fI\u00164\u0017B\u0001\u0015*\u0005\u0019\u0019FO]5oO*\u0011aED\u0001\u0007y%t\u0017\u000e\u001e \u0015\u00071rs\u0006\u0005\u0002.\u00015\tA\u0002C\u0003\u001b\u0007\u0001\u00071\u0004C\u0003\u001f\u0007\u0001\u0007q$\u0001\u0004sK6|g/\u001a\u000b\u0002eA\u00111\u0007N\u0007\u0002\u001d%\u0011QG\u0004\u0002\b\u0005>|G.Z1o\u0003I\u0019\u0006.\u001e;e_^t\u0007j\\8l)\"\u0014X-\u00193\u0011\u0005521C\u0001\u0004:!\t\u0019$(\u0003\u0002<\u001d\t1\u0011I\\=SK\u001a$\u0012aN\u0001\u000eQ>|7NT1nK\u000e{WO\u001c;\u0011\u0005Mz\u0014B\u0001!\u000f\u0005\rIe\u000e^\u0001\tQ>|7NT1nKR\tq$A\u0003baBd\u0017\u0010\u0006\u0002-\u000b\"1aI\u0003CA\u0002\u001d\u000bAAY8esB\u00191\u0007\u0013&\n\u0005%s!\u0001\u0003\u001fcs:\fW.\u001a \u0011\u0005MZ\u0015B\u0001\'\u000f\u0005\u0011)f.\u001b;
   #9 = Utf8               apply
  #10 = Utf8               (Lscala/Function0;)Lscala/sys/ShutdownHookThread;
  #11 = Utf8               (Lscala/Function0<Lscala/runtime/BoxedUnit;>;)Lscala/sys/ShutdownHookThread;
  #12 = Utf8               body
  #13 = Utf8               scala/sys/ShutdownHookThread$
  #14 = Class              #13            // scala/sys/ShutdownHookThread$
  #15 = Utf8               MODULE$
  #16 = Utf8               Lscala/sys/ShutdownHookThread$;
  #17 = NameAndType        #15:#16        // MODULE$:Lscala/sys/ShutdownHookThread$;
  #18 = Fieldref           #14.#17        // scala/sys/ShutdownHookThread$.MODULE$:Lscala/sys/ShutdownHookThread$;
  #19 = NameAndType        #9:#10         // apply:(Lscala/Function0;)Lscala/sys/ShutdownHookThread;
  #20 = Methodref          #14.#19        // scala/sys/ShutdownHookThread$.apply:(Lscala/Function0;)Lscala/sys/ShutdownHookThread;
  #21 = Utf8               Lscala/Function0;
  #22 = Utf8               remove
  #23 = Utf8               ()Z
  #24 = Utf8               java/lang/Runtime
  #25 = Class              #24            // java/lang/Runtime
  #26 = Utf8               getRuntime
  #27 = Utf8               ()Ljava/lang/Runtime;
  #28 = NameAndType        #26:#27        // getRuntime:()Ljava/lang/Runtime;
  #29 = Methodref          #25.#28        // java/lang/Runtime.getRuntime:()Ljava/lang/Runtime;
  #30 = Utf8               removeShutdownHook
  #31 = Utf8               (Ljava/lang/Thread;)Z
  #32 = NameAndType        #30:#31        // removeShutdownHook:(Ljava/lang/Thread;)Z
  #33 = Methodref          #25.#32        // java/lang/Runtime.removeShutdownHook:(Ljava/lang/Thread;)Z
  #34 = Utf8               this
  #35 = Utf8               Lscala/sys/ShutdownHookThread;
  #36 = Utf8               <init>
  #37 = Utf8               (Ljava/lang/Runnable;Ljava/lang/String;)V
  #38 = Utf8               runnable
  #39 = Utf8               name
  #40 = NameAndType        #36:#37        // "<init>":(Ljava/lang/Runnable;Ljava/lang/String;)V
  #41 = Methodref          #4.#40         // java/lang/Thread."<init>":(Ljava/lang/Runnable;Ljava/lang/String;)V
  #42 = Utf8               Ljava/lang/Runnable;
  #43 = Utf8               Ljava/lang/String;
  #44 = Utf8               Code
  #45 = Utf8               LocalVariableTable
  #46 = Utf8               Signature
  #47 = Utf8               MethodParameters
  #48 = Utf8               LineNumberTable
  #49 = Utf8               SourceFile
  #50 = Utf8               RuntimeVisibleAnnotations
  #51 = Utf8               ScalaInlineInfo
  #52 = Utf8               ScalaSig
{
  public static scala.sys.ShutdownHookThread apply(scala.Function0<scala.runtime.BoxedUnit>);
    descriptor: (Lscala/Function0;)Lscala/sys/ShutdownHookThread;
    flags: (0x0009) ACC_PUBLIC, ACC_STATIC
    Code:
      stack=2, locals=1, args_size=1
         0: getstatic     #18                 // Field scala/sys/ShutdownHookThread$.MODULE$:Lscala/sys/ShutdownHookThread$;
         3: aload_0
         4: invokevirtual #20                 // Method scala/sys/ShutdownHookThread$.apply:(Lscala/Function0;)Lscala/sys/ShutdownHookThread;
         7: areturn
      LocalVariableTable:
        Start  Length  Slot  Name   Signature
            0       8     0  body   Lscala/Function0;
    Signature: #11                          // (Lscala/Function0<Lscala/runtime/BoxedUnit;>;)Lscala/sys/ShutdownHookThread;
    MethodParameters:
      Name                           Flags
      body                           final

  public boolean remove();
    descriptor: ()Z
    flags: (0x0001) ACC_PUBLIC
    Code:
      stack=2, locals=1, args_size=1
         0: invokestatic  #29                 // Method java/lang/Runtime.getRuntime:()Ljava/lang/Runtime;
         3: aload_0
         4: invokevirtual #33                 // Method java/lang/Runtime.removeShutdownHook:(Ljava/lang/Thread;)Z
         7: ireturn
      LineNumberTable:
        line 20: 0
      LocalVariableTable:
        Start  Length  Slot  Name   Signature
            0       8     0  this   Lscala/sys/ShutdownHookThread;

  public scala.sys.ShutdownHookThread(java.lang.Runnable, java.lang.String);
    descriptor: (Ljava/lang/Runnable;Ljava/lang/String;)V
    flags: (0x0001) ACC_PUBLIC
    Code:
      stack=3, locals=3, args_size=3
         0: aload_0
         1: aload_1
         2: aload_2
         3: invokespecial #41                 // Method java/lang/Thread."<init>":(Ljava/lang/Runnable;Ljava/lang/String;)V
         6: return
      LineNumberTable:
        line 19: 0
      LocalVariableTable:
        Start  Length  Slot  Name   Signature
            0       7     0  this   Lscala/sys/ShutdownHookThread;
            0       7     1 runnable   Ljava/lang/Runnable;
            0       7     2  name   Ljava/lang/String;
    MethodParameters:
      Name                           Flags
      runnable                       final
      name                           final
}
SourceFile: "ShutdownHookThread.scala"
RuntimeVisibleAnnotations:
  0: #6(#7=s#8)
    scala.reflect.ScalaSignature(
      bytes="\u0006\u000553Aa\u0003\u0007\u0001#!A!\u0004\u0001B\u0001B\u0003%1\u0004\u0003\u0005\u001f\u0001\t\u0005\t\u0015!\u0003 \u0011\u0015Q\u0003\u0001\"\u0003,\u0011\u0015\u0001\u0004\u0001\"\u00012\u000f\u00151D\u0002#\u00018\r\u0015YA\u0002#\u00019\u0011\u0015Qc\u0001\"\u0001=\u0011\u0019id\u0001)Q\u0005}!)\u0011I\u0002C\u0005\u0005\")1I\u0002C\u0001\t\n\u00112\u000b[;uI><h\u000eS8pWRC\'/Z1e\u0015\tia\"A\u0002tsNT\u0011aD\u0001\u0006g\u000e\fG.Y\u0002\u0001\'\t\u0001!\u0003\u0005\u0002\u001415\tAC\u0003\u0002\u0016-\u0005!A.\u00198h\u0015\u00059\u0012\u0001\u00026bm\u0006L!!\u0007\u000b\u0003\rQC\'/Z1e\u0003!\u0011XO\u001c8bE2,\u0007CA\n\u001d\u0013\tiBC\u0001\u0005Sk:t\u0017M\u00197f\u0003\u0011q\u0017-\\3\u0011\u0005\u0001:cBA\u0011&!\t\u0011c\"D\u0001$\u0015\t!\u0003#\u0001\u0004=e>|GOP\u0005\u0003M9\ta\u0001\u0015:fI\u00164\u0017B\u0001\u0015*\u0005\u0019\u0019FO]5oO*\u0011aED\u0001\u0007y%t\u0017\u000e\u001e \u0015\u00071rs\u0006\u0005\u0002.\u00015\tA\u0002C\u0003\u001b\u0007\u0001\u00071\u0004C\u0003\u001f\u0007\u0001\u0007q$\u0001\u0004sK6|g/\u001a\u000b\u0002eA\u00111\u0007N\u0007\u0002\u001d%\u0011QG\u0004\u0002\b\u0005>|G.Z1o\u0003I\u0019\u0006.\u001e;e_^t\u0007j\\8l)\"\u0014X-\u00193\u0011\u0005521C\u0001\u0004:!\t\u0019$(\u0003\u0002<\u001d\t1\u0011I\\=SK\u001a$\u0012aN\u0001\u000eQ>|7NT1nK\u000e{WO\u001c;\u0011\u0005Mz\u0014B\u0001!\u000f\u0005\rIe\u000e^\u0001\tQ>|7NT1nKR\tq$A\u0003baBd\u0017\u0010\u0006\u0002-\u000b\"1aI\u0003CA\u0002\u001d\u000bAAY8esB\u00191\u0007\u0013&\n\u0005%s!\u0001\u0003\u001fcs:\fW.\u001a \u0011\u0005MZ\u0015B\u0001\'\u000f\u0005\u0011)f.\u001b;"
    )
  ScalaInlineInfo: length = 0xE (unknown attribute)
   01 00 00 02 00 24 00 25 01 00 16 00 17 00
  ScalaSig: length = 0x3 (unknown attribute)
   05 02 00
