Classfile /Users/mw/Projects/slang-braindump/.jar/jar8/assemble/slang-braindump/assemble/content/com/fasterxml/jackson/core/sym/Name1.class
  Last modified May 29, 2022; size 1192 bytes
  SHA-256 checksum 5a79d15e10590be54449f78ab66fc7b42a3e47a0427b7564b71fb2a84b79c898
  Compiled from "Name1.java"
public final class com.fasterxml.jackson.core.sym.Name1 extends com.fasterxml.jackson.core.sym.Name
  minor version: 0
  major version: 50
  flags: (0x0031) ACC_PUBLIC, ACC_FINAL, ACC_SUPER
  this_class: #4                          // com/fasterxml/jackson/core/sym/Name1
  super_class: #7                         // com/fasterxml/jackson/core/sym/Name
  interfaces: 0, fields: 2, methods: 7, attributes: 1
Constant pool:
   #1 = Methodref          #7.#42         // com/fasterxml/jackson/core/sym/Name."<init>":(Ljava/lang/String;I)V
   #2 = Fieldref           #4.#43         // com/fasterxml/jackson/core/sym/Name1.q:I
   #3 = Fieldref           #4.#44         // com/fasterxml/jackson/core/sym/Name1.EMPTY:Lcom/fasterxml/jackson/core/sym/Name1;
   #4 = Class              #45            // com/fasterxml/jackson/core/sym/Name1
   #5 = String             #46            //
   #6 = Methodref          #4.#47         // com/fasterxml/jackson/core/sym/Name1."<init>":(Ljava/lang/String;II)V
   #7 = Class              #48            // com/fasterxml/jackson/core/sym/Name
   #8 = Utf8               EMPTY
   #9 = Utf8               Lcom/fasterxml/jackson/core/sym/Name1;
  #10 = Utf8               q
  #11 = Utf8               I
  #12 = Utf8               <init>
  #13 = Utf8               (Ljava/lang/String;II)V
  #14 = Utf8               Code
  #15 = Utf8               LineNumberTable
  #16 = Utf8               LocalVariableTable
  #17 = Utf8               this
  #18 = Utf8               name
  #19 = Utf8               Ljava/lang/String;
  #20 = Utf8               hash
  #21 = Utf8               quad
  #22 = Utf8               getEmptyName
  #23 = Utf8               ()Lcom/fasterxml/jackson/core/sym/Name1;
  #24 = Utf8               equals
  #25 = Utf8               (I)Z
  #26 = Utf8               StackMapTable
  #27 = Utf8               (II)Z
  #28 = Utf8               quad1
  #29 = Utf8               quad2
  #30 = Utf8               (III)Z
  #31 = Utf8               q1
  #32 = Utf8               q2
  #33 = Utf8               q3
  #34 = Utf8               ([II)Z
  #35 = Utf8               quads
  #36 = Utf8               [I
  #37 = Utf8               qlen
  #38 = Utf8               <clinit>
  #39 = Utf8               ()V
  #40 = Utf8               SourceFile
  #41 = Utf8               Name1.java
  #42 = NameAndType        #12:#49        // "<init>":(Ljava/lang/String;I)V
  #43 = NameAndType        #10:#11        // q:I
  #44 = NameAndType        #8:#9          // EMPTY:Lcom/fasterxml/jackson/core/sym/Name1;
  #45 = Utf8               com/fasterxml/jackson/core/sym/Name1
  #46 = Utf8
  #47 = NameAndType        #12:#13        // "<init>":(Ljava/lang/String;II)V
  #48 = Utf8               com/fasterxml/jackson/core/sym/Name
  #49 = Utf8               (Ljava/lang/String;I)V
{
  private static final com.fasterxml.jackson.core.sym.Name1 EMPTY;
    descriptor: Lcom/fasterxml/jackson/core/sym/Name1;
    flags: (0x001a) ACC_PRIVATE, ACC_STATIC, ACC_FINAL

  private final int q;
    descriptor: I
    flags: (0x0012) ACC_PRIVATE, ACC_FINAL

  com.fasterxml.jackson.core.sym.Name1(java.lang.String, int, int);
    descriptor: (Ljava/lang/String;II)V
    flags: (0x0000)
    Code:
      stack=3, locals=4, args_size=4
         0: aload_0
         1: aload_1
         2: iload_2
         3: invokespecial #1                  // Method com/fasterxml/jackson/core/sym/Name."<init>":(Ljava/lang/String;I)V
         6: aload_0
         7: iload_3
         8: putfield      #2                  // Field q:I
        11: return
      LineNumberTable:
        line 18: 0
        line 19: 6
        line 20: 11
      LocalVariableTable:
        Start  Length  Slot  Name   Signature
            0      12     0  this   Lcom/fasterxml/jackson/core/sym/Name1;
            0      12     1  name   Ljava/lang/String;
            0      12     2  hash   I
            0      12     3  quad   I

  public static com.fasterxml.jackson.core.sym.Name1 getEmptyName();
    descriptor: ()Lcom/fasterxml/jackson/core/sym/Name1;
    flags: (0x0009) ACC_PUBLIC, ACC_STATIC
    Code:
      stack=1, locals=0, args_size=0
         0: getstatic     #3                  // Field EMPTY:Lcom/fasterxml/jackson/core/sym/Name1;
         3: areturn
      LineNumberTable:
        line 22: 0

  public boolean equals(int);
    descriptor: (I)Z
    flags: (0x0001) ACC_PUBLIC
    Code:
      stack=2, locals=2, args_size=2
         0: iload_1
         1: aload_0
         2: getfield      #2                  // Field q:I
         5: if_icmpne     12
         8: iconst_1
         9: goto          13
        12: iconst_0
        13: ireturn
      LineNumberTable:
        line 24: 0
      LocalVariableTable:
        Start  Length  Slot  Name   Signature
            0      14     0  this   Lcom/fasterxml/jackson/core/sym/Name1;
            0      14     1  quad   I
      StackMapTable: number_of_entries = 2
        frame_type = 12 /* same */
        frame_type = 64 /* same_locals_1_stack_item */
          stack = [ int ]

  public boolean equals(int, int);
    descriptor: (II)Z
    flags: (0x0001) ACC_PUBLIC
    Code:
      stack=2, locals=3, args_size=3
         0: iload_1
         1: aload_0
         2: getfield      #2                  // Field q:I
         5: if_icmpne     16
         8: iload_2
         9: ifne          16
        12: iconst_1
        13: goto          17
        16: iconst_0
        17: ireturn
      LineNumberTable:
        line 25: 0
      LocalVariableTable:
        Start  Length  Slot  Name   Signature
            0      18     0  this   Lcom/fasterxml/jackson/core/sym/Name1;
            0      18     1 quad1   I
            0      18     2 quad2   I
      StackMapTable: number_of_entries = 2
        frame_type = 16 /* same */
        frame_type = 64 /* same_locals_1_stack_item */
          stack = [ int ]

  public boolean equals(int, int, int);
    descriptor: (III)Z
    flags: (0x0001) ACC_PUBLIC
    Code:
      stack=1, locals=4, args_size=4
         0: iconst_0
         1: ireturn
      LineNumberTable:
        line 26: 0
      LocalVariableTable:
        Start  Length  Slot  Name   Signature
            0       2     0  this   Lcom/fasterxml/jackson/core/sym/Name1;
            0       2     1    q1   I
            0       2     2    q2   I
            0       2     3    q3   I

  public boolean equals(int[], int);
    descriptor: ([II)Z
    flags: (0x0001) ACC_PUBLIC
    Code:
      stack=2, locals=3, args_size=3
         0: iload_2
         1: iconst_1
         2: if_icmpne     19
         5: aload_1
         6: iconst_0
         7: iaload
         8: aload_0
         9: getfield      #2                  // Field q:I
        12: if_icmpne     19
        15: iconst_1
        16: goto          20
        19: iconst_0
        20: ireturn
      LineNumberTable:
        line 28: 0
      LocalVariableTable:
        Start  Length  Slot  Name   Signature
            0      21     0  this   Lcom/fasterxml/jackson/core/sym/Name1;
            0      21     1 quads   [I
            0      21     2  qlen   I
      StackMapTable: number_of_entries = 2
        frame_type = 19 /* same */
        frame_type = 64 /* same_locals_1_stack_item */
          stack = [ int ]

  static {};
    descriptor: ()V
    flags: (0x0008) ACC_STATIC
    Code:
      stack=5, locals=0, args_size=0
         0: new           #4                  // class com/fasterxml/jackson/core/sym/Name1
         3: dup
         4: ldc           #5                  // String
         6: iconst_0
         7: iconst_0
         8: invokespecial #6                  // Method "<init>":(Ljava/lang/String;II)V
        11: putstatic     #3                  // Field EMPTY:Lcom/fasterxml/jackson/core/sym/Name1;
        14: return
      LineNumberTable:
        line 14: 0
}
SourceFile: "Name1.java"
