Classfile /Users/mw/Projects/slang-braindump/.jar/jar8/assemble/slang-braindump/assemble/content/com/fasterxml/jackson/core/sym/Name.class
  Last modified May 29, 2022; size 925 bytes
  SHA-256 checksum 615e39951a371414d4511b1c83225d5374c8adcd793d25f371e9dc9825f5968e
  Compiled from "Name.java"
public abstract class com.fasterxml.jackson.core.sym.Name
  minor version: 0
  major version: 50
  flags: (0x0421) ACC_PUBLIC, ACC_SUPER, ACC_ABSTRACT
  this_class: #4                          // com/fasterxml/jackson/core/sym/Name
  super_class: #5                         // java/lang/Object
  interfaces: 0, fields: 2, methods: 9, attributes: 1
Constant pool:
   #1 = Methodref          #5.#34         // java/lang/Object."<init>":()V
   #2 = Fieldref           #4.#35         // com/fasterxml/jackson/core/sym/Name._name:Ljava/lang/String;
   #3 = Fieldref           #4.#36         // com/fasterxml/jackson/core/sym/Name._hashCode:I
   #4 = Class              #37            // com/fasterxml/jackson/core/sym/Name
   #5 = Class              #38            // java/lang/Object
   #6 = Utf8               _name
   #7 = Utf8               Ljava/lang/String;
   #8 = Utf8               _hashCode
   #9 = Utf8               I
  #10 = Utf8               <init>
  #11 = Utf8               (Ljava/lang/String;I)V
  #12 = Utf8               Code
  #13 = Utf8               LineNumberTable
  #14 = Utf8               LocalVariableTable
  #15 = Utf8               this
  #16 = Utf8               Lcom/fasterxml/jackson/core/sym/Name;
  #17 = Utf8               name
  #18 = Utf8               hashCode
  #19 = Utf8               getName
  #20 = Utf8               ()Ljava/lang/String;
  #21 = Utf8               equals
  #22 = Utf8               (I)Z
  #23 = Utf8               (II)Z
  #24 = Utf8               (III)Z
  #25 = Utf8               ([II)Z
  #26 = Utf8               toString
  #27 = Utf8               ()I
  #28 = Utf8               (Ljava/lang/Object;)Z
  #29 = Utf8               o
  #30 = Utf8               Ljava/lang/Object;
  #31 = Utf8               StackMapTable
  #32 = Utf8               SourceFile
  #33 = Utf8               Name.java
  #34 = NameAndType        #10:#39        // "<init>":()V
  #35 = NameAndType        #6:#7          // _name:Ljava/lang/String;
  #36 = NameAndType        #8:#9          // _hashCode:I
  #37 = Utf8               com/fasterxml/jackson/core/sym/Name
  #38 = Utf8               java/lang/Object
  #39 = Utf8               ()V
{
  protected final java.lang.String _name;
    descriptor: Ljava/lang/String;
    flags: (0x0014) ACC_PROTECTED, ACC_FINAL

  protected final int _hashCode;
    descriptor: I
    flags: (0x0014) ACC_PROTECTED, ACC_FINAL

  protected com.fasterxml.jackson.core.sym.Name(java.lang.String, int);
    descriptor: (Ljava/lang/String;I)V
    flags: (0x0004) ACC_PROTECTED
    Code:
      stack=2, locals=3, args_size=3
         0: aload_0
         1: invokespecial #1                  // Method java/lang/Object."<init>":()V
         4: aload_0
         5: aload_1
         6: putfield      #2                  // Field _name:Ljava/lang/String;
         9: aload_0
        10: iload_2
        11: putfield      #3                  // Field _hashCode:I
        14: return
      LineNumberTable:
        line 16: 0
        line 17: 4
        line 18: 9
        line 19: 14
      LocalVariableTable:
        Start  Length  Slot  Name   Signature
            0      15     0  this   Lcom/fasterxml/jackson/core/sym/Name;
            0      15     1  name   Ljava/lang/String;
            0      15     2 hashCode   I

  public java.lang.String getName();
    descriptor: ()Ljava/lang/String;
    flags: (0x0001) ACC_PUBLIC
    Code:
      stack=1, locals=1, args_size=1
         0: aload_0
         1: getfield      #2                  // Field _name:Ljava/lang/String;
         4: areturn
      LineNumberTable:
        line 21: 0
      LocalVariableTable:
        Start  Length  Slot  Name   Signature
            0       5     0  this   Lcom/fasterxml/jackson/core/sym/Name;

  public abstract boolean equals(int);
    descriptor: (I)Z
    flags: (0x0401) ACC_PUBLIC, ACC_ABSTRACT

  public abstract boolean equals(int, int);
    descriptor: (II)Z
    flags: (0x0401) ACC_PUBLIC, ACC_ABSTRACT

  public abstract boolean equals(int, int, int);
    descriptor: (III)Z
    flags: (0x0401) ACC_PUBLIC, ACC_ABSTRACT

  public abstract boolean equals(int[], int);
    descriptor: ([II)Z
    flags: (0x0401) ACC_PUBLIC, ACC_ABSTRACT

  public java.lang.String toString();
    descriptor: ()Ljava/lang/String;
    flags: (0x0001) ACC_PUBLIC
    Code:
      stack=1, locals=1, args_size=1
         0: aload_0
         1: getfield      #2                  // Field _name:Ljava/lang/String;
         4: areturn
      LineNumberTable:
        line 43: 0
      LocalVariableTable:
        Start  Length  Slot  Name   Signature
            0       5     0  this   Lcom/fasterxml/jackson/core/sym/Name;

  public final int hashCode();
    descriptor: ()I
    flags: (0x0011) ACC_PUBLIC, ACC_FINAL
    Code:
      stack=1, locals=1, args_size=1
         0: aload_0
         1: getfield      #3                  // Field _hashCode:I
         4: ireturn
      LineNumberTable:
        line 45: 0
      LocalVariableTable:
        Start  Length  Slot  Name   Signature
            0       5     0  this   Lcom/fasterxml/jackson/core/sym/Name;

  public boolean equals(java.lang.Object);
    descriptor: (Ljava/lang/Object;)Z
    flags: (0x0001) ACC_PUBLIC
    Code:
      stack=2, locals=2, args_size=2
         0: aload_1
         1: aload_0
         2: if_acmpne     9
         5: iconst_1
         6: goto          10
         9: iconst_0
        10: ireturn
      LineNumberTable:
        line 49: 0
      LocalVariableTable:
        Start  Length  Slot  Name   Signature
            0      11     0  this   Lcom/fasterxml/jackson/core/sym/Name;
            0      11     1     o   Ljava/lang/Object;
      StackMapTable: number_of_entries = 2
        frame_type = 9 /* same */
        frame_type = 64 /* same_locals_1_stack_item */
          stack = [ int ]
}
SourceFile: "Name.java"
