Classfile /Users/mw/Projects/slang-braindump/.jar/jar11/assemble/slang-braindump/assemble/content/scala/util/hashing/MurmurHash3$$anon$2.class
  Last modified May 29, 2022; size 1242 bytes
  SHA-256 checksum cf307a8171e6e75db53509a18b42551c85ef7db8a3d07e56c942a2150338180a
  Compiled from "MurmurHash3.scala"
public final class scala.util.hashing.MurmurHash3$$anon$2 extends java.lang.Object implements scala.util.hashing.Hashing<scala.collection.IterableOnce<java.lang.Object>>
  minor version: 0
  major version: 52
  flags: (0x0031) ACC_PUBLIC, ACC_FINAL, ACC_SUPER
  this_class: #2                          // scala/util/hashing/MurmurHash3$$anon$2
  super_class: #5                         // java/lang/Object
  interfaces: 1, fields: 0, methods: 3, attributes: 6
Constant pool:
   #1 = Utf8               scala/util/hashing/MurmurHash3$$anon$2
   #2 = Class              #1             // scala/util/hashing/MurmurHash3$$anon$2
   #3 = Utf8               Ljava/lang/Object;Lscala/util/hashing/Hashing<Lscala/collection/IterableOnce<Ljava/lang/Object;>;>;
   #4 = Utf8               java/lang/Object
   #5 = Class              #4             // java/lang/Object
   #6 = Utf8               scala/util/hashing/Hashing
   #7 = Class              #6             // scala/util/hashing/Hashing
   #8 = Utf8               MurmurHash3.scala
   #9 = Utf8               scala/util/hashing/MurmurHash3$
  #10 = Class              #9             // scala/util/hashing/MurmurHash3$
  #11 = Utf8               orderedHashing
  #12 = Utf8               ()Lscala/util/hashing/Hashing;
  #13 = NameAndType        #11:#12        // orderedHashing:()Lscala/util/hashing/Hashing;
  #14 = Utf8               hash
  #15 = Utf8               (Lscala/collection/IterableOnce;)I
  #16 = Utf8               (Lscala/collection/IterableOnce<Ljava/lang/Object;>;)I
  #17 = Utf8               xs
  #18 = Utf8               MODULE$
  #19 = Utf8               Lscala/util/hashing/MurmurHash3$;
  #20 = NameAndType        #18:#19        // MODULE$:Lscala/util/hashing/MurmurHash3$;
  #21 = Fieldref           #10.#20        // scala/util/hashing/MurmurHash3$.MODULE$:Lscala/util/hashing/MurmurHash3$;
  #22 = Integer            -1248659538
  #23 = Utf8               orderedHash
  #24 = Utf8               (Lscala/collection/IterableOnce;I)I
  #25 = NameAndType        #23:#24        // orderedHash:(Lscala/collection/IterableOnce;I)I
  #26 = Methodref          #10.#25        // scala/util/hashing/MurmurHash3$.orderedHash:(Lscala/collection/IterableOnce;I)I
  #27 = Utf8               this
  #28 = Utf8               Lscala/util/hashing/MurmurHash3$$anon$2;
  #29 = Utf8               Lscala/collection/IterableOnce;
  #30 = Utf8               (Ljava/lang/Object;)I
  #31 = Utf8               x
  #32 = Utf8               scala/collection/IterableOnce
  #33 = Class              #32            // scala/collection/IterableOnce
  #34 = NameAndType        #14:#15        // hash:(Lscala/collection/IterableOnce;)I
  #35 = Methodref          #2.#34         // scala/util/hashing/MurmurHash3$$anon$2.hash:(Lscala/collection/IterableOnce;)I
  #36 = Utf8               Ljava/lang/Object;
  #37 = Utf8               <init>
  #38 = Utf8               ()V
  #39 = NameAndType        #37:#38        // "<init>":()V
  #40 = Methodref          #5.#39         // java/lang/Object."<init>":()V
  #41 = Utf8               Code
  #42 = Utf8               LineNumberTable
  #43 = Utf8               LocalVariableTable
  #44 = Utf8               Signature
  #45 = Utf8               MethodParameters
  #46 = Utf8               InnerClasses
  #47 = Utf8               EnclosingMethod
  #48 = Utf8               SourceFile
  #49 = Utf8               ScalaInlineInfo
  #50 = Utf8               Scala
{
  public int hash(scala.collection.IterableOnce<java.lang.Object>);
    descriptor: (Lscala/collection/IterableOnce;)I
    flags: (0x0001) ACC_PUBLIC
    Code:
      stack=3, locals=2, args_size=2
         0: getstatic     #21                 // Field scala/util/hashing/MurmurHash3$.MODULE$:Lscala/util/hashing/MurmurHash3$;
         3: aload_1
         4: ldc           #22                 // int -1248659538
         6: invokevirtual #26                 // Method scala/util/hashing/MurmurHash3$.orderedHash:(Lscala/collection/IterableOnce;I)I
         9: ireturn
      LineNumberTable:
        line 397: 0
        line 342: 3
        line 397: 9
      LocalVariableTable:
        Start  Length  Slot  Name   Signature
            0      10     0  this   Lscala/util/hashing/MurmurHash3$$anon$2;
            0      10     1    xs   Lscala/collection/IterableOnce;
    Signature: #16                          // (Lscala/collection/IterableOnce<Ljava/lang/Object;>;)I
    MethodParameters:
      Name                           Flags
      xs                             final

  public int hash(java.lang.Object);
    descriptor: (Ljava/lang/Object;)I
    flags: (0x1041) ACC_PUBLIC, ACC_BRIDGE, ACC_SYNTHETIC
    Code:
      stack=2, locals=2, args_size=2
         0: aload_0
         1: aload_1
         2: checkcast     #33                 // class scala/collection/IterableOnce
         5: invokevirtual #35                 // Method hash:(Lscala/collection/IterableOnce;)I
         8: ireturn
      LineNumberTable:
        line 396: 0
      LocalVariableTable:
        Start  Length  Slot  Name   Signature
            0       9     0  this   Lscala/util/hashing/MurmurHash3$$anon$2;
            0       9     1     x   Ljava/lang/Object;
    MethodParameters:
      Name                           Flags
      x                              final

  public scala.util.hashing.MurmurHash3$$anon$2();
    descriptor: ()V
    flags: (0x0001) ACC_PUBLIC
    Code:
      stack=1, locals=1, args_size=1
         0: aload_0
         1: invokespecial #40                 // Method java/lang/Object."<init>":()V
         4: return
      LineNumberTable:
        line 396: 0
      LocalVariableTable:
        Start  Length  Slot  Name   Signature
            0       5     0  this   Lscala/util/hashing/MurmurHash3$$anon$2;
}
InnerClasses:
  public final #2;                        // class scala/util/hashing/MurmurHash3$$anon$2
EnclosingMethod: #10.#13                // scala.util.hashing.MurmurHash3$.orderedHashing
Signature: #3                           // Ljava/lang/Object;Lscala/util/hashing/Hashing<Lscala/collection/IterableOnce<Ljava/lang/Object;>;>;
SourceFile: "MurmurHash3.scala"
  ScalaInlineInfo: length = 0x13 (unknown attribute)
   01 01 00 03 00 25 00 26 01 00 0E 00 1E 01 00 0E
   00 0F 01
  Scala: length = 0x0 (unknown attribute)

