Classfile /Users/mw/Projects/slang-braindump/.jar/jar8/assemble/slang-braindump/assemble/content/org/scalatest/wordspec/AsyncWordSpecLike$$anon$3.class
  Last modified May 29, 2022; size 4372 bytes
  SHA-256 checksum 23f48fc58050accc63521765553c847eb06a345aaa2e0cc27e41ab3171d67e31
  Compiled from "AsyncWordSpecLike.scala"
public final class org.scalatest.wordspec.AsyncWordSpecLike$$anon$3 implements org.scalatest.AsyncTestSuite$NoArgAsyncTest
  minor version: 0
  major version: 52
  flags: (0x0031) ACC_PUBLIC, ACC_FINAL, ACC_SUPER
  this_class: #2                          // org/scalatest/wordspec/AsyncWordSpecLike$$anon$3
  super_class: #4                         // java/lang/Object
  interfaces: 1, fields: 7, methods: 19, attributes: 5
Constant pool:
    #1 = Utf8               org/scalatest/wordspec/AsyncWordSpecLike$$anon$3
    #2 = Class              #1            // org/scalatest/wordspec/AsyncWordSpecLike$$anon$3
    #3 = Utf8               java/lang/Object
    #4 = Class              #3            // java/lang/Object
    #5 = Utf8               org/scalatest/AsyncTestSuite$NoArgAsyncTest
    #6 = Class              #5            // org/scalatest/AsyncTestSuite$NoArgAsyncTest
    #7 = Utf8               AsyncWordSpecLike.scala
    #8 = Utf8               org/scalatest/wordspec/AsyncWordSpecLike
    #9 = Class              #8            // org/scalatest/wordspec/AsyncWordSpecLike
   #10 = Utf8               invokeWithAsyncFixture$1
   #11 = Utf8               (Lorg/scalatest/AsyncSuperEngine$TestLeaf;Lscala/Function1;Lorg/scalatest/Args;Ljava/lang/String;)Lorg/scalatest/AsyncOutcome;
   #12 = NameAndType        #10:#11       // invokeWithAsyncFixture$1:(Lorg/scalatest/AsyncSuperEngine$TestLeaf;Lscala/Function1;Lorg/scalatest/Args;Ljava/lang/String;)Lorg/scalatest/AsyncOutcome;
   #13 = Utf8               org/scalatest/AsyncSuperEngine$TestLeaf
   #14 = Class              #13           // org/scalatest/AsyncSuperEngine$TestLeaf
   #15 = Utf8               org/scalatest/AsyncSuperEngine
   #16 = Class              #15           // org/scalatest/AsyncSuperEngine
   #17 = Utf8               TestLeaf
   #18 = Utf8               org/scalatest/AsyncTestSuite
   #19 = Class              #18           // org/scalatest/AsyncTestSuite
   #20 = Utf8               NoArgAsyncTest
   #21 = Utf8               name
   #22 = Utf8               Ljava/lang/String;
   #23 = Utf8               configMap
   #24 = Utf8               Lorg/scalatest/ConfigMap;
   #25 = Utf8               scopes
   #26 = Utf8               Lscala/collection/immutable/IndexedSeq;
   #27 = Utf8               Lscala/collection/immutable/IndexedSeq<Ljava/lang/String;>;
   #28 = Utf8               text
   #29 = Utf8               tags
   #30 = Utf8               Lscala/collection/immutable/Set;
   #31 = Utf8               Lscala/collection/immutable/Set<Ljava/lang/String;>;
   #32 = Utf8               pos
   #33 = Utf8               Lscala/Option;
   #34 = Utf8               Lscala/Option<Lorg/scalactic/source/Position;>;
   #35 = Utf8               theTest$1
   #36 = Utf8               Lorg/scalatest/AsyncSuperEngine$TestLeaf;
   #37 = Utf8               apply$mcZ$sp
   #38 = Utf8               ()Z
   #39 = Utf8               scala/Function0
   #40 = Class              #39           // scala/Function0
   #41 = Utf8               apply$mcZ$sp$
   #42 = Utf8               (Lscala/Function0;)Z
   #43 = NameAndType        #41:#42       // apply$mcZ$sp$:(Lscala/Function0;)Z
   #44 = InterfaceMethodref #40.#43       // scala/Function0.apply$mcZ$sp$:(Lscala/Function0;)Z
   #45 = Utf8               this
   #46 = Utf8               Lorg/scalatest/wordspec/AsyncWordSpecLike$$anon$3;
   #47 = Utf8               apply$mcB$sp
   #48 = Utf8               ()B
   #49 = Utf8               apply$mcB$sp$
   #50 = Utf8               (Lscala/Function0;)B
   #51 = NameAndType        #49:#50       // apply$mcB$sp$:(Lscala/Function0;)B
   #52 = InterfaceMethodref #40.#51       // scala/Function0.apply$mcB$sp$:(Lscala/Function0;)B
   #53 = Utf8               apply$mcC$sp
   #54 = Utf8               ()C
   #55 = Utf8               apply$mcC$sp$
   #56 = Utf8               (Lscala/Function0;)C
   #57 = NameAndType        #55:#56       // apply$mcC$sp$:(Lscala/Function0;)C
   #58 = InterfaceMethodref #40.#57       // scala/Function0.apply$mcC$sp$:(Lscala/Function0;)C
   #59 = Utf8               apply$mcD$sp
   #60 = Utf8               ()D
   #61 = Utf8               apply$mcD$sp$
   #62 = Utf8               (Lscala/Function0;)D
   #63 = NameAndType        #61:#62       // apply$mcD$sp$:(Lscala/Function0;)D
   #64 = InterfaceMethodref #40.#63       // scala/Function0.apply$mcD$sp$:(Lscala/Function0;)D
   #65 = Utf8               apply$mcF$sp
   #66 = Utf8               ()F
   #67 = Utf8               apply$mcF$sp$
   #68 = Utf8               (Lscala/Function0;)F
   #69 = NameAndType        #67:#68       // apply$mcF$sp$:(Lscala/Function0;)F
   #70 = InterfaceMethodref #40.#69       // scala/Function0.apply$mcF$sp$:(Lscala/Function0;)F
   #71 = Utf8               apply$mcI$sp
   #72 = Utf8               ()I
   #73 = Utf8               apply$mcI$sp$
   #74 = Utf8               (Lscala/Function0;)I
   #75 = NameAndType        #73:#74       // apply$mcI$sp$:(Lscala/Function0;)I
   #76 = InterfaceMethodref #40.#75       // scala/Function0.apply$mcI$sp$:(Lscala/Function0;)I
   #77 = Utf8               apply$mcJ$sp
   #78 = Utf8               ()J
   #79 = Utf8               apply$mcJ$sp$
   #80 = Utf8               (Lscala/Function0;)J
   #81 = NameAndType        #79:#80       // apply$mcJ$sp$:(Lscala/Function0;)J
   #82 = InterfaceMethodref #40.#81       // scala/Function0.apply$mcJ$sp$:(Lscala/Function0;)J
   #83 = Utf8               apply$mcS$sp
   #84 = Utf8               ()S
   #85 = Utf8               apply$mcS$sp$
   #86 = Utf8               (Lscala/Function0;)S
   #87 = NameAndType        #85:#86       // apply$mcS$sp$:(Lscala/Function0;)S
   #88 = InterfaceMethodref #40.#87       // scala/Function0.apply$mcS$sp$:(Lscala/Function0;)S
   #89 = Utf8               apply$mcV$sp
   #90 = Utf8               ()V
   #91 = Utf8               apply$mcV$sp$
   #92 = Utf8               (Lscala/Function0;)V
   #93 = NameAndType        #91:#92       // apply$mcV$sp$:(Lscala/Function0;)V
   #94 = InterfaceMethodref #40.#93       // scala/Function0.apply$mcV$sp$:(Lscala/Function0;)V
   #95 = Utf8               toString
   #96 = Utf8               ()Ljava/lang/String;
   #97 = Utf8               toString$
   #98 = Utf8               (Lscala/Function0;)Ljava/lang/String;
   #99 = NameAndType        #97:#98       // toString$:(Lscala/Function0;)Ljava/lang/String;
  #100 = InterfaceMethodref #40.#99       // scala/Function0.toString$:(Lscala/Function0;)Ljava/lang/String;
  #101 = NameAndType        #21:#22       // name:Ljava/lang/String;
  #102 = Fieldref           #2.#101       // org/scalatest/wordspec/AsyncWordSpecLike$$anon$3.name:Ljava/lang/String;
  #103 = Utf8               apply
  #104 = Utf8               ()Lorg/scalatest/FutureOutcome;
  #105 = NameAndType        #35:#36       // theTest$1:Lorg/scalatest/AsyncSuperEngine$TestLeaf;
  #106 = Fieldref           #2.#105       // org/scalatest/wordspec/AsyncWordSpecLike$$anon$3.theTest$1:Lorg/scalatest/AsyncSuperEngine$TestLeaf;
  #107 = Utf8               testFun
  #108 = Utf8               ()Ljava/lang/Object;
  #109 = NameAndType        #107:#108     // testFun:()Ljava/lang/Object;
  #110 = Methodref          #14.#109      // org/scalatest/AsyncSuperEngine$TestLeaf.testFun:()Ljava/lang/Object;
  #111 = NameAndType        #103:#108     // apply:()Ljava/lang/Object;
  #112 = InterfaceMethodref #40.#111      // scala/Function0.apply:()Ljava/lang/Object;
  #113 = Utf8               org/scalatest/AsyncTestHolder
  #114 = Class              #113          // org/scalatest/AsyncTestHolder
  #115 = Utf8               toFutureOutcome
  #116 = NameAndType        #115:#104     // toFutureOutcome:()Lorg/scalatest/FutureOutcome;
  #117 = InterfaceMethodref #114.#116     // org/scalatest/AsyncTestHolder.toFutureOutcome:()Lorg/scalatest/FutureOutcome;
  #118 = Utf8               ()Lorg/scalatest/ConfigMap;
  #119 = NameAndType        #23:#24       // configMap:Lorg/scalatest/ConfigMap;
  #120 = Fieldref           #2.#119       // org/scalatest/wordspec/AsyncWordSpecLike$$anon$3.configMap:Lorg/scalatest/ConfigMap;
  #121 = Utf8               ()Lscala/collection/immutable/IndexedSeq;
  #122 = Utf8               ()Lscala/collection/immutable/IndexedSeq<Ljava/lang/String;>;
  #123 = NameAndType        #25:#26       // scopes:Lscala/collection/immutable/IndexedSeq;
  #124 = Fieldref           #2.#123       // org/scalatest/wordspec/AsyncWordSpecLike$$anon$3.scopes:Lscala/collection/immutable/IndexedSeq;
  #125 = NameAndType        #28:#22       // text:Ljava/lang/String;
  #126 = Fieldref           #2.#125       // org/scalatest/wordspec/AsyncWordSpecLike$$anon$3.text:Ljava/lang/String;
  #127 = Utf8               ()Lscala/collection/immutable/Set;
  #128 = Utf8               ()Lscala/collection/immutable/Set<Ljava/lang/String;>;
  #129 = NameAndType        #29:#30       // tags:Lscala/collection/immutable/Set;
  #130 = Fieldref           #2.#129       // org/scalatest/wordspec/AsyncWordSpecLike$$anon$3.tags:Lscala/collection/immutable/Set;
  #131 = Utf8               ()Lscala/Option;
  #132 = Utf8               ()Lscala/Option<Lorg/scalactic/source/Position;>;
  #133 = NameAndType        #32:#33       // pos:Lscala/Option;
  #134 = Fieldref           #2.#133       // org/scalatest/wordspec/AsyncWordSpecLike$$anon$3.pos:Lscala/Option;
  #135 = NameAndType        #103:#104     // apply:()Lorg/scalatest/FutureOutcome;
  #136 = Methodref          #2.#135       // org/scalatest/wordspec/AsyncWordSpecLike$$anon$3.apply:()Lorg/scalatest/FutureOutcome;
  #137 = Utf8               <init>
  #138 = Utf8               (Lorg/scalatest/wordspec/AsyncWordSpecLike;Lorg/scalatest/TestData;Lorg/scalatest/AsyncSuperEngine$TestLeaf;)V
  #139 = Utf8               $outer
  #140 = Utf8               testData$1
  #141 = NameAndType        #137:#90      // "<init>":()V
  #142 = Methodref          #4.#141       // java/lang/Object."<init>":()V
  #143 = Utf8               $init$
  #144 = NameAndType        #143:#92      // $init$:(Lscala/Function0;)V
  #145 = InterfaceMethodref #40.#144      // scala/Function0.$init$:(Lscala/Function0;)V
  #146 = Utf8               org/scalatest/TestData
  #147 = Class              #146          // org/scalatest/TestData
  #148 = NameAndType        #21:#96       // name:()Ljava/lang/String;
  #149 = InterfaceMethodref #147.#148     // org/scalatest/TestData.name:()Ljava/lang/String;
  #150 = NameAndType        #23:#118      // configMap:()Lorg/scalatest/ConfigMap;
  #151 = InterfaceMethodref #147.#150     // org/scalatest/TestData.configMap:()Lorg/scalatest/ConfigMap;
  #152 = NameAndType        #25:#121      // scopes:()Lscala/collection/immutable/IndexedSeq;
  #153 = InterfaceMethodref #147.#152     // org/scalatest/TestData.scopes:()Lscala/collection/immutable/IndexedSeq;
  #154 = NameAndType        #28:#96       // text:()Ljava/lang/String;
  #155 = InterfaceMethodref #147.#154     // org/scalatest/TestData.text:()Ljava/lang/String;
  #156 = NameAndType        #29:#127      // tags:()Lscala/collection/immutable/Set;
  #157 = InterfaceMethodref #147.#156     // org/scalatest/TestData.tags:()Lscala/collection/immutable/Set;
  #158 = NameAndType        #32:#131      // pos:()Lscala/Option;
  #159 = InterfaceMethodref #147.#158     // org/scalatest/TestData.pos:()Lscala/Option;
  #160 = Utf8               Lorg/scalatest/wordspec/AsyncWordSpecLike;
  #161 = Utf8               Lorg/scalatest/TestData;
  #162 = Utf8               Signature
  #163 = Utf8               Code
  #164 = Utf8               LineNumberTable
  #165 = Utf8               LocalVariableTable
  #166 = Utf8               MethodParameters
  #167 = Utf8               InnerClasses
  #168 = Utf8               EnclosingMethod
  #169 = Utf8               SourceFile
  #170 = Utf8               ScalaInlineInfo
  #171 = Utf8               Scala
{
  private final java.lang.String name;
    descriptor: Ljava/lang/String;
    flags: (0x0012) ACC_PRIVATE, ACC_FINAL

  private final org.scalatest.ConfigMap configMap;
    descriptor: Lorg/scalatest/ConfigMap;
    flags: (0x0012) ACC_PRIVATE, ACC_FINAL

  private final scala.collection.immutable.IndexedSeq<java.lang.String> scopes;
    descriptor: Lscala/collection/immutable/IndexedSeq;
    flags: (0x0012) ACC_PRIVATE, ACC_FINAL
    Signature: #27                          // Lscala/collection/immutable/IndexedSeq<Ljava/lang/String;>;

  private final java.lang.String text;
    descriptor: Ljava/lang/String;
    flags: (0x0012) ACC_PRIVATE, ACC_FINAL

  private final scala.collection.immutable.Set<java.lang.String> tags;
    descriptor: Lscala/collection/immutable/Set;
    flags: (0x0012) ACC_PRIVATE, ACC_FINAL
    Signature: #31                          // Lscala/collection/immutable/Set<Ljava/lang/String;>;

  private final scala.Option<org.scalactic.source.Position> pos;
    descriptor: Lscala/Option;
    flags: (0x0012) ACC_PRIVATE, ACC_FINAL
    Signature: #34                          // Lscala/Option<Lorg/scalactic/source/Position;>;

  private final org.scalatest.AsyncSuperEngine$TestLeaf theTest$1;
    descriptor: Lorg/scalatest/AsyncSuperEngine$TestLeaf;
    flags: (0x0012) ACC_PRIVATE, ACC_FINAL
    Signature: #36                          // Lorg/scalatest/AsyncSuperEngine$TestLeaf;

  public boolean apply$mcZ$sp();
    descriptor: ()Z
    flags: (0x0001) ACC_PUBLIC
    Code:
      stack=1, locals=1, args_size=1
         0: aload_0
         1: invokestatic  #44                 // InterfaceMethod scala/Function0.apply$mcZ$sp$:(Lscala/Function0;)Z
         4: ireturn
      LineNumberTable:
        line 1210: 0
      LocalVariableTable:
        Start  Length  Slot  Name   Signature
            0       5     0  this   Lorg/scalatest/wordspec/AsyncWordSpecLike$$anon$3;

  public byte apply$mcB$sp();
    descriptor: ()B
    flags: (0x0001) ACC_PUBLIC
    Code:
      stack=1, locals=1, args_size=1
         0: aload_0
         1: invokestatic  #52                 // InterfaceMethod scala/Function0.apply$mcB$sp$:(Lscala/Function0;)B
         4: ireturn
      LineNumberTable:
        line 1210: 0
      LocalVariableTable:
        Start  Length  Slot  Name   Signature
            0       5     0  this   Lorg/scalatest/wordspec/AsyncWordSpecLike$$anon$3;

  public char apply$mcC$sp();
    descriptor: ()C
    flags: (0x0001) ACC_PUBLIC
    Code:
      stack=1, locals=1, args_size=1
         0: aload_0
         1: invokestatic  #58                 // InterfaceMethod scala/Function0.apply$mcC$sp$:(Lscala/Function0;)C
         4: ireturn
      LineNumberTable:
        line 1210: 0
      LocalVariableTable:
        Start  Length  Slot  Name   Signature
            0       5     0  this   Lorg/scalatest/wordspec/AsyncWordSpecLike$$anon$3;

  public double apply$mcD$sp();
    descriptor: ()D
    flags: (0x0001) ACC_PUBLIC
    Code:
      stack=2, locals=1, args_size=1
         0: aload_0
         1: invokestatic  #64                 // InterfaceMethod scala/Function0.apply$mcD$sp$:(Lscala/Function0;)D
         4: dreturn
      LineNumberTable:
        line 1210: 0
      LocalVariableTable:
        Start  Length  Slot  Name   Signature
            0       5     0  this   Lorg/scalatest/wordspec/AsyncWordSpecLike$$anon$3;

  public float apply$mcF$sp();
    descriptor: ()F
    flags: (0x0001) ACC_PUBLIC
    Code:
      stack=1, locals=1, args_size=1
         0: aload_0
         1: invokestatic  #70                 // InterfaceMethod scala/Function0.apply$mcF$sp$:(Lscala/Function0;)F
         4: freturn
      LineNumberTable:
        line 1210: 0
      LocalVariableTable:
        Start  Length  Slot  Name   Signature
            0       5     0  this   Lorg/scalatest/wordspec/AsyncWordSpecLike$$anon$3;

  public int apply$mcI$sp();
    descriptor: ()I
    flags: (0x0001) ACC_PUBLIC
    Code:
      stack=1, locals=1, args_size=1
         0: aload_0
         1: invokestatic  #76                 // InterfaceMethod scala/Function0.apply$mcI$sp$:(Lscala/Function0;)I
         4: ireturn
      LineNumberTable:
        line 1210: 0
      LocalVariableTable:
        Start  Length  Slot  Name   Signature
            0       5     0  this   Lorg/scalatest/wordspec/AsyncWordSpecLike$$anon$3;

  public long apply$mcJ$sp();
    descriptor: ()J
    flags: (0x0001) ACC_PUBLIC
    Code:
      stack=2, locals=1, args_size=1
         0: aload_0
         1: invokestatic  #82                 // InterfaceMethod scala/Function0.apply$mcJ$sp$:(Lscala/Function0;)J
         4: lreturn
      LineNumberTable:
        line 1210: 0
      LocalVariableTable:
        Start  Length  Slot  Name   Signature
            0       5     0  this   Lorg/scalatest/wordspec/AsyncWordSpecLike$$anon$3;

  public short apply$mcS$sp();
    descriptor: ()S
    flags: (0x0001) ACC_PUBLIC
    Code:
      stack=1, locals=1, args_size=1
         0: aload_0
         1: invokestatic  #88                 // InterfaceMethod scala/Function0.apply$mcS$sp$:(Lscala/Function0;)S
         4: ireturn
      LineNumberTable:
        line 1210: 0
      LocalVariableTable:
        Start  Length  Slot  Name   Signature
            0       5     0  this   Lorg/scalatest/wordspec/AsyncWordSpecLike$$anon$3;

  public void apply$mcV$sp();
    descriptor: ()V
    flags: (0x0001) ACC_PUBLIC
    Code:
      stack=1, locals=1, args_size=1
         0: aload_0
         1: invokestatic  #94                 // InterfaceMethod scala/Function0.apply$mcV$sp$:(Lscala/Function0;)V
         4: return
      LineNumberTable:
        line 1210: 0
      LocalVariableTable:
        Start  Length  Slot  Name   Signature
            0       5     0  this   Lorg/scalatest/wordspec/AsyncWordSpecLike$$anon$3;

  public java.lang.String toString();
    descriptor: ()Ljava/lang/String;
    flags: (0x0001) ACC_PUBLIC
    Code:
      stack=1, locals=1, args_size=1
         0: aload_0
         1: invokestatic  #100                // InterfaceMethod scala/Function0.toString$:(Lscala/Function0;)Ljava/lang/String;
         4: areturn
      LineNumberTable:
        line 1210: 0
      LocalVariableTable:
        Start  Length  Slot  Name   Signature
            0       5     0  this   Lorg/scalatest/wordspec/AsyncWordSpecLike$$anon$3;

  public java.lang.String name();
    descriptor: ()Ljava/lang/String;
    flags: (0x0001) ACC_PUBLIC
    Code:
      stack=1, locals=1, args_size=1
         0: aload_0
         1: getfield      #102                // Field name:Ljava/lang/String;
         4: areturn
      LineNumberTable:
        line 1211: 0
      LocalVariableTable:
        Start  Length  Slot  Name   Signature
            0       5     0  this   Lorg/scalatest/wordspec/AsyncWordSpecLike$$anon$3;

  public org.scalatest.FutureOutcome apply();
    descriptor: ()Lorg/scalatest/FutureOutcome;
    flags: (0x0001) ACC_PUBLIC
    Code:
      stack=1, locals=1, args_size=1
         0: aload_0
         1: getfield      #106                // Field theTest$1:Lorg/scalatest/AsyncSuperEngine$TestLeaf;
         4: invokevirtual #110                // Method org/scalatest/AsyncSuperEngine$TestLeaf.testFun:()Ljava/lang/Object;
         7: checkcast     #40                 // class scala/Function0
        10: invokeinterface #112,  1          // InterfaceMethod scala/Function0.apply:()Ljava/lang/Object;
        15: checkcast     #114                // class org/scalatest/AsyncTestHolder
        18: invokeinterface #117,  1          // InterfaceMethod org/scalatest/AsyncTestHolder.toFutureOutcome:()Lorg/scalatest/FutureOutcome;
        23: areturn
      LineNumberTable:
        line 1212: 0
      LocalVariableTable:
        Start  Length  Slot  Name   Signature
            0      24     0  this   Lorg/scalatest/wordspec/AsyncWordSpecLike$$anon$3;

  public org.scalatest.ConfigMap configMap();
    descriptor: ()Lorg/scalatest/ConfigMap;
    flags: (0x0001) ACC_PUBLIC
    Code:
      stack=1, locals=1, args_size=1
         0: aload_0
         1: getfield      #120                // Field configMap:Lorg/scalatest/ConfigMap;
         4: areturn
      LineNumberTable:
        line 1213: 0
      LocalVariableTable:
        Start  Length  Slot  Name   Signature
            0       5     0  this   Lorg/scalatest/wordspec/AsyncWordSpecLike$$anon$3;

  public scala.collection.immutable.IndexedSeq<java.lang.String> scopes();
    descriptor: ()Lscala/collection/immutable/IndexedSeq;
    flags: (0x0001) ACC_PUBLIC
    Code:
      stack=1, locals=1, args_size=1
         0: aload_0
         1: getfield      #124                // Field scopes:Lscala/collection/immutable/IndexedSeq;
         4: areturn
      LineNumberTable:
        line 1214: 0
      LocalVariableTable:
        Start  Length  Slot  Name   Signature
            0       5     0  this   Lorg/scalatest/wordspec/AsyncWordSpecLike$$anon$3;
    Signature: #122                         // ()Lscala/collection/immutable/IndexedSeq<Ljava/lang/String;>;

  public java.lang.String text();
    descriptor: ()Ljava/lang/String;
    flags: (0x0001) ACC_PUBLIC
    Code:
      stack=1, locals=1, args_size=1
         0: aload_0
         1: getfield      #126                // Field text:Ljava/lang/String;
         4: areturn
      LineNumberTable:
        line 1215: 0
      LocalVariableTable:
        Start  Length  Slot  Name   Signature
            0       5     0  this   Lorg/scalatest/wordspec/AsyncWordSpecLike$$anon$3;

  public scala.collection.immutable.Set<java.lang.String> tags();
    descriptor: ()Lscala/collection/immutable/Set;
    flags: (0x0001) ACC_PUBLIC
    Code:
      stack=1, locals=1, args_size=1
         0: aload_0
         1: getfield      #130                // Field tags:Lscala/collection/immutable/Set;
         4: areturn
      LineNumberTable:
        line 1216: 0
      LocalVariableTable:
        Start  Length  Slot  Name   Signature
            0       5     0  this   Lorg/scalatest/wordspec/AsyncWordSpecLike$$anon$3;
    Signature: #128                         // ()Lscala/collection/immutable/Set<Ljava/lang/String;>;

  public scala.Option<org.scalactic.source.Position> pos();
    descriptor: ()Lscala/Option;
    flags: (0x0001) ACC_PUBLIC
    Code:
      stack=1, locals=1, args_size=1
         0: aload_0
         1: getfield      #134                // Field pos:Lscala/Option;
         4: areturn
      LineNumberTable:
        line 1217: 0
      LocalVariableTable:
        Start  Length  Slot  Name   Signature
            0       5     0  this   Lorg/scalatest/wordspec/AsyncWordSpecLike$$anon$3;
    Signature: #132                         // ()Lscala/Option<Lorg/scalactic/source/Position;>;

  public java.lang.Object apply();
    descriptor: ()Ljava/lang/Object;
    flags: (0x1041) ACC_PUBLIC, ACC_BRIDGE, ACC_SYNTHETIC
    Code:
      stack=1, locals=1, args_size=1
         0: aload_0
         1: invokevirtual #136                // Method apply:()Lorg/scalatest/FutureOutcome;
         4: areturn
      LineNumberTable:
        line 1210: 0
      LocalVariableTable:
        Start  Length  Slot  Name   Signature
            0       5     0  this   Lorg/scalatest/wordspec/AsyncWordSpecLike$$anon$3;

  public org.scalatest.wordspec.AsyncWordSpecLike$$anon$3(org.scalatest.wordspec.AsyncWordSpecLike, org.scalatest.TestData, org.scalatest.AsyncSuperEngine$TestLeaf);
    descriptor: (Lorg/scalatest/wordspec/AsyncWordSpecLike;Lorg/scalatest/TestData;Lorg/scalatest/AsyncSuperEngine$TestLeaf;)V
    flags: (0x0001) ACC_PUBLIC
    Code:
      stack=2, locals=4, args_size=4
         0: aload_0
         1: aload_3
         2: putfield      #106                // Field theTest$1:Lorg/scalatest/AsyncSuperEngine$TestLeaf;
         5: aload_0
         6: invokespecial #142                // Method java/lang/Object."<init>":()V
         9: aload_0
        10: invokestatic  #145                // InterfaceMethod scala/Function0.$init$:(Lscala/Function0;)V
        13: aload_0
        14: aload_2
        15: invokeinterface #149,  1          // InterfaceMethod org/scalatest/TestData.name:()Ljava/lang/String;
        20: putfield      #102                // Field name:Ljava/lang/String;
        23: aload_0
        24: aload_2
        25: invokeinterface #151,  1          // InterfaceMethod org/scalatest/TestData.configMap:()Lorg/scalatest/ConfigMap;
        30: putfield      #120                // Field configMap:Lorg/scalatest/ConfigMap;
        33: aload_0
        34: aload_2
        35: invokeinterface #153,  1          // InterfaceMethod org/scalatest/TestData.scopes:()Lscala/collection/immutable/IndexedSeq;
        40: putfield      #124                // Field scopes:Lscala/collection/immutable/IndexedSeq;
        43: aload_0
        44: aload_2
        45: invokeinterface #155,  1          // InterfaceMethod org/scalatest/TestData.text:()Ljava/lang/String;
        50: putfield      #126                // Field text:Ljava/lang/String;
        53: aload_0
        54: aload_2
        55: invokeinterface #157,  1          // InterfaceMethod org/scalatest/TestData.tags:()Lscala/collection/immutable/Set;
        60: putfield      #130                // Field tags:Lscala/collection/immutable/Set;
        63: aload_0
        64: aload_2
        65: invokeinterface #159,  1          // InterfaceMethod org/scalatest/TestData.pos:()Lscala/Option;
        70: putfield      #134                // Field pos:Lscala/Option;
        73: return
      LineNumberTable:
        line 1205: 0
        line 1210: 5
        line 1211: 13
        line 1213: 23
        line 1214: 33
        line 1215: 43
        line 1216: 53
        line 1217: 63
        line 1210: 73
      LocalVariableTable:
        Start  Length  Slot  Name   Signature
            0      74     0  this   Lorg/scalatest/wordspec/AsyncWordSpecLike$$anon$3;
            0      74     1 $outer   Lorg/scalatest/wordspec/AsyncWordSpecLike;
            0      74     2 testData$1   Lorg/scalatest/TestData;
            0      74     3 theTest$1   Lorg/scalatest/AsyncSuperEngine$TestLeaf;
    MethodParameters:
      Name                           Flags
      $outer                         final synthetic
      testData$1                     final
      theTest$1                      final
}
InnerClasses:
  public #17= #14 of #16;                 // TestLeaf=class org/scalatest/AsyncSuperEngine$TestLeaf of class org/scalatest/AsyncSuperEngine
  public #20= #6 of #19;                  // NoArgAsyncTest=class org/scalatest/AsyncTestSuite$NoArgAsyncTest of class org/scalatest/AsyncTestSuite
  public final #2;                        // class org/scalatest/wordspec/AsyncWordSpecLike$$anon$3
EnclosingMethod: #9.#12                 // org.scalatest.wordspec.AsyncWordSpecLike.invokeWithAsyncFixture$1
SourceFile: "AsyncWordSpecLike.scala"
  ScalaInlineInfo: length = 0x63 (unknown attribute)
   01 01 00 13 00 89 00 8A 01 00 67 00 6C 01 00 67
   00 68 01 00 2F 00 30 01 00 35 00 36 01 00 3B 00
   3C 01 00 41 00 42 01 00 47 00 48 01 00 4D 00 4E
   01 00 53 00 54 01 00 59 00 5A 01 00 25 00 26 01
   00 17 00 76 01 00 15 00 60 01 00 20 00 83 01 00
   19 00 79 01 00 1D 00 7F 01 00 1C 00 60 01 00 5F
   00 60 01
  Scala: length = 0x0 (unknown attribute)

