Classfile /Users/mw/Projects/slang-braindump/.jar/jar8/assemble/slang-braindump/assemble/content/org/scalatest/wordspec/FixtureAnyWordSpecLike$$anon$1.class
  Last modified May 29, 2022; size 1486 bytes
  SHA-256 checksum beef427a42bb1b7ec0a44a1d0450607e85a92074b0ec2bef12ccba25cb3f6af9
  Compiled from "FixtureAnyWordSpecLike.scala"
public final class org.scalatest.wordspec.FixtureAnyWordSpecLike$$anon$1 extends org.scalatest.verbs.StringVerbBlockRegistration
  minor version: 0
  major version: 52
  flags: (0x0031) ACC_PUBLIC, ACC_FINAL, ACC_SUPER
  this_class: #2                          // org/scalatest/wordspec/FixtureAnyWordSpecLike$$anon$1
  super_class: #4                         // org/scalatest/verbs/StringVerbBlockRegistration
  interfaces: 0, fields: 1, methods: 2, attributes: 5
Constant pool:
   #1 = Utf8               org/scalatest/wordspec/FixtureAnyWordSpecLike$$anon$1
   #2 = Class              #1             // org/scalatest/wordspec/FixtureAnyWordSpecLike$$anon$1
   #3 = Utf8               org/scalatest/verbs/StringVerbBlockRegistration
   #4 = Class              #3             // org/scalatest/verbs/StringVerbBlockRegistration
   #5 = Utf8               FixtureAnyWordSpecLike.scala
   #6 = Utf8               org/scalatest/wordspec/FixtureAnyWordSpecLike
   #7 = Class              #6             // org/scalatest/wordspec/FixtureAnyWordSpecLike
   #8 = Utf8               $outer
   #9 = Utf8               Lorg/scalatest/wordspec/FixtureAnyWordSpecLike;
  #10 = Utf8               apply
  #11 = Utf8               (Ljava/lang/String;Ljava/lang/String;Lorg/scalactic/source/Position;Lscala/Function0;)V
  #12 = Utf8               (Ljava/lang/String;Ljava/lang/String;Lorg/scalactic/source/Position;Lscala/Function0<Lscala/runtime/BoxedUnit;>;)V
  #13 = Utf8               left
  #14 = Utf8               verb
  #15 = Utf8               pos
  #16 = Utf8               f
  #17 = NameAndType        #8:#9          // $outer:Lorg/scalatest/wordspec/FixtureAnyWordSpecLike;
  #18 = Fieldref           #2.#17         // org/scalatest/wordspec/FixtureAnyWordSpecLike$$anon$1.$outer:Lorg/scalatest/wordspec/FixtureAnyWordSpecLike;
  #19 = Utf8               scala/Some
  #20 = Class              #19            // scala/Some
  #21 = Utf8               <init>
  #22 = Utf8               (Ljava/lang/Object;)V
  #23 = NameAndType        #21:#22        // "<init>":(Ljava/lang/Object;)V
  #24 = Methodref          #20.#23        // scala/Some."<init>":(Ljava/lang/Object;)V
  #25 = String             #10            // apply
  #26 = Utf8               org$scalatest$wordspec$FixtureAnyWordSpecLike$$registerBranch
  #27 = Utf8               (Ljava/lang/String;Lscala/Option;Ljava/lang/String;Ljava/lang/String;IILorg/scalactic/source/Position;Lscala/Function0;)V
  #28 = NameAndType        #26:#27        // org$scalatest$wordspec$FixtureAnyWordSpecLike$$registerBranch:(Ljava/lang/String;Lscala/Option;Ljava/lang/String;Ljava/lang/String;IILorg/scalactic/source/Position;Lscala/Function0;)V
  #29 = InterfaceMethodref #7.#28         // org/scalatest/wordspec/FixtureAnyWordSpecLike.org$scalatest$wordspec$FixtureAnyWordSpecLike$$registerBranch:(Ljava/lang/String;Lscala/Option;Ljava/lang/String;Ljava/lang/String;IILorg/scalactic/source/Position;Lscala/Function0;)V
  #30 = Utf8               this
  #31 = Utf8               Lorg/scalatest/wordspec/FixtureAnyWordSpecLike$$anon$1;
  #32 = Utf8               Ljava/lang/String;
  #33 = Utf8               Lorg/scalactic/source/Position;
  #34 = Utf8               Lscala/Function0;
  #35 = Utf8               (Lorg/scalatest/wordspec/FixtureAnyWordSpecLike;)V
  #36 = Utf8               ()V
  #37 = NameAndType        #21:#36        // "<init>":()V
  #38 = Methodref          #4.#37         // org/scalatest/verbs/StringVerbBlockRegistration."<init>":()V
  #39 = Utf8               Code
  #40 = Utf8               LineNumberTable
  #41 = Utf8               LocalVariableTable
  #42 = Utf8               Signature
  #43 = Utf8               MethodParameters
  #44 = Utf8               StackMapTable
  #45 = Utf8               InnerClasses
  #46 = Utf8               EnclosingMethod
  #47 = Utf8               SourceFile
  #48 = Utf8               ScalaInlineInfo
  #49 = Utf8               Scala
{
  private final org.scalatest.wordspec.FixtureAnyWordSpecLike $outer;
    descriptor: Lorg/scalatest/wordspec/FixtureAnyWordSpecLike;
    flags: (0x1012) ACC_PRIVATE, ACC_FINAL, ACC_SYNTHETIC

  public void apply(java.lang.String, java.lang.String, org.scalactic.source.Position, scala.Function0<scala.runtime.BoxedUnit>);
    descriptor: (Ljava/lang/String;Ljava/lang/String;Lorg/scalactic/source/Position;Lscala/Function0;)V
    flags: (0x0001) ACC_PUBLIC
    Code:
      stack=9, locals=5, args_size=5
         0: aload_0
         1: getfield      #18                 // Field $outer:Lorg/scalatest/wordspec/FixtureAnyWordSpecLike;
         4: aload_1
         5: new           #20                 // class scala/Some
         8: dup
         9: aload_2
        10: invokespecial #24                 // Method scala/Some."<init>":(Ljava/lang/Object;)V
        13: aload_2
        14: ldc           #25                 // String apply
        16: bipush        6
        18: bipush        -2
        20: aload_3
        21: aload         4
        23: invokeinterface #29,  9           // InterfaceMethod org/scalatest/wordspec/FixtureAnyWordSpecLike.org$scalatest$wordspec$FixtureAnyWordSpecLike$$registerBranch:(Ljava/lang/String;Lscala/Option;Ljava/lang/String;Ljava/lang/String;IILorg/scalactic/source/Position;Lscala/Function0;)V
        28: return
      LineNumberTable:
        line 1320: 0
      LocalVariableTable:
        Start  Length  Slot  Name   Signature
            0      29     0  this   Lorg/scalatest/wordspec/FixtureAnyWordSpecLike$$anon$1;
            0      29     1  left   Ljava/lang/String;
            0      29     2  verb   Ljava/lang/String;
            0      29     3   pos   Lorg/scalactic/source/Position;
            0      29     4     f   Lscala/Function0;
    Signature: #12                          // (Ljava/lang/String;Ljava/lang/String;Lorg/scalactic/source/Position;Lscala/Function0<Lscala/runtime/BoxedUnit;>;)V
    MethodParameters:
      Name                           Flags
      left                           final
      verb                           final
      pos                            final
      f                              final

  public org.scalatest.wordspec.FixtureAnyWordSpecLike$$anon$1(org.scalatest.wordspec.FixtureAnyWordSpecLike);
    descriptor: (Lorg/scalatest/wordspec/FixtureAnyWordSpecLike;)V
    flags: (0x0001) ACC_PUBLIC
    Code:
      stack=2, locals=2, args_size=2
         0: aload_1
         1: ifnonnull     6
         4: aconst_null
         5: athrow
         6: aload_0
         7: aload_1
         8: putfield      #18                 // Field $outer:Lorg/scalatest/wordspec/FixtureAnyWordSpecLike;
        11: aload_0
        12: invokespecial #38                 // Method org/scalatest/verbs/StringVerbBlockRegistration."<init>":()V
        15: return
      StackMapTable: number_of_entries = 1
        frame_type = 6 /* same */
      LineNumberTable:
        line 1319: 0
      LocalVariableTable:
        Start  Length  Slot  Name   Signature
            0      16     0  this   Lorg/scalatest/wordspec/FixtureAnyWordSpecLike$$anon$1;
            0      16     1 $outer   Lorg/scalatest/wordspec/FixtureAnyWordSpecLike;
    MethodParameters:
      Name                           Flags
      $outer                         final synthetic
}
InnerClasses:
  public final #2;                        // class org/scalatest/wordspec/FixtureAnyWordSpecLike$$anon$1
EnclosingMethod: #7.#0                  // org.scalatest.wordspec.FixtureAnyWordSpecLike
SourceFile: "FixtureAnyWordSpecLike.scala"
  ScalaInlineInfo: length = 0xE (unknown attribute)
   01 01 00 02 00 15 00 23 01 00 0A 00 0B 01
  Scala: length = 0x0 (unknown attribute)

