Classfile /Users/mw/Projects/slang-braindump/.jar/jar8/assemble/slang-braindump/assemble/content/coursier/cache/loggers/RefreshInfo$DownloadInfo$.class
  Last modified May 29, 2022; size 1362 bytes
  SHA-256 checksum 233c35a9892c89e9e55f6f47fe7a5ee3195b034a926a1b218bf3428180c3f424
  Compiled from "RefreshInfo.scala"
public class coursier.cache.loggers.RefreshInfo$DownloadInfo$ implements java.io.Serializable
  minor version: 0
  major version: 52
  flags: (0x0021) ACC_PUBLIC, ACC_SUPER
  this_class: #2                          // coursier/cache/loggers/RefreshInfo$DownloadInfo$
  super_class: #4                         // java/lang/Object
  interfaces: 1, fields: 1, methods: 4, attributes: 4
Constant pool:
   #1 = Utf8               coursier/cache/loggers/RefreshInfo$DownloadInfo$
   #2 = Class              #1             // coursier/cache/loggers/RefreshInfo$DownloadInfo$
   #3 = Utf8               java/lang/Object
   #4 = Class              #3             // java/lang/Object
   #5 = Utf8               java/io/Serializable
   #6 = Class              #5             // java/io/Serializable
   #7 = Utf8               RefreshInfo.scala
   #8 = Utf8               coursier/cache/loggers/RefreshInfo$DownloadInfo
   #9 = Class              #8             // coursier/cache/loggers/RefreshInfo$DownloadInfo
  #10 = Utf8               coursier/cache/loggers/RefreshInfo
  #11 = Class              #10            // coursier/cache/loggers/RefreshInfo
  #12 = Utf8               DownloadInfo
  #13 = Utf8
  #14 = Utf8               MODULE$
  #15 = Utf8               Lcoursier/cache/loggers/RefreshInfo$DownloadInfo$;
  #16 = Utf8               <clinit>
  #17 = Utf8               ()V
  #18 = Utf8               <init>
  #19 = NameAndType        #18:#17        // "<init>":()V
  #20 = Methodref          #2.#19         // coursier/cache/loggers/RefreshInfo$DownloadInfo$."<init>":()V
  #21 = NameAndType        #14:#15        // MODULE$:Lcoursier/cache/loggers/RefreshInfo$DownloadInfo$;
  #22 = Fieldref           #2.#21         // coursier/cache/loggers/RefreshInfo$DownloadInfo$.MODULE$:Lcoursier/cache/loggers/RefreshInfo$DownloadInfo$;
  #23 = Utf8               apply
  #24 = Utf8               (JJLscala/Option;JZZ)Lcoursier/cache/loggers/RefreshInfo$DownloadInfo;
  #25 = Utf8               (JJLscala/Option<Ljava/lang/Object;>;JZZ)Lcoursier/cache/loggers/RefreshInfo$DownloadInfo;
  #26 = Utf8               downloaded
  #27 = Utf8               previouslyDownloaded
  #28 = Utf8               length
  #29 = Utf8               startTime
  #30 = Utf8               updateCheck
  #31 = Utf8               watching
  #32 = Utf8               (JJLscala/Option;JZZ)V
  #33 = NameAndType        #18:#32        // "<init>":(JJLscala/Option;JZZ)V
  #34 = Methodref          #9.#33         // coursier/cache/loggers/RefreshInfo$DownloadInfo."<init>":(JJLscala/Option;JZZ)V
  #35 = Utf8               this
  #36 = Utf8               J
  #37 = Utf8               Lscala/Option;
  #38 = Utf8               Z
  #39 = Utf8               writeReplace
  #40 = Utf8               ()Ljava/lang/Object;
  #41 = Utf8               scala/runtime/ModuleSerializationProxy
  #42 = Class              #41            // scala/runtime/ModuleSerializationProxy
  #43 = Utf8               (Ljava/lang/Class;)V
  #44 = NameAndType        #18:#43        // "<init>":(Ljava/lang/Class;)V
  #45 = Methodref          #42.#44        // scala/runtime/ModuleSerializationProxy."<init>":(Ljava/lang/Class;)V
  #46 = Methodref          #4.#19         // java/lang/Object."<init>":()V
  #47 = Utf8               Code
  #48 = Utf8               LineNumberTable
  #49 = Utf8               LocalVariableTable
  #50 = Utf8               Signature
  #51 = Utf8               MethodParameters
  #52 = Utf8               InnerClasses
  #53 = Utf8               SourceFile
  #54 = Utf8               ScalaInlineInfo
  #55 = Utf8               Scala
{
  public static final coursier.cache.loggers.RefreshInfo$DownloadInfo$ MODULE$;
    descriptor: Lcoursier/cache/loggers/RefreshInfo$DownloadInfo$;
    flags: (0x0019) ACC_PUBLIC, ACC_STATIC, ACC_FINAL

  public static {};
    descriptor: ()V
    flags: (0x0009) ACC_PUBLIC, ACC_STATIC
    Code:
      stack=2, locals=0, args_size=0
         0: new           #2                  // class coursier/cache/loggers/RefreshInfo$DownloadInfo$
         3: dup
         4: invokespecial #20                 // Method "<init>":()V
         7: putstatic     #22                 // Field MODULE$:Lcoursier/cache/loggers/RefreshInfo$DownloadInfo$;
        10: return
      LineNumberTable:
        line 12: 0

  public coursier.cache.loggers.RefreshInfo$DownloadInfo apply(long, long, scala.Option<java.lang.Object>, long, boolean, boolean);
    descriptor: (JJLscala/Option;JZZ)Lcoursier/cache/loggers/RefreshInfo$DownloadInfo;
    flags: (0x0001) ACC_PUBLIC
    Code:
      stack=11, locals=10, args_size=7
         0: new           #9                  // class coursier/cache/loggers/RefreshInfo$DownloadInfo
         3: dup
         4: lload_1
         5: lload_3
         6: aload         5
         8: lload         6
        10: iload         8
        12: iload         9
        14: invokespecial #34                 // Method coursier/cache/loggers/RefreshInfo$DownloadInfo."<init>":(JJLscala/Option;JZZ)V
        17: areturn
      LineNumberTable:
        line 12: 0
      LocalVariableTable:
        Start  Length  Slot  Name   Signature
            0      18     0  this   Lcoursier/cache/loggers/RefreshInfo$DownloadInfo$;
            0      18     1 downloaded   J
            0      18     3 previouslyDownloaded   J
            0      18     5 length   Lscala/Option;
            0      18     6 startTime   J
            0      18     8 updateCheck   Z
            0      18     9 watching   Z
    Signature: #25                          // (JJLscala/Option<Ljava/lang/Object;>;JZZ)Lcoursier/cache/loggers/RefreshInfo$DownloadInfo;
    MethodParameters:
      Name                           Flags
      downloaded                     final
      previouslyDownloaded           final
      length                         final
      startTime                      final
      updateCheck                    final
      watching                       final

  private java.lang.Object writeReplace();
    descriptor: ()Ljava/lang/Object;
    flags: (0x0002) ACC_PRIVATE
    Code:
      stack=3, locals=1, args_size=1
         0: new           #42                 // class scala/runtime/ModuleSerializationProxy
         3: dup
         4: ldc           #2                  // class coursier/cache/loggers/RefreshInfo$DownloadInfo$
         6: invokespecial #45                 // Method scala/runtime/ModuleSerializationProxy."<init>":(Ljava/lang/Class;)V
         9: areturn
      LineNumberTable:
        line 12: 0
      LocalVariableTable:
        Start  Length  Slot  Name   Signature
            0      10     0  this   Lcoursier/cache/loggers/RefreshInfo$DownloadInfo$;

  public coursier.cache.loggers.RefreshInfo$DownloadInfo$();
    descriptor: ()V
    flags: (0x0001) ACC_PUBLIC
    Code:
      stack=1, locals=1, args_size=1
         0: aload_0
         1: invokespecial #46                 // Method java/lang/Object."<init>":()V
         4: return
      LineNumberTable:
        line 12: 0
      LocalVariableTable:
        Start  Length  Slot  Name   Signature
            0       5     0  this   Lcoursier/cache/loggers/RefreshInfo$DownloadInfo$;
}
InnerClasses:
  public static final #12= #9 of #11;     // DownloadInfo=class coursier/cache/loggers/RefreshInfo$DownloadInfo of class coursier/cache/loggers/RefreshInfo
  public static #13= #2 of #11;           // =class coursier/cache/loggers/RefreshInfo$DownloadInfo$ of class coursier/cache/loggers/RefreshInfo
SourceFile: "RefreshInfo.scala"
  ScalaInlineInfo: length = 0x13 (unknown attribute)
   01 01 00 03 00 12 00 11 01 00 17 00 18 01 00 27
   00 28 01
  Scala: length = 0x0 (unknown attribute)

