Classfile /Users/mw/Projects/slang-braindump/.jar/jar8/assemble/slang-braindump/assemble/content/coursier/cache/ArtifactError$Locked.class
  Last modified May 29, 2022; size 796 bytes
  SHA-256 checksum 49f40c6cc2657d05a44768bd21687ea63c8bb33af2fbb152fb02769f65c071d9
  Compiled from "ArtifactError.scala"
public final class coursier.cache.ArtifactError$Locked extends coursier.cache.ArtifactError$Recoverable
  minor version: 0
  major version: 52
  flags: (0x0031) ACC_PUBLIC, ACC_FINAL, ACC_SUPER
  this_class: #2                          // coursier/cache/ArtifactError$Locked
  super_class: #4                         // coursier/cache/ArtifactError$Recoverable
  interfaces: 0, fields: 1, methods: 2, attributes: 4
Constant pool:
   #1 = Utf8               coursier/cache/ArtifactError$Locked
   #2 = Class              #1             // coursier/cache/ArtifactError$Locked
   #3 = Utf8               coursier/cache/ArtifactError$Recoverable
   #4 = Class              #3             // coursier/cache/ArtifactError$Recoverable
   #5 = Utf8               ArtifactError.scala
   #6 = Utf8               coursier/cache/ArtifactError
   #7 = Class              #6             // coursier/cache/ArtifactError
   #8 = Utf8               Locked
   #9 = Utf8               Recoverable
  #10 = Utf8               file
  #11 = Utf8               Ljava/io/File;
  #12 = Utf8               ()Ljava/io/File;
  #13 = NameAndType        #10:#11        // file:Ljava/io/File;
  #14 = Fieldref           #2.#13         // coursier/cache/ArtifactError$Locked.file:Ljava/io/File;
  #15 = Utf8               this
  #16 = Utf8               Lcoursier/cache/ArtifactError$Locked;
  #17 = Utf8               <init>
  #18 = Utf8               (Ljava/io/File;)V
  #19 = Utf8               locked
  #20 = String             #19            // locked
  #21 = Utf8               java/io/File
  #22 = Class              #21            // java/io/File
  #23 = Utf8               toString
  #24 = Utf8               ()Ljava/lang/String;
  #25 = NameAndType        #23:#24        // toString:()Ljava/lang/String;
  #26 = Methodref          #22.#25        // java/io/File.toString:()Ljava/lang/String;
  #27 = Utf8               (Ljava/lang/String;Ljava/lang/String;)V
  #28 = NameAndType        #17:#27        // "<init>":(Ljava/lang/String;Ljava/lang/String;)V
  #29 = Methodref          #4.#28         // coursier/cache/ArtifactError$Recoverable."<init>":(Ljava/lang/String;Ljava/lang/String;)V
  #30 = Utf8               Code
  #31 = Utf8               LineNumberTable
  #32 = Utf8               LocalVariableTable
  #33 = Utf8               MethodParameters
  #34 = Utf8               InnerClasses
  #35 = Utf8               SourceFile
  #36 = Utf8               ScalaInlineInfo
  #37 = Utf8               Scala
{
  private final java.io.File file;
    descriptor: Ljava/io/File;
    flags: (0x0012) ACC_PRIVATE, ACC_FINAL

  public java.io.File file();
    descriptor: ()Ljava/io/File;
    flags: (0x0001) ACC_PUBLIC
    Code:
      stack=1, locals=1, args_size=1
         0: aload_0
         1: getfield      #14                 // Field file:Ljava/io/File;
         4: areturn
      LineNumberTable:
        line 121: 0
      LocalVariableTable:
        Start  Length  Slot  Name   Signature
            0       5     0  this   Lcoursier/cache/ArtifactError$Locked;

  public coursier.cache.ArtifactError$Locked(java.io.File);
    descriptor: (Ljava/io/File;)V
    flags: (0x0001) ACC_PUBLIC
    Code:
      stack=3, locals=2, args_size=2
         0: aload_0
         1: aload_1
         2: putfield      #14                 // Field file:Ljava/io/File;
         5: aload_0
         6: ldc           #20                 // String locked
         8: aload_1
         9: invokevirtual #26                 // Method java/io/File.toString:()Ljava/lang/String;
        12: invokespecial #29                 // Method coursier/cache/ArtifactError$Recoverable."<init>":(Ljava/lang/String;Ljava/lang/String;)V
        15: return
      LineNumberTable:
        line 121: 0
        line 122: 6
        line 123: 8
        line 121: 15
      LocalVariableTable:
        Start  Length  Slot  Name   Signature
            0      16     0  this   Lcoursier/cache/ArtifactError$Locked;
            0      16     1  file   Ljava/io/File;
    MethodParameters:
      Name                           Flags
      file                           final
}
InnerClasses:
  public static final #8= #2 of #7;       // Locked=class coursier/cache/ArtifactError$Locked of class coursier/cache/ArtifactError
  public static abstract #9= #4 of #7;    // Recoverable=class coursier/cache/ArtifactError$Recoverable of class coursier/cache/ArtifactError
SourceFile: "ArtifactError.scala"
  ScalaInlineInfo: length = 0xE (unknown attribute)
   01 01 00 02 00 11 00 12 01 00 0A 00 0C 01
  Scala: length = 0x0 (unknown attribute)

