Classfile /Users/mw/Projects/slang-braindump/.jar/jar8/assemble/slang-braindump/assemble/content/coursier/cache/CacheLogger$Using.class
  Last modified May 29, 2022; size 4255 bytes
  SHA-256 checksum 86c0dfbf6e066efe211e76b7f357110bfe97432d39c3db4b292cf1d4b728bd64
  Compiled from "CacheLogger.scala"
public final class coursier.cache.CacheLogger$Using<T extends java.lang.Object> extends java.lang.Object
  minor version: 0
  major version: 52
  flags: (0x0031) ACC_PUBLIC, ACC_FINAL, ACC_SUPER
  this_class: #2                          // coursier/cache/CacheLogger$Using
  super_class: #5                         // java/lang/Object
  interfaces: 0, fields: 1, methods: 9, attributes: 6
Constant pool:
    #1 = Utf8               coursier/cache/CacheLogger$Using
    #2 = Class              #1            // coursier/cache/CacheLogger$Using
    #3 = Utf8               <T:Ljava/lang/Object;>Ljava/lang/Object;
    #4 = Utf8               java/lang/Object
    #5 = Class              #4            // java/lang/Object
    #6 = Utf8               CacheLogger.scala
    #7 = Utf8               coursier/cache/CacheLogger
    #8 = Class              #7            // coursier/cache/CacheLogger
    #9 = Utf8               Using
   #10 = Utf8               coursier/util/Monad$AllOps
   #11 = Class              #10           // coursier/util/Monad$AllOps
   #12 = Utf8               coursier/util/Monad
   #13 = Class              #12           // coursier/util/Monad
   #14 = Utf8               AllOps
   #15 = Utf8               coursier/util/Monad$ops$
   #16 = Class              #15           // coursier/util/Monad$ops$
   #17 = Utf8
   #18 = Utf8               java/lang/invoke/MethodHandles$Lookup
   #19 = Class              #18           // java/lang/invoke/MethodHandles$Lookup
   #20 = Utf8               java/lang/invoke/MethodHandles
   #21 = Class              #20           // java/lang/invoke/MethodHandles
   #22 = Utf8               Lookup
   #23 = Utf8               logger
   #24 = Utf8               Lcoursier/cache/CacheLogger;
   #25 = Utf8               apply
   #26 = Utf8               (Ljava/lang/Object;Lcoursier/util/Sync;)Ljava/lang/Object;
   #27 = Utf8               <F:Ljava/lang/Object;>(TF;Lcoursier/util/Sync<TF;>;)TF;
   #28 = Utf8               task
   #29 = Utf8               sync
   #30 = Utf8               MODULE$
   #31 = Utf8               Lcoursier/util/Monad$ops$;
   #32 = NameAndType        #30:#31       // MODULE$:Lcoursier/util/Monad$ops$;
   #33 = Fieldref           #16.#32       // coursier/util/Monad$ops$.MODULE$:Lcoursier/util/Monad$ops$;
   #34 = Utf8               ()V
   #35 = MethodType         #34           //  ()V
   #36 = Utf8               $anonfun$apply$1
   #37 = Utf8               (Lcoursier/cache/CacheLogger$Using;)V
   #38 = NameAndType        #36:#37       // $anonfun$apply$1:(Lcoursier/cache/CacheLogger$Using;)V
   #39 = Methodref          #2.#38        // coursier/cache/CacheLogger$Using.$anonfun$apply$1:(Lcoursier/cache/CacheLogger$Using;)V
   #40 = MethodHandle       6:#39         // REF_invokeStatic coursier/cache/CacheLogger$Using.$anonfun$apply$1:(Lcoursier/cache/CacheLogger$Using;)V
   #41 = Integer            1
   #42 = Utf8               java/lang/invoke/LambdaMetafactory
   #43 = Class              #42           // java/lang/invoke/LambdaMetafactory
   #44 = Utf8               altMetafactory
   #45 = Utf8               (Ljava/lang/invoke/MethodHandles$Lookup;Ljava/lang/String;Ljava/lang/invoke/MethodType;[Ljava/lang/Object;)Ljava/lang/invoke/CallSite;
   #46 = NameAndType        #44:#45       // altMetafactory:(Ljava/lang/invoke/MethodHandles$Lookup;Ljava/lang/String;Ljava/lang/invoke/MethodType;[Ljava/lang/Object;)Ljava/lang/invoke/CallSite;
   #47 = Methodref          #43.#46       // java/lang/invoke/LambdaMetafactory.altMetafactory:(Ljava/lang/invoke/MethodHandles$Lookup;Ljava/lang/String;Ljava/lang/invoke/MethodType;[Ljava/lang/Object;)Ljava/lang/invoke/CallSite;
   #48 = MethodHandle       6:#47         // REF_invokeStatic java/lang/invoke/LambdaMetafactory.altMetafactory:(Ljava/lang/invoke/MethodHandles$Lookup;Ljava/lang/String;Ljava/lang/invoke/MethodType;[Ljava/lang/Object;)Ljava/lang/invoke/CallSite;
   #49 = Utf8               apply$mcV$sp
   #50 = Utf8               (Lcoursier/cache/CacheLogger$Using;)Lscala/runtime/java8/JFunction0$mcV$sp;
   #51 = NameAndType        #49:#50       // apply$mcV$sp:(Lcoursier/cache/CacheLogger$Using;)Lscala/runtime/java8/JFunction0$mcV$sp;
   #52 = InvokeDynamic      #0:#51        // #0:apply$mcV$sp:(Lcoursier/cache/CacheLogger$Using;)Lscala/runtime/java8/JFunction0$mcV$sp;
   #53 = Utf8               coursier/util/Sync
   #54 = Class              #53           // coursier/util/Sync
   #55 = Utf8               delay
   #56 = Utf8               (Lscala/Function0;)Ljava/lang/Object;
   #57 = NameAndType        #55:#56       // delay:(Lscala/Function0;)Ljava/lang/Object;
   #58 = InterfaceMethodref #54.#57       // coursier/util/Sync.delay:(Lscala/Function0;)Ljava/lang/Object;
   #59 = Utf8               toAllMonadOps
   #60 = Utf8               (Ljava/lang/Object;Lcoursier/util/Monad;)Lcoursier/util/Monad$AllOps;
   #61 = NameAndType        #59:#60       // toAllMonadOps:(Ljava/lang/Object;Lcoursier/util/Monad;)Lcoursier/util/Monad$AllOps;
   #62 = Methodref          #16.#61       // coursier/util/Monad$ops$.toAllMonadOps:(Ljava/lang/Object;Lcoursier/util/Monad;)Lcoursier/util/Monad$AllOps;
   #63 = Utf8               (Ljava/lang/Object;)Ljava/lang/Object;
   #64 = MethodType         #63           //  (Ljava/lang/Object;)Ljava/lang/Object;
   #65 = Utf8               $anonfun$apply$2
   #66 = Utf8               (Lcoursier/cache/CacheLogger$Using;Lcoursier/util/Sync;Ljava/lang/Object;Lscala/runtime/BoxedUnit;)Ljava/lang/Object;
   #67 = NameAndType        #65:#66       // $anonfun$apply$2:(Lcoursier/cache/CacheLogger$Using;Lcoursier/util/Sync;Ljava/lang/Object;Lscala/runtime/BoxedUnit;)Ljava/lang/Object;
   #68 = Methodref          #2.#67        // coursier/cache/CacheLogger$Using.$anonfun$apply$2:(Lcoursier/cache/CacheLogger$Using;Lcoursier/util/Sync;Ljava/lang/Object;Lscala/runtime/BoxedUnit;)Ljava/lang/Object;
   #69 = MethodHandle       6:#68         // REF_invokeStatic coursier/cache/CacheLogger$Using.$anonfun$apply$2:(Lcoursier/cache/CacheLogger$Using;Lcoursier/util/Sync;Ljava/lang/Object;Lscala/runtime/BoxedUnit;)Ljava/lang/Object;
   #70 = Utf8               (Lscala/runtime/BoxedUnit;)Ljava/lang/Object;
   #71 = MethodType         #70           //  (Lscala/runtime/BoxedUnit;)Ljava/lang/Object;
   #72 = Integer            5
   #73 = Utf8               (Lcoursier/cache/CacheLogger$Using;Lcoursier/util/Sync;Ljava/lang/Object;)Lscala/Function1;
   #74 = NameAndType        #25:#73       // apply:(Lcoursier/cache/CacheLogger$Using;Lcoursier/util/Sync;Ljava/lang/Object;)Lscala/Function1;
   #75 = InvokeDynamic      #1:#74        // #1:apply:(Lcoursier/cache/CacheLogger$Using;Lcoursier/util/Sync;Ljava/lang/Object;)Lscala/Function1;
   #76 = Utf8               flatMap
   #77 = Utf8               (Lscala/Function1;)Ljava/lang/Object;
   #78 = NameAndType        #76:#77       // flatMap:(Lscala/Function1;)Ljava/lang/Object;
   #79 = InterfaceMethodref #11.#78       // coursier/util/Monad$AllOps.flatMap:(Lscala/Function1;)Ljava/lang/Object;
   #80 = Utf8               this
   #81 = Utf8               Lcoursier/cache/CacheLogger$Using;
   #82 = Utf8               Ljava/lang/Object;
   #83 = Utf8               Lcoursier/util/Sync;
   #84 = Utf8               $this
   #85 = NameAndType        #23:#24       // logger:Lcoursier/cache/CacheLogger;
   #86 = Fieldref           #2.#85        // coursier/cache/CacheLogger$Using.logger:Lcoursier/cache/CacheLogger;
   #87 = Utf8               init$default$1
   #88 = Utf8               ()Lscala/Option;
   #89 = NameAndType        #87:#88       // init$default$1:()Lscala/Option;
   #90 = InterfaceMethodref #8.#89        // coursier/cache/CacheLogger.init$default$1:()Lscala/Option;
   #91 = Utf8               init
   #92 = Utf8               (Lscala/Option;)V
   #93 = NameAndType        #91:#92       // init:(Lscala/Option;)V
   #94 = InterfaceMethodref #8.#93        // coursier/cache/CacheLogger.init:(Lscala/Option;)V
   #95 = Utf8               $anonfun$apply$4
   #96 = Utf8               stop
   #97 = NameAndType        #96:#34       // stop:()V
   #98 = InterfaceMethodref #8.#97        // coursier/cache/CacheLogger.stop:()V
   #99 = Utf8               $anonfun$apply$6
  #100 = Utf8               t
  #101 = Utf8               $anonfun$apply$5
  #102 = Utf8               (Lcoursier/util/Sync;Lscala/util/Either;Lscala/runtime/BoxedUnit;)Ljava/lang/Object;
  #103 = Utf8               sync$1
  #104 = Utf8               a$1
  #105 = Utf8               x$1
  #106 = Utf8               fromAttempt
  #107 = Utf8               (Lscala/util/Either;)Ljava/lang/Object;
  #108 = NameAndType        #106:#107     // fromAttempt:(Lscala/util/Either;)Ljava/lang/Object;
  #109 = InterfaceMethodref #54.#108      // coursier/util/Sync.fromAttempt:(Lscala/util/Either;)Ljava/lang/Object;
  #110 = NameAndType        #99:#63       // $anonfun$apply$6:(Ljava/lang/Object;)Ljava/lang/Object;
  #111 = Methodref          #2.#110       // coursier/cache/CacheLogger$Using.$anonfun$apply$6:(Ljava/lang/Object;)Ljava/lang/Object;
  #112 = MethodHandle       6:#111        // REF_invokeStatic coursier/cache/CacheLogger$Using.$anonfun$apply$6:(Ljava/lang/Object;)Ljava/lang/Object;
  #113 = Utf8               ()Lscala/Function1;
  #114 = NameAndType        #25:#113      // apply:()Lscala/Function1;
  #115 = InvokeDynamic      #2:#114       // #2:apply:()Lscala/Function1;
  #116 = Utf8               map
  #117 = NameAndType        #116:#77      // map:(Lscala/Function1;)Ljava/lang/Object;
  #118 = InterfaceMethodref #11.#117      // coursier/util/Monad$AllOps.map:(Lscala/Function1;)Ljava/lang/Object;
  #119 = Utf8               scala/runtime/BoxedUnit
  #120 = Class              #119          // scala/runtime/BoxedUnit
  #121 = Utf8               Lscala/util/Either;
  #122 = Utf8               Lscala/runtime/BoxedUnit;
  #123 = Utf8               $anonfun$apply$3
  #124 = Utf8               (Lcoursier/cache/CacheLogger$Using;Lcoursier/util/Sync;Lscala/util/Either;)Ljava/lang/Object;
  #125 = Utf8               a
  #126 = NameAndType        #95:#37       // $anonfun$apply$4:(Lcoursier/cache/CacheLogger$Using;)V
  #127 = Methodref          #2.#126       // coursier/cache/CacheLogger$Using.$anonfun$apply$4:(Lcoursier/cache/CacheLogger$Using;)V
  #128 = MethodHandle       6:#127        // REF_invokeStatic coursier/cache/CacheLogger$Using.$anonfun$apply$4:(Lcoursier/cache/CacheLogger$Using;)V
  #129 = InvokeDynamic      #3:#51        // #3:apply$mcV$sp:(Lcoursier/cache/CacheLogger$Using;)Lscala/runtime/java8/JFunction0$mcV$sp;
  #130 = NameAndType        #101:#102     // $anonfun$apply$5:(Lcoursier/util/Sync;Lscala/util/Either;Lscala/runtime/BoxedUnit;)Ljava/lang/Object;
  #131 = Methodref          #2.#130       // coursier/cache/CacheLogger$Using.$anonfun$apply$5:(Lcoursier/util/Sync;Lscala/util/Either;Lscala/runtime/BoxedUnit;)Ljava/lang/Object;
  #132 = MethodHandle       6:#131        // REF_invokeStatic coursier/cache/CacheLogger$Using.$anonfun$apply$5:(Lcoursier/util/Sync;Lscala/util/Either;Lscala/runtime/BoxedUnit;)Ljava/lang/Object;
  #133 = Utf8               (Lcoursier/util/Sync;Lscala/util/Either;)Lscala/Function1;
  #134 = NameAndType        #25:#133      // apply:(Lcoursier/util/Sync;Lscala/util/Either;)Lscala/Function1;
  #135 = InvokeDynamic      #4:#134       // #4:apply:(Lcoursier/util/Sync;Lscala/util/Either;)Lscala/Function1;
  #136 = Utf8               task$1
  #137 = Utf8               x$2
  #138 = Utf8               attempt
  #139 = NameAndType        #138:#63      // attempt:(Ljava/lang/Object;)Ljava/lang/Object;
  #140 = InterfaceMethodref #54.#139      // coursier/util/Sync.attempt:(Ljava/lang/Object;)Ljava/lang/Object;
  #141 = NameAndType        #123:#124     // $anonfun$apply$3:(Lcoursier/cache/CacheLogger$Using;Lcoursier/util/Sync;Lscala/util/Either;)Ljava/lang/Object;
  #142 = Methodref          #2.#141       // coursier/cache/CacheLogger$Using.$anonfun$apply$3:(Lcoursier/cache/CacheLogger$Using;Lcoursier/util/Sync;Lscala/util/Either;)Ljava/lang/Object;
  #143 = MethodHandle       6:#142        // REF_invokeStatic coursier/cache/CacheLogger$Using.$anonfun$apply$3:(Lcoursier/cache/CacheLogger$Using;Lcoursier/util/Sync;Lscala/util/Either;)Ljava/lang/Object;
  #144 = MethodType         #107          //  (Lscala/util/Either;)Ljava/lang/Object;
  #145 = Utf8               (Lcoursier/cache/CacheLogger$Using;Lcoursier/util/Sync;)Lscala/Function1;
  #146 = NameAndType        #25:#145      // apply:(Lcoursier/cache/CacheLogger$Using;Lcoursier/util/Sync;)Lscala/Function1;
  #147 = InvokeDynamic      #5:#146       // #5:apply:(Lcoursier/cache/CacheLogger$Using;Lcoursier/util/Sync;)Lscala/Function1;
  #148 = Utf8               <init>
  #149 = Utf8               (Lcoursier/cache/CacheLogger;)V
  #150 = NameAndType        #148:#34      // "<init>":()V
  #151 = Methodref          #5.#150       // java/lang/Object."<init>":()V
  #152 = Utf8               $deserializeLambda$
  #153 = Utf8               (Ljava/lang/invoke/SerializedLambda;)Ljava/lang/Object;
  #154 = Utf8               scala/runtime/LambdaDeserialize
  #155 = Class              #154          // scala/runtime/LambdaDeserialize
  #156 = Utf8               bootstrap
  #157 = Utf8               (Ljava/lang/invoke/MethodHandles$Lookup;Ljava/lang/String;Ljava/lang/invoke/MethodType;[Ljava/lang/invoke/MethodHandle;)Ljava/lang/invoke/CallSite;
  #158 = NameAndType        #156:#157     // bootstrap:(Ljava/lang/invoke/MethodHandles$Lookup;Ljava/lang/String;Ljava/lang/invoke/MethodType;[Ljava/lang/invoke/MethodHandle;)Ljava/lang/invoke/CallSite;
  #159 = Methodref          #155.#158     // scala/runtime/LambdaDeserialize.bootstrap:(Ljava/lang/invoke/MethodHandles$Lookup;Ljava/lang/String;Ljava/lang/invoke/MethodType;[Ljava/lang/invoke/MethodHandle;)Ljava/lang/invoke/CallSite;
  #160 = MethodHandle       6:#159        // REF_invokeStatic scala/runtime/LambdaDeserialize.bootstrap:(Ljava/lang/invoke/MethodHandles$Lookup;Ljava/lang/String;Ljava/lang/invoke/MethodType;[Ljava/lang/invoke/MethodHandle;)Ljava/lang/invoke/CallSite;
  #161 = Utf8               lambdaDeserialize
  #162 = NameAndType        #161:#153     // lambdaDeserialize:(Ljava/lang/invoke/SerializedLambda;)Ljava/lang/Object;
  #163 = InvokeDynamic      #6:#162       // #6:lambdaDeserialize:(Ljava/lang/invoke/SerializedLambda;)Ljava/lang/Object;
  #164 = Utf8               Code
  #165 = Utf8               LineNumberTable
  #166 = Utf8               LocalVariableTable
  #167 = Utf8               Signature
  #168 = Utf8               MethodParameters
  #169 = Utf8               StackMapTable
  #170 = Utf8               InnerClasses
  #171 = Utf8               SourceFile
  #172 = Utf8               BootstrapMethods
  #173 = Utf8               ScalaInlineInfo
  #174 = Utf8               Scala
{
  private final coursier.cache.CacheLogger logger;
    descriptor: Lcoursier/cache/CacheLogger;
    flags: (0x0012) ACC_PRIVATE, ACC_FINAL

  public <F extends java.lang.Object> F apply(F, coursier.util.Sync<F>);
    descriptor: (Ljava/lang/Object;Lcoursier/util/Sync;)Ljava/lang/Object;
    flags: (0x0001) ACC_PUBLIC
    Code:
      stack=4, locals=3, args_size=3
         0: getstatic     #33                 // Field coursier/util/Monad$ops$.MODULE$:Lcoursier/util/Monad$ops$;
         3: aload_2
         4: aload_0
         5: invokedynamic #52,  0             // InvokeDynamic #0:apply$mcV$sp:(Lcoursier/cache/CacheLogger$Using;)Lscala/runtime/java8/JFunction0$mcV$sp;
        10: invokeinterface #58,  2           // InterfaceMethod coursier/util/Sync.delay:(Lscala/Function0;)Ljava/lang/Object;
        15: aload_2
        16: invokevirtual #62                 // Method coursier/util/Monad$ops$.toAllMonadOps:(Ljava/lang/Object;Lcoursier/util/Monad;)Lcoursier/util/Monad$AllOps;
        19: aload_0
        20: aload_2
        21: aload_1
        22: invokedynamic #75,  0             // InvokeDynamic #1:apply:(Lcoursier/cache/CacheLogger$Using;Lcoursier/util/Sync;Ljava/lang/Object;)Lscala/Function1;
        27: invokeinterface #79,  2           // InterfaceMethod coursier/util/Monad$AllOps.flatMap:(Lscala/Function1;)Ljava/lang/Object;
        32: areturn
      LineNumberTable:
        line 52: 0
      LocalVariableTable:
        Start  Length  Slot  Name   Signature
            0      33     0  this   Lcoursier/cache/CacheLogger$Using;
            0      33     1  task   Ljava/lang/Object;
            0      33     2  sync   Lcoursier/util/Sync;
    Signature: #27                          // <F:Ljava/lang/Object;>(TF;Lcoursier/util/Sync<TF;>;)TF;
    MethodParameters:
      Name                           Flags
      task                           final
      sync                           final

  public static final void $anonfun$apply$1(coursier.cache.CacheLogger$Using);
    descriptor: (Lcoursier/cache/CacheLogger$Using;)V
    flags: (0x1019) ACC_PUBLIC, ACC_STATIC, ACC_FINAL, ACC_SYNTHETIC
    Code:
      stack=2, locals=1, args_size=1
         0: aload_0
         1: getfield      #86                 // Field logger:Lcoursier/cache/CacheLogger;
         4: aload_0
         5: getfield      #86                 // Field logger:Lcoursier/cache/CacheLogger;
         8: invokeinterface #90,  1           // InterfaceMethod coursier/cache/CacheLogger.init$default$1:()Lscala/Option;
        13: invokeinterface #94,  2           // InterfaceMethod coursier/cache/CacheLogger.init:(Lscala/Option;)V
        18: return
      LineNumberTable:
        line 52: 0
      LocalVariableTable:
        Start  Length  Slot  Name   Signature
            0      19     0 $this   Lcoursier/cache/CacheLogger$Using;
    MethodParameters:
      Name                           Flags
      $this                          final synthetic

  public static final void $anonfun$apply$4(coursier.cache.CacheLogger$Using);
    descriptor: (Lcoursier/cache/CacheLogger$Using;)V
    flags: (0x1019) ACC_PUBLIC, ACC_STATIC, ACC_FINAL, ACC_SYNTHETIC
    Code:
      stack=1, locals=1, args_size=1
         0: aload_0
         1: getfield      #86                 // Field logger:Lcoursier/cache/CacheLogger;
         4: invokeinterface #98,  1           // InterfaceMethod coursier/cache/CacheLogger.stop:()V
         9: return
      LineNumberTable:
        line 54: 0
      LocalVariableTable:
        Start  Length  Slot  Name   Signature
            0      10     0 $this   Lcoursier/cache/CacheLogger$Using;
    MethodParameters:
      Name                           Flags
      $this                          final synthetic

  public static final java.lang.Object $anonfun$apply$6(java.lang.Object);
    descriptor: (Ljava/lang/Object;)Ljava/lang/Object;
    flags: (0x1019) ACC_PUBLIC, ACC_STATIC, ACC_FINAL, ACC_SYNTHETIC
    Code:
      stack=1, locals=1, args_size=1
         0: aload_0
         1: areturn
      LineNumberTable:
        line 56: 0
      LocalVariableTable:
        Start  Length  Slot  Name   Signature
            0       2     0     t   Ljava/lang/Object;
    MethodParameters:
      Name                           Flags
      t                              final

  public static final java.lang.Object $anonfun$apply$5(coursier.util.Sync, scala.util.Either, scala.runtime.BoxedUnit);
    descriptor: (Lcoursier/util/Sync;Lscala/util/Either;Lscala/runtime/BoxedUnit;)Ljava/lang/Object;
    flags: (0x1019) ACC_PUBLIC, ACC_STATIC, ACC_FINAL, ACC_SYNTHETIC
    Code:
      stack=3, locals=5, args_size=3
         0: aload_2
         1: astore        4
         3: getstatic     #33                 // Field coursier/util/Monad$ops$.MODULE$:Lcoursier/util/Monad$ops$;
         6: aload_0
         7: aload_1
         8: invokeinterface #109,  2          // InterfaceMethod coursier/util/Sync.fromAttempt:(Lscala/util/Either;)Ljava/lang/Object;
        13: aload_0
        14: invokevirtual #62                 // Method coursier/util/Monad$ops$.toAllMonadOps:(Ljava/lang/Object;Lcoursier/util/Monad;)Lcoursier/util/Monad$AllOps;
        17: invokedynamic #115,  0            // InvokeDynamic #2:apply:()Lscala/Function1;
        22: invokeinterface #118,  2          // InterfaceMethod coursier/util/Monad$AllOps.map:(Lscala/Function1;)Ljava/lang/Object;
        27: astore_3
        28: goto          31
        31: aload_3
        32: areturn
      StackMapTable: number_of_entries = 1
        frame_type = 253 /* append */
          offset_delta = 31
          locals = [ class java/lang/Object, class scala/runtime/BoxedUnit ]
      LineNumberTable:
        line 54: 0
        line 55: 3
        line 54: 31
      LocalVariableTable:
        Start  Length  Slot  Name   Signature
            0      33     0 sync$1   Lcoursier/util/Sync;
            0      33     1   a$1   Lscala/util/Either;
            0      33     2   x$1   Lscala/runtime/BoxedUnit;
    MethodParameters:
      Name                           Flags
      sync$1                         final
      a$1                            final
      x$1                            final

  public static final java.lang.Object $anonfun$apply$3(coursier.cache.CacheLogger$Using, coursier.util.Sync, scala.util.Either);
    descriptor: (Lcoursier/cache/CacheLogger$Using;Lcoursier/util/Sync;Lscala/util/Either;)Ljava/lang/Object;
    flags: (0x1019) ACC_PUBLIC, ACC_STATIC, ACC_FINAL, ACC_SYNTHETIC
    Code:
      stack=3, locals=3, args_size=3
         0: getstatic     #33                 // Field coursier/util/Monad$ops$.MODULE$:Lcoursier/util/Monad$ops$;
         3: aload_1
         4: aload_0
         5: invokedynamic #129,  0            // InvokeDynamic #3:apply$mcV$sp:(Lcoursier/cache/CacheLogger$Using;)Lscala/runtime/java8/JFunction0$mcV$sp;
        10: invokeinterface #58,  2           // InterfaceMethod coursier/util/Sync.delay:(Lscala/Function0;)Ljava/lang/Object;
        15: aload_1
        16: invokevirtual #62                 // Method coursier/util/Monad$ops$.toAllMonadOps:(Ljava/lang/Object;Lcoursier/util/Monad;)Lcoursier/util/Monad$AllOps;
        19: aload_1
        20: aload_2
        21: invokedynamic #135,  0            // InvokeDynamic #4:apply:(Lcoursier/util/Sync;Lscala/util/Either;)Lscala/Function1;
        26: invokeinterface #79,  2           // InterfaceMethod coursier/util/Monad$AllOps.flatMap:(Lscala/Function1;)Ljava/lang/Object;
        31: areturn
      LineNumberTable:
        line 54: 0
      LocalVariableTable:
        Start  Length  Slot  Name   Signature
            0      32     0 $this   Lcoursier/cache/CacheLogger$Using;
            0      32     1 sync$1   Lcoursier/util/Sync;
            0      32     2     a   Lscala/util/Either;
    MethodParameters:
      Name                           Flags
      $this                          final synthetic
      sync$1                         final
      a                              final

  public static final java.lang.Object $anonfun$apply$2(coursier.cache.CacheLogger$Using, coursier.util.Sync, java.lang.Object, scala.runtime.BoxedUnit);
    descriptor: (Lcoursier/cache/CacheLogger$Using;Lcoursier/util/Sync;Ljava/lang/Object;Lscala/runtime/BoxedUnit;)Ljava/lang/Object;
    flags: (0x1019) ACC_PUBLIC, ACC_STATIC, ACC_FINAL, ACC_SYNTHETIC
    Code:
      stack=3, locals=6, args_size=4
         0: aload_3
         1: astore        5
         3: getstatic     #33                 // Field coursier/util/Monad$ops$.MODULE$:Lcoursier/util/Monad$ops$;
         6: aload_1
         7: aload_2
         8: invokeinterface #140,  2          // InterfaceMethod coursier/util/Sync.attempt:(Ljava/lang/Object;)Ljava/lang/Object;
        13: aload_1
        14: invokevirtual #62                 // Method coursier/util/Monad$ops$.toAllMonadOps:(Ljava/lang/Object;Lcoursier/util/Monad;)Lcoursier/util/Monad$AllOps;
        17: aload_0
        18: aload_1
        19: invokedynamic #147,  0            // InvokeDynamic #5:apply:(Lcoursier/cache/CacheLogger$Using;Lcoursier/util/Sync;)Lscala/Function1;
        24: invokeinterface #79,  2           // InterfaceMethod coursier/util/Monad$AllOps.flatMap:(Lscala/Function1;)Ljava/lang/Object;
        29: astore        4
        31: goto          34
        34: aload         4
        36: areturn
      StackMapTable: number_of_entries = 1
        frame_type = 253 /* append */
          offset_delta = 34
          locals = [ class java/lang/Object, class scala/runtime/BoxedUnit ]
      LineNumberTable:
        line 52: 0
        line 53: 3
        line 52: 34
      LocalVariableTable:
        Start  Length  Slot  Name   Signature
            0      37     0 $this   Lcoursier/cache/CacheLogger$Using;
            0      37     1 sync$1   Lcoursier/util/Sync;
            0      37     2 task$1   Ljava/lang/Object;
            0      37     3   x$2   Lscala/runtime/BoxedUnit;
    MethodParameters:
      Name                           Flags
      $this                          final synthetic
      sync$1                         final
      task$1                         final
      x$2                            final

  public coursier.cache.CacheLogger$Using(coursier.cache.CacheLogger);
    descriptor: (Lcoursier/cache/CacheLogger;)V
    flags: (0x0001) ACC_PUBLIC
    Code:
      stack=2, locals=2, args_size=2
         0: aload_0
         1: aload_1
         2: putfield      #86                 // Field logger:Lcoursier/cache/CacheLogger;
         5: aload_0
         6: invokespecial #151                // Method java/lang/Object."<init>":()V
         9: return
      LineNumberTable:
        line 49: 0
        line 58: 5
        line 49: 9
      LocalVariableTable:
        Start  Length  Slot  Name   Signature
            0      10     0  this   Lcoursier/cache/CacheLogger$Using;
            0      10     1 logger   Lcoursier/cache/CacheLogger;
    MethodParameters:
      Name                           Flags
      logger                         final

  private static java.lang.Object $deserializeLambda$(java.lang.invoke.SerializedLambda);
    descriptor: (Ljava/lang/invoke/SerializedLambda;)Ljava/lang/Object;
    flags: (0x100a) ACC_PRIVATE, ACC_STATIC, ACC_SYNTHETIC
    Code:
      stack=1, locals=1, args_size=1
         0: aload_0
         1: invokedynamic #163,  0            // InvokeDynamic #6:lambdaDeserialize:(Ljava/lang/invoke/SerializedLambda;)Ljava/lang/Object;
         6: areturn
}
InnerClasses:
  public static final #9= #2 of #8;       // Using=class coursier/cache/CacheLogger$Using of class coursier/cache/CacheLogger
  public static #14= #11 of #13;          // AllOps=class coursier/util/Monad$AllOps of class coursier/util/Monad
  public static #17= #16 of #13;          // =class coursier/util/Monad$ops$ of class coursier/util/Monad
  public static final #22= #19 of #21;    // Lookup=class java/lang/invoke/MethodHandles$Lookup of class java/lang/invoke/MethodHandles
Signature: #3                           // <T:Ljava/lang/Object;>Ljava/lang/Object;
SourceFile: "CacheLogger.scala"
BootstrapMethods:
  0: #48 REF_invokeStatic java/lang/invoke/LambdaMetafactory.altMetafactory:(Ljava/lang/invoke/MethodHandles$Lookup;Ljava/lang/String;Ljava/lang/invoke/MethodType;[Ljava/lang/Object;)Ljava/lang/invoke/CallSite;
    Method arguments:
      #35 ()V
      #40 REF_invokeStatic coursier/cache/CacheLogger$Using.$anonfun$apply$1:(Lcoursier/cache/CacheLogger$Using;)V
      #35 ()V
      #41 1
  1: #48 REF_invokeStatic java/lang/invoke/LambdaMetafactory.altMetafactory:(Ljava/lang/invoke/MethodHandles$Lookup;Ljava/lang/String;Ljava/lang/invoke/MethodType;[Ljava/lang/Object;)Ljava/lang/invoke/CallSite;
    Method arguments:
      #64 (Ljava/lang/Object;)Ljava/lang/Object;
      #69 REF_invokeStatic coursier/cache/CacheLogger$Using.$anonfun$apply$2:(Lcoursier/cache/CacheLogger$Using;Lcoursier/util/Sync;Ljava/lang/Object;Lscala/runtime/BoxedUnit;)Ljava/lang/Object;
      #71 (Lscala/runtime/BoxedUnit;)Ljava/lang/Object;
      #72 5
      #41 1
      #71 (Lscala/runtime/BoxedUnit;)Ljava/lang/Object;
  2: #48 REF_invokeStatic java/lang/invoke/LambdaMetafactory.altMetafactory:(Ljava/lang/invoke/MethodHandles$Lookup;Ljava/lang/String;Ljava/lang/invoke/MethodType;[Ljava/lang/Object;)Ljava/lang/invoke/CallSite;
    Method arguments:
      #64 (Ljava/lang/Object;)Ljava/lang/Object;
      #112 REF_invokeStatic coursier/cache/CacheLogger$Using.$anonfun$apply$6:(Ljava/lang/Object;)Ljava/lang/Object;
      #64 (Ljava/lang/Object;)Ljava/lang/Object;
      #41 1
  3: #48 REF_invokeStatic java/lang/invoke/LambdaMetafactory.altMetafactory:(Ljava/lang/invoke/MethodHandles$Lookup;Ljava/lang/String;Ljava/lang/invoke/MethodType;[Ljava/lang/Object;)Ljava/lang/invoke/CallSite;
    Method arguments:
      #35 ()V
      #128 REF_invokeStatic coursier/cache/CacheLogger$Using.$anonfun$apply$4:(Lcoursier/cache/CacheLogger$Using;)V
      #35 ()V
      #41 1
  4: #48 REF_invokeStatic java/lang/invoke/LambdaMetafactory.altMetafactory:(Ljava/lang/invoke/MethodHandles$Lookup;Ljava/lang/String;Ljava/lang/invoke/MethodType;[Ljava/lang/Object;)Ljava/lang/invoke/CallSite;
    Method arguments:
      #64 (Ljava/lang/Object;)Ljava/lang/Object;
      #132 REF_invokeStatic coursier/cache/CacheLogger$Using.$anonfun$apply$5:(Lcoursier/util/Sync;Lscala/util/Either;Lscala/runtime/BoxedUnit;)Ljava/lang/Object;
      #71 (Lscala/runtime/BoxedUnit;)Ljava/lang/Object;
      #72 5
      #41 1
      #71 (Lscala/runtime/BoxedUnit;)Ljava/lang/Object;
  5: #48 REF_invokeStatic java/lang/invoke/LambdaMetafactory.altMetafactory:(Ljava/lang/invoke/MethodHandles$Lookup;Ljava/lang/String;Ljava/lang/invoke/MethodType;[Ljava/lang/Object;)Ljava/lang/invoke/CallSite;
    Method arguments:
      #64 (Ljava/lang/Object;)Ljava/lang/Object;
      #143 REF_invokeStatic coursier/cache/CacheLogger$Using.$anonfun$apply$3:(Lcoursier/cache/CacheLogger$Using;Lcoursier/util/Sync;Lscala/util/Either;)Ljava/lang/Object;
      #144 (Lscala/util/Either;)Ljava/lang/Object;
      #72 5
      #41 1
      #144 (Lscala/util/Either;)Ljava/lang/Object;
  6: #160 REF_invokeStatic scala/runtime/LambdaDeserialize.bootstrap:(Ljava/lang/invoke/MethodHandles$Lookup;Ljava/lang/String;Ljava/lang/invoke/MethodType;[Ljava/lang/invoke/MethodHandle;)Ljava/lang/invoke/CallSite;
    Method arguments:
      #40 REF_invokeStatic coursier/cache/CacheLogger$Using.$anonfun$apply$1:(Lcoursier/cache/CacheLogger$Using;)V
      #69 REF_invokeStatic coursier/cache/CacheLogger$Using.$anonfun$apply$2:(Lcoursier/cache/CacheLogger$Using;Lcoursier/util/Sync;Ljava/lang/Object;Lscala/runtime/BoxedUnit;)Ljava/lang/Object;
      #143 REF_invokeStatic coursier/cache/CacheLogger$Using.$anonfun$apply$3:(Lcoursier/cache/CacheLogger$Using;Lcoursier/util/Sync;Lscala/util/Either;)Ljava/lang/Object;
      #128 REF_invokeStatic coursier/cache/CacheLogger$Using.$anonfun$apply$4:(Lcoursier/cache/CacheLogger$Using;)V
      #132 REF_invokeStatic coursier/cache/CacheLogger$Using.$anonfun$apply$5:(Lcoursier/util/Sync;Lscala/util/Either;Lscala/runtime/BoxedUnit;)Ljava/lang/Object;
      #112 REF_invokeStatic coursier/cache/CacheLogger$Using.$anonfun$apply$6:(Ljava/lang/Object;)Ljava/lang/Object;
  ScalaInlineInfo: length = 0x2C (unknown attribute)
   01 01 00 08 00 24 00 25 01 00 41 00 42 01 00 7B
   00 7C 01 00 5F 00 25 01 00 65 00 66 01 00 63 00
   3F 01 00 94 00 95 01 00 19 00 1A 01
  Scala: length = 0x0 (unknown attribute)

