Classfile /Users/mw/Projects/slang-braindump/.jar/jar8/assemble/slang-braindump/assemble/content/coursier/cache/Cache$.class
  Last modified May 29, 2022; size 434 bytes
  SHA-256 checksum 5c9d380641f41eeed87fe46056aa2ff40f2c922ac865a2f2282173019f372e21
  Compiled from "Cache.scala"
public final class coursier.cache.Cache$ extends coursier.cache.PlatformCacheCompanion
  minor version: 0
  major version: 52
  flags: (0x0031) ACC_PUBLIC, ACC_FINAL, ACC_SUPER
  this_class: #2                          // coursier/cache/Cache$
  super_class: #4                         // coursier/cache/PlatformCacheCompanion
  interfaces: 0, fields: 1, methods: 2, attributes: 3
Constant pool:
   #1 = Utf8               coursier/cache/Cache$
   #2 = Class              #1             // coursier/cache/Cache$
   #3 = Utf8               coursier/cache/PlatformCacheCompanion
   #4 = Class              #3             // coursier/cache/PlatformCacheCompanion
   #5 = Utf8               Cache.scala
   #6 = Utf8               MODULE$
   #7 = Utf8               Lcoursier/cache/Cache$;
   #8 = Utf8               <clinit>
   #9 = Utf8               ()V
  #10 = Utf8               <init>
  #11 = NameAndType        #10:#9         // "<init>":()V
  #12 = Methodref          #2.#11         // coursier/cache/Cache$."<init>":()V
  #13 = NameAndType        #6:#7          // MODULE$:Lcoursier/cache/Cache$;
  #14 = Fieldref           #2.#13         // coursier/cache/Cache$.MODULE$:Lcoursier/cache/Cache$;
  #15 = Methodref          #4.#11         // coursier/cache/PlatformCacheCompanion."<init>":()V
  #16 = Utf8               this
  #17 = Utf8               Code
  #18 = Utf8               LineNumberTable
  #19 = Utf8               LocalVariableTable
  #20 = Utf8               SourceFile
  #21 = Utf8               ScalaInlineInfo
  #22 = Utf8               Scala
{
  public static final coursier.cache.Cache$ MODULE$;
    descriptor: Lcoursier/cache/Cache$;
    flags: (0x0019) ACC_PUBLIC, ACC_STATIC, ACC_FINAL

  public static {};
    descriptor: ()V
    flags: (0x0009) ACC_PUBLIC, ACC_STATIC
    Code:
      stack=2, locals=0, args_size=0
         0: new           #2                  // class coursier/cache/Cache$
         3: dup
         4: invokespecial #12                 // Method "<init>":()V
         7: putstatic     #14                 // Field MODULE$:Lcoursier/cache/Cache$;
        10: return
      LineNumberTable:
        line 38: 0

  private coursier.cache.Cache$();
    descriptor: ()V
    flags: (0x0002) ACC_PRIVATE
    Code:
      stack=1, locals=1, args_size=1
         0: aload_0
         1: invokespecial #15                 // Method coursier/cache/PlatformCacheCompanion."<init>":()V
         4: return
      LineNumberTable:
        line 38: 0
      LocalVariableTable:
        Start  Length  Slot  Name   Signature
            0       5     0  this   Lcoursier/cache/Cache$;
}
SourceFile: "Cache.scala"
  ScalaInlineInfo: length = 0x9 (unknown attribute)
   01 01 00 01 00 0A 00 09 01
  Scala: length = 0x0 (unknown attribute)

