Classfile /Users/mw/Projects/slang-braindump/.jar/jar8/assemble/slang-braindump/assemble/content/coursier/cache/CacheLocks.class
  Last modified May 29, 2022; size 2756 bytes
  SHA-256 checksum 54574849d6be23b1de76f424247b632c2f668fbc9eea2bd336606b461038dd62
  Compiled from "CacheLocks.scala"
public final class coursier.cache.CacheLocks
  minor version: 0
  major version: 52
  flags: (0x0031) ACC_PUBLIC, ACC_FINAL, ACC_SUPER
  this_class: #2                          // coursier/cache/CacheLocks
  super_class: #4                         // java/lang/Object
  interfaces: 0, fields: 0, methods: 5, attributes: 3
Constant pool:
   #1 = Utf8               coursier/cache/CacheLocks
   #2 = Class              #1             // coursier/cache/CacheLocks
   #3 = Utf8               java/lang/Object
   #4 = Class              #3             // java/lang/Object
   #5 = Utf8               CacheLocks.scala
   #6 = Utf8               Lscala/reflect/ScalaSignature;
   #7 = Utf8               bytes
   #8 = Utf8               \u0006\u0005\u0005]r!\u0002\u0007\u000e\u0011\u0003\u0011b!\u0002\u000b\u000e\u0011\u0003)\u0002\"\u0002\u000f\u0002\t\u0003i\u0002\"\u0002\u0010\u0002\t\u0003y\u0002\"\u0002\u0010\u0002\t\u0003Y\u0004\"B&\u0002\t\u0003a\u0005\"B.\u0002\t\u0003a\u0006b\u0002;\u0002\u0005\u0004%I!\u001e\u0005\b\u00033\t\u0001\u0015!\u0003w\u0011%\tY\"\u0001b\u0001\n\u0013\ti\u0002\u0003\u0005\u0002 \u0005\u0001\u000b\u0011BA\u0007\u0011\u001d\t\t#\u0001C\u0001\u0003G\t!bQ1dQ\u0016dunY6t\u0015\tqq\"A\u0003dC\u000eDWMC\u0001\u0011\u0003!\u0019w.\u001e:tS\u0016\u00148\u0001\u0001\t\u0003\'\u0005i\u0011!\u0004\u0002\u000b\u0007\u0006\u001c\u0007.\u001a\'pG.\u001c8CA\u0001\u0017!\t9\"$D\u0001\u0019\u0015\u0005I\u0012!B:dC2\f\u0017BA\u000e\u0019\u0005\u0019\te.\u001f*fM\u00061A(\u001b8jiz\"\u0012AE\u0001\u0012o&$\bn\u0015;sk\u000e$XO]3M_\u000e\\WC\u0001\u0011%)\t\t#\u0007\u0006\u0002#[A\u00111\u0005\n\u0007\u0001\t\u0015)3A1\u0001\'\u0005\u0005!\u0016CA\u0014+!\t9\u0002&\u0003\u0002*1\t9aj\u001c;iS:<\u0007CA\f,\u0013\ta\u0003DA\u0002B]fDaAL\u0002\u0005\u0002\u0004y\u0013!\u00014\u0011\u0007]\u0001$%\u0003\u000221\tAAHY=oC6,g\bC\u0003\u000f\u0007\u0001\u00071\u0007\u0005\u00025s5\tQG\u0003\u00027o\u0005\u0011\u0011n\u001c\u0006\u0002q\u0005!!.\u0019<b\u0013\tQTG\u0001\u0003GS2,WC\u0001\u001f@)\ti$\t\u0006\u0002?\u0001B\u00111e\u0010\u0003\u0006K\u0011\u0011\rA\n\u0005\u0007]\u0011!\t\u0019A!\u0011\u0007]\u0001d\bC\u0003\u000f\t\u0001\u00071\t\u0005\u0002E\u00136\tQI\u0003\u0002G\u000f\u0006!a-\u001b7f\u0015\tAu\'A\u0002oS>L!AS#\u0003\tA\u000bG\u000f[\u0001\u000bo&$\b\u000eT8dW>\u0013XCA\'Q)\rq\u0015L\u0017\u000b\u0004\u001fF\u001b\u0006CA\u0012Q\t\u0015)SA1\u0001\'\u0011\u0019qS\u0001\"a\u0001%B\u0019q\u0003M(\t\rQ+A\u00111\u0001V\u0003!Ig\rT8dW\u0016$\u0007cA\f1-B\u0019qcV(\n\u0005aC\"AB(qi&|g\u000eC\u0003\u000f\u000b\u0001\u00071\u0007C\u0003G\u000b\u0001\u00071\'A\u0006xSRDGj\\2l\r>\u0014XCA/p)\rq&o\u001d\u000b\u0003?B\u0004B\u0001\u00195l]:\u0011\u0011M\u001a\b\u0003E\u0016l\u0011a\u0019\u0006\u0003IF\ta\u0001\u0010:p_Rt\u0014\"A\r\n\u0005\u001dD\u0012a\u00029bG.\fw-Z\u0005\u0003S*\u0014a!R5uQ\u0016\u0014(BA4\u0019!\t\u0019B.\u0003\u0002n\u001b\ti\u0011I\u001d;jM\u0006\u001cG/\u0012:s_J\u0004\"aI8\u0005\u000b\u00152!\u0019\u0001\u0014\t\r92A\u00111\u0001r!\r9\u0002g\u0018\u0005\u0006\u001d\u0019\u0001\ra\r\u0005\u0006\r\u001a\u0001\raM\u0001\tkJdGj\\2lgV\ta\u000fE\u0003xyz\fi!D\u0001y\u0015\tI(0\u0001\u0006d_:\u001cWO\u001d:f]RT!a_\u001c\u0002\tU$\u0018\u000e\\\u0005\u0003{b\u0014\u0011cQ8oGV\u0014(/\u001a8u\u0011\u0006\u001c\b.T1q!\ry\u0018q\u0001\b\u0005\u0003\u0003\t\u0019\u0001\u0005\u0002c1%\u0019\u0011Q\u0001\r\u0002\rA\u0013X\rZ3g\u0013\u0011\tI!a\u0003\u0003\rM#(/\u001b8h\u0015\r\t)\u0001\u0007\t\u0005\u0003\u001f\t)\"\u0004\u0002\u0002\u0012)\u0019\u00111C\u001c\u0002\t1\fgnZ\u0005\u0005\u0003/\t\tB\u0001\u0004PE*,7\r^\u0001\nkJdGj\\2lg\u0002\n!#\u001e:m\u0019>\u001c7\u000eR;n[f|%M[3diV\u0011\u0011QB\u0001\u0014kJdGj\\2l\tVlW._(cU\u0016\u001cG\u000fI\u0001\fo&$\b.\u0016:m\u0019>\u001c7.\u0006\u0003\u0002&\u00055B\u0003BA\u0014\u0003g!B!!\u000b\u00020A!qcVA\u0016!\r\u0019\u0013Q\u0006\u0003\u0006K-\u0011\rA\n\u0005\b]-!\t\u0019AA\u0019!\u00119\u0002\'a\u000b\t\r\u0005U2\u00021\u0001\u007f\u0003\r)(\u000f\u001c
   #9 = Utf8               withUrlLock
  #10 = Utf8               (Ljava/lang/String;Lscala/Function0;)Lscala/Option;
  #11 = Utf8               <T:Ljava/lang/Object;>(Ljava/lang/String;Lscala/Function0<TT;>;)Lscala/Option<TT;>;
  #12 = Utf8               url
  #13 = Utf8               f
  #14 = Utf8               coursier/cache/CacheLocks$
  #15 = Class              #14            // coursier/cache/CacheLocks$
  #16 = Utf8               MODULE$
  #17 = Utf8               Lcoursier/cache/CacheLocks$;
  #18 = NameAndType        #16:#17        // MODULE$:Lcoursier/cache/CacheLocks$;
  #19 = Fieldref           #15.#18        // coursier/cache/CacheLocks$.MODULE$:Lcoursier/cache/CacheLocks$;
  #20 = NameAndType        #9:#10         // withUrlLock:(Ljava/lang/String;Lscala/Function0;)Lscala/Option;
  #21 = Methodref          #15.#20        // coursier/cache/CacheLocks$.withUrlLock:(Ljava/lang/String;Lscala/Function0;)Lscala/Option;
  #22 = Utf8               withLockFor
  #23 = Utf8               (Ljava/io/File;Ljava/io/File;Lscala/Function0;)Lscala/util/Either;
  #24 = Utf8               <T:Ljava/lang/Object;>(Ljava/io/File;Ljava/io/File;Lscala/Function0<Lscala/util/Either<Lcoursier/cache/ArtifactError;TT;>;>;)Lscala/util/Either<Lcoursier/cache/ArtifactError;TT;>;
  #25 = Utf8               cache
  #26 = Utf8               file
  #27 = NameAndType        #22:#23        // withLockFor:(Ljava/io/File;Ljava/io/File;Lscala/Function0;)Lscala/util/Either;
  #28 = Methodref          #15.#27        // coursier/cache/CacheLocks$.withLockFor:(Ljava/io/File;Ljava/io/File;Lscala/Function0;)Lscala/util/Either;
  #29 = Utf8               withLockOr
  #30 = Utf8               (Ljava/io/File;Ljava/io/File;Lscala/Function0;Lscala/Function0;)Ljava/lang/Object;
  #31 = Utf8               <T:Ljava/lang/Object;>(Ljava/io/File;Ljava/io/File;Lscala/Function0<TT;>;Lscala/Function0<Lscala/Option<TT;>;>;)TT;
  #32 = Utf8               ifLocked
  #33 = NameAndType        #29:#30        // withLockOr:(Ljava/io/File;Ljava/io/File;Lscala/Function0;Lscala/Function0;)Ljava/lang/Object;
  #34 = Methodref          #15.#33        // coursier/cache/CacheLocks$.withLockOr:(Ljava/io/File;Ljava/io/File;Lscala/Function0;Lscala/Function0;)Ljava/lang/Object;
  #35 = Utf8               withStructureLock
  #36 = Utf8               (Ljava/nio/file/Path;Lscala/Function0;)Ljava/lang/Object;
  #37 = Utf8               <T:Ljava/lang/Object;>(Ljava/nio/file/Path;Lscala/Function0<TT;>;)TT;
  #38 = NameAndType        #35:#36        // withStructureLock:(Ljava/nio/file/Path;Lscala/Function0;)Ljava/lang/Object;
  #39 = Methodref          #15.#38        // coursier/cache/CacheLocks$.withStructureLock:(Ljava/nio/file/Path;Lscala/Function0;)Ljava/lang/Object;
  #40 = Utf8               (Ljava/io/File;Lscala/Function0;)Ljava/lang/Object;
  #41 = Utf8               <T:Ljava/lang/Object;>(Ljava/io/File;Lscala/Function0<TT;>;)TT;
  #42 = NameAndType        #35:#40        // withStructureLock:(Ljava/io/File;Lscala/Function0;)Ljava/lang/Object;
  #43 = Methodref          #15.#42        // coursier/cache/CacheLocks$.withStructureLock:(Ljava/io/File;Lscala/Function0;)Ljava/lang/Object;
  #44 = Utf8               Code
  #45 = Utf8               Signature
  #46 = Utf8               MethodParameters
  #47 = Utf8               SourceFile
  #48 = Utf8               RuntimeVisibleAnnotations
  #49 = Utf8               ScalaSig
{
  public static <T extends java.lang.Object> scala.Option<T> withUrlLock(java.lang.String, scala.Function0<T>);
    descriptor: (Ljava/lang/String;Lscala/Function0;)Lscala/Option;
    flags: (0x0009) ACC_PUBLIC, ACC_STATIC
    Code:
      stack=3, locals=2, args_size=2
         0: getstatic     #19                 // Field coursier/cache/CacheLocks$.MODULE$:Lcoursier/cache/CacheLocks$;
         3: aload_0
         4: aload_1
         5: invokevirtual #21                 // Method coursier/cache/CacheLocks$.withUrlLock:(Ljava/lang/String;Lscala/Function0;)Lscala/Option;
         8: areturn
    Signature: #11                          // <T:Ljava/lang/Object;>(Ljava/lang/String;Lscala/Function0<TT;>;)Lscala/Option<TT;>;
    MethodParameters:
      Name                           Flags
      url                            final
      f                              final

  public static <T extends java.lang.Object> scala.util.Either<coursier.cache.ArtifactError, T> withLockFor(java.io.File, java.io.File, scala.Function0<scala.util.Either<coursier.cache.ArtifactError, T>>);
    descriptor: (Ljava/io/File;Ljava/io/File;Lscala/Function0;)Lscala/util/Either;
    flags: (0x0009) ACC_PUBLIC, ACC_STATIC
    Code:
      stack=4, locals=3, args_size=3
         0: getstatic     #19                 // Field coursier/cache/CacheLocks$.MODULE$:Lcoursier/cache/CacheLocks$;
         3: aload_0
         4: aload_1
         5: aload_2
         6: invokevirtual #28                 // Method coursier/cache/CacheLocks$.withLockFor:(Ljava/io/File;Ljava/io/File;Lscala/Function0;)Lscala/util/Either;
         9: areturn
    Signature: #24                          // <T:Ljava/lang/Object;>(Ljava/io/File;Ljava/io/File;Lscala/Function0<Lscala/util/Either<Lcoursier/cache/ArtifactError;TT;>;>;)Lscala/util/Either<Lcoursier/cache/ArtifactError;TT;>;
    MethodParameters:
      Name                           Flags
      cache                          final
      file                           final
      f                              final

  public static <T extends java.lang.Object> T withLockOr(java.io.File, java.io.File, scala.Function0<T>, scala.Function0<scala.Option<T>>);
    descriptor: (Ljava/io/File;Ljava/io/File;Lscala/Function0;Lscala/Function0;)Ljava/lang/Object;
    flags: (0x0009) ACC_PUBLIC, ACC_STATIC
    Code:
      stack=5, locals=4, args_size=4
         0: getstatic     #19                 // Field coursier/cache/CacheLocks$.MODULE$:Lcoursier/cache/CacheLocks$;
         3: aload_0
         4: aload_1
         5: aload_2
         6: aload_3
         7: invokevirtual #34                 // Method coursier/cache/CacheLocks$.withLockOr:(Ljava/io/File;Ljava/io/File;Lscala/Function0;Lscala/Function0;)Ljava/lang/Object;
        10: areturn
    Signature: #31                          // <T:Ljava/lang/Object;>(Ljava/io/File;Ljava/io/File;Lscala/Function0<TT;>;Lscala/Function0<Lscala/Option<TT;>;>;)TT;
    MethodParameters:
      Name                           Flags
      cache                          final
      file                           final
      f                              final
      ifLocked                       final

  public static <T extends java.lang.Object> T withStructureLock(java.nio.file.Path, scala.Function0<T>);
    descriptor: (Ljava/nio/file/Path;Lscala/Function0;)Ljava/lang/Object;
    flags: (0x0009) ACC_PUBLIC, ACC_STATIC
    Code:
      stack=3, locals=2, args_size=2
         0: getstatic     #19                 // Field coursier/cache/CacheLocks$.MODULE$:Lcoursier/cache/CacheLocks$;
         3: aload_0
         4: aload_1
         5: invokevirtual #39                 // Method coursier/cache/CacheLocks$.withStructureLock:(Ljava/nio/file/Path;Lscala/Function0;)Ljava/lang/Object;
         8: areturn
    Signature: #37                          // <T:Ljava/lang/Object;>(Ljava/nio/file/Path;Lscala/Function0<TT;>;)TT;
    MethodParameters:
      Name                           Flags
      cache                          final
      f                              final

  public static <T extends java.lang.Object> T withStructureLock(java.io.File, scala.Function0<T>);
    descriptor: (Ljava/io/File;Lscala/Function0;)Ljava/lang/Object;
    flags: (0x0009) ACC_PUBLIC, ACC_STATIC
    Code:
      stack=3, locals=2, args_size=2
         0: getstatic     #19                 // Field coursier/cache/CacheLocks$.MODULE$:Lcoursier/cache/CacheLocks$;
         3: aload_0
         4: aload_1
         5: invokevirtual #43                 // Method coursier/cache/CacheLocks$.withStructureLock:(Ljava/io/File;Lscala/Function0;)Ljava/lang/Object;
         8: areturn
    Signature: #41                          // <T:Ljava/lang/Object;>(Ljava/io/File;Lscala/Function0<TT;>;)TT;
    MethodParameters:
      Name                           Flags
      cache                          final
      f                              final
}
SourceFile: "CacheLocks.scala"
RuntimeVisibleAnnotations:
  0: #6(#7=s#8)
    scala.reflect.ScalaSignature(
      bytes="\u0006\u0005\u0005]r!\u0002\u0007\u000e\u0011\u0003\u0011b!\u0002\u000b\u000e\u0011\u0003)\u0002\"\u0002\u000f\u0002\t\u0003i\u0002\"\u0002\u0010\u0002\t\u0003y\u0002\"\u0002\u0010\u0002\t\u0003Y\u0004\"B&\u0002\t\u0003a\u0005\"B.\u0002\t\u0003a\u0006b\u0002;\u0002\u0005\u0004%I!\u001e\u0005\b\u00033\t\u0001\u0015!\u0003w\u0011%\tY\"\u0001b\u0001\n\u0013\ti\u0002\u0003\u0005\u0002 \u0005\u0001\u000b\u0011BA\u0007\u0011\u001d\t\t#\u0001C\u0001\u0003G\t!bQ1dQ\u0016dunY6t\u0015\tqq\"A\u0003dC\u000eDWMC\u0001\u0011\u0003!\u0019w.\u001e:tS\u0016\u00148\u0001\u0001\t\u0003\'\u0005i\u0011!\u0004\u0002\u000b\u0007\u0006\u001c\u0007.\u001a\'pG.\u001c8CA\u0001\u0017!\t9\"$D\u0001\u0019\u0015\u0005I\u0012!B:dC2\f\u0017BA\u000e\u0019\u0005\u0019\te.\u001f*fM\u00061A(\u001b8jiz\"\u0012AE\u0001\u0012o&$\bn\u0015;sk\u000e$XO]3M_\u000e\\WC\u0001\u0011%)\t\t#\u0007\u0006\u0002#[A\u00111\u0005\n\u0007\u0001\t\u0015)3A1\u0001\'\u0005\u0005!\u0016CA\u0014+!\t9\u0002&\u0003\u0002*1\t9aj\u001c;iS:<\u0007CA\f,\u0013\ta\u0003DA\u0002B]fDaAL\u0002\u0005\u0002\u0004y\u0013!\u00014\u0011\u0007]\u0001$%\u0003\u000221\tAAHY=oC6,g\bC\u0003\u000f\u0007\u0001\u00071\u0007\u0005\u00025s5\tQG\u0003\u00027o\u0005\u0011\u0011n\u001c\u0006\u0002q\u0005!!.\u0019<b\u0013\tQTG\u0001\u0003GS2,WC\u0001\u001f@)\ti$\t\u0006\u0002?\u0001B\u00111e\u0010\u0003\u0006K\u0011\u0011\rA\n\u0005\u0007]\u0011!\t\u0019A!\u0011\u0007]\u0001d\bC\u0003\u000f\t\u0001\u00071\t\u0005\u0002E\u00136\tQI\u0003\u0002G\u000f\u0006!a-\u001b7f\u0015\tAu\'A\u0002oS>L!AS#\u0003\tA\u000bG\u000f[\u0001\u000bo&$\b\u000eT8dW>\u0013XCA\'Q)\rq\u0015L\u0017\u000b\u0004\u001fF\u001b\u0006CA\u0012Q\t\u0015)SA1\u0001\'\u0011\u0019qS\u0001\"a\u0001%B\u0019q\u0003M(\t\rQ+A\u00111\u0001V\u0003!Ig\rT8dW\u0016$\u0007cA\f1-B\u0019qcV(\n\u0005aC\"AB(qi&|g\u000eC\u0003\u000f\u000b\u0001\u00071\u0007C\u0003G\u000b\u0001\u00071\'A\u0006xSRDGj\\2l\r>\u0014XCA/p)\rq&o\u001d\u000b\u0003?B\u0004B\u0001\u00195l]:\u0011\u0011M\u001a\b\u0003E\u0016l\u0011a\u0019\u0006\u0003IF\ta\u0001\u0010:p_Rt\u0014\"A\r\n\u0005\u001dD\u0012a\u00029bG.\fw-Z\u0005\u0003S*\u0014a!R5uQ\u0016\u0014(BA4\u0019!\t\u0019B.\u0003\u0002n\u001b\ti\u0011I\u001d;jM\u0006\u001cG/\u0012:s_J\u0004\"aI8\u0005\u000b\u00152!\u0019\u0001\u0014\t\r92A\u00111\u0001r!\r9\u0002g\u0018\u0005\u0006\u001d\u0019\u0001\ra\r\u0005\u0006\r\u001a\u0001\raM\u0001\tkJdGj\\2lgV\ta\u000fE\u0003xyz\fi!D\u0001y\u0015\tI(0\u0001\u0006d_:\u001cWO\u001d:f]RT!a_\u001c\u0002\tU$\u0018\u000e\\\u0005\u0003{b\u0014\u0011cQ8oGV\u0014(/\u001a8u\u0011\u0006\u001c\b.T1q!\ry\u0018q\u0001\b\u0005\u0003\u0003\t\u0019\u0001\u0005\u0002c1%\u0019\u0011Q\u0001\r\u0002\rA\u0013X\rZ3g\u0013\u0011\tI!a\u0003\u0003\rM#(/\u001b8h\u0015\r\t)\u0001\u0007\t\u0005\u0003\u001f\t)\"\u0004\u0002\u0002\u0012)\u0019\u00111C\u001c\u0002\t1\fgnZ\u0005\u0005\u0003/\t\tB\u0001\u0004PE*,7\r^\u0001\nkJdGj\\2lg\u0002\n!#\u001e:m\u0019>\u001c7\u000eR;n[f|%M[3diV\u0011\u0011QB\u0001\u0014kJdGj\\2l\tVlW._(cU\u0016\u001cG\u000fI\u0001\fo&$\b.\u0016:m\u0019>\u001c7.\u0006\u0003\u0002&\u00055B\u0003BA\u0014\u0003g!B!!\u000b\u00020A!qcVA\u0016!\r\u0019\u0013Q\u0006\u0003\u0006K-\u0011\rA\n\u0005\b]-!\t\u0019AA\u0019!\u00119\u0002\'a\u000b\t\r\u0005U2\u00021\u0001\u007f\u0003\r)(\u000f\u001c"
    )
  ScalaSig: length = 0x3 (unknown attribute)
   05 02 00
