Classfile /Users/mw/Projects/slang-braindump/.jar/jar11/assemble/slang-braindump/assemble/content/org/scalatest/tagobjects/ChromeBrowser.class
  Last modified May 29, 2022; size 583 bytes
  SHA-256 checksum 5e3568f0890b0527ec13e453d61b6a43c85108e6c0c059234b6f19cb79099cf5
  Compiled from "ChromeBrowser.scala"
public final class org.scalatest.tagobjects.ChromeBrowser
  minor version: 0
  major version: 52
  flags: (0x0031) ACC_PUBLIC, ACC_FINAL, ACC_SUPER
  this_class: #2                          // org/scalatest/tagobjects/ChromeBrowser
  super_class: #4                         // java/lang/Object
  interfaces: 0, fields: 0, methods: 1, attributes: 3
Constant pool:
   #1 = Utf8               org/scalatest/tagobjects/ChromeBrowser
   #2 = Class              #1             // org/scalatest/tagobjects/ChromeBrowser
   #3 = Utf8               java/lang/Object
   #4 = Class              #3             // java/lang/Object
   #5 = Utf8               ChromeBrowser.scala
   #6 = Utf8               Lscala/reflect/ScalaSignature;
   #7 = Utf8               bytes
   #8 = Utf8               \u0006\u0005U9Qa\u0001\u0003\t\u0002-1Q!\u0004\u0003\t\u00029AQaE\u0001\u0005\u0002Q\tQb\u00115s_6,\'I]8xg\u0016\u0014(BA\u0003\u0007\u0003)!\u0018mZ8cU\u0016\u001cGo\u001d\u0006\u0003\u000f!\t\u0011b]2bY\u0006$Xm\u001d;\u000b\u0003%\t1a\u001c:h\u0007\u0001\u0001\"\u0001D\u0001\u000e\u0003\u0011\u0011Qb\u00115s_6,\'I]8xg\u0016\u00148CA\u0001\u0010!\t\u0001\u0012#D\u0001\u0007\u0013\t\u0011bAA\u0002UC\u001e\fa\u0001P5oSRtD#A\u0006
   #9 = Utf8               name
  #10 = Utf8               ()Ljava/lang/String;
  #11 = Utf8               org/scalatest/tagobjects/ChromeBrowser$
  #12 = Class              #11            // org/scalatest/tagobjects/ChromeBrowser$
  #13 = Utf8               MODULE$
  #14 = Utf8               Lorg/scalatest/tagobjects/ChromeBrowser$;
  #15 = NameAndType        #13:#14        // MODULE$:Lorg/scalatest/tagobjects/ChromeBrowser$;
  #16 = Fieldref           #12.#15        // org/scalatest/tagobjects/ChromeBrowser$.MODULE$:Lorg/scalatest/tagobjects/ChromeBrowser$;
  #17 = NameAndType        #9:#10         // name:()Ljava/lang/String;
  #18 = Methodref          #12.#17        // org/scalatest/tagobjects/ChromeBrowser$.name:()Ljava/lang/String;
  #19 = Utf8               Code
  #20 = Utf8               SourceFile
  #21 = Utf8               RuntimeVisibleAnnotations
  #22 = Utf8               ScalaSig
{
  public static java.lang.String name();
    descriptor: ()Ljava/lang/String;
    flags: (0x0009) ACC_PUBLIC, ACC_STATIC
    Code:
      stack=1, locals=0, args_size=0
         0: getstatic     #16                 // Field org/scalatest/tagobjects/ChromeBrowser$.MODULE$:Lorg/scalatest/tagobjects/ChromeBrowser$;
         3: invokevirtual #18                 // Method org/scalatest/tagobjects/ChromeBrowser$.name:()Ljava/lang/String;
         6: areturn
}
SourceFile: "ChromeBrowser.scala"
RuntimeVisibleAnnotations:
  0: #6(#7=s#8)
    scala.reflect.ScalaSignature(
      bytes="\u0006\u0005U9Qa\u0001\u0003\t\u0002-1Q!\u0004\u0003\t\u00029AQaE\u0001\u0005\u0002Q\tQb\u00115s_6,\'I]8xg\u0016\u0014(BA\u0003\u0007\u0003)!\u0018mZ8cU\u0016\u001cGo\u001d\u0006\u0003\u000f!\t\u0011b]2bY\u0006$Xm\u001d;\u000b\u0003%\t1a\u001c:h\u0007\u0001\u0001\"\u0001D\u0001\u000e\u0003\u0011\u0011Qb\u00115s_6,\'I]8xg\u0016\u00148CA\u0001\u0010!\t\u0001\u0012#D\u0001\u0007\u0013\t\u0011bAA\u0002UC\u001e\fa\u0001P5oSRtD#A\u0006"
    )
  ScalaSig: length = 0x3 (unknown attribute)
   05 02 00
