Classfile /Users/mw/Projects/slang-braindump/.jar/jar11/assemble/slang-braindump/assemble/content/org/scalatest/tagobjects/CPU.class
  Last modified May 29, 2022; size 521 bytes
  SHA-256 checksum 312c769f008344c80651f9f46dd4b4b00c1f1ef670a57d390405b5f200f3b546
  Compiled from "CPU.scala"
public final class org.scalatest.tagobjects.CPU
  minor version: 0
  major version: 52
  flags: (0x0031) ACC_PUBLIC, ACC_FINAL, ACC_SUPER
  this_class: #2                          // org/scalatest/tagobjects/CPU
  super_class: #4                         // java/lang/Object
  interfaces: 0, fields: 0, methods: 1, attributes: 3
Constant pool:
   #1 = Utf8               org/scalatest/tagobjects/CPU
   #2 = Class              #1             // org/scalatest/tagobjects/CPU
   #3 = Utf8               java/lang/Object
   #4 = Class              #3             // java/lang/Object
   #5 = Utf8               CPU.scala
   #6 = Utf8               Lscala/reflect/ScalaSignature;
   #7 = Utf8               bytes
   #8 = Utf8               \u0006\u0005U9Qa\u0001\u0003\t\u0002-1Q!\u0004\u0003\t\u00029AQaE\u0001\u0005\u0002Q\t1a\u0011)V\u0015\t)a!\u0001\u0006uC\u001e|\'M[3diNT!a\u0002\u0005\u0002\u0013M\u001c\u0017\r\\1uKN$(\"A\u0005\u0002\u0007=\u0014xm\u0001\u0001\u0011\u00051\tQ\"\u0001\u0003\u0003\u0007\r\u0003Vk\u0005\u0002\u0002\u001fA\u0011\u0001#E\u0007\u0002\r%\u0011!C\u0002\u0002\u0004)\u0006<\u0017A\u0002\u001fj]&$h\bF\u0001\f\u0001
   #9 = Utf8               name
  #10 = Utf8               ()Ljava/lang/String;
  #11 = Utf8               org/scalatest/tagobjects/CPU$
  #12 = Class              #11            // org/scalatest/tagobjects/CPU$
  #13 = Utf8               MODULE$
  #14 = Utf8               Lorg/scalatest/tagobjects/CPU$;
  #15 = NameAndType        #13:#14        // MODULE$:Lorg/scalatest/tagobjects/CPU$;
  #16 = Fieldref           #12.#15        // org/scalatest/tagobjects/CPU$.MODULE$:Lorg/scalatest/tagobjects/CPU$;
  #17 = NameAndType        #9:#10         // name:()Ljava/lang/String;
  #18 = Methodref          #12.#17        // org/scalatest/tagobjects/CPU$.name:()Ljava/lang/String;
  #19 = Utf8               Code
  #20 = Utf8               SourceFile
  #21 = Utf8               RuntimeVisibleAnnotations
  #22 = Utf8               ScalaSig
{
  public static java.lang.String name();
    descriptor: ()Ljava/lang/String;
    flags: (0x0009) ACC_PUBLIC, ACC_STATIC
    Code:
      stack=1, locals=0, args_size=0
         0: getstatic     #16                 // Field org/scalatest/tagobjects/CPU$.MODULE$:Lorg/scalatest/tagobjects/CPU$;
         3: invokevirtual #18                 // Method org/scalatest/tagobjects/CPU$.name:()Ljava/lang/String;
         6: areturn
}
SourceFile: "CPU.scala"
RuntimeVisibleAnnotations:
  0: #6(#7=s#8)
    scala.reflect.ScalaSignature(
      bytes="\u0006\u0005U9Qa\u0001\u0003\t\u0002-1Q!\u0004\u0003\t\u00029AQaE\u0001\u0005\u0002Q\t1a\u0011)V\u0015\t)a!\u0001\u0006uC\u001e|\'M[3diNT!a\u0002\u0005\u0002\u0013M\u001c\u0017\r\\1uKN$(\"A\u0005\u0002\u0007=\u0014xm\u0001\u0001\u0011\u00051\tQ\"\u0001\u0003\u0003\u0007\r\u0003Vk\u0005\u0002\u0002\u001fA\u0011\u0001#E\u0007\u0002\r%\u0011!C\u0002\u0002\u0004)\u0006<\u0017A\u0002\u001fj]&$h\bF\u0001\f\u0001"
    )
  ScalaSig: length = 0x3 (unknown attribute)
   05 02 00
