Classfile /Users/mw/Projects/slang-braindump/.jar/jar11/assemble/slang-braindump/assemble/content/org/scalatest/tagobjects/FirefoxBrowser.class
  Last modified May 29, 2022; size 590 bytes
  SHA-256 checksum d968a63690f43ad52edc778e6955e486d84d6c1de4b6246f3d85128a24f6aa56
  Compiled from "FirefoxBrowser.scala"
public final class org.scalatest.tagobjects.FirefoxBrowser
  minor version: 0
  major version: 52
  flags: (0x0031) ACC_PUBLIC, ACC_FINAL, ACC_SUPER
  this_class: #2                          // org/scalatest/tagobjects/FirefoxBrowser
  super_class: #4                         // java/lang/Object
  interfaces: 0, fields: 0, methods: 1, attributes: 3
Constant pool:
   #1 = Utf8               org/scalatest/tagobjects/FirefoxBrowser
   #2 = Class              #1             // org/scalatest/tagobjects/FirefoxBrowser
   #3 = Utf8               java/lang/Object
   #4 = Class              #3             // java/lang/Object
   #5 = Utf8               FirefoxBrowser.scala
   #6 = Utf8               Lscala/reflect/ScalaSignature;
   #7 = Utf8               bytes
   #8 = Utf8               \u0006\u0005U9Qa\u0001\u0003\t\u0002-1Q!\u0004\u0003\t\u00029AQaE\u0001\u0005\u0002Q\taBR5sK\u001a|\u0007P\u0011:poN,\'O\u0003\u0002\u0006\r\u0005QA/Y4pE*,7\r^:\u000b\u0005\u001dA\u0011!C:dC2\fG/Z:u\u0015\u0005I\u0011aA8sO\u000e\u0001\u0001C\u0001\u0007\u0002\u001b\u0005!!A\u0004$je\u00164w\u000e\u001f\"s_^\u001cXM]\n\u0003\u0003=\u0001\"\u0001E\t\u000e\u0003\u0019I!A\u0005\u0004\u0003\u0007Q\u000bw-\u0001\u0004=S:LGO\u0010\u000b\u0002\u0017\u0001
   #9 = Utf8               name
  #10 = Utf8               ()Ljava/lang/String;
  #11 = Utf8               org/scalatest/tagobjects/FirefoxBrowser$
  #12 = Class              #11            // org/scalatest/tagobjects/FirefoxBrowser$
  #13 = Utf8               MODULE$
  #14 = Utf8               Lorg/scalatest/tagobjects/FirefoxBrowser$;
  #15 = NameAndType        #13:#14        // MODULE$:Lorg/scalatest/tagobjects/FirefoxBrowser$;
  #16 = Fieldref           #12.#15        // org/scalatest/tagobjects/FirefoxBrowser$.MODULE$:Lorg/scalatest/tagobjects/FirefoxBrowser$;
  #17 = NameAndType        #9:#10         // name:()Ljava/lang/String;
  #18 = Methodref          #12.#17        // org/scalatest/tagobjects/FirefoxBrowser$.name:()Ljava/lang/String;
  #19 = Utf8               Code
  #20 = Utf8               SourceFile
  #21 = Utf8               RuntimeVisibleAnnotations
  #22 = Utf8               ScalaSig
{
  public static java.lang.String name();
    descriptor: ()Ljava/lang/String;
    flags: (0x0009) ACC_PUBLIC, ACC_STATIC
    Code:
      stack=1, locals=0, args_size=0
         0: getstatic     #16                 // Field org/scalatest/tagobjects/FirefoxBrowser$.MODULE$:Lorg/scalatest/tagobjects/FirefoxBrowser$;
         3: invokevirtual #18                 // Method org/scalatest/tagobjects/FirefoxBrowser$.name:()Ljava/lang/String;
         6: areturn
}
SourceFile: "FirefoxBrowser.scala"
RuntimeVisibleAnnotations:
  0: #6(#7=s#8)
    scala.reflect.ScalaSignature(
      bytes="\u0006\u0005U9Qa\u0001\u0003\t\u0002-1Q!\u0004\u0003\t\u00029AQaE\u0001\u0005\u0002Q\taBR5sK\u001a|\u0007P\u0011:poN,\'O\u0003\u0002\u0006\r\u0005QA/Y4pE*,7\r^:\u000b\u0005\u001dA\u0011!C:dC2\fG/Z:u\u0015\u0005I\u0011aA8sO\u000e\u0001\u0001C\u0001\u0007\u0002\u001b\u0005!!A\u0004$je\u00164w\u000e\u001f\"s_^\u001cXM]\n\u0003\u0003=\u0001\"\u0001E\t\u000e\u0003\u0019I!A\u0005\u0004\u0003\u0007Q\u000bw-\u0001\u0004=S:LGO\u0010\u000b\u0002\u0017\u0001"
    )
  ScalaSig: length = 0x3 (unknown attribute)
   05 02 00
