Classfile /Users/mw/Projects/slang-braindump/.jar/jar8/assemble/slang-braindump/assemble/content/org/sireum/logika/package$$Boolean2B.class
  Last modified May 29, 2022; size 1491 bytes
  SHA-256 checksum 05cc95dcf72395ab97d9cc1db29df830f3f0a2bfe9ac1a66cf39f34e65371aab
  Compiled from "package.scala"
public final class org.sireum.logika.package$$Boolean2B
  minor version: 0
  major version: 52
  flags: (0x0031) ACC_PUBLIC, ACC_FINAL, ACC_SUPER
  this_class: #2                          // org/sireum/logika/package$$Boolean2B
  super_class: #4                         // java/lang/Object
  interfaces: 0, fields: 1, methods: 7, attributes: 4
Constant pool:
   #1 = Utf8               org/sireum/logika/package$$Boolean2B
   #2 = Class              #1             // org/sireum/logika/package$$Boolean2B
   #3 = Utf8               java/lang/Object
   #4 = Class              #3             // java/lang/Object
   #5 = Utf8               package.scala
   #6 = Utf8               org/sireum/logika/package
   #7 = Class              #6             // org/sireum/logika/package
   #8 = Utf8               $Boolean2B
   #9 = Utf8               org/sireum/logika/package$$Boolean2B$
  #10 = Class              #9             // org/sireum/logika/package$$Boolean2B$
  #11 = Utf8               $Boolean2B$
  #12 = Utf8               _value
  #13 = Utf8               Z
  #14 = Utf8               ()Z
  #15 = NameAndType        #12:#13        // _value:Z
  #16 = Fieldref           #2.#15         // org/sireum/logika/package$$Boolean2B._value:Z
  #17 = Utf8               this
  #18 = Utf8               Lorg/sireum/logika/package$$Boolean2B;
  #19 = Utf8               $bar$up
  #20 = Utf8               (Z)Z
  #21 = Utf8               other
  #22 = Utf8               MODULE$
  #23 = Utf8               Lorg/sireum/logika/package$$Boolean2B$;
  #24 = NameAndType        #22:#23        // MODULE$:Lorg/sireum/logika/package$$Boolean2B$;
  #25 = Fieldref           #10.#24        // org/sireum/logika/package$$Boolean2B$.MODULE$:Lorg/sireum/logika/package$$Boolean2B$;
  #26 = NameAndType        #12:#14        // _value:()Z
  #27 = Methodref          #2.#26         // org/sireum/logika/package$$Boolean2B._value:()Z
  #28 = Utf8               $bar$up$extension
  #29 = Utf8               (ZZ)Z
  #30 = NameAndType        #28:#29        // $bar$up$extension:(ZZ)Z
  #31 = Methodref          #10.#30        // org/sireum/logika/package$$Boolean2B$.$bar$up$extension:(ZZ)Z
  #32 = Utf8               $eq$eq$eq
  #33 = Utf8               $eq$eq$eq$extension
  #34 = NameAndType        #33:#29        // $eq$eq$eq$extension:(ZZ)Z
  #35 = Methodref          #10.#34        // org/sireum/logika/package$$Boolean2B$.$eq$eq$eq$extension:(ZZ)Z
  #36 = Utf8               $eq$bang$eq
  #37 = Utf8               $eq$bang$eq$extension
  #38 = NameAndType        #37:#29        // $eq$bang$eq$extension:(ZZ)Z
  #39 = Methodref          #10.#38        // org/sireum/logika/package$$Boolean2B$.$eq$bang$eq$extension:(ZZ)Z
  #40 = Utf8               hashCode
  #41 = Utf8               ()I
  #42 = Utf8               hashCode$extension
  #43 = Utf8               (Z)I
  #44 = NameAndType        #42:#43        // hashCode$extension:(Z)I
  #45 = Methodref          #10.#44        // org/sireum/logika/package$$Boolean2B$.hashCode$extension:(Z)I
  #46 = Utf8               equals
  #47 = Utf8               (Ljava/lang/Object;)Z
  #48 = Utf8               x$1
  #49 = Utf8               equals$extension
  #50 = Utf8               (ZLjava/lang/Object;)Z
  #51 = NameAndType        #49:#50        // equals$extension:(ZLjava/lang/Object;)Z
  #52 = Methodref          #10.#51        // org/sireum/logika/package$$Boolean2B$.equals$extension:(ZLjava/lang/Object;)Z
  #53 = Utf8               Ljava/lang/Object;
  #54 = Utf8               <init>
  #55 = Utf8               (Z)V
  #56 = Utf8               ()V
  #57 = NameAndType        #54:#56        // "<init>":()V
  #58 = Methodref          #4.#57         // java/lang/Object."<init>":()V
  #59 = Utf8               Code
  #60 = Utf8               LineNumberTable
  #61 = Utf8               LocalVariableTable
  #62 = Utf8               MethodParameters
  #63 = Utf8               InnerClasses
  #64 = Utf8               SourceFile
  #65 = Utf8               ScalaInlineInfo
  #66 = Utf8               Scala
{
  private final boolean _value;
    descriptor: Z
    flags: (0x0012) ACC_PRIVATE, ACC_FINAL

  public boolean _value();
    descriptor: ()Z
    flags: (0x0001) ACC_PUBLIC
    Code:
      stack=1, locals=1, args_size=1
         0: aload_0
         1: getfield      #16                 // Field _value:Z
         4: ireturn
      LineNumberTable:
        line 493: 0
      LocalVariableTable:
        Start  Length  Slot  Name   Signature
            0       5     0  this   Lorg/sireum/logika/package$$Boolean2B;

  public boolean $bar$up(boolean);
    descriptor: (Z)Z
    flags: (0x0001) ACC_PUBLIC
    Code:
      stack=3, locals=2, args_size=2
         0: getstatic     #25                 // Field org/sireum/logika/package$$Boolean2B$.MODULE$:Lorg/sireum/logika/package$$Boolean2B$;
         3: aload_0
         4: invokevirtual #27                 // Method _value:()Z
         7: iload_1
         8: invokevirtual #31                 // Method org/sireum/logika/package$$Boolean2B$.$bar$up$extension:(ZZ)Z
        11: ireturn
      LineNumberTable:
        line 495: 0
      LocalVariableTable:
        Start  Length  Slot  Name   Signature
            0      12     0  this   Lorg/sireum/logika/package$$Boolean2B;
            0      12     1 other   Z
    MethodParameters:
      Name                           Flags
      other                          final

  public boolean $eq$eq$eq(boolean);
    descriptor: (Z)Z
    flags: (0x0001) ACC_PUBLIC
    Code:
      stack=3, locals=2, args_size=2
         0: getstatic     #25                 // Field org/sireum/logika/package$$Boolean2B$.MODULE$:Lorg/sireum/logika/package$$Boolean2B$;
         3: aload_0
         4: invokevirtual #27                 // Method _value:()Z
         7: iload_1
         8: invokevirtual #35                 // Method org/sireum/logika/package$$Boolean2B$.$eq$eq$eq$extension:(ZZ)Z
        11: ireturn
      LineNumberTable:
        line 497: 0
      LocalVariableTable:
        Start  Length  Slot  Name   Signature
            0      12     0  this   Lorg/sireum/logika/package$$Boolean2B;
            0      12     1 other   Z
    MethodParameters:
      Name                           Flags
      other                          final

  public boolean $eq$bang$eq(boolean);
    descriptor: (Z)Z
    flags: (0x0001) ACC_PUBLIC
    Code:
      stack=3, locals=2, args_size=2
         0: getstatic     #25                 // Field org/sireum/logika/package$$Boolean2B$.MODULE$:Lorg/sireum/logika/package$$Boolean2B$;
         3: aload_0
         4: invokevirtual #27                 // Method _value:()Z
         7: iload_1
         8: invokevirtual #39                 // Method org/sireum/logika/package$$Boolean2B$.$eq$bang$eq$extension:(ZZ)Z
        11: ireturn
      LineNumberTable:
        line 499: 0
      LocalVariableTable:
        Start  Length  Slot  Name   Signature
            0      12     0  this   Lorg/sireum/logika/package$$Boolean2B;
            0      12     1 other   Z
    MethodParameters:
      Name                           Flags
      other                          final

  public int hashCode();
    descriptor: ()I
    flags: (0x0001) ACC_PUBLIC
    Code:
      stack=2, locals=1, args_size=1
         0: getstatic     #25                 // Field org/sireum/logika/package$$Boolean2B$.MODULE$:Lorg/sireum/logika/package$$Boolean2B$;
         3: aload_0
         4: invokevirtual #27                 // Method _value:()Z
         7: invokevirtual #45                 // Method org/sireum/logika/package$$Boolean2B$.hashCode$extension:(Z)I
        10: ireturn
      LineNumberTable:
        line 493: 0
      LocalVariableTable:
        Start  Length  Slot  Name   Signature
            0      11     0  this   Lorg/sireum/logika/package$$Boolean2B;

  public boolean equals(java.lang.Object);
    descriptor: (Ljava/lang/Object;)Z
    flags: (0x0001) ACC_PUBLIC
    Code:
      stack=3, locals=2, args_size=2
         0: getstatic     #25                 // Field org/sireum/logika/package$$Boolean2B$.MODULE$:Lorg/sireum/logika/package$$Boolean2B$;
         3: aload_0
         4: invokevirtual #27                 // Method _value:()Z
         7: aload_1
         8: invokevirtual #52                 // Method org/sireum/logika/package$$Boolean2B$.equals$extension:(ZLjava/lang/Object;)Z
        11: ireturn
      LineNumberTable:
        line 493: 0
      LocalVariableTable:
        Start  Length  Slot  Name   Signature
            0      12     0  this   Lorg/sireum/logika/package$$Boolean2B;
            0      12     1   x$1   Ljava/lang/Object;
    MethodParameters:
      Name                           Flags
      x$1                            final

  public org.sireum.logika.package$$Boolean2B(boolean);
    descriptor: (Z)V
    flags: (0x0001) ACC_PUBLIC
    Code:
      stack=2, locals=2, args_size=2
         0: aload_0
         1: iload_1
         2: putfield      #16                 // Field _value:Z
         5: aload_0
         6: invokespecial #58                 // Method java/lang/Object."<init>":()V
         9: return
      LineNumberTable:
        line 493: 0
      LocalVariableTable:
        Start  Length  Slot  Name   Signature
            0      10     0  this   Lorg/sireum/logika/package$$Boolean2B;
            0      10     1 _value   Z
    MethodParameters:
      Name                           Flags
      _value                         final
}
InnerClasses:
  public static final #8= #2 of #7;       // $Boolean2B=class org/sireum/logika/package$$Boolean2B of class org/sireum/logika/package
  public static #11= #10 of #7;           // $Boolean2B$=class org/sireum/logika/package$$Boolean2B$ of class org/sireum/logika/package
SourceFile: "package.scala"
  ScalaInlineInfo: length = 0x27 (unknown attribute)
   01 01 00 07 00 13 00 14 05 00 24 00 14 05 00 20
   00 14 05 00 36 00 37 01 00 0C 00 0E 01 00 2E 00
   2F 01 00 28 00 29 01
  Scala: length = 0x0 (unknown attribute)

