Classfile /Users/mw/Projects/slang-braindump/.jar/jar8/assemble/slang-braindump/assemble/content/org/sireum/logika/package$_Slang$.class
  Last modified May 29, 2022; size 7887 bytes
  SHA-256 checksum 0f04ec12b81accc140b84d0ffb935ef82420da62c7f57767e455718a4617d0eb
  Compiled from "package.scala"
public class org.sireum.logika.package$_Slang$
  minor version: 0
  major version: 52
  flags: (0x0021) ACC_PUBLIC, ACC_SUPER
  this_class: #2                          // org/sireum/logika/package$_Slang$
  super_class: #4                         // java/lang/Object
  interfaces: 0, fields: 1, methods: 25, attributes: 4
Constant pool:
    #1 = Utf8               org/sireum/logika/package$_Slang$
    #2 = Class              #1            // org/sireum/logika/package$_Slang$
    #3 = Utf8               java/lang/Object
    #4 = Class              #3            // java/lang/Object
    #5 = Utf8               package.scala
    #6 = Utf8               org/sireum/F32$$String$
    #7 = Class              #6            // org/sireum/F32$$String$
    #8 = Utf8               org/sireum/F32
    #9 = Class              #8            // org/sireum/F32
   #10 = Utf8               $String$
   #11 = Utf8               org/sireum/F64$$String$
   #12 = Class              #11           // org/sireum/F64$$String$
   #13 = Utf8               org/sireum/F64
   #14 = Class              #13           // org/sireum/F64
   #15 = Utf8               org/sireum/N$$String$
   #16 = Class              #15           // org/sireum/N$$String$
   #17 = Utf8               org/sireum/N
   #18 = Class              #17           // org/sireum/N
   #19 = Utf8               org/sireum/N16$$String$
   #20 = Class              #19           // org/sireum/N16$$String$
   #21 = Utf8               org/sireum/N16
   #22 = Class              #21           // org/sireum/N16
   #23 = Utf8               org/sireum/N32$$String$
   #24 = Class              #23           // org/sireum/N32$$String$
   #25 = Utf8               org/sireum/N32
   #26 = Class              #25           // org/sireum/N32
   #27 = Utf8               org/sireum/N64$$String$
   #28 = Class              #27           // org/sireum/N64$$String$
   #29 = Utf8               org/sireum/N64
   #30 = Class              #29           // org/sireum/N64
   #31 = Utf8               org/sireum/N8$$String$
   #32 = Class              #31           // org/sireum/N8$$String$
   #33 = Utf8               org/sireum/N8
   #34 = Class              #33           // org/sireum/N8
   #35 = Utf8               org/sireum/R$$String$
   #36 = Class              #35           // org/sireum/R$$String$
   #37 = Utf8               org/sireum/R
   #38 = Class              #37           // org/sireum/R
   #39 = Utf8               org/sireum/S16$$String$
   #40 = Class              #39           // org/sireum/S16$$String$
   #41 = Utf8               org/sireum/S16
   #42 = Class              #41           // org/sireum/S16
   #43 = Utf8               org/sireum/S32$$String$
   #44 = Class              #43           // org/sireum/S32$$String$
   #45 = Utf8               org/sireum/S32
   #46 = Class              #45           // org/sireum/S32
   #47 = Utf8               org/sireum/S64$$String$
   #48 = Class              #47           // org/sireum/S64$$String$
   #49 = Utf8               org/sireum/S64
   #50 = Class              #49           // org/sireum/S64
   #51 = Utf8               org/sireum/S8$$String$
   #52 = Class              #51           // org/sireum/S8$$String$
   #53 = Utf8               org/sireum/S8
   #54 = Class              #53           // org/sireum/S8
   #55 = Utf8               org/sireum/U16$$String$
   #56 = Class              #55           // org/sireum/U16$$String$
   #57 = Utf8               org/sireum/U16
   #58 = Class              #57           // org/sireum/U16
   #59 = Utf8               org/sireum/U32$$String$
   #60 = Class              #59           // org/sireum/U32$$String$
   #61 = Utf8               org/sireum/U32
   #62 = Class              #61           // org/sireum/U32
   #63 = Utf8               org/sireum/U64$$String$
   #64 = Class              #63           // org/sireum/U64$$String$
   #65 = Utf8               org/sireum/U64
   #66 = Class              #65           // org/sireum/U64
   #67 = Utf8               org/sireum/U8$$String$
   #68 = Class              #67           // org/sireum/U8$$String$
   #69 = Utf8               org/sireum/U8
   #70 = Class              #69           // org/sireum/U8
   #71 = Utf8               org/sireum/Z$$String$
   #72 = Class              #71           // org/sireum/Z$$String$
   #73 = Utf8               org/sireum/Z
   #74 = Class              #73           // org/sireum/Z
   #75 = Utf8               org/sireum/Z16$$String$
   #76 = Class              #75           // org/sireum/Z16$$String$
   #77 = Utf8               org/sireum/Z16
   #78 = Class              #77           // org/sireum/Z16
   #79 = Utf8               org/sireum/Z32$$String$
   #80 = Class              #79           // org/sireum/Z32$$String$
   #81 = Utf8               org/sireum/Z32
   #82 = Class              #81           // org/sireum/Z32
   #83 = Utf8               org/sireum/Z64$$String$
   #84 = Class              #83           // org/sireum/Z64$$String$
   #85 = Utf8               org/sireum/Z64
   #86 = Class              #85           // org/sireum/Z64
   #87 = Utf8               org/sireum/Z8$$String$
   #88 = Class              #87           // org/sireum/Z8$$String$
   #89 = Utf8               org/sireum/Z8
   #90 = Class              #89           // org/sireum/Z8
   #91 = Utf8               org/sireum/logika/package$_Slang
   #92 = Class              #91           // org/sireum/logika/package$_Slang
   #93 = Utf8               org/sireum/logika/package
   #94 = Class              #93           // org/sireum/logika/package
   #95 = Utf8               _Slang
   #96 = Utf8               _Slang$
   #97 = Utf8               MODULE$
   #98 = Utf8               Lorg/sireum/logika/package$_Slang$;
   #99 = Utf8               <clinit>
  #100 = Utf8               ()V
  #101 = Utf8               <init>
  #102 = NameAndType        #101:#100     // "<init>":()V
  #103 = Methodref          #2.#102       // org/sireum/logika/package$_Slang$."<init>":()V
  #104 = NameAndType        #97:#98       // MODULE$:Lorg/sireum/logika/package$_Slang$;
  #105 = Fieldref           #2.#104       // org/sireum/logika/package$_Slang$.MODULE$:Lorg/sireum/logika/package$_Slang$;
  #106 = Utf8               z$extension
  #107 = Utf8               (Lscala/StringContext;Lscala/collection/immutable/Seq;)Lorg/sireum/Z;
  #108 = Utf8               (Lscala/StringContext;Lscala/collection/immutable/Seq<Ljava/lang/Object;>;)Lorg/sireum/Z;
  #109 = Utf8               $this
  #110 = Utf8               args
  #111 = Utf8               Lorg/sireum/Z$$String$;
  #112 = NameAndType        #97:#111      // MODULE$:Lorg/sireum/Z$$String$;
  #113 = Fieldref           #72.#112      // org/sireum/Z$$String$.MODULE$:Lorg/sireum/Z$$String$;
  #114 = Utf8               scala/StringContext
  #115 = Class              #114          // scala/StringContext
  #116 = Utf8               parts
  #117 = Utf8               ()Lscala/collection/immutable/Seq;
  #118 = NameAndType        #116:#117     // parts:()Lscala/collection/immutable/Seq;
  #119 = Methodref          #115.#118     // scala/StringContext.parts:()Lscala/collection/immutable/Seq;
  #120 = Utf8
  #121 = String             #120          //
  #122 = Utf8               scala/collection/immutable/Seq
  #123 = Class              #122          // scala/collection/immutable/Seq
  #124 = Utf8               mkString
  #125 = Utf8               (Ljava/lang/String;)Ljava/lang/String;
  #126 = NameAndType        #124:#125     // mkString:(Ljava/lang/String;)Ljava/lang/String;
  #127 = InterfaceMethodref #123.#126     // scala/collection/immutable/Seq.mkString:(Ljava/lang/String;)Ljava/lang/String;
  #128 = Utf8               apply
  #129 = Utf8               (Ljava/lang/String;)Lorg/sireum/Z;
  #130 = NameAndType        #128:#129     // apply:(Ljava/lang/String;)Lorg/sireum/Z;
  #131 = Methodref          #72.#130      // org/sireum/Z$$String$.apply:(Ljava/lang/String;)Lorg/sireum/Z;
  #132 = Utf8               this
  #133 = Utf8               Lscala/StringContext;
  #134 = Utf8               Lscala/collection/immutable/Seq;
  #135 = Utf8               z8$extension
  #136 = Utf8               Lorg/sireum/Z8$$String$;
  #137 = NameAndType        #97:#136      // MODULE$:Lorg/sireum/Z8$$String$;
  #138 = Fieldref           #88.#137      // org/sireum/Z8$$String$.MODULE$:Lorg/sireum/Z8$$String$;
  #139 = Methodref          #88.#130      // org/sireum/Z8$$String$.apply:(Ljava/lang/String;)Lorg/sireum/Z;
  #140 = Utf8               z16$extension
  #141 = Utf8               Lorg/sireum/Z16$$String$;
  #142 = NameAndType        #97:#141      // MODULE$:Lorg/sireum/Z16$$String$;
  #143 = Fieldref           #76.#142      // org/sireum/Z16$$String$.MODULE$:Lorg/sireum/Z16$$String$;
  #144 = Methodref          #76.#130      // org/sireum/Z16$$String$.apply:(Ljava/lang/String;)Lorg/sireum/Z;
  #145 = Utf8               z32$extension
  #146 = Utf8               Lorg/sireum/Z32$$String$;
  #147 = NameAndType        #97:#146      // MODULE$:Lorg/sireum/Z32$$String$;
  #148 = Fieldref           #80.#147      // org/sireum/Z32$$String$.MODULE$:Lorg/sireum/Z32$$String$;
  #149 = Methodref          #80.#130      // org/sireum/Z32$$String$.apply:(Ljava/lang/String;)Lorg/sireum/Z;
  #150 = Utf8               z64$extension
  #151 = Utf8               Lorg/sireum/Z64$$String$;
  #152 = NameAndType        #97:#151      // MODULE$:Lorg/sireum/Z64$$String$;
  #153 = Fieldref           #84.#152      // org/sireum/Z64$$String$.MODULE$:Lorg/sireum/Z64$$String$;
  #154 = Methodref          #84.#130      // org/sireum/Z64$$String$.apply:(Ljava/lang/String;)Lorg/sireum/Z;
  #155 = Utf8               n$extension
  #156 = Utf8               Lorg/sireum/N$$String$;
  #157 = NameAndType        #97:#156      // MODULE$:Lorg/sireum/N$$String$;
  #158 = Fieldref           #16.#157      // org/sireum/N$$String$.MODULE$:Lorg/sireum/N$$String$;
  #159 = Methodref          #16.#130      // org/sireum/N$$String$.apply:(Ljava/lang/String;)Lorg/sireum/Z;
  #160 = Utf8               n8$extension
  #161 = Utf8               Lorg/sireum/N8$$String$;
  #162 = NameAndType        #97:#161      // MODULE$:Lorg/sireum/N8$$String$;
  #163 = Fieldref           #32.#162      // org/sireum/N8$$String$.MODULE$:Lorg/sireum/N8$$String$;
  #164 = Methodref          #32.#130      // org/sireum/N8$$String$.apply:(Ljava/lang/String;)Lorg/sireum/Z;
  #165 = Utf8               n16$extension
  #166 = Utf8               Lorg/sireum/N16$$String$;
  #167 = NameAndType        #97:#166      // MODULE$:Lorg/sireum/N16$$String$;
  #168 = Fieldref           #20.#167      // org/sireum/N16$$String$.MODULE$:Lorg/sireum/N16$$String$;
  #169 = Methodref          #20.#130      // org/sireum/N16$$String$.apply:(Ljava/lang/String;)Lorg/sireum/Z;
  #170 = Utf8               n32$extension
  #171 = Utf8               Lorg/sireum/N32$$String$;
  #172 = NameAndType        #97:#171      // MODULE$:Lorg/sireum/N32$$String$;
  #173 = Fieldref           #24.#172      // org/sireum/N32$$String$.MODULE$:Lorg/sireum/N32$$String$;
  #174 = Methodref          #24.#130      // org/sireum/N32$$String$.apply:(Ljava/lang/String;)Lorg/sireum/Z;
  #175 = Utf8               n64$extension
  #176 = Utf8               Lorg/sireum/N64$$String$;
  #177 = NameAndType        #97:#176      // MODULE$:Lorg/sireum/N64$$String$;
  #178 = Fieldref           #28.#177      // org/sireum/N64$$String$.MODULE$:Lorg/sireum/N64$$String$;
  #179 = Methodref          #28.#130      // org/sireum/N64$$String$.apply:(Ljava/lang/String;)Lorg/sireum/Z;
  #180 = Utf8               s8$extension
  #181 = Utf8               (Lscala/StringContext;Lscala/collection/immutable/Seq;)B
  #182 = Utf8               (Lscala/StringContext;Lscala/collection/immutable/Seq<Ljava/lang/Object;>;)B
  #183 = Utf8               Lorg/sireum/S8$$String$;
  #184 = NameAndType        #97:#183      // MODULE$:Lorg/sireum/S8$$String$;
  #185 = Fieldref           #52.#184      // org/sireum/S8$$String$.MODULE$:Lorg/sireum/S8$$String$;
  #186 = Utf8               (Ljava/lang/String;)B
  #187 = NameAndType        #128:#186     // apply:(Ljava/lang/String;)B
  #188 = Methodref          #52.#187      // org/sireum/S8$$String$.apply:(Ljava/lang/String;)B
  #189 = Utf8               s16$extension
  #190 = Utf8               (Lscala/StringContext;Lscala/collection/immutable/Seq;)S
  #191 = Utf8               (Lscala/StringContext;Lscala/collection/immutable/Seq<Ljava/lang/Object;>;)S
  #192 = Utf8               Lorg/sireum/S16$$String$;
  #193 = NameAndType        #97:#192      // MODULE$:Lorg/sireum/S16$$String$;
  #194 = Fieldref           #40.#193      // org/sireum/S16$$String$.MODULE$:Lorg/sireum/S16$$String$;
  #195 = Utf8               (Ljava/lang/String;)S
  #196 = NameAndType        #128:#195     // apply:(Ljava/lang/String;)S
  #197 = Methodref          #40.#196      // org/sireum/S16$$String$.apply:(Ljava/lang/String;)S
  #198 = Utf8               s32$extension
  #199 = Utf8               (Lscala/StringContext;Lscala/collection/immutable/Seq;)I
  #200 = Utf8               (Lscala/StringContext;Lscala/collection/immutable/Seq<Ljava/lang/Object;>;)I
  #201 = Utf8               Lorg/sireum/S32$$String$;
  #202 = NameAndType        #97:#201      // MODULE$:Lorg/sireum/S32$$String$;
  #203 = Fieldref           #44.#202      // org/sireum/S32$$String$.MODULE$:Lorg/sireum/S32$$String$;
  #204 = Utf8               (Ljava/lang/String;)I
  #205 = NameAndType        #128:#204     // apply:(Ljava/lang/String;)I
  #206 = Methodref          #44.#205      // org/sireum/S32$$String$.apply:(Ljava/lang/String;)I
  #207 = Utf8               s64$extension
  #208 = Utf8               (Lscala/StringContext;Lscala/collection/immutable/Seq;)J
  #209 = Utf8               (Lscala/StringContext;Lscala/collection/immutable/Seq<Ljava/lang/Object;>;)J
  #210 = Utf8               Lorg/sireum/S64$$String$;
  #211 = NameAndType        #97:#210      // MODULE$:Lorg/sireum/S64$$String$;
  #212 = Fieldref           #48.#211      // org/sireum/S64$$String$.MODULE$:Lorg/sireum/S64$$String$;
  #213 = Utf8               (Ljava/lang/String;)J
  #214 = NameAndType        #128:#213     // apply:(Ljava/lang/String;)J
  #215 = Methodref          #48.#214      // org/sireum/S64$$String$.apply:(Ljava/lang/String;)J
  #216 = Utf8               u8$extension
  #217 = Utf8               Lorg/sireum/U8$$String$;
  #218 = NameAndType        #97:#217      // MODULE$:Lorg/sireum/U8$$String$;
  #219 = Fieldref           #68.#218      // org/sireum/U8$$String$.MODULE$:Lorg/sireum/U8$$String$;
  #220 = Methodref          #68.#187      // org/sireum/U8$$String$.apply:(Ljava/lang/String;)B
  #221 = Utf8               u16$extension
  #222 = Utf8               Lorg/sireum/U16$$String$;
  #223 = NameAndType        #97:#222      // MODULE$:Lorg/sireum/U16$$String$;
  #224 = Fieldref           #56.#223      // org/sireum/U16$$String$.MODULE$:Lorg/sireum/U16$$String$;
  #225 = Methodref          #56.#196      // org/sireum/U16$$String$.apply:(Ljava/lang/String;)S
  #226 = Utf8               u32$extension
  #227 = Utf8               Lorg/sireum/U32$$String$;
  #228 = NameAndType        #97:#227      // MODULE$:Lorg/sireum/U32$$String$;
  #229 = Fieldref           #60.#228      // org/sireum/U32$$String$.MODULE$:Lorg/sireum/U32$$String$;
  #230 = Methodref          #60.#205      // org/sireum/U32$$String$.apply:(Ljava/lang/String;)I
  #231 = Utf8               u64$extension
  #232 = Utf8               Lorg/sireum/U64$$String$;
  #233 = NameAndType        #97:#232      // MODULE$:Lorg/sireum/U64$$String$;
  #234 = Fieldref           #64.#233      // org/sireum/U64$$String$.MODULE$:Lorg/sireum/U64$$String$;
  #235 = Methodref          #64.#214      // org/sireum/U64$$String$.apply:(Ljava/lang/String;)J
  #236 = Utf8               f32$extension
  #237 = Utf8               (Lscala/StringContext;Lscala/collection/immutable/Seq;)F
  #238 = Utf8               (Lscala/StringContext;Lscala/collection/immutable/Seq<Ljava/lang/Object;>;)F
  #239 = Utf8               Lorg/sireum/F32$$String$;
  #240 = NameAndType        #97:#239      // MODULE$:Lorg/sireum/F32$$String$;
  #241 = Fieldref           #7.#240       // org/sireum/F32$$String$.MODULE$:Lorg/sireum/F32$$String$;
  #242 = Utf8               (Ljava/lang/String;)F
  #243 = NameAndType        #128:#242     // apply:(Ljava/lang/String;)F
  #244 = Methodref          #7.#243       // org/sireum/F32$$String$.apply:(Ljava/lang/String;)F
  #245 = Utf8               f64$extension
  #246 = Utf8               (Lscala/StringContext;Lscala/collection/immutable/Seq;)D
  #247 = Utf8               (Lscala/StringContext;Lscala/collection/immutable/Seq<Ljava/lang/Object;>;)D
  #248 = Utf8               Lorg/sireum/F64$$String$;
  #249 = NameAndType        #97:#248      // MODULE$:Lorg/sireum/F64$$String$;
  #250 = Fieldref           #12.#249      // org/sireum/F64$$String$.MODULE$:Lorg/sireum/F64$$String$;
  #251 = Utf8               (Ljava/lang/String;)D
  #252 = NameAndType        #128:#251     // apply:(Ljava/lang/String;)D
  #253 = Methodref          #12.#252      // org/sireum/F64$$String$.apply:(Ljava/lang/String;)D
  #254 = Utf8               r$extension
  #255 = Utf8               (Lscala/StringContext;Lscala/collection/immutable/Seq;)Lscala/math/BigDecimal;
  #256 = Utf8               (Lscala/StringContext;Lscala/collection/immutable/Seq<Ljava/lang/Object;>;)Lscala/math/BigDecimal;
  #257 = Utf8               Lorg/sireum/R$$String$;
  #258 = NameAndType        #97:#257      // MODULE$:Lorg/sireum/R$$String$;
  #259 = Fieldref           #36.#258      // org/sireum/R$$String$.MODULE$:Lorg/sireum/R$$String$;
  #260 = Utf8               (Ljava/lang/String;)Lscala/math/BigDecimal;
  #261 = NameAndType        #128:#260     // apply:(Ljava/lang/String;)Lscala/math/BigDecimal;
  #262 = Methodref          #36.#261      // org/sireum/R$$String$.apply:(Ljava/lang/String;)Lscala/math/BigDecimal;
  #263 = Utf8               hashCode$extension
  #264 = Utf8               (Lscala/StringContext;)I
  #265 = Utf8               hashCode
  #266 = Utf8               ()I
  #267 = NameAndType        #265:#266     // hashCode:()I
  #268 = Methodref          #115.#267     // scala/StringContext.hashCode:()I
  #269 = Utf8               equals$extension
  #270 = Utf8               (Lscala/StringContext;Ljava/lang/Object;)Z
  #271 = Utf8               x$1
  #272 = Utf8               _sc
  #273 = Utf8               ()Lscala/StringContext;
  #274 = NameAndType        #272:#273     // _sc:()Lscala/StringContext;
  #275 = Methodref          #92.#274      // org/sireum/logika/package$_Slang._sc:()Lscala/StringContext;
  #276 = Utf8               equals
  #277 = Utf8               (Ljava/lang/Object;)Z
  #278 = NameAndType        #276:#277     // equals:(Ljava/lang/Object;)Z
  #279 = Methodref          #4.#278       // java/lang/Object.equals:(Ljava/lang/Object;)Z
  #280 = Utf8               Ljava/lang/Object;
  #281 = Methodref          #4.#102       // java/lang/Object."<init>":()V
  #282 = Utf8               Code
  #283 = Utf8               LineNumberTable
  #284 = Utf8               LocalVariableTable
  #285 = Utf8               Signature
  #286 = Utf8               MethodParameters
  #287 = Utf8               StackMapTable
  #288 = Utf8               InnerClasses
  #289 = Utf8               SourceFile
  #290 = Utf8               ScalaInlineInfo
  #291 = Utf8               Scala
{
  public static final org.sireum.logika.package$_Slang$ MODULE$;
    descriptor: Lorg/sireum/logika/package$_Slang$;
    flags: (0x0019) ACC_PUBLIC, ACC_STATIC, ACC_FINAL

  public static {};
    descriptor: ()V
    flags: (0x0009) ACC_PUBLIC, ACC_STATIC
    Code:
      stack=2, locals=0, args_size=0
         0: new           #2                  // class org/sireum/logika/package$_Slang$
         3: dup
         4: invokespecial #103                // Method "<init>":()V
         7: putstatic     #105                // Field MODULE$:Lorg/sireum/logika/package$_Slang$;
        10: return
      LineNumberTable:
        line 427: 0

  public final org.sireum.Z z$extension(scala.StringContext, scala.collection.immutable.Seq<java.lang.Object>);
    descriptor: (Lscala/StringContext;Lscala/collection/immutable/Seq;)Lorg/sireum/Z;
    flags: (0x0011) ACC_PUBLIC, ACC_FINAL
    Code:
      stack=3, locals=3, args_size=3
         0: getstatic     #113                // Field org/sireum/Z$$String$.MODULE$:Lorg/sireum/Z$$String$;
         3: aload_1
         4: invokevirtual #119                // Method scala/StringContext.parts:()Lscala/collection/immutable/Seq;
         7: ldc           #121                // String
         9: invokeinterface #127,  2          // InterfaceMethod scala/collection/immutable/Seq.mkString:(Ljava/lang/String;)Ljava/lang/String;
        14: invokevirtual #131                // Method org/sireum/Z$$String$.apply:(Ljava/lang/String;)Lorg/sireum/Z;
        17: areturn
      LineNumberTable:
        line 429: 0
      LocalVariableTable:
        Start  Length  Slot  Name   Signature
            0      18     0  this   Lorg/sireum/logika/package$_Slang$;
            0      18     1 $this   Lscala/StringContext;
            0      18     2  args   Lscala/collection/immutable/Seq;
    Signature: #108                         // (Lscala/StringContext;Lscala/collection/immutable/Seq<Ljava/lang/Object;>;)Lorg/sireum/Z;
    MethodParameters:
      Name                           Flags
      $this                          final
      args                           final

  public final org.sireum.Z z8$extension(scala.StringContext, scala.collection.immutable.Seq<java.lang.Object>);
    descriptor: (Lscala/StringContext;Lscala/collection/immutable/Seq;)Lorg/sireum/Z;
    flags: (0x0011) ACC_PUBLIC, ACC_FINAL
    Code:
      stack=3, locals=3, args_size=3
         0: getstatic     #138                // Field org/sireum/Z8$$String$.MODULE$:Lorg/sireum/Z8$$String$;
         3: aload_1
         4: invokevirtual #119                // Method scala/StringContext.parts:()Lscala/collection/immutable/Seq;
         7: ldc           #121                // String
         9: invokeinterface #127,  2          // InterfaceMethod scala/collection/immutable/Seq.mkString:(Ljava/lang/String;)Ljava/lang/String;
        14: invokevirtual #139                // Method org/sireum/Z8$$String$.apply:(Ljava/lang/String;)Lorg/sireum/Z;
        17: areturn
      LineNumberTable:
        line 431: 0
      LocalVariableTable:
        Start  Length  Slot  Name   Signature
            0      18     0  this   Lorg/sireum/logika/package$_Slang$;
            0      18     1 $this   Lscala/StringContext;
            0      18     2  args   Lscala/collection/immutable/Seq;
    Signature: #108                         // (Lscala/StringContext;Lscala/collection/immutable/Seq<Ljava/lang/Object;>;)Lorg/sireum/Z;
    MethodParameters:
      Name                           Flags
      $this                          final
      args                           final

  public final org.sireum.Z z16$extension(scala.StringContext, scala.collection.immutable.Seq<java.lang.Object>);
    descriptor: (Lscala/StringContext;Lscala/collection/immutable/Seq;)Lorg/sireum/Z;
    flags: (0x0011) ACC_PUBLIC, ACC_FINAL
    Code:
      stack=3, locals=3, args_size=3
         0: getstatic     #143                // Field org/sireum/Z16$$String$.MODULE$:Lorg/sireum/Z16$$String$;
         3: aload_1
         4: invokevirtual #119                // Method scala/StringContext.parts:()Lscala/collection/immutable/Seq;
         7: ldc           #121                // String
         9: invokeinterface #127,  2          // InterfaceMethod scala/collection/immutable/Seq.mkString:(Ljava/lang/String;)Ljava/lang/String;
        14: invokevirtual #144                // Method org/sireum/Z16$$String$.apply:(Ljava/lang/String;)Lorg/sireum/Z;
        17: areturn
      LineNumberTable:
        line 433: 0
      LocalVariableTable:
        Start  Length  Slot  Name   Signature
            0      18     0  this   Lorg/sireum/logika/package$_Slang$;
            0      18     1 $this   Lscala/StringContext;
            0      18     2  args   Lscala/collection/immutable/Seq;
    Signature: #108                         // (Lscala/StringContext;Lscala/collection/immutable/Seq<Ljava/lang/Object;>;)Lorg/sireum/Z;
    MethodParameters:
      Name                           Flags
      $this                          final
      args                           final

  public final org.sireum.Z z32$extension(scala.StringContext, scala.collection.immutable.Seq<java.lang.Object>);
    descriptor: (Lscala/StringContext;Lscala/collection/immutable/Seq;)Lorg/sireum/Z;
    flags: (0x0011) ACC_PUBLIC, ACC_FINAL
    Code:
      stack=3, locals=3, args_size=3
         0: getstatic     #148                // Field org/sireum/Z32$$String$.MODULE$:Lorg/sireum/Z32$$String$;
         3: aload_1
         4: invokevirtual #119                // Method scala/StringContext.parts:()Lscala/collection/immutable/Seq;
         7: ldc           #121                // String
         9: invokeinterface #127,  2          // InterfaceMethod scala/collection/immutable/Seq.mkString:(Ljava/lang/String;)Ljava/lang/String;
        14: invokevirtual #149                // Method org/sireum/Z32$$String$.apply:(Ljava/lang/String;)Lorg/sireum/Z;
        17: areturn
      LineNumberTable:
        line 435: 0
      LocalVariableTable:
        Start  Length  Slot  Name   Signature
            0      18     0  this   Lorg/sireum/logika/package$_Slang$;
            0      18     1 $this   Lscala/StringContext;
            0      18     2  args   Lscala/collection/immutable/Seq;
    Signature: #108                         // (Lscala/StringContext;Lscala/collection/immutable/Seq<Ljava/lang/Object;>;)Lorg/sireum/Z;
    MethodParameters:
      Name                           Flags
      $this                          final
      args                           final

  public final org.sireum.Z z64$extension(scala.StringContext, scala.collection.immutable.Seq<java.lang.Object>);
    descriptor: (Lscala/StringContext;Lscala/collection/immutable/Seq;)Lorg/sireum/Z;
    flags: (0x0011) ACC_PUBLIC, ACC_FINAL
    Code:
      stack=3, locals=3, args_size=3
         0: getstatic     #153                // Field org/sireum/Z64$$String$.MODULE$:Lorg/sireum/Z64$$String$;
         3: aload_1
         4: invokevirtual #119                // Method scala/StringContext.parts:()Lscala/collection/immutable/Seq;
         7: ldc           #121                // String
         9: invokeinterface #127,  2          // InterfaceMethod scala/collection/immutable/Seq.mkString:(Ljava/lang/String;)Ljava/lang/String;
        14: invokevirtual #154                // Method org/sireum/Z64$$String$.apply:(Ljava/lang/String;)Lorg/sireum/Z;
        17: areturn
      LineNumberTable:
        line 437: 0
      LocalVariableTable:
        Start  Length  Slot  Name   Signature
            0      18     0  this   Lorg/sireum/logika/package$_Slang$;
            0      18     1 $this   Lscala/StringContext;
            0      18     2  args   Lscala/collection/immutable/Seq;
    Signature: #108                         // (Lscala/StringContext;Lscala/collection/immutable/Seq<Ljava/lang/Object;>;)Lorg/sireum/Z;
    MethodParameters:
      Name                           Flags
      $this                          final
      args                           final

  public final org.sireum.Z n$extension(scala.StringContext, scala.collection.immutable.Seq<java.lang.Object>);
    descriptor: (Lscala/StringContext;Lscala/collection/immutable/Seq;)Lorg/sireum/Z;
    flags: (0x0011) ACC_PUBLIC, ACC_FINAL
    Code:
      stack=3, locals=3, args_size=3
         0: getstatic     #158                // Field org/sireum/N$$String$.MODULE$:Lorg/sireum/N$$String$;
         3: aload_1
         4: invokevirtual #119                // Method scala/StringContext.parts:()Lscala/collection/immutable/Seq;
         7: ldc           #121                // String
         9: invokeinterface #127,  2          // InterfaceMethod scala/collection/immutable/Seq.mkString:(Ljava/lang/String;)Ljava/lang/String;
        14: invokevirtual #159                // Method org/sireum/N$$String$.apply:(Ljava/lang/String;)Lorg/sireum/Z;
        17: areturn
      LineNumberTable:
        line 439: 0
      LocalVariableTable:
        Start  Length  Slot  Name   Signature
            0      18     0  this   Lorg/sireum/logika/package$_Slang$;
            0      18     1 $this   Lscala/StringContext;
            0      18     2  args   Lscala/collection/immutable/Seq;
    Signature: #108                         // (Lscala/StringContext;Lscala/collection/immutable/Seq<Ljava/lang/Object;>;)Lorg/sireum/Z;
    MethodParameters:
      Name                           Flags
      $this                          final
      args                           final

  public final org.sireum.Z n8$extension(scala.StringContext, scala.collection.immutable.Seq<java.lang.Object>);
    descriptor: (Lscala/StringContext;Lscala/collection/immutable/Seq;)Lorg/sireum/Z;
    flags: (0x0011) ACC_PUBLIC, ACC_FINAL
    Code:
      stack=3, locals=3, args_size=3
         0: getstatic     #163                // Field org/sireum/N8$$String$.MODULE$:Lorg/sireum/N8$$String$;
         3: aload_1
         4: invokevirtual #119                // Method scala/StringContext.parts:()Lscala/collection/immutable/Seq;
         7: ldc           #121                // String
         9: invokeinterface #127,  2          // InterfaceMethod scala/collection/immutable/Seq.mkString:(Ljava/lang/String;)Ljava/lang/String;
        14: invokevirtual #164                // Method org/sireum/N8$$String$.apply:(Ljava/lang/String;)Lorg/sireum/Z;
        17: areturn
      LineNumberTable:
        line 441: 0
      LocalVariableTable:
        Start  Length  Slot  Name   Signature
            0      18     0  this   Lorg/sireum/logika/package$_Slang$;
            0      18     1 $this   Lscala/StringContext;
            0      18     2  args   Lscala/collection/immutable/Seq;
    Signature: #108                         // (Lscala/StringContext;Lscala/collection/immutable/Seq<Ljava/lang/Object;>;)Lorg/sireum/Z;
    MethodParameters:
      Name                           Flags
      $this                          final
      args                           final

  public final org.sireum.Z n16$extension(scala.StringContext, scala.collection.immutable.Seq<java.lang.Object>);
    descriptor: (Lscala/StringContext;Lscala/collection/immutable/Seq;)Lorg/sireum/Z;
    flags: (0x0011) ACC_PUBLIC, ACC_FINAL
    Code:
      stack=3, locals=3, args_size=3
         0: getstatic     #168                // Field org/sireum/N16$$String$.MODULE$:Lorg/sireum/N16$$String$;
         3: aload_1
         4: invokevirtual #119                // Method scala/StringContext.parts:()Lscala/collection/immutable/Seq;
         7: ldc           #121                // String
         9: invokeinterface #127,  2          // InterfaceMethod scala/collection/immutable/Seq.mkString:(Ljava/lang/String;)Ljava/lang/String;
        14: invokevirtual #169                // Method org/sireum/N16$$String$.apply:(Ljava/lang/String;)Lorg/sireum/Z;
        17: areturn
      LineNumberTable:
        line 443: 0
      LocalVariableTable:
        Start  Length  Slot  Name   Signature
            0      18     0  this   Lorg/sireum/logika/package$_Slang$;
            0      18     1 $this   Lscala/StringContext;
            0      18     2  args   Lscala/collection/immutable/Seq;
    Signature: #108                         // (Lscala/StringContext;Lscala/collection/immutable/Seq<Ljava/lang/Object;>;)Lorg/sireum/Z;
    MethodParameters:
      Name                           Flags
      $this                          final
      args                           final

  public final org.sireum.Z n32$extension(scala.StringContext, scala.collection.immutable.Seq<java.lang.Object>);
    descriptor: (Lscala/StringContext;Lscala/collection/immutable/Seq;)Lorg/sireum/Z;
    flags: (0x0011) ACC_PUBLIC, ACC_FINAL
    Code:
      stack=3, locals=3, args_size=3
         0: getstatic     #173                // Field org/sireum/N32$$String$.MODULE$:Lorg/sireum/N32$$String$;
         3: aload_1
         4: invokevirtual #119                // Method scala/StringContext.parts:()Lscala/collection/immutable/Seq;
         7: ldc           #121                // String
         9: invokeinterface #127,  2          // InterfaceMethod scala/collection/immutable/Seq.mkString:(Ljava/lang/String;)Ljava/lang/String;
        14: invokevirtual #174                // Method org/sireum/N32$$String$.apply:(Ljava/lang/String;)Lorg/sireum/Z;
        17: areturn
      LineNumberTable:
        line 445: 0
      LocalVariableTable:
        Start  Length  Slot  Name   Signature
            0      18     0  this   Lorg/sireum/logika/package$_Slang$;
            0      18     1 $this   Lscala/StringContext;
            0      18     2  args   Lscala/collection/immutable/Seq;
    Signature: #108                         // (Lscala/StringContext;Lscala/collection/immutable/Seq<Ljava/lang/Object;>;)Lorg/sireum/Z;
    MethodParameters:
      Name                           Flags
      $this                          final
      args                           final

  public final org.sireum.Z n64$extension(scala.StringContext, scala.collection.immutable.Seq<java.lang.Object>);
    descriptor: (Lscala/StringContext;Lscala/collection/immutable/Seq;)Lorg/sireum/Z;
    flags: (0x0011) ACC_PUBLIC, ACC_FINAL
    Code:
      stack=3, locals=3, args_size=3
         0: getstatic     #178                // Field org/sireum/N64$$String$.MODULE$:Lorg/sireum/N64$$String$;
         3: aload_1
         4: invokevirtual #119                // Method scala/StringContext.parts:()Lscala/collection/immutable/Seq;
         7: ldc           #121                // String
         9: invokeinterface #127,  2          // InterfaceMethod scala/collection/immutable/Seq.mkString:(Ljava/lang/String;)Ljava/lang/String;
        14: invokevirtual #179                // Method org/sireum/N64$$String$.apply:(Ljava/lang/String;)Lorg/sireum/Z;
        17: areturn
      LineNumberTable:
        line 447: 0
      LocalVariableTable:
        Start  Length  Slot  Name   Signature
            0      18     0  this   Lorg/sireum/logika/package$_Slang$;
            0      18     1 $this   Lscala/StringContext;
            0      18     2  args   Lscala/collection/immutable/Seq;
    Signature: #108                         // (Lscala/StringContext;Lscala/collection/immutable/Seq<Ljava/lang/Object;>;)Lorg/sireum/Z;
    MethodParameters:
      Name                           Flags
      $this                          final
      args                           final

  public final byte s8$extension(scala.StringContext, scala.collection.immutable.Seq<java.lang.Object>);
    descriptor: (Lscala/StringContext;Lscala/collection/immutable/Seq;)B
    flags: (0x0011) ACC_PUBLIC, ACC_FINAL
    Code:
      stack=3, locals=3, args_size=3
         0: getstatic     #185                // Field org/sireum/S8$$String$.MODULE$:Lorg/sireum/S8$$String$;
         3: aload_1
         4: invokevirtual #119                // Method scala/StringContext.parts:()Lscala/collection/immutable/Seq;
         7: ldc           #121                // String
         9: invokeinterface #127,  2          // InterfaceMethod scala/collection/immutable/Seq.mkString:(Ljava/lang/String;)Ljava/lang/String;
        14: invokevirtual #188                // Method org/sireum/S8$$String$.apply:(Ljava/lang/String;)B
        17: ireturn
      LineNumberTable:
        line 449: 0
      LocalVariableTable:
        Start  Length  Slot  Name   Signature
            0      18     0  this   Lorg/sireum/logika/package$_Slang$;
            0      18     1 $this   Lscala/StringContext;
            0      18     2  args   Lscala/collection/immutable/Seq;
    Signature: #182                         // (Lscala/StringContext;Lscala/collection/immutable/Seq<Ljava/lang/Object;>;)B
    MethodParameters:
      Name                           Flags
      $this                          final
      args                           final

  public final short s16$extension(scala.StringContext, scala.collection.immutable.Seq<java.lang.Object>);
    descriptor: (Lscala/StringContext;Lscala/collection/immutable/Seq;)S
    flags: (0x0011) ACC_PUBLIC, ACC_FINAL
    Code:
      stack=3, locals=3, args_size=3
         0: getstatic     #194                // Field org/sireum/S16$$String$.MODULE$:Lorg/sireum/S16$$String$;
         3: aload_1
         4: invokevirtual #119                // Method scala/StringContext.parts:()Lscala/collection/immutable/Seq;
         7: ldc           #121                // String
         9: invokeinterface #127,  2          // InterfaceMethod scala/collection/immutable/Seq.mkString:(Ljava/lang/String;)Ljava/lang/String;
        14: invokevirtual #197                // Method org/sireum/S16$$String$.apply:(Ljava/lang/String;)S
        17: ireturn
      LineNumberTable:
        line 451: 0
      LocalVariableTable:
        Start  Length  Slot  Name   Signature
            0      18     0  this   Lorg/sireum/logika/package$_Slang$;
            0      18     1 $this   Lscala/StringContext;
            0      18     2  args   Lscala/collection/immutable/Seq;
    Signature: #191                         // (Lscala/StringContext;Lscala/collection/immutable/Seq<Ljava/lang/Object;>;)S
    MethodParameters:
      Name                           Flags
      $this                          final
      args                           final

  public final int s32$extension(scala.StringContext, scala.collection.immutable.Seq<java.lang.Object>);
    descriptor: (Lscala/StringContext;Lscala/collection/immutable/Seq;)I
    flags: (0x0011) ACC_PUBLIC, ACC_FINAL
    Code:
      stack=3, locals=3, args_size=3
         0: getstatic     #203                // Field org/sireum/S32$$String$.MODULE$:Lorg/sireum/S32$$String$;
         3: aload_1
         4: invokevirtual #119                // Method scala/StringContext.parts:()Lscala/collection/immutable/Seq;
         7: ldc           #121                // String
         9: invokeinterface #127,  2          // InterfaceMethod scala/collection/immutable/Seq.mkString:(Ljava/lang/String;)Ljava/lang/String;
        14: invokevirtual #206                // Method org/sireum/S32$$String$.apply:(Ljava/lang/String;)I
        17: ireturn
      LineNumberTable:
        line 453: 0
      LocalVariableTable:
        Start  Length  Slot  Name   Signature
            0      18     0  this   Lorg/sireum/logika/package$_Slang$;
            0      18     1 $this   Lscala/StringContext;
            0      18     2  args   Lscala/collection/immutable/Seq;
    Signature: #200                         // (Lscala/StringContext;Lscala/collection/immutable/Seq<Ljava/lang/Object;>;)I
    MethodParameters:
      Name                           Flags
      $this                          final
      args                           final

  public final long s64$extension(scala.StringContext, scala.collection.immutable.Seq<java.lang.Object>);
    descriptor: (Lscala/StringContext;Lscala/collection/immutable/Seq;)J
    flags: (0x0011) ACC_PUBLIC, ACC_FINAL
    Code:
      stack=3, locals=3, args_size=3
         0: getstatic     #212                // Field org/sireum/S64$$String$.MODULE$:Lorg/sireum/S64$$String$;
         3: aload_1
         4: invokevirtual #119                // Method scala/StringContext.parts:()Lscala/collection/immutable/Seq;
         7: ldc           #121                // String
         9: invokeinterface #127,  2          // InterfaceMethod scala/collection/immutable/Seq.mkString:(Ljava/lang/String;)Ljava/lang/String;
        14: invokevirtual #215                // Method org/sireum/S64$$String$.apply:(Ljava/lang/String;)J
        17: lreturn
      LineNumberTable:
        line 455: 0
      LocalVariableTable:
        Start  Length  Slot  Name   Signature
            0      18     0  this   Lorg/sireum/logika/package$_Slang$;
            0      18     1 $this   Lscala/StringContext;
            0      18     2  args   Lscala/collection/immutable/Seq;
    Signature: #209                         // (Lscala/StringContext;Lscala/collection/immutable/Seq<Ljava/lang/Object;>;)J
    MethodParameters:
      Name                           Flags
      $this                          final
      args                           final

  public final byte u8$extension(scala.StringContext, scala.collection.immutable.Seq<java.lang.Object>);
    descriptor: (Lscala/StringContext;Lscala/collection/immutable/Seq;)B
    flags: (0x0011) ACC_PUBLIC, ACC_FINAL
    Code:
      stack=3, locals=3, args_size=3
         0: getstatic     #219                // Field org/sireum/U8$$String$.MODULE$:Lorg/sireum/U8$$String$;
         3: aload_1
         4: invokevirtual #119                // Method scala/StringContext.parts:()Lscala/collection/immutable/Seq;
         7: ldc           #121                // String
         9: invokeinterface #127,  2          // InterfaceMethod scala/collection/immutable/Seq.mkString:(Ljava/lang/String;)Ljava/lang/String;
        14: invokevirtual #220                // Method org/sireum/U8$$String$.apply:(Ljava/lang/String;)B
        17: ireturn
      LineNumberTable:
        line 457: 0
      LocalVariableTable:
        Start  Length  Slot  Name   Signature
            0      18     0  this   Lorg/sireum/logika/package$_Slang$;
            0      18     1 $this   Lscala/StringContext;
            0      18     2  args   Lscala/collection/immutable/Seq;
    Signature: #182                         // (Lscala/StringContext;Lscala/collection/immutable/Seq<Ljava/lang/Object;>;)B
    MethodParameters:
      Name                           Flags
      $this                          final
      args                           final

  public final short u16$extension(scala.StringContext, scala.collection.immutable.Seq<java.lang.Object>);
    descriptor: (Lscala/StringContext;Lscala/collection/immutable/Seq;)S
    flags: (0x0011) ACC_PUBLIC, ACC_FINAL
    Code:
      stack=3, locals=3, args_size=3
         0: getstatic     #224                // Field org/sireum/U16$$String$.MODULE$:Lorg/sireum/U16$$String$;
         3: aload_1
         4: invokevirtual #119                // Method scala/StringContext.parts:()Lscala/collection/immutable/Seq;
         7: ldc           #121                // String
         9: invokeinterface #127,  2          // InterfaceMethod scala/collection/immutable/Seq.mkString:(Ljava/lang/String;)Ljava/lang/String;
        14: invokevirtual #225                // Method org/sireum/U16$$String$.apply:(Ljava/lang/String;)S
        17: ireturn
      LineNumberTable:
        line 459: 0
      LocalVariableTable:
        Start  Length  Slot  Name   Signature
            0      18     0  this   Lorg/sireum/logika/package$_Slang$;
            0      18     1 $this   Lscala/StringContext;
            0      18     2  args   Lscala/collection/immutable/Seq;
    Signature: #191                         // (Lscala/StringContext;Lscala/collection/immutable/Seq<Ljava/lang/Object;>;)S
    MethodParameters:
      Name                           Flags
      $this                          final
      args                           final

  public final int u32$extension(scala.StringContext, scala.collection.immutable.Seq<java.lang.Object>);
    descriptor: (Lscala/StringContext;Lscala/collection/immutable/Seq;)I
    flags: (0x0011) ACC_PUBLIC, ACC_FINAL
    Code:
      stack=3, locals=3, args_size=3
         0: getstatic     #229                // Field org/sireum/U32$$String$.MODULE$:Lorg/sireum/U32$$String$;
         3: aload_1
         4: invokevirtual #119                // Method scala/StringContext.parts:()Lscala/collection/immutable/Seq;
         7: ldc           #121                // String
         9: invokeinterface #127,  2          // InterfaceMethod scala/collection/immutable/Seq.mkString:(Ljava/lang/String;)Ljava/lang/String;
        14: invokevirtual #230                // Method org/sireum/U32$$String$.apply:(Ljava/lang/String;)I
        17: ireturn
      LineNumberTable:
        line 461: 0
      LocalVariableTable:
        Start  Length  Slot  Name   Signature
            0      18     0  this   Lorg/sireum/logika/package$_Slang$;
            0      18     1 $this   Lscala/StringContext;
            0      18     2  args   Lscala/collection/immutable/Seq;
    Signature: #200                         // (Lscala/StringContext;Lscala/collection/immutable/Seq<Ljava/lang/Object;>;)I
    MethodParameters:
      Name                           Flags
      $this                          final
      args                           final

  public final long u64$extension(scala.StringContext, scala.collection.immutable.Seq<java.lang.Object>);
    descriptor: (Lscala/StringContext;Lscala/collection/immutable/Seq;)J
    flags: (0x0011) ACC_PUBLIC, ACC_FINAL
    Code:
      stack=3, locals=3, args_size=3
         0: getstatic     #234                // Field org/sireum/U64$$String$.MODULE$:Lorg/sireum/U64$$String$;
         3: aload_1
         4: invokevirtual #119                // Method scala/StringContext.parts:()Lscala/collection/immutable/Seq;
         7: ldc           #121                // String
         9: invokeinterface #127,  2          // InterfaceMethod scala/collection/immutable/Seq.mkString:(Ljava/lang/String;)Ljava/lang/String;
        14: invokevirtual #235                // Method org/sireum/U64$$String$.apply:(Ljava/lang/String;)J
        17: lreturn
      LineNumberTable:
        line 463: 0
      LocalVariableTable:
        Start  Length  Slot  Name   Signature
            0      18     0  this   Lorg/sireum/logika/package$_Slang$;
            0      18     1 $this   Lscala/StringContext;
            0      18     2  args   Lscala/collection/immutable/Seq;
    Signature: #209                         // (Lscala/StringContext;Lscala/collection/immutable/Seq<Ljava/lang/Object;>;)J
    MethodParameters:
      Name                           Flags
      $this                          final
      args                           final

  public final float f32$extension(scala.StringContext, scala.collection.immutable.Seq<java.lang.Object>);
    descriptor: (Lscala/StringContext;Lscala/collection/immutable/Seq;)F
    flags: (0x0011) ACC_PUBLIC, ACC_FINAL
    Code:
      stack=3, locals=3, args_size=3
         0: getstatic     #241                // Field org/sireum/F32$$String$.MODULE$:Lorg/sireum/F32$$String$;
         3: aload_1
         4: invokevirtual #119                // Method scala/StringContext.parts:()Lscala/collection/immutable/Seq;
         7: ldc           #121                // String
         9: invokeinterface #127,  2          // InterfaceMethod scala/collection/immutable/Seq.mkString:(Ljava/lang/String;)Ljava/lang/String;
        14: invokevirtual #244                // Method org/sireum/F32$$String$.apply:(Ljava/lang/String;)F
        17: freturn
      LineNumberTable:
        line 465: 0
      LocalVariableTable:
        Start  Length  Slot  Name   Signature
            0      18     0  this   Lorg/sireum/logika/package$_Slang$;
            0      18     1 $this   Lscala/StringContext;
            0      18     2  args   Lscala/collection/immutable/Seq;
    Signature: #238                         // (Lscala/StringContext;Lscala/collection/immutable/Seq<Ljava/lang/Object;>;)F
    MethodParameters:
      Name                           Flags
      $this                          final
      args                           final

  public final double f64$extension(scala.StringContext, scala.collection.immutable.Seq<java.lang.Object>);
    descriptor: (Lscala/StringContext;Lscala/collection/immutable/Seq;)D
    flags: (0x0011) ACC_PUBLIC, ACC_FINAL
    Code:
      stack=3, locals=3, args_size=3
         0: getstatic     #250                // Field org/sireum/F64$$String$.MODULE$:Lorg/sireum/F64$$String$;
         3: aload_1
         4: invokevirtual #119                // Method scala/StringContext.parts:()Lscala/collection/immutable/Seq;
         7: ldc           #121                // String
         9: invokeinterface #127,  2          // InterfaceMethod scala/collection/immutable/Seq.mkString:(Ljava/lang/String;)Ljava/lang/String;
        14: invokevirtual #253                // Method org/sireum/F64$$String$.apply:(Ljava/lang/String;)D
        17: dreturn
      LineNumberTable:
        line 467: 0
      LocalVariableTable:
        Start  Length  Slot  Name   Signature
            0      18     0  this   Lorg/sireum/logika/package$_Slang$;
            0      18     1 $this   Lscala/StringContext;
            0      18     2  args   Lscala/collection/immutable/Seq;
    Signature: #247                         // (Lscala/StringContext;Lscala/collection/immutable/Seq<Ljava/lang/Object;>;)D
    MethodParameters:
      Name                           Flags
      $this                          final
      args                           final

  public final scala.math.BigDecimal r$extension(scala.StringContext, scala.collection.immutable.Seq<java.lang.Object>);
    descriptor: (Lscala/StringContext;Lscala/collection/immutable/Seq;)Lscala/math/BigDecimal;
    flags: (0x0011) ACC_PUBLIC, ACC_FINAL
    Code:
      stack=3, locals=3, args_size=3
         0: getstatic     #259                // Field org/sireum/R$$String$.MODULE$:Lorg/sireum/R$$String$;
         3: aload_1
         4: invokevirtual #119                // Method scala/StringContext.parts:()Lscala/collection/immutable/Seq;
         7: ldc           #121                // String
         9: invokeinterface #127,  2          // InterfaceMethod scala/collection/immutable/Seq.mkString:(Ljava/lang/String;)Ljava/lang/String;
        14: invokevirtual #262                // Method org/sireum/R$$String$.apply:(Ljava/lang/String;)Lscala/math/BigDecimal;
        17: areturn
      LineNumberTable:
        line 469: 0
      LocalVariableTable:
        Start  Length  Slot  Name   Signature
            0      18     0  this   Lorg/sireum/logika/package$_Slang$;
            0      18     1 $this   Lscala/StringContext;
            0      18     2  args   Lscala/collection/immutable/Seq;
    Signature: #256                         // (Lscala/StringContext;Lscala/collection/immutable/Seq<Ljava/lang/Object;>;)Lscala/math/BigDecimal;
    MethodParameters:
      Name                           Flags
      $this                          final
      args                           final

  public final int hashCode$extension(scala.StringContext);
    descriptor: (Lscala/StringContext;)I
    flags: (0x0011) ACC_PUBLIC, ACC_FINAL
    Code:
      stack=1, locals=2, args_size=2
         0: aload_1
         1: invokevirtual #268                // Method scala/StringContext.hashCode:()I
         4: ireturn
      LineNumberTable:
        line 427: 0
      LocalVariableTable:
        Start  Length  Slot  Name   Signature
            0       5     0  this   Lorg/sireum/logika/package$_Slang$;
            0       5     1 $this   Lscala/StringContext;
    MethodParameters:
      Name                           Flags
      $this                          final

  public final boolean equals$extension(scala.StringContext, java.lang.Object);
    descriptor: (Lscala/StringContext;Ljava/lang/Object;)Z
    flags: (0x0011) ACC_PUBLIC, ACC_FINAL
    Code:
      stack=2, locals=7, args_size=3
         0: aload_2
         1: astore        4
         3: aload         4
         5: instanceof    #92                 // class org/sireum/logika/package$_Slang
         8: ifeq          16
        11: iconst_1
        12: istore_3
        13: goto          24
        16: goto          19
        19: iconst_0
        20: istore_3
        21: goto          24
        24: iload_3
        25: ifeq          83
        28: aload_2
        29: ifnonnull     36
        32: aconst_null
        33: goto          43
        36: aload_2
        37: checkcast     #92                 // class org/sireum/logika/package$_Slang
        40: invokevirtual #275                // Method org/sireum/logika/package$_Slang._sc:()Lscala/StringContext;
        43: astore        5
        45: aload_1
        46: aload         5
        48: astore        6
        50: dup
        51: ifnonnull     63
        54: pop
        55: aload         6
        57: ifnull        71
        60: goto          75
        63: aload         6
        65: invokevirtual #279                // Method java/lang/Object.equals:(Ljava/lang/Object;)Z
        68: ifeq          75
        71: iconst_1
        72: goto          76
        75: iconst_0
        76: ifeq          83
        79: iconst_1
        80: goto          84
        83: iconst_0
        84: ireturn
      StackMapTable: number_of_entries = 11
        frame_type = 253 /* append */
          offset_delta = 16
          locals = [ top, class java/lang/Object ]
        frame_type = 2 /* same */
        frame_type = 255 /* full_frame */
          offset_delta = 4
          locals = [ class org/sireum/logika/package$_Slang$, class scala/StringContext, class java/lang/Object, int, class java/lang/Object ]
          stack = []
        frame_type = 11 /* same */
        frame_type = 70 /* same_locals_1_stack_item */
          stack = [ class scala/StringContext ]
        frame_type = 255 /* full_frame */
          offset_delta = 19
          locals = [ class org/sireum/logika/package$_Slang$, class scala/StringContext, class java/lang/Object, int, class java/lang/Object, class scala/StringContext, class scala/StringContext ]
          stack = [ class scala/StringContext ]
        frame_type = 7 /* same */
        frame_type = 3 /* same */
        frame_type = 64 /* same_locals_1_stack_item */
          stack = [ int ]
        frame_type = 249 /* chop */
          offset_delta = 6
        frame_type = 64 /* same_locals_1_stack_item */
          stack = [ int ]
      LineNumberTable:
        line 427: 0
      LocalVariableTable:
        Start  Length  Slot  Name   Signature
            0      85     0  this   Lorg/sireum/logika/package$_Slang$;
            0      85     1 $this   Lscala/StringContext;
            0      85     2   x$1   Ljava/lang/Object;
    MethodParameters:
      Name                           Flags
      $this                          final
      x$1                            final

  public org.sireum.logika.package$_Slang$();
    descriptor: ()V
    flags: (0x0001) ACC_PUBLIC
    Code:
      stack=1, locals=1, args_size=1
         0: aload_0
         1: invokespecial #281                // Method java/lang/Object."<init>":()V
         4: return
      LineNumberTable:
        line 427: 0
      LocalVariableTable:
        Start  Length  Slot  Name   Signature
            0       5     0  this   Lorg/sireum/logika/package$_Slang$;
}
InnerClasses:
  public static #10= #7 of #9;            // $String$=class org/sireum/F32$$String$ of class org/sireum/F32
  public static #10= #12 of #14;          // $String$=class org/sireum/F64$$String$ of class org/sireum/F64
  public static #10= #16 of #18;          // $String$=class org/sireum/N$$String$ of class org/sireum/N
  public static #10= #20 of #22;          // $String$=class org/sireum/N16$$String$ of class org/sireum/N16
  public static #10= #24 of #26;          // $String$=class org/sireum/N32$$String$ of class org/sireum/N32
  public static #10= #28 of #30;          // $String$=class org/sireum/N64$$String$ of class org/sireum/N64
  public static #10= #32 of #34;          // $String$=class org/sireum/N8$$String$ of class org/sireum/N8
  public static #10= #36 of #38;          // $String$=class org/sireum/R$$String$ of class org/sireum/R
  public static #10= #40 of #42;          // $String$=class org/sireum/S16$$String$ of class org/sireum/S16
  public static #10= #44 of #46;          // $String$=class org/sireum/S32$$String$ of class org/sireum/S32
  public static #10= #48 of #50;          // $String$=class org/sireum/S64$$String$ of class org/sireum/S64
  public static #10= #52 of #54;          // $String$=class org/sireum/S8$$String$ of class org/sireum/S8
  public static #10= #56 of #58;          // $String$=class org/sireum/U16$$String$ of class org/sireum/U16
  public static #10= #60 of #62;          // $String$=class org/sireum/U32$$String$ of class org/sireum/U32
  public static #10= #64 of #66;          // $String$=class org/sireum/U64$$String$ of class org/sireum/U64
  public static #10= #68 of #70;          // $String$=class org/sireum/U8$$String$ of class org/sireum/U8
  public static #10= #72 of #74;          // $String$=class org/sireum/Z$$String$ of class org/sireum/Z
  public static #10= #76 of #78;          // $String$=class org/sireum/Z16$$String$ of class org/sireum/Z16
  public static #10= #80 of #82;          // $String$=class org/sireum/Z32$$String$ of class org/sireum/Z32
  public static #10= #84 of #86;          // $String$=class org/sireum/Z64$$String$ of class org/sireum/Z64
  public static #10= #88 of #90;          // $String$=class org/sireum/Z8$$String$ of class org/sireum/Z8
  public static final #95= #92 of #94;    // _Slang=class org/sireum/logika/package$_Slang of class org/sireum/logika/package
  public static #96= #2 of #94;           // _Slang$=class org/sireum/logika/package$_Slang$ of class org/sireum/logika/package
SourceFile: "package.scala"
  ScalaInlineInfo: length = 0x7C (unknown attribute)
   01 01 00 18 00 65 00 64 01 01 0D 01 0E 01 00 EC
   00 ED 01 00 F5 00 F6 01 01 07 01 08 01 00 9B 00
   6B 01 00 A5 00 6B 01 00 AA 00 6B 01 00 AF 00 6B
   01 00 A0 00 6B 01 00 FE 00 FF 01 00 BD 00 BE 01
   00 C6 00 C7 01 00 CF 00 D0 01 00 B4 00 B5 01 00
   DD 00 BE 01 00 E2 00 C7 01 00 E7 00 D0 01 00 D8
   00 B5 01 00 6A 00 6B 01 00 8C 00 6B 01 00 91 00
   6B 01 00 96 00 6B 01 00 87 00 6B 01
  Scala: length = 0x0 (unknown attribute)

