Classfile /Users/mw/Projects/slang-braindump/.jar/jar11/assemble/slang-braindump/assemble/content/scala/xml/Attribute.class
  Last modified May 29, 2022; size 8242 bytes
  SHA-256 checksum a8274aa7faf812aa53cf9f078be3dd9c154999e11f95852321f868325259532a
  Compiled from "Attribute.scala"
public interface scala.xml.Attribute
  minor version: 0
  major version: 52
  flags: (0x0601) ACC_PUBLIC, ACC_INTERFACE, ACC_ABSTRACT
  this_class: #2                          // scala/xml/Attribute
  super_class: #4                         // java/lang/Object
  interfaces: 0, fields: 0, methods: 26, attributes: 6
Constant pool:
    #1 = Utf8               scala/xml/Attribute
    #2 = Class              #1            // scala/xml/Attribute
    #3 = Utf8               java/lang/Object
    #4 = Class              #3            // java/lang/Object
    #5 = Utf8               Attribute.scala
    #6 = Utf8               Lscala/reflect/ScalaSignature;
    #7 = Utf8               bytes
    #8 = Utf8               \u0006\u0005\u0005%t!\u0002\u000e\u001c\u0011\u0003\u0001c!\u0002\u0012\u001c\u0011\u0003\u0019\u0003\"\u0002\u0019\u0002\t\u0003\t\u0004\"\u0002\u001a\u0002\t\u0003\u0019\u0004BB1\u0002\t\u0003\t\t\u0004\u0003\u0004b\u0003\u0011\u0005\u0011\u0011\b\u0005\u0007C\u0006!\t!a\u0011\t\r\u0005\fA\u0011AA\'\u0011%\tI&AA\u0001\n\u0013\tYFB\u0004#7A\u0005\u0019\u0011\u0001+\t\u000bUKA\u0011\u0001,\t\u000biKa\u0011A.\t\u000fqK!\u0019!D\u00017\"9Q,\u0003b\u0001\u000e\u0003q\u0006bB0\n\u0005\u00045\t\u0001\u0019\u0005\u0006C&1\tA\u0019\u0005\u0006C&1\t\u0001\u001a\u0005\u0006[&1\tA\u001c\u0005\u0006a&!\t!\u001d\u0005\u0006a&!\ta\u001d\u0005\u0006o&!\t\u0001\u001f\u0005\u0006y&1\t! \u0005\b\u0003\u0003IA\u0011AA\u0002\u0011\u001d\t9!\u0003C!\u0003\u0013Aq!!\u0007\n\t\u0003\nY\u0002C\u0004\u0002$%!\t\"!\n\u0002\u0013\u0005#HO]5ckR,\'B\u0001\u000f\u001e\u0003\rAX\u000e\u001c\u0006\u0002=\u0005)1oY1mC\u000e\u0001\u0001CA\u0011\u0002\u001b\u0005Y\"!C!uiJL\'-\u001e;f\'\r\tA\u0005\u000b\t\u0003K\u0019j\u0011!H\u0005\u0003Ou\u0011a!\u00118z%\u00164\u0007CA\u0015/\u001b\u0005Q#BA\u0016-\u0003\tIwNC\u0001.\u0003\u0011Q\u0017M^1\n\u0005=R#\u0001D*fe&\fG.\u001b>bE2,\u0017A\u0002\u001fj]&$h\bF\u0001!\u0003\u001d)h.\u00199qYf$\"\u0001N)\u0011\u0007\u0015*t\'\u0003\u00027;\t1q\n\u001d;j_:\u0004R!\n\u001d;\u000b:K!!O\u000f\u0003\rQ+\b\u000f\\34!\tY$I\u0004\u0002=\u0001B\u0011Q(H\u0007\u0002})\u0011qhH\u0001\u0007yI|w\u000e\u001e \n\u0005\u0005k\u0012A\u0002)sK\u0012,g-\u0003\u0002D\t\n11\u000b\u001e:j]\u001eT!!Q\u000f\u0011\u0007\u0019K5*D\u0001H\u0015\tAU$\u0001\u0006d_2dWm\u0019;j_:L!AS$\u0003\u0007M+\u0017\u000f\u0005\u0002\"\u0019&\u0011Qj\u0007\u0002\u0005\u001d>$W\r\u0005\u0002\"\u001f&\u0011\u0001k\u0007\u0002\t\u001b\u0016$\u0018\rR1uC\")!k\u0001a\u0001\'\u0006\t\u0001\u0010\u0005\u0002\"\u0013M\u0011\u0011BT\u0001\u0007I%t\u0017\u000e\u001e\u0013\u0015\u0003]\u0003\"!\n-\n\u0005ek\"\u0001B+oSR\f1\u0001\u001d:f+\u0005Q\u0014aA6fs\u0006)a/\u00197vKV\tQ)\u0001\u0003oKb$X#\u0001(\u0002\u000b\u0005\u0004\b\u000f\\=\u0015\u0005\u0015\u001b\u0007\"\u0002/\u0010\u0001\u0004QD\u0003B#fO2DQA\u001a\tA\u0002i\n\u0011B\\1nKN\u0004\u0018mY3\t\u000b!\u0004\u0002\u0019A5\u0002\u000bM\u001cw\u000e]3\u0011\u0005\u0005R\u0017BA6\u001c\u0005Aq\u0015-\\3ta\u0006\u001cWMQ5oI&tw\rC\u0003]!\u0001\u0007!(\u0001\u0003d_BLHCA*p\u0011\u0015y\u0016\u00031\u0001O\u0003\u0019\u0011X-\\8wKR\u0011aJ\u001d\u0005\u00069J\u0001\rA\u000f\u000b\u0005\u001dR,h\u000fC\u0003g\'\u0001\u0007!\bC\u0003i\'\u0001\u0007\u0011\u000eC\u0003]\'\u0001\u0007!(\u0001\u0006jgB\u0013XMZ5yK\u0012,\u0012!\u001f\t\u0003KiL!a_\u000f\u0003\u000f\t{w\u000e\\3b]\u0006aq-\u001a;OC6,7\u000f]1dKR\u0011!H \u0005\u0006\u007fV\u0001\raS\u0001\u0006_^tWM]\u0001\u000bo\u0016dGNZ8s[\u0016$GcA=\u0002\u0006!)\u0001N\u0006a\u0001S\u0006A\u0011\u000e^3sCR|\'/\u0006\u0002\u0002\fA)\u0011QBA\n\u001d:\u0019Q%a\u0004\n\u0007\u0005EQ$A\u0004qC\u000e\\\u0017mZ3\n\t\u0005U\u0011q\u0003\u0002\t\u0013R,\'/\u0019;pe*\u0019\u0011\u0011C\u000f\u0002\tML\'0Z\u000b\u0003\u0003;\u00012!JA\u0010\u0013\r\t\t#\b\u0002\u0004\u0013:$\u0018!\u0003;p\'R\u0014\u0018N\\42)\r9\u0016q\u0005\u0005\b\u0003SI\u0002\u0019AA\u0016\u0003\t\u0019(\r\u0005\u0003\u0002\u000e\u00055\u0012\u0002BA\u0018\u0003/\u0011Qb\u0015;sS:<\')^5mI\u0016\u0014HcB*\u00024\u0005U\u0012q\u0007\u0005\u00069\u0012\u0001\rA\u000f\u0005\u0006;\u0012\u0001\r!\u0012\u0005\u0006?\u0012\u0001\rA\u0014\u000b\n\'\u0006m\u0012QHA \u0003\u0003BQAW\u0003A\u0002iBQ\u0001X\u0003A\u0002iBQ!X\u0003A\u0002iBQaX\u0003A\u00029#\u0012bUA#\u0003\u000f\nI%a\u0013\t\u000bi3\u0001\u0019\u0001\u001e\t\u000bq3\u0001\u0019\u0001\u001e\t\u000bu3\u0001\u0019A#\t\u000b}3\u0001\u0019\u0001(\u0015\u0013M\u000by%a\u0015\u0002V\u0005]\u0003B\u0002.\b\u0001\u0004\t\t\u0006E\u0002&kiBQ\u0001X\u0004A\u0002iBQ!X\u0004A\u0002\u0015CQaX\u0004A\u00029\u000bAb\u001e:ji\u0016\u0014V\r\u001d7bG\u0016$\"!!\u0018\u0011\t\u0005}\u0013QM\u0007\u0003\u0003CR1!a\u0019-\u0003\u0011a\u0017M\\4\n\t\u0005\u001d\u0014\u0011\r\u0002\u0007\u001f\nTWm\u0019;
    #9 = Utf8               java/lang/invoke/MethodHandles$Lookup
   #10 = Class              #9            // java/lang/invoke/MethodHandles$Lookup
   #11 = Utf8               java/lang/invoke/MethodHandles
   #12 = Class              #11           // java/lang/invoke/MethodHandles
   #13 = Utf8               Lookup
   #14 = Utf8               scala/Enumeration$Value
   #15 = Class              #14           // scala/Enumeration$Value
   #16 = Utf8               scala/Enumeration
   #17 = Class              #16           // scala/Enumeration
   #18 = Utf8               Value
   #19 = Utf8               unapply
   #20 = Utf8               (Lscala/xml/Attribute;)Lscala/Option;
   #21 = Utf8               (Lscala/xml/Attribute;)Lscala/Option<Lscala/Tuple3<Ljava/lang/String;Lscala/collection/Seq<Lscala/xml/Node;>;Lscala/xml/MetaData;>;>;
   #22 = Utf8               x
   #23 = Utf8               scala/xml/Attribute$
   #24 = Class              #23           // scala/xml/Attribute$
   #25 = Utf8               MODULE$
   #26 = Utf8               Lscala/xml/Attribute$;
   #27 = NameAndType        #25:#26       // MODULE$:Lscala/xml/Attribute$;
   #28 = Fieldref           #24.#27       // scala/xml/Attribute$.MODULE$:Lscala/xml/Attribute$;
   #29 = NameAndType        #19:#20       // unapply:(Lscala/xml/Attribute;)Lscala/Option;
   #30 = Methodref          #24.#29       // scala/xml/Attribute$.unapply:(Lscala/xml/Attribute;)Lscala/Option;
   #31 = Utf8               Lscala/xml/Attribute;
   #32 = Utf8               pre
   #33 = Utf8               ()Ljava/lang/String;
   #34 = Utf8               key
   #35 = Utf8               value
   #36 = Utf8               ()Lscala/collection/Seq;
   #37 = Utf8               ()Lscala/collection/Seq<Lscala/xml/Node;>;
   #38 = Utf8               next
   #39 = Utf8               ()Lscala/xml/MetaData;
   #40 = Utf8               apply
   #41 = Utf8               (Ljava/lang/String;)Lscala/collection/Seq;
   #42 = Utf8               (Ljava/lang/String;)Lscala/collection/Seq<Lscala/xml/Node;>;
   #43 = Utf8               (Ljava/lang/String;Lscala/xml/NamespaceBinding;Ljava/lang/String;)Lscala/collection/Seq;
   #44 = Utf8               (Ljava/lang/String;Lscala/xml/NamespaceBinding;Ljava/lang/String;)Lscala/collection/Seq<Lscala/xml/Node;>;
   #45 = Utf8               namespace
   #46 = Utf8               scope
   #47 = Utf8               copy
   #48 = Utf8               (Lscala/xml/MetaData;)Lscala/xml/Attribute;
   #49 = Utf8               remove$
   #50 = Utf8               (Lscala/xml/Attribute;Ljava/lang/String;)Lscala/xml/MetaData;
   #51 = Utf8               $this
   #52 = Utf8               remove
   #53 = Utf8               (Ljava/lang/String;)Lscala/xml/MetaData;
   #54 = NameAndType        #52:#53       // remove:(Ljava/lang/String;)Lscala/xml/MetaData;
   #55 = InterfaceMethodref #2.#54        // scala/xml/Attribute.remove:(Ljava/lang/String;)Lscala/xml/MetaData;
   #56 = Utf8               Ljava/lang/String;
   #57 = Utf8               isPrefixed
   #58 = Utf8               ()Z
   #59 = NameAndType        #57:#58       // isPrefixed:()Z
   #60 = InterfaceMethodref #2.#59        // scala/xml/Attribute.isPrefixed:()Z
   #61 = NameAndType        #34:#33       // key:()Ljava/lang/String;
   #62 = InterfaceMethodref #2.#61        // scala/xml/Attribute.key:()Ljava/lang/String;
   #63 = Utf8               equals
   #64 = Utf8               (Ljava/lang/Object;)Z
   #65 = NameAndType        #63:#64       // equals:(Ljava/lang/Object;)Z
   #66 = Methodref          #4.#65        // java/lang/Object.equals:(Ljava/lang/Object;)Z
   #67 = NameAndType        #38:#39       // next:()Lscala/xml/MetaData;
   #68 = InterfaceMethodref #2.#67        // scala/xml/Attribute.next:()Lscala/xml/MetaData;
   #69 = Utf8               scala/xml/MetaData
   #70 = Class              #69           // scala/xml/MetaData
   #71 = Methodref          #70.#54       // scala/xml/MetaData.remove:(Ljava/lang/String;)Lscala/xml/MetaData;
   #72 = NameAndType        #47:#48       // copy:(Lscala/xml/MetaData;)Lscala/xml/Attribute;
   #73 = InterfaceMethodref #2.#72        // scala/xml/Attribute.copy:(Lscala/xml/MetaData;)Lscala/xml/Attribute;
   #74 = Utf8               this
   #75 = Utf8               java/lang/String
   #76 = Class              #75           // java/lang/String
   #77 = Utf8               (Lscala/xml/Attribute;Ljava/lang/String;Lscala/xml/NamespaceBinding;Ljava/lang/String;)Lscala/xml/MetaData;
   #78 = Utf8               (Ljava/lang/String;Lscala/xml/NamespaceBinding;Ljava/lang/String;)Lscala/xml/MetaData;
   #79 = NameAndType        #52:#78       // remove:(Ljava/lang/String;Lscala/xml/NamespaceBinding;Ljava/lang/String;)Lscala/xml/MetaData;
   #80 = InterfaceMethodref #2.#79        // scala/xml/Attribute.remove:(Ljava/lang/String;Lscala/xml/NamespaceBinding;Ljava/lang/String;)Lscala/xml/MetaData;
   #81 = Utf8               Lscala/xml/NamespaceBinding;
   #82 = NameAndType        #32:#33       // pre:()Ljava/lang/String;
   #83 = InterfaceMethodref #2.#82        // scala/xml/Attribute.pre:()Ljava/lang/String;
   #84 = Utf8               scala/xml/NamespaceBinding
   #85 = Class              #84           // scala/xml/NamespaceBinding
   #86 = Utf8               getURI
   #87 = Utf8               (Ljava/lang/String;)Ljava/lang/String;
   #88 = NameAndType        #86:#87       // getURI:(Ljava/lang/String;)Ljava/lang/String;
   #89 = Methodref          #85.#88       // scala/xml/NamespaceBinding.getURI:(Ljava/lang/String;)Ljava/lang/String;
   #90 = Methodref          #70.#79       // scala/xml/MetaData.remove:(Ljava/lang/String;Lscala/xml/NamespaceBinding;Ljava/lang/String;)Lscala/xml/MetaData;
   #91 = Utf8               isPrefixed$
   #92 = Utf8               (Lscala/xml/Attribute;)Z
   #93 = Utf8               getNamespace
   #94 = Utf8               (Lscala/xml/Node;)Ljava/lang/String;
   #95 = Utf8               owner
   #96 = Utf8               wellformed$
   #97 = Utf8               (Lscala/xml/Attribute;Lscala/xml/NamespaceBinding;)Z
   #98 = Utf8               wellformed
   #99 = Utf8               (Lscala/xml/NamespaceBinding;)Z
  #100 = NameAndType        #98:#99       // wellformed:(Lscala/xml/NamespaceBinding;)Z
  #101 = InterfaceMethodref #2.#100       // scala/xml/Attribute.wellformed:(Lscala/xml/NamespaceBinding;)Z
  #102 = NameAndType        #40:#43       // apply:(Ljava/lang/String;Lscala/xml/NamespaceBinding;Ljava/lang/String;)Lscala/collection/Seq;
  #103 = Methodref          #70.#102      // scala/xml/MetaData.apply:(Ljava/lang/String;Lscala/xml/NamespaceBinding;Ljava/lang/String;)Lscala/collection/Seq;
  #104 = Methodref          #70.#100      // scala/xml/MetaData.wellformed:(Lscala/xml/NamespaceBinding;)Z
  #105 = Utf8               arg
  #106 = Utf8               iterator$
  #107 = Utf8               (Lscala/xml/Attribute;)Lscala/collection/Iterator;
  #108 = Utf8               iterator
  #109 = Utf8               ()Lscala/collection/Iterator;
  #110 = NameAndType        #108:#109     // iterator:()Lscala/collection/Iterator;
  #111 = InterfaceMethodref #2.#110       // scala/xml/Attribute.iterator:()Lscala/collection/Iterator;
  #112 = Utf8               ()Lscala/collection/Iterator<Lscala/xml/MetaData;>;
  #113 = NameAndType        #35:#36       // value:()Lscala/collection/Seq;
  #114 = InterfaceMethodref #2.#113       // scala/xml/Attribute.value:()Lscala/collection/Seq;
  #115 = Methodref          #70.#110      // scala/xml/MetaData.iterator:()Lscala/collection/Iterator;
  #116 = Utf8               scala/package$
  #117 = Class              #116          // scala/package$
  #118 = Utf8               Lscala/package$;
  #119 = NameAndType        #25:#118      // MODULE$:Lscala/package$;
  #120 = Fieldref           #117.#119     // scala/package$.MODULE$:Lscala/package$;
  #121 = Utf8               Iterator
  #122 = Utf8               ()Lscala/collection/Iterator$;
  #123 = NameAndType        #121:#122     // Iterator:()Lscala/collection/Iterator$;
  #124 = Methodref          #117.#123     // scala/package$.Iterator:()Lscala/collection/Iterator$;
  #125 = Utf8               scala/collection/Iterator$
  #126 = Class              #125          // scala/collection/Iterator$
  #127 = Utf8               single
  #128 = Utf8               (Ljava/lang/Object;)Lscala/collection/Iterator;
  #129 = NameAndType        #127:#128     // single:(Ljava/lang/Object;)Lscala/collection/Iterator;
  #130 = Methodref          #126.#129     // scala/collection/Iterator$.single:(Ljava/lang/Object;)Lscala/collection/Iterator;
  #131 = Utf8               ()Ljava/lang/Object;
  #132 = MethodType         #131          //  ()Ljava/lang/Object;
  #133 = Utf8               $anonfun$iterator$1
  #134 = NameAndType        #133:#107     // $anonfun$iterator$1:(Lscala/xml/Attribute;)Lscala/collection/Iterator;
  #135 = InterfaceMethodref #2.#134       // scala/xml/Attribute.$anonfun$iterator$1:(Lscala/xml/Attribute;)Lscala/collection/Iterator;
  #136 = MethodHandle       6:#135        // REF_invokeStatic scala/xml/Attribute.$anonfun$iterator$1:(Lscala/xml/Attribute;)Lscala/collection/Iterator;
  #137 = MethodType         #109          //  ()Lscala/collection/Iterator;
  #138 = Integer            5
  #139 = Integer            1
  #140 = Utf8               java/lang/invoke/LambdaMetafactory
  #141 = Class              #140          // java/lang/invoke/LambdaMetafactory
  #142 = Utf8               altMetafactory
  #143 = Utf8               (Ljava/lang/invoke/MethodHandles$Lookup;Ljava/lang/String;Ljava/lang/invoke/MethodType;[Ljava/lang/Object;)Ljava/lang/invoke/CallSite;
  #144 = NameAndType        #142:#143     // altMetafactory:(Ljava/lang/invoke/MethodHandles$Lookup;Ljava/lang/String;Ljava/lang/invoke/MethodType;[Ljava/lang/Object;)Ljava/lang/invoke/CallSite;
  #145 = Methodref          #141.#144     // java/lang/invoke/LambdaMetafactory.altMetafactory:(Ljava/lang/invoke/MethodHandles$Lookup;Ljava/lang/String;Ljava/lang/invoke/MethodType;[Ljava/lang/Object;)Ljava/lang/invoke/CallSite;
  #146 = MethodHandle       6:#145        // REF_invokeStatic java/lang/invoke/LambdaMetafactory.altMetafactory:(Ljava/lang/invoke/MethodHandles$Lookup;Ljava/lang/String;Ljava/lang/invoke/MethodType;[Ljava/lang/Object;)Ljava/lang/invoke/CallSite;
  #147 = Utf8               (Lscala/xml/Attribute;)Lscala/Function0;
  #148 = NameAndType        #40:#147      // apply:(Lscala/xml/Attribute;)Lscala/Function0;
  #149 = InvokeDynamic      #0:#148       // #0:apply:(Lscala/xml/Attribute;)Lscala/Function0;
  #150 = Utf8               scala/collection/Iterator
  #151 = Class              #150          // scala/collection/Iterator
  #152 = Utf8               $plus$plus
  #153 = Utf8               (Lscala/Function0;)Lscala/collection/Iterator;
  #154 = NameAndType        #152:#153     // $plus$plus:(Lscala/Function0;)Lscala/collection/Iterator;
  #155 = InterfaceMethodref #151.#154     // scala/collection/Iterator.$plus$plus:(Lscala/Function0;)Lscala/collection/Iterator;
  #156 = Utf8               size$
  #157 = Utf8               (Lscala/xml/Attribute;)I
  #158 = Utf8               size
  #159 = Utf8               ()I
  #160 = NameAndType        #158:#159     // size:()I
  #161 = InterfaceMethodref #2.#160       // scala/xml/Attribute.size:()I
  #162 = Methodref          #70.#160      // scala/xml/MetaData.size:()I
  #163 = Utf8               toString1$
  #164 = Utf8               (Lscala/xml/Attribute;Lscala/collection/mutable/StringBuilder;)V
  #165 = Utf8               sb
  #166 = Utf8               toString1
  #167 = Utf8               (Lscala/collection/mutable/StringBuilder;)V
  #168 = NameAndType        #166:#167     // toString1:(Lscala/collection/mutable/StringBuilder;)V
  #169 = InterfaceMethodref #2.#168       // scala/xml/Attribute.toString1:(Lscala/collection/mutable/StringBuilder;)V
  #170 = Utf8               Lscala/collection/mutable/StringBuilder;
  #171 = Utf8               scala/collection/mutable/StringBuilder
  #172 = Class              #171          // scala/collection/mutable/StringBuilder
  #173 = Utf8               append
  #174 = Utf8               (Ljava/lang/String;)Lscala/collection/mutable/StringBuilder;
  #175 = NameAndType        #173:#174     // append:(Ljava/lang/String;)Lscala/collection/mutable/StringBuilder;
  #176 = Methodref          #172.#175     // scala/collection/mutable/StringBuilder.append:(Ljava/lang/String;)Lscala/collection/mutable/StringBuilder;
  #177 = Utf8               (C)Lscala/collection/mutable/StringBuilder;
  #178 = NameAndType        #173:#177     // append:(C)Lscala/collection/mutable/StringBuilder;
  #179 = Methodref          #172.#178     // scala/collection/mutable/StringBuilder.append:(C)Lscala/collection/mutable/StringBuilder;
  #180 = Utf8               scala/runtime/BoxedUnit
  #181 = Class              #180          // scala/runtime/BoxedUnit
  #182 = Utf8               UNIT
  #183 = Utf8               Lscala/runtime/BoxedUnit;
  #184 = NameAndType        #182:#183     // UNIT:Lscala/runtime/BoxedUnit;
  #185 = Fieldref           #181.#184     // scala/runtime/BoxedUnit.UNIT:Lscala/runtime/BoxedUnit;
  #186 = Utf8               <init>
  #187 = Utf8               ()V
  #188 = NameAndType        #186:#187     // "<init>":()V
  #189 = Methodref          #172.#188     // scala/collection/mutable/StringBuilder."<init>":()V
  #190 = Utf8               scala/xml/Utility$
  #191 = Class              #190          // scala/xml/Utility$
  #192 = Utf8               Lscala/xml/Utility$;
  #193 = NameAndType        #25:#192      // MODULE$:Lscala/xml/Utility$;
  #194 = Fieldref           #191.#193     // scala/xml/Utility$.MODULE$:Lscala/xml/Utility$;
  #195 = Utf8               scala/xml/TopScope$
  #196 = Class              #195          // scala/xml/TopScope$
  #197 = Utf8               Lscala/xml/TopScope$;
  #198 = NameAndType        #25:#197      // MODULE$:Lscala/xml/TopScope$;
  #199 = Fieldref           #196.#198     // scala/xml/TopScope$.MODULE$:Lscala/xml/TopScope$;
  #200 = Utf8               sequenceToXML$default$5
  #201 = NameAndType        #200:#58      // sequenceToXML$default$5:()Z
  #202 = Methodref          #191.#201     // scala/xml/Utility$.sequenceToXML$default$5:()Z
  #203 = Utf8               sequenceToXML$default$6
  #204 = NameAndType        #203:#58      // sequenceToXML$default$6:()Z
  #205 = Methodref          #191.#204     // scala/xml/Utility$.sequenceToXML$default$6:()Z
  #206 = Utf8               sequenceToXML$default$7
  #207 = Utf8               ()Lscala/Enumeration$Value;
  #208 = NameAndType        #206:#207     // sequenceToXML$default$7:()Lscala/Enumeration$Value;
  #209 = Methodref          #191.#208     // scala/xml/Utility$.sequenceToXML$default$7:()Lscala/Enumeration$Value;
  #210 = Utf8               sequenceToXML
  #211 = Utf8               (Lscala/collection/Seq;Lscala/xml/NamespaceBinding;Lscala/collection/mutable/StringBuilder;ZZZLscala/Enumeration$Value;)V
  #212 = NameAndType        #210:#211     // sequenceToXML:(Lscala/collection/Seq;Lscala/xml/NamespaceBinding;Lscala/collection/mutable/StringBuilder;ZZZLscala/Enumeration$Value;)V
  #213 = Methodref          #191.#212     // scala/xml/Utility$.sequenceToXML:(Lscala/collection/Seq;Lscala/xml/NamespaceBinding;Lscala/collection/mutable/StringBuilder;ZZZLscala/Enumeration$Value;)V
  #214 = Utf8               toString
  #215 = NameAndType        #214:#33      // toString:()Ljava/lang/String;
  #216 = Methodref          #172.#215     // scala/collection/mutable/StringBuilder.toString:()Ljava/lang/String;
  #217 = Utf8               appendQuoted
  #218 = Utf8               (Ljava/lang/String;Lscala/collection/mutable/StringBuilder;)Lscala/collection/mutable/StringBuilder;
  #219 = NameAndType        #217:#218     // appendQuoted:(Ljava/lang/String;Lscala/collection/mutable/StringBuilder;)Lscala/collection/mutable/StringBuilder;
  #220 = Methodref          #191.#219     // scala/xml/Utility$.appendQuoted:(Ljava/lang/String;Lscala/collection/mutable/StringBuilder;)Lscala/collection/mutable/StringBuilder;
  #221 = Utf8               sb2
  #222 = Utf8               $init$
  #223 = Utf8               (Lscala/xml/Attribute;)V
  #224 = Utf8               $deserializeLambda$
  #225 = Utf8               (Ljava/lang/invoke/SerializedLambda;)Ljava/lang/Object;
  #226 = Utf8               scala/runtime/LambdaDeserialize
  #227 = Class              #226          // scala/runtime/LambdaDeserialize
  #228 = Utf8               bootstrap
  #229 = Utf8               (Ljava/lang/invoke/MethodHandles$Lookup;Ljava/lang/String;Ljava/lang/invoke/MethodType;[Ljava/lang/invoke/MethodHandle;)Ljava/lang/invoke/CallSite;
  #230 = NameAndType        #228:#229     // bootstrap:(Ljava/lang/invoke/MethodHandles$Lookup;Ljava/lang/String;Ljava/lang/invoke/MethodType;[Ljava/lang/invoke/MethodHandle;)Ljava/lang/invoke/CallSite;
  #231 = Methodref          #227.#230     // scala/runtime/LambdaDeserialize.bootstrap:(Ljava/lang/invoke/MethodHandles$Lookup;Ljava/lang/String;Ljava/lang/invoke/MethodType;[Ljava/lang/invoke/MethodHandle;)Ljava/lang/invoke/CallSite;
  #232 = MethodHandle       6:#231        // REF_invokeStatic scala/runtime/LambdaDeserialize.bootstrap:(Ljava/lang/invoke/MethodHandles$Lookup;Ljava/lang/String;Ljava/lang/invoke/MethodType;[Ljava/lang/invoke/MethodHandle;)Ljava/lang/invoke/CallSite;
  #233 = Utf8               lambdaDeserialize
  #234 = NameAndType        #233:#225     // lambdaDeserialize:(Ljava/lang/invoke/SerializedLambda;)Ljava/lang/Object;
  #235 = InvokeDynamic      #1:#234       // #1:lambdaDeserialize:(Ljava/lang/invoke/SerializedLambda;)Ljava/lang/Object;
  #236 = Utf8               Code
  #237 = Utf8               LocalVariableTable
  #238 = Utf8               Signature
  #239 = Utf8               MethodParameters
  #240 = Utf8               LineNumberTable
  #241 = Utf8               StackMapTable
  #242 = Utf8               InnerClasses
  #243 = Utf8               SourceFile
  #244 = Utf8               RuntimeVisibleAnnotations
  #245 = Utf8               BootstrapMethods
  #246 = Utf8               ScalaInlineInfo
  #247 = Utf8               ScalaSig
{
  public static scala.Option<scala.Tuple3<java.lang.String, scala.collection.Seq<scala.xml.Node>, scala.xml.MetaData>> unapply(scala.xml.Attribute);
    descriptor: (Lscala/xml/Attribute;)Lscala/Option;
    flags: (0x0009) ACC_PUBLIC, ACC_STATIC
    Code:
      stack=2, locals=1, args_size=1
         0: getstatic     #28                 // Field scala/xml/Attribute$.MODULE$:Lscala/xml/Attribute$;
         3: aload_0
         4: invokevirtual #30                 // Method scala/xml/Attribute$.unapply:(Lscala/xml/Attribute;)Lscala/Option;
         7: areturn
      LocalVariableTable:
        Start  Length  Slot  Name   Signature
            0       8     0     x   Lscala/xml/Attribute;
    Signature: #21                          // (Lscala/xml/Attribute;)Lscala/Option<Lscala/Tuple3<Ljava/lang/String;Lscala/collection/Seq<Lscala/xml/Node;>;Lscala/xml/MetaData;>;>;
    MethodParameters:
      Name                           Flags
      x                              final

  public abstract java.lang.String pre();
    descriptor: ()Ljava/lang/String;
    flags: (0x0401) ACC_PUBLIC, ACC_ABSTRACT

  public abstract java.lang.String key();
    descriptor: ()Ljava/lang/String;
    flags: (0x0401) ACC_PUBLIC, ACC_ABSTRACT

  public abstract scala.collection.Seq<scala.xml.Node> value();
    descriptor: ()Lscala/collection/Seq;
    flags: (0x0401) ACC_PUBLIC, ACC_ABSTRACT
    Signature: #37                          // ()Lscala/collection/Seq<Lscala/xml/Node;>;

  public abstract scala.xml.MetaData next();
    descriptor: ()Lscala/xml/MetaData;
    flags: (0x0401) ACC_PUBLIC, ACC_ABSTRACT

  public abstract scala.collection.Seq<scala.xml.Node> apply(java.lang.String);
    descriptor: (Ljava/lang/String;)Lscala/collection/Seq;
    flags: (0x0401) ACC_PUBLIC, ACC_ABSTRACT
    Signature: #42                          // (Ljava/lang/String;)Lscala/collection/Seq<Lscala/xml/Node;>;
    MethodParameters:
      Name                           Flags
      key                            final

  public abstract scala.collection.Seq<scala.xml.Node> apply(java.lang.String, scala.xml.NamespaceBinding, java.lang.String);
    descriptor: (Ljava/lang/String;Lscala/xml/NamespaceBinding;Ljava/lang/String;)Lscala/collection/Seq;
    flags: (0x0401) ACC_PUBLIC, ACC_ABSTRACT
    Signature: #44                          // (Ljava/lang/String;Lscala/xml/NamespaceBinding;Ljava/lang/String;)Lscala/collection/Seq<Lscala/xml/Node;>;
    MethodParameters:
      Name                           Flags
      namespace                      final
      scope                          final
      key                            final

  public abstract scala.xml.Attribute copy(scala.xml.MetaData);
    descriptor: (Lscala/xml/MetaData;)Lscala/xml/Attribute;
    flags: (0x0401) ACC_PUBLIC, ACC_ABSTRACT
    MethodParameters:
      Name                           Flags
      next                           final

  public static scala.xml.MetaData remove$(scala.xml.Attribute, java.lang.String);
    descriptor: (Lscala/xml/Attribute;Ljava/lang/String;)Lscala/xml/MetaData;
    flags: (0x1009) ACC_PUBLIC, ACC_STATIC, ACC_SYNTHETIC
    Code:
      stack=2, locals=2, args_size=2
         0: aload_0
         1: aload_1
         2: invokespecial #55                 // InterfaceMethod remove:(Ljava/lang/String;)Lscala/xml/MetaData;
         5: areturn
      LineNumberTable:
        line 66: 0
      LocalVariableTable:
        Start  Length  Slot  Name   Signature
            0       6     0 $this   Lscala/xml/Attribute;
            0       6     1   key   Ljava/lang/String;
    MethodParameters:
      Name                           Flags
      $this                          final synthetic
      key                            final

  public default scala.xml.MetaData remove(java.lang.String);
    descriptor: (Ljava/lang/String;)Lscala/xml/MetaData;
    flags: (0x0001) ACC_PUBLIC
    Code:
      stack=3, locals=3, args_size=2
         0: aload_0
         1: invokeinterface #60,  1           // InterfaceMethod isPrefixed:()Z
         6: ifne          45
         9: aload_0
        10: invokeinterface #62,  1           // InterfaceMethod key:()Ljava/lang/String;
        15: aload_1
        16: astore_2
        17: dup
        18: ifnonnull     29
        21: pop
        22: aload_2
        23: ifnull        36
        26: goto          45
        29: aload_2
        30: invokevirtual #66                 // Method java/lang/Object.equals:(Ljava/lang/Object;)Z
        33: ifeq          45
        36: aload_0
        37: invokeinterface #68,  1           // InterfaceMethod next:()Lscala/xml/MetaData;
        42: goto          64
        45: aload_0
        46: aload_0
        47: invokeinterface #68,  1           // InterfaceMethod next:()Lscala/xml/MetaData;
        52: aload_1
        53: invokevirtual #71                 // Method scala/xml/MetaData.remove:(Ljava/lang/String;)Lscala/xml/MetaData;
        56: invokeinterface #73,  2           // InterfaceMethod copy:(Lscala/xml/MetaData;)Lscala/xml/Attribute;
        61: checkcast     #70                 // class scala/xml/MetaData
        64: areturn
      StackMapTable: number_of_entries = 4
        frame_type = 255 /* full_frame */
          offset_delta = 29
          locals = [ class scala/xml/Attribute, class java/lang/String, class java/lang/String ]
          stack = [ class java/lang/String ]
        frame_type = 6 /* same */
        frame_type = 250 /* chop */
          offset_delta = 8
        frame_type = 82 /* same_locals_1_stack_item */
          stack = [ class scala/xml/MetaData ]
      LineNumberTable:
        line 67: 0
        line 68: 45
      LocalVariableTable:
        Start  Length  Slot  Name   Signature
            0      65     0  this   Lscala/xml/Attribute;
            0      65     1   key   Ljava/lang/String;
    MethodParameters:
      Name                           Flags
      key                            final

  public static scala.xml.MetaData remove$(scala.xml.Attribute, java.lang.String, scala.xml.NamespaceBinding, java.lang.String);
    descriptor: (Lscala/xml/Attribute;Ljava/lang/String;Lscala/xml/NamespaceBinding;Ljava/lang/String;)Lscala/xml/MetaData;
    flags: (0x1009) ACC_PUBLIC, ACC_STATIC, ACC_SYNTHETIC
    Code:
      stack=4, locals=4, args_size=4
         0: aload_0
         1: aload_1
         2: aload_2
         3: aload_3
         4: invokespecial #80                 // InterfaceMethod remove:(Ljava/lang/String;Lscala/xml/NamespaceBinding;Ljava/lang/String;)Lscala/xml/MetaData;
         7: areturn
      LineNumberTable:
        line 70: 0
      LocalVariableTable:
        Start  Length  Slot  Name   Signature
            0       8     0 $this   Lscala/xml/Attribute;
            0       8     1 namespace   Ljava/lang/String;
            0       8     2 scope   Lscala/xml/NamespaceBinding;
            0       8     3   key   Ljava/lang/String;
    MethodParameters:
      Name                           Flags
      $this                          final synthetic
      namespace                      final
      scope                          final
      key                            final

  public default scala.xml.MetaData remove(java.lang.String, scala.xml.NamespaceBinding, java.lang.String);
    descriptor: (Ljava/lang/String;Lscala/xml/NamespaceBinding;Ljava/lang/String;)Lscala/xml/MetaData;
    flags: (0x0001) ACC_PUBLIC
    Code:
      stack=5, locals=6, args_size=4
         0: aload_0
         1: invokeinterface #62,  1           // InterfaceMethod key:()Ljava/lang/String;
         6: aload_3
         7: astore        4
         9: dup
        10: ifnonnull     22
        13: pop
        14: aload         4
        16: ifnull        30
        19: goto          73
        22: aload         4
        24: invokevirtual #66                 // Method java/lang/Object.equals:(Ljava/lang/Object;)Z
        27: ifeq          73
        30: aload_2
        31: aload_0
        32: invokeinterface #83,  1           // InterfaceMethod pre:()Ljava/lang/String;
        37: invokevirtual #89                 // Method scala/xml/NamespaceBinding.getURI:(Ljava/lang/String;)Ljava/lang/String;
        40: aload_1
        41: astore        5
        43: dup
        44: ifnonnull     56
        47: pop
        48: aload         5
        50: ifnull        64
        53: goto          73
        56: aload         5
        58: invokevirtual #66                 // Method java/lang/Object.equals:(Ljava/lang/Object;)Z
        61: ifeq          73
        64: aload_0
        65: invokeinterface #68,  1           // InterfaceMethod next:()Lscala/xml/MetaData;
        70: goto          94
        73: aload_0
        74: aload_0
        75: invokeinterface #68,  1           // InterfaceMethod next:()Lscala/xml/MetaData;
        80: aload_1
        81: aload_2
        82: aload_3
        83: invokevirtual #90                 // Method scala/xml/MetaData.remove:(Ljava/lang/String;Lscala/xml/NamespaceBinding;Ljava/lang/String;)Lscala/xml/MetaData;
        86: invokeinterface #73,  2           // InterfaceMethod copy:(Lscala/xml/MetaData;)Lscala/xml/Attribute;
        91: checkcast     #70                 // class scala/xml/MetaData
        94: areturn
      StackMapTable: number_of_entries = 6
        frame_type = 255 /* full_frame */
          offset_delta = 22
          locals = [ class scala/xml/Attribute, class java/lang/String, class scala/xml/NamespaceBinding, class java/lang/String, class java/lang/String ]
          stack = [ class java/lang/String ]
        frame_type = 7 /* same */
        frame_type = 255 /* full_frame */
          offset_delta = 25
          locals = [ class scala/xml/Attribute, class java/lang/String, class scala/xml/NamespaceBinding, class java/lang/String, class java/lang/String, class java/lang/String ]
          stack = [ class java/lang/String ]
        frame_type = 7 /* same */
        frame_type = 250 /* chop */
          offset_delta = 8
        frame_type = 84 /* same_locals_1_stack_item */
          stack = [ class scala/xml/MetaData ]
      LineNumberTable:
        line 71: 0
        line 72: 73
      LocalVariableTable:
        Start  Length  Slot  Name   Signature
            0      95     0  this   Lscala/xml/Attribute;
            0      95     1 namespace   Ljava/lang/String;
            0      95     2 scope   Lscala/xml/NamespaceBinding;
            0      95     3   key   Ljava/lang/String;
    MethodParameters:
      Name                           Flags
      namespace                      final
      scope                          final
      key                            final

  public static boolean isPrefixed$(scala.xml.Attribute);
    descriptor: (Lscala/xml/Attribute;)Z
    flags: (0x1009) ACC_PUBLIC, ACC_STATIC, ACC_SYNTHETIC
    Code:
      stack=1, locals=1, args_size=1
         0: aload_0
         1: invokespecial #60                 // InterfaceMethod isPrefixed:()Z
         4: ireturn
      LineNumberTable:
        line 74: 0
      LocalVariableTable:
        Start  Length  Slot  Name   Signature
            0       5     0 $this   Lscala/xml/Attribute;
    MethodParameters:
      Name                           Flags
      $this                          final synthetic

  public default boolean isPrefixed();
    descriptor: ()Z
    flags: (0x0001) ACC_PUBLIC
    Code:
      stack=1, locals=1, args_size=1
         0: aload_0
         1: invokeinterface #83,  1           // InterfaceMethod pre:()Ljava/lang/String;
         6: ifnull        13
         9: iconst_1
        10: goto          14
        13: iconst_0
        14: ireturn
      StackMapTable: number_of_entries = 2
        frame_type = 13 /* same */
        frame_type = 64 /* same_locals_1_stack_item */
          stack = [ int ]
      LineNumberTable:
        line 74: 0
      LocalVariableTable:
        Start  Length  Slot  Name   Signature
            0      15     0  this   Lscala/xml/Attribute;

  public abstract java.lang.String getNamespace(scala.xml.Node);
    descriptor: (Lscala/xml/Node;)Ljava/lang/String;
    flags: (0x0401) ACC_PUBLIC, ACC_ABSTRACT
    MethodParameters:
      Name                           Flags
      owner                          final

  public static boolean wellformed$(scala.xml.Attribute, scala.xml.NamespaceBinding);
    descriptor: (Lscala/xml/Attribute;Lscala/xml/NamespaceBinding;)Z
    flags: (0x1009) ACC_PUBLIC, ACC_STATIC, ACC_SYNTHETIC
    Code:
      stack=2, locals=2, args_size=2
         0: aload_0
         1: aload_1
         2: invokespecial #101                // InterfaceMethod wellformed:(Lscala/xml/NamespaceBinding;)Z
         5: ireturn
      LineNumberTable:
        line 78: 0
      LocalVariableTable:
        Start  Length  Slot  Name   Signature
            0       6     0 $this   Lscala/xml/Attribute;
            0       6     1 scope   Lscala/xml/NamespaceBinding;
    MethodParameters:
      Name                           Flags
      $this                          final synthetic
      scope                          final

  public default boolean wellformed(scala.xml.NamespaceBinding);
    descriptor: (Lscala/xml/NamespaceBinding;)Z
    flags: (0x0001) ACC_PUBLIC
    Code:
      stack=4, locals=3, args_size=2
         0: aload_0
         1: invokeinterface #60,  1           // InterfaceMethod isPrefixed:()Z
         6: ifeq          22
         9: aload_1
        10: aload_0
        11: invokeinterface #83,  1           // InterfaceMethod pre:()Ljava/lang/String;
        16: invokevirtual #89                 // Method scala/xml/NamespaceBinding.getURI:(Ljava/lang/String;)Ljava/lang/String;
        19: goto          23
        22: aconst_null
        23: astore_2
        24: aload_0
        25: invokeinterface #68,  1           // InterfaceMethod next:()Lscala/xml/MetaData;
        30: aload_2
        31: aload_1
        32: aload_0
        33: invokeinterface #62,  1           // InterfaceMethod key:()Ljava/lang/String;
        38: invokevirtual #103                // Method scala/xml/MetaData.apply:(Ljava/lang/String;Lscala/xml/NamespaceBinding;Ljava/lang/String;)Lscala/collection/Seq;
        41: ifnonnull     61
        44: aload_0
        45: invokeinterface #68,  1           // InterfaceMethod next:()Lscala/xml/MetaData;
        50: aload_1
        51: invokevirtual #104                // Method scala/xml/MetaData.wellformed:(Lscala/xml/NamespaceBinding;)Z
        54: ifeq          61
        57: iconst_1
        58: goto          62
        61: iconst_0
        62: ireturn
      StackMapTable: number_of_entries = 4
        frame_type = 22 /* same */
        frame_type = 64 /* same_locals_1_stack_item */
          stack = [ class java/lang/String ]
        frame_type = 252 /* append */
          offset_delta = 37
          locals = [ class java/lang/String ]
        frame_type = 64 /* same_locals_1_stack_item */
          stack = [ int ]
      LineNumberTable:
        line 79: 0
        line 80: 24
      LocalVariableTable:
        Start  Length  Slot  Name   Signature
           24      38     2   arg   Ljava/lang/String;
            0      63     0  this   Lscala/xml/Attribute;
            0      63     1 scope   Lscala/xml/NamespaceBinding;
    MethodParameters:
      Name                           Flags
      scope                          final

  public static scala.collection.Iterator iterator$(scala.xml.Attribute);
    descriptor: (Lscala/xml/Attribute;)Lscala/collection/Iterator;
    flags: (0x1009) ACC_PUBLIC, ACC_STATIC, ACC_SYNTHETIC
    Code:
      stack=1, locals=1, args_size=1
         0: aload_0
         1: invokespecial #111                // InterfaceMethod iterator:()Lscala/collection/Iterator;
         4: areturn
      LineNumberTable:
        line 84: 0
      LocalVariableTable:
        Start  Length  Slot  Name   Signature
            0       5     0 $this   Lscala/xml/Attribute;
    MethodParameters:
      Name                           Flags
      $this                          final synthetic

  public default scala.collection.Iterator<scala.xml.MetaData> iterator();
    descriptor: ()Lscala/collection/Iterator;
    flags: (0x0001) ACC_PUBLIC
    Code:
      stack=2, locals=1, args_size=1
         0: aload_0
         1: invokeinterface #114,  1          // InterfaceMethod value:()Lscala/collection/Seq;
         6: ifnonnull     21
         9: aload_0
        10: invokeinterface #68,  1           // InterfaceMethod next:()Lscala/xml/MetaData;
        15: invokevirtual #115                // Method scala/xml/MetaData.iterator:()Lscala/collection/Iterator;
        18: goto          42
        21: getstatic     #120                // Field scala/package$.MODULE$:Lscala/package$;
        24: invokevirtual #124                // Method scala/package$.Iterator:()Lscala/collection/Iterator$;
        27: aload_0
        28: invokevirtual #130                // Method scala/collection/Iterator$.single:(Ljava/lang/Object;)Lscala/collection/Iterator;
        31: aload_0
        32: invokedynamic #149,  0            // InvokeDynamic #0:apply:(Lscala/xml/Attribute;)Lscala/Function0;
        37: invokeinterface #155,  2          // InterfaceMethod scala/collection/Iterator.$plus$plus:(Lscala/Function0;)Lscala/collection/Iterator;
        42: areturn
      StackMapTable: number_of_entries = 2
        frame_type = 21 /* same */
        frame_type = 84 /* same_locals_1_stack_item */
          stack = [ class scala/collection/Iterator ]
      LineNumberTable:
        line 85: 0
        line 86: 21
      LocalVariableTable:
        Start  Length  Slot  Name   Signature
            0      43     0  this   Lscala/xml/Attribute;
    Signature: #112                         // ()Lscala/collection/Iterator<Lscala/xml/MetaData;>;

  public static int size$(scala.xml.Attribute);
    descriptor: (Lscala/xml/Attribute;)I
    flags: (0x1009) ACC_PUBLIC, ACC_STATIC, ACC_SYNTHETIC
    Code:
      stack=1, locals=1, args_size=1
         0: aload_0
         1: invokespecial #161                // InterfaceMethod size:()I
         4: ireturn
      LineNumberTable:
        line 89: 0
      LocalVariableTable:
        Start  Length  Slot  Name   Signature
            0       5     0 $this   Lscala/xml/Attribute;
    MethodParameters:
      Name                           Flags
      $this                          final synthetic

  public default int size();
    descriptor: ()I
    flags: (0x0001) ACC_PUBLIC
    Code:
      stack=2, locals=1, args_size=1
         0: aload_0
         1: invokeinterface #114,  1          // InterfaceMethod value:()Lscala/collection/Seq;
         6: ifnonnull     21
         9: aload_0
        10: invokeinterface #68,  1           // InterfaceMethod next:()Lscala/xml/MetaData;
        15: invokevirtual #162                // Method scala/xml/MetaData.size:()I
        18: goto          32
        21: iconst_1
        22: aload_0
        23: invokeinterface #68,  1           // InterfaceMethod next:()Lscala/xml/MetaData;
        28: invokevirtual #162                // Method scala/xml/MetaData.size:()I
        31: iadd
        32: ireturn
      StackMapTable: number_of_entries = 2
        frame_type = 21 /* same */
        frame_type = 74 /* same_locals_1_stack_item */
          stack = [ int ]
      LineNumberTable:
        line 90: 0
        line 91: 21
      LocalVariableTable:
        Start  Length  Slot  Name   Signature
            0      33     0  this   Lscala/xml/Attribute;

  public static void toString1$(scala.xml.Attribute, scala.collection.mutable.StringBuilder);
    descriptor: (Lscala/xml/Attribute;Lscala/collection/mutable/StringBuilder;)V
    flags: (0x1009) ACC_PUBLIC, ACC_STATIC, ACC_SYNTHETIC
    Code:
      stack=2, locals=2, args_size=2
         0: aload_0
         1: aload_1
         2: invokespecial #169                // InterfaceMethod toString1:(Lscala/collection/mutable/StringBuilder;)V
         5: return
      LineNumberTable:
        line 97: 0
      LocalVariableTable:
        Start  Length  Slot  Name   Signature
            0       6     0 $this   Lscala/xml/Attribute;
            0       6     1    sb   Lscala/collection/mutable/StringBuilder;
    MethodParameters:
      Name                           Flags
      $this                          final synthetic
      sb                             final

  public default void toString1(scala.collection.mutable.StringBuilder);
    descriptor: (Lscala/collection/mutable/StringBuilder;)V
    flags: (0x0001) ACC_PUBLIC
    Code:
      stack=8, locals=3, args_size=2
         0: aload_0
         1: invokeinterface #114,  1          // InterfaceMethod value:()Lscala/collection/Seq;
         6: ifnonnull     10
         9: return
        10: aload_0
        11: invokeinterface #60,  1           // InterfaceMethod isPrefixed:()Z
        16: ifeq          37
        19: aload_1
        20: aload_0
        21: invokeinterface #83,  1           // InterfaceMethod pre:()Ljava/lang/String;
        26: invokevirtual #176                // Method scala/collection/mutable/StringBuilder.append:(Ljava/lang/String;)Lscala/collection/mutable/StringBuilder;
        29: bipush        58
        31: invokevirtual #179                // Method scala/collection/mutable/StringBuilder.append:(C)Lscala/collection/mutable/StringBuilder;
        34: goto          40
        37: getstatic     #185                // Field scala/runtime/BoxedUnit.UNIT:Lscala/runtime/BoxedUnit;
        40: pop
        41: aload_1
        42: aload_0
        43: invokeinterface #62,  1           // InterfaceMethod key:()Ljava/lang/String;
        48: invokevirtual #176                // Method scala/collection/mutable/StringBuilder.append:(Ljava/lang/String;)Lscala/collection/mutable/StringBuilder;
        51: bipush        61
        53: invokevirtual #179                // Method scala/collection/mutable/StringBuilder.append:(C)Lscala/collection/mutable/StringBuilder;
        56: pop
        57: new           #172                // class scala/collection/mutable/StringBuilder
        60: dup
        61: invokespecial #189                // Method scala/collection/mutable/StringBuilder."<init>":()V
        64: astore_2
        65: getstatic     #194                // Field scala/xml/Utility$.MODULE$:Lscala/xml/Utility$;
        68: aload_0
        69: invokeinterface #114,  1          // InterfaceMethod value:()Lscala/collection/Seq;
        74: getstatic     #199                // Field scala/xml/TopScope$.MODULE$:Lscala/xml/TopScope$;
        77: aload_2
        78: iconst_1
        79: getstatic     #194                // Field scala/xml/Utility$.MODULE$:Lscala/xml/Utility$;
        82: invokevirtual #202                // Method scala/xml/Utility$.sequenceToXML$default$5:()Z
        85: getstatic     #194                // Field scala/xml/Utility$.MODULE$:Lscala/xml/Utility$;
        88: invokevirtual #205                // Method scala/xml/Utility$.sequenceToXML$default$6:()Z
        91: getstatic     #194                // Field scala/xml/Utility$.MODULE$:Lscala/xml/Utility$;
        94: invokevirtual #209                // Method scala/xml/Utility$.sequenceToXML$default$7:()Lscala/Enumeration$Value;
        97: invokevirtual #213                // Method scala/xml/Utility$.sequenceToXML:(Lscala/collection/Seq;Lscala/xml/NamespaceBinding;Lscala/collection/mutable/StringBuilder;ZZZLscala/Enumeration$Value;)V
       100: getstatic     #194                // Field scala/xml/Utility$.MODULE$:Lscala/xml/Utility$;
       103: aload_2
       104: invokevirtual #216                // Method scala/collection/mutable/StringBuilder.toString:()Ljava/lang/String;
       107: aload_1
       108: invokevirtual #220                // Method scala/xml/Utility$.appendQuoted:(Ljava/lang/String;Lscala/collection/mutable/StringBuilder;)Lscala/collection/mutable/StringBuilder;
       111: pop
       112: return
      StackMapTable: number_of_entries = 3
        frame_type = 10 /* same */
        frame_type = 26 /* same */
        frame_type = 66 /* same_locals_1_stack_item */
          stack = [ class java/lang/Object ]
      LineNumberTable:
        line 98: 0
        line 99: 9
        line 100: 10
        line 101: 19
        line 100: 37
        line 103: 41
        line 104: 57
        line 105: 65
        line 106: 100
      LocalVariableTable:
        Start  Length  Slot  Name   Signature
           65      47     2   sb2   Lscala/collection/mutable/StringBuilder;
            0     113     0  this   Lscala/xml/Attribute;
            0     113     1    sb   Lscala/collection/mutable/StringBuilder;
    MethodParameters:
      Name                           Flags
      sb                             final

  public static scala.collection.Iterator $anonfun$iterator$1(scala.xml.Attribute);
    descriptor: (Lscala/xml/Attribute;)Lscala/collection/Iterator;
    flags: (0x1009) ACC_PUBLIC, ACC_STATIC, ACC_SYNTHETIC
    Code:
      stack=1, locals=1, args_size=1
         0: aload_0
         1: invokeinterface #68,  1           // InterfaceMethod next:()Lscala/xml/MetaData;
         6: invokevirtual #115                // Method scala/xml/MetaData.iterator:()Lscala/collection/Iterator;
         9: areturn
      LineNumberTable:
        line 86: 0
      LocalVariableTable:
        Start  Length  Slot  Name   Signature
            0      10     0 $this   Lscala/xml/Attribute;
    MethodParameters:
      Name                           Flags
      $this                          final synthetic

  public static void $init$(scala.xml.Attribute);
    descriptor: (Lscala/xml/Attribute;)V
    flags: (0x0009) ACC_PUBLIC, ACC_STATIC
    Code:
      stack=0, locals=1, args_size=1
         0: return
      LineNumberTable:
        line 56: 0
      LocalVariableTable:
        Start  Length  Slot  Name   Signature
            0       1     0 $this   Lscala/xml/Attribute;
    MethodParameters:
      Name                           Flags
      $this                          final synthetic

  private static java.lang.Object $deserializeLambda$(java.lang.invoke.SerializedLambda);
    descriptor: (Ljava/lang/invoke/SerializedLambda;)Ljava/lang/Object;
    flags: (0x100a) ACC_PRIVATE, ACC_STATIC, ACC_SYNTHETIC
    Code:
      stack=1, locals=1, args_size=1
         0: aload_0
         1: invokedynamic #235,  0            // InvokeDynamic #1:lambdaDeserialize:(Ljava/lang/invoke/SerializedLambda;)Ljava/lang/Object;
         6: areturn
}
InnerClasses:
  public static final #13= #10 of #12;    // Lookup=class java/lang/invoke/MethodHandles$Lookup of class java/lang/invoke/MethodHandles
  public abstract #18= #15 of #17;        // Value=class scala/Enumeration$Value of class scala/Enumeration
SourceFile: "Attribute.scala"
RuntimeVisibleAnnotations:
  0: #6(#7=s#8)
    scala.reflect.ScalaSignature(
      bytes="\u0006\u0005\u0005%t!\u0002\u000e\u001c\u0011\u0003\u0001c!\u0002\u0012\u001c\u0011\u0003\u0019\u0003\"\u0002\u0019\u0002\t\u0003\t\u0004\"\u0002\u001a\u0002\t\u0003\u0019\u0004BB1\u0002\t\u0003\t\t\u0004\u0003\u0004b\u0003\u0011\u0005\u0011\u0011\b\u0005\u0007C\u0006!\t!a\u0011\t\r\u0005\fA\u0011AA\'\u0011%\tI&AA\u0001\n\u0013\tYFB\u0004#7A\u0005\u0019\u0011\u0001+\t\u000bUKA\u0011\u0001,\t\u000biKa\u0011A.\t\u000fqK!\u0019!D\u00017\"9Q,\u0003b\u0001\u000e\u0003q\u0006bB0\n\u0005\u00045\t\u0001\u0019\u0005\u0006C&1\tA\u0019\u0005\u0006C&1\t\u0001\u001a\u0005\u0006[&1\tA\u001c\u0005\u0006a&!\t!\u001d\u0005\u0006a&!\ta\u001d\u0005\u0006o&!\t\u0001\u001f\u0005\u0006y&1\t! \u0005\b\u0003\u0003IA\u0011AA\u0002\u0011\u001d\t9!\u0003C!\u0003\u0013Aq!!\u0007\n\t\u0003\nY\u0002C\u0004\u0002$%!\t\"!\n\u0002\u0013\u0005#HO]5ckR,\'B\u0001\u000f\u001e\u0003\rAX\u000e\u001c\u0006\u0002=\u0005)1oY1mC\u000e\u0001\u0001CA\u0011\u0002\u001b\u0005Y\"!C!uiJL\'-\u001e;f\'\r\tA\u0005\u000b\t\u0003K\u0019j\u0011!H\u0005\u0003Ou\u0011a!\u00118z%\u00164\u0007CA\u0015/\u001b\u0005Q#BA\u0016-\u0003\tIwNC\u0001.\u0003\u0011Q\u0017M^1\n\u0005=R#\u0001D*fe&\fG.\u001b>bE2,\u0017A\u0002\u001fj]&$h\bF\u0001!\u0003\u001d)h.\u00199qYf$\"\u0001N)\u0011\u0007\u0015*t\'\u0003\u00027;\t1q\n\u001d;j_:\u0004R!\n\u001d;\u000b:K!!O\u000f\u0003\rQ+\b\u000f\\34!\tY$I\u0004\u0002=\u0001B\u0011Q(H\u0007\u0002})\u0011qhH\u0001\u0007yI|w\u000e\u001e \n\u0005\u0005k\u0012A\u0002)sK\u0012,g-\u0003\u0002D\t\n11\u000b\u001e:j]\u001eT!!Q\u000f\u0011\u0007\u0019K5*D\u0001H\u0015\tAU$\u0001\u0006d_2dWm\u0019;j_:L!AS$\u0003\u0007M+\u0017\u000f\u0005\u0002\"\u0019&\u0011Qj\u0007\u0002\u0005\u001d>$W\r\u0005\u0002\"\u001f&\u0011\u0001k\u0007\u0002\t\u001b\u0016$\u0018\rR1uC\")!k\u0001a\u0001\'\u0006\t\u0001\u0010\u0005\u0002\"\u0013M\u0011\u0011BT\u0001\u0007I%t\u0017\u000e\u001e\u0013\u0015\u0003]\u0003\"!\n-\n\u0005ek\"\u0001B+oSR\f1\u0001\u001d:f+\u0005Q\u0014aA6fs\u0006)a/\u00197vKV\tQ)\u0001\u0003oKb$X#\u0001(\u0002\u000b\u0005\u0004\b\u000f\\=\u0015\u0005\u0015\u001b\u0007\"\u0002/\u0010\u0001\u0004QD\u0003B#fO2DQA\u001a\tA\u0002i\n\u0011B\\1nKN\u0004\u0018mY3\t\u000b!\u0004\u0002\u0019A5\u0002\u000bM\u001cw\u000e]3\u0011\u0005\u0005R\u0017BA6\u001c\u0005Aq\u0015-\\3ta\u0006\u001cWMQ5oI&tw\rC\u0003]!\u0001\u0007!(\u0001\u0003d_BLHCA*p\u0011\u0015y\u0016\u00031\u0001O\u0003\u0019\u0011X-\\8wKR\u0011aJ\u001d\u0005\u00069J\u0001\rA\u000f\u000b\u0005\u001dR,h\u000fC\u0003g\'\u0001\u0007!\bC\u0003i\'\u0001\u0007\u0011\u000eC\u0003]\'\u0001\u0007!(\u0001\u0006jgB\u0013XMZ5yK\u0012,\u0012!\u001f\t\u0003KiL!a_\u000f\u0003\u000f\t{w\u000e\\3b]\u0006aq-\u001a;OC6,7\u000f]1dKR\u0011!H \u0005\u0006\u007fV\u0001\raS\u0001\u0006_^tWM]\u0001\u000bo\u0016dGNZ8s[\u0016$GcA=\u0002\u0006!)\u0001N\u0006a\u0001S\u0006A\u0011\u000e^3sCR|\'/\u0006\u0002\u0002\fA)\u0011QBA\n\u001d:\u0019Q%a\u0004\n\u0007\u0005EQ$A\u0004qC\u000e\\\u0017mZ3\n\t\u0005U\u0011q\u0003\u0002\t\u0013R,\'/\u0019;pe*\u0019\u0011\u0011C\u000f\u0002\tML\'0Z\u000b\u0003\u0003;\u00012!JA\u0010\u0013\r\t\t#\b\u0002\u0004\u0013:$\u0018!\u0003;p\'R\u0014\u0018N\\42)\r9\u0016q\u0005\u0005\b\u0003SI\u0002\u0019AA\u0016\u0003\t\u0019(\r\u0005\u0003\u0002\u000e\u00055\u0012\u0002BA\u0018\u0003/\u0011Qb\u0015;sS:<\')^5mI\u0016\u0014HcB*\u00024\u0005U\u0012q\u0007\u0005\u00069\u0012\u0001\rA\u000f\u0005\u0006;\u0012\u0001\r!\u0012\u0005\u0006?\u0012\u0001\rA\u0014\u000b\n\'\u0006m\u0012QHA \u0003\u0003BQAW\u0003A\u0002iBQ\u0001X\u0003A\u0002iBQ!X\u0003A\u0002iBQaX\u0003A\u00029#\u0012bUA#\u0003\u000f\nI%a\u0013\t\u000bi3\u0001\u0019\u0001\u001e\t\u000bq3\u0001\u0019\u0001\u001e\t\u000bu3\u0001\u0019A#\t\u000b}3\u0001\u0019\u0001(\u0015\u0013M\u000by%a\u0015\u0002V\u0005]\u0003B\u0002.\b\u0001\u0004\t\t\u0006E\u0002&kiBQ\u0001X\u0004A\u0002iBQ!X\u0004A\u0002\u0015CQaX\u0004A\u00029\u000bAb\u001e:ji\u0016\u0014V\r\u001d7bG\u0016$\"!!\u0018\u0011\t\u0005}\u0013QM\u0007\u0003\u0003CR1!a\u0019-\u0003\u0011a\u0017M\\4\n\t\u0005\u001d\u0014\u0011\r\u0002\u0007\u001f\nTWm\u0019;"
    )
BootstrapMethods:
  0: #146 REF_invokeStatic java/lang/invoke/LambdaMetafactory.altMetafactory:(Ljava/lang/invoke/MethodHandles$Lookup;Ljava/lang/String;Ljava/lang/invoke/MethodType;[Ljava/lang/Object;)Ljava/lang/invoke/CallSite;
    Method arguments:
      #132 ()Ljava/lang/Object;
      #136 REF_invokeStatic scala/xml/Attribute.$anonfun$iterator$1:(Lscala/xml/Attribute;)Lscala/collection/Iterator;
      #137 ()Lscala/collection/Iterator;
      #138 5
      #139 1
      #137 ()Lscala/collection/Iterator;
  1: #232 REF_invokeStatic scala/runtime/LambdaDeserialize.bootstrap:(Ljava/lang/invoke/MethodHandles$Lookup;Ljava/lang/String;Ljava/lang/invoke/MethodType;[Ljava/lang/invoke/MethodHandle;)Ljava/lang/invoke/CallSite;
    Method arguments:
      #136 REF_invokeStatic scala/xml/Attribute.$anonfun$iterator$1:(Lscala/xml/Attribute;)Lscala/collection/Iterator;
  ScalaInlineInfo: length = 0x7C (unknown attribute)
   01 00 00 18 00 85 00 6B 01 00 DE 00 DF 01 00 28
   00 29 00 00 28 00 2B 00 00 2F 00 30 00 00 5D 00
   5E 00 00 39 00 3A 00 00 5B 00 5C 01 00 6C 00 6D
   00 00 6A 00 6B 01 00 22 00 21 00 00 26 00 27 00
   00 20 00 21 00 00 34 00 35 00 00 34 00 4E 00 00
   31 00 32 01 00 31 00 4D 01 00 9E 00 9F 00 00 9C
   00 9D 01 00 A6 00 A7 00 00 A3 00 A4 01 00 23 00
   24 00 00 62 00 63 00 00 60 00 61 01
  ScalaSig: length = 0x3 (unknown attribute)
   05 02 00
