Classfile /Users/mw/Projects/slang-braindump/.jar/jar11/assemble/slang-braindump/assemble/content/scala/xml/MetaData$.class
  Last modified May 29, 2022; size 3419 bytes
  SHA-256 checksum d3c677bbd9f66a82e9711016cc326191006e915153abbc58edb7fc2658f78330
  Compiled from "MetaData.scala"
public final class scala.xml.MetaData$ implements java.io.Serializable
  minor version: 0
  major version: 52
  flags: (0x0031) ACC_PUBLIC, ACC_FINAL, ACC_SUPER
  this_class: #2                          // scala/xml/MetaData$
  super_class: #4                         // java/lang/Object
  interfaces: 1, fields: 1, methods: 8, attributes: 3
Constant pool:
    #1 = Utf8               scala/xml/MetaData$
    #2 = Class              #1            // scala/xml/MetaData$
    #3 = Utf8               java/lang/Object
    #4 = Class              #3            // java/lang/Object
    #5 = Utf8               java/io/Serializable
    #6 = Class              #5            // java/io/Serializable
    #7 = Utf8               MetaData.scala
    #8 = Utf8               MODULE$
    #9 = Utf8               Lscala/xml/MetaData$;
   #10 = Utf8               <clinit>
   #11 = Utf8               ()V
   #12 = Utf8               <init>
   #13 = NameAndType        #12:#11       // "<init>":()V
   #14 = Methodref          #2.#13        // scala/xml/MetaData$."<init>":()V
   #15 = NameAndType        #8:#9         // MODULE$:Lscala/xml/MetaData$;
   #16 = Fieldref           #2.#15        // scala/xml/MetaData$.MODULE$:Lscala/xml/MetaData$;
   #17 = Utf8               concatenate
   #18 = Utf8               (Lscala/xml/MetaData;Lscala/xml/MetaData;)Lscala/xml/MetaData;
   #19 = Utf8               attribs
   #20 = Utf8               new_tail
   #21 = Utf8               scala/xml/Null$
   #22 = Class              #21           // scala/xml/Null$
   #23 = Utf8               Lscala/xml/Null$;
   #24 = NameAndType        #8:#23        // MODULE$:Lscala/xml/Null$;
   #25 = Fieldref           #22.#24       // scala/xml/Null$.MODULE$:Lscala/xml/Null$;
   #26 = Utf8               scala/xml/MetaData
   #27 = Class              #26           // scala/xml/MetaData
   #28 = Utf8               next
   #29 = Utf8               ()Lscala/xml/MetaData;
   #30 = NameAndType        #28:#29       // next:()Lscala/xml/MetaData;
   #31 = Methodref          #27.#30       // scala/xml/MetaData.next:()Lscala/xml/MetaData;
   #32 = Utf8               copy
   #33 = Utf8               (Lscala/xml/MetaData;)Lscala/xml/MetaData;
   #34 = NameAndType        #32:#33       // copy:(Lscala/xml/MetaData;)Lscala/xml/MetaData;
   #35 = Methodref          #27.#34       // scala/xml/MetaData.copy:(Lscala/xml/MetaData;)Lscala/xml/MetaData;
   #36 = Utf8               this
   #37 = Utf8               Lscala/xml/MetaData;
   #38 = Utf8               normalize
   #39 = Utf8               (Lscala/xml/MetaData;Lscala/xml/NamespaceBinding;)Lscala/xml/MetaData;
   #40 = Utf8               scope
   #41 = Utf8               scala/Predef$
   #42 = Class              #41           // scala/Predef$
   #43 = Utf8               Lscala/Predef$;
   #44 = NameAndType        #8:#43        // MODULE$:Lscala/Predef$;
   #45 = Fieldref           #42.#44       // scala/Predef$.MODULE$:Lscala/Predef$;
   #46 = Utf8               Set
   #47 = Utf8               ()Lscala/collection/immutable/Set$;
   #48 = NameAndType        #46:#47       // Set:()Lscala/collection/immutable/Set$;
   #49 = Methodref          #42.#48       // scala/Predef$.Set:()Lscala/collection/immutable/Set$;
   #50 = Utf8               scala/collection/immutable/Nil$
   #51 = Class              #50           // scala/collection/immutable/Nil$
   #52 = Utf8               Lscala/collection/immutable/Nil$;
   #53 = NameAndType        #8:#52        // MODULE$:Lscala/collection/immutable/Nil$;
   #54 = Fieldref           #51.#53       // scala/collection/immutable/Nil$.MODULE$:Lscala/collection/immutable/Nil$;
   #55 = Utf8               scala/collection/immutable/Set$
   #56 = Class              #55           // scala/collection/immutable/Set$
   #57 = Utf8               apply
   #58 = Utf8               (Lscala/collection/immutable/Seq;)Ljava/lang/Object;
   #59 = NameAndType        #57:#58       // apply:(Lscala/collection/immutable/Seq;)Ljava/lang/Object;
   #60 = Methodref          #56.#59       // scala/collection/immutable/Set$.apply:(Lscala/collection/immutable/Seq;)Ljava/lang/Object;
   #61 = Utf8               scala/collection/immutable/Set
   #62 = Class              #61           // scala/collection/immutable/Set
   #63 = Utf8               iterate$1
   #64 = Utf8               (Lscala/xml/MetaData;Lscala/xml/MetaData;Lscala/collection/immutable/Set;Lscala/xml/NamespaceBinding;)Lscala/xml/MetaData;
   #65 = NameAndType        #63:#64       // iterate$1:(Lscala/xml/MetaData;Lscala/xml/MetaData;Lscala/collection/immutable/Set;Lscala/xml/NamespaceBinding;)Lscala/xml/MetaData;
   #66 = Methodref          #2.#65        // scala/xml/MetaData$.iterate$1:(Lscala/xml/MetaData;Lscala/xml/MetaData;Lscala/collection/immutable/Set;Lscala/xml/NamespaceBinding;)Lscala/xml/MetaData;
   #67 = Utf8               Lscala/xml/NamespaceBinding;
   #68 = Utf8               getUniversalKey
   #69 = Utf8               (Lscala/xml/MetaData;Lscala/xml/NamespaceBinding;)Ljava/lang/String;
   #70 = Utf8               attrib
   #71 = Utf8               scala/xml/PrefixedAttribute
   #72 = Class              #71           // scala/xml/PrefixedAttribute
   #73 = Utf8               java/lang/StringBuilder
   #74 = Class              #73           // java/lang/StringBuilder
   #75 = Integer            0
   #76 = Utf8               (I)V
   #77 = NameAndType        #12:#76       // "<init>":(I)V
   #78 = Methodref          #74.#77       // java/lang/StringBuilder."<init>":(I)V
   #79 = Utf8               pre
   #80 = Utf8               ()Ljava/lang/String;
   #81 = NameAndType        #79:#80       // pre:()Ljava/lang/String;
   #82 = Methodref          #72.#81       // scala/xml/PrefixedAttribute.pre:()Ljava/lang/String;
   #83 = Utf8               scala/xml/NamespaceBinding
   #84 = Class              #83           // scala/xml/NamespaceBinding
   #85 = Utf8               getURI
   #86 = Utf8               (Ljava/lang/String;)Ljava/lang/String;
   #87 = NameAndType        #85:#86       // getURI:(Ljava/lang/String;)Ljava/lang/String;
   #88 = Methodref          #84.#87       // scala/xml/NamespaceBinding.getURI:(Ljava/lang/String;)Ljava/lang/String;
   #89 = Utf8               append
   #90 = Utf8               (Ljava/lang/String;)Ljava/lang/StringBuilder;
   #91 = NameAndType        #89:#90       // append:(Ljava/lang/String;)Ljava/lang/StringBuilder;
   #92 = Methodref          #74.#91       // java/lang/StringBuilder.append:(Ljava/lang/String;)Ljava/lang/StringBuilder;
   #93 = Utf8               key
   #94 = NameAndType        #93:#80       // key:()Ljava/lang/String;
   #95 = Methodref          #72.#94       // scala/xml/PrefixedAttribute.key:()Ljava/lang/String;
   #96 = Utf8               toString
   #97 = NameAndType        #96:#80       // toString:()Ljava/lang/String;
   #98 = Methodref          #74.#97       // java/lang/StringBuilder.toString:()Ljava/lang/String;
   #99 = Utf8               scala/xml/UnprefixedAttribute
  #100 = Class              #99           // scala/xml/UnprefixedAttribute
  #101 = Methodref          #100.#94      // scala/xml/UnprefixedAttribute.key:()Ljava/lang/String;
  #102 = Utf8               scala/MatchError
  #103 = Class              #102          // scala/MatchError
  #104 = Utf8               (Ljava/lang/Object;)V
  #105 = NameAndType        #12:#104      // "<init>":(Ljava/lang/Object;)V
  #106 = Methodref          #103.#105     // scala/MatchError."<init>":(Ljava/lang/Object;)V
  #107 = Utf8               java/lang/String
  #108 = Class              #107          // java/lang/String
  #109 = Utf8               update
  #110 = Utf8               (Lscala/xml/MetaData;Lscala/xml/NamespaceBinding;Lscala/xml/MetaData;)Lscala/xml/MetaData;
  #111 = Utf8               updates
  #112 = NameAndType        #17:#18       // concatenate:(Lscala/xml/MetaData;Lscala/xml/MetaData;)Lscala/xml/MetaData;
  #113 = Methodref          #2.#112       // scala/xml/MetaData$.concatenate:(Lscala/xml/MetaData;Lscala/xml/MetaData;)Lscala/xml/MetaData;
  #114 = NameAndType        #38:#39       // normalize:(Lscala/xml/MetaData;Lscala/xml/NamespaceBinding;)Lscala/xml/MetaData;
  #115 = Methodref          #2.#114       // scala/xml/MetaData$.normalize:(Lscala/xml/MetaData;Lscala/xml/NamespaceBinding;)Lscala/xml/MetaData;
  #116 = Utf8               writeReplace
  #117 = Utf8               ()Ljava/lang/Object;
  #118 = Utf8               scala/runtime/ModuleSerializationProxy
  #119 = Class              #118          // scala/runtime/ModuleSerializationProxy
  #120 = Utf8               (Ljava/lang/Class;)V
  #121 = NameAndType        #12:#120      // "<init>":(Ljava/lang/Class;)V
  #122 = Methodref          #119.#121     // scala/runtime/ModuleSerializationProxy."<init>":(Ljava/lang/Class;)V
  #123 = Utf8               md
  #124 = Utf8               normalized_attribs
  #125 = Utf8               set
  #126 = Utf8               scope$1
  #127 = Utf8               value
  #128 = Utf8               ()Lscala/collection/Seq;
  #129 = NameAndType        #127:#128     // value:()Lscala/collection/Seq;
  #130 = Methodref          #27.#129      // scala/xml/MetaData.value:()Lscala/collection/Seq;
  #131 = NameAndType        #68:#69       // getUniversalKey:(Lscala/xml/MetaData;Lscala/xml/NamespaceBinding;)Ljava/lang/String;
  #132 = Methodref          #2.#131       // scala/xml/MetaData$.getUniversalKey:(Lscala/xml/MetaData;Lscala/xml/NamespaceBinding;)Ljava/lang/String;
  #133 = Utf8               (Ljava/lang/Object;)Z
  #134 = NameAndType        #57:#133      // apply:(Ljava/lang/Object;)Z
  #135 = InterfaceMethodref #62.#134      // scala/collection/immutable/Set.apply:(Ljava/lang/Object;)Z
  #136 = Utf8               $plus
  #137 = Utf8               (Ljava/lang/Object;)Lscala/collection/immutable/SetOps;
  #138 = NameAndType        #136:#137     // $plus:(Ljava/lang/Object;)Lscala/collection/immutable/SetOps;
  #139 = InterfaceMethodref #62.#138      // scala/collection/immutable/Set.$plus:(Ljava/lang/Object;)Lscala/collection/immutable/SetOps;
  #140 = Utf8               Ljava/lang/String;
  #141 = Utf8               Lscala/collection/immutable/Set;
  #142 = Methodref          #4.#13        // java/lang/Object."<init>":()V
  #143 = Utf8               Code
  #144 = Utf8               LineNumberTable
  #145 = Utf8               StackMapTable
  #146 = Utf8               LocalVariableTable
  #147 = Utf8               MethodParameters
  #148 = Utf8               SourceFile
  #149 = Utf8               ScalaInlineInfo
  #150 = Utf8               Scala
{
  public static final scala.xml.MetaData$ MODULE$;
    descriptor: Lscala/xml/MetaData$;
    flags: (0x0019) ACC_PUBLIC, ACC_STATIC, ACC_FINAL

  public static {};
    descriptor: ()V
    flags: (0x0009) ACC_PUBLIC, ACC_STATIC
    Code:
      stack=2, locals=0, args_size=0
         0: new           #2                  // class scala/xml/MetaData$
         3: dup
         4: invokespecial #14                 // Method "<init>":()V
         7: putstatic     #16                 // Field MODULE$:Lscala/xml/MetaData$;
        10: return
      LineNumberTable:
        line 21: 0

  public scala.xml.MetaData concatenate(scala.xml.MetaData, scala.xml.MetaData);
    descriptor: (Lscala/xml/MetaData;Lscala/xml/MetaData;)Lscala/xml/MetaData;
    flags: (0x0001) ACC_PUBLIC
    Code:
      stack=3, locals=3, args_size=3
         0: aload_1
         1: getstatic     #25                 // Field scala/xml/Null$.MODULE$:Lscala/xml/Null$;
         4: if_acmpne     11
         7: aload_2
         8: goto          25
        11: aload_1
        12: invokevirtual #31                 // Method scala/xml/MetaData.next:()Lscala/xml/MetaData;
        15: aload_1
        16: aload_2
        17: invokevirtual #35                 // Method scala/xml/MetaData.copy:(Lscala/xml/MetaData;)Lscala/xml/MetaData;
        20: astore_2
        21: astore_1
        22: goto          0
        25: areturn
      StackMapTable: number_of_entries = 3
        frame_type = 0 /* same */
        frame_type = 10 /* same */
        frame_type = 77 /* same_locals_1_stack_item */
          stack = [ class scala/xml/MetaData ]
      LineNumberTable:
        line 32: 0
        line 33: 11
      LocalVariableTable:
        Start  Length  Slot  Name   Signature
            0      26     0  this   Lscala/xml/MetaData$;
            0      26     1 attribs   Lscala/xml/MetaData;
            0      26     2 new_tail   Lscala/xml/MetaData;
    MethodParameters:
      Name                           Flags
      attribs                        final
      new_tail                       final

  public scala.xml.MetaData normalize(scala.xml.MetaData, scala.xml.NamespaceBinding);
    descriptor: (Lscala/xml/MetaData;Lscala/xml/NamespaceBinding;)Lscala/xml/MetaData;
    flags: (0x0001) ACC_PUBLIC
    Code:
      stack=5, locals=3, args_size=3
         0: aload_0
         1: aload_1
         2: getstatic     #25                 // Field scala/xml/Null$.MODULE$:Lscala/xml/Null$;
         5: getstatic     #45                 // Field scala/Predef$.MODULE$:Lscala/Predef$;
         8: invokevirtual #49                 // Method scala/Predef$.Set:()Lscala/collection/immutable/Set$;
        11: getstatic     #54                 // Field scala/collection/immutable/Nil$.MODULE$:Lscala/collection/immutable/Nil$;
        14: invokevirtual #60                 // Method scala/collection/immutable/Set$.apply:(Lscala/collection/immutable/Seq;)Ljava/lang/Object;
        17: checkcast     #62                 // class scala/collection/immutable/Set
        20: aload_2
        21: invokespecial #66                 // Method iterate$1:(Lscala/xml/MetaData;Lscala/xml/MetaData;Lscala/collection/immutable/Set;Lscala/xml/NamespaceBinding;)Lscala/xml/MetaData;
        24: areturn
      LineNumberTable:
        line 54: 0
      LocalVariableTable:
        Start  Length  Slot  Name   Signature
            0      25     0  this   Lscala/xml/MetaData$;
            0      25     1 attribs   Lscala/xml/MetaData;
            0      25     2 scope   Lscala/xml/NamespaceBinding;
    MethodParameters:
      Name                           Flags
      attribs                        final
      scope                          final

  public java.lang.String getUniversalKey(scala.xml.MetaData, scala.xml.NamespaceBinding);
    descriptor: (Lscala/xml/MetaData;Lscala/xml/NamespaceBinding;)Ljava/lang/String;
    flags: (0x0001) ACC_PUBLIC
    Code:
      stack=3, locals=7, args_size=3
         0: aload_1
         1: astore        4
         3: aload         4
         5: instanceof    #72                 // class scala/xml/PrefixedAttribute
         8: ifeq          54
        11: aload         4
        13: checkcast     #72                 // class scala/xml/PrefixedAttribute
        16: astore        5
        18: new           #74                 // class java/lang/StringBuilder
        21: dup
        22: ldc           #75                 // int 0
        24: invokespecial #78                 // Method java/lang/StringBuilder."<init>":(I)V
        27: aload_2
        28: aload         5
        30: invokevirtual #82                 // Method scala/xml/PrefixedAttribute.pre:()Ljava/lang/String;
        33: invokevirtual #88                 // Method scala/xml/NamespaceBinding.getURI:(Ljava/lang/String;)Ljava/lang/String;
        36: invokevirtual #92                 // Method java/lang/StringBuilder.append:(Ljava/lang/String;)Ljava/lang/StringBuilder;
        39: aload         5
        41: invokevirtual #95                 // Method scala/xml/PrefixedAttribute.key:()Ljava/lang/String;
        44: invokevirtual #92                 // Method java/lang/StringBuilder.append:(Ljava/lang/String;)Ljava/lang/StringBuilder;
        47: invokevirtual #98                 // Method java/lang/StringBuilder.toString:()Ljava/lang/String;
        50: astore_3
        51: goto          94
        54: goto          57
        57: aload         4
        59: instanceof    #100                // class scala/xml/UnprefixedAttribute
        62: ifeq          81
        65: aload         4
        67: checkcast     #100                // class scala/xml/UnprefixedAttribute
        70: astore        6
        72: aload         6
        74: invokevirtual #101                // Method scala/xml/UnprefixedAttribute.key:()Ljava/lang/String;
        77: astore_3
        78: goto          94
        81: goto          84
        84: new           #103                // class scala/MatchError
        87: dup
        88: aload         4
        90: invokespecial #106                // Method scala/MatchError."<init>":(Ljava/lang/Object;)V
        93: athrow
        94: aload_3
        95: areturn
      StackMapTable: number_of_entries = 5
        frame_type = 253 /* append */
          offset_delta = 54
          locals = [ top, class scala/xml/MetaData ]
        frame_type = 2 /* same */
        frame_type = 23 /* same */
        frame_type = 2 /* same */
        frame_type = 255 /* full_frame */
          offset_delta = 9
          locals = [ class scala/xml/MetaData$, class scala/xml/MetaData, class scala/xml/NamespaceBinding, class java/lang/String, class scala/xml/MetaData ]
          stack = []
      LineNumberTable:
        line 60: 0
        line 61: 3
        line 62: 57
        line 60: 84
      LocalVariableTable:
        Start  Length  Slot  Name   Signature
            0      96     0  this   Lscala/xml/MetaData$;
            0      96     1 attrib   Lscala/xml/MetaData;
            0      96     2 scope   Lscala/xml/NamespaceBinding;
    MethodParameters:
      Name                           Flags
      attrib                         final
      scope                          final

  public scala.xml.MetaData update(scala.xml.MetaData, scala.xml.NamespaceBinding, scala.xml.MetaData);
    descriptor: (Lscala/xml/MetaData;Lscala/xml/NamespaceBinding;Lscala/xml/MetaData;)Lscala/xml/MetaData;
    flags: (0x0001) ACC_PUBLIC
    Code:
      stack=4, locals=4, args_size=4
         0: aload_0
         1: aload_0
         2: aload_3
         3: aload_1
         4: invokevirtual #113                // Method concatenate:(Lscala/xml/MetaData;Lscala/xml/MetaData;)Lscala/xml/MetaData;
         7: aload_2
         8: invokevirtual #115                // Method normalize:(Lscala/xml/MetaData;Lscala/xml/NamespaceBinding;)Lscala/xml/MetaData;
        11: areturn
      LineNumberTable:
        line 69: 0
      LocalVariableTable:
        Start  Length  Slot  Name   Signature
            0      12     0  this   Lscala/xml/MetaData$;
            0      12     1 attribs   Lscala/xml/MetaData;
            0      12     2 scope   Lscala/xml/NamespaceBinding;
            0      12     3 updates   Lscala/xml/MetaData;
    MethodParameters:
      Name                           Flags
      attribs                        final
      scope                          final
      updates                        final

  private java.lang.Object writeReplace();
    descriptor: ()Ljava/lang/Object;
    flags: (0x0002) ACC_PRIVATE
    Code:
      stack=3, locals=1, args_size=1
         0: new           #119                // class scala/runtime/ModuleSerializationProxy
         3: dup
         4: ldc           #2                  // class scala/xml/MetaData$
         6: invokespecial #122                // Method scala/runtime/ModuleSerializationProxy."<init>":(Ljava/lang/Class;)V
         9: areturn
      LineNumberTable:
        line 21: 0
      LocalVariableTable:
        Start  Length  Slot  Name   Signature
            0      10     0  this   Lscala/xml/MetaData$;

  private final scala.xml.MetaData iterate$1(scala.xml.MetaData, scala.xml.MetaData, scala.collection.immutable.Set, scala.xml.NamespaceBinding);
    descriptor: (Lscala/xml/MetaData;Lscala/xml/MetaData;Lscala/collection/immutable/Set;Lscala/xml/NamespaceBinding;)Lscala/xml/MetaData;
    flags: (0x0012) ACC_PRIVATE, ACC_FINAL
    Code:
      stack=6, locals=7, args_size=5
         0: aload_1
         1: getstatic     #25                 // Field scala/xml/Null$.MODULE$:Lscala/xml/Null$;
         4: if_acmpne     11
         7: aload_2
         8: goto          88
        11: aload_1
        12: invokevirtual #130                // Method scala/xml/MetaData.value:()Lscala/collection/Seq;
        15: ifnonnull     30
        18: aload_1
        19: invokevirtual #31                 // Method scala/xml/MetaData.next:()Lscala/xml/MetaData;
        22: aload_2
        23: aload_3
        24: astore_3
        25: astore_2
        26: astore_1
        27: goto          0
        30: aload_0
        31: aload_1
        32: aload         4
        34: invokevirtual #132                // Method getUniversalKey:(Lscala/xml/MetaData;Lscala/xml/NamespaceBinding;)Ljava/lang/String;
        37: astore        6
        39: aload_3
        40: aload         6
        42: invokeinterface #135,  2          // InterfaceMethod scala/collection/immutable/Set.apply:(Ljava/lang/Object;)Z
        47: ifeq          62
        50: aload_1
        51: invokevirtual #31                 // Method scala/xml/MetaData.next:()Lscala/xml/MetaData;
        54: aload_2
        55: aload_3
        56: astore_3
        57: astore_2
        58: astore_1
        59: goto          0
        62: aload_1
        63: aload_0
        64: aload_1
        65: invokevirtual #31                 // Method scala/xml/MetaData.next:()Lscala/xml/MetaData;
        68: aload_2
        69: aload_3
        70: aload         6
        72: invokeinterface #139,  2          // InterfaceMethod scala/collection/immutable/Set.$plus:(Ljava/lang/Object;)Lscala/collection/immutable/SetOps;
        77: checkcast     #62                 // class scala/collection/immutable/Set
        80: aload         4
        82: invokespecial #66                 // Method iterate$1:(Lscala/xml/MetaData;Lscala/xml/MetaData;Lscala/collection/immutable/Set;Lscala/xml/NamespaceBinding;)Lscala/xml/MetaData;
        85: invokevirtual #35                 // Method scala/xml/MetaData.copy:(Lscala/xml/MetaData;)Lscala/xml/MetaData;
        88: areturn
      StackMapTable: number_of_entries = 5
        frame_type = 0 /* same */
        frame_type = 10 /* same */
        frame_type = 18 /* same */
        frame_type = 253 /* append */
          offset_delta = 31
          locals = [ top, class java/lang/String ]
        frame_type = 255 /* full_frame */
          offset_delta = 25
          locals = [ class scala/xml/MetaData$, class scala/xml/MetaData, class scala/xml/MetaData, class scala/collection/immutable/Set, class scala/xml/NamespaceBinding ]
          stack = [ class scala/xml/MetaData ]
      LineNumberTable:
        line 41: 0
        line 42: 7
        line 43: 11
        line 44: 18
        line 46: 30
        line 47: 39
        line 48: 50
        line 50: 62
      LocalVariableTable:
        Start  Length  Slot  Name   Signature
           39      49     6   key   Ljava/lang/String;
            0      89     0  this   Lscala/xml/MetaData$;
            0      89     1    md   Lscala/xml/MetaData;
            0      89     2 normalized_attribs   Lscala/xml/MetaData;
            0      89     3   set   Lscala/collection/immutable/Set;
            0      89     4 scope$1   Lscala/xml/NamespaceBinding;
    MethodParameters:
      Name                           Flags
      md                             final
      normalized_attribs             final
      set                            final
      scope$1                        final

  private scala.xml.MetaData$();
    descriptor: ()V
    flags: (0x0002) ACC_PRIVATE
    Code:
      stack=1, locals=1, args_size=1
         0: aload_0
         1: invokespecial #142                // Method java/lang/Object."<init>":()V
         4: return
      LineNumberTable:
        line 83: 0
        line 21: 4
      LocalVariableTable:
        Start  Length  Slot  Name   Signature
            0       5     0  this   Lscala/xml/MetaData$;
}
SourceFile: "MetaData.scala"
  ScalaInlineInfo: length = 0x27 (unknown attribute)
   01 01 00 07 00 0C 00 0B 01 00 11 00 12 01 00 44
   00 45 01 00 3F 00 40 01 00 26 00 27 01 00 6D 00
   6E 01 00 74 00 75 01
  Scala: length = 0x0 (unknown attribute)

