Classfile /Users/mw/Projects/slang-braindump/.jar/jar11/assemble/slang-braindump/assemble/content/scala/xml/NamespaceBinding.class
  Last modified May 29, 2022; size 13556 bytes
  SHA-256 checksum 1d2839ebfdd165022be428ba9350786922823992edea7a1611ab3705f826121e
  Compiled from "NamespaceBinding.scala"
public class scala.xml.NamespaceBinding implements scala.xml.Equality,scala.Product,java.io.Serializable
  minor version: 0
  major version: 52
  flags: (0x0021) ACC_PUBLIC, ACC_SUPER
  this_class: #2                          // scala/xml/NamespaceBinding
  super_class: #4                         // java/lang/Object
  interfaces: 3, fields: 4, methods: 40, attributes: 6
Constant pool:
    #1 = Utf8               scala/xml/NamespaceBinding
    #2 = Class              #1            // scala/xml/NamespaceBinding
    #3 = Utf8               java/lang/Object
    #4 = Class              #3            // java/lang/Object
    #5 = Utf8               scala/xml/Equality
    #6 = Class              #5            // scala/xml/Equality
    #7 = Utf8               scala/Product
    #8 = Class              #7            // scala/Product
    #9 = Utf8               java/io/Serializable
   #10 = Class              #9            // java/io/Serializable
   #11 = Utf8               NamespaceBinding.scala
   #12 = Utf8               Lscala/reflect/ScalaSignature;
   #13 = Utf8               bytes
   #14 = Utf8               \u0006\u0005\u0005%g\u0001\u0002\u0012$\u0001\"B\u0001\u0002\u0011\u0001\u0003\u0016\u0004%\t!\u0011\u0005\t\u0015\u0002\u0011\t\u0012)A\u0005\u0005\"A1\n\u0001BK\u0002\u0013\u0005\u0011\t\u0003\u0005M\u0001\tE\t\u0015!\u0003C\u0011!i\u0005A!f\u0001\n\u0003q\u0005\u0002\u0003)\u0001\u0005#\u0005\u000b\u0011B(\t\u000bE\u0003A\u0011\u0001*\t\u000bY\u0003A\u0011A,\t\u000bi\u0003A\u0011A.\t\u000by\u0003A\u0011I0\t\u000b\u0001\u0004A\u0011B1\t\u000b\u0011\u0004A\u0011I3\t\u000b9\u0004A\u0011I8\t\u000bE\u0004A\u0011\u0001:\t\u000be\u0004A\u0011\u0001>\t\u000be\u0004A\u0011\u0001?\t\u000f\u0005=\u0001\u0001\"\u0003\u0002\u0012!I\u0011q\u0003\u0001\u0002\u0002\u0013\u0005\u0011\u0011\u0004\u0005\n\u0003C\u0001\u0011\u0013!C\u0001\u0003GA\u0011\"!\u000f\u0001#\u0003%\t!a\t\t\u0013\u0005m\u0002!%A\u0005\u0002\u0005u\u0002\"CA!\u0001\u0005\u0005I\u0011IA\"\u0011%\t\u0019\u0006AA\u0001\n\u0003\t)\u0006C\u0005\u0002^\u0001\t\t\u0011\"\u0001\u0002`!I\u0011Q\r\u0001\u0002\u0002\u0013\u0005\u0013q\r\u0005\n\u0003_\u0002\u0011\u0011!C!\u0003c:\u0011\"!!$\u0003\u0003E\t!a!\u0007\u0011\t\u001a\u0013\u0011!E\u0001\u0003\u000bCa!\u0015\u000f\u0005\u0002\u0005u\u0005\u0002\u00030\u001d\u0003\u0003%)%a(\t\u0013\u0005\u0005F$!A\u0005\u0002\u0006\r\u0006\"CAV9\u0005\u0005I\u0011QAW\u0011%\ty\fHA\u0001\n\u0013\t\tM\u0001\tOC6,7\u000f]1dK\nKg\u000eZ5oO*\u0011A%J\u0001\u0004q6d\'\"\u0001\u0014\u0002\u000bM\u001c\u0017\r\\1\u0004\u0001M)\u0001!K\u00172iA\u0011!fK\u0007\u0002K%\u0011A&\n\u0002\u0007\u0003:L(+\u001a4\u0011\u00059zS\"A\u0012\n\u0005A\u001a#\u0001C#rk\u0006d\u0017\u000e^=\u0011\u0005)\u0012\u0014BA\u001a&\u0005\u001d\u0001&o\u001c3vGR\u0004\"!N\u001f\u000f\u0005YZdBA\u001c;\u001b\u0005A$BA\u001d(\u0003\u0019a$o\\8u}%\ta%\u0003\u0002=K\u00059\u0001/Y2lC\u001e,\u0017B\u0001 @\u00051\u0019VM]5bY&T\u0018M\u00197f\u0015\taT%\u0001\u0004qe\u00164\u0017\u000e_\u000b\u0002\u0005B\u00111i\u0012\b\u0003\t\u0016\u0003\"aN\u0013\n\u0005\u0019+\u0013A\u0002)sK\u0012,g-\u0003\u0002I\u0013\n11\u000b\u001e:j]\u001eT!AR\u0013\u0002\u000fA\u0014XMZ5yA\u0005\u0019QO]5\u0002\tU\u0014\u0018\u000eI\u0001\u0007a\u0006\u0014XM\u001c;\u0016\u0003=\u0003\"A\f\u0001\u0002\u000fA\f\'/\u001a8uA\u00051A(\u001b8jiz\"BaT*U+\")\u0001i\u0002a\u0001\u0005\")1j\u0002a\u0001\u0005\")Qj\u0002a\u0001\u001f\u00061q-\u001a;V%&#\"A\u0011-\t\u000beC\u0001\u0019\u0001\"\u0002\u000f}\u0003(/\u001a4jq\u0006Iq-\u001a;Qe\u00164\u0017\u000e\u001f\u000b\u0003\u0005rCQ!X\u0005A\u0002\t\u000bAaX;sS\u0006AAo\\*ue&tw\rF\u0001C\u0003=\u0019\b.\u00193poJ+G-\u001a4j]\u0016$GCA(c\u0011\u0015\u00197\u00021\u0001P\u0003\u0011\u0019Ho\u001c9\u0002\u0011\r\fg.R9vC2$\"AZ5\u0011\u0005):\u0017B\u00015&\u0005\u001d\u0011un\u001c7fC:DQA\u001b\u0007A\u0002-\fQa\u001c;iKJ\u0004\"A\u000b7\n\u00055,#aA!os\u0006i1\u000f\u001e:jGR|F%Z9%KF$\"A\u001a9\t\u000b)l\u0001\u0019A\u0017\u0002!\t\f7/[:G_JD\u0015m\u001d5D_\u0012,W#A:\u0011\u0007Q<8.D\u0001v\u0015\t1X%\u0001\u0006d_2dWm\u0019;j_:L!\u0001_;\u0003\u0007M+\u0017/A\u0006ck&dGm\u0015;sS:<GC\u0001\"|\u0011\u0015\u0019w\u00021\u0001P)\u0015i\u0018\u0011AA\u0007!\tQc0\u0003\u0002\u0000K\t!QK\\5u\u0011\u001d\t\u0019\u0001\u0005a\u0001\u0003\u000b\t!a\u001d2\u0011\t\u0005\u001d\u0011\u0011\u0002\b\u0003UmJ1!a\u0003@\u00055\u0019FO]5oO\n+\u0018\u000e\u001c3fe\")1\r\u0005a\u0001\u001f\u0006iAm\u001c\"vS2$7\u000b\u001e:j]\u001e$R!`A\n\u0003+Aq!a\u0001\u0012\u0001\u0004\t)\u0001C\u0003d#\u0001\u0007q*\u0001\u0003d_BLHcB(\u0002\u001c\u0005u\u0011q\u0004\u0005\b\u0001J\u0001\n\u00111\u0001C\u0011\u001dY%\u0003%AA\u0002\tCq!\u0014\n\u0011\u0002\u0003\u0007q*\u0001\bd_BLH\u0005Z3gCVdG\u000fJ\u0019\u0016\u0005\u0005\u0015\"f\u0001\"\u0002(-\u0012\u0011\u0011\u0006\t\u0005\u0003W\t)$\u0004\u0002\u0002.)!\u0011qFA\u0019\u0003%)hn\u00195fG.,GMC\u0002\u00024\u0015\n!\"\u00198o_R\fG/[8o\u0013\u0011\t9$!\f\u0003#Ut7\r[3dW\u0016$g+\u0019:jC:\u001cW-\u0001\bd_BLH\u0005Z3gCVdG\u000f\n\u001a\u0002\u001d\r|\u0007/\u001f\u0013eK\u001a\fW\u000f\u001c;%gU\u0011\u0011q\b\u0016\u0004\u001f\u0006\u001d\u0012!\u00049s_\u0012,8\r\u001e)sK\u001aL\u00070\u0006\u0002\u0002FA!\u0011qIA)\u001b\t\tIE\u0003\u0003\u0002L\u00055\u0013\u0001\u00027b]\u001eT!!a\u0014\u0002\t)\fg/Y\u0005\u0004\u0011\u0006%\u0013\u0001\u00049s_\u0012,8\r^!sSRLXCAA,!\rQ\u0013\u0011L\u0005\u0004\u00037*#aA%oi\u0006q\u0001O]8ek\u000e$X\t\\3nK:$HcA6\u0002b!I\u00111\r\r\u0002\u0002\u0003\u0007\u0011qK\u0001\u0004q\u0012\n\u0014a\u00049s_\u0012,8\r^%uKJ\fGo\u001c:\u0016\u0005\u0005%\u0004\u0003\u0002;\u0002l-L1!!\u001cv\u0005!IE/\u001a:bi>\u0014\u0018A\u00059s_\u0012,8\r^#mK6,g\u000e\u001e(b[\u0016$B!!\u0012\u0002t!I\u00111\r\u000e\u0002\u0002\u0003\u0007\u0011q\u000b\u0015\b\u0001\u0005]\u0014QPA@!\rQ\u0013\u0011P\u0005\u0004\u0003w*#\u0001E*fe&\fGNV3sg&|g.V%E\u0003\u00151\u0018\r\\;f=!i>B\u007f=LFN\\\u001c\u0001\u0005(b[\u0016\u001c\b/Y2f\u0005&tG-\u001b8h!\tqCdE\u0003\u001d\u0003\u000f\u000b\u0019\n\u0005\u0005\u0002\n\u0006=%IQ(P\u001b\t\tYIC\u0002\u0002\u000e\u0016\nqA];oi&lW-\u0003\u0003\u0002\u0012\u0006-%!E!cgR\u0014\u0018m\u0019;Gk:\u001cG/[8ogA!\u0011QSAN\u001b\t\t9J\u0003\u0003\u0002\u001a\u00065\u0013AA5p\u0013\rq\u0014q\u0013\u000b\u0003\u0003\u0007#\"!!\u0012\u0002\u000b\u0005\u0004\b\u000f\\=\u0015\u000f=\u000b)+a*\u0002*\")\u0001i\ba\u0001\u0005\")1j\ba\u0001\u0005\")Qj\ba\u0001\u001f\u00069QO\\1qa2LH\u0003BAX\u0003w\u0003RAKAY\u0003kK1!a-&\u0005\u0019y\u0005\u000f^5p]B1!&a.C\u0005>K1!!/&\u0005\u0019!V\u000f\u001d7fg!A\u0011Q\u0018\u0011\u0002\u0002\u0003\u0007q*A\u0002yIA\nAb\u001e:ji\u0016\u0014V\r\u001d7bG\u0016$\"!a1\u0011\t\u0005\u001d\u0013QY\u0005\u0005\u0003\u000f\fIE\u0001\u0004PE*,7\r\u001e
   #15 = Utf8               java/lang/invoke/MethodHandles$Lookup
   #16 = Class              #15           // java/lang/invoke/MethodHandles$Lookup
   #17 = Utf8               java/lang/invoke/MethodHandles
   #18 = Class              #17           // java/lang/invoke/MethodHandles
   #19 = Utf8               Lookup
   #20 = Utf8               serialVersionUID
   #21 = Utf8               J
   #22 = Long               -2518644165573446725l
   #24 = Utf8               prefix
   #25 = Utf8               Ljava/lang/String;
   #26 = Utf8               uri
   #27 = Utf8               parent
   #28 = Utf8               Lscala/xml/NamespaceBinding;
   #29 = Utf8               unapply
   #30 = Utf8               (Lscala/xml/NamespaceBinding;)Lscala/Option;
   #31 = Utf8               (Lscala/xml/NamespaceBinding;)Lscala/Option<Lscala/Tuple3<Ljava/lang/String;Ljava/lang/String;Lscala/xml/NamespaceBinding;>;>;
   #32 = Utf8               x$0
   #33 = Utf8               scala/xml/NamespaceBinding$
   #34 = Class              #33           // scala/xml/NamespaceBinding$
   #35 = Utf8               MODULE$
   #36 = Utf8               Lscala/xml/NamespaceBinding$;
   #37 = NameAndType        #35:#36       // MODULE$:Lscala/xml/NamespaceBinding$;
   #38 = Fieldref           #34.#37       // scala/xml/NamespaceBinding$.MODULE$:Lscala/xml/NamespaceBinding$;
   #39 = NameAndType        #29:#30       // unapply:(Lscala/xml/NamespaceBinding;)Lscala/Option;
   #40 = Methodref          #34.#39       // scala/xml/NamespaceBinding$.unapply:(Lscala/xml/NamespaceBinding;)Lscala/Option;
   #41 = Utf8               apply
   #42 = Utf8               (Ljava/lang/String;Ljava/lang/String;Lscala/xml/NamespaceBinding;)Lscala/xml/NamespaceBinding;
   #43 = NameAndType        #41:#42       // apply:(Ljava/lang/String;Ljava/lang/String;Lscala/xml/NamespaceBinding;)Lscala/xml/NamespaceBinding;
   #44 = Methodref          #34.#43       // scala/xml/NamespaceBinding$.apply:(Ljava/lang/String;Ljava/lang/String;Lscala/xml/NamespaceBinding;)Lscala/xml/NamespaceBinding;
   #45 = Utf8               tupled
   #46 = Utf8               ()Lscala/Function1;
   #47 = Utf8               ()Lscala/Function1<Lscala/Tuple3<Ljava/lang/String;Ljava/lang/String;Lscala/xml/NamespaceBinding;>;Lscala/xml/NamespaceBinding;>;
   #48 = NameAndType        #45:#46       // tupled:()Lscala/Function1;
   #49 = Methodref          #34.#48       // scala/xml/NamespaceBinding$.tupled:()Lscala/Function1;
   #50 = Utf8               curried
   #51 = Utf8               ()Lscala/Function1<Ljava/lang/String;Lscala/Function1<Ljava/lang/String;Lscala/Function1<Lscala/xml/NamespaceBinding;Lscala/xml/NamespaceBinding;>;>;>;
   #52 = NameAndType        #50:#46       // curried:()Lscala/Function1;
   #53 = Methodref          #34.#52       // scala/xml/NamespaceBinding$.curried:()Lscala/Function1;
   #54 = Utf8               productElementNames
   #55 = Utf8               ()Lscala/collection/Iterator;
   #56 = Utf8               ()Lscala/collection/Iterator<Ljava/lang/String;>;
   #57 = Utf8               productElementNames$
   #58 = Utf8               (Lscala/Product;)Lscala/collection/Iterator;
   #59 = NameAndType        #57:#58       // productElementNames$:(Lscala/Product;)Lscala/collection/Iterator;
   #60 = InterfaceMethodref #8.#59        // scala/Product.productElementNames$:(Lscala/Product;)Lscala/collection/Iterator;
   #61 = Utf8               this
   #62 = Utf8               strict_$bang$eq
   #63 = Utf8               (Lscala/xml/Equality;)Z
   #64 = Utf8               other
   #65 = Utf8               strict_$bang$eq$
   #66 = Utf8               (Lscala/xml/Equality;Lscala/xml/Equality;)Z
   #67 = NameAndType        #65:#66       // strict_$bang$eq$:(Lscala/xml/Equality;Lscala/xml/Equality;)Z
   #68 = InterfaceMethodref #6.#67        // scala/xml/Equality.strict_$bang$eq$:(Lscala/xml/Equality;Lscala/xml/Equality;)Z
   #69 = Utf8               Lscala/xml/Equality;
   #70 = Utf8               hashCode
   #71 = Utf8               ()I
   #72 = Utf8               hashCode$
   #73 = Utf8               (Lscala/xml/Equality;)I
   #74 = NameAndType        #72:#73       // hashCode$:(Lscala/xml/Equality;)I
   #75 = InterfaceMethodref #6.#74        // scala/xml/Equality.hashCode$:(Lscala/xml/Equality;)I
   #76 = Utf8               equals
   #77 = Utf8               (Ljava/lang/Object;)Z
   #78 = Utf8               equals$
   #79 = Utf8               (Lscala/xml/Equality;Ljava/lang/Object;)Z
   #80 = NameAndType        #78:#79       // equals$:(Lscala/xml/Equality;Ljava/lang/Object;)Z
   #81 = InterfaceMethodref #6.#80        // scala/xml/Equality.equals$:(Lscala/xml/Equality;Ljava/lang/Object;)Z
   #82 = Utf8               Ljava/lang/Object;
   #83 = Utf8               xml_$eq$eq
   #84 = Utf8               xml_$eq$eq$
   #85 = NameAndType        #84:#79       // xml_$eq$eq$:(Lscala/xml/Equality;Ljava/lang/Object;)Z
   #86 = InterfaceMethodref #6.#85        // scala/xml/Equality.xml_$eq$eq$:(Lscala/xml/Equality;Ljava/lang/Object;)Z
   #87 = Utf8               xml_$bang$eq
   #88 = Utf8               xml_$bang$eq$
   #89 = NameAndType        #88:#79       // xml_$bang$eq$:(Lscala/xml/Equality;Ljava/lang/Object;)Z
   #90 = InterfaceMethodref #6.#89        // scala/xml/Equality.xml_$bang$eq$:(Lscala/xml/Equality;Ljava/lang/Object;)Z
   #91 = Utf8               ()Ljava/lang/String;
   #92 = NameAndType        #24:#25       // prefix:Ljava/lang/String;
   #93 = Fieldref           #2.#92        // scala/xml/NamespaceBinding.prefix:Ljava/lang/String;
   #94 = NameAndType        #26:#25       // uri:Ljava/lang/String;
   #95 = Fieldref           #2.#94        // scala/xml/NamespaceBinding.uri:Ljava/lang/String;
   #96 = Utf8               ()Lscala/xml/NamespaceBinding;
   #97 = NameAndType        #27:#28       // parent:Lscala/xml/NamespaceBinding;
   #98 = Fieldref           #2.#97        // scala/xml/NamespaceBinding.parent:Lscala/xml/NamespaceBinding;
   #99 = Utf8               getURI
  #100 = Utf8               (Ljava/lang/String;)Ljava/lang/String;
  #101 = Utf8               _prefix
  #102 = NameAndType        #24:#91       // prefix:()Ljava/lang/String;
  #103 = Methodref          #2.#102       // scala/xml/NamespaceBinding.prefix:()Ljava/lang/String;
  #104 = NameAndType        #76:#77       // equals:(Ljava/lang/Object;)Z
  #105 = Methodref          #4.#104       // java/lang/Object.equals:(Ljava/lang/Object;)Z
  #106 = NameAndType        #26:#91       // uri:()Ljava/lang/String;
  #107 = Methodref          #2.#106       // scala/xml/NamespaceBinding.uri:()Ljava/lang/String;
  #108 = NameAndType        #27:#96       // parent:()Lscala/xml/NamespaceBinding;
  #109 = Methodref          #2.#108       // scala/xml/NamespaceBinding.parent:()Lscala/xml/NamespaceBinding;
  #110 = NameAndType        #99:#100      // getURI:(Ljava/lang/String;)Ljava/lang/String;
  #111 = Methodref          #2.#110       // scala/xml/NamespaceBinding.getURI:(Ljava/lang/String;)Ljava/lang/String;
  #112 = Utf8               java/lang/String
  #113 = Class              #112          // java/lang/String
  #114 = Utf8               getPrefix
  #115 = Utf8               _uri
  #116 = NameAndType        #114:#100     // getPrefix:(Ljava/lang/String;)Ljava/lang/String;
  #117 = Methodref          #2.#116       // scala/xml/NamespaceBinding.getPrefix:(Ljava/lang/String;)Ljava/lang/String;
  #118 = Utf8               toString
  #119 = Utf8               scala/xml/Utility$
  #120 = Class              #119          // scala/xml/Utility$
  #121 = Utf8               Lscala/xml/Utility$;
  #122 = NameAndType        #35:#121      // MODULE$:Lscala/xml/Utility$;
  #123 = Fieldref           #120.#122     // scala/xml/Utility$.MODULE$:Lscala/xml/Utility$;
  #124 = Utf8               (Ljava/lang/Object;)Ljava/lang/Object;
  #125 = MethodType         #124          //  (Ljava/lang/Object;)Ljava/lang/Object;
  #126 = Utf8               $anonfun$toString$1$adapted
  #127 = Utf8               (Lscala/xml/NamespaceBinding;Lscala/collection/mutable/StringBuilder;)Ljava/lang/Object;
  #128 = NameAndType        #126:#127     // $anonfun$toString$1$adapted:(Lscala/xml/NamespaceBinding;Lscala/collection/mutable/StringBuilder;)Ljava/lang/Object;
  #129 = Methodref          #2.#128       // scala/xml/NamespaceBinding.$anonfun$toString$1$adapted:(Lscala/xml/NamespaceBinding;Lscala/collection/mutable/StringBuilder;)Ljava/lang/Object;
  #130 = MethodHandle       6:#129        // REF_invokeStatic scala/xml/NamespaceBinding.$anonfun$toString$1$adapted:(Lscala/xml/NamespaceBinding;Lscala/collection/mutable/StringBuilder;)Ljava/lang/Object;
  #131 = Utf8               (Lscala/collection/mutable/StringBuilder;)Ljava/lang/Object;
  #132 = MethodType         #131          //  (Lscala/collection/mutable/StringBuilder;)Ljava/lang/Object;
  #133 = Integer            5
  #134 = Integer            1
  #135 = Utf8               java/lang/invoke/LambdaMetafactory
  #136 = Class              #135          // java/lang/invoke/LambdaMetafactory
  #137 = Utf8               altMetafactory
  #138 = Utf8               (Ljava/lang/invoke/MethodHandles$Lookup;Ljava/lang/String;Ljava/lang/invoke/MethodType;[Ljava/lang/Object;)Ljava/lang/invoke/CallSite;
  #139 = NameAndType        #137:#138     // altMetafactory:(Ljava/lang/invoke/MethodHandles$Lookup;Ljava/lang/String;Ljava/lang/invoke/MethodType;[Ljava/lang/Object;)Ljava/lang/invoke/CallSite;
  #140 = Methodref          #136.#139     // java/lang/invoke/LambdaMetafactory.altMetafactory:(Ljava/lang/invoke/MethodHandles$Lookup;Ljava/lang/String;Ljava/lang/invoke/MethodType;[Ljava/lang/Object;)Ljava/lang/invoke/CallSite;
  #141 = MethodHandle       6:#140        // REF_invokeStatic java/lang/invoke/LambdaMetafactory.altMetafactory:(Ljava/lang/invoke/MethodHandles$Lookup;Ljava/lang/String;Ljava/lang/invoke/MethodType;[Ljava/lang/Object;)Ljava/lang/invoke/CallSite;
  #142 = Utf8               (Lscala/xml/NamespaceBinding;)Lscala/Function1;
  #143 = NameAndType        #41:#142      // apply:(Lscala/xml/NamespaceBinding;)Lscala/Function1;
  #144 = InvokeDynamic      #0:#143       // #0:apply:(Lscala/xml/NamespaceBinding;)Lscala/Function1;
  #145 = Utf8               sbToString
  #146 = Utf8               (Lscala/Function1;)Ljava/lang/String;
  #147 = NameAndType        #145:#146     // sbToString:(Lscala/Function1;)Ljava/lang/String;
  #148 = Methodref          #120.#147     // scala/xml/Utility$.sbToString:(Lscala/Function1;)Ljava/lang/String;
  #149 = Utf8               shadowRedefined
  #150 = Utf8               (Lscala/xml/NamespaceBinding;)Lscala/xml/NamespaceBinding;
  #151 = Utf8               stop
  #152 = Utf8               prefixList$1
  #153 = Utf8               (Lscala/xml/NamespaceBinding;Lscala/xml/NamespaceBinding;)Lscala/collection/immutable/List;
  #154 = NameAndType        #152:#153     // prefixList$1:(Lscala/xml/NamespaceBinding;Lscala/xml/NamespaceBinding;)Lscala/collection/immutable/List;
  #155 = Methodref          #2.#154       // scala/xml/NamespaceBinding.prefixList$1:(Lscala/xml/NamespaceBinding;Lscala/xml/NamespaceBinding;)Lscala/collection/immutable/List;
  #156 = Utf8               scala/collection/immutable/List
  #157 = Class              #156          // scala/collection/immutable/List
  #158 = Utf8               reverse
  #159 = Utf8               ()Lscala/collection/immutable/List;
  #160 = NameAndType        #158:#159     // reverse:()Lscala/collection/immutable/List;
  #161 = Methodref          #157.#160     // scala/collection/immutable/List.reverse:()Lscala/collection/immutable/List;
  #162 = Utf8               distinct
  #163 = Utf8               ()Ljava/lang/Object;
  #164 = NameAndType        #162:#163     // distinct:()Ljava/lang/Object;
  #165 = Methodref          #157.#164     // scala/collection/immutable/List.distinct:()Ljava/lang/Object;
  #166 = Utf8               size
  #167 = NameAndType        #166:#71      // size:()I
  #168 = Methodref          #157.#167     // scala/collection/immutable/List.size:()I
  #169 = Utf8               fromPrefixList$1
  #170 = Utf8               (Lscala/collection/immutable/List;Lscala/xml/NamespaceBinding;)Lscala/xml/NamespaceBinding;
  #171 = NameAndType        #169:#170     // fromPrefixList$1:(Lscala/collection/immutable/List;Lscala/xml/NamespaceBinding;)Lscala/xml/NamespaceBinding;
  #172 = Methodref          #2.#171       // scala/xml/NamespaceBinding.fromPrefixList$1:(Lscala/collection/immutable/List;Lscala/xml/NamespaceBinding;)Lscala/xml/NamespaceBinding;
  #173 = Utf8               ps0
  #174 = Utf8               Lscala/collection/immutable/List;
  #175 = Utf8               ps
  #176 = Utf8               canEqual
  #177 = Utf8               strict_$eq$eq
  #178 = Utf8               basisForHashCode
  #179 = Utf8               ()Lscala/collection/Seq;
  #180 = Utf8               ()Lscala/collection/Seq<Ljava/lang/Object;>;
  #181 = Utf8               scala/package$
  #182 = Class              #181          // scala/package$
  #183 = Utf8               Lscala/package$;
  #184 = NameAndType        #35:#183      // MODULE$:Lscala/package$;
  #185 = Fieldref           #182.#184     // scala/package$.MODULE$:Lscala/package$;
  #186 = Utf8               List
  #187 = Utf8               ()Lscala/collection/immutable/List$;
  #188 = NameAndType        #186:#187     // List:()Lscala/collection/immutable/List$;
  #189 = Methodref          #182.#188     // scala/package$.List:()Lscala/collection/immutable/List$;
  #190 = Utf8               scala/runtime/ScalaRunTime$
  #191 = Class              #190          // scala/runtime/ScalaRunTime$
  #192 = Utf8               Lscala/runtime/ScalaRunTime$;
  #193 = NameAndType        #35:#192      // MODULE$:Lscala/runtime/ScalaRunTime$;
  #194 = Fieldref           #191.#193     // scala/runtime/ScalaRunTime$.MODULE$:Lscala/runtime/ScalaRunTime$;
  #195 = Utf8               wrapRefArray
  #196 = Utf8               ([Ljava/lang/Object;)Lscala/collection/immutable/ArraySeq;
  #197 = NameAndType        #195:#196     // wrapRefArray:([Ljava/lang/Object;)Lscala/collection/immutable/ArraySeq;
  #198 = Methodref          #191.#197     // scala/runtime/ScalaRunTime$.wrapRefArray:([Ljava/lang/Object;)Lscala/collection/immutable/ArraySeq;
  #199 = Utf8               scala/collection/immutable/List$
  #200 = Class              #199          // scala/collection/immutable/List$
  #201 = Utf8               (Lscala/collection/immutable/Seq;)Ljava/lang/Object;
  #202 = NameAndType        #41:#201      // apply:(Lscala/collection/immutable/Seq;)Ljava/lang/Object;
  #203 = Methodref          #200.#202     // scala/collection/immutable/List$.apply:(Lscala/collection/immutable/Seq;)Ljava/lang/Object;
  #204 = Utf8               scala/collection/Seq
  #205 = Class              #204          // scala/collection/Seq
  #206 = Utf8               buildString
  #207 = Utf8               (Lscala/xml/NamespaceBinding;)Ljava/lang/String;
  #208 = Utf8               $anonfun$buildString$1$adapted
  #209 = Utf8               (Lscala/xml/NamespaceBinding;Lscala/xml/NamespaceBinding;Lscala/collection/mutable/StringBuilder;)Ljava/lang/Object;
  #210 = NameAndType        #208:#209     // $anonfun$buildString$1$adapted:(Lscala/xml/NamespaceBinding;Lscala/xml/NamespaceBinding;Lscala/collection/mutable/StringBuilder;)Ljava/lang/Object;
  #211 = Methodref          #2.#210       // scala/xml/NamespaceBinding.$anonfun$buildString$1$adapted:(Lscala/xml/NamespaceBinding;Lscala/xml/NamespaceBinding;Lscala/collection/mutable/StringBuilder;)Ljava/lang/Object;
  #212 = MethodHandle       6:#211        // REF_invokeStatic scala/xml/NamespaceBinding.$anonfun$buildString$1$adapted:(Lscala/xml/NamespaceBinding;Lscala/xml/NamespaceBinding;Lscala/collection/mutable/StringBuilder;)Ljava/lang/Object;
  #213 = Utf8               (Lscala/xml/NamespaceBinding;Lscala/xml/NamespaceBinding;)Lscala/Function1;
  #214 = NameAndType        #41:#213      // apply:(Lscala/xml/NamespaceBinding;Lscala/xml/NamespaceBinding;)Lscala/Function1;
  #215 = InvokeDynamic      #1:#214       // #1:apply:(Lscala/xml/NamespaceBinding;Lscala/xml/NamespaceBinding;)Lscala/Function1;
  #216 = Utf8               (Lscala/collection/mutable/StringBuilder;Lscala/xml/NamespaceBinding;)V
  #217 = Utf8               sb
  #218 = NameAndType        #149:#150     // shadowRedefined:(Lscala/xml/NamespaceBinding;)Lscala/xml/NamespaceBinding;
  #219 = Methodref          #2.#218       // scala/xml/NamespaceBinding.shadowRedefined:(Lscala/xml/NamespaceBinding;)Lscala/xml/NamespaceBinding;
  #220 = Utf8               doBuildString
  #221 = NameAndType        #220:#216     // doBuildString:(Lscala/collection/mutable/StringBuilder;Lscala/xml/NamespaceBinding;)V
  #222 = Methodref          #2.#221       // scala/xml/NamespaceBinding.doBuildString:(Lscala/collection/mutable/StringBuilder;Lscala/xml/NamespaceBinding;)V
  #223 = Utf8               Lscala/collection/mutable/StringBuilder;
  #224 = Utf8               scala/xml/TopScope$
  #225 = Class              #224          // scala/xml/TopScope$
  #226 = Utf8               Lscala/xml/TopScope$;
  #227 = NameAndType        #35:#226      // MODULE$:Lscala/xml/TopScope$;
  #228 = Fieldref           #225.#227     // scala/xml/TopScope$.MODULE$:Lscala/xml/TopScope$;
  #229 = Utf8               [Ljava/lang/Object;
  #230 = Class              #229          // "[Ljava/lang/Object;"
  #231 = Utf8               contains
  #232 = NameAndType        #231:#77      // contains:(Ljava/lang/Object;)Z
  #233 = Methodref          #157.#232     // scala/collection/immutable/List.contains:(Ljava/lang/Object;)Z
  #234 = Utf8               scala/collection/StringOps$
  #235 = Class              #234          // scala/collection/StringOps$
  #236 = Utf8               Lscala/collection/StringOps$;
  #237 = NameAndType        #35:#236      // MODULE$:Lscala/collection/StringOps$;
  #238 = Fieldref           #235.#237     // scala/collection/StringOps$.MODULE$:Lscala/collection/StringOps$;
  #239 = Utf8               scala/Predef$
  #240 = Class              #239          // scala/Predef$
  #241 = Utf8               Lscala/Predef$;
  #242 = NameAndType        #35:#241      // MODULE$:Lscala/Predef$;
  #243 = Fieldref           #240.#242     // scala/Predef$.MODULE$:Lscala/Predef$;
  #244 = Utf8                xmlns%s=\"%s\"
  #245 = String             #244          //  xmlns%s=\"%s\"
  #246 = Utf8               augmentString
  #247 = NameAndType        #246:#100     // augmentString:(Ljava/lang/String;)Ljava/lang/String;
  #248 = Methodref          #240.#247     // scala/Predef$.augmentString:(Ljava/lang/String;)Ljava/lang/String;
  #249 = Utf8               java/lang/StringBuilder
  #250 = Class              #249          // java/lang/StringBuilder
  #251 = Utf8               <init>
  #252 = Utf8               (I)V
  #253 = NameAndType        #251:#252     // "<init>":(I)V
  #254 = Methodref          #250.#253     // java/lang/StringBuilder."<init>":(I)V
  #255 = Utf8               :
  #256 = String             #255          // :
  #257 = Utf8               append
  #258 = Utf8               (Ljava/lang/String;)Ljava/lang/StringBuilder;
  #259 = NameAndType        #257:#258     // append:(Ljava/lang/String;)Ljava/lang/StringBuilder;
  #260 = Methodref          #250.#259     // java/lang/StringBuilder.append:(Ljava/lang/String;)Ljava/lang/StringBuilder;
  #261 = NameAndType        #118:#91      // toString:()Ljava/lang/String;
  #262 = Methodref          #250.#261     // java/lang/StringBuilder.toString:()Ljava/lang/String;
  #263 = Utf8
  #264 = String             #263          //
  #265 = Utf8               genericWrapArray
  #266 = Utf8               (Ljava/lang/Object;)Lscala/collection/immutable/ArraySeq;
  #267 = NameAndType        #265:#266     // genericWrapArray:(Ljava/lang/Object;)Lscala/collection/immutable/ArraySeq;
  #268 = Methodref          #191.#267     // scala/runtime/ScalaRunTime$.genericWrapArray:(Ljava/lang/Object;)Lscala/collection/immutable/ArraySeq;
  #269 = Utf8               format$extension
  #270 = Utf8               (Ljava/lang/String;Lscala/collection/immutable/Seq;)Ljava/lang/String;
  #271 = NameAndType        #269:#270     // format$extension:(Ljava/lang/String;Lscala/collection/immutable/Seq;)Ljava/lang/String;
  #272 = Methodref          #235.#271     // scala/collection/StringOps$.format$extension:(Ljava/lang/String;Lscala/collection/immutable/Seq;)Ljava/lang/String;
  #273 = Utf8               scala/collection/mutable/StringBuilder
  #274 = Class              #273          // scala/collection/mutable/StringBuilder
  #275 = Utf8               (Ljava/lang/String;)Lscala/collection/mutable/StringBuilder;
  #276 = NameAndType        #257:#275     // append:(Ljava/lang/String;)Lscala/collection/mutable/StringBuilder;
  #277 = Methodref          #274.#276     // scala/collection/mutable/StringBuilder.append:(Ljava/lang/String;)Lscala/collection/mutable/StringBuilder;
  #278 = Utf8               s
  #279 = Utf8               copy
  #280 = Utf8               (Ljava/lang/String;Ljava/lang/String;Lscala/xml/NamespaceBinding;)V
  #281 = NameAndType        #251:#280     // "<init>":(Ljava/lang/String;Ljava/lang/String;Lscala/xml/NamespaceBinding;)V
  #282 = Methodref          #2.#281       // scala/xml/NamespaceBinding."<init>":(Ljava/lang/String;Ljava/lang/String;Lscala/xml/NamespaceBinding;)V
  #283 = Utf8               copy$default$1
  #284 = Utf8               copy$default$2
  #285 = Utf8               copy$default$3
  #286 = Utf8               productPrefix
  #287 = Utf8               NamespaceBinding
  #288 = String             #287          // NamespaceBinding
  #289 = Utf8               productArity
  #290 = Utf8               productElement
  #291 = Utf8               (I)Ljava/lang/Object;
  #292 = Utf8               x$1
  #293 = Utf8               scala/runtime/Statics
  #294 = Class              #293          // scala/runtime/Statics
  #295 = Utf8               ioobe
  #296 = NameAndType        #295:#291     // ioobe:(I)Ljava/lang/Object;
  #297 = Methodref          #294.#296     // scala/runtime/Statics.ioobe:(I)Ljava/lang/Object;
  #298 = Utf8               I
  #299 = Utf8               productIterator
  #300 = Utf8               ()Lscala/collection/Iterator<Ljava/lang/Object;>;
  #301 = Utf8               typedProductIterator
  #302 = NameAndType        #301:#58      // typedProductIterator:(Lscala/Product;)Lscala/collection/Iterator;
  #303 = Methodref          #191.#302     // scala/runtime/ScalaRunTime$.typedProductIterator:(Lscala/Product;)Lscala/collection/Iterator;
  #304 = Utf8               productElementName
  #305 = Utf8               (I)Ljava/lang/String;
  #306 = String             #24           // prefix
  #307 = String             #26           // uri
  #308 = String             #27           // parent
  #309 = Utf8               $anonfun$toString$1
  #310 = Utf8               (Lscala/xml/NamespaceBinding;Lscala/collection/mutable/StringBuilder;)V
  #311 = Utf8               $this
  #312 = NameAndType        #206:#216     // buildString:(Lscala/collection/mutable/StringBuilder;Lscala/xml/NamespaceBinding;)V
  #313 = Methodref          #2.#312       // scala/xml/NamespaceBinding.buildString:(Lscala/collection/mutable/StringBuilder;Lscala/xml/NamespaceBinding;)V
  #314 = Utf8               x
  #315 = Utf8               stop$1
  #316 = Utf8               Nil
  #317 = Utf8               ()Lscala/collection/immutable/Nil$;
  #318 = NameAndType        #316:#317     // Nil:()Lscala/collection/immutable/Nil$;
  #319 = Methodref          #182.#318     // scala/package$.Nil:()Lscala/collection/immutable/Nil$;
  #320 = Utf8               $colon$colon
  #321 = Utf8               (Ljava/lang/Object;)Lscala/collection/immutable/List;
  #322 = NameAndType        #320:#321     // $colon$colon:(Ljava/lang/Object;)Lscala/collection/immutable/List;
  #323 = Methodref          #157.#322     // scala/collection/immutable/List.$colon$colon:(Ljava/lang/Object;)Lscala/collection/immutable/List;
  #324 = Utf8               l
  #325 = Utf8               scala/collection/immutable/$colon$colon
  #326 = Class              #325          // scala/collection/immutable/$colon$colon
  #327 = Utf8               head
  #328 = NameAndType        #327:#163     // head:()Ljava/lang/Object;
  #329 = Methodref          #326.#328     // scala/collection/immutable/$colon$colon.head:()Ljava/lang/Object;
  #330 = Utf8               next$access$1
  #331 = NameAndType        #330:#159     // next$access$1:()Lscala/collection/immutable/List;
  #332 = Methodref          #326.#331     // scala/collection/immutable/$colon$colon.next$access$1:()Lscala/collection/immutable/List;
  #333 = Utf8               scala/MatchError
  #334 = Class              #333          // scala/MatchError
  #335 = Utf8               (Ljava/lang/Object;)V
  #336 = NameAndType        #251:#335     // "<init>":(Ljava/lang/Object;)V
  #337 = Methodref          #334.#336     // scala/MatchError."<init>":(Ljava/lang/Object;)V
  #338 = Utf8               xs
  #339 = Utf8               scala/collection/immutable/Nil$
  #340 = Class              #339          // scala/collection/immutable/Nil$
  #341 = Utf8               $anonfun$buildString$1
  #342 = Utf8               (Lscala/xml/NamespaceBinding;Lscala/xml/NamespaceBinding;Lscala/collection/mutable/StringBuilder;)V
  #343 = Utf8               stop$2
  #344 = Utf8               x$2
  #345 = Utf8               ()V
  #346 = NameAndType        #251:#345     // "<init>":()V
  #347 = Methodref          #4.#346       // java/lang/Object."<init>":()V
  #348 = Utf8               $init$
  #349 = Utf8               (Lscala/xml/Equality;)V
  #350 = NameAndType        #348:#349     // $init$:(Lscala/xml/Equality;)V
  #351 = InterfaceMethodref #6.#350       // scala/xml/Equality.$init$:(Lscala/xml/Equality;)V
  #352 = Utf8               (Lscala/Product;)V
  #353 = NameAndType        #348:#352     // $init$:(Lscala/Product;)V
  #354 = InterfaceMethodref #8.#353       // scala/Product.$init$:(Lscala/Product;)V
  #355 = Utf8               java/lang/IllegalArgumentException
  #356 = Class              #355          // java/lang/IllegalArgumentException
  #357 = Utf8               zero length prefix not allowed
  #358 = String             #357          // zero length prefix not allowed
  #359 = Utf8               (Ljava/lang/String;)V
  #360 = NameAndType        #251:#359     // "<init>":(Ljava/lang/String;)V
  #361 = Methodref          #356.#360     // java/lang/IllegalArgumentException."<init>":(Ljava/lang/String;)V
  #362 = NameAndType        #309:#310     // $anonfun$toString$1:(Lscala/xml/NamespaceBinding;Lscala/collection/mutable/StringBuilder;)V
  #363 = Methodref          #2.#362       // scala/xml/NamespaceBinding.$anonfun$toString$1:(Lscala/xml/NamespaceBinding;Lscala/collection/mutable/StringBuilder;)V
  #364 = Utf8               scala/runtime/BoxedUnit
  #365 = Class              #364          // scala/runtime/BoxedUnit
  #366 = Utf8               UNIT
  #367 = Utf8               Lscala/runtime/BoxedUnit;
  #368 = NameAndType        #366:#367     // UNIT:Lscala/runtime/BoxedUnit;
  #369 = Fieldref           #365.#368     // scala/runtime/BoxedUnit.UNIT:Lscala/runtime/BoxedUnit;
  #370 = NameAndType        #341:#342     // $anonfun$buildString$1:(Lscala/xml/NamespaceBinding;Lscala/xml/NamespaceBinding;Lscala/collection/mutable/StringBuilder;)V
  #371 = Methodref          #2.#370       // scala/xml/NamespaceBinding.$anonfun$buildString$1:(Lscala/xml/NamespaceBinding;Lscala/xml/NamespaceBinding;Lscala/collection/mutable/StringBuilder;)V
  #372 = Utf8               $deserializeLambda$
  #373 = Utf8               (Ljava/lang/invoke/SerializedLambda;)Ljava/lang/Object;
  #374 = Utf8               scala/runtime/LambdaDeserialize
  #375 = Class              #374          // scala/runtime/LambdaDeserialize
  #376 = Utf8               bootstrap
  #377 = Utf8               (Ljava/lang/invoke/MethodHandles$Lookup;Ljava/lang/String;Ljava/lang/invoke/MethodType;[Ljava/lang/invoke/MethodHandle;)Ljava/lang/invoke/CallSite;
  #378 = NameAndType        #376:#377     // bootstrap:(Ljava/lang/invoke/MethodHandles$Lookup;Ljava/lang/String;Ljava/lang/invoke/MethodType;[Ljava/lang/invoke/MethodHandle;)Ljava/lang/invoke/CallSite;
  #379 = Methodref          #375.#378     // scala/runtime/LambdaDeserialize.bootstrap:(Ljava/lang/invoke/MethodHandles$Lookup;Ljava/lang/String;Ljava/lang/invoke/MethodType;[Ljava/lang/invoke/MethodHandle;)Ljava/lang/invoke/CallSite;
  #380 = MethodHandle       6:#379        // REF_invokeStatic scala/runtime/LambdaDeserialize.bootstrap:(Ljava/lang/invoke/MethodHandles$Lookup;Ljava/lang/String;Ljava/lang/invoke/MethodType;[Ljava/lang/invoke/MethodHandle;)Ljava/lang/invoke/CallSite;
  #381 = Utf8               lambdaDeserialize
  #382 = NameAndType        #381:#373     // lambdaDeserialize:(Ljava/lang/invoke/SerializedLambda;)Ljava/lang/Object;
  #383 = InvokeDynamic      #2:#382       // #2:lambdaDeserialize:(Ljava/lang/invoke/SerializedLambda;)Ljava/lang/Object;
  #384 = Utf8               ConstantValue
  #385 = Utf8               Code
  #386 = Utf8               LocalVariableTable
  #387 = Utf8               Signature
  #388 = Utf8               MethodParameters
  #389 = Utf8               LineNumberTable
  #390 = Utf8               StackMapTable
  #391 = Utf8               InnerClasses
  #392 = Utf8               SourceFile
  #393 = Utf8               RuntimeVisibleAnnotations
  #394 = Utf8               BootstrapMethods
  #395 = Utf8               ScalaInlineInfo
  #396 = Utf8               ScalaSig
{
  private static final long serialVersionUID;
    descriptor: J
    flags: (0x001a) ACC_PRIVATE, ACC_STATIC, ACC_FINAL
    ConstantValue: long -2518644165573446725l

  private final java.lang.String prefix;
    descriptor: Ljava/lang/String;
    flags: (0x0012) ACC_PRIVATE, ACC_FINAL

  private final java.lang.String uri;
    descriptor: Ljava/lang/String;
    flags: (0x0012) ACC_PRIVATE, ACC_FINAL

  private final scala.xml.NamespaceBinding parent;
    descriptor: Lscala/xml/NamespaceBinding;
    flags: (0x0012) ACC_PRIVATE, ACC_FINAL

  public static scala.Option<scala.Tuple3<java.lang.String, java.lang.String, scala.xml.NamespaceBinding>> unapply(scala.xml.NamespaceBinding);
    descriptor: (Lscala/xml/NamespaceBinding;)Lscala/Option;
    flags: (0x0009) ACC_PUBLIC, ACC_STATIC
    Code:
      stack=2, locals=1, args_size=1
         0: getstatic     #38                 // Field scala/xml/NamespaceBinding$.MODULE$:Lscala/xml/NamespaceBinding$;
         3: aload_0
         4: invokevirtual #40                 // Method scala/xml/NamespaceBinding$.unapply:(Lscala/xml/NamespaceBinding;)Lscala/Option;
         7: areturn
      LocalVariableTable:
        Start  Length  Slot  Name   Signature
            0       8     0   x$0   Lscala/xml/NamespaceBinding;
    Signature: #31                          // (Lscala/xml/NamespaceBinding;)Lscala/Option<Lscala/Tuple3<Ljava/lang/String;Ljava/lang/String;Lscala/xml/NamespaceBinding;>;>;
    MethodParameters:
      Name                           Flags
      x$0                            final

  public static scala.xml.NamespaceBinding apply(java.lang.String, java.lang.String, scala.xml.NamespaceBinding);
    descriptor: (Ljava/lang/String;Ljava/lang/String;Lscala/xml/NamespaceBinding;)Lscala/xml/NamespaceBinding;
    flags: (0x0009) ACC_PUBLIC, ACC_STATIC
    Code:
      stack=4, locals=3, args_size=3
         0: getstatic     #38                 // Field scala/xml/NamespaceBinding$.MODULE$:Lscala/xml/NamespaceBinding$;
         3: aload_0
         4: aload_1
         5: aload_2
         6: invokevirtual #44                 // Method scala/xml/NamespaceBinding$.apply:(Ljava/lang/String;Ljava/lang/String;Lscala/xml/NamespaceBinding;)Lscala/xml/NamespaceBinding;
         9: areturn
      LocalVariableTable:
        Start  Length  Slot  Name   Signature
            0      10     0 prefix   Ljava/lang/String;
            0      10     1   uri   Ljava/lang/String;
            0      10     2 parent   Lscala/xml/NamespaceBinding;
    MethodParameters:
      Name                           Flags
      prefix                         final
      uri                            final
      parent                         final

  public static scala.Function1<scala.Tuple3<java.lang.String, java.lang.String, scala.xml.NamespaceBinding>, scala.xml.NamespaceBinding> tupled();
    descriptor: ()Lscala/Function1;
    flags: (0x0009) ACC_PUBLIC, ACC_STATIC
    Code:
      stack=1, locals=0, args_size=0
         0: getstatic     #38                 // Field scala/xml/NamespaceBinding$.MODULE$:Lscala/xml/NamespaceBinding$;
         3: invokevirtual #49                 // Method scala/xml/NamespaceBinding$.tupled:()Lscala/Function1;
         6: areturn
    Signature: #47                          // ()Lscala/Function1<Lscala/Tuple3<Ljava/lang/String;Ljava/lang/String;Lscala/xml/NamespaceBinding;>;Lscala/xml/NamespaceBinding;>;

  public static scala.Function1<java.lang.String, scala.Function1<java.lang.String, scala.Function1<scala.xml.NamespaceBinding, scala.xml.NamespaceBinding>>> curried();
    descriptor: ()Lscala/Function1;
    flags: (0x0009) ACC_PUBLIC, ACC_STATIC
    Code:
      stack=1, locals=0, args_size=0
         0: getstatic     #38                 // Field scala/xml/NamespaceBinding$.MODULE$:Lscala/xml/NamespaceBinding$;
         3: invokevirtual #53                 // Method scala/xml/NamespaceBinding$.curried:()Lscala/Function1;
         6: areturn
    Signature: #51                          // ()Lscala/Function1<Ljava/lang/String;Lscala/Function1<Ljava/lang/String;Lscala/Function1<Lscala/xml/NamespaceBinding;Lscala/xml/NamespaceBinding;>;>;>;

  public scala.collection.Iterator<java.lang.String> productElementNames();
    descriptor: ()Lscala/collection/Iterator;
    flags: (0x0001) ACC_PUBLIC
    Code:
      stack=1, locals=1, args_size=1
         0: aload_0
         1: invokestatic  #60                 // InterfaceMethod scala/Product.productElementNames$:(Lscala/Product;)Lscala/collection/Iterator;
         4: areturn
      LineNumberTable:
        line 28: 0
      LocalVariableTable:
        Start  Length  Slot  Name   Signature
            0       5     0  this   Lscala/xml/NamespaceBinding;
    Signature: #56                          // ()Lscala/collection/Iterator<Ljava/lang/String;>;

  public boolean strict_$bang$eq(scala.xml.Equality);
    descriptor: (Lscala/xml/Equality;)Z
    flags: (0x0001) ACC_PUBLIC
    Code:
      stack=2, locals=2, args_size=2
         0: aload_0
         1: aload_1
         2: invokestatic  #68                 // InterfaceMethod scala/xml/Equality.strict_$bang$eq$:(Lscala/xml/Equality;Lscala/xml/Equality;)Z
         5: ireturn
      LineNumberTable:
        line 28: 0
      LocalVariableTable:
        Start  Length  Slot  Name   Signature
            0       6     0  this   Lscala/xml/NamespaceBinding;
            0       6     1 other   Lscala/xml/Equality;
    MethodParameters:
      Name                           Flags
      other                          final

  public int hashCode();
    descriptor: ()I
    flags: (0x0001) ACC_PUBLIC
    Code:
      stack=1, locals=1, args_size=1
         0: aload_0
         1: invokestatic  #75                 // InterfaceMethod scala/xml/Equality.hashCode$:(Lscala/xml/Equality;)I
         4: ireturn
      LineNumberTable:
        line 28: 0
      LocalVariableTable:
        Start  Length  Slot  Name   Signature
            0       5     0  this   Lscala/xml/NamespaceBinding;

  public boolean equals(java.lang.Object);
    descriptor: (Ljava/lang/Object;)Z
    flags: (0x0001) ACC_PUBLIC
    Code:
      stack=2, locals=2, args_size=2
         0: aload_0
         1: aload_1
         2: invokestatic  #81                 // InterfaceMethod scala/xml/Equality.equals$:(Lscala/xml/Equality;Ljava/lang/Object;)Z
         5: ireturn
      LineNumberTable:
        line 28: 0
      LocalVariableTable:
        Start  Length  Slot  Name   Signature
            0       6     0  this   Lscala/xml/NamespaceBinding;
            0       6     1 other   Ljava/lang/Object;
    MethodParameters:
      Name                           Flags
      other                          final

  public final boolean xml_$eq$eq(java.lang.Object);
    descriptor: (Ljava/lang/Object;)Z
    flags: (0x0011) ACC_PUBLIC, ACC_FINAL
    Code:
      stack=2, locals=2, args_size=2
         0: aload_0
         1: aload_1
         2: invokestatic  #86                 // InterfaceMethod scala/xml/Equality.xml_$eq$eq$:(Lscala/xml/Equality;Ljava/lang/Object;)Z
         5: ireturn
      LineNumberTable:
        line 28: 0
      LocalVariableTable:
        Start  Length  Slot  Name   Signature
            0       6     0  this   Lscala/xml/NamespaceBinding;
            0       6     1 other   Ljava/lang/Object;
    MethodParameters:
      Name                           Flags
      other                          final

  public final boolean xml_$bang$eq(java.lang.Object);
    descriptor: (Ljava/lang/Object;)Z
    flags: (0x0011) ACC_PUBLIC, ACC_FINAL
    Code:
      stack=2, locals=2, args_size=2
         0: aload_0
         1: aload_1
         2: invokestatic  #90                 // InterfaceMethod scala/xml/Equality.xml_$bang$eq$:(Lscala/xml/Equality;Ljava/lang/Object;)Z
         5: ireturn
      LineNumberTable:
        line 28: 0
      LocalVariableTable:
        Start  Length  Slot  Name   Signature
            0       6     0  this   Lscala/xml/NamespaceBinding;
            0       6     1 other   Ljava/lang/Object;
    MethodParameters:
      Name                           Flags
      other                          final

  public java.lang.String prefix();
    descriptor: ()Ljava/lang/String;
    flags: (0x0001) ACC_PUBLIC
    Code:
      stack=1, locals=1, args_size=1
         0: aload_0
         1: getfield      #93                 // Field prefix:Ljava/lang/String;
         4: areturn
      LineNumberTable:
        line 28: 0
      LocalVariableTable:
        Start  Length  Slot  Name   Signature
            0       5     0  this   Lscala/xml/NamespaceBinding;

  public java.lang.String uri();
    descriptor: ()Ljava/lang/String;
    flags: (0x0001) ACC_PUBLIC
    Code:
      stack=1, locals=1, args_size=1
         0: aload_0
         1: getfield      #95                 // Field uri:Ljava/lang/String;
         4: areturn
      LineNumberTable:
        line 28: 0
      LocalVariableTable:
        Start  Length  Slot  Name   Signature
            0       5     0  this   Lscala/xml/NamespaceBinding;

  public scala.xml.NamespaceBinding parent();
    descriptor: ()Lscala/xml/NamespaceBinding;
    flags: (0x0001) ACC_PUBLIC
    Code:
      stack=1, locals=1, args_size=1
         0: aload_0
         1: getfield      #98                 // Field parent:Lscala/xml/NamespaceBinding;
         4: areturn
      LineNumberTable:
        line 28: 0
      LocalVariableTable:
        Start  Length  Slot  Name   Signature
            0       5     0  this   Lscala/xml/NamespaceBinding;

  public java.lang.String getURI(java.lang.String);
    descriptor: (Ljava/lang/String;)Ljava/lang/String;
    flags: (0x0001) ACC_PUBLIC
    Code:
      stack=2, locals=3, args_size=2
         0: aload_0
         1: invokevirtual #103                // Method prefix:()Ljava/lang/String;
         4: aload_1
         5: astore_2
         6: dup
         7: ifnonnull     18
        10: pop
        11: aload_2
        12: ifnull        25
        15: goto          32
        18: aload_2
        19: invokevirtual #105                // Method java/lang/Object.equals:(Ljava/lang/Object;)Z
        22: ifeq          32
        25: aload_0
        26: invokevirtual #107                // Method uri:()Ljava/lang/String;
        29: goto          40
        32: aload_0
        33: invokevirtual #109                // Method parent:()Lscala/xml/NamespaceBinding;
        36: aload_1
        37: invokevirtual #111                // Method getURI:(Ljava/lang/String;)Ljava/lang/String;
        40: areturn
      StackMapTable: number_of_entries = 4
        frame_type = 255 /* full_frame */
          offset_delta = 18
          locals = [ class scala/xml/NamespaceBinding, class java/lang/String, class java/lang/String ]
          stack = [ class java/lang/String ]
        frame_type = 6 /* same */
        frame_type = 6 /* same */
        frame_type = 71 /* same_locals_1_stack_item */
          stack = [ class java/lang/String ]
      LineNumberTable:
        line 33: 0
      LocalVariableTable:
        Start  Length  Slot  Name   Signature
            0      41     0  this   Lscala/xml/NamespaceBinding;
            0      41     1 _prefix   Ljava/lang/String;
    MethodParameters:
      Name                           Flags
      _prefix                        final

  public java.lang.String getPrefix(java.lang.String);
    descriptor: (Ljava/lang/String;)Ljava/lang/String;
    flags: (0x0001) ACC_PUBLIC
    Code:
      stack=2, locals=3, args_size=2
         0: aload_1
         1: aload_0
         2: invokevirtual #107                // Method uri:()Ljava/lang/String;
         5: astore_2
         6: dup
         7: ifnonnull     18
        10: pop
        11: aload_2
        12: ifnull        25
        15: goto          32
        18: aload_2
        19: invokevirtual #105                // Method java/lang/Object.equals:(Ljava/lang/Object;)Z
        22: ifeq          32
        25: aload_0
        26: invokevirtual #103                // Method prefix:()Ljava/lang/String;
        29: goto          40
        32: aload_0
        33: invokevirtual #109                // Method parent:()Lscala/xml/NamespaceBinding;
        36: aload_1
        37: invokevirtual #117                // Method getPrefix:(Ljava/lang/String;)Ljava/lang/String;
        40: areturn
      StackMapTable: number_of_entries = 4
        frame_type = 255 /* full_frame */
          offset_delta = 18
          locals = [ class scala/xml/NamespaceBinding, class java/lang/String, class java/lang/String ]
          stack = [ class java/lang/String ]
        frame_type = 6 /* same */
        frame_type = 6 /* same */
        frame_type = 71 /* same_locals_1_stack_item */
          stack = [ class java/lang/String ]
      LineNumberTable:
        line 43: 0
      LocalVariableTable:
        Start  Length  Slot  Name   Signature
            0      41     0  this   Lscala/xml/NamespaceBinding;
            0      41     1  _uri   Ljava/lang/String;
    MethodParameters:
      Name                           Flags
      _uri                           final

  public java.lang.String toString();
    descriptor: ()Ljava/lang/String;
    flags: (0x0001) ACC_PUBLIC
    Code:
      stack=2, locals=1, args_size=1
         0: getstatic     #123                // Field scala/xml/Utility$.MODULE$:Lscala/xml/Utility$;
         3: aload_0
         4: invokedynamic #144,  0            // InvokeDynamic #0:apply:(Lscala/xml/NamespaceBinding;)Lscala/Function1;
         9: invokevirtual #148                // Method scala/xml/Utility$.sbToString:(Lscala/Function1;)Ljava/lang/String;
        12: areturn
      LineNumberTable:
        line 45: 0
      LocalVariableTable:
        Start  Length  Slot  Name   Signature
            0      13     0  this   Lscala/xml/NamespaceBinding;

  private scala.xml.NamespaceBinding shadowRedefined(scala.xml.NamespaceBinding);
    descriptor: (Lscala/xml/NamespaceBinding;)Lscala/xml/NamespaceBinding;
    flags: (0x0002) ACC_PRIVATE
    Code:
      stack=3, locals=4, args_size=2
         0: aload_0
         1: aload_1
         2: invokestatic  #155                // Method prefixList$1:(Lscala/xml/NamespaceBinding;Lscala/xml/NamespaceBinding;)Lscala/collection/immutable/List;
         5: invokevirtual #161                // Method scala/collection/immutable/List.reverse:()Lscala/collection/immutable/List;
         8: astore_2
         9: aload_2
        10: invokevirtual #165                // Method scala/collection/immutable/List.distinct:()Ljava/lang/Object;
        13: checkcast     #157                // class scala/collection/immutable/List
        16: astore_3
        17: aload_3
        18: invokevirtual #168                // Method scala/collection/immutable/List.size:()I
        21: aload_2
        22: invokevirtual #168                // Method scala/collection/immutable/List.size:()I
        25: if_icmpne     32
        28: aload_0
        29: goto          38
        32: aload_0
        33: aload_3
        34: aload_1
        35: invokespecial #172                // Method fromPrefixList$1:(Lscala/collection/immutable/List;Lscala/xml/NamespaceBinding;)Lscala/xml/NamespaceBinding;
        38: areturn
      StackMapTable: number_of_entries = 2
        frame_type = 253 /* append */
          offset_delta = 32
          locals = [ class scala/collection/immutable/List, class scala/collection/immutable/List ]
        frame_type = 69 /* same_locals_1_stack_item */
          stack = [ class scala/xml/NamespaceBinding ]
      LineNumberTable:
        line 55: 0
        line 56: 9
        line 57: 17
        line 58: 32
      LocalVariableTable:
        Start  Length  Slot  Name   Signature
            9      29     2   ps0   Lscala/collection/immutable/List;
           17      21     3    ps   Lscala/collection/immutable/List;
            0      39     0  this   Lscala/xml/NamespaceBinding;
            0      39     1  stop   Lscala/xml/NamespaceBinding;
    MethodParameters:
      Name                           Flags
      stop                           final

  public boolean canEqual(java.lang.Object);
    descriptor: (Ljava/lang/Object;)Z
    flags: (0x0001) ACC_PUBLIC
    Code:
      stack=1, locals=4, args_size=2
         0: aload_1
         1: astore_3
         2: aload_3
         3: instanceof    #2                  // class scala/xml/NamespaceBinding
         6: ifeq          14
         9: iconst_1
        10: istore_2
        11: goto          22
        14: goto          17
        17: iconst_0
        18: istore_2
        19: goto          22
        22: iload_2
        23: ireturn
      StackMapTable: number_of_entries = 3
        frame_type = 253 /* append */
          offset_delta = 14
          locals = [ top, class java/lang/Object ]
        frame_type = 2 /* same */
        frame_type = 255 /* full_frame */
          offset_delta = 4
          locals = [ class scala/xml/NamespaceBinding, class java/lang/Object, int, class java/lang/Object ]
          stack = []
      LineNumberTable:
        line 61: 0
        line 62: 2
        line 63: 17
        line 61: 22
      LocalVariableTable:
        Start  Length  Slot  Name   Signature
            0      24     0  this   Lscala/xml/NamespaceBinding;
            0      24     1 other   Ljava/lang/Object;
    MethodParameters:
      Name                           Flags
      other                          final

  public boolean strict_$eq$eq(scala.xml.Equality);
    descriptor: (Lscala/xml/Equality;)Z
    flags: (0x0001) ACC_PUBLIC
    Code:
      stack=2, locals=8, args_size=2
         0: aload_1
         1: astore_3
         2: aload_3
         3: instanceof    #2                  // class scala/xml/NamespaceBinding
         6: ifeq          120
         9: aload_3
        10: checkcast     #2                  // class scala/xml/NamespaceBinding
        13: astore        4
        15: aload_0
        16: invokevirtual #103                // Method prefix:()Ljava/lang/String;
        19: aload         4
        21: invokevirtual #103                // Method prefix:()Ljava/lang/String;
        24: astore        5
        26: dup
        27: ifnonnull     39
        30: pop
        31: aload         5
        33: ifnull        47
        36: goto          115
        39: aload         5
        41: invokevirtual #105                // Method java/lang/Object.equals:(Ljava/lang/Object;)Z
        44: ifeq          115
        47: aload_0
        48: invokevirtual #107                // Method uri:()Ljava/lang/String;
        51: aload         4
        53: invokevirtual #107                // Method uri:()Ljava/lang/String;
        56: astore        6
        58: dup
        59: ifnonnull     71
        62: pop
        63: aload         6
        65: ifnull        79
        68: goto          115
        71: aload         6
        73: invokevirtual #105                // Method java/lang/Object.equals:(Ljava/lang/Object;)Z
        76: ifeq          115
        79: aload_0
        80: invokevirtual #109                // Method parent:()Lscala/xml/NamespaceBinding;
        83: aload         4
        85: invokevirtual #109                // Method parent:()Lscala/xml/NamespaceBinding;
        88: astore        7
        90: dup
        91: ifnonnull     103
        94: pop
        95: aload         7
        97: ifnull        111
       100: goto          115
       103: aload         7
       105: invokevirtual #105                // Method java/lang/Object.equals:(Ljava/lang/Object;)Z
       108: ifeq          115
       111: iconst_1
       112: goto          116
       115: iconst_0
       116: istore_2
       117: goto          128
       120: goto          123
       123: iconst_0
       124: istore_2
       125: goto          128
       128: iload_2
       129: ireturn
      StackMapTable: number_of_entries = 11
        frame_type = 255 /* full_frame */
          offset_delta = 39
          locals = [ class scala/xml/NamespaceBinding, class scala/xml/Equality, top, class scala/xml/Equality, class scala/xml/NamespaceBinding, class java/lang/String ]
          stack = [ class java/lang/String ]
        frame_type = 7 /* same */
        frame_type = 255 /* full_frame */
          offset_delta = 23
          locals = [ class scala/xml/NamespaceBinding, class scala/xml/Equality, top, class scala/xml/Equality, class scala/xml/NamespaceBinding, class java/lang/String, class java/lang/String ]
          stack = [ class java/lang/String ]
        frame_type = 7 /* same */
        frame_type = 255 /* full_frame */
          offset_delta = 23
          locals = [ class scala/xml/NamespaceBinding, class scala/xml/Equality, top, class scala/xml/Equality, class scala/xml/NamespaceBinding, class java/lang/String, class java/lang/String, class scala/xml/NamespaceBinding ]
          stack = [ class scala/xml/NamespaceBinding ]
        frame_type = 7 /* same */
        frame_type = 249 /* chop */
          offset_delta = 3
        frame_type = 64 /* same_locals_1_stack_item */
          stack = [ int ]
        frame_type = 249 /* chop */
          offset_delta = 3
        frame_type = 2 /* same */
        frame_type = 255 /* full_frame */
          offset_delta = 4
          locals = [ class scala/xml/NamespaceBinding, class scala/xml/Equality, int, class scala/xml/Equality ]
          stack = []
      LineNumberTable:
        line 66: 0
        line 67: 2
        line 68: 123
        line 66: 128
      LocalVariableTable:
        Start  Length  Slot  Name   Signature
            0     130     0  this   Lscala/xml/NamespaceBinding;
            0     130     1 other   Lscala/xml/Equality;
    MethodParameters:
      Name                           Flags
      other                          final

  public scala.collection.Seq<java.lang.Object> basisForHashCode();
    descriptor: ()Lscala/collection/Seq;
    flags: (0x0001) ACC_PUBLIC
    Code:
      stack=6, locals=1, args_size=1
         0: getstatic     #185                // Field scala/package$.MODULE$:Lscala/package$;
         3: invokevirtual #189                // Method scala/package$.List:()Lscala/collection/immutable/List$;
         6: getstatic     #194                // Field scala/runtime/ScalaRunTime$.MODULE$:Lscala/runtime/ScalaRunTime$;
         9: iconst_3
        10: anewarray     #4                  // class java/lang/Object
        13: dup
        14: iconst_0
        15: aload_0
        16: invokevirtual #103                // Method prefix:()Ljava/lang/String;
        19: aastore
        20: dup
        21: iconst_1
        22: aload_0
        23: invokevirtual #107                // Method uri:()Ljava/lang/String;
        26: aastore
        27: dup
        28: iconst_2
        29: aload_0
        30: invokevirtual #109                // Method parent:()Lscala/xml/NamespaceBinding;
        33: aastore
        34: invokevirtual #198                // Method scala/runtime/ScalaRunTime$.wrapRefArray:([Ljava/lang/Object;)Lscala/collection/immutable/ArraySeq;
        37: invokevirtual #203                // Method scala/collection/immutable/List$.apply:(Lscala/collection/immutable/Seq;)Ljava/lang/Object;
        40: checkcast     #205                // class scala/collection/Seq
        43: areturn
      LineNumberTable:
        line 71: 0
      LocalVariableTable:
        Start  Length  Slot  Name   Signature
            0      44     0  this   Lscala/xml/NamespaceBinding;
    Signature: #180                         // ()Lscala/collection/Seq<Ljava/lang/Object;>;

  public java.lang.String buildString(scala.xml.NamespaceBinding);
    descriptor: (Lscala/xml/NamespaceBinding;)Ljava/lang/String;
    flags: (0x0001) ACC_PUBLIC
    Code:
      stack=3, locals=2, args_size=2
         0: getstatic     #123                // Field scala/xml/Utility$.MODULE$:Lscala/xml/Utility$;
         3: aload_0
         4: aload_1
         5: invokedynamic #215,  0            // InvokeDynamic #1:apply:(Lscala/xml/NamespaceBinding;Lscala/xml/NamespaceBinding;)Lscala/Function1;
        10: invokevirtual #148                // Method scala/xml/Utility$.sbToString:(Lscala/Function1;)Ljava/lang/String;
        13: areturn
      LineNumberTable:
        line 73: 0
      LocalVariableTable:
        Start  Length  Slot  Name   Signature
            0      14     0  this   Lscala/xml/NamespaceBinding;
            0      14     1  stop   Lscala/xml/NamespaceBinding;
    MethodParameters:
      Name                           Flags
      stop                           final

  public void buildString(scala.collection.mutable.StringBuilder, scala.xml.NamespaceBinding);
    descriptor: (Lscala/collection/mutable/StringBuilder;Lscala/xml/NamespaceBinding;)V
    flags: (0x0001) ACC_PUBLIC
    Code:
      stack=3, locals=3, args_size=3
         0: aload_0
         1: aload_2
         2: invokespecial #219                // Method shadowRedefined:(Lscala/xml/NamespaceBinding;)Lscala/xml/NamespaceBinding;
         5: aload_1
         6: aload_2
         7: invokespecial #222                // Method doBuildString:(Lscala/collection/mutable/StringBuilder;Lscala/xml/NamespaceBinding;)V
        10: return
      LineNumberTable:
        line 76: 0
      LocalVariableTable:
        Start  Length  Slot  Name   Signature
            0      11     0  this   Lscala/xml/NamespaceBinding;
            0      11     1    sb   Lscala/collection/mutable/StringBuilder;
            0      11     2  stop   Lscala/xml/NamespaceBinding;
    MethodParameters:
      Name                           Flags
      sb                             final
      stop                           final

  private void doBuildString(scala.collection.mutable.StringBuilder, scala.xml.NamespaceBinding);
    descriptor: (Lscala/collection/mutable/StringBuilder;Lscala/xml/NamespaceBinding;)V
    flags: (0x0002) ACC_PRIVATE
    Code:
      stack=9, locals=5, args_size=3
         0: getstatic     #185                // Field scala/package$.MODULE$:Lscala/package$;
         3: invokevirtual #189                // Method scala/package$.List:()Lscala/collection/immutable/List$;
         6: getstatic     #194                // Field scala/runtime/ScalaRunTime$.MODULE$:Lscala/runtime/ScalaRunTime$;
         9: iconst_3
        10: anewarray     #2                  // class scala/xml/NamespaceBinding
        13: dup
        14: iconst_0
        15: aconst_null
        16: aastore
        17: dup
        18: iconst_1
        19: aload_2
        20: aastore
        21: dup
        22: iconst_2
        23: getstatic     #228                // Field scala/xml/TopScope$.MODULE$:Lscala/xml/TopScope$;
        26: aastore
        27: checkcast     #230                // class "[Ljava/lang/Object;"
        30: invokevirtual #198                // Method scala/runtime/ScalaRunTime$.wrapRefArray:([Ljava/lang/Object;)Lscala/collection/immutable/ArraySeq;
        33: invokevirtual #203                // Method scala/collection/immutable/List$.apply:(Lscala/collection/immutable/Seq;)Ljava/lang/Object;
        36: checkcast     #157                // class scala/collection/immutable/List
        39: aload_0
        40: invokevirtual #233                // Method scala/collection/immutable/List.contains:(Ljava/lang/Object;)Z
        43: ifeq          47
        46: return
        47: getstatic     #238                // Field scala/collection/StringOps$.MODULE$:Lscala/collection/StringOps$;
        50: getstatic     #243                // Field scala/Predef$.MODULE$:Lscala/Predef$;
        53: ldc           #245                // String  xmlns%s=\"%s\"
        55: invokevirtual #248                // Method scala/Predef$.augmentString:(Ljava/lang/String;)Ljava/lang/String;
        58: getstatic     #194                // Field scala/runtime/ScalaRunTime$.MODULE$:Lscala/runtime/ScalaRunTime$;
        61: iconst_2
        62: anewarray     #4                  // class java/lang/Object
        65: dup
        66: iconst_0
        67: aload_0
        68: invokevirtual #103                // Method prefix:()Ljava/lang/String;
        71: ifnull        102
        74: new           #250                // class java/lang/StringBuilder
        77: dup
        78: ldc           #134                // int 1
        80: invokespecial #254                // Method java/lang/StringBuilder."<init>":(I)V
        83: ldc_w         #256                // String :
        86: invokevirtual #260                // Method java/lang/StringBuilder.append:(Ljava/lang/String;)Ljava/lang/StringBuilder;
        89: aload_0
        90: invokevirtual #103                // Method prefix:()Ljava/lang/String;
        93: invokevirtual #260                // Method java/lang/StringBuilder.append:(Ljava/lang/String;)Ljava/lang/StringBuilder;
        96: invokevirtual #262                // Method java/lang/StringBuilder.toString:()Ljava/lang/String;
        99: goto          105
       102: ldc_w         #264                // String
       105: aastore
       106: dup
       107: iconst_1
       108: aload_0
       109: invokevirtual #107                // Method uri:()Ljava/lang/String;
       112: ifnull        122
       115: aload_0
       116: invokevirtual #107                // Method uri:()Ljava/lang/String;
       119: goto          125
       122: ldc_w         #264                // String
       125: aastore
       126: invokevirtual #268                // Method scala/runtime/ScalaRunTime$.genericWrapArray:(Ljava/lang/Object;)Lscala/collection/immutable/ArraySeq;
       129: invokevirtual #272                // Method scala/collection/StringOps$.format$extension:(Ljava/lang/String;Lscala/collection/immutable/Seq;)Ljava/lang/String;
       132: astore        4
       134: aload_0
       135: invokevirtual #109                // Method parent:()Lscala/xml/NamespaceBinding;
       138: aload_1
       139: aload         4
       141: invokevirtual #277                // Method scala/collection/mutable/StringBuilder.append:(Ljava/lang/String;)Lscala/collection/mutable/StringBuilder;
       144: aload_2
       145: astore_2
       146: astore_1
       147: astore_0
       148: goto          0
      StackMapTable: number_of_entries = 6
        frame_type = 0 /* same */
        frame_type = 46 /* same */
        frame_type = 255 /* full_frame */
          offset_delta = 54
          locals = [ class scala/xml/NamespaceBinding, class scala/collection/mutable/StringBuilder, class scala/xml/NamespaceBinding ]
          stack = [ class scala/collection/StringOps$, class java/lang/String, class scala/runtime/ScalaRunTime$, class "[Ljava/lang/Object;", class "[Ljava/lang/Object;", int ]
        frame_type = 255 /* full_frame */
          offset_delta = 2
          locals = [ class scala/xml/NamespaceBinding, class scala/collection/mutable/StringBuilder, class scala/xml/NamespaceBinding ]
          stack = [ class scala/collection/StringOps$, class java/lang/String, class scala/runtime/ScalaRunTime$, class "[Ljava/lang/Object;", class "[Ljava/lang/Object;", int, class java/lang/String ]
        frame_type = 255 /* full_frame */
          offset_delta = 16
          locals = [ class scala/xml/NamespaceBinding, class scala/collection/mutable/StringBuilder, class scala/xml/NamespaceBinding ]
          stack = [ class scala/collection/StringOps$, class java/lang/String, class scala/runtime/ScalaRunTime$, class "[Ljava/lang/Object;", class "[Ljava/lang/Object;", int ]
        frame_type = 255 /* full_frame */
          offset_delta = 2
          locals = [ class scala/xml/NamespaceBinding, class scala/collection/mutable/StringBuilder, class scala/xml/NamespaceBinding ]
          stack = [ class scala/collection/StringOps$, class java/lang/String, class scala/runtime/ScalaRunTime$, class "[Ljava/lang/Object;", class "[Ljava/lang/Object;", int, class java/lang/String ]
      LineNumberTable:
        line 80: 0
        line 82: 47
        line 83: 67
        line 84: 108
        line 86: 134
      LocalVariableTable:
        Start  Length  Slot  Name   Signature
          134      17     4     s   Ljava/lang/String;
            0     151     0  this   Lscala/xml/NamespaceBinding;
            0     151     1    sb   Lscala/collection/mutable/StringBuilder;
            0     151     2  stop   Lscala/xml/NamespaceBinding;
    MethodParameters:
      Name                           Flags
      sb                             final
      stop                           final

  public scala.xml.NamespaceBinding copy(java.lang.String, java.lang.String, scala.xml.NamespaceBinding);
    descriptor: (Ljava/lang/String;Ljava/lang/String;Lscala/xml/NamespaceBinding;)Lscala/xml/NamespaceBinding;
    flags: (0x0001) ACC_PUBLIC
    Code:
      stack=5, locals=4, args_size=4
         0: new           #2                  // class scala/xml/NamespaceBinding
         3: dup
         4: aload_1
         5: aload_2
         6: aload_3
         7: invokespecial #282                // Method "<init>":(Ljava/lang/String;Ljava/lang/String;Lscala/xml/NamespaceBinding;)V
        10: areturn
      LineNumberTable:
        line 28: 0
      LocalVariableTable:
        Start  Length  Slot  Name   Signature
            0      11     0  this   Lscala/xml/NamespaceBinding;
            0      11     1 prefix   Ljava/lang/String;
            0      11     2   uri   Ljava/lang/String;
            0      11     3 parent   Lscala/xml/NamespaceBinding;
    MethodParameters:
      Name                           Flags
      prefix                         final
      uri                            final
      parent                         final

  public java.lang.String copy$default$1();
    descriptor: ()Ljava/lang/String;
    flags: (0x0001) ACC_PUBLIC
    Code:
      stack=1, locals=1, args_size=1
         0: aload_0
         1: invokevirtual #103                // Method prefix:()Ljava/lang/String;
         4: areturn
      LineNumberTable:
        line 28: 0
      LocalVariableTable:
        Start  Length  Slot  Name   Signature
            0       5     0  this   Lscala/xml/NamespaceBinding;

  public java.lang.String copy$default$2();
    descriptor: ()Ljava/lang/String;
    flags: (0x0001) ACC_PUBLIC
    Code:
      stack=1, locals=1, args_size=1
         0: aload_0
         1: invokevirtual #107                // Method uri:()Ljava/lang/String;
         4: areturn
      LineNumberTable:
        line 28: 0
      LocalVariableTable:
        Start  Length  Slot  Name   Signature
            0       5     0  this   Lscala/xml/NamespaceBinding;

  public scala.xml.NamespaceBinding copy$default$3();
    descriptor: ()Lscala/xml/NamespaceBinding;
    flags: (0x0001) ACC_PUBLIC
    Code:
      stack=1, locals=1, args_size=1
         0: aload_0
         1: invokevirtual #109                // Method parent:()Lscala/xml/NamespaceBinding;
         4: areturn
      LineNumberTable:
        line 28: 0
      LocalVariableTable:
        Start  Length  Slot  Name   Signature
            0       5     0  this   Lscala/xml/NamespaceBinding;

  public java.lang.String productPrefix();
    descriptor: ()Ljava/lang/String;
    flags: (0x0001) ACC_PUBLIC
    Code:
      stack=1, locals=1, args_size=1
         0: ldc_w         #288                // String NamespaceBinding
         3: areturn
      LineNumberTable:
        line 28: 0
      LocalVariableTable:
        Start  Length  Slot  Name   Signature
            0       4     0  this   Lscala/xml/NamespaceBinding;

  public int productArity();
    descriptor: ()I
    flags: (0x0001) ACC_PUBLIC
    Code:
      stack=1, locals=1, args_size=1
         0: iconst_3
         1: ireturn
      LineNumberTable:
        line 28: 0
      LocalVariableTable:
        Start  Length  Slot  Name   Signature
            0       2     0  this   Lscala/xml/NamespaceBinding;

  public java.lang.Object productElement(int);
    descriptor: (I)Ljava/lang/Object;
    flags: (0x0001) ACC_PUBLIC
    Code:
      stack=1, locals=3, args_size=2
         0: iload_1
         1: istore_2
         2: iload_2
         3: tableswitch   { // 0 to 2
                       0: 28
                       1: 35
                       2: 42
                 default: 49
            }
        28: aload_0
        29: invokevirtual #103                // Method prefix:()Ljava/lang/String;
        32: goto          56
        35: aload_0
        36: invokevirtual #107                // Method uri:()Ljava/lang/String;
        39: goto          56
        42: aload_0
        43: invokevirtual #109                // Method parent:()Lscala/xml/NamespaceBinding;
        46: goto          56
        49: iload_1
        50: invokestatic  #297                // Method scala/runtime/Statics.ioobe:(I)Ljava/lang/Object;
        53: goto          56
        56: areturn
      StackMapTable: number_of_entries = 5
        frame_type = 252 /* append */
          offset_delta = 28
          locals = [ int ]
        frame_type = 6 /* same */
        frame_type = 6 /* same */
        frame_type = 6 /* same */
        frame_type = 70 /* same_locals_1_stack_item */
          stack = [ class java/lang/Object ]
      LineNumberTable:
        line 28: 0
      LocalVariableTable:
        Start  Length  Slot  Name   Signature
            0      57     0  this   Lscala/xml/NamespaceBinding;
            0      57     1   x$1   I
    MethodParameters:
      Name                           Flags
      x$1                            final

  public scala.collection.Iterator<java.lang.Object> productIterator();
    descriptor: ()Lscala/collection/Iterator;
    flags: (0x0001) ACC_PUBLIC
    Code:
      stack=2, locals=1, args_size=1
         0: getstatic     #194                // Field scala/runtime/ScalaRunTime$.MODULE$:Lscala/runtime/ScalaRunTime$;
         3: aload_0
         4: invokevirtual #303                // Method scala/runtime/ScalaRunTime$.typedProductIterator:(Lscala/Product;)Lscala/collection/Iterator;
         7: areturn
      LineNumberTable:
        line 28: 0
      LocalVariableTable:
        Start  Length  Slot  Name   Signature
            0       8     0  this   Lscala/xml/NamespaceBinding;
    Signature: #300                         // ()Lscala/collection/Iterator<Ljava/lang/Object;>;

  public java.lang.String productElementName(int);
    descriptor: (I)Ljava/lang/String;
    flags: (0x0001) ACC_PUBLIC
    Code:
      stack=1, locals=3, args_size=2
         0: iload_1
         1: istore_2
         2: iload_2
         3: tableswitch   { // 0 to 2
                       0: 28
                       1: 34
                       2: 40
                 default: 46
            }
        28: ldc_w         #306                // String prefix
        31: goto          56
        34: ldc_w         #307                // String uri
        37: goto          56
        40: ldc_w         #308                // String parent
        43: goto          56
        46: iload_1
        47: invokestatic  #297                // Method scala/runtime/Statics.ioobe:(I)Ljava/lang/Object;
        50: checkcast     #113                // class java/lang/String
        53: goto          56
        56: areturn
      StackMapTable: number_of_entries = 5
        frame_type = 252 /* append */
          offset_delta = 28
          locals = [ int ]
        frame_type = 5 /* same */
        frame_type = 5 /* same */
        frame_type = 5 /* same */
        frame_type = 73 /* same_locals_1_stack_item */
          stack = [ class java/lang/String ]
      LineNumberTable:
        line 28: 0
      LocalVariableTable:
        Start  Length  Slot  Name   Signature
            0      57     0  this   Lscala/xml/NamespaceBinding;
            0      57     1   x$1   I
    MethodParameters:
      Name                           Flags
      x$1                            final

  public static final void $anonfun$toString$1(scala.xml.NamespaceBinding, scala.collection.mutable.StringBuilder);
    descriptor: (Lscala/xml/NamespaceBinding;Lscala/collection/mutable/StringBuilder;)V
    flags: (0x1019) ACC_PUBLIC, ACC_STATIC, ACC_FINAL, ACC_SYNTHETIC
    Code:
      stack=3, locals=2, args_size=2
         0: aload_0
         1: aload_1
         2: getstatic     #228                // Field scala/xml/TopScope$.MODULE$:Lscala/xml/TopScope$;
         5: invokevirtual #313                // Method buildString:(Lscala/collection/mutable/StringBuilder;Lscala/xml/NamespaceBinding;)V
         8: return
      LineNumberTable:
        line 45: 0
      LocalVariableTable:
        Start  Length  Slot  Name   Signature
            0       9     0 $this   Lscala/xml/NamespaceBinding;
            0       9     1   x$1   Lscala/collection/mutable/StringBuilder;
    MethodParameters:
      Name                           Flags
      $this                          final synthetic
      x$1                            final

  private static final scala.collection.immutable.List prefixList$1(scala.xml.NamespaceBinding, scala.xml.NamespaceBinding);
    descriptor: (Lscala/xml/NamespaceBinding;Lscala/xml/NamespaceBinding;)Lscala/collection/immutable/List;
    flags: (0x001a) ACC_PRIVATE, ACC_STATIC, ACC_FINAL
    Code:
      stack=2, locals=3, args_size=2
         0: aload_0
         1: ifnull        9
         4: aload_0
         5: aload_1
         6: if_acmpne     18
         9: getstatic     #185                // Field scala/package$.MODULE$:Lscala/package$;
        12: invokevirtual #319                // Method scala/package$.Nil:()Lscala/collection/immutable/Nil$;
        15: goto          35
        18: aload_0
        19: invokevirtual #103                // Method prefix:()Ljava/lang/String;
        22: astore_2
        23: aload_0
        24: invokevirtual #109                // Method parent:()Lscala/xml/NamespaceBinding;
        27: aload_1
        28: invokestatic  #155                // Method prefixList$1:(Lscala/xml/NamespaceBinding;Lscala/xml/NamespaceBinding;)Lscala/collection/immutable/List;
        31: aload_2
        32: invokevirtual #323                // Method scala/collection/immutable/List.$colon$colon:(Ljava/lang/Object;)Lscala/collection/immutable/List;
        35: areturn
      StackMapTable: number_of_entries = 3
        frame_type = 9 /* same */
        frame_type = 8 /* same */
        frame_type = 80 /* same_locals_1_stack_item */
          stack = [ class scala/collection/immutable/List ]
      LineNumberTable:
        line 49: 0
        line 50: 18
      LocalVariableTable:
        Start  Length  Slot  Name   Signature
            0      36     0     x   Lscala/xml/NamespaceBinding;
            0      36     1 stop$1   Lscala/xml/NamespaceBinding;
    MethodParameters:
      Name                           Flags
      x                              final
      stop$1                         final

  private final scala.xml.NamespaceBinding fromPrefixList$1(scala.collection.immutable.List, scala.xml.NamespaceBinding);
    descriptor: (Lscala/collection/immutable/List;Lscala/xml/NamespaceBinding;)Lscala/xml/NamespaceBinding;
    flags: (0x0012) ACC_PRIVATE, ACC_FINAL
    Code:
      stack=7, locals=9, args_size=3
         0: aload_1
         1: astore        4
         3: getstatic     #185                // Field scala/package$.MODULE$:Lscala/package$;
         6: invokevirtual #319                // Method scala/package$.Nil:()Lscala/collection/immutable/Nil$;
         9: aload         4
        11: astore        5
        13: dup
        14: ifnonnull     26
        17: pop
        18: aload         5
        20: ifnull        34
        23: goto          39
        26: aload         5
        28: invokevirtual #105                // Method java/lang/Object.equals:(Ljava/lang/Object;)Z
        31: ifeq          39
        34: aload_2
        35: astore_3
        36: goto          113
        39: goto          42
        42: aload         4
        44: instanceof    #326                // class scala/collection/immutable/$colon$colon
        47: ifeq          100
        50: aload         4
        52: checkcast     #326                // class scala/collection/immutable/$colon$colon
        55: astore        6
        57: aload         6
        59: invokevirtual #329                // Method scala/collection/immutable/$colon$colon.head:()Ljava/lang/Object;
        62: checkcast     #113                // class java/lang/String
        65: astore        7
        67: aload         6
        69: invokevirtual #332                // Method scala/collection/immutable/$colon$colon.next$access$1:()Lscala/collection/immutable/List;
        72: astore        8
        74: new           #2                  // class scala/xml/NamespaceBinding
        77: dup
        78: aload         7
        80: aload_0
        81: aload         7
        83: invokevirtual #111                // Method getURI:(Ljava/lang/String;)Ljava/lang/String;
        86: aload_0
        87: aload         8
        89: aload_2
        90: invokespecial #172                // Method fromPrefixList$1:(Lscala/collection/immutable/List;Lscala/xml/NamespaceBinding;)Lscala/xml/NamespaceBinding;
        93: invokespecial #282                // Method "<init>":(Ljava/lang/String;Ljava/lang/String;Lscala/xml/NamespaceBinding;)V
        96: astore_3
        97: goto          113
       100: goto          103
       103: new           #334                // class scala/MatchError
       106: dup
       107: aload         4
       109: invokespecial #337                // Method scala/MatchError."<init>":(Ljava/lang/Object;)V
       112: athrow
       113: aload_3
       114: areturn
      StackMapTable: number_of_entries = 7
        frame_type = 255 /* full_frame */
          offset_delta = 26
          locals = [ class scala/xml/NamespaceBinding, class scala/collection/immutable/List, class scala/xml/NamespaceBinding, top, class scala/collection/immutable/List, class scala/collection/immutable/List ]
          stack = [ class scala/collection/immutable/Nil$ ]
        frame_type = 7 /* same */
        frame_type = 4 /* same */
        frame_type = 2 /* same */
        frame_type = 57 /* same */
        frame_type = 2 /* same */
        frame_type = 255 /* full_frame */
          offset_delta = 9
          locals = [ class scala/xml/NamespaceBinding, class scala/collection/immutable/List, class scala/xml/NamespaceBinding, class scala/xml/NamespaceBinding, class scala/collection/immutable/List, class scala/collection/immutable/List ]
          stack = []
      LineNumberTable:
        line 51: 0
        line 52: 3
        line 53: 42
        line 51: 103
      LocalVariableTable:
        Start  Length  Slot  Name   Signature
           67      33     7     x   Ljava/lang/String;
           74      26     8    xs   Lscala/collection/immutable/List;
            0     115     0  this   Lscala/xml/NamespaceBinding;
            0     115     1     l   Lscala/collection/immutable/List;
            0     115     2 stop$1   Lscala/xml/NamespaceBinding;
    MethodParameters:
      Name                           Flags
      l                              final
      stop$1                         final

  public static final void $anonfun$buildString$1(scala.xml.NamespaceBinding, scala.xml.NamespaceBinding, scala.collection.mutable.StringBuilder);
    descriptor: (Lscala/xml/NamespaceBinding;Lscala/xml/NamespaceBinding;Lscala/collection/mutable/StringBuilder;)V
    flags: (0x1019) ACC_PUBLIC, ACC_STATIC, ACC_FINAL, ACC_SYNTHETIC
    Code:
      stack=3, locals=3, args_size=3
         0: aload_0
         1: aload_2
         2: aload_1
         3: invokevirtual #313                // Method buildString:(Lscala/collection/mutable/StringBuilder;Lscala/xml/NamespaceBinding;)V
         6: return
      LineNumberTable:
        line 73: 0
      LocalVariableTable:
        Start  Length  Slot  Name   Signature
            0       7     0 $this   Lscala/xml/NamespaceBinding;
            0       7     1 stop$2   Lscala/xml/NamespaceBinding;
            0       7     2   x$2   Lscala/collection/mutable/StringBuilder;
    MethodParameters:
      Name                           Flags
      $this                          final synthetic
      stop$2                         final
      x$2                            final

  public scala.xml.NamespaceBinding(java.lang.String, java.lang.String, scala.xml.NamespaceBinding);
    descriptor: (Ljava/lang/String;Ljava/lang/String;Lscala/xml/NamespaceBinding;)V
    flags: (0x0001) ACC_PUBLIC
    Code:
      stack=3, locals=5, args_size=4
         0: aload_0
         1: aload_1
         2: putfield      #93                 // Field prefix:Ljava/lang/String;
         5: aload_0
         6: aload_2
         7: putfield      #95                 // Field uri:Ljava/lang/String;
        10: aload_0
        11: aload_3
        12: putfield      #98                 // Field parent:Lscala/xml/NamespaceBinding;
        15: aload_0
        16: invokespecial #347                // Method java/lang/Object."<init>":()V
        19: aload_0
        20: invokestatic  #351                // InterfaceMethod scala/xml/Equality.$init$:(Lscala/xml/Equality;)V
        23: aload_0
        24: invokestatic  #354                // InterfaceMethod scala/Product.$init$:(Lscala/Product;)V
        27: aload_1
        28: ldc_w         #264                // String
        31: astore        4
        33: dup
        34: ifnonnull     46
        37: pop
        38: aload         4
        40: ifnull        54
        43: goto          65
        46: aload         4
        48: invokevirtual #105                // Method java/lang/Object.equals:(Ljava/lang/Object;)Z
        51: ifeq          65
        54: new           #356                // class java/lang/IllegalArgumentException
        57: dup
        58: ldc_w         #358                // String zero length prefix not allowed
        61: invokespecial #361                // Method java/lang/IllegalArgumentException."<init>":(Ljava/lang/String;)V
        64: athrow
        65: return
      StackMapTable: number_of_entries = 3
        frame_type = 255 /* full_frame */
          offset_delta = 46
          locals = [ class scala/xml/NamespaceBinding, class java/lang/String, class java/lang/String, class scala/xml/NamespaceBinding, class java/lang/String ]
          stack = [ class java/lang/String ]
        frame_type = 7 /* same */
        frame_type = 10 /* same */
      LineNumberTable:
        line 28: 0
        line 29: 27
        line 30: 54
        line 28: 65
      LocalVariableTable:
        Start  Length  Slot  Name   Signature
            0      66     0  this   Lscala/xml/NamespaceBinding;
            0      66     1 prefix   Ljava/lang/String;
            0      66     2   uri   Ljava/lang/String;
            0      66     3 parent   Lscala/xml/NamespaceBinding;
    MethodParameters:
      Name                           Flags
      prefix                         final
      uri                            final
      parent                         final

  public static final java.lang.Object $anonfun$toString$1$adapted(scala.xml.NamespaceBinding, scala.collection.mutable.StringBuilder);
    descriptor: (Lscala/xml/NamespaceBinding;Lscala/collection/mutable/StringBuilder;)Ljava/lang/Object;
    flags: (0x1019) ACC_PUBLIC, ACC_STATIC, ACC_FINAL, ACC_SYNTHETIC
    Code:
      stack=2, locals=2, args_size=2
         0: aload_0
         1: aload_1
         2: invokestatic  #363                // Method $anonfun$toString$1:(Lscala/xml/NamespaceBinding;Lscala/collection/mutable/StringBuilder;)V
         5: getstatic     #369                // Field scala/runtime/BoxedUnit.UNIT:Lscala/runtime/BoxedUnit;
         8: areturn
      LineNumberTable:
        line 45: 0
      LocalVariableTable:
        Start  Length  Slot  Name   Signature
            0       9     0 $this   Lscala/xml/NamespaceBinding;
            0       9     1   x$1   Lscala/collection/mutable/StringBuilder;
    MethodParameters:
      Name                           Flags
      $this                          final
      x$1                            final

  public static final java.lang.Object $anonfun$buildString$1$adapted(scala.xml.NamespaceBinding, scala.xml.NamespaceBinding, scala.collection.mutable.StringBuilder);
    descriptor: (Lscala/xml/NamespaceBinding;Lscala/xml/NamespaceBinding;Lscala/collection/mutable/StringBuilder;)Ljava/lang/Object;
    flags: (0x1019) ACC_PUBLIC, ACC_STATIC, ACC_FINAL, ACC_SYNTHETIC
    Code:
      stack=3, locals=3, args_size=3
         0: aload_0
         1: aload_1
         2: aload_2
         3: invokestatic  #371                // Method $anonfun$buildString$1:(Lscala/xml/NamespaceBinding;Lscala/xml/NamespaceBinding;Lscala/collection/mutable/StringBuilder;)V
         6: getstatic     #369                // Field scala/runtime/BoxedUnit.UNIT:Lscala/runtime/BoxedUnit;
         9: areturn
      LineNumberTable:
        line 73: 0
      LocalVariableTable:
        Start  Length  Slot  Name   Signature
            0      10     0 $this   Lscala/xml/NamespaceBinding;
            0      10     1 stop$2   Lscala/xml/NamespaceBinding;
            0      10     2   x$2   Lscala/collection/mutable/StringBuilder;
    MethodParameters:
      Name                           Flags
      $this                          final
      stop$2                         final
      x$2                            final

  private static java.lang.Object $deserializeLambda$(java.lang.invoke.SerializedLambda);
    descriptor: (Ljava/lang/invoke/SerializedLambda;)Ljava/lang/Object;
    flags: (0x100a) ACC_PRIVATE, ACC_STATIC, ACC_SYNTHETIC
    Code:
      stack=1, locals=1, args_size=1
         0: aload_0
         1: invokedynamic #383,  0            // InvokeDynamic #2:lambdaDeserialize:(Ljava/lang/invoke/SerializedLambda;)Ljava/lang/Object;
         6: areturn
}
InnerClasses:
  public static final #19= #16 of #18;    // Lookup=class java/lang/invoke/MethodHandles$Lookup of class java/lang/invoke/MethodHandles
SourceFile: "NamespaceBinding.scala"
RuntimeVisibleAnnotations:
  0: #12(#13=s#14)
    scala.reflect.ScalaSignature(
      bytes="\u0006\u0005\u0005%g\u0001\u0002\u0012$\u0001\"B\u0001\u0002\u0011\u0001\u0003\u0016\u0004%\t!\u0011\u0005\t\u0015\u0002\u0011\t\u0012)A\u0005\u0005\"A1\n\u0001BK\u0002\u0013\u0005\u0011\t\u0003\u0005M\u0001\tE\t\u0015!\u0003C\u0011!i\u0005A!f\u0001\n\u0003q\u0005\u0002\u0003)\u0001\u0005#\u0005\u000b\u0011B(\t\u000bE\u0003A\u0011\u0001*\t\u000bY\u0003A\u0011A,\t\u000bi\u0003A\u0011A.\t\u000by\u0003A\u0011I0\t\u000b\u0001\u0004A\u0011B1\t\u000b\u0011\u0004A\u0011I3\t\u000b9\u0004A\u0011I8\t\u000bE\u0004A\u0011\u0001:\t\u000be\u0004A\u0011\u0001>\t\u000be\u0004A\u0011\u0001?\t\u000f\u0005=\u0001\u0001\"\u0003\u0002\u0012!I\u0011q\u0003\u0001\u0002\u0002\u0013\u0005\u0011\u0011\u0004\u0005\n\u0003C\u0001\u0011\u0013!C\u0001\u0003GA\u0011\"!\u000f\u0001#\u0003%\t!a\t\t\u0013\u0005m\u0002!%A\u0005\u0002\u0005u\u0002\"CA!\u0001\u0005\u0005I\u0011IA\"\u0011%\t\u0019\u0006AA\u0001\n\u0003\t)\u0006C\u0005\u0002^\u0001\t\t\u0011\"\u0001\u0002`!I\u0011Q\r\u0001\u0002\u0002\u0013\u0005\u0013q\r\u0005\n\u0003_\u0002\u0011\u0011!C!\u0003c:\u0011\"!!$\u0003\u0003E\t!a!\u0007\u0011\t\u001a\u0013\u0011!E\u0001\u0003\u000bCa!\u0015\u000f\u0005\u0002\u0005u\u0005\u0002\u00030\u001d\u0003\u0003%)%a(\t\u0013\u0005\u0005F$!A\u0005\u0002\u0006\r\u0006\"CAV9\u0005\u0005I\u0011QAW\u0011%\ty\fHA\u0001\n\u0013\t\tM\u0001\tOC6,7\u000f]1dK\nKg\u000eZ5oO*\u0011A%J\u0001\u0004q6d\'\"\u0001\u0014\u0002\u000bM\u001c\u0017\r\\1\u0004\u0001M)\u0001!K\u00172iA\u0011!fK\u0007\u0002K%\u0011A&\n\u0002\u0007\u0003:L(+\u001a4\u0011\u00059zS\"A\u0012\n\u0005A\u001a#\u0001C#rk\u0006d\u0017\u000e^=\u0011\u0005)\u0012\u0014BA\u001a&\u0005\u001d\u0001&o\u001c3vGR\u0004\"!N\u001f\u000f\u0005YZdBA\u001c;\u001b\u0005A$BA\u001d(\u0003\u0019a$o\\8u}%\ta%\u0003\u0002=K\u00059\u0001/Y2lC\u001e,\u0017B\u0001 @\u00051\u0019VM]5bY&T\u0018M\u00197f\u0015\taT%\u0001\u0004qe\u00164\u0017\u000e_\u000b\u0002\u0005B\u00111i\u0012\b\u0003\t\u0016\u0003\"aN\u0013\n\u0005\u0019+\u0013A\u0002)sK\u0012,g-\u0003\u0002I\u0013\n11\u000b\u001e:j]\u001eT!AR\u0013\u0002\u000fA\u0014XMZ5yA\u0005\u0019QO]5\u0002\tU\u0014\u0018\u000eI\u0001\u0007a\u0006\u0014XM\u001c;\u0016\u0003=\u0003\"A\f\u0001\u0002\u000fA\f\'/\u001a8uA\u00051A(\u001b8jiz\"BaT*U+\")\u0001i\u0002a\u0001\u0005\")1j\u0002a\u0001\u0005\")Qj\u0002a\u0001\u001f\u00061q-\u001a;V%&#\"A\u0011-\t\u000beC\u0001\u0019\u0001\"\u0002\u000f}\u0003(/\u001a4jq\u0006Iq-\u001a;Qe\u00164\u0017\u000e\u001f\u000b\u0003\u0005rCQ!X\u0005A\u0002\t\u000bAaX;sS\u0006AAo\\*ue&tw\rF\u0001C\u0003=\u0019\b.\u00193poJ+G-\u001a4j]\u0016$GCA(c\u0011\u0015\u00197\u00021\u0001P\u0003\u0011\u0019Ho\u001c9\u0002\u0011\r\fg.R9vC2$\"AZ5\u0011\u0005):\u0017B\u00015&\u0005\u001d\u0011un\u001c7fC:DQA\u001b\u0007A\u0002-\fQa\u001c;iKJ\u0004\"A\u000b7\n\u00055,#aA!os\u0006i1\u000f\u001e:jGR|F%Z9%KF$\"A\u001a9\t\u000b)l\u0001\u0019A\u0017\u0002!\t\f7/[:G_JD\u0015m\u001d5D_\u0012,W#A:\u0011\u0007Q<8.D\u0001v\u0015\t1X%\u0001\u0006d_2dWm\u0019;j_:L!\u0001_;\u0003\u0007M+\u0017/A\u0006ck&dGm\u0015;sS:<GC\u0001\"|\u0011\u0015\u0019w\u00021\u0001P)\u0015i\u0018\u0011AA\u0007!\tQc0\u0003\u0002\u0000K\t!QK\\5u\u0011\u001d\t\u0019\u0001\u0005a\u0001\u0003\u000b\t!a\u001d2\u0011\t\u0005\u001d\u0011\u0011\u0002\b\u0003UmJ1!a\u0003@\u00055\u0019FO]5oO\n+\u0018\u000e\u001c3fe\")1\r\u0005a\u0001\u001f\u0006iAm\u001c\"vS2$7\u000b\u001e:j]\u001e$R!`A\n\u0003+Aq!a\u0001\u0012\u0001\u0004\t)\u0001C\u0003d#\u0001\u0007q*\u0001\u0003d_BLHcB(\u0002\u001c\u0005u\u0011q\u0004\u0005\b\u0001J\u0001\n\u00111\u0001C\u0011\u001dY%\u0003%AA\u0002\tCq!\u0014\n\u0011\u0002\u0003\u0007q*\u0001\bd_BLH\u0005Z3gCVdG\u000fJ\u0019\u0016\u0005\u0005\u0015\"f\u0001\"\u0002(-\u0012\u0011\u0011\u0006\t\u0005\u0003W\t)$\u0004\u0002\u0002.)!\u0011qFA\u0019\u0003%)hn\u00195fG.,GMC\u0002\u00024\u0015\n!\"\u00198o_R\fG/[8o\u0013\u0011\t9$!\f\u0003#Ut7\r[3dW\u0016$g+\u0019:jC:\u001cW-\u0001\bd_BLH\u0005Z3gCVdG\u000f\n\u001a\u0002\u001d\r|\u0007/\u001f\u0013eK\u001a\fW\u000f\u001c;%gU\u0011\u0011q\b\u0016\u0004\u001f\u0006\u001d\u0012!\u00049s_\u0012,8\r\u001e)sK\u001aL\u00070\u0006\u0002\u0002FA!\u0011qIA)\u001b\t\tIE\u0003\u0003\u0002L\u00055\u0013\u0001\u00027b]\u001eT!!a\u0014\u0002\t)\fg/Y\u0005\u0004\u0011\u0006%\u0013\u0001\u00049s_\u0012,8\r^!sSRLXCAA,!\rQ\u0013\u0011L\u0005\u0004\u00037*#aA%oi\u0006q\u0001O]8ek\u000e$X\t\\3nK:$HcA6\u0002b!I\u00111\r\r\u0002\u0002\u0003\u0007\u0011qK\u0001\u0004q\u0012\n\u0014a\u00049s_\u0012,8\r^%uKJ\fGo\u001c:\u0016\u0005\u0005%\u0004\u0003\u0002;\u0002l-L1!!\u001cv\u0005!IE/\u001a:bi>\u0014\u0018A\u00059s_\u0012,8\r^#mK6,g\u000e\u001e(b[\u0016$B!!\u0012\u0002t!I\u00111\r\u000e\u0002\u0002\u0003\u0007\u0011q\u000b\u0015\b\u0001\u0005]\u0014QPA@!\rQ\u0013\u0011P\u0005\u0004\u0003w*#\u0001E*fe&\fGNV3sg&|g.V%E\u0003\u00151\u0018\r\\;f=!i>B\u007f=LFN\\\u001c\u0001\u0005(b[\u0016\u001c\b/Y2f\u0005&tG-\u001b8h!\tqCdE\u0003\u001d\u0003\u000f\u000b\u0019\n\u0005\u0005\u0002\n\u0006=%IQ(P\u001b\t\tYIC\u0002\u0002\u000e\u0016\nqA];oi&lW-\u0003\u0003\u0002\u0012\u0006-%!E!cgR\u0014\u0018m\u0019;Gk:\u001cG/[8ogA!\u0011QSAN\u001b\t\t9J\u0003\u0003\u0002\u001a\u00065\u0013AA5p\u0013\rq\u0014q\u0013\u000b\u0003\u0003\u0007#\"!!\u0012\u0002\u000b\u0005\u0004\b\u000f\\=\u0015\u000f=\u000b)+a*\u0002*\")\u0001i\ba\u0001\u0005\")1j\ba\u0001\u0005\")Qj\ba\u0001\u001f\u00069QO\\1qa2LH\u0003BAX\u0003w\u0003RAKAY\u0003kK1!a-&\u0005\u0019y\u0005\u000f^5p]B1!&a.C\u0005>K1!!/&\u0005\u0019!V\u000f\u001d7fg!A\u0011Q\u0018\u0011\u0002\u0002\u0003\u0007q*A\u0002yIA\nAb\u001e:ji\u0016\u0014V\r\u001d7bG\u0016$\"!a1\u0011\t\u0005\u001d\u0013QY\u0005\u0005\u0003\u000f\fIE\u0001\u0004PE*,7\r\u001e"
    )
BootstrapMethods:
  0: #141 REF_invokeStatic java/lang/invoke/LambdaMetafactory.altMetafactory:(Ljava/lang/invoke/MethodHandles$Lookup;Ljava/lang/String;Ljava/lang/invoke/MethodType;[Ljava/lang/Object;)Ljava/lang/invoke/CallSite;
    Method arguments:
      #125 (Ljava/lang/Object;)Ljava/lang/Object;
      #130 REF_invokeStatic scala/xml/NamespaceBinding.$anonfun$toString$1$adapted:(Lscala/xml/NamespaceBinding;Lscala/collection/mutable/StringBuilder;)Ljava/lang/Object;
      #132 (Lscala/collection/mutable/StringBuilder;)Ljava/lang/Object;
      #133 5
      #134 1
      #132 (Lscala/collection/mutable/StringBuilder;)Ljava/lang/Object;
  1: #141 REF_invokeStatic java/lang/invoke/LambdaMetafactory.altMetafactory:(Ljava/lang/invoke/MethodHandles$Lookup;Ljava/lang/String;Ljava/lang/invoke/MethodType;[Ljava/lang/Object;)Ljava/lang/invoke/CallSite;
    Method arguments:
      #125 (Ljava/lang/Object;)Ljava/lang/Object;
      #212 REF_invokeStatic scala/xml/NamespaceBinding.$anonfun$buildString$1$adapted:(Lscala/xml/NamespaceBinding;Lscala/xml/NamespaceBinding;Lscala/collection/mutable/StringBuilder;)Ljava/lang/Object;
      #132 (Lscala/collection/mutable/StringBuilder;)Ljava/lang/Object;
      #133 5
      #134 1
      #132 (Lscala/collection/mutable/StringBuilder;)Ljava/lang/Object;
  2: #380 REF_invokeStatic scala/runtime/LambdaDeserialize.bootstrap:(Ljava/lang/invoke/MethodHandles$Lookup;Ljava/lang/String;Ljava/lang/invoke/MethodType;[Ljava/lang/invoke/MethodHandle;)Ljava/lang/invoke/CallSite;
    Method arguments:
      #212 REF_invokeStatic scala/xml/NamespaceBinding.$anonfun$buildString$1$adapted:(Lscala/xml/NamespaceBinding;Lscala/xml/NamespaceBinding;Lscala/collection/mutable/StringBuilder;)Ljava/lang/Object;
      #130 REF_invokeStatic scala/xml/NamespaceBinding.$anonfun$toString$1$adapted:(Lscala/xml/NamespaceBinding;Lscala/collection/mutable/StringBuilder;)Ljava/lang/Object;
  ScalaInlineInfo: length = 0xB3 (unknown attribute)
   01 00 00 23 01 55 01 56 01 00 D0 00 D1 01 01 35
   01 36 01 00 7E 00 7F 01 00 FB 01 18 00 00 B2 00
   B3 00 00 CE 00 D8 00 00 CE 00 CF 00 00 B0 00 4D
   00 01 17 00 2A 00 01 1B 00 5B 00 01 1C 00 5B 00
   01 1D 00 60 00 00 DC 00 D8 01 00 4C 00 4D 00 00
   A9 00 AA 01 00 72 00 64 00 00 63 00 64 00 00 46
   00 47 00 00 1B 00 60 00 00 18 00 5B 00 00 98 00
   99 01 01 21 00 47 00 01 22 01 23 00 01 30 01 31
   00 00 36 00 37 00 01 2B 00 37 00 01 1E 00 5B 00
   00 95 00 96 01 00 3E 00 3F 00 00 B1 00 3F 00 00
   76 00 5B 00 00 1A 00 5B 00 00 57 00 4D 01 00 53
   00 4D 01
  ScalaSig: length = 0x3 (unknown attribute)
   05 02 00
