Classfile /Users/mw/Projects/slang-braindump/.jar/jar11/assemble/slang-braindump/assemble/content/scala/xml/NodeSeq$$anon$1.class
  Last modified May 29, 2022; size 764 bytes
  SHA-256 checksum 5dc87a6d74c1e3e8a6e526f8e381f15cdadfcec67718c6be27c06336e1b6d5f5
  Compiled from "NodeSeq.scala"
public final class scala.xml.NodeSeq$$anon$1 extends scala.xml.NodeSeq
  minor version: 0
  major version: 52
  flags: (0x0031) ACC_PUBLIC, ACC_FINAL, ACC_SUPER
  this_class: #2                          // scala/xml/NodeSeq$$anon$1
  super_class: #4                         // scala/xml/NodeSeq
  interfaces: 0, fields: 1, methods: 2, attributes: 5
Constant pool:
   #1 = Utf8               scala/xml/NodeSeq$$anon$1
   #2 = Class              #1             // scala/xml/NodeSeq$$anon$1
   #3 = Utf8               scala/xml/NodeSeq
   #4 = Class              #3             // scala/xml/NodeSeq
   #5 = Utf8               NodeSeq.scala
   #6 = Utf8               scala/xml/NodeSeq$
   #7 = Class              #6             // scala/xml/NodeSeq$
   #8 = Utf8               fromSeq
   #9 = Utf8               (Lscala/collection/Seq;)Lscala/xml/NodeSeq;
  #10 = NameAndType        #8:#9          // fromSeq:(Lscala/collection/Seq;)Lscala/xml/NodeSeq;
  #11 = Utf8               s$1
  #12 = Utf8               Lscala/collection/Seq;
  #13 = Utf8               theSeq
  #14 = Utf8               ()Lscala/collection/Seq;
  #15 = Utf8               ()Lscala/collection/Seq<Lscala/xml/Node;>;
  #16 = NameAndType        #11:#12        // s$1:Lscala/collection/Seq;
  #17 = Fieldref           #2.#16         // scala/xml/NodeSeq$$anon$1.s$1:Lscala/collection/Seq;
  #18 = Utf8               this
  #19 = Utf8               Lscala/xml/NodeSeq$$anon$1;
  #20 = Utf8               <init>
  #21 = Utf8               (Lscala/collection/Seq;)V
  #22 = Utf8               ()V
  #23 = NameAndType        #20:#22        // "<init>":()V
  #24 = Methodref          #4.#23         // scala/xml/NodeSeq."<init>":()V
  #25 = Utf8               Code
  #26 = Utf8               LineNumberTable
  #27 = Utf8               LocalVariableTable
  #28 = Utf8               Signature
  #29 = Utf8               MethodParameters
  #30 = Utf8               InnerClasses
  #31 = Utf8               EnclosingMethod
  #32 = Utf8               SourceFile
  #33 = Utf8               ScalaInlineInfo
  #34 = Utf8               Scala
{
  private final scala.collection.Seq s$1;
    descriptor: Lscala/collection/Seq;
    flags: (0x0012) ACC_PRIVATE, ACC_FINAL

  public scala.collection.Seq<scala.xml.Node> theSeq();
    descriptor: ()Lscala/collection/Seq;
    flags: (0x0001) ACC_PUBLIC
    Code:
      stack=1, locals=1, args_size=1
         0: aload_0
         1: getfield      #17                 // Field s$1:Lscala/collection/Seq;
         4: areturn
      LineNumberTable:
        line 30: 0
      LocalVariableTable:
        Start  Length  Slot  Name   Signature
            0       5     0  this   Lscala/xml/NodeSeq$$anon$1;
    Signature: #15                          // ()Lscala/collection/Seq<Lscala/xml/Node;>;

  public scala.xml.NodeSeq$$anon$1(scala.collection.Seq);
    descriptor: (Lscala/collection/Seq;)V
    flags: (0x0001) ACC_PUBLIC
    Code:
      stack=2, locals=2, args_size=2
         0: aload_0
         1: aload_1
         2: putfield      #17                 // Field s$1:Lscala/collection/Seq;
         5: aload_0
         6: invokespecial #24                 // Method scala/xml/NodeSeq."<init>":()V
         9: return
      LineNumberTable:
        line 29: 0
      LocalVariableTable:
        Start  Length  Slot  Name   Signature
            0      10     0  this   Lscala/xml/NodeSeq$$anon$1;
            0      10     1   s$1   Lscala/collection/Seq;
    MethodParameters:
      Name                           Flags
      s$1                            final
}
InnerClasses:
  public final #2;                        // class scala/xml/NodeSeq$$anon$1
EnclosingMethod: #7.#10                 // scala.xml.NodeSeq$.fromSeq
SourceFile: "NodeSeq.scala"
  ScalaInlineInfo: length = 0xE (unknown attribute)
   01 01 00 02 00 14 00 15 01 00 0D 00 0E 01
  Scala: length = 0x0 (unknown attribute)

