Classfile /Users/mw/Projects/slang-braindump/.jar/jar11/assemble/slang-braindump/assemble/content/scala/xml/package$.class
  Last modified May 29, 2022; size 612 bytes
  SHA-256 checksum 2aae2af5c812bda7905da9fb62b1c0d0690cad9601bdd4a581d473c76db11b65
  Compiled from "package.scala"
public final class scala.xml.package$
  minor version: 0
  major version: 52
  flags: (0x0031) ACC_PUBLIC, ACC_FINAL, ACC_SUPER
  this_class: #2                          // scala/xml/package$
  super_class: #4                         // java/lang/Object
  interfaces: 0, fields: 2, methods: 3, attributes: 3
Constant pool:
   #1 = Utf8               scala/xml/package$
   #2 = Class              #1             // scala/xml/package$
   #3 = Utf8               java/lang/Object
   #4 = Class              #3             // java/lang/Object
   #5 = Utf8               package.scala
   #6 = Utf8               MODULE$
   #7 = Utf8               Lscala/xml/package$;
   #8 = Utf8               XercesClassName
   #9 = Utf8               Ljava/lang/String;
  #10 = Utf8               <clinit>
  #11 = Utf8               ()V
  #12 = Utf8               <init>
  #13 = NameAndType        #12:#11        // "<init>":()V
  #14 = Methodref          #2.#13         // scala/xml/package$."<init>":()V
  #15 = NameAndType        #6:#7          // MODULE$:Lscala/xml/package$;
  #16 = Fieldref           #2.#15         // scala/xml/package$.MODULE$:Lscala/xml/package$;
  #17 = Utf8               org.apache.xerces.parsers.SAXParser
  #18 = String             #17            // org.apache.xerces.parsers.SAXParser
  #19 = NameAndType        #8:#9          // XercesClassName:Ljava/lang/String;
  #20 = Fieldref           #2.#19         // scala/xml/package$.XercesClassName:Ljava/lang/String;
  #21 = Utf8               ()Ljava/lang/String;
  #22 = Utf8               this
  #23 = Methodref          #4.#13         // java/lang/Object."<init>":()V
  #24 = Utf8               Code
  #25 = Utf8               LineNumberTable
  #26 = Utf8               LocalVariableTable
  #27 = Utf8               SourceFile
  #28 = Utf8               ScalaInlineInfo
  #29 = Utf8               Scala
{
  public static final scala.xml.package$ MODULE$;
    descriptor: Lscala/xml/package$;
    flags: (0x0019) ACC_PUBLIC, ACC_STATIC, ACC_FINAL

  private static final java.lang.String XercesClassName;
    descriptor: Ljava/lang/String;
    flags: (0x001a) ACC_PRIVATE, ACC_STATIC, ACC_FINAL

  public static {};
    descriptor: ()V
    flags: (0x0009) ACC_PUBLIC, ACC_STATIC
    Code:
      stack=2, locals=0, args_size=0
         0: new           #2                  // class scala/xml/package$
         3: dup
         4: invokespecial #14                 // Method "<init>":()V
         7: putstatic     #16                 // Field MODULE$:Lscala/xml/package$;
        10: ldc           #18                 // String org.apache.xerces.parsers.SAXParser
        12: putstatic     #20                 // Field XercesClassName:Ljava/lang/String;
        15: return
      LineNumberTable:
        line 76: 0
        line 77: 10
        line 76: 15

  public java.lang.String XercesClassName();
    descriptor: ()Ljava/lang/String;
    flags: (0x0001) ACC_PUBLIC
    Code:
      stack=1, locals=1, args_size=1
         0: getstatic     #20                 // Field XercesClassName:Ljava/lang/String;
         3: areturn
      LineNumberTable:
        line 77: 0
      LocalVariableTable:
        Start  Length  Slot  Name   Signature
            0       4     0  this   Lscala/xml/package$;

  private scala.xml.package$();
    descriptor: ()V
    flags: (0x0002) ACC_PRIVATE
    Code:
      stack=1, locals=1, args_size=1
         0: aload_0
         1: invokespecial #23                 // Method java/lang/Object."<init>":()V
         4: return
      LineNumberTable:
        line 84: 0
        line 76: 4
      LocalVariableTable:
        Start  Length  Slot  Name   Signature
            0       5     0  this   Lscala/xml/package$;
}
SourceFile: "package.scala"
  ScalaInlineInfo: length = 0xE (unknown attribute)
   01 01 00 02 00 0C 00 0B 01 00 08 00 15 01
  Scala: length = 0x0 (unknown attribute)

