Classfile /Users/mw/Projects/slang-braindump/.jar/jar11/assemble/slang-braindump/assemble/content/scala/xml/PrefixedAttribute.class
  Last modified May 29, 2022; size 7304 bytes
  SHA-256 checksum 3ca2fd04d871d3eed45b8fda8c00b9ac402851bafae5639f5dd3b2556569cd97
  Compiled from "PrefixedAttribute.scala"
public class scala.xml.PrefixedAttribute extends scala.xml.MetaData implements scala.xml.Attribute
  minor version: 0
  major version: 52
  flags: (0x0021) ACC_PUBLIC, ACC_SUPER
  this_class: #2                          // scala/xml/PrefixedAttribute
  super_class: #4                         // scala/xml/MetaData
  interfaces: 1, fields: 5, methods: 22, attributes: 4
Constant pool:
    #1 = Utf8               scala/xml/PrefixedAttribute
    #2 = Class              #1            // scala/xml/PrefixedAttribute
    #3 = Utf8               scala/xml/MetaData
    #4 = Class              #3            // scala/xml/MetaData
    #5 = Utf8               scala/xml/Attribute
    #6 = Class              #5            // scala/xml/Attribute
    #7 = Utf8               PrefixedAttribute.scala
    #8 = Utf8               Lscala/reflect/ScalaSignature;
    #9 = Utf8               bytes
   #10 = Utf8               \u0006\u0005\u0005}a\u0001B\f\u0019\u0001uA\u0001\"\n\u0001\u0003\u0006\u0004%\tA\n\u0005\te\u0001\u0011\t\u0011)A\u0005O!A1\u0007\u0001BC\u0002\u0013\u0005a\u0005\u0003\u00055\u0001\t\u0005\t\u0015!\u0003(\u0011!)\u0004A!b\u0001\n\u00031\u0004\u0002\u0003!\u0001\u0005\u0003\u0005\u000b\u0011B\u001c\t\u0011\u0005\u0003!Q1A\u0005\u0002\tC\u0001b\u0011\u0001\u0003\u0002\u0003\u0006IA\b\u0005\u0006\t\u0002!\t!\u0012\u0005\b\u0017\u0002\u0011\r\u0011\"\u0001C\u0011\u0019a\u0005\u0001)A\u0005=!)A\t\u0001C\u0001\u001b\")A\t\u0001C\u0001%\")1\f\u0001C\u00019\")a\f\u0001C\u0001?\")!\r\u0001C\u0001G\")!\r\u0001C\u0001K\u001e)a\u000e\u0007E\u0001_\u001a)q\u0003\u0007E\u0001a\")Ai\u0005C\u0001y\")Qp\u0005C\u0001}\"I\u0011qB\n\u0002\u0002\u0013%\u0011\u0011\u0003\u0002\u0012!J,g-\u001b=fI\u0006#HO]5ckR,\'BA\r\u001b\u0003\rAX\u000e\u001c\u0006\u00027\u0005)1oY1mC\u000e\u00011c\u0001\u0001\u001fEA\u0011q\u0004I\u0007\u00021%\u0011\u0011\u0005\u0007\u0002\t\u001b\u0016$\u0018\rR1uCB\u0011qdI\u0005\u0003Ia\u0011\u0011\"\u0011;ue&\u0014W\u000f^3\u0002\u0007A\u0014X-F\u0001(!\tAsF\u0004\u0002*[A\u0011!FG\u0007\u0002W)\u0011A\u0006H\u0001\u0007yI|w\u000e\u001e \n\u00059R\u0012A\u0002)sK\u0012,g-\u0003\u00021c\t11\u000b\u001e:j]\u001eT!A\f\u000e\u0002\tA\u0014X\rI\u0001\u0004W\u0016L\u0018\u0001B6fs\u0002\nQA^1mk\u0016,\u0012a\u000e\t\u0004qmjT\"A\u001d\u000b\u0005iR\u0012AC2pY2,7\r^5p]&\u0011A(\u000f\u0002\u0004\'\u0016\f\bCA\u0010?\u0013\ty\u0004D\u0001\u0003O_\u0012,\u0017A\u0002<bYV,\u0007%A\u0003oKb$\u0018\'F\u0001\u001f\u0003\u0019qW\r\u001f;2A\u00051A(\u001b8jiz\"RAR$I\u0013*\u0003\"a\b\u0001\t\u000b\u0015J\u0001\u0019A\u0014\t\u000bMJ\u0001\u0019A\u0014\t\u000bUJ\u0001\u0019A\u001c\t\u000b\u0005K\u0001\u0019\u0001\u0010\u0002\t9,\u0007\u0010^\u0001\u0006]\u0016DH\u000f\t\u000b\u0006\r:{\u0005+\u0015\u0005\u0006K1\u0001\ra\n\u0005\u0006g1\u0001\ra\n\u0005\u0006k1\u0001\ra\n\u0005\u0006\u00172\u0001\rA\b\u000b\u0006\rN#VK\u0017\u0005\u0006K5\u0001\ra\n\u0005\u0006g5\u0001\ra\n\u0005\u0006k5\u0001\rA\u0016\t\u0004/b;T\"\u0001\u000e\n\u0005eS\"AB(qi&|g\u000eC\u0003L\u001b\u0001\u0007a$\u0001\u0003d_BLHC\u0001$^\u0011\u0015Ye\u00021\u0001\u001f\u000319W\r\u001e(b[\u0016\u001c\b/Y2f)\t9\u0003\rC\u0003b\u001f\u0001\u0007Q(A\u0003po:,\'/A\u0003baBd\u0017\u0010\u0006\u00028I\")1\u0007\u0005a\u0001OQ!qG\u001a5n\u0011\u00159\u0017\u00031\u0001(\u0003%q\u0017-\\3ta\u0006\u001cW\rC\u0003j#\u0001\u0007!.A\u0003tG>\u0004X\r\u0005\u0002 W&\u0011A\u000e\u0007\u0002\u0011\u001d\u0006lWm\u001d9bG\u0016\u0014\u0015N\u001c3j]\u001eDQaM\tA\u0002\u001d\n\u0011\u0003\u0015:fM&DX\rZ!uiJL\'-\u001e;f!\ty2cE\u0002\u0014cR\u0004\"a\u0016:\n\u0005MT\"AB!osJ+g\r\u0005\u0002vu6\taO\u0003\u0002xq\u0006\u0011\u0011n\u001c\u0006\u0002s\u0006!!.\u0019<b\u0013\tYhO\u0001\u0007TKJL\u0017\r\\5{C\ndW\rF\u0001p\u0003\u001d)h.\u00199qYf$2a`A\u0006!\u00159\u0016\u0011AA\u0003\u0013\r\t\u0019A\u0007\u0002\u0005\'>lW\rE\u0004X\u0003\u000f9se\u000e\u0010\n\u0007\u0005%!D\u0001\u0004UkBdW\r\u000e\u0005\u0007\u0003\u001b)\u0002\u0019\u0001$\u0002\u0003a\fAb\u001e:ji\u0016\u0014V\r\u001d7bG\u0016$\"!a\u0005\u0011\t\u0005U\u00111D\u0007\u0003\u0003/Q1!!\u0007y\u0003\u0011a\u0017M\\4\n\t\u0005u\u0011q\u0003\u0002\u0007\u001f\nTWm\u0019;
   #11 = Utf8               pre
   #12 = Utf8               Ljava/lang/String;
   #13 = Utf8               key
   #14 = Utf8               value
   #15 = Utf8               Lscala/collection/Seq;
   #16 = Utf8               Lscala/collection/Seq<Lscala/xml/Node;>;
   #17 = Utf8               next1
   #18 = Utf8               Lscala/xml/MetaData;
   #19 = Utf8               next
   #20 = Utf8               unapply
   #21 = Utf8               (Lscala/xml/PrefixedAttribute;)Lscala/Some;
   #22 = Utf8               (Lscala/xml/PrefixedAttribute;)Lscala/Some<Lscala/Tuple4<Ljava/lang/String;Ljava/lang/String;Lscala/collection/Seq<Lscala/xml/Node;>;Lscala/xml/MetaData;>;>;
   #23 = Utf8               x
   #24 = Utf8               scala/xml/PrefixedAttribute$
   #25 = Class              #24           // scala/xml/PrefixedAttribute$
   #26 = Utf8               MODULE$
   #27 = Utf8               Lscala/xml/PrefixedAttribute$;
   #28 = NameAndType        #26:#27       // MODULE$:Lscala/xml/PrefixedAttribute$;
   #29 = Fieldref           #25.#28       // scala/xml/PrefixedAttribute$.MODULE$:Lscala/xml/PrefixedAttribute$;
   #30 = NameAndType        #20:#21       // unapply:(Lscala/xml/PrefixedAttribute;)Lscala/Some;
   #31 = Methodref          #25.#30       // scala/xml/PrefixedAttribute$.unapply:(Lscala/xml/PrefixedAttribute;)Lscala/Some;
   #32 = Utf8               Lscala/xml/PrefixedAttribute;
   #33 = Utf8               remove
   #34 = Utf8               (Ljava/lang/String;)Lscala/xml/MetaData;
   #35 = Utf8               remove$
   #36 = Utf8               (Lscala/xml/Attribute;Ljava/lang/String;)Lscala/xml/MetaData;
   #37 = NameAndType        #35:#36       // remove$:(Lscala/xml/Attribute;Ljava/lang/String;)Lscala/xml/MetaData;
   #38 = InterfaceMethodref #6.#37        // scala/xml/Attribute.remove$:(Lscala/xml/Attribute;Ljava/lang/String;)Lscala/xml/MetaData;
   #39 = Utf8               this
   #40 = Utf8               (Ljava/lang/String;Lscala/xml/NamespaceBinding;Ljava/lang/String;)Lscala/xml/MetaData;
   #41 = Utf8               namespace
   #42 = Utf8               scope
   #43 = Utf8               (Lscala/xml/Attribute;Ljava/lang/String;Lscala/xml/NamespaceBinding;Ljava/lang/String;)Lscala/xml/MetaData;
   #44 = NameAndType        #35:#43       // remove$:(Lscala/xml/Attribute;Ljava/lang/String;Lscala/xml/NamespaceBinding;Ljava/lang/String;)Lscala/xml/MetaData;
   #45 = InterfaceMethodref #6.#44        // scala/xml/Attribute.remove$:(Lscala/xml/Attribute;Ljava/lang/String;Lscala/xml/NamespaceBinding;Ljava/lang/String;)Lscala/xml/MetaData;
   #46 = Utf8               Lscala/xml/NamespaceBinding;
   #47 = Utf8               isPrefixed
   #48 = Utf8               ()Z
   #49 = Utf8               isPrefixed$
   #50 = Utf8               (Lscala/xml/Attribute;)Z
   #51 = NameAndType        #49:#50       // isPrefixed$:(Lscala/xml/Attribute;)Z
   #52 = InterfaceMethodref #6.#51        // scala/xml/Attribute.isPrefixed$:(Lscala/xml/Attribute;)Z
   #53 = Utf8               wellformed
   #54 = Utf8               (Lscala/xml/NamespaceBinding;)Z
   #55 = Utf8               wellformed$
   #56 = Utf8               (Lscala/xml/Attribute;Lscala/xml/NamespaceBinding;)Z
   #57 = NameAndType        #55:#56       // wellformed$:(Lscala/xml/Attribute;Lscala/xml/NamespaceBinding;)Z
   #58 = InterfaceMethodref #6.#57        // scala/xml/Attribute.wellformed$:(Lscala/xml/Attribute;Lscala/xml/NamespaceBinding;)Z
   #59 = Utf8               iterator
   #60 = Utf8               ()Lscala/collection/Iterator;
   #61 = Utf8               ()Lscala/collection/Iterator<Lscala/xml/MetaData;>;
   #62 = Utf8               iterator$
   #63 = Utf8               (Lscala/xml/Attribute;)Lscala/collection/Iterator;
   #64 = NameAndType        #62:#63       // iterator$:(Lscala/xml/Attribute;)Lscala/collection/Iterator;
   #65 = InterfaceMethodref #6.#64        // scala/xml/Attribute.iterator$:(Lscala/xml/Attribute;)Lscala/collection/Iterator;
   #66 = Utf8               size
   #67 = Utf8               ()I
   #68 = Utf8               size$
   #69 = Utf8               (Lscala/xml/Attribute;)I
   #70 = NameAndType        #68:#69       // size$:(Lscala/xml/Attribute;)I
   #71 = InterfaceMethodref #6.#70        // scala/xml/Attribute.size$:(Lscala/xml/Attribute;)I
   #72 = Utf8               toString1
   #73 = Utf8               (Lscala/collection/mutable/StringBuilder;)V
   #74 = Utf8               sb
   #75 = Utf8               toString1$
   #76 = Utf8               (Lscala/xml/Attribute;Lscala/collection/mutable/StringBuilder;)V
   #77 = NameAndType        #75:#76       // toString1$:(Lscala/xml/Attribute;Lscala/collection/mutable/StringBuilder;)V
   #78 = InterfaceMethodref #6.#77        // scala/xml/Attribute.toString1$:(Lscala/xml/Attribute;Lscala/collection/mutable/StringBuilder;)V
   #79 = Utf8               Lscala/collection/mutable/StringBuilder;
   #80 = Utf8               ()Ljava/lang/String;
   #81 = NameAndType        #11:#12       // pre:Ljava/lang/String;
   #82 = Fieldref           #2.#81        // scala/xml/PrefixedAttribute.pre:Ljava/lang/String;
   #83 = NameAndType        #13:#12       // key:Ljava/lang/String;
   #84 = Fieldref           #2.#83        // scala/xml/PrefixedAttribute.key:Ljava/lang/String;
   #85 = Utf8               ()Lscala/collection/Seq;
   #86 = Utf8               ()Lscala/collection/Seq<Lscala/xml/Node;>;
   #87 = NameAndType        #14:#15       // value:Lscala/collection/Seq;
   #88 = Fieldref           #2.#87        // scala/xml/PrefixedAttribute.value:Lscala/collection/Seq;
   #89 = Utf8               ()Lscala/xml/MetaData;
   #90 = NameAndType        #17:#18       // next1:Lscala/xml/MetaData;
   #91 = Fieldref           #2.#90        // scala/xml/PrefixedAttribute.next1:Lscala/xml/MetaData;
   #92 = NameAndType        #19:#18       // next:Lscala/xml/MetaData;
   #93 = Fieldref           #2.#92        // scala/xml/PrefixedAttribute.next:Lscala/xml/MetaData;
   #94 = Utf8               copy
   #95 = Utf8               (Lscala/xml/MetaData;)Lscala/xml/PrefixedAttribute;
   #96 = NameAndType        #11:#80       // pre:()Ljava/lang/String;
   #97 = Methodref          #2.#96        // scala/xml/PrefixedAttribute.pre:()Ljava/lang/String;
   #98 = NameAndType        #13:#80       // key:()Ljava/lang/String;
   #99 = Methodref          #2.#98        // scala/xml/PrefixedAttribute.key:()Ljava/lang/String;
  #100 = NameAndType        #14:#85       // value:()Lscala/collection/Seq;
  #101 = Methodref          #2.#100       // scala/xml/PrefixedAttribute.value:()Lscala/collection/Seq;
  #102 = Utf8               <init>
  #103 = Utf8               (Ljava/lang/String;Ljava/lang/String;Lscala/collection/Seq;Lscala/xml/MetaData;)V
  #104 = NameAndType        #102:#103     // "<init>":(Ljava/lang/String;Ljava/lang/String;Lscala/collection/Seq;Lscala/xml/MetaData;)V
  #105 = Methodref          #2.#104       // scala/xml/PrefixedAttribute."<init>":(Ljava/lang/String;Ljava/lang/String;Lscala/collection/Seq;Lscala/xml/MetaData;)V
  #106 = Utf8               getNamespace
  #107 = Utf8               (Lscala/xml/Node;)Ljava/lang/String;
  #108 = Utf8               owner
  #109 = Utf8               scala/xml/Node
  #110 = Class              #109          // scala/xml/Node
  #111 = Utf8               (Ljava/lang/String;)Ljava/lang/String;
  #112 = NameAndType        #106:#111     // getNamespace:(Ljava/lang/String;)Ljava/lang/String;
  #113 = Methodref          #110.#112     // scala/xml/Node.getNamespace:(Ljava/lang/String;)Ljava/lang/String;
  #114 = Utf8               Lscala/xml/Node;
  #115 = Utf8               apply
  #116 = Utf8               (Ljava/lang/String;)Lscala/collection/Seq;
  #117 = Utf8               (Ljava/lang/String;)Lscala/collection/Seq<Lscala/xml/Node;>;
  #118 = NameAndType        #19:#89       // next:()Lscala/xml/MetaData;
  #119 = Methodref          #2.#118       // scala/xml/PrefixedAttribute.next:()Lscala/xml/MetaData;
  #120 = NameAndType        #115:#116     // apply:(Ljava/lang/String;)Lscala/collection/Seq;
  #121 = Methodref          #4.#120       // scala/xml/MetaData.apply:(Ljava/lang/String;)Lscala/collection/Seq;
  #122 = Utf8               (Ljava/lang/String;Lscala/xml/NamespaceBinding;Ljava/lang/String;)Lscala/collection/Seq;
  #123 = Utf8               (Ljava/lang/String;Lscala/xml/NamespaceBinding;Ljava/lang/String;)Lscala/collection/Seq<Lscala/xml/Node;>;
  #124 = Utf8               java/lang/Object
  #125 = Class              #124          // java/lang/Object
  #126 = Utf8               equals
  #127 = Utf8               (Ljava/lang/Object;)Z
  #128 = NameAndType        #126:#127     // equals:(Ljava/lang/Object;)Z
  #129 = Methodref          #125.#128     // java/lang/Object.equals:(Ljava/lang/Object;)Z
  #130 = Utf8               scala/xml/NamespaceBinding
  #131 = Class              #130          // scala/xml/NamespaceBinding
  #132 = Utf8               getURI
  #133 = NameAndType        #132:#111     // getURI:(Ljava/lang/String;)Ljava/lang/String;
  #134 = Methodref          #131.#133     // scala/xml/NamespaceBinding.getURI:(Ljava/lang/String;)Ljava/lang/String;
  #135 = NameAndType        #115:#122     // apply:(Ljava/lang/String;Lscala/xml/NamespaceBinding;Ljava/lang/String;)Lscala/collection/Seq;
  #136 = Methodref          #4.#135       // scala/xml/MetaData.apply:(Ljava/lang/String;Lscala/xml/NamespaceBinding;Ljava/lang/String;)Lscala/collection/Seq;
  #137 = Utf8               java/lang/String
  #138 = Class              #137          // java/lang/String
  #139 = Utf8               scala/collection/Seq
  #140 = Class              #139          // scala/collection/Seq
  #141 = Utf8               (Lscala/xml/MetaData;)Lscala/xml/MetaData;
  #142 = NameAndType        #94:#95       // copy:(Lscala/xml/MetaData;)Lscala/xml/PrefixedAttribute;
  #143 = Methodref          #2.#142       // scala/xml/PrefixedAttribute.copy:(Lscala/xml/MetaData;)Lscala/xml/PrefixedAttribute;
  #144 = Utf8               (Lscala/xml/MetaData;)Lscala/xml/Attribute;
  #145 = Utf8               (Ljava/lang/String;Ljava/lang/String;Lscala/collection/Seq<Lscala/xml/Node;>;Lscala/xml/MetaData;)V
  #146 = Utf8               ()V
  #147 = NameAndType        #102:#146     // "<init>":()V
  #148 = Methodref          #4.#147       // scala/xml/MetaData."<init>":()V
  #149 = Utf8               $init$
  #150 = Utf8               (Lscala/xml/Attribute;)V
  #151 = NameAndType        #149:#150     // $init$:(Lscala/xml/Attribute;)V
  #152 = InterfaceMethodref #6.#151       // scala/xml/Attribute.$init$:(Lscala/xml/Attribute;)V
  #153 = NameAndType        #33:#34       // remove:(Ljava/lang/String;)Lscala/xml/MetaData;
  #154 = Methodref          #4.#153       // scala/xml/MetaData.remove:(Ljava/lang/String;)Lscala/xml/MetaData;
  #155 = Utf8               (Ljava/lang/String;Ljava/lang/String;Ljava/lang/String;Lscala/xml/MetaData;)V
  #156 = Utf8               scala/xml/Text$
  #157 = Class              #156          // scala/xml/Text$
  #158 = Utf8               Lscala/xml/Text$;
  #159 = NameAndType        #26:#158      // MODULE$:Lscala/xml/Text$;
  #160 = Fieldref           #157.#159     // scala/xml/Text$.MODULE$:Lscala/xml/Text$;
  #161 = Utf8               (Ljava/lang/String;)Lscala/xml/Text;
  #162 = NameAndType        #115:#161     // apply:(Ljava/lang/String;)Lscala/xml/Text;
  #163 = Methodref          #157.#162     // scala/xml/Text$.apply:(Ljava/lang/String;)Lscala/xml/Text;
  #164 = Utf8               scala/xml/Text
  #165 = Class              #164          // scala/xml/Text
  #166 = Utf8               (Ljava/lang/String;Ljava/lang/String;Lscala/Option;Lscala/xml/MetaData;)V
  #167 = Utf8               (Ljava/lang/String;Ljava/lang/String;Lscala/Option<Lscala/collection/Seq<Lscala/xml/Node;>;>;Lscala/xml/MetaData;)V
  #168 = Utf8               scala/$less$colon$less$
  #169 = Class              #168          // scala/$less$colon$less$
  #170 = Utf8               Lscala/$less$colon$less$;
  #171 = NameAndType        #26:#170      // MODULE$:Lscala/$less$colon$less$;
  #172 = Fieldref           #169.#171     // scala/$less$colon$less$.MODULE$:Lscala/$less$colon$less$;
  #173 = Utf8               refl
  #174 = Utf8               ()Lscala/$eq$colon$eq;
  #175 = NameAndType        #173:#174     // refl:()Lscala/$eq$colon$eq;
  #176 = Methodref          #169.#175     // scala/$less$colon$less$.refl:()Lscala/$eq$colon$eq;
  #177 = Utf8               scala/Option
  #178 = Class              #177          // scala/Option
  #179 = Utf8               orNull
  #180 = Utf8               (Lscala/$less$colon$less;)Ljava/lang/Object;
  #181 = NameAndType        #179:#180     // orNull:(Lscala/$less$colon$less;)Ljava/lang/Object;
  #182 = Methodref          #178.#181     // scala/Option.orNull:(Lscala/$less$colon$less;)Ljava/lang/Object;
  #183 = Utf8               Lscala/Option;
  #184 = Utf8               Signature
  #185 = Utf8               Code
  #186 = Utf8               LocalVariableTable
  #187 = Utf8               MethodParameters
  #188 = Utf8               LineNumberTable
  #189 = Utf8               StackMapTable
  #190 = Utf8               SourceFile
  #191 = Utf8               RuntimeVisibleAnnotations
  #192 = Utf8               ScalaInlineInfo
  #193 = Utf8               ScalaSig
{
  private final java.lang.String pre;
    descriptor: Ljava/lang/String;
    flags: (0x0012) ACC_PRIVATE, ACC_FINAL

  private final java.lang.String key;
    descriptor: Ljava/lang/String;
    flags: (0x0012) ACC_PRIVATE, ACC_FINAL

  private final scala.collection.Seq<scala.xml.Node> value;
    descriptor: Lscala/collection/Seq;
    flags: (0x0012) ACC_PRIVATE, ACC_FINAL
    Signature: #16                          // Lscala/collection/Seq<Lscala/xml/Node;>;

  private final scala.xml.MetaData next1;
    descriptor: Lscala/xml/MetaData;
    flags: (0x0012) ACC_PRIVATE, ACC_FINAL

  private final scala.xml.MetaData next;
    descriptor: Lscala/xml/MetaData;
    flags: (0x0012) ACC_PRIVATE, ACC_FINAL

  public static scala.Some<scala.Tuple4<java.lang.String, java.lang.String, scala.collection.Seq<scala.xml.Node>, scala.xml.MetaData>> unapply(scala.xml.PrefixedAttribute);
    descriptor: (Lscala/xml/PrefixedAttribute;)Lscala/Some;
    flags: (0x0009) ACC_PUBLIC, ACC_STATIC
    Code:
      stack=2, locals=1, args_size=1
         0: getstatic     #29                 // Field scala/xml/PrefixedAttribute$.MODULE$:Lscala/xml/PrefixedAttribute$;
         3: aload_0
         4: invokevirtual #31                 // Method scala/xml/PrefixedAttribute$.unapply:(Lscala/xml/PrefixedAttribute;)Lscala/Some;
         7: areturn
      LocalVariableTable:
        Start  Length  Slot  Name   Signature
            0       8     0     x   Lscala/xml/PrefixedAttribute;
    Signature: #22                          // (Lscala/xml/PrefixedAttribute;)Lscala/Some<Lscala/Tuple4<Ljava/lang/String;Ljava/lang/String;Lscala/collection/Seq<Lscala/xml/Node;>;Lscala/xml/MetaData;>;>;
    MethodParameters:
      Name                           Flags
      x                              final

  public scala.xml.MetaData remove(java.lang.String);
    descriptor: (Ljava/lang/String;)Lscala/xml/MetaData;
    flags: (0x0001) ACC_PUBLIC
    Code:
      stack=2, locals=2, args_size=2
         0: aload_0
         1: aload_1
         2: invokestatic  #38                 // InterfaceMethod scala/xml/Attribute.remove$:(Lscala/xml/Attribute;Ljava/lang/String;)Lscala/xml/MetaData;
         5: areturn
      LineNumberTable:
        line 26: 0
      LocalVariableTable:
        Start  Length  Slot  Name   Signature
            0       6     0  this   Lscala/xml/PrefixedAttribute;
            0       6     1   key   Ljava/lang/String;
    MethodParameters:
      Name                           Flags
      key                            final

  public scala.xml.MetaData remove(java.lang.String, scala.xml.NamespaceBinding, java.lang.String);
    descriptor: (Ljava/lang/String;Lscala/xml/NamespaceBinding;Ljava/lang/String;)Lscala/xml/MetaData;
    flags: (0x0001) ACC_PUBLIC
    Code:
      stack=4, locals=4, args_size=4
         0: aload_0
         1: aload_1
         2: aload_2
         3: aload_3
         4: invokestatic  #45                 // InterfaceMethod scala/xml/Attribute.remove$:(Lscala/xml/Attribute;Ljava/lang/String;Lscala/xml/NamespaceBinding;Ljava/lang/String;)Lscala/xml/MetaData;
         7: areturn
      LineNumberTable:
        line 26: 0
      LocalVariableTable:
        Start  Length  Slot  Name   Signature
            0       8     0  this   Lscala/xml/PrefixedAttribute;
            0       8     1 namespace   Ljava/lang/String;
            0       8     2 scope   Lscala/xml/NamespaceBinding;
            0       8     3   key   Ljava/lang/String;
    MethodParameters:
      Name                           Flags
      namespace                      final
      scope                          final
      key                            final

  public boolean isPrefixed();
    descriptor: ()Z
    flags: (0x0001) ACC_PUBLIC
    Code:
      stack=1, locals=1, args_size=1
         0: aload_0
         1: invokestatic  #52                 // InterfaceMethod scala/xml/Attribute.isPrefixed$:(Lscala/xml/Attribute;)Z
         4: ireturn
      LineNumberTable:
        line 26: 0
      LocalVariableTable:
        Start  Length  Slot  Name   Signature
            0       5     0  this   Lscala/xml/PrefixedAttribute;

  public boolean wellformed(scala.xml.NamespaceBinding);
    descriptor: (Lscala/xml/NamespaceBinding;)Z
    flags: (0x0001) ACC_PUBLIC
    Code:
      stack=2, locals=2, args_size=2
         0: aload_0
         1: aload_1
         2: invokestatic  #58                 // InterfaceMethod scala/xml/Attribute.wellformed$:(Lscala/xml/Attribute;Lscala/xml/NamespaceBinding;)Z
         5: ireturn
      LineNumberTable:
        line 26: 0
      LocalVariableTable:
        Start  Length  Slot  Name   Signature
            0       6     0  this   Lscala/xml/PrefixedAttribute;
            0       6     1 scope   Lscala/xml/NamespaceBinding;
    MethodParameters:
      Name                           Flags
      scope                          final

  public scala.collection.Iterator<scala.xml.MetaData> iterator();
    descriptor: ()Lscala/collection/Iterator;
    flags: (0x0001) ACC_PUBLIC
    Code:
      stack=1, locals=1, args_size=1
         0: aload_0
         1: invokestatic  #65                 // InterfaceMethod scala/xml/Attribute.iterator$:(Lscala/xml/Attribute;)Lscala/collection/Iterator;
         4: areturn
      LineNumberTable:
        line 26: 0
      LocalVariableTable:
        Start  Length  Slot  Name   Signature
            0       5     0  this   Lscala/xml/PrefixedAttribute;
    Signature: #61                          // ()Lscala/collection/Iterator<Lscala/xml/MetaData;>;

  public int size();
    descriptor: ()I
    flags: (0x0001) ACC_PUBLIC
    Code:
      stack=1, locals=1, args_size=1
         0: aload_0
         1: invokestatic  #71                 // InterfaceMethod scala/xml/Attribute.size$:(Lscala/xml/Attribute;)I
         4: ireturn
      LineNumberTable:
        line 26: 0
      LocalVariableTable:
        Start  Length  Slot  Name   Signature
            0       5     0  this   Lscala/xml/PrefixedAttribute;

  public void toString1(scala.collection.mutable.StringBuilder);
    descriptor: (Lscala/collection/mutable/StringBuilder;)V
    flags: (0x0001) ACC_PUBLIC
    Code:
      stack=2, locals=2, args_size=2
         0: aload_0
         1: aload_1
         2: invokestatic  #78                 // InterfaceMethod scala/xml/Attribute.toString1$:(Lscala/xml/Attribute;Lscala/collection/mutable/StringBuilder;)V
         5: return
      LineNumberTable:
        line 26: 0
      LocalVariableTable:
        Start  Length  Slot  Name   Signature
            0       6     0  this   Lscala/xml/PrefixedAttribute;
            0       6     1    sb   Lscala/collection/mutable/StringBuilder;
    MethodParameters:
      Name                           Flags
      sb                             final

  public java.lang.String pre();
    descriptor: ()Ljava/lang/String;
    flags: (0x0001) ACC_PUBLIC
    Code:
      stack=1, locals=1, args_size=1
         0: aload_0
         1: getfield      #82                 // Field pre:Ljava/lang/String;
         4: areturn
      LineNumberTable:
        line 27: 0
      LocalVariableTable:
        Start  Length  Slot  Name   Signature
            0       5     0  this   Lscala/xml/PrefixedAttribute;

  public java.lang.String key();
    descriptor: ()Ljava/lang/String;
    flags: (0x0001) ACC_PUBLIC
    Code:
      stack=1, locals=1, args_size=1
         0: aload_0
         1: getfield      #84                 // Field key:Ljava/lang/String;
         4: areturn
      LineNumberTable:
        line 28: 0
      LocalVariableTable:
        Start  Length  Slot  Name   Signature
            0       5     0  this   Lscala/xml/PrefixedAttribute;

  public scala.collection.Seq<scala.xml.Node> value();
    descriptor: ()Lscala/collection/Seq;
    flags: (0x0001) ACC_PUBLIC
    Code:
      stack=1, locals=1, args_size=1
         0: aload_0
         1: getfield      #88                 // Field value:Lscala/collection/Seq;
         4: areturn
      LineNumberTable:
        line 29: 0
      LocalVariableTable:
        Start  Length  Slot  Name   Signature
            0       5     0  this   Lscala/xml/PrefixedAttribute;
    Signature: #86                          // ()Lscala/collection/Seq<Lscala/xml/Node;>;

  public scala.xml.MetaData next1();
    descriptor: ()Lscala/xml/MetaData;
    flags: (0x0001) ACC_PUBLIC
    Code:
      stack=1, locals=1, args_size=1
         0: aload_0
         1: getfield      #91                 // Field next1:Lscala/xml/MetaData;
         4: areturn
      LineNumberTable:
        line 30: 0
      LocalVariableTable:
        Start  Length  Slot  Name   Signature
            0       5     0  this   Lscala/xml/PrefixedAttribute;

  public scala.xml.MetaData next();
    descriptor: ()Lscala/xml/MetaData;
    flags: (0x0001) ACC_PUBLIC
    Code:
      stack=1, locals=1, args_size=1
         0: aload_0
         1: getfield      #93                 // Field next:Lscala/xml/MetaData;
         4: areturn
      LineNumberTable:
        line 32: 0
      LocalVariableTable:
        Start  Length  Slot  Name   Signature
            0       5     0  this   Lscala/xml/PrefixedAttribute;

  public scala.xml.PrefixedAttribute copy(scala.xml.MetaData);
    descriptor: (Lscala/xml/MetaData;)Lscala/xml/PrefixedAttribute;
    flags: (0x0001) ACC_PUBLIC
    Code:
      stack=6, locals=2, args_size=2
         0: new           #2                  // class scala/xml/PrefixedAttribute
         3: dup
         4: aload_0
         5: invokevirtual #97                 // Method pre:()Ljava/lang/String;
         8: aload_0
         9: invokevirtual #99                 // Method key:()Ljava/lang/String;
        12: aload_0
        13: invokevirtual #101                // Method value:()Lscala/collection/Seq;
        16: aload_1
        17: invokespecial #105                // Method "<init>":(Ljava/lang/String;Ljava/lang/String;Lscala/collection/Seq;Lscala/xml/MetaData;)V
        20: areturn
      LineNumberTable:
        line 47: 0
      LocalVariableTable:
        Start  Length  Slot  Name   Signature
            0      21     0  this   Lscala/xml/PrefixedAttribute;
            0      21     1  next   Lscala/xml/MetaData;
    MethodParameters:
      Name                           Flags
      next                           final

  public java.lang.String getNamespace(scala.xml.Node);
    descriptor: (Lscala/xml/Node;)Ljava/lang/String;
    flags: (0x0001) ACC_PUBLIC
    Code:
      stack=2, locals=2, args_size=2
         0: aload_1
         1: aload_0
         2: invokevirtual #97                 // Method pre:()Ljava/lang/String;
         5: invokevirtual #113                // Method scala/xml/Node.getNamespace:(Ljava/lang/String;)Ljava/lang/String;
         8: areturn
      LineNumberTable:
        line 50: 0
      LocalVariableTable:
        Start  Length  Slot  Name   Signature
            0       9     0  this   Lscala/xml/PrefixedAttribute;
            0       9     1 owner   Lscala/xml/Node;
    MethodParameters:
      Name                           Flags
      owner                          final

  public scala.collection.Seq<scala.xml.Node> apply(java.lang.String);
    descriptor: (Ljava/lang/String;)Lscala/collection/Seq;
    flags: (0x0001) ACC_PUBLIC
    Code:
      stack=2, locals=2, args_size=2
         0: aload_0
         1: invokevirtual #119                // Method next:()Lscala/xml/MetaData;
         4: aload_1
         5: invokevirtual #121                // Method scala/xml/MetaData.apply:(Ljava/lang/String;)Lscala/collection/Seq;
         8: areturn
      LineNumberTable:
        line 53: 0
      LocalVariableTable:
        Start  Length  Slot  Name   Signature
            0       9     0  this   Lscala/xml/PrefixedAttribute;
            0       9     1   key   Ljava/lang/String;
    Signature: #117                         // (Ljava/lang/String;)Lscala/collection/Seq<Lscala/xml/Node;>;
    MethodParameters:
      Name                           Flags
      key                            final

  public scala.collection.Seq<scala.xml.Node> apply(java.lang.String, scala.xml.NamespaceBinding, java.lang.String);
    descriptor: (Ljava/lang/String;Lscala/xml/NamespaceBinding;Ljava/lang/String;)Lscala/collection/Seq;
    flags: (0x0001) ACC_PUBLIC
    Code:
      stack=4, locals=6, args_size=4
         0: aload_3
         1: aload_0
         2: invokevirtual #99                 // Method key:()Ljava/lang/String;
         5: astore        4
         7: dup
         8: ifnonnull     20
        11: pop
        12: aload         4
        14: ifnull        28
        17: goto          67
        20: aload         4
        22: invokevirtual #129                // Method java/lang/Object.equals:(Ljava/lang/Object;)Z
        25: ifeq          67
        28: aload_2
        29: aload_0
        30: invokevirtual #97                 // Method pre:()Ljava/lang/String;
        33: invokevirtual #134                // Method scala/xml/NamespaceBinding.getURI:(Ljava/lang/String;)Ljava/lang/String;
        36: aload_1
        37: astore        5
        39: dup
        40: ifnonnull     52
        43: pop
        44: aload         5
        46: ifnull        60
        49: goto          67
        52: aload         5
        54: invokevirtual #129                // Method java/lang/Object.equals:(Ljava/lang/Object;)Z
        57: ifeq          67
        60: aload_0
        61: invokevirtual #101                // Method value:()Lscala/collection/Seq;
        64: goto          77
        67: aload_0
        68: invokevirtual #119                // Method next:()Lscala/xml/MetaData;
        71: aload_1
        72: aload_2
        73: aload_3
        74: invokevirtual #136                // Method scala/xml/MetaData.apply:(Ljava/lang/String;Lscala/xml/NamespaceBinding;Ljava/lang/String;)Lscala/collection/Seq;
        77: areturn
      StackMapTable: number_of_entries = 6
        frame_type = 255 /* full_frame */
          offset_delta = 20
          locals = [ class scala/xml/PrefixedAttribute, class java/lang/String, class scala/xml/NamespaceBinding, class java/lang/String, class java/lang/String ]
          stack = [ class java/lang/String ]
        frame_type = 7 /* same */
        frame_type = 255 /* full_frame */
          offset_delta = 23
          locals = [ class scala/xml/PrefixedAttribute, class java/lang/String, class scala/xml/NamespaceBinding, class java/lang/String, class java/lang/String, class java/lang/String ]
          stack = [ class java/lang/String ]
        frame_type = 7 /* same */
        frame_type = 250 /* chop */
          offset_delta = 6
        frame_type = 73 /* same_locals_1_stack_item */
          stack = [ class scala/collection/Seq ]
      LineNumberTable:
        line 59: 0
        line 60: 60
        line 62: 67
      LocalVariableTable:
        Start  Length  Slot  Name   Signature
            0      78     0  this   Lscala/xml/PrefixedAttribute;
            0      78     1 namespace   Ljava/lang/String;
            0      78     2 scope   Lscala/xml/NamespaceBinding;
            0      78     3   key   Ljava/lang/String;
    Signature: #123                         // (Ljava/lang/String;Lscala/xml/NamespaceBinding;Ljava/lang/String;)Lscala/collection/Seq<Lscala/xml/Node;>;
    MethodParameters:
      Name                           Flags
      namespace                      final
      scope                          final
      key                            final

  public scala.xml.MetaData copy(scala.xml.MetaData);
    descriptor: (Lscala/xml/MetaData;)Lscala/xml/MetaData;
    flags: (0x1041) ACC_PUBLIC, ACC_BRIDGE, ACC_SYNTHETIC
    Code:
      stack=2, locals=2, args_size=2
         0: aload_0
         1: aload_1
         2: invokevirtual #143                // Method copy:(Lscala/xml/MetaData;)Lscala/xml/PrefixedAttribute;
         5: areturn
      LineNumberTable:
        line 26: 0
      LocalVariableTable:
        Start  Length  Slot  Name   Signature
            0       6     0  this   Lscala/xml/PrefixedAttribute;
            0       6     1  next   Lscala/xml/MetaData;
    MethodParameters:
      Name                           Flags
      next                           final

  public scala.xml.Attribute copy(scala.xml.MetaData);
    descriptor: (Lscala/xml/MetaData;)Lscala/xml/Attribute;
    flags: (0x1041) ACC_PUBLIC, ACC_BRIDGE, ACC_SYNTHETIC
    Code:
      stack=2, locals=2, args_size=2
         0: aload_0
         1: aload_1
         2: invokevirtual #143                // Method copy:(Lscala/xml/MetaData;)Lscala/xml/PrefixedAttribute;
         5: areturn
      LineNumberTable:
        line 26: 0
      LocalVariableTable:
        Start  Length  Slot  Name   Signature
            0       6     0  this   Lscala/xml/PrefixedAttribute;
            0       6     1  next   Lscala/xml/MetaData;
    MethodParameters:
      Name                           Flags
      next                           final

  public scala.xml.PrefixedAttribute(java.lang.String, java.lang.String, scala.collection.Seq<scala.xml.Node>, scala.xml.MetaData);
    descriptor: (Ljava/lang/String;Ljava/lang/String;Lscala/collection/Seq;Lscala/xml/MetaData;)V
    flags: (0x0001) ACC_PUBLIC
    Code:
      stack=3, locals=5, args_size=5
         0: aload_0
         1: aload_1
         2: putfield      #82                 // Field pre:Ljava/lang/String;
         5: aload_0
         6: aload_2
         7: putfield      #84                 // Field key:Ljava/lang/String;
        10: aload_0
        11: aload_3
        12: putfield      #88                 // Field value:Lscala/collection/Seq;
        15: aload_0
        16: aload         4
        18: putfield      #91                 // Field next1:Lscala/xml/MetaData;
        21: aload_0
        22: invokespecial #148                // Method scala/xml/MetaData."<init>":()V
        25: aload_0
        26: invokestatic  #152                // InterfaceMethod scala/xml/Attribute.$init$:(Lscala/xml/Attribute;)V
        29: aload_0
        30: aload_3
        31: ifnull        39
        34: aload         4
        36: goto          45
        39: aload         4
        41: aload_2
        42: invokevirtual #154                // Method scala/xml/MetaData.remove:(Ljava/lang/String;)Lscala/xml/MetaData;
        45: putfield      #93                 // Field next:Lscala/xml/MetaData;
        48: return
      StackMapTable: number_of_entries = 2
        frame_type = 255 /* full_frame */
          offset_delta = 39
          locals = [ class scala/xml/PrefixedAttribute, class java/lang/String, class java/lang/String, class scala/collection/Seq, class scala/xml/MetaData ]
          stack = [ class scala/xml/PrefixedAttribute ]
        frame_type = 255 /* full_frame */
          offset_delta = 5
          locals = [ class scala/xml/PrefixedAttribute, class java/lang/String, class java/lang/String, class scala/collection/Seq, class scala/xml/MetaData ]
          stack = [ class scala/xml/PrefixedAttribute, class scala/xml/MetaData ]
      LineNumberTable:
        line 27: 0
        line 28: 5
        line 29: 10
        line 30: 15
        line 31: 21
        line 32: 29
        line 26: 48
      LocalVariableTable:
        Start  Length  Slot  Name   Signature
            0      49     0  this   Lscala/xml/PrefixedAttribute;
            0      49     1   pre   Ljava/lang/String;
            0      49     2   key   Ljava/lang/String;
            0      49     3 value   Lscala/collection/Seq;
            0      49     4 next1   Lscala/xml/MetaData;
    Signature: #145                         // (Ljava/lang/String;Ljava/lang/String;Lscala/collection/Seq<Lscala/xml/Node;>;Lscala/xml/MetaData;)V
    MethodParameters:
      Name                           Flags
      pre                            final
      key                            final
      value                          final
      next1                          final

  public scala.xml.PrefixedAttribute(java.lang.String, java.lang.String, java.lang.String, scala.xml.MetaData);
    descriptor: (Ljava/lang/String;Ljava/lang/String;Ljava/lang/String;Lscala/xml/MetaData;)V
    flags: (0x0001) ACC_PUBLIC
    Code:
      stack=5, locals=5, args_size=5
         0: aload_0
         1: aload_1
         2: aload_2
         3: aload_3
         4: ifnull        17
         7: getstatic     #160                // Field scala/xml/Text$.MODULE$:Lscala/xml/Text$;
        10: aload_3
        11: invokevirtual #163                // Method scala/xml/Text$.apply:(Ljava/lang/String;)Lscala/xml/Text;
        14: goto          18
        17: aconst_null
        18: aload         4
        20: invokespecial #105                // Method "<init>":(Ljava/lang/String;Ljava/lang/String;Lscala/collection/Seq;Lscala/xml/MetaData;)V
        23: return
      StackMapTable: number_of_entries = 2
        frame_type = 255 /* full_frame */
          offset_delta = 17
          locals = [ this, class java/lang/String, class java/lang/String, class java/lang/String, class scala/xml/MetaData ]
          stack = [ this, class java/lang/String, class java/lang/String ]
        frame_type = 255 /* full_frame */
          offset_delta = 0
          locals = [ this, class java/lang/String, class java/lang/String, class java/lang/String, class scala/xml/MetaData ]
          stack = [ this, class java/lang/String, class java/lang/String, class scala/xml/Text ]
      LineNumberTable:
        line 36: 0
      LocalVariableTable:
        Start  Length  Slot  Name   Signature
            0      24     0  this   Lscala/xml/PrefixedAttribute;
            0      24     1   pre   Ljava/lang/String;
            0      24     2   key   Ljava/lang/String;
            0      24     3 value   Ljava/lang/String;
            0      24     4  next   Lscala/xml/MetaData;
    MethodParameters:
      Name                           Flags
      pre                            final
      key                            final
      value                          final
      next                           final

  public scala.xml.PrefixedAttribute(java.lang.String, java.lang.String, scala.Option<scala.collection.Seq<scala.xml.Node>>, scala.xml.MetaData);
    descriptor: (Ljava/lang/String;Ljava/lang/String;Lscala/Option;Lscala/xml/MetaData;)V
    flags: (0x0001) ACC_PUBLIC
    Code:
      stack=5, locals=5, args_size=5
         0: aload_0
         1: aload_1
         2: aload_2
         3: aload_3
         4: getstatic     #172                // Field scala/$less$colon$less$.MODULE$:Lscala/$less$colon$less$;
         7: invokevirtual #176                // Method scala/$less$colon$less$.refl:()Lscala/$eq$colon$eq;
        10: invokevirtual #182                // Method scala/Option.orNull:(Lscala/$less$colon$less;)Ljava/lang/Object;
        13: checkcast     #140                // class scala/collection/Seq
        16: aload         4
        18: invokespecial #105                // Method "<init>":(Ljava/lang/String;Ljava/lang/String;Lscala/collection/Seq;Lscala/xml/MetaData;)V
        21: return
      LineNumberTable:
        line 40: 0
      LocalVariableTable:
        Start  Length  Slot  Name   Signature
            0      22     0  this   Lscala/xml/PrefixedAttribute;
            0      22     1   pre   Ljava/lang/String;
            0      22     2   key   Ljava/lang/String;
            0      22     3 value   Lscala/Option;
            0      22     4  next   Lscala/xml/MetaData;
    Signature: #167                         // (Ljava/lang/String;Ljava/lang/String;Lscala/Option<Lscala/collection/Seq<Lscala/xml/Node;>;>;Lscala/xml/MetaData;)V
    MethodParameters:
      Name                           Flags
      pre                            final
      key                            final
      value                          final
      next                           final
}
SourceFile: "PrefixedAttribute.scala"
RuntimeVisibleAnnotations:
  0: #8(#9=s#10)
    scala.reflect.ScalaSignature(
      bytes="\u0006\u0005\u0005}a\u0001B\f\u0019\u0001uA\u0001\"\n\u0001\u0003\u0006\u0004%\tA\n\u0005\te\u0001\u0011\t\u0011)A\u0005O!A1\u0007\u0001BC\u0002\u0013\u0005a\u0005\u0003\u00055\u0001\t\u0005\t\u0015!\u0003(\u0011!)\u0004A!b\u0001\n\u00031\u0004\u0002\u0003!\u0001\u0005\u0003\u0005\u000b\u0011B\u001c\t\u0011\u0005\u0003!Q1A\u0005\u0002\tC\u0001b\u0011\u0001\u0003\u0002\u0003\u0006IA\b\u0005\u0006\t\u0002!\t!\u0012\u0005\b\u0017\u0002\u0011\r\u0011\"\u0001C\u0011\u0019a\u0005\u0001)A\u0005=!)A\t\u0001C\u0001\u001b\")A\t\u0001C\u0001%\")1\f\u0001C\u00019\")a\f\u0001C\u0001?\")!\r\u0001C\u0001G\")!\r\u0001C\u0001K\u001e)a\u000e\u0007E\u0001_\u001a)q\u0003\u0007E\u0001a\")Ai\u0005C\u0001y\")Qp\u0005C\u0001}\"I\u0011qB\n\u0002\u0002\u0013%\u0011\u0011\u0003\u0002\u0012!J,g-\u001b=fI\u0006#HO]5ckR,\'BA\r\u001b\u0003\rAX\u000e\u001c\u0006\u00027\u0005)1oY1mC\u000e\u00011c\u0001\u0001\u001fEA\u0011q\u0004I\u0007\u00021%\u0011\u0011\u0005\u0007\u0002\t\u001b\u0016$\u0018\rR1uCB\u0011qdI\u0005\u0003Ia\u0011\u0011\"\u0011;ue&\u0014W\u000f^3\u0002\u0007A\u0014X-F\u0001(!\tAsF\u0004\u0002*[A\u0011!FG\u0007\u0002W)\u0011A\u0006H\u0001\u0007yI|w\u000e\u001e \n\u00059R\u0012A\u0002)sK\u0012,g-\u0003\u00021c\t11\u000b\u001e:j]\u001eT!A\f\u000e\u0002\tA\u0014X\rI\u0001\u0004W\u0016L\u0018\u0001B6fs\u0002\nQA^1mk\u0016,\u0012a\u000e\t\u0004qmjT\"A\u001d\u000b\u0005iR\u0012AC2pY2,7\r^5p]&\u0011A(\u000f\u0002\u0004\'\u0016\f\bCA\u0010?\u0013\ty\u0004D\u0001\u0003O_\u0012,\u0017A\u0002<bYV,\u0007%A\u0003oKb$\u0018\'F\u0001\u001f\u0003\u0019qW\r\u001f;2A\u00051A(\u001b8jiz\"RAR$I\u0013*\u0003\"a\b\u0001\t\u000b\u0015J\u0001\u0019A\u0014\t\u000bMJ\u0001\u0019A\u0014\t\u000bUJ\u0001\u0019A\u001c\t\u000b\u0005K\u0001\u0019\u0001\u0010\u0002\t9,\u0007\u0010^\u0001\u0006]\u0016DH\u000f\t\u000b\u0006\r:{\u0005+\u0015\u0005\u0006K1\u0001\ra\n\u0005\u0006g1\u0001\ra\n\u0005\u0006k1\u0001\ra\n\u0005\u0006\u00172\u0001\rA\b\u000b\u0006\rN#VK\u0017\u0005\u0006K5\u0001\ra\n\u0005\u0006g5\u0001\ra\n\u0005\u0006k5\u0001\rA\u0016\t\u0004/b;T\"\u0001\u000e\n\u0005eS\"AB(qi&|g\u000eC\u0003L\u001b\u0001\u0007a$\u0001\u0003d_BLHC\u0001$^\u0011\u0015Ye\u00021\u0001\u001f\u000319W\r\u001e(b[\u0016\u001c\b/Y2f)\t9\u0003\rC\u0003b\u001f\u0001\u0007Q(A\u0003po:,\'/A\u0003baBd\u0017\u0010\u0006\u00028I\")1\u0007\u0005a\u0001OQ!qG\u001a5n\u0011\u00159\u0017\u00031\u0001(\u0003%q\u0017-\\3ta\u0006\u001cW\rC\u0003j#\u0001\u0007!.A\u0003tG>\u0004X\r\u0005\u0002 W&\u0011A\u000e\u0007\u0002\u0011\u001d\u0006lWm\u001d9bG\u0016\u0014\u0015N\u001c3j]\u001eDQaM\tA\u0002\u001d\n\u0011\u0003\u0015:fM&DX\rZ!uiJL\'-\u001e;f!\ty2cE\u0002\u0014cR\u0004\"a\u0016:\n\u0005MT\"AB!osJ+g\r\u0005\u0002vu6\taO\u0003\u0002xq\u0006\u0011\u0011n\u001c\u0006\u0002s\u0006!!.\u0019<b\u0013\tYhO\u0001\u0007TKJL\u0017\r\\5{C\ndW\rF\u0001p\u0003\u001d)h.\u00199qYf$2a`A\u0006!\u00159\u0016\u0011AA\u0003\u0013\r\t\u0019A\u0007\u0002\u0005\'>lW\rE\u0004X\u0003\u000f9se\u000e\u0010\n\u0007\u0005%!D\u0001\u0004UkBdW\r\u000e\u0005\u0007\u0003\u001b)\u0002\u0019\u0001$\u0002\u0003a\fAb\u001e:ji\u0016\u0014V\r\u001d7bG\u0016$\"!a\u0005\u0011\t\u0005U\u00111D\u0007\u0003\u0003/Q1!!\u0007y\u0003\u0011a\u0017M\\4\n\t\u0005u\u0011q\u0003\u0002\u0007\u001f\nTWm\u0019;"
    )
  ScalaInlineInfo: length = 0x6D (unknown attribute)
   01 00 00 15 00 66 00 9B 00 00 66 00 A6 00 00 66
   00 67 00 00 73 00 74 00 00 73 00 7A 00 00 5E 00
   90 00 00 5E 00 8D 00 00 5E 00 5F 00 00 6A 00 6B
   00 00 2F 00 30 00 00 3B 00 3C 00 00 0D 00 50 00
   00 13 00 59 00 00 11 00 59 00 00 0B 00 50 00 00
   21 00 22 00 00 21 00 28 00 00 42 00 43 00 00 48
   00 49 00 00 0E 00 55 00 00 35 00 36 00
  ScalaSig: length = 0x3 (unknown attribute)
   05 02 00
