Classfile /Users/mw/Projects/slang-braindump/.jar/jar11/assemble/slang-braindump/assemble/content/scala/xml/QNode.class
  Last modified May 29, 2022; size 987 bytes
  SHA-256 checksum 03153e53da110e0c35641cc2b935263816e65a6d33d26396f0a677697137e15d
  Compiled from "QNode.scala"
public final class scala.xml.QNode
  minor version: 0
  major version: 52
  flags: (0x0031) ACC_PUBLIC, ACC_FINAL, ACC_SUPER
  this_class: #2                          // scala/xml/QNode
  super_class: #4                         // java/lang/Object
  interfaces: 0, fields: 0, methods: 1, attributes: 3
Constant pool:
   #1 = Utf8               scala/xml/QNode
   #2 = Class              #1             // scala/xml/QNode
   #3 = Utf8               java/lang/Object
   #4 = Class              #3             // java/lang/Object
   #5 = Utf8               QNode.scala
   #6 = Utf8               Lscala/reflect/ScalaSignature;
   #7 = Utf8               bytes
   #8 = Utf8               \u0006\u0005]:Q\u0001B\u0003\t\u0002)1Q\u0001D\u0003\t\u00025AQAE\u0001\u0005\u0002MAQ\u0001F\u0001\u0005\u0002U\tQ!\u0015(pI\u0016T!AB\u0004\u0002\u0007alGNC\u0001\t\u0003\u0015\u00198-\u00197b\u0007\u0001\u0001\"aC\u0001\u000e\u0003\u0015\u0011Q!\u0015(pI\u0016\u001c\"!\u0001\b\u0011\u0005=\u0001R\"A\u0004\n\u0005E9!AB!osJ+g-\u0001\u0004=S:LGO\u0010\u000b\u0002\u0015\u0005QQO\\1qa2L8+Z9\u0015\u0005Y)\u0004cA\b\u00183%\u0011\u0001d\u0002\u0002\u0005\'>lW\r\u0005\u0004\u00105qarEK\u0005\u00037\u001d\u0011a\u0001V;qY\u0016$\u0004CA\u000f%\u001d\tq\"\u0005\u0005\u0002 \u000f5\t\u0001E\u0003\u0002\"\u0013\u00051AH]8pizJ!aI\u0004\u0002\rA\u0013X\rZ3g\u0013\t)cE\u0001\u0004TiJLgn\u001a\u0006\u0003G\u001d\u0001\"a\u0003\u0015\n\u0005%*!\u0001C\'fi\u0006$\u0015\r^1\u0011\u0007-\u0002$\'D\u0001-\u0015\tic&A\u0005j[6,H/\u00192mK*\u0011qfB\u0001\u000bG>dG.Z2uS>t\u0017BA\u0019-\u0005\r\u0019V-\u001d\t\u0003\u0017MJ!\u0001N\u0003\u0003\t9{G-\u001a\u0005\u0006m\r\u0001\rAM\u0001\u0002]\u0002
   #9 = Utf8               unapplySeq
  #10 = Utf8               (Lscala/xml/Node;)Lscala/Some;
  #11 = Utf8               (Lscala/xml/Node;)Lscala/Some<Lscala/Tuple4<Ljava/lang/String;Ljava/lang/String;Lscala/xml/MetaData;Lscala/collection/immutable/Seq<Lscala/xml/Node;>;>;>;
  #12 = Utf8               n
  #13 = Utf8               scala/xml/QNode$
  #14 = Class              #13            // scala/xml/QNode$
  #15 = Utf8               MODULE$
  #16 = Utf8               Lscala/xml/QNode$;
  #17 = NameAndType        #15:#16        // MODULE$:Lscala/xml/QNode$;
  #18 = Fieldref           #14.#17        // scala/xml/QNode$.MODULE$:Lscala/xml/QNode$;
  #19 = NameAndType        #9:#10         // unapplySeq:(Lscala/xml/Node;)Lscala/Some;
  #20 = Methodref          #14.#19        // scala/xml/QNode$.unapplySeq:(Lscala/xml/Node;)Lscala/Some;
  #21 = Utf8               Lscala/xml/Node;
  #22 = Utf8               Code
  #23 = Utf8               LocalVariableTable
  #24 = Utf8               Signature
  #25 = Utf8               MethodParameters
  #26 = Utf8               SourceFile
  #27 = Utf8               RuntimeVisibleAnnotations
  #28 = Utf8               ScalaSig
{
  public static scala.Some<scala.Tuple4<java.lang.String, java.lang.String, scala.xml.MetaData, scala.collection.immutable.Seq<scala.xml.Node>>> unapplySeq(scala.xml.Node);
    descriptor: (Lscala/xml/Node;)Lscala/Some;
    flags: (0x0009) ACC_PUBLIC, ACC_STATIC
    Code:
      stack=2, locals=1, args_size=1
         0: getstatic     #18                 // Field scala/xml/QNode$.MODULE$:Lscala/xml/QNode$;
         3: aload_0
         4: invokevirtual #20                 // Method scala/xml/QNode$.unapplySeq:(Lscala/xml/Node;)Lscala/Some;
         7: areturn
      LocalVariableTable:
        Start  Length  Slot  Name   Signature
            0       8     0     n   Lscala/xml/Node;
    Signature: #11                          // (Lscala/xml/Node;)Lscala/Some<Lscala/Tuple4<Ljava/lang/String;Ljava/lang/String;Lscala/xml/MetaData;Lscala/collection/immutable/Seq<Lscala/xml/Node;>;>;>;
    MethodParameters:
      Name                           Flags
      n                              final
}
SourceFile: "QNode.scala"
RuntimeVisibleAnnotations:
  0: #6(#7=s#8)
    scala.reflect.ScalaSignature(
      bytes="\u0006\u0005]:Q\u0001B\u0003\t\u0002)1Q\u0001D\u0003\t\u00025AQAE\u0001\u0005\u0002MAQ\u0001F\u0001\u0005\u0002U\tQ!\u0015(pI\u0016T!AB\u0004\u0002\u0007alGNC\u0001\t\u0003\u0015\u00198-\u00197b\u0007\u0001\u0001\"aC\u0001\u000e\u0003\u0015\u0011Q!\u0015(pI\u0016\u001c\"!\u0001\b\u0011\u0005=\u0001R\"A\u0004\n\u0005E9!AB!osJ+g-\u0001\u0004=S:LGO\u0010\u000b\u0002\u0015\u0005QQO\\1qa2L8+Z9\u0015\u0005Y)\u0004cA\b\u00183%\u0011\u0001d\u0002\u0002\u0005\'>lW\r\u0005\u0004\u00105qarEK\u0005\u00037\u001d\u0011a\u0001V;qY\u0016$\u0004CA\u000f%\u001d\tq\"\u0005\u0005\u0002 \u000f5\t\u0001E\u0003\u0002\"\u0013\u00051AH]8pizJ!aI\u0004\u0002\rA\u0013X\rZ3g\u0013\t)cE\u0001\u0004TiJLgn\u001a\u0006\u0003G\u001d\u0001\"a\u0003\u0015\n\u0005%*!\u0001C\'fi\u0006$\u0015\r^1\u0011\u0007-\u0002$\'D\u0001-\u0015\tic&A\u0005j[6,H/\u00192mK*\u0011qfB\u0001\u000bG>dG.Z2uS>t\u0017BA\u0019-\u0005\r\u0019V-\u001d\t\u0003\u0017MJ!\u0001N\u0003\u0003\t9{G-\u001a\u0005\u0006m\r\u0001\rAM\u0001\u0002]\u0002"
    )
  ScalaSig: length = 0x3 (unknown attribute)
   05 02 00
