Classfile /Users/mw/Projects/slang-braindump/.jar/jar11/assemble/slang-braindump/assemble/content/scala/xml/ScalaVersionSpecificNodeSeq.class
  Last modified May 29, 2022; size 7575 bytes
  SHA-256 checksum 7e52cb6fccb9b6c640476d7b2925b7b042a24fa717dbdc5916f9914e6bbde04e
  Compiled from "ScalaVersionSpecific.scala"
public interface scala.xml.ScalaVersionSpecificNodeSeq extends scala.collection.immutable.StrictOptimizedSeqOps<scala.xml.Node, scala.collection.immutable.Seq, scala.xml.NodeSeq>
  minor version: 0
  major version: 52
  flags: (0x0601) ACC_PUBLIC, ACC_INTERFACE, ACC_ABSTRACT
  this_class: #2                          // scala/xml/ScalaVersionSpecificNodeSeq
  super_class: #5                         // java/lang/Object
  interfaces: 1, fields: 0, methods: 26, attributes: 7
Constant pool:
    #1 = Utf8               scala/xml/ScalaVersionSpecificNodeSeq
    #2 = Class              #1            // scala/xml/ScalaVersionSpecificNodeSeq
    #3 = Utf8               Ljava/lang/Object;Lscala/collection/immutable/StrictOptimizedSeqOps<Lscala/xml/Node;Lscala/collection/immutable/Seq;Lscala/xml/NodeSeq;>;
    #4 = Utf8               java/lang/Object
    #5 = Class              #4            // java/lang/Object
    #6 = Utf8               scala/collection/immutable/StrictOptimizedSeqOps
    #7 = Class              #6            // scala/collection/immutable/StrictOptimizedSeqOps
    #8 = Utf8               ScalaVersionSpecific.scala
    #9 = Utf8               Lscala/reflect/ScalaSignature;
   #10 = Utf8               bytes
   #11 = Utf8               \u0006\u0005M4\u0011\"\u0004\b\u0011\u0002\u0007\u0005aBE\u0014\t\u000b5\u0002A\u0011A\u0018\t\u000bM\u0002A\u0011\t\u001b\t\u000bi\u0002A\u0011I\u001e\t\u000b\t\u0003A\u0011I\"\t\u000b\u0011\u0003A\u0011A#\t\u000b!\u0003AQA%\t\u000bi\u0003A\u0011A.\t\u000by\u0003A\u0011A0\t\u000b\u0005\u0004A\u0011\u00012\t\u000b\u0011\u0004A\u0011A3\t\u000b!\u0004A\u0011A5\t\u000b=\u0004A\u0011\u00019\u00037M\u001b\u0017\r\\1WKJ\u001c\u0018n\u001c8Ta\u0016\u001c\u0017NZ5d\u001d>$WmU3r\u0015\ty\u0001#A\u0002y[2T\u0011!E\u0001\u0006g\u000e\fG.Y\n\u0005\u0001M9\"\u0006\u0005\u0002\u0015+5\t\u0001#\u0003\u0002\u0017!\t1\u0011I\\=SK\u001a\u0004R\u0001G\u000e\u001eC\u001dj\u0011!\u0007\u0006\u00035A\t!bY8mY\u0016\u001cG/[8o\u0013\ta\u0012D\u0001\u0004TKF|\u0005o\u001d\t\u0003=}i\u0011AD\u0005\u0003A9\u0011AAT8eKB\u0011!%J\u0007\u0002G)\u0011A%G\u0001\nS6lW\u000f^1cY\u0016L!AJ\u0012\u0003\u0007M+\u0017\u000f\u0005\u0002\u001fQ%\u0011\u0011F\u0004\u0002\b\u001d>$WmU3r!\u0015\u00113&H\u0011(\u0013\ta3EA\u000bTiJL7\r^(qi&l\u0017N_3e\'\u0016\fx\n]:\u0002\r\u0011Jg.\u001b;%\u0007\u0001!\u0012\u0001\r\t\u0003)EJ!A\r\t\u0003\tUs\u0017\u000e^\u0001\rMJ|Wn\u00159fG&4\u0017n\u0019\u000b\u0003OUBQA\u000e\u0002A\u0002]\nAaY8mYB\u0019\u0001\u0004O\u000f\n\u0005eJ\"\u0001D%uKJ\f\'\r\\3P]\u000e,\u0017A\u00058foN\u0003XmY5gS\u000e\u0014U/\u001b7eKJ,\u0012\u0001\u0010\t\u0005{\u0001kr%D\u0001?\u0015\ty\u0014$A\u0004nkR\f\'\r\\3\n\u0005\u0005s$a\u0002\"vS2$WM]\u0001\u0006K6\u0004H/_\u000b\u0002O\u000511m\u001c8dCR$\"a\n$\t\u000b\u001d+\u0001\u0019A\u001c\u0002\rM,hMZ5y\u0003)!\u0003\u000f\\;tIAdWo\u001d\u000b\u0003O)CQa\u0012\u0004A\u0002-\u00032\u0001\u0014+\u001e\u001d\ti%K\u0004\u0002O#6\tqJ\u0003\u0002Q]\u00051AH]8pizJ\u0011!E\u0005\u0003\'B\tq\u0001]1dW\u0006<W-\u0003\u0002\'+*\u00111\u000b\u0005\u0015\u0003\r]\u0003\"\u0001\u0006-\n\u0005e\u0003\"AB5oY&tW-\u0001\u0005baB,g\u000eZ3e)\t9C\fC\u0003^\u000f\u0001\u0007Q$\u0001\u0003cCN,\u0017aC1qa\u0016tG-\u001a3BY2$\"a\n1\t\u000b\u001dC\u0001\u0019A\u001c\u0002\u0013A\u0014X\r]3oI\u0016$GCA\u0014d\u0011\u0015i\u0016\u00021\u0001\u001e\u00031\u0001(/\u001a9f]\u0012,G-\u00117m)\t9c\rC\u0003h\u0015\u0001\u0007q\'\u0001\u0004qe\u00164\u0017\u000e_\u0001\u0004[\u0006\u0004HCA\u0014k\u0011\u0015Y7\u00021\u0001m\u0003\u00051\u0007\u0003\u0002\u000bn;uI!A\u001c\t\u0003\u0013\u0019+hn\u0019;j_:\f\u0014a\u00024mCRl\u0015\r\u001d\u000b\u0003OEDQa\u001b\u0007A\u0002I\u0004B\u0001F7\u001eo\u0001
   #12 = Utf8               java/lang/invoke/MethodHandles$Lookup
   #13 = Class              #12           // java/lang/invoke/MethodHandles$Lookup
   #14 = Utf8               java/lang/invoke/MethodHandles
   #15 = Class              #14           // java/lang/invoke/MethodHandles
   #16 = Utf8               Lookup
   #17 = Utf8               scala/collection/View$Appended
   #18 = Class              #17           // scala/collection/View$Appended
   #19 = Utf8               scala/collection/View
   #20 = Class              #19           // scala/collection/View
   #21 = Utf8               Appended
   #22 = Utf8               scala/collection/View$FlatMap
   #23 = Class              #22           // scala/collection/View$FlatMap
   #24 = Utf8               FlatMap
   #25 = Utf8               scala/collection/View$Map
   #26 = Class              #25           // scala/collection/View$Map
   #27 = Utf8               Map
   #28 = Utf8               scala/collection/View$Prepended
   #29 = Class              #28           // scala/collection/View$Prepended
   #30 = Utf8               Prepended
   #31 = Utf8               fromSpecific$
   #32 = Utf8               (Lscala/xml/ScalaVersionSpecificNodeSeq;Lscala/collection/IterableOnce;)Lscala/xml/NodeSeq;
   #33 = Utf8               $this
   #34 = Utf8               coll
   #35 = Utf8               fromSpecific
   #36 = Utf8               (Lscala/collection/IterableOnce;)Lscala/xml/NodeSeq;
   #37 = NameAndType        #35:#36       // fromSpecific:(Lscala/collection/IterableOnce;)Lscala/xml/NodeSeq;
   #38 = InterfaceMethodref #2.#37        // scala/xml/ScalaVersionSpecificNodeSeq.fromSpecific:(Lscala/collection/IterableOnce;)Lscala/xml/NodeSeq;
   #39 = Utf8               Lscala/xml/ScalaVersionSpecificNodeSeq;
   #40 = Utf8               Lscala/collection/IterableOnce;
   #41 = Utf8               (Lscala/collection/IterableOnce<Lscala/xml/Node;>;)Lscala/xml/NodeSeq;
   #42 = Utf8               scala/xml/NodeSeq$
   #43 = Class              #42           // scala/xml/NodeSeq$
   #44 = Utf8               MODULE$
   #45 = Utf8               Lscala/xml/NodeSeq$;
   #46 = NameAndType        #44:#45       // MODULE$:Lscala/xml/NodeSeq$;
   #47 = Fieldref           #43.#46       // scala/xml/NodeSeq$.MODULE$:Lscala/xml/NodeSeq$;
   #48 = Utf8               newBuilder
   #49 = Utf8               ()Lscala/collection/mutable/Builder;
   #50 = NameAndType        #48:#49       // newBuilder:()Lscala/collection/mutable/Builder;
   #51 = Methodref          #43.#50       // scala/xml/NodeSeq$.newBuilder:()Lscala/collection/mutable/Builder;
   #52 = Utf8               scala/collection/mutable/Builder
   #53 = Class              #52           // scala/collection/mutable/Builder
   #54 = Utf8               $plus$plus$eq
   #55 = Utf8               (Lscala/collection/IterableOnce;)Lscala/collection/mutable/Growable;
   #56 = NameAndType        #54:#55       // $plus$plus$eq:(Lscala/collection/IterableOnce;)Lscala/collection/mutable/Growable;
   #57 = InterfaceMethodref #53.#56       // scala/collection/mutable/Builder.$plus$plus$eq:(Lscala/collection/IterableOnce;)Lscala/collection/mutable/Growable;
   #58 = Utf8               result
   #59 = Utf8               ()Ljava/lang/Object;
   #60 = NameAndType        #58:#59       // result:()Ljava/lang/Object;
   #61 = InterfaceMethodref #53.#60       // scala/collection/mutable/Builder.result:()Ljava/lang/Object;
   #62 = Utf8               scala/xml/NodeSeq
   #63 = Class              #62           // scala/xml/NodeSeq
   #64 = Utf8               this
   #65 = Utf8               newSpecificBuilder$
   #66 = Utf8               (Lscala/xml/ScalaVersionSpecificNodeSeq;)Lscala/collection/mutable/Builder;
   #67 = Utf8               newSpecificBuilder
   #68 = NameAndType        #67:#49       // newSpecificBuilder:()Lscala/collection/mutable/Builder;
   #69 = InterfaceMethodref #2.#68        // scala/xml/ScalaVersionSpecificNodeSeq.newSpecificBuilder:()Lscala/collection/mutable/Builder;
   #70 = Utf8               ()Lscala/collection/mutable/Builder<Lscala/xml/Node;Lscala/xml/NodeSeq;>;
   #71 = Utf8               empty$
   #72 = Utf8               (Lscala/xml/ScalaVersionSpecificNodeSeq;)Lscala/xml/NodeSeq;
   #73 = Utf8               empty
   #74 = Utf8               ()Lscala/xml/NodeSeq;
   #75 = NameAndType        #73:#74       // empty:()Lscala/xml/NodeSeq;
   #76 = InterfaceMethodref #2.#75        // scala/xml/ScalaVersionSpecificNodeSeq.empty:()Lscala/xml/NodeSeq;
   #77 = Utf8               Empty
   #78 = NameAndType        #77:#74       // Empty:()Lscala/xml/NodeSeq;
   #79 = Methodref          #43.#78       // scala/xml/NodeSeq$.Empty:()Lscala/xml/NodeSeq;
   #80 = Utf8               concat$
   #81 = Utf8               suffix
   #82 = Utf8               concat
   #83 = NameAndType        #82:#36       // concat:(Lscala/collection/IterableOnce;)Lscala/xml/NodeSeq;
   #84 = InterfaceMethodref #2.#83        // scala/xml/ScalaVersionSpecificNodeSeq.concat:(Lscala/collection/IterableOnce;)Lscala/xml/NodeSeq;
   #85 = Utf8               iterator
   #86 = Utf8               ()Lscala/collection/Iterator;
   #87 = NameAndType        #85:#86       // iterator:()Lscala/collection/Iterator;
   #88 = Methodref          #63.#87       // scala/xml/NodeSeq.iterator:()Lscala/collection/Iterator;
   #89 = MethodType         #59           //  ()Ljava/lang/Object;
   #90 = Utf8               $anonfun$concat$1
   #91 = Utf8               (Lscala/collection/IterableOnce;)Lscala/collection/Iterator;
   #92 = NameAndType        #90:#91       // $anonfun$concat$1:(Lscala/collection/IterableOnce;)Lscala/collection/Iterator;
   #93 = InterfaceMethodref #2.#92        // scala/xml/ScalaVersionSpecificNodeSeq.$anonfun$concat$1:(Lscala/collection/IterableOnce;)Lscala/collection/Iterator;
   #94 = MethodHandle       6:#93         // REF_invokeStatic scala/xml/ScalaVersionSpecificNodeSeq.$anonfun$concat$1:(Lscala/collection/IterableOnce;)Lscala/collection/Iterator;
   #95 = MethodType         #86           //  ()Lscala/collection/Iterator;
   #96 = Integer            5
   #97 = Integer            1
   #98 = Utf8               java/lang/invoke/LambdaMetafactory
   #99 = Class              #98           // java/lang/invoke/LambdaMetafactory
  #100 = Utf8               altMetafactory
  #101 = Utf8               (Ljava/lang/invoke/MethodHandles$Lookup;Ljava/lang/String;Ljava/lang/invoke/MethodType;[Ljava/lang/Object;)Ljava/lang/invoke/CallSite;
  #102 = NameAndType        #100:#101     // altMetafactory:(Ljava/lang/invoke/MethodHandles$Lookup;Ljava/lang/String;Ljava/lang/invoke/MethodType;[Ljava/lang/Object;)Ljava/lang/invoke/CallSite;
  #103 = Methodref          #99.#102      // java/lang/invoke/LambdaMetafactory.altMetafactory:(Ljava/lang/invoke/MethodHandles$Lookup;Ljava/lang/String;Ljava/lang/invoke/MethodType;[Ljava/lang/Object;)Ljava/lang/invoke/CallSite;
  #104 = MethodHandle       6:#103        // REF_invokeStatic java/lang/invoke/LambdaMetafactory.altMetafactory:(Ljava/lang/invoke/MethodHandles$Lookup;Ljava/lang/String;Ljava/lang/invoke/MethodType;[Ljava/lang/Object;)Ljava/lang/invoke/CallSite;
  #105 = Utf8               apply
  #106 = Utf8               (Lscala/collection/IterableOnce;)Lscala/Function0;
  #107 = NameAndType        #105:#106     // apply:(Lscala/collection/IterableOnce;)Lscala/Function0;
  #108 = InvokeDynamic      #0:#107       // #0:apply:(Lscala/collection/IterableOnce;)Lscala/Function0;
  #109 = Utf8               scala/collection/Iterator
  #110 = Class              #109          // scala/collection/Iterator
  #111 = Utf8               $plus$plus
  #112 = Utf8               (Lscala/Function0;)Lscala/collection/Iterator;
  #113 = NameAndType        #111:#112     // $plus$plus:(Lscala/Function0;)Lscala/collection/Iterator;
  #114 = InterfaceMethodref #110.#113     // scala/collection/Iterator.$plus$plus:(Lscala/Function0;)Lscala/collection/Iterator;
  #115 = Utf8               $plus$plus$
  #116 = Utf8               (Lscala/xml/ScalaVersionSpecificNodeSeq;Lscala/collection/immutable/Seq;)Lscala/xml/NodeSeq;
  #117 = Utf8               (Lscala/collection/immutable/Seq;)Lscala/xml/NodeSeq;
  #118 = NameAndType        #111:#117     // $plus$plus:(Lscala/collection/immutable/Seq;)Lscala/xml/NodeSeq;
  #119 = InterfaceMethodref #2.#118       // scala/xml/ScalaVersionSpecificNodeSeq.$plus$plus:(Lscala/collection/immutable/Seq;)Lscala/xml/NodeSeq;
  #120 = Utf8               Lscala/collection/immutable/Seq;
  #121 = Utf8               (Lscala/collection/immutable/Seq<Lscala/xml/Node;>;)Lscala/xml/NodeSeq;
  #122 = Utf8               appended$
  #123 = Utf8               (Lscala/xml/ScalaVersionSpecificNodeSeq;Lscala/xml/Node;)Lscala/xml/NodeSeq;
  #124 = Utf8               base
  #125 = Utf8               appended
  #126 = Utf8               (Lscala/xml/Node;)Lscala/xml/NodeSeq;
  #127 = NameAndType        #125:#126     // appended:(Lscala/xml/Node;)Lscala/xml/NodeSeq;
  #128 = InterfaceMethodref #2.#127       // scala/xml/ScalaVersionSpecificNodeSeq.appended:(Lscala/xml/Node;)Lscala/xml/NodeSeq;
  #129 = Utf8               Lscala/xml/Node;
  #130 = Utf8               <init>
  #131 = Utf8               (Lscala/collection/IterableOps;Ljava/lang/Object;)V
  #132 = NameAndType        #130:#131     // "<init>":(Lscala/collection/IterableOps;Ljava/lang/Object;)V
  #133 = Methodref          #18.#132      // scala/collection/View$Appended."<init>":(Lscala/collection/IterableOps;Ljava/lang/Object;)V
  #134 = Utf8               appendedAll$
  #135 = Utf8               appendedAll
  #136 = NameAndType        #135:#36      // appendedAll:(Lscala/collection/IterableOnce;)Lscala/xml/NodeSeq;
  #137 = InterfaceMethodref #2.#136       // scala/xml/ScalaVersionSpecificNodeSeq.appendedAll:(Lscala/collection/IterableOnce;)Lscala/xml/NodeSeq;
  #138 = Utf8               prepended$
  #139 = Utf8               prepended
  #140 = NameAndType        #139:#126     // prepended:(Lscala/xml/Node;)Lscala/xml/NodeSeq;
  #141 = InterfaceMethodref #2.#140       // scala/xml/ScalaVersionSpecificNodeSeq.prepended:(Lscala/xml/Node;)Lscala/xml/NodeSeq;
  #142 = Utf8               (Ljava/lang/Object;Lscala/collection/IterableOps;)V
  #143 = NameAndType        #130:#142     // "<init>":(Ljava/lang/Object;Lscala/collection/IterableOps;)V
  #144 = Methodref          #29.#143      // scala/collection/View$Prepended."<init>":(Ljava/lang/Object;Lscala/collection/IterableOps;)V
  #145 = Utf8               prependedAll$
  #146 = Utf8               prefix
  #147 = Utf8               prependedAll
  #148 = NameAndType        #147:#36      // prependedAll:(Lscala/collection/IterableOnce;)Lscala/xml/NodeSeq;
  #149 = InterfaceMethodref #2.#148       // scala/xml/ScalaVersionSpecificNodeSeq.prependedAll:(Lscala/collection/IterableOnce;)Lscala/xml/NodeSeq;
  #150 = Utf8               scala/collection/IterableOnce
  #151 = Class              #150          // scala/collection/IterableOnce
  #152 = InterfaceMethodref #151.#87      // scala/collection/IterableOnce.iterator:()Lscala/collection/Iterator;
  #153 = Utf8               $anonfun$prependedAll$1
  #154 = Utf8               (Lscala/xml/ScalaVersionSpecificNodeSeq;)Lscala/collection/Iterator;
  #155 = NameAndType        #153:#154     // $anonfun$prependedAll$1:(Lscala/xml/ScalaVersionSpecificNodeSeq;)Lscala/collection/Iterator;
  #156 = InterfaceMethodref #2.#155       // scala/xml/ScalaVersionSpecificNodeSeq.$anonfun$prependedAll$1:(Lscala/xml/ScalaVersionSpecificNodeSeq;)Lscala/collection/Iterator;
  #157 = MethodHandle       6:#156        // REF_invokeStatic scala/xml/ScalaVersionSpecificNodeSeq.$anonfun$prependedAll$1:(Lscala/xml/ScalaVersionSpecificNodeSeq;)Lscala/collection/Iterator;
  #158 = Utf8               (Lscala/xml/ScalaVersionSpecificNodeSeq;)Lscala/Function0;
  #159 = NameAndType        #105:#158     // apply:(Lscala/xml/ScalaVersionSpecificNodeSeq;)Lscala/Function0;
  #160 = InvokeDynamic      #1:#159       // #1:apply:(Lscala/xml/ScalaVersionSpecificNodeSeq;)Lscala/Function0;
  #161 = Utf8               map$
  #162 = Utf8               (Lscala/xml/ScalaVersionSpecificNodeSeq;Lscala/Function1;)Lscala/xml/NodeSeq;
  #163 = Utf8               f
  #164 = Utf8               map
  #165 = Utf8               (Lscala/Function1;)Lscala/xml/NodeSeq;
  #166 = NameAndType        #164:#165     // map:(Lscala/Function1;)Lscala/xml/NodeSeq;
  #167 = InterfaceMethodref #2.#166       // scala/xml/ScalaVersionSpecificNodeSeq.map:(Lscala/Function1;)Lscala/xml/NodeSeq;
  #168 = Utf8               Lscala/Function1;
  #169 = Utf8               (Lscala/Function1<Lscala/xml/Node;Lscala/xml/Node;>;)Lscala/xml/NodeSeq;
  #170 = Utf8               (Lscala/collection/IterableOps;Lscala/Function1;)V
  #171 = NameAndType        #130:#170     // "<init>":(Lscala/collection/IterableOps;Lscala/Function1;)V
  #172 = Methodref          #26.#171      // scala/collection/View$Map."<init>":(Lscala/collection/IterableOps;Lscala/Function1;)V
  #173 = Utf8               flatMap$
  #174 = Utf8               flatMap
  #175 = NameAndType        #174:#165     // flatMap:(Lscala/Function1;)Lscala/xml/NodeSeq;
  #176 = InterfaceMethodref #2.#175       // scala/xml/ScalaVersionSpecificNodeSeq.flatMap:(Lscala/Function1;)Lscala/xml/NodeSeq;
  #177 = Utf8               (Lscala/Function1<Lscala/xml/Node;Lscala/collection/IterableOnce<Lscala/xml/Node;>;>;)Lscala/xml/NodeSeq;
  #178 = Methodref          #23.#171      // scala/collection/View$FlatMap."<init>":(Lscala/collection/IterableOps;Lscala/Function1;)V
  #179 = Utf8               suffix$1
  #180 = Utf8               $init$
  #181 = Utf8               (Lscala/xml/ScalaVersionSpecificNodeSeq;)V
  #182 = Utf8               $deserializeLambda$
  #183 = Utf8               (Ljava/lang/invoke/SerializedLambda;)Ljava/lang/Object;
  #184 = Utf8               scala/runtime/LambdaDeserialize
  #185 = Class              #184          // scala/runtime/LambdaDeserialize
  #186 = Utf8               bootstrap
  #187 = Utf8               (Ljava/lang/invoke/MethodHandles$Lookup;Ljava/lang/String;Ljava/lang/invoke/MethodType;[Ljava/lang/invoke/MethodHandle;)Ljava/lang/invoke/CallSite;
  #188 = NameAndType        #186:#187     // bootstrap:(Ljava/lang/invoke/MethodHandles$Lookup;Ljava/lang/String;Ljava/lang/invoke/MethodType;[Ljava/lang/invoke/MethodHandle;)Ljava/lang/invoke/CallSite;
  #189 = Methodref          #185.#188     // scala/runtime/LambdaDeserialize.bootstrap:(Ljava/lang/invoke/MethodHandles$Lookup;Ljava/lang/String;Ljava/lang/invoke/MethodType;[Ljava/lang/invoke/MethodHandle;)Ljava/lang/invoke/CallSite;
  #190 = MethodHandle       6:#189        // REF_invokeStatic scala/runtime/LambdaDeserialize.bootstrap:(Ljava/lang/invoke/MethodHandles$Lookup;Ljava/lang/String;Ljava/lang/invoke/MethodType;[Ljava/lang/invoke/MethodHandle;)Ljava/lang/invoke/CallSite;
  #191 = Utf8               lambdaDeserialize
  #192 = NameAndType        #191:#183     // lambdaDeserialize:(Ljava/lang/invoke/SerializedLambda;)Ljava/lang/Object;
  #193 = InvokeDynamic      #2:#192       // #2:lambdaDeserialize:(Ljava/lang/invoke/SerializedLambda;)Ljava/lang/Object;
  #194 = Utf8               Code
  #195 = Utf8               LineNumberTable
  #196 = Utf8               LocalVariableTable
  #197 = Utf8               MethodParameters
  #198 = Utf8               Signature
  #199 = Utf8               InnerClasses
  #200 = Utf8               SourceFile
  #201 = Utf8               RuntimeVisibleAnnotations
  #202 = Utf8               BootstrapMethods
  #203 = Utf8               ScalaInlineInfo
  #204 = Utf8               ScalaSig
{
  public static scala.xml.NodeSeq fromSpecific$(scala.xml.ScalaVersionSpecificNodeSeq, scala.collection.IterableOnce);
    descriptor: (Lscala/xml/ScalaVersionSpecificNodeSeq;Lscala/collection/IterableOnce;)Lscala/xml/NodeSeq;
    flags: (0x1009) ACC_PUBLIC, ACC_STATIC, ACC_SYNTHETIC
    Code:
      stack=2, locals=2, args_size=2
         0: aload_0
         1: aload_1
         2: invokespecial #38                 // InterfaceMethod fromSpecific:(Lscala/collection/IterableOnce;)Lscala/xml/NodeSeq;
         5: areturn
      LineNumberTable:
        line 32: 0
      LocalVariableTable:
        Start  Length  Slot  Name   Signature
            0       6     0 $this   Lscala/xml/ScalaVersionSpecificNodeSeq;
            0       6     1  coll   Lscala/collection/IterableOnce;
    MethodParameters:
      Name                           Flags
      $this                          final synthetic
      coll                           final

  public default scala.xml.NodeSeq fromSpecific(scala.collection.IterableOnce<scala.xml.Node>);
    descriptor: (Lscala/collection/IterableOnce;)Lscala/xml/NodeSeq;
    flags: (0x0001) ACC_PUBLIC
    Code:
      stack=2, locals=2, args_size=2
         0: getstatic     #47                 // Field scala/xml/NodeSeq$.MODULE$:Lscala/xml/NodeSeq$;
         3: invokevirtual #51                 // Method scala/xml/NodeSeq$.newBuilder:()Lscala/collection/mutable/Builder;
         6: aload_1
         7: invokeinterface #57,  2           // InterfaceMethod scala/collection/mutable/Builder.$plus$plus$eq:(Lscala/collection/IterableOnce;)Lscala/collection/mutable/Growable;
        12: checkcast     #53                 // class scala/collection/mutable/Builder
        15: invokeinterface #61,  1           // InterfaceMethod scala/collection/mutable/Builder.result:()Ljava/lang/Object;
        20: checkcast     #63                 // class scala/xml/NodeSeq
        23: areturn
      LineNumberTable:
        line 32: 0
      LocalVariableTable:
        Start  Length  Slot  Name   Signature
            0      24     0  this   Lscala/xml/ScalaVersionSpecificNodeSeq;
            0      24     1  coll   Lscala/collection/IterableOnce;
    Signature: #41                          // (Lscala/collection/IterableOnce<Lscala/xml/Node;>;)Lscala/xml/NodeSeq;
    MethodParameters:
      Name                           Flags
      coll                           final

  public static scala.collection.mutable.Builder newSpecificBuilder$(scala.xml.ScalaVersionSpecificNodeSeq);
    descriptor: (Lscala/xml/ScalaVersionSpecificNodeSeq;)Lscala/collection/mutable/Builder;
    flags: (0x1009) ACC_PUBLIC, ACC_STATIC, ACC_SYNTHETIC
    Code:
      stack=1, locals=1, args_size=1
         0: aload_0
         1: invokespecial #69                 // InterfaceMethod newSpecificBuilder:()Lscala/collection/mutable/Builder;
         4: areturn
      LineNumberTable:
        line 33: 0
      LocalVariableTable:
        Start  Length  Slot  Name   Signature
            0       5     0 $this   Lscala/xml/ScalaVersionSpecificNodeSeq;
    MethodParameters:
      Name                           Flags
      $this                          final synthetic

  public default scala.collection.mutable.Builder<scala.xml.Node, scala.xml.NodeSeq> newSpecificBuilder();
    descriptor: ()Lscala/collection/mutable/Builder;
    flags: (0x0001) ACC_PUBLIC
    Code:
      stack=1, locals=1, args_size=1
         0: getstatic     #47                 // Field scala/xml/NodeSeq$.MODULE$:Lscala/xml/NodeSeq$;
         3: invokevirtual #51                 // Method scala/xml/NodeSeq$.newBuilder:()Lscala/collection/mutable/Builder;
         6: areturn
      LineNumberTable:
        line 33: 0
      LocalVariableTable:
        Start  Length  Slot  Name   Signature
            0       7     0  this   Lscala/xml/ScalaVersionSpecificNodeSeq;
    Signature: #70                          // ()Lscala/collection/mutable/Builder<Lscala/xml/Node;Lscala/xml/NodeSeq;>;

  public static scala.xml.NodeSeq empty$(scala.xml.ScalaVersionSpecificNodeSeq);
    descriptor: (Lscala/xml/ScalaVersionSpecificNodeSeq;)Lscala/xml/NodeSeq;
    flags: (0x1009) ACC_PUBLIC, ACC_STATIC, ACC_SYNTHETIC
    Code:
      stack=1, locals=1, args_size=1
         0: aload_0
         1: invokespecial #76                 // InterfaceMethod empty:()Lscala/xml/NodeSeq;
         4: areturn
      LineNumberTable:
        line 34: 0
      LocalVariableTable:
        Start  Length  Slot  Name   Signature
            0       5     0 $this   Lscala/xml/ScalaVersionSpecificNodeSeq;
    MethodParameters:
      Name                           Flags
      $this                          final synthetic

  public default scala.xml.NodeSeq empty();
    descriptor: ()Lscala/xml/NodeSeq;
    flags: (0x0001) ACC_PUBLIC
    Code:
      stack=1, locals=1, args_size=1
         0: getstatic     #47                 // Field scala/xml/NodeSeq$.MODULE$:Lscala/xml/NodeSeq$;
         3: invokevirtual #79                 // Method scala/xml/NodeSeq$.Empty:()Lscala/xml/NodeSeq;
         6: areturn
      LineNumberTable:
        line 34: 0
      LocalVariableTable:
        Start  Length  Slot  Name   Signature
            0       7     0  this   Lscala/xml/ScalaVersionSpecificNodeSeq;

  public static scala.xml.NodeSeq concat$(scala.xml.ScalaVersionSpecificNodeSeq, scala.collection.IterableOnce);
    descriptor: (Lscala/xml/ScalaVersionSpecificNodeSeq;Lscala/collection/IterableOnce;)Lscala/xml/NodeSeq;
    flags: (0x1009) ACC_PUBLIC, ACC_STATIC, ACC_SYNTHETIC
    Code:
      stack=2, locals=2, args_size=2
         0: aload_0
         1: aload_1
         2: invokespecial #84                 // InterfaceMethod concat:(Lscala/collection/IterableOnce;)Lscala/xml/NodeSeq;
         5: areturn
      LineNumberTable:
        line 35: 0
      LocalVariableTable:
        Start  Length  Slot  Name   Signature
            0       6     0 $this   Lscala/xml/ScalaVersionSpecificNodeSeq;
            0       6     1 suffix   Lscala/collection/IterableOnce;
    MethodParameters:
      Name                           Flags
      $this                          final synthetic
      suffix                         final

  public default scala.xml.NodeSeq concat(scala.collection.IterableOnce<scala.xml.Node>);
    descriptor: (Lscala/collection/IterableOnce;)Lscala/xml/NodeSeq;
    flags: (0x0001) ACC_PUBLIC
    Code:
      stack=3, locals=2, args_size=2
         0: aload_0
         1: aload_0
         2: checkcast     #63                 // class scala/xml/NodeSeq
         5: invokevirtual #88                 // Method scala/xml/NodeSeq.iterator:()Lscala/collection/Iterator;
         8: aload_1
         9: invokedynamic #108,  0            // InvokeDynamic #0:apply:(Lscala/collection/IterableOnce;)Lscala/Function0;
        14: invokeinterface #114,  2          // InterfaceMethod scala/collection/Iterator.$plus$plus:(Lscala/Function0;)Lscala/collection/Iterator;
        19: invokeinterface #38,  2           // InterfaceMethod fromSpecific:(Lscala/collection/IterableOnce;)Lscala/xml/NodeSeq;
        24: areturn
      LineNumberTable:
        line 36: 0
      LocalVariableTable:
        Start  Length  Slot  Name   Signature
            0      25     0  this   Lscala/xml/ScalaVersionSpecificNodeSeq;
            0      25     1 suffix   Lscala/collection/IterableOnce;
    Signature: #41                          // (Lscala/collection/IterableOnce<Lscala/xml/Node;>;)Lscala/xml/NodeSeq;
    MethodParameters:
      Name                           Flags
      suffix                         final

  public static scala.xml.NodeSeq $plus$plus$(scala.xml.ScalaVersionSpecificNodeSeq, scala.collection.immutable.Seq);
    descriptor: (Lscala/xml/ScalaVersionSpecificNodeSeq;Lscala/collection/immutable/Seq;)Lscala/xml/NodeSeq;
    flags: (0x1009) ACC_PUBLIC, ACC_STATIC, ACC_SYNTHETIC
    Code:
      stack=2, locals=2, args_size=2
         0: aload_0
         1: aload_1
         2: invokespecial #119                // InterfaceMethod $plus$plus:(Lscala/collection/immutable/Seq;)Lscala/xml/NodeSeq;
         5: areturn
      LineNumberTable:
        line 37: 0
      LocalVariableTable:
        Start  Length  Slot  Name   Signature
            0       6     0 $this   Lscala/xml/ScalaVersionSpecificNodeSeq;
            0       6     1 suffix   Lscala/collection/immutable/Seq;
    MethodParameters:
      Name                           Flags
      $this                          final synthetic
      suffix                         final

  public default scala.xml.NodeSeq $plus$plus(scala.collection.immutable.Seq<scala.xml.Node>);
    descriptor: (Lscala/collection/immutable/Seq;)Lscala/xml/NodeSeq;
    flags: (0x0001) ACC_PUBLIC
    Code:
      stack=2, locals=2, args_size=2
         0: aload_0
         1: aload_1
         2: invokeinterface #84,  2           // InterfaceMethod concat:(Lscala/collection/IterableOnce;)Lscala/xml/NodeSeq;
         7: areturn
      LineNumberTable:
        line 37: 0
      LocalVariableTable:
        Start  Length  Slot  Name   Signature
            0       8     0  this   Lscala/xml/ScalaVersionSpecificNodeSeq;
            0       8     1 suffix   Lscala/collection/immutable/Seq;
    Signature: #121                         // (Lscala/collection/immutable/Seq<Lscala/xml/Node;>;)Lscala/xml/NodeSeq;
    MethodParameters:
      Name                           Flags
      suffix                         final

  public static scala.xml.NodeSeq appended$(scala.xml.ScalaVersionSpecificNodeSeq, scala.xml.Node);
    descriptor: (Lscala/xml/ScalaVersionSpecificNodeSeq;Lscala/xml/Node;)Lscala/xml/NodeSeq;
    flags: (0x1009) ACC_PUBLIC, ACC_STATIC, ACC_SYNTHETIC
    Code:
      stack=2, locals=2, args_size=2
         0: aload_0
         1: aload_1
         2: invokespecial #128                // InterfaceMethod appended:(Lscala/xml/Node;)Lscala/xml/NodeSeq;
         5: areturn
      LineNumberTable:
        line 38: 0
      LocalVariableTable:
        Start  Length  Slot  Name   Signature
            0       6     0 $this   Lscala/xml/ScalaVersionSpecificNodeSeq;
            0       6     1  base   Lscala/xml/Node;
    MethodParameters:
      Name                           Flags
      $this                          final synthetic
      base                           final

  public default scala.xml.NodeSeq appended(scala.xml.Node);
    descriptor: (Lscala/xml/Node;)Lscala/xml/NodeSeq;
    flags: (0x0001) ACC_PUBLIC
    Code:
      stack=5, locals=2, args_size=2
         0: aload_0
         1: new           #18                 // class scala/collection/View$Appended
         4: dup
         5: aload_0
         6: aload_1
         7: invokespecial #133                // Method scala/collection/View$Appended."<init>":(Lscala/collection/IterableOps;Ljava/lang/Object;)V
        10: invokeinterface #38,  2           // InterfaceMethod fromSpecific:(Lscala/collection/IterableOnce;)Lscala/xml/NodeSeq;
        15: areturn
      LineNumberTable:
        line 39: 0
      LocalVariableTable:
        Start  Length  Slot  Name   Signature
            0      16     0  this   Lscala/xml/ScalaVersionSpecificNodeSeq;
            0      16     1  base   Lscala/xml/Node;
    MethodParameters:
      Name                           Flags
      base                           final

  public static scala.xml.NodeSeq appendedAll$(scala.xml.ScalaVersionSpecificNodeSeq, scala.collection.IterableOnce);
    descriptor: (Lscala/xml/ScalaVersionSpecificNodeSeq;Lscala/collection/IterableOnce;)Lscala/xml/NodeSeq;
    flags: (0x1009) ACC_PUBLIC, ACC_STATIC, ACC_SYNTHETIC
    Code:
      stack=2, locals=2, args_size=2
         0: aload_0
         1: aload_1
         2: invokespecial #137                // InterfaceMethod appendedAll:(Lscala/collection/IterableOnce;)Lscala/xml/NodeSeq;
         5: areturn
      LineNumberTable:
        line 40: 0
      LocalVariableTable:
        Start  Length  Slot  Name   Signature
            0       6     0 $this   Lscala/xml/ScalaVersionSpecificNodeSeq;
            0       6     1 suffix   Lscala/collection/IterableOnce;
    MethodParameters:
      Name                           Flags
      $this                          final synthetic
      suffix                         final

  public default scala.xml.NodeSeq appendedAll(scala.collection.IterableOnce<scala.xml.Node>);
    descriptor: (Lscala/collection/IterableOnce;)Lscala/xml/NodeSeq;
    flags: (0x0001) ACC_PUBLIC
    Code:
      stack=2, locals=2, args_size=2
         0: aload_0
         1: aload_1
         2: invokeinterface #84,  2           // InterfaceMethod concat:(Lscala/collection/IterableOnce;)Lscala/xml/NodeSeq;
         7: areturn
      LineNumberTable:
        line 41: 0
      LocalVariableTable:
        Start  Length  Slot  Name   Signature
            0       8     0  this   Lscala/xml/ScalaVersionSpecificNodeSeq;
            0       8     1 suffix   Lscala/collection/IterableOnce;
    Signature: #41                          // (Lscala/collection/IterableOnce<Lscala/xml/Node;>;)Lscala/xml/NodeSeq;
    MethodParameters:
      Name                           Flags
      suffix                         final

  public static scala.xml.NodeSeq prepended$(scala.xml.ScalaVersionSpecificNodeSeq, scala.xml.Node);
    descriptor: (Lscala/xml/ScalaVersionSpecificNodeSeq;Lscala/xml/Node;)Lscala/xml/NodeSeq;
    flags: (0x1009) ACC_PUBLIC, ACC_STATIC, ACC_SYNTHETIC
    Code:
      stack=2, locals=2, args_size=2
         0: aload_0
         1: aload_1
         2: invokespecial #141                // InterfaceMethod prepended:(Lscala/xml/Node;)Lscala/xml/NodeSeq;
         5: areturn
      LineNumberTable:
        line 42: 0
      LocalVariableTable:
        Start  Length  Slot  Name   Signature
            0       6     0 $this   Lscala/xml/ScalaVersionSpecificNodeSeq;
            0       6     1  base   Lscala/xml/Node;
    MethodParameters:
      Name                           Flags
      $this                          final synthetic
      base                           final

  public default scala.xml.NodeSeq prepended(scala.xml.Node);
    descriptor: (Lscala/xml/Node;)Lscala/xml/NodeSeq;
    flags: (0x0001) ACC_PUBLIC
    Code:
      stack=5, locals=2, args_size=2
         0: aload_0
         1: new           #29                 // class scala/collection/View$Prepended
         4: dup
         5: aload_1
         6: aload_0
         7: invokespecial #144                // Method scala/collection/View$Prepended."<init>":(Ljava/lang/Object;Lscala/collection/IterableOps;)V
        10: invokeinterface #38,  2           // InterfaceMethod fromSpecific:(Lscala/collection/IterableOnce;)Lscala/xml/NodeSeq;
        15: areturn
      LineNumberTable:
        line 43: 0
      LocalVariableTable:
        Start  Length  Slot  Name   Signature
            0      16     0  this   Lscala/xml/ScalaVersionSpecificNodeSeq;
            0      16     1  base   Lscala/xml/Node;
    MethodParameters:
      Name                           Flags
      base                           final

  public static scala.xml.NodeSeq prependedAll$(scala.xml.ScalaVersionSpecificNodeSeq, scala.collection.IterableOnce);
    descriptor: (Lscala/xml/ScalaVersionSpecificNodeSeq;Lscala/collection/IterableOnce;)Lscala/xml/NodeSeq;
    flags: (0x1009) ACC_PUBLIC, ACC_STATIC, ACC_SYNTHETIC
    Code:
      stack=2, locals=2, args_size=2
         0: aload_0
         1: aload_1
         2: invokespecial #149                // InterfaceMethod prependedAll:(Lscala/collection/IterableOnce;)Lscala/xml/NodeSeq;
         5: areturn
      LineNumberTable:
        line 44: 0
      LocalVariableTable:
        Start  Length  Slot  Name   Signature
            0       6     0 $this   Lscala/xml/ScalaVersionSpecificNodeSeq;
            0       6     1 prefix   Lscala/collection/IterableOnce;
    MethodParameters:
      Name                           Flags
      $this                          final synthetic
      prefix                         final

  public default scala.xml.NodeSeq prependedAll(scala.collection.IterableOnce<scala.xml.Node>);
    descriptor: (Lscala/collection/IterableOnce;)Lscala/xml/NodeSeq;
    flags: (0x0001) ACC_PUBLIC
    Code:
      stack=3, locals=2, args_size=2
         0: aload_0
         1: aload_1
         2: invokeinterface #152,  1          // InterfaceMethod scala/collection/IterableOnce.iterator:()Lscala/collection/Iterator;
         7: aload_0
         8: invokedynamic #160,  0            // InvokeDynamic #1:apply:(Lscala/xml/ScalaVersionSpecificNodeSeq;)Lscala/Function0;
        13: invokeinterface #114,  2          // InterfaceMethod scala/collection/Iterator.$plus$plus:(Lscala/Function0;)Lscala/collection/Iterator;
        18: invokeinterface #38,  2           // InterfaceMethod fromSpecific:(Lscala/collection/IterableOnce;)Lscala/xml/NodeSeq;
        23: areturn
      LineNumberTable:
        line 45: 0
      LocalVariableTable:
        Start  Length  Slot  Name   Signature
            0      24     0  this   Lscala/xml/ScalaVersionSpecificNodeSeq;
            0      24     1 prefix   Lscala/collection/IterableOnce;
    Signature: #41                          // (Lscala/collection/IterableOnce<Lscala/xml/Node;>;)Lscala/xml/NodeSeq;
    MethodParameters:
      Name                           Flags
      prefix                         final

  public static scala.xml.NodeSeq map$(scala.xml.ScalaVersionSpecificNodeSeq, scala.Function1);
    descriptor: (Lscala/xml/ScalaVersionSpecificNodeSeq;Lscala/Function1;)Lscala/xml/NodeSeq;
    flags: (0x1009) ACC_PUBLIC, ACC_STATIC, ACC_SYNTHETIC
    Code:
      stack=2, locals=2, args_size=2
         0: aload_0
         1: aload_1
         2: invokespecial #167                // InterfaceMethod map:(Lscala/Function1;)Lscala/xml/NodeSeq;
         5: areturn
      LineNumberTable:
        line 46: 0
      LocalVariableTable:
        Start  Length  Slot  Name   Signature
            0       6     0 $this   Lscala/xml/ScalaVersionSpecificNodeSeq;
            0       6     1     f   Lscala/Function1;
    MethodParameters:
      Name                           Flags
      $this                          final synthetic
      f                              final

  public default scala.xml.NodeSeq map(scala.Function1<scala.xml.Node, scala.xml.Node>);
    descriptor: (Lscala/Function1;)Lscala/xml/NodeSeq;
    flags: (0x0001) ACC_PUBLIC
    Code:
      stack=5, locals=2, args_size=2
         0: aload_0
         1: new           #26                 // class scala/collection/View$Map
         4: dup
         5: aload_0
         6: aload_1
         7: invokespecial #172                // Method scala/collection/View$Map."<init>":(Lscala/collection/IterableOps;Lscala/Function1;)V
        10: invokeinterface #38,  2           // InterfaceMethod fromSpecific:(Lscala/collection/IterableOnce;)Lscala/xml/NodeSeq;
        15: areturn
      LineNumberTable:
        line 47: 0
      LocalVariableTable:
        Start  Length  Slot  Name   Signature
            0      16     0  this   Lscala/xml/ScalaVersionSpecificNodeSeq;
            0      16     1     f   Lscala/Function1;
    Signature: #169                         // (Lscala/Function1<Lscala/xml/Node;Lscala/xml/Node;>;)Lscala/xml/NodeSeq;
    MethodParameters:
      Name                           Flags
      f                              final

  public static scala.xml.NodeSeq flatMap$(scala.xml.ScalaVersionSpecificNodeSeq, scala.Function1);
    descriptor: (Lscala/xml/ScalaVersionSpecificNodeSeq;Lscala/Function1;)Lscala/xml/NodeSeq;
    flags: (0x1009) ACC_PUBLIC, ACC_STATIC, ACC_SYNTHETIC
    Code:
      stack=2, locals=2, args_size=2
         0: aload_0
         1: aload_1
         2: invokespecial #176                // InterfaceMethod flatMap:(Lscala/Function1;)Lscala/xml/NodeSeq;
         5: areturn
      LineNumberTable:
        line 48: 0
      LocalVariableTable:
        Start  Length  Slot  Name   Signature
            0       6     0 $this   Lscala/xml/ScalaVersionSpecificNodeSeq;
            0       6     1     f   Lscala/Function1;
    MethodParameters:
      Name                           Flags
      $this                          final synthetic
      f                              final

  public default scala.xml.NodeSeq flatMap(scala.Function1<scala.xml.Node, scala.collection.IterableOnce<scala.xml.Node>>);
    descriptor: (Lscala/Function1;)Lscala/xml/NodeSeq;
    flags: (0x0001) ACC_PUBLIC
    Code:
      stack=5, locals=2, args_size=2
         0: aload_0
         1: new           #23                 // class scala/collection/View$FlatMap
         4: dup
         5: aload_0
         6: aload_1
         7: invokespecial #178                // Method scala/collection/View$FlatMap."<init>":(Lscala/collection/IterableOps;Lscala/Function1;)V
        10: invokeinterface #38,  2           // InterfaceMethod fromSpecific:(Lscala/collection/IterableOnce;)Lscala/xml/NodeSeq;
        15: areturn
      LineNumberTable:
        line 49: 0
      LocalVariableTable:
        Start  Length  Slot  Name   Signature
            0      16     0  this   Lscala/xml/ScalaVersionSpecificNodeSeq;
            0      16     1     f   Lscala/Function1;
    Signature: #177                         // (Lscala/Function1<Lscala/xml/Node;Lscala/collection/IterableOnce<Lscala/xml/Node;>;>;)Lscala/xml/NodeSeq;
    MethodParameters:
      Name                           Flags
      f                              final

  public static scala.collection.Iterator $anonfun$concat$1(scala.collection.IterableOnce);
    descriptor: (Lscala/collection/IterableOnce;)Lscala/collection/Iterator;
    flags: (0x1009) ACC_PUBLIC, ACC_STATIC, ACC_SYNTHETIC
    Code:
      stack=1, locals=1, args_size=1
         0: aload_0
         1: invokeinterface #152,  1          // InterfaceMethod scala/collection/IterableOnce.iterator:()Lscala/collection/Iterator;
         6: areturn
      LineNumberTable:
        line 36: 0
      LocalVariableTable:
        Start  Length  Slot  Name   Signature
            0       7     0 suffix$1   Lscala/collection/IterableOnce;
    MethodParameters:
      Name                           Flags
      suffix$1                       final

  public static scala.collection.Iterator $anonfun$prependedAll$1(scala.xml.ScalaVersionSpecificNodeSeq);
    descriptor: (Lscala/xml/ScalaVersionSpecificNodeSeq;)Lscala/collection/Iterator;
    flags: (0x1009) ACC_PUBLIC, ACC_STATIC, ACC_SYNTHETIC
    Code:
      stack=1, locals=1, args_size=1
         0: aload_0
         1: checkcast     #63                 // class scala/xml/NodeSeq
         4: invokevirtual #88                 // Method scala/xml/NodeSeq.iterator:()Lscala/collection/Iterator;
         7: areturn
      LineNumberTable:
        line 45: 0
      LocalVariableTable:
        Start  Length  Slot  Name   Signature
            0       8     0 $this   Lscala/xml/ScalaVersionSpecificNodeSeq;
    MethodParameters:
      Name                           Flags
      $this                          final synthetic

  public static void $init$(scala.xml.ScalaVersionSpecificNodeSeq);
    descriptor: (Lscala/xml/ScalaVersionSpecificNodeSeq;)V
    flags: (0x0009) ACC_PUBLIC, ACC_STATIC
    Code:
      stack=0, locals=1, args_size=1
         0: return
      LineNumberTable:
        line 30: 0
      LocalVariableTable:
        Start  Length  Slot  Name   Signature
            0       1     0 $this   Lscala/xml/ScalaVersionSpecificNodeSeq;
    MethodParameters:
      Name                           Flags
      $this                          final synthetic

  private static java.lang.Object $deserializeLambda$(java.lang.invoke.SerializedLambda);
    descriptor: (Ljava/lang/invoke/SerializedLambda;)Ljava/lang/Object;
    flags: (0x100a) ACC_PRIVATE, ACC_STATIC, ACC_SYNTHETIC
    Code:
      stack=1, locals=1, args_size=1
         0: aload_0
         1: invokedynamic #193,  0            // InvokeDynamic #2:lambdaDeserialize:(Ljava/lang/invoke/SerializedLambda;)Ljava/lang/Object;
         6: areturn
}
InnerClasses:
  public static final #16= #13 of #15;    // Lookup=class java/lang/invoke/MethodHandles$Lookup of class java/lang/invoke/MethodHandles
  public static #21= #18 of #20;          // Appended=class scala/collection/View$Appended of class scala/collection/View
  public static #24= #23 of #20;          // FlatMap=class scala/collection/View$FlatMap of class scala/collection/View
  public static #27= #26 of #20;          // Map=class scala/collection/View$Map of class scala/collection/View
  public static #30= #29 of #20;          // Prepended=class scala/collection/View$Prepended of class scala/collection/View
Signature: #3                           // Ljava/lang/Object;Lscala/collection/immutable/StrictOptimizedSeqOps<Lscala/xml/Node;Lscala/collection/immutable/Seq;Lscala/xml/NodeSeq;>;
SourceFile: "ScalaVersionSpecific.scala"
RuntimeVisibleAnnotations:
  0: #9(#10=s#11)
    scala.reflect.ScalaSignature(
      bytes="\u0006\u0005M4\u0011\"\u0004\b\u0011\u0002\u0007\u0005aBE\u0014\t\u000b5\u0002A\u0011A\u0018\t\u000bM\u0002A\u0011\t\u001b\t\u000bi\u0002A\u0011I\u001e\t\u000b\t\u0003A\u0011I\"\t\u000b\u0011\u0003A\u0011A#\t\u000b!\u0003AQA%\t\u000bi\u0003A\u0011A.\t\u000by\u0003A\u0011A0\t\u000b\u0005\u0004A\u0011\u00012\t\u000b\u0011\u0004A\u0011A3\t\u000b!\u0004A\u0011A5\t\u000b=\u0004A\u0011\u00019\u00037M\u001b\u0017\r\\1WKJ\u001c\u0018n\u001c8Ta\u0016\u001c\u0017NZ5d\u001d>$WmU3r\u0015\ty\u0001#A\u0002y[2T\u0011!E\u0001\u0006g\u000e\fG.Y\n\u0005\u0001M9\"\u0006\u0005\u0002\u0015+5\t\u0001#\u0003\u0002\u0017!\t1\u0011I\\=SK\u001a\u0004R\u0001G\u000e\u001eC\u001dj\u0011!\u0007\u0006\u00035A\t!bY8mY\u0016\u001cG/[8o\u0013\ta\u0012D\u0001\u0004TKF|\u0005o\u001d\t\u0003=}i\u0011AD\u0005\u0003A9\u0011AAT8eKB\u0011!%J\u0007\u0002G)\u0011A%G\u0001\nS6lW\u000f^1cY\u0016L!AJ\u0012\u0003\u0007M+\u0017\u000f\u0005\u0002\u001fQ%\u0011\u0011F\u0004\u0002\b\u001d>$WmU3r!\u0015\u00113&H\u0011(\u0013\ta3EA\u000bTiJL7\r^(qi&l\u0017N_3e\'\u0016\fx\n]:\u0002\r\u0011Jg.\u001b;%\u0007\u0001!\u0012\u0001\r\t\u0003)EJ!A\r\t\u0003\tUs\u0017\u000e^\u0001\rMJ|Wn\u00159fG&4\u0017n\u0019\u000b\u0003OUBQA\u000e\u0002A\u0002]\nAaY8mYB\u0019\u0001\u0004O\u000f\n\u0005eJ\"\u0001D%uKJ\f\'\r\\3P]\u000e,\u0017A\u00058foN\u0003XmY5gS\u000e\u0014U/\u001b7eKJ,\u0012\u0001\u0010\t\u0005{\u0001kr%D\u0001?\u0015\ty\u0014$A\u0004nkR\f\'\r\\3\n\u0005\u0005s$a\u0002\"vS2$WM]\u0001\u0006K6\u0004H/_\u000b\u0002O\u000511m\u001c8dCR$\"a\n$\t\u000b\u001d+\u0001\u0019A\u001c\u0002\rM,hMZ5y\u0003)!\u0003\u000f\\;tIAdWo\u001d\u000b\u0003O)CQa\u0012\u0004A\u0002-\u00032\u0001\u0014+\u001e\u001d\ti%K\u0004\u0002O#6\tqJ\u0003\u0002Q]\u00051AH]8pizJ\u0011!E\u0005\u0003\'B\tq\u0001]1dW\u0006<W-\u0003\u0002\'+*\u00111\u000b\u0005\u0015\u0003\r]\u0003\"\u0001\u0006-\n\u0005e\u0003\"AB5oY&tW-\u0001\u0005baB,g\u000eZ3e)\t9C\fC\u0003^\u000f\u0001\u0007Q$\u0001\u0003cCN,\u0017aC1qa\u0016tG-\u001a3BY2$\"a\n1\t\u000b\u001dC\u0001\u0019A\u001c\u0002\u0013A\u0014X\r]3oI\u0016$GCA\u0014d\u0011\u0015i\u0016\u00021\u0001\u001e\u00031\u0001(/\u001a9f]\u0012,G-\u00117m)\t9c\rC\u0003h\u0015\u0001\u0007q\'\u0001\u0004qe\u00164\u0017\u000e_\u0001\u0004[\u0006\u0004HCA\u0014k\u0011\u0015Y7\u00021\u0001m\u0003\u00051\u0007\u0003\u0002\u000bn;uI!A\u001c\t\u0003\u0013\u0019+hn\u0019;j_:\f\u0014a\u00024mCRl\u0015\r\u001d\u000b\u0003OEDQa\u001b\u0007A\u0002I\u0004B\u0001F7\u001eo\u0001"
    )
BootstrapMethods:
  0: #104 REF_invokeStatic java/lang/invoke/LambdaMetafactory.altMetafactory:(Ljava/lang/invoke/MethodHandles$Lookup;Ljava/lang/String;Ljava/lang/invoke/MethodType;[Ljava/lang/Object;)Ljava/lang/invoke/CallSite;
    Method arguments:
      #89 ()Ljava/lang/Object;
      #94 REF_invokeStatic scala/xml/ScalaVersionSpecificNodeSeq.$anonfun$concat$1:(Lscala/collection/IterableOnce;)Lscala/collection/Iterator;
      #95 ()Lscala/collection/Iterator;
      #96 5
      #97 1
      #95 ()Lscala/collection/Iterator;
  1: #104 REF_invokeStatic java/lang/invoke/LambdaMetafactory.altMetafactory:(Ljava/lang/invoke/MethodHandles$Lookup;Ljava/lang/String;Ljava/lang/invoke/MethodType;[Ljava/lang/Object;)Ljava/lang/invoke/CallSite;
    Method arguments:
      #89 ()Ljava/lang/Object;
      #157 REF_invokeStatic scala/xml/ScalaVersionSpecificNodeSeq.$anonfun$prependedAll$1:(Lscala/xml/ScalaVersionSpecificNodeSeq;)Lscala/collection/Iterator;
      #95 ()Lscala/collection/Iterator;
      #96 5
      #97 1
      #95 ()Lscala/collection/Iterator;
  2: #190 REF_invokeStatic scala/runtime/LambdaDeserialize.bootstrap:(Ljava/lang/invoke/MethodHandles$Lookup;Ljava/lang/String;Ljava/lang/invoke/MethodType;[Ljava/lang/invoke/MethodHandle;)Ljava/lang/invoke/CallSite;
    Method arguments:
      #94 REF_invokeStatic scala/xml/ScalaVersionSpecificNodeSeq.$anonfun$concat$1:(Lscala/collection/IterableOnce;)Lscala/collection/Iterator;
      #157 REF_invokeStatic scala/xml/ScalaVersionSpecificNodeSeq.$anonfun$prependedAll$1:(Lscala/xml/ScalaVersionSpecificNodeSeq;)Lscala/collection/Iterator;
  ScalaInlineInfo: length = 0x81 (unknown attribute)
   01 00 00 19 00 5A 00 5B 01 00 99 00 9A 01 00 B4
   00 B5 01 00 6F 00 75 05 00 73 00 74 05 00 7D 00
   7E 00 00 7A 00 7B 01 00 87 00 24 00 00 86 00 20
   01 00 52 00 24 00 00 50 00 20 01 00 49 00 4A 00
   00 47 00 48 01 00 AE 00 A5 00 00 AD 00 A2 01 00
   23 00 24 00 00 1F 00 20 01 00 A4 00 A5 00 00 A1
   00 A2 01 00 43 00 31 00 00 41 00 42 01 00 8B 00
   7E 00 00 8A 00 7B 01 00 93 00 24 00 00 91 00 20
   01
  ScalaSig: length = 0x3 (unknown attribute)
   05 02 00
