Classfile /Users/mw/Projects/slang-braindump/.jar/jar11/assemble/slang-braindump/assemble/content/scala/xml/Source.class
  Last modified May 29, 2022; size 1905 bytes
  SHA-256 checksum 4f45330c20c5bfb4a4073a0b2c4a9dfdad299f3fa582863de397cebbc790ad62
  Compiled from "XML.scala"
public final class scala.xml.Source
  minor version: 0
  major version: 52
  flags: (0x0031) ACC_PUBLIC, ACC_FINAL, ACC_SUPER
  this_class: #2                          // scala/xml/Source
  super_class: #4                         // java/lang/Object
  interfaces: 0, fields: 0, methods: 7, attributes: 3
Constant pool:
   #1 = Utf8               scala/xml/Source
   #2 = Class              #1             // scala/xml/Source
   #3 = Utf8               java/lang/Object
   #4 = Class              #3             // java/lang/Object
   #5 = Utf8               XML.scala
   #6 = Utf8               Lscala/reflect/ScalaSignature;
   #7 = Utf8               bytes
   #8 = Utf8               \u0006\u0005e;QAC\u0006\t\u0002A1QAE\u0006\t\u0002MAQ\u0001G\u0001\u0005\u0002eAQAG\u0001\u0005\u0002mAQAG\u0001\u0005\u0002=BQAG\u0001\u0005\u0002UBQaQ\u0001\u0005\u0002\u0011CQAS\u0001\u0005\u0002-CQ!U\u0001\u0005\u0002ICQ!V\u0001\u0005\u0002Y\u000baaU8ve\u000e,\'B\u0001\u0007\u000e\u0003\rAX\u000e\u001c\u0006\u0002\u001d\u0005)1oY1mC\u000e\u0001\u0001CA\t\u0002\u001b\u0005Y!AB*pkJ\u001cWm\u0005\u0002\u0002)A\u0011QCF\u0007\u0002\u001b%\u0011q#\u0004\u0002\u0007\u0003:L(+\u001a4\u0002\rqJg.\u001b;?)\u0005\u0001\u0012\u0001\u00034s_64\u0015\u000e\\3\u0015\u0005q)\u0003CA\u000f$\u001b\u0005q\"BA\u0010!\u0003\r\u0019\u0018\r\u001f\u0006\u0003\u0019\u0005R\u0011AI\u0001\u0004_J<\u0017B\u0001\u0013\u001f\u0005-Ie\u000e];u\'>,(oY3\t\u000b\u0019\u001a\u0001\u0019A\u0014\u0002\t\u0019LG.\u001a\t\u0003Q5j\u0011!\u000b\u0006\u0003U-\n!![8\u000b\u00031\nAA[1wC&\u0011a&\u000b\u0002\u0005\r&dW\r\u0006\u0002\u001da!)\u0011\u0007\u0002a\u0001e\u0005\u0011a\r\u001a\t\u0003QMJ!\u0001N\u0015\u0003\u001d\u0019KG.\u001a#fg\u000e\u0014\u0018\u000e\u001d;peR\u0011AD\u000e\u0005\u0006o\u0015\u0001\r\u0001O\u0001\u0005]\u0006lW\r\u0005\u0002:\u0001:\u0011!H\u0010\t\u0003w5i\u0011\u0001\u0010\u0006\u0003{=\ta\u0001\u0010:p_Rt\u0014BA \u000e\u0003\u0019\u0001&/\u001a3fM&\u0011\u0011I\u0011\u0002\u0007\'R\u0014\u0018N\\4\u000b\u0005}j\u0011a\u00044s_6Le\u000e];u\'R\u0014X-Y7\u0015\u0005q)\u0005\"\u0002$\u0007\u0001\u00049\u0015AA5t!\tA\u0003*\u0003\u0002JS\tY\u0011J\u001c9viN#(/Z1n\u0003)1\'o\\7SK\u0006$WM\u001d\u000b\u000391CQ!T\u0004A\u00029\u000baA]3bI\u0016\u0014\bC\u0001\u0015P\u0013\t\u0001\u0016F\u0001\u0004SK\u0006$WM]\u0001\nMJ|WnU=t\u0013\u0012$\"\u0001H*\t\u000bQC\u0001\u0019\u0001\u001d\u0002\u000bML8/\u0013#\u0002\u0015\u0019\u0014x.\\*ue&tw\r\u0006\u0002\u001d/\")\u0001,\u0003a\u0001q\u000511\u000f\u001e:j]\u001e\u0004
   #9 = Utf8               fromString
  #10 = Utf8               (Ljava/lang/String;)Lorg/xml/sax/InputSource;
  #11 = Utf8               string
  #12 = Utf8               scala/xml/Source$
  #13 = Class              #12            // scala/xml/Source$
  #14 = Utf8               MODULE$
  #15 = Utf8               Lscala/xml/Source$;
  #16 = NameAndType        #14:#15        // MODULE$:Lscala/xml/Source$;
  #17 = Fieldref           #13.#16        // scala/xml/Source$.MODULE$:Lscala/xml/Source$;
  #18 = NameAndType        #9:#10         // fromString:(Ljava/lang/String;)Lorg/xml/sax/InputSource;
  #19 = Methodref          #13.#18        // scala/xml/Source$.fromString:(Ljava/lang/String;)Lorg/xml/sax/InputSource;
  #20 = Utf8               Ljava/lang/String;
  #21 = Utf8               fromSysId
  #22 = Utf8               sysID
  #23 = NameAndType        #21:#10        // fromSysId:(Ljava/lang/String;)Lorg/xml/sax/InputSource;
  #24 = Methodref          #13.#23        // scala/xml/Source$.fromSysId:(Ljava/lang/String;)Lorg/xml/sax/InputSource;
  #25 = Utf8               fromReader
  #26 = Utf8               (Ljava/io/Reader;)Lorg/xml/sax/InputSource;
  #27 = Utf8               reader
  #28 = NameAndType        #25:#26        // fromReader:(Ljava/io/Reader;)Lorg/xml/sax/InputSource;
  #29 = Methodref          #13.#28        // scala/xml/Source$.fromReader:(Ljava/io/Reader;)Lorg/xml/sax/InputSource;
  #30 = Utf8               Ljava/io/Reader;
  #31 = Utf8               fromInputStream
  #32 = Utf8               (Ljava/io/InputStream;)Lorg/xml/sax/InputSource;
  #33 = Utf8               is
  #34 = NameAndType        #31:#32        // fromInputStream:(Ljava/io/InputStream;)Lorg/xml/sax/InputSource;
  #35 = Methodref          #13.#34        // scala/xml/Source$.fromInputStream:(Ljava/io/InputStream;)Lorg/xml/sax/InputSource;
  #36 = Utf8               Ljava/io/InputStream;
  #37 = Utf8               fromFile
  #38 = Utf8               name
  #39 = NameAndType        #37:#10        // fromFile:(Ljava/lang/String;)Lorg/xml/sax/InputSource;
  #40 = Methodref          #13.#39        // scala/xml/Source$.fromFile:(Ljava/lang/String;)Lorg/xml/sax/InputSource;
  #41 = Utf8               (Ljava/io/FileDescriptor;)Lorg/xml/sax/InputSource;
  #42 = Utf8               fd
  #43 = NameAndType        #37:#41        // fromFile:(Ljava/io/FileDescriptor;)Lorg/xml/sax/InputSource;
  #44 = Methodref          #13.#43        // scala/xml/Source$.fromFile:(Ljava/io/FileDescriptor;)Lorg/xml/sax/InputSource;
  #45 = Utf8               Ljava/io/FileDescriptor;
  #46 = Utf8               (Ljava/io/File;)Lorg/xml/sax/InputSource;
  #47 = Utf8               file
  #48 = NameAndType        #37:#46        // fromFile:(Ljava/io/File;)Lorg/xml/sax/InputSource;
  #49 = Methodref          #13.#48        // scala/xml/Source$.fromFile:(Ljava/io/File;)Lorg/xml/sax/InputSource;
  #50 = Utf8               Ljava/io/File;
  #51 = Utf8               Code
  #52 = Utf8               LocalVariableTable
  #53 = Utf8               MethodParameters
  #54 = Utf8               SourceFile
  #55 = Utf8               RuntimeVisibleAnnotations
  #56 = Utf8               ScalaSig
{
  public static org.xml.sax.InputSource fromString(java.lang.String);
    descriptor: (Ljava/lang/String;)Lorg/xml/sax/InputSource;
    flags: (0x0009) ACC_PUBLIC, ACC_STATIC
    Code:
      stack=2, locals=1, args_size=1
         0: getstatic     #17                 // Field scala/xml/Source$.MODULE$:Lscala/xml/Source$;
         3: aload_0
         4: invokevirtual #19                 // Method scala/xml/Source$.fromString:(Ljava/lang/String;)Lorg/xml/sax/InputSource;
         7: areturn
      LocalVariableTable:
        Start  Length  Slot  Name   Signature
            0       8     0 string   Ljava/lang/String;
    MethodParameters:
      Name                           Flags
      string                         final

  public static org.xml.sax.InputSource fromSysId(java.lang.String);
    descriptor: (Ljava/lang/String;)Lorg/xml/sax/InputSource;
    flags: (0x0009) ACC_PUBLIC, ACC_STATIC
    Code:
      stack=2, locals=1, args_size=1
         0: getstatic     #17                 // Field scala/xml/Source$.MODULE$:Lscala/xml/Source$;
         3: aload_0
         4: invokevirtual #24                 // Method scala/xml/Source$.fromSysId:(Ljava/lang/String;)Lorg/xml/sax/InputSource;
         7: areturn
      LocalVariableTable:
        Start  Length  Slot  Name   Signature
            0       8     0 sysID   Ljava/lang/String;
    MethodParameters:
      Name                           Flags
      sysID                          final

  public static org.xml.sax.InputSource fromReader(java.io.Reader);
    descriptor: (Ljava/io/Reader;)Lorg/xml/sax/InputSource;
    flags: (0x0009) ACC_PUBLIC, ACC_STATIC
    Code:
      stack=2, locals=1, args_size=1
         0: getstatic     #17                 // Field scala/xml/Source$.MODULE$:Lscala/xml/Source$;
         3: aload_0
         4: invokevirtual #29                 // Method scala/xml/Source$.fromReader:(Ljava/io/Reader;)Lorg/xml/sax/InputSource;
         7: areturn
      LocalVariableTable:
        Start  Length  Slot  Name   Signature
            0       8     0 reader   Ljava/io/Reader;
    MethodParameters:
      Name                           Flags
      reader                         final

  public static org.xml.sax.InputSource fromInputStream(java.io.InputStream);
    descriptor: (Ljava/io/InputStream;)Lorg/xml/sax/InputSource;
    flags: (0x0009) ACC_PUBLIC, ACC_STATIC
    Code:
      stack=2, locals=1, args_size=1
         0: getstatic     #17                 // Field scala/xml/Source$.MODULE$:Lscala/xml/Source$;
         3: aload_0
         4: invokevirtual #35                 // Method scala/xml/Source$.fromInputStream:(Ljava/io/InputStream;)Lorg/xml/sax/InputSource;
         7: areturn
      LocalVariableTable:
        Start  Length  Slot  Name   Signature
            0       8     0    is   Ljava/io/InputStream;
    MethodParameters:
      Name                           Flags
      is                             final

  public static org.xml.sax.InputSource fromFile(java.lang.String);
    descriptor: (Ljava/lang/String;)Lorg/xml/sax/InputSource;
    flags: (0x0009) ACC_PUBLIC, ACC_STATIC
    Code:
      stack=2, locals=1, args_size=1
         0: getstatic     #17                 // Field scala/xml/Source$.MODULE$:Lscala/xml/Source$;
         3: aload_0
         4: invokevirtual #40                 // Method scala/xml/Source$.fromFile:(Ljava/lang/String;)Lorg/xml/sax/InputSource;
         7: areturn
      LocalVariableTable:
        Start  Length  Slot  Name   Signature
            0       8     0  name   Ljava/lang/String;
    MethodParameters:
      Name                           Flags
      name                           final

  public static org.xml.sax.InputSource fromFile(java.io.FileDescriptor);
    descriptor: (Ljava/io/FileDescriptor;)Lorg/xml/sax/InputSource;
    flags: (0x0009) ACC_PUBLIC, ACC_STATIC
    Code:
      stack=2, locals=1, args_size=1
         0: getstatic     #17                 // Field scala/xml/Source$.MODULE$:Lscala/xml/Source$;
         3: aload_0
         4: invokevirtual #44                 // Method scala/xml/Source$.fromFile:(Ljava/io/FileDescriptor;)Lorg/xml/sax/InputSource;
         7: areturn
      LocalVariableTable:
        Start  Length  Slot  Name   Signature
            0       8     0    fd   Ljava/io/FileDescriptor;
    MethodParameters:
      Name                           Flags
      fd                             final

  public static org.xml.sax.InputSource fromFile(java.io.File);
    descriptor: (Ljava/io/File;)Lorg/xml/sax/InputSource;
    flags: (0x0009) ACC_PUBLIC, ACC_STATIC
    Code:
      stack=2, locals=1, args_size=1
         0: getstatic     #17                 // Field scala/xml/Source$.MODULE$:Lscala/xml/Source$;
         3: aload_0
         4: invokevirtual #49                 // Method scala/xml/Source$.fromFile:(Ljava/io/File;)Lorg/xml/sax/InputSource;
         7: areturn
      LocalVariableTable:
        Start  Length  Slot  Name   Signature
            0       8     0  file   Ljava/io/File;
    MethodParameters:
      Name                           Flags
      file                           final
}
SourceFile: "XML.scala"
RuntimeVisibleAnnotations:
  0: #6(#7=s#8)
    scala.reflect.ScalaSignature(
      bytes="\u0006\u0005e;QAC\u0006\t\u0002A1QAE\u0006\t\u0002MAQ\u0001G\u0001\u0005\u0002eAQAG\u0001\u0005\u0002mAQAG\u0001\u0005\u0002=BQAG\u0001\u0005\u0002UBQaQ\u0001\u0005\u0002\u0011CQAS\u0001\u0005\u0002-CQ!U\u0001\u0005\u0002ICQ!V\u0001\u0005\u0002Y\u000baaU8ve\u000e,\'B\u0001\u0007\u000e\u0003\rAX\u000e\u001c\u0006\u0002\u001d\u0005)1oY1mC\u000e\u0001\u0001CA\t\u0002\u001b\u0005Y!AB*pkJ\u001cWm\u0005\u0002\u0002)A\u0011QCF\u0007\u0002\u001b%\u0011q#\u0004\u0002\u0007\u0003:L(+\u001a4\u0002\rqJg.\u001b;?)\u0005\u0001\u0012\u0001\u00034s_64\u0015\u000e\\3\u0015\u0005q)\u0003CA\u000f$\u001b\u0005q\"BA\u0010!\u0003\r\u0019\u0018\r\u001f\u0006\u0003\u0019\u0005R\u0011AI\u0001\u0004_J<\u0017B\u0001\u0013\u001f\u0005-Ie\u000e];u\'>,(oY3\t\u000b\u0019\u001a\u0001\u0019A\u0014\u0002\t\u0019LG.\u001a\t\u0003Q5j\u0011!\u000b\u0006\u0003U-\n!![8\u000b\u00031\nAA[1wC&\u0011a&\u000b\u0002\u0005\r&dW\r\u0006\u0002\u001da!)\u0011\u0007\u0002a\u0001e\u0005\u0011a\r\u001a\t\u0003QMJ!\u0001N\u0015\u0003\u001d\u0019KG.\u001a#fg\u000e\u0014\u0018\u000e\u001d;peR\u0011AD\u000e\u0005\u0006o\u0015\u0001\r\u0001O\u0001\u0005]\u0006lW\r\u0005\u0002:\u0001:\u0011!H\u0010\t\u0003w5i\u0011\u0001\u0010\u0006\u0003{=\ta\u0001\u0010:p_Rt\u0014BA \u000e\u0003\u0019\u0001&/\u001a3fM&\u0011\u0011I\u0011\u0002\u0007\'R\u0014\u0018N\\4\u000b\u0005}j\u0011a\u00044s_6Le\u000e];u\'R\u0014X-Y7\u0015\u0005q)\u0005\"\u0002$\u0007\u0001\u00049\u0015AA5t!\tA\u0003*\u0003\u0002JS\tY\u0011J\u001c9viN#(/Z1n\u0003)1\'o\\7SK\u0006$WM\u001d\u000b\u000391CQ!T\u0004A\u00029\u000baA]3bI\u0016\u0014\bC\u0001\u0015P\u0013\t\u0001\u0016F\u0001\u0004SK\u0006$WM]\u0001\nMJ|WnU=t\u0013\u0012$\"\u0001H*\t\u000bQC\u0001\u0019\u0001\u001d\u0002\u000bML8/\u0013#\u0002\u0015\u0019\u0014x.\\*ue&tw\r\u0006\u0002\u001d/\")\u0001,\u0003a\u0001q\u000511\u000f\u001e:j]\u001e\u0004"
    )
  ScalaSig: length = 0x3 (unknown attribute)
   05 02 00
