Classfile /Users/mw/Projects/slang-braindump/.jar/jar11/assemble/slang-braindump/assemble/content/scala/xml/TopScope$.class
  Last modified May 29, 2022; size 1821 bytes
  SHA-256 checksum 4d14e2e9b74cf8480e6535848e7c81b303e53decae20ccae6a8115decbdd7f20
  Compiled from "TopScope.scala"
public final class scala.xml.TopScope$ extends scala.xml.NamespaceBinding
  minor version: 0
  major version: 52
  flags: (0x0031) ACC_PUBLIC, ACC_FINAL, ACC_SUPER
  this_class: #2                          // scala/xml/TopScope$
  super_class: #4                         // scala/xml/NamespaceBinding
  interfaces: 0, fields: 1, methods: 8, attributes: 3
Constant pool:
   #1 = Utf8               scala/xml/TopScope$
   #2 = Class              #1             // scala/xml/TopScope$
   #3 = Utf8               scala/xml/NamespaceBinding
   #4 = Class              #3             // scala/xml/NamespaceBinding
   #5 = Utf8               TopScope.scala
   #6 = Utf8               MODULE$
   #7 = Utf8               Lscala/xml/TopScope$;
   #8 = Utf8               <clinit>
   #9 = Utf8               ()V
  #10 = Utf8               <init>
  #11 = NameAndType        #10:#9         // "<init>":()V
  #12 = Methodref          #2.#11         // scala/xml/TopScope$."<init>":()V
  #13 = NameAndType        #6:#7          // MODULE$:Lscala/xml/TopScope$;
  #14 = Fieldref           #2.#13         // scala/xml/TopScope$.MODULE$:Lscala/xml/TopScope$;
  #15 = Utf8               getURI
  #16 = Utf8               (Ljava/lang/String;)Ljava/lang/String;
  #17 = Utf8               prefix1
  #18 = Utf8               scala/xml/XML$
  #19 = Class              #18            // scala/xml/XML$
  #20 = Utf8               Lscala/xml/XML$;
  #21 = NameAndType        #6:#20         // MODULE$:Lscala/xml/XML$;
  #22 = Fieldref           #19.#21        // scala/xml/XML$.MODULE$:Lscala/xml/XML$;
  #23 = Utf8               xml
  #24 = Utf8               ()Ljava/lang/String;
  #25 = NameAndType        #23:#24        // xml:()Ljava/lang/String;
  #26 = Methodref          #19.#25        // scala/xml/XML$.xml:()Ljava/lang/String;
  #27 = Utf8               java/lang/Object
  #28 = Class              #27            // java/lang/Object
  #29 = Utf8               equals
  #30 = Utf8               (Ljava/lang/Object;)Z
  #31 = NameAndType        #29:#30        // equals:(Ljava/lang/Object;)Z
  #32 = Methodref          #28.#31        // java/lang/Object.equals:(Ljava/lang/Object;)Z
  #33 = Utf8               namespace
  #34 = NameAndType        #33:#24        // namespace:()Ljava/lang/String;
  #35 = Methodref          #19.#34        // scala/xml/XML$.namespace:()Ljava/lang/String;
  #36 = Utf8               this
  #37 = Utf8               Ljava/lang/String;
  #38 = Utf8               java/lang/String
  #39 = Class              #38            // java/lang/String
  #40 = Utf8               getPrefix
  #41 = Utf8               uri1
  #42 = Utf8               toString
  #43 = Utf8
  #44 = String             #43            //
  #45 = Utf8               buildString
  #46 = Utf8               (Lscala/xml/NamespaceBinding;)Ljava/lang/String;
  #47 = Utf8               stop
  #48 = Utf8               Lscala/xml/NamespaceBinding;
  #49 = Utf8               (Lscala/collection/mutable/StringBuilder;Lscala/xml/NamespaceBinding;)V
  #50 = Utf8               sb
  #51 = Utf8               ignore
  #52 = Utf8               Lscala/collection/mutable/StringBuilder;
  #53 = Utf8               writeReplace
  #54 = Utf8               ()Ljava/lang/Object;
  #55 = Utf8               scala/runtime/ModuleSerializationProxy
  #56 = Class              #55            // scala/runtime/ModuleSerializationProxy
  #57 = Utf8               (Ljava/lang/Class;)V
  #58 = NameAndType        #10:#57        // "<init>":(Ljava/lang/Class;)V
  #59 = Methodref          #56.#58        // scala/runtime/ModuleSerializationProxy."<init>":(Ljava/lang/Class;)V
  #60 = Utf8               (Ljava/lang/String;Ljava/lang/String;Lscala/xml/NamespaceBinding;)V
  #61 = NameAndType        #10:#60        // "<init>":(Ljava/lang/String;Ljava/lang/String;Lscala/xml/NamespaceBinding;)V
  #62 = Methodref          #4.#61         // scala/xml/NamespaceBinding."<init>":(Ljava/lang/String;Ljava/lang/String;Lscala/xml/NamespaceBinding;)V
  #63 = Utf8               Code
  #64 = Utf8               LineNumberTable
  #65 = Utf8               StackMapTable
  #66 = Utf8               LocalVariableTable
  #67 = Utf8               MethodParameters
  #68 = Utf8               SourceFile
  #69 = Utf8               ScalaInlineInfo
  #70 = Utf8               Scala
{
  public static final scala.xml.TopScope$ MODULE$;
    descriptor: Lscala/xml/TopScope$;
    flags: (0x0019) ACC_PUBLIC, ACC_STATIC, ACC_FINAL

  public static {};
    descriptor: ()V
    flags: (0x0009) ACC_PUBLIC, ACC_STATIC
    Code:
      stack=2, locals=0, args_size=0
         0: new           #2                  // class scala/xml/TopScope$
         3: dup
         4: invokespecial #12                 // Method "<init>":()V
         7: putstatic     #14                 // Field MODULE$:Lscala/xml/TopScope$;
        10: return
      LineNumberTable:
        line 21: 0

  public java.lang.String getURI(java.lang.String);
    descriptor: (Ljava/lang/String;)Ljava/lang/String;
    flags: (0x0001) ACC_PUBLIC
    Code:
      stack=2, locals=3, args_size=2
         0: aload_1
         1: getstatic     #22                 // Field scala/xml/XML$.MODULE$:Lscala/xml/XML$;
         4: invokevirtual #26                 // Method scala/xml/XML$.xml:()Ljava/lang/String;
         7: astore_2
         8: dup
         9: ifnonnull     20
        12: pop
        13: aload_2
        14: ifnull        27
        17: goto          36
        20: aload_2
        21: invokevirtual #32                 // Method java/lang/Object.equals:(Ljava/lang/Object;)Z
        24: ifeq          36
        27: getstatic     #22                 // Field scala/xml/XML$.MODULE$:Lscala/xml/XML$;
        30: invokevirtual #35                 // Method scala/xml/XML$.namespace:()Ljava/lang/String;
        33: goto          37
        36: aconst_null
        37: areturn
      StackMapTable: number_of_entries = 4
        frame_type = 255 /* full_frame */
          offset_delta = 20
          locals = [ class scala/xml/TopScope$, class java/lang/String, class java/lang/String ]
          stack = [ class java/lang/String ]
        frame_type = 6 /* same */
        frame_type = 8 /* same */
        frame_type = 64 /* same_locals_1_stack_item */
          stack = [ class java/lang/String ]
      LineNumberTable:
        line 26: 0
      LocalVariableTable:
        Start  Length  Slot  Name   Signature
            0      38     0  this   Lscala/xml/TopScope$;
            0      38     1 prefix1   Ljava/lang/String;
    MethodParameters:
      Name                           Flags
      prefix1                        final

  public java.lang.String getPrefix(java.lang.String);
    descriptor: (Ljava/lang/String;)Ljava/lang/String;
    flags: (0x0001) ACC_PUBLIC
    Code:
      stack=2, locals=3, args_size=2
         0: aload_1
         1: getstatic     #22                 // Field scala/xml/XML$.MODULE$:Lscala/xml/XML$;
         4: invokevirtual #35                 // Method scala/xml/XML$.namespace:()Ljava/lang/String;
         7: astore_2
         8: dup
         9: ifnonnull     20
        12: pop
        13: aload_2
        14: ifnull        27
        17: goto          36
        20: aload_2
        21: invokevirtual #32                 // Method java/lang/Object.equals:(Ljava/lang/Object;)Z
        24: ifeq          36
        27: getstatic     #22                 // Field scala/xml/XML$.MODULE$:Lscala/xml/XML$;
        30: invokevirtual #26                 // Method scala/xml/XML$.xml:()Ljava/lang/String;
        33: goto          37
        36: aconst_null
        37: areturn
      StackMapTable: number_of_entries = 4
        frame_type = 255 /* full_frame */
          offset_delta = 20
          locals = [ class scala/xml/TopScope$, class java/lang/String, class java/lang/String ]
          stack = [ class java/lang/String ]
        frame_type = 6 /* same */
        frame_type = 8 /* same */
        frame_type = 64 /* same_locals_1_stack_item */
          stack = [ class java/lang/String ]
      LineNumberTable:
        line 29: 0
      LocalVariableTable:
        Start  Length  Slot  Name   Signature
            0      38     0  this   Lscala/xml/TopScope$;
            0      38     1  uri1   Ljava/lang/String;
    MethodParameters:
      Name                           Flags
      uri1                           final

  public java.lang.String toString();
    descriptor: ()Ljava/lang/String;
    flags: (0x0001) ACC_PUBLIC
    Code:
      stack=1, locals=1, args_size=1
         0: ldc           #44                 // String
         2: areturn
      LineNumberTable:
        line 31: 0
      LocalVariableTable:
        Start  Length  Slot  Name   Signature
            0       3     0  this   Lscala/xml/TopScope$;

  public java.lang.String buildString(scala.xml.NamespaceBinding);
    descriptor: (Lscala/xml/NamespaceBinding;)Ljava/lang/String;
    flags: (0x0001) ACC_PUBLIC
    Code:
      stack=1, locals=2, args_size=2
         0: ldc           #44                 // String
         2: areturn
      LineNumberTable:
        line 33: 0
      LocalVariableTable:
        Start  Length  Slot  Name   Signature
            0       3     0  this   Lscala/xml/TopScope$;
            0       3     1  stop   Lscala/xml/NamespaceBinding;
    MethodParameters:
      Name                           Flags
      stop                           final

  public void buildString(scala.collection.mutable.StringBuilder, scala.xml.NamespaceBinding);
    descriptor: (Lscala/collection/mutable/StringBuilder;Lscala/xml/NamespaceBinding;)V
    flags: (0x0001) ACC_PUBLIC
    Code:
      stack=0, locals=3, args_size=3
         0: return
      LineNumberTable:
        line 34: 0
      LocalVariableTable:
        Start  Length  Slot  Name   Signature
            0       1     0  this   Lscala/xml/TopScope$;
            0       1     1    sb   Lscala/collection/mutable/StringBuilder;
            0       1     2 ignore   Lscala/xml/NamespaceBinding;
    MethodParameters:
      Name                           Flags
      sb                             final
      ignore                         final

  private java.lang.Object writeReplace();
    descriptor: ()Ljava/lang/Object;
    flags: (0x0002) ACC_PRIVATE
    Code:
      stack=3, locals=1, args_size=1
         0: new           #56                 // class scala/runtime/ModuleSerializationProxy
         3: dup
         4: ldc           #2                  // class scala/xml/TopScope$
         6: invokespecial #59                 // Method scala/runtime/ModuleSerializationProxy."<init>":(Ljava/lang/Class;)V
         9: areturn
      LineNumberTable:
        line 21: 0
      LocalVariableTable:
        Start  Length  Slot  Name   Signature
            0      10     0  this   Lscala/xml/TopScope$;

  private scala.xml.TopScope$();
    descriptor: ()V
    flags: (0x0002) ACC_PRIVATE
    Code:
      stack=4, locals=1, args_size=1
         0: aload_0
         1: aconst_null
         2: aconst_null
         3: aconst_null
         4: invokespecial #62                 // Method scala/xml/NamespaceBinding."<init>":(Ljava/lang/String;Ljava/lang/String;Lscala/xml/NamespaceBinding;)V
         7: return
      LineNumberTable:
        line 21: 0
      LocalVariableTable:
        Start  Length  Slot  Name   Signature
            0       8     0  this   Lscala/xml/TopScope$;
}
SourceFile: "TopScope.scala"
  ScalaInlineInfo: length = 0x27 (unknown attribute)
   01 01 00 07 00 0A 00 09 01 00 2D 00 31 01 00 2D
   00 2E 01 00 28 00 10 01 00 0F 00 10 01 00 2A 00
   18 01 00 35 00 36 01
  Scala: length = 0x0 (unknown attribute)

