Classfile /Users/mw/Projects/slang-braindump/.jar/jar11/assemble/slang-braindump/assemble/content/scala/xml/Utility$Escapes$.class
  Last modified May 29, 2022; size 4070 bytes
  SHA-256 checksum dde231fdaec34e2732b2ffeef047411e1db1d1183b43b9e42e54118b17867193
  Compiled from "Utility.scala"
public class scala.xml.Utility$Escapes$
  minor version: 0
  major version: 52
  flags: (0x0021) ACC_PUBLIC, ACC_SUPER
  this_class: #2                          // scala/xml/Utility$Escapes$
  super_class: #4                         // java/lang/Object
  interfaces: 0, fields: 4, methods: 7, attributes: 5
Constant pool:
    #1 = Utf8               scala/xml/Utility$Escapes$
    #2 = Class              #1            // scala/xml/Utility$Escapes$
    #3 = Utf8               java/lang/Object
    #4 = Class              #3            // java/lang/Object
    #5 = Utf8               Utility.scala
    #6 = Utf8               java/lang/invoke/MethodHandles$Lookup
    #7 = Class              #6            // java/lang/invoke/MethodHandles$Lookup
    #8 = Utf8               java/lang/invoke/MethodHandles
    #9 = Class              #8            // java/lang/invoke/MethodHandles
   #10 = Utf8               Lookup
   #11 = Utf8               scala/Predef$ArrowAssoc$
   #12 = Class              #11           // scala/Predef$ArrowAssoc$
   #13 = Utf8               scala/Predef
   #14 = Class              #13           // scala/Predef
   #15 = Utf8               ArrowAssoc$
   #16 = Utf8               scala/xml/Utility
   #17 = Class              #16           // scala/xml/Utility
   #18 = Utf8               Escapes$
   #19 = Utf8               MODULE$
   #20 = Utf8               Lscala/xml/Utility$Escapes$;
   #21 = Utf8               pairs
   #22 = Utf8               Lscala/collection/immutable/Map;
   #23 = Utf8               Lscala/collection/immutable/Map<Ljava/lang/String;Ljava/lang/Object;>;
   #24 = Utf8               escMap
   #25 = Utf8               Lscala/collection/immutable/Map<Ljava/lang/Object;Ljava/lang/String;>;
   #26 = Utf8               unescMap
   #27 = Utf8               <clinit>
   #28 = Utf8               ()V
   #29 = Utf8               <init>
   #30 = NameAndType        #29:#28       // "<init>":()V
   #31 = Methodref          #2.#30        // scala/xml/Utility$Escapes$."<init>":()V
   #32 = NameAndType        #19:#20       // MODULE$:Lscala/xml/Utility$Escapes$;
   #33 = Fieldref           #2.#32        // scala/xml/Utility$Escapes$.MODULE$:Lscala/xml/Utility$Escapes$;
   #34 = Utf8               scala/Predef$
   #35 = Class              #34           // scala/Predef$
   #36 = Utf8               Lscala/Predef$;
   #37 = NameAndType        #19:#36       // MODULE$:Lscala/Predef$;
   #38 = Fieldref           #35.#37       // scala/Predef$.MODULE$:Lscala/Predef$;
   #39 = Utf8               Map
   #40 = Utf8               ()Lscala/collection/immutable/Map$;
   #41 = NameAndType        #39:#40       // Map:()Lscala/collection/immutable/Map$;
   #42 = Methodref          #35.#41       // scala/Predef$.Map:()Lscala/collection/immutable/Map$;
   #43 = Utf8               scala/runtime/ScalaRunTime$
   #44 = Class              #43           // scala/runtime/ScalaRunTime$
   #45 = Utf8               Lscala/runtime/ScalaRunTime$;
   #46 = NameAndType        #19:#45       // MODULE$:Lscala/runtime/ScalaRunTime$;
   #47 = Fieldref           #44.#46       // scala/runtime/ScalaRunTime$.MODULE$:Lscala/runtime/ScalaRunTime$;
   #48 = Utf8               scala/Tuple2
   #49 = Class              #48           // scala/Tuple2
   #50 = Utf8               Lscala/Predef$ArrowAssoc$;
   #51 = NameAndType        #19:#50       // MODULE$:Lscala/Predef$ArrowAssoc$;
   #52 = Fieldref           #12.#51       // scala/Predef$ArrowAssoc$.MODULE$:Lscala/Predef$ArrowAssoc$;
   #53 = Utf8               lt
   #54 = String             #53           // lt
   #55 = Utf8               ArrowAssoc
   #56 = Utf8               (Ljava/lang/Object;)Ljava/lang/Object;
   #57 = NameAndType        #55:#56       // ArrowAssoc:(Ljava/lang/Object;)Ljava/lang/Object;
   #58 = Methodref          #35.#57       // scala/Predef$.ArrowAssoc:(Ljava/lang/Object;)Ljava/lang/Object;
   #59 = Utf8               scala/runtime/BoxesRunTime
   #60 = Class              #59           // scala/runtime/BoxesRunTime
   #61 = Utf8               boxToCharacter
   #62 = Utf8               (C)Ljava/lang/Character;
   #63 = NameAndType        #61:#62       // boxToCharacter:(C)Ljava/lang/Character;
   #64 = Methodref          #60.#63       // scala/runtime/BoxesRunTime.boxToCharacter:(C)Ljava/lang/Character;
   #65 = Utf8               $minus$greater$extension
   #66 = Utf8               (Ljava/lang/Object;Ljava/lang/Object;)Lscala/Tuple2;
   #67 = NameAndType        #65:#66       // $minus$greater$extension:(Ljava/lang/Object;Ljava/lang/Object;)Lscala/Tuple2;
   #68 = Methodref          #12.#67       // scala/Predef$ArrowAssoc$.$minus$greater$extension:(Ljava/lang/Object;Ljava/lang/Object;)Lscala/Tuple2;
   #69 = Utf8               gt
   #70 = String             #69           // gt
   #71 = Utf8               amp
   #72 = String             #71           // amp
   #73 = Utf8               quot
   #74 = String             #73           // quot
   #75 = Utf8               apos
   #76 = String             #75           // apos
   #77 = Utf8               [Ljava/lang/Object;
   #78 = Class              #77           // "[Ljava/lang/Object;"
   #79 = Utf8               wrapRefArray
   #80 = Utf8               ([Ljava/lang/Object;)Lscala/collection/immutable/ArraySeq;
   #81 = NameAndType        #79:#80       // wrapRefArray:([Ljava/lang/Object;)Lscala/collection/immutable/ArraySeq;
   #82 = Methodref          #44.#81       // scala/runtime/ScalaRunTime$.wrapRefArray:([Ljava/lang/Object;)Lscala/collection/immutable/ArraySeq;
   #83 = Utf8               scala/collection/immutable/Map$
   #84 = Class              #83           // scala/collection/immutable/Map$
   #85 = Utf8               apply
   #86 = Utf8               (Lscala/collection/immutable/Seq;)Ljava/lang/Object;
   #87 = NameAndType        #85:#86       // apply:(Lscala/collection/immutable/Seq;)Ljava/lang/Object;
   #88 = Methodref          #84.#87       // scala/collection/immutable/Map$.apply:(Lscala/collection/immutable/Seq;)Ljava/lang/Object;
   #89 = Utf8               scala/collection/immutable/Map
   #90 = Class              #89           // scala/collection/immutable/Map
   #91 = NameAndType        #21:#22       // pairs:Lscala/collection/immutable/Map;
   #92 = Fieldref           #2.#91        // scala/xml/Utility$Escapes$.pairs:Lscala/collection/immutable/Map;
   #93 = Utf8               ()Lscala/collection/immutable/Map;
   #94 = NameAndType        #21:#93       // pairs:()Lscala/collection/immutable/Map;
   #95 = Methodref          #2.#94        // scala/xml/Utility$Escapes$.pairs:()Lscala/collection/immutable/Map;
   #96 = Utf8               $minus
   #97 = Utf8               (Ljava/lang/Object;)Lscala/collection/immutable/MapOps;
   #98 = NameAndType        #96:#97       // $minus:(Ljava/lang/Object;)Lscala/collection/immutable/MapOps;
   #99 = InterfaceMethodref #90.#98       // scala/collection/immutable/Map.$minus:(Ljava/lang/Object;)Lscala/collection/immutable/MapOps;
  #100 = MethodType         #56           //  (Ljava/lang/Object;)Ljava/lang/Object;
  #101 = Utf8               $anonfun$escMap$1
  #102 = Utf8               (Lscala/Tuple2;)Lscala/Tuple2;
  #103 = NameAndType        #101:#102     // $anonfun$escMap$1:(Lscala/Tuple2;)Lscala/Tuple2;
  #104 = Methodref          #2.#103       // scala/xml/Utility$Escapes$.$anonfun$escMap$1:(Lscala/Tuple2;)Lscala/Tuple2;
  #105 = MethodHandle       6:#104        // REF_invokeStatic scala/xml/Utility$Escapes$.$anonfun$escMap$1:(Lscala/Tuple2;)Lscala/Tuple2;
  #106 = MethodType         #102          //  (Lscala/Tuple2;)Lscala/Tuple2;
  #107 = Integer            5
  #108 = Integer            1
  #109 = Utf8               java/lang/invoke/LambdaMetafactory
  #110 = Class              #109          // java/lang/invoke/LambdaMetafactory
  #111 = Utf8               altMetafactory
  #112 = Utf8               (Ljava/lang/invoke/MethodHandles$Lookup;Ljava/lang/String;Ljava/lang/invoke/MethodType;[Ljava/lang/Object;)Ljava/lang/invoke/CallSite;
  #113 = NameAndType        #111:#112     // altMetafactory:(Ljava/lang/invoke/MethodHandles$Lookup;Ljava/lang/String;Ljava/lang/invoke/MethodType;[Ljava/lang/Object;)Ljava/lang/invoke/CallSite;
  #114 = Methodref          #110.#113     // java/lang/invoke/LambdaMetafactory.altMetafactory:(Ljava/lang/invoke/MethodHandles$Lookup;Ljava/lang/String;Ljava/lang/invoke/MethodType;[Ljava/lang/Object;)Ljava/lang/invoke/CallSite;
  #115 = MethodHandle       6:#114        // REF_invokeStatic java/lang/invoke/LambdaMetafactory.altMetafactory:(Ljava/lang/invoke/MethodHandles$Lookup;Ljava/lang/String;Ljava/lang/invoke/MethodType;[Ljava/lang/Object;)Ljava/lang/invoke/CallSite;
  #116 = Utf8               ()Lscala/Function1;
  #117 = NameAndType        #85:#116      // apply:()Lscala/Function1;
  #118 = InvokeDynamic      #0:#117       // #0:apply:()Lscala/Function1;
  #119 = Utf8               scala/collection/immutable/MapOps
  #120 = Class              #119          // scala/collection/immutable/MapOps
  #121 = Utf8               map
  #122 = Utf8               (Lscala/Function1;)Lscala/collection/IterableOps;
  #123 = NameAndType        #121:#122     // map:(Lscala/Function1;)Lscala/collection/IterableOps;
  #124 = InterfaceMethodref #120.#123     // scala/collection/immutable/MapOps.map:(Lscala/Function1;)Lscala/collection/IterableOps;
  #125 = NameAndType        #24:#22       // escMap:Lscala/collection/immutable/Map;
  #126 = Fieldref           #2.#125       // scala/xml/Utility$Escapes$.escMap:Lscala/collection/immutable/Map;
  #127 = NameAndType        #26:#22       // unescMap:Lscala/collection/immutable/Map;
  #128 = Fieldref           #2.#127       // scala/xml/Utility$Escapes$.unescMap:Lscala/collection/immutable/Map;
  #129 = Utf8               ()Lscala/collection/immutable/Map<Ljava/lang/String;Ljava/lang/Object;>;
  #130 = Utf8               this
  #131 = Utf8               ()Lscala/collection/immutable/Map<Ljava/lang/Object;Ljava/lang/String;>;
  #132 = Utf8               x0$1
  #133 = Utf8               _1
  #134 = Utf8               ()Ljava/lang/Object;
  #135 = NameAndType        #133:#134     // _1:()Ljava/lang/Object;
  #136 = Methodref          #49.#135      // scala/Tuple2._1:()Ljava/lang/Object;
  #137 = Utf8               java/lang/String
  #138 = Class              #137          // java/lang/String
  #139 = Utf8               _2$mcC$sp
  #140 = Utf8               ()C
  #141 = NameAndType        #139:#140     // _2$mcC$sp:()C
  #142 = Methodref          #49.#141      // scala/Tuple2._2$mcC$sp:()C
  #143 = Utf8               scala/collection/StringOps$
  #144 = Class              #143          // scala/collection/StringOps$
  #145 = Utf8               Lscala/collection/StringOps$;
  #146 = NameAndType        #19:#145      // MODULE$:Lscala/collection/StringOps$;
  #147 = Fieldref           #144.#146     // scala/collection/StringOps$.MODULE$:Lscala/collection/StringOps$;
  #148 = Utf8               &%s;
  #149 = String             #148          // &%s;
  #150 = Utf8               augmentString
  #151 = Utf8               (Ljava/lang/String;)Ljava/lang/String;
  #152 = NameAndType        #150:#151     // augmentString:(Ljava/lang/String;)Ljava/lang/String;
  #153 = Methodref          #35.#152      // scala/Predef$.augmentString:(Ljava/lang/String;)Ljava/lang/String;
  #154 = Utf8               genericWrapArray
  #155 = Utf8               (Ljava/lang/Object;)Lscala/collection/immutable/ArraySeq;
  #156 = NameAndType        #154:#155     // genericWrapArray:(Ljava/lang/Object;)Lscala/collection/immutable/ArraySeq;
  #157 = Methodref          #44.#156      // scala/runtime/ScalaRunTime$.genericWrapArray:(Ljava/lang/Object;)Lscala/collection/immutable/ArraySeq;
  #158 = Utf8               format$extension
  #159 = Utf8               (Ljava/lang/String;Lscala/collection/immutable/Seq;)Ljava/lang/String;
  #160 = NameAndType        #158:#159     // format$extension:(Ljava/lang/String;Lscala/collection/immutable/Seq;)Ljava/lang/String;
  #161 = Methodref          #144.#160     // scala/collection/StringOps$.format$extension:(Ljava/lang/String;Lscala/collection/immutable/Seq;)Ljava/lang/String;
  #162 = Utf8               scala/MatchError
  #163 = Class              #162          // scala/MatchError
  #164 = Utf8               (Ljava/lang/Object;)V
  #165 = NameAndType        #29:#164      // "<init>":(Ljava/lang/Object;)V
  #166 = Methodref          #163.#165     // scala/MatchError."<init>":(Ljava/lang/Object;)V
  #167 = Utf8               s
  #168 = Utf8               Ljava/lang/String;
  #169 = Utf8               c
  #170 = Utf8               C
  #171 = Utf8               Lscala/Tuple2;
  #172 = Methodref          #4.#30        // java/lang/Object."<init>":()V
  #173 = Utf8               $deserializeLambda$
  #174 = Utf8               (Ljava/lang/invoke/SerializedLambda;)Ljava/lang/Object;
  #175 = Utf8               scala/runtime/LambdaDeserialize
  #176 = Class              #175          // scala/runtime/LambdaDeserialize
  #177 = Utf8               bootstrap
  #178 = Utf8               (Ljava/lang/invoke/MethodHandles$Lookup;Ljava/lang/String;Ljava/lang/invoke/MethodType;[Ljava/lang/invoke/MethodHandle;)Ljava/lang/invoke/CallSite;
  #179 = NameAndType        #177:#178     // bootstrap:(Ljava/lang/invoke/MethodHandles$Lookup;Ljava/lang/String;Ljava/lang/invoke/MethodType;[Ljava/lang/invoke/MethodHandle;)Ljava/lang/invoke/CallSite;
  #180 = Methodref          #176.#179     // scala/runtime/LambdaDeserialize.bootstrap:(Ljava/lang/invoke/MethodHandles$Lookup;Ljava/lang/String;Ljava/lang/invoke/MethodType;[Ljava/lang/invoke/MethodHandle;)Ljava/lang/invoke/CallSite;
  #181 = MethodHandle       6:#180        // REF_invokeStatic scala/runtime/LambdaDeserialize.bootstrap:(Ljava/lang/invoke/MethodHandles$Lookup;Ljava/lang/String;Ljava/lang/invoke/MethodType;[Ljava/lang/invoke/MethodHandle;)Ljava/lang/invoke/CallSite;
  #182 = Utf8               lambdaDeserialize
  #183 = NameAndType        #182:#174     // lambdaDeserialize:(Ljava/lang/invoke/SerializedLambda;)Ljava/lang/Object;
  #184 = InvokeDynamic      #1:#183       // #1:lambdaDeserialize:(Ljava/lang/invoke/SerializedLambda;)Ljava/lang/Object;
  #185 = Utf8               Signature
  #186 = Utf8               Code
  #187 = Utf8               LineNumberTable
  #188 = Utf8               LocalVariableTable
  #189 = Utf8               StackMapTable
  #190 = Utf8               MethodParameters
  #191 = Utf8               InnerClasses
  #192 = Utf8               SourceFile
  #193 = Utf8               BootstrapMethods
  #194 = Utf8               ScalaInlineInfo
  #195 = Utf8               Scala
{
  public static final scala.xml.Utility$Escapes$ MODULE$;
    descriptor: Lscala/xml/Utility$Escapes$;
    flags: (0x0019) ACC_PUBLIC, ACC_STATIC, ACC_FINAL

  private static final scala.collection.immutable.Map<java.lang.String, java.lang.Object> pairs;
    descriptor: Lscala/collection/immutable/Map;
    flags: (0x001a) ACC_PRIVATE, ACC_STATIC, ACC_FINAL
    Signature: #23                          // Lscala/collection/immutable/Map<Ljava/lang/String;Ljava/lang/Object;>;

  private static final scala.collection.immutable.Map<java.lang.Object, java.lang.String> escMap;
    descriptor: Lscala/collection/immutable/Map;
    flags: (0x001a) ACC_PRIVATE, ACC_STATIC, ACC_FINAL
    Signature: #25                          // Lscala/collection/immutable/Map<Ljava/lang/Object;Ljava/lang/String;>;

  private static final scala.collection.immutable.Map<java.lang.String, java.lang.Object> unescMap;
    descriptor: Lscala/collection/immutable/Map;
    flags: (0x001a) ACC_PRIVATE, ACC_STATIC, ACC_FINAL
    Signature: #23                          // Lscala/collection/immutable/Map<Ljava/lang/String;Ljava/lang/Object;>;

  public static {};
    descriptor: ()V
    flags: (0x0009) ACC_PUBLIC, ACC_STATIC
    Code:
      stack=8, locals=0, args_size=0
         0: new           #2                  // class scala/xml/Utility$Escapes$
         3: dup
         4: invokespecial #31                 // Method "<init>":()V
         7: putstatic     #33                 // Field MODULE$:Lscala/xml/Utility$Escapes$;
        10: getstatic     #38                 // Field scala/Predef$.MODULE$:Lscala/Predef$;
        13: invokevirtual #42                 // Method scala/Predef$.Map:()Lscala/collection/immutable/Map$;
        16: getstatic     #47                 // Field scala/runtime/ScalaRunTime$.MODULE$:Lscala/runtime/ScalaRunTime$;
        19: iconst_5
        20: anewarray     #49                 // class scala/Tuple2
        23: dup
        24: iconst_0
        25: getstatic     #52                 // Field scala/Predef$ArrowAssoc$.MODULE$:Lscala/Predef$ArrowAssoc$;
        28: getstatic     #38                 // Field scala/Predef$.MODULE$:Lscala/Predef$;
        31: ldc           #54                 // String lt
        33: invokevirtual #58                 // Method scala/Predef$.ArrowAssoc:(Ljava/lang/Object;)Ljava/lang/Object;
        36: bipush        60
        38: invokestatic  #64                 // Method scala/runtime/BoxesRunTime.boxToCharacter:(C)Ljava/lang/Character;
        41: invokevirtual #68                 // Method scala/Predef$ArrowAssoc$.$minus$greater$extension:(Ljava/lang/Object;Ljava/lang/Object;)Lscala/Tuple2;
        44: aastore
        45: dup
        46: iconst_1
        47: getstatic     #52                 // Field scala/Predef$ArrowAssoc$.MODULE$:Lscala/Predef$ArrowAssoc$;
        50: getstatic     #38                 // Field scala/Predef$.MODULE$:Lscala/Predef$;
        53: ldc           #70                 // String gt
        55: invokevirtual #58                 // Method scala/Predef$.ArrowAssoc:(Ljava/lang/Object;)Ljava/lang/Object;
        58: bipush        62
        60: invokestatic  #64                 // Method scala/runtime/BoxesRunTime.boxToCharacter:(C)Ljava/lang/Character;
        63: invokevirtual #68                 // Method scala/Predef$ArrowAssoc$.$minus$greater$extension:(Ljava/lang/Object;Ljava/lang/Object;)Lscala/Tuple2;
        66: aastore
        67: dup
        68: iconst_2
        69: getstatic     #52                 // Field scala/Predef$ArrowAssoc$.MODULE$:Lscala/Predef$ArrowAssoc$;
        72: getstatic     #38                 // Field scala/Predef$.MODULE$:Lscala/Predef$;
        75: ldc           #72                 // String amp
        77: invokevirtual #58                 // Method scala/Predef$.ArrowAssoc:(Ljava/lang/Object;)Ljava/lang/Object;
        80: bipush        38
        82: invokestatic  #64                 // Method scala/runtime/BoxesRunTime.boxToCharacter:(C)Ljava/lang/Character;
        85: invokevirtual #68                 // Method scala/Predef$ArrowAssoc$.$minus$greater$extension:(Ljava/lang/Object;Ljava/lang/Object;)Lscala/Tuple2;
        88: aastore
        89: dup
        90: iconst_3
        91: getstatic     #52                 // Field scala/Predef$ArrowAssoc$.MODULE$:Lscala/Predef$ArrowAssoc$;
        94: getstatic     #38                 // Field scala/Predef$.MODULE$:Lscala/Predef$;
        97: ldc           #74                 // String quot
        99: invokevirtual #58                 // Method scala/Predef$.ArrowAssoc:(Ljava/lang/Object;)Ljava/lang/Object;
       102: bipush        34
       104: invokestatic  #64                 // Method scala/runtime/BoxesRunTime.boxToCharacter:(C)Ljava/lang/Character;
       107: invokevirtual #68                 // Method scala/Predef$ArrowAssoc$.$minus$greater$extension:(Ljava/lang/Object;Ljava/lang/Object;)Lscala/Tuple2;
       110: aastore
       111: dup
       112: iconst_4
       113: getstatic     #52                 // Field scala/Predef$ArrowAssoc$.MODULE$:Lscala/Predef$ArrowAssoc$;
       116: getstatic     #38                 // Field scala/Predef$.MODULE$:Lscala/Predef$;
       119: ldc           #76                 // String apos
       121: invokevirtual #58                 // Method scala/Predef$.ArrowAssoc:(Ljava/lang/Object;)Ljava/lang/Object;
       124: bipush        39
       126: invokestatic  #64                 // Method scala/runtime/BoxesRunTime.boxToCharacter:(C)Ljava/lang/Character;
       129: invokevirtual #68                 // Method scala/Predef$ArrowAssoc$.$minus$greater$extension:(Ljava/lang/Object;Ljava/lang/Object;)Lscala/Tuple2;
       132: aastore
       133: checkcast     #78                 // class "[Ljava/lang/Object;"
       136: invokevirtual #82                 // Method scala/runtime/ScalaRunTime$.wrapRefArray:([Ljava/lang/Object;)Lscala/collection/immutable/ArraySeq;
       139: invokevirtual #88                 // Method scala/collection/immutable/Map$.apply:(Lscala/collection/immutable/Seq;)Ljava/lang/Object;
       142: checkcast     #90                 // class scala/collection/immutable/Map
       145: putstatic     #92                 // Field pairs:Lscala/collection/immutable/Map;
       148: getstatic     #33                 // Field MODULE$:Lscala/xml/Utility$Escapes$;
       151: invokevirtual #95                 // Method pairs:()Lscala/collection/immutable/Map;
       154: ldc           #76                 // String apos
       156: invokeinterface #99,  2           // InterfaceMethod scala/collection/immutable/Map.$minus:(Ljava/lang/Object;)Lscala/collection/immutable/MapOps;
       161: invokedynamic #118,  0            // InvokeDynamic #0:apply:()Lscala/Function1;
       166: invokeinterface #124,  2          // InterfaceMethod scala/collection/immutable/MapOps.map:(Lscala/Function1;)Lscala/collection/IterableOps;
       171: checkcast     #90                 // class scala/collection/immutable/Map
       174: putstatic     #126                // Field escMap:Lscala/collection/immutable/Map;
       177: getstatic     #33                 // Field MODULE$:Lscala/xml/Utility$Escapes$;
       180: invokevirtual #95                 // Method pairs:()Lscala/collection/immutable/Map;
       183: putstatic     #128                // Field unescMap:Lscala/collection/immutable/Map;
       186: return
      LineNumberTable:
        line 102: 0
        line 107: 10
        line 108: 28
        line 109: 50
        line 110: 72
        line 111: 94
        line 112: 116
        line 107: 145
        line 114: 148
        line 115: 177
        line 102: 186

  public scala.collection.immutable.Map<java.lang.String, java.lang.Object> pairs();
    descriptor: ()Lscala/collection/immutable/Map;
    flags: (0x0001) ACC_PUBLIC
    Code:
      stack=1, locals=1, args_size=1
         0: getstatic     #92                 // Field pairs:Lscala/collection/immutable/Map;
         3: areturn
      LineNumberTable:
        line 107: 0
      LocalVariableTable:
        Start  Length  Slot  Name   Signature
            0       4     0  this   Lscala/xml/Utility$Escapes$;
    Signature: #129                         // ()Lscala/collection/immutable/Map<Ljava/lang/String;Ljava/lang/Object;>;

  public scala.collection.immutable.Map<java.lang.Object, java.lang.String> escMap();
    descriptor: ()Lscala/collection/immutable/Map;
    flags: (0x0001) ACC_PUBLIC
    Code:
      stack=1, locals=1, args_size=1
         0: getstatic     #126                // Field escMap:Lscala/collection/immutable/Map;
         3: areturn
      LineNumberTable:
        line 114: 0
      LocalVariableTable:
        Start  Length  Slot  Name   Signature
            0       4     0  this   Lscala/xml/Utility$Escapes$;
    Signature: #131                         // ()Lscala/collection/immutable/Map<Ljava/lang/Object;Ljava/lang/String;>;

  public scala.collection.immutable.Map<java.lang.String, java.lang.Object> unescMap();
    descriptor: ()Lscala/collection/immutable/Map;
    flags: (0x0001) ACC_PUBLIC
    Code:
      stack=1, locals=1, args_size=1
         0: getstatic     #128                // Field unescMap:Lscala/collection/immutable/Map;
         3: areturn
      LineNumberTable:
        line 115: 0
      LocalVariableTable:
        Start  Length  Slot  Name   Signature
            0       4     0  this   Lscala/xml/Utility$Escapes$;
    Signature: #129                         // ()Lscala/collection/immutable/Map<Ljava/lang/String;Ljava/lang/Object;>;

  public static final scala.Tuple2 $anonfun$escMap$1(scala.Tuple2);
    descriptor: (Lscala/Tuple2;)Lscala/Tuple2;
    flags: (0x1019) ACC_PUBLIC, ACC_STATIC, ACC_FINAL, ACC_SYNTHETIC
    Code:
      stack=9, locals=5, args_size=1
         0: aload_0
         1: astore_2
         2: aload_2
         3: ifnull        69
         6: aload_2
         7: invokevirtual #136                // Method scala/Tuple2._1:()Ljava/lang/Object;
        10: checkcast     #138                // class java/lang/String
        13: astore_3
        14: aload_2
        15: invokevirtual #142                // Method scala/Tuple2._2$mcC$sp:()C
        18: istore        4
        20: getstatic     #52                 // Field scala/Predef$ArrowAssoc$.MODULE$:Lscala/Predef$ArrowAssoc$;
        23: getstatic     #38                 // Field scala/Predef$.MODULE$:Lscala/Predef$;
        26: iload         4
        28: invokestatic  #64                 // Method scala/runtime/BoxesRunTime.boxToCharacter:(C)Ljava/lang/Character;
        31: invokevirtual #58                 // Method scala/Predef$.ArrowAssoc:(Ljava/lang/Object;)Ljava/lang/Object;
        34: getstatic     #147                // Field scala/collection/StringOps$.MODULE$:Lscala/collection/StringOps$;
        37: getstatic     #38                 // Field scala/Predef$.MODULE$:Lscala/Predef$;
        40: ldc           #149                // String &%s;
        42: invokevirtual #153                // Method scala/Predef$.augmentString:(Ljava/lang/String;)Ljava/lang/String;
        45: getstatic     #47                 // Field scala/runtime/ScalaRunTime$.MODULE$:Lscala/runtime/ScalaRunTime$;
        48: iconst_1
        49: anewarray     #4                  // class java/lang/Object
        52: dup
        53: iconst_0
        54: aload_3
        55: aastore
        56: invokevirtual #157                // Method scala/runtime/ScalaRunTime$.genericWrapArray:(Ljava/lang/Object;)Lscala/collection/immutable/ArraySeq;
        59: invokevirtual #161                // Method scala/collection/StringOps$.format$extension:(Ljava/lang/String;Lscala/collection/immutable/Seq;)Ljava/lang/String;
        62: invokevirtual #68                 // Method scala/Predef$ArrowAssoc$.$minus$greater$extension:(Ljava/lang/Object;Ljava/lang/Object;)Lscala/Tuple2;
        65: astore_1
        66: goto          81
        69: goto          72
        72: new           #163                // class scala/MatchError
        75: dup
        76: aload_2
        77: invokespecial #166                // Method scala/MatchError."<init>":(Ljava/lang/Object;)V
        80: athrow
        81: aload_1
        82: areturn
      StackMapTable: number_of_entries = 3
        frame_type = 253 /* append */
          offset_delta = 69
          locals = [ top, class scala/Tuple2 ]
        frame_type = 2 /* same */
        frame_type = 255 /* full_frame */
          offset_delta = 8
          locals = [ class scala/Tuple2, class scala/Tuple2, class scala/Tuple2, class java/lang/String, int ]
          stack = []
      LineNumberTable:
        line 114: 0
      LocalVariableTable:
        Start  Length  Slot  Name   Signature
           14      55     3     s   Ljava/lang/String;
           20      49     4     c   C
            0      83     0  x0$1   Lscala/Tuple2;
    MethodParameters:
      Name                           Flags
      x0$1                           final

  public scala.xml.Utility$Escapes$();
    descriptor: ()V
    flags: (0x0001) ACC_PUBLIC
    Code:
      stack=1, locals=1, args_size=1
         0: aload_0
         1: invokespecial #172                // Method java/lang/Object."<init>":()V
         4: return
      LineNumberTable:
        line 117: 0
        line 102: 4
      LocalVariableTable:
        Start  Length  Slot  Name   Signature
            0       5     0  this   Lscala/xml/Utility$Escapes$;

  private static java.lang.Object $deserializeLambda$(java.lang.invoke.SerializedLambda);
    descriptor: (Ljava/lang/invoke/SerializedLambda;)Ljava/lang/Object;
    flags: (0x100a) ACC_PRIVATE, ACC_STATIC, ACC_SYNTHETIC
    Code:
      stack=1, locals=1, args_size=1
         0: aload_0
         1: invokedynamic #184,  0            // InvokeDynamic #1:lambdaDeserialize:(Ljava/lang/invoke/SerializedLambda;)Ljava/lang/Object;
         6: areturn
}
InnerClasses:
  public static final #10= #7 of #9;      // Lookup=class java/lang/invoke/MethodHandles$Lookup of class java/lang/invoke/MethodHandles
  public static #15= #12 of #14;          // ArrowAssoc$=class scala/Predef$ArrowAssoc$ of class scala/Predef
  public static #18= #2 of #17;           // Escapes$=class scala/xml/Utility$Escapes$ of class scala/xml/Utility
SourceFile: "Utility.scala"
BootstrapMethods:
  0: #115 REF_invokeStatic java/lang/invoke/LambdaMetafactory.altMetafactory:(Ljava/lang/invoke/MethodHandles$Lookup;Ljava/lang/String;Ljava/lang/invoke/MethodType;[Ljava/lang/Object;)Ljava/lang/invoke/CallSite;
    Method arguments:
      #100 (Ljava/lang/Object;)Ljava/lang/Object;
      #105 REF_invokeStatic scala/xml/Utility$Escapes$.$anonfun$escMap$1:(Lscala/Tuple2;)Lscala/Tuple2;
      #106 (Lscala/Tuple2;)Lscala/Tuple2;
      #107 5
      #108 1
      #106 (Lscala/Tuple2;)Lscala/Tuple2;
  1: #181 REF_invokeStatic scala/runtime/LambdaDeserialize.bootstrap:(Ljava/lang/invoke/MethodHandles$Lookup;Ljava/lang/String;Ljava/lang/invoke/MethodType;[Ljava/lang/invoke/MethodHandle;)Ljava/lang/invoke/CallSite;
    Method arguments:
      #105 REF_invokeStatic scala/xml/Utility$Escapes$.$anonfun$escMap$1:(Lscala/Tuple2;)Lscala/Tuple2;
  ScalaInlineInfo: length = 0x1D (unknown attribute)
   01 01 00 05 00 65 00 66 01 00 1D 00 1C 01 00 18
   00 5D 01 00 15 00 5D 01 00 1A 00 5D 01
  Scala: length = 0x0 (unknown attribute)

