Classfile /Users/mw/Projects/slang-braindump/.jar/jar11/assemble/slang-braindump/assemble/content/org/scalatest/funspec/AsyncFunSpecLike.class
  Last modified May 29, 2022; size 20955 bytes
  SHA-256 checksum 3e25dfe32bb18a7db4d49bcb1c100d639e49e931df6af5b8962461c547958594
  Compiled from "AsyncFunSpecLike.scala"
public interface org.scalatest.funspec.AsyncFunSpecLike extends org.scalatest.AsyncTestSuite,org.scalatest.AsyncTestRegistration,org.scalatest.Informing,org.scalatest.Notifying,org.scalatest.Alerting,org.scalatest.Documenting
  minor version: 0
  major version: 52
  flags: (0x0601) ACC_PUBLIC, ACC_INTERFACE, ACC_ABSTRACT
  this_class: #2                          // org/scalatest/funspec/AsyncFunSpecLike
  super_class: #4                         // java/lang/Object
  interfaces: 6, fields: 0, methods: 59, attributes: 6
Constant pool:
    #1 = Utf8               org/scalatest/funspec/AsyncFunSpecLike
    #2 = Class              #1            // org/scalatest/funspec/AsyncFunSpecLike
    #3 = Utf8               java/lang/Object
    #4 = Class              #3            // java/lang/Object
    #5 = Utf8               org/scalatest/AsyncTestSuite
    #6 = Class              #5            // org/scalatest/AsyncTestSuite
    #7 = Utf8               org/scalatest/AsyncTestRegistration
    #8 = Class              #7            // org/scalatest/AsyncTestRegistration
    #9 = Utf8               org/scalatest/Informing
   #10 = Class              #9            // org/scalatest/Informing
   #11 = Utf8               org/scalatest/Notifying
   #12 = Class              #11           // org/scalatest/Notifying
   #13 = Utf8               org/scalatest/Alerting
   #14 = Class              #13           // org/scalatest/Alerting
   #15 = Utf8               org/scalatest/Documenting
   #16 = Class              #15           // org/scalatest/Documenting
   #17 = Utf8               AsyncFunSpecLike.scala
   #18 = Utf8               Lorg/scalatest/Finders;
   #19 = Utf8               value
   #20 = Utf8               org.scalatest.finders.FunSpecFinder
   #21 = Utf8               Lscala/reflect/ScalaSignature;
   #22 = Utf8               bytes
   #23 = Utf8               \u0006\u0005\t\rgaB\u0014)!\u0003\r\ta\f\u0005\u0006\u0013\u0002!\tA\u0013\u0005\b\u001d\u0002\u0011\r\u0011\"\u0004P\u0011\u0015\u0019\u0006\u0001\"\u0005U\u0011\u0015A\u0006\u0001\"\u0005Z\u0011\u0015i\u0006\u0001\"\u0005_\u0011\u0015\u0011\u0007\u0001\"\u0005d\u0011\u00159\u0007\u0001\"\u0004i\u0011\u001d\t)\u0004\u0001C\u0003\u0003oAq!!\u0012\u0001\t\u001b\t9\u0005C\u0004\u0002T\u0001!)!!\u0016\u0007\r\u0005\r\u0004\u0001CA3\u0011\u001d\t9g\u0003C\u0001\u0003SBq!a\u001c\f\t\u001b\t\t\bC\u0004\u0002\u0000-!\t!!!\t\u000f\u0005=5\u0002\"\u0001\u0002\u0012\"9\u00111U\u0006\u0005\u0002\u0005\u0015\u0006\"CAU\u0001\t\u0007I\u0011CAV\r\u0019\ti\u000b\u0001\u0005\u00020\"9\u0011q\r\n\u0005\u0002\u0005E\u0006bBA8%\u00115\u0011Q\u0017\u0005\b\u0003\u007f\u0012B\u0011AAa\u0011\u001d\tyI\u0005C\u0001\u0003\u001fDq!a)\u0013\t\u0003\t\u0019\u000eC\u0005\u0002X\u0002\u0011\r\u0011\"\u0005\u0002Z\"9\u00111\u001c\u0001\u0005\u000e\u0005u\u0007bBAu\u0001\u0011E\u00111\u001e\u0005\b\u0003s\u0004AQBA~\u0011\u001d\u0011Y\u0001\u0001C\t\u0005\u001bAqA!\u0007\u0001\t\u0003\u0012Y\u0002C\u0004\u0003$\u0001!\tF!\n\t\u000f\tm\u0002\u0001\"\u0011\u0003>!9!Q\t\u0001\u0005R\t\u001d\u0003b\u0002B*\u0001\u0011\u0005#Q\u000b\u0005\n\u00057\u0002!\u0019!C\t\u0005;B\u0011Ba\u0018\u0001\u0005\u0004%)E!\u0019\t\u000f\t]\u0004\u0001\"\u0011\u0003z!I!Q\u0012\u0001\u0012\u0002\u0013\u0005!q\u0012\u0005\u000f\u0005K\u0003\u0001\u0013aA\u0001\u0002\u0013%!q\u0015BW\u0005A\t5/\u001f8d\rVt7\u000b]3d\u0019&\\WM\u0003\u0002*U\u00059a-\u001e8ta\u0016\u001c\'BA\u0016-\u0003%\u00198-\u00197bi\u0016\u001cHOC\u0001.\u0003\ry\'oZ\u0002\u0001\'!\u0001\u0001G\u000e\u001e>\u0001\u000e3\u0005CA\u00195\u001b\u0005\u0011$\"A\u001a\u0002\u000bM\u001c\u0017\r\\1\n\u0005U\u0012$AB!osJ+g\r\u0005\u00028q5\t!&\u0003\u0002:U\tq\u0011i]=oGR+7\u000f^*vSR,\u0007CA\u001c<\u0013\ta$FA\u000bBgft7\rV3tiJ+w-[:ue\u0006$\u0018n\u001c8\u0011\u0005]r\u0014BA +\u0005%IeNZ8s[&tw\r\u0005\u00028\u0003&\u0011!I\u000b\u0002\n\u001d>$\u0018NZ=j]\u001e\u0004\"a\u000e#\n\u0005\u0015S#\u0001C!mKJ$\u0018N\\4\u0011\u0005]:\u0015B\u0001%+\u0005-!unY;nK:$\u0018N\\4\u0002\r\u0011Jg.\u001b;%)\u0005Y\u0005CA\u0019M\u0013\ti%G\u0001\u0003V]&$\u0018AB3oO&tW-F\u0001Q!\t9\u0014+\u0003\u0002SU\tY\u0011i]=oG\u0016sw-\u001b8f\u0003\u0011IgNZ8\u0016\u0003U\u0003\"a\u000e,\n\u0005]S#\u0001C%oM>\u0014X.\u001a:\u0002\t9|G/Z\u000b\u00025B\u0011qgW\u0005\u00039*\u0012\u0001BT8uS\u001aLWM]\u0001\u0006C2,\'\u000f^\u000b\u0002?B\u0011q\u0007Y\u0005\u0003C*\u0012q!\u00117feR,\'/\u0001\u0004nCJ\\W\u000f]\u000b\u0002IB\u0011q\'Z\u0005\u0003M*\u0012!\u0002R8dk6,g\u000e^3s\u0003U\u0011XmZ5ti\u0016\u0014\u0018i]=oGR+7\u000f^%na2$R![A\u0006\u0003K!2a\u00136|\u0011\u0019Yw\u0001\"a\u0001Y\u00069A/Z:u\rVt\u0007cA\u0019n_&\u0011aN\r\u0002\ty\tLh.Y7f}A\u0019\u0001o];\u000e\u0003ET!A\u001d\u001a\u0002\u0015\r|gnY;se\u0016tG/\u0003\u0002uc\n1a)\u001e;ve\u0016\u0004\"A^=\u000e\u0003]T!\u0001\u001f\u0016\u0002\u0015\r|W\u000e]1uS\ndW-\u0003\u0002{o\nI\u0011i]:feRLwN\u001c\u0005\u0006y\u001e\u0001\r!`\u0001\u0004a>\u001c\bc\u0001@\u0002\b5\tqP\u0003\u0003\u0002\u0002\u0005\r\u0011AB:pkJ\u001cWMC\u0002\u0002\u00061\n\u0011b]2bY\u0006\u001cG/[2\n\u0007\u0005%qP\u0001\u0005Q_NLG/[8o\u0011\u001d\tia\u0002a\u0001\u0003\u001f\t\u0001\u0002^3tiR+\u0007\u0010\u001e\t\u0005\u0003#\tyB\u0004\u0003\u0002\u0014\u0005m\u0001cAA\u000be5\u0011\u0011q\u0003\u0006\u0004\u00033q\u0013A\u0002\u001fs_>$h(C\u0002\u0002\u001eI\na\u0001\u0015:fI\u00164\u0017\u0002BA\u0011\u0003G\u0011aa\u0015;sS:<\'bAA\u000fe!9\u0011qE\u0004A\u0002\u0005%\u0012\u0001\u0003;fgR$\u0016mZ:\u0011\u000bE\nY#a\f\n\u0007\u00055\"G\u0001\u0006=e\u0016\u0004X-\u0019;fIz\u00022aNA\u0019\u0013\r\t\u0019D\u000b\u0002\u0004)\u0006<\u0017!\u0005:fO&\u001cH/\u001a:Bgft7\rV3tiR1\u0011\u0011HA!\u0003\u0007\"B!a\u000f\u0002@Q\u00191*!\u0010\t\u000bqD\u00019A?\t\r-DA\u00111\u0001m\u0011\u001d\ti\u0001\u0003a\u0001\u0003\u001fAq!a\n\t\u0001\u0004\tI#\u0001\u000fsK\u001eL7\u000f^3s\u0013\u001etwN]3e\u0003NLhn\u0019+fgRLU\u000e\u001d7\u0015\r\u0005%\u0013qJA))\u0015Y\u00151JA\'\u0011\u0019Y\u0017\u0002\"a\u0001Y\")A0\u0003a\u0001{\"9\u0011QB\u0005A\u0002\u0005=\u0001bBA\u0014\u0013\u0001\u0007\u0011\u0011F\u0001\u0019e\u0016<\u0017n\u001d;fe&;gn\u001c:fI\u0006\u001b\u0018P\\2UKN$HCBA,\u0003?\n\t\u0007\u0006\u0003\u0002Z\u0005uCcA&\u0002\\!)AP\u0003a\u0002{\"11N\u0003CA\u00021Dq!!\u0004\u000b\u0001\u0004\ty\u0001C\u0004\u0002()\u0001\r!!\u000b\u0003\r%#xk\u001c:e\'\tY\u0001\'\u0001\u0004=S:LGO\u0010\u000b\u0003\u0003W\u00022!!\u001c\f\u001b\u0005\u0001\u0011!C1qa2L\u0018*\u001c9m)\u0019\t\u0019(!\u001f\u0002~Q)1*!\u001e\u0002x!11.\u0004CA\u00021DQ\u0001`\u0007A\u0002uDq!a\u001f\u000e\u0001\u0004\ty!\u0001\u0005ta\u0016\u001cG+\u001a=u\u0011\u001d\t9#\u0004a\u0001\u0003S\tQ!\u00199qYf$b!a!\u0002\f\u00065E\u0003BAC\u0003\u0013#2aSAD\u0011\u0015ah\u0002q\u0001~\u0011\u0019Yg\u0002\"a\u0001Y\"9\u00111\u0010\bA\u0002\u0005=\u0001bBA\u0014\u001d\u0001\u0007\u0011\u0011F\u0001\u0007g\"|W\u000f\u001c3\u0015\t\u0005M\u0015q\u0014\t\u0005\u0003+\u000bY*\u0004\u0002\u0002\u0018*\u0019\u0011\u0011\u0014\u0016\u0002\u000bY,\'OY:\n\t\u0005u\u0015q\u0013\u0002\u000b\u0005\u0016D\u0017M^3X_J$\u0007bBAQ\u001f\u0001\u0007\u00111S\u0001\u000bE\u0016D\u0017M^3X_J$\u0017\u0001B7vgR$B!a%\u0002(\"9\u0011\u0011\u0015\tA\u0002\u0005M\u0015AA5u+\t\tYG\u0001\u0005UQ\u0016Lxk\u001c:e\'\t\u0011\u0002\u0007\u0006\u0002\u00024B\u0019\u0011Q\u000e\n\u0015\r\u0005]\u0016QXA`)\u0015Y\u0015\u0011XA^\u0011\u0019YG\u0003\"a\u0001Y\")A\u0010\u0006a\u0001{\"9\u00111\u0010\u000bA\u0002\u0005=\u0001bBA\u0014)\u0001\u0007\u0011\u0011\u0006\u000b\u0007\u0003\u0007\fY-!4\u0015\t\u0005\u0015\u0017\u0011\u001a\u000b\u0004\u0017\u0006\u001d\u0007\"\u0002?\u0016\u0001\bi\bBB6\u0016\t\u0003\u0007A\u000eC\u0004\u0002|U\u0001\r!a\u0004\t\u000f\u0005\u001dR\u00031\u0001\u0002*Q!\u00111SAi\u0011\u001d\t\tK\u0006a\u0001\u0003\'#B!a%\u0002V\"9\u0011\u0011U\fA\u0002\u0005M\u0015\u0001\u0002;iKf,\"!a-\u0002\u0015%<gn\u001c:f\u00136\u0004H\u000e\u0006\u0004\u0002`\u0006\u0015\u0018q\u001d\u000b\u0006\u0017\u0006\u0005\u00181\u001d\u0005\u0007Wf!\t\u0019\u00017\t\u000bqL\u0002\u0019A?\t\u000f\u00055\u0011\u00041\u0001\u0002\u0010!9\u0011qE\rA\u0002\u0005%\u0012AB5h]>\u0014X\r\u0006\u0004\u0002n\u0006U\u0018q\u001f\u000b\u0005\u0003_\f\u0019\u0010F\u0002L\u0003cDQ\u0001 \u000eA\u0004uDaa\u001b\u000e\u0005\u0002\u0004a\u0007bBA\u00075\u0001\u0007\u0011q\u0002\u0005\b\u0003OQ\u0002\u0019AA\u0015\u00031!Wm]2sS\n,\u0017*\u001c9m)\u0011\tiPa\u0002\u0015\u000b-\u000byP!\u0002\t\u0011\t\u00051\u0004\"a\u0001\u0005\u0007\t1AZ;o!\r\tTn\u0013\u0005\u0006yn\u0001\r! \u0005\b\u0005\u0013Y\u0002\u0019AA\b\u0003-!Wm]2sSB$\u0018n\u001c8\u0002\u0011\u0011,7o\u0019:jE\u0016$BAa\u0004\u0003\u0018Q!!\u0011\u0003B\u000b)\rY%1\u0003\u0005\u0006yr\u0001\u001d! \u0005\t\u0005\u0003aB\u00111\u0001\u0003\u0004!9!\u0011\u0002\u000fA\u0002\u0005=\u0011!\u0003;fgRt\u0015-\\3t+\t\u0011i\u0002\u0005\u0004\u0002\u0012\t}\u0011qB\u0005\u0005\u0005C\t\u0019CA\u0002TKR\fqA];o)\u0016\u001cH\u000f\u0006\u0004\u0003(\t5\"\u0011\u0007\t\u0004o\t%\u0012b\u0001B\u0016U\t11\u000b^1ukNDqAa\f\u001f\u0001\u0004\ty!\u0001\u0005uKN$h*Y7f\u0011\u001d\u0011\u0019D\ba\u0001\u0005k\tA!\u0019:hgB\u0019qGa\u000e\n\u0007\te\"F\u0001\u0003Be\u001e\u001c\u0018\u0001\u0002;bON,\"Aa\u0010\u0011\u0011\u0005E!\u0011IA\b\u0005;IAAa\u0011\u0002$\t\u0019Q*\u00199\u0002\u0011I,h\u000eV3tiN$bAa\n\u0003J\tE\u0003b\u0002B\u0018A\u0001\u0007!1\n\t\u0006c\t5\u0013qB\u0005\u0004\u0005\u001f\u0012$AB(qi&|g\u000eC\u0004\u00034\u0001\u0002\rA!\u000e\u0002\u0007I,h\u000e\u0006\u0004\u0003(\t]#\u0011\f\u0005\b\u0005_\t\u0003\u0019\u0001B&\u0011\u001d\u0011\u0019$\ta\u0001\u0005k\taAY3iCZ,WCAAJ\u0003%\u0019H/\u001f7f\u001d\u0006lW-\u0006\u0002\u0002\u0010!Z1E!\u001a\u0003l\t5$\u0011\u000fB:!\r\t$qM\u0005\u0004\u0005S\u0012$A\u00033faJ,7-\u0019;fI\u00069Q.Z:tC\u001e,\u0017E\u0001B8\u0003q$\u0006.\u001a\u0011tifdWMT1nK\u0002b\u0017NZ3ds\u000edW\rI7fi\"|G\r\t5bg\u0002\u0012W-\u001a8!I\u0016\u0004(/Z2bi\u0016$\u0007%\u00198eA]LG\u000e\u001c\u0011cK\u0002\u0012X-\\8wK\u0012\u0004\u0013N\u001c\u0011bA\u0019,H/\u001e:fAY,\'o]5p]\u0002zg\rI*dC2\fG+Z:uA]LG\u000f\u001b\u0011o_\u0002\u0012X\r\u001d7bG\u0016lWM\u001c;/\u0003\u0015\u0019\u0018N\\2fC\t\u0011)(A\u00034]Er\u0003\'A\u0006uKN$H)\u0019;b\r>\u0014HC\u0002B>\u0005\u0003\u0013\u0019\tE\u00028\u0005{J1Aa +\u0005!!Vm\u001d;ECR\f\u0007b\u0002B\u0018I\u0001\u0007\u0011q\u0002\u0005\n\u0005\u000b#\u0003\u0013!a\u0001\u0005\u000f\u000bA\u0002\u001e5f\u0007>tg-[4NCB\u00042a\u000eBE\u0013\r\u0011YI\u000b\u0002\n\u0007>tg-[4NCB\fQ\u0003^3ti\u0012\u000bG/\u0019$pe\u0012\"WMZ1vYR$#\'\u0006\u0002\u0003\u0012*\"!q\u0011BJW\t\u0011)\n\u0005\u0003\u0003\u0018\n\u0005VB\u0001BM\u0015\u0011\u0011YJ!(\u0002\u0013Ut7\r[3dW\u0016$\'b\u0001BPe\u0005Q\u0011M\u001c8pi\u0006$\u0018n\u001c8\n\t\t\r&\u0011\u0014\u0002\u0012k:\u001c\u0007.Z2lK\u00124\u0016M]5b]\u000e,\u0017!C:va\u0016\u0014HE];o)\u0019\u00119C!+\u0003,\"9!q\u0006\u0014A\u0002\t-\u0003b\u0002B\u001aM\u0001\u0007!QG\u0005\u0005\u0005\'\u0012y+C\u0002\u00032*\u0012QaU;ji\u0016Ds\u0001\u0001B[\u0005w\u0013i\fE\u00028\u0005oK1A!/+\u0005\u001d1\u0015N\u001c3feN\fQA^1mk\u0016d#Aa0\"\u0005\t\u0005\u0017aI8sO:\u001a8-\u00197bi\u0016\u001cHO\f4j]\u0012,\'o\u001d\u0018Gk:\u001c\u0006/Z2GS:$WM\u001d
   #24 = Utf8               java/lang/invoke/MethodHandles$Lookup
   #25 = Class              #24           // java/lang/invoke/MethodHandles$Lookup
   #26 = Utf8               java/lang/invoke/MethodHandles
   #27 = Class              #26           // java/lang/invoke/MethodHandles
   #28 = Utf8               Lookup
   #29 = Utf8               org/scalatest/AsyncSuperEngine$Bundle
   #30 = Class              #29           // org/scalatest/AsyncSuperEngine$Bundle
   #31 = Utf8               org/scalatest/AsyncSuperEngine
   #32 = Class              #31           // org/scalatest/AsyncSuperEngine
   #33 = Utf8               Bundle
   #34 = Utf8               org/scalatest/AsyncSuperEngine$TestLeaf
   #35 = Class              #34           // org/scalatest/AsyncSuperEngine$TestLeaf
   #36 = Utf8               TestLeaf
   #37 = Utf8               org/scalatest/AsyncTestSuite$NoArgAsyncTest
   #38 = Class              #37           // org/scalatest/AsyncTestSuite$NoArgAsyncTest
   #39 = Utf8               NoArgAsyncTest
   #40 = Utf8               org/scalatest/funspec/AsyncFunSpecLike$$anon$1
   #41 = Class              #40           // org/scalatest/funspec/AsyncFunSpecLike$$anon$1
   #42 = Utf8               org/scalatest/funspec/AsyncFunSpecLike$ItWord
   #43 = Class              #42           // org/scalatest/funspec/AsyncFunSpecLike$ItWord
   #44 = Utf8               ItWord
   #45 = Utf8               org/scalatest/funspec/AsyncFunSpecLike$TheyWord
   #46 = Class              #45           // org/scalatest/funspec/AsyncFunSpecLike$TheyWord
   #47 = Utf8               TheyWord
   #48 = Utf8               org$scalatest$funspec$AsyncFunSpecLike$_setter_$org$scalatest$funspec$AsyncFunSpecLike$$engine_$eq
   #49 = Utf8               (Lorg/scalatest/AsyncEngine;)V
   #50 = Utf8               x$1
   #51 = Utf8               org$scalatest$funspec$AsyncFunSpecLike$_setter_$it_$eq
   #52 = Utf8               (Lorg/scalatest/funspec/AsyncFunSpecLike$ItWord;)V
   #53 = Utf8               org$scalatest$funspec$AsyncFunSpecLike$_setter_$they_$eq
   #54 = Utf8               (Lorg/scalatest/funspec/AsyncFunSpecLike$TheyWord;)V
   #55 = Utf8               org$scalatest$funspec$AsyncFunSpecLike$_setter_$behave_$eq
   #56 = Utf8               (Lorg/scalatest/verbs/BehaveWord;)V
   #57 = Utf8               org$scalatest$funspec$AsyncFunSpecLike$_setter_$styleName_$eq
   #58 = Utf8               (Ljava/lang/String;)V
   #59 = Utf8               org$scalatest$funspec$AsyncFunSpecLike$$super$run
   #60 = Utf8               (Lscala/Option;Lorg/scalatest/Args;)Lorg/scalatest/Status;
   #61 = Utf8               testName
   #62 = Utf8               args
   #63 = Utf8               org$scalatest$funspec$AsyncFunSpecLike$$engine
   #64 = Utf8               ()Lorg/scalatest/AsyncEngine;
   #65 = Utf8               info$
   #66 = Utf8               (Lorg/scalatest/funspec/AsyncFunSpecLike;)Lorg/scalatest/Informer;
   #67 = Utf8               $this
   #68 = Utf8               info
   #69 = Utf8               ()Lorg/scalatest/Informer;
   #70 = NameAndType        #68:#69       // info:()Lorg/scalatest/Informer;
   #71 = InterfaceMethodref #2.#70        // org/scalatest/funspec/AsyncFunSpecLike.info:()Lorg/scalatest/Informer;
   #72 = Utf8               Lorg/scalatest/funspec/AsyncFunSpecLike;
   #73 = NameAndType        #63:#64       // org$scalatest$funspec$AsyncFunSpecLike$$engine:()Lorg/scalatest/AsyncEngine;
   #74 = InterfaceMethodref #2.#73        // org/scalatest/funspec/AsyncFunSpecLike.org$scalatest$funspec$AsyncFunSpecLike$$engine:()Lorg/scalatest/AsyncEngine;
   #75 = Utf8               org/scalatest/AsyncEngine
   #76 = Class              #75           // org/scalatest/AsyncEngine
   #77 = Utf8               atomicInformer
   #78 = Utf8               ()Ljava/util/concurrent/atomic/AtomicReference;
   #79 = NameAndType        #77:#78       // atomicInformer:()Ljava/util/concurrent/atomic/AtomicReference;
   #80 = Methodref          #76.#79       // org/scalatest/AsyncEngine.atomicInformer:()Ljava/util/concurrent/atomic/AtomicReference;
   #81 = Utf8               java/util/concurrent/atomic/AtomicReference
   #82 = Class              #81           // java/util/concurrent/atomic/AtomicReference
   #83 = Utf8               get
   #84 = Utf8               ()Ljava/lang/Object;
   #85 = NameAndType        #83:#84       // get:()Ljava/lang/Object;
   #86 = Methodref          #82.#85       // java/util/concurrent/atomic/AtomicReference.get:()Ljava/lang/Object;
   #87 = Utf8               org/scalatest/Informer
   #88 = Class              #87           // org/scalatest/Informer
   #89 = Utf8               this
   #90 = Utf8               note$
   #91 = Utf8               (Lorg/scalatest/funspec/AsyncFunSpecLike;)Lorg/scalatest/Notifier;
   #92 = Utf8               note
   #93 = Utf8               ()Lorg/scalatest/Notifier;
   #94 = NameAndType        #92:#93       // note:()Lorg/scalatest/Notifier;
   #95 = InterfaceMethodref #2.#94        // org/scalatest/funspec/AsyncFunSpecLike.note:()Lorg/scalatest/Notifier;
   #96 = Utf8               atomicNotifier
   #97 = NameAndType        #96:#78       // atomicNotifier:()Ljava/util/concurrent/atomic/AtomicReference;
   #98 = Methodref          #76.#97       // org/scalatest/AsyncEngine.atomicNotifier:()Ljava/util/concurrent/atomic/AtomicReference;
   #99 = Utf8               org/scalatest/Notifier
  #100 = Class              #99           // org/scalatest/Notifier
  #101 = Utf8               alert$
  #102 = Utf8               (Lorg/scalatest/funspec/AsyncFunSpecLike;)Lorg/scalatest/Alerter;
  #103 = Utf8               alert
  #104 = Utf8               ()Lorg/scalatest/Alerter;
  #105 = NameAndType        #103:#104     // alert:()Lorg/scalatest/Alerter;
  #106 = InterfaceMethodref #2.#105       // org/scalatest/funspec/AsyncFunSpecLike.alert:()Lorg/scalatest/Alerter;
  #107 = Utf8               atomicAlerter
  #108 = NameAndType        #107:#78      // atomicAlerter:()Ljava/util/concurrent/atomic/AtomicReference;
  #109 = Methodref          #76.#108      // org/scalatest/AsyncEngine.atomicAlerter:()Ljava/util/concurrent/atomic/AtomicReference;
  #110 = Utf8               org/scalatest/Alerter
  #111 = Class              #110          // org/scalatest/Alerter
  #112 = Utf8               markup$
  #113 = Utf8               (Lorg/scalatest/funspec/AsyncFunSpecLike;)Lorg/scalatest/Documenter;
  #114 = Utf8               markup
  #115 = Utf8               ()Lorg/scalatest/Documenter;
  #116 = NameAndType        #114:#115     // markup:()Lorg/scalatest/Documenter;
  #117 = InterfaceMethodref #2.#116       // org/scalatest/funspec/AsyncFunSpecLike.markup:()Lorg/scalatest/Documenter;
  #118 = Utf8               atomicDocumenter
  #119 = NameAndType        #118:#78      // atomicDocumenter:()Ljava/util/concurrent/atomic/AtomicReference;
  #120 = Methodref          #76.#119      // org/scalatest/AsyncEngine.atomicDocumenter:()Ljava/util/concurrent/atomic/AtomicReference;
  #121 = Utf8               org/scalatest/Documenter
  #122 = Class              #121          // org/scalatest/Documenter
  #123 = Utf8               registerAsyncTestImpl
  #124 = Utf8               (Ljava/lang/String;Lscala/collection/immutable/Seq;Lscala/Function0;Lorg/scalactic/source/Position;)V
  #125 = Utf8               (Ljava/lang/String;Lscala/collection/immutable/Seq<Lorg/scalatest/Tag;>;Lscala/Function0<Lscala/concurrent/Future<Lorg/scalatest/compatible/Assertion;>;>;Lorg/scalactic/source/Position;)V
  #126 = Utf8               testText
  #127 = Utf8               testTags
  #128 = Utf8               testFun
  #129 = Utf8               pos
  #130 = Utf8               transformToOutcome
  #131 = Utf8               (Lscala/Function0;)Lscala/Function0;
  #132 = NameAndType        #130:#131     // transformToOutcome:(Lscala/Function0;)Lscala/Function0;
  #133 = InterfaceMethodref #2.#132       // org/scalatest/funspec/AsyncFunSpecLike.transformToOutcome:(Lscala/Function0;)Lscala/Function0;
  #134 = MethodType         #84           //  ()Ljava/lang/Object;
  #135 = Utf8               $anonfun$registerAsyncTestImpl$1
  #136 = Utf8               ()Ljava/lang/String;
  #137 = NameAndType        #135:#136     // $anonfun$registerAsyncTestImpl$1:()Ljava/lang/String;
  #138 = InterfaceMethodref #2.#137       // org/scalatest/funspec/AsyncFunSpecLike.$anonfun$registerAsyncTestImpl$1:()Ljava/lang/String;
  #139 = MethodHandle       6:#138        // REF_invokeStatic org/scalatest/funspec/AsyncFunSpecLike.$anonfun$registerAsyncTestImpl$1:()Ljava/lang/String;
  #140 = MethodType         #136          //  ()Ljava/lang/String;
  #141 = Integer            5
  #142 = Integer            1
  #143 = Utf8               java/lang/invoke/LambdaMetafactory
  #144 = Class              #143          // java/lang/invoke/LambdaMetafactory
  #145 = Utf8               altMetafactory
  #146 = Utf8               (Ljava/lang/invoke/MethodHandles$Lookup;Ljava/lang/String;Ljava/lang/invoke/MethodType;[Ljava/lang/Object;)Ljava/lang/invoke/CallSite;
  #147 = NameAndType        #145:#146     // altMetafactory:(Ljava/lang/invoke/MethodHandles$Lookup;Ljava/lang/String;Ljava/lang/invoke/MethodType;[Ljava/lang/Object;)Ljava/lang/invoke/CallSite;
  #148 = Methodref          #144.#147     // java/lang/invoke/LambdaMetafactory.altMetafactory:(Ljava/lang/invoke/MethodHandles$Lookup;Ljava/lang/String;Ljava/lang/invoke/MethodType;[Ljava/lang/Object;)Ljava/lang/invoke/CallSite;
  #149 = MethodHandle       6:#148        // REF_invokeStatic java/lang/invoke/LambdaMetafactory.altMetafactory:(Ljava/lang/invoke/MethodHandles$Lookup;Ljava/lang/String;Ljava/lang/invoke/MethodType;[Ljava/lang/Object;)Ljava/lang/invoke/CallSite;
  #150 = Utf8               apply
  #151 = Utf8               ()Lscala/Function0;
  #152 = NameAndType        #150:#151     // apply:()Lscala/Function0;
  #153 = InvokeDynamic      #0:#152       // #0:apply:()Lscala/Function0;
  #154 = Utf8               scala/None$
  #155 = Class              #154          // scala/None$
  #156 = Utf8               MODULE$
  #157 = Utf8               Lscala/None$;
  #158 = NameAndType        #156:#157     // MODULE$:Lscala/None$;
  #159 = Fieldref           #155.#158     // scala/None$.MODULE$:Lscala/None$;
  #160 = Utf8               registerAsyncTest
  #161 = Utf8               (Ljava/lang/String;Ljava/lang/Object;Lscala/Function0;Lscala/Option;Lscala/Option;Lorg/scalactic/source/Position;Lscala/collection/immutable/Seq;)Ljava/lang/String;
  #162 = NameAndType        #160:#161     // registerAsyncTest:(Ljava/lang/String;Ljava/lang/Object;Lscala/Function0;Lscala/Option;Lscala/Option;Lorg/scalactic/source/Position;Lscala/collection/immutable/Seq;)Ljava/lang/String;
  #163 = Methodref          #76.#162      // org/scalatest/AsyncEngine.registerAsyncTest:(Ljava/lang/String;Ljava/lang/Object;Lscala/Function0;Lscala/Option;Lscala/Option;Lorg/scalactic/source/Position;Lscala/collection/immutable/Seq;)Ljava/lang/String;
  #164 = Utf8               Ljava/lang/String;
  #165 = Utf8               Lscala/collection/immutable/Seq;
  #166 = Utf8               Lscala/Function0;
  #167 = Utf8               Lorg/scalactic/source/Position;
  #168 = Utf8               registerAsyncTest$
  #169 = Utf8               (Lorg/scalatest/funspec/AsyncFunSpecLike;Ljava/lang/String;Lscala/collection/immutable/Seq;Lscala/Function0;Lorg/scalactic/source/Position;)V
  #170 = NameAndType        #160:#124     // registerAsyncTest:(Ljava/lang/String;Lscala/collection/immutable/Seq;Lscala/Function0;Lorg/scalactic/source/Position;)V
  #171 = InterfaceMethodref #2.#170       // org/scalatest/funspec/AsyncFunSpecLike.registerAsyncTest:(Ljava/lang/String;Lscala/collection/immutable/Seq;Lscala/Function0;Lorg/scalactic/source/Position;)V
  #172 = NameAndType        #123:#124     // registerAsyncTestImpl:(Ljava/lang/String;Lscala/collection/immutable/Seq;Lscala/Function0;Lorg/scalactic/source/Position;)V
  #173 = InterfaceMethodref #2.#172       // org/scalatest/funspec/AsyncFunSpecLike.registerAsyncTestImpl:(Ljava/lang/String;Lscala/collection/immutable/Seq;Lscala/Function0;Lorg/scalactic/source/Position;)V
  #174 = Utf8               registerIgnoredAsyncTestImpl
  #175 = Utf8               $anonfun$registerIgnoredAsyncTestImpl$1
  #176 = NameAndType        #175:#136     // $anonfun$registerIgnoredAsyncTestImpl$1:()Ljava/lang/String;
  #177 = InterfaceMethodref #2.#176       // org/scalatest/funspec/AsyncFunSpecLike.$anonfun$registerIgnoredAsyncTestImpl$1:()Ljava/lang/String;
  #178 = MethodHandle       6:#177        // REF_invokeStatic org/scalatest/funspec/AsyncFunSpecLike.$anonfun$registerIgnoredAsyncTestImpl$1:()Ljava/lang/String;
  #179 = InvokeDynamic      #1:#152       // #1:apply:()Lscala/Function0;
  #180 = Utf8               registerIgnoredAsyncTest
  #181 = Utf8               (Ljava/lang/String;Ljava/lang/Object;Lscala/Function0;Lscala/Option;Lorg/scalactic/source/Position;Lscala/collection/immutable/Seq;)V
  #182 = NameAndType        #180:#181     // registerIgnoredAsyncTest:(Ljava/lang/String;Ljava/lang/Object;Lscala/Function0;Lscala/Option;Lorg/scalactic/source/Position;Lscala/collection/immutable/Seq;)V
  #183 = Methodref          #76.#182      // org/scalatest/AsyncEngine.registerIgnoredAsyncTest:(Ljava/lang/String;Ljava/lang/Object;Lscala/Function0;Lscala/Option;Lorg/scalactic/source/Position;Lscala/collection/immutable/Seq;)V
  #184 = Utf8               registerIgnoredAsyncTest$
  #185 = NameAndType        #180:#124     // registerIgnoredAsyncTest:(Ljava/lang/String;Lscala/collection/immutable/Seq;Lscala/Function0;Lorg/scalactic/source/Position;)V
  #186 = InterfaceMethodref #2.#185       // org/scalatest/funspec/AsyncFunSpecLike.registerIgnoredAsyncTest:(Ljava/lang/String;Lscala/collection/immutable/Seq;Lscala/Function0;Lorg/scalactic/source/Position;)V
  #187 = NameAndType        #174:#124     // registerIgnoredAsyncTestImpl:(Ljava/lang/String;Lscala/collection/immutable/Seq;Lscala/Function0;Lorg/scalactic/source/Position;)V
  #188 = InterfaceMethodref #2.#187       // org/scalatest/funspec/AsyncFunSpecLike.registerIgnoredAsyncTestImpl:(Ljava/lang/String;Lscala/collection/immutable/Seq;Lscala/Function0;Lorg/scalactic/source/Position;)V
  #189 = Utf8               it
  #190 = Utf8               ()Lorg/scalatest/funspec/AsyncFunSpecLike$ItWord;
  #191 = Utf8               they
  #192 = Utf8               ()Lorg/scalatest/funspec/AsyncFunSpecLike$TheyWord;
  #193 = Utf8               ignoreImpl
  #194 = Utf8               $anonfun$ignoreImpl$1
  #195 = NameAndType        #194:#136     // $anonfun$ignoreImpl$1:()Ljava/lang/String;
  #196 = InterfaceMethodref #2.#195       // org/scalatest/funspec/AsyncFunSpecLike.$anonfun$ignoreImpl$1:()Ljava/lang/String;
  #197 = MethodHandle       6:#196        // REF_invokeStatic org/scalatest/funspec/AsyncFunSpecLike.$anonfun$ignoreImpl$1:()Ljava/lang/String;
  #198 = InvokeDynamic      #2:#152       // #2:apply:()Lscala/Function0;
  #199 = Utf8               ignore$
  #200 = Utf8               ignore
  #201 = NameAndType        #200:#124     // ignore:(Ljava/lang/String;Lscala/collection/immutable/Seq;Lscala/Function0;Lorg/scalactic/source/Position;)V
  #202 = InterfaceMethodref #2.#201       // org/scalatest/funspec/AsyncFunSpecLike.ignore:(Ljava/lang/String;Lscala/collection/immutable/Seq;Lscala/Function0;Lorg/scalactic/source/Position;)V
  #203 = NameAndType        #193:#124     // ignoreImpl:(Ljava/lang/String;Lscala/collection/immutable/Seq;Lscala/Function0;Lorg/scalactic/source/Position;)V
  #204 = InterfaceMethodref #2.#203       // org/scalatest/funspec/AsyncFunSpecLike.ignoreImpl:(Ljava/lang/String;Lscala/collection/immutable/Seq;Lscala/Function0;Lorg/scalactic/source/Position;)V
  #205 = Utf8               describeImpl
  #206 = Utf8               (Ljava/lang/String;Lscala/Function0;Lorg/scalactic/source/Position;)V
  #207 = Utf8               (Ljava/lang/String;Lscala/Function0<Lscala/runtime/BoxedUnit;>;Lorg/scalactic/source/Position;)V
  #208 = Utf8               description
  #209 = Utf8               fun
  #210 = Utf8               java/lang/Throwable
  #211 = Class              #210          // java/lang/Throwable
  #212 = Utf8               $anonfun$describeImpl$1
  #213 = NameAndType        #212:#136     // $anonfun$describeImpl$1:()Ljava/lang/String;
  #214 = InterfaceMethodref #2.#213       // org/scalatest/funspec/AsyncFunSpecLike.$anonfun$describeImpl$1:()Ljava/lang/String;
  #215 = MethodHandle       6:#214        // REF_invokeStatic org/scalatest/funspec/AsyncFunSpecLike.$anonfun$describeImpl$1:()Ljava/lang/String;
  #216 = InvokeDynamic      #3:#152       // #3:apply:()Lscala/Function0;
  #217 = Utf8               registerNestedBranch
  #218 = Utf8               (Ljava/lang/String;Lscala/Option;Lscala/Function0;Lscala/Function0;Lscala/Option;Lorg/scalactic/source/Position;)V
  #219 = NameAndType        #217:#218     // registerNestedBranch:(Ljava/lang/String;Lscala/Option;Lscala/Function0;Lscala/Function0;Lscala/Option;Lorg/scalactic/source/Position;)V
  #220 = Methodref          #76.#219      // org/scalatest/AsyncEngine.registerNestedBranch:(Ljava/lang/String;Lscala/Option;Lscala/Function0;Lscala/Function0;Lscala/Option;Lorg/scalactic/source/Position;)V
  #221 = Utf8               org/scalatest/exceptions/TestFailedException
  #222 = Class              #221          // org/scalatest/exceptions/TestFailedException
  #223 = Utf8               org/scalatest/exceptions/NotAllowedException
  #224 = Class              #223          // org/scalatest/exceptions/NotAllowedException
  #225 = Utf8               org/scalatest/FailureMessages$
  #226 = Class              #225          // org/scalatest/FailureMessages$
  #227 = Utf8               Lorg/scalatest/FailureMessages$;
  #228 = NameAndType        #156:#227     // MODULE$:Lorg/scalatest/FailureMessages$;
  #229 = Fieldref           #226.#228     // org/scalatest/FailureMessages$.MODULE$:Lorg/scalatest/FailureMessages$;
  #230 = Utf8               assertionShouldBePutInsideItOrTheyClauseNotDescribeClause
  #231 = NameAndType        #230:#136     // assertionShouldBePutInsideItOrTheyClauseNotDescribeClause:()Ljava/lang/String;
  #232 = Methodref          #226.#231     // org/scalatest/FailureMessages$.assertionShouldBePutInsideItOrTheyClauseNotDescribeClause:()Ljava/lang/String;
  #233 = Utf8               scala/Some
  #234 = Class              #233          // scala/Some
  #235 = Utf8               <init>
  #236 = Utf8               (Ljava/lang/Object;)V
  #237 = NameAndType        #235:#236     // "<init>":(Ljava/lang/Object;)V
  #238 = Methodref          #234.#237     // scala/Some."<init>":(Ljava/lang/Object;)V
  #239 = Utf8               position
  #240 = Utf8               ()Lscala/Option;
  #241 = NameAndType        #239:#240     // position:()Lscala/Option;
  #242 = Methodref          #222.#241     // org/scalatest/exceptions/TestFailedException.position:()Lscala/Option;
  #243 = Utf8               $anonfun$describeImpl$2
  #244 = Utf8               (Lorg/scalactic/source/Position;)Lorg/scalactic/source/Position;
  #245 = NameAndType        #243:#244     // $anonfun$describeImpl$2:(Lorg/scalactic/source/Position;)Lorg/scalactic/source/Position;
  #246 = InterfaceMethodref #2.#245       // org/scalatest/funspec/AsyncFunSpecLike.$anonfun$describeImpl$2:(Lorg/scalactic/source/Position;)Lorg/scalactic/source/Position;
  #247 = MethodHandle       6:#246        // REF_invokeStatic org/scalatest/funspec/AsyncFunSpecLike.$anonfun$describeImpl$2:(Lorg/scalactic/source/Position;)Lorg/scalactic/source/Position;
  #248 = Utf8               ()Lorg/scalactic/source/Position;
  #249 = MethodType         #248          //  ()Lorg/scalactic/source/Position;
  #250 = Utf8               (Lorg/scalactic/source/Position;)Lscala/Function0;
  #251 = NameAndType        #150:#250     // apply:(Lorg/scalactic/source/Position;)Lscala/Function0;
  #252 = InvokeDynamic      #4:#251       // #4:apply:(Lorg/scalactic/source/Position;)Lscala/Function0;
  #253 = Utf8               scala/Option
  #254 = Class              #253          // scala/Option
  #255 = Utf8               getOrElse
  #256 = Utf8               (Lscala/Function0;)Ljava/lang/Object;
  #257 = NameAndType        #255:#256     // getOrElse:(Lscala/Function0;)Ljava/lang/Object;
  #258 = Methodref          #254.#257     // scala/Option.getOrElse:(Lscala/Function0;)Ljava/lang/Object;
  #259 = Utf8               org/scalactic/source/Position
  #260 = Class              #259          // org/scalactic/source/Position
  #261 = Utf8               (Ljava/lang/String;Lscala/Option;Lorg/scalactic/source/Position;)V
  #262 = NameAndType        #235:#261     // "<init>":(Ljava/lang/String;Lscala/Option;Lorg/scalactic/source/Position;)V
  #263 = Methodref          #224.#262     // org/scalatest/exceptions/NotAllowedException."<init>":(Ljava/lang/String;Lscala/Option;Lorg/scalactic/source/Position;)V
  #264 = Utf8               org/scalatest/exceptions/TestCanceledException
  #265 = Class              #264          // org/scalatest/exceptions/TestCanceledException
  #266 = Methodref          #265.#241     // org/scalatest/exceptions/TestCanceledException.position:()Lscala/Option;
  #267 = Utf8               $anonfun$describeImpl$3
  #268 = NameAndType        #267:#244     // $anonfun$describeImpl$3:(Lorg/scalactic/source/Position;)Lorg/scalactic/source/Position;
  #269 = InterfaceMethodref #2.#268       // org/scalatest/funspec/AsyncFunSpecLike.$anonfun$describeImpl$3:(Lorg/scalactic/source/Position;)Lorg/scalactic/source/Position;
  #270 = MethodHandle       6:#269        // REF_invokeStatic org/scalatest/funspec/AsyncFunSpecLike.$anonfun$describeImpl$3:(Lorg/scalactic/source/Position;)Lorg/scalactic/source/Position;
  #271 = InvokeDynamic      #5:#251       // #5:apply:(Lorg/scalactic/source/Position;)Lscala/Function0;
  #272 = Utf8               org/scalatest/exceptions/DuplicateTestNameException
  #273 = Class              #272          // org/scalatest/exceptions/DuplicateTestNameException
  #274 = Utf8               org/scalactic/Prettifier$
  #275 = Class              #274          // org/scalactic/Prettifier$
  #276 = Utf8               Lorg/scalactic/Prettifier$;
  #277 = NameAndType        #156:#276     // MODULE$:Lorg/scalactic/Prettifier$;
  #278 = Fieldref           #275.#277     // org/scalactic/Prettifier$.MODULE$:Lorg/scalactic/Prettifier$;
  #279 = Utf8               default
  #280 = Utf8               ()Lorg/scalactic/Prettifier;
  #281 = NameAndType        #279:#280     // default:()Lorg/scalactic/Prettifier;
  #282 = Methodref          #275.#281     // org/scalactic/Prettifier$.default:()Lorg/scalactic/Prettifier;
  #283 = Utf8               org/scalatest/UnquotedString$
  #284 = Class              #283          // org/scalatest/UnquotedString$
  #285 = Utf8               Lorg/scalatest/UnquotedString$;
  #286 = NameAndType        #156:#285     // MODULE$:Lorg/scalatest/UnquotedString$;
  #287 = Fieldref           #284.#286     // org/scalatest/UnquotedString$.MODULE$:Lorg/scalatest/UnquotedString$;
  #288 = Utf8               getClass
  #289 = Utf8               ()Ljava/lang/Class;
  #290 = NameAndType        #288:#289     // getClass:()Ljava/lang/Class;
  #291 = Methodref          #273.#290     // org/scalatest/exceptions/DuplicateTestNameException.getClass:()Ljava/lang/Class;
  #292 = Utf8               java/lang/Class
  #293 = Class              #292          // java/lang/Class
  #294 = Utf8               getName
  #295 = NameAndType        #294:#136     // getName:()Ljava/lang/String;
  #296 = Methodref          #293.#295     // java/lang/Class.getName:()Ljava/lang/String;
  #297 = Utf8               (Ljava/lang/String;)Lorg/scalatest/UnquotedString;
  #298 = NameAndType        #150:#297     // apply:(Ljava/lang/String;)Lorg/scalatest/UnquotedString;
  #299 = Methodref          #284.#298     // org/scalatest/UnquotedString$.apply:(Ljava/lang/String;)Lorg/scalatest/UnquotedString;
  #300 = Utf8               getMessage
  #301 = NameAndType        #300:#136     // getMessage:()Ljava/lang/String;
  #302 = Methodref          #273.#301     // org/scalatest/exceptions/DuplicateTestNameException.getMessage:()Ljava/lang/String;
  #303 = Utf8               exceptionWasThrownInDescribeClause
  #304 = Utf8               (Lorg/scalactic/Prettifier;Ljava/lang/Object;Ljava/lang/Object;Ljava/lang/Object;)Ljava/lang/String;
  #305 = NameAndType        #303:#304     // exceptionWasThrownInDescribeClause:(Lorg/scalactic/Prettifier;Ljava/lang/Object;Ljava/lang/Object;Ljava/lang/Object;)Ljava/lang/String;
  #306 = Methodref          #226.#305     // org/scalatest/FailureMessages$.exceptionWasThrownInDescribeClause:(Lorg/scalactic/Prettifier;Ljava/lang/Object;Ljava/lang/Object;Ljava/lang/Object;)Ljava/lang/String;
  #307 = Methodref          #273.#241     // org/scalatest/exceptions/DuplicateTestNameException.position:()Lscala/Option;
  #308 = Utf8               $anonfun$describeImpl$4
  #309 = NameAndType        #308:#244     // $anonfun$describeImpl$4:(Lorg/scalactic/source/Position;)Lorg/scalactic/source/Position;
  #310 = InterfaceMethodref #2.#309       // org/scalatest/funspec/AsyncFunSpecLike.$anonfun$describeImpl$4:(Lorg/scalactic/source/Position;)Lorg/scalactic/source/Position;
  #311 = MethodHandle       6:#310        // REF_invokeStatic org/scalatest/funspec/AsyncFunSpecLike.$anonfun$describeImpl$4:(Lorg/scalactic/source/Position;)Lorg/scalactic/source/Position;
  #312 = InvokeDynamic      #6:#251       // #6:apply:(Lorg/scalactic/source/Position;)Lscala/Function0;
  #313 = Utf8               org/scalatest/Suite$
  #314 = Class              #313          // org/scalatest/Suite$
  #315 = Utf8               Lorg/scalatest/Suite$;
  #316 = NameAndType        #156:#315     // MODULE$:Lorg/scalatest/Suite$;
  #317 = Fieldref           #314.#316     // org/scalatest/Suite$.MODULE$:Lorg/scalatest/Suite$;
  #318 = Utf8               anExceptionThatShouldCauseAnAbort
  #319 = Utf8               (Ljava/lang/Throwable;)Z
  #320 = NameAndType        #318:#319     // anExceptionThatShouldCauseAnAbort:(Ljava/lang/Throwable;)Z
  #321 = Methodref          #314.#320     // org/scalatest/Suite$.anExceptionThatShouldCauseAnAbort:(Ljava/lang/Throwable;)Z
  #322 = Methodref          #211.#290     // java/lang/Throwable.getClass:()Ljava/lang/Class;
  #323 = Methodref          #211.#301     // java/lang/Throwable.getMessage:()Ljava/lang/String;
  #324 = Utf8               java/lang/String
  #325 = Class              #324          // java/lang/String
  #326 = Utf8               scala/Function0
  #327 = Class              #326          // scala/Function0
  #328 = Utf8               describe$
  #329 = Utf8               (Lorg/scalatest/funspec/AsyncFunSpecLike;Ljava/lang/String;Lscala/Function0;Lorg/scalactic/source/Position;)V
  #330 = Utf8               describe
  #331 = NameAndType        #330:#206     // describe:(Ljava/lang/String;Lscala/Function0;Lorg/scalactic/source/Position;)V
  #332 = InterfaceMethodref #2.#331       // org/scalatest/funspec/AsyncFunSpecLike.describe:(Ljava/lang/String;Lscala/Function0;Lorg/scalactic/source/Position;)V
  #333 = NameAndType        #205:#206     // describeImpl:(Ljava/lang/String;Lscala/Function0;Lorg/scalactic/source/Position;)V
  #334 = InterfaceMethodref #2.#333       // org/scalatest/funspec/AsyncFunSpecLike.describeImpl:(Ljava/lang/String;Lscala/Function0;Lorg/scalactic/source/Position;)V
  #335 = Utf8               testNames$
  #336 = Utf8               (Lorg/scalatest/funspec/AsyncFunSpecLike;)Lscala/collection/immutable/Set;
  #337 = Utf8               testNames
  #338 = Utf8               ()Lscala/collection/immutable/Set;
  #339 = NameAndType        #337:#338     // testNames:()Lscala/collection/immutable/Set;
  #340 = InterfaceMethodref #2.#339       // org/scalatest/funspec/AsyncFunSpecLike.testNames:()Lscala/collection/immutable/Set;
  #341 = Utf8               ()Lscala/collection/immutable/Set<Ljava/lang/String;>;
  #342 = Utf8               org/scalatest/InsertionOrderSet$
  #343 = Class              #342          // org/scalatest/InsertionOrderSet$
  #344 = Utf8               Lorg/scalatest/InsertionOrderSet$;
  #345 = NameAndType        #156:#344     // MODULE$:Lorg/scalatest/InsertionOrderSet$;
  #346 = Fieldref           #343.#345     // org/scalatest/InsertionOrderSet$.MODULE$:Lorg/scalatest/InsertionOrderSet$;
  #347 = Utf8               atomic
  #348 = NameAndType        #347:#78      // atomic:()Ljava/util/concurrent/atomic/AtomicReference;
  #349 = Methodref          #76.#348      // org/scalatest/AsyncEngine.atomic:()Ljava/util/concurrent/atomic/AtomicReference;
  #350 = Utf8               testNamesList
  #351 = Utf8               ()Lscala/collection/immutable/List;
  #352 = NameAndType        #350:#351     // testNamesList:()Lscala/collection/immutable/List;
  #353 = Methodref          #30.#352      // org/scalatest/AsyncSuperEngine$Bundle.testNamesList:()Lscala/collection/immutable/List;
  #354 = Utf8               (Lscala/collection/immutable/List;)Lscala/collection/immutable/Set;
  #355 = NameAndType        #150:#354     // apply:(Lscala/collection/immutable/List;)Lscala/collection/immutable/Set;
  #356 = Methodref          #343.#355     // org/scalatest/InsertionOrderSet$.apply:(Lscala/collection/immutable/List;)Lscala/collection/immutable/Set;
  #357 = Utf8               runTest$
  #358 = Utf8               (Lorg/scalatest/funspec/AsyncFunSpecLike;Ljava/lang/String;Lorg/scalatest/Args;)Lorg/scalatest/Status;
  #359 = Utf8               runTest
  #360 = Utf8               (Ljava/lang/String;Lorg/scalatest/Args;)Lorg/scalatest/Status;
  #361 = NameAndType        #359:#360     // runTest:(Ljava/lang/String;Lorg/scalatest/Args;)Lorg/scalatest/Status;
  #362 = InterfaceMethodref #2.#361       // org/scalatest/funspec/AsyncFunSpecLike.runTest:(Ljava/lang/String;Lorg/scalatest/Args;)Lorg/scalatest/Status;
  #363 = Utf8               Lorg/scalatest/Args;
  #364 = Utf8               parallelAsyncTestExecution
  #365 = Utf8               ()Z
  #366 = NameAndType        #364:#365     // parallelAsyncTestExecution:()Z
  #367 = InterfaceMethodref #2.#366       // org/scalatest/funspec/AsyncFunSpecLike.parallelAsyncTestExecution:()Z
  #368 = Utf8               (Ljava/lang/Object;Ljava/lang/Object;)Ljava/lang/Object;
  #369 = MethodType         #368          //  (Ljava/lang/Object;Ljava/lang/Object;)Ljava/lang/Object;
  #370 = Utf8               $anonfun$runTest$1
  #371 = Utf8               (Lorg/scalatest/funspec/AsyncFunSpecLike;Lorg/scalatest/Args;Ljava/lang/String;Lorg/scalatest/AsyncSuperEngine$TestLeaf;Lscala/Function1;)Lorg/scalatest/AsyncOutcome;
  #372 = NameAndType        #370:#371     // $anonfun$runTest$1:(Lorg/scalatest/funspec/AsyncFunSpecLike;Lorg/scalatest/Args;Ljava/lang/String;Lorg/scalatest/AsyncSuperEngine$TestLeaf;Lscala/Function1;)Lorg/scalatest/AsyncOutcome;
  #373 = InterfaceMethodref #2.#372       // org/scalatest/funspec/AsyncFunSpecLike.$anonfun$runTest$1:(Lorg/scalatest/funspec/AsyncFunSpecLike;Lorg/scalatest/Args;Ljava/lang/String;Lorg/scalatest/AsyncSuperEngine$TestLeaf;Lscala/Function1;)Lorg/scalatest/AsyncOutcome;
  #374 = MethodHandle       6:#373        // REF_invokeStatic org/scalatest/funspec/AsyncFunSpecLike.$anonfun$runTest$1:(Lorg/scalatest/funspec/AsyncFunSpecLike;Lorg/scalatest/Args;Ljava/lang/String;Lorg/scalatest/AsyncSuperEngine$TestLeaf;Lscala/Function1;)Lorg/scalatest/AsyncOutcome;
  #375 = Utf8               (Lorg/scalatest/AsyncSuperEngine$TestLeaf;Lscala/Function1;)Lorg/scalatest/AsyncOutcome;
  #376 = MethodType         #375          //  (Lorg/scalatest/AsyncSuperEngine$TestLeaf;Lscala/Function1;)Lorg/scalatest/AsyncOutcome;
  #377 = Utf8               (Lorg/scalatest/funspec/AsyncFunSpecLike;Lorg/scalatest/Args;Ljava/lang/String;)Lscala/Function2;
  #378 = NameAndType        #150:#377     // apply:(Lorg/scalatest/funspec/AsyncFunSpecLike;Lorg/scalatest/Args;Ljava/lang/String;)Lscala/Function2;
  #379 = InvokeDynamic      #7:#378       // #7:apply:(Lorg/scalatest/funspec/AsyncFunSpecLike;Lorg/scalatest/Args;Ljava/lang/String;)Lscala/Function2;
  #380 = Utf8               executionContext
  #381 = Utf8               ()Lscala/concurrent/ExecutionContext;
  #382 = NameAndType        #380:#381     // executionContext:()Lscala/concurrent/ExecutionContext;
  #383 = InterfaceMethodref #2.#382       // org/scalatest/funspec/AsyncFunSpecLike.executionContext:()Lscala/concurrent/ExecutionContext;
  #384 = Utf8               runTestImpl
  #385 = Utf8               (Lorg/scalatest/Suite;Ljava/lang/String;Lorg/scalatest/Args;ZZLscala/Function2;Lscala/concurrent/ExecutionContext;)Lorg/scalatest/Status;
  #386 = NameAndType        #384:#385     // runTestImpl:(Lorg/scalatest/Suite;Ljava/lang/String;Lorg/scalatest/Args;ZZLscala/Function2;Lscala/concurrent/ExecutionContext;)Lorg/scalatest/Status;
  #387 = Methodref          #76.#386      // org/scalatest/AsyncEngine.runTestImpl:(Lorg/scalatest/Suite;Ljava/lang/String;Lorg/scalatest/Args;ZZLscala/Function2;Lscala/concurrent/ExecutionContext;)Lorg/scalatest/Status;
  #388 = Utf8               tags$
  #389 = Utf8               (Lorg/scalatest/funspec/AsyncFunSpecLike;)Lscala/collection/immutable/Map;
  #390 = Utf8               tags
  #391 = Utf8               ()Lscala/collection/immutable/Map;
  #392 = NameAndType        #390:#391     // tags:()Lscala/collection/immutable/Map;
  #393 = InterfaceMethodref #2.#392       // org/scalatest/funspec/AsyncFunSpecLike.tags:()Lscala/collection/immutable/Map;
  #394 = Utf8               ()Lscala/collection/immutable/Map<Ljava/lang/String;Lscala/collection/immutable/Set<Ljava/lang/String;>;>;
  #395 = Utf8               tagsMap
  #396 = NameAndType        #395:#391     // tagsMap:()Lscala/collection/immutable/Map;
  #397 = Methodref          #30.#396      // org/scalatest/AsyncSuperEngine$Bundle.tagsMap:()Lscala/collection/immutable/Map;
  #398 = Utf8               autoTagClassAnnotations
  #399 = Utf8               (Lscala/collection/immutable/Map;Lorg/scalatest/Suite;)Lscala/collection/immutable/Map;
  #400 = NameAndType        #398:#399     // autoTagClassAnnotations:(Lscala/collection/immutable/Map;Lorg/scalatest/Suite;)Lscala/collection/immutable/Map;
  #401 = Methodref          #314.#400     // org/scalatest/Suite$.autoTagClassAnnotations:(Lscala/collection/immutable/Map;Lorg/scalatest/Suite;)Lscala/collection/immutable/Map;
  #402 = Utf8               runTests$
  #403 = Utf8               (Lorg/scalatest/funspec/AsyncFunSpecLike;Lscala/Option;Lorg/scalatest/Args;)Lorg/scalatest/Status;
  #404 = Utf8               runTests
  #405 = NameAndType        #404:#60      // runTests:(Lscala/Option;Lorg/scalatest/Args;)Lorg/scalatest/Status;
  #406 = InterfaceMethodref #2.#405       // org/scalatest/funspec/AsyncFunSpecLike.runTests:(Lscala/Option;Lorg/scalatest/Args;)Lorg/scalatest/Status;
  #407 = Utf8               Lscala/Option;
  #408 = Utf8               (Lscala/Option<Ljava/lang/String;>;Lorg/scalatest/Args;)Lorg/scalatest/Status;
  #409 = Utf8               $anonfun$runTests$1
  #410 = NameAndType        #409:#358     // $anonfun$runTests$1:(Lorg/scalatest/funspec/AsyncFunSpecLike;Ljava/lang/String;Lorg/scalatest/Args;)Lorg/scalatest/Status;
  #411 = InterfaceMethodref #2.#410       // org/scalatest/funspec/AsyncFunSpecLike.$anonfun$runTests$1:(Lorg/scalatest/funspec/AsyncFunSpecLike;Ljava/lang/String;Lorg/scalatest/Args;)Lorg/scalatest/Status;
  #412 = MethodHandle       6:#411        // REF_invokeStatic org/scalatest/funspec/AsyncFunSpecLike.$anonfun$runTests$1:(Lorg/scalatest/funspec/AsyncFunSpecLike;Ljava/lang/String;Lorg/scalatest/Args;)Lorg/scalatest/Status;
  #413 = MethodType         #360          //  (Ljava/lang/String;Lorg/scalatest/Args;)Lorg/scalatest/Status;
  #414 = Utf8               (Lorg/scalatest/funspec/AsyncFunSpecLike;)Lscala/Function2;
  #415 = NameAndType        #150:#414     // apply:(Lorg/scalatest/funspec/AsyncFunSpecLike;)Lscala/Function2;
  #416 = InvokeDynamic      #8:#415       // #8:apply:(Lorg/scalatest/funspec/AsyncFunSpecLike;)Lscala/Function2;
  #417 = Utf8               runTestsImpl
  #418 = Utf8               (Lorg/scalatest/Suite;Lscala/Option;Lorg/scalatest/Args;ZZLscala/Function2;)Lorg/scalatest/Status;
  #419 = NameAndType        #417:#418     // runTestsImpl:(Lorg/scalatest/Suite;Lscala/Option;Lorg/scalatest/Args;ZZLscala/Function2;)Lorg/scalatest/Status;
  #420 = Methodref          #76.#419      // org/scalatest/AsyncEngine.runTestsImpl:(Lorg/scalatest/Suite;Lscala/Option;Lorg/scalatest/Args;ZZLscala/Function2;)Lorg/scalatest/Status;
  #421 = Utf8               run$
  #422 = Utf8               run
  #423 = NameAndType        #422:#60      // run:(Lscala/Option;Lorg/scalatest/Args;)Lorg/scalatest/Status;
  #424 = InterfaceMethodref #2.#423       // org/scalatest/funspec/AsyncFunSpecLike.run:(Lscala/Option;Lorg/scalatest/Args;)Lorg/scalatest/Status;
  #425 = Utf8               $anonfun$run$1
  #426 = NameAndType        #425:#403     // $anonfun$run$1:(Lorg/scalatest/funspec/AsyncFunSpecLike;Lscala/Option;Lorg/scalatest/Args;)Lorg/scalatest/Status;
  #427 = InterfaceMethodref #2.#426       // org/scalatest/funspec/AsyncFunSpecLike.$anonfun$run$1:(Lorg/scalatest/funspec/AsyncFunSpecLike;Lscala/Option;Lorg/scalatest/Args;)Lorg/scalatest/Status;
  #428 = MethodHandle       6:#427        // REF_invokeStatic org/scalatest/funspec/AsyncFunSpecLike.$anonfun$run$1:(Lorg/scalatest/funspec/AsyncFunSpecLike;Lscala/Option;Lorg/scalatest/Args;)Lorg/scalatest/Status;
  #429 = MethodType         #60           //  (Lscala/Option;Lorg/scalatest/Args;)Lorg/scalatest/Status;
  #430 = InvokeDynamic      #9:#415       // #9:apply:(Lorg/scalatest/funspec/AsyncFunSpecLike;)Lscala/Function2;
  #431 = Utf8               runImpl
  #432 = Utf8               (Lorg/scalatest/Suite;Lscala/Option;Lorg/scalatest/Args;ZLscala/Function2;)Lorg/scalatest/Status;
  #433 = NameAndType        #431:#432     // runImpl:(Lorg/scalatest/Suite;Lscala/Option;Lorg/scalatest/Args;ZLscala/Function2;)Lorg/scalatest/Status;
  #434 = Methodref          #76.#433      // org/scalatest/AsyncEngine.runImpl:(Lorg/scalatest/Suite;Lscala/Option;Lorg/scalatest/Args;ZLscala/Function2;)Lorg/scalatest/Status;
  #435 = Utf8               behave
  #436 = Utf8               ()Lorg/scalatest/verbs/BehaveWord;
  #437 = Utf8               styleName
  #438 = Utf8               testDataFor$
  #439 = Utf8               (Lorg/scalatest/funspec/AsyncFunSpecLike;Ljava/lang/String;Lorg/scalatest/ConfigMap;)Lorg/scalatest/TestData;
  #440 = Utf8               theConfigMap
  #441 = Utf8               testDataFor
  #442 = Utf8               (Ljava/lang/String;Lorg/scalatest/ConfigMap;)Lorg/scalatest/TestData;
  #443 = NameAndType        #441:#442     // testDataFor:(Ljava/lang/String;Lorg/scalatest/ConfigMap;)Lorg/scalatest/TestData;
  #444 = InterfaceMethodref #2.#443       // org/scalatest/funspec/AsyncFunSpecLike.testDataFor:(Ljava/lang/String;Lorg/scalatest/ConfigMap;)Lorg/scalatest/TestData;
  #445 = Utf8               Lorg/scalatest/ConfigMap;
  #446 = Utf8               createTestDataFor
  #447 = Utf8               (Ljava/lang/String;Lorg/scalatest/ConfigMap;Lorg/scalatest/Suite;)Lorg/scalatest/TestData;
  #448 = NameAndType        #446:#447     // createTestDataFor:(Ljava/lang/String;Lorg/scalatest/ConfigMap;Lorg/scalatest/Suite;)Lorg/scalatest/TestData;
  #449 = Methodref          #76.#448      // org/scalatest/AsyncEngine.createTestDataFor:(Ljava/lang/String;Lorg/scalatest/ConfigMap;Lorg/scalatest/Suite;)Lorg/scalatest/TestData;
  #450 = Utf8               testDataFor$default$2$
  #451 = Utf8               (Lorg/scalatest/funspec/AsyncFunSpecLike;)Lorg/scalatest/ConfigMap;
  #452 = Utf8               testDataFor$default$2
  #453 = Utf8               ()Lorg/scalatest/ConfigMap;
  #454 = NameAndType        #452:#453     // testDataFor$default$2:()Lorg/scalatest/ConfigMap;
  #455 = InterfaceMethodref #2.#454       // org/scalatest/funspec/AsyncFunSpecLike.testDataFor$default$2:()Lorg/scalatest/ConfigMap;
  #456 = Utf8               org/scalatest/ConfigMap$
  #457 = Class              #456          // org/scalatest/ConfigMap$
  #458 = Utf8               Lorg/scalatest/ConfigMap$;
  #459 = NameAndType        #156:#458     // MODULE$:Lorg/scalatest/ConfigMap$;
  #460 = Fieldref           #457.#459     // org/scalatest/ConfigMap$.MODULE$:Lorg/scalatest/ConfigMap$;
  #461 = Utf8               empty
  #462 = NameAndType        #461:#453     // empty:()Lorg/scalatest/ConfigMap;
  #463 = Methodref          #457.#462     // org/scalatest/ConfigMap$.empty:()Lorg/scalatest/ConfigMap;
  #464 = Utf8               $anonfun$engine$1
  #465 = Utf8               org/scalatest/Resources$
  #466 = Class              #465          // org/scalatest/Resources$
  #467 = Utf8               Lorg/scalatest/Resources$;
  #468 = NameAndType        #156:#467     // MODULE$:Lorg/scalatest/Resources$;
  #469 = Fieldref           #466.#468     // org/scalatest/Resources$.MODULE$:Lorg/scalatest/Resources$;
  #470 = Utf8               concurrentSpecMod
  #471 = NameAndType        #470:#136     // concurrentSpecMod:()Ljava/lang/String;
  #472 = Methodref          #466.#471     // org/scalatest/Resources$.concurrentSpecMod:()Ljava/lang/String;
  #473 = Utf8               testCannotBeNestedInsideAnotherTest
  #474 = NameAndType        #473:#136     // testCannotBeNestedInsideAnotherTest:()Ljava/lang/String;
  #475 = Methodref          #466.#474     // org/scalatest/Resources$.testCannotBeNestedInsideAnotherTest:()Ljava/lang/String;
  #476 = Utf8               ignoreCannotAppearInsideAnItOrAThey
  #477 = NameAndType        #476:#136     // ignoreCannotAppearInsideAnItOrAThey:()Ljava/lang/String;
  #478 = Methodref          #466.#477     // org/scalatest/Resources$.ignoreCannotAppearInsideAnItOrAThey:()Ljava/lang/String;
  #479 = Utf8               describeCannotAppearInsideAnIt
  #480 = NameAndType        #479:#136     // describeCannotAppearInsideAnIt:()Ljava/lang/String;
  #481 = Methodref          #466.#480     // org/scalatest/Resources$.describeCannotAppearInsideAnIt:()Ljava/lang/String;
  #482 = Utf8               pos$1
  #483 = Utf8               invokeWithAsyncFixture$1
  #484 = Utf8               (Lorg/scalatest/AsyncSuperEngine$TestLeaf;Lscala/Function1;Lorg/scalatest/Args;Ljava/lang/String;)Lorg/scalatest/AsyncOutcome;
  #485 = Utf8               theTest
  #486 = Utf8               onCompleteFun
  #487 = Utf8               args$1
  #488 = Utf8               testName$1
  #489 = Utf8               org/scalatest/Args
  #490 = Class              #489          // org/scalatest/Args
  #491 = Utf8               configMap
  #492 = NameAndType        #491:#453     // configMap:()Lorg/scalatest/ConfigMap;
  #493 = Methodref          #490.#492     // org/scalatest/Args.configMap:()Lorg/scalatest/ConfigMap;
  #494 = Utf8               org/scalatest/FutureAsyncOutcome
  #495 = Class              #494          // org/scalatest/FutureAsyncOutcome
  #496 = Utf8               (Lorg/scalatest/funspec/AsyncFunSpecLike;Lorg/scalatest/TestData;Lorg/scalatest/AsyncSuperEngine$TestLeaf;)V
  #497 = NameAndType        #235:#496     // "<init>":(Lorg/scalatest/funspec/AsyncFunSpecLike;Lorg/scalatest/TestData;Lorg/scalatest/AsyncSuperEngine$TestLeaf;)V
  #498 = Methodref          #41.#497      // org/scalatest/funspec/AsyncFunSpecLike$$anon$1."<init>":(Lorg/scalatest/funspec/AsyncFunSpecLike;Lorg/scalatest/TestData;Lorg/scalatest/AsyncSuperEngine$TestLeaf;)V
  #499 = Utf8               withFixture
  #500 = Utf8               (Lorg/scalatest/AsyncTestSuite$NoArgAsyncTest;)Lorg/scalatest/FutureOutcome;
  #501 = NameAndType        #499:#500     // withFixture:(Lorg/scalatest/AsyncTestSuite$NoArgAsyncTest;)Lorg/scalatest/FutureOutcome;
  #502 = InterfaceMethodref #2.#501       // org/scalatest/funspec/AsyncFunSpecLike.withFixture:(Lorg/scalatest/AsyncTestSuite$NoArgAsyncTest;)Lorg/scalatest/FutureOutcome;
  #503 = Utf8               org/scalatest/FutureOutcome
  #504 = Class              #503          // org/scalatest/FutureOutcome
  #505 = Utf8               underlying
  #506 = Utf8               ()Lscala/concurrent/Future;
  #507 = NameAndType        #505:#506     // underlying:()Lscala/concurrent/Future;
  #508 = Methodref          #504.#507     // org/scalatest/FutureOutcome.underlying:()Lscala/concurrent/Future;
  #509 = Utf8               (Lscala/concurrent/Future;Lscala/Function1;Lscala/concurrent/ExecutionContext;)V
  #510 = NameAndType        #235:#509     // "<init>":(Lscala/concurrent/Future;Lscala/Function1;Lscala/concurrent/ExecutionContext;)V
  #511 = Methodref          #495.#510     // org/scalatest/FutureAsyncOutcome."<init>":(Lscala/concurrent/Future;Lscala/Function1;Lscala/concurrent/ExecutionContext;)V
  #512 = Utf8               testData
  #513 = Utf8               Lorg/scalatest/TestData;
  #514 = Utf8               Lorg/scalatest/AsyncSuperEngine$TestLeaf;
  #515 = Utf8               Lscala/Function1;
  #516 = NameAndType        #483:#484     // invokeWithAsyncFixture$1:(Lorg/scalatest/AsyncSuperEngine$TestLeaf;Lscala/Function1;Lorg/scalatest/Args;Ljava/lang/String;)Lorg/scalatest/AsyncOutcome;
  #517 = InterfaceMethodref #2.#516       // org/scalatest/funspec/AsyncFunSpecLike.invokeWithAsyncFixture$1:(Lorg/scalatest/AsyncSuperEngine$TestLeaf;Lscala/Function1;Lorg/scalatest/Args;Ljava/lang/String;)Lorg/scalatest/AsyncOutcome;
  #518 = NameAndType        #59:#60       // org$scalatest$funspec$AsyncFunSpecLike$$super$run:(Lscala/Option;Lorg/scalatest/Args;)Lorg/scalatest/Status;
  #519 = InterfaceMethodref #2.#518       // org/scalatest/funspec/AsyncFunSpecLike.org$scalatest$funspec$AsyncFunSpecLike$$super$run:(Lscala/Option;Lorg/scalatest/Args;)Lorg/scalatest/Status;
  #520 = Utf8               $init$
  #521 = Utf8               (Lorg/scalatest/funspec/AsyncFunSpecLike;)V
  #522 = NameAndType        #464:#136     // $anonfun$engine$1:()Ljava/lang/String;
  #523 = InterfaceMethodref #2.#522       // org/scalatest/funspec/AsyncFunSpecLike.$anonfun$engine$1:()Ljava/lang/String;
  #524 = MethodHandle       6:#523        // REF_invokeStatic org/scalatest/funspec/AsyncFunSpecLike.$anonfun$engine$1:()Ljava/lang/String;
  #525 = InvokeDynamic      #10:#152      // #10:apply:()Lscala/Function0;
  #526 = Utf8               FunSpec
  #527 = String             #526          // FunSpec
  #528 = Utf8               (Lscala/Function0;Ljava/lang/String;)V
  #529 = NameAndType        #235:#528     // "<init>":(Lscala/Function0;Ljava/lang/String;)V
  #530 = Methodref          #76.#529      // org/scalatest/AsyncEngine."<init>":(Lscala/Function0;Ljava/lang/String;)V
  #531 = NameAndType        #48:#49       // org$scalatest$funspec$AsyncFunSpecLike$_setter_$org$scalatest$funspec$AsyncFunSpecLike$$engine_$eq:(Lorg/scalatest/AsyncEngine;)V
  #532 = InterfaceMethodref #2.#531       // org/scalatest/funspec/AsyncFunSpecLike.org$scalatest$funspec$AsyncFunSpecLike$_setter_$org$scalatest$funspec$AsyncFunSpecLike$$engine_$eq:(Lorg/scalatest/AsyncEngine;)V
  #533 = NameAndType        #235:#521     // "<init>":(Lorg/scalatest/funspec/AsyncFunSpecLike;)V
  #534 = Methodref          #43.#533      // org/scalatest/funspec/AsyncFunSpecLike$ItWord."<init>":(Lorg/scalatest/funspec/AsyncFunSpecLike;)V
  #535 = NameAndType        #51:#52       // org$scalatest$funspec$AsyncFunSpecLike$_setter_$it_$eq:(Lorg/scalatest/funspec/AsyncFunSpecLike$ItWord;)V
  #536 = InterfaceMethodref #2.#535       // org/scalatest/funspec/AsyncFunSpecLike.org$scalatest$funspec$AsyncFunSpecLike$_setter_$it_$eq:(Lorg/scalatest/funspec/AsyncFunSpecLike$ItWord;)V
  #537 = Methodref          #46.#533      // org/scalatest/funspec/AsyncFunSpecLike$TheyWord."<init>":(Lorg/scalatest/funspec/AsyncFunSpecLike;)V
  #538 = NameAndType        #53:#54       // org$scalatest$funspec$AsyncFunSpecLike$_setter_$they_$eq:(Lorg/scalatest/funspec/AsyncFunSpecLike$TheyWord;)V
  #539 = InterfaceMethodref #2.#538       // org/scalatest/funspec/AsyncFunSpecLike.org$scalatest$funspec$AsyncFunSpecLike$_setter_$they_$eq:(Lorg/scalatest/funspec/AsyncFunSpecLike$TheyWord;)V
  #540 = Utf8               org/scalatest/verbs/BehaveWord
  #541 = Class              #540          // org/scalatest/verbs/BehaveWord
  #542 = Utf8               ()V
  #543 = NameAndType        #235:#542     // "<init>":()V
  #544 = Methodref          #541.#543     // org/scalatest/verbs/BehaveWord."<init>":()V
  #545 = NameAndType        #55:#56       // org$scalatest$funspec$AsyncFunSpecLike$_setter_$behave_$eq:(Lorg/scalatest/verbs/BehaveWord;)V
  #546 = InterfaceMethodref #2.#545       // org/scalatest/funspec/AsyncFunSpecLike.org$scalatest$funspec$AsyncFunSpecLike$_setter_$behave_$eq:(Lorg/scalatest/verbs/BehaveWord;)V
  #547 = Utf8               org.scalatest.FunSpec
  #548 = String             #547          // org.scalatest.FunSpec
  #549 = NameAndType        #57:#58       // org$scalatest$funspec$AsyncFunSpecLike$_setter_$styleName_$eq:(Ljava/lang/String;)V
  #550 = InterfaceMethodref #2.#549       // org/scalatest/funspec/AsyncFunSpecLike.org$scalatest$funspec$AsyncFunSpecLike$_setter_$styleName_$eq:(Ljava/lang/String;)V
  #551 = Utf8               $deserializeLambda$
  #552 = Utf8               (Ljava/lang/invoke/SerializedLambda;)Ljava/lang/Object;
  #553 = Utf8               scala/runtime/LambdaDeserialize
  #554 = Class              #553          // scala/runtime/LambdaDeserialize
  #555 = Utf8               bootstrap
  #556 = Utf8               (Ljava/lang/invoke/MethodHandles$Lookup;Ljava/lang/String;Ljava/lang/invoke/MethodType;[Ljava/lang/invoke/MethodHandle;)Ljava/lang/invoke/CallSite;
  #557 = NameAndType        #555:#556     // bootstrap:(Ljava/lang/invoke/MethodHandles$Lookup;Ljava/lang/String;Ljava/lang/invoke/MethodType;[Ljava/lang/invoke/MethodHandle;)Ljava/lang/invoke/CallSite;
  #558 = Methodref          #554.#557     // scala/runtime/LambdaDeserialize.bootstrap:(Ljava/lang/invoke/MethodHandles$Lookup;Ljava/lang/String;Ljava/lang/invoke/MethodType;[Ljava/lang/invoke/MethodHandle;)Ljava/lang/invoke/CallSite;
  #559 = MethodHandle       6:#558        // REF_invokeStatic scala/runtime/LambdaDeserialize.bootstrap:(Ljava/lang/invoke/MethodHandles$Lookup;Ljava/lang/String;Ljava/lang/invoke/MethodType;[Ljava/lang/invoke/MethodHandle;)Ljava/lang/invoke/CallSite;
  #560 = Utf8               lambdaDeserialize
  #561 = NameAndType        #560:#552     // lambdaDeserialize:(Ljava/lang/invoke/SerializedLambda;)Ljava/lang/Object;
  #562 = InvokeDynamic      #11:#561      // #11:lambdaDeserialize:(Ljava/lang/invoke/SerializedLambda;)Ljava/lang/Object;
  #563 = Utf8               MethodParameters
  #564 = Utf8               Code
  #565 = Utf8               LineNumberTable
  #566 = Utf8               LocalVariableTable
  #567 = Utf8               Signature
  #568 = Utf8               StackMapTable
  #569 = Utf8               Deprecated
  #570 = Utf8               InnerClasses
  #571 = Utf8               SourceFile
  #572 = Utf8               RuntimeVisibleAnnotations
  #573 = Utf8               BootstrapMethods
  #574 = Utf8               ScalaInlineInfo
  #575 = Utf8               ScalaSig
{
  public abstract void org$scalatest$funspec$AsyncFunSpecLike$_setter_$org$scalatest$funspec$AsyncFunSpecLike$$engine_$eq(org.scalatest.AsyncEngine);
    descriptor: (Lorg/scalatest/AsyncEngine;)V
    flags: (0x0401) ACC_PUBLIC, ACC_ABSTRACT
    MethodParameters:
      Name                           Flags
      x$1                            final

  public abstract void org$scalatest$funspec$AsyncFunSpecLike$_setter_$it_$eq(org.scalatest.funspec.AsyncFunSpecLike$ItWord);
    descriptor: (Lorg/scalatest/funspec/AsyncFunSpecLike$ItWord;)V
    flags: (0x0401) ACC_PUBLIC, ACC_ABSTRACT
    MethodParameters:
      Name                           Flags
      x$1                            final

  public abstract void org$scalatest$funspec$AsyncFunSpecLike$_setter_$they_$eq(org.scalatest.funspec.AsyncFunSpecLike$TheyWord);
    descriptor: (Lorg/scalatest/funspec/AsyncFunSpecLike$TheyWord;)V
    flags: (0x0401) ACC_PUBLIC, ACC_ABSTRACT
    MethodParameters:
      Name                           Flags
      x$1                            final

  public abstract void org$scalatest$funspec$AsyncFunSpecLike$_setter_$behave_$eq(org.scalatest.verbs.BehaveWord);
    descriptor: (Lorg/scalatest/verbs/BehaveWord;)V
    flags: (0x0401) ACC_PUBLIC, ACC_ABSTRACT
    MethodParameters:
      Name                           Flags
      x$1                            final

  public abstract void org$scalatest$funspec$AsyncFunSpecLike$_setter_$styleName_$eq(java.lang.String);
    descriptor: (Ljava/lang/String;)V
    flags: (0x0401) ACC_PUBLIC, ACC_ABSTRACT
    MethodParameters:
      Name                           Flags
      x$1                            final

  public abstract org.scalatest.Status org$scalatest$funspec$AsyncFunSpecLike$$super$run(scala.Option, org.scalatest.Args);
    descriptor: (Lscala/Option;Lorg/scalatest/Args;)Lorg/scalatest/Status;
    flags: (0x1401) ACC_PUBLIC, ACC_ABSTRACT, ACC_SYNTHETIC
    MethodParameters:
      Name                           Flags
      testName                       final
      args                           final

  public abstract org.scalatest.AsyncEngine org$scalatest$funspec$AsyncFunSpecLike$$engine();
    descriptor: ()Lorg/scalatest/AsyncEngine;
    flags: (0x0401) ACC_PUBLIC, ACC_ABSTRACT

  public static org.scalatest.Informer info$(org.scalatest.funspec.AsyncFunSpecLike);
    descriptor: (Lorg/scalatest/funspec/AsyncFunSpecLike;)Lorg/scalatest/Informer;
    flags: (0x1009) ACC_PUBLIC, ACC_STATIC, ACC_SYNTHETIC
    Code:
      stack=1, locals=1, args_size=1
         0: aload_0
         1: invokespecial #71                 // InterfaceMethod info:()Lorg/scalatest/Informer;
         4: areturn
      LineNumberTable:
        line 66: 0
      LocalVariableTable:
        Start  Length  Slot  Name   Signature
            0       5     0 $this   Lorg/scalatest/funspec/AsyncFunSpecLike;
    MethodParameters:
      Name                           Flags
      $this                          final synthetic

  public default org.scalatest.Informer info();
    descriptor: ()Lorg/scalatest/Informer;
    flags: (0x0001) ACC_PUBLIC
    Code:
      stack=1, locals=1, args_size=1
         0: aload_0
         1: invokeinterface #74,  1           // InterfaceMethod org$scalatest$funspec$AsyncFunSpecLike$$engine:()Lorg/scalatest/AsyncEngine;
         6: invokevirtual #80                 // Method org/scalatest/AsyncEngine.atomicInformer:()Ljava/util/concurrent/atomic/AtomicReference;
         9: invokevirtual #86                 // Method java/util/concurrent/atomic/AtomicReference.get:()Ljava/lang/Object;
        12: checkcast     #88                 // class org/scalatest/Informer
        15: areturn
      LineNumberTable:
        line 66: 0
      LocalVariableTable:
        Start  Length  Slot  Name   Signature
            0      16     0  this   Lorg/scalatest/funspec/AsyncFunSpecLike;

  public static org.scalatest.Notifier note$(org.scalatest.funspec.AsyncFunSpecLike);
    descriptor: (Lorg/scalatest/funspec/AsyncFunSpecLike;)Lorg/scalatest/Notifier;
    flags: (0x1009) ACC_PUBLIC, ACC_STATIC, ACC_SYNTHETIC
    Code:
      stack=1, locals=1, args_size=1
         0: aload_0
         1: invokespecial #95                 // InterfaceMethod note:()Lorg/scalatest/Notifier;
         4: areturn
      LineNumberTable:
        line 76: 0
      LocalVariableTable:
        Start  Length  Slot  Name   Signature
            0       5     0 $this   Lorg/scalatest/funspec/AsyncFunSpecLike;
    MethodParameters:
      Name                           Flags
      $this                          final synthetic

  public default org.scalatest.Notifier note();
    descriptor: ()Lorg/scalatest/Notifier;
    flags: (0x0001) ACC_PUBLIC
    Code:
      stack=1, locals=1, args_size=1
         0: aload_0
         1: invokeinterface #74,  1           // InterfaceMethod org$scalatest$funspec$AsyncFunSpecLike$$engine:()Lorg/scalatest/AsyncEngine;
         6: invokevirtual #98                 // Method org/scalatest/AsyncEngine.atomicNotifier:()Ljava/util/concurrent/atomic/AtomicReference;
         9: invokevirtual #86                 // Method java/util/concurrent/atomic/AtomicReference.get:()Ljava/lang/Object;
        12: checkcast     #100                // class org/scalatest/Notifier
        15: areturn
      LineNumberTable:
        line 76: 0
      LocalVariableTable:
        Start  Length  Slot  Name   Signature
            0      16     0  this   Lorg/scalatest/funspec/AsyncFunSpecLike;

  public static org.scalatest.Alerter alert$(org.scalatest.funspec.AsyncFunSpecLike);
    descriptor: (Lorg/scalatest/funspec/AsyncFunSpecLike;)Lorg/scalatest/Alerter;
    flags: (0x1009) ACC_PUBLIC, ACC_STATIC, ACC_SYNTHETIC
    Code:
      stack=1, locals=1, args_size=1
         0: aload_0
         1: invokespecial #106                // InterfaceMethod alert:()Lorg/scalatest/Alerter;
         4: areturn
      LineNumberTable:
        line 86: 0
      LocalVariableTable:
        Start  Length  Slot  Name   Signature
            0       5     0 $this   Lorg/scalatest/funspec/AsyncFunSpecLike;
    MethodParameters:
      Name                           Flags
      $this                          final synthetic

  public default org.scalatest.Alerter alert();
    descriptor: ()Lorg/scalatest/Alerter;
    flags: (0x0001) ACC_PUBLIC
    Code:
      stack=1, locals=1, args_size=1
         0: aload_0
         1: invokeinterface #74,  1           // InterfaceMethod org$scalatest$funspec$AsyncFunSpecLike$$engine:()Lorg/scalatest/AsyncEngine;
         6: invokevirtual #109                // Method org/scalatest/AsyncEngine.atomicAlerter:()Ljava/util/concurrent/atomic/AtomicReference;
         9: invokevirtual #86                 // Method java/util/concurrent/atomic/AtomicReference.get:()Ljava/lang/Object;
        12: checkcast     #111                // class org/scalatest/Alerter
        15: areturn
      LineNumberTable:
        line 86: 0
      LocalVariableTable:
        Start  Length  Slot  Name   Signature
            0      16     0  this   Lorg/scalatest/funspec/AsyncFunSpecLike;

  public static org.scalatest.Documenter markup$(org.scalatest.funspec.AsyncFunSpecLike);
    descriptor: (Lorg/scalatest/funspec/AsyncFunSpecLike;)Lorg/scalatest/Documenter;
    flags: (0x1009) ACC_PUBLIC, ACC_STATIC, ACC_SYNTHETIC
    Code:
      stack=1, locals=1, args_size=1
         0: aload_0
         1: invokespecial #117                // InterfaceMethod markup:()Lorg/scalatest/Documenter;
         4: areturn
      LineNumberTable:
        line 97: 0
      LocalVariableTable:
        Start  Length  Slot  Name   Signature
            0       5     0 $this   Lorg/scalatest/funspec/AsyncFunSpecLike;
    MethodParameters:
      Name                           Flags
      $this                          final synthetic

  public default org.scalatest.Documenter markup();
    descriptor: ()Lorg/scalatest/Documenter;
    flags: (0x0001) ACC_PUBLIC
    Code:
      stack=1, locals=1, args_size=1
         0: aload_0
         1: invokeinterface #74,  1           // InterfaceMethod org$scalatest$funspec$AsyncFunSpecLike$$engine:()Lorg/scalatest/AsyncEngine;
         6: invokevirtual #120                // Method org/scalatest/AsyncEngine.atomicDocumenter:()Ljava/util/concurrent/atomic/AtomicReference;
         9: invokevirtual #86                 // Method java/util/concurrent/atomic/AtomicReference.get:()Ljava/lang/Object;
        12: checkcast     #122                // class org/scalatest/Documenter
        15: areturn
      LineNumberTable:
        line 97: 0
      LocalVariableTable:
        Start  Length  Slot  Name   Signature
            0      16     0  this   Lorg/scalatest/funspec/AsyncFunSpecLike;

  private void registerAsyncTestImpl(java.lang.String, scala.collection.immutable.Seq<org.scalatest.Tag>, scala.Function0<scala.concurrent.Future<org.scalatest.compatible.Assertion>>, org.scalactic.source.Position);
    descriptor: (Ljava/lang/String;Lscala/collection/immutable/Seq;Lscala/Function0;Lorg/scalactic/source/Position;)V
    flags: (0x0002) ACC_PRIVATE
    Code:
      stack=8, locals=5, args_size=5
         0: aload_0
         1: invokeinterface #74,  1           // InterfaceMethod org$scalatest$funspec$AsyncFunSpecLike$$engine:()Lorg/scalatest/AsyncEngine;
         6: aload_1
         7: aload_0
         8: aload_3
         9: invokeinterface #133,  2          // InterfaceMethod transformToOutcome:(Lscala/Function0;)Lscala/Function0;
        14: invokedynamic #153,  0            // InvokeDynamic #0:apply:()Lscala/Function0;
        19: getstatic     #159                // Field scala/None$.MODULE$:Lscala/None$;
        22: getstatic     #159                // Field scala/None$.MODULE$:Lscala/None$;
        25: aload         4
        27: aload_2
        28: invokevirtual #163                // Method org/scalatest/AsyncEngine.registerAsyncTest:(Ljava/lang/String;Ljava/lang/Object;Lscala/Function0;Lscala/Option;Lscala/Option;Lorg/scalactic/source/Position;Lscala/collection/immutable/Seq;)Ljava/lang/String;
        31: pop
        32: return
      LineNumberTable:
        line 100: 0
      LocalVariableTable:
        Start  Length  Slot  Name   Signature
            0      33     0  this   Lorg/scalatest/funspec/AsyncFunSpecLike;
            0      33     1 testText   Ljava/lang/String;
            0      33     2 testTags   Lscala/collection/immutable/Seq;
            0      33     3 testFun   Lscala/Function0;
            0      33     4   pos   Lorg/scalactic/source/Position;
    Signature: #125                         // (Ljava/lang/String;Lscala/collection/immutable/Seq<Lorg/scalatest/Tag;>;Lscala/Function0<Lscala/concurrent/Future<Lorg/scalatest/compatible/Assertion;>;>;Lorg/scalactic/source/Position;)V
    MethodParameters:
      Name                           Flags
      testText                       final
      testTags                       final
      testFun                        final
      pos                            final

  public static void registerAsyncTest$(org.scalatest.funspec.AsyncFunSpecLike, java.lang.String, scala.collection.immutable.Seq, scala.Function0, org.scalactic.source.Position);
    descriptor: (Lorg/scalatest/funspec/AsyncFunSpecLike;Ljava/lang/String;Lscala/collection/immutable/Seq;Lscala/Function0;Lorg/scalactic/source/Position;)V
    flags: (0x1009) ACC_PUBLIC, ACC_STATIC, ACC_SYNTHETIC
    Code:
      stack=5, locals=5, args_size=5
         0: aload_0
         1: aload_1
         2: aload_2
         3: aload_3
         4: aload         4
         6: invokespecial #171                // InterfaceMethod registerAsyncTest:(Ljava/lang/String;Lscala/collection/immutable/Seq;Lscala/Function0;Lorg/scalactic/source/Position;)V
         9: return
      LineNumberTable:
        line 104: 0
      LocalVariableTable:
        Start  Length  Slot  Name   Signature
            0      10     0 $this   Lorg/scalatest/funspec/AsyncFunSpecLike;
            0      10     1 testText   Ljava/lang/String;
            0      10     2 testTags   Lscala/collection/immutable/Seq;
            0      10     3 testFun   Lscala/Function0;
            0      10     4   pos   Lorg/scalactic/source/Position;
    MethodParameters:
      Name                           Flags
      $this                          final synthetic
      testText                       final
      testTags                       final
      testFun                        final
      pos                            final

  public default void registerAsyncTest(java.lang.String, scala.collection.immutable.Seq<org.scalatest.Tag>, scala.Function0<scala.concurrent.Future<org.scalatest.compatible.Assertion>>, org.scalactic.source.Position);
    descriptor: (Ljava/lang/String;Lscala/collection/immutable/Seq;Lscala/Function0;Lorg/scalactic/source/Position;)V
    flags: (0x0001) ACC_PUBLIC
    Code:
      stack=5, locals=5, args_size=5
         0: aload_0
         1: aload_1
         2: aload_2
         3: aload_3
         4: aload         4
         6: invokespecial #173                // InterfaceMethod registerAsyncTestImpl:(Ljava/lang/String;Lscala/collection/immutable/Seq;Lscala/Function0;Lorg/scalactic/source/Position;)V
         9: return
      LineNumberTable:
        line 105: 0
      LocalVariableTable:
        Start  Length  Slot  Name   Signature
            0      10     0  this   Lorg/scalatest/funspec/AsyncFunSpecLike;
            0      10     1 testText   Ljava/lang/String;
            0      10     2 testTags   Lscala/collection/immutable/Seq;
            0      10     3 testFun   Lscala/Function0;
            0      10     4   pos   Lorg/scalactic/source/Position;
    Signature: #125                         // (Ljava/lang/String;Lscala/collection/immutable/Seq<Lorg/scalatest/Tag;>;Lscala/Function0<Lscala/concurrent/Future<Lorg/scalatest/compatible/Assertion;>;>;Lorg/scalactic/source/Position;)V
    MethodParameters:
      Name                           Flags
      testText                       final
      testTags                       final
      testFun                        final
      pos                            final

  private void registerIgnoredAsyncTestImpl(java.lang.String, scala.collection.immutable.Seq<org.scalatest.Tag>, scala.Function0<scala.concurrent.Future<org.scalatest.compatible.Assertion>>, org.scalactic.source.Position);
    descriptor: (Ljava/lang/String;Lscala/collection/immutable/Seq;Lscala/Function0;Lorg/scalactic/source/Position;)V
    flags: (0x0002) ACC_PRIVATE
    Code:
      stack=7, locals=5, args_size=5
         0: aload_0
         1: invokeinterface #74,  1           // InterfaceMethod org$scalatest$funspec$AsyncFunSpecLike$$engine:()Lorg/scalatest/AsyncEngine;
         6: aload_1
         7: aload_0
         8: aload_3
         9: invokeinterface #133,  2          // InterfaceMethod transformToOutcome:(Lscala/Function0;)Lscala/Function0;
        14: invokedynamic #179,  0            // InvokeDynamic #1:apply:()Lscala/Function0;
        19: getstatic     #159                // Field scala/None$.MODULE$:Lscala/None$;
        22: aload         4
        24: aload_2
        25: invokevirtual #183                // Method org/scalatest/AsyncEngine.registerIgnoredAsyncTest:(Ljava/lang/String;Ljava/lang/Object;Lscala/Function0;Lscala/Option;Lorg/scalactic/source/Position;Lscala/collection/immutable/Seq;)V
        28: return
      LineNumberTable:
        line 113: 0
      LocalVariableTable:
        Start  Length  Slot  Name   Signature
            0      29     0  this   Lorg/scalatest/funspec/AsyncFunSpecLike;
            0      29     1 testText   Ljava/lang/String;
            0      29     2 testTags   Lscala/collection/immutable/Seq;
            0      29     3 testFun   Lscala/Function0;
            0      29     4   pos   Lorg/scalactic/source/Position;
    Signature: #125                         // (Ljava/lang/String;Lscala/collection/immutable/Seq<Lorg/scalatest/Tag;>;Lscala/Function0<Lscala/concurrent/Future<Lorg/scalatest/compatible/Assertion;>;>;Lorg/scalactic/source/Position;)V
    MethodParameters:
      Name                           Flags
      testText                       final
      testTags                       final
      testFun                        final
      pos                            final

  public static void registerIgnoredAsyncTest$(org.scalatest.funspec.AsyncFunSpecLike, java.lang.String, scala.collection.immutable.Seq, scala.Function0, org.scalactic.source.Position);
    descriptor: (Lorg/scalatest/funspec/AsyncFunSpecLike;Ljava/lang/String;Lscala/collection/immutable/Seq;Lscala/Function0;Lorg/scalactic/source/Position;)V
    flags: (0x1009) ACC_PUBLIC, ACC_STATIC, ACC_SYNTHETIC
    Code:
      stack=5, locals=5, args_size=5
         0: aload_0
         1: aload_1
         2: aload_2
         3: aload_3
         4: aload         4
         6: invokespecial #186                // InterfaceMethod registerIgnoredAsyncTest:(Ljava/lang/String;Lscala/collection/immutable/Seq;Lscala/Function0;Lorg/scalactic/source/Position;)V
         9: return
      LineNumberTable:
        line 117: 0
      LocalVariableTable:
        Start  Length  Slot  Name   Signature
            0      10     0 $this   Lorg/scalatest/funspec/AsyncFunSpecLike;
            0      10     1 testText   Ljava/lang/String;
            0      10     2 testTags   Lscala/collection/immutable/Seq;
            0      10     3 testFun   Lscala/Function0;
            0      10     4   pos   Lorg/scalactic/source/Position;
    MethodParameters:
      Name                           Flags
      $this                          final synthetic
      testText                       final
      testTags                       final
      testFun                        final
      pos                            final

  public default void registerIgnoredAsyncTest(java.lang.String, scala.collection.immutable.Seq<org.scalatest.Tag>, scala.Function0<scala.concurrent.Future<org.scalatest.compatible.Assertion>>, org.scalactic.source.Position);
    descriptor: (Ljava/lang/String;Lscala/collection/immutable/Seq;Lscala/Function0;Lorg/scalactic/source/Position;)V
    flags: (0x0001) ACC_PUBLIC
    Code:
      stack=5, locals=5, args_size=5
         0: aload_0
         1: aload_1
         2: aload_2
         3: aload_3
         4: aload         4
         6: invokespecial #188                // InterfaceMethod registerIgnoredAsyncTestImpl:(Ljava/lang/String;Lscala/collection/immutable/Seq;Lscala/Function0;Lorg/scalactic/source/Position;)V
         9: return
      LineNumberTable:
        line 118: 0
      LocalVariableTable:
        Start  Length  Slot  Name   Signature
            0      10     0  this   Lorg/scalatest/funspec/AsyncFunSpecLike;
            0      10     1 testText   Ljava/lang/String;
            0      10     2 testTags   Lscala/collection/immutable/Seq;
            0      10     3 testFun   Lscala/Function0;
            0      10     4   pos   Lorg/scalactic/source/Position;
    Signature: #125                         // (Ljava/lang/String;Lscala/collection/immutable/Seq<Lorg/scalatest/Tag;>;Lscala/Function0<Lscala/concurrent/Future<Lorg/scalatest/compatible/Assertion;>;>;Lorg/scalactic/source/Position;)V
    MethodParameters:
      Name                           Flags
      testText                       final
      testTags                       final
      testFun                        final
      pos                            final

  public abstract org.scalatest.funspec.AsyncFunSpecLike$ItWord it();
    descriptor: ()Lorg/scalatest/funspec/AsyncFunSpecLike$ItWord;
    flags: (0x0401) ACC_PUBLIC, ACC_ABSTRACT

  public abstract org.scalatest.funspec.AsyncFunSpecLike$TheyWord they();
    descriptor: ()Lorg/scalatest/funspec/AsyncFunSpecLike$TheyWord;
    flags: (0x0401) ACC_PUBLIC, ACC_ABSTRACT

  private void ignoreImpl(java.lang.String, scala.collection.immutable.Seq<org.scalatest.Tag>, scala.Function0<scala.concurrent.Future<org.scalatest.compatible.Assertion>>, org.scalactic.source.Position);
    descriptor: (Ljava/lang/String;Lscala/collection/immutable/Seq;Lscala/Function0;Lorg/scalactic/source/Position;)V
    flags: (0x0002) ACC_PRIVATE
    Code:
      stack=7, locals=5, args_size=5
         0: aload_0
         1: invokeinterface #74,  1           // InterfaceMethod org$scalatest$funspec$AsyncFunSpecLike$$engine:()Lorg/scalatest/AsyncEngine;
         6: aload_1
         7: aload_0
         8: aload_3
         9: invokeinterface #133,  2          // InterfaceMethod transformToOutcome:(Lscala/Function0;)Lscala/Function0;
        14: invokedynamic #198,  0            // InvokeDynamic #2:apply:()Lscala/Function0;
        19: getstatic     #159                // Field scala/None$.MODULE$:Lscala/None$;
        22: aload         4
        24: aload_2
        25: invokevirtual #183                // Method org/scalatest/AsyncEngine.registerIgnoredAsyncTest:(Ljava/lang/String;Ljava/lang/Object;Lscala/Function0;Lscala/Option;Lorg/scalactic/source/Position;Lscala/collection/immutable/Seq;)V
        28: return
      LineNumberTable:
        line 368: 0
      LocalVariableTable:
        Start  Length  Slot  Name   Signature
            0      29     0  this   Lorg/scalatest/funspec/AsyncFunSpecLike;
            0      29     1 testText   Ljava/lang/String;
            0      29     2 testTags   Lscala/collection/immutable/Seq;
            0      29     3 testFun   Lscala/Function0;
            0      29     4   pos   Lorg/scalactic/source/Position;
    Signature: #125                         // (Ljava/lang/String;Lscala/collection/immutable/Seq<Lorg/scalatest/Tag;>;Lscala/Function0<Lscala/concurrent/Future<Lorg/scalatest/compatible/Assertion;>;>;Lorg/scalactic/source/Position;)V
    MethodParameters:
      Name                           Flags
      testText                       final
      testTags                       final
      testFun                        final
      pos                            final

  public static void ignore$(org.scalatest.funspec.AsyncFunSpecLike, java.lang.String, scala.collection.immutable.Seq, scala.Function0, org.scalactic.source.Position);
    descriptor: (Lorg/scalatest/funspec/AsyncFunSpecLike;Ljava/lang/String;Lscala/collection/immutable/Seq;Lscala/Function0;Lorg/scalactic/source/Position;)V
    flags: (0x1009) ACC_PUBLIC, ACC_STATIC, ACC_SYNTHETIC
    Code:
      stack=5, locals=5, args_size=5
         0: aload_0
         1: aload_1
         2: aload_2
         3: aload_3
         4: aload         4
         6: invokespecial #202                // InterfaceMethod ignore:(Ljava/lang/String;Lscala/collection/immutable/Seq;Lscala/Function0;Lorg/scalactic/source/Position;)V
         9: return
      LineNumberTable:
        line 390: 0
      LocalVariableTable:
        Start  Length  Slot  Name   Signature
            0      10     0 $this   Lorg/scalatest/funspec/AsyncFunSpecLike;
            0      10     1 testText   Ljava/lang/String;
            0      10     2 testTags   Lscala/collection/immutable/Seq;
            0      10     3 testFun   Lscala/Function0;
            0      10     4   pos   Lorg/scalactic/source/Position;
    MethodParameters:
      Name                           Flags
      $this                          final synthetic
      testText                       final
      testTags                       final
      testFun                        final
      pos                            final

  public default void ignore(java.lang.String, scala.collection.immutable.Seq<org.scalatest.Tag>, scala.Function0<scala.concurrent.Future<org.scalatest.compatible.Assertion>>, org.scalactic.source.Position);
    descriptor: (Ljava/lang/String;Lscala/collection/immutable/Seq;Lscala/Function0;Lorg/scalactic/source/Position;)V
    flags: (0x0001) ACC_PUBLIC
    Code:
      stack=5, locals=5, args_size=5
         0: aload_0
         1: aload_1
         2: aload_2
         3: aload_3
         4: aload         4
         6: invokespecial #204                // InterfaceMethod ignoreImpl:(Ljava/lang/String;Lscala/collection/immutable/Seq;Lscala/Function0;Lorg/scalactic/source/Position;)V
         9: return
      LineNumberTable:
        line 391: 0
      LocalVariableTable:
        Start  Length  Slot  Name   Signature
            0      10     0  this   Lorg/scalatest/funspec/AsyncFunSpecLike;
            0      10     1 testText   Ljava/lang/String;
            0      10     2 testTags   Lscala/collection/immutable/Seq;
            0      10     3 testFun   Lscala/Function0;
            0      10     4   pos   Lorg/scalactic/source/Position;
    Signature: #125                         // (Ljava/lang/String;Lscala/collection/immutable/Seq<Lorg/scalatest/Tag;>;Lscala/Function0<Lscala/concurrent/Future<Lorg/scalatest/compatible/Assertion;>;>;Lorg/scalactic/source/Position;)V
    MethodParameters:
      Name                           Flags
      testText                       final
      testTags                       final
      testFun                        final
      pos                            final

  private void describeImpl(java.lang.String, scala.Function0<scala.runtime.BoxedUnit>, org.scalactic.source.Position);
    descriptor: (Ljava/lang/String;Lscala/Function0;Lorg/scalactic/source/Position;)V
    flags: (0x0002) ACC_PRIVATE
    Code:
      stack=7, locals=12, args_size=4
         0: aload_0
         1: invokeinterface #74,  1           // InterfaceMethod org$scalatest$funspec$AsyncFunSpecLike$$engine:()Lorg/scalatest/AsyncEngine;
         6: aload_1
         7: getstatic     #159                // Field scala/None$.MODULE$:Lscala/None$;
        10: aload_2
        11: invokedynamic #216,  0            // InvokeDynamic #3:apply:()Lscala/Function0;
        16: getstatic     #159                // Field scala/None$.MODULE$:Lscala/None$;
        19: aload_3
        20: invokevirtual #220                // Method org/scalatest/AsyncEngine.registerNestedBranch:(Ljava/lang/String;Lscala/Option;Lscala/Function0;Lscala/Function0;Lscala/Option;Lorg/scalactic/source/Position;)V
        23: goto          326
        26: astore        5
        28: aload         5
        30: astore        6
        32: aload         6
        34: instanceof    #222                // class org/scalatest/exceptions/TestFailedException
        37: ifeq          87
        40: aload         6
        42: checkcast     #222                // class org/scalatest/exceptions/TestFailedException
        45: astore        7
        47: new           #224                // class org/scalatest/exceptions/NotAllowedException
        50: dup
        51: getstatic     #229                // Field org/scalatest/FailureMessages$.MODULE$:Lorg/scalatest/FailureMessages$;
        54: invokevirtual #232                // Method org/scalatest/FailureMessages$.assertionShouldBePutInsideItOrTheyClauseNotDescribeClause:()Ljava/lang/String;
        57: new           #234                // class scala/Some
        60: dup
        61: aload         7
        63: invokespecial #238                // Method scala/Some."<init>":(Ljava/lang/Object;)V
        66: aload         7
        68: invokevirtual #242                // Method org/scalatest/exceptions/TestFailedException.position:()Lscala/Option;
        71: aload_3
        72: invokedynamic #252,  0            // InvokeDynamic #4:apply:(Lorg/scalactic/source/Position;)Lscala/Function0;
        77: invokevirtual #258                // Method scala/Option.getOrElse:(Lscala/Function0;)Ljava/lang/Object;
        80: checkcast     #260                // class org/scalactic/source/Position
        83: invokespecial #263                // Method org/scalatest/exceptions/NotAllowedException."<init>":(Ljava/lang/String;Lscala/Option;Lorg/scalactic/source/Position;)V
        86: athrow
        87: goto          90
        90: aload         6
        92: instanceof    #265                // class org/scalatest/exceptions/TestCanceledException
        95: ifeq          145
        98: aload         6
       100: checkcast     #265                // class org/scalatest/exceptions/TestCanceledException
       103: astore        8
       105: new           #224                // class org/scalatest/exceptions/NotAllowedException
       108: dup
       109: getstatic     #229                // Field org/scalatest/FailureMessages$.MODULE$:Lorg/scalatest/FailureMessages$;
       112: invokevirtual #232                // Method org/scalatest/FailureMessages$.assertionShouldBePutInsideItOrTheyClauseNotDescribeClause:()Ljava/lang/String;
       115: new           #234                // class scala/Some
       118: dup
       119: aload         8
       121: invokespecial #238                // Method scala/Some."<init>":(Ljava/lang/Object;)V
       124: aload         8
       126: invokevirtual #266                // Method org/scalatest/exceptions/TestCanceledException.position:()Lscala/Option;
       129: aload_3
       130: invokedynamic #271,  0            // InvokeDynamic #5:apply:(Lorg/scalactic/source/Position;)Lscala/Function0;
       135: invokevirtual #258                // Method scala/Option.getOrElse:(Lscala/Function0;)Ljava/lang/Object;
       138: checkcast     #260                // class org/scalactic/source/Position
       141: invokespecial #263                // Method org/scalatest/exceptions/NotAllowedException."<init>":(Ljava/lang/String;Lscala/Option;Lorg/scalactic/source/Position;)V
       144: athrow
       145: goto          148
       148: aload         6
       150: instanceof    #273                // class org/scalatest/exceptions/DuplicateTestNameException
       153: ifeq          229
       156: aload         6
       158: checkcast     #273                // class org/scalatest/exceptions/DuplicateTestNameException
       161: astore        9
       163: new           #224                // class org/scalatest/exceptions/NotAllowedException
       166: dup
       167: getstatic     #229                // Field org/scalatest/FailureMessages$.MODULE$:Lorg/scalatest/FailureMessages$;
       170: getstatic     #278                // Field org/scalactic/Prettifier$.MODULE$:Lorg/scalactic/Prettifier$;
       173: invokevirtual #282                // Method org/scalactic/Prettifier$.default:()Lorg/scalactic/Prettifier;
       176: getstatic     #287                // Field org/scalatest/UnquotedString$.MODULE$:Lorg/scalatest/UnquotedString$;
       179: aload         9
       181: invokevirtual #291                // Method org/scalatest/exceptions/DuplicateTestNameException.getClass:()Ljava/lang/Class;
       184: invokevirtual #296                // Method java/lang/Class.getName:()Ljava/lang/String;
       187: invokevirtual #299                // Method org/scalatest/UnquotedString$.apply:(Ljava/lang/String;)Lorg/scalatest/UnquotedString;
       190: aload_1
       191: aload         9
       193: invokevirtual #302                // Method org/scalatest/exceptions/DuplicateTestNameException.getMessage:()Ljava/lang/String;
       196: invokevirtual #306                // Method org/scalatest/FailureMessages$.exceptionWasThrownInDescribeClause:(Lorg/scalactic/Prettifier;Ljava/lang/Object;Ljava/lang/Object;Ljava/lang/Object;)Ljava/lang/String;
       199: new           #234                // class scala/Some
       202: dup
       203: aload         9
       205: invokespecial #238                // Method scala/Some."<init>":(Ljava/lang/Object;)V
       208: aload         9
       210: invokevirtual #307                // Method org/scalatest/exceptions/DuplicateTestNameException.position:()Lscala/Option;
       213: aload_3
       214: invokedynamic #312,  0            // InvokeDynamic #6:apply:(Lorg/scalactic/source/Position;)Lscala/Function0;
       219: invokevirtual #258                // Method scala/Option.getOrElse:(Lscala/Function0;)Ljava/lang/Object;
       222: checkcast     #260                // class org/scalactic/source/Position
       225: invokespecial #263                // Method org/scalatest/exceptions/NotAllowedException."<init>":(Ljava/lang/String;Lscala/Option;Lorg/scalactic/source/Position;)V
       228: athrow
       229: goto          232
       232: aload         6
       234: ifnull        305
       237: aload         6
       239: astore        10
       241: getstatic     #317                // Field org/scalatest/Suite$.MODULE$:Lorg/scalatest/Suite$;
       244: aload         10
       246: invokevirtual #321                // Method org/scalatest/Suite$.anExceptionThatShouldCauseAnAbort:(Ljava/lang/Throwable;)Z
       249: ifne          302
       252: new           #224                // class org/scalatest/exceptions/NotAllowedException
       255: dup
       256: getstatic     #229                // Field org/scalatest/FailureMessages$.MODULE$:Lorg/scalatest/FailureMessages$;
       259: getstatic     #278                // Field org/scalactic/Prettifier$.MODULE$:Lorg/scalactic/Prettifier$;
       262: invokevirtual #282                // Method org/scalactic/Prettifier$.default:()Lorg/scalactic/Prettifier;
       265: getstatic     #287                // Field org/scalatest/UnquotedString$.MODULE$:Lorg/scalatest/UnquotedString$;
       268: aload         10
       270: invokevirtual #322                // Method java/lang/Throwable.getClass:()Ljava/lang/Class;
       273: invokevirtual #296                // Method java/lang/Class.getName:()Ljava/lang/String;
       276: invokevirtual #299                // Method org/scalatest/UnquotedString$.apply:(Ljava/lang/String;)Lorg/scalatest/UnquotedString;
       279: aload_1
       280: aload         10
       282: invokevirtual #323                // Method java/lang/Throwable.getMessage:()Ljava/lang/String;
       285: invokevirtual #306                // Method org/scalatest/FailureMessages$.exceptionWasThrownInDescribeClause:(Lorg/scalactic/Prettifier;Ljava/lang/Object;Ljava/lang/Object;Ljava/lang/Object;)Ljava/lang/String;
       288: new           #234                // class scala/Some
       291: dup
       292: aload         10
       294: invokespecial #238                // Method scala/Some."<init>":(Ljava/lang/Object;)V
       297: aload_3
       298: invokespecial #263                // Method org/scalatest/exceptions/NotAllowedException."<init>":(Ljava/lang/String;Lscala/Option;Lorg/scalactic/source/Position;)V
       301: athrow
       302: goto          308
       305: goto          308
       308: aload         6
       310: ifnull        320
       313: aload         6
       315: astore        11
       317: aload         11
       319: athrow
       320: goto          323
       323: aload         5
       325: athrow
       326: return
      Exception table:
         from    to  target type
             0    23    26   Class java/lang/Throwable
      StackMapTable: number_of_entries = 13
        frame_type = 90 /* same_locals_1_stack_item */
          stack = [ class java/lang/Throwable ]
        frame_type = 254 /* append */
          offset_delta = 60
          locals = [ top, class java/lang/Throwable, class java/lang/Throwable ]
        frame_type = 2 /* same */
        frame_type = 54 /* same */
        frame_type = 2 /* same */
        frame_type = 251 /* same_frame_extended */
          offset_delta = 80
        frame_type = 2 /* same */
        frame_type = 255 /* full_frame */
          offset_delta = 69
          locals = [ class org/scalatest/funspec/AsyncFunSpecLike, class java/lang/String, class scala/Function0, class org/scalactic/source/Position, top, class java/lang/Throwable, class java/lang/Throwable, top, top, top, class java/lang/Throwable ]
          stack = []
        frame_type = 255 /* full_frame */
          offset_delta = 2
          locals = [ class org/scalatest/funspec/AsyncFunSpecLike, class java/lang/String, class scala/Function0, class org/scalactic/source/Position, top, class java/lang/Throwable, class java/lang/Throwable ]
          stack = []
        frame_type = 2 /* same */
        frame_type = 11 /* same */
        frame_type = 2 /* same */
        frame_type = 248 /* chop */
          offset_delta = 2
      LineNumberTable:
        line 400: 0
        line 403: 28
        line 403: 32
        line 404: 90
        line 405: 148
        line 406: 232
        line 407: 308
        line 399: 323
      LocalVariableTable:
        Start  Length  Slot  Name   Signature
            0     327     0  this   Lorg/scalatest/funspec/AsyncFunSpecLike;
            0     327     1 description   Ljava/lang/String;
            0     327     2   fun   Lscala/Function0;
            0     327     3   pos   Lorg/scalactic/source/Position;
    Signature: #207                         // (Ljava/lang/String;Lscala/Function0<Lscala/runtime/BoxedUnit;>;Lorg/scalactic/source/Position;)V
    MethodParameters:
      Name                           Flags
      description                    final
      fun                            final
      pos                            final

  public static void describe$(org.scalatest.funspec.AsyncFunSpecLike, java.lang.String, scala.Function0, org.scalactic.source.Position);
    descriptor: (Lorg/scalatest/funspec/AsyncFunSpecLike;Ljava/lang/String;Lscala/Function0;Lorg/scalactic/source/Position;)V
    flags: (0x1009) ACC_PUBLIC, ACC_STATIC, ACC_SYNTHETIC
    Code:
      stack=4, locals=4, args_size=4
         0: aload_0
         1: aload_1
         2: aload_2
         3: aload_3
         4: invokespecial #332                // InterfaceMethod describe:(Ljava/lang/String;Lscala/Function0;Lorg/scalactic/source/Position;)V
         7: return
      LineNumberTable:
        line 418: 0
      LocalVariableTable:
        Start  Length  Slot  Name   Signature
            0       8     0 $this   Lorg/scalatest/funspec/AsyncFunSpecLike;
            0       8     1 description   Ljava/lang/String;
            0       8     2   fun   Lscala/Function0;
            0       8     3   pos   Lorg/scalactic/source/Position;
    MethodParameters:
      Name                           Flags
      $this                          final synthetic
      description                    final
      fun                            final
      pos                            final

  public default void describe(java.lang.String, scala.Function0<scala.runtime.BoxedUnit>, org.scalactic.source.Position);
    descriptor: (Ljava/lang/String;Lscala/Function0;Lorg/scalactic/source/Position;)V
    flags: (0x0001) ACC_PUBLIC
    Code:
      stack=4, locals=4, args_size=4
         0: aload_0
         1: aload_1
         2: aload_2
         3: aload_3
         4: invokespecial #334                // InterfaceMethod describeImpl:(Ljava/lang/String;Lscala/Function0;Lorg/scalactic/source/Position;)V
         7: return
      LineNumberTable:
        line 419: 0
      LocalVariableTable:
        Start  Length  Slot  Name   Signature
            0       8     0  this   Lorg/scalatest/funspec/AsyncFunSpecLike;
            0       8     1 description   Ljava/lang/String;
            0       8     2   fun   Lscala/Function0;
            0       8     3   pos   Lorg/scalactic/source/Position;
    Signature: #207                         // (Ljava/lang/String;Lscala/Function0<Lscala/runtime/BoxedUnit;>;Lorg/scalactic/source/Position;)V
    MethodParameters:
      Name                           Flags
      description                    final
      fun                            final
      pos                            final

  public static scala.collection.immutable.Set testNames$(org.scalatest.funspec.AsyncFunSpecLike);
    descriptor: (Lorg/scalatest/funspec/AsyncFunSpecLike;)Lscala/collection/immutable/Set;
    flags: (0x1009) ACC_PUBLIC, ACC_STATIC, ACC_SYNTHETIC
    Code:
      stack=1, locals=1, args_size=1
         0: aload_0
         1: invokespecial #340                // InterfaceMethod testNames:()Lscala/collection/immutable/Set;
         4: areturn
      LineNumberTable:
        line 462: 0
      LocalVariableTable:
        Start  Length  Slot  Name   Signature
            0       5     0 $this   Lorg/scalatest/funspec/AsyncFunSpecLike;
    MethodParameters:
      Name                           Flags
      $this                          final synthetic

  public default scala.collection.immutable.Set<java.lang.String> testNames();
    descriptor: ()Lscala/collection/immutable/Set;
    flags: (0x0001) ACC_PUBLIC
    Code:
      stack=2, locals=1, args_size=1
         0: getstatic     #346                // Field org/scalatest/InsertionOrderSet$.MODULE$:Lorg/scalatest/InsertionOrderSet$;
         3: aload_0
         4: invokeinterface #74,  1           // InterfaceMethod org$scalatest$funspec$AsyncFunSpecLike$$engine:()Lorg/scalatest/AsyncEngine;
         9: invokevirtual #349                // Method org/scalatest/AsyncEngine.atomic:()Ljava/util/concurrent/atomic/AtomicReference;
        12: invokevirtual #86                 // Method java/util/concurrent/atomic/AtomicReference.get:()Ljava/lang/Object;
        15: checkcast     #30                 // class org/scalatest/AsyncSuperEngine$Bundle
        18: invokevirtual #353                // Method org/scalatest/AsyncSuperEngine$Bundle.testNamesList:()Lscala/collection/immutable/List;
        21: invokevirtual #356                // Method org/scalatest/InsertionOrderSet$.apply:(Lscala/collection/immutable/List;)Lscala/collection/immutable/Set;
        24: areturn
      LineNumberTable:
        line 464: 0
      LocalVariableTable:
        Start  Length  Slot  Name   Signature
            0      25     0  this   Lorg/scalatest/funspec/AsyncFunSpecLike;
    Signature: #341                         // ()Lscala/collection/immutable/Set<Ljava/lang/String;>;

  public static org.scalatest.Status runTest$(org.scalatest.funspec.AsyncFunSpecLike, java.lang.String, org.scalatest.Args);
    descriptor: (Lorg/scalatest/funspec/AsyncFunSpecLike;Ljava/lang/String;Lorg/scalatest/Args;)Lorg/scalatest/Status;
    flags: (0x1009) ACC_PUBLIC, ACC_STATIC, ACC_SYNTHETIC
    Code:
      stack=3, locals=3, args_size=3
         0: aload_0
         1: aload_1
         2: aload_2
         3: invokespecial #362                // InterfaceMethod runTest:(Ljava/lang/String;Lorg/scalatest/Args;)Lorg/scalatest/Status;
         6: areturn
      LineNumberTable:
        line 480: 0
      LocalVariableTable:
        Start  Length  Slot  Name   Signature
            0       7     0 $this   Lorg/scalatest/funspec/AsyncFunSpecLike;
            0       7     1 testName   Ljava/lang/String;
            0       7     2  args   Lorg/scalatest/Args;
    MethodParameters:
      Name                           Flags
      $this                          final synthetic
      testName                       final
      args                           final

  public default org.scalatest.Status runTest(java.lang.String, org.scalatest.Args);
    descriptor: (Ljava/lang/String;Lorg/scalatest/Args;)Lorg/scalatest/Status;
    flags: (0x0001) ACC_PUBLIC
    Code:
      stack=9, locals=3, args_size=3
         0: aload_0
         1: invokeinterface #74,  1           // InterfaceMethod org$scalatest$funspec$AsyncFunSpecLike$$engine:()Lorg/scalatest/AsyncEngine;
         6: aload_0
         7: aload_1
         8: aload_2
         9: iconst_1
        10: aload_0
        11: invokeinterface #367,  1          // InterfaceMethod parallelAsyncTestExecution:()Z
        16: aload_0
        17: aload_2
        18: aload_1
        19: invokedynamic #379,  0            // InvokeDynamic #7:apply:(Lorg/scalatest/funspec/AsyncFunSpecLike;Lorg/scalatest/Args;Ljava/lang/String;)Lscala/Function2;
        24: aload_0
        25: invokeinterface #383,  1          // InterfaceMethod executionContext:()Lscala/concurrent/ExecutionContext;
        30: invokevirtual #387                // Method org/scalatest/AsyncEngine.runTestImpl:(Lorg/scalatest/Suite;Ljava/lang/String;Lorg/scalatest/Args;ZZLscala/Function2;Lscala/concurrent/ExecutionContext;)Lorg/scalatest/Status;
        33: areturn
      LineNumberTable:
        line 500: 0
      LocalVariableTable:
        Start  Length  Slot  Name   Signature
            0      34     0  this   Lorg/scalatest/funspec/AsyncFunSpecLike;
            0      34     1 testName   Ljava/lang/String;
            0      34     2  args   Lorg/scalatest/Args;
    MethodParameters:
      Name                           Flags
      testName                       final
      args                           final

  public static scala.collection.immutable.Map tags$(org.scalatest.funspec.AsyncFunSpecLike);
    descriptor: (Lorg/scalatest/funspec/AsyncFunSpecLike;)Lscala/collection/immutable/Map;
    flags: (0x1009) ACC_PUBLIC, ACC_STATIC, ACC_SYNTHETIC
    Code:
      stack=1, locals=1, args_size=1
         0: aload_0
         1: invokespecial #393                // InterfaceMethod tags:()Lscala/collection/immutable/Map;
         4: areturn
      LineNumberTable:
        line 518: 0
      LocalVariableTable:
        Start  Length  Slot  Name   Signature
            0       5     0 $this   Lorg/scalatest/funspec/AsyncFunSpecLike;
    MethodParameters:
      Name                           Flags
      $this                          final synthetic

  public default scala.collection.immutable.Map<java.lang.String, scala.collection.immutable.Set<java.lang.String>> tags();
    descriptor: ()Lscala/collection/immutable/Map;
    flags: (0x0001) ACC_PUBLIC
    Code:
      stack=3, locals=1, args_size=1
         0: getstatic     #317                // Field org/scalatest/Suite$.MODULE$:Lorg/scalatest/Suite$;
         3: aload_0
         4: invokeinterface #74,  1           // InterfaceMethod org$scalatest$funspec$AsyncFunSpecLike$$engine:()Lorg/scalatest/AsyncEngine;
         9: invokevirtual #349                // Method org/scalatest/AsyncEngine.atomic:()Ljava/util/concurrent/atomic/AtomicReference;
        12: invokevirtual #86                 // Method java/util/concurrent/atomic/AtomicReference.get:()Ljava/lang/Object;
        15: checkcast     #30                 // class org/scalatest/AsyncSuperEngine$Bundle
        18: invokevirtual #397                // Method org/scalatest/AsyncSuperEngine$Bundle.tagsMap:()Lscala/collection/immutable/Map;
        21: aload_0
        22: invokevirtual #401                // Method org/scalatest/Suite$.autoTagClassAnnotations:(Lscala/collection/immutable/Map;Lorg/scalatest/Suite;)Lscala/collection/immutable/Map;
        25: areturn
      LineNumberTable:
        line 518: 0
      LocalVariableTable:
        Start  Length  Slot  Name   Signature
            0      26     0  this   Lorg/scalatest/funspec/AsyncFunSpecLike;
    Signature: #394                         // ()Lscala/collection/immutable/Map<Ljava/lang/String;Lscala/collection/immutable/Set<Ljava/lang/String;>;>;

  public static org.scalatest.Status runTests$(org.scalatest.funspec.AsyncFunSpecLike, scala.Option, org.scalatest.Args);
    descriptor: (Lorg/scalatest/funspec/AsyncFunSpecLike;Lscala/Option;Lorg/scalatest/Args;)Lorg/scalatest/Status;
    flags: (0x1009) ACC_PUBLIC, ACC_STATIC, ACC_SYNTHETIC
    Code:
      stack=3, locals=3, args_size=3
         0: aload_0
         1: aload_1
         2: aload_2
         3: invokespecial #406                // InterfaceMethod runTests:(Lscala/Option;Lorg/scalatest/Args;)Lorg/scalatest/Status;
         6: areturn
      LineNumberTable:
        line 532: 0
      LocalVariableTable:
        Start  Length  Slot  Name   Signature
            0       7     0 $this   Lorg/scalatest/funspec/AsyncFunSpecLike;
            0       7     1 testName   Lscala/Option;
            0       7     2  args   Lorg/scalatest/Args;
    MethodParameters:
      Name                           Flags
      $this                          final synthetic
      testName                       final
      args                           final

  public default org.scalatest.Status runTests(scala.Option<java.lang.String>, org.scalatest.Args);
    descriptor: (Lscala/Option;Lorg/scalatest/Args;)Lorg/scalatest/Status;
    flags: (0x0001) ACC_PUBLIC
    Code:
      stack=7, locals=3, args_size=3
         0: aload_0
         1: invokeinterface #74,  1           // InterfaceMethod org$scalatest$funspec$AsyncFunSpecLike$$engine:()Lorg/scalatest/AsyncEngine;
         6: aload_0
         7: aload_1
         8: aload_2
         9: iconst_1
        10: aload_0
        11: invokeinterface #367,  1          // InterfaceMethod parallelAsyncTestExecution:()Z
        16: aload_0
        17: invokedynamic #416,  0            // InvokeDynamic #8:apply:(Lorg/scalatest/funspec/AsyncFunSpecLike;)Lscala/Function2;
        22: invokevirtual #420                // Method org/scalatest/AsyncEngine.runTestsImpl:(Lorg/scalatest/Suite;Lscala/Option;Lorg/scalatest/Args;ZZLscala/Function2;)Lorg/scalatest/Status;
        25: areturn
      LineNumberTable:
        line 533: 0
      LocalVariableTable:
        Start  Length  Slot  Name   Signature
            0      26     0  this   Lorg/scalatest/funspec/AsyncFunSpecLike;
            0      26     1 testName   Lscala/Option;
            0      26     2  args   Lorg/scalatest/Args;
    Signature: #408                         // (Lscala/Option<Ljava/lang/String;>;Lorg/scalatest/Args;)Lorg/scalatest/Status;
    MethodParameters:
      Name                           Flags
      testName                       final
      args                           final

  public static org.scalatest.Status run$(org.scalatest.funspec.AsyncFunSpecLike, scala.Option, org.scalatest.Args);
    descriptor: (Lorg/scalatest/funspec/AsyncFunSpecLike;Lscala/Option;Lorg/scalatest/Args;)Lorg/scalatest/Status;
    flags: (0x1009) ACC_PUBLIC, ACC_STATIC, ACC_SYNTHETIC
    Code:
      stack=3, locals=3, args_size=3
         0: aload_0
         1: aload_1
         2: aload_2
         3: invokespecial #424                // InterfaceMethod run:(Lscala/Option;Lorg/scalatest/Args;)Lorg/scalatest/Status;
         6: areturn
      LineNumberTable:
        line 536: 0
      LocalVariableTable:
        Start  Length  Slot  Name   Signature
            0       7     0 $this   Lorg/scalatest/funspec/AsyncFunSpecLike;
            0       7     1 testName   Lscala/Option;
            0       7     2  args   Lorg/scalatest/Args;
    MethodParameters:
      Name                           Flags
      $this                          final synthetic
      testName                       final
      args                           final

  public default org.scalatest.Status run(scala.Option<java.lang.String>, org.scalatest.Args);
    descriptor: (Lscala/Option;Lorg/scalatest/Args;)Lorg/scalatest/Status;
    flags: (0x0001) ACC_PUBLIC
    Code:
      stack=6, locals=3, args_size=3
         0: aload_0
         1: invokeinterface #74,  1           // InterfaceMethod org$scalatest$funspec$AsyncFunSpecLike$$engine:()Lorg/scalatest/AsyncEngine;
         6: aload_0
         7: aload_1
         8: aload_2
         9: aload_0
        10: invokeinterface #367,  1          // InterfaceMethod parallelAsyncTestExecution:()Z
        15: aload_0
        16: invokedynamic #430,  0            // InvokeDynamic #9:apply:(Lorg/scalatest/funspec/AsyncFunSpecLike;)Lscala/Function2;
        21: invokevirtual #434                // Method org/scalatest/AsyncEngine.runImpl:(Lorg/scalatest/Suite;Lscala/Option;Lorg/scalatest/Args;ZLscala/Function2;)Lorg/scalatest/Status;
        24: areturn
      LineNumberTable:
        line 537: 0
      LocalVariableTable:
        Start  Length  Slot  Name   Signature
            0      25     0  this   Lorg/scalatest/funspec/AsyncFunSpecLike;
            0      25     1 testName   Lscala/Option;
            0      25     2  args   Lorg/scalatest/Args;
    Signature: #408                         // (Lscala/Option<Ljava/lang/String;>;Lorg/scalatest/Args;)Lorg/scalatest/Status;
    MethodParameters:
      Name                           Flags
      testName                       final
      args                           final

  public abstract org.scalatest.verbs.BehaveWord behave();
    descriptor: ()Lorg/scalatest/verbs/BehaveWord;
    flags: (0x0401) ACC_PUBLIC, ACC_ABSTRACT

  public abstract java.lang.String styleName();
    descriptor: ()Ljava/lang/String;
    flags: (0x0401) ACC_PUBLIC, ACC_ABSTRACT
    Deprecated: true

  public static org.scalatest.TestData testDataFor$(org.scalatest.funspec.AsyncFunSpecLike, java.lang.String, org.scalatest.ConfigMap);
    descriptor: (Lorg/scalatest/funspec/AsyncFunSpecLike;Ljava/lang/String;Lorg/scalatest/ConfigMap;)Lorg/scalatest/TestData;
    flags: (0x1009) ACC_PUBLIC, ACC_STATIC, ACC_SYNTHETIC
    Code:
      stack=3, locals=3, args_size=3
         0: aload_0
         1: aload_1
         2: aload_2
         3: invokespecial #444                // InterfaceMethod testDataFor:(Ljava/lang/String;Lorg/scalatest/ConfigMap;)Lorg/scalatest/TestData;
         6: areturn
      LineNumberTable:
        line 568: 0
      LocalVariableTable:
        Start  Length  Slot  Name   Signature
            0       7     0 $this   Lorg/scalatest/funspec/AsyncFunSpecLike;
            0       7     1 testName   Ljava/lang/String;
            0       7     2 theConfigMap   Lorg/scalatest/ConfigMap;
    MethodParameters:
      Name                           Flags
      $this                          final synthetic
      testName                       final
      theConfigMap                   final

  public default org.scalatest.TestData testDataFor(java.lang.String, org.scalatest.ConfigMap);
    descriptor: (Ljava/lang/String;Lorg/scalatest/ConfigMap;)Lorg/scalatest/TestData;
    flags: (0x0001) ACC_PUBLIC
    Code:
      stack=4, locals=3, args_size=3
         0: aload_0
         1: invokeinterface #74,  1           // InterfaceMethod org$scalatest$funspec$AsyncFunSpecLike$$engine:()Lorg/scalatest/AsyncEngine;
         6: aload_1
         7: aload_2
         8: aload_0
         9: invokevirtual #449                // Method org/scalatest/AsyncEngine.createTestDataFor:(Ljava/lang/String;Lorg/scalatest/ConfigMap;Lorg/scalatest/Suite;)Lorg/scalatest/TestData;
        12: areturn
      LineNumberTable:
        line 568: 0
      LocalVariableTable:
        Start  Length  Slot  Name   Signature
            0      13     0  this   Lorg/scalatest/funspec/AsyncFunSpecLike;
            0      13     1 testName   Ljava/lang/String;
            0      13     2 theConfigMap   Lorg/scalatest/ConfigMap;
    MethodParameters:
      Name                           Flags
      testName                       final
      theConfigMap                   final

  public static org.scalatest.ConfigMap testDataFor$default$2$(org.scalatest.funspec.AsyncFunSpecLike);
    descriptor: (Lorg/scalatest/funspec/AsyncFunSpecLike;)Lorg/scalatest/ConfigMap;
    flags: (0x1009) ACC_PUBLIC, ACC_STATIC, ACC_SYNTHETIC
    Code:
      stack=1, locals=1, args_size=1
         0: aload_0
         1: invokespecial #455                // InterfaceMethod testDataFor$default$2:()Lorg/scalatest/ConfigMap;
         4: areturn
      LineNumberTable:
        line 568: 0
      LocalVariableTable:
        Start  Length  Slot  Name   Signature
            0       5     0 $this   Lorg/scalatest/funspec/AsyncFunSpecLike;
    MethodParameters:
      Name                           Flags
      $this                          final synthetic

  public default org.scalatest.ConfigMap testDataFor$default$2();
    descriptor: ()Lorg/scalatest/ConfigMap;
    flags: (0x0001) ACC_PUBLIC
    Code:
      stack=1, locals=1, args_size=1
         0: getstatic     #460                // Field org/scalatest/ConfigMap$.MODULE$:Lorg/scalatest/ConfigMap$;
         3: invokevirtual #463                // Method org/scalatest/ConfigMap$.empty:()Lorg/scalatest/ConfigMap;
         6: areturn
      LineNumberTable:
        line 568: 0
      LocalVariableTable:
        Start  Length  Slot  Name   Signature
            0       7     0  this   Lorg/scalatest/funspec/AsyncFunSpecLike;

  public static java.lang.String $anonfun$engine$1();
    descriptor: ()Ljava/lang/String;
    flags: (0x1009) ACC_PUBLIC, ACC_STATIC, ACC_SYNTHETIC
    Code:
      stack=1, locals=0, args_size=0
         0: getstatic     #469                // Field org/scalatest/Resources$.MODULE$:Lorg/scalatest/Resources$;
         3: invokevirtual #472                // Method org/scalatest/Resources$.concurrentSpecMod:()Ljava/lang/String;
         6: areturn
      LineNumberTable:
        line 53: 0

  public static java.lang.String $anonfun$registerAsyncTestImpl$1();
    descriptor: ()Ljava/lang/String;
    flags: (0x1009) ACC_PUBLIC, ACC_STATIC, ACC_SYNTHETIC
    Code:
      stack=1, locals=0, args_size=0
         0: getstatic     #469                // Field org/scalatest/Resources$.MODULE$:Lorg/scalatest/Resources$;
         3: invokevirtual #475                // Method org/scalatest/Resources$.testCannotBeNestedInsideAnotherTest:()Ljava/lang/String;
         6: areturn
      LineNumberTable:
        line 100: 0

  public static java.lang.String $anonfun$registerIgnoredAsyncTestImpl$1();
    descriptor: ()Ljava/lang/String;
    flags: (0x1009) ACC_PUBLIC, ACC_STATIC, ACC_SYNTHETIC
    Code:
      stack=1, locals=0, args_size=0
         0: getstatic     #469                // Field org/scalatest/Resources$.MODULE$:Lorg/scalatest/Resources$;
         3: invokevirtual #475                // Method org/scalatest/Resources$.testCannotBeNestedInsideAnotherTest:()Ljava/lang/String;
         6: areturn
      LineNumberTable:
        line 113: 0

  public static java.lang.String $anonfun$ignoreImpl$1();
    descriptor: ()Ljava/lang/String;
    flags: (0x1009) ACC_PUBLIC, ACC_STATIC, ACC_SYNTHETIC
    Code:
      stack=1, locals=0, args_size=0
         0: getstatic     #469                // Field org/scalatest/Resources$.MODULE$:Lorg/scalatest/Resources$;
         3: invokevirtual #478                // Method org/scalatest/Resources$.ignoreCannotAppearInsideAnItOrAThey:()Ljava/lang/String;
         6: areturn
      LineNumberTable:
        line 368: 0

  public static java.lang.String $anonfun$describeImpl$1();
    descriptor: ()Ljava/lang/String;
    flags: (0x1009) ACC_PUBLIC, ACC_STATIC, ACC_SYNTHETIC
    Code:
      stack=1, locals=0, args_size=0
         0: getstatic     #469                // Field org/scalatest/Resources$.MODULE$:Lorg/scalatest/Resources$;
         3: invokevirtual #481                // Method org/scalatest/Resources$.describeCannotAppearInsideAnIt:()Ljava/lang/String;
         6: areturn
      LineNumberTable:
        line 400: 0

  public static org.scalactic.source.Position $anonfun$describeImpl$2(org.scalactic.source.Position);
    descriptor: (Lorg/scalactic/source/Position;)Lorg/scalactic/source/Position;
    flags: (0x1009) ACC_PUBLIC, ACC_STATIC, ACC_SYNTHETIC
    Code:
      stack=1, locals=1, args_size=1
         0: aload_0
         1: areturn
      LineNumberTable:
        line 403: 0
      LocalVariableTable:
        Start  Length  Slot  Name   Signature
            0       2     0 pos$1   Lorg/scalactic/source/Position;
    MethodParameters:
      Name                           Flags
      pos$1                          final

  public static org.scalactic.source.Position $anonfun$describeImpl$3(org.scalactic.source.Position);
    descriptor: (Lorg/scalactic/source/Position;)Lorg/scalactic/source/Position;
    flags: (0x1009) ACC_PUBLIC, ACC_STATIC, ACC_SYNTHETIC
    Code:
      stack=1, locals=1, args_size=1
         0: aload_0
         1: areturn
      LineNumberTable:
        line 404: 0
      LocalVariableTable:
        Start  Length  Slot  Name   Signature
            0       2     0 pos$1   Lorg/scalactic/source/Position;
    MethodParameters:
      Name                           Flags
      pos$1                          final

  public static org.scalactic.source.Position $anonfun$describeImpl$4(org.scalactic.source.Position);
    descriptor: (Lorg/scalactic/source/Position;)Lorg/scalactic/source/Position;
    flags: (0x1009) ACC_PUBLIC, ACC_STATIC, ACC_SYNTHETIC
    Code:
      stack=1, locals=1, args_size=1
         0: aload_0
         1: areturn
      LineNumberTable:
        line 405: 0
      LocalVariableTable:
        Start  Length  Slot  Name   Signature
            0       2     0 pos$1   Lorg/scalactic/source/Position;
    MethodParameters:
      Name                           Flags
      pos$1                          final

  private org.scalatest.AsyncOutcome invokeWithAsyncFixture$1(org.scalatest.AsyncSuperEngine$TestLeaf, scala.Function1, org.scalatest.Args, java.lang.String);
    descriptor: (Lorg/scalatest/AsyncSuperEngine$TestLeaf;Lscala/Function1;Lorg/scalatest/Args;Ljava/lang/String;)Lorg/scalatest/AsyncOutcome;
    flags: (0x0002) ACC_PRIVATE
    Code:
      stack=8, locals=7, args_size=5
         0: aload_3
         1: invokevirtual #493                // Method org/scalatest/Args.configMap:()Lorg/scalatest/ConfigMap;
         4: astore        5
         6: aload_0
         7: aload         4
         9: aload         5
        11: invokeinterface #444,  3          // InterfaceMethod testDataFor:(Ljava/lang/String;Lorg/scalatest/ConfigMap;)Lorg/scalatest/TestData;
        16: astore        6
        18: new           #495                // class org/scalatest/FutureAsyncOutcome
        21: dup
        22: aload_0
        23: new           #41                 // class org/scalatest/funspec/AsyncFunSpecLike$$anon$1
        26: dup
        27: aconst_null
        28: aload         6
        30: aload_1
        31: invokespecial #498                // Method org/scalatest/funspec/AsyncFunSpecLike$$anon$1."<init>":(Lorg/scalatest/funspec/AsyncFunSpecLike;Lorg/scalatest/TestData;Lorg/scalatest/AsyncSuperEngine$TestLeaf;)V
        34: invokeinterface #502,  2          // InterfaceMethod withFixture:(Lorg/scalatest/AsyncTestSuite$NoArgAsyncTest;)Lorg/scalatest/FutureOutcome;
        39: invokevirtual #508                // Method org/scalatest/FutureOutcome.underlying:()Lscala/concurrent/Future;
        42: aload_2
        43: aload_0
        44: invokeinterface #383,  1          // InterfaceMethod executionContext:()Lscala/concurrent/ExecutionContext;
        49: invokespecial #511                // Method org/scalatest/FutureAsyncOutcome."<init>":(Lscala/concurrent/Future;Lscala/Function1;Lscala/concurrent/ExecutionContext;)V
        52: areturn
      LineNumberTable:
        line 482: 0
        line 483: 6
        line 484: 18
        line 485: 22
        line 486: 23
        line 496: 42
        line 484: 43
      LocalVariableTable:
        Start  Length  Slot  Name   Signature
            6      46     5 theConfigMap   Lorg/scalatest/ConfigMap;
           18      34     6 testData   Lorg/scalatest/TestData;
            0      53     0  this   Lorg/scalatest/funspec/AsyncFunSpecLike;
            0      53     1 theTest   Lorg/scalatest/AsyncSuperEngine$TestLeaf;
            0      53     2 onCompleteFun   Lscala/Function1;
            0      53     3 args$1   Lorg/scalatest/Args;
            0      53     4 testName$1   Ljava/lang/String;
    MethodParameters:
      Name                           Flags
      theTest                        final
      onCompleteFun                  final
      args$1                         final
      testName$1                     final

  public static org.scalatest.AsyncOutcome $anonfun$runTest$1(org.scalatest.funspec.AsyncFunSpecLike, org.scalatest.Args, java.lang.String, org.scalatest.AsyncSuperEngine$TestLeaf, scala.Function1);
    descriptor: (Lorg/scalatest/funspec/AsyncFunSpecLike;Lorg/scalatest/Args;Ljava/lang/String;Lorg/scalatest/AsyncSuperEngine$TestLeaf;Lscala/Function1;)Lorg/scalatest/AsyncOutcome;
    flags: (0x1009) ACC_PUBLIC, ACC_STATIC, ACC_SYNTHETIC
    Code:
      stack=5, locals=5, args_size=5
         0: aload_0
         1: aload_3
         2: aload         4
         4: aload_1
         5: aload_2
         6: invokespecial #517                // InterfaceMethod invokeWithAsyncFixture$1:(Lorg/scalatest/AsyncSuperEngine$TestLeaf;Lscala/Function1;Lorg/scalatest/Args;Ljava/lang/String;)Lorg/scalatest/AsyncOutcome;
         9: areturn
      LineNumberTable:
        line 500: 0
      LocalVariableTable:
        Start  Length  Slot  Name   Signature
            0      10     0 $this   Lorg/scalatest/funspec/AsyncFunSpecLike;
            0      10     1 args$1   Lorg/scalatest/Args;
            0      10     2 testName$1   Ljava/lang/String;
            0      10     3 theTest   Lorg/scalatest/AsyncSuperEngine$TestLeaf;
            0      10     4 onCompleteFun   Lscala/Function1;
    MethodParameters:
      Name                           Flags
      $this                          final synthetic
      args$1                         final
      testName$1                     final
      theTest                        final
      onCompleteFun                  final

  public static org.scalatest.Status $anonfun$runTests$1(org.scalatest.funspec.AsyncFunSpecLike, java.lang.String, org.scalatest.Args);
    descriptor: (Lorg/scalatest/funspec/AsyncFunSpecLike;Ljava/lang/String;Lorg/scalatest/Args;)Lorg/scalatest/Status;
    flags: (0x1009) ACC_PUBLIC, ACC_STATIC, ACC_SYNTHETIC
    Code:
      stack=3, locals=3, args_size=3
         0: aload_0
         1: aload_1
         2: aload_2
         3: invokeinterface #362,  3          // InterfaceMethod runTest:(Ljava/lang/String;Lorg/scalatest/Args;)Lorg/scalatest/Status;
         8: areturn
      LineNumberTable:
        line 533: 0
      LocalVariableTable:
        Start  Length  Slot  Name   Signature
            0       9     0 $this   Lorg/scalatest/funspec/AsyncFunSpecLike;
            0       9     1 testName   Ljava/lang/String;
            0       9     2  args   Lorg/scalatest/Args;
    MethodParameters:
      Name                           Flags
      $this                          final synthetic
      testName                       final
      args                           final

  public static org.scalatest.Status $anonfun$run$1(org.scalatest.funspec.AsyncFunSpecLike, scala.Option, org.scalatest.Args);
    descriptor: (Lorg/scalatest/funspec/AsyncFunSpecLike;Lscala/Option;Lorg/scalatest/Args;)Lorg/scalatest/Status;
    flags: (0x1009) ACC_PUBLIC, ACC_STATIC, ACC_SYNTHETIC
    Code:
      stack=3, locals=3, args_size=3
         0: aload_0
         1: aload_1
         2: aload_2
         3: invokeinterface #519,  3          // InterfaceMethod org$scalatest$funspec$AsyncFunSpecLike$$super$run:(Lscala/Option;Lorg/scalatest/Args;)Lorg/scalatest/Status;
         8: areturn
      LineNumberTable:
        line 537: 0
      LocalVariableTable:
        Start  Length  Slot  Name   Signature
            0       9     0 $this   Lorg/scalatest/funspec/AsyncFunSpecLike;
            0       9     1 testName   Lscala/Option;
            0       9     2  args   Lorg/scalatest/Args;
    MethodParameters:
      Name                           Flags
      $this                          final synthetic
      testName                       final
      args                           final

  public static void $init$(org.scalatest.funspec.AsyncFunSpecLike);
    descriptor: (Lorg/scalatest/funspec/AsyncFunSpecLike;)V
    flags: (0x0009) ACC_PUBLIC, ACC_STATIC
    Code:
      stack=5, locals=1, args_size=1
         0: aload_0
         1: new           #76                 // class org/scalatest/AsyncEngine
         4: dup
         5: invokedynamic #525,  0            // InvokeDynamic #10:apply:()Lscala/Function0;
        10: ldc_w         #527                // String FunSpec
        13: invokespecial #530                // Method org/scalatest/AsyncEngine."<init>":(Lscala/Function0;Ljava/lang/String;)V
        16: invokeinterface #532,  2          // InterfaceMethod org$scalatest$funspec$AsyncFunSpecLike$_setter_$org$scalatest$funspec$AsyncFunSpecLike$$engine_$eq:(Lorg/scalatest/AsyncEngine;)V
        21: aload_0
        22: new           #43                 // class org/scalatest/funspec/AsyncFunSpecLike$ItWord
        25: dup
        26: aload_0
        27: invokespecial #534                // Method org/scalatest/funspec/AsyncFunSpecLike$ItWord."<init>":(Lorg/scalatest/funspec/AsyncFunSpecLike;)V
        30: invokeinterface #536,  2          // InterfaceMethod org$scalatest$funspec$AsyncFunSpecLike$_setter_$it_$eq:(Lorg/scalatest/funspec/AsyncFunSpecLike$ItWord;)V
        35: aload_0
        36: new           #46                 // class org/scalatest/funspec/AsyncFunSpecLike$TheyWord
        39: dup
        40: aload_0
        41: invokespecial #537                // Method org/scalatest/funspec/AsyncFunSpecLike$TheyWord."<init>":(Lorg/scalatest/funspec/AsyncFunSpecLike;)V
        44: invokeinterface #539,  2          // InterfaceMethod org$scalatest$funspec$AsyncFunSpecLike$_setter_$they_$eq:(Lorg/scalatest/funspec/AsyncFunSpecLike$TheyWord;)V
        49: aload_0
        50: new           #541                // class org/scalatest/verbs/BehaveWord
        53: dup
        54: invokespecial #544                // Method org/scalatest/verbs/BehaveWord."<init>":()V
        57: invokeinterface #546,  2          // InterfaceMethod org$scalatest$funspec$AsyncFunSpecLike$_setter_$behave_$eq:(Lorg/scalatest/verbs/BehaveWord;)V
        62: aload_0
        63: ldc_w         #548                // String org.scalatest.FunSpec
        66: invokeinterface #550,  2          // InterfaceMethod org$scalatest$funspec$AsyncFunSpecLike$_setter_$styleName_$eq:(Ljava/lang/String;)V
        71: return
      LineNumberTable:
        line 53: 0
        line 244: 21
        line 365: 35
        line 557: 49
        line 566: 62
        line 51: 71
      LocalVariableTable:
        Start  Length  Slot  Name   Signature
            0      72     0 $this   Lorg/scalatest/funspec/AsyncFunSpecLike;
    MethodParameters:
      Name                           Flags
      $this                          final synthetic

  private static java.lang.Object $deserializeLambda$(java.lang.invoke.SerializedLambda);
    descriptor: (Ljava/lang/invoke/SerializedLambda;)Ljava/lang/Object;
    flags: (0x100a) ACC_PRIVATE, ACC_STATIC, ACC_SYNTHETIC
    Code:
      stack=1, locals=1, args_size=1
         0: aload_0
         1: invokedynamic #562,  0            // InvokeDynamic #11:lambdaDeserialize:(Ljava/lang/invoke/SerializedLambda;)Ljava/lang/Object;
         6: areturn
}
InnerClasses:
  public static final #28= #25 of #27;    // Lookup=class java/lang/invoke/MethodHandles$Lookup of class java/lang/invoke/MethodHandles
  public #33= #30 of #32;                 // Bundle=class org/scalatest/AsyncSuperEngine$Bundle of class org/scalatest/AsyncSuperEngine
  public #36= #35 of #32;                 // TestLeaf=class org/scalatest/AsyncSuperEngine$TestLeaf of class org/scalatest/AsyncSuperEngine
  public #39= #38 of #6;                  // NoArgAsyncTest=class org/scalatest/AsyncTestSuite$NoArgAsyncTest of class org/scalatest/AsyncTestSuite
  public final #41;                       // class org/scalatest/funspec/AsyncFunSpecLike$$anon$1
  public #44= #43 of #2;                  // ItWord=class org/scalatest/funspec/AsyncFunSpecLike$ItWord of class org/scalatest/funspec/AsyncFunSpecLike
  public #47= #46 of #2;                  // TheyWord=class org/scalatest/funspec/AsyncFunSpecLike$TheyWord of class org/scalatest/funspec/AsyncFunSpecLike
SourceFile: "AsyncFunSpecLike.scala"
RuntimeVisibleAnnotations:
  0: #18(#19=[s#20])
    org.scalatest.Finders(
      value=["org.scalatest.finders.FunSpecFinder"]
    )
  1: #21(#22=s#23)
    scala.reflect.ScalaSignature(
      bytes="\u0006\u0005\t\rgaB\u0014)!\u0003\r\ta\f\u0005\u0006\u0013\u0002!\tA\u0013\u0005\b\u001d\u0002\u0011\r\u0011\"\u0004P\u0011\u0015\u0019\u0006\u0001\"\u0005U\u0011\u0015A\u0006\u0001\"\u0005Z\u0011\u0015i\u0006\u0001\"\u0005_\u0011\u0015\u0011\u0007\u0001\"\u0005d\u0011\u00159\u0007\u0001\"\u0004i\u0011\u001d\t)\u0004\u0001C\u0003\u0003oAq!!\u0012\u0001\t\u001b\t9\u0005C\u0004\u0002T\u0001!)!!\u0016\u0007\r\u0005\r\u0004\u0001CA3\u0011\u001d\t9g\u0003C\u0001\u0003SBq!a\u001c\f\t\u001b\t\t\bC\u0004\u0002\u0000-!\t!!!\t\u000f\u0005=5\u0002\"\u0001\u0002\u0012\"9\u00111U\u0006\u0005\u0002\u0005\u0015\u0006\"CAU\u0001\t\u0007I\u0011CAV\r\u0019\ti\u000b\u0001\u0005\u00020\"9\u0011q\r\n\u0005\u0002\u0005E\u0006bBA8%\u00115\u0011Q\u0017\u0005\b\u0003\u007f\u0012B\u0011AAa\u0011\u001d\tyI\u0005C\u0001\u0003\u001fDq!a)\u0013\t\u0003\t\u0019\u000eC\u0005\u0002X\u0002\u0011\r\u0011\"\u0005\u0002Z\"9\u00111\u001c\u0001\u0005\u000e\u0005u\u0007bBAu\u0001\u0011E\u00111\u001e\u0005\b\u0003s\u0004AQBA~\u0011\u001d\u0011Y\u0001\u0001C\t\u0005\u001bAqA!\u0007\u0001\t\u0003\u0012Y\u0002C\u0004\u0003$\u0001!\tF!\n\t\u000f\tm\u0002\u0001\"\u0011\u0003>!9!Q\t\u0001\u0005R\t\u001d\u0003b\u0002B*\u0001\u0011\u0005#Q\u000b\u0005\n\u00057\u0002!\u0019!C\t\u0005;B\u0011Ba\u0018\u0001\u0005\u0004%)E!\u0019\t\u000f\t]\u0004\u0001\"\u0011\u0003z!I!Q\u0012\u0001\u0012\u0002\u0013\u0005!q\u0012\u0005\u000f\u0005K\u0003\u0001\u0013aA\u0001\u0002\u0013%!q\u0015BW\u0005A\t5/\u001f8d\rVt7\u000b]3d\u0019&\\WM\u0003\u0002*U\u00059a-\u001e8ta\u0016\u001c\'BA\u0016-\u0003%\u00198-\u00197bi\u0016\u001cHOC\u0001.\u0003\ry\'oZ\u0002\u0001\'!\u0001\u0001G\u000e\u001e>\u0001\u000e3\u0005CA\u00195\u001b\u0005\u0011$\"A\u001a\u0002\u000bM\u001c\u0017\r\\1\n\u0005U\u0012$AB!osJ+g\r\u0005\u00028q5\t!&\u0003\u0002:U\tq\u0011i]=oGR+7\u000f^*vSR,\u0007CA\u001c<\u0013\ta$FA\u000bBgft7\rV3tiJ+w-[:ue\u0006$\u0018n\u001c8\u0011\u0005]r\u0014BA +\u0005%IeNZ8s[&tw\r\u0005\u00028\u0003&\u0011!I\u000b\u0002\n\u001d>$\u0018NZ=j]\u001e\u0004\"a\u000e#\n\u0005\u0015S#\u0001C!mKJ$\u0018N\\4\u0011\u0005]:\u0015B\u0001%+\u0005-!unY;nK:$\u0018N\\4\u0002\r\u0011Jg.\u001b;%)\u0005Y\u0005CA\u0019M\u0013\ti%G\u0001\u0003V]&$\u0018AB3oO&tW-F\u0001Q!\t9\u0014+\u0003\u0002SU\tY\u0011i]=oG\u0016sw-\u001b8f\u0003\u0011IgNZ8\u0016\u0003U\u0003\"a\u000e,\n\u0005]S#\u0001C%oM>\u0014X.\u001a:\u0002\t9|G/Z\u000b\u00025B\u0011qgW\u0005\u00039*\u0012\u0001BT8uS\u001aLWM]\u0001\u0006C2,\'\u000f^\u000b\u0002?B\u0011q\u0007Y\u0005\u0003C*\u0012q!\u00117feR,\'/\u0001\u0004nCJ\\W\u000f]\u000b\u0002IB\u0011q\'Z\u0005\u0003M*\u0012!\u0002R8dk6,g\u000e^3s\u0003U\u0011XmZ5ti\u0016\u0014\u0018i]=oGR+7\u000f^%na2$R![A\u0006\u0003K!2a\u00136|\u0011\u0019Yw\u0001\"a\u0001Y\u00069A/Z:u\rVt\u0007cA\u0019n_&\u0011aN\r\u0002\ty\tLh.Y7f}A\u0019\u0001o];\u000e\u0003ET!A\u001d\u001a\u0002\u0015\r|gnY;se\u0016tG/\u0003\u0002uc\n1a)\u001e;ve\u0016\u0004\"A^=\u000e\u0003]T!\u0001\u001f\u0016\u0002\u0015\r|W\u000e]1uS\ndW-\u0003\u0002{o\nI\u0011i]:feRLwN\u001c\u0005\u0006y\u001e\u0001\r!`\u0001\u0004a>\u001c\bc\u0001@\u0002\b5\tqP\u0003\u0003\u0002\u0002\u0005\r\u0011AB:pkJ\u001cWMC\u0002\u0002\u00061\n\u0011b]2bY\u0006\u001cG/[2\n\u0007\u0005%qP\u0001\u0005Q_NLG/[8o\u0011\u001d\tia\u0002a\u0001\u0003\u001f\t\u0001\u0002^3tiR+\u0007\u0010\u001e\t\u0005\u0003#\tyB\u0004\u0003\u0002\u0014\u0005m\u0001cAA\u000be5\u0011\u0011q\u0003\u0006\u0004\u00033q\u0013A\u0002\u001fs_>$h(C\u0002\u0002\u001eI\na\u0001\u0015:fI\u00164\u0017\u0002BA\u0011\u0003G\u0011aa\u0015;sS:<\'bAA\u000fe!9\u0011qE\u0004A\u0002\u0005%\u0012\u0001\u0003;fgR$\u0016mZ:\u0011\u000bE\nY#a\f\n\u0007\u00055\"G\u0001\u0006=e\u0016\u0004X-\u0019;fIz\u00022aNA\u0019\u0013\r\t\u0019D\u000b\u0002\u0004)\u0006<\u0017!\u0005:fO&\u001cH/\u001a:Bgft7\rV3tiR1\u0011\u0011HA!\u0003\u0007\"B!a\u000f\u0002@Q\u00191*!\u0010\t\u000bqD\u00019A?\t\r-DA\u00111\u0001m\u0011\u001d\ti\u0001\u0003a\u0001\u0003\u001fAq!a\n\t\u0001\u0004\tI#\u0001\u000fsK\u001eL7\u000f^3s\u0013\u001etwN]3e\u0003NLhn\u0019+fgRLU\u000e\u001d7\u0015\r\u0005%\u0013qJA))\u0015Y\u00151JA\'\u0011\u0019Y\u0017\u0002\"a\u0001Y\")A0\u0003a\u0001{\"9\u0011QB\u0005A\u0002\u0005=\u0001bBA\u0014\u0013\u0001\u0007\u0011\u0011F\u0001\u0019e\u0016<\u0017n\u001d;fe&;gn\u001c:fI\u0006\u001b\u0018P\\2UKN$HCBA,\u0003?\n\t\u0007\u0006\u0003\u0002Z\u0005uCcA&\u0002\\!)AP\u0003a\u0002{\"11N\u0003CA\u00021Dq!!\u0004\u000b\u0001\u0004\ty\u0001C\u0004\u0002()\u0001\r!!\u000b\u0003\r%#xk\u001c:e\'\tY\u0001\'\u0001\u0004=S:LGO\u0010\u000b\u0003\u0003W\u00022!!\u001c\f\u001b\u0005\u0001\u0011!C1qa2L\u0018*\u001c9m)\u0019\t\u0019(!\u001f\u0002~Q)1*!\u001e\u0002x!11.\u0004CA\u00021DQ\u0001`\u0007A\u0002uDq!a\u001f\u000e\u0001\u0004\ty!\u0001\u0005ta\u0016\u001cG+\u001a=u\u0011\u001d\t9#\u0004a\u0001\u0003S\tQ!\u00199qYf$b!a!\u0002\f\u00065E\u0003BAC\u0003\u0013#2aSAD\u0011\u0015ah\u0002q\u0001~\u0011\u0019Yg\u0002\"a\u0001Y\"9\u00111\u0010\bA\u0002\u0005=\u0001bBA\u0014\u001d\u0001\u0007\u0011\u0011F\u0001\u0007g\"|W\u000f\u001c3\u0015\t\u0005M\u0015q\u0014\t\u0005\u0003+\u000bY*\u0004\u0002\u0002\u0018*\u0019\u0011\u0011\u0014\u0016\u0002\u000bY,\'OY:\n\t\u0005u\u0015q\u0013\u0002\u000b\u0005\u0016D\u0017M^3X_J$\u0007bBAQ\u001f\u0001\u0007\u00111S\u0001\u000bE\u0016D\u0017M^3X_J$\u0017\u0001B7vgR$B!a%\u0002(\"9\u0011\u0011\u0015\tA\u0002\u0005M\u0015AA5u+\t\tYG\u0001\u0005UQ\u0016Lxk\u001c:e\'\t\u0011\u0002\u0007\u0006\u0002\u00024B\u0019\u0011Q\u000e\n\u0015\r\u0005]\u0016QXA`)\u0015Y\u0015\u0011XA^\u0011\u0019YG\u0003\"a\u0001Y\")A\u0010\u0006a\u0001{\"9\u00111\u0010\u000bA\u0002\u0005=\u0001bBA\u0014)\u0001\u0007\u0011\u0011\u0006\u000b\u0007\u0003\u0007\fY-!4\u0015\t\u0005\u0015\u0017\u0011\u001a\u000b\u0004\u0017\u0006\u001d\u0007\"\u0002?\u0016\u0001\bi\bBB6\u0016\t\u0003\u0007A\u000eC\u0004\u0002|U\u0001\r!a\u0004\t\u000f\u0005\u001dR\u00031\u0001\u0002*Q!\u00111SAi\u0011\u001d\t\tK\u0006a\u0001\u0003\'#B!a%\u0002V\"9\u0011\u0011U\fA\u0002\u0005M\u0015\u0001\u0002;iKf,\"!a-\u0002\u0015%<gn\u001c:f\u00136\u0004H\u000e\u0006\u0004\u0002`\u0006\u0015\u0018q\u001d\u000b\u0006\u0017\u0006\u0005\u00181\u001d\u0005\u0007Wf!\t\u0019\u00017\t\u000bqL\u0002\u0019A?\t\u000f\u00055\u0011\u00041\u0001\u0002\u0010!9\u0011qE\rA\u0002\u0005%\u0012AB5h]>\u0014X\r\u0006\u0004\u0002n\u0006U\u0018q\u001f\u000b\u0005\u0003_\f\u0019\u0010F\u0002L\u0003cDQ\u0001 \u000eA\u0004uDaa\u001b\u000e\u0005\u0002\u0004a\u0007bBA\u00075\u0001\u0007\u0011q\u0002\u0005\b\u0003OQ\u0002\u0019AA\u0015\u00031!Wm]2sS\n,\u0017*\u001c9m)\u0011\tiPa\u0002\u0015\u000b-\u000byP!\u0002\t\u0011\t\u00051\u0004\"a\u0001\u0005\u0007\t1AZ;o!\r\tTn\u0013\u0005\u0006yn\u0001\r! \u0005\b\u0005\u0013Y\u0002\u0019AA\b\u0003-!Wm]2sSB$\u0018n\u001c8\u0002\u0011\u0011,7o\u0019:jE\u0016$BAa\u0004\u0003\u0018Q!!\u0011\u0003B\u000b)\rY%1\u0003\u0005\u0006yr\u0001\u001d! \u0005\t\u0005\u0003aB\u00111\u0001\u0003\u0004!9!\u0011\u0002\u000fA\u0002\u0005=\u0011!\u0003;fgRt\u0015-\\3t+\t\u0011i\u0002\u0005\u0004\u0002\u0012\t}\u0011qB\u0005\u0005\u0005C\t\u0019CA\u0002TKR\fqA];o)\u0016\u001cH\u000f\u0006\u0004\u0003(\t5\"\u0011\u0007\t\u0004o\t%\u0012b\u0001B\u0016U\t11\u000b^1ukNDqAa\f\u001f\u0001\u0004\ty!\u0001\u0005uKN$h*Y7f\u0011\u001d\u0011\u0019D\ba\u0001\u0005k\tA!\u0019:hgB\u0019qGa\u000e\n\u0007\te\"F\u0001\u0003Be\u001e\u001c\u0018\u0001\u0002;bON,\"Aa\u0010\u0011\u0011\u0005E!\u0011IA\b\u0005;IAAa\u0011\u0002$\t\u0019Q*\u00199\u0002\u0011I,h\u000eV3tiN$bAa\n\u0003J\tE\u0003b\u0002B\u0018A\u0001\u0007!1\n\t\u0006c\t5\u0013qB\u0005\u0004\u0005\u001f\u0012$AB(qi&|g\u000eC\u0004\u00034\u0001\u0002\rA!\u000e\u0002\u0007I,h\u000e\u0006\u0004\u0003(\t]#\u0011\f\u0005\b\u0005_\t\u0003\u0019\u0001B&\u0011\u001d\u0011\u0019$\ta\u0001\u0005k\taAY3iCZ,WCAAJ\u0003%\u0019H/\u001f7f\u001d\u0006lW-\u0006\u0002\u0002\u0010!Z1E!\u001a\u0003l\t5$\u0011\u000fB:!\r\t$qM\u0005\u0004\u0005S\u0012$A\u00033faJ,7-\u0019;fI\u00069Q.Z:tC\u001e,\u0017E\u0001B8\u0003q$\u0006.\u001a\u0011tifdWMT1nK\u0002b\u0017NZ3ds\u000edW\rI7fi\"|G\r\t5bg\u0002\u0012W-\u001a8!I\u0016\u0004(/Z2bi\u0016$\u0007%\u00198eA]LG\u000e\u001c\u0011cK\u0002\u0012X-\\8wK\u0012\u0004\u0013N\u001c\u0011bA\u0019,H/\u001e:fAY,\'o]5p]\u0002zg\rI*dC2\fG+Z:uA]LG\u000f\u001b\u0011o_\u0002\u0012X\r\u001d7bG\u0016lWM\u001c;/\u0003\u0015\u0019\u0018N\\2fC\t\u0011)(A\u00034]Er\u0003\'A\u0006uKN$H)\u0019;b\r>\u0014HC\u0002B>\u0005\u0003\u0013\u0019\tE\u00028\u0005{J1Aa +\u0005!!Vm\u001d;ECR\f\u0007b\u0002B\u0018I\u0001\u0007\u0011q\u0002\u0005\n\u0005\u000b#\u0003\u0013!a\u0001\u0005\u000f\u000bA\u0002\u001e5f\u0007>tg-[4NCB\u00042a\u000eBE\u0013\r\u0011YI\u000b\u0002\n\u0007>tg-[4NCB\fQ\u0003^3ti\u0012\u000bG/\u0019$pe\u0012\"WMZ1vYR$#\'\u0006\u0002\u0003\u0012*\"!q\u0011BJW\t\u0011)\n\u0005\u0003\u0003\u0018\n\u0005VB\u0001BM\u0015\u0011\u0011YJ!(\u0002\u0013Ut7\r[3dW\u0016$\'b\u0001BPe\u0005Q\u0011M\u001c8pi\u0006$\u0018n\u001c8\n\t\t\r&\u0011\u0014\u0002\u0012k:\u001c\u0007.Z2lK\u00124\u0016M]5b]\u000e,\u0017!C:va\u0016\u0014HE];o)\u0019\u00119C!+\u0003,\"9!q\u0006\u0014A\u0002\t-\u0003b\u0002B\u001aM\u0001\u0007!QG\u0005\u0005\u0005\'\u0012y+C\u0002\u00032*\u0012QaU;ji\u0016Ds\u0001\u0001B[\u0005w\u0013i\fE\u00028\u0005oK1A!/+\u0005\u001d1\u0015N\u001c3feN\fQA^1mk\u0016d#Aa0\"\u0005\t\u0005\u0017aI8sO:\u001a8-\u00197bi\u0016\u001cHO\f4j]\u0012,\'o\u001d\u0018Gk:\u001c\u0006/Z2GS:$WM\u001d"
    )
BootstrapMethods:
  0: #149 REF_invokeStatic java/lang/invoke/LambdaMetafactory.altMetafactory:(Ljava/lang/invoke/MethodHandles$Lookup;Ljava/lang/String;Ljava/lang/invoke/MethodType;[Ljava/lang/Object;)Ljava/lang/invoke/CallSite;
    Method arguments:
      #134 ()Ljava/lang/Object;
      #139 REF_invokeStatic org/scalatest/funspec/AsyncFunSpecLike.$anonfun$registerAsyncTestImpl$1:()Ljava/lang/String;
      #140 ()Ljava/lang/String;
      #141 5
      #142 1
      #140 ()Ljava/lang/String;
  1: #149 REF_invokeStatic java/lang/invoke/LambdaMetafactory.altMetafactory:(Ljava/lang/invoke/MethodHandles$Lookup;Ljava/lang/String;Ljava/lang/invoke/MethodType;[Ljava/lang/Object;)Ljava/lang/invoke/CallSite;
    Method arguments:
      #134 ()Ljava/lang/Object;
      #178 REF_invokeStatic org/scalatest/funspec/AsyncFunSpecLike.$anonfun$registerIgnoredAsyncTestImpl$1:()Ljava/lang/String;
      #140 ()Ljava/lang/String;
      #141 5
      #142 1
      #140 ()Ljava/lang/String;
  2: #149 REF_invokeStatic java/lang/invoke/LambdaMetafactory.altMetafactory:(Ljava/lang/invoke/MethodHandles$Lookup;Ljava/lang/String;Ljava/lang/invoke/MethodType;[Ljava/lang/Object;)Ljava/lang/invoke/CallSite;
    Method arguments:
      #134 ()Ljava/lang/Object;
      #197 REF_invokeStatic org/scalatest/funspec/AsyncFunSpecLike.$anonfun$ignoreImpl$1:()Ljava/lang/String;
      #140 ()Ljava/lang/String;
      #141 5
      #142 1
      #140 ()Ljava/lang/String;
  3: #149 REF_invokeStatic java/lang/invoke/LambdaMetafactory.altMetafactory:(Ljava/lang/invoke/MethodHandles$Lookup;Ljava/lang/String;Ljava/lang/invoke/MethodType;[Ljava/lang/Object;)Ljava/lang/invoke/CallSite;
    Method arguments:
      #134 ()Ljava/lang/Object;
      #215 REF_invokeStatic org/scalatest/funspec/AsyncFunSpecLike.$anonfun$describeImpl$1:()Ljava/lang/String;
      #140 ()Ljava/lang/String;
      #141 5
      #142 1
      #140 ()Ljava/lang/String;
  4: #149 REF_invokeStatic java/lang/invoke/LambdaMetafactory.altMetafactory:(Ljava/lang/invoke/MethodHandles$Lookup;Ljava/lang/String;Ljava/lang/invoke/MethodType;[Ljava/lang/Object;)Ljava/lang/invoke/CallSite;
    Method arguments:
      #134 ()Ljava/lang/Object;
      #247 REF_invokeStatic org/scalatest/funspec/AsyncFunSpecLike.$anonfun$describeImpl$2:(Lorg/scalactic/source/Position;)Lorg/scalactic/source/Position;
      #249 ()Lorg/scalactic/source/Position;
      #141 5
      #142 1
      #249 ()Lorg/scalactic/source/Position;
  5: #149 REF_invokeStatic java/lang/invoke/LambdaMetafactory.altMetafactory:(Ljava/lang/invoke/MethodHandles$Lookup;Ljava/lang/String;Ljava/lang/invoke/MethodType;[Ljava/lang/Object;)Ljava/lang/invoke/CallSite;
    Method arguments:
      #134 ()Ljava/lang/Object;
      #270 REF_invokeStatic org/scalatest/funspec/AsyncFunSpecLike.$anonfun$describeImpl$3:(Lorg/scalactic/source/Position;)Lorg/scalactic/source/Position;
      #249 ()Lorg/scalactic/source/Position;
      #141 5
      #142 1
      #249 ()Lorg/scalactic/source/Position;
  6: #149 REF_invokeStatic java/lang/invoke/LambdaMetafactory.altMetafactory:(Ljava/lang/invoke/MethodHandles$Lookup;Ljava/lang/String;Ljava/lang/invoke/MethodType;[Ljava/lang/Object;)Ljava/lang/invoke/CallSite;
    Method arguments:
      #134 ()Ljava/lang/Object;
      #311 REF_invokeStatic org/scalatest/funspec/AsyncFunSpecLike.$anonfun$describeImpl$4:(Lorg/scalactic/source/Position;)Lorg/scalactic/source/Position;
      #249 ()Lorg/scalactic/source/Position;
      #141 5
      #142 1
      #249 ()Lorg/scalactic/source/Position;
  7: #149 REF_invokeStatic java/lang/invoke/LambdaMetafactory.altMetafactory:(Ljava/lang/invoke/MethodHandles$Lookup;Ljava/lang/String;Ljava/lang/invoke/MethodType;[Ljava/lang/Object;)Ljava/lang/invoke/CallSite;
    Method arguments:
      #369 (Ljava/lang/Object;Ljava/lang/Object;)Ljava/lang/Object;
      #374 REF_invokeStatic org/scalatest/funspec/AsyncFunSpecLike.$anonfun$runTest$1:(Lorg/scalatest/funspec/AsyncFunSpecLike;Lorg/scalatest/Args;Ljava/lang/String;Lorg/scalatest/AsyncSuperEngine$TestLeaf;Lscala/Function1;)Lorg/scalatest/AsyncOutcome;
      #376 (Lorg/scalatest/AsyncSuperEngine$TestLeaf;Lscala/Function1;)Lorg/scalatest/AsyncOutcome;
      #141 5
      #142 1
      #376 (Lorg/scalatest/AsyncSuperEngine$TestLeaf;Lscala/Function1;)Lorg/scalatest/AsyncOutcome;
  8: #149 REF_invokeStatic java/lang/invoke/LambdaMetafactory.altMetafactory:(Ljava/lang/invoke/MethodHandles$Lookup;Ljava/lang/String;Ljava/lang/invoke/MethodType;[Ljava/lang/Object;)Ljava/lang/invoke/CallSite;
    Method arguments:
      #369 (Ljava/lang/Object;Ljava/lang/Object;)Ljava/lang/Object;
      #412 REF_invokeStatic org/scalatest/funspec/AsyncFunSpecLike.$anonfun$runTests$1:(Lorg/scalatest/funspec/AsyncFunSpecLike;Ljava/lang/String;Lorg/scalatest/Args;)Lorg/scalatest/Status;
      #413 (Ljava/lang/String;Lorg/scalatest/Args;)Lorg/scalatest/Status;
      #141 5
      #142 1
      #413 (Ljava/lang/String;Lorg/scalatest/Args;)Lorg/scalatest/Status;
  9: #149 REF_invokeStatic java/lang/invoke/LambdaMetafactory.altMetafactory:(Ljava/lang/invoke/MethodHandles$Lookup;Ljava/lang/String;Ljava/lang/invoke/MethodType;[Ljava/lang/Object;)Ljava/lang/invoke/CallSite;
    Method arguments:
      #369 (Ljava/lang/Object;Ljava/lang/Object;)Ljava/lang/Object;
      #428 REF_invokeStatic org/scalatest/funspec/AsyncFunSpecLike.$anonfun$run$1:(Lorg/scalatest/funspec/AsyncFunSpecLike;Lscala/Option;Lorg/scalatest/Args;)Lorg/scalatest/Status;
      #429 (Lscala/Option;Lorg/scalatest/Args;)Lorg/scalatest/Status;
      #141 5
      #142 1
      #429 (Lscala/Option;Lorg/scalatest/Args;)Lorg/scalatest/Status;
  10: #149 REF_invokeStatic java/lang/invoke/LambdaMetafactory.altMetafactory:(Ljava/lang/invoke/MethodHandles$Lookup;Ljava/lang/String;Ljava/lang/invoke/MethodType;[Ljava/lang/Object;)Ljava/lang/invoke/CallSite;
    Method arguments:
      #134 ()Ljava/lang/Object;
      #524 REF_invokeStatic org/scalatest/funspec/AsyncFunSpecLike.$anonfun$engine$1:()Ljava/lang/String;
      #140 ()Ljava/lang/String;
      #141 5
      #142 1
      #140 ()Ljava/lang/String;
  11: #559 REF_invokeStatic scala/runtime/LambdaDeserialize.bootstrap:(Ljava/lang/invoke/MethodHandles$Lookup;Ljava/lang/String;Ljava/lang/invoke/MethodType;[Ljava/lang/invoke/MethodHandle;)Ljava/lang/invoke/CallSite;
    Method arguments:
      #215 REF_invokeStatic org/scalatest/funspec/AsyncFunSpecLike.$anonfun$describeImpl$1:()Ljava/lang/String;
      #247 REF_invokeStatic org/scalatest/funspec/AsyncFunSpecLike.$anonfun$describeImpl$2:(Lorg/scalactic/source/Position;)Lorg/scalactic/source/Position;
      #270 REF_invokeStatic org/scalatest/funspec/AsyncFunSpecLike.$anonfun$describeImpl$3:(Lorg/scalactic/source/Position;)Lorg/scalactic/source/Position;
      #311 REF_invokeStatic org/scalatest/funspec/AsyncFunSpecLike.$anonfun$describeImpl$4:(Lorg/scalactic/source/Position;)Lorg/scalactic/source/Position;
      #524 REF_invokeStatic org/scalatest/funspec/AsyncFunSpecLike.$anonfun$engine$1:()Ljava/lang/String;
      #197 REF_invokeStatic org/scalatest/funspec/AsyncFunSpecLike.$anonfun$ignoreImpl$1:()Ljava/lang/String;
      #139 REF_invokeStatic org/scalatest/funspec/AsyncFunSpecLike.$anonfun$registerAsyncTestImpl$1:()Ljava/lang/String;
      #178 REF_invokeStatic org/scalatest/funspec/AsyncFunSpecLike.$anonfun$registerIgnoredAsyncTestImpl$1:()Ljava/lang/String;
      #428 REF_invokeStatic org/scalatest/funspec/AsyncFunSpecLike.$anonfun$run$1:(Lorg/scalatest/funspec/AsyncFunSpecLike;Lscala/Option;Lorg/scalatest/Args;)Lorg/scalatest/Status;
      #374 REF_invokeStatic org/scalatest/funspec/AsyncFunSpecLike.$anonfun$runTest$1:(Lorg/scalatest/funspec/AsyncFunSpecLike;Lorg/scalatest/Args;Ljava/lang/String;Lorg/scalatest/AsyncSuperEngine$TestLeaf;Lscala/Function1;)Lorg/scalatest/AsyncOutcome;
      #412 REF_invokeStatic org/scalatest/funspec/AsyncFunSpecLike.$anonfun$runTests$1:(Lorg/scalatest/funspec/AsyncFunSpecLike;Ljava/lang/String;Lorg/scalatest/Args;)Lorg/scalatest/Status;
  ScalaInlineInfo: length = 0x126 (unknown attribute)
   01 00 00 3A 00 D4 00 88 01 00 F3 00 F4 01 01 0B
   00 F4 01 01 34 00 F4 01 01 D0 00 88 01 00 C2 00
   88 01 00 87 00 88 01 00 AF 00 88 01 01 A9 01 93
   01 01 72 01 73 01 01 99 01 66 01 02 08 02 09 01
   00 67 00 68 00 00 65 00 66 01 01 B3 01 B4 00 01
   4A 00 CE 00 01 48 01 49 01 00 CD 00 CE 01 00 C8
   00 7C 00 00 C7 00 A9 01 00 C1 00 7C 01 00 44 00
   45 00 00 41 00 42 01 01 E3 01 E4 01 00 BD 00 BE
   00 00 72 00 73 00 00 70 00 71 01 00 5C 00 5D 00
   00 5A 00 5B 01 00 3F 00 40 00 00 3B 00 3C 01 00
   37 00 38 00 00 33 00 34 00 00 30 00 31 00 00 39
   00 3A 00 00 35 00 36 00 00 A0 00 7C 01 00 A8 00
   A9 01 00 7B 00 7C 01 00 B4 00 7C 01 00 B8 00 A9
   01 00 AE 00 7C 01 01 A6 00 3C 00 01 A5 01 93 01
   01 67 01 68 00 01 65 01 66 01 01 94 00 3C 00 01
   92 01 93 01 01 B5 00 88 00 01 86 01 87 00 01 84
   01 85 01 01 B9 01 BA 00 01 B6 01 B7 01 01 C4 01
   C5 00 01 C2 01 C3 01 01 51 01 52 00 01 4F 01 50
   01 00 BF 00 C0 00
  ScalaSig: length = 0x3 (unknown attribute)
   05 02 00
