Classfile /Users/mw/Projects/slang-braindump/.jar/jar11/assemble/slang-braindump/assemble/content/org/scalatest/funspec/PathAnyFunSpecLike.class
  Last modified May 29, 2022; size 19521 bytes
  SHA-256 checksum 959f0ed87d5ccacf37f41a90e0a0ce068760e06a0160e8938447eb0cc5361163
  Compiled from "PathAnyFunSpecLike.scala"
public interface org.scalatest.funspec.PathAnyFunSpecLike extends org.scalatest.Suite,org.scalatest.OneInstancePerTest,org.scalatest.Informing,org.scalatest.Notifying,org.scalatest.Alerting,org.scalatest.Documenting
  minor version: 0
  major version: 52
  flags: (0x0601) ACC_PUBLIC, ACC_INTERFACE, ACC_ABSTRACT
  this_class: #2                          // org/scalatest/funspec/PathAnyFunSpecLike
  super_class: #4                         // java/lang/Object
  interfaces: 6, fields: 0, methods: 57, attributes: 6
Constant pool:
    #1 = Utf8               org/scalatest/funspec/PathAnyFunSpecLike
    #2 = Class              #1            // org/scalatest/funspec/PathAnyFunSpecLike
    #3 = Utf8               java/lang/Object
    #4 = Class              #3            // java/lang/Object
    #5 = Utf8               org/scalatest/Suite
    #6 = Class              #5            // org/scalatest/Suite
    #7 = Utf8               org/scalatest/OneInstancePerTest
    #8 = Class              #7            // org/scalatest/OneInstancePerTest
    #9 = Utf8               org/scalatest/Informing
   #10 = Class              #9            // org/scalatest/Informing
   #11 = Utf8               org/scalatest/Notifying
   #12 = Class              #11           // org/scalatest/Notifying
   #13 = Utf8               org/scalatest/Alerting
   #14 = Class              #13           // org/scalatest/Alerting
   #15 = Utf8               org/scalatest/Documenting
   #16 = Class              #15           // org/scalatest/Documenting
   #17 = Utf8               PathAnyFunSpecLike.scala
   #18 = Utf8               Lorg/scalatest/Finders;
   #19 = Utf8               value
   #20 = Utf8               org.scalatest.finders.FunSpecFinder
   #21 = Utf8               Lscala/reflect/ScalaSignature;
   #22 = Utf8               bytes
   #23 = Utf8               \u0006\u0005\tmeaB\u0014)!\u0003\r\ta\f\u0005\u0006\u0013\u0002!\tA\u0013\u0005\b\u001d\u0002\u0011\r\u0011\"\u0004P\u0011\u0015\u0019\u0006\u0001\"\u0011U\u0011\u00159\u0006\u0001\"\u0005Y\u0011\u0015a\u0006\u0001\"\u0005^\u0011\u0015\t\u0007\u0001\"\u0005c\u0011\u00151\u0007\u0001\"\u0005h\r\u0011Y\u0007\u0001\u00037\t\u000b5DA\u0011\u00018\t\u000bEDAQ\u0002:\t\u000f\u0005E\u0002\u0002\"\u0001\u00024!9\u0011\u0011\t\u0005\u0005\u0002\u0005\r\u0003bBA+\u0011\u0011\u0005\u0011q\u000b\u0005\n\u00037\u0002!\u0019!C\t\u0003;2a!a\u0018\u0001\u0011\u0005\u0005\u0004BB7\u0010\t\u0003\t\u0019\u0007\u0003\u0004r\u001f\u0011%\u0011q\r\u0005\b\u0003cyA\u0011AA:\u0011\u001d\t\te\u0004C\u0001\u0003\u0003Cq!!\u0016\u0010\t\u0003\t)\tC\u0005\u0002\n\u0002\u0011\r\u0011\"\u0005\u0002\f\"9\u0011Q\u0012\u0001\u0005\u000e\u0005=\u0005bBAN\u0001\u0011E\u0011Q\u0014\u0005\b\u0003W\u0003AQBAW\u0011\u001d\tY\f\u0001C\t\u0003{C\u0011\"!3\u0001\u0005\u0004%\t\"a3\t\u000f\u00055\u0007\u0001\"\u0012\u0002P\"9\u0011q\u001b\u0001\u0005F\u0005e\u0007bBAv\u0001\u0011U\u0013Q\u001e\u0005\b\u0005\u0007\u0001AQ\tB\u0003\u0011\u001d\u0011i\u0001\u0001C#\u0005\u001fAqAa\u0007\u0001\t+\u0012i\u0002C\u0004\u0003$\u0001!)F!\n\t\u000f\t%\u0002\u0001\"\u0012\u0003,!I!Q\b\u0001C\u0002\u0013\u0015#q\b\u0005\b\u0005+\u0002A\u0011\tB,\u0011%\u0011Y\u0007AI\u0001\n\u0003\u0011i\u0007\u0003\b\u0003\u0004\u0002\u0001\n1!A\u0001\n\u0013\u0011)I!#\u0003%A\u000bG\u000f[!os\u001a+hn\u00159fG2K7.\u001a\u0006\u0003S)\nqAZ;ogB,7M\u0003\u0002,Y\u0005I1oY1mCR,7\u000f\u001e\u0006\u0002[\u0005\u0019qN]4\u0004\u0001MA\u0001\u0001\r\u001c;{\u0001\u001be\t\u0005\u00022i5\t!GC\u00014\u0003\u0015\u00198-\u00197b\u0013\t)$G\u0001\u0004B]f\u0014VM\u001a\t\u0003oaj\u0011AK\u0005\u0003s)\u0012QaU;ji\u0016\u0004\"aN\u001e\n\u0005qR#AE(oK&s7\u000f^1oG\u0016\u0004VM\u001d+fgR\u0004\"a\u000e \n\u0005}R#!C%oM>\u0014X.\u001b8h!\t9\u0014)\u0003\u0002CU\tIaj\u001c;jMfLgn\u001a\t\u0003o\u0011K!!\u0012\u0016\u0003\u0011\u0005cWM\u001d;j]\u001e\u0004\"aN$\n\u0005!S#a\u0003#pGVlWM\u001c;j]\u001e\fa\u0001J5oSR$C#A&\u0011\u0005Eb\u0015BA\'3\u0005\u0011)f.\u001b;\u0002\r\u0015tw-\u001b8f+\u0005\u0001\u0006CA\u001cR\u0013\t\u0011&F\u0001\u0006QCRDWI\\4j]\u0016\f1B\\3x\u0013:\u001cH/\u00198dKV\tQ\u000b\u0005\u0002W\u00015\t\u0001&\u0001\u0003j]\u001a|W#A-\u0011\u0005]R\u0016BA.+\u0005!IeNZ8s[\u0016\u0014\u0018\u0001\u00028pi\u0016,\u0012A\u0018\t\u0003o}K!\u0001\u0019\u0016\u0003\u00119{G/\u001b4jKJ\fQ!\u00197feR,\u0012a\u0019\t\u0003o\u0011L!!\u001a\u0016\u0003\u000f\u0005cWM\u001d;fe\u00061Q.\u0019:lkB,\u0012\u0001\u001b\t\u0003o%L!A\u001b\u0016\u0003\u0015\u0011{7-^7f]R,\'O\u0001\u0004Ji^{\'\u000fZ\n\u0003\u0011A\na\u0001P5oSRtD#A8\u0011\u0005ADQ\"\u0001\u0001\u0002\u0013\u0005\u0004\b\u000f\\=J[BdG#B:\u0002\b\u0005\u0005BcA&us\"1QO\u0003CA\u0002Y\fq\u0001^3ti\u001a+h\u000eE\u00022o.K!\u0001\u001f\u001a\u0003\u0011q\u0012\u0017P\\1nKzBQA\u001f\u0006A\u0002m\f1\u0001]8t!\ra\u00181A\u0007\u0002{*\u0011ap`\u0001\u0007g>,(oY3\u000b\u0007\u0005\u0005A&A\u0005tG\u0006d\u0017m\u0019;jG&\u0019\u0011QA?\u0003\u0011A{7/\u001b;j_:Dq!!\u0003\u000b\u0001\u0004\tY!\u0001\u0005uKN$H+\u001a=u!\u0011\ti!a\u0007\u000f\t\u0005=\u0011q\u0003\t\u0004\u0003#\u0011TBAA\n\u0015\r\t)BL\u0001\u0007yI|w\u000e\u001e \n\u0007\u0005e!\'\u0001\u0004Qe\u0016$WMZ\u0005\u0005\u0003;\tyB\u0001\u0004TiJLgn\u001a\u0006\u0004\u00033\u0011\u0004bBA\u0012\u0015\u0001\u0007\u0011QE\u0001\ti\u0016\u001cH\u000fV1hgB)\u0011\'a\n\u0002,%\u0019\u0011\u0011\u0006\u001a\u0003\u0015q\u0012X\r]3bi\u0016$g\bE\u00028\u0003[I1!a\f+\u0005\r!\u0016mZ\u0001\u0006CB\u0004H.\u001f\u000b\u0007\u0003k\ti$a\u0010\u0015\t\u0005]\u00121\b\u000b\u0004\u0017\u0006e\u0002\"\u0002>\f\u0001\bY\bBB;\f\t\u0003\u0007a\u000fC\u0004\u0002\n-\u0001\r!a\u0003\t\u000f\u0005\r2\u00021\u0001\u0002&\u000511\u000f[8vY\u0012$B!!\u0012\u0002RA!\u0011qIA\'\u001b\t\tIEC\u0002\u0002L)\nQA^3sENLA!a\u0014\u0002J\tQ!)\u001a5bm\u0016<vN\u001d3\t\u000f\u0005MC\u00021\u0001\u0002F\u0005Q!-\u001a5bm\u0016<vN\u001d3\u0002\t5,8\u000f\u001e\u000b\u0005\u0003\u000b\nI\u0006C\u0004\u0002T5\u0001\r!!\u0012\u0002\u0005%$X#A8\u0003\u0011QCW-_,pe\u0012\u001c\"a\u0004\u0019\u0015\u0005\u0005\u0015\u0004C\u00019\u0010)\u0019\tI\'a\u001c\u0002rQ)1*a\u001b\u0002n!1Q/\u0005CA\u0002YDQA_\tA\u0002mDq!!\u0003\u0012\u0001\u0004\tY\u0001C\u0004\u0002$E\u0001\r!!\n\u0015\r\u0005U\u0014QPA@)\u0011\t9(a\u001f\u0015\u0007-\u000bI\bC\u0003{%\u0001\u000f1\u0010\u0003\u0004v%\u0011\u0005\rA\u001e\u0005\b\u0003\u0013\u0011\u0002\u0019AA\u0006\u0011\u001d\t\u0019C\u0005a\u0001\u0003K!B!!\u0012\u0002\u0004\"9\u00111K\nA\u0002\u0005\u0015C\u0003BA#\u0003\u000fCq!a\u0015\u0015\u0001\u0004\t)%\u0001\u0003uQ\u0016LXCAA3\u0003)IwM\\8sK&k\u0007\u000f\u001c\u000b\u0007\u0003#\u000b9*!\'\u0015\u000b-\u000b\u0019*!&\t\rU4B\u00111\u0001w\u0011\u0015Qh\u00031\u0001|\u0011\u001d\tIA\u0006a\u0001\u0003\u0017Aq!a\t\u0017\u0001\u0004\t)#\u0001\u0004jO:|\'/\u001a\u000b\u0007\u0003?\u000b9+!+\u0015\t\u0005\u0005\u0016Q\u0015\u000b\u0004\u0017\u0006\r\u0006\"\u0002>\u0018\u0001\bY\bBB;\u0018\t\u0003\u0007a\u000fC\u0004\u0002\n]\u0001\r!a\u0003\t\u000f\u0005\rr\u00031\u0001\u0002&\u0005aA-Z:de&\u0014W-S7qYR!\u0011qVA\\)\u0015Y\u0015\u0011WA[\u0011\u001d\t\u0019\f\u0007CA\u0002Y\f1AZ;o\u0011\u0015Q\b\u00041\u0001|\u0011\u001d\tI\f\u0007a\u0001\u0003\u0017\t1\u0002Z3tGJL\u0007\u000f^5p]\u0006AA-Z:de&\u0014W\r\u0006\u0003\u0002@\u0006\u001dG\u0003BAa\u0003\u000b$2aSAb\u0011\u0015Q\u0018\u0004q\u0001|\u0011\u001d\t\u0019,\u0007CA\u0002YDq!!/\u001a\u0001\u0004\tY!\u0001\u0004cK\"\fg/Z\u000b\u0003\u0003\u000b\n\u0011\u0002^3ti:\u000bW.Z:\u0016\u0005\u0005E\u0007CBA\u0007\u0003\'\fY!\u0003\u0003\u0002V\u0006}!aA*fi\u0006\tR\r\u001f9fGR,G\rV3ti\u000e{WO\u001c;\u0015\t\u0005m\u0017\u0011\u001d\t\u0004c\u0005u\u0017bAApe\t\u0019\u0011J\u001c;\t\u000f\u0005\rH\u00041\u0001\u0002f\u00061a-\u001b7uKJ\u00042aNAt\u0013\r\tIO\u000b\u0002\u0007\r&dG/\u001a:\u0002\u000fI,h\u000eV3tiR1\u0011q^A{\u0003s\u00042aNAy\u0013\r\t\u0019P\u000b\u0002\u0007\'R\fG/^:\t\u000f\u0005]X\u00041\u0001\u0002\f\u0005AA/Z:u\u001d\u0006lW\rC\u0004\u0002|v\u0001\r!!@\u0002\t\u0005\u0014xm\u001d\t\u0004o\u0005}\u0018b\u0001B\u0001U\t!\u0011I]4t\u0003\u0011!\u0018mZ:\u0016\u0005\t\u001d\u0001\u0003CA\u0007\u0005\u0013\tY!!5\n\t\t-\u0011q\u0004\u0002\u0004\u001b\u0006\u0004\u0018a\u0001:v]R1\u0011q\u001eB\t\u00053Aq!a> \u0001\u0004\u0011\u0019\u0002E\u00032\u0005+\tY!C\u0002\u0003\u0018I\u0012aa\u00149uS>t\u0007bBA~?\u0001\u0007\u0011Q`\u0001\teVtG+Z:ugR1\u0011q\u001eB\u0010\u0005CAq!a>!\u0001\u0004\u0011\u0019\u0002C\u0004\u0002|\u0002\u0002\r!!@\u0002\u001fI,hNT3ti\u0016$7+^5uKN$B!a<\u0003(!9\u00111`\u0011A\u0002\u0005u\u0018\u0001\u00048fgR,GmU;ji\u0016\u001cXC\u0001B\u0017!\u0015\u0011yC!\u000f7\u001b\t\u0011\tD\u0003\u0003\u00034\tU\u0012!C5n[V$\u0018M\u00197f\u0015\r\u00119DM\u0001\u000bG>dG.Z2uS>t\u0017\u0002\u0002B\u001e\u0005c\u0011!\"\u00138eKb,GmU3r\u0003%\u0019H/\u001f7f\u001d\u0006lW-\u0006\u0002\u0002\f!Z1Ea\u0011\u0003J\t-#q\nB)!\r\t$QI\u0005\u0004\u0005\u000f\u0012$A\u00033faJ,7-\u0019;fI\u00069Q.Z:tC\u001e,\u0017E\u0001B\'\u0003q$\u0006.\u001a\u0011tifdWMT1nK\u0002b\u0017NZ3ds\u000edW\rI7fi\"|G\r\t5bg\u0002\u0012W-\u001a8!I\u0016\u0004(/Z2bi\u0016$\u0007%\u00198eA]LG\u000e\u001c\u0011cK\u0002\u0012X-\\8wK\u0012\u0004\u0013N\u001c\u0011bA\u0019,H/\u001e:fAY,\'o]5p]\u0002zg\rI*dC2\fG+Z:uA]LG\u000f\u001b\u0011o_\u0002\u0012X\r\u001d7bG\u0016lWM\u001c;/\u0003\u0015\u0019\u0018N\\2fC\t\u0011\u0019&A\u00034]Er\u0003\'A\u0006uKN$H)\u0019;b\r>\u0014HC\u0002B-\u0005?\u0012\t\u0007E\u00028\u00057J1A!\u0018+\u0005!!Vm\u001d;ECR\f\u0007bBA|I\u0001\u0007\u00111\u0002\u0005\n\u0005G\"\u0003\u0013!a\u0001\u0005K\nA\u0002\u001e5f\u0007>tg-[4NCB\u00042a\u000eB4\u0013\r\u0011IG\u000b\u0002\n\u0007>tg-[4NCB\fQ\u0003^3ti\u0012\u000bG/\u0019$pe\u0012\"WMZ1vYR$#\'\u0006\u0002\u0003p)\"!Q\rB9W\t\u0011\u0019\b\u0005\u0003\u0003v\t}TB\u0001B<\u0015\u0011\u0011IHa\u001f\u0002\u0013Ut7\r[3dW\u0016$\'b\u0001B?e\u0005Q\u0011M\u001c8pi\u0006$\u0018n\u001c8\n\t\t\u0005%q\u000f\u0002\u0012k:\u001c\u0007.Z2lK\u00124\u0016M]5b]\u000e,\u0017aF:va\u0016\u0014H%\u001a=qK\u000e$X\r\u001a+fgR\u001cu.\u001e8u)\u0011\tYNa\"\t\u000f\u0005\rh\u00051\u0001\u0002f&\u0019\u0011q\u001b\u001d)\u000f\u0001\u0011iIa%\u0003\u0016B\u0019qGa$\n\u0007\tE%FA\u0004GS:$WM]:\u0002\u000bY\fG.^3-\u0005\t]\u0015E\u0001BM\u0003\rz\'o\u001a\u0018tG\u0006d\u0017\r^3ti:2\u0017N\u001c3feNtc)\u001e8Ta\u0016\u001cg)\u001b8eKJ\u0004
   #24 = Utf8               java/lang/invoke/MethodHandles$Lookup
   #25 = Class              #24           // java/lang/invoke/MethodHandles$Lookup
   #26 = Utf8               java/lang/invoke/MethodHandles
   #27 = Class              #26           // java/lang/invoke/MethodHandles
   #28 = Utf8               Lookup
   #29 = Utf8               org/scalatest/SuperEngine$Bundle
   #30 = Class              #29           // org/scalatest/SuperEngine$Bundle
   #31 = Utf8               org/scalatest/SuperEngine
   #32 = Class              #31           // org/scalatest/SuperEngine
   #33 = Utf8               Bundle
   #34 = Utf8               org/scalatest/SuperEngine$TestLeaf
   #35 = Class              #34           // org/scalatest/SuperEngine$TestLeaf
   #36 = Utf8               TestLeaf
   #37 = Utf8               org/scalatest/funspec/PathAnyFunSpecLike$ItWord
   #38 = Class              #37           // org/scalatest/funspec/PathAnyFunSpecLike$ItWord
   #39 = Utf8               ItWord
   #40 = Utf8               org/scalatest/funspec/PathAnyFunSpecLike$TheyWord
   #41 = Class              #40           // org/scalatest/funspec/PathAnyFunSpecLike$TheyWord
   #42 = Utf8               TheyWord
   #43 = Utf8               org$scalatest$funspec$PathAnyFunSpecLike$_setter_$org$scalatest$funspec$PathAnyFunSpecLike$$engine_$eq
   #44 = Utf8               (Lorg/scalatest/PathEngine;)V
   #45 = Utf8               x$1
   #46 = Utf8               org$scalatest$funspec$PathAnyFunSpecLike$_setter_$it_$eq
   #47 = Utf8               (Lorg/scalatest/funspec/PathAnyFunSpecLike$ItWord;)V
   #48 = Utf8               org$scalatest$funspec$PathAnyFunSpecLike$_setter_$they_$eq
   #49 = Utf8               (Lorg/scalatest/funspec/PathAnyFunSpecLike$TheyWord;)V
   #50 = Utf8               org$scalatest$funspec$PathAnyFunSpecLike$_setter_$behave_$eq
   #51 = Utf8               (Lorg/scalatest/verbs/BehaveWord;)V
   #52 = Utf8               org$scalatest$funspec$PathAnyFunSpecLike$_setter_$styleName_$eq
   #53 = Utf8               (Ljava/lang/String;)V
   #54 = Utf8               org$scalatest$funspec$PathAnyFunSpecLike$$super$expectedTestCount
   #55 = Utf8               (Lorg/scalatest/Filter;)I
   #56 = Utf8               filter
   #57 = Utf8               org$scalatest$funspec$PathAnyFunSpecLike$$engine
   #58 = Utf8               ()Lorg/scalatest/PathEngine;
   #59 = Utf8               newInstance$
   #60 = Utf8               (Lorg/scalatest/funspec/PathAnyFunSpecLike;)Lorg/scalatest/funspec/PathAnyFunSpecLike;
   #61 = Utf8               $this
   #62 = Utf8               newInstance
   #63 = Utf8               ()Lorg/scalatest/funspec/PathAnyFunSpecLike;
   #64 = NameAndType        #62:#63       // newInstance:()Lorg/scalatest/funspec/PathAnyFunSpecLike;
   #65 = InterfaceMethodref #2.#64        // org/scalatest/funspec/PathAnyFunSpecLike.newInstance:()Lorg/scalatest/funspec/PathAnyFunSpecLike;
   #66 = Utf8               Lorg/scalatest/funspec/PathAnyFunSpecLike;
   #67 = Utf8               getClass
   #68 = Utf8               ()Ljava/lang/Class;
   #69 = NameAndType        #67:#68       // getClass:()Ljava/lang/Class;
   #70 = Methodref          #4.#69        // java/lang/Object.getClass:()Ljava/lang/Class;
   #71 = Utf8               java/lang/Class
   #72 = Class              #71           // java/lang/Class
   #73 = Utf8               ()Ljava/lang/Object;
   #74 = NameAndType        #62:#73       // newInstance:()Ljava/lang/Object;
   #75 = Methodref          #72.#74       // java/lang/Class.newInstance:()Ljava/lang/Object;
   #76 = Utf8               this
   #77 = Utf8               info$
   #78 = Utf8               (Lorg/scalatest/funspec/PathAnyFunSpecLike;)Lorg/scalatest/Informer;
   #79 = Utf8               info
   #80 = Utf8               ()Lorg/scalatest/Informer;
   #81 = NameAndType        #79:#80       // info:()Lorg/scalatest/Informer;
   #82 = InterfaceMethodref #2.#81        // org/scalatest/funspec/PathAnyFunSpecLike.info:()Lorg/scalatest/Informer;
   #83 = NameAndType        #57:#58       // org$scalatest$funspec$PathAnyFunSpecLike$$engine:()Lorg/scalatest/PathEngine;
   #84 = InterfaceMethodref #2.#83        // org/scalatest/funspec/PathAnyFunSpecLike.org$scalatest$funspec$PathAnyFunSpecLike$$engine:()Lorg/scalatest/PathEngine;
   #85 = Utf8               org/scalatest/PathEngine
   #86 = Class              #85           // org/scalatest/PathEngine
   #87 = Utf8               atomicInformer
   #88 = Utf8               ()Ljava/util/concurrent/atomic/AtomicReference;
   #89 = NameAndType        #87:#88       // atomicInformer:()Ljava/util/concurrent/atomic/AtomicReference;
   #90 = Methodref          #86.#89       // org/scalatest/PathEngine.atomicInformer:()Ljava/util/concurrent/atomic/AtomicReference;
   #91 = Utf8               java/util/concurrent/atomic/AtomicReference
   #92 = Class              #91           // java/util/concurrent/atomic/AtomicReference
   #93 = Utf8               get
   #94 = NameAndType        #93:#73       // get:()Ljava/lang/Object;
   #95 = Methodref          #92.#94       // java/util/concurrent/atomic/AtomicReference.get:()Ljava/lang/Object;
   #96 = Utf8               org/scalatest/Informer
   #97 = Class              #96           // org/scalatest/Informer
   #98 = Utf8               note$
   #99 = Utf8               (Lorg/scalatest/funspec/PathAnyFunSpecLike;)Lorg/scalatest/Notifier;
  #100 = Utf8               note
  #101 = Utf8               ()Lorg/scalatest/Notifier;
  #102 = NameAndType        #100:#101     // note:()Lorg/scalatest/Notifier;
  #103 = InterfaceMethodref #2.#102       // org/scalatest/funspec/PathAnyFunSpecLike.note:()Lorg/scalatest/Notifier;
  #104 = Utf8               atomicNotifier
  #105 = NameAndType        #104:#88      // atomicNotifier:()Ljava/util/concurrent/atomic/AtomicReference;
  #106 = Methodref          #86.#105      // org/scalatest/PathEngine.atomicNotifier:()Ljava/util/concurrent/atomic/AtomicReference;
  #107 = Utf8               org/scalatest/Notifier
  #108 = Class              #107          // org/scalatest/Notifier
  #109 = Utf8               alert$
  #110 = Utf8               (Lorg/scalatest/funspec/PathAnyFunSpecLike;)Lorg/scalatest/Alerter;
  #111 = Utf8               alert
  #112 = Utf8               ()Lorg/scalatest/Alerter;
  #113 = NameAndType        #111:#112     // alert:()Lorg/scalatest/Alerter;
  #114 = InterfaceMethodref #2.#113       // org/scalatest/funspec/PathAnyFunSpecLike.alert:()Lorg/scalatest/Alerter;
  #115 = Utf8               atomicAlerter
  #116 = NameAndType        #115:#88      // atomicAlerter:()Ljava/util/concurrent/atomic/AtomicReference;
  #117 = Methodref          #86.#116      // org/scalatest/PathEngine.atomicAlerter:()Ljava/util/concurrent/atomic/AtomicReference;
  #118 = Utf8               org/scalatest/Alerter
  #119 = Class              #118          // org/scalatest/Alerter
  #120 = Utf8               markup$
  #121 = Utf8               (Lorg/scalatest/funspec/PathAnyFunSpecLike;)Lorg/scalatest/Documenter;
  #122 = Utf8               markup
  #123 = Utf8               ()Lorg/scalatest/Documenter;
  #124 = NameAndType        #122:#123     // markup:()Lorg/scalatest/Documenter;
  #125 = InterfaceMethodref #2.#124       // org/scalatest/funspec/PathAnyFunSpecLike.markup:()Lorg/scalatest/Documenter;
  #126 = Utf8               atomicDocumenter
  #127 = NameAndType        #126:#88      // atomicDocumenter:()Ljava/util/concurrent/atomic/AtomicReference;
  #128 = Methodref          #86.#127      // org/scalatest/PathEngine.atomicDocumenter:()Ljava/util/concurrent/atomic/AtomicReference;
  #129 = Utf8               org/scalatest/Documenter
  #130 = Class              #129          // org/scalatest/Documenter
  #131 = Utf8               it
  #132 = Utf8               ()Lorg/scalatest/funspec/PathAnyFunSpecLike$ItWord;
  #133 = Utf8               they
  #134 = Utf8               ()Lorg/scalatest/funspec/PathAnyFunSpecLike$TheyWord;
  #135 = Utf8               ignoreImpl
  #136 = Utf8               (Ljava/lang/String;Lscala/collection/immutable/Seq;Lscala/Function0;Lorg/scalactic/source/Position;)V
  #137 = Utf8               (Ljava/lang/String;Lscala/collection/immutable/Seq<Lorg/scalatest/Tag;>;Lscala/Function0<Lscala/runtime/BoxedUnit;>;Lorg/scalactic/source/Position;)V
  #138 = Utf8               testText
  #139 = Utf8               testTags
  #140 = Utf8               testFun
  #141 = Utf8               pos
  #142 = Utf8               org/scalatest/Transformer
  #143 = Class              #142          // org/scalatest/Transformer
  #144 = Utf8               <init>
  #145 = Utf8               (Lscala/Function0;)V
  #146 = NameAndType        #144:#145     // "<init>":(Lscala/Function0;)V
  #147 = Methodref          #143.#146     // org/scalatest/Transformer."<init>":(Lscala/Function0;)V
  #148 = MethodType         #73           //  ()Ljava/lang/Object;
  #149 = Utf8               $anonfun$ignoreImpl$1
  #150 = Utf8               ()Ljava/lang/String;
  #151 = NameAndType        #149:#150     // $anonfun$ignoreImpl$1:()Ljava/lang/String;
  #152 = InterfaceMethodref #2.#151       // org/scalatest/funspec/PathAnyFunSpecLike.$anonfun$ignoreImpl$1:()Ljava/lang/String;
  #153 = MethodHandle       6:#152        // REF_invokeStatic org/scalatest/funspec/PathAnyFunSpecLike.$anonfun$ignoreImpl$1:()Ljava/lang/String;
  #154 = MethodType         #150          //  ()Ljava/lang/String;
  #155 = Integer            5
  #156 = Integer            1
  #157 = Utf8               java/lang/invoke/LambdaMetafactory
  #158 = Class              #157          // java/lang/invoke/LambdaMetafactory
  #159 = Utf8               altMetafactory
  #160 = Utf8               (Ljava/lang/invoke/MethodHandles$Lookup;Ljava/lang/String;Ljava/lang/invoke/MethodType;[Ljava/lang/Object;)Ljava/lang/invoke/CallSite;
  #161 = NameAndType        #159:#160     // altMetafactory:(Ljava/lang/invoke/MethodHandles$Lookup;Ljava/lang/String;Ljava/lang/invoke/MethodType;[Ljava/lang/Object;)Ljava/lang/invoke/CallSite;
  #162 = Methodref          #158.#161     // java/lang/invoke/LambdaMetafactory.altMetafactory:(Ljava/lang/invoke/MethodHandles$Lookup;Ljava/lang/String;Ljava/lang/invoke/MethodType;[Ljava/lang/Object;)Ljava/lang/invoke/CallSite;
  #163 = MethodHandle       6:#162        // REF_invokeStatic java/lang/invoke/LambdaMetafactory.altMetafactory:(Ljava/lang/invoke/MethodHandles$Lookup;Ljava/lang/String;Ljava/lang/invoke/MethodType;[Ljava/lang/Object;)Ljava/lang/invoke/CallSite;
  #164 = Utf8               apply
  #165 = Utf8               ()Lscala/Function0;
  #166 = NameAndType        #164:#165     // apply:()Lscala/Function0;
  #167 = InvokeDynamic      #0:#166       // #0:apply:()Lscala/Function0;
  #168 = String             #17           // PathAnyFunSpecLike.scala
  #169 = Utf8               ignore
  #170 = String             #169          // ignore
  #171 = Utf8               scala/None$
  #172 = Class              #171          // scala/None$
  #173 = Utf8               MODULE$
  #174 = Utf8               Lscala/None$;
  #175 = NameAndType        #173:#174     // MODULE$:Lscala/None$;
  #176 = Fieldref           #172.#175     // scala/None$.MODULE$:Lscala/None$;
  #177 = Utf8               scala/Some
  #178 = Class              #177          // scala/Some
  #179 = Utf8               (Ljava/lang/Object;)V
  #180 = NameAndType        #144:#179     // "<init>":(Ljava/lang/Object;)V
  #181 = Methodref          #178.#180     // scala/Some."<init>":(Ljava/lang/Object;)V
  #182 = Utf8               handleIgnoredTest
  #183 = Utf8               (Ljava/lang/String;Lscala/Function0;Lscala/Function0;Ljava/lang/String;Ljava/lang/String;IILscala/Option;Lscala/Option;Lscala/collection/immutable/Seq;)V
  #184 = NameAndType        #182:#183     // handleIgnoredTest:(Ljava/lang/String;Lscala/Function0;Lscala/Function0;Ljava/lang/String;Ljava/lang/String;IILscala/Option;Lscala/Option;Lscala/collection/immutable/Seq;)V
  #185 = Methodref          #86.#184      // org/scalatest/PathEngine.handleIgnoredTest:(Ljava/lang/String;Lscala/Function0;Lscala/Function0;Ljava/lang/String;Ljava/lang/String;IILscala/Option;Lscala/Option;Lscala/collection/immutable/Seq;)V
  #186 = Utf8               stackDepth
  #187 = Utf8               I
  #188 = Utf8               stackDepthAdjustment
  #189 = Utf8               Ljava/lang/String;
  #190 = Utf8               Lscala/collection/immutable/Seq;
  #191 = Utf8               Lscala/Function0;
  #192 = Utf8               Lorg/scalactic/source/Position;
  #193 = Utf8               ignore$
  #194 = Utf8               (Lorg/scalatest/funspec/PathAnyFunSpecLike;Ljava/lang/String;Lscala/collection/immutable/Seq;Lscala/Function0;Lorg/scalactic/source/Position;)V
  #195 = NameAndType        #169:#136     // ignore:(Ljava/lang/String;Lscala/collection/immutable/Seq;Lscala/Function0;Lorg/scalactic/source/Position;)V
  #196 = InterfaceMethodref #2.#195       // org/scalatest/funspec/PathAnyFunSpecLike.ignore:(Ljava/lang/String;Lscala/collection/immutable/Seq;Lscala/Function0;Lorg/scalactic/source/Position;)V
  #197 = NameAndType        #135:#136     // ignoreImpl:(Ljava/lang/String;Lscala/collection/immutable/Seq;Lscala/Function0;Lorg/scalactic/source/Position;)V
  #198 = InterfaceMethodref #2.#197       // org/scalatest/funspec/PathAnyFunSpecLike.ignoreImpl:(Ljava/lang/String;Lscala/collection/immutable/Seq;Lscala/Function0;Lorg/scalactic/source/Position;)V
  #199 = Utf8               describeImpl
  #200 = Utf8               (Ljava/lang/String;Lscala/Function0;Lorg/scalactic/source/Position;)V
  #201 = Utf8               (Ljava/lang/String;Lscala/Function0<Lscala/runtime/BoxedUnit;>;Lorg/scalactic/source/Position;)V
  #202 = Utf8               description
  #203 = Utf8               fun
  #204 = Utf8               java/lang/Throwable
  #205 = Class              #204          // java/lang/Throwable
  #206 = Utf8               $anonfun$describeImpl$1
  #207 = NameAndType        #206:#150     // $anonfun$describeImpl$1:()Ljava/lang/String;
  #208 = InterfaceMethodref #2.#207       // org/scalatest/funspec/PathAnyFunSpecLike.$anonfun$describeImpl$1:()Ljava/lang/String;
  #209 = MethodHandle       6:#208        // REF_invokeStatic org/scalatest/funspec/PathAnyFunSpecLike.$anonfun$describeImpl$1:()Ljava/lang/String;
  #210 = InvokeDynamic      #1:#166       // #1:apply:()Lscala/Function0;
  #211 = Utf8               describe
  #212 = String             #211          // describe
  #213 = Utf8               handleNestedBranch
  #214 = Utf8               (Ljava/lang/String;Lscala/Option;Lscala/Function0;Lscala/Function0;Ljava/lang/String;Ljava/lang/String;IILscala/Option;Lscala/Option;)V
  #215 = NameAndType        #213:#214     // handleNestedBranch:(Ljava/lang/String;Lscala/Option;Lscala/Function0;Lscala/Function0;Ljava/lang/String;Ljava/lang/String;IILscala/Option;Lscala/Option;)V
  #216 = Methodref          #86.#215      // org/scalatest/PathEngine.handleNestedBranch:(Ljava/lang/String;Lscala/Option;Lscala/Function0;Lscala/Function0;Ljava/lang/String;Ljava/lang/String;IILscala/Option;Lscala/Option;)V
  #217 = Utf8               org/scalatest/exceptions/TestFailedException
  #218 = Class              #217          // org/scalatest/exceptions/TestFailedException
  #219 = Utf8               org/scalatest/exceptions/NotAllowedException
  #220 = Class              #219          // org/scalatest/exceptions/NotAllowedException
  #221 = Utf8               org/scalatest/FailureMessages$
  #222 = Class              #221          // org/scalatest/FailureMessages$
  #223 = Utf8               Lorg/scalatest/FailureMessages$;
  #224 = NameAndType        #173:#223     // MODULE$:Lorg/scalatest/FailureMessages$;
  #225 = Fieldref           #222.#224     // org/scalatest/FailureMessages$.MODULE$:Lorg/scalatest/FailureMessages$;
  #226 = Utf8               assertionShouldBePutInsideItOrTheyClauseNotDescribeClause
  #227 = NameAndType        #226:#150     // assertionShouldBePutInsideItOrTheyClauseNotDescribeClause:()Ljava/lang/String;
  #228 = Methodref          #222.#227     // org/scalatest/FailureMessages$.assertionShouldBePutInsideItOrTheyClauseNotDescribeClause:()Ljava/lang/String;
  #229 = Utf8               position
  #230 = Utf8               ()Lscala/Option;
  #231 = NameAndType        #229:#230     // position:()Lscala/Option;
  #232 = Methodref          #218.#231     // org/scalatest/exceptions/TestFailedException.position:()Lscala/Option;
  #233 = Utf8               $anonfun$describeImpl$2
  #234 = Utf8               (Lorg/scalactic/source/Position;)Lorg/scalactic/source/Position;
  #235 = NameAndType        #233:#234     // $anonfun$describeImpl$2:(Lorg/scalactic/source/Position;)Lorg/scalactic/source/Position;
  #236 = InterfaceMethodref #2.#235       // org/scalatest/funspec/PathAnyFunSpecLike.$anonfun$describeImpl$2:(Lorg/scalactic/source/Position;)Lorg/scalactic/source/Position;
  #237 = MethodHandle       6:#236        // REF_invokeStatic org/scalatest/funspec/PathAnyFunSpecLike.$anonfun$describeImpl$2:(Lorg/scalactic/source/Position;)Lorg/scalactic/source/Position;
  #238 = Utf8               ()Lorg/scalactic/source/Position;
  #239 = MethodType         #238          //  ()Lorg/scalactic/source/Position;
  #240 = Utf8               (Lorg/scalactic/source/Position;)Lscala/Function0;
  #241 = NameAndType        #164:#240     // apply:(Lorg/scalactic/source/Position;)Lscala/Function0;
  #242 = InvokeDynamic      #2:#241       // #2:apply:(Lorg/scalactic/source/Position;)Lscala/Function0;
  #243 = Utf8               scala/Option
  #244 = Class              #243          // scala/Option
  #245 = Utf8               getOrElse
  #246 = Utf8               (Lscala/Function0;)Ljava/lang/Object;
  #247 = NameAndType        #245:#246     // getOrElse:(Lscala/Function0;)Ljava/lang/Object;
  #248 = Methodref          #244.#247     // scala/Option.getOrElse:(Lscala/Function0;)Ljava/lang/Object;
  #249 = Utf8               org/scalactic/source/Position
  #250 = Class              #249          // org/scalactic/source/Position
  #251 = Utf8               (Ljava/lang/String;Lscala/Option;Lorg/scalactic/source/Position;)V
  #252 = NameAndType        #144:#251     // "<init>":(Ljava/lang/String;Lscala/Option;Lorg/scalactic/source/Position;)V
  #253 = Methodref          #220.#252     // org/scalatest/exceptions/NotAllowedException."<init>":(Ljava/lang/String;Lscala/Option;Lorg/scalactic/source/Position;)V
  #254 = Utf8               org/scalatest/exceptions/TestCanceledException
  #255 = Class              #254          // org/scalatest/exceptions/TestCanceledException
  #256 = Methodref          #255.#231     // org/scalatest/exceptions/TestCanceledException.position:()Lscala/Option;
  #257 = Utf8               $anonfun$describeImpl$3
  #258 = NameAndType        #257:#234     // $anonfun$describeImpl$3:(Lorg/scalactic/source/Position;)Lorg/scalactic/source/Position;
  #259 = InterfaceMethodref #2.#258       // org/scalatest/funspec/PathAnyFunSpecLike.$anonfun$describeImpl$3:(Lorg/scalactic/source/Position;)Lorg/scalactic/source/Position;
  #260 = MethodHandle       6:#259        // REF_invokeStatic org/scalatest/funspec/PathAnyFunSpecLike.$anonfun$describeImpl$3:(Lorg/scalactic/source/Position;)Lorg/scalactic/source/Position;
  #261 = InvokeDynamic      #3:#241       // #3:apply:(Lorg/scalactic/source/Position;)Lscala/Function0;
  #262 = Utf8               org/scalatest/exceptions/DuplicateTestNameException
  #263 = Class              #262          // org/scalatest/exceptions/DuplicateTestNameException
  #264 = Utf8               org/scalactic/Prettifier$
  #265 = Class              #264          // org/scalactic/Prettifier$
  #266 = Utf8               Lorg/scalactic/Prettifier$;
  #267 = NameAndType        #173:#266     // MODULE$:Lorg/scalactic/Prettifier$;
  #268 = Fieldref           #265.#267     // org/scalactic/Prettifier$.MODULE$:Lorg/scalactic/Prettifier$;
  #269 = Utf8               default
  #270 = Utf8               ()Lorg/scalactic/Prettifier;
  #271 = NameAndType        #269:#270     // default:()Lorg/scalactic/Prettifier;
  #272 = Methodref          #265.#271     // org/scalactic/Prettifier$.default:()Lorg/scalactic/Prettifier;
  #273 = Utf8               org/scalatest/UnquotedString$
  #274 = Class              #273          // org/scalatest/UnquotedString$
  #275 = Utf8               Lorg/scalatest/UnquotedString$;
  #276 = NameAndType        #173:#275     // MODULE$:Lorg/scalatest/UnquotedString$;
  #277 = Fieldref           #274.#276     // org/scalatest/UnquotedString$.MODULE$:Lorg/scalatest/UnquotedString$;
  #278 = Methodref          #263.#69      // org/scalatest/exceptions/DuplicateTestNameException.getClass:()Ljava/lang/Class;
  #279 = Utf8               getName
  #280 = NameAndType        #279:#150     // getName:()Ljava/lang/String;
  #281 = Methodref          #72.#280      // java/lang/Class.getName:()Ljava/lang/String;
  #282 = Utf8               (Ljava/lang/String;)Lorg/scalatest/UnquotedString;
  #283 = NameAndType        #164:#282     // apply:(Ljava/lang/String;)Lorg/scalatest/UnquotedString;
  #284 = Methodref          #274.#283     // org/scalatest/UnquotedString$.apply:(Ljava/lang/String;)Lorg/scalatest/UnquotedString;
  #285 = Utf8               getMessage
  #286 = NameAndType        #285:#150     // getMessage:()Ljava/lang/String;
  #287 = Methodref          #263.#286     // org/scalatest/exceptions/DuplicateTestNameException.getMessage:()Ljava/lang/String;
  #288 = Utf8               exceptionWasThrownInDescribeClause
  #289 = Utf8               (Lorg/scalactic/Prettifier;Ljava/lang/Object;Ljava/lang/Object;Ljava/lang/Object;)Ljava/lang/String;
  #290 = NameAndType        #288:#289     // exceptionWasThrownInDescribeClause:(Lorg/scalactic/Prettifier;Ljava/lang/Object;Ljava/lang/Object;Ljava/lang/Object;)Ljava/lang/String;
  #291 = Methodref          #222.#290     // org/scalatest/FailureMessages$.exceptionWasThrownInDescribeClause:(Lorg/scalactic/Prettifier;Ljava/lang/Object;Ljava/lang/Object;Ljava/lang/Object;)Ljava/lang/String;
  #292 = Methodref          #263.#231     // org/scalatest/exceptions/DuplicateTestNameException.position:()Lscala/Option;
  #293 = Utf8               $anonfun$describeImpl$4
  #294 = NameAndType        #293:#234     // $anonfun$describeImpl$4:(Lorg/scalactic/source/Position;)Lorg/scalactic/source/Position;
  #295 = InterfaceMethodref #2.#294       // org/scalatest/funspec/PathAnyFunSpecLike.$anonfun$describeImpl$4:(Lorg/scalactic/source/Position;)Lorg/scalactic/source/Position;
  #296 = MethodHandle       6:#295        // REF_invokeStatic org/scalatest/funspec/PathAnyFunSpecLike.$anonfun$describeImpl$4:(Lorg/scalactic/source/Position;)Lorg/scalactic/source/Position;
  #297 = InvokeDynamic      #4:#241       // #4:apply:(Lorg/scalactic/source/Position;)Lscala/Function0;
  #298 = Utf8               org/scalatest/Suite$
  #299 = Class              #298          // org/scalatest/Suite$
  #300 = Utf8               Lorg/scalatest/Suite$;
  #301 = NameAndType        #173:#300     // MODULE$:Lorg/scalatest/Suite$;
  #302 = Fieldref           #299.#301     // org/scalatest/Suite$.MODULE$:Lorg/scalatest/Suite$;
  #303 = Utf8               anExceptionThatShouldCauseAnAbort
  #304 = Utf8               (Ljava/lang/Throwable;)Z
  #305 = NameAndType        #303:#304     // anExceptionThatShouldCauseAnAbort:(Ljava/lang/Throwable;)Z
  #306 = Methodref          #299.#305     // org/scalatest/Suite$.anExceptionThatShouldCauseAnAbort:(Ljava/lang/Throwable;)Z
  #307 = Methodref          #205.#69      // java/lang/Throwable.getClass:()Ljava/lang/Class;
  #308 = Methodref          #205.#286     // java/lang/Throwable.getMessage:()Ljava/lang/String;
  #309 = Utf8               java/lang/String
  #310 = Class              #309          // java/lang/String
  #311 = Utf8               scala/Function0
  #312 = Class              #311          // scala/Function0
  #313 = Utf8               describe$
  #314 = Utf8               (Lorg/scalatest/funspec/PathAnyFunSpecLike;Ljava/lang/String;Lscala/Function0;Lorg/scalactic/source/Position;)V
  #315 = NameAndType        #211:#200     // describe:(Ljava/lang/String;Lscala/Function0;Lorg/scalactic/source/Position;)V
  #316 = InterfaceMethodref #2.#315       // org/scalatest/funspec/PathAnyFunSpecLike.describe:(Ljava/lang/String;Lscala/Function0;Lorg/scalactic/source/Position;)V
  #317 = NameAndType        #199:#200     // describeImpl:(Ljava/lang/String;Lscala/Function0;Lorg/scalactic/source/Position;)V
  #318 = InterfaceMethodref #2.#317       // org/scalatest/funspec/PathAnyFunSpecLike.describeImpl:(Ljava/lang/String;Lscala/Function0;Lorg/scalactic/source/Position;)V
  #319 = Utf8               behave
  #320 = Utf8               ()Lorg/scalatest/verbs/BehaveWord;
  #321 = Utf8               testNames$
  #322 = Utf8               (Lorg/scalatest/funspec/PathAnyFunSpecLike;)Lscala/collection/immutable/Set;
  #323 = Utf8               testNames
  #324 = Utf8               ()Lscala/collection/immutable/Set;
  #325 = NameAndType        #323:#324     // testNames:()Lscala/collection/immutable/Set;
  #326 = InterfaceMethodref #2.#325       // org/scalatest/funspec/PathAnyFunSpecLike.testNames:()Lscala/collection/immutable/Set;
  #327 = Utf8               ()Lscala/collection/immutable/Set<Ljava/lang/String;>;
  #328 = Utf8               ensureTestResultsRegistered
  #329 = Utf8               (Lorg/scalatest/Suite;)V
  #330 = NameAndType        #328:#329     // ensureTestResultsRegistered:(Lorg/scalatest/Suite;)V
  #331 = Methodref          #86.#330      // org/scalatest/PathEngine.ensureTestResultsRegistered:(Lorg/scalatest/Suite;)V
  #332 = Utf8               org/scalatest/InsertionOrderSet$
  #333 = Class              #332          // org/scalatest/InsertionOrderSet$
  #334 = Utf8               Lorg/scalatest/InsertionOrderSet$;
  #335 = NameAndType        #173:#334     // MODULE$:Lorg/scalatest/InsertionOrderSet$;
  #336 = Fieldref           #333.#335     // org/scalatest/InsertionOrderSet$.MODULE$:Lorg/scalatest/InsertionOrderSet$;
  #337 = Utf8               atomic
  #338 = NameAndType        #337:#88      // atomic:()Ljava/util/concurrent/atomic/AtomicReference;
  #339 = Methodref          #86.#338      // org/scalatest/PathEngine.atomic:()Ljava/util/concurrent/atomic/AtomicReference;
  #340 = Utf8               testNamesList
  #341 = Utf8               ()Lscala/collection/immutable/List;
  #342 = NameAndType        #340:#341     // testNamesList:()Lscala/collection/immutable/List;
  #343 = Methodref          #30.#342      // org/scalatest/SuperEngine$Bundle.testNamesList:()Lscala/collection/immutable/List;
  #344 = Utf8               (Lscala/collection/immutable/List;)Lscala/collection/immutable/Set;
  #345 = NameAndType        #164:#344     // apply:(Lscala/collection/immutable/List;)Lscala/collection/immutable/Set;
  #346 = Methodref          #333.#345     // org/scalatest/InsertionOrderSet$.apply:(Lscala/collection/immutable/List;)Lscala/collection/immutable/Set;
  #347 = Utf8               expectedTestCount$
  #348 = Utf8               (Lorg/scalatest/funspec/PathAnyFunSpecLike;Lorg/scalatest/Filter;)I
  #349 = Utf8               expectedTestCount
  #350 = NameAndType        #349:#55      // expectedTestCount:(Lorg/scalatest/Filter;)I
  #351 = InterfaceMethodref #2.#350       // org/scalatest/funspec/PathAnyFunSpecLike.expectedTestCount:(Lorg/scalatest/Filter;)I
  #352 = Utf8               Lorg/scalatest/Filter;
  #353 = NameAndType        #54:#55       // org$scalatest$funspec$PathAnyFunSpecLike$$super$expectedTestCount:(Lorg/scalatest/Filter;)I
  #354 = InterfaceMethodref #2.#353       // org/scalatest/funspec/PathAnyFunSpecLike.org$scalatest$funspec$PathAnyFunSpecLike$$super$expectedTestCount:(Lorg/scalatest/Filter;)I
  #355 = Utf8               runTest$
  #356 = Utf8               (Lorg/scalatest/funspec/PathAnyFunSpecLike;Ljava/lang/String;Lorg/scalatest/Args;)Lorg/scalatest/Status;
  #357 = Utf8               testName
  #358 = Utf8               args
  #359 = Utf8               runTest
  #360 = Utf8               (Ljava/lang/String;Lorg/scalatest/Args;)Lorg/scalatest/Status;
  #361 = NameAndType        #359:#360     // runTest:(Ljava/lang/String;Lorg/scalatest/Args;)Lorg/scalatest/Status;
  #362 = InterfaceMethodref #2.#361       // org/scalatest/funspec/PathAnyFunSpecLike.runTest:(Ljava/lang/String;Lorg/scalatest/Args;)Lorg/scalatest/Status;
  #363 = Utf8               Lorg/scalatest/Args;
  #364 = Utf8               (Ljava/lang/Object;)Ljava/lang/Object;
  #365 = MethodType         #364          //  (Ljava/lang/Object;)Ljava/lang/Object;
  #366 = Utf8               $anonfun$runTest$1
  #367 = Utf8               (Lorg/scalatest/SuperEngine$TestLeaf;)Lorg/scalatest/Outcome;
  #368 = NameAndType        #366:#367     // $anonfun$runTest$1:(Lorg/scalatest/SuperEngine$TestLeaf;)Lorg/scalatest/Outcome;
  #369 = InterfaceMethodref #2.#368       // org/scalatest/funspec/PathAnyFunSpecLike.$anonfun$runTest$1:(Lorg/scalatest/SuperEngine$TestLeaf;)Lorg/scalatest/Outcome;
  #370 = MethodHandle       6:#369        // REF_invokeStatic org/scalatest/funspec/PathAnyFunSpecLike.$anonfun$runTest$1:(Lorg/scalatest/SuperEngine$TestLeaf;)Lorg/scalatest/Outcome;
  #371 = MethodType         #367          //  (Lorg/scalatest/SuperEngine$TestLeaf;)Lorg/scalatest/Outcome;
  #372 = Utf8               ()Lscala/Function1;
  #373 = NameAndType        #164:#372     // apply:()Lscala/Function1;
  #374 = InvokeDynamic      #5:#373       // #5:apply:()Lscala/Function1;
  #375 = Utf8               runTestImpl
  #376 = Utf8               (Lorg/scalatest/Suite;Ljava/lang/String;Lorg/scalatest/Args;ZLscala/Function1;)Lorg/scalatest/Status;
  #377 = NameAndType        #375:#376     // runTestImpl:(Lorg/scalatest/Suite;Ljava/lang/String;Lorg/scalatest/Args;ZLscala/Function1;)Lorg/scalatest/Status;
  #378 = Methodref          #86.#377      // org/scalatest/PathEngine.runTestImpl:(Lorg/scalatest/Suite;Ljava/lang/String;Lorg/scalatest/Args;ZLscala/Function1;)Lorg/scalatest/Status;
  #379 = Utf8               tags$
  #380 = Utf8               (Lorg/scalatest/funspec/PathAnyFunSpecLike;)Lscala/collection/immutable/Map;
  #381 = Utf8               tags
  #382 = Utf8               ()Lscala/collection/immutable/Map;
  #383 = NameAndType        #381:#382     // tags:()Lscala/collection/immutable/Map;
  #384 = InterfaceMethodref #2.#383       // org/scalatest/funspec/PathAnyFunSpecLike.tags:()Lscala/collection/immutable/Map;
  #385 = Utf8               ()Lscala/collection/immutable/Map<Ljava/lang/String;Lscala/collection/immutable/Set<Ljava/lang/String;>;>;
  #386 = Utf8               tagsMap
  #387 = NameAndType        #386:#382     // tagsMap:()Lscala/collection/immutable/Map;
  #388 = Methodref          #30.#387      // org/scalatest/SuperEngine$Bundle.tagsMap:()Lscala/collection/immutable/Map;
  #389 = Utf8               autoTagClassAnnotations
  #390 = Utf8               (Lscala/collection/immutable/Map;Lorg/scalatest/Suite;)Lscala/collection/immutable/Map;
  #391 = NameAndType        #389:#390     // autoTagClassAnnotations:(Lscala/collection/immutable/Map;Lorg/scalatest/Suite;)Lscala/collection/immutable/Map;
  #392 = Methodref          #299.#391     // org/scalatest/Suite$.autoTagClassAnnotations:(Lscala/collection/immutable/Map;Lorg/scalatest/Suite;)Lscala/collection/immutable/Map;
  #393 = Utf8               run$
  #394 = Utf8               (Lorg/scalatest/funspec/PathAnyFunSpecLike;Lscala/Option;Lorg/scalatest/Args;)Lorg/scalatest/Status;
  #395 = Utf8               run
  #396 = Utf8               (Lscala/Option;Lorg/scalatest/Args;)Lorg/scalatest/Status;
  #397 = NameAndType        #395:#396     // run:(Lscala/Option;Lorg/scalatest/Args;)Lorg/scalatest/Status;
  #398 = InterfaceMethodref #2.#397       // org/scalatest/funspec/PathAnyFunSpecLike.run:(Lscala/Option;Lorg/scalatest/Args;)Lorg/scalatest/Status;
  #399 = Utf8               Lscala/Option;
  #400 = Utf8               (Lscala/Option<Ljava/lang/String;>;Lorg/scalatest/Args;)Lorg/scalatest/Status;
  #401 = Utf8               (Ljava/lang/Object;Ljava/lang/Object;)Ljava/lang/Object;
  #402 = MethodType         #401          //  (Ljava/lang/Object;Ljava/lang/Object;)Ljava/lang/Object;
  #403 = Utf8               $anonfun$run$1
  #404 = NameAndType        #403:#356     // $anonfun$run$1:(Lorg/scalatest/funspec/PathAnyFunSpecLike;Ljava/lang/String;Lorg/scalatest/Args;)Lorg/scalatest/Status;
  #405 = InterfaceMethodref #2.#404       // org/scalatest/funspec/PathAnyFunSpecLike.$anonfun$run$1:(Lorg/scalatest/funspec/PathAnyFunSpecLike;Ljava/lang/String;Lorg/scalatest/Args;)Lorg/scalatest/Status;
  #406 = MethodHandle       6:#405        // REF_invokeStatic org/scalatest/funspec/PathAnyFunSpecLike.$anonfun$run$1:(Lorg/scalatest/funspec/PathAnyFunSpecLike;Ljava/lang/String;Lorg/scalatest/Args;)Lorg/scalatest/Status;
  #407 = MethodType         #360          //  (Ljava/lang/String;Lorg/scalatest/Args;)Lorg/scalatest/Status;
  #408 = Utf8               (Lorg/scalatest/funspec/PathAnyFunSpecLike;)Lscala/Function2;
  #409 = NameAndType        #164:#408     // apply:(Lorg/scalatest/funspec/PathAnyFunSpecLike;)Lscala/Function2;
  #410 = InvokeDynamic      #6:#409       // #6:apply:(Lorg/scalatest/funspec/PathAnyFunSpecLike;)Lscala/Function2;
  #411 = Utf8               runPathTestsImpl
  #412 = Utf8               (Lorg/scalatest/Suite;Lscala/Option;Lorg/scalatest/Args;Lorg/scalatest/Informer;ZLscala/Function2;)Lorg/scalatest/Status;
  #413 = NameAndType        #411:#412     // runPathTestsImpl:(Lorg/scalatest/Suite;Lscala/Option;Lorg/scalatest/Args;Lorg/scalatest/Informer;ZLscala/Function2;)Lorg/scalatest/Status;
  #414 = Methodref          #86.#413      // org/scalatest/PathEngine.runPathTestsImpl:(Lorg/scalatest/Suite;Lscala/Option;Lorg/scalatest/Args;Lorg/scalatest/Informer;ZLscala/Function2;)Lorg/scalatest/Status;
  #415 = Utf8               runTests$
  #416 = Utf8               runTests
  #417 = NameAndType        #416:#396     // runTests:(Lscala/Option;Lorg/scalatest/Args;)Lorg/scalatest/Status;
  #418 = InterfaceMethodref #2.#417       // org/scalatest/funspec/PathAnyFunSpecLike.runTests:(Lscala/Option;Lorg/scalatest/Args;)Lorg/scalatest/Status;
  #419 = Utf8               java/lang/UnsupportedOperationException
  #420 = Class              #419          // java/lang/UnsupportedOperationException
  #421 = Utf8               ()V
  #422 = NameAndType        #144:#421     // "<init>":()V
  #423 = Methodref          #420.#422     // java/lang/UnsupportedOperationException."<init>":()V
  #424 = Utf8               runNestedSuites$
  #425 = Utf8               (Lorg/scalatest/funspec/PathAnyFunSpecLike;Lorg/scalatest/Args;)Lorg/scalatest/Status;
  #426 = Utf8               runNestedSuites
  #427 = Utf8               (Lorg/scalatest/Args;)Lorg/scalatest/Status;
  #428 = NameAndType        #426:#427     // runNestedSuites:(Lorg/scalatest/Args;)Lorg/scalatest/Status;
  #429 = InterfaceMethodref #2.#428       // org/scalatest/funspec/PathAnyFunSpecLike.runNestedSuites:(Lorg/scalatest/Args;)Lorg/scalatest/Status;
  #430 = Utf8               org/scalatest/SucceededStatus$
  #431 = Class              #430          // org/scalatest/SucceededStatus$
  #432 = Utf8               Lorg/scalatest/SucceededStatus$;
  #433 = NameAndType        #173:#432     // MODULE$:Lorg/scalatest/SucceededStatus$;
  #434 = Fieldref           #431.#433     // org/scalatest/SucceededStatus$.MODULE$:Lorg/scalatest/SucceededStatus$;
  #435 = Utf8               nestedSuites$
  #436 = Utf8               (Lorg/scalatest/funspec/PathAnyFunSpecLike;)Lscala/collection/immutable/IndexedSeq;
  #437 = Utf8               nestedSuites
  #438 = Utf8               ()Lscala/collection/immutable/IndexedSeq;
  #439 = NameAndType        #437:#438     // nestedSuites:()Lscala/collection/immutable/IndexedSeq;
  #440 = InterfaceMethodref #2.#439       // org/scalatest/funspec/PathAnyFunSpecLike.nestedSuites:()Lscala/collection/immutable/IndexedSeq;
  #441 = Utf8               ()Lscala/collection/immutable/IndexedSeq<Lorg/scalatest/Suite;>;
  #442 = Utf8               scala/package$
  #443 = Class              #442          // scala/package$
  #444 = Utf8               Lscala/package$;
  #445 = NameAndType        #173:#444     // MODULE$:Lscala/package$;
  #446 = Fieldref           #443.#445     // scala/package$.MODULE$:Lscala/package$;
  #447 = Utf8               Vector
  #448 = Utf8               ()Lscala/collection/immutable/Vector$;
  #449 = NameAndType        #447:#448     // Vector:()Lscala/collection/immutable/Vector$;
  #450 = Methodref          #443.#449     // scala/package$.Vector:()Lscala/collection/immutable/Vector$;
  #451 = Utf8               scala/collection/immutable/Vector$
  #452 = Class              #451          // scala/collection/immutable/Vector$
  #453 = Utf8               empty
  #454 = Utf8               ()Lscala/collection/immutable/Vector;
  #455 = NameAndType        #453:#454     // empty:()Lscala/collection/immutable/Vector;
  #456 = Methodref          #452.#455     // scala/collection/immutable/Vector$.empty:()Lscala/collection/immutable/Vector;
  #457 = Utf8               styleName
  #458 = Utf8               testDataFor$
  #459 = Utf8               (Lorg/scalatest/funspec/PathAnyFunSpecLike;Ljava/lang/String;Lorg/scalatest/ConfigMap;)Lorg/scalatest/TestData;
  #460 = Utf8               theConfigMap
  #461 = Utf8               testDataFor
  #462 = Utf8               (Ljava/lang/String;Lorg/scalatest/ConfigMap;)Lorg/scalatest/TestData;
  #463 = NameAndType        #461:#462     // testDataFor:(Ljava/lang/String;Lorg/scalatest/ConfigMap;)Lorg/scalatest/TestData;
  #464 = InterfaceMethodref #2.#463       // org/scalatest/funspec/PathAnyFunSpecLike.testDataFor:(Ljava/lang/String;Lorg/scalatest/ConfigMap;)Lorg/scalatest/TestData;
  #465 = Utf8               Lorg/scalatest/ConfigMap;
  #466 = Utf8               createTestDataFor
  #467 = Utf8               (Ljava/lang/String;Lorg/scalatest/ConfigMap;Lorg/scalatest/Suite;)Lorg/scalatest/TestData;
  #468 = NameAndType        #466:#467     // createTestDataFor:(Ljava/lang/String;Lorg/scalatest/ConfigMap;Lorg/scalatest/Suite;)Lorg/scalatest/TestData;
  #469 = Methodref          #86.#468      // org/scalatest/PathEngine.createTestDataFor:(Ljava/lang/String;Lorg/scalatest/ConfigMap;Lorg/scalatest/Suite;)Lorg/scalatest/TestData;
  #470 = Utf8               testDataFor$default$2$
  #471 = Utf8               (Lorg/scalatest/funspec/PathAnyFunSpecLike;)Lorg/scalatest/ConfigMap;
  #472 = Utf8               testDataFor$default$2
  #473 = Utf8               ()Lorg/scalatest/ConfigMap;
  #474 = NameAndType        #472:#473     // testDataFor$default$2:()Lorg/scalatest/ConfigMap;
  #475 = InterfaceMethodref #2.#474       // org/scalatest/funspec/PathAnyFunSpecLike.testDataFor$default$2:()Lorg/scalatest/ConfigMap;
  #476 = Utf8               org/scalatest/ConfigMap$
  #477 = Class              #476          // org/scalatest/ConfigMap$
  #478 = Utf8               Lorg/scalatest/ConfigMap$;
  #479 = NameAndType        #173:#478     // MODULE$:Lorg/scalatest/ConfigMap$;
  #480 = Fieldref           #477.#479     // org/scalatest/ConfigMap$.MODULE$:Lorg/scalatest/ConfigMap$;
  #481 = NameAndType        #453:#473     // empty:()Lorg/scalatest/ConfigMap;
  #482 = Methodref          #477.#481     // org/scalatest/ConfigMap$.empty:()Lorg/scalatest/ConfigMap;
  #483 = Utf8               org/scalatest/Resources$
  #484 = Class              #483          // org/scalatest/Resources$
  #485 = Utf8               Lorg/scalatest/Resources$;
  #486 = NameAndType        #173:#485     // MODULE$:Lorg/scalatest/Resources$;
  #487 = Fieldref           #484.#486     // org/scalatest/Resources$.MODULE$:Lorg/scalatest/Resources$;
  #488 = Utf8               ignoreCannotAppearInsideAnItOrAThey
  #489 = NameAndType        #488:#150     // ignoreCannotAppearInsideAnItOrAThey:()Ljava/lang/String;
  #490 = Methodref          #484.#489     // org/scalatest/Resources$.ignoreCannotAppearInsideAnItOrAThey:()Ljava/lang/String;
  #491 = Utf8               describeCannotAppearInsideAnIt
  #492 = NameAndType        #491:#150     // describeCannotAppearInsideAnIt:()Ljava/lang/String;
  #493 = Methodref          #484.#492     // org/scalatest/Resources$.describeCannotAppearInsideAnIt:()Ljava/lang/String;
  #494 = Utf8               pos$1
  #495 = Utf8               dontInvokeWithFixture$1
  #496 = Utf8               theTest
  #497 = NameAndType        #140:#73      // testFun:()Ljava/lang/Object;
  #498 = Methodref          #35.#497      // org/scalatest/SuperEngine$TestLeaf.testFun:()Ljava/lang/Object;
  #499 = NameAndType        #164:#73      // apply:()Ljava/lang/Object;
  #500 = InterfaceMethodref #312.#499     // scala/Function0.apply:()Ljava/lang/Object;
  #501 = Utf8               org/scalatest/Outcome
  #502 = Class              #501          // org/scalatest/Outcome
  #503 = Utf8               Lorg/scalatest/SuperEngine$TestLeaf;
  #504 = NameAndType        #495:#367     // dontInvokeWithFixture$1:(Lorg/scalatest/SuperEngine$TestLeaf;)Lorg/scalatest/Outcome;
  #505 = InterfaceMethodref #2.#504       // org/scalatest/funspec/PathAnyFunSpecLike.dontInvokeWithFixture$1:(Lorg/scalatest/SuperEngine$TestLeaf;)Lorg/scalatest/Outcome;
  #506 = Utf8               $init$
  #507 = Utf8               (Lorg/scalatest/funspec/PathAnyFunSpecLike;)V
  #508 = Utf8               org/scalatest/PathEngine$
  #509 = Class              #508          // org/scalatest/PathEngine$
  #510 = Utf8               Lorg/scalatest/PathEngine$;
  #511 = NameAndType        #173:#510     // MODULE$:Lorg/scalatest/PathEngine$;
  #512 = Fieldref           #509.#511     // org/scalatest/PathEngine$.MODULE$:Lorg/scalatest/PathEngine$;
  #513 = Utf8               getEngine
  #514 = NameAndType        #513:#58      // getEngine:()Lorg/scalatest/PathEngine;
  #515 = Methodref          #509.#514     // org/scalatest/PathEngine$.getEngine:()Lorg/scalatest/PathEngine;
  #516 = NameAndType        #43:#44       // org$scalatest$funspec$PathAnyFunSpecLike$_setter_$org$scalatest$funspec$PathAnyFunSpecLike$$engine_$eq:(Lorg/scalatest/PathEngine;)V
  #517 = InterfaceMethodref #2.#516       // org/scalatest/funspec/PathAnyFunSpecLike.org$scalatest$funspec$PathAnyFunSpecLike$_setter_$org$scalatest$funspec$PathAnyFunSpecLike$$engine_$eq:(Lorg/scalatest/PathEngine;)V
  #518 = NameAndType        #144:#507     // "<init>":(Lorg/scalatest/funspec/PathAnyFunSpecLike;)V
  #519 = Methodref          #38.#518      // org/scalatest/funspec/PathAnyFunSpecLike$ItWord."<init>":(Lorg/scalatest/funspec/PathAnyFunSpecLike;)V
  #520 = NameAndType        #46:#47       // org$scalatest$funspec$PathAnyFunSpecLike$_setter_$it_$eq:(Lorg/scalatest/funspec/PathAnyFunSpecLike$ItWord;)V
  #521 = InterfaceMethodref #2.#520       // org/scalatest/funspec/PathAnyFunSpecLike.org$scalatest$funspec$PathAnyFunSpecLike$_setter_$it_$eq:(Lorg/scalatest/funspec/PathAnyFunSpecLike$ItWord;)V
  #522 = Methodref          #41.#518      // org/scalatest/funspec/PathAnyFunSpecLike$TheyWord."<init>":(Lorg/scalatest/funspec/PathAnyFunSpecLike;)V
  #523 = NameAndType        #48:#49       // org$scalatest$funspec$PathAnyFunSpecLike$_setter_$they_$eq:(Lorg/scalatest/funspec/PathAnyFunSpecLike$TheyWord;)V
  #524 = InterfaceMethodref #2.#523       // org/scalatest/funspec/PathAnyFunSpecLike.org$scalatest$funspec$PathAnyFunSpecLike$_setter_$they_$eq:(Lorg/scalatest/funspec/PathAnyFunSpecLike$TheyWord;)V
  #525 = Utf8               org/scalatest/verbs/BehaveWord
  #526 = Class              #525          // org/scalatest/verbs/BehaveWord
  #527 = Methodref          #526.#422     // org/scalatest/verbs/BehaveWord."<init>":()V
  #528 = NameAndType        #50:#51       // org$scalatest$funspec$PathAnyFunSpecLike$_setter_$behave_$eq:(Lorg/scalatest/verbs/BehaveWord;)V
  #529 = InterfaceMethodref #2.#528       // org/scalatest/funspec/PathAnyFunSpecLike.org$scalatest$funspec$PathAnyFunSpecLike$_setter_$behave_$eq:(Lorg/scalatest/verbs/BehaveWord;)V
  #530 = Utf8               org.scalatest.path.FunSpec
  #531 = String             #530          // org.scalatest.path.FunSpec
  #532 = NameAndType        #52:#53       // org$scalatest$funspec$PathAnyFunSpecLike$_setter_$styleName_$eq:(Ljava/lang/String;)V
  #533 = InterfaceMethodref #2.#532       // org/scalatest/funspec/PathAnyFunSpecLike.org$scalatest$funspec$PathAnyFunSpecLike$_setter_$styleName_$eq:(Ljava/lang/String;)V
  #534 = Utf8               $deserializeLambda$
  #535 = Utf8               (Ljava/lang/invoke/SerializedLambda;)Ljava/lang/Object;
  #536 = Utf8               scala/runtime/LambdaDeserialize
  #537 = Class              #536          // scala/runtime/LambdaDeserialize
  #538 = Utf8               bootstrap
  #539 = Utf8               (Ljava/lang/invoke/MethodHandles$Lookup;Ljava/lang/String;Ljava/lang/invoke/MethodType;[Ljava/lang/invoke/MethodHandle;)Ljava/lang/invoke/CallSite;
  #540 = NameAndType        #538:#539     // bootstrap:(Ljava/lang/invoke/MethodHandles$Lookup;Ljava/lang/String;Ljava/lang/invoke/MethodType;[Ljava/lang/invoke/MethodHandle;)Ljava/lang/invoke/CallSite;
  #541 = Methodref          #537.#540     // scala/runtime/LambdaDeserialize.bootstrap:(Ljava/lang/invoke/MethodHandles$Lookup;Ljava/lang/String;Ljava/lang/invoke/MethodType;[Ljava/lang/invoke/MethodHandle;)Ljava/lang/invoke/CallSite;
  #542 = MethodHandle       6:#541        // REF_invokeStatic scala/runtime/LambdaDeserialize.bootstrap:(Ljava/lang/invoke/MethodHandles$Lookup;Ljava/lang/String;Ljava/lang/invoke/MethodType;[Ljava/lang/invoke/MethodHandle;)Ljava/lang/invoke/CallSite;
  #543 = Utf8               lambdaDeserialize
  #544 = NameAndType        #543:#535     // lambdaDeserialize:(Ljava/lang/invoke/SerializedLambda;)Ljava/lang/Object;
  #545 = InvokeDynamic      #7:#544       // #7:lambdaDeserialize:(Ljava/lang/invoke/SerializedLambda;)Ljava/lang/Object;
  #546 = Utf8               MethodParameters
  #547 = Utf8               Code
  #548 = Utf8               LineNumberTable
  #549 = Utf8               LocalVariableTable
  #550 = Utf8               Signature
  #551 = Utf8               StackMapTable
  #552 = Utf8               Deprecated
  #553 = Utf8               InnerClasses
  #554 = Utf8               SourceFile
  #555 = Utf8               RuntimeVisibleAnnotations
  #556 = Utf8               BootstrapMethods
  #557 = Utf8               ScalaInlineInfo
  #558 = Utf8               ScalaSig
{
  public abstract void org$scalatest$funspec$PathAnyFunSpecLike$_setter_$org$scalatest$funspec$PathAnyFunSpecLike$$engine_$eq(org.scalatest.PathEngine);
    descriptor: (Lorg/scalatest/PathEngine;)V
    flags: (0x0401) ACC_PUBLIC, ACC_ABSTRACT
    MethodParameters:
      Name                           Flags
      x$1                            final

  public abstract void org$scalatest$funspec$PathAnyFunSpecLike$_setter_$it_$eq(org.scalatest.funspec.PathAnyFunSpecLike$ItWord);
    descriptor: (Lorg/scalatest/funspec/PathAnyFunSpecLike$ItWord;)V
    flags: (0x0401) ACC_PUBLIC, ACC_ABSTRACT
    MethodParameters:
      Name                           Flags
      x$1                            final

  public abstract void org$scalatest$funspec$PathAnyFunSpecLike$_setter_$they_$eq(org.scalatest.funspec.PathAnyFunSpecLike$TheyWord);
    descriptor: (Lorg/scalatest/funspec/PathAnyFunSpecLike$TheyWord;)V
    flags: (0x0401) ACC_PUBLIC, ACC_ABSTRACT
    MethodParameters:
      Name                           Flags
      x$1                            final

  public abstract void org$scalatest$funspec$PathAnyFunSpecLike$_setter_$behave_$eq(org.scalatest.verbs.BehaveWord);
    descriptor: (Lorg/scalatest/verbs/BehaveWord;)V
    flags: (0x0401) ACC_PUBLIC, ACC_ABSTRACT
    MethodParameters:
      Name                           Flags
      x$1                            final

  public abstract void org$scalatest$funspec$PathAnyFunSpecLike$_setter_$styleName_$eq(java.lang.String);
    descriptor: (Ljava/lang/String;)V
    flags: (0x0401) ACC_PUBLIC, ACC_ABSTRACT
    MethodParameters:
      Name                           Flags
      x$1                            final

  public abstract int org$scalatest$funspec$PathAnyFunSpecLike$$super$expectedTestCount(org.scalatest.Filter);
    descriptor: (Lorg/scalatest/Filter;)I
    flags: (0x1401) ACC_PUBLIC, ACC_ABSTRACT, ACC_SYNTHETIC
    MethodParameters:
      Name                           Flags
      filter                         final

  public abstract org.scalatest.PathEngine org$scalatest$funspec$PathAnyFunSpecLike$$engine();
    descriptor: ()Lorg/scalatest/PathEngine;
    flags: (0x0401) ACC_PUBLIC, ACC_ABSTRACT

  public static org.scalatest.funspec.PathAnyFunSpecLike newInstance$(org.scalatest.funspec.PathAnyFunSpecLike);
    descriptor: (Lorg/scalatest/funspec/PathAnyFunSpecLike;)Lorg/scalatest/funspec/PathAnyFunSpecLike;
    flags: (0x1009) ACC_PUBLIC, ACC_STATIC, ACC_SYNTHETIC
    Code:
      stack=1, locals=1, args_size=1
         0: aload_0
         1: invokespecial #65                 // InterfaceMethod newInstance:()Lorg/scalatest/funspec/PathAnyFunSpecLike;
         4: areturn
      LineNumberTable:
        line 56: 0
      LocalVariableTable:
        Start  Length  Slot  Name   Signature
            0       5     0 $this   Lorg/scalatest/funspec/PathAnyFunSpecLike;
    MethodParameters:
      Name                           Flags
      $this                          final synthetic

  public default org.scalatest.funspec.PathAnyFunSpecLike newInstance();
    descriptor: ()Lorg/scalatest/funspec/PathAnyFunSpecLike;
    flags: (0x0001) ACC_PUBLIC
    Code:
      stack=1, locals=1, args_size=1
         0: aload_0
         1: invokevirtual #70                 // Method java/lang/Object.getClass:()Ljava/lang/Class;
         4: invokevirtual #75                 // Method java/lang/Class.newInstance:()Ljava/lang/Object;
         7: checkcast     #2                  // class org/scalatest/funspec/PathAnyFunSpecLike
        10: areturn
      LineNumberTable:
        line 56: 0
      LocalVariableTable:
        Start  Length  Slot  Name   Signature
            0      11     0  this   Lorg/scalatest/funspec/PathAnyFunSpecLike;

  public static org.scalatest.Informer info$(org.scalatest.funspec.PathAnyFunSpecLike);
    descriptor: (Lorg/scalatest/funspec/PathAnyFunSpecLike;)Lorg/scalatest/Informer;
    flags: (0x1009) ACC_PUBLIC, ACC_STATIC, ACC_SYNTHETIC
    Code:
      stack=1, locals=1, args_size=1
         0: aload_0
         1: invokespecial #82                 // InterfaceMethod info:()Lorg/scalatest/Informer;
         4: areturn
      LineNumberTable:
        line 69: 0
      LocalVariableTable:
        Start  Length  Slot  Name   Signature
            0       5     0 $this   Lorg/scalatest/funspec/PathAnyFunSpecLike;
    MethodParameters:
      Name                           Flags
      $this                          final synthetic

  public default org.scalatest.Informer info();
    descriptor: ()Lorg/scalatest/Informer;
    flags: (0x0001) ACC_PUBLIC
    Code:
      stack=1, locals=1, args_size=1
         0: aload_0
         1: invokeinterface #84,  1           // InterfaceMethod org$scalatest$funspec$PathAnyFunSpecLike$$engine:()Lorg/scalatest/PathEngine;
         6: invokevirtual #90                 // Method org/scalatest/PathEngine.atomicInformer:()Ljava/util/concurrent/atomic/AtomicReference;
         9: invokevirtual #95                 // Method java/util/concurrent/atomic/AtomicReference.get:()Ljava/lang/Object;
        12: checkcast     #97                 // class org/scalatest/Informer
        15: areturn
      LineNumberTable:
        line 69: 0
      LocalVariableTable:
        Start  Length  Slot  Name   Signature
            0      16     0  this   Lorg/scalatest/funspec/PathAnyFunSpecLike;

  public static org.scalatest.Notifier note$(org.scalatest.funspec.PathAnyFunSpecLike);
    descriptor: (Lorg/scalatest/funspec/PathAnyFunSpecLike;)Lorg/scalatest/Notifier;
    flags: (0x1009) ACC_PUBLIC, ACC_STATIC, ACC_SYNTHETIC
    Code:
      stack=1, locals=1, args_size=1
         0: aload_0
         1: invokespecial #103                // InterfaceMethod note:()Lorg/scalatest/Notifier;
         4: areturn
      LineNumberTable:
        line 79: 0
      LocalVariableTable:
        Start  Length  Slot  Name   Signature
            0       5     0 $this   Lorg/scalatest/funspec/PathAnyFunSpecLike;
    MethodParameters:
      Name                           Flags
      $this                          final synthetic

  public default org.scalatest.Notifier note();
    descriptor: ()Lorg/scalatest/Notifier;
    flags: (0x0001) ACC_PUBLIC
    Code:
      stack=1, locals=1, args_size=1
         0: aload_0
         1: invokeinterface #84,  1           // InterfaceMethod org$scalatest$funspec$PathAnyFunSpecLike$$engine:()Lorg/scalatest/PathEngine;
         6: invokevirtual #106                // Method org/scalatest/PathEngine.atomicNotifier:()Ljava/util/concurrent/atomic/AtomicReference;
         9: invokevirtual #95                 // Method java/util/concurrent/atomic/AtomicReference.get:()Ljava/lang/Object;
        12: checkcast     #108                // class org/scalatest/Notifier
        15: areturn
      LineNumberTable:
        line 79: 0
      LocalVariableTable:
        Start  Length  Slot  Name   Signature
            0      16     0  this   Lorg/scalatest/funspec/PathAnyFunSpecLike;

  public static org.scalatest.Alerter alert$(org.scalatest.funspec.PathAnyFunSpecLike);
    descriptor: (Lorg/scalatest/funspec/PathAnyFunSpecLike;)Lorg/scalatest/Alerter;
    flags: (0x1009) ACC_PUBLIC, ACC_STATIC, ACC_SYNTHETIC
    Code:
      stack=1, locals=1, args_size=1
         0: aload_0
         1: invokespecial #114                // InterfaceMethod alert:()Lorg/scalatest/Alerter;
         4: areturn
      LineNumberTable:
        line 89: 0
      LocalVariableTable:
        Start  Length  Slot  Name   Signature
            0       5     0 $this   Lorg/scalatest/funspec/PathAnyFunSpecLike;
    MethodParameters:
      Name                           Flags
      $this                          final synthetic

  public default org.scalatest.Alerter alert();
    descriptor: ()Lorg/scalatest/Alerter;
    flags: (0x0001) ACC_PUBLIC
    Code:
      stack=1, locals=1, args_size=1
         0: aload_0
         1: invokeinterface #84,  1           // InterfaceMethod org$scalatest$funspec$PathAnyFunSpecLike$$engine:()Lorg/scalatest/PathEngine;
         6: invokevirtual #117                // Method org/scalatest/PathEngine.atomicAlerter:()Ljava/util/concurrent/atomic/AtomicReference;
         9: invokevirtual #95                 // Method java/util/concurrent/atomic/AtomicReference.get:()Ljava/lang/Object;
        12: checkcast     #119                // class org/scalatest/Alerter
        15: areturn
      LineNumberTable:
        line 89: 0
      LocalVariableTable:
        Start  Length  Slot  Name   Signature
            0      16     0  this   Lorg/scalatest/funspec/PathAnyFunSpecLike;

  public static org.scalatest.Documenter markup$(org.scalatest.funspec.PathAnyFunSpecLike);
    descriptor: (Lorg/scalatest/funspec/PathAnyFunSpecLike;)Lorg/scalatest/Documenter;
    flags: (0x1009) ACC_PUBLIC, ACC_STATIC, ACC_SYNTHETIC
    Code:
      stack=1, locals=1, args_size=1
         0: aload_0
         1: invokespecial #125                // InterfaceMethod markup:()Lorg/scalatest/Documenter;
         4: areturn
      LineNumberTable:
        line 100: 0
      LocalVariableTable:
        Start  Length  Slot  Name   Signature
            0       5     0 $this   Lorg/scalatest/funspec/PathAnyFunSpecLike;
    MethodParameters:
      Name                           Flags
      $this                          final synthetic

  public default org.scalatest.Documenter markup();
    descriptor: ()Lorg/scalatest/Documenter;
    flags: (0x0001) ACC_PUBLIC
    Code:
      stack=1, locals=1, args_size=1
         0: aload_0
         1: invokeinterface #84,  1           // InterfaceMethod org$scalatest$funspec$PathAnyFunSpecLike$$engine:()Lorg/scalatest/PathEngine;
         6: invokevirtual #128                // Method org/scalatest/PathEngine.atomicDocumenter:()Ljava/util/concurrent/atomic/AtomicReference;
         9: invokevirtual #95                 // Method java/util/concurrent/atomic/AtomicReference.get:()Ljava/lang/Object;
        12: checkcast     #130                // class org/scalatest/Documenter
        15: areturn
      LineNumberTable:
        line 100: 0
      LocalVariableTable:
        Start  Length  Slot  Name   Signature
            0      16     0  this   Lorg/scalatest/funspec/PathAnyFunSpecLike;

  public abstract org.scalatest.funspec.PathAnyFunSpecLike$ItWord it();
    descriptor: ()Lorg/scalatest/funspec/PathAnyFunSpecLike$ItWord;
    flags: (0x0401) ACC_PUBLIC, ACC_ABSTRACT

  public abstract org.scalatest.funspec.PathAnyFunSpecLike$TheyWord they();
    descriptor: ()Lorg/scalatest/funspec/PathAnyFunSpecLike$TheyWord;
    flags: (0x0401) ACC_PUBLIC, ACC_ABSTRACT

  private void ignoreImpl(java.lang.String, scala.collection.immutable.Seq<org.scalatest.Tag>, scala.Function0<scala.runtime.BoxedUnit>, org.scalactic.source.Position);
    descriptor: (Ljava/lang/String;Lscala/collection/immutable/Seq;Lscala/Function0;Lorg/scalactic/source/Position;)V
    flags: (0x0002) ACC_PRIVATE
    Code:
      stack=12, locals=7, args_size=5
         0: iconst_4
         1: istore        5
         3: bipush        -2
         5: istore        6
         7: aload_0
         8: invokeinterface #84,  1           // InterfaceMethod org$scalatest$funspec$PathAnyFunSpecLike$$engine:()Lorg/scalatest/PathEngine;
        13: aload_1
        14: new           #143                // class org/scalatest/Transformer
        17: dup
        18: aload_3
        19: invokespecial #147                // Method org/scalatest/Transformer."<init>":(Lscala/Function0;)V
        22: invokedynamic #167,  0            // InvokeDynamic #0:apply:()Lscala/Function0;
        27: ldc           #168                // String PathAnyFunSpecLike.scala
        29: ldc           #170                // String ignore
        31: iload         5
        33: iload         6
        35: getstatic     #176                // Field scala/None$.MODULE$:Lscala/None$;
        38: new           #178                // class scala/Some
        41: dup
        42: aload         4
        44: invokespecial #181                // Method scala/Some."<init>":(Ljava/lang/Object;)V
        47: aload_2
        48: invokevirtual #185                // Method org/scalatest/PathEngine.handleIgnoredTest:(Ljava/lang/String;Lscala/Function0;Lscala/Function0;Ljava/lang/String;Ljava/lang/String;IILscala/Option;Lscala/Option;Lscala/collection/immutable/Seq;)V
        51: return
      LineNumberTable:
        line 352: 0
        line 353: 3
        line 358: 7
      LocalVariableTable:
        Start  Length  Slot  Name   Signature
            3      48     5 stackDepth   I
            7      44     6 stackDepthAdjustment   I
            0      52     0  this   Lorg/scalatest/funspec/PathAnyFunSpecLike;
            0      52     1 testText   Ljava/lang/String;
            0      52     2 testTags   Lscala/collection/immutable/Seq;
            0      52     3 testFun   Lscala/Function0;
            0      52     4   pos   Lorg/scalactic/source/Position;
    Signature: #137                         // (Ljava/lang/String;Lscala/collection/immutable/Seq<Lorg/scalatest/Tag;>;Lscala/Function0<Lscala/runtime/BoxedUnit;>;Lorg/scalactic/source/Position;)V
    MethodParameters:
      Name                           Flags
      testText                       final
      testTags                       final
      testFun                        final
      pos                            final

  public static void ignore$(org.scalatest.funspec.PathAnyFunSpecLike, java.lang.String, scala.collection.immutable.Seq, scala.Function0, org.scalactic.source.Position);
    descriptor: (Lorg/scalatest/funspec/PathAnyFunSpecLike;Ljava/lang/String;Lscala/collection/immutable/Seq;Lscala/Function0;Lorg/scalactic/source/Position;)V
    flags: (0x1009) ACC_PUBLIC, ACC_STATIC, ACC_SYNTHETIC
    Code:
      stack=5, locals=5, args_size=5
         0: aload_0
         1: aload_1
         2: aload_2
         3: aload_3
         4: aload         4
         6: invokespecial #196                // InterfaceMethod ignore:(Ljava/lang/String;Lscala/collection/immutable/Seq;Lscala/Function0;Lorg/scalactic/source/Position;)V
         9: return
      LineNumberTable:
        line 381: 0
      LocalVariableTable:
        Start  Length  Slot  Name   Signature
            0      10     0 $this   Lorg/scalatest/funspec/PathAnyFunSpecLike;
            0      10     1 testText   Ljava/lang/String;
            0      10     2 testTags   Lscala/collection/immutable/Seq;
            0      10     3 testFun   Lscala/Function0;
            0      10     4   pos   Lorg/scalactic/source/Position;
    MethodParameters:
      Name                           Flags
      $this                          final synthetic
      testText                       final
      testTags                       final
      testFun                        final
      pos                            final

  public default void ignore(java.lang.String, scala.collection.immutable.Seq<org.scalatest.Tag>, scala.Function0<scala.runtime.BoxedUnit>, org.scalactic.source.Position);
    descriptor: (Ljava/lang/String;Lscala/collection/immutable/Seq;Lscala/Function0;Lorg/scalactic/source/Position;)V
    flags: (0x0001) ACC_PUBLIC
    Code:
      stack=5, locals=5, args_size=5
         0: aload_0
         1: aload_1
         2: aload_2
         3: aload_3
         4: aload         4
         6: invokespecial #198                // InterfaceMethod ignoreImpl:(Ljava/lang/String;Lscala/collection/immutable/Seq;Lscala/Function0;Lorg/scalactic/source/Position;)V
         9: return
      LineNumberTable:
        line 382: 0
      LocalVariableTable:
        Start  Length  Slot  Name   Signature
            0      10     0  this   Lorg/scalatest/funspec/PathAnyFunSpecLike;
            0      10     1 testText   Ljava/lang/String;
            0      10     2 testTags   Lscala/collection/immutable/Seq;
            0      10     3 testFun   Lscala/Function0;
            0      10     4   pos   Lorg/scalactic/source/Position;
    Signature: #137                         // (Ljava/lang/String;Lscala/collection/immutable/Seq<Lorg/scalatest/Tag;>;Lscala/Function0<Lscala/runtime/BoxedUnit;>;Lorg/scalactic/source/Position;)V
    MethodParameters:
      Name                           Flags
      testText                       final
      testTags                       final
      testFun                        final
      pos                            final

  private void describeImpl(java.lang.String, scala.Function0<scala.runtime.BoxedUnit>, org.scalactic.source.Position);
    descriptor: (Ljava/lang/String;Lscala/Function0;Lorg/scalactic/source/Position;)V
    flags: (0x0002) ACC_PRIVATE
    Code:
      stack=13, locals=13, args_size=4
         0: iconst_4
         1: istore        5
         3: aload_0
         4: invokeinterface #84,  1           // InterfaceMethod org$scalatest$funspec$PathAnyFunSpecLike$$engine:()Lorg/scalatest/PathEngine;
         9: aload_1
        10: getstatic     #176                // Field scala/None$.MODULE$:Lscala/None$;
        13: aload_2
        14: invokedynamic #210,  0            // InvokeDynamic #1:apply:()Lscala/Function0;
        19: ldc           #168                // String PathAnyFunSpecLike.scala
        21: ldc           #212                // String describe
        23: iload         5
        25: bipush        -2
        27: getstatic     #176                // Field scala/None$.MODULE$:Lscala/None$;
        30: new           #178                // class scala/Some
        33: dup
        34: aload_3
        35: invokespecial #181                // Method scala/Some."<init>":(Ljava/lang/Object;)V
        38: invokevirtual #216                // Method org/scalatest/PathEngine.handleNestedBranch:(Ljava/lang/String;Lscala/Option;Lscala/Function0;Lscala/Function0;Ljava/lang/String;Ljava/lang/String;IILscala/Option;Lscala/Option;)V
        41: goto          344
        44: astore        6
        46: aload         6
        48: astore        7
        50: aload         7
        52: instanceof    #218                // class org/scalatest/exceptions/TestFailedException
        55: ifeq          105
        58: aload         7
        60: checkcast     #218                // class org/scalatest/exceptions/TestFailedException
        63: astore        8
        65: new           #220                // class org/scalatest/exceptions/NotAllowedException
        68: dup
        69: getstatic     #225                // Field org/scalatest/FailureMessages$.MODULE$:Lorg/scalatest/FailureMessages$;
        72: invokevirtual #228                // Method org/scalatest/FailureMessages$.assertionShouldBePutInsideItOrTheyClauseNotDescribeClause:()Ljava/lang/String;
        75: new           #178                // class scala/Some
        78: dup
        79: aload         8
        81: invokespecial #181                // Method scala/Some."<init>":(Ljava/lang/Object;)V
        84: aload         8
        86: invokevirtual #232                // Method org/scalatest/exceptions/TestFailedException.position:()Lscala/Option;
        89: aload_3
        90: invokedynamic #242,  0            // InvokeDynamic #2:apply:(Lorg/scalactic/source/Position;)Lscala/Function0;
        95: invokevirtual #248                // Method scala/Option.getOrElse:(Lscala/Function0;)Ljava/lang/Object;
        98: checkcast     #250                // class org/scalactic/source/Position
       101: invokespecial #253                // Method org/scalatest/exceptions/NotAllowedException."<init>":(Ljava/lang/String;Lscala/Option;Lorg/scalactic/source/Position;)V
       104: athrow
       105: goto          108
       108: aload         7
       110: instanceof    #255                // class org/scalatest/exceptions/TestCanceledException
       113: ifeq          163
       116: aload         7
       118: checkcast     #255                // class org/scalatest/exceptions/TestCanceledException
       121: astore        9
       123: new           #220                // class org/scalatest/exceptions/NotAllowedException
       126: dup
       127: getstatic     #225                // Field org/scalatest/FailureMessages$.MODULE$:Lorg/scalatest/FailureMessages$;
       130: invokevirtual #228                // Method org/scalatest/FailureMessages$.assertionShouldBePutInsideItOrTheyClauseNotDescribeClause:()Ljava/lang/String;
       133: new           #178                // class scala/Some
       136: dup
       137: aload         9
       139: invokespecial #181                // Method scala/Some."<init>":(Ljava/lang/Object;)V
       142: aload         9
       144: invokevirtual #256                // Method org/scalatest/exceptions/TestCanceledException.position:()Lscala/Option;
       147: aload_3
       148: invokedynamic #261,  0            // InvokeDynamic #3:apply:(Lorg/scalactic/source/Position;)Lscala/Function0;
       153: invokevirtual #248                // Method scala/Option.getOrElse:(Lscala/Function0;)Ljava/lang/Object;
       156: checkcast     #250                // class org/scalactic/source/Position
       159: invokespecial #253                // Method org/scalatest/exceptions/NotAllowedException."<init>":(Ljava/lang/String;Lscala/Option;Lorg/scalactic/source/Position;)V
       162: athrow
       163: goto          166
       166: aload         7
       168: instanceof    #263                // class org/scalatest/exceptions/DuplicateTestNameException
       171: ifeq          247
       174: aload         7
       176: checkcast     #263                // class org/scalatest/exceptions/DuplicateTestNameException
       179: astore        10
       181: new           #220                // class org/scalatest/exceptions/NotAllowedException
       184: dup
       185: getstatic     #225                // Field org/scalatest/FailureMessages$.MODULE$:Lorg/scalatest/FailureMessages$;
       188: getstatic     #268                // Field org/scalactic/Prettifier$.MODULE$:Lorg/scalactic/Prettifier$;
       191: invokevirtual #272                // Method org/scalactic/Prettifier$.default:()Lorg/scalactic/Prettifier;
       194: getstatic     #277                // Field org/scalatest/UnquotedString$.MODULE$:Lorg/scalatest/UnquotedString$;
       197: aload         10
       199: invokevirtual #278                // Method org/scalatest/exceptions/DuplicateTestNameException.getClass:()Ljava/lang/Class;
       202: invokevirtual #281                // Method java/lang/Class.getName:()Ljava/lang/String;
       205: invokevirtual #284                // Method org/scalatest/UnquotedString$.apply:(Ljava/lang/String;)Lorg/scalatest/UnquotedString;
       208: aload_1
       209: aload         10
       211: invokevirtual #287                // Method org/scalatest/exceptions/DuplicateTestNameException.getMessage:()Ljava/lang/String;
       214: invokevirtual #291                // Method org/scalatest/FailureMessages$.exceptionWasThrownInDescribeClause:(Lorg/scalactic/Prettifier;Ljava/lang/Object;Ljava/lang/Object;Ljava/lang/Object;)Ljava/lang/String;
       217: new           #178                // class scala/Some
       220: dup
       221: aload         10
       223: invokespecial #181                // Method scala/Some."<init>":(Ljava/lang/Object;)V
       226: aload         10
       228: invokevirtual #292                // Method org/scalatest/exceptions/DuplicateTestNameException.position:()Lscala/Option;
       231: aload_3
       232: invokedynamic #297,  0            // InvokeDynamic #4:apply:(Lorg/scalactic/source/Position;)Lscala/Function0;
       237: invokevirtual #248                // Method scala/Option.getOrElse:(Lscala/Function0;)Ljava/lang/Object;
       240: checkcast     #250                // class org/scalactic/source/Position
       243: invokespecial #253                // Method org/scalatest/exceptions/NotAllowedException."<init>":(Ljava/lang/String;Lscala/Option;Lorg/scalactic/source/Position;)V
       246: athrow
       247: goto          250
       250: aload         7
       252: ifnull        323
       255: aload         7
       257: astore        11
       259: getstatic     #302                // Field org/scalatest/Suite$.MODULE$:Lorg/scalatest/Suite$;
       262: aload         11
       264: invokevirtual #306                // Method org/scalatest/Suite$.anExceptionThatShouldCauseAnAbort:(Ljava/lang/Throwable;)Z
       267: ifne          320
       270: new           #220                // class org/scalatest/exceptions/NotAllowedException
       273: dup
       274: getstatic     #225                // Field org/scalatest/FailureMessages$.MODULE$:Lorg/scalatest/FailureMessages$;
       277: getstatic     #268                // Field org/scalactic/Prettifier$.MODULE$:Lorg/scalactic/Prettifier$;
       280: invokevirtual #272                // Method org/scalactic/Prettifier$.default:()Lorg/scalactic/Prettifier;
       283: getstatic     #277                // Field org/scalatest/UnquotedString$.MODULE$:Lorg/scalatest/UnquotedString$;
       286: aload         11
       288: invokevirtual #307                // Method java/lang/Throwable.getClass:()Ljava/lang/Class;
       291: invokevirtual #281                // Method java/lang/Class.getName:()Ljava/lang/String;
       294: invokevirtual #284                // Method org/scalatest/UnquotedString$.apply:(Ljava/lang/String;)Lorg/scalatest/UnquotedString;
       297: aload_1
       298: aload         11
       300: invokevirtual #308                // Method java/lang/Throwable.getMessage:()Ljava/lang/String;
       303: invokevirtual #291                // Method org/scalatest/FailureMessages$.exceptionWasThrownInDescribeClause:(Lorg/scalactic/Prettifier;Ljava/lang/Object;Ljava/lang/Object;Ljava/lang/Object;)Ljava/lang/String;
       306: new           #178                // class scala/Some
       309: dup
       310: aload         11
       312: invokespecial #181                // Method scala/Some."<init>":(Ljava/lang/Object;)V
       315: aload_3
       316: invokespecial #253                // Method org/scalatest/exceptions/NotAllowedException."<init>":(Ljava/lang/String;Lscala/Option;Lorg/scalactic/source/Position;)V
       319: athrow
       320: goto          326
       323: goto          326
       326: aload         7
       328: ifnull        338
       331: aload         7
       333: astore        12
       335: aload         12
       337: athrow
       338: goto          341
       341: aload         6
       343: athrow
       344: return
      Exception table:
         from    to  target type
             3    41    44   Class java/lang/Throwable
      StackMapTable: number_of_entries = 13
        frame_type = 255 /* full_frame */
          offset_delta = 44
          locals = [ class org/scalatest/funspec/PathAnyFunSpecLike, class java/lang/String, class scala/Function0, class org/scalactic/source/Position, top, int ]
          stack = [ class java/lang/Throwable ]
        frame_type = 253 /* append */
          offset_delta = 60
          locals = [ class java/lang/Throwable, class java/lang/Throwable ]
        frame_type = 2 /* same */
        frame_type = 54 /* same */
        frame_type = 2 /* same */
        frame_type = 251 /* same_frame_extended */
          offset_delta = 80
        frame_type = 2 /* same */
        frame_type = 255 /* full_frame */
          offset_delta = 69
          locals = [ class org/scalatest/funspec/PathAnyFunSpecLike, class java/lang/String, class scala/Function0, class org/scalactic/source/Position, top, int, class java/lang/Throwable, class java/lang/Throwable, top, top, top, class java/lang/Throwable ]
          stack = []
        frame_type = 255 /* full_frame */
          offset_delta = 2
          locals = [ class org/scalatest/funspec/PathAnyFunSpecLike, class java/lang/String, class scala/Function0, class org/scalactic/source/Position, top, int, class java/lang/Throwable, class java/lang/Throwable ]
          stack = []
        frame_type = 2 /* same */
        frame_type = 11 /* same */
        frame_type = 2 /* same */
        frame_type = 249 /* chop */
          offset_delta = 2
      LineNumberTable:
        line 391: 0
        line 396: 3
        line 399: 46
        line 399: 50
        line 400: 108
        line 401: 166
        line 402: 250
        line 403: 326
        line 395: 341
      LocalVariableTable:
        Start  Length  Slot  Name   Signature
            3     341     5 stackDepth   I
            0     345     0  this   Lorg/scalatest/funspec/PathAnyFunSpecLike;
            0     345     1 description   Ljava/lang/String;
            0     345     2   fun   Lscala/Function0;
            0     345     3   pos   Lorg/scalactic/source/Position;
    Signature: #201                         // (Ljava/lang/String;Lscala/Function0<Lscala/runtime/BoxedUnit;>;Lorg/scalactic/source/Position;)V
    MethodParameters:
      Name                           Flags
      description                    final
      fun                            final
      pos                            final

  public static void describe$(org.scalatest.funspec.PathAnyFunSpecLike, java.lang.String, scala.Function0, org.scalactic.source.Position);
    descriptor: (Lorg/scalatest/funspec/PathAnyFunSpecLike;Ljava/lang/String;Lscala/Function0;Lorg/scalactic/source/Position;)V
    flags: (0x1009) ACC_PUBLIC, ACC_STATIC, ACC_SYNTHETIC
    Code:
      stack=4, locals=4, args_size=4
         0: aload_0
         1: aload_1
         2: aload_2
         3: aload_3
         4: invokespecial #316                // InterfaceMethod describe:(Ljava/lang/String;Lscala/Function0;Lorg/scalactic/source/Position;)V
         7: return
      LineNumberTable:
        line 421: 0
      LocalVariableTable:
        Start  Length  Slot  Name   Signature
            0       8     0 $this   Lorg/scalatest/funspec/PathAnyFunSpecLike;
            0       8     1 description   Ljava/lang/String;
            0       8     2   fun   Lscala/Function0;
            0       8     3   pos   Lorg/scalactic/source/Position;
    MethodParameters:
      Name                           Flags
      $this                          final synthetic
      description                    final
      fun                            final
      pos                            final

  public default void describe(java.lang.String, scala.Function0<scala.runtime.BoxedUnit>, org.scalactic.source.Position);
    descriptor: (Ljava/lang/String;Lscala/Function0;Lorg/scalactic/source/Position;)V
    flags: (0x0001) ACC_PUBLIC
    Code:
      stack=4, locals=4, args_size=4
         0: aload_0
         1: aload_1
         2: aload_2
         3: aload_3
         4: invokespecial #318                // InterfaceMethod describeImpl:(Ljava/lang/String;Lscala/Function0;Lorg/scalactic/source/Position;)V
         7: return
      LineNumberTable:
        line 422: 0
      LocalVariableTable:
        Start  Length  Slot  Name   Signature
            0       8     0  this   Lorg/scalatest/funspec/PathAnyFunSpecLike;
            0       8     1 description   Ljava/lang/String;
            0       8     2   fun   Lscala/Function0;
            0       8     3   pos   Lorg/scalactic/source/Position;
    Signature: #201                         // (Ljava/lang/String;Lscala/Function0<Lscala/runtime/BoxedUnit;>;Lorg/scalactic/source/Position;)V
    MethodParameters:
      Name                           Flags
      description                    final
      fun                            final
      pos                            final

  public abstract org.scalatest.verbs.BehaveWord behave();
    descriptor: ()Lorg/scalatest/verbs/BehaveWord;
    flags: (0x0401) ACC_PUBLIC, ACC_ABSTRACT

  public static scala.collection.immutable.Set testNames$(org.scalatest.funspec.PathAnyFunSpecLike);
    descriptor: (Lorg/scalatest/funspec/PathAnyFunSpecLike;)Lscala/collection/immutable/Set;
    flags: (0x1009) ACC_PUBLIC, ACC_STATIC, ACC_SYNTHETIC
    Code:
      stack=1, locals=1, args_size=1
         0: aload_0
         1: invokespecial #326                // InterfaceMethod testNames:()Lscala/collection/immutable/Set;
         4: areturn
      LineNumberTable:
        line 496: 0
      LocalVariableTable:
        Start  Length  Slot  Name   Signature
            0       5     0 $this   Lorg/scalatest/funspec/PathAnyFunSpecLike;
    MethodParameters:
      Name                           Flags
      $this                          final synthetic

  public default scala.collection.immutable.Set<java.lang.String> testNames();
    descriptor: ()Lscala/collection/immutable/Set;
    flags: (0x0001) ACC_PUBLIC
    Code:
      stack=2, locals=1, args_size=1
         0: aload_0
         1: invokeinterface #84,  1           // InterfaceMethod org$scalatest$funspec$PathAnyFunSpecLike$$engine:()Lorg/scalatest/PathEngine;
         6: aload_0
         7: invokevirtual #331                // Method org/scalatest/PathEngine.ensureTestResultsRegistered:(Lorg/scalatest/Suite;)V
        10: getstatic     #336                // Field org/scalatest/InsertionOrderSet$.MODULE$:Lorg/scalatest/InsertionOrderSet$;
        13: aload_0
        14: invokeinterface #84,  1           // InterfaceMethod org$scalatest$funspec$PathAnyFunSpecLike$$engine:()Lorg/scalatest/PathEngine;
        19: invokevirtual #339                // Method org/scalatest/PathEngine.atomic:()Ljava/util/concurrent/atomic/AtomicReference;
        22: invokevirtual #95                 // Method java/util/concurrent/atomic/AtomicReference.get:()Ljava/lang/Object;
        25: checkcast     #30                 // class org/scalatest/SuperEngine$Bundle
        28: invokevirtual #343                // Method org/scalatest/SuperEngine$Bundle.testNamesList:()Lscala/collection/immutable/List;
        31: invokevirtual #346                // Method org/scalatest/InsertionOrderSet$.apply:(Lscala/collection/immutable/List;)Lscala/collection/immutable/Set;
        34: areturn
      LineNumberTable:
        line 497: 0
        line 498: 10
      LocalVariableTable:
        Start  Length  Slot  Name   Signature
            0      35     0  this   Lorg/scalatest/funspec/PathAnyFunSpecLike;
    Signature: #327                         // ()Lscala/collection/immutable/Set<Ljava/lang/String;>;

  public static int expectedTestCount$(org.scalatest.funspec.PathAnyFunSpecLike, org.scalatest.Filter);
    descriptor: (Lorg/scalatest/funspec/PathAnyFunSpecLike;Lorg/scalatest/Filter;)I
    flags: (0x1009) ACC_PUBLIC, ACC_STATIC, ACC_SYNTHETIC
    Code:
      stack=2, locals=2, args_size=2
         0: aload_0
         1: aload_1
         2: invokespecial #351                // InterfaceMethod expectedTestCount:(Lorg/scalatest/Filter;)I
         5: ireturn
      LineNumberTable:
        line 523: 0
      LocalVariableTable:
        Start  Length  Slot  Name   Signature
            0       6     0 $this   Lorg/scalatest/funspec/PathAnyFunSpecLike;
            0       6     1 filter   Lorg/scalatest/Filter;
    MethodParameters:
      Name                           Flags
      $this                          final synthetic
      filter                         final

  public default int expectedTestCount(org.scalatest.Filter);
    descriptor: (Lorg/scalatest/Filter;)I
    flags: (0x0001) ACC_PUBLIC
    Code:
      stack=2, locals=2, args_size=2
         0: aload_0
         1: invokeinterface #84,  1           // InterfaceMethod org$scalatest$funspec$PathAnyFunSpecLike$$engine:()Lorg/scalatest/PathEngine;
         6: aload_0
         7: invokevirtual #331                // Method org/scalatest/PathEngine.ensureTestResultsRegistered:(Lorg/scalatest/Suite;)V
        10: aload_0
        11: aload_1
        12: invokeinterface #354,  2          // InterfaceMethod org$scalatest$funspec$PathAnyFunSpecLike$$super$expectedTestCount:(Lorg/scalatest/Filter;)I
        17: ireturn
      LineNumberTable:
        line 524: 0
        line 525: 10
      LocalVariableTable:
        Start  Length  Slot  Name   Signature
            0      18     0  this   Lorg/scalatest/funspec/PathAnyFunSpecLike;
            0      18     1 filter   Lorg/scalatest/Filter;
    MethodParameters:
      Name                           Flags
      filter                         final

  public static org.scalatest.Status runTest$(org.scalatest.funspec.PathAnyFunSpecLike, java.lang.String, org.scalatest.Args);
    descriptor: (Lorg/scalatest/funspec/PathAnyFunSpecLike;Ljava/lang/String;Lorg/scalatest/Args;)Lorg/scalatest/Status;
    flags: (0x1009) ACC_PUBLIC, ACC_STATIC, ACC_SYNTHETIC
    Code:
      stack=3, locals=3, args_size=3
         0: aload_0
         1: aload_1
         2: aload_2
         3: invokespecial #362                // InterfaceMethod runTest:(Ljava/lang/String;Lorg/scalatest/Args;)Lorg/scalatest/Status;
         6: areturn
      LineNumberTable:
        line 555: 0
      LocalVariableTable:
        Start  Length  Slot  Name   Signature
            0       7     0 $this   Lorg/scalatest/funspec/PathAnyFunSpecLike;
            0       7     1 testName   Ljava/lang/String;
            0       7     2  args   Lorg/scalatest/Args;
    MethodParameters:
      Name                           Flags
      $this                          final synthetic
      testName                       final
      args                           final

  public default org.scalatest.Status runTest(java.lang.String, org.scalatest.Args);
    descriptor: (Ljava/lang/String;Lorg/scalatest/Args;)Lorg/scalatest/Status;
    flags: (0x0001) ACC_PUBLIC
    Code:
      stack=6, locals=3, args_size=3
         0: aload_0
         1: invokeinterface #84,  1           // InterfaceMethod org$scalatest$funspec$PathAnyFunSpecLike$$engine:()Lorg/scalatest/PathEngine;
         6: aload_0
         7: invokevirtual #331                // Method org/scalatest/PathEngine.ensureTestResultsRegistered:(Lorg/scalatest/Suite;)V
        10: aload_0
        11: invokeinterface #84,  1           // InterfaceMethod org$scalatest$funspec$PathAnyFunSpecLike$$engine:()Lorg/scalatest/PathEngine;
        16: aload_0
        17: aload_1
        18: aload_2
        19: iconst_1
        20: invokedynamic #374,  0            // InvokeDynamic #5:apply:()Lscala/Function1;
        25: invokevirtual #378                // Method org/scalatest/PathEngine.runTestImpl:(Lorg/scalatest/Suite;Ljava/lang/String;Lorg/scalatest/Args;ZLscala/Function1;)Lorg/scalatest/Status;
        28: areturn
      LineNumberTable:
        line 557: 0
        line 563: 10
      LocalVariableTable:
        Start  Length  Slot  Name   Signature
            0      29     0  this   Lorg/scalatest/funspec/PathAnyFunSpecLike;
            0      29     1 testName   Ljava/lang/String;
            0      29     2  args   Lorg/scalatest/Args;
    MethodParameters:
      Name                           Flags
      testName                       final
      args                           final

  public static scala.collection.immutable.Map tags$(org.scalatest.funspec.PathAnyFunSpecLike);
    descriptor: (Lorg/scalatest/funspec/PathAnyFunSpecLike;)Lscala/collection/immutable/Map;
    flags: (0x1009) ACC_PUBLIC, ACC_STATIC, ACC_SYNTHETIC
    Code:
      stack=1, locals=1, args_size=1
         0: aload_0
         1: invokespecial #384                // InterfaceMethod tags:()Lscala/collection/immutable/Map;
         4: areturn
      LineNumberTable:
        line 592: 0
      LocalVariableTable:
        Start  Length  Slot  Name   Signature
            0       5     0 $this   Lorg/scalatest/funspec/PathAnyFunSpecLike;
    MethodParameters:
      Name                           Flags
      $this                          final synthetic

  public default scala.collection.immutable.Map<java.lang.String, scala.collection.immutable.Set<java.lang.String>> tags();
    descriptor: ()Lscala/collection/immutable/Map;
    flags: (0x0001) ACC_PUBLIC
    Code:
      stack=3, locals=1, args_size=1
         0: aload_0
         1: invokeinterface #84,  1           // InterfaceMethod org$scalatest$funspec$PathAnyFunSpecLike$$engine:()Lorg/scalatest/PathEngine;
         6: aload_0
         7: invokevirtual #331                // Method org/scalatest/PathEngine.ensureTestResultsRegistered:(Lorg/scalatest/Suite;)V
        10: getstatic     #302                // Field org/scalatest/Suite$.MODULE$:Lorg/scalatest/Suite$;
        13: aload_0
        14: invokeinterface #84,  1           // InterfaceMethod org$scalatest$funspec$PathAnyFunSpecLike$$engine:()Lorg/scalatest/PathEngine;
        19: invokevirtual #339                // Method org/scalatest/PathEngine.atomic:()Ljava/util/concurrent/atomic/AtomicReference;
        22: invokevirtual #95                 // Method java/util/concurrent/atomic/AtomicReference.get:()Ljava/lang/Object;
        25: checkcast     #30                 // class org/scalatest/SuperEngine$Bundle
        28: invokevirtual #388                // Method org/scalatest/SuperEngine$Bundle.tagsMap:()Lscala/collection/immutable/Map;
        31: aload_0
        32: invokevirtual #392                // Method org/scalatest/Suite$.autoTagClassAnnotations:(Lscala/collection/immutable/Map;Lorg/scalatest/Suite;)Lscala/collection/immutable/Map;
        35: areturn
      LineNumberTable:
        line 593: 0
        line 594: 10
      LocalVariableTable:
        Start  Length  Slot  Name   Signature
            0      36     0  this   Lorg/scalatest/funspec/PathAnyFunSpecLike;
    Signature: #385                         // ()Lscala/collection/immutable/Map<Ljava/lang/String;Lscala/collection/immutable/Set<Ljava/lang/String;>;>;

  public static org.scalatest.Status run$(org.scalatest.funspec.PathAnyFunSpecLike, scala.Option, org.scalatest.Args);
    descriptor: (Lorg/scalatest/funspec/PathAnyFunSpecLike;Lscala/Option;Lorg/scalatest/Args;)Lorg/scalatest/Status;
    flags: (0x1009) ACC_PUBLIC, ACC_STATIC, ACC_SYNTHETIC
    Code:
      stack=3, locals=3, args_size=3
         0: aload_0
         1: aload_1
         2: aload_2
         3: invokespecial #398                // InterfaceMethod run:(Lscala/Option;Lorg/scalatest/Args;)Lorg/scalatest/Status;
         6: areturn
      LineNumberTable:
        line 627: 0
      LocalVariableTable:
        Start  Length  Slot  Name   Signature
            0       7     0 $this   Lorg/scalatest/funspec/PathAnyFunSpecLike;
            0       7     1 testName   Lscala/Option;
            0       7     2  args   Lorg/scalatest/Args;
    MethodParameters:
      Name                           Flags
      $this                          final synthetic
      testName                       final
      args                           final

  public default org.scalatest.Status run(scala.Option<java.lang.String>, org.scalatest.Args);
    descriptor: (Lscala/Option;Lorg/scalatest/Args;)Lorg/scalatest/Status;
    flags: (0x0001) ACC_PUBLIC
    Code:
      stack=7, locals=3, args_size=3
         0: aload_0
         1: invokeinterface #84,  1           // InterfaceMethod org$scalatest$funspec$PathAnyFunSpecLike$$engine:()Lorg/scalatest/PathEngine;
         6: aload_0
         7: invokevirtual #331                // Method org/scalatest/PathEngine.ensureTestResultsRegistered:(Lorg/scalatest/Suite;)V
        10: aload_0
        11: invokeinterface #84,  1           // InterfaceMethod org$scalatest$funspec$PathAnyFunSpecLike$$engine:()Lorg/scalatest/PathEngine;
        16: aload_0
        17: aload_1
        18: aload_2
        19: aload_0
        20: invokeinterface #82,  1           // InterfaceMethod info:()Lorg/scalatest/Informer;
        25: iconst_1
        26: aload_0
        27: invokedynamic #410,  0            // InvokeDynamic #6:apply:(Lorg/scalatest/funspec/PathAnyFunSpecLike;)Lscala/Function2;
        32: invokevirtual #414                // Method org/scalatest/PathEngine.runPathTestsImpl:(Lorg/scalatest/Suite;Lscala/Option;Lorg/scalatest/Args;Lorg/scalatest/Informer;ZLscala/Function2;)Lorg/scalatest/Status;
        35: areturn
      LineNumberTable:
        line 628: 0
        line 629: 10
      LocalVariableTable:
        Start  Length  Slot  Name   Signature
            0      36     0  this   Lorg/scalatest/funspec/PathAnyFunSpecLike;
            0      36     1 testName   Lscala/Option;
            0      36     2  args   Lorg/scalatest/Args;
    Signature: #400                         // (Lscala/Option<Ljava/lang/String;>;Lorg/scalatest/Args;)Lorg/scalatest/Status;
    MethodParameters:
      Name                           Flags
      testName                       final
      args                           final

  public static org.scalatest.Status runTests$(org.scalatest.funspec.PathAnyFunSpecLike, scala.Option, org.scalatest.Args);
    descriptor: (Lorg/scalatest/funspec/PathAnyFunSpecLike;Lscala/Option;Lorg/scalatest/Args;)Lorg/scalatest/Status;
    flags: (0x1009) ACC_PUBLIC, ACC_STATIC, ACC_SYNTHETIC
    Code:
      stack=3, locals=3, args_size=3
         0: aload_0
         1: aload_1
         2: aload_2
         3: invokespecial #418                // InterfaceMethod runTests:(Lscala/Option;Lorg/scalatest/Args;)Lorg/scalatest/Status;
         6: areturn
      LineNumberTable:
        line 641: 0
      LocalVariableTable:
        Start  Length  Slot  Name   Signature
            0       7     0 $this   Lorg/scalatest/funspec/PathAnyFunSpecLike;
            0       7     1 testName   Lscala/Option;
            0       7     2  args   Lorg/scalatest/Args;
    MethodParameters:
      Name                           Flags
      $this                          final synthetic
      testName                       final
      args                           final

  public default org.scalatest.Status runTests(scala.Option<java.lang.String>, org.scalatest.Args);
    descriptor: (Lscala/Option;Lorg/scalatest/Args;)Lorg/scalatest/Status;
    flags: (0x0001) ACC_PUBLIC
    Code:
      stack=2, locals=3, args_size=3
         0: new           #420                // class java/lang/UnsupportedOperationException
         3: dup
         4: invokespecial #423                // Method java/lang/UnsupportedOperationException."<init>":()V
         7: athrow
      LineNumberTable:
        line 642: 0
      LocalVariableTable:
        Start  Length  Slot  Name   Signature
            0       8     0  this   Lorg/scalatest/funspec/PathAnyFunSpecLike;
            0       8     1 testName   Lscala/Option;
            0       8     2  args   Lorg/scalatest/Args;
    Signature: #400                         // (Lscala/Option<Ljava/lang/String;>;Lorg/scalatest/Args;)Lorg/scalatest/Status;
    MethodParameters:
      Name                           Flags
      testName                       final
      args                           final

  public static org.scalatest.Status runNestedSuites$(org.scalatest.funspec.PathAnyFunSpecLike, org.scalatest.Args);
    descriptor: (Lorg/scalatest/funspec/PathAnyFunSpecLike;Lorg/scalatest/Args;)Lorg/scalatest/Status;
    flags: (0x1009) ACC_PUBLIC, ACC_STATIC, ACC_SYNTHETIC
    Code:
      stack=2, locals=2, args_size=2
         0: aload_0
         1: aload_1
         2: invokespecial #429                // InterfaceMethod runNestedSuites:(Lorg/scalatest/Args;)Lorg/scalatest/Status;
         5: areturn
      LineNumberTable:
        line 668: 0
      LocalVariableTable:
        Start  Length  Slot  Name   Signature
            0       6     0 $this   Lorg/scalatest/funspec/PathAnyFunSpecLike;
            0       6     1  args   Lorg/scalatest/Args;
    MethodParameters:
      Name                           Flags
      $this                          final synthetic
      args                           final

  public default org.scalatest.Status runNestedSuites(org.scalatest.Args);
    descriptor: (Lorg/scalatest/Args;)Lorg/scalatest/Status;
    flags: (0x0001) ACC_PUBLIC
    Code:
      stack=1, locals=2, args_size=2
         0: getstatic     #434                // Field org/scalatest/SucceededStatus$.MODULE$:Lorg/scalatest/SucceededStatus$;
         3: areturn
      LineNumberTable:
        line 668: 0
      LocalVariableTable:
        Start  Length  Slot  Name   Signature
            0       4     0  this   Lorg/scalatest/funspec/PathAnyFunSpecLike;
            0       4     1  args   Lorg/scalatest/Args;
    MethodParameters:
      Name                           Flags
      args                           final

  public static scala.collection.immutable.IndexedSeq nestedSuites$(org.scalatest.funspec.PathAnyFunSpecLike);
    descriptor: (Lorg/scalatest/funspec/PathAnyFunSpecLike;)Lscala/collection/immutable/IndexedSeq;
    flags: (0x1009) ACC_PUBLIC, ACC_STATIC, ACC_SYNTHETIC
    Code:
      stack=1, locals=1, args_size=1
         0: aload_0
         1: invokespecial #440                // InterfaceMethod nestedSuites:()Lscala/collection/immutable/IndexedSeq;
         4: areturn
      LineNumberTable:
        line 691: 0
      LocalVariableTable:
        Start  Length  Slot  Name   Signature
            0       5     0 $this   Lorg/scalatest/funspec/PathAnyFunSpecLike;
    MethodParameters:
      Name                           Flags
      $this                          final synthetic

  public default scala.collection.immutable.IndexedSeq<org.scalatest.Suite> nestedSuites();
    descriptor: ()Lscala/collection/immutable/IndexedSeq;
    flags: (0x0001) ACC_PUBLIC
    Code:
      stack=1, locals=1, args_size=1
         0: getstatic     #446                // Field scala/package$.MODULE$:Lscala/package$;
         3: invokevirtual #450                // Method scala/package$.Vector:()Lscala/collection/immutable/Vector$;
         6: invokevirtual #456                // Method scala/collection/immutable/Vector$.empty:()Lscala/collection/immutable/Vector;
         9: areturn
      LineNumberTable:
        line 691: 0
      LocalVariableTable:
        Start  Length  Slot  Name   Signature
            0      10     0  this   Lorg/scalatest/funspec/PathAnyFunSpecLike;
    Signature: #441                         // ()Lscala/collection/immutable/IndexedSeq<Lorg/scalatest/Suite;>;

  public abstract java.lang.String styleName();
    descriptor: ()Ljava/lang/String;
    flags: (0x0401) ACC_PUBLIC, ACC_ABSTRACT
    Deprecated: true

  public static org.scalatest.TestData testDataFor$(org.scalatest.funspec.PathAnyFunSpecLike, java.lang.String, org.scalatest.ConfigMap);
    descriptor: (Lorg/scalatest/funspec/PathAnyFunSpecLike;Ljava/lang/String;Lorg/scalatest/ConfigMap;)Lorg/scalatest/TestData;
    flags: (0x1009) ACC_PUBLIC, ACC_STATIC, ACC_SYNTHETIC
    Code:
      stack=3, locals=3, args_size=3
         0: aload_0
         1: aload_1
         2: aload_2
         3: invokespecial #464                // InterfaceMethod testDataFor:(Ljava/lang/String;Lorg/scalatest/ConfigMap;)Lorg/scalatest/TestData;
         6: areturn
      LineNumberTable:
        line 702: 0
      LocalVariableTable:
        Start  Length  Slot  Name   Signature
            0       7     0 $this   Lorg/scalatest/funspec/PathAnyFunSpecLike;
            0       7     1 testName   Ljava/lang/String;
            0       7     2 theConfigMap   Lorg/scalatest/ConfigMap;
    MethodParameters:
      Name                           Flags
      $this                          final synthetic
      testName                       final
      theConfigMap                   final

  public default org.scalatest.TestData testDataFor(java.lang.String, org.scalatest.ConfigMap);
    descriptor: (Ljava/lang/String;Lorg/scalatest/ConfigMap;)Lorg/scalatest/TestData;
    flags: (0x0001) ACC_PUBLIC
    Code:
      stack=4, locals=3, args_size=3
         0: aload_0
         1: invokeinterface #84,  1           // InterfaceMethod org$scalatest$funspec$PathAnyFunSpecLike$$engine:()Lorg/scalatest/PathEngine;
         6: aload_0
         7: invokevirtual #331                // Method org/scalatest/PathEngine.ensureTestResultsRegistered:(Lorg/scalatest/Suite;)V
        10: aload_0
        11: invokeinterface #84,  1           // InterfaceMethod org$scalatest$funspec$PathAnyFunSpecLike$$engine:()Lorg/scalatest/PathEngine;
        16: aload_1
        17: aload_2
        18: aload_0
        19: invokevirtual #469                // Method org/scalatest/PathEngine.createTestDataFor:(Ljava/lang/String;Lorg/scalatest/ConfigMap;Lorg/scalatest/Suite;)Lorg/scalatest/TestData;
        22: areturn
      LineNumberTable:
        line 703: 0
        line 704: 10
      LocalVariableTable:
        Start  Length  Slot  Name   Signature
            0      23     0  this   Lorg/scalatest/funspec/PathAnyFunSpecLike;
            0      23     1 testName   Ljava/lang/String;
            0      23     2 theConfigMap   Lorg/scalatest/ConfigMap;
    MethodParameters:
      Name                           Flags
      testName                       final
      theConfigMap                   final

  public static org.scalatest.ConfigMap testDataFor$default$2$(org.scalatest.funspec.PathAnyFunSpecLike);
    descriptor: (Lorg/scalatest/funspec/PathAnyFunSpecLike;)Lorg/scalatest/ConfigMap;
    flags: (0x1009) ACC_PUBLIC, ACC_STATIC, ACC_SYNTHETIC
    Code:
      stack=1, locals=1, args_size=1
         0: aload_0
         1: invokespecial #475                // InterfaceMethod testDataFor$default$2:()Lorg/scalatest/ConfigMap;
         4: areturn
      LineNumberTable:
        line 702: 0
      LocalVariableTable:
        Start  Length  Slot  Name   Signature
            0       5     0 $this   Lorg/scalatest/funspec/PathAnyFunSpecLike;
    MethodParameters:
      Name                           Flags
      $this                          final synthetic

  public default org.scalatest.ConfigMap testDataFor$default$2();
    descriptor: ()Lorg/scalatest/ConfigMap;
    flags: (0x0001) ACC_PUBLIC
    Code:
      stack=1, locals=1, args_size=1
         0: getstatic     #480                // Field org/scalatest/ConfigMap$.MODULE$:Lorg/scalatest/ConfigMap$;
         3: invokevirtual #482                // Method org/scalatest/ConfigMap$.empty:()Lorg/scalatest/ConfigMap;
         6: areturn
      LineNumberTable:
        line 702: 0
      LocalVariableTable:
        Start  Length  Slot  Name   Signature
            0       7     0  this   Lorg/scalatest/funspec/PathAnyFunSpecLike;

  public static java.lang.String $anonfun$ignoreImpl$1();
    descriptor: ()Ljava/lang/String;
    flags: (0x1009) ACC_PUBLIC, ACC_STATIC, ACC_SYNTHETIC
    Code:
      stack=1, locals=0, args_size=0
         0: getstatic     #487                // Field org/scalatest/Resources$.MODULE$:Lorg/scalatest/Resources$;
         3: invokevirtual #490                // Method org/scalatest/Resources$.ignoreCannotAppearInsideAnItOrAThey:()Ljava/lang/String;
         6: areturn
      LineNumberTable:
        line 358: 0

  public static java.lang.String $anonfun$describeImpl$1();
    descriptor: ()Ljava/lang/String;
    flags: (0x1009) ACC_PUBLIC, ACC_STATIC, ACC_SYNTHETIC
    Code:
      stack=1, locals=0, args_size=0
         0: getstatic     #487                // Field org/scalatest/Resources$.MODULE$:Lorg/scalatest/Resources$;
         3: invokevirtual #493                // Method org/scalatest/Resources$.describeCannotAppearInsideAnIt:()Ljava/lang/String;
         6: areturn
      LineNumberTable:
        line 396: 0

  public static org.scalactic.source.Position $anonfun$describeImpl$2(org.scalactic.source.Position);
    descriptor: (Lorg/scalactic/source/Position;)Lorg/scalactic/source/Position;
    flags: (0x1009) ACC_PUBLIC, ACC_STATIC, ACC_SYNTHETIC
    Code:
      stack=1, locals=1, args_size=1
         0: aload_0
         1: areturn
      LineNumberTable:
        line 399: 0
      LocalVariableTable:
        Start  Length  Slot  Name   Signature
            0       2     0 pos$1   Lorg/scalactic/source/Position;
    MethodParameters:
      Name                           Flags
      pos$1                          final

  public static org.scalactic.source.Position $anonfun$describeImpl$3(org.scalactic.source.Position);
    descriptor: (Lorg/scalactic/source/Position;)Lorg/scalactic/source/Position;
    flags: (0x1009) ACC_PUBLIC, ACC_STATIC, ACC_SYNTHETIC
    Code:
      stack=1, locals=1, args_size=1
         0: aload_0
         1: areturn
      LineNumberTable:
        line 400: 0
      LocalVariableTable:
        Start  Length  Slot  Name   Signature
            0       2     0 pos$1   Lorg/scalactic/source/Position;
    MethodParameters:
      Name                           Flags
      pos$1                          final

  public static org.scalactic.source.Position $anonfun$describeImpl$4(org.scalactic.source.Position);
    descriptor: (Lorg/scalactic/source/Position;)Lorg/scalactic/source/Position;
    flags: (0x1009) ACC_PUBLIC, ACC_STATIC, ACC_SYNTHETIC
    Code:
      stack=1, locals=1, args_size=1
         0: aload_0
         1: areturn
      LineNumberTable:
        line 401: 0
      LocalVariableTable:
        Start  Length  Slot  Name   Signature
            0       2     0 pos$1   Lorg/scalactic/source/Position;
    MethodParameters:
      Name                           Flags
      pos$1                          final

  private static org.scalatest.Outcome dontInvokeWithFixture$1(org.scalatest.SuperEngine$TestLeaf);
    descriptor: (Lorg/scalatest/SuperEngine$TestLeaf;)Lorg/scalatest/Outcome;
    flags: (0x000a) ACC_PRIVATE, ACC_STATIC
    Code:
      stack=1, locals=1, args_size=1
         0: aload_0
         1: invokevirtual #498                // Method org/scalatest/SuperEngine$TestLeaf.testFun:()Ljava/lang/Object;
         4: checkcast     #312                // class scala/Function0
         7: invokeinterface #500,  1          // InterfaceMethod scala/Function0.apply:()Ljava/lang/Object;
        12: checkcast     #502                // class org/scalatest/Outcome
        15: areturn
      LineNumberTable:
        line 560: 0
      LocalVariableTable:
        Start  Length  Slot  Name   Signature
            0      16     0 theTest   Lorg/scalatest/SuperEngine$TestLeaf;
    MethodParameters:
      Name                           Flags
      theTest                        final

  public static org.scalatest.Outcome $anonfun$runTest$1(org.scalatest.SuperEngine$TestLeaf);
    descriptor: (Lorg/scalatest/SuperEngine$TestLeaf;)Lorg/scalatest/Outcome;
    flags: (0x1009) ACC_PUBLIC, ACC_STATIC, ACC_SYNTHETIC
    Code:
      stack=1, locals=1, args_size=1
         0: aload_0
         1: invokestatic  #505                // InterfaceMethod dontInvokeWithFixture$1:(Lorg/scalatest/SuperEngine$TestLeaf;)Lorg/scalatest/Outcome;
         4: areturn
      LineNumberTable:
        line 563: 0
      LocalVariableTable:
        Start  Length  Slot  Name   Signature
            0       5     0 theTest   Lorg/scalatest/SuperEngine$TestLeaf;
    MethodParameters:
      Name                           Flags
      theTest                        final

  public static org.scalatest.Status $anonfun$run$1(org.scalatest.funspec.PathAnyFunSpecLike, java.lang.String, org.scalatest.Args);
    descriptor: (Lorg/scalatest/funspec/PathAnyFunSpecLike;Ljava/lang/String;Lorg/scalatest/Args;)Lorg/scalatest/Status;
    flags: (0x1009) ACC_PUBLIC, ACC_STATIC, ACC_SYNTHETIC
    Code:
      stack=3, locals=3, args_size=3
         0: aload_0
         1: aload_1
         2: aload_2
         3: invokeinterface #362,  3          // InterfaceMethod runTest:(Ljava/lang/String;Lorg/scalatest/Args;)Lorg/scalatest/Status;
         8: areturn
      LineNumberTable:
        line 629: 0
      LocalVariableTable:
        Start  Length  Slot  Name   Signature
            0       9     0 $this   Lorg/scalatest/funspec/PathAnyFunSpecLike;
            0       9     1 testName   Ljava/lang/String;
            0       9     2  args   Lorg/scalatest/Args;
    MethodParameters:
      Name                           Flags
      $this                          final synthetic
      testName                       final
      args                           final

  public static void $init$(org.scalatest.funspec.PathAnyFunSpecLike);
    descriptor: (Lorg/scalatest/funspec/PathAnyFunSpecLike;)V
    flags: (0x0009) ACC_PUBLIC, ACC_STATIC
    Code:
      stack=4, locals=1, args_size=1
         0: aload_0
         1: getstatic     #512                // Field org/scalatest/PathEngine$.MODULE$:Lorg/scalatest/PathEngine$;
         4: invokevirtual #515                // Method org/scalatest/PathEngine$.getEngine:()Lorg/scalatest/PathEngine;
         7: invokeinterface #517,  2          // InterfaceMethod org$scalatest$funspec$PathAnyFunSpecLike$_setter_$org$scalatest$funspec$PathAnyFunSpecLike$$engine_$eq:(Lorg/scalatest/PathEngine;)V
        12: aload_0
        13: new           #38                 // class org/scalatest/funspec/PathAnyFunSpecLike$ItWord
        16: dup
        17: aload_0
        18: invokespecial #519                // Method org/scalatest/funspec/PathAnyFunSpecLike$ItWord."<init>":(Lorg/scalatest/funspec/PathAnyFunSpecLike;)V
        21: invokeinterface #521,  2          // InterfaceMethod org$scalatest$funspec$PathAnyFunSpecLike$_setter_$it_$eq:(Lorg/scalatest/funspec/PathAnyFunSpecLike$ItWord;)V
        26: aload_0
        27: new           #41                 // class org/scalatest/funspec/PathAnyFunSpecLike$TheyWord
        30: dup
        31: aload_0
        32: invokespecial #522                // Method org/scalatest/funspec/PathAnyFunSpecLike$TheyWord."<init>":(Lorg/scalatest/funspec/PathAnyFunSpecLike;)V
        35: invokeinterface #524,  2          // InterfaceMethod org$scalatest$funspec$PathAnyFunSpecLike$_setter_$they_$eq:(Lorg/scalatest/funspec/PathAnyFunSpecLike$TheyWord;)V
        40: aload_0
        41: new           #526                // class org/scalatest/verbs/BehaveWord
        44: dup
        45: invokespecial #527                // Method org/scalatest/verbs/BehaveWord."<init>":()V
        48: invokeinterface #529,  2          // InterfaceMethod org$scalatest$funspec$PathAnyFunSpecLike$_setter_$behave_$eq:(Lorg/scalatest/verbs/BehaveWord;)V
        53: aload_0
        54: ldc_w         #531                // String org.scalatest.path.FunSpec
        57: invokeinterface #533,  2          // InterfaceMethod org$scalatest$funspec$PathAnyFunSpecLike$_setter_$styleName_$eq:(Ljava/lang/String;)V
        62: return
      LineNumberTable:
        line 52: 0
        line 227: 12
        line 348: 26
        line 447: 40
        line 700: 53
        line 50: 62
      LocalVariableTable:
        Start  Length  Slot  Name   Signature
            0      63     0 $this   Lorg/scalatest/funspec/PathAnyFunSpecLike;
    MethodParameters:
      Name                           Flags
      $this                          final synthetic

  private static java.lang.Object $deserializeLambda$(java.lang.invoke.SerializedLambda);
    descriptor: (Ljava/lang/invoke/SerializedLambda;)Ljava/lang/Object;
    flags: (0x100a) ACC_PRIVATE, ACC_STATIC, ACC_SYNTHETIC
    Code:
      stack=1, locals=1, args_size=1
         0: aload_0
         1: invokedynamic #545,  0            // InvokeDynamic #7:lambdaDeserialize:(Ljava/lang/invoke/SerializedLambda;)Ljava/lang/Object;
         6: areturn
}
InnerClasses:
  public static final #28= #25 of #27;    // Lookup=class java/lang/invoke/MethodHandles$Lookup of class java/lang/invoke/MethodHandles
  public #33= #30 of #32;                 // Bundle=class org/scalatest/SuperEngine$Bundle of class org/scalatest/SuperEngine
  public #36= #35 of #32;                 // TestLeaf=class org/scalatest/SuperEngine$TestLeaf of class org/scalatest/SuperEngine
  public #39= #38 of #2;                  // ItWord=class org/scalatest/funspec/PathAnyFunSpecLike$ItWord of class org/scalatest/funspec/PathAnyFunSpecLike
  public #42= #41 of #2;                  // TheyWord=class org/scalatest/funspec/PathAnyFunSpecLike$TheyWord of class org/scalatest/funspec/PathAnyFunSpecLike
SourceFile: "PathAnyFunSpecLike.scala"
RuntimeVisibleAnnotations:
  0: #18(#19=[s#20])
    org.scalatest.Finders(
      value=["org.scalatest.finders.FunSpecFinder"]
    )
  1: #21(#22=s#23)
    scala.reflect.ScalaSignature(
      bytes="\u0006\u0005\tmeaB\u0014)!\u0003\r\ta\f\u0005\u0006\u0013\u0002!\tA\u0013\u0005\b\u001d\u0002\u0011\r\u0011\"\u0004P\u0011\u0015\u0019\u0006\u0001\"\u0011U\u0011\u00159\u0006\u0001\"\u0005Y\u0011\u0015a\u0006\u0001\"\u0005^\u0011\u0015\t\u0007\u0001\"\u0005c\u0011\u00151\u0007\u0001\"\u0005h\r\u0011Y\u0007\u0001\u00037\t\u000b5DA\u0011\u00018\t\u000bEDAQ\u0002:\t\u000f\u0005E\u0002\u0002\"\u0001\u00024!9\u0011\u0011\t\u0005\u0005\u0002\u0005\r\u0003bBA+\u0011\u0011\u0005\u0011q\u000b\u0005\n\u00037\u0002!\u0019!C\t\u0003;2a!a\u0018\u0001\u0011\u0005\u0005\u0004BB7\u0010\t\u0003\t\u0019\u0007\u0003\u0004r\u001f\u0011%\u0011q\r\u0005\b\u0003cyA\u0011AA:\u0011\u001d\t\te\u0004C\u0001\u0003\u0003Cq!!\u0016\u0010\t\u0003\t)\tC\u0005\u0002\n\u0002\u0011\r\u0011\"\u0005\u0002\f\"9\u0011Q\u0012\u0001\u0005\u000e\u0005=\u0005bBAN\u0001\u0011E\u0011Q\u0014\u0005\b\u0003W\u0003AQBAW\u0011\u001d\tY\f\u0001C\t\u0003{C\u0011\"!3\u0001\u0005\u0004%\t\"a3\t\u000f\u00055\u0007\u0001\"\u0012\u0002P\"9\u0011q\u001b\u0001\u0005F\u0005e\u0007bBAv\u0001\u0011U\u0013Q\u001e\u0005\b\u0005\u0007\u0001AQ\tB\u0003\u0011\u001d\u0011i\u0001\u0001C#\u0005\u001fAqAa\u0007\u0001\t+\u0012i\u0002C\u0004\u0003$\u0001!)F!\n\t\u000f\t%\u0002\u0001\"\u0012\u0003,!I!Q\b\u0001C\u0002\u0013\u0015#q\b\u0005\b\u0005+\u0002A\u0011\tB,\u0011%\u0011Y\u0007AI\u0001\n\u0003\u0011i\u0007\u0003\b\u0003\u0004\u0002\u0001\n1!A\u0001\n\u0013\u0011)I!#\u0003%A\u000bG\u000f[!os\u001a+hn\u00159fG2K7.\u001a\u0006\u0003S)\nqAZ;ogB,7M\u0003\u0002,Y\u0005I1oY1mCR,7\u000f\u001e\u0006\u0002[\u0005\u0019qN]4\u0004\u0001MA\u0001\u0001\r\u001c;{\u0001\u001be\t\u0005\u00022i5\t!GC\u00014\u0003\u0015\u00198-\u00197b\u0013\t)$G\u0001\u0004B]f\u0014VM\u001a\t\u0003oaj\u0011AK\u0005\u0003s)\u0012QaU;ji\u0016\u0004\"aN\u001e\n\u0005qR#AE(oK&s7\u000f^1oG\u0016\u0004VM\u001d+fgR\u0004\"a\u000e \n\u0005}R#!C%oM>\u0014X.\u001b8h!\t9\u0014)\u0003\u0002CU\tIaj\u001c;jMfLgn\u001a\t\u0003o\u0011K!!\u0012\u0016\u0003\u0011\u0005cWM\u001d;j]\u001e\u0004\"aN$\n\u0005!S#a\u0003#pGVlWM\u001c;j]\u001e\fa\u0001J5oSR$C#A&\u0011\u0005Eb\u0015BA\'3\u0005\u0011)f.\u001b;\u0002\r\u0015tw-\u001b8f+\u0005\u0001\u0006CA\u001cR\u0013\t\u0011&F\u0001\u0006QCRDWI\\4j]\u0016\f1B\\3x\u0013:\u001cH/\u00198dKV\tQ\u000b\u0005\u0002W\u00015\t\u0001&\u0001\u0003j]\u001a|W#A-\u0011\u0005]R\u0016BA.+\u0005!IeNZ8s[\u0016\u0014\u0018\u0001\u00028pi\u0016,\u0012A\u0018\t\u0003o}K!\u0001\u0019\u0016\u0003\u00119{G/\u001b4jKJ\fQ!\u00197feR,\u0012a\u0019\t\u0003o\u0011L!!\u001a\u0016\u0003\u000f\u0005cWM\u001d;fe\u00061Q.\u0019:lkB,\u0012\u0001\u001b\t\u0003o%L!A\u001b\u0016\u0003\u0015\u0011{7-^7f]R,\'O\u0001\u0004Ji^{\'\u000fZ\n\u0003\u0011A\na\u0001P5oSRtD#A8\u0011\u0005ADQ\"\u0001\u0001\u0002\u0013\u0005\u0004\b\u000f\\=J[BdG#B:\u0002\b\u0005\u0005BcA&us\"1QO\u0003CA\u0002Y\fq\u0001^3ti\u001a+h\u000eE\u00022o.K!\u0001\u001f\u001a\u0003\u0011q\u0012\u0017P\\1nKzBQA\u001f\u0006A\u0002m\f1\u0001]8t!\ra\u00181A\u0007\u0002{*\u0011ap`\u0001\u0007g>,(oY3\u000b\u0007\u0005\u0005A&A\u0005tG\u0006d\u0017m\u0019;jG&\u0019\u0011QA?\u0003\u0011A{7/\u001b;j_:Dq!!\u0003\u000b\u0001\u0004\tY!\u0001\u0005uKN$H+\u001a=u!\u0011\ti!a\u0007\u000f\t\u0005=\u0011q\u0003\t\u0004\u0003#\u0011TBAA\n\u0015\r\t)BL\u0001\u0007yI|w\u000e\u001e \n\u0007\u0005e!\'\u0001\u0004Qe\u0016$WMZ\u0005\u0005\u0003;\tyB\u0001\u0004TiJLgn\u001a\u0006\u0004\u00033\u0011\u0004bBA\u0012\u0015\u0001\u0007\u0011QE\u0001\ti\u0016\u001cH\u000fV1hgB)\u0011\'a\n\u0002,%\u0019\u0011\u0011\u0006\u001a\u0003\u0015q\u0012X\r]3bi\u0016$g\bE\u00028\u0003[I1!a\f+\u0005\r!\u0016mZ\u0001\u0006CB\u0004H.\u001f\u000b\u0007\u0003k\ti$a\u0010\u0015\t\u0005]\u00121\b\u000b\u0004\u0017\u0006e\u0002\"\u0002>\f\u0001\bY\bBB;\f\t\u0003\u0007a\u000fC\u0004\u0002\n-\u0001\r!a\u0003\t\u000f\u0005\r2\u00021\u0001\u0002&\u000511\u000f[8vY\u0012$B!!\u0012\u0002RA!\u0011qIA\'\u001b\t\tIEC\u0002\u0002L)\nQA^3sENLA!a\u0014\u0002J\tQ!)\u001a5bm\u0016<vN\u001d3\t\u000f\u0005MC\u00021\u0001\u0002F\u0005Q!-\u001a5bm\u0016<vN\u001d3\u0002\t5,8\u000f\u001e\u000b\u0005\u0003\u000b\nI\u0006C\u0004\u0002T5\u0001\r!!\u0012\u0002\u0005%$X#A8\u0003\u0011QCW-_,pe\u0012\u001c\"a\u0004\u0019\u0015\u0005\u0005\u0015\u0004C\u00019\u0010)\u0019\tI\'a\u001c\u0002rQ)1*a\u001b\u0002n!1Q/\u0005CA\u0002YDQA_\tA\u0002mDq!!\u0003\u0012\u0001\u0004\tY\u0001C\u0004\u0002$E\u0001\r!!\n\u0015\r\u0005U\u0014QPA@)\u0011\t9(a\u001f\u0015\u0007-\u000bI\bC\u0003{%\u0001\u000f1\u0010\u0003\u0004v%\u0011\u0005\rA\u001e\u0005\b\u0003\u0013\u0011\u0002\u0019AA\u0006\u0011\u001d\t\u0019C\u0005a\u0001\u0003K!B!!\u0012\u0002\u0004\"9\u00111K\nA\u0002\u0005\u0015C\u0003BA#\u0003\u000fCq!a\u0015\u0015\u0001\u0004\t)%\u0001\u0003uQ\u0016LXCAA3\u0003)IwM\\8sK&k\u0007\u000f\u001c\u000b\u0007\u0003#\u000b9*!\'\u0015\u000b-\u000b\u0019*!&\t\rU4B\u00111\u0001w\u0011\u0015Qh\u00031\u0001|\u0011\u001d\tIA\u0006a\u0001\u0003\u0017Aq!a\t\u0017\u0001\u0004\t)#\u0001\u0004jO:|\'/\u001a\u000b\u0007\u0003?\u000b9+!+\u0015\t\u0005\u0005\u0016Q\u0015\u000b\u0004\u0017\u0006\r\u0006\"\u0002>\u0018\u0001\bY\bBB;\u0018\t\u0003\u0007a\u000fC\u0004\u0002\n]\u0001\r!a\u0003\t\u000f\u0005\rr\u00031\u0001\u0002&\u0005aA-Z:de&\u0014W-S7qYR!\u0011qVA\\)\u0015Y\u0015\u0011WA[\u0011\u001d\t\u0019\f\u0007CA\u0002Y\f1AZ;o\u0011\u0015Q\b\u00041\u0001|\u0011\u001d\tI\f\u0007a\u0001\u0003\u0017\t1\u0002Z3tGJL\u0007\u000f^5p]\u0006AA-Z:de&\u0014W\r\u0006\u0003\u0002@\u0006\u001dG\u0003BAa\u0003\u000b$2aSAb\u0011\u0015Q\u0018\u0004q\u0001|\u0011\u001d\t\u0019,\u0007CA\u0002YDq!!/\u001a\u0001\u0004\tY!\u0001\u0004cK\"\fg/Z\u000b\u0003\u0003\u000b\n\u0011\u0002^3ti:\u000bW.Z:\u0016\u0005\u0005E\u0007CBA\u0007\u0003\'\fY!\u0003\u0003\u0002V\u0006}!aA*fi\u0006\tR\r\u001f9fGR,G\rV3ti\u000e{WO\u001c;\u0015\t\u0005m\u0017\u0011\u001d\t\u0004c\u0005u\u0017bAApe\t\u0019\u0011J\u001c;\t\u000f\u0005\rH\u00041\u0001\u0002f\u00061a-\u001b7uKJ\u00042aNAt\u0013\r\tIO\u000b\u0002\u0007\r&dG/\u001a:\u0002\u000fI,h\u000eV3tiR1\u0011q^A{\u0003s\u00042aNAy\u0013\r\t\u0019P\u000b\u0002\u0007\'R\fG/^:\t\u000f\u0005]X\u00041\u0001\u0002\f\u0005AA/Z:u\u001d\u0006lW\rC\u0004\u0002|v\u0001\r!!@\u0002\t\u0005\u0014xm\u001d\t\u0004o\u0005}\u0018b\u0001B\u0001U\t!\u0011I]4t\u0003\u0011!\u0018mZ:\u0016\u0005\t\u001d\u0001\u0003CA\u0007\u0005\u0013\tY!!5\n\t\t-\u0011q\u0004\u0002\u0004\u001b\u0006\u0004\u0018a\u0001:v]R1\u0011q\u001eB\t\u00053Aq!a> \u0001\u0004\u0011\u0019\u0002E\u00032\u0005+\tY!C\u0002\u0003\u0018I\u0012aa\u00149uS>t\u0007bBA~?\u0001\u0007\u0011Q`\u0001\teVtG+Z:ugR1\u0011q\u001eB\u0010\u0005CAq!a>!\u0001\u0004\u0011\u0019\u0002C\u0004\u0002|\u0002\u0002\r!!@\u0002\u001fI,hNT3ti\u0016$7+^5uKN$B!a<\u0003(!9\u00111`\u0011A\u0002\u0005u\u0018\u0001\u00048fgR,GmU;ji\u0016\u001cXC\u0001B\u0017!\u0015\u0011yC!\u000f7\u001b\t\u0011\tD\u0003\u0003\u00034\tU\u0012!C5n[V$\u0018M\u00197f\u0015\r\u00119DM\u0001\u000bG>dG.Z2uS>t\u0017\u0002\u0002B\u001e\u0005c\u0011!\"\u00138eKb,GmU3r\u0003%\u0019H/\u001f7f\u001d\u0006lW-\u0006\u0002\u0002\f!Z1Ea\u0011\u0003J\t-#q\nB)!\r\t$QI\u0005\u0004\u0005\u000f\u0012$A\u00033faJ,7-\u0019;fI\u00069Q.Z:tC\u001e,\u0017E\u0001B\'\u0003q$\u0006.\u001a\u0011tifdWMT1nK\u0002b\u0017NZ3ds\u000edW\rI7fi\"|G\r\t5bg\u0002\u0012W-\u001a8!I\u0016\u0004(/Z2bi\u0016$\u0007%\u00198eA]LG\u000e\u001c\u0011cK\u0002\u0012X-\\8wK\u0012\u0004\u0013N\u001c\u0011bA\u0019,H/\u001e:fAY,\'o]5p]\u0002zg\rI*dC2\fG+Z:uA]LG\u000f\u001b\u0011o_\u0002\u0012X\r\u001d7bG\u0016lWM\u001c;/\u0003\u0015\u0019\u0018N\\2fC\t\u0011\u0019&A\u00034]Er\u0003\'A\u0006uKN$H)\u0019;b\r>\u0014HC\u0002B-\u0005?\u0012\t\u0007E\u00028\u00057J1A!\u0018+\u0005!!Vm\u001d;ECR\f\u0007bBA|I\u0001\u0007\u00111\u0002\u0005\n\u0005G\"\u0003\u0013!a\u0001\u0005K\nA\u0002\u001e5f\u0007>tg-[4NCB\u00042a\u000eB4\u0013\r\u0011IG\u000b\u0002\n\u0007>tg-[4NCB\fQ\u0003^3ti\u0012\u000bG/\u0019$pe\u0012\"WMZ1vYR$#\'\u0006\u0002\u0003p)\"!Q\rB9W\t\u0011\u0019\b\u0005\u0003\u0003v\t}TB\u0001B<\u0015\u0011\u0011IHa\u001f\u0002\u0013Ut7\r[3dW\u0016$\'b\u0001B?e\u0005Q\u0011M\u001c8pi\u0006$\u0018n\u001c8\n\t\t\u0005%q\u000f\u0002\u0012k:\u001c\u0007.Z2lK\u00124\u0016M]5b]\u000e,\u0017aF:va\u0016\u0014H%\u001a=qK\u000e$X\r\u001a+fgR\u001cu.\u001e8u)\u0011\tYNa\"\t\u000f\u0005\rh\u00051\u0001\u0002f&\u0019\u0011q\u001b\u001d)\u000f\u0001\u0011iIa%\u0003\u0016B\u0019qGa$\n\u0007\tE%FA\u0004GS:$WM]:\u0002\u000bY\fG.^3-\u0005\t]\u0015E\u0001BM\u0003\rz\'o\u001a\u0018tG\u0006d\u0017\r^3ti:2\u0017N\u001c3feNtc)\u001e8Ta\u0016\u001cg)\u001b8eKJ\u0004"
    )
BootstrapMethods:
  0: #163 REF_invokeStatic java/lang/invoke/LambdaMetafactory.altMetafactory:(Ljava/lang/invoke/MethodHandles$Lookup;Ljava/lang/String;Ljava/lang/invoke/MethodType;[Ljava/lang/Object;)Ljava/lang/invoke/CallSite;
    Method arguments:
      #148 ()Ljava/lang/Object;
      #153 REF_invokeStatic org/scalatest/funspec/PathAnyFunSpecLike.$anonfun$ignoreImpl$1:()Ljava/lang/String;
      #154 ()Ljava/lang/String;
      #155 5
      #156 1
      #154 ()Ljava/lang/String;
  1: #163 REF_invokeStatic java/lang/invoke/LambdaMetafactory.altMetafactory:(Ljava/lang/invoke/MethodHandles$Lookup;Ljava/lang/String;Ljava/lang/invoke/MethodType;[Ljava/lang/Object;)Ljava/lang/invoke/CallSite;
    Method arguments:
      #148 ()Ljava/lang/Object;
      #209 REF_invokeStatic org/scalatest/funspec/PathAnyFunSpecLike.$anonfun$describeImpl$1:()Ljava/lang/String;
      #154 ()Ljava/lang/String;
      #155 5
      #156 1
      #154 ()Ljava/lang/String;
  2: #163 REF_invokeStatic java/lang/invoke/LambdaMetafactory.altMetafactory:(Ljava/lang/invoke/MethodHandles$Lookup;Ljava/lang/String;Ljava/lang/invoke/MethodType;[Ljava/lang/Object;)Ljava/lang/invoke/CallSite;
    Method arguments:
      #148 ()Ljava/lang/Object;
      #237 REF_invokeStatic org/scalatest/funspec/PathAnyFunSpecLike.$anonfun$describeImpl$2:(Lorg/scalactic/source/Position;)Lorg/scalactic/source/Position;
      #239 ()Lorg/scalactic/source/Position;
      #155 5
      #156 1
      #239 ()Lorg/scalactic/source/Position;
  3: #163 REF_invokeStatic java/lang/invoke/LambdaMetafactory.altMetafactory:(Ljava/lang/invoke/MethodHandles$Lookup;Ljava/lang/String;Ljava/lang/invoke/MethodType;[Ljava/lang/Object;)Ljava/lang/invoke/CallSite;
    Method arguments:
      #148 ()Ljava/lang/Object;
      #260 REF_invokeStatic org/scalatest/funspec/PathAnyFunSpecLike.$anonfun$describeImpl$3:(Lorg/scalactic/source/Position;)Lorg/scalactic/source/Position;
      #239 ()Lorg/scalactic/source/Position;
      #155 5
      #156 1
      #239 ()Lorg/scalactic/source/Position;
  4: #163 REF_invokeStatic java/lang/invoke/LambdaMetafactory.altMetafactory:(Ljava/lang/invoke/MethodHandles$Lookup;Ljava/lang/String;Ljava/lang/invoke/MethodType;[Ljava/lang/Object;)Ljava/lang/invoke/CallSite;
    Method arguments:
      #148 ()Ljava/lang/Object;
      #296 REF_invokeStatic org/scalatest/funspec/PathAnyFunSpecLike.$anonfun$describeImpl$4:(Lorg/scalactic/source/Position;)Lorg/scalactic/source/Position;
      #239 ()Lorg/scalactic/source/Position;
      #155 5
      #156 1
      #239 ()Lorg/scalactic/source/Position;
  5: #163 REF_invokeStatic java/lang/invoke/LambdaMetafactory.altMetafactory:(Ljava/lang/invoke/MethodHandles$Lookup;Ljava/lang/String;Ljava/lang/invoke/MethodType;[Ljava/lang/Object;)Ljava/lang/invoke/CallSite;
    Method arguments:
      #365 (Ljava/lang/Object;)Ljava/lang/Object;
      #370 REF_invokeStatic org/scalatest/funspec/PathAnyFunSpecLike.$anonfun$runTest$1:(Lorg/scalatest/SuperEngine$TestLeaf;)Lorg/scalatest/Outcome;
      #371 (Lorg/scalatest/SuperEngine$TestLeaf;)Lorg/scalatest/Outcome;
      #155 5
      #156 1
      #371 (Lorg/scalatest/SuperEngine$TestLeaf;)Lorg/scalatest/Outcome;
  6: #163 REF_invokeStatic java/lang/invoke/LambdaMetafactory.altMetafactory:(Ljava/lang/invoke/MethodHandles$Lookup;Ljava/lang/String;Ljava/lang/invoke/MethodType;[Ljava/lang/Object;)Ljava/lang/invoke/CallSite;
    Method arguments:
      #402 (Ljava/lang/Object;Ljava/lang/Object;)Ljava/lang/Object;
      #406 REF_invokeStatic org/scalatest/funspec/PathAnyFunSpecLike.$anonfun$run$1:(Lorg/scalatest/funspec/PathAnyFunSpecLike;Ljava/lang/String;Lorg/scalatest/Args;)Lorg/scalatest/Status;
      #407 (Ljava/lang/String;Lorg/scalatest/Args;)Lorg/scalatest/Status;
      #155 5
      #156 1
      #407 (Ljava/lang/String;Lorg/scalatest/Args;)Lorg/scalatest/Status;
  7: #542 REF_invokeStatic scala/runtime/LambdaDeserialize.bootstrap:(Ljava/lang/invoke/MethodHandles$Lookup;Ljava/lang/String;Ljava/lang/invoke/MethodType;[Ljava/lang/invoke/MethodHandle;)Ljava/lang/invoke/CallSite;
    Method arguments:
      #209 REF_invokeStatic org/scalatest/funspec/PathAnyFunSpecLike.$anonfun$describeImpl$1:()Ljava/lang/String;
      #237 REF_invokeStatic org/scalatest/funspec/PathAnyFunSpecLike.$anonfun$describeImpl$2:(Lorg/scalactic/source/Position;)Lorg/scalactic/source/Position;
      #260 REF_invokeStatic org/scalatest/funspec/PathAnyFunSpecLike.$anonfun$describeImpl$3:(Lorg/scalactic/source/Position;)Lorg/scalactic/source/Position;
      #296 REF_invokeStatic org/scalatest/funspec/PathAnyFunSpecLike.$anonfun$describeImpl$4:(Lorg/scalactic/source/Position;)Lorg/scalactic/source/Position;
      #153 REF_invokeStatic org/scalatest/funspec/PathAnyFunSpecLike.$anonfun$ignoreImpl$1:()Ljava/lang/String;
      #406 REF_invokeStatic org/scalatest/funspec/PathAnyFunSpecLike.$anonfun$run$1:(Lorg/scalatest/funspec/PathAnyFunSpecLike;Ljava/lang/String;Lorg/scalatest/Args;)Lorg/scalatest/Status;
      #370 REF_invokeStatic org/scalatest/funspec/PathAnyFunSpecLike.$anonfun$runTest$1:(Lorg/scalatest/SuperEngine$TestLeaf;)Lorg/scalatest/Outcome;
  ScalaInlineInfo: length = 0x11C (unknown attribute)
   01 00 00 38 00 CE 00 96 01 00 E9 00 EA 01 01 01
   00 EA 01 01 25 00 EA 01 00 95 00 96 01 01 93 01
   64 01 01 6E 01 6F 01 01 FA 01 FB 01 00 6F 00 70
   00 00 6D 00 6E 01 01 3F 01 40 00 00 D3 00 C8 00
   01 39 01 3A 01 00 C7 00 C8 01 01 EF 01 6F 01 01
   5D 00 37 01 01 5B 01 5C 01 00 A9 00 88 00 00 C1
   00 C2 01 00 87 00 88 01 00 4F 00 50 00 00 4D 00
   4E 01 00 83 00 84 00 00 7A 00 7B 00 00 78 00 79
   01 01 B5 01 B6 01 01 B3 01 B4 01 00 3E 00 3F 00
   00 3B 00 3C 01 00 64 00 65 00 00 62 00 63 01 00
   39 00 3A 00 00 36 00 37 01 00 32 00 33 00 00 2E
   00 2F 00 00 2B 00 2C 00 00 34 00 35 00 00 30 00
   31 00 01 8B 01 8C 01 01 89 01 8A 01 01 AA 01 AB
   01 01 A8 01 A9 01 01 67 01 68 01 01 63 01 64 01
   01 A0 01 8C 01 01 9F 01 8A 01 01 C9 00 96 00 01
   7D 01 7E 01 01 7B 01 7C 01 01 CD 01 CE 00 01 CA
   01 CB 01 01 D8 01 D9 00 01 D6 01 D7 01 01 43 01
   44 01 01 41 01 42 01 00 85 00 86 00
  ScalaSig: length = 0x3 (unknown attribute)
   05 02 00
