Classfile /Users/mw/Projects/slang-braindump/.jar/jar11/assemble/slang-braindump/assemble/content/coursier/internal/PlatformMirrorConfFile.class
  Last modified May 29, 2022; size 4434 bytes
  SHA-256 checksum 9db76d15e878bd72045fb5dee584afc9f8184b05b1c0cc78fd938ec1ab05c9be
  Compiled from "PlatformMirrorConfFile.scala"
public abstract class coursier.internal.PlatformMirrorConfFile
  minor version: 0
  major version: 52
  flags: (0x0421) ACC_PUBLIC, ACC_SUPER, ACC_ABSTRACT
  this_class: #2                          // coursier/internal/PlatformMirrorConfFile
  super_class: #4                         // java/lang/Object
  interfaces: 0, fields: 0, methods: 6, attributes: 6
Constant pool:
    #1 = Utf8               coursier/internal/PlatformMirrorConfFile
    #2 = Class              #1            // coursier/internal/PlatformMirrorConfFile
    #3 = Utf8               java/lang/Object
    #4 = Class              #3            // java/lang/Object
    #5 = Utf8               PlatformMirrorConfFile.scala
    #6 = Utf8               Lscala/reflect/ScalaSignature;
    #7 = Utf8               bytes
    #8 = Utf8               \u0006\u0005e2Q!\u0002\u0004\u0002\u0002-AQA\u0005\u0001\u0005\u0002MAQA\u0006\u0001\u0007\u0002]AQa\t\u0001\u0007\u0002\u0011BQ\u0001\u000b\u0001\u0005\u0002%\u0012a\u0003\u00157bi\u001a|\'/\\\'jeJ|\'oQ8oM\u001aKG.\u001a\u0006\u0003\u000f!\t\u0001\"\u001b8uKJt\u0017\r\u001c\u0006\u0002\u0013\u0005A1m\\;sg&,\'o\u0001\u0001\u0014\u0005\u0001a\u0001CA\u0007\u0011\u001b\u0005q!\"A\b\u0002\u000bM\u001c\u0017\r\\1\n\u0005Eq!AB!osJ+g-\u0001\u0004=S:LGO\u0010\u000b\u0002)A\u0011Q\u0003A\u0007\u0002\r\u0005!\u0001/\u0019;i+\u0005A\u0002CA\r!\u001d\tQb\u0004\u0005\u0002\u001c\u001d5\tAD\u0003\u0002\u001e\u0015\u00051AH]8pizJ!a\b\b\u0002\rA\u0013X\rZ3g\u0013\t\t#E\u0001\u0004TiJLgn\u001a\u0006\u0003?9\t\u0001b\u001c9uS>t\u0017\r\\\u000b\u0002KA\u0011QBJ\u0005\u0003O9\u0011qAQ8pY\u0016\fg.A\u0004nSJ\u0014xN]:\u0015\u0003)\u00022a\u000b\u00194\u001d\tacF\u0004\u0002\u001c[%\tq\"\u0003\u00020\u001d\u00059\u0001/Y2lC\u001e,\u0017BA\u00193\u0005\r\u0019V-\u001d\u0006\u0003_9\u0001\"\u0001N\u001c\u000e\u0003UR!A\u000e\u0005\u0002\rA\f\'/Y7t\u0013\tATG\u0001\u0004NSJ\u0014xN\u001d
    #9 = Utf8               java/lang/invoke/MethodHandles$Lookup
   #10 = Class              #9            // java/lang/invoke/MethodHandles$Lookup
   #11 = Utf8               java/lang/invoke/MethodHandles
   #12 = Class              #11           // java/lang/invoke/MethodHandles
   #13 = Utf8               Lookup
   #14 = Utf8               scala/collection/convert/AsScalaExtensions$ListHasAsScala
   #15 = Class              #14           // scala/collection/convert/AsScalaExtensions$ListHasAsScala
   #16 = Utf8               scala/collection/convert/AsScalaExtensions
   #17 = Class              #16           // scala/collection/convert/AsScalaExtensions
   #18 = Utf8               ListHasAsScala
   #19 = Utf8               path
   #20 = Utf8               ()Ljava/lang/String;
   #21 = Utf8               optional
   #22 = Utf8               ()Z
   #23 = Utf8               mirrors
   #24 = Utf8               ()Lscala/collection/immutable/Seq;
   #25 = Utf8               ()Lscala/collection/immutable/Seq<Lcoursier/params/Mirror;>;
   #26 = Utf8               java/io/File
   #27 = Class              #26           // java/io/File
   #28 = NameAndType        #19:#20       // path:()Ljava/lang/String;
   #29 = Methodref          #2.#28        // coursier/internal/PlatformMirrorConfFile.path:()Ljava/lang/String;
   #30 = Utf8               <init>
   #31 = Utf8               (Ljava/lang/String;)V
   #32 = NameAndType        #30:#31       // "<init>":(Ljava/lang/String;)V
   #33 = Methodref          #27.#32       // java/io/File."<init>":(Ljava/lang/String;)V
   #34 = Utf8               isFile
   #35 = NameAndType        #34:#22       // isFile:()Z
   #36 = Methodref          #27.#35       // java/io/File.isFile:()Z
   #37 = Utf8               scala/jdk/CollectionConverters$
   #38 = Class              #37           // scala/jdk/CollectionConverters$
   #39 = Utf8               MODULE$
   #40 = Utf8               Lscala/jdk/CollectionConverters$;
   #41 = NameAndType        #39:#40       // MODULE$:Lscala/jdk/CollectionConverters$;
   #42 = Fieldref           #38.#41       // scala/jdk/CollectionConverters$.MODULE$:Lscala/jdk/CollectionConverters$;
   #43 = Utf8               coursier/paths/Mirror
   #44 = Class              #43           // coursier/paths/Mirror
   #45 = Utf8               parse
   #46 = Utf8               (Ljava/io/File;)Ljava/util/List;
   #47 = NameAndType        #45:#46       // parse:(Ljava/io/File;)Ljava/util/List;
   #48 = Methodref          #44.#47       // coursier/paths/Mirror.parse:(Ljava/io/File;)Ljava/util/List;
   #49 = Utf8               (Ljava/util/List;)Lscala/collection/convert/AsScalaExtensions$ListHasAsScala;
   #50 = NameAndType        #18:#49       // ListHasAsScala:(Ljava/util/List;)Lscala/collection/convert/AsScalaExtensions$ListHasAsScala;
   #51 = Methodref          #38.#50       // scala/jdk/CollectionConverters$.ListHasAsScala:(Ljava/util/List;)Lscala/collection/convert/AsScalaExtensions$ListHasAsScala;
   #52 = Utf8               asScala
   #53 = Utf8               ()Lscala/collection/mutable/Buffer;
   #54 = NameAndType        #52:#53       // asScala:()Lscala/collection/mutable/Buffer;
   #55 = Methodref          #15.#54       // scala/collection/convert/AsScalaExtensions$ListHasAsScala.asScala:()Lscala/collection/mutable/Buffer;
   #56 = Utf8               scala/collection/mutable/Buffer
   #57 = Class              #56           // scala/collection/mutable/Buffer
   #58 = Utf8               iterator
   #59 = Utf8               ()Lscala/collection/Iterator;
   #60 = NameAndType        #58:#59       // iterator:()Lscala/collection/Iterator;
   #61 = InterfaceMethodref #57.#60       // scala/collection/mutable/Buffer.iterator:()Lscala/collection/Iterator;
   #62 = Utf8               (Ljava/lang/Object;)Ljava/lang/Object;
   #63 = MethodType         #62           //  (Ljava/lang/Object;)Ljava/lang/Object;
   #64 = Utf8               $anonfun$mirrors$1
   #65 = Utf8               (Lcoursier/paths/Mirror;)Lcoursier/params/Mirror;
   #66 = NameAndType        #64:#65       // $anonfun$mirrors$1:(Lcoursier/paths/Mirror;)Lcoursier/params/Mirror;
   #67 = Methodref          #2.#66        // coursier/internal/PlatformMirrorConfFile.$anonfun$mirrors$1:(Lcoursier/paths/Mirror;)Lcoursier/params/Mirror;
   #68 = MethodHandle       6:#67         // REF_invokeStatic coursier/internal/PlatformMirrorConfFile.$anonfun$mirrors$1:(Lcoursier/paths/Mirror;)Lcoursier/params/Mirror;
   #69 = MethodType         #65           //  (Lcoursier/paths/Mirror;)Lcoursier/params/Mirror;
   #70 = Integer            5
   #71 = Integer            1
   #72 = Utf8               java/lang/invoke/LambdaMetafactory
   #73 = Class              #72           // java/lang/invoke/LambdaMetafactory
   #74 = Utf8               altMetafactory
   #75 = Utf8               (Ljava/lang/invoke/MethodHandles$Lookup;Ljava/lang/String;Ljava/lang/invoke/MethodType;[Ljava/lang/Object;)Ljava/lang/invoke/CallSite;
   #76 = NameAndType        #74:#75       // altMetafactory:(Ljava/lang/invoke/MethodHandles$Lookup;Ljava/lang/String;Ljava/lang/invoke/MethodType;[Ljava/lang/Object;)Ljava/lang/invoke/CallSite;
   #77 = Methodref          #73.#76       // java/lang/invoke/LambdaMetafactory.altMetafactory:(Ljava/lang/invoke/MethodHandles$Lookup;Ljava/lang/String;Ljava/lang/invoke/MethodType;[Ljava/lang/Object;)Ljava/lang/invoke/CallSite;
   #78 = MethodHandle       6:#77         // REF_invokeStatic java/lang/invoke/LambdaMetafactory.altMetafactory:(Ljava/lang/invoke/MethodHandles$Lookup;Ljava/lang/String;Ljava/lang/invoke/MethodType;[Ljava/lang/Object;)Ljava/lang/invoke/CallSite;
   #79 = Utf8               apply
   #80 = Utf8               ()Lscala/Function1;
   #81 = NameAndType        #79:#80       // apply:()Lscala/Function1;
   #82 = InvokeDynamic      #0:#81        // #0:apply:()Lscala/Function1;
   #83 = Utf8               scala/collection/Iterator
   #84 = Class              #83           // scala/collection/Iterator
   #85 = Utf8               map
   #86 = Utf8               (Lscala/Function1;)Lscala/collection/Iterator;
   #87 = NameAndType        #85:#86       // map:(Lscala/Function1;)Lscala/collection/Iterator;
   #88 = InterfaceMethodref #84.#87       // scala/collection/Iterator.map:(Lscala/Function1;)Lscala/collection/Iterator;
   #89 = Utf8               toVector
   #90 = Utf8               ()Lscala/collection/immutable/Vector;
   #91 = NameAndType        #89:#90       // toVector:()Lscala/collection/immutable/Vector;
   #92 = InterfaceMethodref #84.#91       // scala/collection/Iterator.toVector:()Lscala/collection/immutable/Vector;
   #93 = NameAndType        #21:#22       // optional:()Z
   #94 = Methodref          #2.#93        // coursier/internal/PlatformMirrorConfFile.optional:()Z
   #95 = Utf8               scala/collection/immutable/Nil$
   #96 = Class              #95           // scala/collection/immutable/Nil$
   #97 = Utf8               Lscala/collection/immutable/Nil$;
   #98 = NameAndType        #39:#97       // MODULE$:Lscala/collection/immutable/Nil$;
   #99 = Fieldref           #96.#98       // scala/collection/immutable/Nil$.MODULE$:Lscala/collection/immutable/Nil$;
  #100 = Utf8               java/lang/Exception
  #101 = Class              #100          // java/lang/Exception
  #102 = Utf8               java/lang/StringBuilder
  #103 = Class              #102          // java/lang/StringBuilder
  #104 = Integer            26
  #105 = Utf8               (I)V
  #106 = NameAndType        #30:#105      // "<init>":(I)V
  #107 = Methodref          #103.#106     // java/lang/StringBuilder."<init>":(I)V
  #108 = Utf8               Credential file
  #109 = String             #108          // Credential file
  #110 = Utf8               append
  #111 = Utf8               (Ljava/lang/String;)Ljava/lang/StringBuilder;
  #112 = NameAndType        #110:#111     // append:(Ljava/lang/String;)Ljava/lang/StringBuilder;
  #113 = Methodref          #103.#112     // java/lang/StringBuilder.append:(Ljava/lang/String;)Ljava/lang/StringBuilder;
  #114 = Utf8                not found
  #115 = String             #114          //  not found
  #116 = Utf8               toString
  #117 = NameAndType        #116:#20      // toString:()Ljava/lang/String;
  #118 = Methodref          #103.#117     // java/lang/StringBuilder.toString:()Ljava/lang/String;
  #119 = Methodref          #101.#32      // java/lang/Exception."<init>":(Ljava/lang/String;)V
  #120 = Utf8               scala/collection/immutable/AbstractSeq
  #121 = Class              #120          // scala/collection/immutable/AbstractSeq
  #122 = Utf8               f
  #123 = Utf8               Ljava/io/File;
  #124 = Utf8               this
  #125 = Utf8               Lcoursier/internal/PlatformMirrorConfFile;
  #126 = Utf8               m
  #127 = Utf8               type
  #128 = NameAndType        #127:#20      // type:()Ljava/lang/String;
  #129 = Methodref          #44.#128      // coursier/paths/Mirror.type:()Ljava/lang/String;
  #130 = Utf8               java/lang/String
  #131 = Class              #130          // java/lang/String
  #132 = Utf8               hashCode
  #133 = Utf8               ()I
  #134 = NameAndType        #132:#133     // hashCode:()I
  #135 = Methodref          #131.#134     // java/lang/String.hashCode:()I
  #136 = Utf8               tree
  #137 = String             #136          // tree
  #138 = Utf8               equals
  #139 = Utf8               (Ljava/lang/Object;)Z
  #140 = NameAndType        #138:#139     // equals:(Ljava/lang/Object;)Z
  #141 = Methodref          #131.#140     // java/lang/String.equals:(Ljava/lang/Object;)Z
  #142 = Utf8               maven
  #143 = String             #142          // maven
  #144 = Utf8               coursier/params/MavenMirror$
  #145 = Class              #144          // coursier/params/MavenMirror$
  #146 = Utf8               Lcoursier/params/MavenMirror$;
  #147 = NameAndType        #39:#146      // MODULE$:Lcoursier/params/MavenMirror$;
  #148 = Fieldref           #145.#147     // coursier/params/MavenMirror$.MODULE$:Lcoursier/params/MavenMirror$;
  #149 = Utf8               from
  #150 = Utf8               ()Ljava/util/List;
  #151 = NameAndType        #149:#150     // from:()Ljava/util/List;
  #152 = Methodref          #44.#151      // coursier/paths/Mirror.from:()Ljava/util/List;
  #153 = InterfaceMethodref #57.#91       // scala/collection/mutable/Buffer.toVector:()Lscala/collection/immutable/Vector;
  #154 = Utf8               to
  #155 = NameAndType        #154:#20      // to:()Ljava/lang/String;
  #156 = Methodref          #44.#155      // coursier/paths/Mirror.to:()Ljava/lang/String;
  #157 = Utf8               (Lscala/collection/immutable/Seq;Ljava/lang/String;)Lcoursier/params/MavenMirror;
  #158 = NameAndType        #79:#157      // apply:(Lscala/collection/immutable/Seq;Ljava/lang/String;)Lcoursier/params/MavenMirror;
  #159 = Methodref          #145.#158     // coursier/params/MavenMirror$.apply:(Lscala/collection/immutable/Seq;Ljava/lang/String;)Lcoursier/params/MavenMirror;
  #160 = Utf8               coursier/params/TreeMirror$
  #161 = Class              #160          // coursier/params/TreeMirror$
  #162 = Utf8               Lcoursier/params/TreeMirror$;
  #163 = NameAndType        #39:#162      // MODULE$:Lcoursier/params/TreeMirror$;
  #164 = Fieldref           #161.#163     // coursier/params/TreeMirror$.MODULE$:Lcoursier/params/TreeMirror$;
  #165 = Utf8               (Lscala/collection/immutable/Seq;Ljava/lang/String;)Lcoursier/params/TreeMirror;
  #166 = NameAndType        #79:#165      // apply:(Lscala/collection/immutable/Seq;Ljava/lang/String;)Lcoursier/params/TreeMirror;
  #167 = Methodref          #161.#166     // coursier/params/TreeMirror$.apply:(Lscala/collection/immutable/Seq;Ljava/lang/String;)Lcoursier/params/TreeMirror;
  #168 = Utf8               scala/sys/package$
  #169 = Class              #168          // scala/sys/package$
  #170 = Utf8               Lscala/sys/package$;
  #171 = NameAndType        #39:#170      // MODULE$:Lscala/sys/package$;
  #172 = Fieldref           #169.#171     // scala/sys/package$.MODULE$:Lscala/sys/package$;
  #173 = Integer            25
  #174 = Utf8               Unrecognized mirror type
  #175 = String             #174          // Unrecognized mirror type
  #176 = Utf8               error
  #177 = Utf8               (Ljava/lang/String;)Lscala/runtime/Nothing$;
  #178 = NameAndType        #176:#177     // error:(Ljava/lang/String;)Lscala/runtime/Nothing$;
  #179 = Methodref          #169.#178     // scala/sys/package$.error:(Ljava/lang/String;)Lscala/runtime/Nothing$;
  #180 = Utf8               coursier/params/Mirror
  #181 = Class              #180          // coursier/params/Mirror
  #182 = Utf8               Lcoursier/paths/Mirror;
  #183 = Utf8               ()V
  #184 = NameAndType        #30:#183      // "<init>":()V
  #185 = Methodref          #4.#184       // java/lang/Object."<init>":()V
  #186 = Utf8               $deserializeLambda$
  #187 = Utf8               (Ljava/lang/invoke/SerializedLambda;)Ljava/lang/Object;
  #188 = Utf8               scala/runtime/LambdaDeserialize
  #189 = Class              #188          // scala/runtime/LambdaDeserialize
  #190 = Utf8               bootstrap
  #191 = Utf8               (Ljava/lang/invoke/MethodHandles$Lookup;Ljava/lang/String;Ljava/lang/invoke/MethodType;[Ljava/lang/invoke/MethodHandle;)Ljava/lang/invoke/CallSite;
  #192 = NameAndType        #190:#191     // bootstrap:(Ljava/lang/invoke/MethodHandles$Lookup;Ljava/lang/String;Ljava/lang/invoke/MethodType;[Ljava/lang/invoke/MethodHandle;)Ljava/lang/invoke/CallSite;
  #193 = Methodref          #189.#192     // scala/runtime/LambdaDeserialize.bootstrap:(Ljava/lang/invoke/MethodHandles$Lookup;Ljava/lang/String;Ljava/lang/invoke/MethodType;[Ljava/lang/invoke/MethodHandle;)Ljava/lang/invoke/CallSite;
  #194 = MethodHandle       6:#193        // REF_invokeStatic scala/runtime/LambdaDeserialize.bootstrap:(Ljava/lang/invoke/MethodHandles$Lookup;Ljava/lang/String;Ljava/lang/invoke/MethodType;[Ljava/lang/invoke/MethodHandle;)Ljava/lang/invoke/CallSite;
  #195 = Utf8               lambdaDeserialize
  #196 = NameAndType        #195:#187     // lambdaDeserialize:(Ljava/lang/invoke/SerializedLambda;)Ljava/lang/Object;
  #197 = InvokeDynamic      #1:#196       // #1:lambdaDeserialize:(Ljava/lang/invoke/SerializedLambda;)Ljava/lang/Object;
  #198 = Utf8               Code
  #199 = Utf8               StackMapTable
  #200 = Utf8               LineNumberTable
  #201 = Utf8               LocalVariableTable
  #202 = Utf8               Signature
  #203 = Utf8               MethodParameters
  #204 = Utf8               InnerClasses
  #205 = Utf8               SourceFile
  #206 = Utf8               RuntimeVisibleAnnotations
  #207 = Utf8               BootstrapMethods
  #208 = Utf8               ScalaInlineInfo
  #209 = Utf8               ScalaSig
{
  public abstract java.lang.String path();
    descriptor: ()Ljava/lang/String;
    flags: (0x0401) ACC_PUBLIC, ACC_ABSTRACT

  public abstract boolean optional();
    descriptor: ()Z
    flags: (0x0401) ACC_PUBLIC, ACC_ABSTRACT

  public scala.collection.immutable.Seq<coursier.params.Mirror> mirrors();
    descriptor: ()Lscala/collection/immutable/Seq;
    flags: (0x0001) ACC_PUBLIC
    Code:
      stack=5, locals=2, args_size=1
         0: new           #27                 // class java/io/File
         3: dup
         4: aload_0
         5: invokevirtual #29                 // Method path:()Ljava/lang/String;
         8: invokespecial #33                 // Method java/io/File."<init>":(Ljava/lang/String;)V
        11: astore_1
        12: aload_1
        13: invokevirtual #36                 // Method java/io/File.isFile:()Z
        16: ifeq          65
        19: getstatic     #42                 // Field scala/jdk/CollectionConverters$.MODULE$:Lscala/jdk/CollectionConverters$;
        22: new           #27                 // class java/io/File
        25: dup
        26: aload_0
        27: invokevirtual #29                 // Method path:()Ljava/lang/String;
        30: invokespecial #33                 // Method java/io/File."<init>":(Ljava/lang/String;)V
        33: invokestatic  #48                 // Method coursier/paths/Mirror.parse:(Ljava/io/File;)Ljava/util/List;
        36: invokevirtual #51                 // Method scala/jdk/CollectionConverters$.ListHasAsScala:(Ljava/util/List;)Lscala/collection/convert/AsScalaExtensions$ListHasAsScala;
        39: invokevirtual #55                 // Method scala/collection/convert/AsScalaExtensions$ListHasAsScala.asScala:()Lscala/collection/mutable/Buffer;
        42: invokeinterface #61,  1           // InterfaceMethod scala/collection/mutable/Buffer.iterator:()Lscala/collection/Iterator;
        47: invokedynamic #82,  0             // InvokeDynamic #0:apply:()Lscala/Function1;
        52: invokeinterface #88,  2           // InterfaceMethod scala/collection/Iterator.map:(Lscala/Function1;)Lscala/collection/Iterator;
        57: invokeinterface #92,  1           // InterfaceMethod scala/collection/Iterator.toVector:()Lscala/collection/immutable/Vector;
        62: goto          115
        65: aload_0
        66: invokevirtual #94                 // Method optional:()Z
        69: ifeq          78
        72: getstatic     #99                 // Field scala/collection/immutable/Nil$.MODULE$:Lscala/collection/immutable/Nil$;
        75: goto          115
        78: new           #101                // class java/lang/Exception
        81: dup
        82: new           #103                // class java/lang/StringBuilder
        85: dup
        86: ldc           #104                // int 26
        88: invokespecial #107                // Method java/lang/StringBuilder."<init>":(I)V
        91: ldc           #109                // String Credential file
        93: invokevirtual #113                // Method java/lang/StringBuilder.append:(Ljava/lang/String;)Ljava/lang/StringBuilder;
        96: aload_0
        97: invokevirtual #29                 // Method path:()Ljava/lang/String;
       100: invokevirtual #113                // Method java/lang/StringBuilder.append:(Ljava/lang/String;)Ljava/lang/StringBuilder;
       103: ldc           #115                // String  not found
       105: invokevirtual #113                // Method java/lang/StringBuilder.append:(Ljava/lang/String;)Ljava/lang/StringBuilder;
       108: invokevirtual #118                // Method java/lang/StringBuilder.toString:()Ljava/lang/String;
       111: invokespecial #119                // Method java/lang/Exception."<init>":(Ljava/lang/String;)V
       114: athrow
       115: areturn
      StackMapTable: number_of_entries = 3
        frame_type = 252 /* append */
          offset_delta = 65
          locals = [ class java/io/File ]
        frame_type = 12 /* same */
        frame_type = 100 /* same_locals_1_stack_item */
          stack = [ class scala/collection/immutable/AbstractSeq ]
      LineNumberTable:
        line 16: 0
        line 18: 12
        line 19: 19
        line 22: 47
        line 33: 65
        line 34: 72
        line 36: 78
      LocalVariableTable:
        Start  Length  Slot  Name   Signature
           12     103     1     f   Ljava/io/File;
            0     116     0  this   Lcoursier/internal/PlatformMirrorConfFile;
    Signature: #25                          // ()Lscala/collection/immutable/Seq<Lcoursier/params/Mirror;>;

  public static final coursier.params.Mirror $anonfun$mirrors$1(coursier.paths.Mirror);
    descriptor: (Lcoursier/paths/Mirror;)Lcoursier/params/Mirror;
    flags: (0x1019) ACC_PUBLIC, ACC_STATIC, ACC_FINAL, ACC_SYNTHETIC
    Code:
      stack=4, locals=3, args_size=1
         0: aload_0
         1: invokevirtual #129                // Method coursier/paths/Mirror.type:()Ljava/lang/String;
         4: astore_2
         5: aload_2
         6: ifnonnull     13
         9: iconst_0
        10: goto          17
        13: aload_2
        14: invokevirtual #135                // Method java/lang/String.hashCode:()I
        17: lookupswitch  { // 2
                 3568542: 44
               103670155: 59
                 default: 74
            }
        44: ldc           #137                // String tree
        46: aload_2
        47: invokevirtual #141                // Method java/lang/String.equals:(Ljava/lang/Object;)Z
        50: ifeq          56
        53: goto          109
        56: goto          141
        59: ldc           #143                // String maven
        61: aload_2
        62: invokevirtual #141                // Method java/lang/String.equals:(Ljava/lang/Object;)Z
        65: ifeq          71
        68: goto          77
        71: goto          141
        74: goto          141
        77: getstatic     #148                // Field coursier/params/MavenMirror$.MODULE$:Lcoursier/params/MavenMirror$;
        80: getstatic     #42                 // Field scala/jdk/CollectionConverters$.MODULE$:Lscala/jdk/CollectionConverters$;
        83: aload_0
        84: invokevirtual #152                // Method coursier/paths/Mirror.from:()Ljava/util/List;
        87: invokevirtual #51                 // Method scala/jdk/CollectionConverters$.ListHasAsScala:(Ljava/util/List;)Lscala/collection/convert/AsScalaExtensions$ListHasAsScala;
        90: invokevirtual #55                 // Method scala/collection/convert/AsScalaExtensions$ListHasAsScala.asScala:()Lscala/collection/mutable/Buffer;
        93: invokeinterface #153,  1          // InterfaceMethod scala/collection/mutable/Buffer.toVector:()Lscala/collection/immutable/Vector;
        98: aload_0
        99: invokevirtual #156                // Method coursier/paths/Mirror.to:()Ljava/lang/String;
       102: invokevirtual #159                // Method coursier/params/MavenMirror$.apply:(Lscala/collection/immutable/Seq;Ljava/lang/String;)Lcoursier/params/MavenMirror;
       105: astore_1
       106: goto          169
       109: getstatic     #164                // Field coursier/params/TreeMirror$.MODULE$:Lcoursier/params/TreeMirror$;
       112: getstatic     #42                 // Field scala/jdk/CollectionConverters$.MODULE$:Lscala/jdk/CollectionConverters$;
       115: aload_0
       116: invokevirtual #152                // Method coursier/paths/Mirror.from:()Ljava/util/List;
       119: invokevirtual #51                 // Method scala/jdk/CollectionConverters$.ListHasAsScala:(Ljava/util/List;)Lscala/collection/convert/AsScalaExtensions$ListHasAsScala;
       122: invokevirtual #55                 // Method scala/collection/convert/AsScalaExtensions$ListHasAsScala.asScala:()Lscala/collection/mutable/Buffer;
       125: invokeinterface #153,  1          // InterfaceMethod scala/collection/mutable/Buffer.toVector:()Lscala/collection/immutable/Vector;
       130: aload_0
       131: invokevirtual #156                // Method coursier/paths/Mirror.to:()Ljava/lang/String;
       134: invokevirtual #167                // Method coursier/params/TreeMirror$.apply:(Lscala/collection/immutable/Seq;Ljava/lang/String;)Lcoursier/params/TreeMirror;
       137: astore_1
       138: goto          169
       141: getstatic     #172                // Field scala/sys/package$.MODULE$:Lscala/sys/package$;
       144: new           #103                // class java/lang/StringBuilder
       147: dup
       148: ldc           #173                // int 25
       150: invokespecial #107                // Method java/lang/StringBuilder."<init>":(I)V
       153: ldc           #175                // String Unrecognized mirror type
       155: invokevirtual #113                // Method java/lang/StringBuilder.append:(Ljava/lang/String;)Ljava/lang/StringBuilder;
       158: aload_2
       159: invokevirtual #113                // Method java/lang/StringBuilder.append:(Ljava/lang/String;)Ljava/lang/StringBuilder;
       162: invokevirtual #118                // Method java/lang/StringBuilder.toString:()Ljava/lang/String;
       165: invokevirtual #179                // Method scala/sys/package$.error:(Ljava/lang/String;)Lscala/runtime/Nothing$;
       168: athrow
       169: aload_1
       170: areturn
      StackMapTable: number_of_entries = 11
        frame_type = 253 /* append */
          offset_delta = 13
          locals = [ top, class java/lang/String ]
        frame_type = 67 /* same_locals_1_stack_item */
          stack = [ int ]
        frame_type = 26 /* same */
        frame_type = 11 /* same */
        frame_type = 2 /* same */
        frame_type = 11 /* same */
        frame_type = 2 /* same */
        frame_type = 2 /* same */
        frame_type = 31 /* same */
        frame_type = 31 /* same */
        frame_type = 255 /* full_frame */
          offset_delta = 27
          locals = [ class coursier/paths/Mirror, class coursier/params/Mirror, class java/lang/String ]
          stack = []
      LineNumberTable:
        line 23: 0
        line 26: 44
        line 23: 56
        line 24: 59
        line 23: 71
        line 25: 77
        line 27: 109
        line 29: 141
        line 23: 169
      LocalVariableTable:
        Start  Length  Slot  Name   Signature
            0     171     0     m   Lcoursier/paths/Mirror;
    MethodParameters:
      Name                           Flags
      m                              final

  public coursier.internal.PlatformMirrorConfFile();
    descriptor: ()V
    flags: (0x0001) ACC_PUBLIC
    Code:
      stack=1, locals=1, args_size=1
         0: aload_0
         1: invokespecial #185                // Method java/lang/Object."<init>":()V
         4: return
      LineNumberTable:
        line 38: 0
        line 9: 4
      LocalVariableTable:
        Start  Length  Slot  Name   Signature
            0       5     0  this   Lcoursier/internal/PlatformMirrorConfFile;

  private static java.lang.Object $deserializeLambda$(java.lang.invoke.SerializedLambda);
    descriptor: (Ljava/lang/invoke/SerializedLambda;)Ljava/lang/Object;
    flags: (0x100a) ACC_PRIVATE, ACC_STATIC, ACC_SYNTHETIC
    Code:
      stack=1, locals=1, args_size=1
         0: aload_0
         1: invokedynamic #197,  0            // InvokeDynamic #1:lambdaDeserialize:(Ljava/lang/invoke/SerializedLambda;)Ljava/lang/Object;
         6: areturn
}
InnerClasses:
  public static final #13= #10 of #12;    // Lookup=class java/lang/invoke/MethodHandles$Lookup of class java/lang/invoke/MethodHandles
  public #18= #15 of #17;                 // ListHasAsScala=class scala/collection/convert/AsScalaExtensions$ListHasAsScala of class scala/collection/convert/AsScalaExtensions
SourceFile: "PlatformMirrorConfFile.scala"
RuntimeVisibleAnnotations:
  0: #6(#7=s#8)
    scala.reflect.ScalaSignature(
      bytes="\u0006\u0005e2Q!\u0002\u0004\u0002\u0002-AQA\u0005\u0001\u0005\u0002MAQA\u0006\u0001\u0007\u0002]AQa\t\u0001\u0007\u0002\u0011BQ\u0001\u000b\u0001\u0005\u0002%\u0012a\u0003\u00157bi\u001a|\'/\\\'jeJ|\'oQ8oM\u001aKG.\u001a\u0006\u0003\u000f!\t\u0001\"\u001b8uKJt\u0017\r\u001c\u0006\u0002\u0013\u0005A1m\\;sg&,\'o\u0001\u0001\u0014\u0005\u0001a\u0001CA\u0007\u0011\u001b\u0005q!\"A\b\u0002\u000bM\u001c\u0017\r\\1\n\u0005Eq!AB!osJ+g-\u0001\u0004=S:LGO\u0010\u000b\u0002)A\u0011Q\u0003A\u0007\u0002\r\u0005!\u0001/\u0019;i+\u0005A\u0002CA\r!\u001d\tQb\u0004\u0005\u0002\u001c\u001d5\tAD\u0003\u0002\u001e\u0015\u00051AH]8pizJ!a\b\b\u0002\rA\u0013X\rZ3g\u0013\t\t#E\u0001\u0004TiJLgn\u001a\u0006\u0003?9\t\u0001b\u001c9uS>t\u0017\r\\\u000b\u0002KA\u0011QBJ\u0005\u0003O9\u0011qAQ8pY\u0016\fg.A\u0004nSJ\u0014xN]:\u0015\u0003)\u00022a\u000b\u00194\u001d\tacF\u0004\u0002\u001c[%\tq\"\u0003\u00020\u001d\u00059\u0001/Y2lC\u001e,\u0017BA\u00193\u0005\r\u0019V-\u001d\u0006\u0003_9\u0001\"\u0001N\u001c\u000e\u0003UR!A\u000e\u0005\u0002\rA\f\'/Y7t\u0013\tATG\u0001\u0004NSJ\u0014xN\u001d"
    )
BootstrapMethods:
  0: #78 REF_invokeStatic java/lang/invoke/LambdaMetafactory.altMetafactory:(Ljava/lang/invoke/MethodHandles$Lookup;Ljava/lang/String;Ljava/lang/invoke/MethodType;[Ljava/lang/Object;)Ljava/lang/invoke/CallSite;
    Method arguments:
      #63 (Ljava/lang/Object;)Ljava/lang/Object;
      #68 REF_invokeStatic coursier/internal/PlatformMirrorConfFile.$anonfun$mirrors$1:(Lcoursier/paths/Mirror;)Lcoursier/params/Mirror;
      #69 (Lcoursier/paths/Mirror;)Lcoursier/params/Mirror;
      #70 5
      #71 1
      #69 (Lcoursier/paths/Mirror;)Lcoursier/params/Mirror;
  1: #194 REF_invokeStatic scala/runtime/LambdaDeserialize.bootstrap:(Ljava/lang/invoke/MethodHandles$Lookup;Ljava/lang/String;Ljava/lang/invoke/MethodType;[Ljava/lang/invoke/MethodHandle;)Ljava/lang/invoke/CallSite;
    Method arguments:
      #68 REF_invokeStatic coursier/internal/PlatformMirrorConfFile.$anonfun$mirrors$1:(Lcoursier/paths/Mirror;)Lcoursier/params/Mirror;
  ScalaInlineInfo: length = 0x1D (unknown attribute)
   01 00 00 05 00 40 00 41 01 00 1E 00 B7 00 00 17
   00 18 00 00 15 00 16 00 00 13 00 14 00
  ScalaSig: length = 0x3 (unknown attribute)
   05 02 00
