Classfile /Users/mw/Projects/slang-braindump/.jar/jar11/assemble/slang-braindump/assemble/content/coursier/internal/Typelevel$.class
  Last modified May 29, 2022; size 3907 bytes
  SHA-256 checksum 922a3c6cdd8a92f6f46c1a16447f67b34060a9b04ac1bdef5e67ebebcecc3df0
  Compiled from "Typelevel.scala"
public final class coursier.internal.Typelevel$
  minor version: 0
  major version: 52
  flags: (0x0031) ACC_PUBLIC, ACC_FINAL, ACC_SUPER
  this_class: #2                          // coursier/internal/Typelevel$
  super_class: #4                         // java/lang/Object
  interfaces: 0, fields: 5, methods: 9, attributes: 5
Constant pool:
    #1 = Utf8               coursier/internal/Typelevel$
    #2 = Class              #1            // coursier/internal/Typelevel$
    #3 = Utf8               java/lang/Object
    #4 = Class              #3            // java/lang/Object
    #5 = Utf8               Typelevel.scala
    #6 = Utf8               java/lang/invoke/MethodHandles$Lookup
    #7 = Class              #6            // java/lang/invoke/MethodHandles$Lookup
    #8 = Utf8               java/lang/invoke/MethodHandles
    #9 = Class              #8            // java/lang/invoke/MethodHandles
   #10 = Utf8               Lookup
   #11 = Utf8               MODULE$
   #12 = Utf8               Lcoursier/internal/Typelevel$;
   #13 = Utf8               mainLineOrg
   #14 = Utf8               Ljava/lang/String;
   #15 = Utf8               typelevelOrg
   #16 = Utf8               modules
   #17 = Utf8               Lscala/collection/immutable/Set;
   #18 = Utf8               Lscala/collection/immutable/Set<Lcoursier/core/ModuleName;>;
   #19 = Utf8               swap
   #20 = Utf8               Lscala/Function1;
   #21 = Utf8               Lscala/Function1<Lcoursier/core/Dependency;Lcoursier/core/Dependency;>;
   #22 = Utf8               <clinit>
   #23 = Utf8               ()V
   #24 = Utf8               <init>
   #25 = NameAndType        #24:#23       // "<init>":()V
   #26 = Methodref          #2.#25        // coursier/internal/Typelevel$."<init>":()V
   #27 = NameAndType        #11:#12       // MODULE$:Lcoursier/internal/Typelevel$;
   #28 = Fieldref           #2.#27        // coursier/internal/Typelevel$.MODULE$:Lcoursier/internal/Typelevel$;
   #29 = Utf8               org.scala-lang
   #30 = String             #29           // org.scala-lang
   #31 = NameAndType        #13:#14       // mainLineOrg:Ljava/lang/String;
   #32 = Fieldref           #2.#31        // coursier/internal/Typelevel$.mainLineOrg:Ljava/lang/String;
   #33 = Utf8               org.typelevel
   #34 = String             #33           // org.typelevel
   #35 = NameAndType        #15:#14       // typelevelOrg:Ljava/lang/String;
   #36 = Fieldref           #2.#35        // coursier/internal/Typelevel$.typelevelOrg:Ljava/lang/String;
   #37 = Utf8               scala/Predef$
   #38 = Class              #37           // scala/Predef$
   #39 = Utf8               Lscala/Predef$;
   #40 = NameAndType        #11:#39       // MODULE$:Lscala/Predef$;
   #41 = Fieldref           #38.#40       // scala/Predef$.MODULE$:Lscala/Predef$;
   #42 = Utf8               Set
   #43 = Utf8               ()Lscala/collection/immutable/Set$;
   #44 = NameAndType        #42:#43       // Set:()Lscala/collection/immutable/Set$;
   #45 = Methodref          #38.#44       // scala/Predef$.Set:()Lscala/collection/immutable/Set$;
   #46 = Utf8               scala/runtime/ScalaRunTime$
   #47 = Class              #46           // scala/runtime/ScalaRunTime$
   #48 = Utf8               Lscala/runtime/ScalaRunTime$;
   #49 = NameAndType        #11:#48       // MODULE$:Lscala/runtime/ScalaRunTime$;
   #50 = Fieldref           #47.#49       // scala/runtime/ScalaRunTime$.MODULE$:Lscala/runtime/ScalaRunTime$;
   #51 = Utf8               coursier/core/ModuleName
   #52 = Class              #51           // coursier/core/ModuleName
   #53 = Utf8               scala-compiler
   #54 = String             #53           // scala-compiler
   #55 = Utf8               (Ljava/lang/String;)V
   #56 = NameAndType        #24:#55       // "<init>":(Ljava/lang/String;)V
   #57 = Methodref          #52.#56       // coursier/core/ModuleName."<init>":(Ljava/lang/String;)V
   #58 = Utf8               scala-library
   #59 = String             #58           // scala-library
   #60 = Utf8               scala-library-all
   #61 = String             #60           // scala-library-all
   #62 = Utf8               scala-reflect
   #63 = String             #62           // scala-reflect
   #64 = Utf8               scalap
   #65 = String             #64           // scalap
   #66 = Utf8               genericWrapArray
   #67 = Utf8               (Ljava/lang/Object;)Lscala/collection/immutable/ArraySeq;
   #68 = NameAndType        #66:#67       // genericWrapArray:(Ljava/lang/Object;)Lscala/collection/immutable/ArraySeq;
   #69 = Methodref          #47.#68       // scala/runtime/ScalaRunTime$.genericWrapArray:(Ljava/lang/Object;)Lscala/collection/immutable/ArraySeq;
   #70 = Utf8               scala/collection/immutable/Set$
   #71 = Class              #70           // scala/collection/immutable/Set$
   #72 = Utf8               apply
   #73 = Utf8               (Lscala/collection/immutable/Seq;)Ljava/lang/Object;
   #74 = NameAndType        #72:#73       // apply:(Lscala/collection/immutable/Seq;)Ljava/lang/Object;
   #75 = Methodref          #71.#74       // scala/collection/immutable/Set$.apply:(Lscala/collection/immutable/Seq;)Ljava/lang/Object;
   #76 = Utf8               scala/collection/immutable/Set
   #77 = Class              #76           // scala/collection/immutable/Set
   #78 = NameAndType        #16:#17       // modules:Lscala/collection/immutable/Set;
   #79 = Fieldref           #2.#78        // coursier/internal/Typelevel$.modules:Lscala/collection/immutable/Set;
   #80 = Utf8               (Ljava/lang/Object;)Ljava/lang/Object;
   #81 = MethodType         #80           //  (Ljava/lang/Object;)Ljava/lang/Object;
   #82 = Utf8               $anonfun$swap$1
   #83 = Utf8               (Lcoursier/core/Dependency;)Lcoursier/core/Dependency;
   #84 = NameAndType        #82:#83       // $anonfun$swap$1:(Lcoursier/core/Dependency;)Lcoursier/core/Dependency;
   #85 = Methodref          #2.#84        // coursier/internal/Typelevel$.$anonfun$swap$1:(Lcoursier/core/Dependency;)Lcoursier/core/Dependency;
   #86 = MethodHandle       6:#85         // REF_invokeStatic coursier/internal/Typelevel$.$anonfun$swap$1:(Lcoursier/core/Dependency;)Lcoursier/core/Dependency;
   #87 = MethodType         #83           //  (Lcoursier/core/Dependency;)Lcoursier/core/Dependency;
   #88 = Integer            5
   #89 = Integer            1
   #90 = Utf8               java/lang/invoke/LambdaMetafactory
   #91 = Class              #90           // java/lang/invoke/LambdaMetafactory
   #92 = Utf8               altMetafactory
   #93 = Utf8               (Ljava/lang/invoke/MethodHandles$Lookup;Ljava/lang/String;Ljava/lang/invoke/MethodType;[Ljava/lang/Object;)Ljava/lang/invoke/CallSite;
   #94 = NameAndType        #92:#93       // altMetafactory:(Ljava/lang/invoke/MethodHandles$Lookup;Ljava/lang/String;Ljava/lang/invoke/MethodType;[Ljava/lang/Object;)Ljava/lang/invoke/CallSite;
   #95 = Methodref          #91.#94       // java/lang/invoke/LambdaMetafactory.altMetafactory:(Ljava/lang/invoke/MethodHandles$Lookup;Ljava/lang/String;Ljava/lang/invoke/MethodType;[Ljava/lang/Object;)Ljava/lang/invoke/CallSite;
   #96 = MethodHandle       6:#95         // REF_invokeStatic java/lang/invoke/LambdaMetafactory.altMetafactory:(Ljava/lang/invoke/MethodHandles$Lookup;Ljava/lang/String;Ljava/lang/invoke/MethodType;[Ljava/lang/Object;)Ljava/lang/invoke/CallSite;
   #97 = Utf8               ()Lscala/Function1;
   #98 = NameAndType        #72:#97       // apply:()Lscala/Function1;
   #99 = InvokeDynamic      #0:#98        // #0:apply:()Lscala/Function1;
  #100 = NameAndType        #19:#20       // swap:Lscala/Function1;
  #101 = Fieldref           #2.#100       // coursier/internal/Typelevel$.swap:Lscala/Function1;
  #102 = Utf8               ()Ljava/lang/String;
  #103 = Utf8               this
  #104 = Utf8               ()Lscala/collection/immutable/Set;
  #105 = Utf8               ()Lscala/collection/immutable/Set<Lcoursier/core/ModuleName;>;
  #106 = Utf8               (Lcoursier/core/Module;)Lcoursier/core/Module;
  #107 = Utf8               module
  #108 = Utf8               coursier/core/Module
  #109 = Class              #108          // coursier/core/Module
  #110 = Utf8               organization
  #111 = NameAndType        #110:#102     // organization:()Ljava/lang/String;
  #112 = Methodref          #109.#111     // coursier/core/Module.organization:()Ljava/lang/String;
  #113 = NameAndType        #13:#102      // mainLineOrg:()Ljava/lang/String;
  #114 = Methodref          #2.#113       // coursier/internal/Typelevel$.mainLineOrg:()Ljava/lang/String;
  #115 = Utf8               java/lang/String
  #116 = Class              #115          // java/lang/String
  #117 = Utf8               equals
  #118 = Utf8               (Ljava/lang/Object;)Z
  #119 = NameAndType        #117:#118     // equals:(Ljava/lang/Object;)Z
  #120 = Methodref          #4.#119       // java/lang/Object.equals:(Ljava/lang/Object;)Z
  #121 = NameAndType        #16:#104      // modules:()Lscala/collection/immutable/Set;
  #122 = Methodref          #2.#121       // coursier/internal/Typelevel$.modules:()Lscala/collection/immutable/Set;
  #123 = Utf8               name
  #124 = NameAndType        #123:#102     // name:()Ljava/lang/String;
  #125 = Methodref          #109.#124     // coursier/core/Module.name:()Ljava/lang/String;
  #126 = NameAndType        #72:#118      // apply:(Ljava/lang/Object;)Z
  #127 = InterfaceMethodref #77.#126      // scala/collection/immutable/Set.apply:(Ljava/lang/Object;)Z
  #128 = Utf8               attributes
  #129 = Utf8               ()Lscala/collection/immutable/Map;
  #130 = NameAndType        #128:#129     // attributes:()Lscala/collection/immutable/Map;
  #131 = Methodref          #109.#130     // coursier/core/Module.attributes:()Lscala/collection/immutable/Map;
  #132 = Utf8               scala/collection/immutable/Map
  #133 = Class              #132          // scala/collection/immutable/Map
  #134 = Utf8               isEmpty
  #135 = Utf8               ()Z
  #136 = NameAndType        #134:#135     // isEmpty:()Z
  #137 = InterfaceMethodref #133.#136     // scala/collection/immutable/Map.isEmpty:()Z
  #138 = NameAndType        #15:#102      // typelevelOrg:()Ljava/lang/String;
  #139 = Methodref          #2.#138       // coursier/internal/Typelevel$.typelevelOrg:()Ljava/lang/String;
  #140 = Utf8               withOrganization
  #141 = Utf8               (Ljava/lang/String;)Lcoursier/core/Module;
  #142 = NameAndType        #140:#141     // withOrganization:(Ljava/lang/String;)Lcoursier/core/Module;
  #143 = Methodref          #109.#142     // coursier/core/Module.withOrganization:(Ljava/lang/String;)Lcoursier/core/Module;
  #144 = Utf8               Lcoursier/core/Module;
  #145 = Utf8               ()Lscala/Function1<Lcoursier/core/Dependency;Lcoursier/core/Dependency;>;
  #146 = Utf8               dependency
  #147 = Utf8               coursier/core/Dependency
  #148 = Class              #147          // coursier/core/Dependency
  #149 = Utf8               ()Lcoursier/core/Module;
  #150 = NameAndType        #107:#149     // module:()Lcoursier/core/Module;
  #151 = Methodref          #148.#150     // coursier/core/Dependency.module:()Lcoursier/core/Module;
  #152 = NameAndType        #19:#106      // swap:(Lcoursier/core/Module;)Lcoursier/core/Module;
  #153 = Methodref          #2.#152       // coursier/internal/Typelevel$.swap:(Lcoursier/core/Module;)Lcoursier/core/Module;
  #154 = Utf8               withModule
  #155 = Utf8               (Lcoursier/core/Module;)Lcoursier/core/Dependency;
  #156 = NameAndType        #154:#155     // withModule:(Lcoursier/core/Module;)Lcoursier/core/Dependency;
  #157 = Methodref          #148.#156     // coursier/core/Dependency.withModule:(Lcoursier/core/Module;)Lcoursier/core/Dependency;
  #158 = Utf8               Lcoursier/core/Dependency;
  #159 = Methodref          #4.#25        // java/lang/Object."<init>":()V
  #160 = Utf8               $deserializeLambda$
  #161 = Utf8               (Ljava/lang/invoke/SerializedLambda;)Ljava/lang/Object;
  #162 = Utf8               scala/runtime/LambdaDeserialize
  #163 = Class              #162          // scala/runtime/LambdaDeserialize
  #164 = Utf8               bootstrap
  #165 = Utf8               (Ljava/lang/invoke/MethodHandles$Lookup;Ljava/lang/String;Ljava/lang/invoke/MethodType;[Ljava/lang/invoke/MethodHandle;)Ljava/lang/invoke/CallSite;
  #166 = NameAndType        #164:#165     // bootstrap:(Ljava/lang/invoke/MethodHandles$Lookup;Ljava/lang/String;Ljava/lang/invoke/MethodType;[Ljava/lang/invoke/MethodHandle;)Ljava/lang/invoke/CallSite;
  #167 = Methodref          #163.#166     // scala/runtime/LambdaDeserialize.bootstrap:(Ljava/lang/invoke/MethodHandles$Lookup;Ljava/lang/String;Ljava/lang/invoke/MethodType;[Ljava/lang/invoke/MethodHandle;)Ljava/lang/invoke/CallSite;
  #168 = MethodHandle       6:#167        // REF_invokeStatic scala/runtime/LambdaDeserialize.bootstrap:(Ljava/lang/invoke/MethodHandles$Lookup;Ljava/lang/String;Ljava/lang/invoke/MethodType;[Ljava/lang/invoke/MethodHandle;)Ljava/lang/invoke/CallSite;
  #169 = Utf8               lambdaDeserialize
  #170 = NameAndType        #169:#161     // lambdaDeserialize:(Ljava/lang/invoke/SerializedLambda;)Ljava/lang/Object;
  #171 = InvokeDynamic      #1:#170       // #1:lambdaDeserialize:(Ljava/lang/invoke/SerializedLambda;)Ljava/lang/Object;
  #172 = Utf8               Signature
  #173 = Utf8               Code
  #174 = Utf8               LineNumberTable
  #175 = Utf8               LocalVariableTable
  #176 = Utf8               StackMapTable
  #177 = Utf8               MethodParameters
  #178 = Utf8               InnerClasses
  #179 = Utf8               SourceFile
  #180 = Utf8               BootstrapMethods
  #181 = Utf8               ScalaInlineInfo
  #182 = Utf8               Scala
{
  public static final coursier.internal.Typelevel$ MODULE$;
    descriptor: Lcoursier/internal/Typelevel$;
    flags: (0x0019) ACC_PUBLIC, ACC_STATIC, ACC_FINAL

  private static final java.lang.String mainLineOrg;
    descriptor: Ljava/lang/String;
    flags: (0x001a) ACC_PRIVATE, ACC_STATIC, ACC_FINAL

  private static final java.lang.String typelevelOrg;
    descriptor: Ljava/lang/String;
    flags: (0x001a) ACC_PRIVATE, ACC_STATIC, ACC_FINAL

  private static final scala.collection.immutable.Set<coursier.core.ModuleName> modules;
    descriptor: Lscala/collection/immutable/Set;
    flags: (0x001a) ACC_PRIVATE, ACC_STATIC, ACC_FINAL
    Signature: #18                          // Lscala/collection/immutable/Set<Lcoursier/core/ModuleName;>;

  private static final scala.Function1<coursier.core.Dependency, coursier.core.Dependency> swap;
    descriptor: Lscala/Function1;
    flags: (0x001a) ACC_PRIVATE, ACC_STATIC, ACC_FINAL
    Signature: #21                          // Lscala/Function1<Lcoursier/core/Dependency;Lcoursier/core/Dependency;>;

  public static {};
    descriptor: ()V
    flags: (0x0009) ACC_PUBLIC, ACC_STATIC
    Code:
      stack=8, locals=0, args_size=0
         0: new           #2                  // class coursier/internal/Typelevel$
         3: dup
         4: invokespecial #26                 // Method "<init>":()V
         7: putstatic     #28                 // Field MODULE$:Lcoursier/internal/Typelevel$;
        10: ldc           #30                 // String org.scala-lang
        12: putstatic     #32                 // Field mainLineOrg:Ljava/lang/String;
        15: ldc           #34                 // String org.typelevel
        17: putstatic     #36                 // Field typelevelOrg:Ljava/lang/String;
        20: getstatic     #41                 // Field scala/Predef$.MODULE$:Lscala/Predef$;
        23: invokevirtual #45                 // Method scala/Predef$.Set:()Lscala/collection/immutable/Set$;
        26: getstatic     #50                 // Field scala/runtime/ScalaRunTime$.MODULE$:Lscala/runtime/ScalaRunTime$;
        29: iconst_5
        30: anewarray     #52                 // class coursier/core/ModuleName
        33: dup
        34: iconst_0
        35: new           #52                 // class coursier/core/ModuleName
        38: dup
        39: ldc           #54                 // String scala-compiler
        41: invokespecial #57                 // Method coursier/core/ModuleName."<init>":(Ljava/lang/String;)V
        44: aastore
        45: dup
        46: iconst_1
        47: new           #52                 // class coursier/core/ModuleName
        50: dup
        51: ldc           #59                 // String scala-library
        53: invokespecial #57                 // Method coursier/core/ModuleName."<init>":(Ljava/lang/String;)V
        56: aastore
        57: dup
        58: iconst_2
        59: new           #52                 // class coursier/core/ModuleName
        62: dup
        63: ldc           #61                 // String scala-library-all
        65: invokespecial #57                 // Method coursier/core/ModuleName."<init>":(Ljava/lang/String;)V
        68: aastore
        69: dup
        70: iconst_3
        71: new           #52                 // class coursier/core/ModuleName
        74: dup
        75: ldc           #63                 // String scala-reflect
        77: invokespecial #57                 // Method coursier/core/ModuleName."<init>":(Ljava/lang/String;)V
        80: aastore
        81: dup
        82: iconst_4
        83: new           #52                 // class coursier/core/ModuleName
        86: dup
        87: ldc           #65                 // String scalap
        89: invokespecial #57                 // Method coursier/core/ModuleName."<init>":(Ljava/lang/String;)V
        92: aastore
        93: invokevirtual #69                 // Method scala/runtime/ScalaRunTime$.genericWrapArray:(Ljava/lang/Object;)Lscala/collection/immutable/ArraySeq;
        96: invokevirtual #75                 // Method scala/collection/immutable/Set$.apply:(Lscala/collection/immutable/Seq;)Ljava/lang/Object;
        99: checkcast     #77                 // class scala/collection/immutable/Set
       102: putstatic     #79                 // Field modules:Lscala/collection/immutable/Set;
       105: invokedynamic #99,  0             // InvokeDynamic #0:apply:()Lscala/Function1;
       110: putstatic     #101                // Field swap:Lscala/Function1;
       113: return
      LineNumberTable:
        line 6: 0
        line 8: 10
        line 9: 15
        line 11: 20
        line 12: 35
        line 13: 47
        line 14: 59
        line 15: 71
        line 16: 83
        line 11: 102
        line 27: 105
        line 26: 110
        line 6: 113

  public java.lang.String mainLineOrg();
    descriptor: ()Ljava/lang/String;
    flags: (0x0001) ACC_PUBLIC
    Code:
      stack=1, locals=1, args_size=1
         0: getstatic     #32                 // Field mainLineOrg:Ljava/lang/String;
         3: areturn
      LineNumberTable:
        line 8: 0
      LocalVariableTable:
        Start  Length  Slot  Name   Signature
            0       4     0  this   Lcoursier/internal/Typelevel$;

  public java.lang.String typelevelOrg();
    descriptor: ()Ljava/lang/String;
    flags: (0x0001) ACC_PUBLIC
    Code:
      stack=1, locals=1, args_size=1
         0: getstatic     #36                 // Field typelevelOrg:Ljava/lang/String;
         3: areturn
      LineNumberTable:
        line 9: 0
      LocalVariableTable:
        Start  Length  Slot  Name   Signature
            0       4     0  this   Lcoursier/internal/Typelevel$;

  public scala.collection.immutable.Set<coursier.core.ModuleName> modules();
    descriptor: ()Lscala/collection/immutable/Set;
    flags: (0x0001) ACC_PUBLIC
    Code:
      stack=1, locals=1, args_size=1
         0: getstatic     #79                 // Field modules:Lscala/collection/immutable/Set;
         3: areturn
      LineNumberTable:
        line 11: 0
      LocalVariableTable:
        Start  Length  Slot  Name   Signature
            0       4     0  this   Lcoursier/internal/Typelevel$;
    Signature: #105                         // ()Lscala/collection/immutable/Set<Lcoursier/core/ModuleName;>;

  public coursier.core.Module swap(coursier.core.Module);
    descriptor: (Lcoursier/core/Module;)Lcoursier/core/Module;
    flags: (0x0001) ACC_PUBLIC
    Code:
      stack=4, locals=3, args_size=2
         0: aload_1
         1: invokevirtual #112                // Method coursier/core/Module.organization:()Ljava/lang/String;
         4: aload_0
         5: invokevirtual #114                // Method mainLineOrg:()Ljava/lang/String;
         8: astore_2
         9: dup
        10: ifnonnull     21
        13: pop
        14: aload_2
        15: ifnull        28
        18: goto          74
        21: aload_2
        22: invokevirtual #120                // Method java/lang/Object.equals:(Ljava/lang/Object;)Z
        25: ifeq          74
        28: aload_0
        29: invokevirtual #122                // Method modules:()Lscala/collection/immutable/Set;
        32: new           #52                 // class coursier/core/ModuleName
        35: dup
        36: aload_1
        37: invokevirtual #125                // Method coursier/core/Module.name:()Ljava/lang/String;
        40: invokespecial #57                 // Method coursier/core/ModuleName."<init>":(Ljava/lang/String;)V
        43: invokeinterface #127,  2          // InterfaceMethod scala/collection/immutable/Set.apply:(Ljava/lang/Object;)Z
        48: ifeq          74
        51: aload_1
        52: invokevirtual #131                // Method coursier/core/Module.attributes:()Lscala/collection/immutable/Map;
        55: invokeinterface #137,  1          // InterfaceMethod scala/collection/immutable/Map.isEmpty:()Z
        60: ifeq          74
        63: aload_1
        64: aload_0
        65: invokevirtual #139                // Method typelevelOrg:()Ljava/lang/String;
        68: invokevirtual #143                // Method coursier/core/Module.withOrganization:(Ljava/lang/String;)Lcoursier/core/Module;
        71: goto          75
        74: aload_1
        75: areturn
      StackMapTable: number_of_entries = 4
        frame_type = 255 /* full_frame */
          offset_delta = 21
          locals = [ class coursier/internal/Typelevel$, class coursier/core/Module, class java/lang/String ]
          stack = [ class java/lang/String ]
        frame_type = 6 /* same */
        frame_type = 45 /* same */
        frame_type = 64 /* same_locals_1_stack_item */
          stack = [ class coursier/core/Module ]
      LineNumberTable:
        line 21: 0
        line 22: 63
        line 24: 74
      LocalVariableTable:
        Start  Length  Slot  Name   Signature
            0      76     0  this   Lcoursier/internal/Typelevel$;
            0      76     1 module   Lcoursier/core/Module;
    MethodParameters:
      Name                           Flags
      module                         final

  public scala.Function1<coursier.core.Dependency, coursier.core.Dependency> swap();
    descriptor: ()Lscala/Function1;
    flags: (0x0001) ACC_PUBLIC
    Code:
      stack=1, locals=1, args_size=1
         0: getstatic     #101                // Field swap:Lscala/Function1;
         3: areturn
      LineNumberTable:
        line 26: 0
      LocalVariableTable:
        Start  Length  Slot  Name   Signature
            0       4     0  this   Lcoursier/internal/Typelevel$;
    Signature: #145                         // ()Lscala/Function1<Lcoursier/core/Dependency;Lcoursier/core/Dependency;>;

  public static final coursier.core.Dependency $anonfun$swap$1(coursier.core.Dependency);
    descriptor: (Lcoursier/core/Dependency;)Lcoursier/core/Dependency;
    flags: (0x1019) ACC_PUBLIC, ACC_STATIC, ACC_FINAL, ACC_SYNTHETIC
    Code:
      stack=3, locals=1, args_size=1
         0: aload_0
         1: getstatic     #28                 // Field MODULE$:Lcoursier/internal/Typelevel$;
         4: aload_0
         5: invokevirtual #151                // Method coursier/core/Dependency.module:()Lcoursier/core/Module;
         8: invokevirtual #153                // Method swap:(Lcoursier/core/Module;)Lcoursier/core/Module;
        11: invokevirtual #157                // Method coursier/core/Dependency.withModule:(Lcoursier/core/Module;)Lcoursier/core/Dependency;
        14: areturn
      LineNumberTable:
        line 27: 0
      LocalVariableTable:
        Start  Length  Slot  Name   Signature
            0      15     0 dependency   Lcoursier/core/Dependency;
    MethodParameters:
      Name                           Flags
      dependency                     final

  private coursier.internal.Typelevel$();
    descriptor: ()V
    flags: (0x0002) ACC_PRIVATE
    Code:
      stack=1, locals=1, args_size=1
         0: aload_0
         1: invokespecial #159                // Method java/lang/Object."<init>":()V
         4: return
      LineNumberTable:
        line 29: 0
        line 6: 4
      LocalVariableTable:
        Start  Length  Slot  Name   Signature
            0       5     0  this   Lcoursier/internal/Typelevel$;

  private static java.lang.Object $deserializeLambda$(java.lang.invoke.SerializedLambda);
    descriptor: (Ljava/lang/invoke/SerializedLambda;)Ljava/lang/Object;
    flags: (0x100a) ACC_PRIVATE, ACC_STATIC, ACC_SYNTHETIC
    Code:
      stack=1, locals=1, args_size=1
         0: aload_0
         1: invokedynamic #171,  0            // InvokeDynamic #1:lambdaDeserialize:(Ljava/lang/invoke/SerializedLambda;)Ljava/lang/Object;
         6: areturn
}
InnerClasses:
  public static final #10= #7 of #9;      // Lookup=class java/lang/invoke/MethodHandles$Lookup of class java/lang/invoke/MethodHandles
SourceFile: "Typelevel.scala"
BootstrapMethods:
  0: #96 REF_invokeStatic java/lang/invoke/LambdaMetafactory.altMetafactory:(Ljava/lang/invoke/MethodHandles$Lookup;Ljava/lang/String;Ljava/lang/invoke/MethodType;[Ljava/lang/Object;)Ljava/lang/invoke/CallSite;
    Method arguments:
      #81 (Ljava/lang/Object;)Ljava/lang/Object;
      #86 REF_invokeStatic coursier/internal/Typelevel$.$anonfun$swap$1:(Lcoursier/core/Dependency;)Lcoursier/core/Dependency;
      #87 (Lcoursier/core/Dependency;)Lcoursier/core/Dependency;
      #88 5
      #89 1
      #87 (Lcoursier/core/Dependency;)Lcoursier/core/Dependency;
  1: #168 REF_invokeStatic scala/runtime/LambdaDeserialize.bootstrap:(Ljava/lang/invoke/MethodHandles$Lookup;Ljava/lang/String;Ljava/lang/invoke/MethodType;[Ljava/lang/invoke/MethodHandle;)Ljava/lang/invoke/CallSite;
    Method arguments:
      #86 REF_invokeStatic coursier/internal/Typelevel$.$anonfun$swap$1:(Lcoursier/core/Dependency;)Lcoursier/core/Dependency;
  ScalaInlineInfo: length = 0x27 (unknown attribute)
   01 01 00 07 00 52 00 53 01 00 18 00 17 01 00 0D
   00 66 01 00 10 00 68 01 00 13 00 61 01 00 13 00
   6A 01 00 0F 00 66 01
  Scala: length = 0x0 (unknown attribute)

