Classfile /Users/mw/Projects/slang-braindump/.jar/jar11/assemble/slang-braindump/assemble/content/org/sireum/extension/Cancel_Ext$.class
  Last modified May 29, 2022; size 1193 bytes
  SHA-256 checksum 8bf50b2dd85540002fb245689306de6793b0f9b18e10365ca003ac0f0b6eb54f
  Compiled from "Cancel_Ext.scala"
public final class org.sireum.extension.Cancel_Ext$
  minor version: 0
  major version: 52
  flags: (0x0031) ACC_PUBLIC, ACC_FINAL, ACC_SUPER
  this_class: #2                          // org/sireum/extension/Cancel_Ext$
  super_class: #4                         // java/lang/Object
  interfaces: 0, fields: 1, methods: 4, attributes: 3
Constant pool:
   #1 = Utf8               org/sireum/extension/Cancel_Ext$
   #2 = Class              #1             // org/sireum/extension/Cancel_Ext$
   #3 = Utf8               java/lang/Object
   #4 = Class              #3             // java/lang/Object
   #5 = Utf8               Cancel_Ext.scala
   #6 = Utf8               MODULE$
   #7 = Utf8               Lorg/sireum/extension/Cancel_Ext$;
   #8 = Utf8               <clinit>
   #9 = Utf8               ()V
  #10 = Utf8               <init>
  #11 = NameAndType        #10:#9         // "<init>":()V
  #12 = Methodref          #2.#11         // org/sireum/extension/Cancel_Ext$."<init>":()V
  #13 = NameAndType        #6:#7          // MODULE$:Lorg/sireum/extension/Cancel_Ext$;
  #14 = Fieldref           #2.#13         // org/sireum/extension/Cancel_Ext$.MODULE$:Lorg/sireum/extension/Cancel_Ext$;
  #15 = Utf8               handleCancellable
  #16 = Utf8               (Lscala/Function0;)V
  #17 = Utf8               <T:Ljava/lang/Object;>(Lscala/Function0<TT;>;)V
  #18 = Utf8               p
  #19 = Utf8               java/lang/InterruptedException
  #20 = Class              #19            // java/lang/InterruptedException
  #21 = Utf8               java/nio/channels/ClosedByInterruptException
  #22 = Class              #21            // java/nio/channels/ClosedByInterruptException
  #23 = Utf8               scala/Function0
  #24 = Class              #23            // scala/Function0
  #25 = Utf8               apply
  #26 = Utf8               ()Ljava/lang/Object;
  #27 = NameAndType        #25:#26        // apply:()Ljava/lang/Object;
  #28 = InterfaceMethodref #24.#27        // scala/Function0.apply:()Ljava/lang/Object;
  #29 = Utf8               this
  #30 = Utf8               Lscala/Function0;
  #31 = Utf8               cancellable
  #32 = Utf8               (Lscala/Function0;)Ljava/lang/Object;
  #33 = Utf8               <T:Ljava/lang/Object;>(Lscala/Function0<TT;>;)TT;
  #34 = Utf8               java/lang/Thread
  #35 = Class              #34            // java/lang/Thread
  #36 = Utf8               interrupted
  #37 = Utf8               ()Z
  #38 = NameAndType        #36:#37        // interrupted:()Z
  #39 = Methodref          #35.#38        // java/lang/Thread.interrupted:()Z
  #40 = Methodref          #20.#11        // java/lang/InterruptedException."<init>":()V
  #41 = Methodref          #4.#11         // java/lang/Object."<init>":()V
  #42 = Utf8               Code
  #43 = Utf8               LineNumberTable
  #44 = Utf8               StackMapTable
  #45 = Utf8               LocalVariableTable
  #46 = Utf8               Signature
  #47 = Utf8               MethodParameters
  #48 = Utf8               SourceFile
  #49 = Utf8               ScalaInlineInfo
  #50 = Utf8               Scala
{
  public static final org.sireum.extension.Cancel_Ext$ MODULE$;
    descriptor: Lorg/sireum/extension/Cancel_Ext$;
    flags: (0x0019) ACC_PUBLIC, ACC_STATIC, ACC_FINAL

  public static {};
    descriptor: ()V
    flags: (0x0009) ACC_PUBLIC, ACC_STATIC
    Code:
      stack=2, locals=0, args_size=0
         0: new           #2                  // class org/sireum/extension/Cancel_Ext$
         3: dup
         4: invokespecial #12                 // Method "<init>":()V
         7: putstatic     #14                 // Field MODULE$:Lorg/sireum/extension/Cancel_Ext$;
        10: return
      LineNumberTable:
        line 29: 0

  public <T extends java.lang.Object> void handleCancellable(scala.Function0<T>);
    descriptor: (Lscala/Function0;)V
    flags: (0x0001) ACC_PUBLIC
    Code:
      stack=1, locals=2, args_size=2
         0: aload_1
         1: invokeinterface #28,  1           // InterfaceMethod scala/Function0.apply:()Ljava/lang/Object;
         6: pop
         7: goto          18
        10: pop
        11: goto          18
        14: pop
        15: goto          18
        18: return
      Exception table:
         from    to  target type
             0     7    10   Class java/lang/InterruptedException
             0     7    14   Class java/nio/channels/ClosedByInterruptException
      StackMapTable: number_of_entries = 3
        frame_type = 74 /* same_locals_1_stack_item */
          stack = [ class java/lang/InterruptedException ]
        frame_type = 67 /* same_locals_1_stack_item */
          stack = [ class java/nio/channels/ClosedByInterruptException ]
        frame_type = 3 /* same */
      LineNumberTable:
        line 31: 0
        line 33: 11
        line 34: 15
      LocalVariableTable:
        Start  Length  Slot  Name   Signature
            0      19     0  this   Lorg/sireum/extension/Cancel_Ext$;
            0      19     1     p   Lscala/Function0;
    Signature: #17                          // <T:Ljava/lang/Object;>(Lscala/Function0<TT;>;)V
    MethodParameters:
      Name                           Flags
      p                              final

  public <T extends java.lang.Object> T cancellable(scala.Function0<T>);
    descriptor: (Lscala/Function0;)Ljava/lang/Object;
    flags: (0x0001) ACC_PUBLIC
    Code:
      stack=2, locals=2, args_size=2
         0: invokestatic  #39                 // Method java/lang/Thread.interrupted:()Z
         3: ifeq          14
         6: new           #20                 // class java/lang/InterruptedException
         9: dup
        10: invokespecial #40                 // Method java/lang/InterruptedException."<init>":()V
        13: athrow
        14: aload_1
        15: invokeinterface #28,  1           // InterfaceMethod scala/Function0.apply:()Ljava/lang/Object;
        20: areturn
      StackMapTable: number_of_entries = 1
        frame_type = 14 /* same */
      LineNumberTable:
        line 38: 0
        line 39: 6
        line 41: 14
      LocalVariableTable:
        Start  Length  Slot  Name   Signature
            0      21     0  this   Lorg/sireum/extension/Cancel_Ext$;
            0      21     1     p   Lscala/Function0;
    Signature: #33                          // <T:Ljava/lang/Object;>(Lscala/Function0<TT;>;)TT;
    MethodParameters:
      Name                           Flags
      p                              final

  private org.sireum.extension.Cancel_Ext$();
    descriptor: ()V
    flags: (0x0002) ACC_PRIVATE
    Code:
      stack=1, locals=1, args_size=1
         0: aload_0
         1: invokespecial #41                 // Method java/lang/Object."<init>":()V
         4: return
      LineNumberTable:
        line 29: 0
      LocalVariableTable:
        Start  Length  Slot  Name   Signature
            0       5     0  this   Lorg/sireum/extension/Cancel_Ext$;
}
SourceFile: "Cancel_Ext.scala"
  ScalaInlineInfo: length = 0x13 (unknown attribute)
   01 01 00 03 00 0A 00 09 01 00 1F 00 20 01 00 0F
   00 10 01
  Scala: length = 0x0 (unknown attribute)

