Classfile /Users/mw/Projects/slang-braindump/.jar/jar11/assemble/slang-braindump/assemble/content/org/sireum/extension/Cancel$.class
  Last modified May 29, 2022; size 1061 bytes
  SHA-256 checksum 16389fd93f8a37bcc8491d848fec72c5004a5c1baf2c0f694dc74da1b6c82df3
  Compiled from "Cancel.scala"
public final class org.sireum.extension.Cancel$
  minor version: 0
  major version: 52
  flags: (0x0031) ACC_PUBLIC, ACC_FINAL, ACC_SUPER
  this_class: #2                          // org/sireum/extension/Cancel$
  super_class: #4                         // java/lang/Object
  interfaces: 0, fields: 1, methods: 4, attributes: 3
Constant pool:
   #1 = Utf8               org/sireum/extension/Cancel$
   #2 = Class              #1             // org/sireum/extension/Cancel$
   #3 = Utf8               java/lang/Object
   #4 = Class              #3             // java/lang/Object
   #5 = Utf8               Cancel.scala
   #6 = Utf8               MODULE$
   #7 = Utf8               Lorg/sireum/extension/Cancel$;
   #8 = Utf8               <clinit>
   #9 = Utf8               ()V
  #10 = Utf8               <init>
  #11 = NameAndType        #10:#9         // "<init>":()V
  #12 = Methodref          #2.#11         // org/sireum/extension/Cancel$."<init>":()V
  #13 = NameAndType        #6:#7          // MODULE$:Lorg/sireum/extension/Cancel$;
  #14 = Fieldref           #2.#13         // org/sireum/extension/Cancel$.MODULE$:Lorg/sireum/extension/Cancel$;
  #15 = Utf8               handleCancellable
  #16 = Utf8               (Lscala/Function0;)V
  #17 = Utf8               <T:Ljava/lang/Object;>(Lscala/Function0<TT;>;)V
  #18 = Utf8               p
  #19 = Utf8               org/sireum/extension/Cancel_Ext$
  #20 = Class              #19            // org/sireum/extension/Cancel_Ext$
  #21 = Utf8               Lorg/sireum/extension/Cancel_Ext$;
  #22 = NameAndType        #6:#21         // MODULE$:Lorg/sireum/extension/Cancel_Ext$;
  #23 = Fieldref           #20.#22        // org/sireum/extension/Cancel_Ext$.MODULE$:Lorg/sireum/extension/Cancel_Ext$;
  #24 = NameAndType        #15:#16        // handleCancellable:(Lscala/Function0;)V
  #25 = Methodref          #20.#24        // org/sireum/extension/Cancel_Ext$.handleCancellable:(Lscala/Function0;)V
  #26 = Utf8               scala/runtime/BoxedUnit
  #27 = Class              #26            // scala/runtime/BoxedUnit
  #28 = Utf8               UNIT
  #29 = Utf8               Lscala/runtime/BoxedUnit;
  #30 = NameAndType        #28:#29        // UNIT:Lscala/runtime/BoxedUnit;
  #31 = Fieldref           #27.#30        // scala/runtime/BoxedUnit.UNIT:Lscala/runtime/BoxedUnit;
  #32 = Utf8               this
  #33 = Utf8               Lscala/Function0;
  #34 = Utf8               cancellable
  #35 = Utf8               (Lscala/Function0;)Ljava/lang/Object;
  #36 = Utf8               <T:Ljava/lang/Object;>(Lscala/Function0<TT;>;)TT;
  #37 = NameAndType        #34:#35        // cancellable:(Lscala/Function0;)Ljava/lang/Object;
  #38 = Methodref          #20.#37        // org/sireum/extension/Cancel_Ext$.cancellable:(Lscala/Function0;)Ljava/lang/Object;
  #39 = Methodref          #4.#11         // java/lang/Object."<init>":()V
  #40 = Utf8               Code
  #41 = Utf8               LineNumberTable
  #42 = Utf8               LocalVariableTable
  #43 = Utf8               Signature
  #44 = Utf8               MethodParameters
  #45 = Utf8               SourceFile
  #46 = Utf8               ScalaInlineInfo
  #47 = Utf8               Scala
{
  public static final org.sireum.extension.Cancel$ MODULE$;
    descriptor: Lorg/sireum/extension/Cancel$;
    flags: (0x0019) ACC_PUBLIC, ACC_STATIC, ACC_FINAL

  public static {};
    descriptor: ()V
    flags: (0x0009) ACC_PUBLIC, ACC_STATIC
    Code:
      stack=2, locals=0, args_size=0
         0: new           #2                  // class org/sireum/extension/Cancel$
         3: dup
         4: invokespecial #12                 // Method "<init>":()V
         7: putstatic     #14                 // Field MODULE$:Lorg/sireum/extension/Cancel$;
        10: return
      LineNumberTable:
        line 30: 0

  public <T extends java.lang.Object> void handleCancellable(scala.Function0<T>);
    descriptor: (Lscala/Function0;)V
    flags: (0x0001) ACC_PUBLIC
    Code:
      stack=2, locals=2, args_size=2
         0: getstatic     #23                 // Field org/sireum/extension/Cancel_Ext$.MODULE$:Lorg/sireum/extension/Cancel_Ext$;
         3: aload_1
         4: invokevirtual #25                 // Method org/sireum/extension/Cancel_Ext$.handleCancellable:(Lscala/Function0;)V
         7: getstatic     #31                 // Field scala/runtime/BoxedUnit.UNIT:Lscala/runtime/BoxedUnit;
        10: pop
        11: return
      LineNumberTable:
        line 31: 0
      LocalVariableTable:
        Start  Length  Slot  Name   Signature
            0      12     0  this   Lorg/sireum/extension/Cancel$;
            0      12     1     p   Lscala/Function0;
    Signature: #17                          // <T:Ljava/lang/Object;>(Lscala/Function0<TT;>;)V
    MethodParameters:
      Name                           Flags
      p                              final

  public <T extends java.lang.Object> T cancellable(scala.Function0<T>);
    descriptor: (Lscala/Function0;)Ljava/lang/Object;
    flags: (0x0001) ACC_PUBLIC
    Code:
      stack=2, locals=2, args_size=2
         0: getstatic     #23                 // Field org/sireum/extension/Cancel_Ext$.MODULE$:Lorg/sireum/extension/Cancel_Ext$;
         3: aload_1
         4: invokevirtual #38                 // Method org/sireum/extension/Cancel_Ext$.cancellable:(Lscala/Function0;)Ljava/lang/Object;
         7: areturn
      LineNumberTable:
        line 32: 0
      LocalVariableTable:
        Start  Length  Slot  Name   Signature
            0       8     0  this   Lorg/sireum/extension/Cancel$;
            0       8     1     p   Lscala/Function0;
    Signature: #36                          // <T:Ljava/lang/Object;>(Lscala/Function0<TT;>;)TT;
    MethodParameters:
      Name                           Flags
      p                              final

  private org.sireum.extension.Cancel$();
    descriptor: ()V
    flags: (0x0002) ACC_PRIVATE
    Code:
      stack=1, locals=1, args_size=1
         0: aload_0
         1: invokespecial #39                 // Method java/lang/Object."<init>":()V
         4: return
      LineNumberTable:
        line 30: 0
      LocalVariableTable:
        Start  Length  Slot  Name   Signature
            0       5     0  this   Lorg/sireum/extension/Cancel$;
}
SourceFile: "Cancel.scala"
  ScalaInlineInfo: length = 0x13 (unknown attribute)
   01 01 00 03 00 0A 00 09 01 00 22 00 23 01 00 0F
   00 10 01
  Scala: length = 0x0 (unknown attribute)

