Classfile /Users/mw/Projects/slang-braindump/.jar/jar11/assemble/slang-braindump/assemble/content/org/sireum/extension/Console.class
  Last modified May 29, 2022; size 1227 bytes
  SHA-256 checksum 94b4d87dad55bebf3b5e038469a31d7079f641eb725c84cdcf0930c047cca999
  Compiled from "Console.scala"
public final class org.sireum.extension.Console
  minor version: 0
  major version: 52
  flags: (0x0031) ACC_PUBLIC, ACC_FINAL, ACC_SUPER
  this_class: #2                          // org/sireum/extension/Console
  super_class: #4                         // java/lang/Object
  interfaces: 0, fields: 0, methods: 2, attributes: 4
Constant pool:
   #1 = Utf8               org/sireum/extension/Console
   #2 = Class              #1             // org/sireum/extension/Console
   #3 = Utf8               java/lang/Object
   #4 = Class              #3             // java/lang/Object
   #5 = Utf8               Console.scala
   #6 = Utf8               Lscala/reflect/ScalaSignature;
   #7 = Utf8               bytes
   #8 = Utf8               \u0006\u0005Y;Q!\u0003\u0006\t\u0002E1Qa\u0005\u0006\t\u0002QAQaG\u0001\u0005\u0002qAQ!H\u0001\u0005\u0002yAQ\u0001K\u0001\u0005\u0002%:QaK\u0001\t\u000212QAL\u0001\t\u0002=BQa\u0007\u0004\u0005\u0002ABQ\u0001\u000b\u0004\u0005\u0002E\nqaQ8og>dWM\u0003\u0002\f\u0019\u0005IQ\r\u001f;f]NLwN\u001c\u0006\u0003\u001b9\taa]5sKVl\'\"A\b\u0002\u0007=\u0014xm\u0001\u0001\u0011\u0005I\tQ\"\u0001\u0006\u0003\u000f\r{gn]8mKN\u0011\u0011!\u0006\t\u0003-ei\u0011a\u0006\u0006\u00021\u0005)1oY1mC&\u0011!d\u0006\u0002\u0007\u0003:L(+\u001a4\u0002\rqJg.\u001b;?)\u0005\t\u0012!\u00029bkN,GCA\u0010#!\t1\u0002%\u0003\u0002\"/\t!QK\\5u\u0011\u0015\u00193\u00011\u0001%\u0003\u0019\u0001(o\\7qiB\u0011QEJ\u0007\u0002\u0019%\u0011q\u0005\u0004\u0002\u0007\'R\u0014\u0018N\\4\u0002\u0011I,\u0017\r\u001a\'j]\u0016$\"\u0001\n\u0016\t\u000b\r\"\u0001\u0019\u0001\u0013\u0002\u0007\u0015CH\u000f\u0005\u0002.\r5\t\u0011AA\u0002FqR\u001c\"AB\u000b\u0015\u00031\"\u0012\u0001\n\u0015\u0004\rM2\u0004CA\u00135\u0013\t)DBA\u0002fqR\fDa\b\u00138#F*1\u0005O\u001eFyQ\u0011A%\u000f\u0005\u0006u\u0001\u0001\raP\u0001\u0002g&\u0011A(P\u0001\u0006CB\u0004H.\u001f\u0006\u0003}1\taa\u0015;sS:<\u0007C\u0001!D\u001d\t1\u0012)\u0003\u0002C/\u00051\u0001K]3eK\u001aL!a\n#\u000b\u0005\t;\u0012\'B\u0012G\u001d>sdBA$O\u001d\tAUJ\u0004\u0002J\u00196\t!J\u0003\u0002L!\u00051AH]8pizJ\u0011aD\u0005\u0003\u001b9I!A\u0010\u00072\u000b\r:U\nU\u00072\t\u0011BEjD\u0019\u0004KI\u001bv\"A*\"\u0003Q\u000b1bQ8og>dWmX#yi\"\u001aQa\r\u001c
   #9 = Utf8               org/sireum/extension/Console$Ext$
  #10 = Class              #9             // org/sireum/extension/Console$Ext$
  #11 = Utf8               Ext$
  #12 = Utf8               readLine
  #13 = Utf8               (Ljava/lang/String;)Ljava/lang/String;
  #14 = Utf8               prompt
  #15 = Utf8               org/sireum/extension/Console$
  #16 = Class              #15            // org/sireum/extension/Console$
  #17 = Utf8               MODULE$
  #18 = Utf8               Lorg/sireum/extension/Console$;
  #19 = NameAndType        #17:#18        // MODULE$:Lorg/sireum/extension/Console$;
  #20 = Fieldref           #16.#19        // org/sireum/extension/Console$.MODULE$:Lorg/sireum/extension/Console$;
  #21 = NameAndType        #12:#13        // readLine:(Ljava/lang/String;)Ljava/lang/String;
  #22 = Methodref          #16.#21        // org/sireum/extension/Console$.readLine:(Ljava/lang/String;)Ljava/lang/String;
  #23 = Utf8               Ljava/lang/String;
  #24 = Utf8               pause
  #25 = Utf8               (Ljava/lang/String;)V
  #26 = NameAndType        #24:#25        // pause:(Ljava/lang/String;)V
  #27 = Methodref          #16.#26        // org/sireum/extension/Console$.pause:(Ljava/lang/String;)V
  #28 = Utf8               Code
  #29 = Utf8               LocalVariableTable
  #30 = Utf8               MethodParameters
  #31 = Utf8               InnerClasses
  #32 = Utf8               SourceFile
  #33 = Utf8               RuntimeVisibleAnnotations
  #34 = Utf8               ScalaSig
{
  public static java.lang.String readLine(java.lang.String);
    descriptor: (Ljava/lang/String;)Ljava/lang/String;
    flags: (0x0009) ACC_PUBLIC, ACC_STATIC
    Code:
      stack=2, locals=1, args_size=1
         0: getstatic     #20                 // Field org/sireum/extension/Console$.MODULE$:Lorg/sireum/extension/Console$;
         3: aload_0
         4: invokevirtual #22                 // Method org/sireum/extension/Console$.readLine:(Ljava/lang/String;)Ljava/lang/String;
         7: areturn
      LocalVariableTable:
        Start  Length  Slot  Name   Signature
            0       8     0 prompt   Ljava/lang/String;
    MethodParameters:
      Name                           Flags
      prompt                         final

  public static void pause(java.lang.String);
    descriptor: (Ljava/lang/String;)V
    flags: (0x0009) ACC_PUBLIC, ACC_STATIC
    Code:
      stack=2, locals=1, args_size=1
         0: getstatic     #20                 // Field org/sireum/extension/Console$.MODULE$:Lorg/sireum/extension/Console$;
         3: aload_0
         4: invokevirtual #27                 // Method org/sireum/extension/Console$.pause:(Ljava/lang/String;)V
         7: return
      LocalVariableTable:
        Start  Length  Slot  Name   Signature
            0       8     0 prompt   Ljava/lang/String;
    MethodParameters:
      Name                           Flags
      prompt                         final
}
InnerClasses:
  public static #11= #10 of #2;           // Ext$=class org/sireum/extension/Console$Ext$ of class org/sireum/extension/Console
SourceFile: "Console.scala"
RuntimeVisibleAnnotations:
  0: #6(#7=s#8)
    scala.reflect.ScalaSignature(
      bytes="\u0006\u0005Y;Q!\u0003\u0006\t\u0002E1Qa\u0005\u0006\t\u0002QAQaG\u0001\u0005\u0002qAQ!H\u0001\u0005\u0002yAQ\u0001K\u0001\u0005\u0002%:QaK\u0001\t\u000212QAL\u0001\t\u0002=BQa\u0007\u0004\u0005\u0002ABQ\u0001\u000b\u0004\u0005\u0002E\nqaQ8og>dWM\u0003\u0002\f\u0019\u0005IQ\r\u001f;f]NLwN\u001c\u0006\u0003\u001b9\taa]5sKVl\'\"A\b\u0002\u0007=\u0014xm\u0001\u0001\u0011\u0005I\tQ\"\u0001\u0006\u0003\u000f\r{gn]8mKN\u0011\u0011!\u0006\t\u0003-ei\u0011a\u0006\u0006\u00021\u0005)1oY1mC&\u0011!d\u0006\u0002\u0007\u0003:L(+\u001a4\u0002\rqJg.\u001b;?)\u0005\t\u0012!\u00029bkN,GCA\u0010#!\t1\u0002%\u0003\u0002\"/\t!QK\\5u\u0011\u0015\u00193\u00011\u0001%\u0003\u0019\u0001(o\\7qiB\u0011QEJ\u0007\u0002\u0019%\u0011q\u0005\u0004\u0002\u0007\'R\u0014\u0018N\\4\u0002\u0011I,\u0017\r\u001a\'j]\u0016$\"\u0001\n\u0016\t\u000b\r\"\u0001\u0019\u0001\u0013\u0002\u0007\u0015CH\u000f\u0005\u0002.\r5\t\u0011AA\u0002FqR\u001c\"AB\u000b\u0015\u00031\"\u0012\u0001\n\u0015\u0004\rM2\u0004CA\u00135\u0013\t)DBA\u0002fqR\fDa\b\u00138#F*1\u0005O\u001eFyQ\u0011A%\u000f\u0005\u0006u\u0001\u0001\raP\u0001\u0002g&\u0011A(P\u0001\u0006CB\u0004H.\u001f\u0006\u0003}1\taa\u0015;sS:<\u0007C\u0001!D\u001d\t1\u0012)\u0003\u0002C/\u00051\u0001K]3eK\u001aL!a\n#\u000b\u0005\t;\u0012\'B\u0012G\u001d>sdBA$O\u001d\tAUJ\u0004\u0002J\u00196\t!J\u0003\u0002L!\u00051AH]8pizJ\u0011aD\u0005\u0003\u001b9I!A\u0010\u00072\u000b\r:U\nU\u00072\t\u0011BEjD\u0019\u0004KI\u001bv\"A*\"\u0003Q\u000b1bQ8og>dWmX#yi\"\u001aQa\r\u001c"
    )
  ScalaSig: length = 0x3 (unknown attribute)
   05 02 00
