Classfile /Users/mw/Projects/slang-braindump/.jar/jar11/assemble/slang-braindump/assemble/content/org/sireum/extension/Time$.class
  Last modified May 29, 2022; size 616 bytes
  SHA-256 checksum 8e0fb219ba57449fa65c85ffea312be9dde9efb551064f3bf8727f409f85a47b
  Compiled from "Time.scala"
public final class org.sireum.extension.Time$
  minor version: 0
  major version: 52
  flags: (0x0031) ACC_PUBLIC, ACC_FINAL, ACC_SUPER
  this_class: #2                          // org/sireum/extension/Time$
  super_class: #4                         // java/lang/Object
  interfaces: 0, fields: 1, methods: 3, attributes: 3
Constant pool:
   #1 = Utf8               org/sireum/extension/Time$
   #2 = Class              #1             // org/sireum/extension/Time$
   #3 = Utf8               java/lang/Object
   #4 = Class              #3             // java/lang/Object
   #5 = Utf8               Time.scala
   #6 = Utf8               MODULE$
   #7 = Utf8               Lorg/sireum/extension/Time$;
   #8 = Utf8               <clinit>
   #9 = Utf8               ()V
  #10 = Utf8               <init>
  #11 = NameAndType        #10:#9         // "<init>":()V
  #12 = Methodref          #2.#11         // org/sireum/extension/Time$."<init>":()V
  #13 = NameAndType        #6:#7          // MODULE$:Lorg/sireum/extension/Time$;
  #14 = Fieldref           #2.#13         // org/sireum/extension/Time$.MODULE$:Lorg/sireum/extension/Time$;
  #15 = Utf8               currentMillis
  #16 = Utf8               ()Lorg/sireum/Z;
  #17 = Utf8               org/sireum/extension/Time_Ext$
  #18 = Class              #17            // org/sireum/extension/Time_Ext$
  #19 = Utf8               Lorg/sireum/extension/Time_Ext$;
  #20 = NameAndType        #6:#19         // MODULE$:Lorg/sireum/extension/Time_Ext$;
  #21 = Fieldref           #18.#20        // org/sireum/extension/Time_Ext$.MODULE$:Lorg/sireum/extension/Time_Ext$;
  #22 = NameAndType        #15:#16        // currentMillis:()Lorg/sireum/Z;
  #23 = Methodref          #18.#22        // org/sireum/extension/Time_Ext$.currentMillis:()Lorg/sireum/Z;
  #24 = Utf8               this
  #25 = Methodref          #4.#11         // java/lang/Object."<init>":()V
  #26 = Utf8               Code
  #27 = Utf8               LineNumberTable
  #28 = Utf8               LocalVariableTable
  #29 = Utf8               SourceFile
  #30 = Utf8               ScalaInlineInfo
  #31 = Utf8               Scala
{
  public static final org.sireum.extension.Time$ MODULE$;
    descriptor: Lorg/sireum/extension/Time$;
    flags: (0x0019) ACC_PUBLIC, ACC_STATIC, ACC_FINAL

  public static {};
    descriptor: ()V
    flags: (0x0009) ACC_PUBLIC, ACC_STATIC
    Code:
      stack=2, locals=0, args_size=0
         0: new           #2                  // class org/sireum/extension/Time$
         3: dup
         4: invokespecial #12                 // Method "<init>":()V
         7: putstatic     #14                 // Field MODULE$:Lorg/sireum/extension/Time$;
        10: return
      LineNumberTable:
        line 30: 0

  public org.sireum.Z currentMillis();
    descriptor: ()Lorg/sireum/Z;
    flags: (0x0001) ACC_PUBLIC
    Code:
      stack=1, locals=1, args_size=1
         0: getstatic     #21                 // Field org/sireum/extension/Time_Ext$.MODULE$:Lorg/sireum/extension/Time_Ext$;
         3: invokevirtual #23                 // Method org/sireum/extension/Time_Ext$.currentMillis:()Lorg/sireum/Z;
         6: areturn
      LineNumberTable:
        line 31: 0
      LocalVariableTable:
        Start  Length  Slot  Name   Signature
            0       7     0  this   Lorg/sireum/extension/Time$;

  private org.sireum.extension.Time$();
    descriptor: ()V
    flags: (0x0002) ACC_PRIVATE
    Code:
      stack=1, locals=1, args_size=1
         0: aload_0
         1: invokespecial #25                 // Method java/lang/Object."<init>":()V
         4: return
      LineNumberTable:
        line 30: 0
      LocalVariableTable:
        Start  Length  Slot  Name   Signature
            0       5     0  this   Lorg/sireum/extension/Time$;
}
SourceFile: "Time.scala"
  ScalaInlineInfo: length = 0xE (unknown attribute)
   01 01 00 02 00 0A 00 09 01 00 0F 00 10 01
  Scala: length = 0x0 (unknown attribute)

