Classfile /Users/mw/Projects/slang-braindump/.jar/jar11/assemble/slang-braindump/assemble/content/org/sireum/extension/Time_Ext.class
  Last modified May 29, 2022; size 600 bytes
  SHA-256 checksum c10e15b04e24e1b586fca433dd50958e48397e7d846c2dde59ba93ce31c68cd8
  Compiled from "Time_Ext.scala"
public final class org.sireum.extension.Time_Ext
  minor version: 0
  major version: 52
  flags: (0x0031) ACC_PUBLIC, ACC_FINAL, ACC_SUPER
  this_class: #2                          // org/sireum/extension/Time_Ext
  super_class: #4                         // java/lang/Object
  interfaces: 0, fields: 0, methods: 1, attributes: 3
Constant pool:
   #1 = Utf8               org/sireum/extension/Time_Ext
   #2 = Class              #1             // org/sireum/extension/Time_Ext
   #3 = Utf8               java/lang/Object
   #4 = Class              #3             // java/lang/Object
   #5 = Utf8               Time_Ext.scala
   #6 = Utf8               Lscala/reflect/ScalaSignature;
   #7 = Utf8               bytes
   #8 = Utf8               \u0006\u0005y9Q\u0001B\u0003\t\u000211QAD\u0003\t\u0002=AQAF\u0001\u0005\u0002]AQ\u0001G\u0001\u0005\u0002e\t\u0001\u0002V5nK~+\u0005\u0010\u001e\u0006\u0003\r\u001d\t\u0011\"\u001a=uK:\u001c\u0018n\u001c8\u000b\u0005!I\u0011AB:je\u0016,XNC\u0001\u000b\u0003\ry\'oZ\u0002\u0001!\ti\u0011!D\u0001\u0006\u0005!!\u0016.\\3`\u000bb$8CA\u0001\u0011!\t\tB#D\u0001\u0013\u0015\u0005\u0019\u0012!B:dC2\f\u0017BA\u000b\u0013\u0005\u0019\te.\u001f*fM\u00061A(\u001b8jiz\"\u0012\u0001D\u0001\u000eGV\u0014(/\u001a8u\u001b&dG.[:\u0016\u0003i\u0001\"a\u0007\u000f\u000e\u0003\u001dI!!H\u0004\u0003\u0003i\u0003
   #9 = Utf8               currentMillis
  #10 = Utf8               ()Lorg/sireum/Z;
  #11 = Utf8               org/sireum/extension/Time_Ext$
  #12 = Class              #11            // org/sireum/extension/Time_Ext$
  #13 = Utf8               MODULE$
  #14 = Utf8               Lorg/sireum/extension/Time_Ext$;
  #15 = NameAndType        #13:#14        // MODULE$:Lorg/sireum/extension/Time_Ext$;
  #16 = Fieldref           #12.#15        // org/sireum/extension/Time_Ext$.MODULE$:Lorg/sireum/extension/Time_Ext$;
  #17 = NameAndType        #9:#10         // currentMillis:()Lorg/sireum/Z;
  #18 = Methodref          #12.#17        // org/sireum/extension/Time_Ext$.currentMillis:()Lorg/sireum/Z;
  #19 = Utf8               Code
  #20 = Utf8               SourceFile
  #21 = Utf8               RuntimeVisibleAnnotations
  #22 = Utf8               ScalaSig
{
  public static org.sireum.Z currentMillis();
    descriptor: ()Lorg/sireum/Z;
    flags: (0x0009) ACC_PUBLIC, ACC_STATIC
    Code:
      stack=1, locals=0, args_size=0
         0: getstatic     #16                 // Field org/sireum/extension/Time_Ext$.MODULE$:Lorg/sireum/extension/Time_Ext$;
         3: invokevirtual #18                 // Method org/sireum/extension/Time_Ext$.currentMillis:()Lorg/sireum/Z;
         6: areturn
}
SourceFile: "Time_Ext.scala"
RuntimeVisibleAnnotations:
  0: #6(#7=s#8)
    scala.reflect.ScalaSignature(
      bytes="\u0006\u0005y9Q\u0001B\u0003\t\u000211QAD\u0003\t\u0002=AQAF\u0001\u0005\u0002]AQ\u0001G\u0001\u0005\u0002e\t\u0001\u0002V5nK~+\u0005\u0010\u001e\u0006\u0003\r\u001d\t\u0011\"\u001a=uK:\u001c\u0018n\u001c8\u000b\u0005!I\u0011AB:je\u0016,XNC\u0001\u000b\u0003\ry\'oZ\u0002\u0001!\ti\u0011!D\u0001\u0006\u0005!!\u0016.\\3`\u000bb$8CA\u0001\u0011!\t\tB#D\u0001\u0013\u0015\u0005\u0019\u0012!B:dC2\f\u0017BA\u000b\u0013\u0005\u0019\te.\u001f*fM\u00061A(\u001b8jiz\"\u0012\u0001D\u0001\u000eGV\u0014(/\u001a8u\u001b&dG.[:\u0016\u0003i\u0001\"a\u0007\u000f\u000e\u0003\u001dI!!H\u0004\u0003\u0003i\u0003"
    )
  ScalaSig: length = 0x3 (unknown attribute)
   05 02 00
