Classfile /Users/mw/Projects/slang-braindump/.jar/jar11/assemble/slang-braindump/assemble/content/coursier/util/shaded/org/jsoup/parser/HtmlTreeBuilderState$16.class
  Last modified May 29, 2022; size 5008 bytes
  SHA-256 checksum c30972a36da5c7d3c76e7b0963c524b35e80ab97d9bd601b984ac3c340013b52
  Compiled from "HtmlTreeBuilderState.java"
final class coursier.util.shaded.org.jsoup.parser.HtmlTreeBuilderState$16 extends coursier.util.shaded.org.jsoup.parser.HtmlTreeBuilderState
  minor version: 0
  major version: 51
  flags: (0x4030) ACC_FINAL, ACC_SUPER, ACC_ENUM
  this_class: #2                          // coursier/util/shaded/org/jsoup/parser/HtmlTreeBuilderState$16
  super_class: #4                         // coursier/util/shaded/org/jsoup/parser/HtmlTreeBuilderState
  interfaces: 0, fields: 0, methods: 3, attributes: 3
Constant pool:
    #1 = Utf8               coursier/util/shaded/org/jsoup/parser/HtmlTreeBuilderState$16
    #2 = Class              #1            // coursier/util/shaded/org/jsoup/parser/HtmlTreeBuilderState$16
    #3 = Utf8               coursier/util/shaded/org/jsoup/parser/HtmlTreeBuilderState
    #4 = Class              #3            // coursier/util/shaded/org/jsoup/parser/HtmlTreeBuilderState
    #5 = Utf8               HtmlTreeBuilderState.java
    #6 = Utf8               coursier/util/shaded/org/jsoup/parser/HtmlTreeBuilderState$1
    #7 = Class              #6            // coursier/util/shaded/org/jsoup/parser/HtmlTreeBuilderState$1
    #8 = Utf8               coursier/util/shaded/org/jsoup/parser/HtmlTreeBuilderState$24
    #9 = Class              #8            // coursier/util/shaded/org/jsoup/parser/HtmlTreeBuilderState$24
   #10 = Utf8               coursier/util/shaded/org/jsoup/parser/Token$TokenType
   #11 = Class              #10           // coursier/util/shaded/org/jsoup/parser/Token$TokenType
   #12 = Utf8               coursier/util/shaded/org/jsoup/parser/Token
   #13 = Class              #12           // coursier/util/shaded/org/jsoup/parser/Token
   #14 = Utf8               TokenType
   #15 = Utf8               coursier/util/shaded/org/jsoup/parser/Token$Character
   #16 = Class              #15           // coursier/util/shaded/org/jsoup/parser/Token$Character
   #17 = Utf8               Character
   #18 = Utf8               coursier/util/shaded/org/jsoup/parser/Token$Comment
   #19 = Class              #18           // coursier/util/shaded/org/jsoup/parser/Token$Comment
   #20 = Utf8               Comment
   #21 = Utf8               coursier/util/shaded/org/jsoup/parser/Token$StartTag
   #22 = Class              #21           // coursier/util/shaded/org/jsoup/parser/Token$StartTag
   #23 = Utf8               StartTag
   #24 = Utf8               coursier/util/shaded/org/jsoup/parser/HtmlTreeBuilderState$Constants
   #25 = Class              #24           // coursier/util/shaded/org/jsoup/parser/HtmlTreeBuilderState$Constants
   #26 = Utf8               Constants
   #27 = Utf8               coursier/util/shaded/org/jsoup/parser/Token$EndTag
   #28 = Class              #27           // coursier/util/shaded/org/jsoup/parser/Token$EndTag
   #29 = Utf8               EndTag
   #30 = Utf8               <init>
   #31 = Utf8               (Ljava/lang/String;I)V
   #32 = Utf8               (Ljava/lang/String;ILcoursier/util/shaded/org/jsoup/parser/HtmlTreeBuilderState$1;)V
   #33 = NameAndType        #30:#32       // "<init>":(Ljava/lang/String;ILcoursier/util/shaded/org/jsoup/parser/HtmlTreeBuilderState$1;)V
   #34 = Methodref          #4.#33        // coursier/util/shaded/org/jsoup/parser/HtmlTreeBuilderState."<init>":(Ljava/lang/String;ILcoursier/util/shaded/org/jsoup/parser/HtmlTreeBuilderState$1;)V
   #35 = Utf8               this
   #36 = Utf8               Lcoursier/util/shaded/org/jsoup/parser/HtmlTreeBuilderState$16;
   #37 = Utf8               process
   #38 = Utf8               (Lcoursier/util/shaded/org/jsoup/parser/Token;Lcoursier/util/shaded/org/jsoup/parser/HtmlTreeBuilder;)Z
   #39 = Utf8               $SwitchMap$org$jsoup$parser$Token$TokenType
   #40 = Utf8               [I
   #41 = NameAndType        #39:#40       // $SwitchMap$org$jsoup$parser$Token$TokenType:[I
   #42 = Fieldref           #9.#41        // coursier/util/shaded/org/jsoup/parser/HtmlTreeBuilderState$24.$SwitchMap$org$jsoup$parser$Token$TokenType:[I
   #43 = Utf8               type
   #44 = Utf8               Lcoursier/util/shaded/org/jsoup/parser/Token$TokenType;
   #45 = NameAndType        #43:#44       // type:Lcoursier/util/shaded/org/jsoup/parser/Token$TokenType;
   #46 = Fieldref           #13.#45       // coursier/util/shaded/org/jsoup/parser/Token.type:Lcoursier/util/shaded/org/jsoup/parser/Token$TokenType;
   #47 = Utf8               ordinal
   #48 = Utf8               ()I
   #49 = NameAndType        #47:#48       // ordinal:()I
   #50 = Methodref          #11.#49       // coursier/util/shaded/org/jsoup/parser/Token$TokenType.ordinal:()I
   #51 = Utf8               asCharacter
   #52 = Utf8               ()Lcoursier/util/shaded/org/jsoup/parser/Token$Character;
   #53 = NameAndType        #51:#52       // asCharacter:()Lcoursier/util/shaded/org/jsoup/parser/Token$Character;
   #54 = Methodref          #13.#53       // coursier/util/shaded/org/jsoup/parser/Token.asCharacter:()Lcoursier/util/shaded/org/jsoup/parser/Token$Character;
   #55 = Utf8               getData
   #56 = Utf8               ()Ljava/lang/String;
   #57 = NameAndType        #55:#56       // getData:()Ljava/lang/String;
   #58 = Methodref          #16.#57       // coursier/util/shaded/org/jsoup/parser/Token$Character.getData:()Ljava/lang/String;
   #59 = Utf8               access$400
   #60 = NameAndType        #59:#56       // access$400:()Ljava/lang/String;
   #61 = Methodref          #4.#60        // coursier/util/shaded/org/jsoup/parser/HtmlTreeBuilderState.access$400:()Ljava/lang/String;
   #62 = Utf8               java/lang/String
   #63 = Class              #62           // java/lang/String
   #64 = Utf8               equals
   #65 = Utf8               (Ljava/lang/Object;)Z
   #66 = NameAndType        #64:#65       // equals:(Ljava/lang/Object;)Z
   #67 = Methodref          #63.#66       // java/lang/String.equals:(Ljava/lang/Object;)Z
   #68 = Utf8               coursier/util/shaded/org/jsoup/parser/HtmlTreeBuilder
   #69 = Class              #68           // coursier/util/shaded/org/jsoup/parser/HtmlTreeBuilder
   #70 = Utf8               error
   #71 = Utf8               (Lcoursier/util/shaded/org/jsoup/parser/HtmlTreeBuilderState;)V
   #72 = NameAndType        #70:#71       // error:(Lcoursier/util/shaded/org/jsoup/parser/HtmlTreeBuilderState;)V
   #73 = Methodref          #69.#72       // coursier/util/shaded/org/jsoup/parser/HtmlTreeBuilder.error:(Lcoursier/util/shaded/org/jsoup/parser/HtmlTreeBuilderState;)V
   #74 = Utf8               insert
   #75 = Utf8               (Lcoursier/util/shaded/org/jsoup/parser/Token$Character;)V
   #76 = NameAndType        #74:#75       // insert:(Lcoursier/util/shaded/org/jsoup/parser/Token$Character;)V
   #77 = Methodref          #69.#76       // coursier/util/shaded/org/jsoup/parser/HtmlTreeBuilder.insert:(Lcoursier/util/shaded/org/jsoup/parser/Token$Character;)V
   #78 = Utf8               asComment
   #79 = Utf8               ()Lcoursier/util/shaded/org/jsoup/parser/Token$Comment;
   #80 = NameAndType        #78:#79       // asComment:()Lcoursier/util/shaded/org/jsoup/parser/Token$Comment;
   #81 = Methodref          #13.#80       // coursier/util/shaded/org/jsoup/parser/Token.asComment:()Lcoursier/util/shaded/org/jsoup/parser/Token$Comment;
   #82 = Utf8               (Lcoursier/util/shaded/org/jsoup/parser/Token$Comment;)V
   #83 = NameAndType        #74:#82       // insert:(Lcoursier/util/shaded/org/jsoup/parser/Token$Comment;)V
   #84 = Methodref          #69.#83       // coursier/util/shaded/org/jsoup/parser/HtmlTreeBuilder.insert:(Lcoursier/util/shaded/org/jsoup/parser/Token$Comment;)V
   #85 = Utf8               asStartTag
   #86 = Utf8               ()Lcoursier/util/shaded/org/jsoup/parser/Token$StartTag;
   #87 = NameAndType        #85:#86       // asStartTag:()Lcoursier/util/shaded/org/jsoup/parser/Token$StartTag;
   #88 = Methodref          #13.#87       // coursier/util/shaded/org/jsoup/parser/Token.asStartTag:()Lcoursier/util/shaded/org/jsoup/parser/Token$StartTag;
   #89 = Utf8               normalName
   #90 = NameAndType        #89:#56       // normalName:()Ljava/lang/String;
   #91 = Methodref          #22.#90       // coursier/util/shaded/org/jsoup/parser/Token$StartTag.normalName:()Ljava/lang/String;
   #92 = Utf8               html
   #93 = String             #92           // html
   #94 = Utf8               InBody
   #95 = Utf8               Lcoursier/util/shaded/org/jsoup/parser/HtmlTreeBuilderState;
   #96 = NameAndType        #94:#95       // InBody:Lcoursier/util/shaded/org/jsoup/parser/HtmlTreeBuilderState;
   #97 = Fieldref           #2.#96        // coursier/util/shaded/org/jsoup/parser/HtmlTreeBuilderState$16.InBody:Lcoursier/util/shaded/org/jsoup/parser/HtmlTreeBuilderState;
   #98 = Utf8               (Lcoursier/util/shaded/org/jsoup/parser/Token;Lcoursier/util/shaded/org/jsoup/parser/HtmlTreeBuilderState;)Z
   #99 = NameAndType        #37:#98       // process:(Lcoursier/util/shaded/org/jsoup/parser/Token;Lcoursier/util/shaded/org/jsoup/parser/HtmlTreeBuilderState;)Z
  #100 = Methodref          #69.#99       // coursier/util/shaded/org/jsoup/parser/HtmlTreeBuilder.process:(Lcoursier/util/shaded/org/jsoup/parser/Token;Lcoursier/util/shaded/org/jsoup/parser/HtmlTreeBuilderState;)Z
  #101 = Utf8               option
  #102 = String             #101          // option
  #103 = Utf8               currentElement
  #104 = Utf8               ()Lcoursier/util/shaded/org/jsoup/nodes/Element;
  #105 = NameAndType        #103:#104     // currentElement:()Lcoursier/util/shaded/org/jsoup/nodes/Element;
  #106 = Methodref          #69.#105      // coursier/util/shaded/org/jsoup/parser/HtmlTreeBuilder.currentElement:()Lcoursier/util/shaded/org/jsoup/nodes/Element;
  #107 = Utf8               coursier/util/shaded/org/jsoup/nodes/Element
  #108 = Class              #107          // coursier/util/shaded/org/jsoup/nodes/Element
  #109 = Methodref          #108.#90      // coursier/util/shaded/org/jsoup/nodes/Element.normalName:()Ljava/lang/String;
  #110 = Utf8               processEndTag
  #111 = Utf8               (Ljava/lang/String;)Z
  #112 = NameAndType        #110:#111     // processEndTag:(Ljava/lang/String;)Z
  #113 = Methodref          #69.#112      // coursier/util/shaded/org/jsoup/parser/HtmlTreeBuilder.processEndTag:(Ljava/lang/String;)Z
  #114 = Utf8               (Lcoursier/util/shaded/org/jsoup/parser/Token$StartTag;)Lcoursier/util/shaded/org/jsoup/nodes/Element;
  #115 = NameAndType        #74:#114      // insert:(Lcoursier/util/shaded/org/jsoup/parser/Token$StartTag;)Lcoursier/util/shaded/org/jsoup/nodes/Element;
  #116 = Methodref          #69.#115      // coursier/util/shaded/org/jsoup/parser/HtmlTreeBuilder.insert:(Lcoursier/util/shaded/org/jsoup/parser/Token$StartTag;)Lcoursier/util/shaded/org/jsoup/nodes/Element;
  #117 = Utf8               optgroup
  #118 = String             #117          // optgroup
  #119 = Utf8               select
  #120 = String             #119          // select
  #121 = Utf8               InSelectEnd
  #122 = Utf8               [Ljava/lang/String;
  #123 = NameAndType        #121:#122     // InSelectEnd:[Ljava/lang/String;
  #124 = Fieldref           #25.#123      // coursier/util/shaded/org/jsoup/parser/HtmlTreeBuilderState$Constants.InSelectEnd:[Ljava/lang/String;
  #125 = Utf8               coursier/util/shaded/org/jsoup/internal/StringUtil
  #126 = Class              #125          // coursier/util/shaded/org/jsoup/internal/StringUtil
  #127 = Utf8               inSorted
  #128 = Utf8               (Ljava/lang/String;[Ljava/lang/String;)Z
  #129 = NameAndType        #127:#128     // inSorted:(Ljava/lang/String;[Ljava/lang/String;)Z
  #130 = Methodref          #126.#129     // coursier/util/shaded/org/jsoup/internal/StringUtil.inSorted:(Ljava/lang/String;[Ljava/lang/String;)Z
  #131 = Utf8               inSelectScope
  #132 = NameAndType        #131:#111     // inSelectScope:(Ljava/lang/String;)Z
  #133 = Methodref          #69.#132      // coursier/util/shaded/org/jsoup/parser/HtmlTreeBuilder.inSelectScope:(Ljava/lang/String;)Z
  #134 = Utf8               (Lcoursier/util/shaded/org/jsoup/parser/Token;)Z
  #135 = NameAndType        #37:#134      // process:(Lcoursier/util/shaded/org/jsoup/parser/Token;)Z
  #136 = Methodref          #69.#135      // coursier/util/shaded/org/jsoup/parser/HtmlTreeBuilder.process:(Lcoursier/util/shaded/org/jsoup/parser/Token;)Z
  #137 = Utf8               script
  #138 = String             #137          // script
  #139 = Utf8               InHead
  #140 = NameAndType        #139:#95      // InHead:Lcoursier/util/shaded/org/jsoup/parser/HtmlTreeBuilderState;
  #141 = Fieldref           #2.#140       // coursier/util/shaded/org/jsoup/parser/HtmlTreeBuilderState$16.InHead:Lcoursier/util/shaded/org/jsoup/parser/HtmlTreeBuilderState;
  #142 = Utf8               anythingElse
  #143 = NameAndType        #142:#38      // anythingElse:(Lcoursier/util/shaded/org/jsoup/parser/Token;Lcoursier/util/shaded/org/jsoup/parser/HtmlTreeBuilder;)Z
  #144 = Methodref          #2.#143       // coursier/util/shaded/org/jsoup/parser/HtmlTreeBuilderState$16.anythingElse:(Lcoursier/util/shaded/org/jsoup/parser/Token;Lcoursier/util/shaded/org/jsoup/parser/HtmlTreeBuilder;)Z
  #145 = Utf8               asEndTag
  #146 = Utf8               ()Lcoursier/util/shaded/org/jsoup/parser/Token$EndTag;
  #147 = NameAndType        #145:#146     // asEndTag:()Lcoursier/util/shaded/org/jsoup/parser/Token$EndTag;
  #148 = Methodref          #13.#147      // coursier/util/shaded/org/jsoup/parser/Token.asEndTag:()Lcoursier/util/shaded/org/jsoup/parser/Token$EndTag;
  #149 = Methodref          #28.#90       // coursier/util/shaded/org/jsoup/parser/Token$EndTag.normalName:()Ljava/lang/String;
  #150 = Utf8               hashCode
  #151 = NameAndType        #150:#48      // hashCode:()I
  #152 = Methodref          #63.#151      // java/lang/String.hashCode:()I
  #153 = Utf8               aboveOnStack
  #154 = Utf8               (Lcoursier/util/shaded/org/jsoup/nodes/Element;)Lcoursier/util/shaded/org/jsoup/nodes/Element;
  #155 = NameAndType        #153:#154     // aboveOnStack:(Lcoursier/util/shaded/org/jsoup/nodes/Element;)Lcoursier/util/shaded/org/jsoup/nodes/Element;
  #156 = Methodref          #69.#155      // coursier/util/shaded/org/jsoup/parser/HtmlTreeBuilder.aboveOnStack:(Lcoursier/util/shaded/org/jsoup/nodes/Element;)Lcoursier/util/shaded/org/jsoup/nodes/Element;
  #157 = Utf8               pop
  #158 = NameAndType        #157:#104     // pop:()Lcoursier/util/shaded/org/jsoup/nodes/Element;
  #159 = Methodref          #69.#158      // coursier/util/shaded/org/jsoup/parser/HtmlTreeBuilder.pop:()Lcoursier/util/shaded/org/jsoup/nodes/Element;
  #160 = Utf8               popStackToClose
  #161 = Utf8               (Ljava/lang/String;)Lcoursier/util/shaded/org/jsoup/nodes/Element;
  #162 = NameAndType        #160:#161     // popStackToClose:(Ljava/lang/String;)Lcoursier/util/shaded/org/jsoup/nodes/Element;
  #163 = Methodref          #69.#162      // coursier/util/shaded/org/jsoup/parser/HtmlTreeBuilder.popStackToClose:(Ljava/lang/String;)Lcoursier/util/shaded/org/jsoup/nodes/Element;
  #164 = Utf8               resetInsertionMode
  #165 = Utf8               ()V
  #166 = NameAndType        #164:#165     // resetInsertionMode:()V
  #167 = Methodref          #69.#166      // coursier/util/shaded/org/jsoup/parser/HtmlTreeBuilder.resetInsertionMode:()V
  #168 = Utf8               c
  #169 = Utf8               Lcoursier/util/shaded/org/jsoup/parser/Token$Character;
  #170 = Utf8               start
  #171 = Utf8               Lcoursier/util/shaded/org/jsoup/parser/Token$StartTag;
  #172 = Utf8               name
  #173 = Utf8               Ljava/lang/String;
  #174 = Utf8               end
  #175 = Utf8               Lcoursier/util/shaded/org/jsoup/parser/Token$EndTag;
  #176 = Utf8               t
  #177 = Utf8               Lcoursier/util/shaded/org/jsoup/parser/Token;
  #178 = Utf8               tb
  #179 = Utf8               Lcoursier/util/shaded/org/jsoup/parser/HtmlTreeBuilder;
  #180 = Utf8               Code
  #181 = Utf8               LineNumberTable
  #182 = Utf8               LocalVariableTable
  #183 = Utf8               StackMapTable
  #184 = Utf8               InnerClasses
  #185 = Utf8               EnclosingMethod
  #186 = Utf8               SourceFile
{
  coursier.util.shaded.org.jsoup.parser.HtmlTreeBuilderState$16(java.lang.String, int);
    descriptor: (Ljava/lang/String;I)V
    flags: (0x0000)
    Code:
      stack=4, locals=3, args_size=3
         0: aload_0
         1: aload_1
         2: iload_2
         3: aconst_null
         4: invokespecial #34                 // Method coursier/util/shaded/org/jsoup/parser/HtmlTreeBuilderState."<init>":(Ljava/lang/String;ILcoursier/util/shaded/org/jsoup/parser/HtmlTreeBuilderState$1;)V
         7: return
      LineNumberTable:
        line 1294: 0
      LocalVariableTable:
        Start  Length  Slot  Name   Signature
            0       8     0  this   Lcoursier/util/shaded/org/jsoup/parser/HtmlTreeBuilderState$16;

  boolean process(coursier.util.shaded.org.jsoup.parser.Token, coursier.util.shaded.org.jsoup.parser.HtmlTreeBuilder);
    descriptor: (Lcoursier/util/shaded/org/jsoup/parser/Token;Lcoursier/util/shaded/org/jsoup/parser/HtmlTreeBuilder;)Z
    flags: (0x0000)
    Code:
      stack=3, locals=9, args_size=3
         0: getstatic     #42                 // Field coursier/util/shaded/org/jsoup/parser/HtmlTreeBuilderState$24.$SwitchMap$org$jsoup$parser$Token$TokenType:[I
         3: aload_1
         4: getfield      #46                 // Field coursier/util/shaded/org/jsoup/parser/Token.type:Lcoursier/util/shaded/org/jsoup/parser/Token$TokenType;
         7: invokevirtual #50                 // Method coursier/util/shaded/org/jsoup/parser/Token$TokenType.ordinal:()I
        10: iaload
        11: tableswitch   { // 1 to 6
                       1: 81
                       2: 92
                       3: 99
                       4: 327
                       5: 48
                       6: 614
                 default: 637
            }
        48: aload_1
        49: invokevirtual #54                 // Method coursier/util/shaded/org/jsoup/parser/Token.asCharacter:()Lcoursier/util/shaded/org/jsoup/parser/Token$Character;
        52: astore_3
        53: aload_3
        54: invokevirtual #58                 // Method coursier/util/shaded/org/jsoup/parser/Token$Character.getData:()Ljava/lang/String;
        57: invokestatic  #61                 // Method coursier/util/shaded/org/jsoup/parser/HtmlTreeBuilderState.access$400:()Ljava/lang/String;
        60: invokevirtual #67                 // Method java/lang/String.equals:(Ljava/lang/Object;)Z
        63: ifeq          73
        66: aload_2
        67: aload_0
        68: invokevirtual #73                 // Method coursier/util/shaded/org/jsoup/parser/HtmlTreeBuilder.error:(Lcoursier/util/shaded/org/jsoup/parser/HtmlTreeBuilderState;)V
        71: iconst_0
        72: ireturn
        73: aload_2
        74: aload_3
        75: invokevirtual #77                 // Method coursier/util/shaded/org/jsoup/parser/HtmlTreeBuilder.insert:(Lcoursier/util/shaded/org/jsoup/parser/Token$Character;)V
        78: goto          644
        81: aload_2
        82: aload_1
        83: invokevirtual #81                 // Method coursier/util/shaded/org/jsoup/parser/Token.asComment:()Lcoursier/util/shaded/org/jsoup/parser/Token$Comment;
        86: invokevirtual #84                 // Method coursier/util/shaded/org/jsoup/parser/HtmlTreeBuilder.insert:(Lcoursier/util/shaded/org/jsoup/parser/Token$Comment;)V
        89: goto          644
        92: aload_2
        93: aload_0
        94: invokevirtual #73                 // Method coursier/util/shaded/org/jsoup/parser/HtmlTreeBuilder.error:(Lcoursier/util/shaded/org/jsoup/parser/HtmlTreeBuilderState;)V
        97: iconst_0
        98: ireturn
        99: aload_1
       100: invokevirtual #88                 // Method coursier/util/shaded/org/jsoup/parser/Token.asStartTag:()Lcoursier/util/shaded/org/jsoup/parser/Token$StartTag;
       103: astore        4
       105: aload         4
       107: invokevirtual #91                 // Method coursier/util/shaded/org/jsoup/parser/Token$StartTag.normalName:()Ljava/lang/String;
       110: astore        5
       112: aload         5
       114: ldc           #93                 // String html
       116: invokevirtual #67                 // Method java/lang/String.equals:(Ljava/lang/Object;)Z
       119: ifeq          132
       122: aload_2
       123: aload         4
       125: getstatic     #97                 // Field InBody:Lcoursier/util/shaded/org/jsoup/parser/HtmlTreeBuilderState;
       128: invokevirtual #100                // Method coursier/util/shaded/org/jsoup/parser/HtmlTreeBuilder.process:(Lcoursier/util/shaded/org/jsoup/parser/Token;Lcoursier/util/shaded/org/jsoup/parser/HtmlTreeBuilderState;)Z
       131: ireturn
       132: aload         5
       134: ldc           #102                // String option
       136: invokevirtual #67                 // Method java/lang/String.equals:(Ljava/lang/Object;)Z
       139: ifeq          174
       142: aload_2
       143: invokevirtual #106                // Method coursier/util/shaded/org/jsoup/parser/HtmlTreeBuilder.currentElement:()Lcoursier/util/shaded/org/jsoup/nodes/Element;
       146: invokevirtual #109                // Method coursier/util/shaded/org/jsoup/nodes/Element.normalName:()Ljava/lang/String;
       149: ldc           #102                // String option
       151: invokevirtual #67                 // Method java/lang/String.equals:(Ljava/lang/Object;)Z
       154: ifeq          164
       157: aload_2
       158: ldc           #102                // String option
       160: invokevirtual #113                // Method coursier/util/shaded/org/jsoup/parser/HtmlTreeBuilder.processEndTag:(Ljava/lang/String;)Z
       163: pop
       164: aload_2
       165: aload         4
       167: invokevirtual #116                // Method coursier/util/shaded/org/jsoup/parser/HtmlTreeBuilder.insert:(Lcoursier/util/shaded/org/jsoup/parser/Token$StartTag;)Lcoursier/util/shaded/org/jsoup/nodes/Element;
       170: pop
       171: goto          644
       174: aload         5
       176: ldc           #118                // String optgroup
       178: invokevirtual #67                 // Method java/lang/String.equals:(Ljava/lang/Object;)Z
       181: ifeq          238
       184: aload_2
       185: invokevirtual #106                // Method coursier/util/shaded/org/jsoup/parser/HtmlTreeBuilder.currentElement:()Lcoursier/util/shaded/org/jsoup/nodes/Element;
       188: invokevirtual #109                // Method coursier/util/shaded/org/jsoup/nodes/Element.normalName:()Ljava/lang/String;
       191: ldc           #102                // String option
       193: invokevirtual #67                 // Method java/lang/String.equals:(Ljava/lang/Object;)Z
       196: ifeq          206
       199: aload_2
       200: ldc           #102                // String option
       202: invokevirtual #113                // Method coursier/util/shaded/org/jsoup/parser/HtmlTreeBuilder.processEndTag:(Ljava/lang/String;)Z
       205: pop
       206: aload_2
       207: invokevirtual #106                // Method coursier/util/shaded/org/jsoup/parser/HtmlTreeBuilder.currentElement:()Lcoursier/util/shaded/org/jsoup/nodes/Element;
       210: invokevirtual #109                // Method coursier/util/shaded/org/jsoup/nodes/Element.normalName:()Ljava/lang/String;
       213: ldc           #118                // String optgroup
       215: invokevirtual #67                 // Method java/lang/String.equals:(Ljava/lang/Object;)Z
       218: ifeq          228
       221: aload_2
       222: ldc           #118                // String optgroup
       224: invokevirtual #113                // Method coursier/util/shaded/org/jsoup/parser/HtmlTreeBuilder.processEndTag:(Ljava/lang/String;)Z
       227: pop
       228: aload_2
       229: aload         4
       231: invokevirtual #116                // Method coursier/util/shaded/org/jsoup/parser/HtmlTreeBuilder.insert:(Lcoursier/util/shaded/org/jsoup/parser/Token$StartTag;)Lcoursier/util/shaded/org/jsoup/nodes/Element;
       234: pop
       235: goto          644
       238: aload         5
       240: ldc           #120                // String select
       242: invokevirtual #67                 // Method java/lang/String.equals:(Ljava/lang/Object;)Z
       245: ifeq          260
       248: aload_2
       249: aload_0
       250: invokevirtual #73                 // Method coursier/util/shaded/org/jsoup/parser/HtmlTreeBuilder.error:(Lcoursier/util/shaded/org/jsoup/parser/HtmlTreeBuilderState;)V
       253: aload_2
       254: ldc           #120                // String select
       256: invokevirtual #113                // Method coursier/util/shaded/org/jsoup/parser/HtmlTreeBuilder.processEndTag:(Ljava/lang/String;)Z
       259: ireturn
       260: aload         5
       262: getstatic     #124                // Field coursier/util/shaded/org/jsoup/parser/HtmlTreeBuilderState$Constants.InSelectEnd:[Ljava/lang/String;
       265: invokestatic  #130                // Method coursier/util/shaded/org/jsoup/internal/StringUtil.inSorted:(Ljava/lang/String;[Ljava/lang/String;)Z
       268: ifeq          301
       271: aload_2
       272: aload_0
       273: invokevirtual #73                 // Method coursier/util/shaded/org/jsoup/parser/HtmlTreeBuilder.error:(Lcoursier/util/shaded/org/jsoup/parser/HtmlTreeBuilderState;)V
       276: aload_2
       277: ldc           #120                // String select
       279: invokevirtual #133                // Method coursier/util/shaded/org/jsoup/parser/HtmlTreeBuilder.inSelectScope:(Ljava/lang/String;)Z
       282: ifne          287
       285: iconst_0
       286: ireturn
       287: aload_2
       288: ldc           #120                // String select
       290: invokevirtual #113                // Method coursier/util/shaded/org/jsoup/parser/HtmlTreeBuilder.processEndTag:(Ljava/lang/String;)Z
       293: pop
       294: aload_2
       295: aload         4
       297: invokevirtual #136                // Method coursier/util/shaded/org/jsoup/parser/HtmlTreeBuilder.process:(Lcoursier/util/shaded/org/jsoup/parser/Token;)Z
       300: ireturn
       301: aload         5
       303: ldc           #138                // String script
       305: invokevirtual #67                 // Method java/lang/String.equals:(Ljava/lang/Object;)Z
       308: ifeq          320
       311: aload_2
       312: aload_1
       313: getstatic     #141                // Field InHead:Lcoursier/util/shaded/org/jsoup/parser/HtmlTreeBuilderState;
       316: invokevirtual #100                // Method coursier/util/shaded/org/jsoup/parser/HtmlTreeBuilder.process:(Lcoursier/util/shaded/org/jsoup/parser/Token;Lcoursier/util/shaded/org/jsoup/parser/HtmlTreeBuilderState;)Z
       319: ireturn
       320: aload_0
       321: aload_1
       322: aload_2
       323: invokespecial #144                // Method anythingElse:(Lcoursier/util/shaded/org/jsoup/parser/Token;Lcoursier/util/shaded/org/jsoup/parser/HtmlTreeBuilder;)Z
       326: ireturn
       327: aload_1
       328: invokevirtual #148                // Method coursier/util/shaded/org/jsoup/parser/Token.asEndTag:()Lcoursier/util/shaded/org/jsoup/parser/Token$EndTag;
       331: astore        6
       333: aload         6
       335: invokevirtual #149                // Method coursier/util/shaded/org/jsoup/parser/Token$EndTag.normalName:()Ljava/lang/String;
       338: astore        5
       340: aload         5
       342: astore        7
       344: iconst_m1
       345: istore        8
       347: aload         7
       349: invokevirtual #152                // Method java/lang/String.hashCode:()I
       352: lookupswitch  { // 3
             -1010136971: 404
              -906021636: 420
               -80773204: 388
                 default: 433
            }
       388: aload         7
       390: ldc           #118                // String optgroup
       392: invokevirtual #67                 // Method java/lang/String.equals:(Ljava/lang/Object;)Z
       395: ifeq          433
       398: iconst_0
       399: istore        8
       401: goto          433
       404: aload         7
       406: ldc           #102                // String option
       408: invokevirtual #67                 // Method java/lang/String.equals:(Ljava/lang/Object;)Z
       411: ifeq          433
       414: iconst_1
       415: istore        8
       417: goto          433
       420: aload         7
       422: ldc           #120                // String select
       424: invokevirtual #67                 // Method java/lang/String.equals:(Ljava/lang/Object;)Z
       427: ifeq          433
       430: iconst_2
       431: istore        8
       433: iload         8
       435: tableswitch   { // 0 to 2
                       0: 460
                       1: 543
                       2: 574
                 default: 604
            }
       460: aload_2
       461: invokevirtual #106                // Method coursier/util/shaded/org/jsoup/parser/HtmlTreeBuilder.currentElement:()Lcoursier/util/shaded/org/jsoup/nodes/Element;
       464: invokevirtual #109                // Method coursier/util/shaded/org/jsoup/nodes/Element.normalName:()Ljava/lang/String;
       467: ldc           #102                // String option
       469: invokevirtual #67                 // Method java/lang/String.equals:(Ljava/lang/Object;)Z
       472: ifeq          512
       475: aload_2
       476: aload_2
       477: invokevirtual #106                // Method coursier/util/shaded/org/jsoup/parser/HtmlTreeBuilder.currentElement:()Lcoursier/util/shaded/org/jsoup/nodes/Element;
       480: invokevirtual #156                // Method coursier/util/shaded/org/jsoup/parser/HtmlTreeBuilder.aboveOnStack:(Lcoursier/util/shaded/org/jsoup/nodes/Element;)Lcoursier/util/shaded/org/jsoup/nodes/Element;
       483: ifnull        512
       486: aload_2
       487: aload_2
       488: invokevirtual #106                // Method coursier/util/shaded/org/jsoup/parser/HtmlTreeBuilder.currentElement:()Lcoursier/util/shaded/org/jsoup/nodes/Element;
       491: invokevirtual #156                // Method coursier/util/shaded/org/jsoup/parser/HtmlTreeBuilder.aboveOnStack:(Lcoursier/util/shaded/org/jsoup/nodes/Element;)Lcoursier/util/shaded/org/jsoup/nodes/Element;
       494: invokevirtual #109                // Method coursier/util/shaded/org/jsoup/nodes/Element.normalName:()Ljava/lang/String;
       497: ldc           #118                // String optgroup
       499: invokevirtual #67                 // Method java/lang/String.equals:(Ljava/lang/Object;)Z
       502: ifeq          512
       505: aload_2
       506: ldc           #102                // String option
       508: invokevirtual #113                // Method coursier/util/shaded/org/jsoup/parser/HtmlTreeBuilder.processEndTag:(Ljava/lang/String;)Z
       511: pop
       512: aload_2
       513: invokevirtual #106                // Method coursier/util/shaded/org/jsoup/parser/HtmlTreeBuilder.currentElement:()Lcoursier/util/shaded/org/jsoup/nodes/Element;
       516: invokevirtual #109                // Method coursier/util/shaded/org/jsoup/nodes/Element.normalName:()Ljava/lang/String;
       519: ldc           #118                // String optgroup
       521: invokevirtual #67                 // Method java/lang/String.equals:(Ljava/lang/Object;)Z
       524: ifeq          535
       527: aload_2
       528: invokevirtual #159                // Method coursier/util/shaded/org/jsoup/parser/HtmlTreeBuilder.pop:()Lcoursier/util/shaded/org/jsoup/nodes/Element;
       531: pop
       532: goto          611
       535: aload_2
       536: aload_0
       537: invokevirtual #73                 // Method coursier/util/shaded/org/jsoup/parser/HtmlTreeBuilder.error:(Lcoursier/util/shaded/org/jsoup/parser/HtmlTreeBuilderState;)V
       540: goto          611
       543: aload_2
       544: invokevirtual #106                // Method coursier/util/shaded/org/jsoup/parser/HtmlTreeBuilder.currentElement:()Lcoursier/util/shaded/org/jsoup/nodes/Element;
       547: invokevirtual #109                // Method coursier/util/shaded/org/jsoup/nodes/Element.normalName:()Ljava/lang/String;
       550: ldc           #102                // String option
       552: invokevirtual #67                 // Method java/lang/String.equals:(Ljava/lang/Object;)Z
       555: ifeq          566
       558: aload_2
       559: invokevirtual #159                // Method coursier/util/shaded/org/jsoup/parser/HtmlTreeBuilder.pop:()Lcoursier/util/shaded/org/jsoup/nodes/Element;
       562: pop
       563: goto          611
       566: aload_2
       567: aload_0
       568: invokevirtual #73                 // Method coursier/util/shaded/org/jsoup/parser/HtmlTreeBuilder.error:(Lcoursier/util/shaded/org/jsoup/parser/HtmlTreeBuilderState;)V
       571: goto          611
       574: aload_2
       575: aload         5
       577: invokevirtual #133                // Method coursier/util/shaded/org/jsoup/parser/HtmlTreeBuilder.inSelectScope:(Ljava/lang/String;)Z
       580: ifne          590
       583: aload_2
       584: aload_0
       585: invokevirtual #73                 // Method coursier/util/shaded/org/jsoup/parser/HtmlTreeBuilder.error:(Lcoursier/util/shaded/org/jsoup/parser/HtmlTreeBuilderState;)V
       588: iconst_0
       589: ireturn
       590: aload_2
       591: aload         5
       593: invokevirtual #163                // Method coursier/util/shaded/org/jsoup/parser/HtmlTreeBuilder.popStackToClose:(Ljava/lang/String;)Lcoursier/util/shaded/org/jsoup/nodes/Element;
       596: pop
       597: aload_2
       598: invokevirtual #167                // Method coursier/util/shaded/org/jsoup/parser/HtmlTreeBuilder.resetInsertionMode:()V
       601: goto          611
       604: aload_0
       605: aload_1
       606: aload_2
       607: invokespecial #144                // Method anythingElse:(Lcoursier/util/shaded/org/jsoup/parser/Token;Lcoursier/util/shaded/org/jsoup/parser/HtmlTreeBuilder;)Z
       610: ireturn
       611: goto          644
       614: aload_2
       615: invokevirtual #106                // Method coursier/util/shaded/org/jsoup/parser/HtmlTreeBuilder.currentElement:()Lcoursier/util/shaded/org/jsoup/nodes/Element;
       618: invokevirtual #109                // Method coursier/util/shaded/org/jsoup/nodes/Element.normalName:()Ljava/lang/String;
       621: ldc           #93                 // String html
       623: invokevirtual #67                 // Method java/lang/String.equals:(Ljava/lang/Object;)Z
       626: ifne          644
       629: aload_2
       630: aload_0
       631: invokevirtual #73                 // Method coursier/util/shaded/org/jsoup/parser/HtmlTreeBuilder.error:(Lcoursier/util/shaded/org/jsoup/parser/HtmlTreeBuilderState;)V
       634: goto          644
       637: aload_0
       638: aload_1
       639: aload_2
       640: invokespecial #144                // Method anythingElse:(Lcoursier/util/shaded/org/jsoup/parser/Token;Lcoursier/util/shaded/org/jsoup/parser/HtmlTreeBuilder;)Z
       643: ireturn
       644: iconst_1
       645: ireturn
      StackMapTable: number_of_entries = 32
        frame_type = 48 /* same */
        frame_type = 252 /* append */
          offset_delta = 24
          locals = [ class coursier/util/shaded/org/jsoup/parser/Token$Character ]
        frame_type = 250 /* chop */
          offset_delta = 7
        frame_type = 10 /* same */
        frame_type = 6 /* same */
        frame_type = 254 /* append */
          offset_delta = 32
          locals = [ top, class coursier/util/shaded/org/jsoup/parser/Token$StartTag, class java/lang/String ]
        frame_type = 31 /* same */
        frame_type = 9 /* same */
        frame_type = 31 /* same */
        frame_type = 21 /* same */
        frame_type = 9 /* same */
        frame_type = 21 /* same */
        frame_type = 26 /* same */
        frame_type = 13 /* same */
        frame_type = 18 /* same */
        frame_type = 248 /* chop */
          offset_delta = 6
        frame_type = 255 /* full_frame */
          offset_delta = 60
          locals = [ class coursier/util/shaded/org/jsoup/parser/HtmlTreeBuilderState$16, class coursier/util/shaded/org/jsoup/parser/Token, class coursier/util/shaded/org/jsoup/parser/HtmlTreeBuilder, top, top, class java/lang/String, class coursier/util/shaded/org/jsoup/parser/Token$EndTag, class java/lang/String, int ]
          stack = []
        frame_type = 15 /* same */
        frame_type = 15 /* same */
        frame_type = 12 /* same */
        frame_type = 26 /* same */
        frame_type = 51 /* same */
        frame_type = 22 /* same */
        frame_type = 7 /* same */
        frame_type = 22 /* same */
        frame_type = 7 /* same */
        frame_type = 15 /* same */
        frame_type = 13 /* same */
        frame_type = 249 /* chop */
          offset_delta = 6
        frame_type = 255 /* full_frame */
          offset_delta = 2
          locals = [ class coursier/util/shaded/org/jsoup/parser/HtmlTreeBuilderState$16, class coursier/util/shaded/org/jsoup/parser/Token, class coursier/util/shaded/org/jsoup/parser/HtmlTreeBuilder ]
          stack = []
        frame_type = 22 /* same */
        frame_type = 6 /* same */
      LineNumberTable:
        line 1296: 0
        line 1298: 48
        line 1299: 53
        line 1300: 66
        line 1301: 71
        line 1303: 73
        line 1305: 78
        line 1307: 81
        line 1308: 89
        line 1310: 92
        line 1311: 97
        line 1313: 99
        line 1314: 105
        line 1315: 112
        line 1316: 122
        line 1317: 132
        line 1318: 142
        line 1319: 157
        line 1320: 164
        line 1321: 174
        line 1322: 184
        line 1323: 199
        line 1324: 206
        line 1325: 221
        line 1326: 228
        line 1327: 238
        line 1328: 248
        line 1329: 253
        line 1330: 260
        line 1331: 271
        line 1332: 276
        line 1333: 285
        line 1334: 287
        line 1335: 294
        line 1336: 301
        line 1337: 311
        line 1339: 320
        line 1343: 327
        line 1344: 333
        line 1345: 340
        line 1347: 460
        line 1348: 505
        line 1349: 512
        line 1350: 527
        line 1352: 535
        line 1353: 540
        line 1355: 543
        line 1356: 558
        line 1358: 566
        line 1359: 571
        line 1361: 574
        line 1362: 583
        line 1363: 588
        line 1365: 590
        line 1366: 597
        line 1368: 601
        line 1370: 604
        line 1372: 611
        line 1374: 614
        line 1375: 629
        line 1378: 637
        line 1380: 644
      LocalVariableTable:
        Start  Length  Slot  Name   Signature
           53      28     3     c   Lcoursier/util/shaded/org/jsoup/parser/Token$Character;
          105     222     4 start   Lcoursier/util/shaded/org/jsoup/parser/Token$StartTag;
          112     215     5  name   Ljava/lang/String;
          340     274     5  name   Ljava/lang/String;
          333     281     6   end   Lcoursier/util/shaded/org/jsoup/parser/Token$EndTag;
            0     646     0  this   Lcoursier/util/shaded/org/jsoup/parser/HtmlTreeBuilderState$16;
            0     646     1     t   Lcoursier/util/shaded/org/jsoup/parser/Token;
            0     646     2    tb   Lcoursier/util/shaded/org/jsoup/parser/HtmlTreeBuilder;

  private boolean anythingElse(coursier.util.shaded.org.jsoup.parser.Token, coursier.util.shaded.org.jsoup.parser.HtmlTreeBuilder);
    descriptor: (Lcoursier/util/shaded/org/jsoup/parser/Token;Lcoursier/util/shaded/org/jsoup/parser/HtmlTreeBuilder;)Z
    flags: (0x0002) ACC_PRIVATE
    Code:
      stack=2, locals=3, args_size=3
         0: aload_2
         1: aload_0
         2: invokevirtual #73                 // Method coursier/util/shaded/org/jsoup/parser/HtmlTreeBuilder.error:(Lcoursier/util/shaded/org/jsoup/parser/HtmlTreeBuilderState;)V
         5: iconst_0
         6: ireturn
      LineNumberTable:
        line 1384: 0
        line 1385: 5
      LocalVariableTable:
        Start  Length  Slot  Name   Signature
            0       7     0  this   Lcoursier/util/shaded/org/jsoup/parser/HtmlTreeBuilderState$16;
            0       7     1     t   Lcoursier/util/shaded/org/jsoup/parser/Token;
            0       7     2    tb   Lcoursier/util/shaded/org/jsoup/parser/HtmlTreeBuilder;
}
InnerClasses:
  final #7;                               // class coursier/util/shaded/org/jsoup/parser/HtmlTreeBuilderState$1
  static #9;                              // class coursier/util/shaded/org/jsoup/parser/HtmlTreeBuilderState$24
  public static final #14= #11 of #13;    // TokenType=class coursier/util/shaded/org/jsoup/parser/Token$TokenType of class coursier/util/shaded/org/jsoup/parser/Token
  static #17= #16 of #13;                 // Character=class coursier/util/shaded/org/jsoup/parser/Token$Character of class coursier/util/shaded/org/jsoup/parser/Token
  static final #20= #19 of #13;           // Comment=class coursier/util/shaded/org/jsoup/parser/Token$Comment of class coursier/util/shaded/org/jsoup/parser/Token
  static final #23= #22 of #13;           // StartTag=class coursier/util/shaded/org/jsoup/parser/Token$StartTag of class coursier/util/shaded/org/jsoup/parser/Token
  final #2;                               // class coursier/util/shaded/org/jsoup/parser/HtmlTreeBuilderState$16
  static final #26= #25 of #4;            // Constants=class coursier/util/shaded/org/jsoup/parser/HtmlTreeBuilderState$Constants of class coursier/util/shaded/org/jsoup/parser/HtmlTreeBuilderState
  static final #29= #28 of #13;           // EndTag=class coursier/util/shaded/org/jsoup/parser/Token$EndTag of class coursier/util/shaded/org/jsoup/parser/Token
EnclosingMethod: #4.#0                  // coursier.util.shaded.org.jsoup.parser.HtmlTreeBuilderState
SourceFile: "HtmlTreeBuilderState.java"
