Classfile /Users/mw/Projects/slang-braindump/.jar/jar11/assemble/slang-braindump/assemble/content/coursier/util/shaded/org/jsoup/parser/HtmlTreeBuilderState$24.class
  Last modified May 29, 2022; size 1079 bytes
  SHA-256 checksum 888a556531bc7e0e7af6e0d0f515e9719c40c294f99766e01ee7f49dca017a02
  Compiled from "HtmlTreeBuilderState.java"
class coursier.util.shaded.org.jsoup.parser.HtmlTreeBuilderState$24
  minor version: 0
  major version: 51
  flags: (0x1020) ACC_SUPER, ACC_SYNTHETIC
  this_class: #2                          // coursier/util/shaded/org/jsoup/parser/HtmlTreeBuilderState$24
  super_class: #4                         // java/lang/Object
  interfaces: 0, fields: 1, methods: 1, attributes: 3
Constant pool:
   #1 = Utf8               coursier/util/shaded/org/jsoup/parser/HtmlTreeBuilderState$24
   #2 = Class              #1             // coursier/util/shaded/org/jsoup/parser/HtmlTreeBuilderState$24
   #3 = Utf8               java/lang/Object
   #4 = Class              #3             // java/lang/Object
   #5 = Utf8               HtmlTreeBuilderState.java
   #6 = Utf8               coursier/util/shaded/org/jsoup/parser/HtmlTreeBuilderState
   #7 = Class              #6             // coursier/util/shaded/org/jsoup/parser/HtmlTreeBuilderState
   #8 = Utf8               coursier/util/shaded/org/jsoup/parser/Token$TokenType
   #9 = Class              #8             // coursier/util/shaded/org/jsoup/parser/Token$TokenType
  #10 = Utf8               coursier/util/shaded/org/jsoup/parser/Token
  #11 = Class              #10            // coursier/util/shaded/org/jsoup/parser/Token
  #12 = Utf8               TokenType
  #13 = Utf8               $SwitchMap$org$jsoup$parser$Token$TokenType
  #14 = Utf8               [I
  #15 = Utf8               <clinit>
  #16 = Utf8               ()V
  #17 = Utf8               java/lang/NoSuchFieldError
  #18 = Class              #17            // java/lang/NoSuchFieldError
  #19 = Utf8               values
  #20 = Utf8               ()[Lcoursier/util/shaded/org/jsoup/parser/Token$TokenType;
  #21 = NameAndType        #19:#20        // values:()[Lcoursier/util/shaded/org/jsoup/parser/Token$TokenType;
  #22 = Methodref          #9.#21         // coursier/util/shaded/org/jsoup/parser/Token$TokenType.values:()[Lcoursier/util/shaded/org/jsoup/parser/Token$TokenType;
  #23 = NameAndType        #13:#14        // $SwitchMap$org$jsoup$parser$Token$TokenType:[I
  #24 = Fieldref           #2.#23         // coursier/util/shaded/org/jsoup/parser/HtmlTreeBuilderState$24.$SwitchMap$org$jsoup$parser$Token$TokenType:[I
  #25 = Utf8               Comment
  #26 = Utf8               Lcoursier/util/shaded/org/jsoup/parser/Token$TokenType;
  #27 = NameAndType        #25:#26        // Comment:Lcoursier/util/shaded/org/jsoup/parser/Token$TokenType;
  #28 = Fieldref           #9.#27         // coursier/util/shaded/org/jsoup/parser/Token$TokenType.Comment:Lcoursier/util/shaded/org/jsoup/parser/Token$TokenType;
  #29 = Utf8               ordinal
  #30 = Utf8               ()I
  #31 = NameAndType        #29:#30        // ordinal:()I
  #32 = Methodref          #9.#31         // coursier/util/shaded/org/jsoup/parser/Token$TokenType.ordinal:()I
  #33 = Utf8               Doctype
  #34 = NameAndType        #33:#26        // Doctype:Lcoursier/util/shaded/org/jsoup/parser/Token$TokenType;
  #35 = Fieldref           #9.#34         // coursier/util/shaded/org/jsoup/parser/Token$TokenType.Doctype:Lcoursier/util/shaded/org/jsoup/parser/Token$TokenType;
  #36 = Utf8               StartTag
  #37 = NameAndType        #36:#26        // StartTag:Lcoursier/util/shaded/org/jsoup/parser/Token$TokenType;
  #38 = Fieldref           #9.#37         // coursier/util/shaded/org/jsoup/parser/Token$TokenType.StartTag:Lcoursier/util/shaded/org/jsoup/parser/Token$TokenType;
  #39 = Utf8               EndTag
  #40 = NameAndType        #39:#26        // EndTag:Lcoursier/util/shaded/org/jsoup/parser/Token$TokenType;
  #41 = Fieldref           #9.#40         // coursier/util/shaded/org/jsoup/parser/Token$TokenType.EndTag:Lcoursier/util/shaded/org/jsoup/parser/Token$TokenType;
  #42 = Utf8               Character
  #43 = NameAndType        #42:#26        // Character:Lcoursier/util/shaded/org/jsoup/parser/Token$TokenType;
  #44 = Fieldref           #9.#43         // coursier/util/shaded/org/jsoup/parser/Token$TokenType.Character:Lcoursier/util/shaded/org/jsoup/parser/Token$TokenType;
  #45 = Utf8               EOF
  #46 = NameAndType        #45:#26        // EOF:Lcoursier/util/shaded/org/jsoup/parser/Token$TokenType;
  #47 = Fieldref           #9.#46         // coursier/util/shaded/org/jsoup/parser/Token$TokenType.EOF:Lcoursier/util/shaded/org/jsoup/parser/Token$TokenType;
  #48 = Utf8               Code
  #49 = Utf8               StackMapTable
  #50 = Utf8               LineNumberTable
  #51 = Utf8               InnerClasses
  #52 = Utf8               EnclosingMethod
  #53 = Utf8               SourceFile
{
  static final int[] $SwitchMap$org$jsoup$parser$Token$TokenType;
    descriptor: [I
    flags: (0x1018) ACC_STATIC, ACC_FINAL, ACC_SYNTHETIC

  static {};
    descriptor: ()V
    flags: (0x0008) ACC_STATIC
    Code:
      stack=3, locals=1, args_size=0
         0: invokestatic  #22                 // Method coursier/util/shaded/org/jsoup/parser/Token$TokenType.values:()[Lcoursier/util/shaded/org/jsoup/parser/Token$TokenType;
         3: arraylength
         4: newarray       int
         6: putstatic     #24                 // Field $SwitchMap$org$jsoup$parser$Token$TokenType:[I
         9: getstatic     #24                 // Field $SwitchMap$org$jsoup$parser$Token$TokenType:[I
        12: getstatic     #28                 // Field coursier/util/shaded/org/jsoup/parser/Token$TokenType.Comment:Lcoursier/util/shaded/org/jsoup/parser/Token$TokenType;
        15: invokevirtual #32                 // Method coursier/util/shaded/org/jsoup/parser/Token$TokenType.ordinal:()I
        18: iconst_1
        19: iastore
        20: goto          24
        23: astore_0
        24: getstatic     #24                 // Field $SwitchMap$org$jsoup$parser$Token$TokenType:[I
        27: getstatic     #35                 // Field coursier/util/shaded/org/jsoup/parser/Token$TokenType.Doctype:Lcoursier/util/shaded/org/jsoup/parser/Token$TokenType;
        30: invokevirtual #32                 // Method coursier/util/shaded/org/jsoup/parser/Token$TokenType.ordinal:()I
        33: iconst_2
        34: iastore
        35: goto          39
        38: astore_0
        39: getstatic     #24                 // Field $SwitchMap$org$jsoup$parser$Token$TokenType:[I
        42: getstatic     #38                 // Field coursier/util/shaded/org/jsoup/parser/Token$TokenType.StartTag:Lcoursier/util/shaded/org/jsoup/parser/Token$TokenType;
        45: invokevirtual #32                 // Method coursier/util/shaded/org/jsoup/parser/Token$TokenType.ordinal:()I
        48: iconst_3
        49: iastore
        50: goto          54
        53: astore_0
        54: getstatic     #24                 // Field $SwitchMap$org$jsoup$parser$Token$TokenType:[I
        57: getstatic     #41                 // Field coursier/util/shaded/org/jsoup/parser/Token$TokenType.EndTag:Lcoursier/util/shaded/org/jsoup/parser/Token$TokenType;
        60: invokevirtual #32                 // Method coursier/util/shaded/org/jsoup/parser/Token$TokenType.ordinal:()I
        63: iconst_4
        64: iastore
        65: goto          69
        68: astore_0
        69: getstatic     #24                 // Field $SwitchMap$org$jsoup$parser$Token$TokenType:[I
        72: getstatic     #44                 // Field coursier/util/shaded/org/jsoup/parser/Token$TokenType.Character:Lcoursier/util/shaded/org/jsoup/parser/Token$TokenType;
        75: invokevirtual #32                 // Method coursier/util/shaded/org/jsoup/parser/Token$TokenType.ordinal:()I
        78: iconst_5
        79: iastore
        80: goto          84
        83: astore_0
        84: getstatic     #24                 // Field $SwitchMap$org$jsoup$parser$Token$TokenType:[I
        87: getstatic     #47                 // Field coursier/util/shaded/org/jsoup/parser/Token$TokenType.EOF:Lcoursier/util/shaded/org/jsoup/parser/Token$TokenType;
        90: invokevirtual #32                 // Method coursier/util/shaded/org/jsoup/parser/Token$TokenType.ordinal:()I
        93: bipush        6
        95: iastore
        96: goto          100
        99: astore_0
       100: return
      Exception table:
         from    to  target type
             9    20    23   Class java/lang/NoSuchFieldError
            24    35    38   Class java/lang/NoSuchFieldError
            39    50    53   Class java/lang/NoSuchFieldError
            54    65    68   Class java/lang/NoSuchFieldError
            69    80    83   Class java/lang/NoSuchFieldError
            84    96    99   Class java/lang/NoSuchFieldError
      StackMapTable: number_of_entries = 12
        frame_type = 87 /* same_locals_1_stack_item */
          stack = [ class java/lang/NoSuchFieldError ]
        frame_type = 0 /* same */
        frame_type = 77 /* same_locals_1_stack_item */
          stack = [ class java/lang/NoSuchFieldError ]
        frame_type = 0 /* same */
        frame_type = 77 /* same_locals_1_stack_item */
          stack = [ class java/lang/NoSuchFieldError ]
        frame_type = 0 /* same */
        frame_type = 77 /* same_locals_1_stack_item */
          stack = [ class java/lang/NoSuchFieldError ]
        frame_type = 0 /* same */
        frame_type = 77 /* same_locals_1_stack_item */
          stack = [ class java/lang/NoSuchFieldError ]
        frame_type = 0 /* same */
        frame_type = 78 /* same_locals_1_stack_item */
          stack = [ class java/lang/NoSuchFieldError ]
        frame_type = 0 /* same */
      LineNumberTable:
        line 108: 0
}
InnerClasses:
  public static final #12= #9 of #11;     // TokenType=class coursier/util/shaded/org/jsoup/parser/Token$TokenType of class coursier/util/shaded/org/jsoup/parser/Token
  static #2;                              // class coursier/util/shaded/org/jsoup/parser/HtmlTreeBuilderState$24
EnclosingMethod: #7.#0                  // coursier.util.shaded.org.jsoup.parser.HtmlTreeBuilderState
SourceFile: "HtmlTreeBuilderState.java"
