Classfile /Users/mw/Projects/slang-braindump/.jar/jar11/assemble/slang-braindump/assemble/content/coursier/util/shaded/org/jsoup/parser/HtmlTreeBuilderState$10.class
  Last modified May 29, 2022; size 3436 bytes
  SHA-256 checksum 9f6e67ebe130cfb34cdb70dd980105db5946828c9d444302848956c02e242081
  Compiled from "HtmlTreeBuilderState.java"
final class coursier.util.shaded.org.jsoup.parser.HtmlTreeBuilderState$10 extends coursier.util.shaded.org.jsoup.parser.HtmlTreeBuilderState
  minor version: 0
  major version: 51
  flags: (0x4030) ACC_FINAL, ACC_SUPER, ACC_ENUM
  this_class: #2                          // coursier/util/shaded/org/jsoup/parser/HtmlTreeBuilderState$10
  super_class: #4                         // coursier/util/shaded/org/jsoup/parser/HtmlTreeBuilderState
  interfaces: 0, fields: 0, methods: 2, attributes: 3
Constant pool:
    #1 = Utf8               coursier/util/shaded/org/jsoup/parser/HtmlTreeBuilderState$10
    #2 = Class              #1            // coursier/util/shaded/org/jsoup/parser/HtmlTreeBuilderState$10
    #3 = Utf8               coursier/util/shaded/org/jsoup/parser/HtmlTreeBuilderState
    #4 = Class              #3            // coursier/util/shaded/org/jsoup/parser/HtmlTreeBuilderState
    #5 = Utf8               HtmlTreeBuilderState.java
    #6 = Utf8               coursier/util/shaded/org/jsoup/parser/HtmlTreeBuilderState$1
    #7 = Class              #6            // coursier/util/shaded/org/jsoup/parser/HtmlTreeBuilderState$1
    #8 = Utf8               coursier/util/shaded/org/jsoup/parser/Token$TokenType
    #9 = Class              #8            // coursier/util/shaded/org/jsoup/parser/Token$TokenType
   #10 = Utf8               coursier/util/shaded/org/jsoup/parser/Token
   #11 = Class              #10           // coursier/util/shaded/org/jsoup/parser/Token
   #12 = Utf8               TokenType
   #13 = Utf8               coursier/util/shaded/org/jsoup/parser/Token$Character
   #14 = Class              #13           // coursier/util/shaded/org/jsoup/parser/Token$Character
   #15 = Utf8               Character
   #16 = Utf8               coursier/util/shaded/org/jsoup/parser/HtmlTreeBuilderState$Constants
   #17 = Class              #16           // coursier/util/shaded/org/jsoup/parser/HtmlTreeBuilderState$Constants
   #18 = Utf8               Constants
   #19 = Utf8               <init>
   #20 = Utf8               (Ljava/lang/String;I)V
   #21 = Utf8               (Ljava/lang/String;ILcoursier/util/shaded/org/jsoup/parser/HtmlTreeBuilderState$1;)V
   #22 = NameAndType        #19:#21       // "<init>":(Ljava/lang/String;ILcoursier/util/shaded/org/jsoup/parser/HtmlTreeBuilderState$1;)V
   #23 = Methodref          #4.#22        // coursier/util/shaded/org/jsoup/parser/HtmlTreeBuilderState."<init>":(Ljava/lang/String;ILcoursier/util/shaded/org/jsoup/parser/HtmlTreeBuilderState$1;)V
   #24 = Utf8               this
   #25 = Utf8               Lcoursier/util/shaded/org/jsoup/parser/HtmlTreeBuilderState$10;
   #26 = Utf8               process
   #27 = Utf8               (Lcoursier/util/shaded/org/jsoup/parser/Token;Lcoursier/util/shaded/org/jsoup/parser/HtmlTreeBuilder;)Z
   #28 = Utf8               type
   #29 = Utf8               Lcoursier/util/shaded/org/jsoup/parser/Token$TokenType;
   #30 = NameAndType        #28:#29       // type:Lcoursier/util/shaded/org/jsoup/parser/Token$TokenType;
   #31 = Fieldref           #11.#30       // coursier/util/shaded/org/jsoup/parser/Token.type:Lcoursier/util/shaded/org/jsoup/parser/Token$TokenType;
   #32 = NameAndType        #15:#29       // Character:Lcoursier/util/shaded/org/jsoup/parser/Token$TokenType;
   #33 = Fieldref           #9.#32        // coursier/util/shaded/org/jsoup/parser/Token$TokenType.Character:Lcoursier/util/shaded/org/jsoup/parser/Token$TokenType;
   #34 = Utf8               asCharacter
   #35 = Utf8               ()Lcoursier/util/shaded/org/jsoup/parser/Token$Character;
   #36 = NameAndType        #34:#35       // asCharacter:()Lcoursier/util/shaded/org/jsoup/parser/Token$Character;
   #37 = Methodref          #11.#36       // coursier/util/shaded/org/jsoup/parser/Token.asCharacter:()Lcoursier/util/shaded/org/jsoup/parser/Token$Character;
   #38 = Utf8               getData
   #39 = Utf8               ()Ljava/lang/String;
   #40 = NameAndType        #38:#39       // getData:()Ljava/lang/String;
   #41 = Methodref          #14.#40       // coursier/util/shaded/org/jsoup/parser/Token$Character.getData:()Ljava/lang/String;
   #42 = Utf8               access$400
   #43 = NameAndType        #42:#39       // access$400:()Ljava/lang/String;
   #44 = Methodref          #4.#43        // coursier/util/shaded/org/jsoup/parser/HtmlTreeBuilderState.access$400:()Ljava/lang/String;
   #45 = Utf8               java/lang/String
   #46 = Class              #45           // java/lang/String
   #47 = Utf8               equals
   #48 = Utf8               (Ljava/lang/Object;)Z
   #49 = NameAndType        #47:#48       // equals:(Ljava/lang/Object;)Z
   #50 = Methodref          #46.#49       // java/lang/String.equals:(Ljava/lang/Object;)Z
   #51 = Utf8               coursier/util/shaded/org/jsoup/parser/HtmlTreeBuilder
   #52 = Class              #51           // coursier/util/shaded/org/jsoup/parser/HtmlTreeBuilder
   #53 = Utf8               error
   #54 = Utf8               (Lcoursier/util/shaded/org/jsoup/parser/HtmlTreeBuilderState;)V
   #55 = NameAndType        #53:#54       // error:(Lcoursier/util/shaded/org/jsoup/parser/HtmlTreeBuilderState;)V
   #56 = Methodref          #52.#55       // coursier/util/shaded/org/jsoup/parser/HtmlTreeBuilder.error:(Lcoursier/util/shaded/org/jsoup/parser/HtmlTreeBuilderState;)V
   #57 = Utf8               getPendingTableCharacters
   #58 = Utf8               ()Ljava/util/List;
   #59 = NameAndType        #57:#58       // getPendingTableCharacters:()Ljava/util/List;
   #60 = Methodref          #52.#59       // coursier/util/shaded/org/jsoup/parser/HtmlTreeBuilder.getPendingTableCharacters:()Ljava/util/List;
   #61 = Utf8               java/util/List
   #62 = Class              #61           // java/util/List
   #63 = Utf8               add
   #64 = NameAndType        #63:#48       // add:(Ljava/lang/Object;)Z
   #65 = InterfaceMethodref #62.#64       // java/util/List.add:(Ljava/lang/Object;)Z
   #66 = Utf8               size
   #67 = Utf8               ()I
   #68 = NameAndType        #66:#67       // size:()I
   #69 = InterfaceMethodref #62.#68       // java/util/List.size:()I
   #70 = Utf8               iterator
   #71 = Utf8               ()Ljava/util/Iterator;
   #72 = NameAndType        #70:#71       // iterator:()Ljava/util/Iterator;
   #73 = InterfaceMethodref #62.#72       // java/util/List.iterator:()Ljava/util/Iterator;
   #74 = Utf8               java/util/Iterator
   #75 = Class              #74           // java/util/Iterator
   #76 = Utf8               hasNext
   #77 = Utf8               ()Z
   #78 = NameAndType        #76:#77       // hasNext:()Z
   #79 = InterfaceMethodref #75.#78       // java/util/Iterator.hasNext:()Z
   #80 = Utf8               next
   #81 = Utf8               ()Ljava/lang/Object;
   #82 = NameAndType        #80:#81       // next:()Ljava/lang/Object;
   #83 = InterfaceMethodref #75.#82       // java/util/Iterator.next:()Ljava/lang/Object;
   #84 = Utf8               access$500
   #85 = Utf8               (Ljava/lang/String;)Z
   #86 = NameAndType        #84:#85       // access$500:(Ljava/lang/String;)Z
   #87 = Methodref          #4.#86        // coursier/util/shaded/org/jsoup/parser/HtmlTreeBuilderState.access$500:(Ljava/lang/String;)Z
   #88 = Utf8               currentElement
   #89 = Utf8               ()Lcoursier/util/shaded/org/jsoup/nodes/Element;
   #90 = NameAndType        #88:#89       // currentElement:()Lcoursier/util/shaded/org/jsoup/nodes/Element;
   #91 = Methodref          #52.#90       // coursier/util/shaded/org/jsoup/parser/HtmlTreeBuilder.currentElement:()Lcoursier/util/shaded/org/jsoup/nodes/Element;
   #92 = Utf8               coursier/util/shaded/org/jsoup/nodes/Element
   #93 = Class              #92           // coursier/util/shaded/org/jsoup/nodes/Element
   #94 = Utf8               normalName
   #95 = NameAndType        #94:#39       // normalName:()Ljava/lang/String;
   #96 = Methodref          #93.#95       // coursier/util/shaded/org/jsoup/nodes/Element.normalName:()Ljava/lang/String;
   #97 = Utf8               InTableFoster
   #98 = Utf8               [Ljava/lang/String;
   #99 = NameAndType        #97:#98       // InTableFoster:[Ljava/lang/String;
  #100 = Fieldref           #17.#99       // coursier/util/shaded/org/jsoup/parser/HtmlTreeBuilderState$Constants.InTableFoster:[Ljava/lang/String;
  #101 = Utf8               coursier/util/shaded/org/jsoup/internal/StringUtil
  #102 = Class              #101          // coursier/util/shaded/org/jsoup/internal/StringUtil
  #103 = Utf8               inSorted
  #104 = Utf8               (Ljava/lang/String;[Ljava/lang/String;)Z
  #105 = NameAndType        #103:#104     // inSorted:(Ljava/lang/String;[Ljava/lang/String;)Z
  #106 = Methodref          #102.#105     // coursier/util/shaded/org/jsoup/internal/StringUtil.inSorted:(Ljava/lang/String;[Ljava/lang/String;)Z
  #107 = Utf8               setFosterInserts
  #108 = Utf8               (Z)V
  #109 = NameAndType        #107:#108     // setFosterInserts:(Z)V
  #110 = Methodref          #52.#109      // coursier/util/shaded/org/jsoup/parser/HtmlTreeBuilder.setFosterInserts:(Z)V
  #111 = Utf8               ()V
  #112 = NameAndType        #19:#111      // "<init>":()V
  #113 = Methodref          #14.#112      // coursier/util/shaded/org/jsoup/parser/Token$Character."<init>":()V
  #114 = Utf8               data
  #115 = Utf8               (Ljava/lang/String;)Lcoursier/util/shaded/org/jsoup/parser/Token$Character;
  #116 = NameAndType        #114:#115     // data:(Ljava/lang/String;)Lcoursier/util/shaded/org/jsoup/parser/Token$Character;
  #117 = Methodref          #14.#116      // coursier/util/shaded/org/jsoup/parser/Token$Character.data:(Ljava/lang/String;)Lcoursier/util/shaded/org/jsoup/parser/Token$Character;
  #118 = Utf8               InBody
  #119 = Utf8               Lcoursier/util/shaded/org/jsoup/parser/HtmlTreeBuilderState;
  #120 = NameAndType        #118:#119     // InBody:Lcoursier/util/shaded/org/jsoup/parser/HtmlTreeBuilderState;
  #121 = Fieldref           #2.#120       // coursier/util/shaded/org/jsoup/parser/HtmlTreeBuilderState$10.InBody:Lcoursier/util/shaded/org/jsoup/parser/HtmlTreeBuilderState;
  #122 = Utf8               (Lcoursier/util/shaded/org/jsoup/parser/Token;Lcoursier/util/shaded/org/jsoup/parser/HtmlTreeBuilderState;)Z
  #123 = NameAndType        #26:#122      // process:(Lcoursier/util/shaded/org/jsoup/parser/Token;Lcoursier/util/shaded/org/jsoup/parser/HtmlTreeBuilderState;)Z
  #124 = Methodref          #52.#123      // coursier/util/shaded/org/jsoup/parser/HtmlTreeBuilder.process:(Lcoursier/util/shaded/org/jsoup/parser/Token;Lcoursier/util/shaded/org/jsoup/parser/HtmlTreeBuilderState;)Z
  #125 = Utf8               insert
  #126 = Utf8               (Lcoursier/util/shaded/org/jsoup/parser/Token$Character;)V
  #127 = NameAndType        #125:#126     // insert:(Lcoursier/util/shaded/org/jsoup/parser/Token$Character;)V
  #128 = Methodref          #52.#127      // coursier/util/shaded/org/jsoup/parser/HtmlTreeBuilder.insert:(Lcoursier/util/shaded/org/jsoup/parser/Token$Character;)V
  #129 = Utf8               newPendingTableCharacters
  #130 = NameAndType        #129:#111     // newPendingTableCharacters:()V
  #131 = Methodref          #52.#130      // coursier/util/shaded/org/jsoup/parser/HtmlTreeBuilder.newPendingTableCharacters:()V
  #132 = Utf8               originalState
  #133 = Utf8               ()Lcoursier/util/shaded/org/jsoup/parser/HtmlTreeBuilderState;
  #134 = NameAndType        #132:#133     // originalState:()Lcoursier/util/shaded/org/jsoup/parser/HtmlTreeBuilderState;
  #135 = Methodref          #52.#134      // coursier/util/shaded/org/jsoup/parser/HtmlTreeBuilder.originalState:()Lcoursier/util/shaded/org/jsoup/parser/HtmlTreeBuilderState;
  #136 = Utf8               transition
  #137 = NameAndType        #136:#54      // transition:(Lcoursier/util/shaded/org/jsoup/parser/HtmlTreeBuilderState;)V
  #138 = Methodref          #52.#137      // coursier/util/shaded/org/jsoup/parser/HtmlTreeBuilder.transition:(Lcoursier/util/shaded/org/jsoup/parser/HtmlTreeBuilderState;)V
  #139 = Utf8               (Lcoursier/util/shaded/org/jsoup/parser/Token;)Z
  #140 = NameAndType        #26:#139      // process:(Lcoursier/util/shaded/org/jsoup/parser/Token;)Z
  #141 = Methodref          #52.#140      // coursier/util/shaded/org/jsoup/parser/HtmlTreeBuilder.process:(Lcoursier/util/shaded/org/jsoup/parser/Token;)Z
  #142 = Utf8               c
  #143 = Utf8               Lcoursier/util/shaded/org/jsoup/parser/Token$Character;
  #144 = Utf8               character
  #145 = Utf8               Ljava/lang/String;
  #146 = Utf8               t
  #147 = Utf8               Lcoursier/util/shaded/org/jsoup/parser/Token;
  #148 = Utf8               tb
  #149 = Utf8               Lcoursier/util/shaded/org/jsoup/parser/HtmlTreeBuilder;
  #150 = Utf8               Code
  #151 = Utf8               LineNumberTable
  #152 = Utf8               LocalVariableTable
  #153 = Utf8               StackMapTable
  #154 = Utf8               InnerClasses
  #155 = Utf8               EnclosingMethod
  #156 = Utf8               SourceFile
{
  coursier.util.shaded.org.jsoup.parser.HtmlTreeBuilderState$10(java.lang.String, int);
    descriptor: (Ljava/lang/String;I)V
    flags: (0x0000)
    Code:
      stack=4, locals=3, args_size=3
         0: aload_0
         1: aload_1
         2: iload_2
         3: aconst_null
         4: invokespecial #23                 // Method coursier/util/shaded/org/jsoup/parser/HtmlTreeBuilderState."<init>":(Ljava/lang/String;ILcoursier/util/shaded/org/jsoup/parser/HtmlTreeBuilderState$1;)V
         7: return
      LineNumberTable:
        line 990: 0
      LocalVariableTable:
        Start  Length  Slot  Name   Signature
            0       8     0  this   Lcoursier/util/shaded/org/jsoup/parser/HtmlTreeBuilderState$10;

  boolean process(coursier.util.shaded.org.jsoup.parser.Token, coursier.util.shaded.org.jsoup.parser.HtmlTreeBuilder);
    descriptor: (Lcoursier/util/shaded/org/jsoup/parser/Token;Lcoursier/util/shaded/org/jsoup/parser/HtmlTreeBuilder;)Z
    flags: (0x0000)
    Code:
      stack=3, locals=5, args_size=3
         0: aload_1
         1: getfield      #31                 // Field coursier/util/shaded/org/jsoup/parser/Token.type:Lcoursier/util/shaded/org/jsoup/parser/Token$TokenType;
         4: getstatic     #33                 // Field coursier/util/shaded/org/jsoup/parser/Token$TokenType.Character:Lcoursier/util/shaded/org/jsoup/parser/Token$TokenType;
         7: if_acmpne     52
        10: aload_1
        11: invokevirtual #37                 // Method coursier/util/shaded/org/jsoup/parser/Token.asCharacter:()Lcoursier/util/shaded/org/jsoup/parser/Token$Character;
        14: astore_3
        15: aload_3
        16: invokevirtual #41                 // Method coursier/util/shaded/org/jsoup/parser/Token$Character.getData:()Ljava/lang/String;
        19: invokestatic  #44                 // Method coursier/util/shaded/org/jsoup/parser/HtmlTreeBuilderState.access$400:()Ljava/lang/String;
        22: invokevirtual #50                 // Method java/lang/String.equals:(Ljava/lang/Object;)Z
        25: ifeq          35
        28: aload_2
        29: aload_0
        30: invokevirtual #56                 // Method coursier/util/shaded/org/jsoup/parser/HtmlTreeBuilder.error:(Lcoursier/util/shaded/org/jsoup/parser/HtmlTreeBuilderState;)V
        33: iconst_0
        34: ireturn
        35: aload_2
        36: invokevirtual #60                 // Method coursier/util/shaded/org/jsoup/parser/HtmlTreeBuilder.getPendingTableCharacters:()Ljava/util/List;
        39: aload_3
        40: invokevirtual #41                 // Method coursier/util/shaded/org/jsoup/parser/Token$Character.getData:()Ljava/lang/String;
        43: invokeinterface #65,  2           // InterfaceMethod java/util/List.add:(Ljava/lang/Object;)Z
        48: pop
        49: goto          216
        52: aload_2
        53: invokevirtual #60                 // Method coursier/util/shaded/org/jsoup/parser/HtmlTreeBuilder.getPendingTableCharacters:()Ljava/util/List;
        56: invokeinterface #69,  1           // InterfaceMethod java/util/List.size:()I
        61: ifle          202
        64: aload_2
        65: invokevirtual #60                 // Method coursier/util/shaded/org/jsoup/parser/HtmlTreeBuilder.getPendingTableCharacters:()Ljava/util/List;
        68: invokeinterface #73,  1           // InterfaceMethod java/util/List.iterator:()Ljava/util/Iterator;
        73: astore_3
        74: aload_3
        75: invokeinterface #79,  1           // InterfaceMethod java/util/Iterator.hasNext:()Z
        80: ifeq          198
        83: aload_3
        84: invokeinterface #83,  1           // InterfaceMethod java/util/Iterator.next:()Ljava/lang/Object;
        89: checkcast     #46                 // class java/lang/String
        92: astore        4
        94: aload         4
        96: invokestatic  #87                 // Method coursier/util/shaded/org/jsoup/parser/HtmlTreeBuilderState.access$500:(Ljava/lang/String;)Z
        99: ifne          179
       102: aload_2
       103: aload_0
       104: invokevirtual #56                 // Method coursier/util/shaded/org/jsoup/parser/HtmlTreeBuilder.error:(Lcoursier/util/shaded/org/jsoup/parser/HtmlTreeBuilderState;)V
       107: aload_2
       108: invokevirtual #91                 // Method coursier/util/shaded/org/jsoup/parser/HtmlTreeBuilder.currentElement:()Lcoursier/util/shaded/org/jsoup/nodes/Element;
       111: invokevirtual #96                 // Method coursier/util/shaded/org/jsoup/nodes/Element.normalName:()Ljava/lang/String;
       114: getstatic     #100                // Field coursier/util/shaded/org/jsoup/parser/HtmlTreeBuilderState$Constants.InTableFoster:[Ljava/lang/String;
       117: invokestatic  #106                // Method coursier/util/shaded/org/jsoup/internal/StringUtil.inSorted:(Ljava/lang/String;[Ljava/lang/String;)Z
       120: ifeq          156
       123: aload_2
       124: iconst_1
       125: invokevirtual #110                // Method coursier/util/shaded/org/jsoup/parser/HtmlTreeBuilder.setFosterInserts:(Z)V
       128: aload_2
       129: new           #14                 // class coursier/util/shaded/org/jsoup/parser/Token$Character
       132: dup
       133: invokespecial #113                // Method coursier/util/shaded/org/jsoup/parser/Token$Character."<init>":()V
       136: aload         4
       138: invokevirtual #117                // Method coursier/util/shaded/org/jsoup/parser/Token$Character.data:(Ljava/lang/String;)Lcoursier/util/shaded/org/jsoup/parser/Token$Character;
       141: getstatic     #121                // Field InBody:Lcoursier/util/shaded/org/jsoup/parser/HtmlTreeBuilderState;
       144: invokevirtual #124                // Method coursier/util/shaded/org/jsoup/parser/HtmlTreeBuilder.process:(Lcoursier/util/shaded/org/jsoup/parser/Token;Lcoursier/util/shaded/org/jsoup/parser/HtmlTreeBuilderState;)Z
       147: pop
       148: aload_2
       149: iconst_0
       150: invokevirtual #110                // Method coursier/util/shaded/org/jsoup/parser/HtmlTreeBuilder.setFosterInserts:(Z)V
       153: goto          195
       156: aload_2
       157: new           #14                 // class coursier/util/shaded/org/jsoup/parser/Token$Character
       160: dup
       161: invokespecial #113                // Method coursier/util/shaded/org/jsoup/parser/Token$Character."<init>":()V
       164: aload         4
       166: invokevirtual #117                // Method coursier/util/shaded/org/jsoup/parser/Token$Character.data:(Ljava/lang/String;)Lcoursier/util/shaded/org/jsoup/parser/Token$Character;
       169: getstatic     #121                // Field InBody:Lcoursier/util/shaded/org/jsoup/parser/HtmlTreeBuilderState;
       172: invokevirtual #124                // Method coursier/util/shaded/org/jsoup/parser/HtmlTreeBuilder.process:(Lcoursier/util/shaded/org/jsoup/parser/Token;Lcoursier/util/shaded/org/jsoup/parser/HtmlTreeBuilderState;)Z
       175: pop
       176: goto          195
       179: aload_2
       180: new           #14                 // class coursier/util/shaded/org/jsoup/parser/Token$Character
       183: dup
       184: invokespecial #113                // Method coursier/util/shaded/org/jsoup/parser/Token$Character."<init>":()V
       187: aload         4
       189: invokevirtual #117                // Method coursier/util/shaded/org/jsoup/parser/Token$Character.data:(Ljava/lang/String;)Lcoursier/util/shaded/org/jsoup/parser/Token$Character;
       192: invokevirtual #128                // Method coursier/util/shaded/org/jsoup/parser/HtmlTreeBuilder.insert:(Lcoursier/util/shaded/org/jsoup/parser/Token$Character;)V
       195: goto          74
       198: aload_2
       199: invokevirtual #131                // Method coursier/util/shaded/org/jsoup/parser/HtmlTreeBuilder.newPendingTableCharacters:()V
       202: aload_2
       203: aload_2
       204: invokevirtual #135                // Method coursier/util/shaded/org/jsoup/parser/HtmlTreeBuilder.originalState:()Lcoursier/util/shaded/org/jsoup/parser/HtmlTreeBuilderState;
       207: invokevirtual #138                // Method coursier/util/shaded/org/jsoup/parser/HtmlTreeBuilder.transition:(Lcoursier/util/shaded/org/jsoup/parser/HtmlTreeBuilderState;)V
       210: aload_2
       211: aload_1
       212: invokevirtual #141                // Method coursier/util/shaded/org/jsoup/parser/HtmlTreeBuilder.process:(Lcoursier/util/shaded/org/jsoup/parser/Token;)Z
       215: ireturn
       216: iconst_1
       217: ireturn
      StackMapTable: number_of_entries = 9
        frame_type = 252 /* append */
          offset_delta = 35
          locals = [ class coursier/util/shaded/org/jsoup/parser/Token$Character ]
        frame_type = 250 /* chop */
          offset_delta = 16
        frame_type = 252 /* append */
          offset_delta = 21
          locals = [ class java/util/Iterator ]
        frame_type = 252 /* append */
          offset_delta = 81
          locals = [ class java/lang/String ]
        frame_type = 22 /* same */
        frame_type = 250 /* chop */
          offset_delta = 15
        frame_type = 250 /* chop */
          offset_delta = 2
        frame_type = 3 /* same */
        frame_type = 13 /* same */
      LineNumberTable:
        line 992: 0
        line 993: 10
        line 994: 15
        line 995: 28
        line 996: 33
        line 998: 35
        line 1000: 49
        line 1001: 52
        line 1002: 64
        line 1003: 94
        line 1005: 102
        line 1006: 107
        line 1007: 123
        line 1008: 128
        line 1009: 148
        line 1011: 156
        line 1014: 179
        line 1015: 195
        line 1016: 198
        line 1018: 202
        line 1019: 210
        line 1021: 216
      LocalVariableTable:
        Start  Length  Slot  Name   Signature
           15      34     3     c   Lcoursier/util/shaded/org/jsoup/parser/Token$Character;
           94     101     4 character   Ljava/lang/String;
            0     218     0  this   Lcoursier/util/shaded/org/jsoup/parser/HtmlTreeBuilderState$10;
            0     218     1     t   Lcoursier/util/shaded/org/jsoup/parser/Token;
            0     218     2    tb   Lcoursier/util/shaded/org/jsoup/parser/HtmlTreeBuilder;
}
InnerClasses:
  final #7;                               // class coursier/util/shaded/org/jsoup/parser/HtmlTreeBuilderState$1
  public static final #12= #9 of #11;     // TokenType=class coursier/util/shaded/org/jsoup/parser/Token$TokenType of class coursier/util/shaded/org/jsoup/parser/Token
  static #15= #14 of #11;                 // Character=class coursier/util/shaded/org/jsoup/parser/Token$Character of class coursier/util/shaded/org/jsoup/parser/Token
  static final #18= #17 of #4;            // Constants=class coursier/util/shaded/org/jsoup/parser/HtmlTreeBuilderState$Constants of class coursier/util/shaded/org/jsoup/parser/HtmlTreeBuilderState
  final #2;                               // class coursier/util/shaded/org/jsoup/parser/HtmlTreeBuilderState$10
EnclosingMethod: #4.#0                  // coursier.util.shaded.org.jsoup.parser.HtmlTreeBuilderState
SourceFile: "HtmlTreeBuilderState.java"
