Classfile /Users/mw/Projects/slang-braindump/.jar/jar11/assemble/slang-braindump/assemble/content/coursier/util/shaded/org/jsoup/parser/Parser.class
  Last modified May 29, 2022; size 6733 bytes
  SHA-256 checksum 930873388cbdc6ec0ce3a63745613a81352a3cec88ccf9779d73035b43dfbe31
  Compiled from "Parser.java"
public class coursier.util.shaded.org.jsoup.parser.Parser
  minor version: 0
  major version: 51
  flags: (0x0021) ACC_PUBLIC, ACC_SUPER
  this_class: #2                          // coursier/util/shaded/org/jsoup/parser/Parser
  super_class: #4                         // java/lang/Object
  interfaces: 0, fields: 3, methods: 19, attributes: 1
Constant pool:
    #1 = Utf8               coursier/util/shaded/org/jsoup/parser/Parser
    #2 = Class              #1            // coursier/util/shaded/org/jsoup/parser/Parser
    #3 = Utf8               java/lang/Object
    #4 = Class              #3            // java/lang/Object
    #5 = Utf8               Parser.java
    #6 = Utf8               treeBuilder
    #7 = Utf8               Lcoursier/util/shaded/org/jsoup/parser/TreeBuilder;
    #8 = Utf8               errors
    #9 = Utf8               Lcoursier/util/shaded/org/jsoup/parser/ParseErrorList;
   #10 = Utf8               settings
   #11 = Utf8               Lcoursier/util/shaded/org/jsoup/parser/ParseSettings;
   #12 = Utf8               <init>
   #13 = Utf8               (Lcoursier/util/shaded/org/jsoup/parser/TreeBuilder;)V
   #14 = Utf8               ()V
   #15 = NameAndType        #12:#14       // "<init>":()V
   #16 = Methodref          #4.#15        // java/lang/Object."<init>":()V
   #17 = NameAndType        #6:#7         // treeBuilder:Lcoursier/util/shaded/org/jsoup/parser/TreeBuilder;
   #18 = Fieldref           #2.#17        // coursier/util/shaded/org/jsoup/parser/Parser.treeBuilder:Lcoursier/util/shaded/org/jsoup/parser/TreeBuilder;
   #19 = Utf8               coursier/util/shaded/org/jsoup/parser/TreeBuilder
   #20 = Class              #19           // coursier/util/shaded/org/jsoup/parser/TreeBuilder
   #21 = Utf8               defaultSettings
   #22 = Utf8               ()Lcoursier/util/shaded/org/jsoup/parser/ParseSettings;
   #23 = NameAndType        #21:#22       // defaultSettings:()Lcoursier/util/shaded/org/jsoup/parser/ParseSettings;
   #24 = Methodref          #20.#23       // coursier/util/shaded/org/jsoup/parser/TreeBuilder.defaultSettings:()Lcoursier/util/shaded/org/jsoup/parser/ParseSettings;
   #25 = NameAndType        #10:#11       // settings:Lcoursier/util/shaded/org/jsoup/parser/ParseSettings;
   #26 = Fieldref           #2.#25        // coursier/util/shaded/org/jsoup/parser/Parser.settings:Lcoursier/util/shaded/org/jsoup/parser/ParseSettings;
   #27 = Utf8               coursier/util/shaded/org/jsoup/parser/ParseErrorList
   #28 = Class              #27           // coursier/util/shaded/org/jsoup/parser/ParseErrorList
   #29 = Utf8               noTracking
   #30 = Utf8               ()Lcoursier/util/shaded/org/jsoup/parser/ParseErrorList;
   #31 = NameAndType        #29:#30       // noTracking:()Lcoursier/util/shaded/org/jsoup/parser/ParseErrorList;
   #32 = Methodref          #28.#31       // coursier/util/shaded/org/jsoup/parser/ParseErrorList.noTracking:()Lcoursier/util/shaded/org/jsoup/parser/ParseErrorList;
   #33 = NameAndType        #8:#9         // errors:Lcoursier/util/shaded/org/jsoup/parser/ParseErrorList;
   #34 = Fieldref           #2.#33        // coursier/util/shaded/org/jsoup/parser/Parser.errors:Lcoursier/util/shaded/org/jsoup/parser/ParseErrorList;
   #35 = Utf8               this
   #36 = Utf8               Lcoursier/util/shaded/org/jsoup/parser/Parser;
   #37 = Utf8               parseInput
   #38 = Utf8               (Ljava/lang/String;Ljava/lang/String;)Lcoursier/util/shaded/org/jsoup/nodes/Document;
   #39 = Utf8               java/io/StringReader
   #40 = Class              #39           // java/io/StringReader
   #41 = Utf8               (Ljava/lang/String;)V
   #42 = NameAndType        #12:#41       // "<init>":(Ljava/lang/String;)V
   #43 = Methodref          #40.#42       // java/io/StringReader."<init>":(Ljava/lang/String;)V
   #44 = Utf8               parse
   #45 = Utf8               (Ljava/io/Reader;Ljava/lang/String;Lcoursier/util/shaded/org/jsoup/parser/Parser;)Lcoursier/util/shaded/org/jsoup/nodes/Document;
   #46 = NameAndType        #44:#45       // parse:(Ljava/io/Reader;Ljava/lang/String;Lcoursier/util/shaded/org/jsoup/parser/Parser;)Lcoursier/util/shaded/org/jsoup/nodes/Document;
   #47 = Methodref          #20.#46       // coursier/util/shaded/org/jsoup/parser/TreeBuilder.parse:(Ljava/io/Reader;Ljava/lang/String;Lcoursier/util/shaded/org/jsoup/parser/Parser;)Lcoursier/util/shaded/org/jsoup/nodes/Document;
   #48 = Utf8               html
   #49 = Utf8               Ljava/lang/String;
   #50 = Utf8               baseUri
   #51 = Utf8               (Ljava/io/Reader;Ljava/lang/String;)Lcoursier/util/shaded/org/jsoup/nodes/Document;
   #52 = Utf8               inputHtml
   #53 = Utf8               Ljava/io/Reader;
   #54 = Utf8               parseFragmentInput
   #55 = Utf8               (Ljava/lang/String;Lcoursier/util/shaded/org/jsoup/nodes/Element;Ljava/lang/String;)Ljava/util/List;
   #56 = Utf8               (Ljava/lang/String;Lcoursier/util/shaded/org/jsoup/nodes/Element;Ljava/lang/String;)Ljava/util/List<Lcoursier/util/shaded/org/jsoup/nodes/Node;>;
   #57 = Utf8               parseFragment
   #58 = Utf8               (Ljava/lang/String;Lcoursier/util/shaded/org/jsoup/nodes/Element;Ljava/lang/String;Lcoursier/util/shaded/org/jsoup/parser/Parser;)Ljava/util/List;
   #59 = NameAndType        #57:#58       // parseFragment:(Ljava/lang/String;Lcoursier/util/shaded/org/jsoup/nodes/Element;Ljava/lang/String;Lcoursier/util/shaded/org/jsoup/parser/Parser;)Ljava/util/List;
   #60 = Methodref          #20.#59       // coursier/util/shaded/org/jsoup/parser/TreeBuilder.parseFragment:(Ljava/lang/String;Lcoursier/util/shaded/org/jsoup/nodes/Element;Ljava/lang/String;Lcoursier/util/shaded/org/jsoup/parser/Parser;)Ljava/util/List;
   #61 = Utf8               fragment
   #62 = Utf8               context
   #63 = Utf8               Lcoursier/util/shaded/org/jsoup/nodes/Element;
   #64 = Utf8               getTreeBuilder
   #65 = Utf8               ()Lcoursier/util/shaded/org/jsoup/parser/TreeBuilder;
   #66 = Utf8               setTreeBuilder
   #67 = Utf8               (Lcoursier/util/shaded/org/jsoup/parser/TreeBuilder;)Lcoursier/util/shaded/org/jsoup/parser/Parser;
   #68 = Utf8               parser
   #69 = NameAndType        #68:#36       // parser:Lcoursier/util/shaded/org/jsoup/parser/Parser;
   #70 = Fieldref           #20.#69       // coursier/util/shaded/org/jsoup/parser/TreeBuilder.parser:Lcoursier/util/shaded/org/jsoup/parser/Parser;
   #71 = Utf8               isTrackErrors
   #72 = Utf8               ()Z
   #73 = Utf8               getMaxSize
   #74 = Utf8               ()I
   #75 = NameAndType        #73:#74       // getMaxSize:()I
   #76 = Methodref          #28.#75       // coursier/util/shaded/org/jsoup/parser/ParseErrorList.getMaxSize:()I
   #77 = Utf8               setTrackErrors
   #78 = Utf8               (I)Lcoursier/util/shaded/org/jsoup/parser/Parser;
   #79 = Utf8               tracking
   #80 = Utf8               (I)Lcoursier/util/shaded/org/jsoup/parser/ParseErrorList;
   #81 = NameAndType        #79:#80       // tracking:(I)Lcoursier/util/shaded/org/jsoup/parser/ParseErrorList;
   #82 = Methodref          #28.#81       // coursier/util/shaded/org/jsoup/parser/ParseErrorList.tracking:(I)Lcoursier/util/shaded/org/jsoup/parser/ParseErrorList;
   #83 = Utf8               maxErrors
   #84 = Utf8               I
   #85 = Utf8               getErrors
   #86 = Utf8               (Lcoursier/util/shaded/org/jsoup/parser/ParseSettings;)Lcoursier/util/shaded/org/jsoup/parser/Parser;
   #87 = Utf8               coursier/util/shaded/org/jsoup/parser/HtmlTreeBuilder
   #88 = Class              #87           // coursier/util/shaded/org/jsoup/parser/HtmlTreeBuilder
   #89 = Methodref          #88.#15       // coursier/util/shaded/org/jsoup/parser/HtmlTreeBuilder."<init>":()V
   #90 = NameAndType        #12:#13       // "<init>":(Lcoursier/util/shaded/org/jsoup/parser/TreeBuilder;)V
   #91 = Methodref          #2.#90        // coursier/util/shaded/org/jsoup/parser/Parser."<init>":(Lcoursier/util/shaded/org/jsoup/parser/TreeBuilder;)V
   #92 = Methodref          #88.#59       // coursier/util/shaded/org/jsoup/parser/HtmlTreeBuilder.parseFragment:(Ljava/lang/String;Lcoursier/util/shaded/org/jsoup/nodes/Element;Ljava/lang/String;Lcoursier/util/shaded/org/jsoup/parser/Parser;)Ljava/util/List;
   #93 = Utf8               fragmentHtml
   #94 = Utf8               Lcoursier/util/shaded/org/jsoup/parser/HtmlTreeBuilder;
   #95 = Utf8               (Ljava/lang/String;Lcoursier/util/shaded/org/jsoup/nodes/Element;Ljava/lang/String;Lcoursier/util/shaded/org/jsoup/parser/ParseErrorList;)Ljava/util/List;
   #96 = Utf8               (Ljava/lang/String;Lcoursier/util/shaded/org/jsoup/nodes/Element;Ljava/lang/String;Lcoursier/util/shaded/org/jsoup/parser/ParseErrorList;)Ljava/util/List<Lcoursier/util/shaded/org/jsoup/nodes/Node;>;
   #97 = Utf8               errorList
   #98 = Utf8               parseXmlFragment
   #99 = Utf8               (Ljava/lang/String;Ljava/lang/String;)Ljava/util/List;
  #100 = Utf8               (Ljava/lang/String;Ljava/lang/String;)Ljava/util/List<Lcoursier/util/shaded/org/jsoup/nodes/Node;>;
  #101 = Utf8               coursier/util/shaded/org/jsoup/parser/XmlTreeBuilder
  #102 = Class              #101          // coursier/util/shaded/org/jsoup/parser/XmlTreeBuilder
  #103 = Methodref          #102.#15      // coursier/util/shaded/org/jsoup/parser/XmlTreeBuilder."<init>":()V
  #104 = Utf8               (Ljava/lang/String;Ljava/lang/String;Lcoursier/util/shaded/org/jsoup/parser/Parser;)Ljava/util/List;
  #105 = NameAndType        #57:#104      // parseFragment:(Ljava/lang/String;Ljava/lang/String;Lcoursier/util/shaded/org/jsoup/parser/Parser;)Ljava/util/List;
  #106 = Methodref          #102.#105     // coursier/util/shaded/org/jsoup/parser/XmlTreeBuilder.parseFragment:(Ljava/lang/String;Ljava/lang/String;Lcoursier/util/shaded/org/jsoup/parser/Parser;)Ljava/util/List;
  #107 = Utf8               fragmentXml
  #108 = Utf8               Lcoursier/util/shaded/org/jsoup/parser/XmlTreeBuilder;
  #109 = Utf8               parseBodyFragment
  #110 = Utf8               coursier/util/shaded/org/jsoup/nodes/Document
  #111 = Class              #110          // coursier/util/shaded/org/jsoup/nodes/Document
  #112 = Utf8               createShell
  #113 = Utf8               (Ljava/lang/String;)Lcoursier/util/shaded/org/jsoup/nodes/Document;
  #114 = NameAndType        #112:#113     // createShell:(Ljava/lang/String;)Lcoursier/util/shaded/org/jsoup/nodes/Document;
  #115 = Methodref          #111.#114     // coursier/util/shaded/org/jsoup/nodes/Document.createShell:(Ljava/lang/String;)Lcoursier/util/shaded/org/jsoup/nodes/Document;
  #116 = Utf8               body
  #117 = Utf8               ()Lcoursier/util/shaded/org/jsoup/nodes/Element;
  #118 = NameAndType        #116:#117     // body:()Lcoursier/util/shaded/org/jsoup/nodes/Element;
  #119 = Methodref          #111.#118     // coursier/util/shaded/org/jsoup/nodes/Document.body:()Lcoursier/util/shaded/org/jsoup/nodes/Element;
  #120 = NameAndType        #57:#55       // parseFragment:(Ljava/lang/String;Lcoursier/util/shaded/org/jsoup/nodes/Element;Ljava/lang/String;)Ljava/util/List;
  #121 = Methodref          #2.#120       // coursier/util/shaded/org/jsoup/parser/Parser.parseFragment:(Ljava/lang/String;Lcoursier/util/shaded/org/jsoup/nodes/Element;Ljava/lang/String;)Ljava/util/List;
  #122 = Utf8               coursier/util/shaded/org/jsoup/nodes/Node
  #123 = Class              #122          // coursier/util/shaded/org/jsoup/nodes/Node
  #124 = Utf8               java/util/List
  #125 = Class              #124          // java/util/List
  #126 = Utf8               toArray
  #127 = Utf8               ([Ljava/lang/Object;)[Ljava/lang/Object;
  #128 = NameAndType        #126:#127     // toArray:([Ljava/lang/Object;)[Ljava/lang/Object;
  #129 = InterfaceMethodref #125.#128     // java/util/List.toArray:([Ljava/lang/Object;)[Ljava/lang/Object;
  #130 = Utf8               [Lcoursier/util/shaded/org/jsoup/nodes/Node;
  #131 = Class              #130          // "[Lcoursier/util/shaded/org/jsoup/nodes/Node;"
  #132 = Utf8               java/lang/String
  #133 = Class              #132          // java/lang/String
  #134 = Utf8               coursier/util/shaded/org/jsoup/nodes/Element
  #135 = Class              #134          // coursier/util/shaded/org/jsoup/nodes/Element
  #136 = Utf8               remove
  #137 = NameAndType        #136:#14      // remove:()V
  #138 = Methodref          #123.#137     // coursier/util/shaded/org/jsoup/nodes/Node.remove:()V
  #139 = Utf8               appendChild
  #140 = Utf8               (Lcoursier/util/shaded/org/jsoup/nodes/Node;)Lcoursier/util/shaded/org/jsoup/nodes/Element;
  #141 = NameAndType        #139:#140     // appendChild:(Lcoursier/util/shaded/org/jsoup/nodes/Node;)Lcoursier/util/shaded/org/jsoup/nodes/Element;
  #142 = Methodref          #135.#141     // coursier/util/shaded/org/jsoup/nodes/Element.appendChild:(Lcoursier/util/shaded/org/jsoup/nodes/Node;)Lcoursier/util/shaded/org/jsoup/nodes/Element;
  #143 = Utf8               i
  #144 = Utf8               node
  #145 = Utf8               Lcoursier/util/shaded/org/jsoup/nodes/Node;
  #146 = Utf8               bodyHtml
  #147 = Utf8               doc
  #148 = Utf8               Lcoursier/util/shaded/org/jsoup/nodes/Document;
  #149 = Utf8               nodeList
  #150 = Utf8               Ljava/util/List<Lcoursier/util/shaded/org/jsoup/nodes/Node;>;
  #151 = Utf8               Ljava/util/List;
  #152 = Utf8               nodes
  #153 = Utf8               unescapeEntities
  #154 = Utf8               (Ljava/lang/String;Z)Ljava/lang/String;
  #155 = Utf8               coursier/util/shaded/org/jsoup/parser/Tokeniser
  #156 = Class              #155          // coursier/util/shaded/org/jsoup/parser/Tokeniser
  #157 = Utf8               coursier/util/shaded/org/jsoup/parser/CharacterReader
  #158 = Class              #157          // coursier/util/shaded/org/jsoup/parser/CharacterReader
  #159 = Methodref          #158.#42      // coursier/util/shaded/org/jsoup/parser/CharacterReader."<init>":(Ljava/lang/String;)V
  #160 = Utf8               (Lcoursier/util/shaded/org/jsoup/parser/CharacterReader;Lcoursier/util/shaded/org/jsoup/parser/ParseErrorList;)V
  #161 = NameAndType        #12:#160      // "<init>":(Lcoursier/util/shaded/org/jsoup/parser/CharacterReader;Lcoursier/util/shaded/org/jsoup/parser/ParseErrorList;)V
  #162 = Methodref          #156.#161     // coursier/util/shaded/org/jsoup/parser/Tokeniser."<init>":(Lcoursier/util/shaded/org/jsoup/parser/CharacterReader;Lcoursier/util/shaded/org/jsoup/parser/ParseErrorList;)V
  #163 = Utf8               (Z)Ljava/lang/String;
  #164 = NameAndType        #153:#163     // unescapeEntities:(Z)Ljava/lang/String;
  #165 = Methodref          #156.#164     // coursier/util/shaded/org/jsoup/parser/Tokeniser.unescapeEntities:(Z)Ljava/lang/String;
  #166 = Utf8               string
  #167 = Utf8               inAttribute
  #168 = Utf8               Z
  #169 = Utf8               tokeniser
  #170 = Utf8               Lcoursier/util/shaded/org/jsoup/parser/Tokeniser;
  #171 = Utf8               htmlParser
  #172 = Utf8               ()Lcoursier/util/shaded/org/jsoup/parser/Parser;
  #173 = Utf8               xmlParser
  #174 = Utf8               Code
  #175 = Utf8               LineNumberTable
  #176 = Utf8               LocalVariableTable
  #177 = Utf8               Signature
  #178 = Utf8               StackMapTable
  #179 = Utf8               LocalVariableTypeTable
  #180 = Utf8               SourceFile
{
  private coursier.util.shaded.org.jsoup.parser.TreeBuilder treeBuilder;
    descriptor: Lcoursier/util/shaded/org/jsoup/parser/TreeBuilder;
    flags: (0x0002) ACC_PRIVATE

  private coursier.util.shaded.org.jsoup.parser.ParseErrorList errors;
    descriptor: Lcoursier/util/shaded/org/jsoup/parser/ParseErrorList;
    flags: (0x0002) ACC_PRIVATE

  private coursier.util.shaded.org.jsoup.parser.ParseSettings settings;
    descriptor: Lcoursier/util/shaded/org/jsoup/parser/ParseSettings;
    flags: (0x0002) ACC_PRIVATE

  public coursier.util.shaded.org.jsoup.parser.Parser(coursier.util.shaded.org.jsoup.parser.TreeBuilder);
    descriptor: (Lcoursier/util/shaded/org/jsoup/parser/TreeBuilder;)V
    flags: (0x0001) ACC_PUBLIC
    Code:
      stack=2, locals=2, args_size=2
         0: aload_0
         1: invokespecial #16                 // Method java/lang/Object."<init>":()V
         4: aload_0
         5: aload_1
         6: putfield      #18                 // Field treeBuilder:Lcoursier/util/shaded/org/jsoup/parser/TreeBuilder;
         9: aload_0
        10: aload_1
        11: invokevirtual #24                 // Method coursier/util/shaded/org/jsoup/parser/TreeBuilder.defaultSettings:()Lcoursier/util/shaded/org/jsoup/parser/ParseSettings;
        14: putfield      #26                 // Field settings:Lcoursier/util/shaded/org/jsoup/parser/ParseSettings;
        17: aload_0
        18: invokestatic  #32                 // Method coursier/util/shaded/org/jsoup/parser/ParseErrorList.noTracking:()Lcoursier/util/shaded/org/jsoup/parser/ParseErrorList;
        21: putfield      #34                 // Field errors:Lcoursier/util/shaded/org/jsoup/parser/ParseErrorList;
        24: return
      LineNumberTable:
        line 24: 0
        line 25: 4
        line 26: 9
        line 27: 17
        line 28: 24
      LocalVariableTable:
        Start  Length  Slot  Name   Signature
            0      25     0  this   Lcoursier/util/shaded/org/jsoup/parser/Parser;
            0      25     1 treeBuilder   Lcoursier/util/shaded/org/jsoup/parser/TreeBuilder;

  public coursier.util.shaded.org.jsoup.nodes.Document parseInput(java.lang.String, java.lang.String);
    descriptor: (Ljava/lang/String;Ljava/lang/String;)Lcoursier/util/shaded/org/jsoup/nodes/Document;
    flags: (0x0001) ACC_PUBLIC
    Code:
      stack=4, locals=3, args_size=3
         0: aload_0
         1: getfield      #18                 // Field treeBuilder:Lcoursier/util/shaded/org/jsoup/parser/TreeBuilder;
         4: new           #40                 // class java/io/StringReader
         7: dup
         8: aload_1
         9: invokespecial #43                 // Method java/io/StringReader."<init>":(Ljava/lang/String;)V
        12: aload_2
        13: aload_0
        14: invokevirtual #47                 // Method coursier/util/shaded/org/jsoup/parser/TreeBuilder.parse:(Ljava/io/Reader;Ljava/lang/String;Lcoursier/util/shaded/org/jsoup/parser/Parser;)Lcoursier/util/shaded/org/jsoup/nodes/Document;
        17: areturn
      LineNumberTable:
        line 31: 0
      LocalVariableTable:
        Start  Length  Slot  Name   Signature
            0      18     0  this   Lcoursier/util/shaded/org/jsoup/parser/Parser;
            0      18     1  html   Ljava/lang/String;
            0      18     2 baseUri   Ljava/lang/String;

  public coursier.util.shaded.org.jsoup.nodes.Document parseInput(java.io.Reader, java.lang.String);
    descriptor: (Ljava/io/Reader;Ljava/lang/String;)Lcoursier/util/shaded/org/jsoup/nodes/Document;
    flags: (0x0001) ACC_PUBLIC
    Code:
      stack=4, locals=3, args_size=3
         0: aload_0
         1: getfield      #18                 // Field treeBuilder:Lcoursier/util/shaded/org/jsoup/parser/TreeBuilder;
         4: aload_1
         5: aload_2
         6: aload_0
         7: invokevirtual #47                 // Method coursier/util/shaded/org/jsoup/parser/TreeBuilder.parse:(Ljava/io/Reader;Ljava/lang/String;Lcoursier/util/shaded/org/jsoup/parser/Parser;)Lcoursier/util/shaded/org/jsoup/nodes/Document;
        10: areturn
      LineNumberTable:
        line 35: 0
      LocalVariableTable:
        Start  Length  Slot  Name   Signature
            0      11     0  this   Lcoursier/util/shaded/org/jsoup/parser/Parser;
            0      11     1 inputHtml   Ljava/io/Reader;
            0      11     2 baseUri   Ljava/lang/String;

  public java.util.List<coursier.util.shaded.org.jsoup.nodes.Node> parseFragmentInput(java.lang.String, coursier.util.shaded.org.jsoup.nodes.Element, java.lang.String);
    descriptor: (Ljava/lang/String;Lcoursier/util/shaded/org/jsoup/nodes/Element;Ljava/lang/String;)Ljava/util/List;
    flags: (0x0001) ACC_PUBLIC
    Code:
      stack=5, locals=4, args_size=4
         0: aload_0
         1: getfield      #18                 // Field treeBuilder:Lcoursier/util/shaded/org/jsoup/parser/TreeBuilder;
         4: aload_1
         5: aload_2
         6: aload_3
         7: aload_0
         8: invokevirtual #60                 // Method coursier/util/shaded/org/jsoup/parser/TreeBuilder.parseFragment:(Ljava/lang/String;Lcoursier/util/shaded/org/jsoup/nodes/Element;Ljava/lang/String;Lcoursier/util/shaded/org/jsoup/parser/Parser;)Ljava/util/List;
        11: areturn
      LineNumberTable:
        line 39: 0
      LocalVariableTable:
        Start  Length  Slot  Name   Signature
            0      12     0  this   Lcoursier/util/shaded/org/jsoup/parser/Parser;
            0      12     1 fragment   Ljava/lang/String;
            0      12     2 context   Lcoursier/util/shaded/org/jsoup/nodes/Element;
            0      12     3 baseUri   Ljava/lang/String;
    Signature: #56                          // (Ljava/lang/String;Lcoursier/util/shaded/org/jsoup/nodes/Element;Ljava/lang/String;)Ljava/util/List<Lcoursier/util/shaded/org/jsoup/nodes/Node;>;

  public coursier.util.shaded.org.jsoup.parser.TreeBuilder getTreeBuilder();
    descriptor: ()Lcoursier/util/shaded/org/jsoup/parser/TreeBuilder;
    flags: (0x0001) ACC_PUBLIC
    Code:
      stack=1, locals=1, args_size=1
         0: aload_0
         1: getfield      #18                 // Field treeBuilder:Lcoursier/util/shaded/org/jsoup/parser/TreeBuilder;
         4: areturn
      LineNumberTable:
        line 47: 0
      LocalVariableTable:
        Start  Length  Slot  Name   Signature
            0       5     0  this   Lcoursier/util/shaded/org/jsoup/parser/Parser;

  public coursier.util.shaded.org.jsoup.parser.Parser setTreeBuilder(coursier.util.shaded.org.jsoup.parser.TreeBuilder);
    descriptor: (Lcoursier/util/shaded/org/jsoup/parser/TreeBuilder;)Lcoursier/util/shaded/org/jsoup/parser/Parser;
    flags: (0x0001) ACC_PUBLIC
    Code:
      stack=2, locals=2, args_size=2
         0: aload_0
         1: aload_1
         2: putfield      #18                 // Field treeBuilder:Lcoursier/util/shaded/org/jsoup/parser/TreeBuilder;
         5: aload_1
         6: aload_0
         7: putfield      #70                 // Field coursier/util/shaded/org/jsoup/parser/TreeBuilder.parser:Lcoursier/util/shaded/org/jsoup/parser/Parser;
        10: aload_0
        11: areturn
      LineNumberTable:
        line 56: 0
        line 57: 5
        line 58: 10
      LocalVariableTable:
        Start  Length  Slot  Name   Signature
            0      12     0  this   Lcoursier/util/shaded/org/jsoup/parser/Parser;
            0      12     1 treeBuilder   Lcoursier/util/shaded/org/jsoup/parser/TreeBuilder;

  public boolean isTrackErrors();
    descriptor: ()Z
    flags: (0x0001) ACC_PUBLIC
    Code:
      stack=1, locals=1, args_size=1
         0: aload_0
         1: getfield      #34                 // Field errors:Lcoursier/util/shaded/org/jsoup/parser/ParseErrorList;
         4: invokevirtual #76                 // Method coursier/util/shaded/org/jsoup/parser/ParseErrorList.getMaxSize:()I
         7: ifle          14
        10: iconst_1
        11: goto          15
        14: iconst_0
        15: ireturn
      StackMapTable: number_of_entries = 2
        frame_type = 14 /* same */
        frame_type = 64 /* same_locals_1_stack_item */
          stack = [ int ]
      LineNumberTable:
        line 66: 0
      LocalVariableTable:
        Start  Length  Slot  Name   Signature
            0      16     0  this   Lcoursier/util/shaded/org/jsoup/parser/Parser;

  public coursier.util.shaded.org.jsoup.parser.Parser setTrackErrors(int);
    descriptor: (I)Lcoursier/util/shaded/org/jsoup/parser/Parser;
    flags: (0x0001) ACC_PUBLIC
    Code:
      stack=2, locals=2, args_size=2
         0: aload_0
         1: iload_1
         2: ifle          12
         5: iload_1
         6: invokestatic  #82                 // Method coursier/util/shaded/org/jsoup/parser/ParseErrorList.tracking:(I)Lcoursier/util/shaded/org/jsoup/parser/ParseErrorList;
         9: goto          15
        12: invokestatic  #32                 // Method coursier/util/shaded/org/jsoup/parser/ParseErrorList.noTracking:()Lcoursier/util/shaded/org/jsoup/parser/ParseErrorList;
        15: putfield      #34                 // Field errors:Lcoursier/util/shaded/org/jsoup/parser/ParseErrorList;
        18: aload_0
        19: areturn
      StackMapTable: number_of_entries = 2
        frame_type = 76 /* same_locals_1_stack_item */
          stack = [ class coursier/util/shaded/org/jsoup/parser/Parser ]
        frame_type = 255 /* full_frame */
          offset_delta = 2
          locals = [ class coursier/util/shaded/org/jsoup/parser/Parser, int ]
          stack = [ class coursier/util/shaded/org/jsoup/parser/Parser, class coursier/util/shaded/org/jsoup/parser/ParseErrorList ]
      LineNumberTable:
        line 75: 0
        line 76: 18
      LocalVariableTable:
        Start  Length  Slot  Name   Signature
            0      20     0  this   Lcoursier/util/shaded/org/jsoup/parser/Parser;
            0      20     1 maxErrors   I

  public coursier.util.shaded.org.jsoup.parser.ParseErrorList getErrors();
    descriptor: ()Lcoursier/util/shaded/org/jsoup/parser/ParseErrorList;
    flags: (0x0001) ACC_PUBLIC
    Code:
      stack=1, locals=1, args_size=1
         0: aload_0
         1: getfield      #34                 // Field errors:Lcoursier/util/shaded/org/jsoup/parser/ParseErrorList;
         4: areturn
      LineNumberTable:
        line 84: 0
      LocalVariableTable:
        Start  Length  Slot  Name   Signature
            0       5     0  this   Lcoursier/util/shaded/org/jsoup/parser/Parser;

  public coursier.util.shaded.org.jsoup.parser.Parser settings(coursier.util.shaded.org.jsoup.parser.ParseSettings);
    descriptor: (Lcoursier/util/shaded/org/jsoup/parser/ParseSettings;)Lcoursier/util/shaded/org/jsoup/parser/Parser;
    flags: (0x0001) ACC_PUBLIC
    Code:
      stack=2, locals=2, args_size=2
         0: aload_0
         1: aload_1
         2: putfield      #26                 // Field settings:Lcoursier/util/shaded/org/jsoup/parser/ParseSettings;
         5: aload_0
         6: areturn
      LineNumberTable:
        line 88: 0
        line 89: 5
      LocalVariableTable:
        Start  Length  Slot  Name   Signature
            0       7     0  this   Lcoursier/util/shaded/org/jsoup/parser/Parser;
            0       7     1 settings   Lcoursier/util/shaded/org/jsoup/parser/ParseSettings;

  public coursier.util.shaded.org.jsoup.parser.ParseSettings settings();
    descriptor: ()Lcoursier/util/shaded/org/jsoup/parser/ParseSettings;
    flags: (0x0001) ACC_PUBLIC
    Code:
      stack=1, locals=1, args_size=1
         0: aload_0
         1: getfield      #26                 // Field settings:Lcoursier/util/shaded/org/jsoup/parser/ParseSettings;
         4: areturn
      LineNumberTable:
        line 93: 0
      LocalVariableTable:
        Start  Length  Slot  Name   Signature
            0       5     0  this   Lcoursier/util/shaded/org/jsoup/parser/Parser;

  public static coursier.util.shaded.org.jsoup.nodes.Document parse(java.lang.String, java.lang.String);
    descriptor: (Ljava/lang/String;Ljava/lang/String;)Lcoursier/util/shaded/org/jsoup/nodes/Document;
    flags: (0x0009) ACC_PUBLIC, ACC_STATIC
    Code:
      stack=6, locals=3, args_size=2
         0: new           #88                 // class coursier/util/shaded/org/jsoup/parser/HtmlTreeBuilder
         3: dup
         4: invokespecial #89                 // Method coursier/util/shaded/org/jsoup/parser/HtmlTreeBuilder."<init>":()V
         7: astore_2
         8: aload_2
         9: new           #40                 // class java/io/StringReader
        12: dup
        13: aload_0
        14: invokespecial #43                 // Method java/io/StringReader."<init>":(Ljava/lang/String;)V
        17: aload_1
        18: new           #2                  // class coursier/util/shaded/org/jsoup/parser/Parser
        21: dup
        22: aload_2
        23: invokespecial #91                 // Method "<init>":(Lcoursier/util/shaded/org/jsoup/parser/TreeBuilder;)V
        26: invokevirtual #47                 // Method coursier/util/shaded/org/jsoup/parser/TreeBuilder.parse:(Ljava/io/Reader;Ljava/lang/String;Lcoursier/util/shaded/org/jsoup/parser/Parser;)Lcoursier/util/shaded/org/jsoup/nodes/Document;
        29: areturn
      LineNumberTable:
        line 106: 0
        line 107: 8
      LocalVariableTable:
        Start  Length  Slot  Name   Signature
            0      30     0  html   Ljava/lang/String;
            0      30     1 baseUri   Ljava/lang/String;
            8      22     2 treeBuilder   Lcoursier/util/shaded/org/jsoup/parser/TreeBuilder;

  public static java.util.List<coursier.util.shaded.org.jsoup.nodes.Node> parseFragment(java.lang.String, coursier.util.shaded.org.jsoup.nodes.Element, java.lang.String);
    descriptor: (Ljava/lang/String;Lcoursier/util/shaded/org/jsoup/nodes/Element;Ljava/lang/String;)Ljava/util/List;
    flags: (0x0009) ACC_PUBLIC, ACC_STATIC
    Code:
      stack=7, locals=4, args_size=3
         0: new           #88                 // class coursier/util/shaded/org/jsoup/parser/HtmlTreeBuilder
         3: dup
         4: invokespecial #89                 // Method coursier/util/shaded/org/jsoup/parser/HtmlTreeBuilder."<init>":()V
         7: astore_3
         8: aload_3
         9: aload_0
        10: aload_1
        11: aload_2
        12: new           #2                  // class coursier/util/shaded/org/jsoup/parser/Parser
        15: dup
        16: aload_3
        17: invokespecial #91                 // Method "<init>":(Lcoursier/util/shaded/org/jsoup/parser/TreeBuilder;)V
        20: invokevirtual #92                 // Method coursier/util/shaded/org/jsoup/parser/HtmlTreeBuilder.parseFragment:(Ljava/lang/String;Lcoursier/util/shaded/org/jsoup/nodes/Element;Ljava/lang/String;Lcoursier/util/shaded/org/jsoup/parser/Parser;)Ljava/util/List;
        23: areturn
      LineNumberTable:
        line 121: 0
        line 122: 8
      LocalVariableTable:
        Start  Length  Slot  Name   Signature
            0      24     0 fragmentHtml   Ljava/lang/String;
            0      24     1 context   Lcoursier/util/shaded/org/jsoup/nodes/Element;
            0      24     2 baseUri   Ljava/lang/String;
            8      16     3 treeBuilder   Lcoursier/util/shaded/org/jsoup/parser/HtmlTreeBuilder;
    Signature: #56                          // (Ljava/lang/String;Lcoursier/util/shaded/org/jsoup/nodes/Element;Ljava/lang/String;)Ljava/util/List<Lcoursier/util/shaded/org/jsoup/nodes/Node;>;

  public static java.util.List<coursier.util.shaded.org.jsoup.nodes.Node> parseFragment(java.lang.String, coursier.util.shaded.org.jsoup.nodes.Element, java.lang.String, coursier.util.shaded.org.jsoup.parser.ParseErrorList);
    descriptor: (Ljava/lang/String;Lcoursier/util/shaded/org/jsoup/nodes/Element;Ljava/lang/String;Lcoursier/util/shaded/org/jsoup/parser/ParseErrorList;)Ljava/util/List;
    flags: (0x0009) ACC_PUBLIC, ACC_STATIC
    Code:
      stack=5, locals=6, args_size=4
         0: new           #88                 // class coursier/util/shaded/org/jsoup/parser/HtmlTreeBuilder
         3: dup
         4: invokespecial #89                 // Method coursier/util/shaded/org/jsoup/parser/HtmlTreeBuilder."<init>":()V
         7: astore        4
         9: new           #2                  // class coursier/util/shaded/org/jsoup/parser/Parser
        12: dup
        13: aload         4
        15: invokespecial #91                 // Method "<init>":(Lcoursier/util/shaded/org/jsoup/parser/TreeBuilder;)V
        18: astore        5
        20: aload         5
        22: aload_3
        23: putfield      #34                 // Field errors:Lcoursier/util/shaded/org/jsoup/parser/ParseErrorList;
        26: aload         4
        28: aload_0
        29: aload_1
        30: aload_2
        31: aload         5
        33: invokevirtual #92                 // Method coursier/util/shaded/org/jsoup/parser/HtmlTreeBuilder.parseFragment:(Ljava/lang/String;Lcoursier/util/shaded/org/jsoup/nodes/Element;Ljava/lang/String;Lcoursier/util/shaded/org/jsoup/parser/Parser;)Ljava/util/List;
        36: areturn
      LineNumberTable:
        line 137: 0
        line 138: 9
        line 139: 20
        line 140: 26
      LocalVariableTable:
        Start  Length  Slot  Name   Signature
            0      37     0 fragmentHtml   Ljava/lang/String;
            0      37     1 context   Lcoursier/util/shaded/org/jsoup/nodes/Element;
            0      37     2 baseUri   Ljava/lang/String;
            0      37     3 errorList   Lcoursier/util/shaded/org/jsoup/parser/ParseErrorList;
            9      28     4 treeBuilder   Lcoursier/util/shaded/org/jsoup/parser/HtmlTreeBuilder;
           20      17     5 parser   Lcoursier/util/shaded/org/jsoup/parser/Parser;
    Signature: #96                          // (Ljava/lang/String;Lcoursier/util/shaded/org/jsoup/nodes/Element;Ljava/lang/String;Lcoursier/util/shaded/org/jsoup/parser/ParseErrorList;)Ljava/util/List<Lcoursier/util/shaded/org/jsoup/nodes/Node;>;

  public static java.util.List<coursier.util.shaded.org.jsoup.nodes.Node> parseXmlFragment(java.lang.String, java.lang.String);
    descriptor: (Ljava/lang/String;Ljava/lang/String;)Ljava/util/List;
    flags: (0x0009) ACC_PUBLIC, ACC_STATIC
    Code:
      stack=6, locals=3, args_size=2
         0: new           #102                // class coursier/util/shaded/org/jsoup/parser/XmlTreeBuilder
         3: dup
         4: invokespecial #103                // Method coursier/util/shaded/org/jsoup/parser/XmlTreeBuilder."<init>":()V
         7: astore_2
         8: aload_2
         9: aload_0
        10: aload_1
        11: new           #2                  // class coursier/util/shaded/org/jsoup/parser/Parser
        14: dup
        15: aload_2
        16: invokespecial #91                 // Method "<init>":(Lcoursier/util/shaded/org/jsoup/parser/TreeBuilder;)V
        19: invokevirtual #106                // Method coursier/util/shaded/org/jsoup/parser/XmlTreeBuilder.parseFragment:(Ljava/lang/String;Ljava/lang/String;Lcoursier/util/shaded/org/jsoup/parser/Parser;)Ljava/util/List;
        22: areturn
      LineNumberTable:
        line 151: 0
        line 152: 8
      LocalVariableTable:
        Start  Length  Slot  Name   Signature
            0      23     0 fragmentXml   Ljava/lang/String;
            0      23     1 baseUri   Ljava/lang/String;
            8      15     2 treeBuilder   Lcoursier/util/shaded/org/jsoup/parser/XmlTreeBuilder;
    Signature: #100                         // (Ljava/lang/String;Ljava/lang/String;)Ljava/util/List<Lcoursier/util/shaded/org/jsoup/nodes/Node;>;

  public static coursier.util.shaded.org.jsoup.nodes.Document parseBodyFragment(java.lang.String, java.lang.String);
    descriptor: (Ljava/lang/String;Ljava/lang/String;)Lcoursier/util/shaded/org/jsoup/nodes/Document;
    flags: (0x0009) ACC_PUBLIC, ACC_STATIC
    Code:
      stack=3, locals=10, args_size=2
         0: aload_1
         1: invokestatic  #115                // Method coursier/util/shaded/org/jsoup/nodes/Document.createShell:(Ljava/lang/String;)Lcoursier/util/shaded/org/jsoup/nodes/Document;
         4: astore_2
         5: aload_2
         6: invokevirtual #119                // Method coursier/util/shaded/org/jsoup/nodes/Document.body:()Lcoursier/util/shaded/org/jsoup/nodes/Element;
         9: astore_3
        10: aload_0
        11: aload_3
        12: aload_1
        13: invokestatic  #121                // Method parseFragment:(Ljava/lang/String;Lcoursier/util/shaded/org/jsoup/nodes/Element;Ljava/lang/String;)Ljava/util/List;
        16: astore        4
        18: aload         4
        20: iconst_0
        21: anewarray     #123                // class coursier/util/shaded/org/jsoup/nodes/Node
        24: invokeinterface #129,  2          // InterfaceMethod java/util/List.toArray:([Ljava/lang/Object;)[Ljava/lang/Object;
        29: checkcast     #131                // class "[Lcoursier/util/shaded/org/jsoup/nodes/Node;"
        32: astore        5
        34: aload         5
        36: arraylength
        37: iconst_1
        38: isub
        39: istore        6
        41: iload         6
        43: ifle          60
        46: aload         5
        48: iload         6
        50: aaload
        51: invokevirtual #138                // Method coursier/util/shaded/org/jsoup/nodes/Node.remove:()V
        54: iinc          6, -1
        57: goto          41
        60: aload         5
        62: astore        6
        64: aload         6
        66: arraylength
        67: istore        7
        69: iconst_0
        70: istore        8
        72: iload         8
        74: iload         7
        76: if_icmpge     99
        79: aload         6
        81: iload         8
        83: aaload
        84: astore        9
        86: aload_3
        87: aload         9
        89: invokevirtual #142                // Method coursier/util/shaded/org/jsoup/nodes/Element.appendChild:(Lcoursier/util/shaded/org/jsoup/nodes/Node;)Lcoursier/util/shaded/org/jsoup/nodes/Element;
        92: pop
        93: iinc          8, 1
        96: goto          72
        99: aload_2
       100: areturn
      StackMapTable: number_of_entries = 4
        frame_type = 255 /* full_frame */
          offset_delta = 41
          locals = [ class java/lang/String, class java/lang/String, class coursier/util/shaded/org/jsoup/nodes/Document, class coursier/util/shaded/org/jsoup/nodes/Element, class java/util/List, class "[Lcoursier/util/shaded/org/jsoup/nodes/Node;", int ]
          stack = []
        frame_type = 250 /* chop */
          offset_delta = 18
        frame_type = 254 /* append */
          offset_delta = 11
          locals = [ class "[Lcoursier/util/shaded/org/jsoup/nodes/Node;", int, int ]
        frame_type = 248 /* chop */
          offset_delta = 26
      LineNumberTable:
        line 164: 0
        line 165: 5
        line 166: 10
        line 167: 18
        line 168: 34
        line 169: 46
        line 168: 54
        line 171: 60
        line 172: 86
        line 171: 93
        line 174: 99
      LocalVariableTable:
        Start  Length  Slot  Name   Signature
           41      19     6     i   I
           86       7     9  node   Lcoursier/util/shaded/org/jsoup/nodes/Node;
            0     101     0 bodyHtml   Ljava/lang/String;
            0     101     1 baseUri   Ljava/lang/String;
            5      96     2   doc   Lcoursier/util/shaded/org/jsoup/nodes/Document;
           10      91     3  body   Lcoursier/util/shaded/org/jsoup/nodes/Element;
           18      83     4 nodeList   Ljava/util/List;
           34      67     5 nodes   [Lcoursier/util/shaded/org/jsoup/nodes/Node;
      LocalVariableTypeTable:
        Start  Length  Slot  Name   Signature
           18      83     4 nodeList   Ljava/util/List<Lcoursier/util/shaded/org/jsoup/nodes/Node;>;

  public static java.lang.String unescapeEntities(java.lang.String, boolean);
    descriptor: (Ljava/lang/String;Z)Ljava/lang/String;
    flags: (0x0009) ACC_PUBLIC, ACC_STATIC
    Code:
      stack=5, locals=3, args_size=2
         0: new           #156                // class coursier/util/shaded/org/jsoup/parser/Tokeniser
         3: dup
         4: new           #158                // class coursier/util/shaded/org/jsoup/parser/CharacterReader
         7: dup
         8: aload_0
         9: invokespecial #159                // Method coursier/util/shaded/org/jsoup/parser/CharacterReader."<init>":(Ljava/lang/String;)V
        12: invokestatic  #32                 // Method coursier/util/shaded/org/jsoup/parser/ParseErrorList.noTracking:()Lcoursier/util/shaded/org/jsoup/parser/ParseErrorList;
        15: invokespecial #162                // Method coursier/util/shaded/org/jsoup/parser/Tokeniser."<init>":(Lcoursier/util/shaded/org/jsoup/parser/CharacterReader;Lcoursier/util/shaded/org/jsoup/parser/ParseErrorList;)V
        18: astore_2
        19: aload_2
        20: iload_1
        21: invokevirtual #165                // Method coursier/util/shaded/org/jsoup/parser/Tokeniser.unescapeEntities:(Z)Ljava/lang/String;
        24: areturn
      LineNumberTable:
        line 184: 0
        line 185: 19
      LocalVariableTable:
        Start  Length  Slot  Name   Signature
            0      25     0 string   Ljava/lang/String;
            0      25     1 inAttribute   Z
           19       6     2 tokeniser   Lcoursier/util/shaded/org/jsoup/parser/Tokeniser;

  public static coursier.util.shaded.org.jsoup.parser.Parser htmlParser();
    descriptor: ()Lcoursier/util/shaded/org/jsoup/parser/Parser;
    flags: (0x0009) ACC_PUBLIC, ACC_STATIC
    Code:
      stack=4, locals=0, args_size=0
         0: new           #2                  // class coursier/util/shaded/org/jsoup/parser/Parser
         3: dup
         4: new           #88                 // class coursier/util/shaded/org/jsoup/parser/HtmlTreeBuilder
         7: dup
         8: invokespecial #89                 // Method coursier/util/shaded/org/jsoup/parser/HtmlTreeBuilder."<init>":()V
        11: invokespecial #91                 // Method "<init>":(Lcoursier/util/shaded/org/jsoup/parser/TreeBuilder;)V
        14: areturn
      LineNumberTable:
        line 196: 0

  public static coursier.util.shaded.org.jsoup.parser.Parser xmlParser();
    descriptor: ()Lcoursier/util/shaded/org/jsoup/parser/Parser;
    flags: (0x0009) ACC_PUBLIC, ACC_STATIC
    Code:
      stack=4, locals=0, args_size=0
         0: new           #2                  // class coursier/util/shaded/org/jsoup/parser/Parser
         3: dup
         4: new           #102                // class coursier/util/shaded/org/jsoup/parser/XmlTreeBuilder
         7: dup
         8: invokespecial #103                // Method coursier/util/shaded/org/jsoup/parser/XmlTreeBuilder."<init>":()V
        11: invokespecial #91                 // Method "<init>":(Lcoursier/util/shaded/org/jsoup/parser/TreeBuilder;)V
        14: areturn
      LineNumberTable:
        line 205: 0
}
SourceFile: "Parser.java"
