Classfile /Users/mw/Projects/slang-braindump/.jar/jar11/assemble/slang-braindump/assemble/content/coursier/util/shaded/org/jsoup/parser/ParseSettings.class
  Last modified May 29, 2022; size 1613 bytes
  SHA-256 checksum 8efde9b7baf90f500ab09e0a34718a6cfd71799ccdb14e8eac67f2af84b9ddcf
  Compiled from "ParseSettings.java"
public class coursier.util.shaded.org.jsoup.parser.ParseSettings
  minor version: 0
  major version: 51
  flags: (0x0021) ACC_PUBLIC, ACC_SUPER
  this_class: #2                          // coursier/util/shaded/org/jsoup/parser/ParseSettings
  super_class: #4                         // java/lang/Object
  interfaces: 0, fields: 4, methods: 7, attributes: 1
Constant pool:
   #1 = Utf8               coursier/util/shaded/org/jsoup/parser/ParseSettings
   #2 = Class              #1             // coursier/util/shaded/org/jsoup/parser/ParseSettings
   #3 = Utf8               java/lang/Object
   #4 = Class              #3             // java/lang/Object
   #5 = Utf8               ParseSettings.java
   #6 = Utf8               htmlDefault
   #7 = Utf8               Lcoursier/util/shaded/org/jsoup/parser/ParseSettings;
   #8 = Utf8               preserveCase
   #9 = Utf8               preserveTagCase
  #10 = Utf8               Z
  #11 = Utf8               preserveAttributeCase
  #12 = Utf8               ()Z
  #13 = NameAndType        #9:#10         // preserveTagCase:Z
  #14 = Fieldref           #2.#13         // coursier/util/shaded/org/jsoup/parser/ParseSettings.preserveTagCase:Z
  #15 = Utf8               this
  #16 = NameAndType        #11:#10        // preserveAttributeCase:Z
  #17 = Fieldref           #2.#16         // coursier/util/shaded/org/jsoup/parser/ParseSettings.preserveAttributeCase:Z
  #18 = Utf8               <init>
  #19 = Utf8               (ZZ)V
  #20 = Utf8               ()V
  #21 = NameAndType        #18:#20        // "<init>":()V
  #22 = Methodref          #4.#21         // java/lang/Object."<init>":()V
  #23 = Utf8               tag
  #24 = Utf8               attribute
  #25 = Utf8               normalizeTag
  #26 = Utf8               (Ljava/lang/String;)Ljava/lang/String;
  #27 = Utf8               java/lang/String
  #28 = Class              #27            // java/lang/String
  #29 = Utf8               trim
  #30 = Utf8               ()Ljava/lang/String;
  #31 = NameAndType        #29:#30        // trim:()Ljava/lang/String;
  #32 = Methodref          #28.#31        // java/lang/String.trim:()Ljava/lang/String;
  #33 = Utf8               coursier/util/shaded/org/jsoup/internal/Normalizer
  #34 = Class              #33            // coursier/util/shaded/org/jsoup/internal/Normalizer
  #35 = Utf8               lowerCase
  #36 = NameAndType        #35:#26        // lowerCase:(Ljava/lang/String;)Ljava/lang/String;
  #37 = Methodref          #34.#36        // coursier/util/shaded/org/jsoup/internal/Normalizer.lowerCase:(Ljava/lang/String;)Ljava/lang/String;
  #38 = Utf8               name
  #39 = Utf8               Ljava/lang/String;
  #40 = Utf8               normalizeAttribute
  #41 = Utf8               normalizeAttributes
  #42 = Utf8               (Lcoursier/util/shaded/org/jsoup/nodes/Attributes;)Lcoursier/util/shaded/org/jsoup/nodes/Attributes;
  #43 = Utf8               coursier/util/shaded/org/jsoup/nodes/Attributes
  #44 = Class              #43            // coursier/util/shaded/org/jsoup/nodes/Attributes
  #45 = Utf8               normalize
  #46 = NameAndType        #45:#20        // normalize:()V
  #47 = Methodref          #44.#46        // coursier/util/shaded/org/jsoup/nodes/Attributes.normalize:()V
  #48 = Utf8               attributes
  #49 = Utf8               Lcoursier/util/shaded/org/jsoup/nodes/Attributes;
  #50 = Utf8               <clinit>
  #51 = NameAndType        #18:#19        // "<init>":(ZZ)V
  #52 = Methodref          #2.#51         // coursier/util/shaded/org/jsoup/parser/ParseSettings."<init>":(ZZ)V
  #53 = NameAndType        #6:#7          // htmlDefault:Lcoursier/util/shaded/org/jsoup/parser/ParseSettings;
  #54 = Fieldref           #2.#53         // coursier/util/shaded/org/jsoup/parser/ParseSettings.htmlDefault:Lcoursier/util/shaded/org/jsoup/parser/ParseSettings;
  #55 = NameAndType        #8:#7          // preserveCase:Lcoursier/util/shaded/org/jsoup/parser/ParseSettings;
  #56 = Fieldref           #2.#55         // coursier/util/shaded/org/jsoup/parser/ParseSettings.preserveCase:Lcoursier/util/shaded/org/jsoup/parser/ParseSettings;
  #57 = Utf8               Code
  #58 = Utf8               LineNumberTable
  #59 = Utf8               LocalVariableTable
  #60 = Utf8               StackMapTable
  #61 = Utf8               SourceFile
{
  public static final coursier.util.shaded.org.jsoup.parser.ParseSettings htmlDefault;
    descriptor: Lcoursier/util/shaded/org/jsoup/parser/ParseSettings;
    flags: (0x0019) ACC_PUBLIC, ACC_STATIC, ACC_FINAL

  public static final coursier.util.shaded.org.jsoup.parser.ParseSettings preserveCase;
    descriptor: Lcoursier/util/shaded/org/jsoup/parser/ParseSettings;
    flags: (0x0019) ACC_PUBLIC, ACC_STATIC, ACC_FINAL

  private final boolean preserveTagCase;
    descriptor: Z
    flags: (0x0012) ACC_PRIVATE, ACC_FINAL

  private final boolean preserveAttributeCase;
    descriptor: Z
    flags: (0x0012) ACC_PRIVATE, ACC_FINAL

  public boolean preserveTagCase();
    descriptor: ()Z
    flags: (0x0001) ACC_PUBLIC
    Code:
      stack=1, locals=1, args_size=1
         0: aload_0
         1: getfield      #14                 // Field preserveTagCase:Z
         4: ireturn
      LineNumberTable:
        line 32: 0
      LocalVariableTable:
        Start  Length  Slot  Name   Signature
            0       5     0  this   Lcoursier/util/shaded/org/jsoup/parser/ParseSettings;

  public boolean preserveAttributeCase();
    descriptor: ()Z
    flags: (0x0001) ACC_PUBLIC
    Code:
      stack=1, locals=1, args_size=1
         0: aload_0
         1: getfield      #17                 // Field preserveAttributeCase:Z
         4: ireturn
      LineNumberTable:
        line 39: 0
      LocalVariableTable:
        Start  Length  Slot  Name   Signature
            0       5     0  this   Lcoursier/util/shaded/org/jsoup/parser/ParseSettings;

  public coursier.util.shaded.org.jsoup.parser.ParseSettings(boolean, boolean);
    descriptor: (ZZ)V
    flags: (0x0001) ACC_PUBLIC
    Code:
      stack=2, locals=3, args_size=3
         0: aload_0
         1: invokespecial #22                 // Method java/lang/Object."<init>":()V
         4: aload_0
         5: iload_1
         6: putfield      #14                 // Field preserveTagCase:Z
         9: aload_0
        10: iload_2
        11: putfield      #17                 // Field preserveAttributeCase:Z
        14: return
      LineNumberTable:
        line 47: 0
        line 48: 4
        line 49: 9
        line 50: 14
      LocalVariableTable:
        Start  Length  Slot  Name   Signature
            0      15     0  this   Lcoursier/util/shaded/org/jsoup/parser/ParseSettings;
            0      15     1   tag   Z
            0      15     2 attribute   Z

  public java.lang.String normalizeTag(java.lang.String);
    descriptor: (Ljava/lang/String;)Ljava/lang/String;
    flags: (0x0001) ACC_PUBLIC
    Code:
      stack=1, locals=2, args_size=2
         0: aload_1
         1: invokevirtual #32                 // Method java/lang/String.trim:()Ljava/lang/String;
         4: astore_1
         5: aload_0
         6: getfield      #14                 // Field preserveTagCase:Z
         9: ifne          17
        12: aload_1
        13: invokestatic  #37                 // Method coursier/util/shaded/org/jsoup/internal/Normalizer.lowerCase:(Ljava/lang/String;)Ljava/lang/String;
        16: astore_1
        17: aload_1
        18: areturn
      StackMapTable: number_of_entries = 1
        frame_type = 17 /* same */
      LineNumberTable:
        line 56: 0
        line 57: 5
        line 58: 12
        line 59: 17
      LocalVariableTable:
        Start  Length  Slot  Name   Signature
            0      19     0  this   Lcoursier/util/shaded/org/jsoup/parser/ParseSettings;
            0      19     1  name   Ljava/lang/String;

  public java.lang.String normalizeAttribute(java.lang.String);
    descriptor: (Ljava/lang/String;)Ljava/lang/String;
    flags: (0x0001) ACC_PUBLIC
    Code:
      stack=1, locals=2, args_size=2
         0: aload_1
         1: invokevirtual #32                 // Method java/lang/String.trim:()Ljava/lang/String;
         4: astore_1
         5: aload_0
         6: getfield      #17                 // Field preserveAttributeCase:Z
         9: ifne          17
        12: aload_1
        13: invokestatic  #37                 // Method coursier/util/shaded/org/jsoup/internal/Normalizer.lowerCase:(Ljava/lang/String;)Ljava/lang/String;
        16: astore_1
        17: aload_1
        18: areturn
      StackMapTable: number_of_entries = 1
        frame_type = 17 /* same */
      LineNumberTable:
        line 66: 0
        line 67: 5
        line 68: 12
        line 69: 17
      LocalVariableTable:
        Start  Length  Slot  Name   Signature
            0      19     0  this   Lcoursier/util/shaded/org/jsoup/parser/ParseSettings;
            0      19     1  name   Ljava/lang/String;

  coursier.util.shaded.org.jsoup.nodes.Attributes normalizeAttributes(coursier.util.shaded.org.jsoup.nodes.Attributes);
    descriptor: (Lcoursier/util/shaded/org/jsoup/nodes/Attributes;)Lcoursier/util/shaded/org/jsoup/nodes/Attributes;
    flags: (0x0000)
    Code:
      stack=1, locals=2, args_size=2
         0: aload_1
         1: ifnull        15
         4: aload_0
         5: getfield      #17                 // Field preserveAttributeCase:Z
         8: ifne          15
        11: aload_1
        12: invokevirtual #47                 // Method coursier/util/shaded/org/jsoup/nodes/Attributes.normalize:()V
        15: aload_1
        16: areturn
      StackMapTable: number_of_entries = 1
        frame_type = 15 /* same */
      LineNumberTable:
        line 73: 0
        line 74: 11
        line 76: 15
      LocalVariableTable:
        Start  Length  Slot  Name   Signature
            0      17     0  this   Lcoursier/util/shaded/org/jsoup/parser/ParseSettings;
            0      17     1 attributes   Lcoursier/util/shaded/org/jsoup/nodes/Attributes;

  static {};
    descriptor: ()V
    flags: (0x0008) ACC_STATIC
    Code:
      stack=4, locals=0, args_size=0
         0: new           #2                  // class coursier/util/shaded/org/jsoup/parser/ParseSettings
         3: dup
         4: iconst_0
         5: iconst_0
         6: invokespecial #52                 // Method "<init>":(ZZ)V
         9: putstatic     #54                 // Field htmlDefault:Lcoursier/util/shaded/org/jsoup/parser/ParseSettings;
        12: new           #2                  // class coursier/util/shaded/org/jsoup/parser/ParseSettings
        15: dup
        16: iconst_1
        17: iconst_1
        18: invokespecial #52                 // Method "<init>":(ZZ)V
        21: putstatic     #56                 // Field preserveCase:Lcoursier/util/shaded/org/jsoup/parser/ParseSettings;
        24: return
      LineNumberTable:
        line 21: 0
        line 22: 12
        line 23: 24
}
SourceFile: "ParseSettings.java"
