Classfile /Users/mw/Projects/slang-braindump/.jar/jar11/assemble/slang-braindump/assemble/content/coursier/util/shaded/org/jsoup/parser/Tag.class
  Last modified May 29, 2022; size 8195 bytes
  SHA-256 checksum e77dd2c3fa2e5f6fa21f2b4447e59ddcdd312697e67544e78cfe218e46521834
  Compiled from "Tag.java"
public class coursier.util.shaded.org.jsoup.parser.Tag implements java.lang.Cloneable
  minor version: 0
  major version: 51
  flags: (0x0021) ACC_PUBLIC, ACC_SUPER
  this_class: #2                          // coursier/util/shaded/org/jsoup/parser/Tag
  super_class: #4                         // java/lang/Object
  interfaces: 1, fields: 17, methods: 23, attributes: 1
Constant pool:
    #1 = Utf8               coursier/util/shaded/org/jsoup/parser/Tag
    #2 = Class              #1            // coursier/util/shaded/org/jsoup/parser/Tag
    #3 = Utf8               java/lang/Object
    #4 = Class              #3            // java/lang/Object
    #5 = Utf8               java/lang/Cloneable
    #6 = Class              #5            // java/lang/Cloneable
    #7 = Utf8               Tag.java
    #8 = Utf8               tags
    #9 = Utf8               Ljava/util/Map;
   #10 = Utf8               Ljava/util/Map<Ljava/lang/String;Lcoursier/util/shaded/org/jsoup/parser/Tag;>;
   #11 = Utf8               tagName
   #12 = Utf8               Ljava/lang/String;
   #13 = Utf8               normalName
   #14 = Utf8               isBlock
   #15 = Utf8               Z
   #16 = Utf8               formatAsBlock
   #17 = Utf8               empty
   #18 = Utf8               selfClosing
   #19 = Utf8               preserveWhitespace
   #20 = Utf8               formList
   #21 = Utf8               formSubmit
   #22 = Utf8               blockTags
   #23 = Utf8               [Ljava/lang/String;
   #24 = Utf8               inlineTags
   #25 = Utf8               emptyTags
   #26 = Utf8               formatAsInlineTags
   #27 = Utf8               preserveWhitespaceTags
   #28 = Utf8               formListedTags
   #29 = Utf8               formSubmitTags
   #30 = Utf8               <init>
   #31 = Utf8               (Ljava/lang/String;)V
   #32 = Utf8               ()V
   #33 = NameAndType        #30:#32       // "<init>":()V
   #34 = Methodref          #4.#33        // java/lang/Object."<init>":()V
   #35 = NameAndType        #14:#15       // isBlock:Z
   #36 = Fieldref           #2.#35        // coursier/util/shaded/org/jsoup/parser/Tag.isBlock:Z
   #37 = NameAndType        #16:#15       // formatAsBlock:Z
   #38 = Fieldref           #2.#37        // coursier/util/shaded/org/jsoup/parser/Tag.formatAsBlock:Z
   #39 = NameAndType        #17:#15       // empty:Z
   #40 = Fieldref           #2.#39        // coursier/util/shaded/org/jsoup/parser/Tag.empty:Z
   #41 = NameAndType        #18:#15       // selfClosing:Z
   #42 = Fieldref           #2.#41        // coursier/util/shaded/org/jsoup/parser/Tag.selfClosing:Z
   #43 = NameAndType        #19:#15       // preserveWhitespace:Z
   #44 = Fieldref           #2.#43        // coursier/util/shaded/org/jsoup/parser/Tag.preserveWhitespace:Z
   #45 = NameAndType        #20:#15       // formList:Z
   #46 = Fieldref           #2.#45        // coursier/util/shaded/org/jsoup/parser/Tag.formList:Z
   #47 = NameAndType        #21:#15       // formSubmit:Z
   #48 = Fieldref           #2.#47        // coursier/util/shaded/org/jsoup/parser/Tag.formSubmit:Z
   #49 = NameAndType        #11:#12       // tagName:Ljava/lang/String;
   #50 = Fieldref           #2.#49        // coursier/util/shaded/org/jsoup/parser/Tag.tagName:Ljava/lang/String;
   #51 = Utf8               coursier/util/shaded/org/jsoup/internal/Normalizer
   #52 = Class              #51           // coursier/util/shaded/org/jsoup/internal/Normalizer
   #53 = Utf8               lowerCase
   #54 = Utf8               (Ljava/lang/String;)Ljava/lang/String;
   #55 = NameAndType        #53:#54       // lowerCase:(Ljava/lang/String;)Ljava/lang/String;
   #56 = Methodref          #52.#55       // coursier/util/shaded/org/jsoup/internal/Normalizer.lowerCase:(Ljava/lang/String;)Ljava/lang/String;
   #57 = NameAndType        #13:#12       // normalName:Ljava/lang/String;
   #58 = Fieldref           #2.#57        // coursier/util/shaded/org/jsoup/parser/Tag.normalName:Ljava/lang/String;
   #59 = Utf8               this
   #60 = Utf8               Lcoursier/util/shaded/org/jsoup/parser/Tag;
   #61 = Utf8               getName
   #62 = Utf8               ()Ljava/lang/String;
   #63 = Utf8               valueOf
   #64 = Utf8               (Ljava/lang/String;Lcoursier/util/shaded/org/jsoup/parser/ParseSettings;)Lcoursier/util/shaded/org/jsoup/parser/Tag;
   #65 = Utf8               coursier/util/shaded/org/jsoup/helper/Validate
   #66 = Class              #65           // coursier/util/shaded/org/jsoup/helper/Validate
   #67 = Utf8               notNull
   #68 = Utf8               (Ljava/lang/Object;)V
   #69 = NameAndType        #67:#68       // notNull:(Ljava/lang/Object;)V
   #70 = Methodref          #66.#69       // coursier/util/shaded/org/jsoup/helper/Validate.notNull:(Ljava/lang/Object;)V
   #71 = NameAndType        #8:#9         // tags:Ljava/util/Map;
   #72 = Fieldref           #2.#71        // coursier/util/shaded/org/jsoup/parser/Tag.tags:Ljava/util/Map;
   #73 = Utf8               java/util/Map
   #74 = Class              #73           // java/util/Map
   #75 = Utf8               get
   #76 = Utf8               (Ljava/lang/Object;)Ljava/lang/Object;
   #77 = NameAndType        #75:#76       // get:(Ljava/lang/Object;)Ljava/lang/Object;
   #78 = InterfaceMethodref #74.#77       // java/util/Map.get:(Ljava/lang/Object;)Ljava/lang/Object;
   #79 = Utf8               coursier/util/shaded/org/jsoup/parser/ParseSettings
   #80 = Class              #79           // coursier/util/shaded/org/jsoup/parser/ParseSettings
   #81 = Utf8               normalizeTag
   #82 = NameAndType        #81:#54       // normalizeTag:(Ljava/lang/String;)Ljava/lang/String;
   #83 = Methodref          #80.#82       // coursier/util/shaded/org/jsoup/parser/ParseSettings.normalizeTag:(Ljava/lang/String;)Ljava/lang/String;
   #84 = Utf8               notEmpty
   #85 = NameAndType        #84:#31       // notEmpty:(Ljava/lang/String;)V
   #86 = Methodref          #66.#85       // coursier/util/shaded/org/jsoup/helper/Validate.notEmpty:(Ljava/lang/String;)V
   #87 = NameAndType        #30:#31       // "<init>":(Ljava/lang/String;)V
   #88 = Methodref          #2.#87        // coursier/util/shaded/org/jsoup/parser/Tag."<init>":(Ljava/lang/String;)V
   #89 = Utf8               java/lang/String
   #90 = Class              #89           // java/lang/String
   #91 = Utf8               preserveTagCase
   #92 = Utf8               ()Z
   #93 = NameAndType        #91:#92       // preserveTagCase:()Z
   #94 = Methodref          #80.#93       // coursier/util/shaded/org/jsoup/parser/ParseSettings.preserveTagCase:()Z
   #95 = Utf8               equals
   #96 = Utf8               (Ljava/lang/Object;)Z
   #97 = NameAndType        #95:#96       // equals:(Ljava/lang/Object;)Z
   #98 = Methodref          #90.#97       // java/lang/String.equals:(Ljava/lang/Object;)Z
   #99 = Utf8               clone
  #100 = Utf8               ()Lcoursier/util/shaded/org/jsoup/parser/Tag;
  #101 = NameAndType        #99:#100      // clone:()Lcoursier/util/shaded/org/jsoup/parser/Tag;
  #102 = Methodref          #2.#101       // coursier/util/shaded/org/jsoup/parser/Tag.clone:()Lcoursier/util/shaded/org/jsoup/parser/Tag;
  #103 = Utf8               settings
  #104 = Utf8               Lcoursier/util/shaded/org/jsoup/parser/ParseSettings;
  #105 = Utf8               tag
  #106 = Utf8               (Ljava/lang/String;)Lcoursier/util/shaded/org/jsoup/parser/Tag;
  #107 = Utf8               preserveCase
  #108 = NameAndType        #107:#104     // preserveCase:Lcoursier/util/shaded/org/jsoup/parser/ParseSettings;
  #109 = Fieldref           #80.#108      // coursier/util/shaded/org/jsoup/parser/ParseSettings.preserveCase:Lcoursier/util/shaded/org/jsoup/parser/ParseSettings;
  #110 = NameAndType        #63:#64       // valueOf:(Ljava/lang/String;Lcoursier/util/shaded/org/jsoup/parser/ParseSettings;)Lcoursier/util/shaded/org/jsoup/parser/Tag;
  #111 = Methodref          #2.#110       // coursier/util/shaded/org/jsoup/parser/Tag.valueOf:(Ljava/lang/String;Lcoursier/util/shaded/org/jsoup/parser/ParseSettings;)Lcoursier/util/shaded/org/jsoup/parser/Tag;
  #112 = Utf8               isInline
  #113 = Utf8               isEmpty
  #114 = Utf8               isSelfClosing
  #115 = Utf8               isKnownTag
  #116 = Utf8               containsKey
  #117 = NameAndType        #116:#96      // containsKey:(Ljava/lang/Object;)Z
  #118 = InterfaceMethodref #74.#117      // java/util/Map.containsKey:(Ljava/lang/Object;)Z
  #119 = Utf8               (Ljava/lang/String;)Z
  #120 = Utf8               isFormListed
  #121 = Utf8               isFormSubmittable
  #122 = Utf8               setSelfClosing
  #123 = Utf8               o
  #124 = Utf8               Ljava/lang/Object;
  #125 = Utf8               hashCode
  #126 = Utf8               ()I
  #127 = NameAndType        #125:#126     // hashCode:()I
  #128 = Methodref          #90.#127      // java/lang/String.hashCode:()I
  #129 = Utf8               result
  #130 = Utf8               I
  #131 = Utf8               toString
  #132 = Utf8               java/lang/CloneNotSupportedException
  #133 = Class              #132          // java/lang/CloneNotSupportedException
  #134 = Utf8               ()Ljava/lang/Object;
  #135 = NameAndType        #99:#134      // clone:()Ljava/lang/Object;
  #136 = Methodref          #4.#135       // java/lang/Object.clone:()Ljava/lang/Object;
  #137 = Utf8               java/lang/RuntimeException
  #138 = Class              #137          // java/lang/RuntimeException
  #139 = Utf8               (Ljava/lang/Throwable;)V
  #140 = NameAndType        #30:#139      // "<init>":(Ljava/lang/Throwable;)V
  #141 = Methodref          #138.#140     // java/lang/RuntimeException."<init>":(Ljava/lang/Throwable;)V
  #142 = Utf8               e
  #143 = Utf8               Ljava/lang/CloneNotSupportedException;
  #144 = Utf8               register
  #145 = Utf8               (Lcoursier/util/shaded/org/jsoup/parser/Tag;)V
  #146 = Utf8               put
  #147 = Utf8               (Ljava/lang/Object;Ljava/lang/Object;)Ljava/lang/Object;
  #148 = NameAndType        #146:#147     // put:(Ljava/lang/Object;Ljava/lang/Object;)Ljava/lang/Object;
  #149 = InterfaceMethodref #74.#148      // java/util/Map.put:(Ljava/lang/Object;Ljava/lang/Object;)Ljava/lang/Object;
  #150 = Utf8               <clinit>
  #151 = Utf8               java/util/HashMap
  #152 = Class              #151          // java/util/HashMap
  #153 = Methodref          #152.#33      // java/util/HashMap."<init>":()V
  #154 = Utf8               html
  #155 = String             #154          // html
  #156 = Utf8               head
  #157 = String             #156          // head
  #158 = Utf8               body
  #159 = String             #158          // body
  #160 = Utf8               frameset
  #161 = String             #160          // frameset
  #162 = Utf8               script
  #163 = String             #162          // script
  #164 = Utf8               noscript
  #165 = String             #164          // noscript
  #166 = Utf8               style
  #167 = String             #166          // style
  #168 = Utf8               meta
  #169 = String             #168          // meta
  #170 = Utf8               link
  #171 = String             #170          // link
  #172 = Utf8               title
  #173 = String             #172          // title
  #174 = Utf8               frame
  #175 = String             #174          // frame
  #176 = Utf8               noframes
  #177 = String             #176          // noframes
  #178 = Utf8               section
  #179 = String             #178          // section
  #180 = Utf8               nav
  #181 = String             #180          // nav
  #182 = Utf8               aside
  #183 = String             #182          // aside
  #184 = Utf8               hgroup
  #185 = String             #184          // hgroup
  #186 = Utf8               header
  #187 = String             #186          // header
  #188 = Utf8               footer
  #189 = String             #188          // footer
  #190 = Utf8               p
  #191 = String             #190          // p
  #192 = Utf8               h1
  #193 = String             #192          // h1
  #194 = Utf8               h2
  #195 = String             #194          // h2
  #196 = Utf8               h3
  #197 = String             #196          // h3
  #198 = Utf8               h4
  #199 = String             #198          // h4
  #200 = Utf8               h5
  #201 = String             #200          // h5
  #202 = Utf8               h6
  #203 = String             #202          // h6
  #204 = Utf8               ul
  #205 = String             #204          // ul
  #206 = Utf8               ol
  #207 = String             #206          // ol
  #208 = Utf8               pre
  #209 = String             #208          // pre
  #210 = Utf8               div
  #211 = String             #210          // div
  #212 = Utf8               blockquote
  #213 = String             #212          // blockquote
  #214 = Utf8               hr
  #215 = String             #214          // hr
  #216 = Utf8               address
  #217 = String             #216          // address
  #218 = Utf8               figure
  #219 = String             #218          // figure
  #220 = Utf8               figcaption
  #221 = String             #220          // figcaption
  #222 = Utf8               form
  #223 = String             #222          // form
  #224 = Utf8               fieldset
  #225 = String             #224          // fieldset
  #226 = Utf8               ins
  #227 = String             #226          // ins
  #228 = Utf8               del
  #229 = String             #228          // del
  #230 = Utf8               dl
  #231 = String             #230          // dl
  #232 = Utf8               dt
  #233 = String             #232          // dt
  #234 = Utf8               dd
  #235 = String             #234          // dd
  #236 = Utf8               li
  #237 = String             #236          // li
  #238 = Utf8               table
  #239 = String             #238          // table
  #240 = Utf8               caption
  #241 = String             #240          // caption
  #242 = Utf8               thead
  #243 = String             #242          // thead
  #244 = Utf8               tfoot
  #245 = String             #244          // tfoot
  #246 = Utf8               tbody
  #247 = String             #246          // tbody
  #248 = Utf8               colgroup
  #249 = String             #248          // colgroup
  #250 = Utf8               col
  #251 = String             #250          // col
  #252 = Utf8               tr
  #253 = String             #252          // tr
  #254 = Utf8               th
  #255 = String             #254          // th
  #256 = Utf8               td
  #257 = String             #256          // td
  #258 = Utf8               video
  #259 = String             #258          // video
  #260 = Utf8               audio
  #261 = String             #260          // audio
  #262 = Utf8               canvas
  #263 = String             #262          // canvas
  #264 = Utf8               details
  #265 = String             #264          // details
  #266 = Utf8               menu
  #267 = String             #266          // menu
  #268 = Utf8               plaintext
  #269 = String             #268          // plaintext
  #270 = Utf8               template
  #271 = String             #270          // template
  #272 = Utf8               article
  #273 = String             #272          // article
  #274 = Utf8               main
  #275 = String             #274          // main
  #276 = Utf8               svg
  #277 = String             #276          // svg
  #278 = Utf8               math
  #279 = String             #278          // math
  #280 = Utf8               center
  #281 = String             #280          // center
  #282 = NameAndType        #22:#23       // blockTags:[Ljava/lang/String;
  #283 = Fieldref           #2.#282       // coursier/util/shaded/org/jsoup/parser/Tag.blockTags:[Ljava/lang/String;
  #284 = Utf8               object
  #285 = String             #284          // object
  #286 = Utf8               base
  #287 = String             #286          // base
  #288 = Utf8               font
  #289 = String             #288          // font
  #290 = Utf8               tt
  #291 = String             #290          // tt
  #292 = Utf8               i
  #293 = String             #292          // i
  #294 = Utf8               b
  #295 = String             #294          // b
  #296 = Utf8               u
  #297 = String             #296          // u
  #298 = Utf8               big
  #299 = String             #298          // big
  #300 = Utf8               small
  #301 = String             #300          // small
  #302 = Utf8               em
  #303 = String             #302          // em
  #304 = Utf8               strong
  #305 = String             #304          // strong
  #306 = Utf8               dfn
  #307 = String             #306          // dfn
  #308 = Utf8               code
  #309 = String             #308          // code
  #310 = Utf8               samp
  #311 = String             #310          // samp
  #312 = Utf8               kbd
  #313 = String             #312          // kbd
  #314 = Utf8               var
  #315 = String             #314          // var
  #316 = Utf8               cite
  #317 = String             #316          // cite
  #318 = Utf8               abbr
  #319 = String             #318          // abbr
  #320 = Utf8               time
  #321 = String             #320          // time
  #322 = Utf8               acronym
  #323 = String             #322          // acronym
  #324 = Utf8               mark
  #325 = String             #324          // mark
  #326 = Utf8               ruby
  #327 = String             #326          // ruby
  #328 = Utf8               rt
  #329 = String             #328          // rt
  #330 = Utf8               rp
  #331 = String             #330          // rp
  #332 = Utf8               a
  #333 = String             #332          // a
  #334 = Utf8               img
  #335 = String             #334          // img
  #336 = Utf8               br
  #337 = String             #336          // br
  #338 = Utf8               wbr
  #339 = String             #338          // wbr
  #340 = Utf8               map
  #341 = String             #340          // map
  #342 = Utf8               q
  #343 = String             #342          // q
  #344 = Utf8               sub
  #345 = String             #344          // sub
  #346 = Utf8               sup
  #347 = String             #346          // sup
  #348 = Utf8               bdo
  #349 = String             #348          // bdo
  #350 = Utf8               iframe
  #351 = String             #350          // iframe
  #352 = Utf8               embed
  #353 = String             #352          // embed
  #354 = Utf8               span
  #355 = String             #354          // span
  #356 = Utf8               input
  #357 = String             #356          // input
  #358 = Utf8               select
  #359 = String             #358          // select
  #360 = Utf8               textarea
  #361 = String             #360          // textarea
  #362 = Utf8               label
  #363 = String             #362          // label
  #364 = Utf8               button
  #365 = String             #364          // button
  #366 = Utf8               optgroup
  #367 = String             #366          // optgroup
  #368 = Utf8               option
  #369 = String             #368          // option
  #370 = Utf8               legend
  #371 = String             #370          // legend
  #372 = Utf8               datalist
  #373 = String             #372          // datalist
  #374 = Utf8               keygen
  #375 = String             #374          // keygen
  #376 = Utf8               output
  #377 = String             #376          // output
  #378 = Utf8               progress
  #379 = String             #378          // progress
  #380 = Utf8               meter
  #381 = String             #380          // meter
  #382 = Utf8               area
  #383 = String             #382          // area
  #384 = Utf8               param
  #385 = String             #384          // param
  #386 = Utf8               source
  #387 = String             #386          // source
  #388 = Utf8               track
  #389 = String             #388          // track
  #390 = Utf8               summary
  #391 = String             #390          // summary
  #392 = Utf8               command
  #393 = String             #392          // command
  #394 = Utf8               device
  #395 = String             #394          // device
  #396 = Utf8               basefont
  #397 = String             #396          // basefont
  #398 = Utf8               bgsound
  #399 = String             #398          // bgsound
  #400 = Utf8               menuitem
  #401 = String             #400          // menuitem
  #402 = Utf8               data
  #403 = String             #402          // data
  #404 = Utf8               bdi
  #405 = String             #404          // bdi
  #406 = Utf8               s
  #407 = String             #406          // s
  #408 = NameAndType        #24:#23       // inlineTags:[Ljava/lang/String;
  #409 = Fieldref           #2.#408       // coursier/util/shaded/org/jsoup/parser/Tag.inlineTags:[Ljava/lang/String;
  #410 = NameAndType        #25:#23       // emptyTags:[Ljava/lang/String;
  #411 = Fieldref           #2.#410       // coursier/util/shaded/org/jsoup/parser/Tag.emptyTags:[Ljava/lang/String;
  #412 = NameAndType        #26:#23       // formatAsInlineTags:[Ljava/lang/String;
  #413 = Fieldref           #2.#412       // coursier/util/shaded/org/jsoup/parser/Tag.formatAsInlineTags:[Ljava/lang/String;
  #414 = NameAndType        #27:#23       // preserveWhitespaceTags:[Ljava/lang/String;
  #415 = Fieldref           #2.#414       // coursier/util/shaded/org/jsoup/parser/Tag.preserveWhitespaceTags:[Ljava/lang/String;
  #416 = NameAndType        #28:#23       // formListedTags:[Ljava/lang/String;
  #417 = Fieldref           #2.#416       // coursier/util/shaded/org/jsoup/parser/Tag.formListedTags:[Ljava/lang/String;
  #418 = NameAndType        #29:#23       // formSubmitTags:[Ljava/lang/String;
  #419 = Fieldref           #2.#418       // coursier/util/shaded/org/jsoup/parser/Tag.formSubmitTags:[Ljava/lang/String;
  #420 = Class              #23           // "[Ljava/lang/String;"
  #421 = NameAndType        #144:#145     // register:(Lcoursier/util/shaded/org/jsoup/parser/Tag;)V
  #422 = Methodref          #2.#421       // coursier/util/shaded/org/jsoup/parser/Tag.register:(Lcoursier/util/shaded/org/jsoup/parser/Tag;)V
  #423 = Utf8               Signature
  #424 = Utf8               Code
  #425 = Utf8               LineNumberTable
  #426 = Utf8               LocalVariableTable
  #427 = Utf8               StackMapTable
  #428 = Utf8               Exceptions
  #429 = Utf8               SourceFile
{
  private static final java.util.Map<java.lang.String, coursier.util.shaded.org.jsoup.parser.Tag> tags;
    descriptor: Ljava/util/Map;
    flags: (0x001a) ACC_PRIVATE, ACC_STATIC, ACC_FINAL
    Signature: #10                          // Ljava/util/Map<Ljava/lang/String;Lcoursier/util/shaded/org/jsoup/parser/Tag;>;

  private java.lang.String tagName;
    descriptor: Ljava/lang/String;
    flags: (0x0002) ACC_PRIVATE

  private java.lang.String normalName;
    descriptor: Ljava/lang/String;
    flags: (0x0002) ACC_PRIVATE

  private boolean isBlock;
    descriptor: Z
    flags: (0x0002) ACC_PRIVATE

  private boolean formatAsBlock;
    descriptor: Z
    flags: (0x0002) ACC_PRIVATE

  private boolean empty;
    descriptor: Z
    flags: (0x0002) ACC_PRIVATE

  private boolean selfClosing;
    descriptor: Z
    flags: (0x0002) ACC_PRIVATE

  private boolean preserveWhitespace;
    descriptor: Z
    flags: (0x0002) ACC_PRIVATE

  private boolean formList;
    descriptor: Z
    flags: (0x0002) ACC_PRIVATE

  private boolean formSubmit;
    descriptor: Z
    flags: (0x0002) ACC_PRIVATE

  private static final java.lang.String[] blockTags;
    descriptor: [Ljava/lang/String;
    flags: (0x001a) ACC_PRIVATE, ACC_STATIC, ACC_FINAL

  private static final java.lang.String[] inlineTags;
    descriptor: [Ljava/lang/String;
    flags: (0x001a) ACC_PRIVATE, ACC_STATIC, ACC_FINAL

  private static final java.lang.String[] emptyTags;
    descriptor: [Ljava/lang/String;
    flags: (0x001a) ACC_PRIVATE, ACC_STATIC, ACC_FINAL

  private static final java.lang.String[] formatAsInlineTags;
    descriptor: [Ljava/lang/String;
    flags: (0x001a) ACC_PRIVATE, ACC_STATIC, ACC_FINAL

  private static final java.lang.String[] preserveWhitespaceTags;
    descriptor: [Ljava/lang/String;
    flags: (0x001a) ACC_PRIVATE, ACC_STATIC, ACC_FINAL

  private static final java.lang.String[] formListedTags;
    descriptor: [Ljava/lang/String;
    flags: (0x001a) ACC_PRIVATE, ACC_STATIC, ACC_FINAL

  private static final java.lang.String[] formSubmitTags;
    descriptor: [Ljava/lang/String;
    flags: (0x001a) ACC_PRIVATE, ACC_STATIC, ACC_FINAL

  private coursier.util.shaded.org.jsoup.parser.Tag(java.lang.String);
    descriptor: (Ljava/lang/String;)V
    flags: (0x0002) ACC_PRIVATE
    Code:
      stack=2, locals=2, args_size=2
         0: aload_0
         1: invokespecial #34                 // Method java/lang/Object."<init>":()V
         4: aload_0
         5: iconst_1
         6: putfield      #36                 // Field isBlock:Z
         9: aload_0
        10: iconst_1
        11: putfield      #38                 // Field formatAsBlock:Z
        14: aload_0
        15: iconst_0
        16: putfield      #40                 // Field empty:Z
        19: aload_0
        20: iconst_0
        21: putfield      #42                 // Field selfClosing:Z
        24: aload_0
        25: iconst_0
        26: putfield      #44                 // Field preserveWhitespace:Z
        29: aload_0
        30: iconst_0
        31: putfield      #46                 // Field formList:Z
        34: aload_0
        35: iconst_0
        36: putfield      #48                 // Field formSubmit:Z
        39: aload_0
        40: aload_1
        41: putfield      #50                 // Field tagName:Ljava/lang/String;
        44: aload_0
        45: aload_1
        46: invokestatic  #56                 // Method coursier/util/shaded/org/jsoup/internal/Normalizer.lowerCase:(Ljava/lang/String;)Ljava/lang/String;
        49: putfield      #58                 // Field normalName:Ljava/lang/String;
        52: return
      LineNumberTable:
        line 27: 0
        line 19: 4
        line 20: 9
        line 21: 14
        line 22: 19
        line 23: 24
        line 24: 29
        line 25: 34
        line 28: 39
        line 29: 44
        line 30: 52
      LocalVariableTable:
        Start  Length  Slot  Name   Signature
            0      53     0  this   Lcoursier/util/shaded/org/jsoup/parser/Tag;
            0      53     1 tagName   Ljava/lang/String;

  public java.lang.String getName();
    descriptor: ()Ljava/lang/String;
    flags: (0x0001) ACC_PUBLIC
    Code:
      stack=1, locals=1, args_size=1
         0: aload_0
         1: getfield      #50                 // Field tagName:Ljava/lang/String;
         4: areturn
      LineNumberTable:
        line 38: 0
      LocalVariableTable:
        Start  Length  Slot  Name   Signature
            0       5     0  this   Lcoursier/util/shaded/org/jsoup/parser/Tag;

  public java.lang.String normalName();
    descriptor: ()Ljava/lang/String;
    flags: (0x0001) ACC_PUBLIC
    Code:
      stack=1, locals=1, args_size=1
         0: aload_0
         1: getfield      #58                 // Field normalName:Ljava/lang/String;
         4: areturn
      LineNumberTable:
        line 46: 0
      LocalVariableTable:
        Start  Length  Slot  Name   Signature
            0       5     0  this   Lcoursier/util/shaded/org/jsoup/parser/Tag;

  public static coursier.util.shaded.org.jsoup.parser.Tag valueOf(java.lang.String, coursier.util.shaded.org.jsoup.parser.ParseSettings);
    descriptor: (Ljava/lang/String;Lcoursier/util/shaded/org/jsoup/parser/ParseSettings;)Lcoursier/util/shaded/org/jsoup/parser/Tag;
    flags: (0x0009) ACC_PUBLIC, ACC_STATIC
    Code:
      stack=3, locals=4, args_size=2
         0: aload_0
         1: invokestatic  #70                 // Method coursier/util/shaded/org/jsoup/helper/Validate.notNull:(Ljava/lang/Object;)V
         4: getstatic     #72                 // Field tags:Ljava/util/Map;
         7: aload_0
         8: invokeinterface #78,  2           // InterfaceMethod java/util/Map.get:(Ljava/lang/Object;)Ljava/lang/Object;
        13: checkcast     #2                  // class coursier/util/shaded/org/jsoup/parser/Tag
        16: astore_2
        17: aload_2
        18: ifnonnull     95
        21: aload_1
        22: aload_0
        23: invokevirtual #83                 // Method coursier/util/shaded/org/jsoup/parser/ParseSettings.normalizeTag:(Ljava/lang/String;)Ljava/lang/String;
        26: astore_0
        27: aload_0
        28: invokestatic  #86                 // Method coursier/util/shaded/org/jsoup/helper/Validate.notEmpty:(Ljava/lang/String;)V
        31: aload_0
        32: invokestatic  #56                 // Method coursier/util/shaded/org/jsoup/internal/Normalizer.lowerCase:(Ljava/lang/String;)Ljava/lang/String;
        35: astore_3
        36: getstatic     #72                 // Field tags:Ljava/util/Map;
        39: aload_3
        40: invokeinterface #78,  2           // InterfaceMethod java/util/Map.get:(Ljava/lang/Object;)Ljava/lang/Object;
        45: checkcast     #2                  // class coursier/util/shaded/org/jsoup/parser/Tag
        48: astore_2
        49: aload_2
        50: ifnonnull     70
        53: new           #2                  // class coursier/util/shaded/org/jsoup/parser/Tag
        56: dup
        57: aload_0
        58: invokespecial #88                 // Method "<init>":(Ljava/lang/String;)V
        61: astore_2
        62: aload_2
        63: iconst_0
        64: putfield      #36                 // Field isBlock:Z
        67: goto          95
        70: aload_1
        71: invokevirtual #94                 // Method coursier/util/shaded/org/jsoup/parser/ParseSettings.preserveTagCase:()Z
        74: ifeq          95
        77: aload_0
        78: aload_3
        79: invokevirtual #98                 // Method java/lang/String.equals:(Ljava/lang/Object;)Z
        82: ifne          95
        85: aload_2
        86: invokevirtual #102                // Method clone:()Lcoursier/util/shaded/org/jsoup/parser/Tag;
        89: astore_2
        90: aload_2
        91: aload_0
        92: putfield      #50                 // Field tagName:Ljava/lang/String;
        95: aload_2
        96: areturn
      StackMapTable: number_of_entries = 2
        frame_type = 253 /* append */
          offset_delta = 70
          locals = [ class coursier/util/shaded/org/jsoup/parser/Tag, class java/lang/String ]
        frame_type = 250 /* chop */
          offset_delta = 24
      LineNumberTable:
        line 60: 0
        line 61: 4
        line 63: 17
        line 64: 21
        line 65: 27
        line 66: 31
        line 67: 36
        line 69: 49
        line 71: 53
        line 72: 62
        line 73: 70
        line 74: 85
        line 75: 90
        line 78: 95
      LocalVariableTable:
        Start  Length  Slot  Name   Signature
           36      59     3 normalName   Ljava/lang/String;
            0      97     0 tagName   Ljava/lang/String;
            0      97     1 settings   Lcoursier/util/shaded/org/jsoup/parser/ParseSettings;
           17      80     2   tag   Lcoursier/util/shaded/org/jsoup/parser/Tag;

  public static coursier.util.shaded.org.jsoup.parser.Tag valueOf(java.lang.String);
    descriptor: (Ljava/lang/String;)Lcoursier/util/shaded/org/jsoup/parser/Tag;
    flags: (0x0009) ACC_PUBLIC, ACC_STATIC
    Code:
      stack=2, locals=1, args_size=1
         0: aload_0
         1: getstatic     #109                // Field coursier/util/shaded/org/jsoup/parser/ParseSettings.preserveCase:Lcoursier/util/shaded/org/jsoup/parser/ParseSettings;
         4: invokestatic  #111                // Method valueOf:(Ljava/lang/String;Lcoursier/util/shaded/org/jsoup/parser/ParseSettings;)Lcoursier/util/shaded/org/jsoup/parser/Tag;
         7: areturn
      LineNumberTable:
        line 91: 0
      LocalVariableTable:
        Start  Length  Slot  Name   Signature
            0       8     0 tagName   Ljava/lang/String;

  public boolean isBlock();
    descriptor: ()Z
    flags: (0x0001) ACC_PUBLIC
    Code:
      stack=1, locals=1, args_size=1
         0: aload_0
         1: getfield      #36                 // Field isBlock:Z
         4: ireturn
      LineNumberTable:
        line 100: 0
      LocalVariableTable:
        Start  Length  Slot  Name   Signature
            0       5     0  this   Lcoursier/util/shaded/org/jsoup/parser/Tag;

  public boolean formatAsBlock();
    descriptor: ()Z
    flags: (0x0001) ACC_PUBLIC
    Code:
      stack=1, locals=1, args_size=1
         0: aload_0
         1: getfield      #38                 // Field formatAsBlock:Z
         4: ireturn
      LineNumberTable:
        line 109: 0
      LocalVariableTable:
        Start  Length  Slot  Name   Signature
            0       5     0  this   Lcoursier/util/shaded/org/jsoup/parser/Tag;

  public boolean isInline();
    descriptor: ()Z
    flags: (0x0001) ACC_PUBLIC
    Code:
      stack=1, locals=1, args_size=1
         0: aload_0
         1: getfield      #36                 // Field isBlock:Z
         4: ifne          11
         7: iconst_1
         8: goto          12
        11: iconst_0
        12: ireturn
      StackMapTable: number_of_entries = 2
        frame_type = 11 /* same */
        frame_type = 64 /* same_locals_1_stack_item */
          stack = [ int ]
      LineNumberTable:
        line 118: 0
      LocalVariableTable:
        Start  Length  Slot  Name   Signature
            0      13     0  this   Lcoursier/util/shaded/org/jsoup/parser/Tag;

  public boolean isEmpty();
    descriptor: ()Z
    flags: (0x0001) ACC_PUBLIC
    Code:
      stack=1, locals=1, args_size=1
         0: aload_0
         1: getfield      #40                 // Field empty:Z
         4: ireturn
      LineNumberTable:
        line 127: 0
      LocalVariableTable:
        Start  Length  Slot  Name   Signature
            0       5     0  this   Lcoursier/util/shaded/org/jsoup/parser/Tag;

  public boolean isSelfClosing();
    descriptor: ()Z
    flags: (0x0001) ACC_PUBLIC
    Code:
      stack=1, locals=1, args_size=1
         0: aload_0
         1: getfield      #40                 // Field empty:Z
         4: ifne          14
         7: aload_0
         8: getfield      #42                 // Field selfClosing:Z
        11: ifeq          18
        14: iconst_1
        15: goto          19
        18: iconst_0
        19: ireturn
      StackMapTable: number_of_entries = 3
        frame_type = 14 /* same */
        frame_type = 3 /* same */
        frame_type = 64 /* same_locals_1_stack_item */
          stack = [ int ]
      LineNumberTable:
        line 136: 0
      LocalVariableTable:
        Start  Length  Slot  Name   Signature
            0      20     0  this   Lcoursier/util/shaded/org/jsoup/parser/Tag;

  public boolean isKnownTag();
    descriptor: ()Z
    flags: (0x0001) ACC_PUBLIC
    Code:
      stack=2, locals=1, args_size=1
         0: getstatic     #72                 // Field tags:Ljava/util/Map;
         3: aload_0
         4: getfield      #50                 // Field tagName:Ljava/lang/String;
         7: invokeinterface #118,  2          // InterfaceMethod java/util/Map.containsKey:(Ljava/lang/Object;)Z
        12: ireturn
      LineNumberTable:
        line 145: 0
      LocalVariableTable:
        Start  Length  Slot  Name   Signature
            0      13     0  this   Lcoursier/util/shaded/org/jsoup/parser/Tag;

  public static boolean isKnownTag(java.lang.String);
    descriptor: (Ljava/lang/String;)Z
    flags: (0x0009) ACC_PUBLIC, ACC_STATIC
    Code:
      stack=2, locals=1, args_size=1
         0: getstatic     #72                 // Field tags:Ljava/util/Map;
         3: aload_0
         4: invokeinterface #118,  2          // InterfaceMethod java/util/Map.containsKey:(Ljava/lang/Object;)Z
         9: ireturn
      LineNumberTable:
        line 155: 0
      LocalVariableTable:
        Start  Length  Slot  Name   Signature
            0      10     0 tagName   Ljava/lang/String;

  public boolean preserveWhitespace();
    descriptor: ()Z
    flags: (0x0001) ACC_PUBLIC
    Code:
      stack=1, locals=1, args_size=1
         0: aload_0
         1: getfield      #44                 // Field preserveWhitespace:Z
         4: ireturn
      LineNumberTable:
        line 164: 0
      LocalVariableTable:
        Start  Length  Slot  Name   Signature
            0       5     0  this   Lcoursier/util/shaded/org/jsoup/parser/Tag;

  public boolean isFormListed();
    descriptor: ()Z
    flags: (0x0001) ACC_PUBLIC
    Code:
      stack=1, locals=1, args_size=1
         0: aload_0
         1: getfield      #46                 // Field formList:Z
         4: ireturn
      LineNumberTable:
        line 172: 0
      LocalVariableTable:
        Start  Length  Slot  Name   Signature
            0       5     0  this   Lcoursier/util/shaded/org/jsoup/parser/Tag;

  public boolean isFormSubmittable();
    descriptor: ()Z
    flags: (0x0001) ACC_PUBLIC
    Code:
      stack=1, locals=1, args_size=1
         0: aload_0
         1: getfield      #48                 // Field formSubmit:Z
         4: ireturn
      LineNumberTable:
        line 180: 0
      LocalVariableTable:
        Start  Length  Slot  Name   Signature
            0       5     0  this   Lcoursier/util/shaded/org/jsoup/parser/Tag;

  coursier.util.shaded.org.jsoup.parser.Tag setSelfClosing();
    descriptor: ()Lcoursier/util/shaded/org/jsoup/parser/Tag;
    flags: (0x0000)
    Code:
      stack=2, locals=1, args_size=1
         0: aload_0
         1: iconst_1
         2: putfield      #42                 // Field selfClosing:Z
         5: aload_0
         6: areturn
      LineNumberTable:
        line 184: 0
        line 185: 5
      LocalVariableTable:
        Start  Length  Slot  Name   Signature
            0       7     0  this   Lcoursier/util/shaded/org/jsoup/parser/Tag;

  public boolean equals(java.lang.Object);
    descriptor: (Ljava/lang/Object;)Z
    flags: (0x0001) ACC_PUBLIC
    Code:
      stack=2, locals=3, args_size=2
         0: aload_0
         1: aload_1
         2: if_acmpne     7
         5: iconst_1
         6: ireturn
         7: aload_1
         8: instanceof    #2                  // class coursier/util/shaded/org/jsoup/parser/Tag
        11: ifne          16
        14: iconst_0
        15: ireturn
        16: aload_1
        17: checkcast     #2                  // class coursier/util/shaded/org/jsoup/parser/Tag
        20: astore_2
        21: aload_0
        22: getfield      #50                 // Field tagName:Ljava/lang/String;
        25: aload_2
        26: getfield      #50                 // Field tagName:Ljava/lang/String;
        29: invokevirtual #98                 // Method java/lang/String.equals:(Ljava/lang/Object;)Z
        32: ifne          37
        35: iconst_0
        36: ireturn
        37: aload_0
        38: getfield      #40                 // Field empty:Z
        41: aload_2
        42: getfield      #40                 // Field empty:Z
        45: if_icmpeq     50
        48: iconst_0
        49: ireturn
        50: aload_0
        51: getfield      #38                 // Field formatAsBlock:Z
        54: aload_2
        55: getfield      #38                 // Field formatAsBlock:Z
        58: if_icmpeq     63
        61: iconst_0
        62: ireturn
        63: aload_0
        64: getfield      #36                 // Field isBlock:Z
        67: aload_2
        68: getfield      #36                 // Field isBlock:Z
        71: if_icmpeq     76
        74: iconst_0
        75: ireturn
        76: aload_0
        77: getfield      #44                 // Field preserveWhitespace:Z
        80: aload_2
        81: getfield      #44                 // Field preserveWhitespace:Z
        84: if_icmpeq     89
        87: iconst_0
        88: ireturn
        89: aload_0
        90: getfield      #42                 // Field selfClosing:Z
        93: aload_2
        94: getfield      #42                 // Field selfClosing:Z
        97: if_icmpeq     102
       100: iconst_0
       101: ireturn
       102: aload_0
       103: getfield      #46                 // Field formList:Z
       106: aload_2
       107: getfield      #46                 // Field formList:Z
       110: if_icmpeq     115
       113: iconst_0
       114: ireturn
       115: aload_0
       116: getfield      #48                 // Field formSubmit:Z
       119: aload_2
       120: getfield      #48                 // Field formSubmit:Z
       123: if_icmpne     130
       126: iconst_1
       127: goto          131
       130: iconst_0
       131: ireturn
      StackMapTable: number_of_entries = 11
        frame_type = 7 /* same */
        frame_type = 8 /* same */
        frame_type = 252 /* append */
          offset_delta = 20
          locals = [ class coursier/util/shaded/org/jsoup/parser/Tag ]
        frame_type = 12 /* same */
        frame_type = 12 /* same */
        frame_type = 12 /* same */
        frame_type = 12 /* same */
        frame_type = 12 /* same */
        frame_type = 12 /* same */
        frame_type = 14 /* same */
        frame_type = 64 /* same_locals_1_stack_item */
          stack = [ int ]
      LineNumberTable:
        line 190: 0
        line 191: 7
        line 193: 16
        line 195: 21
        line 196: 37
        line 197: 50
        line 198: 63
        line 199: 76
        line 200: 89
        line 201: 102
        line 202: 115
      LocalVariableTable:
        Start  Length  Slot  Name   Signature
            0     132     0  this   Lcoursier/util/shaded/org/jsoup/parser/Tag;
            0     132     1     o   Ljava/lang/Object;
           21     111     2   tag   Lcoursier/util/shaded/org/jsoup/parser/Tag;

  public int hashCode();
    descriptor: ()I
    flags: (0x0001) ACC_PUBLIC
    Code:
      stack=2, locals=2, args_size=1
         0: aload_0
         1: getfield      #50                 // Field tagName:Ljava/lang/String;
         4: invokevirtual #128                // Method java/lang/String.hashCode:()I
         7: istore_1
         8: bipush        31
        10: iload_1
        11: imul
        12: aload_0
        13: getfield      #36                 // Field isBlock:Z
        16: ifeq          23
        19: iconst_1
        20: goto          24
        23: iconst_0
        24: iadd
        25: istore_1
        26: bipush        31
        28: iload_1
        29: imul
        30: aload_0
        31: getfield      #38                 // Field formatAsBlock:Z
        34: ifeq          41
        37: iconst_1
        38: goto          42
        41: iconst_0
        42: iadd
        43: istore_1
        44: bipush        31
        46: iload_1
        47: imul
        48: aload_0
        49: getfield      #40                 // Field empty:Z
        52: ifeq          59
        55: iconst_1
        56: goto          60
        59: iconst_0
        60: iadd
        61: istore_1
        62: bipush        31
        64: iload_1
        65: imul
        66: aload_0
        67: getfield      #42                 // Field selfClosing:Z
        70: ifeq          77
        73: iconst_1
        74: goto          78
        77: iconst_0
        78: iadd
        79: istore_1
        80: bipush        31
        82: iload_1
        83: imul
        84: aload_0
        85: getfield      #44                 // Field preserveWhitespace:Z
        88: ifeq          95
        91: iconst_1
        92: goto          96
        95: iconst_0
        96: iadd
        97: istore_1
        98: bipush        31
       100: iload_1
       101: imul
       102: aload_0
       103: getfield      #46                 // Field formList:Z
       106: ifeq          113
       109: iconst_1
       110: goto          114
       113: iconst_0
       114: iadd
       115: istore_1
       116: bipush        31
       118: iload_1
       119: imul
       120: aload_0
       121: getfield      #48                 // Field formSubmit:Z
       124: ifeq          131
       127: iconst_1
       128: goto          132
       131: iconst_0
       132: iadd
       133: istore_1
       134: iload_1
       135: ireturn
      StackMapTable: number_of_entries = 14
        frame_type = 255 /* full_frame */
          offset_delta = 23
          locals = [ class coursier/util/shaded/org/jsoup/parser/Tag, int ]
          stack = [ int ]
        frame_type = 255 /* full_frame */
          offset_delta = 0
          locals = [ class coursier/util/shaded/org/jsoup/parser/Tag, int ]
          stack = [ int, int ]
        frame_type = 80 /* same_locals_1_stack_item */
          stack = [ int ]
        frame_type = 255 /* full_frame */
          offset_delta = 0
          locals = [ class coursier/util/shaded/org/jsoup/parser/Tag, int ]
          stack = [ int, int ]
        frame_type = 80 /* same_locals_1_stack_item */
          stack = [ int ]
        frame_type = 255 /* full_frame */
          offset_delta = 0
          locals = [ class coursier/util/shaded/org/jsoup/parser/Tag, int ]
          stack = [ int, int ]
        frame_type = 80 /* same_locals_1_stack_item */
          stack = [ int ]
        frame_type = 255 /* full_frame */
          offset_delta = 0
          locals = [ class coursier/util/shaded/org/jsoup/parser/Tag, int ]
          stack = [ int, int ]
        frame_type = 80 /* same_locals_1_stack_item */
          stack = [ int ]
        frame_type = 255 /* full_frame */
          offset_delta = 0
          locals = [ class coursier/util/shaded/org/jsoup/parser/Tag, int ]
          stack = [ int, int ]
        frame_type = 80 /* same_locals_1_stack_item */
          stack = [ int ]
        frame_type = 255 /* full_frame */
          offset_delta = 0
          locals = [ class coursier/util/shaded/org/jsoup/parser/Tag, int ]
          stack = [ int, int ]
        frame_type = 80 /* same_locals_1_stack_item */
          stack = [ int ]
        frame_type = 255 /* full_frame */
          offset_delta = 0
          locals = [ class coursier/util/shaded/org/jsoup/parser/Tag, int ]
          stack = [ int, int ]
      LineNumberTable:
        line 207: 0
        line 208: 8
        line 209: 26
        line 210: 44
        line 211: 62
        line 212: 80
        line 213: 98
        line 214: 116
        line 215: 134
      LocalVariableTable:
        Start  Length  Slot  Name   Signature
            0     136     0  this   Lcoursier/util/shaded/org/jsoup/parser/Tag;
            8     128     1 result   I

  public java.lang.String toString();
    descriptor: ()Ljava/lang/String;
    flags: (0x0001) ACC_PUBLIC
    Code:
      stack=1, locals=1, args_size=1
         0: aload_0
         1: getfield      #50                 // Field tagName:Ljava/lang/String;
         4: areturn
      LineNumberTable:
        line 220: 0
      LocalVariableTable:
        Start  Length  Slot  Name   Signature
            0       5     0  this   Lcoursier/util/shaded/org/jsoup/parser/Tag;

  protected coursier.util.shaded.org.jsoup.parser.Tag clone();
    descriptor: ()Lcoursier/util/shaded/org/jsoup/parser/Tag;
    flags: (0x0004) ACC_PROTECTED
    Code:
      stack=3, locals=2, args_size=1
         0: aload_0
         1: invokespecial #136                // Method java/lang/Object.clone:()Ljava/lang/Object;
         4: checkcast     #2                  // class coursier/util/shaded/org/jsoup/parser/Tag
         7: areturn
         8: astore_1
         9: new           #138                // class java/lang/RuntimeException
        12: dup
        13: aload_1
        14: invokespecial #141                // Method java/lang/RuntimeException."<init>":(Ljava/lang/Throwable;)V
        17: athrow
      Exception table:
         from    to  target type
             0     7     8   Class java/lang/CloneNotSupportedException
      StackMapTable: number_of_entries = 1
        frame_type = 72 /* same_locals_1_stack_item */
          stack = [ class java/lang/CloneNotSupportedException ]
      LineNumberTable:
        line 226: 0
        line 227: 8
        line 228: 9
      LocalVariableTable:
        Start  Length  Slot  Name   Signature
            9       9     1     e   Ljava/lang/CloneNotSupportedException;
            0      18     0  this   Lcoursier/util/shaded/org/jsoup/parser/Tag;

  private static void register(coursier.util.shaded.org.jsoup.parser.Tag);
    descriptor: (Lcoursier/util/shaded/org/jsoup/parser/Tag;)V
    flags: (0x000a) ACC_PRIVATE, ACC_STATIC
    Code:
      stack=3, locals=1, args_size=1
         0: getstatic     #72                 // Field tags:Ljava/util/Map;
         3: aload_0
         4: getfield      #50                 // Field tagName:Ljava/lang/String;
         7: aload_0
         8: invokeinterface #149,  3          // InterfaceMethod java/util/Map.put:(Ljava/lang/Object;Ljava/lang/Object;)Ljava/lang/Object;
        13: pop
        14: return
      LineNumberTable:
        line 317: 0
        line 318: 14
      LocalVariableTable:
        Start  Length  Slot  Name   Signature
            0      15     0   tag   Lcoursier/util/shaded/org/jsoup/parser/Tag;

  protected java.lang.Object clone() throws java.lang.CloneNotSupportedException;
    descriptor: ()Ljava/lang/Object;
    flags: (0x1044) ACC_PROTECTED, ACC_BRIDGE, ACC_SYNTHETIC
    Code:
      stack=1, locals=1, args_size=1
         0: aload_0
         1: invokevirtual #102                // Method clone:()Lcoursier/util/shaded/org/jsoup/parser/Tag;
         4: areturn
      LineNumberTable:
        line 14: 0
      LocalVariableTable:
        Start  Length  Slot  Name   Signature
            0       5     0  this   Lcoursier/util/shaded/org/jsoup/parser/Tag;
    Exceptions:
      throws java.lang.CloneNotSupportedException

  static {};
    descriptor: ()V
    flags: (0x0008) ACC_STATIC
    Code:
      stack=4, locals=5, args_size=0
         0: new           #152                // class java/util/HashMap
         3: dup
         4: invokespecial #153                // Method java/util/HashMap."<init>":()V
         7: putstatic     #72                 // Field tags:Ljava/util/Map;
        10: bipush        64
        12: anewarray     #90                 // class java/lang/String
        15: dup
        16: iconst_0
        17: ldc           #155                // String html
        19: aastore
        20: dup
        21: iconst_1
        22: ldc           #157                // String head
        24: aastore
        25: dup
        26: iconst_2
        27: ldc           #159                // String body
        29: aastore
        30: dup
        31: iconst_3
        32: ldc           #161                // String frameset
        34: aastore
        35: dup
        36: iconst_4
        37: ldc           #163                // String script
        39: aastore
        40: dup
        41: iconst_5
        42: ldc           #165                // String noscript
        44: aastore
        45: dup
        46: bipush        6
        48: ldc           #167                // String style
        50: aastore
        51: dup
        52: bipush        7
        54: ldc           #169                // String meta
        56: aastore
        57: dup
        58: bipush        8
        60: ldc           #171                // String link
        62: aastore
        63: dup
        64: bipush        9
        66: ldc           #173                // String title
        68: aastore
        69: dup
        70: bipush        10
        72: ldc           #175                // String frame
        74: aastore
        75: dup
        76: bipush        11
        78: ldc           #177                // String noframes
        80: aastore
        81: dup
        82: bipush        12
        84: ldc           #179                // String section
        86: aastore
        87: dup
        88: bipush        13
        90: ldc           #181                // String nav
        92: aastore
        93: dup
        94: bipush        14
        96: ldc           #183                // String aside
        98: aastore
        99: dup
       100: bipush        15
       102: ldc           #185                // String hgroup
       104: aastore
       105: dup
       106: bipush        16
       108: ldc           #187                // String header
       110: aastore
       111: dup
       112: bipush        17
       114: ldc           #189                // String footer
       116: aastore
       117: dup
       118: bipush        18
       120: ldc           #191                // String p
       122: aastore
       123: dup
       124: bipush        19
       126: ldc           #193                // String h1
       128: aastore
       129: dup
       130: bipush        20
       132: ldc           #195                // String h2
       134: aastore
       135: dup
       136: bipush        21
       138: ldc           #197                // String h3
       140: aastore
       141: dup
       142: bipush        22
       144: ldc           #199                // String h4
       146: aastore
       147: dup
       148: bipush        23
       150: ldc           #201                // String h5
       152: aastore
       153: dup
       154: bipush        24
       156: ldc           #203                // String h6
       158: aastore
       159: dup
       160: bipush        25
       162: ldc           #205                // String ul
       164: aastore
       165: dup
       166: bipush        26
       168: ldc           #207                // String ol
       170: aastore
       171: dup
       172: bipush        27
       174: ldc           #209                // String pre
       176: aastore
       177: dup
       178: bipush        28
       180: ldc           #211                // String div
       182: aastore
       183: dup
       184: bipush        29
       186: ldc           #213                // String blockquote
       188: aastore
       189: dup
       190: bipush        30
       192: ldc           #215                // String hr
       194: aastore
       195: dup
       196: bipush        31
       198: ldc           #217                // String address
       200: aastore
       201: dup
       202: bipush        32
       204: ldc           #219                // String figure
       206: aastore
       207: dup
       208: bipush        33
       210: ldc           #221                // String figcaption
       212: aastore
       213: dup
       214: bipush        34
       216: ldc           #223                // String form
       218: aastore
       219: dup
       220: bipush        35
       222: ldc           #225                // String fieldset
       224: aastore
       225: dup
       226: bipush        36
       228: ldc           #227                // String ins
       230: aastore
       231: dup
       232: bipush        37
       234: ldc           #229                // String del
       236: aastore
       237: dup
       238: bipush        38
       240: ldc           #231                // String dl
       242: aastore
       243: dup
       244: bipush        39
       246: ldc           #233                // String dt
       248: aastore
       249: dup
       250: bipush        40
       252: ldc           #235                // String dd
       254: aastore
       255: dup
       256: bipush        41
       258: ldc           #237                // String li
       260: aastore
       261: dup
       262: bipush        42
       264: ldc           #239                // String table
       266: aastore
       267: dup
       268: bipush        43
       270: ldc           #241                // String caption
       272: aastore
       273: dup
       274: bipush        44
       276: ldc           #243                // String thead
       278: aastore
       279: dup
       280: bipush        45
       282: ldc           #245                // String tfoot
       284: aastore
       285: dup
       286: bipush        46
       288: ldc           #247                // String tbody
       290: aastore
       291: dup
       292: bipush        47
       294: ldc           #249                // String colgroup
       296: aastore
       297: dup
       298: bipush        48
       300: ldc           #251                // String col
       302: aastore
       303: dup
       304: bipush        49
       306: ldc           #253                // String tr
       308: aastore
       309: dup
       310: bipush        50
       312: ldc           #255                // String th
       314: aastore
       315: dup
       316: bipush        51
       318: ldc_w         #257                // String td
       321: aastore
       322: dup
       323: bipush        52
       325: ldc_w         #259                // String video
       328: aastore
       329: dup
       330: bipush        53
       332: ldc_w         #261                // String audio
       335: aastore
       336: dup
       337: bipush        54
       339: ldc_w         #263                // String canvas
       342: aastore
       343: dup
       344: bipush        55
       346: ldc_w         #265                // String details
       349: aastore
       350: dup
       351: bipush        56
       353: ldc_w         #267                // String menu
       356: aastore
       357: dup
       358: bipush        57
       360: ldc_w         #269                // String plaintext
       363: aastore
       364: dup
       365: bipush        58
       367: ldc_w         #271                // String template
       370: aastore
       371: dup
       372: bipush        59
       374: ldc_w         #273                // String article
       377: aastore
       378: dup
       379: bipush        60
       381: ldc_w         #275                // String main
       384: aastore
       385: dup
       386: bipush        61
       388: ldc_w         #277                // String svg
       391: aastore
       392: dup
       393: bipush        62
       395: ldc_w         #279                // String math
       398: aastore
       399: dup
       400: bipush        63
       402: ldc_w         #281                // String center
       405: aastore
       406: putstatic     #283                // Field blockTags:[Ljava/lang/String;
       409: bipush        66
       411: anewarray     #90                 // class java/lang/String
       414: dup
       415: iconst_0
       416: ldc_w         #285                // String object
       419: aastore
       420: dup
       421: iconst_1
       422: ldc_w         #287                // String base
       425: aastore
       426: dup
       427: iconst_2
       428: ldc_w         #289                // String font
       431: aastore
       432: dup
       433: iconst_3
       434: ldc_w         #291                // String tt
       437: aastore
       438: dup
       439: iconst_4
       440: ldc_w         #293                // String i
       443: aastore
       444: dup
       445: iconst_5
       446: ldc_w         #295                // String b
       449: aastore
       450: dup
       451: bipush        6
       453: ldc_w         #297                // String u
       456: aastore
       457: dup
       458: bipush        7
       460: ldc_w         #299                // String big
       463: aastore
       464: dup
       465: bipush        8
       467: ldc_w         #301                // String small
       470: aastore
       471: dup
       472: bipush        9
       474: ldc_w         #303                // String em
       477: aastore
       478: dup
       479: bipush        10
       481: ldc_w         #305                // String strong
       484: aastore
       485: dup
       486: bipush        11
       488: ldc_w         #307                // String dfn
       491: aastore
       492: dup
       493: bipush        12
       495: ldc_w         #309                // String code
       498: aastore
       499: dup
       500: bipush        13
       502: ldc_w         #311                // String samp
       505: aastore
       506: dup
       507: bipush        14
       509: ldc_w         #313                // String kbd
       512: aastore
       513: dup
       514: bipush        15
       516: ldc_w         #315                // String var
       519: aastore
       520: dup
       521: bipush        16
       523: ldc_w         #317                // String cite
       526: aastore
       527: dup
       528: bipush        17
       530: ldc_w         #319                // String abbr
       533: aastore
       534: dup
       535: bipush        18
       537: ldc_w         #321                // String time
       540: aastore
       541: dup
       542: bipush        19
       544: ldc_w         #323                // String acronym
       547: aastore
       548: dup
       549: bipush        20
       551: ldc_w         #325                // String mark
       554: aastore
       555: dup
       556: bipush        21
       558: ldc_w         #327                // String ruby
       561: aastore
       562: dup
       563: bipush        22
       565: ldc_w         #329                // String rt
       568: aastore
       569: dup
       570: bipush        23
       572: ldc_w         #331                // String rp
       575: aastore
       576: dup
       577: bipush        24
       579: ldc_w         #333                // String a
       582: aastore
       583: dup
       584: bipush        25
       586: ldc_w         #335                // String img
       589: aastore
       590: dup
       591: bipush        26
       593: ldc_w         #337                // String br
       596: aastore
       597: dup
       598: bipush        27
       600: ldc_w         #339                // String wbr
       603: aastore
       604: dup
       605: bipush        28
       607: ldc_w         #341                // String map
       610: aastore
       611: dup
       612: bipush        29
       614: ldc_w         #343                // String q
       617: aastore
       618: dup
       619: bipush        30
       621: ldc_w         #345                // String sub
       624: aastore
       625: dup
       626: bipush        31
       628: ldc_w         #347                // String sup
       631: aastore
       632: dup
       633: bipush        32
       635: ldc_w         #349                // String bdo
       638: aastore
       639: dup
       640: bipush        33
       642: ldc_w         #351                // String iframe
       645: aastore
       646: dup
       647: bipush        34
       649: ldc_w         #353                // String embed
       652: aastore
       653: dup
       654: bipush        35
       656: ldc_w         #355                // String span
       659: aastore
       660: dup
       661: bipush        36
       663: ldc_w         #357                // String input
       666: aastore
       667: dup
       668: bipush        37
       670: ldc_w         #359                // String select
       673: aastore
       674: dup
       675: bipush        38
       677: ldc_w         #361                // String textarea
       680: aastore
       681: dup
       682: bipush        39
       684: ldc_w         #363                // String label
       687: aastore
       688: dup
       689: bipush        40
       691: ldc_w         #365                // String button
       694: aastore
       695: dup
       696: bipush        41
       698: ldc_w         #367                // String optgroup
       701: aastore
       702: dup
       703: bipush        42
       705: ldc_w         #369                // String option
       708: aastore
       709: dup
       710: bipush        43
       712: ldc_w         #371                // String legend
       715: aastore
       716: dup
       717: bipush        44
       719: ldc_w         #373                // String datalist
       722: aastore
       723: dup
       724: bipush        45
       726: ldc_w         #375                // String keygen
       729: aastore
       730: dup
       731: bipush        46
       733: ldc_w         #377                // String output
       736: aastore
       737: dup
       738: bipush        47
       740: ldc_w         #379                // String progress
       743: aastore
       744: dup
       745: bipush        48
       747: ldc_w         #381                // String meter
       750: aastore
       751: dup
       752: bipush        49
       754: ldc_w         #383                // String area
       757: aastore
       758: dup
       759: bipush        50
       761: ldc_w         #385                // String param
       764: aastore
       765: dup
       766: bipush        51
       768: ldc_w         #387                // String source
       771: aastore
       772: dup
       773: bipush        52
       775: ldc_w         #389                // String track
       778: aastore
       779: dup
       780: bipush        53
       782: ldc_w         #391                // String summary
       785: aastore
       786: dup
       787: bipush        54
       789: ldc_w         #393                // String command
       792: aastore
       793: dup
       794: bipush        55
       796: ldc_w         #395                // String device
       799: aastore
       800: dup
       801: bipush        56
       803: ldc_w         #383                // String area
       806: aastore
       807: dup
       808: bipush        57
       810: ldc_w         #397                // String basefont
       813: aastore
       814: dup
       815: bipush        58
       817: ldc_w         #399                // String bgsound
       820: aastore
       821: dup
       822: bipush        59
       824: ldc_w         #401                // String menuitem
       827: aastore
       828: dup
       829: bipush        60
       831: ldc_w         #385                // String param
       834: aastore
       835: dup
       836: bipush        61
       838: ldc_w         #387                // String source
       841: aastore
       842: dup
       843: bipush        62
       845: ldc_w         #389                // String track
       848: aastore
       849: dup
       850: bipush        63
       852: ldc_w         #403                // String data
       855: aastore
       856: dup
       857: bipush        64
       859: ldc_w         #405                // String bdi
       862: aastore
       863: dup
       864: bipush        65
       866: ldc_w         #407                // String s
       869: aastore
       870: putstatic     #409                // Field inlineTags:[Ljava/lang/String;
       873: bipush        21
       875: anewarray     #90                 // class java/lang/String
       878: dup
       879: iconst_0
       880: ldc           #169                // String meta
       882: aastore
       883: dup
       884: iconst_1
       885: ldc           #171                // String link
       887: aastore
       888: dup
       889: iconst_2
       890: ldc_w         #287                // String base
       893: aastore
       894: dup
       895: iconst_3
       896: ldc           #175                // String frame
       898: aastore
       899: dup
       900: iconst_4
       901: ldc_w         #335                // String img
       904: aastore
       905: dup
       906: iconst_5
       907: ldc_w         #337                // String br
       910: aastore
       911: dup
       912: bipush        6
       914: ldc_w         #339                // String wbr
       917: aastore
       918: dup
       919: bipush        7
       921: ldc_w         #353                // String embed
       924: aastore
       925: dup
       926: bipush        8
       928: ldc           #215                // String hr
       930: aastore
       931: dup
       932: bipush        9
       934: ldc_w         #357                // String input
       937: aastore
       938: dup
       939: bipush        10
       941: ldc_w         #375                // String keygen
       944: aastore
       945: dup
       946: bipush        11
       948: ldc           #251                // String col
       950: aastore
       951: dup
       952: bipush        12
       954: ldc_w         #393                // String command
       957: aastore
       958: dup
       959: bipush        13
       961: ldc_w         #395                // String device
       964: aastore
       965: dup
       966: bipush        14
       968: ldc_w         #383                // String area
       971: aastore
       972: dup
       973: bipush        15
       975: ldc_w         #397                // String basefont
       978: aastore
       979: dup
       980: bipush        16
       982: ldc_w         #399                // String bgsound
       985: aastore
       986: dup
       987: bipush        17
       989: ldc_w         #401                // String menuitem
       992: aastore
       993: dup
       994: bipush        18
       996: ldc_w         #385                // String param
       999: aastore
      1000: dup
      1001: bipush        19
      1003: ldc_w         #387                // String source
      1006: aastore
      1007: dup
      1008: bipush        20
      1010: ldc_w         #389                // String track
      1013: aastore
      1014: putstatic     #411                // Field emptyTags:[Ljava/lang/String;
      1017: bipush        19
      1019: anewarray     #90                 // class java/lang/String
      1022: dup
      1023: iconst_0
      1024: ldc           #173                // String title
      1026: aastore
      1027: dup
      1028: iconst_1
      1029: ldc_w         #333                // String a
      1032: aastore
      1033: dup
      1034: iconst_2
      1035: ldc           #191                // String p
      1037: aastore
      1038: dup
      1039: iconst_3
      1040: ldc           #193                // String h1
      1042: aastore
      1043: dup
      1044: iconst_4
      1045: ldc           #195                // String h2
      1047: aastore
      1048: dup
      1049: iconst_5
      1050: ldc           #197                // String h3
      1052: aastore
      1053: dup
      1054: bipush        6
      1056: ldc           #199                // String h4
      1058: aastore
      1059: dup
      1060: bipush        7
      1062: ldc           #201                // String h5
      1064: aastore
      1065: dup
      1066: bipush        8
      1068: ldc           #203                // String h6
      1070: aastore
      1071: dup
      1072: bipush        9
      1074: ldc           #209                // String pre
      1076: aastore
      1077: dup
      1078: bipush        10
      1080: ldc           #217                // String address
      1082: aastore
      1083: dup
      1084: bipush        11
      1086: ldc           #237                // String li
      1088: aastore
      1089: dup
      1090: bipush        12
      1092: ldc           #255                // String th
      1094: aastore
      1095: dup
      1096: bipush        13
      1098: ldc_w         #257                // String td
      1101: aastore
      1102: dup
      1103: bipush        14
      1105: ldc           #163                // String script
      1107: aastore
      1108: dup
      1109: bipush        15
      1111: ldc           #167                // String style
      1113: aastore
      1114: dup
      1115: bipush        16
      1117: ldc           #227                // String ins
      1119: aastore
      1120: dup
      1121: bipush        17
      1123: ldc           #229                // String del
      1125: aastore
      1126: dup
      1127: bipush        18
      1129: ldc_w         #407                // String s
      1132: aastore
      1133: putstatic     #413                // Field formatAsInlineTags:[Ljava/lang/String;
      1136: iconst_4
      1137: anewarray     #90                 // class java/lang/String
      1140: dup
      1141: iconst_0
      1142: ldc           #209                // String pre
      1144: aastore
      1145: dup
      1146: iconst_1
      1147: ldc_w         #269                // String plaintext
      1150: aastore
      1151: dup
      1152: iconst_2
      1153: ldc           #173                // String title
      1155: aastore
      1156: dup
      1157: iconst_3
      1158: ldc_w         #361                // String textarea
      1161: aastore
      1162: putstatic     #415                // Field preserveWhitespaceTags:[Ljava/lang/String;
      1165: bipush        8
      1167: anewarray     #90                 // class java/lang/String
      1170: dup
      1171: iconst_0
      1172: ldc_w         #365                // String button
      1175: aastore
      1176: dup
      1177: iconst_1
      1178: ldc           #225                // String fieldset
      1180: aastore
      1181: dup
      1182: iconst_2
      1183: ldc_w         #357                // String input
      1186: aastore
      1187: dup
      1188: iconst_3
      1189: ldc_w         #375                // String keygen
      1192: aastore
      1193: dup
      1194: iconst_4
      1195: ldc_w         #285                // String object
      1198: aastore
      1199: dup
      1200: iconst_5
      1201: ldc_w         #377                // String output
      1204: aastore
      1205: dup
      1206: bipush        6
      1208: ldc_w         #359                // String select
      1211: aastore
      1212: dup
      1213: bipush        7
      1215: ldc_w         #361                // String textarea
      1218: aastore
      1219: putstatic     #417                // Field formListedTags:[Ljava/lang/String;
      1222: iconst_5
      1223: anewarray     #90                 // class java/lang/String
      1226: dup
      1227: iconst_0
      1228: ldc_w         #357                // String input
      1231: aastore
      1232: dup
      1233: iconst_1
      1234: ldc_w         #375                // String keygen
      1237: aastore
      1238: dup
      1239: iconst_2
      1240: ldc_w         #285                // String object
      1243: aastore
      1244: dup
      1245: iconst_3
      1246: ldc_w         #359                // String select
      1249: aastore
      1250: dup
      1251: iconst_4
      1252: ldc_w         #361                // String textarea
      1255: aastore
      1256: putstatic     #419                // Field formSubmitTags:[Ljava/lang/String;
      1259: getstatic     #283                // Field blockTags:[Ljava/lang/String;
      1262: astore_0
      1263: aload_0
      1264: arraylength
      1265: istore_1
      1266: iconst_0
      1267: istore_2
      1268: iload_2
      1269: iload_1
      1270: if_icmpge     1298
      1273: aload_0
      1274: iload_2
      1275: aaload
      1276: astore_3
      1277: new           #2                  // class coursier/util/shaded/org/jsoup/parser/Tag
      1280: dup
      1281: aload_3
      1282: invokespecial #88                 // Method "<init>":(Ljava/lang/String;)V
      1285: astore        4
      1287: aload         4
      1289: invokestatic  #422                // Method register:(Lcoursier/util/shaded/org/jsoup/parser/Tag;)V
      1292: iinc          2, 1
      1295: goto          1268
      1298: getstatic     #409                // Field inlineTags:[Ljava/lang/String;
      1301: astore_0
      1302: aload_0
      1303: arraylength
      1304: istore_1
      1305: iconst_0
      1306: istore_2
      1307: iload_2
      1308: iload_1
      1309: if_icmpge     1349
      1312: aload_0
      1313: iload_2
      1314: aaload
      1315: astore_3
      1316: new           #2                  // class coursier/util/shaded/org/jsoup/parser/Tag
      1319: dup
      1320: aload_3
      1321: invokespecial #88                 // Method "<init>":(Ljava/lang/String;)V
      1324: astore        4
      1326: aload         4
      1328: iconst_0
      1329: putfield      #36                 // Field isBlock:Z
      1332: aload         4
      1334: iconst_0
      1335: putfield      #38                 // Field formatAsBlock:Z
      1338: aload         4
      1340: invokestatic  #422                // Method register:(Lcoursier/util/shaded/org/jsoup/parser/Tag;)V
      1343: iinc          2, 1
      1346: goto          1307
      1349: getstatic     #411                // Field emptyTags:[Ljava/lang/String;
      1352: astore_0
      1353: aload_0
      1354: arraylength
      1355: istore_1
      1356: iconst_0
      1357: istore_2
      1358: iload_2
      1359: iload_1
      1360: if_icmpge     1398
      1363: aload_0
      1364: iload_2
      1365: aaload
      1366: astore_3
      1367: getstatic     #72                 // Field tags:Ljava/util/Map;
      1370: aload_3
      1371: invokeinterface #78,  2           // InterfaceMethod java/util/Map.get:(Ljava/lang/Object;)Ljava/lang/Object;
      1376: checkcast     #2                  // class coursier/util/shaded/org/jsoup/parser/Tag
      1379: astore        4
      1381: aload         4
      1383: invokestatic  #70                 // Method coursier/util/shaded/org/jsoup/helper/Validate.notNull:(Ljava/lang/Object;)V
      1386: aload         4
      1388: iconst_1
      1389: putfield      #40                 // Field empty:Z
      1392: iinc          2, 1
      1395: goto          1358
      1398: getstatic     #413                // Field formatAsInlineTags:[Ljava/lang/String;
      1401: astore_0
      1402: aload_0
      1403: arraylength
      1404: istore_1
      1405: iconst_0
      1406: istore_2
      1407: iload_2
      1408: iload_1
      1409: if_icmpge     1447
      1412: aload_0
      1413: iload_2
      1414: aaload
      1415: astore_3
      1416: getstatic     #72                 // Field tags:Ljava/util/Map;
      1419: aload_3
      1420: invokeinterface #78,  2           // InterfaceMethod java/util/Map.get:(Ljava/lang/Object;)Ljava/lang/Object;
      1425: checkcast     #2                  // class coursier/util/shaded/org/jsoup/parser/Tag
      1428: astore        4
      1430: aload         4
      1432: invokestatic  #70                 // Method coursier/util/shaded/org/jsoup/helper/Validate.notNull:(Ljava/lang/Object;)V
      1435: aload         4
      1437: iconst_0
      1438: putfield      #38                 // Field formatAsBlock:Z
      1441: iinc          2, 1
      1444: goto          1407
      1447: getstatic     #415                // Field preserveWhitespaceTags:[Ljava/lang/String;
      1450: astore_0
      1451: aload_0
      1452: arraylength
      1453: istore_1
      1454: iconst_0
      1455: istore_2
      1456: iload_2
      1457: iload_1
      1458: if_icmpge     1496
      1461: aload_0
      1462: iload_2
      1463: aaload
      1464: astore_3
      1465: getstatic     #72                 // Field tags:Ljava/util/Map;
      1468: aload_3
      1469: invokeinterface #78,  2           // InterfaceMethod java/util/Map.get:(Ljava/lang/Object;)Ljava/lang/Object;
      1474: checkcast     #2                  // class coursier/util/shaded/org/jsoup/parser/Tag
      1477: astore        4
      1479: aload         4
      1481: invokestatic  #70                 // Method coursier/util/shaded/org/jsoup/helper/Validate.notNull:(Ljava/lang/Object;)V
      1484: aload         4
      1486: iconst_1
      1487: putfield      #44                 // Field preserveWhitespace:Z
      1490: iinc          2, 1
      1493: goto          1456
      1496: getstatic     #417                // Field formListedTags:[Ljava/lang/String;
      1499: astore_0
      1500: aload_0
      1501: arraylength
      1502: istore_1
      1503: iconst_0
      1504: istore_2
      1505: iload_2
      1506: iload_1
      1507: if_icmpge     1545
      1510: aload_0
      1511: iload_2
      1512: aaload
      1513: astore_3
      1514: getstatic     #72                 // Field tags:Ljava/util/Map;
      1517: aload_3
      1518: invokeinterface #78,  2           // InterfaceMethod java/util/Map.get:(Ljava/lang/Object;)Ljava/lang/Object;
      1523: checkcast     #2                  // class coursier/util/shaded/org/jsoup/parser/Tag
      1526: astore        4
      1528: aload         4
      1530: invokestatic  #70                 // Method coursier/util/shaded/org/jsoup/helper/Validate.notNull:(Ljava/lang/Object;)V
      1533: aload         4
      1535: iconst_1
      1536: putfield      #46                 // Field formList:Z
      1539: iinc          2, 1
      1542: goto          1505
      1545: getstatic     #419                // Field formSubmitTags:[Ljava/lang/String;
      1548: astore_0
      1549: aload_0
      1550: arraylength
      1551: istore_1
      1552: iconst_0
      1553: istore_2
      1554: iload_2
      1555: iload_1
      1556: if_icmpge     1594
      1559: aload_0
      1560: iload_2
      1561: aaload
      1562: astore_3
      1563: getstatic     #72                 // Field tags:Ljava/util/Map;
      1566: aload_3
      1567: invokeinterface #78,  2           // InterfaceMethod java/util/Map.get:(Ljava/lang/Object;)Ljava/lang/Object;
      1572: checkcast     #2                  // class coursier/util/shaded/org/jsoup/parser/Tag
      1575: astore        4
      1577: aload         4
      1579: invokestatic  #70                 // Method coursier/util/shaded/org/jsoup/helper/Validate.notNull:(Ljava/lang/Object;)V
      1582: aload         4
      1584: iconst_1
      1585: putfield      #48                 // Field formSubmit:Z
      1588: iinc          2, 1
      1591: goto          1554
      1594: return
      StackMapTable: number_of_entries = 14
        frame_type = 254 /* append */
          offset_delta = 1268
          locals = [ class "[Ljava/lang/String;", int, int ]
        frame_type = 248 /* chop */
          offset_delta = 29
        frame_type = 254 /* append */
          offset_delta = 8
          locals = [ class "[Ljava/lang/String;", int, int ]
        frame_type = 248 /* chop */
          offset_delta = 41
        frame_type = 254 /* append */
          offset_delta = 8
          locals = [ class "[Ljava/lang/String;", int, int ]
        frame_type = 248 /* chop */
          offset_delta = 39
        frame_type = 254 /* append */
          offset_delta = 8
          locals = [ class "[Ljava/lang/String;", int, int ]
        frame_type = 248 /* chop */
          offset_delta = 39
        frame_type = 254 /* append */
          offset_delta = 8
          locals = [ class "[Ljava/lang/String;", int, int ]
        frame_type = 248 /* chop */
          offset_delta = 39
        frame_type = 254 /* append */
          offset_delta = 8
          locals = [ class "[Ljava/lang/String;", int, int ]
        frame_type = 248 /* chop */
          offset_delta = 39
        frame_type = 254 /* append */
          offset_delta = 8
          locals = [ class "[Ljava/lang/String;", int, int ]
        frame_type = 248 /* chop */
          offset_delta = 39
      LineNumberTable:
        line 15: 0
        line 234: 10
        line 242: 409
        line 250: 873
        line 255: 1017
        line 259: 1136
        line 264: 1165
        line 267: 1222
        line 273: 1259
        line 274: 1277
        line 275: 1287
        line 273: 1292
        line 277: 1298
        line 278: 1316
        line 279: 1326
        line 280: 1332
        line 281: 1338
        line 277: 1343
        line 285: 1349
        line 286: 1367
        line 287: 1381
        line 288: 1386
        line 285: 1392
        line 291: 1398
        line 292: 1416
        line 293: 1430
        line 294: 1435
        line 291: 1441
        line 297: 1447
        line 298: 1465
        line 299: 1479
        line 300: 1484
        line 297: 1490
        line 303: 1496
        line 304: 1514
        line 305: 1528
        line 306: 1533
        line 303: 1539
        line 309: 1545
        line 310: 1563
        line 311: 1577
        line 312: 1582
        line 309: 1588
        line 314: 1594
      LocalVariableTable:
        Start  Length  Slot  Name   Signature
         1287       5     4   tag   Lcoursier/util/shaded/org/jsoup/parser/Tag;
         1277      15     3 tagName   Ljava/lang/String;
         1326      17     4   tag   Lcoursier/util/shaded/org/jsoup/parser/Tag;
         1316      27     3 tagName   Ljava/lang/String;
         1381      11     4   tag   Lcoursier/util/shaded/org/jsoup/parser/Tag;
         1367      25     3 tagName   Ljava/lang/String;
         1430      11     4   tag   Lcoursier/util/shaded/org/jsoup/parser/Tag;
         1416      25     3 tagName   Ljava/lang/String;
         1479      11     4   tag   Lcoursier/util/shaded/org/jsoup/parser/Tag;
         1465      25     3 tagName   Ljava/lang/String;
         1528      11     4   tag   Lcoursier/util/shaded/org/jsoup/parser/Tag;
         1514      25     3 tagName   Ljava/lang/String;
         1577      11     4   tag   Lcoursier/util/shaded/org/jsoup/parser/Tag;
         1563      25     3 tagName   Ljava/lang/String;
}
SourceFile: "Tag.java"
