Classfile /Users/mw/Projects/slang-braindump/.jar/jar11/assemble/slang-braindump/assemble/content/coursier/util/shaded/org/jsoup/parser/Token$EndTag.class
  Last modified May 29, 2022; size 1019 bytes
  SHA-256 checksum 414f0032216034a884b1ad28e3ea7a6954a16bb346b3f0cdb78fd55e3a21e9bb
  Compiled from "Token.java"
final class coursier.util.shaded.org.jsoup.parser.Token$EndTag extends coursier.util.shaded.org.jsoup.parser.Token$Tag
  minor version: 0
  major version: 51
  flags: (0x0030) ACC_FINAL, ACC_SUPER
  this_class: #2                          // coursier/util/shaded/org/jsoup/parser/Token$EndTag
  super_class: #4                         // coursier/util/shaded/org/jsoup/parser/Token$Tag
  interfaces: 0, fields: 0, methods: 2, attributes: 2
Constant pool:
   #1 = Utf8               coursier/util/shaded/org/jsoup/parser/Token$EndTag
   #2 = Class              #1             // coursier/util/shaded/org/jsoup/parser/Token$EndTag
   #3 = Utf8               coursier/util/shaded/org/jsoup/parser/Token$Tag
   #4 = Class              #3             // coursier/util/shaded/org/jsoup/parser/Token$Tag
   #5 = Utf8               Token.java
   #6 = Utf8               coursier/util/shaded/org/jsoup/parser/Token
   #7 = Class              #6             // coursier/util/shaded/org/jsoup/parser/Token
   #8 = Utf8               Tag
   #9 = Utf8               coursier/util/shaded/org/jsoup/parser/Token$TokenType
  #10 = Class              #9             // coursier/util/shaded/org/jsoup/parser/Token$TokenType
  #11 = Utf8               TokenType
  #12 = Utf8               EndTag
  #13 = Utf8               <init>
  #14 = Utf8               ()V
  #15 = NameAndType        #13:#14        // "<init>":()V
  #16 = Methodref          #4.#15         // coursier/util/shaded/org/jsoup/parser/Token$Tag."<init>":()V
  #17 = Utf8               Lcoursier/util/shaded/org/jsoup/parser/Token$TokenType;
  #18 = NameAndType        #12:#17        // EndTag:Lcoursier/util/shaded/org/jsoup/parser/Token$TokenType;
  #19 = Fieldref           #10.#18        // coursier/util/shaded/org/jsoup/parser/Token$TokenType.EndTag:Lcoursier/util/shaded/org/jsoup/parser/Token$TokenType;
  #20 = Utf8               type
  #21 = NameAndType        #20:#17        // type:Lcoursier/util/shaded/org/jsoup/parser/Token$TokenType;
  #22 = Fieldref           #2.#21         // coursier/util/shaded/org/jsoup/parser/Token$EndTag.type:Lcoursier/util/shaded/org/jsoup/parser/Token$TokenType;
  #23 = Utf8               this
  #24 = Utf8               Lcoursier/util/shaded/org/jsoup/parser/Token$EndTag;
  #25 = Utf8               toString
  #26 = Utf8               ()Ljava/lang/String;
  #27 = Utf8               java/lang/StringBuilder
  #28 = Class              #27            // java/lang/StringBuilder
  #29 = Methodref          #28.#15        // java/lang/StringBuilder."<init>":()V
  #30 = Utf8               </
  #31 = String             #30            // </
  #32 = Utf8               append
  #33 = Utf8               (Ljava/lang/String;)Ljava/lang/StringBuilder;
  #34 = NameAndType        #32:#33        // append:(Ljava/lang/String;)Ljava/lang/StringBuilder;
  #35 = Methodref          #28.#34        // java/lang/StringBuilder.append:(Ljava/lang/String;)Ljava/lang/StringBuilder;
  #36 = Utf8               tagName
  #37 = Utf8               Ljava/lang/String;
  #38 = NameAndType        #36:#37        // tagName:Ljava/lang/String;
  #39 = Fieldref           #2.#38         // coursier/util/shaded/org/jsoup/parser/Token$EndTag.tagName:Ljava/lang/String;
  #40 = Utf8               (unset)
  #41 = String             #40            // (unset)
  #42 = Utf8               java/lang/String
  #43 = Class              #42            // java/lang/String
  #44 = Utf8               >
  #45 = String             #44            // >
  #46 = NameAndType        #25:#26        // toString:()Ljava/lang/String;
  #47 = Methodref          #28.#46        // java/lang/StringBuilder.toString:()Ljava/lang/String;
  #48 = Utf8               Code
  #49 = Utf8               LineNumberTable
  #50 = Utf8               LocalVariableTable
  #51 = Utf8               StackMapTable
  #52 = Utf8               InnerClasses
  #53 = Utf8               SourceFile
{
  coursier.util.shaded.org.jsoup.parser.Token$EndTag();
    descriptor: ()V
    flags: (0x0000)
    Code:
      stack=2, locals=1, args_size=1
         0: aload_0
         1: invokespecial #16                 // Method coursier/util/shaded/org/jsoup/parser/Token$Tag."<init>":()V
         4: aload_0
         5: getstatic     #19                 // Field coursier/util/shaded/org/jsoup/parser/Token$TokenType.EndTag:Lcoursier/util/shaded/org/jsoup/parser/Token$TokenType;
         8: putfield      #22                 // Field type:Lcoursier/util/shaded/org/jsoup/parser/Token$TokenType;
        11: return
      LineNumberTable:
        line 249: 0
        line 250: 4
        line 251: 11
      LocalVariableTable:
        Start  Length  Slot  Name   Signature
            0      12     0  this   Lcoursier/util/shaded/org/jsoup/parser/Token$EndTag;

  public java.lang.String toString();
    descriptor: ()Ljava/lang/String;
    flags: (0x0001) ACC_PUBLIC
    Code:
      stack=2, locals=1, args_size=1
         0: new           #28                 // class java/lang/StringBuilder
         3: dup
         4: invokespecial #29                 // Method java/lang/StringBuilder."<init>":()V
         7: ldc           #31                 // String </
         9: invokevirtual #35                 // Method java/lang/StringBuilder.append:(Ljava/lang/String;)Ljava/lang/StringBuilder;
        12: aload_0
        13: getfield      #39                 // Field tagName:Ljava/lang/String;
        16: ifnull        26
        19: aload_0
        20: getfield      #39                 // Field tagName:Ljava/lang/String;
        23: goto          28
        26: ldc           #41                 // String (unset)
        28: invokevirtual #35                 // Method java/lang/StringBuilder.append:(Ljava/lang/String;)Ljava/lang/StringBuilder;
        31: ldc           #45                 // String >
        33: invokevirtual #35                 // Method java/lang/StringBuilder.append:(Ljava/lang/String;)Ljava/lang/StringBuilder;
        36: invokevirtual #47                 // Method java/lang/StringBuilder.toString:()Ljava/lang/String;
        39: areturn
      StackMapTable: number_of_entries = 2
        frame_type = 90 /* same_locals_1_stack_item */
          stack = [ class java/lang/StringBuilder ]
        frame_type = 255 /* full_frame */
          offset_delta = 1
          locals = [ class coursier/util/shaded/org/jsoup/parser/Token$EndTag ]
          stack = [ class java/lang/StringBuilder, class java/lang/String ]
      LineNumberTable:
        line 255: 0
      LocalVariableTable:
        Start  Length  Slot  Name   Signature
            0      40     0  this   Lcoursier/util/shaded/org/jsoup/parser/Token$EndTag;
}
InnerClasses:
  static abstract #8= #4 of #7;           // Tag=class coursier/util/shaded/org/jsoup/parser/Token$Tag of class coursier/util/shaded/org/jsoup/parser/Token
  public static final #11= #10 of #7;     // TokenType=class coursier/util/shaded/org/jsoup/parser/Token$TokenType of class coursier/util/shaded/org/jsoup/parser/Token
  static final #12= #2 of #7;             // EndTag=class coursier/util/shaded/org/jsoup/parser/Token$EndTag of class coursier/util/shaded/org/jsoup/parser/Token
SourceFile: "Token.java"
