Classfile /Users/mw/Projects/slang-braindump/.jar/jar11/assemble/slang-braindump/assemble/content/coursier/util/shaded/org/jsoup/parser/Token$EOF.class
  Last modified May 29, 2022; size 796 bytes
  SHA-256 checksum 68dc093ae807704fc051a7d7d29f00c42945f510ff7f819061bfc5a3c096f66f
  Compiled from "Token.java"
final class coursier.util.shaded.org.jsoup.parser.Token$EOF extends coursier.util.shaded.org.jsoup.parser.Token
  minor version: 0
  major version: 51
  flags: (0x0030) ACC_FINAL, ACC_SUPER
  this_class: #2                          // coursier/util/shaded/org/jsoup/parser/Token$EOF
  super_class: #4                         // coursier/util/shaded/org/jsoup/parser/Token
  interfaces: 0, fields: 0, methods: 2, attributes: 2
Constant pool:
   #1 = Utf8               coursier/util/shaded/org/jsoup/parser/Token$EOF
   #2 = Class              #1             // coursier/util/shaded/org/jsoup/parser/Token$EOF
   #3 = Utf8               coursier/util/shaded/org/jsoup/parser/Token
   #4 = Class              #3             // coursier/util/shaded/org/jsoup/parser/Token
   #5 = Utf8               Token.java
   #6 = Utf8               coursier/util/shaded/org/jsoup/parser/Token$1
   #7 = Class              #6             // coursier/util/shaded/org/jsoup/parser/Token$1
   #8 = Utf8               coursier/util/shaded/org/jsoup/parser/Token$TokenType
   #9 = Class              #8             // coursier/util/shaded/org/jsoup/parser/Token$TokenType
  #10 = Utf8               TokenType
  #11 = Utf8               EOF
  #12 = Utf8               <init>
  #13 = Utf8               ()V
  #14 = Utf8               (Lcoursier/util/shaded/org/jsoup/parser/Token$1;)V
  #15 = NameAndType        #12:#14        // "<init>":(Lcoursier/util/shaded/org/jsoup/parser/Token$1;)V
  #16 = Methodref          #4.#15         // coursier/util/shaded/org/jsoup/parser/Token."<init>":(Lcoursier/util/shaded/org/jsoup/parser/Token$1;)V
  #17 = Utf8               Lcoursier/util/shaded/org/jsoup/parser/Token$TokenType;
  #18 = NameAndType        #11:#17        // EOF:Lcoursier/util/shaded/org/jsoup/parser/Token$TokenType;
  #19 = Fieldref           #9.#18         // coursier/util/shaded/org/jsoup/parser/Token$TokenType.EOF:Lcoursier/util/shaded/org/jsoup/parser/Token$TokenType;
  #20 = Utf8               type
  #21 = NameAndType        #20:#17        // type:Lcoursier/util/shaded/org/jsoup/parser/Token$TokenType;
  #22 = Fieldref           #2.#21         // coursier/util/shaded/org/jsoup/parser/Token$EOF.type:Lcoursier/util/shaded/org/jsoup/parser/Token$TokenType;
  #23 = Utf8               this
  #24 = Utf8               Lcoursier/util/shaded/org/jsoup/parser/Token$EOF;
  #25 = Utf8               reset
  #26 = Utf8               ()Lcoursier/util/shaded/org/jsoup/parser/Token;
  #27 = Utf8               Code
  #28 = Utf8               LineNumberTable
  #29 = Utf8               LocalVariableTable
  #30 = Utf8               InnerClasses
  #31 = Utf8               SourceFile
{
  coursier.util.shaded.org.jsoup.parser.Token$EOF();
    descriptor: ()V
    flags: (0x0000)
    Code:
      stack=2, locals=1, args_size=1
         0: aload_0
         1: aconst_null
         2: invokespecial #16                 // Method coursier/util/shaded/org/jsoup/parser/Token."<init>":(Lcoursier/util/shaded/org/jsoup/parser/Token$1;)V
         5: aload_0
         6: getstatic     #19                 // Field coursier/util/shaded/org/jsoup/parser/Token$TokenType.EOF:Lcoursier/util/shaded/org/jsoup/parser/Token$TokenType;
         9: putfield      #22                 // Field type:Lcoursier/util/shaded/org/jsoup/parser/Token$TokenType;
        12: return
      LineNumberTable:
        line 354: 0
        line 355: 5
        line 356: 12
      LocalVariableTable:
        Start  Length  Slot  Name   Signature
            0      13     0  this   Lcoursier/util/shaded/org/jsoup/parser/Token$EOF;

  coursier.util.shaded.org.jsoup.parser.Token reset();
    descriptor: ()Lcoursier/util/shaded/org/jsoup/parser/Token;
    flags: (0x0000)
    Code:
      stack=1, locals=1, args_size=1
         0: aload_0
         1: areturn
      LineNumberTable:
        line 360: 0
      LocalVariableTable:
        Start  Length  Slot  Name   Signature
            0       2     0  this   Lcoursier/util/shaded/org/jsoup/parser/Token$EOF;
}
InnerClasses:
  static #7;                              // class coursier/util/shaded/org/jsoup/parser/Token$1
  public static final #10= #9 of #4;      // TokenType=class coursier/util/shaded/org/jsoup/parser/Token$TokenType of class coursier/util/shaded/org/jsoup/parser/Token
  static final #11= #2 of #4;             // EOF=class coursier/util/shaded/org/jsoup/parser/Token$EOF of class coursier/util/shaded/org/jsoup/parser/Token
SourceFile: "Token.java"
