Classfile /Users/mw/Projects/slang-braindump/.jar/jar11/assemble/slang-braindump/assemble/content/coursier/util/shaded/org/jsoup/parser/TokeniserState$54.class
  Last modified May 29, 2022; size 2151 bytes
  SHA-256 checksum 2cd4778df327ce842c73b6a30c6b16db04e49588ffc3b71d81f571ac0dafdd54
  Compiled from "TokeniserState.java"
final class coursier.util.shaded.org.jsoup.parser.TokeniserState$54 extends coursier.util.shaded.org.jsoup.parser.TokeniserState
  minor version: 0
  major version: 51
  flags: (0x4030) ACC_FINAL, ACC_SUPER, ACC_ENUM
  this_class: #2                          // coursier/util/shaded/org/jsoup/parser/TokeniserState$54
  super_class: #4                         // coursier/util/shaded/org/jsoup/parser/TokeniserState
  interfaces: 0, fields: 0, methods: 2, attributes: 3
Constant pool:
    #1 = Utf8               coursier/util/shaded/org/jsoup/parser/TokeniserState$54
    #2 = Class              #1            // coursier/util/shaded/org/jsoup/parser/TokeniserState$54
    #3 = Utf8               coursier/util/shaded/org/jsoup/parser/TokeniserState
    #4 = Class              #3            // coursier/util/shaded/org/jsoup/parser/TokeniserState
    #5 = Utf8               TokeniserState.java
    #6 = Utf8               coursier/util/shaded/org/jsoup/parser/TokeniserState$1
    #7 = Class              #6            // coursier/util/shaded/org/jsoup/parser/TokeniserState$1
    #8 = Utf8               coursier/util/shaded/org/jsoup/parser/Token$Doctype
    #9 = Class              #8            // coursier/util/shaded/org/jsoup/parser/Token$Doctype
   #10 = Utf8               coursier/util/shaded/org/jsoup/parser/Token
   #11 = Class              #10           // coursier/util/shaded/org/jsoup/parser/Token
   #12 = Utf8               Doctype
   #13 = Utf8               <init>
   #14 = Utf8               (Ljava/lang/String;I)V
   #15 = Utf8               (Ljava/lang/String;ILcoursier/util/shaded/org/jsoup/parser/TokeniserState$1;)V
   #16 = NameAndType        #13:#15       // "<init>":(Ljava/lang/String;ILcoursier/util/shaded/org/jsoup/parser/TokeniserState$1;)V
   #17 = Methodref          #4.#16        // coursier/util/shaded/org/jsoup/parser/TokeniserState."<init>":(Ljava/lang/String;ILcoursier/util/shaded/org/jsoup/parser/TokeniserState$1;)V
   #18 = Utf8               this
   #19 = Utf8               Lcoursier/util/shaded/org/jsoup/parser/TokeniserState$54;
   #20 = Utf8               read
   #21 = Utf8               (Lcoursier/util/shaded/org/jsoup/parser/Tokeniser;Lcoursier/util/shaded/org/jsoup/parser/CharacterReader;)V
   #22 = Utf8               coursier/util/shaded/org/jsoup/parser/CharacterReader
   #23 = Class              #22           // coursier/util/shaded/org/jsoup/parser/CharacterReader
   #24 = Utf8               isEmpty
   #25 = Utf8               ()Z
   #26 = NameAndType        #24:#25       // isEmpty:()Z
   #27 = Methodref          #23.#26       // coursier/util/shaded/org/jsoup/parser/CharacterReader.isEmpty:()Z
   #28 = Utf8               coursier/util/shaded/org/jsoup/parser/Tokeniser
   #29 = Class              #28           // coursier/util/shaded/org/jsoup/parser/Tokeniser
   #30 = Utf8               eofError
   #31 = Utf8               (Lcoursier/util/shaded/org/jsoup/parser/TokeniserState;)V
   #32 = NameAndType        #30:#31       // eofError:(Lcoursier/util/shaded/org/jsoup/parser/TokeniserState;)V
   #33 = Methodref          #29.#32       // coursier/util/shaded/org/jsoup/parser/Tokeniser.eofError:(Lcoursier/util/shaded/org/jsoup/parser/TokeniserState;)V
   #34 = Utf8               doctypePending
   #35 = Utf8               Lcoursier/util/shaded/org/jsoup/parser/Token$Doctype;
   #36 = NameAndType        #34:#35       // doctypePending:Lcoursier/util/shaded/org/jsoup/parser/Token$Doctype;
   #37 = Fieldref           #29.#36       // coursier/util/shaded/org/jsoup/parser/Tokeniser.doctypePending:Lcoursier/util/shaded/org/jsoup/parser/Token$Doctype;
   #38 = Utf8               forceQuirks
   #39 = Utf8               Z
   #40 = NameAndType        #38:#39       // forceQuirks:Z
   #41 = Fieldref           #9.#40        // coursier/util/shaded/org/jsoup/parser/Token$Doctype.forceQuirks:Z
   #42 = Utf8               emitDoctypePending
   #43 = Utf8               ()V
   #44 = NameAndType        #42:#43       // emitDoctypePending:()V
   #45 = Methodref          #29.#44       // coursier/util/shaded/org/jsoup/parser/Tokeniser.emitDoctypePending:()V
   #46 = Utf8               Data
   #47 = Utf8               Lcoursier/util/shaded/org/jsoup/parser/TokeniserState;
   #48 = NameAndType        #46:#47       // Data:Lcoursier/util/shaded/org/jsoup/parser/TokeniserState;
   #49 = Fieldref           #2.#48        // coursier/util/shaded/org/jsoup/parser/TokeniserState$54.Data:Lcoursier/util/shaded/org/jsoup/parser/TokeniserState;
   #50 = Utf8               transition
   #51 = NameAndType        #50:#31       // transition:(Lcoursier/util/shaded/org/jsoup/parser/TokeniserState;)V
   #52 = Methodref          #29.#51       // coursier/util/shaded/org/jsoup/parser/Tokeniser.transition:(Lcoursier/util/shaded/org/jsoup/parser/TokeniserState;)V
   #53 = Utf8               matchesAny
   #54 = Utf8               ([C)Z
   #55 = NameAndType        #53:#54       // matchesAny:([C)Z
   #56 = Methodref          #23.#55       // coursier/util/shaded/org/jsoup/parser/CharacterReader.matchesAny:([C)Z
   #57 = Utf8               advance
   #58 = NameAndType        #57:#43       // advance:()V
   #59 = Methodref          #23.#58       // coursier/util/shaded/org/jsoup/parser/CharacterReader.advance:()V
   #60 = Utf8               matches
   #61 = Utf8               (C)Z
   #62 = NameAndType        #60:#61       // matches:(C)Z
   #63 = Methodref          #23.#62       // coursier/util/shaded/org/jsoup/parser/CharacterReader.matches:(C)Z
   #64 = Utf8               advanceTransition
   #65 = NameAndType        #64:#31       // advanceTransition:(Lcoursier/util/shaded/org/jsoup/parser/TokeniserState;)V
   #66 = Methodref          #29.#65       // coursier/util/shaded/org/jsoup/parser/Tokeniser.advanceTransition:(Lcoursier/util/shaded/org/jsoup/parser/TokeniserState;)V
   #67 = Utf8               PUBLIC
   #68 = String             #67           // PUBLIC
   #69 = Utf8               matchConsumeIgnoreCase
   #70 = Utf8               (Ljava/lang/String;)Z
   #71 = NameAndType        #69:#70       // matchConsumeIgnoreCase:(Ljava/lang/String;)Z
   #72 = Methodref          #23.#71       // coursier/util/shaded/org/jsoup/parser/CharacterReader.matchConsumeIgnoreCase:(Ljava/lang/String;)Z
   #73 = Utf8               pubSysKey
   #74 = Utf8               Ljava/lang/String;
   #75 = NameAndType        #73:#74       // pubSysKey:Ljava/lang/String;
   #76 = Fieldref           #9.#75        // coursier/util/shaded/org/jsoup/parser/Token$Doctype.pubSysKey:Ljava/lang/String;
   #77 = Utf8               AfterDoctypePublicKeyword
   #78 = NameAndType        #77:#47       // AfterDoctypePublicKeyword:Lcoursier/util/shaded/org/jsoup/parser/TokeniserState;
   #79 = Fieldref           #2.#78        // coursier/util/shaded/org/jsoup/parser/TokeniserState$54.AfterDoctypePublicKeyword:Lcoursier/util/shaded/org/jsoup/parser/TokeniserState;
   #80 = Utf8               SYSTEM
   #81 = String             #80           // SYSTEM
   #82 = Utf8               AfterDoctypeSystemKeyword
   #83 = NameAndType        #82:#47       // AfterDoctypeSystemKeyword:Lcoursier/util/shaded/org/jsoup/parser/TokeniserState;
   #84 = Fieldref           #2.#83        // coursier/util/shaded/org/jsoup/parser/TokeniserState$54.AfterDoctypeSystemKeyword:Lcoursier/util/shaded/org/jsoup/parser/TokeniserState;
   #85 = Utf8               error
   #86 = NameAndType        #85:#31       // error:(Lcoursier/util/shaded/org/jsoup/parser/TokeniserState;)V
   #87 = Methodref          #29.#86       // coursier/util/shaded/org/jsoup/parser/Tokeniser.error:(Lcoursier/util/shaded/org/jsoup/parser/TokeniserState;)V
   #88 = Utf8               BogusDoctype
   #89 = NameAndType        #88:#47       // BogusDoctype:Lcoursier/util/shaded/org/jsoup/parser/TokeniserState;
   #90 = Fieldref           #2.#89        // coursier/util/shaded/org/jsoup/parser/TokeniserState$54.BogusDoctype:Lcoursier/util/shaded/org/jsoup/parser/TokeniserState;
   #91 = Utf8               t
   #92 = Utf8               Lcoursier/util/shaded/org/jsoup/parser/Tokeniser;
   #93 = Utf8               r
   #94 = Utf8               Lcoursier/util/shaded/org/jsoup/parser/CharacterReader;
   #95 = Utf8               Code
   #96 = Utf8               LineNumberTable
   #97 = Utf8               LocalVariableTable
   #98 = Utf8               StackMapTable
   #99 = Utf8               InnerClasses
  #100 = Utf8               EnclosingMethod
  #101 = Utf8               SourceFile
{
  coursier.util.shaded.org.jsoup.parser.TokeniserState$54(java.lang.String, int);
    descriptor: (Ljava/lang/String;I)V
    flags: (0x0000)
    Code:
      stack=4, locals=3, args_size=3
         0: aload_0
         1: aload_1
         2: iload_2
         3: aconst_null
         4: invokespecial #17                 // Method coursier/util/shaded/org/jsoup/parser/TokeniserState."<init>":(Ljava/lang/String;ILcoursier/util/shaded/org/jsoup/parser/TokeniserState$1;)V
         7: return
      LineNumberTable:
        line 1203: 0
      LocalVariableTable:
        Start  Length  Slot  Name   Signature
            0       8     0  this   Lcoursier/util/shaded/org/jsoup/parser/TokeniserState$54;

  void read(coursier.util.shaded.org.jsoup.parser.Tokeniser, coursier.util.shaded.org.jsoup.parser.CharacterReader);
    descriptor: (Lcoursier/util/shaded/org/jsoup/parser/Tokeniser;Lcoursier/util/shaded/org/jsoup/parser/CharacterReader;)V
    flags: (0x0000)
    Code:
      stack=5, locals=3, args_size=3
         0: aload_2
         1: invokevirtual #27                 // Method coursier/util/shaded/org/jsoup/parser/CharacterReader.isEmpty:()Z
         4: ifeq          32
         7: aload_1
         8: aload_0
         9: invokevirtual #33                 // Method coursier/util/shaded/org/jsoup/parser/Tokeniser.eofError:(Lcoursier/util/shaded/org/jsoup/parser/TokeniserState;)V
        12: aload_1
        13: getfield      #37                 // Field coursier/util/shaded/org/jsoup/parser/Tokeniser.doctypePending:Lcoursier/util/shaded/org/jsoup/parser/Token$Doctype;
        16: iconst_1
        17: putfield      #41                 // Field coursier/util/shaded/org/jsoup/parser/Token$Doctype.forceQuirks:Z
        20: aload_1
        21: invokevirtual #45                 // Method coursier/util/shaded/org/jsoup/parser/Tokeniser.emitDoctypePending:()V
        24: aload_1
        25: getstatic     #49                 // Field Data:Lcoursier/util/shaded/org/jsoup/parser/TokeniserState;
        28: invokevirtual #52                 // Method coursier/util/shaded/org/jsoup/parser/Tokeniser.transition:(Lcoursier/util/shaded/org/jsoup/parser/TokeniserState;)V
        31: return
        32: aload_2
        33: iconst_5
        34: newarray       char
        36: dup
        37: iconst_0
        38: bipush        9
        40: castore
        41: dup
        42: iconst_1
        43: bipush        10
        45: castore
        46: dup
        47: iconst_2
        48: bipush        13
        50: castore
        51: dup
        52: iconst_3
        53: bipush        12
        55: castore
        56: dup
        57: iconst_4
        58: bipush        32
        60: castore
        61: invokevirtual #56                 // Method coursier/util/shaded/org/jsoup/parser/CharacterReader.matchesAny:([C)Z
        64: ifeq          74
        67: aload_2
        68: invokevirtual #59                 // Method coursier/util/shaded/org/jsoup/parser/CharacterReader.advance:()V
        71: goto          173
        74: aload_2
        75: bipush        62
        77: invokevirtual #63                 // Method coursier/util/shaded/org/jsoup/parser/CharacterReader.matches:(C)Z
        80: ifeq          97
        83: aload_1
        84: invokevirtual #45                 // Method coursier/util/shaded/org/jsoup/parser/Tokeniser.emitDoctypePending:()V
        87: aload_1
        88: getstatic     #49                 // Field Data:Lcoursier/util/shaded/org/jsoup/parser/TokeniserState;
        91: invokevirtual #66                 // Method coursier/util/shaded/org/jsoup/parser/Tokeniser.advanceTransition:(Lcoursier/util/shaded/org/jsoup/parser/TokeniserState;)V
        94: goto          173
        97: aload_2
        98: ldc           #68                 // String PUBLIC
       100: invokevirtual #72                 // Method coursier/util/shaded/org/jsoup/parser/CharacterReader.matchConsumeIgnoreCase:(Ljava/lang/String;)Z
       103: ifeq          125
       106: aload_1
       107: getfield      #37                 // Field coursier/util/shaded/org/jsoup/parser/Tokeniser.doctypePending:Lcoursier/util/shaded/org/jsoup/parser/Token$Doctype;
       110: ldc           #68                 // String PUBLIC
       112: putfield      #76                 // Field coursier/util/shaded/org/jsoup/parser/Token$Doctype.pubSysKey:Ljava/lang/String;
       115: aload_1
       116: getstatic     #79                 // Field AfterDoctypePublicKeyword:Lcoursier/util/shaded/org/jsoup/parser/TokeniserState;
       119: invokevirtual #52                 // Method coursier/util/shaded/org/jsoup/parser/Tokeniser.transition:(Lcoursier/util/shaded/org/jsoup/parser/TokeniserState;)V
       122: goto          173
       125: aload_2
       126: ldc           #81                 // String SYSTEM
       128: invokevirtual #72                 // Method coursier/util/shaded/org/jsoup/parser/CharacterReader.matchConsumeIgnoreCase:(Ljava/lang/String;)Z
       131: ifeq          153
       134: aload_1
       135: getfield      #37                 // Field coursier/util/shaded/org/jsoup/parser/Tokeniser.doctypePending:Lcoursier/util/shaded/org/jsoup/parser/Token$Doctype;
       138: ldc           #81                 // String SYSTEM
       140: putfield      #76                 // Field coursier/util/shaded/org/jsoup/parser/Token$Doctype.pubSysKey:Ljava/lang/String;
       143: aload_1
       144: getstatic     #84                 // Field AfterDoctypeSystemKeyword:Lcoursier/util/shaded/org/jsoup/parser/TokeniserState;
       147: invokevirtual #52                 // Method coursier/util/shaded/org/jsoup/parser/Tokeniser.transition:(Lcoursier/util/shaded/org/jsoup/parser/TokeniserState;)V
       150: goto          173
       153: aload_1
       154: aload_0
       155: invokevirtual #87                 // Method coursier/util/shaded/org/jsoup/parser/Tokeniser.error:(Lcoursier/util/shaded/org/jsoup/parser/TokeniserState;)V
       158: aload_1
       159: getfield      #37                 // Field coursier/util/shaded/org/jsoup/parser/Tokeniser.doctypePending:Lcoursier/util/shaded/org/jsoup/parser/Token$Doctype;
       162: iconst_1
       163: putfield      #41                 // Field coursier/util/shaded/org/jsoup/parser/Token$Doctype.forceQuirks:Z
       166: aload_1
       167: getstatic     #90                 // Field BogusDoctype:Lcoursier/util/shaded/org/jsoup/parser/TokeniserState;
       170: invokevirtual #66                 // Method coursier/util/shaded/org/jsoup/parser/Tokeniser.advanceTransition:(Lcoursier/util/shaded/org/jsoup/parser/TokeniserState;)V
       173: return
      StackMapTable: number_of_entries = 6
        frame_type = 32 /* same */
        frame_type = 41 /* same */
        frame_type = 22 /* same */
        frame_type = 27 /* same */
        frame_type = 27 /* same */
        frame_type = 19 /* same */
      LineNumberTable:
        line 1205: 0
        line 1206: 7
        line 1207: 12
        line 1208: 20
        line 1209: 24
        line 1210: 31
        line 1212: 32
        line 1213: 67
        line 1214: 74
        line 1215: 83
        line 1216: 87
        line 1217: 97
        line 1218: 106
        line 1219: 115
        line 1220: 125
        line 1221: 134
        line 1222: 143
        line 1224: 153
        line 1225: 158
        line 1226: 166
        line 1229: 173
      LocalVariableTable:
        Start  Length  Slot  Name   Signature
            0     174     0  this   Lcoursier/util/shaded/org/jsoup/parser/TokeniserState$54;
            0     174     1     t   Lcoursier/util/shaded/org/jsoup/parser/Tokeniser;
            0     174     2     r   Lcoursier/util/shaded/org/jsoup/parser/CharacterReader;
}
InnerClasses:
  final #7;                               // class coursier/util/shaded/org/jsoup/parser/TokeniserState$1
  static final #12= #9 of #11;            // Doctype=class coursier/util/shaded/org/jsoup/parser/Token$Doctype of class coursier/util/shaded/org/jsoup/parser/Token
  final #2;                               // class coursier/util/shaded/org/jsoup/parser/TokeniserState$54
EnclosingMethod: #4.#0                  // coursier.util.shaded.org.jsoup.parser.TokeniserState
SourceFile: "TokeniserState.java"
