Classfile /Users/mw/Projects/slang-braindump/.jar/jar11/assemble/slang-braindump/assemble/content/coursier/util/shaded/org/jsoup/parser/TokenQueue.class
  Last modified May 29, 2022; size 7172 bytes
  SHA-256 checksum 8b979a6a6162c3b122757ab396a1e511a8579783eb4e54d04f1f2f9c9119b908
  Compiled from "TokenQueue.java"
public class coursier.util.shaded.org.jsoup.parser.TokenQueue
  minor version: 0
  major version: 51
  flags: (0x0021) ACC_PUBLIC, ACC_SUPER
  this_class: #2                          // coursier/util/shaded/org/jsoup/parser/TokenQueue
  super_class: #4                         // java/lang/Object
  interfaces: 0, fields: 3, methods: 32, attributes: 1
Constant pool:
    #1 = Utf8               coursier/util/shaded/org/jsoup/parser/TokenQueue
    #2 = Class              #1            // coursier/util/shaded/org/jsoup/parser/TokenQueue
    #3 = Utf8               java/lang/Object
    #4 = Class              #3            // java/lang/Object
    #5 = Utf8               TokenQueue.java
    #6 = Utf8               queue
    #7 = Utf8               Ljava/lang/String;
    #8 = Utf8               pos
    #9 = Utf8               I
   #10 = Utf8               ESC
   #11 = Utf8               C
   #12 = Integer            92
   #13 = Utf8               <init>
   #14 = Utf8               (Ljava/lang/String;)V
   #15 = Utf8               ()V
   #16 = NameAndType        #13:#15       // "<init>":()V
   #17 = Methodref          #4.#16        // java/lang/Object."<init>":()V
   #18 = NameAndType        #8:#9         // pos:I
   #19 = Fieldref           #2.#18        // coursier/util/shaded/org/jsoup/parser/TokenQueue.pos:I
   #20 = Utf8               coursier/util/shaded/org/jsoup/helper/Validate
   #21 = Class              #20           // coursier/util/shaded/org/jsoup/helper/Validate
   #22 = Utf8               notNull
   #23 = Utf8               (Ljava/lang/Object;)V
   #24 = NameAndType        #22:#23       // notNull:(Ljava/lang/Object;)V
   #25 = Methodref          #21.#24       // coursier/util/shaded/org/jsoup/helper/Validate.notNull:(Ljava/lang/Object;)V
   #26 = NameAndType        #6:#7         // queue:Ljava/lang/String;
   #27 = Fieldref           #2.#26        // coursier/util/shaded/org/jsoup/parser/TokenQueue.queue:Ljava/lang/String;
   #28 = Utf8               this
   #29 = Utf8               Lcoursier/util/shaded/org/jsoup/parser/TokenQueue;
   #30 = Utf8               data
   #31 = Utf8               isEmpty
   #32 = Utf8               ()Z
   #33 = Utf8               remainingLength
   #34 = Utf8               ()I
   #35 = NameAndType        #33:#34       // remainingLength:()I
   #36 = Methodref          #2.#35        // coursier/util/shaded/org/jsoup/parser/TokenQueue.remainingLength:()I
   #37 = Utf8               java/lang/String
   #38 = Class              #37           // java/lang/String
   #39 = Utf8               length
   #40 = NameAndType        #39:#34       // length:()I
   #41 = Methodref          #38.#40       // java/lang/String.length:()I
   #42 = Utf8               peek
   #43 = Utf8               ()C
   #44 = NameAndType        #31:#32       // isEmpty:()Z
   #45 = Methodref          #2.#44        // coursier/util/shaded/org/jsoup/parser/TokenQueue.isEmpty:()Z
   #46 = Utf8               charAt
   #47 = Utf8               (I)C
   #48 = NameAndType        #46:#47       // charAt:(I)C
   #49 = Methodref          #38.#48       // java/lang/String.charAt:(I)C
   #50 = Utf8               addFirst
   #51 = Utf8               (Ljava/lang/Character;)V
   #52 = Utf8               java/lang/Character
   #53 = Class              #52           // java/lang/Character
   #54 = Utf8               toString
   #55 = Utf8               ()Ljava/lang/String;
   #56 = NameAndType        #54:#55       // toString:()Ljava/lang/String;
   #57 = Methodref          #53.#56       // java/lang/Character.toString:()Ljava/lang/String;
   #58 = NameAndType        #50:#14       // addFirst:(Ljava/lang/String;)V
   #59 = Methodref          #2.#58        // coursier/util/shaded/org/jsoup/parser/TokenQueue.addFirst:(Ljava/lang/String;)V
   #60 = Utf8               c
   #61 = Utf8               Ljava/lang/Character;
   #62 = Utf8               java/lang/StringBuilder
   #63 = Class              #62           // java/lang/StringBuilder
   #64 = Methodref          #63.#16       // java/lang/StringBuilder."<init>":()V
   #65 = Utf8               append
   #66 = Utf8               (Ljava/lang/String;)Ljava/lang/StringBuilder;
   #67 = NameAndType        #65:#66       // append:(Ljava/lang/String;)Ljava/lang/StringBuilder;
   #68 = Methodref          #63.#67       // java/lang/StringBuilder.append:(Ljava/lang/String;)Ljava/lang/StringBuilder;
   #69 = Utf8               substring
   #70 = Utf8               (I)Ljava/lang/String;
   #71 = NameAndType        #69:#70       // substring:(I)Ljava/lang/String;
   #72 = Methodref          #38.#71       // java/lang/String.substring:(I)Ljava/lang/String;
   #73 = Methodref          #63.#56       // java/lang/StringBuilder.toString:()Ljava/lang/String;
   #74 = Utf8               seq
   #75 = Utf8               matches
   #76 = Utf8               (Ljava/lang/String;)Z
   #77 = Utf8               regionMatches
   #78 = Utf8               (ZILjava/lang/String;II)Z
   #79 = NameAndType        #77:#78       // regionMatches:(ZILjava/lang/String;II)Z
   #80 = Methodref          #38.#79       // java/lang/String.regionMatches:(ZILjava/lang/String;II)Z
   #81 = Utf8               matchesCS
   #82 = Utf8               startsWith
   #83 = Utf8               (Ljava/lang/String;I)Z
   #84 = NameAndType        #82:#83       // startsWith:(Ljava/lang/String;I)Z
   #85 = Methodref          #38.#84       // java/lang/String.startsWith:(Ljava/lang/String;I)Z
   #86 = Utf8               matchesAny
   #87 = Utf8               ([Ljava/lang/String;)Z
   #88 = Utf8               [Ljava/lang/String;
   #89 = Class              #88           // "[Ljava/lang/String;"
   #90 = NameAndType        #75:#76       // matches:(Ljava/lang/String;)Z
   #91 = Methodref          #2.#90        // coursier/util/shaded/org/jsoup/parser/TokenQueue.matches:(Ljava/lang/String;)Z
   #92 = Utf8               s
   #93 = Utf8               ([C)Z
   #94 = Utf8               [C
   #95 = Class              #94           // "[C"
   #96 = Utf8               matchesStartTag
   #97 = Utf8               isLetter
   #98 = Utf8               (C)Z
   #99 = NameAndType        #97:#98       // isLetter:(C)Z
  #100 = Methodref          #53.#99       // java/lang/Character.isLetter:(C)Z
  #101 = Utf8               matchChomp
  #102 = Utf8               matchesWhitespace
  #103 = Utf8               coursier/util/shaded/org/jsoup/internal/StringUtil
  #104 = Class              #103          // coursier/util/shaded/org/jsoup/internal/StringUtil
  #105 = Utf8               isWhitespace
  #106 = Utf8               (I)Z
  #107 = NameAndType        #105:#106     // isWhitespace:(I)Z
  #108 = Methodref          #104.#107     // coursier/util/shaded/org/jsoup/internal/StringUtil.isWhitespace:(I)Z
  #109 = Utf8               matchesWord
  #110 = Utf8               isLetterOrDigit
  #111 = NameAndType        #110:#98      // isLetterOrDigit:(C)Z
  #112 = Methodref          #53.#111      // java/lang/Character.isLetterOrDigit:(C)Z
  #113 = Utf8               advance
  #114 = Utf8               consume
  #115 = Utf8               java/lang/IllegalStateException
  #116 = Class              #115          // java/lang/IllegalStateException
  #117 = Utf8               Queue did not match expected sequence
  #118 = String             #117          // Queue did not match expected sequence
  #119 = NameAndType        #13:#14       // "<init>":(Ljava/lang/String;)V
  #120 = Methodref          #116.#119     // java/lang/IllegalStateException."<init>":(Ljava/lang/String;)V
  #121 = Utf8               Queue not long enough to consume sequence
  #122 = String             #121          // Queue not long enough to consume sequence
  #123 = Utf8               len
  #124 = Utf8               consumeTo
  #125 = Utf8               (Ljava/lang/String;)Ljava/lang/String;
  #126 = Utf8               indexOf
  #127 = Utf8               (Ljava/lang/String;I)I
  #128 = NameAndType        #126:#127     // indexOf:(Ljava/lang/String;I)I
  #129 = Methodref          #38.#128      // java/lang/String.indexOf:(Ljava/lang/String;I)I
  #130 = Utf8               (II)Ljava/lang/String;
  #131 = NameAndType        #69:#130      // substring:(II)Ljava/lang/String;
  #132 = Methodref          #38.#131      // java/lang/String.substring:(II)Ljava/lang/String;
  #133 = Utf8               remainder
  #134 = NameAndType        #133:#55      // remainder:()Ljava/lang/String;
  #135 = Methodref          #2.#134       // coursier/util/shaded/org/jsoup/parser/TokenQueue.remainder:()Ljava/lang/String;
  #136 = Utf8               consumed
  #137 = Utf8               offset
  #138 = Utf8               consumeToIgnoreCase
  #139 = Utf8               toLowerCase
  #140 = NameAndType        #139:#55      // toLowerCase:()Ljava/lang/String;
  #141 = Methodref          #38.#140      // java/lang/String.toLowerCase:()Ljava/lang/String;
  #142 = Utf8               toUpperCase
  #143 = NameAndType        #142:#55      // toUpperCase:()Ljava/lang/String;
  #144 = Methodref          #38.#143      // java/lang/String.toUpperCase:()Ljava/lang/String;
  #145 = Utf8               equals
  #146 = Utf8               (Ljava/lang/Object;)Z
  #147 = NameAndType        #145:#146     // equals:(Ljava/lang/Object;)Z
  #148 = Methodref          #38.#147      // java/lang/String.equals:(Ljava/lang/Object;)Z
  #149 = Utf8               skip
  #150 = Utf8               start
  #151 = Utf8               first
  #152 = Utf8               canScan
  #153 = Utf8               Z
  #154 = Utf8               consumeToAny
  #155 = Utf8               ([Ljava/lang/String;)Ljava/lang/String;
  #156 = NameAndType        #86:#87       // matchesAny:([Ljava/lang/String;)Z
  #157 = Methodref          #2.#156       // coursier/util/shaded/org/jsoup/parser/TokenQueue.matchesAny:([Ljava/lang/String;)Z
  #158 = Utf8               chompTo
  #159 = NameAndType        #124:#125     // consumeTo:(Ljava/lang/String;)Ljava/lang/String;
  #160 = Methodref          #2.#159       // coursier/util/shaded/org/jsoup/parser/TokenQueue.consumeTo:(Ljava/lang/String;)Ljava/lang/String;
  #161 = NameAndType        #101:#76      // matchChomp:(Ljava/lang/String;)Z
  #162 = Methodref          #2.#161       // coursier/util/shaded/org/jsoup/parser/TokenQueue.matchChomp:(Ljava/lang/String;)Z
  #163 = Utf8               chompToIgnoreCase
  #164 = NameAndType        #138:#125     // consumeToIgnoreCase:(Ljava/lang/String;)Ljava/lang/String;
  #165 = Methodref          #2.#164       // coursier/util/shaded/org/jsoup/parser/TokenQueue.consumeToIgnoreCase:(Ljava/lang/String;)Ljava/lang/String;
  #166 = Utf8               chompBalanced
  #167 = Utf8               (CC)Ljava/lang/String;
  #168 = NameAndType        #114:#43      // consume:()C
  #169 = Methodref          #2.#168       // coursier/util/shaded/org/jsoup/parser/TokenQueue.consume:()C
  #170 = Utf8
  #171 = String             #170          //
  #172 = Utf8               Did not find balanced marker at \'
  #173 = String             #172          // Did not find balanced marker at \'
  #174 = Utf8               \'
  #175 = String             #174          // \'
  #176 = Utf8               fail
  #177 = NameAndType        #176:#14      // fail:(Ljava/lang/String;)V
  #178 = Methodref          #21.#177      // coursier/util/shaded/org/jsoup/helper/Validate.fail:(Ljava/lang/String;)V
  #179 = Utf8               open
  #180 = Utf8               close
  #181 = Utf8               end
  #182 = Utf8               depth
  #183 = Utf8               last
  #184 = Utf8               inSingleQuote
  #185 = Utf8               inDoubleQuote
  #186 = Utf8               out
  #187 = Utf8               unescape
  #188 = Utf8               borrowBuilder
  #189 = Utf8               ()Ljava/lang/StringBuilder;
  #190 = NameAndType        #188:#189     // borrowBuilder:()Ljava/lang/StringBuilder;
  #191 = Methodref          #104.#190     // coursier/util/shaded/org/jsoup/internal/StringUtil.borrowBuilder:()Ljava/lang/StringBuilder;
  #192 = Utf8               toCharArray
  #193 = Utf8               ()[C
  #194 = NameAndType        #192:#193     // toCharArray:()[C
  #195 = Methodref          #38.#194      // java/lang/String.toCharArray:()[C
  #196 = Utf8               (C)Ljava/lang/StringBuilder;
  #197 = NameAndType        #65:#196      // append:(C)Ljava/lang/StringBuilder;
  #198 = Methodref          #63.#197      // java/lang/StringBuilder.append:(C)Ljava/lang/StringBuilder;
  #199 = Utf8               releaseBuilder
  #200 = Utf8               (Ljava/lang/StringBuilder;)Ljava/lang/String;
  #201 = NameAndType        #199:#200     // releaseBuilder:(Ljava/lang/StringBuilder;)Ljava/lang/String;
  #202 = Methodref          #104.#201     // coursier/util/shaded/org/jsoup/internal/StringUtil.releaseBuilder:(Ljava/lang/StringBuilder;)Ljava/lang/String;
  #203 = Utf8               in
  #204 = Utf8               Ljava/lang/StringBuilder;
  #205 = Utf8               consumeWhitespace
  #206 = NameAndType        #102:#32      // matchesWhitespace:()Z
  #207 = Methodref          #2.#206       // coursier/util/shaded/org/jsoup/parser/TokenQueue.matchesWhitespace:()Z
  #208 = Utf8               seen
  #209 = Utf8               consumeWord
  #210 = NameAndType        #109:#32      // matchesWord:()Z
  #211 = Methodref          #2.#210       // coursier/util/shaded/org/jsoup/parser/TokenQueue.matchesWord:()Z
  #212 = Utf8               consumeTagName
  #213 = NameAndType        #86:#93       // matchesAny:([C)Z
  #214 = Methodref          #2.#213       // coursier/util/shaded/org/jsoup/parser/TokenQueue.matchesAny:([C)Z
  #215 = Utf8               consumeElementSelector
  #216 = Utf8               *|
  #217 = String             #216          // *|
  #218 = Utf8               |
  #219 = String             #218          // |
  #220 = Utf8               _
  #221 = String             #220          // _
  #222 = Utf8               -
  #223 = String             #222          // -
  #224 = Utf8               consumeCssIdentifier
  #225 = Utf8               consumeAttributeKey
  #226 = Utf8               ConstantValue
  #227 = Utf8               Code
  #228 = Utf8               LineNumberTable
  #229 = Utf8               LocalVariableTable
  #230 = Utf8               StackMapTable
  #231 = Utf8               SourceFile
{
  private java.lang.String queue;
    descriptor: Ljava/lang/String;
    flags: (0x0002) ACC_PRIVATE

  private int pos;
    descriptor: I
    flags: (0x0002) ACC_PRIVATE

  private static final char ESC;
    descriptor: C
    flags: (0x001a) ACC_PRIVATE, ACC_STATIC, ACC_FINAL
    ConstantValue: int 92

  public coursier.util.shaded.org.jsoup.parser.TokenQueue(java.lang.String);
    descriptor: (Ljava/lang/String;)V
    flags: (0x0001) ACC_PUBLIC
    Code:
      stack=2, locals=2, args_size=2
         0: aload_0
         1: invokespecial #17                 // Method java/lang/Object."<init>":()V
         4: aload_0
         5: iconst_0
         6: putfield      #19                 // Field pos:I
         9: aload_1
        10: invokestatic  #25                 // Method coursier/util/shaded/org/jsoup/helper/Validate.notNull:(Ljava/lang/Object;)V
        13: aload_0
        14: aload_1
        15: putfield      #27                 // Field queue:Ljava/lang/String;
        18: return
      LineNumberTable:
        line 21: 0
        line 13: 4
        line 22: 9
        line 23: 13
        line 24: 18
      LocalVariableTable:
        Start  Length  Slot  Name   Signature
            0      19     0  this   Lcoursier/util/shaded/org/jsoup/parser/TokenQueue;
            0      19     1  data   Ljava/lang/String;

  public boolean isEmpty();
    descriptor: ()Z
    flags: (0x0001) ACC_PUBLIC
    Code:
      stack=1, locals=1, args_size=1
         0: aload_0
         1: invokespecial #36                 // Method remainingLength:()I
         4: ifne          11
         7: iconst_1
         8: goto          12
        11: iconst_0
        12: ireturn
      StackMapTable: number_of_entries = 2
        frame_type = 11 /* same */
        frame_type = 64 /* same_locals_1_stack_item */
          stack = [ int ]
      LineNumberTable:
        line 31: 0
      LocalVariableTable:
        Start  Length  Slot  Name   Signature
            0      13     0  this   Lcoursier/util/shaded/org/jsoup/parser/TokenQueue;

  private int remainingLength();
    descriptor: ()I
    flags: (0x0002) ACC_PRIVATE
    Code:
      stack=2, locals=1, args_size=1
         0: aload_0
         1: getfield      #27                 // Field queue:Ljava/lang/String;
         4: invokevirtual #41                 // Method java/lang/String.length:()I
         7: aload_0
         8: getfield      #19                 // Field pos:I
        11: isub
        12: ireturn
      LineNumberTable:
        line 35: 0
      LocalVariableTable:
        Start  Length  Slot  Name   Signature
            0      13     0  this   Lcoursier/util/shaded/org/jsoup/parser/TokenQueue;

  public char peek();
    descriptor: ()C
    flags: (0x0001) ACC_PUBLIC
    Code:
      stack=2, locals=1, args_size=1
         0: aload_0
         1: invokevirtual #45                 // Method isEmpty:()Z
         4: ifeq          11
         7: iconst_0
         8: goto          22
        11: aload_0
        12: getfield      #27                 // Field queue:Ljava/lang/String;
        15: aload_0
        16: getfield      #19                 // Field pos:I
        19: invokevirtual #49                 // Method java/lang/String.charAt:(I)C
        22: ireturn
      StackMapTable: number_of_entries = 2
        frame_type = 11 /* same */
        frame_type = 74 /* same_locals_1_stack_item */
          stack = [ int ]
      LineNumberTable:
        line 43: 0
      LocalVariableTable:
        Start  Length  Slot  Name   Signature
            0      23     0  this   Lcoursier/util/shaded/org/jsoup/parser/TokenQueue;

  public void addFirst(java.lang.Character);
    descriptor: (Ljava/lang/Character;)V
    flags: (0x0001) ACC_PUBLIC
    Code:
      stack=2, locals=2, args_size=2
         0: aload_0
         1: aload_1
         2: invokevirtual #57                 // Method java/lang/Character.toString:()Ljava/lang/String;
         5: invokevirtual #59                 // Method addFirst:(Ljava/lang/String;)V
         8: return
      LineNumberTable:
        line 51: 0
        line 52: 8
      LocalVariableTable:
        Start  Length  Slot  Name   Signature
            0       9     0  this   Lcoursier/util/shaded/org/jsoup/parser/TokenQueue;
            0       9     1     c   Ljava/lang/Character;

  public void addFirst(java.lang.String);
    descriptor: (Ljava/lang/String;)V
    flags: (0x0001) ACC_PUBLIC
    Code:
      stack=4, locals=2, args_size=2
         0: aload_0
         1: new           #63                 // class java/lang/StringBuilder
         4: dup
         5: invokespecial #64                 // Method java/lang/StringBuilder."<init>":()V
         8: aload_1
         9: invokevirtual #68                 // Method java/lang/StringBuilder.append:(Ljava/lang/String;)Ljava/lang/StringBuilder;
        12: aload_0
        13: getfield      #27                 // Field queue:Ljava/lang/String;
        16: aload_0
        17: getfield      #19                 // Field pos:I
        20: invokevirtual #72                 // Method java/lang/String.substring:(I)Ljava/lang/String;
        23: invokevirtual #68                 // Method java/lang/StringBuilder.append:(Ljava/lang/String;)Ljava/lang/StringBuilder;
        26: invokevirtual #73                 // Method java/lang/StringBuilder.toString:()Ljava/lang/String;
        29: putfield      #27                 // Field queue:Ljava/lang/String;
        32: aload_0
        33: iconst_0
        34: putfield      #19                 // Field pos:I
        37: return
      LineNumberTable:
        line 60: 0
        line 61: 32
        line 62: 37
      LocalVariableTable:
        Start  Length  Slot  Name   Signature
            0      38     0  this   Lcoursier/util/shaded/org/jsoup/parser/TokenQueue;
            0      38     1   seq   Ljava/lang/String;

  public boolean matches(java.lang.String);
    descriptor: (Ljava/lang/String;)Z
    flags: (0x0001) ACC_PUBLIC
    Code:
      stack=6, locals=2, args_size=2
         0: aload_0
         1: getfield      #27                 // Field queue:Ljava/lang/String;
         4: iconst_1
         5: aload_0
         6: getfield      #19                 // Field pos:I
         9: aload_1
        10: iconst_0
        11: aload_1
        12: invokevirtual #41                 // Method java/lang/String.length:()I
        15: invokevirtual #80                 // Method java/lang/String.regionMatches:(ZILjava/lang/String;II)Z
        18: ireturn
      LineNumberTable:
        line 70: 0
      LocalVariableTable:
        Start  Length  Slot  Name   Signature
            0      19     0  this   Lcoursier/util/shaded/org/jsoup/parser/TokenQueue;
            0      19     1   seq   Ljava/lang/String;

  public boolean matchesCS(java.lang.String);
    descriptor: (Ljava/lang/String;)Z
    flags: (0x0001) ACC_PUBLIC
    Code:
      stack=3, locals=2, args_size=2
         0: aload_0
         1: getfield      #27                 // Field queue:Ljava/lang/String;
         4: aload_1
         5: aload_0
         6: getfield      #19                 // Field pos:I
         9: invokevirtual #85                 // Method java/lang/String.startsWith:(Ljava/lang/String;I)Z
        12: ireturn
      LineNumberTable:
        line 79: 0
      LocalVariableTable:
        Start  Length  Slot  Name   Signature
            0      13     0  this   Lcoursier/util/shaded/org/jsoup/parser/TokenQueue;
            0      13     1   seq   Ljava/lang/String;

  public boolean matchesAny(java.lang.String...);
    descriptor: ([Ljava/lang/String;)Z
    flags: (0x0081) ACC_PUBLIC, ACC_VARARGS
    Code:
      stack=2, locals=6, args_size=2
         0: aload_1
         1: astore_2
         2: aload_2
         3: arraylength
         4: istore_3
         5: iconst_0
         6: istore        4
         8: iload         4
        10: iload_3
        11: if_icmpge     37
        14: aload_2
        15: iload         4
        17: aaload
        18: astore        5
        20: aload_0
        21: aload         5
        23: invokevirtual #91                 // Method matches:(Ljava/lang/String;)Z
        26: ifeq          31
        29: iconst_1
        30: ireturn
        31: iinc          4, 1
        34: goto          8
        37: iconst_0
        38: ireturn
      StackMapTable: number_of_entries = 3
        frame_type = 254 /* append */
          offset_delta = 8
          locals = [ class "[Ljava/lang/String;", int, int ]
        frame_type = 22 /* same */
        frame_type = 248 /* chop */
          offset_delta = 5
      LineNumberTable:
        line 89: 0
        line 90: 20
        line 91: 29
        line 89: 31
        line 93: 37
      LocalVariableTable:
        Start  Length  Slot  Name   Signature
           20      11     5     s   Ljava/lang/String;
            0      39     0  this   Lcoursier/util/shaded/org/jsoup/parser/TokenQueue;
            0      39     1   seq   [Ljava/lang/String;

  public boolean matchesAny(char...);
    descriptor: ([C)Z
    flags: (0x0081) ACC_PUBLIC, ACC_VARARGS
    Code:
      stack=2, locals=6, args_size=2
         0: aload_0
         1: invokevirtual #45                 // Method isEmpty:()Z
         4: ifeq          9
         7: iconst_0
         8: ireturn
         9: aload_1
        10: astore_2
        11: aload_2
        12: arraylength
        13: istore_3
        14: iconst_0
        15: istore        4
        17: iload         4
        19: iload_3
        20: if_icmpge     53
        23: aload_2
        24: iload         4
        26: caload
        27: istore        5
        29: aload_0
        30: getfield      #27                 // Field queue:Ljava/lang/String;
        33: aload_0
        34: getfield      #19                 // Field pos:I
        37: invokevirtual #49                 // Method java/lang/String.charAt:(I)C
        40: iload         5
        42: if_icmpne     47
        45: iconst_1
        46: ireturn
        47: iinc          4, 1
        50: goto          17
        53: iconst_0
        54: ireturn
      StackMapTable: number_of_entries = 4
        frame_type = 9 /* same */
        frame_type = 254 /* append */
          offset_delta = 7
          locals = [ class "[C", int, int ]
        frame_type = 29 /* same */
        frame_type = 248 /* chop */
          offset_delta = 5
      LineNumberTable:
        line 97: 0
        line 98: 7
        line 100: 9
        line 101: 29
        line 102: 45
        line 100: 47
        line 104: 53
      LocalVariableTable:
        Start  Length  Slot  Name   Signature
           29      18     5     c   C
            0      55     0  this   Lcoursier/util/shaded/org/jsoup/parser/TokenQueue;
            0      55     1   seq   [C

  public boolean matchesStartTag();
    descriptor: ()Z
    flags: (0x0001) ACC_PUBLIC
    Code:
      stack=3, locals=1, args_size=1
         0: aload_0
         1: invokespecial #36                 // Method remainingLength:()I
         4: iconst_2
         5: if_icmplt     47
         8: aload_0
         9: getfield      #27                 // Field queue:Ljava/lang/String;
        12: aload_0
        13: getfield      #19                 // Field pos:I
        16: invokevirtual #49                 // Method java/lang/String.charAt:(I)C
        19: bipush        60
        21: if_icmpne     47
        24: aload_0
        25: getfield      #27                 // Field queue:Ljava/lang/String;
        28: aload_0
        29: getfield      #19                 // Field pos:I
        32: iconst_1
        33: iadd
        34: invokevirtual #49                 // Method java/lang/String.charAt:(I)C
        37: invokestatic  #100                // Method java/lang/Character.isLetter:(C)Z
        40: ifeq          47
        43: iconst_1
        44: goto          48
        47: iconst_0
        48: ireturn
      StackMapTable: number_of_entries = 2
        frame_type = 47 /* same */
        frame_type = 64 /* same_locals_1_stack_item */
          stack = [ int ]
      LineNumberTable:
        line 109: 0
      LocalVariableTable:
        Start  Length  Slot  Name   Signature
            0      49     0  this   Lcoursier/util/shaded/org/jsoup/parser/TokenQueue;

  public boolean matchChomp(java.lang.String);
    descriptor: (Ljava/lang/String;)Z
    flags: (0x0001) ACC_PUBLIC
    Code:
      stack=3, locals=2, args_size=2
         0: aload_0
         1: aload_1
         2: invokevirtual #91                 // Method matches:(Ljava/lang/String;)Z
         5: ifeq          23
         8: aload_0
         9: dup
        10: getfield      #19                 // Field pos:I
        13: aload_1
        14: invokevirtual #41                 // Method java/lang/String.length:()I
        17: iadd
        18: putfield      #19                 // Field pos:I
        21: iconst_1
        22: ireturn
        23: iconst_0
        24: ireturn
      StackMapTable: number_of_entries = 1
        frame_type = 23 /* same */
      LineNumberTable:
        line 119: 0
        line 120: 8
        line 121: 21
        line 123: 23
      LocalVariableTable:
        Start  Length  Slot  Name   Signature
            0      25     0  this   Lcoursier/util/shaded/org/jsoup/parser/TokenQueue;
            0      25     1   seq   Ljava/lang/String;

  public boolean matchesWhitespace();
    descriptor: ()Z
    flags: (0x0001) ACC_PUBLIC
    Code:
      stack=2, locals=1, args_size=1
         0: aload_0
         1: invokevirtual #45                 // Method isEmpty:()Z
         4: ifne          28
         7: aload_0
         8: getfield      #27                 // Field queue:Ljava/lang/String;
        11: aload_0
        12: getfield      #19                 // Field pos:I
        15: invokevirtual #49                 // Method java/lang/String.charAt:(I)C
        18: invokestatic  #108                // Method coursier/util/shaded/org/jsoup/internal/StringUtil.isWhitespace:(I)Z
        21: ifeq          28
        24: iconst_1
        25: goto          29
        28: iconst_0
        29: ireturn
      StackMapTable: number_of_entries = 2
        frame_type = 28 /* same */
        frame_type = 64 /* same_locals_1_stack_item */
          stack = [ int ]
      LineNumberTable:
        line 132: 0
      LocalVariableTable:
        Start  Length  Slot  Name   Signature
            0      30     0  this   Lcoursier/util/shaded/org/jsoup/parser/TokenQueue;

  public boolean matchesWord();
    descriptor: ()Z
    flags: (0x0001) ACC_PUBLIC
    Code:
      stack=2, locals=1, args_size=1
         0: aload_0
         1: invokevirtual #45                 // Method isEmpty:()Z
         4: ifne          28
         7: aload_0
         8: getfield      #27                 // Field queue:Ljava/lang/String;
        11: aload_0
        12: getfield      #19                 // Field pos:I
        15: invokevirtual #49                 // Method java/lang/String.charAt:(I)C
        18: invokestatic  #112                // Method java/lang/Character.isLetterOrDigit:(C)Z
        21: ifeq          28
        24: iconst_1
        25: goto          29
        28: iconst_0
        29: ireturn
      StackMapTable: number_of_entries = 2
        frame_type = 28 /* same */
        frame_type = 64 /* same_locals_1_stack_item */
          stack = [ int ]
      LineNumberTable:
        line 140: 0
      LocalVariableTable:
        Start  Length  Slot  Name   Signature
            0      30     0  this   Lcoursier/util/shaded/org/jsoup/parser/TokenQueue;

  public void advance();
    descriptor: ()V
    flags: (0x0001) ACC_PUBLIC
    Code:
      stack=3, locals=1, args_size=1
         0: aload_0
         1: invokevirtual #45                 // Method isEmpty:()Z
         4: ifne          17
         7: aload_0
         8: dup
         9: getfield      #19                 // Field pos:I
        12: iconst_1
        13: iadd
        14: putfield      #19                 // Field pos:I
        17: return
      StackMapTable: number_of_entries = 1
        frame_type = 17 /* same */
      LineNumberTable:
        line 147: 0
        line 148: 17
      LocalVariableTable:
        Start  Length  Slot  Name   Signature
            0      18     0  this   Lcoursier/util/shaded/org/jsoup/parser/TokenQueue;

  public char consume();
    descriptor: ()C
    flags: (0x0001) ACC_PUBLIC
    Code:
      stack=5, locals=1, args_size=1
         0: aload_0
         1: getfield      #27                 // Field queue:Ljava/lang/String;
         4: aload_0
         5: dup
         6: getfield      #19                 // Field pos:I
         9: dup_x1
        10: iconst_1
        11: iadd
        12: putfield      #19                 // Field pos:I
        15: invokevirtual #49                 // Method java/lang/String.charAt:(I)C
        18: ireturn
      LineNumberTable:
        line 155: 0
      LocalVariableTable:
        Start  Length  Slot  Name   Signature
            0      19     0  this   Lcoursier/util/shaded/org/jsoup/parser/TokenQueue;

  public void consume(java.lang.String);
    descriptor: (Ljava/lang/String;)V
    flags: (0x0001) ACC_PUBLIC
    Code:
      stack=3, locals=3, args_size=2
         0: aload_0
         1: aload_1
         2: invokevirtual #91                 // Method matches:(Ljava/lang/String;)Z
         5: ifne          18
         8: new           #116                // class java/lang/IllegalStateException
        11: dup
        12: ldc           #118                // String Queue did not match expected sequence
        14: invokespecial #120                // Method java/lang/IllegalStateException."<init>":(Ljava/lang/String;)V
        17: athrow
        18: aload_1
        19: invokevirtual #41                 // Method java/lang/String.length:()I
        22: istore_2
        23: iload_2
        24: aload_0
        25: invokespecial #36                 // Method remainingLength:()I
        28: if_icmple     41
        31: new           #116                // class java/lang/IllegalStateException
        34: dup
        35: ldc           #122                // String Queue not long enough to consume sequence
        37: invokespecial #120                // Method java/lang/IllegalStateException."<init>":(Ljava/lang/String;)V
        40: athrow
        41: aload_0
        42: dup
        43: getfield      #19                 // Field pos:I
        46: iload_2
        47: iadd
        48: putfield      #19                 // Field pos:I
        51: return
      StackMapTable: number_of_entries = 2
        frame_type = 18 /* same */
        frame_type = 252 /* append */
          offset_delta = 22
          locals = [ int ]
      LineNumberTable:
        line 166: 0
        line 167: 8
        line 168: 18
        line 169: 23
        line 170: 31
        line 172: 41
        line 173: 51
      LocalVariableTable:
        Start  Length  Slot  Name   Signature
            0      52     0  this   Lcoursier/util/shaded/org/jsoup/parser/TokenQueue;
            0      52     1   seq   Ljava/lang/String;
           23      29     2   len   I

  public java.lang.String consumeTo(java.lang.String);
    descriptor: (Ljava/lang/String;)Ljava/lang/String;
    flags: (0x0001) ACC_PUBLIC
    Code:
      stack=3, locals=4, args_size=2
         0: aload_0
         1: getfield      #27                 // Field queue:Ljava/lang/String;
         4: aload_1
         5: aload_0
         6: getfield      #19                 // Field pos:I
         9: invokevirtual #129                // Method java/lang/String.indexOf:(Ljava/lang/String;I)I
        12: istore_2
        13: iload_2
        14: iconst_m1
        15: if_icmpeq     46
        18: aload_0
        19: getfield      #27                 // Field queue:Ljava/lang/String;
        22: aload_0
        23: getfield      #19                 // Field pos:I
        26: iload_2
        27: invokevirtual #132                // Method java/lang/String.substring:(II)Ljava/lang/String;
        30: astore_3
        31: aload_0
        32: dup
        33: getfield      #19                 // Field pos:I
        36: aload_3
        37: invokevirtual #41                 // Method java/lang/String.length:()I
        40: iadd
        41: putfield      #19                 // Field pos:I
        44: aload_3
        45: areturn
        46: aload_0
        47: invokevirtual #135                // Method remainder:()Ljava/lang/String;
        50: areturn
      StackMapTable: number_of_entries = 1
        frame_type = 252 /* append */
          offset_delta = 46
          locals = [ int ]
      LineNumberTable:
        line 181: 0
        line 182: 13
        line 183: 18
        line 184: 31
        line 185: 44
        line 187: 46
      LocalVariableTable:
        Start  Length  Slot  Name   Signature
           31      15     3 consumed   Ljava/lang/String;
            0      51     0  this   Lcoursier/util/shaded/org/jsoup/parser/TokenQueue;
            0      51     1   seq   Ljava/lang/String;
           13      38     2 offset   I

  public java.lang.String consumeToIgnoreCase(java.lang.String);
    descriptor: (Ljava/lang/String;)Ljava/lang/String;
    flags: (0x0001) ACC_PUBLIC
    Code:
      stack=3, locals=6, args_size=2
         0: aload_0
         1: getfield      #19                 // Field pos:I
         4: istore_2
         5: aload_1
         6: iconst_0
         7: iconst_1
         8: invokevirtual #132                // Method java/lang/String.substring:(II)Ljava/lang/String;
        11: astore_3
        12: aload_3
        13: invokevirtual #141                // Method java/lang/String.toLowerCase:()Ljava/lang/String;
        16: aload_3
        17: invokevirtual #144                // Method java/lang/String.toUpperCase:()Ljava/lang/String;
        20: invokevirtual #148                // Method java/lang/String.equals:(Ljava/lang/Object;)Z
        23: istore        4
        25: aload_0
        26: invokevirtual #45                 // Method isEmpty:()Z
        29: ifne          131
        32: aload_0
        33: aload_1
        34: invokevirtual #91                 // Method matches:(Ljava/lang/String;)Z
        37: ifeq          43
        40: goto          131
        43: iload         4
        45: ifeq          118
        48: aload_0
        49: getfield      #27                 // Field queue:Ljava/lang/String;
        52: aload_3
        53: aload_0
        54: getfield      #19                 // Field pos:I
        57: invokevirtual #129                // Method java/lang/String.indexOf:(Ljava/lang/String;I)I
        60: aload_0
        61: getfield      #19                 // Field pos:I
        64: isub
        65: istore        5
        67: iload         5
        69: ifne          85
        72: aload_0
        73: dup
        74: getfield      #19                 // Field pos:I
        77: iconst_1
        78: iadd
        79: putfield      #19                 // Field pos:I
        82: goto          115
        85: iload         5
        87: ifge          104
        90: aload_0
        91: aload_0
        92: getfield      #27                 // Field queue:Ljava/lang/String;
        95: invokevirtual #41                 // Method java/lang/String.length:()I
        98: putfield      #19                 // Field pos:I
       101: goto          115
       104: aload_0
       105: dup
       106: getfield      #19                 // Field pos:I
       109: iload         5
       111: iadd
       112: putfield      #19                 // Field pos:I
       115: goto          25
       118: aload_0
       119: dup
       120: getfield      #19                 // Field pos:I
       123: iconst_1
       124: iadd
       125: putfield      #19                 // Field pos:I
       128: goto          25
       131: aload_0
       132: getfield      #27                 // Field queue:Ljava/lang/String;
       135: iload_2
       136: aload_0
       137: getfield      #19                 // Field pos:I
       140: invokevirtual #132                // Method java/lang/String.substring:(II)Ljava/lang/String;
       143: areturn
      StackMapTable: number_of_entries = 7
        frame_type = 254 /* append */
          offset_delta = 25
          locals = [ int, class java/lang/String, int ]
        frame_type = 17 /* same */
        frame_type = 252 /* append */
          offset_delta = 41
          locals = [ int ]
        frame_type = 18 /* same */
        frame_type = 250 /* chop */
          offset_delta = 10
        frame_type = 2 /* same */
        frame_type = 12 /* same */
      LineNumberTable:
        line 192: 0
        line 193: 5
        line 194: 12
        line 195: 25
        line 196: 32
        line 197: 40
        line 199: 43
        line 200: 48
        line 201: 67
        line 202: 72
        line 203: 85
        line 204: 90
        line 206: 104
        line 207: 115
        line 209: 118
        line 212: 131
      LocalVariableTable:
        Start  Length  Slot  Name   Signature
           67      48     5  skip   I
            0     144     0  this   Lcoursier/util/shaded/org/jsoup/parser/TokenQueue;
            0     144     1   seq   Ljava/lang/String;
            5     139     2 start   I
           12     132     3 first   Ljava/lang/String;
           25     119     4 canScan   Z

  public java.lang.String consumeToAny(java.lang.String...);
    descriptor: ([Ljava/lang/String;)Ljava/lang/String;
    flags: (0x0081) ACC_PUBLIC, ACC_VARARGS
    Code:
      stack=3, locals=3, args_size=2
         0: aload_0
         1: getfield      #19                 // Field pos:I
         4: istore_2
         5: aload_0
         6: invokevirtual #45                 // Method isEmpty:()Z
         9: ifne          33
        12: aload_0
        13: aload_1
        14: invokevirtual #157                // Method matchesAny:([Ljava/lang/String;)Z
        17: ifne          33
        20: aload_0
        21: dup
        22: getfield      #19                 // Field pos:I
        25: iconst_1
        26: iadd
        27: putfield      #19                 // Field pos:I
        30: goto          5
        33: aload_0
        34: getfield      #27                 // Field queue:Ljava/lang/String;
        37: iload_2
        38: aload_0
        39: getfield      #19                 // Field pos:I
        42: invokevirtual #132                // Method java/lang/String.substring:(II)Ljava/lang/String;
        45: areturn
      StackMapTable: number_of_entries = 2
        frame_type = 252 /* append */
          offset_delta = 5
          locals = [ int ]
        frame_type = 27 /* same */
      LineNumberTable:
        line 223: 0
        line 224: 5
        line 225: 20
        line 228: 33
      LocalVariableTable:
        Start  Length  Slot  Name   Signature
            0      46     0  this   Lcoursier/util/shaded/org/jsoup/parser/TokenQueue;
            0      46     1   seq   [Ljava/lang/String;
            5      41     2 start   I

  public java.lang.String chompTo(java.lang.String);
    descriptor: (Ljava/lang/String;)Ljava/lang/String;
    flags: (0x0001) ACC_PUBLIC
    Code:
      stack=2, locals=3, args_size=2
         0: aload_0
         1: aload_1
         2: invokevirtual #160                // Method consumeTo:(Ljava/lang/String;)Ljava/lang/String;
         5: astore_2
         6: aload_0
         7: aload_1
         8: invokevirtual #162                // Method matchChomp:(Ljava/lang/String;)Z
        11: pop
        12: aload_2
        13: areturn
      LineNumberTable:
        line 240: 0
        line 241: 6
        line 242: 12
      LocalVariableTable:
        Start  Length  Slot  Name   Signature
            0      14     0  this   Lcoursier/util/shaded/org/jsoup/parser/TokenQueue;
            0      14     1   seq   Ljava/lang/String;
            6       8     2  data   Ljava/lang/String;

  public java.lang.String chompToIgnoreCase(java.lang.String);
    descriptor: (Ljava/lang/String;)Ljava/lang/String;
    flags: (0x0001) ACC_PUBLIC
    Code:
      stack=2, locals=3, args_size=2
         0: aload_0
         1: aload_1
         2: invokevirtual #165                // Method consumeToIgnoreCase:(Ljava/lang/String;)Ljava/lang/String;
         5: astore_2
         6: aload_0
         7: aload_1
         8: invokevirtual #162                // Method matchChomp:(Ljava/lang/String;)Z
        11: pop
        12: aload_2
        13: areturn
      LineNumberTable:
        line 246: 0
        line 247: 6
        line 248: 12
      LocalVariableTable:
        Start  Length  Slot  Name   Signature
            0      14     0  this   Lcoursier/util/shaded/org/jsoup/parser/TokenQueue;
            0      14     1   seq   Ljava/lang/String;
            6       8     2  data   Ljava/lang/String;

  public java.lang.String chompBalanced(char, char);
    descriptor: (CC)Ljava/lang/String;
    flags: (0x0001) ACC_PUBLIC
    Code:
      stack=3, locals=10, args_size=3
         0: iconst_m1
         1: istore_3
         2: iconst_m1
         3: istore        4
         5: iconst_0
         6: istore        5
         8: iconst_0
         9: istore        6
        11: iconst_0
        12: istore        7
        14: iconst_0
        15: istore        8
        17: aload_0
        18: invokevirtual #45                 // Method isEmpty:()Z
        21: ifeq          27
        24: goto          177
        27: aload_0
        28: invokevirtual #169                // Method consume:()C
        31: istore        9
        33: iload         6
        35: ifeq          45
        38: iload         6
        40: bipush        92
        42: if_icmpeq     152
        45: iload         9
        47: bipush        39
        49: if_icmpne     78
        52: iload         9
        54: iload_1
        55: if_icmpeq     78
        58: iload         8
        60: ifne          78
        63: iload         7
        65: ifne          72
        68: iconst_1
        69: goto          73
        72: iconst_0
        73: istore        7
        75: goto          108
        78: iload         9
        80: bipush        34
        82: if_icmpne     108
        85: iload         9
        87: iload_1
        88: if_icmpeq     108
        91: iload         7
        93: ifne          108
        96: iload         8
        98: ifne          105
       101: iconst_1
       102: goto          106
       105: iconst_0
       106: istore        8
       108: iload         7
       110: ifne          172
       113: iload         8
       115: ifeq          121
       118: goto          172
       121: iload         9
       123: iload_1
       124: if_icmpne     143
       127: iinc          5, 1
       130: iload_3
       131: iconst_m1
       132: if_icmpne     152
       135: aload_0
       136: getfield      #19                 // Field pos:I
       139: istore_3
       140: goto          152
       143: iload         9
       145: iload_2
       146: if_icmpne     152
       149: iinc          5, -1
       152: iload         5
       154: ifle          168
       157: iload         6
       159: ifeq          168
       162: aload_0
       163: getfield      #19                 // Field pos:I
       166: istore        4
       168: iload         9
       170: istore        6
       172: iload         5
       174: ifgt          17
       177: iload         4
       179: iflt          195
       182: aload_0
       183: getfield      #27                 // Field queue:Ljava/lang/String;
       186: iload_3
       187: iload         4
       189: invokevirtual #132                // Method java/lang/String.substring:(II)Ljava/lang/String;
       192: goto          197
       195: ldc           #171                // String
       197: astore        9
       199: iload         5
       201: ifle          232
       204: new           #63                 // class java/lang/StringBuilder
       207: dup
       208: invokespecial #64                 // Method java/lang/StringBuilder."<init>":()V
       211: ldc           #173                // String Did not find balanced marker at \'
       213: invokevirtual #68                 // Method java/lang/StringBuilder.append:(Ljava/lang/String;)Ljava/lang/StringBuilder;
       216: aload         9
       218: invokevirtual #68                 // Method java/lang/StringBuilder.append:(Ljava/lang/String;)Ljava/lang/StringBuilder;
       221: ldc           #175                // String \'
       223: invokevirtual #68                 // Method java/lang/StringBuilder.append:(Ljava/lang/String;)Ljava/lang/StringBuilder;
       226: invokevirtual #73                 // Method java/lang/StringBuilder.toString:()Ljava/lang/String;
       229: invokestatic  #178                // Method coursier/util/shaded/org/jsoup/helper/Validate.fail:(Ljava/lang/String;)V
       232: aload         9
       234: areturn
      StackMapTable: number_of_entries = 18
        frame_type = 255 /* full_frame */
          offset_delta = 17
          locals = [ class coursier/util/shaded/org/jsoup/parser/TokenQueue, int, int, int, int, int, int, int, int ]
          stack = []
        frame_type = 9 /* same */
        frame_type = 252 /* append */
          offset_delta = 17
          locals = [ int ]
        frame_type = 26 /* same */
        frame_type = 64 /* same_locals_1_stack_item */
          stack = [ int ]
        frame_type = 4 /* same */
        frame_type = 26 /* same */
        frame_type = 64 /* same_locals_1_stack_item */
          stack = [ int ]
        frame_type = 1 /* same */
        frame_type = 12 /* same */
        frame_type = 21 /* same */
        frame_type = 8 /* same */
        frame_type = 15 /* same */
        frame_type = 250 /* chop */
          offset_delta = 3
        frame_type = 4 /* same */
        frame_type = 17 /* same */
        frame_type = 65 /* same_locals_1_stack_item */
          stack = [ class java/lang/String ]
        frame_type = 252 /* append */
          offset_delta = 34
          locals = [ class java/lang/String ]
      LineNumberTable:
        line 261: 0
        line 262: 2
        line 263: 5
        line 264: 8
        line 265: 11
        line 266: 14
        line 269: 17
        line 270: 27
        line 271: 33
        line 272: 45
        line 273: 63
        line 274: 78
        line 275: 96
        line 276: 108
        line 277: 118
        line 279: 121
        line 280: 127
        line 281: 130
        line 282: 135
        line 284: 143
        line 285: 149
        line 288: 152
        line 289: 162
        line 290: 168
        line 291: 172
        line 292: 177
        line 293: 199
        line 294: 204
        line 296: 232
      LocalVariableTable:
        Start  Length  Slot  Name   Signature
           33     139     9     c   C
            0     235     0  this   Lcoursier/util/shaded/org/jsoup/parser/TokenQueue;
            0     235     1  open   C
            0     235     2 close   C
            2     233     3 start   I
            5     230     4   end   I
            8     227     5 depth   I
           11     224     6  last   C
           14     221     7 inSingleQuote   Z
           17     218     8 inDoubleQuote   Z
          199      36     9   out   Ljava/lang/String;

  public static java.lang.String unescape(java.lang.String);
    descriptor: (Ljava/lang/String;)Ljava/lang/String;
    flags: (0x0009) ACC_PUBLIC, ACC_STATIC
    Code:
      stack=2, locals=7, args_size=1
         0: invokestatic  #191                // Method coursier/util/shaded/org/jsoup/internal/StringUtil.borrowBuilder:()Ljava/lang/StringBuilder;
         3: astore_1
         4: iconst_0
         5: istore_2
         6: aload_0
         7: invokevirtual #195                // Method java/lang/String.toCharArray:()[C
        10: astore_3
        11: aload_3
        12: arraylength
        13: istore        4
        15: iconst_0
        16: istore        5
        18: iload         5
        20: iload         4
        22: if_icmpge     74
        25: aload_3
        26: iload         5
        28: caload
        29: istore        6
        31: iload         6
        33: bipush        92
        35: if_icmpne     58
        38: iload_2
        39: ifeq          65
        42: iload_2
        43: bipush        92
        45: if_icmpne     65
        48: aload_1
        49: iload         6
        51: invokevirtual #198                // Method java/lang/StringBuilder.append:(C)Ljava/lang/StringBuilder;
        54: pop
        55: goto          65
        58: aload_1
        59: iload         6
        61: invokevirtual #198                // Method java/lang/StringBuilder.append:(C)Ljava/lang/StringBuilder;
        64: pop
        65: iload         6
        67: istore_2
        68: iinc          5, 1
        71: goto          18
        74: aload_1
        75: invokestatic  #202                // Method coursier/util/shaded/org/jsoup/internal/StringUtil.releaseBuilder:(Ljava/lang/StringBuilder;)Ljava/lang/String;
        78: areturn
      StackMapTable: number_of_entries = 4
        frame_type = 255 /* full_frame */
          offset_delta = 18
          locals = [ class java/lang/String, class java/lang/StringBuilder, int, class "[C", int, int ]
          stack = []
        frame_type = 252 /* append */
          offset_delta = 39
          locals = [ int ]
        frame_type = 6 /* same */
        frame_type = 255 /* full_frame */
          offset_delta = 8
          locals = [ class java/lang/String, class java/lang/StringBuilder, int ]
          stack = []
      LineNumberTable:
        line 305: 0
        line 306: 4
        line 307: 6
        line 308: 31
        line 309: 38
        line 310: 48
        line 313: 58
        line 314: 65
        line 307: 68
        line 316: 74
      LocalVariableTable:
        Start  Length  Slot  Name   Signature
           31      37     6     c   C
            0      79     0    in   Ljava/lang/String;
            4      75     1   out   Ljava/lang/StringBuilder;
            6      73     2  last   C

  public boolean consumeWhitespace();
    descriptor: ()Z
    flags: (0x0001) ACC_PUBLIC
    Code:
      stack=3, locals=2, args_size=1
         0: iconst_0
         1: istore_1
         2: aload_0
         3: invokevirtual #207                // Method matchesWhitespace:()Z
         6: ifeq          24
         9: aload_0
        10: dup
        11: getfield      #19                 // Field pos:I
        14: iconst_1
        15: iadd
        16: putfield      #19                 // Field pos:I
        19: iconst_1
        20: istore_1
        21: goto          2
        24: iload_1
        25: ireturn
      StackMapTable: number_of_entries = 2
        frame_type = 252 /* append */
          offset_delta = 2
          locals = [ int ]
        frame_type = 21 /* same */
      LineNumberTable:
        line 324: 0
        line 325: 2
        line 326: 9
        line 327: 19
        line 329: 24
      LocalVariableTable:
        Start  Length  Slot  Name   Signature
            0      26     0  this   Lcoursier/util/shaded/org/jsoup/parser/TokenQueue;
            2      24     1  seen   Z

  public java.lang.String consumeWord();
    descriptor: ()Ljava/lang/String;
    flags: (0x0001) ACC_PUBLIC
    Code:
      stack=3, locals=2, args_size=1
         0: aload_0
         1: getfield      #19                 // Field pos:I
         4: istore_1
         5: aload_0
         6: invokevirtual #211                // Method matchesWord:()Z
         9: ifeq          25
        12: aload_0
        13: dup
        14: getfield      #19                 // Field pos:I
        17: iconst_1
        18: iadd
        19: putfield      #19                 // Field pos:I
        22: goto          5
        25: aload_0
        26: getfield      #27                 // Field queue:Ljava/lang/String;
        29: iload_1
        30: aload_0
        31: getfield      #19                 // Field pos:I
        34: invokevirtual #132                // Method java/lang/String.substring:(II)Ljava/lang/String;
        37: areturn
      StackMapTable: number_of_entries = 2
        frame_type = 252 /* append */
          offset_delta = 5
          locals = [ int ]
        frame_type = 19 /* same */
      LineNumberTable:
        line 337: 0
        line 338: 5
        line 339: 12
        line 340: 25
      LocalVariableTable:
        Start  Length  Slot  Name   Signature
            0      38     0  this   Lcoursier/util/shaded/org/jsoup/parser/TokenQueue;
            5      33     1 start   I

  public java.lang.String consumeTagName();
    descriptor: ()Ljava/lang/String;
    flags: (0x0001) ACC_PUBLIC
    Code:
      stack=5, locals=2, args_size=1
         0: aload_0
         1: getfield      #19                 // Field pos:I
         4: istore_1
         5: aload_0
         6: invokevirtual #45                 // Method isEmpty:()Z
         9: ifne          57
        12: aload_0
        13: invokevirtual #211                // Method matchesWord:()Z
        16: ifne          44
        19: aload_0
        20: iconst_3
        21: newarray       char
        23: dup
        24: iconst_0
        25: bipush        58
        27: castore
        28: dup
        29: iconst_1
        30: bipush        95
        32: castore
        33: dup
        34: iconst_2
        35: bipush        45
        37: castore
        38: invokevirtual #214                // Method matchesAny:([C)Z
        41: ifeq          57
        44: aload_0
        45: dup
        46: getfield      #19                 // Field pos:I
        49: iconst_1
        50: iadd
        51: putfield      #19                 // Field pos:I
        54: goto          5
        57: aload_0
        58: getfield      #27                 // Field queue:Ljava/lang/String;
        61: iload_1
        62: aload_0
        63: getfield      #19                 // Field pos:I
        66: invokevirtual #132                // Method java/lang/String.substring:(II)Ljava/lang/String;
        69: areturn
      StackMapTable: number_of_entries = 3
        frame_type = 252 /* append */
          offset_delta = 5
          locals = [ int ]
        frame_type = 38 /* same */
        frame_type = 12 /* same */
      LineNumberTable:
        line 349: 0
        line 350: 5
        line 351: 44
        line 353: 57
      LocalVariableTable:
        Start  Length  Slot  Name   Signature
            0      70     0  this   Lcoursier/util/shaded/org/jsoup/parser/TokenQueue;
            5      65     1 start   I

  public java.lang.String consumeElementSelector();
    descriptor: ()Ljava/lang/String;
    flags: (0x0001) ACC_PUBLIC
    Code:
      stack=5, locals=2, args_size=1
         0: aload_0
         1: getfield      #19                 // Field pos:I
         4: istore_1
         5: aload_0
         6: invokevirtual #45                 // Method isEmpty:()Z
         9: ifne          63
        12: aload_0
        13: invokevirtual #211                // Method matchesWord:()Z
        16: ifne          50
        19: aload_0
        20: iconst_4
        21: anewarray     #38                 // class java/lang/String
        24: dup
        25: iconst_0
        26: ldc           #217                // String *|
        28: aastore
        29: dup
        30: iconst_1
        31: ldc           #219                // String |
        33: aastore
        34: dup
        35: iconst_2
        36: ldc           #221                // String _
        38: aastore
        39: dup
        40: iconst_3
        41: ldc           #223                // String -
        43: aastore
        44: invokevirtual #157                // Method matchesAny:([Ljava/lang/String;)Z
        47: ifeq          63
        50: aload_0
        51: dup
        52: getfield      #19                 // Field pos:I
        55: iconst_1
        56: iadd
        57: putfield      #19                 // Field pos:I
        60: goto          5
        63: aload_0
        64: getfield      #27                 // Field queue:Ljava/lang/String;
        67: iload_1
        68: aload_0
        69: getfield      #19                 // Field pos:I
        72: invokevirtual #132                // Method java/lang/String.substring:(II)Ljava/lang/String;
        75: areturn
      StackMapTable: number_of_entries = 3
        frame_type = 252 /* append */
          offset_delta = 5
          locals = [ int ]
        frame_type = 44 /* same */
        frame_type = 12 /* same */
      LineNumberTable:
        line 362: 0
        line 363: 5
        line 364: 50
        line 366: 63
      LocalVariableTable:
        Start  Length  Slot  Name   Signature
            0      76     0  this   Lcoursier/util/shaded/org/jsoup/parser/TokenQueue;
            5      71     1 start   I

  public java.lang.String consumeCssIdentifier();
    descriptor: ()Ljava/lang/String;
    flags: (0x0001) ACC_PUBLIC
    Code:
      stack=5, locals=2, args_size=1
         0: aload_0
         1: getfield      #19                 // Field pos:I
         4: istore_1
         5: aload_0
         6: invokevirtual #45                 // Method isEmpty:()Z
         9: ifne          52
        12: aload_0
        13: invokevirtual #211                // Method matchesWord:()Z
        16: ifne          39
        19: aload_0
        20: iconst_2
        21: newarray       char
        23: dup
        24: iconst_0
        25: bipush        45
        27: castore
        28: dup
        29: iconst_1
        30: bipush        95
        32: castore
        33: invokevirtual #214                // Method matchesAny:([C)Z
        36: ifeq          52
        39: aload_0
        40: dup
        41: getfield      #19                 // Field pos:I
        44: iconst_1
        45: iadd
        46: putfield      #19                 // Field pos:I
        49: goto          5
        52: aload_0
        53: getfield      #27                 // Field queue:Ljava/lang/String;
        56: iload_1
        57: aload_0
        58: getfield      #19                 // Field pos:I
        61: invokevirtual #132                // Method java/lang/String.substring:(II)Ljava/lang/String;
        64: areturn
      StackMapTable: number_of_entries = 3
        frame_type = 252 /* append */
          offset_delta = 5
          locals = [ int ]
        frame_type = 33 /* same */
        frame_type = 12 /* same */
      LineNumberTable:
        line 375: 0
        line 376: 5
        line 377: 39
        line 379: 52
      LocalVariableTable:
        Start  Length  Slot  Name   Signature
            0      65     0  this   Lcoursier/util/shaded/org/jsoup/parser/TokenQueue;
            5      60     1 start   I

  public java.lang.String consumeAttributeKey();
    descriptor: ()Ljava/lang/String;
    flags: (0x0001) ACC_PUBLIC
    Code:
      stack=5, locals=2, args_size=1
         0: aload_0
         1: getfield      #19                 // Field pos:I
         4: istore_1
         5: aload_0
         6: invokevirtual #45                 // Method isEmpty:()Z
         9: ifne          57
        12: aload_0
        13: invokevirtual #211                // Method matchesWord:()Z
        16: ifne          44
        19: aload_0
        20: iconst_3
        21: newarray       char
        23: dup
        24: iconst_0
        25: bipush        45
        27: castore
        28: dup
        29: iconst_1
        30: bipush        95
        32: castore
        33: dup
        34: iconst_2
        35: bipush        58
        37: castore
        38: invokevirtual #214                // Method matchesAny:([C)Z
        41: ifeq          57
        44: aload_0
        45: dup
        46: getfield      #19                 // Field pos:I
        49: iconst_1
        50: iadd
        51: putfield      #19                 // Field pos:I
        54: goto          5
        57: aload_0
        58: getfield      #27                 // Field queue:Ljava/lang/String;
        61: iload_1
        62: aload_0
        63: getfield      #19                 // Field pos:I
        66: invokevirtual #132                // Method java/lang/String.substring:(II)Ljava/lang/String;
        69: areturn
      StackMapTable: number_of_entries = 3
        frame_type = 252 /* append */
          offset_delta = 5
          locals = [ int ]
        frame_type = 38 /* same */
        frame_type = 12 /* same */
      LineNumberTable:
        line 387: 0
        line 388: 5
        line 389: 44
        line 391: 57
      LocalVariableTable:
        Start  Length  Slot  Name   Signature
            0      70     0  this   Lcoursier/util/shaded/org/jsoup/parser/TokenQueue;
            5      65     1 start   I

  public java.lang.String remainder();
    descriptor: ()Ljava/lang/String;
    flags: (0x0001) ACC_PUBLIC
    Code:
      stack=3, locals=2, args_size=1
         0: aload_0
         1: getfield      #27                 // Field queue:Ljava/lang/String;
         4: aload_0
         5: getfield      #19                 // Field pos:I
         8: aload_0
         9: getfield      #27                 // Field queue:Ljava/lang/String;
        12: invokevirtual #41                 // Method java/lang/String.length:()I
        15: invokevirtual #132                // Method java/lang/String.substring:(II)Ljava/lang/String;
        18: astore_1
        19: aload_0
        20: aload_0
        21: getfield      #27                 // Field queue:Ljava/lang/String;
        24: invokevirtual #41                 // Method java/lang/String.length:()I
        27: putfield      #19                 // Field pos:I
        30: aload_1
        31: areturn
      LineNumberTable:
        line 399: 0
        line 400: 19
        line 401: 30
      LocalVariableTable:
        Start  Length  Slot  Name   Signature
            0      32     0  this   Lcoursier/util/shaded/org/jsoup/parser/TokenQueue;
           19      13     1 remainder   Ljava/lang/String;

  public java.lang.String toString();
    descriptor: ()Ljava/lang/String;
    flags: (0x0001) ACC_PUBLIC
    Code:
      stack=2, locals=1, args_size=1
         0: aload_0
         1: getfield      #27                 // Field queue:Ljava/lang/String;
         4: aload_0
         5: getfield      #19                 // Field pos:I
         8: invokevirtual #72                 // Method java/lang/String.substring:(I)Ljava/lang/String;
        11: areturn
      LineNumberTable:
        line 406: 0
      LocalVariableTable:
        Start  Length  Slot  Name   Signature
            0      12     0  this   Lcoursier/util/shaded/org/jsoup/parser/TokenQueue;
}
SourceFile: "TokenQueue.java"
