Classfile /Users/mw/Projects/slang-braindump/.jar/jar11/assemble/slang-braindump/assemble/content/coursier/util/shaded/org/jsoup/parser/XmlTreeBuilder.class
  Last modified May 29, 2022; size 9754 bytes
  SHA-256 checksum e16dccd5646815657a864db23087eab0b73f82df8b492c36f0fb6efe7c95cd97
  Compiled from "XmlTreeBuilder.java"
public class coursier.util.shaded.org.jsoup.parser.XmlTreeBuilder extends coursier.util.shaded.org.jsoup.parser.TreeBuilder
  minor version: 0
  major version: 51
  flags: (0x0021) ACC_PUBLIC, ACC_SUPER
  this_class: #2                          // coursier/util/shaded/org/jsoup/parser/XmlTreeBuilder
  super_class: #4                         // coursier/util/shaded/org/jsoup/parser/TreeBuilder
  interfaces: 0, fields: 0, methods: 15, attributes: 2
Constant pool:
    #1 = Utf8               coursier/util/shaded/org/jsoup/parser/XmlTreeBuilder
    #2 = Class              #1            // coursier/util/shaded/org/jsoup/parser/XmlTreeBuilder
    #3 = Utf8               coursier/util/shaded/org/jsoup/parser/TreeBuilder
    #4 = Class              #3            // coursier/util/shaded/org/jsoup/parser/TreeBuilder
    #5 = Utf8               XmlTreeBuilder.java
    #6 = Utf8               coursier/util/shaded/org/jsoup/nodes/Document$OutputSettings
    #7 = Class              #6            // coursier/util/shaded/org/jsoup/nodes/Document$OutputSettings
    #8 = Utf8               coursier/util/shaded/org/jsoup/nodes/Document
    #9 = Class              #8            // coursier/util/shaded/org/jsoup/nodes/Document
   #10 = Utf8               OutputSettings
   #11 = Utf8               coursier/util/shaded/org/jsoup/nodes/Document$OutputSettings$Syntax
   #12 = Class              #11           // coursier/util/shaded/org/jsoup/nodes/Document$OutputSettings$Syntax
   #13 = Utf8               Syntax
   #14 = Utf8               coursier/util/shaded/org/jsoup/parser/XmlTreeBuilder$1
   #15 = Class              #14           // coursier/util/shaded/org/jsoup/parser/XmlTreeBuilder$1
   #16 = Utf8               coursier/util/shaded/org/jsoup/parser/Token$TokenType
   #17 = Class              #16           // coursier/util/shaded/org/jsoup/parser/Token$TokenType
   #18 = Utf8               coursier/util/shaded/org/jsoup/parser/Token
   #19 = Class              #18           // coursier/util/shaded/org/jsoup/parser/Token
   #20 = Utf8               TokenType
   #21 = Utf8               coursier/util/shaded/org/jsoup/parser/Token$StartTag
   #22 = Class              #21           // coursier/util/shaded/org/jsoup/parser/Token$StartTag
   #23 = Utf8               StartTag
   #24 = Utf8               coursier/util/shaded/org/jsoup/parser/Token$EndTag
   #25 = Class              #24           // coursier/util/shaded/org/jsoup/parser/Token$EndTag
   #26 = Utf8               EndTag
   #27 = Utf8               coursier/util/shaded/org/jsoup/parser/Token$Comment
   #28 = Class              #27           // coursier/util/shaded/org/jsoup/parser/Token$Comment
   #29 = Utf8               Comment
   #30 = Utf8               coursier/util/shaded/org/jsoup/parser/Token$Character
   #31 = Class              #30           // coursier/util/shaded/org/jsoup/parser/Token$Character
   #32 = Utf8               Character
   #33 = Utf8               coursier/util/shaded/org/jsoup/parser/Token$Doctype
   #34 = Class              #33           // coursier/util/shaded/org/jsoup/parser/Token$Doctype
   #35 = Utf8               Doctype
   #36 = Utf8               <init>
   #37 = Utf8               ()V
   #38 = NameAndType        #36:#37       // "<init>":()V
   #39 = Methodref          #4.#38        // coursier/util/shaded/org/jsoup/parser/TreeBuilder."<init>":()V
   #40 = Utf8               this
   #41 = Utf8               Lcoursier/util/shaded/org/jsoup/parser/XmlTreeBuilder;
   #42 = Utf8               defaultSettings
   #43 = Utf8               ()Lcoursier/util/shaded/org/jsoup/parser/ParseSettings;
   #44 = Utf8               coursier/util/shaded/org/jsoup/parser/ParseSettings
   #45 = Class              #44           // coursier/util/shaded/org/jsoup/parser/ParseSettings
   #46 = Utf8               preserveCase
   #47 = Utf8               Lcoursier/util/shaded/org/jsoup/parser/ParseSettings;
   #48 = NameAndType        #46:#47       // preserveCase:Lcoursier/util/shaded/org/jsoup/parser/ParseSettings;
   #49 = Fieldref           #45.#48       // coursier/util/shaded/org/jsoup/parser/ParseSettings.preserveCase:Lcoursier/util/shaded/org/jsoup/parser/ParseSettings;
   #50 = Utf8               initialiseParse
   #51 = Utf8               (Ljava/io/Reader;Ljava/lang/String;Lcoursier/util/shaded/org/jsoup/parser/Parser;)V
   #52 = NameAndType        #50:#51       // initialiseParse:(Ljava/io/Reader;Ljava/lang/String;Lcoursier/util/shaded/org/jsoup/parser/Parser;)V
   #53 = Methodref          #4.#52        // coursier/util/shaded/org/jsoup/parser/TreeBuilder.initialiseParse:(Ljava/io/Reader;Ljava/lang/String;Lcoursier/util/shaded/org/jsoup/parser/Parser;)V
   #54 = Utf8               stack
   #55 = Utf8               Ljava/util/ArrayList;
   #56 = NameAndType        #54:#55       // stack:Ljava/util/ArrayList;
   #57 = Fieldref           #2.#56        // coursier/util/shaded/org/jsoup/parser/XmlTreeBuilder.stack:Ljava/util/ArrayList;
   #58 = Utf8               doc
   #59 = Utf8               Lcoursier/util/shaded/org/jsoup/nodes/Document;
   #60 = NameAndType        #58:#59       // doc:Lcoursier/util/shaded/org/jsoup/nodes/Document;
   #61 = Fieldref           #2.#60        // coursier/util/shaded/org/jsoup/parser/XmlTreeBuilder.doc:Lcoursier/util/shaded/org/jsoup/nodes/Document;
   #62 = Utf8               java/util/ArrayList
   #63 = Class              #62           // java/util/ArrayList
   #64 = Utf8               add
   #65 = Utf8               (Ljava/lang/Object;)Z
   #66 = NameAndType        #64:#65       // add:(Ljava/lang/Object;)Z
   #67 = Methodref          #63.#66       // java/util/ArrayList.add:(Ljava/lang/Object;)Z
   #68 = Utf8               outputSettings
   #69 = Utf8               ()Lcoursier/util/shaded/org/jsoup/nodes/Document$OutputSettings;
   #70 = NameAndType        #68:#69       // outputSettings:()Lcoursier/util/shaded/org/jsoup/nodes/Document$OutputSettings;
   #71 = Methodref          #9.#70        // coursier/util/shaded/org/jsoup/nodes/Document.outputSettings:()Lcoursier/util/shaded/org/jsoup/nodes/Document$OutputSettings;
   #72 = Utf8               xml
   #73 = Utf8               Lcoursier/util/shaded/org/jsoup/nodes/Document$OutputSettings$Syntax;
   #74 = NameAndType        #72:#73       // xml:Lcoursier/util/shaded/org/jsoup/nodes/Document$OutputSettings$Syntax;
   #75 = Fieldref           #12.#74       // coursier/util/shaded/org/jsoup/nodes/Document$OutputSettings$Syntax.xml:Lcoursier/util/shaded/org/jsoup/nodes/Document$OutputSettings$Syntax;
   #76 = Utf8               syntax
   #77 = Utf8               (Lcoursier/util/shaded/org/jsoup/nodes/Document$OutputSettings$Syntax;)Lcoursier/util/shaded/org/jsoup/nodes/Document$OutputSettings;
   #78 = NameAndType        #76:#77       // syntax:(Lcoursier/util/shaded/org/jsoup/nodes/Document$OutputSettings$Syntax;)Lcoursier/util/shaded/org/jsoup/nodes/Document$OutputSettings;
   #79 = Methodref          #7.#78        // coursier/util/shaded/org/jsoup/nodes/Document$OutputSettings.syntax:(Lcoursier/util/shaded/org/jsoup/nodes/Document$OutputSettings$Syntax;)Lcoursier/util/shaded/org/jsoup/nodes/Document$OutputSettings;
   #80 = Utf8               input
   #81 = Utf8               Ljava/io/Reader;
   #82 = Utf8               baseUri
   #83 = Utf8               Ljava/lang/String;
   #84 = Utf8               parser
   #85 = Utf8               Lcoursier/util/shaded/org/jsoup/parser/Parser;
   #86 = Utf8               parse
   #87 = Utf8               (Ljava/io/Reader;Ljava/lang/String;)Lcoursier/util/shaded/org/jsoup/nodes/Document;
   #88 = Utf8               coursier/util/shaded/org/jsoup/parser/Parser
   #89 = Class              #88           // coursier/util/shaded/org/jsoup/parser/Parser
   #90 = Utf8               (Lcoursier/util/shaded/org/jsoup/parser/TreeBuilder;)V
   #91 = NameAndType        #36:#90       // "<init>":(Lcoursier/util/shaded/org/jsoup/parser/TreeBuilder;)V
   #92 = Methodref          #89.#91       // coursier/util/shaded/org/jsoup/parser/Parser."<init>":(Lcoursier/util/shaded/org/jsoup/parser/TreeBuilder;)V
   #93 = Utf8               (Ljava/io/Reader;Ljava/lang/String;Lcoursier/util/shaded/org/jsoup/parser/Parser;)Lcoursier/util/shaded/org/jsoup/nodes/Document;
   #94 = NameAndType        #86:#93       // parse:(Ljava/io/Reader;Ljava/lang/String;Lcoursier/util/shaded/org/jsoup/parser/Parser;)Lcoursier/util/shaded/org/jsoup/nodes/Document;
   #95 = Methodref          #2.#94        // coursier/util/shaded/org/jsoup/parser/XmlTreeBuilder.parse:(Ljava/io/Reader;Ljava/lang/String;Lcoursier/util/shaded/org/jsoup/parser/Parser;)Lcoursier/util/shaded/org/jsoup/nodes/Document;
   #96 = Utf8               (Ljava/lang/String;Ljava/lang/String;)Lcoursier/util/shaded/org/jsoup/nodes/Document;
   #97 = Utf8               java/io/StringReader
   #98 = Class              #97           // java/io/StringReader
   #99 = Utf8               (Ljava/lang/String;)V
  #100 = NameAndType        #36:#99       // "<init>":(Ljava/lang/String;)V
  #101 = Methodref          #98.#100      // java/io/StringReader."<init>":(Ljava/lang/String;)V
  #102 = Utf8               process
  #103 = Utf8               (Lcoursier/util/shaded/org/jsoup/parser/Token;)Z
  #104 = Utf8               $SwitchMap$org$jsoup$parser$Token$TokenType
  #105 = Utf8               [I
  #106 = NameAndType        #104:#105     // $SwitchMap$org$jsoup$parser$Token$TokenType:[I
  #107 = Fieldref           #15.#106      // coursier/util/shaded/org/jsoup/parser/XmlTreeBuilder$1.$SwitchMap$org$jsoup$parser$Token$TokenType:[I
  #108 = Utf8               type
  #109 = Utf8               Lcoursier/util/shaded/org/jsoup/parser/Token$TokenType;
  #110 = NameAndType        #108:#109     // type:Lcoursier/util/shaded/org/jsoup/parser/Token$TokenType;
  #111 = Fieldref           #19.#110      // coursier/util/shaded/org/jsoup/parser/Token.type:Lcoursier/util/shaded/org/jsoup/parser/Token$TokenType;
  #112 = Utf8               ordinal
  #113 = Utf8               ()I
  #114 = NameAndType        #112:#113     // ordinal:()I
  #115 = Methodref          #17.#114      // coursier/util/shaded/org/jsoup/parser/Token$TokenType.ordinal:()I
  #116 = Utf8               asStartTag
  #117 = Utf8               ()Lcoursier/util/shaded/org/jsoup/parser/Token$StartTag;
  #118 = NameAndType        #116:#117     // asStartTag:()Lcoursier/util/shaded/org/jsoup/parser/Token$StartTag;
  #119 = Methodref          #19.#118      // coursier/util/shaded/org/jsoup/parser/Token.asStartTag:()Lcoursier/util/shaded/org/jsoup/parser/Token$StartTag;
  #120 = Utf8               insert
  #121 = Utf8               (Lcoursier/util/shaded/org/jsoup/parser/Token$StartTag;)Lcoursier/util/shaded/org/jsoup/nodes/Element;
  #122 = NameAndType        #120:#121     // insert:(Lcoursier/util/shaded/org/jsoup/parser/Token$StartTag;)Lcoursier/util/shaded/org/jsoup/nodes/Element;
  #123 = Methodref          #2.#122       // coursier/util/shaded/org/jsoup/parser/XmlTreeBuilder.insert:(Lcoursier/util/shaded/org/jsoup/parser/Token$StartTag;)Lcoursier/util/shaded/org/jsoup/nodes/Element;
  #124 = Utf8               asEndTag
  #125 = Utf8               ()Lcoursier/util/shaded/org/jsoup/parser/Token$EndTag;
  #126 = NameAndType        #124:#125     // asEndTag:()Lcoursier/util/shaded/org/jsoup/parser/Token$EndTag;
  #127 = Methodref          #19.#126      // coursier/util/shaded/org/jsoup/parser/Token.asEndTag:()Lcoursier/util/shaded/org/jsoup/parser/Token$EndTag;
  #128 = Utf8               popStackToClose
  #129 = Utf8               (Lcoursier/util/shaded/org/jsoup/parser/Token$EndTag;)V
  #130 = NameAndType        #128:#129     // popStackToClose:(Lcoursier/util/shaded/org/jsoup/parser/Token$EndTag;)V
  #131 = Methodref          #2.#130       // coursier/util/shaded/org/jsoup/parser/XmlTreeBuilder.popStackToClose:(Lcoursier/util/shaded/org/jsoup/parser/Token$EndTag;)V
  #132 = Utf8               asComment
  #133 = Utf8               ()Lcoursier/util/shaded/org/jsoup/parser/Token$Comment;
  #134 = NameAndType        #132:#133     // asComment:()Lcoursier/util/shaded/org/jsoup/parser/Token$Comment;
  #135 = Methodref          #19.#134      // coursier/util/shaded/org/jsoup/parser/Token.asComment:()Lcoursier/util/shaded/org/jsoup/parser/Token$Comment;
  #136 = Utf8               (Lcoursier/util/shaded/org/jsoup/parser/Token$Comment;)V
  #137 = NameAndType        #120:#136     // insert:(Lcoursier/util/shaded/org/jsoup/parser/Token$Comment;)V
  #138 = Methodref          #2.#137       // coursier/util/shaded/org/jsoup/parser/XmlTreeBuilder.insert:(Lcoursier/util/shaded/org/jsoup/parser/Token$Comment;)V
  #139 = Utf8               asCharacter
  #140 = Utf8               ()Lcoursier/util/shaded/org/jsoup/parser/Token$Character;
  #141 = NameAndType        #139:#140     // asCharacter:()Lcoursier/util/shaded/org/jsoup/parser/Token$Character;
  #142 = Methodref          #19.#141      // coursier/util/shaded/org/jsoup/parser/Token.asCharacter:()Lcoursier/util/shaded/org/jsoup/parser/Token$Character;
  #143 = Utf8               (Lcoursier/util/shaded/org/jsoup/parser/Token$Character;)V
  #144 = NameAndType        #120:#143     // insert:(Lcoursier/util/shaded/org/jsoup/parser/Token$Character;)V
  #145 = Methodref          #2.#144       // coursier/util/shaded/org/jsoup/parser/XmlTreeBuilder.insert:(Lcoursier/util/shaded/org/jsoup/parser/Token$Character;)V
  #146 = Utf8               asDoctype
  #147 = Utf8               ()Lcoursier/util/shaded/org/jsoup/parser/Token$Doctype;
  #148 = NameAndType        #146:#147     // asDoctype:()Lcoursier/util/shaded/org/jsoup/parser/Token$Doctype;
  #149 = Methodref          #19.#148      // coursier/util/shaded/org/jsoup/parser/Token.asDoctype:()Lcoursier/util/shaded/org/jsoup/parser/Token$Doctype;
  #150 = Utf8               (Lcoursier/util/shaded/org/jsoup/parser/Token$Doctype;)V
  #151 = NameAndType        #120:#150     // insert:(Lcoursier/util/shaded/org/jsoup/parser/Token$Doctype;)V
  #152 = Methodref          #2.#151       // coursier/util/shaded/org/jsoup/parser/XmlTreeBuilder.insert:(Lcoursier/util/shaded/org/jsoup/parser/Token$Doctype;)V
  #153 = Utf8               java/lang/StringBuilder
  #154 = Class              #153          // java/lang/StringBuilder
  #155 = Methodref          #154.#38      // java/lang/StringBuilder."<init>":()V
  #156 = Utf8               Unexpected token type:
  #157 = String             #156          // Unexpected token type:
  #158 = Utf8               append
  #159 = Utf8               (Ljava/lang/String;)Ljava/lang/StringBuilder;
  #160 = NameAndType        #158:#159     // append:(Ljava/lang/String;)Ljava/lang/StringBuilder;
  #161 = Methodref          #154.#160     // java/lang/StringBuilder.append:(Ljava/lang/String;)Ljava/lang/StringBuilder;
  #162 = Utf8               (Ljava/lang/Object;)Ljava/lang/StringBuilder;
  #163 = NameAndType        #158:#162     // append:(Ljava/lang/Object;)Ljava/lang/StringBuilder;
  #164 = Methodref          #154.#163     // java/lang/StringBuilder.append:(Ljava/lang/Object;)Ljava/lang/StringBuilder;
  #165 = Utf8               toString
  #166 = Utf8               ()Ljava/lang/String;
  #167 = NameAndType        #165:#166     // toString:()Ljava/lang/String;
  #168 = Methodref          #154.#167     // java/lang/StringBuilder.toString:()Ljava/lang/String;
  #169 = Utf8               coursier/util/shaded/org/jsoup/helper/Validate
  #170 = Class              #169          // coursier/util/shaded/org/jsoup/helper/Validate
  #171 = Utf8               fail
  #172 = NameAndType        #171:#99      // fail:(Ljava/lang/String;)V
  #173 = Methodref          #170.#172     // coursier/util/shaded/org/jsoup/helper/Validate.fail:(Ljava/lang/String;)V
  #174 = Utf8               token
  #175 = Utf8               Lcoursier/util/shaded/org/jsoup/parser/Token;
  #176 = Utf8               insertNode
  #177 = Utf8               (Lcoursier/util/shaded/org/jsoup/nodes/Node;)V
  #178 = Utf8               currentElement
  #179 = Utf8               ()Lcoursier/util/shaded/org/jsoup/nodes/Element;
  #180 = NameAndType        #178:#179     // currentElement:()Lcoursier/util/shaded/org/jsoup/nodes/Element;
  #181 = Methodref          #2.#180       // coursier/util/shaded/org/jsoup/parser/XmlTreeBuilder.currentElement:()Lcoursier/util/shaded/org/jsoup/nodes/Element;
  #182 = Utf8               coursier/util/shaded/org/jsoup/nodes/Element
  #183 = Class              #182          // coursier/util/shaded/org/jsoup/nodes/Element
  #184 = Utf8               appendChild
  #185 = Utf8               (Lcoursier/util/shaded/org/jsoup/nodes/Node;)Lcoursier/util/shaded/org/jsoup/nodes/Element;
  #186 = NameAndType        #184:#185     // appendChild:(Lcoursier/util/shaded/org/jsoup/nodes/Node;)Lcoursier/util/shaded/org/jsoup/nodes/Element;
  #187 = Methodref          #183.#186     // coursier/util/shaded/org/jsoup/nodes/Element.appendChild:(Lcoursier/util/shaded/org/jsoup/nodes/Node;)Lcoursier/util/shaded/org/jsoup/nodes/Element;
  #188 = Utf8               node
  #189 = Utf8               Lcoursier/util/shaded/org/jsoup/nodes/Node;
  #190 = Utf8               name
  #191 = NameAndType        #190:#166     // name:()Ljava/lang/String;
  #192 = Methodref          #22.#191      // coursier/util/shaded/org/jsoup/parser/Token$StartTag.name:()Ljava/lang/String;
  #193 = Utf8               settings
  #194 = NameAndType        #193:#47      // settings:Lcoursier/util/shaded/org/jsoup/parser/ParseSettings;
  #195 = Fieldref           #2.#194       // coursier/util/shaded/org/jsoup/parser/XmlTreeBuilder.settings:Lcoursier/util/shaded/org/jsoup/parser/ParseSettings;
  #196 = Utf8               coursier/util/shaded/org/jsoup/parser/Tag
  #197 = Class              #196          // coursier/util/shaded/org/jsoup/parser/Tag
  #198 = Utf8               valueOf
  #199 = Utf8               (Ljava/lang/String;Lcoursier/util/shaded/org/jsoup/parser/ParseSettings;)Lcoursier/util/shaded/org/jsoup/parser/Tag;
  #200 = NameAndType        #198:#199     // valueOf:(Ljava/lang/String;Lcoursier/util/shaded/org/jsoup/parser/ParseSettings;)Lcoursier/util/shaded/org/jsoup/parser/Tag;
  #201 = Methodref          #197.#200     // coursier/util/shaded/org/jsoup/parser/Tag.valueOf:(Ljava/lang/String;Lcoursier/util/shaded/org/jsoup/parser/ParseSettings;)Lcoursier/util/shaded/org/jsoup/parser/Tag;
  #202 = Utf8               attributes
  #203 = Utf8               Lcoursier/util/shaded/org/jsoup/nodes/Attributes;
  #204 = NameAndType        #202:#203     // attributes:Lcoursier/util/shaded/org/jsoup/nodes/Attributes;
  #205 = Fieldref           #22.#204      // coursier/util/shaded/org/jsoup/parser/Token$StartTag.attributes:Lcoursier/util/shaded/org/jsoup/nodes/Attributes;
  #206 = Utf8               coursier/util/shaded/org/jsoup/nodes/Attributes
  #207 = Class              #206          // coursier/util/shaded/org/jsoup/nodes/Attributes
  #208 = Utf8               deduplicate
  #209 = Utf8               (Lcoursier/util/shaded/org/jsoup/parser/ParseSettings;)I
  #210 = NameAndType        #208:#209     // deduplicate:(Lcoursier/util/shaded/org/jsoup/parser/ParseSettings;)I
  #211 = Methodref          #207.#210     // coursier/util/shaded/org/jsoup/nodes/Attributes.deduplicate:(Lcoursier/util/shaded/org/jsoup/parser/ParseSettings;)I
  #212 = Utf8               normalizeAttributes
  #213 = Utf8               (Lcoursier/util/shaded/org/jsoup/nodes/Attributes;)Lcoursier/util/shaded/org/jsoup/nodes/Attributes;
  #214 = NameAndType        #212:#213     // normalizeAttributes:(Lcoursier/util/shaded/org/jsoup/nodes/Attributes;)Lcoursier/util/shaded/org/jsoup/nodes/Attributes;
  #215 = Methodref          #45.#214      // coursier/util/shaded/org/jsoup/parser/ParseSettings.normalizeAttributes:(Lcoursier/util/shaded/org/jsoup/nodes/Attributes;)Lcoursier/util/shaded/org/jsoup/nodes/Attributes;
  #216 = Utf8               (Lcoursier/util/shaded/org/jsoup/parser/Tag;Ljava/lang/String;Lcoursier/util/shaded/org/jsoup/nodes/Attributes;)V
  #217 = NameAndType        #36:#216      // "<init>":(Lcoursier/util/shaded/org/jsoup/parser/Tag;Ljava/lang/String;Lcoursier/util/shaded/org/jsoup/nodes/Attributes;)V
  #218 = Methodref          #183.#217     // coursier/util/shaded/org/jsoup/nodes/Element."<init>":(Lcoursier/util/shaded/org/jsoup/parser/Tag;Ljava/lang/String;Lcoursier/util/shaded/org/jsoup/nodes/Attributes;)V
  #219 = NameAndType        #176:#177     // insertNode:(Lcoursier/util/shaded/org/jsoup/nodes/Node;)V
  #220 = Methodref          #2.#219       // coursier/util/shaded/org/jsoup/parser/XmlTreeBuilder.insertNode:(Lcoursier/util/shaded/org/jsoup/nodes/Node;)V
  #221 = Utf8               isSelfClosing
  #222 = Utf8               ()Z
  #223 = NameAndType        #221:#222     // isSelfClosing:()Z
  #224 = Methodref          #22.#223      // coursier/util/shaded/org/jsoup/parser/Token$StartTag.isSelfClosing:()Z
  #225 = Utf8               isKnownTag
  #226 = NameAndType        #225:#222     // isKnownTag:()Z
  #227 = Methodref          #197.#226     // coursier/util/shaded/org/jsoup/parser/Tag.isKnownTag:()Z
  #228 = Utf8               setSelfClosing
  #229 = Utf8               ()Lcoursier/util/shaded/org/jsoup/parser/Tag;
  #230 = NameAndType        #228:#229     // setSelfClosing:()Lcoursier/util/shaded/org/jsoup/parser/Tag;
  #231 = Methodref          #197.#230     // coursier/util/shaded/org/jsoup/parser/Tag.setSelfClosing:()Lcoursier/util/shaded/org/jsoup/parser/Tag;
  #232 = Utf8               startTag
  #233 = Utf8               Lcoursier/util/shaded/org/jsoup/parser/Token$StartTag;
  #234 = Utf8               tag
  #235 = Utf8               Lcoursier/util/shaded/org/jsoup/parser/Tag;
  #236 = Utf8               el
  #237 = Utf8               Lcoursier/util/shaded/org/jsoup/nodes/Element;
  #238 = Utf8               coursier/util/shaded/org/jsoup/nodes/Comment
  #239 = Class              #238          // coursier/util/shaded/org/jsoup/nodes/Comment
  #240 = Utf8               getData
  #241 = NameAndType        #240:#166     // getData:()Ljava/lang/String;
  #242 = Methodref          #28.#241      // coursier/util/shaded/org/jsoup/parser/Token$Comment.getData:()Ljava/lang/String;
  #243 = Methodref          #239.#100     // coursier/util/shaded/org/jsoup/nodes/Comment."<init>":(Ljava/lang/String;)V
  #244 = Utf8               bogus
  #245 = Utf8               Z
  #246 = NameAndType        #244:#245     // bogus:Z
  #247 = Fieldref           #28.#246      // coursier/util/shaded/org/jsoup/parser/Token$Comment.bogus:Z
  #248 = Utf8               isXmlDeclaration
  #249 = NameAndType        #248:#222     // isXmlDeclaration:()Z
  #250 = Methodref          #239.#249     // coursier/util/shaded/org/jsoup/nodes/Comment.isXmlDeclaration:()Z
  #251 = Utf8               asXmlDeclaration
  #252 = Utf8               ()Lcoursier/util/shaded/org/jsoup/nodes/XmlDeclaration;
  #253 = NameAndType        #251:#252     // asXmlDeclaration:()Lcoursier/util/shaded/org/jsoup/nodes/XmlDeclaration;
  #254 = Methodref          #239.#253     // coursier/util/shaded/org/jsoup/nodes/Comment.asXmlDeclaration:()Lcoursier/util/shaded/org/jsoup/nodes/XmlDeclaration;
  #255 = Utf8               coursier/util/shaded/org/jsoup/nodes/Node
  #256 = Class              #255          // coursier/util/shaded/org/jsoup/nodes/Node
  #257 = Utf8               decl
  #258 = Utf8               Lcoursier/util/shaded/org/jsoup/nodes/XmlDeclaration;
  #259 = Utf8               commentToken
  #260 = Utf8               Lcoursier/util/shaded/org/jsoup/parser/Token$Comment;
  #261 = Utf8               comment
  #262 = Utf8               Lcoursier/util/shaded/org/jsoup/nodes/Comment;
  #263 = Methodref          #31.#241      // coursier/util/shaded/org/jsoup/parser/Token$Character.getData:()Ljava/lang/String;
  #264 = Utf8               isCData
  #265 = NameAndType        #264:#222     // isCData:()Z
  #266 = Methodref          #31.#265      // coursier/util/shaded/org/jsoup/parser/Token$Character.isCData:()Z
  #267 = Utf8               coursier/util/shaded/org/jsoup/nodes/CDataNode
  #268 = Class              #267          // coursier/util/shaded/org/jsoup/nodes/CDataNode
  #269 = Methodref          #268.#100     // coursier/util/shaded/org/jsoup/nodes/CDataNode."<init>":(Ljava/lang/String;)V
  #270 = Utf8               java/lang/String
  #271 = Class              #270          // java/lang/String
  #272 = Utf8               coursier/util/shaded/org/jsoup/nodes/TextNode
  #273 = Class              #272          // coursier/util/shaded/org/jsoup/nodes/TextNode
  #274 = Methodref          #273.#100     // coursier/util/shaded/org/jsoup/nodes/TextNode."<init>":(Ljava/lang/String;)V
  #275 = Utf8               Lcoursier/util/shaded/org/jsoup/parser/Token$Character;
  #276 = Utf8               data
  #277 = Utf8               coursier/util/shaded/org/jsoup/nodes/DocumentType
  #278 = Class              #277          // coursier/util/shaded/org/jsoup/nodes/DocumentType
  #279 = Utf8               getName
  #280 = NameAndType        #279:#166     // getName:()Ljava/lang/String;
  #281 = Methodref          #34.#280      // coursier/util/shaded/org/jsoup/parser/Token$Doctype.getName:()Ljava/lang/String;
  #282 = Utf8               normalizeTag
  #283 = Utf8               (Ljava/lang/String;)Ljava/lang/String;
  #284 = NameAndType        #282:#283     // normalizeTag:(Ljava/lang/String;)Ljava/lang/String;
  #285 = Methodref          #45.#284      // coursier/util/shaded/org/jsoup/parser/ParseSettings.normalizeTag:(Ljava/lang/String;)Ljava/lang/String;
  #286 = Utf8               getPublicIdentifier
  #287 = NameAndType        #286:#166     // getPublicIdentifier:()Ljava/lang/String;
  #288 = Methodref          #34.#287      // coursier/util/shaded/org/jsoup/parser/Token$Doctype.getPublicIdentifier:()Ljava/lang/String;
  #289 = Utf8               getSystemIdentifier
  #290 = NameAndType        #289:#166     // getSystemIdentifier:()Ljava/lang/String;
  #291 = Methodref          #34.#290      // coursier/util/shaded/org/jsoup/parser/Token$Doctype.getSystemIdentifier:()Ljava/lang/String;
  #292 = Utf8               (Ljava/lang/String;Ljava/lang/String;Ljava/lang/String;)V
  #293 = NameAndType        #36:#292      // "<init>":(Ljava/lang/String;Ljava/lang/String;Ljava/lang/String;)V
  #294 = Methodref          #278.#293     // coursier/util/shaded/org/jsoup/nodes/DocumentType."<init>":(Ljava/lang/String;Ljava/lang/String;Ljava/lang/String;)V
  #295 = Utf8               getPubSysKey
  #296 = NameAndType        #295:#166     // getPubSysKey:()Ljava/lang/String;
  #297 = Methodref          #34.#296      // coursier/util/shaded/org/jsoup/parser/Token$Doctype.getPubSysKey:()Ljava/lang/String;
  #298 = Utf8               setPubSysKey
  #299 = NameAndType        #298:#99      // setPubSysKey:(Ljava/lang/String;)V
  #300 = Methodref          #278.#299     // coursier/util/shaded/org/jsoup/nodes/DocumentType.setPubSysKey:(Ljava/lang/String;)V
  #301 = Utf8               d
  #302 = Utf8               Lcoursier/util/shaded/org/jsoup/parser/Token$Doctype;
  #303 = Utf8               doctypeNode
  #304 = Utf8               Lcoursier/util/shaded/org/jsoup/nodes/DocumentType;
  #305 = Utf8               tagName
  #306 = NameAndType        #305:#83      // tagName:Ljava/lang/String;
  #307 = Fieldref           #25.#306      // coursier/util/shaded/org/jsoup/parser/Token$EndTag.tagName:Ljava/lang/String;
  #308 = Utf8               size
  #309 = NameAndType        #308:#113     // size:()I
  #310 = Methodref          #63.#309      // java/util/ArrayList.size:()I
  #311 = Utf8               get
  #312 = Utf8               (I)Ljava/lang/Object;
  #313 = NameAndType        #311:#312     // get:(I)Ljava/lang/Object;
  #314 = Methodref          #63.#313      // java/util/ArrayList.get:(I)Ljava/lang/Object;
  #315 = Utf8               nodeName
  #316 = NameAndType        #315:#166     // nodeName:()Ljava/lang/String;
  #317 = Methodref          #183.#316     // coursier/util/shaded/org/jsoup/nodes/Element.nodeName:()Ljava/lang/String;
  #318 = Utf8               equals
  #319 = NameAndType        #318:#65      // equals:(Ljava/lang/Object;)Z
  #320 = Methodref          #271.#319     // java/lang/String.equals:(Ljava/lang/Object;)Z
  #321 = Utf8               remove
  #322 = NameAndType        #321:#312     // remove:(I)Ljava/lang/Object;
  #323 = Methodref          #63.#322      // java/util/ArrayList.remove:(I)Ljava/lang/Object;
  #324 = Utf8               next
  #325 = Utf8               pos
  #326 = Utf8               I
  #327 = Utf8               endTag
  #328 = Utf8               Lcoursier/util/shaded/org/jsoup/parser/Token$EndTag;
  #329 = Utf8               elName
  #330 = Utf8               firstFound
  #331 = Utf8               parseFragment
  #332 = Utf8               (Ljava/lang/String;Ljava/lang/String;Lcoursier/util/shaded/org/jsoup/parser/Parser;)Ljava/util/List;
  #333 = Utf8               (Ljava/lang/String;Ljava/lang/String;Lcoursier/util/shaded/org/jsoup/parser/Parser;)Ljava/util/List<Lcoursier/util/shaded/org/jsoup/nodes/Node;>;
  #334 = Methodref          #2.#52        // coursier/util/shaded/org/jsoup/parser/XmlTreeBuilder.initialiseParse:(Ljava/io/Reader;Ljava/lang/String;Lcoursier/util/shaded/org/jsoup/parser/Parser;)V
  #335 = Utf8               runParser
  #336 = NameAndType        #335:#37      // runParser:()V
  #337 = Methodref          #2.#336       // coursier/util/shaded/org/jsoup/parser/XmlTreeBuilder.runParser:()V
  #338 = Utf8               childNodes
  #339 = Utf8               ()Ljava/util/List;
  #340 = NameAndType        #338:#339     // childNodes:()Ljava/util/List;
  #341 = Methodref          #9.#340       // coursier/util/shaded/org/jsoup/nodes/Document.childNodes:()Ljava/util/List;
  #342 = Utf8               inputFragment
  #343 = Utf8               (Ljava/lang/String;Lcoursier/util/shaded/org/jsoup/nodes/Element;Ljava/lang/String;Lcoursier/util/shaded/org/jsoup/parser/Parser;)Ljava/util/List;
  #344 = Utf8               (Ljava/lang/String;Lcoursier/util/shaded/org/jsoup/nodes/Element;Ljava/lang/String;Lcoursier/util/shaded/org/jsoup/parser/Parser;)Ljava/util/List<Lcoursier/util/shaded/org/jsoup/nodes/Node;>;
  #345 = NameAndType        #331:#332     // parseFragment:(Ljava/lang/String;Ljava/lang/String;Lcoursier/util/shaded/org/jsoup/parser/Parser;)Ljava/util/List;
  #346 = Methodref          #2.#345       // coursier/util/shaded/org/jsoup/parser/XmlTreeBuilder.parseFragment:(Ljava/lang/String;Ljava/lang/String;Lcoursier/util/shaded/org/jsoup/parser/Parser;)Ljava/util/List;
  #347 = Utf8               context
  #348 = Utf8               processStartTag
  #349 = Utf8               (Ljava/lang/String;Lcoursier/util/shaded/org/jsoup/nodes/Attributes;)Z
  #350 = NameAndType        #348:#349     // processStartTag:(Ljava/lang/String;Lcoursier/util/shaded/org/jsoup/nodes/Attributes;)Z
  #351 = Methodref          #4.#350       // coursier/util/shaded/org/jsoup/parser/TreeBuilder.processStartTag:(Ljava/lang/String;Lcoursier/util/shaded/org/jsoup/nodes/Attributes;)Z
  #352 = Utf8               Code
  #353 = Utf8               LineNumberTable
  #354 = Utf8               LocalVariableTable
  #355 = Utf8               StackMapTable
  #356 = Utf8               Signature
  #357 = Utf8               InnerClasses
  #358 = Utf8               SourceFile
{
  public coursier.util.shaded.org.jsoup.parser.XmlTreeBuilder();
    descriptor: ()V
    flags: (0x0001) ACC_PUBLIC
    Code:
      stack=1, locals=1, args_size=1
         0: aload_0
         1: invokespecial #39                 // Method coursier/util/shaded/org/jsoup/parser/TreeBuilder."<init>":()V
         4: return
      LineNumberTable:
        line 24: 0
      LocalVariableTable:
        Start  Length  Slot  Name   Signature
            0       5     0  this   Lcoursier/util/shaded/org/jsoup/parser/XmlTreeBuilder;

  coursier.util.shaded.org.jsoup.parser.ParseSettings defaultSettings();
    descriptor: ()Lcoursier/util/shaded/org/jsoup/parser/ParseSettings;
    flags: (0x0000)
    Code:
      stack=1, locals=1, args_size=1
         0: getstatic     #49                 // Field coursier/util/shaded/org/jsoup/parser/ParseSettings.preserveCase:Lcoursier/util/shaded/org/jsoup/parser/ParseSettings;
         3: areturn
      LineNumberTable:
        line 26: 0
      LocalVariableTable:
        Start  Length  Slot  Name   Signature
            0       4     0  this   Lcoursier/util/shaded/org/jsoup/parser/XmlTreeBuilder;

  protected void initialiseParse(java.io.Reader, java.lang.String, coursier.util.shaded.org.jsoup.parser.Parser);
    descriptor: (Ljava/io/Reader;Ljava/lang/String;Lcoursier/util/shaded/org/jsoup/parser/Parser;)V
    flags: (0x0004) ACC_PROTECTED
    Code:
      stack=4, locals=4, args_size=4
         0: aload_0
         1: aload_1
         2: aload_2
         3: aload_3
         4: invokespecial #53                 // Method coursier/util/shaded/org/jsoup/parser/TreeBuilder.initialiseParse:(Ljava/io/Reader;Ljava/lang/String;Lcoursier/util/shaded/org/jsoup/parser/Parser;)V
         7: aload_0
         8: getfield      #57                 // Field stack:Ljava/util/ArrayList;
        11: aload_0
        12: getfield      #61                 // Field doc:Lcoursier/util/shaded/org/jsoup/nodes/Document;
        15: invokevirtual #67                 // Method java/util/ArrayList.add:(Ljava/lang/Object;)Z
        18: pop
        19: aload_0
        20: getfield      #61                 // Field doc:Lcoursier/util/shaded/org/jsoup/nodes/Document;
        23: invokevirtual #71                 // Method coursier/util/shaded/org/jsoup/nodes/Document.outputSettings:()Lcoursier/util/shaded/org/jsoup/nodes/Document$OutputSettings;
        26: getstatic     #75                 // Field coursier/util/shaded/org/jsoup/nodes/Document$OutputSettings$Syntax.xml:Lcoursier/util/shaded/org/jsoup/nodes/Document$OutputSettings$Syntax;
        29: invokevirtual #79                 // Method coursier/util/shaded/org/jsoup/nodes/Document$OutputSettings.syntax:(Lcoursier/util/shaded/org/jsoup/nodes/Document$OutputSettings$Syntax;)Lcoursier/util/shaded/org/jsoup/nodes/Document$OutputSettings;
        32: pop
        33: return
      LineNumberTable:
        line 31: 0
        line 32: 7
        line 33: 19
        line 34: 33
      LocalVariableTable:
        Start  Length  Slot  Name   Signature
            0      34     0  this   Lcoursier/util/shaded/org/jsoup/parser/XmlTreeBuilder;
            0      34     1 input   Ljava/io/Reader;
            0      34     2 baseUri   Ljava/lang/String;
            0      34     3 parser   Lcoursier/util/shaded/org/jsoup/parser/Parser;

  coursier.util.shaded.org.jsoup.nodes.Document parse(java.io.Reader, java.lang.String);
    descriptor: (Ljava/io/Reader;Ljava/lang/String;)Lcoursier/util/shaded/org/jsoup/nodes/Document;
    flags: (0x0000)
    Code:
      stack=6, locals=3, args_size=3
         0: aload_0
         1: aload_1
         2: aload_2
         3: new           #89                 // class coursier/util/shaded/org/jsoup/parser/Parser
         6: dup
         7: aload_0
         8: invokespecial #92                 // Method coursier/util/shaded/org/jsoup/parser/Parser."<init>":(Lcoursier/util/shaded/org/jsoup/parser/TreeBuilder;)V
        11: invokevirtual #95                 // Method parse:(Ljava/io/Reader;Ljava/lang/String;Lcoursier/util/shaded/org/jsoup/parser/Parser;)Lcoursier/util/shaded/org/jsoup/nodes/Document;
        14: areturn
      LineNumberTable:
        line 37: 0
      LocalVariableTable:
        Start  Length  Slot  Name   Signature
            0      15     0  this   Lcoursier/util/shaded/org/jsoup/parser/XmlTreeBuilder;
            0      15     1 input   Ljava/io/Reader;
            0      15     2 baseUri   Ljava/lang/String;

  coursier.util.shaded.org.jsoup.nodes.Document parse(java.lang.String, java.lang.String);
    descriptor: (Ljava/lang/String;Ljava/lang/String;)Lcoursier/util/shaded/org/jsoup/nodes/Document;
    flags: (0x0000)
    Code:
      stack=6, locals=3, args_size=3
         0: aload_0
         1: new           #98                 // class java/io/StringReader
         4: dup
         5: aload_1
         6: invokespecial #101                // Method java/io/StringReader."<init>":(Ljava/lang/String;)V
         9: aload_2
        10: new           #89                 // class coursier/util/shaded/org/jsoup/parser/Parser
        13: dup
        14: aload_0
        15: invokespecial #92                 // Method coursier/util/shaded/org/jsoup/parser/Parser."<init>":(Lcoursier/util/shaded/org/jsoup/parser/TreeBuilder;)V
        18: invokevirtual #95                 // Method parse:(Ljava/io/Reader;Ljava/lang/String;Lcoursier/util/shaded/org/jsoup/parser/Parser;)Lcoursier/util/shaded/org/jsoup/nodes/Document;
        21: areturn
      LineNumberTable:
        line 41: 0
      LocalVariableTable:
        Start  Length  Slot  Name   Signature
            0      22     0  this   Lcoursier/util/shaded/org/jsoup/parser/XmlTreeBuilder;
            0      22     1 input   Ljava/lang/String;
            0      22     2 baseUri   Ljava/lang/String;

  protected boolean process(coursier.util.shaded.org.jsoup.parser.Token);
    descriptor: (Lcoursier/util/shaded/org/jsoup/parser/Token;)Z
    flags: (0x0004) ACC_PROTECTED
    Code:
      stack=2, locals=2, args_size=2
         0: getstatic     #107                // Field coursier/util/shaded/org/jsoup/parser/XmlTreeBuilder$1.$SwitchMap$org$jsoup$parser$Token$TokenType:[I
         3: aload_1
         4: getfield      #111                // Field coursier/util/shaded/org/jsoup/parser/Token.type:Lcoursier/util/shaded/org/jsoup/parser/Token$TokenType;
         7: invokevirtual #115                // Method coursier/util/shaded/org/jsoup/parser/Token$TokenType.ordinal:()I
        10: iaload
        11: tableswitch   { // 1 to 6
                       1: 48
                       2: 60
                       3: 71
                       4: 82
                       5: 93
                       6: 104
                 default: 107
            }
        48: aload_0
        49: aload_1
        50: invokevirtual #119                // Method coursier/util/shaded/org/jsoup/parser/Token.asStartTag:()Lcoursier/util/shaded/org/jsoup/parser/Token$StartTag;
        53: invokevirtual #123                // Method insert:(Lcoursier/util/shaded/org/jsoup/parser/Token$StartTag;)Lcoursier/util/shaded/org/jsoup/nodes/Element;
        56: pop
        57: goto          132
        60: aload_0
        61: aload_1
        62: invokevirtual #127                // Method coursier/util/shaded/org/jsoup/parser/Token.asEndTag:()Lcoursier/util/shaded/org/jsoup/parser/Token$EndTag;
        65: invokespecial #131                // Method popStackToClose:(Lcoursier/util/shaded/org/jsoup/parser/Token$EndTag;)V
        68: goto          132
        71: aload_0
        72: aload_1
        73: invokevirtual #135                // Method coursier/util/shaded/org/jsoup/parser/Token.asComment:()Lcoursier/util/shaded/org/jsoup/parser/Token$Comment;
        76: invokevirtual #138                // Method insert:(Lcoursier/util/shaded/org/jsoup/parser/Token$Comment;)V
        79: goto          132
        82: aload_0
        83: aload_1
        84: invokevirtual #142                // Method coursier/util/shaded/org/jsoup/parser/Token.asCharacter:()Lcoursier/util/shaded/org/jsoup/parser/Token$Character;
        87: invokevirtual #145                // Method insert:(Lcoursier/util/shaded/org/jsoup/parser/Token$Character;)V
        90: goto          132
        93: aload_0
        94: aload_1
        95: invokevirtual #149                // Method coursier/util/shaded/org/jsoup/parser/Token.asDoctype:()Lcoursier/util/shaded/org/jsoup/parser/Token$Doctype;
        98: invokevirtual #152                // Method insert:(Lcoursier/util/shaded/org/jsoup/parser/Token$Doctype;)V
       101: goto          132
       104: goto          132
       107: new           #154                // class java/lang/StringBuilder
       110: dup
       111: invokespecial #155                // Method java/lang/StringBuilder."<init>":()V
       114: ldc           #157                // String Unexpected token type:
       116: invokevirtual #161                // Method java/lang/StringBuilder.append:(Ljava/lang/String;)Ljava/lang/StringBuilder;
       119: aload_1
       120: getfield      #111                // Field coursier/util/shaded/org/jsoup/parser/Token.type:Lcoursier/util/shaded/org/jsoup/parser/Token$TokenType;
       123: invokevirtual #164                // Method java/lang/StringBuilder.append:(Ljava/lang/Object;)Ljava/lang/StringBuilder;
       126: invokevirtual #168                // Method java/lang/StringBuilder.toString:()Ljava/lang/String;
       129: invokestatic  #173                // Method coursier/util/shaded/org/jsoup/helper/Validate.fail:(Ljava/lang/String;)V
       132: iconst_1
       133: ireturn
      StackMapTable: number_of_entries = 8
        frame_type = 48 /* same */
        frame_type = 11 /* same */
        frame_type = 10 /* same */
        frame_type = 10 /* same */
        frame_type = 10 /* same */
        frame_type = 10 /* same */
        frame_type = 2 /* same */
        frame_type = 24 /* same */
      LineNumberTable:
        line 47: 0
        line 49: 48
        line 50: 57
        line 52: 60
        line 53: 68
        line 55: 71
        line 56: 79
        line 58: 82
        line 59: 90
        line 61: 93
        line 62: 101
        line 64: 104
        line 66: 107
        line 68: 132
      LocalVariableTable:
        Start  Length  Slot  Name   Signature
            0     134     0  this   Lcoursier/util/shaded/org/jsoup/parser/XmlTreeBuilder;
            0     134     1 token   Lcoursier/util/shaded/org/jsoup/parser/Token;

  private void insertNode(coursier.util.shaded.org.jsoup.nodes.Node);
    descriptor: (Lcoursier/util/shaded/org/jsoup/nodes/Node;)V
    flags: (0x0002) ACC_PRIVATE
    Code:
      stack=2, locals=2, args_size=2
         0: aload_0
         1: invokevirtual #181                // Method currentElement:()Lcoursier/util/shaded/org/jsoup/nodes/Element;
         4: aload_1
         5: invokevirtual #187                // Method coursier/util/shaded/org/jsoup/nodes/Element.appendChild:(Lcoursier/util/shaded/org/jsoup/nodes/Node;)Lcoursier/util/shaded/org/jsoup/nodes/Element;
         8: pop
         9: return
      LineNumberTable:
        line 72: 0
        line 73: 9
      LocalVariableTable:
        Start  Length  Slot  Name   Signature
            0      10     0  this   Lcoursier/util/shaded/org/jsoup/parser/XmlTreeBuilder;
            0      10     1  node   Lcoursier/util/shaded/org/jsoup/nodes/Node;

  coursier.util.shaded.org.jsoup.nodes.Element insert(coursier.util.shaded.org.jsoup.parser.Token$StartTag);
    descriptor: (Lcoursier/util/shaded/org/jsoup/parser/Token$StartTag;)Lcoursier/util/shaded/org/jsoup/nodes/Element;
    flags: (0x0000)
    Code:
      stack=6, locals=4, args_size=2
         0: aload_1
         1: invokevirtual #192                // Method coursier/util/shaded/org/jsoup/parser/Token$StartTag.name:()Ljava/lang/String;
         4: aload_0
         5: getfield      #195                // Field settings:Lcoursier/util/shaded/org/jsoup/parser/ParseSettings;
         8: invokestatic  #201                // Method coursier/util/shaded/org/jsoup/parser/Tag.valueOf:(Ljava/lang/String;Lcoursier/util/shaded/org/jsoup/parser/ParseSettings;)Lcoursier/util/shaded/org/jsoup/parser/Tag;
        11: astore_2
        12: aload_1
        13: getfield      #205                // Field coursier/util/shaded/org/jsoup/parser/Token$StartTag.attributes:Lcoursier/util/shaded/org/jsoup/nodes/Attributes;
        16: ifnull        31
        19: aload_1
        20: getfield      #205                // Field coursier/util/shaded/org/jsoup/parser/Token$StartTag.attributes:Lcoursier/util/shaded/org/jsoup/nodes/Attributes;
        23: aload_0
        24: getfield      #195                // Field settings:Lcoursier/util/shaded/org/jsoup/parser/ParseSettings;
        27: invokevirtual #211                // Method coursier/util/shaded/org/jsoup/nodes/Attributes.deduplicate:(Lcoursier/util/shaded/org/jsoup/parser/ParseSettings;)I
        30: pop
        31: new           #183                // class coursier/util/shaded/org/jsoup/nodes/Element
        34: dup
        35: aload_2
        36: aconst_null
        37: aload_0
        38: getfield      #195                // Field settings:Lcoursier/util/shaded/org/jsoup/parser/ParseSettings;
        41: aload_1
        42: getfield      #205                // Field coursier/util/shaded/org/jsoup/parser/Token$StartTag.attributes:Lcoursier/util/shaded/org/jsoup/nodes/Attributes;
        45: invokevirtual #215                // Method coursier/util/shaded/org/jsoup/parser/ParseSettings.normalizeAttributes:(Lcoursier/util/shaded/org/jsoup/nodes/Attributes;)Lcoursier/util/shaded/org/jsoup/nodes/Attributes;
        48: invokespecial #218                // Method coursier/util/shaded/org/jsoup/nodes/Element."<init>":(Lcoursier/util/shaded/org/jsoup/parser/Tag;Ljava/lang/String;Lcoursier/util/shaded/org/jsoup/nodes/Attributes;)V
        51: astore_3
        52: aload_0
        53: aload_3
        54: invokespecial #220                // Method insertNode:(Lcoursier/util/shaded/org/jsoup/nodes/Node;)V
        57: aload_1
        58: invokevirtual #224                // Method coursier/util/shaded/org/jsoup/parser/Token$StartTag.isSelfClosing:()Z
        61: ifeq          79
        64: aload_2
        65: invokevirtual #227                // Method coursier/util/shaded/org/jsoup/parser/Tag.isKnownTag:()Z
        68: ifne          88
        71: aload_2
        72: invokevirtual #231                // Method coursier/util/shaded/org/jsoup/parser/Tag.setSelfClosing:()Lcoursier/util/shaded/org/jsoup/parser/Tag;
        75: pop
        76: goto          88
        79: aload_0
        80: getfield      #57                 // Field stack:Ljava/util/ArrayList;
        83: aload_3
        84: invokevirtual #67                 // Method java/util/ArrayList.add:(Ljava/lang/Object;)Z
        87: pop
        88: aload_3
        89: areturn
      StackMapTable: number_of_entries = 3
        frame_type = 252 /* append */
          offset_delta = 31
          locals = [ class coursier/util/shaded/org/jsoup/parser/Tag ]
        frame_type = 252 /* append */
          offset_delta = 47
          locals = [ class coursier/util/shaded/org/jsoup/nodes/Element ]
        frame_type = 8 /* same */
      LineNumberTable:
        line 76: 0
        line 78: 12
        line 79: 19
        line 81: 31
        line 82: 52
        line 83: 57
        line 84: 64
        line 85: 71
        line 87: 79
        line 89: 88
      LocalVariableTable:
        Start  Length  Slot  Name   Signature
            0      90     0  this   Lcoursier/util/shaded/org/jsoup/parser/XmlTreeBuilder;
            0      90     1 startTag   Lcoursier/util/shaded/org/jsoup/parser/Token$StartTag;
           12      78     2   tag   Lcoursier/util/shaded/org/jsoup/parser/Tag;
           52      38     3    el   Lcoursier/util/shaded/org/jsoup/nodes/Element;

  void insert(coursier.util.shaded.org.jsoup.parser.Token$Comment);
    descriptor: (Lcoursier/util/shaded/org/jsoup/parser/Token$Comment;)V
    flags: (0x0000)
    Code:
      stack=3, locals=5, args_size=2
         0: new           #239                // class coursier/util/shaded/org/jsoup/nodes/Comment
         3: dup
         4: aload_1
         5: invokevirtual #242                // Method coursier/util/shaded/org/jsoup/parser/Token$Comment.getData:()Ljava/lang/String;
         8: invokespecial #243                // Method coursier/util/shaded/org/jsoup/nodes/Comment."<init>":(Ljava/lang/String;)V
        11: astore_2
        12: aload_2
        13: astore_3
        14: aload_1
        15: getfield      #247                // Field coursier/util/shaded/org/jsoup/parser/Token$Comment.bogus:Z
        18: ifeq          42
        21: aload_2
        22: invokevirtual #250                // Method coursier/util/shaded/org/jsoup/nodes/Comment.isXmlDeclaration:()Z
        25: ifeq          42
        28: aload_2
        29: invokevirtual #254                // Method coursier/util/shaded/org/jsoup/nodes/Comment.asXmlDeclaration:()Lcoursier/util/shaded/org/jsoup/nodes/XmlDeclaration;
        32: astore        4
        34: aload         4
        36: ifnull        42
        39: aload         4
        41: astore_3
        42: aload_0
        43: aload_3
        44: invokespecial #220                // Method insertNode:(Lcoursier/util/shaded/org/jsoup/nodes/Node;)V
        47: return
      StackMapTable: number_of_entries = 1
        frame_type = 253 /* append */
          offset_delta = 42
          locals = [ class coursier/util/shaded/org/jsoup/nodes/Comment, class coursier/util/shaded/org/jsoup/nodes/Node ]
      LineNumberTable:
        line 93: 0
        line 94: 12
        line 95: 14
        line 98: 28
        line 99: 34
        line 100: 39
        line 102: 42
        line 103: 47
      LocalVariableTable:
        Start  Length  Slot  Name   Signature
           34       8     4  decl   Lcoursier/util/shaded/org/jsoup/nodes/XmlDeclaration;
            0      48     0  this   Lcoursier/util/shaded/org/jsoup/parser/XmlTreeBuilder;
            0      48     1 commentToken   Lcoursier/util/shaded/org/jsoup/parser/Token$Comment;
           12      36     2 comment   Lcoursier/util/shaded/org/jsoup/nodes/Comment;
           14      34     3 insert   Lcoursier/util/shaded/org/jsoup/nodes/Node;

  void insert(coursier.util.shaded.org.jsoup.parser.Token$Character);
    descriptor: (Lcoursier/util/shaded/org/jsoup/parser/Token$Character;)V
    flags: (0x0000)
    Code:
      stack=4, locals=3, args_size=2
         0: aload_1
         1: invokevirtual #263                // Method coursier/util/shaded/org/jsoup/parser/Token$Character.getData:()Ljava/lang/String;
         4: astore_2
         5: aload_0
         6: aload_1
         7: invokevirtual #266                // Method coursier/util/shaded/org/jsoup/parser/Token$Character.isCData:()Z
        10: ifeq          24
        13: new           #268                // class coursier/util/shaded/org/jsoup/nodes/CDataNode
        16: dup
        17: aload_2
        18: invokespecial #269                // Method coursier/util/shaded/org/jsoup/nodes/CDataNode."<init>":(Ljava/lang/String;)V
        21: goto          32
        24: new           #273                // class coursier/util/shaded/org/jsoup/nodes/TextNode
        27: dup
        28: aload_2
        29: invokespecial #274                // Method coursier/util/shaded/org/jsoup/nodes/TextNode."<init>":(Ljava/lang/String;)V
        32: invokespecial #220                // Method insertNode:(Lcoursier/util/shaded/org/jsoup/nodes/Node;)V
        35: return
      StackMapTable: number_of_entries = 2
        frame_type = 255 /* full_frame */
          offset_delta = 24
          locals = [ class coursier/util/shaded/org/jsoup/parser/XmlTreeBuilder, class coursier/util/shaded/org/jsoup/parser/Token$Character, class java/lang/String ]
          stack = [ class coursier/util/shaded/org/jsoup/parser/XmlTreeBuilder ]
        frame_type = 255 /* full_frame */
          offset_delta = 7
          locals = [ class coursier/util/shaded/org/jsoup/parser/XmlTreeBuilder, class coursier/util/shaded/org/jsoup/parser/Token$Character, class java/lang/String ]
          stack = [ class coursier/util/shaded/org/jsoup/parser/XmlTreeBuilder, class coursier/util/shaded/org/jsoup/nodes/TextNode ]
      LineNumberTable:
        line 106: 0
        line 107: 5
        line 108: 35
      LocalVariableTable:
        Start  Length  Slot  Name   Signature
            0      36     0  this   Lcoursier/util/shaded/org/jsoup/parser/XmlTreeBuilder;
            0      36     1 token   Lcoursier/util/shaded/org/jsoup/parser/Token$Character;
            5      31     2  data   Ljava/lang/String;

  void insert(coursier.util.shaded.org.jsoup.parser.Token$Doctype);
    descriptor: (Lcoursier/util/shaded/org/jsoup/parser/Token$Doctype;)V
    flags: (0x0000)
    Code:
      stack=5, locals=3, args_size=2
         0: new           #278                // class coursier/util/shaded/org/jsoup/nodes/DocumentType
         3: dup
         4: aload_0
         5: getfield      #195                // Field settings:Lcoursier/util/shaded/org/jsoup/parser/ParseSettings;
         8: aload_1
         9: invokevirtual #281                // Method coursier/util/shaded/org/jsoup/parser/Token$Doctype.getName:()Ljava/lang/String;
        12: invokevirtual #285                // Method coursier/util/shaded/org/jsoup/parser/ParseSettings.normalizeTag:(Ljava/lang/String;)Ljava/lang/String;
        15: aload_1
        16: invokevirtual #288                // Method coursier/util/shaded/org/jsoup/parser/Token$Doctype.getPublicIdentifier:()Ljava/lang/String;
        19: aload_1
        20: invokevirtual #291                // Method coursier/util/shaded/org/jsoup/parser/Token$Doctype.getSystemIdentifier:()Ljava/lang/String;
        23: invokespecial #294                // Method coursier/util/shaded/org/jsoup/nodes/DocumentType."<init>":(Ljava/lang/String;Ljava/lang/String;Ljava/lang/String;)V
        26: astore_2
        27: aload_2
        28: aload_1
        29: invokevirtual #297                // Method coursier/util/shaded/org/jsoup/parser/Token$Doctype.getPubSysKey:()Ljava/lang/String;
        32: invokevirtual #300                // Method coursier/util/shaded/org/jsoup/nodes/DocumentType.setPubSysKey:(Ljava/lang/String;)V
        35: aload_0
        36: aload_2
        37: invokespecial #220                // Method insertNode:(Lcoursier/util/shaded/org/jsoup/nodes/Node;)V
        40: return
      LineNumberTable:
        line 111: 0
        line 112: 27
        line 113: 35
        line 114: 40
      LocalVariableTable:
        Start  Length  Slot  Name   Signature
            0      41     0  this   Lcoursier/util/shaded/org/jsoup/parser/XmlTreeBuilder;
            0      41     1     d   Lcoursier/util/shaded/org/jsoup/parser/Token$Doctype;
           27      14     2 doctypeNode   Lcoursier/util/shaded/org/jsoup/nodes/DocumentType;

  private void popStackToClose(coursier.util.shaded.org.jsoup.parser.Token$EndTag);
    descriptor: (Lcoursier/util/shaded/org/jsoup/parser/Token$EndTag;)V
    flags: (0x0002) ACC_PRIVATE
    Code:
      stack=2, locals=6, args_size=2
         0: aload_0
         1: getfield      #195                // Field settings:Lcoursier/util/shaded/org/jsoup/parser/ParseSettings;
         4: aload_1
         5: getfield      #307                // Field coursier/util/shaded/org/jsoup/parser/Token$EndTag.tagName:Ljava/lang/String;
         8: invokevirtual #285                // Method coursier/util/shaded/org/jsoup/parser/ParseSettings.normalizeTag:(Ljava/lang/String;)Ljava/lang/String;
        11: astore_2
        12: aconst_null
        13: astore_3
        14: aload_0
        15: getfield      #57                 // Field stack:Ljava/util/ArrayList;
        18: invokevirtual #310                // Method java/util/ArrayList.size:()I
        21: iconst_1
        22: isub
        23: istore        4
        25: iload         4
        27: iflt          68
        30: aload_0
        31: getfield      #57                 // Field stack:Ljava/util/ArrayList;
        34: iload         4
        36: invokevirtual #314                // Method java/util/ArrayList.get:(I)Ljava/lang/Object;
        39: checkcast     #183                // class coursier/util/shaded/org/jsoup/nodes/Element
        42: astore        5
        44: aload         5
        46: invokevirtual #317                // Method coursier/util/shaded/org/jsoup/nodes/Element.nodeName:()Ljava/lang/String;
        49: aload_2
        50: invokevirtual #320                // Method java/lang/String.equals:(Ljava/lang/Object;)Z
        53: ifeq          62
        56: aload         5
        58: astore_3
        59: goto          68
        62: iinc          4, -1
        65: goto          25
        68: aload_3
        69: ifnonnull     73
        72: return
        73: aload_0
        74: getfield      #57                 // Field stack:Ljava/util/ArrayList;
        77: invokevirtual #310                // Method java/util/ArrayList.size:()I
        80: iconst_1
        81: isub
        82: istore        4
        84: iload         4
        86: iflt          128
        89: aload_0
        90: getfield      #57                 // Field stack:Ljava/util/ArrayList;
        93: iload         4
        95: invokevirtual #314                // Method java/util/ArrayList.get:(I)Ljava/lang/Object;
        98: checkcast     #183                // class coursier/util/shaded/org/jsoup/nodes/Element
       101: astore        5
       103: aload_0
       104: getfield      #57                 // Field stack:Ljava/util/ArrayList;
       107: iload         4
       109: invokevirtual #323                // Method java/util/ArrayList.remove:(I)Ljava/lang/Object;
       112: pop
       113: aload         5
       115: aload_3
       116: if_acmpne     122
       119: goto          128
       122: iinc          4, -1
       125: goto          84
       128: return
      StackMapTable: number_of_entries = 7
        frame_type = 254 /* append */
          offset_delta = 25
          locals = [ class java/lang/String, class coursier/util/shaded/org/jsoup/nodes/Element, int ]
        frame_type = 36 /* same */
        frame_type = 250 /* chop */
          offset_delta = 5
        frame_type = 4 /* same */
        frame_type = 252 /* append */
          offset_delta = 10
          locals = [ int ]
        frame_type = 37 /* same */
        frame_type = 250 /* chop */
          offset_delta = 5
      LineNumberTable:
        line 123: 0
        line 124: 12
        line 126: 14
        line 127: 30
        line 128: 44
        line 129: 56
        line 130: 59
        line 126: 62
        line 133: 68
        line 134: 72
        line 136: 73
        line 137: 89
        line 138: 103
        line 139: 113
        line 140: 119
        line 136: 122
        line 142: 128
      LocalVariableTable:
        Start  Length  Slot  Name   Signature
           44      18     5  next   Lcoursier/util/shaded/org/jsoup/nodes/Element;
           25      43     4   pos   I
          103      19     5  next   Lcoursier/util/shaded/org/jsoup/nodes/Element;
           84      44     4   pos   I
            0     129     0  this   Lcoursier/util/shaded/org/jsoup/parser/XmlTreeBuilder;
            0     129     1 endTag   Lcoursier/util/shaded/org/jsoup/parser/Token$EndTag;
           12     117     2 elName   Ljava/lang/String;
           14     115     3 firstFound   Lcoursier/util/shaded/org/jsoup/nodes/Element;

  java.util.List<coursier.util.shaded.org.jsoup.nodes.Node> parseFragment(java.lang.String, java.lang.String, coursier.util.shaded.org.jsoup.parser.Parser);
    descriptor: (Ljava/lang/String;Ljava/lang/String;Lcoursier/util/shaded/org/jsoup/parser/Parser;)Ljava/util/List;
    flags: (0x0000)
    Code:
      stack=4, locals=4, args_size=4
         0: aload_0
         1: new           #98                 // class java/io/StringReader
         4: dup
         5: aload_1
         6: invokespecial #101                // Method java/io/StringReader."<init>":(Ljava/lang/String;)V
         9: aload_2
        10: aload_3
        11: invokevirtual #334                // Method initialiseParse:(Ljava/io/Reader;Ljava/lang/String;Lcoursier/util/shaded/org/jsoup/parser/Parser;)V
        14: aload_0
        15: invokevirtual #337                // Method runParser:()V
        18: aload_0
        19: getfield      #61                 // Field doc:Lcoursier/util/shaded/org/jsoup/nodes/Document;
        22: invokevirtual #341                // Method coursier/util/shaded/org/jsoup/nodes/Document.childNodes:()Ljava/util/List;
        25: areturn
      LineNumberTable:
        line 146: 0
        line 147: 14
        line 148: 18
      LocalVariableTable:
        Start  Length  Slot  Name   Signature
            0      26     0  this   Lcoursier/util/shaded/org/jsoup/parser/XmlTreeBuilder;
            0      26     1 inputFragment   Ljava/lang/String;
            0      26     2 baseUri   Ljava/lang/String;
            0      26     3 parser   Lcoursier/util/shaded/org/jsoup/parser/Parser;
    Signature: #333                         // (Ljava/lang/String;Ljava/lang/String;Lcoursier/util/shaded/org/jsoup/parser/Parser;)Ljava/util/List<Lcoursier/util/shaded/org/jsoup/nodes/Node;>;

  java.util.List<coursier.util.shaded.org.jsoup.nodes.Node> parseFragment(java.lang.String, coursier.util.shaded.org.jsoup.nodes.Element, java.lang.String, coursier.util.shaded.org.jsoup.parser.Parser);
    descriptor: (Ljava/lang/String;Lcoursier/util/shaded/org/jsoup/nodes/Element;Ljava/lang/String;Lcoursier/util/shaded/org/jsoup/parser/Parser;)Ljava/util/List;
    flags: (0x0000)
    Code:
      stack=4, locals=5, args_size=5
         0: aload_0
         1: aload_1
         2: aload_3
         3: aload         4
         5: invokevirtual #346                // Method parseFragment:(Ljava/lang/String;Ljava/lang/String;Lcoursier/util/shaded/org/jsoup/parser/Parser;)Ljava/util/List;
         8: areturn
      LineNumberTable:
        line 152: 0
      LocalVariableTable:
        Start  Length  Slot  Name   Signature
            0       9     0  this   Lcoursier/util/shaded/org/jsoup/parser/XmlTreeBuilder;
            0       9     1 inputFragment   Ljava/lang/String;
            0       9     2 context   Lcoursier/util/shaded/org/jsoup/nodes/Element;
            0       9     3 baseUri   Ljava/lang/String;
            0       9     4 parser   Lcoursier/util/shaded/org/jsoup/parser/Parser;
    Signature: #344                         // (Ljava/lang/String;Lcoursier/util/shaded/org/jsoup/nodes/Element;Ljava/lang/String;Lcoursier/util/shaded/org/jsoup/parser/Parser;)Ljava/util/List<Lcoursier/util/shaded/org/jsoup/nodes/Node;>;

  public boolean processStartTag(java.lang.String, coursier.util.shaded.org.jsoup.nodes.Attributes);
    descriptor: (Ljava/lang/String;Lcoursier/util/shaded/org/jsoup/nodes/Attributes;)Z
    flags: (0x1041) ACC_PUBLIC, ACC_BRIDGE, ACC_SYNTHETIC
    Code:
      stack=3, locals=3, args_size=3
         0: aload_0
         1: aload_1
         2: aload_2
         3: invokespecial #351                // Method coursier/util/shaded/org/jsoup/parser/TreeBuilder.processStartTag:(Ljava/lang/String;Lcoursier/util/shaded/org/jsoup/nodes/Attributes;)Z
         6: ireturn
      LineNumberTable:
        line 24: 0
      LocalVariableTable:
        Start  Length  Slot  Name   Signature
            0       7     0  this   Lcoursier/util/shaded/org/jsoup/parser/XmlTreeBuilder;
}
InnerClasses:
  public static #10= #7 of #9;            // OutputSettings=class coursier/util/shaded/org/jsoup/nodes/Document$OutputSettings of class coursier/util/shaded/org/jsoup/nodes/Document
  public static final #13= #12 of #7;     // Syntax=class coursier/util/shaded/org/jsoup/nodes/Document$OutputSettings$Syntax of class coursier/util/shaded/org/jsoup/nodes/Document$OutputSettings
  static #15;                             // class coursier/util/shaded/org/jsoup/parser/XmlTreeBuilder$1
  public static final #20= #17 of #19;    // TokenType=class coursier/util/shaded/org/jsoup/parser/Token$TokenType of class coursier/util/shaded/org/jsoup/parser/Token
  static final #23= #22 of #19;           // StartTag=class coursier/util/shaded/org/jsoup/parser/Token$StartTag of class coursier/util/shaded/org/jsoup/parser/Token
  static final #26= #25 of #19;           // EndTag=class coursier/util/shaded/org/jsoup/parser/Token$EndTag of class coursier/util/shaded/org/jsoup/parser/Token
  static final #29= #28 of #19;           // Comment=class coursier/util/shaded/org/jsoup/parser/Token$Comment of class coursier/util/shaded/org/jsoup/parser/Token
  static #32= #31 of #19;                 // Character=class coursier/util/shaded/org/jsoup/parser/Token$Character of class coursier/util/shaded/org/jsoup/parser/Token
  static final #35= #34 of #19;           // Doctype=class coursier/util/shaded/org/jsoup/parser/Token$Doctype of class coursier/util/shaded/org/jsoup/parser/Token
SourceFile: "XmlTreeBuilder.java"
