Classfile /Users/mw/Projects/slang-braindump/.jar/jar11/assemble/slang-braindump/assemble/content/META-INF/versions/11/org/kohsuke/github/extras/HttpClientGitHubConnector.class
  Last modified May 29, 2022; size 4799 bytes
  SHA-256 checksum 31116fa1c430464298074804f7472f9a706d6591bed9ec093d896d220db92fd3
  Compiled from "HttpClientGitHubConnector.java"
public class org.kohsuke.github.extras.HttpClientGitHubConnector implements org.kohsuke.github.connector.GitHubConnector
  minor version: 0
  major version: 55
  flags: (0x0021) ACC_PUBLIC, ACC_SUPER
  this_class: #46                         // org/kohsuke/github/extras/HttpClientGitHubConnector
  super_class: #47                        // java/lang/Object
  interfaces: 1, fields: 1, methods: 3, attributes: 3
Constant pool:
    #1 = Methodref          #96.#97       // java/net/http/HttpClient.newBuilder:()Ljava/net/http/HttpClient$Builder;
    #2 = Fieldref           #98.#99       // java/net/http/HttpClient$Redirect.NORMAL:Ljava/net/http/HttpClient$Redirect;
    #3 = InterfaceMethodref #100.#101     // java/net/http/HttpClient$Builder.followRedirects:(Ljava/net/http/HttpClient$Redirect;)Ljava/net/http/HttpClient$Builder;
    #4 = InterfaceMethodref #100.#102     // java/net/http/HttpClient$Builder.build:()Ljava/net/http/HttpClient;
    #5 = Methodref          #46.#103      // org/kohsuke/github/extras/HttpClientGitHubConnector."<init>":(Ljava/net/http/HttpClient;)V
    #6 = Methodref          #47.#104      // java/lang/Object."<init>":()V
    #7 = Fieldref           #46.#105      // org/kohsuke/github/extras/HttpClientGitHubConnector.client:Ljava/net/http/HttpClient;
    #8 = Methodref          #91.#106      // java/net/http/HttpRequest.newBuilder:()Ljava/net/http/HttpRequest$Builder;
    #9 = InterfaceMethodref #89.#107      // org/kohsuke/github/connector/GitHubConnectorRequest.url:()Ljava/net/URL;
   #10 = Methodref          #108.#109     // java/net/URL.toURI:()Ljava/net/URI;
   #11 = InterfaceMethodref #75.#110      // java/net/http/HttpRequest$Builder.uri:(Ljava/net/URI;)Ljava/net/http/HttpRequest$Builder;
   #12 = Class              #111          // java/net/URISyntaxException
   #13 = Class              #112          // java/io/IOException
   #14 = String             #113          // Invalid URL
   #15 = Methodref          #13.#114      // java/io/IOException."<init>":(Ljava/lang/String;Ljava/lang/Throwable;)V
   #16 = InterfaceMethodref #89.#115      // org/kohsuke/github/connector/GitHubConnectorRequest.allHeaders:()Ljava/util/Map;
   #17 = InterfaceMethodref #116.#117     // java/util/Map.entrySet:()Ljava/util/Set;
   #18 = InterfaceMethodref #118.#119     // java/util/Set.iterator:()Ljava/util/Iterator;
   #19 = InterfaceMethodref #90.#120      // java/util/Iterator.hasNext:()Z
   #20 = InterfaceMethodref #90.#121      // java/util/Iterator.next:()Ljava/lang/Object;
   #21 = Class              #122          // java/util/Map$Entry
   #22 = InterfaceMethodref #21.#123      // java/util/Map$Entry.getValue:()Ljava/lang/Object;
   #23 = Class              #124          // java/util/List
   #24 = InterfaceMethodref #21.#125      // java/util/Map$Entry.getKey:()Ljava/lang/Object;
   #25 = Class              #126          // java/lang/String
   #26 = String             #127          // ,
   #27 = Methodref          #25.#128      // java/lang/String.join:(Ljava/lang/CharSequence;Ljava/lang/Iterable;)Ljava/lang/String;
   #28 = InterfaceMethodref #75.#129      // java/net/http/HttpRequest$Builder.header:(Ljava/lang/String;Ljava/lang/String;)Ljava/net/http/HttpRequest$Builder;
   #29 = Methodref          #130.#131     // java/net/http/HttpRequest$BodyPublishers.noBody:()Ljava/net/http/HttpRequest$BodyPublisher;
   #30 = InterfaceMethodref #89.#132      // org/kohsuke/github/connector/GitHubConnectorRequest.hasBody:()Z
   #31 = InterfaceMethodref #89.#133      // org/kohsuke/github/connector/GitHubConnectorRequest.body:()Ljava/io/InputStream;
   #32 = Methodref          #134.#135     // org/apache/commons/io/IOUtils.toByteArray:(Ljava/io/InputStream;)[B
   #33 = Methodref          #130.#136     // java/net/http/HttpRequest$BodyPublishers.ofByteArray:([B)Ljava/net/http/HttpRequest$BodyPublisher;
   #34 = InterfaceMethodref #89.#137      // org/kohsuke/github/connector/GitHubConnectorRequest.method:()Ljava/lang/String;
   #35 = InterfaceMethodref #75.#138      // java/net/http/HttpRequest$Builder.method:(Ljava/lang/String;Ljava/net/http/HttpRequest$BodyPublisher;)Ljava/net/http/HttpRequest$Builder;
   #36 = InterfaceMethodref #75.#139      // java/net/http/HttpRequest$Builder.build:()Ljava/net/http/HttpRequest;
   #37 = Methodref          #140.#141     // java/net/http/HttpResponse$BodyHandlers.ofInputStream:()Ljava/net/http/HttpResponse$BodyHandler;
   #38 = Methodref          #96.#142      // java/net/http/HttpClient.send:(Ljava/net/http/HttpRequest;Ljava/net/http/HttpResponse$BodyHandler;)Ljava/net/http/HttpResponse;
   #39 = Class              #143          // org/kohsuke/github/extras/HttpClientGitHubConnector$HttpClientGitHubConnectorResponse
   #40 = Methodref          #39.#144      // org/kohsuke/github/extras/HttpClientGitHubConnector$HttpClientGitHubConnectorResponse."<init>":(Lorg/kohsuke/github/connector/GitHubConnectorRequest;Ljava/net/http/HttpResponse;)V
   #41 = Class              #145          // java/lang/InterruptedException
   #42 = Class              #146          // java/io/InterruptedIOException
   #43 = Methodref          #41.#147      // java/lang/InterruptedException.getMessage:()Ljava/lang/String;
   #44 = Methodref          #42.#148      // java/io/InterruptedIOException."<init>":(Ljava/lang/String;)V
   #45 = Methodref          #42.#149      // java/io/InterruptedIOException.initCause:(Ljava/lang/Throwable;)Ljava/lang/Throwable;
   #46 = Class              #150          // org/kohsuke/github/extras/HttpClientGitHubConnector
   #47 = Class              #151          // java/lang/Object
   #48 = Class              #152          // org/kohsuke/github/connector/GitHubConnector
   #49 = Utf8               HttpClientGitHubConnectorResponse
   #50 = Utf8               InnerClasses
   #51 = Utf8               client
   #52 = Utf8               Ljava/net/http/HttpClient;
   #53 = Utf8               <init>
   #54 = Utf8               ()V
   #55 = Utf8               Code
   #56 = Utf8               LineNumberTable
   #57 = Utf8               LocalVariableTable
   #58 = Utf8               this
   #59 = Utf8               Lorg/kohsuke/github/extras/HttpClientGitHubConnector;
   #60 = Utf8               (Ljava/net/http/HttpClient;)V
   #61 = Utf8               send
   #62 = Utf8               (Lorg/kohsuke/github/connector/GitHubConnectorRequest;)Lorg/kohsuke/github/connector/GitHubConnectorResponse;
   #63 = Utf8               e
   #64 = Utf8               Ljava/net/URISyntaxException;
   #65 = Utf8               v
   #66 = Utf8               Ljava/util/List;
   #67 = Utf8               Entry
   #68 = Utf8               Ljava/util/Map$Entry;
   #69 = Utf8               httpResponse
   #70 = Utf8               Ljava/net/http/HttpResponse;
   #71 = Utf8               Ljava/lang/InterruptedException;
   #72 = Utf8               connectorRequest
   #73 = Utf8               Lorg/kohsuke/github/connector/GitHubConnectorRequest;
   #74 = Utf8               builder
   #75 = Class              #153          // java/net/http/HttpRequest$Builder
   #76 = Utf8               Builder
   #77 = Utf8               Ljava/net/http/HttpRequest$Builder;
   #78 = Utf8               publisher
   #79 = Class              #154          // java/net/http/HttpRequest$BodyPublisher
   #80 = Utf8               BodyPublisher
   #81 = Utf8               Ljava/net/http/HttpRequest$BodyPublisher;
   #82 = Utf8               request
   #83 = Utf8               Ljava/net/http/HttpRequest;
   #84 = Utf8               LocalVariableTypeTable
   #85 = Utf8               Ljava/util/List<Ljava/lang/String;>;
   #86 = Utf8               Ljava/util/Map$Entry<Ljava/lang/String;Ljava/util/List<Ljava/lang/String;>;>;
   #87 = Utf8               Ljava/net/http/HttpResponse<Ljava/io/InputStream;>;
   #88 = Utf8               StackMapTable
   #89 = Class              #155          // org/kohsuke/github/connector/GitHubConnectorRequest
   #90 = Class              #156          // java/util/Iterator
   #91 = Class              #157          // java/net/http/HttpRequest
   #92 = Utf8               Exceptions
   #93 = Utf8               SourceFile
   #94 = Utf8               HttpClientGitHubConnector.java
   #95 = Utf8               NestMembers
   #96 = Class              #158          // java/net/http/HttpClient
   #97 = NameAndType        #159:#160     // newBuilder:()Ljava/net/http/HttpClient$Builder;
   #98 = Class              #161          // java/net/http/HttpClient$Redirect
   #99 = NameAndType        #163:#164     // NORMAL:Ljava/net/http/HttpClient$Redirect;
  #100 = Class              #165          // java/net/http/HttpClient$Builder
  #101 = NameAndType        #166:#167     // followRedirects:(Ljava/net/http/HttpClient$Redirect;)Ljava/net/http/HttpClient$Builder;
  #102 = NameAndType        #168:#169     // build:()Ljava/net/http/HttpClient;
  #103 = NameAndType        #53:#60       // "<init>":(Ljava/net/http/HttpClient;)V
  #104 = NameAndType        #53:#54       // "<init>":()V
  #105 = NameAndType        #51:#52       // client:Ljava/net/http/HttpClient;
  #106 = NameAndType        #159:#170     // newBuilder:()Ljava/net/http/HttpRequest$Builder;
  #107 = NameAndType        #171:#172     // url:()Ljava/net/URL;
  #108 = Class              #173          // java/net/URL
  #109 = NameAndType        #174:#175     // toURI:()Ljava/net/URI;
  #110 = NameAndType        #176:#177     // uri:(Ljava/net/URI;)Ljava/net/http/HttpRequest$Builder;
  #111 = Utf8               java/net/URISyntaxException
  #112 = Utf8               java/io/IOException
  #113 = Utf8               Invalid URL
  #114 = NameAndType        #53:#178      // "<init>":(Ljava/lang/String;Ljava/lang/Throwable;)V
  #115 = NameAndType        #179:#180     // allHeaders:()Ljava/util/Map;
  #116 = Class              #181          // java/util/Map
  #117 = NameAndType        #182:#183     // entrySet:()Ljava/util/Set;
  #118 = Class              #184          // java/util/Set
  #119 = NameAndType        #185:#186     // iterator:()Ljava/util/Iterator;
  #120 = NameAndType        #187:#188     // hasNext:()Z
  #121 = NameAndType        #189:#190     // next:()Ljava/lang/Object;
  #122 = Utf8               java/util/Map$Entry
  #123 = NameAndType        #191:#190     // getValue:()Ljava/lang/Object;
  #124 = Utf8               java/util/List
  #125 = NameAndType        #192:#190     // getKey:()Ljava/lang/Object;
  #126 = Utf8               java/lang/String
  #127 = Utf8               ,
  #128 = NameAndType        #193:#194     // join:(Ljava/lang/CharSequence;Ljava/lang/Iterable;)Ljava/lang/String;
  #129 = NameAndType        #195:#196     // header:(Ljava/lang/String;Ljava/lang/String;)Ljava/net/http/HttpRequest$Builder;
  #130 = Class              #197          // java/net/http/HttpRequest$BodyPublishers
  #131 = NameAndType        #199:#200     // noBody:()Ljava/net/http/HttpRequest$BodyPublisher;
  #132 = NameAndType        #201:#188     // hasBody:()Z
  #133 = NameAndType        #202:#203     // body:()Ljava/io/InputStream;
  #134 = Class              #204          // org/apache/commons/io/IOUtils
  #135 = NameAndType        #205:#206     // toByteArray:(Ljava/io/InputStream;)[B
  #136 = NameAndType        #207:#208     // ofByteArray:([B)Ljava/net/http/HttpRequest$BodyPublisher;
  #137 = NameAndType        #209:#210     // method:()Ljava/lang/String;
  #138 = NameAndType        #209:#211     // method:(Ljava/lang/String;Ljava/net/http/HttpRequest$BodyPublisher;)Ljava/net/http/HttpRequest$Builder;
  #139 = NameAndType        #168:#212     // build:()Ljava/net/http/HttpRequest;
  #140 = Class              #214          // java/net/http/HttpResponse$BodyHandlers
  #141 = NameAndType        #216:#219     // ofInputStream:()Ljava/net/http/HttpResponse$BodyHandler;
  #142 = NameAndType        #61:#220      // send:(Ljava/net/http/HttpRequest;Ljava/net/http/HttpResponse$BodyHandler;)Ljava/net/http/HttpResponse;
  #143 = Utf8               org/kohsuke/github/extras/HttpClientGitHubConnector$HttpClientGitHubConnectorResponse
  #144 = NameAndType        #53:#221      // "<init>":(Lorg/kohsuke/github/connector/GitHubConnectorRequest;Ljava/net/http/HttpResponse;)V
  #145 = Utf8               java/lang/InterruptedException
  #146 = Utf8               java/io/InterruptedIOException
  #147 = NameAndType        #222:#210     // getMessage:()Ljava/lang/String;
  #148 = NameAndType        #53:#223      // "<init>":(Ljava/lang/String;)V
  #149 = NameAndType        #224:#225     // initCause:(Ljava/lang/Throwable;)Ljava/lang/Throwable;
  #150 = Utf8               org/kohsuke/github/extras/HttpClientGitHubConnector
  #151 = Utf8               java/lang/Object
  #152 = Utf8               org/kohsuke/github/connector/GitHubConnector
  #153 = Utf8               java/net/http/HttpRequest$Builder
  #154 = Utf8               java/net/http/HttpRequest$BodyPublisher
  #155 = Utf8               org/kohsuke/github/connector/GitHubConnectorRequest
  #156 = Utf8               java/util/Iterator
  #157 = Utf8               java/net/http/HttpRequest
  #158 = Utf8               java/net/http/HttpClient
  #159 = Utf8               newBuilder
  #160 = Utf8               ()Ljava/net/http/HttpClient$Builder;
  #161 = Utf8               java/net/http/HttpClient$Redirect
  #162 = Utf8               Redirect
  #163 = Utf8               NORMAL
  #164 = Utf8               Ljava/net/http/HttpClient$Redirect;
  #165 = Utf8               java/net/http/HttpClient$Builder
  #166 = Utf8               followRedirects
  #167 = Utf8               (Ljava/net/http/HttpClient$Redirect;)Ljava/net/http/HttpClient$Builder;
  #168 = Utf8               build
  #169 = Utf8               ()Ljava/net/http/HttpClient;
  #170 = Utf8               ()Ljava/net/http/HttpRequest$Builder;
  #171 = Utf8               url
  #172 = Utf8               ()Ljava/net/URL;
  #173 = Utf8               java/net/URL
  #174 = Utf8               toURI
  #175 = Utf8               ()Ljava/net/URI;
  #176 = Utf8               uri
  #177 = Utf8               (Ljava/net/URI;)Ljava/net/http/HttpRequest$Builder;
  #178 = Utf8               (Ljava/lang/String;Ljava/lang/Throwable;)V
  #179 = Utf8               allHeaders
  #180 = Utf8               ()Ljava/util/Map;
  #181 = Utf8               java/util/Map
  #182 = Utf8               entrySet
  #183 = Utf8               ()Ljava/util/Set;
  #184 = Utf8               java/util/Set
  #185 = Utf8               iterator
  #186 = Utf8               ()Ljava/util/Iterator;
  #187 = Utf8               hasNext
  #188 = Utf8               ()Z
  #189 = Utf8               next
  #190 = Utf8               ()Ljava/lang/Object;
  #191 = Utf8               getValue
  #192 = Utf8               getKey
  #193 = Utf8               join
  #194 = Utf8               (Ljava/lang/CharSequence;Ljava/lang/Iterable;)Ljava/lang/String;
  #195 = Utf8               header
  #196 = Utf8               (Ljava/lang/String;Ljava/lang/String;)Ljava/net/http/HttpRequest$Builder;
  #197 = Utf8               java/net/http/HttpRequest$BodyPublishers
  #198 = Utf8               BodyPublishers
  #199 = Utf8               noBody
  #200 = Utf8               ()Ljava/net/http/HttpRequest$BodyPublisher;
  #201 = Utf8               hasBody
  #202 = Utf8               body
  #203 = Utf8               ()Ljava/io/InputStream;
  #204 = Utf8               org/apache/commons/io/IOUtils
  #205 = Utf8               toByteArray
  #206 = Utf8               (Ljava/io/InputStream;)[B
  #207 = Utf8               ofByteArray
  #208 = Utf8               ([B)Ljava/net/http/HttpRequest$BodyPublisher;
  #209 = Utf8               method
  #210 = Utf8               ()Ljava/lang/String;
  #211 = Utf8               (Ljava/lang/String;Ljava/net/http/HttpRequest$BodyPublisher;)Ljava/net/http/HttpRequest$Builder;
  #212 = Utf8               ()Ljava/net/http/HttpRequest;
  #213 = Class              #226          // java/net/http/HttpResponse
  #214 = Utf8               java/net/http/HttpResponse$BodyHandlers
  #215 = Utf8               BodyHandlers
  #216 = Utf8               ofInputStream
  #217 = Class              #227          // java/net/http/HttpResponse$BodyHandler
  #218 = Utf8               BodyHandler
  #219 = Utf8               ()Ljava/net/http/HttpResponse$BodyHandler;
  #220 = Utf8               (Ljava/net/http/HttpRequest;Ljava/net/http/HttpResponse$BodyHandler;)Ljava/net/http/HttpResponse;
  #221 = Utf8               (Lorg/kohsuke/github/connector/GitHubConnectorRequest;Ljava/net/http/HttpResponse;)V
  #222 = Utf8               getMessage
  #223 = Utf8               (Ljava/lang/String;)V
  #224 = Utf8               initCause
  #225 = Utf8               (Ljava/lang/Throwable;)Ljava/lang/Throwable;
  #226 = Utf8               java/net/http/HttpResponse
  #227 = Utf8               java/net/http/HttpResponse$BodyHandler
{
  private final java.net.http.HttpClient client;
    descriptor: Ljava/net/http/HttpClient;
    flags: (0x0012) ACC_PRIVATE, ACC_FINAL

  public org.kohsuke.github.extras.HttpClientGitHubConnector();
    descriptor: ()V
    flags: (0x0001) ACC_PUBLIC
    Code:
      stack=3, locals=1, args_size=1
         0: aload_0
         1: invokestatic  #1                  // Method java/net/http/HttpClient.newBuilder:()Ljava/net/http/HttpClient$Builder;
         4: getstatic     #2                  // Field java/net/http/HttpClient$Redirect.NORMAL:Ljava/net/http/HttpClient$Redirect;
         7: invokeinterface #3,  2            // InterfaceMethod java/net/http/HttpClient$Builder.followRedirects:(Ljava/net/http/HttpClient$Redirect;)Ljava/net/http/HttpClient$Builder;
        12: invokeinterface #4,  1            // InterfaceMethod java/net/http/HttpClient$Builder.build:()Ljava/net/http/HttpClient;
        17: invokespecial #5                  // Method "<init>":(Ljava/net/http/HttpClient;)V
        20: return
      LineNumberTable:
        line 34: 0
        line 35: 20
      LocalVariableTable:
        Start  Length  Slot  Name   Signature
            0      21     0  this   Lorg/kohsuke/github/extras/HttpClientGitHubConnector;

  public org.kohsuke.github.extras.HttpClientGitHubConnector(java.net.http.HttpClient);
    descriptor: (Ljava/net/http/HttpClient;)V
    flags: (0x0001) ACC_PUBLIC
    Code:
      stack=2, locals=2, args_size=2
         0: aload_0
         1: invokespecial #6                  // Method java/lang/Object."<init>":()V
         4: aload_0
         5: aload_1
         6: putfield      #7                  // Field client:Ljava/net/http/HttpClient;
         9: return
      LineNumberTable:
        line 43: 0
        line 44: 4
        line 45: 9
      LocalVariableTable:
        Start  Length  Slot  Name   Signature
            0      10     0  this   Lorg/kohsuke/github/extras/HttpClientGitHubConnector;
            0      10     1 client   Ljava/net/http/HttpClient;

  public org.kohsuke.github.connector.GitHubConnectorResponse send(org.kohsuke.github.connector.GitHubConnectorRequest) throws java.io.IOException;
    descriptor: (Lorg/kohsuke/github/connector/GitHubConnectorRequest;)Lorg/kohsuke/github/connector/GitHubConnectorResponse;
    flags: (0x0001) ACC_PUBLIC
    Code:
      stack=4, locals=6, args_size=2
         0: invokestatic  #8                  // Method java/net/http/HttpRequest.newBuilder:()Ljava/net/http/HttpRequest$Builder;
         3: astore_2
         4: aload_2
         5: aload_1
         6: invokeinterface #9,  1            // InterfaceMethod org/kohsuke/github/connector/GitHubConnectorRequest.url:()Ljava/net/URL;
        11: invokevirtual #10                 // Method java/net/URL.toURI:()Ljava/net/URI;
        14: invokeinterface #11,  2           // InterfaceMethod java/net/http/HttpRequest$Builder.uri:(Ljava/net/URI;)Ljava/net/http/HttpRequest$Builder;
        19: pop
        20: goto          35
        23: astore_3
        24: new           #13                 // class java/io/IOException
        27: dup
        28: ldc           #14                 // String Invalid URL
        30: aload_3
        31: invokespecial #15                 // Method java/io/IOException."<init>":(Ljava/lang/String;Ljava/lang/Throwable;)V
        34: athrow
        35: aload_1
        36: invokeinterface #16,  1           // InterfaceMethod org/kohsuke/github/connector/GitHubConnectorRequest.allHeaders:()Ljava/util/Map;
        41: invokeinterface #17,  1           // InterfaceMethod java/util/Map.entrySet:()Ljava/util/Set;
        46: invokeinterface #18,  1           // InterfaceMethod java/util/Set.iterator:()Ljava/util/Iterator;
        51: astore_3
        52: aload_3
        53: invokeinterface #19,  1           // InterfaceMethod java/util/Iterator.hasNext:()Z
        58: ifeq          116
        61: aload_3
        62: invokeinterface #20,  1           // InterfaceMethod java/util/Iterator.next:()Ljava/lang/Object;
        67: checkcast     #21                 // class java/util/Map$Entry
        70: astore        4
        72: aload         4
        74: invokeinterface #22,  1           // InterfaceMethod java/util/Map$Entry.getValue:()Ljava/lang/Object;
        79: checkcast     #23                 // class java/util/List
        82: astore        5
        84: aload         5
        86: ifnull        113
        89: aload_2
        90: aload         4
        92: invokeinterface #24,  1           // InterfaceMethod java/util/Map$Entry.getKey:()Ljava/lang/Object;
        97: checkcast     #25                 // class java/lang/String
       100: ldc           #26                 // String ,
       102: aload         5
       104: invokestatic  #27                 // Method java/lang/String.join:(Ljava/lang/CharSequence;Ljava/lang/Iterable;)Ljava/lang/String;
       107: invokeinterface #28,  3           // InterfaceMethod java/net/http/HttpRequest$Builder.header:(Ljava/lang/String;Ljava/lang/String;)Ljava/net/http/HttpRequest$Builder;
       112: pop
       113: goto          52
       116: invokestatic  #29                 // Method java/net/http/HttpRequest$BodyPublishers.noBody:()Ljava/net/http/HttpRequest$BodyPublisher;
       119: astore_3
       120: aload_1
       121: invokeinterface #30,  1           // InterfaceMethod org/kohsuke/github/connector/GitHubConnectorRequest.hasBody:()Z
       126: ifeq          142
       129: aload_1
       130: invokeinterface #31,  1           // InterfaceMethod org/kohsuke/github/connector/GitHubConnectorRequest.body:()Ljava/io/InputStream;
       135: invokestatic  #32                 // Method org/apache/commons/io/IOUtils.toByteArray:(Ljava/io/InputStream;)[B
       138: invokestatic  #33                 // Method java/net/http/HttpRequest$BodyPublishers.ofByteArray:([B)Ljava/net/http/HttpRequest$BodyPublisher;
       141: astore_3
       142: aload_2
       143: aload_1
       144: invokeinterface #34,  1           // InterfaceMethod org/kohsuke/github/connector/GitHubConnectorRequest.method:()Ljava/lang/String;
       149: aload_3
       150: invokeinterface #35,  3           // InterfaceMethod java/net/http/HttpRequest$Builder.method:(Ljava/lang/String;Ljava/net/http/HttpRequest$BodyPublisher;)Ljava/net/http/HttpRequest$Builder;
       155: pop
       156: aload_2
       157: invokeinterface #36,  1           // InterfaceMethod java/net/http/HttpRequest$Builder.build:()Ljava/net/http/HttpRequest;
       162: astore        4
       164: aload_0
       165: getfield      #7                  // Field client:Ljava/net/http/HttpClient;
       168: aload         4
       170: invokestatic  #37                 // Method java/net/http/HttpResponse$BodyHandlers.ofInputStream:()Ljava/net/http/HttpResponse$BodyHandler;
       173: invokevirtual #38                 // Method java/net/http/HttpClient.send:(Ljava/net/http/HttpRequest;Ljava/net/http/HttpResponse$BodyHandler;)Ljava/net/http/HttpResponse;
       176: astore        5
       178: new           #39                 // class org/kohsuke/github/extras/HttpClientGitHubConnector$HttpClientGitHubConnectorResponse
       181: dup
       182: aload_1
       183: aload         5
       185: invokespecial #40                 // Method org/kohsuke/github/extras/HttpClientGitHubConnector$HttpClientGitHubConnectorResponse."<init>":(Lorg/kohsuke/github/connector/GitHubConnectorRequest;Ljava/net/http/HttpResponse;)V
       188: areturn
       189: astore        5
       191: new           #42                 // class java/io/InterruptedIOException
       194: dup
       195: aload         5
       197: invokevirtual #43                 // Method java/lang/InterruptedException.getMessage:()Ljava/lang/String;
       200: invokespecial #44                 // Method java/io/InterruptedIOException."<init>":(Ljava/lang/String;)V
       203: aload         5
       205: invokevirtual #45                 // Method java/io/InterruptedIOException.initCause:(Ljava/lang/Throwable;)Ljava/lang/Throwable;
       208: checkcast     #42                 // class java/io/InterruptedIOException
       211: athrow
      Exception table:
         from    to  target type
             4    20    23   Class java/net/URISyntaxException
           164   188   189   Class java/lang/InterruptedException
      LineNumberTable:
        line 49: 0
        line 51: 4
        line 54: 20
        line 52: 23
        line 53: 24
        line 56: 35
        line 57: 72
        line 58: 84
        line 59: 89
        line 61: 113
        line 63: 116
        line 64: 120
        line 65: 129
        line 67: 142
        line 69: 156
        line 72: 164
        line 73: 178
        line 74: 189
        line 75: 191
      LocalVariableTable:
        Start  Length  Slot  Name   Signature
           24      11     3     e   Ljava/net/URISyntaxException;
           84      29     5     v   Ljava/util/List;
           72      41     4     e   Ljava/util/Map$Entry;
          178      11     5 httpResponse   Ljava/net/http/HttpResponse;
          191      21     5     e   Ljava/lang/InterruptedException;
            0     212     0  this   Lorg/kohsuke/github/extras/HttpClientGitHubConnector;
            0     212     1 connectorRequest   Lorg/kohsuke/github/connector/GitHubConnectorRequest;
            4     208     2 builder   Ljava/net/http/HttpRequest$Builder;
          120      92     3 publisher   Ljava/net/http/HttpRequest$BodyPublisher;
          164      48     4 request   Ljava/net/http/HttpRequest;
      LocalVariableTypeTable:
        Start  Length  Slot  Name   Signature
           84      29     5     v   Ljava/util/List<Ljava/lang/String;>;
           72      41     4     e   Ljava/util/Map$Entry<Ljava/lang/String;Ljava/util/List<Ljava/lang/String;>;>;
          178      11     5 httpResponse   Ljava/net/http/HttpResponse<Ljava/io/InputStream;>;
      StackMapTable: number_of_entries = 7
        frame_type = 255 /* full_frame */
          offset_delta = 23
          locals = [ class org/kohsuke/github/extras/HttpClientGitHubConnector, class org/kohsuke/github/connector/GitHubConnectorRequest, class java/net/http/HttpRequest$Builder ]
          stack = [ class java/net/URISyntaxException ]
        frame_type = 11 /* same */
        frame_type = 252 /* append */
          offset_delta = 16
          locals = [ class java/util/Iterator ]
        frame_type = 60 /* same */
        frame_type = 250 /* chop */
          offset_delta = 2
        frame_type = 252 /* append */
          offset_delta = 25
          locals = [ class java/net/http/HttpRequest$BodyPublisher ]
        frame_type = 255 /* full_frame */
          offset_delta = 46
          locals = [ class org/kohsuke/github/extras/HttpClientGitHubConnector, class org/kohsuke/github/connector/GitHubConnectorRequest, class java/net/http/HttpRequest$Builder, class java/net/http/HttpRequest$BodyPublisher, class java/net/http/HttpRequest ]
          stack = [ class java/lang/InterruptedException ]
    Exceptions:
      throws java.io.IOException
}
SourceFile: "HttpClientGitHubConnector.java"
NestMembers:
  org/kohsuke/github/extras/HttpClientGitHubConnector$HttpClientGitHubConnectorResponse
InnerClasses:
  private static #49= #39 of #46;         // HttpClientGitHubConnectorResponse=class org/kohsuke/github/extras/HttpClientGitHubConnector$HttpClientGitHubConnectorResponse of class org/kohsuke/github/extras/HttpClientGitHubConnector
  public static #67= #21 of #116;         // Entry=class java/util/Map$Entry of class java/util/Map
  public static #76= #75 of #91;          // Builder=class java/net/http/HttpRequest$Builder of class java/net/http/HttpRequest
  public static #80= #79 of #91;          // BodyPublisher=class java/net/http/HttpRequest$BodyPublisher of class java/net/http/HttpRequest
  public static #76= #100 of #96;         // Builder=class java/net/http/HttpClient$Builder of class java/net/http/HttpClient
  public static final #162= #98 of #96;   // Redirect=class java/net/http/HttpClient$Redirect of class java/net/http/HttpClient
  public static #198= #130 of #91;        // BodyPublishers=class java/net/http/HttpRequest$BodyPublishers of class java/net/http/HttpRequest
  public static #215= #140 of #213;       // BodyHandlers=class java/net/http/HttpResponse$BodyHandlers of class java/net/http/HttpResponse
  public static #218= #217 of #213;       // BodyHandler=class java/net/http/HttpResponse$BodyHandler of class java/net/http/HttpResponse
