Classfile /Users/mw/Projects/slang-braindump/.jar/jar11/assemble/slang-braindump/assemble/content/com/fasterxml/jackson/annotation/Nulls.class
  Last modified May 29, 2022; size 1198 bytes
  SHA-256 checksum 78c177ce421632da33138d494151650d34e88580986789960bb1bd933a7fefd5
  Compiled from "Nulls.java"
public final class com.fasterxml.jackson.annotation.Nulls extends java.lang.Enum<com.fasterxml.jackson.annotation.Nulls>
  minor version: 0
  major version: 50
  flags: (0x4031) ACC_PUBLIC, ACC_FINAL, ACC_SUPER, ACC_ENUM
  this_class: #4                          // com/fasterxml/jackson/annotation/Nulls
  super_class: #18                        // java/lang/Enum
  interfaces: 0, fields: 6, methods: 4, attributes: 2
Constant pool:
   #1 = Fieldref           #4.#45         // com/fasterxml/jackson/annotation/Nulls.$VALUES:[Lcom/fasterxml/jackson/annotation/Nulls;
   #2 = Methodref          #46.#47        // "[Lcom/fasterxml/jackson/annotation/Nulls;".clone:()Ljava/lang/Object;
   #3 = Class              #26            // "[Lcom/fasterxml/jackson/annotation/Nulls;"
   #4 = Class              #48            // com/fasterxml/jackson/annotation/Nulls
   #5 = Methodref          #18.#49        // java/lang/Enum.valueOf:(Ljava/lang/Class;Ljava/lang/String;)Ljava/lang/Enum;
   #6 = Methodref          #18.#50        // java/lang/Enum."<init>":(Ljava/lang/String;I)V
   #7 = String             #19            // SET
   #8 = Methodref          #4.#50         // com/fasterxml/jackson/annotation/Nulls."<init>":(Ljava/lang/String;I)V
   #9 = Fieldref           #4.#51         // com/fasterxml/jackson/annotation/Nulls.SET:Lcom/fasterxml/jackson/annotation/Nulls;
  #10 = String             #21            // SKIP
  #11 = Fieldref           #4.#52         // com/fasterxml/jackson/annotation/Nulls.SKIP:Lcom/fasterxml/jackson/annotation/Nulls;
  #12 = String             #22            // FAIL
  #13 = Fieldref           #4.#53         // com/fasterxml/jackson/annotation/Nulls.FAIL:Lcom/fasterxml/jackson/annotation/Nulls;
  #14 = String             #23            // AS_EMPTY
  #15 = Fieldref           #4.#54         // com/fasterxml/jackson/annotation/Nulls.AS_EMPTY:Lcom/fasterxml/jackson/annotation/Nulls;
  #16 = String             #24            // DEFAULT
  #17 = Fieldref           #4.#55         // com/fasterxml/jackson/annotation/Nulls.DEFAULT:Lcom/fasterxml/jackson/annotation/Nulls;
  #18 = Class              #56            // java/lang/Enum
  #19 = Utf8               SET
  #20 = Utf8               Lcom/fasterxml/jackson/annotation/Nulls;
  #21 = Utf8               SKIP
  #22 = Utf8               FAIL
  #23 = Utf8               AS_EMPTY
  #24 = Utf8               DEFAULT
  #25 = Utf8               $VALUES
  #26 = Utf8               [Lcom/fasterxml/jackson/annotation/Nulls;
  #27 = Utf8               values
  #28 = Utf8               ()[Lcom/fasterxml/jackson/annotation/Nulls;
  #29 = Utf8               Code
  #30 = Utf8               LineNumberTable
  #31 = Utf8               valueOf
  #32 = Utf8               (Ljava/lang/String;)Lcom/fasterxml/jackson/annotation/Nulls;
  #33 = Utf8               LocalVariableTable
  #34 = Utf8               name
  #35 = Utf8               Ljava/lang/String;
  #36 = Utf8               <init>
  #37 = Utf8               (Ljava/lang/String;I)V
  #38 = Utf8               this
  #39 = Utf8               Signature
  #40 = Utf8               ()V
  #41 = Utf8               <clinit>
  #42 = Utf8               Ljava/lang/Enum<Lcom/fasterxml/jackson/annotation/Nulls;>;
  #43 = Utf8               SourceFile
  #44 = Utf8               Nulls.java
  #45 = NameAndType        #25:#26        // $VALUES:[Lcom/fasterxml/jackson/annotation/Nulls;
  #46 = Class              #26            // "[Lcom/fasterxml/jackson/annotation/Nulls;"
  #47 = NameAndType        #57:#58        // clone:()Ljava/lang/Object;
  #48 = Utf8               com/fasterxml/jackson/annotation/Nulls
  #49 = NameAndType        #31:#59        // valueOf:(Ljava/lang/Class;Ljava/lang/String;)Ljava/lang/Enum;
  #50 = NameAndType        #36:#37        // "<init>":(Ljava/lang/String;I)V
  #51 = NameAndType        #19:#20        // SET:Lcom/fasterxml/jackson/annotation/Nulls;
  #52 = NameAndType        #21:#20        // SKIP:Lcom/fasterxml/jackson/annotation/Nulls;
  #53 = NameAndType        #22:#20        // FAIL:Lcom/fasterxml/jackson/annotation/Nulls;
  #54 = NameAndType        #23:#20        // AS_EMPTY:Lcom/fasterxml/jackson/annotation/Nulls;
  #55 = NameAndType        #24:#20        // DEFAULT:Lcom/fasterxml/jackson/annotation/Nulls;
  #56 = Utf8               java/lang/Enum
  #57 = Utf8               clone
  #58 = Utf8               ()Ljava/lang/Object;
  #59 = Utf8               (Ljava/lang/Class;Ljava/lang/String;)Ljava/lang/Enum;
{
  public static final com.fasterxml.jackson.annotation.Nulls SET;
    descriptor: Lcom/fasterxml/jackson/annotation/Nulls;
    flags: (0x4019) ACC_PUBLIC, ACC_STATIC, ACC_FINAL, ACC_ENUM

  public static final com.fasterxml.jackson.annotation.Nulls SKIP;
    descriptor: Lcom/fasterxml/jackson/annotation/Nulls;
    flags: (0x4019) ACC_PUBLIC, ACC_STATIC, ACC_FINAL, ACC_ENUM

  public static final com.fasterxml.jackson.annotation.Nulls FAIL;
    descriptor: Lcom/fasterxml/jackson/annotation/Nulls;
    flags: (0x4019) ACC_PUBLIC, ACC_STATIC, ACC_FINAL, ACC_ENUM

  public static final com.fasterxml.jackson.annotation.Nulls AS_EMPTY;
    descriptor: Lcom/fasterxml/jackson/annotation/Nulls;
    flags: (0x4019) ACC_PUBLIC, ACC_STATIC, ACC_FINAL, ACC_ENUM

  public static final com.fasterxml.jackson.annotation.Nulls DEFAULT;
    descriptor: Lcom/fasterxml/jackson/annotation/Nulls;
    flags: (0x4019) ACC_PUBLIC, ACC_STATIC, ACC_FINAL, ACC_ENUM

  private static final com.fasterxml.jackson.annotation.Nulls[] $VALUES;
    descriptor: [Lcom/fasterxml/jackson/annotation/Nulls;
    flags: (0x101a) ACC_PRIVATE, ACC_STATIC, ACC_FINAL, ACC_SYNTHETIC

  public static com.fasterxml.jackson.annotation.Nulls[] values();
    descriptor: ()[Lcom/fasterxml/jackson/annotation/Nulls;
    flags: (0x0009) ACC_PUBLIC, ACC_STATIC
    Code:
      stack=1, locals=0, args_size=0
         0: getstatic     #1                  // Field $VALUES:[Lcom/fasterxml/jackson/annotation/Nulls;
         3: invokevirtual #2                  // Method "[Lcom/fasterxml/jackson/annotation/Nulls;".clone:()Ljava/lang/Object;
         6: checkcast     #3                  // class "[Lcom/fasterxml/jackson/annotation/Nulls;"
         9: areturn
      LineNumberTable:
        line 9: 0

  public static com.fasterxml.jackson.annotation.Nulls valueOf(java.lang.String);
    descriptor: (Ljava/lang/String;)Lcom/fasterxml/jackson/annotation/Nulls;
    flags: (0x0009) ACC_PUBLIC, ACC_STATIC
    Code:
      stack=2, locals=1, args_size=1
         0: ldc           #4                  // class com/fasterxml/jackson/annotation/Nulls
         2: aload_0
         3: invokestatic  #5                  // Method java/lang/Enum.valueOf:(Ljava/lang/Class;Ljava/lang/String;)Ljava/lang/Enum;
         6: checkcast     #4                  // class com/fasterxml/jackson/annotation/Nulls
         9: areturn
      LineNumberTable:
        line 9: 0
      LocalVariableTable:
        Start  Length  Slot  Name   Signature
            0      10     0  name   Ljava/lang/String;

  private com.fasterxml.jackson.annotation.Nulls();
    descriptor: (Ljava/lang/String;I)V
    flags: (0x0002) ACC_PRIVATE
    Code:
      stack=3, locals=3, args_size=3
         0: aload_0
         1: aload_1
         2: iload_2
         3: invokespecial #6                  // Method java/lang/Enum."<init>":(Ljava/lang/String;I)V
         6: return
      LineNumberTable:
        line 9: 0
      LocalVariableTable:
        Start  Length  Slot  Name   Signature
            0       7     0  this   Lcom/fasterxml/jackson/annotation/Nulls;
    Signature: #40                          // ()V

  static {};
    descriptor: ()V
    flags: (0x0008) ACC_STATIC
    Code:
      stack=4, locals=0, args_size=0
         0: new           #4                  // class com/fasterxml/jackson/annotation/Nulls
         3: dup
         4: ldc           #7                  // String SET
         6: iconst_0
         7: invokespecial #8                  // Method "<init>":(Ljava/lang/String;I)V
        10: putstatic     #9                  // Field SET:Lcom/fasterxml/jackson/annotation/Nulls;
        13: new           #4                  // class com/fasterxml/jackson/annotation/Nulls
        16: dup
        17: ldc           #10                 // String SKIP
        19: iconst_1
        20: invokespecial #8                  // Method "<init>":(Ljava/lang/String;I)V
        23: putstatic     #11                 // Field SKIP:Lcom/fasterxml/jackson/annotation/Nulls;
        26: new           #4                  // class com/fasterxml/jackson/annotation/Nulls
        29: dup
        30: ldc           #12                 // String FAIL
        32: iconst_2
        33: invokespecial #8                  // Method "<init>":(Ljava/lang/String;I)V
        36: putstatic     #13                 // Field FAIL:Lcom/fasterxml/jackson/annotation/Nulls;
        39: new           #4                  // class com/fasterxml/jackson/annotation/Nulls
        42: dup
        43: ldc           #14                 // String AS_EMPTY
        45: iconst_3
        46: invokespecial #8                  // Method "<init>":(Ljava/lang/String;I)V
        49: putstatic     #15                 // Field AS_EMPTY:Lcom/fasterxml/jackson/annotation/Nulls;
        52: new           #4                  // class com/fasterxml/jackson/annotation/Nulls
        55: dup
        56: ldc           #16                 // String DEFAULT
        58: iconst_4
        59: invokespecial #8                  // Method "<init>":(Ljava/lang/String;I)V
        62: putstatic     #17                 // Field DEFAULT:Lcom/fasterxml/jackson/annotation/Nulls;
        65: iconst_5
        66: anewarray     #4                  // class com/fasterxml/jackson/annotation/Nulls
        69: dup
        70: iconst_0
        71: getstatic     #9                  // Field SET:Lcom/fasterxml/jackson/annotation/Nulls;
        74: aastore
        75: dup
        76: iconst_1
        77: getstatic     #11                 // Field SKIP:Lcom/fasterxml/jackson/annotation/Nulls;
        80: aastore
        81: dup
        82: iconst_2
        83: getstatic     #13                 // Field FAIL:Lcom/fasterxml/jackson/annotation/Nulls;
        86: aastore
        87: dup
        88: iconst_3
        89: getstatic     #15                 // Field AS_EMPTY:Lcom/fasterxml/jackson/annotation/Nulls;
        92: aastore
        93: dup
        94: iconst_4
        95: getstatic     #17                 // Field DEFAULT:Lcom/fasterxml/jackson/annotation/Nulls;
        98: aastore
        99: putstatic     #1                  // Field $VALUES:[Lcom/fasterxml/jackson/annotation/Nulls;
       102: return
      LineNumberTable:
        line 17: 0
        line 24: 13
        line 30: 26
        line 36: 39
        line 42: 52
        line 9: 65
}
Signature: #42                          // Ljava/lang/Enum<Lcom/fasterxml/jackson/annotation/Nulls;>;
SourceFile: "Nulls.java"
