Classfile /Users/mw/Projects/slang-braindump/.jar/jar11/assemble/slang-braindump/assemble/content/com/fasterxml/jackson/annotation/ObjectIdGenerator.class
  Last modified May 29, 2022; size 1779 bytes
  SHA-256 checksum 783bb0e6bb14d70e5a4c7a1b56fc9e0d2fdab2730532e938d9335f13de74733c
  Compiled from "ObjectIdGenerator.java"
public abstract class com.fasterxml.jackson.annotation.ObjectIdGenerator<T extends java.lang.Object> extends java.lang.Object implements java.io.Serializable
  minor version: 0
  major version: 50
  flags: (0x0421) ACC_PUBLIC, ACC_SUPER, ACC_ABSTRACT
  this_class: #2                          // com/fasterxml/jackson/annotation/ObjectIdGenerator
  super_class: #3                         // java/lang/Object
  interfaces: 1, fields: 0, methods: 9, attributes: 3
Constant pool:
   #1 = Methodref          #3.#46         // java/lang/Object."<init>":()V
   #2 = Class              #47            // com/fasterxml/jackson/annotation/ObjectIdGenerator
   #3 = Class              #48            // java/lang/Object
   #4 = Class              #49            // java/io/Serializable
   #5 = Class              #50            // com/fasterxml/jackson/annotation/ObjectIdGenerator$IdKey
   #6 = Utf8               IdKey
   #7 = Utf8               InnerClasses
   #8 = Utf8               <init>
   #9 = Utf8               ()V
  #10 = Utf8               Code
  #11 = Utf8               LineNumberTable
  #12 = Utf8               LocalVariableTable
  #13 = Utf8               this
  #14 = Utf8               Lcom/fasterxml/jackson/annotation/ObjectIdGenerator;
  #15 = Utf8               LocalVariableTypeTable
  #16 = Utf8               Lcom/fasterxml/jackson/annotation/ObjectIdGenerator<TT;>;
  #17 = Utf8               getScope
  #18 = Utf8               ()Ljava/lang/Class;
  #19 = Utf8               Signature
  #20 = Utf8               ()Ljava/lang/Class<*>;
  #21 = Utf8               canUseFor
  #22 = Utf8               (Lcom/fasterxml/jackson/annotation/ObjectIdGenerator;)Z
  #23 = Utf8               (Lcom/fasterxml/jackson/annotation/ObjectIdGenerator<*>;)Z
  #24 = Utf8               maySerializeAsObject
  #25 = Utf8               ()Z
  #26 = Utf8               isValidReferencePropertyName
  #27 = Utf8               (Ljava/lang/String;Ljava/lang/Object;)Z
  #28 = Utf8               name
  #29 = Utf8               Ljava/lang/String;
  #30 = Utf8               parser
  #31 = Utf8               Ljava/lang/Object;
  #32 = Utf8               forScope
  #33 = Utf8               (Ljava/lang/Class;)Lcom/fasterxml/jackson/annotation/ObjectIdGenerator;
  #34 = Utf8               (Ljava/lang/Class<*>;)Lcom/fasterxml/jackson/annotation/ObjectIdGenerator<TT;>;
  #35 = Utf8               newForSerialization
  #36 = Utf8               (Ljava/lang/Object;)Lcom/fasterxml/jackson/annotation/ObjectIdGenerator;
  #37 = Utf8               (Ljava/lang/Object;)Lcom/fasterxml/jackson/annotation/ObjectIdGenerator<TT;>;
  #38 = Utf8               key
  #39 = Utf8               (Ljava/lang/Object;)Lcom/fasterxml/jackson/annotation/ObjectIdGenerator$IdKey;
  #40 = Utf8               generateId
  #41 = Utf8               (Ljava/lang/Object;)Ljava/lang/Object;
  #42 = Utf8               (Ljava/lang/Object;)TT;
  #43 = Utf8               <T:Ljava/lang/Object;>Ljava/lang/Object;Ljava/io/Serializable;
  #44 = Utf8               SourceFile
  #45 = Utf8               ObjectIdGenerator.java
  #46 = NameAndType        #8:#9          // "<init>":()V
  #47 = Utf8               com/fasterxml/jackson/annotation/ObjectIdGenerator
  #48 = Utf8               java/lang/Object
  #49 = Utf8               java/io/Serializable
  #50 = Utf8               com/fasterxml/jackson/annotation/ObjectIdGenerator$IdKey
{
  public com.fasterxml.jackson.annotation.ObjectIdGenerator();
    descriptor: ()V
    flags: (0x0001) ACC_PUBLIC
    Code:
      stack=1, locals=1, args_size=1
         0: aload_0
         1: invokespecial #1                  // Method java/lang/Object."<init>":()V
         4: return
      LineNumberTable:
        line 12: 0
      LocalVariableTable:
        Start  Length  Slot  Name   Signature
            0       5     0  this   Lcom/fasterxml/jackson/annotation/ObjectIdGenerator;
      LocalVariableTypeTable:
        Start  Length  Slot  Name   Signature
            0       5     0  this   Lcom/fasterxml/jackson/annotation/ObjectIdGenerator<TT;>;

  public abstract java.lang.Class<?> getScope();
    descriptor: ()Ljava/lang/Class;
    flags: (0x0401) ACC_PUBLIC, ACC_ABSTRACT
    Signature: #20                          // ()Ljava/lang/Class<*>;

  public abstract boolean canUseFor(com.fasterxml.jackson.annotation.ObjectIdGenerator<?>);
    descriptor: (Lcom/fasterxml/jackson/annotation/ObjectIdGenerator;)Z
    flags: (0x0401) ACC_PUBLIC, ACC_ABSTRACT
    Signature: #23                          // (Lcom/fasterxml/jackson/annotation/ObjectIdGenerator<*>;)Z

  public boolean maySerializeAsObject();
    descriptor: ()Z
    flags: (0x0001) ACC_PUBLIC
    Code:
      stack=1, locals=1, args_size=1
         0: iconst_0
         1: ireturn
      LineNumberTable:
        line 49: 0
      LocalVariableTable:
        Start  Length  Slot  Name   Signature
            0       2     0  this   Lcom/fasterxml/jackson/annotation/ObjectIdGenerator;
      LocalVariableTypeTable:
        Start  Length  Slot  Name   Signature
            0       2     0  this   Lcom/fasterxml/jackson/annotation/ObjectIdGenerator<TT;>;

  public boolean isValidReferencePropertyName(java.lang.String, java.lang.Object);
    descriptor: (Ljava/lang/String;Ljava/lang/Object;)Z
    flags: (0x0001) ACC_PUBLIC
    Code:
      stack=1, locals=3, args_size=3
         0: iconst_0
         1: ireturn
      LineNumberTable:
        line 64: 0
      LocalVariableTable:
        Start  Length  Slot  Name   Signature
            0       2     0  this   Lcom/fasterxml/jackson/annotation/ObjectIdGenerator;
            0       2     1  name   Ljava/lang/String;
            0       2     2 parser   Ljava/lang/Object;
      LocalVariableTypeTable:
        Start  Length  Slot  Name   Signature
            0       2     0  this   Lcom/fasterxml/jackson/annotation/ObjectIdGenerator<TT;>;

  public abstract com.fasterxml.jackson.annotation.ObjectIdGenerator<T> forScope(java.lang.Class<?>);
    descriptor: (Ljava/lang/Class;)Lcom/fasterxml/jackson/annotation/ObjectIdGenerator;
    flags: (0x0401) ACC_PUBLIC, ACC_ABSTRACT
    Signature: #34                          // (Ljava/lang/Class<*>;)Lcom/fasterxml/jackson/annotation/ObjectIdGenerator<TT;>;

  public abstract com.fasterxml.jackson.annotation.ObjectIdGenerator<T> newForSerialization(java.lang.Object);
    descriptor: (Ljava/lang/Object;)Lcom/fasterxml/jackson/annotation/ObjectIdGenerator;
    flags: (0x0401) ACC_PUBLIC, ACC_ABSTRACT
    Signature: #37                          // (Ljava/lang/Object;)Lcom/fasterxml/jackson/annotation/ObjectIdGenerator<TT;>;

  public abstract com.fasterxml.jackson.annotation.ObjectIdGenerator$IdKey key(java.lang.Object);
    descriptor: (Ljava/lang/Object;)Lcom/fasterxml/jackson/annotation/ObjectIdGenerator$IdKey;
    flags: (0x0401) ACC_PUBLIC, ACC_ABSTRACT

  public abstract T generateId(java.lang.Object);
    descriptor: (Ljava/lang/Object;)Ljava/lang/Object;
    flags: (0x0401) ACC_PUBLIC, ACC_ABSTRACT
    Signature: #42                          // (Ljava/lang/Object;)TT;
}
Signature: #43                          // <T:Ljava/lang/Object;>Ljava/lang/Object;Ljava/io/Serializable;
SourceFile: "ObjectIdGenerator.java"
InnerClasses:
  public static final #6= #5 of #2;       // IdKey=class com/fasterxml/jackson/annotation/ObjectIdGenerator$IdKey of class com/fasterxml/jackson/annotation/ObjectIdGenerator
