Classfile /Users/mw/Projects/slang-braindump/.jar/jar8/assemble/slang-braindump/assemble/content/com/fasterxml/jackson/databind/AnnotationIntrospector$ReferenceProperty$Type.class
  Last modified May 29, 2022; size 1509 bytes
  SHA-256 checksum 56fd9ec2a6e0aeceb56f9e8e18e3843041010fdc505524c8dc66912e57328d1b
  Compiled from "AnnotationIntrospector.java"
public final class com.fasterxml.jackson.databind.AnnotationIntrospector$ReferenceProperty$Type extends java.lang.Enum<com.fasterxml.jackson.databind.AnnotationIntrospector$ReferenceProperty$Type>
  minor version: 0
  major version: 52
  flags: (0x4031) ACC_PUBLIC, ACC_FINAL, ACC_SUPER, ACC_ENUM
  this_class: #4                          // com/fasterxml/jackson/databind/AnnotationIntrospector$ReferenceProperty$Type
  super_class: #12                        // java/lang/Enum
  interfaces: 0, fields: 3, methods: 4, attributes: 3
Constant pool:
   #1 = Fieldref           #4.#40         // com/fasterxml/jackson/databind/AnnotationIntrospector$ReferenceProperty$Type.$VALUES:[Lcom/fasterxml/jackson/databind/AnnotationIntrospector$ReferenceProperty$Type;
   #2 = Methodref          #41.#42        // "[Lcom/fasterxml/jackson/databind/AnnotationIntrospector$ReferenceProperty$Type;".clone:()Ljava/lang/Object;
   #3 = Class              #21            // "[Lcom/fasterxml/jackson/databind/AnnotationIntrospector$ReferenceProperty$Type;"
   #4 = Class              #43            // com/fasterxml/jackson/databind/AnnotationIntrospector$ReferenceProperty$Type
   #5 = Methodref          #12.#44        // java/lang/Enum.valueOf:(Ljava/lang/Class;Ljava/lang/String;)Ljava/lang/Enum;
   #6 = Methodref          #12.#45        // java/lang/Enum."<init>":(Ljava/lang/String;I)V
   #7 = String             #13            // MANAGED_REFERENCE
   #8 = Methodref          #4.#45         // com/fasterxml/jackson/databind/AnnotationIntrospector$ReferenceProperty$Type."<init>":(Ljava/lang/String;I)V
   #9 = Fieldref           #4.#46         // com/fasterxml/jackson/databind/AnnotationIntrospector$ReferenceProperty$Type.MANAGED_REFERENCE:Lcom/fasterxml/jackson/databind/AnnotationIntrospector$ReferenceProperty$Type;
  #10 = String             #19            // BACK_REFERENCE
  #11 = Fieldref           #4.#47         // com/fasterxml/jackson/databind/AnnotationIntrospector$ReferenceProperty$Type.BACK_REFERENCE:Lcom/fasterxml/jackson/databind/AnnotationIntrospector$ReferenceProperty$Type;
  #12 = Class              #48            // java/lang/Enum
  #13 = Utf8               MANAGED_REFERENCE
  #14 = Class              #50            // com/fasterxml/jackson/databind/AnnotationIntrospector$ReferenceProperty
  #15 = Utf8               ReferenceProperty
  #16 = Utf8               InnerClasses
  #17 = Utf8               Type
  #18 = Utf8               Lcom/fasterxml/jackson/databind/AnnotationIntrospector$ReferenceProperty$Type;
  #19 = Utf8               BACK_REFERENCE
  #20 = Utf8               $VALUES
  #21 = Utf8               [Lcom/fasterxml/jackson/databind/AnnotationIntrospector$ReferenceProperty$Type;
  #22 = Utf8               values
  #23 = Utf8               ()[Lcom/fasterxml/jackson/databind/AnnotationIntrospector$ReferenceProperty$Type;
  #24 = Utf8               Code
  #25 = Utf8               LineNumberTable
  #26 = Utf8               valueOf
  #27 = Utf8               (Ljava/lang/String;)Lcom/fasterxml/jackson/databind/AnnotationIntrospector$ReferenceProperty$Type;
  #28 = Utf8               LocalVariableTable
  #29 = Utf8               name
  #30 = Utf8               Ljava/lang/String;
  #31 = Utf8               <init>
  #32 = Utf8               (Ljava/lang/String;I)V
  #33 = Utf8               this
  #34 = Utf8               Signature
  #35 = Utf8               ()V
  #36 = Utf8               <clinit>
  #37 = Utf8               Ljava/lang/Enum<Lcom/fasterxml/jackson/databind/AnnotationIntrospector$ReferenceProperty$Type;>;
  #38 = Utf8               SourceFile
  #39 = Utf8               AnnotationIntrospector.java
  #40 = NameAndType        #20:#21        // $VALUES:[Lcom/fasterxml/jackson/databind/AnnotationIntrospector$ReferenceProperty$Type;
  #41 = Class              #21            // "[Lcom/fasterxml/jackson/databind/AnnotationIntrospector$ReferenceProperty$Type;"
  #42 = NameAndType        #51:#52        // clone:()Ljava/lang/Object;
  #43 = Utf8               com/fasterxml/jackson/databind/AnnotationIntrospector$ReferenceProperty$Type
  #44 = NameAndType        #26:#53        // valueOf:(Ljava/lang/Class;Ljava/lang/String;)Ljava/lang/Enum;
  #45 = NameAndType        #31:#32        // "<init>":(Ljava/lang/String;I)V
  #46 = NameAndType        #13:#18        // MANAGED_REFERENCE:Lcom/fasterxml/jackson/databind/AnnotationIntrospector$ReferenceProperty$Type;
  #47 = NameAndType        #19:#18        // BACK_REFERENCE:Lcom/fasterxml/jackson/databind/AnnotationIntrospector$ReferenceProperty$Type;
  #48 = Utf8               java/lang/Enum
  #49 = Class              #54            // com/fasterxml/jackson/databind/AnnotationIntrospector
  #50 = Utf8               com/fasterxml/jackson/databind/AnnotationIntrospector$ReferenceProperty
  #51 = Utf8               clone
  #52 = Utf8               ()Ljava/lang/Object;
  #53 = Utf8               (Ljava/lang/Class;Ljava/lang/String;)Ljava/lang/Enum;
  #54 = Utf8               com/fasterxml/jackson/databind/AnnotationIntrospector
{
  public static final com.fasterxml.jackson.databind.AnnotationIntrospector$ReferenceProperty$Type MANAGED_REFERENCE;
    descriptor: Lcom/fasterxml/jackson/databind/AnnotationIntrospector$ReferenceProperty$Type;
    flags: (0x4019) ACC_PUBLIC, ACC_STATIC, ACC_FINAL, ACC_ENUM

  public static final com.fasterxml.jackson.databind.AnnotationIntrospector$ReferenceProperty$Type BACK_REFERENCE;
    descriptor: Lcom/fasterxml/jackson/databind/AnnotationIntrospector$ReferenceProperty$Type;
    flags: (0x4019) ACC_PUBLIC, ACC_STATIC, ACC_FINAL, ACC_ENUM

  private static final com.fasterxml.jackson.databind.AnnotationIntrospector$ReferenceProperty$Type[] $VALUES;
    descriptor: [Lcom/fasterxml/jackson/databind/AnnotationIntrospector$ReferenceProperty$Type;
    flags: (0x101a) ACC_PRIVATE, ACC_STATIC, ACC_FINAL, ACC_SYNTHETIC

  public static com.fasterxml.jackson.databind.AnnotationIntrospector$ReferenceProperty$Type[] values();
    descriptor: ()[Lcom/fasterxml/jackson/databind/AnnotationIntrospector$ReferenceProperty$Type;
    flags: (0x0009) ACC_PUBLIC, ACC_STATIC
    Code:
      stack=1, locals=0, args_size=0
         0: getstatic     #1                  // Field $VALUES:[Lcom/fasterxml/jackson/databind/AnnotationIntrospector$ReferenceProperty$Type;
         3: invokevirtual #2                  // Method "[Lcom/fasterxml/jackson/databind/AnnotationIntrospector$ReferenceProperty$Type;".clone:()Ljava/lang/Object;
         6: checkcast     #3                  // class "[Lcom/fasterxml/jackson/databind/AnnotationIntrospector$ReferenceProperty$Type;"
         9: areturn
      LineNumberTable:
        line 54: 0

  public static com.fasterxml.jackson.databind.AnnotationIntrospector$ReferenceProperty$Type valueOf(java.lang.String);
    descriptor: (Ljava/lang/String;)Lcom/fasterxml/jackson/databind/AnnotationIntrospector$ReferenceProperty$Type;
    flags: (0x0009) ACC_PUBLIC, ACC_STATIC
    Code:
      stack=2, locals=1, args_size=1
         0: ldc           #4                  // class com/fasterxml/jackson/databind/AnnotationIntrospector$ReferenceProperty$Type
         2: aload_0
         3: invokestatic  #5                  // Method java/lang/Enum.valueOf:(Ljava/lang/Class;Ljava/lang/String;)Ljava/lang/Enum;
         6: checkcast     #4                  // class com/fasterxml/jackson/databind/AnnotationIntrospector$ReferenceProperty$Type
         9: areturn
      LineNumberTable:
        line 54: 0
      LocalVariableTable:
        Start  Length  Slot  Name   Signature
            0      10     0  name   Ljava/lang/String;

  private com.fasterxml.jackson.databind.AnnotationIntrospector$ReferenceProperty$Type();
    descriptor: (Ljava/lang/String;I)V
    flags: (0x0002) ACC_PRIVATE
    Code:
      stack=3, locals=3, args_size=3
         0: aload_0
         1: aload_1
         2: iload_2
         3: invokespecial #6                  // Method java/lang/Enum."<init>":(Ljava/lang/String;I)V
         6: return
      LineNumberTable:
        line 54: 0
      LocalVariableTable:
        Start  Length  Slot  Name   Signature
            0       7     0  this   Lcom/fasterxml/jackson/databind/AnnotationIntrospector$ReferenceProperty$Type;
    Signature: #35                          // ()V

  static {};
    descriptor: ()V
    flags: (0x0008) ACC_STATIC
    Code:
      stack=4, locals=0, args_size=0
         0: new           #4                  // class com/fasterxml/jackson/databind/AnnotationIntrospector$ReferenceProperty$Type
         3: dup
         4: ldc           #7                  // String MANAGED_REFERENCE
         6: iconst_0
         7: invokespecial #8                  // Method "<init>":(Ljava/lang/String;I)V
        10: putstatic     #9                  // Field MANAGED_REFERENCE:Lcom/fasterxml/jackson/databind/AnnotationIntrospector$ReferenceProperty$Type;
        13: new           #4                  // class com/fasterxml/jackson/databind/AnnotationIntrospector$ReferenceProperty$Type
        16: dup
        17: ldc           #10                 // String BACK_REFERENCE
        19: iconst_1
        20: invokespecial #8                  // Method "<init>":(Ljava/lang/String;I)V
        23: putstatic     #11                 // Field BACK_REFERENCE:Lcom/fasterxml/jackson/databind/AnnotationIntrospector$ReferenceProperty$Type;
        26: iconst_2
        27: anewarray     #4                  // class com/fasterxml/jackson/databind/AnnotationIntrospector$ReferenceProperty$Type
        30: dup
        31: iconst_0
        32: getstatic     #9                  // Field MANAGED_REFERENCE:Lcom/fasterxml/jackson/databind/AnnotationIntrospector$ReferenceProperty$Type;
        35: aastore
        36: dup
        37: iconst_1
        38: getstatic     #11                 // Field BACK_REFERENCE:Lcom/fasterxml/jackson/databind/AnnotationIntrospector$ReferenceProperty$Type;
        41: aastore
        42: putstatic     #1                  // Field $VALUES:[Lcom/fasterxml/jackson/databind/AnnotationIntrospector$ReferenceProperty$Type;
        45: return
      LineNumberTable:
        line 62: 0
        line 70: 13
        line 54: 26
}
Signature: #37                          // Ljava/lang/Enum<Lcom/fasterxml/jackson/databind/AnnotationIntrospector$ReferenceProperty$Type;>;
SourceFile: "AnnotationIntrospector.java"
InnerClasses:
  public static #15= #14 of #49;          // ReferenceProperty=class com/fasterxml/jackson/databind/AnnotationIntrospector$ReferenceProperty of class com/fasterxml/jackson/databind/AnnotationIntrospector
  public static final #17= #4 of #14;     // Type=class com/fasterxml/jackson/databind/AnnotationIntrospector$ReferenceProperty$Type of class com/fasterxml/jackson/databind/AnnotationIntrospector$ReferenceProperty
