Classfile /Users/mw/Projects/slang-braindump/.jar/jar8/assemble/slang-braindump/assemble/content/com/fasterxml/jackson/databind/DatabindException.class
  Last modified May 29, 2022; size 1164 bytes
  SHA-256 checksum 0d397b288e9201646c0289b1d391247c1e58025cbdce0673249b9fbfe3bd9e0e
  Compiled from "DatabindException.java"
public abstract class com.fasterxml.jackson.databind.DatabindException extends com.fasterxml.jackson.core.JsonProcessingException
  minor version: 0
  major version: 52
  flags: (0x0421) ACC_PUBLIC, ACC_SUPER, ACC_ABSTRACT
  this_class: #4                          // com/fasterxml/jackson/databind/DatabindException
  super_class: #5                         // com/fasterxml/jackson/core/JsonProcessingException
  interfaces: 0, fields: 1, methods: 6, attributes: 1
Constant pool:
   #1 = Methodref          #5.#32         // com/fasterxml/jackson/core/JsonProcessingException."<init>":(Ljava/lang/String;Lcom/fasterxml/jackson/core/JsonLocation;Ljava/lang/Throwable;)V
   #2 = Methodref          #5.#33         // com/fasterxml/jackson/core/JsonProcessingException."<init>":(Ljava/lang/String;)V
   #3 = Methodref          #4.#32         // com/fasterxml/jackson/databind/DatabindException."<init>":(Ljava/lang/String;Lcom/fasterxml/jackson/core/JsonLocation;Ljava/lang/Throwable;)V
   #4 = Class              #34            // com/fasterxml/jackson/databind/DatabindException
   #5 = Class              #35            // com/fasterxml/jackson/core/JsonProcessingException
   #6 = Utf8               serialVersionUID
   #7 = Utf8               J
   #8 = Utf8               ConstantValue
   #9 = Long               3l
  #11 = Utf8               <init>
  #12 = Utf8               (Ljava/lang/String;Lcom/fasterxml/jackson/core/JsonLocation;Ljava/lang/Throwable;)V
  #13 = Utf8               Code
  #14 = Utf8               LineNumberTable
  #15 = Utf8               LocalVariableTable
  #16 = Utf8               this
  #17 = Utf8               Lcom/fasterxml/jackson/databind/DatabindException;
  #18 = Utf8               msg
  #19 = Utf8               Ljava/lang/String;
  #20 = Utf8               loc
  #21 = Utf8               Lcom/fasterxml/jackson/core/JsonLocation;
  #22 = Utf8               rootCause
  #23 = Utf8               Ljava/lang/Throwable;
  #24 = Utf8               (Ljava/lang/String;)V
  #25 = Utf8               (Ljava/lang/String;Lcom/fasterxml/jackson/core/JsonLocation;)V
  #26 = Utf8               (Ljava/lang/String;Ljava/lang/Throwable;)V
  #27 = Utf8               prependPath
  #28 = Utf8               (Ljava/lang/Object;Ljava/lang/String;)V
  #29 = Utf8               (Ljava/lang/Object;I)V
  #30 = Utf8               SourceFile
  #31 = Utf8               DatabindException.java
  #32 = NameAndType        #11:#12        // "<init>":(Ljava/lang/String;Lcom/fasterxml/jackson/core/JsonLocation;Ljava/lang/Throwable;)V
  #33 = NameAndType        #11:#24        // "<init>":(Ljava/lang/String;)V
  #34 = Utf8               com/fasterxml/jackson/databind/DatabindException
  #35 = Utf8               com/fasterxml/jackson/core/JsonProcessingException
{
  private static final long serialVersionUID;
    descriptor: J
    flags: (0x001a) ACC_PRIVATE, ACC_STATIC, ACC_FINAL
    ConstantValue: long 3l

  protected com.fasterxml.jackson.databind.DatabindException(java.lang.String, com.fasterxml.jackson.core.JsonLocation, java.lang.Throwable);
    descriptor: (Ljava/lang/String;Lcom/fasterxml/jackson/core/JsonLocation;Ljava/lang/Throwable;)V
    flags: (0x0004) ACC_PROTECTED
    Code:
      stack=4, locals=4, args_size=4
         0: aload_0
         1: aload_1
         2: aload_2
         3: aload_3
         4: invokespecial #1                  // Method com/fasterxml/jackson/core/JsonProcessingException."<init>":(Ljava/lang/String;Lcom/fasterxml/jackson/core/JsonLocation;Ljava/lang/Throwable;)V
         7: return
      LineNumberTable:
        line 22: 0
        line 23: 7
      LocalVariableTable:
        Start  Length  Slot  Name   Signature
            0       8     0  this   Lcom/fasterxml/jackson/databind/DatabindException;
            0       8     1   msg   Ljava/lang/String;
            0       8     2   loc   Lcom/fasterxml/jackson/core/JsonLocation;
            0       8     3 rootCause   Ljava/lang/Throwable;

  protected com.fasterxml.jackson.databind.DatabindException(java.lang.String);
    descriptor: (Ljava/lang/String;)V
    flags: (0x0004) ACC_PROTECTED
    Code:
      stack=2, locals=2, args_size=2
         0: aload_0
         1: aload_1
         2: invokespecial #2                  // Method com/fasterxml/jackson/core/JsonProcessingException."<init>":(Ljava/lang/String;)V
         5: return
      LineNumberTable:
        line 26: 0
        line 27: 5
      LocalVariableTable:
        Start  Length  Slot  Name   Signature
            0       6     0  this   Lcom/fasterxml/jackson/databind/DatabindException;
            0       6     1   msg   Ljava/lang/String;

  protected com.fasterxml.jackson.databind.DatabindException(java.lang.String, com.fasterxml.jackson.core.JsonLocation);
    descriptor: (Ljava/lang/String;Lcom/fasterxml/jackson/core/JsonLocation;)V
    flags: (0x0004) ACC_PROTECTED
    Code:
      stack=4, locals=3, args_size=3
         0: aload_0
         1: aload_1
         2: aload_2
         3: aconst_null
         4: invokespecial #3                  // Method "<init>":(Ljava/lang/String;Lcom/fasterxml/jackson/core/JsonLocation;Ljava/lang/Throwable;)V
         7: return
      LineNumberTable:
        line 30: 0
        line 31: 7
      LocalVariableTable:
        Start  Length  Slot  Name   Signature
            0       8     0  this   Lcom/fasterxml/jackson/databind/DatabindException;
            0       8     1   msg   Ljava/lang/String;
            0       8     2   loc   Lcom/fasterxml/jackson/core/JsonLocation;

  protected com.fasterxml.jackson.databind.DatabindException(java.lang.String, java.lang.Throwable);
    descriptor: (Ljava/lang/String;Ljava/lang/Throwable;)V
    flags: (0x0004) ACC_PROTECTED
    Code:
      stack=4, locals=3, args_size=3
         0: aload_0
         1: aload_1
         2: aconst_null
         3: aload_2
         4: invokespecial #3                  // Method "<init>":(Ljava/lang/String;Lcom/fasterxml/jackson/core/JsonLocation;Ljava/lang/Throwable;)V
         7: return
      LineNumberTable:
        line 34: 0
        line 35: 7
      LocalVariableTable:
        Start  Length  Slot  Name   Signature
            0       8     0  this   Lcom/fasterxml/jackson/databind/DatabindException;
            0       8     1   msg   Ljava/lang/String;
            0       8     2 rootCause   Ljava/lang/Throwable;

  public abstract void prependPath(java.lang.Object, java.lang.String);
    descriptor: (Ljava/lang/Object;Ljava/lang/String;)V
    flags: (0x0401) ACC_PUBLIC, ACC_ABSTRACT

  public abstract void prependPath(java.lang.Object, int);
    descriptor: (Ljava/lang/Object;I)V
    flags: (0x0401) ACC_PUBLIC, ACC_ABSTRACT
}
SourceFile: "DatabindException.java"
