Classfile /Users/mw/Projects/slang-braindump/.jar/jar8/assemble/slang-braindump/assemble/content/com/fasterxml/jackson/databind/PropertyNamingStrategy$LowerCaseWithUnderscoresStrategy.class
  Last modified May 29, 2022; size 711 bytes
  SHA-256 checksum 23eb54a15e2162a075f4bc7d5bc5e74404da1bbaa4031a1272123213640d9a3f
  Compiled from "PropertyNamingStrategy.java"
public class com.fasterxml.jackson.databind.PropertyNamingStrategy$LowerCaseWithUnderscoresStrategy extends com.fasterxml.jackson.databind.PropertyNamingStrategy$SnakeCaseStrategy
  minor version: 0
  major version: 52
  flags: (0x0021) ACC_PUBLIC, ACC_SUPER
  this_class: #2                          // com/fasterxml/jackson/databind/PropertyNamingStrategy$LowerCaseWithUnderscoresStrategy
  super_class: #3                         // com/fasterxml/jackson/databind/PropertyNamingStrategy$SnakeCaseStrategy
  interfaces: 0, fields: 0, methods: 1, attributes: 4
Constant pool:
   #1 = Methodref          #3.#18         // com/fasterxml/jackson/databind/PropertyNamingStrategy$SnakeCaseStrategy."<init>":()V
   #2 = Class              #20            // com/fasterxml/jackson/databind/PropertyNamingStrategy$LowerCaseWithUnderscoresStrategy
   #3 = Class              #21            // com/fasterxml/jackson/databind/PropertyNamingStrategy$SnakeCaseStrategy
   #4 = Utf8               <init>
   #5 = Utf8               ()V
   #6 = Utf8               Code
   #7 = Utf8               LineNumberTable
   #8 = Utf8               LocalVariableTable
   #9 = Utf8               this
  #10 = Utf8               LowerCaseWithUnderscoresStrategy
  #11 = Utf8               InnerClasses
  #12 = Utf8               Lcom/fasterxml/jackson/databind/PropertyNamingStrategy$LowerCaseWithUnderscoresStrategy;
  #13 = Utf8               SourceFile
  #14 = Utf8               PropertyNamingStrategy.java
  #15 = Utf8               Deprecated
  #16 = Utf8               RuntimeVisibleAnnotations
  #17 = Utf8               Ljava/lang/Deprecated;
  #18 = NameAndType        #4:#5          // "<init>":()V
  #19 = Class              #23            // com/fasterxml/jackson/databind/PropertyNamingStrategy
  #20 = Utf8               com/fasterxml/jackson/databind/PropertyNamingStrategy$LowerCaseWithUnderscoresStrategy
  #21 = Utf8               com/fasterxml/jackson/databind/PropertyNamingStrategy$SnakeCaseStrategy
  #22 = Utf8               SnakeCaseStrategy
  #23 = Utf8               com/fasterxml/jackson/databind/PropertyNamingStrategy
{
  public com.fasterxml.jackson.databind.PropertyNamingStrategy$LowerCaseWithUnderscoresStrategy();
    descriptor: ()V
    flags: (0x0001) ACC_PUBLIC
    Code:
      stack=1, locals=1, args_size=1
         0: aload_0
         1: invokespecial #1                  // Method com/fasterxml/jackson/databind/PropertyNamingStrategy$SnakeCaseStrategy."<init>":()V
         4: return
      LineNumberTable:
        line 413: 0
      LocalVariableTable:
        Start  Length  Slot  Name   Signature
            0       5     0  this   Lcom/fasterxml/jackson/databind/PropertyNamingStrategy$LowerCaseWithUnderscoresStrategy;
}
SourceFile: "PropertyNamingStrategy.java"
Deprecated: true
RuntimeVisibleAnnotations:
  0: #17()
    java.lang.Deprecated
InnerClasses:
  public static #10= #2 of #19;           // LowerCaseWithUnderscoresStrategy=class com/fasterxml/jackson/databind/PropertyNamingStrategy$LowerCaseWithUnderscoresStrategy of class com/fasterxml/jackson/databind/PropertyNamingStrategy
  public static #22= #3 of #19;           // SnakeCaseStrategy=class com/fasterxml/jackson/databind/PropertyNamingStrategy$SnakeCaseStrategy of class com/fasterxml/jackson/databind/PropertyNamingStrategy
