Classfile /Users/mw/Projects/slang-braindump/.jar/jar8/assemble/slang-braindump/assemble/content/com/fasterxml/jackson/databind/PropertyNamingStrategy$LowerCaseStrategy.class
  Last modified May 29, 2022; size 906 bytes
  SHA-256 checksum c3d9b939fa4dfee56fbdc54a2244d6d6e592e029c6a87871249506ce2600f96c
  Compiled from "PropertyNamingStrategy.java"
public class com.fasterxml.jackson.databind.PropertyNamingStrategy$LowerCaseStrategy extends com.fasterxml.jackson.databind.PropertyNamingStrategy$PropertyNamingStrategyBase
  minor version: 0
  major version: 52
  flags: (0x0021) ACC_PUBLIC, ACC_SUPER
  this_class: #3                          // com/fasterxml/jackson/databind/PropertyNamingStrategy$LowerCaseStrategy
  super_class: #4                         // com/fasterxml/jackson/databind/PropertyNamingStrategy$PropertyNamingStrategyBase
  interfaces: 0, fields: 0, methods: 2, attributes: 4
Constant pool:
   #1 = Methodref          #4.#23         // com/fasterxml/jackson/databind/PropertyNamingStrategy$PropertyNamingStrategyBase."<init>":()V
   #2 = Methodref          #24.#25        // java/lang/String.toLowerCase:()Ljava/lang/String;
   #3 = Class              #27            // com/fasterxml/jackson/databind/PropertyNamingStrategy$LowerCaseStrategy
   #4 = Class              #28            // com/fasterxml/jackson/databind/PropertyNamingStrategy$PropertyNamingStrategyBase
   #5 = Utf8               <init>
   #6 = Utf8               ()V
   #7 = Utf8               Code
   #8 = Utf8               LineNumberTable
   #9 = Utf8               LocalVariableTable
  #10 = Utf8               this
  #11 = Utf8               LowerCaseStrategy
  #12 = Utf8               InnerClasses
  #13 = Utf8               Lcom/fasterxml/jackson/databind/PropertyNamingStrategy$LowerCaseStrategy;
  #14 = Utf8               translate
  #15 = Utf8               (Ljava/lang/String;)Ljava/lang/String;
  #16 = Utf8               input
  #17 = Utf8               Ljava/lang/String;
  #18 = Utf8               SourceFile
  #19 = Utf8               PropertyNamingStrategy.java
  #20 = Utf8               Deprecated
  #21 = Utf8               RuntimeVisibleAnnotations
  #22 = Utf8               Ljava/lang/Deprecated;
  #23 = NameAndType        #5:#6          // "<init>":()V
  #24 = Class              #30            // java/lang/String
  #25 = NameAndType        #31:#32        // toLowerCase:()Ljava/lang/String;
  #26 = Class              #33            // com/fasterxml/jackson/databind/PropertyNamingStrategy
  #27 = Utf8               com/fasterxml/jackson/databind/PropertyNamingStrategy$LowerCaseStrategy
  #28 = Utf8               com/fasterxml/jackson/databind/PropertyNamingStrategy$PropertyNamingStrategyBase
  #29 = Utf8               PropertyNamingStrategyBase
  #30 = Utf8               java/lang/String
  #31 = Utf8               toLowerCase
  #32 = Utf8               ()Ljava/lang/String;
  #33 = Utf8               com/fasterxml/jackson/databind/PropertyNamingStrategy
{
  public com.fasterxml.jackson.databind.PropertyNamingStrategy$LowerCaseStrategy();
    descriptor: ()V
    flags: (0x0001) ACC_PUBLIC
    Code:
      stack=1, locals=1, args_size=1
         0: aload_0
         1: invokespecial #1                  // Method com/fasterxml/jackson/databind/PropertyNamingStrategy$PropertyNamingStrategyBase."<init>":()V
         4: return
      LineNumberTable:
        line 354: 0
      LocalVariableTable:
        Start  Length  Slot  Name   Signature
            0       5     0  this   Lcom/fasterxml/jackson/databind/PropertyNamingStrategy$LowerCaseStrategy;

  public java.lang.String translate(java.lang.String);
    descriptor: (Ljava/lang/String;)Ljava/lang/String;
    flags: (0x0001) ACC_PUBLIC
    Code:
      stack=1, locals=2, args_size=2
         0: aload_1
         1: invokevirtual #2                  // Method java/lang/String.toLowerCase:()Ljava/lang/String;
         4: areturn
      LineNumberTable:
        line 358: 0
      LocalVariableTable:
        Start  Length  Slot  Name   Signature
            0       5     0  this   Lcom/fasterxml/jackson/databind/PropertyNamingStrategy$LowerCaseStrategy;
            0       5     1 input   Ljava/lang/String;
}
SourceFile: "PropertyNamingStrategy.java"
Deprecated: true
RuntimeVisibleAnnotations:
  0: #22()
    java.lang.Deprecated
InnerClasses:
  public static #11= #3 of #26;           // LowerCaseStrategy=class com/fasterxml/jackson/databind/PropertyNamingStrategy$LowerCaseStrategy of class com/fasterxml/jackson/databind/PropertyNamingStrategy
  public static abstract #29= #4 of #26;  // PropertyNamingStrategyBase=class com/fasterxml/jackson/databind/PropertyNamingStrategy$PropertyNamingStrategyBase of class com/fasterxml/jackson/databind/PropertyNamingStrategy
