Classfile /Users/mw/Projects/slang-braindump/.jar/jar11/assemble/slang-braindump/assemble/content/scala/annotation/meta/param.class
  Last modified May 29, 2022; size 631 bytes
  SHA-256 checksum 6c171cbab3674328fe1f4a08710a90c540e577e62c931dddee80624ca738e999
  Compiled from "param.scala"
public final class scala.annotation.meta.param extends scala.annotation.Annotation implements scala.annotation.StaticAnnotation
  minor version: 0
  major version: 52
  flags: (0x0031) ACC_PUBLIC, ACC_FINAL, ACC_SUPER
  this_class: #2                          // scala/annotation/meta/param
  super_class: #4                         // scala/annotation/Annotation
  interfaces: 1, fields: 0, methods: 1, attributes: 4
Constant pool:
   #1 = Utf8               scala/annotation/meta/param
   #2 = Class              #1             // scala/annotation/meta/param
   #3 = Utf8               scala/annotation/Annotation
   #4 = Class              #3             // scala/annotation/Annotation
   #5 = Utf8               scala/annotation/StaticAnnotation
   #6 = Class              #5             // scala/annotation/StaticAnnotation
   #7 = Utf8               param.scala
   #8 = Utf8               Lscala/reflect/ScalaSignature;
   #9 = Utf8               bytes
  #10 = Utf8               \u0006\u0005Y1AAA\u0002\u0003\u0015!)!\u0003\u0001C\u0001\'\t)\u0001/\u0019:b[*\u0011A!B\u0001\u0005[\u0016$\u0018M\u0003\u0002\u0007\u000f\u0005Q\u0011M\u001c8pi\u0006$\u0018n\u001c8\u000b\u0003!\tQa]2bY\u0006\u001c\u0001aE\u0002\u0001\u0017=\u0001\"\u0001D\u0007\u000e\u0003\u0015I!AD\u0003\u0003\u0015\u0005sgn\u001c;bi&|g\u000e\u0005\u0002\r!%\u0011\u0011#\u0002\u0002\u0011\'R\fG/[2B]:|G/\u0019;j_:\fa\u0001P5oSRtD#\u0001\u000b\u0011\u0005U\u0001Q\"A\u0002
  #11 = Utf8               <init>
  #12 = Utf8               ()V
  #13 = NameAndType        #11:#12        // "<init>":()V
  #14 = Methodref          #4.#13         // scala/annotation/Annotation."<init>":()V
  #15 = Utf8               this
  #16 = Utf8               Lscala/annotation/meta/param;
  #17 = Utf8               Code
  #18 = Utf8               LineNumberTable
  #19 = Utf8               LocalVariableTable
  #20 = Utf8               SourceFile
  #21 = Utf8               RuntimeVisibleAnnotations
  #22 = Utf8               ScalaInlineInfo
  #23 = Utf8               ScalaSig
{
  public scala.annotation.meta.param();
    descriptor: ()V
    flags: (0x0001) ACC_PUBLIC
    Code:
      stack=1, locals=1, args_size=1
         0: aload_0
         1: invokespecial #14                 // Method scala/annotation/Annotation."<init>":()V
         4: return
      LineNumberTable:
        line 18: 0
      LocalVariableTable:
        Start  Length  Slot  Name   Signature
            0       5     0  this   Lscala/annotation/meta/param;
}
SourceFile: "param.scala"
RuntimeVisibleAnnotations:
  0: #8(#9=s#10)
    scala.reflect.ScalaSignature(
      bytes="\u0006\u0005Y1AAA\u0002\u0003\u0015!)!\u0003\u0001C\u0001\'\t)\u0001/\u0019:b[*\u0011A!B\u0001\u0005[\u0016$\u0018M\u0003\u0002\u0007\u000f\u0005Q\u0011M\u001c8pi\u0006$\u0018n\u001c8\u000b\u0003!\tQa]2bY\u0006\u001c\u0001aE\u0002\u0001\u0017=\u0001\"\u0001D\u0007\u000e\u0003\u0015I!AD\u0003\u0003\u0015\u0005sgn\u001c;bi&|g\u000e\u0005\u0002\r!%\u0011\u0011#\u0002\u0002\u0011\'R\fG/[2B]:|G/\u0019;j_:\fa\u0001P5oSRtD#\u0001\u000b\u0011\u0005U\u0001Q\"A\u0002"
    )
  ScalaInlineInfo: length = 0x9 (unknown attribute)
   01 01 00 01 00 0B 00 0C 01
  ScalaSig: length = 0x3 (unknown attribute)
   05 02 00
