Classfile /Users/mw/Projects/slang-braindump/.jar/jar8/assemble/slang-braindump/assemble/content/coursier/Fetch$Result$.class
  Last modified May 29, 2022; size 1908 bytes
  SHA-256 checksum cdf5de11e80c12adde37935d729ca4e9b7732c1bde6ed6f76efdc95b54dd5c4d
  Compiled from "Fetch.scala"
public class coursier.Fetch$Result$ implements java.io.Serializable
  minor version: 0
  major version: 52
  flags: (0x0021) ACC_PUBLIC, ACC_SUPER
  this_class: #2                          // coursier/Fetch$Result$
  super_class: #4                         // java/lang/Object
  interfaces: 1, fields: 1, methods: 5, attributes: 4
Constant pool:
   #1 = Utf8               coursier/Fetch$Result$
   #2 = Class              #1             // coursier/Fetch$Result$
   #3 = Utf8               java/lang/Object
   #4 = Class              #3             // java/lang/Object
   #5 = Utf8               java/io/Serializable
   #6 = Class              #5             // java/io/Serializable
   #7 = Utf8               Fetch.scala
   #8 = Utf8               coursier/Fetch$Result
   #9 = Class              #8             // coursier/Fetch$Result
  #10 = Utf8               coursier/Fetch
  #11 = Class              #10            // coursier/Fetch
  #12 = Utf8               Result
  #13 = Utf8
  #14 = Utf8               coursier/package$Resolution$
  #15 = Class              #14            // coursier/package$Resolution$
  #16 = Utf8               coursier/package
  #17 = Class              #16            // coursier/package
  #18 = Utf8               MODULE$
  #19 = Utf8               Lcoursier/Fetch$Result$;
  #20 = Utf8               <clinit>
  #21 = Utf8               ()V
  #22 = Utf8               <init>
  #23 = NameAndType        #22:#21        // "<init>":()V
  #24 = Methodref          #2.#23         // coursier/Fetch$Result$."<init>":()V
  #25 = NameAndType        #18:#19        // MODULE$:Lcoursier/Fetch$Result$;
  #26 = Fieldref           #2.#25         // coursier/Fetch$Result$.MODULE$:Lcoursier/Fetch$Result$;
  #27 = Utf8               apply
  #28 = Utf8               ()Lcoursier/Fetch$Result;
  #29 = Utf8               Lcoursier/package$Resolution$;
  #30 = NameAndType        #18:#29        // MODULE$:Lcoursier/package$Resolution$;
  #31 = Fieldref           #15.#30        // coursier/package$Resolution$.MODULE$:Lcoursier/package$Resolution$;
  #32 = Utf8               ()Lcoursier/core/Resolution;
  #33 = NameAndType        #27:#32        // apply:()Lcoursier/core/Resolution;
  #34 = Methodref          #15.#33        // coursier/package$Resolution$.apply:()Lcoursier/core/Resolution;
  #35 = Utf8               scala/collection/immutable/Nil$
  #36 = Class              #35            // scala/collection/immutable/Nil$
  #37 = Utf8               Lscala/collection/immutable/Nil$;
  #38 = NameAndType        #18:#37        // MODULE$:Lscala/collection/immutable/Nil$;
  #39 = Fieldref           #36.#38        // scala/collection/immutable/Nil$.MODULE$:Lscala/collection/immutable/Nil$;
  #40 = Utf8               (Lcoursier/core/Resolution;Lscala/collection/immutable/Seq;Lscala/collection/immutable/Seq;)V
  #41 = NameAndType        #22:#40        // "<init>":(Lcoursier/core/Resolution;Lscala/collection/immutable/Seq;Lscala/collection/immutable/Seq;)V
  #42 = Methodref          #9.#41         // coursier/Fetch$Result."<init>":(Lcoursier/core/Resolution;Lscala/collection/immutable/Seq;Lscala/collection/immutable/Seq;)V
  #43 = Utf8               this
  #44 = Utf8               (Lcoursier/core/Resolution;Lscala/collection/immutable/Seq;Lscala/collection/immutable/Seq;)Lcoursier/Fetch$Result;
  #45 = Utf8               (Lcoursier/core/Resolution;Lscala/collection/immutable/Seq<Lscala/Tuple4<Lcoursier/core/Dependency;Lcoursier/core/Publication;Lcoursier/util/Artifact;Lscala/Option<Ljava/io/File;>;>;>;Lscala/collection/immutable/Seq<Lscala/Tuple2<Lcoursier/util/Artifact;Lscala/Option<Ljava/io/File;>;>;>;)Lcoursier/Fetch$Result;
  #46 = Utf8               resolution
  #47 = Utf8               fullDetailedArtifacts
  #48 = Utf8               fullExtraArtifacts
  #49 = Utf8               Lcoursier/core/Resolution;
  #50 = Utf8               Lscala/collection/immutable/Seq;
  #51 = Utf8               writeReplace
  #52 = Utf8               ()Ljava/lang/Object;
  #53 = Utf8               scala/runtime/ModuleSerializationProxy
  #54 = Class              #53            // scala/runtime/ModuleSerializationProxy
  #55 = Utf8               (Ljava/lang/Class;)V
  #56 = NameAndType        #22:#55        // "<init>":(Ljava/lang/Class;)V
  #57 = Methodref          #54.#56        // scala/runtime/ModuleSerializationProxy."<init>":(Ljava/lang/Class;)V
  #58 = Methodref          #4.#23         // java/lang/Object."<init>":()V
  #59 = Utf8               Code
  #60 = Utf8               LineNumberTable
  #61 = Utf8               LocalVariableTable
  #62 = Utf8               Signature
  #63 = Utf8               MethodParameters
  #64 = Utf8               InnerClasses
  #65 = Utf8               SourceFile
  #66 = Utf8               ScalaInlineInfo
  #67 = Utf8               Scala
{
  public static final coursier.Fetch$Result$ MODULE$;
    descriptor: Lcoursier/Fetch$Result$;
    flags: (0x0019) ACC_PUBLIC, ACC_STATIC, ACC_FINAL

  public static {};
    descriptor: ()V
    flags: (0x0009) ACC_PUBLIC, ACC_STATIC
    Code:
      stack=2, locals=0, args_size=0
         0: new           #2                  // class coursier/Fetch$Result$
         3: dup
         4: invokespecial #24                 // Method "<init>":()V
         7: putstatic     #26                 // Field MODULE$:Lcoursier/Fetch$Result$;
        10: return
      LineNumberTable:
        line 235: 0

  public coursier.Fetch$Result apply();
    descriptor: ()Lcoursier/Fetch$Result;
    flags: (0x0001) ACC_PUBLIC
    Code:
      stack=5, locals=1, args_size=1
         0: new           #9                  // class coursier/Fetch$Result
         3: dup
         4: getstatic     #31                 // Field coursier/package$Resolution$.MODULE$:Lcoursier/package$Resolution$;
         7: invokevirtual #34                 // Method coursier/package$Resolution$.apply:()Lcoursier/core/Resolution;
        10: getstatic     #39                 // Field scala/collection/immutable/Nil$.MODULE$:Lscala/collection/immutable/Nil$;
        13: getstatic     #39                 // Field scala/collection/immutable/Nil$.MODULE$:Lscala/collection/immutable/Nil$;
        16: invokespecial #42                 // Method coursier/Fetch$Result."<init>":(Lcoursier/core/Resolution;Lscala/collection/immutable/Seq;Lscala/collection/immutable/Seq;)V
        19: areturn
      LineNumberTable:
        line 235: 0
        line 236: 4
        line 237: 10
        line 238: 13
      LocalVariableTable:
        Start  Length  Slot  Name   Signature
            0      20     0  this   Lcoursier/Fetch$Result$;

  public coursier.Fetch$Result apply(coursier.core.Resolution, scala.collection.immutable.Seq<scala.Tuple4<coursier.core.Dependency, coursier.core.Publication, coursier.util.Artifact, scala.Option<java.io.File>>>, scala.collection.immutable.Seq<scala.Tuple2<coursier.util.Artifact, scala.Option<java.io.File>>>);
    descriptor: (Lcoursier/core/Resolution;Lscala/collection/immutable/Seq;Lscala/collection/immutable/Seq;)Lcoursier/Fetch$Result;
    flags: (0x0001) ACC_PUBLIC
    Code:
      stack=5, locals=4, args_size=4
         0: new           #9                  // class coursier/Fetch$Result
         3: dup
         4: aload_1
         5: aload_2
         6: aload_3
         7: invokespecial #42                 // Method coursier/Fetch$Result."<init>":(Lcoursier/core/Resolution;Lscala/collection/immutable/Seq;Lscala/collection/immutable/Seq;)V
        10: areturn
      LineNumberTable:
        line 235: 0
      LocalVariableTable:
        Start  Length  Slot  Name   Signature
            0      11     0  this   Lcoursier/Fetch$Result$;
            0      11     1 resolution   Lcoursier/core/Resolution;
            0      11     2 fullDetailedArtifacts   Lscala/collection/immutable/Seq;
            0      11     3 fullExtraArtifacts   Lscala/collection/immutable/Seq;
    Signature: #45                          // (Lcoursier/core/Resolution;Lscala/collection/immutable/Seq<Lscala/Tuple4<Lcoursier/core/Dependency;Lcoursier/core/Publication;Lcoursier/util/Artifact;Lscala/Option<Ljava/io/File;>;>;>;Lscala/collection/immutable/Seq<Lscala/Tuple2<Lcoursier/util/Artifact;Lscala/Option<Ljava/io/File;>;>;>;)Lcoursier/Fetch$Result;
    MethodParameters:
      Name                           Flags
      resolution                     final
      fullDetailedArtifacts          final
      fullExtraArtifacts             final

  private java.lang.Object writeReplace();
    descriptor: ()Ljava/lang/Object;
    flags: (0x0002) ACC_PRIVATE
    Code:
      stack=3, locals=1, args_size=1
         0: new           #54                 // class scala/runtime/ModuleSerializationProxy
         3: dup
         4: ldc           #2                  // class coursier/Fetch$Result$
         6: invokespecial #57                 // Method scala/runtime/ModuleSerializationProxy."<init>":(Ljava/lang/Class;)V
         9: areturn
      LineNumberTable:
        line 235: 0
      LocalVariableTable:
        Start  Length  Slot  Name   Signature
            0      10     0  this   Lcoursier/Fetch$Result$;

  public coursier.Fetch$Result$();
    descriptor: ()V
    flags: (0x0001) ACC_PUBLIC
    Code:
      stack=1, locals=1, args_size=1
         0: aload_0
         1: invokespecial #58                 // Method java/lang/Object."<init>":()V
         4: return
      LineNumberTable:
        line 235: 0
      LocalVariableTable:
        Start  Length  Slot  Name   Signature
            0       5     0  this   Lcoursier/Fetch$Result$;
}
InnerClasses:
  public static final #12= #9 of #11;     // Result=class coursier/Fetch$Result of class coursier/Fetch
  public static #13= #2 of #11;           // =class coursier/Fetch$Result$ of class coursier/Fetch
  public static #13= #15 of #17;          // =class coursier/package$Resolution$ of class coursier/package
SourceFile: "Fetch.scala"
  ScalaInlineInfo: length = 0x18 (unknown attribute)
   01 01 00 04 00 17 00 16 01 00 1C 00 1D 01 00 1C
   00 2D 01 00 34 00 35 01
  Scala: length = 0x0 (unknown attribute)

