Classfile /Users/mw/Projects/slang-braindump/.jar/jar8/assemble/slang-braindump/assemble/content/coursier/LocalRepositories$.class
  Last modified May 29, 2022; size 4424 bytes
  SHA-256 checksum 8a889d33f3252ca535ccb4361a2dffd4d116c807d546b9ebc35da2152a87bfad
  Compiled from "LocalRepositories.scala"
public final class coursier.LocalRepositories$
  minor version: 0
  major version: 52
  flags: (0x0031) ACC_PUBLIC, ACC_FINAL, ACC_SUPER
  this_class: #2                          // coursier/LocalRepositories$
  super_class: #4                         // java/lang/Object
  interfaces: 0, fields: 4, methods: 9, attributes: 5
Constant pool:
    #1 = Utf8               coursier/LocalRepositories$
    #2 = Class              #1            // coursier/LocalRepositories$
    #3 = Utf8               java/lang/Object
    #4 = Class              #3            // java/lang/Object
    #5 = Utf8               LocalRepositories.scala
    #6 = Utf8               coursier/ivy/Pattern$Chunk
    #7 = Class              #6            // coursier/ivy/Pattern$Chunk
    #8 = Utf8               coursier/ivy/Pattern
    #9 = Class              #8            // coursier/ivy/Pattern
   #10 = Utf8               Chunk
   #11 = Utf8               coursier/ivy/Pattern$Chunk$
   #12 = Class              #11           // coursier/ivy/Pattern$Chunk$
   #13 = Utf8
   #14 = Utf8               java/lang/invoke/MethodHandles$Lookup
   #15 = Class              #14           // java/lang/invoke/MethodHandles$Lookup
   #16 = Utf8               java/lang/invoke/MethodHandles
   #17 = Class              #16           // java/lang/invoke/MethodHandles
   #18 = Utf8               Lookup
   #19 = Utf8               MODULE$
   #20 = Utf8               Lcoursier/LocalRepositories$;
   #21 = Utf8               coursier$LocalRepositories$$ivy2HomeUri
   #22 = Utf8               Ljava/lang/String;
   #23 = Utf8               ivy2Local
   #24 = Utf8               Lcoursier/ivy/IvyRepository;
   #25 = Utf8               bitmap$0
   #26 = Utf8               B
   #27 = Utf8               <clinit>
   #28 = Utf8               ()V
   #29 = Utf8               <init>
   #30 = NameAndType        #29:#28       // "<init>":()V
   #31 = Methodref          #2.#30        // coursier/LocalRepositories$."<init>":()V
   #32 = NameAndType        #19:#20       // MODULE$:Lcoursier/LocalRepositories$;
   #33 = Fieldref           #2.#32        // coursier/LocalRepositories$.MODULE$:Lcoursier/LocalRepositories$;
   #34 = Utf8               ivy2HomeUri$lzycompute
   #35 = Utf8               ()Ljava/lang/String;
   #36 = NameAndType        #25:#26       // bitmap$0:B
   #37 = Fieldref           #2.#36        // coursier/LocalRepositories$.bitmap$0:B
   #38 = Utf8               scala/sys/package$
   #39 = Class              #38           // scala/sys/package$
   #40 = Utf8               Lscala/sys/package$;
   #41 = NameAndType        #19:#40       // MODULE$:Lscala/sys/package$;
   #42 = Fieldref           #39.#41       // scala/sys/package$.MODULE$:Lscala/sys/package$;
   #43 = Utf8               props
   #44 = Utf8               ()Lscala/sys/SystemProperties;
   #45 = NameAndType        #43:#44       // props:()Lscala/sys/SystemProperties;
   #46 = Methodref          #39.#45       // scala/sys/package$.props:()Lscala/sys/SystemProperties;
   #47 = Utf8               coursier.ivy.home
   #48 = String             #47           // coursier.ivy.home
   #49 = Utf8               scala/sys/SystemProperties
   #50 = Class              #49           // scala/sys/SystemProperties
   #51 = Utf8               get
   #52 = Utf8               (Ljava/lang/String;)Lscala/Option;
   #53 = NameAndType        #51:#52       // get:(Ljava/lang/String;)Lscala/Option;
   #54 = Methodref          #50.#53       // scala/sys/SystemProperties.get:(Ljava/lang/String;)Lscala/Option;
   #55 = Utf8               ()Ljava/lang/Object;
   #56 = MethodType         #55           //  ()Ljava/lang/Object;
   #57 = Utf8               $anonfun$ivy2HomeUri$1
   #58 = Utf8               ()Lscala/Option;
   #59 = NameAndType        #57:#58       // $anonfun$ivy2HomeUri$1:()Lscala/Option;
   #60 = Methodref          #2.#59        // coursier/LocalRepositories$.$anonfun$ivy2HomeUri$1:()Lscala/Option;
   #61 = MethodHandle       6:#60         // REF_invokeStatic coursier/LocalRepositories$.$anonfun$ivy2HomeUri$1:()Lscala/Option;
   #62 = MethodType         #58           //  ()Lscala/Option;
   #63 = Integer            5
   #64 = Integer            1
   #65 = Utf8               java/lang/invoke/LambdaMetafactory
   #66 = Class              #65           // java/lang/invoke/LambdaMetafactory
   #67 = Utf8               altMetafactory
   #68 = Utf8               (Ljava/lang/invoke/MethodHandles$Lookup;Ljava/lang/String;Ljava/lang/invoke/MethodType;[Ljava/lang/Object;)Ljava/lang/invoke/CallSite;
   #69 = NameAndType        #67:#68       // altMetafactory:(Ljava/lang/invoke/MethodHandles$Lookup;Ljava/lang/String;Ljava/lang/invoke/MethodType;[Ljava/lang/Object;)Ljava/lang/invoke/CallSite;
   #70 = Methodref          #66.#69       // java/lang/invoke/LambdaMetafactory.altMetafactory:(Ljava/lang/invoke/MethodHandles$Lookup;Ljava/lang/String;Ljava/lang/invoke/MethodType;[Ljava/lang/Object;)Ljava/lang/invoke/CallSite;
   #71 = MethodHandle       6:#70         // REF_invokeStatic java/lang/invoke/LambdaMetafactory.altMetafactory:(Ljava/lang/invoke/MethodHandles$Lookup;Ljava/lang/String;Ljava/lang/invoke/MethodType;[Ljava/lang/Object;)Ljava/lang/invoke/CallSite;
   #72 = Utf8               apply
   #73 = Utf8               ()Lscala/Function0;
   #74 = NameAndType        #72:#73       // apply:()Lscala/Function0;
   #75 = InvokeDynamic      #0:#74        // #0:apply:()Lscala/Function0;
   #76 = Utf8               scala/Option
   #77 = Class              #76           // scala/Option
   #78 = Utf8               orElse
   #79 = Utf8               (Lscala/Function0;)Lscala/Option;
   #80 = NameAndType        #78:#79       // orElse:(Lscala/Function0;)Lscala/Option;
   #81 = Methodref          #77.#80       // scala/Option.orElse:(Lscala/Function0;)Lscala/Option;
   #82 = Utf8               $anonfun$ivy2HomeUri$2
   #83 = NameAndType        #82:#35       // $anonfun$ivy2HomeUri$2:()Ljava/lang/String;
   #84 = Methodref          #2.#83        // coursier/LocalRepositories$.$anonfun$ivy2HomeUri$2:()Ljava/lang/String;
   #85 = MethodHandle       6:#84         // REF_invokeStatic coursier/LocalRepositories$.$anonfun$ivy2HomeUri$2:()Ljava/lang/String;
   #86 = MethodType         #35           //  ()Ljava/lang/String;
   #87 = InvokeDynamic      #1:#74        // #1:apply:()Lscala/Function0;
   #88 = Utf8               getOrElse
   #89 = Utf8               (Lscala/Function0;)Ljava/lang/Object;
   #90 = NameAndType        #88:#89       // getOrElse:(Lscala/Function0;)Ljava/lang/Object;
   #91 = Methodref          #77.#90       // scala/Option.getOrElse:(Lscala/Function0;)Ljava/lang/Object;
   #92 = Utf8               java/lang/String
   #93 = Class              #92           // java/lang/String
   #94 = Utf8               java/io/File
   #95 = Class              #94           // java/io/File
   #96 = Utf8               (Ljava/lang/String;)V
   #97 = NameAndType        #29:#96       // "<init>":(Ljava/lang/String;)V
   #98 = Methodref          #95.#97       // java/io/File."<init>":(Ljava/lang/String;)V
   #99 = Utf8               toURI
  #100 = Utf8               ()Ljava/net/URI;
  #101 = NameAndType        #99:#100      // toURI:()Ljava/net/URI;
  #102 = Methodref          #95.#101      // java/io/File.toURI:()Ljava/net/URI;
  #103 = Utf8               java/net/URI
  #104 = Class              #103          // java/net/URI
  #105 = Utf8               toString
  #106 = NameAndType        #105:#35      // toString:()Ljava/lang/String;
  #107 = Methodref          #104.#106     // java/net/URI.toString:()Ljava/lang/String;
  #108 = Utf8               /
  #109 = String             #108          // /
  #110 = Utf8               endsWith
  #111 = Utf8               (Ljava/lang/String;)Z
  #112 = NameAndType        #110:#111     // endsWith:(Ljava/lang/String;)Z
  #113 = Methodref          #93.#112      // java/lang/String.endsWith:(Ljava/lang/String;)Z
  #114 = Utf8               java/lang/StringBuilder
  #115 = Class              #114          // java/lang/StringBuilder
  #116 = Utf8               (I)V
  #117 = NameAndType        #29:#116      // "<init>":(I)V
  #118 = Methodref          #115.#117     // java/lang/StringBuilder."<init>":(I)V
  #119 = Utf8               append
  #120 = Utf8               (Ljava/lang/String;)Ljava/lang/StringBuilder;
  #121 = NameAndType        #119:#120     // append:(Ljava/lang/String;)Ljava/lang/StringBuilder;
  #122 = Methodref          #115.#121     // java/lang/StringBuilder.append:(Ljava/lang/String;)Ljava/lang/StringBuilder;
  #123 = Methodref          #115.#106     // java/lang/StringBuilder.toString:()Ljava/lang/String;
  #124 = NameAndType        #21:#22       // coursier$LocalRepositories$$ivy2HomeUri:Ljava/lang/String;
  #125 = Fieldref           #2.#124       // coursier/LocalRepositories$.coursier$LocalRepositories$$ivy2HomeUri:Ljava/lang/String;
  #126 = Utf8               java/lang/Throwable
  #127 = Class              #126          // java/lang/Throwable
  #128 = Utf8               path
  #129 = Utf8               str
  #130 = Utf8               this
  #131 = NameAndType        #34:#35       // ivy2HomeUri$lzycompute:()Ljava/lang/String;
  #132 = Methodref          #2.#131       // coursier/LocalRepositories$.ivy2HomeUri$lzycompute:()Ljava/lang/String;
  #133 = Utf8               ivy2Local$lzycompute
  #134 = Utf8               ()Lcoursier/ivy/IvyRepository;
  #135 = Integer            6
  #136 = NameAndType        #21:#35       // coursier$LocalRepositories$$ivy2HomeUri:()Ljava/lang/String;
  #137 = Methodref          #2.#136       // coursier/LocalRepositories$.coursier$LocalRepositories$$ivy2HomeUri:()Ljava/lang/String;
  #138 = Utf8               local/
  #139 = String             #138          // local/
  #140 = Utf8               coursier/ivy/Pattern$
  #141 = Class              #140          // coursier/ivy/Pattern$
  #142 = Utf8               Lcoursier/ivy/Pattern$;
  #143 = NameAndType        #19:#142      // MODULE$:Lcoursier/ivy/Pattern$;
  #144 = Fieldref           #141.#143     // coursier/ivy/Pattern$.MODULE$:Lcoursier/ivy/Pattern$;
  #145 = Utf8               default
  #146 = Utf8               ()Lcoursier/ivy/Pattern;
  #147 = NameAndType        #145:#146     // default:()Lcoursier/ivy/Pattern;
  #148 = Methodref          #141.#147     // coursier/ivy/Pattern$.default:()Lcoursier/ivy/Pattern;
  #149 = Utf8               Lcoursier/ivy/Pattern$Chunk$;
  #150 = NameAndType        #19:#149      // MODULE$:Lcoursier/ivy/Pattern$Chunk$;
  #151 = Fieldref           #12.#150      // coursier/ivy/Pattern$Chunk$.MODULE$:Lcoursier/ivy/Pattern$Chunk$;
  #152 = Utf8               fromString
  #153 = Utf8               (Ljava/lang/String;)Lcoursier/ivy/Pattern$Chunk;
  #154 = NameAndType        #152:#153     // fromString:(Ljava/lang/String;)Lcoursier/ivy/Pattern$Chunk;
  #155 = Methodref          #12.#154      // coursier/ivy/Pattern$Chunk$.fromString:(Ljava/lang/String;)Lcoursier/ivy/Pattern$Chunk;
  #156 = Utf8               $plus$colon
  #157 = Utf8               (Lcoursier/ivy/Pattern$Chunk;)Lcoursier/ivy/Pattern;
  #158 = NameAndType        #156:#157     // $plus$colon:(Lcoursier/ivy/Pattern$Chunk;)Lcoursier/ivy/Pattern;
  #159 = Methodref          #9.#158       // coursier/ivy/Pattern.$plus$colon:(Lcoursier/ivy/Pattern$Chunk;)Lcoursier/ivy/Pattern;
  #160 = Utf8               coursier/ivy/IvyRepository$
  #161 = Class              #160          // coursier/ivy/IvyRepository$
  #162 = Utf8               Lcoursier/ivy/IvyRepository$;
  #163 = NameAndType        #19:#162      // MODULE$:Lcoursier/ivy/IvyRepository$;
  #164 = Fieldref           #161.#163     // coursier/ivy/IvyRepository$.MODULE$:Lcoursier/ivy/IvyRepository$;
  #165 = Utf8               fromPattern$default$2
  #166 = NameAndType        #165:#58      // fromPattern$default$2:()Lscala/Option;
  #167 = Methodref          #161.#166     // coursier/ivy/IvyRepository$.fromPattern$default$2:()Lscala/Option;
  #168 = Utf8               fromPattern$default$3
  #169 = NameAndType        #168:#58      // fromPattern$default$3:()Lscala/Option;
  #170 = Methodref          #161.#169     // coursier/ivy/IvyRepository$.fromPattern$default$3:()Lscala/Option;
  #171 = Utf8               fromPattern$default$4
  #172 = Utf8               ()Z
  #173 = NameAndType        #171:#172     // fromPattern$default$4:()Z
  #174 = Methodref          #161.#173     // coursier/ivy/IvyRepository$.fromPattern$default$4:()Z
  #175 = Utf8               fromPattern$default$5
  #176 = NameAndType        #175:#172     // fromPattern$default$5:()Z
  #177 = Methodref          #161.#176     // coursier/ivy/IvyRepository$.fromPattern$default$5:()Z
  #178 = Utf8               fromPattern$default$6
  #179 = NameAndType        #178:#172     // fromPattern$default$6:()Z
  #180 = Methodref          #161.#179     // coursier/ivy/IvyRepository$.fromPattern$default$6:()Z
  #181 = Utf8               fromPattern$default$8
  #182 = NameAndType        #181:#58      // fromPattern$default$8:()Lscala/Option;
  #183 = Methodref          #161.#182     // coursier/ivy/IvyRepository$.fromPattern$default$8:()Lscala/Option;
  #184 = Utf8               fromPattern
  #185 = Utf8               (Lcoursier/ivy/Pattern;Lscala/Option;Lscala/Option;ZZZZLscala/Option;)Lcoursier/ivy/IvyRepository;
  #186 = NameAndType        #184:#185     // fromPattern:(Lcoursier/ivy/Pattern;Lscala/Option;Lscala/Option;ZZZZLscala/Option;)Lcoursier/ivy/IvyRepository;
  #187 = Methodref          #161.#186     // coursier/ivy/IvyRepository$.fromPattern:(Lcoursier/ivy/Pattern;Lscala/Option;Lscala/Option;ZZZZLscala/Option;)Lcoursier/ivy/IvyRepository;
  #188 = NameAndType        #23:#24       // ivy2Local:Lcoursier/ivy/IvyRepository;
  #189 = Fieldref           #2.#188       // coursier/LocalRepositories$.ivy2Local:Lcoursier/ivy/IvyRepository;
  #190 = Utf8               x$1
  #191 = Utf8               Lcoursier/ivy/Pattern;
  #192 = Utf8               x$2
  #193 = Utf8               Z
  #194 = Utf8               x$3
  #195 = Utf8               Lscala/Option;
  #196 = Utf8               x$4
  #197 = Utf8               x$5
  #198 = Utf8               x$6
  #199 = Utf8               x$7
  #200 = Utf8               x$8
  #201 = NameAndType        #133:#134     // ivy2Local$lzycompute:()Lcoursier/ivy/IvyRepository;
  #202 = Methodref          #2.#201       // coursier/LocalRepositories$.ivy2Local$lzycompute:()Lcoursier/ivy/IvyRepository;
  #203 = Utf8               coursier/ivy/IvyRepository
  #204 = Class              #203          // coursier/ivy/IvyRepository
  #205 = Utf8               ivy.home
  #206 = String             #205          // ivy.home
  #207 = Integer            7
  #208 = Utf8               user.home
  #209 = String             #208          // user.home
  #210 = Utf8               (Ljava/lang/Object;)Ljava/lang/Object;
  #211 = NameAndType        #72:#210      // apply:(Ljava/lang/Object;)Ljava/lang/Object;
  #212 = Methodref          #50.#211      // scala/sys/SystemProperties.apply:(Ljava/lang/Object;)Ljava/lang/Object;
  #213 = Utf8               /.ivy2/
  #214 = String             #213          // /.ivy2/
  #215 = Methodref          #4.#30        // java/lang/Object."<init>":()V
  #216 = Utf8               $deserializeLambda$
  #217 = Utf8               (Ljava/lang/invoke/SerializedLambda;)Ljava/lang/Object;
  #218 = Utf8               scala/runtime/LambdaDeserialize
  #219 = Class              #218          // scala/runtime/LambdaDeserialize
  #220 = Utf8               bootstrap
  #221 = Utf8               (Ljava/lang/invoke/MethodHandles$Lookup;Ljava/lang/String;Ljava/lang/invoke/MethodType;[Ljava/lang/invoke/MethodHandle;)Ljava/lang/invoke/CallSite;
  #222 = NameAndType        #220:#221     // bootstrap:(Ljava/lang/invoke/MethodHandles$Lookup;Ljava/lang/String;Ljava/lang/invoke/MethodType;[Ljava/lang/invoke/MethodHandle;)Ljava/lang/invoke/CallSite;
  #223 = Methodref          #219.#222     // scala/runtime/LambdaDeserialize.bootstrap:(Ljava/lang/invoke/MethodHandles$Lookup;Ljava/lang/String;Ljava/lang/invoke/MethodType;[Ljava/lang/invoke/MethodHandle;)Ljava/lang/invoke/CallSite;
  #224 = MethodHandle       6:#223        // REF_invokeStatic scala/runtime/LambdaDeserialize.bootstrap:(Ljava/lang/invoke/MethodHandles$Lookup;Ljava/lang/String;Ljava/lang/invoke/MethodType;[Ljava/lang/invoke/MethodHandle;)Ljava/lang/invoke/CallSite;
  #225 = Utf8               lambdaDeserialize
  #226 = NameAndType        #225:#217     // lambdaDeserialize:(Ljava/lang/invoke/SerializedLambda;)Ljava/lang/Object;
  #227 = InvokeDynamic      #2:#226       // #2:lambdaDeserialize:(Ljava/lang/invoke/SerializedLambda;)Ljava/lang/Object;
  #228 = Utf8               Code
  #229 = Utf8               LineNumberTable
  #230 = Utf8               StackMapTable
  #231 = Utf8               LocalVariableTable
  #232 = Utf8               InnerClasses
  #233 = Utf8               SourceFile
  #234 = Utf8               BootstrapMethods
  #235 = Utf8               ScalaInlineInfo
  #236 = Utf8               Scala
{
  public static final coursier.LocalRepositories$ MODULE$;
    descriptor: Lcoursier/LocalRepositories$;
    flags: (0x0019) ACC_PUBLIC, ACC_STATIC, ACC_FINAL

  private static java.lang.String coursier$LocalRepositories$$ivy2HomeUri;
    descriptor: Ljava/lang/String;
    flags: (0x000a) ACC_PRIVATE, ACC_STATIC

  private static coursier.ivy.IvyRepository ivy2Local;
    descriptor: Lcoursier/ivy/IvyRepository;
    flags: (0x000a) ACC_PRIVATE, ACC_STATIC

  private static volatile byte bitmap$0;
    descriptor: B
    flags: (0x004a) ACC_PRIVATE, ACC_STATIC, ACC_VOLATILE

  public static {};
    descriptor: ()V
    flags: (0x0009) ACC_PUBLIC, ACC_STATIC
    Code:
      stack=2, locals=0, args_size=0
         0: new           #2                  // class coursier/LocalRepositories$
         3: dup
         4: invokespecial #31                 // Method "<init>":()V
         7: putstatic     #33                 // Field MODULE$:Lcoursier/LocalRepositories$;
        10: return
      LineNumberTable:
        line 9: 0

  private java.lang.String ivy2HomeUri$lzycompute();
    descriptor: ()Ljava/lang/String;
    flags: (0x0002) ACC_PRIVATE
    Code:
      stack=3, locals=4, args_size=1
         0: aload_0
         1: dup
         2: astore_1
         3: monitorenter
         4: getstatic     #37                 // Field bitmap$0:B
         7: iconst_1
         8: iand
         9: i2b
        10: iconst_0
        11: if_icmpne     106
        14: getstatic     #42                 // Field scala/sys/package$.MODULE$:Lscala/sys/package$;
        17: invokevirtual #46                 // Method scala/sys/package$.props:()Lscala/sys/SystemProperties;
        20: ldc           #48                 // String coursier.ivy.home
        22: invokevirtual #54                 // Method scala/sys/SystemProperties.get:(Ljava/lang/String;)Lscala/Option;
        25: invokedynamic #75,  0             // InvokeDynamic #0:apply:()Lscala/Function0;
        30: invokevirtual #81                 // Method scala/Option.orElse:(Lscala/Function0;)Lscala/Option;
        33: invokedynamic #87,  0             // InvokeDynamic #1:apply:()Lscala/Function0;
        38: invokevirtual #91                 // Method scala/Option.getOrElse:(Lscala/Function0;)Ljava/lang/Object;
        41: checkcast     #93                 // class java/lang/String
        44: astore_2
        45: new           #95                 // class java/io/File
        48: dup
        49: aload_2
        50: invokespecial #98                 // Method java/io/File."<init>":(Ljava/lang/String;)V
        53: invokevirtual #102                // Method java/io/File.toURI:()Ljava/net/URI;
        56: invokevirtual #107                // Method java/net/URI.toString:()Ljava/lang/String;
        59: astore_3
        60: aload_3
        61: ldc           #109                // String /
        63: invokevirtual #113                // Method java/lang/String.endsWith:(Ljava/lang/String;)Z
        66: ifeq          73
        69: aload_3
        70: goto          94
        73: new           #115                // class java/lang/StringBuilder
        76: dup
        77: ldc           #64                 // int 1
        79: invokespecial #118                // Method java/lang/StringBuilder."<init>":(I)V
        82: aload_3
        83: invokevirtual #122                // Method java/lang/StringBuilder.append:(Ljava/lang/String;)Ljava/lang/StringBuilder;
        86: ldc           #109                // String /
        88: invokevirtual #122                // Method java/lang/StringBuilder.append:(Ljava/lang/String;)Ljava/lang/StringBuilder;
        91: invokevirtual #123                // Method java/lang/StringBuilder.toString:()Ljava/lang/String;
        94: putstatic     #125                // Field coursier$LocalRepositories$$ivy2HomeUri:Ljava/lang/String;
        97: getstatic     #37                 // Field bitmap$0:B
       100: iconst_1
       101: ior
       102: i2b
       103: putstatic     #37                 // Field bitmap$0:B
       106: aload_1
       107: monitorexit
       108: goto          114
       111: aload_1
       112: monitorexit
       113: athrow
       114: getstatic     #125                // Field coursier$LocalRepositories$$ivy2HomeUri:Ljava/lang/String;
       117: areturn
      Exception table:
         from    to  target type
             4   106   111   any
      StackMapTable: number_of_entries = 5
        frame_type = 254 /* append */
          offset_delta = 73
          locals = [ class coursier/LocalRepositories$, class java/lang/String, class java/lang/String ]
        frame_type = 84 /* same_locals_1_stack_item */
          stack = [ class java/lang/String ]
        frame_type = 249 /* chop */
          offset_delta = 11
        frame_type = 68 /* same_locals_1_stack_item */
          stack = [ class java/lang/Throwable ]
        frame_type = 2 /* same */
      LineNumberTable:
        line 11: 0
        line 14: 14
        line 15: 25
        line 16: 33
        line 19: 45
        line 20: 60
        line 21: 69
        line 23: 73
        line 11: 94
      LocalVariableTable:
        Start  Length  Slot  Name   Signature
           45      49     2  path   Ljava/lang/String;
           60      34     3   str   Ljava/lang/String;
            0     118     0  this   Lcoursier/LocalRepositories$;

  public java.lang.String coursier$LocalRepositories$$ivy2HomeUri();
    descriptor: ()Ljava/lang/String;
    flags: (0x0001) ACC_PUBLIC
    Code:
      stack=2, locals=1, args_size=1
         0: getstatic     #37                 // Field bitmap$0:B
         3: iconst_1
         4: iand
         5: i2b
         6: iconst_0
         7: if_icmpne     17
        10: aload_0
        11: invokespecial #132                // Method ivy2HomeUri$lzycompute:()Ljava/lang/String;
        14: goto          20
        17: getstatic     #125                // Field coursier$LocalRepositories$$ivy2HomeUri:Ljava/lang/String;
        20: areturn
      StackMapTable: number_of_entries = 2
        frame_type = 17 /* same */
        frame_type = 66 /* same_locals_1_stack_item */
          stack = [ class java/lang/String ]
      LineNumberTable:
        line 11: 0
      LocalVariableTable:
        Start  Length  Slot  Name   Signature
            0      21     0  this   Lcoursier/LocalRepositories$;

  private coursier.ivy.IvyRepository ivy2Local$lzycompute();
    descriptor: ()Lcoursier/ivy/IvyRepository;
    flags: (0x0002) ACC_PRIVATE
    Code:
      stack=9, locals=11, args_size=1
         0: aload_0
         1: dup
         2: astore_1
         3: monitorenter
         4: getstatic     #37                 // Field bitmap$0:B
         7: iconst_2
         8: iand
         9: i2b
        10: iconst_0
        11: if_icmpne     139
        14: new           #115                // class java/lang/StringBuilder
        17: dup
        18: ldc           #135                // int 6
        20: invokespecial #118                // Method java/lang/StringBuilder."<init>":(I)V
        23: aload_0
        24: invokevirtual #137                // Method coursier$LocalRepositories$$ivy2HomeUri:()Ljava/lang/String;
        27: invokevirtual #122                // Method java/lang/StringBuilder.append:(Ljava/lang/String;)Ljava/lang/StringBuilder;
        30: ldc           #139                // String local/
        32: invokevirtual #122                // Method java/lang/StringBuilder.append:(Ljava/lang/String;)Ljava/lang/StringBuilder;
        35: invokevirtual #123                // Method java/lang/StringBuilder.toString:()Ljava/lang/String;
        38: astore_3
        39: getstatic     #144                // Field coursier/ivy/Pattern$.MODULE$:Lcoursier/ivy/Pattern$;
        42: invokevirtual #148                // Method coursier/ivy/Pattern$.default:()Lcoursier/ivy/Pattern;
        45: getstatic     #151                // Field coursier/ivy/Pattern$Chunk$.MODULE$:Lcoursier/ivy/Pattern$Chunk$;
        48: aload_3
        49: invokevirtual #155                // Method coursier/ivy/Pattern$Chunk$.fromString:(Ljava/lang/String;)Lcoursier/ivy/Pattern$Chunk;
        52: invokevirtual #159                // Method coursier/ivy/Pattern.$plus$colon:(Lcoursier/ivy/Pattern$Chunk;)Lcoursier/ivy/Pattern;
        55: astore_2
        56: iconst_1
        57: istore        4
        59: getstatic     #164                // Field coursier/ivy/IvyRepository$.MODULE$:Lcoursier/ivy/IvyRepository$;
        62: invokevirtual #167                // Method coursier/ivy/IvyRepository$.fromPattern$default$2:()Lscala/Option;
        65: astore        5
        67: getstatic     #164                // Field coursier/ivy/IvyRepository$.MODULE$:Lcoursier/ivy/IvyRepository$;
        70: invokevirtual #170                // Method coursier/ivy/IvyRepository$.fromPattern$default$3:()Lscala/Option;
        73: astore        6
        75: getstatic     #164                // Field coursier/ivy/IvyRepository$.MODULE$:Lcoursier/ivy/IvyRepository$;
        78: invokevirtual #174                // Method coursier/ivy/IvyRepository$.fromPattern$default$4:()Z
        81: istore        7
        83: getstatic     #164                // Field coursier/ivy/IvyRepository$.MODULE$:Lcoursier/ivy/IvyRepository$;
        86: invokevirtual #177                // Method coursier/ivy/IvyRepository$.fromPattern$default$5:()Z
        89: istore        8
        91: getstatic     #164                // Field coursier/ivy/IvyRepository$.MODULE$:Lcoursier/ivy/IvyRepository$;
        94: invokevirtual #180                // Method coursier/ivy/IvyRepository$.fromPattern$default$6:()Z
        97: istore        9
        99: getstatic     #164                // Field coursier/ivy/IvyRepository$.MODULE$:Lcoursier/ivy/IvyRepository$;
       102: invokevirtual #183                // Method coursier/ivy/IvyRepository$.fromPattern$default$8:()Lscala/Option;
       105: astore        10
       107: getstatic     #164                // Field coursier/ivy/IvyRepository$.MODULE$:Lcoursier/ivy/IvyRepository$;
       110: aload_2
       111: aload         5
       113: aload         6
       115: iload         7
       117: iload         8
       119: iload         9
       121: iconst_1
       122: aload         10
       124: invokevirtual #187                // Method coursier/ivy/IvyRepository$.fromPattern:(Lcoursier/ivy/Pattern;Lscala/Option;Lscala/Option;ZZZZLscala/Option;)Lcoursier/ivy/IvyRepository;
       127: putstatic     #189                // Field ivy2Local:Lcoursier/ivy/IvyRepository;
       130: getstatic     #37                 // Field bitmap$0:B
       133: iconst_2
       134: ior
       135: i2b
       136: putstatic     #37                 // Field bitmap$0:B
       139: aload_1
       140: monitorexit
       141: goto          147
       144: aload_1
       145: monitorexit
       146: athrow
       147: getstatic     #189                // Field ivy2Local:Lcoursier/ivy/IvyRepository;
       150: areturn
      Exception table:
         from    to  target type
             4   139   144   any
      StackMapTable: number_of_entries = 3
        frame_type = 252 /* append */
          offset_delta = 139
          locals = [ class coursier/LocalRepositories$ ]
        frame_type = 68 /* same_locals_1_stack_item */
          stack = [ class java/lang/Throwable ]
        frame_type = 2 /* same */
      LineNumberTable:
        line 26: 0
        line 27: 14
        line 28: 56
        line 26: 59
        line 27: 110
        line 26: 111
        line 28: 121
        line 26: 122
      LocalVariableTable:
        Start  Length  Slot  Name   Signature
           56      71     2   x$1   Lcoursier/ivy/Pattern;
           59      68     4   x$2   Z
           67      60     5   x$3   Lscala/Option;
           75      52     6   x$4   Lscala/Option;
           83      44     7   x$5   Z
           91      36     8   x$6   Z
           99      28     9   x$7   Z
          107      20    10   x$8   Lscala/Option;
            0     151     0  this   Lcoursier/LocalRepositories$;

  public coursier.ivy.IvyRepository ivy2Local();
    descriptor: ()Lcoursier/ivy/IvyRepository;
    flags: (0x0001) ACC_PUBLIC
    Code:
      stack=2, locals=1, args_size=1
         0: getstatic     #37                 // Field bitmap$0:B
         3: iconst_2
         4: iand
         5: i2b
         6: iconst_0
         7: if_icmpne     17
        10: aload_0
        11: invokespecial #202                // Method ivy2Local$lzycompute:()Lcoursier/ivy/IvyRepository;
        14: goto          20
        17: getstatic     #189                // Field ivy2Local:Lcoursier/ivy/IvyRepository;
        20: areturn
      StackMapTable: number_of_entries = 2
        frame_type = 17 /* same */
        frame_type = 66 /* same_locals_1_stack_item */
          stack = [ class coursier/ivy/IvyRepository ]
      LineNumberTable:
        line 26: 0
      LocalVariableTable:
        Start  Length  Slot  Name   Signature
            0      21     0  this   Lcoursier/LocalRepositories$;

  public static final scala.Option $anonfun$ivy2HomeUri$1();
    descriptor: ()Lscala/Option;
    flags: (0x1019) ACC_PUBLIC, ACC_STATIC, ACC_FINAL, ACC_SYNTHETIC
    Code:
      stack=2, locals=0, args_size=0
         0: getstatic     #42                 // Field scala/sys/package$.MODULE$:Lscala/sys/package$;
         3: invokevirtual #46                 // Method scala/sys/package$.props:()Lscala/sys/SystemProperties;
         6: ldc           #206                // String ivy.home
         8: invokevirtual #54                 // Method scala/sys/SystemProperties.get:(Ljava/lang/String;)Lscala/Option;
        11: areturn
      LineNumberTable:
        line 15: 0

  public static final java.lang.String $anonfun$ivy2HomeUri$2();
    descriptor: ()Ljava/lang/String;
    flags: (0x1019) ACC_PUBLIC, ACC_STATIC, ACC_FINAL, ACC_SYNTHETIC
    Code:
      stack=3, locals=0, args_size=0
         0: new           #115                // class java/lang/StringBuilder
         3: dup
         4: ldc           #207                // int 7
         6: invokespecial #118                // Method java/lang/StringBuilder."<init>":(I)V
         9: getstatic     #42                 // Field scala/sys/package$.MODULE$:Lscala/sys/package$;
        12: invokevirtual #46                 // Method scala/sys/package$.props:()Lscala/sys/SystemProperties;
        15: ldc           #209                // String user.home
        17: invokevirtual #212                // Method scala/sys/SystemProperties.apply:(Ljava/lang/Object;)Ljava/lang/Object;
        20: checkcast     #93                 // class java/lang/String
        23: invokevirtual #122                // Method java/lang/StringBuilder.append:(Ljava/lang/String;)Ljava/lang/StringBuilder;
        26: ldc           #214                // String /.ivy2/
        28: invokevirtual #122                // Method java/lang/StringBuilder.append:(Ljava/lang/String;)Ljava/lang/StringBuilder;
        31: invokevirtual #123                // Method java/lang/StringBuilder.toString:()Ljava/lang/String;
        34: areturn
      LineNumberTable:
        line 16: 0

  private coursier.LocalRepositories$();
    descriptor: ()V
    flags: (0x0002) ACC_PRIVATE
    Code:
      stack=1, locals=1, args_size=1
         0: aload_0
         1: invokespecial #215                // Method java/lang/Object."<init>":()V
         4: return
      LineNumberTable:
        line 69: 0
        line 9: 4
      LocalVariableTable:
        Start  Length  Slot  Name   Signature
            0       5     0  this   Lcoursier/LocalRepositories$;

  private static java.lang.Object $deserializeLambda$(java.lang.invoke.SerializedLambda);
    descriptor: (Ljava/lang/invoke/SerializedLambda;)Ljava/lang/Object;
    flags: (0x100a) ACC_PRIVATE, ACC_STATIC, ACC_SYNTHETIC
    Code:
      stack=1, locals=1, args_size=1
         0: aload_0
         1: invokedynamic #227,  0            // InvokeDynamic #2:lambdaDeserialize:(Ljava/lang/invoke/SerializedLambda;)Ljava/lang/Object;
         6: areturn
}
InnerClasses:
  public static abstract #10= #7 of #9;   // Chunk=class coursier/ivy/Pattern$Chunk of class coursier/ivy/Pattern
  public static #13= #12 of #9;           // =class coursier/ivy/Pattern$Chunk$ of class coursier/ivy/Pattern
  public static final #18= #15 of #17;    // Lookup=class java/lang/invoke/MethodHandles$Lookup of class java/lang/invoke/MethodHandles
SourceFile: "LocalRepositories.scala"
BootstrapMethods:
  0: #71 REF_invokeStatic java/lang/invoke/LambdaMetafactory.altMetafactory:(Ljava/lang/invoke/MethodHandles$Lookup;Ljava/lang/String;Ljava/lang/invoke/MethodType;[Ljava/lang/Object;)Ljava/lang/invoke/CallSite;
    Method arguments:
      #56 ()Ljava/lang/Object;
      #61 REF_invokeStatic coursier/LocalRepositories$.$anonfun$ivy2HomeUri$1:()Lscala/Option;
      #62 ()Lscala/Option;
      #63 5
      #64 1
      #62 ()Lscala/Option;
  1: #71 REF_invokeStatic java/lang/invoke/LambdaMetafactory.altMetafactory:(Ljava/lang/invoke/MethodHandles$Lookup;Ljava/lang/String;Ljava/lang/invoke/MethodType;[Ljava/lang/Object;)Ljava/lang/invoke/CallSite;
    Method arguments:
      #56 ()Ljava/lang/Object;
      #85 REF_invokeStatic coursier/LocalRepositories$.$anonfun$ivy2HomeUri$2:()Ljava/lang/String;
      #86 ()Ljava/lang/String;
      #63 5
      #64 1
      #86 ()Ljava/lang/String;
  2: #224 REF_invokeStatic scala/runtime/LambdaDeserialize.bootstrap:(Ljava/lang/invoke/MethodHandles$Lookup;Ljava/lang/String;Ljava/lang/invoke/MethodType;[Ljava/lang/invoke/MethodHandle;)Ljava/lang/invoke/CallSite;
    Method arguments:
      #61 REF_invokeStatic coursier/LocalRepositories$.$anonfun$ivy2HomeUri$1:()Lscala/Option;
      #85 REF_invokeStatic coursier/LocalRepositories$.$anonfun$ivy2HomeUri$2:()Ljava/lang/String;
  ScalaInlineInfo: length = 0x27 (unknown attribute)
   01 01 00 07 00 39 00 3A 01 00 52 00 23 01 00 1D
   00 1C 01 00 15 00 23 01 00 22 00 23 01 00 17 00
   86 01 00 85 00 86 01
  Scala: length = 0x0 (unknown attribute)

