Classfile /Users/mw/Projects/slang-braindump/.jar/jar8/assemble/slang-braindump/assemble/content/coursier/package$Resolution$.class
  Last modified May 29, 2022; size 1415 bytes
  SHA-256 checksum a6013e10bdbf851f9132f8c6a1ab62afd2d7d9c375396069c4f6e14003660342
  Compiled from "package.scala"
public class coursier.package$Resolution$
  minor version: 0
  major version: 52
  flags: (0x0021) ACC_PUBLIC, ACC_SUPER
  this_class: #2                          // coursier/package$Resolution$
  super_class: #4                         // java/lang/Object
  interfaces: 0, fields: 2, methods: 6, attributes: 4
Constant pool:
   #1 = Utf8               coursier/package$Resolution$
   #2 = Class              #1             // coursier/package$Resolution$
   #3 = Utf8               java/lang/Object
   #4 = Class              #3             // java/lang/Object
   #5 = Utf8               package.scala
   #6 = Utf8               coursier/package
   #7 = Class              #6             // coursier/package
   #8 = Utf8
   #9 = Utf8               MODULE$
  #10 = Utf8               Lcoursier/package$Resolution$;
  #11 = Utf8               empty
  #12 = Utf8               Lcoursier/core/Resolution;
  #13 = Utf8               <clinit>
  #14 = Utf8               ()V
  #15 = Utf8               <init>
  #16 = NameAndType        #15:#14        // "<init>":()V
  #17 = Methodref          #2.#16         // coursier/package$Resolution$."<init>":()V
  #18 = NameAndType        #9:#10         // MODULE$:Lcoursier/package$Resolution$;
  #19 = Fieldref           #2.#18         // coursier/package$Resolution$.MODULE$:Lcoursier/package$Resolution$;
  #20 = Utf8               apply
  #21 = Utf8               ()Lcoursier/core/Resolution;
  #22 = NameAndType        #20:#21        // apply:()Lcoursier/core/Resolution;
  #23 = Methodref          #2.#22         // coursier/package$Resolution$.apply:()Lcoursier/core/Resolution;
  #24 = NameAndType        #11:#12        // empty:Lcoursier/core/Resolution;
  #25 = Fieldref           #2.#24         // coursier/package$Resolution$.empty:Lcoursier/core/Resolution;
  #26 = Utf8               this
  #27 = Utf8               coursier/core/Resolution$
  #28 = Class              #27            // coursier/core/Resolution$
  #29 = Utf8               Lcoursier/core/Resolution$;
  #30 = NameAndType        #9:#29         // MODULE$:Lcoursier/core/Resolution$;
  #31 = Fieldref           #28.#30        // coursier/core/Resolution$.MODULE$:Lcoursier/core/Resolution$;
  #32 = Methodref          #28.#22        // coursier/core/Resolution$.apply:()Lcoursier/core/Resolution;
  #33 = Utf8               (Lscala/collection/immutable/Seq;)Lcoursier/core/Resolution;
  #34 = Utf8               (Lscala/collection/immutable/Seq<Lcoursier/core/Dependency;>;)Lcoursier/core/Resolution;
  #35 = Utf8               dependencies
  #36 = Utf8               coursier/core/Resolution
  #37 = Class              #36            // coursier/core/Resolution
  #38 = Utf8               withRootDependencies
  #39 = NameAndType        #38:#33        // withRootDependencies:(Lscala/collection/immutable/Seq;)Lcoursier/core/Resolution;
  #40 = Methodref          #37.#39        // coursier/core/Resolution.withRootDependencies:(Lscala/collection/immutable/Seq;)Lcoursier/core/Resolution;
  #41 = Utf8               Lscala/collection/immutable/Seq;
  #42 = Utf8               defaultTypes
  #43 = Utf8               ()Lscala/collection/immutable/Set;
  #44 = Utf8               ()Lscala/collection/immutable/Set<Lcoursier/core/Type;>;
  #45 = NameAndType        #42:#43        // defaultTypes:()Lscala/collection/immutable/Set;
  #46 = Methodref          #28.#45        // coursier/core/Resolution$.defaultTypes:()Lscala/collection/immutable/Set;
  #47 = Methodref          #4.#16         // java/lang/Object."<init>":()V
  #48 = Utf8               Code
  #49 = Utf8               LineNumberTable
  #50 = Utf8               LocalVariableTable
  #51 = Utf8               Signature
  #52 = Utf8               MethodParameters
  #53 = Utf8               InnerClasses
  #54 = Utf8               SourceFile
  #55 = Utf8               ScalaInlineInfo
  #56 = Utf8               Scala
{
  public static final coursier.package$Resolution$ MODULE$;
    descriptor: Lcoursier/package$Resolution$;
    flags: (0x0019) ACC_PUBLIC, ACC_STATIC, ACC_FINAL

  private static final coursier.core.Resolution empty;
    descriptor: Lcoursier/core/Resolution;
    flags: (0x001a) ACC_PRIVATE, ACC_STATIC, ACC_FINAL

  public static {};
    descriptor: ()V
    flags: (0x0009) ACC_PUBLIC, ACC_STATIC
    Code:
      stack=2, locals=0, args_size=0
         0: new           #2                  // class coursier/package$Resolution$
         3: dup
         4: invokespecial #17                 // Method "<init>":()V
         7: putstatic     #19                 // Field MODULE$:Lcoursier/package$Resolution$;
        10: getstatic     #19                 // Field MODULE$:Lcoursier/package$Resolution$;
        13: invokevirtual #23                 // Method apply:()Lcoursier/core/Resolution;
        16: putstatic     #25                 // Field empty:Lcoursier/core/Resolution;
        19: return
      LineNumberTable:
        line 64: 0
        line 65: 10
        line 64: 19

  public coursier.core.Resolution empty();
    descriptor: ()Lcoursier/core/Resolution;
    flags: (0x0001) ACC_PUBLIC
    Code:
      stack=1, locals=1, args_size=1
         0: getstatic     #25                 // Field empty:Lcoursier/core/Resolution;
         3: areturn
      LineNumberTable:
        line 65: 0
      LocalVariableTable:
        Start  Length  Slot  Name   Signature
            0       4     0  this   Lcoursier/package$Resolution$;

  public coursier.core.Resolution apply();
    descriptor: ()Lcoursier/core/Resolution;
    flags: (0x0001) ACC_PUBLIC
    Code:
      stack=1, locals=1, args_size=1
         0: getstatic     #31                 // Field coursier/core/Resolution$.MODULE$:Lcoursier/core/Resolution$;
         3: invokevirtual #32                 // Method coursier/core/Resolution$.apply:()Lcoursier/core/Resolution;
         6: areturn
      LineNumberTable:
        line 67: 0
      LocalVariableTable:
        Start  Length  Slot  Name   Signature
            0       7     0  this   Lcoursier/package$Resolution$;

  public coursier.core.Resolution apply(scala.collection.immutable.Seq<coursier.core.Dependency>);
    descriptor: (Lscala/collection/immutable/Seq;)Lcoursier/core/Resolution;
    flags: (0x0001) ACC_PUBLIC
    Code:
      stack=2, locals=2, args_size=2
         0: getstatic     #31                 // Field coursier/core/Resolution$.MODULE$:Lcoursier/core/Resolution$;
         3: invokevirtual #32                 // Method coursier/core/Resolution$.apply:()Lcoursier/core/Resolution;
         6: aload_1
         7: invokevirtual #40                 // Method coursier/core/Resolution.withRootDependencies:(Lscala/collection/immutable/Seq;)Lcoursier/core/Resolution;
        10: areturn
      LineNumberTable:
        line 69: 0
      LocalVariableTable:
        Start  Length  Slot  Name   Signature
            0      11     0  this   Lcoursier/package$Resolution$;
            0      11     1 dependencies   Lscala/collection/immutable/Seq;
    Signature: #34                          // (Lscala/collection/immutable/Seq<Lcoursier/core/Dependency;>;)Lcoursier/core/Resolution;
    MethodParameters:
      Name                           Flags
      dependencies                   final

  public scala.collection.immutable.Set<coursier.core.Type> defaultTypes();
    descriptor: ()Lscala/collection/immutable/Set;
    flags: (0x0001) ACC_PUBLIC
    Code:
      stack=1, locals=1, args_size=1
         0: getstatic     #31                 // Field coursier/core/Resolution$.MODULE$:Lcoursier/core/Resolution$;
         3: invokevirtual #46                 // Method coursier/core/Resolution$.defaultTypes:()Lscala/collection/immutable/Set;
         6: areturn
      LineNumberTable:
        line 71: 0
      LocalVariableTable:
        Start  Length  Slot  Name   Signature
            0       7     0  this   Lcoursier/package$Resolution$;
    Signature: #44                          // ()Lscala/collection/immutable/Set<Lcoursier/core/Type;>;

  public coursier.package$Resolution$();
    descriptor: ()V
    flags: (0x0001) ACC_PUBLIC
    Code:
      stack=1, locals=1, args_size=1
         0: aload_0
         1: invokespecial #47                 // Method java/lang/Object."<init>":()V
         4: return
      LineNumberTable:
        line 74: 0
        line 64: 4
      LocalVariableTable:
        Start  Length  Slot  Name   Signature
            0       5     0  this   Lcoursier/package$Resolution$;
}
InnerClasses:
  public static #8= #2 of #7;             // =class coursier/package$Resolution$ of class coursier/package
SourceFile: "package.scala"
  ScalaInlineInfo: length = 0x1D (unknown attribute)
   01 01 00 05 00 0F 00 0E 01 00 14 00 15 01 00 14
   00 21 01 00 2A 00 2B 01 00 0B 00 15 01
  Scala: length = 0x0 (unknown attribute)

