Classfile /Users/mw/Projects/slang-braindump/.jar/jar8/assemble/slang-braindump/assemble/content/coursier/PlatformResolve.class
  Last modified May 29, 2022; size 10224 bytes
  SHA-256 checksum 0681cef5956662922396a48f494853cb5486c0e4fcf04278f7bba5c963514802
  Compiled from "PlatformResolve.scala"
public abstract class coursier.PlatformResolve
  minor version: 0
  major version: 52
  flags: (0x0421) ACC_PUBLIC, ACC_SUPER, ACC_ABSTRACT
  this_class: #2                          // coursier/PlatformResolve
  super_class: #4                         // java/lang/Object
  interfaces: 0, fields: 2, methods: 22, attributes: 6
Constant pool:
    #1 = Utf8               coursier/PlatformResolve
    #2 = Class              #1            // coursier/PlatformResolve
    #3 = Utf8               java/lang/Object
    #4 = Class              #3            // java/lang/Object
    #5 = Utf8               PlatformResolve.scala
    #6 = Utf8               Lscala/reflect/ScalaSignature;
    #7 = Utf8               bytes
    #8 = Utf8               \u0006\u0005A2Q\u0001B\u0003\u0002\u0002!AQa\u0004\u0001\u0005\u0002AAQa\u0005\u0001\u0005\u0002QA\u0001b\n\u0001\t\u0006\u0004%\t\u0001\u000b\u0002\u0010!2\fGOZ8s[J+7o\u001c7wK*\ta!\u0001\u0005d_V\u00148/[3s\u0007\u0001\u0019\"\u0001A\u0005\u0011\u0005)iQ\"A\u0006\u000b\u00031\tQa]2bY\u0006L!AD\u0006\u0003\r\u0005s\u0017PU3g\u0003\u0019a\u0014N\\5u}Q\t\u0011\u0003\u0005\u0002\u0013\u00015\tQ!\u0001\feK\u001a\fW\u000f\u001c;NSJ\u0014xN]\"p]\u001a4\u0015\u000e\\3t+\u0005)\u0002c\u0001\f\u001fC9\u0011q\u0003\b\b\u00031mi\u0011!\u0007\u0006\u00035\u001d\ta\u0001\u0010:p_Rt\u0014\"\u0001\u0007\n\u0005uY\u0011a\u00029bG.\fw-Z\u0005\u0003?\u0001\u00121aU3r\u0015\ti2\u0002\u0005\u0002#K5\t1E\u0003\u0002%\u000b\u00051\u0001/\u0019:b[NL!AJ\u0012\u0003\u001d5K\'O]8s\u0007>tgMR5mK\u0006\u0019B-\u001a4bk2$(+\u001a9pg&$xN]5fgV\t\u0011\u0006E\u0002\u0017=)\u0002\"aK\u0017\u000f\u0005Ia\u0013BA\u000f\u0006\u0013\tqsF\u0001\u0006SKB|7/\u001b;pefT!!H\u0003
    #9 = Utf8               java/lang/invoke/MethodHandles$Lookup
   #10 = Class              #9            // java/lang/invoke/MethodHandles$Lookup
   #11 = Utf8               java/lang/invoke/MethodHandles
   #12 = Class              #11           // java/lang/invoke/MethodHandles
   #13 = Utf8               Lookup
   #14 = Utf8               defaultRepositories
   #15 = Utf8               Lscala/collection/immutable/Seq;
   #16 = Utf8               Lscala/collection/immutable/Seq<Lcoursier/core/Repository;>;
   #17 = Utf8               bitmap$0
   #18 = Utf8               Z
   #19 = Utf8               defaultMirrorConfFiles
   #20 = Utf8               ()Lscala/collection/immutable/Seq;
   #21 = Utf8               ()Lscala/collection/immutable/Seq<Lcoursier/params/MirrorConfFile;>;
   #22 = Utf8               scala/collection/ArrayOps$
   #23 = Class              #22           // scala/collection/ArrayOps$
   #24 = Utf8               MODULE$
   #25 = Utf8               Lscala/collection/ArrayOps$;
   #26 = NameAndType        #24:#25       // MODULE$:Lscala/collection/ArrayOps$;
   #27 = Fieldref           #23.#26       // scala/collection/ArrayOps$.MODULE$:Lscala/collection/ArrayOps$;
   #28 = Utf8               scala/Predef$
   #29 = Class              #28           // scala/Predef$
   #30 = Utf8               Lscala/Predef$;
   #31 = NameAndType        #24:#30       // MODULE$:Lscala/Predef$;
   #32 = Fieldref           #29.#31       // scala/Predef$.MODULE$:Lscala/Predef$;
   #33 = Utf8               coursier/paths/Mirror
   #34 = Class              #33           // coursier/paths/Mirror
   #35 = Utf8               defaultConfigFiles
   #36 = Utf8               ()[Ljava/io/File;
   #37 = NameAndType        #35:#36       // defaultConfigFiles:()[Ljava/io/File;
   #38 = Methodref          #34.#37       // coursier/paths/Mirror.defaultConfigFiles:()[Ljava/io/File;
   #39 = Utf8               [Ljava/lang/Object;
   #40 = Class              #39           // "[Ljava/lang/Object;"
   #41 = Utf8               refArrayOps
   #42 = Utf8               ([Ljava/lang/Object;)Ljava/lang/Object;
   #43 = NameAndType        #41:#42       // refArrayOps:([Ljava/lang/Object;)Ljava/lang/Object;
   #44 = Methodref          #29.#43       // scala/Predef$.refArrayOps:([Ljava/lang/Object;)Ljava/lang/Object;
   #45 = Utf8               toSeq$extension
   #46 = Utf8               (Ljava/lang/Object;)Lscala/collection/immutable/Seq;
   #47 = NameAndType        #45:#46       // toSeq$extension:(Ljava/lang/Object;)Lscala/collection/immutable/Seq;
   #48 = Methodref          #23.#47       // scala/collection/ArrayOps$.toSeq$extension:(Ljava/lang/Object;)Lscala/collection/immutable/Seq;
   #49 = Utf8               scala/Option$
   #50 = Class              #49           // scala/Option$
   #51 = Utf8               Lscala/Option$;
   #52 = NameAndType        #24:#51       // MODULE$:Lscala/Option$;
   #53 = Fieldref           #50.#52       // scala/Option$.MODULE$:Lscala/Option$;
   #54 = Utf8               extraConfigFile
   #55 = Utf8               ()Ljava/io/File;
   #56 = NameAndType        #54:#55       // extraConfigFile:()Ljava/io/File;
   #57 = Methodref          #34.#56       // coursier/paths/Mirror.extraConfigFile:()Ljava/io/File;
   #58 = Utf8               apply
   #59 = Utf8               (Ljava/lang/Object;)Lscala/Option;
   #60 = NameAndType        #58:#59       // apply:(Ljava/lang/Object;)Lscala/Option;
   #61 = Methodref          #50.#60       // scala/Option$.apply:(Ljava/lang/Object;)Lscala/Option;
   #62 = Utf8               option2Iterable
   #63 = Utf8               (Lscala/Option;)Lscala/collection/Iterable;
   #64 = NameAndType        #62:#63       // option2Iterable:(Lscala/Option;)Lscala/collection/Iterable;
   #65 = Methodref          #50.#64       // scala/Option$.option2Iterable:(Lscala/Option;)Lscala/collection/Iterable;
   #66 = Utf8               scala/collection/Iterable
   #67 = Class              #66           // scala/collection/Iterable
   #68 = Utf8               toSeq
   #69 = NameAndType        #68:#20       // toSeq:()Lscala/collection/immutable/Seq;
   #70 = InterfaceMethodref #67.#69       // scala/collection/Iterable.toSeq:()Lscala/collection/immutable/Seq;
   #71 = Utf8               scala/collection/immutable/Seq
   #72 = Class              #71           // scala/collection/immutable/Seq
   #73 = Utf8               $plus$plus
   #74 = Utf8               (Lscala/collection/IterableOnce;)Ljava/lang/Object;
   #75 = NameAndType        #73:#74       // $plus$plus:(Lscala/collection/IterableOnce;)Ljava/lang/Object;
   #76 = InterfaceMethodref #72.#75       // scala/collection/immutable/Seq.$plus$plus:(Lscala/collection/IterableOnce;)Ljava/lang/Object;
   #77 = Utf8               (Ljava/lang/Object;)Ljava/lang/Object;
   #78 = MethodType         #77           //  (Ljava/lang/Object;)Ljava/lang/Object;
   #79 = Utf8               $anonfun$defaultMirrorConfFiles$1
   #80 = Utf8               (Ljava/io/File;)Lcoursier/params/MirrorConfFile;
   #81 = NameAndType        #79:#80       // $anonfun$defaultMirrorConfFiles$1:(Ljava/io/File;)Lcoursier/params/MirrorConfFile;
   #82 = Methodref          #2.#81        // coursier/PlatformResolve.$anonfun$defaultMirrorConfFiles$1:(Ljava/io/File;)Lcoursier/params/MirrorConfFile;
   #83 = MethodHandle       6:#82         // REF_invokeStatic coursier/PlatformResolve.$anonfun$defaultMirrorConfFiles$1:(Ljava/io/File;)Lcoursier/params/MirrorConfFile;
   #84 = MethodType         #80           //  (Ljava/io/File;)Lcoursier/params/MirrorConfFile;
   #85 = Integer            5
   #86 = Integer            1
   #87 = Utf8               java/lang/invoke/LambdaMetafactory
   #88 = Class              #87           // java/lang/invoke/LambdaMetafactory
   #89 = Utf8               altMetafactory
   #90 = Utf8               (Ljava/lang/invoke/MethodHandles$Lookup;Ljava/lang/String;Ljava/lang/invoke/MethodType;[Ljava/lang/Object;)Ljava/lang/invoke/CallSite;
   #91 = NameAndType        #89:#90       // altMetafactory:(Ljava/lang/invoke/MethodHandles$Lookup;Ljava/lang/String;Ljava/lang/invoke/MethodType;[Ljava/lang/Object;)Ljava/lang/invoke/CallSite;
   #92 = Methodref          #88.#91       // java/lang/invoke/LambdaMetafactory.altMetafactory:(Ljava/lang/invoke/MethodHandles$Lookup;Ljava/lang/String;Ljava/lang/invoke/MethodType;[Ljava/lang/Object;)Ljava/lang/invoke/CallSite;
   #93 = MethodHandle       6:#92         // REF_invokeStatic java/lang/invoke/LambdaMetafactory.altMetafactory:(Ljava/lang/invoke/MethodHandles$Lookup;Ljava/lang/String;Ljava/lang/invoke/MethodType;[Ljava/lang/Object;)Ljava/lang/invoke/CallSite;
   #94 = Utf8               ()Lscala/Function1;
   #95 = NameAndType        #58:#94       // apply:()Lscala/Function1;
   #96 = InvokeDynamic      #0:#95        // #0:apply:()Lscala/Function1;
   #97 = Utf8               map
   #98 = Utf8               (Lscala/Function1;)Ljava/lang/Object;
   #99 = NameAndType        #97:#98       // map:(Lscala/Function1;)Ljava/lang/Object;
  #100 = InterfaceMethodref #72.#99       // scala/collection/immutable/Seq.map:(Lscala/Function1;)Ljava/lang/Object;
  #101 = Utf8               files
  #102 = Utf8               this
  #103 = Utf8               Lcoursier/PlatformResolve;
  #104 = Utf8               defaultRepositories$lzycompute
  #105 = Utf8               ()Lscala/collection/immutable/Seq<Lcoursier/core/Repository;>;
  #106 = NameAndType        #17:#18       // bitmap$0:Z
  #107 = Fieldref           #2.#106       // coursier/PlatformResolve.bitmap$0:Z
  #108 = Utf8               scala/collection/StringOps$
  #109 = Class              #108          // scala/collection/StringOps$
  #110 = Utf8               Lscala/collection/StringOps$;
  #111 = NameAndType        #24:#110      // MODULE$:Lscala/collection/StringOps$;
  #112 = Fieldref           #109.#111     // scala/collection/StringOps$.MODULE$:Lscala/collection/StringOps$;
  #113 = Utf8               \\s+
  #114 = String             #113          // \\s+
  #115 = Utf8               augmentString
  #116 = Utf8               (Ljava/lang/String;)Ljava/lang/String;
  #117 = NameAndType        #115:#116     // augmentString:(Ljava/lang/String;)Ljava/lang/String;
  #118 = Methodref          #29.#117      // scala/Predef$.augmentString:(Ljava/lang/String;)Ljava/lang/String;
  #119 = Utf8               r$extension
  #120 = Utf8               (Ljava/lang/String;)Lscala/util/matching/Regex;
  #121 = NameAndType        #119:#120     // r$extension:(Ljava/lang/String;)Lscala/util/matching/Regex;
  #122 = Methodref          #109.#121     // scala/collection/StringOps$.r$extension:(Ljava/lang/String;)Lscala/util/matching/Regex;
  #123 = Utf8               COURSIER_REPOSITORIES
  #124 = String             #123          // COURSIER_REPOSITORIES
  #125 = Utf8               java/lang/System
  #126 = Class              #125          // java/lang/System
  #127 = Utf8               getenv
  #128 = NameAndType        #127:#116     // getenv:(Ljava/lang/String;)Ljava/lang/String;
  #129 = Methodref          #126.#128     // java/lang/System.getenv:(Ljava/lang/String;)Ljava/lang/String;
  #130 = Utf8               $anonfun$defaultRepositories$4
  #131 = NameAndType        #130:#116     // $anonfun$defaultRepositories$4:(Ljava/lang/String;)Ljava/lang/String;
  #132 = Methodref          #2.#131       // coursier/PlatformResolve.$anonfun$defaultRepositories$4:(Ljava/lang/String;)Ljava/lang/String;
  #133 = MethodHandle       6:#132        // REF_invokeStatic coursier/PlatformResolve.$anonfun$defaultRepositories$4:(Ljava/lang/String;)Ljava/lang/String;
  #134 = MethodType         #116          //  (Ljava/lang/String;)Ljava/lang/String;
  #135 = InvokeDynamic      #1:#95        // #1:apply:()Lscala/Function1;
  #136 = Utf8               scala/Option
  #137 = Class              #136          // scala/Option
  #138 = Utf8               (Lscala/Function1;)Lscala/Option;
  #139 = NameAndType        #97:#138      // map:(Lscala/Function1;)Lscala/Option;
  #140 = Methodref          #137.#139     // scala/Option.map:(Lscala/Function1;)Lscala/Option;
  #141 = Utf8               $anonfun$defaultRepositories$5$adapted
  #142 = Utf8               (Ljava/lang/String;)Ljava/lang/Object;
  #143 = NameAndType        #141:#142     // $anonfun$defaultRepositories$5$adapted:(Ljava/lang/String;)Ljava/lang/Object;
  #144 = Methodref          #2.#143       // coursier/PlatformResolve.$anonfun$defaultRepositories$5$adapted:(Ljava/lang/String;)Ljava/lang/Object;
  #145 = MethodHandle       6:#144        // REF_invokeStatic coursier/PlatformResolve.$anonfun$defaultRepositories$5$adapted:(Ljava/lang/String;)Ljava/lang/Object;
  #146 = MethodType         #142          //  (Ljava/lang/String;)Ljava/lang/Object;
  #147 = InvokeDynamic      #2:#95        // #2:apply:()Lscala/Function1;
  #148 = Utf8               filter
  #149 = NameAndType        #148:#138     // filter:(Lscala/Function1;)Lscala/Option;
  #150 = Methodref          #137.#149     // scala/Option.filter:(Lscala/Function1;)Lscala/Option;
  #151 = Utf8               $anonfun$defaultRepositories$6
  #152 = Utf8               (Lscala/util/matching/Regex;Ljava/lang/String;)Lscala/Option;
  #153 = NameAndType        #151:#152     // $anonfun$defaultRepositories$6:(Lscala/util/matching/Regex;Ljava/lang/String;)Lscala/Option;
  #154 = Methodref          #2.#153       // coursier/PlatformResolve.$anonfun$defaultRepositories$6:(Lscala/util/matching/Regex;Ljava/lang/String;)Lscala/Option;
  #155 = MethodHandle       6:#154        // REF_invokeStatic coursier/PlatformResolve.$anonfun$defaultRepositories$6:(Lscala/util/matching/Regex;Ljava/lang/String;)Lscala/Option;
  #156 = Utf8               (Ljava/lang/String;)Lscala/Option;
  #157 = MethodType         #156          //  (Ljava/lang/String;)Lscala/Option;
  #158 = Utf8               (Lscala/util/matching/Regex;)Lscala/Function1;
  #159 = NameAndType        #58:#158      // apply:(Lscala/util/matching/Regex;)Lscala/Function1;
  #160 = InvokeDynamic      #3:#159       // #3:apply:(Lscala/util/matching/Regex;)Lscala/Function1;
  #161 = Utf8               flatMap
  #162 = NameAndType        #161:#138     // flatMap:(Lscala/Function1;)Lscala/Option;
  #163 = Methodref          #137.#162     // scala/Option.flatMap:(Lscala/Function1;)Lscala/Option;
  #164 = Utf8               scala/sys/package$
  #165 = Class              #164          // scala/sys/package$
  #166 = Utf8               Lscala/sys/package$;
  #167 = NameAndType        #24:#166      // MODULE$:Lscala/sys/package$;
  #168 = Fieldref           #165.#167     // scala/sys/package$.MODULE$:Lscala/sys/package$;
  #169 = Utf8               props
  #170 = Utf8               ()Lscala/sys/SystemProperties;
  #171 = NameAndType        #169:#170     // props:()Lscala/sys/SystemProperties;
  #172 = Methodref          #165.#171     // scala/sys/package$.props:()Lscala/sys/SystemProperties;
  #173 = Utf8               coursier.repositories
  #174 = String             #173          // coursier.repositories
  #175 = Utf8               scala/sys/SystemProperties
  #176 = Class              #175          // scala/sys/SystemProperties
  #177 = Utf8               get
  #178 = NameAndType        #177:#156     // get:(Ljava/lang/String;)Lscala/Option;
  #179 = Methodref          #176.#178     // scala/sys/SystemProperties.get:(Ljava/lang/String;)Lscala/Option;
  #180 = Utf8               $anonfun$defaultRepositories$7
  #181 = NameAndType        #180:#116     // $anonfun$defaultRepositories$7:(Ljava/lang/String;)Ljava/lang/String;
  #182 = Methodref          #2.#181       // coursier/PlatformResolve.$anonfun$defaultRepositories$7:(Ljava/lang/String;)Ljava/lang/String;
  #183 = MethodHandle       6:#182        // REF_invokeStatic coursier/PlatformResolve.$anonfun$defaultRepositories$7:(Ljava/lang/String;)Ljava/lang/String;
  #184 = InvokeDynamic      #4:#95        // #4:apply:()Lscala/Function1;
  #185 = Utf8               $anonfun$defaultRepositories$8$adapted
  #186 = NameAndType        #185:#142     // $anonfun$defaultRepositories$8$adapted:(Ljava/lang/String;)Ljava/lang/Object;
  #187 = Methodref          #2.#186       // coursier/PlatformResolve.$anonfun$defaultRepositories$8$adapted:(Ljava/lang/String;)Ljava/lang/Object;
  #188 = MethodHandle       6:#187        // REF_invokeStatic coursier/PlatformResolve.$anonfun$defaultRepositories$8$adapted:(Ljava/lang/String;)Ljava/lang/Object;
  #189 = InvokeDynamic      #5:#95        // #5:apply:()Lscala/Function1;
  #190 = Utf8               $anonfun$defaultRepositories$9
  #191 = NameAndType        #190:#152     // $anonfun$defaultRepositories$9:(Lscala/util/matching/Regex;Ljava/lang/String;)Lscala/Option;
  #192 = Methodref          #2.#191       // coursier/PlatformResolve.$anonfun$defaultRepositories$9:(Lscala/util/matching/Regex;Ljava/lang/String;)Lscala/Option;
  #193 = MethodHandle       6:#192        // REF_invokeStatic coursier/PlatformResolve.$anonfun$defaultRepositories$9:(Lscala/util/matching/Regex;Ljava/lang/String;)Lscala/Option;
  #194 = InvokeDynamic      #6:#159       // #6:apply:(Lscala/util/matching/Regex;)Lscala/Function1;
  #195 = Utf8               scala/collection/immutable/$colon$colon
  #196 = Class              #195          // scala/collection/immutable/$colon$colon
  #197 = Utf8               coursier/LocalRepositories$
  #198 = Class              #197          // coursier/LocalRepositories$
  #199 = Utf8               Lcoursier/LocalRepositories$;
  #200 = NameAndType        #24:#199      // MODULE$:Lcoursier/LocalRepositories$;
  #201 = Fieldref           #198.#200     // coursier/LocalRepositories$.MODULE$:Lcoursier/LocalRepositories$;
  #202 = Utf8               ivy2Local
  #203 = Utf8               ()Lcoursier/ivy/IvyRepository;
  #204 = NameAndType        #202:#203     // ivy2Local:()Lcoursier/ivy/IvyRepository;
  #205 = Methodref          #198.#204     // coursier/LocalRepositories$.ivy2Local:()Lcoursier/ivy/IvyRepository;
  #206 = Utf8               coursier/Repositories$
  #207 = Class              #206          // coursier/Repositories$
  #208 = Utf8               Lcoursier/Repositories$;
  #209 = NameAndType        #24:#208      // MODULE$:Lcoursier/Repositories$;
  #210 = Fieldref           #207.#209     // coursier/Repositories$.MODULE$:Lcoursier/Repositories$;
  #211 = Utf8               central
  #212 = Utf8               ()Lcoursier/maven/MavenRepository;
  #213 = NameAndType        #211:#212     // central:()Lcoursier/maven/MavenRepository;
  #214 = Methodref          #207.#213     // coursier/Repositories$.central:()Lcoursier/maven/MavenRepository;
  #215 = Utf8               scala/collection/immutable/Nil$
  #216 = Class              #215          // scala/collection/immutable/Nil$
  #217 = Utf8               Lscala/collection/immutable/Nil$;
  #218 = NameAndType        #24:#217      // MODULE$:Lscala/collection/immutable/Nil$;
  #219 = Fieldref           #216.#218     // scala/collection/immutable/Nil$.MODULE$:Lscala/collection/immutable/Nil$;
  #220 = Utf8               <init>
  #221 = Utf8               (Ljava/lang/Object;Lscala/collection/immutable/List;)V
  #222 = NameAndType        #220:#221     // "<init>":(Ljava/lang/Object;Lscala/collection/immutable/List;)V
  #223 = Methodref          #196.#222     // scala/collection/immutable/$colon$colon."<init>":(Ljava/lang/Object;Lscala/collection/immutable/List;)V
  #224 = Utf8               ()Ljava/lang/Object;
  #225 = MethodType         #224          //  ()Ljava/lang/Object;
  #226 = Utf8               $anonfun$defaultRepositories$10
  #227 = Utf8               (Lscala/Option;)Lscala/Option;
  #228 = NameAndType        #226:#227     // $anonfun$defaultRepositories$10:(Lscala/Option;)Lscala/Option;
  #229 = Methodref          #2.#228       // coursier/PlatformResolve.$anonfun$defaultRepositories$10:(Lscala/Option;)Lscala/Option;
  #230 = MethodHandle       6:#229        // REF_invokeStatic coursier/PlatformResolve.$anonfun$defaultRepositories$10:(Lscala/Option;)Lscala/Option;
  #231 = Utf8               ()Lscala/Option;
  #232 = MethodType         #231          //  ()Lscala/Option;
  #233 = Utf8               (Lscala/Option;)Lscala/Function0;
  #234 = NameAndType        #58:#233      // apply:(Lscala/Option;)Lscala/Function0;
  #235 = InvokeDynamic      #7:#234       // #7:apply:(Lscala/Option;)Lscala/Function0;
  #236 = Utf8               orElse
  #237 = Utf8               (Lscala/Function0;)Lscala/Option;
  #238 = NameAndType        #236:#237     // orElse:(Lscala/Function0;)Lscala/Option;
  #239 = Methodref          #137.#238     // scala/Option.orElse:(Lscala/Function0;)Lscala/Option;
  #240 = Utf8               $anonfun$defaultRepositories$11
  #241 = Utf8               (Lscala/collection/immutable/Seq;)Lscala/collection/immutable/Seq;
  #242 = NameAndType        #240:#241     // $anonfun$defaultRepositories$11:(Lscala/collection/immutable/Seq;)Lscala/collection/immutable/Seq;
  #243 = Methodref          #2.#242       // coursier/PlatformResolve.$anonfun$defaultRepositories$11:(Lscala/collection/immutable/Seq;)Lscala/collection/immutable/Seq;
  #244 = MethodHandle       6:#243        // REF_invokeStatic coursier/PlatformResolve.$anonfun$defaultRepositories$11:(Lscala/collection/immutable/Seq;)Lscala/collection/immutable/Seq;
  #245 = MethodType         #20           //  ()Lscala/collection/immutable/Seq;
  #246 = Utf8               (Lscala/collection/immutable/Seq;)Lscala/Function0;
  #247 = NameAndType        #58:#246      // apply:(Lscala/collection/immutable/Seq;)Lscala/Function0;
  #248 = InvokeDynamic      #8:#247       // #8:apply:(Lscala/collection/immutable/Seq;)Lscala/Function0;
  #249 = Utf8               getOrElse
  #250 = Utf8               (Lscala/Function0;)Ljava/lang/Object;
  #251 = NameAndType        #249:#250     // getOrElse:(Lscala/Function0;)Ljava/lang/Object;
  #252 = Methodref          #137.#251     // scala/Option.getOrElse:(Lscala/Function0;)Ljava/lang/Object;
  #253 = NameAndType        #14:#15       // defaultRepositories:Lscala/collection/immutable/Seq;
  #254 = Fieldref           #2.#253       // coursier/PlatformResolve.defaultRepositories:Lscala/collection/immutable/Seq;
  #255 = Utf8               java/lang/Throwable
  #256 = Class              #255          // java/lang/Throwable
  #257 = Utf8               spaceSep
  #258 = Utf8               Lscala/util/matching/Regex;
  #259 = Utf8               fromEnvOpt
  #260 = Utf8               Lscala/Option;
  #261 = Utf8               fromPropsOpt
  #262 = Utf8               default
  #263 = NameAndType        #104:#20      // defaultRepositories$lzycompute:()Lscala/collection/immutable/Seq;
  #264 = Methodref          #2.#263       // coursier/PlatformResolve.defaultRepositories$lzycompute:()Lscala/collection/immutable/Seq;
  #265 = Utf8               f
  #266 = Utf8               coursier/params/MirrorConfFile$
  #267 = Class              #266          // coursier/params/MirrorConfFile$
  #268 = Utf8               Lcoursier/params/MirrorConfFile$;
  #269 = NameAndType        #24:#268      // MODULE$:Lcoursier/params/MirrorConfFile$;
  #270 = Fieldref           #267.#269     // coursier/params/MirrorConfFile$.MODULE$:Lcoursier/params/MirrorConfFile$;
  #271 = Utf8               java/io/File
  #272 = Class              #271          // java/io/File
  #273 = Utf8               getAbsolutePath
  #274 = Utf8               ()Ljava/lang/String;
  #275 = NameAndType        #273:#274     // getAbsolutePath:()Ljava/lang/String;
  #276 = Methodref          #272.#275     // java/io/File.getAbsolutePath:()Ljava/lang/String;
  #277 = Utf8               (Ljava/lang/String;Z)Lcoursier/params/MirrorConfFile;
  #278 = NameAndType        #58:#277      // apply:(Ljava/lang/String;Z)Lcoursier/params/MirrorConfFile;
  #279 = Methodref          #267.#278     // coursier/params/MirrorConfFile$.apply:(Ljava/lang/String;Z)Lcoursier/params/MirrorConfFile;
  #280 = Utf8               Ljava/io/File;
  #281 = Utf8               $anonfun$defaultRepositories$1
  #282 = Utf8               (Ljava/lang/String;)Z
  #283 = Utf8               x$1
  #284 = Utf8               nonEmpty$extension
  #285 = NameAndType        #284:#282     // nonEmpty$extension:(Ljava/lang/String;)Z
  #286 = Methodref          #109.#285     // scala/collection/StringOps$.nonEmpty$extension:(Ljava/lang/String;)Z
  #287 = Utf8               Ljava/lang/String;
  #288 = Utf8               $anonfun$defaultRepositories$2
  #289 = Utf8               x$2
  #290 = Utf8               $anonfun$defaultRepositories$3
  #291 = Utf8               x$3
  #292 = Utf8               java/lang/StringBuilder
  #293 = Class              #292          // java/lang/StringBuilder
  #294 = Integer            2
  #295 = Utf8               (I)V
  #296 = NameAndType        #220:#295     // "<init>":(I)V
  #297 = Methodref          #293.#296     // java/lang/StringBuilder."<init>":(I)V
  #298 = Utf8
  #299 = String             #298          //
  #300 = Utf8               append
  #301 = Utf8               (Ljava/lang/String;)Ljava/lang/StringBuilder;
  #302 = NameAndType        #300:#301     // append:(Ljava/lang/String;)Ljava/lang/StringBuilder;
  #303 = Methodref          #293.#302     // java/lang/StringBuilder.append:(Ljava/lang/String;)Ljava/lang/StringBuilder;
  #304 = Utf8               lineSeparator
  #305 = NameAndType        #304:#274     // lineSeparator:()Ljava/lang/String;
  #306 = Methodref          #126.#305     // java/lang/System.lineSeparator:()Ljava/lang/String;
  #307 = Utf8               toString
  #308 = NameAndType        #307:#274     // toString:()Ljava/lang/String;
  #309 = Methodref          #293.#308     // java/lang/StringBuilder.toString:()Ljava/lang/String;
  #310 = Utf8               fromString$1
  #311 = Utf8               (Ljava/lang/String;Ljava/lang/String;Lscala/util/matching/Regex;)Lscala/Option;
  #312 = Utf8               str
  #313 = Utf8               origin
  #314 = Utf8               spaceSep$1
  #315 = Utf8               scala/util/matching/Regex
  #316 = Class              #315          // scala/util/matching/Regex
  #317 = Utf8               findFirstIn
  #318 = Utf8               (Ljava/lang/CharSequence;)Lscala/Option;
  #319 = NameAndType        #317:#318     // findFirstIn:(Ljava/lang/CharSequence;)Lscala/Option;
  #320 = Methodref          #316.#319     // scala/util/matching/Regex.findFirstIn:(Ljava/lang/CharSequence;)Lscala/Option;
  #321 = Utf8               isEmpty
  #322 = Utf8               ()Z
  #323 = NameAndType        #321:#322     // isEmpty:()Z
  #324 = Methodref          #137.#323     // scala/Option.isEmpty:()Z
  #325 = Utf8               split$extension
  #326 = Utf8               (Ljava/lang/String;C)[Ljava/lang/String;
  #327 = NameAndType        #325:#326     // split$extension:(Ljava/lang/String;C)[Ljava/lang/String;
  #328 = Methodref          #109.#327     // scala/collection/StringOps$.split$extension:(Ljava/lang/String;C)[Ljava/lang/String;
  #329 = Utf8               $anonfun$defaultRepositories$1$adapted
  #330 = NameAndType        #329:#142     // $anonfun$defaultRepositories$1$adapted:(Ljava/lang/String;)Ljava/lang/Object;
  #331 = Methodref          #2.#330       // coursier/PlatformResolve.$anonfun$defaultRepositories$1$adapted:(Ljava/lang/String;)Ljava/lang/Object;
  #332 = MethodHandle       6:#331        // REF_invokeStatic coursier/PlatformResolve.$anonfun$defaultRepositories$1$adapted:(Ljava/lang/String;)Ljava/lang/Object;
  #333 = InvokeDynamic      #9:#95        // #9:apply:()Lscala/Function1;
  #334 = NameAndType        #148:#98      // filter:(Lscala/Function1;)Ljava/lang/Object;
  #335 = InterfaceMethodref #72.#334      // scala/collection/immutable/Seq.filter:(Lscala/Function1;)Ljava/lang/Object;
  #336 = Utf8               split
  #337 = Utf8               (Ljava/lang/CharSequence;)[Ljava/lang/String;
  #338 = NameAndType        #336:#337     // split:(Ljava/lang/CharSequence;)[Ljava/lang/String;
  #339 = Methodref          #316.#338     // scala/util/matching/Regex.split:(Ljava/lang/CharSequence;)[Ljava/lang/String;
  #340 = Utf8               $anonfun$defaultRepositories$2$adapted
  #341 = NameAndType        #340:#142     // $anonfun$defaultRepositories$2$adapted:(Ljava/lang/String;)Ljava/lang/Object;
  #342 = Methodref          #2.#341       // coursier/PlatformResolve.$anonfun$defaultRepositories$2$adapted:(Ljava/lang/String;)Ljava/lang/Object;
  #343 = MethodHandle       6:#342        // REF_invokeStatic coursier/PlatformResolve.$anonfun$defaultRepositories$2$adapted:(Ljava/lang/String;)Ljava/lang/Object;
  #344 = InvokeDynamic      #10:#95       // #10:apply:()Lscala/Function1;
  #345 = Utf8               coursier/parse/RepositoryParser$
  #346 = Class              #345          // coursier/parse/RepositoryParser$
  #347 = Utf8               Lcoursier/parse/RepositoryParser$;
  #348 = NameAndType        #24:#347      // MODULE$:Lcoursier/parse/RepositoryParser$;
  #349 = Fieldref           #346.#348     // coursier/parse/RepositoryParser$.MODULE$:Lcoursier/parse/RepositoryParser$;
  #350 = Utf8               repositories
  #351 = Utf8               (Lscala/collection/immutable/Seq;)Lcoursier/util/ValidationNel;
  #352 = NameAndType        #350:#351     // repositories:(Lscala/collection/immutable/Seq;)Lcoursier/util/ValidationNel;
  #353 = Methodref          #346.#352     // coursier/parse/RepositoryParser$.repositories:(Lscala/collection/immutable/Seq;)Lcoursier/util/ValidationNel;
  #354 = Utf8               coursier/util/ValidationNel
  #355 = Class              #354          // coursier/util/ValidationNel
  #356 = Utf8               either
  #357 = Utf8               ()Lscala/util/Either;
  #358 = NameAndType        #356:#357     // either:()Lscala/util/Either;
  #359 = Methodref          #355.#358     // coursier/util/ValidationNel.either:()Lscala/util/Either;
  #360 = Utf8               scala/util/Left
  #361 = Class              #360          // scala/util/Left
  #362 = Utf8               value
  #363 = NameAndType        #362:#224     // value:()Ljava/lang/Object;
  #364 = Methodref          #361.#363     // scala/util/Left.value:()Ljava/lang/Object;
  #365 = Utf8               err
  #366 = Utf8               Ljava/io/PrintStream;
  #367 = NameAndType        #365:#366     // err:Ljava/io/PrintStream;
  #368 = Fieldref           #126.#367     // java/lang/System.err:Ljava/io/PrintStream;
  #369 = Integer            0
  #370 = Integer            46
  #371 = Utf8               Ignoring
  #372 = String             #371          // Ignoring
  #373 = Utf8               , error parsing repositories from it:
  #374 = String             #373          // , error parsing repositories from it:
  #375 = NameAndType        #290:#116     // $anonfun$defaultRepositories$3:(Ljava/lang/String;)Ljava/lang/String;
  #376 = Methodref          #2.#375       // coursier/PlatformResolve.$anonfun$defaultRepositories$3:(Ljava/lang/String;)Ljava/lang/String;
  #377 = MethodHandle       6:#376        // REF_invokeStatic coursier/PlatformResolve.$anonfun$defaultRepositories$3:(Ljava/lang/String;)Ljava/lang/String;
  #378 = InvokeDynamic      #11:#95       // #11:apply:()Lscala/Function1;
  #379 = Utf8               (Lscala/Function1;)Lscala/collection/immutable/List;
  #380 = NameAndType        #97:#379      // map:(Lscala/Function1;)Lscala/collection/immutable/List;
  #381 = Methodref          #196.#380     // scala/collection/immutable/$colon$colon.map:(Lscala/Function1;)Lscala/collection/immutable/List;
  #382 = Utf8               scala/collection/immutable/List
  #383 = Class              #382          // scala/collection/immutable/List
  #384 = Utf8               mkString
  #385 = NameAndType        #384:#274     // mkString:()Ljava/lang/String;
  #386 = Methodref          #383.#385     // scala/collection/immutable/List.mkString:()Ljava/lang/String;
  #387 = Utf8               java/io/PrintStream
  #388 = Class              #387          // java/io/PrintStream
  #389 = Utf8               println
  #390 = Utf8               (Ljava/lang/String;)V
  #391 = NameAndType        #389:#390     // println:(Ljava/lang/String;)V
  #392 = Methodref          #388.#391     // java/io/PrintStream.println:(Ljava/lang/String;)V
  #393 = Utf8               scala/None$
  #394 = Class              #393          // scala/None$
  #395 = Utf8               Lscala/None$;
  #396 = NameAndType        #24:#395      // MODULE$:Lscala/None$;
  #397 = Fieldref           #394.#396     // scala/None$.MODULE$:Lscala/None$;
  #398 = Utf8               scala/util/Either
  #399 = Class              #398          // scala/util/Either
  #400 = Utf8               scala/util/Right
  #401 = Class              #400          // scala/util/Right
  #402 = Methodref          #401.#363     // scala/util/Right.value:()Ljava/lang/Object;
  #403 = Utf8               scala/Some
  #404 = Class              #403          // scala/Some
  #405 = Utf8               (Ljava/lang/Object;)V
  #406 = NameAndType        #220:#405     // "<init>":(Ljava/lang/Object;)V
  #407 = Methodref          #404.#406     // scala/Some."<init>":(Ljava/lang/Object;)V
  #408 = Utf8               scala/MatchError
  #409 = Class              #408          // scala/MatchError
  #410 = Methodref          #409.#406     // scala/MatchError."<init>":(Ljava/lang/Object;)V
  #411 = Utf8               java/lang/String
  #412 = Class              #411          // java/lang/String
  #413 = Utf8               errs
  #414 = Utf8               Lscala/collection/immutable/$colon$colon;
  #415 = Utf8               repos
  #416 = Utf8               l
  #417 = Utf8               x$4
  #418 = Utf8               trim
  #419 = NameAndType        #418:#274     // trim:()Ljava/lang/String;
  #420 = Methodref          #412.#419     // java/lang/String.trim:()Ljava/lang/String;
  #421 = Utf8               $anonfun$defaultRepositories$5
  #422 = Utf8               x$5
  #423 = Utf8               x$6
  #424 = Utf8               environment variable COURSIER_REPOSITORIES
  #425 = String             #424          // environment variable COURSIER_REPOSITORIES
  #426 = NameAndType        #310:#311     // fromString$1:(Ljava/lang/String;Ljava/lang/String;Lscala/util/matching/Regex;)Lscala/Option;
  #427 = Methodref          #2.#426       // coursier/PlatformResolve.fromString$1:(Ljava/lang/String;Ljava/lang/String;Lscala/util/matching/Regex;)Lscala/Option;
  #428 = Utf8               x$7
  #429 = Utf8               $anonfun$defaultRepositories$8
  #430 = Utf8               x$8
  #431 = Utf8               x$9
  #432 = Utf8               Java property coursier.repositories
  #433 = String             #432          // Java property coursier.repositories
  #434 = Utf8               fromPropsOpt$1
  #435 = Utf8               default$1
  #436 = Utf8               ()V
  #437 = NameAndType        #220:#436     // "<init>":()V
  #438 = Methodref          #4.#437       // java/lang/Object."<init>":()V
  #439 = NameAndType        #421:#282     // $anonfun$defaultRepositories$5:(Ljava/lang/String;)Z
  #440 = Methodref          #2.#439       // coursier/PlatformResolve.$anonfun$defaultRepositories$5:(Ljava/lang/String;)Z
  #441 = Utf8               scala/runtime/BoxesRunTime
  #442 = Class              #441          // scala/runtime/BoxesRunTime
  #443 = Utf8               boxToBoolean
  #444 = Utf8               (Z)Ljava/lang/Boolean;
  #445 = NameAndType        #443:#444     // boxToBoolean:(Z)Ljava/lang/Boolean;
  #446 = Methodref          #442.#445     // scala/runtime/BoxesRunTime.boxToBoolean:(Z)Ljava/lang/Boolean;
  #447 = NameAndType        #429:#282     // $anonfun$defaultRepositories$8:(Ljava/lang/String;)Z
  #448 = Methodref          #2.#447       // coursier/PlatformResolve.$anonfun$defaultRepositories$8:(Ljava/lang/String;)Z
  #449 = NameAndType        #281:#282     // $anonfun$defaultRepositories$1:(Ljava/lang/String;)Z
  #450 = Methodref          #2.#449       // coursier/PlatformResolve.$anonfun$defaultRepositories$1:(Ljava/lang/String;)Z
  #451 = NameAndType        #288:#282     // $anonfun$defaultRepositories$2:(Ljava/lang/String;)Z
  #452 = Methodref          #2.#451       // coursier/PlatformResolve.$anonfun$defaultRepositories$2:(Ljava/lang/String;)Z
  #453 = Utf8               $deserializeLambda$
  #454 = Utf8               (Ljava/lang/invoke/SerializedLambda;)Ljava/lang/Object;
  #455 = Utf8               scala/runtime/LambdaDeserialize
  #456 = Class              #455          // scala/runtime/LambdaDeserialize
  #457 = Utf8               bootstrap
  #458 = Utf8               (Ljava/lang/invoke/MethodHandles$Lookup;Ljava/lang/String;Ljava/lang/invoke/MethodType;[Ljava/lang/invoke/MethodHandle;)Ljava/lang/invoke/CallSite;
  #459 = NameAndType        #457:#458     // bootstrap:(Ljava/lang/invoke/MethodHandles$Lookup;Ljava/lang/String;Ljava/lang/invoke/MethodType;[Ljava/lang/invoke/MethodHandle;)Ljava/lang/invoke/CallSite;
  #460 = Methodref          #456.#459     // scala/runtime/LambdaDeserialize.bootstrap:(Ljava/lang/invoke/MethodHandles$Lookup;Ljava/lang/String;Ljava/lang/invoke/MethodType;[Ljava/lang/invoke/MethodHandle;)Ljava/lang/invoke/CallSite;
  #461 = MethodHandle       6:#460        // REF_invokeStatic scala/runtime/LambdaDeserialize.bootstrap:(Ljava/lang/invoke/MethodHandles$Lookup;Ljava/lang/String;Ljava/lang/invoke/MethodType;[Ljava/lang/invoke/MethodHandle;)Ljava/lang/invoke/CallSite;
  #462 = Utf8               lambdaDeserialize
  #463 = NameAndType        #462:#454     // lambdaDeserialize:(Ljava/lang/invoke/SerializedLambda;)Ljava/lang/Object;
  #464 = InvokeDynamic      #12:#463      // #12:lambdaDeserialize:(Ljava/lang/invoke/SerializedLambda;)Ljava/lang/Object;
  #465 = Utf8               Signature
  #466 = Utf8               Code
  #467 = Utf8               LineNumberTable
  #468 = Utf8               LocalVariableTable
  #469 = Utf8               StackMapTable
  #470 = Utf8               MethodParameters
  #471 = Utf8               InnerClasses
  #472 = Utf8               SourceFile
  #473 = Utf8               RuntimeVisibleAnnotations
  #474 = Utf8               BootstrapMethods
  #475 = Utf8               ScalaInlineInfo
  #476 = Utf8               ScalaSig
{
  private scala.collection.immutable.Seq<coursier.core.Repository> defaultRepositories;
    descriptor: Lscala/collection/immutable/Seq;
    flags: (0x0002) ACC_PRIVATE
    Signature: #16                          // Lscala/collection/immutable/Seq<Lcoursier/core/Repository;>;

  private volatile boolean bitmap$0;
    descriptor: Z
    flags: (0x0042) ACC_PRIVATE, ACC_VOLATILE

  public scala.collection.immutable.Seq<coursier.params.MirrorConfFile> defaultMirrorConfFiles();
    descriptor: ()Lscala/collection/immutable/Seq;
    flags: (0x0001) ACC_PUBLIC
    Code:
      stack=4, locals=2, args_size=1
         0: getstatic     #27                 // Field scala/collection/ArrayOps$.MODULE$:Lscala/collection/ArrayOps$;
         3: getstatic     #32                 // Field scala/Predef$.MODULE$:Lscala/Predef$;
         6: invokestatic  #38                 // Method coursier/paths/Mirror.defaultConfigFiles:()[Ljava/io/File;
         9: checkcast     #40                 // class "[Ljava/lang/Object;"
        12: invokevirtual #44                 // Method scala/Predef$.refArrayOps:([Ljava/lang/Object;)Ljava/lang/Object;
        15: invokevirtual #48                 // Method scala/collection/ArrayOps$.toSeq$extension:(Ljava/lang/Object;)Lscala/collection/immutable/Seq;
        18: getstatic     #53                 // Field scala/Option$.MODULE$:Lscala/Option$;
        21: getstatic     #53                 // Field scala/Option$.MODULE$:Lscala/Option$;
        24: invokestatic  #57                 // Method coursier/paths/Mirror.extraConfigFile:()Ljava/io/File;
        27: invokevirtual #61                 // Method scala/Option$.apply:(Ljava/lang/Object;)Lscala/Option;
        30: invokevirtual #65                 // Method scala/Option$.option2Iterable:(Lscala/Option;)Lscala/collection/Iterable;
        33: invokeinterface #70,  1           // InterfaceMethod scala/collection/Iterable.toSeq:()Lscala/collection/immutable/Seq;
        38: invokeinterface #76,  2           // InterfaceMethod scala/collection/immutable/Seq.$plus$plus:(Lscala/collection/IterableOnce;)Ljava/lang/Object;
        43: checkcast     #72                 // class scala/collection/immutable/Seq
        46: astore_1
        47: aload_1
        48: invokedynamic #96,  0             // InvokeDynamic #0:apply:()Lscala/Function1;
        53: invokeinterface #100,  2          // InterfaceMethod scala/collection/immutable/Seq.map:(Lscala/Function1;)Ljava/lang/Object;
        58: checkcast     #72                 // class scala/collection/immutable/Seq
        61: areturn
      LineNumberTable:
        line 11: 0
        line 12: 18
        line 13: 47
      LocalVariableTable:
        Start  Length  Slot  Name   Signature
           47      14     1 files   Lscala/collection/immutable/Seq;
            0      62     0  this   Lcoursier/PlatformResolve;
    Signature: #21                          // ()Lscala/collection/immutable/Seq<Lcoursier/params/MirrorConfFile;>;

  private scala.collection.immutable.Seq<coursier.core.Repository> defaultRepositories$lzycompute();
    descriptor: ()Lscala/collection/immutable/Seq;
    flags: (0x0002) ACC_PRIVATE
    Code:
      stack=8, locals=6, args_size=1
         0: aload_0
         1: dup
         2: astore_1
         3: monitorenter
         4: aload_0
         5: getfield      #107                // Field bitmap$0:Z
         8: ifne          168
        11: aload_0
        12: getstatic     #112                // Field scala/collection/StringOps$.MODULE$:Lscala/collection/StringOps$;
        15: getstatic     #32                 // Field scala/Predef$.MODULE$:Lscala/Predef$;
        18: ldc           #114                // String \\s+
        20: invokevirtual #118                // Method scala/Predef$.augmentString:(Ljava/lang/String;)Ljava/lang/String;
        23: invokevirtual #122                // Method scala/collection/StringOps$.r$extension:(Ljava/lang/String;)Lscala/util/matching/Regex;
        26: astore_2
        27: getstatic     #53                 // Field scala/Option$.MODULE$:Lscala/Option$;
        30: ldc           #124                // String COURSIER_REPOSITORIES
        32: invokestatic  #129                // Method java/lang/System.getenv:(Ljava/lang/String;)Ljava/lang/String;
        35: invokevirtual #61                 // Method scala/Option$.apply:(Ljava/lang/Object;)Lscala/Option;
        38: invokedynamic #135,  0            // InvokeDynamic #1:apply:()Lscala/Function1;
        43: invokevirtual #140                // Method scala/Option.map:(Lscala/Function1;)Lscala/Option;
        46: invokedynamic #147,  0            // InvokeDynamic #2:apply:()Lscala/Function1;
        51: invokevirtual #150                // Method scala/Option.filter:(Lscala/Function1;)Lscala/Option;
        54: aload_2
        55: invokedynamic #160,  0            // InvokeDynamic #3:apply:(Lscala/util/matching/Regex;)Lscala/Function1;
        60: invokevirtual #163                // Method scala/Option.flatMap:(Lscala/Function1;)Lscala/Option;
        63: astore_3
        64: getstatic     #168                // Field scala/sys/package$.MODULE$:Lscala/sys/package$;
        67: invokevirtual #172                // Method scala/sys/package$.props:()Lscala/sys/SystemProperties;
        70: ldc           #174                // String coursier.repositories
        72: invokevirtual #179                // Method scala/sys/SystemProperties.get:(Ljava/lang/String;)Lscala/Option;
        75: invokedynamic #184,  0            // InvokeDynamic #4:apply:()Lscala/Function1;
        80: invokevirtual #140                // Method scala/Option.map:(Lscala/Function1;)Lscala/Option;
        83: invokedynamic #189,  0            // InvokeDynamic #5:apply:()Lscala/Function1;
        88: invokevirtual #150                // Method scala/Option.filter:(Lscala/Function1;)Lscala/Option;
        91: aload_2
        92: invokedynamic #194,  0            // InvokeDynamic #6:apply:(Lscala/util/matching/Regex;)Lscala/Function1;
        97: invokevirtual #163                // Method scala/Option.flatMap:(Lscala/Function1;)Lscala/Option;
       100: astore        4
       102: new           #196                // class scala/collection/immutable/$colon$colon
       105: dup
       106: getstatic     #201                // Field coursier/LocalRepositories$.MODULE$:Lcoursier/LocalRepositories$;
       109: invokevirtual #205                // Method coursier/LocalRepositories$.ivy2Local:()Lcoursier/ivy/IvyRepository;
       112: new           #196                // class scala/collection/immutable/$colon$colon
       115: dup
       116: getstatic     #210                // Field coursier/Repositories$.MODULE$:Lcoursier/Repositories$;
       119: invokevirtual #214                // Method coursier/Repositories$.central:()Lcoursier/maven/MavenRepository;
       122: getstatic     #219                // Field scala/collection/immutable/Nil$.MODULE$:Lscala/collection/immutable/Nil$;
       125: invokespecial #223                // Method scala/collection/immutable/$colon$colon."<init>":(Ljava/lang/Object;Lscala/collection/immutable/List;)V
       128: invokespecial #223                // Method scala/collection/immutable/$colon$colon."<init>":(Ljava/lang/Object;Lscala/collection/immutable/List;)V
       131: checkcast     #72                 // class scala/collection/immutable/Seq
       134: astore        5
       136: aload_3
       137: aload         4
       139: invokedynamic #235,  0            // InvokeDynamic #7:apply:(Lscala/Option;)Lscala/Function0;
       144: invokevirtual #239                // Method scala/Option.orElse:(Lscala/Function0;)Lscala/Option;
       147: aload         5
       149: invokedynamic #248,  0            // InvokeDynamic #8:apply:(Lscala/collection/immutable/Seq;)Lscala/Function0;
       154: invokevirtual #252                // Method scala/Option.getOrElse:(Lscala/Function0;)Ljava/lang/Object;
       157: checkcast     #72                 // class scala/collection/immutable/Seq
       160: putfield      #254                // Field defaultRepositories:Lscala/collection/immutable/Seq;
       163: aload_0
       164: iconst_1
       165: putfield      #107                // Field bitmap$0:Z
       168: aload_1
       169: monitorexit
       170: goto          176
       173: aload_1
       174: monitorexit
       175: athrow
       176: aload_0
       177: getfield      #254                // Field defaultRepositories:Lscala/collection/immutable/Seq;
       180: areturn
      Exception table:
         from    to  target type
             4   168   173   any
      StackMapTable: number_of_entries = 3
        frame_type = 252 /* append */
          offset_delta = 168
          locals = [ class coursier/PlatformResolve ]
        frame_type = 68 /* same_locals_1_stack_item */
          stack = [ class java/lang/Throwable ]
        frame_type = 2 /* same */
      LineNumberTable:
        line 19: 0
        line 21: 12
        line 49: 27
        line 50: 38
        line 51: 46
        line 52: 54
        line 54: 64
        line 55: 70
        line 56: 75
        line 57: 83
        line 58: 91
        line 60: 102
        line 61: 106
        line 60: 112
        line 62: 116
        line 60: 122
        line 65: 136
        line 66: 137
        line 67: 147
        line 19: 160
      LocalVariableTable:
        Start  Length  Slot  Name   Signature
           27     133     2 spaceSep   Lscala/util/matching/Regex;
           64      96     3 fromEnvOpt   Lscala/Option;
          102      58     4 fromPropsOpt   Lscala/Option;
          136      24     5 default   Lscala/collection/immutable/Seq;
            0     181     0  this   Lcoursier/PlatformResolve;
    Signature: #105                         // ()Lscala/collection/immutable/Seq<Lcoursier/core/Repository;>;

  public scala.collection.immutable.Seq<coursier.core.Repository> defaultRepositories();
    descriptor: ()Lscala/collection/immutable/Seq;
    flags: (0x0001) ACC_PUBLIC
    Code:
      stack=1, locals=1, args_size=1
         0: aload_0
         1: getfield      #107                // Field bitmap$0:Z
         4: ifne          14
         7: aload_0
         8: invokespecial #264                // Method defaultRepositories$lzycompute:()Lscala/collection/immutable/Seq;
        11: goto          18
        14: aload_0
        15: getfield      #254                // Field defaultRepositories:Lscala/collection/immutable/Seq;
        18: areturn
      StackMapTable: number_of_entries = 2
        frame_type = 14 /* same */
        frame_type = 67 /* same_locals_1_stack_item */
          stack = [ class scala/collection/immutable/Seq ]
      LineNumberTable:
        line 19: 0
      LocalVariableTable:
        Start  Length  Slot  Name   Signature
            0      19     0  this   Lcoursier/PlatformResolve;
    Signature: #105                         // ()Lscala/collection/immutable/Seq<Lcoursier/core/Repository;>;

  public static final coursier.params.MirrorConfFile $anonfun$defaultMirrorConfFiles$1(java.io.File);
    descriptor: (Ljava/io/File;)Lcoursier/params/MirrorConfFile;
    flags: (0x1019) ACC_PUBLIC, ACC_STATIC, ACC_FINAL, ACC_SYNTHETIC
    Code:
      stack=3, locals=1, args_size=1
         0: getstatic     #270                // Field coursier/params/MirrorConfFile$.MODULE$:Lcoursier/params/MirrorConfFile$;
         3: aload_0
         4: invokevirtual #276                // Method java/io/File.getAbsolutePath:()Ljava/lang/String;
         7: iconst_1
         8: invokevirtual #279                // Method coursier/params/MirrorConfFile$.apply:(Ljava/lang/String;Z)Lcoursier/params/MirrorConfFile;
        11: areturn
      LineNumberTable:
        line 15: 0
      LocalVariableTable:
        Start  Length  Slot  Name   Signature
            0      12     0     f   Ljava/io/File;
    MethodParameters:
      Name                           Flags
      f                              final

  public static final boolean $anonfun$defaultRepositories$1(java.lang.String);
    descriptor: (Ljava/lang/String;)Z
    flags: (0x1019) ACC_PUBLIC, ACC_STATIC, ACC_FINAL, ACC_SYNTHETIC
    Code:
      stack=3, locals=1, args_size=1
         0: getstatic     #112                // Field scala/collection/StringOps$.MODULE$:Lscala/collection/StringOps$;
         3: getstatic     #32                 // Field scala/Predef$.MODULE$:Lscala/Predef$;
         6: aload_0
         7: invokevirtual #118                // Method scala/Predef$.augmentString:(Ljava/lang/String;)Ljava/lang/String;
        10: invokevirtual #286                // Method scala/collection/StringOps$.nonEmpty$extension:(Ljava/lang/String;)Z
        13: ireturn
      LineNumberTable:
        line 30: 3
      LocalVariableTable:
        Start  Length  Slot  Name   Signature
            0      14     0   x$1   Ljava/lang/String;
    MethodParameters:
      Name                           Flags
      x$1                            final

  public static final boolean $anonfun$defaultRepositories$2(java.lang.String);
    descriptor: (Ljava/lang/String;)Z
    flags: (0x1019) ACC_PUBLIC, ACC_STATIC, ACC_FINAL, ACC_SYNTHETIC
    Code:
      stack=3, locals=1, args_size=1
         0: getstatic     #112                // Field scala/collection/StringOps$.MODULE$:Lscala/collection/StringOps$;
         3: getstatic     #32                 // Field scala/Predef$.MODULE$:Lscala/Predef$;
         6: aload_0
         7: invokevirtual #118                // Method scala/Predef$.augmentString:(Ljava/lang/String;)Ljava/lang/String;
        10: invokevirtual #286                // Method scala/collection/StringOps$.nonEmpty$extension:(Ljava/lang/String;)Z
        13: ireturn
      LineNumberTable:
        line 35: 3
      LocalVariableTable:
        Start  Length  Slot  Name   Signature
            0      14     0   x$2   Ljava/lang/String;
    MethodParameters:
      Name                           Flags
      x$2                            final

  public static final java.lang.String $anonfun$defaultRepositories$3(java.lang.String);
    descriptor: (Ljava/lang/String;)Ljava/lang/String;
    flags: (0x1019) ACC_PUBLIC, ACC_STATIC, ACC_FINAL, ACC_SYNTHETIC
    Code:
      stack=3, locals=1, args_size=1
         0: new           #293                // class java/lang/StringBuilder
         3: dup
         4: ldc_w         #294                // int 2
         7: invokespecial #297                // Method java/lang/StringBuilder."<init>":(I)V
        10: ldc_w         #299                // String
        13: invokevirtual #303                // Method java/lang/StringBuilder.append:(Ljava/lang/String;)Ljava/lang/StringBuilder;
        16: aload_0
        17: invokevirtual #303                // Method java/lang/StringBuilder.append:(Ljava/lang/String;)Ljava/lang/StringBuilder;
        20: invokestatic  #306                // Method java/lang/System.lineSeparator:()Ljava/lang/String;
        23: invokevirtual #303                // Method java/lang/StringBuilder.append:(Ljava/lang/String;)Ljava/lang/StringBuilder;
        26: invokevirtual #309                // Method java/lang/StringBuilder.toString:()Ljava/lang/String;
        29: areturn
      LineNumberTable:
        line 41: 0
      LocalVariableTable:
        Start  Length  Slot  Name   Signature
            0      30     0   x$3   Ljava/lang/String;
    MethodParameters:
      Name                           Flags
      x$3                            final

  private static final scala.Option fromString$1(java.lang.String, java.lang.String, scala.util.matching.Regex);
    descriptor: (Ljava/lang/String;Ljava/lang/String;Lscala/util/matching/Regex;)Lscala/Option;
    flags: (0x001a) ACC_PRIVATE, ACC_STATIC, ACC_FINAL
    Code:
      stack=5, locals=10, args_size=3
         0: aload_2
         1: aload_0
         2: invokevirtual #320                // Method scala/util/matching/Regex.findFirstIn:(Ljava/lang/CharSequence;)Lscala/Option;
         5: invokevirtual #324                // Method scala/Option.isEmpty:()Z
         8: ifeq          57
        11: getstatic     #27                 // Field scala/collection/ArrayOps$.MODULE$:Lscala/collection/ArrayOps$;
        14: getstatic     #32                 // Field scala/Predef$.MODULE$:Lscala/Predef$;
        17: getstatic     #112                // Field scala/collection/StringOps$.MODULE$:Lscala/collection/StringOps$;
        20: getstatic     #32                 // Field scala/Predef$.MODULE$:Lscala/Predef$;
        23: aload_0
        24: invokevirtual #118                // Method scala/Predef$.augmentString:(Ljava/lang/String;)Ljava/lang/String;
        27: bipush        124
        29: invokevirtual #328                // Method scala/collection/StringOps$.split$extension:(Ljava/lang/String;C)[Ljava/lang/String;
        32: checkcast     #40                 // class "[Ljava/lang/Object;"
        35: invokevirtual #44                 // Method scala/Predef$.refArrayOps:([Ljava/lang/Object;)Ljava/lang/Object;
        38: invokevirtual #48                 // Method scala/collection/ArrayOps$.toSeq$extension:(Ljava/lang/Object;)Lscala/collection/immutable/Seq;
        41: invokedynamic #333,  0            // InvokeDynamic #9:apply:()Lscala/Function1;
        46: invokeinterface #335,  2          // InterfaceMethod scala/collection/immutable/Seq.filter:(Lscala/Function1;)Ljava/lang/Object;
        51: checkcast     #72                 // class scala/collection/immutable/Seq
        54: goto          90
        57: getstatic     #27                 // Field scala/collection/ArrayOps$.MODULE$:Lscala/collection/ArrayOps$;
        60: getstatic     #32                 // Field scala/Predef$.MODULE$:Lscala/Predef$;
        63: aload_2
        64: aload_0
        65: invokevirtual #339                // Method scala/util/matching/Regex.split:(Ljava/lang/CharSequence;)[Ljava/lang/String;
        68: checkcast     #40                 // class "[Ljava/lang/Object;"
        71: invokevirtual #44                 // Method scala/Predef$.refArrayOps:([Ljava/lang/Object;)Ljava/lang/Object;
        74: invokevirtual #48                 // Method scala/collection/ArrayOps$.toSeq$extension:(Ljava/lang/Object;)Lscala/collection/immutable/Seq;
        77: invokedynamic #344,  0            // InvokeDynamic #10:apply:()Lscala/Function1;
        82: invokeinterface #335,  2          // InterfaceMethod scala/collection/immutable/Seq.filter:(Lscala/Function1;)Ljava/lang/Object;
        87: checkcast     #72                 // class scala/collection/immutable/Seq
        90: astore        4
        92: getstatic     #349                // Field coursier/parse/RepositoryParser$.MODULE$:Lcoursier/parse/RepositoryParser$;
        95: aload         4
        97: invokevirtual #353                // Method coursier/parse/RepositoryParser$.repositories:(Lscala/collection/immutable/Seq;)Lcoursier/util/ValidationNel;
       100: invokevirtual #359                // Method coursier/util/ValidationNel.either:()Lscala/util/Either;
       103: astore        5
       105: aload         5
       107: instanceof    #361                // class scala/util/Left
       110: ifeq          210
       113: aload         5
       115: checkcast     #361                // class scala/util/Left
       118: astore        6
       120: aload         6
       122: invokevirtual #364                // Method scala/util/Left.value:()Ljava/lang/Object;
       125: checkcast     #196                // class scala/collection/immutable/$colon$colon
       128: astore        7
       130: getstatic     #368                // Field java/lang/System.err:Ljava/io/PrintStream;
       133: new           #293                // class java/lang/StringBuilder
       136: dup
       137: ldc_w         #369                // int 0
       140: invokespecial #297                // Method java/lang/StringBuilder."<init>":(I)V
       143: new           #293                // class java/lang/StringBuilder
       146: dup
       147: ldc_w         #370                // int 46
       150: invokespecial #297                // Method java/lang/StringBuilder."<init>":(I)V
       153: ldc_w         #372                // String Ignoring
       156: invokevirtual #303                // Method java/lang/StringBuilder.append:(Ljava/lang/String;)Ljava/lang/StringBuilder;
       159: aload_1
       160: invokevirtual #303                // Method java/lang/StringBuilder.append:(Ljava/lang/String;)Ljava/lang/StringBuilder;
       163: ldc_w         #374                // String , error parsing repositories from it:
       166: invokevirtual #303                // Method java/lang/StringBuilder.append:(Ljava/lang/String;)Ljava/lang/StringBuilder;
       169: invokevirtual #309                // Method java/lang/StringBuilder.toString:()Ljava/lang/String;
       172: invokevirtual #303                // Method java/lang/StringBuilder.append:(Ljava/lang/String;)Ljava/lang/StringBuilder;
       175: invokestatic  #306                // Method java/lang/System.lineSeparator:()Ljava/lang/String;
       178: invokevirtual #303                // Method java/lang/StringBuilder.append:(Ljava/lang/String;)Ljava/lang/StringBuilder;
       181: aload         7
       183: invokedynamic #378,  0            // InvokeDynamic #11:apply:()Lscala/Function1;
       188: invokevirtual #381                // Method scala/collection/immutable/$colon$colon.map:(Lscala/Function1;)Lscala/collection/immutable/List;
       191: invokevirtual #386                // Method scala/collection/immutable/List.mkString:()Ljava/lang/String;
       194: invokevirtual #303                // Method java/lang/StringBuilder.append:(Ljava/lang/String;)Ljava/lang/StringBuilder;
       197: invokevirtual #309                // Method java/lang/StringBuilder.toString:()Ljava/lang/String;
       200: invokevirtual #392                // Method java/io/PrintStream.println:(Ljava/lang/String;)V
       203: getstatic     #397                // Field scala/None$.MODULE$:Lscala/None$;
       206: astore_3
       207: goto          264
       210: goto          213
       213: aload         5
       215: instanceof    #401                // class scala/util/Right
       218: ifeq          251
       221: aload         5
       223: checkcast     #401                // class scala/util/Right
       226: astore        8
       228: aload         8
       230: invokevirtual #402                // Method scala/util/Right.value:()Ljava/lang/Object;
       233: checkcast     #72                 // class scala/collection/immutable/Seq
       236: astore        9
       238: new           #404                // class scala/Some
       241: dup
       242: aload         9
       244: invokespecial #407                // Method scala/Some."<init>":(Ljava/lang/Object;)V
       247: astore_3
       248: goto          264
       251: goto          254
       254: new           #409                // class scala/MatchError
       257: dup
       258: aload         5
       260: invokespecial #410                // Method scala/MatchError."<init>":(Ljava/lang/Object;)V
       263: athrow
       264: aload_3
       265: areturn
      StackMapTable: number_of_entries = 7
        frame_type = 57 /* same */
        frame_type = 96 /* same_locals_1_stack_item */
          stack = [ class scala/collection/immutable/Seq ]
        frame_type = 254 /* append */
          offset_delta = 119
          locals = [ top, class scala/collection/immutable/Seq, class scala/util/Either ]
        frame_type = 2 /* same */
        frame_type = 37 /* same */
        frame_type = 2 /* same */
        frame_type = 255 /* full_frame */
          offset_delta = 9
          locals = [ class java/lang/String, class java/lang/String, class scala/util/matching/Regex, class scala/Option, class scala/collection/immutable/Seq, class scala/util/Either ]
          stack = []
      LineNumberTable:
        line 26: 0
        line 30: 11
        line 28: 14
        line 27: 20
        line 28: 27
        line 30: 41
        line 35: 57
        line 33: 60
        line 32: 63
        line 33: 64
        line 35: 77
        line 37: 92
        line 38: 105
        line 39: 130
        line 40: 133
        line 41: 181
        line 43: 203
        line 38: 210
        line 44: 213
        line 45: 238
        line 44: 251
        line 37: 254
      LocalVariableTable:
        Start  Length  Slot  Name   Signature
          130      80     7  errs   Lscala/collection/immutable/$colon$colon;
          238      13     9 repos   Lscala/collection/immutable/Seq;
           92     173     4     l   Lscala/collection/immutable/Seq;
            0     266     0   str   Ljava/lang/String;
            0     266     1 origin   Ljava/lang/String;
            0     266     2 spaceSep$1   Lscala/util/matching/Regex;
    MethodParameters:
      Name                           Flags
      str                            final
      origin                         final
      spaceSep$1                     final

  public static final java.lang.String $anonfun$defaultRepositories$4(java.lang.String);
    descriptor: (Ljava/lang/String;)Ljava/lang/String;
    flags: (0x1019) ACC_PUBLIC, ACC_STATIC, ACC_FINAL, ACC_SYNTHETIC
    Code:
      stack=1, locals=1, args_size=1
         0: aload_0
         1: invokevirtual #420                // Method java/lang/String.trim:()Ljava/lang/String;
         4: areturn
      LineNumberTable:
        line 50: 0
      LocalVariableTable:
        Start  Length  Slot  Name   Signature
            0       5     0   x$4   Ljava/lang/String;
    MethodParameters:
      Name                           Flags
      x$4                            final

  public static final boolean $anonfun$defaultRepositories$5(java.lang.String);
    descriptor: (Ljava/lang/String;)Z
    flags: (0x1019) ACC_PUBLIC, ACC_STATIC, ACC_FINAL, ACC_SYNTHETIC
    Code:
      stack=3, locals=1, args_size=1
         0: getstatic     #112                // Field scala/collection/StringOps$.MODULE$:Lscala/collection/StringOps$;
         3: getstatic     #32                 // Field scala/Predef$.MODULE$:Lscala/Predef$;
         6: aload_0
         7: invokevirtual #118                // Method scala/Predef$.augmentString:(Ljava/lang/String;)Ljava/lang/String;
        10: invokevirtual #286                // Method scala/collection/StringOps$.nonEmpty$extension:(Ljava/lang/String;)Z
        13: ireturn
      LineNumberTable:
        line 51: 3
      LocalVariableTable:
        Start  Length  Slot  Name   Signature
            0      14     0   x$5   Ljava/lang/String;
    MethodParameters:
      Name                           Flags
      x$5                            final

  public static final scala.Option $anonfun$defaultRepositories$6(scala.util.matching.Regex, java.lang.String);
    descriptor: (Lscala/util/matching/Regex;Ljava/lang/String;)Lscala/Option;
    flags: (0x1019) ACC_PUBLIC, ACC_STATIC, ACC_FINAL, ACC_SYNTHETIC
    Code:
      stack=3, locals=2, args_size=2
         0: aload_1
         1: ldc_w         #425                // String environment variable COURSIER_REPOSITORIES
         4: aload_0
         5: invokestatic  #427                // Method fromString$1:(Ljava/lang/String;Ljava/lang/String;Lscala/util/matching/Regex;)Lscala/Option;
         8: areturn
      LineNumberTable:
        line 52: 0
      LocalVariableTable:
        Start  Length  Slot  Name   Signature
            0       9     0 spaceSep$1   Lscala/util/matching/Regex;
            0       9     1   x$6   Ljava/lang/String;
    MethodParameters:
      Name                           Flags
      spaceSep$1                     final
      x$6                            final

  public static final java.lang.String $anonfun$defaultRepositories$7(java.lang.String);
    descriptor: (Ljava/lang/String;)Ljava/lang/String;
    flags: (0x1019) ACC_PUBLIC, ACC_STATIC, ACC_FINAL, ACC_SYNTHETIC
    Code:
      stack=1, locals=1, args_size=1
         0: aload_0
         1: invokevirtual #420                // Method java/lang/String.trim:()Ljava/lang/String;
         4: areturn
      LineNumberTable:
        line 56: 0
      LocalVariableTable:
        Start  Length  Slot  Name   Signature
            0       5     0   x$7   Ljava/lang/String;
    MethodParameters:
      Name                           Flags
      x$7                            final

  public static final boolean $anonfun$defaultRepositories$8(java.lang.String);
    descriptor: (Ljava/lang/String;)Z
    flags: (0x1019) ACC_PUBLIC, ACC_STATIC, ACC_FINAL, ACC_SYNTHETIC
    Code:
      stack=3, locals=1, args_size=1
         0: getstatic     #112                // Field scala/collection/StringOps$.MODULE$:Lscala/collection/StringOps$;
         3: getstatic     #32                 // Field scala/Predef$.MODULE$:Lscala/Predef$;
         6: aload_0
         7: invokevirtual #118                // Method scala/Predef$.augmentString:(Ljava/lang/String;)Ljava/lang/String;
        10: invokevirtual #286                // Method scala/collection/StringOps$.nonEmpty$extension:(Ljava/lang/String;)Z
        13: ireturn
      LineNumberTable:
        line 57: 3
      LocalVariableTable:
        Start  Length  Slot  Name   Signature
            0      14     0   x$8   Ljava/lang/String;
    MethodParameters:
      Name                           Flags
      x$8                            final

  public static final scala.Option $anonfun$defaultRepositories$9(scala.util.matching.Regex, java.lang.String);
    descriptor: (Lscala/util/matching/Regex;Ljava/lang/String;)Lscala/Option;
    flags: (0x1019) ACC_PUBLIC, ACC_STATIC, ACC_FINAL, ACC_SYNTHETIC
    Code:
      stack=3, locals=2, args_size=2
         0: aload_1
         1: ldc_w         #433                // String Java property coursier.repositories
         4: aload_0
         5: invokestatic  #427                // Method fromString$1:(Ljava/lang/String;Ljava/lang/String;Lscala/util/matching/Regex;)Lscala/Option;
         8: areturn
      LineNumberTable:
        line 58: 0
      LocalVariableTable:
        Start  Length  Slot  Name   Signature
            0       9     0 spaceSep$1   Lscala/util/matching/Regex;
            0       9     1   x$9   Ljava/lang/String;
    MethodParameters:
      Name                           Flags
      spaceSep$1                     final
      x$9                            final

  public static final scala.Option $anonfun$defaultRepositories$10(scala.Option);
    descriptor: (Lscala/Option;)Lscala/Option;
    flags: (0x1019) ACC_PUBLIC, ACC_STATIC, ACC_FINAL, ACC_SYNTHETIC
    Code:
      stack=1, locals=1, args_size=1
         0: aload_0
         1: areturn
      LineNumberTable:
        line 66: 0
      LocalVariableTable:
        Start  Length  Slot  Name   Signature
            0       2     0 fromPropsOpt$1   Lscala/Option;
    MethodParameters:
      Name                           Flags
      fromPropsOpt$1                 final

  public static final scala.collection.immutable.Seq $anonfun$defaultRepositories$11(scala.collection.immutable.Seq);
    descriptor: (Lscala/collection/immutable/Seq;)Lscala/collection/immutable/Seq;
    flags: (0x1019) ACC_PUBLIC, ACC_STATIC, ACC_FINAL, ACC_SYNTHETIC
    Code:
      stack=1, locals=1, args_size=1
         0: aload_0
         1: areturn
      LineNumberTable:
        line 67: 0
      LocalVariableTable:
        Start  Length  Slot  Name   Signature
            0       2     0 default$1   Lscala/collection/immutable/Seq;
    MethodParameters:
      Name                           Flags
      default$1                      final

  public coursier.PlatformResolve();
    descriptor: ()V
    flags: (0x0001) ACC_PUBLIC
    Code:
      stack=1, locals=1, args_size=1
         0: aload_0
         1: invokespecial #438                // Method java/lang/Object."<init>":()V
         4: return
      LineNumberTable:
        line 70: 0
        line 8: 4
      LocalVariableTable:
        Start  Length  Slot  Name   Signature
            0       5     0  this   Lcoursier/PlatformResolve;

  public static final java.lang.Object $anonfun$defaultRepositories$5$adapted(java.lang.String);
    descriptor: (Ljava/lang/String;)Ljava/lang/Object;
    flags: (0x1019) ACC_PUBLIC, ACC_STATIC, ACC_FINAL, ACC_SYNTHETIC
    Code:
      stack=1, locals=1, args_size=1
         0: aload_0
         1: invokestatic  #440                // Method $anonfun$defaultRepositories$5:(Ljava/lang/String;)Z
         4: invokestatic  #446                // Method scala/runtime/BoxesRunTime.boxToBoolean:(Z)Ljava/lang/Boolean;
         7: areturn
      LineNumberTable:
        line 51: 0
      LocalVariableTable:
        Start  Length  Slot  Name   Signature
            0       8     0   x$5   Ljava/lang/String;
    MethodParameters:
      Name                           Flags
      x$5                            final

  public static final java.lang.Object $anonfun$defaultRepositories$8$adapted(java.lang.String);
    descriptor: (Ljava/lang/String;)Ljava/lang/Object;
    flags: (0x1019) ACC_PUBLIC, ACC_STATIC, ACC_FINAL, ACC_SYNTHETIC
    Code:
      stack=1, locals=1, args_size=1
         0: aload_0
         1: invokestatic  #448                // Method $anonfun$defaultRepositories$8:(Ljava/lang/String;)Z
         4: invokestatic  #446                // Method scala/runtime/BoxesRunTime.boxToBoolean:(Z)Ljava/lang/Boolean;
         7: areturn
      LineNumberTable:
        line 57: 0
      LocalVariableTable:
        Start  Length  Slot  Name   Signature
            0       8     0   x$8   Ljava/lang/String;
    MethodParameters:
      Name                           Flags
      x$8                            final

  public static final java.lang.Object $anonfun$defaultRepositories$1$adapted(java.lang.String);
    descriptor: (Ljava/lang/String;)Ljava/lang/Object;
    flags: (0x1019) ACC_PUBLIC, ACC_STATIC, ACC_FINAL, ACC_SYNTHETIC
    Code:
      stack=1, locals=1, args_size=1
         0: aload_0
         1: invokestatic  #450                // Method $anonfun$defaultRepositories$1:(Ljava/lang/String;)Z
         4: invokestatic  #446                // Method scala/runtime/BoxesRunTime.boxToBoolean:(Z)Ljava/lang/Boolean;
         7: areturn
      LineNumberTable:
        line 30: 0
      LocalVariableTable:
        Start  Length  Slot  Name   Signature
            0       8     0   x$1   Ljava/lang/String;
    MethodParameters:
      Name                           Flags
      x$1                            final

  public static final java.lang.Object $anonfun$defaultRepositories$2$adapted(java.lang.String);
    descriptor: (Ljava/lang/String;)Ljava/lang/Object;
    flags: (0x1019) ACC_PUBLIC, ACC_STATIC, ACC_FINAL, ACC_SYNTHETIC
    Code:
      stack=1, locals=1, args_size=1
         0: aload_0
         1: invokestatic  #452                // Method $anonfun$defaultRepositories$2:(Ljava/lang/String;)Z
         4: invokestatic  #446                // Method scala/runtime/BoxesRunTime.boxToBoolean:(Z)Ljava/lang/Boolean;
         7: areturn
      LineNumberTable:
        line 35: 0
      LocalVariableTable:
        Start  Length  Slot  Name   Signature
            0       8     0   x$2   Ljava/lang/String;
    MethodParameters:
      Name                           Flags
      x$2                            final

  private static java.lang.Object $deserializeLambda$(java.lang.invoke.SerializedLambda);
    descriptor: (Ljava/lang/invoke/SerializedLambda;)Ljava/lang/Object;
    flags: (0x100a) ACC_PRIVATE, ACC_STATIC, ACC_SYNTHETIC
    Code:
      stack=1, locals=1, args_size=1
         0: aload_0
         1: invokedynamic #464,  0            // InvokeDynamic #12:lambdaDeserialize:(Ljava/lang/invoke/SerializedLambda;)Ljava/lang/Object;
         6: areturn
}
InnerClasses:
  public static final #13= #10 of #12;    // Lookup=class java/lang/invoke/MethodHandles$Lookup of class java/lang/invoke/MethodHandles
SourceFile: "PlatformResolve.scala"
RuntimeVisibleAnnotations:
  0: #6(#7=s#8)
    scala.reflect.ScalaSignature(
      bytes="\u0006\u0005A2Q\u0001B\u0003\u0002\u0002!AQa\u0004\u0001\u0005\u0002AAQa\u0005\u0001\u0005\u0002QA\u0001b\n\u0001\t\u0006\u0004%\t\u0001\u000b\u0002\u0010!2\fGOZ8s[J+7o\u001c7wK*\ta!\u0001\u0005d_V\u00148/[3s\u0007\u0001\u0019\"\u0001A\u0005\u0011\u0005)iQ\"A\u0006\u000b\u00031\tQa]2bY\u0006L!AD\u0006\u0003\r\u0005s\u0017PU3g\u0003\u0019a\u0014N\\5u}Q\t\u0011\u0003\u0005\u0002\u0013\u00015\tQ!\u0001\feK\u001a\fW\u000f\u001c;NSJ\u0014xN]\"p]\u001a4\u0015\u000e\\3t+\u0005)\u0002c\u0001\f\u001fC9\u0011q\u0003\b\b\u00031mi\u0011!\u0007\u0006\u00035\u001d\ta\u0001\u0010:p_Rt\u0014\"\u0001\u0007\n\u0005uY\u0011a\u00029bG.\fw-Z\u0005\u0003?\u0001\u00121aU3r\u0015\ti2\u0002\u0005\u0002#K5\t1E\u0003\u0002%\u000b\u00051\u0001/\u0019:b[NL!AJ\u0012\u0003\u001d5K\'O]8s\u0007>tgMR5mK\u0006\u0019B-\u001a4bk2$(+\u001a9pg&$xN]5fgV\t\u0011\u0006E\u0002\u0017=)\u0002\"aK\u0017\u000f\u0005Ia\u0013BA\u000f\u0006\u0013\tqsF\u0001\u0006SKB|7/\u001b;pefT!!H\u0003"
    )
BootstrapMethods:
  0: #93 REF_invokeStatic java/lang/invoke/LambdaMetafactory.altMetafactory:(Ljava/lang/invoke/MethodHandles$Lookup;Ljava/lang/String;Ljava/lang/invoke/MethodType;[Ljava/lang/Object;)Ljava/lang/invoke/CallSite;
    Method arguments:
      #78 (Ljava/lang/Object;)Ljava/lang/Object;
      #83 REF_invokeStatic coursier/PlatformResolve.$anonfun$defaultMirrorConfFiles$1:(Ljava/io/File;)Lcoursier/params/MirrorConfFile;
      #84 (Ljava/io/File;)Lcoursier/params/MirrorConfFile;
      #85 5
      #86 1
      #84 (Ljava/io/File;)Lcoursier/params/MirrorConfFile;
  1: #93 REF_invokeStatic java/lang/invoke/LambdaMetafactory.altMetafactory:(Ljava/lang/invoke/MethodHandles$Lookup;Ljava/lang/String;Ljava/lang/invoke/MethodType;[Ljava/lang/Object;)Ljava/lang/invoke/CallSite;
    Method arguments:
      #78 (Ljava/lang/Object;)Ljava/lang/Object;
      #133 REF_invokeStatic coursier/PlatformResolve.$anonfun$defaultRepositories$4:(Ljava/lang/String;)Ljava/lang/String;
      #134 (Ljava/lang/String;)Ljava/lang/String;
      #85 5
      #86 1
      #134 (Ljava/lang/String;)Ljava/lang/String;
  2: #93 REF_invokeStatic java/lang/invoke/LambdaMetafactory.altMetafactory:(Ljava/lang/invoke/MethodHandles$Lookup;Ljava/lang/String;Ljava/lang/invoke/MethodType;[Ljava/lang/Object;)Ljava/lang/invoke/CallSite;
    Method arguments:
      #78 (Ljava/lang/Object;)Ljava/lang/Object;
      #145 REF_invokeStatic coursier/PlatformResolve.$anonfun$defaultRepositories$5$adapted:(Ljava/lang/String;)Ljava/lang/Object;
      #146 (Ljava/lang/String;)Ljava/lang/Object;
      #85 5
      #86 1
      #146 (Ljava/lang/String;)Ljava/lang/Object;
  3: #93 REF_invokeStatic java/lang/invoke/LambdaMetafactory.altMetafactory:(Ljava/lang/invoke/MethodHandles$Lookup;Ljava/lang/String;Ljava/lang/invoke/MethodType;[Ljava/lang/Object;)Ljava/lang/invoke/CallSite;
    Method arguments:
      #78 (Ljava/lang/Object;)Ljava/lang/Object;
      #155 REF_invokeStatic coursier/PlatformResolve.$anonfun$defaultRepositories$6:(Lscala/util/matching/Regex;Ljava/lang/String;)Lscala/Option;
      #157 (Ljava/lang/String;)Lscala/Option;
      #85 5
      #86 1
      #157 (Ljava/lang/String;)Lscala/Option;
  4: #93 REF_invokeStatic java/lang/invoke/LambdaMetafactory.altMetafactory:(Ljava/lang/invoke/MethodHandles$Lookup;Ljava/lang/String;Ljava/lang/invoke/MethodType;[Ljava/lang/Object;)Ljava/lang/invoke/CallSite;
    Method arguments:
      #78 (Ljava/lang/Object;)Ljava/lang/Object;
      #183 REF_invokeStatic coursier/PlatformResolve.$anonfun$defaultRepositories$7:(Ljava/lang/String;)Ljava/lang/String;
      #134 (Ljava/lang/String;)Ljava/lang/String;
      #85 5
      #86 1
      #134 (Ljava/lang/String;)Ljava/lang/String;
  5: #93 REF_invokeStatic java/lang/invoke/LambdaMetafactory.altMetafactory:(Ljava/lang/invoke/MethodHandles$Lookup;Ljava/lang/String;Ljava/lang/invoke/MethodType;[Ljava/lang/Object;)Ljava/lang/invoke/CallSite;
    Method arguments:
      #78 (Ljava/lang/Object;)Ljava/lang/Object;
      #188 REF_invokeStatic coursier/PlatformResolve.$anonfun$defaultRepositories$8$adapted:(Ljava/lang/String;)Ljava/lang/Object;
      #146 (Ljava/lang/String;)Ljava/lang/Object;
      #85 5
      #86 1
      #146 (Ljava/lang/String;)Ljava/lang/Object;
  6: #93 REF_invokeStatic java/lang/invoke/LambdaMetafactory.altMetafactory:(Ljava/lang/invoke/MethodHandles$Lookup;Ljava/lang/String;Ljava/lang/invoke/MethodType;[Ljava/lang/Object;)Ljava/lang/invoke/CallSite;
    Method arguments:
      #78 (Ljava/lang/Object;)Ljava/lang/Object;
      #193 REF_invokeStatic coursier/PlatformResolve.$anonfun$defaultRepositories$9:(Lscala/util/matching/Regex;Ljava/lang/String;)Lscala/Option;
      #157 (Ljava/lang/String;)Lscala/Option;
      #85 5
      #86 1
      #157 (Ljava/lang/String;)Lscala/Option;
  7: #93 REF_invokeStatic java/lang/invoke/LambdaMetafactory.altMetafactory:(Ljava/lang/invoke/MethodHandles$Lookup;Ljava/lang/String;Ljava/lang/invoke/MethodType;[Ljava/lang/Object;)Ljava/lang/invoke/CallSite;
    Method arguments:
      #225 ()Ljava/lang/Object;
      #230 REF_invokeStatic coursier/PlatformResolve.$anonfun$defaultRepositories$10:(Lscala/Option;)Lscala/Option;
      #232 ()Lscala/Option;
      #85 5
      #86 1
      #232 ()Lscala/Option;
  8: #93 REF_invokeStatic java/lang/invoke/LambdaMetafactory.altMetafactory:(Ljava/lang/invoke/MethodHandles$Lookup;Ljava/lang/String;Ljava/lang/invoke/MethodType;[Ljava/lang/Object;)Ljava/lang/invoke/CallSite;
    Method arguments:
      #225 ()Ljava/lang/Object;
      #244 REF_invokeStatic coursier/PlatformResolve.$anonfun$defaultRepositories$11:(Lscala/collection/immutable/Seq;)Lscala/collection/immutable/Seq;
      #245 ()Lscala/collection/immutable/Seq;
      #85 5
      #86 1
      #245 ()Lscala/collection/immutable/Seq;
  9: #93 REF_invokeStatic java/lang/invoke/LambdaMetafactory.altMetafactory:(Ljava/lang/invoke/MethodHandles$Lookup;Ljava/lang/String;Ljava/lang/invoke/MethodType;[Ljava/lang/Object;)Ljava/lang/invoke/CallSite;
    Method arguments:
      #78 (Ljava/lang/Object;)Ljava/lang/Object;
      #332 REF_invokeStatic coursier/PlatformResolve.$anonfun$defaultRepositories$1$adapted:(Ljava/lang/String;)Ljava/lang/Object;
      #146 (Ljava/lang/String;)Ljava/lang/Object;
      #85 5
      #86 1
      #146 (Ljava/lang/String;)Ljava/lang/Object;
  10: #93 REF_invokeStatic java/lang/invoke/LambdaMetafactory.altMetafactory:(Ljava/lang/invoke/MethodHandles$Lookup;Ljava/lang/String;Ljava/lang/invoke/MethodType;[Ljava/lang/Object;)Ljava/lang/invoke/CallSite;
    Method arguments:
      #78 (Ljava/lang/Object;)Ljava/lang/Object;
      #343 REF_invokeStatic coursier/PlatformResolve.$anonfun$defaultRepositories$2$adapted:(Ljava/lang/String;)Ljava/lang/Object;
      #146 (Ljava/lang/String;)Ljava/lang/Object;
      #85 5
      #86 1
      #146 (Ljava/lang/String;)Ljava/lang/Object;
  11: #93 REF_invokeStatic java/lang/invoke/LambdaMetafactory.altMetafactory:(Ljava/lang/invoke/MethodHandles$Lookup;Ljava/lang/String;Ljava/lang/invoke/MethodType;[Ljava/lang/Object;)Ljava/lang/invoke/CallSite;
    Method arguments:
      #78 (Ljava/lang/Object;)Ljava/lang/Object;
      #377 REF_invokeStatic coursier/PlatformResolve.$anonfun$defaultRepositories$3:(Ljava/lang/String;)Ljava/lang/String;
      #134 (Ljava/lang/String;)Ljava/lang/String;
      #85 5
      #86 1
      #134 (Ljava/lang/String;)Ljava/lang/String;
  12: #461 REF_invokeStatic scala/runtime/LambdaDeserialize.bootstrap:(Ljava/lang/invoke/MethodHandles$Lookup;Ljava/lang/String;Ljava/lang/invoke/MethodType;[Ljava/lang/invoke/MethodHandle;)Ljava/lang/invoke/CallSite;
    Method arguments:
      #83 REF_invokeStatic coursier/PlatformResolve.$anonfun$defaultMirrorConfFiles$1:(Ljava/io/File;)Lcoursier/params/MirrorConfFile;
      #332 REF_invokeStatic coursier/PlatformResolve.$anonfun$defaultRepositories$1$adapted:(Ljava/lang/String;)Ljava/lang/Object;
      #230 REF_invokeStatic coursier/PlatformResolve.$anonfun$defaultRepositories$10:(Lscala/Option;)Lscala/Option;
      #244 REF_invokeStatic coursier/PlatformResolve.$anonfun$defaultRepositories$11:(Lscala/collection/immutable/Seq;)Lscala/collection/immutable/Seq;
      #343 REF_invokeStatic coursier/PlatformResolve.$anonfun$defaultRepositories$2$adapted:(Ljava/lang/String;)Ljava/lang/Object;
      #377 REF_invokeStatic coursier/PlatformResolve.$anonfun$defaultRepositories$3:(Ljava/lang/String;)Ljava/lang/String;
      #133 REF_invokeStatic coursier/PlatformResolve.$anonfun$defaultRepositories$4:(Ljava/lang/String;)Ljava/lang/String;
      #145 REF_invokeStatic coursier/PlatformResolve.$anonfun$defaultRepositories$5$adapted:(Ljava/lang/String;)Ljava/lang/Object;
      #155 REF_invokeStatic coursier/PlatformResolve.$anonfun$defaultRepositories$6:(Lscala/util/matching/Regex;Ljava/lang/String;)Lscala/Option;
      #183 REF_invokeStatic coursier/PlatformResolve.$anonfun$defaultRepositories$7:(Ljava/lang/String;)Ljava/lang/String;
      #188 REF_invokeStatic coursier/PlatformResolve.$anonfun$defaultRepositories$8$adapted:(Ljava/lang/String;)Ljava/lang/Object;
      #193 REF_invokeStatic coursier/PlatformResolve.$anonfun$defaultRepositories$9:(Lscala/util/matching/Regex;Ljava/lang/String;)Lscala/Option;
  ScalaInlineInfo: length = 0x6D (unknown attribute)
   01 00 00 15 00 4F 00 50 01 01 19 01 1A 01 01 49
   00 8E 01 00 E2 00 E3 01 00 F0 00 F1 01 01 20 01
   1A 01 01 54 00 8E 01 01 22 00 74 01 00 82 00 74
   01 01 A5 01 1A 01 00 8D 00 8E 01 00 97 00 98 01
   00 B4 00 74 01 01 AD 01 1A 01 00 B9 00 8E 01 00
   BE 00 98 01 00 DC 01 B4 00 00 13 00 14 00 00 0E
   00 14 00 00 68 00 14 01 01 36 01 37 01
  ScalaSig: length = 0x3 (unknown attribute)
   05 02 00
