Classfile /Users/mw/Projects/slang-braindump/.jar/jar8/assemble/slang-braindump/assemble/content/scala/util/matching/Regex$MatchData.class
  Last modified May 29, 2022; size 7331 bytes
  SHA-256 checksum 7f583ab609b55d26951bdc1faada4111b8f56a215918472de5599ad63b3871e6
  Compiled from "Regex.scala"
public interface scala.util.matching.Regex$MatchData
  minor version: 0
  major version: 52
  flags: (0x0601) ACC_PUBLIC, ACC_INTERFACE, ACC_ABSTRACT
  this_class: #2                          // scala/util/matching/Regex$MatchData
  super_class: #4                         // java/lang/Object
  interfaces: 0, fields: 0, methods: 32, attributes: 4
Constant pool:
    #1 = Utf8               scala/util/matching/Regex$MatchData
    #2 = Class              #1            // scala/util/matching/Regex$MatchData
    #3 = Utf8               java/lang/Object
    #4 = Class              #3            // java/lang/Object
    #5 = Utf8               Regex.scala
    #6 = Utf8               scala/collection/immutable/Range$Inclusive
    #7 = Class              #6            // scala/collection/immutable/Range$Inclusive
    #8 = Utf8               scala/collection/immutable/Range
    #9 = Class              #8            // scala/collection/immutable/Range
   #10 = Utf8               Inclusive
   #11 = Utf8               scala/util/matching/Regex
   #12 = Class              #11           // scala/util/matching/Regex
   #13 = Utf8               MatchData
   #14 = Utf8               matcher
   #15 = Utf8               ()Ljava/util/regex/Matcher;
   #16 = Utf8               source
   #17 = Utf8               ()Ljava/lang/CharSequence;
   #18 = Utf8               groupNames
   #19 = Utf8               ()Lscala/collection/immutable/Seq;
   #20 = Utf8               ()Lscala/collection/immutable/Seq<Ljava/lang/String;>;
   #21 = Utf8               groupCount
   #22 = Utf8               ()I
   #23 = Utf8               start
   #24 = Utf8               (I)I
   #25 = Utf8               i
   #26 = Utf8               end
   #27 = Utf8               matched$
   #28 = Utf8               (Lscala/util/matching/Regex$MatchData;)Ljava/lang/String;
   #29 = Utf8               $this
   #30 = Utf8               matched
   #31 = Utf8               ()Ljava/lang/String;
   #32 = NameAndType        #30:#31       // matched:()Ljava/lang/String;
   #33 = InterfaceMethodref #2.#32        // scala/util/matching/Regex$MatchData.matched:()Ljava/lang/String;
   #34 = Utf8               Lscala/util/matching/Regex$MatchData;
   #35 = NameAndType        #23:#22       // start:()I
   #36 = InterfaceMethodref #2.#35        // scala/util/matching/Regex$MatchData.start:()I
   #37 = NameAndType        #16:#17       // source:()Ljava/lang/CharSequence;
   #38 = InterfaceMethodref #2.#37        // scala/util/matching/Regex$MatchData.source:()Ljava/lang/CharSequence;
   #39 = NameAndType        #26:#22       // end:()I
   #40 = InterfaceMethodref #2.#39        // scala/util/matching/Regex$MatchData.end:()I
   #41 = Utf8               java/lang/CharSequence
   #42 = Class              #41           // java/lang/CharSequence
   #43 = Utf8               subSequence
   #44 = Utf8               (II)Ljava/lang/CharSequence;
   #45 = NameAndType        #43:#44       // subSequence:(II)Ljava/lang/CharSequence;
   #46 = InterfaceMethodref #42.#45       // java/lang/CharSequence.subSequence:(II)Ljava/lang/CharSequence;
   #47 = Utf8               toString
   #48 = NameAndType        #47:#31       // toString:()Ljava/lang/String;
   #49 = Methodref          #4.#48        // java/lang/Object.toString:()Ljava/lang/String;
   #50 = Utf8               this
   #51 = Utf8               group$
   #52 = Utf8               (Lscala/util/matching/Regex$MatchData;I)Ljava/lang/String;
   #53 = Utf8               group
   #54 = Utf8               (I)Ljava/lang/String;
   #55 = NameAndType        #53:#54       // group:(I)Ljava/lang/String;
   #56 = InterfaceMethodref #2.#55        // scala/util/matching/Regex$MatchData.group:(I)Ljava/lang/String;
   #57 = Utf8               I
   #58 = NameAndType        #23:#24       // start:(I)I
   #59 = InterfaceMethodref #2.#58        // scala/util/matching/Regex$MatchData.start:(I)I
   #60 = NameAndType        #26:#24       // end:(I)I
   #61 = InterfaceMethodref #2.#60        // scala/util/matching/Regex$MatchData.end:(I)I
   #62 = Utf8               subgroups$
   #63 = Utf8               (Lscala/util/matching/Regex$MatchData;)Lscala/collection/immutable/List;
   #64 = Utf8               subgroups
   #65 = Utf8               ()Lscala/collection/immutable/List;
   #66 = NameAndType        #64:#65       // subgroups:()Lscala/collection/immutable/List;
   #67 = InterfaceMethodref #2.#66        // scala/util/matching/Regex$MatchData.subgroups:()Lscala/collection/immutable/List;
   #68 = Utf8               ()Lscala/collection/immutable/List<Ljava/lang/String;>;
   #69 = Utf8               scala/runtime/RichInt$
   #70 = Class              #69           // scala/runtime/RichInt$
   #71 = Utf8               MODULE$
   #72 = Utf8               Lscala/runtime/RichInt$;
   #73 = NameAndType        #71:#72       // MODULE$:Lscala/runtime/RichInt$;
   #74 = Fieldref           #70.#73       // scala/runtime/RichInt$.MODULE$:Lscala/runtime/RichInt$;
   #75 = NameAndType        #21:#22       // groupCount:()I
   #76 = InterfaceMethodref #2.#75        // scala/util/matching/Regex$MatchData.groupCount:()I
   #77 = Utf8               scala/collection/immutable/Range$
   #78 = Class              #77           // scala/collection/immutable/Range$
   #79 = Utf8               Lscala/collection/immutable/Range$;
   #80 = NameAndType        #71:#79       // MODULE$:Lscala/collection/immutable/Range$;
   #81 = Fieldref           #78.#80       // scala/collection/immutable/Range$.MODULE$:Lscala/collection/immutable/Range$;
   #82 = Utf8               <init>
   #83 = Utf8               (III)V
   #84 = NameAndType        #82:#83       // "<init>":(III)V
   #85 = Methodref          #7.#84        // scala/collection/immutable/Range$Inclusive."<init>":(III)V
   #86 = Utf8               scala/collection/IterableOnceOps
   #87 = Class              #86           // scala/collection/IterableOnceOps
   #88 = Utf8               toList$
   #89 = Utf8               (Lscala/collection/IterableOnceOps;)Lscala/collection/immutable/List;
   #90 = NameAndType        #88:#89       // toList$:(Lscala/collection/IterableOnceOps;)Lscala/collection/immutable/List;
   #91 = InterfaceMethodref #87.#90       // scala/collection/IterableOnceOps.toList$:(Lscala/collection/IterableOnceOps;)Lscala/collection/immutable/List;
   #92 = Utf8               scala/collection/immutable/Nil$
   #93 = Class              #92           // scala/collection/immutable/Nil$
   #94 = Utf8               Lscala/collection/immutable/Nil$;
   #95 = NameAndType        #71:#94       // MODULE$:Lscala/collection/immutable/Nil$;
   #96 = Fieldref           #93.#95       // scala/collection/immutable/Nil$.MODULE$:Lscala/collection/immutable/Nil$;
   #97 = Utf8               scala/collection/immutable/$colon$colon
   #98 = Class              #97           // scala/collection/immutable/$colon$colon
   #99 = Utf8               scala/collection/immutable/List
  #100 = Class              #99           // scala/collection/immutable/List
  #101 = Utf8               head
  #102 = Utf8               ()Ljava/lang/Object;
  #103 = NameAndType        #101:#102     // head:()Ljava/lang/Object;
  #104 = Methodref          #100.#103     // scala/collection/immutable/List.head:()Ljava/lang/Object;
  #105 = Utf8               scala/runtime/BoxesRunTime
  #106 = Class              #105          // scala/runtime/BoxesRunTime
  #107 = Utf8               unboxToInt
  #108 = Utf8               (Ljava/lang/Object;)I
  #109 = NameAndType        #107:#108     // unboxToInt:(Ljava/lang/Object;)I
  #110 = Methodref          #106.#109     // scala/runtime/BoxesRunTime.unboxToInt:(Ljava/lang/Object;)I
  #111 = Utf8               (Ljava/lang/Object;Lscala/collection/immutable/List;)V
  #112 = NameAndType        #82:#111      // "<init>":(Ljava/lang/Object;Lscala/collection/immutable/List;)V
  #113 = Methodref          #98.#112      // scala/collection/immutable/$colon$colon."<init>":(Ljava/lang/Object;Lscala/collection/immutable/List;)V
  #114 = Utf8               tail
  #115 = NameAndType        #114:#102     // tail:()Ljava/lang/Object;
  #116 = Methodref          #100.#115     // scala/collection/immutable/List.tail:()Ljava/lang/Object;
  #117 = Utf8               next_$eq
  #118 = Utf8               (Lscala/collection/immutable/List;)V
  #119 = NameAndType        #117:#118     // next_$eq:(Lscala/collection/immutable/List;)V
  #120 = Methodref          #98.#119      // scala/collection/immutable/$colon$colon.next_$eq:(Lscala/collection/immutable/List;)V
  #121 = Utf8               scala/runtime/Statics
  #122 = Class              #121          // scala/runtime/Statics
  #123 = Utf8               releaseFence
  #124 = Utf8               ()V
  #125 = NameAndType        #123:#124     // releaseFence:()V
  #126 = Methodref          #122.#125     // scala/runtime/Statics.releaseFence:()V
  #127 = Utf8               map_nx
  #128 = Utf8               Lscala/collection/immutable/$colon$colon;
  #129 = Utf8               map_h
  #130 = Utf8               map_t
  #131 = Utf8               map_rest
  #132 = Utf8               Lscala/collection/immutable/List;
  #133 = Utf8               map_this
  #134 = Utf8               to$extension_end
  #135 = Utf8               $anonfun$subgroups$1_i
  #136 = Utf8               before$
  #137 = Utf8               (Lscala/util/matching/Regex$MatchData;)Ljava/lang/CharSequence;
  #138 = Utf8               before
  #139 = NameAndType        #138:#17      // before:()Ljava/lang/CharSequence;
  #140 = InterfaceMethodref #2.#139       // scala/util/matching/Regex$MatchData.before:()Ljava/lang/CharSequence;
  #141 = Utf8               (Lscala/util/matching/Regex$MatchData;I)Ljava/lang/CharSequence;
  #142 = Utf8               (I)Ljava/lang/CharSequence;
  #143 = NameAndType        #138:#142     // before:(I)Ljava/lang/CharSequence;
  #144 = InterfaceMethodref #2.#143       // scala/util/matching/Regex$MatchData.before:(I)Ljava/lang/CharSequence;
  #145 = Utf8               after$
  #146 = Utf8               after
  #147 = NameAndType        #146:#17      // after:()Ljava/lang/CharSequence;
  #148 = InterfaceMethodref #2.#147       // scala/util/matching/Regex$MatchData.after:()Ljava/lang/CharSequence;
  #149 = Utf8               length
  #150 = NameAndType        #149:#22      // length:()I
  #151 = InterfaceMethodref #42.#150      // java/lang/CharSequence.length:()I
  #152 = NameAndType        #146:#142     // after:(I)Ljava/lang/CharSequence;
  #153 = InterfaceMethodref #2.#152       // scala/util/matching/Regex$MatchData.after:(I)Ljava/lang/CharSequence;
  #154 = Utf8               groupNamesNowarn
  #155 = NameAndType        #18:#19       // groupNames:()Lscala/collection/immutable/Seq;
  #156 = InterfaceMethodref #2.#155       // scala/util/matching/Regex$MatchData.groupNames:()Lscala/collection/immutable/Seq;
  #157 = Utf8               scala$util$matching$Regex$MatchData$$nameToIndex$
  #158 = Utf8               (Lscala/util/matching/Regex$MatchData;)Lscala/collection/immutable/Map;
  #159 = Utf8               scala$util$matching$Regex$MatchData$$nameToIndex
  #160 = Utf8               ()Lscala/collection/immutable/Map;
  #161 = NameAndType        #159:#160     // scala$util$matching$Regex$MatchData$$nameToIndex:()Lscala/collection/immutable/Map;
  #162 = InterfaceMethodref #2.#161       // scala/util/matching/Regex$MatchData.scala$util$matching$Regex$MatchData$$nameToIndex:()Lscala/collection/immutable/Map;
  #163 = Utf8               ()Lscala/collection/immutable/Map<Ljava/lang/String;Ljava/lang/Object;>;
  #164 = Utf8               scala/Predef$
  #165 = Class              #164          // scala/Predef$
  #166 = Utf8               Lscala/Predef$;
  #167 = NameAndType        #71:#166      // MODULE$:Lscala/Predef$;
  #168 = Fieldref           #165.#167     // scala/Predef$.MODULE$:Lscala/Predef$;
  #169 = Utf8               Map
  #170 = Utf8               ()Lscala/collection/immutable/Map$;
  #171 = NameAndType        #169:#170     // Map:()Lscala/collection/immutable/Map$;
  #172 = Methodref          #165.#171     // scala/Predef$.Map:()Lscala/collection/immutable/Map$;
  #173 = Utf8               scala/collection/immutable/Map$
  #174 = Class              #173          // scala/collection/immutable/Map$
  #175 = Utf8               from
  #176 = Utf8               (Lscala/collection/IterableOnce;)Lscala/collection/immutable/Map;
  #177 = NameAndType        #175:#176     // from:(Lscala/collection/IterableOnce;)Lscala/collection/immutable/Map;
  #178 = Methodref          #174.#177     // scala/collection/immutable/Map$.from:(Lscala/collection/IterableOnce;)Lscala/collection/immutable/Map;
  #179 = Utf8               scala/collection/immutable/Seq
  #180 = Class              #179          // scala/collection/immutable/Seq
  #181 = Utf8               toList
  #182 = NameAndType        #181:#65      // toList:()Lscala/collection/immutable/List;
  #183 = InterfaceMethodref #180.#182     // scala/collection/immutable/Seq.toList:()Lscala/collection/immutable/List;
  #184 = Utf8
  #185 = String             #184          //
  #186 = Utf8               scala/collection/StrictOptimizedIterableOps
  #187 = Class              #186          // scala/collection/StrictOptimizedIterableOps
  #188 = Utf8               zipWithIndex$
  #189 = Utf8               (Lscala/collection/StrictOptimizedIterableOps;)Ljava/lang/Object;
  #190 = NameAndType        #188:#189     // zipWithIndex$:(Lscala/collection/StrictOptimizedIterableOps;)Ljava/lang/Object;
  #191 = InterfaceMethodref #187.#190     // scala/collection/StrictOptimizedIterableOps.zipWithIndex$:(Lscala/collection/StrictOptimizedIterableOps;)Ljava/lang/Object;
  #192 = Utf8               scala/collection/IterableOnce
  #193 = Class              #192          // scala/collection/IterableOnce
  #194 = Utf8               scala/collection/MapOps
  #195 = Class              #194          // scala/collection/MapOps
  #196 = Utf8               $plus$plus
  #197 = Utf8               (Lscala/collection/IterableOnce;)Lscala/collection/IterableOps;
  #198 = NameAndType        #196:#197     // $plus$plus:(Lscala/collection/IterableOnce;)Lscala/collection/IterableOps;
  #199 = InterfaceMethodref #195.#198     // scala/collection/MapOps.$plus$plus:(Lscala/collection/IterableOnce;)Lscala/collection/IterableOps;
  #200 = Utf8               scala/collection/immutable/Map
  #201 = Class              #200          // scala/collection/immutable/Map
  #202 = Utf8               apply_elems
  #203 = Utf8               Lscala/collection/immutable/Seq;
  #204 = Utf8               $colon$colon_this
  #205 = Utf8               $colon$colon_elem
  #206 = Utf8               Ljava/lang/Object;
  #207 = Utf8               java/lang/String
  #208 = Class              #207          // java/lang/String
  #209 = Utf8               (Lscala/util/matching/Regex$MatchData;Ljava/lang/String;)Ljava/lang/String;
  #210 = Utf8               id
  #211 = Utf8               (Ljava/lang/String;)Ljava/lang/String;
  #212 = NameAndType        #53:#211      // group:(Ljava/lang/String;)Ljava/lang/String;
  #213 = InterfaceMethodref #2.#212       // scala/util/matching/Regex$MatchData.group:(Ljava/lang/String;)Ljava/lang/String;
  #214 = Utf8               Ljava/lang/String;
  #215 = Utf8               isEmpty
  #216 = Utf8               ()Z
  #217 = NameAndType        #215:#216     // isEmpty:()Z
  #218 = InterfaceMethodref #180.#217     // scala/collection/immutable/Seq.isEmpty:()Z
  #219 = NameAndType        #14:#15       // matcher:()Ljava/util/regex/Matcher;
  #220 = InterfaceMethodref #2.#219       // scala/util/matching/Regex$MatchData.matcher:()Ljava/util/regex/Matcher;
  #221 = Utf8               java/util/regex/Matcher
  #222 = Class              #221          // java/util/regex/Matcher
  #223 = Methodref          #222.#212     // java/util/regex/Matcher.group:(Ljava/lang/String;)Ljava/lang/String;
  #224 = Utf8               get
  #225 = Utf8               (Ljava/lang/Object;)Lscala/Option;
  #226 = NameAndType        #224:#225     // get:(Ljava/lang/Object;)Lscala/Option;
  #227 = InterfaceMethodref #201.#226     // scala/collection/immutable/Map.get:(Ljava/lang/Object;)Lscala/Option;
  #228 = Utf8               scala/Some
  #229 = Class              #228          // scala/Some
  #230 = Utf8               value
  #231 = NameAndType        #230:#102     // value:()Ljava/lang/Object;
  #232 = Methodref          #229.#231     // scala/Some.value:()Ljava/lang/Object;
  #233 = Utf8               scala/None$
  #234 = Class              #233          // scala/None$
  #235 = Utf8               Lscala/None$;
  #236 = NameAndType        #71:#235      // MODULE$:Lscala/None$;
  #237 = Fieldref           #234.#236     // scala/None$.MODULE$:Lscala/None$;
  #238 = Utf8               equals
  #239 = Utf8               (Ljava/lang/Object;)Z
  #240 = NameAndType        #238:#239     // equals:(Ljava/lang/Object;)Z
  #241 = Methodref          #4.#240       // java/lang/Object.equals:(Ljava/lang/Object;)Z
  #242 = Utf8               scala/MatchError
  #243 = Class              #242          // scala/MatchError
  #244 = Utf8               (Ljava/lang/Object;)V
  #245 = NameAndType        #82:#244      // "<init>":(Ljava/lang/Object;)V
  #246 = Methodref          #243.#245     // scala/MatchError."<init>":(Ljava/lang/Object;)V
  #247 = Utf8               index
  #248 = Utf8               scala/Option
  #249 = Class              #248          // scala/Option
  #250 = Utf8               toString$
  #251 = InterfaceMethodref #2.#48        // scala/util/matching/Regex$MatchData.toString:()Ljava/lang/String;
  #252 = Utf8               $anonfun$subgroups$1
  #253 = Utf8               $init$
  #254 = Utf8               (Lscala/util/matching/Regex$MatchData;)V
  #255 = Utf8               $anonfun$subgroups$1$adapted
  #256 = Utf8               (Lscala/util/matching/Regex$MatchData;Ljava/lang/Object;)Ljava/lang/String;
  #257 = NameAndType        #252:#52      // $anonfun$subgroups$1:(Lscala/util/matching/Regex$MatchData;I)Ljava/lang/String;
  #258 = InterfaceMethodref #2.#257       // scala/util/matching/Regex$MatchData.$anonfun$subgroups$1:(Lscala/util/matching/Regex$MatchData;I)Ljava/lang/String;
  #259 = Utf8               Signature
  #260 = Utf8               Deprecated
  #261 = Utf8               MethodParameters
  #262 = Utf8               Code
  #263 = Utf8               LineNumberTable
  #264 = Utf8               LocalVariableTable
  #265 = Utf8               StackMapTable
  #266 = Utf8               InnerClasses
  #267 = Utf8               SourceFile
  #268 = Utf8               ScalaInlineInfo
  #269 = Utf8               Scala
{
  public abstract java.util.regex.Matcher matcher();
    descriptor: ()Ljava/util/regex/Matcher;
    flags: (0x0401) ACC_PUBLIC, ACC_ABSTRACT

  public abstract java.lang.CharSequence source();
    descriptor: ()Ljava/lang/CharSequence;
    flags: (0x0401) ACC_PUBLIC, ACC_ABSTRACT

  public abstract scala.collection.immutable.Seq<java.lang.String> groupNames();
    descriptor: ()Lscala/collection/immutable/Seq;
    flags: (0x0401) ACC_PUBLIC, ACC_ABSTRACT
    Signature: #20                          // ()Lscala/collection/immutable/Seq<Ljava/lang/String;>;
    Deprecated: true

  public abstract int groupCount();
    descriptor: ()I
    flags: (0x0401) ACC_PUBLIC, ACC_ABSTRACT

  public abstract int start();
    descriptor: ()I
    flags: (0x0401) ACC_PUBLIC, ACC_ABSTRACT

  public abstract int start(int);
    descriptor: (I)I
    flags: (0x0401) ACC_PUBLIC, ACC_ABSTRACT
    MethodParameters:
      Name                           Flags
      i                              final

  public abstract int end();
    descriptor: ()I
    flags: (0x0401) ACC_PUBLIC, ACC_ABSTRACT

  public abstract int end(int);
    descriptor: (I)I
    flags: (0x0401) ACC_PUBLIC, ACC_ABSTRACT
    MethodParameters:
      Name                           Flags
      i                              final

  public static java.lang.String matched$(scala.util.matching.Regex$MatchData);
    descriptor: (Lscala/util/matching/Regex$MatchData;)Ljava/lang/String;
    flags: (0x1009) ACC_PUBLIC, ACC_STATIC, ACC_SYNTHETIC
    Code:
      stack=1, locals=1, args_size=1
         0: aload_0
         1: invokespecial #33                 // InterfaceMethod matched:()Ljava/lang/String;
         4: areturn
      LineNumberTable:
        line 652: 0
      LocalVariableTable:
        Start  Length  Slot  Name   Signature
            0       5     0 $this   Lscala/util/matching/Regex$MatchData;
    MethodParameters:
      Name                           Flags
      $this                          final synthetic

  public default java.lang.String matched();
    descriptor: ()Ljava/lang/String;
    flags: (0x0001) ACC_PUBLIC
    Code:
      stack=3, locals=1, args_size=1
         0: aload_0
         1: invokeinterface #36,  1           // InterfaceMethod start:()I
         6: iconst_0
         7: if_icmplt     37
        10: aload_0
        11: invokeinterface #38,  1           // InterfaceMethod source:()Ljava/lang/CharSequence;
        16: aload_0
        17: invokeinterface #36,  1           // InterfaceMethod start:()I
        22: aload_0
        23: invokeinterface #40,  1           // InterfaceMethod end:()I
        28: invokeinterface #46,  3           // InterfaceMethod java/lang/CharSequence.subSequence:(II)Ljava/lang/CharSequence;
        33: invokevirtual #49                 // Method java/lang/Object.toString:()Ljava/lang/String;
        36: areturn
        37: aconst_null
        38: areturn
      StackMapTable: number_of_entries = 1
        frame_type = 37 /* same */
      LineNumberTable:
        line 653: 0
        line 654: 37
      LocalVariableTable:
        Start  Length  Slot  Name   Signature
            0      39     0  this   Lscala/util/matching/Regex$MatchData;

  public static java.lang.String group$(scala.util.matching.Regex$MatchData, int);
    descriptor: (Lscala/util/matching/Regex$MatchData;I)Ljava/lang/String;
    flags: (0x1009) ACC_PUBLIC, ACC_STATIC, ACC_SYNTHETIC
    Code:
      stack=2, locals=2, args_size=2
         0: aload_0
         1: iload_1
         2: invokespecial #56                 // InterfaceMethod group:(I)Ljava/lang/String;
         5: areturn
      LineNumberTable:
        line 659: 0
      LocalVariableTable:
        Start  Length  Slot  Name   Signature
            0       6     0 $this   Lscala/util/matching/Regex$MatchData;
            0       6     1     i   I
    MethodParameters:
      Name                           Flags
      $this                          final synthetic
      i                              final

  public default java.lang.String group(int);
    descriptor: (I)Ljava/lang/String;
    flags: (0x0001) ACC_PUBLIC
    Code:
      stack=4, locals=2, args_size=2
         0: aload_0
         1: iload_1
         2: invokeinterface #59,  2           // InterfaceMethod start:(I)I
         7: iconst_0
         8: if_icmplt     40
        11: aload_0
        12: invokeinterface #38,  1           // InterfaceMethod source:()Ljava/lang/CharSequence;
        17: aload_0
        18: iload_1
        19: invokeinterface #59,  2           // InterfaceMethod start:(I)I
        24: aload_0
        25: iload_1
        26: invokeinterface #61,  2           // InterfaceMethod end:(I)I
        31: invokeinterface #46,  3           // InterfaceMethod java/lang/CharSequence.subSequence:(II)Ljava/lang/CharSequence;
        36: invokevirtual #49                 // Method java/lang/Object.toString:()Ljava/lang/String;
        39: areturn
        40: aconst_null
        41: areturn
      StackMapTable: number_of_entries = 1
        frame_type = 40 /* same */
      LineNumberTable:
        line 660: 0
        line 661: 40
      LocalVariableTable:
        Start  Length  Slot  Name   Signature
            0      42     0  this   Lscala/util/matching/Regex$MatchData;
            0      42     1     i   I
    MethodParameters:
      Name                           Flags
      i                              final

  public static scala.collection.immutable.List subgroups$(scala.util.matching.Regex$MatchData);
    descriptor: (Lscala/util/matching/Regex$MatchData;)Lscala/collection/immutable/List;
    flags: (0x1009) ACC_PUBLIC, ACC_STATIC, ACC_SYNTHETIC
    Code:
      stack=1, locals=1, args_size=1
         0: aload_0
         1: invokespecial #67                 // InterfaceMethod subgroups:()Lscala/collection/immutable/List;
         4: areturn
      LineNumberTable:
        line 664: 0
      LocalVariableTable:
        Start  Length  Slot  Name   Signature
            0       5     0 $this   Lscala/util/matching/Regex$MatchData;
    MethodParameters:
      Name                           Flags
      $this                          final synthetic

  public default scala.collection.immutable.List<java.lang.String> subgroups();
    descriptor: ()Lscala/collection/immutable/List;
    flags: (0x0001) ACC_PUBLIC
    Code:
      stack=5, locals=10, args_size=1
         0: getstatic     #74                 // Field scala/runtime/RichInt$.MODULE$:Lscala/runtime/RichInt$;
         3: pop
         4: iconst_1
         5: istore_1
         6: aload_0
         7: invokeinterface #76,  1           // InterfaceMethod groupCount:()I
        12: istore        7
        14: getstatic     #81                 // Field scala/collection/immutable/Range$.MODULE$:Lscala/collection/immutable/Range$;
        17: pop
        18: new           #7                  // class scala/collection/immutable/Range$Inclusive
        21: dup
        22: iload_1
        23: iload         7
        25: iconst_1
        26: invokespecial #85                 // Method scala/collection/immutable/Range$Inclusive."<init>":(III)V
        29: invokestatic  #91                 // InterfaceMethod scala/collection/IterableOnceOps.toList$:(Lscala/collection/IterableOnceOps;)Lscala/collection/immutable/List;
        32: dup
        33: ifnonnull     38
        36: aconst_null
        37: athrow
        38: astore_2
        39: aload_2
        40: getstatic     #96                 // Field scala/collection/immutable/Nil$.MODULE$:Lscala/collection/immutable/Nil$;
        43: if_acmpne     50
        46: getstatic     #96                 // Field scala/collection/immutable/Nil$.MODULE$:Lscala/collection/immutable/Nil$;
        49: areturn
        50: new           #98                 // class scala/collection/immutable/$colon$colon
        53: dup
        54: aload_2
        55: invokevirtual #104                // Method scala/collection/immutable/List.head:()Ljava/lang/Object;
        58: invokestatic  #110                // Method scala/runtime/BoxesRunTime.unboxToInt:(Ljava/lang/Object;)I
        61: istore        8
        63: aload_0
        64: iload         8
        66: invokeinterface #56,  2           // InterfaceMethod group:(I)Ljava/lang/String;
        71: getstatic     #96                 // Field scala/collection/immutable/Nil$.MODULE$:Lscala/collection/immutable/Nil$;
        74: invokespecial #113                // Method scala/collection/immutable/$colon$colon."<init>":(Ljava/lang/Object;Lscala/collection/immutable/List;)V
        77: astore_3
        78: aload_3
        79: astore        4
        81: aload_2
        82: invokevirtual #116                // Method scala/collection/immutable/List.tail:()Ljava/lang/Object;
        85: checkcast     #100                // class scala/collection/immutable/List
        88: astore        5
        90: aload         5
        92: getstatic     #96                 // Field scala/collection/immutable/Nil$.MODULE$:Lscala/collection/immutable/Nil$;
        95: if_acmpeq     152
        98: new           #98                 // class scala/collection/immutable/$colon$colon
       101: dup
       102: aload         5
       104: invokevirtual #104                // Method scala/collection/immutable/List.head:()Ljava/lang/Object;
       107: invokestatic  #110                // Method scala/runtime/BoxesRunTime.unboxToInt:(Ljava/lang/Object;)I
       110: istore        9
       112: aload_0
       113: iload         9
       115: invokeinterface #56,  2           // InterfaceMethod group:(I)Ljava/lang/String;
       120: getstatic     #96                 // Field scala/collection/immutable/Nil$.MODULE$:Lscala/collection/immutable/Nil$;
       123: invokespecial #113                // Method scala/collection/immutable/$colon$colon."<init>":(Ljava/lang/Object;Lscala/collection/immutable/List;)V
       126: astore        6
       128: aload         4
       130: aload         6
       132: invokevirtual #120                // Method scala/collection/immutable/$colon$colon.next_$eq:(Lscala/collection/immutable/List;)V
       135: aload         6
       137: astore        4
       139: aload         5
       141: invokevirtual #116                // Method scala/collection/immutable/List.tail:()Ljava/lang/Object;
       144: checkcast     #100                // class scala/collection/immutable/List
       147: astore        5
       149: goto          90
       152: invokestatic  #126                // Method scala/runtime/Statics.releaseFence:()V
       155: aload_3
       156: areturn
      StackMapTable: number_of_entries = 4
        frame_type = 255 /* full_frame */
          offset_delta = 38
          locals = [ class scala/util/matching/Regex$MatchData, int, top, top, top, top, top, int ]
          stack = [ class scala/collection/immutable/List ]
        frame_type = 255 /* full_frame */
          offset_delta = 11
          locals = [ class scala/util/matching/Regex$MatchData, int, class scala/collection/immutable/List, top, top, top, top, int ]
          stack = []
        frame_type = 255 /* full_frame */
          offset_delta = 39
          locals = [ class scala/util/matching/Regex$MatchData, int, class scala/collection/immutable/List, class scala/collection/immutable/$colon$colon, class scala/collection/immutable/$colon$colon, class scala/collection/immutable/List, top, int, int ]
          stack = []
        frame_type = 61 /* same */
      LineNumberTable:
        line 664: 0
        line 664: 58
        line 664: 63
        line 664: 71
        line 664: 107
        line 664: 112
        line 664: 120
      LocalVariableTable:
        Start  Length  Slot  Name   Signature
            0     157     0  this   Lscala/util/matching/Regex$MatchData;
          128      21     6 map_nx   Lscala/collection/immutable/$colon$colon;
           78      78     3 map_h   Lscala/collection/immutable/$colon$colon;
           81      75     4 map_t   Lscala/collection/immutable/$colon$colon;
           90      66     5 map_rest   Lscala/collection/immutable/List;
           39     117     2 map_this   Lscala/collection/immutable/List;
           14      15     7 to$extension_end   I
           63       8     8 $anonfun$subgroups$1_i   I
          112       8     9 $anonfun$subgroups$1_i   I
    Signature: #68                          // ()Lscala/collection/immutable/List<Ljava/lang/String;>;

  public static java.lang.CharSequence before$(scala.util.matching.Regex$MatchData);
    descriptor: (Lscala/util/matching/Regex$MatchData;)Ljava/lang/CharSequence;
    flags: (0x1009) ACC_PUBLIC, ACC_STATIC, ACC_SYNTHETIC
    Code:
      stack=1, locals=1, args_size=1
         0: aload_0
         1: invokespecial #140                // InterfaceMethod before:()Ljava/lang/CharSequence;
         4: areturn
      LineNumberTable:
        line 669: 0
      LocalVariableTable:
        Start  Length  Slot  Name   Signature
            0       5     0 $this   Lscala/util/matching/Regex$MatchData;
    MethodParameters:
      Name                           Flags
      $this                          final synthetic

  public default java.lang.CharSequence before();
    descriptor: ()Ljava/lang/CharSequence;
    flags: (0x0001) ACC_PUBLIC
    Code:
      stack=3, locals=1, args_size=1
         0: aload_0
         1: invokeinterface #36,  1           // InterfaceMethod start:()I
         6: iconst_0
         7: if_icmplt     29
        10: aload_0
        11: invokeinterface #38,  1           // InterfaceMethod source:()Ljava/lang/CharSequence;
        16: iconst_0
        17: aload_0
        18: invokeinterface #36,  1           // InterfaceMethod start:()I
        23: invokeinterface #46,  3           // InterfaceMethod java/lang/CharSequence.subSequence:(II)Ljava/lang/CharSequence;
        28: areturn
        29: aconst_null
        30: areturn
      StackMapTable: number_of_entries = 1
        frame_type = 29 /* same */
      LineNumberTable:
        line 670: 0
        line 671: 29
      LocalVariableTable:
        Start  Length  Slot  Name   Signature
            0      31     0  this   Lscala/util/matching/Regex$MatchData;

  public static java.lang.CharSequence before$(scala.util.matching.Regex$MatchData, int);
    descriptor: (Lscala/util/matching/Regex$MatchData;I)Ljava/lang/CharSequence;
    flags: (0x1009) ACC_PUBLIC, ACC_STATIC, ACC_SYNTHETIC
    Code:
      stack=2, locals=2, args_size=2
         0: aload_0
         1: iload_1
         2: invokespecial #144                // InterfaceMethod before:(I)Ljava/lang/CharSequence;
         5: areturn
      LineNumberTable:
        line 676: 0
      LocalVariableTable:
        Start  Length  Slot  Name   Signature
            0       6     0 $this   Lscala/util/matching/Regex$MatchData;
            0       6     1     i   I
    MethodParameters:
      Name                           Flags
      $this                          final synthetic
      i                              final

  public default java.lang.CharSequence before(int);
    descriptor: (I)Ljava/lang/CharSequence;
    flags: (0x0001) ACC_PUBLIC
    Code:
      stack=4, locals=2, args_size=2
         0: aload_0
         1: iload_1
         2: invokeinterface #59,  2           // InterfaceMethod start:(I)I
         7: iconst_0
         8: if_icmplt     31
        11: aload_0
        12: invokeinterface #38,  1           // InterfaceMethod source:()Ljava/lang/CharSequence;
        17: iconst_0
        18: aload_0
        19: iload_1
        20: invokeinterface #59,  2           // InterfaceMethod start:(I)I
        25: invokeinterface #46,  3           // InterfaceMethod java/lang/CharSequence.subSequence:(II)Ljava/lang/CharSequence;
        30: areturn
        31: aconst_null
        32: areturn
      StackMapTable: number_of_entries = 1
        frame_type = 31 /* same */
      LineNumberTable:
        line 677: 0
        line 678: 31
      LocalVariableTable:
        Start  Length  Slot  Name   Signature
            0      33     0  this   Lscala/util/matching/Regex$MatchData;
            0      33     1     i   I
    MethodParameters:
      Name                           Flags
      i                              final

  public static java.lang.CharSequence after$(scala.util.matching.Regex$MatchData);
    descriptor: (Lscala/util/matching/Regex$MatchData;)Ljava/lang/CharSequence;
    flags: (0x1009) ACC_PUBLIC, ACC_STATIC, ACC_SYNTHETIC
    Code:
      stack=1, locals=1, args_size=1
         0: aload_0
         1: invokespecial #148                // InterfaceMethod after:()Ljava/lang/CharSequence;
         4: areturn
      LineNumberTable:
        line 683: 0
      LocalVariableTable:
        Start  Length  Slot  Name   Signature
            0       5     0 $this   Lscala/util/matching/Regex$MatchData;
    MethodParameters:
      Name                           Flags
      $this                          final synthetic

  public default java.lang.CharSequence after();
    descriptor: ()Ljava/lang/CharSequence;
    flags: (0x0001) ACC_PUBLIC
    Code:
      stack=3, locals=1, args_size=1
         0: aload_0
         1: invokeinterface #40,  1           // InterfaceMethod end:()I
         6: iconst_0
         7: if_icmplt     39
        10: aload_0
        11: invokeinterface #38,  1           // InterfaceMethod source:()Ljava/lang/CharSequence;
        16: aload_0
        17: invokeinterface #40,  1           // InterfaceMethod end:()I
        22: aload_0
        23: invokeinterface #38,  1           // InterfaceMethod source:()Ljava/lang/CharSequence;
        28: invokeinterface #151,  1          // InterfaceMethod java/lang/CharSequence.length:()I
        33: invokeinterface #46,  3           // InterfaceMethod java/lang/CharSequence.subSequence:(II)Ljava/lang/CharSequence;
        38: areturn
        39: aconst_null
        40: areturn
      StackMapTable: number_of_entries = 1
        frame_type = 39 /* same */
      LineNumberTable:
        line 684: 0
        line 685: 39
      LocalVariableTable:
        Start  Length  Slot  Name   Signature
            0      41     0  this   Lscala/util/matching/Regex$MatchData;

  public static java.lang.CharSequence after$(scala.util.matching.Regex$MatchData, int);
    descriptor: (Lscala/util/matching/Regex$MatchData;I)Ljava/lang/CharSequence;
    flags: (0x1009) ACC_PUBLIC, ACC_STATIC, ACC_SYNTHETIC
    Code:
      stack=2, locals=2, args_size=2
         0: aload_0
         1: iload_1
         2: invokespecial #153                // InterfaceMethod after:(I)Ljava/lang/CharSequence;
         5: areturn
      LineNumberTable:
        line 690: 0
      LocalVariableTable:
        Start  Length  Slot  Name   Signature
            0       6     0 $this   Lscala/util/matching/Regex$MatchData;
            0       6     1     i   I
    MethodParameters:
      Name                           Flags
      $this                          final synthetic
      i                              final

  public default java.lang.CharSequence after(int);
    descriptor: (I)Ljava/lang/CharSequence;
    flags: (0x0001) ACC_PUBLIC
    Code:
      stack=3, locals=2, args_size=2
         0: aload_0
         1: iload_1
         2: invokeinterface #61,  2           // InterfaceMethod end:(I)I
         7: iconst_0
         8: if_icmplt     41
        11: aload_0
        12: invokeinterface #38,  1           // InterfaceMethod source:()Ljava/lang/CharSequence;
        17: aload_0
        18: iload_1
        19: invokeinterface #61,  2           // InterfaceMethod end:(I)I
        24: aload_0
        25: invokeinterface #38,  1           // InterfaceMethod source:()Ljava/lang/CharSequence;
        30: invokeinterface #151,  1          // InterfaceMethod java/lang/CharSequence.length:()I
        35: invokeinterface #46,  3           // InterfaceMethod java/lang/CharSequence.subSequence:(II)Ljava/lang/CharSequence;
        40: areturn
        41: aconst_null
        42: areturn
      StackMapTable: number_of_entries = 1
        frame_type = 41 /* same */
      LineNumberTable:
        line 691: 0
        line 692: 41
      LocalVariableTable:
        Start  Length  Slot  Name   Signature
            0      43     0  this   Lscala/util/matching/Regex$MatchData;
            0      43     1     i   I
    MethodParameters:
      Name                           Flags
      i                              final

  private scala.collection.immutable.Seq<java.lang.String> groupNamesNowarn();
    descriptor: ()Lscala/collection/immutable/Seq;
    flags: (0x0002) ACC_PRIVATE
    Code:
      stack=1, locals=1, args_size=1
         0: aload_0
         1: invokeinterface #156,  1          // InterfaceMethod groupNames:()Lscala/collection/immutable/Seq;
         6: areturn
      LineNumberTable:
        line 695: 0
      LocalVariableTable:
        Start  Length  Slot  Name   Signature
            0       7     0  this   Lscala/util/matching/Regex$MatchData;
    Signature: #20                          // ()Lscala/collection/immutable/Seq<Ljava/lang/String;>;

  public static scala.collection.immutable.Map scala$util$matching$Regex$MatchData$$nameToIndex$(scala.util.matching.Regex$MatchData);
    descriptor: (Lscala/util/matching/Regex$MatchData;)Lscala/collection/immutable/Map;
    flags: (0x1009) ACC_PUBLIC, ACC_STATIC, ACC_SYNTHETIC
    Code:
      stack=1, locals=1, args_size=1
         0: aload_0
         1: invokespecial #162                // InterfaceMethod scala$util$matching$Regex$MatchData$$nameToIndex:()Lscala/collection/immutable/Map;
         4: areturn
      LineNumberTable:
        line 697: 0
      LocalVariableTable:
        Start  Length  Slot  Name   Signature
            0       5     0 $this   Lscala/util/matching/Regex$MatchData;
    MethodParameters:
      Name                           Flags
      $this                          final synthetic

  public default scala.collection.immutable.Map<java.lang.String, java.lang.Object> scala$util$matching$Regex$MatchData$$nameToIndex();
    descriptor: ()Lscala/collection/immutable/Map;
    flags: (0x0001) ACC_PUBLIC
    Code:
      stack=5, locals=4, args_size=1
         0: getstatic     #168                // Field scala/Predef$.MODULE$:Lscala/Predef$;
         3: invokevirtual #172                // Method scala/Predef$.Map:()Lscala/collection/immutable/Map$;
         6: getstatic     #96                 // Field scala/collection/immutable/Nil$.MODULE$:Lscala/collection/immutable/Nil$;
         9: astore_1
        10: dup
        11: ifnonnull     16
        14: aconst_null
        15: athrow
        16: aload_1
        17: invokevirtual #178                // Method scala/collection/immutable/Map$.from:(Lscala/collection/IterableOnce;)Lscala/collection/immutable/Map;
        20: aconst_null
        21: astore_1
        22: aload_0
        23: invokeinterface #156,  1          // InterfaceMethod groupNames:()Lscala/collection/immutable/Seq;
        28: invokeinterface #183,  1          // InterfaceMethod scala/collection/immutable/Seq.toList:()Lscala/collection/immutable/List;
        33: ldc           #185                // String
        35: astore_3
        36: dup
        37: ifnonnull     42
        40: aconst_null
        41: athrow
        42: astore_2
        43: new           #98                 // class scala/collection/immutable/$colon$colon
        46: dup
        47: aload_3
        48: aload_2
        49: invokespecial #113                // Method scala/collection/immutable/$colon$colon."<init>":(Ljava/lang/Object;Lscala/collection/immutable/List;)V
        52: aconst_null
        53: astore_2
        54: aconst_null
        55: astore_3
        56: invokestatic  #191                // InterfaceMethod scala/collection/StrictOptimizedIterableOps.zipWithIndex$:(Lscala/collection/StrictOptimizedIterableOps;)Ljava/lang/Object;
        59: checkcast     #193                // class scala/collection/IterableOnce
        62: invokeinterface #199,  2          // InterfaceMethod scala/collection/MapOps.$plus$plus:(Lscala/collection/IterableOnce;)Lscala/collection/IterableOps;
        67: checkcast     #201                // class scala/collection/immutable/Map
        70: areturn
      StackMapTable: number_of_entries = 2
        frame_type = 255 /* full_frame */
          offset_delta = 16
          locals = [ class scala/util/matching/Regex$MatchData, class scala/collection/immutable/Nil$ ]
          stack = [ class scala/collection/immutable/Map$ ]
        frame_type = 255 /* full_frame */
          offset_delta = 25
          locals = [ class scala/util/matching/Regex$MatchData, null, top, class java/lang/String ]
          stack = [ class scala/collection/immutable/Map, class scala/collection/immutable/List ]
      LineNumberTable:
        line 698: 0
        line 695: 22
        line 698: 28
      LocalVariableTable:
        Start  Length  Slot  Name   Signature
            0      71     0  this   Lscala/util/matching/Regex$MatchData;
           16       4     1 apply_elems   Lscala/collection/immutable/Seq;
           43       9     2 $colon$colon_this   Lscala/collection/immutable/List;
           43       9     3 $colon$colon_elem   Ljava/lang/Object;
    Signature: #163                         // ()Lscala/collection/immutable/Map<Ljava/lang/String;Ljava/lang/Object;>;

  public static java.lang.String group$(scala.util.matching.Regex$MatchData, java.lang.String);
    descriptor: (Lscala/util/matching/Regex$MatchData;Ljava/lang/String;)Ljava/lang/String;
    flags: (0x1009) ACC_PUBLIC, ACC_STATIC, ACC_SYNTHETIC
    Code:
      stack=2, locals=2, args_size=2
         0: aload_0
         1: aload_1
         2: invokespecial #213                // InterfaceMethod group:(Ljava/lang/String;)Ljava/lang/String;
         5: areturn
      LineNumberTable:
        line 710: 0
      LocalVariableTable:
        Start  Length  Slot  Name   Signature
            0       6     0 $this   Lscala/util/matching/Regex$MatchData;
            0       6     1    id   Ljava/lang/String;
    MethodParameters:
      Name                           Flags
      $this                          final synthetic
      id                             final

  public default java.lang.String group(java.lang.String);
    descriptor: (Ljava/lang/String;)Ljava/lang/String;
    flags: (0x0001) ACC_PUBLIC
    Code:
      stack=3, locals=5, args_size=2
         0: aload_0
         1: invokeinterface #156,  1          // InterfaceMethod groupNames:()Lscala/collection/immutable/Seq;
         6: invokeinterface #218,  1          // InterfaceMethod scala/collection/immutable/Seq.isEmpty:()Z
        11: ifeq          25
        14: aload_0
        15: invokeinterface #220,  1          // InterfaceMethod matcher:()Ljava/util/regex/Matcher;
        20: aload_1
        21: invokevirtual #223                // Method java/util/regex/Matcher.group:(Ljava/lang/String;)Ljava/lang/String;
        24: areturn
        25: aload_0
        26: invokeinterface #162,  1          // InterfaceMethod scala$util$matching$Regex$MatchData$$nameToIndex:()Lscala/collection/immutable/Map;
        31: aload_1
        32: invokeinterface #227,  2          // InterfaceMethod scala/collection/immutable/Map.get:(Ljava/lang/Object;)Lscala/Option;
        37: astore_3
        38: aload_3
        39: instanceof    #229                // class scala/Some
        42: ifeq          69
        45: aload_3
        46: checkcast     #229                // class scala/Some
        49: invokevirtual #232                // Method scala/Some.value:()Ljava/lang/Object;
        52: invokestatic  #110                // Method scala/runtime/BoxesRunTime.unboxToInt:(Ljava/lang/Object;)I
        55: istore        4
        57: aload_0
        58: iload         4
        60: invokeinterface #56,  2           // InterfaceMethod group:(I)Ljava/lang/String;
        65: astore_2
        66: goto          102
        69: getstatic     #237                // Field scala/None$.MODULE$:Lscala/None$;
        72: aload_3
        73: invokevirtual #241                // Method java/lang/Object.equals:(Ljava/lang/Object;)Z
        76: ifeq          93
        79: aload_0
        80: invokeinterface #220,  1          // InterfaceMethod matcher:()Ljava/util/regex/Matcher;
        85: aload_1
        86: invokevirtual #223                // Method java/util/regex/Matcher.group:(Ljava/lang/String;)Ljava/lang/String;
        89: astore_2
        90: goto          102
        93: new           #243                // class scala/MatchError
        96: dup
        97: aload_3
        98: invokespecial #246                // Method scala/MatchError."<init>":(Ljava/lang/Object;)V
       101: athrow
       102: aload_2
       103: areturn
      StackMapTable: number_of_entries = 4
        frame_type = 25 /* same */
        frame_type = 253 /* append */
          offset_delta = 43
          locals = [ top, class scala/Option ]
        frame_type = 23 /* same */
        frame_type = 255 /* full_frame */
          offset_delta = 8
          locals = [ class scala/util/matching/Regex$MatchData, class java/lang/String, class java/lang/String, class scala/Option ]
          stack = []
      LineNumberTable:
        line 695: 0
        line 711: 6
        line 712: 14
        line 714: 25
        line 715: 38
        line 716: 69
        line 714: 93
      LocalVariableTable:
        Start  Length  Slot  Name   Signature
           57      12     4 index   I
            0     104     0  this   Lscala/util/matching/Regex$MatchData;
            0     104     1    id   Ljava/lang/String;
    MethodParameters:
      Name                           Flags
      id                             final

  public static java.lang.String toString$(scala.util.matching.Regex$MatchData);
    descriptor: (Lscala/util/matching/Regex$MatchData;)Ljava/lang/String;
    flags: (0x1009) ACC_PUBLIC, ACC_STATIC, ACC_SYNTHETIC
    Code:
      stack=1, locals=1, args_size=1
         0: aload_0
         1: invokespecial #251                // InterfaceMethod toString:()Ljava/lang/String;
         4: areturn
      LineNumberTable:
        line 721: 0
      LocalVariableTable:
        Start  Length  Slot  Name   Signature
            0       5     0 $this   Lscala/util/matching/Regex$MatchData;
    MethodParameters:
      Name                           Flags
      $this                          final synthetic

  public default java.lang.String toString();
    descriptor: ()Ljava/lang/String;
    flags: (0x0001) ACC_PUBLIC
    Code:
      stack=1, locals=1, args_size=1
         0: aload_0
         1: invokeinterface #33,  1           // InterfaceMethod matched:()Ljava/lang/String;
         6: areturn
      LineNumberTable:
        line 721: 0
      LocalVariableTable:
        Start  Length  Slot  Name   Signature
            0       7     0  this   Lscala/util/matching/Regex$MatchData;

  public static java.lang.String $anonfun$subgroups$1(scala.util.matching.Regex$MatchData, int);
    descriptor: (Lscala/util/matching/Regex$MatchData;I)Ljava/lang/String;
    flags: (0x1009) ACC_PUBLIC, ACC_STATIC, ACC_SYNTHETIC
    Code:
      stack=2, locals=2, args_size=2
         0: aload_0
         1: iload_1
         2: invokeinterface #56,  2           // InterfaceMethod group:(I)Ljava/lang/String;
         7: areturn
      LineNumberTable:
        line 664: 0
      LocalVariableTable:
        Start  Length  Slot  Name   Signature
            0       8     0 $this   Lscala/util/matching/Regex$MatchData;
            0       8     1     i   I
    MethodParameters:
      Name                           Flags
      $this                          final synthetic
      i                              final

  public static void $init$(scala.util.matching.Regex$MatchData);
    descriptor: (Lscala/util/matching/Regex$MatchData;)V
    flags: (0x0009) ACC_PUBLIC, ACC_STATIC
    Code:
      stack=0, locals=1, args_size=1
         0: return
      LineNumberTable:
        line 618: 0
      LocalVariableTable:
        Start  Length  Slot  Name   Signature
            0       1     0 $this   Lscala/util/matching/Regex$MatchData;
    MethodParameters:
      Name                           Flags
      $this                          final synthetic

  public static java.lang.String $anonfun$subgroups$1$adapted(scala.util.matching.Regex$MatchData, java.lang.Object);
    descriptor: (Lscala/util/matching/Regex$MatchData;Ljava/lang/Object;)Ljava/lang/String;
    flags: (0x1009) ACC_PUBLIC, ACC_STATIC, ACC_SYNTHETIC
    Code:
      stack=2, locals=2, args_size=2
         0: aload_0
         1: aload_1
         2: invokestatic  #110                // Method scala/runtime/BoxesRunTime.unboxToInt:(Ljava/lang/Object;)I
         5: invokestatic  #258                // InterfaceMethod $anonfun$subgroups$1:(Lscala/util/matching/Regex$MatchData;I)Ljava/lang/String;
         8: areturn
      LineNumberTable:
        line 664: 0
      LocalVariableTable:
        Start  Length  Slot  Name   Signature
            0       9     0 $this   Lscala/util/matching/Regex$MatchData;
            0       9     1     i   Ljava/lang/Object;
    MethodParameters:
      Name                           Flags
      $this                          final
      i                              final
}
InnerClasses:
  public static final #10= #7 of #9;      // Inclusive=class scala/collection/immutable/Range$Inclusive of class scala/collection/immutable/Range
  public static #13= #2 of #12;           // MatchData=class scala/util/matching/Regex$MatchData of class scala/util/matching/Regex
SourceFile: "Regex.scala"
  ScalaInlineInfo: length = 0xA4 (unknown attribute)
   01 00 00 20 00 FC 00 34 01 00 FF 01 00 01 00 FD
   00 FE 01 00 92 00 11 00 00 92 00 8E 00 00 91 00
   89 01 00 91 00 8D 01 00 8A 00 11 00 00 8A 00 8E
   00 00 88 00 89 01 00 88 00 8D 01 00 1A 00 16 00
   00 1A 00 18 00 00 35 00 36 00 00 35 00 D3 00 00
   33 00 34 01 00 33 00 D1 01 00 15 00 16 00 00 12
   00 13 00 00 9A 00 13 01 00 1E 00 1F 00 00 1B 00
   1C 01 00 0E 00 0F 00 00 9F 00 A0 00 00 9D 00 9E
   01 00 10 00 11 00 00 17 00 16 00 00 17 00 18 00
   00 40 00 41 00 00 3E 00 3F 01 00 2F 00 1F 00 00
   FA 00 1C 01
  Scala: length = 0x0 (unknown attribute)

