Classfile /Users/mw/Projects/slang-braindump/.jar/jar8/assemble/slang-braindump/assemble/content/org/scalatest/exceptions/PropertyCheckFailedException.class
  Last modified May 29, 2022; size 8645 bytes
  SHA-256 checksum d6d2514f2aeab4c41c326c68b1460787f3dc9beba3afd02cb64c50a8f06831bb
  Compiled from "PropertyCheckFailedException.scala"
public abstract class org.scalatest.exceptions.PropertyCheckFailedException extends org.scalatest.exceptions.TestFailedException
  minor version: 0
  major version: 52
  flags: (0x0421) ACC_PUBLIC, ACC_SUPER, ACC_ABSTRACT
  this_class: #2                          // org/scalatest/exceptions/PropertyCheckFailedException
  super_class: #4                         // org/scalatest/exceptions/TestFailedException
  interfaces: 0, fields: 3, methods: 8, attributes: 6
Constant pool:
    #1 = Utf8               org/scalatest/exceptions/PropertyCheckFailedException
    #2 = Class              #1            // org/scalatest/exceptions/PropertyCheckFailedException
    #3 = Utf8               org/scalatest/exceptions/TestFailedException
    #4 = Class              #3            // org/scalatest/exceptions/TestFailedException
    #5 = Utf8               PropertyCheckFailedException.scala
    #6 = Utf8               Lscala/reflect/ScalaSignature;
    #7 = Utf8               bytes
    #8 = Utf8               \u0006\u0005Q4Q!\u0004\b\u0002\u0002UA\u0001B\u0007\u0001\u0003\u0002\u0003\u0006Ia\u0007\u0005\n_\u0001\u0011\t\u0011)A\u0005aqB\u0001\"\u0010\u0001\u0003\u0002\u0003\u0006IA\u0010\u0005\n\u001b\u0002\u0011\t\u0011)A\u0005\u001dJC\u0001b\u0015\u0001\u0003\u0006\u0004%\t\u0001\u0016\u0005\t+\u0002\u0011\t\u0011)A\u0005I!Aa\u000b\u0001BC\u0002\u0013\u0005q\u000b\u0003\u0005\\\u0001\t\u0005\t\u0015!\u0003Y\u0011!a\u0006A!A!\u0002\u0013i\u0006\"B0\u0001\t\u0003\u0001\u0007\"B0\u0001\t\u0003I\u0007\"\u0002:\u0001\t\u0003\u0019(\u0001\b)s_B,\'\u000f^=DQ\u0016\u001c7NR1jY\u0016$W\t_2faRLwN\u001c\u0006\u0003\u001fA\t!\"\u001a=dKB$\u0018n\u001c8t\u0015\t\t\"#A\u0005tG\u0006d\u0017\r^3ti*\t1#A\u0002pe\u001e\u001c\u0001a\u0005\u0002\u0001-A\u0011q\u0003G\u0007\u0002\u001d%\u0011\u0011D\u0004\u0002\u0014)\u0016\u001cHOR1jY\u0016$W\t_2faRLwN\\\u0001\u000b[\u0016\u001c8/Y4f\rVt\u0007\u0003\u0002\u000f C\u0011j\u0011!\b\u0006\u0002=\u0005)1oY1mC&\u0011\u0001%\b\u0002\n\rVt7\r^5p]F\u0002\"a\u0006\u0012\n\u0005\rr!aE*uC\u000e\\G)\u001a9uQ\u0016C8-\u001a9uS>t\u0007CA\u0013-\u001d\t1#\u0006\u0005\u0002(;5\t\u0001F\u0003\u0002*)\u00051AH]8pizJ!aK\u000f\u0002\rA\u0013X\rZ3g\u0013\ticF\u0001\u0004TiJLgn\u001a\u0006\u0003Wu\tQaY1vg\u0016\u00042\u0001H\u00194\u0013\t\u0011TD\u0001\u0004PaRLwN\u001c\t\u0003ier!!N\u001c\u000f\u0005\u001d2\u0014\"\u0001\u0010\n\u0005aj\u0012a\u00029bG.\fw-Z\u0005\u0003um\u0012\u0011\u0002\u00165s_^\f\'\r\\3\u000b\u0005aj\u0012BA\u0018#\u0003I\u0001xn](s\'R\f7m\u001b#faRDg)\u001e8\u0011\tQz\u0014)S\u0005\u0003\u0001n\u0012a!R5uQ\u0016\u0014\bC\u0001\"H\u001b\u0005\u0019%B\u0001#F\u0003\u0019\u0019x.\u001e:dK*\u0011aIE\u0001\ng\u000e\fG.Y2uS\u000eL!\u0001S\"\u0003\u0011A{7/\u001b;j_:\u0004B\u0001H\u0010\"\u0015B\u0011AdS\u0005\u0003\u0019v\u00111!\u00138u\u0003\u001d\u0001\u0018-\u001f7pC\u0012\u00042\u0001H\u0019P!\ta\u0002+\u0003\u0002R;\t\u0019\u0011I\\=\n\u00055C\u0012AE;oI\u0016\u001cwN]1uK\u0012lUm]:bO\u0016,\u0012\u0001J\u0001\u0014k:$WmY8sCR,G-T3tg\u0006<W\rI\u0001\u0005CJ<7/F\u0001Y!\r!\u0014lT\u0005\u00035n\u0012A\u0001T5ti\u0006)\u0011M]4tA\u0005\u0001r\u000e\u001d;j_:\fG.\u0011:h\u001d\u0006lWm\u001d\t\u00049Er\u0006c\u0001\u001bZI\u00051A(\u001b8jiz\"\u0002\"\u00192dI\u00164w\r\u001b\t\u0003/\u0001AQA\u0007\u0006A\u0002mAQa\f\u0006A\u0002ABQ!\u0010\u0006A\u0002yBQ!\u0014\u0006A\u00029CQa\u0015\u0006A\u0002\u0011BQA\u0016\u0006A\u0002aCQ\u0001\u0018\u0006A\u0002u#\u0002\"\u00196lY:|\u0007/\u001d\u0005\u00065-\u0001\ra\u0007\u0005\u0006_-\u0001\r\u0001\r\u0005\u0006[.\u0001\r!S\u0001\u0018M\u0006LG.\u001a3D_\u0012,7\u000b^1dW\u0012+\u0007\u000f\u001e5Gk:DQ!T\u0006A\u00029CQaU\u0006A\u0002\u0011BQAV\u0006A\u0002aCQ\u0001X\u0006A\u0002u\u000b\u0001\"\u0019:h\u001d\u0006lWm]\u000b\u0002=\u0002
    #9 = Utf8               java/lang/invoke/MethodHandles$Lookup
   #10 = Class              #9            // java/lang/invoke/MethodHandles$Lookup
   #11 = Utf8               java/lang/invoke/MethodHandles
   #12 = Class              #11           // java/lang/invoke/MethodHandles
   #13 = Utf8               Lookup
   #14 = Utf8               org/scalactic/Requirements$RequirementsHelper
   #15 = Class              #14           // org/scalactic/Requirements$RequirementsHelper
   #16 = Utf8               org/scalactic/Requirements
   #17 = Class              #16           // org/scalactic/Requirements
   #18 = Utf8               RequirementsHelper
   #19 = Utf8               org/scalatest/exceptions/PropertyCheckFailedException$$anonfun$$lessinit$greater$1
   #20 = Class              #19           // org/scalatest/exceptions/PropertyCheckFailedException$$anonfun$$lessinit$greater$1
   #21 = Utf8               undecoratedMessage
   #22 = Utf8               Ljava/lang/String;
   #23 = Utf8               args
   #24 = Utf8               Lscala/collection/immutable/List;
   #25 = Utf8               Lscala/collection/immutable/List<Ljava/lang/Object;>;
   #26 = Utf8               optionalArgNames
   #27 = Utf8               Lscala/Option;
   #28 = Utf8               Lscala/Option<Lscala/collection/immutable/List<Ljava/lang/String;>;>;
   #29 = Utf8               ()Ljava/lang/String;
   #30 = NameAndType        #21:#22       // undecoratedMessage:Ljava/lang/String;
   #31 = Fieldref           #2.#30        // org/scalatest/exceptions/PropertyCheckFailedException.undecoratedMessage:Ljava/lang/String;
   #32 = Utf8               this
   #33 = Utf8               Lorg/scalatest/exceptions/PropertyCheckFailedException;
   #34 = Utf8               ()Lscala/collection/immutable/List;
   #35 = Utf8               ()Lscala/collection/immutable/List<Ljava/lang/Object;>;
   #36 = NameAndType        #23:#24       // args:Lscala/collection/immutable/List;
   #37 = Fieldref           #2.#36        // org/scalatest/exceptions/PropertyCheckFailedException.args:Lscala/collection/immutable/List;
   #38 = Utf8               argNames
   #39 = Utf8               ()Lscala/collection/immutable/List<Ljava/lang/String;>;
   #40 = NameAndType        #26:#27       // optionalArgNames:Lscala/Option;
   #41 = Fieldref           #2.#40        // org/scalatest/exceptions/PropertyCheckFailedException.optionalArgNames:Lscala/Option;
   #42 = Utf8               scala/Some
   #43 = Class              #42           // scala/Some
   #44 = Utf8               value
   #45 = Utf8               ()Ljava/lang/Object;
   #46 = NameAndType        #44:#45       // value:()Ljava/lang/Object;
   #47 = Methodref          #43.#46       // scala/Some.value:()Ljava/lang/Object;
   #48 = Utf8               scala/collection/immutable/List
   #49 = Class              #48           // scala/collection/immutable/List
   #50 = Utf8               scala/None$
   #51 = Class              #50           // scala/None$
   #52 = Utf8               MODULE$
   #53 = Utf8               Lscala/None$;
   #54 = NameAndType        #52:#53       // MODULE$:Lscala/None$;
   #55 = Fieldref           #51.#54       // scala/None$.MODULE$:Lscala/None$;
   #56 = Utf8               java/lang/Object
   #57 = Class              #56           // java/lang/Object
   #58 = Utf8               equals
   #59 = Utf8               (Ljava/lang/Object;)Z
   #60 = NameAndType        #58:#59       // equals:(Ljava/lang/Object;)Z
   #61 = Methodref          #57.#60       // java/lang/Object.equals:(Ljava/lang/Object;)Z
   #62 = Utf8               scala/runtime/RichInt$
   #63 = Class              #62           // scala/runtime/RichInt$
   #64 = Utf8               Lscala/runtime/RichInt$;
   #65 = NameAndType        #52:#64       // MODULE$:Lscala/runtime/RichInt$;
   #66 = Fieldref           #63.#65       // scala/runtime/RichInt$.MODULE$:Lscala/runtime/RichInt$;
   #67 = Utf8               scala/Predef$
   #68 = Class              #67           // scala/Predef$
   #69 = Utf8               Lscala/Predef$;
   #70 = NameAndType        #52:#69       // MODULE$:Lscala/Predef$;
   #71 = Fieldref           #68.#70       // scala/Predef$.MODULE$:Lscala/Predef$;
   #72 = Utf8               intWrapper
   #73 = Utf8               (I)I
   #74 = NameAndType        #72:#73       // intWrapper:(I)I
   #75 = Methodref          #68.#74       // scala/Predef$.intWrapper:(I)I
   #76 = NameAndType        #23:#34       // args:()Lscala/collection/immutable/List;
   #77 = Methodref          #2.#76        // org/scalatest/exceptions/PropertyCheckFailedException.args:()Lscala/collection/immutable/List;
   #78 = Utf8               length
   #79 = Utf8               ()I
   #80 = NameAndType        #78:#79       // length:()I
   #81 = Methodref          #49.#80       // scala/collection/immutable/List.length:()I
   #82 = Utf8               until$extension
   #83 = Utf8               (II)Lscala/collection/immutable/Range;
   #84 = NameAndType        #82:#83       // until$extension:(II)Lscala/collection/immutable/Range;
   #85 = Methodref          #63.#84       // scala/runtime/RichInt$.until$extension:(II)Lscala/collection/immutable/Range;
   #86 = Utf8               (Ljava/lang/Object;)Ljava/lang/Object;
   #87 = MethodType         #86           //  (Ljava/lang/Object;)Ljava/lang/Object;
   #88 = Utf8               $anonfun$argNames$1$adapted
   #89 = Utf8               (Ljava/lang/Object;)Ljava/lang/String;
   #90 = NameAndType        #88:#89       // $anonfun$argNames$1$adapted:(Ljava/lang/Object;)Ljava/lang/String;
   #91 = Methodref          #2.#90        // org/scalatest/exceptions/PropertyCheckFailedException.$anonfun$argNames$1$adapted:(Ljava/lang/Object;)Ljava/lang/String;
   #92 = MethodHandle       6:#91         // REF_invokeStatic org/scalatest/exceptions/PropertyCheckFailedException.$anonfun$argNames$1$adapted:(Ljava/lang/Object;)Ljava/lang/String;
   #93 = MethodType         #89           //  (Ljava/lang/Object;)Ljava/lang/String;
   #94 = Integer            5
   #95 = Integer            1
   #96 = Utf8               java/lang/invoke/LambdaMetafactory
   #97 = Class              #96           // java/lang/invoke/LambdaMetafactory
   #98 = Utf8               altMetafactory
   #99 = Utf8               (Ljava/lang/invoke/MethodHandles$Lookup;Ljava/lang/String;Ljava/lang/invoke/MethodType;[Ljava/lang/Object;)Ljava/lang/invoke/CallSite;
  #100 = NameAndType        #98:#99       // altMetafactory:(Ljava/lang/invoke/MethodHandles$Lookup;Ljava/lang/String;Ljava/lang/invoke/MethodType;[Ljava/lang/Object;)Ljava/lang/invoke/CallSite;
  #101 = Methodref          #97.#100      // java/lang/invoke/LambdaMetafactory.altMetafactory:(Ljava/lang/invoke/MethodHandles$Lookup;Ljava/lang/String;Ljava/lang/invoke/MethodType;[Ljava/lang/Object;)Ljava/lang/invoke/CallSite;
  #102 = MethodHandle       6:#101        // REF_invokeStatic java/lang/invoke/LambdaMetafactory.altMetafactory:(Ljava/lang/invoke/MethodHandles$Lookup;Ljava/lang/String;Ljava/lang/invoke/MethodType;[Ljava/lang/Object;)Ljava/lang/invoke/CallSite;
  #103 = Utf8               apply
  #104 = Utf8               ()Lscala/Function1;
  #105 = NameAndType        #103:#104     // apply:()Lscala/Function1;
  #106 = InvokeDynamic      #0:#105       // #0:apply:()Lscala/Function1;
  #107 = Utf8               scala/collection/immutable/Range
  #108 = Class              #107          // scala/collection/immutable/Range
  #109 = Utf8               map
  #110 = Utf8               (Lscala/Function1;)Lscala/collection/immutable/IndexedSeq;
  #111 = NameAndType        #109:#110     // map:(Lscala/Function1;)Lscala/collection/immutable/IndexedSeq;
  #112 = Methodref          #108.#111     // scala/collection/immutable/Range.map:(Lscala/Function1;)Lscala/collection/immutable/IndexedSeq;
  #113 = Utf8               scala/collection/immutable/IndexedSeq
  #114 = Class              #113          // scala/collection/immutable/IndexedSeq
  #115 = Utf8               toList
  #116 = NameAndType        #115:#34      // toList:()Lscala/collection/immutable/List;
  #117 = InterfaceMethodref #114.#116     // scala/collection/immutable/IndexedSeq.toList:()Lscala/collection/immutable/List;
  #118 = Utf8               scala/MatchError
  #119 = Class              #118          // scala/MatchError
  #120 = Utf8               <init>
  #121 = Utf8               (Ljava/lang/Object;)V
  #122 = NameAndType        #120:#121     // "<init>":(Ljava/lang/Object;)V
  #123 = Methodref          #119.#122     // scala/MatchError."<init>":(Ljava/lang/Object;)V
  #124 = Utf8               scala/Option
  #125 = Class              #124          // scala/Option
  #126 = Utf8               $anonfun$argNames$1
  #127 = Utf8               (I)Ljava/lang/String;
  #128 = Utf8               idx
  #129 = Utf8               java/lang/StringBuilder
  #130 = Class              #129          // java/lang/StringBuilder
  #131 = Integer            3
  #132 = Utf8               (I)V
  #133 = NameAndType        #120:#132     // "<init>":(I)V
  #134 = Methodref          #130.#133     // java/lang/StringBuilder."<init>":(I)V
  #135 = Utf8               arg
  #136 = String             #135          // arg
  #137 = Utf8               append
  #138 = Utf8               (Ljava/lang/String;)Ljava/lang/StringBuilder;
  #139 = NameAndType        #137:#138     // append:(Ljava/lang/String;)Ljava/lang/StringBuilder;
  #140 = Methodref          #130.#139     // java/lang/StringBuilder.append:(Ljava/lang/String;)Ljava/lang/StringBuilder;
  #141 = Utf8               (I)Ljava/lang/StringBuilder;
  #142 = NameAndType        #137:#141     // append:(I)Ljava/lang/StringBuilder;
  #143 = Methodref          #130.#142     // java/lang/StringBuilder.append:(I)Ljava/lang/StringBuilder;
  #144 = Utf8               toString
  #145 = NameAndType        #144:#29      // toString:()Ljava/lang/String;
  #146 = Methodref          #130.#145     // java/lang/StringBuilder.toString:()Ljava/lang/String;
  #147 = Utf8               I
  #148 = Utf8               (Lscala/Function1;Lscala/Option;Lscala/util/Either;Lscala/Option;Ljava/lang/String;Lscala/collection/immutable/List;Lscala/Option;)V
  #149 = Utf8               (Lscala/Function1<Lorg/scalatest/exceptions/StackDepthException;Ljava/lang/String;>;Lscala/Option<Ljava/lang/Throwable;>;Lscala/util/Either<Lorg/scalactic/source/Position;Lscala/Function1<Lorg/scalatest/exceptions/StackDepthException;Ljava/lang/Object;>;>;Lscala/Option<Ljava/lang/Object;>;Ljava/lang/String;Lscala/collection/immutable/List<Ljava/lang/Object;>;Lscala/Option<Lscala/collection/immutable/List<Ljava/lang/String;>;>;)V
  #150 = Utf8               messageFun
  #151 = Utf8               cause
  #152 = Utf8               posOrStackDepthFun
  #153 = Utf8               payload
  #154 = Utf8               (Lscala/Function1;)V
  #155 = NameAndType        #120:#154     // "<init>":(Lscala/Function1;)V
  #156 = Methodref          #20.#155      // org/scalatest/exceptions/PropertyCheckFailedException$$anonfun$$lessinit$greater$1."<init>":(Lscala/Function1;)V
  #157 = Utf8               scala/package$
  #158 = Class              #157          // scala/package$
  #159 = Utf8               Lscala/package$;
  #160 = NameAndType        #52:#159      // MODULE$:Lscala/package$;
  #161 = Fieldref           #158.#160     // scala/package$.MODULE$:Lscala/package$;
  #162 = Utf8               Vector
  #163 = Utf8               ()Lscala/collection/immutable/Vector$;
  #164 = NameAndType        #162:#163     // Vector:()Lscala/collection/immutable/Vector$;
  #165 = Methodref          #158.#164     // scala/package$.Vector:()Lscala/collection/immutable/Vector$;
  #166 = Utf8               scala/collection/immutable/Vector$
  #167 = Class              #166          // scala/collection/immutable/Vector$
  #168 = Utf8               empty
  #169 = Utf8               ()Lscala/collection/immutable/Vector;
  #170 = NameAndType        #168:#169     // empty:()Lscala/collection/immutable/Vector;
  #171 = Methodref          #167.#170     // scala/collection/immutable/Vector$.empty:()Lscala/collection/immutable/Vector;
  #172 = Utf8               (Lscala/Function1;Lscala/Option;Lscala/util/Either;Lscala/Option;Lscala/collection/immutable/IndexedSeq;)V
  #173 = NameAndType        #120:#172     // "<init>":(Lscala/Function1;Lscala/Option;Lscala/util/Either;Lscala/Option;Lscala/collection/immutable/IndexedSeq;)V
  #174 = Methodref          #4.#173       // org/scalatest/exceptions/TestFailedException."<init>":(Lscala/Function1;Lscala/Option;Lscala/util/Either;Lscala/Option;Lscala/collection/immutable/IndexedSeq;)V
  #175 = Utf8               org/scalactic/Requirements$
  #176 = Class              #175          // org/scalactic/Requirements$
  #177 = Utf8               Lorg/scalactic/Requirements$;
  #178 = NameAndType        #52:#177      // MODULE$:Lorg/scalactic/Requirements$;
  #179 = Fieldref           #176.#178     // org/scalactic/Requirements$.MODULE$:Lorg/scalactic/Requirements$;
  #180 = Utf8               requirementsHelper
  #181 = Utf8               ()Lorg/scalactic/Requirements$RequirementsHelper;
  #182 = NameAndType        #180:#181     // requirementsHelper:()Lorg/scalactic/Requirements$RequirementsHelper;
  #183 = Methodref          #176.#182     // org/scalactic/Requirements$.requirementsHelper:()Lorg/scalactic/Requirements$RequirementsHelper;
  #184 = Utf8               java/lang/String
  #185 = Class              #184          // java/lang/String
  #186 = Utf8               PropertyCheckFailedException.this.messageFun
  #187 = String             #186          // PropertyCheckFailedException.this.messageFun
  #188 = Utf8               PropertyCheckFailedException.this.cause
  #189 = String             #188          // PropertyCheckFailedException.this.cause
  #190 = Utf8               PropertyCheckFailedException.this.posOrStackDepthFun
  #191 = String             #190          // PropertyCheckFailedException.this.posOrStackDepthFun
  #192 = Utf8               PropertyCheckFailedException.this.undecoratedMessage
  #193 = String             #192          // PropertyCheckFailedException.this.undecoratedMessage
  #194 = Utf8               PropertyCheckFailedException.this.args
  #195 = String             #194          // PropertyCheckFailedException.this.args
  #196 = Utf8               PropertyCheckFailedException.this.optionalArgNames
  #197 = String             #196          // PropertyCheckFailedException.this.optionalArgNames
  #198 = Utf8               [Ljava/lang/Object;
  #199 = Class              #198          // "[Ljava/lang/Object;"
  #200 = Utf8               [Ljava/lang/String;
  #201 = Class              #200          // "[Ljava/lang/String;"
  #202 = Utf8               org/scalatest/exceptions/StackDepthException
  #203 = Class              #202          // org/scalatest/exceptions/StackDepthException
  #204 = Utf8               ()Lscala/Option;
  #205 = NameAndType        #151:#204     // cause:()Lscala/Option;
  #206 = Methodref          #203.#205     // org/scalatest/exceptions/StackDepthException.cause:()Lscala/Option;
  #207 = Utf8               org/scalactic/Prettifier$
  #208 = Class              #207          // org/scalactic/Prettifier$
  #209 = Utf8               Lorg/scalactic/Prettifier$;
  #210 = NameAndType        #52:#209      // MODULE$:Lorg/scalactic/Prettifier$;
  #211 = Fieldref           #208.#210     // org/scalactic/Prettifier$.MODULE$:Lorg/scalactic/Prettifier$;
  #212 = Utf8               default
  #213 = Utf8               ()Lorg/scalactic/Prettifier;
  #214 = NameAndType        #212:#213     // default:()Lorg/scalactic/Prettifier;
  #215 = Methodref          #208.#214     // org/scalactic/Prettifier$.default:()Lorg/scalactic/Prettifier;
  #216 = Utf8               org/scalactic/source/Position
  #217 = Class              #216          // org/scalactic/source/Position
  #218 = String             #5            // PropertyCheckFailedException.scala
  #219 = Utf8               Please set the environment variable SCALACTIC_FILL_FILE_PATHNAMES to yes at compile time to enable this feature.
  #220 = String             #219          // Please set the environment variable SCALACTIC_FILL_FILE_PATHNAMES to yes at compile time to enable this feature.
  #221 = Utf8               (Ljava/lang/String;Ljava/lang/String;I)V
  #222 = NameAndType        #120:#221     // "<init>":(Ljava/lang/String;Ljava/lang/String;I)V
  #223 = Methodref          #217.#222     // org/scalactic/source/Position."<init>":(Ljava/lang/String;Ljava/lang/String;I)V
  #224 = Utf8               macroRequireNonNull
  #225 = Utf8               ([Ljava/lang/String;[Ljava/lang/Object;Lorg/scalactic/Prettifier;Lorg/scalactic/source/Position;)V
  #226 = NameAndType        #224:#225     // macroRequireNonNull:([Ljava/lang/String;[Ljava/lang/Object;Lorg/scalactic/Prettifier;Lorg/scalactic/source/Position;)V
  #227 = Methodref          #15.#226      // org/scalactic/Requirements$RequirementsHelper.macroRequireNonNull:([Ljava/lang/String;[Ljava/lang/Object;Lorg/scalactic/Prettifier;Lorg/scalactic/source/Position;)V
  #228 = Utf8               java/lang/Throwable
  #229 = Class              #228          // java/lang/Throwable
  #230 = Utf8               org/scalactic/exceptions/NullArgumentException
  #231 = Class              #230          // org/scalactic/exceptions/NullArgumentException
  #232 = Utf8               cause was a Some(null)
  #233 = String             #232          // cause was a Some(null)
  #234 = Utf8               (Ljava/lang/String;)V
  #235 = NameAndType        #120:#234     // "<init>":(Ljava/lang/String;)V
  #236 = Methodref          #231.#235     // org/scalactic/exceptions/NullArgumentException."<init>":(Ljava/lang/String;)V
  #237 = Utf8               scala/runtime/BoxedUnit
  #238 = Class              #237          // scala/runtime/BoxedUnit
  #239 = Utf8               UNIT
  #240 = Utf8               Lscala/runtime/BoxedUnit;
  #241 = NameAndType        #239:#240     // UNIT:Lscala/runtime/BoxedUnit;
  #242 = Fieldref           #238.#241     // scala/runtime/BoxedUnit.UNIT:Lscala/runtime/BoxedUnit;
  #243 = Utf8               optionalArgNames was a Some(null)
  #244 = String             #243          // optionalArgNames was a Some(null)
  #245 = Utf8               Lscala/Function1;
  #246 = Utf8               Lscala/util/Either;
  #247 = Utf8               scala/Function1
  #248 = Class              #247          // scala/Function1
  #249 = Utf8               scala/util/Either
  #250 = Class              #249          // scala/util/Either
  #251 = Utf8               (Lscala/Function1;Lscala/Option;Lscala/Function1;Lscala/Option;Ljava/lang/String;Lscala/collection/immutable/List;Lscala/Option;)V
  #252 = Utf8               (Lscala/Function1<Lorg/scalatest/exceptions/StackDepthException;Ljava/lang/String;>;Lscala/Option<Ljava/lang/Throwable;>;Lscala/Function1<Lorg/scalatest/exceptions/StackDepthException;Ljava/lang/Object;>;Lscala/Option<Ljava/lang/Object;>;Ljava/lang/String;Lscala/collection/immutable/List<Ljava/lang/Object;>;Lscala/Option<Lscala/collection/immutable/List<Ljava/lang/String;>;>;)V
  #253 = Utf8               failedCodeStackDepthFun
  #254 = Utf8               Right
  #255 = Utf8               ()Lscala/util/Right$;
  #256 = NameAndType        #254:#255     // Right:()Lscala/util/Right$;
  #257 = Methodref          #158.#256     // scala/package$.Right:()Lscala/util/Right$;
  #258 = Utf8               scala/util/Right$
  #259 = Class              #258          // scala/util/Right$
  #260 = Utf8               (Ljava/lang/Object;)Lscala/util/Right;
  #261 = NameAndType        #103:#260     // apply:(Ljava/lang/Object;)Lscala/util/Right;
  #262 = Methodref          #259.#261     // scala/util/Right$.apply:(Ljava/lang/Object;)Lscala/util/Right;
  #263 = NameAndType        #120:#148     // "<init>":(Lscala/Function1;Lscala/Option;Lscala/util/Either;Lscala/Option;Ljava/lang/String;Lscala/collection/immutable/List;Lscala/Option;)V
  #264 = Methodref          #2.#263       // org/scalatest/exceptions/PropertyCheckFailedException."<init>":(Lscala/Function1;Lscala/Option;Lscala/util/Either;Lscala/Option;Ljava/lang/String;Lscala/collection/immutable/List;Lscala/Option;)V
  #265 = Utf8               scala/runtime/BoxesRunTime
  #266 = Class              #265          // scala/runtime/BoxesRunTime
  #267 = Utf8               unboxToInt
  #268 = Utf8               (Ljava/lang/Object;)I
  #269 = NameAndType        #267:#268     // unboxToInt:(Ljava/lang/Object;)I
  #270 = Methodref          #266.#269     // scala/runtime/BoxesRunTime.unboxToInt:(Ljava/lang/Object;)I
  #271 = NameAndType        #126:#127     // $anonfun$argNames$1:(I)Ljava/lang/String;
  #272 = Methodref          #2.#271       // org/scalatest/exceptions/PropertyCheckFailedException.$anonfun$argNames$1:(I)Ljava/lang/String;
  #273 = Utf8               Ljava/lang/Object;
  #274 = Utf8               $deserializeLambda$
  #275 = Utf8               (Ljava/lang/invoke/SerializedLambda;)Ljava/lang/Object;
  #276 = Utf8               scala/runtime/LambdaDeserialize
  #277 = Class              #276          // scala/runtime/LambdaDeserialize
  #278 = Utf8               bootstrap
  #279 = Utf8               (Ljava/lang/invoke/MethodHandles$Lookup;Ljava/lang/String;Ljava/lang/invoke/MethodType;[Ljava/lang/invoke/MethodHandle;)Ljava/lang/invoke/CallSite;
  #280 = NameAndType        #278:#279     // bootstrap:(Ljava/lang/invoke/MethodHandles$Lookup;Ljava/lang/String;Ljava/lang/invoke/MethodType;[Ljava/lang/invoke/MethodHandle;)Ljava/lang/invoke/CallSite;
  #281 = Methodref          #277.#280     // scala/runtime/LambdaDeserialize.bootstrap:(Ljava/lang/invoke/MethodHandles$Lookup;Ljava/lang/String;Ljava/lang/invoke/MethodType;[Ljava/lang/invoke/MethodHandle;)Ljava/lang/invoke/CallSite;
  #282 = MethodHandle       6:#281        // REF_invokeStatic scala/runtime/LambdaDeserialize.bootstrap:(Ljava/lang/invoke/MethodHandles$Lookup;Ljava/lang/String;Ljava/lang/invoke/MethodType;[Ljava/lang/invoke/MethodHandle;)Ljava/lang/invoke/CallSite;
  #283 = Utf8               lambdaDeserialize
  #284 = NameAndType        #283:#275     // lambdaDeserialize:(Ljava/lang/invoke/SerializedLambda;)Ljava/lang/Object;
  #285 = InvokeDynamic      #1:#284       // #1:lambdaDeserialize:(Ljava/lang/invoke/SerializedLambda;)Ljava/lang/Object;
  #286 = Utf8               Signature
  #287 = Utf8               Code
  #288 = Utf8               LineNumberTable
  #289 = Utf8               LocalVariableTable
  #290 = Utf8               StackMapTable
  #291 = Utf8               MethodParameters
  #292 = Utf8               InnerClasses
  #293 = Utf8               SourceFile
  #294 = Utf8               RuntimeVisibleAnnotations
  #295 = Utf8               BootstrapMethods
  #296 = Utf8               ScalaInlineInfo
  #297 = Utf8               ScalaSig
{
  private final java.lang.String undecoratedMessage;
    descriptor: Ljava/lang/String;
    flags: (0x0012) ACC_PRIVATE, ACC_FINAL

  private final scala.collection.immutable.List<java.lang.Object> args;
    descriptor: Lscala/collection/immutable/List;
    flags: (0x0012) ACC_PRIVATE, ACC_FINAL
    Signature: #25                          // Lscala/collection/immutable/List<Ljava/lang/Object;>;

  private final scala.Option<scala.collection.immutable.List<java.lang.String>> optionalArgNames;
    descriptor: Lscala/Option;
    flags: (0x0012) ACC_PRIVATE, ACC_FINAL
    Signature: #28                          // Lscala/Option<Lscala/collection/immutable/List<Ljava/lang/String;>;>;

  public java.lang.String undecoratedMessage();
    descriptor: ()Ljava/lang/String;
    flags: (0x0001) ACC_PUBLIC
    Code:
      stack=1, locals=1, args_size=1
         0: aload_0
         1: getfield      #31                 // Field undecoratedMessage:Ljava/lang/String;
         4: areturn
      LineNumberTable:
        line 44: 0
      LocalVariableTable:
        Start  Length  Slot  Name   Signature
            0       5     0  this   Lorg/scalatest/exceptions/PropertyCheckFailedException;

  public scala.collection.immutable.List<java.lang.Object> args();
    descriptor: ()Lscala/collection/immutable/List;
    flags: (0x0001) ACC_PUBLIC
    Code:
      stack=1, locals=1, args_size=1
         0: aload_0
         1: getfield      #37                 // Field args:Lscala/collection/immutable/List;
         4: areturn
      LineNumberTable:
        line 45: 0
      LocalVariableTable:
        Start  Length  Slot  Name   Signature
            0       5     0  this   Lorg/scalatest/exceptions/PropertyCheckFailedException;
    Signature: #35                          // ()Lscala/collection/immutable/List<Ljava/lang/Object;>;

  public scala.collection.immutable.List<java.lang.String> argNames();
    descriptor: ()Lscala/collection/immutable/List;
    flags: (0x0001) ACC_PUBLIC
    Code:
      stack=3, locals=5, args_size=1
         0: aload_0
         1: getfield      #41                 // Field optionalArgNames:Lscala/Option;
         4: astore_2
         5: aload_2
         6: instanceof    #43                 // class scala/Some
         9: ifeq          32
        12: aload_2
        13: checkcast     #43                 // class scala/Some
        16: astore_3
        17: aload_3
        18: invokevirtual #47                 // Method scala/Some.value:()Ljava/lang/Object;
        21: checkcast     #49                 // class scala/collection/immutable/List
        24: astore        4
        26: aload         4
        28: astore_1
        29: goto          94
        32: goto          35
        35: getstatic     #55                 // Field scala/None$.MODULE$:Lscala/None$;
        38: aload_2
        39: invokevirtual #61                 // Method java/lang/Object.equals:(Ljava/lang/Object;)Z
        42: ifeq          82
        45: getstatic     #66                 // Field scala/runtime/RichInt$.MODULE$:Lscala/runtime/RichInt$;
        48: getstatic     #71                 // Field scala/Predef$.MODULE$:Lscala/Predef$;
        51: iconst_0
        52: invokevirtual #75                 // Method scala/Predef$.intWrapper:(I)I
        55: aload_0
        56: invokevirtual #77                 // Method args:()Lscala/collection/immutable/List;
        59: invokevirtual #81                 // Method scala/collection/immutable/List.length:()I
        62: invokevirtual #85                 // Method scala/runtime/RichInt$.until$extension:(II)Lscala/collection/immutable/Range;
        65: invokedynamic #106,  0            // InvokeDynamic #0:apply:()Lscala/Function1;
        70: invokevirtual #112                // Method scala/collection/immutable/Range.map:(Lscala/Function1;)Lscala/collection/immutable/IndexedSeq;
        73: invokeinterface #117,  1          // InterfaceMethod scala/collection/immutable/IndexedSeq.toList:()Lscala/collection/immutable/List;
        78: astore_1
        79: goto          94
        82: goto          85
        85: new           #119                // class scala/MatchError
        88: dup
        89: aload_2
        90: invokespecial #123                // Method scala/MatchError."<init>":(Ljava/lang/Object;)V
        93: athrow
        94: aload_1
        95: areturn
      StackMapTable: number_of_entries = 5
        frame_type = 253 /* append */
          offset_delta = 32
          locals = [ top, class scala/Option ]
        frame_type = 2 /* same */
        frame_type = 46 /* same */
        frame_type = 2 /* same */
        frame_type = 255 /* full_frame */
          offset_delta = 8
          locals = [ class org/scalatest/exceptions/PropertyCheckFailedException, class scala/collection/immutable/List, class scala/Option ]
          stack = []
      LineNumberTable:
        line 96: 0
        line 97: 5
        line 98: 35
        line 96: 85
      LocalVariableTable:
        Start  Length  Slot  Name   Signature
           26       6     4 argNames   Lscala/collection/immutable/List;
            0      96     0  this   Lorg/scalatest/exceptions/PropertyCheckFailedException;
    Signature: #39                          // ()Lscala/collection/immutable/List<Ljava/lang/String;>;

  public static final java.lang.String $anonfun$argNames$1(int);
    descriptor: (I)Ljava/lang/String;
    flags: (0x1019) ACC_PUBLIC, ACC_STATIC, ACC_FINAL, ACC_SYNTHETIC
    Code:
      stack=3, locals=1, args_size=1
         0: new           #130                // class java/lang/StringBuilder
         3: dup
         4: ldc           #131                // int 3
         6: invokespecial #134                // Method java/lang/StringBuilder."<init>":(I)V
         9: ldc           #136                // String arg
        11: invokevirtual #140                // Method java/lang/StringBuilder.append:(Ljava/lang/String;)Ljava/lang/StringBuilder;
        14: iload_0
        15: invokevirtual #143                // Method java/lang/StringBuilder.append:(I)Ljava/lang/StringBuilder;
        18: invokevirtual #146                // Method java/lang/StringBuilder.toString:()Ljava/lang/String;
        21: areturn
      LineNumberTable:
        line 98: 0
      LocalVariableTable:
        Start  Length  Slot  Name   Signature
            0      22     0   idx   I
    MethodParameters:
      Name                           Flags
      idx                            final

  public org.scalatest.exceptions.PropertyCheckFailedException(scala.Function1<org.scalatest.exceptions.StackDepthException, java.lang.String>, scala.Option<java.lang.Throwable>, scala.util.Either<org.scalactic.source.Position, scala.Function1<org.scalatest.exceptions.StackDepthException, java.lang.Object>>, scala.Option<java.lang.Object>, java.lang.String, scala.collection.immutable.List<java.lang.Object>, scala.Option<scala.collection.immutable.List<java.lang.String>>);
    descriptor: (Lscala/Function1;Lscala/Option;Lscala/util/Either;Lscala/Option;Ljava/lang/String;Lscala/collection/immutable/List;Lscala/Option;)V
    flags: (0x0001) ACC_PUBLIC
    Code:
      stack=9, locals=16, args_size=8
         0: aload_0
         1: aload         5
         3: putfield      #31                 // Field undecoratedMessage:Ljava/lang/String;
         6: aload_0
         7: aload         6
         9: putfield      #37                 // Field args:Lscala/collection/immutable/List;
        12: aload_0
        13: aload         7
        15: putfield      #41                 // Field optionalArgNames:Lscala/Option;
        18: aload_0
        19: new           #20                 // class org/scalatest/exceptions/PropertyCheckFailedException$$anonfun$$lessinit$greater$1
        22: dup
        23: aload_1
        24: invokespecial #156                // Method org/scalatest/exceptions/PropertyCheckFailedException$$anonfun$$lessinit$greater$1."<init>":(Lscala/Function1;)V
        27: aload_2
        28: aload_3
        29: aload         4
        31: getstatic     #161                // Field scala/package$.MODULE$:Lscala/package$;
        34: invokevirtual #165                // Method scala/package$.Vector:()Lscala/collection/immutable/Vector$;
        37: invokevirtual #171                // Method scala/collection/immutable/Vector$.empty:()Lscala/collection/immutable/Vector;
        40: invokespecial #174                // Method org/scalatest/exceptions/TestFailedException."<init>":(Lscala/Function1;Lscala/Option;Lscala/util/Either;Lscala/Option;Lscala/collection/immutable/IndexedSeq;)V
        43: getstatic     #179                // Field org/scalactic/Requirements$.MODULE$:Lorg/scalactic/Requirements$;
        46: invokevirtual #183                // Method org/scalactic/Requirements$.requirementsHelper:()Lorg/scalactic/Requirements$RequirementsHelper;
        49: bipush        6
        51: anewarray     #185                // class java/lang/String
        54: dup
        55: iconst_0
        56: ldc           #187                // String PropertyCheckFailedException.this.messageFun
        58: aastore
        59: dup
        60: iconst_1
        61: ldc           #189                // String PropertyCheckFailedException.this.cause
        63: aastore
        64: dup
        65: iconst_2
        66: ldc           #191                // String PropertyCheckFailedException.this.posOrStackDepthFun
        68: aastore
        69: dup
        70: iconst_3
        71: ldc           #193                // String PropertyCheckFailedException.this.undecoratedMessage
        73: aastore
        74: dup
        75: iconst_4
        76: ldc           #195                // String PropertyCheckFailedException.this.args
        78: aastore
        79: dup
        80: iconst_5
        81: ldc           #197                // String PropertyCheckFailedException.this.optionalArgNames
        83: aastore
        84: checkcast     #199                // class "[Ljava/lang/Object;"
        87: checkcast     #201                // class "[Ljava/lang/String;"
        90: bipush        6
        92: anewarray     #57                 // class java/lang/Object
        95: dup
        96: iconst_0
        97: aload_1
        98: aastore
        99: dup
       100: iconst_1
       101: aload_0
       102: invokespecial #206                // Method org/scalatest/exceptions/StackDepthException.cause:()Lscala/Option;
       105: aastore
       106: dup
       107: iconst_2
       108: aload_3
       109: aastore
       110: dup
       111: iconst_3
       112: aload         5
       114: aastore
       115: dup
       116: iconst_4
       117: aload         6
       119: aastore
       120: dup
       121: iconst_5
       122: aload         7
       124: aastore
       125: checkcast     #199                // class "[Ljava/lang/Object;"
       128: getstatic     #211                // Field org/scalactic/Prettifier$.MODULE$:Lorg/scalactic/Prettifier$;
       131: invokevirtual #215                // Method org/scalactic/Prettifier$.default:()Lorg/scalactic/Prettifier;
       134: new           #217                // class org/scalactic/source/Position
       137: dup
       138: ldc           #218                // String PropertyCheckFailedException.scala
       140: ldc           #220                // String Please set the environment variable SCALACTIC_FILL_FILE_PATHNAMES to yes at compile time to enable this feature.
       142: bipush        71
       144: invokespecial #223                // Method org/scalactic/source/Position."<init>":(Ljava/lang/String;Ljava/lang/String;I)V
       147: invokevirtual #227                // Method org/scalactic/Requirements$RequirementsHelper.macroRequireNonNull:([Ljava/lang/String;[Ljava/lang/Object;Lorg/scalactic/Prettifier;Lorg/scalactic/source/Position;)V
       150: aload_0
       151: invokespecial #206                // Method org/scalatest/exceptions/StackDepthException.cause:()Lscala/Option;
       154: astore        10
       156: aload         10
       158: instanceof    #43                 // class scala/Some
       161: ifeq          199
       164: aload         10
       166: checkcast     #43                 // class scala/Some
       169: astore        11
       171: aload         11
       173: invokevirtual #47                 // Method scala/Some.value:()Ljava/lang/Object;
       176: checkcast     #229                // class java/lang/Throwable
       179: astore        12
       181: aload         12
       183: ifnonnull     196
       186: new           #231                // class org/scalactic/exceptions/NullArgumentException
       189: dup
       190: ldc           #233                // String cause was a Some(null)
       192: invokespecial #236                // Method org/scalactic/exceptions/NullArgumentException."<init>":(Ljava/lang/String;)V
       195: athrow
       196: goto          202
       199: goto          202
       202: getstatic     #242                // Field scala/runtime/BoxedUnit.UNIT:Lscala/runtime/BoxedUnit;
       205: astore        9
       207: goto          210
       210: aload         7
       212: astore        13
       214: aload         13
       216: instanceof    #43                 // class scala/Some
       219: ifeq          257
       222: aload         13
       224: checkcast     #43                 // class scala/Some
       227: astore        14
       229: aload         14
       231: invokevirtual #47                 // Method scala/Some.value:()Ljava/lang/Object;
       234: checkcast     #49                 // class scala/collection/immutable/List
       237: astore        15
       239: aload         15
       241: ifnonnull     254
       244: new           #231                // class org/scalactic/exceptions/NullArgumentException
       247: dup
       248: ldc           #244                // String optionalArgNames was a Some(null)
       250: invokespecial #236                // Method org/scalactic/exceptions/NullArgumentException."<init>":(Ljava/lang/String;)V
       253: athrow
       254: goto          260
       257: goto          260
       260: getstatic     #242                // Field scala/runtime/BoxedUnit.UNIT:Lscala/runtime/BoxedUnit;
       263: astore        8
       265: goto          268
       268: return
      StackMapTable: number_of_entries = 8
        frame_type = 255 /* full_frame */
          offset_delta = 196
          locals = [ class org/scalatest/exceptions/PropertyCheckFailedException, class scala/Function1, class scala/Option, class scala/util/Either, class scala/Option, class java/lang/String, class scala/collection/immutable/List, class scala/Option, top, top, class scala/Option, class scala/Some, class java/lang/Throwable ]
          stack = []
        frame_type = 249 /* chop */
          offset_delta = 2
        frame_type = 2 /* same */
        frame_type = 255 /* full_frame */
          offset_delta = 7
          locals = [ class org/scalatest/exceptions/PropertyCheckFailedException, class scala/Function1, class scala/Option, class scala/util/Either, class scala/Option, class java/lang/String, class scala/collection/immutable/List, class scala/Option, top, class scala/runtime/BoxedUnit, class scala/Option ]
          stack = []
        frame_type = 255 /* full_frame */
          offset_delta = 43
          locals = [ class org/scalatest/exceptions/PropertyCheckFailedException, class scala/Function1, class scala/Option, class scala/util/Either, class scala/Option, class java/lang/String, class scala/collection/immutable/List, class scala/Option, top, class scala/runtime/BoxedUnit, class scala/Option, top, top, class scala/Option, class scala/Some, class scala/collection/immutable/List ]
          stack = []
        frame_type = 249 /* chop */
          offset_delta = 2
        frame_type = 2 /* same */
        frame_type = 255 /* full_frame */
          offset_delta = 7
          locals = [ class org/scalatest/exceptions/PropertyCheckFailedException, class scala/Function1, class scala/Option, class scala/util/Either, class scala/Option, class java/lang/String, class scala/collection/immutable/List, class scala/Option, class scala/runtime/BoxedUnit, class scala/runtime/BoxedUnit, class scala/Option, top, top, class scala/Option ]
          stack = []
      LineNumberTable:
        line 44: 0
        line 45: 6
        line 46: 12
        line 47: 18
        line 71: 43
        line 72: 97
        line 73: 122
        line 71: 128
        line 75: 150
        line 76: 156
        line 77: 202
        line 80: 210
        line 81: 214
        line 82: 260
        line 39: 268
      LocalVariableTable:
        Start  Length  Slot  Name   Signature
            0     269     0  this   Lorg/scalatest/exceptions/PropertyCheckFailedException;
            0     269     1 messageFun   Lscala/Function1;
            0     269     2 cause   Lscala/Option;
            0     269     3 posOrStackDepthFun   Lscala/util/Either;
            0     269     4 payload   Lscala/Option;
            0     269     5 undecoratedMessage   Ljava/lang/String;
            0     269     6  args   Lscala/collection/immutable/List;
            0     269     7 optionalArgNames   Lscala/Option;
    Signature: #149                         // (Lscala/Function1<Lorg/scalatest/exceptions/StackDepthException;Ljava/lang/String;>;Lscala/Option<Ljava/lang/Throwable;>;Lscala/util/Either<Lorg/scalactic/source/Position;Lscala/Function1<Lorg/scalatest/exceptions/StackDepthException;Ljava/lang/Object;>;>;Lscala/Option<Ljava/lang/Object;>;Ljava/lang/String;Lscala/collection/immutable/List<Ljava/lang/Object;>;Lscala/Option<Lscala/collection/immutable/List<Ljava/lang/String;>;>;)V
    MethodParameters:
      Name                           Flags
      messageFun                     final
      cause                          final
      posOrStackDepthFun             final
      payload                        final
      undecoratedMessage             final
      args                           final
      optionalArgNames               final

  public org.scalatest.exceptions.PropertyCheckFailedException(scala.Function1<org.scalatest.exceptions.StackDepthException, java.lang.String>, scala.Option<java.lang.Throwable>, scala.Function1<org.scalatest.exceptions.StackDepthException, java.lang.Object>, scala.Option<java.lang.Object>, java.lang.String, scala.collection.immutable.List<java.lang.Object>, scala.Option<scala.collection.immutable.List<java.lang.String>>);
    descriptor: (Lscala/Function1;Lscala/Option;Lscala/Function1;Lscala/Option;Ljava/lang/String;Lscala/collection/immutable/List;Lscala/Option;)V
    flags: (0x0001) ACC_PUBLIC
    Code:
      stack=8, locals=8, args_size=8
         0: aload_0
         1: aload_1
         2: aload_2
         3: getstatic     #161                // Field scala/package$.MODULE$:Lscala/package$;
         6: invokevirtual #257                // Method scala/package$.Right:()Lscala/util/Right$;
         9: aload_3
        10: invokevirtual #262                // Method scala/util/Right$.apply:(Ljava/lang/Object;)Lscala/util/Right;
        13: aload         4
        15: aload         5
        17: aload         6
        19: aload         7
        21: invokespecial #264                // Method "<init>":(Lscala/Function1;Lscala/Option;Lscala/util/Either;Lscala/Option;Ljava/lang/String;Lscala/collection/immutable/List;Lscala/Option;)V
        24: return
      LineNumberTable:
        line 69: 0
      LocalVariableTable:
        Start  Length  Slot  Name   Signature
            0      25     0  this   Lorg/scalatest/exceptions/PropertyCheckFailedException;
            0      25     1 messageFun   Lscala/Function1;
            0      25     2 cause   Lscala/Option;
            0      25     3 failedCodeStackDepthFun   Lscala/Function1;
            0      25     4 payload   Lscala/Option;
            0      25     5 undecoratedMessage   Ljava/lang/String;
            0      25     6  args   Lscala/collection/immutable/List;
            0      25     7 optionalArgNames   Lscala/Option;
    Signature: #252                         // (Lscala/Function1<Lorg/scalatest/exceptions/StackDepthException;Ljava/lang/String;>;Lscala/Option<Ljava/lang/Throwable;>;Lscala/Function1<Lorg/scalatest/exceptions/StackDepthException;Ljava/lang/Object;>;Lscala/Option<Ljava/lang/Object;>;Ljava/lang/String;Lscala/collection/immutable/List<Ljava/lang/Object;>;Lscala/Option<Lscala/collection/immutable/List<Ljava/lang/String;>;>;)V
    MethodParameters:
      Name                           Flags
      messageFun                     final
      cause                          final
      failedCodeStackDepthFun        final
      payload                        final
      undecoratedMessage             final
      args                           final
      optionalArgNames               final

  public static final java.lang.String $anonfun$argNames$1$adapted(java.lang.Object);
    descriptor: (Ljava/lang/Object;)Ljava/lang/String;
    flags: (0x1019) ACC_PUBLIC, ACC_STATIC, ACC_FINAL, ACC_SYNTHETIC
    Code:
      stack=1, locals=1, args_size=1
         0: aload_0
         1: invokestatic  #270                // Method scala/runtime/BoxesRunTime.unboxToInt:(Ljava/lang/Object;)I
         4: invokestatic  #272                // Method $anonfun$argNames$1:(I)Ljava/lang/String;
         7: areturn
      LineNumberTable:
        line 98: 0
      LocalVariableTable:
        Start  Length  Slot  Name   Signature
            0       8     0   idx   Ljava/lang/Object;
    MethodParameters:
      Name                           Flags
      idx                            final

  private static java.lang.Object $deserializeLambda$(java.lang.invoke.SerializedLambda);
    descriptor: (Ljava/lang/invoke/SerializedLambda;)Ljava/lang/Object;
    flags: (0x100a) ACC_PRIVATE, ACC_STATIC, ACC_SYNTHETIC
    Code:
      stack=1, locals=1, args_size=1
         0: aload_0
         1: invokedynamic #285,  0            // InvokeDynamic #1:lambdaDeserialize:(Ljava/lang/invoke/SerializedLambda;)Ljava/lang/Object;
         6: areturn
}
InnerClasses:
  public static final #13= #10 of #12;    // Lookup=class java/lang/invoke/MethodHandles$Lookup of class java/lang/invoke/MethodHandles
  public static #18= #15 of #17;          // RequirementsHelper=class org/scalactic/Requirements$RequirementsHelper of class org/scalactic/Requirements
  public final #20;                       // class org/scalatest/exceptions/PropertyCheckFailedException$$anonfun$$lessinit$greater$1
SourceFile: "PropertyCheckFailedException.scala"
RuntimeVisibleAnnotations:
  0: #6(#7=s#8)
    scala.reflect.ScalaSignature(
      bytes="\u0006\u0005Q4Q!\u0004\b\u0002\u0002UA\u0001B\u0007\u0001\u0003\u0002\u0003\u0006Ia\u0007\u0005\n_\u0001\u0011\t\u0011)A\u0005aqB\u0001\"\u0010\u0001\u0003\u0002\u0003\u0006IA\u0010\u0005\n\u001b\u0002\u0011\t\u0011)A\u0005\u001dJC\u0001b\u0015\u0001\u0003\u0006\u0004%\t\u0001\u0016\u0005\t+\u0002\u0011\t\u0011)A\u0005I!Aa\u000b\u0001BC\u0002\u0013\u0005q\u000b\u0003\u0005\\\u0001\t\u0005\t\u0015!\u0003Y\u0011!a\u0006A!A!\u0002\u0013i\u0006\"B0\u0001\t\u0003\u0001\u0007\"B0\u0001\t\u0003I\u0007\"\u0002:\u0001\t\u0003\u0019(\u0001\b)s_B,\'\u000f^=DQ\u0016\u001c7NR1jY\u0016$W\t_2faRLwN\u001c\u0006\u0003\u001fA\t!\"\u001a=dKB$\u0018n\u001c8t\u0015\t\t\"#A\u0005tG\u0006d\u0017\r^3ti*\t1#A\u0002pe\u001e\u001c\u0001a\u0005\u0002\u0001-A\u0011q\u0003G\u0007\u0002\u001d%\u0011\u0011D\u0004\u0002\u0014)\u0016\u001cHOR1jY\u0016$W\t_2faRLwN\\\u0001\u000b[\u0016\u001c8/Y4f\rVt\u0007\u0003\u0002\u000f C\u0011j\u0011!\b\u0006\u0002=\u0005)1oY1mC&\u0011\u0001%\b\u0002\n\rVt7\r^5p]F\u0002\"a\u0006\u0012\n\u0005\rr!aE*uC\u000e\\G)\u001a9uQ\u0016C8-\u001a9uS>t\u0007CA\u0013-\u001d\t1#\u0006\u0005\u0002(;5\t\u0001F\u0003\u0002*)\u00051AH]8pizJ!aK\u000f\u0002\rA\u0013X\rZ3g\u0013\ticF\u0001\u0004TiJLgn\u001a\u0006\u0003Wu\tQaY1vg\u0016\u00042\u0001H\u00194\u0013\t\u0011TD\u0001\u0004PaRLwN\u001c\t\u0003ier!!N\u001c\u000f\u0005\u001d2\u0014\"\u0001\u0010\n\u0005aj\u0012a\u00029bG.\fw-Z\u0005\u0003um\u0012\u0011\u0002\u00165s_^\f\'\r\\3\u000b\u0005aj\u0012BA\u0018#\u0003I\u0001xn](s\'R\f7m\u001b#faRDg)\u001e8\u0011\tQz\u0014)S\u0005\u0003\u0001n\u0012a!R5uQ\u0016\u0014\bC\u0001\"H\u001b\u0005\u0019%B\u0001#F\u0003\u0019\u0019x.\u001e:dK*\u0011aIE\u0001\ng\u000e\fG.Y2uS\u000eL!\u0001S\"\u0003\u0011A{7/\u001b;j_:\u0004B\u0001H\u0010\"\u0015B\u0011AdS\u0005\u0003\u0019v\u00111!\u00138u\u0003\u001d\u0001\u0018-\u001f7pC\u0012\u00042\u0001H\u0019P!\ta\u0002+\u0003\u0002R;\t\u0019\u0011I\\=\n\u00055C\u0012AE;oI\u0016\u001cwN]1uK\u0012lUm]:bO\u0016,\u0012\u0001J\u0001\u0014k:$WmY8sCR,G-T3tg\u0006<W\rI\u0001\u0005CJ<7/F\u0001Y!\r!\u0014lT\u0005\u00035n\u0012A\u0001T5ti\u0006)\u0011M]4tA\u0005\u0001r\u000e\u001d;j_:\fG.\u0011:h\u001d\u0006lWm\u001d\t\u00049Er\u0006c\u0001\u001bZI\u00051A(\u001b8jiz\"\u0002\"\u00192dI\u00164w\r\u001b\t\u0003/\u0001AQA\u0007\u0006A\u0002mAQa\f\u0006A\u0002ABQ!\u0010\u0006A\u0002yBQ!\u0014\u0006A\u00029CQa\u0015\u0006A\u0002\u0011BQA\u0016\u0006A\u0002aCQ\u0001\u0018\u0006A\u0002u#\u0002\"\u00196lY:|\u0007/\u001d\u0005\u00065-\u0001\ra\u0007\u0005\u0006_-\u0001\r\u0001\r\u0005\u0006[.\u0001\r!S\u0001\u0018M\u0006LG.\u001a3D_\u0012,7\u000b^1dW\u0012+\u0007\u000f\u001e5Gk:DQ!T\u0006A\u00029CQaU\u0006A\u0002\u0011BQAV\u0006A\u0002aCQ\u0001X\u0006A\u0002u\u000b\u0001\"\u0019:h\u001d\u0006lWm]\u000b\u0002=\u0002"
    )
BootstrapMethods:
  0: #102 REF_invokeStatic java/lang/invoke/LambdaMetafactory.altMetafactory:(Ljava/lang/invoke/MethodHandles$Lookup;Ljava/lang/String;Ljava/lang/invoke/MethodType;[Ljava/lang/Object;)Ljava/lang/invoke/CallSite;
    Method arguments:
      #87 (Ljava/lang/Object;)Ljava/lang/Object;
      #92 REF_invokeStatic org/scalatest/exceptions/PropertyCheckFailedException.$anonfun$argNames$1$adapted:(Ljava/lang/Object;)Ljava/lang/String;
      #93 (Ljava/lang/Object;)Ljava/lang/String;
      #94 5
      #95 1
      #93 (Ljava/lang/Object;)Ljava/lang/String;
  1: #282 REF_invokeStatic scala/runtime/LambdaDeserialize.bootstrap:(Ljava/lang/invoke/MethodHandles$Lookup;Ljava/lang/String;Ljava/lang/invoke/MethodType;[Ljava/lang/invoke/MethodHandle;)Ljava/lang/invoke/CallSite;
    Method arguments:
      #92 REF_invokeStatic org/scalatest/exceptions/PropertyCheckFailedException.$anonfun$argNames$1$adapted:(Ljava/lang/Object;)Ljava/lang/String;
  ScalaInlineInfo: length = 0x27 (unknown attribute)
   01 00 00 07 00 7E 00 7F 01 00 58 00 59 01 00 78
   00 FB 00 00 78 00 94 00 00 26 00 22 00 00 17 00
   22 00 00 15 00 1D 00
  ScalaSig: length = 0x3 (unknown attribute)
   05 02 00
