Classfile /Users/mw/Projects/slang-braindump/.jar/jar8/assemble/slang-braindump/assemble/content/org/scalatest/exceptions/StackDepth.class
  Last modified May 29, 2022; size 8453 bytes
  SHA-256 checksum b2753f94b5acb54ca9b755574e7e786374c6dd46b557d444af524988a78635a7
  Compiled from "StackDepth.scala"
public interface org.scalatest.exceptions.StackDepth
  minor version: 0
  major version: 52
  flags: (0x0601) ACC_PUBLIC, ACC_INTERFACE, ACC_ABSTRACT
  this_class: #2                          // org/scalatest/exceptions/StackDepth
  super_class: #4                         // java/lang/Object
  interfaces: 0, fields: 0, methods: 27, attributes: 6
Constant pool:
    #1 = Utf8               org/scalatest/exceptions/StackDepth
    #2 = Class              #1            // org/scalatest/exceptions/StackDepth
    #3 = Utf8               java/lang/Object
    #4 = Class              #3            // java/lang/Object
    #5 = Utf8               StackDepth.scala
    #6 = Utf8               Lscala/reflect/ScalaSignature;
    #7 = Utf8               bytes
    #8 = Utf8               \u0006\u0005!4\u0001\"\u0004\b\u0011\u0002\u0007\u0005QC\u001a\u0005\u00069\u0001!\t!\b\u0005\u0006C\u00011\tA\t\u0005\u0006c\u00011\tA\r\u0005\u0006{\u00011\tA\u0010\u0005\u0006\u0005\u00021\tA\t\u0005\u0006\u0007\u00021\t\u0001\u0012\u0005\u0006\u001d\u0002!\tA\t\u0005\t\u001f\u0002A)\u0019!C\u0001E!)\u0001\u000b\u0001C\u0005#\")1\f\u0001C\u0001E!)A\f\u0001C\u0001;\")q\f\u0001D\u0001A\nQ1\u000b^1dW\u0012+\u0007\u000f\u001e5\u000b\u0005=\u0001\u0012AC3yG\u0016\u0004H/[8og*\u0011\u0011CE\u0001\ng\u000e\fG.\u0019;fgRT\u0011aE\u0001\u0004_J<7\u0001A\n\u0003\u0001Y\u0001\"a\u0006\u000e\u000e\u0003aQ\u0011!G\u0001\u0006g\u000e\fG.Y\u0005\u00037a\u0011a!\u00118z%\u00164\u0017A\u0002\u0013j]&$H\u0005F\u0001\u001f!\t9r$\u0003\u0002!1\t!QK\\5u\u0003\u001diWm]:bO\u0016,\u0012a\t\t\u0004/\u00112\u0013BA\u0013\u0019\u0005\u0019y\u0005\u000f^5p]B\u0011qE\f\b\u0003Q1\u0002\"!\u000b\r\u000e\u0003)R!a\u000b\u000b\u0002\rq\u0012xn\u001c;?\u0013\ti\u0003$\u0001\u0004Qe\u0016$WMZ\u0005\u0003_A\u0012aa\u0015;sS:<\'BA\u0017\u0019\u0003\u0015\u0019\u0017-^:f+\u0005\u0019\u0004cA\f%iA\u0011QG\u000f\b\u0003mar!!K\u001c\n\u0003eI!!\u000f\r\u0002\u000fA\f7m[1hK&\u00111\b\u0010\u0002\n)\"\u0014xn^1cY\u0016T!!\u000f\r\u0002)\u0019\f\u0017\u000e\\3e\u0007>$Wm\u0015;bG.$U\r\u001d;i+\u0005y\u0004CA\fA\u0013\t\t\u0005DA\u0002J]R\faCZ1jY\u0016$7i\u001c3f\r&dW\rU1uQ:\fW.Z\u0001\ta>\u001c\u0018\u000e^5p]V\tQ\tE\u0002\u0018I\u0019\u0003\"a\u0012\'\u000e\u0003!S!!\u0013&\u0002\rM|WO]2f\u0015\tY%#A\u0005tG\u0006d\u0017m\u0019;jG&\u0011Q\n\u0013\u0002\t!>\u001c\u0018\u000e^5p]\u0006)c-Y5mK\u0012\u001cu\u000eZ3GS2,g*Y7f\u0003:$G*\u001b8f\u001dVl\'-\u001a:TiJLgnZ\u0001*M\u0006LG.\u001a3D_\u0012,g)\u001b7f!\u0006$\bN\\1nK\u0006sG\rT5oK:+XNY3s\'R\u0014\u0018N\\4\u0002#M$\u0018mY6Ue\u0006\u001cW-\u00127f[\u0016tG/F\u0001S!\r9Be\u0015\t\u0003)fk\u0011!\u0016\u0006\u0003-^\u000bA\u0001\\1oO*\t\u0001,\u0001\u0003kCZ\f\u0017B\u0001.V\u0005E\u0019F/Y2l)J\f7-Z#mK6,g\u000e^\u0001\u0013M\u0006LG.\u001a3D_\u0012,g)\u001b7f\u001d\u0006lW-\u0001\u000bgC&dW\rZ\"pI\u0016d\u0015N\\3Ok6\u0014WM]\u000b\u0002=B\u0019q\u0003J \u0002\'M,g/\u001a:fI\u0006#8\u000b^1dW\u0012+\u0007\u000f\u001e5\u0016\u0003\u0005\u00142A\u0019\u001be\r\u0011\u0019\u0007\u0001A1\u0003\u0019q\u0012XMZ5oK6,g\u000e\u001e \u0011\u0005\u0015\u0004Q\"\u0001\b\u0013\u0007\u001d$GG\u0002\u0003d\u0001\u00011\u0007
    #9 = Utf8               java/lang/invoke/MethodHandles$Lookup
   #10 = Class              #9            // java/lang/invoke/MethodHandles$Lookup
   #11 = Utf8               java/lang/invoke/MethodHandles
   #12 = Class              #11           // java/lang/invoke/MethodHandles
   #13 = Utf8               Lookup
   #14 = Utf8               message
   #15 = Utf8               ()Lscala/Option;
   #16 = Utf8               ()Lscala/Option<Ljava/lang/String;>;
   #17 = Utf8               cause
   #18 = Utf8               ()Lscala/Option<Ljava/lang/Throwable;>;
   #19 = Utf8               failedCodeStackDepth
   #20 = Utf8               ()I
   #21 = Utf8               failedCodeFilePathname
   #22 = Utf8               position
   #23 = Utf8               ()Lscala/Option<Lorg/scalactic/source/Position;>;
   #24 = Utf8               failedCodeFileNameAndLineNumberString$
   #25 = Utf8               (Lorg/scalatest/exceptions/StackDepth;)Lscala/Option;
   #26 = Utf8               $this
   #27 = Utf8               failedCodeFileNameAndLineNumberString
   #28 = NameAndType        #27:#15       // failedCodeFileNameAndLineNumberString:()Lscala/Option;
   #29 = InterfaceMethodref #2.#28        // org/scalatest/exceptions/StackDepth.failedCodeFileNameAndLineNumberString:()Lscala/Option;
   #30 = Utf8               Lorg/scalatest/exceptions/StackDepth;
   #31 = Utf8               failedCodeFileName
   #32 = NameAndType        #31:#15       // failedCodeFileName:()Lscala/Option;
   #33 = InterfaceMethodref #2.#32        // org/scalatest/exceptions/StackDepth.failedCodeFileName:()Lscala/Option;
   #34 = Utf8               (Ljava/lang/Object;)Ljava/lang/Object;
   #35 = MethodType         #34           //  (Ljava/lang/Object;)Ljava/lang/Object;
   #36 = Utf8               $anonfun$failedCodeFileNameAndLineNumberString$1
   #37 = Utf8               (Lorg/scalatest/exceptions/StackDepth;Ljava/lang/String;)Lscala/Option;
   #38 = NameAndType        #36:#37       // $anonfun$failedCodeFileNameAndLineNumberString$1:(Lorg/scalatest/exceptions/StackDepth;Ljava/lang/String;)Lscala/Option;
   #39 = InterfaceMethodref #2.#38        // org/scalatest/exceptions/StackDepth.$anonfun$failedCodeFileNameAndLineNumberString$1:(Lorg/scalatest/exceptions/StackDepth;Ljava/lang/String;)Lscala/Option;
   #40 = MethodHandle       6:#39         // REF_invokeStatic org/scalatest/exceptions/StackDepth.$anonfun$failedCodeFileNameAndLineNumberString$1:(Lorg/scalatest/exceptions/StackDepth;Ljava/lang/String;)Lscala/Option;
   #41 = Utf8               (Ljava/lang/String;)Lscala/Option;
   #42 = MethodType         #41           //  (Ljava/lang/String;)Lscala/Option;
   #43 = Integer            5
   #44 = Integer            1
   #45 = Utf8               java/lang/invoke/LambdaMetafactory
   #46 = Class              #45           // java/lang/invoke/LambdaMetafactory
   #47 = Utf8               altMetafactory
   #48 = Utf8               (Ljava/lang/invoke/MethodHandles$Lookup;Ljava/lang/String;Ljava/lang/invoke/MethodType;[Ljava/lang/Object;)Ljava/lang/invoke/CallSite;
   #49 = NameAndType        #47:#48       // altMetafactory:(Ljava/lang/invoke/MethodHandles$Lookup;Ljava/lang/String;Ljava/lang/invoke/MethodType;[Ljava/lang/Object;)Ljava/lang/invoke/CallSite;
   #50 = Methodref          #46.#49       // java/lang/invoke/LambdaMetafactory.altMetafactory:(Ljava/lang/invoke/MethodHandles$Lookup;Ljava/lang/String;Ljava/lang/invoke/MethodType;[Ljava/lang/Object;)Ljava/lang/invoke/CallSite;
   #51 = MethodHandle       6:#50         // REF_invokeStatic java/lang/invoke/LambdaMetafactory.altMetafactory:(Ljava/lang/invoke/MethodHandles$Lookup;Ljava/lang/String;Ljava/lang/invoke/MethodType;[Ljava/lang/Object;)Ljava/lang/invoke/CallSite;
   #52 = Utf8               apply
   #53 = Utf8               (Lorg/scalatest/exceptions/StackDepth;)Lscala/Function1;
   #54 = NameAndType        #52:#53       // apply:(Lorg/scalatest/exceptions/StackDepth;)Lscala/Function1;
   #55 = InvokeDynamic      #0:#54        // #0:apply:(Lorg/scalatest/exceptions/StackDepth;)Lscala/Function1;
   #56 = Utf8               scala/Option
   #57 = Class              #56           // scala/Option
   #58 = Utf8               flatMap
   #59 = Utf8               (Lscala/Function1;)Lscala/Option;
   #60 = NameAndType        #58:#59       // flatMap:(Lscala/Function1;)Lscala/Option;
   #61 = Methodref          #57.#60       // scala/Option.flatMap:(Lscala/Function1;)Lscala/Option;
   #62 = Utf8               this
   #63 = Utf8               failedCodeFilePathnameAndLineNumberString$
   #64 = Utf8               failedCodeFilePathnameAndLineNumberString
   #65 = NameAndType        #64:#15       // failedCodeFilePathnameAndLineNumberString:()Lscala/Option;
   #66 = InterfaceMethodref #2.#65        // org/scalatest/exceptions/StackDepth.failedCodeFilePathnameAndLineNumberString:()Lscala/Option;
   #67 = NameAndType        #21:#15       // failedCodeFilePathname:()Lscala/Option;
   #68 = InterfaceMethodref #2.#67        // org/scalatest/exceptions/StackDepth.failedCodeFilePathname:()Lscala/Option;
   #69 = Utf8               $anonfun$failedCodeFilePathnameAndLineNumberString$1
   #70 = NameAndType        #69:#37       // $anonfun$failedCodeFilePathnameAndLineNumberString$1:(Lorg/scalatest/exceptions/StackDepth;Ljava/lang/String;)Lscala/Option;
   #71 = InterfaceMethodref #2.#70        // org/scalatest/exceptions/StackDepth.$anonfun$failedCodeFilePathnameAndLineNumberString$1:(Lorg/scalatest/exceptions/StackDepth;Ljava/lang/String;)Lscala/Option;
   #72 = MethodHandle       6:#71         // REF_invokeStatic org/scalatest/exceptions/StackDepth.$anonfun$failedCodeFilePathnameAndLineNumberString$1:(Lorg/scalatest/exceptions/StackDepth;Ljava/lang/String;)Lscala/Option;
   #73 = InvokeDynamic      #1:#54        // #1:apply:(Lorg/scalatest/exceptions/StackDepth;)Lscala/Function1;
   #74 = Utf8               stackTraceElement
   #75 = Utf8               ()Lscala/Option<Ljava/lang/StackTraceElement;>;
   #76 = Utf8               java/lang/Throwable
   #77 = Class              #76           // java/lang/Throwable
   #78 = Utf8               getStackTrace
   #79 = Utf8               ()[Ljava/lang/StackTraceElement;
   #80 = NameAndType        #78:#79       // getStackTrace:()[Ljava/lang/StackTraceElement;
   #81 = Methodref          #77.#80       // java/lang/Throwable.getStackTrace:()[Ljava/lang/StackTraceElement;
   #82 = NameAndType        #22:#15       // position:()Lscala/Option;
   #83 = InterfaceMethodref #2.#82        // org/scalatest/exceptions/StackDepth.position:()Lscala/Option;
   #84 = Utf8               scala/Some
   #85 = Class              #84           // scala/Some
   #86 = Utf8               value
   #87 = Utf8               ()Ljava/lang/Object;
   #88 = NameAndType        #86:#87       // value:()Ljava/lang/Object;
   #89 = Methodref          #85.#88       // scala/Some.value:()Ljava/lang/Object;
   #90 = Utf8               org/scalactic/source/Position
   #91 = Class              #90           // org/scalactic/source/Position
   #92 = Utf8               scala/collection/ArrayOps$
   #93 = Class              #92           // scala/collection/ArrayOps$
   #94 = Utf8               MODULE$
   #95 = Utf8               Lscala/collection/ArrayOps$;
   #96 = NameAndType        #94:#95       // MODULE$:Lscala/collection/ArrayOps$;
   #97 = Fieldref           #93.#96       // scala/collection/ArrayOps$.MODULE$:Lscala/collection/ArrayOps$;
   #98 = Utf8               scala/Predef$
   #99 = Class              #98           // scala/Predef$
  #100 = Utf8               Lscala/Predef$;
  #101 = NameAndType        #94:#100      // MODULE$:Lscala/Predef$;
  #102 = Fieldref           #99.#101      // scala/Predef$.MODULE$:Lscala/Predef$;
  #103 = Utf8               [Ljava/lang/Object;
  #104 = Class              #103          // "[Ljava/lang/Object;"
  #105 = Utf8               refArrayOps
  #106 = Utf8               ([Ljava/lang/Object;)Ljava/lang/Object;
  #107 = NameAndType        #105:#106     // refArrayOps:([Ljava/lang/Object;)Ljava/lang/Object;
  #108 = Methodref          #99.#107      // scala/Predef$.refArrayOps:([Ljava/lang/Object;)Ljava/lang/Object;
  #109 = Utf8               $anonfun$stackTraceElement$1$adapted
  #110 = Utf8               (Lorg/scalactic/source/Position;Ljava/lang/StackTraceElement;)Ljava/lang/Object;
  #111 = NameAndType        #109:#110     // $anonfun$stackTraceElement$1$adapted:(Lorg/scalactic/source/Position;Ljava/lang/StackTraceElement;)Ljava/lang/Object;
  #112 = InterfaceMethodref #2.#111       // org/scalatest/exceptions/StackDepth.$anonfun$stackTraceElement$1$adapted:(Lorg/scalactic/source/Position;Ljava/lang/StackTraceElement;)Ljava/lang/Object;
  #113 = MethodHandle       6:#112        // REF_invokeStatic org/scalatest/exceptions/StackDepth.$anonfun$stackTraceElement$1$adapted:(Lorg/scalactic/source/Position;Ljava/lang/StackTraceElement;)Ljava/lang/Object;
  #114 = Utf8               (Ljava/lang/StackTraceElement;)Ljava/lang/Object;
  #115 = MethodType         #114          //  (Ljava/lang/StackTraceElement;)Ljava/lang/Object;
  #116 = Utf8               (Lorg/scalactic/source/Position;)Lscala/Function1;
  #117 = NameAndType        #52:#116      // apply:(Lorg/scalactic/source/Position;)Lscala/Function1;
  #118 = InvokeDynamic      #2:#117       // #2:apply:(Lorg/scalactic/source/Position;)Lscala/Function1;
  #119 = Utf8               find$extension
  #120 = Utf8               (Ljava/lang/Object;Lscala/Function1;)Lscala/Option;
  #121 = NameAndType        #119:#120     // find$extension:(Ljava/lang/Object;Lscala/Function1;)Lscala/Option;
  #122 = Methodref          #93.#121      // scala/collection/ArrayOps$.find$extension:(Ljava/lang/Object;Lscala/Function1;)Lscala/Option;
  #123 = Utf8               scala/None$
  #124 = Class              #123          // scala/None$
  #125 = Utf8               Lscala/None$;
  #126 = NameAndType        #94:#125      // MODULE$:Lscala/None$;
  #127 = Fieldref           #124.#126     // scala/None$.MODULE$:Lscala/None$;
  #128 = Utf8               equals
  #129 = Utf8               (Ljava/lang/Object;)Z
  #130 = NameAndType        #128:#129     // equals:(Ljava/lang/Object;)Z
  #131 = Methodref          #4.#130       // java/lang/Object.equals:(Ljava/lang/Object;)Z
  #132 = NameAndType        #19:#20       // failedCodeStackDepth:()I
  #133 = InterfaceMethodref #2.#132       // org/scalatest/exceptions/StackDepth.failedCodeStackDepth:()I
  #134 = Utf8               <init>
  #135 = Utf8               (Ljava/lang/Object;)V
  #136 = NameAndType        #134:#135     // "<init>":(Ljava/lang/Object;)V
  #137 = Methodref          #85.#136      // scala/Some."<init>":(Ljava/lang/Object;)V
  #138 = Utf8               scala/MatchError
  #139 = Class              #138          // scala/MatchError
  #140 = Methodref          #139.#136     // scala/MatchError."<init>":(Ljava/lang/Object;)V
  #141 = Utf8               pos
  #142 = Utf8               Lorg/scalactic/source/Position;
  #143 = Utf8               stackTrace
  #144 = Utf8               [Ljava/lang/StackTraceElement;
  #145 = Class              #144          // "[Ljava/lang/StackTraceElement;"
  #146 = Utf8               failedCodeFileName$
  #147 = Utf8               fileName
  #148 = Utf8               ()Ljava/lang/String;
  #149 = NameAndType        #147:#148     // fileName:()Ljava/lang/String;
  #150 = Methodref          #91.#149      // org/scalactic/source/Position.fileName:()Ljava/lang/String;
  #151 = NameAndType        #74:#15       // stackTraceElement:()Lscala/Option;
  #152 = InterfaceMethodref #2.#151       // org/scalatest/exceptions/StackDepth.stackTraceElement:()Lscala/Option;
  #153 = Utf8               $anonfun$failedCodeFileName$1
  #154 = Utf8               (Ljava/lang/StackTraceElement;)Lscala/Option;
  #155 = NameAndType        #153:#154     // $anonfun$failedCodeFileName$1:(Ljava/lang/StackTraceElement;)Lscala/Option;
  #156 = InterfaceMethodref #2.#155       // org/scalatest/exceptions/StackDepth.$anonfun$failedCodeFileName$1:(Ljava/lang/StackTraceElement;)Lscala/Option;
  #157 = MethodHandle       6:#156        // REF_invokeStatic org/scalatest/exceptions/StackDepth.$anonfun$failedCodeFileName$1:(Ljava/lang/StackTraceElement;)Lscala/Option;
  #158 = MethodType         #154          //  (Ljava/lang/StackTraceElement;)Lscala/Option;
  #159 = Utf8               ()Lscala/Function1;
  #160 = NameAndType        #52:#159      // apply:()Lscala/Function1;
  #161 = InvokeDynamic      #3:#160       // #3:apply:()Lscala/Function1;
  #162 = Utf8               failedCodeLineNumber$
  #163 = Utf8               failedCodeLineNumber
  #164 = NameAndType        #163:#15      // failedCodeLineNumber:()Lscala/Option;
  #165 = InterfaceMethodref #2.#164       // org/scalatest/exceptions/StackDepth.failedCodeLineNumber:()Lscala/Option;
  #166 = Utf8               ()Lscala/Option<Ljava/lang/Object;>;
  #167 = Utf8               lineNumber
  #168 = NameAndType        #167:#20      // lineNumber:()I
  #169 = Methodref          #91.#168      // org/scalactic/source/Position.lineNumber:()I
  #170 = Utf8               scala/runtime/BoxesRunTime
  #171 = Class              #170          // scala/runtime/BoxesRunTime
  #172 = Utf8               boxToInteger
  #173 = Utf8               (I)Ljava/lang/Integer;
  #174 = NameAndType        #172:#173     // boxToInteger:(I)Ljava/lang/Integer;
  #175 = Methodref          #171.#174     // scala/runtime/BoxesRunTime.boxToInteger:(I)Ljava/lang/Integer;
  #176 = Utf8               $anonfun$failedCodeLineNumber$1
  #177 = NameAndType        #176:#154     // $anonfun$failedCodeLineNumber$1:(Ljava/lang/StackTraceElement;)Lscala/Option;
  #178 = InterfaceMethodref #2.#177       // org/scalatest/exceptions/StackDepth.$anonfun$failedCodeLineNumber$1:(Ljava/lang/StackTraceElement;)Lscala/Option;
  #179 = MethodHandle       6:#178        // REF_invokeStatic org/scalatest/exceptions/StackDepth.$anonfun$failedCodeLineNumber$1:(Ljava/lang/StackTraceElement;)Lscala/Option;
  #180 = InvokeDynamic      #4:#160       // #4:apply:()Lscala/Function1;
  #181 = Utf8               severedAtStackDepth
  #182 = Utf8               ()Ljava/lang/Throwable;
  #183 = Utf8               $anonfun$failedCodeFileNameAndLineNumberString$2
  #184 = Utf8               (Ljava/lang/String;I)Ljava/lang/String;
  #185 = Utf8               fileName$1
  #186 = Utf8               lineNum
  #187 = Utf8               java/lang/StringBuilder
  #188 = Class              #187          // java/lang/StringBuilder
  #189 = Utf8               (I)V
  #190 = NameAndType        #134:#189     // "<init>":(I)V
  #191 = Methodref          #188.#190     // java/lang/StringBuilder."<init>":(I)V
  #192 = Utf8               append
  #193 = Utf8               (Ljava/lang/String;)Ljava/lang/StringBuilder;
  #194 = NameAndType        #192:#193     // append:(Ljava/lang/String;)Ljava/lang/StringBuilder;
  #195 = Methodref          #188.#194     // java/lang/StringBuilder.append:(Ljava/lang/String;)Ljava/lang/StringBuilder;
  #196 = Utf8               :
  #197 = String             #196          // :
  #198 = Utf8               (I)Ljava/lang/StringBuilder;
  #199 = NameAndType        #192:#198     // append:(I)Ljava/lang/StringBuilder;
  #200 = Methodref          #188.#199     // java/lang/StringBuilder.append:(I)Ljava/lang/StringBuilder;
  #201 = Utf8               toString
  #202 = NameAndType        #201:#148     // toString:()Ljava/lang/String;
  #203 = Methodref          #188.#202     // java/lang/StringBuilder.toString:()Ljava/lang/String;
  #204 = Utf8               Ljava/lang/String;
  #205 = Utf8               I
  #206 = Utf8               $anonfun$failedCodeFileNameAndLineNumberString$2$adapted
  #207 = Utf8               (Ljava/lang/String;Ljava/lang/Object;)Ljava/lang/String;
  #208 = NameAndType        #206:#207     // $anonfun$failedCodeFileNameAndLineNumberString$2$adapted:(Ljava/lang/String;Ljava/lang/Object;)Ljava/lang/String;
  #209 = InterfaceMethodref #2.#208       // org/scalatest/exceptions/StackDepth.$anonfun$failedCodeFileNameAndLineNumberString$2$adapted:(Ljava/lang/String;Ljava/lang/Object;)Ljava/lang/String;
  #210 = MethodHandle       6:#209        // REF_invokeStatic org/scalatest/exceptions/StackDepth.$anonfun$failedCodeFileNameAndLineNumberString$2$adapted:(Ljava/lang/String;Ljava/lang/Object;)Ljava/lang/String;
  #211 = Utf8               (Ljava/lang/Object;)Ljava/lang/String;
  #212 = MethodType         #211          //  (Ljava/lang/Object;)Ljava/lang/String;
  #213 = Utf8               (Ljava/lang/String;)Lscala/Function1;
  #214 = NameAndType        #52:#213      // apply:(Ljava/lang/String;)Lscala/Function1;
  #215 = InvokeDynamic      #5:#214       // #5:apply:(Ljava/lang/String;)Lscala/Function1;
  #216 = Utf8               map
  #217 = NameAndType        #216:#59      // map:(Lscala/Function1;)Lscala/Option;
  #218 = Methodref          #57.#217      // scala/Option.map:(Lscala/Function1;)Lscala/Option;
  #219 = Utf8               $anonfun$failedCodeFilePathnameAndLineNumberString$2
  #220 = Utf8               fileName$2
  #221 = Utf8               $anonfun$failedCodeFilePathnameAndLineNumberString$2$adapted
  #222 = NameAndType        #221:#207     // $anonfun$failedCodeFilePathnameAndLineNumberString$2$adapted:(Ljava/lang/String;Ljava/lang/Object;)Ljava/lang/String;
  #223 = InterfaceMethodref #2.#222       // org/scalatest/exceptions/StackDepth.$anonfun$failedCodeFilePathnameAndLineNumberString$2$adapted:(Ljava/lang/String;Ljava/lang/Object;)Ljava/lang/String;
  #224 = MethodHandle       6:#223        // REF_invokeStatic org/scalatest/exceptions/StackDepth.$anonfun$failedCodeFilePathnameAndLineNumberString$2$adapted:(Ljava/lang/String;Ljava/lang/Object;)Ljava/lang/String;
  #225 = InvokeDynamic      #6:#214       // #6:apply:(Ljava/lang/String;)Lscala/Function1;
  #226 = Utf8               $anonfun$stackTraceElement$1
  #227 = Utf8               (Lorg/scalactic/source/Position;Ljava/lang/StackTraceElement;)Z
  #228 = Utf8               pos$1
  #229 = Utf8               e
  #230 = Utf8               org/scalatest/exceptions/StackDepthExceptionHelper$
  #231 = Class              #230          // org/scalatest/exceptions/StackDepthExceptionHelper$
  #232 = Utf8               Lorg/scalatest/exceptions/StackDepthExceptionHelper$;
  #233 = NameAndType        #94:#232      // MODULE$:Lorg/scalatest/exceptions/StackDepthExceptionHelper$;
  #234 = Fieldref           #231.#233     // org/scalatest/exceptions/StackDepthExceptionHelper$.MODULE$:Lorg/scalatest/exceptions/StackDepthExceptionHelper$;
  #235 = Utf8               isMatch
  #236 = Utf8               (Ljava/lang/StackTraceElement;Lorg/scalactic/source/Position;)Z
  #237 = NameAndType        #235:#236     // isMatch:(Ljava/lang/StackTraceElement;Lorg/scalactic/source/Position;)Z
  #238 = Methodref          #231.#237     // org/scalatest/exceptions/StackDepthExceptionHelper$.isMatch:(Ljava/lang/StackTraceElement;Lorg/scalactic/source/Position;)Z
  #239 = Utf8               Ljava/lang/StackTraceElement;
  #240 = Utf8               ele
  #241 = Utf8               getFailedCodeFileName
  #242 = NameAndType        #241:#154     // getFailedCodeFileName:(Ljava/lang/StackTraceElement;)Lscala/Option;
  #243 = Methodref          #231.#242     // org/scalatest/exceptions/StackDepthExceptionHelper$.getFailedCodeFileName:(Ljava/lang/StackTraceElement;)Lscala/Option;
  #244 = Utf8               java/lang/StackTraceElement
  #245 = Class              #244          // java/lang/StackTraceElement
  #246 = Utf8               getLineNumber
  #247 = NameAndType        #246:#20      // getLineNumber:()I
  #248 = Methodref          #245.#247     // java/lang/StackTraceElement.getLineNumber:()I
  #249 = Utf8               $init$
  #250 = Utf8               (Lorg/scalatest/exceptions/StackDepth;)V
  #251 = NameAndType        #226:#227     // $anonfun$stackTraceElement$1:(Lorg/scalactic/source/Position;Ljava/lang/StackTraceElement;)Z
  #252 = InterfaceMethodref #2.#251       // org/scalatest/exceptions/StackDepth.$anonfun$stackTraceElement$1:(Lorg/scalactic/source/Position;Ljava/lang/StackTraceElement;)Z
  #253 = Utf8               boxToBoolean
  #254 = Utf8               (Z)Ljava/lang/Boolean;
  #255 = NameAndType        #253:#254     // boxToBoolean:(Z)Ljava/lang/Boolean;
  #256 = Methodref          #171.#255     // scala/runtime/BoxesRunTime.boxToBoolean:(Z)Ljava/lang/Boolean;
  #257 = Utf8               unboxToInt
  #258 = Utf8               (Ljava/lang/Object;)I
  #259 = NameAndType        #257:#258     // unboxToInt:(Ljava/lang/Object;)I
  #260 = Methodref          #171.#259     // scala/runtime/BoxesRunTime.unboxToInt:(Ljava/lang/Object;)I
  #261 = NameAndType        #183:#184     // $anonfun$failedCodeFileNameAndLineNumberString$2:(Ljava/lang/String;I)Ljava/lang/String;
  #262 = InterfaceMethodref #2.#261       // org/scalatest/exceptions/StackDepth.$anonfun$failedCodeFileNameAndLineNumberString$2:(Ljava/lang/String;I)Ljava/lang/String;
  #263 = Utf8               Ljava/lang/Object;
  #264 = NameAndType        #219:#184     // $anonfun$failedCodeFilePathnameAndLineNumberString$2:(Ljava/lang/String;I)Ljava/lang/String;
  #265 = InterfaceMethodref #2.#264       // org/scalatest/exceptions/StackDepth.$anonfun$failedCodeFilePathnameAndLineNumberString$2:(Ljava/lang/String;I)Ljava/lang/String;
  #266 = Utf8               $deserializeLambda$
  #267 = Utf8               (Ljava/lang/invoke/SerializedLambda;)Ljava/lang/Object;
  #268 = Utf8               scala/runtime/LambdaDeserialize
  #269 = Class              #268          // scala/runtime/LambdaDeserialize
  #270 = Utf8               bootstrap
  #271 = Utf8               (Ljava/lang/invoke/MethodHandles$Lookup;Ljava/lang/String;Ljava/lang/invoke/MethodType;[Ljava/lang/invoke/MethodHandle;)Ljava/lang/invoke/CallSite;
  #272 = NameAndType        #270:#271     // bootstrap:(Ljava/lang/invoke/MethodHandles$Lookup;Ljava/lang/String;Ljava/lang/invoke/MethodType;[Ljava/lang/invoke/MethodHandle;)Ljava/lang/invoke/CallSite;
  #273 = Methodref          #269.#272     // scala/runtime/LambdaDeserialize.bootstrap:(Ljava/lang/invoke/MethodHandles$Lookup;Ljava/lang/String;Ljava/lang/invoke/MethodType;[Ljava/lang/invoke/MethodHandle;)Ljava/lang/invoke/CallSite;
  #274 = MethodHandle       6:#273        // REF_invokeStatic scala/runtime/LambdaDeserialize.bootstrap:(Ljava/lang/invoke/MethodHandles$Lookup;Ljava/lang/String;Ljava/lang/invoke/MethodType;[Ljava/lang/invoke/MethodHandle;)Ljava/lang/invoke/CallSite;
  #275 = Utf8               lambdaDeserialize
  #276 = NameAndType        #275:#267     // lambdaDeserialize:(Ljava/lang/invoke/SerializedLambda;)Ljava/lang/Object;
  #277 = InvokeDynamic      #7:#276       // #7:lambdaDeserialize:(Ljava/lang/invoke/SerializedLambda;)Ljava/lang/Object;
  #278 = Utf8               Signature
  #279 = Utf8               Code
  #280 = Utf8               LineNumberTable
  #281 = Utf8               LocalVariableTable
  #282 = Utf8               MethodParameters
  #283 = Utf8               StackMapTable
  #284 = Utf8               InnerClasses
  #285 = Utf8               SourceFile
  #286 = Utf8               RuntimeVisibleAnnotations
  #287 = Utf8               BootstrapMethods
  #288 = Utf8               ScalaInlineInfo
  #289 = Utf8               ScalaSig
{
  public abstract scala.Option<java.lang.String> message();
    descriptor: ()Lscala/Option;
    flags: (0x0401) ACC_PUBLIC, ACC_ABSTRACT
    Signature: #16                          // ()Lscala/Option<Ljava/lang/String;>;

  public abstract scala.Option<java.lang.Throwable> cause();
    descriptor: ()Lscala/Option;
    flags: (0x0401) ACC_PUBLIC, ACC_ABSTRACT
    Signature: #18                          // ()Lscala/Option<Ljava/lang/Throwable;>;

  public abstract int failedCodeStackDepth();
    descriptor: ()I
    flags: (0x0401) ACC_PUBLIC, ACC_ABSTRACT

  public abstract scala.Option<java.lang.String> failedCodeFilePathname();
    descriptor: ()Lscala/Option;
    flags: (0x0401) ACC_PUBLIC, ACC_ABSTRACT
    Signature: #16                          // ()Lscala/Option<Ljava/lang/String;>;

  public abstract scala.Option<org.scalactic.source.Position> position();
    descriptor: ()Lscala/Option;
    flags: (0x0401) ACC_PUBLIC, ACC_ABSTRACT
    Signature: #23                          // ()Lscala/Option<Lorg/scalactic/source/Position;>;

  public static scala.Option failedCodeFileNameAndLineNumberString$(org.scalatest.exceptions.StackDepth);
    descriptor: (Lorg/scalatest/exceptions/StackDepth;)Lscala/Option;
    flags: (0x1009) ACC_PUBLIC, ACC_STATIC, ACC_SYNTHETIC
    Code:
      stack=1, locals=1, args_size=1
         0: aload_0
         1: invokespecial #29                 // InterfaceMethod failedCodeFileNameAndLineNumberString:()Lscala/Option;
         4: areturn
      LineNumberTable:
        line 75: 0
      LocalVariableTable:
        Start  Length  Slot  Name   Signature
            0       5     0 $this   Lorg/scalatest/exceptions/StackDepth;
    MethodParameters:
      Name                           Flags
      $this                          final synthetic

  public default scala.Option<java.lang.String> failedCodeFileNameAndLineNumberString();
    descriptor: ()Lscala/Option;
    flags: (0x0001) ACC_PUBLIC
    Code:
      stack=2, locals=1, args_size=1
         0: aload_0
         1: invokeinterface #33,  1           // InterfaceMethod failedCodeFileName:()Lscala/Option;
         6: aload_0
         7: invokedynamic #55,  0             // InvokeDynamic #0:apply:(Lorg/scalatest/exceptions/StackDepth;)Lscala/Function1;
        12: invokevirtual #61                 // Method scala/Option.flatMap:(Lscala/Function1;)Lscala/Option;
        15: areturn
      LineNumberTable:
        line 76: 0
      LocalVariableTable:
        Start  Length  Slot  Name   Signature
            0      16     0  this   Lorg/scalatest/exceptions/StackDepth;
    Signature: #16                          // ()Lscala/Option<Ljava/lang/String;>;

  public static scala.Option failedCodeFilePathnameAndLineNumberString$(org.scalatest.exceptions.StackDepth);
    descriptor: (Lorg/scalatest/exceptions/StackDepth;)Lscala/Option;
    flags: (0x1009) ACC_PUBLIC, ACC_STATIC, ACC_SYNTHETIC
    Code:
      stack=1, locals=1, args_size=1
         0: aload_0
         1: invokespecial #66                 // InterfaceMethod failedCodeFilePathnameAndLineNumberString:()Lscala/Option;
         4: areturn
      LineNumberTable:
        line 87: 0
      LocalVariableTable:
        Start  Length  Slot  Name   Signature
            0       5     0 $this   Lorg/scalatest/exceptions/StackDepth;
    MethodParameters:
      Name                           Flags
      $this                          final synthetic

  public default scala.Option<java.lang.String> failedCodeFilePathnameAndLineNumberString();
    descriptor: ()Lscala/Option;
    flags: (0x0001) ACC_PUBLIC
    Code:
      stack=2, locals=1, args_size=1
         0: aload_0
         1: invokeinterface #68,  1           // InterfaceMethod failedCodeFilePathname:()Lscala/Option;
         6: aload_0
         7: invokedynamic #73,  0             // InvokeDynamic #1:apply:(Lorg/scalatest/exceptions/StackDepth;)Lscala/Function1;
        12: invokevirtual #61                 // Method scala/Option.flatMap:(Lscala/Function1;)Lscala/Option;
        15: areturn
      LineNumberTable:
        line 88: 0
      LocalVariableTable:
        Start  Length  Slot  Name   Signature
            0      16     0  this   Lorg/scalatest/exceptions/StackDepth;
    Signature: #16                          // ()Lscala/Option<Ljava/lang/String;>;

  private scala.Option<java.lang.StackTraceElement> stackTraceElement();
    descriptor: ()Lscala/Option;
    flags: (0x0002) ACC_PRIVATE
    Code:
      stack=4, locals=6, args_size=1
         0: aload_0
         1: checkcast     #77                 // class java/lang/Throwable
         4: invokevirtual #81                 // Method java/lang/Throwable.getStackTrace:()[Ljava/lang/StackTraceElement;
         7: astore_2
         8: aload_0
         9: invokeinterface #83,  1           // InterfaceMethod position:()Lscala/Option;
        14: astore_3
        15: aload_3
        16: instanceof    #85                 // class scala/Some
        19: ifeq          65
        22: aload_3
        23: checkcast     #85                 // class scala/Some
        26: astore        4
        28: aload         4
        30: invokevirtual #89                 // Method scala/Some.value:()Ljava/lang/Object;
        33: checkcast     #91                 // class org/scalactic/source/Position
        36: astore        5
        38: getstatic     #97                 // Field scala/collection/ArrayOps$.MODULE$:Lscala/collection/ArrayOps$;
        41: getstatic     #102                // Field scala/Predef$.MODULE$:Lscala/Predef$;
        44: aload_2
        45: checkcast     #104                // class "[Ljava/lang/Object;"
        48: invokevirtual #108                // Method scala/Predef$.refArrayOps:([Ljava/lang/Object;)Ljava/lang/Object;
        51: aload         5
        53: invokedynamic #118,  0            // InvokeDynamic #2:apply:(Lorg/scalactic/source/Position;)Lscala/Function1;
        58: invokevirtual #122                // Method scala/collection/ArrayOps$.find$extension:(Ljava/lang/Object;Lscala/Function1;)Lscala/Option;
        61: astore_1
        62: goto          126
        65: goto          68
        68: getstatic     #127                // Field scala/None$.MODULE$:Lscala/None$;
        71: aload_3
        72: invokevirtual #131                // Method java/lang/Object.equals:(Ljava/lang/Object;)Z
        75: ifeq          114
        78: aload_2
        79: arraylength
        80: aload_0
        81: invokeinterface #133,  1          // InterfaceMethod failedCodeStackDepth:()I
        86: if_icmpgt     95
        89: getstatic     #127                // Field scala/None$.MODULE$:Lscala/None$;
        92: goto          110
        95: new           #85                 // class scala/Some
        98: dup
        99: aload_2
       100: aload_0
       101: invokeinterface #133,  1          // InterfaceMethod failedCodeStackDepth:()I
       106: aaload
       107: invokespecial #137                // Method scala/Some."<init>":(Ljava/lang/Object;)V
       110: astore_1
       111: goto          126
       114: goto          117
       117: new           #139                // class scala/MatchError
       120: dup
       121: aload_3
       122: invokespecial #140                // Method scala/MatchError."<init>":(Ljava/lang/Object;)V
       125: athrow
       126: aload_1
       127: areturn
      StackMapTable: number_of_entries = 7
        frame_type = 254 /* append */
          offset_delta = 65
          locals = [ top, class "[Ljava/lang/StackTraceElement;", class scala/Option ]
        frame_type = 2 /* same */
        frame_type = 26 /* same */
        frame_type = 78 /* same_locals_1_stack_item */
          stack = [ class scala/Option ]
        frame_type = 3 /* same */
        frame_type = 2 /* same */
        frame_type = 255 /* full_frame */
          offset_delta = 8
          locals = [ class org/scalatest/exceptions/StackDepth, class scala/Option, class "[Ljava/lang/StackTraceElement;", class scala/Option ]
          stack = []
      LineNumberTable:
        line 93: 0
        line 94: 8
        line 95: 15
        line 96: 68
        line 97: 78
        line 98: 95
        line 96: 114
        line 94: 117
      LocalVariableTable:
        Start  Length  Slot  Name   Signature
           38      27     5   pos   Lorg/scalactic/source/Position;
            8     119     2 stackTrace   [Ljava/lang/StackTraceElement;
            0     128     0  this   Lorg/scalatest/exceptions/StackDepth;
    Signature: #75                          // ()Lscala/Option<Ljava/lang/StackTraceElement;>;

  public static scala.Option failedCodeFileName$(org.scalatest.exceptions.StackDepth);
    descriptor: (Lorg/scalatest/exceptions/StackDepth;)Lscala/Option;
    flags: (0x1009) ACC_PUBLIC, ACC_STATIC, ACC_SYNTHETIC
    Code:
      stack=1, locals=1, args_size=1
         0: aload_0
         1: invokespecial #33                 // InterfaceMethod failedCodeFileName:()Lscala/Option;
         4: areturn
      LineNumberTable:
        line 114: 0
      LocalVariableTable:
        Start  Length  Slot  Name   Signature
            0       5     0 $this   Lorg/scalatest/exceptions/StackDepth;
    MethodParameters:
      Name                           Flags
      $this                          final synthetic

  public default scala.Option<java.lang.String> failedCodeFileName();
    descriptor: ()Lscala/Option;
    flags: (0x0001) ACC_PUBLIC
    Code:
      stack=3, locals=5, args_size=1
         0: aload_0
         1: invokeinterface #83,  1           // InterfaceMethod position:()Lscala/Option;
         6: astore_2
         7: aload_2
         8: instanceof    #85                 // class scala/Some
        11: ifeq          44
        14: aload_2
        15: checkcast     #85                 // class scala/Some
        18: astore_3
        19: aload_3
        20: invokevirtual #89                 // Method scala/Some.value:()Ljava/lang/Object;
        23: checkcast     #91                 // class org/scalactic/source/Position
        26: astore        4
        28: new           #85                 // class scala/Some
        31: dup
        32: aload         4
        34: invokevirtual #150                // Method org/scalactic/source/Position.fileName:()Ljava/lang/String;
        37: invokespecial #137                // Method scala/Some."<init>":(Ljava/lang/Object;)V
        40: astore_1
        41: goto          85
        44: goto          47
        47: getstatic     #127                // Field scala/None$.MODULE$:Lscala/None$;
        50: aload_2
        51: invokevirtual #131                // Method java/lang/Object.equals:(Ljava/lang/Object;)Z
        54: ifeq          73
        57: aload_0
        58: invokespecial #152                // InterfaceMethod stackTraceElement:()Lscala/Option;
        61: invokedynamic #161,  0            // InvokeDynamic #3:apply:()Lscala/Function1;
        66: invokevirtual #61                 // Method scala/Option.flatMap:(Lscala/Function1;)Lscala/Option;
        69: astore_1
        70: goto          85
        73: goto          76
        76: new           #139                // class scala/MatchError
        79: dup
        80: aload_2
        81: invokespecial #140                // Method scala/MatchError."<init>":(Ljava/lang/Object;)V
        84: athrow
        85: aload_1
        86: areturn
      StackMapTable: number_of_entries = 5
        frame_type = 253 /* append */
          offset_delta = 44
          locals = [ top, class scala/Option ]
        frame_type = 2 /* same */
        frame_type = 25 /* same */
        frame_type = 2 /* same */
        frame_type = 255 /* full_frame */
          offset_delta = 8
          locals = [ class org/scalatest/exceptions/StackDepth, class scala/Option, class scala/Option ]
          stack = []
      LineNumberTable:
        line 115: 0
        line 116: 7
        line 117: 47
        line 118: 57
        line 117: 73
        line 115: 76
      LocalVariableTable:
        Start  Length  Slot  Name   Signature
           28      16     4   pos   Lorg/scalactic/source/Position;
            0      87     0  this   Lorg/scalatest/exceptions/StackDepth;
    Signature: #16                          // ()Lscala/Option<Ljava/lang/String;>;

  public static scala.Option failedCodeLineNumber$(org.scalatest.exceptions.StackDepth);
    descriptor: (Lorg/scalatest/exceptions/StackDepth;)Lscala/Option;
    flags: (0x1009) ACC_PUBLIC, ACC_STATIC, ACC_SYNTHETIC
    Code:
      stack=1, locals=1, args_size=1
         0: aload_0
         1: invokespecial #165                // InterfaceMethod failedCodeLineNumber:()Lscala/Option;
         4: areturn
      LineNumberTable:
        line 136: 0
      LocalVariableTable:
        Start  Length  Slot  Name   Signature
            0       5     0 $this   Lorg/scalatest/exceptions/StackDepth;
    MethodParameters:
      Name                           Flags
      $this                          final synthetic

  public default scala.Option<java.lang.Object> failedCodeLineNumber();
    descriptor: ()Lscala/Option;
    flags: (0x0001) ACC_PUBLIC
    Code:
      stack=3, locals=5, args_size=1
         0: aload_0
         1: invokeinterface #83,  1           // InterfaceMethod position:()Lscala/Option;
         6: astore_2
         7: aload_2
         8: instanceof    #85                 // class scala/Some
        11: ifeq          47
        14: aload_2
        15: checkcast     #85                 // class scala/Some
        18: astore_3
        19: aload_3
        20: invokevirtual #89                 // Method scala/Some.value:()Ljava/lang/Object;
        23: checkcast     #91                 // class org/scalactic/source/Position
        26: astore        4
        28: new           #85                 // class scala/Some
        31: dup
        32: aload         4
        34: invokevirtual #169                // Method org/scalactic/source/Position.lineNumber:()I
        37: invokestatic  #175                // Method scala/runtime/BoxesRunTime.boxToInteger:(I)Ljava/lang/Integer;
        40: invokespecial #137                // Method scala/Some."<init>":(Ljava/lang/Object;)V
        43: astore_1
        44: goto          88
        47: goto          50
        50: getstatic     #127                // Field scala/None$.MODULE$:Lscala/None$;
        53: aload_2
        54: invokevirtual #131                // Method java/lang/Object.equals:(Ljava/lang/Object;)Z
        57: ifeq          76
        60: aload_0
        61: invokespecial #152                // InterfaceMethod stackTraceElement:()Lscala/Option;
        64: invokedynamic #180,  0            // InvokeDynamic #4:apply:()Lscala/Function1;
        69: invokevirtual #61                 // Method scala/Option.flatMap:(Lscala/Function1;)Lscala/Option;
        72: astore_1
        73: goto          88
        76: goto          79
        79: new           #139                // class scala/MatchError
        82: dup
        83: aload_2
        84: invokespecial #140                // Method scala/MatchError."<init>":(Ljava/lang/Object;)V
        87: athrow
        88: aload_1
        89: areturn
      StackMapTable: number_of_entries = 5
        frame_type = 253 /* append */
          offset_delta = 47
          locals = [ top, class scala/Option ]
        frame_type = 2 /* same */
        frame_type = 25 /* same */
        frame_type = 2 /* same */
        frame_type = 255 /* full_frame */
          offset_delta = 8
          locals = [ class org/scalatest/exceptions/StackDepth, class scala/Option, class scala/Option ]
          stack = []
      LineNumberTable:
        line 137: 0
        line 138: 7
        line 139: 50
        line 140: 60
        line 139: 76
        line 137: 79
      LocalVariableTable:
        Start  Length  Slot  Name   Signature
           28      19     4   pos   Lorg/scalactic/source/Position;
            0      90     0  this   Lorg/scalatest/exceptions/StackDepth;
    Signature: #166                         // ()Lscala/Option<Ljava/lang/Object;>;

  public abstract java.lang.Throwable severedAtStackDepth();
    descriptor: ()Ljava/lang/Throwable;
    flags: (0x0401) ACC_PUBLIC, ACC_ABSTRACT

  public static java.lang.String $anonfun$failedCodeFileNameAndLineNumberString$2(java.lang.String, int);
    descriptor: (Ljava/lang/String;I)Ljava/lang/String;
    flags: (0x1009) ACC_PUBLIC, ACC_STATIC, ACC_SYNTHETIC
    Code:
      stack=3, locals=2, args_size=2
         0: new           #188                // class java/lang/StringBuilder
         3: dup
         4: ldc           #44                 // int 1
         6: invokespecial #191                // Method java/lang/StringBuilder."<init>":(I)V
         9: aload_0
        10: invokevirtual #195                // Method java/lang/StringBuilder.append:(Ljava/lang/String;)Ljava/lang/StringBuilder;
        13: ldc           #197                // String :
        15: invokevirtual #195                // Method java/lang/StringBuilder.append:(Ljava/lang/String;)Ljava/lang/StringBuilder;
        18: iload_1
        19: invokevirtual #200                // Method java/lang/StringBuilder.append:(I)Ljava/lang/StringBuilder;
        22: invokevirtual #203                // Method java/lang/StringBuilder.toString:()Ljava/lang/String;
        25: areturn
      LineNumberTable:
        line 77: 0
      LocalVariableTable:
        Start  Length  Slot  Name   Signature
            0      26     0 fileName$1   Ljava/lang/String;
            0      26     1 lineNum   I
    MethodParameters:
      Name                           Flags
      fileName$1                     final
      lineNum                        final

  public static scala.Option $anonfun$failedCodeFileNameAndLineNumberString$1(org.scalatest.exceptions.StackDepth, java.lang.String);
    descriptor: (Lorg/scalatest/exceptions/StackDepth;Ljava/lang/String;)Lscala/Option;
    flags: (0x1009) ACC_PUBLIC, ACC_STATIC, ACC_SYNTHETIC
    Code:
      stack=2, locals=2, args_size=2
         0: aload_0
         1: invokeinterface #165,  1          // InterfaceMethod failedCodeLineNumber:()Lscala/Option;
         6: aload_1
         7: invokedynamic #215,  0            // InvokeDynamic #5:apply:(Ljava/lang/String;)Lscala/Function1;
        12: invokevirtual #218                // Method scala/Option.map:(Lscala/Function1;)Lscala/Option;
        15: areturn
      LineNumberTable:
        line 76: 0
      LocalVariableTable:
        Start  Length  Slot  Name   Signature
            0      16     0 $this   Lorg/scalatest/exceptions/StackDepth;
            0      16     1 fileName   Ljava/lang/String;
    MethodParameters:
      Name                           Flags
      $this                          final synthetic
      fileName                       final

  public static java.lang.String $anonfun$failedCodeFilePathnameAndLineNumberString$2(java.lang.String, int);
    descriptor: (Ljava/lang/String;I)Ljava/lang/String;
    flags: (0x1009) ACC_PUBLIC, ACC_STATIC, ACC_SYNTHETIC
    Code:
      stack=3, locals=2, args_size=2
         0: new           #188                // class java/lang/StringBuilder
         3: dup
         4: ldc           #44                 // int 1
         6: invokespecial #191                // Method java/lang/StringBuilder."<init>":(I)V
         9: aload_0
        10: invokevirtual #195                // Method java/lang/StringBuilder.append:(Ljava/lang/String;)Ljava/lang/StringBuilder;
        13: ldc           #197                // String :
        15: invokevirtual #195                // Method java/lang/StringBuilder.append:(Ljava/lang/String;)Ljava/lang/StringBuilder;
        18: iload_1
        19: invokevirtual #200                // Method java/lang/StringBuilder.append:(I)Ljava/lang/StringBuilder;
        22: invokevirtual #203                // Method java/lang/StringBuilder.toString:()Ljava/lang/String;
        25: areturn
      LineNumberTable:
        line 89: 0
      LocalVariableTable:
        Start  Length  Slot  Name   Signature
            0      26     0 fileName$2   Ljava/lang/String;
            0      26     1 lineNum   I
    MethodParameters:
      Name                           Flags
      fileName$2                     final
      lineNum                        final

  public static scala.Option $anonfun$failedCodeFilePathnameAndLineNumberString$1(org.scalatest.exceptions.StackDepth, java.lang.String);
    descriptor: (Lorg/scalatest/exceptions/StackDepth;Ljava/lang/String;)Lscala/Option;
    flags: (0x1009) ACC_PUBLIC, ACC_STATIC, ACC_SYNTHETIC
    Code:
      stack=2, locals=2, args_size=2
         0: aload_0
         1: invokeinterface #165,  1          // InterfaceMethod failedCodeLineNumber:()Lscala/Option;
         6: aload_1
         7: invokedynamic #225,  0            // InvokeDynamic #6:apply:(Ljava/lang/String;)Lscala/Function1;
        12: invokevirtual #218                // Method scala/Option.map:(Lscala/Function1;)Lscala/Option;
        15: areturn
      LineNumberTable:
        line 88: 0
      LocalVariableTable:
        Start  Length  Slot  Name   Signature
            0      16     0 $this   Lorg/scalatest/exceptions/StackDepth;
            0      16     1 fileName   Ljava/lang/String;
    MethodParameters:
      Name                           Flags
      $this                          final synthetic
      fileName                       final

  public static boolean $anonfun$stackTraceElement$1(org.scalactic.source.Position, java.lang.StackTraceElement);
    descriptor: (Lorg/scalactic/source/Position;Ljava/lang/StackTraceElement;)Z
    flags: (0x1009) ACC_PUBLIC, ACC_STATIC, ACC_SYNTHETIC
    Code:
      stack=3, locals=2, args_size=2
         0: getstatic     #234                // Field org/scalatest/exceptions/StackDepthExceptionHelper$.MODULE$:Lorg/scalatest/exceptions/StackDepthExceptionHelper$;
         3: aload_1
         4: aload_0
         5: invokevirtual #238                // Method org/scalatest/exceptions/StackDepthExceptionHelper$.isMatch:(Ljava/lang/StackTraceElement;Lorg/scalactic/source/Position;)Z
         8: ireturn
      LineNumberTable:
        line 95: 0
      LocalVariableTable:
        Start  Length  Slot  Name   Signature
            0       9     0 pos$1   Lorg/scalactic/source/Position;
            0       9     1     e   Ljava/lang/StackTraceElement;
    MethodParameters:
      Name                           Flags
      pos$1                          final
      e                              final

  public static scala.Option $anonfun$failedCodeFileName$1(java.lang.StackTraceElement);
    descriptor: (Ljava/lang/StackTraceElement;)Lscala/Option;
    flags: (0x1009) ACC_PUBLIC, ACC_STATIC, ACC_SYNTHETIC
    Code:
      stack=2, locals=1, args_size=1
         0: getstatic     #234                // Field org/scalatest/exceptions/StackDepthExceptionHelper$.MODULE$:Lorg/scalatest/exceptions/StackDepthExceptionHelper$;
         3: aload_0
         4: invokevirtual #243                // Method org/scalatest/exceptions/StackDepthExceptionHelper$.getFailedCodeFileName:(Ljava/lang/StackTraceElement;)Lscala/Option;
         7: areturn
      LineNumberTable:
        line 119: 0
      LocalVariableTable:
        Start  Length  Slot  Name   Signature
            0       8     0   ele   Ljava/lang/StackTraceElement;
    MethodParameters:
      Name                           Flags
      ele                            final

  public static scala.Option $anonfun$failedCodeLineNumber$1(java.lang.StackTraceElement);
    descriptor: (Ljava/lang/StackTraceElement;)Lscala/Option;
    flags: (0x1009) ACC_PUBLIC, ACC_STATIC, ACC_SYNTHETIC
    Code:
      stack=3, locals=2, args_size=1
         0: aload_0
         1: invokevirtual #248                // Method java/lang/StackTraceElement.getLineNumber:()I
         4: istore_1
         5: iload_1
         6: iconst_0
         7: if_icmple     24
        10: new           #85                 // class scala/Some
        13: dup
        14: iload_1
        15: invokestatic  #175                // Method scala/runtime/BoxesRunTime.boxToInteger:(I)Ljava/lang/Integer;
        18: invokespecial #137                // Method scala/Some."<init>":(Ljava/lang/Object;)V
        21: goto          27
        24: getstatic     #127                // Field scala/None$.MODULE$:Lscala/None$;
        27: areturn
      StackMapTable: number_of_entries = 2
        frame_type = 252 /* append */
          offset_delta = 24
          locals = [ int ]
        frame_type = 66 /* same_locals_1_stack_item */
          stack = [ class scala/Option ]
      LineNumberTable:
        line 141: 0
        line 142: 5
      LocalVariableTable:
        Start  Length  Slot  Name   Signature
            5      22     1 lineNum   I
            0      28     0   ele   Ljava/lang/StackTraceElement;
    MethodParameters:
      Name                           Flags
      ele                            final

  public static void $init$(org.scalatest.exceptions.StackDepth);
    descriptor: (Lorg/scalatest/exceptions/StackDepth;)V
    flags: (0x0009) ACC_PUBLIC, ACC_STATIC
    Code:
      stack=0, locals=1, args_size=1
         0: return
      LineNumberTable:
        line 31: 0
      LocalVariableTable:
        Start  Length  Slot  Name   Signature
            0       1     0 $this   Lorg/scalatest/exceptions/StackDepth;
    MethodParameters:
      Name                           Flags
      $this                          final synthetic

  public static java.lang.Object $anonfun$stackTraceElement$1$adapted(org.scalactic.source.Position, java.lang.StackTraceElement);
    descriptor: (Lorg/scalactic/source/Position;Ljava/lang/StackTraceElement;)Ljava/lang/Object;
    flags: (0x1009) ACC_PUBLIC, ACC_STATIC, ACC_SYNTHETIC
    Code:
      stack=2, locals=2, args_size=2
         0: aload_0
         1: aload_1
         2: invokestatic  #252                // InterfaceMethod $anonfun$stackTraceElement$1:(Lorg/scalactic/source/Position;Ljava/lang/StackTraceElement;)Z
         5: invokestatic  #256                // Method scala/runtime/BoxesRunTime.boxToBoolean:(Z)Ljava/lang/Boolean;
         8: areturn
      LineNumberTable:
        line 95: 0
      LocalVariableTable:
        Start  Length  Slot  Name   Signature
            0       9     0 pos$1   Lorg/scalactic/source/Position;
            0       9     1     e   Ljava/lang/StackTraceElement;
    MethodParameters:
      Name                           Flags
      pos$1                          final
      e                              final

  public static java.lang.String $anonfun$failedCodeFileNameAndLineNumberString$2$adapted(java.lang.String, java.lang.Object);
    descriptor: (Ljava/lang/String;Ljava/lang/Object;)Ljava/lang/String;
    flags: (0x1009) ACC_PUBLIC, ACC_STATIC, ACC_SYNTHETIC
    Code:
      stack=2, locals=2, args_size=2
         0: aload_0
         1: aload_1
         2: invokestatic  #260                // Method scala/runtime/BoxesRunTime.unboxToInt:(Ljava/lang/Object;)I
         5: invokestatic  #262                // InterfaceMethod $anonfun$failedCodeFileNameAndLineNumberString$2:(Ljava/lang/String;I)Ljava/lang/String;
         8: areturn
      LineNumberTable:
        line 76: 0
      LocalVariableTable:
        Start  Length  Slot  Name   Signature
            0       9     0 fileName$1   Ljava/lang/String;
            0       9     1 lineNum   Ljava/lang/Object;
    MethodParameters:
      Name                           Flags
      fileName$1                     final
      lineNum                        final

  public static java.lang.String $anonfun$failedCodeFilePathnameAndLineNumberString$2$adapted(java.lang.String, java.lang.Object);
    descriptor: (Ljava/lang/String;Ljava/lang/Object;)Ljava/lang/String;
    flags: (0x1009) ACC_PUBLIC, ACC_STATIC, ACC_SYNTHETIC
    Code:
      stack=2, locals=2, args_size=2
         0: aload_0
         1: aload_1
         2: invokestatic  #260                // Method scala/runtime/BoxesRunTime.unboxToInt:(Ljava/lang/Object;)I
         5: invokestatic  #265                // InterfaceMethod $anonfun$failedCodeFilePathnameAndLineNumberString$2:(Ljava/lang/String;I)Ljava/lang/String;
         8: areturn
      LineNumberTable:
        line 88: 0
      LocalVariableTable:
        Start  Length  Slot  Name   Signature
            0       9     0 fileName$2   Ljava/lang/String;
            0       9     1 lineNum   Ljava/lang/Object;
    MethodParameters:
      Name                           Flags
      fileName$2                     final
      lineNum                        final

  private static java.lang.Object $deserializeLambda$(java.lang.invoke.SerializedLambda);
    descriptor: (Ljava/lang/invoke/SerializedLambda;)Ljava/lang/Object;
    flags: (0x100a) ACC_PRIVATE, ACC_STATIC, ACC_SYNTHETIC
    Code:
      stack=1, locals=1, args_size=1
         0: aload_0
         1: invokedynamic #277,  0            // InvokeDynamic #7:lambdaDeserialize:(Ljava/lang/invoke/SerializedLambda;)Ljava/lang/Object;
         6: areturn
}
InnerClasses:
  public static final #13= #10 of #12;    // Lookup=class java/lang/invoke/MethodHandles$Lookup of class java/lang/invoke/MethodHandles
SourceFile: "StackDepth.scala"
RuntimeVisibleAnnotations:
  0: #6(#7=s#8)
    scala.reflect.ScalaSignature(
      bytes="\u0006\u0005!4\u0001\"\u0004\b\u0011\u0002\u0007\u0005QC\u001a\u0005\u00069\u0001!\t!\b\u0005\u0006C\u00011\tA\t\u0005\u0006c\u00011\tA\r\u0005\u0006{\u00011\tA\u0010\u0005\u0006\u0005\u00021\tA\t\u0005\u0006\u0007\u00021\t\u0001\u0012\u0005\u0006\u001d\u0002!\tA\t\u0005\t\u001f\u0002A)\u0019!C\u0001E!)\u0001\u000b\u0001C\u0005#\")1\f\u0001C\u0001E!)A\f\u0001C\u0001;\")q\f\u0001D\u0001A\nQ1\u000b^1dW\u0012+\u0007\u000f\u001e5\u000b\u0005=\u0001\u0012AC3yG\u0016\u0004H/[8og*\u0011\u0011CE\u0001\ng\u000e\fG.\u0019;fgRT\u0011aE\u0001\u0004_J<7\u0001A\n\u0003\u0001Y\u0001\"a\u0006\u000e\u000e\u0003aQ\u0011!G\u0001\u0006g\u000e\fG.Y\u0005\u00037a\u0011a!\u00118z%\u00164\u0017A\u0002\u0013j]&$H\u0005F\u0001\u001f!\t9r$\u0003\u0002!1\t!QK\\5u\u0003\u001diWm]:bO\u0016,\u0012a\t\t\u0004/\u00112\u0013BA\u0013\u0019\u0005\u0019y\u0005\u000f^5p]B\u0011qE\f\b\u0003Q1\u0002\"!\u000b\r\u000e\u0003)R!a\u000b\u000b\u0002\rq\u0012xn\u001c;?\u0013\ti\u0003$\u0001\u0004Qe\u0016$WMZ\u0005\u0003_A\u0012aa\u0015;sS:<\'BA\u0017\u0019\u0003\u0015\u0019\u0017-^:f+\u0005\u0019\u0004cA\f%iA\u0011QG\u000f\b\u0003mar!!K\u001c\n\u0003eI!!\u000f\r\u0002\u000fA\f7m[1hK&\u00111\b\u0010\u0002\n)\"\u0014xn^1cY\u0016T!!\u000f\r\u0002)\u0019\f\u0017\u000e\\3e\u0007>$Wm\u0015;bG.$U\r\u001d;i+\u0005y\u0004CA\fA\u0013\t\t\u0005DA\u0002J]R\faCZ1jY\u0016$7i\u001c3f\r&dW\rU1uQ:\fW.Z\u0001\ta>\u001c\u0018\u000e^5p]V\tQ\tE\u0002\u0018I\u0019\u0003\"a\u0012\'\u000e\u0003!S!!\u0013&\u0002\rM|WO]2f\u0015\tY%#A\u0005tG\u0006d\u0017m\u0019;jG&\u0011Q\n\u0013\u0002\t!>\u001c\u0018\u000e^5p]\u0006)c-Y5mK\u0012\u001cu\u000eZ3GS2,g*Y7f\u0003:$G*\u001b8f\u001dVl\'-\u001a:TiJLgnZ\u0001*M\u0006LG.\u001a3D_\u0012,g)\u001b7f!\u0006$\bN\\1nK\u0006sG\rT5oK:+XNY3s\'R\u0014\u0018N\\4\u0002#M$\u0018mY6Ue\u0006\u001cW-\u00127f[\u0016tG/F\u0001S!\r9Be\u0015\t\u0003)fk\u0011!\u0016\u0006\u0003-^\u000bA\u0001\\1oO*\t\u0001,\u0001\u0003kCZ\f\u0017B\u0001.V\u0005E\u0019F/Y2l)J\f7-Z#mK6,g\u000e^\u0001\u0013M\u0006LG.\u001a3D_\u0012,g)\u001b7f\u001d\u0006lW-\u0001\u000bgC&dW\rZ\"pI\u0016d\u0015N\\3Ok6\u0014WM]\u000b\u0002=B\u0019q\u0003J \u0002\'M,g/\u001a:fI\u0006#8\u000b^1dW\u0012+\u0007\u000f\u001e5\u0016\u0003\u0005\u00142A\u0019\u001be\r\u0011\u0019\u0007\u0001A1\u0003\u0019q\u0012XMZ5oK6,g\u000e\u001e \u0011\u0005\u0015\u0004Q\"\u0001\b\u0013\u0007\u001d$GG\u0002\u0003d\u0001\u00011\u0007"
    )
BootstrapMethods:
  0: #51 REF_invokeStatic java/lang/invoke/LambdaMetafactory.altMetafactory:(Ljava/lang/invoke/MethodHandles$Lookup;Ljava/lang/String;Ljava/lang/invoke/MethodType;[Ljava/lang/Object;)Ljava/lang/invoke/CallSite;
    Method arguments:
      #35 (Ljava/lang/Object;)Ljava/lang/Object;
      #40 REF_invokeStatic org/scalatest/exceptions/StackDepth.$anonfun$failedCodeFileNameAndLineNumberString$1:(Lorg/scalatest/exceptions/StackDepth;Ljava/lang/String;)Lscala/Option;
      #42 (Ljava/lang/String;)Lscala/Option;
      #43 5
      #44 1
      #42 (Ljava/lang/String;)Lscala/Option;
  1: #51 REF_invokeStatic java/lang/invoke/LambdaMetafactory.altMetafactory:(Ljava/lang/invoke/MethodHandles$Lookup;Ljava/lang/String;Ljava/lang/invoke/MethodType;[Ljava/lang/Object;)Ljava/lang/invoke/CallSite;
    Method arguments:
      #35 (Ljava/lang/Object;)Ljava/lang/Object;
      #72 REF_invokeStatic org/scalatest/exceptions/StackDepth.$anonfun$failedCodeFilePathnameAndLineNumberString$1:(Lorg/scalatest/exceptions/StackDepth;Ljava/lang/String;)Lscala/Option;
      #42 (Ljava/lang/String;)Lscala/Option;
      #43 5
      #44 1
      #42 (Ljava/lang/String;)Lscala/Option;
  2: #51 REF_invokeStatic java/lang/invoke/LambdaMetafactory.altMetafactory:(Ljava/lang/invoke/MethodHandles$Lookup;Ljava/lang/String;Ljava/lang/invoke/MethodType;[Ljava/lang/Object;)Ljava/lang/invoke/CallSite;
    Method arguments:
      #35 (Ljava/lang/Object;)Ljava/lang/Object;
      #113 REF_invokeStatic org/scalatest/exceptions/StackDepth.$anonfun$stackTraceElement$1$adapted:(Lorg/scalactic/source/Position;Ljava/lang/StackTraceElement;)Ljava/lang/Object;
      #115 (Ljava/lang/StackTraceElement;)Ljava/lang/Object;
      #43 5
      #44 1
      #115 (Ljava/lang/StackTraceElement;)Ljava/lang/Object;
  3: #51 REF_invokeStatic java/lang/invoke/LambdaMetafactory.altMetafactory:(Ljava/lang/invoke/MethodHandles$Lookup;Ljava/lang/String;Ljava/lang/invoke/MethodType;[Ljava/lang/Object;)Ljava/lang/invoke/CallSite;
    Method arguments:
      #35 (Ljava/lang/Object;)Ljava/lang/Object;
      #157 REF_invokeStatic org/scalatest/exceptions/StackDepth.$anonfun$failedCodeFileName$1:(Ljava/lang/StackTraceElement;)Lscala/Option;
      #158 (Ljava/lang/StackTraceElement;)Lscala/Option;
      #43 5
      #44 1
      #158 (Ljava/lang/StackTraceElement;)Lscala/Option;
  4: #51 REF_invokeStatic java/lang/invoke/LambdaMetafactory.altMetafactory:(Ljava/lang/invoke/MethodHandles$Lookup;Ljava/lang/String;Ljava/lang/invoke/MethodType;[Ljava/lang/Object;)Ljava/lang/invoke/CallSite;
    Method arguments:
      #35 (Ljava/lang/Object;)Ljava/lang/Object;
      #179 REF_invokeStatic org/scalatest/exceptions/StackDepth.$anonfun$failedCodeLineNumber$1:(Ljava/lang/StackTraceElement;)Lscala/Option;
      #158 (Ljava/lang/StackTraceElement;)Lscala/Option;
      #43 5
      #44 1
      #158 (Ljava/lang/StackTraceElement;)Lscala/Option;
  5: #51 REF_invokeStatic java/lang/invoke/LambdaMetafactory.altMetafactory:(Ljava/lang/invoke/MethodHandles$Lookup;Ljava/lang/String;Ljava/lang/invoke/MethodType;[Ljava/lang/Object;)Ljava/lang/invoke/CallSite;
    Method arguments:
      #35 (Ljava/lang/Object;)Ljava/lang/Object;
      #210 REF_invokeStatic org/scalatest/exceptions/StackDepth.$anonfun$failedCodeFileNameAndLineNumberString$2$adapted:(Ljava/lang/String;Ljava/lang/Object;)Ljava/lang/String;
      #212 (Ljava/lang/Object;)Ljava/lang/String;
      #43 5
      #44 1
      #212 (Ljava/lang/Object;)Ljava/lang/String;
  6: #51 REF_invokeStatic java/lang/invoke/LambdaMetafactory.altMetafactory:(Ljava/lang/invoke/MethodHandles$Lookup;Ljava/lang/String;Ljava/lang/invoke/MethodType;[Ljava/lang/Object;)Ljava/lang/invoke/CallSite;
    Method arguments:
      #35 (Ljava/lang/Object;)Ljava/lang/Object;
      #224 REF_invokeStatic org/scalatest/exceptions/StackDepth.$anonfun$failedCodeFilePathnameAndLineNumberString$2$adapted:(Ljava/lang/String;Ljava/lang/Object;)Ljava/lang/String;
      #212 (Ljava/lang/Object;)Ljava/lang/String;
      #43 5
      #44 1
      #212 (Ljava/lang/Object;)Ljava/lang/String;
  7: #274 REF_invokeStatic scala/runtime/LambdaDeserialize.bootstrap:(Ljava/lang/invoke/MethodHandles$Lookup;Ljava/lang/String;Ljava/lang/invoke/MethodType;[Ljava/lang/invoke/MethodHandle;)Ljava/lang/invoke/CallSite;
    Method arguments:
      #157 REF_invokeStatic org/scalatest/exceptions/StackDepth.$anonfun$failedCodeFileName$1:(Ljava/lang/StackTraceElement;)Lscala/Option;
      #40 REF_invokeStatic org/scalatest/exceptions/StackDepth.$anonfun$failedCodeFileNameAndLineNumberString$1:(Lorg/scalatest/exceptions/StackDepth;Ljava/lang/String;)Lscala/Option;
      #210 REF_invokeStatic org/scalatest/exceptions/StackDepth.$anonfun$failedCodeFileNameAndLineNumberString$2$adapted:(Ljava/lang/String;Ljava/lang/Object;)Ljava/lang/String;
      #72 REF_invokeStatic org/scalatest/exceptions/StackDepth.$anonfun$failedCodeFilePathnameAndLineNumberString$1:(Lorg/scalatest/exceptions/StackDepth;Ljava/lang/String;)Lscala/Option;
      #224 REF_invokeStatic org/scalatest/exceptions/StackDepth.$anonfun$failedCodeFilePathnameAndLineNumberString$2$adapted:(Ljava/lang/String;Ljava/lang/Object;)Ljava/lang/String;
      #179 REF_invokeStatic org/scalatest/exceptions/StackDepth.$anonfun$failedCodeLineNumber$1:(Ljava/lang/StackTraceElement;)Lscala/Option;
      #113 REF_invokeStatic org/scalatest/exceptions/StackDepth.$anonfun$stackTraceElement$1$adapted:(Lorg/scalactic/source/Position;Ljava/lang/StackTraceElement;)Ljava/lang/Object;
  ScalaInlineInfo: length = 0x86 (unknown attribute)
   01 00 00 1A 00 99 00 9A 01 00 24 00 25 01 00 B7
   00 B8 01 00 CE 00 CF 01 00 45 00 25 01 00 DB 00
   B8 01 00 DD 00 CF 01 00 B0 00 9A 01 00 E2 00 E3
   01 00 6D 00 6E 01 00 F9 00 FA 01 00 11 00 0F 00
   00 1F 00 0F 00 00 92 00 19 01 00 1B 00 0F 00 00
   18 00 19 01 00 15 00 0F 00 00 40 00 0F 00 00 3F
   00 19 01 00 A3 00 0F 00 00 A2 00 19 01 00 13 00
   14 00 00 0E 00 0F 00 00 16 00 0F 00 00 B5 00 B6
   00 00 4A 00 0F 01
  ScalaSig: length = 0x3 (unknown attribute)
   05 02 00
