Classfile /Users/mw/Projects/slang-braindump/.jar/jar8/assemble/slang-braindump/assemble/content/org/scalatest/exceptions/StackDepthExceptionHelper$.class
  Last modified May 29, 2022; size 12928 bytes
  SHA-256 checksum 51aba7fb9382d1bf52987f04fed7e068505b59f89135dd66385e1387ec56a91e
  Compiled from "StackDepthExceptionHelper.scala"
public final class org.scalatest.exceptions.StackDepthExceptionHelper$ implements java.io.Serializable
  minor version: 0
  major version: 52
  flags: (0x0031) ACC_PUBLIC, ACC_FINAL, ACC_SUPER
  this_class: #2                          // org/scalatest/exceptions/StackDepthExceptionHelper$
  super_class: #4                         // java/lang/Object
  interfaces: 1, fields: 1, methods: 35, attributes: 5
Constant pool:
    #1 = Utf8               org/scalatest/exceptions/StackDepthExceptionHelper$
    #2 = Class              #1            // org/scalatest/exceptions/StackDepthExceptionHelper$
    #3 = Utf8               java/lang/Object
    #4 = Class              #3            // java/lang/Object
    #5 = Utf8               java/io/Serializable
    #6 = Class              #5            // java/io/Serializable
    #7 = Utf8               StackDepthExceptionHelper.scala
    #8 = Utf8               java/lang/invoke/MethodHandles$Lookup
    #9 = Class              #8            // java/lang/invoke/MethodHandles$Lookup
   #10 = Utf8               java/lang/invoke/MethodHandles
   #11 = Class              #10           // java/lang/invoke/MethodHandles
   #12 = Utf8               Lookup
   #13 = Utf8               scala/collection/mutable/ArraySeq$ofRef
   #14 = Class              #13           // scala/collection/mutable/ArraySeq$ofRef
   #15 = Utf8               scala/collection/mutable/ArraySeq
   #16 = Class              #15           // scala/collection/mutable/ArraySeq
   #17 = Utf8               ofRef
   #18 = Utf8               MODULE$
   #19 = Utf8               Lorg/scalatest/exceptions/StackDepthExceptionHelper$;
   #20 = Utf8               <clinit>
   #21 = Utf8               ()V
   #22 = Utf8               <init>
   #23 = NameAndType        #22:#21       // "<init>":()V
   #24 = Methodref          #2.#23        // org/scalatest/exceptions/StackDepthExceptionHelper$."<init>":()V
   #25 = NameAndType        #18:#19       // MODULE$:Lorg/scalatest/exceptions/StackDepthExceptionHelper$;
   #26 = Fieldref           #2.#25        // org/scalatest/exceptions/StackDepthExceptionHelper$.MODULE$:Lorg/scalatest/exceptions/StackDepthExceptionHelper$;
   #27 = Utf8               getStackDepth
   #28 = Utf8               ([Ljava/lang/StackTraceElement;Ljava/lang/String;Ljava/lang/String;I)I
   #29 = Utf8               stackTrace
   #30 = Utf8               fileName
   #31 = Utf8               methodName
   #32 = Utf8               adjustment
   #33 = Utf8               scala/Predef$
   #34 = Class              #33           // scala/Predef$
   #35 = Utf8               Lscala/Predef$;
   #36 = NameAndType        #18:#35       // MODULE$:Lscala/Predef$;
   #37 = Fieldref           #34.#36       // scala/Predef$.MODULE$:Lscala/Predef$;
   #38 = Utf8               [Ljava/lang/Object;
   #39 = Class              #38           // "[Ljava/lang/Object;"
   #40 = Utf8               wrapRefArray
   #41 = Utf8               ([Ljava/lang/Object;)Lscala/collection/mutable/ArraySeq$ofRef;
   #42 = NameAndType        #40:#41       // wrapRefArray:([Ljava/lang/Object;)Lscala/collection/mutable/ArraySeq$ofRef;
   #43 = Methodref          #34.#42       // scala/Predef$.wrapRefArray:([Ljava/lang/Object;)Lscala/collection/mutable/ArraySeq$ofRef;
   #44 = Utf8               toList
   #45 = Utf8               ()Lscala/collection/immutable/List;
   #46 = NameAndType        #44:#45       // toList:()Lscala/collection/immutable/List;
   #47 = Methodref          #14.#46       // scala/collection/mutable/ArraySeq$ofRef.toList:()Lscala/collection/immutable/List;
   #48 = Utf8               (Ljava/lang/Object;)Ljava/lang/Object;
   #49 = MethodType         #48           //  (Ljava/lang/Object;)Ljava/lang/Object;
   #50 = Utf8               $anonfun$getStackDepth$1$adapted
   #51 = Utf8               (Ljava/lang/String;Ljava/lang/StackTraceElement;)Ljava/lang/Object;
   #52 = NameAndType        #50:#51       // $anonfun$getStackDepth$1$adapted:(Ljava/lang/String;Ljava/lang/StackTraceElement;)Ljava/lang/Object;
   #53 = Methodref          #2.#52        // org/scalatest/exceptions/StackDepthExceptionHelper$.$anonfun$getStackDepth$1$adapted:(Ljava/lang/String;Ljava/lang/StackTraceElement;)Ljava/lang/Object;
   #54 = MethodHandle       6:#53         // REF_invokeStatic org/scalatest/exceptions/StackDepthExceptionHelper$.$anonfun$getStackDepth$1$adapted:(Ljava/lang/String;Ljava/lang/StackTraceElement;)Ljava/lang/Object;
   #55 = Utf8               (Ljava/lang/StackTraceElement;)Ljava/lang/Object;
   #56 = MethodType         #55           //  (Ljava/lang/StackTraceElement;)Ljava/lang/Object;
   #57 = Integer            5
   #58 = Integer            1
   #59 = Utf8               java/lang/invoke/LambdaMetafactory
   #60 = Class              #59           // java/lang/invoke/LambdaMetafactory
   #61 = Utf8               altMetafactory
   #62 = Utf8               (Ljava/lang/invoke/MethodHandles$Lookup;Ljava/lang/String;Ljava/lang/invoke/MethodType;[Ljava/lang/Object;)Ljava/lang/invoke/CallSite;
   #63 = NameAndType        #61:#62       // altMetafactory:(Ljava/lang/invoke/MethodHandles$Lookup;Ljava/lang/String;Ljava/lang/invoke/MethodType;[Ljava/lang/Object;)Ljava/lang/invoke/CallSite;
   #64 = Methodref          #60.#63       // java/lang/invoke/LambdaMetafactory.altMetafactory:(Ljava/lang/invoke/MethodHandles$Lookup;Ljava/lang/String;Ljava/lang/invoke/MethodType;[Ljava/lang/Object;)Ljava/lang/invoke/CallSite;
   #65 = MethodHandle       6:#64         // REF_invokeStatic java/lang/invoke/LambdaMetafactory.altMetafactory:(Ljava/lang/invoke/MethodHandles$Lookup;Ljava/lang/String;Ljava/lang/invoke/MethodType;[Ljava/lang/Object;)Ljava/lang/invoke/CallSite;
   #66 = Utf8               apply
   #67 = Utf8               (Ljava/lang/String;)Lscala/Function1;
   #68 = NameAndType        #66:#67       // apply:(Ljava/lang/String;)Lscala/Function1;
   #69 = InvokeDynamic      #0:#68        // #0:apply:(Ljava/lang/String;)Lscala/Function1;
   #70 = Utf8               scala/collection/immutable/List
   #71 = Class              #70           // scala/collection/immutable/List
   #72 = Utf8               map
   #73 = Utf8               (Lscala/Function1;)Lscala/collection/immutable/List;
   #74 = NameAndType        #72:#73       // map:(Lscala/Function1;)Lscala/collection/immutable/List;
   #75 = Methodref          #71.#74       // scala/collection/immutable/List.map:(Lscala/Function1;)Lscala/collection/immutable/List;
   #76 = Utf8               $anonfun$getStackDepth$2$adapted
   #77 = NameAndType        #76:#51       // $anonfun$getStackDepth$2$adapted:(Ljava/lang/String;Ljava/lang/StackTraceElement;)Ljava/lang/Object;
   #78 = Methodref          #2.#77        // org/scalatest/exceptions/StackDepthExceptionHelper$.$anonfun$getStackDepth$2$adapted:(Ljava/lang/String;Ljava/lang/StackTraceElement;)Ljava/lang/Object;
   #79 = MethodHandle       6:#78         // REF_invokeStatic org/scalatest/exceptions/StackDepthExceptionHelper$.$anonfun$getStackDepth$2$adapted:(Ljava/lang/String;Ljava/lang/StackTraceElement;)Ljava/lang/Object;
   #80 = InvokeDynamic      #1:#68        // #1:apply:(Ljava/lang/String;)Lscala/Function1;
   #81 = Utf8               dropRight
   #82 = Utf8               (I)Ljava/lang/Object;
   #83 = NameAndType        #81:#82       // dropRight:(I)Ljava/lang/Object;
   #84 = Methodref          #71.#83       // scala/collection/immutable/List.dropRight:(I)Ljava/lang/Object;
   #85 = Utf8               scala/runtime/BoxesRunTime
   #86 = Class              #85           // scala/runtime/BoxesRunTime
   #87 = Utf8               boxToBoolean
   #88 = Utf8               (Z)Ljava/lang/Boolean;
   #89 = NameAndType        #87:#88       // boxToBoolean:(Z)Ljava/lang/Boolean;
   #90 = Methodref          #86.#89       // scala/runtime/BoxesRunTime.boxToBoolean:(Z)Ljava/lang/Boolean;
   #91 = Utf8               $colon$colon
   #92 = Utf8               (Ljava/lang/Object;)Lscala/collection/immutable/List;
   #93 = NameAndType        #91:#92       // $colon$colon:(Ljava/lang/Object;)Lscala/collection/immutable/List;
   #94 = Methodref          #71.#93       // scala/collection/immutable/List.$colon$colon:(Ljava/lang/Object;)Lscala/collection/immutable/List;
   #95 = Utf8               zip
   #96 = Utf8               (Lscala/collection/IterableOnce;)Ljava/lang/Object;
   #97 = NameAndType        #95:#96       // zip:(Lscala/collection/IterableOnce;)Ljava/lang/Object;
   #98 = Methodref          #71.#97       // scala/collection/immutable/List.zip:(Lscala/collection/IterableOnce;)Ljava/lang/Object;
   #99 = Utf8               $anonfun$getStackDepth$3$adapted
  #100 = Utf8               (Lscala/Tuple2;)Ljava/lang/Object;
  #101 = NameAndType        #99:#100      // $anonfun$getStackDepth$3$adapted:(Lscala/Tuple2;)Ljava/lang/Object;
  #102 = Methodref          #2.#101       // org/scalatest/exceptions/StackDepthExceptionHelper$.$anonfun$getStackDepth$3$adapted:(Lscala/Tuple2;)Ljava/lang/Object;
  #103 = MethodHandle       6:#102        // REF_invokeStatic org/scalatest/exceptions/StackDepthExceptionHelper$.$anonfun$getStackDepth$3$adapted:(Lscala/Tuple2;)Ljava/lang/Object;
  #104 = MethodType         #100          //  (Lscala/Tuple2;)Ljava/lang/Object;
  #105 = Utf8               ()Lscala/Function1;
  #106 = NameAndType        #66:#105      // apply:()Lscala/Function1;
  #107 = InvokeDynamic      #2:#106       // #2:apply:()Lscala/Function1;
  #108 = Utf8               withFilter
  #109 = Utf8               (Lscala/Function1;)Lscala/collection/WithFilter;
  #110 = NameAndType        #108:#109     // withFilter:(Lscala/Function1;)Lscala/collection/WithFilter;
  #111 = Methodref          #71.#110      // scala/collection/immutable/List.withFilter:(Lscala/Function1;)Lscala/collection/WithFilter;
  #112 = Utf8               $anonfun$getStackDepth$4$adapted
  #113 = NameAndType        #112:#100     // $anonfun$getStackDepth$4$adapted:(Lscala/Tuple2;)Ljava/lang/Object;
  #114 = Methodref          #2.#113       // org/scalatest/exceptions/StackDepthExceptionHelper$.$anonfun$getStackDepth$4$adapted:(Lscala/Tuple2;)Ljava/lang/Object;
  #115 = MethodHandle       6:#114        // REF_invokeStatic org/scalatest/exceptions/StackDepthExceptionHelper$.$anonfun$getStackDepth$4$adapted:(Lscala/Tuple2;)Ljava/lang/Object;
  #116 = InvokeDynamic      #3:#106       // #3:apply:()Lscala/Function1;
  #117 = Utf8               scala/collection/WithFilter
  #118 = Class              #117          // scala/collection/WithFilter
  #119 = Utf8               (Lscala/Function1;)Ljava/lang/Object;
  #120 = NameAndType        #72:#119      // map:(Lscala/Function1;)Ljava/lang/Object;
  #121 = Methodref          #118.#120     // scala/collection/WithFilter.map:(Lscala/Function1;)Ljava/lang/Object;
  #122 = Utf8               $anonfun$getStackDepth$5$adapted
  #123 = NameAndType        #122:#100     // $anonfun$getStackDepth$5$adapted:(Lscala/Tuple2;)Ljava/lang/Object;
  #124 = Methodref          #2.#123       // org/scalatest/exceptions/StackDepthExceptionHelper$.$anonfun$getStackDepth$5$adapted:(Lscala/Tuple2;)Ljava/lang/Object;
  #125 = MethodHandle       6:#124        // REF_invokeStatic org/scalatest/exceptions/StackDepthExceptionHelper$.$anonfun$getStackDepth$5$adapted:(Lscala/Tuple2;)Ljava/lang/Object;
  #126 = InvokeDynamic      #4:#106       // #4:apply:()Lscala/Function1;
  #127 = Utf8               $anonfun$getStackDepth$6$adapted
  #128 = NameAndType        #127:#100     // $anonfun$getStackDepth$6$adapted:(Lscala/Tuple2;)Ljava/lang/Object;
  #129 = Methodref          #2.#128       // org/scalatest/exceptions/StackDepthExceptionHelper$.$anonfun$getStackDepth$6$adapted:(Lscala/Tuple2;)Ljava/lang/Object;
  #130 = MethodHandle       6:#129        // REF_invokeStatic org/scalatest/exceptions/StackDepthExceptionHelper$.$anonfun$getStackDepth$6$adapted:(Lscala/Tuple2;)Ljava/lang/Object;
  #131 = InvokeDynamic      #5:#106       // #5:apply:()Lscala/Function1;
  #132 = Utf8               $anonfun$getStackDepth$7$adapted
  #133 = NameAndType        #132:#48      // $anonfun$getStackDepth$7$adapted:(Ljava/lang/Object;)Ljava/lang/Object;
  #134 = Methodref          #2.#133       // org/scalatest/exceptions/StackDepthExceptionHelper$.$anonfun$getStackDepth$7$adapted:(Ljava/lang/Object;)Ljava/lang/Object;
  #135 = MethodHandle       6:#134        // REF_invokeStatic org/scalatest/exceptions/StackDepthExceptionHelper$.$anonfun$getStackDepth$7$adapted:(Ljava/lang/Object;)Ljava/lang/Object;
  #136 = InvokeDynamic      #6:#106       // #6:apply:()Lscala/Function1;
  #137 = Utf8               takeWhile
  #138 = NameAndType        #137:#73      // takeWhile:(Lscala/Function1;)Lscala/collection/immutable/List;
  #139 = Methodref          #71.#138      // scala/collection/immutable/List.takeWhile:(Lscala/Function1;)Lscala/collection/immutable/List;
  #140 = Utf8               length
  #141 = Utf8               ()I
  #142 = NameAndType        #140:#141     // length:()I
  #143 = Methodref          #71.#142      // scala/collection/immutable/List.length:()I
  #144 = Utf8               java/lang/StackTraceElement
  #145 = Class              #144          // java/lang/StackTraceElement
  #146 = Utf8               getFileName
  #147 = Utf8               ()Ljava/lang/String;
  #148 = NameAndType        #146:#147     // getFileName:()Ljava/lang/String;
  #149 = Methodref          #145.#148     // java/lang/StackTraceElement.getFileName:()Ljava/lang/String;
  #150 = Utf8               equals
  #151 = Utf8               (Ljava/lang/Object;)Z
  #152 = NameAndType        #150:#151     // equals:(Ljava/lang/Object;)Z
  #153 = Methodref          #4.#152       // java/lang/Object.equals:(Ljava/lang/Object;)Z
  #154 = Utf8               getMethodName
  #155 = NameAndType        #154:#147     // getMethodName:()Ljava/lang/String;
  #156 = Methodref          #145.#155     // java/lang/StackTraceElement.getMethodName:()Ljava/lang/String;
  #157 = Utf8               $anonfun$getStackDepth$8$adapted
  #158 = Utf8               (Ljava/lang/String;Ljava/lang/String;Ljava/lang/StackTraceElement;)Ljava/lang/Object;
  #159 = NameAndType        #157:#158     // $anonfun$getStackDepth$8$adapted:(Ljava/lang/String;Ljava/lang/String;Ljava/lang/StackTraceElement;)Ljava/lang/Object;
  #160 = Methodref          #2.#159       // org/scalatest/exceptions/StackDepthExceptionHelper$.$anonfun$getStackDepth$8$adapted:(Ljava/lang/String;Ljava/lang/String;Ljava/lang/StackTraceElement;)Ljava/lang/Object;
  #161 = MethodHandle       6:#160        // REF_invokeStatic org/scalatest/exceptions/StackDepthExceptionHelper$.$anonfun$getStackDepth$8$adapted:(Ljava/lang/String;Ljava/lang/String;Ljava/lang/StackTraceElement;)Ljava/lang/Object;
  #162 = Utf8               (Ljava/lang/String;Ljava/lang/String;)Lscala/Function1;
  #163 = NameAndType        #66:#162      // apply:(Ljava/lang/String;Ljava/lang/String;)Lscala/Function1;
  #164 = InvokeDynamic      #7:#163       // #7:apply:(Ljava/lang/String;Ljava/lang/String;)Lscala/Function1;
  #165 = Utf8               stackTraceList
  #166 = Utf8               Lscala/collection/immutable/List;
  #167 = Utf8               fileNameIsDesiredList
  #168 = Utf8               methodNameIsDesiredList
  #169 = Utf8               previousFileNameIsDesiredList
  #170 = Utf8               zipped1
  #171 = Utf8               methodNameAndPreviousFileNameAreDesiredList
  #172 = Utf8               zipped2
  #173 = Utf8               includeInStackDepthList
  #174 = Utf8               includeDepth
  #175 = Utf8               I
  #176 = Utf8               depth
  #177 = Utf8               this
  #178 = Utf8               [Ljava/lang/StackTraceElement;
  #179 = Utf8               Ljava/lang/String;
  #180 = Class              #178          // "[Ljava/lang/StackTraceElement;"
  #181 = Utf8               java/lang/String
  #182 = Class              #181          // java/lang/String
  #183 = Utf8               getStackDepthFun
  #184 = Utf8               (Ljava/lang/String;Ljava/lang/String;I)Lscala/Function1;
  #185 = Utf8               (Ljava/lang/String;Ljava/lang/String;I)Lscala/Function1<Lorg/scalatest/exceptions/StackDepthException;Ljava/lang/Object;>;
  #186 = Utf8               $anonfun$getStackDepthFun$1$adapted
  #187 = Utf8               (Ljava/lang/String;Ljava/lang/String;ILorg/scalatest/exceptions/StackDepthException;)Ljava/lang/Object;
  #188 = NameAndType        #186:#187     // $anonfun$getStackDepthFun$1$adapted:(Ljava/lang/String;Ljava/lang/String;ILorg/scalatest/exceptions/StackDepthException;)Ljava/lang/Object;
  #189 = Methodref          #2.#188       // org/scalatest/exceptions/StackDepthExceptionHelper$.$anonfun$getStackDepthFun$1$adapted:(Ljava/lang/String;Ljava/lang/String;ILorg/scalatest/exceptions/StackDepthException;)Ljava/lang/Object;
  #190 = MethodHandle       6:#189        // REF_invokeStatic org/scalatest/exceptions/StackDepthExceptionHelper$.$anonfun$getStackDepthFun$1$adapted:(Ljava/lang/String;Ljava/lang/String;ILorg/scalatest/exceptions/StackDepthException;)Ljava/lang/Object;
  #191 = Utf8               (Lorg/scalatest/exceptions/StackDepthException;)Ljava/lang/Object;
  #192 = MethodType         #191          //  (Lorg/scalatest/exceptions/StackDepthException;)Ljava/lang/Object;
  #193 = NameAndType        #66:#184      // apply:(Ljava/lang/String;Ljava/lang/String;I)Lscala/Function1;
  #194 = InvokeDynamic      #8:#193       // #8:apply:(Ljava/lang/String;Ljava/lang/String;I)Lscala/Function1;
  #195 = Utf8               isMatch
  #196 = Utf8               (Ljava/lang/StackTraceElement;Lorg/scalactic/source/Position;)Z
  #197 = Utf8               ele
  #198 = Utf8               pos
  #199 = Utf8               org/scalactic/source/Position
  #200 = Class              #199          // org/scalactic/source/Position
  #201 = NameAndType        #30:#147      // fileName:()Ljava/lang/String;
  #202 = Methodref          #200.#201     // org/scalactic/source/Position.fileName:()Ljava/lang/String;
  #203 = Utf8               getLineNumber
  #204 = NameAndType        #203:#141     // getLineNumber:()I
  #205 = Methodref          #145.#204     // java/lang/StackTraceElement.getLineNumber:()I
  #206 = Utf8               lineNumber
  #207 = NameAndType        #206:#141     // lineNumber:()I
  #208 = Methodref          #200.#207     // org/scalactic/source/Position.lineNumber:()I
  #209 = Utf8               Ljava/lang/StackTraceElement;
  #210 = Utf8               Lorg/scalactic/source/Position;
  #211 = Utf8               ([Ljava/lang/StackTraceElement;Lorg/scalactic/source/Position;)I
  #212 = Utf8               refArrayOps
  #213 = Utf8               ([Ljava/lang/Object;)Ljava/lang/Object;
  #214 = NameAndType        #212:#213     // refArrayOps:([Ljava/lang/Object;)Ljava/lang/Object;
  #215 = Methodref          #34.#214      // scala/Predef$.refArrayOps:([Ljava/lang/Object;)Ljava/lang/Object;
  #216 = Utf8               $anonfun$getStackDepth$9$adapted
  #217 = Utf8               (Lorg/scalactic/source/Position;Ljava/lang/StackTraceElement;)Ljava/lang/Object;
  #218 = NameAndType        #216:#217     // $anonfun$getStackDepth$9$adapted:(Lorg/scalactic/source/Position;Ljava/lang/StackTraceElement;)Ljava/lang/Object;
  #219 = Methodref          #2.#218       // org/scalatest/exceptions/StackDepthExceptionHelper$.$anonfun$getStackDepth$9$adapted:(Lorg/scalactic/source/Position;Ljava/lang/StackTraceElement;)Ljava/lang/Object;
  #220 = MethodHandle       6:#219        // REF_invokeStatic org/scalatest/exceptions/StackDepthExceptionHelper$.$anonfun$getStackDepth$9$adapted:(Lorg/scalactic/source/Position;Ljava/lang/StackTraceElement;)Ljava/lang/Object;
  #221 = Utf8               (Lorg/scalactic/source/Position;)Lscala/Function1;
  #222 = NameAndType        #66:#221      // apply:(Lorg/scalactic/source/Position;)Lscala/Function1;
  #223 = InvokeDynamic      #9:#222       // #9:apply:(Lorg/scalactic/source/Position;)Lscala/Function1;
  #224 = Utf8               scala/collection/ArrayOps$
  #225 = Class              #224          // scala/collection/ArrayOps$
  #226 = Utf8               Lscala/collection/ArrayOps$;
  #227 = NameAndType        #18:#226      // MODULE$:Lscala/collection/ArrayOps$;
  #228 = Fieldref           #225.#227     // scala/collection/ArrayOps$.MODULE$:Lscala/collection/ArrayOps$;
  #229 = Utf8               indexWhere$default$2$extension
  #230 = Utf8               (Ljava/lang/Object;)I
  #231 = NameAndType        #229:#230     // indexWhere$default$2$extension:(Ljava/lang/Object;)I
  #232 = Methodref          #225.#231     // scala/collection/ArrayOps$.indexWhere$default$2$extension:(Ljava/lang/Object;)I
  #233 = Utf8               indexWhere$extension
  #234 = Utf8               (Ljava/lang/Object;Lscala/Function1;I)I
  #235 = NameAndType        #233:#234     // indexWhere$extension:(Ljava/lang/Object;Lscala/Function1;I)I
  #236 = Methodref          #225.#235     // scala/collection/ArrayOps$.indexWhere$extension:(Ljava/lang/Object;Lscala/Function1;I)I
  #237 = Utf8               qual$1
  #238 = Utf8               Ljava/lang/Object;
  #239 = Utf8               x$1
  #240 = Utf8               Lscala/Function1;
  #241 = Utf8               x$2
  #242 = Utf8               idx
  #243 = Utf8               scala/Function1
  #244 = Class              #243          // scala/Function1
  #245 = Utf8               getStackDepth$default$4
  #246 = Utf8               (Lorg/scalactic/source/Position;)Lscala/Function1<Lorg/scalatest/exceptions/StackDepthException;Ljava/lang/Object;>;
  #247 = Utf8               $anonfun$getStackDepthFun$2$adapted
  #248 = Utf8               (Lorg/scalactic/source/Position;Lorg/scalatest/exceptions/StackDepthException;)Ljava/lang/Object;
  #249 = NameAndType        #247:#248     // $anonfun$getStackDepthFun$2$adapted:(Lorg/scalactic/source/Position;Lorg/scalatest/exceptions/StackDepthException;)Ljava/lang/Object;
  #250 = Methodref          #2.#249       // org/scalatest/exceptions/StackDepthExceptionHelper$.$anonfun$getStackDepthFun$2$adapted:(Lorg/scalactic/source/Position;Lorg/scalatest/exceptions/StackDepthException;)Ljava/lang/Object;
  #251 = MethodHandle       6:#250        // REF_invokeStatic org/scalatest/exceptions/StackDepthExceptionHelper$.$anonfun$getStackDepthFun$2$adapted:(Lorg/scalactic/source/Position;Lorg/scalatest/exceptions/StackDepthException;)Ljava/lang/Object;
  #252 = InvokeDynamic      #10:#222      // #10:apply:(Lorg/scalactic/source/Position;)Lscala/Function1;
  #253 = Utf8               getStackDepthFun$default$3
  #254 = Utf8               getFailedCodeFileName
  #255 = Utf8               (Ljava/lang/StackTraceElement;)Lscala/Option;
  #256 = Utf8               (Ljava/lang/StackTraceElement;)Lscala/Option<Ljava/lang/String;>;
  #257 = Utf8               stackTraceElement
  #258 = Utf8               scala/Some
  #259 = Class              #258          // scala/Some
  #260 = Utf8               (Ljava/lang/Object;)V
  #261 = NameAndType        #22:#260      // "<init>":(Ljava/lang/Object;)V
  #262 = Methodref          #259.#261     // scala/Some."<init>":(Ljava/lang/Object;)V
  #263 = Utf8               scala/None$
  #264 = Class              #263          // scala/None$
  #265 = Utf8               Lscala/None$;
  #266 = NameAndType        #18:#265      // MODULE$:Lscala/None$;
  #267 = Fieldref           #264.#266     // scala/None$.MODULE$:Lscala/None$;
  #268 = Utf8               scala/Option
  #269 = Class              #268          // scala/Option
  #270 = Utf8               posOrElseStackDepthFun
  #271 = Utf8               (Lscala/Option;Lscala/Function1;)Lscala/util/Either;
  #272 = Utf8               (Lscala/Option<Lorg/scalactic/source/Position;>;Lscala/Function1<Lorg/scalatest/exceptions/StackDepthException;Ljava/lang/Object;>;)Lscala/util/Either<Lorg/scalactic/source/Position;Lscala/Function1<Lorg/scalatest/exceptions/StackDepthException;Ljava/lang/Object;>;>;
  #273 = Utf8               sdf
  #274 = Utf8               org/scalactic/exceptions/NullArgumentException
  #275 = Class              #274          // org/scalactic/exceptions/NullArgumentException
  #276 = Utf8               pos was null
  #277 = String             #276          // pos was null
  #278 = Utf8               (Ljava/lang/String;)V
  #279 = NameAndType        #22:#278      // "<init>":(Ljava/lang/String;)V
  #280 = Methodref          #275.#279     // org/scalactic/exceptions/NullArgumentException."<init>":(Ljava/lang/String;)V
  #281 = Utf8               sdf was null
  #282 = String             #281          // sdf was null
  #283 = Utf8               value
  #284 = Utf8               ()Ljava/lang/Object;
  #285 = NameAndType        #283:#284     // value:()Ljava/lang/Object;
  #286 = Methodref          #259.#285     // scala/Some.value:()Ljava/lang/Object;
  #287 = Utf8               pos was Some(null)
  #288 = String             #287          // pos was Some(null)
  #289 = Utf8               scala/runtime/BoxedUnit
  #290 = Class              #289          // scala/runtime/BoxedUnit
  #291 = Utf8               UNIT
  #292 = Utf8               Lscala/runtime/BoxedUnit;
  #293 = NameAndType        #291:#292     // UNIT:Lscala/runtime/BoxedUnit;
  #294 = Fieldref           #290.#293     // scala/runtime/BoxedUnit.UNIT:Lscala/runtime/BoxedUnit;
  #295 = Utf8               scala/package$
  #296 = Class              #295          // scala/package$
  #297 = Utf8               Lscala/package$;
  #298 = NameAndType        #18:#297      // MODULE$:Lscala/package$;
  #299 = Fieldref           #296.#298     // scala/package$.MODULE$:Lscala/package$;
  #300 = Utf8               Left
  #301 = Utf8               ()Lscala/util/Left$;
  #302 = NameAndType        #300:#301     // Left:()Lscala/util/Left$;
  #303 = Methodref          #296.#302     // scala/package$.Left:()Lscala/util/Left$;
  #304 = Utf8               scala/util/Left$
  #305 = Class              #304          // scala/util/Left$
  #306 = Utf8               (Ljava/lang/Object;)Lscala/util/Left;
  #307 = NameAndType        #66:#306      // apply:(Ljava/lang/Object;)Lscala/util/Left;
  #308 = Methodref          #305.#307     // scala/util/Left$.apply:(Ljava/lang/Object;)Lscala/util/Left;
  #309 = Utf8               Right
  #310 = Utf8               ()Lscala/util/Right$;
  #311 = NameAndType        #309:#310     // Right:()Lscala/util/Right$;
  #312 = Methodref          #296.#311     // scala/package$.Right:()Lscala/util/Right$;
  #313 = Utf8               scala/util/Right$
  #314 = Class              #313          // scala/util/Right$
  #315 = Utf8               (Ljava/lang/Object;)Lscala/util/Right;
  #316 = NameAndType        #66:#315      // apply:(Ljava/lang/Object;)Lscala/util/Right;
  #317 = Methodref          #314.#316     // scala/util/Right$.apply:(Ljava/lang/Object;)Lscala/util/Right;
  #318 = Utf8               scala/MatchError
  #319 = Class              #318          // scala/MatchError
  #320 = Methodref          #319.#261     // scala/MatchError."<init>":(Ljava/lang/Object;)V
  #321 = Utf8               Lscala/Option;
  #322 = Utf8               scala/util/Either
  #323 = Class              #322          // scala/util/Either
  #324 = Utf8               writeReplace
  #325 = Utf8               scala/runtime/ModuleSerializationProxy
  #326 = Class              #325          // scala/runtime/ModuleSerializationProxy
  #327 = Utf8               (Ljava/lang/Class;)V
  #328 = NameAndType        #22:#327      // "<init>":(Ljava/lang/Class;)V
  #329 = Methodref          #326.#328     // scala/runtime/ModuleSerializationProxy."<init>":(Ljava/lang/Class;)V
  #330 = Utf8               $anonfun$getStackDepth$1
  #331 = Utf8               (Ljava/lang/String;Ljava/lang/StackTraceElement;)Z
  #332 = Utf8               fileName$1
  #333 = Utf8               element
  #334 = Utf8               $anonfun$getStackDepth$2
  #335 = Utf8               methodName$1
  #336 = Utf8               $anonfun$getStackDepth$3
  #337 = Utf8               (Lscala/Tuple2;)Z
  #338 = Utf8               check$ifrefutable$1
  #339 = Utf8               Lscala/Tuple2;
  #340 = Utf8               scala/Tuple2
  #341 = Class              #340          // scala/Tuple2
  #342 = Utf8               $anonfun$getStackDepth$4
  #343 = Utf8               _1$mcZ$sp
  #344 = Utf8               ()Z
  #345 = NameAndType        #343:#344     // _1$mcZ$sp:()Z
  #346 = Methodref          #341.#345     // scala/Tuple2._1$mcZ$sp:()Z
  #347 = Utf8               _2$mcZ$sp
  #348 = NameAndType        #347:#344     // _2$mcZ$sp:()Z
  #349 = Methodref          #341.#348     // scala/Tuple2._2$mcZ$sp:()Z
  #350 = Utf8               methodNameIsDesired
  #351 = Utf8               Z
  #352 = Utf8               previousFileNameIsDesired
  #353 = Utf8               $anonfun$getStackDepth$5
  #354 = Utf8               check$ifrefutable$2
  #355 = Utf8               $anonfun$getStackDepth$6
  #356 = Utf8               fileNameIsDesired
  #357 = Utf8               methodNameAndPreviousFileNameAreDesired
  #358 = Utf8               $anonfun$getStackDepth$7
  #359 = Utf8               (Z)Z
  #360 = Utf8               include
  #361 = Utf8               $anonfun$getStackDepth$8
  #362 = Utf8               (Ljava/lang/String;Ljava/lang/String;Ljava/lang/StackTraceElement;)Z
  #363 = Utf8               st
  #364 = Utf8               $anonfun$getStackDepthFun$1
  #365 = Utf8               (Ljava/lang/String;Ljava/lang/String;ILorg/scalatest/exceptions/StackDepthException;)I
  #366 = Utf8               fileName$2
  #367 = Utf8               methodName$2
  #368 = Utf8               adjustment$1
  #369 = Utf8               sde
  #370 = Utf8               org/scalatest/exceptions/StackDepthException
  #371 = Class              #370          // org/scalatest/exceptions/StackDepthException
  #372 = Utf8               getStackTrace
  #373 = Utf8               ()[Ljava/lang/StackTraceElement;
  #374 = NameAndType        #372:#373     // getStackTrace:()[Ljava/lang/StackTraceElement;
  #375 = Methodref          #371.#374     // org/scalatest/exceptions/StackDepthException.getStackTrace:()[Ljava/lang/StackTraceElement;
  #376 = NameAndType        #27:#28       // getStackDepth:([Ljava/lang/StackTraceElement;Ljava/lang/String;Ljava/lang/String;I)I
  #377 = Methodref          #2.#376       // org/scalatest/exceptions/StackDepthExceptionHelper$.getStackDepth:([Ljava/lang/StackTraceElement;Ljava/lang/String;Ljava/lang/String;I)I
  #378 = Utf8               Lorg/scalatest/exceptions/StackDepthException;
  #379 = Utf8               $anonfun$getStackDepth$9
  #380 = Utf8               (Lorg/scalactic/source/Position;Ljava/lang/StackTraceElement;)Z
  #381 = Utf8               pos$1
  #382 = Utf8               e
  #383 = NameAndType        #195:#196     // isMatch:(Ljava/lang/StackTraceElement;Lorg/scalactic/source/Position;)Z
  #384 = Methodref          #2.#383       // org/scalatest/exceptions/StackDepthExceptionHelper$.isMatch:(Ljava/lang/StackTraceElement;Lorg/scalactic/source/Position;)Z
  #385 = Utf8               $anonfun$getStackDepthFun$2
  #386 = Utf8               (Lorg/scalactic/source/Position;Lorg/scalatest/exceptions/StackDepthException;)I
  #387 = Utf8               pos$2
  #388 = NameAndType        #27:#211      // getStackDepth:([Ljava/lang/StackTraceElement;Lorg/scalactic/source/Position;)I
  #389 = Methodref          #2.#388       // org/scalatest/exceptions/StackDepthExceptionHelper$.getStackDepth:([Ljava/lang/StackTraceElement;Lorg/scalactic/source/Position;)I
  #390 = Methodref          #4.#23        // java/lang/Object."<init>":()V
  #391 = NameAndType        #330:#331     // $anonfun$getStackDepth$1:(Ljava/lang/String;Ljava/lang/StackTraceElement;)Z
  #392 = Methodref          #2.#391       // org/scalatest/exceptions/StackDepthExceptionHelper$.$anonfun$getStackDepth$1:(Ljava/lang/String;Ljava/lang/StackTraceElement;)Z
  #393 = NameAndType        #334:#331     // $anonfun$getStackDepth$2:(Ljava/lang/String;Ljava/lang/StackTraceElement;)Z
  #394 = Methodref          #2.#393       // org/scalatest/exceptions/StackDepthExceptionHelper$.$anonfun$getStackDepth$2:(Ljava/lang/String;Ljava/lang/StackTraceElement;)Z
  #395 = NameAndType        #336:#337     // $anonfun$getStackDepth$3:(Lscala/Tuple2;)Z
  #396 = Methodref          #2.#395       // org/scalatest/exceptions/StackDepthExceptionHelper$.$anonfun$getStackDepth$3:(Lscala/Tuple2;)Z
  #397 = NameAndType        #342:#337     // $anonfun$getStackDepth$4:(Lscala/Tuple2;)Z
  #398 = Methodref          #2.#397       // org/scalatest/exceptions/StackDepthExceptionHelper$.$anonfun$getStackDepth$4:(Lscala/Tuple2;)Z
  #399 = NameAndType        #353:#337     // $anonfun$getStackDepth$5:(Lscala/Tuple2;)Z
  #400 = Methodref          #2.#399       // org/scalatest/exceptions/StackDepthExceptionHelper$.$anonfun$getStackDepth$5:(Lscala/Tuple2;)Z
  #401 = NameAndType        #355:#337     // $anonfun$getStackDepth$6:(Lscala/Tuple2;)Z
  #402 = Methodref          #2.#401       // org/scalatest/exceptions/StackDepthExceptionHelper$.$anonfun$getStackDepth$6:(Lscala/Tuple2;)Z
  #403 = Utf8               unboxToBoolean
  #404 = NameAndType        #403:#151     // unboxToBoolean:(Ljava/lang/Object;)Z
  #405 = Methodref          #86.#404      // scala/runtime/BoxesRunTime.unboxToBoolean:(Ljava/lang/Object;)Z
  #406 = NameAndType        #358:#359     // $anonfun$getStackDepth$7:(Z)Z
  #407 = Methodref          #2.#406       // org/scalatest/exceptions/StackDepthExceptionHelper$.$anonfun$getStackDepth$7:(Z)Z
  #408 = NameAndType        #361:#362     // $anonfun$getStackDepth$8:(Ljava/lang/String;Ljava/lang/String;Ljava/lang/StackTraceElement;)Z
  #409 = Methodref          #2.#408       // org/scalatest/exceptions/StackDepthExceptionHelper$.$anonfun$getStackDepth$8:(Ljava/lang/String;Ljava/lang/String;Ljava/lang/StackTraceElement;)Z
  #410 = NameAndType        #364:#365     // $anonfun$getStackDepthFun$1:(Ljava/lang/String;Ljava/lang/String;ILorg/scalatest/exceptions/StackDepthException;)I
  #411 = Methodref          #2.#410       // org/scalatest/exceptions/StackDepthExceptionHelper$.$anonfun$getStackDepthFun$1:(Ljava/lang/String;Ljava/lang/String;ILorg/scalatest/exceptions/StackDepthException;)I
  #412 = Utf8               boxToInteger
  #413 = Utf8               (I)Ljava/lang/Integer;
  #414 = NameAndType        #412:#413     // boxToInteger:(I)Ljava/lang/Integer;
  #415 = Methodref          #86.#414      // scala/runtime/BoxesRunTime.boxToInteger:(I)Ljava/lang/Integer;
  #416 = NameAndType        #379:#380     // $anonfun$getStackDepth$9:(Lorg/scalactic/source/Position;Ljava/lang/StackTraceElement;)Z
  #417 = Methodref          #2.#416       // org/scalatest/exceptions/StackDepthExceptionHelper$.$anonfun$getStackDepth$9:(Lorg/scalactic/source/Position;Ljava/lang/StackTraceElement;)Z
  #418 = NameAndType        #385:#386     // $anonfun$getStackDepthFun$2:(Lorg/scalactic/source/Position;Lorg/scalatest/exceptions/StackDepthException;)I
  #419 = Methodref          #2.#418       // org/scalatest/exceptions/StackDepthExceptionHelper$.$anonfun$getStackDepthFun$2:(Lorg/scalactic/source/Position;Lorg/scalatest/exceptions/StackDepthException;)I
  #420 = Utf8               $deserializeLambda$
  #421 = Utf8               (Ljava/lang/invoke/SerializedLambda;)Ljava/lang/Object;
  #422 = Utf8               scala/runtime/LambdaDeserialize
  #423 = Class              #422          // scala/runtime/LambdaDeserialize
  #424 = Utf8               bootstrap
  #425 = Utf8               (Ljava/lang/invoke/MethodHandles$Lookup;Ljava/lang/String;Ljava/lang/invoke/MethodType;[Ljava/lang/invoke/MethodHandle;)Ljava/lang/invoke/CallSite;
  #426 = NameAndType        #424:#425     // bootstrap:(Ljava/lang/invoke/MethodHandles$Lookup;Ljava/lang/String;Ljava/lang/invoke/MethodType;[Ljava/lang/invoke/MethodHandle;)Ljava/lang/invoke/CallSite;
  #427 = Methodref          #423.#426     // scala/runtime/LambdaDeserialize.bootstrap:(Ljava/lang/invoke/MethodHandles$Lookup;Ljava/lang/String;Ljava/lang/invoke/MethodType;[Ljava/lang/invoke/MethodHandle;)Ljava/lang/invoke/CallSite;
  #428 = MethodHandle       6:#427        // REF_invokeStatic scala/runtime/LambdaDeserialize.bootstrap:(Ljava/lang/invoke/MethodHandles$Lookup;Ljava/lang/String;Ljava/lang/invoke/MethodType;[Ljava/lang/invoke/MethodHandle;)Ljava/lang/invoke/CallSite;
  #429 = Utf8               lambdaDeserialize
  #430 = NameAndType        #429:#421     // lambdaDeserialize:(Ljava/lang/invoke/SerializedLambda;)Ljava/lang/Object;
  #431 = InvokeDynamic      #11:#430      // #11:lambdaDeserialize:(Ljava/lang/invoke/SerializedLambda;)Ljava/lang/Object;
  #432 = Utf8               Code
  #433 = Utf8               LineNumberTable
  #434 = Utf8               StackMapTable
  #435 = Utf8               LocalVariableTable
  #436 = Utf8               MethodParameters
  #437 = Utf8               Signature
  #438 = Utf8               InnerClasses
  #439 = Utf8               SourceFile
  #440 = Utf8               BootstrapMethods
  #441 = Utf8               ScalaInlineInfo
  #442 = Utf8               Scala
{
  public static final org.scalatest.exceptions.StackDepthExceptionHelper$ MODULE$;
    descriptor: Lorg/scalatest/exceptions/StackDepthExceptionHelper$;
    flags: (0x0019) ACC_PUBLIC, ACC_STATIC, ACC_FINAL

  public static {};
    descriptor: ()V
    flags: (0x0009) ACC_PUBLIC, ACC_STATIC
    Code:
      stack=2, locals=0, args_size=0
         0: new           #2                  // class org/scalatest/exceptions/StackDepthExceptionHelper$
         3: dup
         4: invokespecial #24                 // Method "<init>":()V
         7: putstatic     #26                 // Field MODULE$:Lorg/scalatest/exceptions/StackDepthExceptionHelper$;
        10: return
      LineNumberTable:
        line 102: 0

  public int getStackDepth(java.lang.StackTraceElement[], java.lang.String, java.lang.String, int);
    descriptor: ([Ljava/lang/StackTraceElement;Ljava/lang/String;Ljava/lang/String;I)I
    flags: (0x0001) ACC_PUBLIC
    Code:
      stack=3, locals=17, args_size=5
         0: getstatic     #37                 // Field scala/Predef$.MODULE$:Lscala/Predef$;
         3: aload_1
         4: checkcast     #39                 // class "[Ljava/lang/Object;"
         7: invokevirtual #43                 // Method scala/Predef$.wrapRefArray:([Ljava/lang/Object;)Lscala/collection/mutable/ArraySeq$ofRef;
        10: invokevirtual #47                 // Method scala/collection/mutable/ArraySeq$ofRef.toList:()Lscala/collection/immutable/List;
        13: astore        5
        15: aload         5
        17: aload_2
        18: invokedynamic #69,  0             // InvokeDynamic #0:apply:(Ljava/lang/String;)Lscala/Function1;
        23: invokevirtual #75                 // Method scala/collection/immutable/List.map:(Lscala/Function1;)Lscala/collection/immutable/List;
        26: astore        6
        28: aload         5
        30: aload_3
        31: invokedynamic #80,  0             // InvokeDynamic #1:apply:(Ljava/lang/String;)Lscala/Function1;
        36: invokevirtual #75                 // Method scala/collection/immutable/List.map:(Lscala/Function1;)Lscala/collection/immutable/List;
        39: astore        7
        41: aload         6
        43: iconst_1
        44: invokevirtual #84                 // Method scala/collection/immutable/List.dropRight:(I)Ljava/lang/Object;
        47: checkcast     #71                 // class scala/collection/immutable/List
        50: iconst_0
        51: invokestatic  #90                 // Method scala/runtime/BoxesRunTime.boxToBoolean:(Z)Ljava/lang/Boolean;
        54: invokevirtual #94                 // Method scala/collection/immutable/List.$colon$colon:(Ljava/lang/Object;)Lscala/collection/immutable/List;
        57: astore        8
        59: aload         7
        61: aload         8
        63: invokevirtual #98                 // Method scala/collection/immutable/List.zip:(Lscala/collection/IterableOnce;)Ljava/lang/Object;
        66: checkcast     #71                 // class scala/collection/immutable/List
        69: astore        9
        71: aload         9
        73: invokedynamic #107,  0            // InvokeDynamic #2:apply:()Lscala/Function1;
        78: invokevirtual #111                // Method scala/collection/immutable/List.withFilter:(Lscala/Function1;)Lscala/collection/WithFilter;
        81: invokedynamic #116,  0            // InvokeDynamic #3:apply:()Lscala/Function1;
        86: invokevirtual #121                // Method scala/collection/WithFilter.map:(Lscala/Function1;)Ljava/lang/Object;
        89: checkcast     #71                 // class scala/collection/immutable/List
        92: astore        10
        94: aload         6
        96: aload         10
        98: invokevirtual #98                 // Method scala/collection/immutable/List.zip:(Lscala/collection/IterableOnce;)Ljava/lang/Object;
       101: checkcast     #71                 // class scala/collection/immutable/List
       104: astore        11
       106: aload         11
       108: invokedynamic #126,  0            // InvokeDynamic #4:apply:()Lscala/Function1;
       113: invokevirtual #111                // Method scala/collection/immutable/List.withFilter:(Lscala/Function1;)Lscala/collection/WithFilter;
       116: invokedynamic #131,  0            // InvokeDynamic #5:apply:()Lscala/Function1;
       121: invokevirtual #121                // Method scala/collection/WithFilter.map:(Lscala/Function1;)Ljava/lang/Object;
       124: checkcast     #71                 // class scala/collection/immutable/List
       127: astore        12
       129: aload         12
       131: invokedynamic #136,  0            // InvokeDynamic #6:apply:()Lscala/Function1;
       136: invokevirtual #139                // Method scala/collection/immutable/List.takeWhile:(Lscala/Function1;)Lscala/collection/immutable/List;
       139: invokevirtual #143                // Method scala/collection/immutable/List.length:()I
       142: istore        13
       144: iload         13
       146: iconst_0
       147: if_icmpne     228
       150: aload_1
       151: iconst_0
       152: aaload
       153: invokevirtual #149                // Method java/lang/StackTraceElement.getFileName:()Ljava/lang/String;
       156: aload_2
       157: astore        15
       159: dup
       160: ifnonnull     172
       163: pop
       164: aload         15
       166: ifnull        228
       169: goto          180
       172: aload         15
       174: invokevirtual #153                // Method java/lang/Object.equals:(Ljava/lang/Object;)Z
       177: ifne          228
       180: aload_1
       181: iconst_0
       182: aaload
       183: invokevirtual #156                // Method java/lang/StackTraceElement.getMethodName:()Ljava/lang/String;
       186: aload_3
       187: astore        16
       189: dup
       190: ifnonnull     202
       193: pop
       194: aload         16
       196: ifnull        228
       199: goto          210
       202: aload         16
       204: invokevirtual #153                // Method java/lang/Object.equals:(Ljava/lang/Object;)Z
       207: ifne          228
       210: aload         5
       212: aload_2
       213: aload_3
       214: invokedynamic #164,  0            // InvokeDynamic #7:apply:(Ljava/lang/String;Ljava/lang/String;)Lscala/Function1;
       219: invokevirtual #139                // Method scala/collection/immutable/List.takeWhile:(Lscala/Function1;)Lscala/collection/immutable/List;
       222: invokevirtual #143                // Method scala/collection/immutable/List.length:()I
       225: goto          230
       228: iload         13
       230: istore        14
       232: iload         14
       234: iload         4
       236: iadd
       237: ireturn
      StackMapTable: number_of_entries = 6
        frame_type = 255 /* full_frame */
          offset_delta = 172
          locals = [ class org/scalatest/exceptions/StackDepthExceptionHelper$, class "[Ljava/lang/StackTraceElement;", class java/lang/String, class java/lang/String, int, class scala/collection/immutable/List, class scala/collection/immutable/List, class scala/collection/immutable/List, class scala/collection/immutable/List, class scala/collection/immutable/List, class scala/collection/immutable/List, class scala/collection/immutable/List, class scala/collection/immutable/List, int, top, class java/lang/String ]
          stack = [ class java/lang/String ]
        frame_type = 7 /* same */
        frame_type = 255 /* full_frame */
          offset_delta = 21
          locals = [ class org/scalatest/exceptions/StackDepthExceptionHelper$, class "[Ljava/lang/StackTraceElement;", class java/lang/String, class java/lang/String, int, class scala/collection/immutable/List, class scala/collection/immutable/List, class scala/collection/immutable/List, class scala/collection/immutable/List, class scala/collection/immutable/List, class scala/collection/immutable/List, class scala/collection/immutable/List, class scala/collection/immutable/List, int, top, class java/lang/String, class java/lang/String ]
          stack = [ class java/lang/String ]
        frame_type = 7 /* same */
        frame_type = 248 /* chop */
          offset_delta = 17
        frame_type = 65 /* same_locals_1_stack_item */
          stack = [ int ]
      LineNumberTable:
        line 105: 0
        line 108: 15
        line 112: 28
        line 118: 41
        line 122: 59
        line 124: 71
        line 128: 94
        line 130: 106
        line 133: 129
        line 134: 144
        line 135: 210
        line 137: 228
        line 139: 232
      LocalVariableTable:
        Start  Length  Slot  Name   Signature
           15     222     5 stackTraceList   Lscala/collection/immutable/List;
           28     209     6 fileNameIsDesiredList   Lscala/collection/immutable/List;
           41     196     7 methodNameIsDesiredList   Lscala/collection/immutable/List;
           59     178     8 previousFileNameIsDesiredList   Lscala/collection/immutable/List;
           71     166     9 zipped1   Lscala/collection/immutable/List;
           94     143    10 methodNameAndPreviousFileNameAreDesiredList   Lscala/collection/immutable/List;
          106     131    11 zipped2   Lscala/collection/immutable/List;
          129     108    12 includeInStackDepthList   Lscala/collection/immutable/List;
          144      93    13 includeDepth   I
          232       5    14 depth   I
            0     238     0  this   Lorg/scalatest/exceptions/StackDepthExceptionHelper$;
            0     238     1 stackTrace   [Ljava/lang/StackTraceElement;
            0     238     2 fileName   Ljava/lang/String;
            0     238     3 methodName   Ljava/lang/String;
            0     238     4 adjustment   I
    MethodParameters:
      Name                           Flags
      stackTrace                     final
      fileName                       final
      methodName                     final
      adjustment                     final

  public scala.Function1<org.scalatest.exceptions.StackDepthException, java.lang.Object> getStackDepthFun(java.lang.String, java.lang.String, int);
    descriptor: (Ljava/lang/String;Ljava/lang/String;I)Lscala/Function1;
    flags: (0x0001) ACC_PUBLIC
    Code:
      stack=3, locals=4, args_size=4
         0: aload_1
         1: aload_2
         2: iload_3
         3: invokedynamic #194,  0            // InvokeDynamic #8:apply:(Ljava/lang/String;Ljava/lang/String;I)Lscala/Function1;
         8: areturn
      LineNumberTable:
        line 142: 0
      LocalVariableTable:
        Start  Length  Slot  Name   Signature
            0       9     0  this   Lorg/scalatest/exceptions/StackDepthExceptionHelper$;
            0       9     1 fileName   Ljava/lang/String;
            0       9     2 methodName   Ljava/lang/String;
            0       9     3 adjustment   I
    Signature: #185                         // (Ljava/lang/String;Ljava/lang/String;I)Lscala/Function1<Lorg/scalatest/exceptions/StackDepthException;Ljava/lang/Object;>;
    MethodParameters:
      Name                           Flags
      fileName                       final
      methodName                     final
      adjustment                     final

  public boolean isMatch(java.lang.StackTraceElement, org.scalactic.source.Position);
    descriptor: (Ljava/lang/StackTraceElement;Lorg/scalactic/source/Position;)Z
    flags: (0x0001) ACC_PUBLIC
    Code:
      stack=2, locals=4, args_size=3
         0: aload_1
         1: invokevirtual #149                // Method java/lang/StackTraceElement.getFileName:()Ljava/lang/String;
         4: aload_2
         5: invokevirtual #202                // Method org/scalactic/source/Position.fileName:()Ljava/lang/String;
         8: astore_3
         9: dup
        10: ifnonnull     21
        13: pop
        14: aload_3
        15: ifnull        28
        18: goto          43
        21: aload_3
        22: invokevirtual #153                // Method java/lang/Object.equals:(Ljava/lang/Object;)Z
        25: ifeq          43
        28: aload_1
        29: invokevirtual #205                // Method java/lang/StackTraceElement.getLineNumber:()I
        32: aload_2
        33: invokevirtual #208                // Method org/scalactic/source/Position.lineNumber:()I
        36: if_icmpne     43
        39: iconst_1
        40: goto          44
        43: iconst_0
        44: ireturn
      StackMapTable: number_of_entries = 4
        frame_type = 255 /* full_frame */
          offset_delta = 21
          locals = [ class org/scalatest/exceptions/StackDepthExceptionHelper$, class java/lang/StackTraceElement, class org/scalactic/source/Position, class java/lang/String ]
          stack = [ class java/lang/String ]
        frame_type = 6 /* same */
        frame_type = 14 /* same */
        frame_type = 64 /* same_locals_1_stack_item */
          stack = [ int ]
      LineNumberTable:
        line 147: 0
      LocalVariableTable:
        Start  Length  Slot  Name   Signature
            0      45     0  this   Lorg/scalatest/exceptions/StackDepthExceptionHelper$;
            0      45     1   ele   Ljava/lang/StackTraceElement;
            0      45     2   pos   Lorg/scalactic/source/Position;
    MethodParameters:
      Name                           Flags
      ele                            final
      pos                            final

  public int getStackDepth(java.lang.StackTraceElement[], org.scalactic.source.Position);
    descriptor: ([Ljava/lang/StackTraceElement;Lorg/scalactic/source/Position;)I
    flags: (0x0001) ACC_PUBLIC
    Code:
      stack=4, locals=7, args_size=3
         0: getstatic     #37                 // Field scala/Predef$.MODULE$:Lscala/Predef$;
         3: aload_1
         4: checkcast     #39                 // class "[Ljava/lang/Object;"
         7: invokevirtual #215                // Method scala/Predef$.refArrayOps:([Ljava/lang/Object;)Ljava/lang/Object;
        10: astore        4
        12: aload_2
        13: invokedynamic #223,  0            // InvokeDynamic #9:apply:(Lorg/scalactic/source/Position;)Lscala/Function1;
        18: astore        5
        20: getstatic     #228                // Field scala/collection/ArrayOps$.MODULE$:Lscala/collection/ArrayOps$;
        23: aload         4
        25: invokevirtual #232                // Method scala/collection/ArrayOps$.indexWhere$default$2$extension:(Ljava/lang/Object;)I
        28: istore        6
        30: getstatic     #228                // Field scala/collection/ArrayOps$.MODULE$:Lscala/collection/ArrayOps$;
        33: aload         4
        35: aload         5
        37: iload         6
        39: invokevirtual #236                // Method scala/collection/ArrayOps$.indexWhere$extension:(Ljava/lang/Object;Lscala/Function1;I)I
        42: istore_3
        43: iload_3
        44: iconst_0
        45: if_icmplt     52
        48: iload_3
        49: goto          53
        52: iconst_0
        53: ireturn
      StackMapTable: number_of_entries = 2
        frame_type = 255 /* full_frame */
          offset_delta = 52
          locals = [ class org/scalatest/exceptions/StackDepthExceptionHelper$, class "[Ljava/lang/StackTraceElement;", class org/scalactic/source/Position, int, class java/lang/Object, class scala/Function1, int ]
          stack = []
        frame_type = 64 /* same_locals_1_stack_item */
          stack = [ int ]
      LineNumberTable:
        line 150: 0
        line 151: 43
      LocalVariableTable:
        Start  Length  Slot  Name   Signature
           12      30     4 qual$1   Ljava/lang/Object;
           20      22     5   x$1   Lscala/Function1;
           30      12     6   x$2   I
           43      10     3   idx   I
            0      54     0  this   Lorg/scalatest/exceptions/StackDepthExceptionHelper$;
            0      54     1 stackTrace   [Ljava/lang/StackTraceElement;
            0      54     2   pos   Lorg/scalactic/source/Position;
    MethodParameters:
      Name                           Flags
      stackTrace                     final
      pos                            final

  public int getStackDepth$default$4();
    descriptor: ()I
    flags: (0x0001) ACC_PUBLIC
    Code:
      stack=1, locals=1, args_size=1
         0: iconst_0
         1: ireturn
      LineNumberTable:
        line 104: 0
      LocalVariableTable:
        Start  Length  Slot  Name   Signature
            0       2     0  this   Lorg/scalatest/exceptions/StackDepthExceptionHelper$;

  public scala.Function1<org.scalatest.exceptions.StackDepthException, java.lang.Object> getStackDepthFun(org.scalactic.source.Position);
    descriptor: (Lorg/scalactic/source/Position;)Lscala/Function1;
    flags: (0x0001) ACC_PUBLIC
    Code:
      stack=1, locals=2, args_size=2
         0: aload_1
         1: invokedynamic #252,  0            // InvokeDynamic #10:apply:(Lorg/scalactic/source/Position;)Lscala/Function1;
         6: areturn
      LineNumberTable:
        line 154: 0
      LocalVariableTable:
        Start  Length  Slot  Name   Signature
            0       7     0  this   Lorg/scalatest/exceptions/StackDepthExceptionHelper$;
            0       7     1   pos   Lorg/scalactic/source/Position;
    Signature: #246                         // (Lorg/scalactic/source/Position;)Lscala/Function1<Lorg/scalatest/exceptions/StackDepthException;Ljava/lang/Object;>;
    MethodParameters:
      Name                           Flags
      pos                            final

  public int getStackDepthFun$default$3();
    descriptor: ()I
    flags: (0x0001) ACC_PUBLIC
    Code:
      stack=1, locals=1, args_size=1
         0: iconst_0
         1: ireturn
      LineNumberTable:
        line 142: 0
      LocalVariableTable:
        Start  Length  Slot  Name   Signature
            0       2     0  this   Lorg/scalatest/exceptions/StackDepthExceptionHelper$;

  public scala.Option<java.lang.String> getFailedCodeFileName(java.lang.StackTraceElement);
    descriptor: (Ljava/lang/StackTraceElement;)Lscala/Option;
    flags: (0x0001) ACC_PUBLIC
    Code:
      stack=3, locals=3, args_size=2
         0: aload_1
         1: invokevirtual #149                // Method java/lang/StackTraceElement.getFileName:()Ljava/lang/String;
         4: astore_2
         5: aload_2
         6: ifnull        20
         9: new           #259                // class scala/Some
        12: dup
        13: aload_2
        14: invokespecial #262                // Method scala/Some."<init>":(Ljava/lang/Object;)V
        17: goto          23
        20: getstatic     #267                // Field scala/None$.MODULE$:Lscala/None$;
        23: areturn
      StackMapTable: number_of_entries = 2
        frame_type = 252 /* append */
          offset_delta = 20
          locals = [ class java/lang/String ]
        frame_type = 66 /* same_locals_1_stack_item */
          stack = [ class scala/Option ]
      LineNumberTable:
        line 159: 0
        line 160: 5
        line 161: 9
        line 163: 20
      LocalVariableTable:
        Start  Length  Slot  Name   Signature
            5      18     2 fileName   Ljava/lang/String;
            0      24     0  this   Lorg/scalatest/exceptions/StackDepthExceptionHelper$;
            0      24     1 stackTraceElement   Ljava/lang/StackTraceElement;
    Signature: #256                         // (Ljava/lang/StackTraceElement;)Lscala/Option<Ljava/lang/String;>;
    MethodParameters:
      Name                           Flags
      stackTraceElement              final

  public scala.util.Either<org.scalactic.source.Position, scala.Function1<org.scalatest.exceptions.StackDepthException, java.lang.Object>> posOrElseStackDepthFun(scala.Option<org.scalactic.source.Position>, scala.Function1<org.scalatest.exceptions.StackDepthException, java.lang.Object>);
    descriptor: (Lscala/Option;Lscala/Function1;)Lscala/util/Either;
    flags: (0x0001) ACC_PUBLIC
    Code:
      stack=3, locals=11, args_size=3
         0: aload_1
         1: ifnonnull     15
         4: new           #275                // class org/scalactic/exceptions/NullArgumentException
         7: dup
         8: ldc_w         #277                // String pos was null
        11: invokespecial #280                // Method org/scalactic/exceptions/NullArgumentException."<init>":(Ljava/lang/String;)V
        14: athrow
        15: aload_2
        16: ifnonnull     30
        19: new           #275                // class org/scalactic/exceptions/NullArgumentException
        22: dup
        23: ldc_w         #282                // String sdf was null
        26: invokespecial #280                // Method org/scalactic/exceptions/NullArgumentException."<init>":(Ljava/lang/String;)V
        29: athrow
        30: aload_1
        31: astore        5
        33: aload         5
        35: instanceof    #259                // class scala/Some
        38: ifeq          77
        41: aload         5
        43: checkcast     #259                // class scala/Some
        46: astore        6
        48: aload         6
        50: invokevirtual #286                // Method scala/Some.value:()Ljava/lang/Object;
        53: checkcast     #200                // class org/scalactic/source/Position
        56: astore        7
        58: aload         7
        60: ifnonnull     74
        63: new           #275                // class org/scalactic/exceptions/NullArgumentException
        66: dup
        67: ldc_w         #288                // String pos was Some(null)
        70: invokespecial #280                // Method org/scalactic/exceptions/NullArgumentException."<init>":(Ljava/lang/String;)V
        73: athrow
        74: goto          80
        77: goto          80
        80: getstatic     #294                // Field scala/runtime/BoxedUnit.UNIT:Lscala/runtime/BoxedUnit;
        83: astore        4
        85: goto          88
        88: aload_1
        89: astore        8
        91: aload         8
        93: instanceof    #259                // class scala/Some
        96: ifeq          131
        99: aload         8
       101: checkcast     #259                // class scala/Some
       104: astore        9
       106: aload         9
       108: invokevirtual #286                // Method scala/Some.value:()Ljava/lang/Object;
       111: checkcast     #200                // class org/scalactic/source/Position
       114: astore        10
       116: getstatic     #299                // Field scala/package$.MODULE$:Lscala/package$;
       119: invokevirtual #303                // Method scala/package$.Left:()Lscala/util/Left$;
       122: aload         10
       124: invokevirtual #308                // Method scala/util/Left$.apply:(Ljava/lang/Object;)Lscala/util/Left;
       127: astore_3
       128: goto          172
       131: goto          134
       134: getstatic     #267                // Field scala/None$.MODULE$:Lscala/None$;
       137: aload         8
       139: invokevirtual #153                // Method java/lang/Object.equals:(Ljava/lang/Object;)Z
       142: ifeq          159
       145: getstatic     #299                // Field scala/package$.MODULE$:Lscala/package$;
       148: invokevirtual #312                // Method scala/package$.Right:()Lscala/util/Right$;
       151: aload_2
       152: invokevirtual #317                // Method scala/util/Right$.apply:(Ljava/lang/Object;)Lscala/util/Right;
       155: astore_3
       156: goto          172
       159: goto          162
       162: new           #319                // class scala/MatchError
       165: dup
       166: aload         8
       168: invokespecial #320                // Method scala/MatchError."<init>":(Ljava/lang/Object;)V
       171: athrow
       172: aload_3
       173: areturn
      StackMapTable: number_of_entries = 11
        frame_type = 15 /* same */
        frame_type = 14 /* same */
        frame_type = 255 /* full_frame */
          offset_delta = 43
          locals = [ class org/scalatest/exceptions/StackDepthExceptionHelper$, class scala/Option, class scala/Function1, top, top, class scala/Option, class scala/Some, class org/scalactic/source/Position ]
          stack = []
        frame_type = 249 /* chop */
          offset_delta = 2
        frame_type = 2 /* same */
        frame_type = 255 /* full_frame */
          offset_delta = 7
          locals = [ class org/scalatest/exceptions/StackDepthExceptionHelper$, class scala/Option, class scala/Function1, top, class scala/runtime/BoxedUnit, class scala/Option ]
          stack = []
        frame_type = 254 /* append */
          offset_delta = 42
          locals = [ top, top, class scala/Option ]
        frame_type = 2 /* same */
        frame_type = 24 /* same */
        frame_type = 2 /* same */
        frame_type = 255 /* full_frame */
          offset_delta = 9
          locals = [ class org/scalatest/exceptions/StackDepthExceptionHelper$, class scala/Option, class scala/Function1, class scala/util/Either, class scala/runtime/BoxedUnit, class scala/Option, top, top, class scala/Option ]
          stack = []
      LineNumberTable:
        line 168: 0
        line 169: 15
        line 170: 30
        line 171: 33
        line 172: 80
        line 174: 88
        line 175: 91
        line 176: 134
        line 174: 162
      LocalVariableTable:
        Start  Length  Slot  Name   Signature
          116      15    10   pos   Lorg/scalactic/source/Position;
            0     174     0  this   Lorg/scalatest/exceptions/StackDepthExceptionHelper$;
            0     174     1   pos   Lscala/Option;
            0     174     2   sdf   Lscala/Function1;
    Signature: #272                         // (Lscala/Option<Lorg/scalactic/source/Position;>;Lscala/Function1<Lorg/scalatest/exceptions/StackDepthException;Ljava/lang/Object;>;)Lscala/util/Either<Lorg/scalactic/source/Position;Lscala/Function1<Lorg/scalatest/exceptions/StackDepthException;Ljava/lang/Object;>;>;
    MethodParameters:
      Name                           Flags
      pos                            final
      sdf                            final

  private java.lang.Object writeReplace();
    descriptor: ()Ljava/lang/Object;
    flags: (0x0002) ACC_PRIVATE
    Code:
      stack=3, locals=1, args_size=1
         0: new           #326                // class scala/runtime/ModuleSerializationProxy
         3: dup
         4: ldc           #2                  // class org/scalatest/exceptions/StackDepthExceptionHelper$
         6: invokespecial #329                // Method scala/runtime/ModuleSerializationProxy."<init>":(Ljava/lang/Class;)V
         9: areturn
      LineNumberTable:
        line 102: 0
      LocalVariableTable:
        Start  Length  Slot  Name   Signature
            0      10     0  this   Lorg/scalatest/exceptions/StackDepthExceptionHelper$;

  public static final boolean $anonfun$getStackDepth$1(java.lang.String, java.lang.StackTraceElement);
    descriptor: (Ljava/lang/String;Ljava/lang/StackTraceElement;)Z
    flags: (0x1019) ACC_PUBLIC, ACC_STATIC, ACC_FINAL, ACC_SYNTHETIC
    Code:
      stack=2, locals=3, args_size=2
         0: aload_1
         1: invokevirtual #149                // Method java/lang/StackTraceElement.getFileName:()Ljava/lang/String;
         4: aload_0
         5: astore_2
         6: dup
         7: ifnonnull     18
        10: pop
        11: aload_2
        12: ifnull        25
        15: goto          29
        18: aload_2
        19: invokevirtual #153                // Method java/lang/Object.equals:(Ljava/lang/Object;)Z
        22: ifeq          29
        25: iconst_1
        26: goto          30
        29: iconst_0
        30: ireturn
      StackMapTable: number_of_entries = 4
        frame_type = 255 /* full_frame */
          offset_delta = 18
          locals = [ class java/lang/String, class java/lang/StackTraceElement, class java/lang/String ]
          stack = [ class java/lang/String ]
        frame_type = 6 /* same */
        frame_type = 3 /* same */
        frame_type = 64 /* same_locals_1_stack_item */
          stack = [ int ]
      LineNumberTable:
        line 109: 0
      LocalVariableTable:
        Start  Length  Slot  Name   Signature
            0      31     0 fileName$1   Ljava/lang/String;
            0      31     1 element   Ljava/lang/StackTraceElement;
    MethodParameters:
      Name                           Flags
      fileName$1                     final
      element                        final

  public static final boolean $anonfun$getStackDepth$2(java.lang.String, java.lang.StackTraceElement);
    descriptor: (Ljava/lang/String;Ljava/lang/StackTraceElement;)Z
    flags: (0x1019) ACC_PUBLIC, ACC_STATIC, ACC_FINAL, ACC_SYNTHETIC
    Code:
      stack=2, locals=3, args_size=2
         0: aload_1
         1: invokevirtual #156                // Method java/lang/StackTraceElement.getMethodName:()Ljava/lang/String;
         4: aload_0
         5: astore_2
         6: dup
         7: ifnonnull     18
        10: pop
        11: aload_2
        12: ifnull        25
        15: goto          29
        18: aload_2
        19: invokevirtual #153                // Method java/lang/Object.equals:(Ljava/lang/Object;)Z
        22: ifeq          29
        25: iconst_1
        26: goto          30
        29: iconst_0
        30: ireturn
      StackMapTable: number_of_entries = 4
        frame_type = 255 /* full_frame */
          offset_delta = 18
          locals = [ class java/lang/String, class java/lang/StackTraceElement, class java/lang/String ]
          stack = [ class java/lang/String ]
        frame_type = 6 /* same */
        frame_type = 3 /* same */
        frame_type = 64 /* same_locals_1_stack_item */
          stack = [ int ]
      LineNumberTable:
        line 113: 0
      LocalVariableTable:
        Start  Length  Slot  Name   Signature
            0      31     0 methodName$1   Ljava/lang/String;
            0      31     1 element   Ljava/lang/StackTraceElement;
    MethodParameters:
      Name                           Flags
      methodName$1                   final
      element                        final

  public static final boolean $anonfun$getStackDepth$3(scala.Tuple2);
    descriptor: (Lscala/Tuple2;)Z
    flags: (0x1019) ACC_PUBLIC, ACC_STATIC, ACC_FINAL, ACC_SYNTHETIC
    Code:
      stack=1, locals=3, args_size=1
         0: aload_0
         1: astore_2
         2: aload_2
         3: ifnull        11
         6: iconst_1
         7: istore_1
         8: goto          19
        11: goto          14
        14: iconst_0
        15: istore_1
        16: goto          19
        19: iload_1
        20: ireturn
      StackMapTable: number_of_entries = 3
        frame_type = 253 /* append */
          offset_delta = 11
          locals = [ top, class scala/Tuple2 ]
        frame_type = 2 /* same */
        frame_type = 255 /* full_frame */
          offset_delta = 4
          locals = [ class scala/Tuple2, int, class scala/Tuple2 ]
          stack = []
      LineNumberTable:
        line 124: 0
      LocalVariableTable:
        Start  Length  Slot  Name   Signature
            0      21     0 check$ifrefutable$1   Lscala/Tuple2;
    MethodParameters:
      Name                           Flags
      check$ifrefutable$1            final

  public static final boolean $anonfun$getStackDepth$4(scala.Tuple2);
    descriptor: (Lscala/Tuple2;)Z
    flags: (0x1019) ACC_PUBLIC, ACC_STATIC, ACC_FINAL, ACC_SYNTHETIC
    Code:
      stack=3, locals=5, args_size=1
         0: aload_0
         1: astore_2
         2: aload_2
         3: ifnull        35
         6: aload_2
         7: invokevirtual #346                // Method scala/Tuple2._1$mcZ$sp:()Z
        10: istore_3
        11: aload_2
        12: invokevirtual #349                // Method scala/Tuple2._2$mcZ$sp:()Z
        15: istore        4
        17: iload_3
        18: ifeq          30
        21: iload         4
        23: ifeq          30
        26: iconst_1
        27: goto          31
        30: iconst_0
        31: istore_1
        32: goto          47
        35: goto          38
        38: new           #319                // class scala/MatchError
        41: dup
        42: aload_2
        43: invokespecial #320                // Method scala/MatchError."<init>":(Ljava/lang/Object;)V
        46: athrow
        47: iload_1
        48: ireturn
      StackMapTable: number_of_entries = 5
        frame_type = 255 /* full_frame */
          offset_delta = 30
          locals = [ class scala/Tuple2, top, class scala/Tuple2, int, int ]
          stack = []
        frame_type = 64 /* same_locals_1_stack_item */
          stack = [ int ]
        frame_type = 249 /* chop */
          offset_delta = 3
        frame_type = 2 /* same */
        frame_type = 255 /* full_frame */
          offset_delta = 8
          locals = [ class scala/Tuple2, int, class scala/Tuple2, int, int ]
          stack = []
      LineNumberTable:
        line 124: 0
        line 125: 17
        line 124: 35
      LocalVariableTable:
        Start  Length  Slot  Name   Signature
           11      24     3 methodNameIsDesired   Z
           17      18     4 previousFileNameIsDesired   Z
            0      49     0   x$1   Lscala/Tuple2;
    MethodParameters:
      Name                           Flags
      x$1                            final

  public static final boolean $anonfun$getStackDepth$5(scala.Tuple2);
    descriptor: (Lscala/Tuple2;)Z
    flags: (0x1019) ACC_PUBLIC, ACC_STATIC, ACC_FINAL, ACC_SYNTHETIC
    Code:
      stack=1, locals=3, args_size=1
         0: aload_0
         1: astore_2
         2: aload_2
         3: ifnull        11
         6: iconst_1
         7: istore_1
         8: goto          19
        11: goto          14
        14: iconst_0
        15: istore_1
        16: goto          19
        19: iload_1
        20: ireturn
      StackMapTable: number_of_entries = 3
        frame_type = 253 /* append */
          offset_delta = 11
          locals = [ top, class scala/Tuple2 ]
        frame_type = 2 /* same */
        frame_type = 255 /* full_frame */
          offset_delta = 4
          locals = [ class scala/Tuple2, int, class scala/Tuple2 ]
          stack = []
      LineNumberTable:
        line 130: 0
      LocalVariableTable:
        Start  Length  Slot  Name   Signature
            0      21     0 check$ifrefutable$2   Lscala/Tuple2;
    MethodParameters:
      Name                           Flags
      check$ifrefutable$2            final

  public static final boolean $anonfun$getStackDepth$6(scala.Tuple2);
    descriptor: (Lscala/Tuple2;)Z
    flags: (0x1019) ACC_PUBLIC, ACC_STATIC, ACC_FINAL, ACC_SYNTHETIC
    Code:
      stack=3, locals=5, args_size=1
         0: aload_0
         1: astore_2
         2: aload_2
         3: ifnull        35
         6: aload_2
         7: invokevirtual #346                // Method scala/Tuple2._1$mcZ$sp:()Z
        10: istore_3
        11: aload_2
        12: invokevirtual #349                // Method scala/Tuple2._2$mcZ$sp:()Z
        15: istore        4
        17: iload_3
        18: ifne          26
        21: iload         4
        23: ifeq          30
        26: iconst_1
        27: goto          31
        30: iconst_0
        31: istore_1
        32: goto          47
        35: goto          38
        38: new           #319                // class scala/MatchError
        41: dup
        42: aload_2
        43: invokespecial #320                // Method scala/MatchError."<init>":(Ljava/lang/Object;)V
        46: athrow
        47: iload_1
        48: ireturn
      StackMapTable: number_of_entries = 6
        frame_type = 255 /* full_frame */
          offset_delta = 26
          locals = [ class scala/Tuple2, top, class scala/Tuple2, int, int ]
          stack = []
        frame_type = 3 /* same */
        frame_type = 64 /* same_locals_1_stack_item */
          stack = [ int ]
        frame_type = 249 /* chop */
          offset_delta = 3
        frame_type = 2 /* same */
        frame_type = 255 /* full_frame */
          offset_delta = 8
          locals = [ class scala/Tuple2, int, class scala/Tuple2, int, int ]
          stack = []
      LineNumberTable:
        line 130: 0
        line 131: 17
        line 130: 35
      LocalVariableTable:
        Start  Length  Slot  Name   Signature
           11      24     3 fileNameIsDesired   Z
           17      18     4 methodNameAndPreviousFileNameAreDesired   Z
            0      49     0   x$2   Lscala/Tuple2;
    MethodParameters:
      Name                           Flags
      x$2                            final

  public static final boolean $anonfun$getStackDepth$7(boolean);
    descriptor: (Z)Z
    flags: (0x1019) ACC_PUBLIC, ACC_STATIC, ACC_FINAL, ACC_SYNTHETIC
    Code:
      stack=1, locals=1, args_size=1
         0: iload_0
         1: ireturn
      LineNumberTable:
        line 133: 0
      LocalVariableTable:
        Start  Length  Slot  Name   Signature
            0       2     0 include   Z
    MethodParameters:
      Name                           Flags
      include                        final

  public static final boolean $anonfun$getStackDepth$8(java.lang.String, java.lang.String, java.lang.StackTraceElement);
    descriptor: (Ljava/lang/String;Ljava/lang/String;Ljava/lang/StackTraceElement;)Z
    flags: (0x1019) ACC_PUBLIC, ACC_STATIC, ACC_FINAL, ACC_SYNTHETIC
    Code:
      stack=2, locals=5, args_size=3
         0: aload_2
         1: invokevirtual #149                // Method java/lang/StackTraceElement.getFileName:()Ljava/lang/String;
         4: aload_0
         5: astore_3
         6: dup
         7: ifnonnull     18
        10: pop
        11: aload_3
        12: ifnull        25
        15: goto          53
        18: aload_3
        19: invokevirtual #153                // Method java/lang/Object.equals:(Ljava/lang/Object;)Z
        22: ifeq          53
        25: aload_2
        26: invokevirtual #156                // Method java/lang/StackTraceElement.getMethodName:()Ljava/lang/String;
        29: aload_1
        30: astore        4
        32: dup
        33: ifnonnull     45
        36: pop
        37: aload         4
        39: ifnull        57
        42: goto          53
        45: aload         4
        47: invokevirtual #153                // Method java/lang/Object.equals:(Ljava/lang/Object;)Z
        50: ifne          57
        53: iconst_1
        54: goto          58
        57: iconst_0
        58: ireturn
      StackMapTable: number_of_entries = 6
        frame_type = 255 /* full_frame */
          offset_delta = 18
          locals = [ class java/lang/String, class java/lang/String, class java/lang/StackTraceElement, class java/lang/String ]
          stack = [ class java/lang/String ]
        frame_type = 6 /* same */
        frame_type = 255 /* full_frame */
          offset_delta = 19
          locals = [ class java/lang/String, class java/lang/String, class java/lang/StackTraceElement, class java/lang/String, class java/lang/String ]
          stack = [ class java/lang/String ]
        frame_type = 250 /* chop */
          offset_delta = 7
        frame_type = 252 /* append */
          offset_delta = 3
          locals = [ class java/lang/String ]
        frame_type = 255 /* full_frame */
          offset_delta = 0
          locals = [ class java/lang/String, class java/lang/String, class java/lang/StackTraceElement, class java/lang/String ]
          stack = [ int ]
      LineNumberTable:
        line 135: 0
      LocalVariableTable:
        Start  Length  Slot  Name   Signature
            0      59     0 fileName$1   Ljava/lang/String;
            0      59     1 methodName$1   Ljava/lang/String;
            0      59     2    st   Ljava/lang/StackTraceElement;
    MethodParameters:
      Name                           Flags
      fileName$1                     final
      methodName$1                   final
      st                             final

  public static final int $anonfun$getStackDepthFun$1(java.lang.String, java.lang.String, int, org.scalatest.exceptions.StackDepthException);
    descriptor: (Ljava/lang/String;Ljava/lang/String;ILorg/scalatest/exceptions/StackDepthException;)I
    flags: (0x1019) ACC_PUBLIC, ACC_STATIC, ACC_FINAL, ACC_SYNTHETIC
    Code:
      stack=5, locals=4, args_size=4
         0: getstatic     #26                 // Field MODULE$:Lorg/scalatest/exceptions/StackDepthExceptionHelper$;
         3: aload_3
         4: invokevirtual #375                // Method org/scalatest/exceptions/StackDepthException.getStackTrace:()[Ljava/lang/StackTraceElement;
         7: aload_0
         8: aload_1
         9: iload_2
        10: invokevirtual #377                // Method getStackDepth:([Ljava/lang/StackTraceElement;Ljava/lang/String;Ljava/lang/String;I)I
        13: ireturn
      LineNumberTable:
        line 143: 0
      LocalVariableTable:
        Start  Length  Slot  Name   Signature
            0      14     0 fileName$2   Ljava/lang/String;
            0      14     1 methodName$2   Ljava/lang/String;
            0      14     2 adjustment$1   I
            0      14     3   sde   Lorg/scalatest/exceptions/StackDepthException;
    MethodParameters:
      Name                           Flags
      fileName$2                     final
      methodName$2                   final
      adjustment$1                   final
      sde                            final

  public static final boolean $anonfun$getStackDepth$9(org.scalactic.source.Position, java.lang.StackTraceElement);
    descriptor: (Lorg/scalactic/source/Position;Ljava/lang/StackTraceElement;)Z
    flags: (0x1019) ACC_PUBLIC, ACC_STATIC, ACC_FINAL, ACC_SYNTHETIC
    Code:
      stack=3, locals=2, args_size=2
         0: getstatic     #26                 // Field MODULE$:Lorg/scalatest/exceptions/StackDepthExceptionHelper$;
         3: aload_1
         4: aload_0
         5: invokevirtual #384                // Method isMatch:(Ljava/lang/StackTraceElement;Lorg/scalactic/source/Position;)Z
         8: ireturn
      LineNumberTable:
        line 150: 0
      LocalVariableTable:
        Start  Length  Slot  Name   Signature
            0       9     0 pos$1   Lorg/scalactic/source/Position;
            0       9     1     e   Ljava/lang/StackTraceElement;
    MethodParameters:
      Name                           Flags
      pos$1                          final
      e                              final

  public static final int $anonfun$getStackDepthFun$2(org.scalactic.source.Position, org.scalatest.exceptions.StackDepthException);
    descriptor: (Lorg/scalactic/source/Position;Lorg/scalatest/exceptions/StackDepthException;)I
    flags: (0x1019) ACC_PUBLIC, ACC_STATIC, ACC_FINAL, ACC_SYNTHETIC
    Code:
      stack=3, locals=2, args_size=2
         0: getstatic     #26                 // Field MODULE$:Lorg/scalatest/exceptions/StackDepthExceptionHelper$;
         3: aload_1
         4: invokevirtual #375                // Method org/scalatest/exceptions/StackDepthException.getStackTrace:()[Ljava/lang/StackTraceElement;
         7: aload_0
         8: invokevirtual #389                // Method getStackDepth:([Ljava/lang/StackTraceElement;Lorg/scalactic/source/Position;)I
        11: ireturn
      LineNumberTable:
        line 155: 0
      LocalVariableTable:
        Start  Length  Slot  Name   Signature
            0      12     0 pos$2   Lorg/scalactic/source/Position;
            0      12     1   sde   Lorg/scalatest/exceptions/StackDepthException;
    MethodParameters:
      Name                           Flags
      pos$2                          final
      sde                            final

  private org.scalatest.exceptions.StackDepthExceptionHelper$();
    descriptor: ()V
    flags: (0x0002) ACC_PRIVATE
    Code:
      stack=1, locals=1, args_size=1
         0: aload_0
         1: invokespecial #390                // Method java/lang/Object."<init>":()V
         4: return
      LineNumberTable:
        line 102: 0
      LocalVariableTable:
        Start  Length  Slot  Name   Signature
            0       5     0  this   Lorg/scalatest/exceptions/StackDepthExceptionHelper$;

  public static final java.lang.Object $anonfun$getStackDepth$1$adapted(java.lang.String, java.lang.StackTraceElement);
    descriptor: (Ljava/lang/String;Ljava/lang/StackTraceElement;)Ljava/lang/Object;
    flags: (0x1019) ACC_PUBLIC, ACC_STATIC, ACC_FINAL, ACC_SYNTHETIC
    Code:
      stack=2, locals=2, args_size=2
         0: aload_0
         1: aload_1
         2: invokestatic  #392                // Method $anonfun$getStackDepth$1:(Ljava/lang/String;Ljava/lang/StackTraceElement;)Z
         5: invokestatic  #90                 // Method scala/runtime/BoxesRunTime.boxToBoolean:(Z)Ljava/lang/Boolean;
         8: areturn
      LineNumberTable:
        line 108: 0
      LocalVariableTable:
        Start  Length  Slot  Name   Signature
            0       9     0 fileName$1   Ljava/lang/String;
            0       9     1 element   Ljava/lang/StackTraceElement;
    MethodParameters:
      Name                           Flags
      fileName$1                     final
      element                        final

  public static final java.lang.Object $anonfun$getStackDepth$2$adapted(java.lang.String, java.lang.StackTraceElement);
    descriptor: (Ljava/lang/String;Ljava/lang/StackTraceElement;)Ljava/lang/Object;
    flags: (0x1019) ACC_PUBLIC, ACC_STATIC, ACC_FINAL, ACC_SYNTHETIC
    Code:
      stack=2, locals=2, args_size=2
         0: aload_0
         1: aload_1
         2: invokestatic  #394                // Method $anonfun$getStackDepth$2:(Ljava/lang/String;Ljava/lang/StackTraceElement;)Z
         5: invokestatic  #90                 // Method scala/runtime/BoxesRunTime.boxToBoolean:(Z)Ljava/lang/Boolean;
         8: areturn
      LineNumberTable:
        line 112: 0
      LocalVariableTable:
        Start  Length  Slot  Name   Signature
            0       9     0 methodName$1   Ljava/lang/String;
            0       9     1 element   Ljava/lang/StackTraceElement;
    MethodParameters:
      Name                           Flags
      methodName$1                   final
      element                        final

  public static final java.lang.Object $anonfun$getStackDepth$3$adapted(scala.Tuple2);
    descriptor: (Lscala/Tuple2;)Ljava/lang/Object;
    flags: (0x1019) ACC_PUBLIC, ACC_STATIC, ACC_FINAL, ACC_SYNTHETIC
    Code:
      stack=1, locals=1, args_size=1
         0: aload_0
         1: invokestatic  #396                // Method $anonfun$getStackDepth$3:(Lscala/Tuple2;)Z
         4: invokestatic  #90                 // Method scala/runtime/BoxesRunTime.boxToBoolean:(Z)Ljava/lang/Boolean;
         7: areturn
      LineNumberTable:
        line 124: 0
      LocalVariableTable:
        Start  Length  Slot  Name   Signature
            0       8     0 check$ifrefutable$1   Lscala/Tuple2;
    MethodParameters:
      Name                           Flags
      check$ifrefutable$1            final

  public static final java.lang.Object $anonfun$getStackDepth$4$adapted(scala.Tuple2);
    descriptor: (Lscala/Tuple2;)Ljava/lang/Object;
    flags: (0x1019) ACC_PUBLIC, ACC_STATIC, ACC_FINAL, ACC_SYNTHETIC
    Code:
      stack=1, locals=1, args_size=1
         0: aload_0
         1: invokestatic  #398                // Method $anonfun$getStackDepth$4:(Lscala/Tuple2;)Z
         4: invokestatic  #90                 // Method scala/runtime/BoxesRunTime.boxToBoolean:(Z)Ljava/lang/Boolean;
         7: areturn
      LineNumberTable:
        line 124: 0
      LocalVariableTable:
        Start  Length  Slot  Name   Signature
            0       8     0   x$1   Lscala/Tuple2;
    MethodParameters:
      Name                           Flags
      x$1                            final

  public static final java.lang.Object $anonfun$getStackDepth$5$adapted(scala.Tuple2);
    descriptor: (Lscala/Tuple2;)Ljava/lang/Object;
    flags: (0x1019) ACC_PUBLIC, ACC_STATIC, ACC_FINAL, ACC_SYNTHETIC
    Code:
      stack=1, locals=1, args_size=1
         0: aload_0
         1: invokestatic  #400                // Method $anonfun$getStackDepth$5:(Lscala/Tuple2;)Z
         4: invokestatic  #90                 // Method scala/runtime/BoxesRunTime.boxToBoolean:(Z)Ljava/lang/Boolean;
         7: areturn
      LineNumberTable:
        line 130: 0
      LocalVariableTable:
        Start  Length  Slot  Name   Signature
            0       8     0 check$ifrefutable$2   Lscala/Tuple2;
    MethodParameters:
      Name                           Flags
      check$ifrefutable$2            final

  public static final java.lang.Object $anonfun$getStackDepth$6$adapted(scala.Tuple2);
    descriptor: (Lscala/Tuple2;)Ljava/lang/Object;
    flags: (0x1019) ACC_PUBLIC, ACC_STATIC, ACC_FINAL, ACC_SYNTHETIC
    Code:
      stack=1, locals=1, args_size=1
         0: aload_0
         1: invokestatic  #402                // Method $anonfun$getStackDepth$6:(Lscala/Tuple2;)Z
         4: invokestatic  #90                 // Method scala/runtime/BoxesRunTime.boxToBoolean:(Z)Ljava/lang/Boolean;
         7: areturn
      LineNumberTable:
        line 130: 0
      LocalVariableTable:
        Start  Length  Slot  Name   Signature
            0       8     0   x$2   Lscala/Tuple2;
    MethodParameters:
      Name                           Flags
      x$2                            final

  public static final java.lang.Object $anonfun$getStackDepth$7$adapted(java.lang.Object);
    descriptor: (Ljava/lang/Object;)Ljava/lang/Object;
    flags: (0x1019) ACC_PUBLIC, ACC_STATIC, ACC_FINAL, ACC_SYNTHETIC
    Code:
      stack=1, locals=1, args_size=1
         0: aload_0
         1: invokestatic  #405                // Method scala/runtime/BoxesRunTime.unboxToBoolean:(Ljava/lang/Object;)Z
         4: invokestatic  #407                // Method $anonfun$getStackDepth$7:(Z)Z
         7: invokestatic  #90                 // Method scala/runtime/BoxesRunTime.boxToBoolean:(Z)Ljava/lang/Boolean;
        10: areturn
      LineNumberTable:
        line 133: 0
      LocalVariableTable:
        Start  Length  Slot  Name   Signature
            0      11     0 include   Ljava/lang/Object;
    MethodParameters:
      Name                           Flags
      include                        final

  public static final java.lang.Object $anonfun$getStackDepth$8$adapted(java.lang.String, java.lang.String, java.lang.StackTraceElement);
    descriptor: (Ljava/lang/String;Ljava/lang/String;Ljava/lang/StackTraceElement;)Ljava/lang/Object;
    flags: (0x1019) ACC_PUBLIC, ACC_STATIC, ACC_FINAL, ACC_SYNTHETIC
    Code:
      stack=3, locals=3, args_size=3
         0: aload_0
         1: aload_1
         2: aload_2
         3: invokestatic  #409                // Method $anonfun$getStackDepth$8:(Ljava/lang/String;Ljava/lang/String;Ljava/lang/StackTraceElement;)Z
         6: invokestatic  #90                 // Method scala/runtime/BoxesRunTime.boxToBoolean:(Z)Ljava/lang/Boolean;
         9: areturn
      LineNumberTable:
        line 135: 0
      LocalVariableTable:
        Start  Length  Slot  Name   Signature
            0      10     0 fileName$1   Ljava/lang/String;
            0      10     1 methodName$1   Ljava/lang/String;
            0      10     2    st   Ljava/lang/StackTraceElement;
    MethodParameters:
      Name                           Flags
      fileName$1                     final
      methodName$1                   final
      st                             final

  public static final java.lang.Object $anonfun$getStackDepthFun$1$adapted(java.lang.String, java.lang.String, int, org.scalatest.exceptions.StackDepthException);
    descriptor: (Ljava/lang/String;Ljava/lang/String;ILorg/scalatest/exceptions/StackDepthException;)Ljava/lang/Object;
    flags: (0x1019) ACC_PUBLIC, ACC_STATIC, ACC_FINAL, ACC_SYNTHETIC
    Code:
      stack=4, locals=4, args_size=4
         0: aload_0
         1: aload_1
         2: iload_2
         3: aload_3
         4: invokestatic  #411                // Method $anonfun$getStackDepthFun$1:(Ljava/lang/String;Ljava/lang/String;ILorg/scalatest/exceptions/StackDepthException;)I
         7: invokestatic  #415                // Method scala/runtime/BoxesRunTime.boxToInteger:(I)Ljava/lang/Integer;
        10: areturn
      LineNumberTable:
        line 142: 0
      LocalVariableTable:
        Start  Length  Slot  Name   Signature
            0      11     0 fileName$2   Ljava/lang/String;
            0      11     1 methodName$2   Ljava/lang/String;
            0      11     2 adjustment$1   I
            0      11     3   sde   Lorg/scalatest/exceptions/StackDepthException;
    MethodParameters:
      Name                           Flags
      fileName$2                     final
      methodName$2                   final
      adjustment$1                   final
      sde                            final

  public static final java.lang.Object $anonfun$getStackDepth$9$adapted(org.scalactic.source.Position, java.lang.StackTraceElement);
    descriptor: (Lorg/scalactic/source/Position;Ljava/lang/StackTraceElement;)Ljava/lang/Object;
    flags: (0x1019) ACC_PUBLIC, ACC_STATIC, ACC_FINAL, ACC_SYNTHETIC
    Code:
      stack=2, locals=2, args_size=2
         0: aload_0
         1: aload_1
         2: invokestatic  #417                // Method $anonfun$getStackDepth$9:(Lorg/scalactic/source/Position;Ljava/lang/StackTraceElement;)Z
         5: invokestatic  #90                 // Method scala/runtime/BoxesRunTime.boxToBoolean:(Z)Ljava/lang/Boolean;
         8: areturn
      LineNumberTable:
        line 150: 0
      LocalVariableTable:
        Start  Length  Slot  Name   Signature
            0       9     0 pos$1   Lorg/scalactic/source/Position;
            0       9     1     e   Ljava/lang/StackTraceElement;
    MethodParameters:
      Name                           Flags
      pos$1                          final
      e                              final

  public static final java.lang.Object $anonfun$getStackDepthFun$2$adapted(org.scalactic.source.Position, org.scalatest.exceptions.StackDepthException);
    descriptor: (Lorg/scalactic/source/Position;Lorg/scalatest/exceptions/StackDepthException;)Ljava/lang/Object;
    flags: (0x1019) ACC_PUBLIC, ACC_STATIC, ACC_FINAL, ACC_SYNTHETIC
    Code:
      stack=2, locals=2, args_size=2
         0: aload_0
         1: aload_1
         2: invokestatic  #419                // Method $anonfun$getStackDepthFun$2:(Lorg/scalactic/source/Position;Lorg/scalatest/exceptions/StackDepthException;)I
         5: invokestatic  #415                // Method scala/runtime/BoxesRunTime.boxToInteger:(I)Ljava/lang/Integer;
         8: areturn
      LineNumberTable:
        line 154: 0
      LocalVariableTable:
        Start  Length  Slot  Name   Signature
            0       9     0 pos$2   Lorg/scalactic/source/Position;
            0       9     1   sde   Lorg/scalatest/exceptions/StackDepthException;
    MethodParameters:
      Name                           Flags
      pos$2                          final
      sde                            final

  private static java.lang.Object $deserializeLambda$(java.lang.invoke.SerializedLambda);
    descriptor: (Ljava/lang/invoke/SerializedLambda;)Ljava/lang/Object;
    flags: (0x100a) ACC_PRIVATE, ACC_STATIC, ACC_SYNTHETIC
    Code:
      stack=1, locals=1, args_size=1
         0: aload_0
         1: invokedynamic #431,  0            // InvokeDynamic #11:lambdaDeserialize:(Ljava/lang/invoke/SerializedLambda;)Ljava/lang/Object;
         6: areturn
}
InnerClasses:
  public static final #12= #9 of #11;     // Lookup=class java/lang/invoke/MethodHandles$Lookup of class java/lang/invoke/MethodHandles
  public static final #17= #14 of #16;    // ofRef=class scala/collection/mutable/ArraySeq$ofRef of class scala/collection/mutable/ArraySeq
SourceFile: "StackDepthExceptionHelper.scala"
BootstrapMethods:
  0: #65 REF_invokeStatic java/lang/invoke/LambdaMetafactory.altMetafactory:(Ljava/lang/invoke/MethodHandles$Lookup;Ljava/lang/String;Ljava/lang/invoke/MethodType;[Ljava/lang/Object;)Ljava/lang/invoke/CallSite;
    Method arguments:
      #49 (Ljava/lang/Object;)Ljava/lang/Object;
      #54 REF_invokeStatic org/scalatest/exceptions/StackDepthExceptionHelper$.$anonfun$getStackDepth$1$adapted:(Ljava/lang/String;Ljava/lang/StackTraceElement;)Ljava/lang/Object;
      #56 (Ljava/lang/StackTraceElement;)Ljava/lang/Object;
      #57 5
      #58 1
      #56 (Ljava/lang/StackTraceElement;)Ljava/lang/Object;
  1: #65 REF_invokeStatic java/lang/invoke/LambdaMetafactory.altMetafactory:(Ljava/lang/invoke/MethodHandles$Lookup;Ljava/lang/String;Ljava/lang/invoke/MethodType;[Ljava/lang/Object;)Ljava/lang/invoke/CallSite;
    Method arguments:
      #49 (Ljava/lang/Object;)Ljava/lang/Object;
      #79 REF_invokeStatic org/scalatest/exceptions/StackDepthExceptionHelper$.$anonfun$getStackDepth$2$adapted:(Ljava/lang/String;Ljava/lang/StackTraceElement;)Ljava/lang/Object;
      #56 (Ljava/lang/StackTraceElement;)Ljava/lang/Object;
      #57 5
      #58 1
      #56 (Ljava/lang/StackTraceElement;)Ljava/lang/Object;
  2: #65 REF_invokeStatic java/lang/invoke/LambdaMetafactory.altMetafactory:(Ljava/lang/invoke/MethodHandles$Lookup;Ljava/lang/String;Ljava/lang/invoke/MethodType;[Ljava/lang/Object;)Ljava/lang/invoke/CallSite;
    Method arguments:
      #49 (Ljava/lang/Object;)Ljava/lang/Object;
      #103 REF_invokeStatic org/scalatest/exceptions/StackDepthExceptionHelper$.$anonfun$getStackDepth$3$adapted:(Lscala/Tuple2;)Ljava/lang/Object;
      #104 (Lscala/Tuple2;)Ljava/lang/Object;
      #57 5
      #58 1
      #104 (Lscala/Tuple2;)Ljava/lang/Object;
  3: #65 REF_invokeStatic java/lang/invoke/LambdaMetafactory.altMetafactory:(Ljava/lang/invoke/MethodHandles$Lookup;Ljava/lang/String;Ljava/lang/invoke/MethodType;[Ljava/lang/Object;)Ljava/lang/invoke/CallSite;
    Method arguments:
      #49 (Ljava/lang/Object;)Ljava/lang/Object;
      #115 REF_invokeStatic org/scalatest/exceptions/StackDepthExceptionHelper$.$anonfun$getStackDepth$4$adapted:(Lscala/Tuple2;)Ljava/lang/Object;
      #104 (Lscala/Tuple2;)Ljava/lang/Object;
      #57 5
      #58 1
      #104 (Lscala/Tuple2;)Ljava/lang/Object;
  4: #65 REF_invokeStatic java/lang/invoke/LambdaMetafactory.altMetafactory:(Ljava/lang/invoke/MethodHandles$Lookup;Ljava/lang/String;Ljava/lang/invoke/MethodType;[Ljava/lang/Object;)Ljava/lang/invoke/CallSite;
    Method arguments:
      #49 (Ljava/lang/Object;)Ljava/lang/Object;
      #125 REF_invokeStatic org/scalatest/exceptions/StackDepthExceptionHelper$.$anonfun$getStackDepth$5$adapted:(Lscala/Tuple2;)Ljava/lang/Object;
      #104 (Lscala/Tuple2;)Ljava/lang/Object;
      #57 5
      #58 1
      #104 (Lscala/Tuple2;)Ljava/lang/Object;
  5: #65 REF_invokeStatic java/lang/invoke/LambdaMetafactory.altMetafactory:(Ljava/lang/invoke/MethodHandles$Lookup;Ljava/lang/String;Ljava/lang/invoke/MethodType;[Ljava/lang/Object;)Ljava/lang/invoke/CallSite;
    Method arguments:
      #49 (Ljava/lang/Object;)Ljava/lang/Object;
      #130 REF_invokeStatic org/scalatest/exceptions/StackDepthExceptionHelper$.$anonfun$getStackDepth$6$adapted:(Lscala/Tuple2;)Ljava/lang/Object;
      #104 (Lscala/Tuple2;)Ljava/lang/Object;
      #57 5
      #58 1
      #104 (Lscala/Tuple2;)Ljava/lang/Object;
  6: #65 REF_invokeStatic java/lang/invoke/LambdaMetafactory.altMetafactory:(Ljava/lang/invoke/MethodHandles$Lookup;Ljava/lang/String;Ljava/lang/invoke/MethodType;[Ljava/lang/Object;)Ljava/lang/invoke/CallSite;
    Method arguments:
      #49 (Ljava/lang/Object;)Ljava/lang/Object;
      #135 REF_invokeStatic org/scalatest/exceptions/StackDepthExceptionHelper$.$anonfun$getStackDepth$7$adapted:(Ljava/lang/Object;)Ljava/lang/Object;
      #49 (Ljava/lang/Object;)Ljava/lang/Object;
      #58 1
  7: #65 REF_invokeStatic java/lang/invoke/LambdaMetafactory.altMetafactory:(Ljava/lang/invoke/MethodHandles$Lookup;Ljava/lang/String;Ljava/lang/invoke/MethodType;[Ljava/lang/Object;)Ljava/lang/invoke/CallSite;
    Method arguments:
      #49 (Ljava/lang/Object;)Ljava/lang/Object;
      #161 REF_invokeStatic org/scalatest/exceptions/StackDepthExceptionHelper$.$anonfun$getStackDepth$8$adapted:(Ljava/lang/String;Ljava/lang/String;Ljava/lang/StackTraceElement;)Ljava/lang/Object;
      #56 (Ljava/lang/StackTraceElement;)Ljava/lang/Object;
      #57 5
      #58 1
      #56 (Ljava/lang/StackTraceElement;)Ljava/lang/Object;
  8: #65 REF_invokeStatic java/lang/invoke/LambdaMetafactory.altMetafactory:(Ljava/lang/invoke/MethodHandles$Lookup;Ljava/lang/String;Ljava/lang/invoke/MethodType;[Ljava/lang/Object;)Ljava/lang/invoke/CallSite;
    Method arguments:
      #49 (Ljava/lang/Object;)Ljava/lang/Object;
      #190 REF_invokeStatic org/scalatest/exceptions/StackDepthExceptionHelper$.$anonfun$getStackDepthFun$1$adapted:(Ljava/lang/String;Ljava/lang/String;ILorg/scalatest/exceptions/StackDepthException;)Ljava/lang/Object;
      #192 (Lorg/scalatest/exceptions/StackDepthException;)Ljava/lang/Object;
      #57 5
      #58 1
      #192 (Lorg/scalatest/exceptions/StackDepthException;)Ljava/lang/Object;
  9: #65 REF_invokeStatic java/lang/invoke/LambdaMetafactory.altMetafactory:(Ljava/lang/invoke/MethodHandles$Lookup;Ljava/lang/String;Ljava/lang/invoke/MethodType;[Ljava/lang/Object;)Ljava/lang/invoke/CallSite;
    Method arguments:
      #49 (Ljava/lang/Object;)Ljava/lang/Object;
      #220 REF_invokeStatic org/scalatest/exceptions/StackDepthExceptionHelper$.$anonfun$getStackDepth$9$adapted:(Lorg/scalactic/source/Position;Ljava/lang/StackTraceElement;)Ljava/lang/Object;
      #56 (Ljava/lang/StackTraceElement;)Ljava/lang/Object;
      #57 5
      #58 1
      #56 (Ljava/lang/StackTraceElement;)Ljava/lang/Object;
  10: #65 REF_invokeStatic java/lang/invoke/LambdaMetafactory.altMetafactory:(Ljava/lang/invoke/MethodHandles$Lookup;Ljava/lang/String;Ljava/lang/invoke/MethodType;[Ljava/lang/Object;)Ljava/lang/invoke/CallSite;
    Method arguments:
      #49 (Ljava/lang/Object;)Ljava/lang/Object;
      #251 REF_invokeStatic org/scalatest/exceptions/StackDepthExceptionHelper$.$anonfun$getStackDepthFun$2$adapted:(Lorg/scalactic/source/Position;Lorg/scalatest/exceptions/StackDepthException;)Ljava/lang/Object;
      #192 (Lorg/scalatest/exceptions/StackDepthException;)Ljava/lang/Object;
      #57 5
      #58 1
      #192 (Lorg/scalatest/exceptions/StackDepthException;)Ljava/lang/Object;
  11: #428 REF_invokeStatic scala/runtime/LambdaDeserialize.bootstrap:(Ljava/lang/invoke/MethodHandles$Lookup;Ljava/lang/String;Ljava/lang/invoke/MethodType;[Ljava/lang/invoke/MethodHandle;)Ljava/lang/invoke/CallSite;
    Method arguments:
      #54 REF_invokeStatic org/scalatest/exceptions/StackDepthExceptionHelper$.$anonfun$getStackDepth$1$adapted:(Ljava/lang/String;Ljava/lang/StackTraceElement;)Ljava/lang/Object;
      #79 REF_invokeStatic org/scalatest/exceptions/StackDepthExceptionHelper$.$anonfun$getStackDepth$2$adapted:(Ljava/lang/String;Ljava/lang/StackTraceElement;)Ljava/lang/Object;
      #103 REF_invokeStatic org/scalatest/exceptions/StackDepthExceptionHelper$.$anonfun$getStackDepth$3$adapted:(Lscala/Tuple2;)Ljava/lang/Object;
      #115 REF_invokeStatic org/scalatest/exceptions/StackDepthExceptionHelper$.$anonfun$getStackDepth$4$adapted:(Lscala/Tuple2;)Ljava/lang/Object;
      #125 REF_invokeStatic org/scalatest/exceptions/StackDepthExceptionHelper$.$anonfun$getStackDepth$5$adapted:(Lscala/Tuple2;)Ljava/lang/Object;
      #130 REF_invokeStatic org/scalatest/exceptions/StackDepthExceptionHelper$.$anonfun$getStackDepth$6$adapted:(Lscala/Tuple2;)Ljava/lang/Object;
      #135 REF_invokeStatic org/scalatest/exceptions/StackDepthExceptionHelper$.$anonfun$getStackDepth$7$adapted:(Ljava/lang/Object;)Ljava/lang/Object;
      #161 REF_invokeStatic org/scalatest/exceptions/StackDepthExceptionHelper$.$anonfun$getStackDepth$8$adapted:(Ljava/lang/String;Ljava/lang/String;Ljava/lang/StackTraceElement;)Ljava/lang/Object;
      #220 REF_invokeStatic org/scalatest/exceptions/StackDepthExceptionHelper$.$anonfun$getStackDepth$9$adapted:(Lorg/scalactic/source/Position;Ljava/lang/StackTraceElement;)Ljava/lang/Object;
      #190 REF_invokeStatic org/scalatest/exceptions/StackDepthExceptionHelper$.$anonfun$getStackDepthFun$1$adapted:(Ljava/lang/String;Ljava/lang/String;ILorg/scalatest/exceptions/StackDepthException;)Ljava/lang/Object;
      #251 REF_invokeStatic org/scalatest/exceptions/StackDepthExceptionHelper$.$anonfun$getStackDepthFun$2$adapted:(Lorg/scalactic/source/Position;Lorg/scalatest/exceptions/StackDepthException;)Ljava/lang/Object;
  ScalaInlineInfo: length = 0xA9 (unknown attribute)
   01 01 00 21 01 4A 01 4B 01 00 32 00 33 01 01 4E
   01 4B 01 00 4C 00 33 01 01 50 01 51 01 00 63 00
   64 01 01 56 01 51 01 00 70 00 64 01 01 61 01 51
   01 00 7A 00 64 01 01 63 01 51 01 00 7F 00 64 01
   01 66 01 67 01 00 84 00 30 01 01 69 01 6A 01 00
   9D 00 9E 01 01 7B 01 7C 01 00 D8 00 D9 01 01 6C
   01 6D 01 00 BA 00 BB 01 01 81 01 82 01 00 F7 00
   F8 01 00 16 00 15 01 00 FE 00 FF 01 00 1B 00 1C
   01 00 1B 00 D3 01 00 F5 00 8D 01 00 B7 00 B8 01
   00 B7 00 DD 01 00 FD 00 8D 01 00 C3 00 C4 01 01
   0E 01 0F 01 01 44 01 1C 01
  Scala: length = 0x0 (unknown attribute)

