Classfile /Users/mw/Projects/slang-braindump/.jar/jar8/assemble/slang-braindump/assemble/content/org/scalatest/exceptions/StackDepthException$.class
  Last modified May 29, 2022; size 2576 bytes
  SHA-256 checksum e57b104851123602e80c4e337481c0b44ea3581b67aca0bd36c5638c259db399
  Compiled from "StackDepthException.scala"
public final class org.scalatest.exceptions.StackDepthException$ implements java.io.Serializable
  minor version: 0
  major version: 52
  flags: (0x0031) ACC_PUBLIC, ACC_FINAL, ACC_SUPER
  this_class: #2                          // org/scalatest/exceptions/StackDepthException$
  super_class: #4                         // java/lang/Object
  interfaces: 1, fields: 1, methods: 6, attributes: 5
Constant pool:
    #1 = Utf8               org/scalatest/exceptions/StackDepthException$
    #2 = Class              #1            // org/scalatest/exceptions/StackDepthException$
    #3 = Utf8               java/lang/Object
    #4 = Class              #3            // java/lang/Object
    #5 = Utf8               java/io/Serializable
    #6 = Class              #5            // java/io/Serializable
    #7 = Utf8               StackDepthException.scala
    #8 = Utf8               java/lang/invoke/MethodHandles$Lookup
    #9 = Class              #8            // java/lang/invoke/MethodHandles$Lookup
   #10 = Utf8               java/lang/invoke/MethodHandles
   #11 = Class              #10           // java/lang/invoke/MethodHandles
   #12 = Utf8               Lookup
   #13 = Utf8               MODULE$
   #14 = Utf8               Lorg/scalatest/exceptions/StackDepthException$;
   #15 = Utf8               <clinit>
   #16 = Utf8               ()V
   #17 = Utf8               <init>
   #18 = NameAndType        #17:#16       // "<init>":()V
   #19 = Methodref          #2.#18        // org/scalatest/exceptions/StackDepthException$."<init>":()V
   #20 = NameAndType        #13:#14       // MODULE$:Lorg/scalatest/exceptions/StackDepthException$;
   #21 = Fieldref           #2.#20        // org/scalatest/exceptions/StackDepthException$.MODULE$:Lorg/scalatest/exceptions/StackDepthException$;
   #22 = Utf8               toExceptionFunction
   #23 = Utf8               (Lscala/Option;)Lscala/Function1;
   #24 = Utf8               (Lscala/Option<Ljava/lang/String;>;)Lscala/Function1<Lorg/scalatest/exceptions/StackDepthException;Lscala/Option<Ljava/lang/String;>;>;
   #25 = Utf8               message
   #26 = Utf8               org/scalactic/exceptions/NullArgumentException
   #27 = Class              #26           // org/scalactic/exceptions/NullArgumentException
   #28 = Utf8               message was null
   #29 = String             #28           // message was null
   #30 = Utf8               (Ljava/lang/String;)V
   #31 = NameAndType        #17:#30       // "<init>":(Ljava/lang/String;)V
   #32 = Methodref          #27.#31       // org/scalactic/exceptions/NullArgumentException."<init>":(Ljava/lang/String;)V
   #33 = Utf8               scala/Some
   #34 = Class              #33           // scala/Some
   #35 = Utf8               value
   #36 = Utf8               ()Ljava/lang/Object;
   #37 = NameAndType        #35:#36       // value:()Ljava/lang/Object;
   #38 = Methodref          #34.#37       // scala/Some.value:()Ljava/lang/Object;
   #39 = Utf8               java/lang/String
   #40 = Class              #39           // java/lang/String
   #41 = Utf8               message was a Some(null)
   #42 = String             #41           // message was a Some(null)
   #43 = Utf8               (Ljava/lang/Object;)Ljava/lang/Object;
   #44 = MethodType         #43           //  (Ljava/lang/Object;)Ljava/lang/Object;
   #45 = Utf8               $anonfun$toExceptionFunction$1
   #46 = Utf8               (Lscala/Option;Lorg/scalatest/exceptions/StackDepthException;)Lscala/Option;
   #47 = NameAndType        #45:#46       // $anonfun$toExceptionFunction$1:(Lscala/Option;Lorg/scalatest/exceptions/StackDepthException;)Lscala/Option;
   #48 = Methodref          #2.#47        // org/scalatest/exceptions/StackDepthException$.$anonfun$toExceptionFunction$1:(Lscala/Option;Lorg/scalatest/exceptions/StackDepthException;)Lscala/Option;
   #49 = MethodHandle       6:#48         // REF_invokeStatic org/scalatest/exceptions/StackDepthException$.$anonfun$toExceptionFunction$1:(Lscala/Option;Lorg/scalatest/exceptions/StackDepthException;)Lscala/Option;
   #50 = Utf8               (Lorg/scalatest/exceptions/StackDepthException;)Lscala/Option;
   #51 = MethodType         #50           //  (Lorg/scalatest/exceptions/StackDepthException;)Lscala/Option;
   #52 = Integer            5
   #53 = Integer            1
   #54 = Utf8               java/lang/invoke/LambdaMetafactory
   #55 = Class              #54           // java/lang/invoke/LambdaMetafactory
   #56 = Utf8               altMetafactory
   #57 = Utf8               (Ljava/lang/invoke/MethodHandles$Lookup;Ljava/lang/String;Ljava/lang/invoke/MethodType;[Ljava/lang/Object;)Ljava/lang/invoke/CallSite;
   #58 = NameAndType        #56:#57       // altMetafactory:(Ljava/lang/invoke/MethodHandles$Lookup;Ljava/lang/String;Ljava/lang/invoke/MethodType;[Ljava/lang/Object;)Ljava/lang/invoke/CallSite;
   #59 = Methodref          #55.#58       // java/lang/invoke/LambdaMetafactory.altMetafactory:(Ljava/lang/invoke/MethodHandles$Lookup;Ljava/lang/String;Ljava/lang/invoke/MethodType;[Ljava/lang/Object;)Ljava/lang/invoke/CallSite;
   #60 = MethodHandle       6:#59         // REF_invokeStatic java/lang/invoke/LambdaMetafactory.altMetafactory:(Ljava/lang/invoke/MethodHandles$Lookup;Ljava/lang/String;Ljava/lang/invoke/MethodType;[Ljava/lang/Object;)Ljava/lang/invoke/CallSite;
   #61 = Utf8               apply
   #62 = NameAndType        #61:#23       // apply:(Lscala/Option;)Lscala/Function1;
   #63 = InvokeDynamic      #0:#62        // #0:apply:(Lscala/Option;)Lscala/Function1;
   #64 = Utf8               this
   #65 = Utf8               Lscala/Option;
   #66 = Utf8               scala/Option
   #67 = Class              #66           // scala/Option
   #68 = Utf8               scala/Function1
   #69 = Class              #68           // scala/Function1
   #70 = Utf8               writeReplace
   #71 = Utf8               scala/runtime/ModuleSerializationProxy
   #72 = Class              #71           // scala/runtime/ModuleSerializationProxy
   #73 = Utf8               (Ljava/lang/Class;)V
   #74 = NameAndType        #17:#73       // "<init>":(Ljava/lang/Class;)V
   #75 = Methodref          #72.#74       // scala/runtime/ModuleSerializationProxy."<init>":(Ljava/lang/Class;)V
   #76 = Utf8               message$4
   #77 = Utf8               e
   #78 = Utf8               Lorg/scalatest/exceptions/StackDepthException;
   #79 = Methodref          #4.#18        // java/lang/Object."<init>":()V
   #80 = Utf8               $deserializeLambda$
   #81 = Utf8               (Ljava/lang/invoke/SerializedLambda;)Ljava/lang/Object;
   #82 = Utf8               scala/runtime/LambdaDeserialize
   #83 = Class              #82           // scala/runtime/LambdaDeserialize
   #84 = Utf8               bootstrap
   #85 = Utf8               (Ljava/lang/invoke/MethodHandles$Lookup;Ljava/lang/String;Ljava/lang/invoke/MethodType;[Ljava/lang/invoke/MethodHandle;)Ljava/lang/invoke/CallSite;
   #86 = NameAndType        #84:#85       // bootstrap:(Ljava/lang/invoke/MethodHandles$Lookup;Ljava/lang/String;Ljava/lang/invoke/MethodType;[Ljava/lang/invoke/MethodHandle;)Ljava/lang/invoke/CallSite;
   #87 = Methodref          #83.#86       // scala/runtime/LambdaDeserialize.bootstrap:(Ljava/lang/invoke/MethodHandles$Lookup;Ljava/lang/String;Ljava/lang/invoke/MethodType;[Ljava/lang/invoke/MethodHandle;)Ljava/lang/invoke/CallSite;
   #88 = MethodHandle       6:#87         // REF_invokeStatic scala/runtime/LambdaDeserialize.bootstrap:(Ljava/lang/invoke/MethodHandles$Lookup;Ljava/lang/String;Ljava/lang/invoke/MethodType;[Ljava/lang/invoke/MethodHandle;)Ljava/lang/invoke/CallSite;
   #89 = Utf8               lambdaDeserialize
   #90 = NameAndType        #89:#81       // lambdaDeserialize:(Ljava/lang/invoke/SerializedLambda;)Ljava/lang/Object;
   #91 = InvokeDynamic      #1:#90        // #1:lambdaDeserialize:(Ljava/lang/invoke/SerializedLambda;)Ljava/lang/Object;
   #92 = Utf8               Code
   #93 = Utf8               LineNumberTable
   #94 = Utf8               StackMapTable
   #95 = Utf8               LocalVariableTable
   #96 = Utf8               Signature
   #97 = Utf8               MethodParameters
   #98 = Utf8               InnerClasses
   #99 = Utf8               SourceFile
  #100 = Utf8               BootstrapMethods
  #101 = Utf8               ScalaInlineInfo
  #102 = Utf8               Scala
{
  public static final org.scalatest.exceptions.StackDepthException$ MODULE$;
    descriptor: Lorg/scalatest/exceptions/StackDepthException$;
    flags: (0x0019) ACC_PUBLIC, ACC_STATIC, ACC_FINAL

  public static {};
    descriptor: ()V
    flags: (0x0009) ACC_PUBLIC, ACC_STATIC
    Code:
      stack=2, locals=0, args_size=0
         0: new           #2                  // class org/scalatest/exceptions/StackDepthException$
         3: dup
         4: invokespecial #19                 // Method "<init>":()V
         7: putstatic     #21                 // Field MODULE$:Lorg/scalatest/exceptions/StackDepthException$;
        10: return
      LineNumberTable:
        line 230: 0

  public scala.Function1<org.scalatest.exceptions.StackDepthException, scala.Option<java.lang.String>> toExceptionFunction(scala.Option<java.lang.String>);
    descriptor: (Lscala/Option;)Lscala/Function1;
    flags: (0x0001) ACC_PUBLIC
    Code:
      stack=3, locals=6, args_size=2
         0: aload_1
         1: astore_3
         2: aload_3
         3: ifnonnull     16
         6: new           #27                 // class org/scalactic/exceptions/NullArgumentException
         9: dup
        10: ldc           #29                 // String message was null
        12: invokespecial #32                 // Method org/scalactic/exceptions/NullArgumentException."<init>":(Ljava/lang/String;)V
        15: athrow
        16: goto          19
        19: aload_3
        20: instanceof    #34                 // class scala/Some
        23: ifeq          60
        26: aload_3
        27: checkcast     #34                 // class scala/Some
        30: astore        4
        32: aload         4
        34: invokevirtual #38                 // Method scala/Some.value:()Ljava/lang/Object;
        37: checkcast     #40                 // class java/lang/String
        40: astore        5
        42: aload         5
        44: ifnonnull     57
        47: new           #27                 // class org/scalactic/exceptions/NullArgumentException
        50: dup
        51: ldc           #42                 // String message was a Some(null)
        53: invokespecial #32                 // Method org/scalactic/exceptions/NullArgumentException."<init>":(Ljava/lang/String;)V
        56: athrow
        57: goto          63
        60: goto          63
        63: aload_1
        64: invokedynamic #63,  0             // InvokeDynamic #0:apply:(Lscala/Option;)Lscala/Function1;
        69: astore_2
        70: goto          73
        73: aload_2
        74: areturn
      StackMapTable: number_of_entries = 6
        frame_type = 253 /* append */
          offset_delta = 16
          locals = [ top, class scala/Option ]
        frame_type = 2 /* same */
        frame_type = 253 /* append */
          offset_delta = 37
          locals = [ class scala/Some, class java/lang/String ]
        frame_type = 249 /* chop */
          offset_delta = 2
        frame_type = 2 /* same */
        frame_type = 255 /* full_frame */
          offset_delta = 9
          locals = [ class org/scalatest/exceptions/StackDepthException$, class scala/Option, class scala/Function1, class scala/Option ]
          stack = []
      LineNumberTable:
        line 237: 0
        line 238: 2
        line 239: 19
        line 240: 63
        line 237: 73
      LocalVariableTable:
        Start  Length  Slot  Name   Signature
            0      75     0  this   Lorg/scalatest/exceptions/StackDepthException$;
            0      75     1 message   Lscala/Option;
    Signature: #24                          // (Lscala/Option<Ljava/lang/String;>;)Lscala/Function1<Lorg/scalatest/exceptions/StackDepthException;Lscala/Option<Ljava/lang/String;>;>;
    MethodParameters:
      Name                           Flags
      message                        final

  private java.lang.Object writeReplace();
    descriptor: ()Ljava/lang/Object;
    flags: (0x0002) ACC_PRIVATE
    Code:
      stack=3, locals=1, args_size=1
         0: new           #72                 // class scala/runtime/ModuleSerializationProxy
         3: dup
         4: ldc           #2                  // class org/scalatest/exceptions/StackDepthException$
         6: invokespecial #75                 // Method scala/runtime/ModuleSerializationProxy."<init>":(Ljava/lang/Class;)V
         9: areturn
      LineNumberTable:
        line 230: 0
      LocalVariableTable:
        Start  Length  Slot  Name   Signature
            0      10     0  this   Lorg/scalatest/exceptions/StackDepthException$;

  public static final scala.Option $anonfun$toExceptionFunction$1(scala.Option, org.scalatest.exceptions.StackDepthException);
    descriptor: (Lscala/Option;Lorg/scalatest/exceptions/StackDepthException;)Lscala/Option;
    flags: (0x1019) ACC_PUBLIC, ACC_STATIC, ACC_FINAL, ACC_SYNTHETIC
    Code:
      stack=1, locals=2, args_size=2
         0: aload_0
         1: areturn
      LineNumberTable:
        line 240: 0
      LocalVariableTable:
        Start  Length  Slot  Name   Signature
            0       2     0 message$4   Lscala/Option;
            0       2     1     e   Lorg/scalatest/exceptions/StackDepthException;
    MethodParameters:
      Name                           Flags
      message$4                      final
      e                              final

  private org.scalatest.exceptions.StackDepthException$();
    descriptor: ()V
    flags: (0x0002) ACC_PRIVATE
    Code:
      stack=1, locals=1, args_size=1
         0: aload_0
         1: invokespecial #79                 // Method java/lang/Object."<init>":()V
         4: return
      LineNumberTable:
        line 244: 0
        line 230: 4
      LocalVariableTable:
        Start  Length  Slot  Name   Signature
            0       5     0  this   Lorg/scalatest/exceptions/StackDepthException$;

  private static java.lang.Object $deserializeLambda$(java.lang.invoke.SerializedLambda);
    descriptor: (Ljava/lang/invoke/SerializedLambda;)Ljava/lang/Object;
    flags: (0x100a) ACC_PRIVATE, ACC_STATIC, ACC_SYNTHETIC
    Code:
      stack=1, locals=1, args_size=1
         0: aload_0
         1: invokedynamic #91,  0             // InvokeDynamic #1:lambdaDeserialize:(Ljava/lang/invoke/SerializedLambda;)Ljava/lang/Object;
         6: areturn
}
InnerClasses:
  public static final #12= #9 of #11;     // Lookup=class java/lang/invoke/MethodHandles$Lookup of class java/lang/invoke/MethodHandles
SourceFile: "StackDepthException.scala"
BootstrapMethods:
  0: #60 REF_invokeStatic java/lang/invoke/LambdaMetafactory.altMetafactory:(Ljava/lang/invoke/MethodHandles$Lookup;Ljava/lang/String;Ljava/lang/invoke/MethodType;[Ljava/lang/Object;)Ljava/lang/invoke/CallSite;
    Method arguments:
      #44 (Ljava/lang/Object;)Ljava/lang/Object;
      #49 REF_invokeStatic org/scalatest/exceptions/StackDepthException$.$anonfun$toExceptionFunction$1:(Lscala/Option;Lorg/scalatest/exceptions/StackDepthException;)Lscala/Option;
      #51 (Lorg/scalatest/exceptions/StackDepthException;)Lscala/Option;
      #52 5
      #53 1
      #51 (Lorg/scalatest/exceptions/StackDepthException;)Lscala/Option;
  1: #88 REF_invokeStatic scala/runtime/LambdaDeserialize.bootstrap:(Ljava/lang/invoke/MethodHandles$Lookup;Ljava/lang/String;Ljava/lang/invoke/MethodType;[Ljava/lang/invoke/MethodHandle;)Ljava/lang/invoke/CallSite;
    Method arguments:
      #49 REF_invokeStatic org/scalatest/exceptions/StackDepthException$.$anonfun$toExceptionFunction$1:(Lscala/Option;Lorg/scalatest/exceptions/StackDepthException;)Lscala/Option;
  ScalaInlineInfo: length = 0x18 (unknown attribute)
   01 01 00 04 00 2D 00 2E 01 00 11 00 10 01 00 16
   00 17 01 00 46 00 24 01
  Scala: length = 0x0 (unknown attribute)

