Classfile /Users/mw/Projects/slang-braindump/.jar/jar8/assemble/slang-braindump/assemble/content/org/scalatest/exceptions/TestRegistrationClosedException.class
  Last modified May 29, 2022; size 5455 bytes
  SHA-256 checksum aefb35b1885de1fc09d23314a34ec6091598061dba48325ad0d6367c575468ba
  Compiled from "TestRegistrationClosedException.scala"
public class org.scalatest.exceptions.TestRegistrationClosedException extends org.scalatest.exceptions.StackDepthException
  minor version: 0
  major version: 52
  flags: (0x0021) ACC_PUBLIC, ACC_SUPER
  this_class: #2                          // org/scalatest/exceptions/TestRegistrationClosedException
  super_class: #4                         // org/scalatest/exceptions/StackDepthException
  interfaces: 0, fields: 2, methods: 9, attributes: 5
Constant pool:
    #1 = Utf8               org/scalatest/exceptions/TestRegistrationClosedException
    #2 = Class              #1            // org/scalatest/exceptions/TestRegistrationClosedException
    #3 = Utf8               org/scalatest/exceptions/StackDepthException
    #4 = Class              #3            // org/scalatest/exceptions/StackDepthException
    #5 = Utf8               TestRegistrationClosedException.scala
    #6 = Utf8               Lscala/reflect/ScalaSignature;
    #7 = Utf8               bytes
    #8 = Utf8               \u0006\u0005\u00054Aa\u0003\u0007\u0001\'!A\u0001\u0004\u0001B\u0001B\u0003%\u0011\u0004\u0003\u0005\'\u0001\t\u0005\t\u0015!\u0003(\u0011\u0015y\u0004\u0001\"\u0001A\u0011\u0015y\u0004\u0001\"\u0001E\u0011\u0015y\u0004\u0001\"\u0001I\u0011\u0015y\u0004\u0001\"\u0001M\u0011\u0015\u0001\u0006\u0001\"\u0001R\u0011\u0015\u0011\u0006\u0001\"\u0011T\u0011\u0015a\u0006\u0001\"\u0011^\u0011\u0015y\u0006\u0001\"\u0011a\u0005}!Vm\u001d;SK\u001eL7\u000f\u001e:bi&|gn\u00117pg\u0016$W\t_2faRLwN\u001c\u0006\u0003\u001b9\t!\"\u001a=dKB$\u0018n\u001c8t\u0015\ty\u0001#A\u0005tG\u0006d\u0017\r^3ti*\t\u0011#A\u0002pe\u001e\u001c\u0001a\u0005\u0002\u0001)A\u0011QCF\u0007\u0002\u0019%\u0011q\u0003\u0004\u0002\u0014\'R\f7m\u001b#faRDW\t_2faRLwN\\\u0001\b[\u0016\u001c8/Y4f!\tQ2E\u0004\u0002\u001cCA\u0011AdH\u0007\u0002;)\u0011aDE\u0001\u0007yI|w\u000e\u001e \u000b\u0003\u0001\nQa]2bY\u0006L!AI\u0010\u0002\rA\u0013X\rZ3g\u0013\t!SE\u0001\u0004TiJLgn\u001a\u0006\u0003E}\t!\u0003]8t\u001fJ\u001cF/Y2l\t\u0016\u0004H\u000f\u001b$v]B!\u0001&\f\u00199\u001d\tI3F\u0004\u0002\u001dU%\t\u0001%\u0003\u0002-?\u00059\u0001/Y2lC\u001e,\u0017B\u0001\u00180\u0005\u0019)\u0015\u000e\u001e5fe*\u0011Af\b\t\u0003cYj\u0011A\r\u0006\u0003gQ\naa]8ve\u000e,\'BA\u001b\u0011\u0003%\u00198-\u00197bGRL7-\u0003\u00028e\tA\u0001k\\:ji&|g\u000e\u0005\u0003:uQaT\"A\u0010\n\u0005mz\"!\u0003$v]\u000e$\u0018n\u001c82!\tIT(\u0003\u0002??\t\u0019\u0011J\u001c;\u0002\rqJg.\u001b;?)\r\t%i\u0011\t\u0003+\u0001AQ\u0001G\u0002A\u0002eAQAJ\u0002A\u0002\u001d\"2!Q#G\u0011\u0015AB\u00011\u0001\u001a\u0011\u00159E\u00011\u00011\u0003\r\u0001xn\u001d\u000b\u0004\u0003&S\u0005\"\u0002\r\u0006\u0001\u0004I\u0002\"B&\u0006\u0001\u0004a\u0014\u0001\u00064bS2,GmQ8eKN#\u0018mY6EKB$\b\u000eF\u0002B\u001b:CQ\u0001\u0007\u0004A\u0002eAQa\u0014\u0004A\u0002a\nqCZ1jY\u0016$7i\u001c3f\'R\f7m\u001b#faRDg)\u001e8\u0002\'M,g/\u001a:fI\u0006#8\u000b^1dW\u0012+\u0007\u000f\u001e5\u0016\u0003\u0005\u000b\u0001bY1o\u000bF,\u0018\r\u001c\u000b\u0003)^\u0003\"!O+\n\u0005Y{\"a\u0002\"p_2,\u0017M\u001c\u0005\u00061\"\u0001\r!W\u0001\u0006_RDWM\u001d\t\u0003siK!aW\u0010\u0003\u0007\u0005s\u00170\u0001\u0004fcV\fGn\u001d\u000b\u0003)zCQ\u0001W\u0005A\u0002e\u000b\u0001\u0002[1tQ\u000e{G-\u001a\u000b\u0002y\u0001
    #9 = Utf8               org/scalactic/Requirements$RequirementsHelper
   #10 = Class              #9            // org/scalactic/Requirements$RequirementsHelper
   #11 = Utf8               org/scalactic/Requirements
   #12 = Class              #11           // org/scalactic/Requirements
   #13 = Utf8               RequirementsHelper
   #14 = Utf8               org/scalatest/exceptions/TestRegistrationClosedException$$anonfun$$lessinit$greater$1
   #15 = Class              #14           // org/scalatest/exceptions/TestRegistrationClosedException$$anonfun$$lessinit$greater$1
   #16 = Utf8               org/scalatest/exceptions/TestRegistrationClosedException$$anonfun$$lessinit$greater$2
   #17 = Class              #16           // org/scalatest/exceptions/TestRegistrationClosedException$$anonfun$$lessinit$greater$2
   #18 = Utf8               message
   #19 = Utf8               Ljava/lang/String;
   #20 = Utf8               posOrStackDepthFun
   #21 = Utf8               Lscala/util/Either;
   #22 = Utf8               Lscala/util/Either<Lorg/scalactic/source/Position;Lscala/Function1<Lorg/scalatest/exceptions/StackDepthException;Ljava/lang/Object;>;>;
   #23 = Utf8               severedAtStackDepth
   #24 = Utf8               ()Lorg/scalatest/exceptions/TestRegistrationClosedException;
   #25 = Utf8               scala/collection/ArrayOps$
   #26 = Class              #25           // scala/collection/ArrayOps$
   #27 = Utf8               MODULE$
   #28 = Utf8               Lscala/collection/ArrayOps$;
   #29 = NameAndType        #27:#28       // MODULE$:Lscala/collection/ArrayOps$;
   #30 = Fieldref           #26.#29       // scala/collection/ArrayOps$.MODULE$:Lscala/collection/ArrayOps$;
   #31 = Utf8               scala/Predef$
   #32 = Class              #31           // scala/Predef$
   #33 = Utf8               Lscala/Predef$;
   #34 = NameAndType        #27:#33       // MODULE$:Lscala/Predef$;
   #35 = Fieldref           #32.#34       // scala/Predef$.MODULE$:Lscala/Predef$;
   #36 = Utf8               getStackTrace
   #37 = Utf8               ()[Ljava/lang/StackTraceElement;
   #38 = NameAndType        #36:#37       // getStackTrace:()[Ljava/lang/StackTraceElement;
   #39 = Methodref          #2.#38        // org/scalatest/exceptions/TestRegistrationClosedException.getStackTrace:()[Ljava/lang/StackTraceElement;
   #40 = Utf8               [Ljava/lang/Object;
   #41 = Class              #40           // "[Ljava/lang/Object;"
   #42 = Utf8               refArrayOps
   #43 = Utf8               ([Ljava/lang/Object;)Ljava/lang/Object;
   #44 = NameAndType        #42:#43       // refArrayOps:([Ljava/lang/Object;)Ljava/lang/Object;
   #45 = Methodref          #32.#44       // scala/Predef$.refArrayOps:([Ljava/lang/Object;)Ljava/lang/Object;
   #46 = Utf8               failedCodeStackDepth
   #47 = Utf8               ()I
   #48 = NameAndType        #46:#47       // failedCodeStackDepth:()I
   #49 = Methodref          #2.#48        // org/scalatest/exceptions/TestRegistrationClosedException.failedCodeStackDepth:()I
   #50 = Utf8               drop$extension
   #51 = Utf8               (Ljava/lang/Object;I)Ljava/lang/Object;
   #52 = NameAndType        #50:#51       // drop$extension:(Ljava/lang/Object;I)Ljava/lang/Object;
   #53 = Methodref          #26.#52       // scala/collection/ArrayOps$.drop$extension:(Ljava/lang/Object;I)Ljava/lang/Object;
   #54 = Utf8               [Ljava/lang/StackTraceElement;
   #55 = Class              #54           // "[Ljava/lang/StackTraceElement;"
   #56 = NameAndType        #18:#19       // message:Ljava/lang/String;
   #57 = Fieldref           #2.#56        // org/scalatest/exceptions/TestRegistrationClosedException.message:Ljava/lang/String;
   #58 = NameAndType        #20:#21       // posOrStackDepthFun:Lscala/util/Either;
   #59 = Fieldref           #2.#58        // org/scalatest/exceptions/TestRegistrationClosedException.posOrStackDepthFun:Lscala/util/Either;
   #60 = Utf8               <init>
   #61 = Utf8               (Ljava/lang/String;Lscala/util/Either;)V
   #62 = NameAndType        #60:#61       // "<init>":(Ljava/lang/String;Lscala/util/Either;)V
   #63 = Methodref          #2.#62        // org/scalatest/exceptions/TestRegistrationClosedException."<init>":(Ljava/lang/String;Lscala/util/Either;)V
   #64 = Utf8               setStackTrace
   #65 = Utf8               ([Ljava/lang/StackTraceElement;)V
   #66 = NameAndType        #64:#65       // setStackTrace:([Ljava/lang/StackTraceElement;)V
   #67 = Methodref          #2.#66        // org/scalatest/exceptions/TestRegistrationClosedException.setStackTrace:([Ljava/lang/StackTraceElement;)V
   #68 = Utf8               truncated
   #69 = Utf8               e
   #70 = Utf8               Lorg/scalatest/exceptions/TestRegistrationClosedException;
   #71 = Utf8               this
   #72 = Utf8               canEqual
   #73 = Utf8               (Ljava/lang/Object;)Z
   #74 = Utf8               other
   #75 = Utf8               Ljava/lang/Object;
   #76 = Utf8               equals
   #77 = NameAndType        #76:#73       // equals:(Ljava/lang/Object;)Z
   #78 = Methodref          #4.#77        // org/scalatest/exceptions/StackDepthException.equals:(Ljava/lang/Object;)Z
   #79 = Utf8               java/lang/Object
   #80 = Class              #79           // java/lang/Object
   #81 = Utf8               hashCode
   #82 = NameAndType        #81:#47       // hashCode:()I
   #83 = Methodref          #4.#82        // org/scalatest/exceptions/StackDepthException.hashCode:()I
   #84 = Utf8               ()Ljava/lang/Throwable;
   #85 = NameAndType        #23:#24       // severedAtStackDepth:()Lorg/scalatest/exceptions/TestRegistrationClosedException;
   #86 = Methodref          #2.#85        // org/scalatest/exceptions/TestRegistrationClosedException.severedAtStackDepth:()Lorg/scalatest/exceptions/TestRegistrationClosedException;
   #87 = Utf8               (Ljava/lang/String;Lscala/util/Either<Lorg/scalactic/source/Position;Lscala/Function1<Lorg/scalatest/exceptions/StackDepthException;Ljava/lang/Object;>;>;)V
   #88 = Utf8               (Ljava/lang/String;)V
   #89 = NameAndType        #60:#88       // "<init>":(Ljava/lang/String;)V
   #90 = Methodref          #15.#89       // org/scalatest/exceptions/TestRegistrationClosedException$$anonfun$$lessinit$greater$1."<init>":(Ljava/lang/String;)V
   #91 = Utf8               scala/None$
   #92 = Class              #91           // scala/None$
   #93 = Utf8               Lscala/None$;
   #94 = NameAndType        #27:#93       // MODULE$:Lscala/None$;
   #95 = Fieldref           #92.#94       // scala/None$.MODULE$:Lscala/None$;
   #96 = Utf8               (Lscala/Function1;Lscala/Option;Lscala/util/Either;)V
   #97 = NameAndType        #60:#96       // "<init>":(Lscala/Function1;Lscala/Option;Lscala/util/Either;)V
   #98 = Methodref          #4.#97        // org/scalatest/exceptions/StackDepthException."<init>":(Lscala/Function1;Lscala/Option;Lscala/util/Either;)V
   #99 = Utf8               org/scalactic/Requirements$
  #100 = Class              #99           // org/scalactic/Requirements$
  #101 = Utf8               Lorg/scalactic/Requirements$;
  #102 = NameAndType        #27:#101      // MODULE$:Lorg/scalactic/Requirements$;
  #103 = Fieldref           #100.#102     // org/scalactic/Requirements$.MODULE$:Lorg/scalactic/Requirements$;
  #104 = Utf8               requirementsHelper
  #105 = Utf8               ()Lorg/scalactic/Requirements$RequirementsHelper;
  #106 = NameAndType        #104:#105     // requirementsHelper:()Lorg/scalactic/Requirements$RequirementsHelper;
  #107 = Methodref          #100.#106     // org/scalactic/Requirements$.requirementsHelper:()Lorg/scalactic/Requirements$RequirementsHelper;
  #108 = Utf8               java/lang/String
  #109 = Class              #108          // java/lang/String
  #110 = Utf8               TestRegistrationClosedException.this.message
  #111 = String             #110          // TestRegistrationClosedException.this.message
  #112 = Utf8               TestRegistrationClosedException.this.posOrStackDepthFun
  #113 = String             #112          // TestRegistrationClosedException.this.posOrStackDepthFun
  #114 = Utf8               [Ljava/lang/String;
  #115 = Class              #114          // "[Ljava/lang/String;"
  #116 = Utf8               org/scalactic/Prettifier$
  #117 = Class              #116          // org/scalactic/Prettifier$
  #118 = Utf8               Lorg/scalactic/Prettifier$;
  #119 = NameAndType        #27:#118      // MODULE$:Lorg/scalactic/Prettifier$;
  #120 = Fieldref           #117.#119     // org/scalactic/Prettifier$.MODULE$:Lorg/scalactic/Prettifier$;
  #121 = Utf8               default
  #122 = Utf8               ()Lorg/scalactic/Prettifier;
  #123 = NameAndType        #121:#122     // default:()Lorg/scalactic/Prettifier;
  #124 = Methodref          #117.#123     // org/scalactic/Prettifier$.default:()Lorg/scalactic/Prettifier;
  #125 = Utf8               org/scalactic/source/Position
  #126 = Class              #125          // org/scalactic/source/Position
  #127 = String             #5            // TestRegistrationClosedException.scala
  #128 = Utf8               Please set the environment variable SCALACTIC_FILL_FILE_PATHNAMES to yes at compile time to enable this feature.
  #129 = String             #128          // Please set the environment variable SCALACTIC_FILL_FILE_PATHNAMES to yes at compile time to enable this feature.
  #130 = Utf8               (Ljava/lang/String;Ljava/lang/String;I)V
  #131 = NameAndType        #60:#130      // "<init>":(Ljava/lang/String;Ljava/lang/String;I)V
  #132 = Methodref          #126.#131     // org/scalactic/source/Position."<init>":(Ljava/lang/String;Ljava/lang/String;I)V
  #133 = Utf8               macroRequireNonNull
  #134 = Utf8               ([Ljava/lang/String;[Ljava/lang/Object;Lorg/scalactic/Prettifier;Lorg/scalactic/source/Position;)V
  #135 = NameAndType        #133:#134     // macroRequireNonNull:([Ljava/lang/String;[Ljava/lang/Object;Lorg/scalactic/Prettifier;Lorg/scalactic/source/Position;)V
  #136 = Methodref          #10.#135      // org/scalactic/Requirements$RequirementsHelper.macroRequireNonNull:([Ljava/lang/String;[Ljava/lang/Object;Lorg/scalactic/Prettifier;Lorg/scalactic/source/Position;)V
  #137 = Utf8               (Ljava/lang/String;Lorg/scalactic/source/Position;)V
  #138 = Utf8               pos
  #139 = Utf8               scala/package$
  #140 = Class              #139          // scala/package$
  #141 = Utf8               Lscala/package$;
  #142 = NameAndType        #27:#141      // MODULE$:Lscala/package$;
  #143 = Fieldref           #140.#142     // scala/package$.MODULE$:Lscala/package$;
  #144 = Utf8               Left
  #145 = Utf8               ()Lscala/util/Left$;
  #146 = NameAndType        #144:#145     // Left:()Lscala/util/Left$;
  #147 = Methodref          #140.#146     // scala/package$.Left:()Lscala/util/Left$;
  #148 = Utf8               scala/util/Left$
  #149 = Class              #148          // scala/util/Left$
  #150 = Utf8               apply
  #151 = Utf8               (Ljava/lang/Object;)Lscala/util/Left;
  #152 = NameAndType        #150:#151     // apply:(Ljava/lang/Object;)Lscala/util/Left;
  #153 = Methodref          #149.#152     // scala/util/Left$.apply:(Ljava/lang/Object;)Lscala/util/Left;
  #154 = Utf8               Lorg/scalactic/source/Position;
  #155 = Utf8               (Ljava/lang/String;I)V
  #156 = Utf8               Right
  #157 = Utf8               ()Lscala/util/Right$;
  #158 = NameAndType        #156:#157     // Right:()Lscala/util/Right$;
  #159 = Methodref          #140.#158     // scala/package$.Right:()Lscala/util/Right$;
  #160 = Utf8               (I)V
  #161 = NameAndType        #60:#160      // "<init>":(I)V
  #162 = Methodref          #17.#161      // org/scalatest/exceptions/TestRegistrationClosedException$$anonfun$$lessinit$greater$2."<init>":(I)V
  #163 = Utf8               scala/util/Right$
  #164 = Class              #163          // scala/util/Right$
  #165 = Utf8               (Ljava/lang/Object;)Lscala/util/Right;
  #166 = NameAndType        #150:#165     // apply:(Ljava/lang/Object;)Lscala/util/Right;
  #167 = Methodref          #164.#166     // scala/util/Right$.apply:(Ljava/lang/Object;)Lscala/util/Right;
  #168 = Utf8               I
  #169 = Utf8               (Ljava/lang/String;Lscala/Function1;)V
  #170 = Utf8               (Ljava/lang/String;Lscala/Function1<Lorg/scalatest/exceptions/StackDepthException;Ljava/lang/Object;>;)V
  #171 = Utf8               failedCodeStackDepthFun
  #172 = Utf8               Lscala/Function1;
  #173 = Utf8               Signature
  #174 = Utf8               Code
  #175 = Utf8               LineNumberTable
  #176 = Utf8               LocalVariableTable
  #177 = Utf8               MethodParameters
  #178 = Utf8               StackMapTable
  #179 = Utf8               InnerClasses
  #180 = Utf8               SourceFile
  #181 = Utf8               RuntimeVisibleAnnotations
  #182 = Utf8               ScalaInlineInfo
  #183 = Utf8               ScalaSig
{
  private final java.lang.String message;
    descriptor: Ljava/lang/String;
    flags: (0x0012) ACC_PRIVATE, ACC_FINAL

  private final scala.util.Either<org.scalactic.source.Position, scala.Function1<org.scalatest.exceptions.StackDepthException, java.lang.Object>> posOrStackDepthFun;
    descriptor: Lscala/util/Either;
    flags: (0x0012) ACC_PRIVATE, ACC_FINAL
    Signature: #22                          // Lscala/util/Either<Lorg/scalactic/source/Position;Lscala/Function1<Lorg/scalatest/exceptions/StackDepthException;Ljava/lang/Object;>;>;

  public org.scalatest.exceptions.TestRegistrationClosedException severedAtStackDepth();
    descriptor: ()Lorg/scalatest/exceptions/TestRegistrationClosedException;
    flags: (0x0001) ACC_PUBLIC
    Code:
      stack=4, locals=3, args_size=1
         0: getstatic     #30                 // Field scala/collection/ArrayOps$.MODULE$:Lscala/collection/ArrayOps$;
         3: getstatic     #35                 // Field scala/Predef$.MODULE$:Lscala/Predef$;
         6: aload_0
         7: invokevirtual #39                 // Method getStackTrace:()[Ljava/lang/StackTraceElement;
        10: checkcast     #41                 // class "[Ljava/lang/Object;"
        13: invokevirtual #45                 // Method scala/Predef$.refArrayOps:([Ljava/lang/Object;)Ljava/lang/Object;
        16: aload_0
        17: invokevirtual #49                 // Method failedCodeStackDepth:()I
        20: invokevirtual #53                 // Method scala/collection/ArrayOps$.drop$extension:(Ljava/lang/Object;I)Ljava/lang/Object;
        23: checkcast     #55                 // class "[Ljava/lang/StackTraceElement;"
        26: astore_1
        27: new           #2                  // class org/scalatest/exceptions/TestRegistrationClosedException
        30: dup
        31: aload_0
        32: getfield      #57                 // Field message:Ljava/lang/String;
        35: aload_0
        36: getfield      #59                 // Field posOrStackDepthFun:Lscala/util/Either;
        39: invokespecial #63                 // Method "<init>":(Ljava/lang/String;Lscala/util/Either;)V
        42: astore_2
        43: aload_2
        44: aload_1
        45: invokevirtual #67                 // Method setStackTrace:([Ljava/lang/StackTraceElement;)V
        48: aload_2
        49: areturn
      LineNumberTable:
        line 109: 0
        line 110: 27
        line 111: 43
        line 112: 48
      LocalVariableTable:
        Start  Length  Slot  Name   Signature
           27      22     1 truncated   [Ljava/lang/StackTraceElement;
           43       6     2     e   Lorg/scalatest/exceptions/TestRegistrationClosedException;
            0      50     0  this   Lorg/scalatest/exceptions/TestRegistrationClosedException;

  public boolean canEqual(java.lang.Object);
    descriptor: (Ljava/lang/Object;)Z
    flags: (0x0001) ACC_PUBLIC
    Code:
      stack=1, locals=2, args_size=2
         0: aload_1
         1: instanceof    #2                  // class org/scalatest/exceptions/TestRegistrationClosedException
         4: ireturn
      LineNumberTable:
        line 118: 0
      LocalVariableTable:
        Start  Length  Slot  Name   Signature
            0       5     0  this   Lorg/scalatest/exceptions/TestRegistrationClosedException;
            0       5     1 other   Ljava/lang/Object;
    MethodParameters:
      Name                           Flags
      other                          final

  public boolean equals(java.lang.Object);
    descriptor: (Ljava/lang/Object;)Z
    flags: (0x0001) ACC_PUBLIC
    Code:
      stack=2, locals=5, args_size=2
         0: aload_1
         1: astore_3
         2: aload_3
         3: instanceof    #2                  // class org/scalatest/exceptions/TestRegistrationClosedException
         6: ifeq          25
         9: aload_3
        10: checkcast     #2                  // class org/scalatest/exceptions/TestRegistrationClosedException
        13: astore        4
        15: aload_0
        16: aload         4
        18: invokespecial #78                 // Method org/scalatest/exceptions/StackDepthException.equals:(Ljava/lang/Object;)Z
        21: istore_2
        22: goto          33
        25: goto          28
        28: iconst_0
        29: istore_2
        30: goto          33
        33: iload_2
        34: ireturn
      StackMapTable: number_of_entries = 3
        frame_type = 253 /* append */
          offset_delta = 25
          locals = [ top, class java/lang/Object ]
        frame_type = 2 /* same */
        frame_type = 255 /* full_frame */
          offset_delta = 4
          locals = [ class org/scalatest/exceptions/TestRegistrationClosedException, class java/lang/Object, int, class java/lang/Object ]
          stack = []
      LineNumberTable:
        line 127: 0
        line 128: 2
        line 129: 28
        line 127: 33
      LocalVariableTable:
        Start  Length  Slot  Name   Signature
            0      35     0  this   Lorg/scalatest/exceptions/TestRegistrationClosedException;
            0      35     1 other   Ljava/lang/Object;
    MethodParameters:
      Name                           Flags
      other                          final

  public int hashCode();
    descriptor: ()I
    flags: (0x0001) ACC_PUBLIC
    Code:
      stack=1, locals=1, args_size=1
         0: aload_0
         1: invokespecial #83                 // Method org/scalatest/exceptions/StackDepthException.hashCode:()I
         4: ireturn
      LineNumberTable:
        line 137: 0
      LocalVariableTable:
        Start  Length  Slot  Name   Signature
            0       5     0  this   Lorg/scalatest/exceptions/TestRegistrationClosedException;

  public java.lang.Throwable severedAtStackDepth();
    descriptor: ()Ljava/lang/Throwable;
    flags: (0x1041) ACC_PUBLIC, ACC_BRIDGE, ACC_SYNTHETIC
    Code:
      stack=1, locals=1, args_size=1
         0: aload_0
         1: invokevirtual #86                 // Method severedAtStackDepth:()Lorg/scalatest/exceptions/TestRegistrationClosedException;
         4: areturn
      LineNumberTable:
        line 58: 0
      LocalVariableTable:
        Start  Length  Slot  Name   Signature
            0       5     0  this   Lorg/scalatest/exceptions/TestRegistrationClosedException;

  public org.scalatest.exceptions.TestRegistrationClosedException(java.lang.String, scala.util.Either<org.scalactic.source.Position, scala.Function1<org.scalatest.exceptions.StackDepthException, java.lang.Object>>);
    descriptor: (Ljava/lang/String;Lscala/util/Either;)V
    flags: (0x0001) ACC_PUBLIC
    Code:
      stack=9, locals=3, args_size=3
         0: aload_0
         1: aload_1
         2: putfield      #57                 // Field message:Ljava/lang/String;
         5: aload_0
         6: aload_2
         7: putfield      #59                 // Field posOrStackDepthFun:Lscala/util/Either;
        10: aload_0
        11: new           #15                 // class org/scalatest/exceptions/TestRegistrationClosedException$$anonfun$$lessinit$greater$1
        14: dup
        15: aload_1
        16: invokespecial #90                 // Method org/scalatest/exceptions/TestRegistrationClosedException$$anonfun$$lessinit$greater$1."<init>":(Ljava/lang/String;)V
        19: getstatic     #95                 // Field scala/None$.MODULE$:Lscala/None$;
        22: aload_2
        23: invokespecial #98                 // Method org/scalatest/exceptions/StackDepthException."<init>":(Lscala/Function1;Lscala/Option;Lscala/util/Either;)V
        26: getstatic     #103                // Field org/scalactic/Requirements$.MODULE$:Lorg/scalactic/Requirements$;
        29: invokevirtual #107                // Method org/scalactic/Requirements$.requirementsHelper:()Lorg/scalactic/Requirements$RequirementsHelper;
        32: iconst_2
        33: anewarray     #109                // class java/lang/String
        36: dup
        37: iconst_0
        38: ldc           #111                // String TestRegistrationClosedException.this.message
        40: aastore
        41: dup
        42: iconst_1
        43: ldc           #113                // String TestRegistrationClosedException.this.posOrStackDepthFun
        45: aastore
        46: checkcast     #41                 // class "[Ljava/lang/Object;"
        49: checkcast     #115                // class "[Ljava/lang/String;"
        52: iconst_2
        53: anewarray     #80                 // class java/lang/Object
        56: dup
        57: iconst_0
        58: aload_1
        59: aastore
        60: dup
        61: iconst_1
        62: aload_2
        63: aastore
        64: checkcast     #41                 // class "[Ljava/lang/Object;"
        67: getstatic     #120                // Field org/scalactic/Prettifier$.MODULE$:Lorg/scalactic/Prettifier$;
        70: invokevirtual #124                // Method org/scalactic/Prettifier$.default:()Lorg/scalactic/Prettifier;
        73: new           #126                // class org/scalactic/source/Position
        76: dup
        77: ldc           #127                // String TestRegistrationClosedException.scala
        79: ldc           #129                // String Please set the environment variable SCALACTIC_FILL_FILE_PATHNAMES to yes at compile time to enable this feature.
        81: bipush        63
        83: invokespecial #132                // Method org/scalactic/source/Position."<init>":(Ljava/lang/String;Ljava/lang/String;I)V
        86: invokevirtual #136                // Method org/scalactic/Requirements$RequirementsHelper.macroRequireNonNull:([Ljava/lang/String;[Ljava/lang/Object;Lorg/scalactic/Prettifier;Lorg/scalactic/source/Position;)V
        89: return
      LineNumberTable:
        line 59: 0
        line 60: 5
        line 61: 10
        line 63: 26
        line 58: 89
      LocalVariableTable:
        Start  Length  Slot  Name   Signature
            0      90     0  this   Lorg/scalatest/exceptions/TestRegistrationClosedException;
            0      90     1 message   Ljava/lang/String;
            0      90     2 posOrStackDepthFun   Lscala/util/Either;
    Signature: #87                          // (Ljava/lang/String;Lscala/util/Either<Lorg/scalactic/source/Position;Lscala/Function1<Lorg/scalatest/exceptions/StackDepthException;Ljava/lang/Object;>;>;)V
    MethodParameters:
      Name                           Flags
      message                        final
      posOrStackDepthFun             final

  public org.scalatest.exceptions.TestRegistrationClosedException(java.lang.String, org.scalactic.source.Position);
    descriptor: (Ljava/lang/String;Lorg/scalactic/source/Position;)V
    flags: (0x0001) ACC_PUBLIC
    Code:
      stack=4, locals=3, args_size=3
         0: aload_0
         1: aload_1
         2: getstatic     #143                // Field scala/package$.MODULE$:Lscala/package$;
         5: invokevirtual #147                // Method scala/package$.Left:()Lscala/util/Left$;
         8: aload_2
         9: invokevirtual #153                // Method scala/util/Left$.apply:(Ljava/lang/Object;)Lscala/util/Left;
        12: invokespecial #63                 // Method "<init>":(Ljava/lang/String;Lscala/util/Either;)V
        15: return
      LineNumberTable:
        line 76: 0
      LocalVariableTable:
        Start  Length  Slot  Name   Signature
            0      16     0  this   Lorg/scalatest/exceptions/TestRegistrationClosedException;
            0      16     1 message   Ljava/lang/String;
            0      16     2   pos   Lorg/scalactic/source/Position;
    MethodParameters:
      Name                           Flags
      message                        final
      pos                            final

  public org.scalatest.exceptions.TestRegistrationClosedException(java.lang.String, int);
    descriptor: (Ljava/lang/String;I)V
    flags: (0x0001) ACC_PUBLIC
    Code:
      stack=6, locals=3, args_size=3
         0: aload_0
         1: aload_1
         2: getstatic     #143                // Field scala/package$.MODULE$:Lscala/package$;
         5: invokevirtual #159                // Method scala/package$.Right:()Lscala/util/Right$;
         8: new           #17                 // class org/scalatest/exceptions/TestRegistrationClosedException$$anonfun$$lessinit$greater$2
        11: dup
        12: iload_2
        13: invokespecial #162                // Method org/scalatest/exceptions/TestRegistrationClosedException$$anonfun$$lessinit$greater$2."<init>":(I)V
        16: invokevirtual #167                // Method scala/util/Right$.apply:(Ljava/lang/Object;)Lscala/util/Right;
        19: invokespecial #63                 // Method "<init>":(Ljava/lang/String;Lscala/util/Either;)V
        22: return
      LineNumberTable:
        line 88: 0
      LocalVariableTable:
        Start  Length  Slot  Name   Signature
            0      23     0  this   Lorg/scalatest/exceptions/TestRegistrationClosedException;
            0      23     1 message   Ljava/lang/String;
            0      23     2 failedCodeStackDepth   I
    MethodParameters:
      Name                           Flags
      message                        final
      failedCodeStackDepth           final

  public org.scalatest.exceptions.TestRegistrationClosedException(java.lang.String, scala.Function1<org.scalatest.exceptions.StackDepthException, java.lang.Object>);
    descriptor: (Ljava/lang/String;Lscala/Function1;)V
    flags: (0x0001) ACC_PUBLIC
    Code:
      stack=4, locals=3, args_size=3
         0: aload_0
         1: aload_1
         2: getstatic     #143                // Field scala/package$.MODULE$:Lscala/package$;
         5: invokevirtual #159                // Method scala/package$.Right:()Lscala/util/Right$;
         8: aload_2
         9: invokevirtual #167                // Method scala/util/Right$.apply:(Ljava/lang/Object;)Lscala/util/Right;
        12: invokespecial #63                 // Method "<init>":(Ljava/lang/String;Lscala/util/Either;)V
        15: return
      LineNumberTable:
        line 100: 0
      LocalVariableTable:
        Start  Length  Slot  Name   Signature
            0      16     0  this   Lorg/scalatest/exceptions/TestRegistrationClosedException;
            0      16     1 message   Ljava/lang/String;
            0      16     2 failedCodeStackDepthFun   Lscala/Function1;
    Signature: #170                         // (Ljava/lang/String;Lscala/Function1<Lorg/scalatest/exceptions/StackDepthException;Ljava/lang/Object;>;)V
    MethodParameters:
      Name                           Flags
      message                        final
      failedCodeStackDepthFun        final
}
InnerClasses:
  public static #13= #10 of #12;          // RequirementsHelper=class org/scalactic/Requirements$RequirementsHelper of class org/scalactic/Requirements
  public final #15;                       // class org/scalatest/exceptions/TestRegistrationClosedException$$anonfun$$lessinit$greater$1
  public final #17;                       // class org/scalatest/exceptions/TestRegistrationClosedException$$anonfun$$lessinit$greater$2
SourceFile: "TestRegistrationClosedException.scala"
RuntimeVisibleAnnotations:
  0: #6(#7=s#8)
    scala.reflect.ScalaSignature(
      bytes="\u0006\u0005\u00054Aa\u0003\u0007\u0001\'!A\u0001\u0004\u0001B\u0001B\u0003%\u0011\u0004\u0003\u0005\'\u0001\t\u0005\t\u0015!\u0003(\u0011\u0015y\u0004\u0001\"\u0001A\u0011\u0015y\u0004\u0001\"\u0001E\u0011\u0015y\u0004\u0001\"\u0001I\u0011\u0015y\u0004\u0001\"\u0001M\u0011\u0015\u0001\u0006\u0001\"\u0001R\u0011\u0015\u0011\u0006\u0001\"\u0011T\u0011\u0015a\u0006\u0001\"\u0011^\u0011\u0015y\u0006\u0001\"\u0011a\u0005}!Vm\u001d;SK\u001eL7\u000f\u001e:bi&|gn\u00117pg\u0016$W\t_2faRLwN\u001c\u0006\u0003\u001b9\t!\"\u001a=dKB$\u0018n\u001c8t\u0015\ty\u0001#A\u0005tG\u0006d\u0017\r^3ti*\t\u0011#A\u0002pe\u001e\u001c\u0001a\u0005\u0002\u0001)A\u0011QCF\u0007\u0002\u0019%\u0011q\u0003\u0004\u0002\u0014\'R\f7m\u001b#faRDW\t_2faRLwN\\\u0001\b[\u0016\u001c8/Y4f!\tQ2E\u0004\u0002\u001cCA\u0011AdH\u0007\u0002;)\u0011aDE\u0001\u0007yI|w\u000e\u001e \u000b\u0003\u0001\nQa]2bY\u0006L!AI\u0010\u0002\rA\u0013X\rZ3g\u0013\t!SE\u0001\u0004TiJLgn\u001a\u0006\u0003E}\t!\u0003]8t\u001fJ\u001cF/Y2l\t\u0016\u0004H\u000f\u001b$v]B!\u0001&\f\u00199\u001d\tI3F\u0004\u0002\u001dU%\t\u0001%\u0003\u0002-?\u00059\u0001/Y2lC\u001e,\u0017B\u0001\u00180\u0005\u0019)\u0015\u000e\u001e5fe*\u0011Af\b\t\u0003cYj\u0011A\r\u0006\u0003gQ\naa]8ve\u000e,\'BA\u001b\u0011\u0003%\u00198-\u00197bGRL7-\u0003\u00028e\tA\u0001k\\:ji&|g\u000e\u0005\u0003:uQaT\"A\u0010\n\u0005mz\"!\u0003$v]\u000e$\u0018n\u001c82!\tIT(\u0003\u0002??\t\u0019\u0011J\u001c;\u0002\rqJg.\u001b;?)\r\t%i\u0011\t\u0003+\u0001AQ\u0001G\u0002A\u0002eAQAJ\u0002A\u0002\u001d\"2!Q#G\u0011\u0015AB\u00011\u0001\u001a\u0011\u00159E\u00011\u00011\u0003\r\u0001xn\u001d\u000b\u0004\u0003&S\u0005\"\u0002\r\u0006\u0001\u0004I\u0002\"B&\u0006\u0001\u0004a\u0014\u0001\u00064bS2,GmQ8eKN#\u0018mY6EKB$\b\u000eF\u0002B\u001b:CQ\u0001\u0007\u0004A\u0002eAQa\u0014\u0004A\u0002a\nqCZ1jY\u0016$7i\u001c3f\'R\f7m\u001b#faRDg)\u001e8\u0002\'M,g/\u001a:fI\u0006#8\u000b^1dW\u0012+\u0007\u000f\u001e5\u0016\u0003\u0005\u000b\u0001bY1o\u000bF,\u0018\r\u001c\u000b\u0003)^\u0003\"!O+\n\u0005Y{\"a\u0002\"p_2,\u0017M\u001c\u0005\u00061\"\u0001\r!W\u0001\u0006_RDWM\u001d\t\u0003siK!aW\u0010\u0003\u0007\u0005s\u00170\u0001\u0004fcV\fGn\u001d\u000b\u0003)zCQ\u0001W\u0005A\u0002e\u000b\u0001\u0002[1tQ\u000e{G-\u001a\u000b\u0002y\u0001"
    )
  ScalaInlineInfo: length = 0x31 (unknown attribute)
   01 00 00 09 00 3C 00 9B 00 00 3C 00 89 00 00 3C
   00 A9 00 00 3C 00 3D 00 00 48 00 49 00 00 4C 00
   49 00 00 51 00 2F 00 00 17 00 54 00 00 17 00 18
   00
  ScalaSig: length = 0x3 (unknown attribute)
   05 02 00
