Classfile /Users/mw/Projects/slang-braindump/.jar/jar8/assemble/slang-braindump/assemble/content/scala/compat/java8/functionConverterImpls/AsJavaObjDoubleConsumer.class
  Last modified May 29, 2022; size 1760 bytes
  SHA-256 checksum fd7800a739cd2c7a9afee3c30d58a9593502ce6f43cc4f2ab3928a4d796d0b1a
  Compiled from "FunctionConverters.scala"
public class scala.compat.java8.functionConverterImpls.AsJavaObjDoubleConsumer<T extends java.lang.Object> extends java.lang.Object implements java.util.function.ObjDoubleConsumer<T>
  minor version: 0
  major version: 52
  flags: (0x0021) ACC_PUBLIC, ACC_SUPER
  this_class: #2                          // scala/compat/java8/functionConverterImpls/AsJavaObjDoubleConsumer
  super_class: #5                         // java/lang/Object
  interfaces: 1, fields: 1, methods: 2, attributes: 5
Constant pool:
   #1 = Utf8               scala/compat/java8/functionConverterImpls/AsJavaObjDoubleConsumer
   #2 = Class              #1             // scala/compat/java8/functionConverterImpls/AsJavaObjDoubleConsumer
   #3 = Utf8               <T:Ljava/lang/Object;>Ljava/lang/Object;Ljava/util/function/ObjDoubleConsumer<TT;>;
   #4 = Utf8               java/lang/Object
   #5 = Class              #4             // java/lang/Object
   #6 = Utf8               java/util/function/ObjDoubleConsumer
   #7 = Class              #6             // java/util/function/ObjDoubleConsumer
   #8 = Utf8               FunctionConverters.scala
   #9 = Utf8               Lscala/reflect/ScalaSignature;
  #10 = Utf8               bytes
  #11 = Utf8               \u0006\u0005\u00053A\u0001B\u0003\u0001\u001d!AA\u0006\u0001B\u0001B\u0003%Q\u0006C\u00037\u0001\u0011\u0005q\u0007C\u0003<\u0001\u0011\u0005AHA\fBg*\u000bg/Y(cU\u0012{WO\u00197f\u0007>t7/^7fe*\u0011aaB\u0001\u0017MVt7\r^5p]\u000e{gN^3si\u0016\u0014\u0018*\u001c9mg*\u0011\u0001\"C\u0001\u0006U\u00064\u0018\r\u000f\u0006\u0003\u0015-\taaY8na\u0006$(\"\u0001\u0007\u0002\u000bM\u001c\u0017\r\\1\u0004\u0001U\u0011qBI\n\u0004\u0001AA\u0002CA\t\u0017\u001b\u0005\u0011\"BA\n\u0015\u0003\u0011a\u0017M\\4\u000b\u0003U\tAA[1wC&\u0011qC\u0005\u0002\u0007\u001f\nTWm\u0019;\u0011\u0007eq\u0002%D\u0001\u001b\u0015\tYB$\u0001\u0005gk:\u001cG/[8o\u0015\tiB#\u0001\u0003vi&d\u0017BA\u0010\u001b\u0005Ey%M\u001b#pk\ndWmQ8ogVlWM\u001d\t\u0003C\tb\u0001\u0001B\u0003$\u0001\t\u0007AEA\u0001U#\t)\u0013\u0006\u0005\u0002\'O5\t1\"\u0003\u0002)\u0017\t9aj\u001c;iS:<\u0007C\u0001\u0014+\u0013\tY3BA\u0002B]f\f!a\u001d4\u0011\u000b\u0019r\u0003\u0005M\u001a\n\u0005=Z!!\u0003$v]\u000e$\u0018n\u001c83!\t1\u0013\'\u0003\u00023\u0017\t1Ai\\;cY\u0016\u0004\"A\n\u001b\n\u0005UZ!\u0001B+oSR\fa\u0001P5oSRtDC\u0001\u001d;!\rI\u0004\u0001I\u0007\u0002\u000b!)AF\u0001a\u0001[\u00051\u0011mY2faR$2aM\u001f@\u0011\u0015q4\u00011\u0001!\u0003\tA\u0018\u0007C\u0003A\u0007\u0001\u0007\u0001\'\u0001\u0002ye\u0001
  #12 = Utf8               sf
  #13 = Utf8               Lscala/Function2;
  #14 = Utf8               Lscala/Function2<TT;Ljava/lang/Object;Lscala/runtime/BoxedUnit;>;
  #15 = Utf8               accept
  #16 = Utf8               (Ljava/lang/Object;D)V
  #17 = Utf8               (TT;D)V
  #18 = Utf8               x1
  #19 = Utf8               x2
  #20 = NameAndType        #12:#13        // sf:Lscala/Function2;
  #21 = Fieldref           #2.#20         // scala/compat/java8/functionConverterImpls/AsJavaObjDoubleConsumer.sf:Lscala/Function2;
  #22 = Utf8               scala/runtime/BoxesRunTime
  #23 = Class              #22            // scala/runtime/BoxesRunTime
  #24 = Utf8               boxToDouble
  #25 = Utf8               (D)Ljava/lang/Double;
  #26 = NameAndType        #24:#25        // boxToDouble:(D)Ljava/lang/Double;
  #27 = Methodref          #23.#26        // scala/runtime/BoxesRunTime.boxToDouble:(D)Ljava/lang/Double;
  #28 = Utf8               scala/Function2
  #29 = Class              #28            // scala/Function2
  #30 = Utf8               apply
  #31 = Utf8               (Ljava/lang/Object;Ljava/lang/Object;)Ljava/lang/Object;
  #32 = NameAndType        #30:#31        // apply:(Ljava/lang/Object;Ljava/lang/Object;)Ljava/lang/Object;
  #33 = InterfaceMethodref #29.#32        // scala/Function2.apply:(Ljava/lang/Object;Ljava/lang/Object;)Ljava/lang/Object;
  #34 = Utf8               this
  #35 = Utf8               Lscala/compat/java8/functionConverterImpls/AsJavaObjDoubleConsumer;
  #36 = Utf8               Ljava/lang/Object;
  #37 = Utf8               D
  #38 = Utf8               <init>
  #39 = Utf8               (Lscala/Function2;)V
  #40 = Utf8               (Lscala/Function2<TT;Ljava/lang/Object;Lscala/runtime/BoxedUnit;>;)V
  #41 = Utf8               ()V
  #42 = NameAndType        #38:#41        // "<init>":()V
  #43 = Methodref          #5.#42         // java/lang/Object."<init>":()V
  #44 = Utf8               Signature
  #45 = Utf8               Code
  #46 = Utf8               LineNumberTable
  #47 = Utf8               LocalVariableTable
  #48 = Utf8               MethodParameters
  #49 = Utf8               SourceFile
  #50 = Utf8               RuntimeVisibleAnnotations
  #51 = Utf8               ScalaInlineInfo
  #52 = Utf8               ScalaSig
{
  private final scala.Function2<T, java.lang.Object, scala.runtime.BoxedUnit> sf;
    descriptor: Lscala/Function2;
    flags: (0x0012) ACC_PRIVATE, ACC_FINAL
    Signature: #14                          // Lscala/Function2<TT;Ljava/lang/Object;Lscala/runtime/BoxedUnit;>;

  public void accept(T, double);
    descriptor: (Ljava/lang/Object;D)V
    flags: (0x0001) ACC_PUBLIC
    Code:
      stack=4, locals=4, args_size=3
         0: aload_0
         1: getfield      #21                 // Field sf:Lscala/Function2;
         4: aload_1
         5: dload_2
         6: invokestatic  #27                 // Method scala/runtime/BoxesRunTime.boxToDouble:(D)Ljava/lang/Double;
         9: invokeinterface #33,  3           // InterfaceMethod scala/Function2.apply:(Ljava/lang/Object;Ljava/lang/Object;)Ljava/lang/Object;
        14: pop
        15: return
      LineNumberTable:
        line 548: 0
      LocalVariableTable:
        Start  Length  Slot  Name   Signature
            0      16     0  this   Lscala/compat/java8/functionConverterImpls/AsJavaObjDoubleConsumer;
            0      16     1    x1   Ljava/lang/Object;
            0      16     2    x2   D
    Signature: #17                          // (TT;D)V
    MethodParameters:
      Name                           Flags
      x1                             final
      x2                             final

  public scala.compat.java8.functionConverterImpls.AsJavaObjDoubleConsumer(scala.Function2<T, java.lang.Object, scala.runtime.BoxedUnit>);
    descriptor: (Lscala/Function2;)V
    flags: (0x0001) ACC_PUBLIC
    Code:
      stack=2, locals=2, args_size=2
         0: aload_0
         1: aload_1
         2: putfield      #21                 // Field sf:Lscala/Function2;
         5: aload_0
         6: invokespecial #43                 // Method java/lang/Object."<init>":()V
         9: return
      LineNumberTable:
        line 547: 0
      LocalVariableTable:
        Start  Length  Slot  Name   Signature
            0      10     0  this   Lscala/compat/java8/functionConverterImpls/AsJavaObjDoubleConsumer;
            0      10     1    sf   Lscala/Function2;
    Signature: #40                          // (Lscala/Function2<TT;Ljava/lang/Object;Lscala/runtime/BoxedUnit;>;)V
    MethodParameters:
      Name                           Flags
      sf                             final
}
Signature: #3                           // <T:Ljava/lang/Object;>Ljava/lang/Object;Ljava/util/function/ObjDoubleConsumer<TT;>;
SourceFile: "FunctionConverters.scala"
RuntimeVisibleAnnotations:
  0: #9(#10=s#11)
    scala.reflect.ScalaSignature(
      bytes="\u0006\u0005\u00053A\u0001B\u0003\u0001\u001d!AA\u0006\u0001B\u0001B\u0003%Q\u0006C\u00037\u0001\u0011\u0005q\u0007C\u0003<\u0001\u0011\u0005AHA\fBg*\u000bg/Y(cU\u0012{WO\u00197f\u0007>t7/^7fe*\u0011aaB\u0001\u0017MVt7\r^5p]\u000e{gN^3si\u0016\u0014\u0018*\u001c9mg*\u0011\u0001\"C\u0001\u0006U\u00064\u0018\r\u000f\u0006\u0003\u0015-\taaY8na\u0006$(\"\u0001\u0007\u0002\u000bM\u001c\u0017\r\\1\u0004\u0001U\u0011qBI\n\u0004\u0001AA\u0002CA\t\u0017\u001b\u0005\u0011\"BA\n\u0015\u0003\u0011a\u0017M\\4\u000b\u0003U\tAA[1wC&\u0011qC\u0005\u0002\u0007\u001f\nTWm\u0019;\u0011\u0007eq\u0002%D\u0001\u001b\u0015\tYB$\u0001\u0005gk:\u001cG/[8o\u0015\tiB#\u0001\u0003vi&d\u0017BA\u0010\u001b\u0005Ey%M\u001b#pk\ndWmQ8ogVlWM\u001d\t\u0003C\tb\u0001\u0001B\u0003$\u0001\t\u0007AEA\u0001U#\t)\u0013\u0006\u0005\u0002\'O5\t1\"\u0003\u0002)\u0017\t9aj\u001c;iS:<\u0007C\u0001\u0014+\u0013\tY3BA\u0002B]f\f!a\u001d4\u0011\u000b\u0019r\u0003\u0005M\u001a\n\u0005=Z!!\u0003$v]\u000e$\u0018n\u001c83!\t1\u0013\'\u0003\u00023\u0017\t1Ai\\;cY\u0016\u0004\"A\n\u001b\n\u0005UZ!\u0001B+oSR\fa\u0001P5oSRtDC\u0001\u001d;!\rI\u0004\u0001I\u0007\u0002\u000b!)AF\u0001a\u0001[\u00051\u0011mY2faR$2aM\u001f@\u0011\u0015q4\u00011\u0001!\u0003\tA\u0018\u0007C\u0003A\u0007\u0001\u0007\u0001\'\u0001\u0002ye\u0001"
    )
  ScalaInlineInfo: length = 0xE (unknown attribute)
   01 00 00 02 00 26 00 27 00 00 0F 00 10 00
  ScalaSig: length = 0x3 (unknown attribute)
   05 02 00
