Classfile /Users/mw/Projects/slang-braindump/.jar/jar8/assemble/slang-braindump/assemble/content/scala/compat/java8/functionConverterImpls/AsJavaToLongBiFunction.class
  Last modified May 29, 2022; size 1758 bytes
  SHA-256 checksum 44475d898aed4b8163b98d5dd3d5719014bd497c2a97cc0538ab322e85745f9d
  Compiled from "FunctionConverters.scala"
public class scala.compat.java8.functionConverterImpls.AsJavaToLongBiFunction<T extends java.lang.Object, U extends java.lang.Object> extends java.lang.Object implements java.util.function.ToLongBiFunction<T, U>
  minor version: 0
  major version: 52
  flags: (0x0021) ACC_PUBLIC, ACC_SUPER
  this_class: #2                          // scala/compat/java8/functionConverterImpls/AsJavaToLongBiFunction
  super_class: #5                         // java/lang/Object
  interfaces: 1, fields: 1, methods: 2, attributes: 5
Constant pool:
   #1 = Utf8               scala/compat/java8/functionConverterImpls/AsJavaToLongBiFunction
   #2 = Class              #1             // scala/compat/java8/functionConverterImpls/AsJavaToLongBiFunction
   #3 = Utf8               <T:Ljava/lang/Object;U:Ljava/lang/Object;>Ljava/lang/Object;Ljava/util/function/ToLongBiFunction<TT;TU;>;
   #4 = Utf8               java/lang/Object
   #5 = Class              #4             // java/lang/Object
   #6 = Utf8               java/util/function/ToLongBiFunction
   #7 = Class              #6             // java/util/function/ToLongBiFunction
   #8 = Utf8               FunctionConverters.scala
   #9 = Utf8               Lscala/reflect/ScalaSignature;
  #10 = Utf8               bytes
  #11 = Utf8               \u0006\u0005\u00053A\u0001B\u0003\u0001\u001d!Aq\u0006\u0001B\u0001B\u0003%\u0001\u0007C\u00037\u0001\u0011\u0005q\u0007C\u0003<\u0001\u0011\u0005AH\u0001\fBg*\u000bg/\u0019+p\u0019>twMQ5Gk:\u001cG/[8o\u0015\t1q!\u0001\fgk:\u001cG/[8o\u0007>tg/\u001a:uKJLU\u000e\u001d7t\u0015\tA\u0011\"A\u0003kCZ\f\u0007H\u0003\u0002\u000b\u0017\u000511m\\7qCRT\u0011\u0001D\u0001\u0006g\u000e\fG.Y\u0002\u0001+\ry!%L\n\u0004\u0001AA\u0002CA\t\u0017\u001b\u0005\u0011\"BA\n\u0015\u0003\u0011a\u0017M\\4\u000b\u0003U\tAA[1wC&\u0011qC\u0005\u0002\u0007\u001f\nTWm\u0019;\u0011\teq\u0002\u0005L\u0007\u00025)\u00111\u0004H\u0001\tMVt7\r^5p]*\u0011Q\u0004F\u0001\u0005kRLG.\u0003\u0002 5\t\u0001Bk\u001c\'p]\u001e\u0014\u0015NR;oGRLwN\u001c\t\u0003C\tb\u0001\u0001B\u0003$\u0001\t\u0007AEA\u0001U#\t)\u0013\u0006\u0005\u0002\'O5\t1\"\u0003\u0002)\u0017\t9aj\u001c;iS:<\u0007C\u0001\u0014+\u0013\tY3BA\u0002B]f\u0004\"!I\u0017\u0005\u000b9\u0002!\u0019\u0001\u0013\u0003\u0003U\u000b!a\u001d4\u0011\u000b\u0019\n\u0004\u0005L\u001a\n\u0005IZ!!\u0003$v]\u000e$\u0018n\u001c83!\t1C\'\u0003\u00026\u0017\t!Aj\u001c8h\u0003\u0019a\u0014N\\5u}Q\u0011\u0001H\u000f\t\u0005s\u0001\u0001C&D\u0001\u0006\u0011\u0015y#\u00011\u00011\u0003-\t\u0007\u000f\u001d7z\u0003NduN\\4\u0015\u0007Mjt\bC\u0003?\u0007\u0001\u0007\u0001%\u0001\u0002yc!)\u0001i\u0001a\u0001Y\u0005\u0011\u0001P\r
  #12 = Utf8               sf
  #13 = Utf8               Lscala/Function2;
  #14 = Utf8               Lscala/Function2<TT;TU;Ljava/lang/Object;>;
  #15 = Utf8               applyAsLong
  #16 = Utf8               (Ljava/lang/Object;Ljava/lang/Object;)J
  #17 = Utf8               (TT;TU;)J
  #18 = Utf8               x1
  #19 = Utf8               x2
  #20 = NameAndType        #12:#13        // sf:Lscala/Function2;
  #21 = Fieldref           #2.#20         // scala/compat/java8/functionConverterImpls/AsJavaToLongBiFunction.sf:Lscala/Function2;
  #22 = Utf8               scala/Function2
  #23 = Class              #22            // scala/Function2
  #24 = Utf8               apply
  #25 = Utf8               (Ljava/lang/Object;Ljava/lang/Object;)Ljava/lang/Object;
  #26 = NameAndType        #24:#25        // apply:(Ljava/lang/Object;Ljava/lang/Object;)Ljava/lang/Object;
  #27 = InterfaceMethodref #23.#26        // scala/Function2.apply:(Ljava/lang/Object;Ljava/lang/Object;)Ljava/lang/Object;
  #28 = Utf8               scala/runtime/BoxesRunTime
  #29 = Class              #28            // scala/runtime/BoxesRunTime
  #30 = Utf8               unboxToLong
  #31 = Utf8               (Ljava/lang/Object;)J
  #32 = NameAndType        #30:#31        // unboxToLong:(Ljava/lang/Object;)J
  #33 = Methodref          #29.#32        // scala/runtime/BoxesRunTime.unboxToLong:(Ljava/lang/Object;)J
  #34 = Utf8               this
  #35 = Utf8               Lscala/compat/java8/functionConverterImpls/AsJavaToLongBiFunction;
  #36 = Utf8               Ljava/lang/Object;
  #37 = Utf8               <init>
  #38 = Utf8               (Lscala/Function2;)V
  #39 = Utf8               (Lscala/Function2<TT;TU;Ljava/lang/Object;>;)V
  #40 = Utf8               ()V
  #41 = NameAndType        #37:#40        // "<init>":()V
  #42 = Methodref          #5.#41         // java/lang/Object."<init>":()V
  #43 = Utf8               Signature
  #44 = Utf8               Code
  #45 = Utf8               LineNumberTable
  #46 = Utf8               LocalVariableTable
  #47 = Utf8               MethodParameters
  #48 = Utf8               SourceFile
  #49 = Utf8               RuntimeVisibleAnnotations
  #50 = Utf8               ScalaInlineInfo
  #51 = Utf8               ScalaSig
{
  private final scala.Function2<T, U, java.lang.Object> sf;
    descriptor: Lscala/Function2;
    flags: (0x0012) ACC_PRIVATE, ACC_FINAL
    Signature: #14                          // Lscala/Function2<TT;TU;Ljava/lang/Object;>;

  public long applyAsLong(T, U);
    descriptor: (Ljava/lang/Object;Ljava/lang/Object;)J
    flags: (0x0001) ACC_PUBLIC
    Code:
      stack=3, locals=3, args_size=3
         0: aload_0
         1: getfield      #21                 // Field sf:Lscala/Function2;
         4: aload_1
         5: aload_2
         6: invokeinterface #27,  3           // InterfaceMethod scala/Function2.apply:(Ljava/lang/Object;Ljava/lang/Object;)Ljava/lang/Object;
        11: invokestatic  #33                 // Method scala/runtime/BoxesRunTime.unboxToLong:(Ljava/lang/Object;)J
        14: lreturn
      LineNumberTable:
        line 701: 0
      LocalVariableTable:
        Start  Length  Slot  Name   Signature
            0      15     0  this   Lscala/compat/java8/functionConverterImpls/AsJavaToLongBiFunction;
            0      15     1    x1   Ljava/lang/Object;
            0      15     2    x2   Ljava/lang/Object;
    Signature: #17                          // (TT;TU;)J
    MethodParameters:
      Name                           Flags
      x1                             final
      x2                             final

  public scala.compat.java8.functionConverterImpls.AsJavaToLongBiFunction(scala.Function2<T, U, java.lang.Object>);
    descriptor: (Lscala/Function2;)V
    flags: (0x0001) ACC_PUBLIC
    Code:
      stack=2, locals=2, args_size=2
         0: aload_0
         1: aload_1
         2: putfield      #21                 // Field sf:Lscala/Function2;
         5: aload_0
         6: invokespecial #42                 // Method java/lang/Object."<init>":()V
         9: return
      LineNumberTable:
        line 700: 0
      LocalVariableTable:
        Start  Length  Slot  Name   Signature
            0      10     0  this   Lscala/compat/java8/functionConverterImpls/AsJavaToLongBiFunction;
            0      10     1    sf   Lscala/Function2;
    Signature: #39                          // (Lscala/Function2<TT;TU;Ljava/lang/Object;>;)V
    MethodParameters:
      Name                           Flags
      sf                             final
}
Signature: #3                           // <T:Ljava/lang/Object;U:Ljava/lang/Object;>Ljava/lang/Object;Ljava/util/function/ToLongBiFunction<TT;TU;>;
SourceFile: "FunctionConverters.scala"
RuntimeVisibleAnnotations:
  0: #9(#10=s#11)
    scala.reflect.ScalaSignature(
      bytes="\u0006\u0005\u00053A\u0001B\u0003\u0001\u001d!Aq\u0006\u0001B\u0001B\u0003%\u0001\u0007C\u00037\u0001\u0011\u0005q\u0007C\u0003<\u0001\u0011\u0005AH\u0001\fBg*\u000bg/\u0019+p\u0019>twMQ5Gk:\u001cG/[8o\u0015\t1q!\u0001\fgk:\u001cG/[8o\u0007>tg/\u001a:uKJLU\u000e\u001d7t\u0015\tA\u0011\"A\u0003kCZ\f\u0007H\u0003\u0002\u000b\u0017\u000511m\\7qCRT\u0011\u0001D\u0001\u0006g\u000e\fG.Y\u0002\u0001+\ry!%L\n\u0004\u0001AA\u0002CA\t\u0017\u001b\u0005\u0011\"BA\n\u0015\u0003\u0011a\u0017M\\4\u000b\u0003U\tAA[1wC&\u0011qC\u0005\u0002\u0007\u001f\nTWm\u0019;\u0011\teq\u0002\u0005L\u0007\u00025)\u00111\u0004H\u0001\tMVt7\r^5p]*\u0011Q\u0004F\u0001\u0005kRLG.\u0003\u0002 5\t\u0001Bk\u001c\'p]\u001e\u0014\u0015NR;oGRLwN\u001c\t\u0003C\tb\u0001\u0001B\u0003$\u0001\t\u0007AEA\u0001U#\t)\u0013\u0006\u0005\u0002\'O5\t1\"\u0003\u0002)\u0017\t9aj\u001c;iS:<\u0007C\u0001\u0014+\u0013\tY3BA\u0002B]f\u0004\"!I\u0017\u0005\u000b9\u0002!\u0019\u0001\u0013\u0003\u0003U\u000b!a\u001d4\u0011\u000b\u0019\n\u0004\u0005L\u001a\n\u0005IZ!!\u0003$v]\u000e$\u0018n\u001c83!\t1C\'\u0003\u00026\u0017\t!Aj\u001c8h\u0003\u0019a\u0014N\\5u}Q\u0011\u0001H\u000f\t\u0005s\u0001\u0001C&D\u0001\u0006\u0011\u0015y#\u00011\u00011\u0003-\t\u0007\u000f\u001d7z\u0003NduN\\4\u0015\u0007Mjt\bC\u0003?\u0007\u0001\u0007\u0001%\u0001\u0002yc!)\u0001i\u0001a\u0001Y\u0005\u0011\u0001P\r"
    )
  ScalaInlineInfo: length = 0xE (unknown attribute)
   01 00 00 02 00 25 00 26 00 00 0F 00 10 00
  ScalaSig: length = 0x3 (unknown attribute)
   05 02 00
