Classfile /Users/mw/Projects/slang-braindump/.jar/jar8/assemble/slang-braindump/assemble/content/scala/compat/java8/functionConverterImpls/RichFunction2AsToDoubleBiFunction.class
  Last modified May 29, 2022; size 3648 bytes
  SHA-256 checksum d23964808bde7988dd7dfb091675d09efb4e7916f2797e12bd73ecc58e559288
  Compiled from "FunctionConverters.scala"
public final class scala.compat.java8.functionConverterImpls.RichFunction2AsToDoubleBiFunction<T extends java.lang.Object, U extends java.lang.Object> extends java.lang.Object
  minor version: 0
  major version: 52
  flags: (0x0031) ACC_PUBLIC, ACC_FINAL, ACC_SUPER
  this_class: #2                          // scala/compat/java8/functionConverterImpls/RichFunction2AsToDoubleBiFunction
  super_class: #5                         // java/lang/Object
  interfaces: 0, fields: 1, methods: 8, attributes: 5
Constant pool:
   #1 = Utf8               scala/compat/java8/functionConverterImpls/RichFunction2AsToDoubleBiFunction
   #2 = Class              #1             // scala/compat/java8/functionConverterImpls/RichFunction2AsToDoubleBiFunction
   #3 = Utf8               <T:Ljava/lang/Object;U:Ljava/lang/Object;>Ljava/lang/Object;
   #4 = Utf8               java/lang/Object
   #5 = Class              #4             // java/lang/Object
   #6 = Utf8               FunctionConverters.scala
   #7 = Utf8               Lscala/reflect/ScalaSignature;
   #8 = Utf8               bytes
   #9 = Utf8               \u0006\u0005u4A!\u0004\b\u0003/!aQ\u0004\u0001C\u0001\u0002\u000b\u0015)\u0019!C\u0005=!I1\u0007\u0001B\u0003\u0002\u0003\u0006Ia\b\u0005\u0006i\u0001!\t!\u000e\u0005\u0006u\u0001!\ta\u000f\u0005\b\u0015\u0002\t\t\u0011\"\u0011L\u0011\u001dy\u0005!!A\u0005BA;qA\u0016\b\u0002\u0002#\u0005qKB\u0004\u000e\u001d\u0005\u0005\t\u0012\u0001-\t\u000bQBA\u0011\u0001/\t\u000buCAQ\u00010\t\u000f%D\u0011\u0011!C\u0003U\"9!\u000fCA\u0001\n\u000b\u0019(!\t*jG\"4UO\\2uS>t\'\'Q:U_\u0012{WO\u00197f\u0005&4UO\\2uS>t\'BA\b\u0011\u0003Y1WO\\2uS>t7i\u001c8wKJ$XM]%na2\u001c(BA\t\u0013\u0003\u0015Q\u0017M^19\u0015\t\u0019B#\u0001\u0004d_6\u0004\u0018\r\u001e\u0006\u0002+\u0005)1oY1mC\u000e\u0001Qc\u0001\r%]M\u0011\u0001!\u0007\t\u00035mi\u0011\u0001F\u0005\u00039Q\u0011a!\u00118z-\u0006d\u0017aV:dC2\fGeY8na\u0006$HE[1wCb\"c-\u001e8di&|gnQ8om\u0016\u0014H/\u001a:J[Bd7\u000f\n*jG\"4UO\\2uS>t\'\'Q:U_\u0012{WO\u00197f\u0005&4UO\\2uS>tG\u0005J;oI\u0016\u0014H._5oOV\tq\u0004E\u0003\u001bA\tj\u0003\'\u0003\u0002\")\tIa)\u001e8di&|gN\r\t\u0003G\u0011b\u0001\u0001B\u0003&\u0001\t\u0007aEA\u0001U#\t9#\u0006\u0005\u0002\u001bQ%\u0011\u0011\u0006\u0006\u0002\b\u001d>$\b.\u001b8h!\tQ2&\u0003\u0002-)\t\u0019\u0011I\\=\u0011\u0005\rrC!B\u0018\u0001\u0005\u00041#!A+\u0011\u0005i\t\u0014B\u0001\u001a\u0015\u0005\u0019!u.\u001e2mK\u0006A6oY1mC\u0012\u001aw.\u001c9bi\u0012R\u0017M^19I\u0019,hn\u0019;j_:\u001cuN\u001c<feR,\'/S7qYN$#+[2i\rVt7\r^5p]J\n5\u000fV8E_V\u0014G.\u001a\"j\rVt7\r^5p]\u0012\"SO\u001c3fe2L\u0018N\\4!\u0003\u0019a\u0014N\\5u}Q\u0011a\u0007\u000f\t\u0005o\u0001\u0011S&D\u0001\u000f\u0011\u0015I4\u00011\u0001 \u0003))h\u000eZ3sYfLgnZ\u0001\u0007CNT\u0015M^1\u0016\u0003q\u0002B!\u0010##[5\taH\u0003\u0002@\u0001\u0006Aa-\u001e8di&|gN\u0003\u0002B\u0005\u0006!Q\u000f^5m\u0015\u0005\u0019\u0015\u0001\u00026bm\u0006L!!\u0012 \u0003%Q{Gi\\;cY\u0016\u0014\u0015NR;oGRLwN\u001c\u0015\u0003\t\u001d\u0003\"A\u0007%\n\u0005%#\"AB5oY&tW-\u0001\u0005iCND7i\u001c3f)\u0005a\u0005C\u0001\u000eN\u0013\tqECA\u0002J]R\fa!Z9vC2\u001cHCA)U!\tQ\"+\u0003\u0002T)\t9!i\\8mK\u0006t\u0007bB+\u0007\u0003\u0003\u0005\rAK\u0001\u0004q\u0012\n\u0014!\t*jG\"4UO\\2uS>t\'\'Q:U_\u0012{WO\u00197f\u0005&4UO\\2uS>t\u0007CA\u001c\t\'\tA\u0011\f\u0005\u0002\u001b5&\u00111\f\u0006\u0002\u0007\u0003:L(+\u001a4\u0015\u0003]\u000b\u0001#Y:KCZ\fG%\u001a=uK:\u001c\u0018n\u001c8\u0016\u0007}\u0013G\r\u0006\u0002aKB!Q\bR1d!\t\u0019#\rB\u0003&\u0015\t\u0007a\u0005\u0005\u0002$I\u0012)qF\u0003b\u0001M!)aM\u0003a\u0001O\u0006)A\u0005\u001e5jgB!q\u0007A1dQ\tQq)\u0001\niCND7i\u001c3fI\u0015DH/\u001a8tS>tWcA6pcR\u00111\n\u001c\u0005\u0006M.\u0001\r!\u001c\t\u0005o\u0001q\u0007\u000f\u0005\u0002$_\u0012)Qe\u0003b\u0001MA\u00111%\u001d\u0003\u0006_-\u0011\rAJ\u0001\u0011KF,\u0018\r\\:%Kb$XM\\:j_:,2\u0001\u001e>})\t)x\u000f\u0006\u0002Rm\"9Q\u000bDA\u0001\u0002\u0004Q\u0003\"\u00024\r\u0001\u0004A\b\u0003B\u001c\u0001sn\u0004\"a\t>\u0005\u000b\u0015b!\u0019\u0001\u0014\u0011\u0005\rbH!B\u0018\r\u0005\u00041\u0003
  #10 = Utf8               scala$compat$java8$functionConverterImpls$RichFunction2AsToDoubleBiFunction$$underlying
  #11 = Utf8               Lscala/Function2;
  #12 = Utf8               Lscala/Function2<TT;TU;Ljava/lang/Object;>;
  #13 = Utf8               equals$extension
  #14 = Utf8               (Lscala/Function2;Ljava/lang/Object;)Z
  #15 = Utf8               <T:Ljava/lang/Object;U:Ljava/lang/Object;>(Lscala/Function2<TT;TU;Ljava/lang/Object;>;Ljava/lang/Object;)Z
  #16 = Utf8               $this
  #17 = Utf8               x$1
  #18 = Utf8               scala/compat/java8/functionConverterImpls/RichFunction2AsToDoubleBiFunction$
  #19 = Class              #18            // scala/compat/java8/functionConverterImpls/RichFunction2AsToDoubleBiFunction$
  #20 = Utf8               MODULE$
  #21 = Utf8               Lscala/compat/java8/functionConverterImpls/RichFunction2AsToDoubleBiFunction$;
  #22 = NameAndType        #20:#21        // MODULE$:Lscala/compat/java8/functionConverterImpls/RichFunction2AsToDoubleBiFunction$;
  #23 = Fieldref           #19.#22        // scala/compat/java8/functionConverterImpls/RichFunction2AsToDoubleBiFunction$.MODULE$:Lscala/compat/java8/functionConverterImpls/RichFunction2AsToDoubleBiFunction$;
  #24 = NameAndType        #13:#14        // equals$extension:(Lscala/Function2;Ljava/lang/Object;)Z
  #25 = Methodref          #19.#24        // scala/compat/java8/functionConverterImpls/RichFunction2AsToDoubleBiFunction$.equals$extension:(Lscala/Function2;Ljava/lang/Object;)Z
  #26 = Utf8               Ljava/lang/Object;
  #27 = Utf8               hashCode$extension
  #28 = Utf8               (Lscala/Function2;)I
  #29 = Utf8               <T:Ljava/lang/Object;U:Ljava/lang/Object;>(Lscala/Function2<TT;TU;Ljava/lang/Object;>;)I
  #30 = NameAndType        #27:#28        // hashCode$extension:(Lscala/Function2;)I
  #31 = Methodref          #19.#30        // scala/compat/java8/functionConverterImpls/RichFunction2AsToDoubleBiFunction$.hashCode$extension:(Lscala/Function2;)I
  #32 = Utf8               asJava$extension
  #33 = Utf8               (Lscala/Function2;)Ljava/util/function/ToDoubleBiFunction;
  #34 = Utf8               <T:Ljava/lang/Object;U:Ljava/lang/Object;>(Lscala/Function2<TT;TU;Ljava/lang/Object;>;)Ljava/util/function/ToDoubleBiFunction<TT;TU;>;
  #35 = NameAndType        #32:#33        // asJava$extension:(Lscala/Function2;)Ljava/util/function/ToDoubleBiFunction;
  #36 = Methodref          #19.#35        // scala/compat/java8/functionConverterImpls/RichFunction2AsToDoubleBiFunction$.asJava$extension:(Lscala/Function2;)Ljava/util/function/ToDoubleBiFunction;
  #37 = Utf8               ()Lscala/Function2;
  #38 = Utf8               ()Lscala/Function2<TT;TU;Ljava/lang/Object;>;
  #39 = NameAndType        #10:#11        // scala$compat$java8$functionConverterImpls$RichFunction2AsToDoubleBiFunction$$underlying:Lscala/Function2;
  #40 = Fieldref           #2.#39         // scala/compat/java8/functionConverterImpls/RichFunction2AsToDoubleBiFunction.scala$compat$java8$functionConverterImpls$RichFunction2AsToDoubleBiFunction$$underlying:Lscala/Function2;
  #41 = Utf8               this
  #42 = Utf8               Lscala/compat/java8/functionConverterImpls/RichFunction2AsToDoubleBiFunction;
  #43 = Utf8               asJava
  #44 = Utf8               ()Ljava/util/function/ToDoubleBiFunction;
  #45 = Utf8               ()Ljava/util/function/ToDoubleBiFunction<TT;TU;>;
  #46 = NameAndType        #10:#37        // scala$compat$java8$functionConverterImpls$RichFunction2AsToDoubleBiFunction$$underlying:()Lscala/Function2;
  #47 = Methodref          #2.#46         // scala/compat/java8/functionConverterImpls/RichFunction2AsToDoubleBiFunction.scala$compat$java8$functionConverterImpls$RichFunction2AsToDoubleBiFunction$$underlying:()Lscala/Function2;
  #48 = Utf8               hashCode
  #49 = Utf8               ()I
  #50 = Utf8               equals
  #51 = Utf8               (Ljava/lang/Object;)Z
  #52 = Utf8               <init>
  #53 = Utf8               (Lscala/Function2;)V
  #54 = Utf8               (Lscala/Function2<TT;TU;Ljava/lang/Object;>;)V
  #55 = Utf8               underlying
  #56 = Utf8               ()V
  #57 = NameAndType        #52:#56        // "<init>":()V
  #58 = Methodref          #5.#57         // java/lang/Object."<init>":()V
  #59 = Utf8               Signature
  #60 = Utf8               Code
  #61 = Utf8               LocalVariableTable
  #62 = Utf8               MethodParameters
  #63 = Utf8               LineNumberTable
  #64 = Utf8               SourceFile
  #65 = Utf8               RuntimeVisibleAnnotations
  #66 = Utf8               ScalaInlineInfo
  #67 = Utf8               ScalaSig
{
  private final scala.Function2<T, U, java.lang.Object> scala$compat$java8$functionConverterImpls$RichFunction2AsToDoubleBiFunction$$underlying;
    descriptor: Lscala/Function2;
    flags: (0x0012) ACC_PRIVATE, ACC_FINAL
    Signature: #12                          // Lscala/Function2<TT;TU;Ljava/lang/Object;>;

  public static <T extends java.lang.Object, U extends java.lang.Object> boolean equals$extension(scala.Function2<T, U, java.lang.Object>, java.lang.Object);
    descriptor: (Lscala/Function2;Ljava/lang/Object;)Z
    flags: (0x0009) ACC_PUBLIC, ACC_STATIC
    Code:
      stack=3, locals=2, args_size=2
         0: getstatic     #23                 // Field scala/compat/java8/functionConverterImpls/RichFunction2AsToDoubleBiFunction$.MODULE$:Lscala/compat/java8/functionConverterImpls/RichFunction2AsToDoubleBiFunction$;
         3: aload_0
         4: aload_1
         5: invokevirtual #25                 // Method scala/compat/java8/functionConverterImpls/RichFunction2AsToDoubleBiFunction$.equals$extension:(Lscala/Function2;Ljava/lang/Object;)Z
         8: ireturn
      LocalVariableTable:
        Start  Length  Slot  Name   Signature
            0       9     0 $this   Lscala/Function2;
            0       9     1   x$1   Ljava/lang/Object;
    Signature: #15                          // <T:Ljava/lang/Object;U:Ljava/lang/Object;>(Lscala/Function2<TT;TU;Ljava/lang/Object;>;Ljava/lang/Object;)Z
    MethodParameters:
      Name                           Flags
      $this                          final
      x$1                            final

  public static <T extends java.lang.Object, U extends java.lang.Object> int hashCode$extension(scala.Function2<T, U, java.lang.Object>);
    descriptor: (Lscala/Function2;)I
    flags: (0x0009) ACC_PUBLIC, ACC_STATIC
    Code:
      stack=2, locals=1, args_size=1
         0: getstatic     #23                 // Field scala/compat/java8/functionConverterImpls/RichFunction2AsToDoubleBiFunction$.MODULE$:Lscala/compat/java8/functionConverterImpls/RichFunction2AsToDoubleBiFunction$;
         3: aload_0
         4: invokevirtual #31                 // Method scala/compat/java8/functionConverterImpls/RichFunction2AsToDoubleBiFunction$.hashCode$extension:(Lscala/Function2;)I
         7: ireturn
      LocalVariableTable:
        Start  Length  Slot  Name   Signature
            0       8     0 $this   Lscala/Function2;
    Signature: #29                          // <T:Ljava/lang/Object;U:Ljava/lang/Object;>(Lscala/Function2<TT;TU;Ljava/lang/Object;>;)I
    MethodParameters:
      Name                           Flags
      $this                          final

  public static <T extends java.lang.Object, U extends java.lang.Object> java.util.function.ToDoubleBiFunction<T, U> asJava$extension(scala.Function2<T, U, java.lang.Object>);
    descriptor: (Lscala/Function2;)Ljava/util/function/ToDoubleBiFunction;
    flags: (0x0009) ACC_PUBLIC, ACC_STATIC
    Code:
      stack=2, locals=1, args_size=1
         0: getstatic     #23                 // Field scala/compat/java8/functionConverterImpls/RichFunction2AsToDoubleBiFunction$.MODULE$:Lscala/compat/java8/functionConverterImpls/RichFunction2AsToDoubleBiFunction$;
         3: aload_0
         4: invokevirtual #36                 // Method scala/compat/java8/functionConverterImpls/RichFunction2AsToDoubleBiFunction$.asJava$extension:(Lscala/Function2;)Ljava/util/function/ToDoubleBiFunction;
         7: areturn
      LocalVariableTable:
        Start  Length  Slot  Name   Signature
            0       8     0 $this   Lscala/Function2;
    Signature: #34                          // <T:Ljava/lang/Object;U:Ljava/lang/Object;>(Lscala/Function2<TT;TU;Ljava/lang/Object;>;)Ljava/util/function/ToDoubleBiFunction<TT;TU;>;
    MethodParameters:
      Name                           Flags
      $this                          final

  public scala.Function2<T, U, java.lang.Object> scala$compat$java8$functionConverterImpls$RichFunction2AsToDoubleBiFunction$$underlying();
    descriptor: ()Lscala/Function2;
    flags: (0x0001) ACC_PUBLIC
    Code:
      stack=1, locals=1, args_size=1
         0: aload_0
         1: getfield      #40                 // Field scala$compat$java8$functionConverterImpls$RichFunction2AsToDoubleBiFunction$$underlying:Lscala/Function2;
         4: areturn
      LineNumberTable:
        line 636: 0
      LocalVariableTable:
        Start  Length  Slot  Name   Signature
            0       5     0  this   Lscala/compat/java8/functionConverterImpls/RichFunction2AsToDoubleBiFunction;
    Signature: #38                          // ()Lscala/Function2<TT;TU;Ljava/lang/Object;>;

  public java.util.function.ToDoubleBiFunction<T, U> asJava();
    descriptor: ()Ljava/util/function/ToDoubleBiFunction;
    flags: (0x0001) ACC_PUBLIC
    Code:
      stack=2, locals=1, args_size=1
         0: getstatic     #23                 // Field scala/compat/java8/functionConverterImpls/RichFunction2AsToDoubleBiFunction$.MODULE$:Lscala/compat/java8/functionConverterImpls/RichFunction2AsToDoubleBiFunction$;
         3: aload_0
         4: invokevirtual #47                 // Method scala$compat$java8$functionConverterImpls$RichFunction2AsToDoubleBiFunction$$underlying:()Lscala/Function2;
         7: invokevirtual #36                 // Method scala/compat/java8/functionConverterImpls/RichFunction2AsToDoubleBiFunction$.asJava$extension:(Lscala/Function2;)Ljava/util/function/ToDoubleBiFunction;
        10: areturn
      LineNumberTable:
        line 637: 0
      LocalVariableTable:
        Start  Length  Slot  Name   Signature
            0      11     0  this   Lscala/compat/java8/functionConverterImpls/RichFunction2AsToDoubleBiFunction;
    Signature: #45                          // ()Ljava/util/function/ToDoubleBiFunction<TT;TU;>;

  public int hashCode();
    descriptor: ()I
    flags: (0x0001) ACC_PUBLIC
    Code:
      stack=2, locals=1, args_size=1
         0: getstatic     #23                 // Field scala/compat/java8/functionConverterImpls/RichFunction2AsToDoubleBiFunction$.MODULE$:Lscala/compat/java8/functionConverterImpls/RichFunction2AsToDoubleBiFunction$;
         3: aload_0
         4: invokevirtual #47                 // Method scala$compat$java8$functionConverterImpls$RichFunction2AsToDoubleBiFunction$$underlying:()Lscala/Function2;
         7: invokevirtual #31                 // Method scala/compat/java8/functionConverterImpls/RichFunction2AsToDoubleBiFunction$.hashCode$extension:(Lscala/Function2;)I
        10: ireturn
      LineNumberTable:
        line 636: 0
      LocalVariableTable:
        Start  Length  Slot  Name   Signature
            0      11     0  this   Lscala/compat/java8/functionConverterImpls/RichFunction2AsToDoubleBiFunction;

  public boolean equals(java.lang.Object);
    descriptor: (Ljava/lang/Object;)Z
    flags: (0x0001) ACC_PUBLIC
    Code:
      stack=3, locals=2, args_size=2
         0: getstatic     #23                 // Field scala/compat/java8/functionConverterImpls/RichFunction2AsToDoubleBiFunction$.MODULE$:Lscala/compat/java8/functionConverterImpls/RichFunction2AsToDoubleBiFunction$;
         3: aload_0
         4: invokevirtual #47                 // Method scala$compat$java8$functionConverterImpls$RichFunction2AsToDoubleBiFunction$$underlying:()Lscala/Function2;
         7: aload_1
         8: invokevirtual #25                 // Method scala/compat/java8/functionConverterImpls/RichFunction2AsToDoubleBiFunction$.equals$extension:(Lscala/Function2;Ljava/lang/Object;)Z
        11: ireturn
      LineNumberTable:
        line 636: 0
      LocalVariableTable:
        Start  Length  Slot  Name   Signature
            0      12     0  this   Lscala/compat/java8/functionConverterImpls/RichFunction2AsToDoubleBiFunction;
            0      12     1   x$1   Ljava/lang/Object;
    MethodParameters:
      Name                           Flags
      x$1                            final

  public scala.compat.java8.functionConverterImpls.RichFunction2AsToDoubleBiFunction(scala.Function2<T, U, java.lang.Object>);
    descriptor: (Lscala/Function2;)V
    flags: (0x0001) ACC_PUBLIC
    Code:
      stack=2, locals=2, args_size=2
         0: aload_0
         1: aload_1
         2: putfield      #40                 // Field scala$compat$java8$functionConverterImpls$RichFunction2AsToDoubleBiFunction$$underlying:Lscala/Function2;
         5: aload_0
         6: invokespecial #58                 // Method java/lang/Object."<init>":()V
         9: return
      LineNumberTable:
        line 636: 0
      LocalVariableTable:
        Start  Length  Slot  Name   Signature
            0      10     0  this   Lscala/compat/java8/functionConverterImpls/RichFunction2AsToDoubleBiFunction;
            0      10     1 underlying   Lscala/Function2;
    Signature: #54                          // (Lscala/Function2<TT;TU;Ljava/lang/Object;>;)V
    MethodParameters:
      Name                           Flags
      underlying                     final
}
Signature: #3                           // <T:Ljava/lang/Object;U:Ljava/lang/Object;>Ljava/lang/Object;
SourceFile: "FunctionConverters.scala"
RuntimeVisibleAnnotations:
  0: #7(#8=s#9)
    scala.reflect.ScalaSignature(
      bytes="\u0006\u0005u4A!\u0004\b\u0003/!aQ\u0004\u0001C\u0001\u0002\u000b\u0015)\u0019!C\u0005=!I1\u0007\u0001B\u0003\u0002\u0003\u0006Ia\b\u0005\u0006i\u0001!\t!\u000e\u0005\u0006u\u0001!\ta\u000f\u0005\b\u0015\u0002\t\t\u0011\"\u0011L\u0011\u001dy\u0005!!A\u0005BA;qA\u0016\b\u0002\u0002#\u0005qKB\u0004\u000e\u001d\u0005\u0005\t\u0012\u0001-\t\u000bQBA\u0011\u0001/\t\u000buCAQ\u00010\t\u000f%D\u0011\u0011!C\u0003U\"9!\u000fCA\u0001\n\u000b\u0019(!\t*jG\"4UO\\2uS>t\'\'Q:U_\u0012{WO\u00197f\u0005&4UO\\2uS>t\'BA\b\u0011\u0003Y1WO\\2uS>t7i\u001c8wKJ$XM]%na2\u001c(BA\t\u0013\u0003\u0015Q\u0017M^19\u0015\t\u0019B#\u0001\u0004d_6\u0004\u0018\r\u001e\u0006\u0002+\u0005)1oY1mC\u000e\u0001Qc\u0001\r%]M\u0011\u0001!\u0007\t\u00035mi\u0011\u0001F\u0005\u00039Q\u0011a!\u00118z-\u0006d\u0017aV:dC2\fGeY8na\u0006$HE[1wCb\"c-\u001e8di&|gnQ8om\u0016\u0014H/\u001a:J[Bd7\u000f\n*jG\"4UO\\2uS>t\'\'Q:U_\u0012{WO\u00197f\u0005&4UO\\2uS>tG\u0005J;oI\u0016\u0014H._5oOV\tq\u0004E\u0003\u001bA\tj\u0003\'\u0003\u0002\")\tIa)\u001e8di&|gN\r\t\u0003G\u0011b\u0001\u0001B\u0003&\u0001\t\u0007aEA\u0001U#\t9#\u0006\u0005\u0002\u001bQ%\u0011\u0011\u0006\u0006\u0002\b\u001d>$\b.\u001b8h!\tQ2&\u0003\u0002-)\t\u0019\u0011I\\=\u0011\u0005\rrC!B\u0018\u0001\u0005\u00041#!A+\u0011\u0005i\t\u0014B\u0001\u001a\u0015\u0005\u0019!u.\u001e2mK\u0006A6oY1mC\u0012\u001aw.\u001c9bi\u0012R\u0017M^19I\u0019,hn\u0019;j_:\u001cuN\u001c<feR,\'/S7qYN$#+[2i\rVt7\r^5p]J\n5\u000fV8E_V\u0014G.\u001a\"j\rVt7\r^5p]\u0012\"SO\u001c3fe2L\u0018N\\4!\u0003\u0019a\u0014N\\5u}Q\u0011a\u0007\u000f\t\u0005o\u0001\u0011S&D\u0001\u000f\u0011\u0015I4\u00011\u0001 \u0003))h\u000eZ3sYfLgnZ\u0001\u0007CNT\u0015M^1\u0016\u0003q\u0002B!\u0010##[5\taH\u0003\u0002@\u0001\u0006Aa-\u001e8di&|gN\u0003\u0002B\u0005\u0006!Q\u000f^5m\u0015\u0005\u0019\u0015\u0001\u00026bm\u0006L!!\u0012 \u0003%Q{Gi\\;cY\u0016\u0014\u0015NR;oGRLwN\u001c\u0015\u0003\t\u001d\u0003\"A\u0007%\n\u0005%#\"AB5oY&tW-\u0001\u0005iCND7i\u001c3f)\u0005a\u0005C\u0001\u000eN\u0013\tqECA\u0002J]R\fa!Z9vC2\u001cHCA)U!\tQ\"+\u0003\u0002T)\t9!i\\8mK\u0006t\u0007bB+\u0007\u0003\u0003\u0005\rAK\u0001\u0004q\u0012\n\u0014!\t*jG\"4UO\\2uS>t\'\'Q:U_\u0012{WO\u00197f\u0005&4UO\\2uS>t\u0007CA\u001c\t\'\tA\u0011\f\u0005\u0002\u001b5&\u00111\f\u0006\u0002\u0007\u0003:L(+\u001a4\u0015\u0003]\u000b\u0001#Y:KCZ\fG%\u001a=uK:\u001c\u0018n\u001c8\u0016\u0007}\u0013G\r\u0006\u0002aKB!Q\bR1d!\t\u0019#\rB\u0003&\u0015\t\u0007a\u0005\u0005\u0002$I\u0012)qF\u0003b\u0001M!)aM\u0003a\u0001O\u0006)A\u0005\u001e5jgB!q\u0007A1dQ\tQq)\u0001\niCND7i\u001c3fI\u0015DH/\u001a8tS>tWcA6pcR\u00111\n\u001c\u0005\u0006M.\u0001\r!\u001c\t\u0005o\u0001q\u0007\u000f\u0005\u0002$_\u0012)Qe\u0003b\u0001MA\u00111%\u001d\u0003\u0006_-\u0011\rAJ\u0001\u0011KF,\u0018\r\\:%Kb$XM\\:j_:,2\u0001\u001e>})\t)x\u000f\u0006\u0002Rm\"9Q\u000bDA\u0001\u0002\u0004Q\u0003\"\u00024\r\u0001\u0004A\b\u0003B\u001c\u0001sn\u0004\"a\t>\u0005\u000b\u0015b!\u0019\u0001\u0014\u0011\u0005\rbH!B\u0018\r\u0005\u00041\u0003"
    )
  ScalaInlineInfo: length = 0x1D (unknown attribute)
   01 01 00 05 00 34 00 35 01 00 2B 00 2C 05 00 32
   00 33 01 00 30 00 31 01 00 0A 00 25 01
  ScalaSig: length = 0x3 (unknown attribute)
   05 02 00
