Classfile /Users/mw/Projects/slang-braindump/.jar/jar8/assemble/slang-braindump/assemble/content/scala/compat/java8/functionConverterImpls/RichLongUnaryOperatorAsFunction1.class
  Last modified May 29, 2022; size 3047 bytes
  SHA-256 checksum 9a28083390c796cd38381e40737aa321e1589191e0119b8921256e6a4ed2c641
  Compiled from "FunctionConverters.scala"
public final class scala.compat.java8.functionConverterImpls.RichLongUnaryOperatorAsFunction1
  minor version: 0
  major version: 52
  flags: (0x0031) ACC_PUBLIC, ACC_FINAL, ACC_SUPER
  this_class: #2                          // scala/compat/java8/functionConverterImpls/RichLongUnaryOperatorAsFunction1
  super_class: #4                         // java/lang/Object
  interfaces: 0, fields: 1, methods: 8, attributes: 4
Constant pool:
   #1 = Utf8               scala/compat/java8/functionConverterImpls/RichLongUnaryOperatorAsFunction1
   #2 = Class              #1             // scala/compat/java8/functionConverterImpls/RichLongUnaryOperatorAsFunction1
   #3 = Utf8               java/lang/Object
   #4 = Class              #3             // java/lang/Object
   #5 = Utf8               FunctionConverters.scala
   #6 = Utf8               Lscala/reflect/ScalaSignature;
   #7 = Utf8               bytes
   #8 = Utf8               \u0006\u0005y3A!\u0004\b\u0003/!aA\u0004\u0001C\u0001\u0002\u000b\u0015)\u0019!C\u0005;!I\u0001\u0006\u0001B\u0003\u0002\u0003\u0006IA\b\u0005\u0006S\u0001!\tA\u000b\u0005\u0006_\u0001!\t\u0001\r\u0005\bw\u0001\t\t\u0011\"\u0011=\u0011\u001d\u0001\u0005!!A\u0005B\u0005;qA\u0013\b\u0002\u0002#\u00051JB\u0004\u000e\u001d\u0005\u0005\t\u0012\u0001\'\t\u000b%BA\u0011\u0001)\t\u000bECAQ\u0001*\t\u000fYC\u0011\u0011!C\u0003/\"9\u0011\fCA\u0001\n\u000bQ&\u0001\t*jG\"duN\\4V]\u0006\u0014\u0018p\u00149fe\u0006$xN]!t\rVt7\r^5p]FR!a\u0004\t\u0002-\u0019,hn\u0019;j_:\u001cuN\u001c<feR,\'/S7qYNT!!\u0005\n\u0002\u000b)\fg/\u0019\u001d\u000b\u0005M!\u0012AB2p[B\fGOC\u0001\u0016\u0003\u0015\u00198-\u00197b\u0007\u0001\u0019\"\u0001\u0001\r\u0011\u0005eQR\"\u0001\u000b\n\u0005m!\"AB!osZ\u000bG.\u0001,tG\u0006d\u0017\rJ2p[B\fG\u000f\n6bm\u0006DDEZ;oGRLwN\\\"p]Z,\'\u000f^3s\u00136\u0004Hn\u001d\u0013SS\u000eDGj\u001c8h+:\f\'/_(qKJ\fGo\u001c:Bg\u001a+hn\u0019;j_:\fD\u0005J;oI\u0016\u0014H._5oOV\ta\u0004\u0005\u0002 M5\t\u0001E\u0003\u0002\"E\u0005Aa-\u001e8di&|gN\u0003\u0002$I\u0005!Q\u000f^5m\u0015\u0005)\u0013\u0001\u00026bm\u0006L!a\n\u0011\u0003#1{gnZ+oCJLx\n]3sCR|\'/A,tG\u0006d\u0017\rJ2p[B\fG\u000f\n6bm\u0006DDEZ;oGRLwN\\\"p]Z,\'\u000f^3s\u00136\u0004Hn\u001d\u0013SS\u000eDGj\u001c8h+:\f\'/_(qKJ\fGo\u001c:Bg\u001a+hn\u0019;j_:\fD\u0005J;oI\u0016\u0014H._5oO\u0002\na\u0001P5oSRtDCA\u0016.!\ta\u0003!D\u0001\u000f\u0011\u0015q3\u00011\u0001\u001f\u0003))h\u000eZ3sYfLgnZ\u0001\bCN\u001c6-\u00197b+\u0005\t\u0004\u0003B\r3iQJ!a\r\u000b\u0003\u0013\u0019+hn\u0019;j_:\f\u0004CA\r6\u0013\t1DC\u0001\u0003M_:<\u0007F\u0001\u00039!\tI\u0012(\u0003\u0002;)\t1\u0011N\u001c7j]\u0016\f\u0001\u0002[1tQ\u000e{G-\u001a\u000b\u0002{A\u0011\u0011DP\u0005\u0003\u007fQ\u00111!\u00138u\u0003\u0019)\u0017/^1mgR\u0011!)\u0012\t\u00033\rK!\u0001\u0012\u000b\u0003\u000f\t{w\u000e\\3b]\"9aIBA\u0001\u0002\u00049\u0015a\u0001=%cA\u0011\u0011\u0004S\u0005\u0003\u0013R\u00111!\u00118z\u0003\u0001\u0012\u0016n\u00195M_:<WK\\1ss>\u0003XM]1u_J\f5OR;oGRLwN\\\u0019\u0011\u00051B1C\u0001\u0005N!\tIb*\u0003\u0002P)\t1\u0011I\\=SK\u001a$\u0012aS\u0001\u0012CN\u001c6-\u00197bI\u0015DH/\u001a8tS>tGCA\u0019T\u0011\u0015!&\u00021\u0001,\u0003\u0015!C\u000f[5tQ\tQ\u0001(\u0001\niCND7i\u001c3fI\u0015DH/\u001a8tS>tGC\u0001\u001fY\u0011\u0015!6\u00021\u0001,\u0003A)\u0017/^1mg\u0012*\u0007\u0010^3og&|g\u000e\u0006\u0002\\;R\u0011!\t\u0018\u0005\b\r2\t\t\u00111\u0001H\u0011\u0015!F\u00021\u0001,\u0001
   #9 = Utf8               scala$compat$java8$functionConverterImpls$RichLongUnaryOperatorAsFunction1$$underlying
  #10 = Utf8               Ljava/util/function/LongUnaryOperator;
  #11 = Utf8               equals$extension
  #12 = Utf8               (Ljava/util/function/LongUnaryOperator;Ljava/lang/Object;)Z
  #13 = Utf8               $this
  #14 = Utf8               x$1
  #15 = Utf8               scala/compat/java8/functionConverterImpls/RichLongUnaryOperatorAsFunction1$
  #16 = Class              #15            // scala/compat/java8/functionConverterImpls/RichLongUnaryOperatorAsFunction1$
  #17 = Utf8               MODULE$
  #18 = Utf8               Lscala/compat/java8/functionConverterImpls/RichLongUnaryOperatorAsFunction1$;
  #19 = NameAndType        #17:#18        // MODULE$:Lscala/compat/java8/functionConverterImpls/RichLongUnaryOperatorAsFunction1$;
  #20 = Fieldref           #16.#19        // scala/compat/java8/functionConverterImpls/RichLongUnaryOperatorAsFunction1$.MODULE$:Lscala/compat/java8/functionConverterImpls/RichLongUnaryOperatorAsFunction1$;
  #21 = NameAndType        #11:#12        // equals$extension:(Ljava/util/function/LongUnaryOperator;Ljava/lang/Object;)Z
  #22 = Methodref          #16.#21        // scala/compat/java8/functionConverterImpls/RichLongUnaryOperatorAsFunction1$.equals$extension:(Ljava/util/function/LongUnaryOperator;Ljava/lang/Object;)Z
  #23 = Utf8               Ljava/lang/Object;
  #24 = Utf8               hashCode$extension
  #25 = Utf8               (Ljava/util/function/LongUnaryOperator;)I
  #26 = NameAndType        #24:#25        // hashCode$extension:(Ljava/util/function/LongUnaryOperator;)I
  #27 = Methodref          #16.#26        // scala/compat/java8/functionConverterImpls/RichLongUnaryOperatorAsFunction1$.hashCode$extension:(Ljava/util/function/LongUnaryOperator;)I
  #28 = Utf8               asScala$extension
  #29 = Utf8               (Ljava/util/function/LongUnaryOperator;)Lscala/Function1;
  #30 = Utf8               (Ljava/util/function/LongUnaryOperator;)Lscala/Function1<Ljava/lang/Object;Ljava/lang/Object;>;
  #31 = NameAndType        #28:#29        // asScala$extension:(Ljava/util/function/LongUnaryOperator;)Lscala/Function1;
  #32 = Methodref          #16.#31        // scala/compat/java8/functionConverterImpls/RichLongUnaryOperatorAsFunction1$.asScala$extension:(Ljava/util/function/LongUnaryOperator;)Lscala/Function1;
  #33 = Utf8               ()Ljava/util/function/LongUnaryOperator;
  #34 = NameAndType        #9:#10         // scala$compat$java8$functionConverterImpls$RichLongUnaryOperatorAsFunction1$$underlying:Ljava/util/function/LongUnaryOperator;
  #35 = Fieldref           #2.#34         // scala/compat/java8/functionConverterImpls/RichLongUnaryOperatorAsFunction1.scala$compat$java8$functionConverterImpls$RichLongUnaryOperatorAsFunction1$$underlying:Ljava/util/function/LongUnaryOperator;
  #36 = Utf8               this
  #37 = Utf8               Lscala/compat/java8/functionConverterImpls/RichLongUnaryOperatorAsFunction1;
  #38 = Utf8               asScala
  #39 = Utf8               ()Lscala/Function1;
  #40 = Utf8               ()Lscala/Function1<Ljava/lang/Object;Ljava/lang/Object;>;
  #41 = NameAndType        #9:#33         // scala$compat$java8$functionConverterImpls$RichLongUnaryOperatorAsFunction1$$underlying:()Ljava/util/function/LongUnaryOperator;
  #42 = Methodref          #2.#41         // scala/compat/java8/functionConverterImpls/RichLongUnaryOperatorAsFunction1.scala$compat$java8$functionConverterImpls$RichLongUnaryOperatorAsFunction1$$underlying:()Ljava/util/function/LongUnaryOperator;
  #43 = Utf8               hashCode
  #44 = Utf8               ()I
  #45 = Utf8               equals
  #46 = Utf8               (Ljava/lang/Object;)Z
  #47 = Utf8               <init>
  #48 = Utf8               (Ljava/util/function/LongUnaryOperator;)V
  #49 = Utf8               underlying
  #50 = Utf8               ()V
  #51 = NameAndType        #47:#50        // "<init>":()V
  #52 = Methodref          #4.#51         // java/lang/Object."<init>":()V
  #53 = Utf8               Code
  #54 = Utf8               LocalVariableTable
  #55 = Utf8               MethodParameters
  #56 = Utf8               Signature
  #57 = Utf8               LineNumberTable
  #58 = Utf8               SourceFile
  #59 = Utf8               RuntimeVisibleAnnotations
  #60 = Utf8               ScalaInlineInfo
  #61 = Utf8               ScalaSig
{
  private final java.util.function.LongUnaryOperator scala$compat$java8$functionConverterImpls$RichLongUnaryOperatorAsFunction1$$underlying;
    descriptor: Ljava/util/function/LongUnaryOperator;
    flags: (0x0012) ACC_PRIVATE, ACC_FINAL

  public static boolean equals$extension(java.util.function.LongUnaryOperator, java.lang.Object);
    descriptor: (Ljava/util/function/LongUnaryOperator;Ljava/lang/Object;)Z
    flags: (0x0009) ACC_PUBLIC, ACC_STATIC
    Code:
      stack=3, locals=2, args_size=2
         0: getstatic     #20                 // Field scala/compat/java8/functionConverterImpls/RichLongUnaryOperatorAsFunction1$.MODULE$:Lscala/compat/java8/functionConverterImpls/RichLongUnaryOperatorAsFunction1$;
         3: aload_0
         4: aload_1
         5: invokevirtual #22                 // Method scala/compat/java8/functionConverterImpls/RichLongUnaryOperatorAsFunction1$.equals$extension:(Ljava/util/function/LongUnaryOperator;Ljava/lang/Object;)Z
         8: ireturn
      LocalVariableTable:
        Start  Length  Slot  Name   Signature
            0       9     0 $this   Ljava/util/function/LongUnaryOperator;
            0       9     1   x$1   Ljava/lang/Object;
    MethodParameters:
      Name                           Flags
      $this                          final
      x$1                            final

  public static int hashCode$extension(java.util.function.LongUnaryOperator);
    descriptor: (Ljava/util/function/LongUnaryOperator;)I
    flags: (0x0009) ACC_PUBLIC, ACC_STATIC
    Code:
      stack=2, locals=1, args_size=1
         0: getstatic     #20                 // Field scala/compat/java8/functionConverterImpls/RichLongUnaryOperatorAsFunction1$.MODULE$:Lscala/compat/java8/functionConverterImpls/RichLongUnaryOperatorAsFunction1$;
         3: aload_0
         4: invokevirtual #27                 // Method scala/compat/java8/functionConverterImpls/RichLongUnaryOperatorAsFunction1$.hashCode$extension:(Ljava/util/function/LongUnaryOperator;)I
         7: ireturn
      LocalVariableTable:
        Start  Length  Slot  Name   Signature
            0       8     0 $this   Ljava/util/function/LongUnaryOperator;
    MethodParameters:
      Name                           Flags
      $this                          final

  public static scala.Function1<java.lang.Object, java.lang.Object> asScala$extension(java.util.function.LongUnaryOperator);
    descriptor: (Ljava/util/function/LongUnaryOperator;)Lscala/Function1;
    flags: (0x0009) ACC_PUBLIC, ACC_STATIC
    Code:
      stack=2, locals=1, args_size=1
         0: getstatic     #20                 // Field scala/compat/java8/functionConverterImpls/RichLongUnaryOperatorAsFunction1$.MODULE$:Lscala/compat/java8/functionConverterImpls/RichLongUnaryOperatorAsFunction1$;
         3: aload_0
         4: invokevirtual #32                 // Method scala/compat/java8/functionConverterImpls/RichLongUnaryOperatorAsFunction1$.asScala$extension:(Ljava/util/function/LongUnaryOperator;)Lscala/Function1;
         7: areturn
      LocalVariableTable:
        Start  Length  Slot  Name   Signature
            0       8     0 $this   Ljava/util/function/LongUnaryOperator;
    Signature: #30                          // (Ljava/util/function/LongUnaryOperator;)Lscala/Function1<Ljava/lang/Object;Ljava/lang/Object;>;
    MethodParameters:
      Name                           Flags
      $this                          final

  public java.util.function.LongUnaryOperator scala$compat$java8$functionConverterImpls$RichLongUnaryOperatorAsFunction1$$underlying();
    descriptor: ()Ljava/util/function/LongUnaryOperator;
    flags: (0x0001) ACC_PUBLIC
    Code:
      stack=1, locals=1, args_size=1
         0: aload_0
         1: getfield      #35                 // Field scala$compat$java8$functionConverterImpls$RichLongUnaryOperatorAsFunction1$$underlying:Ljava/util/function/LongUnaryOperator;
         4: areturn
      LineNumberTable:
        line 526: 0
      LocalVariableTable:
        Start  Length  Slot  Name   Signature
            0       5     0  this   Lscala/compat/java8/functionConverterImpls/RichLongUnaryOperatorAsFunction1;

  public scala.Function1<java.lang.Object, java.lang.Object> asScala();
    descriptor: ()Lscala/Function1;
    flags: (0x0001) ACC_PUBLIC
    Code:
      stack=2, locals=1, args_size=1
         0: getstatic     #20                 // Field scala/compat/java8/functionConverterImpls/RichLongUnaryOperatorAsFunction1$.MODULE$:Lscala/compat/java8/functionConverterImpls/RichLongUnaryOperatorAsFunction1$;
         3: aload_0
         4: invokevirtual #42                 // Method scala$compat$java8$functionConverterImpls$RichLongUnaryOperatorAsFunction1$$underlying:()Ljava/util/function/LongUnaryOperator;
         7: invokevirtual #32                 // Method scala/compat/java8/functionConverterImpls/RichLongUnaryOperatorAsFunction1$.asScala$extension:(Ljava/util/function/LongUnaryOperator;)Lscala/Function1;
        10: areturn
      LineNumberTable:
        line 527: 0
      LocalVariableTable:
        Start  Length  Slot  Name   Signature
            0      11     0  this   Lscala/compat/java8/functionConverterImpls/RichLongUnaryOperatorAsFunction1;
    Signature: #40                          // ()Lscala/Function1<Ljava/lang/Object;Ljava/lang/Object;>;

  public int hashCode();
    descriptor: ()I
    flags: (0x0001) ACC_PUBLIC
    Code:
      stack=2, locals=1, args_size=1
         0: getstatic     #20                 // Field scala/compat/java8/functionConverterImpls/RichLongUnaryOperatorAsFunction1$.MODULE$:Lscala/compat/java8/functionConverterImpls/RichLongUnaryOperatorAsFunction1$;
         3: aload_0
         4: invokevirtual #42                 // Method scala$compat$java8$functionConverterImpls$RichLongUnaryOperatorAsFunction1$$underlying:()Ljava/util/function/LongUnaryOperator;
         7: invokevirtual #27                 // Method scala/compat/java8/functionConverterImpls/RichLongUnaryOperatorAsFunction1$.hashCode$extension:(Ljava/util/function/LongUnaryOperator;)I
        10: ireturn
      LineNumberTable:
        line 526: 0
      LocalVariableTable:
        Start  Length  Slot  Name   Signature
            0      11     0  this   Lscala/compat/java8/functionConverterImpls/RichLongUnaryOperatorAsFunction1;

  public boolean equals(java.lang.Object);
    descriptor: (Ljava/lang/Object;)Z
    flags: (0x0001) ACC_PUBLIC
    Code:
      stack=3, locals=2, args_size=2
         0: getstatic     #20                 // Field scala/compat/java8/functionConverterImpls/RichLongUnaryOperatorAsFunction1$.MODULE$:Lscala/compat/java8/functionConverterImpls/RichLongUnaryOperatorAsFunction1$;
         3: aload_0
         4: invokevirtual #42                 // Method scala$compat$java8$functionConverterImpls$RichLongUnaryOperatorAsFunction1$$underlying:()Ljava/util/function/LongUnaryOperator;
         7: aload_1
         8: invokevirtual #22                 // Method scala/compat/java8/functionConverterImpls/RichLongUnaryOperatorAsFunction1$.equals$extension:(Ljava/util/function/LongUnaryOperator;Ljava/lang/Object;)Z
        11: ireturn
      LineNumberTable:
        line 526: 0
      LocalVariableTable:
        Start  Length  Slot  Name   Signature
            0      12     0  this   Lscala/compat/java8/functionConverterImpls/RichLongUnaryOperatorAsFunction1;
            0      12     1   x$1   Ljava/lang/Object;
    MethodParameters:
      Name                           Flags
      x$1                            final

  public scala.compat.java8.functionConverterImpls.RichLongUnaryOperatorAsFunction1(java.util.function.LongUnaryOperator);
    descriptor: (Ljava/util/function/LongUnaryOperator;)V
    flags: (0x0001) ACC_PUBLIC
    Code:
      stack=2, locals=2, args_size=2
         0: aload_0
         1: aload_1
         2: putfield      #35                 // Field scala$compat$java8$functionConverterImpls$RichLongUnaryOperatorAsFunction1$$underlying:Ljava/util/function/LongUnaryOperator;
         5: aload_0
         6: invokespecial #52                 // Method java/lang/Object."<init>":()V
         9: return
      LineNumberTable:
        line 526: 0
      LocalVariableTable:
        Start  Length  Slot  Name   Signature
            0      10     0  this   Lscala/compat/java8/functionConverterImpls/RichLongUnaryOperatorAsFunction1;
            0      10     1 underlying   Ljava/util/function/LongUnaryOperator;
    MethodParameters:
      Name                           Flags
      underlying                     final
}
SourceFile: "FunctionConverters.scala"
RuntimeVisibleAnnotations:
  0: #6(#7=s#8)
    scala.reflect.ScalaSignature(
      bytes="\u0006\u0005y3A!\u0004\b\u0003/!aA\u0004\u0001C\u0001\u0002\u000b\u0015)\u0019!C\u0005;!I\u0001\u0006\u0001B\u0003\u0002\u0003\u0006IA\b\u0005\u0006S\u0001!\tA\u000b\u0005\u0006_\u0001!\t\u0001\r\u0005\bw\u0001\t\t\u0011\"\u0011=\u0011\u001d\u0001\u0005!!A\u0005B\u0005;qA\u0013\b\u0002\u0002#\u00051JB\u0004\u000e\u001d\u0005\u0005\t\u0012\u0001\'\t\u000b%BA\u0011\u0001)\t\u000bECAQ\u0001*\t\u000fYC\u0011\u0011!C\u0003/\"9\u0011\fCA\u0001\n\u000bQ&\u0001\t*jG\"duN\\4V]\u0006\u0014\u0018p\u00149fe\u0006$xN]!t\rVt7\r^5p]FR!a\u0004\t\u0002-\u0019,hn\u0019;j_:\u001cuN\u001c<feR,\'/S7qYNT!!\u0005\n\u0002\u000b)\fg/\u0019\u001d\u000b\u0005M!\u0012AB2p[B\fGOC\u0001\u0016\u0003\u0015\u00198-\u00197b\u0007\u0001\u0019\"\u0001\u0001\r\u0011\u0005eQR\"\u0001\u000b\n\u0005m!\"AB!osZ\u000bG.\u0001,tG\u0006d\u0017\rJ2p[B\fG\u000f\n6bm\u0006DDEZ;oGRLwN\\\"p]Z,\'\u000f^3s\u00136\u0004Hn\u001d\u0013SS\u000eDGj\u001c8h+:\f\'/_(qKJ\fGo\u001c:Bg\u001a+hn\u0019;j_:\fD\u0005J;oI\u0016\u0014H._5oOV\ta\u0004\u0005\u0002 M5\t\u0001E\u0003\u0002\"E\u0005Aa-\u001e8di&|gN\u0003\u0002$I\u0005!Q\u000f^5m\u0015\u0005)\u0013\u0001\u00026bm\u0006L!a\n\u0011\u0003#1{gnZ+oCJLx\n]3sCR|\'/A,tG\u0006d\u0017\rJ2p[B\fG\u000f\n6bm\u0006DDEZ;oGRLwN\\\"p]Z,\'\u000f^3s\u00136\u0004Hn\u001d\u0013SS\u000eDGj\u001c8h+:\f\'/_(qKJ\fGo\u001c:Bg\u001a+hn\u0019;j_:\fD\u0005J;oI\u0016\u0014H._5oO\u0002\na\u0001P5oSRtDCA\u0016.!\ta\u0003!D\u0001\u000f\u0011\u0015q3\u00011\u0001\u001f\u0003))h\u000eZ3sYfLgnZ\u0001\bCN\u001c6-\u00197b+\u0005\t\u0004\u0003B\r3iQJ!a\r\u000b\u0003\u0013\u0019+hn\u0019;j_:\f\u0004CA\r6\u0013\t1DC\u0001\u0003M_:<\u0007F\u0001\u00039!\tI\u0012(\u0003\u0002;)\t1\u0011N\u001c7j]\u0016\f\u0001\u0002[1tQ\u000e{G-\u001a\u000b\u0002{A\u0011\u0011DP\u0005\u0003\u007fQ\u00111!\u00138u\u0003\u0019)\u0017/^1mgR\u0011!)\u0012\t\u00033\rK!\u0001\u0012\u000b\u0003\u000f\t{w\u000e\\3b]\"9aIBA\u0001\u0002\u00049\u0015a\u0001=%cA\u0011\u0011\u0004S\u0005\u0003\u0013R\u00111!\u00118z\u0003\u0001\u0012\u0016n\u00195M_:<WK\\1ss>\u0003XM]1u_J\f5OR;oGRLwN\\\u0019\u0011\u00051B1C\u0001\u0005N!\tIb*\u0003\u0002P)\t1\u0011I\\=SK\u001a$\u0012aS\u0001\u0012CN\u001c6-\u00197bI\u0015DH/\u001a8tS>tGCA\u0019T\u0011\u0015!&\u00021\u0001,\u0003\u0015!C\u000f[5tQ\tQ\u0001(\u0001\niCND7i\u001c3fI\u0015DH/\u001a8tS>tGC\u0001\u001fY\u0011\u0015!6\u00021\u0001,\u0003A)\u0017/^1mg\u0012*\u0007\u0010^3og&|g\u000e\u0006\u0002\\;R\u0011!\t\u0018\u0005\b\r2\t\t\u00111\u0001H\u0011\u0015!F\u00021\u0001,\u0001"
    )
  ScalaInlineInfo: length = 0x1D (unknown attribute)
   01 01 00 05 00 2F 00 30 01 00 26 00 27 05 00 2D
   00 2E 01 00 2B 00 2C 01 00 09 00 21 01
  ScalaSig: length = 0x3 (unknown attribute)
   05 02 00
