Classfile /Users/mw/Projects/slang-braindump/.jar/jar8/assemble/slang-braindump/assemble/content/scala/compat/java8/functionConverterImpls/RichBiFunctionAsFunction2.class
  Last modified May 29, 2022; size 3696 bytes
  SHA-256 checksum 2d66f1d1410d87a2b0a4e94286232a09adba90b2be2e5964258a8614bdd34067
  Compiled from "FunctionConverters.scala"
public final class scala.compat.java8.functionConverterImpls.RichBiFunctionAsFunction2<T extends java.lang.Object, U extends java.lang.Object, R extends java.lang.Object> extends java.lang.Object
  minor version: 0
  major version: 52
  flags: (0x0031) ACC_PUBLIC, ACC_FINAL, ACC_SUPER
  this_class: #2                          // scala/compat/java8/functionConverterImpls/RichBiFunctionAsFunction2
  super_class: #5                         // java/lang/Object
  interfaces: 0, fields: 1, methods: 8, attributes: 5
Constant pool:
   #1 = Utf8               scala/compat/java8/functionConverterImpls/RichBiFunctionAsFunction2
   #2 = Class              #1             // scala/compat/java8/functionConverterImpls/RichBiFunctionAsFunction2
   #3 = Utf8               <T:Ljava/lang/Object;U:Ljava/lang/Object;R:Ljava/lang/Object;>Ljava/lang/Object;
   #4 = Utf8               java/lang/Object
   #5 = Class              #4             // java/lang/Object
   #6 = Utf8               FunctionConverters.scala
   #7 = Utf8               Lscala/reflect/ScalaSignature;
   #8 = Utf8               bytes
   #9 = Utf8               \u0006\u0005\u0005\u001da\u0001B\u0007\u000f\u0005]AA\"\b\u0001\u0005\u0002\u0003\u0015)Q1A\u0005\nyA\u0011B\u000f\u0001\u0003\u0006\u0003\u0005\u000b\u0011B\u0010\t\u000bm\u0002A\u0011\u0001\u001f\t\u000b\u0005\u0003A\u0011\u0001\"\t\u000f)\u0003\u0011\u0011!C!\u0017\"9q\nAA\u0001\n\u0003\u0002va\u0002,\u000f\u0003\u0003E\ta\u0016\u0004\b\u001b9\t\t\u0011#\u0001Y\u0011\u0015Y\u0004\u0002\"\u0001]\u0011\u0015i\u0006\u0002\"\u0002_\u0011\u001dY\u0007\"!A\u0005\u00061DqA\u001e\u0005\u0002\u0002\u0013\u0015qOA\rSS\u000eD\')\u001b$v]\u000e$\u0018n\u001c8Bg\u001a+hn\u0019;j_:\u0014$BA\b\u0011\u0003Y1WO\\2uS>t7i\u001c8wKJ$XM]%na2\u001c(BA\t\u0013\u0003\u0015Q\u0017M^19\u0015\t\u0019B#\u0001\u0004d_6\u0004\u0018\r\u001e\u0006\u0002+\u0005)1oY1mC\u000e\u0001Q\u0003\u0002\r,ka\u001a\"\u0001A\r\u0011\u0005iYR\"\u0001\u000b\n\u0005q!\"AB!osZ\u000bG.A(tG\u0006d\u0017\rJ2p[B\fG\u000f\n6bm\u0006DDEZ;oGRLwN\\\"p]Z,\'\u000f^3s\u00136\u0004Hn\u001d\u0013SS\u000eD\')\u001b$v]\u000e$\u0018n\u001c8Bg\u001a+hn\u0019;j_:\u0014D\u0005J;oI\u0016\u0014H._5oOV\tq\u0004E\u0003!O%\"t\'D\u0001\"\u0015\t\u00113%\u0001\u0005gk:\u001cG/[8o\u0015\t!S%\u0001\u0003vi&d\'\"\u0001\u0014\u0002\t)\fg/Y\u0005\u0003Q\u0005\u0012!BQ5Gk:\u001cG/[8o!\tQ3\u0006\u0004\u0001\u0005\u000b1\u0002!\u0019A\u0017\u0003\u0003Q\u000b\"AL\u0019\u0011\u0005iy\u0013B\u0001\u0019\u0015\u0005\u001dqu\u000e\u001e5j]\u001e\u0004\"A\u0007\u001a\n\u0005M\"\"aA!osB\u0011!&\u000e\u0003\u0006m\u0001\u0011\r!\f\u0002\u0002+B\u0011!\u0006\u000f\u0003\u0006s\u0001\u0011\r!\f\u0002\u0002%\u0006\u00016oY1mC\u0012\u001aw.\u001c9bi\u0012R\u0017M^19I\u0019,hn\u0019;j_:\u001cuN\u001c<feR,\'/S7qYN$#+[2i\u0005&4UO\\2uS>t\u0017i\u001d$v]\u000e$\u0018n\u001c83I\u0011*h\u000eZ3sYfLgn\u001a\u0011\u0002\rqJg.\u001b;?)\tit\bE\u0003?\u0001%\"t\'D\u0001\u000f\u0011\u0015\u00015\u00011\u0001 \u0003))h\u000eZ3sYfLgnZ\u0001\bCN\u001c6-\u00197b+\u0005\u0019\u0005#\u0002\u000eESQ:\u0014BA#\u0015\u0005%1UO\\2uS>t\'\u0007\u000b\u0002\u0005\u000fB\u0011!\u0004S\u0005\u0003\u0013R\u0011a!\u001b8mS:,\u0017\u0001\u00035bg\"\u001cu\u000eZ3\u0015\u00031\u0003\"AG\'\n\u00059#\"aA%oi\u00061Q-];bYN$\"!\u0015+\u0011\u0005i\u0011\u0016BA*\u0015\u0005\u001d\u0011un\u001c7fC:Dq!\u0016\u0004\u0002\u0002\u0003\u0007\u0011\'A\u0002yIE\n\u0011DU5dQ\nKg)\u001e8di&|g.Q:Gk:\u001cG/[8oeA\u0011a\bC\n\u0003\u0011e\u0003\"A\u0007.\n\u0005m#\"AB!osJ+g\rF\u0001X\u0003E\t7oU2bY\u0006$S\r\u001f;f]NLwN\\\u000b\u0005?\n$g\r\u0006\u0002aOB)!\u0004R1dKB\u0011!F\u0019\u0003\u0006Y)\u0011\r!\f\t\u0003U\u0011$QA\u000e\u0006C\u00025\u0002\"A\u000b4\u0005\u000beR!\u0019A\u0017\t\u000b!T\u0001\u0019A5\u0002\u000b\u0011\"\b.[:\u0011\u000by\u0002\u0011mY3)\u0005)9\u0015A\u00055bg\"\u001cu\u000eZ3%Kb$XM\\:j_:,B!\\9tkR\u00111J\u001c\u0005\u0006Q.\u0001\ra\u001c\t\u0006}\u0001\u0001(\u000f\u001e\t\u0003UE$Q\u0001L\u0006C\u00025\u0002\"AK:\u0005\u000bYZ!\u0019A\u0017\u0011\u0005)*H!B\u001d\f\u0005\u0004i\u0013\u0001E3rk\u0006d7\u000fJ3yi\u0016t7/[8o+\u0019Ah0!\u0001\u0002\u0006Q\u0011\u0011p\u001f\u000b\u0003#jDq!\u0016\u0007\u0002\u0002\u0003\u0007\u0011\u0007C\u0003i\u0019\u0001\u0007A\u0010\u0005\u0004?\u0001u|\u00181\u0001\t\u0003Uy$Q\u0001\f\u0007C\u00025\u00022AKA\u0001\t\u00151DB1\u0001.!\rQ\u0013Q\u0001\u0003\u0006s1\u0011\r!\f
  #10 = Utf8               scala$compat$java8$functionConverterImpls$RichBiFunctionAsFunction2$$underlying
  #11 = Utf8               Ljava/util/function/BiFunction;
  #12 = Utf8               Ljava/util/function/BiFunction<TT;TU;TR;>;
  #13 = Utf8               equals$extension
  #14 = Utf8               (Ljava/util/function/BiFunction;Ljava/lang/Object;)Z
  #15 = Utf8               <T:Ljava/lang/Object;U:Ljava/lang/Object;R:Ljava/lang/Object;>(Ljava/util/function/BiFunction<TT;TU;TR;>;Ljava/lang/Object;)Z
  #16 = Utf8               $this
  #17 = Utf8               x$1
  #18 = Utf8               scala/compat/java8/functionConverterImpls/RichBiFunctionAsFunction2$
  #19 = Class              #18            // scala/compat/java8/functionConverterImpls/RichBiFunctionAsFunction2$
  #20 = Utf8               MODULE$
  #21 = Utf8               Lscala/compat/java8/functionConverterImpls/RichBiFunctionAsFunction2$;
  #22 = NameAndType        #20:#21        // MODULE$:Lscala/compat/java8/functionConverterImpls/RichBiFunctionAsFunction2$;
  #23 = Fieldref           #19.#22        // scala/compat/java8/functionConverterImpls/RichBiFunctionAsFunction2$.MODULE$:Lscala/compat/java8/functionConverterImpls/RichBiFunctionAsFunction2$;
  #24 = NameAndType        #13:#14        // equals$extension:(Ljava/util/function/BiFunction;Ljava/lang/Object;)Z
  #25 = Methodref          #19.#24        // scala/compat/java8/functionConverterImpls/RichBiFunctionAsFunction2$.equals$extension:(Ljava/util/function/BiFunction;Ljava/lang/Object;)Z
  #26 = Utf8               Ljava/lang/Object;
  #27 = Utf8               hashCode$extension
  #28 = Utf8               (Ljava/util/function/BiFunction;)I
  #29 = Utf8               <T:Ljava/lang/Object;U:Ljava/lang/Object;R:Ljava/lang/Object;>(Ljava/util/function/BiFunction<TT;TU;TR;>;)I
  #30 = NameAndType        #27:#28        // hashCode$extension:(Ljava/util/function/BiFunction;)I
  #31 = Methodref          #19.#30        // scala/compat/java8/functionConverterImpls/RichBiFunctionAsFunction2$.hashCode$extension:(Ljava/util/function/BiFunction;)I
  #32 = Utf8               asScala$extension
  #33 = Utf8               (Ljava/util/function/BiFunction;)Lscala/Function2;
  #34 = Utf8               <T:Ljava/lang/Object;U:Ljava/lang/Object;R:Ljava/lang/Object;>(Ljava/util/function/BiFunction<TT;TU;TR;>;)Lscala/Function2<TT;TU;TR;>;
  #35 = NameAndType        #32:#33        // asScala$extension:(Ljava/util/function/BiFunction;)Lscala/Function2;
  #36 = Methodref          #19.#35        // scala/compat/java8/functionConverterImpls/RichBiFunctionAsFunction2$.asScala$extension:(Ljava/util/function/BiFunction;)Lscala/Function2;
  #37 = Utf8               ()Ljava/util/function/BiFunction;
  #38 = Utf8               ()Ljava/util/function/BiFunction<TT;TU;TR;>;
  #39 = NameAndType        #10:#11        // scala$compat$java8$functionConverterImpls$RichBiFunctionAsFunction2$$underlying:Ljava/util/function/BiFunction;
  #40 = Fieldref           #2.#39         // scala/compat/java8/functionConverterImpls/RichBiFunctionAsFunction2.scala$compat$java8$functionConverterImpls$RichBiFunctionAsFunction2$$underlying:Ljava/util/function/BiFunction;
  #41 = Utf8               this
  #42 = Utf8               Lscala/compat/java8/functionConverterImpls/RichBiFunctionAsFunction2;
  #43 = Utf8               asScala
  #44 = Utf8               ()Lscala/Function2;
  #45 = Utf8               ()Lscala/Function2<TT;TU;TR;>;
  #46 = NameAndType        #10:#37        // scala$compat$java8$functionConverterImpls$RichBiFunctionAsFunction2$$underlying:()Ljava/util/function/BiFunction;
  #47 = Methodref          #2.#46         // scala/compat/java8/functionConverterImpls/RichBiFunctionAsFunction2.scala$compat$java8$functionConverterImpls$RichBiFunctionAsFunction2$$underlying:()Ljava/util/function/BiFunction;
  #48 = Utf8               hashCode
  #49 = Utf8               ()I
  #50 = Utf8               equals
  #51 = Utf8               (Ljava/lang/Object;)Z
  #52 = Utf8               <init>
  #53 = Utf8               (Ljava/util/function/BiFunction;)V
  #54 = Utf8               (Ljava/util/function/BiFunction<TT;TU;TR;>;)V
  #55 = Utf8               underlying
  #56 = Utf8               ()V
  #57 = NameAndType        #52:#56        // "<init>":()V
  #58 = Methodref          #5.#57         // java/lang/Object."<init>":()V
  #59 = Utf8               Signature
  #60 = Utf8               Code
  #61 = Utf8               LocalVariableTable
  #62 = Utf8               MethodParameters
  #63 = Utf8               LineNumberTable
  #64 = Utf8               SourceFile
  #65 = Utf8               RuntimeVisibleAnnotations
  #66 = Utf8               ScalaInlineInfo
  #67 = Utf8               ScalaSig
{
  private final java.util.function.BiFunction<T, U, R> scala$compat$java8$functionConverterImpls$RichBiFunctionAsFunction2$$underlying;
    descriptor: Ljava/util/function/BiFunction;
    flags: (0x0012) ACC_PRIVATE, ACC_FINAL
    Signature: #12                          // Ljava/util/function/BiFunction<TT;TU;TR;>;

  public static <T extends java.lang.Object, U extends java.lang.Object, R extends java.lang.Object> boolean equals$extension(java.util.function.BiFunction<T, U, R>, java.lang.Object);
    descriptor: (Ljava/util/function/BiFunction;Ljava/lang/Object;)Z
    flags: (0x0009) ACC_PUBLIC, ACC_STATIC
    Code:
      stack=3, locals=2, args_size=2
         0: getstatic     #23                 // Field scala/compat/java8/functionConverterImpls/RichBiFunctionAsFunction2$.MODULE$:Lscala/compat/java8/functionConverterImpls/RichBiFunctionAsFunction2$;
         3: aload_0
         4: aload_1
         5: invokevirtual #25                 // Method scala/compat/java8/functionConverterImpls/RichBiFunctionAsFunction2$.equals$extension:(Ljava/util/function/BiFunction;Ljava/lang/Object;)Z
         8: ireturn
      LocalVariableTable:
        Start  Length  Slot  Name   Signature
            0       9     0 $this   Ljava/util/function/BiFunction;
            0       9     1   x$1   Ljava/lang/Object;
    Signature: #15                          // <T:Ljava/lang/Object;U:Ljava/lang/Object;R:Ljava/lang/Object;>(Ljava/util/function/BiFunction<TT;TU;TR;>;Ljava/lang/Object;)Z
    MethodParameters:
      Name                           Flags
      $this                          final
      x$1                            final

  public static <T extends java.lang.Object, U extends java.lang.Object, R extends java.lang.Object> int hashCode$extension(java.util.function.BiFunction<T, U, R>);
    descriptor: (Ljava/util/function/BiFunction;)I
    flags: (0x0009) ACC_PUBLIC, ACC_STATIC
    Code:
      stack=2, locals=1, args_size=1
         0: getstatic     #23                 // Field scala/compat/java8/functionConverterImpls/RichBiFunctionAsFunction2$.MODULE$:Lscala/compat/java8/functionConverterImpls/RichBiFunctionAsFunction2$;
         3: aload_0
         4: invokevirtual #31                 // Method scala/compat/java8/functionConverterImpls/RichBiFunctionAsFunction2$.hashCode$extension:(Ljava/util/function/BiFunction;)I
         7: ireturn
      LocalVariableTable:
        Start  Length  Slot  Name   Signature
            0       8     0 $this   Ljava/util/function/BiFunction;
    Signature: #29                          // <T:Ljava/lang/Object;U:Ljava/lang/Object;R:Ljava/lang/Object;>(Ljava/util/function/BiFunction<TT;TU;TR;>;)I
    MethodParameters:
      Name                           Flags
      $this                          final

  public static <T extends java.lang.Object, U extends java.lang.Object, R extends java.lang.Object> scala.Function2<T, U, R> asScala$extension(java.util.function.BiFunction<T, U, R>);
    descriptor: (Ljava/util/function/BiFunction;)Lscala/Function2;
    flags: (0x0009) ACC_PUBLIC, ACC_STATIC
    Code:
      stack=2, locals=1, args_size=1
         0: getstatic     #23                 // Field scala/compat/java8/functionConverterImpls/RichBiFunctionAsFunction2$.MODULE$:Lscala/compat/java8/functionConverterImpls/RichBiFunctionAsFunction2$;
         3: aload_0
         4: invokevirtual #36                 // Method scala/compat/java8/functionConverterImpls/RichBiFunctionAsFunction2$.asScala$extension:(Ljava/util/function/BiFunction;)Lscala/Function2;
         7: areturn
      LocalVariableTable:
        Start  Length  Slot  Name   Signature
            0       8     0 $this   Ljava/util/function/BiFunction;
    Signature: #34                          // <T:Ljava/lang/Object;U:Ljava/lang/Object;R:Ljava/lang/Object;>(Ljava/util/function/BiFunction<TT;TU;TR;>;)Lscala/Function2<TT;TU;TR;>;
    MethodParameters:
      Name                           Flags
      $this                          final

  public java.util.function.BiFunction<T, U, R> scala$compat$java8$functionConverterImpls$RichBiFunctionAsFunction2$$underlying();
    descriptor: ()Ljava/util/function/BiFunction;
    flags: (0x0001) ACC_PUBLIC
    Code:
      stack=1, locals=1, args_size=1
         0: aload_0
         1: getfield      #40                 // Field scala$compat$java8$functionConverterImpls$RichBiFunctionAsFunction2$$underlying:Ljava/util/function/BiFunction;
         4: areturn
      LineNumberTable:
        line 33: 0
      LocalVariableTable:
        Start  Length  Slot  Name   Signature
            0       5     0  this   Lscala/compat/java8/functionConverterImpls/RichBiFunctionAsFunction2;
    Signature: #38                          // ()Ljava/util/function/BiFunction<TT;TU;TR;>;

  public scala.Function2<T, U, R> asScala();
    descriptor: ()Lscala/Function2;
    flags: (0x0001) ACC_PUBLIC
    Code:
      stack=2, locals=1, args_size=1
         0: getstatic     #23                 // Field scala/compat/java8/functionConverterImpls/RichBiFunctionAsFunction2$.MODULE$:Lscala/compat/java8/functionConverterImpls/RichBiFunctionAsFunction2$;
         3: aload_0
         4: invokevirtual #47                 // Method scala$compat$java8$functionConverterImpls$RichBiFunctionAsFunction2$$underlying:()Ljava/util/function/BiFunction;
         7: invokevirtual #36                 // Method scala/compat/java8/functionConverterImpls/RichBiFunctionAsFunction2$.asScala$extension:(Ljava/util/function/BiFunction;)Lscala/Function2;
        10: areturn
      LineNumberTable:
        line 34: 0
      LocalVariableTable:
        Start  Length  Slot  Name   Signature
            0      11     0  this   Lscala/compat/java8/functionConverterImpls/RichBiFunctionAsFunction2;
    Signature: #45                          // ()Lscala/Function2<TT;TU;TR;>;

  public int hashCode();
    descriptor: ()I
    flags: (0x0001) ACC_PUBLIC
    Code:
      stack=2, locals=1, args_size=1
         0: getstatic     #23                 // Field scala/compat/java8/functionConverterImpls/RichBiFunctionAsFunction2$.MODULE$:Lscala/compat/java8/functionConverterImpls/RichBiFunctionAsFunction2$;
         3: aload_0
         4: invokevirtual #47                 // Method scala$compat$java8$functionConverterImpls$RichBiFunctionAsFunction2$$underlying:()Ljava/util/function/BiFunction;
         7: invokevirtual #31                 // Method scala/compat/java8/functionConverterImpls/RichBiFunctionAsFunction2$.hashCode$extension:(Ljava/util/function/BiFunction;)I
        10: ireturn
      LineNumberTable:
        line 33: 0
      LocalVariableTable:
        Start  Length  Slot  Name   Signature
            0      11     0  this   Lscala/compat/java8/functionConverterImpls/RichBiFunctionAsFunction2;

  public boolean equals(java.lang.Object);
    descriptor: (Ljava/lang/Object;)Z
    flags: (0x0001) ACC_PUBLIC
    Code:
      stack=3, locals=2, args_size=2
         0: getstatic     #23                 // Field scala/compat/java8/functionConverterImpls/RichBiFunctionAsFunction2$.MODULE$:Lscala/compat/java8/functionConverterImpls/RichBiFunctionAsFunction2$;
         3: aload_0
         4: invokevirtual #47                 // Method scala$compat$java8$functionConverterImpls$RichBiFunctionAsFunction2$$underlying:()Ljava/util/function/BiFunction;
         7: aload_1
         8: invokevirtual #25                 // Method scala/compat/java8/functionConverterImpls/RichBiFunctionAsFunction2$.equals$extension:(Ljava/util/function/BiFunction;Ljava/lang/Object;)Z
        11: ireturn
      LineNumberTable:
        line 33: 0
      LocalVariableTable:
        Start  Length  Slot  Name   Signature
            0      12     0  this   Lscala/compat/java8/functionConverterImpls/RichBiFunctionAsFunction2;
            0      12     1   x$1   Ljava/lang/Object;
    MethodParameters:
      Name                           Flags
      x$1                            final

  public scala.compat.java8.functionConverterImpls.RichBiFunctionAsFunction2(java.util.function.BiFunction<T, U, R>);
    descriptor: (Ljava/util/function/BiFunction;)V
    flags: (0x0001) ACC_PUBLIC
    Code:
      stack=2, locals=2, args_size=2
         0: aload_0
         1: aload_1
         2: putfield      #40                 // Field scala$compat$java8$functionConverterImpls$RichBiFunctionAsFunction2$$underlying:Ljava/util/function/BiFunction;
         5: aload_0
         6: invokespecial #58                 // Method java/lang/Object."<init>":()V
         9: return
      LineNumberTable:
        line 33: 0
      LocalVariableTable:
        Start  Length  Slot  Name   Signature
            0      10     0  this   Lscala/compat/java8/functionConverterImpls/RichBiFunctionAsFunction2;
            0      10     1 underlying   Ljava/util/function/BiFunction;
    Signature: #54                          // (Ljava/util/function/BiFunction<TT;TU;TR;>;)V
    MethodParameters:
      Name                           Flags
      underlying                     final
}
Signature: #3                           // <T:Ljava/lang/Object;U:Ljava/lang/Object;R:Ljava/lang/Object;>Ljava/lang/Object;
SourceFile: "FunctionConverters.scala"
RuntimeVisibleAnnotations:
  0: #7(#8=s#9)
    scala.reflect.ScalaSignature(
      bytes="\u0006\u0005\u0005\u001da\u0001B\u0007\u000f\u0005]AA\"\b\u0001\u0005\u0002\u0003\u0015)Q1A\u0005\nyA\u0011B\u000f\u0001\u0003\u0006\u0003\u0005\u000b\u0011B\u0010\t\u000bm\u0002A\u0011\u0001\u001f\t\u000b\u0005\u0003A\u0011\u0001\"\t\u000f)\u0003\u0011\u0011!C!\u0017\"9q\nAA\u0001\n\u0003\u0002va\u0002,\u000f\u0003\u0003E\ta\u0016\u0004\b\u001b9\t\t\u0011#\u0001Y\u0011\u0015Y\u0004\u0002\"\u0001]\u0011\u0015i\u0006\u0002\"\u0002_\u0011\u001dY\u0007\"!A\u0005\u00061DqA\u001e\u0005\u0002\u0002\u0013\u0015qOA\rSS\u000eD\')\u001b$v]\u000e$\u0018n\u001c8Bg\u001a+hn\u0019;j_:\u0014$BA\b\u0011\u0003Y1WO\\2uS>t7i\u001c8wKJ$XM]%na2\u001c(BA\t\u0013\u0003\u0015Q\u0017M^19\u0015\t\u0019B#\u0001\u0004d_6\u0004\u0018\r\u001e\u0006\u0002+\u0005)1oY1mC\u000e\u0001Q\u0003\u0002\r,ka\u001a\"\u0001A\r\u0011\u0005iYR\"\u0001\u000b\n\u0005q!\"AB!osZ\u000bG.A(tG\u0006d\u0017\rJ2p[B\fG\u000f\n6bm\u0006DDEZ;oGRLwN\\\"p]Z,\'\u000f^3s\u00136\u0004Hn\u001d\u0013SS\u000eD\')\u001b$v]\u000e$\u0018n\u001c8Bg\u001a+hn\u0019;j_:\u0014D\u0005J;oI\u0016\u0014H._5oOV\tq\u0004E\u0003!O%\"t\'D\u0001\"\u0015\t\u00113%\u0001\u0005gk:\u001cG/[8o\u0015\t!S%\u0001\u0003vi&d\'\"\u0001\u0014\u0002\t)\fg/Y\u0005\u0003Q\u0005\u0012!BQ5Gk:\u001cG/[8o!\tQ3\u0006\u0004\u0001\u0005\u000b1\u0002!\u0019A\u0017\u0003\u0003Q\u000b\"AL\u0019\u0011\u0005iy\u0013B\u0001\u0019\u0015\u0005\u001dqu\u000e\u001e5j]\u001e\u0004\"A\u0007\u001a\n\u0005M\"\"aA!osB\u0011!&\u000e\u0003\u0006m\u0001\u0011\r!\f\u0002\u0002+B\u0011!\u0006\u000f\u0003\u0006s\u0001\u0011\r!\f\u0002\u0002%\u0006\u00016oY1mC\u0012\u001aw.\u001c9bi\u0012R\u0017M^19I\u0019,hn\u0019;j_:\u001cuN\u001c<feR,\'/S7qYN$#+[2i\u0005&4UO\\2uS>t\u0017i\u001d$v]\u000e$\u0018n\u001c83I\u0011*h\u000eZ3sYfLgn\u001a\u0011\u0002\rqJg.\u001b;?)\tit\bE\u0003?\u0001%\"t\'D\u0001\u000f\u0011\u0015\u00015\u00011\u0001 \u0003))h\u000eZ3sYfLgnZ\u0001\bCN\u001c6-\u00197b+\u0005\u0019\u0005#\u0002\u000eESQ:\u0014BA#\u0015\u0005%1UO\\2uS>t\'\u0007\u000b\u0002\u0005\u000fB\u0011!\u0004S\u0005\u0003\u0013R\u0011a!\u001b8mS:,\u0017\u0001\u00035bg\"\u001cu\u000eZ3\u0015\u00031\u0003\"AG\'\n\u00059#\"aA%oi\u00061Q-];bYN$\"!\u0015+\u0011\u0005i\u0011\u0016BA*\u0015\u0005\u001d\u0011un\u001c7fC:Dq!\u0016\u0004\u0002\u0002\u0003\u0007\u0011\'A\u0002yIE\n\u0011DU5dQ\nKg)\u001e8di&|g.Q:Gk:\u001cG/[8oeA\u0011a\bC\n\u0003\u0011e\u0003\"A\u0007.\n\u0005m#\"AB!osJ+g\rF\u0001X\u0003E\t7oU2bY\u0006$S\r\u001f;f]NLwN\\\u000b\u0005?\n$g\r\u0006\u0002aOB)!\u0004R1dKB\u0011!F\u0019\u0003\u0006Y)\u0011\r!\f\t\u0003U\u0011$QA\u000e\u0006C\u00025\u0002\"A\u000b4\u0005\u000beR!\u0019A\u0017\t\u000b!T\u0001\u0019A5\u0002\u000b\u0011\"\b.[:\u0011\u000by\u0002\u0011mY3)\u0005)9\u0015A\u00055bg\"\u001cu\u000eZ3%Kb$XM\\:j_:,B!\\9tkR\u00111J\u001c\u0005\u0006Q.\u0001\ra\u001c\t\u0006}\u0001\u0001(\u000f\u001e\t\u0003UE$Q\u0001L\u0006C\u00025\u0002\"AK:\u0005\u000bYZ!\u0019A\u0017\u0011\u0005)*H!B\u001d\f\u0005\u0004i\u0013\u0001E3rk\u0006d7\u000fJ3yi\u0016t7/[8o+\u0019Ah0!\u0001\u0002\u0006Q\u0011\u0011p\u001f\u000b\u0003#jDq!\u0016\u0007\u0002\u0002\u0003\u0007\u0011\u0007C\u0003i\u0019\u0001\u0007A\u0010\u0005\u0004?\u0001u|\u00181\u0001\t\u0003Uy$Q\u0001\f\u0007C\u00025\u00022AKA\u0001\t\u00151DB1\u0001.!\rQ\u0013Q\u0001\u0003\u0006s1\u0011\r!\f"
    )
  ScalaInlineInfo: length = 0x1D (unknown attribute)
   01 01 00 05 00 34 00 35 01 00 2B 00 2C 05 00 32
   00 33 01 00 30 00 31 01 00 0A 00 25 01
  ScalaSig: length = 0x3 (unknown attribute)
   05 02 00
