Classfile /Users/mw/Projects/slang-braindump/.jar/jar8/assemble/slang-braindump/assemble/content/scala/compat/java8/functionConverterImpls/RichFunction1AsDoubleConsumer.class
  Last modified May 29, 2022; size 2988 bytes
  SHA-256 checksum 495b04efeb22d82e79f89686c16ae3996e71d5783b0a29519901cfe277b27722
  Compiled from "FunctionConverters.scala"
public final class scala.compat.java8.functionConverterImpls.RichFunction1AsDoubleConsumer
  minor version: 0
  major version: 52
  flags: (0x0031) ACC_PUBLIC, ACC_FINAL, ACC_SUPER
  this_class: #2                          // scala/compat/java8/functionConverterImpls/RichFunction1AsDoubleConsumer
  super_class: #4                         // java/lang/Object
  interfaces: 0, fields: 1, methods: 8, attributes: 4
Constant pool:
   #1 = Utf8               scala/compat/java8/functionConverterImpls/RichFunction1AsDoubleConsumer
   #2 = Class              #1             // scala/compat/java8/functionConverterImpls/RichFunction1AsDoubleConsumer
   #3 = Utf8               java/lang/Object
   #4 = Class              #3             // java/lang/Object
   #5 = Utf8               FunctionConverters.scala
   #6 = Utf8               Lscala/reflect/ScalaSignature;
   #7 = Utf8               bytes
   #8 = Utf8               \u0006\u0005\u00054A!\u0004\b\u0003/!aA\u0004\u0001C\u0001\u0002\u000b\u0015)\u0019!C\u0005;!Iq\u0005\u0001B\u0003\u0002\u0003\u0006IA\b\u0005\u0006Q\u0001!\t!\u000b\u0005\u0006]\u0001!\ta\f\u0005\b}\u0001\t\t\u0011\"\u0011@\u0011\u001d\u0019\u0005!!A\u0005B\u0011;q!\u0014\b\u0002\u0002#\u0005aJB\u0004\u000e\u001d\u0005\u0005\t\u0012A(\t\u000b!BA\u0011A*\t\u000bQCAQA+\t\u000feC\u0011\u0011!C\u00035\"9A\fCA\u0001\n\u000bi&!\b*jG\"4UO\\2uS>t\u0017\'Q:E_V\u0014G.Z\"p]N,X.\u001a:\u000b\u0005=\u0001\u0012A\u00064v]\u000e$\u0018n\u001c8D_:4XM\u001d;fe&k\u0007\u000f\\:\u000b\u0005E\u0011\u0012!\u00026bm\u0006D$BA\n\u0015\u0003\u0019\u0019w.\u001c9bi*\tQ#A\u0003tG\u0006d\u0017m\u0001\u0001\u0014\u0005\u0001A\u0002CA\r\u001b\u001b\u0005!\u0012BA\u000e\u0015\u0005\u0019\te.\u001f,bY\u0006\u00196oY1mC\u0012\u001aw.\u001c9bi\u0012R\u0017M^19I\u0019,hn\u0019;j_:\u001cuN\u001c<feR,\'/S7qYN$#+[2i\rVt7\r^5p]F\n5\u000fR8vE2,7i\u001c8tk6,\'\u000f\n\u0013v]\u0012,\'\u000f\\=j]\u001e,\u0012A\b\t\u00053}\tC%\u0003\u0002!)\tIa)\u001e8di&|g.\r\t\u00033\tJ!a\t\u000b\u0003\r\u0011{WO\u00197f!\tIR%\u0003\u0002\')\t!QK\\5u\u0003Q\u001b8-\u00197bI\r|W\u000e]1uI)\fg/\u0019\u001d%MVt7\r^5p]\u000e{gN^3si\u0016\u0014\u0018*\u001c9mg\u0012\u0012\u0016n\u00195Gk:\u001cG/[8oc\u0005\u001bHi\\;cY\u0016\u001cuN\\:v[\u0016\u0014H\u0005J;oI\u0016\u0014H._5oO\u0002\na\u0001P5oSRtDC\u0001\u0016-!\tY\u0003!D\u0001\u000f\u0011\u0015i3\u00011\u0001\u001f\u0003))h\u000eZ3sYfLgnZ\u0001\u0007CNT\u0015M^1\u0016\u0003A\u0002\"!\r\u001d\u000e\u0003IR!a\r\u001b\u0002\u0011\u0019,hn\u0019;j_:T!!\u000e\u001c\u0002\tU$\u0018\u000e\u001c\u0006\u0002o\u0005!!.\u0019<b\u0013\tI$G\u0001\bE_V\u0014G.Z\"p]N,X.\u001a:)\u0005\u0011Y\u0004CA\r=\u0013\tiDC\u0001\u0004j]2Lg.Z\u0001\tQ\u0006\u001c\bnQ8eKR\t\u0001\t\u0005\u0002\u001a\u0003&\u0011!\t\u0006\u0002\u0004\u0013:$\u0018AB3rk\u0006d7\u000f\u0006\u0002F\u0011B\u0011\u0011DR\u0005\u0003\u000fR\u0011qAQ8pY\u0016\fg\u000eC\u0004J\r\u0005\u0005\t\u0019\u0001&\u0002\u0007a$\u0013\u0007\u0005\u0002\u001a\u0017&\u0011A\n\u0006\u0002\u0004\u0003:L\u0018!\b*jG\"4UO\\2uS>t\u0017\'Q:E_V\u0014G.Z\"p]N,X.\u001a:\u0011\u0005-B1C\u0001\u0005Q!\tI\u0012+\u0003\u0002S)\t1\u0011I\\=SK\u001a$\u0012AT\u0001\u0011CNT\u0015M^1%Kb$XM\\:j_:$\"\u0001\r,\t\u000b]S\u0001\u0019\u0001\u0016\u0002\u000b\u0011\"\b.[:)\u0005)Y\u0014A\u00055bg\"\u001cu\u000eZ3%Kb$XM\\:j_:$\"aP.\t\u000b][\u0001\u0019\u0001\u0016\u0002!\u0015\fX/\u00197tI\u0015DH/\u001a8tS>tGC\u00010a)\t)u\fC\u0004J\u0019\u0005\u0005\t\u0019\u0001&\t\u000b]c\u0001\u0019\u0001\u0016
   #9 = Utf8               scala$compat$java8$functionConverterImpls$RichFunction1AsDoubleConsumer$$underlying
  #10 = Utf8               Lscala/Function1;
  #11 = Utf8               Lscala/Function1<Ljava/lang/Object;Lscala/runtime/BoxedUnit;>;
  #12 = Utf8               equals$extension
  #13 = Utf8               (Lscala/Function1;Ljava/lang/Object;)Z
  #14 = Utf8               $this
  #15 = Utf8               x$1
  #16 = Utf8               scala/compat/java8/functionConverterImpls/RichFunction1AsDoubleConsumer$
  #17 = Class              #16            // scala/compat/java8/functionConverterImpls/RichFunction1AsDoubleConsumer$
  #18 = Utf8               MODULE$
  #19 = Utf8               Lscala/compat/java8/functionConverterImpls/RichFunction1AsDoubleConsumer$;
  #20 = NameAndType        #18:#19        // MODULE$:Lscala/compat/java8/functionConverterImpls/RichFunction1AsDoubleConsumer$;
  #21 = Fieldref           #17.#20        // scala/compat/java8/functionConverterImpls/RichFunction1AsDoubleConsumer$.MODULE$:Lscala/compat/java8/functionConverterImpls/RichFunction1AsDoubleConsumer$;
  #22 = NameAndType        #12:#13        // equals$extension:(Lscala/Function1;Ljava/lang/Object;)Z
  #23 = Methodref          #17.#22        // scala/compat/java8/functionConverterImpls/RichFunction1AsDoubleConsumer$.equals$extension:(Lscala/Function1;Ljava/lang/Object;)Z
  #24 = Utf8               Ljava/lang/Object;
  #25 = Utf8               hashCode$extension
  #26 = Utf8               (Lscala/Function1;)I
  #27 = NameAndType        #25:#26        // hashCode$extension:(Lscala/Function1;)I
  #28 = Methodref          #17.#27        // scala/compat/java8/functionConverterImpls/RichFunction1AsDoubleConsumer$.hashCode$extension:(Lscala/Function1;)I
  #29 = Utf8               asJava$extension
  #30 = Utf8               (Lscala/Function1;)Ljava/util/function/DoubleConsumer;
  #31 = NameAndType        #29:#30        // asJava$extension:(Lscala/Function1;)Ljava/util/function/DoubleConsumer;
  #32 = Methodref          #17.#31        // scala/compat/java8/functionConverterImpls/RichFunction1AsDoubleConsumer$.asJava$extension:(Lscala/Function1;)Ljava/util/function/DoubleConsumer;
  #33 = Utf8               ()Lscala/Function1;
  #34 = Utf8               ()Lscala/Function1<Ljava/lang/Object;Lscala/runtime/BoxedUnit;>;
  #35 = NameAndType        #9:#10         // scala$compat$java8$functionConverterImpls$RichFunction1AsDoubleConsumer$$underlying:Lscala/Function1;
  #36 = Fieldref           #2.#35         // scala/compat/java8/functionConverterImpls/RichFunction1AsDoubleConsumer.scala$compat$java8$functionConverterImpls$RichFunction1AsDoubleConsumer$$underlying:Lscala/Function1;
  #37 = Utf8               this
  #38 = Utf8               Lscala/compat/java8/functionConverterImpls/RichFunction1AsDoubleConsumer;
  #39 = Utf8               asJava
  #40 = Utf8               ()Ljava/util/function/DoubleConsumer;
  #41 = NameAndType        #9:#33         // scala$compat$java8$functionConverterImpls$RichFunction1AsDoubleConsumer$$underlying:()Lscala/Function1;
  #42 = Methodref          #2.#41         // scala/compat/java8/functionConverterImpls/RichFunction1AsDoubleConsumer.scala$compat$java8$functionConverterImpls$RichFunction1AsDoubleConsumer$$underlying:()Lscala/Function1;
  #43 = Utf8               hashCode
  #44 = Utf8               ()I
  #45 = Utf8               equals
  #46 = Utf8               (Ljava/lang/Object;)Z
  #47 = Utf8               <init>
  #48 = Utf8               (Lscala/Function1;)V
  #49 = Utf8               (Lscala/Function1<Ljava/lang/Object;Lscala/runtime/BoxedUnit;>;)V
  #50 = Utf8               underlying
  #51 = Utf8               ()V
  #52 = NameAndType        #47:#51        // "<init>":()V
  #53 = Methodref          #4.#52         // java/lang/Object."<init>":()V
  #54 = Utf8               Signature
  #55 = Utf8               Code
  #56 = Utf8               LocalVariableTable
  #57 = Utf8               MethodParameters
  #58 = Utf8               LineNumberTable
  #59 = Utf8               SourceFile
  #60 = Utf8               RuntimeVisibleAnnotations
  #61 = Utf8               ScalaInlineInfo
  #62 = Utf8               ScalaSig
{
  private final scala.Function1<java.lang.Object, scala.runtime.BoxedUnit> scala$compat$java8$functionConverterImpls$RichFunction1AsDoubleConsumer$$underlying;
    descriptor: Lscala/Function1;
    flags: (0x0012) ACC_PRIVATE, ACC_FINAL
    Signature: #11                          // Lscala/Function1<Ljava/lang/Object;Lscala/runtime/BoxedUnit;>;

  public static boolean equals$extension(scala.Function1, java.lang.Object);
    descriptor: (Lscala/Function1;Ljava/lang/Object;)Z
    flags: (0x0009) ACC_PUBLIC, ACC_STATIC
    Code:
      stack=3, locals=2, args_size=2
         0: getstatic     #21                 // Field scala/compat/java8/functionConverterImpls/RichFunction1AsDoubleConsumer$.MODULE$:Lscala/compat/java8/functionConverterImpls/RichFunction1AsDoubleConsumer$;
         3: aload_0
         4: aload_1
         5: invokevirtual #23                 // Method scala/compat/java8/functionConverterImpls/RichFunction1AsDoubleConsumer$.equals$extension:(Lscala/Function1;Ljava/lang/Object;)Z
         8: ireturn
      LocalVariableTable:
        Start  Length  Slot  Name   Signature
            0       9     0 $this   Lscala/Function1;
            0       9     1   x$1   Ljava/lang/Object;
    MethodParameters:
      Name                           Flags
      $this                          final
      x$1                            final

  public static int hashCode$extension(scala.Function1);
    descriptor: (Lscala/Function1;)I
    flags: (0x0009) ACC_PUBLIC, ACC_STATIC
    Code:
      stack=2, locals=1, args_size=1
         0: getstatic     #21                 // Field scala/compat/java8/functionConverterImpls/RichFunction1AsDoubleConsumer$.MODULE$:Lscala/compat/java8/functionConverterImpls/RichFunction1AsDoubleConsumer$;
         3: aload_0
         4: invokevirtual #28                 // Method scala/compat/java8/functionConverterImpls/RichFunction1AsDoubleConsumer$.hashCode$extension:(Lscala/Function1;)I
         7: ireturn
      LocalVariableTable:
        Start  Length  Slot  Name   Signature
            0       8     0 $this   Lscala/Function1;
    MethodParameters:
      Name                           Flags
      $this                          final

  public static java.util.function.DoubleConsumer asJava$extension(scala.Function1);
    descriptor: (Lscala/Function1;)Ljava/util/function/DoubleConsumer;
    flags: (0x0009) ACC_PUBLIC, ACC_STATIC
    Code:
      stack=2, locals=1, args_size=1
         0: getstatic     #21                 // Field scala/compat/java8/functionConverterImpls/RichFunction1AsDoubleConsumer$.MODULE$:Lscala/compat/java8/functionConverterImpls/RichFunction1AsDoubleConsumer$;
         3: aload_0
         4: invokevirtual #32                 // Method scala/compat/java8/functionConverterImpls/RichFunction1AsDoubleConsumer$.asJava$extension:(Lscala/Function1;)Ljava/util/function/DoubleConsumer;
         7: areturn
      LocalVariableTable:
        Start  Length  Slot  Name   Signature
            0       8     0 $this   Lscala/Function1;
    MethodParameters:
      Name                           Flags
      $this                          final

  public scala.Function1<java.lang.Object, scala.runtime.BoxedUnit> scala$compat$java8$functionConverterImpls$RichFunction1AsDoubleConsumer$$underlying();
    descriptor: ()Lscala/Function1;
    flags: (0x0001) ACC_PUBLIC
    Code:
      stack=1, locals=1, args_size=1
         0: aload_0
         1: getfield      #36                 // Field scala$compat$java8$functionConverterImpls$RichFunction1AsDoubleConsumer$$underlying:Lscala/Function1;
         4: areturn
      LineNumberTable:
        line 143: 0
      LocalVariableTable:
        Start  Length  Slot  Name   Signature
            0       5     0  this   Lscala/compat/java8/functionConverterImpls/RichFunction1AsDoubleConsumer;
    Signature: #34                          // ()Lscala/Function1<Ljava/lang/Object;Lscala/runtime/BoxedUnit;>;

  public java.util.function.DoubleConsumer asJava();
    descriptor: ()Ljava/util/function/DoubleConsumer;
    flags: (0x0001) ACC_PUBLIC
    Code:
      stack=2, locals=1, args_size=1
         0: getstatic     #21                 // Field scala/compat/java8/functionConverterImpls/RichFunction1AsDoubleConsumer$.MODULE$:Lscala/compat/java8/functionConverterImpls/RichFunction1AsDoubleConsumer$;
         3: aload_0
         4: invokevirtual #42                 // Method scala$compat$java8$functionConverterImpls$RichFunction1AsDoubleConsumer$$underlying:()Lscala/Function1;
         7: invokevirtual #32                 // Method scala/compat/java8/functionConverterImpls/RichFunction1AsDoubleConsumer$.asJava$extension:(Lscala/Function1;)Ljava/util/function/DoubleConsumer;
        10: areturn
      LineNumberTable:
        line 144: 0
      LocalVariableTable:
        Start  Length  Slot  Name   Signature
            0      11     0  this   Lscala/compat/java8/functionConverterImpls/RichFunction1AsDoubleConsumer;

  public int hashCode();
    descriptor: ()I
    flags: (0x0001) ACC_PUBLIC
    Code:
      stack=2, locals=1, args_size=1
         0: getstatic     #21                 // Field scala/compat/java8/functionConverterImpls/RichFunction1AsDoubleConsumer$.MODULE$:Lscala/compat/java8/functionConverterImpls/RichFunction1AsDoubleConsumer$;
         3: aload_0
         4: invokevirtual #42                 // Method scala$compat$java8$functionConverterImpls$RichFunction1AsDoubleConsumer$$underlying:()Lscala/Function1;
         7: invokevirtual #28                 // Method scala/compat/java8/functionConverterImpls/RichFunction1AsDoubleConsumer$.hashCode$extension:(Lscala/Function1;)I
        10: ireturn
      LineNumberTable:
        line 143: 0
      LocalVariableTable:
        Start  Length  Slot  Name   Signature
            0      11     0  this   Lscala/compat/java8/functionConverterImpls/RichFunction1AsDoubleConsumer;

  public boolean equals(java.lang.Object);
    descriptor: (Ljava/lang/Object;)Z
    flags: (0x0001) ACC_PUBLIC
    Code:
      stack=3, locals=2, args_size=2
         0: getstatic     #21                 // Field scala/compat/java8/functionConverterImpls/RichFunction1AsDoubleConsumer$.MODULE$:Lscala/compat/java8/functionConverterImpls/RichFunction1AsDoubleConsumer$;
         3: aload_0
         4: invokevirtual #42                 // Method scala$compat$java8$functionConverterImpls$RichFunction1AsDoubleConsumer$$underlying:()Lscala/Function1;
         7: aload_1
         8: invokevirtual #23                 // Method scala/compat/java8/functionConverterImpls/RichFunction1AsDoubleConsumer$.equals$extension:(Lscala/Function1;Ljava/lang/Object;)Z
        11: ireturn
      LineNumberTable:
        line 143: 0
      LocalVariableTable:
        Start  Length  Slot  Name   Signature
            0      12     0  this   Lscala/compat/java8/functionConverterImpls/RichFunction1AsDoubleConsumer;
            0      12     1   x$1   Ljava/lang/Object;
    MethodParameters:
      Name                           Flags
      x$1                            final

  public scala.compat.java8.functionConverterImpls.RichFunction1AsDoubleConsumer(scala.Function1<java.lang.Object, scala.runtime.BoxedUnit>);
    descriptor: (Lscala/Function1;)V
    flags: (0x0001) ACC_PUBLIC
    Code:
      stack=2, locals=2, args_size=2
         0: aload_0
         1: aload_1
         2: putfield      #36                 // Field scala$compat$java8$functionConverterImpls$RichFunction1AsDoubleConsumer$$underlying:Lscala/Function1;
         5: aload_0
         6: invokespecial #53                 // Method java/lang/Object."<init>":()V
         9: return
      LineNumberTable:
        line 143: 0
      LocalVariableTable:
        Start  Length  Slot  Name   Signature
            0      10     0  this   Lscala/compat/java8/functionConverterImpls/RichFunction1AsDoubleConsumer;
            0      10     1 underlying   Lscala/Function1;
    Signature: #49                          // (Lscala/Function1<Ljava/lang/Object;Lscala/runtime/BoxedUnit;>;)V
    MethodParameters:
      Name                           Flags
      underlying                     final
}
SourceFile: "FunctionConverters.scala"
RuntimeVisibleAnnotations:
  0: #6(#7=s#8)
    scala.reflect.ScalaSignature(
      bytes="\u0006\u0005\u00054A!\u0004\b\u0003/!aA\u0004\u0001C\u0001\u0002\u000b\u0015)\u0019!C\u0005;!Iq\u0005\u0001B\u0003\u0002\u0003\u0006IA\b\u0005\u0006Q\u0001!\t!\u000b\u0005\u0006]\u0001!\ta\f\u0005\b}\u0001\t\t\u0011\"\u0011@\u0011\u001d\u0019\u0005!!A\u0005B\u0011;q!\u0014\b\u0002\u0002#\u0005aJB\u0004\u000e\u001d\u0005\u0005\t\u0012A(\t\u000b!BA\u0011A*\t\u000bQCAQA+\t\u000feC\u0011\u0011!C\u00035\"9A\fCA\u0001\n\u000bi&!\b*jG\"4UO\\2uS>t\u0017\'Q:E_V\u0014G.Z\"p]N,X.\u001a:\u000b\u0005=\u0001\u0012A\u00064v]\u000e$\u0018n\u001c8D_:4XM\u001d;fe&k\u0007\u000f\\:\u000b\u0005E\u0011\u0012!\u00026bm\u0006D$BA\n\u0015\u0003\u0019\u0019w.\u001c9bi*\tQ#A\u0003tG\u0006d\u0017m\u0001\u0001\u0014\u0005\u0001A\u0002CA\r\u001b\u001b\u0005!\u0012BA\u000e\u0015\u0005\u0019\te.\u001f,bY\u0006\u00196oY1mC\u0012\u001aw.\u001c9bi\u0012R\u0017M^19I\u0019,hn\u0019;j_:\u001cuN\u001c<feR,\'/S7qYN$#+[2i\rVt7\r^5p]F\n5\u000fR8vE2,7i\u001c8tk6,\'\u000f\n\u0013v]\u0012,\'\u000f\\=j]\u001e,\u0012A\b\t\u00053}\tC%\u0003\u0002!)\tIa)\u001e8di&|g.\r\t\u00033\tJ!a\t\u000b\u0003\r\u0011{WO\u00197f!\tIR%\u0003\u0002\')\t!QK\\5u\u0003Q\u001b8-\u00197bI\r|W\u000e]1uI)\fg/\u0019\u001d%MVt7\r^5p]\u000e{gN^3si\u0016\u0014\u0018*\u001c9mg\u0012\u0012\u0016n\u00195Gk:\u001cG/[8oc\u0005\u001bHi\\;cY\u0016\u001cuN\\:v[\u0016\u0014H\u0005J;oI\u0016\u0014H._5oO\u0002\na\u0001P5oSRtDC\u0001\u0016-!\tY\u0003!D\u0001\u000f\u0011\u0015i3\u00011\u0001\u001f\u0003))h\u000eZ3sYfLgnZ\u0001\u0007CNT\u0015M^1\u0016\u0003A\u0002\"!\r\u001d\u000e\u0003IR!a\r\u001b\u0002\u0011\u0019,hn\u0019;j_:T!!\u000e\u001c\u0002\tU$\u0018\u000e\u001c\u0006\u0002o\u0005!!.\u0019<b\u0013\tI$G\u0001\bE_V\u0014G.Z\"p]N,X.\u001a:)\u0005\u0011Y\u0004CA\r=\u0013\tiDC\u0001\u0004j]2Lg.Z\u0001\tQ\u0006\u001c\bnQ8eKR\t\u0001\t\u0005\u0002\u001a\u0003&\u0011!\t\u0006\u0002\u0004\u0013:$\u0018AB3rk\u0006d7\u000f\u0006\u0002F\u0011B\u0011\u0011DR\u0005\u0003\u000fR\u0011qAQ8pY\u0016\fg\u000eC\u0004J\r\u0005\u0005\t\u0019\u0001&\u0002\u0007a$\u0013\u0007\u0005\u0002\u001a\u0017&\u0011A\n\u0006\u0002\u0004\u0003:L\u0018!\b*jG\"4UO\\2uS>t\u0017\'Q:E_V\u0014G.Z\"p]N,X.\u001a:\u0011\u0005-B1C\u0001\u0005Q!\tI\u0012+\u0003\u0002S)\t1\u0011I\\=SK\u001a$\u0012AT\u0001\u0011CNT\u0015M^1%Kb$XM\\:j_:$\"\u0001\r,\t\u000b]S\u0001\u0019\u0001\u0016\u0002\u000b\u0011\"\b.[:)\u0005)Y\u0014A\u00055bg\"\u001cu\u000eZ3%Kb$XM\\:j_:$\"aP.\t\u000b][\u0001\u0019\u0001\u0016\u0002!\u0015\fX/\u00197tI\u0015DH/\u001a8tS>tGC\u00010a)\t)u\fC\u0004J\u0019\u0005\u0005\t\u0019\u0001&\t\u000b]c\u0001\u0019\u0001\u0016"
    )
  ScalaInlineInfo: length = 0x1D (unknown attribute)
   01 01 00 05 00 2F 00 30 01 00 27 00 28 05 00 2D
   00 2E 01 00 2B 00 2C 01 00 09 00 21 01
  ScalaSig: length = 0x3 (unknown attribute)
   05 02 00
