Classfile /Users/mw/Projects/slang-braindump/.jar/jar8/assemble/slang-braindump/assemble/content/scala/compat/java8/functionConverterImpls/RichDoublePredicateAsFunction1.class
  Last modified May 29, 2022; size 3013 bytes
  SHA-256 checksum 1e5f6e80df0bb0ae293a883359d11b883cffa7a44aec93e27a6fb2765bda07a9
  Compiled from "FunctionConverters.scala"
public final class scala.compat.java8.functionConverterImpls.RichDoublePredicateAsFunction1
  minor version: 0
  major version: 52
  flags: (0x0031) ACC_PUBLIC, ACC_FINAL, ACC_SUPER
  this_class: #2                          // scala/compat/java8/functionConverterImpls/RichDoublePredicateAsFunction1
  super_class: #4                         // java/lang/Object
  interfaces: 0, fields: 1, methods: 8, attributes: 4
Constant pool:
   #1 = Utf8               scala/compat/java8/functionConverterImpls/RichDoublePredicateAsFunction1
   #2 = Class              #1             // scala/compat/java8/functionConverterImpls/RichDoublePredicateAsFunction1
   #3 = Utf8               java/lang/Object
   #4 = Class              #3             // java/lang/Object
   #5 = Utf8               FunctionConverters.scala
   #6 = Utf8               Lscala/reflect/ScalaSignature;
   #7 = Utf8               bytes
   #8 = Utf8               \u0006\u0005y3A!\u0004\b\u0003/!aA\u0004\u0001C\u0001\u0002\u000b\u0015)\u0019!C\u0005;!I\u0001\u0006\u0001B\u0003\u0002\u0003\u0006IA\b\u0005\u0006S\u0001!\tA\u000b\u0005\u0006_\u0001!\t\u0001\r\u0005\b}\u0001\t\t\u0011\"\u0011@\u0011\u001d\u0019\u0005!!A\u0005B\u0011;qA\u0013\b\u0002\u0002#\u00051JB\u0004\u000e\u001d\u0005\u0005\t\u0012\u0001\'\t\u000b%BA\u0011\u0001)\t\u000bECAQ\u0001*\t\u000fYC\u0011\u0011!C\u0003/\"9\u0011\fCA\u0001\n\u000bQ&A\b*jG\"$u.\u001e2mKB\u0013X\rZ5dCR,\u0017i\u001d$v]\u000e$\u0018n\u001c82\u0015\ty\u0001#\u0001\fgk:\u001cG/[8o\u0007>tg/\u001a:uKJLU\u000e\u001d7t\u0015\t\t\"#A\u0003kCZ\f\u0007H\u0003\u0002\u0014)\u000511m\\7qCRT\u0011!F\u0001\u0006g\u000e\fG.Y\u0002\u0001\'\t\u0001\u0001\u0004\u0005\u0002\u001a55\tA#\u0003\u0002\u001c)\t1\u0011I\\=WC2\fAk]2bY\u0006$3m\\7qCR$#.\u0019<bq\u00112WO\\2uS>t7i\u001c8wKJ$XM]%na2\u001cHEU5dQ\u0012{WO\u00197f!J,G-[2bi\u0016\f5OR;oGRLwN\\\u0019%IUtG-\u001a:ms&tw-F\u0001\u001f!\tyb%D\u0001!\u0015\t\t#%\u0001\u0005gk:\u001cG/[8o\u0015\t\u0019C%\u0001\u0003vi&d\'\"A\u0013\u0002\t)\fg/Y\u0005\u0003O\u0001\u0012q\u0002R8vE2,\u0007K]3eS\u000e\fG/Z\u0001Vg\u000e\fG.\u0019\u0013d_6\u0004\u0018\r\u001e\u0013kCZ\f\u0007\b\n4v]\u000e$\u0018n\u001c8D_:4XM\u001d;fe&k\u0007\u000f\\:%%&\u001c\u0007\u000eR8vE2,\u0007K]3eS\u000e\fG/Z!t\rVt7\r^5p]F\"C%\u001e8eKJd\u00170\u001b8hA\u00051A(\u001b8jiz\"\"aK\u0017\u0011\u00051\u0002Q\"\u0001\b\t\u000b9\u001a\u0001\u0019\u0001\u0010\u0002\u0015UtG-\u001a:ms&tw-A\u0004bgN\u001b\u0017\r\\1\u0016\u0003E\u0002B!\u0007\u001a5o%\u00111\u0007\u0006\u0002\n\rVt7\r^5p]F\u0002\"!G\u001b\n\u0005Y\"\"A\u0002#pk\ndW\r\u0005\u0002\u001aq%\u0011\u0011\b\u0006\u0002\b\u0005>|G.Z1oQ\t!1\b\u0005\u0002\u001ay%\u0011Q\b\u0006\u0002\u0007S:d\u0017N\\3\u0002\u0011!\f7\u000f[\"pI\u0016$\u0012\u0001\u0011\t\u00033\u0005K!A\u0011\u000b\u0003\u0007%sG/\u0001\u0004fcV\fGn\u001d\u000b\u0003o\u0015CqA\u0012\u0004\u0002\u0002\u0003\u0007q)A\u0002yIE\u0002\"!\u0007%\n\u0005%#\"aA!os\u0006q\"+[2i\t>,(\r\\3Qe\u0016$\u0017nY1uK\u0006\u001bh)\u001e8di&|g.\r\t\u0003Y!\u0019\"\u0001C\'\u0011\u0005eq\u0015BA(\u0015\u0005\u0019\te.\u001f*fMR\t1*A\tbgN\u001b\u0017\r\\1%Kb$XM\\:j_:$\"!M*\t\u000bQS\u0001\u0019A\u0016\u0002\u000b\u0011\"\b.[:)\u0005)Y\u0014A\u00055bg\"\u001cu\u000eZ3%Kb$XM\\:j_:$\"a\u0010-\t\u000bQ[\u0001\u0019A\u0016\u0002!\u0015\fX/\u00197tI\u0015DH/\u001a8tS>tGCA.^)\t9D\fC\u0004G\u0019\u0005\u0005\t\u0019A$\t\u000bQc\u0001\u0019A\u0016
   #9 = Utf8               scala$compat$java8$functionConverterImpls$RichDoublePredicateAsFunction1$$underlying
  #10 = Utf8               Ljava/util/function/DoublePredicate;
  #11 = Utf8               equals$extension
  #12 = Utf8               (Ljava/util/function/DoublePredicate;Ljava/lang/Object;)Z
  #13 = Utf8               $this
  #14 = Utf8               x$1
  #15 = Utf8               scala/compat/java8/functionConverterImpls/RichDoublePredicateAsFunction1$
  #16 = Class              #15            // scala/compat/java8/functionConverterImpls/RichDoublePredicateAsFunction1$
  #17 = Utf8               MODULE$
  #18 = Utf8               Lscala/compat/java8/functionConverterImpls/RichDoublePredicateAsFunction1$;
  #19 = NameAndType        #17:#18        // MODULE$:Lscala/compat/java8/functionConverterImpls/RichDoublePredicateAsFunction1$;
  #20 = Fieldref           #16.#19        // scala/compat/java8/functionConverterImpls/RichDoublePredicateAsFunction1$.MODULE$:Lscala/compat/java8/functionConverterImpls/RichDoublePredicateAsFunction1$;
  #21 = NameAndType        #11:#12        // equals$extension:(Ljava/util/function/DoublePredicate;Ljava/lang/Object;)Z
  #22 = Methodref          #16.#21        // scala/compat/java8/functionConverterImpls/RichDoublePredicateAsFunction1$.equals$extension:(Ljava/util/function/DoublePredicate;Ljava/lang/Object;)Z
  #23 = Utf8               Ljava/lang/Object;
  #24 = Utf8               hashCode$extension
  #25 = Utf8               (Ljava/util/function/DoublePredicate;)I
  #26 = NameAndType        #24:#25        // hashCode$extension:(Ljava/util/function/DoublePredicate;)I
  #27 = Methodref          #16.#26        // scala/compat/java8/functionConverterImpls/RichDoublePredicateAsFunction1$.hashCode$extension:(Ljava/util/function/DoublePredicate;)I
  #28 = Utf8               asScala$extension
  #29 = Utf8               (Ljava/util/function/DoublePredicate;)Lscala/Function1;
  #30 = Utf8               (Ljava/util/function/DoublePredicate;)Lscala/Function1<Ljava/lang/Object;Ljava/lang/Object;>;
  #31 = NameAndType        #28:#29        // asScala$extension:(Ljava/util/function/DoublePredicate;)Lscala/Function1;
  #32 = Methodref          #16.#31        // scala/compat/java8/functionConverterImpls/RichDoublePredicateAsFunction1$.asScala$extension:(Ljava/util/function/DoublePredicate;)Lscala/Function1;
  #33 = Utf8               ()Ljava/util/function/DoublePredicate;
  #34 = NameAndType        #9:#10         // scala$compat$java8$functionConverterImpls$RichDoublePredicateAsFunction1$$underlying:Ljava/util/function/DoublePredicate;
  #35 = Fieldref           #2.#34         // scala/compat/java8/functionConverterImpls/RichDoublePredicateAsFunction1.scala$compat$java8$functionConverterImpls$RichDoublePredicateAsFunction1$$underlying:Ljava/util/function/DoublePredicate;
  #36 = Utf8               this
  #37 = Utf8               Lscala/compat/java8/functionConverterImpls/RichDoublePredicateAsFunction1;
  #38 = Utf8               asScala
  #39 = Utf8               ()Lscala/Function1;
  #40 = Utf8               ()Lscala/Function1<Ljava/lang/Object;Ljava/lang/Object;>;
  #41 = NameAndType        #9:#33         // scala$compat$java8$functionConverterImpls$RichDoublePredicateAsFunction1$$underlying:()Ljava/util/function/DoublePredicate;
  #42 = Methodref          #2.#41         // scala/compat/java8/functionConverterImpls/RichDoublePredicateAsFunction1.scala$compat$java8$functionConverterImpls$RichDoublePredicateAsFunction1$$underlying:()Ljava/util/function/DoublePredicate;
  #43 = Utf8               hashCode
  #44 = Utf8               ()I
  #45 = Utf8               equals
  #46 = Utf8               (Ljava/lang/Object;)Z
  #47 = Utf8               <init>
  #48 = Utf8               (Ljava/util/function/DoublePredicate;)V
  #49 = Utf8               underlying
  #50 = Utf8               ()V
  #51 = NameAndType        #47:#50        // "<init>":()V
  #52 = Methodref          #4.#51         // java/lang/Object."<init>":()V
  #53 = Utf8               Code
  #54 = Utf8               LocalVariableTable
  #55 = Utf8               MethodParameters
  #56 = Utf8               Signature
  #57 = Utf8               LineNumberTable
  #58 = Utf8               SourceFile
  #59 = Utf8               RuntimeVisibleAnnotations
  #60 = Utf8               ScalaInlineInfo
  #61 = Utf8               ScalaSig
{
  private final java.util.function.DoublePredicate scala$compat$java8$functionConverterImpls$RichDoublePredicateAsFunction1$$underlying;
    descriptor: Ljava/util/function/DoublePredicate;
    flags: (0x0012) ACC_PRIVATE, ACC_FINAL

  public static boolean equals$extension(java.util.function.DoublePredicate, java.lang.Object);
    descriptor: (Ljava/util/function/DoublePredicate;Ljava/lang/Object;)Z
    flags: (0x0009) ACC_PUBLIC, ACC_STATIC
    Code:
      stack=3, locals=2, args_size=2
         0: getstatic     #20                 // Field scala/compat/java8/functionConverterImpls/RichDoublePredicateAsFunction1$.MODULE$:Lscala/compat/java8/functionConverterImpls/RichDoublePredicateAsFunction1$;
         3: aload_0
         4: aload_1
         5: invokevirtual #22                 // Method scala/compat/java8/functionConverterImpls/RichDoublePredicateAsFunction1$.equals$extension:(Ljava/util/function/DoublePredicate;Ljava/lang/Object;)Z
         8: ireturn
      LocalVariableTable:
        Start  Length  Slot  Name   Signature
            0       9     0 $this   Ljava/util/function/DoublePredicate;
            0       9     1   x$1   Ljava/lang/Object;
    MethodParameters:
      Name                           Flags
      $this                          final
      x$1                            final

  public static int hashCode$extension(java.util.function.DoublePredicate);
    descriptor: (Ljava/util/function/DoublePredicate;)I
    flags: (0x0009) ACC_PUBLIC, ACC_STATIC
    Code:
      stack=2, locals=1, args_size=1
         0: getstatic     #20                 // Field scala/compat/java8/functionConverterImpls/RichDoublePredicateAsFunction1$.MODULE$:Lscala/compat/java8/functionConverterImpls/RichDoublePredicateAsFunction1$;
         3: aload_0
         4: invokevirtual #27                 // Method scala/compat/java8/functionConverterImpls/RichDoublePredicateAsFunction1$.hashCode$extension:(Ljava/util/function/DoublePredicate;)I
         7: ireturn
      LocalVariableTable:
        Start  Length  Slot  Name   Signature
            0       8     0 $this   Ljava/util/function/DoublePredicate;
    MethodParameters:
      Name                           Flags
      $this                          final

  public static scala.Function1<java.lang.Object, java.lang.Object> asScala$extension(java.util.function.DoublePredicate);
    descriptor: (Ljava/util/function/DoublePredicate;)Lscala/Function1;
    flags: (0x0009) ACC_PUBLIC, ACC_STATIC
    Code:
      stack=2, locals=1, args_size=1
         0: getstatic     #20                 // Field scala/compat/java8/functionConverterImpls/RichDoublePredicateAsFunction1$.MODULE$:Lscala/compat/java8/functionConverterImpls/RichDoublePredicateAsFunction1$;
         3: aload_0
         4: invokevirtual #32                 // Method scala/compat/java8/functionConverterImpls/RichDoublePredicateAsFunction1$.asScala$extension:(Ljava/util/function/DoublePredicate;)Lscala/Function1;
         7: areturn
      LocalVariableTable:
        Start  Length  Slot  Name   Signature
            0       8     0 $this   Ljava/util/function/DoublePredicate;
    Signature: #30                          // (Ljava/util/function/DoublePredicate;)Lscala/Function1<Ljava/lang/Object;Ljava/lang/Object;>;
    MethodParameters:
      Name                           Flags
      $this                          final

  public java.util.function.DoublePredicate scala$compat$java8$functionConverterImpls$RichDoublePredicateAsFunction1$$underlying();
    descriptor: ()Ljava/util/function/DoublePredicate;
    flags: (0x0001) ACC_PUBLIC
    Code:
      stack=1, locals=1, args_size=1
         0: aload_0
         1: getfield      #35                 // Field scala$compat$java8$functionConverterImpls$RichDoublePredicateAsFunction1$$underlying:Ljava/util/function/DoublePredicate;
         4: areturn
      LineNumberTable:
        line 169: 0
      LocalVariableTable:
        Start  Length  Slot  Name   Signature
            0       5     0  this   Lscala/compat/java8/functionConverterImpls/RichDoublePredicateAsFunction1;

  public scala.Function1<java.lang.Object, java.lang.Object> asScala();
    descriptor: ()Lscala/Function1;
    flags: (0x0001) ACC_PUBLIC
    Code:
      stack=2, locals=1, args_size=1
         0: getstatic     #20                 // Field scala/compat/java8/functionConverterImpls/RichDoublePredicateAsFunction1$.MODULE$:Lscala/compat/java8/functionConverterImpls/RichDoublePredicateAsFunction1$;
         3: aload_0
         4: invokevirtual #42                 // Method scala$compat$java8$functionConverterImpls$RichDoublePredicateAsFunction1$$underlying:()Ljava/util/function/DoublePredicate;
         7: invokevirtual #32                 // Method scala/compat/java8/functionConverterImpls/RichDoublePredicateAsFunction1$.asScala$extension:(Ljava/util/function/DoublePredicate;)Lscala/Function1;
        10: areturn
      LineNumberTable:
        line 170: 0
      LocalVariableTable:
        Start  Length  Slot  Name   Signature
            0      11     0  this   Lscala/compat/java8/functionConverterImpls/RichDoublePredicateAsFunction1;
    Signature: #40                          // ()Lscala/Function1<Ljava/lang/Object;Ljava/lang/Object;>;

  public int hashCode();
    descriptor: ()I
    flags: (0x0001) ACC_PUBLIC
    Code:
      stack=2, locals=1, args_size=1
         0: getstatic     #20                 // Field scala/compat/java8/functionConverterImpls/RichDoublePredicateAsFunction1$.MODULE$:Lscala/compat/java8/functionConverterImpls/RichDoublePredicateAsFunction1$;
         3: aload_0
         4: invokevirtual #42                 // Method scala$compat$java8$functionConverterImpls$RichDoublePredicateAsFunction1$$underlying:()Ljava/util/function/DoublePredicate;
         7: invokevirtual #27                 // Method scala/compat/java8/functionConverterImpls/RichDoublePredicateAsFunction1$.hashCode$extension:(Ljava/util/function/DoublePredicate;)I
        10: ireturn
      LineNumberTable:
        line 169: 0
      LocalVariableTable:
        Start  Length  Slot  Name   Signature
            0      11     0  this   Lscala/compat/java8/functionConverterImpls/RichDoublePredicateAsFunction1;

  public boolean equals(java.lang.Object);
    descriptor: (Ljava/lang/Object;)Z
    flags: (0x0001) ACC_PUBLIC
    Code:
      stack=3, locals=2, args_size=2
         0: getstatic     #20                 // Field scala/compat/java8/functionConverterImpls/RichDoublePredicateAsFunction1$.MODULE$:Lscala/compat/java8/functionConverterImpls/RichDoublePredicateAsFunction1$;
         3: aload_0
         4: invokevirtual #42                 // Method scala$compat$java8$functionConverterImpls$RichDoublePredicateAsFunction1$$underlying:()Ljava/util/function/DoublePredicate;
         7: aload_1
         8: invokevirtual #22                 // Method scala/compat/java8/functionConverterImpls/RichDoublePredicateAsFunction1$.equals$extension:(Ljava/util/function/DoublePredicate;Ljava/lang/Object;)Z
        11: ireturn
      LineNumberTable:
        line 169: 0
      LocalVariableTable:
        Start  Length  Slot  Name   Signature
            0      12     0  this   Lscala/compat/java8/functionConverterImpls/RichDoublePredicateAsFunction1;
            0      12     1   x$1   Ljava/lang/Object;
    MethodParameters:
      Name                           Flags
      x$1                            final

  public scala.compat.java8.functionConverterImpls.RichDoublePredicateAsFunction1(java.util.function.DoublePredicate);
    descriptor: (Ljava/util/function/DoublePredicate;)V
    flags: (0x0001) ACC_PUBLIC
    Code:
      stack=2, locals=2, args_size=2
         0: aload_0
         1: aload_1
         2: putfield      #35                 // Field scala$compat$java8$functionConverterImpls$RichDoublePredicateAsFunction1$$underlying:Ljava/util/function/DoublePredicate;
         5: aload_0
         6: invokespecial #52                 // Method java/lang/Object."<init>":()V
         9: return
      LineNumberTable:
        line 169: 0
      LocalVariableTable:
        Start  Length  Slot  Name   Signature
            0      10     0  this   Lscala/compat/java8/functionConverterImpls/RichDoublePredicateAsFunction1;
            0      10     1 underlying   Ljava/util/function/DoublePredicate;
    MethodParameters:
      Name                           Flags
      underlying                     final
}
SourceFile: "FunctionConverters.scala"
RuntimeVisibleAnnotations:
  0: #6(#7=s#8)
    scala.reflect.ScalaSignature(
      bytes="\u0006\u0005y3A!\u0004\b\u0003/!aA\u0004\u0001C\u0001\u0002\u000b\u0015)\u0019!C\u0005;!I\u0001\u0006\u0001B\u0003\u0002\u0003\u0006IA\b\u0005\u0006S\u0001!\tA\u000b\u0005\u0006_\u0001!\t\u0001\r\u0005\b}\u0001\t\t\u0011\"\u0011@\u0011\u001d\u0019\u0005!!A\u0005B\u0011;qA\u0013\b\u0002\u0002#\u00051JB\u0004\u000e\u001d\u0005\u0005\t\u0012\u0001\'\t\u000b%BA\u0011\u0001)\t\u000bECAQ\u0001*\t\u000fYC\u0011\u0011!C\u0003/\"9\u0011\fCA\u0001\n\u000bQ&A\b*jG\"$u.\u001e2mKB\u0013X\rZ5dCR,\u0017i\u001d$v]\u000e$\u0018n\u001c82\u0015\ty\u0001#\u0001\fgk:\u001cG/[8o\u0007>tg/\u001a:uKJLU\u000e\u001d7t\u0015\t\t\"#A\u0003kCZ\f\u0007H\u0003\u0002\u0014)\u000511m\\7qCRT\u0011!F\u0001\u0006g\u000e\fG.Y\u0002\u0001\'\t\u0001\u0001\u0004\u0005\u0002\u001a55\tA#\u0003\u0002\u001c)\t1\u0011I\\=WC2\fAk]2bY\u0006$3m\\7qCR$#.\u0019<bq\u00112WO\\2uS>t7i\u001c8wKJ$XM]%na2\u001cHEU5dQ\u0012{WO\u00197f!J,G-[2bi\u0016\f5OR;oGRLwN\\\u0019%IUtG-\u001a:ms&tw-F\u0001\u001f!\tyb%D\u0001!\u0015\t\t#%\u0001\u0005gk:\u001cG/[8o\u0015\t\u0019C%\u0001\u0003vi&d\'\"A\u0013\u0002\t)\fg/Y\u0005\u0003O\u0001\u0012q\u0002R8vE2,\u0007K]3eS\u000e\fG/Z\u0001Vg\u000e\fG.\u0019\u0013d_6\u0004\u0018\r\u001e\u0013kCZ\f\u0007\b\n4v]\u000e$\u0018n\u001c8D_:4XM\u001d;fe&k\u0007\u000f\\:%%&\u001c\u0007\u000eR8vE2,\u0007K]3eS\u000e\fG/Z!t\rVt7\r^5p]F\"C%\u001e8eKJd\u00170\u001b8hA\u00051A(\u001b8jiz\"\"aK\u0017\u0011\u00051\u0002Q\"\u0001\b\t\u000b9\u001a\u0001\u0019\u0001\u0010\u0002\u0015UtG-\u001a:ms&tw-A\u0004bgN\u001b\u0017\r\\1\u0016\u0003E\u0002B!\u0007\u001a5o%\u00111\u0007\u0006\u0002\n\rVt7\r^5p]F\u0002\"!G\u001b\n\u0005Y\"\"A\u0002#pk\ndW\r\u0005\u0002\u001aq%\u0011\u0011\b\u0006\u0002\b\u0005>|G.Z1oQ\t!1\b\u0005\u0002\u001ay%\u0011Q\b\u0006\u0002\u0007S:d\u0017N\\3\u0002\u0011!\f7\u000f[\"pI\u0016$\u0012\u0001\u0011\t\u00033\u0005K!A\u0011\u000b\u0003\u0007%sG/\u0001\u0004fcV\fGn\u001d\u000b\u0003o\u0015CqA\u0012\u0004\u0002\u0002\u0003\u0007q)A\u0002yIE\u0002\"!\u0007%\n\u0005%#\"aA!os\u0006q\"+[2i\t>,(\r\\3Qe\u0016$\u0017nY1uK\u0006\u001bh)\u001e8di&|g.\r\t\u0003Y!\u0019\"\u0001C\'\u0011\u0005eq\u0015BA(\u0015\u0005\u0019\te.\u001f*fMR\t1*A\tbgN\u001b\u0017\r\\1%Kb$XM\\:j_:$\"!M*\t\u000bQS\u0001\u0019A\u0016\u0002\u000b\u0011\"\b.[:)\u0005)Y\u0014A\u00055bg\"\u001cu\u000eZ3%Kb$XM\\:j_:$\"a\u0010-\t\u000bQ[\u0001\u0019A\u0016\u0002!\u0015\fX/\u00197tI\u0015DH/\u001a8tS>tGCA.^)\t9D\fC\u0004G\u0019\u0005\u0005\t\u0019A$\t\u000bQc\u0001\u0019A\u0016"
    )
  ScalaInlineInfo: length = 0x1D (unknown attribute)
   01 01 00 05 00 2F 00 30 01 00 26 00 27 05 00 2D
   00 2E 01 00 2B 00 2C 01 00 09 00 21 01
  ScalaSig: length = 0x3 (unknown attribute)
   05 02 00
