Classfile /Users/mw/Projects/slang-braindump/.jar/jar8/assemble/slang-braindump/assemble/content/scala/compat/java8/functionConverterImpls/RichFunctionAsFunction1.class
  Last modified May 29, 2022; size 3474 bytes
  SHA-256 checksum 130d7f3fad545451d91308d75a1264dd53550c1c346c01e426fd4bbf2ba3fac9
  Compiled from "FunctionConverters.scala"
public final class scala.compat.java8.functionConverterImpls.RichFunctionAsFunction1<T extends java.lang.Object, R extends java.lang.Object> extends java.lang.Object
  minor version: 0
  major version: 52
  flags: (0x0031) ACC_PUBLIC, ACC_FINAL, ACC_SUPER
  this_class: #2                          // scala/compat/java8/functionConverterImpls/RichFunctionAsFunction1
  super_class: #5                         // java/lang/Object
  interfaces: 0, fields: 1, methods: 8, attributes: 5
Constant pool:
   #1 = Utf8               scala/compat/java8/functionConverterImpls/RichFunctionAsFunction1
   #2 = Class              #1             // scala/compat/java8/functionConverterImpls/RichFunctionAsFunction1
   #3 = Utf8               <T:Ljava/lang/Object;R:Ljava/lang/Object;>Ljava/lang/Object;
   #4 = Utf8               java/lang/Object
   #5 = Class              #4             // java/lang/Object
   #6 = Utf8               FunctionConverters.scala
   #7 = Utf8               Lscala/reflect/ScalaSignature;
   #8 = Utf8               bytes
   #9 = Utf8               \u0006\u0005i4A!\u0004\b\u0003/!aQ\u0004\u0001C\u0001\u0002\u000b\u0015)\u0019!C\u0005=!Iq\u0007\u0001B\u0003\u0002\u0003\u0006Ia\b\u0005\u0006q\u0001!\t!\u000f\u0005\u0006}\u0001!\ta\u0010\u0005\b\u000f\u0002\t\t\u0011\"\u0011I\u0011\u001da\u0005!!A\u0005B5;qa\u0015\b\u0002\u0002#\u0005AKB\u0004\u000e\u001d\u0005\u0005\t\u0012A+\t\u000baBA\u0011A-\t\u000biCAQA.\t\u000f\u0019D\u0011\u0011!C\u0003O\"9q\u000eCA\u0001\n\u000b\u0001(a\u0006*jG\"4UO\\2uS>t\u0017i\u001d$v]\u000e$\u0018n\u001c82\u0015\ty\u0001#\u0001\fgk:\u001cG/[8o\u0007>tg/\u001a:uKJLU\u000e\u001d7t\u0015\t\t\"#A\u0003kCZ\f\u0007H\u0003\u0002\u0014)\u000511m\\7qCRT\u0011!F\u0001\u0006g\u000e\fG.Y\u0002\u0001+\rA2&N\n\u0003\u0001e\u0001\"AG\u000e\u000e\u0003QI!\u0001\b\u000b\u0003\r\u0005s\u0017PV1m\u00035\u001b8-\u00197bI\r|W\u000e]1uI)\fg/\u0019\u001d%MVt7\r^5p]\u000e{gN^3si\u0016\u0014\u0018*\u001c9mg\u0012\u0012\u0016n\u00195Gk:\u001cG/[8o\u0003N4UO\\2uS>t\u0017\u0007\n\u0013v]\u0012,\'\u000f\\=j]\u001e,\u0012a\b\t\u0005A\u001dJC\'D\u0001\"\u0015\t\u00113%\u0001\u0005gk:\u001cG/[8o\u0015\t!S%\u0001\u0003vi&d\'\"\u0001\u0014\u0002\t)\fg/Y\u0005\u0003Q\u0005\u0012\u0001BR;oGRLwN\u001c\t\u0003U-b\u0001\u0001B\u0003-\u0001\t\u0007QFA\u0001U#\tq\u0013\u0007\u0005\u0002\u001b_%\u0011\u0001\u0007\u0006\u0002\b\u001d>$\b.\u001b8h!\tQ\"\'\u0003\u00024)\t\u0019\u0011I\\=\u0011\u0005)*D!\u0002\u001c\u0001\u0005\u0004i#!\u0001*\u0002\u001dN\u001c\u0017\r\\1%G>l\u0007/\u0019;%U\u00064\u0018\r\u000f\u0013gk:\u001cG/[8o\u0007>tg/\u001a:uKJLU\u000e\u001d7tIIK7\r\u001b$v]\u000e$\u0018n\u001c8Bg\u001a+hn\u0019;j_:\fD\u0005J;oI\u0016\u0014H._5oO\u0002\na\u0001P5oSRtDC\u0001\u001e=!\u0011Y\u0004!\u000b\u001b\u000e\u00039AQ!P\u0002A\u0002}\t!\"\u001e8eKJd\u00170\u001b8h\u0003\u001d\t7oU2bY\u0006,\u0012\u0001\u0011\t\u00055\u0005KC\'\u0003\u0002C)\tIa)\u001e8di&|g.\r\u0015\u0003\t\u0011\u0003\"AG#\n\u0005\u0019#\"AB5oY&tW-\u0001\u0005iCND7i\u001c3f)\u0005I\u0005C\u0001\u000eK\u0013\tYECA\u0002J]R\fa!Z9vC2\u001cHC\u0001(R!\tQr*\u0003\u0002Q)\t9!i\\8mK\u0006t\u0007b\u0002*\u0007\u0003\u0003\u0005\r!M\u0001\u0004q\u0012\n\u0014a\u0006*jG\"4UO\\2uS>t\u0017i\u001d$v]\u000e$\u0018n\u001c82!\tY\u0004b\u0005\u0002\t-B\u0011!dV\u0005\u00031R\u0011a!\u00118z%\u00164G#\u0001+\u0002#\u0005\u001c8kY1mC\u0012*\u0007\u0010^3og&|g.F\u0002]?\u0006$\"!\u00182\u0011\ti\te\f\u0019\t\u0003U}#Q\u0001\f\u0006C\u00025\u0002\"AK1\u0005\u000bYR!\u0019A\u0017\t\u000b\rT\u0001\u0019\u00013\u0002\u000b\u0011\"\b.[:\u0011\tm\u0002a\f\u0019\u0015\u0003\u0015\u0011\u000b!\u0003[1tQ\u000e{G-\u001a\u0013fqR,gn]5p]V\u0019\u0001\u000e\u001c8\u0015\u0005!K\u0007\"B2\f\u0001\u0004Q\u0007\u0003B\u001e\u0001W6\u0004\"A\u000b7\u0005\u000b1Z!\u0019A\u0017\u0011\u0005)rG!\u0002\u001c\f\u0005\u0004i\u0013\u0001E3rk\u0006d7\u000fJ3yi\u0016t7/[8o+\r\tx/\u001f\u000b\u0003eR$\"AT:\t\u000fIc\u0011\u0011!a\u0001c!)1\r\u0004a\u0001kB!1\b\u0001<y!\tQs\u000fB\u0003-\u0019\t\u0007Q\u0006\u0005\u0002+s\u0012)a\u0007\u0004b\u0001[\u0001
  #10 = Utf8               scala$compat$java8$functionConverterImpls$RichFunctionAsFunction1$$underlying
  #11 = Utf8               Ljava/util/function/Function;
  #12 = Utf8               Ljava/util/function/Function<TT;TR;>;
  #13 = Utf8               equals$extension
  #14 = Utf8               (Ljava/util/function/Function;Ljava/lang/Object;)Z
  #15 = Utf8               <T:Ljava/lang/Object;R:Ljava/lang/Object;>(Ljava/util/function/Function<TT;TR;>;Ljava/lang/Object;)Z
  #16 = Utf8               $this
  #17 = Utf8               x$1
  #18 = Utf8               scala/compat/java8/functionConverterImpls/RichFunctionAsFunction1$
  #19 = Class              #18            // scala/compat/java8/functionConverterImpls/RichFunctionAsFunction1$
  #20 = Utf8               MODULE$
  #21 = Utf8               Lscala/compat/java8/functionConverterImpls/RichFunctionAsFunction1$;
  #22 = NameAndType        #20:#21        // MODULE$:Lscala/compat/java8/functionConverterImpls/RichFunctionAsFunction1$;
  #23 = Fieldref           #19.#22        // scala/compat/java8/functionConverterImpls/RichFunctionAsFunction1$.MODULE$:Lscala/compat/java8/functionConverterImpls/RichFunctionAsFunction1$;
  #24 = NameAndType        #13:#14        // equals$extension:(Ljava/util/function/Function;Ljava/lang/Object;)Z
  #25 = Methodref          #19.#24        // scala/compat/java8/functionConverterImpls/RichFunctionAsFunction1$.equals$extension:(Ljava/util/function/Function;Ljava/lang/Object;)Z
  #26 = Utf8               Ljava/lang/Object;
  #27 = Utf8               hashCode$extension
  #28 = Utf8               (Ljava/util/function/Function;)I
  #29 = Utf8               <T:Ljava/lang/Object;R:Ljava/lang/Object;>(Ljava/util/function/Function<TT;TR;>;)I
  #30 = NameAndType        #27:#28        // hashCode$extension:(Ljava/util/function/Function;)I
  #31 = Methodref          #19.#30        // scala/compat/java8/functionConverterImpls/RichFunctionAsFunction1$.hashCode$extension:(Ljava/util/function/Function;)I
  #32 = Utf8               asScala$extension
  #33 = Utf8               (Ljava/util/function/Function;)Lscala/Function1;
  #34 = Utf8               <T:Ljava/lang/Object;R:Ljava/lang/Object;>(Ljava/util/function/Function<TT;TR;>;)Lscala/Function1<TT;TR;>;
  #35 = NameAndType        #32:#33        // asScala$extension:(Ljava/util/function/Function;)Lscala/Function1;
  #36 = Methodref          #19.#35        // scala/compat/java8/functionConverterImpls/RichFunctionAsFunction1$.asScala$extension:(Ljava/util/function/Function;)Lscala/Function1;
  #37 = Utf8               ()Ljava/util/function/Function;
  #38 = Utf8               ()Ljava/util/function/Function<TT;TR;>;
  #39 = NameAndType        #10:#11        // scala$compat$java8$functionConverterImpls$RichFunctionAsFunction1$$underlying:Ljava/util/function/Function;
  #40 = Fieldref           #2.#39         // scala/compat/java8/functionConverterImpls/RichFunctionAsFunction1.scala$compat$java8$functionConverterImpls$RichFunctionAsFunction1$$underlying:Ljava/util/function/Function;
  #41 = Utf8               this
  #42 = Utf8               Lscala/compat/java8/functionConverterImpls/RichFunctionAsFunction1;
  #43 = Utf8               asScala
  #44 = Utf8               ()Lscala/Function1;
  #45 = Utf8               ()Lscala/Function1<TT;TR;>;
  #46 = NameAndType        #10:#37        // scala$compat$java8$functionConverterImpls$RichFunctionAsFunction1$$underlying:()Ljava/util/function/Function;
  #47 = Methodref          #2.#46         // scala/compat/java8/functionConverterImpls/RichFunctionAsFunction1.scala$compat$java8$functionConverterImpls$RichFunctionAsFunction1$$underlying:()Ljava/util/function/Function;
  #48 = Utf8               hashCode
  #49 = Utf8               ()I
  #50 = Utf8               equals
  #51 = Utf8               (Ljava/lang/Object;)Z
  #52 = Utf8               <init>
  #53 = Utf8               (Ljava/util/function/Function;)V
  #54 = Utf8               (Ljava/util/function/Function<TT;TR;>;)V
  #55 = Utf8               underlying
  #56 = Utf8               ()V
  #57 = NameAndType        #52:#56        // "<init>":()V
  #58 = Methodref          #5.#57         // java/lang/Object."<init>":()V
  #59 = Utf8               Signature
  #60 = Utf8               Code
  #61 = Utf8               LocalVariableTable
  #62 = Utf8               MethodParameters
  #63 = Utf8               LineNumberTable
  #64 = Utf8               SourceFile
  #65 = Utf8               RuntimeVisibleAnnotations
  #66 = Utf8               ScalaInlineInfo
  #67 = Utf8               ScalaSig
{
  private final java.util.function.Function<T, R> scala$compat$java8$functionConverterImpls$RichFunctionAsFunction1$$underlying;
    descriptor: Ljava/util/function/Function;
    flags: (0x0012) ACC_PRIVATE, ACC_FINAL
    Signature: #12                          // Ljava/util/function/Function<TT;TR;>;

  public static <T extends java.lang.Object, R extends java.lang.Object> boolean equals$extension(java.util.function.Function<T, R>, java.lang.Object);
    descriptor: (Ljava/util/function/Function;Ljava/lang/Object;)Z
    flags: (0x0009) ACC_PUBLIC, ACC_STATIC
    Code:
      stack=3, locals=2, args_size=2
         0: getstatic     #23                 // Field scala/compat/java8/functionConverterImpls/RichFunctionAsFunction1$.MODULE$:Lscala/compat/java8/functionConverterImpls/RichFunctionAsFunction1$;
         3: aload_0
         4: aload_1
         5: invokevirtual #25                 // Method scala/compat/java8/functionConverterImpls/RichFunctionAsFunction1$.equals$extension:(Ljava/util/function/Function;Ljava/lang/Object;)Z
         8: ireturn
      LocalVariableTable:
        Start  Length  Slot  Name   Signature
            0       9     0 $this   Ljava/util/function/Function;
            0       9     1   x$1   Ljava/lang/Object;
    Signature: #15                          // <T:Ljava/lang/Object;R:Ljava/lang/Object;>(Ljava/util/function/Function<TT;TR;>;Ljava/lang/Object;)Z
    MethodParameters:
      Name                           Flags
      $this                          final
      x$1                            final

  public static <T extends java.lang.Object, R extends java.lang.Object> int hashCode$extension(java.util.function.Function<T, R>);
    descriptor: (Ljava/util/function/Function;)I
    flags: (0x0009) ACC_PUBLIC, ACC_STATIC
    Code:
      stack=2, locals=1, args_size=1
         0: getstatic     #23                 // Field scala/compat/java8/functionConverterImpls/RichFunctionAsFunction1$.MODULE$:Lscala/compat/java8/functionConverterImpls/RichFunctionAsFunction1$;
         3: aload_0
         4: invokevirtual #31                 // Method scala/compat/java8/functionConverterImpls/RichFunctionAsFunction1$.hashCode$extension:(Ljava/util/function/Function;)I
         7: ireturn
      LocalVariableTable:
        Start  Length  Slot  Name   Signature
            0       8     0 $this   Ljava/util/function/Function;
    Signature: #29                          // <T:Ljava/lang/Object;R:Ljava/lang/Object;>(Ljava/util/function/Function<TT;TR;>;)I
    MethodParameters:
      Name                           Flags
      $this                          final

  public static <T extends java.lang.Object, R extends java.lang.Object> scala.Function1<T, R> asScala$extension(java.util.function.Function<T, R>);
    descriptor: (Ljava/util/function/Function;)Lscala/Function1;
    flags: (0x0009) ACC_PUBLIC, ACC_STATIC
    Code:
      stack=2, locals=1, args_size=1
         0: getstatic     #23                 // Field scala/compat/java8/functionConverterImpls/RichFunctionAsFunction1$.MODULE$:Lscala/compat/java8/functionConverterImpls/RichFunctionAsFunction1$;
         3: aload_0
         4: invokevirtual #36                 // Method scala/compat/java8/functionConverterImpls/RichFunctionAsFunction1$.asScala$extension:(Ljava/util/function/Function;)Lscala/Function1;
         7: areturn
      LocalVariableTable:
        Start  Length  Slot  Name   Signature
            0       8     0 $this   Ljava/util/function/Function;
    Signature: #34                          // <T:Ljava/lang/Object;R:Ljava/lang/Object;>(Ljava/util/function/Function<TT;TR;>;)Lscala/Function1<TT;TR;>;
    MethodParameters:
      Name                           Flags
      $this                          final

  public java.util.function.Function<T, R> scala$compat$java8$functionConverterImpls$RichFunctionAsFunction1$$underlying();
    descriptor: ()Ljava/util/function/Function;
    flags: (0x0001) ACC_PUBLIC
    Code:
      stack=1, locals=1, args_size=1
         0: aload_0
         1: getfield      #40                 // Field scala$compat$java8$functionConverterImpls$RichFunctionAsFunction1$$underlying:Ljava/util/function/Function;
         4: areturn
      LineNumberTable:
        line 254: 0
      LocalVariableTable:
        Start  Length  Slot  Name   Signature
            0       5     0  this   Lscala/compat/java8/functionConverterImpls/RichFunctionAsFunction1;
    Signature: #38                          // ()Ljava/util/function/Function<TT;TR;>;

  public scala.Function1<T, R> asScala();
    descriptor: ()Lscala/Function1;
    flags: (0x0001) ACC_PUBLIC
    Code:
      stack=2, locals=1, args_size=1
         0: getstatic     #23                 // Field scala/compat/java8/functionConverterImpls/RichFunctionAsFunction1$.MODULE$:Lscala/compat/java8/functionConverterImpls/RichFunctionAsFunction1$;
         3: aload_0
         4: invokevirtual #47                 // Method scala$compat$java8$functionConverterImpls$RichFunctionAsFunction1$$underlying:()Ljava/util/function/Function;
         7: invokevirtual #36                 // Method scala/compat/java8/functionConverterImpls/RichFunctionAsFunction1$.asScala$extension:(Ljava/util/function/Function;)Lscala/Function1;
        10: areturn
      LineNumberTable:
        line 255: 0
      LocalVariableTable:
        Start  Length  Slot  Name   Signature
            0      11     0  this   Lscala/compat/java8/functionConverterImpls/RichFunctionAsFunction1;
    Signature: #45                          // ()Lscala/Function1<TT;TR;>;

  public int hashCode();
    descriptor: ()I
    flags: (0x0001) ACC_PUBLIC
    Code:
      stack=2, locals=1, args_size=1
         0: getstatic     #23                 // Field scala/compat/java8/functionConverterImpls/RichFunctionAsFunction1$.MODULE$:Lscala/compat/java8/functionConverterImpls/RichFunctionAsFunction1$;
         3: aload_0
         4: invokevirtual #47                 // Method scala$compat$java8$functionConverterImpls$RichFunctionAsFunction1$$underlying:()Ljava/util/function/Function;
         7: invokevirtual #31                 // Method scala/compat/java8/functionConverterImpls/RichFunctionAsFunction1$.hashCode$extension:(Ljava/util/function/Function;)I
        10: ireturn
      LineNumberTable:
        line 254: 0
      LocalVariableTable:
        Start  Length  Slot  Name   Signature
            0      11     0  this   Lscala/compat/java8/functionConverterImpls/RichFunctionAsFunction1;

  public boolean equals(java.lang.Object);
    descriptor: (Ljava/lang/Object;)Z
    flags: (0x0001) ACC_PUBLIC
    Code:
      stack=3, locals=2, args_size=2
         0: getstatic     #23                 // Field scala/compat/java8/functionConverterImpls/RichFunctionAsFunction1$.MODULE$:Lscala/compat/java8/functionConverterImpls/RichFunctionAsFunction1$;
         3: aload_0
         4: invokevirtual #47                 // Method scala$compat$java8$functionConverterImpls$RichFunctionAsFunction1$$underlying:()Ljava/util/function/Function;
         7: aload_1
         8: invokevirtual #25                 // Method scala/compat/java8/functionConverterImpls/RichFunctionAsFunction1$.equals$extension:(Ljava/util/function/Function;Ljava/lang/Object;)Z
        11: ireturn
      LineNumberTable:
        line 254: 0
      LocalVariableTable:
        Start  Length  Slot  Name   Signature
            0      12     0  this   Lscala/compat/java8/functionConverterImpls/RichFunctionAsFunction1;
            0      12     1   x$1   Ljava/lang/Object;
    MethodParameters:
      Name                           Flags
      x$1                            final

  public scala.compat.java8.functionConverterImpls.RichFunctionAsFunction1(java.util.function.Function<T, R>);
    descriptor: (Ljava/util/function/Function;)V
    flags: (0x0001) ACC_PUBLIC
    Code:
      stack=2, locals=2, args_size=2
         0: aload_0
         1: aload_1
         2: putfield      #40                 // Field scala$compat$java8$functionConverterImpls$RichFunctionAsFunction1$$underlying:Ljava/util/function/Function;
         5: aload_0
         6: invokespecial #58                 // Method java/lang/Object."<init>":()V
         9: return
      LineNumberTable:
        line 254: 0
      LocalVariableTable:
        Start  Length  Slot  Name   Signature
            0      10     0  this   Lscala/compat/java8/functionConverterImpls/RichFunctionAsFunction1;
            0      10     1 underlying   Ljava/util/function/Function;
    Signature: #54                          // (Ljava/util/function/Function<TT;TR;>;)V
    MethodParameters:
      Name                           Flags
      underlying                     final
}
Signature: #3                           // <T:Ljava/lang/Object;R:Ljava/lang/Object;>Ljava/lang/Object;
SourceFile: "FunctionConverters.scala"
RuntimeVisibleAnnotations:
  0: #7(#8=s#9)
    scala.reflect.ScalaSignature(
      bytes="\u0006\u0005i4A!\u0004\b\u0003/!aQ\u0004\u0001C\u0001\u0002\u000b\u0015)\u0019!C\u0005=!Iq\u0007\u0001B\u0003\u0002\u0003\u0006Ia\b\u0005\u0006q\u0001!\t!\u000f\u0005\u0006}\u0001!\ta\u0010\u0005\b\u000f\u0002\t\t\u0011\"\u0011I\u0011\u001da\u0005!!A\u0005B5;qa\u0015\b\u0002\u0002#\u0005AKB\u0004\u000e\u001d\u0005\u0005\t\u0012A+\t\u000baBA\u0011A-\t\u000biCAQA.\t\u000f\u0019D\u0011\u0011!C\u0003O\"9q\u000eCA\u0001\n\u000b\u0001(a\u0006*jG\"4UO\\2uS>t\u0017i\u001d$v]\u000e$\u0018n\u001c82\u0015\ty\u0001#\u0001\fgk:\u001cG/[8o\u0007>tg/\u001a:uKJLU\u000e\u001d7t\u0015\t\t\"#A\u0003kCZ\f\u0007H\u0003\u0002\u0014)\u000511m\\7qCRT\u0011!F\u0001\u0006g\u000e\fG.Y\u0002\u0001+\rA2&N\n\u0003\u0001e\u0001\"AG\u000e\u000e\u0003QI!\u0001\b\u000b\u0003\r\u0005s\u0017PV1m\u00035\u001b8-\u00197bI\r|W\u000e]1uI)\fg/\u0019\u001d%MVt7\r^5p]\u000e{gN^3si\u0016\u0014\u0018*\u001c9mg\u0012\u0012\u0016n\u00195Gk:\u001cG/[8o\u0003N4UO\\2uS>t\u0017\u0007\n\u0013v]\u0012,\'\u000f\\=j]\u001e,\u0012a\b\t\u0005A\u001dJC\'D\u0001\"\u0015\t\u00113%\u0001\u0005gk:\u001cG/[8o\u0015\t!S%\u0001\u0003vi&d\'\"\u0001\u0014\u0002\t)\fg/Y\u0005\u0003Q\u0005\u0012\u0001BR;oGRLwN\u001c\t\u0003U-b\u0001\u0001B\u0003-\u0001\t\u0007QFA\u0001U#\tq\u0013\u0007\u0005\u0002\u001b_%\u0011\u0001\u0007\u0006\u0002\b\u001d>$\b.\u001b8h!\tQ\"\'\u0003\u00024)\t\u0019\u0011I\\=\u0011\u0005)*D!\u0002\u001c\u0001\u0005\u0004i#!\u0001*\u0002\u001dN\u001c\u0017\r\\1%G>l\u0007/\u0019;%U\u00064\u0018\r\u000f\u0013gk:\u001cG/[8o\u0007>tg/\u001a:uKJLU\u000e\u001d7tIIK7\r\u001b$v]\u000e$\u0018n\u001c8Bg\u001a+hn\u0019;j_:\fD\u0005J;oI\u0016\u0014H._5oO\u0002\na\u0001P5oSRtDC\u0001\u001e=!\u0011Y\u0004!\u000b\u001b\u000e\u00039AQ!P\u0002A\u0002}\t!\"\u001e8eKJd\u00170\u001b8h\u0003\u001d\t7oU2bY\u0006,\u0012\u0001\u0011\t\u00055\u0005KC\'\u0003\u0002C)\tIa)\u001e8di&|g.\r\u0015\u0003\t\u0011\u0003\"AG#\n\u0005\u0019#\"AB5oY&tW-\u0001\u0005iCND7i\u001c3f)\u0005I\u0005C\u0001\u000eK\u0013\tYECA\u0002J]R\fa!Z9vC2\u001cHC\u0001(R!\tQr*\u0003\u0002Q)\t9!i\\8mK\u0006t\u0007b\u0002*\u0007\u0003\u0003\u0005\r!M\u0001\u0004q\u0012\n\u0014a\u0006*jG\"4UO\\2uS>t\u0017i\u001d$v]\u000e$\u0018n\u001c82!\tY\u0004b\u0005\u0002\t-B\u0011!dV\u0005\u00031R\u0011a!\u00118z%\u00164G#\u0001+\u0002#\u0005\u001c8kY1mC\u0012*\u0007\u0010^3og&|g.F\u0002]?\u0006$\"!\u00182\u0011\ti\te\f\u0019\t\u0003U}#Q\u0001\f\u0006C\u00025\u0002\"AK1\u0005\u000bYR!\u0019A\u0017\t\u000b\rT\u0001\u0019\u00013\u0002\u000b\u0011\"\b.[:\u0011\tm\u0002a\f\u0019\u0015\u0003\u0015\u0011\u000b!\u0003[1tQ\u000e{G-\u001a\u0013fqR,gn]5p]V\u0019\u0001\u000e\u001c8\u0015\u0005!K\u0007\"B2\f\u0001\u0004Q\u0007\u0003B\u001e\u0001W6\u0004\"A\u000b7\u0005\u000b1Z!\u0019A\u0017\u0011\u0005)rG!\u0002\u001c\f\u0005\u0004i\u0013\u0001E3rk\u0006d7\u000fJ3yi\u0016t7/[8o+\r\tx/\u001f\u000b\u0003eR$\"AT:\t\u000fIc\u0011\u0011!a\u0001c!)1\r\u0004a\u0001kB!1\b\u0001<y!\tQs\u000fB\u0003-\u0019\t\u0007Q\u0006\u0005\u0002+s\u0012)a\u0007\u0004b\u0001[\u0001"
    )
  ScalaInlineInfo: length = 0x1D (unknown attribute)
   01 01 00 05 00 34 00 35 01 00 2B 00 2C 05 00 32
   00 33 01 00 30 00 31 01 00 0A 00 25 01
  ScalaSig: length = 0x3 (unknown attribute)
   05 02 00
