Classfile /Users/mw/Projects/slang-braindump/.jar/jar11/assemble/slang-braindump/assemble/content/org/kohsuke/github/authorization/ImmutableAuthorizationProvider.class
  Last modified May 29, 2022; size 2625 bytes
  SHA-256 checksum b0994f4f659c87c4f63fa05bd75171994064d4d40fda31141095b087edd758c0
  Compiled from "ImmutableAuthorizationProvider.java"
public class org.kohsuke.github.authorization.ImmutableAuthorizationProvider implements org.kohsuke.github.authorization.AuthorizationProvider
  minor version: 0
  major version: 52
  flags: (0x0021) ACC_PUBLIC, ACC_SUPER
  this_class: #11                         // org/kohsuke/github/authorization/ImmutableAuthorizationProvider
  super_class: #5                         // java/lang/Object
  interfaces: 1, fields: 1, methods: 7, attributes: 2
Constant pool:
    #1 = Methodref          #5.#61        // java/lang/Object."<init>":()V
    #2 = Fieldref           #11.#62       // org/kohsuke/github/authorization/ImmutableAuthorizationProvider.authorization:Ljava/lang/String;
    #3 = Class              #63           // org/kohsuke/github/authorization/ImmutableAuthorizationProvider$UserProvider
    #4 = String             #64           // token %s
    #5 = Class              #65           // java/lang/Object
    #6 = Methodref          #66.#67       // java/lang/String.format:(Ljava/lang/String;[Ljava/lang/Object;)Ljava/lang/String;
    #7 = Methodref          #3.#68        // org/kohsuke/github/authorization/ImmutableAuthorizationProvider$UserProvider."<init>":(Ljava/lang/String;)V
    #8 = Methodref          #3.#69        // org/kohsuke/github/authorization/ImmutableAuthorizationProvider$UserProvider."<init>":(Ljava/lang/String;Ljava/lang/String;)V
    #9 = String             #70           //
   #10 = Methodref          #11.#71       // org/kohsuke/github/authorization/ImmutableAuthorizationProvider.fromOauthToken:(Ljava/lang/String;Ljava/lang/String;)Lorg/kohsuke/github/authorization/AuthorizationProvider;
   #11 = Class              #72           // org/kohsuke/github/authorization/ImmutableAuthorizationProvider
   #12 = String             #73           // Bearer %s
   #13 = Methodref          #11.#68       // org/kohsuke/github/authorization/ImmutableAuthorizationProvider."<init>":(Ljava/lang/String;)V
   #14 = String             #74           // %s:%s
   #15 = Fieldref           #75.#76       // java/nio/charset/StandardCharsets.UTF_8:Ljava/nio/charset/Charset;
   #16 = Methodref          #77.#78       // java/nio/charset/Charset.name:()Ljava/lang/String;
   #17 = Methodref          #79.#80       // java/util/Base64.getEncoder:()Ljava/util/Base64$Encoder;
   #18 = Methodref          #66.#81       // java/lang/String.getBytes:(Ljava/lang/String;)[B
   #19 = Methodref          #82.#83       // java/util/Base64$Encoder.encodeToString:([B)Ljava/lang/String;
   #20 = String             #84           // Basic %s
   #21 = Class              #85           // java/io/UnsupportedEncodingException
   #22 = Class              #86           // java/lang/IllegalStateException
   #23 = String             #87           // Could not generate encoded authorization
   #24 = Methodref          #22.#88       // java/lang/IllegalStateException."<init>":(Ljava/lang/String;Ljava/lang/Throwable;)V
   #25 = Class              #89           // org/kohsuke/github/authorization/AuthorizationProvider
   #26 = Utf8               UserProvider
   #27 = Utf8               InnerClasses
   #28 = Utf8               authorization
   #29 = Utf8               Ljava/lang/String;
   #30 = Utf8               <init>
   #31 = Utf8               (Ljava/lang/String;)V
   #32 = Utf8               Code
   #33 = Utf8               LineNumberTable
   #34 = Utf8               LocalVariableTable
   #35 = Utf8               this
   #36 = Utf8               Lorg/kohsuke/github/authorization/ImmutableAuthorizationProvider;
   #37 = Utf8               fromOauthToken
   #38 = Utf8               (Ljava/lang/String;)Lorg/kohsuke/github/authorization/AuthorizationProvider;
   #39 = Utf8               oauthAccessToken
   #40 = Utf8               (Ljava/lang/String;Ljava/lang/String;)Lorg/kohsuke/github/authorization/AuthorizationProvider;
   #41 = Utf8               login
   #42 = Utf8               fromAppInstallationToken
   #43 = Utf8               appInstallationToken
   #44 = Utf8               fromJwtToken
   #45 = Utf8               jwtToken
   #46 = Utf8               fromLoginAndPassword
   #47 = Utf8               charsetName
   #48 = Utf8               b64encoded
   #49 = Utf8               encodedAuthorization
   #50 = Utf8               e
   #51 = Utf8               Ljava/io/UnsupportedEncodingException;
   #52 = Utf8               password
   #53 = Utf8               StackMapTable
   #54 = Utf8               Deprecated
   #55 = Utf8               RuntimeVisibleAnnotations
   #56 = Utf8               Ljava/lang/Deprecated;
   #57 = Utf8               getEncodedAuthorization
   #58 = Utf8               ()Ljava/lang/String;
   #59 = Utf8               SourceFile
   #60 = Utf8               ImmutableAuthorizationProvider.java
   #61 = NameAndType        #30:#90       // "<init>":()V
   #62 = NameAndType        #28:#29       // authorization:Ljava/lang/String;
   #63 = Utf8               org/kohsuke/github/authorization/ImmutableAuthorizationProvider$UserProvider
   #64 = Utf8               token %s
   #65 = Utf8               java/lang/Object
   #66 = Class              #91           // java/lang/String
   #67 = NameAndType        #92:#93       // format:(Ljava/lang/String;[Ljava/lang/Object;)Ljava/lang/String;
   #68 = NameAndType        #30:#31       // "<init>":(Ljava/lang/String;)V
   #69 = NameAndType        #30:#94       // "<init>":(Ljava/lang/String;Ljava/lang/String;)V
   #70 = Utf8
   #71 = NameAndType        #37:#40       // fromOauthToken:(Ljava/lang/String;Ljava/lang/String;)Lorg/kohsuke/github/authorization/AuthorizationProvider;
   #72 = Utf8               org/kohsuke/github/authorization/ImmutableAuthorizationProvider
   #73 = Utf8               Bearer %s
   #74 = Utf8               %s:%s
   #75 = Class              #95           // java/nio/charset/StandardCharsets
   #76 = NameAndType        #96:#97       // UTF_8:Ljava/nio/charset/Charset;
   #77 = Class              #98           // java/nio/charset/Charset
   #78 = NameAndType        #99:#58       // name:()Ljava/lang/String;
   #79 = Class              #100          // java/util/Base64
   #80 = NameAndType        #101:#103     // getEncoder:()Ljava/util/Base64$Encoder;
   #81 = NameAndType        #104:#105     // getBytes:(Ljava/lang/String;)[B
   #82 = Class              #106          // java/util/Base64$Encoder
   #83 = NameAndType        #107:#108     // encodeToString:([B)Ljava/lang/String;
   #84 = Utf8               Basic %s
   #85 = Utf8               java/io/UnsupportedEncodingException
   #86 = Utf8               java/lang/IllegalStateException
   #87 = Utf8               Could not generate encoded authorization
   #88 = NameAndType        #30:#109      // "<init>":(Ljava/lang/String;Ljava/lang/Throwable;)V
   #89 = Utf8               org/kohsuke/github/authorization/AuthorizationProvider
   #90 = Utf8               ()V
   #91 = Utf8               java/lang/String
   #92 = Utf8               format
   #93 = Utf8               (Ljava/lang/String;[Ljava/lang/Object;)Ljava/lang/String;
   #94 = Utf8               (Ljava/lang/String;Ljava/lang/String;)V
   #95 = Utf8               java/nio/charset/StandardCharsets
   #96 = Utf8               UTF_8
   #97 = Utf8               Ljava/nio/charset/Charset;
   #98 = Utf8               java/nio/charset/Charset
   #99 = Utf8               name
  #100 = Utf8               java/util/Base64
  #101 = Utf8               getEncoder
  #102 = Utf8               Encoder
  #103 = Utf8               ()Ljava/util/Base64$Encoder;
  #104 = Utf8               getBytes
  #105 = Utf8               (Ljava/lang/String;)[B
  #106 = Utf8               java/util/Base64$Encoder
  #107 = Utf8               encodeToString
  #108 = Utf8               ([B)Ljava/lang/String;
  #109 = Utf8               (Ljava/lang/String;Ljava/lang/Throwable;)V
{
  private final java.lang.String authorization;
    descriptor: Ljava/lang/String;
    flags: (0x0012) ACC_PRIVATE, ACC_FINAL

  public org.kohsuke.github.authorization.ImmutableAuthorizationProvider(java.lang.String);
    descriptor: (Ljava/lang/String;)V
    flags: (0x0001) ACC_PUBLIC
    Code:
      stack=2, locals=2, args_size=2
         0: aload_0
         1: invokespecial #1                  // Method java/lang/Object."<init>":()V
         4: aload_0
         5: aload_1
         6: putfield      #2                  // Field authorization:Ljava/lang/String;
         9: return
      LineNumberTable:
        line 16: 0
        line 17: 4
        line 18: 9
      LocalVariableTable:
        Start  Length  Slot  Name   Signature
            0      10     0  this   Lorg/kohsuke/github/authorization/ImmutableAuthorizationProvider;
            0      10     1 authorization   Ljava/lang/String;

  public static org.kohsuke.github.authorization.AuthorizationProvider fromOauthToken(java.lang.String);
    descriptor: (Ljava/lang/String;)Lorg/kohsuke/github/authorization/AuthorizationProvider;
    flags: (0x0009) ACC_PUBLIC, ACC_STATIC
    Code:
      stack=7, locals=1, args_size=1
         0: new           #3                  // class org/kohsuke/github/authorization/ImmutableAuthorizationProvider$UserProvider
         3: dup
         4: ldc           #4                  // String token %s
         6: iconst_1
         7: anewarray     #5                  // class java/lang/Object
        10: dup
        11: iconst_0
        12: aload_0
        13: aastore
        14: invokestatic  #6                  // Method java/lang/String.format:(Ljava/lang/String;[Ljava/lang/Object;)Ljava/lang/String;
        17: invokespecial #7                  // Method org/kohsuke/github/authorization/ImmutableAuthorizationProvider$UserProvider."<init>":(Ljava/lang/String;)V
        20: areturn
      LineNumberTable:
        line 29: 0
      LocalVariableTable:
        Start  Length  Slot  Name   Signature
            0      21     0 oauthAccessToken   Ljava/lang/String;

  public static org.kohsuke.github.authorization.AuthorizationProvider fromOauthToken(java.lang.String, java.lang.String);
    descriptor: (Ljava/lang/String;Ljava/lang/String;)Lorg/kohsuke/github/authorization/AuthorizationProvider;
    flags: (0x0009) ACC_PUBLIC, ACC_STATIC
    Code:
      stack=7, locals=2, args_size=2
         0: new           #3                  // class org/kohsuke/github/authorization/ImmutableAuthorizationProvider$UserProvider
         3: dup
         4: ldc           #4                  // String token %s
         6: iconst_1
         7: anewarray     #5                  // class java/lang/Object
        10: dup
        11: iconst_0
        12: aload_0
        13: aastore
        14: invokestatic  #6                  // Method java/lang/String.format:(Ljava/lang/String;[Ljava/lang/Object;)Ljava/lang/String;
        17: aload_1
        18: invokespecial #8                  // Method org/kohsuke/github/authorization/ImmutableAuthorizationProvider$UserProvider."<init>":(Ljava/lang/String;Ljava/lang/String;)V
        21: areturn
      LineNumberTable:
        line 44: 0
      LocalVariableTable:
        Start  Length  Slot  Name   Signature
            0      22     0 oauthAccessToken   Ljava/lang/String;
            0      22     1 login   Ljava/lang/String;

  public static org.kohsuke.github.authorization.AuthorizationProvider fromAppInstallationToken(java.lang.String);
    descriptor: (Ljava/lang/String;)Lorg/kohsuke/github/authorization/AuthorizationProvider;
    flags: (0x0009) ACC_PUBLIC, ACC_STATIC
    Code:
      stack=2, locals=1, args_size=1
         0: aload_0
         1: ldc           #9                  // String
         3: invokestatic  #10                 // Method fromOauthToken:(Ljava/lang/String;Ljava/lang/String;)Lorg/kohsuke/github/authorization/AuthorizationProvider;
         6: areturn
      LineNumberTable:
        line 55: 0
      LocalVariableTable:
        Start  Length  Slot  Name   Signature
            0       7     0 appInstallationToken   Ljava/lang/String;

  public static org.kohsuke.github.authorization.AuthorizationProvider fromJwtToken(java.lang.String);
    descriptor: (Ljava/lang/String;)Lorg/kohsuke/github/authorization/AuthorizationProvider;
    flags: (0x0009) ACC_PUBLIC, ACC_STATIC
    Code:
      stack=7, locals=1, args_size=1
         0: new           #11                 // class org/kohsuke/github/authorization/ImmutableAuthorizationProvider
         3: dup
         4: ldc           #12                 // String Bearer %s
         6: iconst_1
         7: anewarray     #5                  // class java/lang/Object
        10: dup
        11: iconst_0
        12: aload_0
        13: aastore
        14: invokestatic  #6                  // Method java/lang/String.format:(Ljava/lang/String;[Ljava/lang/Object;)Ljava/lang/String;
        17: invokespecial #13                 // Method "<init>":(Ljava/lang/String;)V
        20: areturn
      LineNumberTable:
        line 66: 0
      LocalVariableTable:
        Start  Length  Slot  Name   Signature
            0      21     0 jwtToken   Ljava/lang/String;

  public static org.kohsuke.github.authorization.AuthorizationProvider fromLoginAndPassword(java.lang.String, java.lang.String);
    descriptor: (Ljava/lang/String;Ljava/lang/String;)Lorg/kohsuke/github/authorization/AuthorizationProvider;
    flags: (0x0009) ACC_PUBLIC, ACC_STATIC
    Code:
      stack=5, locals=6, args_size=2
         0: ldc           #14                 // String %s:%s
         2: iconst_2
         3: anewarray     #5                  // class java/lang/Object
         6: dup
         7: iconst_0
         8: aload_0
         9: aastore
        10: dup
        11: iconst_1
        12: aload_1
        13: aastore
        14: invokestatic  #6                  // Method java/lang/String.format:(Ljava/lang/String;[Ljava/lang/Object;)Ljava/lang/String;
        17: astore_2
        18: getstatic     #15                 // Field java/nio/charset/StandardCharsets.UTF_8:Ljava/nio/charset/Charset;
        21: invokevirtual #16                 // Method java/nio/charset/Charset.name:()Ljava/lang/String;
        24: astore_3
        25: invokestatic  #17                 // Method java/util/Base64.getEncoder:()Ljava/util/Base64$Encoder;
        28: aload_2
        29: aload_3
        30: invokevirtual #18                 // Method java/lang/String.getBytes:(Ljava/lang/String;)[B
        33: invokevirtual #19                 // Method java/util/Base64$Encoder.encodeToString:([B)Ljava/lang/String;
        36: astore        4
        38: ldc           #20                 // String Basic %s
        40: iconst_1
        41: anewarray     #5                  // class java/lang/Object
        44: dup
        45: iconst_0
        46: aload         4
        48: aastore
        49: invokestatic  #6                  // Method java/lang/String.format:(Ljava/lang/String;[Ljava/lang/Object;)Ljava/lang/String;
        52: astore        5
        54: new           #3                  // class org/kohsuke/github/authorization/ImmutableAuthorizationProvider$UserProvider
        57: dup
        58: aload         5
        60: aload_0
        61: invokespecial #8                  // Method org/kohsuke/github/authorization/ImmutableAuthorizationProvider$UserProvider."<init>":(Ljava/lang/String;Ljava/lang/String;)V
        64: areturn
        65: astore_2
        66: new           #22                 // class java/lang/IllegalStateException
        69: dup
        70: ldc           #23                 // String Could not generate encoded authorization
        72: aload_2
        73: invokespecial #24                 // Method java/lang/IllegalStateException."<init>":(Ljava/lang/String;Ljava/lang/Throwable;)V
        76: athrow
      Exception table:
         from    to  target type
             0    64    65   Class java/io/UnsupportedEncodingException
      LineNumberTable:
        line 83: 0
        line 84: 18
        line 85: 25
        line 86: 38
        line 87: 54
        line 88: 65
        line 90: 66
      LocalVariableTable:
        Start  Length  Slot  Name   Signature
           18      47     2 authorization   Ljava/lang/String;
           25      40     3 charsetName   Ljava/lang/String;
           38      27     4 b64encoded   Ljava/lang/String;
           54      11     5 encodedAuthorization   Ljava/lang/String;
           66      11     2     e   Ljava/io/UnsupportedEncodingException;
            0      77     0 login   Ljava/lang/String;
            0      77     1 password   Ljava/lang/String;
      StackMapTable: number_of_entries = 1
        frame_type = 247 /* same_locals_1_stack_item_frame_extended */
          offset_delta = 65
          stack = [ class java/io/UnsupportedEncodingException ]
    Deprecated: true
    RuntimeVisibleAnnotations:
      0: #56()
        java.lang.Deprecated

  public java.lang.String getEncodedAuthorization();
    descriptor: ()Ljava/lang/String;
    flags: (0x0001) ACC_PUBLIC
    Code:
      stack=1, locals=1, args_size=1
         0: aload_0
         1: getfield      #2                  // Field authorization:Ljava/lang/String;
         4: areturn
      LineNumberTable:
        line 96: 0
      LocalVariableTable:
        Start  Length  Slot  Name   Signature
            0       5     0  this   Lorg/kohsuke/github/authorization/ImmutableAuthorizationProvider;
}
SourceFile: "ImmutableAuthorizationProvider.java"
InnerClasses:
  private static #26= #3 of #11;          // UserProvider=class org/kohsuke/github/authorization/ImmutableAuthorizationProvider$UserProvider of class org/kohsuke/github/authorization/ImmutableAuthorizationProvider
  public static #102= #82 of #79;         // Encoder=class java/util/Base64$Encoder of class java/util/Base64
