Classfile /Users/mw/Projects/slang-braindump/.jar/jar11/assemble/slang-braindump/assemble/content/org/apache/commons/io/input/CharacterFilterReader.class
  Last modified May 29, 2022; size 643 bytes
  SHA-256 checksum 7627ad9613c9e6ce6f1a92c9797f275d2dfa6c12e6e8efc99745eb9cc3a55e30
  Compiled from "CharacterFilterReader.java"
public class org.apache.commons.io.input.CharacterFilterReader extends org.apache.commons.io.input.AbstractCharacterFilterReader
  minor version: 0
  major version: 52
  flags: (0x0021) ACC_PUBLIC, ACC_SUPER
  this_class: #3                          // org/apache/commons/io/input/CharacterFilterReader
  super_class: #4                         // org/apache/commons/io/input/AbstractCharacterFilterReader
  interfaces: 0, fields: 1, methods: 2, attributes: 1
Constant pool:
   #1 = Methodref          #4.#22         // org/apache/commons/io/input/AbstractCharacterFilterReader."<init>":(Ljava/io/Reader;)V
   #2 = Fieldref           #3.#23         // org/apache/commons/io/input/CharacterFilterReader.skip:I
   #3 = Class              #24            // org/apache/commons/io/input/CharacterFilterReader
   #4 = Class              #25            // org/apache/commons/io/input/AbstractCharacterFilterReader
   #5 = Utf8               skip
   #6 = Utf8               I
   #7 = Utf8               <init>
   #8 = Utf8               (Ljava/io/Reader;I)V
   #9 = Utf8               Code
  #10 = Utf8               LineNumberTable
  #11 = Utf8               LocalVariableTable
  #12 = Utf8               this
  #13 = Utf8               Lorg/apache/commons/io/input/CharacterFilterReader;
  #14 = Utf8               reader
  #15 = Utf8               Ljava/io/Reader;
  #16 = Utf8               filter
  #17 = Utf8               (I)Z
  #18 = Utf8               ch
  #19 = Utf8               StackMapTable
  #20 = Utf8               SourceFile
  #21 = Utf8               CharacterFilterReader.java
  #22 = NameAndType        #7:#26         // "<init>":(Ljava/io/Reader;)V
  #23 = NameAndType        #5:#6          // skip:I
  #24 = Utf8               org/apache/commons/io/input/CharacterFilterReader
  #25 = Utf8               org/apache/commons/io/input/AbstractCharacterFilterReader
  #26 = Utf8               (Ljava/io/Reader;)V
{
  private final int skip;
    descriptor: I
    flags: (0x0012) ACC_PRIVATE, ACC_FINAL

  public org.apache.commons.io.input.CharacterFilterReader(java.io.Reader, int);
    descriptor: (Ljava/io/Reader;I)V
    flags: (0x0001) ACC_PUBLIC
    Code:
      stack=2, locals=3, args_size=3
         0: aload_0
         1: aload_1
         2: invokespecial #1                  // Method org/apache/commons/io/input/AbstractCharacterFilterReader."<init>":(Ljava/io/Reader;)V
         5: aload_0
         6: iload_2
         7: putfield      #2                  // Field skip:I
        10: return
      LineNumberTable:
        line 39: 0
        line 40: 5
        line 41: 10
      LocalVariableTable:
        Start  Length  Slot  Name   Signature
            0      11     0  this   Lorg/apache/commons/io/input/CharacterFilterReader;
            0      11     1 reader   Ljava/io/Reader;
            0      11     2  skip   I

  protected boolean filter(int);
    descriptor: (I)Z
    flags: (0x0004) ACC_PROTECTED
    Code:
      stack=2, locals=2, args_size=2
         0: iload_1
         1: aload_0
         2: getfield      #2                  // Field skip:I
         5: if_icmpne     12
         8: iconst_1
         9: goto          13
        12: iconst_0
        13: ireturn
      LineNumberTable:
        line 45: 0
      LocalVariableTable:
        Start  Length  Slot  Name   Signature
            0      14     0  this   Lorg/apache/commons/io/input/CharacterFilterReader;
            0      14     1    ch   I
      StackMapTable: number_of_entries = 2
        frame_type = 12 /* same */
        frame_type = 64 /* same_locals_1_stack_item */
          stack = [ int ]
}
SourceFile: "CharacterFilterReader.java"
