Classfile /Users/mw/Projects/slang-braindump/.jar/jar11/assemble/slang-braindump/assemble/content/org/apache/commons/io/input/CharacterSetFilterReader.class
  Last modified May 29, 2022; size 1302 bytes
  SHA-256 checksum 2bea745d88836c5a8f4c3057d4811365429e2edaf034119cab74309a2a30b108
  Compiled from "CharacterSetFilterReader.java"
public class org.apache.commons.io.input.CharacterSetFilterReader extends org.apache.commons.io.input.AbstractCharacterFilterReader
  minor version: 0
  major version: 52
  flags: (0x0021) ACC_PUBLIC, ACC_SUPER
  this_class: #8                          // org/apache/commons/io/input/CharacterSetFilterReader
  super_class: #9                         // org/apache/commons/io/input/AbstractCharacterFilterReader
  interfaces: 0, fields: 2, methods: 3, attributes: 1
Constant pool:
   #1 = Methodref          #9.#39         // org/apache/commons/io/input/AbstractCharacterFilterReader."<init>":(Ljava/io/Reader;)V
   #2 = Fieldref           #8.#40         // org/apache/commons/io/input/CharacterSetFilterReader.EMPTY_SET:Ljava/util/Set;
   #3 = Methodref          #41.#42        // java/util/Collections.unmodifiableSet:(Ljava/util/Set;)Ljava/util/Set;
   #4 = Fieldref           #8.#43         // org/apache/commons/io/input/CharacterSetFilterReader.skipSet:Ljava/util/Set;
   #5 = Methodref          #44.#45        // java/lang/Integer.valueOf:(I)Ljava/lang/Integer;
   #6 = InterfaceMethodref #46.#47        // java/util/Set.contains:(Ljava/lang/Object;)Z
   #7 = Methodref          #41.#48        // java/util/Collections.emptySet:()Ljava/util/Set;
   #8 = Class              #49            // org/apache/commons/io/input/CharacterSetFilterReader
   #9 = Class              #50            // org/apache/commons/io/input/AbstractCharacterFilterReader
  #10 = Utf8               EMPTY_SET
  #11 = Utf8               Ljava/util/Set;
  #12 = Utf8               Signature
  #13 = Utf8               Ljava/util/Set<Ljava/lang/Integer;>;
  #14 = Utf8               skipSet
  #15 = Utf8               <init>
  #16 = Utf8               (Ljava/io/Reader;Ljava/util/Set;)V
  #17 = Utf8               Code
  #18 = Utf8               LineNumberTable
  #19 = Utf8               LocalVariableTable
  #20 = Utf8               this
  #21 = Utf8               Lorg/apache/commons/io/input/CharacterSetFilterReader;
  #22 = Utf8               reader
  #23 = Utf8               Ljava/io/Reader;
  #24 = Utf8               skip
  #25 = Utf8               LocalVariableTypeTable
  #26 = Utf8               StackMapTable
  #27 = Class              #49            // org/apache/commons/io/input/CharacterSetFilterReader
  #28 = Class              #51            // java/io/Reader
  #29 = Class              #52            // java/util/Set
  #30 = Utf8               (Ljava/io/Reader;Ljava/util/Set<Ljava/lang/Integer;>;)V
  #31 = Utf8               filter
  #32 = Utf8               (I)Z
  #33 = Utf8               ch
  #34 = Utf8               I
  #35 = Utf8               <clinit>
  #36 = Utf8               ()V
  #37 = Utf8               SourceFile
  #38 = Utf8               CharacterSetFilterReader.java
  #39 = NameAndType        #15:#53        // "<init>":(Ljava/io/Reader;)V
  #40 = NameAndType        #10:#11        // EMPTY_SET:Ljava/util/Set;
  #41 = Class              #54            // java/util/Collections
  #42 = NameAndType        #55:#56        // unmodifiableSet:(Ljava/util/Set;)Ljava/util/Set;
  #43 = NameAndType        #14:#11        // skipSet:Ljava/util/Set;
  #44 = Class              #57            // java/lang/Integer
  #45 = NameAndType        #58:#59        // valueOf:(I)Ljava/lang/Integer;
  #46 = Class              #52            // java/util/Set
  #47 = NameAndType        #60:#61        // contains:(Ljava/lang/Object;)Z
  #48 = NameAndType        #62:#63        // emptySet:()Ljava/util/Set;
  #49 = Utf8               org/apache/commons/io/input/CharacterSetFilterReader
  #50 = Utf8               org/apache/commons/io/input/AbstractCharacterFilterReader
  #51 = Utf8               java/io/Reader
  #52 = Utf8               java/util/Set
  #53 = Utf8               (Ljava/io/Reader;)V
  #54 = Utf8               java/util/Collections
  #55 = Utf8               unmodifiableSet
  #56 = Utf8               (Ljava/util/Set;)Ljava/util/Set;
  #57 = Utf8               java/lang/Integer
  #58 = Utf8               valueOf
  #59 = Utf8               (I)Ljava/lang/Integer;
  #60 = Utf8               contains
  #61 = Utf8               (Ljava/lang/Object;)Z
  #62 = Utf8               emptySet
  #63 = Utf8               ()Ljava/util/Set;
{
  private static final java.util.Set<java.lang.Integer> EMPTY_SET;
    descriptor: Ljava/util/Set;
    flags: (0x001a) ACC_PRIVATE, ACC_STATIC, ACC_FINAL
    Signature: #13                          // Ljava/util/Set<Ljava/lang/Integer;>;

  private final java.util.Set<java.lang.Integer> skipSet;
    descriptor: Ljava/util/Set;
    flags: (0x0012) ACC_PRIVATE, ACC_FINAL
    Signature: #13                          // Ljava/util/Set<Ljava/lang/Integer;>;

  public org.apache.commons.io.input.CharacterSetFilterReader(java.io.Reader, java.util.Set<java.lang.Integer>);
    descriptor: (Ljava/io/Reader;Ljava/util/Set;)V
    flags: (0x0001) ACC_PUBLIC
    Code:
      stack=2, locals=3, args_size=3
         0: aload_0
         1: aload_1
         2: invokespecial #1                  // Method org/apache/commons/io/input/AbstractCharacterFilterReader."<init>":(Ljava/io/Reader;)V
         5: aload_0
         6: aload_2
         7: ifnonnull     16
        10: getstatic     #2                  // Field EMPTY_SET:Ljava/util/Set;
        13: goto          20
        16: aload_2
        17: invokestatic  #3                  // Method java/util/Collections.unmodifiableSet:(Ljava/util/Set;)Ljava/util/Set;
        20: putfield      #4                  // Field skipSet:Ljava/util/Set;
        23: return
      LineNumberTable:
        line 45: 0
        line 46: 5
        line 47: 23
      LocalVariableTable:
        Start  Length  Slot  Name   Signature
            0      24     0  this   Lorg/apache/commons/io/input/CharacterSetFilterReader;
            0      24     1 reader   Ljava/io/Reader;
            0      24     2  skip   Ljava/util/Set;
      LocalVariableTypeTable:
        Start  Length  Slot  Name   Signature
            0      24     2  skip   Ljava/util/Set<Ljava/lang/Integer;>;
      StackMapTable: number_of_entries = 2
        frame_type = 255 /* full_frame */
          offset_delta = 16
          locals = [ class org/apache/commons/io/input/CharacterSetFilterReader, class java/io/Reader, class java/util/Set ]
          stack = [ class org/apache/commons/io/input/CharacterSetFilterReader ]
        frame_type = 255 /* full_frame */
          offset_delta = 3
          locals = [ class org/apache/commons/io/input/CharacterSetFilterReader, class java/io/Reader, class java/util/Set ]
          stack = [ class org/apache/commons/io/input/CharacterSetFilterReader, class java/util/Set ]
    Signature: #30                          // (Ljava/io/Reader;Ljava/util/Set<Ljava/lang/Integer;>;)V

  protected boolean filter(int);
    descriptor: (I)Z
    flags: (0x0004) ACC_PROTECTED
    Code:
      stack=2, locals=2, args_size=2
         0: aload_0
         1: getfield      #4                  // Field skipSet:Ljava/util/Set;
         4: iload_1
         5: invokestatic  #5                  // Method java/lang/Integer.valueOf:(I)Ljava/lang/Integer;
         8: invokeinterface #6,  2            // InterfaceMethod java/util/Set.contains:(Ljava/lang/Object;)Z
        13: ireturn
      LineNumberTable:
        line 52: 0
      LocalVariableTable:
        Start  Length  Slot  Name   Signature
            0      14     0  this   Lorg/apache/commons/io/input/CharacterSetFilterReader;
            0      14     1    ch   I

  static {};
    descriptor: ()V
    flags: (0x0008) ACC_STATIC
    Code:
      stack=1, locals=0, args_size=0
         0: invokestatic  #7                  // Method java/util/Collections.emptySet:()Ljava/util/Set;
         3: putstatic     #2                  // Field EMPTY_SET:Ljava/util/Set;
         6: return
      LineNumberTable:
        line 33: 0
}
SourceFile: "CharacterSetFilterReader.java"
