Classfile /Users/mw/Projects/slang-braindump/.jar/jar11/assemble/slang-braindump/assemble/content/org/apache/commons/io/input/MessageDigestCalculatingInputStream$MessageDigestMaintainingObserver.class
  Last modified May 29, 2022; size 1194 bytes
  SHA-256 checksum b5da355b658e2022a8db2789b4183918255a3a13dcdabe0acaa5f48ea1b40827
  Compiled from "MessageDigestCalculatingInputStream.java"
public class org.apache.commons.io.input.MessageDigestCalculatingInputStream$MessageDigestMaintainingObserver extends org.apache.commons.io.input.ObservableInputStream$Observer
  minor version: 0
  major version: 52
  flags: (0x0021) ACC_PUBLIC, ACC_SUPER
  this_class: #5                          // org/apache/commons/io/input/MessageDigestCalculatingInputStream$MessageDigestMaintainingObserver
  super_class: #6                         // org/apache/commons/io/input/ObservableInputStream$Observer
  interfaces: 0, fields: 1, methods: 3, attributes: 2
Constant pool:
   #1 = Methodref          #6.#30         // org/apache/commons/io/input/ObservableInputStream$Observer."<init>":()V
   #2 = Fieldref           #5.#31         // org/apache/commons/io/input/MessageDigestCalculatingInputStream$MessageDigestMaintainingObserver.messageDigest:Ljava/security/MessageDigest;
   #3 = Methodref          #32.#33        // java/security/MessageDigest.update:(B)V
   #4 = Methodref          #32.#34        // java/security/MessageDigest.update:([BII)V
   #5 = Class              #36            // org/apache/commons/io/input/MessageDigestCalculatingInputStream$MessageDigestMaintainingObserver
   #6 = Class              #38            // org/apache/commons/io/input/ObservableInputStream$Observer
   #7 = Utf8               messageDigest
   #8 = Utf8               Ljava/security/MessageDigest;
   #9 = Utf8               <init>
  #10 = Utf8               (Ljava/security/MessageDigest;)V
  #11 = Utf8               Code
  #12 = Utf8               LineNumberTable
  #13 = Utf8               LocalVariableTable
  #14 = Utf8               this
  #15 = Utf8               MessageDigestMaintainingObserver
  #16 = Utf8               InnerClasses
  #17 = Utf8               Lorg/apache/commons/io/input/MessageDigestCalculatingInputStream$MessageDigestMaintainingObserver;
  #18 = Utf8               data
  #19 = Utf8               (I)V
  #20 = Utf8               input
  #21 = Utf8               I
  #22 = Utf8               Exceptions
  #23 = Class              #40            // java/io/IOException
  #24 = Utf8               ([BII)V
  #25 = Utf8               [B
  #26 = Utf8               offset
  #27 = Utf8               length
  #28 = Utf8               SourceFile
  #29 = Utf8               MessageDigestCalculatingInputStream.java
  #30 = NameAndType        #9:#41         // "<init>":()V
  #31 = NameAndType        #7:#8          // messageDigest:Ljava/security/MessageDigest;
  #32 = Class              #42            // java/security/MessageDigest
  #33 = NameAndType        #43:#44        // update:(B)V
  #34 = NameAndType        #43:#24        // update:([BII)V
  #35 = Class              #45            // org/apache/commons/io/input/MessageDigestCalculatingInputStream
  #36 = Utf8               org/apache/commons/io/input/MessageDigestCalculatingInputStream$MessageDigestMaintainingObserver
  #37 = Class              #46            // org/apache/commons/io/input/ObservableInputStream
  #38 = Utf8               org/apache/commons/io/input/ObservableInputStream$Observer
  #39 = Utf8               Observer
  #40 = Utf8               java/io/IOException
  #41 = Utf8               ()V
  #42 = Utf8               java/security/MessageDigest
  #43 = Utf8               update
  #44 = Utf8               (B)V
  #45 = Utf8               org/apache/commons/io/input/MessageDigestCalculatingInputStream
  #46 = Utf8               org/apache/commons/io/input/ObservableInputStream
{
  private final java.security.MessageDigest messageDigest;
    descriptor: Ljava/security/MessageDigest;
    flags: (0x0012) ACC_PRIVATE, ACC_FINAL

  public org.apache.commons.io.input.MessageDigestCalculatingInputStream$MessageDigestMaintainingObserver(java.security.MessageDigest);
    descriptor: (Ljava/security/MessageDigest;)V
    flags: (0x0001) ACC_PUBLIC
    Code:
      stack=2, locals=2, args_size=2
         0: aload_0
         1: invokespecial #1                  // Method org/apache/commons/io/input/ObservableInputStream$Observer."<init>":()V
         4: aload_0
         5: aload_1
         6: putfield      #2                  // Field messageDigest:Ljava/security/MessageDigest;
         9: return
      LineNumberTable:
        line 44: 0
        line 45: 4
        line 46: 9
      LocalVariableTable:
        Start  Length  Slot  Name   Signature
            0      10     0  this   Lorg/apache/commons/io/input/MessageDigestCalculatingInputStream$MessageDigestMaintainingObserver;
            0      10     1 messageDigest   Ljava/security/MessageDigest;

  public void data(int) throws java.io.IOException;
    descriptor: (I)V
    flags: (0x0001) ACC_PUBLIC
    Code:
      stack=2, locals=2, args_size=2
         0: aload_0
         1: getfield      #2                  // Field messageDigest:Ljava/security/MessageDigest;
         4: iload_1
         5: i2b
         6: invokevirtual #3                  // Method java/security/MessageDigest.update:(B)V
         9: return
      LineNumberTable:
        line 50: 0
        line 51: 9
      LocalVariableTable:
        Start  Length  Slot  Name   Signature
            0      10     0  this   Lorg/apache/commons/io/input/MessageDigestCalculatingInputStream$MessageDigestMaintainingObserver;
            0      10     1 input   I
    Exceptions:
      throws java.io.IOException

  public void data(byte[], int, int) throws java.io.IOException;
    descriptor: ([BII)V
    flags: (0x0001) ACC_PUBLIC
    Code:
      stack=4, locals=4, args_size=4
         0: aload_0
         1: getfield      #2                  // Field messageDigest:Ljava/security/MessageDigest;
         4: aload_1
         5: iload_2
         6: iload_3
         7: invokevirtual #4                  // Method java/security/MessageDigest.update:([BII)V
        10: return
      LineNumberTable:
        line 55: 0
        line 56: 10
      LocalVariableTable:
        Start  Length  Slot  Name   Signature
            0      11     0  this   Lorg/apache/commons/io/input/MessageDigestCalculatingInputStream$MessageDigestMaintainingObserver;
            0      11     1 input   [B
            0      11     2 offset   I
            0      11     3 length   I
    Exceptions:
      throws java.io.IOException
}
SourceFile: "MessageDigestCalculatingInputStream.java"
InnerClasses:
  public static #15= #5 of #35;           // MessageDigestMaintainingObserver=class org/apache/commons/io/input/MessageDigestCalculatingInputStream$MessageDigestMaintainingObserver of class org/apache/commons/io/input/MessageDigestCalculatingInputStream
  public static abstract #39= #6 of #37;  // Observer=class org/apache/commons/io/input/ObservableInputStream$Observer of class org/apache/commons/io/input/ObservableInputStream
