Classfile /Users/mw/Projects/slang-braindump/.jar/jar11/assemble/slang-braindump/assemble/content/org/apache/commons/io/input/ReversedLinesFileReader$FilePart.class
  Last modified May 29, 2022; size 4938 bytes
  SHA-256 checksum 123cc22f32297cb9fbcd20a4ebbdd692d7d1b01d5b9413b11bfc284af2acce4a
  Compiled from "ReversedLinesFileReader.java"
class org.apache.commons.io.input.ReversedLinesFileReader$FilePart
  minor version: 0
  major version: 52
  flags: (0x0020) ACC_SUPER
  this_class: #34                         // org/apache/commons/io/input/ReversedLinesFileReader$FilePart
  super_class: #36                        // java/lang/Object
  interfaces: 0, fields: 5, methods: 8, attributes: 2
Constant pool:
    #1 = Methodref          #34.#103      // org/apache/commons/io/input/ReversedLinesFileReader$FilePart.rollOver:()Lorg/apache/commons/io/input/ReversedLinesFileReader$FilePart;
    #2 = Methodref          #34.#104      // org/apache/commons/io/input/ReversedLinesFileReader$FilePart.readLine:()Ljava/lang/String;
    #3 = Methodref          #34.#105      // org/apache/commons/io/input/ReversedLinesFileReader$FilePart."<init>":(Lorg/apache/commons/io/input/ReversedLinesFileReader;JI[B)V
    #4 = Fieldref           #34.#106      // org/apache/commons/io/input/ReversedLinesFileReader$FilePart.this$0:Lorg/apache/commons/io/input/ReversedLinesFileReader;
    #5 = Methodref          #36.#107      // java/lang/Object."<init>":()V
    #6 = Fieldref           #34.#108      // org/apache/commons/io/input/ReversedLinesFileReader$FilePart.no:J
    #7 = Fieldref           #34.#109      // org/apache/commons/io/input/ReversedLinesFileReader$FilePart.data:[B
    #8 = Methodref          #110.#111     // org/apache/commons/io/input/ReversedLinesFileReader.access$000:(Lorg/apache/commons/io/input/ReversedLinesFileReader;)I
    #9 = Methodref          #110.#112     // org/apache/commons/io/input/ReversedLinesFileReader.access$100:(Lorg/apache/commons/io/input/ReversedLinesFileReader;)Ljava/nio/channels/SeekableByteChannel;
   #10 = InterfaceMethodref #113.#114     // java/nio/channels/SeekableByteChannel.position:(J)Ljava/nio/channels/SeekableByteChannel;
   #11 = Methodref          #115.#116     // java/nio/ByteBuffer.wrap:([BII)Ljava/nio/ByteBuffer;
   #12 = InterfaceMethodref #113.#117     // java/nio/channels/SeekableByteChannel.read:(Ljava/nio/ByteBuffer;)I
   #13 = Class              #118          // java/lang/IllegalStateException
   #14 = String             #119          // Count of requested bytes and actually read bytes don\'t match
   #15 = Methodref          #13.#120      // java/lang/IllegalStateException."<init>":(Ljava/lang/String;)V
   #16 = Methodref          #121.#122     // java/lang/System.arraycopy:(Ljava/lang/Object;ILjava/lang/Object;II)V
   #17 = Fieldref           #34.#123      // org/apache/commons/io/input/ReversedLinesFileReader$FilePart.currentLastBytePos:I
   #18 = Fieldref           #34.#124      // org/apache/commons/io/input/ReversedLinesFileReader$FilePart.leftOver:[B
   #19 = Methodref          #110.#125     // org/apache/commons/io/input/ReversedLinesFileReader.access$200:(Lorg/apache/commons/io/input/ReversedLinesFileReader;)[[B
   #20 = Methodref          #110.#126     // org/apache/commons/io/input/ReversedLinesFileReader.access$300:(Lorg/apache/commons/io/input/ReversedLinesFileReader;)I
   #21 = Methodref          #34.#127      // org/apache/commons/io/input/ReversedLinesFileReader$FilePart.createLeftOver:()V
   #22 = Methodref          #34.#128      // org/apache/commons/io/input/ReversedLinesFileReader$FilePart.getNewLineMatchByteCount:([BI)I
   #23 = Class              #129          // java/lang/StringBuilder
   #24 = Methodref          #23.#107      // java/lang/StringBuilder."<init>":()V
   #25 = String             #130          // Unexpected negative line length=
   #26 = Methodref          #23.#131      // java/lang/StringBuilder.append:(Ljava/lang/String;)Ljava/lang/StringBuilder;
   #27 = Methodref          #23.#132      // java/lang/StringBuilder.append:(I)Ljava/lang/StringBuilder;
   #28 = Methodref          #23.#133      // java/lang/StringBuilder.toString:()Ljava/lang/String;
   #29 = Class              #134          // java/lang/String
   #30 = Methodref          #110.#135     // org/apache/commons/io/input/ReversedLinesFileReader.access$400:(Lorg/apache/commons/io/input/ReversedLinesFileReader;)Ljava/nio/charset/Charset;
   #31 = Methodref          #29.#136      // java/lang/String."<init>":([BLjava/nio/charset/Charset;)V
   #32 = Methodref          #110.#137     // org/apache/commons/io/input/ReversedLinesFileReader.access$500:(Lorg/apache/commons/io/input/ReversedLinesFileReader;)I
   #33 = String             #138          // Current currentLastCharPos unexpectedly positive... last readLine() should have returned something! currentLastCharPos=
   #34 = Class              #139          // org/apache/commons/io/input/ReversedLinesFileReader$FilePart
   #35 = String             #140          // Unexpected leftover of the last block: leftOverOfThisFilePart=
   #36 = Class              #141          // java/lang/Object
   #37 = Utf8               no
   #38 = Utf8               J
   #39 = Utf8               data
   #40 = Utf8               [B
   #41 = Utf8               leftOver
   #42 = Utf8               currentLastBytePos
   #43 = Utf8               I
   #44 = Utf8               this$0
   #45 = Utf8               Lorg/apache/commons/io/input/ReversedLinesFileReader;
   #46 = Utf8               <init>
   #47 = Utf8               (Lorg/apache/commons/io/input/ReversedLinesFileReader;JI[B)V
   #48 = Utf8               Code
   #49 = Utf8               LineNumberTable
   #50 = Utf8               LocalVariableTable
   #51 = Utf8               countRead
   #52 = Utf8               this
   #53 = Utf8               FilePart
   #54 = Utf8               InnerClasses
   #55 = Utf8               Lorg/apache/commons/io/input/ReversedLinesFileReader$FilePart;
   #56 = Utf8               length
   #57 = Utf8               leftOverOfLastFilePart
   #58 = Utf8               dataLength
   #59 = Utf8               off
   #60 = Utf8               StackMapTable
   #61 = Class              #139          // org/apache/commons/io/input/ReversedLinesFileReader$FilePart
   #62 = Class              #142          // org/apache/commons/io/input/ReversedLinesFileReader
   #63 = Class              #40           // "[B"
   #64 = Utf8               Exceptions
   #65 = Class              #143          // java/io/IOException
   #66 = Utf8               createLeftOver
   #67 = Utf8               ()V
   #68 = Utf8               lineLengthBytes
   #69 = Utf8               getNewLineMatchByteCount
   #70 = Utf8               ([BI)I
   #71 = Utf8               k
   #72 = Utf8               j
   #73 = Utf8               match
   #74 = Utf8               Z
   #75 = Utf8               newLineSequence
   #76 = Utf8               i
   #77 = Class              #144          // "[[B"
   #78 = Utf8               readLine
   #79 = Utf8               ()Ljava/lang/String;
   #80 = Utf8               lineStart
   #81 = Utf8               lineData
   #82 = Utf8               newLineMatchByteCount
   #83 = Utf8               line
   #84 = Utf8               Ljava/lang/String;
   #85 = Utf8               isLastFilePart
   #86 = Class              #134          // java/lang/String
   #87 = Utf8               rollOver
   #88 = Utf8               ()Lorg/apache/commons/io/input/ReversedLinesFileReader$FilePart;
   #89 = Class              #145          // org/apache/commons/io/input/ReversedLinesFileReader$1
   #90 = Utf8               (Lorg/apache/commons/io/input/ReversedLinesFileReader;JI[BLorg/apache/commons/io/input/ReversedLinesFileReader$1;)V
   #91 = Utf8               x0
   #92 = Utf8               x1
   #93 = Utf8               x2
   #94 = Utf8               x3
   #95 = Utf8               x4
   #96 = Utf8               Lorg/apache/commons/io/input/ReversedLinesFileReader$1;
   #97 = Utf8               access$700
   #98 = Utf8               (Lorg/apache/commons/io/input/ReversedLinesFileReader$FilePart;)Ljava/lang/String;
   #99 = Utf8               access$800
  #100 = Utf8               (Lorg/apache/commons/io/input/ReversedLinesFileReader$FilePart;)Lorg/apache/commons/io/input/ReversedLinesFileReader$FilePart;
  #101 = Utf8               SourceFile
  #102 = Utf8               ReversedLinesFileReader.java
  #103 = NameAndType        #87:#88       // rollOver:()Lorg/apache/commons/io/input/ReversedLinesFileReader$FilePart;
  #104 = NameAndType        #78:#79       // readLine:()Ljava/lang/String;
  #105 = NameAndType        #46:#47       // "<init>":(Lorg/apache/commons/io/input/ReversedLinesFileReader;JI[B)V
  #106 = NameAndType        #44:#45       // this$0:Lorg/apache/commons/io/input/ReversedLinesFileReader;
  #107 = NameAndType        #46:#67       // "<init>":()V
  #108 = NameAndType        #37:#38       // no:J
  #109 = NameAndType        #39:#40       // data:[B
  #110 = Class              #142          // org/apache/commons/io/input/ReversedLinesFileReader
  #111 = NameAndType        #146:#147     // access$000:(Lorg/apache/commons/io/input/ReversedLinesFileReader;)I
  #112 = NameAndType        #148:#149     // access$100:(Lorg/apache/commons/io/input/ReversedLinesFileReader;)Ljava/nio/channels/SeekableByteChannel;
  #113 = Class              #150          // java/nio/channels/SeekableByteChannel
  #114 = NameAndType        #151:#152     // position:(J)Ljava/nio/channels/SeekableByteChannel;
  #115 = Class              #153          // java/nio/ByteBuffer
  #116 = NameAndType        #154:#155     // wrap:([BII)Ljava/nio/ByteBuffer;
  #117 = NameAndType        #156:#157     // read:(Ljava/nio/ByteBuffer;)I
  #118 = Utf8               java/lang/IllegalStateException
  #119 = Utf8               Count of requested bytes and actually read bytes don\'t match
  #120 = NameAndType        #46:#158      // "<init>":(Ljava/lang/String;)V
  #121 = Class              #159          // java/lang/System
  #122 = NameAndType        #160:#161     // arraycopy:(Ljava/lang/Object;ILjava/lang/Object;II)V
  #123 = NameAndType        #42:#43       // currentLastBytePos:I
  #124 = NameAndType        #41:#40       // leftOver:[B
  #125 = NameAndType        #162:#163     // access$200:(Lorg/apache/commons/io/input/ReversedLinesFileReader;)[[B
  #126 = NameAndType        #164:#147     // access$300:(Lorg/apache/commons/io/input/ReversedLinesFileReader;)I
  #127 = NameAndType        #66:#67       // createLeftOver:()V
  #128 = NameAndType        #69:#70       // getNewLineMatchByteCount:([BI)I
  #129 = Utf8               java/lang/StringBuilder
  #130 = Utf8               Unexpected negative line length=
  #131 = NameAndType        #165:#166     // append:(Ljava/lang/String;)Ljava/lang/StringBuilder;
  #132 = NameAndType        #165:#167     // append:(I)Ljava/lang/StringBuilder;
  #133 = NameAndType        #168:#79      // toString:()Ljava/lang/String;
  #134 = Utf8               java/lang/String
  #135 = NameAndType        #169:#170     // access$400:(Lorg/apache/commons/io/input/ReversedLinesFileReader;)Ljava/nio/charset/Charset;
  #136 = NameAndType        #46:#171      // "<init>":([BLjava/nio/charset/Charset;)V
  #137 = NameAndType        #172:#147     // access$500:(Lorg/apache/commons/io/input/ReversedLinesFileReader;)I
  #138 = Utf8               Current currentLastCharPos unexpectedly positive... last readLine() should have returned something! currentLastCharPos=
  #139 = Utf8               org/apache/commons/io/input/ReversedLinesFileReader$FilePart
  #140 = Utf8               Unexpected leftover of the last block: leftOverOfThisFilePart=
  #141 = Utf8               java/lang/Object
  #142 = Utf8               org/apache/commons/io/input/ReversedLinesFileReader
  #143 = Utf8               java/io/IOException
  #144 = Utf8               [[B
  #145 = Utf8               org/apache/commons/io/input/ReversedLinesFileReader$1
  #146 = Utf8               access$000
  #147 = Utf8               (Lorg/apache/commons/io/input/ReversedLinesFileReader;)I
  #148 = Utf8               access$100
  #149 = Utf8               (Lorg/apache/commons/io/input/ReversedLinesFileReader;)Ljava/nio/channels/SeekableByteChannel;
  #150 = Utf8               java/nio/channels/SeekableByteChannel
  #151 = Utf8               position
  #152 = Utf8               (J)Ljava/nio/channels/SeekableByteChannel;
  #153 = Utf8               java/nio/ByteBuffer
  #154 = Utf8               wrap
  #155 = Utf8               ([BII)Ljava/nio/ByteBuffer;
  #156 = Utf8               read
  #157 = Utf8               (Ljava/nio/ByteBuffer;)I
  #158 = Utf8               (Ljava/lang/String;)V
  #159 = Utf8               java/lang/System
  #160 = Utf8               arraycopy
  #161 = Utf8               (Ljava/lang/Object;ILjava/lang/Object;II)V
  #162 = Utf8               access$200
  #163 = Utf8               (Lorg/apache/commons/io/input/ReversedLinesFileReader;)[[B
  #164 = Utf8               access$300
  #165 = Utf8               append
  #166 = Utf8               (Ljava/lang/String;)Ljava/lang/StringBuilder;
  #167 = Utf8               (I)Ljava/lang/StringBuilder;
  #168 = Utf8               toString
  #169 = Utf8               access$400
  #170 = Utf8               (Lorg/apache/commons/io/input/ReversedLinesFileReader;)Ljava/nio/charset/Charset;
  #171 = Utf8               ([BLjava/nio/charset/Charset;)V
  #172 = Utf8               access$500
{
  private final long no;
    descriptor: J
    flags: (0x0012) ACC_PRIVATE, ACC_FINAL

  private final byte[] data;
    descriptor: [B
    flags: (0x0012) ACC_PRIVATE, ACC_FINAL

  private byte[] leftOver;
    descriptor: [B
    flags: (0x0002) ACC_PRIVATE

  private int currentLastBytePos;
    descriptor: I
    flags: (0x0002) ACC_PRIVATE

  final org.apache.commons.io.input.ReversedLinesFileReader this$0;
    descriptor: Lorg/apache/commons/io/input/ReversedLinesFileReader;
    flags: (0x1010) ACC_FINAL, ACC_SYNTHETIC

  private org.apache.commons.io.input.ReversedLinesFileReader$FilePart(org.apache.commons.io.input.ReversedLinesFileReader, long, int, byte[]) throws java.io.IOException;
    descriptor: (Lorg/apache/commons/io/input/ReversedLinesFileReader;JI[B)V
    flags: (0x0002) ACC_PRIVATE
    Code:
      stack=5, locals=10, args_size=5
         0: aload_0
         1: aload_1
         2: putfield      #4                  // Field this$0:Lorg/apache/commons/io/input/ReversedLinesFileReader;
         5: aload_0
         6: invokespecial #5                  // Method java/lang/Object."<init>":()V
         9: aload_0
        10: lload_2
        11: putfield      #6                  // Field no:J
        14: iload         4
        16: aload         5
        18: ifnull        27
        21: aload         5
        23: arraylength
        24: goto          28
        27: iconst_0
        28: iadd
        29: istore        6
        31: aload_0
        32: iload         6
        34: newarray       byte
        36: putfield      #7                  // Field data:[B
        39: lload_2
        40: lconst_1
        41: lsub
        42: aload_1
        43: invokestatic  #8                  // Method org/apache/commons/io/input/ReversedLinesFileReader.access$000:(Lorg/apache/commons/io/input/ReversedLinesFileReader;)I
        46: i2l
        47: lmul
        48: lstore        7
        50: lload_2
        51: lconst_0
        52: lcmp
        53: ifle          106
        56: aload_1
        57: invokestatic  #9                  // Method org/apache/commons/io/input/ReversedLinesFileReader.access$100:(Lorg/apache/commons/io/input/ReversedLinesFileReader;)Ljava/nio/channels/SeekableByteChannel;
        60: lload         7
        62: invokeinterface #10,  3           // InterfaceMethod java/nio/channels/SeekableByteChannel.position:(J)Ljava/nio/channels/SeekableByteChannel;
        67: pop
        68: aload_1
        69: invokestatic  #9                  // Method org/apache/commons/io/input/ReversedLinesFileReader.access$100:(Lorg/apache/commons/io/input/ReversedLinesFileReader;)Ljava/nio/channels/SeekableByteChannel;
        72: aload_0
        73: getfield      #7                  // Field data:[B
        76: iconst_0
        77: iload         4
        79: invokestatic  #11                 // Method java/nio/ByteBuffer.wrap:([BII)Ljava/nio/ByteBuffer;
        82: invokeinterface #12,  2           // InterfaceMethod java/nio/channels/SeekableByteChannel.read:(Ljava/nio/ByteBuffer;)I
        87: istore        9
        89: iload         9
        91: iload         4
        93: if_icmpeq     106
        96: new           #13                 // class java/lang/IllegalStateException
        99: dup
       100: ldc           #14                 // String Count of requested bytes and actually read bytes don\'t match
       102: invokespecial #15                 // Method java/lang/IllegalStateException."<init>":(Ljava/lang/String;)V
       105: athrow
       106: aload         5
       108: ifnull        126
       111: aload         5
       113: iconst_0
       114: aload_0
       115: getfield      #7                  // Field data:[B
       118: iload         4
       120: aload         5
       122: arraylength
       123: invokestatic  #16                 // Method java/lang/System.arraycopy:(Ljava/lang/Object;ILjava/lang/Object;II)V
       126: aload_0
       127: aload_0
       128: getfield      #7                  // Field data:[B
       131: arraylength
       132: iconst_1
       133: isub
       134: putfield      #17                 // Field currentLastBytePos:I
       137: aload_0
       138: aconst_null
       139: putfield      #18                 // Field leftOver:[B
       142: return
      LineNumberTable:
        line 63: 0
        line 64: 9
        line 65: 14
        line 66: 31
        line 67: 39
        line 70: 50
        line 71: 56
        line 72: 68
        line 73: 89
        line 74: 96
        line 78: 106
        line 79: 111
        line 81: 126
        line 82: 137
        line 83: 142
      LocalVariableTable:
        Start  Length  Slot  Name   Signature
           89      17     9 countRead   I
            0     143     0  this   Lorg/apache/commons/io/input/ReversedLinesFileReader$FilePart;
            0     143     2    no   J
            0     143     4 length   I
            0     143     5 leftOverOfLastFilePart   [B
           31     112     6 dataLength   I
           50      93     7   off   J
      StackMapTable: number_of_entries = 4
        frame_type = 255 /* full_frame */
          offset_delta = 27
          locals = [ class org/apache/commons/io/input/ReversedLinesFileReader$FilePart, class org/apache/commons/io/input/ReversedLinesFileReader, long, int, class "[B" ]
          stack = [ int ]
        frame_type = 255 /* full_frame */
          offset_delta = 0
          locals = [ class org/apache/commons/io/input/ReversedLinesFileReader$FilePart, class org/apache/commons/io/input/ReversedLinesFileReader, long, int, class "[B" ]
          stack = [ int, int ]
        frame_type = 253 /* append */
          offset_delta = 77
          locals = [ int, long ]
        frame_type = 19 /* same */
    Exceptions:
      throws java.io.IOException

  private void createLeftOver();
    descriptor: ()V
    flags: (0x0002) ACC_PRIVATE
    Code:
      stack=5, locals=2, args_size=1
         0: aload_0
         1: getfield      #17                 // Field currentLastBytePos:I
         4: iconst_1
         5: iadd
         6: istore_1
         7: iload_1
         8: ifle          35
        11: aload_0
        12: iload_1
        13: newarray       byte
        15: putfield      #18                 // Field leftOver:[B
        18: aload_0
        19: getfield      #7                  // Field data:[B
        22: iconst_0
        23: aload_0
        24: getfield      #18                 // Field leftOver:[B
        27: iconst_0
        28: iload_1
        29: invokestatic  #16                 // Method java/lang/System.arraycopy:(Ljava/lang/Object;ILjava/lang/Object;II)V
        32: goto          40
        35: aload_0
        36: aconst_null
        37: putfield      #18                 // Field leftOver:[B
        40: aload_0
        41: iconst_m1
        42: putfield      #17                 // Field currentLastBytePos:I
        45: return
      LineNumberTable:
        line 89: 0
        line 90: 7
        line 92: 11
        line 93: 18
        line 95: 35
        line 97: 40
        line 98: 45
      LocalVariableTable:
        Start  Length  Slot  Name   Signature
            0      46     0  this   Lorg/apache/commons/io/input/ReversedLinesFileReader$FilePart;
            7      39     1 lineLengthBytes   I
      StackMapTable: number_of_entries = 2
        frame_type = 252 /* append */
          offset_delta = 35
          locals = [ int ]
        frame_type = 4 /* same */

  private int getNewLineMatchByteCount(byte[], int);
    descriptor: ([BI)I
    flags: (0x0002) ACC_PRIVATE
    Code:
      stack=4, locals=10, args_size=3
         0: aload_0
         1: getfield      #4                  // Field this$0:Lorg/apache/commons/io/input/ReversedLinesFileReader;
         4: invokestatic  #19                 // Method org/apache/commons/io/input/ReversedLinesFileReader.access$200:(Lorg/apache/commons/io/input/ReversedLinesFileReader;)[[B
         7: astore_3
         8: aload_3
         9: arraylength
        10: istore        4
        12: iconst_0
        13: istore        5
        15: iload         5
        17: iload         4
        19: if_icmpge     103
        22: aload_3
        23: iload         5
        25: aaload
        26: astore        6
        28: iconst_1
        29: istore        7
        31: aload         6
        33: arraylength
        34: iconst_1
        35: isub
        36: istore        8
        38: iload         8
        40: iflt          88
        43: iload_2
        44: iload         8
        46: iadd
        47: aload         6
        49: arraylength
        50: iconst_1
        51: isub
        52: isub
        53: istore        9
        55: iload         7
        57: iload         9
        59: iflt          78
        62: aload_1
        63: iload         9
        65: baload
        66: aload         6
        68: iload         8
        70: baload
        71: if_icmpne     78
        74: iconst_1
        75: goto          79
        78: iconst_0
        79: iand
        80: istore        7
        82: iinc          8, -1
        85: goto          38
        88: iload         7
        90: ifeq          97
        93: aload         6
        95: arraylength
        96: ireturn
        97: iinc          5, 1
       100: goto          15
       103: iconst_0
       104: ireturn
      LineNumberTable:
        line 108: 0
        line 109: 28
        line 110: 31
        line 111: 43
        line 112: 55
        line 110: 82
        line 114: 88
        line 115: 93
        line 108: 97
        line 118: 103
      LocalVariableTable:
        Start  Length  Slot  Name   Signature
           55      27     9     k   I
           38      50     8     j   I
           31      66     7 match   Z
           28      69     6 newLineSequence   [B
            0     105     0  this   Lorg/apache/commons/io/input/ReversedLinesFileReader$FilePart;
            0     105     1  data   [B
            0     105     2     i   I
      StackMapTable: number_of_entries = 7
        frame_type = 254 /* append */
          offset_delta = 15
          locals = [ class "[[B", int, int ]
        frame_type = 254 /* append */
          offset_delta = 22
          locals = [ class "[B", int, int ]
        frame_type = 255 /* full_frame */
          offset_delta = 39
          locals = [ class org/apache/commons/io/input/ReversedLinesFileReader$FilePart, class "[B", int, class "[[B", int, int, class "[B", int, int, int ]
          stack = [ int ]
        frame_type = 255 /* full_frame */
          offset_delta = 0
          locals = [ class org/apache/commons/io/input/ReversedLinesFileReader$FilePart, class "[B", int, class "[[B", int, int, class "[B", int, int, int ]
          stack = [ int, int ]
        frame_type = 249 /* chop */
          offset_delta = 8
        frame_type = 249 /* chop */
          offset_delta = 8
        frame_type = 248 /* chop */
          offset_delta = 5

  private java.lang.String readLine() throws java.io.IOException;
    descriptor: ()Ljava/lang/String;
    flags: (0x0002) ACC_PRIVATE
    Code:
      stack=5, locals=8, args_size=1
         0: aconst_null
         1: astore_1
         2: aload_0
         3: getfield      #6                  // Field no:J
         6: lconst_1
         7: lcmp
         8: ifne          15
        11: iconst_1
        12: goto          16
        15: iconst_0
        16: istore_3
        17: aload_0
        18: getfield      #17                 // Field currentLastBytePos:I
        21: istore        4
        23: iload         4
        25: iconst_m1
        26: if_icmple     189
        29: iload_3
        30: ifne          52
        33: iload         4
        35: aload_0
        36: getfield      #4                  // Field this$0:Lorg/apache/commons/io/input/ReversedLinesFileReader;
        39: invokestatic  #20                 // Method org/apache/commons/io/input/ReversedLinesFileReader.access$300:(Lorg/apache/commons/io/input/ReversedLinesFileReader;)I
        42: if_icmpge     52
        45: aload_0
        46: invokespecial #21                 // Method createLeftOver:()V
        49: goto          189
        52: aload_0
        53: aload_0
        54: getfield      #7                  // Field data:[B
        57: iload         4
        59: invokespecial #22                 // Method getNewLineMatchByteCount:([BI)I
        62: dup
        63: istore_2
        64: ifle          165
        67: iload         4
        69: iconst_1
        70: iadd
        71: istore        5
        73: aload_0
        74: getfield      #17                 // Field currentLastBytePos:I
        77: iload         5
        79: isub
        80: iconst_1
        81: iadd
        82: istore        6
        84: iload         6
        86: ifge          117
        89: new           #13                 // class java/lang/IllegalStateException
        92: dup
        93: new           #23                 // class java/lang/StringBuilder
        96: dup
        97: invokespecial #24                 // Method java/lang/StringBuilder."<init>":()V
       100: ldc           #25                 // String Unexpected negative line length=
       102: invokevirtual #26                 // Method java/lang/StringBuilder.append:(Ljava/lang/String;)Ljava/lang/StringBuilder;
       105: iload         6
       107: invokevirtual #27                 // Method java/lang/StringBuilder.append:(I)Ljava/lang/StringBuilder;
       110: invokevirtual #28                 // Method java/lang/StringBuilder.toString:()Ljava/lang/String;
       113: invokespecial #15                 // Method java/lang/IllegalStateException."<init>":(Ljava/lang/String;)V
       116: athrow
       117: iload         6
       119: newarray       byte
       121: astore        7
       123: aload_0
       124: getfield      #7                  // Field data:[B
       127: iload         5
       129: aload         7
       131: iconst_0
       132: iload         6
       134: invokestatic  #16                 // Method java/lang/System.arraycopy:(Ljava/lang/Object;ILjava/lang/Object;II)V
       137: new           #29                 // class java/lang/String
       140: dup
       141: aload         7
       143: aload_0
       144: getfield      #4                  // Field this$0:Lorg/apache/commons/io/input/ReversedLinesFileReader;
       147: invokestatic  #30                 // Method org/apache/commons/io/input/ReversedLinesFileReader.access$400:(Lorg/apache/commons/io/input/ReversedLinesFileReader;)Ljava/nio/charset/Charset;
       150: invokespecial #31                 // Method java/lang/String."<init>":([BLjava/nio/charset/Charset;)V
       153: astore_1
       154: aload_0
       155: iload         4
       157: iload_2
       158: isub
       159: putfield      #17                 // Field currentLastBytePos:I
       162: goto          189
       165: iload         4
       167: aload_0
       168: getfield      #4                  // Field this$0:Lorg/apache/commons/io/input/ReversedLinesFileReader;
       171: invokestatic  #32                 // Method org/apache/commons/io/input/ReversedLinesFileReader.access$500:(Lorg/apache/commons/io/input/ReversedLinesFileReader;)I
       174: isub
       175: istore        4
       177: iload         4
       179: ifge          23
       182: aload_0
       183: invokespecial #21                 // Method createLeftOver:()V
       186: goto          189
       189: iload_3
       190: ifeq          224
       193: aload_0
       194: getfield      #18                 // Field leftOver:[B
       197: ifnull        224
       200: new           #29                 // class java/lang/String
       203: dup
       204: aload_0
       205: getfield      #18                 // Field leftOver:[B
       208: aload_0
       209: getfield      #4                  // Field this$0:Lorg/apache/commons/io/input/ReversedLinesFileReader;
       212: invokestatic  #30                 // Method org/apache/commons/io/input/ReversedLinesFileReader.access$400:(Lorg/apache/commons/io/input/ReversedLinesFileReader;)Ljava/nio/charset/Charset;
       215: invokespecial #31                 // Method java/lang/String."<init>":([BLjava/nio/charset/Charset;)V
       218: astore_1
       219: aload_0
       220: aconst_null
       221: putfield      #18                 // Field leftOver:[B
       224: aload_1
       225: areturn
      LineNumberTable:
        line 129: 0
        line 132: 2
        line 134: 17
        line 135: 23
        line 137: 29
        line 140: 45
        line 141: 49
        line 145: 52
        line 146: 67
        line 147: 73
        line 149: 84
        line 150: 89
        line 152: 117
        line 153: 123
        line 155: 137
        line 157: 154
        line 158: 162
        line 162: 165
        line 165: 177
        line 166: 182
        line 167: 186
        line 172: 189
        line 174: 200
        line 175: 219
        line 178: 224
      LocalVariableTable:
        Start  Length  Slot  Name   Signature
           73      92     5 lineStart   I
           84      81     6 lineLengthBytes   I
          123      42     7 lineData   [B
           64     125     2 newLineMatchByteCount   I
            0     226     0  this   Lorg/apache/commons/io/input/ReversedLinesFileReader$FilePart;
            2     224     1  line   Ljava/lang/String;
           17     209     3 isLastFilePart   Z
           23     203     4     i   I
      StackMapTable: number_of_entries = 8
        frame_type = 252 /* append */
          offset_delta = 15
          locals = [ class java/lang/String ]
        frame_type = 64 /* same_locals_1_stack_item */
          stack = [ int ]
        frame_type = 254 /* append */
          offset_delta = 6
          locals = [ top, int, int ]
        frame_type = 28 /* same */
        frame_type = 255 /* full_frame */
          offset_delta = 64
          locals = [ class org/apache/commons/io/input/ReversedLinesFileReader$FilePart, class java/lang/String, int, int, int, int, int ]
          stack = []
        frame_type = 249 /* chop */
          offset_delta = 47
        frame_type = 255 /* full_frame */
          offset_delta = 23
          locals = [ class org/apache/commons/io/input/ReversedLinesFileReader$FilePart, class java/lang/String, top, int, int ]
          stack = []
        frame_type = 34 /* same */
    Exceptions:
      throws java.io.IOException

  private org.apache.commons.io.input.ReversedLinesFileReader$FilePart rollOver() throws java.io.IOException;
    descriptor: ()Lorg/apache/commons/io/input/ReversedLinesFileReader$FilePart;
    flags: (0x0002) ACC_PRIVATE
    Code:
      stack=7, locals=1, args_size=1
         0: aload_0
         1: getfield      #17                 // Field currentLastBytePos:I
         4: iconst_m1
         5: if_icmple     38
         8: new           #13                 // class java/lang/IllegalStateException
        11: dup
        12: new           #23                 // class java/lang/StringBuilder
        15: dup
        16: invokespecial #24                 // Method java/lang/StringBuilder."<init>":()V
        19: ldc           #33                 // String Current currentLastCharPos unexpectedly positive... last readLine() should have returned something! currentLastCharPos=
        21: invokevirtual #26                 // Method java/lang/StringBuilder.append:(Ljava/lang/String;)Ljava/lang/StringBuilder;
        24: aload_0
        25: getfield      #17                 // Field currentLastBytePos:I
        28: invokevirtual #27                 // Method java/lang/StringBuilder.append:(I)Ljava/lang/StringBuilder;
        31: invokevirtual #28                 // Method java/lang/StringBuilder.toString:()Ljava/lang/String;
        34: invokespecial #15                 // Method java/lang/IllegalStateException."<init>":(Ljava/lang/String;)V
        37: athrow
        38: aload_0
        39: getfield      #6                  // Field no:J
        42: lconst_1
        43: lcmp
        44: ifle          76
        47: new           #34                 // class org/apache/commons/io/input/ReversedLinesFileReader$FilePart
        50: dup
        51: aload_0
        52: getfield      #4                  // Field this$0:Lorg/apache/commons/io/input/ReversedLinesFileReader;
        55: aload_0
        56: getfield      #6                  // Field no:J
        59: lconst_1
        60: lsub
        61: aload_0
        62: getfield      #4                  // Field this$0:Lorg/apache/commons/io/input/ReversedLinesFileReader;
        65: invokestatic  #8                  // Method org/apache/commons/io/input/ReversedLinesFileReader.access$000:(Lorg/apache/commons/io/input/ReversedLinesFileReader;)I
        68: aload_0
        69: getfield      #18                 // Field leftOver:[B
        72: invokespecial #3                  // Method "<init>":(Lorg/apache/commons/io/input/ReversedLinesFileReader;JI[B)V
        75: areturn
        76: aload_0
        77: getfield      #18                 // Field leftOver:[B
        80: ifnull        127
        83: new           #13                 // class java/lang/IllegalStateException
        86: dup
        87: new           #23                 // class java/lang/StringBuilder
        90: dup
        91: invokespecial #24                 // Method java/lang/StringBuilder."<init>":()V
        94: ldc           #35                 // String Unexpected leftover of the last block: leftOverOfThisFilePart=
        96: invokevirtual #26                 // Method java/lang/StringBuilder.append:(Ljava/lang/String;)Ljava/lang/StringBuilder;
        99: new           #29                 // class java/lang/String
       102: dup
       103: aload_0
       104: getfield      #18                 // Field leftOver:[B
       107: aload_0
       108: getfield      #4                  // Field this$0:Lorg/apache/commons/io/input/ReversedLinesFileReader;
       111: invokestatic  #30                 // Method org/apache/commons/io/input/ReversedLinesFileReader.access$400:(Lorg/apache/commons/io/input/ReversedLinesFileReader;)Ljava/nio/charset/Charset;
       114: invokespecial #31                 // Method java/lang/String."<init>":([BLjava/nio/charset/Charset;)V
       117: invokevirtual #26                 // Method java/lang/StringBuilder.append:(Ljava/lang/String;)Ljava/lang/StringBuilder;
       120: invokevirtual #28                 // Method java/lang/StringBuilder.toString:()Ljava/lang/String;
       123: invokespecial #15                 // Method java/lang/IllegalStateException."<init>":(Ljava/lang/String;)V
       126: athrow
       127: aconst_null
       128: areturn
      LineNumberTable:
        line 189: 0
        line 190: 8
        line 194: 38
        line 195: 47
        line 198: 76
        line 199: 83
        line 200: 111
        line 202: 127
      LocalVariableTable:
        Start  Length  Slot  Name   Signature
            0     129     0  this   Lorg/apache/commons/io/input/ReversedLinesFileReader$FilePart;
      StackMapTable: number_of_entries = 3
        frame_type = 38 /* same */
        frame_type = 37 /* same */
        frame_type = 50 /* same */
    Exceptions:
      throws java.io.IOException

  org.apache.commons.io.input.ReversedLinesFileReader$FilePart(org.apache.commons.io.input.ReversedLinesFileReader, long, int, byte[], org.apache.commons.io.input.ReversedLinesFileReader$1) throws java.io.IOException;
    descriptor: (Lorg/apache/commons/io/input/ReversedLinesFileReader;JI[BLorg/apache/commons/io/input/ReversedLinesFileReader$1;)V
    flags: (0x1000) ACC_SYNTHETIC
    Code:
      stack=6, locals=7, args_size=6
         0: aload_0
         1: aload_1
         2: lload_2
         3: iload         4
         5: aload         5
         7: invokespecial #3                  // Method "<init>":(Lorg/apache/commons/io/input/ReversedLinesFileReader;JI[B)V
        10: return
      LineNumberTable:
        line 46: 0
      LocalVariableTable:
        Start  Length  Slot  Name   Signature
            0      11     0  this   Lorg/apache/commons/io/input/ReversedLinesFileReader$FilePart;
            0      11     1    x0   Lorg/apache/commons/io/input/ReversedLinesFileReader;
            0      11     2    x1   J
            0      11     4    x2   I
            0      11     5    x3   [B
            0      11     6    x4   Lorg/apache/commons/io/input/ReversedLinesFileReader$1;
    Exceptions:
      throws java.io.IOException

  static java.lang.String access$700(org.apache.commons.io.input.ReversedLinesFileReader$FilePart) throws java.io.IOException;
    descriptor: (Lorg/apache/commons/io/input/ReversedLinesFileReader$FilePart;)Ljava/lang/String;
    flags: (0x1008) ACC_STATIC, ACC_SYNTHETIC
    Code:
      stack=1, locals=1, args_size=1
         0: aload_0
         1: invokespecial #2                  // Method readLine:()Ljava/lang/String;
         4: areturn
      LineNumberTable:
        line 46: 0
      LocalVariableTable:
        Start  Length  Slot  Name   Signature
            0       5     0    x0   Lorg/apache/commons/io/input/ReversedLinesFileReader$FilePart;
    Exceptions:
      throws java.io.IOException

  static org.apache.commons.io.input.ReversedLinesFileReader$FilePart access$800(org.apache.commons.io.input.ReversedLinesFileReader$FilePart) throws java.io.IOException;
    descriptor: (Lorg/apache/commons/io/input/ReversedLinesFileReader$FilePart;)Lorg/apache/commons/io/input/ReversedLinesFileReader$FilePart;
    flags: (0x1008) ACC_STATIC, ACC_SYNTHETIC
    Code:
      stack=1, locals=1, args_size=1
         0: aload_0
         1: invokespecial #1                  // Method rollOver:()Lorg/apache/commons/io/input/ReversedLinesFileReader$FilePart;
         4: areturn
      LineNumberTable:
        line 46: 0
      LocalVariableTable:
        Start  Length  Slot  Name   Signature
            0       5     0    x0   Lorg/apache/commons/io/input/ReversedLinesFileReader$FilePart;
    Exceptions:
      throws java.io.IOException
}
SourceFile: "ReversedLinesFileReader.java"
InnerClasses:
  private #53= #34 of #110;               // FilePart=class org/apache/commons/io/input/ReversedLinesFileReader$FilePart of class org/apache/commons/io/input/ReversedLinesFileReader
  static #89;                             // class org/apache/commons/io/input/ReversedLinesFileReader$1
