Classfile /Users/mw/Projects/slang-braindump/.jar/jar11/assemble/slang-braindump/assemble/content/org/apache/commons/io/input/TailerListenerAdapter.class
  Last modified May 29, 2022; size 1028 bytes
  SHA-256 checksum ef031113765399f766ea5b9aa1036d7e9e486b4b96b4166337718b677f1d8fb7
  Compiled from "TailerListenerAdapter.java"
public class org.apache.commons.io.input.TailerListenerAdapter implements org.apache.commons.io.input.TailerListener
  minor version: 0
  major version: 52
  flags: (0x0021) ACC_PUBLIC, ACC_SUPER
  this_class: #2                          // org/apache/commons/io/input/TailerListenerAdapter
  super_class: #3                         // java/lang/Object
  interfaces: 1, fields: 0, methods: 7, attributes: 1
Constant pool:
   #1 = Methodref          #3.#28         // java/lang/Object."<init>":()V
   #2 = Class              #29            // org/apache/commons/io/input/TailerListenerAdapter
   #3 = Class              #30            // java/lang/Object
   #4 = Class              #31            // org/apache/commons/io/input/TailerListener
   #5 = Utf8               <init>
   #6 = Utf8               ()V
   #7 = Utf8               Code
   #8 = Utf8               LineNumberTable
   #9 = Utf8               LocalVariableTable
  #10 = Utf8               this
  #11 = Utf8               Lorg/apache/commons/io/input/TailerListenerAdapter;
  #12 = Utf8               init
  #13 = Utf8               (Lorg/apache/commons/io/input/Tailer;)V
  #14 = Utf8               tailer
  #15 = Utf8               Lorg/apache/commons/io/input/Tailer;
  #16 = Utf8               fileNotFound
  #17 = Utf8               fileRotated
  #18 = Utf8               handle
  #19 = Utf8               (Ljava/lang/String;)V
  #20 = Utf8               line
  #21 = Utf8               Ljava/lang/String;
  #22 = Utf8               (Ljava/lang/Exception;)V
  #23 = Utf8               ex
  #24 = Utf8               Ljava/lang/Exception;
  #25 = Utf8               endOfFileReached
  #26 = Utf8               SourceFile
  #27 = Utf8               TailerListenerAdapter.java
  #28 = NameAndType        #5:#6          // "<init>":()V
  #29 = Utf8               org/apache/commons/io/input/TailerListenerAdapter
  #30 = Utf8               java/lang/Object
  #31 = Utf8               org/apache/commons/io/input/TailerListener
{
  public org.apache.commons.io.input.TailerListenerAdapter();
    descriptor: ()V
    flags: (0x0001) ACC_PUBLIC
    Code:
      stack=1, locals=1, args_size=1
         0: aload_0
         1: invokespecial #1                  // Method java/lang/Object."<init>":()V
         4: return
      LineNumberTable:
        line 24: 0
      LocalVariableTable:
        Start  Length  Slot  Name   Signature
            0       5     0  this   Lorg/apache/commons/io/input/TailerListenerAdapter;

  public void init(org.apache.commons.io.input.Tailer);
    descriptor: (Lorg/apache/commons/io/input/Tailer;)V
    flags: (0x0001) ACC_PUBLIC
    Code:
      stack=0, locals=2, args_size=2
         0: return
      LineNumberTable:
        line 34: 0
      LocalVariableTable:
        Start  Length  Slot  Name   Signature
            0       1     0  this   Lorg/apache/commons/io/input/TailerListenerAdapter;
            0       1     1 tailer   Lorg/apache/commons/io/input/Tailer;

  public void fileNotFound();
    descriptor: ()V
    flags: (0x0001) ACC_PUBLIC
    Code:
      stack=0, locals=1, args_size=1
         0: return
      LineNumberTable:
        line 42: 0
      LocalVariableTable:
        Start  Length  Slot  Name   Signature
            0       1     0  this   Lorg/apache/commons/io/input/TailerListenerAdapter;

  public void fileRotated();
    descriptor: ()V
    flags: (0x0001) ACC_PUBLIC
    Code:
      stack=0, locals=1, args_size=1
         0: return
      LineNumberTable:
        line 53: 0
      LocalVariableTable:
        Start  Length  Slot  Name   Signature
            0       1     0  this   Lorg/apache/commons/io/input/TailerListenerAdapter;

  public void handle(java.lang.String);
    descriptor: (Ljava/lang/String;)V
    flags: (0x0001) ACC_PUBLIC
    Code:
      stack=0, locals=2, args_size=2
         0: return
      LineNumberTable:
        line 62: 0
      LocalVariableTable:
        Start  Length  Slot  Name   Signature
            0       1     0  this   Lorg/apache/commons/io/input/TailerListenerAdapter;
            0       1     1  line   Ljava/lang/String;

  public void handle(java.lang.Exception);
    descriptor: (Ljava/lang/Exception;)V
    flags: (0x0001) ACC_PUBLIC
    Code:
      stack=0, locals=2, args_size=2
         0: return
      LineNumberTable:
        line 71: 0
      LocalVariableTable:
        Start  Length  Slot  Name   Signature
            0       1     0  this   Lorg/apache/commons/io/input/TailerListenerAdapter;
            0       1     1    ex   Ljava/lang/Exception;

  public void endOfFileReached();
    descriptor: ()V
    flags: (0x0001) ACC_PUBLIC
    Code:
      stack=0, locals=1, args_size=1
         0: return
      LineNumberTable:
        line 85: 0
      LocalVariableTable:
        Start  Length  Slot  Name   Signature
            0       1     0  this   Lorg/apache/commons/io/input/TailerListenerAdapter;
}
SourceFile: "TailerListenerAdapter.java"
