Classfile /Users/mw/Projects/slang-braindump/.jar/jar11/assemble/slang-braindump/assemble/content/com/fasterxml/jackson/core/json/JsonGeneratorImpl.class
  Last modified May 29, 2022; size 5591 bytes
  SHA-256 checksum 5a77916e731ddec3acbb6a889dfeb52976e350b2ab5f4ee53abd057ceacc1902
  Compiled from "JsonGeneratorImpl.java"
public abstract class com.fasterxml.jackson.core.json.JsonGeneratorImpl extends com.fasterxml.jackson.core.base.GeneratorBase
  minor version: 0
  major version: 50
  flags: (0x0421) ACC_PUBLIC, ACC_SUPER, ACC_ABSTRACT
  this_class: #38                         // com/fasterxml/jackson/core/json/JsonGeneratorImpl
  super_class: #39                        // com/fasterxml/jackson/core/base/GeneratorBase
  interfaces: 0, fields: 8, methods: 14, attributes: 2
Constant pool:
    #1 = Methodref          #39.#115      // com/fasterxml/jackson/core/base/GeneratorBase."<init>":(ILcom/fasterxml/jackson/core/ObjectCodec;)V
    #2 = Fieldref           #38.#116      // com/fasterxml/jackson/core/json/JsonGeneratorImpl.sOutputEscapes:[I
    #3 = Fieldref           #38.#117      // com/fasterxml/jackson/core/json/JsonGeneratorImpl._outputEscapes:[I
    #4 = Fieldref           #118.#119     // com/fasterxml/jackson/core/util/DefaultPrettyPrinter.DEFAULT_ROOT_VALUE_SEPARATOR:Lcom/fasterxml/jackson/core/io/SerializedString;
    #5 = Fieldref           #38.#120      // com/fasterxml/jackson/core/json/JsonGeneratorImpl._rootValueSeparator:Lcom/fasterxml/jackson/core/SerializableString;
    #6 = Fieldref           #38.#121      // com/fasterxml/jackson/core/json/JsonGeneratorImpl._ioContext:Lcom/fasterxml/jackson/core/io/IOContext;
    #7 = Fieldref           #75.#122      // com/fasterxml/jackson/core/JsonGenerator$Feature.ESCAPE_NON_ASCII:Lcom/fasterxml/jackson/core/JsonGenerator$Feature;
    #8 = Methodref          #75.#123      // com/fasterxml/jackson/core/JsonGenerator$Feature.enabledIn:(I)Z
    #9 = Fieldref           #38.#124      // com/fasterxml/jackson/core/json/JsonGeneratorImpl._maximumNonEscapedChar:I
   #10 = Fieldref           #75.#125      // com/fasterxml/jackson/core/JsonGenerator$Feature.QUOTE_FIELD_NAMES:Lcom/fasterxml/jackson/core/JsonGenerator$Feature;
   #11 = Fieldref           #38.#126      // com/fasterxml/jackson/core/json/JsonGeneratorImpl._cfgUnqNames:Z
   #12 = Methodref          #32.#127      // java/lang/Object.getClass:()Ljava/lang/Class;
   #13 = Methodref          #128.#129     // com/fasterxml/jackson/core/util/VersionUtil.versionFor:(Ljava/lang/Class;)Lcom/fasterxml/jackson/core/Version;
   #14 = Methodref          #39.#130      // com/fasterxml/jackson/core/base/GeneratorBase.enable:(Lcom/fasterxml/jackson/core/JsonGenerator$Feature;)Lcom/fasterxml/jackson/core/JsonGenerator;
   #15 = Methodref          #39.#131      // com/fasterxml/jackson/core/base/GeneratorBase.disable:(Lcom/fasterxml/jackson/core/JsonGenerator$Feature;)Lcom/fasterxml/jackson/core/JsonGenerator;
   #16 = Methodref          #39.#132      // com/fasterxml/jackson/core/base/GeneratorBase._checkStdFeatureChanges:(II)V
   #17 = Fieldref           #38.#133      // com/fasterxml/jackson/core/json/JsonGeneratorImpl._characterEscapes:Lcom/fasterxml/jackson/core/io/CharacterEscapes;
   #18 = Methodref          #134.#135     // com/fasterxml/jackson/core/io/CharacterEscapes.getEscapeCodesForAscii:()[I
   #19 = Fieldref           #38.#136      // com/fasterxml/jackson/core/json/JsonGeneratorImpl.JSON_WRITE_CAPABILITIES:Lcom/fasterxml/jackson/core/util/JacksonFeatureSet;
   #20 = Fieldref           #38.#137      // com/fasterxml/jackson/core/json/JsonGeneratorImpl._cfgPrettyPrinter:Lcom/fasterxml/jackson/core/PrettyPrinter;
   #21 = InterfaceMethodref #138.#139     // com/fasterxml/jackson/core/PrettyPrinter.writeArrayValueSeparator:(Lcom/fasterxml/jackson/core/JsonGenerator;)V
   #22 = InterfaceMethodref #138.#140     // com/fasterxml/jackson/core/PrettyPrinter.writeObjectFieldValueSeparator:(Lcom/fasterxml/jackson/core/JsonGenerator;)V
   #23 = InterfaceMethodref #138.#141     // com/fasterxml/jackson/core/PrettyPrinter.writeRootValueSeparator:(Lcom/fasterxml/jackson/core/JsonGenerator;)V
   #24 = Fieldref           #38.#142      // com/fasterxml/jackson/core/json/JsonGeneratorImpl._writeContext:Lcom/fasterxml/jackson/core/json/JsonWriteContext;
   #25 = Methodref          #143.#144     // com/fasterxml/jackson/core/json/JsonWriteContext.inArray:()Z
   #26 = InterfaceMethodref #138.#145     // com/fasterxml/jackson/core/PrettyPrinter.beforeArrayValues:(Lcom/fasterxml/jackson/core/JsonGenerator;)V
   #27 = Methodref          #143.#146     // com/fasterxml/jackson/core/json/JsonWriteContext.inObject:()Z
   #28 = InterfaceMethodref #138.#147     // com/fasterxml/jackson/core/PrettyPrinter.beforeObjectEntries:(Lcom/fasterxml/jackson/core/JsonGenerator;)V
   #29 = Methodref          #38.#148      // com/fasterxml/jackson/core/json/JsonGeneratorImpl._reportCantWriteValueExpectName:(Ljava/lang/String;)V
   #30 = Methodref          #38.#149      // com/fasterxml/jackson/core/json/JsonGeneratorImpl._throwInternal:()V
   #31 = String             #150          // Can not %s, expecting field name (context: %s)
   #32 = Class              #151          // java/lang/Object
   #33 = Methodref          #143.#152     // com/fasterxml/jackson/core/json/JsonWriteContext.typeDesc:()Ljava/lang/String;
   #34 = Methodref          #153.#154     // java/lang/String.format:(Ljava/lang/String;[Ljava/lang/Object;)Ljava/lang/String;
   #35 = Methodref          #38.#155      // com/fasterxml/jackson/core/json/JsonGeneratorImpl._reportError:(Ljava/lang/String;)V
   #36 = Methodref          #156.#157     // com/fasterxml/jackson/core/io/CharTypes.get7BitOutputEscapes:()[I
   #37 = Fieldref           #38.#158      // com/fasterxml/jackson/core/json/JsonGeneratorImpl.DEFAULT_TEXTUAL_WRITE_CAPABILITIES:Lcom/fasterxml/jackson/core/util/JacksonFeatureSet;
   #38 = Class              #159          // com/fasterxml/jackson/core/json/JsonGeneratorImpl
   #39 = Class              #160          // com/fasterxml/jackson/core/base/GeneratorBase
   #40 = Utf8               sOutputEscapes
   #41 = Utf8               [I
   #42 = Utf8               JSON_WRITE_CAPABILITIES
   #43 = Utf8               Lcom/fasterxml/jackson/core/util/JacksonFeatureSet;
   #44 = Utf8               Signature
   #45 = Utf8               Lcom/fasterxml/jackson/core/util/JacksonFeatureSet<Lcom/fasterxml/jackson/core/StreamWriteCapability;>;
   #46 = Utf8               _ioContext
   #47 = Utf8               Lcom/fasterxml/jackson/core/io/IOContext;
   #48 = Utf8               _outputEscapes
   #49 = Utf8               _maximumNonEscapedChar
   #50 = Utf8               I
   #51 = Utf8               _characterEscapes
   #52 = Utf8               Lcom/fasterxml/jackson/core/io/CharacterEscapes;
   #53 = Utf8               _rootValueSeparator
   #54 = Utf8               Lcom/fasterxml/jackson/core/SerializableString;
   #55 = Utf8               _cfgUnqNames
   #56 = Utf8               Z
   #57 = Utf8               <init>
   #58 = Utf8               (Lcom/fasterxml/jackson/core/io/IOContext;ILcom/fasterxml/jackson/core/ObjectCodec;)V
   #59 = Utf8               Code
   #60 = Utf8               LineNumberTable
   #61 = Utf8               LocalVariableTable
   #62 = Utf8               this
   #63 = Utf8               Lcom/fasterxml/jackson/core/json/JsonGeneratorImpl;
   #64 = Utf8               ctxt
   #65 = Utf8               features
   #66 = Utf8               codec
   #67 = Utf8               Lcom/fasterxml/jackson/core/ObjectCodec;
   #68 = Utf8               StackMapTable
   #69 = Class              #159          // com/fasterxml/jackson/core/json/JsonGeneratorImpl
   #70 = Class              #161          // com/fasterxml/jackson/core/io/IOContext
   #71 = Class              #162          // com/fasterxml/jackson/core/ObjectCodec
   #72 = Utf8               version
   #73 = Utf8               ()Lcom/fasterxml/jackson/core/Version;
   #74 = Utf8               enable
   #75 = Class              #164          // com/fasterxml/jackson/core/JsonGenerator$Feature
   #76 = Utf8               Feature
   #77 = Utf8               InnerClasses
   #78 = Utf8               (Lcom/fasterxml/jackson/core/JsonGenerator$Feature;)Lcom/fasterxml/jackson/core/JsonGenerator;
   #79 = Utf8               f
   #80 = Utf8               Lcom/fasterxml/jackson/core/JsonGenerator$Feature;
   #81 = Utf8               disable
   #82 = Utf8               _checkStdFeatureChanges
   #83 = Utf8               (II)V
   #84 = Utf8               newFeatureFlags
   #85 = Utf8               changedFeatures
   #86 = Utf8               setHighestNonEscapedChar
   #87 = Utf8               (I)Lcom/fasterxml/jackson/core/JsonGenerator;
   #88 = Utf8               charCode
   #89 = Utf8               getHighestEscapedChar
   #90 = Utf8               ()I
   #91 = Utf8               setCharacterEscapes
   #92 = Utf8               (Lcom/fasterxml/jackson/core/io/CharacterEscapes;)Lcom/fasterxml/jackson/core/JsonGenerator;
   #93 = Utf8               esc
   #94 = Utf8               getCharacterEscapes
   #95 = Utf8               ()Lcom/fasterxml/jackson/core/io/CharacterEscapes;
   #96 = Utf8               setRootValueSeparator
   #97 = Utf8               (Lcom/fasterxml/jackson/core/SerializableString;)Lcom/fasterxml/jackson/core/JsonGenerator;
   #98 = Utf8               sep
   #99 = Utf8               getWriteCapabilities
  #100 = Utf8               ()Lcom/fasterxml/jackson/core/util/JacksonFeatureSet;
  #101 = Utf8               ()Lcom/fasterxml/jackson/core/util/JacksonFeatureSet<Lcom/fasterxml/jackson/core/StreamWriteCapability;>;
  #102 = Utf8               _verifyPrettyValueWrite
  #103 = Utf8               (Ljava/lang/String;I)V
  #104 = Utf8               typeMsg
  #105 = Utf8               Ljava/lang/String;
  #106 = Utf8               status
  #107 = Utf8               Exceptions
  #108 = Class              #165          // java/io/IOException
  #109 = Utf8               _reportCantWriteValueExpectName
  #110 = Utf8               (Ljava/lang/String;)V
  #111 = Utf8               <clinit>
  #112 = Utf8               ()V
  #113 = Utf8               SourceFile
  #114 = Utf8               JsonGeneratorImpl.java
  #115 = NameAndType        #57:#166      // "<init>":(ILcom/fasterxml/jackson/core/ObjectCodec;)V
  #116 = NameAndType        #40:#41       // sOutputEscapes:[I
  #117 = NameAndType        #48:#41       // _outputEscapes:[I
  #118 = Class              #167          // com/fasterxml/jackson/core/util/DefaultPrettyPrinter
  #119 = NameAndType        #168:#169     // DEFAULT_ROOT_VALUE_SEPARATOR:Lcom/fasterxml/jackson/core/io/SerializedString;
  #120 = NameAndType        #53:#54       // _rootValueSeparator:Lcom/fasterxml/jackson/core/SerializableString;
  #121 = NameAndType        #46:#47       // _ioContext:Lcom/fasterxml/jackson/core/io/IOContext;
  #122 = NameAndType        #170:#80      // ESCAPE_NON_ASCII:Lcom/fasterxml/jackson/core/JsonGenerator$Feature;
  #123 = NameAndType        #171:#172     // enabledIn:(I)Z
  #124 = NameAndType        #49:#50       // _maximumNonEscapedChar:I
  #125 = NameAndType        #173:#80      // QUOTE_FIELD_NAMES:Lcom/fasterxml/jackson/core/JsonGenerator$Feature;
  #126 = NameAndType        #55:#56       // _cfgUnqNames:Z
  #127 = NameAndType        #174:#175     // getClass:()Ljava/lang/Class;
  #128 = Class              #176          // com/fasterxml/jackson/core/util/VersionUtil
  #129 = NameAndType        #177:#178     // versionFor:(Ljava/lang/Class;)Lcom/fasterxml/jackson/core/Version;
  #130 = NameAndType        #74:#78       // enable:(Lcom/fasterxml/jackson/core/JsonGenerator$Feature;)Lcom/fasterxml/jackson/core/JsonGenerator;
  #131 = NameAndType        #81:#78       // disable:(Lcom/fasterxml/jackson/core/JsonGenerator$Feature;)Lcom/fasterxml/jackson/core/JsonGenerator;
  #132 = NameAndType        #82:#83       // _checkStdFeatureChanges:(II)V
  #133 = NameAndType        #51:#52       // _characterEscapes:Lcom/fasterxml/jackson/core/io/CharacterEscapes;
  #134 = Class              #179          // com/fasterxml/jackson/core/io/CharacterEscapes
  #135 = NameAndType        #180:#181     // getEscapeCodesForAscii:()[I
  #136 = NameAndType        #42:#43       // JSON_WRITE_CAPABILITIES:Lcom/fasterxml/jackson/core/util/JacksonFeatureSet;
  #137 = NameAndType        #182:#183     // _cfgPrettyPrinter:Lcom/fasterxml/jackson/core/PrettyPrinter;
  #138 = Class              #184          // com/fasterxml/jackson/core/PrettyPrinter
  #139 = NameAndType        #185:#186     // writeArrayValueSeparator:(Lcom/fasterxml/jackson/core/JsonGenerator;)V
  #140 = NameAndType        #187:#186     // writeObjectFieldValueSeparator:(Lcom/fasterxml/jackson/core/JsonGenerator;)V
  #141 = NameAndType        #188:#186     // writeRootValueSeparator:(Lcom/fasterxml/jackson/core/JsonGenerator;)V
  #142 = NameAndType        #189:#190     // _writeContext:Lcom/fasterxml/jackson/core/json/JsonWriteContext;
  #143 = Class              #191          // com/fasterxml/jackson/core/json/JsonWriteContext
  #144 = NameAndType        #192:#193     // inArray:()Z
  #145 = NameAndType        #194:#186     // beforeArrayValues:(Lcom/fasterxml/jackson/core/JsonGenerator;)V
  #146 = NameAndType        #195:#193     // inObject:()Z
  #147 = NameAndType        #196:#186     // beforeObjectEntries:(Lcom/fasterxml/jackson/core/JsonGenerator;)V
  #148 = NameAndType        #109:#110     // _reportCantWriteValueExpectName:(Ljava/lang/String;)V
  #149 = NameAndType        #197:#112     // _throwInternal:()V
  #150 = Utf8               Can not %s, expecting field name (context: %s)
  #151 = Utf8               java/lang/Object
  #152 = NameAndType        #198:#199     // typeDesc:()Ljava/lang/String;
  #153 = Class              #200          // java/lang/String
  #154 = NameAndType        #201:#202     // format:(Ljava/lang/String;[Ljava/lang/Object;)Ljava/lang/String;
  #155 = NameAndType        #203:#110     // _reportError:(Ljava/lang/String;)V
  #156 = Class              #204          // com/fasterxml/jackson/core/io/CharTypes
  #157 = NameAndType        #205:#181     // get7BitOutputEscapes:()[I
  #158 = NameAndType        #206:#43      // DEFAULT_TEXTUAL_WRITE_CAPABILITIES:Lcom/fasterxml/jackson/core/util/JacksonFeatureSet;
  #159 = Utf8               com/fasterxml/jackson/core/json/JsonGeneratorImpl
  #160 = Utf8               com/fasterxml/jackson/core/base/GeneratorBase
  #161 = Utf8               com/fasterxml/jackson/core/io/IOContext
  #162 = Utf8               com/fasterxml/jackson/core/ObjectCodec
  #163 = Class              #207          // com/fasterxml/jackson/core/JsonGenerator
  #164 = Utf8               com/fasterxml/jackson/core/JsonGenerator$Feature
  #165 = Utf8               java/io/IOException
  #166 = Utf8               (ILcom/fasterxml/jackson/core/ObjectCodec;)V
  #167 = Utf8               com/fasterxml/jackson/core/util/DefaultPrettyPrinter
  #168 = Utf8               DEFAULT_ROOT_VALUE_SEPARATOR
  #169 = Utf8               Lcom/fasterxml/jackson/core/io/SerializedString;
  #170 = Utf8               ESCAPE_NON_ASCII
  #171 = Utf8               enabledIn
  #172 = Utf8               (I)Z
  #173 = Utf8               QUOTE_FIELD_NAMES
  #174 = Utf8               getClass
  #175 = Utf8               ()Ljava/lang/Class;
  #176 = Utf8               com/fasterxml/jackson/core/util/VersionUtil
  #177 = Utf8               versionFor
  #178 = Utf8               (Ljava/lang/Class;)Lcom/fasterxml/jackson/core/Version;
  #179 = Utf8               com/fasterxml/jackson/core/io/CharacterEscapes
  #180 = Utf8               getEscapeCodesForAscii
  #181 = Utf8               ()[I
  #182 = Utf8               _cfgPrettyPrinter
  #183 = Utf8               Lcom/fasterxml/jackson/core/PrettyPrinter;
  #184 = Utf8               com/fasterxml/jackson/core/PrettyPrinter
  #185 = Utf8               writeArrayValueSeparator
  #186 = Utf8               (Lcom/fasterxml/jackson/core/JsonGenerator;)V
  #187 = Utf8               writeObjectFieldValueSeparator
  #188 = Utf8               writeRootValueSeparator
  #189 = Utf8               _writeContext
  #190 = Utf8               Lcom/fasterxml/jackson/core/json/JsonWriteContext;
  #191 = Utf8               com/fasterxml/jackson/core/json/JsonWriteContext
  #192 = Utf8               inArray
  #193 = Utf8               ()Z
  #194 = Utf8               beforeArrayValues
  #195 = Utf8               inObject
  #196 = Utf8               beforeObjectEntries
  #197 = Utf8               _throwInternal
  #198 = Utf8               typeDesc
  #199 = Utf8               ()Ljava/lang/String;
  #200 = Utf8               java/lang/String
  #201 = Utf8               format
  #202 = Utf8               (Ljava/lang/String;[Ljava/lang/Object;)Ljava/lang/String;
  #203 = Utf8               _reportError
  #204 = Utf8               com/fasterxml/jackson/core/io/CharTypes
  #205 = Utf8               get7BitOutputEscapes
  #206 = Utf8               DEFAULT_TEXTUAL_WRITE_CAPABILITIES
  #207 = Utf8               com/fasterxml/jackson/core/JsonGenerator
{
  protected static final int[] sOutputEscapes;
    descriptor: [I
    flags: (0x001c) ACC_PROTECTED, ACC_STATIC, ACC_FINAL

  protected static final com.fasterxml.jackson.core.util.JacksonFeatureSet<com.fasterxml.jackson.core.StreamWriteCapability> JSON_WRITE_CAPABILITIES;
    descriptor: Lcom/fasterxml/jackson/core/util/JacksonFeatureSet;
    flags: (0x001c) ACC_PROTECTED, ACC_STATIC, ACC_FINAL
    Signature: #45                          // Lcom/fasterxml/jackson/core/util/JacksonFeatureSet<Lcom/fasterxml/jackson/core/StreamWriteCapability;>;

  protected final com.fasterxml.jackson.core.io.IOContext _ioContext;
    descriptor: Lcom/fasterxml/jackson/core/io/IOContext;
    flags: (0x0014) ACC_PROTECTED, ACC_FINAL

  protected int[] _outputEscapes;
    descriptor: [I
    flags: (0x0004) ACC_PROTECTED

  protected int _maximumNonEscapedChar;
    descriptor: I
    flags: (0x0004) ACC_PROTECTED

  protected com.fasterxml.jackson.core.io.CharacterEscapes _characterEscapes;
    descriptor: Lcom/fasterxml/jackson/core/io/CharacterEscapes;
    flags: (0x0004) ACC_PROTECTED

  protected com.fasterxml.jackson.core.SerializableString _rootValueSeparator;
    descriptor: Lcom/fasterxml/jackson/core/SerializableString;
    flags: (0x0004) ACC_PROTECTED

  protected boolean _cfgUnqNames;
    descriptor: Z
    flags: (0x0004) ACC_PROTECTED

  public com.fasterxml.jackson.core.json.JsonGeneratorImpl(com.fasterxml.jackson.core.io.IOContext, int, com.fasterxml.jackson.core.ObjectCodec);
    descriptor: (Lcom/fasterxml/jackson/core/io/IOContext;ILcom/fasterxml/jackson/core/ObjectCodec;)V
    flags: (0x0001) ACC_PUBLIC
    Code:
      stack=3, locals=4, args_size=4
         0: aload_0
         1: iload_2
         2: aload_3
         3: invokespecial #1                  // Method com/fasterxml/jackson/core/base/GeneratorBase."<init>":(ILcom/fasterxml/jackson/core/ObjectCodec;)V
         6: aload_0
         7: getstatic     #2                  // Field sOutputEscapes:[I
        10: putfield      #3                  // Field _outputEscapes:[I
        13: aload_0
        14: getstatic     #4                  // Field com/fasterxml/jackson/core/util/DefaultPrettyPrinter.DEFAULT_ROOT_VALUE_SEPARATOR:Lcom/fasterxml/jackson/core/io/SerializedString;
        17: putfield      #5                  // Field _rootValueSeparator:Lcom/fasterxml/jackson/core/SerializableString;
        20: aload_0
        21: aload_1
        22: putfield      #6                  // Field _ioContext:Lcom/fasterxml/jackson/core/io/IOContext;
        25: getstatic     #7                  // Field com/fasterxml/jackson/core/JsonGenerator$Feature.ESCAPE_NON_ASCII:Lcom/fasterxml/jackson/core/JsonGenerator$Feature;
        28: iload_2
        29: invokevirtual #8                  // Method com/fasterxml/jackson/core/JsonGenerator$Feature.enabledIn:(I)Z
        32: ifeq          41
        35: aload_0
        36: bipush        127
        38: putfield      #9                  // Field _maximumNonEscapedChar:I
        41: aload_0
        42: getstatic     #10                 // Field com/fasterxml/jackson/core/JsonGenerator$Feature.QUOTE_FIELD_NAMES:Lcom/fasterxml/jackson/core/JsonGenerator$Feature;
        45: iload_2
        46: invokevirtual #8                  // Method com/fasterxml/jackson/core/JsonGenerator$Feature.enabledIn:(I)Z
        49: ifne          56
        52: iconst_1
        53: goto          57
        56: iconst_0
        57: putfield      #11                 // Field _cfgUnqNames:Z
        60: return
      LineNumberTable:
        line 114: 0
        line 63: 6
        line 94: 13
        line 115: 20
        line 116: 25
        line 118: 35
        line 120: 41
        line 121: 60
      LocalVariableTable:
        Start  Length  Slot  Name   Signature
            0      61     0  this   Lcom/fasterxml/jackson/core/json/JsonGeneratorImpl;
            0      61     1  ctxt   Lcom/fasterxml/jackson/core/io/IOContext;
            0      61     2 features   I
            0      61     3 codec   Lcom/fasterxml/jackson/core/ObjectCodec;
      StackMapTable: number_of_entries = 3
        frame_type = 255 /* full_frame */
          offset_delta = 41
          locals = [ class com/fasterxml/jackson/core/json/JsonGeneratorImpl, class com/fasterxml/jackson/core/io/IOContext, int, class com/fasterxml/jackson/core/ObjectCodec ]
          stack = []
        frame_type = 78 /* same_locals_1_stack_item */
          stack = [ class com/fasterxml/jackson/core/json/JsonGeneratorImpl ]
        frame_type = 255 /* full_frame */
          offset_delta = 0
          locals = [ class com/fasterxml/jackson/core/json/JsonGeneratorImpl, class com/fasterxml/jackson/core/io/IOContext, int, class com/fasterxml/jackson/core/ObjectCodec ]
          stack = [ class com/fasterxml/jackson/core/json/JsonGeneratorImpl, int ]

  public com.fasterxml.jackson.core.Version version();
    descriptor: ()Lcom/fasterxml/jackson/core/Version;
    flags: (0x0001) ACC_PUBLIC
    Code:
      stack=1, locals=1, args_size=1
         0: aload_0
         1: invokevirtual #12                 // Method java/lang/Object.getClass:()Ljava/lang/Class;
         4: invokestatic  #13                 // Method com/fasterxml/jackson/core/util/VersionUtil.versionFor:(Ljava/lang/Class;)Lcom/fasterxml/jackson/core/Version;
         7: areturn
      LineNumberTable:
        line 131: 0
      LocalVariableTable:
        Start  Length  Slot  Name   Signature
            0       8     0  this   Lcom/fasterxml/jackson/core/json/JsonGeneratorImpl;

  public com.fasterxml.jackson.core.JsonGenerator enable(com.fasterxml.jackson.core.JsonGenerator$Feature);
    descriptor: (Lcom/fasterxml/jackson/core/JsonGenerator$Feature;)Lcom/fasterxml/jackson/core/JsonGenerator;
    flags: (0x0001) ACC_PUBLIC
    Code:
      stack=2, locals=2, args_size=2
         0: aload_0
         1: aload_1
         2: invokespecial #14                 // Method com/fasterxml/jackson/core/base/GeneratorBase.enable:(Lcom/fasterxml/jackson/core/JsonGenerator$Feature;)Lcom/fasterxml/jackson/core/JsonGenerator;
         5: pop
         6: aload_1
         7: getstatic     #10                 // Field com/fasterxml/jackson/core/JsonGenerator$Feature.QUOTE_FIELD_NAMES:Lcom/fasterxml/jackson/core/JsonGenerator$Feature;
        10: if_acmpne     18
        13: aload_0
        14: iconst_0
        15: putfield      #11                 // Field _cfgUnqNames:Z
        18: aload_0
        19: areturn
      LineNumberTable:
        line 143: 0
        line 144: 6
        line 145: 13
        line 147: 18
      LocalVariableTable:
        Start  Length  Slot  Name   Signature
            0      20     0  this   Lcom/fasterxml/jackson/core/json/JsonGeneratorImpl;
            0      20     1     f   Lcom/fasterxml/jackson/core/JsonGenerator$Feature;
      StackMapTable: number_of_entries = 1
        frame_type = 18 /* same */

  public com.fasterxml.jackson.core.JsonGenerator disable(com.fasterxml.jackson.core.JsonGenerator$Feature);
    descriptor: (Lcom/fasterxml/jackson/core/JsonGenerator$Feature;)Lcom/fasterxml/jackson/core/JsonGenerator;
    flags: (0x0001) ACC_PUBLIC
    Code:
      stack=2, locals=2, args_size=2
         0: aload_0
         1: aload_1
         2: invokespecial #15                 // Method com/fasterxml/jackson/core/base/GeneratorBase.disable:(Lcom/fasterxml/jackson/core/JsonGenerator$Feature;)Lcom/fasterxml/jackson/core/JsonGenerator;
         5: pop
         6: aload_1
         7: getstatic     #10                 // Field com/fasterxml/jackson/core/JsonGenerator$Feature.QUOTE_FIELD_NAMES:Lcom/fasterxml/jackson/core/JsonGenerator$Feature;
        10: if_acmpne     18
        13: aload_0
        14: iconst_1
        15: putfield      #11                 // Field _cfgUnqNames:Z
        18: aload_0
        19: areturn
      LineNumberTable:
        line 153: 0
        line 154: 6
        line 155: 13
        line 157: 18
      LocalVariableTable:
        Start  Length  Slot  Name   Signature
            0      20     0  this   Lcom/fasterxml/jackson/core/json/JsonGeneratorImpl;
            0      20     1     f   Lcom/fasterxml/jackson/core/JsonGenerator$Feature;
      StackMapTable: number_of_entries = 1
        frame_type = 18 /* same */

  protected void _checkStdFeatureChanges(int, int);
    descriptor: (II)V
    flags: (0x0004) ACC_PROTECTED
    Code:
      stack=3, locals=3, args_size=3
         0: aload_0
         1: iload_1
         2: iload_2
         3: invokespecial #16                 // Method com/fasterxml/jackson/core/base/GeneratorBase._checkStdFeatureChanges:(II)V
         6: aload_0
         7: getstatic     #10                 // Field com/fasterxml/jackson/core/JsonGenerator$Feature.QUOTE_FIELD_NAMES:Lcom/fasterxml/jackson/core/JsonGenerator$Feature;
        10: iload_1
        11: invokevirtual #8                  // Method com/fasterxml/jackson/core/JsonGenerator$Feature.enabledIn:(I)Z
        14: ifne          21
        17: iconst_1
        18: goto          22
        21: iconst_0
        22: putfield      #11                 // Field _cfgUnqNames:Z
        25: return
      LineNumberTable:
        line 163: 0
        line 164: 6
        line 165: 25
      LocalVariableTable:
        Start  Length  Slot  Name   Signature
            0      26     0  this   Lcom/fasterxml/jackson/core/json/JsonGeneratorImpl;
            0      26     1 newFeatureFlags   I
            0      26     2 changedFeatures   I
      StackMapTable: number_of_entries = 2
        frame_type = 85 /* same_locals_1_stack_item */
          stack = [ class com/fasterxml/jackson/core/json/JsonGeneratorImpl ]
        frame_type = 255 /* full_frame */
          offset_delta = 0
          locals = [ class com/fasterxml/jackson/core/json/JsonGeneratorImpl, int, int ]
          stack = [ class com/fasterxml/jackson/core/json/JsonGeneratorImpl, int ]

  public com.fasterxml.jackson.core.JsonGenerator setHighestNonEscapedChar(int);
    descriptor: (I)Lcom/fasterxml/jackson/core/JsonGenerator;
    flags: (0x0001) ACC_PUBLIC
    Code:
      stack=2, locals=2, args_size=2
         0: aload_0
         1: iload_1
         2: ifge          9
         5: iconst_0
         6: goto          10
         9: iload_1
        10: putfield      #9                  // Field _maximumNonEscapedChar:I
        13: aload_0
        14: areturn
      LineNumberTable:
        line 169: 0
        line 170: 13
      LocalVariableTable:
        Start  Length  Slot  Name   Signature
            0      15     0  this   Lcom/fasterxml/jackson/core/json/JsonGeneratorImpl;
            0      15     1 charCode   I
      StackMapTable: number_of_entries = 2
        frame_type = 73 /* same_locals_1_stack_item */
          stack = [ class com/fasterxml/jackson/core/json/JsonGeneratorImpl ]
        frame_type = 255 /* full_frame */
          offset_delta = 0
          locals = [ class com/fasterxml/jackson/core/json/JsonGeneratorImpl, int ]
          stack = [ class com/fasterxml/jackson/core/json/JsonGeneratorImpl, int ]

  public int getHighestEscapedChar();
    descriptor: ()I
    flags: (0x0001) ACC_PUBLIC
    Code:
      stack=1, locals=1, args_size=1
         0: aload_0
         1: getfield      #9                  // Field _maximumNonEscapedChar:I
         4: ireturn
      LineNumberTable:
        line 175: 0
      LocalVariableTable:
        Start  Length  Slot  Name   Signature
            0       5     0  this   Lcom/fasterxml/jackson/core/json/JsonGeneratorImpl;

  public com.fasterxml.jackson.core.JsonGenerator setCharacterEscapes(com.fasterxml.jackson.core.io.CharacterEscapes);
    descriptor: (Lcom/fasterxml/jackson/core/io/CharacterEscapes;)Lcom/fasterxml/jackson/core/JsonGenerator;
    flags: (0x0001) ACC_PUBLIC
    Code:
      stack=2, locals=2, args_size=2
         0: aload_0
         1: aload_1
         2: putfield      #17                 // Field _characterEscapes:Lcom/fasterxml/jackson/core/io/CharacterEscapes;
         5: aload_1
         6: ifnonnull     19
         9: aload_0
        10: getstatic     #2                  // Field sOutputEscapes:[I
        13: putfield      #3                  // Field _outputEscapes:[I
        16: goto          27
        19: aload_0
        20: aload_1
        21: invokevirtual #18                 // Method com/fasterxml/jackson/core/io/CharacterEscapes.getEscapeCodesForAscii:()[I
        24: putfield      #3                  // Field _outputEscapes:[I
        27: aload_0
        28: areturn
      LineNumberTable:
        line 181: 0
        line 182: 5
        line 183: 9
        line 185: 19
        line 187: 27
      LocalVariableTable:
        Start  Length  Slot  Name   Signature
            0      29     0  this   Lcom/fasterxml/jackson/core/json/JsonGeneratorImpl;
            0      29     1   esc   Lcom/fasterxml/jackson/core/io/CharacterEscapes;
      StackMapTable: number_of_entries = 2
        frame_type = 19 /* same */
        frame_type = 7 /* same */

  public com.fasterxml.jackson.core.io.CharacterEscapes getCharacterEscapes();
    descriptor: ()Lcom/fasterxml/jackson/core/io/CharacterEscapes;
    flags: (0x0001) ACC_PUBLIC
    Code:
      stack=1, locals=1, args_size=1
         0: aload_0
         1: getfield      #17                 // Field _characterEscapes:Lcom/fasterxml/jackson/core/io/CharacterEscapes;
         4: areturn
      LineNumberTable:
        line 196: 0
      LocalVariableTable:
        Start  Length  Slot  Name   Signature
            0       5     0  this   Lcom/fasterxml/jackson/core/json/JsonGeneratorImpl;

  public com.fasterxml.jackson.core.JsonGenerator setRootValueSeparator(com.fasterxml.jackson.core.SerializableString);
    descriptor: (Lcom/fasterxml/jackson/core/SerializableString;)Lcom/fasterxml/jackson/core/JsonGenerator;
    flags: (0x0001) ACC_PUBLIC
    Code:
      stack=2, locals=2, args_size=2
         0: aload_0
         1: aload_1
         2: putfield      #5                  // Field _rootValueSeparator:Lcom/fasterxml/jackson/core/SerializableString;
         5: aload_0
         6: areturn
      LineNumberTable:
        line 201: 0
        line 202: 5
      LocalVariableTable:
        Start  Length  Slot  Name   Signature
            0       7     0  this   Lcom/fasterxml/jackson/core/json/JsonGeneratorImpl;
            0       7     1   sep   Lcom/fasterxml/jackson/core/SerializableString;

  public com.fasterxml.jackson.core.util.JacksonFeatureSet<com.fasterxml.jackson.core.StreamWriteCapability> getWriteCapabilities();
    descriptor: ()Lcom/fasterxml/jackson/core/util/JacksonFeatureSet;
    flags: (0x0001) ACC_PUBLIC
    Code:
      stack=1, locals=1, args_size=1
         0: getstatic     #19                 // Field JSON_WRITE_CAPABILITIES:Lcom/fasterxml/jackson/core/util/JacksonFeatureSet;
         3: areturn
      LineNumberTable:
        line 207: 0
      LocalVariableTable:
        Start  Length  Slot  Name   Signature
            0       4     0  this   Lcom/fasterxml/jackson/core/json/JsonGeneratorImpl;
    Signature: #101                         // ()Lcom/fasterxml/jackson/core/util/JacksonFeatureSet<Lcom/fasterxml/jackson/core/StreamWriteCapability;>;

  protected void _verifyPrettyValueWrite(java.lang.String, int) throws java.io.IOException;
    descriptor: (Ljava/lang/String;I)V
    flags: (0x0004) ACC_PROTECTED
    Code:
      stack=2, locals=3, args_size=3
         0: iload_2
         1: tableswitch   { // 0 to 5
                       0: 79
                       1: 40
                       2: 53
                       3: 66
                       4: 133
                       5: 125
                 default: 133
            }
        40: aload_0
        41: getfield      #20                 // Field _cfgPrettyPrinter:Lcom/fasterxml/jackson/core/PrettyPrinter;
        44: aload_0
        45: invokeinterface #21,  2           // InterfaceMethod com/fasterxml/jackson/core/PrettyPrinter.writeArrayValueSeparator:(Lcom/fasterxml/jackson/core/JsonGenerator;)V
        50: goto          137
        53: aload_0
        54: getfield      #20                 // Field _cfgPrettyPrinter:Lcom/fasterxml/jackson/core/PrettyPrinter;
        57: aload_0
        58: invokeinterface #22,  2           // InterfaceMethod com/fasterxml/jackson/core/PrettyPrinter.writeObjectFieldValueSeparator:(Lcom/fasterxml/jackson/core/JsonGenerator;)V
        63: goto          137
        66: aload_0
        67: getfield      #20                 // Field _cfgPrettyPrinter:Lcom/fasterxml/jackson/core/PrettyPrinter;
        70: aload_0
        71: invokeinterface #23,  2           // InterfaceMethod com/fasterxml/jackson/core/PrettyPrinter.writeRootValueSeparator:(Lcom/fasterxml/jackson/core/JsonGenerator;)V
        76: goto          137
        79: aload_0
        80: getfield      #24                 // Field _writeContext:Lcom/fasterxml/jackson/core/json/JsonWriteContext;
        83: invokevirtual #25                 // Method com/fasterxml/jackson/core/json/JsonWriteContext.inArray:()Z
        86: ifeq          102
        89: aload_0
        90: getfield      #20                 // Field _cfgPrettyPrinter:Lcom/fasterxml/jackson/core/PrettyPrinter;
        93: aload_0
        94: invokeinterface #26,  2           // InterfaceMethod com/fasterxml/jackson/core/PrettyPrinter.beforeArrayValues:(Lcom/fasterxml/jackson/core/JsonGenerator;)V
        99: goto          137
       102: aload_0
       103: getfield      #24                 // Field _writeContext:Lcom/fasterxml/jackson/core/json/JsonWriteContext;
       106: invokevirtual #27                 // Method com/fasterxml/jackson/core/json/JsonWriteContext.inObject:()Z
       109: ifeq          137
       112: aload_0
       113: getfield      #20                 // Field _cfgPrettyPrinter:Lcom/fasterxml/jackson/core/PrettyPrinter;
       116: aload_0
       117: invokeinterface #28,  2           // InterfaceMethod com/fasterxml/jackson/core/PrettyPrinter.beforeObjectEntries:(Lcom/fasterxml/jackson/core/JsonGenerator;)V
       122: goto          137
       125: aload_0
       126: aload_1
       127: invokevirtual #29                 // Method _reportCantWriteValueExpectName:(Ljava/lang/String;)V
       130: goto          137
       133: aload_0
       134: invokevirtual #30                 // Method _throwInternal:()V
       137: return
      LineNumberTable:
        line 219: 0
        line 221: 40
        line 222: 50
        line 224: 53
        line 225: 63
        line 227: 66
        line 228: 76
        line 231: 79
        line 232: 89
        line 233: 102
        line 234: 112
        line 238: 125
        line 239: 130
        line 241: 133
        line 244: 137
      LocalVariableTable:
        Start  Length  Slot  Name   Signature
            0     138     0  this   Lcom/fasterxml/jackson/core/json/JsonGeneratorImpl;
            0     138     1 typeMsg   Ljava/lang/String;
            0     138     2 status   I
      StackMapTable: number_of_entries = 8
        frame_type = 40 /* same */
        frame_type = 12 /* same */
        frame_type = 12 /* same */
        frame_type = 12 /* same */
        frame_type = 22 /* same */
        frame_type = 22 /* same */
        frame_type = 7 /* same */
        frame_type = 3 /* same */
    Exceptions:
      throws java.io.IOException

  protected void _reportCantWriteValueExpectName(java.lang.String) throws java.io.IOException;
    descriptor: (Ljava/lang/String;)V
    flags: (0x0004) ACC_PROTECTED
    Code:
      stack=6, locals=2, args_size=2
         0: aload_0
         1: ldc           #31                 // String Can not %s, expecting field name (context: %s)
         3: iconst_2
         4: anewarray     #32                 // class java/lang/Object
         7: dup
         8: iconst_0
         9: aload_1
        10: aastore
        11: dup
        12: iconst_1
        13: aload_0
        14: getfield      #24                 // Field _writeContext:Lcom/fasterxml/jackson/core/json/JsonWriteContext;
        17: invokevirtual #33                 // Method com/fasterxml/jackson/core/json/JsonWriteContext.typeDesc:()Ljava/lang/String;
        20: aastore
        21: invokestatic  #34                 // Method java/lang/String.format:(Ljava/lang/String;[Ljava/lang/Object;)Ljava/lang/String;
        24: invokevirtual #35                 // Method _reportError:(Ljava/lang/String;)V
        27: return
      LineNumberTable:
        line 248: 0
        line 249: 17
        line 248: 21
        line 250: 27
      LocalVariableTable:
        Start  Length  Slot  Name   Signature
            0      28     0  this   Lcom/fasterxml/jackson/core/json/JsonGeneratorImpl;
            0      28     1 typeMsg   Ljava/lang/String;
    Exceptions:
      throws java.io.IOException

  static {};
    descriptor: ()V
    flags: (0x0008) ACC_STATIC
    Code:
      stack=1, locals=0, args_size=0
         0: invokestatic  #36                 // Method com/fasterxml/jackson/core/io/CharTypes.get7BitOutputEscapes:()[I
         3: putstatic     #2                  // Field sOutputEscapes:[I
         6: getstatic     #37                 // Field DEFAULT_TEXTUAL_WRITE_CAPABILITIES:Lcom/fasterxml/jackson/core/util/JacksonFeatureSet;
         9: putstatic     #19                 // Field JSON_WRITE_CAPABILITIES:Lcom/fasterxml/jackson/core/util/JacksonFeatureSet;
        12: return
      LineNumberTable:
        line 32: 0
        line 40: 6
}
SourceFile: "JsonGeneratorImpl.java"
InnerClasses:
  public static final #76= #75 of #163;   // Feature=class com/fasterxml/jackson/core/JsonGenerator$Feature of class com/fasterxml/jackson/core/JsonGenerator
