Classfile /Users/mw/Projects/slang-braindump/.jar/jar11/assemble/slang-braindump/assemble/content/coursier/core/Activation$.class
  Last modified May 29, 2022; size 1951 bytes
  SHA-256 checksum ad6cb721376caa57ea40a83a05e400fefdab587fd44e7e35cfa3b0393e788fdc
  Compiled from "Activation.scala"
public final class coursier.core.Activation$ implements java.io.Serializable
  minor version: 0
  major version: 52
  flags: (0x0031) ACC_PUBLIC, ACC_FINAL, ACC_SUPER
  this_class: #2                          // coursier/core/Activation$
  super_class: #4                         // java/lang/Object
  interfaces: 1, fields: 2, methods: 5, attributes: 4
Constant pool:
   #1 = Utf8               coursier/core/Activation$
   #2 = Class              #1             // coursier/core/Activation$
   #3 = Utf8               java/lang/Object
   #4 = Class              #3             // java/lang/Object
   #5 = Utf8               java/io/Serializable
   #6 = Class              #5             // java/io/Serializable
   #7 = Utf8               Activation.scala
   #8 = Utf8               coursier/core/Activation$Os
   #9 = Class              #8             // coursier/core/Activation$Os
  #10 = Utf8               coursier/core/Activation
  #11 = Class              #10            // coursier/core/Activation
  #12 = Utf8               Os
  #13 = Utf8               coursier/core/Activation$Os$
  #14 = Class              #13            // coursier/core/Activation$Os$
  #15 = Utf8
  #16 = Utf8               MODULE$
  #17 = Utf8               Lcoursier/core/Activation$;
  #18 = Utf8               empty
  #19 = Utf8               Lcoursier/core/Activation;
  #20 = Utf8               <clinit>
  #21 = Utf8               ()V
  #22 = Utf8               <init>
  #23 = NameAndType        #22:#21        // "<init>":()V
  #24 = Methodref          #2.#23         // coursier/core/Activation$."<init>":()V
  #25 = NameAndType        #16:#17        // MODULE$:Lcoursier/core/Activation$;
  #26 = Fieldref           #2.#25         // coursier/core/Activation$.MODULE$:Lcoursier/core/Activation$;
  #27 = Utf8               scala/collection/immutable/Nil$
  #28 = Class              #27            // scala/collection/immutable/Nil$
  #29 = Utf8               Lscala/collection/immutable/Nil$;
  #30 = NameAndType        #16:#29        // MODULE$:Lscala/collection/immutable/Nil$;
  #31 = Fieldref           #28.#30        // scala/collection/immutable/Nil$.MODULE$:Lscala/collection/immutable/Nil$;
  #32 = Utf8               Lcoursier/core/Activation$Os$;
  #33 = NameAndType        #16:#32        // MODULE$:Lcoursier/core/Activation$Os$;
  #34 = Fieldref           #14.#33        // coursier/core/Activation$Os$.MODULE$:Lcoursier/core/Activation$Os$;
  #35 = Utf8               ()Lcoursier/core/Activation$Os;
  #36 = NameAndType        #18:#35        // empty:()Lcoursier/core/Activation$Os;
  #37 = Methodref          #14.#36        // coursier/core/Activation$Os$.empty:()Lcoursier/core/Activation$Os;
  #38 = Utf8               scala/None$
  #39 = Class              #38            // scala/None$
  #40 = Utf8               Lscala/None$;
  #41 = NameAndType        #16:#40        // MODULE$:Lscala/None$;
  #42 = Fieldref           #39.#41        // scala/None$.MODULE$:Lscala/None$;
  #43 = Utf8               apply
  #44 = Utf8               (Lscala/collection/immutable/Seq;Lcoursier/core/Activation$Os;Lscala/Option;)Lcoursier/core/Activation;
  #45 = NameAndType        #43:#44        // apply:(Lscala/collection/immutable/Seq;Lcoursier/core/Activation$Os;Lscala/Option;)Lcoursier/core/Activation;
  #46 = Methodref          #2.#45         // coursier/core/Activation$.apply:(Lscala/collection/immutable/Seq;Lcoursier/core/Activation$Os;Lscala/Option;)Lcoursier/core/Activation;
  #47 = NameAndType        #18:#19        // empty:Lcoursier/core/Activation;
  #48 = Fieldref           #2.#47         // coursier/core/Activation$.empty:Lcoursier/core/Activation;
  #49 = Utf8               ()Lcoursier/core/Activation;
  #50 = Utf8               this
  #51 = Utf8               (Lscala/collection/immutable/Seq<Lscala/Tuple2<Ljava/lang/String;Lscala/Option<Ljava/lang/String;>;>;>;Lcoursier/core/Activation$Os;Lscala/Option<Lscala/util/Either<Lcoursier/core/VersionInterval;Lscala/collection/immutable/Seq<Lcoursier/core/Version;>;>;>;)Lcoursier/core/Activation;
  #52 = Utf8               properties
  #53 = Utf8               os
  #54 = Utf8               jdk
  #55 = Utf8               (Lscala/collection/immutable/Seq;Lcoursier/core/Activation$Os;Lscala/Option;)V
  #56 = NameAndType        #22:#55        // "<init>":(Lscala/collection/immutable/Seq;Lcoursier/core/Activation$Os;Lscala/Option;)V
  #57 = Methodref          #11.#56        // coursier/core/Activation."<init>":(Lscala/collection/immutable/Seq;Lcoursier/core/Activation$Os;Lscala/Option;)V
  #58 = Utf8               Lscala/collection/immutable/Seq;
  #59 = Utf8               Lcoursier/core/Activation$Os;
  #60 = Utf8               Lscala/Option;
  #61 = Utf8               writeReplace
  #62 = Utf8               ()Ljava/lang/Object;
  #63 = Utf8               scala/runtime/ModuleSerializationProxy
  #64 = Class              #63            // scala/runtime/ModuleSerializationProxy
  #65 = Utf8               (Ljava/lang/Class;)V
  #66 = NameAndType        #22:#65        // "<init>":(Ljava/lang/Class;)V
  #67 = Methodref          #64.#66        // scala/runtime/ModuleSerializationProxy."<init>":(Ljava/lang/Class;)V
  #68 = Methodref          #4.#23         // java/lang/Object."<init>":()V
  #69 = Utf8               Code
  #70 = Utf8               LineNumberTable
  #71 = Utf8               LocalVariableTable
  #72 = Utf8               Signature
  #73 = Utf8               MethodParameters
  #74 = Utf8               InnerClasses
  #75 = Utf8               SourceFile
  #76 = Utf8               ScalaInlineInfo
  #77 = Utf8               Scala
{
  public static final coursier.core.Activation$ MODULE$;
    descriptor: Lcoursier/core/Activation$;
    flags: (0x0019) ACC_PUBLIC, ACC_STATIC, ACC_FINAL

  private static final coursier.core.Activation empty;
    descriptor: Lcoursier/core/Activation;
    flags: (0x001a) ACC_PRIVATE, ACC_STATIC, ACC_FINAL

  public static {};
    descriptor: ()V
    flags: (0x0009) ACC_PUBLIC, ACC_STATIC
    Code:
      stack=4, locals=0, args_size=0
         0: new           #2                  // class coursier/core/Activation$
         3: dup
         4: invokespecial #24                 // Method "<init>":()V
         7: putstatic     #26                 // Field MODULE$:Lcoursier/core/Activation$;
        10: getstatic     #26                 // Field MODULE$:Lcoursier/core/Activation$;
        13: getstatic     #31                 // Field scala/collection/immutable/Nil$.MODULE$:Lscala/collection/immutable/Nil$;
        16: getstatic     #34                 // Field coursier/core/Activation$Os$.MODULE$:Lcoursier/core/Activation$Os$;
        19: invokevirtual #37                 // Method coursier/core/Activation$Os$.empty:()Lcoursier/core/Activation$Os;
        22: getstatic     #42                 // Field scala/None$.MODULE$:Lscala/None$;
        25: invokevirtual #46                 // Method apply:(Lscala/collection/immutable/Seq;Lcoursier/core/Activation$Os;Lscala/Option;)Lcoursier/core/Activation;
        28: putstatic     #48                 // Field empty:Lcoursier/core/Activation;
        31: return
      LineNumberTable:
        line 6: 0
        line 141: 10
        line 6: 31

  public coursier.core.Activation empty();
    descriptor: ()Lcoursier/core/Activation;
    flags: (0x0001) ACC_PUBLIC
    Code:
      stack=1, locals=1, args_size=1
         0: getstatic     #48                 // Field empty:Lcoursier/core/Activation;
         3: areturn
      LineNumberTable:
        line 141: 0
      LocalVariableTable:
        Start  Length  Slot  Name   Signature
            0       4     0  this   Lcoursier/core/Activation$;

  public coursier.core.Activation apply(scala.collection.immutable.Seq<scala.Tuple2<java.lang.String, scala.Option<java.lang.String>>>, coursier.core.Activation$Os, scala.Option<scala.util.Either<coursier.core.VersionInterval, scala.collection.immutable.Seq<coursier.core.Version>>>);
    descriptor: (Lscala/collection/immutable/Seq;Lcoursier/core/Activation$Os;Lscala/Option;)Lcoursier/core/Activation;
    flags: (0x0001) ACC_PUBLIC
    Code:
      stack=5, locals=4, args_size=4
         0: new           #11                 // class coursier/core/Activation
         3: dup
         4: aload_1
         5: aload_2
         6: aload_3
         7: invokespecial #57                 // Method coursier/core/Activation."<init>":(Lscala/collection/immutable/Seq;Lcoursier/core/Activation$Os;Lscala/Option;)V
        10: areturn
      LineNumberTable:
        line 6: 0
      LocalVariableTable:
        Start  Length  Slot  Name   Signature
            0      11     0  this   Lcoursier/core/Activation$;
            0      11     1 properties   Lscala/collection/immutable/Seq;
            0      11     2    os   Lcoursier/core/Activation$Os;
            0      11     3   jdk   Lscala/Option;
    Signature: #51                          // (Lscala/collection/immutable/Seq<Lscala/Tuple2<Ljava/lang/String;Lscala/Option<Ljava/lang/String;>;>;>;Lcoursier/core/Activation$Os;Lscala/Option<Lscala/util/Either<Lcoursier/core/VersionInterval;Lscala/collection/immutable/Seq<Lcoursier/core/Version;>;>;>;)Lcoursier/core/Activation;
    MethodParameters:
      Name                           Flags
      properties                     final
      os                             final
      jdk                            final

  private java.lang.Object writeReplace();
    descriptor: ()Ljava/lang/Object;
    flags: (0x0002) ACC_PRIVATE
    Code:
      stack=3, locals=1, args_size=1
         0: new           #64                 // class scala/runtime/ModuleSerializationProxy
         3: dup
         4: ldc           #2                  // class coursier/core/Activation$
         6: invokespecial #67                 // Method scala/runtime/ModuleSerializationProxy."<init>":(Ljava/lang/Class;)V
         9: areturn
      LineNumberTable:
        line 6: 0
      LocalVariableTable:
        Start  Length  Slot  Name   Signature
            0      10     0  this   Lcoursier/core/Activation$;

  private coursier.core.Activation$();
    descriptor: ()V
    flags: (0x0002) ACC_PRIVATE
    Code:
      stack=1, locals=1, args_size=1
         0: aload_0
         1: invokespecial #68                 // Method java/lang/Object."<init>":()V
         4: return
      LineNumberTable:
        line 142: 0
        line 6: 4
      LocalVariableTable:
        Start  Length  Slot  Name   Signature
            0       5     0  this   Lcoursier/core/Activation$;
}
InnerClasses:
  public static final #12= #9 of #11;     // Os=class coursier/core/Activation$Os of class coursier/core/Activation
  public static #15= #14 of #11;          // =class coursier/core/Activation$Os$ of class coursier/core/Activation
SourceFile: "Activation.scala"
  ScalaInlineInfo: length = 0x18 (unknown attribute)
   01 01 00 04 00 16 00 15 01 00 2B 00 2C 01 00 12
   00 31 01 00 3D 00 3E 01
  Scala: length = 0x0 (unknown attribute)

