Classfile /Users/mw/Projects/slang-braindump/.jar/jar11/assemble/slang-braindump/assemble/content/coursier/core/Authentication.class
  Last modified May 29, 2022; size 13544 bytes
  SHA-256 checksum 3977d3c3e432354ec0b3d7e06396570b506172cdbaa0792b01763df00ae9af83
  Compiled from "Authentication.scala"
public final class coursier.core.Authentication implements scala.Product,java.io.Serializable
  minor version: 0
  major version: 52
  flags: (0x0031) ACC_PUBLIC, ACC_FINAL, ACC_SUPER
  this_class: #2                          // coursier/core/Authentication
  super_class: #4                         // java/lang/Object
  interfaces: 2, fields: 7, methods: 40, attributes: 6
Constant pool:
    #1 = Utf8               coursier/core/Authentication
    #2 = Class              #1            // coursier/core/Authentication
    #3 = Utf8               java/lang/Object
    #4 = Class              #3            // java/lang/Object
    #5 = Utf8               scala/Product
    #6 = Class              #5            // scala/Product
    #7 = Utf8               java/io/Serializable
    #8 = Class              #7            // java/io/Serializable
    #9 = Utf8               Authentication.scala
   #10 = Utf8               Lscala/reflect/ScalaSignature;
   #11 = Utf8               bytes
   #12 = Utf8               \u0006\u0005\u0005Uh\u0001\u0002\u00192\u0005YB\u0001\u0002\u0014\u0001\u0003\u0006\u0004%\t!\u0014\u0005\t-\u0002\u0011\t\u0011)A\u0005\u001d\"Aq\u000b\u0001BC\u0002\u0013\u0005\u0001\f\u0003\u0005]\u0001\t\u0005\t\u0015!\u0003Z\u0011!i\u0006A!b\u0001\n\u0003q\u0006\u0002C3\u0001\u0005\u0003\u0005\u000b\u0011B0\t\u0011\u0019\u0004!Q1A\u0005\u0002\u001dD\u0001b\u001b\u0001\u0003\u0002\u0003\u0006I\u0001\u001b\u0005\tY\u0002\u0011)\u0019!C\u00011\"AQ\u000e\u0001B\u0001B\u0003%\u0011\f\u0003\u0005o\u0001\t\u0015\r\u0011\"\u0001h\u0011!y\u0007A!A!\u0002\u0013A\u0007\u0002\u00039\u0001\u0005\u000b\u0007I\u0011A4\t\u0011E\u0004!\u0011!Q\u0001\n!DQA\u001d\u0001\u0005\u0002MDQ! \u0001\u0005ByDaa \u0001\u0005\u0002\u0005\u0005\u0001bBA\u0004\u0001\u0011\u0005\u0011\u0011\u0002\u0005\u0007\u0003\u001f\u0001A\u0011A4\t\r\u0005E\u0001\u0001\"\u0001_\u0011\u001d\t\u0019\u0002\u0001C\u0001\u0003+Aq!!\u0007\u0001\t\u0003\tY\u0002C\u0004\u0002 \u0001!\t!!\t\t\u000f\u0005\u0015\u0002\u0001\"\u0001\u0002(!9\u00111\u0006\u0001\u0005\u0002\u00055\u0002bBA\u0019\u0001\u0011\u0005\u00111\u0007\u0005\b\u0003o\u0001A\u0011AA\u001d\u0011\u001d\ti\u0004\u0001C!\u0003\u007fAq!a\u0013\u0001\t\u0003\ni\u0005C\u0004\u0002R\u0001!\t%a\u0015\t\u000f\u0005m\u0003\u0001\"\u0003\u0002^!9\u0011Q\r\u0001\u0005B\u0005\u001d\u0004bBA<\u0001\u0011\u0005\u0013\u0011\u0010\u0005\b\u0003w\u0002A\u0011IA?\u0011\u001d\t\u0019\t\u0001C!\u0003\u000b;q!!#2\u0011\u0003\tYI\u0002\u00041c!\u0005\u0011Q\u0012\u0005\u0007e\u0016\"\t!!\'\t\u000f\u0005mU\u0005\"\u0001\u0002\u001e\"9\u00111T\u0013\u0005\u0002\u0005\u0005\u0006bBANK\u0011\u0005\u0011q\u0015\u0005\b\u00037+C\u0011AA[\u0011\u001d\tY*\nC\u0001\u0003\u0007Dq!a\'&\t\u0003\t9\r\u0003\u0005\u0002T\u0016\"\taMAk\u0011\u001d\tY*\nC\u0001\u00037D\u0011\"a;&\u0003\u0003%I!!<\u0003\u001d\u0005+H\u000f[3oi&\u001c\u0017\r^5p]*\u0011!gM\u0001\u0005G>\u0014XMC\u00015\u0003!\u0019w.\u001e:tS\u0016\u00148\u0001A\n\u0005\u0001]j\u0004\t\u0005\u00029w5\t\u0011HC\u0001;\u0003\u0015\u00198-\u00197b\u0013\ta\u0014H\u0001\u0004B]f\u0014VM\u001a\t\u0003qyJ!aP\u001d\u0003\u000fA\u0013x\u000eZ;diB\u0011\u0011)\u0013\b\u0003\u0005\u001es!a\u0011$\u000e\u0003\u0011S!!R\u001b\u0002\rq\u0012xn\u001c;?\u0013\u0005Q\u0014B\u0001%:\u0003\u001d\u0001\u0018mY6bO\u0016L!AS&\u0003\u0019M+\'/[1mSj\f\'\r\\3\u000b\u0005!K\u0014\u0001B;tKJ,\u0012A\u0014\t\u0003\u001fNs!\u0001U)\u0011\u0005\rK\u0014B\u0001*:\u0003\u0019\u0001&/\u001a3fM&\u0011A+\u0016\u0002\u0007\'R\u0014\u0018N\\4\u000b\u0005IK\u0014!B;tKJ\u0004\u0013a\u00039bgN<xN\u001d3PaR,\u0012!\u0017\t\u0004qis\u0015BA.:\u0005\u0019y\u0005\u000f^5p]\u0006a\u0001/Y:to>\u0014Hm\u00149uA\u0005Y\u0001\u000e\u001e;q\u0011\u0016\fG-\u001a:t+\u0005y\u0006cA!aE&\u0011\u0011m\u0013\u0002\u0004\'\u0016\f\b\u0003\u0002\u001dd\u001d:K!\u0001Z\u001d\u0003\rQ+\b\u000f\\33\u00031AG\u000f\u001e9IK\u0006$WM]:!\u0003!y\u0007\u000f^5p]\u0006dW#\u00015\u0011\u0005aJ\u0017B\u00016:\u0005\u001d\u0011un\u001c7fC:\f\u0011b\u001c9uS>t\u0017\r\u001c\u0011\u0002\u0011I,\u0017\r\\7PaR\f\u0011B]3bY6|\u0005\u000f\u001e\u0011\u0002\u0013!$H\u000f]:P]2L\u0018A\u00035uiB\u001cxJ\u001c7zA\u0005q\u0001/Y:t\u001f:\u0014V\rZ5sK\u000e$\u0018a\u00049bgN|eNU3eSJ,7\r\u001e\u0011\u0002\rqJg.\u001b;?)!!ho\u001e=zund\bCA;\u0001\u001b\u0005\t\u0004\"\u0002\'\u0010\u0001\u0004q\u0005\"B,\u0010\u0001\u0004I\u0006\"B/\u0010\u0001\u0004y\u0006\"\u00024\u0010\u0001\u0004A\u0007\"\u00027\u0010\u0001\u0004I\u0006\"\u00028\u0010\u0001\u0004A\u0007\"\u00029\u0010\u0001\u0004A\u0017\u0001\u0003;p\'R\u0014\u0018N\\4\u0015\u00039\u000bAb^5uQB\u000b7o]<pe\u0012$2\u0001^A\u0002\u0011\u0019\t)!\u0005a\u0001\u001d\u0006A\u0001/Y:to>\u0014H-A\u0005xSRD\'+Z1m[R\u0019A/a\u0003\t\r\u00055!\u00031\u0001O\u0003\u0015\u0011X-\u00197n\u0003!)8/\u001a:P]2L\u0018AD1mY\"#H\u000f\u001d%fC\u0012,\'o]\u0001\to&$\b.V:feR\u0019A/a\u0006\t\u000b1+\u0002\u0019\u0001(\u0002\u001f]LG\u000f\u001b)bgN<xN\u001d3PaR$2\u0001^A\u000f\u0011\u00159f\u00031\u0001Z\u0003=9\u0018\u000e\u001e5IiR\u0004\b*Z1eKJ\u001cHc\u0001;\u0002$!)Ql\u0006a\u0001?\u0006aq/\u001b;i\u001fB$\u0018n\u001c8bYR\u0019A/!\u000b\t\u000b\u0019D\u0002\u0019\u00015\u0002\u0019]LG\u000f\u001b*fC2lw\n\u001d;\u0015\u0007Q\fy\u0003C\u0003m3\u0001\u0007\u0011,A\u0007xSRD\u0007\n\u001e;qg>sG.\u001f\u000b\u0004i\u0006U\u0002\"\u00028\u001b\u0001\u0004A\u0017AE<ji\"\u0004\u0016m]:P]J+G-\u001b:fGR$2\u0001^A\u001e\u0011\u0015\u00018\u00041\u0001i\u0003!\u0019\u0017M\\#rk\u0006dGc\u00015\u0002B!9\u00111\t\u000fA\u0002\u0005\u0015\u0013aA8cUB\u0019\u0001(a\u0012\n\u0007\u0005%\u0013HA\u0002B]f\fa!Z9vC2\u001cHc\u00015\u0002P!9\u00111I\u000fA\u0002\u0005\u0015\u0013\u0001\u00035bg\"\u001cu\u000eZ3\u0015\u0005\u0005U\u0003c\u0001\u001d\u0002X%\u0019\u0011\u0011L\u001d\u0003\u0007%sG/A\u0003ukBdW-\u0006\u0002\u0002`AQ\u0001(!\u0019O3~C\u0017\f\u001b5\n\u0007\u0005\r\u0014H\u0001\u0004UkBdWmN\u0001\u000eaJ|G-^2u!J,g-\u001b=\u0016\u0005\u0005%\u0004\u0003BA6\u0003kj!!!\u001c\u000b\t\u0005=\u0014\u0011O\u0001\u0005Y\u0006twM\u0003\u0002\u0002t\u0005!!.\u0019<b\u0013\r!\u0016QN\u0001\raJ|G-^2u\u0003JLG/_\u000b\u0003\u0003+\na\u0002\u001d:pIV\u001cG/\u00127f[\u0016tG\u000f\u0006\u0003\u0002F\u0005}\u0004bBAAE\u0001\u0007\u0011QK\u0001\u0002]\u0006\u0011\u0002O]8ek\u000e$X\t\\3nK:$h*Y7f)\u0011\tI\'a\"\t\u000f\u0005\u00055\u00051\u0001\u0002V\u0005q\u0011)\u001e;iK:$\u0018nY1uS>t\u0007CA;&\'\u0011)s\'a$\u0011\t\u0005E\u0015qS\u0007\u0003\u0003\'SA!!&\u0002r\u0005\u0011\u0011n\\\u0005\u0004\u0015\u0006MECAAF\u0003\u0015\t\u0007\u000f\u001d7z)\r!\u0018q\u0014\u0005\u0006\u0019\u001e\u0002\rA\u0014\u000b\u0006i\u0006\r\u0016Q\u0015\u0005\u0006\u0019\"\u0002\rA\u0014\u0005\u0007\u0003\u000bA\u0003\u0019\u0001(\u0015\u001bQ\fI+a+\u0002.\u0006=\u0016\u0011WAZ\u0011\u0015a\u0015\u00061\u0001O\u0011\u00159\u0016\u00061\u0001Z\u0011\u00151\u0017\u00061\u0001i\u0011\u0015a\u0017\u00061\u0001Z\u0011\u0015q\u0017\u00061\u0001i\u0011\u0015\u0001\u0018\u00061\u0001i)5!\u0018qWA]\u0003w\u000bi,a0\u0002B\")AJ\u000ba\u0001\u001d\"1\u0011Q\u0001\u0016A\u00029CQA\u001a\u0016A\u0002!DQ\u0001\u001c\u0016A\u0002eCQA\u001c\u0016A\u0002!DQ\u0001\u001d\u0016A\u0002!$2\u0001^Ac\u0011\u0015i6\u00061\u0001`)-!\u0018\u0011ZAf\u0003\u001b\fy-!5\t\u000buc\u0003\u0019A0\t\u000b\u0019d\u0003\u0019\u00015\t\u000b1d\u0003\u0019A-\t\u000b9d\u0003\u0019\u00015\t\u000bAd\u0003\u0019\u00015\u00023\t\f7/[2BkRDWM\u001c;jG\u0006$\u0018n\u001c8F]\u000e|G-\u001a\u000b\u0006\u001d\u0006]\u0017\u0011\u001c\u0005\u0006\u00196\u0002\rA\u0014\u0005\u0007\u0003\u000bi\u0003\u0019\u0001(\u0015\u001fQ\fi.a8\u0002b\u0006\r\u0018Q]At\u0003SDQ\u0001\u0014\u0018A\u00029CQa\u0016\u0018A\u0002eCQ!\u0018\u0018A\u0002}CQA\u001a\u0018A\u0002!DQ\u0001\u001c\u0018A\u0002eCQA\u001c\u0018A\u0002!DQ\u0001\u001d\u0018A\u0002!\fAb\u001e:ji\u0016\u0014V\r\u001d7bG\u0016$\"!a<\u0011\t\u0005-\u0014\u0011_\u0005\u0005\u0003g\fiG\u0001\u0004PE*,7\r\u001e
   #13 = Utf8               java/lang/invoke/MethodHandles$Lookup
   #14 = Class              #13           // java/lang/invoke/MethodHandles$Lookup
   #15 = Utf8               java/lang/invoke/MethodHandles
   #16 = Class              #15           // java/lang/invoke/MethodHandles
   #17 = Utf8               Lookup
   #18 = Utf8               user
   #19 = Utf8               Ljava/lang/String;
   #20 = Utf8               passwordOpt
   #21 = Utf8               Lscala/Option;
   #22 = Utf8               Lscala/Option<Ljava/lang/String;>;
   #23 = Utf8               httpHeaders
   #24 = Utf8               Lscala/collection/immutable/Seq;
   #25 = Utf8               Lscala/collection/immutable/Seq<Lscala/Tuple2<Ljava/lang/String;Ljava/lang/String;>;>;
   #26 = Utf8               optional
   #27 = Utf8               Z
   #28 = Utf8               realmOpt
   #29 = Utf8               httpsOnly
   #30 = Utf8               passOnRedirect
   #31 = Utf8               apply
   #32 = Utf8               (Ljava/lang/String;Lscala/Option;Lscala/collection/immutable/Seq;ZLscala/Option;ZZ)Lcoursier/core/Authentication;
   #33 = Utf8               (Ljava/lang/String;Lscala/Option<Ljava/lang/String;>;Lscala/collection/immutable/Seq<Lscala/Tuple2<Ljava/lang/String;Ljava/lang/String;>;>;ZLscala/Option<Ljava/lang/String;>;ZZ)Lcoursier/core/Authentication;
   #34 = Utf8               coursier/core/Authentication$
   #35 = Class              #34           // coursier/core/Authentication$
   #36 = Utf8               MODULE$
   #37 = Utf8               Lcoursier/core/Authentication$;
   #38 = NameAndType        #36:#37       // MODULE$:Lcoursier/core/Authentication$;
   #39 = Fieldref           #35.#38       // coursier/core/Authentication$.MODULE$:Lcoursier/core/Authentication$;
   #40 = NameAndType        #31:#32       // apply:(Ljava/lang/String;Lscala/Option;Lscala/collection/immutable/Seq;ZLscala/Option;ZZ)Lcoursier/core/Authentication;
   #41 = Methodref          #35.#40       // coursier/core/Authentication$.apply:(Ljava/lang/String;Lscala/Option;Lscala/collection/immutable/Seq;ZLscala/Option;ZZ)Lcoursier/core/Authentication;
   #42 = Utf8               (Lscala/collection/immutable/Seq;ZLscala/Option;ZZ)Lcoursier/core/Authentication;
   #43 = Utf8               (Lscala/collection/immutable/Seq<Lscala/Tuple2<Ljava/lang/String;Ljava/lang/String;>;>;ZLscala/Option<Ljava/lang/String;>;ZZ)Lcoursier/core/Authentication;
   #44 = NameAndType        #31:#42       // apply:(Lscala/collection/immutable/Seq;ZLscala/Option;ZZ)Lcoursier/core/Authentication;
   #45 = Methodref          #35.#44       // coursier/core/Authentication$.apply:(Lscala/collection/immutable/Seq;ZLscala/Option;ZZ)Lcoursier/core/Authentication;
   #46 = Utf8               (Lscala/collection/immutable/Seq;)Lcoursier/core/Authentication;
   #47 = Utf8               (Lscala/collection/immutable/Seq<Lscala/Tuple2<Ljava/lang/String;Ljava/lang/String;>;>;)Lcoursier/core/Authentication;
   #48 = NameAndType        #31:#46       // apply:(Lscala/collection/immutable/Seq;)Lcoursier/core/Authentication;
   #49 = Methodref          #35.#48       // coursier/core/Authentication$.apply:(Lscala/collection/immutable/Seq;)Lcoursier/core/Authentication;
   #50 = Utf8               (Ljava/lang/String;Ljava/lang/String;ZLscala/Option;ZZ)Lcoursier/core/Authentication;
   #51 = Utf8               (Ljava/lang/String;Ljava/lang/String;ZLscala/Option<Ljava/lang/String;>;ZZ)Lcoursier/core/Authentication;
   #52 = Utf8               password
   #53 = NameAndType        #31:#50       // apply:(Ljava/lang/String;Ljava/lang/String;ZLscala/Option;ZZ)Lcoursier/core/Authentication;
   #54 = Methodref          #35.#53       // coursier/core/Authentication$.apply:(Ljava/lang/String;Ljava/lang/String;ZLscala/Option;ZZ)Lcoursier/core/Authentication;
   #55 = Utf8               (Ljava/lang/String;Lscala/Option;ZLscala/Option;ZZ)Lcoursier/core/Authentication;
   #56 = Utf8               (Ljava/lang/String;Lscala/Option<Ljava/lang/String;>;ZLscala/Option<Ljava/lang/String;>;ZZ)Lcoursier/core/Authentication;
   #57 = NameAndType        #31:#55       // apply:(Ljava/lang/String;Lscala/Option;ZLscala/Option;ZZ)Lcoursier/core/Authentication;
   #58 = Methodref          #35.#57       // coursier/core/Authentication$.apply:(Ljava/lang/String;Lscala/Option;ZLscala/Option;ZZ)Lcoursier/core/Authentication;
   #59 = Utf8               (Ljava/lang/String;Ljava/lang/String;)Lcoursier/core/Authentication;
   #60 = NameAndType        #31:#59       // apply:(Ljava/lang/String;Ljava/lang/String;)Lcoursier/core/Authentication;
   #61 = Methodref          #35.#60       // coursier/core/Authentication$.apply:(Ljava/lang/String;Ljava/lang/String;)Lcoursier/core/Authentication;
   #62 = Utf8               (Ljava/lang/String;)Lcoursier/core/Authentication;
   #63 = NameAndType        #31:#62       // apply:(Ljava/lang/String;)Lcoursier/core/Authentication;
   #64 = Methodref          #35.#63       // coursier/core/Authentication$.apply:(Ljava/lang/String;)Lcoursier/core/Authentication;
   #65 = Utf8               productIterator
   #66 = Utf8               ()Lscala/collection/Iterator;
   #67 = Utf8               ()Lscala/collection/Iterator<Ljava/lang/Object;>;
   #68 = Utf8               productIterator$
   #69 = Utf8               (Lscala/Product;)Lscala/collection/Iterator;
   #70 = NameAndType        #68:#69       // productIterator$:(Lscala/Product;)Lscala/collection/Iterator;
   #71 = InterfaceMethodref #6.#70        // scala/Product.productIterator$:(Lscala/Product;)Lscala/collection/Iterator;
   #72 = Utf8               this
   #73 = Utf8               Lcoursier/core/Authentication;
   #74 = Utf8               productElementNames
   #75 = Utf8               ()Lscala/collection/Iterator<Ljava/lang/String;>;
   #76 = Utf8               productElementNames$
   #77 = NameAndType        #76:#69       // productElementNames$:(Lscala/Product;)Lscala/collection/Iterator;
   #78 = InterfaceMethodref #6.#77        // scala/Product.productElementNames$:(Lscala/Product;)Lscala/collection/Iterator;
   #79 = Utf8               ()Ljava/lang/String;
   #80 = NameAndType        #18:#19       // user:Ljava/lang/String;
   #81 = Fieldref           #2.#80        // coursier/core/Authentication.user:Ljava/lang/String;
   #82 = Utf8               ()Lscala/Option;
   #83 = Utf8               ()Lscala/Option<Ljava/lang/String;>;
   #84 = NameAndType        #20:#21       // passwordOpt:Lscala/Option;
   #85 = Fieldref           #2.#84        // coursier/core/Authentication.passwordOpt:Lscala/Option;
   #86 = Utf8               ()Lscala/collection/immutable/Seq;
   #87 = Utf8               ()Lscala/collection/immutable/Seq<Lscala/Tuple2<Ljava/lang/String;Ljava/lang/String;>;>;
   #88 = NameAndType        #23:#24       // httpHeaders:Lscala/collection/immutable/Seq;
   #89 = Fieldref           #2.#88        // coursier/core/Authentication.httpHeaders:Lscala/collection/immutable/Seq;
   #90 = Utf8               ()Z
   #91 = NameAndType        #26:#27       // optional:Z
   #92 = Fieldref           #2.#91        // coursier/core/Authentication.optional:Z
   #93 = NameAndType        #28:#21       // realmOpt:Lscala/Option;
   #94 = Fieldref           #2.#93        // coursier/core/Authentication.realmOpt:Lscala/Option;
   #95 = NameAndType        #29:#27       // httpsOnly:Z
   #96 = Fieldref           #2.#95        // coursier/core/Authentication.httpsOnly:Z
   #97 = NameAndType        #30:#27       // passOnRedirect:Z
   #98 = Fieldref           #2.#97        // coursier/core/Authentication.passOnRedirect:Z
   #99 = Utf8               toString
  #100 = Utf8               java/lang/StringBuilder
  #101 = Class              #100          // java/lang/StringBuilder
  #102 = Integer            32
  #103 = Utf8               <init>
  #104 = Utf8               (I)V
  #105 = NameAndType        #103:#104     // "<init>":(I)V
  #106 = Methodref          #101.#105     // java/lang/StringBuilder."<init>":(I)V
  #107 = Utf8               Authentication(
  #108 = String             #107          // Authentication(
  #109 = Utf8               append
  #110 = Utf8               (Ljava/lang/String;)Ljava/lang/StringBuilder;
  #111 = NameAndType        #109:#110     // append:(Ljava/lang/String;)Ljava/lang/StringBuilder;
  #112 = Methodref          #101.#111     // java/lang/StringBuilder.append:(Ljava/lang/String;)Ljava/lang/StringBuilder;
  #113 = NameAndType        #18:#79       // user:()Ljava/lang/String;
  #114 = Methodref          #2.#113       // coursier/core/Authentication.user:()Ljava/lang/String;
  #115 = Utf8               , ****,
  #116 = String             #115          // , ****,
  #117 = NameAndType        #23:#86       // httpHeaders:()Lscala/collection/immutable/Seq;
  #118 = Methodref          #2.#117       // coursier/core/Authentication.httpHeaders:()Lscala/collection/immutable/Seq;
  #119 = Utf8               (Ljava/lang/Object;)Ljava/lang/Object;
  #120 = MethodType         #119          //  (Ljava/lang/Object;)Ljava/lang/Object;
  #121 = Utf8               $anonfun$toString$1
  #122 = Utf8               (Lscala/Tuple2;)Lscala/Tuple2;
  #123 = NameAndType        #121:#122     // $anonfun$toString$1:(Lscala/Tuple2;)Lscala/Tuple2;
  #124 = Methodref          #2.#123       // coursier/core/Authentication.$anonfun$toString$1:(Lscala/Tuple2;)Lscala/Tuple2;
  #125 = MethodHandle       6:#124        // REF_invokeStatic coursier/core/Authentication.$anonfun$toString$1:(Lscala/Tuple2;)Lscala/Tuple2;
  #126 = MethodType         #122          //  (Lscala/Tuple2;)Lscala/Tuple2;
  #127 = Integer            5
  #128 = Integer            1
  #129 = Utf8               java/lang/invoke/LambdaMetafactory
  #130 = Class              #129          // java/lang/invoke/LambdaMetafactory
  #131 = Utf8               altMetafactory
  #132 = Utf8               (Ljava/lang/invoke/MethodHandles$Lookup;Ljava/lang/String;Ljava/lang/invoke/MethodType;[Ljava/lang/Object;)Ljava/lang/invoke/CallSite;
  #133 = NameAndType        #131:#132     // altMetafactory:(Ljava/lang/invoke/MethodHandles$Lookup;Ljava/lang/String;Ljava/lang/invoke/MethodType;[Ljava/lang/Object;)Ljava/lang/invoke/CallSite;
  #134 = Methodref          #130.#133     // java/lang/invoke/LambdaMetafactory.altMetafactory:(Ljava/lang/invoke/MethodHandles$Lookup;Ljava/lang/String;Ljava/lang/invoke/MethodType;[Ljava/lang/Object;)Ljava/lang/invoke/CallSite;
  #135 = MethodHandle       6:#134        // REF_invokeStatic java/lang/invoke/LambdaMetafactory.altMetafactory:(Ljava/lang/invoke/MethodHandles$Lookup;Ljava/lang/String;Ljava/lang/invoke/MethodType;[Ljava/lang/Object;)Ljava/lang/invoke/CallSite;
  #136 = Utf8               ()Lscala/Function1;
  #137 = NameAndType        #31:#136      // apply:()Lscala/Function1;
  #138 = InvokeDynamic      #0:#137       // #0:apply:()Lscala/Function1;
  #139 = Utf8               scala/collection/immutable/Seq
  #140 = Class              #139          // scala/collection/immutable/Seq
  #141 = Utf8               map
  #142 = Utf8               (Lscala/Function1;)Ljava/lang/Object;
  #143 = NameAndType        #141:#142     // map:(Lscala/Function1;)Ljava/lang/Object;
  #144 = InterfaceMethodref #140.#143     // scala/collection/immutable/Seq.map:(Lscala/Function1;)Ljava/lang/Object;
  #145 = Utf8               (Ljava/lang/Object;)Ljava/lang/StringBuilder;
  #146 = NameAndType        #109:#145     // append:(Ljava/lang/Object;)Ljava/lang/StringBuilder;
  #147 = Methodref          #101.#146     // java/lang/StringBuilder.append:(Ljava/lang/Object;)Ljava/lang/StringBuilder;
  #148 = Utf8               ,
  #149 = String             #148          // ,
  #150 = NameAndType        #26:#90       // optional:()Z
  #151 = Methodref          #2.#150       // coursier/core/Authentication.optional:()Z
  #152 = Utf8               (Z)Ljava/lang/StringBuilder;
  #153 = NameAndType        #109:#152     // append:(Z)Ljava/lang/StringBuilder;
  #154 = Methodref          #101.#153     // java/lang/StringBuilder.append:(Z)Ljava/lang/StringBuilder;
  #155 = NameAndType        #28:#82       // realmOpt:()Lscala/Option;
  #156 = Methodref          #2.#155       // coursier/core/Authentication.realmOpt:()Lscala/Option;
  #157 = NameAndType        #29:#90       // httpsOnly:()Z
  #158 = Methodref          #2.#157       // coursier/core/Authentication.httpsOnly:()Z
  #159 = NameAndType        #30:#90       // passOnRedirect:()Z
  #160 = Methodref          #2.#159       // coursier/core/Authentication.passOnRedirect:()Z
  #161 = Utf8               )
  #162 = String             #161          // )
  #163 = NameAndType        #99:#79       // toString:()Ljava/lang/String;
  #164 = Methodref          #101.#163     // java/lang/StringBuilder.toString:()Ljava/lang/String;
  #165 = Utf8               withPassword
  #166 = Utf8               scala/Some
  #167 = Class              #166          // scala/Some
  #168 = Utf8               (Ljava/lang/Object;)V
  #169 = NameAndType        #103:#168     // "<init>":(Ljava/lang/Object;)V
  #170 = Methodref          #167.#169     // scala/Some."<init>":(Ljava/lang/Object;)V
  #171 = Utf8               withPasswordOpt
  #172 = Utf8               (Lscala/Option;)Lcoursier/core/Authentication;
  #173 = NameAndType        #171:#172     // withPasswordOpt:(Lscala/Option;)Lcoursier/core/Authentication;
  #174 = Methodref          #2.#173       // coursier/core/Authentication.withPasswordOpt:(Lscala/Option;)Lcoursier/core/Authentication;
  #175 = Utf8               withRealm
  #176 = Utf8               realm
  #177 = Utf8               withRealmOpt
  #178 = NameAndType        #177:#172     // withRealmOpt:(Lscala/Option;)Lcoursier/core/Authentication;
  #179 = Methodref          #2.#178       // coursier/core/Authentication.withRealmOpt:(Lscala/Option;)Lcoursier/core/Authentication;
  #180 = Utf8               userOnly
  #181 = Utf8               equals
  #182 = Utf8               (Ljava/lang/Object;)Z
  #183 = NameAndType        #181:#182     // equals:(Ljava/lang/Object;)Z
  #184 = Methodref          #4.#183       // java/lang/Object.equals:(Ljava/lang/Object;)Z
  #185 = Utf8               allHttpHeaders
  #186 = Utf8               scala/Option$
  #187 = Class              #186          // scala/Option$
  #188 = Utf8               Lscala/Option$;
  #189 = NameAndType        #36:#188      // MODULE$:Lscala/Option$;
  #190 = Fieldref           #187.#189     // scala/Option$.MODULE$:Lscala/Option$;
  #191 = NameAndType        #20:#82       // passwordOpt:()Lscala/Option;
  #192 = Methodref          #2.#191       // coursier/core/Authentication.passwordOpt:()Lscala/Option;
  #193 = Utf8               option2Iterable
  #194 = Utf8               (Lscala/Option;)Lscala/collection/Iterable;
  #195 = NameAndType        #193:#194     // option2Iterable:(Lscala/Option;)Lscala/collection/Iterable;
  #196 = Methodref          #187.#195     // scala/Option$.option2Iterable:(Lscala/Option;)Lscala/collection/Iterable;
  #197 = Utf8               scala/collection/Iterable
  #198 = Class              #197          // scala/collection/Iterable
  #199 = Utf8               toSeq
  #200 = NameAndType        #199:#86      // toSeq:()Lscala/collection/immutable/Seq;
  #201 = InterfaceMethodref #198.#200     // scala/collection/Iterable.toSeq:()Lscala/collection/immutable/Seq;
  #202 = Utf8               $anonfun$allHttpHeaders$1
  #203 = Utf8               (Lcoursier/core/Authentication;Ljava/lang/String;)Lscala/Tuple2;
  #204 = NameAndType        #202:#203     // $anonfun$allHttpHeaders$1:(Lcoursier/core/Authentication;Ljava/lang/String;)Lscala/Tuple2;
  #205 = Methodref          #2.#204       // coursier/core/Authentication.$anonfun$allHttpHeaders$1:(Lcoursier/core/Authentication;Ljava/lang/String;)Lscala/Tuple2;
  #206 = MethodHandle       6:#205        // REF_invokeStatic coursier/core/Authentication.$anonfun$allHttpHeaders$1:(Lcoursier/core/Authentication;Ljava/lang/String;)Lscala/Tuple2;
  #207 = Utf8               (Ljava/lang/String;)Lscala/Tuple2;
  #208 = MethodType         #207          //  (Ljava/lang/String;)Lscala/Tuple2;
  #209 = Utf8               (Lcoursier/core/Authentication;)Lscala/Function1;
  #210 = NameAndType        #31:#209      // apply:(Lcoursier/core/Authentication;)Lscala/Function1;
  #211 = InvokeDynamic      #1:#210       // #1:apply:(Lcoursier/core/Authentication;)Lscala/Function1;
  #212 = Utf8               $plus$plus
  #213 = Utf8               (Lscala/collection/IterableOnce;)Ljava/lang/Object;
  #214 = NameAndType        #212:#213     // $plus$plus:(Lscala/collection/IterableOnce;)Ljava/lang/Object;
  #215 = InterfaceMethodref #140.#214     // scala/collection/immutable/Seq.$plus$plus:(Lscala/collection/IterableOnce;)Ljava/lang/Object;
  #216 = Utf8               basicAuthHeader
  #217 = Utf8               withUser
  #218 = Utf8               (Ljava/lang/String;Lscala/Option;Lscala/collection/immutable/Seq;ZLscala/Option;ZZ)V
  #219 = NameAndType        #103:#218     // "<init>":(Ljava/lang/String;Lscala/Option;Lscala/collection/immutable/Seq;ZLscala/Option;ZZ)V
  #220 = Methodref          #2.#219       // coursier/core/Authentication."<init>":(Ljava/lang/String;Lscala/Option;Lscala/collection/immutable/Seq;ZLscala/Option;ZZ)V
  #221 = Utf8               (Lscala/Option<Ljava/lang/String;>;)Lcoursier/core/Authentication;
  #222 = Utf8               withHttpHeaders
  #223 = Utf8               withOptional
  #224 = Utf8               (Z)Lcoursier/core/Authentication;
  #225 = Utf8               withHttpsOnly
  #226 = Utf8               withPassOnRedirect
  #227 = Utf8               canEqual
  #228 = Utf8               obj
  #229 = Utf8               Ljava/lang/Object;
  #230 = NameAndType        #227:#182     // canEqual:(Ljava/lang/Object;)Z
  #231 = Methodref          #2.#230       // coursier/core/Authentication.canEqual:(Ljava/lang/Object;)Z
  #232 = Utf8               java/lang/String
  #233 = Class              #232          // java/lang/String
  #234 = Utf8               scala/Option
  #235 = Class              #234          // scala/Option
  #236 = Utf8               other
  #237 = Utf8               hashCode
  #238 = Utf8               ()I
  #239 = Utf8               Authentication
  #240 = String             #239          // Authentication
  #241 = Utf8               scala/runtime/Statics
  #242 = Class              #241          // scala/runtime/Statics
  #243 = Utf8               anyHash
  #244 = Utf8               (Ljava/lang/Object;)I
  #245 = NameAndType        #243:#244     // anyHash:(Ljava/lang/Object;)I
  #246 = Methodref          #242.#245     // scala/runtime/Statics.anyHash:(Ljava/lang/Object;)I
  #247 = Utf8               code
  #248 = Utf8               I
  #249 = Utf8               tuple
  #250 = Utf8               ()Lscala/Tuple7;
  #251 = Utf8               ()Lscala/Tuple7<Ljava/lang/String;Lscala/Option<Ljava/lang/String;>;Lscala/collection/immutable/Seq<Lscala/Tuple2<Ljava/lang/String;Ljava/lang/String;>;>;Ljava/lang/Object;Lscala/Option<Ljava/lang/String;>;Ljava/lang/Object;Ljava/lang/Object;>;
  #252 = Utf8               scala/Tuple7
  #253 = Class              #252          // scala/Tuple7
  #254 = Utf8               scala/runtime/BoxesRunTime
  #255 = Class              #254          // scala/runtime/BoxesRunTime
  #256 = Utf8               boxToBoolean
  #257 = Utf8               (Z)Ljava/lang/Boolean;
  #258 = NameAndType        #256:#257     // boxToBoolean:(Z)Ljava/lang/Boolean;
  #259 = Methodref          #255.#258     // scala/runtime/BoxesRunTime.boxToBoolean:(Z)Ljava/lang/Boolean;
  #260 = Utf8               (Ljava/lang/Object;Ljava/lang/Object;Ljava/lang/Object;Ljava/lang/Object;Ljava/lang/Object;Ljava/lang/Object;Ljava/lang/Object;)V
  #261 = NameAndType        #103:#260     // "<init>":(Ljava/lang/Object;Ljava/lang/Object;Ljava/lang/Object;Ljava/lang/Object;Ljava/lang/Object;Ljava/lang/Object;Ljava/lang/Object;)V
  #262 = Methodref          #253.#261     // scala/Tuple7."<init>":(Ljava/lang/Object;Ljava/lang/Object;Ljava/lang/Object;Ljava/lang/Object;Ljava/lang/Object;Ljava/lang/Object;Ljava/lang/Object;)V
  #263 = Utf8               productPrefix
  #264 = Utf8               productArity
  #265 = Utf8               productElement
  #266 = Utf8               (I)Ljava/lang/Object;
  #267 = Utf8               n
  #268 = Utf8               java/lang/IndexOutOfBoundsException
  #269 = Class              #268          // java/lang/IndexOutOfBoundsException
  #270 = Utf8               boxToInteger
  #271 = Utf8               (I)Ljava/lang/Integer;
  #272 = NameAndType        #270:#271     // boxToInteger:(I)Ljava/lang/Integer;
  #273 = Methodref          #255.#272     // scala/runtime/BoxesRunTime.boxToInteger:(I)Ljava/lang/Integer;
  #274 = Methodref          #4.#163       // java/lang/Object.toString:()Ljava/lang/String;
  #275 = Utf8               (Ljava/lang/String;)V
  #276 = NameAndType        #103:#275     // "<init>":(Ljava/lang/String;)V
  #277 = Methodref          #269.#276     // java/lang/IndexOutOfBoundsException."<init>":(Ljava/lang/String;)V
  #278 = Utf8               productElementName
  #279 = Utf8               (I)Ljava/lang/String;
  #280 = String             #18           // user
  #281 = String             #20           // passwordOpt
  #282 = String             #23           // httpHeaders
  #283 = String             #26           // optional
  #284 = String             #28           // realmOpt
  #285 = String             #29           // httpsOnly
  #286 = String             #30           // passOnRedirect
  #287 = Utf8               x0$1
  #288 = Utf8               scala/Tuple2
  #289 = Class              #288          // scala/Tuple2
  #290 = Utf8               _1
  #291 = Utf8               ()Ljava/lang/Object;
  #292 = NameAndType        #290:#291     // _1:()Ljava/lang/Object;
  #293 = Methodref          #289.#292     // scala/Tuple2._1:()Ljava/lang/Object;
  #294 = Utf8               ****
  #295 = String             #294          // ****
  #296 = Utf8               (Ljava/lang/Object;Ljava/lang/Object;)V
  #297 = NameAndType        #103:#296     // "<init>":(Ljava/lang/Object;Ljava/lang/Object;)V
  #298 = Methodref          #289.#297     // scala/Tuple2."<init>":(Ljava/lang/Object;Ljava/lang/Object;)V
  #299 = Utf8               scala/MatchError
  #300 = Class              #299          // scala/MatchError
  #301 = Methodref          #300.#169     // scala/MatchError."<init>":(Ljava/lang/Object;)V
  #302 = Utf8               k
  #303 = Utf8               Lscala/Tuple2;
  #304 = Utf8               $this
  #305 = Utf8               p
  #306 = Utf8               Authorization
  #307 = String             #306          // Authorization
  #308 = Integer            6
  #309 = Utf8               Basic
  #310 = String             #309          // Basic
  #311 = Utf8               basicAuthenticationEncode
  #312 = Utf8               (Ljava/lang/String;Ljava/lang/String;)Ljava/lang/String;
  #313 = NameAndType        #311:#312     // basicAuthenticationEncode:(Ljava/lang/String;Ljava/lang/String;)Ljava/lang/String;
  #314 = Methodref          #35.#313      // coursier/core/Authentication$.basicAuthenticationEncode:(Ljava/lang/String;Ljava/lang/String;)Ljava/lang/String;
  #315 = Utf8               (Ljava/lang/String;Lscala/Option<Ljava/lang/String;>;Lscala/collection/immutable/Seq<Lscala/Tuple2<Ljava/lang/String;Ljava/lang/String;>;>;ZLscala/Option<Ljava/lang/String;>;ZZ)V
  #316 = Utf8               ()V
  #317 = NameAndType        #103:#316     // "<init>":()V
  #318 = Methodref          #4.#317       // java/lang/Object."<init>":()V
  #319 = Utf8               $init$
  #320 = Utf8               (Lscala/Product;)V
  #321 = NameAndType        #319:#320     // $init$:(Lscala/Product;)V
  #322 = InterfaceMethodref #6.#321       // scala/Product.$init$:(Lscala/Product;)V
  #323 = Utf8               $deserializeLambda$
  #324 = Utf8               (Ljava/lang/invoke/SerializedLambda;)Ljava/lang/Object;
  #325 = Utf8               scala/runtime/LambdaDeserialize
  #326 = Class              #325          // scala/runtime/LambdaDeserialize
  #327 = Utf8               bootstrap
  #328 = Utf8               (Ljava/lang/invoke/MethodHandles$Lookup;Ljava/lang/String;Ljava/lang/invoke/MethodType;[Ljava/lang/invoke/MethodHandle;)Ljava/lang/invoke/CallSite;
  #329 = NameAndType        #327:#328     // bootstrap:(Ljava/lang/invoke/MethodHandles$Lookup;Ljava/lang/String;Ljava/lang/invoke/MethodType;[Ljava/lang/invoke/MethodHandle;)Ljava/lang/invoke/CallSite;
  #330 = Methodref          #326.#329     // scala/runtime/LambdaDeserialize.bootstrap:(Ljava/lang/invoke/MethodHandles$Lookup;Ljava/lang/String;Ljava/lang/invoke/MethodType;[Ljava/lang/invoke/MethodHandle;)Ljava/lang/invoke/CallSite;
  #331 = MethodHandle       6:#330        // REF_invokeStatic scala/runtime/LambdaDeserialize.bootstrap:(Ljava/lang/invoke/MethodHandles$Lookup;Ljava/lang/String;Ljava/lang/invoke/MethodType;[Ljava/lang/invoke/MethodHandle;)Ljava/lang/invoke/CallSite;
  #332 = Utf8               lambdaDeserialize
  #333 = NameAndType        #332:#324     // lambdaDeserialize:(Ljava/lang/invoke/SerializedLambda;)Ljava/lang/Object;
  #334 = InvokeDynamic      #2:#333       // #2:lambdaDeserialize:(Ljava/lang/invoke/SerializedLambda;)Ljava/lang/Object;
  #335 = Utf8               Signature
  #336 = Utf8               Code
  #337 = Utf8               MethodParameters
  #338 = Utf8               LineNumberTable
  #339 = Utf8               LocalVariableTable
  #340 = Utf8               StackMapTable
  #341 = Utf8               InnerClasses
  #342 = Utf8               SourceFile
  #343 = Utf8               RuntimeVisibleAnnotations
  #344 = Utf8               BootstrapMethods
  #345 = Utf8               ScalaInlineInfo
  #346 = Utf8               ScalaSig
{
  private final java.lang.String user;
    descriptor: Ljava/lang/String;
    flags: (0x0012) ACC_PRIVATE, ACC_FINAL

  private final scala.Option<java.lang.String> passwordOpt;
    descriptor: Lscala/Option;
    flags: (0x0012) ACC_PRIVATE, ACC_FINAL
    Signature: #22                          // Lscala/Option<Ljava/lang/String;>;

  private final scala.collection.immutable.Seq<scala.Tuple2<java.lang.String, java.lang.String>> httpHeaders;
    descriptor: Lscala/collection/immutable/Seq;
    flags: (0x0012) ACC_PRIVATE, ACC_FINAL
    Signature: #25                          // Lscala/collection/immutable/Seq<Lscala/Tuple2<Ljava/lang/String;Ljava/lang/String;>;>;

  private final boolean optional;
    descriptor: Z
    flags: (0x0012) ACC_PRIVATE, ACC_FINAL

  private final scala.Option<java.lang.String> realmOpt;
    descriptor: Lscala/Option;
    flags: (0x0012) ACC_PRIVATE, ACC_FINAL
    Signature: #22                          // Lscala/Option<Ljava/lang/String;>;

  private final boolean httpsOnly;
    descriptor: Z
    flags: (0x0012) ACC_PRIVATE, ACC_FINAL

  private final boolean passOnRedirect;
    descriptor: Z
    flags: (0x0012) ACC_PRIVATE, ACC_FINAL

  public static coursier.core.Authentication apply(java.lang.String, scala.Option<java.lang.String>, scala.collection.immutable.Seq<scala.Tuple2<java.lang.String, java.lang.String>>, boolean, scala.Option<java.lang.String>, boolean, boolean);
    descriptor: (Ljava/lang/String;Lscala/Option;Lscala/collection/immutable/Seq;ZLscala/Option;ZZ)Lcoursier/core/Authentication;
    flags: (0x0009) ACC_PUBLIC, ACC_STATIC
    Code:
      stack=8, locals=7, args_size=7
         0: getstatic     #39                 // Field coursier/core/Authentication$.MODULE$:Lcoursier/core/Authentication$;
         3: aload_0
         4: aload_1
         5: aload_2
         6: iload_3
         7: aload         4
         9: iload         5
        11: iload         6
        13: invokevirtual #41                 // Method coursier/core/Authentication$.apply:(Ljava/lang/String;Lscala/Option;Lscala/collection/immutable/Seq;ZLscala/Option;ZZ)Lcoursier/core/Authentication;
        16: areturn
    Signature: #33                          // (Ljava/lang/String;Lscala/Option<Ljava/lang/String;>;Lscala/collection/immutable/Seq<Lscala/Tuple2<Ljava/lang/String;Ljava/lang/String;>;>;ZLscala/Option<Ljava/lang/String;>;ZZ)Lcoursier/core/Authentication;
    MethodParameters:
      Name                           Flags
      user                           final
      passwordOpt                    final
      httpHeaders                    final
      optional                       final
      realmOpt                       final
      httpsOnly                      final
      passOnRedirect                 final

  public static coursier.core.Authentication apply(scala.collection.immutable.Seq<scala.Tuple2<java.lang.String, java.lang.String>>, boolean, scala.Option<java.lang.String>, boolean, boolean);
    descriptor: (Lscala/collection/immutable/Seq;ZLscala/Option;ZZ)Lcoursier/core/Authentication;
    flags: (0x0009) ACC_PUBLIC, ACC_STATIC
    Code:
      stack=6, locals=5, args_size=5
         0: getstatic     #39                 // Field coursier/core/Authentication$.MODULE$:Lcoursier/core/Authentication$;
         3: aload_0
         4: iload_1
         5: aload_2
         6: iload_3
         7: iload         4
         9: invokevirtual #45                 // Method coursier/core/Authentication$.apply:(Lscala/collection/immutable/Seq;ZLscala/Option;ZZ)Lcoursier/core/Authentication;
        12: areturn
    Signature: #43                          // (Lscala/collection/immutable/Seq<Lscala/Tuple2<Ljava/lang/String;Ljava/lang/String;>;>;ZLscala/Option<Ljava/lang/String;>;ZZ)Lcoursier/core/Authentication;
    MethodParameters:
      Name                           Flags
      httpHeaders                    final
      optional                       final
      realmOpt                       final
      httpsOnly                      final
      passOnRedirect                 final

  public static coursier.core.Authentication apply(scala.collection.immutable.Seq<scala.Tuple2<java.lang.String, java.lang.String>>);
    descriptor: (Lscala/collection/immutable/Seq;)Lcoursier/core/Authentication;
    flags: (0x0009) ACC_PUBLIC, ACC_STATIC
    Code:
      stack=2, locals=1, args_size=1
         0: getstatic     #39                 // Field coursier/core/Authentication$.MODULE$:Lcoursier/core/Authentication$;
         3: aload_0
         4: invokevirtual #49                 // Method coursier/core/Authentication$.apply:(Lscala/collection/immutable/Seq;)Lcoursier/core/Authentication;
         7: areturn
    Signature: #47                          // (Lscala/collection/immutable/Seq<Lscala/Tuple2<Ljava/lang/String;Ljava/lang/String;>;>;)Lcoursier/core/Authentication;
    MethodParameters:
      Name                           Flags
      httpHeaders                    final

  public static coursier.core.Authentication apply(java.lang.String, java.lang.String, boolean, scala.Option<java.lang.String>, boolean, boolean);
    descriptor: (Ljava/lang/String;Ljava/lang/String;ZLscala/Option;ZZ)Lcoursier/core/Authentication;
    flags: (0x0009) ACC_PUBLIC, ACC_STATIC
    Code:
      stack=7, locals=6, args_size=6
         0: getstatic     #39                 // Field coursier/core/Authentication$.MODULE$:Lcoursier/core/Authentication$;
         3: aload_0
         4: aload_1
         5: iload_2
         6: aload_3
         7: iload         4
         9: iload         5
        11: invokevirtual #54                 // Method coursier/core/Authentication$.apply:(Ljava/lang/String;Ljava/lang/String;ZLscala/Option;ZZ)Lcoursier/core/Authentication;
        14: areturn
    Signature: #51                          // (Ljava/lang/String;Ljava/lang/String;ZLscala/Option<Ljava/lang/String;>;ZZ)Lcoursier/core/Authentication;
    MethodParameters:
      Name                           Flags
      user                           final
      password                       final
      optional                       final
      realmOpt                       final
      httpsOnly                      final
      passOnRedirect                 final

  public static coursier.core.Authentication apply(java.lang.String, scala.Option<java.lang.String>, boolean, scala.Option<java.lang.String>, boolean, boolean);
    descriptor: (Ljava/lang/String;Lscala/Option;ZLscala/Option;ZZ)Lcoursier/core/Authentication;
    flags: (0x0009) ACC_PUBLIC, ACC_STATIC
    Code:
      stack=7, locals=6, args_size=6
         0: getstatic     #39                 // Field coursier/core/Authentication$.MODULE$:Lcoursier/core/Authentication$;
         3: aload_0
         4: aload_1
         5: iload_2
         6: aload_3
         7: iload         4
         9: iload         5
        11: invokevirtual #58                 // Method coursier/core/Authentication$.apply:(Ljava/lang/String;Lscala/Option;ZLscala/Option;ZZ)Lcoursier/core/Authentication;
        14: areturn
    Signature: #56                          // (Ljava/lang/String;Lscala/Option<Ljava/lang/String;>;ZLscala/Option<Ljava/lang/String;>;ZZ)Lcoursier/core/Authentication;
    MethodParameters:
      Name                           Flags
      user                           final
      passwordOpt                    final
      optional                       final
      realmOpt                       final
      httpsOnly                      final
      passOnRedirect                 final

  public static coursier.core.Authentication apply(java.lang.String, java.lang.String);
    descriptor: (Ljava/lang/String;Ljava/lang/String;)Lcoursier/core/Authentication;
    flags: (0x0009) ACC_PUBLIC, ACC_STATIC
    Code:
      stack=3, locals=2, args_size=2
         0: getstatic     #39                 // Field coursier/core/Authentication$.MODULE$:Lcoursier/core/Authentication$;
         3: aload_0
         4: aload_1
         5: invokevirtual #61                 // Method coursier/core/Authentication$.apply:(Ljava/lang/String;Ljava/lang/String;)Lcoursier/core/Authentication;
         8: areturn
    MethodParameters:
      Name                           Flags
      user                           final
      password                       final

  public static coursier.core.Authentication apply(java.lang.String);
    descriptor: (Ljava/lang/String;)Lcoursier/core/Authentication;
    flags: (0x0009) ACC_PUBLIC, ACC_STATIC
    Code:
      stack=2, locals=1, args_size=1
         0: getstatic     #39                 // Field coursier/core/Authentication$.MODULE$:Lcoursier/core/Authentication$;
         3: aload_0
         4: invokevirtual #64                 // Method coursier/core/Authentication$.apply:(Ljava/lang/String;)Lcoursier/core/Authentication;
         7: areturn
    MethodParameters:
      Name                           Flags
      user                           final

  public scala.collection.Iterator<java.lang.Object> productIterator();
    descriptor: ()Lscala/collection/Iterator;
    flags: (0x0001) ACC_PUBLIC
    Code:
      stack=1, locals=1, args_size=1
         0: aload_0
         1: invokestatic  #71                 // InterfaceMethod scala/Product.productIterator$:(Lscala/Product;)Lscala/collection/Iterator;
         4: areturn
      LineNumberTable:
        line 8: 0
      LocalVariableTable:
        Start  Length  Slot  Name   Signature
            0       5     0  this   Lcoursier/core/Authentication;
    Signature: #67                          // ()Lscala/collection/Iterator<Ljava/lang/Object;>;

  public scala.collection.Iterator<java.lang.String> productElementNames();
    descriptor: ()Lscala/collection/Iterator;
    flags: (0x0001) ACC_PUBLIC
    Code:
      stack=1, locals=1, args_size=1
         0: aload_0
         1: invokestatic  #78                 // InterfaceMethod scala/Product.productElementNames$:(Lscala/Product;)Lscala/collection/Iterator;
         4: areturn
      LineNumberTable:
        line 8: 0
      LocalVariableTable:
        Start  Length  Slot  Name   Signature
            0       5     0  this   Lcoursier/core/Authentication;
    Signature: #75                          // ()Lscala/collection/Iterator<Ljava/lang/String;>;

  public java.lang.String user();
    descriptor: ()Ljava/lang/String;
    flags: (0x0001) ACC_PUBLIC
    Code:
      stack=1, locals=1, args_size=1
         0: aload_0
         1: getfield      #81                 // Field user:Ljava/lang/String;
         4: areturn
      LineNumberTable:
        line 8: 0
      LocalVariableTable:
        Start  Length  Slot  Name   Signature
            0       5     0  this   Lcoursier/core/Authentication;

  public scala.Option<java.lang.String> passwordOpt();
    descriptor: ()Lscala/Option;
    flags: (0x0001) ACC_PUBLIC
    Code:
      stack=1, locals=1, args_size=1
         0: aload_0
         1: getfield      #85                 // Field passwordOpt:Lscala/Option;
         4: areturn
      LineNumberTable:
        line 8: 0
      LocalVariableTable:
        Start  Length  Slot  Name   Signature
            0       5     0  this   Lcoursier/core/Authentication;
    Signature: #83                          // ()Lscala/Option<Ljava/lang/String;>;

  public scala.collection.immutable.Seq<scala.Tuple2<java.lang.String, java.lang.String>> httpHeaders();
    descriptor: ()Lscala/collection/immutable/Seq;
    flags: (0x0001) ACC_PUBLIC
    Code:
      stack=1, locals=1, args_size=1
         0: aload_0
         1: getfield      #89                 // Field httpHeaders:Lscala/collection/immutable/Seq;
         4: areturn
      LineNumberTable:
        line 8: 0
      LocalVariableTable:
        Start  Length  Slot  Name   Signature
            0       5     0  this   Lcoursier/core/Authentication;
    Signature: #87                          // ()Lscala/collection/immutable/Seq<Lscala/Tuple2<Ljava/lang/String;Ljava/lang/String;>;>;

  public boolean optional();
    descriptor: ()Z
    flags: (0x0001) ACC_PUBLIC
    Code:
      stack=1, locals=1, args_size=1
         0: aload_0
         1: getfield      #92                 // Field optional:Z
         4: ireturn
      LineNumberTable:
        line 8: 0
      LocalVariableTable:
        Start  Length  Slot  Name   Signature
            0       5     0  this   Lcoursier/core/Authentication;

  public scala.Option<java.lang.String> realmOpt();
    descriptor: ()Lscala/Option;
    flags: (0x0001) ACC_PUBLIC
    Code:
      stack=1, locals=1, args_size=1
         0: aload_0
         1: getfield      #94                 // Field realmOpt:Lscala/Option;
         4: areturn
      LineNumberTable:
        line 8: 0
      LocalVariableTable:
        Start  Length  Slot  Name   Signature
            0       5     0  this   Lcoursier/core/Authentication;
    Signature: #83                          // ()Lscala/Option<Ljava/lang/String;>;

  public boolean httpsOnly();
    descriptor: ()Z
    flags: (0x0001) ACC_PUBLIC
    Code:
      stack=1, locals=1, args_size=1
         0: aload_0
         1: getfield      #96                 // Field httpsOnly:Z
         4: ireturn
      LineNumberTable:
        line 8: 0
      LocalVariableTable:
        Start  Length  Slot  Name   Signature
            0       5     0  this   Lcoursier/core/Authentication;

  public boolean passOnRedirect();
    descriptor: ()Z
    flags: (0x0001) ACC_PUBLIC
    Code:
      stack=1, locals=1, args_size=1
         0: aload_0
         1: getfield      #98                 // Field passOnRedirect:Z
         4: ireturn
      LineNumberTable:
        line 8: 0
      LocalVariableTable:
        Start  Length  Slot  Name   Signature
            0       5     0  this   Lcoursier/core/Authentication;

  public java.lang.String toString();
    descriptor: ()Ljava/lang/String;
    flags: (0x0001) ACC_PUBLIC
    Code:
      stack=3, locals=1, args_size=1
         0: new           #101                // class java/lang/StringBuilder
         3: dup
         4: ldc           #102                // int 32
         6: invokespecial #106                // Method java/lang/StringBuilder."<init>":(I)V
         9: ldc           #108                // String Authentication(
        11: invokevirtual #112                // Method java/lang/StringBuilder.append:(Ljava/lang/String;)Ljava/lang/StringBuilder;
        14: aload_0
        15: invokevirtual #114                // Method user:()Ljava/lang/String;
        18: invokevirtual #112                // Method java/lang/StringBuilder.append:(Ljava/lang/String;)Ljava/lang/StringBuilder;
        21: ldc           #116                // String , ****,
        23: invokevirtual #112                // Method java/lang/StringBuilder.append:(Ljava/lang/String;)Ljava/lang/StringBuilder;
        26: aload_0
        27: invokevirtual #118                // Method httpHeaders:()Lscala/collection/immutable/Seq;
        30: invokedynamic #138,  0            // InvokeDynamic #0:apply:()Lscala/Function1;
        35: invokeinterface #144,  2          // InterfaceMethod scala/collection/immutable/Seq.map:(Lscala/Function1;)Ljava/lang/Object;
        40: invokevirtual #147                // Method java/lang/StringBuilder.append:(Ljava/lang/Object;)Ljava/lang/StringBuilder;
        43: ldc           #149                // String ,
        45: invokevirtual #112                // Method java/lang/StringBuilder.append:(Ljava/lang/String;)Ljava/lang/StringBuilder;
        48: aload_0
        49: invokevirtual #151                // Method optional:()Z
        52: invokevirtual #154                // Method java/lang/StringBuilder.append:(Z)Ljava/lang/StringBuilder;
        55: ldc           #149                // String ,
        57: invokevirtual #112                // Method java/lang/StringBuilder.append:(Ljava/lang/String;)Ljava/lang/StringBuilder;
        60: aload_0
        61: invokevirtual #156                // Method realmOpt:()Lscala/Option;
        64: invokevirtual #147                // Method java/lang/StringBuilder.append:(Ljava/lang/Object;)Ljava/lang/StringBuilder;
        67: ldc           #149                // String ,
        69: invokevirtual #112                // Method java/lang/StringBuilder.append:(Ljava/lang/String;)Ljava/lang/StringBuilder;
        72: aload_0
        73: invokevirtual #158                // Method httpsOnly:()Z
        76: invokevirtual #154                // Method java/lang/StringBuilder.append:(Z)Ljava/lang/StringBuilder;
        79: ldc           #149                // String ,
        81: invokevirtual #112                // Method java/lang/StringBuilder.append:(Ljava/lang/String;)Ljava/lang/StringBuilder;
        84: aload_0
        85: invokevirtual #160                // Method passOnRedirect:()Z
        88: invokevirtual #154                // Method java/lang/StringBuilder.append:(Z)Ljava/lang/StringBuilder;
        91: ldc           #162                // String )
        93: invokevirtual #112                // Method java/lang/StringBuilder.append:(Ljava/lang/String;)Ljava/lang/StringBuilder;
        96: invokevirtual #164                // Method java/lang/StringBuilder.toString:()Ljava/lang/String;
        99: areturn
      LineNumberTable:
        line 19: 0
      LocalVariableTable:
        Start  Length  Slot  Name   Signature
            0     100     0  this   Lcoursier/core/Authentication;

  public coursier.core.Authentication withPassword(java.lang.String);
    descriptor: (Ljava/lang/String;)Lcoursier/core/Authentication;
    flags: (0x0001) ACC_PUBLIC
    Code:
      stack=4, locals=2, args_size=2
         0: aload_0
         1: new           #167                // class scala/Some
         4: dup
         5: aload_1
         6: invokespecial #170                // Method scala/Some."<init>":(Ljava/lang/Object;)V
         9: invokevirtual #174                // Method withPasswordOpt:(Lscala/Option;)Lcoursier/core/Authentication;
        12: areturn
      LineNumberTable:
        line 23: 0
      LocalVariableTable:
        Start  Length  Slot  Name   Signature
            0      13     0  this   Lcoursier/core/Authentication;
            0      13     1 password   Ljava/lang/String;
    MethodParameters:
      Name                           Flags
      password                       final

  public coursier.core.Authentication withRealm(java.lang.String);
    descriptor: (Ljava/lang/String;)Lcoursier/core/Authentication;
    flags: (0x0001) ACC_PUBLIC
    Code:
      stack=4, locals=2, args_size=2
         0: aload_0
         1: new           #167                // class scala/Some
         4: dup
         5: aload_1
         6: invokespecial #170                // Method scala/Some."<init>":(Ljava/lang/Object;)V
         9: invokevirtual #179                // Method withRealmOpt:(Lscala/Option;)Lcoursier/core/Authentication;
        12: areturn
      LineNumberTable:
        line 25: 0
      LocalVariableTable:
        Start  Length  Slot  Name   Signature
            0      13     0  this   Lcoursier/core/Authentication;
            0      13     1 realm   Ljava/lang/String;
    MethodParameters:
      Name                           Flags
      realm                          final

  public boolean userOnly();
    descriptor: ()Z
    flags: (0x0001) ACC_PUBLIC
    Code:
      stack=3, locals=2, args_size=1
         0: aload_0
         1: getstatic     #39                 // Field coursier/core/Authentication$.MODULE$:Lcoursier/core/Authentication$;
         4: aload_0
         5: invokevirtual #114                // Method user:()Ljava/lang/String;
         8: invokevirtual #64                 // Method coursier/core/Authentication$.apply:(Ljava/lang/String;)Lcoursier/core/Authentication;
        11: astore_1
        12: dup
        13: ifnonnull     24
        16: pop
        17: aload_1
        18: ifnull        31
        21: goto          35
        24: aload_1
        25: invokevirtual #184                // Method java/lang/Object.equals:(Ljava/lang/Object;)Z
        28: ifeq          35
        31: iconst_1
        32: goto          36
        35: iconst_0
        36: ireturn
      StackMapTable: number_of_entries = 4
        frame_type = 255 /* full_frame */
          offset_delta = 24
          locals = [ class coursier/core/Authentication, class coursier/core/Authentication ]
          stack = [ class coursier/core/Authentication ]
        frame_type = 6 /* same */
        frame_type = 3 /* same */
        frame_type = 64 /* same_locals_1_stack_item */
          stack = [ int ]
      LineNumberTable:
        line 28: 0
      LocalVariableTable:
        Start  Length  Slot  Name   Signature
            0      37     0  this   Lcoursier/core/Authentication;

  public scala.collection.immutable.Seq<scala.Tuple2<java.lang.String, java.lang.String>> allHttpHeaders();
    descriptor: ()Lscala/collection/immutable/Seq;
    flags: (0x0001) ACC_PUBLIC
    Code:
      stack=2, locals=2, args_size=1
         0: getstatic     #190                // Field scala/Option$.MODULE$:Lscala/Option$;
         3: aload_0
         4: invokevirtual #192                // Method passwordOpt:()Lscala/Option;
         7: invokevirtual #196                // Method scala/Option$.option2Iterable:(Lscala/Option;)Lscala/collection/Iterable;
        10: invokeinterface #201,  1          // InterfaceMethod scala/collection/Iterable.toSeq:()Lscala/collection/immutable/Seq;
        15: aload_0
        16: invokedynamic #211,  0            // InvokeDynamic #1:apply:(Lcoursier/core/Authentication;)Lscala/Function1;
        21: invokeinterface #144,  2          // InterfaceMethod scala/collection/immutable/Seq.map:(Lscala/Function1;)Ljava/lang/Object;
        26: checkcast     #140                // class scala/collection/immutable/Seq
        29: astore_1
        30: aload_1
        31: aload_0
        32: invokevirtual #118                // Method httpHeaders:()Lscala/collection/immutable/Seq;
        35: invokeinterface #215,  2          // InterfaceMethod scala/collection/immutable/Seq.$plus$plus:(Lscala/collection/IterableOnce;)Ljava/lang/Object;
        40: checkcast     #140                // class scala/collection/immutable/Seq
        43: areturn
      LineNumberTable:
        line 31: 0
        line 34: 30
      LocalVariableTable:
        Start  Length  Slot  Name   Signature
           30      13     1 basicAuthHeader   Lscala/collection/immutable/Seq;
            0      44     0  this   Lcoursier/core/Authentication;
    Signature: #87                          // ()Lscala/collection/immutable/Seq<Lscala/Tuple2<Ljava/lang/String;Ljava/lang/String;>;>;

  public coursier.core.Authentication withUser(java.lang.String);
    descriptor: (Ljava/lang/String;)Lcoursier/core/Authentication;
    flags: (0x0001) ACC_PUBLIC
    Code:
      stack=9, locals=2, args_size=2
         0: new           #2                  // class coursier/core/Authentication
         3: dup
         4: aload_1
         5: aload_0
         6: invokevirtual #192                // Method passwordOpt:()Lscala/Option;
         9: aload_0
        10: invokevirtual #118                // Method httpHeaders:()Lscala/collection/immutable/Seq;
        13: aload_0
        14: invokevirtual #151                // Method optional:()Z
        17: aload_0
        18: invokevirtual #156                // Method realmOpt:()Lscala/Option;
        21: aload_0
        22: invokevirtual #158                // Method httpsOnly:()Z
        25: aload_0
        26: invokevirtual #160                // Method passOnRedirect:()Z
        29: invokespecial #220                // Method "<init>":(Ljava/lang/String;Lscala/Option;Lscala/collection/immutable/Seq;ZLscala/Option;ZZ)V
        32: areturn
      LineNumberTable:
        line 8: 0
      LocalVariableTable:
        Start  Length  Slot  Name   Signature
            0      33     0  this   Lcoursier/core/Authentication;
            0      33     1  user   Ljava/lang/String;
    MethodParameters:
      Name                           Flags
      user                           final

  public coursier.core.Authentication withPasswordOpt(scala.Option<java.lang.String>);
    descriptor: (Lscala/Option;)Lcoursier/core/Authentication;
    flags: (0x0001) ACC_PUBLIC
    Code:
      stack=9, locals=2, args_size=2
         0: new           #2                  // class coursier/core/Authentication
         3: dup
         4: aload_0
         5: invokevirtual #114                // Method user:()Ljava/lang/String;
         8: aload_1
         9: aload_0
        10: invokevirtual #118                // Method httpHeaders:()Lscala/collection/immutable/Seq;
        13: aload_0
        14: invokevirtual #151                // Method optional:()Z
        17: aload_0
        18: invokevirtual #156                // Method realmOpt:()Lscala/Option;
        21: aload_0
        22: invokevirtual #158                // Method httpsOnly:()Z
        25: aload_0
        26: invokevirtual #160                // Method passOnRedirect:()Z
        29: invokespecial #220                // Method "<init>":(Ljava/lang/String;Lscala/Option;Lscala/collection/immutable/Seq;ZLscala/Option;ZZ)V
        32: areturn
      LineNumberTable:
        line 8: 0
      LocalVariableTable:
        Start  Length  Slot  Name   Signature
            0      33     0  this   Lcoursier/core/Authentication;
            0      33     1 passwordOpt   Lscala/Option;
    Signature: #221                         // (Lscala/Option<Ljava/lang/String;>;)Lcoursier/core/Authentication;
    MethodParameters:
      Name                           Flags
      passwordOpt                    final

  public coursier.core.Authentication withHttpHeaders(scala.collection.immutable.Seq<scala.Tuple2<java.lang.String, java.lang.String>>);
    descriptor: (Lscala/collection/immutable/Seq;)Lcoursier/core/Authentication;
    flags: (0x0001) ACC_PUBLIC
    Code:
      stack=9, locals=2, args_size=2
         0: new           #2                  // class coursier/core/Authentication
         3: dup
         4: aload_0
         5: invokevirtual #114                // Method user:()Ljava/lang/String;
         8: aload_0
         9: invokevirtual #192                // Method passwordOpt:()Lscala/Option;
        12: aload_1
        13: aload_0
        14: invokevirtual #151                // Method optional:()Z
        17: aload_0
        18: invokevirtual #156                // Method realmOpt:()Lscala/Option;
        21: aload_0
        22: invokevirtual #158                // Method httpsOnly:()Z
        25: aload_0
        26: invokevirtual #160                // Method passOnRedirect:()Z
        29: invokespecial #220                // Method "<init>":(Ljava/lang/String;Lscala/Option;Lscala/collection/immutable/Seq;ZLscala/Option;ZZ)V
        32: areturn
      LineNumberTable:
        line 8: 0
      LocalVariableTable:
        Start  Length  Slot  Name   Signature
            0      33     0  this   Lcoursier/core/Authentication;
            0      33     1 httpHeaders   Lscala/collection/immutable/Seq;
    Signature: #47                          // (Lscala/collection/immutable/Seq<Lscala/Tuple2<Ljava/lang/String;Ljava/lang/String;>;>;)Lcoursier/core/Authentication;
    MethodParameters:
      Name                           Flags
      httpHeaders                    final

  public coursier.core.Authentication withOptional(boolean);
    descriptor: (Z)Lcoursier/core/Authentication;
    flags: (0x0001) ACC_PUBLIC
    Code:
      stack=9, locals=2, args_size=2
         0: new           #2                  // class coursier/core/Authentication
         3: dup
         4: aload_0
         5: invokevirtual #114                // Method user:()Ljava/lang/String;
         8: aload_0
         9: invokevirtual #192                // Method passwordOpt:()Lscala/Option;
        12: aload_0
        13: invokevirtual #118                // Method httpHeaders:()Lscala/collection/immutable/Seq;
        16: iload_1
        17: aload_0
        18: invokevirtual #156                // Method realmOpt:()Lscala/Option;
        21: aload_0
        22: invokevirtual #158                // Method httpsOnly:()Z
        25: aload_0
        26: invokevirtual #160                // Method passOnRedirect:()Z
        29: invokespecial #220                // Method "<init>":(Ljava/lang/String;Lscala/Option;Lscala/collection/immutable/Seq;ZLscala/Option;ZZ)V
        32: areturn
      LineNumberTable:
        line 8: 0
      LocalVariableTable:
        Start  Length  Slot  Name   Signature
            0      33     0  this   Lcoursier/core/Authentication;
            0      33     1 optional   Z
    MethodParameters:
      Name                           Flags
      optional                       final

  public coursier.core.Authentication withRealmOpt(scala.Option<java.lang.String>);
    descriptor: (Lscala/Option;)Lcoursier/core/Authentication;
    flags: (0x0001) ACC_PUBLIC
    Code:
      stack=9, locals=2, args_size=2
         0: new           #2                  // class coursier/core/Authentication
         3: dup
         4: aload_0
         5: invokevirtual #114                // Method user:()Ljava/lang/String;
         8: aload_0
         9: invokevirtual #192                // Method passwordOpt:()Lscala/Option;
        12: aload_0
        13: invokevirtual #118                // Method httpHeaders:()Lscala/collection/immutable/Seq;
        16: aload_0
        17: invokevirtual #151                // Method optional:()Z
        20: aload_1
        21: aload_0
        22: invokevirtual #158                // Method httpsOnly:()Z
        25: aload_0
        26: invokevirtual #160                // Method passOnRedirect:()Z
        29: invokespecial #220                // Method "<init>":(Ljava/lang/String;Lscala/Option;Lscala/collection/immutable/Seq;ZLscala/Option;ZZ)V
        32: areturn
      LineNumberTable:
        line 8: 0
      LocalVariableTable:
        Start  Length  Slot  Name   Signature
            0      33     0  this   Lcoursier/core/Authentication;
            0      33     1 realmOpt   Lscala/Option;
    Signature: #221                         // (Lscala/Option<Ljava/lang/String;>;)Lcoursier/core/Authentication;
    MethodParameters:
      Name                           Flags
      realmOpt                       final

  public coursier.core.Authentication withHttpsOnly(boolean);
    descriptor: (Z)Lcoursier/core/Authentication;
    flags: (0x0001) ACC_PUBLIC
    Code:
      stack=9, locals=2, args_size=2
         0: new           #2                  // class coursier/core/Authentication
         3: dup
         4: aload_0
         5: invokevirtual #114                // Method user:()Ljava/lang/String;
         8: aload_0
         9: invokevirtual #192                // Method passwordOpt:()Lscala/Option;
        12: aload_0
        13: invokevirtual #118                // Method httpHeaders:()Lscala/collection/immutable/Seq;
        16: aload_0
        17: invokevirtual #151                // Method optional:()Z
        20: aload_0
        21: invokevirtual #156                // Method realmOpt:()Lscala/Option;
        24: iload_1
        25: aload_0
        26: invokevirtual #160                // Method passOnRedirect:()Z
        29: invokespecial #220                // Method "<init>":(Ljava/lang/String;Lscala/Option;Lscala/collection/immutable/Seq;ZLscala/Option;ZZ)V
        32: areturn
      LineNumberTable:
        line 8: 0
      LocalVariableTable:
        Start  Length  Slot  Name   Signature
            0      33     0  this   Lcoursier/core/Authentication;
            0      33     1 httpsOnly   Z
    MethodParameters:
      Name                           Flags
      httpsOnly                      final

  public coursier.core.Authentication withPassOnRedirect(boolean);
    descriptor: (Z)Lcoursier/core/Authentication;
    flags: (0x0001) ACC_PUBLIC
    Code:
      stack=9, locals=2, args_size=2
         0: new           #2                  // class coursier/core/Authentication
         3: dup
         4: aload_0
         5: invokevirtual #114                // Method user:()Ljava/lang/String;
         8: aload_0
         9: invokevirtual #192                // Method passwordOpt:()Lscala/Option;
        12: aload_0
        13: invokevirtual #118                // Method httpHeaders:()Lscala/collection/immutable/Seq;
        16: aload_0
        17: invokevirtual #151                // Method optional:()Z
        20: aload_0
        21: invokevirtual #156                // Method realmOpt:()Lscala/Option;
        24: aload_0
        25: invokevirtual #158                // Method httpsOnly:()Z
        28: iload_1
        29: invokespecial #220                // Method "<init>":(Ljava/lang/String;Lscala/Option;Lscala/collection/immutable/Seq;ZLscala/Option;ZZ)V
        32: areturn
      LineNumberTable:
        line 8: 0
      LocalVariableTable:
        Start  Length  Slot  Name   Signature
            0      33     0  this   Lcoursier/core/Authentication;
            0      33     1 passOnRedirect   Z
    MethodParameters:
      Name                           Flags
      passOnRedirect                 final

  public boolean canEqual(java.lang.Object);
    descriptor: (Ljava/lang/Object;)Z
    flags: (0x0001) ACC_PUBLIC
    Code:
      stack=1, locals=2, args_size=2
         0: aload_1
         1: ifnull        15
         4: aload_1
         5: instanceof    #2                  // class coursier/core/Authentication
         8: ifeq          15
        11: iconst_1
        12: goto          16
        15: iconst_0
        16: ireturn
      StackMapTable: number_of_entries = 2
        frame_type = 15 /* same */
        frame_type = 64 /* same_locals_1_stack_item */
          stack = [ int ]
      LineNumberTable:
        line 8: 0
      LocalVariableTable:
        Start  Length  Slot  Name   Signature
            0      17     0  this   Lcoursier/core/Authentication;
            0      17     1   obj   Ljava/lang/Object;
    MethodParameters:
      Name                           Flags
      obj                            final

  public boolean equals(java.lang.Object);
    descriptor: (Ljava/lang/Object;)Z
    flags: (0x0001) ACC_PUBLIC
    Code:
      stack=2, locals=7, args_size=2
         0: aload_0
         1: aload_1
         2: if_acmpeq     184
         5: aload_0
         6: aload_1
         7: invokevirtual #231                // Method canEqual:(Ljava/lang/Object;)Z
        10: ifeq          188
        13: aload_1
        14: checkcast     #2                  // class coursier/core/Authentication
        17: astore_2
        18: iconst_1
        19: ifeq          180
        22: aload_0
        23: invokevirtual #114                // Method user:()Ljava/lang/String;
        26: aload_2
        27: invokevirtual #114                // Method user:()Ljava/lang/String;
        30: astore_3
        31: dup
        32: ifnonnull     43
        35: pop
        36: aload_3
        37: ifnull        50
        40: goto          180
        43: aload_3
        44: invokevirtual #184                // Method java/lang/Object.equals:(Ljava/lang/Object;)Z
        47: ifeq          180
        50: aload_0
        51: invokevirtual #192                // Method passwordOpt:()Lscala/Option;
        54: aload_2
        55: invokevirtual #192                // Method passwordOpt:()Lscala/Option;
        58: astore        4
        60: dup
        61: ifnonnull     73
        64: pop
        65: aload         4
        67: ifnull        81
        70: goto          180
        73: aload         4
        75: invokevirtual #184                // Method java/lang/Object.equals:(Ljava/lang/Object;)Z
        78: ifeq          180
        81: aload_0
        82: invokevirtual #118                // Method httpHeaders:()Lscala/collection/immutable/Seq;
        85: aload_2
        86: invokevirtual #118                // Method httpHeaders:()Lscala/collection/immutable/Seq;
        89: astore        5
        91: dup
        92: ifnonnull     104
        95: pop
        96: aload         5
        98: ifnull        112
       101: goto          180
       104: aload         5
       106: invokevirtual #184                // Method java/lang/Object.equals:(Ljava/lang/Object;)Z
       109: ifeq          180
       112: aload_0
       113: invokevirtual #151                // Method optional:()Z
       116: aload_2
       117: invokevirtual #151                // Method optional:()Z
       120: if_icmpne     180
       123: aload_0
       124: invokevirtual #156                // Method realmOpt:()Lscala/Option;
       127: aload_2
       128: invokevirtual #156                // Method realmOpt:()Lscala/Option;
       131: astore        6
       133: dup
       134: ifnonnull     146
       137: pop
       138: aload         6
       140: ifnull        154
       143: goto          180
       146: aload         6
       148: invokevirtual #184                // Method java/lang/Object.equals:(Ljava/lang/Object;)Z
       151: ifeq          180
       154: aload_0
       155: invokevirtual #158                // Method httpsOnly:()Z
       158: aload_2
       159: invokevirtual #158                // Method httpsOnly:()Z
       162: if_icmpne     180
       165: aload_0
       166: invokevirtual #160                // Method passOnRedirect:()Z
       169: aload_2
       170: invokevirtual #160                // Method passOnRedirect:()Z
       173: if_icmpne     180
       176: iconst_1
       177: goto          181
       180: iconst_0
       181: ifeq          188
       184: iconst_1
       185: goto          189
       188: iconst_0
       189: ireturn
      StackMapTable: number_of_entries = 13
        frame_type = 255 /* full_frame */
          offset_delta = 43
          locals = [ class coursier/core/Authentication, class java/lang/Object, class coursier/core/Authentication, class java/lang/String ]
          stack = [ class java/lang/String ]
        frame_type = 6 /* same */
        frame_type = 255 /* full_frame */
          offset_delta = 22
          locals = [ class coursier/core/Authentication, class java/lang/Object, class coursier/core/Authentication, class java/lang/String, class scala/Option ]
          stack = [ class scala/Option ]
        frame_type = 7 /* same */
        frame_type = 255 /* full_frame */
          offset_delta = 22
          locals = [ class coursier/core/Authentication, class java/lang/Object, class coursier/core/Authentication, class java/lang/String, class scala/Option, class scala/collection/immutable/Seq ]
          stack = [ class scala/collection/immutable/Seq ]
        frame_type = 7 /* same */
        frame_type = 255 /* full_frame */
          offset_delta = 33
          locals = [ class coursier/core/Authentication, class java/lang/Object, class coursier/core/Authentication, class java/lang/String, class scala/Option, class scala/collection/immutable/Seq, class scala/Option ]
          stack = [ class scala/Option ]
        frame_type = 7 /* same */
        frame_type = 255 /* full_frame */
          offset_delta = 25
          locals = [ class coursier/core/Authentication, class java/lang/Object, class coursier/core/Authentication ]
          stack = []
        frame_type = 64 /* same_locals_1_stack_item */
          stack = [ int ]
        frame_type = 250 /* chop */
          offset_delta = 2
        frame_type = 3 /* same */
        frame_type = 64 /* same_locals_1_stack_item */
          stack = [ int ]
      LineNumberTable:
        line 8: 0
      LocalVariableTable:
        Start  Length  Slot  Name   Signature
           18     163     2 other   Lcoursier/core/Authentication;
            0     190     0  this   Lcoursier/core/Authentication;
            0     190     1   obj   Ljava/lang/Object;
    MethodParameters:
      Name                           Flags
      obj                            final

  public int hashCode();
    descriptor: ()I
    flags: (0x0001) ACC_PUBLIC
    Code:
      stack=2, locals=2, args_size=1
         0: bipush        17
         2: ldc           #240                // String Authentication
         4: invokestatic  #246                // Method scala/runtime/Statics.anyHash:(Ljava/lang/Object;)I
         7: iadd
         8: istore_1
         9: bipush        37
        11: iload_1
        12: imul
        13: aload_0
        14: invokevirtual #114                // Method user:()Ljava/lang/String;
        17: invokestatic  #246                // Method scala/runtime/Statics.anyHash:(Ljava/lang/Object;)I
        20: iadd
        21: istore_1
        22: bipush        37
        24: iload_1
        25: imul
        26: aload_0
        27: invokevirtual #192                // Method passwordOpt:()Lscala/Option;
        30: invokestatic  #246                // Method scala/runtime/Statics.anyHash:(Ljava/lang/Object;)I
        33: iadd
        34: istore_1
        35: bipush        37
        37: iload_1
        38: imul
        39: aload_0
        40: invokevirtual #118                // Method httpHeaders:()Lscala/collection/immutable/Seq;
        43: invokestatic  #246                // Method scala/runtime/Statics.anyHash:(Ljava/lang/Object;)I
        46: iadd
        47: istore_1
        48: bipush        37
        50: iload_1
        51: imul
        52: aload_0
        53: invokevirtual #151                // Method optional:()Z
        56: ifeq          65
        59: sipush        1231
        62: goto          68
        65: sipush        1237
        68: iadd
        69: istore_1
        70: bipush        37
        72: iload_1
        73: imul
        74: aload_0
        75: invokevirtual #156                // Method realmOpt:()Lscala/Option;
        78: invokestatic  #246                // Method scala/runtime/Statics.anyHash:(Ljava/lang/Object;)I
        81: iadd
        82: istore_1
        83: bipush        37
        85: iload_1
        86: imul
        87: aload_0
        88: invokevirtual #158                // Method httpsOnly:()Z
        91: ifeq          100
        94: sipush        1231
        97: goto          103
       100: sipush        1237
       103: iadd
       104: istore_1
       105: bipush        37
       107: iload_1
       108: imul
       109: aload_0
       110: invokevirtual #160                // Method passOnRedirect:()Z
       113: ifeq          122
       116: sipush        1231
       119: goto          125
       122: sipush        1237
       125: iadd
       126: istore_1
       127: bipush        37
       129: iload_1
       130: imul
       131: ireturn
      StackMapTable: number_of_entries = 6
        frame_type = 255 /* full_frame */
          offset_delta = 65
          locals = [ class coursier/core/Authentication, int ]
          stack = [ int ]
        frame_type = 255 /* full_frame */
          offset_delta = 2
          locals = [ class coursier/core/Authentication, int ]
          stack = [ int, int ]
        frame_type = 95 /* same_locals_1_stack_item */
          stack = [ int ]
        frame_type = 255 /* full_frame */
          offset_delta = 2
          locals = [ class coursier/core/Authentication, int ]
          stack = [ int, int ]
        frame_type = 82 /* same_locals_1_stack_item */
          stack = [ int ]
        frame_type = 255 /* full_frame */
          offset_delta = 2
          locals = [ class coursier/core/Authentication, int ]
          stack = [ int, int ]
      LineNumberTable:
        line 8: 0
      LocalVariableTable:
        Start  Length  Slot  Name   Signature
            9     122     1  code   I
            0     132     0  this   Lcoursier/core/Authentication;

  private scala.Tuple7<java.lang.String, scala.Option<java.lang.String>, scala.collection.immutable.Seq<scala.Tuple2<java.lang.String, java.lang.String>>, java.lang.Object, scala.Option<java.lang.String>, java.lang.Object, java.lang.Object> tuple();
    descriptor: ()Lscala/Tuple7;
    flags: (0x0002) ACC_PRIVATE
    Code:
      stack=9, locals=1, args_size=1
         0: new           #253                // class scala/Tuple7
         3: dup
         4: aload_0
         5: invokevirtual #114                // Method user:()Ljava/lang/String;
         8: aload_0
         9: invokevirtual #192                // Method passwordOpt:()Lscala/Option;
        12: aload_0
        13: invokevirtual #118                // Method httpHeaders:()Lscala/collection/immutable/Seq;
        16: aload_0
        17: invokevirtual #151                // Method optional:()Z
        20: invokestatic  #259                // Method scala/runtime/BoxesRunTime.boxToBoolean:(Z)Ljava/lang/Boolean;
        23: aload_0
        24: invokevirtual #156                // Method realmOpt:()Lscala/Option;
        27: aload_0
        28: invokevirtual #158                // Method httpsOnly:()Z
        31: invokestatic  #259                // Method scala/runtime/BoxesRunTime.boxToBoolean:(Z)Ljava/lang/Boolean;
        34: aload_0
        35: invokevirtual #160                // Method passOnRedirect:()Z
        38: invokestatic  #259                // Method scala/runtime/BoxesRunTime.boxToBoolean:(Z)Ljava/lang/Boolean;
        41: invokespecial #262                // Method scala/Tuple7."<init>":(Ljava/lang/Object;Ljava/lang/Object;Ljava/lang/Object;Ljava/lang/Object;Ljava/lang/Object;Ljava/lang/Object;Ljava/lang/Object;)V
        44: areturn
      LineNumberTable:
        line 8: 0
      LocalVariableTable:
        Start  Length  Slot  Name   Signature
            0      45     0  this   Lcoursier/core/Authentication;
    Signature: #251                         // ()Lscala/Tuple7<Ljava/lang/String;Lscala/Option<Ljava/lang/String;>;Lscala/collection/immutable/Seq<Lscala/Tuple2<Ljava/lang/String;Ljava/lang/String;>;>;Ljava/lang/Object;Lscala/Option<Ljava/lang/String;>;Ljava/lang/Object;Ljava/lang/Object;>;

  public java.lang.String productPrefix();
    descriptor: ()Ljava/lang/String;
    flags: (0x0001) ACC_PUBLIC
    Code:
      stack=1, locals=1, args_size=1
         0: ldc           #240                // String Authentication
         2: areturn
      LineNumberTable:
        line 8: 0
      LocalVariableTable:
        Start  Length  Slot  Name   Signature
            0       3     0  this   Lcoursier/core/Authentication;

  public int productArity();
    descriptor: ()I
    flags: (0x0001) ACC_PUBLIC
    Code:
      stack=1, locals=1, args_size=1
         0: bipush        7
         2: ireturn
      LineNumberTable:
        line 8: 0
      LocalVariableTable:
        Start  Length  Slot  Name   Signature
            0       3     0  this   Lcoursier/core/Authentication;

  public java.lang.Object productElement(int);
    descriptor: (I)Ljava/lang/Object;
    flags: (0x0001) ACC_PUBLIC
    Code:
      stack=3, locals=3, args_size=2
         0: iload_1
         1: istore_2
         2: iload_2
         3: tableswitch   { // 0 to 6
                       0: 44
                       1: 51
                       2: 58
                       3: 65
                       4: 75
                       5: 82
                       6: 92
                 default: 102
            }
        44: aload_0
        45: invokevirtual #114                // Method user:()Ljava/lang/String;
        48: goto          117
        51: aload_0
        52: invokevirtual #192                // Method passwordOpt:()Lscala/Option;
        55: goto          117
        58: aload_0
        59: invokevirtual #118                // Method httpHeaders:()Lscala/collection/immutable/Seq;
        62: goto          117
        65: aload_0
        66: invokevirtual #151                // Method optional:()Z
        69: invokestatic  #259                // Method scala/runtime/BoxesRunTime.boxToBoolean:(Z)Ljava/lang/Boolean;
        72: goto          117
        75: aload_0
        76: invokevirtual #156                // Method realmOpt:()Lscala/Option;
        79: goto          117
        82: aload_0
        83: invokevirtual #158                // Method httpsOnly:()Z
        86: invokestatic  #259                // Method scala/runtime/BoxesRunTime.boxToBoolean:(Z)Ljava/lang/Boolean;
        89: goto          117
        92: aload_0
        93: invokevirtual #160                // Method passOnRedirect:()Z
        96: invokestatic  #259                // Method scala/runtime/BoxesRunTime.boxToBoolean:(Z)Ljava/lang/Boolean;
        99: goto          117
       102: new           #269                // class java/lang/IndexOutOfBoundsException
       105: dup
       106: iload_2
       107: invokestatic  #273                // Method scala/runtime/BoxesRunTime.boxToInteger:(I)Ljava/lang/Integer;
       110: invokevirtual #274                // Method java/lang/Object.toString:()Ljava/lang/String;
       113: invokespecial #277                // Method java/lang/IndexOutOfBoundsException."<init>":(Ljava/lang/String;)V
       116: athrow
       117: areturn
      StackMapTable: number_of_entries = 9
        frame_type = 252 /* append */
          offset_delta = 44
          locals = [ int ]
        frame_type = 6 /* same */
        frame_type = 6 /* same */
        frame_type = 6 /* same */
        frame_type = 9 /* same */
        frame_type = 6 /* same */
        frame_type = 9 /* same */
        frame_type = 9 /* same */
        frame_type = 78 /* same_locals_1_stack_item */
          stack = [ class java/lang/Object ]
      LineNumberTable:
        line 8: 0
      LocalVariableTable:
        Start  Length  Slot  Name   Signature
            0     118     0  this   Lcoursier/core/Authentication;
            0     118     1     n   I
    MethodParameters:
      Name                           Flags
      n                              final

  public java.lang.String productElementName(int);
    descriptor: (I)Ljava/lang/String;
    flags: (0x0001) ACC_PUBLIC
    Code:
      stack=3, locals=3, args_size=2
         0: iload_1
         1: istore_2
         2: iload_2
         3: tableswitch   { // 0 to 6
                       0: 44
                       1: 50
                       2: 56
                       3: 62
                       4: 68
                       5: 74
                       6: 80
                 default: 86
            }
        44: ldc_w         #280                // String user
        47: goto          101
        50: ldc_w         #281                // String passwordOpt
        53: goto          101
        56: ldc_w         #282                // String httpHeaders
        59: goto          101
        62: ldc_w         #283                // String optional
        65: goto          101
        68: ldc_w         #284                // String realmOpt
        71: goto          101
        74: ldc_w         #285                // String httpsOnly
        77: goto          101
        80: ldc_w         #286                // String passOnRedirect
        83: goto          101
        86: new           #269                // class java/lang/IndexOutOfBoundsException
        89: dup
        90: iload_2
        91: invokestatic  #273                // Method scala/runtime/BoxesRunTime.boxToInteger:(I)Ljava/lang/Integer;
        94: invokevirtual #274                // Method java/lang/Object.toString:()Ljava/lang/String;
        97: invokespecial #277                // Method java/lang/IndexOutOfBoundsException."<init>":(Ljava/lang/String;)V
       100: athrow
       101: areturn
      StackMapTable: number_of_entries = 9
        frame_type = 252 /* append */
          offset_delta = 44
          locals = [ int ]
        frame_type = 5 /* same */
        frame_type = 5 /* same */
        frame_type = 5 /* same */
        frame_type = 5 /* same */
        frame_type = 5 /* same */
        frame_type = 5 /* same */
        frame_type = 5 /* same */
        frame_type = 78 /* same_locals_1_stack_item */
          stack = [ class java/lang/String ]
      LineNumberTable:
        line 8: 0
      LocalVariableTable:
        Start  Length  Slot  Name   Signature
            0     102     0  this   Lcoursier/core/Authentication;
            0     102     1     n   I
    MethodParameters:
      Name                           Flags
      n                              final

  public static final scala.Tuple2 $anonfun$toString$1(scala.Tuple2);
    descriptor: (Lscala/Tuple2;)Lscala/Tuple2;
    flags: (0x1019) ACC_PUBLIC, ACC_STATIC, ACC_FINAL, ACC_SYNTHETIC
    Code:
      stack=4, locals=4, args_size=1
         0: aload_0
         1: astore_2
         2: aload_2
         3: ifnull        29
         6: aload_2
         7: invokevirtual #293                // Method scala/Tuple2._1:()Ljava/lang/Object;
        10: checkcast     #233                // class java/lang/String
        13: astore_3
        14: new           #289                // class scala/Tuple2
        17: dup
        18: aload_3
        19: ldc_w         #295                // String ****
        22: invokespecial #298                // Method scala/Tuple2."<init>":(Ljava/lang/Object;Ljava/lang/Object;)V
        25: astore_1
        26: goto          41
        29: goto          32
        32: new           #300                // class scala/MatchError
        35: dup
        36: aload_2
        37: invokespecial #301                // Method scala/MatchError."<init>":(Ljava/lang/Object;)V
        40: athrow
        41: aload_1
        42: areturn
      StackMapTable: number_of_entries = 3
        frame_type = 253 /* append */
          offset_delta = 29
          locals = [ top, class scala/Tuple2 ]
        frame_type = 2 /* same */
        frame_type = 255 /* full_frame */
          offset_delta = 8
          locals = [ class scala/Tuple2, class scala/Tuple2, class scala/Tuple2, class java/lang/String ]
          stack = []
      LineNumberTable:
        line 19: 0
      LocalVariableTable:
        Start  Length  Slot  Name   Signature
           14      15     3     k   Ljava/lang/String;
            0      43     0  x0$1   Lscala/Tuple2;
    MethodParameters:
      Name                           Flags
      x0$1                           final

  public static final scala.Tuple2 $anonfun$allHttpHeaders$1(coursier.core.Authentication, java.lang.String);
    descriptor: (Lcoursier/core/Authentication;Ljava/lang/String;)Lscala/Tuple2;
    flags: (0x1019) ACC_PUBLIC, ACC_STATIC, ACC_FINAL, ACC_SYNTHETIC
    Code:
      stack=7, locals=2, args_size=2
         0: new           #289                // class scala/Tuple2
         3: dup
         4: ldc_w         #307                // String Authorization
         7: new           #101                // class java/lang/StringBuilder
        10: dup
        11: ldc_w         #308                // int 6
        14: invokespecial #106                // Method java/lang/StringBuilder."<init>":(I)V
        17: ldc_w         #310                // String Basic
        20: invokevirtual #112                // Method java/lang/StringBuilder.append:(Ljava/lang/String;)Ljava/lang/StringBuilder;
        23: getstatic     #39                 // Field coursier/core/Authentication$.MODULE$:Lcoursier/core/Authentication$;
        26: aload_0
        27: invokevirtual #114                // Method user:()Ljava/lang/String;
        30: aload_1
        31: invokevirtual #314                // Method coursier/core/Authentication$.basicAuthenticationEncode:(Ljava/lang/String;Ljava/lang/String;)Ljava/lang/String;
        34: invokevirtual #112                // Method java/lang/StringBuilder.append:(Ljava/lang/String;)Ljava/lang/StringBuilder;
        37: invokevirtual #164                // Method java/lang/StringBuilder.toString:()Ljava/lang/String;
        40: invokespecial #298                // Method scala/Tuple2."<init>":(Ljava/lang/Object;Ljava/lang/Object;)V
        43: areturn
      LineNumberTable:
        line 32: 0
      LocalVariableTable:
        Start  Length  Slot  Name   Signature
            0      44     0 $this   Lcoursier/core/Authentication;
            0      44     1     p   Ljava/lang/String;
    MethodParameters:
      Name                           Flags
      $this                          final synthetic
      p                              final

  public coursier.core.Authentication(java.lang.String, scala.Option<java.lang.String>, scala.collection.immutable.Seq<scala.Tuple2<java.lang.String, java.lang.String>>, boolean, scala.Option<java.lang.String>, boolean, boolean);
    descriptor: (Ljava/lang/String;Lscala/Option;Lscala/collection/immutable/Seq;ZLscala/Option;ZZ)V
    flags: (0x0001) ACC_PUBLIC
    Code:
      stack=2, locals=8, args_size=8
         0: aload_0
         1: aload_1
         2: putfield      #81                 // Field user:Ljava/lang/String;
         5: aload_0
         6: aload_2
         7: putfield      #85                 // Field passwordOpt:Lscala/Option;
        10: aload_0
        11: aload_3
        12: putfield      #89                 // Field httpHeaders:Lscala/collection/immutable/Seq;
        15: aload_0
        16: iload         4
        18: putfield      #92                 // Field optional:Z
        21: aload_0
        22: aload         5
        24: putfield      #94                 // Field realmOpt:Lscala/Option;
        27: aload_0
        28: iload         6
        30: putfield      #96                 // Field httpsOnly:Z
        33: aload_0
        34: iload         7
        36: putfield      #98                 // Field passOnRedirect:Z
        39: aload_0
        40: invokespecial #318                // Method java/lang/Object."<init>":()V
        43: aload_0
        44: invokestatic  #322                // InterfaceMethod scala/Product.$init$:(Lscala/Product;)V
        47: return
      LineNumberTable:
        line 8: 0
        line 39: 39
        line 8: 47
      LocalVariableTable:
        Start  Length  Slot  Name   Signature
            0      48     0  this   Lcoursier/core/Authentication;
            0      48     1  user   Ljava/lang/String;
            0      48     2 passwordOpt   Lscala/Option;
            0      48     3 httpHeaders   Lscala/collection/immutable/Seq;
            0      48     4 optional   Z
            0      48     5 realmOpt   Lscala/Option;
            0      48     6 httpsOnly   Z
            0      48     7 passOnRedirect   Z
    Signature: #315                         // (Ljava/lang/String;Lscala/Option<Ljava/lang/String;>;Lscala/collection/immutable/Seq<Lscala/Tuple2<Ljava/lang/String;Ljava/lang/String;>;>;ZLscala/Option<Ljava/lang/String;>;ZZ)V
    MethodParameters:
      Name                           Flags
      user                           final
      passwordOpt                    final
      httpHeaders                    final
      optional                       final
      realmOpt                       final
      httpsOnly                      final
      passOnRedirect                 final

  private static java.lang.Object $deserializeLambda$(java.lang.invoke.SerializedLambda);
    descriptor: (Ljava/lang/invoke/SerializedLambda;)Ljava/lang/Object;
    flags: (0x100a) ACC_PRIVATE, ACC_STATIC, ACC_SYNTHETIC
    Code:
      stack=1, locals=1, args_size=1
         0: aload_0
         1: invokedynamic #334,  0            // InvokeDynamic #2:lambdaDeserialize:(Ljava/lang/invoke/SerializedLambda;)Ljava/lang/Object;
         6: areturn
}
InnerClasses:
  public static final #17= #14 of #16;    // Lookup=class java/lang/invoke/MethodHandles$Lookup of class java/lang/invoke/MethodHandles
SourceFile: "Authentication.scala"
RuntimeVisibleAnnotations:
  0: #10(#11=s#12)
    scala.reflect.ScalaSignature(
      bytes="\u0006\u0005\u0005Uh\u0001\u0002\u00192\u0005YB\u0001\u0002\u0014\u0001\u0003\u0006\u0004%\t!\u0014\u0005\t-\u0002\u0011\t\u0011)A\u0005\u001d\"Aq\u000b\u0001BC\u0002\u0013\u0005\u0001\f\u0003\u0005]\u0001\t\u0005\t\u0015!\u0003Z\u0011!i\u0006A!b\u0001\n\u0003q\u0006\u0002C3\u0001\u0005\u0003\u0005\u000b\u0011B0\t\u0011\u0019\u0004!Q1A\u0005\u0002\u001dD\u0001b\u001b\u0001\u0003\u0002\u0003\u0006I\u0001\u001b\u0005\tY\u0002\u0011)\u0019!C\u00011\"AQ\u000e\u0001B\u0001B\u0003%\u0011\f\u0003\u0005o\u0001\t\u0015\r\u0011\"\u0001h\u0011!y\u0007A!A!\u0002\u0013A\u0007\u0002\u00039\u0001\u0005\u000b\u0007I\u0011A4\t\u0011E\u0004!\u0011!Q\u0001\n!DQA\u001d\u0001\u0005\u0002MDQ! \u0001\u0005ByDaa \u0001\u0005\u0002\u0005\u0005\u0001bBA\u0004\u0001\u0011\u0005\u0011\u0011\u0002\u0005\u0007\u0003\u001f\u0001A\u0011A4\t\r\u0005E\u0001\u0001\"\u0001_\u0011\u001d\t\u0019\u0002\u0001C\u0001\u0003+Aq!!\u0007\u0001\t\u0003\tY\u0002C\u0004\u0002 \u0001!\t!!\t\t\u000f\u0005\u0015\u0002\u0001\"\u0001\u0002(!9\u00111\u0006\u0001\u0005\u0002\u00055\u0002bBA\u0019\u0001\u0011\u0005\u00111\u0007\u0005\b\u0003o\u0001A\u0011AA\u001d\u0011\u001d\ti\u0004\u0001C!\u0003\u007fAq!a\u0013\u0001\t\u0003\ni\u0005C\u0004\u0002R\u0001!\t%a\u0015\t\u000f\u0005m\u0003\u0001\"\u0003\u0002^!9\u0011Q\r\u0001\u0005B\u0005\u001d\u0004bBA<\u0001\u0011\u0005\u0013\u0011\u0010\u0005\b\u0003w\u0002A\u0011IA?\u0011\u001d\t\u0019\t\u0001C!\u0003\u000b;q!!#2\u0011\u0003\tYI\u0002\u00041c!\u0005\u0011Q\u0012\u0005\u0007e\u0016\"\t!!\'\t\u000f\u0005mU\u0005\"\u0001\u0002\u001e\"9\u00111T\u0013\u0005\u0002\u0005\u0005\u0006bBANK\u0011\u0005\u0011q\u0015\u0005\b\u00037+C\u0011AA[\u0011\u001d\tY*\nC\u0001\u0003\u0007Dq!a\'&\t\u0003\t9\r\u0003\u0005\u0002T\u0016\"\taMAk\u0011\u001d\tY*\nC\u0001\u00037D\u0011\"a;&\u0003\u0003%I!!<\u0003\u001d\u0005+H\u000f[3oi&\u001c\u0017\r^5p]*\u0011!gM\u0001\u0005G>\u0014XMC\u00015\u0003!\u0019w.\u001e:tS\u0016\u00148\u0001A\n\u0005\u0001]j\u0004\t\u0005\u00029w5\t\u0011HC\u0001;\u0003\u0015\u00198-\u00197b\u0013\ta\u0014H\u0001\u0004B]f\u0014VM\u001a\t\u0003qyJ!aP\u001d\u0003\u000fA\u0013x\u000eZ;diB\u0011\u0011)\u0013\b\u0003\u0005\u001es!a\u0011$\u000e\u0003\u0011S!!R\u001b\u0002\rq\u0012xn\u001c;?\u0013\u0005Q\u0014B\u0001%:\u0003\u001d\u0001\u0018mY6bO\u0016L!AS&\u0003\u0019M+\'/[1mSj\f\'\r\\3\u000b\u0005!K\u0014\u0001B;tKJ,\u0012A\u0014\t\u0003\u001fNs!\u0001U)\u0011\u0005\rK\u0014B\u0001*:\u0003\u0019\u0001&/\u001a3fM&\u0011A+\u0016\u0002\u0007\'R\u0014\u0018N\\4\u000b\u0005IK\u0014!B;tKJ\u0004\u0013a\u00039bgN<xN\u001d3PaR,\u0012!\u0017\t\u0004qis\u0015BA.:\u0005\u0019y\u0005\u000f^5p]\u0006a\u0001/Y:to>\u0014Hm\u00149uA\u0005Y\u0001\u000e\u001e;q\u0011\u0016\fG-\u001a:t+\u0005y\u0006cA!aE&\u0011\u0011m\u0013\u0002\u0004\'\u0016\f\b\u0003\u0002\u001dd\u001d:K!\u0001Z\u001d\u0003\rQ+\b\u000f\\33\u00031AG\u000f\u001e9IK\u0006$WM]:!\u0003!y\u0007\u000f^5p]\u0006dW#\u00015\u0011\u0005aJ\u0017B\u00016:\u0005\u001d\u0011un\u001c7fC:\f\u0011b\u001c9uS>t\u0017\r\u001c\u0011\u0002\u0011I,\u0017\r\\7PaR\f\u0011B]3bY6|\u0005\u000f\u001e\u0011\u0002\u0013!$H\u000f]:P]2L\u0018A\u00035uiB\u001cxJ\u001c7zA\u0005q\u0001/Y:t\u001f:\u0014V\rZ5sK\u000e$\u0018a\u00049bgN|eNU3eSJ,7\r\u001e\u0011\u0002\rqJg.\u001b;?)!!ho\u001e=zund\bCA;\u0001\u001b\u0005\t\u0004\"\u0002\'\u0010\u0001\u0004q\u0005\"B,\u0010\u0001\u0004I\u0006\"B/\u0010\u0001\u0004y\u0006\"\u00024\u0010\u0001\u0004A\u0007\"\u00027\u0010\u0001\u0004I\u0006\"\u00028\u0010\u0001\u0004A\u0007\"\u00029\u0010\u0001\u0004A\u0017\u0001\u0003;p\'R\u0014\u0018N\\4\u0015\u00039\u000bAb^5uQB\u000b7o]<pe\u0012$2\u0001^A\u0002\u0011\u0019\t)!\u0005a\u0001\u001d\u0006A\u0001/Y:to>\u0014H-A\u0005xSRD\'+Z1m[R\u0019A/a\u0003\t\r\u00055!\u00031\u0001O\u0003\u0015\u0011X-\u00197n\u0003!)8/\u001a:P]2L\u0018AD1mY\"#H\u000f\u001d%fC\u0012,\'o]\u0001\to&$\b.V:feR\u0019A/a\u0006\t\u000b1+\u0002\u0019\u0001(\u0002\u001f]LG\u000f\u001b)bgN<xN\u001d3PaR$2\u0001^A\u000f\u0011\u00159f\u00031\u0001Z\u0003=9\u0018\u000e\u001e5IiR\u0004\b*Z1eKJ\u001cHc\u0001;\u0002$!)Ql\u0006a\u0001?\u0006aq/\u001b;i\u001fB$\u0018n\u001c8bYR\u0019A/!\u000b\t\u000b\u0019D\u0002\u0019\u00015\u0002\u0019]LG\u000f\u001b*fC2lw\n\u001d;\u0015\u0007Q\fy\u0003C\u0003m3\u0001\u0007\u0011,A\u0007xSRD\u0007\n\u001e;qg>sG.\u001f\u000b\u0004i\u0006U\u0002\"\u00028\u001b\u0001\u0004A\u0017AE<ji\"\u0004\u0016m]:P]J+G-\u001b:fGR$2\u0001^A\u001e\u0011\u0015\u00018\u00041\u0001i\u0003!\u0019\u0017M\\#rk\u0006dGc\u00015\u0002B!9\u00111\t\u000fA\u0002\u0005\u0015\u0013aA8cUB\u0019\u0001(a\u0012\n\u0007\u0005%\u0013HA\u0002B]f\fa!Z9vC2\u001cHc\u00015\u0002P!9\u00111I\u000fA\u0002\u0005\u0015\u0013\u0001\u00035bg\"\u001cu\u000eZ3\u0015\u0005\u0005U\u0003c\u0001\u001d\u0002X%\u0019\u0011\u0011L\u001d\u0003\u0007%sG/A\u0003ukBdW-\u0006\u0002\u0002`AQ\u0001(!\u0019O3~C\u0017\f\u001b5\n\u0007\u0005\r\u0014H\u0001\u0004UkBdWmN\u0001\u000eaJ|G-^2u!J,g-\u001b=\u0016\u0005\u0005%\u0004\u0003BA6\u0003kj!!!\u001c\u000b\t\u0005=\u0014\u0011O\u0001\u0005Y\u0006twM\u0003\u0002\u0002t\u0005!!.\u0019<b\u0013\r!\u0016QN\u0001\raJ|G-^2u\u0003JLG/_\u000b\u0003\u0003+\na\u0002\u001d:pIV\u001cG/\u00127f[\u0016tG\u000f\u0006\u0003\u0002F\u0005}\u0004bBAAE\u0001\u0007\u0011QK\u0001\u0002]\u0006\u0011\u0002O]8ek\u000e$X\t\\3nK:$h*Y7f)\u0011\tI\'a\"\t\u000f\u0005\u00055\u00051\u0001\u0002V\u0005q\u0011)\u001e;iK:$\u0018nY1uS>t\u0007CA;&\'\u0011)s\'a$\u0011\t\u0005E\u0015qS\u0007\u0003\u0003\'SA!!&\u0002r\u0005\u0011\u0011n\\\u0005\u0004\u0015\u0006MECAAF\u0003\u0015\t\u0007\u000f\u001d7z)\r!\u0018q\u0014\u0005\u0006\u0019\u001e\u0002\rA\u0014\u000b\u0006i\u0006\r\u0016Q\u0015\u0005\u0006\u0019\"\u0002\rA\u0014\u0005\u0007\u0003\u000bA\u0003\u0019\u0001(\u0015\u001bQ\fI+a+\u0002.\u0006=\u0016\u0011WAZ\u0011\u0015a\u0015\u00061\u0001O\u0011\u00159\u0016\u00061\u0001Z\u0011\u00151\u0017\u00061\u0001i\u0011\u0015a\u0017\u00061\u0001Z\u0011\u0015q\u0017\u00061\u0001i\u0011\u0015\u0001\u0018\u00061\u0001i)5!\u0018qWA]\u0003w\u000bi,a0\u0002B\")AJ\u000ba\u0001\u001d\"1\u0011Q\u0001\u0016A\u00029CQA\u001a\u0016A\u0002!DQ\u0001\u001c\u0016A\u0002eCQA\u001c\u0016A\u0002!DQ\u0001\u001d\u0016A\u0002!$2\u0001^Ac\u0011\u0015i6\u00061\u0001`)-!\u0018\u0011ZAf\u0003\u001b\fy-!5\t\u000buc\u0003\u0019A0\t\u000b\u0019d\u0003\u0019\u00015\t\u000b1d\u0003\u0019A-\t\u000b9d\u0003\u0019\u00015\t\u000bAd\u0003\u0019\u00015\u00023\t\f7/[2BkRDWM\u001c;jG\u0006$\u0018n\u001c8F]\u000e|G-\u001a\u000b\u0006\u001d\u0006]\u0017\u0011\u001c\u0005\u0006\u00196\u0002\rA\u0014\u0005\u0007\u0003\u000bi\u0003\u0019\u0001(\u0015\u001fQ\fi.a8\u0002b\u0006\r\u0018Q]At\u0003SDQ\u0001\u0014\u0018A\u00029CQa\u0016\u0018A\u0002eCQ!\u0018\u0018A\u0002}CQA\u001a\u0018A\u0002!DQ\u0001\u001c\u0018A\u0002eCQA\u001c\u0018A\u0002!DQ\u0001\u001d\u0018A\u0002!\fAb\u001e:ji\u0016\u0014V\r\u001d7bG\u0016$\"!a<\u0011\t\u0005-\u0014\u0011_\u0005\u0005\u0003g\fiG\u0001\u0004PE*,7\r\u001e"
    )
BootstrapMethods:
  0: #135 REF_invokeStatic java/lang/invoke/LambdaMetafactory.altMetafactory:(Ljava/lang/invoke/MethodHandles$Lookup;Ljava/lang/String;Ljava/lang/invoke/MethodType;[Ljava/lang/Object;)Ljava/lang/invoke/CallSite;
    Method arguments:
      #120 (Ljava/lang/Object;)Ljava/lang/Object;
      #125 REF_invokeStatic coursier/core/Authentication.$anonfun$toString$1:(Lscala/Tuple2;)Lscala/Tuple2;
      #126 (Lscala/Tuple2;)Lscala/Tuple2;
      #127 5
      #128 1
      #126 (Lscala/Tuple2;)Lscala/Tuple2;
  1: #135 REF_invokeStatic java/lang/invoke/LambdaMetafactory.altMetafactory:(Ljava/lang/invoke/MethodHandles$Lookup;Ljava/lang/String;Ljava/lang/invoke/MethodType;[Ljava/lang/Object;)Ljava/lang/invoke/CallSite;
    Method arguments:
      #120 (Ljava/lang/Object;)Ljava/lang/Object;
      #206 REF_invokeStatic coursier/core/Authentication.$anonfun$allHttpHeaders$1:(Lcoursier/core/Authentication;Ljava/lang/String;)Lscala/Tuple2;
      #208 (Ljava/lang/String;)Lscala/Tuple2;
      #127 5
      #128 1
      #208 (Ljava/lang/String;)Lscala/Tuple2;
  2: #331 REF_invokeStatic scala/runtime/LambdaDeserialize.bootstrap:(Ljava/lang/invoke/MethodHandles$Lookup;Ljava/lang/String;Ljava/lang/invoke/MethodType;[Ljava/lang/invoke/MethodHandle;)Ljava/lang/invoke/CallSite;
    Method arguments:
      #206 REF_invokeStatic coursier/core/Authentication.$anonfun$allHttpHeaders$1:(Lcoursier/core/Authentication;Ljava/lang/String;)Lscala/Tuple2;
      #125 REF_invokeStatic coursier/core/Authentication.$anonfun$toString$1:(Lscala/Tuple2;)Lscala/Tuple2;
  ScalaInlineInfo: length = 0xA4 (unknown attribute)
   01 01 00 20 00 CA 00 CB 01 00 79 00 7A 01 00 67
   00 DA 01 00 B9 00 56 01 00 E3 00 B6 01 00 B5 00
   B6 01 00 ED 00 EE 01 00 17 00 56 01 00 1D 00 5A
   01 00 1A 00 5A 01 00 1E 00 5A 01 00 14 00 52 01
   01 08 00 EE 01 01 09 01 0A 01 01 16 01 17 01 00
   4A 00 42 01 00 41 00 42 01 01 07 00 4F 01 00 1C
   00 52 01 00 63 00 4F 01 00 F9 00 FA 01 00 12 00
   4F 01 00 B4 00 5A 01 00 DE 00 2E 01 00 E1 00 E0
   01 00 DF 00 E0 01 00 E2 00 E0 01 00 A5 00 3E 01
   00 AB 00 AC 01 00 AF 00 3E 01 00 B1 00 AC 01 00
   D9 00 3E 01
  ScalaSig: length = 0x3 (unknown attribute)
   05 02 00
