Classfile /Users/mw/Projects/slang-braindump/.jar/jar11/assemble/slang-braindump/assemble/content/coursier/core/Classifier.class
  Last modified May 29, 2022; size 7312 bytes
  SHA-256 checksum c3d7ed9fcf2e64eadf9d3442407b46b8a878a73d8c5914b7cfbaf98c0060f43b
  Compiled from "Definitions.scala"
public final class coursier.core.Classifier implements scala.Product,java.io.Serializable
  minor version: 0
  major version: 52
  flags: (0x0031) ACC_PUBLIC, ACC_FINAL, ACC_SUPER
  this_class: #2                          // coursier/core/Classifier
  super_class: #4                         // java/lang/Object
  interfaces: 2, fields: 1, methods: 38, attributes: 4
Constant pool:
    #1 = Utf8               coursier/core/Classifier
    #2 = Class              #1            // coursier/core/Classifier
    #3 = Utf8               java/lang/Object
    #4 = Class              #3            // java/lang/Object
    #5 = Utf8               scala/Product
    #6 = Class              #5            // scala/Product
    #7 = Utf8               java/io/Serializable
    #8 = Class              #7            // java/io/Serializable
    #9 = Utf8               Definitions.scala
   #10 = Utf8               Lscala/reflect/ScalaSignature;
   #11 = Utf8               bytes
   #12 = Utf8               \u0006\u0005\t\u001da\u0001\u0002\u00192\u0005ZB\u0001\u0002\u0014\u0001\u0003\u0016\u0004%\t!\u0014\u0005\t-\u0002\u0011\t\u0012)A\u0005\u001d\")q\u000b\u0001C\u00011\")A\f\u0001C\u0001;\")\u0011\r\u0001C\u0001;\")!\r\u0001C\u0001G\"9\u0011\u000eAA\u0001\n\u0003Q\u0007b\u00027\u0001#\u0003%\t!\u001c\u0005\bq\u0002\t\t\u0011\"\u0011z\u0011%\t\u0019\u0001AA\u0001\n\u0003\t)\u0001C\u0005\u0002\u000e\u0001\t\t\u0011\"\u0001\u0002\u0010!I\u00111\u0004\u0001\u0002\u0002\u0013\u0005\u0013Q\u0004\u0005\n\u0003W\u0001\u0011\u0011!C\u0001\u0003[A\u0011\"!\r\u0001\u0003\u0003%\t%a\r\t\u0013\u0005]\u0002!!A\u0005B\u0005e\u0002\"CA\u001e\u0001\u0005\u0005I\u0011IA\u001f\u0011%\t\t\u0005AA\u0001\n\u0003\n\u0019eB\u0004\u0002FEB\t!a\u0012\u0007\rA\n\u0004\u0012AA%\u0011\u001996\u0003\"\u0001\u0002\\!I\u0011QL\nC\u0002\u0013\r\u0011q\f\u0005\t\u0003O\u001a\u0002\u0015!\u0003\u0002b!I\u0011\u0011N\nC\u0002\u0013\u0005\u00111\u000e\u0005\b\u0003[\u001a\u0002\u0015!\u0003Z\u0011%\tyg\u0005b\u0001\n\u0003\tY\u0007C\u0004\u0002rM\u0001\u000b\u0011B-\t\u0013\u0005M4C1A\u0005\u0002\u0005-\u0004bBA;\'\u0001\u0006I!\u0017\u0005\n\u0003o\u001a\"\u0019!C\u0001\u0003WBq!!\u001f\u0014A\u0003%\u0011\fC\u0005\u0002|M\t\t\u0011\"!\u0002~!I\u0011\u0011Q\n\u0002\u0002\u0013\u0005\u00151\u0011\u0005\n\u0003\u001f\u001b\u0012\u0011!C\u0005\u0003#Cq!!\'\u0014\t\u000b\tY\nC\u0004\u0002\"N!)!a)\t\u000f\u0005\u001d6\u0003\"\u0002\u0002*\"I\u0011\u0011W\n\u0002\u0002\u0013\u0015\u00111\u0017\u0005\n\u0003w\u001b\u0012\u0013!C\u0003\u0003{C\u0011\"!1\u0014\u0003\u0003%)!a1\t\u0013\u0005\u001d7#!A\u0005\u0006\u0005%\u0007\"CAg\'\u0005\u0005IQAAh\u0011%\t9nEA\u0001\n\u000b\tI\u000eC\u0005\u0002^N\t\t\u0011\"\u0002\u0002`\"I\u0011q]\n\u0002\u0002\u0013\u0015\u0011\u0011\u001e\u0005\n\u0003c\u001c\u0012\u0011!C\u0003\u0003gD\u0011\"a>\u0014\u0003\u0003%)!!?\t\u0013\t\u00051#!A\u0005\u0006\t\r!AC\"mCN\u001c\u0018NZ5fe*\u0011!gM\u0001\u0005G>\u0014XMC\u00015\u0003!\u0019w.\u001e:tS\u0016\u00148\u0001A\n\u0005\u0001]j\u0004\t\u0005\u00029w5\t\u0011HC\u0001;\u0003\u0015\u00198-\u00197b\u0013\ta\u0014H\u0001\u0004B]f4\u0016\r\u001c\t\u0003qyJ!aP\u001d\u0003\u000fA\u0013x\u000eZ;diB\u0011\u0011)\u0013\b\u0003\u0005\u001es!a\u0011$\u000e\u0003\u0011S!!R\u001b\u0002\rq\u0012xn\u001c;?\u0013\u0005Q\u0014B\u0001%:\u0003\u001d\u0001\u0018mY6bO\u0016L!AS&\u0003\u0019M+\'/[1mSj\f\'\r\\3\u000b\u0005!K\u0014!\u0002<bYV,W#\u0001(\u0011\u0005=\u001bfB\u0001)R!\t\u0019\u0015(\u0003\u0002Ss\u00051\u0001K]3eK\u001aL!\u0001V+\u0003\rM#(/\u001b8h\u0015\t\u0011\u0016(\u0001\u0004wC2,X\rI\u0001\u0007y%t\u0017\u000e\u001e \u0015\u0005e[\u0006C\u0001.\u0001\u001b\u0005\t\u0004\"\u0002\'\u0004\u0001\u0004q\u0015aB5t\u000b6\u0004H/_\u000b\u0002=B\u0011\u0001hX\u0005\u0003Af\u0012qAQ8pY\u0016\fg.\u0001\u0005o_:,U\u000e\u001d;z\u0003\ri\u0017\r\u001d\u000b\u00033\u0012DQ!\u001a\u0004A\u0002\u0019\f\u0011A\u001a\t\u0005q\u001dte*\u0003\u0002is\tIa)\u001e8di&|g.M\u0001\u0005G>\u0004\u0018\u0010\u0006\u0002ZW\"9Aj\u0002I\u0001\u0002\u0004q\u0015AD2paf$C-\u001a4bk2$H%M\u000b\u0002]*\u0012aj\\\u0016\u0002aB\u0011\u0011O^\u0007\u0002e*\u00111\u000f^\u0001\nk:\u001c\u0007.Z2lK\u0012T!!^\u001d\u0002\u0015\u0005tgn\u001c;bi&|g.\u0003\u0002xe\n\tRO\\2iK\u000e\\W\r\u001a,be&\fgnY3\u0002\u001bA\u0014x\u000eZ;diB\u0013XMZ5y+\u0005Q\bcA>\u0002\u00025\tAP\u0003\u0002~}\u0006!A.\u00198h\u0015\u0005y\u0018\u0001\u00026bm\u0006L!\u0001\u0016?\u0002\u0019A\u0014x\u000eZ;di\u0006\u0013\u0018\u000e^=\u0016\u0005\u0005\u001d\u0001c\u0001\u001d\u0002\n%\u0019\u00111B\u001d\u0003\u0007%sG/\u0001\bqe>$Wo\u0019;FY\u0016lWM\u001c;\u0015\t\u0005E\u0011q\u0003\t\u0004q\u0005M\u0011bAA\u000bs\t\u0019\u0011I\\=\t\u0013\u0005e1\"!AA\u0002\u0005\u001d\u0011a\u0001=%c\u0005y\u0001O]8ek\u000e$\u0018\n^3sCR|\'/\u0006\u0002\u0002 A1\u0011\u0011EA\u0014\u0003#i!!a\t\u000b\u0007\u0005\u0015\u0012(\u0001\u0006d_2dWm\u0019;j_:LA!!\u000b\u0002$\tA\u0011\n^3sCR|\'/\u0001\u0005dC:,\u0015/^1m)\rq\u0016q\u0006\u0005\n\u00033i\u0011\u0011!a\u0001\u0003#\t!\u0003\u001d:pIV\u001cG/\u00127f[\u0016tGOT1nKR\u0019!0!\u000e\t\u0013\u0005ea\"!AA\u0002\u0005\u001d\u0011\u0001\u00035bg\"\u001cu\u000eZ3\u0015\u0005\u0005\u001d\u0011AB3rk\u0006d7\u000fF\u0002_\u0003\u007fA\u0011\"!\u0007\u0011\u0003\u0003\u0005\r!!\u0005\u0002\u0011Q|7\u000b\u001e:j]\u001e$\u0012A_\u0001\u000b\u00072\f7o]5gS\u0016\u0014\bC\u0001.\u0014\'\u0015\u0019\u00121JA)!\rA\u0014QJ\u0005\u0004\u0003\u001fJ$AB!osJ+g\r\u0005\u0003\u0002T\u0005eSBAA+\u0015\r\t9F`\u0001\u0003S>L1ASA+)\t\t9%\u0001\u0005pe\u0012,\'/\u001b8h+\t\t\t\u0007\u0005\u0003B\u0003GJ\u0016bAA3\u0017\nAqJ\u001d3fe&tw-A\u0005pe\u0012,\'/\u001b8hA\u0005)Q-\u001c9usV\t\u0011,\u0001\u0004f[B$\u0018\u0010I\u0001\u0006i\u0016\u001cHo]\u0001\u0007i\u0016\u001cHo\u001d\u0011\u0002\u000f)\fg/\u00193pG\u0006A!.\u0019<bI>\u001c\u0007%A\u0004t_V\u00148-Z:\u0002\u0011M|WO]2fg\u0002\nQ!\u00199qYf$2!WA@\u0011\u0015au\u00041\u0001O\u0003\u001d)h.\u00199qYf$B!!\"\u0002\fB!\u0001(a\"O\u0013\r\tI)\u000f\u0002\u0007\u001fB$\u0018n\u001c8\t\u0011\u00055\u0005%!AA\u0002e\u000b1\u0001\u001f\u00131\u000319(/\u001b;f%\u0016\u0004H.Y2f)\t\t\u0019\nE\u0002|\u0003+K1!a&}\u0005\u0019y%M[3di\u0006\t\u0012n]#naRLH%\u001a=uK:\u001c\u0018n\u001c8\u0015\u0007y\u000bi\n\u0003\u0004\u0002 \n\u0002\r!W\u0001\u0006IQD\u0017n]\u0001\u0013]>tW)\u001c9us\u0012*\u0007\u0010^3og&|g\u000eF\u0002_\u0003KCa!a($\u0001\u0004I\u0016!D7ba\u0012*\u0007\u0010^3og&|g\u000e\u0006\u0003\u0002,\u0006=FcA-\u0002.\")Q\r\na\u0001M\"1\u0011q\u0014\u0013A\u0002e\u000babY8qs\u0012*\u0007\u0010^3og&|g\u000e\u0006\u0003\u00026\u0006eFcA-\u00028\"9A*\nI\u0001\u0002\u0004q\u0005BBAPK\u0001\u0007\u0011,\u0001\rd_BLH\u0005Z3gCVdG\u000fJ\u0019%Kb$XM\\:j_:$2A\\A`\u0011\u0019\tyJ\na\u00013\u00069\u0002O]8ek\u000e$\bK]3gSb$S\r\u001f;f]NLwN\u001c\u000b\u0004u\u0006\u0015\u0007BBAPO\u0001\u0007\u0011,\u0001\fqe>$Wo\u0019;Be&$\u0018\u0010J3yi\u0016t7/[8o)\u0011\t9!a3\t\r\u0005}\u0005\u00061\u0001Z\u0003a\u0001(o\u001c3vGR,E.Z7f]R$S\r\u001f;f]NLwN\u001c\u000b\u0005\u0003#\f)\u000e\u0006\u0003\u0002\u0012\u0005M\u0007\"CA\rS\u0005\u0005\t\u0019AA\u0004\u0011\u0019\ty*\u000ba\u00013\u0006I\u0002O]8ek\u000e$\u0018\n^3sCR|\'\u000fJ3yi\u0016t7/[8o)\u0011\ty\"a7\t\r\u0005}%\u00061\u0001Z\u0003I\u0019\u0017M\\#rk\u0006dG%\u001a=uK:\u001c\u0018n\u001c8\u0015\t\u0005\u0005\u0018Q\u001d\u000b\u0004=\u0006\r\b\"CA\rW\u0005\u0005\t\u0019AA\t\u0011\u0019\tyj\u000ba\u00013\u0006a\u0002O]8ek\u000e$X\t\\3nK:$h*Y7fI\u0015DH/\u001a8tS>tG\u0003BAv\u0003_$2A_Aw\u0011%\tI\u0002LA\u0001\u0002\u0004\t9\u0001\u0003\u0004\u0002 2\u0002\r!W\u0001\u0013Q\u0006\u001c\bnQ8eK\u0012*\u0007\u0010^3og&|g\u000e\u0006\u0003\u0002:\u0005U\bBBAP[\u0001\u0007\u0011,\u0001\tfcV\fGn\u001d\u0013fqR,gn]5p]R!\u00111`A\u0000)\rq\u0016Q \u0005\n\u00033q\u0013\u0011!a\u0001\u0003#Aa!a(/\u0001\u0004I\u0016A\u0005;p\'R\u0014\u0018N\\4%Kb$XM\\:j_:$B!a\u0011\u0003\u0006!1\u0011qT\u0018A\u0002e\u0003
   #13 = Utf8               value
   #14 = Utf8               Ljava/lang/String;
   #15 = Utf8               toString$extension
   #16 = Utf8               (Ljava/lang/String;)Ljava/lang/String;
   #17 = Utf8               $this
   #18 = Utf8               coursier/core/Classifier$
   #19 = Class              #18           // coursier/core/Classifier$
   #20 = Utf8               MODULE$
   #21 = Utf8               Lcoursier/core/Classifier$;
   #22 = NameAndType        #20:#21       // MODULE$:Lcoursier/core/Classifier$;
   #23 = Fieldref           #19.#22       // coursier/core/Classifier$.MODULE$:Lcoursier/core/Classifier$;
   #24 = NameAndType        #15:#16       // toString$extension:(Ljava/lang/String;)Ljava/lang/String;
   #25 = Methodref          #19.#24       // coursier/core/Classifier$.toString$extension:(Ljava/lang/String;)Ljava/lang/String;
   #26 = Utf8               equals$extension
   #27 = Utf8               (Ljava/lang/String;Ljava/lang/Object;)Z
   #28 = Utf8               x$1
   #29 = NameAndType        #26:#27       // equals$extension:(Ljava/lang/String;Ljava/lang/Object;)Z
   #30 = Methodref          #19.#29       // coursier/core/Classifier$.equals$extension:(Ljava/lang/String;Ljava/lang/Object;)Z
   #31 = Utf8               hashCode$extension
   #32 = Utf8               (Ljava/lang/String;)I
   #33 = NameAndType        #31:#32       // hashCode$extension:(Ljava/lang/String;)I
   #34 = Methodref          #19.#33       // coursier/core/Classifier$.hashCode$extension:(Ljava/lang/String;)I
   #35 = Utf8               productElementName$extension
   #36 = Utf8               (Ljava/lang/String;I)Ljava/lang/String;
   #37 = NameAndType        #35:#36       // productElementName$extension:(Ljava/lang/String;I)Ljava/lang/String;
   #38 = Methodref          #19.#37       // coursier/core/Classifier$.productElementName$extension:(Ljava/lang/String;I)Ljava/lang/String;
   #39 = Utf8               canEqual$extension
   #40 = NameAndType        #39:#27       // canEqual$extension:(Ljava/lang/String;Ljava/lang/Object;)Z
   #41 = Methodref          #19.#40       // coursier/core/Classifier$.canEqual$extension:(Ljava/lang/String;Ljava/lang/Object;)Z
   #42 = Utf8               productIterator$extension
   #43 = Utf8               (Ljava/lang/String;)Lscala/collection/Iterator;
   #44 = Utf8               (Ljava/lang/String;)Lscala/collection/Iterator<Ljava/lang/Object;>;
   #45 = NameAndType        #42:#43       // productIterator$extension:(Ljava/lang/String;)Lscala/collection/Iterator;
   #46 = Methodref          #19.#45       // coursier/core/Classifier$.productIterator$extension:(Ljava/lang/String;)Lscala/collection/Iterator;
   #47 = Utf8               productElement$extension
   #48 = Utf8               (Ljava/lang/String;I)Ljava/lang/Object;
   #49 = NameAndType        #47:#48       // productElement$extension:(Ljava/lang/String;I)Ljava/lang/Object;
   #50 = Methodref          #19.#49       // coursier/core/Classifier$.productElement$extension:(Ljava/lang/String;I)Ljava/lang/Object;
   #51 = Utf8               productArity$extension
   #52 = NameAndType        #51:#32       // productArity$extension:(Ljava/lang/String;)I
   #53 = Methodref          #19.#52       // coursier/core/Classifier$.productArity$extension:(Ljava/lang/String;)I
   #54 = Utf8               productPrefix$extension
   #55 = NameAndType        #54:#16       // productPrefix$extension:(Ljava/lang/String;)Ljava/lang/String;
   #56 = Methodref          #19.#55       // coursier/core/Classifier$.productPrefix$extension:(Ljava/lang/String;)Ljava/lang/String;
   #57 = Utf8               copy$default$1$extension
   #58 = NameAndType        #57:#16       // copy$default$1$extension:(Ljava/lang/String;)Ljava/lang/String;
   #59 = Methodref          #19.#58       // coursier/core/Classifier$.copy$default$1$extension:(Ljava/lang/String;)Ljava/lang/String;
   #60 = Utf8               copy$extension
   #61 = Utf8               (Ljava/lang/String;Ljava/lang/String;)Ljava/lang/String;
   #62 = NameAndType        #60:#61       // copy$extension:(Ljava/lang/String;Ljava/lang/String;)Ljava/lang/String;
   #63 = Methodref          #19.#62       // coursier/core/Classifier$.copy$extension:(Ljava/lang/String;Ljava/lang/String;)Ljava/lang/String;
   #64 = Utf8               map$extension
   #65 = Utf8               (Ljava/lang/String;Lscala/Function1;)Ljava/lang/String;
   #66 = Utf8               f
   #67 = NameAndType        #64:#65       // map$extension:(Ljava/lang/String;Lscala/Function1;)Ljava/lang/String;
   #68 = Methodref          #19.#67       // coursier/core/Classifier$.map$extension:(Ljava/lang/String;Lscala/Function1;)Ljava/lang/String;
   #69 = Utf8               nonEmpty$extension
   #70 = Utf8               (Ljava/lang/String;)Z
   #71 = NameAndType        #69:#70       // nonEmpty$extension:(Ljava/lang/String;)Z
   #72 = Methodref          #19.#71       // coursier/core/Classifier$.nonEmpty$extension:(Ljava/lang/String;)Z
   #73 = Utf8               isEmpty$extension
   #74 = NameAndType        #73:#70       // isEmpty$extension:(Ljava/lang/String;)Z
   #75 = Methodref          #19.#74       // coursier/core/Classifier$.isEmpty$extension:(Ljava/lang/String;)Z
   #76 = Utf8               unapply
   #77 = Utf8               (Ljava/lang/String;)Lscala/Option;
   #78 = Utf8               (Ljava/lang/String;)Lscala/Option<Ljava/lang/String;>;
   #79 = Utf8               x$0
   #80 = NameAndType        #76:#77       // unapply:(Ljava/lang/String;)Lscala/Option;
   #81 = Methodref          #19.#80       // coursier/core/Classifier$.unapply:(Ljava/lang/String;)Lscala/Option;
   #82 = Utf8               apply
   #83 = NameAndType        #82:#16       // apply:(Ljava/lang/String;)Ljava/lang/String;
   #84 = Methodref          #19.#83       // coursier/core/Classifier$.apply:(Ljava/lang/String;)Ljava/lang/String;
   #85 = Utf8               sources
   #86 = Utf8               ()Ljava/lang/String;
   #87 = NameAndType        #85:#86       // sources:()Ljava/lang/String;
   #88 = Methodref          #19.#87       // coursier/core/Classifier$.sources:()Ljava/lang/String;
   #89 = Utf8               javadoc
   #90 = NameAndType        #89:#86       // javadoc:()Ljava/lang/String;
   #91 = Methodref          #19.#90       // coursier/core/Classifier$.javadoc:()Ljava/lang/String;
   #92 = Utf8               tests
   #93 = NameAndType        #92:#86       // tests:()Ljava/lang/String;
   #94 = Methodref          #19.#93       // coursier/core/Classifier$.tests:()Ljava/lang/String;
   #95 = Utf8               empty
   #96 = NameAndType        #95:#86       // empty:()Ljava/lang/String;
   #97 = Methodref          #19.#96       // coursier/core/Classifier$.empty:()Ljava/lang/String;
   #98 = Utf8               ordering
   #99 = Utf8               ()Lscala/math/Ordering;
  #100 = Utf8               ()Lscala/math/Ordering<Lcoursier/core/Classifier;>;
  #101 = NameAndType        #98:#99       // ordering:()Lscala/math/Ordering;
  #102 = Methodref          #19.#101      // coursier/core/Classifier$.ordering:()Lscala/math/Ordering;
  #103 = Utf8               productElementNames
  #104 = Utf8               ()Lscala/collection/Iterator;
  #105 = Utf8               ()Lscala/collection/Iterator<Ljava/lang/String;>;
  #106 = Utf8               productElementNames$
  #107 = Utf8               (Lscala/Product;)Lscala/collection/Iterator;
  #108 = NameAndType        #106:#107     // productElementNames$:(Lscala/Product;)Lscala/collection/Iterator;
  #109 = InterfaceMethodref #6.#108       // scala/Product.productElementNames$:(Lscala/Product;)Lscala/collection/Iterator;
  #110 = Utf8               this
  #111 = Utf8               Lcoursier/core/Classifier;
  #112 = NameAndType        #13:#14       // value:Ljava/lang/String;
  #113 = Fieldref           #2.#112       // coursier/core/Classifier.value:Ljava/lang/String;
  #114 = Utf8               isEmpty
  #115 = Utf8               ()Z
  #116 = NameAndType        #13:#86       // value:()Ljava/lang/String;
  #117 = Methodref          #2.#116       // coursier/core/Classifier.value:()Ljava/lang/String;
  #118 = Utf8               nonEmpty
  #119 = Utf8               map
  #120 = Utf8               (Lscala/Function1;)Ljava/lang/String;
  #121 = Utf8               (Lscala/Function1<Ljava/lang/String;Ljava/lang/String;>;)Ljava/lang/String;
  #122 = Utf8               Lscala/Function1;
  #123 = Utf8               copy
  #124 = Utf8               copy$default$1
  #125 = Utf8               productPrefix
  #126 = Utf8               productArity
  #127 = Utf8               ()I
  #128 = Utf8               productElement
  #129 = Utf8               (I)Ljava/lang/Object;
  #130 = Utf8               I
  #131 = Utf8               productIterator
  #132 = Utf8               ()Lscala/collection/Iterator<Ljava/lang/Object;>;
  #133 = Utf8               canEqual
  #134 = Utf8               (Ljava/lang/Object;)Z
  #135 = Utf8               Ljava/lang/Object;
  #136 = Utf8               productElementName
  #137 = Utf8               (I)Ljava/lang/String;
  #138 = Utf8               hashCode
  #139 = Utf8               equals
  #140 = Utf8               toString
  #141 = Utf8               <init>
  #142 = Utf8               (Ljava/lang/String;)V
  #143 = Utf8               ()V
  #144 = NameAndType        #141:#143     // "<init>":()V
  #145 = Methodref          #4.#144       // java/lang/Object."<init>":()V
  #146 = Utf8               $init$
  #147 = Utf8               (Lscala/Product;)V
  #148 = NameAndType        #146:#147     // $init$:(Lscala/Product;)V
  #149 = InterfaceMethodref #6.#148       // scala/Product.$init$:(Lscala/Product;)V
  #150 = Utf8               Code
  #151 = Utf8               MethodParameters
  #152 = Utf8               Signature
  #153 = Utf8               LineNumberTable
  #154 = Utf8               LocalVariableTable
  #155 = Utf8               SourceFile
  #156 = Utf8               RuntimeVisibleAnnotations
  #157 = Utf8               ScalaInlineInfo
  #158 = Utf8               ScalaSig
{
  private final java.lang.String value;
    descriptor: Ljava/lang/String;
    flags: (0x0012) ACC_PRIVATE, ACC_FINAL

  public static java.lang.String toString$extension(java.lang.String);
    descriptor: (Ljava/lang/String;)Ljava/lang/String;
    flags: (0x0009) ACC_PUBLIC, ACC_STATIC
    Code:
      stack=2, locals=1, args_size=1
         0: getstatic     #23                 // Field coursier/core/Classifier$.MODULE$:Lcoursier/core/Classifier$;
         3: aload_0
         4: invokevirtual #25                 // Method coursier/core/Classifier$.toString$extension:(Ljava/lang/String;)Ljava/lang/String;
         7: areturn
    MethodParameters:
      Name                           Flags
      $this                          final

  public static boolean equals$extension(java.lang.String, java.lang.Object);
    descriptor: (Ljava/lang/String;Ljava/lang/Object;)Z
    flags: (0x0009) ACC_PUBLIC, ACC_STATIC
    Code:
      stack=3, locals=2, args_size=2
         0: getstatic     #23                 // Field coursier/core/Classifier$.MODULE$:Lcoursier/core/Classifier$;
         3: aload_0
         4: aload_1
         5: invokevirtual #30                 // Method coursier/core/Classifier$.equals$extension:(Ljava/lang/String;Ljava/lang/Object;)Z
         8: ireturn
    MethodParameters:
      Name                           Flags
      $this                          final
      x$1                            final

  public static int hashCode$extension(java.lang.String);
    descriptor: (Ljava/lang/String;)I
    flags: (0x0009) ACC_PUBLIC, ACC_STATIC
    Code:
      stack=2, locals=1, args_size=1
         0: getstatic     #23                 // Field coursier/core/Classifier$.MODULE$:Lcoursier/core/Classifier$;
         3: aload_0
         4: invokevirtual #34                 // Method coursier/core/Classifier$.hashCode$extension:(Ljava/lang/String;)I
         7: ireturn
    MethodParameters:
      Name                           Flags
      $this                          final

  public static java.lang.String productElementName$extension(java.lang.String, int);
    descriptor: (Ljava/lang/String;I)Ljava/lang/String;
    flags: (0x0009) ACC_PUBLIC, ACC_STATIC
    Code:
      stack=3, locals=2, args_size=2
         0: getstatic     #23                 // Field coursier/core/Classifier$.MODULE$:Lcoursier/core/Classifier$;
         3: aload_0
         4: iload_1
         5: invokevirtual #38                 // Method coursier/core/Classifier$.productElementName$extension:(Ljava/lang/String;I)Ljava/lang/String;
         8: areturn
    MethodParameters:
      Name                           Flags
      $this                          final
      x$1                            final

  public static boolean canEqual$extension(java.lang.String, java.lang.Object);
    descriptor: (Ljava/lang/String;Ljava/lang/Object;)Z
    flags: (0x0009) ACC_PUBLIC, ACC_STATIC
    Code:
      stack=3, locals=2, args_size=2
         0: getstatic     #23                 // Field coursier/core/Classifier$.MODULE$:Lcoursier/core/Classifier$;
         3: aload_0
         4: aload_1
         5: invokevirtual #41                 // Method coursier/core/Classifier$.canEqual$extension:(Ljava/lang/String;Ljava/lang/Object;)Z
         8: ireturn
    MethodParameters:
      Name                           Flags
      $this                          final
      x$1                            final

  public static scala.collection.Iterator<java.lang.Object> productIterator$extension(java.lang.String);
    descriptor: (Ljava/lang/String;)Lscala/collection/Iterator;
    flags: (0x0009) ACC_PUBLIC, ACC_STATIC
    Code:
      stack=2, locals=1, args_size=1
         0: getstatic     #23                 // Field coursier/core/Classifier$.MODULE$:Lcoursier/core/Classifier$;
         3: aload_0
         4: invokevirtual #46                 // Method coursier/core/Classifier$.productIterator$extension:(Ljava/lang/String;)Lscala/collection/Iterator;
         7: areturn
    Signature: #44                          // (Ljava/lang/String;)Lscala/collection/Iterator<Ljava/lang/Object;>;
    MethodParameters:
      Name                           Flags
      $this                          final

  public static java.lang.Object productElement$extension(java.lang.String, int);
    descriptor: (Ljava/lang/String;I)Ljava/lang/Object;
    flags: (0x0009) ACC_PUBLIC, ACC_STATIC
    Code:
      stack=3, locals=2, args_size=2
         0: getstatic     #23                 // Field coursier/core/Classifier$.MODULE$:Lcoursier/core/Classifier$;
         3: aload_0
         4: iload_1
         5: invokevirtual #50                 // Method coursier/core/Classifier$.productElement$extension:(Ljava/lang/String;I)Ljava/lang/Object;
         8: areturn
    MethodParameters:
      Name                           Flags
      $this                          final
      x$1                            final

  public static int productArity$extension(java.lang.String);
    descriptor: (Ljava/lang/String;)I
    flags: (0x0009) ACC_PUBLIC, ACC_STATIC
    Code:
      stack=2, locals=1, args_size=1
         0: getstatic     #23                 // Field coursier/core/Classifier$.MODULE$:Lcoursier/core/Classifier$;
         3: aload_0
         4: invokevirtual #53                 // Method coursier/core/Classifier$.productArity$extension:(Ljava/lang/String;)I
         7: ireturn
    MethodParameters:
      Name                           Flags
      $this                          final

  public static java.lang.String productPrefix$extension(java.lang.String);
    descriptor: (Ljava/lang/String;)Ljava/lang/String;
    flags: (0x0009) ACC_PUBLIC, ACC_STATIC
    Code:
      stack=2, locals=1, args_size=1
         0: getstatic     #23                 // Field coursier/core/Classifier$.MODULE$:Lcoursier/core/Classifier$;
         3: aload_0
         4: invokevirtual #56                 // Method coursier/core/Classifier$.productPrefix$extension:(Ljava/lang/String;)Ljava/lang/String;
         7: areturn
    MethodParameters:
      Name                           Flags
      $this                          final

  public static java.lang.String copy$default$1$extension(java.lang.String);
    descriptor: (Ljava/lang/String;)Ljava/lang/String;
    flags: (0x0009) ACC_PUBLIC, ACC_STATIC
    Code:
      stack=2, locals=1, args_size=1
         0: getstatic     #23                 // Field coursier/core/Classifier$.MODULE$:Lcoursier/core/Classifier$;
         3: aload_0
         4: invokevirtual #59                 // Method coursier/core/Classifier$.copy$default$1$extension:(Ljava/lang/String;)Ljava/lang/String;
         7: areturn
    MethodParameters:
      Name                           Flags
      $this                          final

  public static java.lang.String copy$extension(java.lang.String, java.lang.String);
    descriptor: (Ljava/lang/String;Ljava/lang/String;)Ljava/lang/String;
    flags: (0x0009) ACC_PUBLIC, ACC_STATIC
    Code:
      stack=3, locals=2, args_size=2
         0: getstatic     #23                 // Field coursier/core/Classifier$.MODULE$:Lcoursier/core/Classifier$;
         3: aload_0
         4: aload_1
         5: invokevirtual #63                 // Method coursier/core/Classifier$.copy$extension:(Ljava/lang/String;Ljava/lang/String;)Ljava/lang/String;
         8: areturn
    MethodParameters:
      Name                           Flags
      $this                          final
      value                          final

  public static java.lang.String map$extension(java.lang.String, scala.Function1);
    descriptor: (Ljava/lang/String;Lscala/Function1;)Ljava/lang/String;
    flags: (0x0009) ACC_PUBLIC, ACC_STATIC
    Code:
      stack=3, locals=2, args_size=2
         0: getstatic     #23                 // Field coursier/core/Classifier$.MODULE$:Lcoursier/core/Classifier$;
         3: aload_0
         4: aload_1
         5: invokevirtual #68                 // Method coursier/core/Classifier$.map$extension:(Ljava/lang/String;Lscala/Function1;)Ljava/lang/String;
         8: areturn
    MethodParameters:
      Name                           Flags
      $this                          final
      f                              final

  public static boolean nonEmpty$extension(java.lang.String);
    descriptor: (Ljava/lang/String;)Z
    flags: (0x0009) ACC_PUBLIC, ACC_STATIC
    Code:
      stack=2, locals=1, args_size=1
         0: getstatic     #23                 // Field coursier/core/Classifier$.MODULE$:Lcoursier/core/Classifier$;
         3: aload_0
         4: invokevirtual #72                 // Method coursier/core/Classifier$.nonEmpty$extension:(Ljava/lang/String;)Z
         7: ireturn
    MethodParameters:
      Name                           Flags
      $this                          final

  public static boolean isEmpty$extension(java.lang.String);
    descriptor: (Ljava/lang/String;)Z
    flags: (0x0009) ACC_PUBLIC, ACC_STATIC
    Code:
      stack=2, locals=1, args_size=1
         0: getstatic     #23                 // Field coursier/core/Classifier$.MODULE$:Lcoursier/core/Classifier$;
         3: aload_0
         4: invokevirtual #75                 // Method coursier/core/Classifier$.isEmpty$extension:(Ljava/lang/String;)Z
         7: ireturn
    MethodParameters:
      Name                           Flags
      $this                          final

  public static scala.Option<java.lang.String> unapply(java.lang.String);
    descriptor: (Ljava/lang/String;)Lscala/Option;
    flags: (0x0009) ACC_PUBLIC, ACC_STATIC
    Code:
      stack=2, locals=1, args_size=1
         0: getstatic     #23                 // Field coursier/core/Classifier$.MODULE$:Lcoursier/core/Classifier$;
         3: aload_0
         4: invokevirtual #81                 // Method coursier/core/Classifier$.unapply:(Ljava/lang/String;)Lscala/Option;
         7: areturn
    Signature: #78                          // (Ljava/lang/String;)Lscala/Option<Ljava/lang/String;>;
    MethodParameters:
      Name                           Flags
      x$0                            final

  public static java.lang.String apply(java.lang.String);
    descriptor: (Ljava/lang/String;)Ljava/lang/String;
    flags: (0x0009) ACC_PUBLIC, ACC_STATIC
    Code:
      stack=2, locals=1, args_size=1
         0: getstatic     #23                 // Field coursier/core/Classifier$.MODULE$:Lcoursier/core/Classifier$;
         3: aload_0
         4: invokevirtual #84                 // Method coursier/core/Classifier$.apply:(Ljava/lang/String;)Ljava/lang/String;
         7: areturn
    MethodParameters:
      Name                           Flags
      value                          final

  public static java.lang.String sources();
    descriptor: ()Ljava/lang/String;
    flags: (0x0009) ACC_PUBLIC, ACC_STATIC
    Code:
      stack=1, locals=0, args_size=0
         0: getstatic     #23                 // Field coursier/core/Classifier$.MODULE$:Lcoursier/core/Classifier$;
         3: invokevirtual #88                 // Method coursier/core/Classifier$.sources:()Ljava/lang/String;
         6: areturn

  public static java.lang.String javadoc();
    descriptor: ()Ljava/lang/String;
    flags: (0x0009) ACC_PUBLIC, ACC_STATIC
    Code:
      stack=1, locals=0, args_size=0
         0: getstatic     #23                 // Field coursier/core/Classifier$.MODULE$:Lcoursier/core/Classifier$;
         3: invokevirtual #91                 // Method coursier/core/Classifier$.javadoc:()Ljava/lang/String;
         6: areturn

  public static java.lang.String tests();
    descriptor: ()Ljava/lang/String;
    flags: (0x0009) ACC_PUBLIC, ACC_STATIC
    Code:
      stack=1, locals=0, args_size=0
         0: getstatic     #23                 // Field coursier/core/Classifier$.MODULE$:Lcoursier/core/Classifier$;
         3: invokevirtual #94                 // Method coursier/core/Classifier$.tests:()Ljava/lang/String;
         6: areturn

  public static java.lang.String empty();
    descriptor: ()Ljava/lang/String;
    flags: (0x0009) ACC_PUBLIC, ACC_STATIC
    Code:
      stack=1, locals=0, args_size=0
         0: getstatic     #23                 // Field coursier/core/Classifier$.MODULE$:Lcoursier/core/Classifier$;
         3: invokevirtual #97                 // Method coursier/core/Classifier$.empty:()Ljava/lang/String;
         6: areturn

  public static scala.math.Ordering<coursier.core.Classifier> ordering();
    descriptor: ()Lscala/math/Ordering;
    flags: (0x0009) ACC_PUBLIC, ACC_STATIC
    Code:
      stack=1, locals=0, args_size=0
         0: getstatic     #23                 // Field coursier/core/Classifier$.MODULE$:Lcoursier/core/Classifier$;
         3: invokevirtual #102                // Method coursier/core/Classifier$.ordering:()Lscala/math/Ordering;
         6: areturn
    Signature: #100                         // ()Lscala/math/Ordering<Lcoursier/core/Classifier;>;

  public scala.collection.Iterator<java.lang.String> productElementNames();
    descriptor: ()Lscala/collection/Iterator;
    flags: (0x0001) ACC_PUBLIC
    Code:
      stack=1, locals=1, args_size=1
         0: aload_0
         1: invokestatic  #109                // InterfaceMethod scala/Product.productElementNames$:(Lscala/Product;)Lscala/collection/Iterator;
         4: areturn
      LineNumberTable:
        line 127: 0
      LocalVariableTable:
        Start  Length  Slot  Name   Signature
            0       5     0  this   Lcoursier/core/Classifier;
    Signature: #105                         // ()Lscala/collection/Iterator<Ljava/lang/String;>;

  public java.lang.String value();
    descriptor: ()Ljava/lang/String;
    flags: (0x0001) ACC_PUBLIC
    Code:
      stack=1, locals=1, args_size=1
         0: aload_0
         1: getfield      #113                // Field value:Ljava/lang/String;
         4: areturn
      LineNumberTable:
        line 127: 0
      LocalVariableTable:
        Start  Length  Slot  Name   Signature
            0       5     0  this   Lcoursier/core/Classifier;

  public boolean isEmpty();
    descriptor: ()Z
    flags: (0x0001) ACC_PUBLIC
    Code:
      stack=2, locals=1, args_size=1
         0: getstatic     #23                 // Field coursier/core/Classifier$.MODULE$:Lcoursier/core/Classifier$;
         3: aload_0
         4: invokevirtual #117                // Method value:()Ljava/lang/String;
         7: invokevirtual #75                 // Method coursier/core/Classifier$.isEmpty$extension:(Ljava/lang/String;)Z
        10: ireturn
      LineNumberTable:
        line 129: 0
      LocalVariableTable:
        Start  Length  Slot  Name   Signature
            0      11     0  this   Lcoursier/core/Classifier;

  public boolean nonEmpty();
    descriptor: ()Z
    flags: (0x0001) ACC_PUBLIC
    Code:
      stack=2, locals=1, args_size=1
         0: getstatic     #23                 // Field coursier/core/Classifier$.MODULE$:Lcoursier/core/Classifier$;
         3: aload_0
         4: invokevirtual #117                // Method value:()Ljava/lang/String;
         7: invokevirtual #72                 // Method coursier/core/Classifier$.nonEmpty$extension:(Ljava/lang/String;)Z
        10: ireturn
      LineNumberTable:
        line 131: 0
      LocalVariableTable:
        Start  Length  Slot  Name   Signature
            0      11     0  this   Lcoursier/core/Classifier;

  public java.lang.String map(scala.Function1<java.lang.String, java.lang.String>);
    descriptor: (Lscala/Function1;)Ljava/lang/String;
    flags: (0x0001) ACC_PUBLIC
    Code:
      stack=3, locals=2, args_size=2
         0: getstatic     #23                 // Field coursier/core/Classifier$.MODULE$:Lcoursier/core/Classifier$;
         3: aload_0
         4: invokevirtual #117                // Method value:()Ljava/lang/String;
         7: aload_1
         8: invokevirtual #68                 // Method coursier/core/Classifier$.map$extension:(Ljava/lang/String;Lscala/Function1;)Ljava/lang/String;
        11: areturn
      LineNumberTable:
        line 133: 0
      LocalVariableTable:
        Start  Length  Slot  Name   Signature
            0      12     0  this   Lcoursier/core/Classifier;
            0      12     1     f   Lscala/Function1;
    Signature: #121                         // (Lscala/Function1<Ljava/lang/String;Ljava/lang/String;>;)Ljava/lang/String;
    MethodParameters:
      Name                           Flags
      f                              final

  public java.lang.String copy(java.lang.String);
    descriptor: (Ljava/lang/String;)Ljava/lang/String;
    flags: (0x0001) ACC_PUBLIC
    Code:
      stack=3, locals=2, args_size=2
         0: getstatic     #23                 // Field coursier/core/Classifier$.MODULE$:Lcoursier/core/Classifier$;
         3: aload_0
         4: invokevirtual #117                // Method value:()Ljava/lang/String;
         7: aload_1
         8: invokevirtual #63                 // Method coursier/core/Classifier$.copy$extension:(Ljava/lang/String;Ljava/lang/String;)Ljava/lang/String;
        11: areturn
      LineNumberTable:
        line 127: 0
      LocalVariableTable:
        Start  Length  Slot  Name   Signature
            0      12     0  this   Lcoursier/core/Classifier;
            0      12     1 value   Ljava/lang/String;
    MethodParameters:
      Name                           Flags
      value                          final

  public java.lang.String copy$default$1();
    descriptor: ()Ljava/lang/String;
    flags: (0x0001) ACC_PUBLIC
    Code:
      stack=2, locals=1, args_size=1
         0: getstatic     #23                 // Field coursier/core/Classifier$.MODULE$:Lcoursier/core/Classifier$;
         3: aload_0
         4: invokevirtual #117                // Method value:()Ljava/lang/String;
         7: invokevirtual #59                 // Method coursier/core/Classifier$.copy$default$1$extension:(Ljava/lang/String;)Ljava/lang/String;
        10: areturn
      LineNumberTable:
        line 127: 0
      LocalVariableTable:
        Start  Length  Slot  Name   Signature
            0      11     0  this   Lcoursier/core/Classifier;

  public java.lang.String productPrefix();
    descriptor: ()Ljava/lang/String;
    flags: (0x0001) ACC_PUBLIC
    Code:
      stack=2, locals=1, args_size=1
         0: getstatic     #23                 // Field coursier/core/Classifier$.MODULE$:Lcoursier/core/Classifier$;
         3: aload_0
         4: invokevirtual #117                // Method value:()Ljava/lang/String;
         7: invokevirtual #56                 // Method coursier/core/Classifier$.productPrefix$extension:(Ljava/lang/String;)Ljava/lang/String;
        10: areturn
      LineNumberTable:
        line 127: 0
      LocalVariableTable:
        Start  Length  Slot  Name   Signature
            0      11     0  this   Lcoursier/core/Classifier;

  public int productArity();
    descriptor: ()I
    flags: (0x0001) ACC_PUBLIC
    Code:
      stack=2, locals=1, args_size=1
         0: getstatic     #23                 // Field coursier/core/Classifier$.MODULE$:Lcoursier/core/Classifier$;
         3: aload_0
         4: invokevirtual #117                // Method value:()Ljava/lang/String;
         7: invokevirtual #53                 // Method coursier/core/Classifier$.productArity$extension:(Ljava/lang/String;)I
        10: ireturn
      LineNumberTable:
        line 127: 0
      LocalVariableTable:
        Start  Length  Slot  Name   Signature
            0      11     0  this   Lcoursier/core/Classifier;

  public java.lang.Object productElement(int);
    descriptor: (I)Ljava/lang/Object;
    flags: (0x0001) ACC_PUBLIC
    Code:
      stack=3, locals=2, args_size=2
         0: getstatic     #23                 // Field coursier/core/Classifier$.MODULE$:Lcoursier/core/Classifier$;
         3: aload_0
         4: invokevirtual #117                // Method value:()Ljava/lang/String;
         7: iload_1
         8: invokevirtual #50                 // Method coursier/core/Classifier$.productElement$extension:(Ljava/lang/String;I)Ljava/lang/Object;
        11: areturn
      LineNumberTable:
        line 127: 0
      LocalVariableTable:
        Start  Length  Slot  Name   Signature
            0      12     0  this   Lcoursier/core/Classifier;
            0      12     1   x$1   I
    MethodParameters:
      Name                           Flags
      x$1                            final

  public scala.collection.Iterator<java.lang.Object> productIterator();
    descriptor: ()Lscala/collection/Iterator;
    flags: (0x0001) ACC_PUBLIC
    Code:
      stack=2, locals=1, args_size=1
         0: getstatic     #23                 // Field coursier/core/Classifier$.MODULE$:Lcoursier/core/Classifier$;
         3: aload_0
         4: invokevirtual #117                // Method value:()Ljava/lang/String;
         7: invokevirtual #46                 // Method coursier/core/Classifier$.productIterator$extension:(Ljava/lang/String;)Lscala/collection/Iterator;
        10: areturn
      LineNumberTable:
        line 127: 0
      LocalVariableTable:
        Start  Length  Slot  Name   Signature
            0      11     0  this   Lcoursier/core/Classifier;
    Signature: #132                         // ()Lscala/collection/Iterator<Ljava/lang/Object;>;

  public boolean canEqual(java.lang.Object);
    descriptor: (Ljava/lang/Object;)Z
    flags: (0x0001) ACC_PUBLIC
    Code:
      stack=3, locals=2, args_size=2
         0: getstatic     #23                 // Field coursier/core/Classifier$.MODULE$:Lcoursier/core/Classifier$;
         3: aload_0
         4: invokevirtual #117                // Method value:()Ljava/lang/String;
         7: aload_1
         8: invokevirtual #41                 // Method coursier/core/Classifier$.canEqual$extension:(Ljava/lang/String;Ljava/lang/Object;)Z
        11: ireturn
      LineNumberTable:
        line 127: 0
      LocalVariableTable:
        Start  Length  Slot  Name   Signature
            0      12     0  this   Lcoursier/core/Classifier;
            0      12     1   x$1   Ljava/lang/Object;
    MethodParameters:
      Name                           Flags
      x$1                            final

  public java.lang.String productElementName(int);
    descriptor: (I)Ljava/lang/String;
    flags: (0x0001) ACC_PUBLIC
    Code:
      stack=3, locals=2, args_size=2
         0: getstatic     #23                 // Field coursier/core/Classifier$.MODULE$:Lcoursier/core/Classifier$;
         3: aload_0
         4: invokevirtual #117                // Method value:()Ljava/lang/String;
         7: iload_1
         8: invokevirtual #38                 // Method coursier/core/Classifier$.productElementName$extension:(Ljava/lang/String;I)Ljava/lang/String;
        11: areturn
      LineNumberTable:
        line 127: 0
      LocalVariableTable:
        Start  Length  Slot  Name   Signature
            0      12     0  this   Lcoursier/core/Classifier;
            0      12     1   x$1   I
    MethodParameters:
      Name                           Flags
      x$1                            final

  public int hashCode();
    descriptor: ()I
    flags: (0x0001) ACC_PUBLIC
    Code:
      stack=2, locals=1, args_size=1
         0: getstatic     #23                 // Field coursier/core/Classifier$.MODULE$:Lcoursier/core/Classifier$;
         3: aload_0
         4: invokevirtual #117                // Method value:()Ljava/lang/String;
         7: invokevirtual #34                 // Method coursier/core/Classifier$.hashCode$extension:(Ljava/lang/String;)I
        10: ireturn
      LineNumberTable:
        line 127: 0
      LocalVariableTable:
        Start  Length  Slot  Name   Signature
            0      11     0  this   Lcoursier/core/Classifier;

  public boolean equals(java.lang.Object);
    descriptor: (Ljava/lang/Object;)Z
    flags: (0x0001) ACC_PUBLIC
    Code:
      stack=3, locals=2, args_size=2
         0: getstatic     #23                 // Field coursier/core/Classifier$.MODULE$:Lcoursier/core/Classifier$;
         3: aload_0
         4: invokevirtual #117                // Method value:()Ljava/lang/String;
         7: aload_1
         8: invokevirtual #30                 // Method coursier/core/Classifier$.equals$extension:(Ljava/lang/String;Ljava/lang/Object;)Z
        11: ireturn
      LineNumberTable:
        line 127: 0
      LocalVariableTable:
        Start  Length  Slot  Name   Signature
            0      12     0  this   Lcoursier/core/Classifier;
            0      12     1   x$1   Ljava/lang/Object;
    MethodParameters:
      Name                           Flags
      x$1                            final

  public java.lang.String toString();
    descriptor: ()Ljava/lang/String;
    flags: (0x0001) ACC_PUBLIC
    Code:
      stack=2, locals=1, args_size=1
         0: getstatic     #23                 // Field coursier/core/Classifier$.MODULE$:Lcoursier/core/Classifier$;
         3: aload_0
         4: invokevirtual #117                // Method value:()Ljava/lang/String;
         7: invokevirtual #25                 // Method coursier/core/Classifier$.toString$extension:(Ljava/lang/String;)Ljava/lang/String;
        10: areturn
      LineNumberTable:
        line 127: 0
      LocalVariableTable:
        Start  Length  Slot  Name   Signature
            0      11     0  this   Lcoursier/core/Classifier;

  public coursier.core.Classifier(java.lang.String);
    descriptor: (Ljava/lang/String;)V
    flags: (0x0001) ACC_PUBLIC
    Code:
      stack=2, locals=2, args_size=2
         0: aload_0
         1: aload_1
         2: putfield      #113                // Field value:Ljava/lang/String;
         5: aload_0
         6: invokespecial #145                // Method java/lang/Object."<init>":()V
         9: aload_0
        10: invokestatic  #149                // InterfaceMethod scala/Product.$init$:(Lscala/Product;)V
        13: return
      LineNumberTable:
        line 127: 0
      LocalVariableTable:
        Start  Length  Slot  Name   Signature
            0      14     0  this   Lcoursier/core/Classifier;
            0      14     1 value   Ljava/lang/String;
    MethodParameters:
      Name                           Flags
      value                          final
}
SourceFile: "Definitions.scala"
RuntimeVisibleAnnotations:
  0: #10(#11=s#12)
    scala.reflect.ScalaSignature(
      bytes="\u0006\u0005\t\u001da\u0001\u0002\u00192\u0005ZB\u0001\u0002\u0014\u0001\u0003\u0016\u0004%\t!\u0014\u0005\t-\u0002\u0011\t\u0012)A\u0005\u001d\")q\u000b\u0001C\u00011\")A\f\u0001C\u0001;\")\u0011\r\u0001C\u0001;\")!\r\u0001C\u0001G\"9\u0011\u000eAA\u0001\n\u0003Q\u0007b\u00027\u0001#\u0003%\t!\u001c\u0005\bq\u0002\t\t\u0011\"\u0011z\u0011%\t\u0019\u0001AA\u0001\n\u0003\t)\u0001C\u0005\u0002\u000e\u0001\t\t\u0011\"\u0001\u0002\u0010!I\u00111\u0004\u0001\u0002\u0002\u0013\u0005\u0013Q\u0004\u0005\n\u0003W\u0001\u0011\u0011!C\u0001\u0003[A\u0011\"!\r\u0001\u0003\u0003%\t%a\r\t\u0013\u0005]\u0002!!A\u0005B\u0005e\u0002\"CA\u001e\u0001\u0005\u0005I\u0011IA\u001f\u0011%\t\t\u0005AA\u0001\n\u0003\n\u0019eB\u0004\u0002FEB\t!a\u0012\u0007\rA\n\u0004\u0012AA%\u0011\u001996\u0003\"\u0001\u0002\\!I\u0011QL\nC\u0002\u0013\r\u0011q\f\u0005\t\u0003O\u001a\u0002\u0015!\u0003\u0002b!I\u0011\u0011N\nC\u0002\u0013\u0005\u00111\u000e\u0005\b\u0003[\u001a\u0002\u0015!\u0003Z\u0011%\tyg\u0005b\u0001\n\u0003\tY\u0007C\u0004\u0002rM\u0001\u000b\u0011B-\t\u0013\u0005M4C1A\u0005\u0002\u0005-\u0004bBA;\'\u0001\u0006I!\u0017\u0005\n\u0003o\u001a\"\u0019!C\u0001\u0003WBq!!\u001f\u0014A\u0003%\u0011\fC\u0005\u0002|M\t\t\u0011\"!\u0002~!I\u0011\u0011Q\n\u0002\u0002\u0013\u0005\u00151\u0011\u0005\n\u0003\u001f\u001b\u0012\u0011!C\u0005\u0003#Cq!!\'\u0014\t\u000b\tY\nC\u0004\u0002\"N!)!a)\t\u000f\u0005\u001d6\u0003\"\u0002\u0002*\"I\u0011\u0011W\n\u0002\u0002\u0013\u0015\u00111\u0017\u0005\n\u0003w\u001b\u0012\u0013!C\u0003\u0003{C\u0011\"!1\u0014\u0003\u0003%)!a1\t\u0013\u0005\u001d7#!A\u0005\u0006\u0005%\u0007\"CAg\'\u0005\u0005IQAAh\u0011%\t9nEA\u0001\n\u000b\tI\u000eC\u0005\u0002^N\t\t\u0011\"\u0002\u0002`\"I\u0011q]\n\u0002\u0002\u0013\u0015\u0011\u0011\u001e\u0005\n\u0003c\u001c\u0012\u0011!C\u0003\u0003gD\u0011\"a>\u0014\u0003\u0003%)!!?\t\u0013\t\u00051#!A\u0005\u0006\t\r!AC\"mCN\u001c\u0018NZ5fe*\u0011!gM\u0001\u0005G>\u0014XMC\u00015\u0003!\u0019w.\u001e:tS\u0016\u00148\u0001A\n\u0005\u0001]j\u0004\t\u0005\u00029w5\t\u0011HC\u0001;\u0003\u0015\u00198-\u00197b\u0013\ta\u0014H\u0001\u0004B]f4\u0016\r\u001c\t\u0003qyJ!aP\u001d\u0003\u000fA\u0013x\u000eZ;diB\u0011\u0011)\u0013\b\u0003\u0005\u001es!a\u0011$\u000e\u0003\u0011S!!R\u001b\u0002\rq\u0012xn\u001c;?\u0013\u0005Q\u0014B\u0001%:\u0003\u001d\u0001\u0018mY6bO\u0016L!AS&\u0003\u0019M+\'/[1mSj\f\'\r\\3\u000b\u0005!K\u0014!\u0002<bYV,W#\u0001(\u0011\u0005=\u001bfB\u0001)R!\t\u0019\u0015(\u0003\u0002Ss\u00051\u0001K]3eK\u001aL!\u0001V+\u0003\rM#(/\u001b8h\u0015\t\u0011\u0016(\u0001\u0004wC2,X\rI\u0001\u0007y%t\u0017\u000e\u001e \u0015\u0005e[\u0006C\u0001.\u0001\u001b\u0005\t\u0004\"\u0002\'\u0004\u0001\u0004q\u0015aB5t\u000b6\u0004H/_\u000b\u0002=B\u0011\u0001hX\u0005\u0003Af\u0012qAQ8pY\u0016\fg.\u0001\u0005o_:,U\u000e\u001d;z\u0003\ri\u0017\r\u001d\u000b\u00033\u0012DQ!\u001a\u0004A\u0002\u0019\f\u0011A\u001a\t\u0005q\u001dte*\u0003\u0002is\tIa)\u001e8di&|g.M\u0001\u0005G>\u0004\u0018\u0010\u0006\u0002ZW\"9Aj\u0002I\u0001\u0002\u0004q\u0015AD2paf$C-\u001a4bk2$H%M\u000b\u0002]*\u0012aj\\\u0016\u0002aB\u0011\u0011O^\u0007\u0002e*\u00111\u000f^\u0001\nk:\u001c\u0007.Z2lK\u0012T!!^\u001d\u0002\u0015\u0005tgn\u001c;bi&|g.\u0003\u0002xe\n\tRO\\2iK\u000e\\W\r\u001a,be&\fgnY3\u0002\u001bA\u0014x\u000eZ;diB\u0013XMZ5y+\u0005Q\bcA>\u0002\u00025\tAP\u0003\u0002~}\u0006!A.\u00198h\u0015\u0005y\u0018\u0001\u00026bm\u0006L!\u0001\u0016?\u0002\u0019A\u0014x\u000eZ;di\u0006\u0013\u0018\u000e^=\u0016\u0005\u0005\u001d\u0001c\u0001\u001d\u0002\n%\u0019\u00111B\u001d\u0003\u0007%sG/\u0001\bqe>$Wo\u0019;FY\u0016lWM\u001c;\u0015\t\u0005E\u0011q\u0003\t\u0004q\u0005M\u0011bAA\u000bs\t\u0019\u0011I\\=\t\u0013\u0005e1\"!AA\u0002\u0005\u001d\u0011a\u0001=%c\u0005y\u0001O]8ek\u000e$\u0018\n^3sCR|\'/\u0006\u0002\u0002 A1\u0011\u0011EA\u0014\u0003#i!!a\t\u000b\u0007\u0005\u0015\u0012(\u0001\u0006d_2dWm\u0019;j_:LA!!\u000b\u0002$\tA\u0011\n^3sCR|\'/\u0001\u0005dC:,\u0015/^1m)\rq\u0016q\u0006\u0005\n\u00033i\u0011\u0011!a\u0001\u0003#\t!\u0003\u001d:pIV\u001cG/\u00127f[\u0016tGOT1nKR\u0019!0!\u000e\t\u0013\u0005ea\"!AA\u0002\u0005\u001d\u0011\u0001\u00035bg\"\u001cu\u000eZ3\u0015\u0005\u0005\u001d\u0011AB3rk\u0006d7\u000fF\u0002_\u0003\u007fA\u0011\"!\u0007\u0011\u0003\u0003\u0005\r!!\u0005\u0002\u0011Q|7\u000b\u001e:j]\u001e$\u0012A_\u0001\u000b\u00072\f7o]5gS\u0016\u0014\bC\u0001.\u0014\'\u0015\u0019\u00121JA)!\rA\u0014QJ\u0005\u0004\u0003\u001fJ$AB!osJ+g\r\u0005\u0003\u0002T\u0005eSBAA+\u0015\r\t9F`\u0001\u0003S>L1ASA+)\t\t9%\u0001\u0005pe\u0012,\'/\u001b8h+\t\t\t\u0007\u0005\u0003B\u0003GJ\u0016bAA3\u0017\nAqJ\u001d3fe&tw-A\u0005pe\u0012,\'/\u001b8hA\u0005)Q-\u001c9usV\t\u0011,\u0001\u0004f[B$\u0018\u0010I\u0001\u0006i\u0016\u001cHo]\u0001\u0007i\u0016\u001cHo\u001d\u0011\u0002\u000f)\fg/\u00193pG\u0006A!.\u0019<bI>\u001c\u0007%A\u0004t_V\u00148-Z:\u0002\u0011M|WO]2fg\u0002\nQ!\u00199qYf$2!WA@\u0011\u0015au\u00041\u0001O\u0003\u001d)h.\u00199qYf$B!!\"\u0002\fB!\u0001(a\"O\u0013\r\tI)\u000f\u0002\u0007\u001fB$\u0018n\u001c8\t\u0011\u00055\u0005%!AA\u0002e\u000b1\u0001\u001f\u00131\u000319(/\u001b;f%\u0016\u0004H.Y2f)\t\t\u0019\nE\u0002|\u0003+K1!a&}\u0005\u0019y%M[3di\u0006\t\u0012n]#naRLH%\u001a=uK:\u001c\u0018n\u001c8\u0015\u0007y\u000bi\n\u0003\u0004\u0002 \n\u0002\r!W\u0001\u0006IQD\u0017n]\u0001\u0013]>tW)\u001c9us\u0012*\u0007\u0010^3og&|g\u000eF\u0002_\u0003KCa!a($\u0001\u0004I\u0016!D7ba\u0012*\u0007\u0010^3og&|g\u000e\u0006\u0003\u0002,\u0006=FcA-\u0002.\")Q\r\na\u0001M\"1\u0011q\u0014\u0013A\u0002e\u000babY8qs\u0012*\u0007\u0010^3og&|g\u000e\u0006\u0003\u00026\u0006eFcA-\u00028\"9A*\nI\u0001\u0002\u0004q\u0005BBAPK\u0001\u0007\u0011,\u0001\rd_BLH\u0005Z3gCVdG\u000fJ\u0019%Kb$XM\\:j_:$2A\\A`\u0011\u0019\tyJ\na\u00013\u00069\u0002O]8ek\u000e$\bK]3gSb$S\r\u001f;f]NLwN\u001c\u000b\u0004u\u0006\u0015\u0007BBAPO\u0001\u0007\u0011,\u0001\fqe>$Wo\u0019;Be&$\u0018\u0010J3yi\u0016t7/[8o)\u0011\t9!a3\t\r\u0005}\u0005\u00061\u0001Z\u0003a\u0001(o\u001c3vGR,E.Z7f]R$S\r\u001f;f]NLwN\u001c\u000b\u0005\u0003#\f)\u000e\u0006\u0003\u0002\u0012\u0005M\u0007\"CA\rS\u0005\u0005\t\u0019AA\u0004\u0011\u0019\ty*\u000ba\u00013\u0006I\u0002O]8ek\u000e$\u0018\n^3sCR|\'\u000fJ3yi\u0016t7/[8o)\u0011\ty\"a7\t\r\u0005}%\u00061\u0001Z\u0003I\u0019\u0017M\\#rk\u0006dG%\u001a=uK:\u001c\u0018n\u001c8\u0015\t\u0005\u0005\u0018Q\u001d\u000b\u0004=\u0006\r\b\"CA\rW\u0005\u0005\t\u0019AA\t\u0011\u0019\tyj\u000ba\u00013\u0006a\u0002O]8ek\u000e$X\t\\3nK:$h*Y7fI\u0015DH/\u001a8tS>tG\u0003BAv\u0003_$2A_Aw\u0011%\tI\u0002LA\u0001\u0002\u0004\t9\u0001\u0003\u0004\u0002 2\u0002\r!W\u0001\u0013Q\u0006\u001c\bnQ8eK\u0012*\u0007\u0010^3og&|g\u000e\u0006\u0003\u0002:\u0005U\bBBAP[\u0001\u0007\u0011,\u0001\tfcV\fGn\u001d\u0013fqR,gn]5p]R!\u00111`A\u0000)\rq\u0016Q \u0005\n\u00033q\u0013\u0011!a\u0001\u0003#Aa!a(/\u0001\u0004I\u0016A\u0005;p\'R\u0014\u0018N\\4%Kb$XM\\:j_:$B!a\u0011\u0003\u0006!1\u0011qT\u0018A\u0002e\u0003"
    )
  ScalaInlineInfo: length = 0x59 (unknown attribute)
   01 01 00 11 00 8D 00 8E 01 00 85 00 86 01 00 7B
   00 10 01 00 7C 00 56 01 00 8B 00 86 01 00 8A 00
   7F 01 00 72 00 73 01 00 77 00 78 01 00 76 00 73
   01 00 7E 00 7F 01 00 80 00 81 01 00 88 00 89 01
   00 67 00 68 01 00 83 00 68 01 00 7D 00 56 01 00
   8C 00 56 01 00 0D 00 56 01
  ScalaSig: length = 0x3 (unknown attribute)
   05 02 00
