Classfile /Users/mw/Projects/slang-braindump/.jar/jar11/assemble/slang-braindump/assemble/content/coursier/core/Configuration.class
  Last modified May 29, 2022; size 8505 bytes
  SHA-256 checksum 9300e52d58c392d368d75a4d49446ffe18b06b2df8182129968325ec2f5563d7
  Compiled from "Definitions.scala"
public final class coursier.core.Configuration implements scala.Product,java.io.Serializable
  minor version: 0
  major version: 52
  flags: (0x0031) ACC_PUBLIC, ACC_FINAL, ACC_SUPER
  this_class: #2                          // coursier/core/Configuration
  super_class: #4                         // java/lang/Object
  interfaces: 2, fields: 1, methods: 47, attributes: 4
Constant pool:
    #1 = Utf8               coursier/core/Configuration
    #2 = Class              #1            // coursier/core/Configuration
    #3 = Utf8               java/lang/Object
    #4 = Class              #3            // java/lang/Object
    #5 = Utf8               scala/Product
    #6 = Class              #5            // scala/Product
    #7 = Utf8               java/io/Serializable
    #8 = Class              #7            // java/io/Serializable
    #9 = Utf8               Definitions.scala
   #10 = Utf8               Lscala/reflect/ScalaSignature;
   #11 = Utf8               bytes
   #12 = Utf8               \u0006\u0005\tuc\u0001B A\u0005\u0016C\u0001b\u0017\u0001\u0003\u0016\u0004%\t\u0001\u0018\u0005\tK\u0002\u0011\t\u0012)A\u0005;\")a\r\u0001C\u0001O\")1\u000e\u0001C\u0001Y\")\u0001\u000f\u0001C\u0001Y\")\u0011\u000f\u0001C\u0001e\")Q\u000f\u0001C\u0001m\"9A\u0010AA\u0001\n\u0003i\b\u0002C@\u0001#\u0003%\t!!\u0001\t\u0013\u0005]\u0001!!A\u0005B\u0005e\u0001\"CA\u0015\u0001\u0005\u0005I\u0011AA\u0016\u0011%\t\u0019\u0004AA\u0001\n\u0003\t)\u0004C\u0005\u0002B\u0001\t\t\u0011\"\u0011\u0002D!I\u0011\u0011\u000b\u0001\u0002\u0002\u0013\u0005\u00111\u000b\u0005\n\u0003/\u0002\u0011\u0011!C!\u00033B\u0011\"!\u0018\u0001\u0003\u0003%\t%a\u0018\t\u0013\u0005\u0005\u0004!!A\u0005B\u0005\r\u0004\"CA4\u0001\u0005\u0005I\u0011IA5\u000f\u001d\tY\u0007\u0011E\u0001\u0003[2aa\u0010!\t\u0002\u0005=\u0004B\u00024\u0015\t\u0003\t\t\tC\u0005\u0002\u0004R\u0011\r\u0011b\u0001\u0002\u0006\"A\u0011Q\u0012\u000b!\u0002\u0013\t9\tC\u0005\u0002\u0010R\u0011\r\u0011\"\u0001\u0002\u0012\"9\u00111\u0013\u000b!\u0002\u0013A\u0007\"CAK)\t\u0007I\u0011AAI\u0011\u001d\t9\n\u0006Q\u0001\n!D\u0011\"!\'\u0015\u0005\u0004%\t!!%\t\u000f\u0005mE\u0003)A\u0005Q\"I\u0011Q\u0014\u000bC\u0002\u0013\u0005\u0011\u0011\u0013\u0005\b\u0003?#\u0002\u0015!\u0003i\u0011%\t\t\u000b\u0006b\u0001\n\u0003\t\t\nC\u0004\u0002$R\u0001\u000b\u0011\u00025\t\u0013\u0005\u0015FC1A\u0005\u0002\u0005E\u0005bBAT)\u0001\u0006I\u0001\u001b\u0005\n\u0003S#\"\u0019!C\u0001\u0003#Cq!a+\u0015A\u0003%\u0001\u000eC\u0005\u0002.R\u0011\r\u0011\"\u0001\u0002\u0012\"9\u0011q\u0016\u000b!\u0002\u0013A\u0007\"CAY)\t\u0007I\u0011AAI\u0011\u001d\t\u0019\f\u0006Q\u0001\n!D\u0011\"!.\u0015\u0005\u0004%\t!!%\t\u000f\u0005]F\u0003)A\u0005Q\"9\u0011\u0011\u0018\u000b\u0005\u0002\u0005m\u0006\"CAd)\u0005\u0005I\u0011QAe\u0011%\ti\rFA\u0001\n\u0003\u000by\rC\u0005\u0002\\R\t\t\u0011\"\u0003\u0002^\"9\u0011Q\u001d\u000b\u0005\u0006\u0005\u001d\bbBAw)\u0011\u0015\u0011q\u001e\u0005\b\u0003g$BQAA{\u0011\u001d\ti\u0010\u0006C\u0003\u0003\u007fD\u0011Ba\u0002\u0015\u0003\u0003%)A!\u0003\t\u0013\tEA#%A\u0005\u0006\tM\u0001\"\u0003B\f)\u0005\u0005IQ\u0001B\r\u0011%\u0011i\u0002FA\u0001\n\u000b\u0011y\u0002C\u0005\u0003$Q\t\t\u0011\"\u0002\u0003&!I!Q\u0006\u000b\u0002\u0002\u0013\u0015!q\u0006\u0005\n\u0005g!\u0012\u0011!C\u0003\u0005kA\u0011B!\u0010\u0015\u0003\u0003%)Aa\u0010\t\u0013\t\u001dC#!A\u0005\u0006\t%\u0003\"\u0003B\')\u0005\u0005IQ\u0001B(\u0011%\u00119\u0006FA\u0001\n\u000b\u0011IFA\u0007D_:4\u0017nZ;sCRLwN\u001c\u0006\u0003\u0003\n\u000bAaY8sK*\t1)\u0001\u0005d_V\u00148/[3s\u0007\u0001\u0019B\u0001\u0001$M\u001fB\u0011qIS\u0007\u0002\u0011*\t\u0011*A\u0003tG\u0006d\u0017-\u0003\u0002L\u0011\n1\u0011I\\=WC2\u0004\"aR\'\n\u00059C%a\u0002)s_\u0012,8\r\u001e\t\u0003!bs!!\u0015,\u000f\u0005I+V\"A*\u000b\u0005Q#\u0015A\u0002\u001fs_>$h(C\u0001J\u0013\t9\u0006*A\u0004qC\u000e\\\u0017mZ3\n\u0005eS&\u0001D*fe&\fG.\u001b>bE2,\'BA,I\u0003\u00151\u0018\r\\;f+\u0005i\u0006C\u00010c\u001d\ty\u0006\r\u0005\u0002S\u0011&\u0011\u0011\rS\u0001\u0007!J,G-\u001a4\n\u0005\r$\'AB*ue&twM\u0003\u0002b\u0011\u00061a/\u00197vK\u0002\na\u0001P5oSRtDC\u00015k!\tI\u0007!D\u0001A\u0011\u0015Y6\u00011\u0001^\u0003\u001dI7/R7qif,\u0012!\u001c\t\u0003\u000f:L!a\u001c%\u0003\u000f\t{w\u000e\\3b]\u0006Aan\u001c8F[B$\u00180\u0001\u000b%[&tWo\u001d\u0013nS:,8\u000fJ4sK\u0006$XM\u001d\u000b\u0003QNDQ\u0001\u001e\u0004A\u0002!\fa\u0001^1sO\u0016$\u0018aA7baR\u0011\u0001n\u001e\u0005\u0006q\u001e\u0001\r!_\u0001\u0002MB!qI_/^\u0013\tY\bJA\u0005Gk:\u001cG/[8oc\u0005!1m\u001c9z)\tAg\u0010C\u0004\\\u0011A\u0005\t\u0019A/\u0002\u001d\r|\u0007/\u001f\u0013eK\u001a\fW\u000f\u001c;%cU\u0011\u00111\u0001\u0016\u0004;\u0006\u00151FAA\u0004!\u0011\tI!a\u0005\u000e\u0005\u0005-!\u0002BA\u0007\u0003\u001f\t\u0011\"\u001e8dQ\u0016\u001c7.\u001a3\u000b\u0007\u0005E\u0001*\u0001\u0006b]:|G/\u0019;j_:LA!!\u0006\u0002\f\t\tRO\\2iK\u000e\\W\r\u001a,be&\fgnY3\u0002\u001bA\u0014x\u000eZ;diB\u0013XMZ5y+\t\tY\u0002\u0005\u0003\u0002\u001e\u0005\u001dRBAA\u0010\u0015\u0011\t\t#a\t\u0002\t1\fgn\u001a\u0006\u0003\u0003K\tAA[1wC&\u00191-a\b\u0002\u0019A\u0014x\u000eZ;di\u0006\u0013\u0018\u000e^=\u0016\u0005\u00055\u0002cA$\u00020%\u0019\u0011\u0011\u0007%\u0003\u0007%sG/\u0001\bqe>$Wo\u0019;FY\u0016lWM\u001c;\u0015\t\u0005]\u0012Q\b\t\u0004\u000f\u0006e\u0012bAA\u001e\u0011\n\u0019\u0011I\\=\t\u0013\u0005}B\"!AA\u0002\u00055\u0012a\u0001=%c\u0005y\u0001O]8ek\u000e$\u0018\n^3sCR|\'/\u0006\u0002\u0002FA1\u0011qIA\'\u0003oi!!!\u0013\u000b\u0007\u0005-\u0003*\u0001\u0006d_2dWm\u0019;j_:LA!a\u0014\u0002J\tA\u0011\n^3sCR|\'/\u0001\u0005dC:,\u0015/^1m)\ri\u0017Q\u000b\u0005\n\u0003\u007fq\u0011\u0011!a\u0001\u0003o\t!\u0003\u001d:pIV\u001cG/\u00127f[\u0016tGOT1nKR!\u00111DA.\u0011%\tydDA\u0001\u0002\u0004\ti#\u0001\u0005iCND7i\u001c3f)\t\ti#\u0001\u0004fcV\fGn\u001d\u000b\u0004[\u0006\u0015\u0004\"CA #\u0005\u0005\t\u0019AA\u001c\u0003!!xn\u0015;sS:<GCAA\u000e\u00035\u0019uN\u001c4jOV\u0014\u0018\r^5p]B\u0011\u0011\u000eF\n\u0006)\u0005E\u0014q\u000f\t\u0004\u000f\u0006M\u0014bAA;\u0011\n1\u0011I\\=SK\u001a\u0004B!!\u001f\u0002\u00005\u0011\u00111\u0010\u0006\u0005\u0003{\n\u0019#\u0001\u0002j_&\u0019\u0011,a\u001f\u0015\u0005\u00055\u0014\u0001C8sI\u0016\u0014\u0018N\\4\u0016\u0005\u0005\u001d\u0005\u0003\u0002)\u0002\n\"L1!a#[\u0005!y%\u000fZ3sS:<\u0017!C8sI\u0016\u0014\u0018N\\4!\u0003\u0015)W\u000e\u001d;z+\u0005A\u0017AB3naRL\b%A\u0004d_6\u0004\u0018\u000e\\3\u0002\u0011\r|W\u000e]5mK\u0002\nqA];oi&lW-\u0001\u0005sk:$\u0018.\\3!\u0003\u0011!Xm\u001d;\u0002\u000bQ,7\u000f\u001e\u0011\u0002\u000f\u0011,g-Y;mi\u0006AA-\u001a4bk2$\b%\u0001\beK\u001a\fW\u000f\u001c;D_6\u0004\u0018\u000e\\3\u0002\u001f\u0011,g-Y;mi\u000e{W\u000e]5mK\u0002\n\u0001\u0002\u001d:pm&$W\rZ\u0001\naJ|g/\u001b3fI\u0002\na![7q_J$\u0018aB5na>\u0014H\u000fI\u0001\t_B$\u0018n\u001c8bY\u0006Iq\u000e\u001d;j_:\fG\u000eI\u0001\u0004C2d\u0017\u0001B1mY\u0002\nAA[8j]R\u0019\u0001.!0\t\u000f\u0005}F\u00061\u0001\u0002B\u0006)1m\u001c8ggB!q)a1i\u0013\r\t)\r\u0013\u0002\u000byI,\u0007/Z1uK\u0012t\u0014!B1qa2LHc\u00015\u0002L\")1,\fa\u0001;\u00069QO\\1qa2LH\u0003BAi\u0003/\u0004BaRAj;&\u0019\u0011Q\u001b%\u0003\r=\u0003H/[8o\u0011!\tINLA\u0001\u0002\u0004A\u0017a\u0001=%a\u0005aqO]5uKJ+\u0007\u000f\\1dKR\u0011\u0011q\u001c\t\u0005\u0003;\t\t/\u0003\u0003\u0002d\u0006}!AB(cU\u0016\u001cG/A\tjg\u0016k\u0007\u000f^=%Kb$XM\\:j_:$2!\\Au\u0011\u0019\tY\u000f\ra\u0001Q\u0006)A\u0005\u001e5jg\u0006\u0011bn\u001c8F[B$\u0018\u0010J3yi\u0016t7/[8o)\ri\u0017\u0011\u001f\u0005\u0007\u0003W\f\u0004\u0019\u00015\u0002=\u0011j\u0017N\\;tI5Lg.^:%OJ,\u0017\r^3sI\u0015DH/\u001a8tS>tG\u0003BA|\u0003w$2\u0001[A}\u0011\u0015!(\u00071\u0001i\u0011\u0019\tYO\ra\u0001Q\u0006iQ.\u00199%Kb$XM\\:j_:$BA!\u0001\u0003\u0006Q\u0019\u0001Na\u0001\t\u000ba\u001c\u0004\u0019A=\t\r\u0005-8\u00071\u0001i\u00039\u0019w\u000e]=%Kb$XM\\:j_:$BAa\u0003\u0003\u0010Q\u0019\u0001N!\u0004\t\u000fm#\u0004\u0013!a\u0001;\"1\u00111\u001e\u001bA\u0002!\f\u0001dY8qs\u0012\"WMZ1vYR$\u0013\u0007J3yi\u0016t7/[8o)\u0011\t\u0019A!\u0006\t\r\u0005-X\u00071\u0001i\u0003]\u0001(o\u001c3vGR\u0004&/\u001a4jq\u0012*\u0007\u0010^3og&|g\u000e\u0006\u0003\u0002\u001c\tm\u0001BBAvm\u0001\u0007\u0001.\u0001\fqe>$Wo\u0019;Be&$\u0018\u0010J3yi\u0016t7/[8o)\u0011\tiC!\t\t\r\u0005-x\u00071\u0001i\u0003a\u0001(o\u001c3vGR,E.Z7f]R$S\r\u001f;f]NLwN\u001c\u000b\u0005\u0005O\u0011Y\u0003\u0006\u0003\u00028\t%\u0002\"CA q\u0005\u0005\t\u0019AA\u0017\u0011\u0019\tY\u000f\u000fa\u0001Q\u0006I\u0002O]8ek\u000e$\u0018\n^3sCR|\'\u000fJ3yi\u0016t7/[8o)\u0011\t)E!\r\t\r\u0005-\u0018\b1\u0001i\u0003I\u0019\u0017M\\#rk\u0006dG%\u001a=uK:\u001c\u0018n\u001c8\u0015\t\t]\"1\b\u000b\u0004[\ne\u0002\"CA u\u0005\u0005\t\u0019AA\u001c\u0011\u0019\tYO\u000fa\u0001Q\u0006a\u0002O]8ek\u000e$X\t\\3nK:$h*Y7fI\u0015DH/\u001a8tS>tG\u0003\u0002B!\u0005\u000b\"B!a\u0007\u0003D!I\u0011qH\u001e\u0002\u0002\u0003\u0007\u0011Q\u0006\u0005\u0007\u0003W\\\u0004\u0019\u00015\u0002%!\f7\u000f[\"pI\u0016$S\r\u001f;f]NLwN\u001c\u000b\u0005\u0003?\u0012Y\u0005\u0003\u0004\u0002lr\u0002\r\u0001[\u0001\u0011KF,\u0018\r\\:%Kb$XM\\:j_:$BA!\u0015\u0003VQ\u0019QNa\u0015\t\u0013\u0005}R(!AA\u0002\u0005]\u0002BBAv{\u0001\u0007\u0001.\u0001\nu_N#(/\u001b8hI\u0015DH/\u001a8tS>tG\u0003BA5\u00057Ba!a;?\u0001\u0004A\u0007
   #13 = Utf8               value
   #14 = Utf8               Ljava/lang/String;
   #15 = Utf8               toString$extension
   #16 = Utf8               (Ljava/lang/String;)Ljava/lang/String;
   #17 = Utf8               $this
   #18 = Utf8               coursier/core/Configuration$
   #19 = Class              #18           // coursier/core/Configuration$
   #20 = Utf8               MODULE$
   #21 = Utf8               Lcoursier/core/Configuration$;
   #22 = NameAndType        #20:#21       // MODULE$:Lcoursier/core/Configuration$;
   #23 = Fieldref           #19.#22       // coursier/core/Configuration$.MODULE$:Lcoursier/core/Configuration$;
   #24 = NameAndType        #15:#16       // toString$extension:(Ljava/lang/String;)Ljava/lang/String;
   #25 = Methodref          #19.#24       // coursier/core/Configuration$.toString$extension:(Ljava/lang/String;)Ljava/lang/String;
   #26 = Utf8               equals$extension
   #27 = Utf8               (Ljava/lang/String;Ljava/lang/Object;)Z
   #28 = Utf8               x$1
   #29 = NameAndType        #26:#27       // equals$extension:(Ljava/lang/String;Ljava/lang/Object;)Z
   #30 = Methodref          #19.#29       // coursier/core/Configuration$.equals$extension:(Ljava/lang/String;Ljava/lang/Object;)Z
   #31 = Utf8               hashCode$extension
   #32 = Utf8               (Ljava/lang/String;)I
   #33 = NameAndType        #31:#32       // hashCode$extension:(Ljava/lang/String;)I
   #34 = Methodref          #19.#33       // coursier/core/Configuration$.hashCode$extension:(Ljava/lang/String;)I
   #35 = Utf8               productElementName$extension
   #36 = Utf8               (Ljava/lang/String;I)Ljava/lang/String;
   #37 = NameAndType        #35:#36       // productElementName$extension:(Ljava/lang/String;I)Ljava/lang/String;
   #38 = Methodref          #19.#37       // coursier/core/Configuration$.productElementName$extension:(Ljava/lang/String;I)Ljava/lang/String;
   #39 = Utf8               canEqual$extension
   #40 = NameAndType        #39:#27       // canEqual$extension:(Ljava/lang/String;Ljava/lang/Object;)Z
   #41 = Methodref          #19.#40       // coursier/core/Configuration$.canEqual$extension:(Ljava/lang/String;Ljava/lang/Object;)Z
   #42 = Utf8               productIterator$extension
   #43 = Utf8               (Ljava/lang/String;)Lscala/collection/Iterator;
   #44 = Utf8               (Ljava/lang/String;)Lscala/collection/Iterator<Ljava/lang/Object;>;
   #45 = NameAndType        #42:#43       // productIterator$extension:(Ljava/lang/String;)Lscala/collection/Iterator;
   #46 = Methodref          #19.#45       // coursier/core/Configuration$.productIterator$extension:(Ljava/lang/String;)Lscala/collection/Iterator;
   #47 = Utf8               productElement$extension
   #48 = Utf8               (Ljava/lang/String;I)Ljava/lang/Object;
   #49 = NameAndType        #47:#48       // productElement$extension:(Ljava/lang/String;I)Ljava/lang/Object;
   #50 = Methodref          #19.#49       // coursier/core/Configuration$.productElement$extension:(Ljava/lang/String;I)Ljava/lang/Object;
   #51 = Utf8               productArity$extension
   #52 = NameAndType        #51:#32       // productArity$extension:(Ljava/lang/String;)I
   #53 = Methodref          #19.#52       // coursier/core/Configuration$.productArity$extension:(Ljava/lang/String;)I
   #54 = Utf8               productPrefix$extension
   #55 = NameAndType        #54:#16       // productPrefix$extension:(Ljava/lang/String;)Ljava/lang/String;
   #56 = Methodref          #19.#55       // coursier/core/Configuration$.productPrefix$extension:(Ljava/lang/String;)Ljava/lang/String;
   #57 = Utf8               copy$default$1$extension
   #58 = NameAndType        #57:#16       // copy$default$1$extension:(Ljava/lang/String;)Ljava/lang/String;
   #59 = Methodref          #19.#58       // coursier/core/Configuration$.copy$default$1$extension:(Ljava/lang/String;)Ljava/lang/String;
   #60 = Utf8               copy$extension
   #61 = Utf8               (Ljava/lang/String;Ljava/lang/String;)Ljava/lang/String;
   #62 = NameAndType        #60:#61       // copy$extension:(Ljava/lang/String;Ljava/lang/String;)Ljava/lang/String;
   #63 = Methodref          #19.#62       // coursier/core/Configuration$.copy$extension:(Ljava/lang/String;Ljava/lang/String;)Ljava/lang/String;
   #64 = Utf8               map$extension
   #65 = Utf8               (Ljava/lang/String;Lscala/Function1;)Ljava/lang/String;
   #66 = Utf8               f
   #67 = NameAndType        #64:#65       // map$extension:(Ljava/lang/String;Lscala/Function1;)Ljava/lang/String;
   #68 = Methodref          #19.#67       // coursier/core/Configuration$.map$extension:(Ljava/lang/String;Lscala/Function1;)Ljava/lang/String;
   #69 = Utf8               $minus$minus$greater$extension
   #70 = Utf8               target
   #71 = NameAndType        #69:#61       // $minus$minus$greater$extension:(Ljava/lang/String;Ljava/lang/String;)Ljava/lang/String;
   #72 = Methodref          #19.#71       // coursier/core/Configuration$.$minus$minus$greater$extension:(Ljava/lang/String;Ljava/lang/String;)Ljava/lang/String;
   #73 = Utf8               nonEmpty$extension
   #74 = Utf8               (Ljava/lang/String;)Z
   #75 = NameAndType        #73:#74       // nonEmpty$extension:(Ljava/lang/String;)Z
   #76 = Methodref          #19.#75       // coursier/core/Configuration$.nonEmpty$extension:(Ljava/lang/String;)Z
   #77 = Utf8               isEmpty$extension
   #78 = NameAndType        #77:#74       // isEmpty$extension:(Ljava/lang/String;)Z
   #79 = Methodref          #19.#78       // coursier/core/Configuration$.isEmpty$extension:(Ljava/lang/String;)Z
   #80 = Utf8               unapply
   #81 = Utf8               (Ljava/lang/String;)Lscala/Option;
   #82 = Utf8               (Ljava/lang/String;)Lscala/Option<Ljava/lang/String;>;
   #83 = Utf8               x$0
   #84 = NameAndType        #80:#81       // unapply:(Ljava/lang/String;)Lscala/Option;
   #85 = Methodref          #19.#84       // coursier/core/Configuration$.unapply:(Ljava/lang/String;)Lscala/Option;
   #86 = Utf8               apply
   #87 = NameAndType        #86:#16       // apply:(Ljava/lang/String;)Ljava/lang/String;
   #88 = Methodref          #19.#87       // coursier/core/Configuration$.apply:(Ljava/lang/String;)Ljava/lang/String;
   #89 = Utf8               join
   #90 = Utf8               (Lscala/collection/immutable/Seq;)Ljava/lang/String;
   #91 = Utf8               confs
   #92 = NameAndType        #89:#90       // join:(Lscala/collection/immutable/Seq;)Ljava/lang/String;
   #93 = Methodref          #19.#92       // coursier/core/Configuration$.join:(Lscala/collection/immutable/Seq;)Ljava/lang/String;
   #94 = Utf8               all
   #95 = Utf8               ()Ljava/lang/String;
   #96 = NameAndType        #94:#95       // all:()Ljava/lang/String;
   #97 = Methodref          #19.#96       // coursier/core/Configuration$.all:()Ljava/lang/String;
   #98 = Utf8               optional
   #99 = NameAndType        #98:#95       // optional:()Ljava/lang/String;
  #100 = Methodref          #19.#99       // coursier/core/Configuration$.optional:()Ljava/lang/String;
  #101 = Utf8               import
  #102 = NameAndType        #101:#95      // import:()Ljava/lang/String;
  #103 = Methodref          #19.#102      // coursier/core/Configuration$.import:()Ljava/lang/String;
  #104 = Utf8               provided
  #105 = NameAndType        #104:#95      // provided:()Ljava/lang/String;
  #106 = Methodref          #19.#105      // coursier/core/Configuration$.provided:()Ljava/lang/String;
  #107 = Utf8               defaultCompile
  #108 = NameAndType        #107:#95      // defaultCompile:()Ljava/lang/String;
  #109 = Methodref          #19.#108      // coursier/core/Configuration$.defaultCompile:()Ljava/lang/String;
  #110 = Utf8               default
  #111 = NameAndType        #110:#95      // default:()Ljava/lang/String;
  #112 = Methodref          #19.#111      // coursier/core/Configuration$.default:()Ljava/lang/String;
  #113 = Utf8               test
  #114 = NameAndType        #113:#95      // test:()Ljava/lang/String;
  #115 = Methodref          #19.#114      // coursier/core/Configuration$.test:()Ljava/lang/String;
  #116 = Utf8               runtime
  #117 = NameAndType        #116:#95      // runtime:()Ljava/lang/String;
  #118 = Methodref          #19.#117      // coursier/core/Configuration$.runtime:()Ljava/lang/String;
  #119 = Utf8               compile
  #120 = NameAndType        #119:#95      // compile:()Ljava/lang/String;
  #121 = Methodref          #19.#120      // coursier/core/Configuration$.compile:()Ljava/lang/String;
  #122 = Utf8               empty
  #123 = NameAndType        #122:#95      // empty:()Ljava/lang/String;
  #124 = Methodref          #19.#123      // coursier/core/Configuration$.empty:()Ljava/lang/String;
  #125 = Utf8               ordering
  #126 = Utf8               ()Lscala/math/Ordering;
  #127 = Utf8               ()Lscala/math/Ordering<Lcoursier/core/Configuration;>;
  #128 = NameAndType        #125:#126     // ordering:()Lscala/math/Ordering;
  #129 = Methodref          #19.#128      // coursier/core/Configuration$.ordering:()Lscala/math/Ordering;
  #130 = Utf8               productElementNames
  #131 = Utf8               ()Lscala/collection/Iterator;
  #132 = Utf8               ()Lscala/collection/Iterator<Ljava/lang/String;>;
  #133 = Utf8               productElementNames$
  #134 = Utf8               (Lscala/Product;)Lscala/collection/Iterator;
  #135 = NameAndType        #133:#134     // productElementNames$:(Lscala/Product;)Lscala/collection/Iterator;
  #136 = InterfaceMethodref #6.#135       // scala/Product.productElementNames$:(Lscala/Product;)Lscala/collection/Iterator;
  #137 = Utf8               this
  #138 = Utf8               Lcoursier/core/Configuration;
  #139 = NameAndType        #13:#14       // value:Ljava/lang/String;
  #140 = Fieldref           #2.#139       // coursier/core/Configuration.value:Ljava/lang/String;
  #141 = Utf8               isEmpty
  #142 = Utf8               ()Z
  #143 = NameAndType        #13:#95       // value:()Ljava/lang/String;
  #144 = Methodref          #2.#143       // coursier/core/Configuration.value:()Ljava/lang/String;
  #145 = Utf8               nonEmpty
  #146 = Utf8               $minus$minus$greater
  #147 = Utf8               map
  #148 = Utf8               (Lscala/Function1;)Ljava/lang/String;
  #149 = Utf8               (Lscala/Function1<Ljava/lang/String;Ljava/lang/String;>;)Ljava/lang/String;
  #150 = Utf8               Lscala/Function1;
  #151 = Utf8               copy
  #152 = Utf8               copy$default$1
  #153 = Utf8               productPrefix
  #154 = Utf8               productArity
  #155 = Utf8               ()I
  #156 = Utf8               productElement
  #157 = Utf8               (I)Ljava/lang/Object;
  #158 = Utf8               I
  #159 = Utf8               productIterator
  #160 = Utf8               ()Lscala/collection/Iterator<Ljava/lang/Object;>;
  #161 = Utf8               canEqual
  #162 = Utf8               (Ljava/lang/Object;)Z
  #163 = Utf8               Ljava/lang/Object;
  #164 = Utf8               productElementName
  #165 = Utf8               (I)Ljava/lang/String;
  #166 = Utf8               hashCode
  #167 = Utf8               equals
  #168 = Utf8               toString
  #169 = Utf8               <init>
  #170 = Utf8               (Ljava/lang/String;)V
  #171 = Utf8               ()V
  #172 = NameAndType        #169:#171     // "<init>":()V
  #173 = Methodref          #4.#172       // java/lang/Object."<init>":()V
  #174 = Utf8               $init$
  #175 = Utf8               (Lscala/Product;)V
  #176 = NameAndType        #174:#175     // $init$:(Lscala/Product;)V
  #177 = InterfaceMethodref #6.#176       // scala/Product.$init$:(Lscala/Product;)V
  #178 = Utf8               Code
  #179 = Utf8               MethodParameters
  #180 = Utf8               Signature
  #181 = Utf8               LineNumberTable
  #182 = Utf8               LocalVariableTable
  #183 = Utf8               SourceFile
  #184 = Utf8               RuntimeVisibleAnnotations
  #185 = Utf8               ScalaInlineInfo
  #186 = Utf8               ScalaSig
{
  private final java.lang.String value;
    descriptor: Ljava/lang/String;
    flags: (0x0012) ACC_PRIVATE, ACC_FINAL

  public static java.lang.String toString$extension(java.lang.String);
    descriptor: (Ljava/lang/String;)Ljava/lang/String;
    flags: (0x0009) ACC_PUBLIC, ACC_STATIC
    Code:
      stack=2, locals=1, args_size=1
         0: getstatic     #23                 // Field coursier/core/Configuration$.MODULE$:Lcoursier/core/Configuration$;
         3: aload_0
         4: invokevirtual #25                 // Method coursier/core/Configuration$.toString$extension:(Ljava/lang/String;)Ljava/lang/String;
         7: areturn
    MethodParameters:
      Name                           Flags
      $this                          final

  public static boolean equals$extension(java.lang.String, java.lang.Object);
    descriptor: (Ljava/lang/String;Ljava/lang/Object;)Z
    flags: (0x0009) ACC_PUBLIC, ACC_STATIC
    Code:
      stack=3, locals=2, args_size=2
         0: getstatic     #23                 // Field coursier/core/Configuration$.MODULE$:Lcoursier/core/Configuration$;
         3: aload_0
         4: aload_1
         5: invokevirtual #30                 // Method coursier/core/Configuration$.equals$extension:(Ljava/lang/String;Ljava/lang/Object;)Z
         8: ireturn
    MethodParameters:
      Name                           Flags
      $this                          final
      x$1                            final

  public static int hashCode$extension(java.lang.String);
    descriptor: (Ljava/lang/String;)I
    flags: (0x0009) ACC_PUBLIC, ACC_STATIC
    Code:
      stack=2, locals=1, args_size=1
         0: getstatic     #23                 // Field coursier/core/Configuration$.MODULE$:Lcoursier/core/Configuration$;
         3: aload_0
         4: invokevirtual #34                 // Method coursier/core/Configuration$.hashCode$extension:(Ljava/lang/String;)I
         7: ireturn
    MethodParameters:
      Name                           Flags
      $this                          final

  public static java.lang.String productElementName$extension(java.lang.String, int);
    descriptor: (Ljava/lang/String;I)Ljava/lang/String;
    flags: (0x0009) ACC_PUBLIC, ACC_STATIC
    Code:
      stack=3, locals=2, args_size=2
         0: getstatic     #23                 // Field coursier/core/Configuration$.MODULE$:Lcoursier/core/Configuration$;
         3: aload_0
         4: iload_1
         5: invokevirtual #38                 // Method coursier/core/Configuration$.productElementName$extension:(Ljava/lang/String;I)Ljava/lang/String;
         8: areturn
    MethodParameters:
      Name                           Flags
      $this                          final
      x$1                            final

  public static boolean canEqual$extension(java.lang.String, java.lang.Object);
    descriptor: (Ljava/lang/String;Ljava/lang/Object;)Z
    flags: (0x0009) ACC_PUBLIC, ACC_STATIC
    Code:
      stack=3, locals=2, args_size=2
         0: getstatic     #23                 // Field coursier/core/Configuration$.MODULE$:Lcoursier/core/Configuration$;
         3: aload_0
         4: aload_1
         5: invokevirtual #41                 // Method coursier/core/Configuration$.canEqual$extension:(Ljava/lang/String;Ljava/lang/Object;)Z
         8: ireturn
    MethodParameters:
      Name                           Flags
      $this                          final
      x$1                            final

  public static scala.collection.Iterator<java.lang.Object> productIterator$extension(java.lang.String);
    descriptor: (Ljava/lang/String;)Lscala/collection/Iterator;
    flags: (0x0009) ACC_PUBLIC, ACC_STATIC
    Code:
      stack=2, locals=1, args_size=1
         0: getstatic     #23                 // Field coursier/core/Configuration$.MODULE$:Lcoursier/core/Configuration$;
         3: aload_0
         4: invokevirtual #46                 // Method coursier/core/Configuration$.productIterator$extension:(Ljava/lang/String;)Lscala/collection/Iterator;
         7: areturn
    Signature: #44                          // (Ljava/lang/String;)Lscala/collection/Iterator<Ljava/lang/Object;>;
    MethodParameters:
      Name                           Flags
      $this                          final

  public static java.lang.Object productElement$extension(java.lang.String, int);
    descriptor: (Ljava/lang/String;I)Ljava/lang/Object;
    flags: (0x0009) ACC_PUBLIC, ACC_STATIC
    Code:
      stack=3, locals=2, args_size=2
         0: getstatic     #23                 // Field coursier/core/Configuration$.MODULE$:Lcoursier/core/Configuration$;
         3: aload_0
         4: iload_1
         5: invokevirtual #50                 // Method coursier/core/Configuration$.productElement$extension:(Ljava/lang/String;I)Ljava/lang/Object;
         8: areturn
    MethodParameters:
      Name                           Flags
      $this                          final
      x$1                            final

  public static int productArity$extension(java.lang.String);
    descriptor: (Ljava/lang/String;)I
    flags: (0x0009) ACC_PUBLIC, ACC_STATIC
    Code:
      stack=2, locals=1, args_size=1
         0: getstatic     #23                 // Field coursier/core/Configuration$.MODULE$:Lcoursier/core/Configuration$;
         3: aload_0
         4: invokevirtual #53                 // Method coursier/core/Configuration$.productArity$extension:(Ljava/lang/String;)I
         7: ireturn
    MethodParameters:
      Name                           Flags
      $this                          final

  public static java.lang.String productPrefix$extension(java.lang.String);
    descriptor: (Ljava/lang/String;)Ljava/lang/String;
    flags: (0x0009) ACC_PUBLIC, ACC_STATIC
    Code:
      stack=2, locals=1, args_size=1
         0: getstatic     #23                 // Field coursier/core/Configuration$.MODULE$:Lcoursier/core/Configuration$;
         3: aload_0
         4: invokevirtual #56                 // Method coursier/core/Configuration$.productPrefix$extension:(Ljava/lang/String;)Ljava/lang/String;
         7: areturn
    MethodParameters:
      Name                           Flags
      $this                          final

  public static java.lang.String copy$default$1$extension(java.lang.String);
    descriptor: (Ljava/lang/String;)Ljava/lang/String;
    flags: (0x0009) ACC_PUBLIC, ACC_STATIC
    Code:
      stack=2, locals=1, args_size=1
         0: getstatic     #23                 // Field coursier/core/Configuration$.MODULE$:Lcoursier/core/Configuration$;
         3: aload_0
         4: invokevirtual #59                 // Method coursier/core/Configuration$.copy$default$1$extension:(Ljava/lang/String;)Ljava/lang/String;
         7: areturn
    MethodParameters:
      Name                           Flags
      $this                          final

  public static java.lang.String copy$extension(java.lang.String, java.lang.String);
    descriptor: (Ljava/lang/String;Ljava/lang/String;)Ljava/lang/String;
    flags: (0x0009) ACC_PUBLIC, ACC_STATIC
    Code:
      stack=3, locals=2, args_size=2
         0: getstatic     #23                 // Field coursier/core/Configuration$.MODULE$:Lcoursier/core/Configuration$;
         3: aload_0
         4: aload_1
         5: invokevirtual #63                 // Method coursier/core/Configuration$.copy$extension:(Ljava/lang/String;Ljava/lang/String;)Ljava/lang/String;
         8: areturn
    MethodParameters:
      Name                           Flags
      $this                          final
      value                          final

  public static java.lang.String map$extension(java.lang.String, scala.Function1);
    descriptor: (Ljava/lang/String;Lscala/Function1;)Ljava/lang/String;
    flags: (0x0009) ACC_PUBLIC, ACC_STATIC
    Code:
      stack=3, locals=2, args_size=2
         0: getstatic     #23                 // Field coursier/core/Configuration$.MODULE$:Lcoursier/core/Configuration$;
         3: aload_0
         4: aload_1
         5: invokevirtual #68                 // Method coursier/core/Configuration$.map$extension:(Ljava/lang/String;Lscala/Function1;)Ljava/lang/String;
         8: areturn
    MethodParameters:
      Name                           Flags
      $this                          final
      f                              final

  public static java.lang.String $minus$minus$greater$extension(java.lang.String, java.lang.String);
    descriptor: (Ljava/lang/String;Ljava/lang/String;)Ljava/lang/String;
    flags: (0x0009) ACC_PUBLIC, ACC_STATIC
    Code:
      stack=3, locals=2, args_size=2
         0: getstatic     #23                 // Field coursier/core/Configuration$.MODULE$:Lcoursier/core/Configuration$;
         3: aload_0
         4: aload_1
         5: invokevirtual #72                 // Method coursier/core/Configuration$.$minus$minus$greater$extension:(Ljava/lang/String;Ljava/lang/String;)Ljava/lang/String;
         8: areturn
    MethodParameters:
      Name                           Flags
      $this                          final
      target                         final

  public static boolean nonEmpty$extension(java.lang.String);
    descriptor: (Ljava/lang/String;)Z
    flags: (0x0009) ACC_PUBLIC, ACC_STATIC
    Code:
      stack=2, locals=1, args_size=1
         0: getstatic     #23                 // Field coursier/core/Configuration$.MODULE$:Lcoursier/core/Configuration$;
         3: aload_0
         4: invokevirtual #76                 // Method coursier/core/Configuration$.nonEmpty$extension:(Ljava/lang/String;)Z
         7: ireturn
    MethodParameters:
      Name                           Flags
      $this                          final

  public static boolean isEmpty$extension(java.lang.String);
    descriptor: (Ljava/lang/String;)Z
    flags: (0x0009) ACC_PUBLIC, ACC_STATIC
    Code:
      stack=2, locals=1, args_size=1
         0: getstatic     #23                 // Field coursier/core/Configuration$.MODULE$:Lcoursier/core/Configuration$;
         3: aload_0
         4: invokevirtual #79                 // Method coursier/core/Configuration$.isEmpty$extension:(Ljava/lang/String;)Z
         7: ireturn
    MethodParameters:
      Name                           Flags
      $this                          final

  public static scala.Option<java.lang.String> unapply(java.lang.String);
    descriptor: (Ljava/lang/String;)Lscala/Option;
    flags: (0x0009) ACC_PUBLIC, ACC_STATIC
    Code:
      stack=2, locals=1, args_size=1
         0: getstatic     #23                 // Field coursier/core/Configuration$.MODULE$:Lcoursier/core/Configuration$;
         3: aload_0
         4: invokevirtual #85                 // Method coursier/core/Configuration$.unapply:(Ljava/lang/String;)Lscala/Option;
         7: areturn
    Signature: #82                          // (Ljava/lang/String;)Lscala/Option<Ljava/lang/String;>;
    MethodParameters:
      Name                           Flags
      x$0                            final

  public static java.lang.String apply(java.lang.String);
    descriptor: (Ljava/lang/String;)Ljava/lang/String;
    flags: (0x0009) ACC_PUBLIC, ACC_STATIC
    Code:
      stack=2, locals=1, args_size=1
         0: getstatic     #23                 // Field coursier/core/Configuration$.MODULE$:Lcoursier/core/Configuration$;
         3: aload_0
         4: invokevirtual #88                 // Method coursier/core/Configuration$.apply:(Ljava/lang/String;)Ljava/lang/String;
         7: areturn
    MethodParameters:
      Name                           Flags
      value                          final

  public static java.lang.String join(scala.collection.immutable.Seq);
    descriptor: (Lscala/collection/immutable/Seq;)Ljava/lang/String;
    flags: (0x0009) ACC_PUBLIC, ACC_STATIC
    Code:
      stack=2, locals=1, args_size=1
         0: getstatic     #23                 // Field coursier/core/Configuration$.MODULE$:Lcoursier/core/Configuration$;
         3: aload_0
         4: invokevirtual #93                 // Method coursier/core/Configuration$.join:(Lscala/collection/immutable/Seq;)Ljava/lang/String;
         7: areturn
    MethodParameters:
      Name                           Flags
      confs                          final

  public static java.lang.String all();
    descriptor: ()Ljava/lang/String;
    flags: (0x0009) ACC_PUBLIC, ACC_STATIC
    Code:
      stack=1, locals=0, args_size=0
         0: getstatic     #23                 // Field coursier/core/Configuration$.MODULE$:Lcoursier/core/Configuration$;
         3: invokevirtual #97                 // Method coursier/core/Configuration$.all:()Ljava/lang/String;
         6: areturn

  public static java.lang.String optional();
    descriptor: ()Ljava/lang/String;
    flags: (0x0009) ACC_PUBLIC, ACC_STATIC
    Code:
      stack=1, locals=0, args_size=0
         0: getstatic     #23                 // Field coursier/core/Configuration$.MODULE$:Lcoursier/core/Configuration$;
         3: invokevirtual #100                // Method coursier/core/Configuration$.optional:()Ljava/lang/String;
         6: areturn

  public static java.lang.String import();
    descriptor: ()Ljava/lang/String;
    flags: (0x0009) ACC_PUBLIC, ACC_STATIC
    Code:
      stack=1, locals=0, args_size=0
         0: getstatic     #23                 // Field coursier/core/Configuration$.MODULE$:Lcoursier/core/Configuration$;
         3: invokevirtual #103                // Method coursier/core/Configuration$.import:()Ljava/lang/String;
         6: areturn

  public static java.lang.String provided();
    descriptor: ()Ljava/lang/String;
    flags: (0x0009) ACC_PUBLIC, ACC_STATIC
    Code:
      stack=1, locals=0, args_size=0
         0: getstatic     #23                 // Field coursier/core/Configuration$.MODULE$:Lcoursier/core/Configuration$;
         3: invokevirtual #106                // Method coursier/core/Configuration$.provided:()Ljava/lang/String;
         6: areturn

  public static java.lang.String defaultCompile();
    descriptor: ()Ljava/lang/String;
    flags: (0x0009) ACC_PUBLIC, ACC_STATIC
    Code:
      stack=1, locals=0, args_size=0
         0: getstatic     #23                 // Field coursier/core/Configuration$.MODULE$:Lcoursier/core/Configuration$;
         3: invokevirtual #109                // Method coursier/core/Configuration$.defaultCompile:()Ljava/lang/String;
         6: areturn

  public static java.lang.String default();
    descriptor: ()Ljava/lang/String;
    flags: (0x0009) ACC_PUBLIC, ACC_STATIC
    Code:
      stack=1, locals=0, args_size=0
         0: getstatic     #23                 // Field coursier/core/Configuration$.MODULE$:Lcoursier/core/Configuration$;
         3: invokevirtual #112                // Method coursier/core/Configuration$.default:()Ljava/lang/String;
         6: areturn

  public static java.lang.String test();
    descriptor: ()Ljava/lang/String;
    flags: (0x0009) ACC_PUBLIC, ACC_STATIC
    Code:
      stack=1, locals=0, args_size=0
         0: getstatic     #23                 // Field coursier/core/Configuration$.MODULE$:Lcoursier/core/Configuration$;
         3: invokevirtual #115                // Method coursier/core/Configuration$.test:()Ljava/lang/String;
         6: areturn

  public static java.lang.String runtime();
    descriptor: ()Ljava/lang/String;
    flags: (0x0009) ACC_PUBLIC, ACC_STATIC
    Code:
      stack=1, locals=0, args_size=0
         0: getstatic     #23                 // Field coursier/core/Configuration$.MODULE$:Lcoursier/core/Configuration$;
         3: invokevirtual #118                // Method coursier/core/Configuration$.runtime:()Ljava/lang/String;
         6: areturn

  public static java.lang.String compile();
    descriptor: ()Ljava/lang/String;
    flags: (0x0009) ACC_PUBLIC, ACC_STATIC
    Code:
      stack=1, locals=0, args_size=0
         0: getstatic     #23                 // Field coursier/core/Configuration$.MODULE$:Lcoursier/core/Configuration$;
         3: invokevirtual #121                // Method coursier/core/Configuration$.compile:()Ljava/lang/String;
         6: areturn

  public static java.lang.String empty();
    descriptor: ()Ljava/lang/String;
    flags: (0x0009) ACC_PUBLIC, ACC_STATIC
    Code:
      stack=1, locals=0, args_size=0
         0: getstatic     #23                 // Field coursier/core/Configuration$.MODULE$:Lcoursier/core/Configuration$;
         3: invokevirtual #124                // Method coursier/core/Configuration$.empty:()Ljava/lang/String;
         6: areturn

  public static scala.math.Ordering<coursier.core.Configuration> ordering();
    descriptor: ()Lscala/math/Ordering;
    flags: (0x0009) ACC_PUBLIC, ACC_STATIC
    Code:
      stack=1, locals=0, args_size=0
         0: getstatic     #23                 // Field coursier/core/Configuration$.MODULE$:Lcoursier/core/Configuration$;
         3: invokevirtual #129                // Method coursier/core/Configuration$.ordering:()Lscala/math/Ordering;
         6: areturn
    Signature: #127                         // ()Lscala/math/Ordering<Lcoursier/core/Configuration;>;

  public scala.collection.Iterator<java.lang.String> productElementNames();
    descriptor: ()Lscala/collection/Iterator;
    flags: (0x0001) ACC_PUBLIC
    Code:
      stack=1, locals=1, args_size=1
         0: aload_0
         1: invokestatic  #136                // InterfaceMethod scala/Product.productElementNames$:(Lscala/Product;)Lscala/collection/Iterator;
         4: areturn
      LineNumberTable:
        line 167: 0
      LocalVariableTable:
        Start  Length  Slot  Name   Signature
            0       5     0  this   Lcoursier/core/Configuration;
    Signature: #132                         // ()Lscala/collection/Iterator<Ljava/lang/String;>;

  public java.lang.String value();
    descriptor: ()Ljava/lang/String;
    flags: (0x0001) ACC_PUBLIC
    Code:
      stack=1, locals=1, args_size=1
         0: aload_0
         1: getfield      #140                // Field value:Ljava/lang/String;
         4: areturn
      LineNumberTable:
        line 167: 0
      LocalVariableTable:
        Start  Length  Slot  Name   Signature
            0       5     0  this   Lcoursier/core/Configuration;

  public boolean isEmpty();
    descriptor: ()Z
    flags: (0x0001) ACC_PUBLIC
    Code:
      stack=2, locals=1, args_size=1
         0: getstatic     #23                 // Field coursier/core/Configuration$.MODULE$:Lcoursier/core/Configuration$;
         3: aload_0
         4: invokevirtual #144                // Method value:()Ljava/lang/String;
         7: invokevirtual #79                 // Method coursier/core/Configuration$.isEmpty$extension:(Ljava/lang/String;)Z
        10: ireturn
      LineNumberTable:
        line 169: 0
      LocalVariableTable:
        Start  Length  Slot  Name   Signature
            0      11     0  this   Lcoursier/core/Configuration;

  public boolean nonEmpty();
    descriptor: ()Z
    flags: (0x0001) ACC_PUBLIC
    Code:
      stack=2, locals=1, args_size=1
         0: getstatic     #23                 // Field coursier/core/Configuration$.MODULE$:Lcoursier/core/Configuration$;
         3: aload_0
         4: invokevirtual #144                // Method value:()Ljava/lang/String;
         7: invokevirtual #76                 // Method coursier/core/Configuration$.nonEmpty$extension:(Ljava/lang/String;)Z
        10: ireturn
      LineNumberTable:
        line 171: 0
      LocalVariableTable:
        Start  Length  Slot  Name   Signature
            0      11     0  this   Lcoursier/core/Configuration;

  public java.lang.String $minus$minus$greater(java.lang.String);
    descriptor: (Ljava/lang/String;)Ljava/lang/String;
    flags: (0x0001) ACC_PUBLIC
    Code:
      stack=3, locals=2, args_size=2
         0: getstatic     #23                 // Field coursier/core/Configuration$.MODULE$:Lcoursier/core/Configuration$;
         3: aload_0
         4: invokevirtual #144                // Method value:()Ljava/lang/String;
         7: aload_1
         8: invokevirtual #72                 // Method coursier/core/Configuration$.$minus$minus$greater$extension:(Ljava/lang/String;Ljava/lang/String;)Ljava/lang/String;
        11: areturn
      LineNumberTable:
        line 173: 0
      LocalVariableTable:
        Start  Length  Slot  Name   Signature
            0      12     0  this   Lcoursier/core/Configuration;
            0      12     1 target   Ljava/lang/String;
    MethodParameters:
      Name                           Flags
      target                         final

  public java.lang.String map(scala.Function1<java.lang.String, java.lang.String>);
    descriptor: (Lscala/Function1;)Ljava/lang/String;
    flags: (0x0001) ACC_PUBLIC
    Code:
      stack=3, locals=2, args_size=2
         0: getstatic     #23                 // Field coursier/core/Configuration$.MODULE$:Lcoursier/core/Configuration$;
         3: aload_0
         4: invokevirtual #144                // Method value:()Ljava/lang/String;
         7: aload_1
         8: invokevirtual #68                 // Method coursier/core/Configuration$.map$extension:(Ljava/lang/String;Lscala/Function1;)Ljava/lang/String;
        11: areturn
      LineNumberTable:
        line 175: 0
      LocalVariableTable:
        Start  Length  Slot  Name   Signature
            0      12     0  this   Lcoursier/core/Configuration;
            0      12     1     f   Lscala/Function1;
    Signature: #149                         // (Lscala/Function1<Ljava/lang/String;Ljava/lang/String;>;)Ljava/lang/String;
    MethodParameters:
      Name                           Flags
      f                              final

  public java.lang.String copy(java.lang.String);
    descriptor: (Ljava/lang/String;)Ljava/lang/String;
    flags: (0x0001) ACC_PUBLIC
    Code:
      stack=3, locals=2, args_size=2
         0: getstatic     #23                 // Field coursier/core/Configuration$.MODULE$:Lcoursier/core/Configuration$;
         3: aload_0
         4: invokevirtual #144                // Method value:()Ljava/lang/String;
         7: aload_1
         8: invokevirtual #63                 // Method coursier/core/Configuration$.copy$extension:(Ljava/lang/String;Ljava/lang/String;)Ljava/lang/String;
        11: areturn
      LineNumberTable:
        line 167: 0
      LocalVariableTable:
        Start  Length  Slot  Name   Signature
            0      12     0  this   Lcoursier/core/Configuration;
            0      12     1 value   Ljava/lang/String;
    MethodParameters:
      Name                           Flags
      value                          final

  public java.lang.String copy$default$1();
    descriptor: ()Ljava/lang/String;
    flags: (0x0001) ACC_PUBLIC
    Code:
      stack=2, locals=1, args_size=1
         0: getstatic     #23                 // Field coursier/core/Configuration$.MODULE$:Lcoursier/core/Configuration$;
         3: aload_0
         4: invokevirtual #144                // Method value:()Ljava/lang/String;
         7: invokevirtual #59                 // Method coursier/core/Configuration$.copy$default$1$extension:(Ljava/lang/String;)Ljava/lang/String;
        10: areturn
      LineNumberTable:
        line 167: 0
      LocalVariableTable:
        Start  Length  Slot  Name   Signature
            0      11     0  this   Lcoursier/core/Configuration;

  public java.lang.String productPrefix();
    descriptor: ()Ljava/lang/String;
    flags: (0x0001) ACC_PUBLIC
    Code:
      stack=2, locals=1, args_size=1
         0: getstatic     #23                 // Field coursier/core/Configuration$.MODULE$:Lcoursier/core/Configuration$;
         3: aload_0
         4: invokevirtual #144                // Method value:()Ljava/lang/String;
         7: invokevirtual #56                 // Method coursier/core/Configuration$.productPrefix$extension:(Ljava/lang/String;)Ljava/lang/String;
        10: areturn
      LineNumberTable:
        line 167: 0
      LocalVariableTable:
        Start  Length  Slot  Name   Signature
            0      11     0  this   Lcoursier/core/Configuration;

  public int productArity();
    descriptor: ()I
    flags: (0x0001) ACC_PUBLIC
    Code:
      stack=2, locals=1, args_size=1
         0: getstatic     #23                 // Field coursier/core/Configuration$.MODULE$:Lcoursier/core/Configuration$;
         3: aload_0
         4: invokevirtual #144                // Method value:()Ljava/lang/String;
         7: invokevirtual #53                 // Method coursier/core/Configuration$.productArity$extension:(Ljava/lang/String;)I
        10: ireturn
      LineNumberTable:
        line 167: 0
      LocalVariableTable:
        Start  Length  Slot  Name   Signature
            0      11     0  this   Lcoursier/core/Configuration;

  public java.lang.Object productElement(int);
    descriptor: (I)Ljava/lang/Object;
    flags: (0x0001) ACC_PUBLIC
    Code:
      stack=3, locals=2, args_size=2
         0: getstatic     #23                 // Field coursier/core/Configuration$.MODULE$:Lcoursier/core/Configuration$;
         3: aload_0
         4: invokevirtual #144                // Method value:()Ljava/lang/String;
         7: iload_1
         8: invokevirtual #50                 // Method coursier/core/Configuration$.productElement$extension:(Ljava/lang/String;I)Ljava/lang/Object;
        11: areturn
      LineNumberTable:
        line 167: 0
      LocalVariableTable:
        Start  Length  Slot  Name   Signature
            0      12     0  this   Lcoursier/core/Configuration;
            0      12     1   x$1   I
    MethodParameters:
      Name                           Flags
      x$1                            final

  public scala.collection.Iterator<java.lang.Object> productIterator();
    descriptor: ()Lscala/collection/Iterator;
    flags: (0x0001) ACC_PUBLIC
    Code:
      stack=2, locals=1, args_size=1
         0: getstatic     #23                 // Field coursier/core/Configuration$.MODULE$:Lcoursier/core/Configuration$;
         3: aload_0
         4: invokevirtual #144                // Method value:()Ljava/lang/String;
         7: invokevirtual #46                 // Method coursier/core/Configuration$.productIterator$extension:(Ljava/lang/String;)Lscala/collection/Iterator;
        10: areturn
      LineNumberTable:
        line 167: 0
      LocalVariableTable:
        Start  Length  Slot  Name   Signature
            0      11     0  this   Lcoursier/core/Configuration;
    Signature: #160                         // ()Lscala/collection/Iterator<Ljava/lang/Object;>;

  public boolean canEqual(java.lang.Object);
    descriptor: (Ljava/lang/Object;)Z
    flags: (0x0001) ACC_PUBLIC
    Code:
      stack=3, locals=2, args_size=2
         0: getstatic     #23                 // Field coursier/core/Configuration$.MODULE$:Lcoursier/core/Configuration$;
         3: aload_0
         4: invokevirtual #144                // Method value:()Ljava/lang/String;
         7: aload_1
         8: invokevirtual #41                 // Method coursier/core/Configuration$.canEqual$extension:(Ljava/lang/String;Ljava/lang/Object;)Z
        11: ireturn
      LineNumberTable:
        line 167: 0
      LocalVariableTable:
        Start  Length  Slot  Name   Signature
            0      12     0  this   Lcoursier/core/Configuration;
            0      12     1   x$1   Ljava/lang/Object;
    MethodParameters:
      Name                           Flags
      x$1                            final

  public java.lang.String productElementName(int);
    descriptor: (I)Ljava/lang/String;
    flags: (0x0001) ACC_PUBLIC
    Code:
      stack=3, locals=2, args_size=2
         0: getstatic     #23                 // Field coursier/core/Configuration$.MODULE$:Lcoursier/core/Configuration$;
         3: aload_0
         4: invokevirtual #144                // Method value:()Ljava/lang/String;
         7: iload_1
         8: invokevirtual #38                 // Method coursier/core/Configuration$.productElementName$extension:(Ljava/lang/String;I)Ljava/lang/String;
        11: areturn
      LineNumberTable:
        line 167: 0
      LocalVariableTable:
        Start  Length  Slot  Name   Signature
            0      12     0  this   Lcoursier/core/Configuration;
            0      12     1   x$1   I
    MethodParameters:
      Name                           Flags
      x$1                            final

  public int hashCode();
    descriptor: ()I
    flags: (0x0001) ACC_PUBLIC
    Code:
      stack=2, locals=1, args_size=1
         0: getstatic     #23                 // Field coursier/core/Configuration$.MODULE$:Lcoursier/core/Configuration$;
         3: aload_0
         4: invokevirtual #144                // Method value:()Ljava/lang/String;
         7: invokevirtual #34                 // Method coursier/core/Configuration$.hashCode$extension:(Ljava/lang/String;)I
        10: ireturn
      LineNumberTable:
        line 167: 0
      LocalVariableTable:
        Start  Length  Slot  Name   Signature
            0      11     0  this   Lcoursier/core/Configuration;

  public boolean equals(java.lang.Object);
    descriptor: (Ljava/lang/Object;)Z
    flags: (0x0001) ACC_PUBLIC
    Code:
      stack=3, locals=2, args_size=2
         0: getstatic     #23                 // Field coursier/core/Configuration$.MODULE$:Lcoursier/core/Configuration$;
         3: aload_0
         4: invokevirtual #144                // Method value:()Ljava/lang/String;
         7: aload_1
         8: invokevirtual #30                 // Method coursier/core/Configuration$.equals$extension:(Ljava/lang/String;Ljava/lang/Object;)Z
        11: ireturn
      LineNumberTable:
        line 167: 0
      LocalVariableTable:
        Start  Length  Slot  Name   Signature
            0      12     0  this   Lcoursier/core/Configuration;
            0      12     1   x$1   Ljava/lang/Object;
    MethodParameters:
      Name                           Flags
      x$1                            final

  public java.lang.String toString();
    descriptor: ()Ljava/lang/String;
    flags: (0x0001) ACC_PUBLIC
    Code:
      stack=2, locals=1, args_size=1
         0: getstatic     #23                 // Field coursier/core/Configuration$.MODULE$:Lcoursier/core/Configuration$;
         3: aload_0
         4: invokevirtual #144                // Method value:()Ljava/lang/String;
         7: invokevirtual #25                 // Method coursier/core/Configuration$.toString$extension:(Ljava/lang/String;)Ljava/lang/String;
        10: areturn
      LineNumberTable:
        line 167: 0
      LocalVariableTable:
        Start  Length  Slot  Name   Signature
            0      11     0  this   Lcoursier/core/Configuration;

  public coursier.core.Configuration(java.lang.String);
    descriptor: (Ljava/lang/String;)V
    flags: (0x0001) ACC_PUBLIC
    Code:
      stack=2, locals=2, args_size=2
         0: aload_0
         1: aload_1
         2: putfield      #140                // Field value:Ljava/lang/String;
         5: aload_0
         6: invokespecial #173                // Method java/lang/Object."<init>":()V
         9: aload_0
        10: invokestatic  #177                // InterfaceMethod scala/Product.$init$:(Lscala/Product;)V
        13: return
      LineNumberTable:
        line 167: 0
      LocalVariableTable:
        Start  Length  Slot  Name   Signature
            0      14     0  this   Lcoursier/core/Configuration;
            0      14     1 value   Ljava/lang/String;
    MethodParameters:
      Name                           Flags
      value                          final
}
SourceFile: "Definitions.scala"
RuntimeVisibleAnnotations:
  0: #10(#11=s#12)
    scala.reflect.ScalaSignature(
      bytes="\u0006\u0005\tuc\u0001B A\u0005\u0016C\u0001b\u0017\u0001\u0003\u0016\u0004%\t\u0001\u0018\u0005\tK\u0002\u0011\t\u0012)A\u0005;\")a\r\u0001C\u0001O\")1\u000e\u0001C\u0001Y\")\u0001\u000f\u0001C\u0001Y\")\u0011\u000f\u0001C\u0001e\")Q\u000f\u0001C\u0001m\"9A\u0010AA\u0001\n\u0003i\b\u0002C@\u0001#\u0003%\t!!\u0001\t\u0013\u0005]\u0001!!A\u0005B\u0005e\u0001\"CA\u0015\u0001\u0005\u0005I\u0011AA\u0016\u0011%\t\u0019\u0004AA\u0001\n\u0003\t)\u0004C\u0005\u0002B\u0001\t\t\u0011\"\u0011\u0002D!I\u0011\u0011\u000b\u0001\u0002\u0002\u0013\u0005\u00111\u000b\u0005\n\u0003/\u0002\u0011\u0011!C!\u00033B\u0011\"!\u0018\u0001\u0003\u0003%\t%a\u0018\t\u0013\u0005\u0005\u0004!!A\u0005B\u0005\r\u0004\"CA4\u0001\u0005\u0005I\u0011IA5\u000f\u001d\tY\u0007\u0011E\u0001\u0003[2aa\u0010!\t\u0002\u0005=\u0004B\u00024\u0015\t\u0003\t\t\tC\u0005\u0002\u0004R\u0011\r\u0011b\u0001\u0002\u0006\"A\u0011Q\u0012\u000b!\u0002\u0013\t9\tC\u0005\u0002\u0010R\u0011\r\u0011\"\u0001\u0002\u0012\"9\u00111\u0013\u000b!\u0002\u0013A\u0007\"CAK)\t\u0007I\u0011AAI\u0011\u001d\t9\n\u0006Q\u0001\n!D\u0011\"!\'\u0015\u0005\u0004%\t!!%\t\u000f\u0005mE\u0003)A\u0005Q\"I\u0011Q\u0014\u000bC\u0002\u0013\u0005\u0011\u0011\u0013\u0005\b\u0003?#\u0002\u0015!\u0003i\u0011%\t\t\u000b\u0006b\u0001\n\u0003\t\t\nC\u0004\u0002$R\u0001\u000b\u0011\u00025\t\u0013\u0005\u0015FC1A\u0005\u0002\u0005E\u0005bBAT)\u0001\u0006I\u0001\u001b\u0005\n\u0003S#\"\u0019!C\u0001\u0003#Cq!a+\u0015A\u0003%\u0001\u000eC\u0005\u0002.R\u0011\r\u0011\"\u0001\u0002\u0012\"9\u0011q\u0016\u000b!\u0002\u0013A\u0007\"CAY)\t\u0007I\u0011AAI\u0011\u001d\t\u0019\f\u0006Q\u0001\n!D\u0011\"!.\u0015\u0005\u0004%\t!!%\t\u000f\u0005]F\u0003)A\u0005Q\"9\u0011\u0011\u0018\u000b\u0005\u0002\u0005m\u0006\"CAd)\u0005\u0005I\u0011QAe\u0011%\ti\rFA\u0001\n\u0003\u000by\rC\u0005\u0002\\R\t\t\u0011\"\u0003\u0002^\"9\u0011Q\u001d\u000b\u0005\u0006\u0005\u001d\bbBAw)\u0011\u0015\u0011q\u001e\u0005\b\u0003g$BQAA{\u0011\u001d\ti\u0010\u0006C\u0003\u0003\u007fD\u0011Ba\u0002\u0015\u0003\u0003%)A!\u0003\t\u0013\tEA#%A\u0005\u0006\tM\u0001\"\u0003B\f)\u0005\u0005IQ\u0001B\r\u0011%\u0011i\u0002FA\u0001\n\u000b\u0011y\u0002C\u0005\u0003$Q\t\t\u0011\"\u0002\u0003&!I!Q\u0006\u000b\u0002\u0002\u0013\u0015!q\u0006\u0005\n\u0005g!\u0012\u0011!C\u0003\u0005kA\u0011B!\u0010\u0015\u0003\u0003%)Aa\u0010\t\u0013\t\u001dC#!A\u0005\u0006\t%\u0003\"\u0003B\')\u0005\u0005IQ\u0001B(\u0011%\u00119\u0006FA\u0001\n\u000b\u0011IFA\u0007D_:4\u0017nZ;sCRLwN\u001c\u0006\u0003\u0003\n\u000bAaY8sK*\t1)\u0001\u0005d_V\u00148/[3s\u0007\u0001\u0019B\u0001\u0001$M\u001fB\u0011qIS\u0007\u0002\u0011*\t\u0011*A\u0003tG\u0006d\u0017-\u0003\u0002L\u0011\n1\u0011I\\=WC2\u0004\"aR\'\n\u00059C%a\u0002)s_\u0012,8\r\u001e\t\u0003!bs!!\u0015,\u000f\u0005I+V\"A*\u000b\u0005Q#\u0015A\u0002\u001fs_>$h(C\u0001J\u0013\t9\u0006*A\u0004qC\u000e\\\u0017mZ3\n\u0005eS&\u0001D*fe&\fG.\u001b>bE2,\'BA,I\u0003\u00151\u0018\r\\;f+\u0005i\u0006C\u00010c\u001d\ty\u0006\r\u0005\u0002S\u0011&\u0011\u0011\rS\u0001\u0007!J,G-\u001a4\n\u0005\r$\'AB*ue&twM\u0003\u0002b\u0011\u00061a/\u00197vK\u0002\na\u0001P5oSRtDC\u00015k!\tI\u0007!D\u0001A\u0011\u0015Y6\u00011\u0001^\u0003\u001dI7/R7qif,\u0012!\u001c\t\u0003\u000f:L!a\u001c%\u0003\u000f\t{w\u000e\\3b]\u0006Aan\u001c8F[B$\u00180\u0001\u000b%[&tWo\u001d\u0013nS:,8\u000fJ4sK\u0006$XM\u001d\u000b\u0003QNDQ\u0001\u001e\u0004A\u0002!\fa\u0001^1sO\u0016$\u0018aA7baR\u0011\u0001n\u001e\u0005\u0006q\u001e\u0001\r!_\u0001\u0002MB!qI_/^\u0013\tY\bJA\u0005Gk:\u001cG/[8oc\u0005!1m\u001c9z)\tAg\u0010C\u0004\\\u0011A\u0005\t\u0019A/\u0002\u001d\r|\u0007/\u001f\u0013eK\u001a\fW\u000f\u001c;%cU\u0011\u00111\u0001\u0016\u0004;\u0006\u00151FAA\u0004!\u0011\tI!a\u0005\u000e\u0005\u0005-!\u0002BA\u0007\u0003\u001f\t\u0011\"\u001e8dQ\u0016\u001c7.\u001a3\u000b\u0007\u0005E\u0001*\u0001\u0006b]:|G/\u0019;j_:LA!!\u0006\u0002\f\t\tRO\\2iK\u000e\\W\r\u001a,be&\fgnY3\u0002\u001bA\u0014x\u000eZ;diB\u0013XMZ5y+\t\tY\u0002\u0005\u0003\u0002\u001e\u0005\u001dRBAA\u0010\u0015\u0011\t\t#a\t\u0002\t1\fgn\u001a\u0006\u0003\u0003K\tAA[1wC&\u00191-a\b\u0002\u0019A\u0014x\u000eZ;di\u0006\u0013\u0018\u000e^=\u0016\u0005\u00055\u0002cA$\u00020%\u0019\u0011\u0011\u0007%\u0003\u0007%sG/\u0001\bqe>$Wo\u0019;FY\u0016lWM\u001c;\u0015\t\u0005]\u0012Q\b\t\u0004\u000f\u0006e\u0012bAA\u001e\u0011\n\u0019\u0011I\\=\t\u0013\u0005}B\"!AA\u0002\u00055\u0012a\u0001=%c\u0005y\u0001O]8ek\u000e$\u0018\n^3sCR|\'/\u0006\u0002\u0002FA1\u0011qIA\'\u0003oi!!!\u0013\u000b\u0007\u0005-\u0003*\u0001\u0006d_2dWm\u0019;j_:LA!a\u0014\u0002J\tA\u0011\n^3sCR|\'/\u0001\u0005dC:,\u0015/^1m)\ri\u0017Q\u000b\u0005\n\u0003\u007fq\u0011\u0011!a\u0001\u0003o\t!\u0003\u001d:pIV\u001cG/\u00127f[\u0016tGOT1nKR!\u00111DA.\u0011%\tydDA\u0001\u0002\u0004\ti#\u0001\u0005iCND7i\u001c3f)\t\ti#\u0001\u0004fcV\fGn\u001d\u000b\u0004[\u0006\u0015\u0004\"CA #\u0005\u0005\t\u0019AA\u001c\u0003!!xn\u0015;sS:<GCAA\u000e\u00035\u0019uN\u001c4jOV\u0014\u0018\r^5p]B\u0011\u0011\u000eF\n\u0006)\u0005E\u0014q\u000f\t\u0004\u000f\u0006M\u0014bAA;\u0011\n1\u0011I\\=SK\u001a\u0004B!!\u001f\u0002\u00005\u0011\u00111\u0010\u0006\u0005\u0003{\n\u0019#\u0001\u0002j_&\u0019\u0011,a\u001f\u0015\u0005\u00055\u0014\u0001C8sI\u0016\u0014\u0018N\\4\u0016\u0005\u0005\u001d\u0005\u0003\u0002)\u0002\n\"L1!a#[\u0005!y%\u000fZ3sS:<\u0017!C8sI\u0016\u0014\u0018N\\4!\u0003\u0015)W\u000e\u001d;z+\u0005A\u0017AB3naRL\b%A\u0004d_6\u0004\u0018\u000e\\3\u0002\u0011\r|W\u000e]5mK\u0002\nqA];oi&lW-\u0001\u0005sk:$\u0018.\\3!\u0003\u0011!Xm\u001d;\u0002\u000bQ,7\u000f\u001e\u0011\u0002\u000f\u0011,g-Y;mi\u0006AA-\u001a4bk2$\b%\u0001\beK\u001a\fW\u000f\u001c;D_6\u0004\u0018\u000e\\3\u0002\u001f\u0011,g-Y;mi\u000e{W\u000e]5mK\u0002\n\u0001\u0002\u001d:pm&$W\rZ\u0001\naJ|g/\u001b3fI\u0002\na![7q_J$\u0018aB5na>\u0014H\u000fI\u0001\t_B$\u0018n\u001c8bY\u0006Iq\u000e\u001d;j_:\fG\u000eI\u0001\u0004C2d\u0017\u0001B1mY\u0002\nAA[8j]R\u0019\u0001.!0\t\u000f\u0005}F\u00061\u0001\u0002B\u0006)1m\u001c8ggB!q)a1i\u0013\r\t)\r\u0013\u0002\u000byI,\u0007/Z1uK\u0012t\u0014!B1qa2LHc\u00015\u0002L\")1,\fa\u0001;\u00069QO\\1qa2LH\u0003BAi\u0003/\u0004BaRAj;&\u0019\u0011Q\u001b%\u0003\r=\u0003H/[8o\u0011!\tINLA\u0001\u0002\u0004A\u0017a\u0001=%a\u0005aqO]5uKJ+\u0007\u000f\\1dKR\u0011\u0011q\u001c\t\u0005\u0003;\t\t/\u0003\u0003\u0002d\u0006}!AB(cU\u0016\u001cG/A\tjg\u0016k\u0007\u000f^=%Kb$XM\\:j_:$2!\\Au\u0011\u0019\tY\u000f\ra\u0001Q\u0006)A\u0005\u001e5jg\u0006\u0011bn\u001c8F[B$\u0018\u0010J3yi\u0016t7/[8o)\ri\u0017\u0011\u001f\u0005\u0007\u0003W\f\u0004\u0019\u00015\u0002=\u0011j\u0017N\\;tI5Lg.^:%OJ,\u0017\r^3sI\u0015DH/\u001a8tS>tG\u0003BA|\u0003w$2\u0001[A}\u0011\u0015!(\u00071\u0001i\u0011\u0019\tYO\ra\u0001Q\u0006iQ.\u00199%Kb$XM\\:j_:$BA!\u0001\u0003\u0006Q\u0019\u0001Na\u0001\t\u000ba\u001c\u0004\u0019A=\t\r\u0005-8\u00071\u0001i\u00039\u0019w\u000e]=%Kb$XM\\:j_:$BAa\u0003\u0003\u0010Q\u0019\u0001N!\u0004\t\u000fm#\u0004\u0013!a\u0001;\"1\u00111\u001e\u001bA\u0002!\f\u0001dY8qs\u0012\"WMZ1vYR$\u0013\u0007J3yi\u0016t7/[8o)\u0011\t\u0019A!\u0006\t\r\u0005-X\u00071\u0001i\u0003]\u0001(o\u001c3vGR\u0004&/\u001a4jq\u0012*\u0007\u0010^3og&|g\u000e\u0006\u0003\u0002\u001c\tm\u0001BBAvm\u0001\u0007\u0001.\u0001\fqe>$Wo\u0019;Be&$\u0018\u0010J3yi\u0016t7/[8o)\u0011\tiC!\t\t\r\u0005-x\u00071\u0001i\u0003a\u0001(o\u001c3vGR,E.Z7f]R$S\r\u001f;f]NLwN\u001c\u000b\u0005\u0005O\u0011Y\u0003\u0006\u0003\u00028\t%\u0002\"CA q\u0005\u0005\t\u0019AA\u0017\u0011\u0019\tY\u000f\u000fa\u0001Q\u0006I\u0002O]8ek\u000e$\u0018\n^3sCR|\'\u000fJ3yi\u0016t7/[8o)\u0011\t)E!\r\t\r\u0005-\u0018\b1\u0001i\u0003I\u0019\u0017M\\#rk\u0006dG%\u001a=uK:\u001c\u0018n\u001c8\u0015\t\t]\"1\b\u000b\u0004[\ne\u0002\"CA u\u0005\u0005\t\u0019AA\u001c\u0011\u0019\tYO\u000fa\u0001Q\u0006a\u0002O]8ek\u000e$X\t\\3nK:$h*Y7fI\u0015DH/\u001a8tS>tG\u0003\u0002B!\u0005\u000b\"B!a\u0007\u0003D!I\u0011qH\u001e\u0002\u0002\u0003\u0007\u0011Q\u0006\u0005\u0007\u0003W\\\u0004\u0019\u00015\u0002%!\f7\u000f[\"pI\u0016$S\r\u001f;f]NLwN\u001c\u000b\u0005\u0003?\u0012Y\u0005\u0003\u0004\u0002lr\u0002\r\u0001[\u0001\u0011KF,\u0018\r\\:%Kb$XM\\:j_:$BA!\u0015\u0003VQ\u0019QNa\u0015\t\u0013\u0005}R(!AA\u0002\u0005]\u0002BBAv{\u0001\u0007\u0001.\u0001\nu_N#(/\u001b8hI\u0015DH/\u001a8tS>tG\u0003BA5\u00057Ba!a;?\u0001\u0004A\u0007"
    )
  ScalaInlineInfo: length = 0x5E (unknown attribute)
   01 01 00 12 00 92 00 10 01 00 A9 00 AA 01 00 A1
   00 A2 01 00 97 00 10 01 00 98 00 5F 01 00 A7 00
   A2 01 00 A6 00 9B 01 00 8D 00 8E 01 00 93 00 94
   01 00 91 00 8E 01 00 9A 00 9B 01 00 9C 00 9D 01
   00 A4 00 A5 01 00 82 00 83 01 00 9F 00 83 01 00
   99 00 5F 01 00 A8 00 5F 01 00 0D 00 5F 01
  ScalaSig: length = 0x3 (unknown attribute)
   05 02 00
