Classfile /Users/mw/Projects/slang-braindump/.jar/jar11/assemble/slang-braindump/assemble/content/coursier/core/Continue.class
  Last modified May 29, 2022; size 5663 bytes
  SHA-256 checksum 9520f63301c3dd44a15d6c3cac09430a64cf5a2622bc2279b25e8ac2b215e507
  Compiled from "ResolutionProcess.scala"
public final class coursier.core.Continue extends coursier.core.ResolutionProcess
  minor version: 0
  major version: 52
  flags: (0x0031) ACC_PUBLIC, ACC_FINAL, ACC_SUPER
  this_class: #2                          // coursier/core/Continue
  super_class: #4                         // coursier/core/ResolutionProcess
  interfaces: 0, fields: 2, methods: 17, attributes: 4
Constant pool:
    #1 = Utf8               coursier/core/Continue
    #2 = Class              #1            // coursier/core/Continue
    #3 = Utf8               coursier/core/ResolutionProcess
    #4 = Class              #3            // coursier/core/ResolutionProcess
    #5 = Utf8               ResolutionProcess.scala
    #6 = Utf8               Lscala/reflect/ScalaSignature;
    #7 = Utf8               bytes
    #8 = Utf8               \u0006\u0005\u0005=b\u0001\u0002\r\u001a\u0005yA\u0001\"\u000e\u0001\u0003\u0006\u0004%\tA\u000e\u0005\tu\u0001\u0011\t\u0011)A\u0005o!A1\b\u0001BC\u0002\u0013\u0005A\b\u0003\u0005A\u0001\t\u0005\t\u0015!\u0003>\u0011\u0015\t\u0005\u0001\"\u0001C\u0011\u00151\u0005\u0001\"\u0001H\u0011\u0015A\u0005\u0001\"\u0001H\u0011\u0015\u0001\u0006\u0001\"\u0001R\u0011\u0015\u0019\u0006\u0001\"\u0001U\u0011\u00151\u0006\u0001\"\u0011X\u0011\u0015\u0001\u0007\u0001\"\u0011b\u0011\u0015Q\u0007\u0001\"\u0011l\u0011\u0015i\u0007\u0001\"\u0011o\u0011\u0015\u0011\b\u0001\"\u0003t\u0011\u00159\b\u0001\"\u0011y\u0011\u0015I\b\u0001\"\u0011{\u0011\u0015Y\b\u0001\"\u0011}\u0011\u0019y\b\u0001\"\u0011\u0002\u0002\u001d9\u0011QA\r\t\u0002\u0005\u001daA\u0002\r\u001a\u0011\u0003\tI\u0001\u0003\u0004B)\u0011\u0005\u00111\u0004\u0005\b\u0003;!B\u0011AA\u0010\u0011%\t)\u0003FA\u0001\n\u0013\t9C\u0001\u0005D_:$\u0018N\\;f\u0015\tQ2$\u0001\u0003d_J,\'\"\u0001\u000f\u0002\u0011\r|WO]:jKJ\u001c\u0001a\u0005\u0003\u0001?\rJ\u0003C\u0001\u0011\"\u001b\u0005I\u0012B\u0001\u0012\u001a\u0005E\u0011Vm]8mkRLwN\u001c)s_\u000e,7o\u001d\t\u0003I\u001dj\u0011!\n\u0006\u0002M\u0005)1oY1mC&\u0011\u0001&\n\u0002\b!J|G-^2u!\tQ#G\u0004\u0002,a9\u0011AfL\u0007\u0002[)\u0011a&H\u0001\u0007yI|w\u000e\u001e \n\u0003\u0019J!!M\u0013\u0002\u000fA\f7m[1hK&\u00111\u0007\u000e\u0002\r\'\u0016\u0014\u0018.\u00197ju\u0006\u0014G.\u001a\u0006\u0003c\u0015\nqaY;se\u0016tG/F\u00018!\t\u0001\u0003(\u0003\u0002:3\tQ!+Z:pYV$\u0018n\u001c8\u0002\u0011\r,(O]3oi\u0002\nAaY8oiV\tQ\b\u0005\u0003%}]z\u0012BA &\u0005%1UO\\2uS>t\u0017\'A\u0003d_:$\b%\u0001\u0004=S:LGO\u0010\u000b\u0004\u0007\u0012+\u0005C\u0001\u0011\u0001\u0011\u0015)T\u00011\u00018\u0011\u0015YT\u00011\u0001>\u0003\u0011qW\r\u001f;\u0016\u0003}\t!B\\3yi:{7i\u001c8uQ\t9!\n\u0005\u0002L\u001d6\tAJ\u0003\u0002NK\u0005Q\u0011M\u001c8pi\u0006$\u0018n\u001c8\n\u0005=c%a\u0002;bS2\u0014XmY\u0001\fo&$\bnQ;se\u0016tG\u000f\u0006\u0002D%\")Q\u0007\u0003a\u0001o\u0005Aq/\u001b;i\u0007>tG\u000f\u0006\u0002D+\")1(\u0003a\u0001{\u0005AAo\\*ue&tw\rF\u0001Y!\tIf,D\u0001[\u0015\tYF,\u0001\u0003mC:<\'\"A/\u0002\t)\fg/Y\u0005\u0003?j\u0013aa\u0015;sS:<\u0017\u0001C2b]\u0016\u000bX/\u00197\u0015\u0005\t,\u0007C\u0001\u0013d\u0013\t!WEA\u0004C_>dW-\u00198\t\u000b\u0019\\\u0001\u0019A4\u0002\u0007=\u0014\'\u000e\u0005\u0002%Q&\u0011\u0011.\n\u0002\u0004\u0003:L\u0018AB3rk\u0006d7\u000f\u0006\u0002cY\")a\r\u0004a\u0001O\u0006A\u0001.Y:i\u0007>$W\rF\u0001p!\t!\u0003/\u0003\u0002rK\t\u0019\u0011J\u001c;\u0002\u000bQ,\b\u000f\\3\u0016\u0003Q\u0004B\u0001J;8{%\u0011a/\n\u0002\u0007)V\u0004H.\u001a\u001a\u0002\u001bA\u0014x\u000eZ;diB\u0013XMZ5y+\u0005A\u0016\u0001\u00049s_\u0012,8\r^!sSRLX#A8\u0002\u001dA\u0014x\u000eZ;di\u0016cW-\\3oiR\u0011q- \u0005\u0006}F\u0001\ra\\\u0001\u0002]\u0006\u0011\u0002O]8ek\u000e$X\t\\3nK:$h*Y7f)\rA\u00161\u0001\u0005\u0006}J\u0001\ra\\\u0001\t\u0007>tG/\u001b8vKB\u0011\u0001\u0005F\n\u0006)\u0005-\u0011\u0011\u0003\t\u0004I\u00055\u0011bAA\bK\t1\u0011I\\=SK\u001a\u0004B!a\u0005\u0002\u001a5\u0011\u0011Q\u0003\u0006\u0004\u0003/a\u0016AA5p\u0013\r\u0019\u0014Q\u0003\u000b\u0003\u0003\u000f\tQ!\u00199qYf$RaQA\u0011\u0003GAQ!\u000e\fA\u0002]BQa\u000f\fA\u0002u\nAb\u001e:ji\u0016\u0014V\r\u001d7bG\u0016$\"!!\u000b\u0011\u0007e\u000bY#C\u0002\u0002.i\u0013aa\u00142kK\u000e$\b
    #9 = Utf8               current
   #10 = Utf8               Lcoursier/core/Resolution;
   #11 = Utf8               cont
   #12 = Utf8               Lscala/Function1;
   #13 = Utf8               Lscala/Function1<Lcoursier/core/Resolution;Lcoursier/core/ResolutionProcess;>;
   #14 = Utf8               apply
   #15 = Utf8               (Lcoursier/core/Resolution;Lscala/Function1;)Lcoursier/core/Continue;
   #16 = Utf8               (Lcoursier/core/Resolution;Lscala/Function1<Lcoursier/core/Resolution;Lcoursier/core/ResolutionProcess;>;)Lcoursier/core/Continue;
   #17 = Utf8               coursier/core/Continue$
   #18 = Class              #17           // coursier/core/Continue$
   #19 = Utf8               MODULE$
   #20 = Utf8               Lcoursier/core/Continue$;
   #21 = NameAndType        #19:#20       // MODULE$:Lcoursier/core/Continue$;
   #22 = Fieldref           #18.#21       // coursier/core/Continue$.MODULE$:Lcoursier/core/Continue$;
   #23 = NameAndType        #14:#15       // apply:(Lcoursier/core/Resolution;Lscala/Function1;)Lcoursier/core/Continue;
   #24 = Methodref          #18.#23       // coursier/core/Continue$.apply:(Lcoursier/core/Resolution;Lscala/Function1;)Lcoursier/core/Continue;
   #25 = Utf8               ()Lcoursier/core/Resolution;
   #26 = NameAndType        #9:#10        // current:Lcoursier/core/Resolution;
   #27 = Fieldref           #2.#26        // coursier/core/Continue.current:Lcoursier/core/Resolution;
   #28 = Utf8               this
   #29 = Utf8               Lcoursier/core/Continue;
   #30 = Utf8               ()Lscala/Function1;
   #31 = Utf8               ()Lscala/Function1<Lcoursier/core/Resolution;Lcoursier/core/ResolutionProcess;>;
   #32 = NameAndType        #11:#12       // cont:Lscala/Function1;
   #33 = Fieldref           #2.#32        // coursier/core/Continue.cont:Lscala/Function1;
   #34 = Utf8               next
   #35 = Utf8               ()Lcoursier/core/ResolutionProcess;
   #36 = NameAndType        #11:#30       // cont:()Lscala/Function1;
   #37 = Methodref          #2.#36        // coursier/core/Continue.cont:()Lscala/Function1;
   #38 = NameAndType        #9:#25        // current:()Lcoursier/core/Resolution;
   #39 = Methodref          #2.#38        // coursier/core/Continue.current:()Lcoursier/core/Resolution;
   #40 = Utf8               scala/Function1
   #41 = Class              #40           // scala/Function1
   #42 = Utf8               (Ljava/lang/Object;)Ljava/lang/Object;
   #43 = NameAndType        #14:#42       // apply:(Ljava/lang/Object;)Ljava/lang/Object;
   #44 = InterfaceMethodref #41.#43       // scala/Function1.apply:(Ljava/lang/Object;)Ljava/lang/Object;
   #45 = Utf8               nextNoCont
   #46 = NameAndType        #34:#35       // next:()Lcoursier/core/ResolutionProcess;
   #47 = Methodref          #2.#46        // coursier/core/Continue.next:()Lcoursier/core/ResolutionProcess;
   #48 = Utf8               withCurrent
   #49 = Utf8               (Lcoursier/core/Resolution;)Lcoursier/core/Continue;
   #50 = Utf8               <init>
   #51 = Utf8               (Lcoursier/core/Resolution;Lscala/Function1;)V
   #52 = NameAndType        #50:#51       // "<init>":(Lcoursier/core/Resolution;Lscala/Function1;)V
   #53 = Methodref          #2.#52        // coursier/core/Continue."<init>":(Lcoursier/core/Resolution;Lscala/Function1;)V
   #54 = Utf8               withCont
   #55 = Utf8               (Lscala/Function1;)Lcoursier/core/Continue;
   #56 = Utf8               (Lscala/Function1<Lcoursier/core/Resolution;Lcoursier/core/ResolutionProcess;>;)Lcoursier/core/Continue;
   #57 = Utf8               toString
   #58 = Utf8               ()Ljava/lang/String;
   #59 = Utf8               java/lang/StringBuilder
   #60 = Class              #59           // java/lang/StringBuilder
   #61 = Utf8               Continue(
   #62 = String             #61           // Continue(
   #63 = Utf8               (Ljava/lang/String;)V
   #64 = NameAndType        #50:#63       // "<init>":(Ljava/lang/String;)V
   #65 = Methodref          #60.#64       // java/lang/StringBuilder."<init>":(Ljava/lang/String;)V
   #66 = Utf8               java/lang/String
   #67 = Class              #66           // java/lang/String
   #68 = Utf8               valueOf
   #69 = Utf8               (Ljava/lang/Object;)Ljava/lang/String;
   #70 = NameAndType        #68:#69       // valueOf:(Ljava/lang/Object;)Ljava/lang/String;
   #71 = Methodref          #67.#70       // java/lang/String.valueOf:(Ljava/lang/Object;)Ljava/lang/String;
   #72 = Utf8               append
   #73 = Utf8               (Ljava/lang/String;)Ljava/lang/StringBuilder;
   #74 = NameAndType        #72:#73       // append:(Ljava/lang/String;)Ljava/lang/StringBuilder;
   #75 = Methodref          #60.#74       // java/lang/StringBuilder.append:(Ljava/lang/String;)Ljava/lang/StringBuilder;
   #76 = Utf8               ,
   #77 = String             #76           // ,
   #78 = Utf8               )
   #79 = String             #78           // )
   #80 = NameAndType        #57:#58       // toString:()Ljava/lang/String;
   #81 = Methodref          #60.#80       // java/lang/StringBuilder.toString:()Ljava/lang/String;
   #82 = Utf8               b
   #83 = Utf8               Ljava/lang/StringBuilder;
   #84 = Utf8               canEqual
   #85 = Utf8               (Ljava/lang/Object;)Z
   #86 = Utf8               obj
   #87 = Utf8               Ljava/lang/Object;
   #88 = Utf8               equals
   #89 = NameAndType        #84:#85       // canEqual:(Ljava/lang/Object;)Z
   #90 = Methodref          #2.#89        // coursier/core/Continue.canEqual:(Ljava/lang/Object;)Z
   #91 = Utf8               java/lang/Object
   #92 = Class              #91           // java/lang/Object
   #93 = Utf8               coursier/core/Resolution
   #94 = Class              #93           // coursier/core/Resolution
   #95 = NameAndType        #88:#85       // equals:(Ljava/lang/Object;)Z
   #96 = Methodref          #92.#95       // java/lang/Object.equals:(Ljava/lang/Object;)Z
   #97 = Utf8               other
   #98 = Utf8               hashCode
   #99 = Utf8               ()I
  #100 = Utf8               Continue
  #101 = String             #100          // Continue
  #102 = Utf8               scala/runtime/Statics
  #103 = Class              #102          // scala/runtime/Statics
  #104 = Utf8               anyHash
  #105 = Utf8               (Ljava/lang/Object;)I
  #106 = NameAndType        #104:#105     // anyHash:(Ljava/lang/Object;)I
  #107 = Methodref          #103.#106     // scala/runtime/Statics.anyHash:(Ljava/lang/Object;)I
  #108 = Utf8               code
  #109 = Utf8               I
  #110 = Utf8               tuple
  #111 = Utf8               ()Lscala/Tuple2;
  #112 = Utf8               ()Lscala/Tuple2<Lcoursier/core/Resolution;Lscala/Function1<Lcoursier/core/Resolution;Lcoursier/core/ResolutionProcess;>;>;
  #113 = Utf8               scala/Tuple2
  #114 = Class              #113          // scala/Tuple2
  #115 = Utf8               (Ljava/lang/Object;Ljava/lang/Object;)V
  #116 = NameAndType        #50:#115      // "<init>":(Ljava/lang/Object;Ljava/lang/Object;)V
  #117 = Methodref          #114.#116     // scala/Tuple2."<init>":(Ljava/lang/Object;Ljava/lang/Object;)V
  #118 = Utf8               productPrefix
  #119 = Utf8               productArity
  #120 = Utf8               productElement
  #121 = Utf8               (I)Ljava/lang/Object;
  #122 = Utf8               n
  #123 = Utf8               java/lang/IndexOutOfBoundsException
  #124 = Class              #123          // java/lang/IndexOutOfBoundsException
  #125 = Utf8               scala/runtime/BoxesRunTime
  #126 = Class              #125          // scala/runtime/BoxesRunTime
  #127 = Utf8               boxToInteger
  #128 = Utf8               (I)Ljava/lang/Integer;
  #129 = NameAndType        #127:#128     // boxToInteger:(I)Ljava/lang/Integer;
  #130 = Methodref          #126.#129     // scala/runtime/BoxesRunTime.boxToInteger:(I)Ljava/lang/Integer;
  #131 = Methodref          #92.#80       // java/lang/Object.toString:()Ljava/lang/String;
  #132 = Methodref          #124.#64      // java/lang/IndexOutOfBoundsException."<init>":(Ljava/lang/String;)V
  #133 = Utf8               productElementName
  #134 = Utf8               (I)Ljava/lang/String;
  #135 = String             #9            // current
  #136 = String             #11           // cont
  #137 = Utf8               (Lcoursier/core/Resolution;Lscala/Function1<Lcoursier/core/Resolution;Lcoursier/core/ResolutionProcess;>;)V
  #138 = Utf8               ()V
  #139 = NameAndType        #50:#138      // "<init>":()V
  #140 = Methodref          #4.#139       // coursier/core/ResolutionProcess."<init>":()V
  #141 = Utf8               Signature
  #142 = Utf8               Code
  #143 = Utf8               MethodParameters
  #144 = Utf8               LineNumberTable
  #145 = Utf8               LocalVariableTable
  #146 = Utf8               StackMapTable
  #147 = Utf8               SourceFile
  #148 = Utf8               RuntimeVisibleAnnotations
  #149 = Utf8               ScalaInlineInfo
  #150 = Utf8               ScalaSig
{
  private final coursier.core.Resolution current;
    descriptor: Lcoursier/core/Resolution;
    flags: (0x0012) ACC_PRIVATE, ACC_FINAL

  private final scala.Function1<coursier.core.Resolution, coursier.core.ResolutionProcess> cont;
    descriptor: Lscala/Function1;
    flags: (0x0012) ACC_PRIVATE, ACC_FINAL
    Signature: #13                          // Lscala/Function1<Lcoursier/core/Resolution;Lcoursier/core/ResolutionProcess;>;

  public static coursier.core.Continue apply(coursier.core.Resolution, scala.Function1<coursier.core.Resolution, coursier.core.ResolutionProcess>);
    descriptor: (Lcoursier/core/Resolution;Lscala/Function1;)Lcoursier/core/Continue;
    flags: (0x0009) ACC_PUBLIC, ACC_STATIC
    Code:
      stack=3, locals=2, args_size=2
         0: getstatic     #22                 // Field coursier/core/Continue$.MODULE$:Lcoursier/core/Continue$;
         3: aload_0
         4: aload_1
         5: invokevirtual #24                 // Method coursier/core/Continue$.apply:(Lcoursier/core/Resolution;Lscala/Function1;)Lcoursier/core/Continue;
         8: areturn
    Signature: #16                          // (Lcoursier/core/Resolution;Lscala/Function1<Lcoursier/core/Resolution;Lcoursier/core/ResolutionProcess;>;)Lcoursier/core/Continue;
    MethodParameters:
      Name                           Flags
      current                        final
      cont                           final

  public coursier.core.Resolution current();
    descriptor: ()Lcoursier/core/Resolution;
    flags: (0x0001) ACC_PUBLIC
    Code:
      stack=1, locals=1, args_size=1
         0: aload_0
         1: getfield      #27                 // Field current:Lcoursier/core/Resolution;
         4: areturn
      LineNumberTable:
        line 136: 0
      LocalVariableTable:
        Start  Length  Slot  Name   Signature
            0       5     0  this   Lcoursier/core/Continue;

  public scala.Function1<coursier.core.Resolution, coursier.core.ResolutionProcess> cont();
    descriptor: ()Lscala/Function1;
    flags: (0x0001) ACC_PUBLIC
    Code:
      stack=1, locals=1, args_size=1
         0: aload_0
         1: getfield      #33                 // Field cont:Lscala/Function1;
         4: areturn
      LineNumberTable:
        line 136: 0
      LocalVariableTable:
        Start  Length  Slot  Name   Signature
            0       5     0  this   Lcoursier/core/Continue;
    Signature: #31                          // ()Lscala/Function1<Lcoursier/core/Resolution;Lcoursier/core/ResolutionProcess;>;

  public coursier.core.ResolutionProcess next();
    descriptor: ()Lcoursier/core/ResolutionProcess;
    flags: (0x0001) ACC_PUBLIC
    Code:
      stack=2, locals=1, args_size=1
         0: aload_0
         1: invokevirtual #37                 // Method cont:()Lscala/Function1;
         4: aload_0
         5: invokevirtual #39                 // Method current:()Lcoursier/core/Resolution;
         8: invokeinterface #44,  2           // InterfaceMethod scala/Function1.apply:(Ljava/lang/Object;)Ljava/lang/Object;
        13: checkcast     #4                  // class coursier/core/ResolutionProcess
        16: areturn
      LineNumberTable:
        line 141: 0
      LocalVariableTable:
        Start  Length  Slot  Name   Signature
            0      17     0  this   Lcoursier/core/Continue;

  public coursier.core.ResolutionProcess nextNoCont();
    descriptor: ()Lcoursier/core/ResolutionProcess;
    flags: (0x0001) ACC_PUBLIC
    Code:
      stack=1, locals=5, args_size=1
         0: aload_0
         1: invokevirtual #47                 // Method next:()Lcoursier/core/ResolutionProcess;
         4: astore_3
         5: aload_3
         6: instanceof    #2                  // class coursier/core/Continue
         9: ifeq          24
        12: aload_3
        13: checkcast     #2                  // class coursier/core/Continue
        16: astore        4
        18: aload         4
        20: astore_0
        21: goto          0
        24: goto          27
        27: aload_3
        28: astore_2
        29: goto          32
        32: aload_2
        33: areturn
      StackMapTable: number_of_entries = 4
        frame_type = 0 /* same */
        frame_type = 254 /* append */
          offset_delta = 23
          locals = [ top, top, class coursier/core/ResolutionProcess ]
        frame_type = 2 /* same */
        frame_type = 255 /* full_frame */
          offset_delta = 4
          locals = [ class coursier/core/Continue, top, class coursier/core/ResolutionProcess, class coursier/core/ResolutionProcess ]
          stack = []
      LineNumberTable:
        line 144: 0
        line 145: 5
        line 146: 27
        line 144: 32
      LocalVariableTable:
        Start  Length  Slot  Name   Signature
            0      34     0  this   Lcoursier/core/Continue;

  public coursier.core.Continue withCurrent(coursier.core.Resolution);
    descriptor: (Lcoursier/core/Resolution;)Lcoursier/core/Continue;
    flags: (0x0001) ACC_PUBLIC
    Code:
      stack=4, locals=2, args_size=2
         0: new           #2                  // class coursier/core/Continue
         3: dup
         4: aload_1
         5: aload_0
         6: invokevirtual #37                 // Method cont:()Lscala/Function1;
         9: invokespecial #53                 // Method "<init>":(Lcoursier/core/Resolution;Lscala/Function1;)V
        12: areturn
      LineNumberTable:
        line 136: 0
      LocalVariableTable:
        Start  Length  Slot  Name   Signature
            0      13     0  this   Lcoursier/core/Continue;
            0      13     1 current   Lcoursier/core/Resolution;
    MethodParameters:
      Name                           Flags
      current                        final

  public coursier.core.Continue withCont(scala.Function1<coursier.core.Resolution, coursier.core.ResolutionProcess>);
    descriptor: (Lscala/Function1;)Lcoursier/core/Continue;
    flags: (0x0001) ACC_PUBLIC
    Code:
      stack=4, locals=2, args_size=2
         0: new           #2                  // class coursier/core/Continue
         3: dup
         4: aload_0
         5: invokevirtual #39                 // Method current:()Lcoursier/core/Resolution;
         8: aload_1
         9: invokespecial #53                 // Method "<init>":(Lcoursier/core/Resolution;Lscala/Function1;)V
        12: areturn
      LineNumberTable:
        line 136: 0
      LocalVariableTable:
        Start  Length  Slot  Name   Signature
            0      13     0  this   Lcoursier/core/Continue;
            0      13     1  cont   Lscala/Function1;
    Signature: #56                          // (Lscala/Function1<Lcoursier/core/Resolution;Lcoursier/core/ResolutionProcess;>;)Lcoursier/core/Continue;
    MethodParameters:
      Name                           Flags
      cont                           final

  public java.lang.String toString();
    descriptor: ()Ljava/lang/String;
    flags: (0x0001) ACC_PUBLIC
    Code:
      stack=3, locals=2, args_size=1
         0: new           #60                 // class java/lang/StringBuilder
         3: dup
         4: ldc           #62                 // String Continue(
         6: invokespecial #65                 // Method java/lang/StringBuilder."<init>":(Ljava/lang/String;)V
         9: astore_1
        10: aload_1
        11: aload_0
        12: invokevirtual #39                 // Method current:()Lcoursier/core/Resolution;
        15: invokestatic  #71                 // Method java/lang/String.valueOf:(Ljava/lang/Object;)Ljava/lang/String;
        18: invokevirtual #75                 // Method java/lang/StringBuilder.append:(Ljava/lang/String;)Ljava/lang/StringBuilder;
        21: pop
        22: aload_1
        23: ldc           #77                 // String ,
        25: invokevirtual #75                 // Method java/lang/StringBuilder.append:(Ljava/lang/String;)Ljava/lang/StringBuilder;
        28: pop
        29: aload_1
        30: aload_0
        31: invokevirtual #37                 // Method cont:()Lscala/Function1;
        34: invokestatic  #71                 // Method java/lang/String.valueOf:(Ljava/lang/Object;)Ljava/lang/String;
        37: invokevirtual #75                 // Method java/lang/StringBuilder.append:(Ljava/lang/String;)Ljava/lang/StringBuilder;
        40: pop
        41: aload_1
        42: ldc           #79                 // String )
        44: invokevirtual #75                 // Method java/lang/StringBuilder.append:(Ljava/lang/String;)Ljava/lang/StringBuilder;
        47: pop
        48: aload_1
        49: invokevirtual #81                 // Method java/lang/StringBuilder.toString:()Ljava/lang/String;
        52: areturn
      LineNumberTable:
        line 136: 0
      LocalVariableTable:
        Start  Length  Slot  Name   Signature
           10      42     1     b   Ljava/lang/StringBuilder;
            0      53     0  this   Lcoursier/core/Continue;

  public boolean canEqual(java.lang.Object);
    descriptor: (Ljava/lang/Object;)Z
    flags: (0x0001) ACC_PUBLIC
    Code:
      stack=1, locals=2, args_size=2
         0: aload_1
         1: ifnull        15
         4: aload_1
         5: instanceof    #2                  // class coursier/core/Continue
         8: ifeq          15
        11: iconst_1
        12: goto          16
        15: iconst_0
        16: ireturn
      StackMapTable: number_of_entries = 2
        frame_type = 15 /* same */
        frame_type = 64 /* same_locals_1_stack_item */
          stack = [ int ]
      LineNumberTable:
        line 136: 0
      LocalVariableTable:
        Start  Length  Slot  Name   Signature
            0      17     0  this   Lcoursier/core/Continue;
            0      17     1   obj   Ljava/lang/Object;
    MethodParameters:
      Name                           Flags
      obj                            final

  public boolean equals(java.lang.Object);
    descriptor: (Ljava/lang/Object;)Z
    flags: (0x0001) ACC_PUBLIC
    Code:
      stack=2, locals=5, args_size=2
         0: aload_0
         1: aload_1
         2: if_acmpeq     89
         5: aload_0
         6: aload_1
         7: invokevirtual #90                 // Method canEqual:(Ljava/lang/Object;)Z
        10: ifeq          93
        13: aload_1
        14: checkcast     #2                  // class coursier/core/Continue
        17: astore_2
        18: iconst_1
        19: ifeq          85
        22: aload_0
        23: invokevirtual #39                 // Method current:()Lcoursier/core/Resolution;
        26: aload_2
        27: invokevirtual #39                 // Method current:()Lcoursier/core/Resolution;
        30: astore_3
        31: dup
        32: ifnonnull     43
        35: pop
        36: aload_3
        37: ifnull        50
        40: goto          85
        43: aload_3
        44: invokevirtual #96                 // Method java/lang/Object.equals:(Ljava/lang/Object;)Z
        47: ifeq          85
        50: aload_0
        51: invokevirtual #37                 // Method cont:()Lscala/Function1;
        54: aload_2
        55: invokevirtual #37                 // Method cont:()Lscala/Function1;
        58: astore        4
        60: dup
        61: ifnonnull     73
        64: pop
        65: aload         4
        67: ifnull        81
        70: goto          85
        73: aload         4
        75: invokevirtual #96                 // Method java/lang/Object.equals:(Ljava/lang/Object;)Z
        78: ifeq          85
        81: iconst_1
        82: goto          86
        85: iconst_0
        86: ifeq          93
        89: iconst_1
        90: goto          94
        93: iconst_0
        94: ireturn
      StackMapTable: number_of_entries = 9
        frame_type = 255 /* full_frame */
          offset_delta = 43
          locals = [ class coursier/core/Continue, class java/lang/Object, class coursier/core/Continue, class coursier/core/Resolution ]
          stack = [ class coursier/core/Resolution ]
        frame_type = 6 /* same */
        frame_type = 255 /* full_frame */
          offset_delta = 22
          locals = [ class coursier/core/Continue, class java/lang/Object, class coursier/core/Continue, class coursier/core/Resolution, class scala/Function1 ]
          stack = [ class scala/Function1 ]
        frame_type = 7 /* same */
        frame_type = 249 /* chop */
          offset_delta = 3
        frame_type = 64 /* same_locals_1_stack_item */
          stack = [ int ]
        frame_type = 250 /* chop */
          offset_delta = 2
        frame_type = 3 /* same */
        frame_type = 64 /* same_locals_1_stack_item */
          stack = [ int ]
      LineNumberTable:
        line 136: 0
      LocalVariableTable:
        Start  Length  Slot  Name   Signature
           18      68     2 other   Lcoursier/core/Continue;
            0      95     0  this   Lcoursier/core/Continue;
            0      95     1   obj   Ljava/lang/Object;
    MethodParameters:
      Name                           Flags
      obj                            final

  public int hashCode();
    descriptor: ()I
    flags: (0x0001) ACC_PUBLIC
    Code:
      stack=2, locals=2, args_size=1
         0: bipush        17
         2: ldc           #101                // String Continue
         4: invokestatic  #107                // Method scala/runtime/Statics.anyHash:(Ljava/lang/Object;)I
         7: iadd
         8: istore_1
         9: bipush        37
        11: iload_1
        12: imul
        13: aload_0
        14: invokevirtual #39                 // Method current:()Lcoursier/core/Resolution;
        17: invokestatic  #107                // Method scala/runtime/Statics.anyHash:(Ljava/lang/Object;)I
        20: iadd
        21: istore_1
        22: bipush        37
        24: iload_1
        25: imul
        26: aload_0
        27: invokevirtual #37                 // Method cont:()Lscala/Function1;
        30: invokestatic  #107                // Method scala/runtime/Statics.anyHash:(Ljava/lang/Object;)I
        33: iadd
        34: istore_1
        35: bipush        37
        37: iload_1
        38: imul
        39: ireturn
      LineNumberTable:
        line 136: 0
      LocalVariableTable:
        Start  Length  Slot  Name   Signature
            9      30     1  code   I
            0      40     0  this   Lcoursier/core/Continue;

  private scala.Tuple2<coursier.core.Resolution, scala.Function1<coursier.core.Resolution, coursier.core.ResolutionProcess>> tuple();
    descriptor: ()Lscala/Tuple2;
    flags: (0x0002) ACC_PRIVATE
    Code:
      stack=4, locals=1, args_size=1
         0: new           #114                // class scala/Tuple2
         3: dup
         4: aload_0
         5: invokevirtual #39                 // Method current:()Lcoursier/core/Resolution;
         8: aload_0
         9: invokevirtual #37                 // Method cont:()Lscala/Function1;
        12: invokespecial #117                // Method scala/Tuple2."<init>":(Ljava/lang/Object;Ljava/lang/Object;)V
        15: areturn
      LineNumberTable:
        line 136: 0
      LocalVariableTable:
        Start  Length  Slot  Name   Signature
            0      16     0  this   Lcoursier/core/Continue;
    Signature: #112                         // ()Lscala/Tuple2<Lcoursier/core/Resolution;Lscala/Function1<Lcoursier/core/Resolution;Lcoursier/core/ResolutionProcess;>;>;

  public java.lang.String productPrefix();
    descriptor: ()Ljava/lang/String;
    flags: (0x0001) ACC_PUBLIC
    Code:
      stack=1, locals=1, args_size=1
         0: ldc           #101                // String Continue
         2: areturn
      LineNumberTable:
        line 136: 0
      LocalVariableTable:
        Start  Length  Slot  Name   Signature
            0       3     0  this   Lcoursier/core/Continue;

  public int productArity();
    descriptor: ()I
    flags: (0x0001) ACC_PUBLIC
    Code:
      stack=1, locals=1, args_size=1
         0: iconst_2
         1: ireturn
      LineNumberTable:
        line 136: 0
      LocalVariableTable:
        Start  Length  Slot  Name   Signature
            0       2     0  this   Lcoursier/core/Continue;

  public java.lang.Object productElement(int);
    descriptor: (I)Ljava/lang/Object;
    flags: (0x0001) ACC_PUBLIC
    Code:
      stack=3, locals=3, args_size=2
         0: iload_1
         1: istore_2
         2: iload_2
         3: tableswitch   { // 0 to 1
                       0: 24
                       1: 31
                 default: 38
            }
        24: aload_0
        25: invokevirtual #39                 // Method current:()Lcoursier/core/Resolution;
        28: goto          53
        31: aload_0
        32: invokevirtual #37                 // Method cont:()Lscala/Function1;
        35: goto          53
        38: new           #124                // class java/lang/IndexOutOfBoundsException
        41: dup
        42: iload_2
        43: invokestatic  #130                // Method scala/runtime/BoxesRunTime.boxToInteger:(I)Ljava/lang/Integer;
        46: invokevirtual #131                // Method java/lang/Object.toString:()Ljava/lang/String;
        49: invokespecial #132                // Method java/lang/IndexOutOfBoundsException."<init>":(Ljava/lang/String;)V
        52: athrow
        53: areturn
      StackMapTable: number_of_entries = 4
        frame_type = 252 /* append */
          offset_delta = 24
          locals = [ int ]
        frame_type = 6 /* same */
        frame_type = 6 /* same */
        frame_type = 78 /* same_locals_1_stack_item */
          stack = [ class java/lang/Object ]
      LineNumberTable:
        line 136: 0
      LocalVariableTable:
        Start  Length  Slot  Name   Signature
            0      54     0  this   Lcoursier/core/Continue;
            0      54     1     n   I
    MethodParameters:
      Name                           Flags
      n                              final

  public java.lang.String productElementName(int);
    descriptor: (I)Ljava/lang/String;
    flags: (0x0001) ACC_PUBLIC
    Code:
      stack=3, locals=3, args_size=2
         0: iload_1
         1: istore_2
         2: iload_2
         3: tableswitch   { // 0 to 1
                       0: 24
                       1: 29
                 default: 34
            }
        24: ldc           #135                // String current
        26: goto          49
        29: ldc           #136                // String cont
        31: goto          49
        34: new           #124                // class java/lang/IndexOutOfBoundsException
        37: dup
        38: iload_2
        39: invokestatic  #130                // Method scala/runtime/BoxesRunTime.boxToInteger:(I)Ljava/lang/Integer;
        42: invokevirtual #131                // Method java/lang/Object.toString:()Ljava/lang/String;
        45: invokespecial #132                // Method java/lang/IndexOutOfBoundsException."<init>":(Ljava/lang/String;)V
        48: athrow
        49: areturn
      StackMapTable: number_of_entries = 4
        frame_type = 252 /* append */
          offset_delta = 24
          locals = [ int ]
        frame_type = 4 /* same */
        frame_type = 4 /* same */
        frame_type = 78 /* same_locals_1_stack_item */
          stack = [ class java/lang/String ]
      LineNumberTable:
        line 136: 0
      LocalVariableTable:
        Start  Length  Slot  Name   Signature
            0      50     0  this   Lcoursier/core/Continue;
            0      50     1     n   I
    MethodParameters:
      Name                           Flags
      n                              final

  public coursier.core.Continue(coursier.core.Resolution, scala.Function1<coursier.core.Resolution, coursier.core.ResolutionProcess>);
    descriptor: (Lcoursier/core/Resolution;Lscala/Function1;)V
    flags: (0x0001) ACC_PUBLIC
    Code:
      stack=2, locals=3, args_size=3
         0: aload_0
         1: aload_1
         2: putfield      #27                 // Field current:Lcoursier/core/Resolution;
         5: aload_0
         6: aload_2
         7: putfield      #33                 // Field cont:Lscala/Function1;
        10: aload_0
        11: invokespecial #140                // Method coursier/core/ResolutionProcess."<init>":()V
        14: return
      LineNumberTable:
        line 136: 0
        line 139: 10
        line 136: 14
      LocalVariableTable:
        Start  Length  Slot  Name   Signature
            0      15     0  this   Lcoursier/core/Continue;
            0      15     1 current   Lcoursier/core/Resolution;
            0      15     2  cont   Lscala/Function1;
    Signature: #137                         // (Lcoursier/core/Resolution;Lscala/Function1<Lcoursier/core/Resolution;Lcoursier/core/ResolutionProcess;>;)V
    MethodParameters:
      Name                           Flags
      current                        final
      cont                           final
}
SourceFile: "ResolutionProcess.scala"
RuntimeVisibleAnnotations:
  0: #6(#7=s#8)
    scala.reflect.ScalaSignature(
      bytes="\u0006\u0005\u0005=b\u0001\u0002\r\u001a\u0005yA\u0001\"\u000e\u0001\u0003\u0006\u0004%\tA\u000e\u0005\tu\u0001\u0011\t\u0011)A\u0005o!A1\b\u0001BC\u0002\u0013\u0005A\b\u0003\u0005A\u0001\t\u0005\t\u0015!\u0003>\u0011\u0015\t\u0005\u0001\"\u0001C\u0011\u00151\u0005\u0001\"\u0001H\u0011\u0015A\u0005\u0001\"\u0001H\u0011\u0015\u0001\u0006\u0001\"\u0001R\u0011\u0015\u0019\u0006\u0001\"\u0001U\u0011\u00151\u0006\u0001\"\u0011X\u0011\u0015\u0001\u0007\u0001\"\u0011b\u0011\u0015Q\u0007\u0001\"\u0011l\u0011\u0015i\u0007\u0001\"\u0011o\u0011\u0015\u0011\b\u0001\"\u0003t\u0011\u00159\b\u0001\"\u0011y\u0011\u0015I\b\u0001\"\u0011{\u0011\u0015Y\b\u0001\"\u0011}\u0011\u0019y\b\u0001\"\u0011\u0002\u0002\u001d9\u0011QA\r\t\u0002\u0005\u001daA\u0002\r\u001a\u0011\u0003\tI\u0001\u0003\u0004B)\u0011\u0005\u00111\u0004\u0005\b\u0003;!B\u0011AA\u0010\u0011%\t)\u0003FA\u0001\n\u0013\t9C\u0001\u0005D_:$\u0018N\\;f\u0015\tQ2$\u0001\u0003d_J,\'\"\u0001\u000f\u0002\u0011\r|WO]:jKJ\u001c\u0001a\u0005\u0003\u0001?\rJ\u0003C\u0001\u0011\"\u001b\u0005I\u0012B\u0001\u0012\u001a\u0005E\u0011Vm]8mkRLwN\u001c)s_\u000e,7o\u001d\t\u0003I\u001dj\u0011!\n\u0006\u0002M\u0005)1oY1mC&\u0011\u0001&\n\u0002\b!J|G-^2u!\tQ#G\u0004\u0002,a9\u0011AfL\u0007\u0002[)\u0011a&H\u0001\u0007yI|w\u000e\u001e \n\u0003\u0019J!!M\u0013\u0002\u000fA\f7m[1hK&\u00111\u0007\u000e\u0002\r\'\u0016\u0014\u0018.\u00197ju\u0006\u0014G.\u001a\u0006\u0003c\u0015\nqaY;se\u0016tG/F\u00018!\t\u0001\u0003(\u0003\u0002:3\tQ!+Z:pYV$\u0018n\u001c8\u0002\u0011\r,(O]3oi\u0002\nAaY8oiV\tQ\b\u0005\u0003%}]z\u0012BA &\u0005%1UO\\2uS>t\u0017\'A\u0003d_:$\b%\u0001\u0004=S:LGO\u0010\u000b\u0004\u0007\u0012+\u0005C\u0001\u0011\u0001\u0011\u0015)T\u00011\u00018\u0011\u0015YT\u00011\u0001>\u0003\u0011qW\r\u001f;\u0016\u0003}\t!B\\3yi:{7i\u001c8uQ\t9!\n\u0005\u0002L\u001d6\tAJ\u0003\u0002NK\u0005Q\u0011M\u001c8pi\u0006$\u0018n\u001c8\n\u0005=c%a\u0002;bS2\u0014XmY\u0001\fo&$\bnQ;se\u0016tG\u000f\u0006\u0002D%\")Q\u0007\u0003a\u0001o\u0005Aq/\u001b;i\u0007>tG\u000f\u0006\u0002D+\")1(\u0003a\u0001{\u0005AAo\\*ue&tw\rF\u0001Y!\tIf,D\u0001[\u0015\tYF,\u0001\u0003mC:<\'\"A/\u0002\t)\fg/Y\u0005\u0003?j\u0013aa\u0015;sS:<\u0017\u0001C2b]\u0016\u000bX/\u00197\u0015\u0005\t,\u0007C\u0001\u0013d\u0013\t!WEA\u0004C_>dW-\u00198\t\u000b\u0019\\\u0001\u0019A4\u0002\u0007=\u0014\'\u000e\u0005\u0002%Q&\u0011\u0011.\n\u0002\u0004\u0003:L\u0018AB3rk\u0006d7\u000f\u0006\u0002cY\")a\r\u0004a\u0001O\u0006A\u0001.Y:i\u0007>$W\rF\u0001p!\t!\u0003/\u0003\u0002rK\t\u0019\u0011J\u001c;\u0002\u000bQ,\b\u000f\\3\u0016\u0003Q\u0004B\u0001J;8{%\u0011a/\n\u0002\u0007)V\u0004H.\u001a\u001a\u0002\u001bA\u0014x\u000eZ;diB\u0013XMZ5y+\u0005A\u0016\u0001\u00049s_\u0012,8\r^!sSRLX#A8\u0002\u001dA\u0014x\u000eZ;di\u0016cW-\\3oiR\u0011q- \u0005\u0006}F\u0001\ra\\\u0001\u0002]\u0006\u0011\u0002O]8ek\u000e$X\t\\3nK:$h*Y7f)\rA\u00161\u0001\u0005\u0006}J\u0001\ra\\\u0001\t\u0007>tG/\u001b8vKB\u0011\u0001\u0005F\n\u0006)\u0005-\u0011\u0011\u0003\t\u0004I\u00055\u0011bAA\bK\t1\u0011I\\=SK\u001a\u0004B!a\u0005\u0002\u001a5\u0011\u0011Q\u0003\u0006\u0004\u0003/a\u0016AA5p\u0013\r\u0019\u0014Q\u0003\u000b\u0003\u0003\u000f\tQ!\u00199qYf$RaQA\u0011\u0003GAQ!\u000e\fA\u0002]BQa\u000f\fA\u0002u\nAb\u001e:ji\u0016\u0014V\r\u001d7bG\u0016$\"!!\u000b\u0011\u0007e\u000bY#C\u0002\u0002.i\u0013aa\u00142kK\u000e$\b"
    )
  ScalaInlineInfo: length = 0x54 (unknown attribute)
   01 01 00 10 00 32 00 33 01 00 54 00 55 01 00 0B
   00 1E 01 00 09 00 19 01 00 58 00 55 01 00 62 00
   63 01 00 22 00 23 01 00 2D 00 23 01 00 77 00 63
   01 00 78 00 79 01 00 85 00 86 01 00 76 00 3A 01
   00 39 00 3A 01 00 6E 00 6F 01 00 36 00 37 01 00
   30 00 31 01
  ScalaSig: length = 0x3 (unknown attribute)
   05 02 00
