Classfile /Users/mw/Projects/slang-braindump/.jar/jar11/assemble/slang-braindump/assemble/content/coursier/core/DependencySet$Sets$.class
  Last modified May 29, 2022; size 2885 bytes
  SHA-256 checksum 21c4cd8ac422a7eb887eef60ee5780d4e67491521277855a75b6ebe2c31c8352
  Compiled from "DependencySet.scala"
public class coursier.core.DependencySet$Sets$ implements java.io.Serializable
  minor version: 0
  major version: 52
  flags: (0x0021) ACC_PUBLIC, ACC_SUPER
  this_class: #2                          // coursier/core/DependencySet$Sets$
  super_class: #4                         // java/lang/Object
  interfaces: 1, fields: 1, methods: 6, attributes: 4
Constant pool:
    #1 = Utf8               coursier/core/DependencySet$Sets$
    #2 = Class              #1            // coursier/core/DependencySet$Sets$
    #3 = Utf8               java/lang/Object
    #4 = Class              #3            // java/lang/Object
    #5 = Utf8               java/io/Serializable
    #6 = Class              #5            // java/io/Serializable
    #7 = Utf8               DependencySet.scala
    #8 = Utf8               coursier/core/DependencySet$Sets
    #9 = Class              #8            // coursier/core/DependencySet$Sets
   #10 = Utf8               coursier/core/DependencySet
   #11 = Class              #10           // coursier/core/DependencySet
   #12 = Utf8               Sets
   #13 = Utf8
   #14 = Utf8               MODULE$
   #15 = Utf8               Lcoursier/core/DependencySet$Sets$;
   #16 = Utf8               <clinit>
   #17 = Utf8               ()V
   #18 = Utf8               <init>
   #19 = NameAndType        #18:#17       // "<init>":()V
   #20 = Methodref          #2.#19        // coursier/core/DependencySet$Sets$."<init>":()V
   #21 = NameAndType        #14:#15       // MODULE$:Lcoursier/core/DependencySet$Sets$;
   #22 = Fieldref           #2.#21        // coursier/core/DependencySet$Sets$.MODULE$:Lcoursier/core/DependencySet$Sets$;
   #23 = Utf8               empty
   #24 = Utf8               ()Lcoursier/core/DependencySet$Sets;
   #25 = Utf8               <T:Ljava/lang/Object;>()Lcoursier/core/DependencySet$Sets<TT;>;
   #26 = Utf8               scala/collection/immutable/IntMap$
   #27 = Class              #26           // scala/collection/immutable/IntMap$
   #28 = Utf8               Lscala/collection/immutable/IntMap$;
   #29 = NameAndType        #14:#28       // MODULE$:Lscala/collection/immutable/IntMap$;
   #30 = Fieldref           #27.#29       // scala/collection/immutable/IntMap$.MODULE$:Lscala/collection/immutable/IntMap$;
   #31 = Utf8               ()Lscala/collection/immutable/IntMap;
   #32 = NameAndType        #23:#31       // empty:()Lscala/collection/immutable/IntMap;
   #33 = Methodref          #27.#32       // scala/collection/immutable/IntMap$.empty:()Lscala/collection/immutable/IntMap;
   #34 = Utf8               scala/Predef$
   #35 = Class              #34           // scala/Predef$
   #36 = Utf8               Lscala/Predef$;
   #37 = NameAndType        #14:#36       // MODULE$:Lscala/Predef$;
   #38 = Fieldref           #35.#37       // scala/Predef$.MODULE$:Lscala/Predef$;
   #39 = Utf8               Map
   #40 = Utf8               ()Lscala/collection/immutable/Map$;
   #41 = NameAndType        #39:#40       // Map:()Lscala/collection/immutable/Map$;
   #42 = Methodref          #35.#41       // scala/Predef$.Map:()Lscala/collection/immutable/Map$;
   #43 = Utf8               scala/collection/immutable/Map$
   #44 = Class              #43           // scala/collection/immutable/Map$
   #45 = Utf8               ()Lscala/collection/immutable/Map;
   #46 = NameAndType        #23:#45       // empty:()Lscala/collection/immutable/Map;
   #47 = Methodref          #44.#46       // scala/collection/immutable/Map$.empty:()Lscala/collection/immutable/Map;
   #48 = Utf8               apply
   #49 = Utf8               (Lscala/collection/immutable/IntMap;Lscala/collection/immutable/Map;Lscala/collection/immutable/Map;)Lcoursier/core/DependencySet$Sets;
   #50 = NameAndType        #48:#49       // apply:(Lscala/collection/immutable/IntMap;Lscala/collection/immutable/Map;Lscala/collection/immutable/Map;)Lcoursier/core/DependencySet$Sets;
   #51 = Methodref          #2.#50        // coursier/core/DependencySet$Sets$.apply:(Lscala/collection/immutable/IntMap;Lscala/collection/immutable/Map;Lscala/collection/immutable/Map;)Lcoursier/core/DependencySet$Sets;
   #52 = Utf8               this
   #53 = Utf8               <T:Ljava/lang/Object;>(Lscala/collection/immutable/IntMap<Lscala/collection/immutable/Set<TT;>;>;Lscala/collection/immutable/Map<TT;Lscala/collection/immutable/Set<TT;>;>;Lscala/collection/immutable/Map<TT;TT;>;)Lcoursier/core/DependencySet$Sets<TT;>;
   #54 = Utf8               required
   #55 = Utf8               children
   #56 = Utf8               parents
   #57 = Utf8               (Lscala/collection/immutable/IntMap;Lscala/collection/immutable/Map;Lscala/collection/immutable/Map;)V
   #58 = NameAndType        #18:#57       // "<init>":(Lscala/collection/immutable/IntMap;Lscala/collection/immutable/Map;Lscala/collection/immutable/Map;)V
   #59 = Methodref          #9.#58        // coursier/core/DependencySet$Sets."<init>":(Lscala/collection/immutable/IntMap;Lscala/collection/immutable/Map;Lscala/collection/immutable/Map;)V
   #60 = Utf8               Lscala/collection/immutable/IntMap;
   #61 = Utf8               Lscala/collection/immutable/Map;
   #62 = Utf8               unapply
   #63 = Utf8               (Lcoursier/core/DependencySet$Sets;)Lscala/Option;
   #64 = Utf8               <T:Ljava/lang/Object;>(Lcoursier/core/DependencySet$Sets<TT;>;)Lscala/Option<Lscala/Tuple3<Lscala/collection/immutable/IntMap<Lscala/collection/immutable/Set<TT;>;>;Lscala/collection/immutable/Map<TT;Lscala/collection/immutable/Set<TT;>;>;Lscala/collection/immutable/Map<TT;TT;>;>;>;
   #65 = Utf8               x$0
   #66 = Utf8               scala/None$
   #67 = Class              #66           // scala/None$
   #68 = Utf8               Lscala/None$;
   #69 = NameAndType        #14:#68       // MODULE$:Lscala/None$;
   #70 = Fieldref           #67.#69       // scala/None$.MODULE$:Lscala/None$;
   #71 = Utf8               scala/Some
   #72 = Class              #71           // scala/Some
   #73 = Utf8               scala/Tuple3
   #74 = Class              #73           // scala/Tuple3
   #75 = NameAndType        #54:#31       // required:()Lscala/collection/immutable/IntMap;
   #76 = Methodref          #9.#75        // coursier/core/DependencySet$Sets.required:()Lscala/collection/immutable/IntMap;
   #77 = NameAndType        #55:#45       // children:()Lscala/collection/immutable/Map;
   #78 = Methodref          #9.#77        // coursier/core/DependencySet$Sets.children:()Lscala/collection/immutable/Map;
   #79 = NameAndType        #56:#45       // parents:()Lscala/collection/immutable/Map;
   #80 = Methodref          #9.#79        // coursier/core/DependencySet$Sets.parents:()Lscala/collection/immutable/Map;
   #81 = Utf8               (Ljava/lang/Object;Ljava/lang/Object;Ljava/lang/Object;)V
   #82 = NameAndType        #18:#81       // "<init>":(Ljava/lang/Object;Ljava/lang/Object;Ljava/lang/Object;)V
   #83 = Methodref          #74.#82       // scala/Tuple3."<init>":(Ljava/lang/Object;Ljava/lang/Object;Ljava/lang/Object;)V
   #84 = Utf8               (Ljava/lang/Object;)V
   #85 = NameAndType        #18:#84       // "<init>":(Ljava/lang/Object;)V
   #86 = Methodref          #72.#85       // scala/Some."<init>":(Ljava/lang/Object;)V
   #87 = Utf8               scala/Option
   #88 = Class              #87           // scala/Option
   #89 = Utf8               Lcoursier/core/DependencySet$Sets;
   #90 = Utf8               writeReplace
   #91 = Utf8               ()Ljava/lang/Object;
   #92 = Utf8               scala/runtime/ModuleSerializationProxy
   #93 = Class              #92           // scala/runtime/ModuleSerializationProxy
   #94 = Utf8               (Ljava/lang/Class;)V
   #95 = NameAndType        #18:#94       // "<init>":(Ljava/lang/Class;)V
   #96 = Methodref          #93.#95       // scala/runtime/ModuleSerializationProxy."<init>":(Ljava/lang/Class;)V
   #97 = Methodref          #4.#19        // java/lang/Object."<init>":()V
   #98 = Utf8               Code
   #99 = Utf8               LineNumberTable
  #100 = Utf8               LocalVariableTable
  #101 = Utf8               Signature
  #102 = Utf8               MethodParameters
  #103 = Utf8               StackMapTable
  #104 = Utf8               InnerClasses
  #105 = Utf8               SourceFile
  #106 = Utf8               ScalaInlineInfo
  #107 = Utf8               Scala
{
  public static final coursier.core.DependencySet$Sets$ MODULE$;
    descriptor: Lcoursier/core/DependencySet$Sets$;
    flags: (0x0019) ACC_PUBLIC, ACC_STATIC, ACC_FINAL

  public static {};
    descriptor: ()V
    flags: (0x0009) ACC_PUBLIC, ACC_STATIC
    Code:
      stack=2, locals=0, args_size=0
         0: new           #2                  // class coursier/core/DependencySet$Sets$
         3: dup
         4: invokespecial #20                 // Method "<init>":()V
         7: putstatic     #22                 // Field MODULE$:Lcoursier/core/DependencySet$Sets$;
        10: return
      LineNumberTable:
        line 106: 0

  public <T extends java.lang.Object> coursier.core.DependencySet$Sets<T> empty();
    descriptor: ()Lcoursier/core/DependencySet$Sets;
    flags: (0x0001) ACC_PUBLIC
    Code:
      stack=4, locals=1, args_size=1
         0: aload_0
         1: getstatic     #30                 // Field scala/collection/immutable/IntMap$.MODULE$:Lscala/collection/immutable/IntMap$;
         4: invokevirtual #33                 // Method scala/collection/immutable/IntMap$.empty:()Lscala/collection/immutable/IntMap;
         7: getstatic     #38                 // Field scala/Predef$.MODULE$:Lscala/Predef$;
        10: invokevirtual #42                 // Method scala/Predef$.Map:()Lscala/collection/immutable/Map$;
        13: invokevirtual #47                 // Method scala/collection/immutable/Map$.empty:()Lscala/collection/immutable/Map;
        16: getstatic     #38                 // Field scala/Predef$.MODULE$:Lscala/Predef$;
        19: invokevirtual #42                 // Method scala/Predef$.Map:()Lscala/collection/immutable/Map$;
        22: invokevirtual #47                 // Method scala/collection/immutable/Map$.empty:()Lscala/collection/immutable/Map;
        25: invokevirtual #51                 // Method apply:(Lscala/collection/immutable/IntMap;Lscala/collection/immutable/Map;Lscala/collection/immutable/Map;)Lcoursier/core/DependencySet$Sets;
        28: areturn
      LineNumberTable:
        line 107: 0
      LocalVariableTable:
        Start  Length  Slot  Name   Signature
            0      29     0  this   Lcoursier/core/DependencySet$Sets$;
    Signature: #25                          // <T:Ljava/lang/Object;>()Lcoursier/core/DependencySet$Sets<TT;>;

  public <T extends java.lang.Object> coursier.core.DependencySet$Sets<T> apply(scala.collection.immutable.IntMap<scala.collection.immutable.Set<T>>, scala.collection.immutable.Map<T, scala.collection.immutable.Set<T>>, scala.collection.immutable.Map<T, T>);
    descriptor: (Lscala/collection/immutable/IntMap;Lscala/collection/immutable/Map;Lscala/collection/immutable/Map;)Lcoursier/core/DependencySet$Sets;
    flags: (0x0001) ACC_PUBLIC
    Code:
      stack=5, locals=4, args_size=4
         0: new           #9                  // class coursier/core/DependencySet$Sets
         3: dup
         4: aload_1
         5: aload_2
         6: aload_3
         7: invokespecial #59                 // Method coursier/core/DependencySet$Sets."<init>":(Lscala/collection/immutable/IntMap;Lscala/collection/immutable/Map;Lscala/collection/immutable/Map;)V
        10: areturn
      LineNumberTable:
        line 110: 0
      LocalVariableTable:
        Start  Length  Slot  Name   Signature
            0      11     0  this   Lcoursier/core/DependencySet$Sets$;
            0      11     1 required   Lscala/collection/immutable/IntMap;
            0      11     2 children   Lscala/collection/immutable/Map;
            0      11     3 parents   Lscala/collection/immutable/Map;
    Signature: #53                          // <T:Ljava/lang/Object;>(Lscala/collection/immutable/IntMap<Lscala/collection/immutable/Set<TT;>;>;Lscala/collection/immutable/Map<TT;Lscala/collection/immutable/Set<TT;>;>;Lscala/collection/immutable/Map<TT;TT;>;)Lcoursier/core/DependencySet$Sets<TT;>;
    MethodParameters:
      Name                           Flags
      required                       final
      children                       final
      parents                        final

  public <T extends java.lang.Object> scala.Option<scala.Tuple3<scala.collection.immutable.IntMap<scala.collection.immutable.Set<T>>, scala.collection.immutable.Map<T, scala.collection.immutable.Set<T>>, scala.collection.immutable.Map<T, T>>> unapply(coursier.core.DependencySet$Sets<T>);
    descriptor: (Lcoursier/core/DependencySet$Sets;)Lscala/Option;
    flags: (0x0001) ACC_PUBLIC
    Code:
      stack=7, locals=2, args_size=2
         0: aload_1
         1: ifnonnull     10
         4: getstatic     #70                 // Field scala/None$.MODULE$:Lscala/None$;
         7: goto          36
        10: new           #72                 // class scala/Some
        13: dup
        14: new           #74                 // class scala/Tuple3
        17: dup
        18: aload_1
        19: invokevirtual #76                 // Method coursier/core/DependencySet$Sets.required:()Lscala/collection/immutable/IntMap;
        22: aload_1
        23: invokevirtual #78                 // Method coursier/core/DependencySet$Sets.children:()Lscala/collection/immutable/Map;
        26: aload_1
        27: invokevirtual #80                 // Method coursier/core/DependencySet$Sets.parents:()Lscala/collection/immutable/Map;
        30: invokespecial #83                 // Method scala/Tuple3."<init>":(Ljava/lang/Object;Ljava/lang/Object;Ljava/lang/Object;)V
        33: invokespecial #86                 // Method scala/Some."<init>":(Ljava/lang/Object;)V
        36: areturn
      StackMapTable: number_of_entries = 2
        frame_type = 10 /* same */
        frame_type = 89 /* same_locals_1_stack_item */
          stack = [ class scala/Option ]
      LineNumberTable:
        line 110: 0
      LocalVariableTable:
        Start  Length  Slot  Name   Signature
            0      37     0  this   Lcoursier/core/DependencySet$Sets$;
            0      37     1   x$0   Lcoursier/core/DependencySet$Sets;
    Signature: #64                          // <T:Ljava/lang/Object;>(Lcoursier/core/DependencySet$Sets<TT;>;)Lscala/Option<Lscala/Tuple3<Lscala/collection/immutable/IntMap<Lscala/collection/immutable/Set<TT;>;>;Lscala/collection/immutable/Map<TT;Lscala/collection/immutable/Set<TT;>;>;Lscala/collection/immutable/Map<TT;TT;>;>;>;
    MethodParameters:
      Name                           Flags
      x$0                            final

  private java.lang.Object writeReplace();
    descriptor: ()Ljava/lang/Object;
    flags: (0x0002) ACC_PRIVATE
    Code:
      stack=3, locals=1, args_size=1
         0: new           #93                 // class scala/runtime/ModuleSerializationProxy
         3: dup
         4: ldc           #2                  // class coursier/core/DependencySet$Sets$
         6: invokespecial #96                 // Method scala/runtime/ModuleSerializationProxy."<init>":(Ljava/lang/Class;)V
         9: areturn
      LineNumberTable:
        line 106: 0
      LocalVariableTable:
        Start  Length  Slot  Name   Signature
            0      10     0  this   Lcoursier/core/DependencySet$Sets$;

  public coursier.core.DependencySet$Sets$();
    descriptor: ()V
    flags: (0x0001) ACC_PUBLIC
    Code:
      stack=1, locals=1, args_size=1
         0: aload_0
         1: invokespecial #97                 // Method java/lang/Object."<init>":()V
         4: return
      LineNumberTable:
        line 110: 0
        line 106: 4
      LocalVariableTable:
        Start  Length  Slot  Name   Signature
            0       5     0  this   Lcoursier/core/DependencySet$Sets$;
}
InnerClasses:
  public static final #12= #9 of #11;     // Sets=class coursier/core/DependencySet$Sets of class coursier/core/DependencySet
  public static #13= #2 of #11;           // =class coursier/core/DependencySet$Sets$ of class coursier/core/DependencySet
SourceFile: "DependencySet.scala"
  ScalaInlineInfo: length = 0x1D (unknown attribute)
   01 01 00 05 00 12 00 11 01 00 30 00 31 01 00 17
   00 18 01 00 3E 00 3F 01 00 5A 00 5B 01
  Scala: length = 0x0 (unknown attribute)

