Classfile /Users/mw/Projects/slang-braindump/.jar/jar11/assemble/slang-braindump/assemble/content/coursier/core/Done.class
  Last modified May 29, 2022; size 3948 bytes
  SHA-256 checksum cf4cd1298b97ac65c8b0872fbff54930f9857e637d11bfb480a5a3347b3c858d
  Compiled from "ResolutionProcess.scala"
public final class coursier.core.Done extends coursier.core.ResolutionProcess
  minor version: 0
  major version: 52
  flags: (0x0031) ACC_PUBLIC, ACC_FINAL, ACC_SUPER
  this_class: #2                          // coursier/core/Done
  super_class: #4                         // coursier/core/ResolutionProcess
  interfaces: 0, fields: 1, methods: 14, attributes: 4
Constant pool:
    #1 = Utf8               coursier/core/Done
    #2 = Class              #1            // coursier/core/Done
    #3 = Utf8               coursier/core/ResolutionProcess
    #4 = Class              #3            // coursier/core/ResolutionProcess
    #5 = Utf8               ResolutionProcess.scala
    #6 = Utf8               Lscala/reflect/ScalaSignature;
    #7 = Utf8               bytes
    #8 = Utf8               \u0006\u0005}4A\u0001F\u000b\u00035!A\u0011\u0007\u0001BC\u0002\u0013\u0005!\u0007\u0003\u00057\u0001\t\u0005\t\u0015!\u00034\u0011\u00159\u0004\u0001\"\u00019\u0011\u0015Y\u0004\u0001\"\u00013\u0011\u0015a\u0004\u0001\"\u0001>\u0011\u0015y\u0004\u0001\"\u0011A\u0011\u0015I\u0005\u0001\"\u0011K\u0011\u0015\u0019\u0006\u0001\"\u0011U\u0011\u00151\u0006\u0001\"\u0011X\u0011\u0015Y\u0006\u0001\"\u0003]\u0011\u0015\u0001\u0007\u0001\"\u0011b\u0011\u0015\u0011\u0007\u0001\"\u0011d\u0011\u0015!\u0007\u0001\"\u0011f\u0011\u0015A\u0007\u0001\"\u0011j\u000f\u0015YW\u0003#\u0001m\r\u0015!R\u0003#\u0001n\u0011\u00159\u0004\u0003\"\u0001w\u0011\u00159\b\u0003\"\u0001y\u0011\u001dQ\b#!A\u0005\nm\u0014A\u0001R8oK*\u0011acF\u0001\u0005G>\u0014XMC\u0001\u0019\u0003!\u0019w.\u001e:tS\u0016\u00148\u0001A\n\u0005\u0001myR\u0005\u0005\u0002\u001d;5\tQ#\u0003\u0002\u001f+\t\t\"+Z:pYV$\u0018n\u001c8Qe>\u001cWm]:\u0011\u0005\u0001\u001aS\"A\u0011\u000b\u0003\t\nQa]2bY\u0006L!\u0001J\u0011\u0003\u000fA\u0013x\u000eZ;diB\u0011aE\f\b\u0003O1r!\u0001K\u0016\u000e\u0003%R!AK\r\u0002\rq\u0012xn\u001c;?\u0013\u0005\u0011\u0013BA\u0017\"\u0003\u001d\u0001\u0018mY6bO\u0016L!a\f\u0019\u0003\u0019M+\'/[1mSj\f\'\r\\3\u000b\u00055\n\u0013A\u0003:fg>dW\u000f^5p]V\t1\u0007\u0005\u0002\u001di%\u0011Q\'\u0006\u0002\u000b%\u0016\u001cx\u000e\\;uS>t\u0017a\u0003:fg>dW\u000f^5p]\u0002\na\u0001P5oSRtDCA\u001d;!\ta\u0002\u0001C\u00032\u0007\u0001\u00071\'A\u0004dkJ\u0014XM\u001c;\u0002\u001d]LG\u000f\u001b*fg>dW\u000f^5p]R\u0011\u0011H\u0010\u0005\u0006c\u0015\u0001\raM\u0001\ti>\u001cFO]5oOR\t\u0011\t\u0005\u0002C\u000f6\t1I\u0003\u0002E\u000b\u0006!A.\u00198h\u0015\u00051\u0015\u0001\u00026bm\u0006L!\u0001S\"\u0003\rM#(/\u001b8h\u0003!\u0019\u0017M\\#rk\u0006dGCA&O!\t\u0001C*\u0003\u0002NC\t9!i\\8mK\u0006t\u0007\"B(\b\u0001\u0004\u0001\u0016aA8cUB\u0011\u0001%U\u0005\u0003%\u0006\u00121!\u00118z\u0003\u0019)\u0017/^1mgR\u00111*\u0016\u0005\u0006\u001f\"\u0001\r\u0001U\u0001\tQ\u0006\u001c\bnQ8eKR\t\u0001\f\u0005\u0002!3&\u0011!,\t\u0002\u0004\u0013:$\u0018!\u0002;va2,W#A/\u0011\u0007\u0001r6\'\u0003\u0002`C\t1A+\u001e9mKF\nQ\u0002\u001d:pIV\u001cG\u000f\u0015:fM&DX#A!\u0002\u0019A\u0014x\u000eZ;di\u0006\u0013\u0018\u000e^=\u0016\u0003a\u000ba\u0002\u001d:pIV\u001cG/\u00127f[\u0016tG\u000f\u0006\u0002QM\")q-\u0004a\u00011\u0006\ta.\u0001\nqe>$Wo\u0019;FY\u0016lWM\u001c;OC6,GCA!k\u0011\u00159g\u00021\u0001Y\u0003\u0011!uN\\3\u0011\u0005q\u00012c\u0001\tocB\u0011\u0001e\\\u0005\u0003a\u0006\u0012a!\u00118z%\u00164\u0007C\u0001:v\u001b\u0005\u0019(B\u0001;F\u0003\tIw.\u0003\u00020gR\tA.A\u0003baBd\u0017\u0010\u0006\u0002:s\")\u0011G\u0005a\u0001g\u0005aqO]5uKJ+\u0007\u000f\\1dKR\tA\u0010\u0005\u0002C{&\u0011ap\u0011\u0002\u0007\u001f\nTWm\u0019;
    #9 = Utf8               resolution
   #10 = Utf8               Lcoursier/core/Resolution;
   #11 = Utf8               apply
   #12 = Utf8               (Lcoursier/core/Resolution;)Lcoursier/core/Done;
   #13 = Utf8               coursier/core/Done$
   #14 = Class              #13           // coursier/core/Done$
   #15 = Utf8               MODULE$
   #16 = Utf8               Lcoursier/core/Done$;
   #17 = NameAndType        #15:#16       // MODULE$:Lcoursier/core/Done$;
   #18 = Fieldref           #14.#17       // coursier/core/Done$.MODULE$:Lcoursier/core/Done$;
   #19 = NameAndType        #11:#12       // apply:(Lcoursier/core/Resolution;)Lcoursier/core/Done;
   #20 = Methodref          #14.#19       // coursier/core/Done$.apply:(Lcoursier/core/Resolution;)Lcoursier/core/Done;
   #21 = Utf8               ()Lcoursier/core/Resolution;
   #22 = NameAndType        #9:#10        // resolution:Lcoursier/core/Resolution;
   #23 = Fieldref           #2.#22        // coursier/core/Done.resolution:Lcoursier/core/Resolution;
   #24 = Utf8               this
   #25 = Utf8               Lcoursier/core/Done;
   #26 = Utf8               current
   #27 = NameAndType        #9:#21        // resolution:()Lcoursier/core/Resolution;
   #28 = Methodref          #2.#27        // coursier/core/Done.resolution:()Lcoursier/core/Resolution;
   #29 = Utf8               withResolution
   #30 = Utf8               <init>
   #31 = Utf8               (Lcoursier/core/Resolution;)V
   #32 = NameAndType        #30:#31       // "<init>":(Lcoursier/core/Resolution;)V
   #33 = Methodref          #2.#32        // coursier/core/Done."<init>":(Lcoursier/core/Resolution;)V
   #34 = Utf8               toString
   #35 = Utf8               ()Ljava/lang/String;
   #36 = Utf8               java/lang/StringBuilder
   #37 = Class              #36           // java/lang/StringBuilder
   #38 = Utf8               Done(
   #39 = String             #38           // Done(
   #40 = Utf8               (Ljava/lang/String;)V
   #41 = NameAndType        #30:#40       // "<init>":(Ljava/lang/String;)V
   #42 = Methodref          #37.#41       // java/lang/StringBuilder."<init>":(Ljava/lang/String;)V
   #43 = Utf8               java/lang/String
   #44 = Class              #43           // java/lang/String
   #45 = Utf8               valueOf
   #46 = Utf8               (Ljava/lang/Object;)Ljava/lang/String;
   #47 = NameAndType        #45:#46       // valueOf:(Ljava/lang/Object;)Ljava/lang/String;
   #48 = Methodref          #44.#47       // java/lang/String.valueOf:(Ljava/lang/Object;)Ljava/lang/String;
   #49 = Utf8               append
   #50 = Utf8               (Ljava/lang/String;)Ljava/lang/StringBuilder;
   #51 = NameAndType        #49:#50       // append:(Ljava/lang/String;)Ljava/lang/StringBuilder;
   #52 = Methodref          #37.#51       // java/lang/StringBuilder.append:(Ljava/lang/String;)Ljava/lang/StringBuilder;
   #53 = Utf8               )
   #54 = String             #53           // )
   #55 = NameAndType        #34:#35       // toString:()Ljava/lang/String;
   #56 = Methodref          #37.#55       // java/lang/StringBuilder.toString:()Ljava/lang/String;
   #57 = Utf8               b
   #58 = Utf8               Ljava/lang/StringBuilder;
   #59 = Utf8               canEqual
   #60 = Utf8               (Ljava/lang/Object;)Z
   #61 = Utf8               obj
   #62 = Utf8               Ljava/lang/Object;
   #63 = Utf8               equals
   #64 = NameAndType        #59:#60       // canEqual:(Ljava/lang/Object;)Z
   #65 = Methodref          #2.#64        // coursier/core/Done.canEqual:(Ljava/lang/Object;)Z
   #66 = Utf8               java/lang/Object
   #67 = Class              #66           // java/lang/Object
   #68 = Utf8               coursier/core/Resolution
   #69 = Class              #68           // coursier/core/Resolution
   #70 = NameAndType        #63:#60       // equals:(Ljava/lang/Object;)Z
   #71 = Methodref          #67.#70       // java/lang/Object.equals:(Ljava/lang/Object;)Z
   #72 = Utf8               other
   #73 = Utf8               hashCode
   #74 = Utf8               ()I
   #75 = Utf8               Done
   #76 = String             #75           // Done
   #77 = Utf8               scala/runtime/Statics
   #78 = Class              #77           // scala/runtime/Statics
   #79 = Utf8               anyHash
   #80 = Utf8               (Ljava/lang/Object;)I
   #81 = NameAndType        #79:#80       // anyHash:(Ljava/lang/Object;)I
   #82 = Methodref          #78.#81       // scala/runtime/Statics.anyHash:(Ljava/lang/Object;)I
   #83 = Utf8               code
   #84 = Utf8               I
   #85 = Utf8               tuple
   #86 = Utf8               ()Lscala/Tuple1;
   #87 = Utf8               ()Lscala/Tuple1<Lcoursier/core/Resolution;>;
   #88 = Utf8               scala/Tuple1
   #89 = Class              #88           // scala/Tuple1
   #90 = Utf8               (Ljava/lang/Object;)V
   #91 = NameAndType        #30:#90       // "<init>":(Ljava/lang/Object;)V
   #92 = Methodref          #89.#91       // scala/Tuple1."<init>":(Ljava/lang/Object;)V
   #93 = Utf8               productPrefix
   #94 = Utf8               productArity
   #95 = Utf8               productElement
   #96 = Utf8               (I)Ljava/lang/Object;
   #97 = Utf8               n
   #98 = Utf8               java/lang/IndexOutOfBoundsException
   #99 = Class              #98           // java/lang/IndexOutOfBoundsException
  #100 = Utf8               scala/runtime/BoxesRunTime
  #101 = Class              #100          // scala/runtime/BoxesRunTime
  #102 = Utf8               boxToInteger
  #103 = Utf8               (I)Ljava/lang/Integer;
  #104 = NameAndType        #102:#103     // boxToInteger:(I)Ljava/lang/Integer;
  #105 = Methodref          #101.#104     // scala/runtime/BoxesRunTime.boxToInteger:(I)Ljava/lang/Integer;
  #106 = Methodref          #67.#55       // java/lang/Object.toString:()Ljava/lang/String;
  #107 = Methodref          #99.#41       // java/lang/IndexOutOfBoundsException."<init>":(Ljava/lang/String;)V
  #108 = Utf8               productElementName
  #109 = Utf8               (I)Ljava/lang/String;
  #110 = String             #9            // resolution
  #111 = Utf8               ()V
  #112 = NameAndType        #30:#111      // "<init>":()V
  #113 = Methodref          #4.#112       // coursier/core/ResolutionProcess."<init>":()V
  #114 = Utf8               Code
  #115 = Utf8               MethodParameters
  #116 = Utf8               LineNumberTable
  #117 = Utf8               LocalVariableTable
  #118 = Utf8               StackMapTable
  #119 = Utf8               Signature
  #120 = Utf8               SourceFile
  #121 = Utf8               RuntimeVisibleAnnotations
  #122 = Utf8               ScalaInlineInfo
  #123 = Utf8               ScalaSig
{
  private final coursier.core.Resolution resolution;
    descriptor: Lcoursier/core/Resolution;
    flags: (0x0012) ACC_PRIVATE, ACC_FINAL

  public static coursier.core.Done apply(coursier.core.Resolution);
    descriptor: (Lcoursier/core/Resolution;)Lcoursier/core/Done;
    flags: (0x0009) ACC_PUBLIC, ACC_STATIC
    Code:
      stack=2, locals=1, args_size=1
         0: getstatic     #18                 // Field coursier/core/Done$.MODULE$:Lcoursier/core/Done$;
         3: aload_0
         4: invokevirtual #20                 // Method coursier/core/Done$.apply:(Lcoursier/core/Resolution;)Lcoursier/core/Done;
         7: areturn
    MethodParameters:
      Name                           Flags
      resolution                     final

  public coursier.core.Resolution resolution();
    descriptor: ()Lcoursier/core/Resolution;
    flags: (0x0001) ACC_PUBLIC
    Code:
      stack=1, locals=1, args_size=1
         0: aload_0
         1: getfield      #23                 // Field resolution:Lcoursier/core/Resolution;
         4: areturn
      LineNumberTable:
        line 151: 0
      LocalVariableTable:
        Start  Length  Slot  Name   Signature
            0       5     0  this   Lcoursier/core/Done;

  public coursier.core.Resolution current();
    descriptor: ()Lcoursier/core/Resolution;
    flags: (0x0001) ACC_PUBLIC
    Code:
      stack=1, locals=1, args_size=1
         0: aload_0
         1: invokevirtual #28                 // Method resolution:()Lcoursier/core/Resolution;
         4: areturn
      LineNumberTable:
        line 153: 0
      LocalVariableTable:
        Start  Length  Slot  Name   Signature
            0       5     0  this   Lcoursier/core/Done;

  public coursier.core.Done withResolution(coursier.core.Resolution);
    descriptor: (Lcoursier/core/Resolution;)Lcoursier/core/Done;
    flags: (0x0001) ACC_PUBLIC
    Code:
      stack=3, locals=2, args_size=2
         0: new           #2                  // class coursier/core/Done
         3: dup
         4: aload_1
         5: invokespecial #33                 // Method "<init>":(Lcoursier/core/Resolution;)V
         8: areturn
      LineNumberTable:
        line 151: 0
      LocalVariableTable:
        Start  Length  Slot  Name   Signature
            0       9     0  this   Lcoursier/core/Done;
            0       9     1 resolution   Lcoursier/core/Resolution;
    MethodParameters:
      Name                           Flags
      resolution                     final

  public java.lang.String toString();
    descriptor: ()Ljava/lang/String;
    flags: (0x0001) ACC_PUBLIC
    Code:
      stack=3, locals=2, args_size=1
         0: new           #37                 // class java/lang/StringBuilder
         3: dup
         4: ldc           #39                 // String Done(
         6: invokespecial #42                 // Method java/lang/StringBuilder."<init>":(Ljava/lang/String;)V
         9: astore_1
        10: aload_1
        11: aload_0
        12: invokevirtual #28                 // Method resolution:()Lcoursier/core/Resolution;
        15: invokestatic  #48                 // Method java/lang/String.valueOf:(Ljava/lang/Object;)Ljava/lang/String;
        18: invokevirtual #52                 // Method java/lang/StringBuilder.append:(Ljava/lang/String;)Ljava/lang/StringBuilder;
        21: pop
        22: aload_1
        23: ldc           #54                 // String )
        25: invokevirtual #52                 // Method java/lang/StringBuilder.append:(Ljava/lang/String;)Ljava/lang/StringBuilder;
        28: pop
        29: aload_1
        30: invokevirtual #56                 // Method java/lang/StringBuilder.toString:()Ljava/lang/String;
        33: areturn
      LineNumberTable:
        line 151: 0
      LocalVariableTable:
        Start  Length  Slot  Name   Signature
           10      23     1     b   Ljava/lang/StringBuilder;
            0      34     0  this   Lcoursier/core/Done;

  public boolean canEqual(java.lang.Object);
    descriptor: (Ljava/lang/Object;)Z
    flags: (0x0001) ACC_PUBLIC
    Code:
      stack=1, locals=2, args_size=2
         0: aload_1
         1: ifnull        15
         4: aload_1
         5: instanceof    #2                  // class coursier/core/Done
         8: ifeq          15
        11: iconst_1
        12: goto          16
        15: iconst_0
        16: ireturn
      StackMapTable: number_of_entries = 2
        frame_type = 15 /* same */
        frame_type = 64 /* same_locals_1_stack_item */
          stack = [ int ]
      LineNumberTable:
        line 151: 0
      LocalVariableTable:
        Start  Length  Slot  Name   Signature
            0      17     0  this   Lcoursier/core/Done;
            0      17     1   obj   Ljava/lang/Object;
    MethodParameters:
      Name                           Flags
      obj                            final

  public boolean equals(java.lang.Object);
    descriptor: (Ljava/lang/Object;)Z
    flags: (0x0001) ACC_PUBLIC
    Code:
      stack=2, locals=4, args_size=2
         0: aload_0
         1: aload_1
         2: if_acmpeq     58
         5: aload_0
         6: aload_1
         7: invokevirtual #65                 // Method canEqual:(Ljava/lang/Object;)Z
        10: ifeq          62
        13: aload_1
        14: checkcast     #2                  // class coursier/core/Done
        17: astore_2
        18: iconst_1
        19: ifeq          54
        22: aload_0
        23: invokevirtual #28                 // Method resolution:()Lcoursier/core/Resolution;
        26: aload_2
        27: invokevirtual #28                 // Method resolution:()Lcoursier/core/Resolution;
        30: astore_3
        31: dup
        32: ifnonnull     43
        35: pop
        36: aload_3
        37: ifnull        50
        40: goto          54
        43: aload_3
        44: invokevirtual #71                 // Method java/lang/Object.equals:(Ljava/lang/Object;)Z
        47: ifeq          54
        50: iconst_1
        51: goto          55
        54: iconst_0
        55: ifeq          62
        58: iconst_1
        59: goto          63
        62: iconst_0
        63: ireturn
      StackMapTable: number_of_entries = 7
        frame_type = 255 /* full_frame */
          offset_delta = 43
          locals = [ class coursier/core/Done, class java/lang/Object, class coursier/core/Done, class coursier/core/Resolution ]
          stack = [ class coursier/core/Resolution ]
        frame_type = 6 /* same */
        frame_type = 250 /* chop */
          offset_delta = 3
        frame_type = 64 /* same_locals_1_stack_item */
          stack = [ int ]
        frame_type = 250 /* chop */
          offset_delta = 2
        frame_type = 3 /* same */
        frame_type = 64 /* same_locals_1_stack_item */
          stack = [ int ]
      LineNumberTable:
        line 151: 0
      LocalVariableTable:
        Start  Length  Slot  Name   Signature
           18      37     2 other   Lcoursier/core/Done;
            0      64     0  this   Lcoursier/core/Done;
            0      64     1   obj   Ljava/lang/Object;
    MethodParameters:
      Name                           Flags
      obj                            final

  public int hashCode();
    descriptor: ()I
    flags: (0x0001) ACC_PUBLIC
    Code:
      stack=2, locals=2, args_size=1
         0: bipush        17
         2: ldc           #76                 // String Done
         4: invokestatic  #82                 // Method scala/runtime/Statics.anyHash:(Ljava/lang/Object;)I
         7: iadd
         8: istore_1
         9: bipush        37
        11: iload_1
        12: imul
        13: aload_0
        14: invokevirtual #28                 // Method resolution:()Lcoursier/core/Resolution;
        17: invokestatic  #82                 // Method scala/runtime/Statics.anyHash:(Ljava/lang/Object;)I
        20: iadd
        21: istore_1
        22: bipush        37
        24: iload_1
        25: imul
        26: ireturn
      LineNumberTable:
        line 151: 0
      LocalVariableTable:
        Start  Length  Slot  Name   Signature
            9      17     1  code   I
            0      27     0  this   Lcoursier/core/Done;

  private scala.Tuple1<coursier.core.Resolution> tuple();
    descriptor: ()Lscala/Tuple1;
    flags: (0x0002) ACC_PRIVATE
    Code:
      stack=3, locals=1, args_size=1
         0: new           #89                 // class scala/Tuple1
         3: dup
         4: aload_0
         5: invokevirtual #28                 // Method resolution:()Lcoursier/core/Resolution;
         8: invokespecial #92                 // Method scala/Tuple1."<init>":(Ljava/lang/Object;)V
        11: areturn
      LineNumberTable:
        line 151: 0
      LocalVariableTable:
        Start  Length  Slot  Name   Signature
            0      12     0  this   Lcoursier/core/Done;
    Signature: #87                          // ()Lscala/Tuple1<Lcoursier/core/Resolution;>;

  public java.lang.String productPrefix();
    descriptor: ()Ljava/lang/String;
    flags: (0x0001) ACC_PUBLIC
    Code:
      stack=1, locals=1, args_size=1
         0: ldc           #76                 // String Done
         2: areturn
      LineNumberTable:
        line 151: 0
      LocalVariableTable:
        Start  Length  Slot  Name   Signature
            0       3     0  this   Lcoursier/core/Done;

  public int productArity();
    descriptor: ()I
    flags: (0x0001) ACC_PUBLIC
    Code:
      stack=1, locals=1, args_size=1
         0: iconst_1
         1: ireturn
      LineNumberTable:
        line 151: 0
      LocalVariableTable:
        Start  Length  Slot  Name   Signature
            0       2     0  this   Lcoursier/core/Done;

  public java.lang.Object productElement(int);
    descriptor: (I)Ljava/lang/Object;
    flags: (0x0001) ACC_PUBLIC
    Code:
      stack=3, locals=3, args_size=2
         0: iload_1
         1: istore_2
         2: iload_2
         3: tableswitch   { // 0 to 0
                       0: 20
                 default: 27
            }
        20: aload_0
        21: invokevirtual #28                 // Method resolution:()Lcoursier/core/Resolution;
        24: goto          42
        27: new           #99                 // class java/lang/IndexOutOfBoundsException
        30: dup
        31: iload_2
        32: invokestatic  #105                // Method scala/runtime/BoxesRunTime.boxToInteger:(I)Ljava/lang/Integer;
        35: invokevirtual #106                // Method java/lang/Object.toString:()Ljava/lang/String;
        38: invokespecial #107                // Method java/lang/IndexOutOfBoundsException."<init>":(Ljava/lang/String;)V
        41: athrow
        42: areturn
      StackMapTable: number_of_entries = 3
        frame_type = 252 /* append */
          offset_delta = 20
          locals = [ int ]
        frame_type = 6 /* same */
        frame_type = 78 /* same_locals_1_stack_item */
          stack = [ class coursier/core/Resolution ]
      LineNumberTable:
        line 151: 0
      LocalVariableTable:
        Start  Length  Slot  Name   Signature
            0      43     0  this   Lcoursier/core/Done;
            0      43     1     n   I
    MethodParameters:
      Name                           Flags
      n                              final

  public java.lang.String productElementName(int);
    descriptor: (I)Ljava/lang/String;
    flags: (0x0001) ACC_PUBLIC
    Code:
      stack=3, locals=3, args_size=2
         0: iload_1
         1: istore_2
         2: iload_2
         3: tableswitch   { // 0 to 0
                       0: 20
                 default: 25
            }
        20: ldc           #110                // String resolution
        22: goto          40
        25: new           #99                 // class java/lang/IndexOutOfBoundsException
        28: dup
        29: iload_2
        30: invokestatic  #105                // Method scala/runtime/BoxesRunTime.boxToInteger:(I)Ljava/lang/Integer;
        33: invokevirtual #106                // Method java/lang/Object.toString:()Ljava/lang/String;
        36: invokespecial #107                // Method java/lang/IndexOutOfBoundsException."<init>":(Ljava/lang/String;)V
        39: athrow
        40: areturn
      StackMapTable: number_of_entries = 3
        frame_type = 252 /* append */
          offset_delta = 20
          locals = [ int ]
        frame_type = 4 /* same */
        frame_type = 78 /* same_locals_1_stack_item */
          stack = [ class java/lang/String ]
      LineNumberTable:
        line 151: 0
      LocalVariableTable:
        Start  Length  Slot  Name   Signature
            0      41     0  this   Lcoursier/core/Done;
            0      41     1     n   I
    MethodParameters:
      Name                           Flags
      n                              final

  public coursier.core.Done(coursier.core.Resolution);
    descriptor: (Lcoursier/core/Resolution;)V
    flags: (0x0001) ACC_PUBLIC
    Code:
      stack=2, locals=2, args_size=2
         0: aload_0
         1: aload_1
         2: putfield      #23                 // Field resolution:Lcoursier/core/Resolution;
         5: aload_0
         6: invokespecial #113                // Method coursier/core/ResolutionProcess."<init>":()V
         9: return
      LineNumberTable:
        line 151: 0
      LocalVariableTable:
        Start  Length  Slot  Name   Signature
            0      10     0  this   Lcoursier/core/Done;
            0      10     1 resolution   Lcoursier/core/Resolution;
    MethodParameters:
      Name                           Flags
      resolution                     final
}
SourceFile: "ResolutionProcess.scala"
RuntimeVisibleAnnotations:
  0: #6(#7=s#8)
    scala.reflect.ScalaSignature(
      bytes="\u0006\u0005}4A\u0001F\u000b\u00035!A\u0011\u0007\u0001BC\u0002\u0013\u0005!\u0007\u0003\u00057\u0001\t\u0005\t\u0015!\u00034\u0011\u00159\u0004\u0001\"\u00019\u0011\u0015Y\u0004\u0001\"\u00013\u0011\u0015a\u0004\u0001\"\u0001>\u0011\u0015y\u0004\u0001\"\u0011A\u0011\u0015I\u0005\u0001\"\u0011K\u0011\u0015\u0019\u0006\u0001\"\u0011U\u0011\u00151\u0006\u0001\"\u0011X\u0011\u0015Y\u0006\u0001\"\u0003]\u0011\u0015\u0001\u0007\u0001\"\u0011b\u0011\u0015\u0011\u0007\u0001\"\u0011d\u0011\u0015!\u0007\u0001\"\u0011f\u0011\u0015A\u0007\u0001\"\u0011j\u000f\u0015YW\u0003#\u0001m\r\u0015!R\u0003#\u0001n\u0011\u00159\u0004\u0003\"\u0001w\u0011\u00159\b\u0003\"\u0001y\u0011\u001dQ\b#!A\u0005\nm\u0014A\u0001R8oK*\u0011acF\u0001\u0005G>\u0014XMC\u0001\u0019\u0003!\u0019w.\u001e:tS\u0016\u00148\u0001A\n\u0005\u0001myR\u0005\u0005\u0002\u001d;5\tQ#\u0003\u0002\u001f+\t\t\"+Z:pYV$\u0018n\u001c8Qe>\u001cWm]:\u0011\u0005\u0001\u001aS\"A\u0011\u000b\u0003\t\nQa]2bY\u0006L!\u0001J\u0011\u0003\u000fA\u0013x\u000eZ;diB\u0011aE\f\b\u0003O1r!\u0001K\u0016\u000e\u0003%R!AK\r\u0002\rq\u0012xn\u001c;?\u0013\u0005\u0011\u0013BA\u0017\"\u0003\u001d\u0001\u0018mY6bO\u0016L!a\f\u0019\u0003\u0019M+\'/[1mSj\f\'\r\\3\u000b\u00055\n\u0013A\u0003:fg>dW\u000f^5p]V\t1\u0007\u0005\u0002\u001di%\u0011Q\'\u0006\u0002\u000b%\u0016\u001cx\u000e\\;uS>t\u0017a\u0003:fg>dW\u000f^5p]\u0002\na\u0001P5oSRtDCA\u001d;!\ta\u0002\u0001C\u00032\u0007\u0001\u00071\'A\u0004dkJ\u0014XM\u001c;\u0002\u001d]LG\u000f\u001b*fg>dW\u000f^5p]R\u0011\u0011H\u0010\u0005\u0006c\u0015\u0001\raM\u0001\ti>\u001cFO]5oOR\t\u0011\t\u0005\u0002C\u000f6\t1I\u0003\u0002E\u000b\u0006!A.\u00198h\u0015\u00051\u0015\u0001\u00026bm\u0006L!\u0001S\"\u0003\rM#(/\u001b8h\u0003!\u0019\u0017M\\#rk\u0006dGCA&O!\t\u0001C*\u0003\u0002NC\t9!i\\8mK\u0006t\u0007\"B(\b\u0001\u0004\u0001\u0016aA8cUB\u0011\u0001%U\u0005\u0003%\u0006\u00121!\u00118z\u0003\u0019)\u0017/^1mgR\u00111*\u0016\u0005\u0006\u001f\"\u0001\r\u0001U\u0001\tQ\u0006\u001c\bnQ8eKR\t\u0001\f\u0005\u0002!3&\u0011!,\t\u0002\u0004\u0013:$\u0018!\u0002;va2,W#A/\u0011\u0007\u0001r6\'\u0003\u0002`C\t1A+\u001e9mKF\nQ\u0002\u001d:pIV\u001cG\u000f\u0015:fM&DX#A!\u0002\u0019A\u0014x\u000eZ;di\u0006\u0013\u0018\u000e^=\u0016\u0003a\u000ba\u0002\u001d:pIV\u001cG/\u00127f[\u0016tG\u000f\u0006\u0002QM\")q-\u0004a\u00011\u0006\ta.\u0001\nqe>$Wo\u0019;FY\u0016lWM\u001c;OC6,GCA!k\u0011\u00159g\u00021\u0001Y\u0003\u0011!uN\\3\u0011\u0005q\u00012c\u0001\tocB\u0011\u0001e\\\u0005\u0003a\u0006\u0012a!\u00118z%\u00164\u0007C\u0001:v\u001b\u0005\u0019(B\u0001;F\u0003\tIw.\u0003\u00020gR\tA.A\u0003baBd\u0017\u0010\u0006\u0002:s\")\u0011G\u0005a\u0001g\u0005aqO]5uKJ+\u0007\u000f\\1dKR\tA\u0010\u0005\u0002C{&\u0011ap\u0011\u0002\u0007\u001f\nTWm\u0019;"
    )
  ScalaInlineInfo: length = 0x45 (unknown attribute)
   01 01 00 0D 00 1E 00 1F 01 00 3B 00 3C 01 00 1A
   00 15 01 00 3F 00 3C 01 00 49 00 4A 01 00 5E 00
   4A 01 00 5F 00 60 01 00 6C 00 6D 01 00 5D 00 23
   01 00 09 00 15 01 00 22 00 23 01 00 55 00 56 01
   00 1D 00 0C 01
  ScalaSig: length = 0x3 (unknown attribute)
   05 02 00
