Classfile /Users/mw/Projects/slang-braindump/.jar/jar11/assemble/slang-braindump/assemble/content/coursier/core/Latest.class
  Last modified May 29, 2022; size 3254 bytes
  SHA-256 checksum 9e9b7939c95c3fb8f43a53f785a4e9f77b103e1ba2d046bc39798d4d36bd1fe7
  Compiled from "Latest.scala"
public abstract class coursier.core.Latest implements scala.Product,java.io.Serializable
  minor version: 0
  major version: 52
  flags: (0x0421) ACC_PUBLIC, ACC_SUPER, ACC_ABSTRACT
  this_class: #2                          // coursier/core/Latest
  super_class: #4                         // java/lang/Object
  interfaces: 2, fields: 1, methods: 7, attributes: 5
Constant pool:
   #1 = Utf8               coursier/core/Latest
   #2 = Class              #1             // coursier/core/Latest
   #3 = Utf8               java/lang/Object
   #4 = Class              #3             // java/lang/Object
   #5 = Utf8               scala/Product
   #6 = Class              #5             // scala/Product
   #7 = Utf8               java/io/Serializable
   #8 = Class              #7             // java/io/Serializable
   #9 = Utf8               Latest.scala
  #10 = Utf8               Lscala/reflect/ScalaSignature;
  #11 = Utf8               bytes
  #12 = Utf8               \u0006\u0005\u0005]c!\u0002\u0016,\u0003C\u0001\u0004\u0002\u0003$\u0001\u0005\u000b\u0007I\u0011A$\t\u0011A\u0003!\u0011!Q\u0001\n!CQ!\u0015\u0001\u0005\u0002I;a!!\u0016,\u0011\u0003\tg!\u0002\u0016,\u0011\u0003A\u0006\"B)\u0006\t\u0003\u0001w!\u00022\u0006\u0011\u0003\u001bgAB,\u0006\u0011\u0003\u000bI\u0005\u0003\u0004R\u0011\u0011\u0005\u00111\n\u0005\bU\"\t\t\u0011\"\u0011l\u0011\u001d\t\b\"!A\u0005\u0002ID\u0001B\u001e\u0005\u0002\u0002\u0013\u0005\u0011Q\n\u0005\b{\"\t\t\u0011\"\u0011\u007f\u0011%\tY\u0001CA\u0001\n\u0003\t\t\u0006C\u0005\u0002\u0018!\t\t\u0011\"\u0011\u0002\u001a!I\u00111\u0004\u0005\u0002\u0002\u0013\u0005\u0013Q\u0004\u0005\n\u0003?A\u0011\u0011!C\u0005\u0003C9Q!Z\u0003\t\u0002\u001a4QaZ\u0003\t\u0002\"DQ!U\n\u0005\u0002%DqA[\n\u0002\u0002\u0013\u00053\u000eC\u0004r\'\u0005\u0005I\u0011\u0001:\t\u000fY\u001c\u0012\u0011!C\u0001o\"9QpEA\u0001\n\u0003r\b\"CA\u0006\'\u0005\u0005I\u0011AA\u0007\u0011%\t9bEA\u0001\n\u0003\nI\u0002C\u0005\u0002\u001cM\t\t\u0011\"\u0011\u0002\u001e!I\u0011qD\n\u0002\u0002\u0013%\u0011\u0011E\u0004\b\u0003S)\u0001\u0012QA\u0016\r\u001d\ti#\u0002EA\u0003_Aa!\u0015\u0010\u0005\u0002\u0005E\u0002b\u00026\u001f\u0003\u0003%\te\u001b\u0005\bcz\t\t\u0011\"\u0001s\u0011!1h$!A\u0005\u0002\u0005M\u0002bB?\u001f\u0003\u0003%\tE \u0005\n\u0003\u0017q\u0012\u0011!C\u0001\u0003oA\u0011\"a\u0006\u001f\u0003\u0003%\t%!\u0007\t\u0013\u0005ma$!A\u0005B\u0005u\u0001\"CA\u0010=\u0005\u0005I\u0011BA\u0011\u0011\u001d\tY$\u0002C\u0001\u0003{A\u0011\"a\b\u0006\u0003\u0003%I!!\t\u0003\r1\u000bG/Z:u\u0015\taS&\u0001\u0003d_J,\'\"\u0001\u0018\u0002\u0011\r|WO]:jKJ\u001c\u0001a\u0005\u0003\u0001c]R\u0004C\u0001\u001a6\u001b\u0005\u0019$\"\u0001\u001b\u0002\u000bM\u001c\u0017\r\\1\n\u0005Y\u001a$AB!osJ+g\r\u0005\u00023q%\u0011\u0011h\r\u0002\b!J|G-^2u!\tY4I\u0004\u0002=\u0003:\u0011Q\bQ\u0007\u0002})\u0011qhL\u0001\u0007yI|w\u000e\u001e \n\u0003QJ!AQ\u001a\u0002\u000fA\f7m[1hK&\u0011A)\u0012\u0002\r\'\u0016\u0014\u0018.\u00197ju\u0006\u0014G.\u001a\u0006\u0003\u0005N\nAA\\1nKV\t\u0001\n\u0005\u0002J\u001b:\u0011!j\u0013\t\u0003{MJ!\u0001T\u001a\u0002\rA\u0013X\rZ3g\u0013\tquJ\u0001\u0004TiJLgn\u001a\u0006\u0003\u0019N\nQA\\1nK\u0002\na\u0001P5oSRtDCA*V!\t!\u0006!D\u0001,\u0011\u001515\u00011\u0001IS\u0011\u0001\u0001b\u0005\u0010\u0003\u0017%sG/Z4sCRLwN\\\n\u0004\u000bEJ\u0006C\u0001.`\u001b\u0005Y&B\u0001/^\u0003\tIwNC\u0001_\u0003\u0011Q\u0017M^1\n\u0005\u0011[F#A1\u0011\u0005Q+\u0011aC%oi\u0016<\'/\u0019;j_:\u0004\"\u0001\u001a\u0005\u000e\u0003\u0015\tqAU3mK\u0006\u001cX\r\u0005\u0002e\'\t9!+\u001a7fCN,7\u0003B\nToi\"\u0012AZ\u0001\u000eaJ|G-^2u!J,g-\u001b=\u0016\u00031\u0004\"!\u001c9\u000e\u00039T!a\\/\u0002\t1\fgnZ\u0005\u0003\u001d:\fA\u0002\u001d:pIV\u001cG/\u0011:jif,\u0012a\u001d\t\u0003eQL!!^\u001a\u0003\u0007%sG/\u0001\bqe>$Wo\u0019;FY\u0016lWM\u001c;\u0015\u0005a\\\bC\u0001\u001az\u0013\tQ8GA\u0002B]fDq\u0001`\f\u0002\u0002\u0003\u00071/A\u0002yIE\nq\u0002\u001d:pIV\u001cG/\u0013;fe\u0006$xN]\u000b\u0002\u007fB)\u0011\u0011AA\u0004q6\u0011\u00111\u0001\u0006\u0004\u0003\u000b\u0019\u0014AC2pY2,7\r^5p]&!\u0011\u0011BA\u0002\u0005!IE/\u001a:bi>\u0014\u0018\u0001C2b]\u0016\u000bX/\u00197\u0015\t\u0005=\u0011Q\u0003\t\u0004e\u0005E\u0011bAA\ng\t9!i\\8mK\u0006t\u0007b\u0002?\u001a\u0003\u0003\u0005\r\u0001_\u0001\tQ\u0006\u001c\bnQ8eKR\t1/\u0001\u0005u_N#(/\u001b8h)\u0005a\u0017\u0001D<sSR,\'+\u001a9mC\u000e,GCAA\u0012!\ri\u0017QE\u0005\u0004\u0003Oq\'AB(cU\u0016\u001cG/\u0001\u0004Ti\u0006\u0014G.\u001a\t\u0003Iz\u0011aa\u0015;bE2,7\u0003\u0002\u0010Toi\"\"!a\u000b\u0015\u0007a\f)\u0004C\u0004}E\u0005\u0005\t\u0019A:\u0015\t\u0005=\u0011\u0011\b\u0005\by\u0012\n\t\u00111\u0001y\u0003\u0015\t\u0007\u000f\u001d7z)\u0011\ty$!\u0012\u0011\tI\n\teU\u0005\u0004\u0003\u0007\u001a$AB(qi&|g\u000e\u0003\u0004\u0002H!\u0002\r\u0001S\u0001\u0002gN!\u0001bU\u001c;)\u0005\u0019Gc\u0001=\u0002P!9A\u0010DA\u0001\u0002\u0004\u0019H\u0003BA\b\u0003\'Bq\u0001 \b\u0002\u0002\u0003\u0007\u00010\u0001\u0004MCR,7\u000f\u001e
  #13 = Utf8               coursier/core/Latest$Integration$
  #14 = Class              #13            // coursier/core/Latest$Integration$
  #15 = Utf8
  #16 = Utf8               coursier/core/Latest$Release$
  #17 = Class              #16            // coursier/core/Latest$Release$
  #18 = Utf8               coursier/core/Latest$Stable$
  #19 = Class              #18            // coursier/core/Latest$Stable$
  #20 = Utf8               name
  #21 = Utf8               Ljava/lang/String;
  #22 = Utf8               apply
  #23 = Utf8               (Ljava/lang/String;)Lscala/Option;
  #24 = Utf8               (Ljava/lang/String;)Lscala/Option<Lcoursier/core/Latest;>;
  #25 = Utf8               s
  #26 = Utf8               coursier/core/Latest$
  #27 = Class              #26            // coursier/core/Latest$
  #28 = Utf8               MODULE$
  #29 = Utf8               Lcoursier/core/Latest$;
  #30 = NameAndType        #28:#29        // MODULE$:Lcoursier/core/Latest$;
  #31 = Fieldref           #27.#30        // coursier/core/Latest$.MODULE$:Lcoursier/core/Latest$;
  #32 = NameAndType        #22:#23        // apply:(Ljava/lang/String;)Lscala/Option;
  #33 = Methodref          #27.#32        // coursier/core/Latest$.apply:(Ljava/lang/String;)Lscala/Option;
  #34 = Utf8               productIterator
  #35 = Utf8               ()Lscala/collection/Iterator;
  #36 = Utf8               ()Lscala/collection/Iterator<Ljava/lang/Object;>;
  #37 = Utf8               productIterator$
  #38 = Utf8               (Lscala/Product;)Lscala/collection/Iterator;
  #39 = NameAndType        #37:#38        // productIterator$:(Lscala/Product;)Lscala/collection/Iterator;
  #40 = InterfaceMethodref #6.#39         // scala/Product.productIterator$:(Lscala/Product;)Lscala/collection/Iterator;
  #41 = Utf8               this
  #42 = Utf8               Lcoursier/core/Latest;
  #43 = Utf8               productPrefix
  #44 = Utf8               ()Ljava/lang/String;
  #45 = Utf8               productPrefix$
  #46 = Utf8               (Lscala/Product;)Ljava/lang/String;
  #47 = NameAndType        #45:#46        // productPrefix$:(Lscala/Product;)Ljava/lang/String;
  #48 = InterfaceMethodref #6.#47         // scala/Product.productPrefix$:(Lscala/Product;)Ljava/lang/String;
  #49 = Utf8               productElementName
  #50 = Utf8               (I)Ljava/lang/String;
  #51 = Utf8               n
  #52 = Utf8               productElementName$
  #53 = Utf8               (Lscala/Product;I)Ljava/lang/String;
  #54 = NameAndType        #52:#53        // productElementName$:(Lscala/Product;I)Ljava/lang/String;
  #55 = InterfaceMethodref #6.#54         // scala/Product.productElementName$:(Lscala/Product;I)Ljava/lang/String;
  #56 = Utf8               I
  #57 = Utf8               productElementNames
  #58 = Utf8               ()Lscala/collection/Iterator<Ljava/lang/String;>;
  #59 = Utf8               productElementNames$
  #60 = NameAndType        #59:#38        // productElementNames$:(Lscala/Product;)Lscala/collection/Iterator;
  #61 = InterfaceMethodref #6.#60         // scala/Product.productElementNames$:(Lscala/Product;)Lscala/collection/Iterator;
  #62 = NameAndType        #20:#21        // name:Ljava/lang/String;
  #63 = Fieldref           #2.#62         // coursier/core/Latest.name:Ljava/lang/String;
  #64 = Utf8               <init>
  #65 = Utf8               (Ljava/lang/String;)V
  #66 = Utf8               ()V
  #67 = NameAndType        #64:#66        // "<init>":()V
  #68 = Methodref          #4.#67         // java/lang/Object."<init>":()V
  #69 = Utf8               $init$
  #70 = Utf8               (Lscala/Product;)V
  #71 = NameAndType        #69:#70        // $init$:(Lscala/Product;)V
  #72 = InterfaceMethodref #6.#71         // scala/Product.$init$:(Lscala/Product;)V
  #73 = Utf8               Code
  #74 = Utf8               Signature
  #75 = Utf8               MethodParameters
  #76 = Utf8               LineNumberTable
  #77 = Utf8               LocalVariableTable
  #78 = Utf8               InnerClasses
  #79 = Utf8               SourceFile
  #80 = Utf8               RuntimeVisibleAnnotations
  #81 = Utf8               ScalaInlineInfo
  #82 = Utf8               ScalaSig
{
  private final java.lang.String name;
    descriptor: Ljava/lang/String;
    flags: (0x0012) ACC_PRIVATE, ACC_FINAL

  public static scala.Option<coursier.core.Latest> apply(java.lang.String);
    descriptor: (Ljava/lang/String;)Lscala/Option;
    flags: (0x0009) ACC_PUBLIC, ACC_STATIC
    Code:
      stack=2, locals=1, args_size=1
         0: getstatic     #31                 // Field coursier/core/Latest$.MODULE$:Lcoursier/core/Latest$;
         3: aload_0
         4: invokevirtual #33                 // Method coursier/core/Latest$.apply:(Ljava/lang/String;)Lscala/Option;
         7: areturn
    Signature: #24                          // (Ljava/lang/String;)Lscala/Option<Lcoursier/core/Latest;>;
    MethodParameters:
      Name                           Flags
      s                              final

  public scala.collection.Iterator<java.lang.Object> productIterator();
    descriptor: ()Lscala/collection/Iterator;
    flags: (0x0001) ACC_PUBLIC
    Code:
      stack=1, locals=1, args_size=1
         0: aload_0
         1: invokestatic  #40                 // InterfaceMethod scala/Product.productIterator$:(Lscala/Product;)Lscala/collection/Iterator;
         4: areturn
      LineNumberTable:
        line 3: 0
      LocalVariableTable:
        Start  Length  Slot  Name   Signature
            0       5     0  this   Lcoursier/core/Latest;
    Signature: #36                          // ()Lscala/collection/Iterator<Ljava/lang/Object;>;

  public java.lang.String productPrefix();
    descriptor: ()Ljava/lang/String;
    flags: (0x0001) ACC_PUBLIC
    Code:
      stack=1, locals=1, args_size=1
         0: aload_0
         1: invokestatic  #48                 // InterfaceMethod scala/Product.productPrefix$:(Lscala/Product;)Ljava/lang/String;
         4: areturn
      LineNumberTable:
        line 3: 0
      LocalVariableTable:
        Start  Length  Slot  Name   Signature
            0       5     0  this   Lcoursier/core/Latest;

  public java.lang.String productElementName(int);
    descriptor: (I)Ljava/lang/String;
    flags: (0x0001) ACC_PUBLIC
    Code:
      stack=2, locals=2, args_size=2
         0: aload_0
         1: iload_1
         2: invokestatic  #55                 // InterfaceMethod scala/Product.productElementName$:(Lscala/Product;I)Ljava/lang/String;
         5: areturn
      LineNumberTable:
        line 3: 0
      LocalVariableTable:
        Start  Length  Slot  Name   Signature
            0       6     0  this   Lcoursier/core/Latest;
            0       6     1     n   I
    MethodParameters:
      Name                           Flags
      n                              final

  public scala.collection.Iterator<java.lang.String> productElementNames();
    descriptor: ()Lscala/collection/Iterator;
    flags: (0x0001) ACC_PUBLIC
    Code:
      stack=1, locals=1, args_size=1
         0: aload_0
         1: invokestatic  #61                 // InterfaceMethod scala/Product.productElementNames$:(Lscala/Product;)Lscala/collection/Iterator;
         4: areturn
      LineNumberTable:
        line 3: 0
      LocalVariableTable:
        Start  Length  Slot  Name   Signature
            0       5     0  this   Lcoursier/core/Latest;
    Signature: #58                          // ()Lscala/collection/Iterator<Ljava/lang/String;>;

  public java.lang.String name();
    descriptor: ()Ljava/lang/String;
    flags: (0x0001) ACC_PUBLIC
    Code:
      stack=1, locals=1, args_size=1
         0: aload_0
         1: getfield      #63                 // Field name:Ljava/lang/String;
         4: areturn
      LineNumberTable:
        line 3: 0
      LocalVariableTable:
        Start  Length  Slot  Name   Signature
            0       5     0  this   Lcoursier/core/Latest;

  public coursier.core.Latest(java.lang.String);
    descriptor: (Ljava/lang/String;)V
    flags: (0x0001) ACC_PUBLIC
    Code:
      stack=2, locals=2, args_size=2
         0: aload_0
         1: aload_1
         2: putfield      #63                 // Field name:Ljava/lang/String;
         5: aload_0
         6: invokespecial #68                 // Method java/lang/Object."<init>":()V
         9: aload_0
        10: invokestatic  #72                 // InterfaceMethod scala/Product.$init$:(Lscala/Product;)V
        13: return
      LineNumberTable:
        line 3: 0
      LocalVariableTable:
        Start  Length  Slot  Name   Signature
            0      14     0  this   Lcoursier/core/Latest;
            0      14     1  name   Ljava/lang/String;
    MethodParameters:
      Name                           Flags
      name                           final
}
InnerClasses:
  public static #15= #14 of #2;           // =class coursier/core/Latest$Integration$ of class coursier/core/Latest
  public static #15= #17 of #2;           // =class coursier/core/Latest$Release$ of class coursier/core/Latest
  public static #15= #19 of #2;           // =class coursier/core/Latest$Stable$ of class coursier/core/Latest
SourceFile: "Latest.scala"
RuntimeVisibleAnnotations:
  0: #10(#11=s#12)
    scala.reflect.ScalaSignature(
      bytes="\u0006\u0005\u0005]c!\u0002\u0016,\u0003C\u0001\u0004\u0002\u0003$\u0001\u0005\u000b\u0007I\u0011A$\t\u0011A\u0003!\u0011!Q\u0001\n!CQ!\u0015\u0001\u0005\u0002I;a!!\u0016,\u0011\u0003\tg!\u0002\u0016,\u0011\u0003A\u0006\"B)\u0006\t\u0003\u0001w!\u00022\u0006\u0011\u0003\u001bgAB,\u0006\u0011\u0003\u000bI\u0005\u0003\u0004R\u0011\u0011\u0005\u00111\n\u0005\bU\"\t\t\u0011\"\u0011l\u0011\u001d\t\b\"!A\u0005\u0002ID\u0001B\u001e\u0005\u0002\u0002\u0013\u0005\u0011Q\n\u0005\b{\"\t\t\u0011\"\u0011\u007f\u0011%\tY\u0001CA\u0001\n\u0003\t\t\u0006C\u0005\u0002\u0018!\t\t\u0011\"\u0011\u0002\u001a!I\u00111\u0004\u0005\u0002\u0002\u0013\u0005\u0013Q\u0004\u0005\n\u0003?A\u0011\u0011!C\u0005\u0003C9Q!Z\u0003\t\u0002\u001a4QaZ\u0003\t\u0002\"DQ!U\n\u0005\u0002%DqA[\n\u0002\u0002\u0013\u00053\u000eC\u0004r\'\u0005\u0005I\u0011\u0001:\t\u000fY\u001c\u0012\u0011!C\u0001o\"9QpEA\u0001\n\u0003r\b\"CA\u0006\'\u0005\u0005I\u0011AA\u0007\u0011%\t9bEA\u0001\n\u0003\nI\u0002C\u0005\u0002\u001cM\t\t\u0011\"\u0011\u0002\u001e!I\u0011qD\n\u0002\u0002\u0013%\u0011\u0011E\u0004\b\u0003S)\u0001\u0012QA\u0016\r\u001d\ti#\u0002EA\u0003_Aa!\u0015\u0010\u0005\u0002\u0005E\u0002b\u00026\u001f\u0003\u0003%\te\u001b\u0005\bcz\t\t\u0011\"\u0001s\u0011!1h$!A\u0005\u0002\u0005M\u0002bB?\u001f\u0003\u0003%\tE \u0005\n\u0003\u0017q\u0012\u0011!C\u0001\u0003oA\u0011\"a\u0006\u001f\u0003\u0003%\t%!\u0007\t\u0013\u0005ma$!A\u0005B\u0005u\u0001\"CA\u0010=\u0005\u0005I\u0011BA\u0011\u0011\u001d\tY$\u0002C\u0001\u0003{A\u0011\"a\b\u0006\u0003\u0003%I!!\t\u0003\r1\u000bG/Z:u\u0015\taS&\u0001\u0003d_J,\'\"\u0001\u0018\u0002\u0011\r|WO]:jKJ\u001c\u0001a\u0005\u0003\u0001c]R\u0004C\u0001\u001a6\u001b\u0005\u0019$\"\u0001\u001b\u0002\u000bM\u001c\u0017\r\\1\n\u0005Y\u001a$AB!osJ+g\r\u0005\u00023q%\u0011\u0011h\r\u0002\b!J|G-^2u!\tY4I\u0004\u0002=\u0003:\u0011Q\bQ\u0007\u0002})\u0011qhL\u0001\u0007yI|w\u000e\u001e \n\u0003QJ!AQ\u001a\u0002\u000fA\f7m[1hK&\u0011A)\u0012\u0002\r\'\u0016\u0014\u0018.\u00197ju\u0006\u0014G.\u001a\u0006\u0003\u0005N\nAA\\1nKV\t\u0001\n\u0005\u0002J\u001b:\u0011!j\u0013\t\u0003{MJ!\u0001T\u001a\u0002\rA\u0013X\rZ3g\u0013\tquJ\u0001\u0004TiJLgn\u001a\u0006\u0003\u0019N\nQA\\1nK\u0002\na\u0001P5oSRtDCA*V!\t!\u0006!D\u0001,\u0011\u001515\u00011\u0001IS\u0011\u0001\u0001b\u0005\u0010\u0003\u0017%sG/Z4sCRLwN\\\n\u0004\u000bEJ\u0006C\u0001.`\u001b\u0005Y&B\u0001/^\u0003\tIwNC\u0001_\u0003\u0011Q\u0017M^1\n\u0005\u0011[F#A1\u0011\u0005Q+\u0011aC%oi\u0016<\'/\u0019;j_:\u0004\"\u0001\u001a\u0005\u000e\u0003\u0015\tqAU3mK\u0006\u001cX\r\u0005\u0002e\'\t9!+\u001a7fCN,7\u0003B\nToi\"\u0012AZ\u0001\u000eaJ|G-^2u!J,g-\u001b=\u0016\u00031\u0004\"!\u001c9\u000e\u00039T!a\\/\u0002\t1\fgnZ\u0005\u0003\u001d:\fA\u0002\u001d:pIV\u001cG/\u0011:jif,\u0012a\u001d\t\u0003eQL!!^\u001a\u0003\u0007%sG/\u0001\bqe>$Wo\u0019;FY\u0016lWM\u001c;\u0015\u0005a\\\bC\u0001\u001az\u0013\tQ8GA\u0002B]fDq\u0001`\f\u0002\u0002\u0003\u00071/A\u0002yIE\nq\u0002\u001d:pIV\u001cG/\u0013;fe\u0006$xN]\u000b\u0002\u007fB)\u0011\u0011AA\u0004q6\u0011\u00111\u0001\u0006\u0004\u0003\u000b\u0019\u0014AC2pY2,7\r^5p]&!\u0011\u0011BA\u0002\u0005!IE/\u001a:bi>\u0014\u0018\u0001C2b]\u0016\u000bX/\u00197\u0015\t\u0005=\u0011Q\u0003\t\u0004e\u0005E\u0011bAA\ng\t9!i\\8mK\u0006t\u0007b\u0002?\u001a\u0003\u0003\u0005\r\u0001_\u0001\tQ\u0006\u001c\bnQ8eKR\t1/\u0001\u0005u_N#(/\u001b8h)\u0005a\u0017\u0001D<sSR,\'+\u001a9mC\u000e,GCAA\u0012!\ri\u0017QE\u0005\u0004\u0003Oq\'AB(cU\u0016\u001cG/\u0001\u0004Ti\u0006\u0014G.\u001a\t\u0003Iz\u0011aa\u0015;bE2,7\u0003\u0002\u0010Toi\"\"!a\u000b\u0015\u0007a\f)\u0004C\u0004}E\u0005\u0005\t\u0019A:\u0015\t\u0005=\u0011\u0011\b\u0005\by\u0012\n\t\u00111\u0001y\u0003\u0015\t\u0007\u000f\u001d7z)\u0011\ty$!\u0012\u0011\tI\n\teU\u0005\u0004\u0003\u0007\u001a$AB(qi&|g\u000e\u0003\u0004\u0002H!\u0002\r\u0001S\u0001\u0002gN!\u0001bU\u001c;)\u0005\u0019Gc\u0001=\u0002P!9A\u0010DA\u0001\u0002\u0004\u0019H\u0003BA\b\u0003\'Bq\u0001 \b\u0002\u0002\u0003\u0007\u00010\u0001\u0004MCR,7\u000f\u001e"
    )
  ScalaInlineInfo: length = 0x22 (unknown attribute)
   01 00 00 06 00 42 00 43 01 00 16 00 2E 01 00 33
   00 34 01 00 3B 00 25 01 00 24 00 25 00 00 2D 00
   2E 00
  ScalaSig: length = 0x3 (unknown attribute)
   05 02 00
