Classfile /Users/mw/Projects/slang-braindump/.jar/jar11/assemble/slang-braindump/assemble/content/coursier/core/Module$.class
  Last modified May 29, 2022; size 1831 bytes
  SHA-256 checksum b3bcd38d56b24125775342c4954069ac71a7b9a2223c067f3fac0966d472d37d
  Compiled from "Definitions.scala"
public final class coursier.core.Module$ implements java.io.Serializable
  minor version: 0
  major version: 52
  flags: (0x0031) ACC_PUBLIC, ACC_FINAL, ACC_SUPER
  this_class: #2                          // coursier/core/Module$
  super_class: #4                         // java/lang/Object
  interfaces: 1, fields: 2, methods: 5, attributes: 3
Constant pool:
   #1 = Utf8               coursier/core/Module$
   #2 = Class              #1             // coursier/core/Module$
   #3 = Utf8               java/lang/Object
   #4 = Class              #3             // java/lang/Object
   #5 = Utf8               java/io/Serializable
   #6 = Class              #5             // java/io/Serializable
   #7 = Utf8               Definitions.scala
   #8 = Utf8               MODULE$
   #9 = Utf8               Lcoursier/core/Module$;
  #10 = Utf8               instanceCache
  #11 = Utf8               Ljava/util/concurrent/ConcurrentMap;
  #12 = Utf8               Ljava/util/concurrent/ConcurrentMap<Lcoursier/core/Module;Lcoursier/core/Module;>;
  #13 = Utf8               <clinit>
  #14 = Utf8               ()V
  #15 = Utf8               <init>
  #16 = NameAndType        #15:#14        // "<init>":()V
  #17 = Methodref          #2.#16         // coursier/core/Module$."<init>":()V
  #18 = NameAndType        #8:#9          // MODULE$:Lcoursier/core/Module$;
  #19 = Fieldref           #2.#18         // coursier/core/Module$.MODULE$:Lcoursier/core/Module$;
  #20 = Utf8               coursier/util/Cache$
  #21 = Class              #20            // coursier/util/Cache$
  #22 = Utf8               Lcoursier/util/Cache$;
  #23 = NameAndType        #8:#22         // MODULE$:Lcoursier/util/Cache$;
  #24 = Fieldref           #21.#23        // coursier/util/Cache$.MODULE$:Lcoursier/util/Cache$;
  #25 = Utf8               createCache
  #26 = Utf8               ()Ljava/util/concurrent/ConcurrentMap;
  #27 = NameAndType        #25:#26        // createCache:()Ljava/util/concurrent/ConcurrentMap;
  #28 = Methodref          #21.#27        // coursier/util/Cache$.createCache:()Ljava/util/concurrent/ConcurrentMap;
  #29 = NameAndType        #10:#11        // instanceCache:Ljava/util/concurrent/ConcurrentMap;
  #30 = Fieldref           #2.#29         // coursier/core/Module$.instanceCache:Ljava/util/concurrent/ConcurrentMap;
  #31 = Utf8               ()Ljava/util/concurrent/ConcurrentMap<Lcoursier/core/Module;Lcoursier/core/Module;>;
  #32 = Utf8               this
  #33 = Utf8               apply
  #34 = Utf8               (Ljava/lang/String;Ljava/lang/String;Lscala/collection/immutable/Map;)Lcoursier/core/Module;
  #35 = Utf8               (Ljava/lang/String;Ljava/lang/String;Lscala/collection/immutable/Map<Ljava/lang/String;Ljava/lang/String;>;)Lcoursier/core/Module;
  #36 = Utf8               organization
  #37 = Utf8               name
  #38 = Utf8               attributes
  #39 = NameAndType        #10:#26        // instanceCache:()Ljava/util/concurrent/ConcurrentMap;
  #40 = Methodref          #2.#39         // coursier/core/Module$.instanceCache:()Ljava/util/concurrent/ConcurrentMap;
  #41 = Utf8               coursier/core/Module
  #42 = Class              #41            // coursier/core/Module
  #43 = Utf8               (Ljava/lang/String;Ljava/lang/String;Lscala/collection/immutable/Map;)V
  #44 = NameAndType        #15:#43        // "<init>":(Ljava/lang/String;Ljava/lang/String;Lscala/collection/immutable/Map;)V
  #45 = Methodref          #42.#44        // coursier/core/Module."<init>":(Ljava/lang/String;Ljava/lang/String;Lscala/collection/immutable/Map;)V
  #46 = Utf8               cacheMethod
  #47 = Utf8               (Ljava/util/concurrent/ConcurrentMap;Ljava/lang/Object;)Ljava/lang/Object;
  #48 = NameAndType        #46:#47        // cacheMethod:(Ljava/util/concurrent/ConcurrentMap;Ljava/lang/Object;)Ljava/lang/Object;
  #49 = Methodref          #21.#48        // coursier/util/Cache$.cacheMethod:(Ljava/util/concurrent/ConcurrentMap;Ljava/lang/Object;)Ljava/lang/Object;
  #50 = Utf8               Ljava/lang/String;
  #51 = Utf8               Lscala/collection/immutable/Map;
  #52 = Utf8               writeReplace
  #53 = Utf8               ()Ljava/lang/Object;
  #54 = Utf8               scala/runtime/ModuleSerializationProxy
  #55 = Class              #54            // scala/runtime/ModuleSerializationProxy
  #56 = Utf8               (Ljava/lang/Class;)V
  #57 = NameAndType        #15:#56        // "<init>":(Ljava/lang/Class;)V
  #58 = Methodref          #55.#57        // scala/runtime/ModuleSerializationProxy."<init>":(Ljava/lang/Class;)V
  #59 = Methodref          #4.#16         // java/lang/Object."<init>":()V
  #60 = Utf8               Signature
  #61 = Utf8               Code
  #62 = Utf8               LineNumberTable
  #63 = Utf8               LocalVariableTable
  #64 = Utf8               MethodParameters
  #65 = Utf8               SourceFile
  #66 = Utf8               ScalaInlineInfo
  #67 = Utf8               Scala
{
  public static final coursier.core.Module$ MODULE$;
    descriptor: Lcoursier/core/Module$;
    flags: (0x0019) ACC_PUBLIC, ACC_STATIC, ACC_FINAL

  private static final java.util.concurrent.ConcurrentMap<coursier.core.Module, coursier.core.Module> instanceCache;
    descriptor: Ljava/util/concurrent/ConcurrentMap;
    flags: (0x001a) ACC_PRIVATE, ACC_STATIC, ACC_FINAL
    Signature: #12                          // Ljava/util/concurrent/ConcurrentMap<Lcoursier/core/Module;Lcoursier/core/Module;>;

  public static {};
    descriptor: ()V
    flags: (0x0009) ACC_PUBLIC, ACC_STATIC
    Code:
      stack=2, locals=0, args_size=0
         0: new           #2                  // class coursier/core/Module$
         3: dup
         4: invokespecial #17                 // Method "<init>":()V
         7: putstatic     #19                 // Field MODULE$:Lcoursier/core/Module$;
        10: getstatic     #24                 // Field coursier/util/Cache$.MODULE$:Lcoursier/util/Cache$;
        13: invokevirtual #28                 // Method coursier/util/Cache$.createCache:()Ljava/util/concurrent/ConcurrentMap;
        16: putstatic     #30                 // Field instanceCache:Ljava/util/concurrent/ConcurrentMap;
        19: return
      LineNumberTable:
        line 37: 0
        line 77: 10
        line 76: 16
        line 37: 19

  public java.util.concurrent.ConcurrentMap<coursier.core.Module, coursier.core.Module> instanceCache();
    descriptor: ()Ljava/util/concurrent/ConcurrentMap;
    flags: (0x0001) ACC_PUBLIC
    Code:
      stack=1, locals=1, args_size=1
         0: getstatic     #30                 // Field instanceCache:Ljava/util/concurrent/ConcurrentMap;
         3: areturn
      LineNumberTable:
        line 76: 0
      LocalVariableTable:
        Start  Length  Slot  Name   Signature
            0       4     0  this   Lcoursier/core/Module$;
    Signature: #31                          // ()Ljava/util/concurrent/ConcurrentMap<Lcoursier/core/Module;Lcoursier/core/Module;>;

  public coursier.core.Module apply(java.lang.String, java.lang.String, scala.collection.immutable.Map<java.lang.String, java.lang.String>);
    descriptor: (Ljava/lang/String;Ljava/lang/String;Lscala/collection/immutable/Map;)Lcoursier/core/Module;
    flags: (0x0001) ACC_PUBLIC
    Code:
      stack=7, locals=4, args_size=4
         0: getstatic     #24                 // Field coursier/util/Cache$.MODULE$:Lcoursier/util/Cache$;
         3: aload_0
         4: invokevirtual #40                 // Method instanceCache:()Ljava/util/concurrent/ConcurrentMap;
         7: new           #42                 // class coursier/core/Module
        10: dup
        11: aload_1
        12: aload_2
        13: aload_3
        14: invokespecial #45                 // Method coursier/core/Module."<init>":(Ljava/lang/String;Ljava/lang/String;Lscala/collection/immutable/Map;)V
        17: invokevirtual #49                 // Method coursier/util/Cache$.cacheMethod:(Ljava/util/concurrent/ConcurrentMap;Ljava/lang/Object;)Ljava/lang/Object;
        20: checkcast     #42                 // class coursier/core/Module
        23: areturn
      LineNumberTable:
        line 80: 0
      LocalVariableTable:
        Start  Length  Slot  Name   Signature
            0      24     0  this   Lcoursier/core/Module$;
            0      24     1 organization   Ljava/lang/String;
            0      24     2  name   Ljava/lang/String;
            0      24     3 attributes   Lscala/collection/immutable/Map;
    Signature: #35                          // (Ljava/lang/String;Ljava/lang/String;Lscala/collection/immutable/Map<Ljava/lang/String;Ljava/lang/String;>;)Lcoursier/core/Module;
    MethodParameters:
      Name                           Flags
      organization                   final
      name                           final
      attributes                     final

  private java.lang.Object writeReplace();
    descriptor: ()Ljava/lang/Object;
    flags: (0x0002) ACC_PRIVATE
    Code:
      stack=3, locals=1, args_size=1
         0: new           #55                 // class scala/runtime/ModuleSerializationProxy
         3: dup
         4: ldc           #2                  // class coursier/core/Module$
         6: invokespecial #58                 // Method scala/runtime/ModuleSerializationProxy."<init>":(Ljava/lang/Class;)V
         9: areturn
      LineNumberTable:
        line 37: 0
      LocalVariableTable:
        Start  Length  Slot  Name   Signature
            0      10     0  this   Lcoursier/core/Module$;

  private coursier.core.Module$();
    descriptor: ()V
    flags: (0x0002) ACC_PRIVATE
    Code:
      stack=1, locals=1, args_size=1
         0: aload_0
         1: invokespecial #59                 // Method java/lang/Object."<init>":()V
         4: return
      LineNumberTable:
        line 83: 0
        line 37: 4
      LocalVariableTable:
        Start  Length  Slot  Name   Signature
            0       5     0  this   Lcoursier/core/Module$;
}
SourceFile: "Definitions.scala"
  ScalaInlineInfo: length = 0x18 (unknown attribute)
   01 01 00 04 00 0F 00 0E 01 00 21 00 22 01 00 0A
   00 1A 01 00 34 00 35 01
  Scala: length = 0x0 (unknown attribute)

