Classfile /Users/mw/Projects/slang-braindump/.jar/jar11/assemble/slang-braindump/assemble/content/coursier/core/ModuleName.class
  Last modified May 29, 2022; size 6411 bytes
  SHA-256 checksum 37e8bab0674a3485031e273139c1d00e9afa99e394d9e6450c2fd8d3f6b5e39b
  Compiled from "Definitions.scala"
public final class coursier.core.ModuleName implements scala.Product,java.io.Serializable
  minor version: 0
  major version: 52
  flags: (0x0031) ACC_PUBLIC, ACC_FINAL, ACC_SUPER
  this_class: #2                          // coursier/core/ModuleName
  super_class: #4                         // java/lang/Object
  interfaces: 2, fields: 1, methods: 30, attributes: 4
Constant pool:
    #1 = Utf8               coursier/core/ModuleName
    #2 = Class              #1            // coursier/core/ModuleName
    #3 = Utf8               java/lang/Object
    #4 = Class              #3            // java/lang/Object
    #5 = Utf8               scala/Product
    #6 = Class              #5            // scala/Product
    #7 = Utf8               java/io/Serializable
    #8 = Class              #7            // java/io/Serializable
    #9 = Utf8               Definitions.scala
   #10 = Utf8               Lscala/reflect/ScalaSignature;
   #11 = Utf8               bytes
   #12 = Utf8               \u0006\u0005\u0005-g\u0001\u0002\u0013&\u0005*B\u0001\u0002\u0011\u0001\u0003\u0016\u0004%\t!\u0011\u0005\t\u0015\u0002\u0011\t\u0012)A\u0005\u0005\")1\n\u0001C\u0001\u0019\")\u0001\u000b\u0001C\u0001#\"9q\u000bAA\u0001\n\u0003A\u0006b\u0002.\u0001#\u0003%\ta\u0017\u0005\bM\u0002\t\t\u0011\"\u0011h\u0011\u001dy\u0007!!A\u0005\u0002ADq\u0001\u001e\u0001\u0002\u0002\u0013\u0005Q\u000fC\u0004|\u0001\u0005\u0005I\u0011\t?\t\u0013\u0005\u001d\u0001!!A\u0005\u0002\u0005%\u0001\"CA\n\u0001\u0005\u0005I\u0011IA\u000b\u0011%\tI\u0002AA\u0001\n\u0003\nY\u0002C\u0005\u0002\u001e\u0001\t\t\u0011\"\u0011\u0002 !I\u00111\u0005\u0001\u0002\u0002\u0013\u0005\u0013QE\u0004\b\u0003O)\u0003\u0012AA\u0015\r\u0019!S\u0005#\u0001\u0002,!11*\u0005C\u0001\u0003{A\u0011\"a\u0010\u0012\u0005\u0004%\u0019!!\u0011\t\u0011\u0005%\u0013\u0003)A\u0005\u0003\u0007B\u0011\"a\u0013\u0012\u0003\u0003%\t)!\u0014\t\u0013\u0005E\u0013#!A\u0005\u0002\u0006M\u0003\"CA0#\u0005\u0005I\u0011BA1\u0011\u001d\tI\'\u0005C\u0003\u0003WB\u0011\"!\u001e\u0012\u0003\u0003%)!a\u001e\t\u0013\u0005}\u0014#%A\u0005\u0006\u0005\u0005\u0005\"CAC#\u0005\u0005IQAAD\u0011%\tY)EA\u0001\n\u000b\ti\tC\u0005\u0002\u0012F\t\t\u0011\"\u0002\u0002\u0014\"I\u00111T\t\u0002\u0002\u0013\u0015\u0011Q\u0014\u0005\n\u0003C\u000b\u0012\u0011!C\u0003\u0003GC\u0011\"a+\u0012\u0003\u0003%)!!,\t\u0013\u0005U\u0016#!A\u0005\u0006\u0005]\u0006\"CA^#\u0005\u0005IQAA_\u0011%\t)-EA\u0001\n\u000b\t9M\u0001\u0006N_\u0012,H.\u001a(b[\u0016T!AJ\u0014\u0002\t\r|\'/\u001a\u0006\u0002Q\u0005A1m\\;sg&,\'o\u0001\u0001\u0014\t\u0001Y\u0013\u0007\u000e\t\u0003Y=j\u0011!\f\u0006\u0002]\u0005)1oY1mC&\u0011\u0001\'\f\u0002\u0007\u0003:Lh+\u00197\u0011\u00051\u0012\u0014BA\u001a.\u0005\u001d\u0001&o\u001c3vGR\u0004\"!N\u001f\u000f\u0005YZdBA\u001c;\u001b\u0005A$BA\u001d*\u0003\u0019a$o\\8u}%\ta&\u0003\u0002=[\u00059\u0001/Y2lC\u001e,\u0017B\u0001 @\u00051\u0019VM]5bY&T\u0018M\u00197f\u0015\taT&A\u0003wC2,X-F\u0001C!\t\u0019uI\u0004\u0002E\u000bB\u0011q\'L\u0005\u0003\r6\na\u0001\u0015:fI\u00164\u0017B\u0001%J\u0005\u0019\u0019FO]5oO*\u0011a)L\u0001\u0007m\u0006dW/\u001a\u0011\u0002\rqJg.\u001b;?)\tiu\n\u0005\u0002O\u00015\tQ\u0005C\u0003A\u0007\u0001\u0007!)A\u0002nCB$\"!\u0014*\t\u000bM#\u0001\u0019\u0001+\u0002\u0003\u0019\u0004B\u0001L+C\u0005&\u0011a+\f\u0002\n\rVt7\r^5p]F\nAaY8qsR\u0011Q*\u0017\u0005\b\u0001\u0016\u0001\n\u00111\u0001C\u00039\u0019w\u000e]=%I\u00164\u0017-\u001e7uIE*\u0012\u0001\u0018\u0016\u0003\u0005v[\u0013A\u0018\t\u0003?\u0012l\u0011\u0001\u0019\u0006\u0003C\n\f\u0011\"\u001e8dQ\u0016\u001c7.\u001a3\u000b\u0005\rl\u0013AC1o]>$\u0018\r^5p]&\u0011Q\r\u0019\u0002\u0012k:\u001c\u0007.Z2lK\u00124\u0016M]5b]\u000e,\u0017!\u00049s_\u0012,8\r\u001e)sK\u001aL\u00070F\u0001i!\tIg.D\u0001k\u0015\tYG.\u0001\u0003mC:<\'\"A7\u0002\t)\fg/Y\u0005\u0003\u0011*\fA\u0002\u001d:pIV\u001cG/\u0011:jif,\u0012!\u001d\t\u0003YIL!a]\u0017\u0003\u0007%sG/\u0001\bqe>$Wo\u0019;FY\u0016lWM\u001c;\u0015\u0005YL\bC\u0001\u0017x\u0013\tAXFA\u0002B]fDqA_\u0005\u0002\u0002\u0003\u0007\u0011/A\u0002yIE\nq\u0002\u001d:pIV\u001cG/\u0013;fe\u0006$xN]\u000b\u0002{B!a0a\u0001w\u001b\u0005y(bAA\u0001[\u0005Q1m\u001c7mK\u000e$\u0018n\u001c8\n\u0007\u0005\u0015qP\u0001\u0005Ji\u0016\u0014\u0018\r^8s\u0003!\u0019\u0017M\\#rk\u0006dG\u0003BA\u0006\u0003#\u00012\u0001LA\u0007\u0013\r\ty!\f\u0002\b\u0005>|G.Z1o\u0011\u001dQ8\"!AA\u0002Y\f!\u0003\u001d:pIV\u001cG/\u00127f[\u0016tGOT1nKR\u0019\u0001.a\u0006\t\u000fid\u0011\u0011!a\u0001c\u0006A\u0001.Y:i\u0007>$W\rF\u0001r\u0003\u0019)\u0017/^1mgR!\u00111BA\u0011\u0011\u001dQh\"!AA\u0002Y\f\u0001\u0002^8TiJLgn\u001a\u000b\u0002Q\u0006QQj\u001c3vY\u0016t\u0015-\\3\u0011\u00059\u000b2#B\t\u0002.\u0005M\u0002c\u0001\u0017\u00020%\u0019\u0011\u0011G\u0017\u0003\r\u0005s\u0017PU3g!\u0011\t)$a\u000f\u000e\u0005\u0005]\"bAA\u001dY\u0006\u0011\u0011n\\\u0005\u0004}\u0005]BCAA\u0015\u0003!y\'\u000fZ3sS:<WCAA\"!\u0011)\u0014QI\'\n\u0007\u0005\u001dsH\u0001\u0005Pe\u0012,\'/\u001b8h\u0003%y\'\u000fZ3sS:<\u0007%A\u0003baBd\u0017\u0010F\u0002N\u0003\u001fBQ\u0001Q\u000bA\u0002\t\u000bq!\u001e8baBd\u0017\u0010\u0006\u0003\u0002V\u0005m\u0003\u0003\u0002\u0017\u0002X\tK1!!\u0017.\u0005\u0019y\u0005\u000f^5p]\"A\u0011Q\f\f\u0002\u0002\u0003\u0007Q*A\u0002yIA\nAb\u001e:ji\u0016\u0014V\r\u001d7bG\u0016$\"!a\u0019\u0011\u0007%\f)\'C\u0002\u0002h)\u0014aa\u00142kK\u000e$\u0018!D7ba\u0012*\u0007\u0010^3og&|g\u000e\u0006\u0003\u0002n\u0005EDcA\'\u0002p!)1\u000b\u0007a\u0001)\"1\u00111\u000f\rA\u00025\u000bQ\u0001\n;iSN\fabY8qs\u0012*\u0007\u0010^3og&|g\u000e\u0006\u0003\u0002z\u0005uDcA\'\u0002|!9\u0001)\u0007I\u0001\u0002\u0004\u0011\u0005BBA:3\u0001\u0007Q*\u0001\rd_BLH\u0005Z3gCVdG\u000fJ\u0019%Kb$XM\\:j_:$2\u0001XAB\u0011\u0019\t\u0019H\u0007a\u0001\u001b\u00069\u0002O]8ek\u000e$\bK]3gSb$S\r\u001f;f]NLwN\u001c\u000b\u0004Q\u0006%\u0005BBA:7\u0001\u0007Q*\u0001\fqe>$Wo\u0019;Be&$\u0018\u0010J3yi\u0016t7/[8o)\r\t\u0018q\u0012\u0005\u0007\u0003gb\u0002\u0019A\'\u00021A\u0014x\u000eZ;di\u0016cW-\\3oi\u0012*\u0007\u0010^3og&|g\u000e\u0006\u0003\u0002\u0016\u0006eEc\u0001<\u0002\u0018\"9!0HA\u0001\u0002\u0004\t\bBBA:;\u0001\u0007Q*A\rqe>$Wo\u0019;Ji\u0016\u0014\u0018\r^8sI\u0015DH/\u001a8tS>tGcA?\u0002 \"1\u00111\u000f\u0010A\u00025\u000b!cY1o\u000bF,\u0018\r\u001c\u0013fqR,gn]5p]R!\u0011QUAU)\u0011\tY!a*\t\u000fi|\u0012\u0011!a\u0001m\"1\u00111O\u0010A\u00025\u000bA\u0004\u001d:pIV\u001cG/\u00127f[\u0016tGOT1nK\u0012*\u0007\u0010^3og&|g\u000e\u0006\u0003\u00020\u0006MFc\u00015\u00022\"9!\u0010IA\u0001\u0002\u0004\t\bBBA:A\u0001\u0007Q*\u0001\niCND7i\u001c3fI\u0015DH/\u001a8tS>tG\u0003BA\u000e\u0003sCa!a\u001d\"\u0001\u0004i\u0015\u0001E3rk\u0006d7\u000fJ3yi\u0016t7/[8o)\u0011\ty,a1\u0015\t\u0005-\u0011\u0011\u0019\u0005\bu\n\n\t\u00111\u0001w\u0011\u0019\t\u0019H\ta\u0001\u001b\u0006\u0011Bo\\*ue&tw\rJ3yi\u0016t7/[8o)\u0011\t)#!3\t\r\u0005M4\u00051\u0001N\u0001
   #13 = Utf8               value
   #14 = Utf8               Ljava/lang/String;
   #15 = Utf8               toString$extension
   #16 = Utf8               (Ljava/lang/String;)Ljava/lang/String;
   #17 = Utf8               $this
   #18 = Utf8               coursier/core/ModuleName$
   #19 = Class              #18           // coursier/core/ModuleName$
   #20 = Utf8               MODULE$
   #21 = Utf8               Lcoursier/core/ModuleName$;
   #22 = NameAndType        #20:#21       // MODULE$:Lcoursier/core/ModuleName$;
   #23 = Fieldref           #19.#22       // coursier/core/ModuleName$.MODULE$:Lcoursier/core/ModuleName$;
   #24 = NameAndType        #15:#16       // toString$extension:(Ljava/lang/String;)Ljava/lang/String;
   #25 = Methodref          #19.#24       // coursier/core/ModuleName$.toString$extension:(Ljava/lang/String;)Ljava/lang/String;
   #26 = Utf8               equals$extension
   #27 = Utf8               (Ljava/lang/String;Ljava/lang/Object;)Z
   #28 = Utf8               x$1
   #29 = NameAndType        #26:#27       // equals$extension:(Ljava/lang/String;Ljava/lang/Object;)Z
   #30 = Methodref          #19.#29       // coursier/core/ModuleName$.equals$extension:(Ljava/lang/String;Ljava/lang/Object;)Z
   #31 = Utf8               hashCode$extension
   #32 = Utf8               (Ljava/lang/String;)I
   #33 = NameAndType        #31:#32       // hashCode$extension:(Ljava/lang/String;)I
   #34 = Methodref          #19.#33       // coursier/core/ModuleName$.hashCode$extension:(Ljava/lang/String;)I
   #35 = Utf8               productElementName$extension
   #36 = Utf8               (Ljava/lang/String;I)Ljava/lang/String;
   #37 = NameAndType        #35:#36       // productElementName$extension:(Ljava/lang/String;I)Ljava/lang/String;
   #38 = Methodref          #19.#37       // coursier/core/ModuleName$.productElementName$extension:(Ljava/lang/String;I)Ljava/lang/String;
   #39 = Utf8               canEqual$extension
   #40 = NameAndType        #39:#27       // canEqual$extension:(Ljava/lang/String;Ljava/lang/Object;)Z
   #41 = Methodref          #19.#40       // coursier/core/ModuleName$.canEqual$extension:(Ljava/lang/String;Ljava/lang/Object;)Z
   #42 = Utf8               productIterator$extension
   #43 = Utf8               (Ljava/lang/String;)Lscala/collection/Iterator;
   #44 = Utf8               (Ljava/lang/String;)Lscala/collection/Iterator<Ljava/lang/Object;>;
   #45 = NameAndType        #42:#43       // productIterator$extension:(Ljava/lang/String;)Lscala/collection/Iterator;
   #46 = Methodref          #19.#45       // coursier/core/ModuleName$.productIterator$extension:(Ljava/lang/String;)Lscala/collection/Iterator;
   #47 = Utf8               productElement$extension
   #48 = Utf8               (Ljava/lang/String;I)Ljava/lang/Object;
   #49 = NameAndType        #47:#48       // productElement$extension:(Ljava/lang/String;I)Ljava/lang/Object;
   #50 = Methodref          #19.#49       // coursier/core/ModuleName$.productElement$extension:(Ljava/lang/String;I)Ljava/lang/Object;
   #51 = Utf8               productArity$extension
   #52 = NameAndType        #51:#32       // productArity$extension:(Ljava/lang/String;)I
   #53 = Methodref          #19.#52       // coursier/core/ModuleName$.productArity$extension:(Ljava/lang/String;)I
   #54 = Utf8               productPrefix$extension
   #55 = NameAndType        #54:#16       // productPrefix$extension:(Ljava/lang/String;)Ljava/lang/String;
   #56 = Methodref          #19.#55       // coursier/core/ModuleName$.productPrefix$extension:(Ljava/lang/String;)Ljava/lang/String;
   #57 = Utf8               copy$default$1$extension
   #58 = NameAndType        #57:#16       // copy$default$1$extension:(Ljava/lang/String;)Ljava/lang/String;
   #59 = Methodref          #19.#58       // coursier/core/ModuleName$.copy$default$1$extension:(Ljava/lang/String;)Ljava/lang/String;
   #60 = Utf8               copy$extension
   #61 = Utf8               (Ljava/lang/String;Ljava/lang/String;)Ljava/lang/String;
   #62 = NameAndType        #60:#61       // copy$extension:(Ljava/lang/String;Ljava/lang/String;)Ljava/lang/String;
   #63 = Methodref          #19.#62       // coursier/core/ModuleName$.copy$extension:(Ljava/lang/String;Ljava/lang/String;)Ljava/lang/String;
   #64 = Utf8               map$extension
   #65 = Utf8               (Ljava/lang/String;Lscala/Function1;)Ljava/lang/String;
   #66 = Utf8               f
   #67 = NameAndType        #64:#65       // map$extension:(Ljava/lang/String;Lscala/Function1;)Ljava/lang/String;
   #68 = Methodref          #19.#67       // coursier/core/ModuleName$.map$extension:(Ljava/lang/String;Lscala/Function1;)Ljava/lang/String;
   #69 = Utf8               unapply
   #70 = Utf8               (Ljava/lang/String;)Lscala/Option;
   #71 = Utf8               (Ljava/lang/String;)Lscala/Option<Ljava/lang/String;>;
   #72 = Utf8               x$0
   #73 = NameAndType        #69:#70       // unapply:(Ljava/lang/String;)Lscala/Option;
   #74 = Methodref          #19.#73       // coursier/core/ModuleName$.unapply:(Ljava/lang/String;)Lscala/Option;
   #75 = Utf8               apply
   #76 = NameAndType        #75:#16       // apply:(Ljava/lang/String;)Ljava/lang/String;
   #77 = Methodref          #19.#76       // coursier/core/ModuleName$.apply:(Ljava/lang/String;)Ljava/lang/String;
   #78 = Utf8               ordering
   #79 = Utf8               ()Lscala/math/Ordering;
   #80 = Utf8               ()Lscala/math/Ordering<Lcoursier/core/ModuleName;>;
   #81 = NameAndType        #78:#79       // ordering:()Lscala/math/Ordering;
   #82 = Methodref          #19.#81       // coursier/core/ModuleName$.ordering:()Lscala/math/Ordering;
   #83 = Utf8               productElementNames
   #84 = Utf8               ()Lscala/collection/Iterator;
   #85 = Utf8               ()Lscala/collection/Iterator<Ljava/lang/String;>;
   #86 = Utf8               productElementNames$
   #87 = Utf8               (Lscala/Product;)Lscala/collection/Iterator;
   #88 = NameAndType        #86:#87       // productElementNames$:(Lscala/Product;)Lscala/collection/Iterator;
   #89 = InterfaceMethodref #6.#88        // scala/Product.productElementNames$:(Lscala/Product;)Lscala/collection/Iterator;
   #90 = Utf8               this
   #91 = Utf8               Lcoursier/core/ModuleName;
   #92 = Utf8               ()Ljava/lang/String;
   #93 = NameAndType        #13:#14       // value:Ljava/lang/String;
   #94 = Fieldref           #2.#93        // coursier/core/ModuleName.value:Ljava/lang/String;
   #95 = Utf8               map
   #96 = Utf8               (Lscala/Function1;)Ljava/lang/String;
   #97 = Utf8               (Lscala/Function1<Ljava/lang/String;Ljava/lang/String;>;)Ljava/lang/String;
   #98 = NameAndType        #13:#92       // value:()Ljava/lang/String;
   #99 = Methodref          #2.#98        // coursier/core/ModuleName.value:()Ljava/lang/String;
  #100 = Utf8               Lscala/Function1;
  #101 = Utf8               copy
  #102 = Utf8               copy$default$1
  #103 = Utf8               productPrefix
  #104 = Utf8               productArity
  #105 = Utf8               ()I
  #106 = Utf8               productElement
  #107 = Utf8               (I)Ljava/lang/Object;
  #108 = Utf8               I
  #109 = Utf8               productIterator
  #110 = Utf8               ()Lscala/collection/Iterator<Ljava/lang/Object;>;
  #111 = Utf8               canEqual
  #112 = Utf8               (Ljava/lang/Object;)Z
  #113 = Utf8               Ljava/lang/Object;
  #114 = Utf8               productElementName
  #115 = Utf8               (I)Ljava/lang/String;
  #116 = Utf8               hashCode
  #117 = Utf8               equals
  #118 = Utf8               toString
  #119 = Utf8               <init>
  #120 = Utf8               (Ljava/lang/String;)V
  #121 = Utf8               ()V
  #122 = NameAndType        #119:#121     // "<init>":()V
  #123 = Methodref          #4.#122       // java/lang/Object."<init>":()V
  #124 = Utf8               $init$
  #125 = Utf8               (Lscala/Product;)V
  #126 = NameAndType        #124:#125     // $init$:(Lscala/Product;)V
  #127 = InterfaceMethodref #6.#126       // scala/Product.$init$:(Lscala/Product;)V
  #128 = Utf8               Code
  #129 = Utf8               MethodParameters
  #130 = Utf8               Signature
  #131 = Utf8               LineNumberTable
  #132 = Utf8               LocalVariableTable
  #133 = Utf8               SourceFile
  #134 = Utf8               RuntimeVisibleAnnotations
  #135 = Utf8               ScalaInlineInfo
  #136 = Utf8               ScalaSig
{
  private final java.lang.String value;
    descriptor: Ljava/lang/String;
    flags: (0x0012) ACC_PRIVATE, ACC_FINAL

  public static java.lang.String toString$extension(java.lang.String);
    descriptor: (Ljava/lang/String;)Ljava/lang/String;
    flags: (0x0009) ACC_PUBLIC, ACC_STATIC
    Code:
      stack=2, locals=1, args_size=1
         0: getstatic     #23                 // Field coursier/core/ModuleName$.MODULE$:Lcoursier/core/ModuleName$;
         3: aload_0
         4: invokevirtual #25                 // Method coursier/core/ModuleName$.toString$extension:(Ljava/lang/String;)Ljava/lang/String;
         7: areturn
    MethodParameters:
      Name                           Flags
      $this                          final

  public static boolean equals$extension(java.lang.String, java.lang.Object);
    descriptor: (Ljava/lang/String;Ljava/lang/Object;)Z
    flags: (0x0009) ACC_PUBLIC, ACC_STATIC
    Code:
      stack=3, locals=2, args_size=2
         0: getstatic     #23                 // Field coursier/core/ModuleName$.MODULE$:Lcoursier/core/ModuleName$;
         3: aload_0
         4: aload_1
         5: invokevirtual #30                 // Method coursier/core/ModuleName$.equals$extension:(Ljava/lang/String;Ljava/lang/Object;)Z
         8: ireturn
    MethodParameters:
      Name                           Flags
      $this                          final
      x$1                            final

  public static int hashCode$extension(java.lang.String);
    descriptor: (Ljava/lang/String;)I
    flags: (0x0009) ACC_PUBLIC, ACC_STATIC
    Code:
      stack=2, locals=1, args_size=1
         0: getstatic     #23                 // Field coursier/core/ModuleName$.MODULE$:Lcoursier/core/ModuleName$;
         3: aload_0
         4: invokevirtual #34                 // Method coursier/core/ModuleName$.hashCode$extension:(Ljava/lang/String;)I
         7: ireturn
    MethodParameters:
      Name                           Flags
      $this                          final

  public static java.lang.String productElementName$extension(java.lang.String, int);
    descriptor: (Ljava/lang/String;I)Ljava/lang/String;
    flags: (0x0009) ACC_PUBLIC, ACC_STATIC
    Code:
      stack=3, locals=2, args_size=2
         0: getstatic     #23                 // Field coursier/core/ModuleName$.MODULE$:Lcoursier/core/ModuleName$;
         3: aload_0
         4: iload_1
         5: invokevirtual #38                 // Method coursier/core/ModuleName$.productElementName$extension:(Ljava/lang/String;I)Ljava/lang/String;
         8: areturn
    MethodParameters:
      Name                           Flags
      $this                          final
      x$1                            final

  public static boolean canEqual$extension(java.lang.String, java.lang.Object);
    descriptor: (Ljava/lang/String;Ljava/lang/Object;)Z
    flags: (0x0009) ACC_PUBLIC, ACC_STATIC
    Code:
      stack=3, locals=2, args_size=2
         0: getstatic     #23                 // Field coursier/core/ModuleName$.MODULE$:Lcoursier/core/ModuleName$;
         3: aload_0
         4: aload_1
         5: invokevirtual #41                 // Method coursier/core/ModuleName$.canEqual$extension:(Ljava/lang/String;Ljava/lang/Object;)Z
         8: ireturn
    MethodParameters:
      Name                           Flags
      $this                          final
      x$1                            final

  public static scala.collection.Iterator<java.lang.Object> productIterator$extension(java.lang.String);
    descriptor: (Ljava/lang/String;)Lscala/collection/Iterator;
    flags: (0x0009) ACC_PUBLIC, ACC_STATIC
    Code:
      stack=2, locals=1, args_size=1
         0: getstatic     #23                 // Field coursier/core/ModuleName$.MODULE$:Lcoursier/core/ModuleName$;
         3: aload_0
         4: invokevirtual #46                 // Method coursier/core/ModuleName$.productIterator$extension:(Ljava/lang/String;)Lscala/collection/Iterator;
         7: areturn
    Signature: #44                          // (Ljava/lang/String;)Lscala/collection/Iterator<Ljava/lang/Object;>;
    MethodParameters:
      Name                           Flags
      $this                          final

  public static java.lang.Object productElement$extension(java.lang.String, int);
    descriptor: (Ljava/lang/String;I)Ljava/lang/Object;
    flags: (0x0009) ACC_PUBLIC, ACC_STATIC
    Code:
      stack=3, locals=2, args_size=2
         0: getstatic     #23                 // Field coursier/core/ModuleName$.MODULE$:Lcoursier/core/ModuleName$;
         3: aload_0
         4: iload_1
         5: invokevirtual #50                 // Method coursier/core/ModuleName$.productElement$extension:(Ljava/lang/String;I)Ljava/lang/Object;
         8: areturn
    MethodParameters:
      Name                           Flags
      $this                          final
      x$1                            final

  public static int productArity$extension(java.lang.String);
    descriptor: (Ljava/lang/String;)I
    flags: (0x0009) ACC_PUBLIC, ACC_STATIC
    Code:
      stack=2, locals=1, args_size=1
         0: getstatic     #23                 // Field coursier/core/ModuleName$.MODULE$:Lcoursier/core/ModuleName$;
         3: aload_0
         4: invokevirtual #53                 // Method coursier/core/ModuleName$.productArity$extension:(Ljava/lang/String;)I
         7: ireturn
    MethodParameters:
      Name                           Flags
      $this                          final

  public static java.lang.String productPrefix$extension(java.lang.String);
    descriptor: (Ljava/lang/String;)Ljava/lang/String;
    flags: (0x0009) ACC_PUBLIC, ACC_STATIC
    Code:
      stack=2, locals=1, args_size=1
         0: getstatic     #23                 // Field coursier/core/ModuleName$.MODULE$:Lcoursier/core/ModuleName$;
         3: aload_0
         4: invokevirtual #56                 // Method coursier/core/ModuleName$.productPrefix$extension:(Ljava/lang/String;)Ljava/lang/String;
         7: areturn
    MethodParameters:
      Name                           Flags
      $this                          final

  public static java.lang.String copy$default$1$extension(java.lang.String);
    descriptor: (Ljava/lang/String;)Ljava/lang/String;
    flags: (0x0009) ACC_PUBLIC, ACC_STATIC
    Code:
      stack=2, locals=1, args_size=1
         0: getstatic     #23                 // Field coursier/core/ModuleName$.MODULE$:Lcoursier/core/ModuleName$;
         3: aload_0
         4: invokevirtual #59                 // Method coursier/core/ModuleName$.copy$default$1$extension:(Ljava/lang/String;)Ljava/lang/String;
         7: areturn
    MethodParameters:
      Name                           Flags
      $this                          final

  public static java.lang.String copy$extension(java.lang.String, java.lang.String);
    descriptor: (Ljava/lang/String;Ljava/lang/String;)Ljava/lang/String;
    flags: (0x0009) ACC_PUBLIC, ACC_STATIC
    Code:
      stack=3, locals=2, args_size=2
         0: getstatic     #23                 // Field coursier/core/ModuleName$.MODULE$:Lcoursier/core/ModuleName$;
         3: aload_0
         4: aload_1
         5: invokevirtual #63                 // Method coursier/core/ModuleName$.copy$extension:(Ljava/lang/String;Ljava/lang/String;)Ljava/lang/String;
         8: areturn
    MethodParameters:
      Name                           Flags
      $this                          final
      value                          final

  public static java.lang.String map$extension(java.lang.String, scala.Function1);
    descriptor: (Ljava/lang/String;Lscala/Function1;)Ljava/lang/String;
    flags: (0x0009) ACC_PUBLIC, ACC_STATIC
    Code:
      stack=3, locals=2, args_size=2
         0: getstatic     #23                 // Field coursier/core/ModuleName$.MODULE$:Lcoursier/core/ModuleName$;
         3: aload_0
         4: aload_1
         5: invokevirtual #68                 // Method coursier/core/ModuleName$.map$extension:(Ljava/lang/String;Lscala/Function1;)Ljava/lang/String;
         8: areturn
    MethodParameters:
      Name                           Flags
      $this                          final
      f                              final

  public static scala.Option<java.lang.String> unapply(java.lang.String);
    descriptor: (Ljava/lang/String;)Lscala/Option;
    flags: (0x0009) ACC_PUBLIC, ACC_STATIC
    Code:
      stack=2, locals=1, args_size=1
         0: getstatic     #23                 // Field coursier/core/ModuleName$.MODULE$:Lcoursier/core/ModuleName$;
         3: aload_0
         4: invokevirtual #74                 // Method coursier/core/ModuleName$.unapply:(Ljava/lang/String;)Lscala/Option;
         7: areturn
    Signature: #71                          // (Ljava/lang/String;)Lscala/Option<Ljava/lang/String;>;
    MethodParameters:
      Name                           Flags
      x$0                            final

  public static java.lang.String apply(java.lang.String);
    descriptor: (Ljava/lang/String;)Ljava/lang/String;
    flags: (0x0009) ACC_PUBLIC, ACC_STATIC
    Code:
      stack=2, locals=1, args_size=1
         0: getstatic     #23                 // Field coursier/core/ModuleName$.MODULE$:Lcoursier/core/ModuleName$;
         3: aload_0
         4: invokevirtual #77                 // Method coursier/core/ModuleName$.apply:(Ljava/lang/String;)Ljava/lang/String;
         7: areturn
    MethodParameters:
      Name                           Flags
      value                          final

  public static scala.math.Ordering<coursier.core.ModuleName> ordering();
    descriptor: ()Lscala/math/Ordering;
    flags: (0x0009) ACC_PUBLIC, ACC_STATIC
    Code:
      stack=1, locals=0, args_size=0
         0: getstatic     #23                 // Field coursier/core/ModuleName$.MODULE$:Lcoursier/core/ModuleName$;
         3: invokevirtual #82                 // Method coursier/core/ModuleName$.ordering:()Lscala/math/Ordering;
         6: areturn
    Signature: #80                          // ()Lscala/math/Ordering<Lcoursier/core/ModuleName;>;

  public scala.collection.Iterator<java.lang.String> productElementNames();
    descriptor: ()Lscala/collection/Iterator;
    flags: (0x0001) ACC_PUBLIC
    Code:
      stack=1, locals=1, args_size=1
         0: aload_0
         1: invokestatic  #89                 // InterfaceMethod scala/Product.productElementNames$:(Lscala/Product;)Lscala/collection/Iterator;
         4: areturn
      LineNumberTable:
        line 18: 0
      LocalVariableTable:
        Start  Length  Slot  Name   Signature
            0       5     0  this   Lcoursier/core/ModuleName;
    Signature: #85                          // ()Lscala/collection/Iterator<Ljava/lang/String;>;

  public java.lang.String value();
    descriptor: ()Ljava/lang/String;
    flags: (0x0001) ACC_PUBLIC
    Code:
      stack=1, locals=1, args_size=1
         0: aload_0
         1: getfield      #94                 // Field value:Ljava/lang/String;
         4: areturn
      LineNumberTable:
        line 18: 0
      LocalVariableTable:
        Start  Length  Slot  Name   Signature
            0       5     0  this   Lcoursier/core/ModuleName;

  public java.lang.String map(scala.Function1<java.lang.String, java.lang.String>);
    descriptor: (Lscala/Function1;)Ljava/lang/String;
    flags: (0x0001) ACC_PUBLIC
    Code:
      stack=3, locals=2, args_size=2
         0: getstatic     #23                 // Field coursier/core/ModuleName$.MODULE$:Lcoursier/core/ModuleName$;
         3: aload_0
         4: invokevirtual #99                 // Method value:()Ljava/lang/String;
         7: aload_1
         8: invokevirtual #68                 // Method coursier/core/ModuleName$.map$extension:(Ljava/lang/String;Lscala/Function1;)Ljava/lang/String;
        11: areturn
      LineNumberTable:
        line 20: 0
      LocalVariableTable:
        Start  Length  Slot  Name   Signature
            0      12     0  this   Lcoursier/core/ModuleName;
            0      12     1     f   Lscala/Function1;
    Signature: #97                          // (Lscala/Function1<Ljava/lang/String;Ljava/lang/String;>;)Ljava/lang/String;
    MethodParameters:
      Name                           Flags
      f                              final

  public java.lang.String copy(java.lang.String);
    descriptor: (Ljava/lang/String;)Ljava/lang/String;
    flags: (0x0001) ACC_PUBLIC
    Code:
      stack=3, locals=2, args_size=2
         0: getstatic     #23                 // Field coursier/core/ModuleName$.MODULE$:Lcoursier/core/ModuleName$;
         3: aload_0
         4: invokevirtual #99                 // Method value:()Ljava/lang/String;
         7: aload_1
         8: invokevirtual #63                 // Method coursier/core/ModuleName$.copy$extension:(Ljava/lang/String;Ljava/lang/String;)Ljava/lang/String;
        11: areturn
      LineNumberTable:
        line 18: 0
      LocalVariableTable:
        Start  Length  Slot  Name   Signature
            0      12     0  this   Lcoursier/core/ModuleName;
            0      12     1 value   Ljava/lang/String;
    MethodParameters:
      Name                           Flags
      value                          final

  public java.lang.String copy$default$1();
    descriptor: ()Ljava/lang/String;
    flags: (0x0001) ACC_PUBLIC
    Code:
      stack=2, locals=1, args_size=1
         0: getstatic     #23                 // Field coursier/core/ModuleName$.MODULE$:Lcoursier/core/ModuleName$;
         3: aload_0
         4: invokevirtual #99                 // Method value:()Ljava/lang/String;
         7: invokevirtual #59                 // Method coursier/core/ModuleName$.copy$default$1$extension:(Ljava/lang/String;)Ljava/lang/String;
        10: areturn
      LineNumberTable:
        line 18: 0
      LocalVariableTable:
        Start  Length  Slot  Name   Signature
            0      11     0  this   Lcoursier/core/ModuleName;

  public java.lang.String productPrefix();
    descriptor: ()Ljava/lang/String;
    flags: (0x0001) ACC_PUBLIC
    Code:
      stack=2, locals=1, args_size=1
         0: getstatic     #23                 // Field coursier/core/ModuleName$.MODULE$:Lcoursier/core/ModuleName$;
         3: aload_0
         4: invokevirtual #99                 // Method value:()Ljava/lang/String;
         7: invokevirtual #56                 // Method coursier/core/ModuleName$.productPrefix$extension:(Ljava/lang/String;)Ljava/lang/String;
        10: areturn
      LineNumberTable:
        line 18: 0
      LocalVariableTable:
        Start  Length  Slot  Name   Signature
            0      11     0  this   Lcoursier/core/ModuleName;

  public int productArity();
    descriptor: ()I
    flags: (0x0001) ACC_PUBLIC
    Code:
      stack=2, locals=1, args_size=1
         0: getstatic     #23                 // Field coursier/core/ModuleName$.MODULE$:Lcoursier/core/ModuleName$;
         3: aload_0
         4: invokevirtual #99                 // Method value:()Ljava/lang/String;
         7: invokevirtual #53                 // Method coursier/core/ModuleName$.productArity$extension:(Ljava/lang/String;)I
        10: ireturn
      LineNumberTable:
        line 18: 0
      LocalVariableTable:
        Start  Length  Slot  Name   Signature
            0      11     0  this   Lcoursier/core/ModuleName;

  public java.lang.Object productElement(int);
    descriptor: (I)Ljava/lang/Object;
    flags: (0x0001) ACC_PUBLIC
    Code:
      stack=3, locals=2, args_size=2
         0: getstatic     #23                 // Field coursier/core/ModuleName$.MODULE$:Lcoursier/core/ModuleName$;
         3: aload_0
         4: invokevirtual #99                 // Method value:()Ljava/lang/String;
         7: iload_1
         8: invokevirtual #50                 // Method coursier/core/ModuleName$.productElement$extension:(Ljava/lang/String;I)Ljava/lang/Object;
        11: areturn
      LineNumberTable:
        line 18: 0
      LocalVariableTable:
        Start  Length  Slot  Name   Signature
            0      12     0  this   Lcoursier/core/ModuleName;
            0      12     1   x$1   I
    MethodParameters:
      Name                           Flags
      x$1                            final

  public scala.collection.Iterator<java.lang.Object> productIterator();
    descriptor: ()Lscala/collection/Iterator;
    flags: (0x0001) ACC_PUBLIC
    Code:
      stack=2, locals=1, args_size=1
         0: getstatic     #23                 // Field coursier/core/ModuleName$.MODULE$:Lcoursier/core/ModuleName$;
         3: aload_0
         4: invokevirtual #99                 // Method value:()Ljava/lang/String;
         7: invokevirtual #46                 // Method coursier/core/ModuleName$.productIterator$extension:(Ljava/lang/String;)Lscala/collection/Iterator;
        10: areturn
      LineNumberTable:
        line 18: 0
      LocalVariableTable:
        Start  Length  Slot  Name   Signature
            0      11     0  this   Lcoursier/core/ModuleName;
    Signature: #110                         // ()Lscala/collection/Iterator<Ljava/lang/Object;>;

  public boolean canEqual(java.lang.Object);
    descriptor: (Ljava/lang/Object;)Z
    flags: (0x0001) ACC_PUBLIC
    Code:
      stack=3, locals=2, args_size=2
         0: getstatic     #23                 // Field coursier/core/ModuleName$.MODULE$:Lcoursier/core/ModuleName$;
         3: aload_0
         4: invokevirtual #99                 // Method value:()Ljava/lang/String;
         7: aload_1
         8: invokevirtual #41                 // Method coursier/core/ModuleName$.canEqual$extension:(Ljava/lang/String;Ljava/lang/Object;)Z
        11: ireturn
      LineNumberTable:
        line 18: 0
      LocalVariableTable:
        Start  Length  Slot  Name   Signature
            0      12     0  this   Lcoursier/core/ModuleName;
            0      12     1   x$1   Ljava/lang/Object;
    MethodParameters:
      Name                           Flags
      x$1                            final

  public java.lang.String productElementName(int);
    descriptor: (I)Ljava/lang/String;
    flags: (0x0001) ACC_PUBLIC
    Code:
      stack=3, locals=2, args_size=2
         0: getstatic     #23                 // Field coursier/core/ModuleName$.MODULE$:Lcoursier/core/ModuleName$;
         3: aload_0
         4: invokevirtual #99                 // Method value:()Ljava/lang/String;
         7: iload_1
         8: invokevirtual #38                 // Method coursier/core/ModuleName$.productElementName$extension:(Ljava/lang/String;I)Ljava/lang/String;
        11: areturn
      LineNumberTable:
        line 18: 0
      LocalVariableTable:
        Start  Length  Slot  Name   Signature
            0      12     0  this   Lcoursier/core/ModuleName;
            0      12     1   x$1   I
    MethodParameters:
      Name                           Flags
      x$1                            final

  public int hashCode();
    descriptor: ()I
    flags: (0x0001) ACC_PUBLIC
    Code:
      stack=2, locals=1, args_size=1
         0: getstatic     #23                 // Field coursier/core/ModuleName$.MODULE$:Lcoursier/core/ModuleName$;
         3: aload_0
         4: invokevirtual #99                 // Method value:()Ljava/lang/String;
         7: invokevirtual #34                 // Method coursier/core/ModuleName$.hashCode$extension:(Ljava/lang/String;)I
        10: ireturn
      LineNumberTable:
        line 18: 0
      LocalVariableTable:
        Start  Length  Slot  Name   Signature
            0      11     0  this   Lcoursier/core/ModuleName;

  public boolean equals(java.lang.Object);
    descriptor: (Ljava/lang/Object;)Z
    flags: (0x0001) ACC_PUBLIC
    Code:
      stack=3, locals=2, args_size=2
         0: getstatic     #23                 // Field coursier/core/ModuleName$.MODULE$:Lcoursier/core/ModuleName$;
         3: aload_0
         4: invokevirtual #99                 // Method value:()Ljava/lang/String;
         7: aload_1
         8: invokevirtual #30                 // Method coursier/core/ModuleName$.equals$extension:(Ljava/lang/String;Ljava/lang/Object;)Z
        11: ireturn
      LineNumberTable:
        line 18: 0
      LocalVariableTable:
        Start  Length  Slot  Name   Signature
            0      12     0  this   Lcoursier/core/ModuleName;
            0      12     1   x$1   Ljava/lang/Object;
    MethodParameters:
      Name                           Flags
      x$1                            final

  public java.lang.String toString();
    descriptor: ()Ljava/lang/String;
    flags: (0x0001) ACC_PUBLIC
    Code:
      stack=2, locals=1, args_size=1
         0: getstatic     #23                 // Field coursier/core/ModuleName$.MODULE$:Lcoursier/core/ModuleName$;
         3: aload_0
         4: invokevirtual #99                 // Method value:()Ljava/lang/String;
         7: invokevirtual #25                 // Method coursier/core/ModuleName$.toString$extension:(Ljava/lang/String;)Ljava/lang/String;
        10: areturn
      LineNumberTable:
        line 18: 0
      LocalVariableTable:
        Start  Length  Slot  Name   Signature
            0      11     0  this   Lcoursier/core/ModuleName;

  public coursier.core.ModuleName(java.lang.String);
    descriptor: (Ljava/lang/String;)V
    flags: (0x0001) ACC_PUBLIC
    Code:
      stack=2, locals=2, args_size=2
         0: aload_0
         1: aload_1
         2: putfield      #94                 // Field value:Ljava/lang/String;
         5: aload_0
         6: invokespecial #123                // Method java/lang/Object."<init>":()V
         9: aload_0
        10: invokestatic  #127                // InterfaceMethod scala/Product.$init$:(Lscala/Product;)V
        13: return
      LineNumberTable:
        line 18: 0
      LocalVariableTable:
        Start  Length  Slot  Name   Signature
            0      14     0  this   Lcoursier/core/ModuleName;
            0      14     1 value   Ljava/lang/String;
    MethodParameters:
      Name                           Flags
      value                          final
}
SourceFile: "Definitions.scala"
RuntimeVisibleAnnotations:
  0: #10(#11=s#12)
    scala.reflect.ScalaSignature(
      bytes="\u0006\u0005\u0005-g\u0001\u0002\u0013&\u0005*B\u0001\u0002\u0011\u0001\u0003\u0016\u0004%\t!\u0011\u0005\t\u0015\u0002\u0011\t\u0012)A\u0005\u0005\")1\n\u0001C\u0001\u0019\")\u0001\u000b\u0001C\u0001#\"9q\u000bAA\u0001\n\u0003A\u0006b\u0002.\u0001#\u0003%\ta\u0017\u0005\bM\u0002\t\t\u0011\"\u0011h\u0011\u001dy\u0007!!A\u0005\u0002ADq\u0001\u001e\u0001\u0002\u0002\u0013\u0005Q\u000fC\u0004|\u0001\u0005\u0005I\u0011\t?\t\u0013\u0005\u001d\u0001!!A\u0005\u0002\u0005%\u0001\"CA\n\u0001\u0005\u0005I\u0011IA\u000b\u0011%\tI\u0002AA\u0001\n\u0003\nY\u0002C\u0005\u0002\u001e\u0001\t\t\u0011\"\u0011\u0002 !I\u00111\u0005\u0001\u0002\u0002\u0013\u0005\u0013QE\u0004\b\u0003O)\u0003\u0012AA\u0015\r\u0019!S\u0005#\u0001\u0002,!11*\u0005C\u0001\u0003{A\u0011\"a\u0010\u0012\u0005\u0004%\u0019!!\u0011\t\u0011\u0005%\u0013\u0003)A\u0005\u0003\u0007B\u0011\"a\u0013\u0012\u0003\u0003%\t)!\u0014\t\u0013\u0005E\u0013#!A\u0005\u0002\u0006M\u0003\"CA0#\u0005\u0005I\u0011BA1\u0011\u001d\tI\'\u0005C\u0003\u0003WB\u0011\"!\u001e\u0012\u0003\u0003%)!a\u001e\t\u0013\u0005}\u0014#%A\u0005\u0006\u0005\u0005\u0005\"CAC#\u0005\u0005IQAAD\u0011%\tY)EA\u0001\n\u000b\ti\tC\u0005\u0002\u0012F\t\t\u0011\"\u0002\u0002\u0014\"I\u00111T\t\u0002\u0002\u0013\u0015\u0011Q\u0014\u0005\n\u0003C\u000b\u0012\u0011!C\u0003\u0003GC\u0011\"a+\u0012\u0003\u0003%)!!,\t\u0013\u0005U\u0016#!A\u0005\u0006\u0005]\u0006\"CA^#\u0005\u0005IQAA_\u0011%\t)-EA\u0001\n\u000b\t9M\u0001\u0006N_\u0012,H.\u001a(b[\u0016T!AJ\u0014\u0002\t\r|\'/\u001a\u0006\u0002Q\u0005A1m\\;sg&,\'o\u0001\u0001\u0014\t\u0001Y\u0013\u0007\u000e\t\u0003Y=j\u0011!\f\u0006\u0002]\u0005)1oY1mC&\u0011\u0001\'\f\u0002\u0007\u0003:Lh+\u00197\u0011\u00051\u0012\u0014BA\u001a.\u0005\u001d\u0001&o\u001c3vGR\u0004\"!N\u001f\u000f\u0005YZdBA\u001c;\u001b\u0005A$BA\u001d*\u0003\u0019a$o\\8u}%\ta&\u0003\u0002=[\u00059\u0001/Y2lC\u001e,\u0017B\u0001 @\u00051\u0019VM]5bY&T\u0018M\u00197f\u0015\taT&A\u0003wC2,X-F\u0001C!\t\u0019uI\u0004\u0002E\u000bB\u0011q\'L\u0005\u0003\r6\na\u0001\u0015:fI\u00164\u0017B\u0001%J\u0005\u0019\u0019FO]5oO*\u0011a)L\u0001\u0007m\u0006dW/\u001a\u0011\u0002\rqJg.\u001b;?)\tiu\n\u0005\u0002O\u00015\tQ\u0005C\u0003A\u0007\u0001\u0007!)A\u0002nCB$\"!\u0014*\t\u000bM#\u0001\u0019\u0001+\u0002\u0003\u0019\u0004B\u0001L+C\u0005&\u0011a+\f\u0002\n\rVt7\r^5p]F\nAaY8qsR\u0011Q*\u0017\u0005\b\u0001\u0016\u0001\n\u00111\u0001C\u00039\u0019w\u000e]=%I\u00164\u0017-\u001e7uIE*\u0012\u0001\u0018\u0016\u0003\u0005v[\u0013A\u0018\t\u0003?\u0012l\u0011\u0001\u0019\u0006\u0003C\n\f\u0011\"\u001e8dQ\u0016\u001c7.\u001a3\u000b\u0005\rl\u0013AC1o]>$\u0018\r^5p]&\u0011Q\r\u0019\u0002\u0012k:\u001c\u0007.Z2lK\u00124\u0016M]5b]\u000e,\u0017!\u00049s_\u0012,8\r\u001e)sK\u001aL\u00070F\u0001i!\tIg.D\u0001k\u0015\tYG.\u0001\u0003mC:<\'\"A7\u0002\t)\fg/Y\u0005\u0003\u0011*\fA\u0002\u001d:pIV\u001cG/\u0011:jif,\u0012!\u001d\t\u0003YIL!a]\u0017\u0003\u0007%sG/\u0001\bqe>$Wo\u0019;FY\u0016lWM\u001c;\u0015\u0005YL\bC\u0001\u0017x\u0013\tAXFA\u0002B]fDqA_\u0005\u0002\u0002\u0003\u0007\u0011/A\u0002yIE\nq\u0002\u001d:pIV\u001cG/\u0013;fe\u0006$xN]\u000b\u0002{B!a0a\u0001w\u001b\u0005y(bAA\u0001[\u0005Q1m\u001c7mK\u000e$\u0018n\u001c8\n\u0007\u0005\u0015qP\u0001\u0005Ji\u0016\u0014\u0018\r^8s\u0003!\u0019\u0017M\\#rk\u0006dG\u0003BA\u0006\u0003#\u00012\u0001LA\u0007\u0013\r\ty!\f\u0002\b\u0005>|G.Z1o\u0011\u001dQ8\"!AA\u0002Y\f!\u0003\u001d:pIV\u001cG/\u00127f[\u0016tGOT1nKR\u0019\u0001.a\u0006\t\u000fid\u0011\u0011!a\u0001c\u0006A\u0001.Y:i\u0007>$W\rF\u0001r\u0003\u0019)\u0017/^1mgR!\u00111BA\u0011\u0011\u001dQh\"!AA\u0002Y\f\u0001\u0002^8TiJLgn\u001a\u000b\u0002Q\u0006QQj\u001c3vY\u0016t\u0015-\\3\u0011\u00059\u000b2#B\t\u0002.\u0005M\u0002c\u0001\u0017\u00020%\u0019\u0011\u0011G\u0017\u0003\r\u0005s\u0017PU3g!\u0011\t)$a\u000f\u000e\u0005\u0005]\"bAA\u001dY\u0006\u0011\u0011n\\\u0005\u0004}\u0005]BCAA\u0015\u0003!y\'\u000fZ3sS:<WCAA\"!\u0011)\u0014QI\'\n\u0007\u0005\u001dsH\u0001\u0005Pe\u0012,\'/\u001b8h\u0003%y\'\u000fZ3sS:<\u0007%A\u0003baBd\u0017\u0010F\u0002N\u0003\u001fBQ\u0001Q\u000bA\u0002\t\u000bq!\u001e8baBd\u0017\u0010\u0006\u0003\u0002V\u0005m\u0003\u0003\u0002\u0017\u0002X\tK1!!\u0017.\u0005\u0019y\u0005\u000f^5p]\"A\u0011Q\f\f\u0002\u0002\u0003\u0007Q*A\u0002yIA\nAb\u001e:ji\u0016\u0014V\r\u001d7bG\u0016$\"!a\u0019\u0011\u0007%\f)\'C\u0002\u0002h)\u0014aa\u00142kK\u000e$\u0018!D7ba\u0012*\u0007\u0010^3og&|g\u000e\u0006\u0003\u0002n\u0005EDcA\'\u0002p!)1\u000b\u0007a\u0001)\"1\u00111\u000f\rA\u00025\u000bQ\u0001\n;iSN\fabY8qs\u0012*\u0007\u0010^3og&|g\u000e\u0006\u0003\u0002z\u0005uDcA\'\u0002|!9\u0001)\u0007I\u0001\u0002\u0004\u0011\u0005BBA:3\u0001\u0007Q*\u0001\rd_BLH\u0005Z3gCVdG\u000fJ\u0019%Kb$XM\\:j_:$2\u0001XAB\u0011\u0019\t\u0019H\u0007a\u0001\u001b\u00069\u0002O]8ek\u000e$\bK]3gSb$S\r\u001f;f]NLwN\u001c\u000b\u0004Q\u0006%\u0005BBA:7\u0001\u0007Q*\u0001\fqe>$Wo\u0019;Be&$\u0018\u0010J3yi\u0016t7/[8o)\r\t\u0018q\u0012\u0005\u0007\u0003gb\u0002\u0019A\'\u00021A\u0014x\u000eZ;di\u0016cW-\\3oi\u0012*\u0007\u0010^3og&|g\u000e\u0006\u0003\u0002\u0016\u0006eEc\u0001<\u0002\u0018\"9!0HA\u0001\u0002\u0004\t\bBBA:;\u0001\u0007Q*A\rqe>$Wo\u0019;Ji\u0016\u0014\u0018\r^8sI\u0015DH/\u001a8tS>tGcA?\u0002 \"1\u00111\u000f\u0010A\u00025\u000b!cY1o\u000bF,\u0018\r\u001c\u0013fqR,gn]5p]R!\u0011QUAU)\u0011\tY!a*\t\u000fi|\u0012\u0011!a\u0001m\"1\u00111O\u0010A\u00025\u000bA\u0004\u001d:pIV\u001cG/\u00127f[\u0016tGOT1nK\u0012*\u0007\u0010^3og&|g\u000e\u0006\u0003\u00020\u0006MFc\u00015\u00022\"9!\u0010IA\u0001\u0002\u0004\t\bBBA:A\u0001\u0007Q*\u0001\niCND7i\u001c3fI\u0015DH/\u001a8tS>tG\u0003BA\u000e\u0003sCa!a\u001d\"\u0001\u0004i\u0015\u0001E3rk\u0006d7\u000fJ3yi\u0016t7/[8o)\u0011\ty,a1\u0015\t\u0005-\u0011\u0011\u0019\u0005\bu\n\n\t\u00111\u0001w\u0011\u0019\t\u0019H\ta\u0001\u001b\u0006\u0011Bo\\*ue&tw\rJ3yi\u0016t7/[8o)\u0011\t)#!3\t\r\u0005M4\u00051\u0001N\u0001"
    )
  ScalaInlineInfo: length = 0x4F (unknown attribute)
   01 01 00 0F 00 77 00 78 01 00 6F 00 70 01 00 65
   00 10 01 00 66 00 5C 01 00 75 00 70 01 00 74 00
   69 01 00 5F 00 60 01 00 68 00 69 01 00 6A 00 6B
   01 00 72 00 73 01 00 53 00 54 01 00 6D 00 54 01
   00 67 00 5C 01 00 76 00 5C 01 00 0D 00 5C 01
  ScalaSig: length = 0x3 (unknown attribute)
   05 02 00
