Classfile /Users/mw/Projects/slang-braindump/.jar/jar11/assemble/slang-braindump/assemble/content/coursier/core/Profile.class
  Last modified May 29, 2022; size 10004 bytes
  SHA-256 checksum b99d67780cc73c4dcaafba68a1ea60def15df25829c1c55cad49495073be24b2
  Compiled from "Definitions.scala"
public final class coursier.core.Profile implements scala.Product,java.io.Serializable
  minor version: 0
  major version: 52
  flags: (0x0031) ACC_PUBLIC, ACC_FINAL, ACC_SUPER
  this_class: #2                          // coursier/core/Profile
  super_class: #4                         // java/lang/Object
  interfaces: 2, fields: 6, methods: 25, attributes: 4
Constant pool:
    #1 = Utf8               coursier/core/Profile
    #2 = Class              #1            // coursier/core/Profile
    #3 = Utf8               java/lang/Object
    #4 = Class              #3            // java/lang/Object
    #5 = Utf8               scala/Product
    #6 = Class              #5            // scala/Product
    #7 = Utf8               java/io/Serializable
    #8 = Class              #7            // java/io/Serializable
    #9 = Utf8               Definitions.scala
   #10 = Utf8               Lscala/reflect/ScalaSignature;
   #11 = Utf8               bytes
   #12 = Utf8               \u0006\u0005\u0005Me\u0001\u0002\u0012$\u0005!B\u0001B\u0010\u0001\u0003\u0006\u0004%\ta\u0010\u0005\t\u0011\u0002\u0011\t\u0011)A\u0005\u0001\"A\u0011\n\u0001BC\u0002\u0013\u0005!\n\u0003\u0005R\u0001\t\u0005\t\u0015!\u0003L\u0011!\u0011\u0006A!b\u0001\n\u0003\u0019\u0006\u0002\u0003-\u0001\u0005\u0003\u0005\u000b\u0011\u0002+\t\u0011e\u0003!Q1A\u0005\u0002iC\u0001b\u001a\u0001\u0003\u0002\u0003\u0006Ia\u0017\u0005\tQ\u0002\u0011)\u0019!C\u00015\"A\u0011\u000e\u0001B\u0001B\u0003%1\f\u0003\u0005k\u0001\t\u0015\r\u0011\"\u0001l\u0011!y\u0007A!A!\u0002\u0013a\u0007\"\u00029\u0001\t\u0003\t\b\"B=\u0001\t\u0003Q\b\"\u0002?\u0001\t\u0003i\bBB@\u0001\t\u0003\t\t\u0001C\u0004\u0002\u0006\u0001!\t!a\u0002\t\u000f\u0005-\u0001\u0001\"\u0001\u0002\u000e!9\u0011\u0011\u0003\u0001\u0005\u0002\u0005M\u0001bBA\f\u0001\u0011\u0005\u0013\u0011\u0004\u0005\b\u0003S\u0001A\u0011IA\u0016\u0011\u001d\t9\u0004\u0001C!\u0003sAq!!\u0010\u0001\t\u0003\ny\u0004C\u0004\u0002H\u0001!I!!\u0013\t\u000f\u0005E\u0003\u0001\"\u0011\u0002T!9\u0011Q\u000b\u0001\u0005B\u0005]\u0003bBA-\u0001\u0011\u0005\u00131\f\u0005\b\u0003C\u0002A\u0011IA2\u000f\u001d\t9g\tE\u0001\u0003S2aAI\u0012\t\u0002\u0005-\u0004B\u00029\u001f\t\u0003\t9\bC\u0004\u0002zy!\t!a\u001f\t\u0013\u0005%e$!A\u0005\n\u0005-%a\u0002)s_\u001aLG.\u001a\u0006\u0003I\u0015\nAaY8sK*\ta%\u0001\u0005d_V\u00148/[3s\u0007\u0001\u0019B\u0001A\u00150eA\u0011!&L\u0007\u0002W)\tA&A\u0003tG\u0006d\u0017-\u0003\u0002/W\t1\u0011I\\=SK\u001a\u0004\"A\u000b\u0019\n\u0005EZ#a\u0002)s_\u0012,8\r\u001e\t\u0003gmr!\u0001N\u001d\u000f\u0005UBT\"\u0001\u001c\u000b\u0005]:\u0013A\u0002\u001fs_>$h(C\u0001-\u0013\tQ4&A\u0004qC\u000e\\\u0017mZ3\n\u0005qj$\u0001D*fe&\fG.\u001b>bE2,\'B\u0001\u001e,\u0003\tIG-F\u0001A!\t\tUI\u0004\u0002C\u0007B\u0011QgK\u0005\u0003\t.\na\u0001\u0015:fI\u00164\u0017B\u0001$H\u0005\u0019\u0019FO]5oO*\u0011AiK\u0001\u0004S\u0012\u0004\u0013aD1di&4XMQ=EK\u001a\fW\u000f\u001c;\u0016\u0003-\u00032A\u000b\'O\u0013\ti5F\u0001\u0004PaRLwN\u001c\t\u0003U=K!\u0001U\u0016\u0003\u000f\t{w\u000e\\3b]\u0006\u0001\u0012m\u0019;jm\u0016\u0014\u0015\u0010R3gCVdG\u000fI\u0001\u000bC\u000e$\u0018N^1uS>tW#\u0001+\u0011\u0005U3V\"A\u0012\n\u0005]\u001b#AC!di&4\u0018\r^5p]\u0006Y\u0011m\u0019;jm\u0006$\u0018n\u001c8!\u00031!W\r]3oI\u0016t7-[3t+\u0005Y\u0006cA\u001a]=&\u0011Q,\u0010\u0002\u0004\'\u0016\f\b\u0003\u0002\u0016`C\u0012L!\u0001Y\u0016\u0003\rQ+\b\u000f\\33!\t)&-\u0003\u0002dG\ti1i\u001c8gS\u001e,(/\u0019;j_:\u0004\"!V3\n\u0005\u0019\u001c#A\u0003#fa\u0016tG-\u001a8ds\u0006iA-\u001a9f]\u0012,gnY5fg\u0002\nA\u0003Z3qK:$WM\\2z\u001b\u0006t\u0017mZ3nK:$\u0018!\u00063fa\u0016tG-\u001a8ds6\u000bg.Y4f[\u0016tG\u000fI\u0001\u000baJ|\u0007/\u001a:uS\u0016\u001cX#\u00017\u0011\t\u0005k\u0007\tQ\u0005\u0003]\u001e\u00131!T1q\u0003-\u0001(o\u001c9feRLWm\u001d\u0011\u0002\rqJg.\u001b;?)\u001d\u00118\u000f^;wob\u0004\"!\u0016\u0001\t\u000byj\u0001\u0019\u0001!\t\u000b%k\u0001\u0019A&\t\u000bIk\u0001\u0019\u0001+\t\u000bek\u0001\u0019A.\t\u000b!l\u0001\u0019A.\t\u000b)l\u0001\u0019\u00017\u0002\r]LG\u000f[%e)\t\u00118\u0010C\u0003?\u001d\u0001\u0007\u0001)A\nxSRD\u0017i\u0019;jm\u0016\u0014\u0015\u0010R3gCVdG\u000f\u0006\u0002s}\")\u0011j\u0004a\u0001\u0017\u0006qq/\u001b;i\u0003\u000e$\u0018N^1uS>tGc\u0001:\u0002\u0004!)!\u000b\u0005a\u0001)\u0006\u0001r/\u001b;i\t\u0016\u0004XM\u001c3f]\u000eLWm\u001d\u000b\u0004e\u0006%\u0001\"B-\u0012\u0001\u0004Y\u0016\u0001G<ji\"$U\r]3oI\u0016t7-_\'b]\u0006<W-\\3oiR\u0019!/a\u0004\t\u000b!\u0014\u0002\u0019A.\u0002\u001d]LG\u000f\u001b)s_B,\'\u000f^5fgR\u0019!/!\u0006\t\u000b)\u001c\u0002\u0019\u00017\u0002\u0011Q|7\u000b\u001e:j]\u001e$\"!a\u0007\u0011\t\u0005u\u0011qE\u0007\u0003\u0003?QA!!\t\u0002$\u0005!A.\u00198h\u0015\t\t)#\u0001\u0003kCZ\f\u0017b\u0001$\u0002 \u0005A1-\u00198FcV\fG\u000eF\u0002O\u0003[Aq!a\f\u0016\u0001\u0004\t\t$A\u0002pE*\u00042AKA\u001a\u0013\r\t)d\u000b\u0002\u0004\u0003:L\u0018AB3rk\u0006d7\u000fF\u0002O\u0003wAq!a\f\u0017\u0001\u0004\t\t$\u0001\u0005iCND7i\u001c3f)\t\t\t\u0005E\u0002+\u0003\u0007J1!!\u0012,\u0005\rIe\u000e^\u0001\u0006iV\u0004H.Z\u000b\u0003\u0003\u0017\u0002\u0012BKA\'\u0001.#6l\u00177\n\u0007\u0005=3F\u0001\u0004UkBdWMN\u0001\u000eaJ|G-^2u!J,g-\u001b=\u0016\u0005\u0005m\u0011\u0001\u00049s_\u0012,8\r^!sSRLXCAA!\u00039\u0001(o\u001c3vGR,E.Z7f]R$B!!\r\u0002^!9\u0011qL\u000eA\u0002\u0005\u0005\u0013!\u00018\u0002%A\u0014x\u000eZ;di\u0016cW-\\3oi:\u000bW.\u001a\u000b\u0005\u00037\t)\u0007C\u0004\u0002`q\u0001\r!!\u0011\u0002\u000fA\u0013xNZ5mKB\u0011QKH\n\u0005=%\ni\u0007\u0005\u0003\u0002p\u0005UTBAA9\u0015\u0011\t\u0019(a\t\u0002\u0005%|\u0017b\u0001\u001f\u0002rQ\u0011\u0011\u0011N\u0001\u0006CB\u0004H.\u001f\u000b\u000ee\u0006u\u0014qPAA\u0003\u0007\u000b))a\"\t\u000by\u0002\u0003\u0019\u0001!\t\u000b%\u0003\u0003\u0019A&\t\u000bI\u0003\u0003\u0019\u0001+\t\u000be\u0003\u0003\u0019A.\t\u000b!\u0004\u0003\u0019A.\t\u000b)\u0004\u0003\u0019\u00017\u0002\u0019]\u0014\u0018\u000e^3SKBd\u0017mY3\u0015\u0005\u00055\u0005\u0003BA\u000f\u0003\u001fKA!!%\u0002 \t1qJ\u00196fGR\u0004
   #13 = Utf8               id
   #14 = Utf8               Ljava/lang/String;
   #15 = Utf8               activeByDefault
   #16 = Utf8               Lscala/Option;
   #17 = Utf8               Lscala/Option<Ljava/lang/Object;>;
   #18 = Utf8               activation
   #19 = Utf8               Lcoursier/core/Activation;
   #20 = Utf8               dependencies
   #21 = Utf8               Lscala/collection/immutable/Seq;
   #22 = Utf8               Lscala/collection/immutable/Seq<Lscala/Tuple2<Lcoursier/core/Configuration;Lcoursier/core/Dependency;>;>;
   #23 = Utf8               dependencyManagement
   #24 = Utf8               properties
   #25 = Utf8               Lscala/collection/immutable/Map;
   #26 = Utf8               Lscala/collection/immutable/Map<Ljava/lang/String;Ljava/lang/String;>;
   #27 = Utf8               apply
   #28 = Utf8               (Ljava/lang/String;Lscala/Option;Lcoursier/core/Activation;Lscala/collection/immutable/Seq;Lscala/collection/immutable/Seq;Lscala/collection/immutable/Map;)Lcoursier/core/Profile;
   #29 = Utf8               (Ljava/lang/String;Lscala/Option<Ljava/lang/Object;>;Lcoursier/core/Activation;Lscala/collection/immutable/Seq<Lscala/Tuple2<Lcoursier/core/Configuration;Lcoursier/core/Dependency;>;>;Lscala/collection/immutable/Seq<Lscala/Tuple2<Lcoursier/core/Configuration;Lcoursier/core/Dependency;>;>;Lscala/collection/immutable/Map<Ljava/lang/String;Ljava/lang/String;>;)Lcoursier/core/Profile;
   #30 = Utf8               coursier/core/Profile$
   #31 = Class              #30           // coursier/core/Profile$
   #32 = Utf8               MODULE$
   #33 = Utf8               Lcoursier/core/Profile$;
   #34 = NameAndType        #32:#33       // MODULE$:Lcoursier/core/Profile$;
   #35 = Fieldref           #31.#34       // coursier/core/Profile$.MODULE$:Lcoursier/core/Profile$;
   #36 = NameAndType        #27:#28       // apply:(Ljava/lang/String;Lscala/Option;Lcoursier/core/Activation;Lscala/collection/immutable/Seq;Lscala/collection/immutable/Seq;Lscala/collection/immutable/Map;)Lcoursier/core/Profile;
   #37 = Methodref          #31.#36       // coursier/core/Profile$.apply:(Ljava/lang/String;Lscala/Option;Lcoursier/core/Activation;Lscala/collection/immutable/Seq;Lscala/collection/immutable/Seq;Lscala/collection/immutable/Map;)Lcoursier/core/Profile;
   #38 = Utf8               productIterator
   #39 = Utf8               ()Lscala/collection/Iterator;
   #40 = Utf8               ()Lscala/collection/Iterator<Ljava/lang/Object;>;
   #41 = Utf8               productIterator$
   #42 = Utf8               (Lscala/Product;)Lscala/collection/Iterator;
   #43 = NameAndType        #41:#42       // productIterator$:(Lscala/Product;)Lscala/collection/Iterator;
   #44 = InterfaceMethodref #6.#43        // scala/Product.productIterator$:(Lscala/Product;)Lscala/collection/Iterator;
   #45 = Utf8               this
   #46 = Utf8               Lcoursier/core/Profile;
   #47 = Utf8               productElementNames
   #48 = Utf8               ()Lscala/collection/Iterator<Ljava/lang/String;>;
   #49 = Utf8               productElementNames$
   #50 = NameAndType        #49:#42       // productElementNames$:(Lscala/Product;)Lscala/collection/Iterator;
   #51 = InterfaceMethodref #6.#50        // scala/Product.productElementNames$:(Lscala/Product;)Lscala/collection/Iterator;
   #52 = Utf8               ()Ljava/lang/String;
   #53 = NameAndType        #13:#14       // id:Ljava/lang/String;
   #54 = Fieldref           #2.#53        // coursier/core/Profile.id:Ljava/lang/String;
   #55 = Utf8               ()Lscala/Option;
   #56 = Utf8               ()Lscala/Option<Ljava/lang/Object;>;
   #57 = NameAndType        #15:#16       // activeByDefault:Lscala/Option;
   #58 = Fieldref           #2.#57        // coursier/core/Profile.activeByDefault:Lscala/Option;
   #59 = Utf8               ()Lcoursier/core/Activation;
   #60 = NameAndType        #18:#19       // activation:Lcoursier/core/Activation;
   #61 = Fieldref           #2.#60        // coursier/core/Profile.activation:Lcoursier/core/Activation;
   #62 = Utf8               ()Lscala/collection/immutable/Seq;
   #63 = Utf8               ()Lscala/collection/immutable/Seq<Lscala/Tuple2<Lcoursier/core/Configuration;Lcoursier/core/Dependency;>;>;
   #64 = NameAndType        #20:#21       // dependencies:Lscala/collection/immutable/Seq;
   #65 = Fieldref           #2.#64        // coursier/core/Profile.dependencies:Lscala/collection/immutable/Seq;
   #66 = NameAndType        #23:#21       // dependencyManagement:Lscala/collection/immutable/Seq;
   #67 = Fieldref           #2.#66        // coursier/core/Profile.dependencyManagement:Lscala/collection/immutable/Seq;
   #68 = Utf8               ()Lscala/collection/immutable/Map;
   #69 = Utf8               ()Lscala/collection/immutable/Map<Ljava/lang/String;Ljava/lang/String;>;
   #70 = NameAndType        #24:#25       // properties:Lscala/collection/immutable/Map;
   #71 = Fieldref           #2.#70        // coursier/core/Profile.properties:Lscala/collection/immutable/Map;
   #72 = Utf8               withId
   #73 = Utf8               (Ljava/lang/String;)Lcoursier/core/Profile;
   #74 = NameAndType        #15:#55       // activeByDefault:()Lscala/Option;
   #75 = Methodref          #2.#74        // coursier/core/Profile.activeByDefault:()Lscala/Option;
   #76 = NameAndType        #18:#59       // activation:()Lcoursier/core/Activation;
   #77 = Methodref          #2.#76        // coursier/core/Profile.activation:()Lcoursier/core/Activation;
   #78 = NameAndType        #20:#62       // dependencies:()Lscala/collection/immutable/Seq;
   #79 = Methodref          #2.#78        // coursier/core/Profile.dependencies:()Lscala/collection/immutable/Seq;
   #80 = NameAndType        #23:#62       // dependencyManagement:()Lscala/collection/immutable/Seq;
   #81 = Methodref          #2.#80        // coursier/core/Profile.dependencyManagement:()Lscala/collection/immutable/Seq;
   #82 = NameAndType        #24:#68       // properties:()Lscala/collection/immutable/Map;
   #83 = Methodref          #2.#82        // coursier/core/Profile.properties:()Lscala/collection/immutable/Map;
   #84 = Utf8               <init>
   #85 = Utf8               (Ljava/lang/String;Lscala/Option;Lcoursier/core/Activation;Lscala/collection/immutable/Seq;Lscala/collection/immutable/Seq;Lscala/collection/immutable/Map;)V
   #86 = NameAndType        #84:#85       // "<init>":(Ljava/lang/String;Lscala/Option;Lcoursier/core/Activation;Lscala/collection/immutable/Seq;Lscala/collection/immutable/Seq;Lscala/collection/immutable/Map;)V
   #87 = Methodref          #2.#86        // coursier/core/Profile."<init>":(Ljava/lang/String;Lscala/Option;Lcoursier/core/Activation;Lscala/collection/immutable/Seq;Lscala/collection/immutable/Seq;Lscala/collection/immutable/Map;)V
   #88 = Utf8               withActiveByDefault
   #89 = Utf8               (Lscala/Option;)Lcoursier/core/Profile;
   #90 = Utf8               (Lscala/Option<Ljava/lang/Object;>;)Lcoursier/core/Profile;
   #91 = NameAndType        #13:#52       // id:()Ljava/lang/String;
   #92 = Methodref          #2.#91        // coursier/core/Profile.id:()Ljava/lang/String;
   #93 = Utf8               withActivation
   #94 = Utf8               (Lcoursier/core/Activation;)Lcoursier/core/Profile;
   #95 = Utf8               withDependencies
   #96 = Utf8               (Lscala/collection/immutable/Seq;)Lcoursier/core/Profile;
   #97 = Utf8               (Lscala/collection/immutable/Seq<Lscala/Tuple2<Lcoursier/core/Configuration;Lcoursier/core/Dependency;>;>;)Lcoursier/core/Profile;
   #98 = Utf8               withDependencyManagement
   #99 = Utf8               withProperties
  #100 = Utf8               (Lscala/collection/immutable/Map;)Lcoursier/core/Profile;
  #101 = Utf8               (Lscala/collection/immutable/Map<Ljava/lang/String;Ljava/lang/String;>;)Lcoursier/core/Profile;
  #102 = Utf8               toString
  #103 = Utf8               java/lang/StringBuilder
  #104 = Class              #103          // java/lang/StringBuilder
  #105 = Utf8               Profile(
  #106 = String             #105          // Profile(
  #107 = Utf8               (Ljava/lang/String;)V
  #108 = NameAndType        #84:#107      // "<init>":(Ljava/lang/String;)V
  #109 = Methodref          #104.#108     // java/lang/StringBuilder."<init>":(Ljava/lang/String;)V
  #110 = Utf8               java/lang/String
  #111 = Class              #110          // java/lang/String
  #112 = Utf8               valueOf
  #113 = Utf8               (Ljava/lang/Object;)Ljava/lang/String;
  #114 = NameAndType        #112:#113     // valueOf:(Ljava/lang/Object;)Ljava/lang/String;
  #115 = Methodref          #111.#114     // java/lang/String.valueOf:(Ljava/lang/Object;)Ljava/lang/String;
  #116 = Utf8               append
  #117 = Utf8               (Ljava/lang/String;)Ljava/lang/StringBuilder;
  #118 = NameAndType        #116:#117     // append:(Ljava/lang/String;)Ljava/lang/StringBuilder;
  #119 = Methodref          #104.#118     // java/lang/StringBuilder.append:(Ljava/lang/String;)Ljava/lang/StringBuilder;
  #120 = Utf8               ,
  #121 = String             #120          // ,
  #122 = Utf8               )
  #123 = String             #122          // )
  #124 = NameAndType        #102:#52      // toString:()Ljava/lang/String;
  #125 = Methodref          #104.#124     // java/lang/StringBuilder.toString:()Ljava/lang/String;
  #126 = Utf8               b
  #127 = Utf8               Ljava/lang/StringBuilder;
  #128 = Utf8               canEqual
  #129 = Utf8               (Ljava/lang/Object;)Z
  #130 = Utf8               obj
  #131 = Utf8               Ljava/lang/Object;
  #132 = Utf8               equals
  #133 = NameAndType        #128:#129     // canEqual:(Ljava/lang/Object;)Z
  #134 = Methodref          #2.#133       // coursier/core/Profile.canEqual:(Ljava/lang/Object;)Z
  #135 = NameAndType        #132:#129     // equals:(Ljava/lang/Object;)Z
  #136 = Methodref          #4.#135       // java/lang/Object.equals:(Ljava/lang/Object;)Z
  #137 = Utf8               scala/Option
  #138 = Class              #137          // scala/Option
  #139 = Utf8               coursier/core/Activation
  #140 = Class              #139          // coursier/core/Activation
  #141 = Utf8               scala/collection/immutable/Seq
  #142 = Class              #141          // scala/collection/immutable/Seq
  #143 = Utf8               scala/collection/immutable/Map
  #144 = Class              #143          // scala/collection/immutable/Map
  #145 = Utf8               other
  #146 = Utf8               hashCode
  #147 = Utf8               ()I
  #148 = Utf8               Profile
  #149 = String             #148          // Profile
  #150 = Utf8               scala/runtime/Statics
  #151 = Class              #150          // scala/runtime/Statics
  #152 = Utf8               anyHash
  #153 = Utf8               (Ljava/lang/Object;)I
  #154 = NameAndType        #152:#153     // anyHash:(Ljava/lang/Object;)I
  #155 = Methodref          #151.#154     // scala/runtime/Statics.anyHash:(Ljava/lang/Object;)I
  #156 = Utf8               code
  #157 = Utf8               I
  #158 = Utf8               tuple
  #159 = Utf8               ()Lscala/Tuple6;
  #160 = Utf8               ()Lscala/Tuple6<Ljava/lang/String;Lscala/Option<Ljava/lang/Object;>;Lcoursier/core/Activation;Lscala/collection/immutable/Seq<Lscala/Tuple2<Lcoursier/core/Configuration;Lcoursier/core/Dependency;>;>;Lscala/collection/immutable/Seq<Lscala/Tuple2<Lcoursier/core/Configuration;Lcoursier/core/Dependency;>;>;Lscala/collection/immutable/Map<Ljava/lang/String;Ljava/lang/String;>;>;
  #161 = Utf8               scala/Tuple6
  #162 = Class              #161          // scala/Tuple6
  #163 = Utf8               (Ljava/lang/Object;Ljava/lang/Object;Ljava/lang/Object;Ljava/lang/Object;Ljava/lang/Object;Ljava/lang/Object;)V
  #164 = NameAndType        #84:#163      // "<init>":(Ljava/lang/Object;Ljava/lang/Object;Ljava/lang/Object;Ljava/lang/Object;Ljava/lang/Object;Ljava/lang/Object;)V
  #165 = Methodref          #162.#164     // scala/Tuple6."<init>":(Ljava/lang/Object;Ljava/lang/Object;Ljava/lang/Object;Ljava/lang/Object;Ljava/lang/Object;Ljava/lang/Object;)V
  #166 = Utf8               productPrefix
  #167 = Utf8               productArity
  #168 = Utf8               productElement
  #169 = Utf8               (I)Ljava/lang/Object;
  #170 = Utf8               n
  #171 = Utf8               java/lang/IndexOutOfBoundsException
  #172 = Class              #171          // java/lang/IndexOutOfBoundsException
  #173 = Utf8               scala/runtime/BoxesRunTime
  #174 = Class              #173          // scala/runtime/BoxesRunTime
  #175 = Utf8               boxToInteger
  #176 = Utf8               (I)Ljava/lang/Integer;
  #177 = NameAndType        #175:#176     // boxToInteger:(I)Ljava/lang/Integer;
  #178 = Methodref          #174.#177     // scala/runtime/BoxesRunTime.boxToInteger:(I)Ljava/lang/Integer;
  #179 = Methodref          #4.#124       // java/lang/Object.toString:()Ljava/lang/String;
  #180 = Methodref          #172.#108     // java/lang/IndexOutOfBoundsException."<init>":(Ljava/lang/String;)V
  #181 = Utf8               productElementName
  #182 = Utf8               (I)Ljava/lang/String;
  #183 = String             #13           // id
  #184 = String             #15           // activeByDefault
  #185 = String             #18           // activation
  #186 = String             #20           // dependencies
  #187 = String             #23           // dependencyManagement
  #188 = String             #24           // properties
  #189 = Utf8               (Ljava/lang/String;Lscala/Option<Ljava/lang/Object;>;Lcoursier/core/Activation;Lscala/collection/immutable/Seq<Lscala/Tuple2<Lcoursier/core/Configuration;Lcoursier/core/Dependency;>;>;Lscala/collection/immutable/Seq<Lscala/Tuple2<Lcoursier/core/Configuration;Lcoursier/core/Dependency;>;>;Lscala/collection/immutable/Map<Ljava/lang/String;Ljava/lang/String;>;)V
  #190 = Utf8               ()V
  #191 = NameAndType        #84:#190      // "<init>":()V
  #192 = Methodref          #4.#191       // java/lang/Object."<init>":()V
  #193 = Utf8               $init$
  #194 = Utf8               (Lscala/Product;)V
  #195 = NameAndType        #193:#194     // $init$:(Lscala/Product;)V
  #196 = InterfaceMethodref #6.#195       // scala/Product.$init$:(Lscala/Product;)V
  #197 = Utf8               Signature
  #198 = Utf8               Code
  #199 = Utf8               MethodParameters
  #200 = Utf8               LineNumberTable
  #201 = Utf8               LocalVariableTable
  #202 = Utf8               StackMapTable
  #203 = Utf8               SourceFile
  #204 = Utf8               RuntimeVisibleAnnotations
  #205 = Utf8               ScalaInlineInfo
  #206 = Utf8               ScalaSig
{
  private final java.lang.String id;
    descriptor: Ljava/lang/String;
    flags: (0x0012) ACC_PRIVATE, ACC_FINAL

  private final scala.Option<java.lang.Object> activeByDefault;
    descriptor: Lscala/Option;
    flags: (0x0012) ACC_PRIVATE, ACC_FINAL
    Signature: #17                          // Lscala/Option<Ljava/lang/Object;>;

  private final coursier.core.Activation activation;
    descriptor: Lcoursier/core/Activation;
    flags: (0x0012) ACC_PRIVATE, ACC_FINAL

  private final scala.collection.immutable.Seq<scala.Tuple2<coursier.core.Configuration, coursier.core.Dependency>> dependencies;
    descriptor: Lscala/collection/immutable/Seq;
    flags: (0x0012) ACC_PRIVATE, ACC_FINAL
    Signature: #22                          // Lscala/collection/immutable/Seq<Lscala/Tuple2<Lcoursier/core/Configuration;Lcoursier/core/Dependency;>;>;

  private final scala.collection.immutable.Seq<scala.Tuple2<coursier.core.Configuration, coursier.core.Dependency>> dependencyManagement;
    descriptor: Lscala/collection/immutable/Seq;
    flags: (0x0012) ACC_PRIVATE, ACC_FINAL
    Signature: #22                          // Lscala/collection/immutable/Seq<Lscala/Tuple2<Lcoursier/core/Configuration;Lcoursier/core/Dependency;>;>;

  private final scala.collection.immutable.Map<java.lang.String, java.lang.String> properties;
    descriptor: Lscala/collection/immutable/Map;
    flags: (0x0012) ACC_PRIVATE, ACC_FINAL
    Signature: #26                          // Lscala/collection/immutable/Map<Ljava/lang/String;Ljava/lang/String;>;

  public static coursier.core.Profile apply(java.lang.String, scala.Option<java.lang.Object>, coursier.core.Activation, scala.collection.immutable.Seq<scala.Tuple2<coursier.core.Configuration, coursier.core.Dependency>>, scala.collection.immutable.Seq<scala.Tuple2<coursier.core.Configuration, coursier.core.Dependency>>, scala.collection.immutable.Map<java.lang.String, java.lang.String>);
    descriptor: (Ljava/lang/String;Lscala/Option;Lcoursier/core/Activation;Lscala/collection/immutable/Seq;Lscala/collection/immutable/Seq;Lscala/collection/immutable/Map;)Lcoursier/core/Profile;
    flags: (0x0009) ACC_PUBLIC, ACC_STATIC
    Code:
      stack=7, locals=6, args_size=6
         0: getstatic     #35                 // Field coursier/core/Profile$.MODULE$:Lcoursier/core/Profile$;
         3: aload_0
         4: aload_1
         5: aload_2
         6: aload_3
         7: aload         4
         9: aload         5
        11: invokevirtual #37                 // Method coursier/core/Profile$.apply:(Ljava/lang/String;Lscala/Option;Lcoursier/core/Activation;Lscala/collection/immutable/Seq;Lscala/collection/immutable/Seq;Lscala/collection/immutable/Map;)Lcoursier/core/Profile;
        14: areturn
    Signature: #29                          // (Ljava/lang/String;Lscala/Option<Ljava/lang/Object;>;Lcoursier/core/Activation;Lscala/collection/immutable/Seq<Lscala/Tuple2<Lcoursier/core/Configuration;Lcoursier/core/Dependency;>;>;Lscala/collection/immutable/Seq<Lscala/Tuple2<Lcoursier/core/Configuration;Lcoursier/core/Dependency;>;>;Lscala/collection/immutable/Map<Ljava/lang/String;Ljava/lang/String;>;)Lcoursier/core/Profile;
    MethodParameters:
      Name                           Flags
      id                             final
      activeByDefault                final
      activation                     final
      dependencies                   final
      dependencyManagement           final
      properties                     final

  public scala.collection.Iterator<java.lang.Object> productIterator();
    descriptor: ()Lscala/collection/Iterator;
    flags: (0x0001) ACC_PUBLIC
    Code:
      stack=1, locals=1, args_size=1
         0: aload_0
         1: invokestatic  #44                 // InterfaceMethod scala/Product.productIterator$:(Lscala/Product;)Lscala/collection/Iterator;
         4: areturn
      LineNumberTable:
        line 354: 0
      LocalVariableTable:
        Start  Length  Slot  Name   Signature
            0       5     0  this   Lcoursier/core/Profile;
    Signature: #40                          // ()Lscala/collection/Iterator<Ljava/lang/Object;>;

  public scala.collection.Iterator<java.lang.String> productElementNames();
    descriptor: ()Lscala/collection/Iterator;
    flags: (0x0001) ACC_PUBLIC
    Code:
      stack=1, locals=1, args_size=1
         0: aload_0
         1: invokestatic  #51                 // InterfaceMethod scala/Product.productElementNames$:(Lscala/Product;)Lscala/collection/Iterator;
         4: areturn
      LineNumberTable:
        line 354: 0
      LocalVariableTable:
        Start  Length  Slot  Name   Signature
            0       5     0  this   Lcoursier/core/Profile;
    Signature: #48                          // ()Lscala/collection/Iterator<Ljava/lang/String;>;

  public java.lang.String id();
    descriptor: ()Ljava/lang/String;
    flags: (0x0001) ACC_PUBLIC
    Code:
      stack=1, locals=1, args_size=1
         0: aload_0
         1: getfield      #54                 // Field id:Ljava/lang/String;
         4: areturn
      LineNumberTable:
        line 354: 0
      LocalVariableTable:
        Start  Length  Slot  Name   Signature
            0       5     0  this   Lcoursier/core/Profile;

  public scala.Option<java.lang.Object> activeByDefault();
    descriptor: ()Lscala/Option;
    flags: (0x0001) ACC_PUBLIC
    Code:
      stack=1, locals=1, args_size=1
         0: aload_0
         1: getfield      #58                 // Field activeByDefault:Lscala/Option;
         4: areturn
      LineNumberTable:
        line 354: 0
      LocalVariableTable:
        Start  Length  Slot  Name   Signature
            0       5     0  this   Lcoursier/core/Profile;
    Signature: #56                          // ()Lscala/Option<Ljava/lang/Object;>;

  public coursier.core.Activation activation();
    descriptor: ()Lcoursier/core/Activation;
    flags: (0x0001) ACC_PUBLIC
    Code:
      stack=1, locals=1, args_size=1
         0: aload_0
         1: getfield      #61                 // Field activation:Lcoursier/core/Activation;
         4: areturn
      LineNumberTable:
        line 354: 0
      LocalVariableTable:
        Start  Length  Slot  Name   Signature
            0       5     0  this   Lcoursier/core/Profile;

  public scala.collection.immutable.Seq<scala.Tuple2<coursier.core.Configuration, coursier.core.Dependency>> dependencies();
    descriptor: ()Lscala/collection/immutable/Seq;
    flags: (0x0001) ACC_PUBLIC
    Code:
      stack=1, locals=1, args_size=1
         0: aload_0
         1: getfield      #65                 // Field dependencies:Lscala/collection/immutable/Seq;
         4: areturn
      LineNumberTable:
        line 354: 0
      LocalVariableTable:
        Start  Length  Slot  Name   Signature
            0       5     0  this   Lcoursier/core/Profile;
    Signature: #63                          // ()Lscala/collection/immutable/Seq<Lscala/Tuple2<Lcoursier/core/Configuration;Lcoursier/core/Dependency;>;>;

  public scala.collection.immutable.Seq<scala.Tuple2<coursier.core.Configuration, coursier.core.Dependency>> dependencyManagement();
    descriptor: ()Lscala/collection/immutable/Seq;
    flags: (0x0001) ACC_PUBLIC
    Code:
      stack=1, locals=1, args_size=1
         0: aload_0
         1: getfield      #67                 // Field dependencyManagement:Lscala/collection/immutable/Seq;
         4: areturn
      LineNumberTable:
        line 354: 0
      LocalVariableTable:
        Start  Length  Slot  Name   Signature
            0       5     0  this   Lcoursier/core/Profile;
    Signature: #63                          // ()Lscala/collection/immutable/Seq<Lscala/Tuple2<Lcoursier/core/Configuration;Lcoursier/core/Dependency;>;>;

  public scala.collection.immutable.Map<java.lang.String, java.lang.String> properties();
    descriptor: ()Lscala/collection/immutable/Map;
    flags: (0x0001) ACC_PUBLIC
    Code:
      stack=1, locals=1, args_size=1
         0: aload_0
         1: getfield      #71                 // Field properties:Lscala/collection/immutable/Map;
         4: areturn
      LineNumberTable:
        line 354: 0
      LocalVariableTable:
        Start  Length  Slot  Name   Signature
            0       5     0  this   Lcoursier/core/Profile;
    Signature: #69                          // ()Lscala/collection/immutable/Map<Ljava/lang/String;Ljava/lang/String;>;

  public coursier.core.Profile withId(java.lang.String);
    descriptor: (Ljava/lang/String;)Lcoursier/core/Profile;
    flags: (0x0001) ACC_PUBLIC
    Code:
      stack=8, locals=2, args_size=2
         0: new           #2                  // class coursier/core/Profile
         3: dup
         4: aload_1
         5: aload_0
         6: invokevirtual #75                 // Method activeByDefault:()Lscala/Option;
         9: aload_0
        10: invokevirtual #77                 // Method activation:()Lcoursier/core/Activation;
        13: aload_0
        14: invokevirtual #79                 // Method dependencies:()Lscala/collection/immutable/Seq;
        17: aload_0
        18: invokevirtual #81                 // Method dependencyManagement:()Lscala/collection/immutable/Seq;
        21: aload_0
        22: invokevirtual #83                 // Method properties:()Lscala/collection/immutable/Map;
        25: invokespecial #87                 // Method "<init>":(Ljava/lang/String;Lscala/Option;Lcoursier/core/Activation;Lscala/collection/immutable/Seq;Lscala/collection/immutable/Seq;Lscala/collection/immutable/Map;)V
        28: areturn
      LineNumberTable:
        line 354: 0
      LocalVariableTable:
        Start  Length  Slot  Name   Signature
            0      29     0  this   Lcoursier/core/Profile;
            0      29     1    id   Ljava/lang/String;
    MethodParameters:
      Name                           Flags
      id                             final

  public coursier.core.Profile withActiveByDefault(scala.Option<java.lang.Object>);
    descriptor: (Lscala/Option;)Lcoursier/core/Profile;
    flags: (0x0001) ACC_PUBLIC
    Code:
      stack=8, locals=2, args_size=2
         0: new           #2                  // class coursier/core/Profile
         3: dup
         4: aload_0
         5: invokevirtual #92                 // Method id:()Ljava/lang/String;
         8: aload_1
         9: aload_0
        10: invokevirtual #77                 // Method activation:()Lcoursier/core/Activation;
        13: aload_0
        14: invokevirtual #79                 // Method dependencies:()Lscala/collection/immutable/Seq;
        17: aload_0
        18: invokevirtual #81                 // Method dependencyManagement:()Lscala/collection/immutable/Seq;
        21: aload_0
        22: invokevirtual #83                 // Method properties:()Lscala/collection/immutable/Map;
        25: invokespecial #87                 // Method "<init>":(Ljava/lang/String;Lscala/Option;Lcoursier/core/Activation;Lscala/collection/immutable/Seq;Lscala/collection/immutable/Seq;Lscala/collection/immutable/Map;)V
        28: areturn
      LineNumberTable:
        line 354: 0
      LocalVariableTable:
        Start  Length  Slot  Name   Signature
            0      29     0  this   Lcoursier/core/Profile;
            0      29     1 activeByDefault   Lscala/Option;
    Signature: #90                          // (Lscala/Option<Ljava/lang/Object;>;)Lcoursier/core/Profile;
    MethodParameters:
      Name                           Flags
      activeByDefault                final

  public coursier.core.Profile withActivation(coursier.core.Activation);
    descriptor: (Lcoursier/core/Activation;)Lcoursier/core/Profile;
    flags: (0x0001) ACC_PUBLIC
    Code:
      stack=8, locals=2, args_size=2
         0: new           #2                  // class coursier/core/Profile
         3: dup
         4: aload_0
         5: invokevirtual #92                 // Method id:()Ljava/lang/String;
         8: aload_0
         9: invokevirtual #75                 // Method activeByDefault:()Lscala/Option;
        12: aload_1
        13: aload_0
        14: invokevirtual #79                 // Method dependencies:()Lscala/collection/immutable/Seq;
        17: aload_0
        18: invokevirtual #81                 // Method dependencyManagement:()Lscala/collection/immutable/Seq;
        21: aload_0
        22: invokevirtual #83                 // Method properties:()Lscala/collection/immutable/Map;
        25: invokespecial #87                 // Method "<init>":(Ljava/lang/String;Lscala/Option;Lcoursier/core/Activation;Lscala/collection/immutable/Seq;Lscala/collection/immutable/Seq;Lscala/collection/immutable/Map;)V
        28: areturn
      LineNumberTable:
        line 354: 0
      LocalVariableTable:
        Start  Length  Slot  Name   Signature
            0      29     0  this   Lcoursier/core/Profile;
            0      29     1 activation   Lcoursier/core/Activation;
    MethodParameters:
      Name                           Flags
      activation                     final

  public coursier.core.Profile withDependencies(scala.collection.immutable.Seq<scala.Tuple2<coursier.core.Configuration, coursier.core.Dependency>>);
    descriptor: (Lscala/collection/immutable/Seq;)Lcoursier/core/Profile;
    flags: (0x0001) ACC_PUBLIC
    Code:
      stack=8, locals=2, args_size=2
         0: new           #2                  // class coursier/core/Profile
         3: dup
         4: aload_0
         5: invokevirtual #92                 // Method id:()Ljava/lang/String;
         8: aload_0
         9: invokevirtual #75                 // Method activeByDefault:()Lscala/Option;
        12: aload_0
        13: invokevirtual #77                 // Method activation:()Lcoursier/core/Activation;
        16: aload_1
        17: aload_0
        18: invokevirtual #81                 // Method dependencyManagement:()Lscala/collection/immutable/Seq;
        21: aload_0
        22: invokevirtual #83                 // Method properties:()Lscala/collection/immutable/Map;
        25: invokespecial #87                 // Method "<init>":(Ljava/lang/String;Lscala/Option;Lcoursier/core/Activation;Lscala/collection/immutable/Seq;Lscala/collection/immutable/Seq;Lscala/collection/immutable/Map;)V
        28: areturn
      LineNumberTable:
        line 354: 0
      LocalVariableTable:
        Start  Length  Slot  Name   Signature
            0      29     0  this   Lcoursier/core/Profile;
            0      29     1 dependencies   Lscala/collection/immutable/Seq;
    Signature: #97                          // (Lscala/collection/immutable/Seq<Lscala/Tuple2<Lcoursier/core/Configuration;Lcoursier/core/Dependency;>;>;)Lcoursier/core/Profile;
    MethodParameters:
      Name                           Flags
      dependencies                   final

  public coursier.core.Profile withDependencyManagement(scala.collection.immutable.Seq<scala.Tuple2<coursier.core.Configuration, coursier.core.Dependency>>);
    descriptor: (Lscala/collection/immutable/Seq;)Lcoursier/core/Profile;
    flags: (0x0001) ACC_PUBLIC
    Code:
      stack=8, locals=2, args_size=2
         0: new           #2                  // class coursier/core/Profile
         3: dup
         4: aload_0
         5: invokevirtual #92                 // Method id:()Ljava/lang/String;
         8: aload_0
         9: invokevirtual #75                 // Method activeByDefault:()Lscala/Option;
        12: aload_0
        13: invokevirtual #77                 // Method activation:()Lcoursier/core/Activation;
        16: aload_0
        17: invokevirtual #79                 // Method dependencies:()Lscala/collection/immutable/Seq;
        20: aload_1
        21: aload_0
        22: invokevirtual #83                 // Method properties:()Lscala/collection/immutable/Map;
        25: invokespecial #87                 // Method "<init>":(Ljava/lang/String;Lscala/Option;Lcoursier/core/Activation;Lscala/collection/immutable/Seq;Lscala/collection/immutable/Seq;Lscala/collection/immutable/Map;)V
        28: areturn
      LineNumberTable:
        line 354: 0
      LocalVariableTable:
        Start  Length  Slot  Name   Signature
            0      29     0  this   Lcoursier/core/Profile;
            0      29     1 dependencyManagement   Lscala/collection/immutable/Seq;
    Signature: #97                          // (Lscala/collection/immutable/Seq<Lscala/Tuple2<Lcoursier/core/Configuration;Lcoursier/core/Dependency;>;>;)Lcoursier/core/Profile;
    MethodParameters:
      Name                           Flags
      dependencyManagement           final

  public coursier.core.Profile withProperties(scala.collection.immutable.Map<java.lang.String, java.lang.String>);
    descriptor: (Lscala/collection/immutable/Map;)Lcoursier/core/Profile;
    flags: (0x0001) ACC_PUBLIC
    Code:
      stack=8, locals=2, args_size=2
         0: new           #2                  // class coursier/core/Profile
         3: dup
         4: aload_0
         5: invokevirtual #92                 // Method id:()Ljava/lang/String;
         8: aload_0
         9: invokevirtual #75                 // Method activeByDefault:()Lscala/Option;
        12: aload_0
        13: invokevirtual #77                 // Method activation:()Lcoursier/core/Activation;
        16: aload_0
        17: invokevirtual #79                 // Method dependencies:()Lscala/collection/immutable/Seq;
        20: aload_0
        21: invokevirtual #81                 // Method dependencyManagement:()Lscala/collection/immutable/Seq;
        24: aload_1
        25: invokespecial #87                 // Method "<init>":(Ljava/lang/String;Lscala/Option;Lcoursier/core/Activation;Lscala/collection/immutable/Seq;Lscala/collection/immutable/Seq;Lscala/collection/immutable/Map;)V
        28: areturn
      LineNumberTable:
        line 354: 0
      LocalVariableTable:
        Start  Length  Slot  Name   Signature
            0      29     0  this   Lcoursier/core/Profile;
            0      29     1 properties   Lscala/collection/immutable/Map;
    Signature: #101                         // (Lscala/collection/immutable/Map<Ljava/lang/String;Ljava/lang/String;>;)Lcoursier/core/Profile;
    MethodParameters:
      Name                           Flags
      properties                     final

  public java.lang.String toString();
    descriptor: ()Ljava/lang/String;
    flags: (0x0001) ACC_PUBLIC
    Code:
      stack=3, locals=2, args_size=1
         0: new           #104                // class java/lang/StringBuilder
         3: dup
         4: ldc           #106                // String Profile(
         6: invokespecial #109                // Method java/lang/StringBuilder."<init>":(Ljava/lang/String;)V
         9: astore_1
        10: aload_1
        11: aload_0
        12: invokevirtual #92                 // Method id:()Ljava/lang/String;
        15: invokestatic  #115                // Method java/lang/String.valueOf:(Ljava/lang/Object;)Ljava/lang/String;
        18: invokevirtual #119                // Method java/lang/StringBuilder.append:(Ljava/lang/String;)Ljava/lang/StringBuilder;
        21: pop
        22: aload_1
        23: ldc           #121                // String ,
        25: invokevirtual #119                // Method java/lang/StringBuilder.append:(Ljava/lang/String;)Ljava/lang/StringBuilder;
        28: pop
        29: aload_1
        30: aload_0
        31: invokevirtual #75                 // Method activeByDefault:()Lscala/Option;
        34: invokestatic  #115                // Method java/lang/String.valueOf:(Ljava/lang/Object;)Ljava/lang/String;
        37: invokevirtual #119                // Method java/lang/StringBuilder.append:(Ljava/lang/String;)Ljava/lang/StringBuilder;
        40: pop
        41: aload_1
        42: ldc           #121                // String ,
        44: invokevirtual #119                // Method java/lang/StringBuilder.append:(Ljava/lang/String;)Ljava/lang/StringBuilder;
        47: pop
        48: aload_1
        49: aload_0
        50: invokevirtual #77                 // Method activation:()Lcoursier/core/Activation;
        53: invokestatic  #115                // Method java/lang/String.valueOf:(Ljava/lang/Object;)Ljava/lang/String;
        56: invokevirtual #119                // Method java/lang/StringBuilder.append:(Ljava/lang/String;)Ljava/lang/StringBuilder;
        59: pop
        60: aload_1
        61: ldc           #121                // String ,
        63: invokevirtual #119                // Method java/lang/StringBuilder.append:(Ljava/lang/String;)Ljava/lang/StringBuilder;
        66: pop
        67: aload_1
        68: aload_0
        69: invokevirtual #79                 // Method dependencies:()Lscala/collection/immutable/Seq;
        72: invokestatic  #115                // Method java/lang/String.valueOf:(Ljava/lang/Object;)Ljava/lang/String;
        75: invokevirtual #119                // Method java/lang/StringBuilder.append:(Ljava/lang/String;)Ljava/lang/StringBuilder;
        78: pop
        79: aload_1
        80: ldc           #121                // String ,
        82: invokevirtual #119                // Method java/lang/StringBuilder.append:(Ljava/lang/String;)Ljava/lang/StringBuilder;
        85: pop
        86: aload_1
        87: aload_0
        88: invokevirtual #81                 // Method dependencyManagement:()Lscala/collection/immutable/Seq;
        91: invokestatic  #115                // Method java/lang/String.valueOf:(Ljava/lang/Object;)Ljava/lang/String;
        94: invokevirtual #119                // Method java/lang/StringBuilder.append:(Ljava/lang/String;)Ljava/lang/StringBuilder;
        97: pop
        98: aload_1
        99: ldc           #121                // String ,
       101: invokevirtual #119                // Method java/lang/StringBuilder.append:(Ljava/lang/String;)Ljava/lang/StringBuilder;
       104: pop
       105: aload_1
       106: aload_0
       107: invokevirtual #83                 // Method properties:()Lscala/collection/immutable/Map;
       110: invokestatic  #115                // Method java/lang/String.valueOf:(Ljava/lang/Object;)Ljava/lang/String;
       113: invokevirtual #119                // Method java/lang/StringBuilder.append:(Ljava/lang/String;)Ljava/lang/StringBuilder;
       116: pop
       117: aload_1
       118: ldc           #123                // String )
       120: invokevirtual #119                // Method java/lang/StringBuilder.append:(Ljava/lang/String;)Ljava/lang/StringBuilder;
       123: pop
       124: aload_1
       125: invokevirtual #125                // Method java/lang/StringBuilder.toString:()Ljava/lang/String;
       128: areturn
      LineNumberTable:
        line 354: 0
      LocalVariableTable:
        Start  Length  Slot  Name   Signature
           10     118     1     b   Ljava/lang/StringBuilder;
            0     129     0  this   Lcoursier/core/Profile;

  public boolean canEqual(java.lang.Object);
    descriptor: (Ljava/lang/Object;)Z
    flags: (0x0001) ACC_PUBLIC
    Code:
      stack=1, locals=2, args_size=2
         0: aload_1
         1: ifnull        15
         4: aload_1
         5: instanceof    #2                  // class coursier/core/Profile
         8: ifeq          15
        11: iconst_1
        12: goto          16
        15: iconst_0
        16: ireturn
      StackMapTable: number_of_entries = 2
        frame_type = 15 /* same */
        frame_type = 64 /* same_locals_1_stack_item */
          stack = [ int ]
      LineNumberTable:
        line 354: 0
      LocalVariableTable:
        Start  Length  Slot  Name   Signature
            0      17     0  this   Lcoursier/core/Profile;
            0      17     1   obj   Ljava/lang/Object;
    MethodParameters:
      Name                           Flags
      obj                            final

  public boolean equals(java.lang.Object);
    descriptor: (Ljava/lang/Object;)Z
    flags: (0x0001) ACC_PUBLIC
    Code:
      stack=2, locals=9, args_size=2
         0: aload_0
         1: aload_1
         2: if_acmpeq     213
         5: aload_0
         6: aload_1
         7: invokevirtual #134                // Method canEqual:(Ljava/lang/Object;)Z
        10: ifeq          217
        13: aload_1
        14: checkcast     #2                  // class coursier/core/Profile
        17: astore_2
        18: iconst_1
        19: ifeq          209
        22: aload_0
        23: invokevirtual #92                 // Method id:()Ljava/lang/String;
        26: aload_2
        27: invokevirtual #92                 // Method id:()Ljava/lang/String;
        30: astore_3
        31: dup
        32: ifnonnull     43
        35: pop
        36: aload_3
        37: ifnull        50
        40: goto          209
        43: aload_3
        44: invokevirtual #136                // Method java/lang/Object.equals:(Ljava/lang/Object;)Z
        47: ifeq          209
        50: aload_0
        51: invokevirtual #75                 // Method activeByDefault:()Lscala/Option;
        54: aload_2
        55: invokevirtual #75                 // Method activeByDefault:()Lscala/Option;
        58: astore        4
        60: dup
        61: ifnonnull     73
        64: pop
        65: aload         4
        67: ifnull        81
        70: goto          209
        73: aload         4
        75: invokevirtual #136                // Method java/lang/Object.equals:(Ljava/lang/Object;)Z
        78: ifeq          209
        81: aload_0
        82: invokevirtual #77                 // Method activation:()Lcoursier/core/Activation;
        85: aload_2
        86: invokevirtual #77                 // Method activation:()Lcoursier/core/Activation;
        89: astore        5
        91: dup
        92: ifnonnull     104
        95: pop
        96: aload         5
        98: ifnull        112
       101: goto          209
       104: aload         5
       106: invokevirtual #136                // Method java/lang/Object.equals:(Ljava/lang/Object;)Z
       109: ifeq          209
       112: aload_0
       113: invokevirtual #79                 // Method dependencies:()Lscala/collection/immutable/Seq;
       116: aload_2
       117: invokevirtual #79                 // Method dependencies:()Lscala/collection/immutable/Seq;
       120: astore        6
       122: dup
       123: ifnonnull     135
       126: pop
       127: aload         6
       129: ifnull        143
       132: goto          209
       135: aload         6
       137: invokevirtual #136                // Method java/lang/Object.equals:(Ljava/lang/Object;)Z
       140: ifeq          209
       143: aload_0
       144: invokevirtual #81                 // Method dependencyManagement:()Lscala/collection/immutable/Seq;
       147: aload_2
       148: invokevirtual #81                 // Method dependencyManagement:()Lscala/collection/immutable/Seq;
       151: astore        7
       153: dup
       154: ifnonnull     166
       157: pop
       158: aload         7
       160: ifnull        174
       163: goto          209
       166: aload         7
       168: invokevirtual #136                // Method java/lang/Object.equals:(Ljava/lang/Object;)Z
       171: ifeq          209
       174: aload_0
       175: invokevirtual #83                 // Method properties:()Lscala/collection/immutable/Map;
       178: aload_2
       179: invokevirtual #83                 // Method properties:()Lscala/collection/immutable/Map;
       182: astore        8
       184: dup
       185: ifnonnull     197
       188: pop
       189: aload         8
       191: ifnull        205
       194: goto          209
       197: aload         8
       199: invokevirtual #136                // Method java/lang/Object.equals:(Ljava/lang/Object;)Z
       202: ifeq          209
       205: iconst_1
       206: goto          210
       209: iconst_0
       210: ifeq          217
       213: iconst_1
       214: goto          218
       217: iconst_0
       218: ireturn
      StackMapTable: number_of_entries = 17
        frame_type = 255 /* full_frame */
          offset_delta = 43
          locals = [ class coursier/core/Profile, class java/lang/Object, class coursier/core/Profile, class java/lang/String ]
          stack = [ class java/lang/String ]
        frame_type = 6 /* same */
        frame_type = 255 /* full_frame */
          offset_delta = 22
          locals = [ class coursier/core/Profile, class java/lang/Object, class coursier/core/Profile, class java/lang/String, class scala/Option ]
          stack = [ class scala/Option ]
        frame_type = 7 /* same */
        frame_type = 255 /* full_frame */
          offset_delta = 22
          locals = [ class coursier/core/Profile, class java/lang/Object, class coursier/core/Profile, class java/lang/String, class scala/Option, class coursier/core/Activation ]
          stack = [ class coursier/core/Activation ]
        frame_type = 7 /* same */
        frame_type = 255 /* full_frame */
          offset_delta = 22
          locals = [ class coursier/core/Profile, class java/lang/Object, class coursier/core/Profile, class java/lang/String, class scala/Option, class coursier/core/Activation, class scala/collection/immutable/Seq ]
          stack = [ class scala/collection/immutable/Seq ]
        frame_type = 7 /* same */
        frame_type = 255 /* full_frame */
          offset_delta = 22
          locals = [ class coursier/core/Profile, class java/lang/Object, class coursier/core/Profile, class java/lang/String, class scala/Option, class coursier/core/Activation, class scala/collection/immutable/Seq, class scala/collection/immutable/Seq ]
          stack = [ class scala/collection/immutable/Seq ]
        frame_type = 7 /* same */
        frame_type = 255 /* full_frame */
          offset_delta = 22
          locals = [ class coursier/core/Profile, class java/lang/Object, class coursier/core/Profile, class java/lang/String, class scala/Option, class coursier/core/Activation, class scala/collection/immutable/Seq, class scala/collection/immutable/Seq, class scala/collection/immutable/Map ]
          stack = [ class scala/collection/immutable/Map ]
        frame_type = 7 /* same */
        frame_type = 255 /* full_frame */
          offset_delta = 3
          locals = [ class coursier/core/Profile, class java/lang/Object, class coursier/core/Profile ]
          stack = []
        frame_type = 64 /* same_locals_1_stack_item */
          stack = [ int ]
        frame_type = 250 /* chop */
          offset_delta = 2
        frame_type = 3 /* same */
        frame_type = 64 /* same_locals_1_stack_item */
          stack = [ int ]
      LineNumberTable:
        line 354: 0
      LocalVariableTable:
        Start  Length  Slot  Name   Signature
           18     192     2 other   Lcoursier/core/Profile;
            0     219     0  this   Lcoursier/core/Profile;
            0     219     1   obj   Ljava/lang/Object;
    MethodParameters:
      Name                           Flags
      obj                            final

  public int hashCode();
    descriptor: ()I
    flags: (0x0001) ACC_PUBLIC
    Code:
      stack=2, locals=2, args_size=1
         0: bipush        17
         2: ldc           #149                // String Profile
         4: invokestatic  #155                // Method scala/runtime/Statics.anyHash:(Ljava/lang/Object;)I
         7: iadd
         8: istore_1
         9: bipush        37
        11: iload_1
        12: imul
        13: aload_0
        14: invokevirtual #92                 // Method id:()Ljava/lang/String;
        17: invokestatic  #155                // Method scala/runtime/Statics.anyHash:(Ljava/lang/Object;)I
        20: iadd
        21: istore_1
        22: bipush        37
        24: iload_1
        25: imul
        26: aload_0
        27: invokevirtual #75                 // Method activeByDefault:()Lscala/Option;
        30: invokestatic  #155                // Method scala/runtime/Statics.anyHash:(Ljava/lang/Object;)I
        33: iadd
        34: istore_1
        35: bipush        37
        37: iload_1
        38: imul
        39: aload_0
        40: invokevirtual #77                 // Method activation:()Lcoursier/core/Activation;
        43: invokestatic  #155                // Method scala/runtime/Statics.anyHash:(Ljava/lang/Object;)I
        46: iadd
        47: istore_1
        48: bipush        37
        50: iload_1
        51: imul
        52: aload_0
        53: invokevirtual #79                 // Method dependencies:()Lscala/collection/immutable/Seq;
        56: invokestatic  #155                // Method scala/runtime/Statics.anyHash:(Ljava/lang/Object;)I
        59: iadd
        60: istore_1
        61: bipush        37
        63: iload_1
        64: imul
        65: aload_0
        66: invokevirtual #81                 // Method dependencyManagement:()Lscala/collection/immutable/Seq;
        69: invokestatic  #155                // Method scala/runtime/Statics.anyHash:(Ljava/lang/Object;)I
        72: iadd
        73: istore_1
        74: bipush        37
        76: iload_1
        77: imul
        78: aload_0
        79: invokevirtual #83                 // Method properties:()Lscala/collection/immutable/Map;
        82: invokestatic  #155                // Method scala/runtime/Statics.anyHash:(Ljava/lang/Object;)I
        85: iadd
        86: istore_1
        87: bipush        37
        89: iload_1
        90: imul
        91: ireturn
      LineNumberTable:
        line 354: 0
      LocalVariableTable:
        Start  Length  Slot  Name   Signature
            9      82     1  code   I
            0      92     0  this   Lcoursier/core/Profile;

  private scala.Tuple6<java.lang.String, scala.Option<java.lang.Object>, coursier.core.Activation, scala.collection.immutable.Seq<scala.Tuple2<coursier.core.Configuration, coursier.core.Dependency>>, scala.collection.immutable.Seq<scala.Tuple2<coursier.core.Configuration, coursier.core.Dependency>>, scala.collection.immutable.Map<java.lang.String, java.lang.String>> tuple();
    descriptor: ()Lscala/Tuple6;
    flags: (0x0002) ACC_PRIVATE
    Code:
      stack=8, locals=1, args_size=1
         0: new           #162                // class scala/Tuple6
         3: dup
         4: aload_0
         5: invokevirtual #92                 // Method id:()Ljava/lang/String;
         8: aload_0
         9: invokevirtual #75                 // Method activeByDefault:()Lscala/Option;
        12: aload_0
        13: invokevirtual #77                 // Method activation:()Lcoursier/core/Activation;
        16: aload_0
        17: invokevirtual #79                 // Method dependencies:()Lscala/collection/immutable/Seq;
        20: aload_0
        21: invokevirtual #81                 // Method dependencyManagement:()Lscala/collection/immutable/Seq;
        24: aload_0
        25: invokevirtual #83                 // Method properties:()Lscala/collection/immutable/Map;
        28: invokespecial #165                // Method scala/Tuple6."<init>":(Ljava/lang/Object;Ljava/lang/Object;Ljava/lang/Object;Ljava/lang/Object;Ljava/lang/Object;Ljava/lang/Object;)V
        31: areturn
      LineNumberTable:
        line 354: 0
      LocalVariableTable:
        Start  Length  Slot  Name   Signature
            0      32     0  this   Lcoursier/core/Profile;
    Signature: #160                         // ()Lscala/Tuple6<Ljava/lang/String;Lscala/Option<Ljava/lang/Object;>;Lcoursier/core/Activation;Lscala/collection/immutable/Seq<Lscala/Tuple2<Lcoursier/core/Configuration;Lcoursier/core/Dependency;>;>;Lscala/collection/immutable/Seq<Lscala/Tuple2<Lcoursier/core/Configuration;Lcoursier/core/Dependency;>;>;Lscala/collection/immutable/Map<Ljava/lang/String;Ljava/lang/String;>;>;

  public java.lang.String productPrefix();
    descriptor: ()Ljava/lang/String;
    flags: (0x0001) ACC_PUBLIC
    Code:
      stack=1, locals=1, args_size=1
         0: ldc           #149                // String Profile
         2: areturn
      LineNumberTable:
        line 354: 0
      LocalVariableTable:
        Start  Length  Slot  Name   Signature
            0       3     0  this   Lcoursier/core/Profile;

  public int productArity();
    descriptor: ()I
    flags: (0x0001) ACC_PUBLIC
    Code:
      stack=1, locals=1, args_size=1
         0: bipush        6
         2: ireturn
      LineNumberTable:
        line 354: 0
      LocalVariableTable:
        Start  Length  Slot  Name   Signature
            0       3     0  this   Lcoursier/core/Profile;

  public java.lang.Object productElement(int);
    descriptor: (I)Ljava/lang/Object;
    flags: (0x0001) ACC_PUBLIC
    Code:
      stack=3, locals=3, args_size=2
         0: iload_1
         1: istore_2
         2: iload_2
         3: tableswitch   { // 0 to 5
                       0: 40
                       1: 47
                       2: 54
                       3: 61
                       4: 68
                       5: 75
                 default: 82
            }
        40: aload_0
        41: invokevirtual #92                 // Method id:()Ljava/lang/String;
        44: goto          97
        47: aload_0
        48: invokevirtual #75                 // Method activeByDefault:()Lscala/Option;
        51: goto          97
        54: aload_0
        55: invokevirtual #77                 // Method activation:()Lcoursier/core/Activation;
        58: goto          97
        61: aload_0
        62: invokevirtual #79                 // Method dependencies:()Lscala/collection/immutable/Seq;
        65: goto          97
        68: aload_0
        69: invokevirtual #81                 // Method dependencyManagement:()Lscala/collection/immutable/Seq;
        72: goto          97
        75: aload_0
        76: invokevirtual #83                 // Method properties:()Lscala/collection/immutable/Map;
        79: goto          97
        82: new           #172                // class java/lang/IndexOutOfBoundsException
        85: dup
        86: iload_2
        87: invokestatic  #178                // Method scala/runtime/BoxesRunTime.boxToInteger:(I)Ljava/lang/Integer;
        90: invokevirtual #179                // Method java/lang/Object.toString:()Ljava/lang/String;
        93: invokespecial #180                // Method java/lang/IndexOutOfBoundsException."<init>":(Ljava/lang/String;)V
        96: athrow
        97: areturn
      StackMapTable: number_of_entries = 8
        frame_type = 252 /* append */
          offset_delta = 40
          locals = [ int ]
        frame_type = 6 /* same */
        frame_type = 6 /* same */
        frame_type = 6 /* same */
        frame_type = 6 /* same */
        frame_type = 6 /* same */
        frame_type = 6 /* same */
        frame_type = 78 /* same_locals_1_stack_item */
          stack = [ class java/lang/Object ]
      LineNumberTable:
        line 354: 0
      LocalVariableTable:
        Start  Length  Slot  Name   Signature
            0      98     0  this   Lcoursier/core/Profile;
            0      98     1     n   I
    MethodParameters:
      Name                           Flags
      n                              final

  public java.lang.String productElementName(int);
    descriptor: (I)Ljava/lang/String;
    flags: (0x0001) ACC_PUBLIC
    Code:
      stack=3, locals=3, args_size=2
         0: iload_1
         1: istore_2
         2: iload_2
         3: tableswitch   { // 0 to 5
                       0: 40
                       1: 45
                       2: 50
                       3: 55
                       4: 60
                       5: 65
                 default: 70
            }
        40: ldc           #183                // String id
        42: goto          85
        45: ldc           #184                // String activeByDefault
        47: goto          85
        50: ldc           #185                // String activation
        52: goto          85
        55: ldc           #186                // String dependencies
        57: goto          85
        60: ldc           #187                // String dependencyManagement
        62: goto          85
        65: ldc           #188                // String properties
        67: goto          85
        70: new           #172                // class java/lang/IndexOutOfBoundsException
        73: dup
        74: iload_2
        75: invokestatic  #178                // Method scala/runtime/BoxesRunTime.boxToInteger:(I)Ljava/lang/Integer;
        78: invokevirtual #179                // Method java/lang/Object.toString:()Ljava/lang/String;
        81: invokespecial #180                // Method java/lang/IndexOutOfBoundsException."<init>":(Ljava/lang/String;)V
        84: athrow
        85: areturn
      StackMapTable: number_of_entries = 8
        frame_type = 252 /* append */
          offset_delta = 40
          locals = [ int ]
        frame_type = 4 /* same */
        frame_type = 4 /* same */
        frame_type = 4 /* same */
        frame_type = 4 /* same */
        frame_type = 4 /* same */
        frame_type = 4 /* same */
        frame_type = 78 /* same_locals_1_stack_item */
          stack = [ class java/lang/String ]
      LineNumberTable:
        line 354: 0
      LocalVariableTable:
        Start  Length  Slot  Name   Signature
            0      86     0  this   Lcoursier/core/Profile;
            0      86     1     n   I
    MethodParameters:
      Name                           Flags
      n                              final

  public coursier.core.Profile(java.lang.String, scala.Option<java.lang.Object>, coursier.core.Activation, scala.collection.immutable.Seq<scala.Tuple2<coursier.core.Configuration, coursier.core.Dependency>>, scala.collection.immutable.Seq<scala.Tuple2<coursier.core.Configuration, coursier.core.Dependency>>, scala.collection.immutable.Map<java.lang.String, java.lang.String>);
    descriptor: (Ljava/lang/String;Lscala/Option;Lcoursier/core/Activation;Lscala/collection/immutable/Seq;Lscala/collection/immutable/Seq;Lscala/collection/immutable/Map;)V
    flags: (0x0001) ACC_PUBLIC
    Code:
      stack=2, locals=7, args_size=7
         0: aload_0
         1: aload_1
         2: putfield      #54                 // Field id:Ljava/lang/String;
         5: aload_0
         6: aload_2
         7: putfield      #58                 // Field activeByDefault:Lscala/Option;
        10: aload_0
        11: aload_3
        12: putfield      #61                 // Field activation:Lcoursier/core/Activation;
        15: aload_0
        16: aload         4
        18: putfield      #65                 // Field dependencies:Lscala/collection/immutable/Seq;
        21: aload_0
        22: aload         5
        24: putfield      #67                 // Field dependencyManagement:Lscala/collection/immutable/Seq;
        27: aload_0
        28: aload         6
        30: putfield      #71                 // Field properties:Lscala/collection/immutable/Map;
        33: aload_0
        34: invokespecial #192                // Method java/lang/Object."<init>":()V
        37: aload_0
        38: invokestatic  #196                // InterfaceMethod scala/Product.$init$:(Lscala/Product;)V
        41: return
      LineNumberTable:
        line 354: 0
        line 364: 33
        line 354: 41
      LocalVariableTable:
        Start  Length  Slot  Name   Signature
            0      42     0  this   Lcoursier/core/Profile;
            0      42     1    id   Ljava/lang/String;
            0      42     2 activeByDefault   Lscala/Option;
            0      42     3 activation   Lcoursier/core/Activation;
            0      42     4 dependencies   Lscala/collection/immutable/Seq;
            0      42     5 dependencyManagement   Lscala/collection/immutable/Seq;
            0      42     6 properties   Lscala/collection/immutable/Map;
    Signature: #189                         // (Ljava/lang/String;Lscala/Option<Ljava/lang/Object;>;Lcoursier/core/Activation;Lscala/collection/immutable/Seq<Lscala/Tuple2<Lcoursier/core/Configuration;Lcoursier/core/Dependency;>;>;Lscala/collection/immutable/Seq<Lscala/Tuple2<Lcoursier/core/Configuration;Lcoursier/core/Dependency;>;>;Lscala/collection/immutable/Map<Ljava/lang/String;Ljava/lang/String;>;)V
    MethodParameters:
      Name                           Flags
      id                             final
      activeByDefault                final
      activation                     final
      dependencies                   final
      dependencyManagement           final
      properties                     final
}
SourceFile: "Definitions.scala"
RuntimeVisibleAnnotations:
  0: #10(#11=s#12)
    scala.reflect.ScalaSignature(
      bytes="\u0006\u0005\u0005Me\u0001\u0002\u0012$\u0005!B\u0001B\u0010\u0001\u0003\u0006\u0004%\ta\u0010\u0005\t\u0011\u0002\u0011\t\u0011)A\u0005\u0001\"A\u0011\n\u0001BC\u0002\u0013\u0005!\n\u0003\u0005R\u0001\t\u0005\t\u0015!\u0003L\u0011!\u0011\u0006A!b\u0001\n\u0003\u0019\u0006\u0002\u0003-\u0001\u0005\u0003\u0005\u000b\u0011\u0002+\t\u0011e\u0003!Q1A\u0005\u0002iC\u0001b\u001a\u0001\u0003\u0002\u0003\u0006Ia\u0017\u0005\tQ\u0002\u0011)\u0019!C\u00015\"A\u0011\u000e\u0001B\u0001B\u0003%1\f\u0003\u0005k\u0001\t\u0015\r\u0011\"\u0001l\u0011!y\u0007A!A!\u0002\u0013a\u0007\"\u00029\u0001\t\u0003\t\b\"B=\u0001\t\u0003Q\b\"\u0002?\u0001\t\u0003i\bBB@\u0001\t\u0003\t\t\u0001C\u0004\u0002\u0006\u0001!\t!a\u0002\t\u000f\u0005-\u0001\u0001\"\u0001\u0002\u000e!9\u0011\u0011\u0003\u0001\u0005\u0002\u0005M\u0001bBA\f\u0001\u0011\u0005\u0013\u0011\u0004\u0005\b\u0003S\u0001A\u0011IA\u0016\u0011\u001d\t9\u0004\u0001C!\u0003sAq!!\u0010\u0001\t\u0003\ny\u0004C\u0004\u0002H\u0001!I!!\u0013\t\u000f\u0005E\u0003\u0001\"\u0011\u0002T!9\u0011Q\u000b\u0001\u0005B\u0005]\u0003bBA-\u0001\u0011\u0005\u00131\f\u0005\b\u0003C\u0002A\u0011IA2\u000f\u001d\t9g\tE\u0001\u0003S2aAI\u0012\t\u0002\u0005-\u0004B\u00029\u001f\t\u0003\t9\bC\u0004\u0002zy!\t!a\u001f\t\u0013\u0005%e$!A\u0005\n\u0005-%a\u0002)s_\u001aLG.\u001a\u0006\u0003I\u0015\nAaY8sK*\ta%\u0001\u0005d_V\u00148/[3s\u0007\u0001\u0019B\u0001A\u00150eA\u0011!&L\u0007\u0002W)\tA&A\u0003tG\u0006d\u0017-\u0003\u0002/W\t1\u0011I\\=SK\u001a\u0004\"A\u000b\u0019\n\u0005EZ#a\u0002)s_\u0012,8\r\u001e\t\u0003gmr!\u0001N\u001d\u000f\u0005UBT\"\u0001\u001c\u000b\u0005]:\u0013A\u0002\u001fs_>$h(C\u0001-\u0013\tQ4&A\u0004qC\u000e\\\u0017mZ3\n\u0005qj$\u0001D*fe&\fG.\u001b>bE2,\'B\u0001\u001e,\u0003\tIG-F\u0001A!\t\tUI\u0004\u0002C\u0007B\u0011QgK\u0005\u0003\t.\na\u0001\u0015:fI\u00164\u0017B\u0001$H\u0005\u0019\u0019FO]5oO*\u0011AiK\u0001\u0004S\u0012\u0004\u0013aD1di&4XMQ=EK\u001a\fW\u000f\u001c;\u0016\u0003-\u00032A\u000b\'O\u0013\ti5F\u0001\u0004PaRLwN\u001c\t\u0003U=K!\u0001U\u0016\u0003\u000f\t{w\u000e\\3b]\u0006\u0001\u0012m\u0019;jm\u0016\u0014\u0015\u0010R3gCVdG\u000fI\u0001\u000bC\u000e$\u0018N^1uS>tW#\u0001+\u0011\u0005U3V\"A\u0012\n\u0005]\u001b#AC!di&4\u0018\r^5p]\u0006Y\u0011m\u0019;jm\u0006$\u0018n\u001c8!\u00031!W\r]3oI\u0016t7-[3t+\u0005Y\u0006cA\u001a]=&\u0011Q,\u0010\u0002\u0004\'\u0016\f\b\u0003\u0002\u0016`C\u0012L!\u0001Y\u0016\u0003\rQ+\b\u000f\\33!\t)&-\u0003\u0002dG\ti1i\u001c8gS\u001e,(/\u0019;j_:\u0004\"!V3\n\u0005\u0019\u001c#A\u0003#fa\u0016tG-\u001a8ds\u0006iA-\u001a9f]\u0012,gnY5fg\u0002\nA\u0003Z3qK:$WM\\2z\u001b\u0006t\u0017mZ3nK:$\u0018!\u00063fa\u0016tG-\u001a8ds6\u000bg.Y4f[\u0016tG\u000fI\u0001\u000baJ|\u0007/\u001a:uS\u0016\u001cX#\u00017\u0011\t\u0005k\u0007\tQ\u0005\u0003]\u001e\u00131!T1q\u0003-\u0001(o\u001c9feRLWm\u001d\u0011\u0002\rqJg.\u001b;?)\u001d\u00118\u000f^;wob\u0004\"!\u0016\u0001\t\u000byj\u0001\u0019\u0001!\t\u000b%k\u0001\u0019A&\t\u000bIk\u0001\u0019\u0001+\t\u000bek\u0001\u0019A.\t\u000b!l\u0001\u0019A.\t\u000b)l\u0001\u0019\u00017\u0002\r]LG\u000f[%e)\t\u00118\u0010C\u0003?\u001d\u0001\u0007\u0001)A\nxSRD\u0017i\u0019;jm\u0016\u0014\u0015\u0010R3gCVdG\u000f\u0006\u0002s}\")\u0011j\u0004a\u0001\u0017\u0006qq/\u001b;i\u0003\u000e$\u0018N^1uS>tGc\u0001:\u0002\u0004!)!\u000b\u0005a\u0001)\u0006\u0001r/\u001b;i\t\u0016\u0004XM\u001c3f]\u000eLWm\u001d\u000b\u0004e\u0006%\u0001\"B-\u0012\u0001\u0004Y\u0016\u0001G<ji\"$U\r]3oI\u0016t7-_\'b]\u0006<W-\\3oiR\u0019!/a\u0004\t\u000b!\u0014\u0002\u0019A.\u0002\u001d]LG\u000f\u001b)s_B,\'\u000f^5fgR\u0019!/!\u0006\t\u000b)\u001c\u0002\u0019\u00017\u0002\u0011Q|7\u000b\u001e:j]\u001e$\"!a\u0007\u0011\t\u0005u\u0011qE\u0007\u0003\u0003?QA!!\t\u0002$\u0005!A.\u00198h\u0015\t\t)#\u0001\u0003kCZ\f\u0017b\u0001$\u0002 \u0005A1-\u00198FcV\fG\u000eF\u0002O\u0003[Aq!a\f\u0016\u0001\u0004\t\t$A\u0002pE*\u00042AKA\u001a\u0013\r\t)d\u000b\u0002\u0004\u0003:L\u0018AB3rk\u0006d7\u000fF\u0002O\u0003wAq!a\f\u0017\u0001\u0004\t\t$\u0001\u0005iCND7i\u001c3f)\t\t\t\u0005E\u0002+\u0003\u0007J1!!\u0012,\u0005\rIe\u000e^\u0001\u0006iV\u0004H.Z\u000b\u0003\u0003\u0017\u0002\u0012BKA\'\u0001.#6l\u00177\n\u0007\u0005=3F\u0001\u0004UkBdWMN\u0001\u000eaJ|G-^2u!J,g-\u001b=\u0016\u0005\u0005m\u0011\u0001\u00049s_\u0012,8\r^!sSRLXCAA!\u00039\u0001(o\u001c3vGR,E.Z7f]R$B!!\r\u0002^!9\u0011qL\u000eA\u0002\u0005\u0005\u0013!\u00018\u0002%A\u0014x\u000eZ;di\u0016cW-\\3oi:\u000bW.\u001a\u000b\u0005\u00037\t)\u0007C\u0004\u0002`q\u0001\r!!\u0011\u0002\u000fA\u0013xNZ5mKB\u0011QKH\n\u0005=%\ni\u0007\u0005\u0003\u0002p\u0005UTBAA9\u0015\u0011\t\u0019(a\t\u0002\u0005%|\u0017b\u0001\u001f\u0002rQ\u0011\u0011\u0011N\u0001\u0006CB\u0004H.\u001f\u000b\u000ee\u0006u\u0014qPAA\u0003\u0007\u000b))a\"\t\u000by\u0002\u0003\u0019\u0001!\t\u000b%\u0003\u0003\u0019A&\t\u000bI\u0003\u0003\u0019\u0001+\t\u000be\u0003\u0003\u0019A.\t\u000b!\u0004\u0003\u0019A.\t\u000b)\u0004\u0003\u0019\u00017\u0002\u0019]\u0014\u0018\u000e^3SKBd\u0017mY3\u0015\u0005\u00055\u0005\u0003BA\u000f\u0003\u001fKA!!%\u0002 \t1qJ\u00196fGR\u0004"
    )
  ScalaInlineInfo: length = 0x7C (unknown attribute)
   01 01 00 18 00 54 00 55 01 00 12 00 3B 01 00 0F
   00 37 01 00 80 00 81 01 00 14 00 3E 01 00 17 00
   3E 01 00 84 00 81 01 00 92 00 93 01 00 0D 00 34
   01 00 A7 00 93 01 00 A8 00 A9 01 00 B5 00 B6 01
   00 2F 00 27 01 00 26 00 27 01 00 A6 00 34 01 00
   18 00 44 01 00 66 00 34 01 00 9E 00 9F 01 00 5D
   00 5E 01 00 58 00 59 01 00 5F 00 60 01 00 62 00
   60 01 00 48 00 49 01 00 63 00 64 01
  ScalaSig: length = 0x3 (unknown attribute)
   05 02 00
