Classfile /Users/mw/Projects/slang-braindump/.jar/jar11/assemble/slang-braindump/assemble/content/coursier/core/Reconciliation$Default$.class
  Last modified May 29, 2022; size 7466 bytes
  SHA-256 checksum 16218103eaab0b250eb7a7a9c0c7d4f3c332dcbacaee084d6131cbe36c6751eb
  Compiled from "Reconciliation.scala"
public class coursier.core.Reconciliation$Default$ extends coursier.core.Reconciliation implements scala.Product,java.io.Serializable
  minor version: 0
  major version: 52
  flags: (0x0021) ACC_PUBLIC, ACC_SUPER
  this_class: #2                          // coursier/core/Reconciliation$Default$
  super_class: #4                         // coursier/core/Reconciliation
  interfaces: 2, fields: 1, methods: 23, attributes: 5
Constant pool:
    #1 = Utf8               coursier/core/Reconciliation$Default$
    #2 = Class              #1            // coursier/core/Reconciliation$Default$
    #3 = Utf8               coursier/core/Reconciliation
    #4 = Class              #3            // coursier/core/Reconciliation
    #5 = Utf8               scala/Product
    #6 = Class              #5            // scala/Product
    #7 = Utf8               java/io/Serializable
    #8 = Class              #7            // java/io/Serializable
    #9 = Utf8               Reconciliation.scala
   #10 = Utf8
   #11 = Utf8               java/lang/invoke/MethodHandles$Lookup
   #12 = Class              #11           // java/lang/invoke/MethodHandles$Lookup
   #13 = Utf8               java/lang/invoke/MethodHandles
   #14 = Class              #13           // java/lang/invoke/MethodHandles
   #15 = Utf8               Lookup
   #16 = Utf8               MODULE$
   #17 = Utf8               Lcoursier/core/Reconciliation$Default$;
   #18 = Utf8               <clinit>
   #19 = Utf8               ()V
   #20 = Utf8               <init>
   #21 = NameAndType        #20:#19       // "<init>":()V
   #22 = Methodref          #2.#21        // coursier/core/Reconciliation$Default$."<init>":()V
   #23 = NameAndType        #16:#17       // MODULE$:Lcoursier/core/Reconciliation$Default$;
   #24 = Fieldref           #2.#23        // coursier/core/Reconciliation$Default$.MODULE$:Lcoursier/core/Reconciliation$Default$;
   #25 = Utf8               $init$
   #26 = Utf8               (Lscala/Product;)V
   #27 = NameAndType        #25:#26       // $init$:(Lscala/Product;)V
   #28 = InterfaceMethodref #6.#27        // scala/Product.$init$:(Lscala/Product;)V
   #29 = Utf8               productElementName
   #30 = Utf8               (I)Ljava/lang/String;
   #31 = Utf8               n
   #32 = Utf8               productElementName$
   #33 = Utf8               (Lscala/Product;I)Ljava/lang/String;
   #34 = NameAndType        #32:#33       // productElementName$:(Lscala/Product;I)Ljava/lang/String;
   #35 = InterfaceMethodref #6.#34        // scala/Product.productElementName$:(Lscala/Product;I)Ljava/lang/String;
   #36 = Utf8               this
   #37 = Utf8               I
   #38 = Utf8               productElementNames
   #39 = Utf8               ()Lscala/collection/Iterator;
   #40 = Utf8               ()Lscala/collection/Iterator<Ljava/lang/String;>;
   #41 = Utf8               productElementNames$
   #42 = Utf8               (Lscala/Product;)Lscala/collection/Iterator;
   #43 = NameAndType        #41:#42       // productElementNames$:(Lscala/Product;)Lscala/collection/Iterator;
   #44 = InterfaceMethodref #6.#43        // scala/Product.productElementNames$:(Lscala/Product;)Lscala/collection/Iterator;
   #45 = Utf8               apply
   #46 = Utf8               (Lscala/collection/immutable/Seq;)Lscala/Option;
   #47 = Utf8               (Lscala/collection/immutable/Seq<Ljava/lang/String;>;)Lscala/Option<Ljava/lang/String;>;
   #48 = Utf8               versions
   #49 = Utf8               scala/collection/immutable/Seq
   #50 = Class              #49           // scala/collection/immutable/Seq
   #51 = Utf8               isEmpty
   #52 = Utf8               ()Z
   #53 = NameAndType        #51:#52       // isEmpty:()Z
   #54 = InterfaceMethodref #50.#53       // scala/collection/immutable/Seq.isEmpty:()Z
   #55 = Utf8               scala/None$
   #56 = Class              #55           // scala/None$
   #57 = Utf8               Lscala/None$;
   #58 = NameAndType        #16:#57       // MODULE$:Lscala/None$;
   #59 = Fieldref           #56.#58       // scala/None$.MODULE$:Lscala/None$;
   #60 = Utf8               lengthCompare
   #61 = Utf8               (I)I
   #62 = NameAndType        #60:#61       // lengthCompare:(I)I
   #63 = InterfaceMethodref #50.#62       // scala/collection/immutable/Seq.lengthCompare:(I)I
   #64 = Utf8               scala/Some
   #65 = Class              #64           // scala/Some
   #66 = Utf8               head
   #67 = Utf8               ()Ljava/lang/Object;
   #68 = NameAndType        #66:#67       // head:()Ljava/lang/Object;
   #69 = InterfaceMethodref #50.#68       // scala/collection/immutable/Seq.head:()Ljava/lang/Object;
   #70 = Utf8               (Ljava/lang/Object;)V
   #71 = NameAndType        #20:#70       // "<init>":(Ljava/lang/Object;)V
   #72 = Methodref          #65.#71       // scala/Some."<init>":(Ljava/lang/Object;)V
   #73 = Utf8               coursier/core/Reconciliation$
   #74 = Class              #73           // coursier/core/Reconciliation$
   #75 = Utf8               Lcoursier/core/Reconciliation$;
   #76 = NameAndType        #16:#75       // MODULE$:Lcoursier/core/Reconciliation$;
   #77 = Fieldref           #74.#76       // coursier/core/Reconciliation$.MODULE$:Lcoursier/core/Reconciliation$;
   #78 = Utf8               coursier$core$Reconciliation$$splitStandard
   #79 = Utf8               (Lscala/collection/immutable/Seq;)Lscala/Tuple2;
   #80 = NameAndType        #78:#79       // coursier$core$Reconciliation$$splitStandard:(Lscala/collection/immutable/Seq;)Lscala/Tuple2;
   #81 = Methodref          #74.#80       // coursier/core/Reconciliation$.coursier$core$Reconciliation$$splitStandard:(Lscala/collection/immutable/Seq;)Lscala/Tuple2;
   #82 = Utf8               scala/Tuple2
   #83 = Class              #82           // scala/Tuple2
   #84 = Utf8               _1
   #85 = NameAndType        #84:#67       // _1:()Ljava/lang/Object;
   #86 = Methodref          #83.#85       // scala/Tuple2._1:()Ljava/lang/Object;
   #87 = Utf8               _2
   #88 = NameAndType        #87:#67       // _2:()Ljava/lang/Object;
   #89 = Methodref          #83.#88       // scala/Tuple2._2:()Ljava/lang/Object;
   #90 = Utf8               (Ljava/lang/Object;Ljava/lang/Object;)V
   #91 = NameAndType        #20:#90       // "<init>":(Ljava/lang/Object;Ljava/lang/Object;)V
   #92 = Methodref          #83.#91       // scala/Tuple2."<init>":(Ljava/lang/Object;Ljava/lang/Object;)V
   #93 = Utf8               scala/MatchError
   #94 = Class              #93           // scala/MatchError
   #95 = Methodref          #94.#71       // scala/MatchError."<init>":(Ljava/lang/Object;)V
   #96 = Utf8               headOption
   #97 = Utf8               ()Lscala/Option;
   #98 = NameAndType        #96:#97       // headOption:()Lscala/Option;
   #99 = InterfaceMethodref #50.#98       // scala/collection/immutable/Seq.headOption:()Lscala/Option;
  #100 = Utf8               (Ljava/lang/Object;)Ljava/lang/Object;
  #101 = MethodType         #100          //  (Ljava/lang/Object;)Ljava/lang/Object;
  #102 = Utf8               $anonfun$apply$1
  #103 = Utf8               (Ljava/lang/String;)Lcoursier/core/VersionConstraint;
  #104 = NameAndType        #102:#103     // $anonfun$apply$1:(Ljava/lang/String;)Lcoursier/core/VersionConstraint;
  #105 = Methodref          #2.#104       // coursier/core/Reconciliation$Default$.$anonfun$apply$1:(Ljava/lang/String;)Lcoursier/core/VersionConstraint;
  #106 = MethodHandle       6:#105        // REF_invokeStatic coursier/core/Reconciliation$Default$.$anonfun$apply$1:(Ljava/lang/String;)Lcoursier/core/VersionConstraint;
  #107 = MethodType         #103          //  (Ljava/lang/String;)Lcoursier/core/VersionConstraint;
  #108 = Integer            5
  #109 = Integer            1
  #110 = Utf8               java/lang/invoke/LambdaMetafactory
  #111 = Class              #110          // java/lang/invoke/LambdaMetafactory
  #112 = Utf8               altMetafactory
  #113 = Utf8               (Ljava/lang/invoke/MethodHandles$Lookup;Ljava/lang/String;Ljava/lang/invoke/MethodType;[Ljava/lang/Object;)Ljava/lang/invoke/CallSite;
  #114 = NameAndType        #112:#113     // altMetafactory:(Ljava/lang/invoke/MethodHandles$Lookup;Ljava/lang/String;Ljava/lang/invoke/MethodType;[Ljava/lang/Object;)Ljava/lang/invoke/CallSite;
  #115 = Methodref          #111.#114     // java/lang/invoke/LambdaMetafactory.altMetafactory:(Ljava/lang/invoke/MethodHandles$Lookup;Ljava/lang/String;Ljava/lang/invoke/MethodType;[Ljava/lang/Object;)Ljava/lang/invoke/CallSite;
  #116 = MethodHandle       6:#115        // REF_invokeStatic java/lang/invoke/LambdaMetafactory.altMetafactory:(Ljava/lang/invoke/MethodHandles$Lookup;Ljava/lang/String;Ljava/lang/invoke/MethodType;[Ljava/lang/Object;)Ljava/lang/invoke/CallSite;
  #117 = Utf8               ()Lscala/Function1;
  #118 = NameAndType        #45:#117      // apply:()Lscala/Function1;
  #119 = InvokeDynamic      #0:#118       // #0:apply:()Lscala/Function1;
  #120 = Utf8               map
  #121 = Utf8               (Lscala/Function1;)Ljava/lang/Object;
  #122 = NameAndType        #120:#121     // map:(Lscala/Function1;)Ljava/lang/Object;
  #123 = InterfaceMethodref #50.#122      // scala/collection/immutable/Seq.map:(Lscala/Function1;)Ljava/lang/Object;
  #124 = Utf8               coursier/core/VersionConstraint$
  #125 = Class              #124          // coursier/core/VersionConstraint$
  #126 = Utf8               Lcoursier/core/VersionConstraint$;
  #127 = NameAndType        #16:#126      // MODULE$:Lcoursier/core/VersionConstraint$;
  #128 = Fieldref           #125.#127     // coursier/core/VersionConstraint$.MODULE$:Lcoursier/core/VersionConstraint$;
  #129 = Utf8               merge
  #130 = NameAndType        #129:#46      // merge:(Lscala/collection/immutable/Seq;)Lscala/Option;
  #131 = Methodref          #125.#130     // coursier/core/VersionConstraint$.merge:(Lscala/collection/immutable/Seq;)Lscala/Option;
  #132 = Utf8               $anonfun$apply$2
  #133 = Utf8               (Lcoursier/core/VersionConstraint;)Lscala/Option;
  #134 = NameAndType        #132:#133     // $anonfun$apply$2:(Lcoursier/core/VersionConstraint;)Lscala/Option;
  #135 = Methodref          #2.#134       // coursier/core/Reconciliation$Default$.$anonfun$apply$2:(Lcoursier/core/VersionConstraint;)Lscala/Option;
  #136 = MethodHandle       6:#135        // REF_invokeStatic coursier/core/Reconciliation$Default$.$anonfun$apply$2:(Lcoursier/core/VersionConstraint;)Lscala/Option;
  #137 = MethodType         #133          //  (Lcoursier/core/VersionConstraint;)Lscala/Option;
  #138 = InvokeDynamic      #1:#118       // #1:apply:()Lscala/Function1;
  #139 = Utf8               scala/Option
  #140 = Class              #139          // scala/Option
  #141 = Utf8               flatMap
  #142 = Utf8               (Lscala/Function1;)Lscala/Option;
  #143 = NameAndType        #141:#142     // flatMap:(Lscala/Function1;)Lscala/Option;
  #144 = Methodref          #140.#143     // scala/Option.flatMap:(Lscala/Function1;)Lscala/Option;
  #145 = Utf8               coursier$core$Reconciliation$$retainLatestOpt
  #146 = NameAndType        #145:#46      // coursier$core$Reconciliation$$retainLatestOpt:(Lscala/collection/immutable/Seq;)Lscala/Option;
  #147 = Methodref          #74.#146      // coursier/core/Reconciliation$.coursier$core$Reconciliation$$retainLatestOpt:(Lscala/collection/immutable/Seq;)Lscala/Option;
  #148 = Utf8               $anonfun$apply$3
  #149 = NameAndType        #148:#103     // $anonfun$apply$3:(Ljava/lang/String;)Lcoursier/core/VersionConstraint;
  #150 = Methodref          #2.#149       // coursier/core/Reconciliation$Default$.$anonfun$apply$3:(Ljava/lang/String;)Lcoursier/core/VersionConstraint;
  #151 = MethodHandle       6:#150        // REF_invokeStatic coursier/core/Reconciliation$Default$.$anonfun$apply$3:(Ljava/lang/String;)Lcoursier/core/VersionConstraint;
  #152 = InvokeDynamic      #2:#118       // #2:apply:()Lscala/Function1;
  #153 = Utf8               scala/collection/IterableOps
  #154 = Class              #153          // scala/collection/IterableOps
  #155 = Utf8               $anonfun$apply$4$adapted
  #156 = Utf8               (Lcoursier/core/VersionConstraint;)Ljava/lang/Object;
  #157 = NameAndType        #155:#156     // $anonfun$apply$4$adapted:(Lcoursier/core/VersionConstraint;)Ljava/lang/Object;
  #158 = Methodref          #2.#157       // coursier/core/Reconciliation$Default$.$anonfun$apply$4$adapted:(Lcoursier/core/VersionConstraint;)Ljava/lang/Object;
  #159 = MethodHandle       6:#158        // REF_invokeStatic coursier/core/Reconciliation$Default$.$anonfun$apply$4$adapted:(Lcoursier/core/VersionConstraint;)Ljava/lang/Object;
  #160 = MethodType         #156          //  (Lcoursier/core/VersionConstraint;)Ljava/lang/Object;
  #161 = InvokeDynamic      #3:#118       // #3:apply:()Lscala/Function1;
  #162 = Utf8               filter
  #163 = NameAndType        #162:#121     // filter:(Lscala/Function1;)Ljava/lang/Object;
  #164 = InterfaceMethodref #154.#163     // scala/collection/IterableOps.filter:(Lscala/Function1;)Ljava/lang/Object;
  #165 = Utf8               $anonfun$apply$5$adapted
  #166 = NameAndType        #165:#156     // $anonfun$apply$5$adapted:(Lcoursier/core/VersionConstraint;)Ljava/lang/Object;
  #167 = Methodref          #2.#166       // coursier/core/Reconciliation$Default$.$anonfun$apply$5$adapted:(Lcoursier/core/VersionConstraint;)Ljava/lang/Object;
  #168 = MethodHandle       6:#167        // REF_invokeStatic coursier/core/Reconciliation$Default$.$anonfun$apply$5$adapted:(Lcoursier/core/VersionConstraint;)Ljava/lang/Object;
  #169 = InvokeDynamic      #4:#118       // #4:apply:()Lscala/Function1;
  #170 = Utf8               $anonfun$apply$6
  #171 = NameAndType        #170:#133     // $anonfun$apply$6:(Lcoursier/core/VersionConstraint;)Lscala/Option;
  #172 = Methodref          #2.#171       // coursier/core/Reconciliation$Default$.$anonfun$apply$6:(Lcoursier/core/VersionConstraint;)Lscala/Option;
  #173 = MethodHandle       6:#172        // REF_invokeStatic coursier/core/Reconciliation$Default$.$anonfun$apply$6:(Lcoursier/core/VersionConstraint;)Lscala/Option;
  #174 = InvokeDynamic      #5:#118       // #5:apply:()Lscala/Function1;
  #175 = Utf8               $anonfun$apply$7
  #176 = Utf8               (Lscala/Option;Ljava/lang/String;)Ljava/lang/String;
  #177 = NameAndType        #175:#176     // $anonfun$apply$7:(Lscala/Option;Ljava/lang/String;)Ljava/lang/String;
  #178 = Methodref          #2.#177       // coursier/core/Reconciliation$Default$.$anonfun$apply$7:(Lscala/Option;Ljava/lang/String;)Ljava/lang/String;
  #179 = MethodHandle       6:#178        // REF_invokeStatic coursier/core/Reconciliation$Default$.$anonfun$apply$7:(Lscala/Option;Ljava/lang/String;)Ljava/lang/String;
  #180 = Utf8               (Ljava/lang/String;)Ljava/lang/String;
  #181 = MethodType         #180          //  (Ljava/lang/String;)Ljava/lang/String;
  #182 = Utf8               (Lscala/Option;)Lscala/Function1;
  #183 = NameAndType        #45:#182      // apply:(Lscala/Option;)Lscala/Function1;
  #184 = InvokeDynamic      #6:#183       // #6:apply:(Lscala/Option;)Lscala/Function1;
  #185 = NameAndType        #120:#142     // map:(Lscala/Function1;)Lscala/Option;
  #186 = Methodref          #140.#185     // scala/Option.map:(Lscala/Function1;)Lscala/Option;
  #187 = Utf8               standard
  #188 = Utf8               Lscala/collection/immutable/Seq;
  #189 = Utf8               latests
  #190 = Utf8               parsedConstraints
  #191 = Utf8               parsedIntervals
  #192 = Utf8               retainedStandard
  #193 = Utf8               Lscala/Option;
  #194 = Utf8               retainedLatestOpt
  #195 = Utf8               productPrefix
  #196 = Utf8               ()Ljava/lang/String;
  #197 = Utf8               Default
  #198 = String             #197          // Default
  #199 = Utf8               productArity
  #200 = Utf8               ()I
  #201 = Utf8               productElement
  #202 = Utf8               (I)Ljava/lang/Object;
  #203 = Utf8               x$1
  #204 = Utf8               scala/runtime/Statics
  #205 = Class              #204          // scala/runtime/Statics
  #206 = Utf8               ioobe
  #207 = NameAndType        #206:#202     // ioobe:(I)Ljava/lang/Object;
  #208 = Methodref          #205.#207     // scala/runtime/Statics.ioobe:(I)Ljava/lang/Object;
  #209 = Utf8               java/lang/Object
  #210 = Class              #209          // java/lang/Object
  #211 = Utf8               productIterator
  #212 = Utf8               ()Lscala/collection/Iterator<Ljava/lang/Object;>;
  #213 = Utf8               scala/runtime/ScalaRunTime$
  #214 = Class              #213          // scala/runtime/ScalaRunTime$
  #215 = Utf8               Lscala/runtime/ScalaRunTime$;
  #216 = NameAndType        #16:#215      // MODULE$:Lscala/runtime/ScalaRunTime$;
  #217 = Fieldref           #214.#216     // scala/runtime/ScalaRunTime$.MODULE$:Lscala/runtime/ScalaRunTime$;
  #218 = Utf8               typedProductIterator
  #219 = NameAndType        #218:#42      // typedProductIterator:(Lscala/Product;)Lscala/collection/Iterator;
  #220 = Methodref          #214.#219     // scala/runtime/ScalaRunTime$.typedProductIterator:(Lscala/Product;)Lscala/collection/Iterator;
  #221 = Utf8               canEqual
  #222 = Utf8               (Ljava/lang/Object;)Z
  #223 = Utf8               Ljava/lang/Object;
  #224 = Utf8               hashCode
  #225 = Integer            -1085510111
  #226 = Utf8               toString
  #227 = Utf8               writeReplace
  #228 = Utf8               scala/runtime/ModuleSerializationProxy
  #229 = Class              #228          // scala/runtime/ModuleSerializationProxy
  #230 = Utf8               (Ljava/lang/Class;)V
  #231 = NameAndType        #20:#230      // "<init>":(Ljava/lang/Class;)V
  #232 = Methodref          #229.#231     // scala/runtime/ModuleSerializationProxy."<init>":(Ljava/lang/Class;)V
  #233 = Utf8               s
  #234 = Utf8               coursier/core/Parse$
  #235 = Class              #234          // coursier/core/Parse$
  #236 = Utf8               Lcoursier/core/Parse$;
  #237 = NameAndType        #16:#236      // MODULE$:Lcoursier/core/Parse$;
  #238 = Fieldref           #235.#237     // coursier/core/Parse$.MODULE$:Lcoursier/core/Parse$;
  #239 = Utf8               versionConstraint
  #240 = NameAndType        #239:#103     // versionConstraint:(Ljava/lang/String;)Lcoursier/core/VersionConstraint;
  #241 = Methodref          #235.#240     // coursier/core/Parse$.versionConstraint:(Ljava/lang/String;)Lcoursier/core/VersionConstraint;
  #242 = Utf8               Ljava/lang/String;
  #243 = Utf8               x$2
  #244 = Utf8               coursier/core/VersionConstraint
  #245 = Class              #244          // coursier/core/VersionConstraint
  #246 = Utf8               repr
  #247 = NameAndType        #246:#97      // repr:()Lscala/Option;
  #248 = Methodref          #245.#247     // coursier/core/VersionConstraint.repr:()Lscala/Option;
  #249 = Utf8               Lcoursier/core/VersionConstraint;
  #250 = Utf8               $anonfun$apply$4
  #251 = Utf8               (Lcoursier/core/VersionConstraint;)Z
  #252 = Utf8               x$3
  #253 = Utf8               preferred
  #254 = Utf8               ()Lscala/collection/immutable/Seq;
  #255 = NameAndType        #253:#254     // preferred:()Lscala/collection/immutable/Seq;
  #256 = Methodref          #245.#255     // coursier/core/VersionConstraint.preferred:()Lscala/collection/immutable/Seq;
  #257 = Utf8               $anonfun$apply$5
  #258 = Utf8               x$4
  #259 = Utf8               interval
  #260 = Utf8               ()Lcoursier/core/VersionInterval;
  #261 = NameAndType        #259:#260     // interval:()Lcoursier/core/VersionInterval;
  #262 = Methodref          #245.#261     // coursier/core/VersionConstraint.interval:()Lcoursier/core/VersionInterval;
  #263 = Utf8               coursier/core/VersionInterval$
  #264 = Class              #263          // coursier/core/VersionInterval$
  #265 = Utf8               Lcoursier/core/VersionInterval$;
  #266 = NameAndType        #16:#265      // MODULE$:Lcoursier/core/VersionInterval$;
  #267 = Fieldref           #264.#266     // coursier/core/VersionInterval$.MODULE$:Lcoursier/core/VersionInterval$;
  #268 = Utf8               zero
  #269 = NameAndType        #268:#260     // zero:()Lcoursier/core/VersionInterval;
  #270 = Methodref          #264.#269     // coursier/core/VersionInterval$.zero:()Lcoursier/core/VersionInterval;
  #271 = Utf8               coursier/core/VersionInterval
  #272 = Class              #271          // coursier/core/VersionInterval
  #273 = Utf8               equals
  #274 = NameAndType        #273:#222     // equals:(Ljava/lang/Object;)Z
  #275 = Methodref          #210.#274     // java/lang/Object.equals:(Ljava/lang/Object;)Z
  #276 = Utf8               x$5
  #277 = Utf8               retainedLatestOpt$1
  #278 = Utf8               itv
  #279 = Utf8               scala/Option$
  #280 = Class              #279          // scala/Option$
  #281 = Utf8               Lscala/Option$;
  #282 = NameAndType        #16:#281      // MODULE$:Lscala/Option$;
  #283 = Fieldref           #280.#282     // scala/Option$.MODULE$:Lscala/Option$;
  #284 = Utf8               option2Iterable
  #285 = Utf8               (Lscala/Option;)Lscala/collection/Iterable;
  #286 = NameAndType        #284:#285     // option2Iterable:(Lscala/Option;)Lscala/collection/Iterable;
  #287 = Methodref          #280.#286     // scala/Option$.option2Iterable:(Lscala/Option;)Lscala/collection/Iterable;
  #288 = Utf8               scala/collection/Iterable
  #289 = Class              #288          // scala/collection/Iterable
  #290 = Utf8               toSeq
  #291 = NameAndType        #290:#254     // toSeq:()Lscala/collection/immutable/Seq;
  #292 = InterfaceMethodref #289.#291     // scala/collection/Iterable.toSeq:()Lscala/collection/immutable/Seq;
  #293 = Utf8               $plus$colon
  #294 = NameAndType        #293:#100     // $plus$colon:(Ljava/lang/Object;)Ljava/lang/Object;
  #295 = InterfaceMethodref #50.#294      // scala/collection/immutable/Seq.$plus$colon:(Ljava/lang/Object;)Ljava/lang/Object;
  #296 = Utf8               scala/collection/IterableOnceOps
  #297 = Class              #296          // scala/collection/IterableOnceOps
  #298 = Utf8               &
  #299 = String             #298          // &
  #300 = Utf8               mkString
  #301 = NameAndType        #300:#180     // mkString:(Ljava/lang/String;)Ljava/lang/String;
  #302 = InterfaceMethodref #297.#301     // scala/collection/IterableOnceOps.mkString:(Ljava/lang/String;)Ljava/lang/String;
  #303 = Methodref          #4.#21        // coursier/core/Reconciliation."<init>":()V
  #304 = NameAndType        #250:#251     // $anonfun$apply$4:(Lcoursier/core/VersionConstraint;)Z
  #305 = Methodref          #2.#304       // coursier/core/Reconciliation$Default$.$anonfun$apply$4:(Lcoursier/core/VersionConstraint;)Z
  #306 = Utf8               scala/runtime/BoxesRunTime
  #307 = Class              #306          // scala/runtime/BoxesRunTime
  #308 = Utf8               boxToBoolean
  #309 = Utf8               (Z)Ljava/lang/Boolean;
  #310 = NameAndType        #308:#309     // boxToBoolean:(Z)Ljava/lang/Boolean;
  #311 = Methodref          #307.#310     // scala/runtime/BoxesRunTime.boxToBoolean:(Z)Ljava/lang/Boolean;
  #312 = NameAndType        #257:#251     // $anonfun$apply$5:(Lcoursier/core/VersionConstraint;)Z
  #313 = Methodref          #2.#312       // coursier/core/Reconciliation$Default$.$anonfun$apply$5:(Lcoursier/core/VersionConstraint;)Z
  #314 = Utf8               $deserializeLambda$
  #315 = Utf8               (Ljava/lang/invoke/SerializedLambda;)Ljava/lang/Object;
  #316 = Utf8               scala/runtime/LambdaDeserialize
  #317 = Class              #316          // scala/runtime/LambdaDeserialize
  #318 = Utf8               bootstrap
  #319 = Utf8               (Ljava/lang/invoke/MethodHandles$Lookup;Ljava/lang/String;Ljava/lang/invoke/MethodType;[Ljava/lang/invoke/MethodHandle;)Ljava/lang/invoke/CallSite;
  #320 = NameAndType        #318:#319     // bootstrap:(Ljava/lang/invoke/MethodHandles$Lookup;Ljava/lang/String;Ljava/lang/invoke/MethodType;[Ljava/lang/invoke/MethodHandle;)Ljava/lang/invoke/CallSite;
  #321 = Methodref          #317.#320     // scala/runtime/LambdaDeserialize.bootstrap:(Ljava/lang/invoke/MethodHandles$Lookup;Ljava/lang/String;Ljava/lang/invoke/MethodType;[Ljava/lang/invoke/MethodHandle;)Ljava/lang/invoke/CallSite;
  #322 = MethodHandle       6:#321        // REF_invokeStatic scala/runtime/LambdaDeserialize.bootstrap:(Ljava/lang/invoke/MethodHandles$Lookup;Ljava/lang/String;Ljava/lang/invoke/MethodType;[Ljava/lang/invoke/MethodHandle;)Ljava/lang/invoke/CallSite;
  #323 = Utf8               lambdaDeserialize
  #324 = NameAndType        #323:#315     // lambdaDeserialize:(Ljava/lang/invoke/SerializedLambda;)Ljava/lang/Object;
  #325 = InvokeDynamic      #7:#324       // #7:lambdaDeserialize:(Ljava/lang/invoke/SerializedLambda;)Ljava/lang/Object;
  #326 = Utf8               Code
  #327 = Utf8               LineNumberTable
  #328 = Utf8               LocalVariableTable
  #329 = Utf8               MethodParameters
  #330 = Utf8               Signature
  #331 = Utf8               StackMapTable
  #332 = Utf8               InnerClasses
  #333 = Utf8               SourceFile
  #334 = Utf8               BootstrapMethods
  #335 = Utf8               ScalaInlineInfo
  #336 = Utf8               Scala
{
  public static final coursier.core.Reconciliation$Default$ MODULE$;
    descriptor: Lcoursier/core/Reconciliation$Default$;
    flags: (0x0019) ACC_PUBLIC, ACC_STATIC, ACC_FINAL

  public static {};
    descriptor: ()V
    flags: (0x0009) ACC_PUBLIC, ACC_STATIC
    Code:
      stack=2, locals=0, args_size=0
         0: new           #2                  // class coursier/core/Reconciliation$Default$
         3: dup
         4: invokespecial #22                 // Method "<init>":()V
         7: putstatic     #24                 // Field MODULE$:Lcoursier/core/Reconciliation$Default$;
        10: getstatic     #24                 // Field MODULE$:Lcoursier/core/Reconciliation$Default$;
        13: invokestatic  #28                 // InterfaceMethod scala/Product.$init$:(Lscala/Product;)V
        16: return
      LineNumberTable:
        line 46: 0

  public java.lang.String productElementName(int);
    descriptor: (I)Ljava/lang/String;
    flags: (0x0001) ACC_PUBLIC
    Code:
      stack=2, locals=2, args_size=2
         0: aload_0
         1: iload_1
         2: invokestatic  #35                 // InterfaceMethod scala/Product.productElementName$:(Lscala/Product;I)Ljava/lang/String;
         5: areturn
      LineNumberTable:
        line 46: 0
      LocalVariableTable:
        Start  Length  Slot  Name   Signature
            0       6     0  this   Lcoursier/core/Reconciliation$Default$;
            0       6     1     n   I
    MethodParameters:
      Name                           Flags
      n                              final

  public scala.collection.Iterator<java.lang.String> productElementNames();
    descriptor: ()Lscala/collection/Iterator;
    flags: (0x0001) ACC_PUBLIC
    Code:
      stack=1, locals=1, args_size=1
         0: aload_0
         1: invokestatic  #44                 // InterfaceMethod scala/Product.productElementNames$:(Lscala/Product;)Lscala/collection/Iterator;
         4: areturn
      LineNumberTable:
        line 46: 0
      LocalVariableTable:
        Start  Length  Slot  Name   Signature
            0       5     0  this   Lcoursier/core/Reconciliation$Default$;
    Signature: #40                          // ()Lscala/collection/Iterator<Ljava/lang/String;>;

  public scala.Option<java.lang.String> apply(scala.collection.immutable.Seq<java.lang.String>);
    descriptor: (Lscala/collection/immutable/Seq;)Lscala/Option;
    flags: (0x0001) ACC_PUBLIC
    Code:
      stack=4, locals=13, args_size=2
         0: aload_1
         1: invokeinterface #54,  1           // InterfaceMethod scala/collection/immutable/Seq.isEmpty:()Z
         6: ifeq          15
         9: getstatic     #59                 // Field scala/None$.MODULE$:Lscala/None$;
        12: goto          321
        15: aload_1
        16: iconst_1
        17: invokeinterface #63,  2           // InterfaceMethod scala/collection/immutable/Seq.lengthCompare:(I)I
        22: iconst_0
        23: if_icmpne     42
        26: new           #65                 // class scala/Some
        29: dup
        30: aload_1
        31: invokeinterface #69,  1           // InterfaceMethod scala/collection/immutable/Seq.head:()Ljava/lang/Object;
        36: invokespecial #72                 // Method scala/Some."<init>":(Ljava/lang/Object;)V
        39: goto          321
        42: getstatic     #77                 // Field coursier/core/Reconciliation$.MODULE$:Lcoursier/core/Reconciliation$;
        45: aload_1
        46: invokevirtual #81                 // Method coursier/core/Reconciliation$.coursier$core$Reconciliation$$splitStandard:(Lscala/collection/immutable/Seq;)Lscala/Tuple2;
        49: astore        4
        51: aload         4
        53: ifnull        91
        56: aload         4
        58: invokevirtual #86                 // Method scala/Tuple2._1:()Ljava/lang/Object;
        61: checkcast     #50                 // class scala/collection/immutable/Seq
        64: astore        5
        66: aload         4
        68: invokevirtual #89                 // Method scala/Tuple2._2:()Ljava/lang/Object;
        71: checkcast     #50                 // class scala/collection/immutable/Seq
        74: astore        6
        76: new           #83                 // class scala/Tuple2
        79: dup
        80: aload         5
        82: aload         6
        84: invokespecial #92                 // Method scala/Tuple2."<init>":(Ljava/lang/Object;Ljava/lang/Object;)V
        87: astore_2
        88: goto          104
        91: goto          94
        94: new           #94                 // class scala/MatchError
        97: dup
        98: aload         4
       100: invokespecial #95                 // Method scala/MatchError."<init>":(Ljava/lang/Object;)V
       103: athrow
       104: aload_2
       105: astore_3
       106: aload_3
       107: invokevirtual #86                 // Method scala/Tuple2._1:()Ljava/lang/Object;
       110: checkcast     #50                 // class scala/collection/immutable/Seq
       113: astore        7
       115: aload_3
       116: invokevirtual #89                 // Method scala/Tuple2._2:()Ljava/lang/Object;
       119: checkcast     #50                 // class scala/collection/immutable/Seq
       122: astore        8
       124: aload         7
       126: invokeinterface #54,  1           // InterfaceMethod scala/collection/immutable/Seq.isEmpty:()Z
       131: ifeq          140
       134: getstatic     #59                 // Field scala/None$.MODULE$:Lscala/None$;
       137: goto          195
       140: aload         7
       142: iconst_1
       143: invokeinterface #63,  2           // InterfaceMethod scala/collection/immutable/Seq.lengthCompare:(I)I
       148: iconst_0
       149: if_icmpne     162
       152: aload         7
       154: invokeinterface #99,  1           // InterfaceMethod scala/collection/immutable/Seq.headOption:()Lscala/Option;
       159: goto          195
       162: aload         7
       164: invokedynamic #119,  0            // InvokeDynamic #0:apply:()Lscala/Function1;
       169: invokeinterface #123,  2          // InterfaceMethod scala/collection/immutable/Seq.map:(Lscala/Function1;)Ljava/lang/Object;
       174: checkcast     #50                 // class scala/collection/immutable/Seq
       177: astore        10
       179: getstatic     #128                // Field coursier/core/VersionConstraint$.MODULE$:Lcoursier/core/VersionConstraint$;
       182: aload         10
       184: invokevirtual #131                // Method coursier/core/VersionConstraint$.merge:(Lscala/collection/immutable/Seq;)Lscala/Option;
       187: invokedynamic #138,  0            // InvokeDynamic #1:apply:()Lscala/Function1;
       192: invokevirtual #144                // Method scala/Option.flatMap:(Lscala/Function1;)Lscala/Option;
       195: astore        9
       197: getstatic     #77                 // Field coursier/core/Reconciliation$.MODULE$:Lcoursier/core/Reconciliation$;
       200: aload         8
       202: invokevirtual #147                // Method coursier/core/Reconciliation$.coursier$core$Reconciliation$$retainLatestOpt:(Lscala/collection/immutable/Seq;)Lscala/Option;
       205: astore        11
       207: aload         7
       209: invokeinterface #54,  1           // InterfaceMethod scala/collection/immutable/Seq.isEmpty:()Z
       214: ifeq          222
       217: aload         11
       219: goto          321
       222: aload         8
       224: invokeinterface #54,  1           // InterfaceMethod scala/collection/immutable/Seq.isEmpty:()Z
       229: ifeq          237
       232: aload         9
       234: goto          321
       237: aload         7
       239: invokedynamic #152,  0            // InvokeDynamic #2:apply:()Lscala/Function1;
       244: invokeinterface #123,  2          // InterfaceMethod scala/collection/immutable/Seq.map:(Lscala/Function1;)Ljava/lang/Object;
       249: checkcast     #154                // class scala/collection/IterableOps
       252: invokedynamic #161,  0            // InvokeDynamic #3:apply:()Lscala/Function1;
       257: invokeinterface #164,  2          // InterfaceMethod scala/collection/IterableOps.filter:(Lscala/Function1;)Ljava/lang/Object;
       262: checkcast     #154                // class scala/collection/IterableOps
       265: invokedynamic #169,  0            // InvokeDynamic #4:apply:()Lscala/Function1;
       270: invokeinterface #164,  2          // InterfaceMethod scala/collection/IterableOps.filter:(Lscala/Function1;)Ljava/lang/Object;
       275: checkcast     #50                 // class scala/collection/immutable/Seq
       278: astore        12
       280: aload         12
       282: invokeinterface #54,  1           // InterfaceMethod scala/collection/immutable/Seq.isEmpty:()Z
       287: ifeq          295
       290: aload         11
       292: goto          321
       295: getstatic     #128                // Field coursier/core/VersionConstraint$.MODULE$:Lcoursier/core/VersionConstraint$;
       298: aload         12
       300: invokevirtual #131                // Method coursier/core/VersionConstraint$.merge:(Lscala/collection/immutable/Seq;)Lscala/Option;
       303: invokedynamic #174,  0            // InvokeDynamic #5:apply:()Lscala/Function1;
       308: invokevirtual #144                // Method scala/Option.flatMap:(Lscala/Function1;)Lscala/Option;
       311: aload         11
       313: invokedynamic #184,  0            // InvokeDynamic #6:apply:(Lscala/Option;)Lscala/Function1;
       318: invokevirtual #186                // Method scala/Option.map:(Lscala/Function1;)Lscala/Option;
       321: areturn
      StackMapTable: number_of_entries = 12
        frame_type = 15 /* same */
        frame_type = 26 /* same */
        frame_type = 254 /* append */
          offset_delta = 48
          locals = [ top, top, class scala/Tuple2 ]
        frame_type = 2 /* same */
        frame_type = 255 /* full_frame */
          offset_delta = 9
          locals = [ class coursier/core/Reconciliation$Default$, class scala/collection/immutable/Seq, class scala/Tuple2, top, class scala/Tuple2, class scala/collection/immutable/Seq, class scala/collection/immutable/Seq ]
          stack = []
        frame_type = 255 /* full_frame */
          offset_delta = 35
          locals = [ class coursier/core/Reconciliation$Default$, class scala/collection/immutable/Seq, class scala/Tuple2, class scala/Tuple2, class scala/Tuple2, class scala/collection/immutable/Seq, class scala/collection/immutable/Seq, class scala/collection/immutable/Seq, class scala/collection/immutable/Seq ]
          stack = []
        frame_type = 21 /* same */
        frame_type = 96 /* same_locals_1_stack_item */
          stack = [ class scala/Option ]
        frame_type = 254 /* append */
          offset_delta = 26
          locals = [ class scala/Option, top, class scala/Option ]
        frame_type = 14 /* same */
        frame_type = 252 /* append */
          offset_delta = 57
          locals = [ class scala/collection/immutable/Seq ]
        frame_type = 255 /* full_frame */
          offset_delta = 25
          locals = [ class coursier/core/Reconciliation$Default$, class scala/collection/immutable/Seq ]
          stack = [ class scala/Option ]
      LineNumberTable:
        line 48: 0
        line 49: 9
        line 50: 15
        line 51: 26
        line 53: 42
        line 55: 124
        line 56: 140
        line 58: 162
        line 59: 179
        line 60: 187
        line 62: 197
        line 64: 207
        line 65: 217
        line 66: 222
        line 67: 232
        line 69: 237
        line 70: 252
        line 71: 265
        line 73: 280
        line 74: 290
        line 76: 295
        line 77: 303
        line 78: 311
      LocalVariableTable:
        Start  Length  Slot  Name   Signature
           66      25     5 standard   Lscala/collection/immutable/Seq;
           76      15     6 latests   Lscala/collection/immutable/Seq;
          179      16    10 parsedConstraints   Lscala/collection/immutable/Seq;
          280      41    12 parsedIntervals   Lscala/collection/immutable/Seq;
          115     206     7 standard   Lscala/collection/immutable/Seq;
          124     197     8 latests   Lscala/collection/immutable/Seq;
          197     124     9 retainedStandard   Lscala/Option;
          207     114    11 retainedLatestOpt   Lscala/Option;
            0     322     0  this   Lcoursier/core/Reconciliation$Default$;
            0     322     1 versions   Lscala/collection/immutable/Seq;
    Signature: #47                          // (Lscala/collection/immutable/Seq<Ljava/lang/String;>;)Lscala/Option<Ljava/lang/String;>;
    MethodParameters:
      Name                           Flags
      versions                       final

  public java.lang.String productPrefix();
    descriptor: ()Ljava/lang/String;
    flags: (0x0001) ACC_PUBLIC
    Code:
      stack=1, locals=1, args_size=1
         0: ldc           #198                // String Default
         2: areturn
      LineNumberTable:
        line 46: 0
      LocalVariableTable:
        Start  Length  Slot  Name   Signature
            0       3     0  this   Lcoursier/core/Reconciliation$Default$;

  public int productArity();
    descriptor: ()I
    flags: (0x0001) ACC_PUBLIC
    Code:
      stack=1, locals=1, args_size=1
         0: iconst_0
         1: ireturn
      LineNumberTable:
        line 46: 0
      LocalVariableTable:
        Start  Length  Slot  Name   Signature
            0       2     0  this   Lcoursier/core/Reconciliation$Default$;

  public java.lang.Object productElement(int);
    descriptor: (I)Ljava/lang/Object;
    flags: (0x0001) ACC_PUBLIC
    Code:
      stack=1, locals=4, args_size=2
         0: iload_1
         1: istore_3
         2: iload_1
         3: invokestatic  #208                // Method scala/runtime/Statics.ioobe:(I)Ljava/lang/Object;
         6: astore_2
         7: goto          10
        10: aload_2
        11: areturn
      StackMapTable: number_of_entries = 1
        frame_type = 253 /* append */
          offset_delta = 10
          locals = [ class java/lang/Object, int ]
      LineNumberTable:
        line 46: 0
      LocalVariableTable:
        Start  Length  Slot  Name   Signature
            0      12     0  this   Lcoursier/core/Reconciliation$Default$;
            0      12     1   x$1   I
    MethodParameters:
      Name                           Flags
      x$1                            final

  public scala.collection.Iterator<java.lang.Object> productIterator();
    descriptor: ()Lscala/collection/Iterator;
    flags: (0x0001) ACC_PUBLIC
    Code:
      stack=2, locals=1, args_size=1
         0: getstatic     #217                // Field scala/runtime/ScalaRunTime$.MODULE$:Lscala/runtime/ScalaRunTime$;
         3: aload_0
         4: invokevirtual #220                // Method scala/runtime/ScalaRunTime$.typedProductIterator:(Lscala/Product;)Lscala/collection/Iterator;
         7: areturn
      LineNumberTable:
        line 46: 0
      LocalVariableTable:
        Start  Length  Slot  Name   Signature
            0       8     0  this   Lcoursier/core/Reconciliation$Default$;
    Signature: #212                         // ()Lscala/collection/Iterator<Ljava/lang/Object;>;

  public boolean canEqual(java.lang.Object);
    descriptor: (Ljava/lang/Object;)Z
    flags: (0x0001) ACC_PUBLIC
    Code:
      stack=1, locals=2, args_size=2
         0: aload_1
         1: instanceof    #2                  // class coursier/core/Reconciliation$Default$
         4: ireturn
      LineNumberTable:
        line 46: 0
      LocalVariableTable:
        Start  Length  Slot  Name   Signature
            0       5     0  this   Lcoursier/core/Reconciliation$Default$;
            0       5     1   x$1   Ljava/lang/Object;
    MethodParameters:
      Name                           Flags
      x$1                            final

  public int hashCode();
    descriptor: ()I
    flags: (0x0001) ACC_PUBLIC
    Code:
      stack=1, locals=1, args_size=1
         0: ldc           #225                // int -1085510111
         2: ireturn
      LineNumberTable:
        line 46: 0
      LocalVariableTable:
        Start  Length  Slot  Name   Signature
            0       3     0  this   Lcoursier/core/Reconciliation$Default$;

  public java.lang.String toString();
    descriptor: ()Ljava/lang/String;
    flags: (0x0001) ACC_PUBLIC
    Code:
      stack=1, locals=1, args_size=1
         0: ldc           #198                // String Default
         2: areturn
      LineNumberTable:
        line 46: 0
      LocalVariableTable:
        Start  Length  Slot  Name   Signature
            0       3     0  this   Lcoursier/core/Reconciliation$Default$;

  private java.lang.Object writeReplace();
    descriptor: ()Ljava/lang/Object;
    flags: (0x0002) ACC_PRIVATE
    Code:
      stack=3, locals=1, args_size=1
         0: new           #229                // class scala/runtime/ModuleSerializationProxy
         3: dup
         4: ldc           #2                  // class coursier/core/Reconciliation$Default$
         6: invokespecial #232                // Method scala/runtime/ModuleSerializationProxy."<init>":(Ljava/lang/Class;)V
         9: areturn
      LineNumberTable:
        line 46: 0
      LocalVariableTable:
        Start  Length  Slot  Name   Signature
            0      10     0  this   Lcoursier/core/Reconciliation$Default$;

  public static final coursier.core.VersionConstraint $anonfun$apply$1(java.lang.String);
    descriptor: (Ljava/lang/String;)Lcoursier/core/VersionConstraint;
    flags: (0x1019) ACC_PUBLIC, ACC_STATIC, ACC_FINAL, ACC_SYNTHETIC
    Code:
      stack=2, locals=1, args_size=1
         0: getstatic     #238                // Field coursier/core/Parse$.MODULE$:Lcoursier/core/Parse$;
         3: aload_0
         4: invokevirtual #241                // Method coursier/core/Parse$.versionConstraint:(Ljava/lang/String;)Lcoursier/core/VersionConstraint;
         7: areturn
      LineNumberTable:
        line 58: 0
      LocalVariableTable:
        Start  Length  Slot  Name   Signature
            0       8     0     s   Ljava/lang/String;
    MethodParameters:
      Name                           Flags
      s                              final

  public static final scala.Option $anonfun$apply$2(coursier.core.VersionConstraint);
    descriptor: (Lcoursier/core/VersionConstraint;)Lscala/Option;
    flags: (0x1019) ACC_PUBLIC, ACC_STATIC, ACC_FINAL, ACC_SYNTHETIC
    Code:
      stack=1, locals=1, args_size=1
         0: aload_0
         1: invokevirtual #248                // Method coursier/core/VersionConstraint.repr:()Lscala/Option;
         4: areturn
      LineNumberTable:
        line 60: 0
      LocalVariableTable:
        Start  Length  Slot  Name   Signature
            0       5     0   x$2   Lcoursier/core/VersionConstraint;
    MethodParameters:
      Name                           Flags
      x$2                            final

  public static final coursier.core.VersionConstraint $anonfun$apply$3(java.lang.String);
    descriptor: (Ljava/lang/String;)Lcoursier/core/VersionConstraint;
    flags: (0x1019) ACC_PUBLIC, ACC_STATIC, ACC_FINAL, ACC_SYNTHETIC
    Code:
      stack=2, locals=1, args_size=1
         0: getstatic     #238                // Field coursier/core/Parse$.MODULE$:Lcoursier/core/Parse$;
         3: aload_0
         4: invokevirtual #241                // Method coursier/core/Parse$.versionConstraint:(Ljava/lang/String;)Lcoursier/core/VersionConstraint;
         7: areturn
      LineNumberTable:
        line 69: 0
      LocalVariableTable:
        Start  Length  Slot  Name   Signature
            0       8     0     s   Ljava/lang/String;
    MethodParameters:
      Name                           Flags
      s                              final

  public static final boolean $anonfun$apply$4(coursier.core.VersionConstraint);
    descriptor: (Lcoursier/core/VersionConstraint;)Z
    flags: (0x1019) ACC_PUBLIC, ACC_STATIC, ACC_FINAL, ACC_SYNTHETIC
    Code:
      stack=1, locals=1, args_size=1
         0: aload_0
         1: invokevirtual #256                // Method coursier/core/VersionConstraint.preferred:()Lscala/collection/immutable/Seq;
         4: invokeinterface #54,  1           // InterfaceMethod scala/collection/immutable/Seq.isEmpty:()Z
         9: ireturn
      LineNumberTable:
        line 70: 0
      LocalVariableTable:
        Start  Length  Slot  Name   Signature
            0      10     0   x$3   Lcoursier/core/VersionConstraint;
    MethodParameters:
      Name                           Flags
      x$3                            final

  public static final boolean $anonfun$apply$5(coursier.core.VersionConstraint);
    descriptor: (Lcoursier/core/VersionConstraint;)Z
    flags: (0x1019) ACC_PUBLIC, ACC_STATIC, ACC_FINAL, ACC_SYNTHETIC
    Code:
      stack=2, locals=2, args_size=1
         0: aload_0
         1: invokevirtual #262                // Method coursier/core/VersionConstraint.interval:()Lcoursier/core/VersionInterval;
         4: getstatic     #267                // Field coursier/core/VersionInterval$.MODULE$:Lcoursier/core/VersionInterval$;
         7: invokevirtual #270                // Method coursier/core/VersionInterval$.zero:()Lcoursier/core/VersionInterval;
        10: astore_1
        11: dup
        12: ifnonnull     23
        15: pop
        16: aload_1
        17: ifnull        34
        20: goto          30
        23: aload_1
        24: invokevirtual #275                // Method java/lang/Object.equals:(Ljava/lang/Object;)Z
        27: ifne          34
        30: iconst_1
        31: goto          35
        34: iconst_0
        35: ireturn
      StackMapTable: number_of_entries = 4
        frame_type = 255 /* full_frame */
          offset_delta = 23
          locals = [ class coursier/core/VersionConstraint, class coursier/core/VersionInterval ]
          stack = [ class coursier/core/VersionInterval ]
        frame_type = 6 /* same */
        frame_type = 3 /* same */
        frame_type = 64 /* same_locals_1_stack_item */
          stack = [ int ]
      LineNumberTable:
        line 71: 0
      LocalVariableTable:
        Start  Length  Slot  Name   Signature
            0      36     0   x$4   Lcoursier/core/VersionConstraint;
    MethodParameters:
      Name                           Flags
      x$4                            final

  public static final scala.Option $anonfun$apply$6(coursier.core.VersionConstraint);
    descriptor: (Lcoursier/core/VersionConstraint;)Lscala/Option;
    flags: (0x1019) ACC_PUBLIC, ACC_STATIC, ACC_FINAL, ACC_SYNTHETIC
    Code:
      stack=1, locals=1, args_size=1
         0: aload_0
         1: invokevirtual #248                // Method coursier/core/VersionConstraint.repr:()Lscala/Option;
         4: areturn
      LineNumberTable:
        line 77: 0
      LocalVariableTable:
        Start  Length  Slot  Name   Signature
            0       5     0   x$5   Lcoursier/core/VersionConstraint;
    MethodParameters:
      Name                           Flags
      x$5                            final

  public static final java.lang.String $anonfun$apply$7(scala.Option, java.lang.String);
    descriptor: (Lscala/Option;Ljava/lang/String;)Ljava/lang/String;
    flags: (0x1019) ACC_PUBLIC, ACC_STATIC, ACC_FINAL, ACC_SYNTHETIC
    Code:
      stack=2, locals=3, args_size=2
         0: aload_1
         1: astore_2
         2: getstatic     #283                // Field scala/Option$.MODULE$:Lscala/Option$;
         5: aload_0
         6: invokevirtual #287                // Method scala/Option$.option2Iterable:(Lscala/Option;)Lscala/collection/Iterable;
         9: invokeinterface #292,  1          // InterfaceMethod scala/collection/Iterable.toSeq:()Lscala/collection/immutable/Seq;
        14: aload_2
        15: invokeinterface #295,  2          // InterfaceMethod scala/collection/immutable/Seq.$plus$colon:(Ljava/lang/Object;)Ljava/lang/Object;
        20: checkcast     #297                // class scala/collection/IterableOnceOps
        23: ldc_w         #299                // String &
        26: invokeinterface #302,  2          // InterfaceMethod scala/collection/IterableOnceOps.mkString:(Ljava/lang/String;)Ljava/lang/String;
        31: areturn
      LineNumberTable:
        line 78: 0
      LocalVariableTable:
        Start  Length  Slot  Name   Signature
            0      32     0 retainedLatestOpt$1   Lscala/Option;
            0      32     1   itv   Ljava/lang/String;
    MethodParameters:
      Name                           Flags
      retainedLatestOpt$1            final
      itv                            final

  public coursier.core.Reconciliation$Default$();
    descriptor: ()V
    flags: (0x0001) ACC_PUBLIC
    Code:
      stack=1, locals=1, args_size=1
         0: aload_0
         1: invokespecial #303                // Method coursier/core/Reconciliation."<init>":()V
         4: return
      LineNumberTable:
        line 46: 0
      LocalVariableTable:
        Start  Length  Slot  Name   Signature
            0       5     0  this   Lcoursier/core/Reconciliation$Default$;

  public static final java.lang.Object $anonfun$apply$4$adapted(coursier.core.VersionConstraint);
    descriptor: (Lcoursier/core/VersionConstraint;)Ljava/lang/Object;
    flags: (0x1019) ACC_PUBLIC, ACC_STATIC, ACC_FINAL, ACC_SYNTHETIC
    Code:
      stack=1, locals=1, args_size=1
         0: aload_0
         1: invokestatic  #305                // Method $anonfun$apply$4:(Lcoursier/core/VersionConstraint;)Z
         4: invokestatic  #311                // Method scala/runtime/BoxesRunTime.boxToBoolean:(Z)Ljava/lang/Boolean;
         7: areturn
      LineNumberTable:
        line 70: 0
      LocalVariableTable:
        Start  Length  Slot  Name   Signature
            0       8     0   x$3   Lcoursier/core/VersionConstraint;
    MethodParameters:
      Name                           Flags
      x$3                            final

  public static final java.lang.Object $anonfun$apply$5$adapted(coursier.core.VersionConstraint);
    descriptor: (Lcoursier/core/VersionConstraint;)Ljava/lang/Object;
    flags: (0x1019) ACC_PUBLIC, ACC_STATIC, ACC_FINAL, ACC_SYNTHETIC
    Code:
      stack=1, locals=1, args_size=1
         0: aload_0
         1: invokestatic  #313                // Method $anonfun$apply$5:(Lcoursier/core/VersionConstraint;)Z
         4: invokestatic  #311                // Method scala/runtime/BoxesRunTime.boxToBoolean:(Z)Ljava/lang/Boolean;
         7: areturn
      LineNumberTable:
        line 71: 0
      LocalVariableTable:
        Start  Length  Slot  Name   Signature
            0       8     0   x$4   Lcoursier/core/VersionConstraint;
    MethodParameters:
      Name                           Flags
      x$4                            final

  private static java.lang.Object $deserializeLambda$(java.lang.invoke.SerializedLambda);
    descriptor: (Ljava/lang/invoke/SerializedLambda;)Ljava/lang/Object;
    flags: (0x100a) ACC_PRIVATE, ACC_STATIC, ACC_SYNTHETIC
    Code:
      stack=1, locals=1, args_size=1
         0: aload_0
         1: invokedynamic #325,  0            // InvokeDynamic #7:lambdaDeserialize:(Ljava/lang/invoke/SerializedLambda;)Ljava/lang/Object;
         6: areturn
}
InnerClasses:
  public static #10= #2 of #4;            // =class coursier/core/Reconciliation$Default$ of class coursier/core/Reconciliation
  public static final #15= #12 of #14;    // Lookup=class java/lang/invoke/MethodHandles$Lookup of class java/lang/invoke/MethodHandles
SourceFile: "Reconciliation.scala"
BootstrapMethods:
  0: #116 REF_invokeStatic java/lang/invoke/LambdaMetafactory.altMetafactory:(Ljava/lang/invoke/MethodHandles$Lookup;Ljava/lang/String;Ljava/lang/invoke/MethodType;[Ljava/lang/Object;)Ljava/lang/invoke/CallSite;
    Method arguments:
      #101 (Ljava/lang/Object;)Ljava/lang/Object;
      #106 REF_invokeStatic coursier/core/Reconciliation$Default$.$anonfun$apply$1:(Ljava/lang/String;)Lcoursier/core/VersionConstraint;
      #107 (Ljava/lang/String;)Lcoursier/core/VersionConstraint;
      #108 5
      #109 1
      #107 (Ljava/lang/String;)Lcoursier/core/VersionConstraint;
  1: #116 REF_invokeStatic java/lang/invoke/LambdaMetafactory.altMetafactory:(Ljava/lang/invoke/MethodHandles$Lookup;Ljava/lang/String;Ljava/lang/invoke/MethodType;[Ljava/lang/Object;)Ljava/lang/invoke/CallSite;
    Method arguments:
      #101 (Ljava/lang/Object;)Ljava/lang/Object;
      #136 REF_invokeStatic coursier/core/Reconciliation$Default$.$anonfun$apply$2:(Lcoursier/core/VersionConstraint;)Lscala/Option;
      #137 (Lcoursier/core/VersionConstraint;)Lscala/Option;
      #108 5
      #109 1
      #137 (Lcoursier/core/VersionConstraint;)Lscala/Option;
  2: #116 REF_invokeStatic java/lang/invoke/LambdaMetafactory.altMetafactory:(Ljava/lang/invoke/MethodHandles$Lookup;Ljava/lang/String;Ljava/lang/invoke/MethodType;[Ljava/lang/Object;)Ljava/lang/invoke/CallSite;
    Method arguments:
      #101 (Ljava/lang/Object;)Ljava/lang/Object;
      #151 REF_invokeStatic coursier/core/Reconciliation$Default$.$anonfun$apply$3:(Ljava/lang/String;)Lcoursier/core/VersionConstraint;
      #107 (Ljava/lang/String;)Lcoursier/core/VersionConstraint;
      #108 5
      #109 1
      #107 (Ljava/lang/String;)Lcoursier/core/VersionConstraint;
  3: #116 REF_invokeStatic java/lang/invoke/LambdaMetafactory.altMetafactory:(Ljava/lang/invoke/MethodHandles$Lookup;Ljava/lang/String;Ljava/lang/invoke/MethodType;[Ljava/lang/Object;)Ljava/lang/invoke/CallSite;
    Method arguments:
      #101 (Ljava/lang/Object;)Ljava/lang/Object;
      #159 REF_invokeStatic coursier/core/Reconciliation$Default$.$anonfun$apply$4$adapted:(Lcoursier/core/VersionConstraint;)Ljava/lang/Object;
      #160 (Lcoursier/core/VersionConstraint;)Ljava/lang/Object;
      #108 5
      #109 1
      #160 (Lcoursier/core/VersionConstraint;)Ljava/lang/Object;
  4: #116 REF_invokeStatic java/lang/invoke/LambdaMetafactory.altMetafactory:(Ljava/lang/invoke/MethodHandles$Lookup;Ljava/lang/String;Ljava/lang/invoke/MethodType;[Ljava/lang/Object;)Ljava/lang/invoke/CallSite;
    Method arguments:
      #101 (Ljava/lang/Object;)Ljava/lang/Object;
      #168 REF_invokeStatic coursier/core/Reconciliation$Default$.$anonfun$apply$5$adapted:(Lcoursier/core/VersionConstraint;)Ljava/lang/Object;
      #160 (Lcoursier/core/VersionConstraint;)Ljava/lang/Object;
      #108 5
      #109 1
      #160 (Lcoursier/core/VersionConstraint;)Ljava/lang/Object;
  5: #116 REF_invokeStatic java/lang/invoke/LambdaMetafactory.altMetafactory:(Ljava/lang/invoke/MethodHandles$Lookup;Ljava/lang/String;Ljava/lang/invoke/MethodType;[Ljava/lang/Object;)Ljava/lang/invoke/CallSite;
    Method arguments:
      #101 (Ljava/lang/Object;)Ljava/lang/Object;
      #173 REF_invokeStatic coursier/core/Reconciliation$Default$.$anonfun$apply$6:(Lcoursier/core/VersionConstraint;)Lscala/Option;
      #137 (Lcoursier/core/VersionConstraint;)Lscala/Option;
      #108 5
      #109 1
      #137 (Lcoursier/core/VersionConstraint;)Lscala/Option;
  6: #116 REF_invokeStatic java/lang/invoke/LambdaMetafactory.altMetafactory:(Ljava/lang/invoke/MethodHandles$Lookup;Ljava/lang/String;Ljava/lang/invoke/MethodType;[Ljava/lang/Object;)Ljava/lang/invoke/CallSite;
    Method arguments:
      #101 (Ljava/lang/Object;)Ljava/lang/Object;
      #179 REF_invokeStatic coursier/core/Reconciliation$Default$.$anonfun$apply$7:(Lscala/Option;Ljava/lang/String;)Ljava/lang/String;
      #181 (Ljava/lang/String;)Ljava/lang/String;
      #108 5
      #109 1
      #181 (Ljava/lang/String;)Ljava/lang/String;
  7: #322 REF_invokeStatic scala/runtime/LambdaDeserialize.bootstrap:(Ljava/lang/invoke/MethodHandles$Lookup;Ljava/lang/String;Ljava/lang/invoke/MethodType;[Ljava/lang/invoke/MethodHandle;)Ljava/lang/invoke/CallSite;
    Method arguments:
      #106 REF_invokeStatic coursier/core/Reconciliation$Default$.$anonfun$apply$1:(Ljava/lang/String;)Lcoursier/core/VersionConstraint;
      #136 REF_invokeStatic coursier/core/Reconciliation$Default$.$anonfun$apply$2:(Lcoursier/core/VersionConstraint;)Lscala/Option;
      #151 REF_invokeStatic coursier/core/Reconciliation$Default$.$anonfun$apply$3:(Ljava/lang/String;)Lcoursier/core/VersionConstraint;
      #159 REF_invokeStatic coursier/core/Reconciliation$Default$.$anonfun$apply$4$adapted:(Lcoursier/core/VersionConstraint;)Ljava/lang/Object;
      #168 REF_invokeStatic coursier/core/Reconciliation$Default$.$anonfun$apply$5$adapted:(Lcoursier/core/VersionConstraint;)Ljava/lang/Object;
      #173 REF_invokeStatic coursier/core/Reconciliation$Default$.$anonfun$apply$6:(Lcoursier/core/VersionConstraint;)Lscala/Option;
      #179 REF_invokeStatic coursier/core/Reconciliation$Default$.$anonfun$apply$7:(Lscala/Option;Ljava/lang/String;)Ljava/lang/String;
  ScalaInlineInfo: length = 0x6D (unknown attribute)
   01 01 00 15 00 66 00 67 01 00 84 00 85 01 00 94
   00 67 01 00 FA 00 FB 01 00 9B 00 9C 01 01 01 00
   FB 01 00 A5 00 9C 01 00 AA 00 85 01 00 AF 00 B0
   01 00 14 00 13 01 00 2D 00 2E 01 00 DD 00 DE 01
   00 E0 00 C8 01 00 C7 00 C8 01 00 C9 00 CA 01 00
   1D 00 1E 01 00 26 00 27 01 00 D3 00 27 01 00 C3
   00 C4 01 00 E2 00 C4 01 00 E3 00 43 01
  Scala: length = 0x0 (unknown attribute)

