Classfile /Users/mw/Projects/slang-braindump/.jar/jar11/assemble/slang-braindump/assemble/content/coursier/core/SnapshotVersion.class
  Last modified May 29, 2022; size 7075 bytes
  SHA-256 checksum d09d84e4b26c4ad9b1ce3f29cae86003d5a4b7e41e5439557ec33868b2dd4dc9
  Compiled from "Definitions.scala"
public final class coursier.core.SnapshotVersion implements scala.Product,java.io.Serializable
  minor version: 0
  major version: 52
  flags: (0x0031) ACC_PUBLIC, ACC_FINAL, ACC_SUPER
  this_class: #2                          // coursier/core/SnapshotVersion
  super_class: #4                         // java/lang/Object
  interfaces: 2, fields: 4, methods: 21, attributes: 5
Constant pool:
    #1 = Utf8               coursier/core/SnapshotVersion
    #2 = Class              #1            // coursier/core/SnapshotVersion
    #3 = Utf8               java/lang/Object
    #4 = Class              #3            // java/lang/Object
    #5 = Utf8               scala/Product
    #6 = Class              #5            // scala/Product
    #7 = Utf8               java/io/Serializable
    #8 = Class              #7            // java/io/Serializable
    #9 = Utf8               Definitions.scala
   #10 = Utf8               Lscala/reflect/ScalaSignature;
   #11 = Utf8               bytes
   #12 = Utf8               \u0006\u0005\u0005}c\u0001\u0002\u000f\u001e\u0005\tB\u0001\u0002\u000f\u0001\u0003\u0006\u0004%\t!\u000f\u0005\t}\u0001\u0011\t\u0011)A\u0005u!Aq\b\u0001BC\u0002\u0013\u0005\u0001\t\u0003\u0005E\u0001\t\u0005\t\u0015!\u0003B\u0011!)\u0005A!b\u0001\n\u00031\u0005\u0002C(\u0001\u0005\u0003\u0005\u000b\u0011B$\t\u0011A\u0003!Q1A\u0005\u0002EC\u0001\u0002\u0018\u0001\u0003\u0002\u0003\u0006IA\u0015\u0005\u0006;\u0002!\tA\u0018\u0005\u0006I\u0002!\t!\u001a\u0005\u0006O\u0002!\t\u0001\u001b\u0005\u0006U\u0002!\ta\u001b\u0005\u0006[\u0002!\tA\u001c\u0005\u0006a\u0002!\t%\u001d\u0005\u0006s\u0002!\tE\u001f\u0005\b\u0003\u000f\u0001A\u0011IA\u0005\u0011\u001d\ti\u0001\u0001C!\u0003\u001fAq!a\u0006\u0001\t\u0013\tI\u0002C\u0004\u0002\"\u0001!\t%a\t\t\u000f\u0005\u0015\u0002\u0001\"\u0011\u0002(!9\u0011\u0011\u0006\u0001\u0005B\u0005-\u0002bBA\u0019\u0001\u0011\u0005\u00131G\u0004\b\u0003oi\u0002\u0012AA\u001d\r\u0019aR\u0004#\u0001\u0002<!1Q\f\u0007C\u0001\u0003\u000fBq!!\u0013\u0019\t\u0003\tY\u0005C\u0005\u0002Va\t\t\u0011\"\u0003\u0002X\ty1K\\1qg\"|GOV3sg&|gN\u0003\u0002\u001f?\u0005!1m\u001c:f\u0015\u0005\u0001\u0013\u0001C2pkJ\u001c\u0018.\u001a:\u0004\u0001M!\u0001aI\u0015-!\t!s%D\u0001&\u0015\u00051\u0013!B:dC2\f\u0017B\u0001\u0015&\u0005\u0019\te.\u001f*fMB\u0011AEK\u0005\u0003W\u0015\u0012q\u0001\u0015:pIV\u001cG\u000f\u0005\u0002.k9\u0011af\r\b\u0003_Ij\u0011\u0001\r\u0006\u0003c\u0005\na\u0001\u0010:p_Rt\u0014\"\u0001\u0014\n\u0005Q*\u0013a\u00029bG.\fw-Z\u0005\u0003m]\u0012AbU3sS\u0006d\u0017N_1cY\u0016T!\u0001N\u0013\u0002\u0015\rd\u0017m]:jM&,\'/F\u0001;!\tYD(D\u0001\u001e\u0013\tiTD\u0001\u0006DY\u0006\u001c8/\u001b4jKJ\f1b\u00197bgNLg-[3sA\u0005IQ\r\u001f;f]NLwN\\\u000b\u0002\u0003B\u00111HQ\u0005\u0003\u0007v\u0011\u0011\"\u0012=uK:\u001c\u0018n\u001c8\u0002\u0015\u0015DH/\u001a8tS>t\u0007%A\u0003wC2,X-F\u0001H!\tAEJ\u0004\u0002J\u0015B\u0011q&J\u0005\u0003\u0017\u0016\na\u0001\u0015:fI\u00164\u0017BA\'O\u0005\u0019\u0019FO]5oO*\u00111*J\u0001\u0007m\u0006dW/\u001a\u0011\u0002\u000fU\u0004H-\u0019;fIV\t!\u000bE\u0002%\'VK!\u0001V\u0013\u0003\r=\u0003H/[8o!\t1\u0016L\u0004\u0002</&\u0011\u0001,H\u0001\t-\u0016\u00148/[8og&\u0011!l\u0017\u0002\t\t\u0006$X\rV5nK*\u0011\u0001,H\u0001\tkB$\u0017\r^3eA\u00051A(\u001b8jiz\"Ra\u00181bE\u000e\u0004\"a\u000f\u0001\t\u000baJ\u0001\u0019\u0001\u001e\t\u000b}J\u0001\u0019A!\t\u000b\u0015K\u0001\u0019A$\t\u000bAK\u0001\u0019\u0001*\u0002\u001d]LG\u000f[\"mCN\u001c\u0018NZ5feR\u0011qL\u001a\u0005\u0006q)\u0001\rAO\u0001\u000eo&$\b.\u0012=uK:\u001c\u0018n\u001c8\u0015\u0005}K\u0007\"B \f\u0001\u0004\t\u0015!C<ji\"4\u0016\r\\;f)\tyF\u000eC\u0003F\u0019\u0001\u0007q)A\u0006xSRDW\u000b\u001d3bi\u0016$GCA0p\u0011\u0015\u0001V\u00021\u0001S\u0003!!xn\u0015;sS:<G#\u0001:\u0011\u0005MDX\"\u0001;\u000b\u0005U4\u0018\u0001\u00027b]\u001eT\u0011a^\u0001\u0005U\u00064\u0018-\u0003\u0002Ni\u0006A1-\u00198FcV\fG\u000e\u0006\u0002|}B\u0011A\u0005`\u0005\u0003{\u0016\u0012qAQ8pY\u0016\fg\u000e\u0003\u0004\u0000\u001f\u0001\u0007\u0011\u0011A\u0001\u0004_\nT\u0007c\u0001\u0013\u0002\u0004%\u0019\u0011QA\u0013\u0003\u0007\u0005s\u00170\u0001\u0004fcV\fGn\u001d\u000b\u0004w\u0006-\u0001BB@\u0011\u0001\u0004\t\t!\u0001\u0005iCND7i\u001c3f)\t\t\t\u0002E\u0002%\u0003\'I1!!\u0006&\u0005\rIe\u000e^\u0001\u0006iV\u0004H.Z\u000b\u0003\u00037\u0001r\u0001JA\u000fu\u0005;%+C\u0002\u0002 \u0015\u0012a\u0001V;qY\u0016$\u0014!\u00049s_\u0012,8\r\u001e)sK\u001aL\u00070F\u0001s\u00031\u0001(o\u001c3vGR\f%/\u001b;z+\t\t\t\"\u0001\bqe>$Wo\u0019;FY\u0016lWM\u001c;\u0015\t\u0005\u0005\u0011Q\u0006\u0005\b\u0003_)\u0002\u0019AA\t\u0003\u0005q\u0017A\u00059s_\u0012,8\r^#mK6,g\u000e\u001e(b[\u0016$2A]A\u001b\u0011\u001d\tyC\u0006a\u0001\u0003#\tqb\u00158baNDw\u000e\u001e,feNLwN\u001c\t\u0003wa\u0019B\u0001G\u0012\u0002>A!\u0011qHA#\u001b\t\t\tEC\u0002\u0002DY\f!![8\n\u0007Y\n\t\u0005\u0006\u0002\u0002:\u0005)\u0011\r\u001d9msRIq,!\u0014\u0002P\u0005E\u00131\u000b\u0005\u0006qi\u0001\rA\u000f\u0005\u0006\u007fi\u0001\r!\u0011\u0005\u0006\u000bj\u0001\ra\u0012\u0005\u0006!j\u0001\rAU\u0001\roJLG/\u001a*fa2\f7-\u001a\u000b\u0003\u00033\u00022a]A.\u0013\r\ti\u0006\u001e\u0002\u0007\u001f\nTWm\u0019;
   #13 = Utf8               coursier/core/Versions$DateTime
   #14 = Class              #13           // coursier/core/Versions$DateTime
   #15 = Utf8               coursier/core/Versions
   #16 = Class              #15           // coursier/core/Versions
   #17 = Utf8               DateTime
   #18 = Utf8               classifier
   #19 = Utf8               Ljava/lang/String;
   #20 = Utf8               extension
   #21 = Utf8               value
   #22 = Utf8               updated
   #23 = Utf8               Lscala/Option;
   #24 = Utf8               Lscala/Option<Lcoursier/core/Versions$DateTime;>;
   #25 = Utf8               apply
   #26 = Utf8               (Ljava/lang/String;Ljava/lang/String;Ljava/lang/String;Lscala/Option;)Lcoursier/core/SnapshotVersion;
   #27 = Utf8               (Ljava/lang/String;Ljava/lang/String;Ljava/lang/String;Lscala/Option<Lcoursier/core/Versions$DateTime;>;)Lcoursier/core/SnapshotVersion;
   #28 = Utf8               coursier/core/SnapshotVersion$
   #29 = Class              #28           // coursier/core/SnapshotVersion$
   #30 = Utf8               MODULE$
   #31 = Utf8               Lcoursier/core/SnapshotVersion$;
   #32 = NameAndType        #30:#31       // MODULE$:Lcoursier/core/SnapshotVersion$;
   #33 = Fieldref           #29.#32       // coursier/core/SnapshotVersion$.MODULE$:Lcoursier/core/SnapshotVersion$;
   #34 = NameAndType        #25:#26       // apply:(Ljava/lang/String;Ljava/lang/String;Ljava/lang/String;Lscala/Option;)Lcoursier/core/SnapshotVersion;
   #35 = Methodref          #29.#34       // coursier/core/SnapshotVersion$.apply:(Ljava/lang/String;Ljava/lang/String;Ljava/lang/String;Lscala/Option;)Lcoursier/core/SnapshotVersion;
   #36 = Utf8               productIterator
   #37 = Utf8               ()Lscala/collection/Iterator;
   #38 = Utf8               ()Lscala/collection/Iterator<Ljava/lang/Object;>;
   #39 = Utf8               productIterator$
   #40 = Utf8               (Lscala/Product;)Lscala/collection/Iterator;
   #41 = NameAndType        #39:#40       // productIterator$:(Lscala/Product;)Lscala/collection/Iterator;
   #42 = InterfaceMethodref #6.#41        // scala/Product.productIterator$:(Lscala/Product;)Lscala/collection/Iterator;
   #43 = Utf8               this
   #44 = Utf8               Lcoursier/core/SnapshotVersion;
   #45 = Utf8               productElementNames
   #46 = Utf8               ()Lscala/collection/Iterator<Ljava/lang/String;>;
   #47 = Utf8               productElementNames$
   #48 = NameAndType        #47:#40       // productElementNames$:(Lscala/Product;)Lscala/collection/Iterator;
   #49 = InterfaceMethodref #6.#48        // scala/Product.productElementNames$:(Lscala/Product;)Lscala/collection/Iterator;
   #50 = Utf8               ()Ljava/lang/String;
   #51 = NameAndType        #18:#19       // classifier:Ljava/lang/String;
   #52 = Fieldref           #2.#51        // coursier/core/SnapshotVersion.classifier:Ljava/lang/String;
   #53 = NameAndType        #20:#19       // extension:Ljava/lang/String;
   #54 = Fieldref           #2.#53        // coursier/core/SnapshotVersion.extension:Ljava/lang/String;
   #55 = NameAndType        #21:#19       // value:Ljava/lang/String;
   #56 = Fieldref           #2.#55        // coursier/core/SnapshotVersion.value:Ljava/lang/String;
   #57 = Utf8               ()Lscala/Option;
   #58 = Utf8               ()Lscala/Option<Lcoursier/core/Versions$DateTime;>;
   #59 = NameAndType        #22:#23       // updated:Lscala/Option;
   #60 = Fieldref           #2.#59        // coursier/core/SnapshotVersion.updated:Lscala/Option;
   #61 = Utf8               withClassifier
   #62 = Utf8               (Ljava/lang/String;)Lcoursier/core/SnapshotVersion;
   #63 = NameAndType        #20:#50       // extension:()Ljava/lang/String;
   #64 = Methodref          #2.#63        // coursier/core/SnapshotVersion.extension:()Ljava/lang/String;
   #65 = NameAndType        #21:#50       // value:()Ljava/lang/String;
   #66 = Methodref          #2.#65        // coursier/core/SnapshotVersion.value:()Ljava/lang/String;
   #67 = NameAndType        #22:#57       // updated:()Lscala/Option;
   #68 = Methodref          #2.#67        // coursier/core/SnapshotVersion.updated:()Lscala/Option;
   #69 = Utf8               <init>
   #70 = Utf8               (Ljava/lang/String;Ljava/lang/String;Ljava/lang/String;Lscala/Option;)V
   #71 = NameAndType        #69:#70       // "<init>":(Ljava/lang/String;Ljava/lang/String;Ljava/lang/String;Lscala/Option;)V
   #72 = Methodref          #2.#71        // coursier/core/SnapshotVersion."<init>":(Ljava/lang/String;Ljava/lang/String;Ljava/lang/String;Lscala/Option;)V
   #73 = Utf8               withExtension
   #74 = NameAndType        #18:#50       // classifier:()Ljava/lang/String;
   #75 = Methodref          #2.#74        // coursier/core/SnapshotVersion.classifier:()Ljava/lang/String;
   #76 = Utf8               withValue
   #77 = Utf8               withUpdated
   #78 = Utf8               (Lscala/Option;)Lcoursier/core/SnapshotVersion;
   #79 = Utf8               (Lscala/Option<Lcoursier/core/Versions$DateTime;>;)Lcoursier/core/SnapshotVersion;
   #80 = Utf8               toString
   #81 = Utf8               java/lang/StringBuilder
   #82 = Class              #81           // java/lang/StringBuilder
   #83 = Utf8               SnapshotVersion(
   #84 = String             #83           // SnapshotVersion(
   #85 = Utf8               (Ljava/lang/String;)V
   #86 = NameAndType        #69:#85       // "<init>":(Ljava/lang/String;)V
   #87 = Methodref          #82.#86       // java/lang/StringBuilder."<init>":(Ljava/lang/String;)V
   #88 = Utf8               coursier/core/Classifier
   #89 = Class              #88           // coursier/core/Classifier
   #90 = Methodref          #89.#86       // coursier/core/Classifier."<init>":(Ljava/lang/String;)V
   #91 = Utf8               java/lang/String
   #92 = Class              #91           // java/lang/String
   #93 = Utf8               valueOf
   #94 = Utf8               (Ljava/lang/Object;)Ljava/lang/String;
   #95 = NameAndType        #93:#94       // valueOf:(Ljava/lang/Object;)Ljava/lang/String;
   #96 = Methodref          #92.#95       // java/lang/String.valueOf:(Ljava/lang/Object;)Ljava/lang/String;
   #97 = Utf8               append
   #98 = Utf8               (Ljava/lang/String;)Ljava/lang/StringBuilder;
   #99 = NameAndType        #97:#98       // append:(Ljava/lang/String;)Ljava/lang/StringBuilder;
  #100 = Methodref          #82.#99       // java/lang/StringBuilder.append:(Ljava/lang/String;)Ljava/lang/StringBuilder;
  #101 = Utf8               ,
  #102 = String             #101          // ,
  #103 = Utf8               coursier/core/Extension
  #104 = Class              #103          // coursier/core/Extension
  #105 = Methodref          #104.#86      // coursier/core/Extension."<init>":(Ljava/lang/String;)V
  #106 = Utf8               )
  #107 = String             #106          // )
  #108 = NameAndType        #80:#50       // toString:()Ljava/lang/String;
  #109 = Methodref          #82.#108      // java/lang/StringBuilder.toString:()Ljava/lang/String;
  #110 = Utf8               b
  #111 = Utf8               Ljava/lang/StringBuilder;
  #112 = Utf8               canEqual
  #113 = Utf8               (Ljava/lang/Object;)Z
  #114 = Utf8               obj
  #115 = Utf8               Ljava/lang/Object;
  #116 = Utf8               equals
  #117 = NameAndType        #112:#113     // canEqual:(Ljava/lang/Object;)Z
  #118 = Methodref          #2.#117       // coursier/core/SnapshotVersion.canEqual:(Ljava/lang/Object;)Z
  #119 = NameAndType        #116:#113     // equals:(Ljava/lang/Object;)Z
  #120 = Methodref          #4.#119       // java/lang/Object.equals:(Ljava/lang/Object;)Z
  #121 = Utf8               scala/Option
  #122 = Class              #121          // scala/Option
  #123 = Utf8               other
  #124 = Utf8               hashCode
  #125 = Utf8               ()I
  #126 = Utf8               SnapshotVersion
  #127 = String             #126          // SnapshotVersion
  #128 = Utf8               scala/runtime/Statics
  #129 = Class              #128          // scala/runtime/Statics
  #130 = Utf8               anyHash
  #131 = Utf8               (Ljava/lang/Object;)I
  #132 = NameAndType        #130:#131     // anyHash:(Ljava/lang/Object;)I
  #133 = Methodref          #129.#132     // scala/runtime/Statics.anyHash:(Ljava/lang/Object;)I
  #134 = Utf8               code
  #135 = Utf8               I
  #136 = Utf8               tuple
  #137 = Utf8               ()Lscala/Tuple4;
  #138 = Utf8               ()Lscala/Tuple4<Lcoursier/core/Classifier;Lcoursier/core/Extension;Ljava/lang/String;Lscala/Option<Lcoursier/core/Versions$DateTime;>;>;
  #139 = Utf8               scala/Tuple4
  #140 = Class              #139          // scala/Tuple4
  #141 = Utf8               (Ljava/lang/Object;Ljava/lang/Object;Ljava/lang/Object;Ljava/lang/Object;)V
  #142 = NameAndType        #69:#141      // "<init>":(Ljava/lang/Object;Ljava/lang/Object;Ljava/lang/Object;Ljava/lang/Object;)V
  #143 = Methodref          #140.#142     // scala/Tuple4."<init>":(Ljava/lang/Object;Ljava/lang/Object;Ljava/lang/Object;Ljava/lang/Object;)V
  #144 = Utf8               productPrefix
  #145 = Utf8               productArity
  #146 = Utf8               productElement
  #147 = Utf8               (I)Ljava/lang/Object;
  #148 = Utf8               n
  #149 = Utf8               java/lang/IndexOutOfBoundsException
  #150 = Class              #149          // java/lang/IndexOutOfBoundsException
  #151 = Utf8               scala/runtime/BoxesRunTime
  #152 = Class              #151          // scala/runtime/BoxesRunTime
  #153 = Utf8               boxToInteger
  #154 = Utf8               (I)Ljava/lang/Integer;
  #155 = NameAndType        #153:#154     // boxToInteger:(I)Ljava/lang/Integer;
  #156 = Methodref          #152.#155     // scala/runtime/BoxesRunTime.boxToInteger:(I)Ljava/lang/Integer;
  #157 = Methodref          #4.#108       // java/lang/Object.toString:()Ljava/lang/String;
  #158 = Methodref          #150.#86      // java/lang/IndexOutOfBoundsException."<init>":(Ljava/lang/String;)V
  #159 = Utf8               productElementName
  #160 = Utf8               (I)Ljava/lang/String;
  #161 = String             #18           // classifier
  #162 = String             #20           // extension
  #163 = String             #21           // value
  #164 = String             #22           // updated
  #165 = Utf8               (Ljava/lang/String;Ljava/lang/String;Ljava/lang/String;Lscala/Option<Lcoursier/core/Versions$DateTime;>;)V
  #166 = Utf8               ()V
  #167 = NameAndType        #69:#166      // "<init>":()V
  #168 = Methodref          #4.#167       // java/lang/Object."<init>":()V
  #169 = Utf8               $init$
  #170 = Utf8               (Lscala/Product;)V
  #171 = NameAndType        #169:#170     // $init$:(Lscala/Product;)V
  #172 = InterfaceMethodref #6.#171       // scala/Product.$init$:(Lscala/Product;)V
  #173 = Utf8               Signature
  #174 = Utf8               Code
  #175 = Utf8               MethodParameters
  #176 = Utf8               LineNumberTable
  #177 = Utf8               LocalVariableTable
  #178 = Utf8               StackMapTable
  #179 = Utf8               InnerClasses
  #180 = Utf8               SourceFile
  #181 = Utf8               RuntimeVisibleAnnotations
  #182 = Utf8               ScalaInlineInfo
  #183 = Utf8               ScalaSig
{
  private final java.lang.String classifier;
    descriptor: Ljava/lang/String;
    flags: (0x0012) ACC_PRIVATE, ACC_FINAL

  private final java.lang.String extension;
    descriptor: Ljava/lang/String;
    flags: (0x0012) ACC_PRIVATE, ACC_FINAL

  private final java.lang.String value;
    descriptor: Ljava/lang/String;
    flags: (0x0012) ACC_PRIVATE, ACC_FINAL

  private final scala.Option<coursier.core.Versions$DateTime> updated;
    descriptor: Lscala/Option;
    flags: (0x0012) ACC_PRIVATE, ACC_FINAL
    Signature: #24                          // Lscala/Option<Lcoursier/core/Versions$DateTime;>;

  public static coursier.core.SnapshotVersion apply(java.lang.String, java.lang.String, java.lang.String, scala.Option<coursier.core.Versions$DateTime>);
    descriptor: (Ljava/lang/String;Ljava/lang/String;Ljava/lang/String;Lscala/Option;)Lcoursier/core/SnapshotVersion;
    flags: (0x0009) ACC_PUBLIC, ACC_STATIC
    Code:
      stack=5, locals=4, args_size=4
         0: getstatic     #33                 // Field coursier/core/SnapshotVersion$.MODULE$:Lcoursier/core/SnapshotVersion$;
         3: aload_0
         4: aload_1
         5: aload_2
         6: aload_3
         7: invokevirtual #35                 // Method coursier/core/SnapshotVersion$.apply:(Ljava/lang/String;Ljava/lang/String;Ljava/lang/String;Lscala/Option;)Lcoursier/core/SnapshotVersion;
        10: areturn
    Signature: #27                          // (Ljava/lang/String;Ljava/lang/String;Ljava/lang/String;Lscala/Option<Lcoursier/core/Versions$DateTime;>;)Lcoursier/core/SnapshotVersion;
    MethodParameters:
      Name                           Flags
      classifier                     final
      extension                      final
      value                          final
      updated                        final

  public scala.collection.Iterator<java.lang.Object> productIterator();
    descriptor: ()Lscala/collection/Iterator;
    flags: (0x0001) ACC_PUBLIC
    Code:
      stack=1, locals=1, args_size=1
         0: aload_0
         1: invokestatic  #42                 // InterfaceMethod scala/Product.productIterator$:(Lscala/Product;)Lscala/collection/Iterator;
         4: areturn
      LineNumberTable:
        line 364: 0
      LocalVariableTable:
        Start  Length  Slot  Name   Signature
            0       5     0  this   Lcoursier/core/SnapshotVersion;
    Signature: #38                          // ()Lscala/collection/Iterator<Ljava/lang/Object;>;

  public scala.collection.Iterator<java.lang.String> productElementNames();
    descriptor: ()Lscala/collection/Iterator;
    flags: (0x0001) ACC_PUBLIC
    Code:
      stack=1, locals=1, args_size=1
         0: aload_0
         1: invokestatic  #49                 // InterfaceMethod scala/Product.productElementNames$:(Lscala/Product;)Lscala/collection/Iterator;
         4: areturn
      LineNumberTable:
        line 364: 0
      LocalVariableTable:
        Start  Length  Slot  Name   Signature
            0       5     0  this   Lcoursier/core/SnapshotVersion;
    Signature: #46                          // ()Lscala/collection/Iterator<Ljava/lang/String;>;

  public java.lang.String classifier();
    descriptor: ()Ljava/lang/String;
    flags: (0x0001) ACC_PUBLIC
    Code:
      stack=1, locals=1, args_size=1
         0: aload_0
         1: getfield      #52                 // Field classifier:Ljava/lang/String;
         4: areturn
      LineNumberTable:
        line 364: 0
      LocalVariableTable:
        Start  Length  Slot  Name   Signature
            0       5     0  this   Lcoursier/core/SnapshotVersion;

  public java.lang.String extension();
    descriptor: ()Ljava/lang/String;
    flags: (0x0001) ACC_PUBLIC
    Code:
      stack=1, locals=1, args_size=1
         0: aload_0
         1: getfield      #54                 // Field extension:Ljava/lang/String;
         4: areturn
      LineNumberTable:
        line 364: 0
      LocalVariableTable:
        Start  Length  Slot  Name   Signature
            0       5     0  this   Lcoursier/core/SnapshotVersion;

  public java.lang.String value();
    descriptor: ()Ljava/lang/String;
    flags: (0x0001) ACC_PUBLIC
    Code:
      stack=1, locals=1, args_size=1
         0: aload_0
         1: getfield      #56                 // Field value:Ljava/lang/String;
         4: areturn
      LineNumberTable:
        line 364: 0
      LocalVariableTable:
        Start  Length  Slot  Name   Signature
            0       5     0  this   Lcoursier/core/SnapshotVersion;

  public scala.Option<coursier.core.Versions$DateTime> updated();
    descriptor: ()Lscala/Option;
    flags: (0x0001) ACC_PUBLIC
    Code:
      stack=1, locals=1, args_size=1
         0: aload_0
         1: getfield      #60                 // Field updated:Lscala/Option;
         4: areturn
      LineNumberTable:
        line 364: 0
      LocalVariableTable:
        Start  Length  Slot  Name   Signature
            0       5     0  this   Lcoursier/core/SnapshotVersion;
    Signature: #58                          // ()Lscala/Option<Lcoursier/core/Versions$DateTime;>;

  public coursier.core.SnapshotVersion withClassifier(java.lang.String);
    descriptor: (Ljava/lang/String;)Lcoursier/core/SnapshotVersion;
    flags: (0x0001) ACC_PUBLIC
    Code:
      stack=6, locals=2, args_size=2
         0: new           #2                  // class coursier/core/SnapshotVersion
         3: dup
         4: aload_1
         5: aload_0
         6: invokevirtual #64                 // Method extension:()Ljava/lang/String;
         9: aload_0
        10: invokevirtual #66                 // Method value:()Ljava/lang/String;
        13: aload_0
        14: invokevirtual #68                 // Method updated:()Lscala/Option;
        17: invokespecial #72                 // Method "<init>":(Ljava/lang/String;Ljava/lang/String;Ljava/lang/String;Lscala/Option;)V
        20: areturn
      LineNumberTable:
        line 364: 0
      LocalVariableTable:
        Start  Length  Slot  Name   Signature
            0      21     0  this   Lcoursier/core/SnapshotVersion;
            0      21     1 classifier   Ljava/lang/String;
    MethodParameters:
      Name                           Flags
      classifier                     final

  public coursier.core.SnapshotVersion withExtension(java.lang.String);
    descriptor: (Ljava/lang/String;)Lcoursier/core/SnapshotVersion;
    flags: (0x0001) ACC_PUBLIC
    Code:
      stack=6, locals=2, args_size=2
         0: new           #2                  // class coursier/core/SnapshotVersion
         3: dup
         4: aload_0
         5: invokevirtual #75                 // Method classifier:()Ljava/lang/String;
         8: aload_1
         9: aload_0
        10: invokevirtual #66                 // Method value:()Ljava/lang/String;
        13: aload_0
        14: invokevirtual #68                 // Method updated:()Lscala/Option;
        17: invokespecial #72                 // Method "<init>":(Ljava/lang/String;Ljava/lang/String;Ljava/lang/String;Lscala/Option;)V
        20: areturn
      LineNumberTable:
        line 364: 0
      LocalVariableTable:
        Start  Length  Slot  Name   Signature
            0      21     0  this   Lcoursier/core/SnapshotVersion;
            0      21     1 extension   Ljava/lang/String;
    MethodParameters:
      Name                           Flags
      extension                      final

  public coursier.core.SnapshotVersion withValue(java.lang.String);
    descriptor: (Ljava/lang/String;)Lcoursier/core/SnapshotVersion;
    flags: (0x0001) ACC_PUBLIC
    Code:
      stack=6, locals=2, args_size=2
         0: new           #2                  // class coursier/core/SnapshotVersion
         3: dup
         4: aload_0
         5: invokevirtual #75                 // Method classifier:()Ljava/lang/String;
         8: aload_0
         9: invokevirtual #64                 // Method extension:()Ljava/lang/String;
        12: aload_1
        13: aload_0
        14: invokevirtual #68                 // Method updated:()Lscala/Option;
        17: invokespecial #72                 // Method "<init>":(Ljava/lang/String;Ljava/lang/String;Ljava/lang/String;Lscala/Option;)V
        20: areturn
      LineNumberTable:
        line 364: 0
      LocalVariableTable:
        Start  Length  Slot  Name   Signature
            0      21     0  this   Lcoursier/core/SnapshotVersion;
            0      21     1 value   Ljava/lang/String;
    MethodParameters:
      Name                           Flags
      value                          final

  public coursier.core.SnapshotVersion withUpdated(scala.Option<coursier.core.Versions$DateTime>);
    descriptor: (Lscala/Option;)Lcoursier/core/SnapshotVersion;
    flags: (0x0001) ACC_PUBLIC
    Code:
      stack=6, locals=2, args_size=2
         0: new           #2                  // class coursier/core/SnapshotVersion
         3: dup
         4: aload_0
         5: invokevirtual #75                 // Method classifier:()Ljava/lang/String;
         8: aload_0
         9: invokevirtual #64                 // Method extension:()Ljava/lang/String;
        12: aload_0
        13: invokevirtual #66                 // Method value:()Ljava/lang/String;
        16: aload_1
        17: invokespecial #72                 // Method "<init>":(Ljava/lang/String;Ljava/lang/String;Ljava/lang/String;Lscala/Option;)V
        20: areturn
      LineNumberTable:
        line 364: 0
      LocalVariableTable:
        Start  Length  Slot  Name   Signature
            0      21     0  this   Lcoursier/core/SnapshotVersion;
            0      21     1 updated   Lscala/Option;
    Signature: #79                          // (Lscala/Option<Lcoursier/core/Versions$DateTime;>;)Lcoursier/core/SnapshotVersion;
    MethodParameters:
      Name                           Flags
      updated                        final

  public java.lang.String toString();
    descriptor: ()Ljava/lang/String;
    flags: (0x0001) ACC_PUBLIC
    Code:
      stack=4, locals=2, args_size=1
         0: new           #82                 // class java/lang/StringBuilder
         3: dup
         4: ldc           #84                 // String SnapshotVersion(
         6: invokespecial #87                 // Method java/lang/StringBuilder."<init>":(Ljava/lang/String;)V
         9: astore_1
        10: aload_1
        11: new           #89                 // class coursier/core/Classifier
        14: dup
        15: aload_0
        16: invokevirtual #75                 // Method classifier:()Ljava/lang/String;
        19: invokespecial #90                 // Method coursier/core/Classifier."<init>":(Ljava/lang/String;)V
        22: invokestatic  #96                 // Method java/lang/String.valueOf:(Ljava/lang/Object;)Ljava/lang/String;
        25: invokevirtual #100                // Method java/lang/StringBuilder.append:(Ljava/lang/String;)Ljava/lang/StringBuilder;
        28: pop
        29: aload_1
        30: ldc           #102                // String ,
        32: invokevirtual #100                // Method java/lang/StringBuilder.append:(Ljava/lang/String;)Ljava/lang/StringBuilder;
        35: pop
        36: aload_1
        37: new           #104                // class coursier/core/Extension
        40: dup
        41: aload_0
        42: invokevirtual #64                 // Method extension:()Ljava/lang/String;
        45: invokespecial #105                // Method coursier/core/Extension."<init>":(Ljava/lang/String;)V
        48: invokestatic  #96                 // Method java/lang/String.valueOf:(Ljava/lang/Object;)Ljava/lang/String;
        51: invokevirtual #100                // Method java/lang/StringBuilder.append:(Ljava/lang/String;)Ljava/lang/StringBuilder;
        54: pop
        55: aload_1
        56: ldc           #102                // String ,
        58: invokevirtual #100                // Method java/lang/StringBuilder.append:(Ljava/lang/String;)Ljava/lang/StringBuilder;
        61: pop
        62: aload_1
        63: aload_0
        64: invokevirtual #66                 // Method value:()Ljava/lang/String;
        67: invokestatic  #96                 // Method java/lang/String.valueOf:(Ljava/lang/Object;)Ljava/lang/String;
        70: invokevirtual #100                // Method java/lang/StringBuilder.append:(Ljava/lang/String;)Ljava/lang/StringBuilder;
        73: pop
        74: aload_1
        75: ldc           #102                // String ,
        77: invokevirtual #100                // Method java/lang/StringBuilder.append:(Ljava/lang/String;)Ljava/lang/StringBuilder;
        80: pop
        81: aload_1
        82: aload_0
        83: invokevirtual #68                 // Method updated:()Lscala/Option;
        86: invokestatic  #96                 // Method java/lang/String.valueOf:(Ljava/lang/Object;)Ljava/lang/String;
        89: invokevirtual #100                // Method java/lang/StringBuilder.append:(Ljava/lang/String;)Ljava/lang/StringBuilder;
        92: pop
        93: aload_1
        94: ldc           #107                // String )
        96: invokevirtual #100                // Method java/lang/StringBuilder.append:(Ljava/lang/String;)Ljava/lang/StringBuilder;
        99: pop
       100: aload_1
       101: invokevirtual #109                // Method java/lang/StringBuilder.toString:()Ljava/lang/String;
       104: areturn
      LineNumberTable:
        line 364: 0
      LocalVariableTable:
        Start  Length  Slot  Name   Signature
           10      94     1     b   Ljava/lang/StringBuilder;
            0     105     0  this   Lcoursier/core/SnapshotVersion;

  public boolean canEqual(java.lang.Object);
    descriptor: (Ljava/lang/Object;)Z
    flags: (0x0001) ACC_PUBLIC
    Code:
      stack=1, locals=2, args_size=2
         0: aload_1
         1: ifnull        15
         4: aload_1
         5: instanceof    #2                  // class coursier/core/SnapshotVersion
         8: ifeq          15
        11: iconst_1
        12: goto          16
        15: iconst_0
        16: ireturn
      StackMapTable: number_of_entries = 2
        frame_type = 15 /* same */
        frame_type = 64 /* same_locals_1_stack_item */
          stack = [ int ]
      LineNumberTable:
        line 364: 0
      LocalVariableTable:
        Start  Length  Slot  Name   Signature
            0      17     0  this   Lcoursier/core/SnapshotVersion;
            0      17     1   obj   Ljava/lang/Object;
    MethodParameters:
      Name                           Flags
      obj                            final

  public boolean equals(java.lang.Object);
    descriptor: (Ljava/lang/Object;)Z
    flags: (0x0001) ACC_PUBLIC
    Code:
      stack=2, locals=7, args_size=2
         0: aload_0
         1: aload_1
         2: if_acmpeq     151
         5: aload_0
         6: aload_1
         7: invokevirtual #118                // Method canEqual:(Ljava/lang/Object;)Z
        10: ifeq          155
        13: aload_1
        14: checkcast     #2                  // class coursier/core/SnapshotVersion
        17: astore_2
        18: iconst_1
        19: ifeq          147
        22: aload_0
        23: invokevirtual #75                 // Method classifier:()Ljava/lang/String;
        26: aload_2
        27: invokevirtual #75                 // Method classifier:()Ljava/lang/String;
        30: astore_3
        31: dup
        32: ifnonnull     43
        35: pop
        36: aload_3
        37: ifnull        50
        40: goto          147
        43: aload_3
        44: invokevirtual #120                // Method java/lang/Object.equals:(Ljava/lang/Object;)Z
        47: ifeq          147
        50: aload_0
        51: invokevirtual #64                 // Method extension:()Ljava/lang/String;
        54: aload_2
        55: invokevirtual #64                 // Method extension:()Ljava/lang/String;
        58: astore        4
        60: dup
        61: ifnonnull     73
        64: pop
        65: aload         4
        67: ifnull        81
        70: goto          147
        73: aload         4
        75: invokevirtual #120                // Method java/lang/Object.equals:(Ljava/lang/Object;)Z
        78: ifeq          147
        81: aload_0
        82: invokevirtual #66                 // Method value:()Ljava/lang/String;
        85: aload_2
        86: invokevirtual #66                 // Method value:()Ljava/lang/String;
        89: astore        5
        91: dup
        92: ifnonnull     104
        95: pop
        96: aload         5
        98: ifnull        112
       101: goto          147
       104: aload         5
       106: invokevirtual #120                // Method java/lang/Object.equals:(Ljava/lang/Object;)Z
       109: ifeq          147
       112: aload_0
       113: invokevirtual #68                 // Method updated:()Lscala/Option;
       116: aload_2
       117: invokevirtual #68                 // Method updated:()Lscala/Option;
       120: astore        6
       122: dup
       123: ifnonnull     135
       126: pop
       127: aload         6
       129: ifnull        143
       132: goto          147
       135: aload         6
       137: invokevirtual #120                // Method java/lang/Object.equals:(Ljava/lang/Object;)Z
       140: ifeq          147
       143: iconst_1
       144: goto          148
       147: iconst_0
       148: ifeq          155
       151: iconst_1
       152: goto          156
       155: iconst_0
       156: ireturn
      StackMapTable: number_of_entries = 13
        frame_type = 255 /* full_frame */
          offset_delta = 43
          locals = [ class coursier/core/SnapshotVersion, class java/lang/Object, class coursier/core/SnapshotVersion, class java/lang/String ]
          stack = [ class java/lang/String ]
        frame_type = 6 /* same */
        frame_type = 255 /* full_frame */
          offset_delta = 22
          locals = [ class coursier/core/SnapshotVersion, class java/lang/Object, class coursier/core/SnapshotVersion, class java/lang/String, class java/lang/String ]
          stack = [ class java/lang/String ]
        frame_type = 7 /* same */
        frame_type = 255 /* full_frame */
          offset_delta = 22
          locals = [ class coursier/core/SnapshotVersion, class java/lang/Object, class coursier/core/SnapshotVersion, class java/lang/String, class java/lang/String, class java/lang/String ]
          stack = [ class java/lang/String ]
        frame_type = 7 /* same */
        frame_type = 255 /* full_frame */
          offset_delta = 22
          locals = [ class coursier/core/SnapshotVersion, class java/lang/Object, class coursier/core/SnapshotVersion, class java/lang/String, class java/lang/String, class java/lang/String, class scala/Option ]
          stack = [ class scala/Option ]
        frame_type = 7 /* same */
        frame_type = 255 /* full_frame */
          offset_delta = 3
          locals = [ class coursier/core/SnapshotVersion, class java/lang/Object, class coursier/core/SnapshotVersion ]
          stack = []
        frame_type = 64 /* same_locals_1_stack_item */
          stack = [ int ]
        frame_type = 250 /* chop */
          offset_delta = 2
        frame_type = 3 /* same */
        frame_type = 64 /* same_locals_1_stack_item */
          stack = [ int ]
      LineNumberTable:
        line 364: 0
      LocalVariableTable:
        Start  Length  Slot  Name   Signature
           18     130     2 other   Lcoursier/core/SnapshotVersion;
            0     157     0  this   Lcoursier/core/SnapshotVersion;
            0     157     1   obj   Ljava/lang/Object;
    MethodParameters:
      Name                           Flags
      obj                            final

  public int hashCode();
    descriptor: ()I
    flags: (0x0001) ACC_PUBLIC
    Code:
      stack=4, locals=2, args_size=1
         0: bipush        17
         2: ldc           #127                // String SnapshotVersion
         4: invokestatic  #133                // Method scala/runtime/Statics.anyHash:(Ljava/lang/Object;)I
         7: iadd
         8: istore_1
         9: bipush        37
        11: iload_1
        12: imul
        13: new           #89                 // class coursier/core/Classifier
        16: dup
        17: aload_0
        18: invokevirtual #75                 // Method classifier:()Ljava/lang/String;
        21: invokespecial #90                 // Method coursier/core/Classifier."<init>":(Ljava/lang/String;)V
        24: invokestatic  #133                // Method scala/runtime/Statics.anyHash:(Ljava/lang/Object;)I
        27: iadd
        28: istore_1
        29: bipush        37
        31: iload_1
        32: imul
        33: new           #104                // class coursier/core/Extension
        36: dup
        37: aload_0
        38: invokevirtual #64                 // Method extension:()Ljava/lang/String;
        41: invokespecial #105                // Method coursier/core/Extension."<init>":(Ljava/lang/String;)V
        44: invokestatic  #133                // Method scala/runtime/Statics.anyHash:(Ljava/lang/Object;)I
        47: iadd
        48: istore_1
        49: bipush        37
        51: iload_1
        52: imul
        53: aload_0
        54: invokevirtual #66                 // Method value:()Ljava/lang/String;
        57: invokestatic  #133                // Method scala/runtime/Statics.anyHash:(Ljava/lang/Object;)I
        60: iadd
        61: istore_1
        62: bipush        37
        64: iload_1
        65: imul
        66: aload_0
        67: invokevirtual #68                 // Method updated:()Lscala/Option;
        70: invokestatic  #133                // Method scala/runtime/Statics.anyHash:(Ljava/lang/Object;)I
        73: iadd
        74: istore_1
        75: bipush        37
        77: iload_1
        78: imul
        79: ireturn
      LineNumberTable:
        line 364: 0
      LocalVariableTable:
        Start  Length  Slot  Name   Signature
            9      70     1  code   I
            0      80     0  this   Lcoursier/core/SnapshotVersion;

  private scala.Tuple4<coursier.core.Classifier, coursier.core.Extension, java.lang.String, scala.Option<coursier.core.Versions$DateTime>> tuple();
    descriptor: ()Lscala/Tuple4;
    flags: (0x0002) ACC_PRIVATE
    Code:
      stack=6, locals=1, args_size=1
         0: new           #140                // class scala/Tuple4
         3: dup
         4: new           #89                 // class coursier/core/Classifier
         7: dup
         8: aload_0
         9: invokevirtual #75                 // Method classifier:()Ljava/lang/String;
        12: invokespecial #90                 // Method coursier/core/Classifier."<init>":(Ljava/lang/String;)V
        15: new           #104                // class coursier/core/Extension
        18: dup
        19: aload_0
        20: invokevirtual #64                 // Method extension:()Ljava/lang/String;
        23: invokespecial #105                // Method coursier/core/Extension."<init>":(Ljava/lang/String;)V
        26: aload_0
        27: invokevirtual #66                 // Method value:()Ljava/lang/String;
        30: aload_0
        31: invokevirtual #68                 // Method updated:()Lscala/Option;
        34: invokespecial #143                // Method scala/Tuple4."<init>":(Ljava/lang/Object;Ljava/lang/Object;Ljava/lang/Object;Ljava/lang/Object;)V
        37: areturn
      LineNumberTable:
        line 364: 0
      LocalVariableTable:
        Start  Length  Slot  Name   Signature
            0      38     0  this   Lcoursier/core/SnapshotVersion;
    Signature: #138                         // ()Lscala/Tuple4<Lcoursier/core/Classifier;Lcoursier/core/Extension;Ljava/lang/String;Lscala/Option<Lcoursier/core/Versions$DateTime;>;>;

  public java.lang.String productPrefix();
    descriptor: ()Ljava/lang/String;
    flags: (0x0001) ACC_PUBLIC
    Code:
      stack=1, locals=1, args_size=1
         0: ldc           #127                // String SnapshotVersion
         2: areturn
      LineNumberTable:
        line 364: 0
      LocalVariableTable:
        Start  Length  Slot  Name   Signature
            0       3     0  this   Lcoursier/core/SnapshotVersion;

  public int productArity();
    descriptor: ()I
    flags: (0x0001) ACC_PUBLIC
    Code:
      stack=1, locals=1, args_size=1
         0: iconst_4
         1: ireturn
      LineNumberTable:
        line 364: 0
      LocalVariableTable:
        Start  Length  Slot  Name   Signature
            0       2     0  this   Lcoursier/core/SnapshotVersion;

  public java.lang.Object productElement(int);
    descriptor: (I)Ljava/lang/Object;
    flags: (0x0001) ACC_PUBLIC
    Code:
      stack=3, locals=3, args_size=2
         0: iload_1
         1: istore_2
         2: iload_2
         3: tableswitch   { // 0 to 3
                       0: 32
                       1: 46
                       2: 60
                       3: 67
                 default: 74
            }
        32: new           #89                 // class coursier/core/Classifier
        35: dup
        36: aload_0
        37: invokevirtual #75                 // Method classifier:()Ljava/lang/String;
        40: invokespecial #90                 // Method coursier/core/Classifier."<init>":(Ljava/lang/String;)V
        43: goto          89
        46: new           #104                // class coursier/core/Extension
        49: dup
        50: aload_0
        51: invokevirtual #64                 // Method extension:()Ljava/lang/String;
        54: invokespecial #105                // Method coursier/core/Extension."<init>":(Ljava/lang/String;)V
        57: goto          89
        60: aload_0
        61: invokevirtual #66                 // Method value:()Ljava/lang/String;
        64: goto          89
        67: aload_0
        68: invokevirtual #68                 // Method updated:()Lscala/Option;
        71: goto          89
        74: new           #150                // class java/lang/IndexOutOfBoundsException
        77: dup
        78: iload_2
        79: invokestatic  #156                // Method scala/runtime/BoxesRunTime.boxToInteger:(I)Ljava/lang/Integer;
        82: invokevirtual #157                // Method java/lang/Object.toString:()Ljava/lang/String;
        85: invokespecial #158                // Method java/lang/IndexOutOfBoundsException."<init>":(Ljava/lang/String;)V
        88: athrow
        89: areturn
      StackMapTable: number_of_entries = 6
        frame_type = 252 /* append */
          offset_delta = 32
          locals = [ int ]
        frame_type = 13 /* same */
        frame_type = 13 /* same */
        frame_type = 6 /* same */
        frame_type = 6 /* same */
        frame_type = 78 /* same_locals_1_stack_item */
          stack = [ class java/lang/Object ]
      LineNumberTable:
        line 364: 0
      LocalVariableTable:
        Start  Length  Slot  Name   Signature
            0      90     0  this   Lcoursier/core/SnapshotVersion;
            0      90     1     n   I
    MethodParameters:
      Name                           Flags
      n                              final

  public java.lang.String productElementName(int);
    descriptor: (I)Ljava/lang/String;
    flags: (0x0001) ACC_PUBLIC
    Code:
      stack=3, locals=3, args_size=2
         0: iload_1
         1: istore_2
         2: iload_2
         3: tableswitch   { // 0 to 3
                       0: 32
                       1: 37
                       2: 42
                       3: 47
                 default: 52
            }
        32: ldc           #161                // String classifier
        34: goto          67
        37: ldc           #162                // String extension
        39: goto          67
        42: ldc           #163                // String value
        44: goto          67
        47: ldc           #164                // String updated
        49: goto          67
        52: new           #150                // class java/lang/IndexOutOfBoundsException
        55: dup
        56: iload_2
        57: invokestatic  #156                // Method scala/runtime/BoxesRunTime.boxToInteger:(I)Ljava/lang/Integer;
        60: invokevirtual #157                // Method java/lang/Object.toString:()Ljava/lang/String;
        63: invokespecial #158                // Method java/lang/IndexOutOfBoundsException."<init>":(Ljava/lang/String;)V
        66: athrow
        67: areturn
      StackMapTable: number_of_entries = 6
        frame_type = 252 /* append */
          offset_delta = 32
          locals = [ int ]
        frame_type = 4 /* same */
        frame_type = 4 /* same */
        frame_type = 4 /* same */
        frame_type = 4 /* same */
        frame_type = 78 /* same_locals_1_stack_item */
          stack = [ class java/lang/String ]
      LineNumberTable:
        line 364: 0
      LocalVariableTable:
        Start  Length  Slot  Name   Signature
            0      68     0  this   Lcoursier/core/SnapshotVersion;
            0      68     1     n   I
    MethodParameters:
      Name                           Flags
      n                              final

  public coursier.core.SnapshotVersion(java.lang.String, java.lang.String, java.lang.String, scala.Option<coursier.core.Versions$DateTime>);
    descriptor: (Ljava/lang/String;Ljava/lang/String;Ljava/lang/String;Lscala/Option;)V
    flags: (0x0001) ACC_PUBLIC
    Code:
      stack=2, locals=5, args_size=5
         0: aload_0
         1: aload_1
         2: putfield      #52                 // Field classifier:Ljava/lang/String;
         5: aload_0
         6: aload_2
         7: putfield      #54                 // Field extension:Ljava/lang/String;
        10: aload_0
        11: aload_3
        12: putfield      #56                 // Field value:Ljava/lang/String;
        15: aload_0
        16: aload         4
        18: putfield      #60                 // Field updated:Lscala/Option;
        21: aload_0
        22: invokespecial #168                // Method java/lang/Object."<init>":()V
        25: aload_0
        26: invokestatic  #172                // InterfaceMethod scala/Product.$init$:(Lscala/Product;)V
        29: return
      LineNumberTable:
        line 364: 0
        line 372: 21
        line 364: 29
      LocalVariableTable:
        Start  Length  Slot  Name   Signature
            0      30     0  this   Lcoursier/core/SnapshotVersion;
            0      30     1 classifier   Ljava/lang/String;
            0      30     2 extension   Ljava/lang/String;
            0      30     3 value   Ljava/lang/String;
            0      30     4 updated   Lscala/Option;
    Signature: #165                         // (Ljava/lang/String;Ljava/lang/String;Ljava/lang/String;Lscala/Option<Lcoursier/core/Versions$DateTime;>;)V
    MethodParameters:
      Name                           Flags
      classifier                     final
      extension                      final
      value                          final
      updated                        final
}
InnerClasses:
  public static final #17= #14 of #16;    // DateTime=class coursier/core/Versions$DateTime of class coursier/core/Versions
SourceFile: "Definitions.scala"
RuntimeVisibleAnnotations:
  0: #10(#11=s#12)
    scala.reflect.ScalaSignature(
      bytes="\u0006\u0005\u0005}c\u0001\u0002\u000f\u001e\u0005\tB\u0001\u0002\u000f\u0001\u0003\u0006\u0004%\t!\u000f\u0005\t}\u0001\u0011\t\u0011)A\u0005u!Aq\b\u0001BC\u0002\u0013\u0005\u0001\t\u0003\u0005E\u0001\t\u0005\t\u0015!\u0003B\u0011!)\u0005A!b\u0001\n\u00031\u0005\u0002C(\u0001\u0005\u0003\u0005\u000b\u0011B$\t\u0011A\u0003!Q1A\u0005\u0002EC\u0001\u0002\u0018\u0001\u0003\u0002\u0003\u0006IA\u0015\u0005\u0006;\u0002!\tA\u0018\u0005\u0006I\u0002!\t!\u001a\u0005\u0006O\u0002!\t\u0001\u001b\u0005\u0006U\u0002!\ta\u001b\u0005\u0006[\u0002!\tA\u001c\u0005\u0006a\u0002!\t%\u001d\u0005\u0006s\u0002!\tE\u001f\u0005\b\u0003\u000f\u0001A\u0011IA\u0005\u0011\u001d\ti\u0001\u0001C!\u0003\u001fAq!a\u0006\u0001\t\u0013\tI\u0002C\u0004\u0002\"\u0001!\t%a\t\t\u000f\u0005\u0015\u0002\u0001\"\u0011\u0002(!9\u0011\u0011\u0006\u0001\u0005B\u0005-\u0002bBA\u0019\u0001\u0011\u0005\u00131G\u0004\b\u0003oi\u0002\u0012AA\u001d\r\u0019aR\u0004#\u0001\u0002<!1Q\f\u0007C\u0001\u0003\u000fBq!!\u0013\u0019\t\u0003\tY\u0005C\u0005\u0002Va\t\t\u0011\"\u0003\u0002X\ty1K\\1qg\"|GOV3sg&|gN\u0003\u0002\u001f?\u0005!1m\u001c:f\u0015\u0005\u0001\u0013\u0001C2pkJ\u001c\u0018.\u001a:\u0004\u0001M!\u0001aI\u0015-!\t!s%D\u0001&\u0015\u00051\u0013!B:dC2\f\u0017B\u0001\u0015&\u0005\u0019\te.\u001f*fMB\u0011AEK\u0005\u0003W\u0015\u0012q\u0001\u0015:pIV\u001cG\u000f\u0005\u0002.k9\u0011af\r\b\u0003_Ij\u0011\u0001\r\u0006\u0003c\u0005\na\u0001\u0010:p_Rt\u0014\"\u0001\u0014\n\u0005Q*\u0013a\u00029bG.\fw-Z\u0005\u0003m]\u0012AbU3sS\u0006d\u0017N_1cY\u0016T!\u0001N\u0013\u0002\u0015\rd\u0017m]:jM&,\'/F\u0001;!\tYD(D\u0001\u001e\u0013\tiTD\u0001\u0006DY\u0006\u001c8/\u001b4jKJ\f1b\u00197bgNLg-[3sA\u0005IQ\r\u001f;f]NLwN\\\u000b\u0002\u0003B\u00111HQ\u0005\u0003\u0007v\u0011\u0011\"\u0012=uK:\u001c\u0018n\u001c8\u0002\u0015\u0015DH/\u001a8tS>t\u0007%A\u0003wC2,X-F\u0001H!\tAEJ\u0004\u0002J\u0015B\u0011q&J\u0005\u0003\u0017\u0016\na\u0001\u0015:fI\u00164\u0017BA\'O\u0005\u0019\u0019FO]5oO*\u00111*J\u0001\u0007m\u0006dW/\u001a\u0011\u0002\u000fU\u0004H-\u0019;fIV\t!\u000bE\u0002%\'VK!\u0001V\u0013\u0003\r=\u0003H/[8o!\t1\u0016L\u0004\u0002</&\u0011\u0001,H\u0001\t-\u0016\u00148/[8og&\u0011!l\u0017\u0002\t\t\u0006$X\rV5nK*\u0011\u0001,H\u0001\tkB$\u0017\r^3eA\u00051A(\u001b8jiz\"Ra\u00181bE\u000e\u0004\"a\u000f\u0001\t\u000baJ\u0001\u0019\u0001\u001e\t\u000b}J\u0001\u0019A!\t\u000b\u0015K\u0001\u0019A$\t\u000bAK\u0001\u0019\u0001*\u0002\u001d]LG\u000f[\"mCN\u001c\u0018NZ5feR\u0011qL\u001a\u0005\u0006q)\u0001\rAO\u0001\u000eo&$\b.\u0012=uK:\u001c\u0018n\u001c8\u0015\u0005}K\u0007\"B \f\u0001\u0004\t\u0015!C<ji\"4\u0016\r\\;f)\tyF\u000eC\u0003F\u0019\u0001\u0007q)A\u0006xSRDW\u000b\u001d3bi\u0016$GCA0p\u0011\u0015\u0001V\u00021\u0001S\u0003!!xn\u0015;sS:<G#\u0001:\u0011\u0005MDX\"\u0001;\u000b\u0005U4\u0018\u0001\u00027b]\u001eT\u0011a^\u0001\u0005U\u00064\u0018-\u0003\u0002Ni\u0006A1-\u00198FcV\fG\u000e\u0006\u0002|}B\u0011A\u0005`\u0005\u0003{\u0016\u0012qAQ8pY\u0016\fg\u000e\u0003\u0004\u0000\u001f\u0001\u0007\u0011\u0011A\u0001\u0004_\nT\u0007c\u0001\u0013\u0002\u0004%\u0019\u0011QA\u0013\u0003\u0007\u0005s\u00170\u0001\u0004fcV\fGn\u001d\u000b\u0004w\u0006-\u0001BB@\u0011\u0001\u0004\t\t!\u0001\u0005iCND7i\u001c3f)\t\t\t\u0002E\u0002%\u0003\'I1!!\u0006&\u0005\rIe\u000e^\u0001\u0006iV\u0004H.Z\u000b\u0003\u00037\u0001r\u0001JA\u000fu\u0005;%+C\u0002\u0002 \u0015\u0012a\u0001V;qY\u0016$\u0014!\u00049s_\u0012,8\r\u001e)sK\u001aL\u00070F\u0001s\u00031\u0001(o\u001c3vGR\f%/\u001b;z+\t\t\t\"\u0001\bqe>$Wo\u0019;FY\u0016lWM\u001c;\u0015\t\u0005\u0005\u0011Q\u0006\u0005\b\u0003_)\u0002\u0019AA\t\u0003\u0005q\u0017A\u00059s_\u0012,8\r^#mK6,g\u000e\u001e(b[\u0016$2A]A\u001b\u0011\u001d\tyC\u0006a\u0001\u0003#\tqb\u00158baNDw\u000e\u001e,feNLwN\u001c\t\u0003wa\u0019B\u0001G\u0012\u0002>A!\u0011qHA#\u001b\t\t\tEC\u0002\u0002DY\f!![8\n\u0007Y\n\t\u0005\u0006\u0002\u0002:\u0005)\u0011\r\u001d9msRIq,!\u0014\u0002P\u0005E\u00131\u000b\u0005\u0006qi\u0001\rA\u000f\u0005\u0006\u007fi\u0001\r!\u0011\u0005\u0006\u000bj\u0001\ra\u0012\u0005\u0006!j\u0001\rAU\u0001\roJLG/\u001a*fa2\f7-\u001a\u000b\u0003\u00033\u00022a]A.\u0013\r\ti\u0006\u001e\u0002\u0007\u001f\nTWm\u0019;"
    )
  ScalaInlineInfo: length = 0x68 (unknown attribute)
   01 01 00 14 00 45 00 46 01 00 70 00 71 01 00 12
   00 32 01 00 74 00 71 01 00 14 00 32 01 00 7C 00
   7D 01 00 91 00 7D 01 00 92 00 93 01 00 9F 00 A0
   01 00 2D 00 25 01 00 24 00 25 01 00 90 00 32 01
   00 50 00 32 01 00 88 00 89 01 00 16 00 39 01 00
   15 00 32 01 00 3D 00 3E 01 00 49 00 3E 01 00 4D
   00 4E 01 00 4C 00 3E 01
  ScalaSig: length = 0x3 (unknown attribute)
   05 02 00
