Classfile /Users/mw/Projects/slang-braindump/.jar/jar11/assemble/slang-braindump/assemble/content/coursier/core/Versions$DateTime.class
  Last modified May 29, 2022; size 6783 bytes
  SHA-256 checksum 946a9435f65ac9e29c676a1361e484510c80a9e4cc1a3e7e1ff15ca738ea2045
  Compiled from "Versions.scala"
public final class coursier.core.Versions$DateTime extends java.lang.Object implements scala.math.Ordered<coursier.core.Versions$DateTime>, scala.Product, java.io.Serializable
  minor version: 0
  major version: 52
  flags: (0x0031) ACC_PUBLIC, ACC_FINAL, ACC_SUPER
  this_class: #2                          // coursier/core/Versions$DateTime
  super_class: #5                         // java/lang/Object
  interfaces: 3, fields: 6, methods: 31, attributes: 5
Constant pool:
    #1 = Utf8               coursier/core/Versions$DateTime
    #2 = Class              #1            // coursier/core/Versions$DateTime
    #3 = Utf8               Ljava/lang/Object;Lscala/math/Ordered<Lcoursier/core/Versions$DateTime;>;Lscala/Product;Ljava/io/Serializable;
    #4 = Utf8               java/lang/Object
    #5 = Class              #4            // java/lang/Object
    #6 = Utf8               scala/math/Ordered
    #7 = Class              #6            // scala/math/Ordered
    #8 = Utf8               scala/Product
    #9 = Class              #8            // scala/Product
   #10 = Utf8               java/io/Serializable
   #11 = Class              #10           // java/io/Serializable
   #12 = Utf8               Versions.scala
   #13 = Utf8               coursier/core/Versions
   #14 = Class              #13           // coursier/core/Versions
   #15 = Utf8               DateTime
   #16 = Utf8               scala/math/Ordering$Implicits$
   #17 = Class              #16           // scala/math/Ordering$Implicits$
   #18 = Utf8               scala/math/Ordering
   #19 = Class              #18           // scala/math/Ordering
   #20 = Utf8
   #21 = Utf8               scala/math/Ordering$Int$
   #22 = Class              #21           // scala/math/Ordering$Int$
   #23 = Utf8               scala/math/Ordering$OrderingOps
   #24 = Class              #23           // scala/math/Ordering$OrderingOps
   #25 = Utf8               OrderingOps
   #26 = Utf8               year
   #27 = Utf8               I
   #28 = Utf8               month
   #29 = Utf8               day
   #30 = Utf8               hour
   #31 = Utf8               minute
   #32 = Utf8               second
   #33 = Utf8               productIterator
   #34 = Utf8               ()Lscala/collection/Iterator;
   #35 = Utf8               ()Lscala/collection/Iterator<Ljava/lang/Object;>;
   #36 = Utf8               productIterator$
   #37 = Utf8               (Lscala/Product;)Lscala/collection/Iterator;
   #38 = NameAndType        #36:#37       // productIterator$:(Lscala/Product;)Lscala/collection/Iterator;
   #39 = InterfaceMethodref #9.#38        // scala/Product.productIterator$:(Lscala/Product;)Lscala/collection/Iterator;
   #40 = Utf8               this
   #41 = Utf8               Lcoursier/core/Versions$DateTime;
   #42 = Utf8               productElementNames
   #43 = Utf8               ()Lscala/collection/Iterator<Ljava/lang/String;>;
   #44 = Utf8               productElementNames$
   #45 = NameAndType        #44:#37       // productElementNames$:(Lscala/Product;)Lscala/collection/Iterator;
   #46 = InterfaceMethodref #9.#45        // scala/Product.productElementNames$:(Lscala/Product;)Lscala/collection/Iterator;
   #47 = Utf8               $less
   #48 = Utf8               (Ljava/lang/Object;)Z
   #49 = Utf8               that
   #50 = Utf8               $less$
   #51 = Utf8               (Lscala/math/Ordered;Ljava/lang/Object;)Z
   #52 = NameAndType        #50:#51       // $less$:(Lscala/math/Ordered;Ljava/lang/Object;)Z
   #53 = InterfaceMethodref #7.#52        // scala/math/Ordered.$less$:(Lscala/math/Ordered;Ljava/lang/Object;)Z
   #54 = Utf8               Ljava/lang/Object;
   #55 = Utf8               $greater
   #56 = Utf8               $greater$
   #57 = NameAndType        #56:#51       // $greater$:(Lscala/math/Ordered;Ljava/lang/Object;)Z
   #58 = InterfaceMethodref #7.#57        // scala/math/Ordered.$greater$:(Lscala/math/Ordered;Ljava/lang/Object;)Z
   #59 = Utf8               $less$eq
   #60 = Utf8               $less$eq$
   #61 = NameAndType        #60:#51       // $less$eq$:(Lscala/math/Ordered;Ljava/lang/Object;)Z
   #62 = InterfaceMethodref #7.#61        // scala/math/Ordered.$less$eq$:(Lscala/math/Ordered;Ljava/lang/Object;)Z
   #63 = Utf8               $greater$eq
   #64 = Utf8               $greater$eq$
   #65 = NameAndType        #64:#51       // $greater$eq$:(Lscala/math/Ordered;Ljava/lang/Object;)Z
   #66 = InterfaceMethodref #7.#65        // scala/math/Ordered.$greater$eq$:(Lscala/math/Ordered;Ljava/lang/Object;)Z
   #67 = Utf8               compareTo
   #68 = Utf8               (Ljava/lang/Object;)I
   #69 = Utf8               compareTo$
   #70 = Utf8               (Lscala/math/Ordered;Ljava/lang/Object;)I
   #71 = NameAndType        #69:#70       // compareTo$:(Lscala/math/Ordered;Ljava/lang/Object;)I
   #72 = InterfaceMethodref #7.#71        // scala/math/Ordered.compareTo$:(Lscala/math/Ordered;Ljava/lang/Object;)I
   #73 = Utf8               ()I
   #74 = NameAndType        #26:#27       // year:I
   #75 = Fieldref           #2.#74        // coursier/core/Versions$DateTime.year:I
   #76 = NameAndType        #28:#27       // month:I
   #77 = Fieldref           #2.#76        // coursier/core/Versions$DateTime.month:I
   #78 = NameAndType        #29:#27       // day:I
   #79 = Fieldref           #2.#78        // coursier/core/Versions$DateTime.day:I
   #80 = NameAndType        #30:#27       // hour:I
   #81 = Fieldref           #2.#80        // coursier/core/Versions$DateTime.hour:I
   #82 = NameAndType        #31:#27       // minute:I
   #83 = Fieldref           #2.#82        // coursier/core/Versions$DateTime.minute:I
   #84 = NameAndType        #32:#27       // second:I
   #85 = Fieldref           #2.#84        // coursier/core/Versions$DateTime.second:I
   #86 = Utf8               compare
   #87 = Utf8               (Lcoursier/core/Versions$DateTime;)I
   #88 = Utf8               other
   #89 = Utf8               equals
   #90 = NameAndType        #89:#48       // equals:(Ljava/lang/Object;)Z
   #91 = Methodref          #5.#90        // java/lang/Object.equals:(Ljava/lang/Object;)Z
   #92 = Utf8               MODULE$
   #93 = Utf8               Lscala/math/Ordering$Implicits$;
   #94 = NameAndType        #92:#93       // MODULE$:Lscala/math/Ordering$Implicits$;
   #95 = Fieldref           #17.#94       // scala/math/Ordering$Implicits$.MODULE$:Lscala/math/Ordering$Implicits$;
   #96 = Utf8               tuple
   #97 = Utf8               ()Lscala/Tuple6;
   #98 = NameAndType        #96:#97       // tuple:()Lscala/Tuple6;
   #99 = Methodref          #2.#98        // coursier/core/Versions$DateTime.tuple:()Lscala/Tuple6;
  #100 = Utf8               scala/math/Ordering$
  #101 = Class              #100          // scala/math/Ordering$
  #102 = Utf8               Lscala/math/Ordering$;
  #103 = NameAndType        #92:#102      // MODULE$:Lscala/math/Ordering$;
  #104 = Fieldref           #101.#103     // scala/math/Ordering$.MODULE$:Lscala/math/Ordering$;
  #105 = Utf8               Lscala/math/Ordering$Int$;
  #106 = NameAndType        #92:#105      // MODULE$:Lscala/math/Ordering$Int$;
  #107 = Fieldref           #22.#106      // scala/math/Ordering$Int$.MODULE$:Lscala/math/Ordering$Int$;
  #108 = Utf8               Tuple6
  #109 = Utf8               (Lscala/math/Ordering;Lscala/math/Ordering;Lscala/math/Ordering;Lscala/math/Ordering;Lscala/math/Ordering;Lscala/math/Ordering;)Lscala/math/Ordering;
  #110 = NameAndType        #108:#109     // Tuple6:(Lscala/math/Ordering;Lscala/math/Ordering;Lscala/math/Ordering;Lscala/math/Ordering;Lscala/math/Ordering;Lscala/math/Ordering;)Lscala/math/Ordering;
  #111 = Methodref          #101.#110     // scala/math/Ordering$.Tuple6:(Lscala/math/Ordering;Lscala/math/Ordering;Lscala/math/Ordering;Lscala/math/Ordering;Lscala/math/Ordering;Lscala/math/Ordering;)Lscala/math/Ordering;
  #112 = Utf8               infixOrderingOps
  #113 = Utf8               (Ljava/lang/Object;Lscala/math/Ordering;)Lscala/math/Ordering$OrderingOps;
  #114 = NameAndType        #112:#113     // infixOrderingOps:(Ljava/lang/Object;Lscala/math/Ordering;)Lscala/math/Ordering$OrderingOps;
  #115 = Methodref          #17.#114      // scala/math/Ordering$Implicits$.infixOrderingOps:(Ljava/lang/Object;Lscala/math/Ordering;)Lscala/math/Ordering$OrderingOps;
  #116 = NameAndType        #47:#48       // $less:(Ljava/lang/Object;)Z
  #117 = Methodref          #24.#116      // scala/math/Ordering$OrderingOps.$less:(Ljava/lang/Object;)Z
  #118 = Utf8               withYear
  #119 = Utf8               (I)Lcoursier/core/Versions$DateTime;
  #120 = NameAndType        #28:#73       // month:()I
  #121 = Methodref          #2.#120       // coursier/core/Versions$DateTime.month:()I
  #122 = NameAndType        #29:#73       // day:()I
  #123 = Methodref          #2.#122       // coursier/core/Versions$DateTime.day:()I
  #124 = NameAndType        #30:#73       // hour:()I
  #125 = Methodref          #2.#124       // coursier/core/Versions$DateTime.hour:()I
  #126 = NameAndType        #31:#73       // minute:()I
  #127 = Methodref          #2.#126       // coursier/core/Versions$DateTime.minute:()I
  #128 = NameAndType        #32:#73       // second:()I
  #129 = Methodref          #2.#128       // coursier/core/Versions$DateTime.second:()I
  #130 = Utf8               <init>
  #131 = Utf8               (IIIIII)V
  #132 = NameAndType        #130:#131     // "<init>":(IIIIII)V
  #133 = Methodref          #2.#132       // coursier/core/Versions$DateTime."<init>":(IIIIII)V
  #134 = Utf8               withMonth
  #135 = NameAndType        #26:#73       // year:()I
  #136 = Methodref          #2.#135       // coursier/core/Versions$DateTime.year:()I
  #137 = Utf8               withDay
  #138 = Utf8               withHour
  #139 = Utf8               withMinute
  #140 = Utf8               withSecond
  #141 = Utf8               toString
  #142 = Utf8               ()Ljava/lang/String;
  #143 = Utf8               java/lang/StringBuilder
  #144 = Class              #143          // java/lang/StringBuilder
  #145 = Utf8               DateTime(
  #146 = String             #145          // DateTime(
  #147 = Utf8               (Ljava/lang/String;)V
  #148 = NameAndType        #130:#147     // "<init>":(Ljava/lang/String;)V
  #149 = Methodref          #144.#148     // java/lang/StringBuilder."<init>":(Ljava/lang/String;)V
  #150 = Utf8               java/lang/String
  #151 = Class              #150          // java/lang/String
  #152 = Utf8               valueOf
  #153 = Utf8               (I)Ljava/lang/String;
  #154 = NameAndType        #152:#153     // valueOf:(I)Ljava/lang/String;
  #155 = Methodref          #151.#154     // java/lang/String.valueOf:(I)Ljava/lang/String;
  #156 = Utf8               append
  #157 = Utf8               (Ljava/lang/String;)Ljava/lang/StringBuilder;
  #158 = NameAndType        #156:#157     // append:(Ljava/lang/String;)Ljava/lang/StringBuilder;
  #159 = Methodref          #144.#158     // java/lang/StringBuilder.append:(Ljava/lang/String;)Ljava/lang/StringBuilder;
  #160 = Utf8               ,
  #161 = String             #160          // ,
  #162 = Utf8               )
  #163 = String             #162          // )
  #164 = NameAndType        #141:#142     // toString:()Ljava/lang/String;
  #165 = Methodref          #144.#164     // java/lang/StringBuilder.toString:()Ljava/lang/String;
  #166 = Utf8               b
  #167 = Utf8               Ljava/lang/StringBuilder;
  #168 = Utf8               canEqual
  #169 = Utf8               obj
  #170 = NameAndType        #168:#48      // canEqual:(Ljava/lang/Object;)Z
  #171 = Methodref          #2.#170       // coursier/core/Versions$DateTime.canEqual:(Ljava/lang/Object;)Z
  #172 = Utf8               hashCode
  #173 = String             #15           // DateTime
  #174 = Utf8               scala/runtime/Statics
  #175 = Class              #174          // scala/runtime/Statics
  #176 = Utf8               anyHash
  #177 = NameAndType        #176:#68      // anyHash:(Ljava/lang/Object;)I
  #178 = Methodref          #175.#177     // scala/runtime/Statics.anyHash:(Ljava/lang/Object;)I
  #179 = Utf8               code
  #180 = Utf8               ()Lscala/Tuple6<Ljava/lang/Object;Ljava/lang/Object;Ljava/lang/Object;Ljava/lang/Object;Ljava/lang/Object;Ljava/lang/Object;>;
  #181 = Utf8               scala/Tuple6
  #182 = Class              #181          // scala/Tuple6
  #183 = Utf8               scala/runtime/BoxesRunTime
  #184 = Class              #183          // scala/runtime/BoxesRunTime
  #185 = Utf8               boxToInteger
  #186 = Utf8               (I)Ljava/lang/Integer;
  #187 = NameAndType        #185:#186     // boxToInteger:(I)Ljava/lang/Integer;
  #188 = Methodref          #184.#187     // scala/runtime/BoxesRunTime.boxToInteger:(I)Ljava/lang/Integer;
  #189 = Utf8               (Ljava/lang/Object;Ljava/lang/Object;Ljava/lang/Object;Ljava/lang/Object;Ljava/lang/Object;Ljava/lang/Object;)V
  #190 = NameAndType        #130:#189     // "<init>":(Ljava/lang/Object;Ljava/lang/Object;Ljava/lang/Object;Ljava/lang/Object;Ljava/lang/Object;Ljava/lang/Object;)V
  #191 = Methodref          #182.#190     // scala/Tuple6."<init>":(Ljava/lang/Object;Ljava/lang/Object;Ljava/lang/Object;Ljava/lang/Object;Ljava/lang/Object;Ljava/lang/Object;)V
  #192 = Utf8               productPrefix
  #193 = Utf8               productArity
  #194 = Utf8               productElement
  #195 = Utf8               (I)Ljava/lang/Object;
  #196 = Utf8               n
  #197 = Utf8               java/lang/IndexOutOfBoundsException
  #198 = Class              #197          // java/lang/IndexOutOfBoundsException
  #199 = Methodref          #5.#164       // java/lang/Object.toString:()Ljava/lang/String;
  #200 = Methodref          #198.#148     // java/lang/IndexOutOfBoundsException."<init>":(Ljava/lang/String;)V
  #201 = Utf8               java/lang/Integer
  #202 = Class              #201          // java/lang/Integer
  #203 = Utf8               productElementName
  #204 = String             #26           // year
  #205 = String             #28           // month
  #206 = String             #29           // day
  #207 = String             #30           // hour
  #208 = String             #31           // minute
  #209 = String             #32           // second
  #210 = NameAndType        #86:#87       // compare:(Lcoursier/core/Versions$DateTime;)I
  #211 = Methodref          #2.#210       // coursier/core/Versions$DateTime.compare:(Lcoursier/core/Versions$DateTime;)I
  #212 = Utf8               ()V
  #213 = NameAndType        #130:#212     // "<init>":()V
  #214 = Methodref          #5.#213       // java/lang/Object."<init>":()V
  #215 = Utf8               $init$
  #216 = Utf8               (Lscala/math/Ordered;)V
  #217 = NameAndType        #215:#216     // $init$:(Lscala/math/Ordered;)V
  #218 = InterfaceMethodref #7.#217       // scala/math/Ordered.$init$:(Lscala/math/Ordered;)V
  #219 = Utf8               (Lscala/Product;)V
  #220 = NameAndType        #215:#219     // $init$:(Lscala/Product;)V
  #221 = InterfaceMethodref #9.#220       // scala/Product.$init$:(Lscala/Product;)V
  #222 = Utf8               Code
  #223 = Utf8               LineNumberTable
  #224 = Utf8               LocalVariableTable
  #225 = Utf8               Signature
  #226 = Utf8               MethodParameters
  #227 = Utf8               StackMapTable
  #228 = Utf8               InnerClasses
  #229 = Utf8               SourceFile
  #230 = Utf8               ScalaInlineInfo
  #231 = Utf8               Scala
{
  private final int year;
    descriptor: I
    flags: (0x0012) ACC_PRIVATE, ACC_FINAL

  private final int month;
    descriptor: I
    flags: (0x0012) ACC_PRIVATE, ACC_FINAL

  private final int day;
    descriptor: I
    flags: (0x0012) ACC_PRIVATE, ACC_FINAL

  private final int hour;
    descriptor: I
    flags: (0x0012) ACC_PRIVATE, ACC_FINAL

  private final int minute;
    descriptor: I
    flags: (0x0012) ACC_PRIVATE, ACC_FINAL

  private final int second;
    descriptor: I
    flags: (0x0012) ACC_PRIVATE, ACC_FINAL

  public scala.collection.Iterator<java.lang.Object> productIterator();
    descriptor: ()Lscala/collection/Iterator;
    flags: (0x0001) ACC_PUBLIC
    Code:
      stack=1, locals=1, args_size=1
         0: aload_0
         1: invokestatic  #39                 // InterfaceMethod scala/Product.productIterator$:(Lscala/Product;)Lscala/collection/Iterator;
         4: areturn
      LineNumberTable:
        line 105: 0
      LocalVariableTable:
        Start  Length  Slot  Name   Signature
            0       5     0  this   Lcoursier/core/Versions$DateTime;
    Signature: #35                          // ()Lscala/collection/Iterator<Ljava/lang/Object;>;

  public scala.collection.Iterator<java.lang.String> productElementNames();
    descriptor: ()Lscala/collection/Iterator;
    flags: (0x0001) ACC_PUBLIC
    Code:
      stack=1, locals=1, args_size=1
         0: aload_0
         1: invokestatic  #46                 // InterfaceMethod scala/Product.productElementNames$:(Lscala/Product;)Lscala/collection/Iterator;
         4: areturn
      LineNumberTable:
        line 105: 0
      LocalVariableTable:
        Start  Length  Slot  Name   Signature
            0       5     0  this   Lcoursier/core/Versions$DateTime;
    Signature: #43                          // ()Lscala/collection/Iterator<Ljava/lang/String;>;

  public boolean $less(java.lang.Object);
    descriptor: (Ljava/lang/Object;)Z
    flags: (0x0001) ACC_PUBLIC
    Code:
      stack=2, locals=2, args_size=2
         0: aload_0
         1: aload_1
         2: invokestatic  #53                 // InterfaceMethod scala/math/Ordered.$less$:(Lscala/math/Ordered;Ljava/lang/Object;)Z
         5: ireturn
      LineNumberTable:
        line 105: 0
      LocalVariableTable:
        Start  Length  Slot  Name   Signature
            0       6     0  this   Lcoursier/core/Versions$DateTime;
            0       6     1  that   Ljava/lang/Object;
    MethodParameters:
      Name                           Flags
      that                           final

  public boolean $greater(java.lang.Object);
    descriptor: (Ljava/lang/Object;)Z
    flags: (0x0001) ACC_PUBLIC
    Code:
      stack=2, locals=2, args_size=2
         0: aload_0
         1: aload_1
         2: invokestatic  #58                 // InterfaceMethod scala/math/Ordered.$greater$:(Lscala/math/Ordered;Ljava/lang/Object;)Z
         5: ireturn
      LineNumberTable:
        line 105: 0
      LocalVariableTable:
        Start  Length  Slot  Name   Signature
            0       6     0  this   Lcoursier/core/Versions$DateTime;
            0       6     1  that   Ljava/lang/Object;
    MethodParameters:
      Name                           Flags
      that                           final

  public boolean $less$eq(java.lang.Object);
    descriptor: (Ljava/lang/Object;)Z
    flags: (0x0001) ACC_PUBLIC
    Code:
      stack=2, locals=2, args_size=2
         0: aload_0
         1: aload_1
         2: invokestatic  #62                 // InterfaceMethod scala/math/Ordered.$less$eq$:(Lscala/math/Ordered;Ljava/lang/Object;)Z
         5: ireturn
      LineNumberTable:
        line 105: 0
      LocalVariableTable:
        Start  Length  Slot  Name   Signature
            0       6     0  this   Lcoursier/core/Versions$DateTime;
            0       6     1  that   Ljava/lang/Object;
    MethodParameters:
      Name                           Flags
      that                           final

  public boolean $greater$eq(java.lang.Object);
    descriptor: (Ljava/lang/Object;)Z
    flags: (0x0001) ACC_PUBLIC
    Code:
      stack=2, locals=2, args_size=2
         0: aload_0
         1: aload_1
         2: invokestatic  #66                 // InterfaceMethod scala/math/Ordered.$greater$eq$:(Lscala/math/Ordered;Ljava/lang/Object;)Z
         5: ireturn
      LineNumberTable:
        line 105: 0
      LocalVariableTable:
        Start  Length  Slot  Name   Signature
            0       6     0  this   Lcoursier/core/Versions$DateTime;
            0       6     1  that   Ljava/lang/Object;
    MethodParameters:
      Name                           Flags
      that                           final

  public int compareTo(java.lang.Object);
    descriptor: (Ljava/lang/Object;)I
    flags: (0x0001) ACC_PUBLIC
    Code:
      stack=2, locals=2, args_size=2
         0: aload_0
         1: aload_1
         2: invokestatic  #72                 // InterfaceMethod scala/math/Ordered.compareTo$:(Lscala/math/Ordered;Ljava/lang/Object;)I
         5: ireturn
      LineNumberTable:
        line 105: 0
      LocalVariableTable:
        Start  Length  Slot  Name   Signature
            0       6     0  this   Lcoursier/core/Versions$DateTime;
            0       6     1  that   Ljava/lang/Object;
    MethodParameters:
      Name                           Flags
      that                           final

  public int year();
    descriptor: ()I
    flags: (0x0001) ACC_PUBLIC
    Code:
      stack=1, locals=1, args_size=1
         0: aload_0
         1: getfield      #75                 // Field year:I
         4: ireturn
      LineNumberTable:
        line 105: 0
      LocalVariableTable:
        Start  Length  Slot  Name   Signature
            0       5     0  this   Lcoursier/core/Versions$DateTime;

  public int month();
    descriptor: ()I
    flags: (0x0001) ACC_PUBLIC
    Code:
      stack=1, locals=1, args_size=1
         0: aload_0
         1: getfield      #77                 // Field month:I
         4: ireturn
      LineNumberTable:
        line 105: 0
      LocalVariableTable:
        Start  Length  Slot  Name   Signature
            0       5     0  this   Lcoursier/core/Versions$DateTime;

  public int day();
    descriptor: ()I
    flags: (0x0001) ACC_PUBLIC
    Code:
      stack=1, locals=1, args_size=1
         0: aload_0
         1: getfield      #79                 // Field day:I
         4: ireturn
      LineNumberTable:
        line 105: 0
      LocalVariableTable:
        Start  Length  Slot  Name   Signature
            0       5     0  this   Lcoursier/core/Versions$DateTime;

  public int hour();
    descriptor: ()I
    flags: (0x0001) ACC_PUBLIC
    Code:
      stack=1, locals=1, args_size=1
         0: aload_0
         1: getfield      #81                 // Field hour:I
         4: ireturn
      LineNumberTable:
        line 105: 0
      LocalVariableTable:
        Start  Length  Slot  Name   Signature
            0       5     0  this   Lcoursier/core/Versions$DateTime;

  public int minute();
    descriptor: ()I
    flags: (0x0001) ACC_PUBLIC
    Code:
      stack=1, locals=1, args_size=1
         0: aload_0
         1: getfield      #83                 // Field minute:I
         4: ireturn
      LineNumberTable:
        line 105: 0
      LocalVariableTable:
        Start  Length  Slot  Name   Signature
            0       5     0  this   Lcoursier/core/Versions$DateTime;

  public int second();
    descriptor: ()I
    flags: (0x0001) ACC_PUBLIC
    Code:
      stack=1, locals=1, args_size=1
         0: aload_0
         1: getfield      #85                 // Field second:I
         4: ireturn
      LineNumberTable:
        line 105: 0
      LocalVariableTable:
        Start  Length  Slot  Name   Signature
            0       5     0  this   Lcoursier/core/Versions$DateTime;

  public int compare(coursier.core.Versions$DateTime);
    descriptor: (Lcoursier/core/Versions$DateTime;)I
    flags: (0x0001) ACC_PUBLIC
    Code:
      stack=9, locals=3, args_size=2
         0: aload_0
         1: aload_1
         2: astore_2
         3: dup
         4: ifnonnull     15
         7: pop
         8: aload_2
         9: ifnull        22
        12: goto          26
        15: aload_2
        16: invokevirtual #91                 // Method java/lang/Object.equals:(Ljava/lang/Object;)Z
        19: ifeq          26
        22: iconst_0
        23: goto          75
        26: getstatic     #95                 // Field scala/math/Ordering$Implicits$.MODULE$:Lscala/math/Ordering$Implicits$;
        29: aload_0
        30: invokespecial #99                 // Method tuple:()Lscala/Tuple6;
        33: getstatic     #104                // Field scala/math/Ordering$.MODULE$:Lscala/math/Ordering$;
        36: getstatic     #107                // Field scala/math/Ordering$Int$.MODULE$:Lscala/math/Ordering$Int$;
        39: getstatic     #107                // Field scala/math/Ordering$Int$.MODULE$:Lscala/math/Ordering$Int$;
        42: getstatic     #107                // Field scala/math/Ordering$Int$.MODULE$:Lscala/math/Ordering$Int$;
        45: getstatic     #107                // Field scala/math/Ordering$Int$.MODULE$:Lscala/math/Ordering$Int$;
        48: getstatic     #107                // Field scala/math/Ordering$Int$.MODULE$:Lscala/math/Ordering$Int$;
        51: getstatic     #107                // Field scala/math/Ordering$Int$.MODULE$:Lscala/math/Ordering$Int$;
        54: invokevirtual #111                // Method scala/math/Ordering$.Tuple6:(Lscala/math/Ordering;Lscala/math/Ordering;Lscala/math/Ordering;Lscala/math/Ordering;Lscala/math/Ordering;Lscala/math/Ordering;)Lscala/math/Ordering;
        57: invokevirtual #115                // Method scala/math/Ordering$Implicits$.infixOrderingOps:(Ljava/lang/Object;Lscala/math/Ordering;)Lscala/math/Ordering$OrderingOps;
        60: aload_1
        61: invokespecial #99                 // Method tuple:()Lscala/Tuple6;
        64: invokevirtual #117                // Method scala/math/Ordering$OrderingOps.$less:(Ljava/lang/Object;)Z
        67: ifeq          74
        70: iconst_m1
        71: goto          75
        74: iconst_1
        75: ireturn
      StackMapTable: number_of_entries = 5
        frame_type = 255 /* full_frame */
          offset_delta = 15
          locals = [ class coursier/core/Versions$DateTime, class coursier/core/Versions$DateTime, class coursier/core/Versions$DateTime ]
          stack = [ class coursier/core/Versions$DateTime ]
        frame_type = 6 /* same */
        frame_type = 3 /* same */
        frame_type = 47 /* same */
        frame_type = 64 /* same_locals_1_stack_item */
          stack = [ int ]
      LineNumberTable:
        line 115: 0
        line 116: 26
        line 117: 74
      LocalVariableTable:
        Start  Length  Slot  Name   Signature
            0      76     0  this   Lcoursier/core/Versions$DateTime;
            0      76     1 other   Lcoursier/core/Versions$DateTime;
    MethodParameters:
      Name                           Flags
      other                          final

  public coursier.core.Versions$DateTime withYear(int);
    descriptor: (I)Lcoursier/core/Versions$DateTime;
    flags: (0x0001) ACC_PUBLIC
    Code:
      stack=8, locals=2, args_size=2
         0: new           #2                  // class coursier/core/Versions$DateTime
         3: dup
         4: iload_1
         5: aload_0
         6: invokevirtual #121                // Method month:()I
         9: aload_0
        10: invokevirtual #123                // Method day:()I
        13: aload_0
        14: invokevirtual #125                // Method hour:()I
        17: aload_0
        18: invokevirtual #127                // Method minute:()I
        21: aload_0
        22: invokevirtual #129                // Method second:()I
        25: invokespecial #133                // Method "<init>":(IIIIII)V
        28: areturn
      LineNumberTable:
        line 105: 0
      LocalVariableTable:
        Start  Length  Slot  Name   Signature
            0      29     0  this   Lcoursier/core/Versions$DateTime;
            0      29     1  year   I
    MethodParameters:
      Name                           Flags
      year                           final

  public coursier.core.Versions$DateTime withMonth(int);
    descriptor: (I)Lcoursier/core/Versions$DateTime;
    flags: (0x0001) ACC_PUBLIC
    Code:
      stack=8, locals=2, args_size=2
         0: new           #2                  // class coursier/core/Versions$DateTime
         3: dup
         4: aload_0
         5: invokevirtual #136                // Method year:()I
         8: iload_1
         9: aload_0
        10: invokevirtual #123                // Method day:()I
        13: aload_0
        14: invokevirtual #125                // Method hour:()I
        17: aload_0
        18: invokevirtual #127                // Method minute:()I
        21: aload_0
        22: invokevirtual #129                // Method second:()I
        25: invokespecial #133                // Method "<init>":(IIIIII)V
        28: areturn
      LineNumberTable:
        line 105: 0
      LocalVariableTable:
        Start  Length  Slot  Name   Signature
            0      29     0  this   Lcoursier/core/Versions$DateTime;
            0      29     1 month   I
    MethodParameters:
      Name                           Flags
      month                          final

  public coursier.core.Versions$DateTime withDay(int);
    descriptor: (I)Lcoursier/core/Versions$DateTime;
    flags: (0x0001) ACC_PUBLIC
    Code:
      stack=8, locals=2, args_size=2
         0: new           #2                  // class coursier/core/Versions$DateTime
         3: dup
         4: aload_0
         5: invokevirtual #136                // Method year:()I
         8: aload_0
         9: invokevirtual #121                // Method month:()I
        12: iload_1
        13: aload_0
        14: invokevirtual #125                // Method hour:()I
        17: aload_0
        18: invokevirtual #127                // Method minute:()I
        21: aload_0
        22: invokevirtual #129                // Method second:()I
        25: invokespecial #133                // Method "<init>":(IIIIII)V
        28: areturn
      LineNumberTable:
        line 105: 0
      LocalVariableTable:
        Start  Length  Slot  Name   Signature
            0      29     0  this   Lcoursier/core/Versions$DateTime;
            0      29     1   day   I
    MethodParameters:
      Name                           Flags
      day                            final

  public coursier.core.Versions$DateTime withHour(int);
    descriptor: (I)Lcoursier/core/Versions$DateTime;
    flags: (0x0001) ACC_PUBLIC
    Code:
      stack=8, locals=2, args_size=2
         0: new           #2                  // class coursier/core/Versions$DateTime
         3: dup
         4: aload_0
         5: invokevirtual #136                // Method year:()I
         8: aload_0
         9: invokevirtual #121                // Method month:()I
        12: aload_0
        13: invokevirtual #123                // Method day:()I
        16: iload_1
        17: aload_0
        18: invokevirtual #127                // Method minute:()I
        21: aload_0
        22: invokevirtual #129                // Method second:()I
        25: invokespecial #133                // Method "<init>":(IIIIII)V
        28: areturn
      LineNumberTable:
        line 105: 0
      LocalVariableTable:
        Start  Length  Slot  Name   Signature
            0      29     0  this   Lcoursier/core/Versions$DateTime;
            0      29     1  hour   I
    MethodParameters:
      Name                           Flags
      hour                           final

  public coursier.core.Versions$DateTime withMinute(int);
    descriptor: (I)Lcoursier/core/Versions$DateTime;
    flags: (0x0001) ACC_PUBLIC
    Code:
      stack=8, locals=2, args_size=2
         0: new           #2                  // class coursier/core/Versions$DateTime
         3: dup
         4: aload_0
         5: invokevirtual #136                // Method year:()I
         8: aload_0
         9: invokevirtual #121                // Method month:()I
        12: aload_0
        13: invokevirtual #123                // Method day:()I
        16: aload_0
        17: invokevirtual #125                // Method hour:()I
        20: iload_1
        21: aload_0
        22: invokevirtual #129                // Method second:()I
        25: invokespecial #133                // Method "<init>":(IIIIII)V
        28: areturn
      LineNumberTable:
        line 105: 0
      LocalVariableTable:
        Start  Length  Slot  Name   Signature
            0      29     0  this   Lcoursier/core/Versions$DateTime;
            0      29     1 minute   I
    MethodParameters:
      Name                           Flags
      minute                         final

  public coursier.core.Versions$DateTime withSecond(int);
    descriptor: (I)Lcoursier/core/Versions$DateTime;
    flags: (0x0001) ACC_PUBLIC
    Code:
      stack=8, locals=2, args_size=2
         0: new           #2                  // class coursier/core/Versions$DateTime
         3: dup
         4: aload_0
         5: invokevirtual #136                // Method year:()I
         8: aload_0
         9: invokevirtual #121                // Method month:()I
        12: aload_0
        13: invokevirtual #123                // Method day:()I
        16: aload_0
        17: invokevirtual #125                // Method hour:()I
        20: aload_0
        21: invokevirtual #127                // Method minute:()I
        24: iload_1
        25: invokespecial #133                // Method "<init>":(IIIIII)V
        28: areturn
      LineNumberTable:
        line 105: 0
      LocalVariableTable:
        Start  Length  Slot  Name   Signature
            0      29     0  this   Lcoursier/core/Versions$DateTime;
            0      29     1 second   I
    MethodParameters:
      Name                           Flags
      second                         final

  public java.lang.String toString();
    descriptor: ()Ljava/lang/String;
    flags: (0x0001) ACC_PUBLIC
    Code:
      stack=3, locals=2, args_size=1
         0: new           #144                // class java/lang/StringBuilder
         3: dup
         4: ldc           #146                // String DateTime(
         6: invokespecial #149                // Method java/lang/StringBuilder."<init>":(Ljava/lang/String;)V
         9: astore_1
        10: aload_1
        11: aload_0
        12: invokevirtual #136                // Method year:()I
        15: invokestatic  #155                // Method java/lang/String.valueOf:(I)Ljava/lang/String;
        18: invokevirtual #159                // Method java/lang/StringBuilder.append:(Ljava/lang/String;)Ljava/lang/StringBuilder;
        21: pop
        22: aload_1
        23: ldc           #161                // String ,
        25: invokevirtual #159                // Method java/lang/StringBuilder.append:(Ljava/lang/String;)Ljava/lang/StringBuilder;
        28: pop
        29: aload_1
        30: aload_0
        31: invokevirtual #121                // Method month:()I
        34: invokestatic  #155                // Method java/lang/String.valueOf:(I)Ljava/lang/String;
        37: invokevirtual #159                // Method java/lang/StringBuilder.append:(Ljava/lang/String;)Ljava/lang/StringBuilder;
        40: pop
        41: aload_1
        42: ldc           #161                // String ,
        44: invokevirtual #159                // Method java/lang/StringBuilder.append:(Ljava/lang/String;)Ljava/lang/StringBuilder;
        47: pop
        48: aload_1
        49: aload_0
        50: invokevirtual #123                // Method day:()I
        53: invokestatic  #155                // Method java/lang/String.valueOf:(I)Ljava/lang/String;
        56: invokevirtual #159                // Method java/lang/StringBuilder.append:(Ljava/lang/String;)Ljava/lang/StringBuilder;
        59: pop
        60: aload_1
        61: ldc           #161                // String ,
        63: invokevirtual #159                // Method java/lang/StringBuilder.append:(Ljava/lang/String;)Ljava/lang/StringBuilder;
        66: pop
        67: aload_1
        68: aload_0
        69: invokevirtual #125                // Method hour:()I
        72: invokestatic  #155                // Method java/lang/String.valueOf:(I)Ljava/lang/String;
        75: invokevirtual #159                // Method java/lang/StringBuilder.append:(Ljava/lang/String;)Ljava/lang/StringBuilder;
        78: pop
        79: aload_1
        80: ldc           #161                // String ,
        82: invokevirtual #159                // Method java/lang/StringBuilder.append:(Ljava/lang/String;)Ljava/lang/StringBuilder;
        85: pop
        86: aload_1
        87: aload_0
        88: invokevirtual #127                // Method minute:()I
        91: invokestatic  #155                // Method java/lang/String.valueOf:(I)Ljava/lang/String;
        94: invokevirtual #159                // Method java/lang/StringBuilder.append:(Ljava/lang/String;)Ljava/lang/StringBuilder;
        97: pop
        98: aload_1
        99: ldc           #161                // String ,
       101: invokevirtual #159                // Method java/lang/StringBuilder.append:(Ljava/lang/String;)Ljava/lang/StringBuilder;
       104: pop
       105: aload_1
       106: aload_0
       107: invokevirtual #129                // Method second:()I
       110: invokestatic  #155                // Method java/lang/String.valueOf:(I)Ljava/lang/String;
       113: invokevirtual #159                // Method java/lang/StringBuilder.append:(Ljava/lang/String;)Ljava/lang/StringBuilder;
       116: pop
       117: aload_1
       118: ldc           #163                // String )
       120: invokevirtual #159                // Method java/lang/StringBuilder.append:(Ljava/lang/String;)Ljava/lang/StringBuilder;
       123: pop
       124: aload_1
       125: invokevirtual #165                // Method java/lang/StringBuilder.toString:()Ljava/lang/String;
       128: areturn
      LineNumberTable:
        line 105: 0
      LocalVariableTable:
        Start  Length  Slot  Name   Signature
           10     118     1     b   Ljava/lang/StringBuilder;
            0     129     0  this   Lcoursier/core/Versions$DateTime;

  public boolean canEqual(java.lang.Object);
    descriptor: (Ljava/lang/Object;)Z
    flags: (0x0001) ACC_PUBLIC
    Code:
      stack=1, locals=2, args_size=2
         0: aload_1
         1: ifnull        15
         4: aload_1
         5: instanceof    #2                  // class coursier/core/Versions$DateTime
         8: ifeq          15
        11: iconst_1
        12: goto          16
        15: iconst_0
        16: ireturn
      StackMapTable: number_of_entries = 2
        frame_type = 15 /* same */
        frame_type = 64 /* same_locals_1_stack_item */
          stack = [ int ]
      LineNumberTable:
        line 105: 0
      LocalVariableTable:
        Start  Length  Slot  Name   Signature
            0      17     0  this   Lcoursier/core/Versions$DateTime;
            0      17     1   obj   Ljava/lang/Object;
    MethodParameters:
      Name                           Flags
      obj                            final

  public boolean equals(java.lang.Object);
    descriptor: (Ljava/lang/Object;)Z
    flags: (0x0001) ACC_PUBLIC
    Code:
      stack=2, locals=3, args_size=2
         0: aload_0
         1: aload_1
         2: if_acmpeq     96
         5: aload_0
         6: aload_1
         7: invokevirtual #171                // Method canEqual:(Ljava/lang/Object;)Z
        10: ifeq          100
        13: aload_1
        14: checkcast     #2                  // class coursier/core/Versions$DateTime
        17: astore_2
        18: iconst_1
        19: ifeq          92
        22: aload_0
        23: invokevirtual #136                // Method year:()I
        26: aload_2
        27: invokevirtual #136                // Method year:()I
        30: if_icmpne     92
        33: aload_0
        34: invokevirtual #121                // Method month:()I
        37: aload_2
        38: invokevirtual #121                // Method month:()I
        41: if_icmpne     92
        44: aload_0
        45: invokevirtual #123                // Method day:()I
        48: aload_2
        49: invokevirtual #123                // Method day:()I
        52: if_icmpne     92
        55: aload_0
        56: invokevirtual #125                // Method hour:()I
        59: aload_2
        60: invokevirtual #125                // Method hour:()I
        63: if_icmpne     92
        66: aload_0
        67: invokevirtual #127                // Method minute:()I
        70: aload_2
        71: invokevirtual #127                // Method minute:()I
        74: if_icmpne     92
        77: aload_0
        78: invokevirtual #129                // Method second:()I
        81: aload_2
        82: invokevirtual #129                // Method second:()I
        85: if_icmpne     92
        88: iconst_1
        89: goto          93
        92: iconst_0
        93: ifeq          100
        96: iconst_1
        97: goto          101
       100: iconst_0
       101: ireturn
      StackMapTable: number_of_entries = 5
        frame_type = 252 /* append */
          offset_delta = 92
          locals = [ class coursier/core/Versions$DateTime ]
        frame_type = 64 /* same_locals_1_stack_item */
          stack = [ int ]
        frame_type = 250 /* chop */
          offset_delta = 2
        frame_type = 3 /* same */
        frame_type = 64 /* same_locals_1_stack_item */
          stack = [ int ]
      LineNumberTable:
        line 105: 0
      LocalVariableTable:
        Start  Length  Slot  Name   Signature
           18      75     2 other   Lcoursier/core/Versions$DateTime;
            0     102     0  this   Lcoursier/core/Versions$DateTime;
            0     102     1   obj   Ljava/lang/Object;
    MethodParameters:
      Name                           Flags
      obj                            final

  public int hashCode();
    descriptor: ()I
    flags: (0x0001) ACC_PUBLIC
    Code:
      stack=2, locals=2, args_size=1
         0: bipush        17
         2: ldc           #173                // String DateTime
         4: invokestatic  #178                // Method scala/runtime/Statics.anyHash:(Ljava/lang/Object;)I
         7: iadd
         8: istore_1
         9: bipush        37
        11: iload_1
        12: imul
        13: aload_0
        14: invokevirtual #136                // Method year:()I
        17: iadd
        18: istore_1
        19: bipush        37
        21: iload_1
        22: imul
        23: aload_0
        24: invokevirtual #121                // Method month:()I
        27: iadd
        28: istore_1
        29: bipush        37
        31: iload_1
        32: imul
        33: aload_0
        34: invokevirtual #123                // Method day:()I
        37: iadd
        38: istore_1
        39: bipush        37
        41: iload_1
        42: imul
        43: aload_0
        44: invokevirtual #125                // Method hour:()I
        47: iadd
        48: istore_1
        49: bipush        37
        51: iload_1
        52: imul
        53: aload_0
        54: invokevirtual #127                // Method minute:()I
        57: iadd
        58: istore_1
        59: bipush        37
        61: iload_1
        62: imul
        63: aload_0
        64: invokevirtual #129                // Method second:()I
        67: iadd
        68: istore_1
        69: bipush        37
        71: iload_1
        72: imul
        73: ireturn
      LineNumberTable:
        line 105: 0
      LocalVariableTable:
        Start  Length  Slot  Name   Signature
            9      64     1  code   I
            0      74     0  this   Lcoursier/core/Versions$DateTime;

  private scala.Tuple6<java.lang.Object, java.lang.Object, java.lang.Object, java.lang.Object, java.lang.Object, java.lang.Object> tuple();
    descriptor: ()Lscala/Tuple6;
    flags: (0x0002) ACC_PRIVATE
    Code:
      stack=8, locals=1, args_size=1
         0: new           #182                // class scala/Tuple6
         3: dup
         4: aload_0
         5: invokevirtual #136                // Method year:()I
         8: invokestatic  #188                // Method scala/runtime/BoxesRunTime.boxToInteger:(I)Ljava/lang/Integer;
        11: aload_0
        12: invokevirtual #121                // Method month:()I
        15: invokestatic  #188                // Method scala/runtime/BoxesRunTime.boxToInteger:(I)Ljava/lang/Integer;
        18: aload_0
        19: invokevirtual #123                // Method day:()I
        22: invokestatic  #188                // Method scala/runtime/BoxesRunTime.boxToInteger:(I)Ljava/lang/Integer;
        25: aload_0
        26: invokevirtual #125                // Method hour:()I
        29: invokestatic  #188                // Method scala/runtime/BoxesRunTime.boxToInteger:(I)Ljava/lang/Integer;
        32: aload_0
        33: invokevirtual #127                // Method minute:()I
        36: invokestatic  #188                // Method scala/runtime/BoxesRunTime.boxToInteger:(I)Ljava/lang/Integer;
        39: aload_0
        40: invokevirtual #129                // Method second:()I
        43: invokestatic  #188                // Method scala/runtime/BoxesRunTime.boxToInteger:(I)Ljava/lang/Integer;
        46: invokespecial #191                // Method scala/Tuple6."<init>":(Ljava/lang/Object;Ljava/lang/Object;Ljava/lang/Object;Ljava/lang/Object;Ljava/lang/Object;Ljava/lang/Object;)V
        49: areturn
      LineNumberTable:
        line 105: 0
      LocalVariableTable:
        Start  Length  Slot  Name   Signature
            0      50     0  this   Lcoursier/core/Versions$DateTime;
    Signature: #180                         // ()Lscala/Tuple6<Ljava/lang/Object;Ljava/lang/Object;Ljava/lang/Object;Ljava/lang/Object;Ljava/lang/Object;Ljava/lang/Object;>;

  public java.lang.String productPrefix();
    descriptor: ()Ljava/lang/String;
    flags: (0x0001) ACC_PUBLIC
    Code:
      stack=1, locals=1, args_size=1
         0: ldc           #173                // String DateTime
         2: areturn
      LineNumberTable:
        line 105: 0
      LocalVariableTable:
        Start  Length  Slot  Name   Signature
            0       3     0  this   Lcoursier/core/Versions$DateTime;

  public int productArity();
    descriptor: ()I
    flags: (0x0001) ACC_PUBLIC
    Code:
      stack=1, locals=1, args_size=1
         0: bipush        6
         2: ireturn
      LineNumberTable:
        line 105: 0
      LocalVariableTable:
        Start  Length  Slot  Name   Signature
            0       3     0  this   Lcoursier/core/Versions$DateTime;

  public java.lang.Object productElement(int);
    descriptor: (I)Ljava/lang/Object;
    flags: (0x0001) ACC_PUBLIC
    Code:
      stack=3, locals=3, args_size=2
         0: iload_1
         1: istore_2
         2: iload_2
         3: tableswitch   { // 0 to 5
                       0: 40
                       1: 50
                       2: 60
                       3: 70
                       4: 80
                       5: 90
                 default: 100
            }
        40: aload_0
        41: invokevirtual #136                // Method year:()I
        44: invokestatic  #188                // Method scala/runtime/BoxesRunTime.boxToInteger:(I)Ljava/lang/Integer;
        47: goto          115
        50: aload_0
        51: invokevirtual #121                // Method month:()I
        54: invokestatic  #188                // Method scala/runtime/BoxesRunTime.boxToInteger:(I)Ljava/lang/Integer;
        57: goto          115
        60: aload_0
        61: invokevirtual #123                // Method day:()I
        64: invokestatic  #188                // Method scala/runtime/BoxesRunTime.boxToInteger:(I)Ljava/lang/Integer;
        67: goto          115
        70: aload_0
        71: invokevirtual #125                // Method hour:()I
        74: invokestatic  #188                // Method scala/runtime/BoxesRunTime.boxToInteger:(I)Ljava/lang/Integer;
        77: goto          115
        80: aload_0
        81: invokevirtual #127                // Method minute:()I
        84: invokestatic  #188                // Method scala/runtime/BoxesRunTime.boxToInteger:(I)Ljava/lang/Integer;
        87: goto          115
        90: aload_0
        91: invokevirtual #129                // Method second:()I
        94: invokestatic  #188                // Method scala/runtime/BoxesRunTime.boxToInteger:(I)Ljava/lang/Integer;
        97: goto          115
       100: new           #198                // class java/lang/IndexOutOfBoundsException
       103: dup
       104: iload_2
       105: invokestatic  #188                // Method scala/runtime/BoxesRunTime.boxToInteger:(I)Ljava/lang/Integer;
       108: invokevirtual #199                // Method java/lang/Object.toString:()Ljava/lang/String;
       111: invokespecial #200                // Method java/lang/IndexOutOfBoundsException."<init>":(Ljava/lang/String;)V
       114: athrow
       115: areturn
      StackMapTable: number_of_entries = 8
        frame_type = 252 /* append */
          offset_delta = 40
          locals = [ int ]
        frame_type = 9 /* same */
        frame_type = 9 /* same */
        frame_type = 9 /* same */
        frame_type = 9 /* same */
        frame_type = 9 /* same */
        frame_type = 9 /* same */
        frame_type = 78 /* same_locals_1_stack_item */
          stack = [ class java/lang/Integer ]
      LineNumberTable:
        line 105: 0
      LocalVariableTable:
        Start  Length  Slot  Name   Signature
            0     116     0  this   Lcoursier/core/Versions$DateTime;
            0     116     1     n   I
    MethodParameters:
      Name                           Flags
      n                              final

  public java.lang.String productElementName(int);
    descriptor: (I)Ljava/lang/String;
    flags: (0x0001) ACC_PUBLIC
    Code:
      stack=3, locals=3, args_size=2
         0: iload_1
         1: istore_2
         2: iload_2
         3: tableswitch   { // 0 to 5
                       0: 40
                       1: 45
                       2: 50
                       3: 55
                       4: 60
                       5: 65
                 default: 70
            }
        40: ldc           #204                // String year
        42: goto          85
        45: ldc           #205                // String month
        47: goto          85
        50: ldc           #206                // String day
        52: goto          85
        55: ldc           #207                // String hour
        57: goto          85
        60: ldc           #208                // String minute
        62: goto          85
        65: ldc           #209                // String second
        67: goto          85
        70: new           #198                // class java/lang/IndexOutOfBoundsException
        73: dup
        74: iload_2
        75: invokestatic  #188                // Method scala/runtime/BoxesRunTime.boxToInteger:(I)Ljava/lang/Integer;
        78: invokevirtual #199                // Method java/lang/Object.toString:()Ljava/lang/String;
        81: invokespecial #200                // Method java/lang/IndexOutOfBoundsException."<init>":(Ljava/lang/String;)V
        84: athrow
        85: areturn
      StackMapTable: number_of_entries = 8
        frame_type = 252 /* append */
          offset_delta = 40
          locals = [ int ]
        frame_type = 4 /* same */
        frame_type = 4 /* same */
        frame_type = 4 /* same */
        frame_type = 4 /* same */
        frame_type = 4 /* same */
        frame_type = 4 /* same */
        frame_type = 78 /* same_locals_1_stack_item */
          stack = [ class java/lang/String ]
      LineNumberTable:
        line 105: 0
      LocalVariableTable:
        Start  Length  Slot  Name   Signature
            0      86     0  this   Lcoursier/core/Versions$DateTime;
            0      86     1     n   I
    MethodParameters:
      Name                           Flags
      n                              final

  public int compare(java.lang.Object);
    descriptor: (Ljava/lang/Object;)I
    flags: (0x1041) ACC_PUBLIC, ACC_BRIDGE, ACC_SYNTHETIC
    Code:
      stack=2, locals=2, args_size=2
         0: aload_0
         1: aload_1
         2: checkcast     #2                  // class coursier/core/Versions$DateTime
         5: invokevirtual #211                // Method compare:(Lcoursier/core/Versions$DateTime;)I
         8: ireturn
      LineNumberTable:
        line 105: 0
      LocalVariableTable:
        Start  Length  Slot  Name   Signature
            0       9     0  this   Lcoursier/core/Versions$DateTime;
            0       9     1  that   Ljava/lang/Object;
    MethodParameters:
      Name                           Flags
      that                           final

  public coursier.core.Versions$DateTime(int, int, int, int, int, int);
    descriptor: (IIIIII)V
    flags: (0x0001) ACC_PUBLIC
    Code:
      stack=2, locals=7, args_size=7
         0: aload_0
         1: iload_1
         2: putfield      #75                 // Field year:I
         5: aload_0
         6: iload_2
         7: putfield      #77                 // Field month:I
        10: aload_0
        11: iload_3
        12: putfield      #79                 // Field day:I
        15: aload_0
        16: iload         4
        18: putfield      #81                 // Field hour:I
        21: aload_0
        22: iload         5
        24: putfield      #83                 // Field minute:I
        27: aload_0
        28: iload         6
        30: putfield      #85                 // Field second:I
        33: aload_0
        34: invokespecial #214                // Method java/lang/Object."<init>":()V
        37: aload_0
        38: invokestatic  #218                // InterfaceMethod scala/math/Ordered.$init$:(Lscala/math/Ordered;)V
        41: aload_0
        42: invokestatic  #221                // InterfaceMethod scala/Product.$init$:(Lscala/Product;)V
        45: return
      LineNumberTable:
        line 105: 0
        line 112: 33
        line 105: 45
      LocalVariableTable:
        Start  Length  Slot  Name   Signature
            0      46     0  this   Lcoursier/core/Versions$DateTime;
            0      46     1  year   I
            0      46     2 month   I
            0      46     3   day   I
            0      46     4  hour   I
            0      46     5 minute   I
            0      46     6 second   I
    MethodParameters:
      Name                           Flags
      year                           final
      month                          final
      day                            final
      hour                           final
      minute                         final
      second                         final
}
InnerClasses:
  public static final #15= #2 of #14;     // DateTime=class coursier/core/Versions$DateTime of class coursier/core/Versions
  public static #20= #17 of #19;          // =class scala/math/Ordering$Implicits$ of class scala/math/Ordering
  public static #20= #22 of #19;          // =class scala/math/Ordering$Int$ of class scala/math/Ordering
  public #25= #24 of #19;                 // OrderingOps=class scala/math/Ordering$OrderingOps of class scala/math/Ordering
Signature: #3                           // Ljava/lang/Object;Lscala/math/Ordered<Lcoursier/core/Versions$DateTime;>;Lscala/Product;Ljava/io/Serializable;
SourceFile: "Versions.scala"
  ScalaInlineInfo: length = 0x9F (unknown attribute)
   01 01 00 1F 00 38 00 31 01 00 40 00 31 01 00 30
   00 31 01 00 3C 00 31 01 00 83 00 84 01 00 A9 00
   31 01 00 57 00 58 01 00 57 00 45 01 00 44 00 45
   01 00 1E 00 4A 01 00 5A 00 31 01 00 AD 00 4A 01
   00 1F 00 4A 01 00 20 00 4A 01 00 1D 00 4A 01 00
   C2 00 4A 01 00 C3 00 C4 01 00 CC 00 9A 01 00 2B
   00 23 01 00 22 00 23 01 00 C1 00 8F 01 00 21 00
   4A 01 00 8E 00 8F 01 00 61 00 62 01 00 8A 00 78
   01 00 8B 00 78 01 00 8C 00 78 01 00 87 00 78 01
   00 8D 00 78 01 00 77 00 78 01 00 1B 00 4A 01
  Scala: length = 0x0 (unknown attribute)

