Classfile /Users/mw/Projects/slang-braindump/.jar/jar11/assemble/slang-braindump/assemble/content/coursier/core/Version$Tokenizer$Separator.class
  Last modified May 29, 2022; size 481 bytes
  SHA-256 checksum 339da2bf6b2a324df191838296fc16f69ac73e7a8886fed31be276c76507bef8
  Compiled from "Version.scala"
public abstract class coursier.core.Version$Tokenizer$Separator
  minor version: 0
  major version: 52
  flags: (0x0421) ACC_PUBLIC, ACC_SUPER, ACC_ABSTRACT
  this_class: #2                          // coursier/core/Version$Tokenizer$Separator
  super_class: #4                         // java/lang/Object
  interfaces: 0, fields: 0, methods: 1, attributes: 4
Constant pool:
   #1 = Utf8               coursier/core/Version$Tokenizer$Separator
   #2 = Class              #1             // coursier/core/Version$Tokenizer$Separator
   #3 = Utf8               java/lang/Object
   #4 = Class              #3             // java/lang/Object
   #5 = Utf8               Version.scala
   #6 = Utf8               coursier/core/Version$Tokenizer$
   #7 = Class              #6             // coursier/core/Version$Tokenizer$
   #8 = Utf8               coursier/core/Version
   #9 = Class              #8             // coursier/core/Version
  #10 = Utf8
  #11 = Utf8               Separator
  #12 = Utf8               <init>
  #13 = Utf8               ()V
  #14 = NameAndType        #12:#13        // "<init>":()V
  #15 = Methodref          #4.#14         // java/lang/Object."<init>":()V
  #16 = Utf8               this
  #17 = Utf8               Lcoursier/core/Version$Tokenizer$Separator;
  #18 = Utf8               Code
  #19 = Utf8               LineNumberTable
  #20 = Utf8               LocalVariableTable
  #21 = Utf8               InnerClasses
  #22 = Utf8               SourceFile
  #23 = Utf8               ScalaInlineInfo
  #24 = Utf8               Scala
{
  public coursier.core.Version$Tokenizer$Separator();
    descriptor: ()V
    flags: (0x0001) ACC_PUBLIC
    Code:
      stack=1, locals=1, args_size=1
         0: aload_0
         1: invokespecial #15                 // Method java/lang/Object."<init>":()V
         4: return
      LineNumberTable:
        line 105: 0
      LocalVariableTable:
        Start  Length  Slot  Name   Signature
            0       5     0  this   Lcoursier/core/Version$Tokenizer$Separator;
}
InnerClasses:
  public static #10= #7 of #9;            // =class coursier/core/Version$Tokenizer$ of class coursier/core/Version
  public static abstract #11= #2 of #7;   // Separator=class coursier/core/Version$Tokenizer$Separator of class coursier/core/Version$Tokenizer$
SourceFile: "Version.scala"
  ScalaInlineInfo: length = 0x9 (unknown attribute)
   01 00 00 01 00 0C 00 0D 01
  Scala: length = 0x0 (unknown attribute)

