Classfile /Users/mw/Projects/slang-braindump/.jar/jar11/assemble/slang-braindump/assemble/content/scala/xml/include/UnavailableResourceException.class
  Last modified May 29, 2022; size 932 bytes
  SHA-256 checksum 1aca02df241f90232bd1b4fd95a2b0a6c58b73164ca35b80fe4b3b9a7963bea0
  Compiled from "UnavailableResourceException.scala"
public class scala.xml.include.UnavailableResourceException extends scala.xml.include.XIncludeException
  minor version: 0
  major version: 52
  flags: (0x0021) ACC_PUBLIC, ACC_SUPER
  this_class: #2                          // scala/xml/include/UnavailableResourceException
  super_class: #4                         // scala/xml/include/XIncludeException
  interfaces: 0, fields: 0, methods: 2, attributes: 4
Constant pool:
   #1 = Utf8               scala/xml/include/UnavailableResourceException
   #2 = Class              #1             // scala/xml/include/UnavailableResourceException
   #3 = Utf8               scala/xml/include/XIncludeException
   #4 = Class              #3             // scala/xml/include/XIncludeException
   #5 = Utf8               UnavailableResourceException.scala
   #6 = Utf8               Lscala/reflect/ScalaSignature;
   #7 = Utf8               bytes
   #8 = Utf8               \u0006\u0005\t2A\u0001B\u0003\u0001\u0019!A\u0011\u0003\u0001B\u0001B\u0003%!\u0003C\u0003\u001e\u0001\u0011\u0005a\u0004C\u0003\u001e\u0001\u0011\u0005\u0011E\u0001\u000fV]\u00064\u0018-\u001b7bE2,\'+Z:pkJ\u001cW-\u0012=dKB$\u0018n\u001c8\u000b\u0005\u00199\u0011aB5oG2,H-\u001a\u0006\u0003\u0011%\t1\u0001_7m\u0015\u0005Q\u0011!B:dC2\f7\u0001A\n\u0003\u00015\u0001\"AD\b\u000e\u0003\u0015I!\u0001E\u0003\u0003#aKen\u00197vI\u0016,\u0005pY3qi&|g.A\u0004nKN\u001c\u0018mZ3\u0011\u0005MQbB\u0001\u000b\u0019!\t)\u0012\"D\u0001\u0017\u0015\t92\"\u0001\u0004=e>|GOP\u0005\u00033%\ta\u0001\u0015:fI\u00164\u0017BA\u000e\u001d\u0005\u0019\u0019FO]5oO*\u0011\u0011$C\u0001\u0007y%t\u0017\u000e\u001e \u0015\u0005}\u0001\u0003C\u0001\b\u0001\u0011\u0015\t\"\u00011\u0001\u0013)\u0005y\u0002
   #9 = Utf8               <init>
  #10 = Utf8               (Ljava/lang/String;)V
  #11 = Utf8               message
  #12 = NameAndType        #9:#10         // "<init>":(Ljava/lang/String;)V
  #13 = Methodref          #4.#12         // scala/xml/include/XIncludeException."<init>":(Ljava/lang/String;)V
  #14 = Utf8               this
  #15 = Utf8               Lscala/xml/include/UnavailableResourceException;
  #16 = Utf8               Ljava/lang/String;
  #17 = Utf8               ()V
  #18 = Methodref          #2.#12         // scala/xml/include/UnavailableResourceException."<init>":(Ljava/lang/String;)V
  #19 = Utf8               Code
  #20 = Utf8               LineNumberTable
  #21 = Utf8               LocalVariableTable
  #22 = Utf8               MethodParameters
  #23 = Utf8               SourceFile
  #24 = Utf8               RuntimeVisibleAnnotations
  #25 = Utf8               ScalaInlineInfo
  #26 = Utf8               ScalaSig
{
  public scala.xml.include.UnavailableResourceException(java.lang.String);
    descriptor: (Ljava/lang/String;)V
    flags: (0x0001) ACC_PUBLIC
    Code:
      stack=2, locals=2, args_size=2
         0: aload_0
         1: aload_1
         2: invokespecial #13                 // Method scala/xml/include/XIncludeException."<init>":(Ljava/lang/String;)V
         5: return
      LineNumberTable:
        line 22: 0
        line 21: 5
      LocalVariableTable:
        Start  Length  Slot  Name   Signature
            0       6     0  this   Lscala/xml/include/UnavailableResourceException;
            0       6     1 message   Ljava/lang/String;
    MethodParameters:
      Name                           Flags
      message                        final

  public scala.xml.include.UnavailableResourceException();
    descriptor: ()V
    flags: (0x0001) ACC_PUBLIC
    Code:
      stack=2, locals=1, args_size=1
         0: aload_0
         1: aconst_null
         2: invokespecial #18                 // Method "<init>":(Ljava/lang/String;)V
         5: return
      LineNumberTable:
        line 23: 0
      LocalVariableTable:
        Start  Length  Slot  Name   Signature
            0       6     0  this   Lscala/xml/include/UnavailableResourceException;
}
SourceFile: "UnavailableResourceException.scala"
RuntimeVisibleAnnotations:
  0: #6(#7=s#8)
    scala.reflect.ScalaSignature(
      bytes="\u0006\u0005\t2A\u0001B\u0003\u0001\u0019!A\u0011\u0003\u0001B\u0001B\u0003%!\u0003C\u0003\u001e\u0001\u0011\u0005a\u0004C\u0003\u001e\u0001\u0011\u0005\u0011E\u0001\u000fV]\u00064\u0018-\u001b7bE2,\'+Z:pkJ\u001cW-\u0012=dKB$\u0018n\u001c8\u000b\u0005\u00199\u0011aB5oG2,H-\u001a\u0006\u0003\u0011%\t1\u0001_7m\u0015\u0005Q\u0011!B:dC2\f7\u0001A\n\u0003\u00015\u0001\"AD\b\u000e\u0003\u0015I!\u0001E\u0003\u0003#aKen\u00197vI\u0016,\u0005pY3qi&|g.A\u0004nKN\u001c\u0018mZ3\u0011\u0005MQbB\u0001\u000b\u0019!\t)\u0012\"D\u0001\u0017\u0015\t92\"\u0001\u0004=e>|GOP\u0005\u00033%\ta\u0001\u0015:fI\u00164\u0017BA\u000e\u001d\u0005\u0019\u0019FO]5oO*\u0011\u0011$C\u0001\u0007y%t\u0017\u000e\u001e \u0015\u0005}\u0001\u0003C\u0001\b\u0001\u0011\u0015\t\"\u00011\u0001\u0013)\u0005y\u0002"
    )
  ScalaInlineInfo: length = 0xE (unknown attribute)
   01 00 00 02 00 09 00 11 00 00 09 00 0A 00
  ScalaSig: length = 0x3 (unknown attribute)
   05 02 00
