Classfile /Users/mw/Projects/slang-braindump/.jar/jar11/assemble/slang-braindump/assemble/content/com/fasterxml/jackson/databind/cfg/ContextAttributes.class
  Last modified May 29, 2022; size 1102 bytes
  SHA-256 checksum 81c9e40d65267223fe75e2da4932a20736091d34522904faa7332a30df5f683d
  Compiled from "ContextAttributes.java"
public abstract class com.fasterxml.jackson.databind.cfg.ContextAttributes
  minor version: 0
  major version: 52
  flags: (0x0421) ACC_PUBLIC, ACC_SUPER, ACC_ABSTRACT
  this_class: #3                          // com/fasterxml/jackson/databind/cfg/ContextAttributes
  super_class: #4                         // java/lang/Object
  interfaces: 0, fields: 0, methods: 7, attributes: 2
Constant pool:
   #1 = Methodref          #4.#30         // java/lang/Object."<init>":()V
   #2 = Methodref          #5.#31         // com/fasterxml/jackson/databind/cfg/ContextAttributes$Impl.getEmpty:()Lcom/fasterxml/jackson/databind/cfg/ContextAttributes;
   #3 = Class              #32            // com/fasterxml/jackson/databind/cfg/ContextAttributes
   #4 = Class              #33            // java/lang/Object
   #5 = Class              #34            // com/fasterxml/jackson/databind/cfg/ContextAttributes$Impl
   #6 = Utf8               Impl
   #7 = Utf8               InnerClasses
   #8 = Utf8               <init>
   #9 = Utf8               ()V
  #10 = Utf8               Code
  #11 = Utf8               LineNumberTable
  #12 = Utf8               LocalVariableTable
  #13 = Utf8               this
  #14 = Utf8               Lcom/fasterxml/jackson/databind/cfg/ContextAttributes;
  #15 = Utf8               getEmpty
  #16 = Utf8               ()Lcom/fasterxml/jackson/databind/cfg/ContextAttributes;
  #17 = Utf8               withSharedAttribute
  #18 = Utf8               (Ljava/lang/Object;Ljava/lang/Object;)Lcom/fasterxml/jackson/databind/cfg/ContextAttributes;
  #19 = Utf8               withSharedAttributes
  #20 = Utf8               (Ljava/util/Map;)Lcom/fasterxml/jackson/databind/cfg/ContextAttributes;
  #21 = Utf8               Signature
  #22 = Utf8               (Ljava/util/Map<**>;)Lcom/fasterxml/jackson/databind/cfg/ContextAttributes;
  #23 = Utf8               withoutSharedAttribute
  #24 = Utf8               (Ljava/lang/Object;)Lcom/fasterxml/jackson/databind/cfg/ContextAttributes;
  #25 = Utf8               getAttribute
  #26 = Utf8               (Ljava/lang/Object;)Ljava/lang/Object;
  #27 = Utf8               withPerCallAttribute
  #28 = Utf8               SourceFile
  #29 = Utf8               ContextAttributes.java
  #30 = NameAndType        #8:#9          // "<init>":()V
  #31 = NameAndType        #15:#16        // getEmpty:()Lcom/fasterxml/jackson/databind/cfg/ContextAttributes;
  #32 = Utf8               com/fasterxml/jackson/databind/cfg/ContextAttributes
  #33 = Utf8               java/lang/Object
  #34 = Utf8               com/fasterxml/jackson/databind/cfg/ContextAttributes$Impl
{
  public com.fasterxml.jackson.databind.cfg.ContextAttributes();
    descriptor: ()V
    flags: (0x0001) ACC_PUBLIC
    Code:
      stack=1, locals=1, args_size=1
         0: aload_0
         1: invokespecial #1                  // Method java/lang/Object."<init>":()V
         4: return
      LineNumberTable:
        line 21: 0
      LocalVariableTable:
        Start  Length  Slot  Name   Signature
            0       5     0  this   Lcom/fasterxml/jackson/databind/cfg/ContextAttributes;

  public static com.fasterxml.jackson.databind.cfg.ContextAttributes getEmpty();
    descriptor: ()Lcom/fasterxml/jackson/databind/cfg/ContextAttributes;
    flags: (0x0009) ACC_PUBLIC, ACC_STATIC
    Code:
      stack=1, locals=0, args_size=0
         0: invokestatic  #2                  // Method com/fasterxml/jackson/databind/cfg/ContextAttributes$Impl.getEmpty:()Lcom/fasterxml/jackson/databind/cfg/ContextAttributes;
         3: areturn
      LineNumberTable:
        line 24: 0

  public abstract com.fasterxml.jackson.databind.cfg.ContextAttributes withSharedAttribute(java.lang.Object, java.lang.Object);
    descriptor: (Ljava/lang/Object;Ljava/lang/Object;)Lcom/fasterxml/jackson/databind/cfg/ContextAttributes;
    flags: (0x0401) ACC_PUBLIC, ACC_ABSTRACT

  public abstract com.fasterxml.jackson.databind.cfg.ContextAttributes withSharedAttributes(java.util.Map<?, ?>);
    descriptor: (Ljava/util/Map;)Lcom/fasterxml/jackson/databind/cfg/ContextAttributes;
    flags: (0x0401) ACC_PUBLIC, ACC_ABSTRACT
    Signature: #22                          // (Ljava/util/Map<**>;)Lcom/fasterxml/jackson/databind/cfg/ContextAttributes;

  public abstract com.fasterxml.jackson.databind.cfg.ContextAttributes withoutSharedAttribute(java.lang.Object);
    descriptor: (Ljava/lang/Object;)Lcom/fasterxml/jackson/databind/cfg/ContextAttributes;
    flags: (0x0401) ACC_PUBLIC, ACC_ABSTRACT

  public abstract java.lang.Object getAttribute(java.lang.Object);
    descriptor: (Ljava/lang/Object;)Ljava/lang/Object;
    flags: (0x0401) ACC_PUBLIC, ACC_ABSTRACT

  public abstract com.fasterxml.jackson.databind.cfg.ContextAttributes withPerCallAttribute(java.lang.Object, java.lang.Object);
    descriptor: (Ljava/lang/Object;Ljava/lang/Object;)Lcom/fasterxml/jackson/databind/cfg/ContextAttributes;
    flags: (0x0401) ACC_PUBLIC, ACC_ABSTRACT
}
SourceFile: "ContextAttributes.java"
InnerClasses:
  public static #6= #5 of #3;             // Impl=class com/fasterxml/jackson/databind/cfg/ContextAttributes$Impl of class com/fasterxml/jackson/databind/cfg/ContextAttributes
