Classfile /Users/mw/Projects/slang-braindump/.jar/jar11/assemble/slang-braindump/assemble/content/com/fasterxml/jackson/databind/cfg/MutableConfigOverride.class
  Last modified May 29, 2022; size 3376 bytes
  SHA-256 checksum cb87220bbf3b7662f36953383b7b9076fdf52ee5b3314b7d90ba1bf30ffdc924
  Compiled from "MutableConfigOverride.java"
public class com.fasterxml.jackson.databind.cfg.MutableConfigOverride extends com.fasterxml.jackson.databind.cfg.ConfigOverride implements java.io.Serializable
  minor version: 0
  major version: 52
  flags: (0x0021) ACC_PUBLIC, ACC_SUPER
  this_class: #3                          // com/fasterxml/jackson/databind/cfg/MutableConfigOverride
  super_class: #13                        // com/fasterxml/jackson/databind/cfg/ConfigOverride
  interfaces: 1, fields: 1, methods: 11, attributes: 2
Constant pool:
   #1 = Methodref          #13.#61        // com/fasterxml/jackson/databind/cfg/ConfigOverride."<init>":()V
   #2 = Methodref          #13.#62        // com/fasterxml/jackson/databind/cfg/ConfigOverride."<init>":(Lcom/fasterxml/jackson/databind/cfg/ConfigOverride;)V
   #3 = Class              #63            // com/fasterxml/jackson/databind/cfg/MutableConfigOverride
   #4 = Methodref          #3.#64         // com/fasterxml/jackson/databind/cfg/MutableConfigOverride."<init>":(Lcom/fasterxml/jackson/databind/cfg/MutableConfigOverride;)V
   #5 = Fieldref           #3.#65         // com/fasterxml/jackson/databind/cfg/MutableConfigOverride._format:Lcom/fasterxml/jackson/annotation/JsonFormat$Value;
   #6 = Fieldref           #3.#66         // com/fasterxml/jackson/databind/cfg/MutableConfigOverride._include:Lcom/fasterxml/jackson/annotation/JsonInclude$Value;
   #7 = Fieldref           #3.#67         // com/fasterxml/jackson/databind/cfg/MutableConfigOverride._includeAsProperty:Lcom/fasterxml/jackson/annotation/JsonInclude$Value;
   #8 = Fieldref           #3.#68         // com/fasterxml/jackson/databind/cfg/MutableConfigOverride._ignorals:Lcom/fasterxml/jackson/annotation/JsonIgnoreProperties$Value;
   #9 = Fieldref           #3.#69         // com/fasterxml/jackson/databind/cfg/MutableConfigOverride._isIgnoredType:Ljava/lang/Boolean;
  #10 = Fieldref           #3.#70         // com/fasterxml/jackson/databind/cfg/MutableConfigOverride._setterInfo:Lcom/fasterxml/jackson/annotation/JsonSetter$Value;
  #11 = Fieldref           #3.#71         // com/fasterxml/jackson/databind/cfg/MutableConfigOverride._visibility:Lcom/fasterxml/jackson/annotation/JsonAutoDetect$Value;
  #12 = Fieldref           #3.#72         // com/fasterxml/jackson/databind/cfg/MutableConfigOverride._mergeable:Ljava/lang/Boolean;
  #13 = Class              #73            // com/fasterxml/jackson/databind/cfg/ConfigOverride
  #14 = Class              #74            // java/io/Serializable
  #15 = Utf8               serialVersionUID
  #16 = Utf8               J
  #17 = Utf8               ConstantValue
  #18 = Long               1l
  #20 = Utf8               <init>
  #21 = Utf8               ()V
  #22 = Utf8               Code
  #23 = Utf8               LineNumberTable
  #24 = Utf8               LocalVariableTable
  #25 = Utf8               this
  #26 = Utf8               Lcom/fasterxml/jackson/databind/cfg/MutableConfigOverride;
  #27 = Utf8               (Lcom/fasterxml/jackson/databind/cfg/MutableConfigOverride;)V
  #28 = Utf8               src
  #29 = Utf8               copy
  #30 = Utf8               ()Lcom/fasterxml/jackson/databind/cfg/MutableConfigOverride;
  #31 = Utf8               setFormat
  #32 = Class              #76            // com/fasterxml/jackson/annotation/JsonFormat$Value
  #33 = Utf8               Value
  #34 = Utf8               InnerClasses
  #35 = Utf8               (Lcom/fasterxml/jackson/annotation/JsonFormat$Value;)Lcom/fasterxml/jackson/databind/cfg/MutableConfigOverride;
  #36 = Utf8               v
  #37 = Utf8               Lcom/fasterxml/jackson/annotation/JsonFormat$Value;
  #38 = Utf8               setInclude
  #39 = Class              #78            // com/fasterxml/jackson/annotation/JsonInclude$Value
  #40 = Utf8               (Lcom/fasterxml/jackson/annotation/JsonInclude$Value;)Lcom/fasterxml/jackson/databind/cfg/MutableConfigOverride;
  #41 = Utf8               Lcom/fasterxml/jackson/annotation/JsonInclude$Value;
  #42 = Utf8               setIncludeAsProperty
  #43 = Utf8               setIgnorals
  #44 = Class              #80            // com/fasterxml/jackson/annotation/JsonIgnoreProperties$Value
  #45 = Utf8               (Lcom/fasterxml/jackson/annotation/JsonIgnoreProperties$Value;)Lcom/fasterxml/jackson/databind/cfg/MutableConfigOverride;
  #46 = Utf8               Lcom/fasterxml/jackson/annotation/JsonIgnoreProperties$Value;
  #47 = Utf8               setIsIgnoredType
  #48 = Utf8               (Ljava/lang/Boolean;)Lcom/fasterxml/jackson/databind/cfg/MutableConfigOverride;
  #49 = Utf8               Ljava/lang/Boolean;
  #50 = Utf8               setSetterInfo
  #51 = Class              #82            // com/fasterxml/jackson/annotation/JsonSetter$Value
  #52 = Utf8               (Lcom/fasterxml/jackson/annotation/JsonSetter$Value;)Lcom/fasterxml/jackson/databind/cfg/MutableConfigOverride;
  #53 = Utf8               Lcom/fasterxml/jackson/annotation/JsonSetter$Value;
  #54 = Utf8               setVisibility
  #55 = Class              #84            // com/fasterxml/jackson/annotation/JsonAutoDetect$Value
  #56 = Utf8               (Lcom/fasterxml/jackson/annotation/JsonAutoDetect$Value;)Lcom/fasterxml/jackson/databind/cfg/MutableConfigOverride;
  #57 = Utf8               Lcom/fasterxml/jackson/annotation/JsonAutoDetect$Value;
  #58 = Utf8               setMergeable
  #59 = Utf8               SourceFile
  #60 = Utf8               MutableConfigOverride.java
  #61 = NameAndType        #20:#21        // "<init>":()V
  #62 = NameAndType        #20:#85        // "<init>":(Lcom/fasterxml/jackson/databind/cfg/ConfigOverride;)V
  #63 = Utf8               com/fasterxml/jackson/databind/cfg/MutableConfigOverride
  #64 = NameAndType        #20:#27        // "<init>":(Lcom/fasterxml/jackson/databind/cfg/MutableConfigOverride;)V
  #65 = NameAndType        #86:#37        // _format:Lcom/fasterxml/jackson/annotation/JsonFormat$Value;
  #66 = NameAndType        #87:#41        // _include:Lcom/fasterxml/jackson/annotation/JsonInclude$Value;
  #67 = NameAndType        #88:#41        // _includeAsProperty:Lcom/fasterxml/jackson/annotation/JsonInclude$Value;
  #68 = NameAndType        #89:#46        // _ignorals:Lcom/fasterxml/jackson/annotation/JsonIgnoreProperties$Value;
  #69 = NameAndType        #90:#49        // _isIgnoredType:Ljava/lang/Boolean;
  #70 = NameAndType        #91:#53        // _setterInfo:Lcom/fasterxml/jackson/annotation/JsonSetter$Value;
  #71 = NameAndType        #92:#57        // _visibility:Lcom/fasterxml/jackson/annotation/JsonAutoDetect$Value;
  #72 = NameAndType        #93:#49        // _mergeable:Ljava/lang/Boolean;
  #73 = Utf8               com/fasterxml/jackson/databind/cfg/ConfigOverride
  #74 = Utf8               java/io/Serializable
  #75 = Class              #94            // com/fasterxml/jackson/annotation/JsonFormat
  #76 = Utf8               com/fasterxml/jackson/annotation/JsonFormat$Value
  #77 = Class              #95            // com/fasterxml/jackson/annotation/JsonInclude
  #78 = Utf8               com/fasterxml/jackson/annotation/JsonInclude$Value
  #79 = Class              #96            // com/fasterxml/jackson/annotation/JsonIgnoreProperties
  #80 = Utf8               com/fasterxml/jackson/annotation/JsonIgnoreProperties$Value
  #81 = Class              #97            // com/fasterxml/jackson/annotation/JsonSetter
  #82 = Utf8               com/fasterxml/jackson/annotation/JsonSetter$Value
  #83 = Class              #98            // com/fasterxml/jackson/annotation/JsonAutoDetect
  #84 = Utf8               com/fasterxml/jackson/annotation/JsonAutoDetect$Value
  #85 = Utf8               (Lcom/fasterxml/jackson/databind/cfg/ConfigOverride;)V
  #86 = Utf8               _format
  #87 = Utf8               _include
  #88 = Utf8               _includeAsProperty
  #89 = Utf8               _ignorals
  #90 = Utf8               _isIgnoredType
  #91 = Utf8               _setterInfo
  #92 = Utf8               _visibility
  #93 = Utf8               _mergeable
  #94 = Utf8               com/fasterxml/jackson/annotation/JsonFormat
  #95 = Utf8               com/fasterxml/jackson/annotation/JsonInclude
  #96 = Utf8               com/fasterxml/jackson/annotation/JsonIgnoreProperties
  #97 = Utf8               com/fasterxml/jackson/annotation/JsonSetter
  #98 = Utf8               com/fasterxml/jackson/annotation/JsonAutoDetect
{
  private static final long serialVersionUID;
    descriptor: J
    flags: (0x001a) ACC_PRIVATE, ACC_STATIC, ACC_FINAL
    ConstantValue: long 1l

  public com.fasterxml.jackson.databind.cfg.MutableConfigOverride();
    descriptor: ()V
    flags: (0x0001) ACC_PUBLIC
    Code:
      stack=1, locals=1, args_size=1
         0: aload_0
         1: invokespecial #1                  // Method com/fasterxml/jackson/databind/cfg/ConfigOverride."<init>":()V
         4: return
      LineNumberTable:
        line 24: 0
      LocalVariableTable:
        Start  Length  Slot  Name   Signature
            0       5     0  this   Lcom/fasterxml/jackson/databind/cfg/MutableConfigOverride;

  protected com.fasterxml.jackson.databind.cfg.MutableConfigOverride(com.fasterxml.jackson.databind.cfg.MutableConfigOverride);
    descriptor: (Lcom/fasterxml/jackson/databind/cfg/MutableConfigOverride;)V
    flags: (0x0004) ACC_PROTECTED
    Code:
      stack=2, locals=2, args_size=2
         0: aload_0
         1: aload_1
         2: invokespecial #2                  // Method com/fasterxml/jackson/databind/cfg/ConfigOverride."<init>":(Lcom/fasterxml/jackson/databind/cfg/ConfigOverride;)V
         5: return
      LineNumberTable:
        line 27: 0
        line 28: 5
      LocalVariableTable:
        Start  Length  Slot  Name   Signature
            0       6     0  this   Lcom/fasterxml/jackson/databind/cfg/MutableConfigOverride;
            0       6     1   src   Lcom/fasterxml/jackson/databind/cfg/MutableConfigOverride;

  public com.fasterxml.jackson.databind.cfg.MutableConfigOverride copy();
    descriptor: ()Lcom/fasterxml/jackson/databind/cfg/MutableConfigOverride;
    flags: (0x0001) ACC_PUBLIC
    Code:
      stack=3, locals=1, args_size=1
         0: new           #3                  // class com/fasterxml/jackson/databind/cfg/MutableConfigOverride
         3: dup
         4: aload_0
         5: invokespecial #4                  // Method "<init>":(Lcom/fasterxml/jackson/databind/cfg/MutableConfigOverride;)V
         8: areturn
      LineNumberTable:
        line 31: 0
      LocalVariableTable:
        Start  Length  Slot  Name   Signature
            0       9     0  this   Lcom/fasterxml/jackson/databind/cfg/MutableConfigOverride;

  public com.fasterxml.jackson.databind.cfg.MutableConfigOverride setFormat(com.fasterxml.jackson.annotation.JsonFormat$Value);
    descriptor: (Lcom/fasterxml/jackson/annotation/JsonFormat$Value;)Lcom/fasterxml/jackson/databind/cfg/MutableConfigOverride;
    flags: (0x0001) ACC_PUBLIC
    Code:
      stack=2, locals=2, args_size=2
         0: aload_0
         1: aload_1
         2: putfield      #5                  // Field _format:Lcom/fasterxml/jackson/annotation/JsonFormat$Value;
         5: aload_0
         6: areturn
      LineNumberTable:
        line 35: 0
        line 36: 5
      LocalVariableTable:
        Start  Length  Slot  Name   Signature
            0       7     0  this   Lcom/fasterxml/jackson/databind/cfg/MutableConfigOverride;
            0       7     1     v   Lcom/fasterxml/jackson/annotation/JsonFormat$Value;

  public com.fasterxml.jackson.databind.cfg.MutableConfigOverride setInclude(com.fasterxml.jackson.annotation.JsonInclude$Value);
    descriptor: (Lcom/fasterxml/jackson/annotation/JsonInclude$Value;)Lcom/fasterxml/jackson/databind/cfg/MutableConfigOverride;
    flags: (0x0001) ACC_PUBLIC
    Code:
      stack=2, locals=2, args_size=2
         0: aload_0
         1: aload_1
         2: putfield      #6                  // Field _include:Lcom/fasterxml/jackson/annotation/JsonInclude$Value;
         5: aload_0
         6: areturn
      LineNumberTable:
        line 46: 0
        line 47: 5
      LocalVariableTable:
        Start  Length  Slot  Name   Signature
            0       7     0  this   Lcom/fasterxml/jackson/databind/cfg/MutableConfigOverride;
            0       7     1     v   Lcom/fasterxml/jackson/annotation/JsonInclude$Value;

  public com.fasterxml.jackson.databind.cfg.MutableConfigOverride setIncludeAsProperty(com.fasterxml.jackson.annotation.JsonInclude$Value);
    descriptor: (Lcom/fasterxml/jackson/annotation/JsonInclude$Value;)Lcom/fasterxml/jackson/databind/cfg/MutableConfigOverride;
    flags: (0x0001) ACC_PUBLIC
    Code:
      stack=2, locals=2, args_size=2
         0: aload_0
         1: aload_1
         2: putfield      #7                  // Field _includeAsProperty:Lcom/fasterxml/jackson/annotation/JsonInclude$Value;
         5: aload_0
         6: areturn
      LineNumberTable:
        line 59: 0
        line 60: 5
      LocalVariableTable:
        Start  Length  Slot  Name   Signature
            0       7     0  this   Lcom/fasterxml/jackson/databind/cfg/MutableConfigOverride;
            0       7     1     v   Lcom/fasterxml/jackson/annotation/JsonInclude$Value;

  public com.fasterxml.jackson.databind.cfg.MutableConfigOverride setIgnorals(com.fasterxml.jackson.annotation.JsonIgnoreProperties$Value);
    descriptor: (Lcom/fasterxml/jackson/annotation/JsonIgnoreProperties$Value;)Lcom/fasterxml/jackson/databind/cfg/MutableConfigOverride;
    flags: (0x0001) ACC_PUBLIC
    Code:
      stack=2, locals=2, args_size=2
         0: aload_0
         1: aload_1
         2: putfield      #8                  // Field _ignorals:Lcom/fasterxml/jackson/annotation/JsonIgnoreProperties$Value;
         5: aload_0
         6: areturn
      LineNumberTable:
        line 64: 0
        line 65: 5
      LocalVariableTable:
        Start  Length  Slot  Name   Signature
            0       7     0  this   Lcom/fasterxml/jackson/databind/cfg/MutableConfigOverride;
            0       7     1     v   Lcom/fasterxml/jackson/annotation/JsonIgnoreProperties$Value;

  public com.fasterxml.jackson.databind.cfg.MutableConfigOverride setIsIgnoredType(java.lang.Boolean);
    descriptor: (Ljava/lang/Boolean;)Lcom/fasterxml/jackson/databind/cfg/MutableConfigOverride;
    flags: (0x0001) ACC_PUBLIC
    Code:
      stack=2, locals=2, args_size=2
         0: aload_0
         1: aload_1
         2: putfield      #9                  // Field _isIgnoredType:Ljava/lang/Boolean;
         5: aload_0
         6: areturn
      LineNumberTable:
        line 69: 0
        line 70: 5
      LocalVariableTable:
        Start  Length  Slot  Name   Signature
            0       7     0  this   Lcom/fasterxml/jackson/databind/cfg/MutableConfigOverride;
            0       7     1     v   Ljava/lang/Boolean;

  public com.fasterxml.jackson.databind.cfg.MutableConfigOverride setSetterInfo(com.fasterxml.jackson.annotation.JsonSetter$Value);
    descriptor: (Lcom/fasterxml/jackson/annotation/JsonSetter$Value;)Lcom/fasterxml/jackson/databind/cfg/MutableConfigOverride;
    flags: (0x0001) ACC_PUBLIC
    Code:
      stack=2, locals=2, args_size=2
         0: aload_0
         1: aload_1
         2: putfield      #10                 // Field _setterInfo:Lcom/fasterxml/jackson/annotation/JsonSetter$Value;
         5: aload_0
         6: areturn
      LineNumberTable:
        line 77: 0
        line 78: 5
      LocalVariableTable:
        Start  Length  Slot  Name   Signature
            0       7     0  this   Lcom/fasterxml/jackson/databind/cfg/MutableConfigOverride;
            0       7     1     v   Lcom/fasterxml/jackson/annotation/JsonSetter$Value;

  public com.fasterxml.jackson.databind.cfg.MutableConfigOverride setVisibility(com.fasterxml.jackson.annotation.JsonAutoDetect$Value);
    descriptor: (Lcom/fasterxml/jackson/annotation/JsonAutoDetect$Value;)Lcom/fasterxml/jackson/databind/cfg/MutableConfigOverride;
    flags: (0x0001) ACC_PUBLIC
    Code:
      stack=2, locals=2, args_size=2
         0: aload_0
         1: aload_1
         2: putfield      #11                 // Field _visibility:Lcom/fasterxml/jackson/annotation/JsonAutoDetect$Value;
         5: aload_0
         6: areturn
      LineNumberTable:
        line 85: 0
        line 86: 5
      LocalVariableTable:
        Start  Length  Slot  Name   Signature
            0       7     0  this   Lcom/fasterxml/jackson/databind/cfg/MutableConfigOverride;
            0       7     1     v   Lcom/fasterxml/jackson/annotation/JsonAutoDetect$Value;

  public com.fasterxml.jackson.databind.cfg.MutableConfigOverride setMergeable(java.lang.Boolean);
    descriptor: (Ljava/lang/Boolean;)Lcom/fasterxml/jackson/databind/cfg/MutableConfigOverride;
    flags: (0x0001) ACC_PUBLIC
    Code:
      stack=2, locals=2, args_size=2
         0: aload_0
         1: aload_1
         2: putfield      #12                 // Field _mergeable:Ljava/lang/Boolean;
         5: aload_0
         6: areturn
      LineNumberTable:
        line 93: 0
        line 94: 5
      LocalVariableTable:
        Start  Length  Slot  Name   Signature
            0       7     0  this   Lcom/fasterxml/jackson/databind/cfg/MutableConfigOverride;
            0       7     1     v   Ljava/lang/Boolean;
}
SourceFile: "MutableConfigOverride.java"
InnerClasses:
  public static #33= #32 of #75;          // Value=class com/fasterxml/jackson/annotation/JsonFormat$Value of class com/fasterxml/jackson/annotation/JsonFormat
  public static #33= #39 of #77;          // Value=class com/fasterxml/jackson/annotation/JsonInclude$Value of class com/fasterxml/jackson/annotation/JsonInclude
  public static #33= #44 of #79;          // Value=class com/fasterxml/jackson/annotation/JsonIgnoreProperties$Value of class com/fasterxml/jackson/annotation/JsonIgnoreProperties
  public static #33= #51 of #81;          // Value=class com/fasterxml/jackson/annotation/JsonSetter$Value of class com/fasterxml/jackson/annotation/JsonSetter
  public static #33= #55 of #83;          // Value=class com/fasterxml/jackson/annotation/JsonAutoDetect$Value of class com/fasterxml/jackson/annotation/JsonAutoDetect
