Classfile /Users/mw/Projects/slang-braindump/.jar/jar8/assemble/slang-braindump/assemble/content/coursier/util/shaded/org/jsoup/select/NodeTraversor.class
  Last modified May 29, 2022; size 3442 bytes
  SHA-256 checksum 31581c9a3e2d8f438a4cc4da71adc3da62e2b34b198612b4f88a235661258845
  Compiled from "NodeTraversor.java"
public class coursier.util.shaded.org.jsoup.select.NodeTraversor
  minor version: 0
  major version: 51
  flags: (0x0021) ACC_PUBLIC, ACC_SUPER
  this_class: #2                          // coursier/util/shaded/org/jsoup/select/NodeTraversor
  super_class: #4                         // java/lang/Object
  interfaces: 0, fields: 0, methods: 5, attributes: 2
Constant pool:
    #1 = Utf8               coursier/util/shaded/org/jsoup/select/NodeTraversor
    #2 = Class              #1            // coursier/util/shaded/org/jsoup/select/NodeTraversor
    #3 = Utf8               java/lang/Object
    #4 = Class              #3            // java/lang/Object
    #5 = Utf8               NodeTraversor.java
    #6 = Utf8               coursier/util/shaded/org/jsoup/select/NodeFilter$FilterResult
    #7 = Class              #6            // coursier/util/shaded/org/jsoup/select/NodeFilter$FilterResult
    #8 = Utf8               coursier/util/shaded/org/jsoup/select/NodeFilter
    #9 = Class              #8            // coursier/util/shaded/org/jsoup/select/NodeFilter
   #10 = Utf8               FilterResult
   #11 = Utf8               <init>
   #12 = Utf8               ()V
   #13 = NameAndType        #11:#12       // "<init>":()V
   #14 = Methodref          #4.#13        // java/lang/Object."<init>":()V
   #15 = Utf8               this
   #16 = Utf8               Lcoursier/util/shaded/org/jsoup/select/NodeTraversor;
   #17 = Utf8               traverse
   #18 = Utf8               (Lcoursier/util/shaded/org/jsoup/select/NodeVisitor;Lcoursier/util/shaded/org/jsoup/nodes/Node;)V
   #19 = Utf8               coursier/util/shaded/org/jsoup/nodes/Node
   #20 = Class              #19           // coursier/util/shaded/org/jsoup/nodes/Node
   #21 = Utf8               coursier/util/shaded/org/jsoup/select/NodeVisitor
   #22 = Class              #21           // coursier/util/shaded/org/jsoup/select/NodeVisitor
   #23 = Utf8               head
   #24 = Utf8               (Lcoursier/util/shaded/org/jsoup/nodes/Node;I)V
   #25 = NameAndType        #23:#24       // head:(Lcoursier/util/shaded/org/jsoup/nodes/Node;I)V
   #26 = InterfaceMethodref #22.#25       // coursier/util/shaded/org/jsoup/select/NodeVisitor.head:(Lcoursier/util/shaded/org/jsoup/nodes/Node;I)V
   #27 = Utf8               childNodeSize
   #28 = Utf8               ()I
   #29 = NameAndType        #27:#28       // childNodeSize:()I
   #30 = Methodref          #20.#29       // coursier/util/shaded/org/jsoup/nodes/Node.childNodeSize:()I
   #31 = Utf8               childNode
   #32 = Utf8               (I)Lcoursier/util/shaded/org/jsoup/nodes/Node;
   #33 = NameAndType        #31:#32       // childNode:(I)Lcoursier/util/shaded/org/jsoup/nodes/Node;
   #34 = Methodref          #20.#33       // coursier/util/shaded/org/jsoup/nodes/Node.childNode:(I)Lcoursier/util/shaded/org/jsoup/nodes/Node;
   #35 = Utf8               nextSibling
   #36 = Utf8               ()Lcoursier/util/shaded/org/jsoup/nodes/Node;
   #37 = NameAndType        #35:#36       // nextSibling:()Lcoursier/util/shaded/org/jsoup/nodes/Node;
   #38 = Methodref          #20.#37       // coursier/util/shaded/org/jsoup/nodes/Node.nextSibling:()Lcoursier/util/shaded/org/jsoup/nodes/Node;
   #39 = Utf8               tail
   #40 = NameAndType        #39:#24       // tail:(Lcoursier/util/shaded/org/jsoup/nodes/Node;I)V
   #41 = InterfaceMethodref #22.#40       // coursier/util/shaded/org/jsoup/select/NodeVisitor.tail:(Lcoursier/util/shaded/org/jsoup/nodes/Node;I)V
   #42 = Utf8               parentNode
   #43 = NameAndType        #42:#36       // parentNode:()Lcoursier/util/shaded/org/jsoup/nodes/Node;
   #44 = Methodref          #20.#43       // coursier/util/shaded/org/jsoup/nodes/Node.parentNode:()Lcoursier/util/shaded/org/jsoup/nodes/Node;
   #45 = Utf8               visitor
   #46 = Utf8               Lcoursier/util/shaded/org/jsoup/select/NodeVisitor;
   #47 = Utf8               root
   #48 = Utf8               Lcoursier/util/shaded/org/jsoup/nodes/Node;
   #49 = Utf8               node
   #50 = Utf8               depth
   #51 = Utf8               I
   #52 = Utf8               (Lcoursier/util/shaded/org/jsoup/select/NodeVisitor;Lcoursier/util/shaded/org/jsoup/select/Elements;)V
   #53 = Utf8               coursier/util/shaded/org/jsoup/helper/Validate
   #54 = Class              #53           // coursier/util/shaded/org/jsoup/helper/Validate
   #55 = Utf8               notNull
   #56 = Utf8               (Ljava/lang/Object;)V
   #57 = NameAndType        #55:#56       // notNull:(Ljava/lang/Object;)V
   #58 = Methodref          #54.#57       // coursier/util/shaded/org/jsoup/helper/Validate.notNull:(Ljava/lang/Object;)V
   #59 = Utf8               coursier/util/shaded/org/jsoup/select/Elements
   #60 = Class              #59           // coursier/util/shaded/org/jsoup/select/Elements
   #61 = Utf8               iterator
   #62 = Utf8               ()Ljava/util/Iterator;
   #63 = NameAndType        #61:#62       // iterator:()Ljava/util/Iterator;
   #64 = Methodref          #60.#63       // coursier/util/shaded/org/jsoup/select/Elements.iterator:()Ljava/util/Iterator;
   #65 = Utf8               java/util/Iterator
   #66 = Class              #65           // java/util/Iterator
   #67 = Utf8               hasNext
   #68 = Utf8               ()Z
   #69 = NameAndType        #67:#68       // hasNext:()Z
   #70 = InterfaceMethodref #66.#69       // java/util/Iterator.hasNext:()Z
   #71 = Utf8               next
   #72 = Utf8               ()Ljava/lang/Object;
   #73 = NameAndType        #71:#72       // next:()Ljava/lang/Object;
   #74 = InterfaceMethodref #66.#73       // java/util/Iterator.next:()Ljava/lang/Object;
   #75 = Utf8               coursier/util/shaded/org/jsoup/nodes/Element
   #76 = Class              #75           // coursier/util/shaded/org/jsoup/nodes/Element
   #77 = NameAndType        #17:#18       // traverse:(Lcoursier/util/shaded/org/jsoup/select/NodeVisitor;Lcoursier/util/shaded/org/jsoup/nodes/Node;)V
   #78 = Methodref          #2.#77        // coursier/util/shaded/org/jsoup/select/NodeTraversor.traverse:(Lcoursier/util/shaded/org/jsoup/select/NodeVisitor;Lcoursier/util/shaded/org/jsoup/nodes/Node;)V
   #79 = Utf8               el
   #80 = Utf8               Lcoursier/util/shaded/org/jsoup/nodes/Element;
   #81 = Utf8               elements
   #82 = Utf8               Lcoursier/util/shaded/org/jsoup/select/Elements;
   #83 = Utf8               filter
   #84 = Utf8               (Lcoursier/util/shaded/org/jsoup/select/NodeFilter;Lcoursier/util/shaded/org/jsoup/nodes/Node;)Lcoursier/util/shaded/org/jsoup/select/NodeFilter$FilterResult;
   #85 = Utf8               (Lcoursier/util/shaded/org/jsoup/nodes/Node;I)Lcoursier/util/shaded/org/jsoup/select/NodeFilter$FilterResult;
   #86 = NameAndType        #23:#85       // head:(Lcoursier/util/shaded/org/jsoup/nodes/Node;I)Lcoursier/util/shaded/org/jsoup/select/NodeFilter$FilterResult;
   #87 = InterfaceMethodref #9.#86        // coursier/util/shaded/org/jsoup/select/NodeFilter.head:(Lcoursier/util/shaded/org/jsoup/nodes/Node;I)Lcoursier/util/shaded/org/jsoup/select/NodeFilter$FilterResult;
   #88 = Utf8               STOP
   #89 = Utf8               Lcoursier/util/shaded/org/jsoup/select/NodeFilter$FilterResult;
   #90 = NameAndType        #88:#89       // STOP:Lcoursier/util/shaded/org/jsoup/select/NodeFilter$FilterResult;
   #91 = Fieldref           #7.#90        // coursier/util/shaded/org/jsoup/select/NodeFilter$FilterResult.STOP:Lcoursier/util/shaded/org/jsoup/select/NodeFilter$FilterResult;
   #92 = Utf8               CONTINUE
   #93 = NameAndType        #92:#89       // CONTINUE:Lcoursier/util/shaded/org/jsoup/select/NodeFilter$FilterResult;
   #94 = Fieldref           #7.#93        // coursier/util/shaded/org/jsoup/select/NodeFilter$FilterResult.CONTINUE:Lcoursier/util/shaded/org/jsoup/select/NodeFilter$FilterResult;
   #95 = Utf8               SKIP_CHILDREN
   #96 = NameAndType        #95:#89       // SKIP_CHILDREN:Lcoursier/util/shaded/org/jsoup/select/NodeFilter$FilterResult;
   #97 = Fieldref           #7.#96        // coursier/util/shaded/org/jsoup/select/NodeFilter$FilterResult.SKIP_CHILDREN:Lcoursier/util/shaded/org/jsoup/select/NodeFilter$FilterResult;
   #98 = NameAndType        #39:#85       // tail:(Lcoursier/util/shaded/org/jsoup/nodes/Node;I)Lcoursier/util/shaded/org/jsoup/select/NodeFilter$FilterResult;
   #99 = InterfaceMethodref #9.#98        // coursier/util/shaded/org/jsoup/select/NodeFilter.tail:(Lcoursier/util/shaded/org/jsoup/nodes/Node;I)Lcoursier/util/shaded/org/jsoup/select/NodeFilter$FilterResult;
  #100 = Utf8               REMOVE
  #101 = NameAndType        #100:#89      // REMOVE:Lcoursier/util/shaded/org/jsoup/select/NodeFilter$FilterResult;
  #102 = Fieldref           #7.#101       // coursier/util/shaded/org/jsoup/select/NodeFilter$FilterResult.REMOVE:Lcoursier/util/shaded/org/jsoup/select/NodeFilter$FilterResult;
  #103 = Utf8               remove
  #104 = NameAndType        #103:#12      // remove:()V
  #105 = Methodref          #20.#104      // coursier/util/shaded/org/jsoup/nodes/Node.remove:()V
  #106 = Utf8               prev
  #107 = Utf8               result
  #108 = Utf8               Lcoursier/util/shaded/org/jsoup/select/NodeFilter;
  #109 = Utf8               (Lcoursier/util/shaded/org/jsoup/select/NodeFilter;Lcoursier/util/shaded/org/jsoup/select/Elements;)V
  #110 = NameAndType        #83:#84       // filter:(Lcoursier/util/shaded/org/jsoup/select/NodeFilter;Lcoursier/util/shaded/org/jsoup/nodes/Node;)Lcoursier/util/shaded/org/jsoup/select/NodeFilter$FilterResult;
  #111 = Methodref          #2.#110       // coursier/util/shaded/org/jsoup/select/NodeTraversor.filter:(Lcoursier/util/shaded/org/jsoup/select/NodeFilter;Lcoursier/util/shaded/org/jsoup/nodes/Node;)Lcoursier/util/shaded/org/jsoup/select/NodeFilter$FilterResult;
  #112 = Utf8               Code
  #113 = Utf8               LineNumberTable
  #114 = Utf8               LocalVariableTable
  #115 = Utf8               StackMapTable
  #116 = Utf8               InnerClasses
  #117 = Utf8               SourceFile
{
  public coursier.util.shaded.org.jsoup.select.NodeTraversor();
    descriptor: ()V
    flags: (0x0001) ACC_PUBLIC
    Code:
      stack=1, locals=1, args_size=1
         0: aload_0
         1: invokespecial #14                 // Method java/lang/Object."<init>":()V
         4: return
      LineNumberTable:
        line 14: 0
      LocalVariableTable:
        Start  Length  Slot  Name   Signature
            0       5     0  this   Lcoursier/util/shaded/org/jsoup/select/NodeTraversor;

  public static void traverse(coursier.util.shaded.org.jsoup.select.NodeVisitor, coursier.util.shaded.org.jsoup.nodes.Node);
    descriptor: (Lcoursier/util/shaded/org/jsoup/select/NodeVisitor;Lcoursier/util/shaded/org/jsoup/nodes/Node;)V
    flags: (0x0009) ACC_PUBLIC, ACC_STATIC
    Code:
      stack=3, locals=4, args_size=2
         0: aload_1
         1: astore_2
         2: iconst_0
         3: istore_3
         4: aload_2
         5: ifnull        89
         8: aload_0
         9: aload_2
        10: iload_3
        11: invokeinterface #26,  3           // InterfaceMethod coursier/util/shaded/org/jsoup/select/NodeVisitor.head:(Lcoursier/util/shaded/org/jsoup/nodes/Node;I)V
        16: aload_2
        17: invokevirtual #30                 // Method coursier/util/shaded/org/jsoup/nodes/Node.childNodeSize:()I
        20: ifle          35
        23: aload_2
        24: iconst_0
        25: invokevirtual #34                 // Method coursier/util/shaded/org/jsoup/nodes/Node.childNode:(I)Lcoursier/util/shaded/org/jsoup/nodes/Node;
        28: astore_2
        29: iinc          3, 1
        32: goto          4
        35: aload_2
        36: invokevirtual #38                 // Method coursier/util/shaded/org/jsoup/nodes/Node.nextSibling:()Lcoursier/util/shaded/org/jsoup/nodes/Node;
        39: ifnonnull     65
        42: iload_3
        43: ifle          65
        46: aload_0
        47: aload_2
        48: iload_3
        49: invokeinterface #41,  3           // InterfaceMethod coursier/util/shaded/org/jsoup/select/NodeVisitor.tail:(Lcoursier/util/shaded/org/jsoup/nodes/Node;I)V
        54: aload_2
        55: invokevirtual #44                 // Method coursier/util/shaded/org/jsoup/nodes/Node.parentNode:()Lcoursier/util/shaded/org/jsoup/nodes/Node;
        58: astore_2
        59: iinc          3, -1
        62: goto          35
        65: aload_0
        66: aload_2
        67: iload_3
        68: invokeinterface #41,  3           // InterfaceMethod coursier/util/shaded/org/jsoup/select/NodeVisitor.tail:(Lcoursier/util/shaded/org/jsoup/nodes/Node;I)V
        73: aload_2
        74: aload_1
        75: if_acmpne     81
        78: goto          89
        81: aload_2
        82: invokevirtual #38                 // Method coursier/util/shaded/org/jsoup/nodes/Node.nextSibling:()Lcoursier/util/shaded/org/jsoup/nodes/Node;
        85: astore_2
        86: goto          4
        89: return
      StackMapTable: number_of_entries = 5
        frame_type = 253 /* append */
          offset_delta = 4
          locals = [ class coursier/util/shaded/org/jsoup/nodes/Node, int ]
        frame_type = 30 /* same */
        frame_type = 29 /* same */
        frame_type = 15 /* same */
        frame_type = 7 /* same */
      LineNumberTable:
        line 21: 0
        line 22: 2
        line 24: 4
        line 25: 8
        line 26: 16
        line 27: 23
        line 28: 29
        line 30: 35
        line 31: 46
        line 32: 54
        line 33: 59
        line 35: 65
        line 36: 73
        line 37: 78
        line 38: 81
        line 41: 89
      LocalVariableTable:
        Start  Length  Slot  Name   Signature
            0      90     0 visitor   Lcoursier/util/shaded/org/jsoup/select/NodeVisitor;
            0      90     1  root   Lcoursier/util/shaded/org/jsoup/nodes/Node;
            2      88     2  node   Lcoursier/util/shaded/org/jsoup/nodes/Node;
            4      86     3 depth   I

  public static void traverse(coursier.util.shaded.org.jsoup.select.NodeVisitor, coursier.util.shaded.org.jsoup.select.Elements);
    descriptor: (Lcoursier/util/shaded/org/jsoup/select/NodeVisitor;Lcoursier/util/shaded/org/jsoup/select/Elements;)V
    flags: (0x0009) ACC_PUBLIC, ACC_STATIC
    Code:
      stack=2, locals=4, args_size=2
         0: aload_0
         1: invokestatic  #58                 // Method coursier/util/shaded/org/jsoup/helper/Validate.notNull:(Ljava/lang/Object;)V
         4: aload_1
         5: invokestatic  #58                 // Method coursier/util/shaded/org/jsoup/helper/Validate.notNull:(Ljava/lang/Object;)V
         8: aload_1
         9: invokevirtual #64                 // Method coursier/util/shaded/org/jsoup/select/Elements.iterator:()Ljava/util/Iterator;
        12: astore_2
        13: aload_2
        14: invokeinterface #70,  1           // InterfaceMethod java/util/Iterator.hasNext:()Z
        19: ifeq          40
        22: aload_2
        23: invokeinterface #74,  1           // InterfaceMethod java/util/Iterator.next:()Ljava/lang/Object;
        28: checkcast     #76                 // class coursier/util/shaded/org/jsoup/nodes/Element
        31: astore_3
        32: aload_0
        33: aload_3
        34: invokestatic  #78                 // Method traverse:(Lcoursier/util/shaded/org/jsoup/select/NodeVisitor;Lcoursier/util/shaded/org/jsoup/nodes/Node;)V
        37: goto          13
        40: return
      StackMapTable: number_of_entries = 2
        frame_type = 252 /* append */
          offset_delta = 13
          locals = [ class java/util/Iterator ]
        frame_type = 250 /* chop */
          offset_delta = 26
      LineNumberTable:
        line 49: 0
        line 50: 4
        line 51: 8
        line 52: 32
        line 53: 40
      LocalVariableTable:
        Start  Length  Slot  Name   Signature
           32       5     3    el   Lcoursier/util/shaded/org/jsoup/nodes/Element;
            0      41     0 visitor   Lcoursier/util/shaded/org/jsoup/select/NodeVisitor;
            0      41     1 elements   Lcoursier/util/shaded/org/jsoup/select/Elements;

  public static coursier.util.shaded.org.jsoup.select.NodeFilter$FilterResult filter(coursier.util.shaded.org.jsoup.select.NodeFilter, coursier.util.shaded.org.jsoup.nodes.Node);
    descriptor: (Lcoursier/util/shaded/org/jsoup/select/NodeFilter;Lcoursier/util/shaded/org/jsoup/nodes/Node;)Lcoursier/util/shaded/org/jsoup/select/NodeFilter$FilterResult;
    flags: (0x0009) ACC_PUBLIC, ACC_STATIC
    Code:
      stack=3, locals=6, args_size=2
         0: aload_1
         1: astore_2
         2: iconst_0
         3: istore_3
         4: aload_2
         5: ifnull        205
         8: aload_0
         9: aload_2
        10: iload_3
        11: invokeinterface #87,  3           // InterfaceMethod coursier/util/shaded/org/jsoup/select/NodeFilter.head:(Lcoursier/util/shaded/org/jsoup/nodes/Node;I)Lcoursier/util/shaded/org/jsoup/select/NodeFilter$FilterResult;
        16: astore        4
        18: aload         4
        20: getstatic     #91                 // Field coursier/util/shaded/org/jsoup/select/NodeFilter$FilterResult.STOP:Lcoursier/util/shaded/org/jsoup/select/NodeFilter$FilterResult;
        23: if_acmpne     29
        26: aload         4
        28: areturn
        29: aload         4
        31: getstatic     #94                 // Field coursier/util/shaded/org/jsoup/select/NodeFilter$FilterResult.CONTINUE:Lcoursier/util/shaded/org/jsoup/select/NodeFilter$FilterResult;
        34: if_acmpne     56
        37: aload_2
        38: invokevirtual #30                 // Method coursier/util/shaded/org/jsoup/nodes/Node.childNodeSize:()I
        41: ifle          56
        44: aload_2
        45: iconst_0
        46: invokevirtual #34                 // Method coursier/util/shaded/org/jsoup/nodes/Node.childNode:(I)Lcoursier/util/shaded/org/jsoup/nodes/Node;
        49: astore_2
        50: iinc          3, 1
        53: goto          4
        56: aload_2
        57: invokevirtual #38                 // Method coursier/util/shaded/org/jsoup/nodes/Node.nextSibling:()Lcoursier/util/shaded/org/jsoup/nodes/Node;
        60: ifnonnull     136
        63: iload_3
        64: ifle          136
        67: aload         4
        69: getstatic     #94                 // Field coursier/util/shaded/org/jsoup/select/NodeFilter$FilterResult.CONTINUE:Lcoursier/util/shaded/org/jsoup/select/NodeFilter$FilterResult;
        72: if_acmpeq     83
        75: aload         4
        77: getstatic     #97                 // Field coursier/util/shaded/org/jsoup/select/NodeFilter$FilterResult.SKIP_CHILDREN:Lcoursier/util/shaded/org/jsoup/select/NodeFilter$FilterResult;
        80: if_acmpne     104
        83: aload_0
        84: aload_2
        85: iload_3
        86: invokeinterface #99,  3           // InterfaceMethod coursier/util/shaded/org/jsoup/select/NodeFilter.tail:(Lcoursier/util/shaded/org/jsoup/nodes/Node;I)Lcoursier/util/shaded/org/jsoup/select/NodeFilter$FilterResult;
        91: astore        4
        93: aload         4
        95: getstatic     #91                 // Field coursier/util/shaded/org/jsoup/select/NodeFilter$FilterResult.STOP:Lcoursier/util/shaded/org/jsoup/select/NodeFilter$FilterResult;
        98: if_acmpne     104
       101: aload         4
       103: areturn
       104: aload_2
       105: astore        5
       107: aload_2
       108: invokevirtual #44                 // Method coursier/util/shaded/org/jsoup/nodes/Node.parentNode:()Lcoursier/util/shaded/org/jsoup/nodes/Node;
       111: astore_2
       112: iinc          3, -1
       115: aload         4
       117: getstatic     #102                // Field coursier/util/shaded/org/jsoup/select/NodeFilter$FilterResult.REMOVE:Lcoursier/util/shaded/org/jsoup/select/NodeFilter$FilterResult;
       120: if_acmpne     128
       123: aload         5
       125: invokevirtual #105                // Method coursier/util/shaded/org/jsoup/nodes/Node.remove:()V
       128: getstatic     #94                 // Field coursier/util/shaded/org/jsoup/select/NodeFilter$FilterResult.CONTINUE:Lcoursier/util/shaded/org/jsoup/select/NodeFilter$FilterResult;
       131: astore        4
       133: goto          56
       136: aload         4
       138: getstatic     #94                 // Field coursier/util/shaded/org/jsoup/select/NodeFilter$FilterResult.CONTINUE:Lcoursier/util/shaded/org/jsoup/select/NodeFilter$FilterResult;
       141: if_acmpeq     152
       144: aload         4
       146: getstatic     #97                 // Field coursier/util/shaded/org/jsoup/select/NodeFilter$FilterResult.SKIP_CHILDREN:Lcoursier/util/shaded/org/jsoup/select/NodeFilter$FilterResult;
       149: if_acmpne     173
       152: aload_0
       153: aload_2
       154: iload_3
       155: invokeinterface #99,  3           // InterfaceMethod coursier/util/shaded/org/jsoup/select/NodeFilter.tail:(Lcoursier/util/shaded/org/jsoup/nodes/Node;I)Lcoursier/util/shaded/org/jsoup/select/NodeFilter$FilterResult;
       160: astore        4
       162: aload         4
       164: getstatic     #91                 // Field coursier/util/shaded/org/jsoup/select/NodeFilter$FilterResult.STOP:Lcoursier/util/shaded/org/jsoup/select/NodeFilter$FilterResult;
       167: if_acmpne     173
       170: aload         4
       172: areturn
       173: aload_2
       174: aload_1
       175: if_acmpne     181
       178: aload         4
       180: areturn
       181: aload_2
       182: astore        5
       184: aload_2
       185: invokevirtual #38                 // Method coursier/util/shaded/org/jsoup/nodes/Node.nextSibling:()Lcoursier/util/shaded/org/jsoup/nodes/Node;
       188: astore_2
       189: aload         4
       191: getstatic     #102                // Field coursier/util/shaded/org/jsoup/select/NodeFilter$FilterResult.REMOVE:Lcoursier/util/shaded/org/jsoup/select/NodeFilter$FilterResult;
       194: if_acmpne     202
       197: aload         5
       199: invokevirtual #105                // Method coursier/util/shaded/org/jsoup/nodes/Node.remove:()V
       202: goto          4
       205: getstatic     #94                 // Field coursier/util/shaded/org/jsoup/select/NodeFilter$FilterResult.CONTINUE:Lcoursier/util/shaded/org/jsoup/select/NodeFilter$FilterResult;
       208: areturn
      StackMapTable: number_of_entries = 12
        frame_type = 253 /* append */
          offset_delta = 4
          locals = [ class coursier/util/shaded/org/jsoup/nodes/Node, int ]
        frame_type = 252 /* append */
          offset_delta = 24
          locals = [ class coursier/util/shaded/org/jsoup/select/NodeFilter$FilterResult ]
        frame_type = 26 /* same */
        frame_type = 26 /* same */
        frame_type = 20 /* same */
        frame_type = 252 /* append */
          offset_delta = 23
          locals = [ class coursier/util/shaded/org/jsoup/nodes/Node ]
        frame_type = 250 /* chop */
          offset_delta = 7
        frame_type = 15 /* same */
        frame_type = 20 /* same */
        frame_type = 7 /* same */
        frame_type = 250 /* chop */
          offset_delta = 20
        frame_type = 2 /* same */
      LineNumberTable:
        line 62: 0
        line 63: 2
        line 65: 4
        line 66: 8
        line 67: 18
        line 68: 26
        line 70: 29
        line 71: 44
        line 72: 50
        line 73: 53
        line 76: 56
        line 78: 67
        line 79: 83
        line 80: 93
        line 81: 101
        line 83: 104
        line 84: 107
        line 85: 112
        line 86: 115
        line 87: 123
        line 88: 128
        line 89: 133
        line 91: 136
        line 92: 152
        line 93: 162
        line 94: 170
        line 96: 173
        line 97: 178
        line 98: 181
        line 99: 184
        line 100: 189
        line 101: 197
        line 102: 202
        line 104: 205
      LocalVariableTable:
        Start  Length  Slot  Name   Signature
          107      26     5  prev   Lcoursier/util/shaded/org/jsoup/nodes/Node;
           18     184     4 result   Lcoursier/util/shaded/org/jsoup/select/NodeFilter$FilterResult;
          184      18     5  prev   Lcoursier/util/shaded/org/jsoup/nodes/Node;
            0     209     0 filter   Lcoursier/util/shaded/org/jsoup/select/NodeFilter;
            0     209     1  root   Lcoursier/util/shaded/org/jsoup/nodes/Node;
            2     207     2  node   Lcoursier/util/shaded/org/jsoup/nodes/Node;
            4     205     3 depth   I

  public static void filter(coursier.util.shaded.org.jsoup.select.NodeFilter, coursier.util.shaded.org.jsoup.select.Elements);
    descriptor: (Lcoursier/util/shaded/org/jsoup/select/NodeFilter;Lcoursier/util/shaded/org/jsoup/select/Elements;)V
    flags: (0x0009) ACC_PUBLIC, ACC_STATIC
    Code:
      stack=2, locals=4, args_size=2
         0: aload_0
         1: invokestatic  #58                 // Method coursier/util/shaded/org/jsoup/helper/Validate.notNull:(Ljava/lang/Object;)V
         4: aload_1
         5: invokestatic  #58                 // Method coursier/util/shaded/org/jsoup/helper/Validate.notNull:(Ljava/lang/Object;)V
         8: aload_1
         9: invokevirtual #64                 // Method coursier/util/shaded/org/jsoup/select/Elements.iterator:()Ljava/util/Iterator;
        12: astore_2
        13: aload_2
        14: invokeinterface #70,  1           // InterfaceMethod java/util/Iterator.hasNext:()Z
        19: ifeq          49
        22: aload_2
        23: invokeinterface #74,  1           // InterfaceMethod java/util/Iterator.next:()Ljava/lang/Object;
        28: checkcast     #76                 // class coursier/util/shaded/org/jsoup/nodes/Element
        31: astore_3
        32: aload_0
        33: aload_3
        34: invokestatic  #111                // Method filter:(Lcoursier/util/shaded/org/jsoup/select/NodeFilter;Lcoursier/util/shaded/org/jsoup/nodes/Node;)Lcoursier/util/shaded/org/jsoup/select/NodeFilter$FilterResult;
        37: getstatic     #91                 // Field coursier/util/shaded/org/jsoup/select/NodeFilter$FilterResult.STOP:Lcoursier/util/shaded/org/jsoup/select/NodeFilter$FilterResult;
        40: if_acmpne     46
        43: goto          49
        46: goto          13
        49: return
      StackMapTable: number_of_entries = 3
        frame_type = 252 /* append */
          offset_delta = 13
          locals = [ class java/util/Iterator ]
        frame_type = 32 /* same */
        frame_type = 250 /* chop */
          offset_delta = 2
      LineNumberTable:
        line 113: 0
        line 114: 4
        line 115: 8
        line 116: 32
        line 117: 43
        line 116: 46
        line 118: 49
      LocalVariableTable:
        Start  Length  Slot  Name   Signature
           32      14     3    el   Lcoursier/util/shaded/org/jsoup/nodes/Element;
            0      50     0 filter   Lcoursier/util/shaded/org/jsoup/select/NodeFilter;
            0      50     1 elements   Lcoursier/util/shaded/org/jsoup/select/Elements;
}
InnerClasses:
  public static final #10= #7 of #9;      // FilterResult=class coursier/util/shaded/org/jsoup/select/NodeFilter$FilterResult of class coursier/util/shaded/org/jsoup/select/NodeFilter
SourceFile: "NodeTraversor.java"
