Classfile /Users/mw/Projects/slang-braindump/.jar/jar11/assemble/slang-braindump/assemble/content/scala/collection/concurrent/BasicNode.class
  Last modified May 29, 2022; size 349 bytes
  SHA-256 checksum 5501fd883bea43e4b0176d4a03a13623e3cb646a7eddd8e3f8d2fc77900c2557
  Compiled from "BasicNode.java"
public abstract class scala.collection.concurrent.BasicNode
  minor version: 0
  major version: 52
  flags: (0x0421) ACC_PUBLIC, ACC_SUPER, ACC_ABSTRACT
  this_class: #2                          // scala/collection/concurrent/BasicNode
  super_class: #3                         // java/lang/Object
  interfaces: 0, fields: 0, methods: 2, attributes: 1
Constant pool:
   #1 = Methodref          #3.#15         // java/lang/Object."<init>":()V
   #2 = Class              #16            // scala/collection/concurrent/BasicNode
   #3 = Class              #17            // java/lang/Object
   #4 = Utf8               <init>
   #5 = Utf8               ()V
   #6 = Utf8               Code
   #7 = Utf8               LineNumberTable
   #8 = Utf8               LocalVariableTable
   #9 = Utf8               this
  #10 = Utf8               Lscala/collection/concurrent/BasicNode;
  #11 = Utf8               string
  #12 = Utf8               (I)Ljava/lang/String;
  #13 = Utf8               SourceFile
  #14 = Utf8               BasicNode.java
  #15 = NameAndType        #4:#5          // "<init>":()V
  #16 = Utf8               scala/collection/concurrent/BasicNode
  #17 = Utf8               java/lang/Object
{
  public scala.collection.concurrent.BasicNode();
    descriptor: ()V
    flags: (0x0001) ACC_PUBLIC
    Code:
      stack=1, locals=1, args_size=1
         0: aload_0
         1: invokespecial #1                  // Method java/lang/Object."<init>":()V
         4: return
      LineNumberTable:
        line 15: 0
      LocalVariableTable:
        Start  Length  Slot  Name   Signature
            0       5     0  this   Lscala/collection/concurrent/BasicNode;

  public abstract java.lang.String string(int);
    descriptor: (I)Ljava/lang/String;
    flags: (0x0401) ACC_PUBLIC, ACC_ABSTRACT
}
SourceFile: "BasicNode.java"
