Classfile /Users/mw/Projects/slang-braindump/.jar/jar11/assemble/slang-braindump/assemble/content/scala/collection/concurrent/INode$.class
  Last modified May 29, 2022; size 1670 bytes
  SHA-256 checksum 460838b201610dfdcc86cfa35a15c21a611f68cfd083fdff92e02c05c669fad9
  Compiled from "TrieMap.scala"
public final class scala.collection.concurrent.INode$
  minor version: 0
  major version: 52
  flags: (0x0031) ACC_PUBLIC, ACC_FINAL, ACC_SUPER
  this_class: #2                          // scala/collection/concurrent/INode$
  super_class: #4                         // java/lang/Object
  interfaces: 0, fields: 4, methods: 6, attributes: 3
Constant pool:
   #1 = Utf8               scala/collection/concurrent/INode$
   #2 = Class              #1             // scala/collection/concurrent/INode$
   #3 = Utf8               java/lang/Object
   #4 = Class              #3             // java/lang/Object
   #5 = Utf8               TrieMap.scala
   #6 = Utf8               MODULE$
   #7 = Utf8               Lscala/collection/concurrent/INode$;
   #8 = Utf8               KEY_PRESENT
   #9 = Utf8               Ljava/lang/Object;
  #10 = Utf8               KEY_ABSENT
  #11 = Utf8               KEY_PRESENT_OR_ABSENT
  #12 = Utf8               <clinit>
  #13 = Utf8               ()V
  #14 = Utf8               <init>
  #15 = NameAndType        #14:#13        // "<init>":()V
  #16 = Methodref          #2.#15         // scala/collection/concurrent/INode$."<init>":()V
  #17 = NameAndType        #6:#7          // MODULE$:Lscala/collection/concurrent/INode$;
  #18 = Fieldref           #2.#17         // scala/collection/concurrent/INode$.MODULE$:Lscala/collection/concurrent/INode$;
  #19 = Methodref          #4.#15         // java/lang/Object."<init>":()V
  #20 = NameAndType        #8:#9          // KEY_PRESENT:Ljava/lang/Object;
  #21 = Fieldref           #2.#20         // scala/collection/concurrent/INode$.KEY_PRESENT:Ljava/lang/Object;
  #22 = NameAndType        #10:#9         // KEY_ABSENT:Ljava/lang/Object;
  #23 = Fieldref           #2.#22         // scala/collection/concurrent/INode$.KEY_ABSENT:Ljava/lang/Object;
  #24 = NameAndType        #11:#9         // KEY_PRESENT_OR_ABSENT:Ljava/lang/Object;
  #25 = Fieldref           #2.#24         // scala/collection/concurrent/INode$.KEY_PRESENT_OR_ABSENT:Ljava/lang/Object;
  #26 = Utf8               ()Ljava/lang/Object;
  #27 = Utf8               this
  #28 = Utf8               newRootNode
  #29 = Utf8               (Lscala/math/Equiv;)Lscala/collection/concurrent/INode;
  #30 = Utf8               <K:Ljava/lang/Object;V:Ljava/lang/Object;>(Lscala/math/Equiv<TK;>;)Lscala/collection/concurrent/INode<TK;TV;>;
  #31 = Utf8               equiv
  #32 = Utf8               scala/collection/concurrent/Gen
  #33 = Class              #32            // scala/collection/concurrent/Gen
  #34 = Methodref          #33.#15        // scala/collection/concurrent/Gen."<init>":()V
  #35 = Utf8               scala/collection/concurrent/CNode
  #36 = Class              #35            // scala/collection/concurrent/CNode
  #37 = Utf8               scala/collection/concurrent/BasicNode
  #38 = Class              #37            // scala/collection/concurrent/BasicNode
  #39 = Utf8               (I[Lscala/collection/concurrent/BasicNode;Lscala/collection/concurrent/Gen;)V
  #40 = NameAndType        #14:#39        // "<init>":(I[Lscala/collection/concurrent/BasicNode;Lscala/collection/concurrent/Gen;)V
  #41 = Methodref          #36.#40        // scala/collection/concurrent/CNode."<init>":(I[Lscala/collection/concurrent/BasicNode;Lscala/collection/concurrent/Gen;)V
  #42 = Utf8               scala/collection/concurrent/INode
  #43 = Class              #42            // scala/collection/concurrent/INode
  #44 = Utf8               (Lscala/collection/concurrent/MainNode;Lscala/collection/concurrent/Gen;Lscala/math/Equiv;)V
  #45 = NameAndType        #14:#44        // "<init>":(Lscala/collection/concurrent/MainNode;Lscala/collection/concurrent/Gen;Lscala/math/Equiv;)V
  #46 = Methodref          #43.#45        // scala/collection/concurrent/INode."<init>":(Lscala/collection/concurrent/MainNode;Lscala/collection/concurrent/Gen;Lscala/math/Equiv;)V
  #47 = Utf8               gen
  #48 = Utf8               Lscala/collection/concurrent/Gen;
  #49 = Utf8               cn
  #50 = Utf8               Lscala/collection/concurrent/CNode;
  #51 = Utf8               Lscala/math/Equiv;
  #52 = Utf8               Code
  #53 = Utf8               LineNumberTable
  #54 = Utf8               LocalVariableTable
  #55 = Utf8               Signature
  #56 = Utf8               MethodParameters
  #57 = Utf8               SourceFile
  #58 = Utf8               ScalaInlineInfo
  #59 = Utf8               Scala
{
  public static final scala.collection.concurrent.INode$ MODULE$;
    descriptor: Lscala/collection/concurrent/INode$;
    flags: (0x0019) ACC_PUBLIC, ACC_STATIC, ACC_FINAL

  private static final java.lang.Object KEY_PRESENT;
    descriptor: Ljava/lang/Object;
    flags: (0x001a) ACC_PRIVATE, ACC_STATIC, ACC_FINAL

  private static final java.lang.Object KEY_ABSENT;
    descriptor: Ljava/lang/Object;
    flags: (0x001a) ACC_PRIVATE, ACC_STATIC, ACC_FINAL

  private static final java.lang.Object KEY_PRESENT_OR_ABSENT;
    descriptor: Ljava/lang/Object;
    flags: (0x001a) ACC_PRIVATE, ACC_STATIC, ACC_FINAL

  public static {};
    descriptor: ()V
    flags: (0x0009) ACC_PUBLIC, ACC_STATIC
    Code:
      stack=2, locals=0, args_size=0
         0: new           #2                  // class scala/collection/concurrent/INode$
         3: dup
         4: invokespecial #16                 // Method "<init>":()V
         7: putstatic     #18                 // Field MODULE$:Lscala/collection/concurrent/INode$;
        10: new           #4                  // class java/lang/Object
        13: dup
        14: invokespecial #19                 // Method java/lang/Object."<init>":()V
        17: putstatic     #21                 // Field KEY_PRESENT:Ljava/lang/Object;
        20: new           #4                  // class java/lang/Object
        23: dup
        24: invokespecial #19                 // Method java/lang/Object."<init>":()V
        27: putstatic     #23                 // Field KEY_ABSENT:Ljava/lang/Object;
        30: new           #4                  // class java/lang/Object
        33: dup
        34: invokespecial #19                 // Method java/lang/Object."<init>":()V
        37: putstatic     #25                 // Field KEY_PRESENT_OR_ABSENT:Ljava/lang/Object;
        40: return
      LineNumberTable:
        line 421: 0
        line 425: 10
        line 426: 20
        line 427: 30
        line 421: 40

  public final java.lang.Object KEY_PRESENT();
    descriptor: ()Ljava/lang/Object;
    flags: (0x0011) ACC_PUBLIC, ACC_FINAL
    Code:
      stack=1, locals=1, args_size=1
         0: getstatic     #21                 // Field KEY_PRESENT:Ljava/lang/Object;
         3: areturn
      LineNumberTable:
        line 425: 0
      LocalVariableTable:
        Start  Length  Slot  Name   Signature
            0       4     0  this   Lscala/collection/concurrent/INode$;

  public final java.lang.Object KEY_ABSENT();
    descriptor: ()Ljava/lang/Object;
    flags: (0x0011) ACC_PUBLIC, ACC_FINAL
    Code:
      stack=1, locals=1, args_size=1
         0: getstatic     #23                 // Field KEY_ABSENT:Ljava/lang/Object;
         3: areturn
      LineNumberTable:
        line 426: 0
      LocalVariableTable:
        Start  Length  Slot  Name   Signature
            0       4     0  this   Lscala/collection/concurrent/INode$;

  public final java.lang.Object KEY_PRESENT_OR_ABSENT();
    descriptor: ()Ljava/lang/Object;
    flags: (0x0011) ACC_PUBLIC, ACC_FINAL
    Code:
      stack=1, locals=1, args_size=1
         0: getstatic     #25                 // Field KEY_PRESENT_OR_ABSENT:Ljava/lang/Object;
         3: areturn
      LineNumberTable:
        line 427: 0
      LocalVariableTable:
        Start  Length  Slot  Name   Signature
            0       4     0  this   Lscala/collection/concurrent/INode$;

  public <K extends java.lang.Object, V extends java.lang.Object> scala.collection.concurrent.INode<K, V> newRootNode(scala.math.Equiv<K>);
    descriptor: (Lscala/math/Equiv;)Lscala/collection/concurrent/INode;
    flags: (0x0001) ACC_PUBLIC
    Code:
      stack=5, locals=4, args_size=2
         0: new           #33                 // class scala/collection/concurrent/Gen
         3: dup
         4: invokespecial #34                 // Method scala/collection/concurrent/Gen."<init>":()V
         7: astore_2
         8: new           #36                 // class scala/collection/concurrent/CNode
        11: dup
        12: iconst_0
        13: iconst_0
        14: anewarray     #38                 // class scala/collection/concurrent/BasicNode
        17: aload_2
        18: invokespecial #41                 // Method scala/collection/concurrent/CNode."<init>":(I[Lscala/collection/concurrent/BasicNode;Lscala/collection/concurrent/Gen;)V
        21: astore_3
        22: new           #43                 // class scala/collection/concurrent/INode
        25: dup
        26: aload_3
        27: aload_2
        28: aload_1
        29: invokespecial #46                 // Method scala/collection/concurrent/INode."<init>":(Lscala/collection/concurrent/MainNode;Lscala/collection/concurrent/Gen;Lscala/math/Equiv;)V
        32: areturn
      LineNumberTable:
        line 430: 0
        line 431: 8
        line 432: 22
      LocalVariableTable:
        Start  Length  Slot  Name   Signature
            8      24     2   gen   Lscala/collection/concurrent/Gen;
           22      10     3    cn   Lscala/collection/concurrent/CNode;
            0      33     0  this   Lscala/collection/concurrent/INode$;
            0      33     1 equiv   Lscala/math/Equiv;
    Signature: #30                          // <K:Ljava/lang/Object;V:Ljava/lang/Object;>(Lscala/math/Equiv<TK;>;)Lscala/collection/concurrent/INode<TK;TV;>;
    MethodParameters:
      Name                           Flags
      equiv                          final

  private scala.collection.concurrent.INode$();
    descriptor: ()V
    flags: (0x0002) ACC_PRIVATE
    Code:
      stack=1, locals=1, args_size=1
         0: aload_0
         1: invokespecial #19                 // Method java/lang/Object."<init>":()V
         4: return
      LineNumberTable:
        line 421: 0
      LocalVariableTable:
        Start  Length  Slot  Name   Signature
            0       5     0  this   Lscala/collection/concurrent/INode$;
}
SourceFile: "TrieMap.scala"
  ScalaInlineInfo: length = 0x1D (unknown attribute)
   01 01 00 05 00 0E 00 0D 01 00 0A 00 1A 01 00 08
   00 1A 01 00 0B 00 1A 01 00 1C 00 1D 01
  Scala: length = 0x0 (unknown attribute)

