Classfile /Users/mw/Projects/slang-braindump/.jar/jar11/assemble/slang-braindump/assemble/content/scala/collection/concurrent/Map.class
  Last modified May 29, 2022; size 6834 bytes
  SHA-256 checksum 744e5af7e2b75be88ac7cdcda54ab1ec0f7f1ef75ff69628203e3eed58367b8f
  Compiled from "Map.scala"
public interface scala.collection.concurrent.Map<K extends java.lang.Object, V extends java.lang.Object> extends scala.collection.mutable.Map<K, V>
  minor version: 0
  major version: 52
  flags: (0x0601) ACC_PUBLIC, ACC_INTERFACE, ACC_ABSTRACT
  this_class: #2                          // scala/collection/concurrent/Map
  super_class: #5                         // java/lang/Object
  interfaces: 1, fields: 0, methods: 18, attributes: 5
Constant pool:
    #1 = Utf8               scala/collection/concurrent/Map
    #2 = Class              #1            // scala/collection/concurrent/Map
    #3 = Utf8               <K:Ljava/lang/Object;V:Ljava/lang/Object;>Ljava/lang/Object;Lscala/collection/mutable/Map<TK;TV;>;
    #4 = Utf8               java/lang/Object
    #5 = Class              #4            // java/lang/Object
    #6 = Utf8               scala/collection/mutable/Map
    #7 = Class              #6            // scala/collection/mutable/Map
    #8 = Utf8               Map.scala
    #9 = Utf8               Lscala/reflect/ScalaSignature;
   #10 = Utf8               bytes
   #11 = Utf8               \u0006\u0005\u0005\u001daaB\u0007\u000f!\u0003\r\t!\u0006\u0005\u0006]\u0001!\ta\f\u0005\u0006g\u00011\t\u0001\u000e\u0005\u0006y\u00011\t!\u0010\u0005\u0006\u0007\u00021\t\u0001\u0012\u0005\u0006\u0007\u00021\tA\u0013\u0005\u0006\u001b\u0002!\tE\u0014\u0005\u0007-\u0002!\t\u0001E,\t\ri\u0003A\u0011\u0001\t\\\u0011\u0015\t\u0007\u0001\"\u0011c\u0011\u0015Q\u0007\u0001\"\u0003l\u0011\u00191\b\u0001\"\u0001\u0011o\"1a\u0010\u0001C\u0001!}\u00141!T1q\u0015\ty\u0001#\u0001\u0006d_:\u001cWO\u001d:f]RT!!\u0005\n\u0002\u0015\r|G\u000e\\3di&|gNC\u0001\u0014\u0003\u0015\u00198-\u00197b\u0007\u0001)2A\u0006\u0012-\'\r\u0001qc\u0007\t\u00031ei\u0011AE\u0005\u00035I\u0011a!\u00118z%\u00164\u0007\u0003\u0002\u000f A-j\u0011!\b\u0006\u0003=A\tq!\\;uC\ndW-\u0003\u0002\u000e;A\u0011\u0011E\t\u0007\u0001\t\u0015\u0019\u0003A1\u0001%\u0005\u0005Y\u0015CA\u0013)!\tAb%\u0003\u0002(%\t9aj\u001c;iS:<\u0007C\u0001\r*\u0013\tQ#CA\u0002B]f\u0004\"!\t\u0017\u0005\u000b5\u0002!\u0019\u0001\u0013\u0003\u0003Y\u000ba\u0001J5oSR$C#\u0001\u0019\u0011\u0005a\t\u0014B\u0001\u001a\u0013\u0005\u0011)f.\u001b;\u0002\u0017A,H/\u00134BEN,g\u000e\u001e\u000b\u0004kaR\u0004c\u0001\r7W%\u0011qG\u0005\u0002\u0007\u001fB$\u0018n\u001c8\t\u000be\u0012\u0001\u0019\u0001\u0011\u0002\u0003-DQa\u000f\u0002A\u0002-\n\u0011A^\u0001\u0007e\u0016lwN^3\u0015\u0007y\n%\t\u0005\u0002\u0019\u007f%\u0011\u0001I\u0005\u0002\b\u0005>|G.Z1o\u0011\u0015I4\u00011\u0001!\u0011\u0015Y4\u00011\u0001,\u0003\u001d\u0011X\r\u001d7bG\u0016$BAP#G\u0011\")\u0011\b\u0002a\u0001A!)q\t\u0002a\u0001W\u0005Aq\u000e\u001c3wC2,X\rC\u0003J\t\u0001\u00071&\u0001\u0005oK^4\u0018\r\\;f)\r)4\n\u0014\u0005\u0006s\u0015\u0001\r\u0001\t\u0005\u0006w\u0015\u0001\raK\u0001\u0010O\u0016$xJ]#mg\u0016,\u0006\u000fZ1uKR\u00191fT)\t\u000bA3\u0001\u0019\u0001\u0011\u0002\u0007-,\u0017\u0010\u0003\u0004S\r\u0011\u0005\raU\u0001\u0003_B\u00042\u0001\u0007+,\u0013\t)&C\u0001\u0005=Eft\u0017-\\3?\u0003-\u0011X-\\8wKJ+g-R9\u0015\u0007yB\u0016\fC\u0003:\u000f\u0001\u0007\u0001\u0005C\u0003<\u000f\u0001\u00071&\u0001\u0007sKBd\u0017mY3SK\u001a,\u0015\u000f\u0006\u0003?9v{\u0006\"B\u001d\t\u0001\u0004\u0001\u0003\"\u00020\t\u0001\u0004Y\u0013\u0001C8mIZ\u000bG.^3\t\u000b\u0001D\u0001\u0019A\u0016\u0002\u00119,wOV1mk\u0016\f!\"\u001e9eCR,w+\u001b;i)\t\u0019\u0017\u000e\u0006\u00026I\")Q-\u0003a\u0001M\u0006\t\"/Z7baBLgn\u001a$v]\u000e$\u0018n\u001c8\u0011\ta9W\'N\u0005\u0003QJ\u0011\u0011BR;oGRLwN\\\u0019\t\u000bAK\u0001\u0019\u0001\u0011\u0002\u001bU\u0004H-\u0019;f/&$\b.Q;y)\tag\u000e\u0006\u00026[\")QM\u0003a\u0001M\")\u0001K\u0003a\u0001A!\u0012!\u0002\u001d\t\u0003cRl\u0011A\u001d\u0006\u0003gJ\t!\"\u00198o_R\fG/[8o\u0013\t)(OA\u0004uC&d\'/Z2\u0002#\u0019LG\u000e^3s\u0013:\u0004F.Y2f\u00136\u0004H\u000e\u0006\u0002ys6\t\u0001\u0001C\u0003{\u0017\u0001\u000710A\u0001q!\u0015AB\u0010I\u0016?\u0013\ti(CA\u0005Gk:\u001cG/[8oe\u0005!R.\u00199WC2,Xm]%o!2\f7-Z%na2$2\u0001_A\u0001\u0011\u001d\t\u0019\u0001\u0004a\u0001\u0003\u000b\t\u0011A\u001a\t\u00061q\u00043f\u000b
   #12 = Utf8               putIfAbsent
   #13 = Utf8               (Ljava/lang/Object;Ljava/lang/Object;)Lscala/Option;
   #14 = Utf8               (TK;TV;)Lscala/Option<TV;>;
   #15 = Utf8               k
   #16 = Utf8               v
   #17 = Utf8               remove
   #18 = Utf8               (Ljava/lang/Object;Ljava/lang/Object;)Z
   #19 = Utf8               (TK;TV;)Z
   #20 = Utf8               replace
   #21 = Utf8               (Ljava/lang/Object;Ljava/lang/Object;Ljava/lang/Object;)Z
   #22 = Utf8               (TK;TV;TV;)Z
   #23 = Utf8               oldvalue
   #24 = Utf8               newvalue
   #25 = Utf8               getOrElseUpdate$
   #26 = Utf8               (Lscala/collection/concurrent/Map;Ljava/lang/Object;Lscala/Function0;)Ljava/lang/Object;
   #27 = Utf8               $this
   #28 = Utf8               key
   #29 = Utf8               op
   #30 = Utf8               getOrElseUpdate
   #31 = Utf8               (Ljava/lang/Object;Lscala/Function0;)Ljava/lang/Object;
   #32 = NameAndType        #30:#31       // getOrElseUpdate:(Ljava/lang/Object;Lscala/Function0;)Ljava/lang/Object;
   #33 = InterfaceMethodref #2.#32        // scala/collection/concurrent/Map.getOrElseUpdate:(Ljava/lang/Object;Lscala/Function0;)Ljava/lang/Object;
   #34 = Utf8               Lscala/collection/concurrent/Map;
   #35 = Utf8               Ljava/lang/Object;
   #36 = Utf8               Lscala/Function0;
   #37 = Utf8               (TK;Lscala/Function0<TV;>;)TV;
   #38 = Utf8               get
   #39 = Utf8               (Ljava/lang/Object;)Lscala/Option;
   #40 = NameAndType        #38:#39       // get:(Ljava/lang/Object;)Lscala/Option;
   #41 = InterfaceMethodref #2.#40        // scala/collection/concurrent/Map.get:(Ljava/lang/Object;)Lscala/Option;
   #42 = Utf8               scala/Some
   #43 = Class              #42           // scala/Some
   #44 = Utf8               value
   #45 = Utf8               ()Ljava/lang/Object;
   #46 = NameAndType        #44:#45       // value:()Ljava/lang/Object;
   #47 = Methodref          #43.#46       // scala/Some.value:()Ljava/lang/Object;
   #48 = Utf8               scala/None$
   #49 = Class              #48           // scala/None$
   #50 = Utf8               MODULE$
   #51 = Utf8               Lscala/None$;
   #52 = NameAndType        #50:#51       // MODULE$:Lscala/None$;
   #53 = Fieldref           #49.#52       // scala/None$.MODULE$:Lscala/None$;
   #54 = Utf8               equals
   #55 = Utf8               (Ljava/lang/Object;)Z
   #56 = NameAndType        #54:#55       // equals:(Ljava/lang/Object;)Z
   #57 = Methodref          #5.#56        // java/lang/Object.equals:(Ljava/lang/Object;)Z
   #58 = Utf8               scala/Function0
   #59 = Class              #58           // scala/Function0
   #60 = Utf8               apply
   #61 = NameAndType        #60:#45       // apply:()Ljava/lang/Object;
   #62 = InterfaceMethodref #59.#61       // scala/Function0.apply:()Ljava/lang/Object;
   #63 = NameAndType        #12:#13       // putIfAbsent:(Ljava/lang/Object;Ljava/lang/Object;)Lscala/Option;
   #64 = InterfaceMethodref #2.#63        // scala/collection/concurrent/Map.putIfAbsent:(Ljava/lang/Object;Ljava/lang/Object;)Lscala/Option;
   #65 = Utf8               scala/MatchError
   #66 = Class              #65           // scala/MatchError
   #67 = Utf8               <init>
   #68 = Utf8               (Ljava/lang/Object;)V
   #69 = NameAndType        #67:#68       // "<init>":(Ljava/lang/Object;)V
   #70 = Methodref          #66.#69       // scala/MatchError."<init>":(Ljava/lang/Object;)V
   #71 = Utf8               this
   #72 = Utf8               scala/Option
   #73 = Class              #72           // scala/Option
   #74 = Utf8               removeRefEq$
   #75 = Utf8               (Lscala/collection/concurrent/Map;Ljava/lang/Object;Ljava/lang/Object;)Z
   #76 = Utf8               removeRefEq
   #77 = NameAndType        #76:#18       // removeRefEq:(Ljava/lang/Object;Ljava/lang/Object;)Z
   #78 = InterfaceMethodref #2.#77        // scala/collection/concurrent/Map.removeRefEq:(Ljava/lang/Object;Ljava/lang/Object;)Z
   #79 = NameAndType        #17:#18       // remove:(Ljava/lang/Object;Ljava/lang/Object;)Z
   #80 = InterfaceMethodref #2.#79        // scala/collection/concurrent/Map.remove:(Ljava/lang/Object;Ljava/lang/Object;)Z
   #81 = Utf8               replaceRefEq$
   #82 = Utf8               (Lscala/collection/concurrent/Map;Ljava/lang/Object;Ljava/lang/Object;Ljava/lang/Object;)Z
   #83 = Utf8               oldValue
   #84 = Utf8               newValue
   #85 = Utf8               replaceRefEq
   #86 = NameAndType        #85:#21       // replaceRefEq:(Ljava/lang/Object;Ljava/lang/Object;Ljava/lang/Object;)Z
   #87 = InterfaceMethodref #2.#86        // scala/collection/concurrent/Map.replaceRefEq:(Ljava/lang/Object;Ljava/lang/Object;Ljava/lang/Object;)Z
   #88 = NameAndType        #20:#21       // replace:(Ljava/lang/Object;Ljava/lang/Object;Ljava/lang/Object;)Z
   #89 = InterfaceMethodref #2.#88        // scala/collection/concurrent/Map.replace:(Ljava/lang/Object;Ljava/lang/Object;Ljava/lang/Object;)Z
   #90 = Utf8               updateWith$
   #91 = Utf8               (Lscala/collection/concurrent/Map;Ljava/lang/Object;Lscala/Function1;)Lscala/Option;
   #92 = Utf8               remappingFunction
   #93 = Utf8               updateWith
   #94 = Utf8               (Ljava/lang/Object;Lscala/Function1;)Lscala/Option;
   #95 = NameAndType        #93:#94       // updateWith:(Ljava/lang/Object;Lscala/Function1;)Lscala/Option;
   #96 = InterfaceMethodref #2.#95        // scala/collection/concurrent/Map.updateWith:(Ljava/lang/Object;Lscala/Function1;)Lscala/Option;
   #97 = Utf8               Lscala/Function1;
   #98 = Utf8               (TK;Lscala/Function1<Lscala/Option<TV;>;Lscala/Option<TV;>;>;)Lscala/Option<TV;>;
   #99 = Utf8               scala/Function1
  #100 = Class              #99           // scala/Function1
  #101 = Utf8               (Ljava/lang/Object;)Ljava/lang/Object;
  #102 = NameAndType        #60:#101      // apply:(Ljava/lang/Object;)Ljava/lang/Object;
  #103 = InterfaceMethodref #100.#102     // scala/Function1.apply:(Ljava/lang/Object;)Ljava/lang/Object;
  #104 = Utf8               isEmpty
  #105 = Utf8               ()Z
  #106 = NameAndType        #104:#105     // isEmpty:()Z
  #107 = Methodref          #73.#106      // scala/Option.isEmpty:()Z
  #108 = Utf8               updateWithAux_next
  #109 = Utf8               updateWithAux_prev
  #110 = Utf8               updateWithAux_previousValue
  #111 = Utf8               Lscala/Option;
  #112 = Utf8               updateWithAux_nextValue
  #113 = Utf8               updateWithAux
  #114 = Utf8               next
  #115 = Utf8               prev
  #116 = Utf8               previousValue
  #117 = Utf8               nextValue
  #118 = Utf8               filterInPlaceImpl$
  #119 = Utf8               (Lscala/collection/concurrent/Map;Lscala/Function2;)Lscala/collection/concurrent/Map;
  #120 = Utf8               p
  #121 = Utf8               filterInPlaceImpl
  #122 = Utf8               (Lscala/Function2;)Lscala/collection/concurrent/Map;
  #123 = NameAndType        #121:#122     // filterInPlaceImpl:(Lscala/Function2;)Lscala/collection/concurrent/Map;
  #124 = InterfaceMethodref #2.#123       // scala/collection/concurrent/Map.filterInPlaceImpl:(Lscala/Function2;)Lscala/collection/concurrent/Map;
  #125 = Utf8               Lscala/Function2;
  #126 = Utf8               (Lscala/Function2<TK;TV;Ljava/lang/Object;>;)Lscala/collection/concurrent/Map<TK;TV;>;
  #127 = Utf8               iterator
  #128 = Utf8               ()Lscala/collection/Iterator;
  #129 = NameAndType        #127:#128     // iterator:()Lscala/collection/Iterator;
  #130 = InterfaceMethodref #2.#129       // scala/collection/concurrent/Map.iterator:()Lscala/collection/Iterator;
  #131 = Utf8               scala/collection/Iterator
  #132 = Class              #131          // scala/collection/Iterator
  #133 = Utf8               hasNext
  #134 = NameAndType        #133:#105     // hasNext:()Z
  #135 = InterfaceMethodref #132.#134     // scala/collection/Iterator.hasNext:()Z
  #136 = NameAndType        #114:#45      // next:()Ljava/lang/Object;
  #137 = InterfaceMethodref #132.#136     // scala/collection/Iterator.next:()Ljava/lang/Object;
  #138 = Utf8               scala/Tuple2
  #139 = Class              #138          // scala/Tuple2
  #140 = Utf8               _1
  #141 = NameAndType        #140:#45      // _1:()Ljava/lang/Object;
  #142 = Methodref          #139.#141     // scala/Tuple2._1:()Ljava/lang/Object;
  #143 = Utf8               _2
  #144 = NameAndType        #143:#45      // _2:()Ljava/lang/Object;
  #145 = Methodref          #139.#144     // scala/Tuple2._2:()Ljava/lang/Object;
  #146 = Utf8               scala/Function2
  #147 = Class              #146          // scala/Function2
  #148 = Utf8               (Ljava/lang/Object;Ljava/lang/Object;)Ljava/lang/Object;
  #149 = NameAndType        #60:#148      // apply:(Ljava/lang/Object;Ljava/lang/Object;)Ljava/lang/Object;
  #150 = InterfaceMethodref #147.#149     // scala/Function2.apply:(Ljava/lang/Object;Ljava/lang/Object;)Ljava/lang/Object;
  #151 = Utf8               scala/runtime/BoxesRunTime
  #152 = Class              #151          // scala/runtime/BoxesRunTime
  #153 = Utf8               unboxToBoolean
  #154 = NameAndType        #153:#55      // unboxToBoolean:(Ljava/lang/Object;)Z
  #155 = Methodref          #152.#154     // scala/runtime/BoxesRunTime.unboxToBoolean:(Ljava/lang/Object;)Z
  #156 = Utf8               it
  #157 = Utf8               Lscala/collection/Iterator;
  #158 = Utf8               mapValuesInPlaceImpl$
  #159 = Utf8               f
  #160 = Utf8               mapValuesInPlaceImpl
  #161 = NameAndType        #160:#122     // mapValuesInPlaceImpl:(Lscala/Function2;)Lscala/collection/concurrent/Map;
  #162 = InterfaceMethodref #2.#161       // scala/collection/concurrent/Map.mapValuesInPlaceImpl:(Lscala/Function2;)Lscala/collection/concurrent/Map;
  #163 = Utf8               (Lscala/Function2<TK;TV;TV;>;)Lscala/collection/concurrent/Map<TK;TV;>;
  #164 = Utf8               $init$
  #165 = Utf8               (Lscala/collection/concurrent/Map;)V
  #166 = Utf8               Signature
  #167 = Utf8               MethodParameters
  #168 = Utf8               Code
  #169 = Utf8               LineNumberTable
  #170 = Utf8               LocalVariableTable
  #171 = Utf8               StackMapTable
  #172 = Utf8               SourceFile
  #173 = Utf8               RuntimeVisibleAnnotations
  #174 = Utf8               ScalaInlineInfo
  #175 = Utf8               ScalaSig
{
  public abstract scala.Option<V> putIfAbsent(K, V);
    descriptor: (Ljava/lang/Object;Ljava/lang/Object;)Lscala/Option;
    flags: (0x0401) ACC_PUBLIC, ACC_ABSTRACT
    Signature: #14                          // (TK;TV;)Lscala/Option<TV;>;
    MethodParameters:
      Name                           Flags
      k                              final
      v                              final

  public abstract boolean remove(K, V);
    descriptor: (Ljava/lang/Object;Ljava/lang/Object;)Z
    flags: (0x0401) ACC_PUBLIC, ACC_ABSTRACT
    Signature: #19                          // (TK;TV;)Z
    MethodParameters:
      Name                           Flags
      k                              final
      v                              final

  public abstract boolean replace(K, V, V);
    descriptor: (Ljava/lang/Object;Ljava/lang/Object;Ljava/lang/Object;)Z
    flags: (0x0401) ACC_PUBLIC, ACC_ABSTRACT
    Signature: #22                          // (TK;TV;TV;)Z
    MethodParameters:
      Name                           Flags
      k                              final
      oldvalue                       final
      newvalue                       final

  public abstract scala.Option<V> replace(K, V);
    descriptor: (Ljava/lang/Object;Ljava/lang/Object;)Lscala/Option;
    flags: (0x0401) ACC_PUBLIC, ACC_ABSTRACT
    Signature: #14                          // (TK;TV;)Lscala/Option<TV;>;
    MethodParameters:
      Name                           Flags
      k                              final
      v                              final

  public static java.lang.Object getOrElseUpdate$(scala.collection.concurrent.Map, java.lang.Object, scala.Function0);
    descriptor: (Lscala/collection/concurrent/Map;Ljava/lang/Object;Lscala/Function0;)Ljava/lang/Object;
    flags: (0x1009) ACC_PUBLIC, ACC_STATIC, ACC_SYNTHETIC
    Code:
      stack=3, locals=3, args_size=3
         0: aload_0
         1: aload_1
         2: aload_2
         3: invokespecial #33                 // InterfaceMethod getOrElseUpdate:(Ljava/lang/Object;Lscala/Function0;)Ljava/lang/Object;
         6: areturn
      LineNumberTable:
        line 96: 0
      LocalVariableTable:
        Start  Length  Slot  Name   Signature
            0       7     0 $this   Lscala/collection/concurrent/Map;
            0       7     1   key   Ljava/lang/Object;
            0       7     2    op   Lscala/Function0;
    MethodParameters:
      Name                           Flags
      $this                          final synthetic
      key                            final
      op                             final

  public default V getOrElseUpdate(K, scala.Function0<V>);
    descriptor: (Ljava/lang/Object;Lscala/Function0;)Ljava/lang/Object;
    flags: (0x0001) ACC_PUBLIC
    Code:
      stack=3, locals=8, args_size=3
         0: aload_0
         1: aload_1
         2: invokeinterface #41,  2           // InterfaceMethod get:(Ljava/lang/Object;)Lscala/Option;
         7: astore        5
         9: aload         5
        11: instanceof    #43                 // class scala/Some
        14: ifeq          29
        17: aload         5
        19: checkcast     #43                 // class scala/Some
        22: invokevirtual #47                 // Method scala/Some.value:()Ljava/lang/Object;
        25: astore_3
        26: goto          124
        29: getstatic     #53                 // Field scala/None$.MODULE$:Lscala/None$;
        32: aload         5
        34: invokevirtual #57                 // Method java/lang/Object.equals:(Ljava/lang/Object;)Z
        37: ifeq          114
        40: aload_2
        41: invokeinterface #62,  1           // InterfaceMethod scala/Function0.apply:()Ljava/lang/Object;
        46: astore        6
        48: aload_0
        49: aload_1
        50: aload         6
        52: invokeinterface #64,  3           // InterfaceMethod putIfAbsent:(Ljava/lang/Object;Ljava/lang/Object;)Lscala/Option;
        57: astore        7
        59: aload         7
        61: instanceof    #43                 // class scala/Some
        64: ifeq          80
        67: aload         7
        69: checkcast     #43                 // class scala/Some
        72: invokevirtual #47                 // Method scala/Some.value:()Ljava/lang/Object;
        75: astore        4
        77: goto          108
        80: getstatic     #53                 // Field scala/None$.MODULE$:Lscala/None$;
        83: aload         7
        85: invokevirtual #57                 // Method java/lang/Object.equals:(Ljava/lang/Object;)Z
        88: ifeq          98
        91: aload         6
        93: astore        4
        95: goto          108
        98: new           #66                 // class scala/MatchError
       101: dup
       102: aload         7
       104: invokespecial #70                 // Method scala/MatchError."<init>":(Ljava/lang/Object;)V
       107: athrow
       108: aload         4
       110: astore_3
       111: goto          124
       114: new           #66                 // class scala/MatchError
       117: dup
       118: aload         5
       120: invokespecial #70                 // Method scala/MatchError."<init>":(Ljava/lang/Object;)V
       123: athrow
       124: aload_3
       125: areturn
      StackMapTable: number_of_entries = 6
        frame_type = 254 /* append */
          offset_delta = 29
          locals = [ top, top, class scala/Option ]
        frame_type = 253 /* append */
          offset_delta = 50
          locals = [ class java/lang/Object, class scala/Option ]
        frame_type = 17 /* same */
        frame_type = 255 /* full_frame */
          offset_delta = 9
          locals = [ class scala/collection/concurrent/Map, class java/lang/Object, class scala/Function0, top, class java/lang/Object, class scala/Option, class java/lang/Object, class scala/Option ]
          stack = []
        frame_type = 255 /* full_frame */
          offset_delta = 5
          locals = [ class scala/collection/concurrent/Map, class java/lang/Object, class scala/Function0, top, top, class scala/Option ]
          stack = []
        frame_type = 255 /* full_frame */
          offset_delta = 9
          locals = [ class scala/collection/concurrent/Map, class java/lang/Object, class scala/Function0, class java/lang/Object, top, class scala/Option ]
          stack = []
      LineNumberTable:
        line 96: 0
        line 97: 9
        line 98: 29
        line 99: 40
        line 100: 48
        line 101: 59
        line 102: 80
        line 100: 98
        line 96: 114
      LocalVariableTable:
        Start  Length  Slot  Name   Signature
           48      62     6     v   Ljava/lang/Object;
            0     126     0  this   Lscala/collection/concurrent/Map;
            0     126     1   key   Ljava/lang/Object;
            0     126     2    op   Lscala/Function0;
    Signature: #37                          // (TK;Lscala/Function0<TV;>;)TV;
    MethodParameters:
      Name                           Flags
      key                            final
      op                             final

  public static boolean removeRefEq$(scala.collection.concurrent.Map, java.lang.Object, java.lang.Object);
    descriptor: (Lscala/collection/concurrent/Map;Ljava/lang/Object;Ljava/lang/Object;)Z
    flags: (0x1009) ACC_PUBLIC, ACC_STATIC, ACC_SYNTHETIC
    Code:
      stack=3, locals=3, args_size=3
         0: aload_0
         1: aload_1
         2: aload_2
         3: invokespecial #78                 // InterfaceMethod removeRefEq:(Ljava/lang/Object;Ljava/lang/Object;)Z
         6: ireturn
      LineNumberTable:
        line 122: 0
      LocalVariableTable:
        Start  Length  Slot  Name   Signature
            0       7     0 $this   Lscala/collection/concurrent/Map;
            0       7     1     k   Ljava/lang/Object;
            0       7     2     v   Ljava/lang/Object;
    MethodParameters:
      Name                           Flags
      $this                          final synthetic
      k                              final
      v                              final

  public default boolean removeRefEq(K, V);
    descriptor: (Ljava/lang/Object;Ljava/lang/Object;)Z
    flags: (0x0001) ACC_PUBLIC
    Code:
      stack=3, locals=3, args_size=3
         0: aload_0
         1: aload_1
         2: aload_2
         3: invokeinterface #80,  3           // InterfaceMethod remove:(Ljava/lang/Object;Ljava/lang/Object;)Z
         8: ireturn
      LineNumberTable:
        line 122: 0
      LocalVariableTable:
        Start  Length  Slot  Name   Signature
            0       9     0  this   Lscala/collection/concurrent/Map;
            0       9     1     k   Ljava/lang/Object;
            0       9     2     v   Ljava/lang/Object;
    Signature: #19                          // (TK;TV;)Z
    MethodParameters:
      Name                           Flags
      k                              final
      v                              final

  public static boolean replaceRefEq$(scala.collection.concurrent.Map, java.lang.Object, java.lang.Object, java.lang.Object);
    descriptor: (Lscala/collection/concurrent/Map;Ljava/lang/Object;Ljava/lang/Object;Ljava/lang/Object;)Z
    flags: (0x1009) ACC_PUBLIC, ACC_STATIC, ACC_SYNTHETIC
    Code:
      stack=4, locals=4, args_size=4
         0: aload_0
         1: aload_1
         2: aload_2
         3: aload_3
         4: invokespecial #87                 // InterfaceMethod replaceRefEq:(Ljava/lang/Object;Ljava/lang/Object;Ljava/lang/Object;)Z
         7: ireturn
      LineNumberTable:
        line 141: 0
      LocalVariableTable:
        Start  Length  Slot  Name   Signature
            0       8     0 $this   Lscala/collection/concurrent/Map;
            0       8     1     k   Ljava/lang/Object;
            0       8     2 oldValue   Ljava/lang/Object;
            0       8     3 newValue   Ljava/lang/Object;
    MethodParameters:
      Name                           Flags
      $this                          final synthetic
      k                              final
      oldValue                       final
      newValue                       final

  public default boolean replaceRefEq(K, V, V);
    descriptor: (Ljava/lang/Object;Ljava/lang/Object;Ljava/lang/Object;)Z
    flags: (0x0001) ACC_PUBLIC
    Code:
      stack=4, locals=4, args_size=4
         0: aload_0
         1: aload_1
         2: aload_2
         3: aload_3
         4: invokeinterface #89,  4           // InterfaceMethod replace:(Ljava/lang/Object;Ljava/lang/Object;Ljava/lang/Object;)Z
         9: ireturn
      LineNumberTable:
        line 141: 0
      LocalVariableTable:
        Start  Length  Slot  Name   Signature
            0      10     0  this   Lscala/collection/concurrent/Map;
            0      10     1     k   Ljava/lang/Object;
            0      10     2 oldValue   Ljava/lang/Object;
            0      10     3 newValue   Ljava/lang/Object;
    Signature: #22                          // (TK;TV;TV;)Z
    MethodParameters:
      Name                           Flags
      k                              final
      oldValue                       final
      newValue                       final

  public static scala.Option updateWith$(scala.collection.concurrent.Map, java.lang.Object, scala.Function1);
    descriptor: (Lscala/collection/concurrent/Map;Ljava/lang/Object;Lscala/Function1;)Lscala/Option;
    flags: (0x1009) ACC_PUBLIC, ACC_STATIC, ACC_SYNTHETIC
    Code:
      stack=3, locals=3, args_size=3
         0: aload_0
         1: aload_1
         2: aload_2
         3: invokespecial #96                 // InterfaceMethod updateWith:(Ljava/lang/Object;Lscala/Function1;)Lscala/Option;
         6: areturn
      LineNumberTable:
        line 157: 0
      LocalVariableTable:
        Start  Length  Slot  Name   Signature
            0       7     0 $this   Lscala/collection/concurrent/Map;
            0       7     1   key   Ljava/lang/Object;
            0       7     2 remappingFunction   Lscala/Function1;
    MethodParameters:
      Name                           Flags
      $this                          final synthetic
      key                            final
      remappingFunction              final

  public default scala.Option<V> updateWith(K, scala.Function1<scala.Option<V>, scala.Option<V>>);
    descriptor: (Ljava/lang/Object;Lscala/Function1;)Lscala/Option;
    flags: (0x0001) ACC_PUBLIC
    Code:
      stack=4, locals=9, args_size=3
         0: aload_0
         1: aload_1
         2: invokeinterface #41,  2           // InterfaceMethod get:(Ljava/lang/Object;)Lscala/Option;
         7: astore_3
         8: aload_2
         9: aload_3
        10: invokeinterface #103,  2          // InterfaceMethod scala/Function1.apply:(Ljava/lang/Object;)Ljava/lang/Object;
        15: checkcast     #73                 // class scala/Option
        18: astore        4
        20: aload_3
        21: instanceof    #43                 // class scala/Some
        24: ifeq          95
        27: aload_3
        28: checkcast     #43                 // class scala/Some
        31: invokevirtual #47                 // Method scala/Some.value:()Ljava/lang/Object;
        34: astore        5
        36: aload         4
        38: instanceof    #43                 // class scala/Some
        41: ifeq          75
        44: aload         4
        46: checkcast     #43                 // class scala/Some
        49: invokevirtual #47                 // Method scala/Some.value:()Ljava/lang/Object;
        52: astore        6
        54: aload_0
        55: aload_1
        56: aload         5
        58: aload         6
        60: invokeinterface #87,  4           // InterfaceMethod replaceRefEq:(Ljava/lang/Object;Ljava/lang/Object;Ljava/lang/Object;)Z
        65: ifeq          0
        68: aload         4
        70: astore        8
        72: goto          140
        75: aload_0
        76: aload_1
        77: aload         5
        79: invokeinterface #78,  3           // InterfaceMethod removeRefEq:(Ljava/lang/Object;Ljava/lang/Object;)Z
        84: ifeq          0
        87: getstatic     #53                 // Field scala/None$.MODULE$:Lscala/None$;
        90: astore        8
        92: goto          140
        95: aload         4
        97: instanceof    #43                 // class scala/Some
       100: ifeq          135
       103: aload         4
       105: checkcast     #43                 // class scala/Some
       108: invokevirtual #47                 // Method scala/Some.value:()Ljava/lang/Object;
       111: astore        7
       113: aload_0
       114: aload_1
       115: aload         7
       117: invokeinterface #64,  3           // InterfaceMethod putIfAbsent:(Ljava/lang/Object;Ljava/lang/Object;)Lscala/Option;
       122: invokevirtual #107                // Method scala/Option.isEmpty:()Z
       125: ifeq          0
       128: aload         4
       130: astore        8
       132: goto          140
       135: getstatic     #53                 // Field scala/None$.MODULE$:Lscala/None$;
       138: astore        8
       140: aload         8
       142: areturn
      StackMapTable: number_of_entries = 5
        frame_type = 0 /* same */
        frame_type = 254 /* append */
          offset_delta = 74
          locals = [ class scala/Option, class scala/Option, class java/lang/Object ]
        frame_type = 250 /* chop */
          offset_delta = 19
        frame_type = 39 /* same */
        frame_type = 255 /* full_frame */
          offset_delta = 4
          locals = [ class scala/collection/concurrent/Map, class java/lang/Object, class scala/Function1, class scala/Option, class scala/Option, top, top, top, class scala/Option ]
          stack = []
      LineNumberTable:
        line 161: 0
        line 162: 8
        line 164: 20
        line 165: 36
        line 166: 75
        line 169: 95
        line 170: 135
        line 173: 140
        line 157: 140
      LocalVariableTable:
        Start  Length  Slot  Name   Signature
            0     143     0  this   Lscala/collection/concurrent/Map;
            0     143     1   key   Ljava/lang/Object;
            0     143     2 remappingFunction   Lscala/Function1;
           54      21     6 updateWithAux_next   Ljava/lang/Object;
           36      59     5 updateWithAux_prev   Ljava/lang/Object;
          113      22     7 updateWithAux_next   Ljava/lang/Object;
            8     132     3 updateWithAux_previousValue   Lscala/Option;
           20     120     4 updateWithAux_nextValue   Lscala/Option;
    Signature: #98                          // (TK;Lscala/Function1<Lscala/Option<TV;>;Lscala/Option<TV;>;>;)Lscala/Option<TV;>;
    MethodParameters:
      Name                           Flags
      key                            final
      remappingFunction              final

  private scala.Option<V> updateWithAux(K, scala.Function1<scala.Option<V>, scala.Option<V>>);
    descriptor: (Ljava/lang/Object;Lscala/Function1;)Lscala/Option;
    flags: (0x0002) ACC_PRIVATE
    Code:
      stack=4, locals=8, args_size=3
         0: aload_0
         1: aload_1
         2: invokeinterface #41,  2           // InterfaceMethod get:(Ljava/lang/Object;)Lscala/Option;
         7: astore_3
         8: aload_2
         9: aload_3
        10: invokeinterface #103,  2          // InterfaceMethod scala/Function1.apply:(Ljava/lang/Object;)Ljava/lang/Object;
        15: checkcast     #73                 // class scala/Option
        18: astore        4
        20: aload_3
        21: instanceof    #43                 // class scala/Some
        24: ifeq          87
        27: aload_3
        28: checkcast     #43                 // class scala/Some
        31: invokevirtual #47                 // Method scala/Some.value:()Ljava/lang/Object;
        34: astore        5
        36: aload         4
        38: instanceof    #43                 // class scala/Some
        41: ifeq          71
        44: aload         4
        46: checkcast     #43                 // class scala/Some
        49: invokevirtual #47                 // Method scala/Some.value:()Ljava/lang/Object;
        52: astore        6
        54: aload_0
        55: aload_1
        56: aload         5
        58: aload         6
        60: invokeinterface #87,  4           // InterfaceMethod replaceRefEq:(Ljava/lang/Object;Ljava/lang/Object;Ljava/lang/Object;)Z
        65: ifeq          127
        68: aload         4
        70: areturn
        71: aload_0
        72: aload_1
        73: aload         5
        75: invokeinterface #78,  3           // InterfaceMethod removeRefEq:(Ljava/lang/Object;Ljava/lang/Object;)Z
        80: ifeq          127
        83: getstatic     #53                 // Field scala/None$.MODULE$:Lscala/None$;
        86: areturn
        87: aload         4
        89: instanceof    #43                 // class scala/Some
        92: ifeq          123
        95: aload         4
        97: checkcast     #43                 // class scala/Some
       100: invokevirtual #47                 // Method scala/Some.value:()Ljava/lang/Object;
       103: astore        7
       105: aload_0
       106: aload_1
       107: aload         7
       109: invokeinterface #64,  3           // InterfaceMethod putIfAbsent:(Ljava/lang/Object;Ljava/lang/Object;)Lscala/Option;
       114: invokevirtual #107                // Method scala/Option.isEmpty:()Z
       117: ifeq          127
       120: aload         4
       122: areturn
       123: getstatic     #53                 // Field scala/None$.MODULE$:Lscala/None$;
       126: areturn
       127: aload_1
       128: aload_2
       129: astore_2
       130: astore_1
       131: goto          0
      StackMapTable: number_of_entries = 5
        frame_type = 0 /* same */
        frame_type = 254 /* append */
          offset_delta = 70
          locals = [ class scala/Option, class scala/Option, class java/lang/Object ]
        frame_type = 250 /* chop */
          offset_delta = 15
        frame_type = 35 /* same */
        frame_type = 3 /* same */
      LineNumberTable:
        line 161: 0
        line 162: 8
        line 164: 20
        line 165: 36
        line 166: 71
        line 169: 87
        line 170: 123
        line 173: 127
      LocalVariableTable:
        Start  Length  Slot  Name   Signature
           54      17     6  next   Ljava/lang/Object;
           36      51     5  prev   Ljava/lang/Object;
          105      18     7  next   Ljava/lang/Object;
            8     126     3 previousValue   Lscala/Option;
           20     114     4 nextValue   Lscala/Option;
            0     134     0  this   Lscala/collection/concurrent/Map;
            0     134     1   key   Ljava/lang/Object;
            0     134     2 remappingFunction   Lscala/Function1;
    Signature: #98                          // (TK;Lscala/Function1<Lscala/Option<TV;>;Lscala/Option<TV;>;>;)Lscala/Option<TV;>;
    MethodParameters:
      Name                           Flags
      key                            final
      remappingFunction              final

  public static scala.collection.concurrent.Map filterInPlaceImpl$(scala.collection.concurrent.Map, scala.Function2);
    descriptor: (Lscala/collection/concurrent/Map;Lscala/Function2;)Lscala/collection/concurrent/Map;
    flags: (0x1009) ACC_PUBLIC, ACC_STATIC, ACC_SYNTHETIC
    Code:
      stack=2, locals=2, args_size=2
         0: aload_0
         1: aload_1
         2: invokespecial #124                // InterfaceMethod filterInPlaceImpl:(Lscala/Function2;)Lscala/collection/concurrent/Map;
         5: areturn
      LineNumberTable:
        line 176: 0
      LocalVariableTable:
        Start  Length  Slot  Name   Signature
            0       6     0 $this   Lscala/collection/concurrent/Map;
            0       6     1     p   Lscala/Function2;
    MethodParameters:
      Name                           Flags
      $this                          final synthetic
      p                              final

  public default scala.collection.concurrent.Map<K, V> filterInPlaceImpl(scala.Function2<K, V, java.lang.Object>);
    descriptor: (Lscala/Function2;)Lscala/collection/concurrent/Map;
    flags: (0x0001) ACC_PUBLIC
    Code:
      stack=3, locals=6, args_size=2
         0: aload_0
         1: invokeinterface #130,  1          // InterfaceMethod iterator:()Lscala/collection/Iterator;
         6: astore_2
         7: aload_2
         8: invokeinterface #135,  1          // InterfaceMethod scala/collection/Iterator.hasNext:()Z
        13: ifeq          84
        16: aload_2
        17: invokeinterface #137,  1          // InterfaceMethod scala/collection/Iterator.next:()Ljava/lang/Object;
        22: checkcast     #139                // class scala/Tuple2
        25: astore_3
        26: aload_3
        27: ifnull        45
        30: aload_3
        31: invokevirtual #142                // Method scala/Tuple2._1:()Ljava/lang/Object;
        34: astore        4
        36: aload_3
        37: invokevirtual #145                // Method scala/Tuple2._2:()Ljava/lang/Object;
        40: astore        5
        42: goto          54
        45: new           #66                 // class scala/MatchError
        48: dup
        49: aconst_null
        50: invokespecial #70                 // Method scala/MatchError."<init>":(Ljava/lang/Object;)V
        53: athrow
        54: aload_1
        55: aload         4
        57: aload         5
        59: invokeinterface #150,  3          // InterfaceMethod scala/Function2.apply:(Ljava/lang/Object;Ljava/lang/Object;)Ljava/lang/Object;
        64: invokestatic  #155                // Method scala/runtime/BoxesRunTime.unboxToBoolean:(Ljava/lang/Object;)Z
        67: ifne          7
        70: aload_0
        71: aload         4
        73: aload         5
        75: invokeinterface #78,  3           // InterfaceMethod removeRefEq:(Ljava/lang/Object;Ljava/lang/Object;)Z
        80: pop
        81: goto          7
        84: aload_0
        85: areturn
      StackMapTable: number_of_entries = 4
        frame_type = 252 /* append */
          offset_delta = 7
          locals = [ class scala/collection/Iterator ]
        frame_type = 252 /* append */
          offset_delta = 37
          locals = [ class scala/Tuple2 ]
        frame_type = 253 /* append */
          offset_delta = 8
          locals = [ class java/lang/Object, class java/lang/Object ]
        frame_type = 248 /* chop */
          offset_delta = 29
      LineNumberTable:
        line 177: 0
        line 178: 7
        line 179: 16
        line 180: 54
        line 182: 84
      LocalVariableTable:
        Start  Length  Slot  Name   Signature
           36       9     4     k   Ljava/lang/Object;
           42       3     5     v   Ljava/lang/Object;
            7      78     2    it   Lscala/collection/Iterator;
            0      86     0  this   Lscala/collection/concurrent/Map;
            0      86     1     p   Lscala/Function2;
    Signature: #126                         // (Lscala/Function2<TK;TV;Ljava/lang/Object;>;)Lscala/collection/concurrent/Map<TK;TV;>;
    MethodParameters:
      Name                           Flags
      p                              final

  public static scala.collection.concurrent.Map mapValuesInPlaceImpl$(scala.collection.concurrent.Map, scala.Function2);
    descriptor: (Lscala/collection/concurrent/Map;Lscala/Function2;)Lscala/collection/concurrent/Map;
    flags: (0x1009) ACC_PUBLIC, ACC_STATIC, ACC_SYNTHETIC
    Code:
      stack=2, locals=2, args_size=2
         0: aload_0
         1: aload_1
         2: invokespecial #162                // InterfaceMethod mapValuesInPlaceImpl:(Lscala/Function2;)Lscala/collection/concurrent/Map;
         5: areturn
      LineNumberTable:
        line 185: 0
      LocalVariableTable:
        Start  Length  Slot  Name   Signature
            0       6     0 $this   Lscala/collection/concurrent/Map;
            0       6     1     f   Lscala/Function2;
    MethodParameters:
      Name                           Flags
      $this                          final synthetic
      f                              final

  public default scala.collection.concurrent.Map<K, V> mapValuesInPlaceImpl(scala.Function2<K, V, V>);
    descriptor: (Lscala/Function2;)Lscala/collection/concurrent/Map;
    flags: (0x0001) ACC_PUBLIC
    Code:
      stack=6, locals=6, args_size=2
         0: aload_0
         1: invokeinterface #130,  1          // InterfaceMethod iterator:()Lscala/collection/Iterator;
         6: astore_2
         7: aload_2
         8: invokeinterface #135,  1          // InterfaceMethod scala/collection/Iterator.hasNext:()Z
        13: ifeq          78
        16: aload_2
        17: invokeinterface #137,  1          // InterfaceMethod scala/collection/Iterator.next:()Ljava/lang/Object;
        22: checkcast     #139                // class scala/Tuple2
        25: astore_3
        26: aload_3
        27: ifnull        45
        30: aload_3
        31: invokevirtual #142                // Method scala/Tuple2._1:()Ljava/lang/Object;
        34: astore        4
        36: aload_3
        37: invokevirtual #145                // Method scala/Tuple2._2:()Ljava/lang/Object;
        40: astore        5
        42: goto          54
        45: new           #66                 // class scala/MatchError
        48: dup
        49: aconst_null
        50: invokespecial #70                 // Method scala/MatchError."<init>":(Ljava/lang/Object;)V
        53: athrow
        54: aload_0
        55: aload         4
        57: aload         5
        59: aload_1
        60: aload         4
        62: aload         5
        64: invokeinterface #150,  3          // InterfaceMethod scala/Function2.apply:(Ljava/lang/Object;Ljava/lang/Object;)Ljava/lang/Object;
        69: invokeinterface #87,  4           // InterfaceMethod replaceRefEq:(Ljava/lang/Object;Ljava/lang/Object;Ljava/lang/Object;)Z
        74: pop
        75: goto          7
        78: aload_0
        79: areturn
      StackMapTable: number_of_entries = 4
        frame_type = 252 /* append */
          offset_delta = 7
          locals = [ class scala/collection/Iterator ]
        frame_type = 252 /* append */
          offset_delta = 37
          locals = [ class scala/Tuple2 ]
        frame_type = 253 /* append */
          offset_delta = 8
          locals = [ class java/lang/Object, class java/lang/Object ]
        frame_type = 248 /* chop */
          offset_delta = 23
      LineNumberTable:
        line 186: 0
        line 187: 7
        line 188: 16
        line 189: 54
        line 187: 75
        line 191: 78
      LocalVariableTable:
        Start  Length  Slot  Name   Signature
           36       9     4     k   Ljava/lang/Object;
           42       3     5     v   Ljava/lang/Object;
            7      72     2    it   Lscala/collection/Iterator;
            0      80     0  this   Lscala/collection/concurrent/Map;
            0      80     1     f   Lscala/Function2;
    Signature: #163                         // (Lscala/Function2<TK;TV;TV;>;)Lscala/collection/concurrent/Map<TK;TV;>;
    MethodParameters:
      Name                           Flags
      f                              final

  public static void $init$(scala.collection.concurrent.Map);
    descriptor: (Lscala/collection/concurrent/Map;)V
    flags: (0x0009) ACC_PUBLIC, ACC_STATIC
    Code:
      stack=0, locals=1, args_size=1
         0: return
      LineNumberTable:
        line 41: 0
      LocalVariableTable:
        Start  Length  Slot  Name   Signature
            0       1     0 $this   Lscala/collection/concurrent/Map;
    MethodParameters:
      Name                           Flags
      $this                          final synthetic
}
Signature: #3                           // <K:Ljava/lang/Object;V:Ljava/lang/Object;>Ljava/lang/Object;Lscala/collection/mutable/Map<TK;TV;>;
SourceFile: "Map.scala"
RuntimeVisibleAnnotations:
  0: #9(#10=s#11)
    scala.reflect.ScalaSignature(
      bytes="\u0006\u0005\u0005\u001daaB\u0007\u000f!\u0003\r\t!\u0006\u0005\u0006]\u0001!\ta\f\u0005\u0006g\u00011\t\u0001\u000e\u0005\u0006y\u00011\t!\u0010\u0005\u0006\u0007\u00021\t\u0001\u0012\u0005\u0006\u0007\u00021\tA\u0013\u0005\u0006\u001b\u0002!\tE\u0014\u0005\u0007-\u0002!\t\u0001E,\t\ri\u0003A\u0011\u0001\t\\\u0011\u0015\t\u0007\u0001\"\u0011c\u0011\u0015Q\u0007\u0001\"\u0003l\u0011\u00191\b\u0001\"\u0001\u0011o\"1a\u0010\u0001C\u0001!}\u00141!T1q\u0015\ty\u0001#\u0001\u0006d_:\u001cWO\u001d:f]RT!!\u0005\n\u0002\u0015\r|G\u000e\\3di&|gNC\u0001\u0014\u0003\u0015\u00198-\u00197b\u0007\u0001)2A\u0006\u0012-\'\r\u0001qc\u0007\t\u00031ei\u0011AE\u0005\u00035I\u0011a!\u00118z%\u00164\u0007\u0003\u0002\u000f A-j\u0011!\b\u0006\u0003=A\tq!\\;uC\ndW-\u0003\u0002\u000e;A\u0011\u0011E\t\u0007\u0001\t\u0015\u0019\u0003A1\u0001%\u0005\u0005Y\u0015CA\u0013)!\tAb%\u0003\u0002(%\t9aj\u001c;iS:<\u0007C\u0001\r*\u0013\tQ#CA\u0002B]f\u0004\"!\t\u0017\u0005\u000b5\u0002!\u0019\u0001\u0013\u0003\u0003Y\u000ba\u0001J5oSR$C#\u0001\u0019\u0011\u0005a\t\u0014B\u0001\u001a\u0013\u0005\u0011)f.\u001b;\u0002\u0017A,H/\u00134BEN,g\u000e\u001e\u000b\u0004kaR\u0004c\u0001\r7W%\u0011qG\u0005\u0002\u0007\u001fB$\u0018n\u001c8\t\u000be\u0012\u0001\u0019\u0001\u0011\u0002\u0003-DQa\u000f\u0002A\u0002-\n\u0011A^\u0001\u0007e\u0016lwN^3\u0015\u0007y\n%\t\u0005\u0002\u0019\u007f%\u0011\u0001I\u0005\u0002\b\u0005>|G.Z1o\u0011\u0015I4\u00011\u0001!\u0011\u0015Y4\u00011\u0001,\u0003\u001d\u0011X\r\u001d7bG\u0016$BAP#G\u0011\")\u0011\b\u0002a\u0001A!)q\t\u0002a\u0001W\u0005Aq\u000e\u001c3wC2,X\rC\u0003J\t\u0001\u00071&\u0001\u0005oK^4\u0018\r\\;f)\r)4\n\u0014\u0005\u0006s\u0015\u0001\r\u0001\t\u0005\u0006w\u0015\u0001\raK\u0001\u0010O\u0016$xJ]#mg\u0016,\u0006\u000fZ1uKR\u00191fT)\t\u000bA3\u0001\u0019\u0001\u0011\u0002\u0007-,\u0017\u0010\u0003\u0004S\r\u0011\u0005\raU\u0001\u0003_B\u00042\u0001\u0007+,\u0013\t)&C\u0001\u0005=Eft\u0017-\\3?\u0003-\u0011X-\\8wKJ+g-R9\u0015\u0007yB\u0016\fC\u0003:\u000f\u0001\u0007\u0001\u0005C\u0003<\u000f\u0001\u00071&\u0001\u0007sKBd\u0017mY3SK\u001a,\u0015\u000f\u0006\u0003?9v{\u0006\"B\u001d\t\u0001\u0004\u0001\u0003\"\u00020\t\u0001\u0004Y\u0013\u0001C8mIZ\u000bG.^3\t\u000b\u0001D\u0001\u0019A\u0016\u0002\u00119,wOV1mk\u0016\f!\"\u001e9eCR,w+\u001b;i)\t\u0019\u0017\u000e\u0006\u00026I\")Q-\u0003a\u0001M\u0006\t\"/Z7baBLgn\u001a$v]\u000e$\u0018n\u001c8\u0011\ta9W\'N\u0005\u0003QJ\u0011\u0011BR;oGRLwN\\\u0019\t\u000bAK\u0001\u0019\u0001\u0011\u0002\u001bU\u0004H-\u0019;f/&$\b.Q;y)\tag\u000e\u0006\u00026[\")QM\u0003a\u0001M\")\u0001K\u0003a\u0001A!\u0012!\u0002\u001d\t\u0003cRl\u0011A\u001d\u0006\u0003gJ\t!\"\u00198o_R\fG/[8o\u0013\t)(OA\u0004uC&d\'/Z2\u0002#\u0019LG\u000e^3s\u0013:\u0004F.Y2f\u00136\u0004H\u000e\u0006\u0002ys6\t\u0001\u0001C\u0003{\u0017\u0001\u000710A\u0001q!\u0015AB\u0010I\u0016?\u0013\ti(CA\u0005Gk:\u001cG/[8oe\u0005!R.\u00199WC2,Xm]%o!2\f7-Z%na2$2\u0001_A\u0001\u0011\u001d\t\u0019\u0001\u0004a\u0001\u0003\u000b\t\u0011A\u001a\t\u00061q\u00043f\u000b"
    )
  ScalaInlineInfo: length = 0x5E (unknown attribute)
   01 00 00 12 00 A4 00 A5 01 00 79 00 7A 00 00 76
   00 77 01 00 1E 00 1F 00 00 19 00 1A 01 00 A0 00
   7A 00 00 9E 00 77 01 00 0C 00 0D 00 00 11 00 12
   00 00 4C 00 12 00 00 4A 00 4B 01 00 14 00 0D 00
   00 14 00 15 00 00 55 00 15 00 00 51 00 52 01 00
   5D 00 5E 00 00 5A 00 5B 01 00 71 00 5E 01
  ScalaSig: length = 0x3 (unknown attribute)
   05 02 00
