Classfile /Users/mw/Projects/slang-braindump/.jar/jar11/assemble/slang-braindump/assemble/content/scala/collection/concurrent/TrieMap$.class
  Last modified May 29, 2022; size 3869 bytes
  SHA-256 checksum 1c37fb6be08326bc6a6a1cced0f5a4deabb7c67c93730d2218e267417f054072
  Compiled from "TrieMap.scala"
public final class scala.collection.concurrent.TrieMap$ extends java.lang.Object implements scala.collection.MapFactory<scala.collection.concurrent.TrieMap>
  minor version: 0
  major version: 52
  flags: (0x0031) ACC_PUBLIC, ACC_FINAL, ACC_SUPER
  this_class: #2                          // scala/collection/concurrent/TrieMap$
  super_class: #5                         // java/lang/Object
  interfaces: 1, fields: 3, methods: 12, attributes: 4
Constant pool:
    #1 = Utf8               scala/collection/concurrent/TrieMap$
    #2 = Class              #1            // scala/collection/concurrent/TrieMap$
    #3 = Utf8               Ljava/lang/Object;Lscala/collection/MapFactory<Lscala/collection/concurrent/TrieMap;>;
    #4 = Utf8               java/lang/Object
    #5 = Class              #4            // java/lang/Object
    #6 = Utf8               scala/collection/MapFactory
    #7 = Class              #6            // scala/collection/MapFactory
    #8 = Utf8               TrieMap.scala
    #9 = Utf8               MODULE$
   #10 = Utf8               Lscala/collection/concurrent/TrieMap$;
   #11 = Utf8               serialVersionUID
   #12 = Utf8               J
   #13 = Long               3l
   #15 = Utf8               inodeupdater
   #16 = Utf8               Ljava/util/concurrent/atomic/AtomicReferenceFieldUpdater;
   #17 = Utf8               Ljava/util/concurrent/atomic/AtomicReferenceFieldUpdater<Lscala/collection/concurrent/INodeBase<**>;Lscala/collection/concurrent/MainNode<**>;>;
   #18 = Utf8               <clinit>
   #19 = Utf8               ()V
   #20 = Utf8               <init>
   #21 = NameAndType        #20:#19       // "<init>":()V
   #22 = Methodref          #2.#21        // scala/collection/concurrent/TrieMap$."<init>":()V
   #23 = NameAndType        #9:#10        // MODULE$:Lscala/collection/concurrent/TrieMap$;
   #24 = Fieldref           #2.#23        // scala/collection/concurrent/TrieMap$.MODULE$:Lscala/collection/concurrent/TrieMap$;
   #25 = Utf8               scala/collection/concurrent/INodeBase
   #26 = Class              #25           // scala/collection/concurrent/INodeBase
   #27 = Utf8               scala/collection/concurrent/MainNode
   #28 = Class              #27           // scala/collection/concurrent/MainNode
   #29 = Utf8               mainnode
   #30 = String             #29           // mainnode
   #31 = Utf8               java/util/concurrent/atomic/AtomicReferenceFieldUpdater
   #32 = Class              #31           // java/util/concurrent/atomic/AtomicReferenceFieldUpdater
   #33 = Utf8               newUpdater
   #34 = Utf8               (Ljava/lang/Class;Ljava/lang/Class;Ljava/lang/String;)Ljava/util/concurrent/atomic/AtomicReferenceFieldUpdater;
   #35 = NameAndType        #33:#34       // newUpdater:(Ljava/lang/Class;Ljava/lang/Class;Ljava/lang/String;)Ljava/util/concurrent/atomic/AtomicReferenceFieldUpdater;
   #36 = Methodref          #32.#35       // java/util/concurrent/atomic/AtomicReferenceFieldUpdater.newUpdater:(Ljava/lang/Class;Ljava/lang/Class;Ljava/lang/String;)Ljava/util/concurrent/atomic/AtomicReferenceFieldUpdater;
   #37 = NameAndType        #15:#16       // inodeupdater:Ljava/util/concurrent/atomic/AtomicReferenceFieldUpdater;
   #38 = Fieldref           #2.#37        // scala/collection/concurrent/TrieMap$.inodeupdater:Ljava/util/concurrent/atomic/AtomicReferenceFieldUpdater;
   #39 = Utf8               apply
   #40 = Utf8               (Lscala/collection/immutable/Seq;)Ljava/lang/Object;
   #41 = Utf8               elems
   #42 = Utf8               apply$
   #43 = Utf8               (Lscala/collection/MapFactory;Lscala/collection/immutable/Seq;)Ljava/lang/Object;
   #44 = NameAndType        #42:#43       // apply$:(Lscala/collection/MapFactory;Lscala/collection/immutable/Seq;)Ljava/lang/Object;
   #45 = InterfaceMethodref #7.#44        // scala/collection/MapFactory.apply$:(Lscala/collection/MapFactory;Lscala/collection/immutable/Seq;)Ljava/lang/Object;
   #46 = Utf8               this
   #47 = Utf8               Lscala/collection/immutable/Seq;
   #48 = Utf8               mapFactory
   #49 = Utf8               ()Lscala/collection/Factory;
   #50 = Utf8               <K:Ljava/lang/Object;V:Ljava/lang/Object;>()Lscala/collection/Factory<Lscala/Tuple2<TK;TV;>;Lscala/collection/concurrent/TrieMap<TK;TV;>;>;
   #51 = Utf8               mapFactory$
   #52 = Utf8               (Lscala/collection/MapFactory;)Lscala/collection/Factory;
   #53 = NameAndType        #51:#52       // mapFactory$:(Lscala/collection/MapFactory;)Lscala/collection/Factory;
   #54 = InterfaceMethodref #7.#53        // scala/collection/MapFactory.mapFactory$:(Lscala/collection/MapFactory;)Lscala/collection/Factory;
   #55 = Utf8               empty
   #56 = Utf8               ()Lscala/collection/concurrent/TrieMap;
   #57 = Utf8               <K:Ljava/lang/Object;V:Ljava/lang/Object;>()Lscala/collection/concurrent/TrieMap<TK;TV;>;
   #58 = Utf8               scala/collection/concurrent/TrieMap
   #59 = Class              #58           // scala/collection/concurrent/TrieMap
   #60 = Methodref          #59.#21       // scala/collection/concurrent/TrieMap."<init>":()V
   #61 = Utf8               from
   #62 = Utf8               (Lscala/collection/IterableOnce;)Lscala/collection/concurrent/TrieMap;
   #63 = Utf8               <K:Ljava/lang/Object;V:Ljava/lang/Object;>(Lscala/collection/IterableOnce<Lscala/Tuple2<TK;TV;>;>;)Lscala/collection/concurrent/TrieMap<TK;TV;>;
   #64 = Utf8               it
   #65 = Utf8               scala/collection/mutable/Growable
   #66 = Class              #65           // scala/collection/mutable/Growable
   #67 = Utf8               addAll
   #68 = Utf8               (Lscala/collection/IterableOnce;)Lscala/collection/mutable/Growable;
   #69 = NameAndType        #67:#68       // addAll:(Lscala/collection/IterableOnce;)Lscala/collection/mutable/Growable;
   #70 = InterfaceMethodref #66.#69       // scala/collection/mutable/Growable.addAll:(Lscala/collection/IterableOnce;)Lscala/collection/mutable/Growable;
   #71 = Utf8               Lscala/collection/IterableOnce;
   #72 = Utf8               newBuilder
   #73 = Utf8               ()Lscala/collection/mutable/GrowableBuilder;
   #74 = Utf8               <K:Ljava/lang/Object;V:Ljava/lang/Object;>()Lscala/collection/mutable/GrowableBuilder<Lscala/Tuple2<TK;TV;>;Lscala/collection/concurrent/TrieMap<TK;TV;>;>;
   #75 = Utf8               scala/collection/mutable/GrowableBuilder
   #76 = Class              #75           // scala/collection/mutable/GrowableBuilder
   #77 = Utf8               (Lscala/collection/mutable/Growable;)V
   #78 = NameAndType        #20:#77       // "<init>":(Lscala/collection/mutable/Growable;)V
   #79 = Methodref          #76.#78       // scala/collection/mutable/GrowableBuilder."<init>":(Lscala/collection/mutable/Growable;)V
   #80 = Utf8               ()Ljava/util/concurrent/atomic/AtomicReferenceFieldUpdater;
   #81 = Utf8               ()Ljava/util/concurrent/atomic/AtomicReferenceFieldUpdater<Lscala/collection/concurrent/INodeBase<**>;Lscala/collection/concurrent/MainNode<**>;>;
   #82 = Utf8               writeReplace
   #83 = Utf8               ()Ljava/lang/Object;
   #84 = Utf8               scala/runtime/ModuleSerializationProxy
   #85 = Class              #84           // scala/runtime/ModuleSerializationProxy
   #86 = Utf8               (Ljava/lang/Class;)V
   #87 = NameAndType        #20:#86       // "<init>":(Ljava/lang/Class;)V
   #88 = Methodref          #85.#87       // scala/runtime/ModuleSerializationProxy."<init>":(Ljava/lang/Class;)V
   #89 = Utf8               ()Lscala/collection/mutable/Builder;
   #90 = NameAndType        #72:#73       // newBuilder:()Lscala/collection/mutable/GrowableBuilder;
   #91 = Methodref          #2.#90        // scala/collection/concurrent/TrieMap$.newBuilder:()Lscala/collection/mutable/GrowableBuilder;
   #92 = Utf8               (Lscala/collection/IterableOnce;)Ljava/lang/Object;
   #93 = NameAndType        #61:#62       // from:(Lscala/collection/IterableOnce;)Lscala/collection/concurrent/TrieMap;
   #94 = Methodref          #2.#93        // scala/collection/concurrent/TrieMap$.from:(Lscala/collection/IterableOnce;)Lscala/collection/concurrent/TrieMap;
   #95 = NameAndType        #55:#56       // empty:()Lscala/collection/concurrent/TrieMap;
   #96 = Methodref          #2.#95        // scala/collection/concurrent/TrieMap$.empty:()Lscala/collection/concurrent/TrieMap;
   #97 = Methodref          #5.#21        // java/lang/Object."<init>":()V
   #98 = Utf8               ConstantValue
   #99 = Utf8               Signature
  #100 = Utf8               Code
  #101 = Utf8               LineNumberTable
  #102 = Utf8               LocalVariableTable
  #103 = Utf8               MethodParameters
  #104 = Utf8               SourceFile
  #105 = Utf8               ScalaInlineInfo
  #106 = Utf8               Scala
{
  public static final scala.collection.concurrent.TrieMap$ MODULE$;
    descriptor: Lscala/collection/concurrent/TrieMap$;
    flags: (0x0019) ACC_PUBLIC, ACC_STATIC, ACC_FINAL

  private static final long serialVersionUID;
    descriptor: J
    flags: (0x001a) ACC_PRIVATE, ACC_STATIC, ACC_FINAL
    ConstantValue: long 3l

  private static final transient java.util.concurrent.atomic.AtomicReferenceFieldUpdater<scala.collection.concurrent.INodeBase<?, ?>, scala.collection.concurrent.MainNode<?, ?>> inodeupdater;
    descriptor: Ljava/util/concurrent/atomic/AtomicReferenceFieldUpdater;
    flags: (0x009a) ACC_PRIVATE, ACC_STATIC, ACC_FINAL, ACC_TRANSIENT
    Signature: #17                          // Ljava/util/concurrent/atomic/AtomicReferenceFieldUpdater<Lscala/collection/concurrent/INodeBase<**>;Lscala/collection/concurrent/MainNode<**>;>;

  public static {};
    descriptor: ()V
    flags: (0x0009) ACC_PUBLIC, ACC_STATIC
    Code:
      stack=3, locals=0, args_size=0
         0: new           #2                  // class scala/collection/concurrent/TrieMap$
         3: dup
         4: invokespecial #22                 // Method "<init>":()V
         7: putstatic     #24                 // Field MODULE$:Lscala/collection/concurrent/TrieMap$;
        10: getstatic     #24                 // Field MODULE$:Lscala/collection/concurrent/TrieMap$;
        13: pop
        14: ldc           #26                 // class scala/collection/concurrent/INodeBase
        16: ldc           #28                 // class scala/collection/concurrent/MainNode
        18: ldc           #30                 // String mainnode
        20: invokestatic  #36                 // Method java/util/concurrent/atomic/AtomicReferenceFieldUpdater.newUpdater:(Ljava/lang/Class;Ljava/lang/Class;Ljava/lang/String;)Ljava/util/concurrent/atomic/AtomicReferenceFieldUpdater;
        23: putstatic     #38                 // Field inodeupdater:Ljava/util/concurrent/atomic/AtomicReferenceFieldUpdater;
        26: return
      LineNumberTable:
        line 1040: 0
        line 1049: 14
        line 1040: 26

  public java.lang.Object apply(scala.collection.immutable.Seq);
    descriptor: (Lscala/collection/immutable/Seq;)Ljava/lang/Object;
    flags: (0x0001) ACC_PUBLIC
    Code:
      stack=2, locals=2, args_size=2
         0: aload_0
         1: aload_1
         2: invokestatic  #45                 // InterfaceMethod scala/collection/MapFactory.apply$:(Lscala/collection/MapFactory;Lscala/collection/immutable/Seq;)Ljava/lang/Object;
         5: areturn
      LineNumberTable:
        line 1040: 0
      LocalVariableTable:
        Start  Length  Slot  Name   Signature
            0       6     0  this   Lscala/collection/concurrent/TrieMap$;
            0       6     1 elems   Lscala/collection/immutable/Seq;
    MethodParameters:
      Name                           Flags
      elems                          final

  public <K extends java.lang.Object, V extends java.lang.Object> scala.collection.Factory<scala.Tuple2<K, V>, scala.collection.concurrent.TrieMap<K, V>> mapFactory();
    descriptor: ()Lscala/collection/Factory;
    flags: (0x0001) ACC_PUBLIC
    Code:
      stack=1, locals=1, args_size=1
         0: aload_0
         1: invokestatic  #54                 // InterfaceMethod scala/collection/MapFactory.mapFactory$:(Lscala/collection/MapFactory;)Lscala/collection/Factory;
         4: areturn
      LineNumberTable:
        line 1040: 0
      LocalVariableTable:
        Start  Length  Slot  Name   Signature
            0       5     0  this   Lscala/collection/concurrent/TrieMap$;
    Signature: #50                          // <K:Ljava/lang/Object;V:Ljava/lang/Object;>()Lscala/collection/Factory<Lscala/Tuple2<TK;TV;>;Lscala/collection/concurrent/TrieMap<TK;TV;>;>;

  public <K extends java.lang.Object, V extends java.lang.Object> scala.collection.concurrent.TrieMap<K, V> empty();
    descriptor: ()Lscala/collection/concurrent/TrieMap;
    flags: (0x0001) ACC_PUBLIC
    Code:
      stack=2, locals=1, args_size=1
         0: new           #59                 // class scala/collection/concurrent/TrieMap
         3: dup
         4: invokespecial #60                 // Method scala/collection/concurrent/TrieMap."<init>":()V
         7: areturn
      LineNumberTable:
        line 1042: 0
      LocalVariableTable:
        Start  Length  Slot  Name   Signature
            0       8     0  this   Lscala/collection/concurrent/TrieMap$;
    Signature: #57                          // <K:Ljava/lang/Object;V:Ljava/lang/Object;>()Lscala/collection/concurrent/TrieMap<TK;TV;>;

  public <K extends java.lang.Object, V extends java.lang.Object> scala.collection.concurrent.TrieMap<K, V> from(scala.collection.IterableOnce<scala.Tuple2<K, V>>);
    descriptor: (Lscala/collection/IterableOnce;)Lscala/collection/concurrent/TrieMap;
    flags: (0x0001) ACC_PUBLIC
    Code:
      stack=2, locals=2, args_size=2
         0: new           #59                 // class scala/collection/concurrent/TrieMap
         3: dup
         4: invokespecial #60                 // Method scala/collection/concurrent/TrieMap."<init>":()V
         7: aload_1
         8: invokeinterface #70,  2           // InterfaceMethod scala/collection/mutable/Growable.addAll:(Lscala/collection/IterableOnce;)Lscala/collection/mutable/Growable;
        13: checkcast     #59                 // class scala/collection/concurrent/TrieMap
        16: areturn
      LineNumberTable:
        line 1044: 0
      LocalVariableTable:
        Start  Length  Slot  Name   Signature
            0      17     0  this   Lscala/collection/concurrent/TrieMap$;
            0      17     1    it   Lscala/collection/IterableOnce;
    Signature: #63                          // <K:Ljava/lang/Object;V:Ljava/lang/Object;>(Lscala/collection/IterableOnce<Lscala/Tuple2<TK;TV;>;>;)Lscala/collection/concurrent/TrieMap<TK;TV;>;
    MethodParameters:
      Name                           Flags
      it                             final

  public <K extends java.lang.Object, V extends java.lang.Object> scala.collection.mutable.GrowableBuilder<scala.Tuple2<K, V>, scala.collection.concurrent.TrieMap<K, V>> newBuilder();
    descriptor: ()Lscala/collection/mutable/GrowableBuilder;
    flags: (0x0001) ACC_PUBLIC
    Code:
      stack=4, locals=1, args_size=1
         0: new           #76                 // class scala/collection/mutable/GrowableBuilder
         3: dup
         4: new           #59                 // class scala/collection/concurrent/TrieMap
         7: dup
         8: invokespecial #60                 // Method scala/collection/concurrent/TrieMap."<init>":()V
        11: invokespecial #79                 // Method scala/collection/mutable/GrowableBuilder."<init>":(Lscala/collection/mutable/Growable;)V
        14: areturn
      LineNumberTable:
        line 1046: 0
        line 1042: 4
        line 1046: 11
      LocalVariableTable:
        Start  Length  Slot  Name   Signature
            0      15     0  this   Lscala/collection/concurrent/TrieMap$;
    Signature: #74                          // <K:Ljava/lang/Object;V:Ljava/lang/Object;>()Lscala/collection/mutable/GrowableBuilder<Lscala/Tuple2<TK;TV;>;Lscala/collection/concurrent/TrieMap<TK;TV;>;>;

  public java.util.concurrent.atomic.AtomicReferenceFieldUpdater<scala.collection.concurrent.INodeBase<?, ?>, scala.collection.concurrent.MainNode<?, ?>> inodeupdater();
    descriptor: ()Ljava/util/concurrent/atomic/AtomicReferenceFieldUpdater;
    flags: (0x0001) ACC_PUBLIC
    Code:
      stack=1, locals=1, args_size=1
         0: getstatic     #38                 // Field inodeupdater:Ljava/util/concurrent/atomic/AtomicReferenceFieldUpdater;
         3: areturn
      LineNumberTable:
        line 1049: 0
      LocalVariableTable:
        Start  Length  Slot  Name   Signature
            0       4     0  this   Lscala/collection/concurrent/TrieMap$;
    Signature: #81                          // ()Ljava/util/concurrent/atomic/AtomicReferenceFieldUpdater<Lscala/collection/concurrent/INodeBase<**>;Lscala/collection/concurrent/MainNode<**>;>;

  private java.lang.Object writeReplace();
    descriptor: ()Ljava/lang/Object;
    flags: (0x0002) ACC_PRIVATE
    Code:
      stack=3, locals=1, args_size=1
         0: new           #85                 // class scala/runtime/ModuleSerializationProxy
         3: dup
         4: ldc           #2                  // class scala/collection/concurrent/TrieMap$
         6: invokespecial #88                 // Method scala/runtime/ModuleSerializationProxy."<init>":(Ljava/lang/Class;)V
         9: areturn
      LineNumberTable:
        line 1040: 0
      LocalVariableTable:
        Start  Length  Slot  Name   Signature
            0      10     0  this   Lscala/collection/concurrent/TrieMap$;

  public scala.collection.mutable.Builder newBuilder();
    descriptor: ()Lscala/collection/mutable/Builder;
    flags: (0x1041) ACC_PUBLIC, ACC_BRIDGE, ACC_SYNTHETIC
    Code:
      stack=1, locals=1, args_size=1
         0: aload_0
         1: invokevirtual #91                 // Method newBuilder:()Lscala/collection/mutable/GrowableBuilder;
         4: areturn
      LineNumberTable:
        line 1040: 0
      LocalVariableTable:
        Start  Length  Slot  Name   Signature
            0       5     0  this   Lscala/collection/concurrent/TrieMap$;

  public java.lang.Object from(scala.collection.IterableOnce);
    descriptor: (Lscala/collection/IterableOnce;)Ljava/lang/Object;
    flags: (0x1041) ACC_PUBLIC, ACC_BRIDGE, ACC_SYNTHETIC
    Code:
      stack=2, locals=2, args_size=2
         0: aload_0
         1: aload_1
         2: invokevirtual #94                 // Method from:(Lscala/collection/IterableOnce;)Lscala/collection/concurrent/TrieMap;
         5: areturn
      LineNumberTable:
        line 1040: 0
      LocalVariableTable:
        Start  Length  Slot  Name   Signature
            0       6     0  this   Lscala/collection/concurrent/TrieMap$;
            0       6     1    it   Lscala/collection/IterableOnce;
    MethodParameters:
      Name                           Flags
      it                             final

  public java.lang.Object empty();
    descriptor: ()Ljava/lang/Object;
    flags: (0x1041) ACC_PUBLIC, ACC_BRIDGE, ACC_SYNTHETIC
    Code:
      stack=1, locals=1, args_size=1
         0: aload_0
         1: invokevirtual #96                 // Method empty:()Lscala/collection/concurrent/TrieMap;
         4: areturn
      LineNumberTable:
        line 1040: 0
      LocalVariableTable:
        Start  Length  Slot  Name   Signature
            0       5     0  this   Lscala/collection/concurrent/TrieMap$;

  private scala.collection.concurrent.TrieMap$();
    descriptor: ()V
    flags: (0x0002) ACC_PRIVATE
    Code:
      stack=1, locals=1, args_size=1
         0: aload_0
         1: invokespecial #97                 // Method java/lang/Object."<init>":()V
         4: return
      LineNumberTable:
        line 1040: 0
      LocalVariableTable:
        Start  Length  Slot  Name   Signature
            0       5     0  this   Lscala/collection/concurrent/TrieMap$;
}
Signature: #3                           // Ljava/lang/Object;Lscala/collection/MapFactory<Lscala/collection/concurrent/TrieMap;>;
SourceFile: "TrieMap.scala"
  ScalaInlineInfo: length = 0x3B (unknown attribute)
   01 01 00 0B 00 14 00 13 01 00 27 00 28 01 00 37
   00 53 01 00 37 00 38 01 00 3D 00 5C 01 00 3D 00
   3E 01 00 0F 00 50 01 00 30 00 31 01 00 48 00 59
   01 00 48 00 49 01 00 52 00 53 01
  Scala: length = 0x0 (unknown attribute)

