Classfile /Users/mw/Projects/slang-braindump/.jar/jar11/assemble/slang-braindump/assemble/content/scala/collection/concurrent/TrieMap$RemovalPolicy$.class
  Last modified May 29, 2022; size 1374 bytes
  SHA-256 checksum 5a43a8c0c53a5c3299d20fe6ac986657a6108d81290b8a6be97e940d4eaacffd
  Compiled from "TrieMap.scala"
public class scala.collection.concurrent.TrieMap$RemovalPolicy$
  minor version: 0
  major version: 52
  flags: (0x0021) ACC_PUBLIC, ACC_SUPER
  this_class: #2                          // scala/collection/concurrent/TrieMap$RemovalPolicy$
  super_class: #4                         // java/lang/Object
  interfaces: 0, fields: 1, methods: 6, attributes: 4
Constant pool:
   #1 = Utf8               scala/collection/concurrent/TrieMap$RemovalPolicy$
   #2 = Class              #1             // scala/collection/concurrent/TrieMap$RemovalPolicy$
   #3 = Utf8               java/lang/Object
   #4 = Class              #3             // java/lang/Object
   #5 = Utf8               TrieMap.scala
   #6 = Utf8               scala/collection/concurrent/TrieMap
   #7 = Class              #6             // scala/collection/concurrent/TrieMap
   #8 = Utf8               RemovalPolicy$
   #9 = Utf8               MODULE$
  #10 = Utf8               Lscala/collection/concurrent/TrieMap$RemovalPolicy$;
  #11 = Utf8               <clinit>
  #12 = Utf8               ()V
  #13 = Utf8               <init>
  #14 = NameAndType        #13:#12        // "<init>":()V
  #15 = Methodref          #2.#14         // scala/collection/concurrent/TrieMap$RemovalPolicy$."<init>":()V
  #16 = NameAndType        #9:#10         // MODULE$:Lscala/collection/concurrent/TrieMap$RemovalPolicy$;
  #17 = Fieldref           #2.#16         // scala/collection/concurrent/TrieMap$RemovalPolicy$.MODULE$:Lscala/collection/concurrent/TrieMap$RemovalPolicy$;
  #18 = Utf8               Always
  #19 = Utf8               ()I
  #20 = Utf8               this
  #21 = Utf8               FullEquals
  #22 = Utf8               ReferenceEq
  #23 = Utf8               shouldRemove
  #24 = Utf8               (ILjava/lang/Object;Ljava/lang/Object;)Z
  #25 = Utf8               <V:Ljava/lang/Object;>(ITV;TV;)Z
  #26 = Utf8               removalPolicy
  #27 = Utf8               a
  #28 = Utf8               b
  #29 = Utf8               scala/runtime/BoxesRunTime
  #30 = Class              #29            // scala/runtime/BoxesRunTime
  #31 = Utf8               equals
  #32 = Utf8               (Ljava/lang/Object;Ljava/lang/Object;)Z
  #33 = NameAndType        #31:#32        // equals:(Ljava/lang/Object;Ljava/lang/Object;)Z
  #34 = Methodref          #30.#33        // scala/runtime/BoxesRunTime.equals:(Ljava/lang/Object;Ljava/lang/Object;)Z
  #35 = Utf8               scala/MatchError
  #36 = Class              #35            // scala/MatchError
  #37 = Utf8               java/lang/Integer
  #38 = Class              #37            // java/lang/Integer
  #39 = Utf8               valueOf
  #40 = Utf8               (I)Ljava/lang/Integer;
  #41 = NameAndType        #39:#40        // valueOf:(I)Ljava/lang/Integer;
  #42 = Methodref          #38.#41        // java/lang/Integer.valueOf:(I)Ljava/lang/Integer;
  #43 = Utf8               (Ljava/lang/Object;)V
  #44 = NameAndType        #13:#43        // "<init>":(Ljava/lang/Object;)V
  #45 = Methodref          #36.#44        // scala/MatchError."<init>":(Ljava/lang/Object;)V
  #46 = Utf8               I
  #47 = Utf8               Ljava/lang/Object;
  #48 = Methodref          #4.#14         // java/lang/Object."<init>":()V
  #49 = Utf8               Code
  #50 = Utf8               LineNumberTable
  #51 = Utf8               LocalVariableTable
  #52 = Utf8               StackMapTable
  #53 = Utf8               Signature
  #54 = Utf8               MethodParameters
  #55 = Utf8               InnerClasses
  #56 = Utf8               SourceFile
  #57 = Utf8               ScalaInlineInfo
  #58 = Utf8               Scala
{
  public static final scala.collection.concurrent.TrieMap$RemovalPolicy$ MODULE$;
    descriptor: Lscala/collection/concurrent/TrieMap$RemovalPolicy$;
    flags: (0x0019) ACC_PUBLIC, ACC_STATIC, ACC_FINAL

  public static {};
    descriptor: ()V
    flags: (0x0009) ACC_PUBLIC, ACC_STATIC
    Code:
      stack=2, locals=0, args_size=0
         0: new           #2                  // class scala/collection/concurrent/TrieMap$RemovalPolicy$
         3: dup
         4: invokespecial #15                 // Method "<init>":()V
         7: putstatic     #17                 // Field MODULE$:Lscala/collection/concurrent/TrieMap$RemovalPolicy$;
        10: return
      LineNumberTable:
        line 1055: 0

  public final int Always();
    descriptor: ()I
    flags: (0x0011) ACC_PUBLIC, ACC_FINAL
    Code:
      stack=1, locals=1, args_size=1
         0: iconst_0
         1: ireturn
      LocalVariableTable:
        Start  Length  Slot  Name   Signature
            0       2     0  this   Lscala/collection/concurrent/TrieMap$RemovalPolicy$;

  public final int FullEquals();
    descriptor: ()I
    flags: (0x0011) ACC_PUBLIC, ACC_FINAL
    Code:
      stack=1, locals=1, args_size=1
         0: iconst_1
         1: ireturn
      LocalVariableTable:
        Start  Length  Slot  Name   Signature
            0       2     0  this   Lscala/collection/concurrent/TrieMap$RemovalPolicy$;

  public final int ReferenceEq();
    descriptor: ()I
    flags: (0x0011) ACC_PUBLIC, ACC_FINAL
    Code:
      stack=1, locals=1, args_size=1
         0: iconst_2
         1: ireturn
      LocalVariableTable:
        Start  Length  Slot  Name   Signature
            0       2     0  this   Lscala/collection/concurrent/TrieMap$RemovalPolicy$;

  public <V extends java.lang.Object> boolean shouldRemove(int, V, V);
    descriptor: (ILjava/lang/Object;Ljava/lang/Object;)Z
    flags: (0x0001) ACC_PUBLIC
    Code:
      stack=3, locals=4, args_size=4
         0: iload_1
         1: tableswitch   { // 0 to 2
                       0: 28
                       1: 30
                       2: 42
                 default: 51
            }
        28: iconst_1
        29: ireturn
        30: aload_2
        31: aload_3
        32: invokestatic  #34                 // Method scala/runtime/BoxesRunTime.equals:(Ljava/lang/Object;Ljava/lang/Object;)Z
        35: ifeq          40
        38: iconst_1
        39: ireturn
        40: iconst_0
        41: ireturn
        42: aload_2
        43: aload_3
        44: if_acmpne     49
        47: iconst_1
        48: ireturn
        49: iconst_0
        50: ireturn
        51: new           #36                 // class scala/MatchError
        54: dup
        55: iload_1
        56: invokestatic  #42                 // Method java/lang/Integer.valueOf:(I)Ljava/lang/Integer;
        59: invokespecial #45                 // Method scala/MatchError."<init>":(Ljava/lang/Object;)V
        62: athrow
      StackMapTable: number_of_entries = 6
        frame_type = 28 /* same */
        frame_type = 1 /* same */
        frame_type = 9 /* same */
        frame_type = 1 /* same */
        frame_type = 6 /* same */
        frame_type = 1 /* same */
      LineNumberTable:
        line 1061: 0
        line 1062: 28
        line 1063: 30
        line 1064: 42
        line 1061: 51
      LocalVariableTable:
        Start  Length  Slot  Name   Signature
            0      63     0  this   Lscala/collection/concurrent/TrieMap$RemovalPolicy$;
            0      63     1 removalPolicy   I
            0      63     2     a   Ljava/lang/Object;
            0      63     3     b   Ljava/lang/Object;
    Signature: #25                          // <V:Ljava/lang/Object;>(ITV;TV;)Z
    MethodParameters:
      Name                           Flags
      removalPolicy                  final
      a                              final
      b                              final

  public scala.collection.concurrent.TrieMap$RemovalPolicy$();
    descriptor: ()V
    flags: (0x0001) ACC_PUBLIC
    Code:
      stack=1, locals=1, args_size=1
         0: aload_0
         1: invokespecial #48                 // Method java/lang/Object."<init>":()V
         4: return
      LineNumberTable:
        line 1055: 0
      LocalVariableTable:
        Start  Length  Slot  Name   Signature
            0       5     0  this   Lscala/collection/concurrent/TrieMap$RemovalPolicy$;
}
InnerClasses:
  public static #8= #2 of #7;             // RemovalPolicy$=class scala/collection/concurrent/TrieMap$RemovalPolicy$ of class scala/collection/concurrent/TrieMap
SourceFile: "TrieMap.scala"
  ScalaInlineInfo: length = 0x1D (unknown attribute)
   01 01 00 05 00 0D 00 0C 01 00 12 00 13 01 00 15
   00 13 01 00 16 00 13 01 00 17 00 18 01
  Scala: length = 0x0 (unknown attribute)

