Classfile /Users/mw/Projects/slang-braindump/.jar/jar11/assemble/slang-braindump/assemble/content/argonaut/internal/MacrosCompat.class
  Last modified May 29, 2022; size 5025 bytes
  SHA-256 checksum d14f7361302d6fb5c864f1541b8635c988191d4c0d31a4baf545c0d8523ed075
  Compiled from "MacrosCompat.scala"
public interface argonaut.internal.MacrosCompat
  minor version: 0
  major version: 52
  flags: (0x0601) ACC_PUBLIC, ACC_INTERFACE, ACC_ABSTRACT
  this_class: #2                          // argonaut/internal/MacrosCompat
  super_class: #4                         // java/lang/Object
  interfaces: 0, fields: 0, methods: 9, attributes: 5
Constant pool:
    #1 = Utf8               argonaut/internal/MacrosCompat
    #2 = Class              #1            // argonaut/internal/MacrosCompat
    #3 = Utf8               java/lang/Object
    #4 = Class              #3            // java/lang/Object
    #5 = Utf8               MacrosCompat.scala
    #6 = Utf8               Lscala/reflect/ScalaSignature;
    #7 = Utf8               bytes
    #8 = Utf8               \u0006\u0005q4qa\u0002\u0005\u0011\u0002\u0007\u0005Q\u0002C\u0003\u0015\u0001\u0011\u0005Q#\u0002\u0003\u001a\u0001\u0001Q\u0002\"B\u0012\u0001\t\u0003!\u0003\"B\u001f\u0001\t\u0003q\u0004\"\u0002.\u0001\t\u0003Y\u0006\"\u00026\u0001\t\u0003Y\'\u0001D\'bGJ|7oQ8na\u0006$(BA\u0005\u000b\u0003!Ig\u000e^3s]\u0006d\'\"A\u0006\u0002\u0011\u0005\u0014xm\u001c8bkR\u001c\u0001a\u0005\u0002\u0001\u001dA\u0011qBE\u0007\u0002!)\t\u0011#A\u0003tG\u0006d\u0017-\u0003\u0002\u0014!\t1\u0011I\\=SK\u001a\fa\u0001J5oSR$C#\u0001\f\u0011\u0005=9\u0012B\u0001\r\u0011\u0005\u0011)f.\u001b;\u0003\u000f\r{g\u000e^3yiB\u00111DI\u0007\u00029)\u0011QDH\u0001\tE2\f7m\u001b2pq*\u0011q\u0004I\u0001\u0007[\u0006\u001c\'o\\:\u000b\u0005\u0005\u0002\u0012a\u0002:fM2,7\r^\u0005\u00033q\tqbZ3u\t\u0016\u001cG.\u0019:bi&|gn\u001d\u000b\u0003K)\"\"A\n\u001c\u0011\u0005\u001d\u0002dB\u0001\u0015/\u001d\tI#\u0006\u0004\u0001\t\u000b-\u001a\u0001\u0019\u0001\u0017\u0002\u0003\r\u0004\"!\f\u0002\u000e\u0003\u0001I!a\f\u0012\u0002\u0011Ut\u0017N^3sg\u0016L!!\r\u001a\u0003\u00175+WNY3s\'\u000e|\u0007/Z\u0005\u0003gQ\u0012aaU2pa\u0016\u001c(BA\u001b!\u0003\r\t\u0007/\u001b\u0005\u0006o\r\u0001\r\u0001O\u0001\u0004iB,\u0007CA\u0014:\u0013\tQ4H\u0001\u0003UsB,\u0017B\u0001\u001f5\u0005\u0015!\u0016\u0010]3t\u0003E9W\r\u001e)be\u0006lW\r^3s\u0019&\u001cHo\u001d\u000b\u0003\u007fA#\"\u0001Q+\u0011\u0007\u0005KEJ\u0004\u0002C\u000f:\u00111IR\u0007\u0002\t*\u0011Q\tD\u0001\u0007yI|w\u000e\u001e \n\u0003EI!\u0001\u0013\t\u0002\u000fA\f7m[1hK&\u0011!j\u0013\u0002\u0005\u0019&\u001cHO\u0003\u0002I!A\u0019\u0011)S\'\u0011\u00059\u000bfBA(/\u001d\tI\u0003\u000bC\u0003,\t\u0001\u0007A&\u0003\u0002S\'\n11+_7c_2L!\u0001\u0016\u001b\u0003\u000fMKXNY8mg\")a\u000b\u0002a\u0001/\u00061Q.\u001a;i_\u0012\u0004\"A\u0014-\n\u0005e\u001b&\u0001D\'fi\"|GmU=nE>d\u0017AD4fi\u0012+7\r\\1sCRLwN\u001c\u000b\u00039\u0002$2!X1d!\tq\u0016K\u0004\u0002`]9\u0011\u0011\u0006\u0019\u0005\u0006W\u0015\u0001\r\u0001\f\u0005\u0006o\u0015\u0001\rA\u0019\t\u0003=fBQ\u0001Z\u0003A\u0002\u0015\fAA\\1nKB\u0011aLZ\u0005\u0003O\"\u0014AAT1nK&\u0011\u0011\u000e\u000e\u0002\u0006\u001d\u0006lWm]\u0001\u000fGJ,\u0017\r^3UKJlg*Y7f)\ta\u0007\u000f\u0006\u0002ngB\u0011a.\u001d\b\u0003_:r!!\u000b9\t\u000b-2\u0001\u0019\u0001\u0017\n\u0005ID\'\u0001\u0003+fe6t\u0015-\\3\t\u000b\u00114\u0001\u0019\u0001;\u0011\u0005ULhB\u0001<x!\t\u0019\u0005#\u0003\u0002y!\u00051\u0001K]3eK\u001aL!A_>\u0003\rM#(/\u001b8h\u0015\tA\b\u0003
    #9 = Utf8               scala/reflect/api/Names$NameApi
   #10 = Class              #9            // scala/reflect/api/Names$NameApi
   #11 = Utf8               scala/reflect/api/Names
   #12 = Class              #11           // scala/reflect/api/Names
   #13 = Utf8               NameApi
   #14 = Utf8               scala/reflect/api/Names$TermNameApi
   #15 = Class              #14           // scala/reflect/api/Names$TermNameApi
   #16 = Utf8               TermNameApi
   #17 = Utf8               scala/reflect/api/Names$TermNameExtractor
   #18 = Class              #17           // scala/reflect/api/Names$TermNameExtractor
   #19 = Utf8               TermNameExtractor
   #20 = Utf8               scala/reflect/api/Scopes$MemberScopeApi
   #21 = Class              #20           // scala/reflect/api/Scopes$MemberScopeApi
   #22 = Utf8               scala/reflect/api/Scopes
   #23 = Class              #22           // scala/reflect/api/Scopes
   #24 = Utf8               MemberScopeApi
   #25 = Utf8               scala/reflect/api/Symbols$MethodSymbolApi
   #26 = Class              #25           // scala/reflect/api/Symbols$MethodSymbolApi
   #27 = Utf8               scala/reflect/api/Symbols
   #28 = Class              #27           // scala/reflect/api/Symbols
   #29 = Utf8               MethodSymbolApi
   #30 = Utf8               scala/reflect/api/Symbols$SymbolApi
   #31 = Class              #30           // scala/reflect/api/Symbols$SymbolApi
   #32 = Utf8               SymbolApi
   #33 = Utf8               scala/reflect/api/Types$TypeApi
   #34 = Class              #33           // scala/reflect/api/Types$TypeApi
   #35 = Utf8               scala/reflect/api/Types
   #36 = Class              #35           // scala/reflect/api/Types
   #37 = Utf8               TypeApi
   #38 = Utf8               getDeclarations$
   #39 = Utf8               (Largonaut/internal/MacrosCompat;Lscala/reflect/macros/blackbox/Context;Lscala/reflect/api/Types$TypeApi;)Lscala/reflect/api/Scopes$MemberScopeApi;
   #40 = Utf8               $this
   #41 = Utf8               c
   #42 = Utf8               tpe
   #43 = Utf8               getDeclarations
   #44 = Utf8               (Lscala/reflect/macros/blackbox/Context;Lscala/reflect/api/Types$TypeApi;)Lscala/reflect/api/Scopes$MemberScopeApi;
   #45 = NameAndType        #43:#44       // getDeclarations:(Lscala/reflect/macros/blackbox/Context;Lscala/reflect/api/Types$TypeApi;)Lscala/reflect/api/Scopes$MemberScopeApi;
   #46 = InterfaceMethodref #2.#45        // argonaut/internal/MacrosCompat.getDeclarations:(Lscala/reflect/macros/blackbox/Context;Lscala/reflect/api/Types$TypeApi;)Lscala/reflect/api/Scopes$MemberScopeApi;
   #47 = Utf8               Largonaut/internal/MacrosCompat;
   #48 = Utf8               Lscala/reflect/macros/blackbox/Context;
   #49 = Utf8               Lscala/reflect/api/Types$TypeApi;
   #50 = Utf8               decls
   #51 = Utf8               ()Lscala/reflect/api/Scopes$MemberScopeApi;
   #52 = NameAndType        #50:#51       // decls:()Lscala/reflect/api/Scopes$MemberScopeApi;
   #53 = Methodref          #34.#52       // scala/reflect/api/Types$TypeApi.decls:()Lscala/reflect/api/Scopes$MemberScopeApi;
   #54 = Utf8               this
   #55 = Utf8               getParameterLists$
   #56 = Utf8               (Largonaut/internal/MacrosCompat;Lscala/reflect/macros/blackbox/Context;Lscala/reflect/api/Symbols$MethodSymbolApi;)Lscala/collection/immutable/List;
   #57 = Utf8               method
   #58 = Utf8               getParameterLists
   #59 = Utf8               (Lscala/reflect/macros/blackbox/Context;Lscala/reflect/api/Symbols$MethodSymbolApi;)Lscala/collection/immutable/List;
   #60 = NameAndType        #58:#59       // getParameterLists:(Lscala/reflect/macros/blackbox/Context;Lscala/reflect/api/Symbols$MethodSymbolApi;)Lscala/collection/immutable/List;
   #61 = InterfaceMethodref #2.#60        // argonaut/internal/MacrosCompat.getParameterLists:(Lscala/reflect/macros/blackbox/Context;Lscala/reflect/api/Symbols$MethodSymbolApi;)Lscala/collection/immutable/List;
   #62 = Utf8               Lscala/reflect/api/Symbols$MethodSymbolApi;
   #63 = Utf8               (Lscala/reflect/macros/blackbox/Context;Lscala/reflect/api/Symbols$MethodSymbolApi;)Lscala/collection/immutable/List<Lscala/collection/immutable/List<Lscala/reflect/api/Symbols$SymbolApi;>;>;
   #64 = Utf8               paramLists
   #65 = Utf8               ()Lscala/collection/immutable/List;
   #66 = NameAndType        #64:#65       // paramLists:()Lscala/collection/immutable/List;
   #67 = InterfaceMethodref #26.#66       // scala/reflect/api/Symbols$MethodSymbolApi.paramLists:()Lscala/collection/immutable/List;
   #68 = Utf8               getDeclaration$
   #69 = Utf8               (Largonaut/internal/MacrosCompat;Lscala/reflect/macros/blackbox/Context;Lscala/reflect/api/Types$TypeApi;Lscala/reflect/api/Names$NameApi;)Lscala/reflect/api/Symbols$SymbolApi;
   #70 = Utf8               name
   #71 = Utf8               getDeclaration
   #72 = Utf8               (Lscala/reflect/macros/blackbox/Context;Lscala/reflect/api/Types$TypeApi;Lscala/reflect/api/Names$NameApi;)Lscala/reflect/api/Symbols$SymbolApi;
   #73 = NameAndType        #71:#72       // getDeclaration:(Lscala/reflect/macros/blackbox/Context;Lscala/reflect/api/Types$TypeApi;Lscala/reflect/api/Names$NameApi;)Lscala/reflect/api/Symbols$SymbolApi;
   #74 = InterfaceMethodref #2.#73        // argonaut/internal/MacrosCompat.getDeclaration:(Lscala/reflect/macros/blackbox/Context;Lscala/reflect/api/Types$TypeApi;Lscala/reflect/api/Names$NameApi;)Lscala/reflect/api/Symbols$SymbolApi;
   #75 = Utf8               Lscala/reflect/api/Names$NameApi;
   #76 = Utf8               decl
   #77 = Utf8               (Lscala/reflect/api/Names$NameApi;)Lscala/reflect/api/Symbols$SymbolApi;
   #78 = NameAndType        #76:#77       // decl:(Lscala/reflect/api/Names$NameApi;)Lscala/reflect/api/Symbols$SymbolApi;
   #79 = Methodref          #34.#78       // scala/reflect/api/Types$TypeApi.decl:(Lscala/reflect/api/Names$NameApi;)Lscala/reflect/api/Symbols$SymbolApi;
   #80 = Utf8               createTermName$
   #81 = Utf8               (Largonaut/internal/MacrosCompat;Lscala/reflect/macros/blackbox/Context;Ljava/lang/String;)Lscala/reflect/api/Names$TermNameApi;
   #82 = Utf8               createTermName
   #83 = Utf8               (Lscala/reflect/macros/blackbox/Context;Ljava/lang/String;)Lscala/reflect/api/Names$TermNameApi;
   #84 = NameAndType        #82:#83       // createTermName:(Lscala/reflect/macros/blackbox/Context;Ljava/lang/String;)Lscala/reflect/api/Names$TermNameApi;
   #85 = InterfaceMethodref #2.#84        // argonaut/internal/MacrosCompat.createTermName:(Lscala/reflect/macros/blackbox/Context;Ljava/lang/String;)Lscala/reflect/api/Names$TermNameApi;
   #86 = Utf8               Ljava/lang/String;
   #87 = Utf8               scala/reflect/macros/blackbox/Context
   #88 = Class              #87           // scala/reflect/macros/blackbox/Context
   #89 = Utf8               universe
   #90 = Utf8               ()Lscala/reflect/macros/Universe;
   #91 = NameAndType        #89:#90       // universe:()Lscala/reflect/macros/Universe;
   #92 = InterfaceMethodref #88.#91       // scala/reflect/macros/blackbox/Context.universe:()Lscala/reflect/macros/Universe;
   #93 = Utf8               scala/reflect/macros/Universe
   #94 = Class              #93           // scala/reflect/macros/Universe
   #95 = Utf8               TermName
   #96 = Utf8               ()Lscala/reflect/api/Names$TermNameExtractor;
   #97 = NameAndType        #95:#96       // TermName:()Lscala/reflect/api/Names$TermNameExtractor;
   #98 = Methodref          #94.#97       // scala/reflect/macros/Universe.TermName:()Lscala/reflect/api/Names$TermNameExtractor;
   #99 = Utf8               apply
  #100 = Utf8               (Ljava/lang/String;)Lscala/reflect/api/Names$TermNameApi;
  #101 = NameAndType        #99:#100      // apply:(Ljava/lang/String;)Lscala/reflect/api/Names$TermNameApi;
  #102 = Methodref          #18.#101      // scala/reflect/api/Names$TermNameExtractor.apply:(Ljava/lang/String;)Lscala/reflect/api/Names$TermNameApi;
  #103 = Utf8               $init$
  #104 = Utf8               (Largonaut/internal/MacrosCompat;)V
  #105 = Utf8               Code
  #106 = Utf8               LineNumberTable
  #107 = Utf8               LocalVariableTable
  #108 = Utf8               MethodParameters
  #109 = Utf8               Signature
  #110 = Utf8               InnerClasses
  #111 = Utf8               SourceFile
  #112 = Utf8               RuntimeVisibleAnnotations
  #113 = Utf8               ScalaInlineInfo
  #114 = Utf8               ScalaSig
{
  public static scala.reflect.api.Scopes$MemberScopeApi getDeclarations$(argonaut.internal.MacrosCompat, scala.reflect.macros.blackbox.Context, scala.reflect.api.Types$TypeApi);
    descriptor: (Largonaut/internal/MacrosCompat;Lscala/reflect/macros/blackbox/Context;Lscala/reflect/api/Types$TypeApi;)Lscala/reflect/api/Scopes$MemberScopeApi;
    flags: (0x1009) ACC_PUBLIC, ACC_STATIC, ACC_SYNTHETIC
    Code:
      stack=3, locals=3, args_size=3
         0: aload_0
         1: aload_1
         2: aload_2
         3: invokespecial #46                 // InterfaceMethod getDeclarations:(Lscala/reflect/macros/blackbox/Context;Lscala/reflect/api/Types$TypeApi;)Lscala/reflect/api/Scopes$MemberScopeApi;
         6: areturn
      LineNumberTable:
        line 6: 0
      LocalVariableTable:
        Start  Length  Slot  Name   Signature
            0       7     0 $this   Largonaut/internal/MacrosCompat;
            0       7     1     c   Lscala/reflect/macros/blackbox/Context;
            0       7     2   tpe   Lscala/reflect/api/Types$TypeApi;
    MethodParameters:
      Name                           Flags
      $this                          final synthetic
      c                              final
      tpe                            final

  public default scala.reflect.api.Scopes$MemberScopeApi getDeclarations(scala.reflect.macros.blackbox.Context, scala.reflect.api.Types$TypeApi);
    descriptor: (Lscala/reflect/macros/blackbox/Context;Lscala/reflect/api/Types$TypeApi;)Lscala/reflect/api/Scopes$MemberScopeApi;
    flags: (0x0001) ACC_PUBLIC
    Code:
      stack=1, locals=4, args_size=3
         0: aload_2
         1: astore_3
         2: aload_3
         3: invokevirtual #53                 // Method scala/reflect/api/Types$TypeApi.decls:()Lscala/reflect/api/Scopes$MemberScopeApi;
         6: areturn
      LineNumberTable:
        line 6: 0
      LocalVariableTable:
        Start  Length  Slot  Name   Signature
            0       7     0  this   Largonaut/internal/MacrosCompat;
            0       7     1     c   Lscala/reflect/macros/blackbox/Context;
            0       7     2   tpe   Lscala/reflect/api/Types$TypeApi;
    Signature: #44                          // (Lscala/reflect/macros/blackbox/Context;Lscala/reflect/api/Types$TypeApi;)Lscala/reflect/api/Scopes$MemberScopeApi;
    MethodParameters:
      Name                           Flags
      c                              final
      tpe                            final

  public static scala.collection.immutable.List getParameterLists$(argonaut.internal.MacrosCompat, scala.reflect.macros.blackbox.Context, scala.reflect.api.Symbols$MethodSymbolApi);
    descriptor: (Largonaut/internal/MacrosCompat;Lscala/reflect/macros/blackbox/Context;Lscala/reflect/api/Symbols$MethodSymbolApi;)Lscala/collection/immutable/List;
    flags: (0x1009) ACC_PUBLIC, ACC_STATIC, ACC_SYNTHETIC
    Code:
      stack=3, locals=3, args_size=3
         0: aload_0
         1: aload_1
         2: aload_2
         3: invokespecial #61                 // InterfaceMethod getParameterLists:(Lscala/reflect/macros/blackbox/Context;Lscala/reflect/api/Symbols$MethodSymbolApi;)Lscala/collection/immutable/List;
         6: areturn
      LineNumberTable:
        line 8: 0
      LocalVariableTable:
        Start  Length  Slot  Name   Signature
            0       7     0 $this   Largonaut/internal/MacrosCompat;
            0       7     1     c   Lscala/reflect/macros/blackbox/Context;
            0       7     2 method   Lscala/reflect/api/Symbols$MethodSymbolApi;
    MethodParameters:
      Name                           Flags
      $this                          final synthetic
      c                              final
      method                         final

  public default scala.collection.immutable.List<scala.collection.immutable.List<scala.reflect.api.Symbols$SymbolApi>> getParameterLists(scala.reflect.macros.blackbox.Context, scala.reflect.api.Symbols$MethodSymbolApi);
    descriptor: (Lscala/reflect/macros/blackbox/Context;Lscala/reflect/api/Symbols$MethodSymbolApi;)Lscala/collection/immutable/List;
    flags: (0x0001) ACC_PUBLIC
    Code:
      stack=1, locals=4, args_size=3
         0: aload_2
         1: astore_3
         2: aload_3
         3: invokeinterface #67,  1           // InterfaceMethod scala/reflect/api/Symbols$MethodSymbolApi.paramLists:()Lscala/collection/immutable/List;
         8: areturn
      LineNumberTable:
        line 8: 0
      LocalVariableTable:
        Start  Length  Slot  Name   Signature
            0       9     0  this   Largonaut/internal/MacrosCompat;
            0       9     1     c   Lscala/reflect/macros/blackbox/Context;
            0       9     2 method   Lscala/reflect/api/Symbols$MethodSymbolApi;
    Signature: #63                          // (Lscala/reflect/macros/blackbox/Context;Lscala/reflect/api/Symbols$MethodSymbolApi;)Lscala/collection/immutable/List<Lscala/collection/immutable/List<Lscala/reflect/api/Symbols$SymbolApi;>;>;
    MethodParameters:
      Name                           Flags
      c                              final
      method                         final

  public static scala.reflect.api.Symbols$SymbolApi getDeclaration$(argonaut.internal.MacrosCompat, scala.reflect.macros.blackbox.Context, scala.reflect.api.Types$TypeApi, scala.reflect.api.Names$NameApi);
    descriptor: (Largonaut/internal/MacrosCompat;Lscala/reflect/macros/blackbox/Context;Lscala/reflect/api/Types$TypeApi;Lscala/reflect/api/Names$NameApi;)Lscala/reflect/api/Symbols$SymbolApi;
    flags: (0x1009) ACC_PUBLIC, ACC_STATIC, ACC_SYNTHETIC
    Code:
      stack=4, locals=4, args_size=4
         0: aload_0
         1: aload_1
         2: aload_2
         3: aload_3
         4: invokespecial #74                 // InterfaceMethod getDeclaration:(Lscala/reflect/macros/blackbox/Context;Lscala/reflect/api/Types$TypeApi;Lscala/reflect/api/Names$NameApi;)Lscala/reflect/api/Symbols$SymbolApi;
         7: areturn
      LineNumberTable:
        line 10: 0
      LocalVariableTable:
        Start  Length  Slot  Name   Signature
            0       8     0 $this   Largonaut/internal/MacrosCompat;
            0       8     1     c   Lscala/reflect/macros/blackbox/Context;
            0       8     2   tpe   Lscala/reflect/api/Types$TypeApi;
            0       8     3  name   Lscala/reflect/api/Names$NameApi;
    MethodParameters:
      Name                           Flags
      $this                          final synthetic
      c                              final
      tpe                            final
      name                           final

  public default scala.reflect.api.Symbols$SymbolApi getDeclaration(scala.reflect.macros.blackbox.Context, scala.reflect.api.Types$TypeApi, scala.reflect.api.Names$NameApi);
    descriptor: (Lscala/reflect/macros/blackbox/Context;Lscala/reflect/api/Types$TypeApi;Lscala/reflect/api/Names$NameApi;)Lscala/reflect/api/Symbols$SymbolApi;
    flags: (0x0001) ACC_PUBLIC
    Code:
      stack=2, locals=6, args_size=4
         0: aload_2
         1: astore        4
         3: aload_3
         4: astore        5
         6: aload         4
         8: aload         5
        10: invokevirtual #79                 // Method scala/reflect/api/Types$TypeApi.decl:(Lscala/reflect/api/Names$NameApi;)Lscala/reflect/api/Symbols$SymbolApi;
        13: areturn
      LineNumberTable:
        line 10: 0
      LocalVariableTable:
        Start  Length  Slot  Name   Signature
            0      14     0  this   Largonaut/internal/MacrosCompat;
            0      14     1     c   Lscala/reflect/macros/blackbox/Context;
            0      14     2   tpe   Lscala/reflect/api/Types$TypeApi;
            0      14     3  name   Lscala/reflect/api/Names$NameApi;
    Signature: #72                          // (Lscala/reflect/macros/blackbox/Context;Lscala/reflect/api/Types$TypeApi;Lscala/reflect/api/Names$NameApi;)Lscala/reflect/api/Symbols$SymbolApi;
    MethodParameters:
      Name                           Flags
      c                              final
      tpe                            final
      name                           final

  public static scala.reflect.api.Names$TermNameApi createTermName$(argonaut.internal.MacrosCompat, scala.reflect.macros.blackbox.Context, java.lang.String);
    descriptor: (Largonaut/internal/MacrosCompat;Lscala/reflect/macros/blackbox/Context;Ljava/lang/String;)Lscala/reflect/api/Names$TermNameApi;
    flags: (0x1009) ACC_PUBLIC, ACC_STATIC, ACC_SYNTHETIC
    Code:
      stack=3, locals=3, args_size=3
         0: aload_0
         1: aload_1
         2: aload_2
         3: invokespecial #85                 // InterfaceMethod createTermName:(Lscala/reflect/macros/blackbox/Context;Ljava/lang/String;)Lscala/reflect/api/Names$TermNameApi;
         6: areturn
      LineNumberTable:
        line 12: 0
      LocalVariableTable:
        Start  Length  Slot  Name   Signature
            0       7     0 $this   Largonaut/internal/MacrosCompat;
            0       7     1     c   Lscala/reflect/macros/blackbox/Context;
            0       7     2  name   Ljava/lang/String;
    MethodParameters:
      Name                           Flags
      $this                          final synthetic
      c                              final
      name                           final

  public default scala.reflect.api.Names$TermNameApi createTermName(scala.reflect.macros.blackbox.Context, java.lang.String);
    descriptor: (Lscala/reflect/macros/blackbox/Context;Ljava/lang/String;)Lscala/reflect/api/Names$TermNameApi;
    flags: (0x0001) ACC_PUBLIC
    Code:
      stack=2, locals=3, args_size=3
         0: aload_1
         1: invokeinterface #92,  1           // InterfaceMethod scala/reflect/macros/blackbox/Context.universe:()Lscala/reflect/macros/Universe;
         6: invokevirtual #98                 // Method scala/reflect/macros/Universe.TermName:()Lscala/reflect/api/Names$TermNameExtractor;
         9: aload_2
        10: invokevirtual #102                // Method scala/reflect/api/Names$TermNameExtractor.apply:(Ljava/lang/String;)Lscala/reflect/api/Names$TermNameApi;
        13: areturn
      LineNumberTable:
        line 12: 0
      LocalVariableTable:
        Start  Length  Slot  Name   Signature
            0      14     0  this   Largonaut/internal/MacrosCompat;
            0      14     1     c   Lscala/reflect/macros/blackbox/Context;
            0      14     2  name   Ljava/lang/String;
    MethodParameters:
      Name                           Flags
      c                              final
      name                           final

  public static void $init$(argonaut.internal.MacrosCompat);
    descriptor: (Largonaut/internal/MacrosCompat;)V
    flags: (0x0009) ACC_PUBLIC, ACC_STATIC
    Code:
      stack=0, locals=1, args_size=1
         0: return
      LineNumberTable:
        line 3: 0
      LocalVariableTable:
        Start  Length  Slot  Name   Signature
            0       1     0 $this   Largonaut/internal/MacrosCompat;
    MethodParameters:
      Name                           Flags
      $this                          final synthetic
}
InnerClasses:
  public abstract #13= #10 of #12;        // NameApi=class scala/reflect/api/Names$NameApi of class scala/reflect/api/Names
  public #16= #15 of #12;                 // TermNameApi=class scala/reflect/api/Names$TermNameApi of class scala/reflect/api/Names
  public abstract #19= #18 of #12;        // TermNameExtractor=class scala/reflect/api/Names$TermNameExtractor of class scala/reflect/api/Names
  public #24= #21 of #23;                 // MemberScopeApi=class scala/reflect/api/Scopes$MemberScopeApi of class scala/reflect/api/Scopes
  public #29= #26 of #28;                 // MethodSymbolApi=class scala/reflect/api/Symbols$MethodSymbolApi of class scala/reflect/api/Symbols
  public #32= #31 of #28;                 // SymbolApi=class scala/reflect/api/Symbols$SymbolApi of class scala/reflect/api/Symbols
  public abstract #37= #34 of #36;        // TypeApi=class scala/reflect/api/Types$TypeApi of class scala/reflect/api/Types
SourceFile: "MacrosCompat.scala"
RuntimeVisibleAnnotations:
  0: #6(#7=s#8)
    scala.reflect.ScalaSignature(
      bytes="\u0006\u0005q4qa\u0002\u0005\u0011\u0002\u0007\u0005Q\u0002C\u0003\u0015\u0001\u0011\u0005Q#\u0002\u0003\u001a\u0001\u0001Q\u0002\"B\u0012\u0001\t\u0003!\u0003\"B\u001f\u0001\t\u0003q\u0004\"\u0002.\u0001\t\u0003Y\u0006\"\u00026\u0001\t\u0003Y\'\u0001D\'bGJ|7oQ8na\u0006$(BA\u0005\u000b\u0003!Ig\u000e^3s]\u0006d\'\"A\u0006\u0002\u0011\u0005\u0014xm\u001c8bkR\u001c\u0001a\u0005\u0002\u0001\u001dA\u0011qBE\u0007\u0002!)\t\u0011#A\u0003tG\u0006d\u0017-\u0003\u0002\u0014!\t1\u0011I\\=SK\u001a\fa\u0001J5oSR$C#\u0001\f\u0011\u0005=9\u0012B\u0001\r\u0011\u0005\u0011)f.\u001b;\u0003\u000f\r{g\u000e^3yiB\u00111DI\u0007\u00029)\u0011QDH\u0001\tE2\f7m\u001b2pq*\u0011q\u0004I\u0001\u0007[\u0006\u001c\'o\\:\u000b\u0005\u0005\u0002\u0012a\u0002:fM2,7\r^\u0005\u00033q\tqbZ3u\t\u0016\u001cG.\u0019:bi&|gn\u001d\u000b\u0003K)\"\"A\n\u001c\u0011\u0005\u001d\u0002dB\u0001\u0015/\u001d\tI#\u0006\u0004\u0001\t\u000b-\u001a\u0001\u0019\u0001\u0017\u0002\u0003\r\u0004\"!\f\u0002\u000e\u0003\u0001I!a\f\u0012\u0002\u0011Ut\u0017N^3sg\u0016L!!\r\u001a\u0003\u00175+WNY3s\'\u000e|\u0007/Z\u0005\u0003gQ\u0012aaU2pa\u0016\u001c(BA\u001b!\u0003\r\t\u0007/\u001b\u0005\u0006o\r\u0001\r\u0001O\u0001\u0004iB,\u0007CA\u0014:\u0013\tQ4H\u0001\u0003UsB,\u0017B\u0001\u001f5\u0005\u0015!\u0016\u0010]3t\u0003E9W\r\u001e)be\u0006lW\r^3s\u0019&\u001cHo\u001d\u000b\u0003\u007fA#\"\u0001Q+\u0011\u0007\u0005KEJ\u0004\u0002C\u000f:\u00111IR\u0007\u0002\t*\u0011Q\tD\u0001\u0007yI|w\u000e\u001e \n\u0003EI!\u0001\u0013\t\u0002\u000fA\f7m[1hK&\u0011!j\u0013\u0002\u0005\u0019&\u001cHO\u0003\u0002I!A\u0019\u0011)S\'\u0011\u00059\u000bfBA(/\u001d\tI\u0003\u000bC\u0003,\t\u0001\u0007A&\u0003\u0002S\'\n11+_7c_2L!\u0001\u0016\u001b\u0003\u000fMKXNY8mg\")a\u000b\u0002a\u0001/\u00061Q.\u001a;i_\u0012\u0004\"A\u0014-\n\u0005e\u001b&\u0001D\'fi\"|GmU=nE>d\u0017AD4fi\u0012+7\r\\1sCRLwN\u001c\u000b\u00039\u0002$2!X1d!\tq\u0016K\u0004\u0002`]9\u0011\u0011\u0006\u0019\u0005\u0006W\u0015\u0001\r\u0001\f\u0005\u0006o\u0015\u0001\rA\u0019\t\u0003=fBQ\u0001Z\u0003A\u0002\u0015\fAA\\1nKB\u0011aLZ\u0005\u0003O\"\u0014AAT1nK&\u0011\u0011\u000e\u000e\u0002\u0006\u001d\u0006lWm]\u0001\u000fGJ,\u0017\r^3UKJlg*Y7f)\ta\u0007\u000f\u0006\u0002ngB\u0011a.\u001d\b\u0003_:r!!\u000b9\t\u000b-2\u0001\u0019\u0001\u0017\n\u0005ID\'\u0001\u0003+fe6t\u0015-\\3\t\u000b\u00114\u0001\u0019\u0001;\u0011\u0005ULhB\u0001<x!\t\u0019\u0005#\u0003\u0002y!\u00051\u0001K]3eK\u001aL!A_>\u0003\rM#(/\u001b8h\u0015\tA\b\u0003"
    )
  ScalaInlineInfo: length = 0x31 (unknown attribute)
   01 00 00 09 00 67 00 68 01 00 52 00 53 00 00 50
   00 51 01 00 47 00 48 00 00 44 00 45 01 00 2B 00
   2C 00 00 26 00 27 01 00 3A 00 3B 00 00 37 00 38
   01
  ScalaSig: length = 0x3 (unknown attribute)
   05 02 00
