Classfile /Users/mw/Projects/slang-braindump/.jar/jar11/assemble/slang-braindump/assemble/content/argonaut/internal/Macros.class
  Last modified May 29, 2022; size 3722 bytes
  SHA-256 checksum f70b6249fe295f378f152e8548ee381e5b0b033f6b85ff12979a5427696fc474
  Compiled from "Macros.scala"
public final class argonaut.internal.Macros
  minor version: 0
  major version: 52
  flags: (0x0031) ACC_PUBLIC, ACC_FINAL, ACC_SUPER
  this_class: #2                          // argonaut/internal/Macros
  super_class: #4                         // java/lang/Object
  interfaces: 0, fields: 0, methods: 7, attributes: 4
Constant pool:
   #1 = Utf8               argonaut/internal/Macros
   #2 = Class              #1             // argonaut/internal/Macros
   #3 = Utf8               java/lang/Object
   #4 = Class              #3             // java/lang/Object
   #5 = Utf8               Macros.scala
   #6 = Utf8               Lscala/reflect/ScalaSignature;
   #7 = Utf8               bytes
   #8 = Utf8               \u0006\u0005\u0005<QAB\u0004\t\u000211QAD\u0004\t\u0002=AQ!G\u0001\u0005\u0002iAQaG\u0001\u0005\u0002qAQaQ\u0001\u0005\u0002\u0011CQAU\u0001\u0005\u0002M\u000ba!T1de>\u001c(B\u0001\u0005\n\u0003!Ig\u000e^3s]\u0006d\'\"\u0001\u0006\u0002\u0011\u0005\u0014xm\u001c8bkR\u001c\u0001\u0001\u0005\u0002\u000e\u00035\tqA\u0001\u0004NC\u000e\u0014xn]\n\u0004\u0003A1\u0002CA\t\u0015\u001b\u0005\u0011\"\"A\n\u0002\u000bM\u001c\u0017\r\\1\n\u0005U\u0011\"AB!osJ+g\r\u0005\u0002\u000e/%\u0011\u0001d\u0002\u0002\r\u001b\u0006\u001c\'o\\:D_6\u0004\u0018\r^\u0001\u0007y%t\u0017\u000e\u001e \u0015\u00031\tA#\\1uKJL\u0017\r\\5{K\u000e{G-Z2J[BdWCA\u000f6)\tq\"\u0005\u0006\u0002 }A\u0019\u0001\u0005\u000b\u0019\u000f\u0005\u0005\u0012C\u0002\u0001\u0005\u0006G\r\u0001\r\u0001J\u0001\u0002GB\u0011QEJ\u0007\u0002\u0003%\u0011qe\u0006\u0002\b\u0007>tG/\u001a=u\u0013\tI#F\u0001\u0003FqB\u0014\u0018BA\u0016-\u0005\u001d\tE.[1tKNT!!\f\u0018\u0002\r5\f7M]8t\u0015\ty##A\u0004sK\u001adWm\u0019;\u0011\u0007E\u0012D\'D\u0001\n\u0013\t\u0019\u0014BA\u0005D_\u0012,7MS:p]B\u0011\u0011%\u000e\u0003\u0006m\r\u0011\ra\u000e\u0002\u0002)F\u0011\u0001h\u000f\t\u0003#eJ!A\u000f\n\u0003\u000f9{G\u000f[5oOB\u0011\u0011\u0003P\u0005\u0003{I\u00111!\u00118z\u0011\u001dy4!!AA\u0004\u0001\u000b!\"\u001a<jI\u0016t7-\u001a\u00132!\r\u0001\u0013\tN\u0005\u0003\u0005*\u00121bV3bWRK\b/\u001a+bO\u0006)R.\u0019;fe&\fG.\u001b>f\u000b:\u001cw\u000eZ3J[BdWCA#O)\t1\u0015\n\u0006\u0002H\u001fB\u0019\u0001\n\u000b&\u000f\u0005\u0005J\u0005\"B\u0012\u0005\u0001\u0004!\u0003cA\u0019L\u001b&\u0011A*\u0003\u0002\u000b\u000b:\u001cw\u000eZ3Kg>t\u0007CA\u0011O\t\u00151DA1\u00018\u0011\u001d\u0001F!!AA\u0004E\u000b!\"\u001a<jI\u0016t7-\u001a\u00133!\rA\u0015)T\u0001\u0016[\u0006$XM]5bY&TX\rR3d_\u0012,\u0017*\u001c9m+\t!V\f\u0006\u0002V1R\u0011aK\u0018\t\u0004/\"JfBA\u0011Y\u0011\u0015\u0019S\u00011\u0001%!\r\t$\fX\u0005\u00037&\u0011!\u0002R3d_\u0012,\'j]8o!\t\tS\fB\u00037\u000b\t\u0007q\u0007C\u0004`\u000b\u0005\u0005\t9\u00011\u0002\u0015\u00154\u0018\u000eZ3oG\u0016$3\u0007E\u0002X\u0003r\u0003
   #9 = Utf8               scala/reflect/api/Exprs$Expr
  #10 = Class              #9             // scala/reflect/api/Exprs$Expr
  #11 = Utf8               scala/reflect/api/Exprs
  #12 = Class              #11            // scala/reflect/api/Exprs
  #13 = Utf8               Expr
  #14 = Utf8               scala/reflect/api/Names$NameApi
  #15 = Class              #14            // scala/reflect/api/Names$NameApi
  #16 = Utf8               scala/reflect/api/Names
  #17 = Class              #16            // scala/reflect/api/Names
  #18 = Utf8               NameApi
  #19 = Utf8               scala/reflect/api/Names$TermNameApi
  #20 = Class              #19            // scala/reflect/api/Names$TermNameApi
  #21 = Utf8               TermNameApi
  #22 = Utf8               scala/reflect/api/Scopes$MemberScopeApi
  #23 = Class              #22            // scala/reflect/api/Scopes$MemberScopeApi
  #24 = Utf8               scala/reflect/api/Scopes
  #25 = Class              #24            // scala/reflect/api/Scopes
  #26 = Utf8               MemberScopeApi
  #27 = Utf8               scala/reflect/api/Symbols$MethodSymbolApi
  #28 = Class              #27            // scala/reflect/api/Symbols$MethodSymbolApi
  #29 = Utf8               scala/reflect/api/Symbols
  #30 = Class              #29            // scala/reflect/api/Symbols
  #31 = Utf8               MethodSymbolApi
  #32 = Utf8               scala/reflect/api/Symbols$SymbolApi
  #33 = Class              #32            // scala/reflect/api/Symbols$SymbolApi
  #34 = Utf8               SymbolApi
  #35 = Utf8               scala/reflect/api/TypeTags$WeakTypeTag
  #36 = Class              #35            // scala/reflect/api/TypeTags$WeakTypeTag
  #37 = Utf8               scala/reflect/api/TypeTags
  #38 = Class              #37            // scala/reflect/api/TypeTags
  #39 = Utf8               WeakTypeTag
  #40 = Utf8               scala/reflect/api/Types$TypeApi
  #41 = Class              #40            // scala/reflect/api/Types$TypeApi
  #42 = Utf8               scala/reflect/api/Types
  #43 = Class              #42            // scala/reflect/api/Types
  #44 = Utf8               TypeApi
  #45 = Utf8               materializeDecodeImpl
  #46 = Utf8               (Lscala/reflect/macros/blackbox/Context;Lscala/reflect/api/TypeTags$WeakTypeTag;)Lscala/reflect/api/Exprs$Expr;
  #47 = Utf8               <T:Ljava/lang/Object;>(Lscala/reflect/macros/blackbox/Context;Lscala/reflect/api/TypeTags$WeakTypeTag<TT;>;)Lscala/reflect/api/Exprs$Expr<Largonaut/DecodeJson<TT;>;>;
  #48 = Utf8               c
  #49 = Utf8               evidence$3
  #50 = Utf8               argonaut/internal/Macros$
  #51 = Class              #50            // argonaut/internal/Macros$
  #52 = Utf8               MODULE$
  #53 = Utf8               Largonaut/internal/Macros$;
  #54 = NameAndType        #52:#53        // MODULE$:Largonaut/internal/Macros$;
  #55 = Fieldref           #51.#54        // argonaut/internal/Macros$.MODULE$:Largonaut/internal/Macros$;
  #56 = NameAndType        #45:#46        // materializeDecodeImpl:(Lscala/reflect/macros/blackbox/Context;Lscala/reflect/api/TypeTags$WeakTypeTag;)Lscala/reflect/api/Exprs$Expr;
  #57 = Methodref          #51.#56        // argonaut/internal/Macros$.materializeDecodeImpl:(Lscala/reflect/macros/blackbox/Context;Lscala/reflect/api/TypeTags$WeakTypeTag;)Lscala/reflect/api/Exprs$Expr;
  #58 = Utf8               materializeEncodeImpl
  #59 = Utf8               <T:Ljava/lang/Object;>(Lscala/reflect/macros/blackbox/Context;Lscala/reflect/api/TypeTags$WeakTypeTag<TT;>;)Lscala/reflect/api/Exprs$Expr<Largonaut/EncodeJson<TT;>;>;
  #60 = Utf8               evidence$2
  #61 = NameAndType        #58:#46        // materializeEncodeImpl:(Lscala/reflect/macros/blackbox/Context;Lscala/reflect/api/TypeTags$WeakTypeTag;)Lscala/reflect/api/Exprs$Expr;
  #62 = Methodref          #51.#61        // argonaut/internal/Macros$.materializeEncodeImpl:(Lscala/reflect/macros/blackbox/Context;Lscala/reflect/api/TypeTags$WeakTypeTag;)Lscala/reflect/api/Exprs$Expr;
  #63 = Utf8               materializeCodecImpl
  #64 = Utf8               <T:Ljava/lang/Object;>(Lscala/reflect/macros/blackbox/Context;Lscala/reflect/api/TypeTags$WeakTypeTag<TT;>;)Lscala/reflect/api/Exprs$Expr<Largonaut/CodecJson<TT;>;>;
  #65 = Utf8               evidence$1
  #66 = NameAndType        #63:#46        // materializeCodecImpl:(Lscala/reflect/macros/blackbox/Context;Lscala/reflect/api/TypeTags$WeakTypeTag;)Lscala/reflect/api/Exprs$Expr;
  #67 = Methodref          #51.#66        // argonaut/internal/Macros$.materializeCodecImpl:(Lscala/reflect/macros/blackbox/Context;Lscala/reflect/api/TypeTags$WeakTypeTag;)Lscala/reflect/api/Exprs$Expr;
  #68 = Utf8               createTermName
  #69 = Utf8               (Lscala/reflect/macros/blackbox/Context;Ljava/lang/String;)Lscala/reflect/api/Names$TermNameApi;
  #70 = Utf8               name
  #71 = NameAndType        #68:#69        // createTermName:(Lscala/reflect/macros/blackbox/Context;Ljava/lang/String;)Lscala/reflect/api/Names$TermNameApi;
  #72 = Methodref          #51.#71        // argonaut/internal/Macros$.createTermName:(Lscala/reflect/macros/blackbox/Context;Ljava/lang/String;)Lscala/reflect/api/Names$TermNameApi;
  #73 = Utf8               getDeclaration
  #74 = Utf8               (Lscala/reflect/macros/blackbox/Context;Lscala/reflect/api/Types$TypeApi;Lscala/reflect/api/Names$NameApi;)Lscala/reflect/api/Symbols$SymbolApi;
  #75 = Utf8               tpe
  #76 = NameAndType        #73:#74        // getDeclaration:(Lscala/reflect/macros/blackbox/Context;Lscala/reflect/api/Types$TypeApi;Lscala/reflect/api/Names$NameApi;)Lscala/reflect/api/Symbols$SymbolApi;
  #77 = Methodref          #51.#76        // argonaut/internal/Macros$.getDeclaration:(Lscala/reflect/macros/blackbox/Context;Lscala/reflect/api/Types$TypeApi;Lscala/reflect/api/Names$NameApi;)Lscala/reflect/api/Symbols$SymbolApi;
  #78 = Utf8               getParameterLists
  #79 = Utf8               (Lscala/reflect/macros/blackbox/Context;Lscala/reflect/api/Symbols$MethodSymbolApi;)Lscala/collection/immutable/List;
  #80 = Utf8               (Lscala/reflect/macros/blackbox/Context;Lscala/reflect/api/Symbols$MethodSymbolApi;)Lscala/collection/immutable/List<Lscala/collection/immutable/List<Lscala/reflect/api/Symbols$SymbolApi;>;>;
  #81 = Utf8               method
  #82 = NameAndType        #78:#79        // getParameterLists:(Lscala/reflect/macros/blackbox/Context;Lscala/reflect/api/Symbols$MethodSymbolApi;)Lscala/collection/immutable/List;
  #83 = Methodref          #51.#82        // argonaut/internal/Macros$.getParameterLists:(Lscala/reflect/macros/blackbox/Context;Lscala/reflect/api/Symbols$MethodSymbolApi;)Lscala/collection/immutable/List;
  #84 = Utf8               getDeclarations
  #85 = Utf8               (Lscala/reflect/macros/blackbox/Context;Lscala/reflect/api/Types$TypeApi;)Lscala/reflect/api/Scopes$MemberScopeApi;
  #86 = NameAndType        #84:#85        // getDeclarations:(Lscala/reflect/macros/blackbox/Context;Lscala/reflect/api/Types$TypeApi;)Lscala/reflect/api/Scopes$MemberScopeApi;
  #87 = Methodref          #51.#86        // argonaut/internal/Macros$.getDeclarations:(Lscala/reflect/macros/blackbox/Context;Lscala/reflect/api/Types$TypeApi;)Lscala/reflect/api/Scopes$MemberScopeApi;
  #88 = Utf8               Code
  #89 = Utf8               Signature
  #90 = Utf8               MethodParameters
  #91 = Utf8               InnerClasses
  #92 = Utf8               SourceFile
  #93 = Utf8               RuntimeVisibleAnnotations
  #94 = Utf8               ScalaSig
{
  public static <T extends java.lang.Object> scala.reflect.api.Exprs$Expr<argonaut.DecodeJson<T>> materializeDecodeImpl(scala.reflect.macros.blackbox.Context, scala.reflect.api.TypeTags$WeakTypeTag<T>);
    descriptor: (Lscala/reflect/macros/blackbox/Context;Lscala/reflect/api/TypeTags$WeakTypeTag;)Lscala/reflect/api/Exprs$Expr;
    flags: (0x0009) ACC_PUBLIC, ACC_STATIC
    Code:
      stack=3, locals=2, args_size=2
         0: getstatic     #55                 // Field argonaut/internal/Macros$.MODULE$:Largonaut/internal/Macros$;
         3: aload_0
         4: aload_1
         5: invokevirtual #57                 // Method argonaut/internal/Macros$.materializeDecodeImpl:(Lscala/reflect/macros/blackbox/Context;Lscala/reflect/api/TypeTags$WeakTypeTag;)Lscala/reflect/api/Exprs$Expr;
         8: areturn
    Signature: #47                          // <T:Ljava/lang/Object;>(Lscala/reflect/macros/blackbox/Context;Lscala/reflect/api/TypeTags$WeakTypeTag<TT;>;)Lscala/reflect/api/Exprs$Expr<Largonaut/DecodeJson<TT;>;>;
    MethodParameters:
      Name                           Flags
      c                              final
      evidence$3                     final

  public static <T extends java.lang.Object> scala.reflect.api.Exprs$Expr<argonaut.EncodeJson<T>> materializeEncodeImpl(scala.reflect.macros.blackbox.Context, scala.reflect.api.TypeTags$WeakTypeTag<T>);
    descriptor: (Lscala/reflect/macros/blackbox/Context;Lscala/reflect/api/TypeTags$WeakTypeTag;)Lscala/reflect/api/Exprs$Expr;
    flags: (0x0009) ACC_PUBLIC, ACC_STATIC
    Code:
      stack=3, locals=2, args_size=2
         0: getstatic     #55                 // Field argonaut/internal/Macros$.MODULE$:Largonaut/internal/Macros$;
         3: aload_0
         4: aload_1
         5: invokevirtual #62                 // Method argonaut/internal/Macros$.materializeEncodeImpl:(Lscala/reflect/macros/blackbox/Context;Lscala/reflect/api/TypeTags$WeakTypeTag;)Lscala/reflect/api/Exprs$Expr;
         8: areturn
    Signature: #59                          // <T:Ljava/lang/Object;>(Lscala/reflect/macros/blackbox/Context;Lscala/reflect/api/TypeTags$WeakTypeTag<TT;>;)Lscala/reflect/api/Exprs$Expr<Largonaut/EncodeJson<TT;>;>;
    MethodParameters:
      Name                           Flags
      c                              final
      evidence$2                     final

  public static <T extends java.lang.Object> scala.reflect.api.Exprs$Expr<argonaut.CodecJson<T>> materializeCodecImpl(scala.reflect.macros.blackbox.Context, scala.reflect.api.TypeTags$WeakTypeTag<T>);
    descriptor: (Lscala/reflect/macros/blackbox/Context;Lscala/reflect/api/TypeTags$WeakTypeTag;)Lscala/reflect/api/Exprs$Expr;
    flags: (0x0009) ACC_PUBLIC, ACC_STATIC
    Code:
      stack=3, locals=2, args_size=2
         0: getstatic     #55                 // Field argonaut/internal/Macros$.MODULE$:Largonaut/internal/Macros$;
         3: aload_0
         4: aload_1
         5: invokevirtual #67                 // Method argonaut/internal/Macros$.materializeCodecImpl:(Lscala/reflect/macros/blackbox/Context;Lscala/reflect/api/TypeTags$WeakTypeTag;)Lscala/reflect/api/Exprs$Expr;
         8: areturn
    Signature: #64                          // <T:Ljava/lang/Object;>(Lscala/reflect/macros/blackbox/Context;Lscala/reflect/api/TypeTags$WeakTypeTag<TT;>;)Lscala/reflect/api/Exprs$Expr<Largonaut/CodecJson<TT;>;>;
    MethodParameters:
      Name                           Flags
      c                              final
      evidence$1                     final

  public static scala.reflect.api.Names$TermNameApi createTermName(scala.reflect.macros.blackbox.Context, java.lang.String);
    descriptor: (Lscala/reflect/macros/blackbox/Context;Ljava/lang/String;)Lscala/reflect/api/Names$TermNameApi;
    flags: (0x0009) ACC_PUBLIC, ACC_STATIC
    Code:
      stack=3, locals=2, args_size=2
         0: getstatic     #55                 // Field argonaut/internal/Macros$.MODULE$:Largonaut/internal/Macros$;
         3: aload_0
         4: aload_1
         5: invokevirtual #72                 // Method argonaut/internal/Macros$.createTermName:(Lscala/reflect/macros/blackbox/Context;Ljava/lang/String;)Lscala/reflect/api/Names$TermNameApi;
         8: areturn
    MethodParameters:
      Name                           Flags
      c                              final
      name                           final

  public static scala.reflect.api.Symbols$SymbolApi getDeclaration(scala.reflect.macros.blackbox.Context, scala.reflect.api.Types$TypeApi, scala.reflect.api.Names$NameApi);
    descriptor: (Lscala/reflect/macros/blackbox/Context;Lscala/reflect/api/Types$TypeApi;Lscala/reflect/api/Names$NameApi;)Lscala/reflect/api/Symbols$SymbolApi;
    flags: (0x0009) ACC_PUBLIC, ACC_STATIC
    Code:
      stack=4, locals=3, args_size=3
         0: getstatic     #55                 // Field argonaut/internal/Macros$.MODULE$:Largonaut/internal/Macros$;
         3: aload_0
         4: aload_1
         5: aload_2
         6: invokevirtual #77                 // Method argonaut/internal/Macros$.getDeclaration:(Lscala/reflect/macros/blackbox/Context;Lscala/reflect/api/Types$TypeApi;Lscala/reflect/api/Names$NameApi;)Lscala/reflect/api/Symbols$SymbolApi;
         9: areturn
    Signature: #74                          // (Lscala/reflect/macros/blackbox/Context;Lscala/reflect/api/Types$TypeApi;Lscala/reflect/api/Names$NameApi;)Lscala/reflect/api/Symbols$SymbolApi;
    MethodParameters:
      Name                           Flags
      c                              final
      tpe                            final
      name                           final

  public static scala.collection.immutable.List<scala.collection.immutable.List<scala.reflect.api.Symbols$SymbolApi>> getParameterLists(scala.reflect.macros.blackbox.Context, scala.reflect.api.Symbols$MethodSymbolApi);
    descriptor: (Lscala/reflect/macros/blackbox/Context;Lscala/reflect/api/Symbols$MethodSymbolApi;)Lscala/collection/immutable/List;
    flags: (0x0009) ACC_PUBLIC, ACC_STATIC
    Code:
      stack=3, locals=2, args_size=2
         0: getstatic     #55                 // Field argonaut/internal/Macros$.MODULE$:Largonaut/internal/Macros$;
         3: aload_0
         4: aload_1
         5: invokevirtual #83                 // Method argonaut/internal/Macros$.getParameterLists:(Lscala/reflect/macros/blackbox/Context;Lscala/reflect/api/Symbols$MethodSymbolApi;)Lscala/collection/immutable/List;
         8: areturn
    Signature: #80                          // (Lscala/reflect/macros/blackbox/Context;Lscala/reflect/api/Symbols$MethodSymbolApi;)Lscala/collection/immutable/List<Lscala/collection/immutable/List<Lscala/reflect/api/Symbols$SymbolApi;>;>;
    MethodParameters:
      Name                           Flags
      c                              final
      method                         final

  public static scala.reflect.api.Scopes$MemberScopeApi getDeclarations(scala.reflect.macros.blackbox.Context, scala.reflect.api.Types$TypeApi);
    descriptor: (Lscala/reflect/macros/blackbox/Context;Lscala/reflect/api/Types$TypeApi;)Lscala/reflect/api/Scopes$MemberScopeApi;
    flags: (0x0009) ACC_PUBLIC, ACC_STATIC
    Code:
      stack=3, locals=2, args_size=2
         0: getstatic     #55                 // Field argonaut/internal/Macros$.MODULE$:Largonaut/internal/Macros$;
         3: aload_0
         4: aload_1
         5: invokevirtual #87                 // Method argonaut/internal/Macros$.getDeclarations:(Lscala/reflect/macros/blackbox/Context;Lscala/reflect/api/Types$TypeApi;)Lscala/reflect/api/Scopes$MemberScopeApi;
         8: areturn
    Signature: #85                          // (Lscala/reflect/macros/blackbox/Context;Lscala/reflect/api/Types$TypeApi;)Lscala/reflect/api/Scopes$MemberScopeApi;
    MethodParameters:
      Name                           Flags
      c                              final
      tpe                            final
}
InnerClasses:
  public #13= #10 of #12;                 // Expr=class scala/reflect/api/Exprs$Expr of class scala/reflect/api/Exprs
  public abstract #18= #15 of #17;        // NameApi=class scala/reflect/api/Names$NameApi of class scala/reflect/api/Names
  public #21= #20 of #17;                 // TermNameApi=class scala/reflect/api/Names$TermNameApi of class scala/reflect/api/Names
  public #26= #23 of #25;                 // MemberScopeApi=class scala/reflect/api/Scopes$MemberScopeApi of class scala/reflect/api/Scopes
  public #31= #28 of #30;                 // MethodSymbolApi=class scala/reflect/api/Symbols$MethodSymbolApi of class scala/reflect/api/Symbols
  public #34= #33 of #30;                 // SymbolApi=class scala/reflect/api/Symbols$SymbolApi of class scala/reflect/api/Symbols
  public #39= #36 of #38;                 // WeakTypeTag=class scala/reflect/api/TypeTags$WeakTypeTag of class scala/reflect/api/TypeTags
  public abstract #44= #41 of #43;        // TypeApi=class scala/reflect/api/Types$TypeApi of class scala/reflect/api/Types
SourceFile: "Macros.scala"
RuntimeVisibleAnnotations:
  0: #6(#7=s#8)
    scala.reflect.ScalaSignature(
      bytes="\u0006\u0005\u0005<QAB\u0004\t\u000211QAD\u0004\t\u0002=AQ!G\u0001\u0005\u0002iAQaG\u0001\u0005\u0002qAQaQ\u0001\u0005\u0002\u0011CQAU\u0001\u0005\u0002M\u000ba!T1de>\u001c(B\u0001\u0005\n\u0003!Ig\u000e^3s]\u0006d\'\"\u0001\u0006\u0002\u0011\u0005\u0014xm\u001c8bkR\u001c\u0001\u0001\u0005\u0002\u000e\u00035\tqA\u0001\u0004NC\u000e\u0014xn]\n\u0004\u0003A1\u0002CA\t\u0015\u001b\u0005\u0011\"\"A\n\u0002\u000bM\u001c\u0017\r\\1\n\u0005U\u0011\"AB!osJ+g\r\u0005\u0002\u000e/%\u0011\u0001d\u0002\u0002\r\u001b\u0006\u001c\'o\\:D_6\u0004\u0018\r^\u0001\u0007y%t\u0017\u000e\u001e \u0015\u00031\tA#\\1uKJL\u0017\r\\5{K\u000e{G-Z2J[BdWCA\u000f6)\tq\"\u0005\u0006\u0002 }A\u0019\u0001\u0005\u000b\u0019\u000f\u0005\u0005\u0012C\u0002\u0001\u0005\u0006G\r\u0001\r\u0001J\u0001\u0002GB\u0011QEJ\u0007\u0002\u0003%\u0011qe\u0006\u0002\b\u0007>tG/\u001a=u\u0013\tI#F\u0001\u0003FqB\u0014\u0018BA\u0016-\u0005\u001d\tE.[1tKNT!!\f\u0018\u0002\r5\f7M]8t\u0015\ty##A\u0004sK\u001adWm\u0019;\u0011\u0007E\u0012D\'D\u0001\n\u0013\t\u0019\u0014BA\u0005D_\u0012,7MS:p]B\u0011\u0011%\u000e\u0003\u0006m\r\u0011\ra\u000e\u0002\u0002)F\u0011\u0001h\u000f\t\u0003#eJ!A\u000f\n\u0003\u000f9{G\u000f[5oOB\u0011\u0011\u0003P\u0005\u0003{I\u00111!\u00118z\u0011\u001dy4!!AA\u0004\u0001\u000b!\"\u001a<jI\u0016t7-\u001a\u00132!\r\u0001\u0013\tN\u0005\u0003\u0005*\u00121bV3bWRK\b/\u001a+bO\u0006)R.\u0019;fe&\fG.\u001b>f\u000b:\u001cw\u000eZ3J[BdWCA#O)\t1\u0015\n\u0006\u0002H\u001fB\u0019\u0001\n\u000b&\u000f\u0005\u0005J\u0005\"B\u0012\u0005\u0001\u0004!\u0003cA\u0019L\u001b&\u0011A*\u0003\u0002\u000b\u000b:\u001cw\u000eZ3Kg>t\u0007CA\u0011O\t\u00151DA1\u00018\u0011\u001d\u0001F!!AA\u0004E\u000b!\"\u001a<jI\u0016t7-\u001a\u00133!\rA\u0015)T\u0001\u0016[\u0006$XM]5bY&TX\rR3d_\u0012,\u0017*\u001c9m+\t!V\f\u0006\u0002V1R\u0011aK\u0018\t\u0004/\"JfBA\u0011Y\u0011\u0015\u0019S\u00011\u0001%!\r\t$\fX\u0005\u00037&\u0011!\u0002R3d_\u0012,\'j]8o!\t\tS\fB\u00037\u000b\t\u0007q\u0007C\u0004`\u000b\u0005\u0005\t9\u00011\u0002\u0015\u00154\u0018\u000eZ3oG\u0016$3\u0007E\u0002X\u0003r\u0003"
    )
  ScalaSig: length = 0x3 (unknown attribute)
   05 02 00
