Classfile /Users/mw/Projects/slang-braindump/.jar/jar8/assemble/slang-braindump/assemble/content/coursier/params/ResolutionParams.class
  Last modified May 29, 2022; size 30548 bytes
  SHA-256 checksum 72ba9042f843bff7d0b36ef803b0b1b55d7df31da9b5264b5ead44f64eb3d3d3
  Compiled from "ResolutionParams.scala"
public final class coursier.params.ResolutionParams implements scala.Product,java.io.Serializable
  minor version: 0
  major version: 52
  flags: (0x0031) ACC_PUBLIC, ACC_FINAL, ACC_SUPER
  this_class: #2                          // coursier/params/ResolutionParams
  super_class: #4                         // java/lang/Object
  interfaces: 2, fields: 19, methods: 71, attributes: 6
Constant pool:
    #1 = Utf8               coursier/params/ResolutionParams
    #2 = Class              #1            // coursier/params/ResolutionParams
    #3 = Utf8               java/lang/Object
    #4 = Class              #3            // java/lang/Object
    #5 = Utf8               scala/Product
    #6 = Class              #5            // scala/Product
    #7 = Utf8               java/io/Serializable
    #8 = Class              #7            // java/io/Serializable
    #9 = Utf8               ResolutionParams.scala
   #10 = Utf8               Lscala/reflect/ScalaSignature;
   #11 = Utf8               bytes
   #12 = Utf8               \u0006\u0005\rmd\u0001\u0002,X\u0005qC\u0001B\u001d\u0001\u0003\u0006\u0004%\ta\u001d\u0005\to\u0002\u0011\t\u0011)A\u0005i\"A\u0001\u0010\u0001BC\u0002\u0013\u0005\u0011\u0010\u0003\u0005~\u0001\t\u0005\t\u0015!\u0003{\u0011!q\bA!b\u0001\n\u0003y\bBCA\u0012\u0001\t\u0005\t\u0015!\u0003\u0002\u0002!Q\u0011Q\u0005\u0001\u0003\u0006\u0004%\t!a\n\t\u0015\u0005-\u0002A!A!\u0002\u0013\tI\u0003\u0003\u0006\u0002.\u0001\u0011)\u0019!C\u0001\u0003_A!\"a\u000e\u0001\u0005\u0003\u0005\u000b\u0011BA\u0019\u0011)\tI\u0004\u0001BC\u0002\u0013\u0005\u00111\b\u0005\u000b\u0003\u0007\u0002!\u0011!Q\u0001\n\u0005u\u0002BCA#\u0001\t\u0015\r\u0011\"\u0001\u0002H!Q\u00111\n\u0001\u0003\u0002\u0003\u0006I!!\u0013\t\u0013\u00055\u0003A!b\u0001\n\u0003\u0019\b\"CA(\u0001\t\u0005\t\u0015!\u0003u\u0011)\t\t\u0006\u0001BC\u0002\u0013\u0005\u00111\u000b\u0005\u000b\u0003g\u0002!\u0011!Q\u0001\n\u0005U\u0003BCA;\u0001\t\u0015\r\u0011\"\u0001\u0002x!Q\u0011q\u0012\u0001\u0003\u0002\u0003\u0006I!!\u001f\t\u0015\u0005E\u0005A!b\u0001\n\u0003\t\u0019\n\u0003\u0006\u0002\u001a\u0002\u0011\t\u0011)A\u0005\u0003+C!\"a\'\u0001\u0005\u000b\u0007I\u0011AAO\u0011)\ty\u000b\u0001B\u0001B\u0003%\u0011q\u0014\u0005\u000b\u0003c\u0003!Q1A\u0005\u0002\u0005M\u0006BCAc\u0001\t\u0005\t\u0015!\u0003\u00026\"Q\u0011q\u0019\u0001\u0003\u0006\u0004%\t!!3\t\u0015\u0005M\u0007A!A!\u0002\u0013\tY\rC\u0005\u0002V\u0002\u0011)\u0019!C\u0001g\"I\u0011q\u001b\u0001\u0003\u0002\u0003\u0006I\u0001\u001e\u0005\n\u00033\u0004!Q1A\u0005\u0002MD\u0011\"a7\u0001\u0005\u0003\u0005\u000b\u0011\u0002;\t\u0015\u0005u\u0007A!b\u0001\n\u0003\ty\u000e\u0003\u0006\u0002h\u0002\u0011\t\u0011)A\u0005\u0003CDq!!;\u0001\t\u0003\tY\u000fC\u0004\u0002j\u0002!\tAa\u0005\t\u000f\tU\u0001\u0001\"\u0001\u0003\u0018!1!Q\u0005\u0001\u0005\u0002MDqAa\n\u0001\t\u0003\u0011I\u0003C\u0004\u0003,\u0001!\tA!\f\t\u000f\tU\u0002\u0001\"\u0002\u00038!9!Q\u0007\u0001\u0005\u0006\t}\u0002b\u0002B\"\u0001\u0011\u0005!Q\t\u0005\b\u0005\u001b\u0002A\u0011\u0001B(\u0011\u001d\u0011\u0019\u0006\u0001C\u0001\u0005+BqAa\u0017\u0001\t\u0003\u0011i\u0006C\u0004\u0003d\u0001!\tA!\u001a\t\u000f\t-\u0004\u0001\"\u0001\u0003n!9!1\u000e\u0001\u0005\u0002\tM\u0004b\u0002B<\u0001\u0011\u0005!\u0011\u0010\u0005\b\u0005\u007f\u0002A\u0011\u0001BA\u0011\u001d\u00119\t\u0001C\u0001\u0003oB!B!#\u0001\u0011\u000b\u0007I\u0011AA*\u0011\u001d\u0011Y\t\u0001C\u0001\u0005\u001bCqA!%\u0001\t\u0003\u0011\u0019\nC\u0004\u0003\u0018\u0002!\tA!\'\t\u000f\tu\u0005\u0001\"\u0001\u0003 \"9!1\u0015\u0001\u0005\u0002\t\u0015\u0006b\u0002BU\u0001\u0011\u0005!1\u0016\u0005\b\u0005_\u0003A\u0011\u0001BY\u0011\u001d\u0011)\f\u0001C\u0001\u0005oCqAa/\u0001\t\u0003\u0011i\fC\u0004\u0003B\u0002!\tAa1\t\u000f\t\u001d\u0007\u0001\"\u0001\u0003J\"9!Q\u001a\u0001\u0005\u0002\t=\u0007b\u0002Bj\u0001\u0011\u0005!Q\u001b\u0005\b\u00053\u0004A\u0011\u0001Bn\u0011\u001d\u0011y\u000e\u0001C\u0001\u0005CDqA!:\u0001\t\u0003\u00119\u000fC\u0004\u0003l\u0002!\tA!<\t\u000f\tE\b\u0001\"\u0011\u0003t\"911\u0001\u0001\u0005B\r\u0015\u0001bBB\t\u0001\u0011\u000531\u0003\u0005\b\u0007/\u0001A\u0011IB\r\u0011\u001d\u0019Y\u0002\u0001C\u0005\u0007;Aqa!\n\u0001\t\u0003\u001a9\u0003\u0003\u0004\u0004*\u0001!\t%\u001f\u0005\b\u0007W\u0001A\u0011IB\u0017\u0011\u001d\u0019\u0019\u0004\u0001C!\u0007k9qa!\u000fX\u0011\u0003\u0019YD\u0002\u0004W/\"\u00051Q\b\u0005\b\u0003S\fF\u0011AB%\u0011\u001d\u0019Y%\u0015C\u0001\u0005\'Aqaa\u0013R\t\u0003\u0019i\u0005C\u0005\u0004rE\u000b\t\u0011\"\u0003\u0004t\t\u0001\"+Z:pYV$\u0018n\u001c8QCJ\fWn\u001d\u0006\u00031f\u000ba\u0001]1sC6\u001c(\"\u0001.\u0002\u0011\r|WO]:jKJ\u001c\u0001a\u0005\u0003\u0001;\u000e4\u0007C\u00010b\u001b\u0005y&\"\u00011\u0002\u000bM\u001c\u0017\r\\1\n\u0005\t|&AB!osJ+g\r\u0005\u0002_I&\u0011Qm\u0018\u0002\b!J|G-^2u!\t9wN\u0004\u0002i[:\u0011\u0011\u000e\\\u0007\u0002U*\u00111nW\u0001\u0007yI|w\u000e\u001e \n\u0003\u0001L!A\\0\u0002\u000fA\f7m[1hK&\u0011\u0001/\u001d\u0002\r\'\u0016\u0014\u0018.\u00197ju\u0006\u0014G.\u001a\u0006\u0003]~\u000b\u0001d[3fa>\u0003H/[8oC2$U\r]3oI\u0016t7-[3t+\u0005!\bC\u00010v\u0013\t1xLA\u0004C_>dW-\u00198\u00023-,W\r](qi&|g.\u00197EKB,g\u000eZ3oG&,7\u000fI\u0001\u000e[\u0006D\u0018\n^3sCRLwN\\:\u0016\u0003i\u0004\"AX>\n\u0005q|&aA%oi\u0006qQ.\u0019=Ji\u0016\u0014\u0018\r^5p]N\u0004\u0013\u0001\u00044pe\u000e,g+\u001a:tS>tWCAA\u0001!!\t\u0019!a\u0003\u0002\u0012\u0005ua\u0002BA\u0003\u0003\u000f\u0001\"![0\n\u0007\u0005%q,\u0001\u0004Qe\u0016$WMZ\u0005\u0005\u0003\u001b\tyAA\u0002NCBT1!!\u0003`!\u0011\t\u0019\"!\u0007\u000e\u0005\u0005U!bAA\f3\u0006!1m\u001c:f\u0013\u0011\tY\"!\u0006\u0003\r5{G-\u001e7f!\u0011\t\u0019!a\b\n\t\u0005\u0005\u0012q\u0002\u0002\u0007\'R\u0014\u0018N\\4\u0002\u001b\u0019|\'oY3WKJ\u001c\u0018n\u001c8!\u0003A1wN]2fIB\u0013x\u000e]3si&,7/\u0006\u0002\u0002*AA\u00111AA\u0006\u0003;\ti\"A\tg_J\u001cW\r\u001a)s_B,\'\u000f^5fg\u0002\n\u0001\u0002\u001d:pM&dWm]\u000b\u0003\u0003c\u0001b!a\u0001\u00024\u0005u\u0011\u0002BA\u001b\u0003\u001f\u00111aU3u\u0003%\u0001(o\u001c4jY\u0016\u001c\b%A\btG\u0006d\u0017MV3sg&|gn\u00149u+\t\ti\u0004E\u0003_\u0003\u007f\ti\"C\u0002\u0002B}\u0013aa\u00149uS>t\u0017\u0001E:dC2\fg+\u001a:tS>tw\n\u001d;!\u0003Q1wN]2f\'\u000e\fG.\u0019,feNLwN\\(qiV\u0011\u0011\u0011\n\t\u0005=\u0006}B/A\u000bg_J\u001cWmU2bY\u00064VM]:j_:|\u0005\u000f\u001e\u0011\u0002\u0013QL\b/\u001a7fm\u0016d\u0017A\u0003;za\u0016dWM^3mA\u0005)!/\u001e7fgV\u0011\u0011Q\u000b\t\u0006O\u0006]\u00131L\u0005\u0004\u00033\n(aA*fcB9a,!\u0018\u0002b\u00055\u0014bAA0?\n1A+\u001e9mKJ\u0002B!a\u0019\u0002j5\u0011\u0011Q\r\u0006\u0004\u0003O:\u0016\u0001\u0002:vY\u0016LA!a\u001b\u0002f\t!!+\u001e7f!\u0011\t\u0019\'a\u001c\n\t\u0005E\u0014Q\r\u0002\u000f%VdWMU3t_2,H/[8o\u0003\u0019\u0011X\u000f\\3tA\u0005q!/Z2p]\u000eLG.[1uS>tWCAA=!\u00159\u0017qKA>!\u001dq\u0016QLA?\u0003\u0013\u0003B!a \u0002\u00066\u0011\u0011\u0011\u0011\u0006\u0004\u0003\u0007K\u0016\u0001B;uS2LA!a\"\u0002\u0002\nqQj\u001c3vY\u0016l\u0015\r^2iKJ\u001c\b\u0003BA\n\u0003\u0017KA!!$\u0002\u0016\tq!+Z2p]\u000eLG.[1uS>t\u0017a\u0004:fG>t7-\u001b7jCRLwN\u001c\u0011\u0002\u0015A\u0014x\u000e]3si&,7/\u0006\u0002\u0002\u0016B)q-a\u0016\u0002\u0018B9a,!\u0018\u0002\u001e\u0005u\u0011a\u00039s_B,\'\u000f^5fg\u0002\n!\"\u001a=dYV\u001c\u0018n\u001c8t+\t\ty\n\u0005\u0004\u0002\u0004\u0005M\u0012\u0011\u0015\t\b=\u0006u\u00131UAU!\u0011\t\u0019\"!*\n\t\u0005\u001d\u0016Q\u0003\u0002\r\u001fJ<\u0017M\\5{CRLwN\u001c\t\u0005\u0003\'\tY+\u0003\u0003\u0002.\u0006U!AC\'pIVdWMT1nK\u0006YQ\r_2mkNLwN\\:!\u0003%y7/\u00138g_>\u0003H/\u0006\u0002\u00026B)a,a\u0010\u00028B!\u0011\u0011XA`\u001d\u0011\t\u0019\"a/\n\t\u0005u\u0016QC\u0001\u000b\u0003\u000e$\u0018N^1uS>t\u0017\u0002BAa\u0003\u0007\u0014!aT:\u000b\t\u0005u\u0016QC\u0001\u000b_NLeNZ8PaR\u0004\u0013!\u00046eWZ+\'o]5p]>\u0003H/\u0006\u0002\u0002LB)a,a\u0010\u0002NB!\u00111CAh\u0013\u0011\t\t.!\u0006\u0003\u000fY+\'o]5p]\u0006q!\u000eZ6WKJ\u001c\u0018n\u001c8PaR\u0004\u0013aD;tKNK8\u000f^3n\u001fNLeNZ8\u0002!U\u001cXmU=ti\u0016lwj]%oM>\u0004\u0013aE;tKNK8\u000f^3n\u0015\u0012\\g+\u001a:tS>t\u0017\u0001F;tKNK8\u000f^3n\u0015\u0012\\g+\u001a:tS>t\u0007%\u0001\u000beK\u001a\fW\u000f\u001c;D_:4\u0017nZ;sCRLwN\\\u000b\u0003\u0003C\u0004B!a\u0005\u0002d&!\u0011Q]A\u000b\u00055\u0019uN\u001c4jOV\u0014\u0018\r^5p]\u0006)B-\u001a4bk2$8i\u001c8gS\u001e,(/\u0019;j_:\u0004\u0013A\u0002\u001fj]&$h\b\u0006\u0013\u0002n\u0006E\u00181_A{\u0003o\fI0a?\u0002~\u0006}(\u0011\u0001B\u0002\u0005\u000b\u00119A!\u0003\u0003\f\t5!q\u0002B\t!\r\ty\u000fA\u0007\u0002/\")!o\ta\u0001i\")\u0001p\ta\u0001u\"1ap\ta\u0001\u0003\u0003Aq!!\n$\u0001\u0004\tI\u0003C\u0004\u0002.\r\u0002\r!!\r\t\u000f\u0005e2\u00051\u0001\u0002>!9\u0011QI\u0012A\u0002\u0005%\u0003BBA\'G\u0001\u0007A\u000fC\u0004\u0002R\r\u0002\r!!\u0016\t\u000f\u0005U4\u00051\u0001\u0002z!9\u0011\u0011S\u0012A\u0002\u0005U\u0005bBANG\u0001\u0007\u0011q\u0014\u0005\b\u0003c\u001b\u0003\u0019AA[\u0011\u001d\t9m\ta\u0001\u0003\u0017Da!!6$\u0001\u0004!\bBBAmG\u0001\u0007A\u000fC\u0004\u0002^\u000e\u0002\r!!9\u0015\u0005\u00055\u0018aD1eI\u001a{\'oY3WKJ\u001c\u0018n\u001c8\u0015\t\u00055(\u0011\u0004\u0005\b\u00057)\u0003\u0019\u0001B\u000f\u0003\t1g\u000fE\u0003_\u0005?\u0011\u0019#C\u0002\u0003\"}\u0013!\u0002\u0010:fa\u0016\fG/\u001a3?!\u001dq\u0016QLA\t\u0003;\t1\u0003Z8G_J\u001cWmU2bY\u00064VM]:j_:\fAc]3mK\u000e$X\rZ*dC2\fg+\u001a:tS>tWCAA\u000f\u0003)\tG\r\u001a)s_\u001aLG.\u001a\u000b\u0005\u0003[\u0014y\u0003C\u0004\u00032!\u0002\rAa\r\u0002\u000fA\u0014xNZ5mKB)aLa\b\u0002\u001e\u00059\u0011\r\u001a3Sk2,GCBAw\u0005s\u0011Y\u0004C\u0004\u0002h%\u0002\r!!\u0019\t\u000f\tu\u0012\u00061\u0001\u0002n\u0005Q!/Z:pYV$\u0018n\u001c8\u0015\t\u00055(\u0011\t\u0005\b\u0003OR\u0003\u0019AA1\u00035\tG\r\u001a)s_B,\'\u000f^5fgR!\u0011Q\u001eB$\u0011\u001d\u0011Ie\u000ba\u0001\u0005\u0017\nQ\u0001\u001d:paN\u0004RA\u0018B\u0010\u0003/\u000b1#\u00193e\r>\u00148-\u001a3Qe>\u0004XM\u001d;jKN$B!!<\u0003R!9!\u0011\n\u0017A\u0002\t-\u0013\u0001E<ji\"\u001c6-\u00197b-\u0016\u00148/[8o)\u0011\tiOa\u0016\t\u000f\teS\u00061\u0001\u0002\u001e\u0005a1oY1mCZ+\'o]5p]\u0006)r/\u001b;i\r>\u00148-Z*dC2\fg+\u001a:tS>tG\u0003BAw\u0005?BaA!\u0019/\u0001\u0004!\u0018!\u00054pe\u000e,7kY1mCZ+\'o]5p]\u0006Qq/\u001b;i\u001fNLeNZ8\u0015\t\u00055(q\r\u0005\b\u0005Sz\u0003\u0019AA\\\u0003\u0019y7/\u00138g_\u0006qq/\u001b;i\u0015\u0012\\g+\u001a:tS>tG\u0003BAw\u0005_BqA!\u001d1\u0001\u0004\ti\"A\u0004wKJ\u001c\u0018n\u001c8\u0015\t\u00055(Q\u000f\u0005\b\u0005c\n\u0004\u0019AAg\u0003E\tG\r\u001a*fG>t7-\u001b7jCRLwN\u001c\u000b\u0005\u0003[\u0014Y\bC\u0004\u0002vI\u0002\rA! \u0011\u000by\u0013y\"a\u001f\u0002\u001b\u0005$G-\u0012=dYV\u001c\u0018n\u001c8t)\u0011\tiOa!\t\u000f\u0005m5\u00071\u0001\u0003\u0006B)aLa\b\u0002\"\u0006!\u0012m\u0019;vC2\u0014VmY8oG&d\u0017.\u0019;j_:\f1\"Y2uk\u0006d\'+\u001e7fg\u0006ar/\u001b;i\u0017\u0016,\u0007o\u00149uS>t\u0017\r\u001c#fa\u0016tG-\u001a8dS\u0016\u001cH\u0003BAw\u0005\u001fCQA\u001d\u001cA\u0002Q\f\u0011c^5uQ6\u000b\u00070\u0013;fe\u0006$\u0018n\u001c8t)\u0011\tiO!&\t\u000ba<\u0004\u0019\u0001>\u0002!]LG\u000f\u001b$pe\u000e,g+\u001a:tS>tG\u0003BAw\u00057CaA \u001dA\u0002\u0005\u0005\u0011\u0001F<ji\"4uN]2fIB\u0013x\u000e]3si&,7\u000f\u0006\u0003\u0002n\n\u0005\u0006bBA\u0013s\u0001\u0007\u0011\u0011F\u0001\ro&$\b\u000e\u0015:pM&dWm\u001d\u000b\u0005\u0003[\u00149\u000bC\u0004\u0002.i\u0002\r!!\r\u0002\']LG\u000f[*dC2\fg+\u001a:tS>tw\n\u001d;\u0015\t\u00055(Q\u0016\u0005\b\u0003sY\u0004\u0019AA\u001f\u0003a9\u0018\u000e\u001e5G_J\u001cWmU2bY\u00064VM]:j_:|\u0005\u000f\u001e\u000b\u0005\u0003[\u0014\u0019\fC\u0004\u0002Fq\u0002\r!!\u0013\u0002\u001b]LG\u000f\u001b+za\u0016dWM^3m)\u0011\tiO!/\t\r\u00055S\b1\u0001u\u0003%9\u0018\u000e\u001e5Sk2,7\u000f\u0006\u0003\u0002n\n}\u0006bBA)}\u0001\u0007\u0011QK\u0001\u0013o&$\bNU3d_:\u001c\u0017\u000e\\5bi&|g\u000e\u0006\u0003\u0002n\n\u0015\u0007bBA;\u007f\u0001\u0007\u0011\u0011P\u0001\u000fo&$\b\u000e\u0015:pa\u0016\u0014H/[3t)\u0011\tiOa3\t\u000f\u0005E\u0005\t1\u0001\u0002\u0016\u0006qq/\u001b;i\u000bb\u001cG.^:j_:\u001cH\u0003BAw\u0005#Dq!a\'B\u0001\u0004\ty*A\u0007xSRDwj]%oM>|\u0005\u000f\u001e\u000b\u0005\u0003[\u00149\u000eC\u0004\u00022\n\u0003\r!!.\u0002#]LG\u000f\u001b&eWZ+\'o]5p]>\u0003H\u000f\u0006\u0003\u0002n\nu\u0007bBAd\u0007\u0002\u0007\u00111Z\u0001\u0014o&$\b.V:f\'f\u001cH/Z7Pg&sgm\u001c\u000b\u0005\u0003[\u0014\u0019\u000f\u0003\u0004\u0002V\u0012\u0003\r\u0001^\u0001\u0018o&$\b.V:f\'f\u001cH/Z7KI.4VM]:j_:$B!!<\u0003j\"1\u0011\u0011\\#A\u0002Q\f\u0001d^5uQ\u0012+g-Y;mi\u000e{gNZ5hkJ\fG/[8o)\u0011\tiOa<\t\u000f\u0005ug\t1\u0001\u0002b\u0006AAo\\*ue&tw\r\u0006\u0002\u0003vB!!q_B\u0001\u001b\t\u0011IP\u0003\u0003\u0003|\nu\u0018\u0001\u00027b]\u001eT!Aa@\u0002\t)\fg/Y\u0005\u0005\u0003C\u0011I0\u0001\u0005dC:,\u0015/^1m)\r!8q\u0001\u0005\b\u0007\u0013A\u0005\u0019AB\u0006\u0003\ry\'M\u001b\t\u0004=\u000e5\u0011bAB\b?\n\u0019\u0011I\\=\u0002\r\u0015\fX/\u00197t)\r!8Q\u0003\u0005\b\u0007\u0013I\u0005\u0019AB\u0006\u0003!A\u0017m\u001d5D_\u0012,G#\u0001>\u0002\u000bQ,\b\u000f\\3\u0016\u0005\r}\u0001\u0003\t0\u0004\"QT\u0018\u0011AA\u0015\u0003c\ti$!\u0013u\u0003+\nI(!&\u0002 \u0006U\u00161\u001a;u\u0003CL1aa\t`\u0005\u001d!V\u000f\u001d7fc]\nQ\u0002\u001d:pIV\u001cG\u000f\u0015:fM&DXC\u0001B{\u00031\u0001(o\u001c3vGR\f%/\u001b;z\u00039\u0001(o\u001c3vGR,E.Z7f]R$Baa\u0003\u00040!11\u0011\u0007(A\u0002i\f\u0011A\\\u0001\u0013aJ|G-^2u\u000b2,W.\u001a8u\u001d\u0006lW\r\u0006\u0003\u0003v\u000e]\u0002BBB\u0019\u001f\u0002\u0007!0\u0001\tSKN|G.\u001e;j_:\u0004\u0016M]1ngB\u0019\u0011q^)\u0014\tEk6q\b\t\u0005\u0007\u0003\u001a9%\u0004\u0002\u0004D)!1Q\tB\u007f\u0003\tIw.C\u0002q\u0007\u0007\"\"aa\u000f\u0002\u000b\u0005\u0004\b\u000f\\=\u0015I\u000558qJB)\u0007\'\u001a)fa\u0016\u0004Z\rm3QLB0\u0007C\u001a\u0019g!\u001a\u0004h\r%41NB7\u0007_BQA\u001d+A\u0002QDQ\u0001\u001f+A\u0002iDaA +A\u0002\u0005\u0005\u0001bBA\u0013)\u0002\u0007\u0011\u0011\u0006\u0005\b\u0003[!\u0006\u0019AA\u0019\u0011\u001d\tI\u0004\u0016a\u0001\u0003{Aq!!\u0012U\u0001\u0004\tI\u0005\u0003\u0004\u0002NQ\u0003\r\u0001\u001e\u0005\b\u0003#\"\u0006\u0019AA+\u0011\u001d\t)\b\u0016a\u0001\u0003sBq!!%U\u0001\u0004\t)\nC\u0004\u0002\u001cR\u0003\r!a(\t\u000f\u0005EF\u000b1\u0001\u00026\"9\u0011q\u0019+A\u0002\u0005-\u0007BBAk)\u0002\u0007A\u000f\u0003\u0004\u0002ZR\u0003\r\u0001\u001e\u0005\b\u0003;$\u0006\u0019AAq\u000319(/\u001b;f%\u0016\u0004H.Y2f)\t\u0019)\b\u0005\u0003\u0003x\u000e]\u0014\u0002BB=\u0005s\u0014aa\u00142kK\u000e$\b
   #13 = Utf8               coursier/core/Activation$Os
   #14 = Class              #13           // coursier/core/Activation$Os
   #15 = Utf8               coursier/core/Activation
   #16 = Class              #15           // coursier/core/Activation
   #17 = Utf8               Os
   #18 = Utf8               coursier/core/Reconciliation$Default$
   #19 = Class              #18           // coursier/core/Reconciliation$Default$
   #20 = Utf8               coursier/core/Reconciliation
   #21 = Class              #20           // coursier/core/Reconciliation
   #22 = Utf8
   #23 = Utf8               coursier/core/Reconciliation$SemVer$
   #24 = Class              #23           // coursier/core/Reconciliation$SemVer$
   #25 = Utf8               coursier/core/Reconciliation$Strict$
   #26 = Class              #25           // coursier/core/Reconciliation$Strict$
   #27 = Utf8               coursier/params/ResolutionParams$$anonfun$1
   #28 = Class              #27           // coursier/params/ResolutionParams$$anonfun$1
   #29 = Utf8               coursier/params/rule/RuleResolution$TryResolve$
   #30 = Class              #29           // coursier/params/rule/RuleResolution$TryResolve$
   #31 = Utf8               coursier/params/rule/RuleResolution
   #32 = Class              #31           // coursier/params/rule/RuleResolution
   #33 = Utf8               java/lang/invoke/MethodHandles$Lookup
   #34 = Class              #33           // java/lang/invoke/MethodHandles$Lookup
   #35 = Utf8               java/lang/invoke/MethodHandles
   #36 = Class              #35           // java/lang/invoke/MethodHandles
   #37 = Utf8               Lookup
   #38 = Utf8               scala/Predef$ArrowAssoc$
   #39 = Class              #38           // scala/Predef$ArrowAssoc$
   #40 = Utf8               scala/Predef
   #41 = Class              #40           // scala/Predef
   #42 = Utf8               actualRules
   #43 = Utf8               Lscala/collection/immutable/Seq;
   #44 = Utf8               Lscala/collection/immutable/Seq<Lscala/Tuple2<Lcoursier/params/rule/Rule;Lcoursier/params/rule/RuleResolution;>;>;
   #45 = Utf8               keepOptionalDependencies
   #46 = Utf8               Z
   #47 = Utf8               maxIterations
   #48 = Utf8               I
   #49 = Utf8               forceVersion
   #50 = Utf8               Lscala/collection/immutable/Map;
   #51 = Utf8               Lscala/collection/immutable/Map<Lcoursier/core/Module;Ljava/lang/String;>;
   #52 = Utf8               forcedProperties
   #53 = Utf8               Lscala/collection/immutable/Map<Ljava/lang/String;Ljava/lang/String;>;
   #54 = Utf8               profiles
   #55 = Utf8               Lscala/collection/immutable/Set;
   #56 = Utf8               Lscala/collection/immutable/Set<Ljava/lang/String;>;
   #57 = Utf8               scalaVersionOpt
   #58 = Utf8               Lscala/Option;
   #59 = Utf8               Lscala/Option<Ljava/lang/String;>;
   #60 = Utf8               forceScalaVersionOpt
   #61 = Utf8               Lscala/Option<Ljava/lang/Object;>;
   #62 = Utf8               typelevel
   #63 = Utf8               rules
   #64 = Utf8               reconciliation
   #65 = Utf8               Lscala/collection/immutable/Seq<Lscala/Tuple2<Lcoursier/util/ModuleMatchers;Lcoursier/core/Reconciliation;>;>;
   #66 = Utf8               properties
   #67 = Utf8               Lscala/collection/immutable/Seq<Lscala/Tuple2<Ljava/lang/String;Ljava/lang/String;>;>;
   #68 = Utf8               exclusions
   #69 = Utf8               Lscala/collection/immutable/Set<Lscala/Tuple2<Lcoursier/core/Organization;Lcoursier/core/ModuleName;>;>;
   #70 = Utf8               osInfoOpt
   #71 = Utf8               Lscala/Option<Lcoursier/core/Activation$Os;>;
   #72 = Utf8               jdkVersionOpt
   #73 = Utf8               Lscala/Option<Lcoursier/core/Version;>;
   #74 = Utf8               useSystemOsInfo
   #75 = Utf8               useSystemJdkVersion
   #76 = Utf8               defaultConfiguration
   #77 = Utf8               Ljava/lang/String;
   #78 = Utf8               bitmap$0
   #79 = Utf8               apply
   #80 = Utf8               (ZILscala/collection/immutable/Map;Lscala/collection/immutable/Map;Lscala/collection/immutable/Set;Lscala/Option;Lscala/Option;ZLscala/collection/immutable/Seq;Lscala/collection/immutable/Seq;Lscala/collection/immutable/Seq;Lscala/collection/immutable/Set;Lscala/Option;Lscala/Option;ZZLjava/lang/String;)Lcoursier/params/ResolutionParams;
   #81 = Utf8               (ZILscala/collection/immutable/Map<Lcoursier/core/Module;Ljava/lang/String;>;Lscala/collection/immutable/Map<Ljava/lang/String;Ljava/lang/String;>;Lscala/collection/immutable/Set<Ljava/lang/String;>;Lscala/Option<Ljava/lang/String;>;Lscala/Option<Ljava/lang/Object;>;ZLscala/collection/immutable/Seq<Lscala/Tuple2<Lcoursier/params/rule/Rule;Lcoursier/params/rule/RuleResolution;>;>;Lscala/collection/immutable/Seq<Lscala/Tuple2<Lcoursier/util/ModuleMatchers;Lcoursier/core/Reconciliation;>;>;Lscala/collection/immutable/Seq<Lscala/Tuple2<Ljava/lang/String;Ljava/lang/String;>;>;Lscala/collection/immutable/Set<Lscala/Tuple2<Lcoursier/core/Organization;Lcoursier/core/ModuleName;>;>;Lscala/Option<Lcoursier/core/Activation$Os;>;Lscala/Option<Lcoursier/core/Version;>;ZZLjava/lang/String;)Lcoursier/params/ResolutionParams;
   #82 = Utf8               coursier/params/ResolutionParams$
   #83 = Class              #82           // coursier/params/ResolutionParams$
   #84 = Utf8               MODULE$
   #85 = Utf8               Lcoursier/params/ResolutionParams$;
   #86 = NameAndType        #84:#85       // MODULE$:Lcoursier/params/ResolutionParams$;
   #87 = Fieldref           #83.#86       // coursier/params/ResolutionParams$.MODULE$:Lcoursier/params/ResolutionParams$;
   #88 = NameAndType        #79:#80       // apply:(ZILscala/collection/immutable/Map;Lscala/collection/immutable/Map;Lscala/collection/immutable/Set;Lscala/Option;Lscala/Option;ZLscala/collection/immutable/Seq;Lscala/collection/immutable/Seq;Lscala/collection/immutable/Seq;Lscala/collection/immutable/Set;Lscala/Option;Lscala/Option;ZZLjava/lang/String;)Lcoursier/params/ResolutionParams;
   #89 = Methodref          #83.#88       // coursier/params/ResolutionParams$.apply:(ZILscala/collection/immutable/Map;Lscala/collection/immutable/Map;Lscala/collection/immutable/Set;Lscala/Option;Lscala/Option;ZLscala/collection/immutable/Seq;Lscala/collection/immutable/Seq;Lscala/collection/immutable/Seq;Lscala/collection/immutable/Set;Lscala/Option;Lscala/Option;ZZLjava/lang/String;)Lcoursier/params/ResolutionParams;
   #90 = Utf8               ()Lcoursier/params/ResolutionParams;
   #91 = NameAndType        #79:#90       // apply:()Lcoursier/params/ResolutionParams;
   #92 = Methodref          #83.#91       // coursier/params/ResolutionParams$.apply:()Lcoursier/params/ResolutionParams;
   #93 = Utf8               productIterator
   #94 = Utf8               ()Lscala/collection/Iterator;
   #95 = Utf8               ()Lscala/collection/Iterator<Ljava/lang/Object;>;
   #96 = Utf8               productIterator$
   #97 = Utf8               (Lscala/Product;)Lscala/collection/Iterator;
   #98 = NameAndType        #96:#97       // productIterator$:(Lscala/Product;)Lscala/collection/Iterator;
   #99 = InterfaceMethodref #6.#98        // scala/Product.productIterator$:(Lscala/Product;)Lscala/collection/Iterator;
  #100 = Utf8               this
  #101 = Utf8               Lcoursier/params/ResolutionParams;
  #102 = Utf8               productElementNames
  #103 = Utf8               ()Lscala/collection/Iterator<Ljava/lang/String;>;
  #104 = Utf8               productElementNames$
  #105 = NameAndType        #104:#97      // productElementNames$:(Lscala/Product;)Lscala/collection/Iterator;
  #106 = InterfaceMethodref #6.#105       // scala/Product.productElementNames$:(Lscala/Product;)Lscala/collection/Iterator;
  #107 = Utf8               ()Z
  #108 = NameAndType        #45:#46       // keepOptionalDependencies:Z
  #109 = Fieldref           #2.#108       // coursier/params/ResolutionParams.keepOptionalDependencies:Z
  #110 = Utf8               ()I
  #111 = NameAndType        #47:#48       // maxIterations:I
  #112 = Fieldref           #2.#111       // coursier/params/ResolutionParams.maxIterations:I
  #113 = Utf8               ()Lscala/collection/immutable/Map;
  #114 = Utf8               ()Lscala/collection/immutable/Map<Lcoursier/core/Module;Ljava/lang/String;>;
  #115 = NameAndType        #49:#50       // forceVersion:Lscala/collection/immutable/Map;
  #116 = Fieldref           #2.#115       // coursier/params/ResolutionParams.forceVersion:Lscala/collection/immutable/Map;
  #117 = Utf8               ()Lscala/collection/immutable/Map<Ljava/lang/String;Ljava/lang/String;>;
  #118 = NameAndType        #52:#50       // forcedProperties:Lscala/collection/immutable/Map;
  #119 = Fieldref           #2.#118       // coursier/params/ResolutionParams.forcedProperties:Lscala/collection/immutable/Map;
  #120 = Utf8               ()Lscala/collection/immutable/Set;
  #121 = Utf8               ()Lscala/collection/immutable/Set<Ljava/lang/String;>;
  #122 = NameAndType        #54:#55       // profiles:Lscala/collection/immutable/Set;
  #123 = Fieldref           #2.#122       // coursier/params/ResolutionParams.profiles:Lscala/collection/immutable/Set;
  #124 = Utf8               ()Lscala/Option;
  #125 = Utf8               ()Lscala/Option<Ljava/lang/String;>;
  #126 = NameAndType        #57:#58       // scalaVersionOpt:Lscala/Option;
  #127 = Fieldref           #2.#126       // coursier/params/ResolutionParams.scalaVersionOpt:Lscala/Option;
  #128 = Utf8               ()Lscala/Option<Ljava/lang/Object;>;
  #129 = NameAndType        #60:#58       // forceScalaVersionOpt:Lscala/Option;
  #130 = Fieldref           #2.#129       // coursier/params/ResolutionParams.forceScalaVersionOpt:Lscala/Option;
  #131 = NameAndType        #62:#46       // typelevel:Z
  #132 = Fieldref           #2.#131       // coursier/params/ResolutionParams.typelevel:Z
  #133 = Utf8               ()Lscala/collection/immutable/Seq;
  #134 = Utf8               ()Lscala/collection/immutable/Seq<Lscala/Tuple2<Lcoursier/params/rule/Rule;Lcoursier/params/rule/RuleResolution;>;>;
  #135 = NameAndType        #63:#43       // rules:Lscala/collection/immutable/Seq;
  #136 = Fieldref           #2.#135       // coursier/params/ResolutionParams.rules:Lscala/collection/immutable/Seq;
  #137 = Utf8               ()Lscala/collection/immutable/Seq<Lscala/Tuple2<Lcoursier/util/ModuleMatchers;Lcoursier/core/Reconciliation;>;>;
  #138 = NameAndType        #64:#43       // reconciliation:Lscala/collection/immutable/Seq;
  #139 = Fieldref           #2.#138       // coursier/params/ResolutionParams.reconciliation:Lscala/collection/immutable/Seq;
  #140 = Utf8               ()Lscala/collection/immutable/Seq<Lscala/Tuple2<Ljava/lang/String;Ljava/lang/String;>;>;
  #141 = NameAndType        #66:#43       // properties:Lscala/collection/immutable/Seq;
  #142 = Fieldref           #2.#141       // coursier/params/ResolutionParams.properties:Lscala/collection/immutable/Seq;
  #143 = Utf8               ()Lscala/collection/immutable/Set<Lscala/Tuple2<Lcoursier/core/Organization;Lcoursier/core/ModuleName;>;>;
  #144 = NameAndType        #68:#55       // exclusions:Lscala/collection/immutable/Set;
  #145 = Fieldref           #2.#144       // coursier/params/ResolutionParams.exclusions:Lscala/collection/immutable/Set;
  #146 = Utf8               ()Lscala/Option<Lcoursier/core/Activation$Os;>;
  #147 = NameAndType        #70:#58       // osInfoOpt:Lscala/Option;
  #148 = Fieldref           #2.#147       // coursier/params/ResolutionParams.osInfoOpt:Lscala/Option;
  #149 = Utf8               ()Lscala/Option<Lcoursier/core/Version;>;
  #150 = NameAndType        #72:#58       // jdkVersionOpt:Lscala/Option;
  #151 = Fieldref           #2.#150       // coursier/params/ResolutionParams.jdkVersionOpt:Lscala/Option;
  #152 = NameAndType        #74:#46       // useSystemOsInfo:Z
  #153 = Fieldref           #2.#152       // coursier/params/ResolutionParams.useSystemOsInfo:Z
  #154 = NameAndType        #75:#46       // useSystemJdkVersion:Z
  #155 = Fieldref           #2.#154       // coursier/params/ResolutionParams.useSystemJdkVersion:Z
  #156 = Utf8               ()Ljava/lang/String;
  #157 = NameAndType        #76:#77       // defaultConfiguration:Ljava/lang/String;
  #158 = Fieldref           #2.#157       // coursier/params/ResolutionParams.defaultConfiguration:Ljava/lang/String;
  #159 = Utf8               addForceVersion
  #160 = Utf8               (Lscala/collection/immutable/Seq;)Lcoursier/params/ResolutionParams;
  #161 = Utf8               (Lscala/collection/immutable/Seq<Lscala/Tuple2<Lcoursier/core/Module;Ljava/lang/String;>;>;)Lcoursier/params/ResolutionParams;
  #162 = Utf8               fv
  #163 = NameAndType        #49:#113      // forceVersion:()Lscala/collection/immutable/Map;
  #164 = Methodref          #2.#163       // coursier/params/ResolutionParams.forceVersion:()Lscala/collection/immutable/Map;
  #165 = Utf8               scala/collection/immutable/Map
  #166 = Class              #165          // scala/collection/immutable/Map
  #167 = Utf8               $plus$plus
  #168 = Utf8               (Lscala/collection/IterableOnce;)Lscala/collection/IterableOps;
  #169 = NameAndType        #167:#168     // $plus$plus:(Lscala/collection/IterableOnce;)Lscala/collection/IterableOps;
  #170 = InterfaceMethodref #166.#169     // scala/collection/immutable/Map.$plus$plus:(Lscala/collection/IterableOnce;)Lscala/collection/IterableOps;
  #171 = Utf8               withForceVersion
  #172 = Utf8               (Lscala/collection/immutable/Map;)Lcoursier/params/ResolutionParams;
  #173 = NameAndType        #171:#172     // withForceVersion:(Lscala/collection/immutable/Map;)Lcoursier/params/ResolutionParams;
  #174 = Methodref          #2.#173       // coursier/params/ResolutionParams.withForceVersion:(Lscala/collection/immutable/Map;)Lcoursier/params/ResolutionParams;
  #175 = Utf8               doForceScalaVersion
  #176 = NameAndType        #60:#124      // forceScalaVersionOpt:()Lscala/Option;
  #177 = Methodref          #2.#176       // coursier/params/ResolutionParams.forceScalaVersionOpt:()Lscala/Option;
  #178 = MethodType         #107          //  ()Z
  #179 = Utf8               $anonfun$doForceScalaVersion$1
  #180 = Utf8               (Lcoursier/params/ResolutionParams;)Z
  #181 = NameAndType        #179:#180     // $anonfun$doForceScalaVersion$1:(Lcoursier/params/ResolutionParams;)Z
  #182 = Methodref          #2.#181       // coursier/params/ResolutionParams.$anonfun$doForceScalaVersion$1:(Lcoursier/params/ResolutionParams;)Z
  #183 = MethodHandle       6:#182        // REF_invokeStatic coursier/params/ResolutionParams.$anonfun$doForceScalaVersion$1:(Lcoursier/params/ResolutionParams;)Z
  #184 = Integer            1
  #185 = Utf8               java/lang/invoke/LambdaMetafactory
  #186 = Class              #185          // java/lang/invoke/LambdaMetafactory
  #187 = Utf8               altMetafactory
  #188 = Utf8               (Ljava/lang/invoke/MethodHandles$Lookup;Ljava/lang/String;Ljava/lang/invoke/MethodType;[Ljava/lang/Object;)Ljava/lang/invoke/CallSite;
  #189 = NameAndType        #187:#188     // altMetafactory:(Ljava/lang/invoke/MethodHandles$Lookup;Ljava/lang/String;Ljava/lang/invoke/MethodType;[Ljava/lang/Object;)Ljava/lang/invoke/CallSite;
  #190 = Methodref          #186.#189     // java/lang/invoke/LambdaMetafactory.altMetafactory:(Ljava/lang/invoke/MethodHandles$Lookup;Ljava/lang/String;Ljava/lang/invoke/MethodType;[Ljava/lang/Object;)Ljava/lang/invoke/CallSite;
  #191 = MethodHandle       6:#190        // REF_invokeStatic java/lang/invoke/LambdaMetafactory.altMetafactory:(Ljava/lang/invoke/MethodHandles$Lookup;Ljava/lang/String;Ljava/lang/invoke/MethodType;[Ljava/lang/Object;)Ljava/lang/invoke/CallSite;
  #192 = Utf8               apply$mcZ$sp
  #193 = Utf8               (Lcoursier/params/ResolutionParams;)Lscala/runtime/java8/JFunction0$mcZ$sp;
  #194 = NameAndType        #192:#193     // apply$mcZ$sp:(Lcoursier/params/ResolutionParams;)Lscala/runtime/java8/JFunction0$mcZ$sp;
  #195 = InvokeDynamic      #0:#194       // #0:apply$mcZ$sp:(Lcoursier/params/ResolutionParams;)Lscala/runtime/java8/JFunction0$mcZ$sp;
  #196 = Utf8               scala/Option
  #197 = Class              #196          // scala/Option
  #198 = Utf8               getOrElse
  #199 = Utf8               (Lscala/Function0;)Ljava/lang/Object;
  #200 = NameAndType        #198:#199     // getOrElse:(Lscala/Function0;)Ljava/lang/Object;
  #201 = Methodref          #197.#200     // scala/Option.getOrElse:(Lscala/Function0;)Ljava/lang/Object;
  #202 = Utf8               scala/runtime/BoxesRunTime
  #203 = Class              #202          // scala/runtime/BoxesRunTime
  #204 = Utf8               unboxToBoolean
  #205 = Utf8               (Ljava/lang/Object;)Z
  #206 = NameAndType        #204:#205     // unboxToBoolean:(Ljava/lang/Object;)Z
  #207 = Methodref          #203.#206     // scala/runtime/BoxesRunTime.unboxToBoolean:(Ljava/lang/Object;)Z
  #208 = Utf8               selectedScalaVersion
  #209 = NameAndType        #57:#124      // scalaVersionOpt:()Lscala/Option;
  #210 = Methodref          #2.#209       // coursier/params/ResolutionParams.scalaVersionOpt:()Lscala/Option;
  #211 = Utf8               ()Ljava/lang/Object;
  #212 = MethodType         #211          //  ()Ljava/lang/Object;
  #213 = Utf8               $anonfun$selectedScalaVersion$1
  #214 = NameAndType        #213:#156     // $anonfun$selectedScalaVersion$1:()Ljava/lang/String;
  #215 = Methodref          #2.#214       // coursier/params/ResolutionParams.$anonfun$selectedScalaVersion$1:()Ljava/lang/String;
  #216 = MethodHandle       6:#215        // REF_invokeStatic coursier/params/ResolutionParams.$anonfun$selectedScalaVersion$1:()Ljava/lang/String;
  #217 = MethodType         #156          //  ()Ljava/lang/String;
  #218 = Integer            5
  #219 = Utf8               ()Lscala/Function0;
  #220 = NameAndType        #79:#219      // apply:()Lscala/Function0;
  #221 = InvokeDynamic      #1:#220       // #1:apply:()Lscala/Function0;
  #222 = Utf8               java/lang/String
  #223 = Class              #222          // java/lang/String
  #224 = Utf8               addProfile
  #225 = Utf8               (Lscala/collection/immutable/Seq<Ljava/lang/String;>;)Lcoursier/params/ResolutionParams;
  #226 = Utf8               profile
  #227 = NameAndType        #54:#120      // profiles:()Lscala/collection/immutable/Set;
  #228 = Methodref          #2.#227       // coursier/params/ResolutionParams.profiles:()Lscala/collection/immutable/Set;
  #229 = Utf8               scala/collection/immutable/Set
  #230 = Class              #229          // scala/collection/immutable/Set
  #231 = Utf8               (Lscala/collection/IterableOnce;)Lscala/collection/SetOps;
  #232 = NameAndType        #167:#231     // $plus$plus:(Lscala/collection/IterableOnce;)Lscala/collection/SetOps;
  #233 = InterfaceMethodref #230.#232     // scala/collection/immutable/Set.$plus$plus:(Lscala/collection/IterableOnce;)Lscala/collection/SetOps;
  #234 = Utf8               withProfiles
  #235 = Utf8               (Lscala/collection/immutable/Set;)Lcoursier/params/ResolutionParams;
  #236 = NameAndType        #234:#235     // withProfiles:(Lscala/collection/immutable/Set;)Lcoursier/params/ResolutionParams;
  #237 = Methodref          #2.#236       // coursier/params/ResolutionParams.withProfiles:(Lscala/collection/immutable/Set;)Lcoursier/params/ResolutionParams;
  #238 = Utf8               addRule
  #239 = Utf8               (Lcoursier/params/rule/Rule;Lcoursier/params/rule/RuleResolution;)Lcoursier/params/ResolutionParams;
  #240 = Utf8               rule
  #241 = Utf8               resolution
  #242 = Utf8               scala/collection/immutable/$colon$colon
  #243 = Class              #242          // scala/collection/immutable/$colon$colon
  #244 = Utf8               Lscala/Predef$ArrowAssoc$;
  #245 = NameAndType        #84:#244      // MODULE$:Lscala/Predef$ArrowAssoc$;
  #246 = Fieldref           #39.#245      // scala/Predef$ArrowAssoc$.MODULE$:Lscala/Predef$ArrowAssoc$;
  #247 = Utf8               scala/Predef$
  #248 = Class              #247          // scala/Predef$
  #249 = Utf8               Lscala/Predef$;
  #250 = NameAndType        #84:#249      // MODULE$:Lscala/Predef$;
  #251 = Fieldref           #248.#250     // scala/Predef$.MODULE$:Lscala/Predef$;
  #252 = Utf8               ArrowAssoc
  #253 = Utf8               (Ljava/lang/Object;)Ljava/lang/Object;
  #254 = NameAndType        #252:#253     // ArrowAssoc:(Ljava/lang/Object;)Ljava/lang/Object;
  #255 = Methodref          #248.#254     // scala/Predef$.ArrowAssoc:(Ljava/lang/Object;)Ljava/lang/Object;
  #256 = Utf8               $minus$greater$extension
  #257 = Utf8               (Ljava/lang/Object;Ljava/lang/Object;)Lscala/Tuple2;
  #258 = NameAndType        #256:#257     // $minus$greater$extension:(Ljava/lang/Object;Ljava/lang/Object;)Lscala/Tuple2;
  #259 = Methodref          #39.#258      // scala/Predef$ArrowAssoc$.$minus$greater$extension:(Ljava/lang/Object;Ljava/lang/Object;)Lscala/Tuple2;
  #260 = Utf8               scala/collection/immutable/Nil$
  #261 = Class              #260          // scala/collection/immutable/Nil$
  #262 = Utf8               Lscala/collection/immutable/Nil$;
  #263 = NameAndType        #84:#262      // MODULE$:Lscala/collection/immutable/Nil$;
  #264 = Fieldref           #261.#263     // scala/collection/immutable/Nil$.MODULE$:Lscala/collection/immutable/Nil$;
  #265 = Utf8               <init>
  #266 = Utf8               (Ljava/lang/Object;Lscala/collection/immutable/List;)V
  #267 = NameAndType        #265:#266     // "<init>":(Ljava/lang/Object;Lscala/collection/immutable/List;)V
  #268 = Methodref          #243.#267     // scala/collection/immutable/$colon$colon."<init>":(Ljava/lang/Object;Lscala/collection/immutable/List;)V
  #269 = Utf8               scala/collection/immutable/Seq
  #270 = Class              #269          // scala/collection/immutable/Seq
  #271 = Utf8               withRules
  #272 = NameAndType        #271:#160     // withRules:(Lscala/collection/immutable/Seq;)Lcoursier/params/ResolutionParams;
  #273 = Methodref          #2.#272       // coursier/params/ResolutionParams.withRules:(Lscala/collection/immutable/Seq;)Lcoursier/params/ResolutionParams;
  #274 = Utf8               Lcoursier/params/rule/Rule;
  #275 = Utf8               Lcoursier/params/rule/RuleResolution;
  #276 = Utf8               (Lcoursier/params/rule/Rule;)Lcoursier/params/ResolutionParams;
  #277 = Utf8               Lcoursier/params/rule/RuleResolution$TryResolve$;
  #278 = NameAndType        #84:#277      // MODULE$:Lcoursier/params/rule/RuleResolution$TryResolve$;
  #279 = Fieldref           #30.#278      // coursier/params/rule/RuleResolution$TryResolve$.MODULE$:Lcoursier/params/rule/RuleResolution$TryResolve$;
  #280 = NameAndType        #238:#239     // addRule:(Lcoursier/params/rule/Rule;Lcoursier/params/rule/RuleResolution;)Lcoursier/params/ResolutionParams;
  #281 = Methodref          #2.#280       // coursier/params/ResolutionParams.addRule:(Lcoursier/params/rule/Rule;Lcoursier/params/rule/RuleResolution;)Lcoursier/params/ResolutionParams;
  #282 = Utf8               addProperties
  #283 = Utf8               (Lscala/collection/immutable/Seq<Lscala/Tuple2<Ljava/lang/String;Ljava/lang/String;>;>;)Lcoursier/params/ResolutionParams;
  #284 = Utf8               props
  #285 = NameAndType        #66:#133      // properties:()Lscala/collection/immutable/Seq;
  #286 = Methodref          #2.#285       // coursier/params/ResolutionParams.properties:()Lscala/collection/immutable/Seq;
  #287 = Utf8               (Lscala/collection/IterableOnce;)Ljava/lang/Object;
  #288 = NameAndType        #167:#287     // $plus$plus:(Lscala/collection/IterableOnce;)Ljava/lang/Object;
  #289 = InterfaceMethodref #270.#288     // scala/collection/immutable/Seq.$plus$plus:(Lscala/collection/IterableOnce;)Ljava/lang/Object;
  #290 = Utf8               withProperties
  #291 = NameAndType        #290:#160     // withProperties:(Lscala/collection/immutable/Seq;)Lcoursier/params/ResolutionParams;
  #292 = Methodref          #2.#291       // coursier/params/ResolutionParams.withProperties:(Lscala/collection/immutable/Seq;)Lcoursier/params/ResolutionParams;
  #293 = Utf8               addForcedProperties
  #294 = NameAndType        #52:#113      // forcedProperties:()Lscala/collection/immutable/Map;
  #295 = Methodref          #2.#294       // coursier/params/ResolutionParams.forcedProperties:()Lscala/collection/immutable/Map;
  #296 = Utf8               withForcedProperties
  #297 = NameAndType        #296:#172     // withForcedProperties:(Lscala/collection/immutable/Map;)Lcoursier/params/ResolutionParams;
  #298 = Methodref          #2.#297       // coursier/params/ResolutionParams.withForcedProperties:(Lscala/collection/immutable/Map;)Lcoursier/params/ResolutionParams;
  #299 = Utf8               withScalaVersion
  #300 = Utf8               (Ljava/lang/String;)Lcoursier/params/ResolutionParams;
  #301 = Utf8               scalaVersion
  #302 = Utf8               scala/Option$
  #303 = Class              #302          // scala/Option$
  #304 = Utf8               Lscala/Option$;
  #305 = NameAndType        #84:#304      // MODULE$:Lscala/Option$;
  #306 = Fieldref           #303.#305     // scala/Option$.MODULE$:Lscala/Option$;
  #307 = Utf8               (Ljava/lang/Object;)Lscala/Option;
  #308 = NameAndType        #79:#307      // apply:(Ljava/lang/Object;)Lscala/Option;
  #309 = Methodref          #303.#308     // scala/Option$.apply:(Ljava/lang/Object;)Lscala/Option;
  #310 = Utf8               withScalaVersionOpt
  #311 = Utf8               (Lscala/Option;)Lcoursier/params/ResolutionParams;
  #312 = NameAndType        #310:#311     // withScalaVersionOpt:(Lscala/Option;)Lcoursier/params/ResolutionParams;
  #313 = Methodref          #2.#312       // coursier/params/ResolutionParams.withScalaVersionOpt:(Lscala/Option;)Lcoursier/params/ResolutionParams;
  #314 = Utf8               withForceScalaVersion
  #315 = Utf8               (Z)Lcoursier/params/ResolutionParams;
  #316 = Utf8               forceScalaVersion
  #317 = Utf8               boxToBoolean
  #318 = Utf8               (Z)Ljava/lang/Boolean;
  #319 = NameAndType        #317:#318     // boxToBoolean:(Z)Ljava/lang/Boolean;
  #320 = Methodref          #203.#319     // scala/runtime/BoxesRunTime.boxToBoolean:(Z)Ljava/lang/Boolean;
  #321 = Utf8               withForceScalaVersionOpt
  #322 = NameAndType        #321:#311     // withForceScalaVersionOpt:(Lscala/Option;)Lcoursier/params/ResolutionParams;
  #323 = Methodref          #2.#322       // coursier/params/ResolutionParams.withForceScalaVersionOpt:(Lscala/Option;)Lcoursier/params/ResolutionParams;
  #324 = Utf8               withOsInfo
  #325 = Utf8               (Lcoursier/core/Activation$Os;)Lcoursier/params/ResolutionParams;
  #326 = Utf8               osInfo
  #327 = Utf8               scala/Some
  #328 = Class              #327          // scala/Some
  #329 = Utf8               (Ljava/lang/Object;)V
  #330 = NameAndType        #265:#329     // "<init>":(Ljava/lang/Object;)V
  #331 = Methodref          #328.#330     // scala/Some."<init>":(Ljava/lang/Object;)V
  #332 = Utf8               withOsInfoOpt
  #333 = NameAndType        #332:#311     // withOsInfoOpt:(Lscala/Option;)Lcoursier/params/ResolutionParams;
  #334 = Methodref          #2.#333       // coursier/params/ResolutionParams.withOsInfoOpt:(Lscala/Option;)Lcoursier/params/ResolutionParams;
  #335 = Utf8               Lcoursier/core/Activation$Os;
  #336 = Utf8               withJdkVersion
  #337 = Utf8               version
  #338 = Utf8               coursier/core/Version$
  #339 = Class              #338          // coursier/core/Version$
  #340 = Utf8               Lcoursier/core/Version$;
  #341 = NameAndType        #84:#340      // MODULE$:Lcoursier/core/Version$;
  #342 = Fieldref           #339.#341     // coursier/core/Version$.MODULE$:Lcoursier/core/Version$;
  #343 = Utf8               (Ljava/lang/String;)Lcoursier/core/Version;
  #344 = NameAndType        #79:#343      // apply:(Ljava/lang/String;)Lcoursier/core/Version;
  #345 = Methodref          #339.#344     // coursier/core/Version$.apply:(Ljava/lang/String;)Lcoursier/core/Version;
  #346 = Utf8               withJdkVersionOpt
  #347 = NameAndType        #346:#311     // withJdkVersionOpt:(Lscala/Option;)Lcoursier/params/ResolutionParams;
  #348 = Methodref          #2.#347       // coursier/params/ResolutionParams.withJdkVersionOpt:(Lscala/Option;)Lcoursier/params/ResolutionParams;
  #349 = Utf8               (Lcoursier/core/Version;)Lcoursier/params/ResolutionParams;
  #350 = Utf8               Lcoursier/core/Version;
  #351 = Utf8               addReconciliation
  #352 = Utf8               (Lscala/collection/immutable/Seq<Lscala/Tuple2<Lcoursier/util/ModuleMatchers;Lcoursier/core/Reconciliation;>;>;)Lcoursier/params/ResolutionParams;
  #353 = NameAndType        #64:#133      // reconciliation:()Lscala/collection/immutable/Seq;
  #354 = Methodref          #2.#353       // coursier/params/ResolutionParams.reconciliation:()Lscala/collection/immutable/Seq;
  #355 = Utf8               withReconciliation
  #356 = NameAndType        #355:#160     // withReconciliation:(Lscala/collection/immutable/Seq;)Lcoursier/params/ResolutionParams;
  #357 = Methodref          #2.#356       // coursier/params/ResolutionParams.withReconciliation:(Lscala/collection/immutable/Seq;)Lcoursier/params/ResolutionParams;
  #358 = Utf8               addExclusions
  #359 = Utf8               (Lscala/collection/immutable/Seq<Lscala/Tuple2<Lcoursier/core/Organization;Lcoursier/core/ModuleName;>;>;)Lcoursier/params/ResolutionParams;
  #360 = NameAndType        #68:#120      // exclusions:()Lscala/collection/immutable/Set;
  #361 = Methodref          #2.#360       // coursier/params/ResolutionParams.exclusions:()Lscala/collection/immutable/Set;
  #362 = Utf8               withExclusions
  #363 = NameAndType        #362:#235     // withExclusions:(Lscala/collection/immutable/Set;)Lcoursier/params/ResolutionParams;
  #364 = Methodref          #2.#363       // coursier/params/ResolutionParams.withExclusions:(Lscala/collection/immutable/Set;)Lcoursier/params/ResolutionParams;
  #365 = Utf8               actualReconciliation
  #366 = MethodType         #253          //  (Ljava/lang/Object;)Ljava/lang/Object;
  #367 = Utf8               $anonfun$actualReconciliation$1
  #368 = Utf8               (Lscala/Tuple2;)Lscala/Tuple2;
  #369 = NameAndType        #367:#368     // $anonfun$actualReconciliation$1:(Lscala/Tuple2;)Lscala/Tuple2;
  #370 = Methodref          #2.#369       // coursier/params/ResolutionParams.$anonfun$actualReconciliation$1:(Lscala/Tuple2;)Lscala/Tuple2;
  #371 = MethodHandle       6:#370        // REF_invokeStatic coursier/params/ResolutionParams.$anonfun$actualReconciliation$1:(Lscala/Tuple2;)Lscala/Tuple2;
  #372 = MethodType         #368          //  (Lscala/Tuple2;)Lscala/Tuple2;
  #373 = Utf8               ()Lscala/Function1;
  #374 = NameAndType        #79:#373      // apply:()Lscala/Function1;
  #375 = InvokeDynamic      #2:#374       // #2:apply:()Lscala/Function1;
  #376 = Utf8               map
  #377 = Utf8               (Lscala/Function1;)Ljava/lang/Object;
  #378 = NameAndType        #376:#377     // map:(Lscala/Function1;)Ljava/lang/Object;
  #379 = InterfaceMethodref #270.#378     // scala/collection/immutable/Seq.map:(Lscala/Function1;)Ljava/lang/Object;
  #380 = Utf8               actualRules$lzycompute
  #381 = NameAndType        #78:#46       // bitmap$0:Z
  #382 = Fieldref           #2.#381       // coursier/params/ResolutionParams.bitmap$0:Z
  #383 = Utf8               (Lcoursier/params/ResolutionParams;)V
  #384 = NameAndType        #265:#383     // "<init>":(Lcoursier/params/ResolutionParams;)V
  #385 = Methodref          #28.#384      // coursier/params/ResolutionParams$$anonfun$1."<init>":(Lcoursier/params/ResolutionParams;)V
  #386 = Utf8               collect
  #387 = Utf8               (Lscala/PartialFunction;)Ljava/lang/Object;
  #388 = NameAndType        #386:#387     // collect:(Lscala/PartialFunction;)Ljava/lang/Object;
  #389 = InterfaceMethodref #270.#388     // scala/collection/immutable/Seq.collect:(Lscala/PartialFunction;)Ljava/lang/Object;
  #390 = NameAndType        #63:#133      // rules:()Lscala/collection/immutable/Seq;
  #391 = Methodref          #2.#390       // coursier/params/ResolutionParams.rules:()Lscala/collection/immutable/Seq;
  #392 = NameAndType        #42:#43       // actualRules:Lscala/collection/immutable/Seq;
  #393 = Fieldref           #2.#392       // coursier/params/ResolutionParams.actualRules:Lscala/collection/immutable/Seq;
  #394 = Utf8               java/lang/Throwable
  #395 = Class              #394          // java/lang/Throwable
  #396 = Utf8               fromReconciliation
  #397 = NameAndType        #380:#133     // actualRules$lzycompute:()Lscala/collection/immutable/Seq;
  #398 = Methodref          #2.#397       // coursier/params/ResolutionParams.actualRules$lzycompute:()Lscala/collection/immutable/Seq;
  #399 = Utf8               withKeepOptionalDependencies
  #400 = NameAndType        #47:#110      // maxIterations:()I
  #401 = Methodref          #2.#400       // coursier/params/ResolutionParams.maxIterations:()I
  #402 = NameAndType        #62:#107      // typelevel:()Z
  #403 = Methodref          #2.#402       // coursier/params/ResolutionParams.typelevel:()Z
  #404 = NameAndType        #70:#124      // osInfoOpt:()Lscala/Option;
  #405 = Methodref          #2.#404       // coursier/params/ResolutionParams.osInfoOpt:()Lscala/Option;
  #406 = NameAndType        #72:#124      // jdkVersionOpt:()Lscala/Option;
  #407 = Methodref          #2.#406       // coursier/params/ResolutionParams.jdkVersionOpt:()Lscala/Option;
  #408 = NameAndType        #74:#107      // useSystemOsInfo:()Z
  #409 = Methodref          #2.#408       // coursier/params/ResolutionParams.useSystemOsInfo:()Z
  #410 = NameAndType        #75:#107      // useSystemJdkVersion:()Z
  #411 = Methodref          #2.#410       // coursier/params/ResolutionParams.useSystemJdkVersion:()Z
  #412 = NameAndType        #76:#156      // defaultConfiguration:()Ljava/lang/String;
  #413 = Methodref          #2.#412       // coursier/params/ResolutionParams.defaultConfiguration:()Ljava/lang/String;
  #414 = Utf8               (ZILscala/collection/immutable/Map;Lscala/collection/immutable/Map;Lscala/collection/immutable/Set;Lscala/Option;Lscala/Option;ZLscala/collection/immutable/Seq;Lscala/collection/immutable/Seq;Lscala/collection/immutable/Seq;Lscala/collection/immutable/Set;Lscala/Option;Lscala/Option;ZZLjava/lang/String;)V
  #415 = NameAndType        #265:#414     // "<init>":(ZILscala/collection/immutable/Map;Lscala/collection/immutable/Map;Lscala/collection/immutable/Set;Lscala/Option;Lscala/Option;ZLscala/collection/immutable/Seq;Lscala/collection/immutable/Seq;Lscala/collection/immutable/Seq;Lscala/collection/immutable/Set;Lscala/Option;Lscala/Option;ZZLjava/lang/String;)V
  #416 = Methodref          #2.#415       // coursier/params/ResolutionParams."<init>":(ZILscala/collection/immutable/Map;Lscala/collection/immutable/Map;Lscala/collection/immutable/Set;Lscala/Option;Lscala/Option;ZLscala/collection/immutable/Seq;Lscala/collection/immutable/Seq;Lscala/collection/immutable/Seq;Lscala/collection/immutable/Set;Lscala/Option;Lscala/Option;ZZLjava/lang/String;)V
  #417 = Utf8               withMaxIterations
  #418 = Utf8               (I)Lcoursier/params/ResolutionParams;
  #419 = NameAndType        #45:#107      // keepOptionalDependencies:()Z
  #420 = Methodref          #2.#419       // coursier/params/ResolutionParams.keepOptionalDependencies:()Z
  #421 = Utf8               (Lscala/collection/immutable/Map<Lcoursier/core/Module;Ljava/lang/String;>;)Lcoursier/params/ResolutionParams;
  #422 = Utf8               (Lscala/collection/immutable/Map<Ljava/lang/String;Ljava/lang/String;>;)Lcoursier/params/ResolutionParams;
  #423 = Utf8               (Lscala/collection/immutable/Set<Ljava/lang/String;>;)Lcoursier/params/ResolutionParams;
  #424 = Utf8               (Lscala/Option<Ljava/lang/String;>;)Lcoursier/params/ResolutionParams;
  #425 = Utf8               (Lscala/Option<Ljava/lang/Object;>;)Lcoursier/params/ResolutionParams;
  #426 = Utf8               withTypelevel
  #427 = Utf8               (Lscala/collection/immutable/Seq<Lscala/Tuple2<Lcoursier/params/rule/Rule;Lcoursier/params/rule/RuleResolution;>;>;)Lcoursier/params/ResolutionParams;
  #428 = Utf8               (Lscala/collection/immutable/Set<Lscala/Tuple2<Lcoursier/core/Organization;Lcoursier/core/ModuleName;>;>;)Lcoursier/params/ResolutionParams;
  #429 = Utf8               (Lscala/Option<Lcoursier/core/Activation$Os;>;)Lcoursier/params/ResolutionParams;
  #430 = Utf8               (Lscala/Option<Lcoursier/core/Version;>;)Lcoursier/params/ResolutionParams;
  #431 = Utf8               withUseSystemOsInfo
  #432 = Utf8               withUseSystemJdkVersion
  #433 = Utf8               withDefaultConfiguration
  #434 = Utf8               toString
  #435 = Utf8               java/lang/StringBuilder
  #436 = Class              #435          // java/lang/StringBuilder
  #437 = Utf8               ResolutionParams(
  #438 = String             #437          // ResolutionParams(
  #439 = Utf8               (Ljava/lang/String;)V
  #440 = NameAndType        #265:#439     // "<init>":(Ljava/lang/String;)V
  #441 = Methodref          #436.#440     // java/lang/StringBuilder."<init>":(Ljava/lang/String;)V
  #442 = Utf8               valueOf
  #443 = Utf8               (Z)Ljava/lang/String;
  #444 = NameAndType        #442:#443     // valueOf:(Z)Ljava/lang/String;
  #445 = Methodref          #223.#444     // java/lang/String.valueOf:(Z)Ljava/lang/String;
  #446 = Utf8               append
  #447 = Utf8               (Ljava/lang/String;)Ljava/lang/StringBuilder;
  #448 = NameAndType        #446:#447     // append:(Ljava/lang/String;)Ljava/lang/StringBuilder;
  #449 = Methodref          #436.#448     // java/lang/StringBuilder.append:(Ljava/lang/String;)Ljava/lang/StringBuilder;
  #450 = Utf8               ,
  #451 = String             #450          // ,
  #452 = Utf8               (I)Ljava/lang/String;
  #453 = NameAndType        #442:#452     // valueOf:(I)Ljava/lang/String;
  #454 = Methodref          #223.#453     // java/lang/String.valueOf:(I)Ljava/lang/String;
  #455 = Utf8               (Ljava/lang/Object;)Ljava/lang/String;
  #456 = NameAndType        #442:#455     // valueOf:(Ljava/lang/Object;)Ljava/lang/String;
  #457 = Methodref          #223.#456     // java/lang/String.valueOf:(Ljava/lang/Object;)Ljava/lang/String;
  #458 = Utf8               coursier/core/Configuration
  #459 = Class              #458          // coursier/core/Configuration
  #460 = Methodref          #459.#440     // coursier/core/Configuration."<init>":(Ljava/lang/String;)V
  #461 = Utf8               )
  #462 = String             #461          // )
  #463 = NameAndType        #434:#156     // toString:()Ljava/lang/String;
  #464 = Methodref          #436.#463     // java/lang/StringBuilder.toString:()Ljava/lang/String;
  #465 = Utf8               b
  #466 = Utf8               Ljava/lang/StringBuilder;
  #467 = Utf8               canEqual
  #468 = Utf8               obj
  #469 = Utf8               Ljava/lang/Object;
  #470 = Utf8               equals
  #471 = NameAndType        #467:#205     // canEqual:(Ljava/lang/Object;)Z
  #472 = Methodref          #2.#471       // coursier/params/ResolutionParams.canEqual:(Ljava/lang/Object;)Z
  #473 = NameAndType        #470:#205     // equals:(Ljava/lang/Object;)Z
  #474 = Methodref          #4.#473       // java/lang/Object.equals:(Ljava/lang/Object;)Z
  #475 = Utf8               other
  #476 = Utf8               hashCode
  #477 = Utf8               ResolutionParams
  #478 = String             #477          // ResolutionParams
  #479 = Utf8               scala/runtime/Statics
  #480 = Class              #479          // scala/runtime/Statics
  #481 = Utf8               anyHash
  #482 = Utf8               (Ljava/lang/Object;)I
  #483 = NameAndType        #481:#482     // anyHash:(Ljava/lang/Object;)I
  #484 = Methodref          #480.#483     // scala/runtime/Statics.anyHash:(Ljava/lang/Object;)I
  #485 = Utf8               code
  #486 = Utf8               tuple
  #487 = Utf8               ()Lscala/Tuple17;
  #488 = Utf8               ()Lscala/Tuple17<Ljava/lang/Object;Ljava/lang/Object;Lscala/collection/immutable/Map<Lcoursier/core/Module;Ljava/lang/String;>;Lscala/collection/immutable/Map<Ljava/lang/String;Ljava/lang/String;>;Lscala/collection/immutable/Set<Ljava/lang/String;>;Lscala/Option<Ljava/lang/String;>;Lscala/Option<Ljava/lang/Object;>;Ljava/lang/Object;Lscala/collection/immutable/Seq<Lscala/Tuple2<Lcoursier/params/rule/Rule;Lcoursier/params/rule/RuleResolution;>;>;Lscala/collection/immutable/Seq<Lscala/Tuple2<Lcoursier/util/ModuleMatchers;Lcoursier/core/Reconciliation;>;>;Lscala/collection/immutable/Seq<Lscala/Tuple2<Ljava/lang/String;Ljava/lang/String;>;>;Lscala/collection/immutable/Set<Lscala/Tuple2<Lcoursier/core/Organization;Lcoursier/core/ModuleName;>;>;Lscala/Option<Lcoursier/core/Activation$Os;>;Lscala/Option<Lcoursier/core/Version;>;Ljava/lang/Object;Ljava/lang/Object;Lcoursier/core/Configuration;>;
  #489 = Utf8               scala/Tuple17
  #490 = Class              #489          // scala/Tuple17
  #491 = Utf8               boxToInteger
  #492 = Utf8               (I)Ljava/lang/Integer;
  #493 = NameAndType        #491:#492     // boxToInteger:(I)Ljava/lang/Integer;
  #494 = Methodref          #203.#493     // scala/runtime/BoxesRunTime.boxToInteger:(I)Ljava/lang/Integer;
  #495 = Utf8               (Ljava/lang/Object;Ljava/lang/Object;Ljava/lang/Object;Ljava/lang/Object;Ljava/lang/Object;Ljava/lang/Object;Ljava/lang/Object;Ljava/lang/Object;Ljava/lang/Object;Ljava/lang/Object;Ljava/lang/Object;Ljava/lang/Object;Ljava/lang/Object;Ljava/lang/Object;Ljava/lang/Object;Ljava/lang/Object;Ljava/lang/Object;)V
  #496 = NameAndType        #265:#495     // "<init>":(Ljava/lang/Object;Ljava/lang/Object;Ljava/lang/Object;Ljava/lang/Object;Ljava/lang/Object;Ljava/lang/Object;Ljava/lang/Object;Ljava/lang/Object;Ljava/lang/Object;Ljava/lang/Object;Ljava/lang/Object;Ljava/lang/Object;Ljava/lang/Object;Ljava/lang/Object;Ljava/lang/Object;Ljava/lang/Object;Ljava/lang/Object;)V
  #497 = Methodref          #490.#496     // scala/Tuple17."<init>":(Ljava/lang/Object;Ljava/lang/Object;Ljava/lang/Object;Ljava/lang/Object;Ljava/lang/Object;Ljava/lang/Object;Ljava/lang/Object;Ljava/lang/Object;Ljava/lang/Object;Ljava/lang/Object;Ljava/lang/Object;Ljava/lang/Object;Ljava/lang/Object;Ljava/lang/Object;Ljava/lang/Object;Ljava/lang/Object;Ljava/lang/Object;)V
  #498 = Utf8               productPrefix
  #499 = Utf8               productArity
  #500 = Utf8               productElement
  #501 = Utf8               (I)Ljava/lang/Object;
  #502 = Utf8               n
  #503 = Utf8               java/lang/IndexOutOfBoundsException
  #504 = Class              #503          // java/lang/IndexOutOfBoundsException
  #505 = Methodref          #4.#463       // java/lang/Object.toString:()Ljava/lang/String;
  #506 = Methodref          #504.#440     // java/lang/IndexOutOfBoundsException."<init>":(Ljava/lang/String;)V
  #507 = Utf8               productElementName
  #508 = String             #45           // keepOptionalDependencies
  #509 = String             #47           // maxIterations
  #510 = String             #49           // forceVersion
  #511 = String             #52           // forcedProperties
  #512 = String             #54           // profiles
  #513 = String             #57           // scalaVersionOpt
  #514 = String             #60           // forceScalaVersionOpt
  #515 = String             #62           // typelevel
  #516 = String             #63           // rules
  #517 = String             #64           // reconciliation
  #518 = String             #66           // properties
  #519 = String             #68           // exclusions
  #520 = String             #70           // osInfoOpt
  #521 = String             #72           // jdkVersionOpt
  #522 = String             #74           // useSystemOsInfo
  #523 = String             #75           // useSystemJdkVersion
  #524 = String             #76           // defaultConfiguration
  #525 = Utf8               $this
  #526 = Utf8               nonEmpty
  #527 = NameAndType        #526:#107     // nonEmpty:()Z
  #528 = Methodref          #197.#527     // scala/Option.nonEmpty:()Z
  #529 = Utf8               coursier/internal/Defaults$
  #530 = Class              #529          // coursier/internal/Defaults$
  #531 = Utf8               Lcoursier/internal/Defaults$;
  #532 = NameAndType        #84:#531      // MODULE$:Lcoursier/internal/Defaults$;
  #533 = Fieldref           #530.#532     // coursier/internal/Defaults$.MODULE$:Lcoursier/internal/Defaults$;
  #534 = NameAndType        #301:#156     // scalaVersion:()Ljava/lang/String;
  #535 = Methodref          #530.#534     // coursier/internal/Defaults$.scalaVersion:()Ljava/lang/String;
  #536 = Utf8               x0$1
  #537 = Utf8               scala/Tuple2
  #538 = Class              #537          // scala/Tuple2
  #539 = Utf8               _1
  #540 = NameAndType        #539:#211     // _1:()Ljava/lang/Object;
  #541 = Methodref          #538.#540     // scala/Tuple2._1:()Ljava/lang/Object;
  #542 = Utf8               coursier/util/ModuleMatchers
  #543 = Class              #542          // coursier/util/ModuleMatchers
  #544 = Utf8               _2
  #545 = NameAndType        #544:#211     // _2:()Ljava/lang/Object;
  #546 = Methodref          #538.#545     // scala/Tuple2._2:()Ljava/lang/Object;
  #547 = Utf8               Lcoursier/core/Reconciliation$Strict$;
  #548 = NameAndType        #84:#547      // MODULE$:Lcoursier/core/Reconciliation$Strict$;
  #549 = Fieldref           #26.#548      // coursier/core/Reconciliation$Strict$.MODULE$:Lcoursier/core/Reconciliation$Strict$;
  #550 = Utf8               Lcoursier/core/Reconciliation$SemVer$;
  #551 = NameAndType        #84:#550      // MODULE$:Lcoursier/core/Reconciliation$SemVer$;
  #552 = Fieldref           #24.#551      // coursier/core/Reconciliation$SemVer$.MODULE$:Lcoursier/core/Reconciliation$SemVer$;
  #553 = Utf8               Lcoursier/core/Reconciliation$Default$;
  #554 = NameAndType        #84:#553      // MODULE$:Lcoursier/core/Reconciliation$Default$;
  #555 = Fieldref           #19.#554      // coursier/core/Reconciliation$Default$.MODULE$:Lcoursier/core/Reconciliation$Default$;
  #556 = Utf8               (Ljava/lang/Object;Ljava/lang/Object;)V
  #557 = NameAndType        #265:#556     // "<init>":(Ljava/lang/Object;Ljava/lang/Object;)V
  #558 = Methodref          #538.#557     // scala/Tuple2."<init>":(Ljava/lang/Object;Ljava/lang/Object;)V
  #559 = Utf8               m
  #560 = Utf8               Lcoursier/util/ModuleMatchers;
  #561 = Utf8               Lscala/Tuple2;
  #562 = Utf8               (ZILscala/collection/immutable/Map<Lcoursier/core/Module;Ljava/lang/String;>;Lscala/collection/immutable/Map<Ljava/lang/String;Ljava/lang/String;>;Lscala/collection/immutable/Set<Ljava/lang/String;>;Lscala/Option<Ljava/lang/String;>;Lscala/Option<Ljava/lang/Object;>;ZLscala/collection/immutable/Seq<Lscala/Tuple2<Lcoursier/params/rule/Rule;Lcoursier/params/rule/RuleResolution;>;>;Lscala/collection/immutable/Seq<Lscala/Tuple2<Lcoursier/util/ModuleMatchers;Lcoursier/core/Reconciliation;>;>;Lscala/collection/immutable/Seq<Lscala/Tuple2<Ljava/lang/String;Ljava/lang/String;>;>;Lscala/collection/immutable/Set<Lscala/Tuple2<Lcoursier/core/Organization;Lcoursier/core/ModuleName;>;>;Lscala/Option<Lcoursier/core/Activation$Os;>;Lscala/Option<Lcoursier/core/Version;>;ZZLjava/lang/String;)V
  #563 = Utf8               ()V
  #564 = NameAndType        #265:#563     // "<init>":()V
  #565 = Methodref          #4.#564       // java/lang/Object."<init>":()V
  #566 = Utf8               $init$
  #567 = Utf8               (Lscala/Product;)V
  #568 = NameAndType        #566:#567     // $init$:(Lscala/Product;)V
  #569 = InterfaceMethodref #6.#568       // scala/Product.$init$:(Lscala/Product;)V
  #570 = Utf8               Map
  #571 = Utf8               ()Lscala/collection/immutable/Map$;
  #572 = NameAndType        #570:#571     // Map:()Lscala/collection/immutable/Map$;
  #573 = Methodref          #248.#572     // scala/Predef$.Map:()Lscala/collection/immutable/Map$;
  #574 = Utf8               scala/collection/immutable/Map$
  #575 = Class              #574          // scala/collection/immutable/Map$
  #576 = Utf8               empty
  #577 = NameAndType        #576:#113     // empty:()Lscala/collection/immutable/Map;
  #578 = Methodref          #575.#577     // scala/collection/immutable/Map$.empty:()Lscala/collection/immutable/Map;
  #579 = Utf8               Set
  #580 = Utf8               ()Lscala/collection/immutable/Set$;
  #581 = NameAndType        #579:#580     // Set:()Lscala/collection/immutable/Set$;
  #582 = Methodref          #248.#581     // scala/Predef$.Set:()Lscala/collection/immutable/Set$;
  #583 = Utf8               scala/collection/immutable/Set$
  #584 = Class              #583          // scala/collection/immutable/Set$
  #585 = NameAndType        #576:#120     // empty:()Lscala/collection/immutable/Set;
  #586 = Methodref          #584.#585     // scala/collection/immutable/Set$.empty:()Lscala/collection/immutable/Set;
  #587 = Utf8               scala/None$
  #588 = Class              #587          // scala/None$
  #589 = Utf8               Lscala/None$;
  #590 = NameAndType        #84:#589      // MODULE$:Lscala/None$;
  #591 = Fieldref           #588.#590     // scala/None$.MODULE$:Lscala/None$;
  #592 = Utf8               scala/collection/immutable/Seq$
  #593 = Class              #592          // scala/collection/immutable/Seq$
  #594 = Utf8               Lscala/collection/immutable/Seq$;
  #595 = NameAndType        #84:#594      // MODULE$:Lscala/collection/immutable/Seq$;
  #596 = Fieldref           #593.#595     // scala/collection/immutable/Seq$.MODULE$:Lscala/collection/immutable/Seq$;
  #597 = Utf8               ()Lscala/collection/SeqOps;
  #598 = NameAndType        #576:#597     // empty:()Lscala/collection/SeqOps;
  #599 = Methodref          #593.#598     // scala/collection/immutable/Seq$.empty:()Lscala/collection/SeqOps;
  #600 = Utf8               coursier/core/Configuration$
  #601 = Class              #600          // coursier/core/Configuration$
  #602 = Utf8               Lcoursier/core/Configuration$;
  #603 = NameAndType        #84:#602      // MODULE$:Lcoursier/core/Configuration$;
  #604 = Fieldref           #601.#603     // coursier/core/Configuration$.MODULE$:Lcoursier/core/Configuration$;
  #605 = Utf8               defaultCompile
  #606 = NameAndType        #605:#156     // defaultCompile:()Ljava/lang/String;
  #607 = Methodref          #601.#606     // coursier/core/Configuration$.defaultCompile:()Ljava/lang/String;
  #608 = Utf8               $deserializeLambda$
  #609 = Utf8               (Ljava/lang/invoke/SerializedLambda;)Ljava/lang/Object;
  #610 = Utf8               scala/runtime/LambdaDeserialize
  #611 = Class              #610          // scala/runtime/LambdaDeserialize
  #612 = Utf8               bootstrap
  #613 = Utf8               (Ljava/lang/invoke/MethodHandles$Lookup;Ljava/lang/String;Ljava/lang/invoke/MethodType;[Ljava/lang/invoke/MethodHandle;)Ljava/lang/invoke/CallSite;
  #614 = NameAndType        #612:#613     // bootstrap:(Ljava/lang/invoke/MethodHandles$Lookup;Ljava/lang/String;Ljava/lang/invoke/MethodType;[Ljava/lang/invoke/MethodHandle;)Ljava/lang/invoke/CallSite;
  #615 = Methodref          #611.#614     // scala/runtime/LambdaDeserialize.bootstrap:(Ljava/lang/invoke/MethodHandles$Lookup;Ljava/lang/String;Ljava/lang/invoke/MethodType;[Ljava/lang/invoke/MethodHandle;)Ljava/lang/invoke/CallSite;
  #616 = MethodHandle       6:#615        // REF_invokeStatic scala/runtime/LambdaDeserialize.bootstrap:(Ljava/lang/invoke/MethodHandles$Lookup;Ljava/lang/String;Ljava/lang/invoke/MethodType;[Ljava/lang/invoke/MethodHandle;)Ljava/lang/invoke/CallSite;
  #617 = Utf8               lambdaDeserialize
  #618 = NameAndType        #617:#609     // lambdaDeserialize:(Ljava/lang/invoke/SerializedLambda;)Ljava/lang/Object;
  #619 = InvokeDynamic      #3:#618       // #3:lambdaDeserialize:(Ljava/lang/invoke/SerializedLambda;)Ljava/lang/Object;
  #620 = Utf8               Signature
  #621 = Utf8               Code
  #622 = Utf8               MethodParameters
  #623 = Utf8               LineNumberTable
  #624 = Utf8               LocalVariableTable
  #625 = Utf8               StackMapTable
  #626 = Utf8               InnerClasses
  #627 = Utf8               SourceFile
  #628 = Utf8               RuntimeVisibleAnnotations
  #629 = Utf8               BootstrapMethods
  #630 = Utf8               ScalaInlineInfo
  #631 = Utf8               ScalaSig
{
  private scala.collection.immutable.Seq<scala.Tuple2<coursier.params.rule.Rule, coursier.params.rule.RuleResolution>> actualRules;
    descriptor: Lscala/collection/immutable/Seq;
    flags: (0x0002) ACC_PRIVATE
    Signature: #44                          // Lscala/collection/immutable/Seq<Lscala/Tuple2<Lcoursier/params/rule/Rule;Lcoursier/params/rule/RuleResolution;>;>;

  private final boolean keepOptionalDependencies;
    descriptor: Z
    flags: (0x0012) ACC_PRIVATE, ACC_FINAL

  private final int maxIterations;
    descriptor: I
    flags: (0x0012) ACC_PRIVATE, ACC_FINAL

  private final scala.collection.immutable.Map<coursier.core.Module, java.lang.String> forceVersion;
    descriptor: Lscala/collection/immutable/Map;
    flags: (0x0012) ACC_PRIVATE, ACC_FINAL
    Signature: #51                          // Lscala/collection/immutable/Map<Lcoursier/core/Module;Ljava/lang/String;>;

  private final scala.collection.immutable.Map<java.lang.String, java.lang.String> forcedProperties;
    descriptor: Lscala/collection/immutable/Map;
    flags: (0x0012) ACC_PRIVATE, ACC_FINAL
    Signature: #53                          // Lscala/collection/immutable/Map<Ljava/lang/String;Ljava/lang/String;>;

  private final scala.collection.immutable.Set<java.lang.String> profiles;
    descriptor: Lscala/collection/immutable/Set;
    flags: (0x0012) ACC_PRIVATE, ACC_FINAL
    Signature: #56                          // Lscala/collection/immutable/Set<Ljava/lang/String;>;

  private final scala.Option<java.lang.String> scalaVersionOpt;
    descriptor: Lscala/Option;
    flags: (0x0012) ACC_PRIVATE, ACC_FINAL
    Signature: #59                          // Lscala/Option<Ljava/lang/String;>;

  private final scala.Option<java.lang.Object> forceScalaVersionOpt;
    descriptor: Lscala/Option;
    flags: (0x0012) ACC_PRIVATE, ACC_FINAL
    Signature: #61                          // Lscala/Option<Ljava/lang/Object;>;

  private final boolean typelevel;
    descriptor: Z
    flags: (0x0012) ACC_PRIVATE, ACC_FINAL

  private final scala.collection.immutable.Seq<scala.Tuple2<coursier.params.rule.Rule, coursier.params.rule.RuleResolution>> rules;
    descriptor: Lscala/collection/immutable/Seq;
    flags: (0x0012) ACC_PRIVATE, ACC_FINAL
    Signature: #44                          // Lscala/collection/immutable/Seq<Lscala/Tuple2<Lcoursier/params/rule/Rule;Lcoursier/params/rule/RuleResolution;>;>;

  private final scala.collection.immutable.Seq<scala.Tuple2<coursier.util.ModuleMatchers, coursier.core.Reconciliation>> reconciliation;
    descriptor: Lscala/collection/immutable/Seq;
    flags: (0x0012) ACC_PRIVATE, ACC_FINAL
    Signature: #65                          // Lscala/collection/immutable/Seq<Lscala/Tuple2<Lcoursier/util/ModuleMatchers;Lcoursier/core/Reconciliation;>;>;

  private final scala.collection.immutable.Seq<scala.Tuple2<java.lang.String, java.lang.String>> properties;
    descriptor: Lscala/collection/immutable/Seq;
    flags: (0x0012) ACC_PRIVATE, ACC_FINAL
    Signature: #67                          // Lscala/collection/immutable/Seq<Lscala/Tuple2<Ljava/lang/String;Ljava/lang/String;>;>;

  private final scala.collection.immutable.Set<scala.Tuple2<coursier.core.Organization, coursier.core.ModuleName>> exclusions;
    descriptor: Lscala/collection/immutable/Set;
    flags: (0x0012) ACC_PRIVATE, ACC_FINAL
    Signature: #69                          // Lscala/collection/immutable/Set<Lscala/Tuple2<Lcoursier/core/Organization;Lcoursier/core/ModuleName;>;>;

  private final scala.Option<coursier.core.Activation$Os> osInfoOpt;
    descriptor: Lscala/Option;
    flags: (0x0012) ACC_PRIVATE, ACC_FINAL
    Signature: #71                          // Lscala/Option<Lcoursier/core/Activation$Os;>;

  private final scala.Option<coursier.core.Version> jdkVersionOpt;
    descriptor: Lscala/Option;
    flags: (0x0012) ACC_PRIVATE, ACC_FINAL
    Signature: #73                          // Lscala/Option<Lcoursier/core/Version;>;

  private final boolean useSystemOsInfo;
    descriptor: Z
    flags: (0x0012) ACC_PRIVATE, ACC_FINAL

  private final boolean useSystemJdkVersion;
    descriptor: Z
    flags: (0x0012) ACC_PRIVATE, ACC_FINAL

  private final java.lang.String defaultConfiguration;
    descriptor: Ljava/lang/String;
    flags: (0x0012) ACC_PRIVATE, ACC_FINAL

  private volatile boolean bitmap$0;
    descriptor: Z
    flags: (0x0042) ACC_PRIVATE, ACC_VOLATILE

  public static coursier.params.ResolutionParams apply(boolean, int, scala.collection.immutable.Map<coursier.core.Module, java.lang.String>, scala.collection.immutable.Map<java.lang.String, java.lang.String>, scala.collection.immutable.Set<java.lang.String>, scala.Option<java.lang.String>, scala.Option<java.lang.Object>, boolean, scala.collection.immutable.Seq<scala.Tuple2<coursier.params.rule.Rule, coursier.params.rule.RuleResolution>>, scala.collection.immutable.Seq<scala.Tuple2<coursier.util.ModuleMatchers, coursier.core.Reconciliation>>, scala.collection.immutable.Seq<scala.Tuple2<java.lang.String, java.lang.String>>, scala.collection.immutable.Set<scala.Tuple2<coursier.core.Organization, coursier.core.ModuleName>>, scala.Option<coursier.core.Activation$Os>, scala.Option<coursier.core.Version>, boolean, boolean, java.lang.String);
    descriptor: (ZILscala/collection/immutable/Map;Lscala/collection/immutable/Map;Lscala/collection/immutable/Set;Lscala/Option;Lscala/Option;ZLscala/collection/immutable/Seq;Lscala/collection/immutable/Seq;Lscala/collection/immutable/Seq;Lscala/collection/immutable/Set;Lscala/Option;Lscala/Option;ZZLjava/lang/String;)Lcoursier/params/ResolutionParams;
    flags: (0x0009) ACC_PUBLIC, ACC_STATIC
    Code:
      stack=18, locals=17, args_size=17
         0: getstatic     #87                 // Field coursier/params/ResolutionParams$.MODULE$:Lcoursier/params/ResolutionParams$;
         3: iload_0
         4: iload_1
         5: aload_2
         6: aload_3
         7: aload         4
         9: aload         5
        11: aload         6
        13: iload         7
        15: aload         8
        17: aload         9
        19: aload         10
        21: aload         11
        23: aload         12
        25: aload         13
        27: iload         14
        29: iload         15
        31: aload         16
        33: invokevirtual #89                 // Method coursier/params/ResolutionParams$.apply:(ZILscala/collection/immutable/Map;Lscala/collection/immutable/Map;Lscala/collection/immutable/Set;Lscala/Option;Lscala/Option;ZLscala/collection/immutable/Seq;Lscala/collection/immutable/Seq;Lscala/collection/immutable/Seq;Lscala/collection/immutable/Set;Lscala/Option;Lscala/Option;ZZLjava/lang/String;)Lcoursier/params/ResolutionParams;
        36: areturn
    Signature: #81                          // (ZILscala/collection/immutable/Map<Lcoursier/core/Module;Ljava/lang/String;>;Lscala/collection/immutable/Map<Ljava/lang/String;Ljava/lang/String;>;Lscala/collection/immutable/Set<Ljava/lang/String;>;Lscala/Option<Ljava/lang/String;>;Lscala/Option<Ljava/lang/Object;>;ZLscala/collection/immutable/Seq<Lscala/Tuple2<Lcoursier/params/rule/Rule;Lcoursier/params/rule/RuleResolution;>;>;Lscala/collection/immutable/Seq<Lscala/Tuple2<Lcoursier/util/ModuleMatchers;Lcoursier/core/Reconciliation;>;>;Lscala/collection/immutable/Seq<Lscala/Tuple2<Ljava/lang/String;Ljava/lang/String;>;>;Lscala/collection/immutable/Set<Lscala/Tuple2<Lcoursier/core/Organization;Lcoursier/core/ModuleName;>;>;Lscala/Option<Lcoursier/core/Activation$Os;>;Lscala/Option<Lcoursier/core/Version;>;ZZLjava/lang/String;)Lcoursier/params/ResolutionParams;
    MethodParameters:
      Name                           Flags
      keepOptionalDependencies       final
      maxIterations                  final
      forceVersion                   final
      forcedProperties               final
      profiles                       final
      scalaVersionOpt                final
      forceScalaVersionOpt           final
      typelevel                      final
      rules                          final
      reconciliation                 final
      properties                     final
      exclusions                     final
      osInfoOpt                      final
      jdkVersionOpt                  final
      useSystemOsInfo                final
      useSystemJdkVersion            final
      defaultConfiguration           final

  public static coursier.params.ResolutionParams apply();
    descriptor: ()Lcoursier/params/ResolutionParams;
    flags: (0x0009) ACC_PUBLIC, ACC_STATIC
    Code:
      stack=1, locals=0, args_size=0
         0: getstatic     #87                 // Field coursier/params/ResolutionParams$.MODULE$:Lcoursier/params/ResolutionParams$;
         3: invokevirtual #92                 // Method coursier/params/ResolutionParams$.apply:()Lcoursier/params/ResolutionParams;
         6: areturn

  public scala.collection.Iterator<java.lang.Object> productIterator();
    descriptor: ()Lscala/collection/Iterator;
    flags: (0x0001) ACC_PUBLIC
    Code:
      stack=1, locals=1, args_size=1
         0: aload_0
         1: invokestatic  #99                 // InterfaceMethod scala/Product.productIterator$:(Lscala/Product;)Lscala/collection/Iterator;
         4: areturn
      LineNumberTable:
        line 8: 0
      LocalVariableTable:
        Start  Length  Slot  Name   Signature
            0       5     0  this   Lcoursier/params/ResolutionParams;
    Signature: #95                          // ()Lscala/collection/Iterator<Ljava/lang/Object;>;

  public scala.collection.Iterator<java.lang.String> productElementNames();
    descriptor: ()Lscala/collection/Iterator;
    flags: (0x0001) ACC_PUBLIC
    Code:
      stack=1, locals=1, args_size=1
         0: aload_0
         1: invokestatic  #106                // InterfaceMethod scala/Product.productElementNames$:(Lscala/Product;)Lscala/collection/Iterator;
         4: areturn
      LineNumberTable:
        line 8: 0
      LocalVariableTable:
        Start  Length  Slot  Name   Signature
            0       5     0  this   Lcoursier/params/ResolutionParams;
    Signature: #103                         // ()Lscala/collection/Iterator<Ljava/lang/String;>;

  public boolean keepOptionalDependencies();
    descriptor: ()Z
    flags: (0x0001) ACC_PUBLIC
    Code:
      stack=1, locals=1, args_size=1
         0: aload_0
         1: getfield      #109                // Field keepOptionalDependencies:Z
         4: ireturn
      LineNumberTable:
        line 8: 0
      LocalVariableTable:
        Start  Length  Slot  Name   Signature
            0       5     0  this   Lcoursier/params/ResolutionParams;

  public int maxIterations();
    descriptor: ()I
    flags: (0x0001) ACC_PUBLIC
    Code:
      stack=1, locals=1, args_size=1
         0: aload_0
         1: getfield      #112                // Field maxIterations:I
         4: ireturn
      LineNumberTable:
        line 8: 0
      LocalVariableTable:
        Start  Length  Slot  Name   Signature
            0       5     0  this   Lcoursier/params/ResolutionParams;

  public scala.collection.immutable.Map<coursier.core.Module, java.lang.String> forceVersion();
    descriptor: ()Lscala/collection/immutable/Map;
    flags: (0x0001) ACC_PUBLIC
    Code:
      stack=1, locals=1, args_size=1
         0: aload_0
         1: getfield      #116                // Field forceVersion:Lscala/collection/immutable/Map;
         4: areturn
      LineNumberTable:
        line 8: 0
      LocalVariableTable:
        Start  Length  Slot  Name   Signature
            0       5     0  this   Lcoursier/params/ResolutionParams;
    Signature: #114                         // ()Lscala/collection/immutable/Map<Lcoursier/core/Module;Ljava/lang/String;>;

  public scala.collection.immutable.Map<java.lang.String, java.lang.String> forcedProperties();
    descriptor: ()Lscala/collection/immutable/Map;
    flags: (0x0001) ACC_PUBLIC
    Code:
      stack=1, locals=1, args_size=1
         0: aload_0
         1: getfield      #119                // Field forcedProperties:Lscala/collection/immutable/Map;
         4: areturn
      LineNumberTable:
        line 8: 0
      LocalVariableTable:
        Start  Length  Slot  Name   Signature
            0       5     0  this   Lcoursier/params/ResolutionParams;
    Signature: #117                         // ()Lscala/collection/immutable/Map<Ljava/lang/String;Ljava/lang/String;>;

  public scala.collection.immutable.Set<java.lang.String> profiles();
    descriptor: ()Lscala/collection/immutable/Set;
    flags: (0x0001) ACC_PUBLIC
    Code:
      stack=1, locals=1, args_size=1
         0: aload_0
         1: getfield      #123                // Field profiles:Lscala/collection/immutable/Set;
         4: areturn
      LineNumberTable:
        line 8: 0
      LocalVariableTable:
        Start  Length  Slot  Name   Signature
            0       5     0  this   Lcoursier/params/ResolutionParams;
    Signature: #121                         // ()Lscala/collection/immutable/Set<Ljava/lang/String;>;

  public scala.Option<java.lang.String> scalaVersionOpt();
    descriptor: ()Lscala/Option;
    flags: (0x0001) ACC_PUBLIC
    Code:
      stack=1, locals=1, args_size=1
         0: aload_0
         1: getfield      #127                // Field scalaVersionOpt:Lscala/Option;
         4: areturn
      LineNumberTable:
        line 8: 0
      LocalVariableTable:
        Start  Length  Slot  Name   Signature
            0       5     0  this   Lcoursier/params/ResolutionParams;
    Signature: #125                         // ()Lscala/Option<Ljava/lang/String;>;

  public scala.Option<java.lang.Object> forceScalaVersionOpt();
    descriptor: ()Lscala/Option;
    flags: (0x0001) ACC_PUBLIC
    Code:
      stack=1, locals=1, args_size=1
         0: aload_0
         1: getfield      #130                // Field forceScalaVersionOpt:Lscala/Option;
         4: areturn
      LineNumberTable:
        line 8: 0
      LocalVariableTable:
        Start  Length  Slot  Name   Signature
            0       5     0  this   Lcoursier/params/ResolutionParams;
    Signature: #128                         // ()Lscala/Option<Ljava/lang/Object;>;

  public boolean typelevel();
    descriptor: ()Z
    flags: (0x0001) ACC_PUBLIC
    Code:
      stack=1, locals=1, args_size=1
         0: aload_0
         1: getfield      #132                // Field typelevel:Z
         4: ireturn
      LineNumberTable:
        line 8: 0
      LocalVariableTable:
        Start  Length  Slot  Name   Signature
            0       5     0  this   Lcoursier/params/ResolutionParams;

  public scala.collection.immutable.Seq<scala.Tuple2<coursier.params.rule.Rule, coursier.params.rule.RuleResolution>> rules();
    descriptor: ()Lscala/collection/immutable/Seq;
    flags: (0x0001) ACC_PUBLIC
    Code:
      stack=1, locals=1, args_size=1
         0: aload_0
         1: getfield      #136                // Field rules:Lscala/collection/immutable/Seq;
         4: areturn
      LineNumberTable:
        line 8: 0
      LocalVariableTable:
        Start  Length  Slot  Name   Signature
            0       5     0  this   Lcoursier/params/ResolutionParams;
    Signature: #134                         // ()Lscala/collection/immutable/Seq<Lscala/Tuple2<Lcoursier/params/rule/Rule;Lcoursier/params/rule/RuleResolution;>;>;

  public scala.collection.immutable.Seq<scala.Tuple2<coursier.util.ModuleMatchers, coursier.core.Reconciliation>> reconciliation();
    descriptor: ()Lscala/collection/immutable/Seq;
    flags: (0x0001) ACC_PUBLIC
    Code:
      stack=1, locals=1, args_size=1
         0: aload_0
         1: getfield      #139                // Field reconciliation:Lscala/collection/immutable/Seq;
         4: areturn
      LineNumberTable:
        line 8: 0
      LocalVariableTable:
        Start  Length  Slot  Name   Signature
            0       5     0  this   Lcoursier/params/ResolutionParams;
    Signature: #137                         // ()Lscala/collection/immutable/Seq<Lscala/Tuple2<Lcoursier/util/ModuleMatchers;Lcoursier/core/Reconciliation;>;>;

  public scala.collection.immutable.Seq<scala.Tuple2<java.lang.String, java.lang.String>> properties();
    descriptor: ()Lscala/collection/immutable/Seq;
    flags: (0x0001) ACC_PUBLIC
    Code:
      stack=1, locals=1, args_size=1
         0: aload_0
         1: getfield      #142                // Field properties:Lscala/collection/immutable/Seq;
         4: areturn
      LineNumberTable:
        line 8: 0
      LocalVariableTable:
        Start  Length  Slot  Name   Signature
            0       5     0  this   Lcoursier/params/ResolutionParams;
    Signature: #140                         // ()Lscala/collection/immutable/Seq<Lscala/Tuple2<Ljava/lang/String;Ljava/lang/String;>;>;

  public scala.collection.immutable.Set<scala.Tuple2<coursier.core.Organization, coursier.core.ModuleName>> exclusions();
    descriptor: ()Lscala/collection/immutable/Set;
    flags: (0x0001) ACC_PUBLIC
    Code:
      stack=1, locals=1, args_size=1
         0: aload_0
         1: getfield      #145                // Field exclusions:Lscala/collection/immutable/Set;
         4: areturn
      LineNumberTable:
        line 8: 0
      LocalVariableTable:
        Start  Length  Slot  Name   Signature
            0       5     0  this   Lcoursier/params/ResolutionParams;
    Signature: #143                         // ()Lscala/collection/immutable/Set<Lscala/Tuple2<Lcoursier/core/Organization;Lcoursier/core/ModuleName;>;>;

  public scala.Option<coursier.core.Activation$Os> osInfoOpt();
    descriptor: ()Lscala/Option;
    flags: (0x0001) ACC_PUBLIC
    Code:
      stack=1, locals=1, args_size=1
         0: aload_0
         1: getfield      #148                // Field osInfoOpt:Lscala/Option;
         4: areturn
      LineNumberTable:
        line 8: 0
      LocalVariableTable:
        Start  Length  Slot  Name   Signature
            0       5     0  this   Lcoursier/params/ResolutionParams;
    Signature: #146                         // ()Lscala/Option<Lcoursier/core/Activation$Os;>;

  public scala.Option<coursier.core.Version> jdkVersionOpt();
    descriptor: ()Lscala/Option;
    flags: (0x0001) ACC_PUBLIC
    Code:
      stack=1, locals=1, args_size=1
         0: aload_0
         1: getfield      #151                // Field jdkVersionOpt:Lscala/Option;
         4: areturn
      LineNumberTable:
        line 8: 0
      LocalVariableTable:
        Start  Length  Slot  Name   Signature
            0       5     0  this   Lcoursier/params/ResolutionParams;
    Signature: #149                         // ()Lscala/Option<Lcoursier/core/Version;>;

  public boolean useSystemOsInfo();
    descriptor: ()Z
    flags: (0x0001) ACC_PUBLIC
    Code:
      stack=1, locals=1, args_size=1
         0: aload_0
         1: getfield      #153                // Field useSystemOsInfo:Z
         4: ireturn
      LineNumberTable:
        line 8: 0
      LocalVariableTable:
        Start  Length  Slot  Name   Signature
            0       5     0  this   Lcoursier/params/ResolutionParams;

  public boolean useSystemJdkVersion();
    descriptor: ()Z
    flags: (0x0001) ACC_PUBLIC
    Code:
      stack=1, locals=1, args_size=1
         0: aload_0
         1: getfield      #155                // Field useSystemJdkVersion:Z
         4: ireturn
      LineNumberTable:
        line 8: 0
      LocalVariableTable:
        Start  Length  Slot  Name   Signature
            0       5     0  this   Lcoursier/params/ResolutionParams;

  public java.lang.String defaultConfiguration();
    descriptor: ()Ljava/lang/String;
    flags: (0x0001) ACC_PUBLIC
    Code:
      stack=1, locals=1, args_size=1
         0: aload_0
         1: getfield      #158                // Field defaultConfiguration:Ljava/lang/String;
         4: areturn
      LineNumberTable:
        line 8: 0
      LocalVariableTable:
        Start  Length  Slot  Name   Signature
            0       5     0  this   Lcoursier/params/ResolutionParams;

  public coursier.params.ResolutionParams addForceVersion(scala.collection.immutable.Seq<scala.Tuple2<coursier.core.Module, java.lang.String>>);
    descriptor: (Lscala/collection/immutable/Seq;)Lcoursier/params/ResolutionParams;
    flags: (0x0001) ACC_PUBLIC
    Code:
      stack=3, locals=2, args_size=2
         0: aload_0
         1: aload_0
         2: invokevirtual #164                // Method forceVersion:()Lscala/collection/immutable/Map;
         5: aload_1
         6: invokeinterface #170,  2          // InterfaceMethod scala/collection/immutable/Map.$plus$plus:(Lscala/collection/IterableOnce;)Lscala/collection/IterableOps;
        11: checkcast     #166                // class scala/collection/immutable/Map
        14: invokevirtual #174                // Method withForceVersion:(Lscala/collection/immutable/Map;)Lcoursier/params/ResolutionParams;
        17: areturn
      LineNumberTable:
        line 29: 0
      LocalVariableTable:
        Start  Length  Slot  Name   Signature
            0      18     0  this   Lcoursier/params/ResolutionParams;
            0      18     1    fv   Lscala/collection/immutable/Seq;
    Signature: #161                         // (Lscala/collection/immutable/Seq<Lscala/Tuple2<Lcoursier/core/Module;Ljava/lang/String;>;>;)Lcoursier/params/ResolutionParams;
    MethodParameters:
      Name                           Flags
      fv                             final

  public boolean doForceScalaVersion();
    descriptor: ()Z
    flags: (0x0001) ACC_PUBLIC
    Code:
      stack=2, locals=1, args_size=1
         0: aload_0
         1: invokevirtual #177                // Method forceScalaVersionOpt:()Lscala/Option;
         4: aload_0
         5: invokedynamic #195,  0            // InvokeDynamic #0:apply$mcZ$sp:(Lcoursier/params/ResolutionParams;)Lscala/runtime/java8/JFunction0$mcZ$sp;
        10: invokevirtual #201                // Method scala/Option.getOrElse:(Lscala/Function0;)Ljava/lang/Object;
        13: invokestatic  #207                // Method scala/runtime/BoxesRunTime.unboxToBoolean:(Ljava/lang/Object;)Z
        16: ireturn
      LineNumberTable:
        line 32: 0
        line 33: 4
      LocalVariableTable:
        Start  Length  Slot  Name   Signature
            0      17     0  this   Lcoursier/params/ResolutionParams;

  public java.lang.String selectedScalaVersion();
    descriptor: ()Ljava/lang/String;
    flags: (0x0001) ACC_PUBLIC
    Code:
      stack=2, locals=1, args_size=1
         0: aload_0
         1: invokevirtual #210                // Method scalaVersionOpt:()Lscala/Option;
         4: invokedynamic #221,  0            // InvokeDynamic #1:apply:()Lscala/Function0;
         9: invokevirtual #201                // Method scala/Option.getOrElse:(Lscala/Function0;)Ljava/lang/Object;
        12: checkcast     #223                // class java/lang/String
        15: areturn
      LineNumberTable:
        line 36: 0
        line 37: 4
      LocalVariableTable:
        Start  Length  Slot  Name   Signature
            0      16     0  this   Lcoursier/params/ResolutionParams;

  public coursier.params.ResolutionParams addProfile(scala.collection.immutable.Seq<java.lang.String>);
    descriptor: (Lscala/collection/immutable/Seq;)Lcoursier/params/ResolutionParams;
    flags: (0x0001) ACC_PUBLIC
    Code:
      stack=3, locals=2, args_size=2
         0: aload_0
         1: aload_0
         2: invokevirtual #228                // Method profiles:()Lscala/collection/immutable/Set;
         5: aload_1
         6: invokeinterface #233,  2          // InterfaceMethod scala/collection/immutable/Set.$plus$plus:(Lscala/collection/IterableOnce;)Lscala/collection/SetOps;
        11: checkcast     #230                // class scala/collection/immutable/Set
        14: invokevirtual #237                // Method withProfiles:(Lscala/collection/immutable/Set;)Lcoursier/params/ResolutionParams;
        17: areturn
      LineNumberTable:
        line 41: 0
      LocalVariableTable:
        Start  Length  Slot  Name   Signature
            0      18     0  this   Lcoursier/params/ResolutionParams;
            0      18     1 profile   Lscala/collection/immutable/Seq;
    Signature: #225                         // (Lscala/collection/immutable/Seq<Ljava/lang/String;>;)Lcoursier/params/ResolutionParams;
    MethodParameters:
      Name                           Flags
      profile                        final

  public final coursier.params.ResolutionParams addRule(coursier.params.rule.Rule, coursier.params.rule.RuleResolution);
    descriptor: (Lcoursier/params/rule/Rule;Lcoursier/params/rule/RuleResolution;)Lcoursier/params/ResolutionParams;
    flags: (0x0011) ACC_PUBLIC, ACC_FINAL
    Code:
      stack=6, locals=3, args_size=3
         0: aload_0
         1: new           #243                // class scala/collection/immutable/$colon$colon
         4: dup
         5: getstatic     #246                // Field scala/Predef$ArrowAssoc$.MODULE$:Lscala/Predef$ArrowAssoc$;
         8: getstatic     #251                // Field scala/Predef$.MODULE$:Lscala/Predef$;
        11: aload_1
        12: invokevirtual #255                // Method scala/Predef$.ArrowAssoc:(Ljava/lang/Object;)Ljava/lang/Object;
        15: aload_2
        16: invokevirtual #259                // Method scala/Predef$ArrowAssoc$.$minus$greater$extension:(Ljava/lang/Object;Ljava/lang/Object;)Lscala/Tuple2;
        19: getstatic     #264                // Field scala/collection/immutable/Nil$.MODULE$:Lscala/collection/immutable/Nil$;
        22: invokespecial #268                // Method scala/collection/immutable/$colon$colon."<init>":(Ljava/lang/Object;Lscala/collection/immutable/List;)V
        25: checkcast     #270                // class scala/collection/immutable/Seq
        28: invokevirtual #273                // Method withRules:(Lscala/collection/immutable/Seq;)Lcoursier/params/ResolutionParams;
        31: areturn
      LineNumberTable:
        line 44: 0
      LocalVariableTable:
        Start  Length  Slot  Name   Signature
            0      32     0  this   Lcoursier/params/ResolutionParams;
            0      32     1  rule   Lcoursier/params/rule/Rule;
            0      32     2 resolution   Lcoursier/params/rule/RuleResolution;
    MethodParameters:
      Name                           Flags
      rule                           final
      resolution                     final

  public final coursier.params.ResolutionParams addRule(coursier.params.rule.Rule);
    descriptor: (Lcoursier/params/rule/Rule;)Lcoursier/params/ResolutionParams;
    flags: (0x0011) ACC_PUBLIC, ACC_FINAL
    Code:
      stack=3, locals=2, args_size=2
         0: aload_0
         1: aload_1
         2: getstatic     #279                // Field coursier/params/rule/RuleResolution$TryResolve$.MODULE$:Lcoursier/params/rule/RuleResolution$TryResolve$;
         5: invokevirtual #281                // Method addRule:(Lcoursier/params/rule/Rule;Lcoursier/params/rule/RuleResolution;)Lcoursier/params/ResolutionParams;
         8: areturn
      LineNumberTable:
        line 46: 0
      LocalVariableTable:
        Start  Length  Slot  Name   Signature
            0       9     0  this   Lcoursier/params/ResolutionParams;
            0       9     1  rule   Lcoursier/params/rule/Rule;
    MethodParameters:
      Name                           Flags
      rule                           final

  public coursier.params.ResolutionParams addProperties(scala.collection.immutable.Seq<scala.Tuple2<java.lang.String, java.lang.String>>);
    descriptor: (Lscala/collection/immutable/Seq;)Lcoursier/params/ResolutionParams;
    flags: (0x0001) ACC_PUBLIC
    Code:
      stack=3, locals=2, args_size=2
         0: aload_0
         1: aload_0
         2: invokevirtual #286                // Method properties:()Lscala/collection/immutable/Seq;
         5: aload_1
         6: invokeinterface #289,  2          // InterfaceMethod scala/collection/immutable/Seq.$plus$plus:(Lscala/collection/IterableOnce;)Ljava/lang/Object;
        11: checkcast     #270                // class scala/collection/immutable/Seq
        14: invokevirtual #292                // Method withProperties:(Lscala/collection/immutable/Seq;)Lcoursier/params/ResolutionParams;
        17: areturn
      LineNumberTable:
        line 49: 0
      LocalVariableTable:
        Start  Length  Slot  Name   Signature
            0      18     0  this   Lcoursier/params/ResolutionParams;
            0      18     1 props   Lscala/collection/immutable/Seq;
    Signature: #283                         // (Lscala/collection/immutable/Seq<Lscala/Tuple2<Ljava/lang/String;Ljava/lang/String;>;>;)Lcoursier/params/ResolutionParams;
    MethodParameters:
      Name                           Flags
      props                          final

  public coursier.params.ResolutionParams addForcedProperties(scala.collection.immutable.Seq<scala.Tuple2<java.lang.String, java.lang.String>>);
    descriptor: (Lscala/collection/immutable/Seq;)Lcoursier/params/ResolutionParams;
    flags: (0x0001) ACC_PUBLIC
    Code:
      stack=3, locals=2, args_size=2
         0: aload_0
         1: aload_0
         2: invokevirtual #295                // Method forcedProperties:()Lscala/collection/immutable/Map;
         5: aload_1
         6: invokeinterface #170,  2          // InterfaceMethod scala/collection/immutable/Map.$plus$plus:(Lscala/collection/IterableOnce;)Lscala/collection/IterableOps;
        11: checkcast     #166                // class scala/collection/immutable/Map
        14: invokevirtual #298                // Method withForcedProperties:(Lscala/collection/immutable/Map;)Lcoursier/params/ResolutionParams;
        17: areturn
      LineNumberTable:
        line 51: 0
      LocalVariableTable:
        Start  Length  Slot  Name   Signature
            0      18     0  this   Lcoursier/params/ResolutionParams;
            0      18     1 props   Lscala/collection/immutable/Seq;
    Signature: #283                         // (Lscala/collection/immutable/Seq<Lscala/Tuple2<Ljava/lang/String;Ljava/lang/String;>;>;)Lcoursier/params/ResolutionParams;
    MethodParameters:
      Name                           Flags
      props                          final

  public coursier.params.ResolutionParams withScalaVersion(java.lang.String);
    descriptor: (Ljava/lang/String;)Lcoursier/params/ResolutionParams;
    flags: (0x0001) ACC_PUBLIC
    Code:
      stack=3, locals=2, args_size=2
         0: aload_0
         1: getstatic     #306                // Field scala/Option$.MODULE$:Lscala/Option$;
         4: aload_1
         5: invokevirtual #309                // Method scala/Option$.apply:(Ljava/lang/Object;)Lscala/Option;
         8: invokevirtual #313                // Method withScalaVersionOpt:(Lscala/Option;)Lcoursier/params/ResolutionParams;
        11: areturn
      LineNumberTable:
        line 54: 0
      LocalVariableTable:
        Start  Length  Slot  Name   Signature
            0      12     0  this   Lcoursier/params/ResolutionParams;
            0      12     1 scalaVersion   Ljava/lang/String;
    MethodParameters:
      Name                           Flags
      scalaVersion                   final

  public coursier.params.ResolutionParams withForceScalaVersion(boolean);
    descriptor: (Z)Lcoursier/params/ResolutionParams;
    flags: (0x0001) ACC_PUBLIC
    Code:
      stack=3, locals=2, args_size=2
         0: aload_0
         1: getstatic     #306                // Field scala/Option$.MODULE$:Lscala/Option$;
         4: iload_1
         5: invokestatic  #320                // Method scala/runtime/BoxesRunTime.boxToBoolean:(Z)Ljava/lang/Boolean;
         8: invokevirtual #309                // Method scala/Option$.apply:(Ljava/lang/Object;)Lscala/Option;
        11: invokevirtual #323                // Method withForceScalaVersionOpt:(Lscala/Option;)Lcoursier/params/ResolutionParams;
        14: areturn
      LineNumberTable:
        line 56: 0
      LocalVariableTable:
        Start  Length  Slot  Name   Signature
            0      15     0  this   Lcoursier/params/ResolutionParams;
            0      15     1 forceScalaVersion   Z
    MethodParameters:
      Name                           Flags
      forceScalaVersion              final

  public coursier.params.ResolutionParams withOsInfo(coursier.core.Activation$Os);
    descriptor: (Lcoursier/core/Activation$Os;)Lcoursier/params/ResolutionParams;
    flags: (0x0001) ACC_PUBLIC
    Code:
      stack=4, locals=2, args_size=2
         0: aload_0
         1: new           #328                // class scala/Some
         4: dup
         5: aload_1
         6: invokespecial #331                // Method scala/Some."<init>":(Ljava/lang/Object;)V
         9: invokevirtual #334                // Method withOsInfoOpt:(Lscala/Option;)Lcoursier/params/ResolutionParams;
        12: areturn
      LineNumberTable:
        line 58: 0
      LocalVariableTable:
        Start  Length  Slot  Name   Signature
            0      13     0  this   Lcoursier/params/ResolutionParams;
            0      13     1 osInfo   Lcoursier/core/Activation$Os;
    MethodParameters:
      Name                           Flags
      osInfo                         final

  public coursier.params.ResolutionParams withJdkVersion(java.lang.String);
    descriptor: (Ljava/lang/String;)Lcoursier/params/ResolutionParams;
    flags: (0x0001) ACC_PUBLIC
    Code:
      stack=5, locals=2, args_size=2
         0: aload_0
         1: new           #328                // class scala/Some
         4: dup
         5: getstatic     #342                // Field coursier/core/Version$.MODULE$:Lcoursier/core/Version$;
         8: aload_1
         9: invokevirtual #345                // Method coursier/core/Version$.apply:(Ljava/lang/String;)Lcoursier/core/Version;
        12: invokespecial #331                // Method scala/Some."<init>":(Ljava/lang/Object;)V
        15: invokevirtual #348                // Method withJdkVersionOpt:(Lscala/Option;)Lcoursier/params/ResolutionParams;
        18: areturn
      LineNumberTable:
        line 60: 0
      LocalVariableTable:
        Start  Length  Slot  Name   Signature
            0      19     0  this   Lcoursier/params/ResolutionParams;
            0      19     1 version   Ljava/lang/String;
    MethodParameters:
      Name                           Flags
      version                        final

  public coursier.params.ResolutionParams withJdkVersion(coursier.core.Version);
    descriptor: (Lcoursier/core/Version;)Lcoursier/params/ResolutionParams;
    flags: (0x0001) ACC_PUBLIC
    Code:
      stack=4, locals=2, args_size=2
         0: aload_0
         1: new           #328                // class scala/Some
         4: dup
         5: aload_1
         6: invokespecial #331                // Method scala/Some."<init>":(Ljava/lang/Object;)V
         9: invokevirtual #348                // Method withJdkVersionOpt:(Lscala/Option;)Lcoursier/params/ResolutionParams;
        12: areturn
      LineNumberTable:
        line 62: 0
      LocalVariableTable:
        Start  Length  Slot  Name   Signature
            0      13     0  this   Lcoursier/params/ResolutionParams;
            0      13     1 version   Lcoursier/core/Version;
    MethodParameters:
      Name                           Flags
      version                        final

  public coursier.params.ResolutionParams addReconciliation(scala.collection.immutable.Seq<scala.Tuple2<coursier.util.ModuleMatchers, coursier.core.Reconciliation>>);
    descriptor: (Lscala/collection/immutable/Seq;)Lcoursier/params/ResolutionParams;
    flags: (0x0001) ACC_PUBLIC
    Code:
      stack=3, locals=2, args_size=2
         0: aload_0
         1: aload_0
         2: invokevirtual #354                // Method reconciliation:()Lscala/collection/immutable/Seq;
         5: aload_1
         6: invokeinterface #289,  2          // InterfaceMethod scala/collection/immutable/Seq.$plus$plus:(Lscala/collection/IterableOnce;)Ljava/lang/Object;
        11: checkcast     #270                // class scala/collection/immutable/Seq
        14: invokevirtual #357                // Method withReconciliation:(Lscala/collection/immutable/Seq;)Lcoursier/params/ResolutionParams;
        17: areturn
      LineNumberTable:
        line 65: 0
      LocalVariableTable:
        Start  Length  Slot  Name   Signature
            0      18     0  this   Lcoursier/params/ResolutionParams;
            0      18     1 reconciliation   Lscala/collection/immutable/Seq;
    Signature: #352                         // (Lscala/collection/immutable/Seq<Lscala/Tuple2<Lcoursier/util/ModuleMatchers;Lcoursier/core/Reconciliation;>;>;)Lcoursier/params/ResolutionParams;
    MethodParameters:
      Name                           Flags
      reconciliation                 final

  public coursier.params.ResolutionParams addExclusions(scala.collection.immutable.Seq<scala.Tuple2<coursier.core.Organization, coursier.core.ModuleName>>);
    descriptor: (Lscala/collection/immutable/Seq;)Lcoursier/params/ResolutionParams;
    flags: (0x0001) ACC_PUBLIC
    Code:
      stack=3, locals=2, args_size=2
         0: aload_0
         1: aload_0
         2: invokevirtual #361                // Method exclusions:()Lscala/collection/immutable/Set;
         5: aload_1
         6: invokeinterface #233,  2          // InterfaceMethod scala/collection/immutable/Set.$plus$plus:(Lscala/collection/IterableOnce;)Lscala/collection/SetOps;
        11: checkcast     #230                // class scala/collection/immutable/Set
        14: invokevirtual #364                // Method withExclusions:(Lscala/collection/immutable/Set;)Lcoursier/params/ResolutionParams;
        17: areturn
      LineNumberTable:
        line 67: 0
      LocalVariableTable:
        Start  Length  Slot  Name   Signature
            0      18     0  this   Lcoursier/params/ResolutionParams;
            0      18     1 exclusions   Lscala/collection/immutable/Seq;
    Signature: #359                         // (Lscala/collection/immutable/Seq<Lscala/Tuple2<Lcoursier/core/Organization;Lcoursier/core/ModuleName;>;>;)Lcoursier/params/ResolutionParams;
    MethodParameters:
      Name                           Flags
      exclusions                     final

  public scala.collection.immutable.Seq<scala.Tuple2<coursier.util.ModuleMatchers, coursier.core.Reconciliation>> actualReconciliation();
    descriptor: ()Lscala/collection/immutable/Seq;
    flags: (0x0001) ACC_PUBLIC
    Code:
      stack=2, locals=1, args_size=1
         0: aload_0
         1: invokevirtual #354                // Method reconciliation:()Lscala/collection/immutable/Seq;
         4: invokedynamic #375,  0            // InvokeDynamic #2:apply:()Lscala/Function1;
         9: invokeinterface #379,  2          // InterfaceMethod scala/collection/immutable/Seq.map:(Lscala/Function1;)Ljava/lang/Object;
        14: checkcast     #270                // class scala/collection/immutable/Seq
        17: areturn
      LineNumberTable:
        line 70: 0
      LocalVariableTable:
        Start  Length  Slot  Name   Signature
            0      18     0  this   Lcoursier/params/ResolutionParams;
    Signature: #137                         // ()Lscala/collection/immutable/Seq<Lscala/Tuple2<Lcoursier/util/ModuleMatchers;Lcoursier/core/Reconciliation;>;>;

  private scala.collection.immutable.Seq<scala.Tuple2<coursier.params.rule.Rule, coursier.params.rule.RuleResolution>> actualRules$lzycompute();
    descriptor: ()Lscala/collection/immutable/Seq;
    flags: (0x0002) ACC_PRIVATE
    Code:
      stack=5, locals=3, args_size=1
         0: aload_0
         1: dup
         2: astore_1
         3: monitorenter
         4: aload_0
         5: getfield      #382                // Field bitmap$0:Z
         8: ifne          54
        11: aload_0
        12: aload_0
        13: invokevirtual #354                // Method reconciliation:()Lscala/collection/immutable/Seq;
        16: new           #28                 // class coursier/params/ResolutionParams$$anonfun$1
        19: dup
        20: aconst_null
        21: invokespecial #385                // Method coursier/params/ResolutionParams$$anonfun$1."<init>":(Lcoursier/params/ResolutionParams;)V
        24: invokeinterface #389,  2          // InterfaceMethod scala/collection/immutable/Seq.collect:(Lscala/PartialFunction;)Ljava/lang/Object;
        29: checkcast     #270                // class scala/collection/immutable/Seq
        32: astore_2
        33: aload_0
        34: invokevirtual #391                // Method rules:()Lscala/collection/immutable/Seq;
        37: aload_2
        38: invokeinterface #289,  2          // InterfaceMethod scala/collection/immutable/Seq.$plus$plus:(Lscala/collection/IterableOnce;)Ljava/lang/Object;
        43: checkcast     #270                // class scala/collection/immutable/Seq
        46: putfield      #393                // Field actualRules:Lscala/collection/immutable/Seq;
        49: aload_0
        50: iconst_1
        51: putfield      #382                // Field bitmap$0:Z
        54: aload_1
        55: monitorexit
        56: goto          62
        59: aload_1
        60: monitorexit
        61: athrow
        62: aload_0
        63: getfield      #393                // Field actualRules:Lscala/collection/immutable/Seq;
        66: areturn
      Exception table:
         from    to  target type
             4    54    59   any
      StackMapTable: number_of_entries = 3
        frame_type = 252 /* append */
          offset_delta = 54
          locals = [ class coursier/params/ResolutionParams ]
        frame_type = 68 /* same_locals_1_stack_item */
          stack = [ class java/lang/Throwable ]
        frame_type = 2 /* same */
      LineNumberTable:
        line 75: 0
        line 77: 12
        line 84: 33
        line 75: 46
      LocalVariableTable:
        Start  Length  Slot  Name   Signature
           33      13     2 fromReconciliation   Lscala/collection/immutable/Seq;
            0      67     0  this   Lcoursier/params/ResolutionParams;
    Signature: #134                         // ()Lscala/collection/immutable/Seq<Lscala/Tuple2<Lcoursier/params/rule/Rule;Lcoursier/params/rule/RuleResolution;>;>;

  public scala.collection.immutable.Seq<scala.Tuple2<coursier.params.rule.Rule, coursier.params.rule.RuleResolution>> actualRules();
    descriptor: ()Lscala/collection/immutable/Seq;
    flags: (0x0001) ACC_PUBLIC
    Code:
      stack=1, locals=1, args_size=1
         0: aload_0
         1: getfield      #382                // Field bitmap$0:Z
         4: ifne          14
         7: aload_0
         8: invokespecial #398                // Method actualRules$lzycompute:()Lscala/collection/immutable/Seq;
        11: goto          18
        14: aload_0
        15: getfield      #393                // Field actualRules:Lscala/collection/immutable/Seq;
        18: areturn
      StackMapTable: number_of_entries = 2
        frame_type = 14 /* same */
        frame_type = 67 /* same_locals_1_stack_item */
          stack = [ class scala/collection/immutable/Seq ]
      LineNumberTable:
        line 75: 0
      LocalVariableTable:
        Start  Length  Slot  Name   Signature
            0      19     0  this   Lcoursier/params/ResolutionParams;
    Signature: #134                         // ()Lscala/collection/immutable/Seq<Lscala/Tuple2<Lcoursier/params/rule/Rule;Lcoursier/params/rule/RuleResolution;>;>;

  public coursier.params.ResolutionParams withKeepOptionalDependencies(boolean);
    descriptor: (Z)Lcoursier/params/ResolutionParams;
    flags: (0x0001) ACC_PUBLIC
    Code:
      stack=19, locals=2, args_size=2
         0: new           #2                  // class coursier/params/ResolutionParams
         3: dup
         4: iload_1
         5: aload_0
         6: invokevirtual #401                // Method maxIterations:()I
         9: aload_0
        10: invokevirtual #164                // Method forceVersion:()Lscala/collection/immutable/Map;
        13: aload_0
        14: invokevirtual #295                // Method forcedProperties:()Lscala/collection/immutable/Map;
        17: aload_0
        18: invokevirtual #228                // Method profiles:()Lscala/collection/immutable/Set;
        21: aload_0
        22: invokevirtual #210                // Method scalaVersionOpt:()Lscala/Option;
        25: aload_0
        26: invokevirtual #177                // Method forceScalaVersionOpt:()Lscala/Option;
        29: aload_0
        30: invokevirtual #403                // Method typelevel:()Z
        33: aload_0
        34: invokevirtual #391                // Method rules:()Lscala/collection/immutable/Seq;
        37: aload_0
        38: invokevirtual #354                // Method reconciliation:()Lscala/collection/immutable/Seq;
        41: aload_0
        42: invokevirtual #286                // Method properties:()Lscala/collection/immutable/Seq;
        45: aload_0
        46: invokevirtual #361                // Method exclusions:()Lscala/collection/immutable/Set;
        49: aload_0
        50: invokevirtual #405                // Method osInfoOpt:()Lscala/Option;
        53: aload_0
        54: invokevirtual #407                // Method jdkVersionOpt:()Lscala/Option;
        57: aload_0
        58: invokevirtual #409                // Method useSystemOsInfo:()Z
        61: aload_0
        62: invokevirtual #411                // Method useSystemJdkVersion:()Z
        65: aload_0
        66: invokevirtual #413                // Method defaultConfiguration:()Ljava/lang/String;
        69: invokespecial #416                // Method "<init>":(ZILscala/collection/immutable/Map;Lscala/collection/immutable/Map;Lscala/collection/immutable/Set;Lscala/Option;Lscala/Option;ZLscala/collection/immutable/Seq;Lscala/collection/immutable/Seq;Lscala/collection/immutable/Seq;Lscala/collection/immutable/Set;Lscala/Option;Lscala/Option;ZZLjava/lang/String;)V
        72: areturn
      LineNumberTable:
        line 8: 0
      LocalVariableTable:
        Start  Length  Slot  Name   Signature
            0      73     0  this   Lcoursier/params/ResolutionParams;
            0      73     1 keepOptionalDependencies   Z
    MethodParameters:
      Name                           Flags
      keepOptionalDependencies       final

  public coursier.params.ResolutionParams withMaxIterations(int);
    descriptor: (I)Lcoursier/params/ResolutionParams;
    flags: (0x0001) ACC_PUBLIC
    Code:
      stack=19, locals=2, args_size=2
         0: new           #2                  // class coursier/params/ResolutionParams
         3: dup
         4: aload_0
         5: invokevirtual #420                // Method keepOptionalDependencies:()Z
         8: iload_1
         9: aload_0
        10: invokevirtual #164                // Method forceVersion:()Lscala/collection/immutable/Map;
        13: aload_0
        14: invokevirtual #295                // Method forcedProperties:()Lscala/collection/immutable/Map;
        17: aload_0
        18: invokevirtual #228                // Method profiles:()Lscala/collection/immutable/Set;
        21: aload_0
        22: invokevirtual #210                // Method scalaVersionOpt:()Lscala/Option;
        25: aload_0
        26: invokevirtual #177                // Method forceScalaVersionOpt:()Lscala/Option;
        29: aload_0
        30: invokevirtual #403                // Method typelevel:()Z
        33: aload_0
        34: invokevirtual #391                // Method rules:()Lscala/collection/immutable/Seq;
        37: aload_0
        38: invokevirtual #354                // Method reconciliation:()Lscala/collection/immutable/Seq;
        41: aload_0
        42: invokevirtual #286                // Method properties:()Lscala/collection/immutable/Seq;
        45: aload_0
        46: invokevirtual #361                // Method exclusions:()Lscala/collection/immutable/Set;
        49: aload_0
        50: invokevirtual #405                // Method osInfoOpt:()Lscala/Option;
        53: aload_0
        54: invokevirtual #407                // Method jdkVersionOpt:()Lscala/Option;
        57: aload_0
        58: invokevirtual #409                // Method useSystemOsInfo:()Z
        61: aload_0
        62: invokevirtual #411                // Method useSystemJdkVersion:()Z
        65: aload_0
        66: invokevirtual #413                // Method defaultConfiguration:()Ljava/lang/String;
        69: invokespecial #416                // Method "<init>":(ZILscala/collection/immutable/Map;Lscala/collection/immutable/Map;Lscala/collection/immutable/Set;Lscala/Option;Lscala/Option;ZLscala/collection/immutable/Seq;Lscala/collection/immutable/Seq;Lscala/collection/immutable/Seq;Lscala/collection/immutable/Set;Lscala/Option;Lscala/Option;ZZLjava/lang/String;)V
        72: areturn
      LineNumberTable:
        line 8: 0
      LocalVariableTable:
        Start  Length  Slot  Name   Signature
            0      73     0  this   Lcoursier/params/ResolutionParams;
            0      73     1 maxIterations   I
    MethodParameters:
      Name                           Flags
      maxIterations                  final

  public coursier.params.ResolutionParams withForceVersion(scala.collection.immutable.Map<coursier.core.Module, java.lang.String>);
    descriptor: (Lscala/collection/immutable/Map;)Lcoursier/params/ResolutionParams;
    flags: (0x0001) ACC_PUBLIC
    Code:
      stack=19, locals=2, args_size=2
         0: new           #2                  // class coursier/params/ResolutionParams
         3: dup
         4: aload_0
         5: invokevirtual #420                // Method keepOptionalDependencies:()Z
         8: aload_0
         9: invokevirtual #401                // Method maxIterations:()I
        12: aload_1
        13: aload_0
        14: invokevirtual #295                // Method forcedProperties:()Lscala/collection/immutable/Map;
        17: aload_0
        18: invokevirtual #228                // Method profiles:()Lscala/collection/immutable/Set;
        21: aload_0
        22: invokevirtual #210                // Method scalaVersionOpt:()Lscala/Option;
        25: aload_0
        26: invokevirtual #177                // Method forceScalaVersionOpt:()Lscala/Option;
        29: aload_0
        30: invokevirtual #403                // Method typelevel:()Z
        33: aload_0
        34: invokevirtual #391                // Method rules:()Lscala/collection/immutable/Seq;
        37: aload_0
        38: invokevirtual #354                // Method reconciliation:()Lscala/collection/immutable/Seq;
        41: aload_0
        42: invokevirtual #286                // Method properties:()Lscala/collection/immutable/Seq;
        45: aload_0
        46: invokevirtual #361                // Method exclusions:()Lscala/collection/immutable/Set;
        49: aload_0
        50: invokevirtual #405                // Method osInfoOpt:()Lscala/Option;
        53: aload_0
        54: invokevirtual #407                // Method jdkVersionOpt:()Lscala/Option;
        57: aload_0
        58: invokevirtual #409                // Method useSystemOsInfo:()Z
        61: aload_0
        62: invokevirtual #411                // Method useSystemJdkVersion:()Z
        65: aload_0
        66: invokevirtual #413                // Method defaultConfiguration:()Ljava/lang/String;
        69: invokespecial #416                // Method "<init>":(ZILscala/collection/immutable/Map;Lscala/collection/immutable/Map;Lscala/collection/immutable/Set;Lscala/Option;Lscala/Option;ZLscala/collection/immutable/Seq;Lscala/collection/immutable/Seq;Lscala/collection/immutable/Seq;Lscala/collection/immutable/Set;Lscala/Option;Lscala/Option;ZZLjava/lang/String;)V
        72: areturn
      LineNumberTable:
        line 8: 0
      LocalVariableTable:
        Start  Length  Slot  Name   Signature
            0      73     0  this   Lcoursier/params/ResolutionParams;
            0      73     1 forceVersion   Lscala/collection/immutable/Map;
    Signature: #421                         // (Lscala/collection/immutable/Map<Lcoursier/core/Module;Ljava/lang/String;>;)Lcoursier/params/ResolutionParams;
    MethodParameters:
      Name                           Flags
      forceVersion                   final

  public coursier.params.ResolutionParams withForcedProperties(scala.collection.immutable.Map<java.lang.String, java.lang.String>);
    descriptor: (Lscala/collection/immutable/Map;)Lcoursier/params/ResolutionParams;
    flags: (0x0001) ACC_PUBLIC
    Code:
      stack=19, locals=2, args_size=2
         0: new           #2                  // class coursier/params/ResolutionParams
         3: dup
         4: aload_0
         5: invokevirtual #420                // Method keepOptionalDependencies:()Z
         8: aload_0
         9: invokevirtual #401                // Method maxIterations:()I
        12: aload_0
        13: invokevirtual #164                // Method forceVersion:()Lscala/collection/immutable/Map;
        16: aload_1
        17: aload_0
        18: invokevirtual #228                // Method profiles:()Lscala/collection/immutable/Set;
        21: aload_0
        22: invokevirtual #210                // Method scalaVersionOpt:()Lscala/Option;
        25: aload_0
        26: invokevirtual #177                // Method forceScalaVersionOpt:()Lscala/Option;
        29: aload_0
        30: invokevirtual #403                // Method typelevel:()Z
        33: aload_0
        34: invokevirtual #391                // Method rules:()Lscala/collection/immutable/Seq;
        37: aload_0
        38: invokevirtual #354                // Method reconciliation:()Lscala/collection/immutable/Seq;
        41: aload_0
        42: invokevirtual #286                // Method properties:()Lscala/collection/immutable/Seq;
        45: aload_0
        46: invokevirtual #361                // Method exclusions:()Lscala/collection/immutable/Set;
        49: aload_0
        50: invokevirtual #405                // Method osInfoOpt:()Lscala/Option;
        53: aload_0
        54: invokevirtual #407                // Method jdkVersionOpt:()Lscala/Option;
        57: aload_0
        58: invokevirtual #409                // Method useSystemOsInfo:()Z
        61: aload_0
        62: invokevirtual #411                // Method useSystemJdkVersion:()Z
        65: aload_0
        66: invokevirtual #413                // Method defaultConfiguration:()Ljava/lang/String;
        69: invokespecial #416                // Method "<init>":(ZILscala/collection/immutable/Map;Lscala/collection/immutable/Map;Lscala/collection/immutable/Set;Lscala/Option;Lscala/Option;ZLscala/collection/immutable/Seq;Lscala/collection/immutable/Seq;Lscala/collection/immutable/Seq;Lscala/collection/immutable/Set;Lscala/Option;Lscala/Option;ZZLjava/lang/String;)V
        72: areturn
      LineNumberTable:
        line 8: 0
      LocalVariableTable:
        Start  Length  Slot  Name   Signature
            0      73     0  this   Lcoursier/params/ResolutionParams;
            0      73     1 forcedProperties   Lscala/collection/immutable/Map;
    Signature: #422                         // (Lscala/collection/immutable/Map<Ljava/lang/String;Ljava/lang/String;>;)Lcoursier/params/ResolutionParams;
    MethodParameters:
      Name                           Flags
      forcedProperties               final

  public coursier.params.ResolutionParams withProfiles(scala.collection.immutable.Set<java.lang.String>);
    descriptor: (Lscala/collection/immutable/Set;)Lcoursier/params/ResolutionParams;
    flags: (0x0001) ACC_PUBLIC
    Code:
      stack=19, locals=2, args_size=2
         0: new           #2                  // class coursier/params/ResolutionParams
         3: dup
         4: aload_0
         5: invokevirtual #420                // Method keepOptionalDependencies:()Z
         8: aload_0
         9: invokevirtual #401                // Method maxIterations:()I
        12: aload_0
        13: invokevirtual #164                // Method forceVersion:()Lscala/collection/immutable/Map;
        16: aload_0
        17: invokevirtual #295                // Method forcedProperties:()Lscala/collection/immutable/Map;
        20: aload_1
        21: aload_0
        22: invokevirtual #210                // Method scalaVersionOpt:()Lscala/Option;
        25: aload_0
        26: invokevirtual #177                // Method forceScalaVersionOpt:()Lscala/Option;
        29: aload_0
        30: invokevirtual #403                // Method typelevel:()Z
        33: aload_0
        34: invokevirtual #391                // Method rules:()Lscala/collection/immutable/Seq;
        37: aload_0
        38: invokevirtual #354                // Method reconciliation:()Lscala/collection/immutable/Seq;
        41: aload_0
        42: invokevirtual #286                // Method properties:()Lscala/collection/immutable/Seq;
        45: aload_0
        46: invokevirtual #361                // Method exclusions:()Lscala/collection/immutable/Set;
        49: aload_0
        50: invokevirtual #405                // Method osInfoOpt:()Lscala/Option;
        53: aload_0
        54: invokevirtual #407                // Method jdkVersionOpt:()Lscala/Option;
        57: aload_0
        58: invokevirtual #409                // Method useSystemOsInfo:()Z
        61: aload_0
        62: invokevirtual #411                // Method useSystemJdkVersion:()Z
        65: aload_0
        66: invokevirtual #413                // Method defaultConfiguration:()Ljava/lang/String;
        69: invokespecial #416                // Method "<init>":(ZILscala/collection/immutable/Map;Lscala/collection/immutable/Map;Lscala/collection/immutable/Set;Lscala/Option;Lscala/Option;ZLscala/collection/immutable/Seq;Lscala/collection/immutable/Seq;Lscala/collection/immutable/Seq;Lscala/collection/immutable/Set;Lscala/Option;Lscala/Option;ZZLjava/lang/String;)V
        72: areturn
      LineNumberTable:
        line 8: 0
      LocalVariableTable:
        Start  Length  Slot  Name   Signature
            0      73     0  this   Lcoursier/params/ResolutionParams;
            0      73     1 profiles   Lscala/collection/immutable/Set;
    Signature: #423                         // (Lscala/collection/immutable/Set<Ljava/lang/String;>;)Lcoursier/params/ResolutionParams;
    MethodParameters:
      Name                           Flags
      profiles                       final

  public coursier.params.ResolutionParams withScalaVersionOpt(scala.Option<java.lang.String>);
    descriptor: (Lscala/Option;)Lcoursier/params/ResolutionParams;
    flags: (0x0001) ACC_PUBLIC
    Code:
      stack=19, locals=2, args_size=2
         0: new           #2                  // class coursier/params/ResolutionParams
         3: dup
         4: aload_0
         5: invokevirtual #420                // Method keepOptionalDependencies:()Z
         8: aload_0
         9: invokevirtual #401                // Method maxIterations:()I
        12: aload_0
        13: invokevirtual #164                // Method forceVersion:()Lscala/collection/immutable/Map;
        16: aload_0
        17: invokevirtual #295                // Method forcedProperties:()Lscala/collection/immutable/Map;
        20: aload_0
        21: invokevirtual #228                // Method profiles:()Lscala/collection/immutable/Set;
        24: aload_1
        25: aload_0
        26: invokevirtual #177                // Method forceScalaVersionOpt:()Lscala/Option;
        29: aload_0
        30: invokevirtual #403                // Method typelevel:()Z
        33: aload_0
        34: invokevirtual #391                // Method rules:()Lscala/collection/immutable/Seq;
        37: aload_0
        38: invokevirtual #354                // Method reconciliation:()Lscala/collection/immutable/Seq;
        41: aload_0
        42: invokevirtual #286                // Method properties:()Lscala/collection/immutable/Seq;
        45: aload_0
        46: invokevirtual #361                // Method exclusions:()Lscala/collection/immutable/Set;
        49: aload_0
        50: invokevirtual #405                // Method osInfoOpt:()Lscala/Option;
        53: aload_0
        54: invokevirtual #407                // Method jdkVersionOpt:()Lscala/Option;
        57: aload_0
        58: invokevirtual #409                // Method useSystemOsInfo:()Z
        61: aload_0
        62: invokevirtual #411                // Method useSystemJdkVersion:()Z
        65: aload_0
        66: invokevirtual #413                // Method defaultConfiguration:()Ljava/lang/String;
        69: invokespecial #416                // Method "<init>":(ZILscala/collection/immutable/Map;Lscala/collection/immutable/Map;Lscala/collection/immutable/Set;Lscala/Option;Lscala/Option;ZLscala/collection/immutable/Seq;Lscala/collection/immutable/Seq;Lscala/collection/immutable/Seq;Lscala/collection/immutable/Set;Lscala/Option;Lscala/Option;ZZLjava/lang/String;)V
        72: areturn
      LineNumberTable:
        line 8: 0
      LocalVariableTable:
        Start  Length  Slot  Name   Signature
            0      73     0  this   Lcoursier/params/ResolutionParams;
            0      73     1 scalaVersionOpt   Lscala/Option;
    Signature: #424                         // (Lscala/Option<Ljava/lang/String;>;)Lcoursier/params/ResolutionParams;
    MethodParameters:
      Name                           Flags
      scalaVersionOpt                final

  public coursier.params.ResolutionParams withForceScalaVersionOpt(scala.Option<java.lang.Object>);
    descriptor: (Lscala/Option;)Lcoursier/params/ResolutionParams;
    flags: (0x0001) ACC_PUBLIC
    Code:
      stack=19, locals=2, args_size=2
         0: new           #2                  // class coursier/params/ResolutionParams
         3: dup
         4: aload_0
         5: invokevirtual #420                // Method keepOptionalDependencies:()Z
         8: aload_0
         9: invokevirtual #401                // Method maxIterations:()I
        12: aload_0
        13: invokevirtual #164                // Method forceVersion:()Lscala/collection/immutable/Map;
        16: aload_0
        17: invokevirtual #295                // Method forcedProperties:()Lscala/collection/immutable/Map;
        20: aload_0
        21: invokevirtual #228                // Method profiles:()Lscala/collection/immutable/Set;
        24: aload_0
        25: invokevirtual #210                // Method scalaVersionOpt:()Lscala/Option;
        28: aload_1
        29: aload_0
        30: invokevirtual #403                // Method typelevel:()Z
        33: aload_0
        34: invokevirtual #391                // Method rules:()Lscala/collection/immutable/Seq;
        37: aload_0
        38: invokevirtual #354                // Method reconciliation:()Lscala/collection/immutable/Seq;
        41: aload_0
        42: invokevirtual #286                // Method properties:()Lscala/collection/immutable/Seq;
        45: aload_0
        46: invokevirtual #361                // Method exclusions:()Lscala/collection/immutable/Set;
        49: aload_0
        50: invokevirtual #405                // Method osInfoOpt:()Lscala/Option;
        53: aload_0
        54: invokevirtual #407                // Method jdkVersionOpt:()Lscala/Option;
        57: aload_0
        58: invokevirtual #409                // Method useSystemOsInfo:()Z
        61: aload_0
        62: invokevirtual #411                // Method useSystemJdkVersion:()Z
        65: aload_0
        66: invokevirtual #413                // Method defaultConfiguration:()Ljava/lang/String;
        69: invokespecial #416                // Method "<init>":(ZILscala/collection/immutable/Map;Lscala/collection/immutable/Map;Lscala/collection/immutable/Set;Lscala/Option;Lscala/Option;ZLscala/collection/immutable/Seq;Lscala/collection/immutable/Seq;Lscala/collection/immutable/Seq;Lscala/collection/immutable/Set;Lscala/Option;Lscala/Option;ZZLjava/lang/String;)V
        72: areturn
      LineNumberTable:
        line 8: 0
      LocalVariableTable:
        Start  Length  Slot  Name   Signature
            0      73     0  this   Lcoursier/params/ResolutionParams;
            0      73     1 forceScalaVersionOpt   Lscala/Option;
    Signature: #425                         // (Lscala/Option<Ljava/lang/Object;>;)Lcoursier/params/ResolutionParams;
    MethodParameters:
      Name                           Flags
      forceScalaVersionOpt           final

  public coursier.params.ResolutionParams withTypelevel(boolean);
    descriptor: (Z)Lcoursier/params/ResolutionParams;
    flags: (0x0001) ACC_PUBLIC
    Code:
      stack=19, locals=2, args_size=2
         0: new           #2                  // class coursier/params/ResolutionParams
         3: dup
         4: aload_0
         5: invokevirtual #420                // Method keepOptionalDependencies:()Z
         8: aload_0
         9: invokevirtual #401                // Method maxIterations:()I
        12: aload_0
        13: invokevirtual #164                // Method forceVersion:()Lscala/collection/immutable/Map;
        16: aload_0
        17: invokevirtual #295                // Method forcedProperties:()Lscala/collection/immutable/Map;
        20: aload_0
        21: invokevirtual #228                // Method profiles:()Lscala/collection/immutable/Set;
        24: aload_0
        25: invokevirtual #210                // Method scalaVersionOpt:()Lscala/Option;
        28: aload_0
        29: invokevirtual #177                // Method forceScalaVersionOpt:()Lscala/Option;
        32: iload_1
        33: aload_0
        34: invokevirtual #391                // Method rules:()Lscala/collection/immutable/Seq;
        37: aload_0
        38: invokevirtual #354                // Method reconciliation:()Lscala/collection/immutable/Seq;
        41: aload_0
        42: invokevirtual #286                // Method properties:()Lscala/collection/immutable/Seq;
        45: aload_0
        46: invokevirtual #361                // Method exclusions:()Lscala/collection/immutable/Set;
        49: aload_0
        50: invokevirtual #405                // Method osInfoOpt:()Lscala/Option;
        53: aload_0
        54: invokevirtual #407                // Method jdkVersionOpt:()Lscala/Option;
        57: aload_0
        58: invokevirtual #409                // Method useSystemOsInfo:()Z
        61: aload_0
        62: invokevirtual #411                // Method useSystemJdkVersion:()Z
        65: aload_0
        66: invokevirtual #413                // Method defaultConfiguration:()Ljava/lang/String;
        69: invokespecial #416                // Method "<init>":(ZILscala/collection/immutable/Map;Lscala/collection/immutable/Map;Lscala/collection/immutable/Set;Lscala/Option;Lscala/Option;ZLscala/collection/immutable/Seq;Lscala/collection/immutable/Seq;Lscala/collection/immutable/Seq;Lscala/collection/immutable/Set;Lscala/Option;Lscala/Option;ZZLjava/lang/String;)V
        72: areturn
      LineNumberTable:
        line 8: 0
      LocalVariableTable:
        Start  Length  Slot  Name   Signature
            0      73     0  this   Lcoursier/params/ResolutionParams;
            0      73     1 typelevel   Z
    MethodParameters:
      Name                           Flags
      typelevel                      final

  public coursier.params.ResolutionParams withRules(scala.collection.immutable.Seq<scala.Tuple2<coursier.params.rule.Rule, coursier.params.rule.RuleResolution>>);
    descriptor: (Lscala/collection/immutable/Seq;)Lcoursier/params/ResolutionParams;
    flags: (0x0001) ACC_PUBLIC
    Code:
      stack=19, locals=2, args_size=2
         0: new           #2                  // class coursier/params/ResolutionParams
         3: dup
         4: aload_0
         5: invokevirtual #420                // Method keepOptionalDependencies:()Z
         8: aload_0
         9: invokevirtual #401                // Method maxIterations:()I
        12: aload_0
        13: invokevirtual #164                // Method forceVersion:()Lscala/collection/immutable/Map;
        16: aload_0
        17: invokevirtual #295                // Method forcedProperties:()Lscala/collection/immutable/Map;
        20: aload_0
        21: invokevirtual #228                // Method profiles:()Lscala/collection/immutable/Set;
        24: aload_0
        25: invokevirtual #210                // Method scalaVersionOpt:()Lscala/Option;
        28: aload_0
        29: invokevirtual #177                // Method forceScalaVersionOpt:()Lscala/Option;
        32: aload_0
        33: invokevirtual #403                // Method typelevel:()Z
        36: aload_1
        37: aload_0
        38: invokevirtual #354                // Method reconciliation:()Lscala/collection/immutable/Seq;
        41: aload_0
        42: invokevirtual #286                // Method properties:()Lscala/collection/immutable/Seq;
        45: aload_0
        46: invokevirtual #361                // Method exclusions:()Lscala/collection/immutable/Set;
        49: aload_0
        50: invokevirtual #405                // Method osInfoOpt:()Lscala/Option;
        53: aload_0
        54: invokevirtual #407                // Method jdkVersionOpt:()Lscala/Option;
        57: aload_0
        58: invokevirtual #409                // Method useSystemOsInfo:()Z
        61: aload_0
        62: invokevirtual #411                // Method useSystemJdkVersion:()Z
        65: aload_0
        66: invokevirtual #413                // Method defaultConfiguration:()Ljava/lang/String;
        69: invokespecial #416                // Method "<init>":(ZILscala/collection/immutable/Map;Lscala/collection/immutable/Map;Lscala/collection/immutable/Set;Lscala/Option;Lscala/Option;ZLscala/collection/immutable/Seq;Lscala/collection/immutable/Seq;Lscala/collection/immutable/Seq;Lscala/collection/immutable/Set;Lscala/Option;Lscala/Option;ZZLjava/lang/String;)V
        72: areturn
      LineNumberTable:
        line 8: 0
      LocalVariableTable:
        Start  Length  Slot  Name   Signature
            0      73     0  this   Lcoursier/params/ResolutionParams;
            0      73     1 rules   Lscala/collection/immutable/Seq;
    Signature: #427                         // (Lscala/collection/immutable/Seq<Lscala/Tuple2<Lcoursier/params/rule/Rule;Lcoursier/params/rule/RuleResolution;>;>;)Lcoursier/params/ResolutionParams;
    MethodParameters:
      Name                           Flags
      rules                          final

  public coursier.params.ResolutionParams withReconciliation(scala.collection.immutable.Seq<scala.Tuple2<coursier.util.ModuleMatchers, coursier.core.Reconciliation>>);
    descriptor: (Lscala/collection/immutable/Seq;)Lcoursier/params/ResolutionParams;
    flags: (0x0001) ACC_PUBLIC
    Code:
      stack=19, locals=2, args_size=2
         0: new           #2                  // class coursier/params/ResolutionParams
         3: dup
         4: aload_0
         5: invokevirtual #420                // Method keepOptionalDependencies:()Z
         8: aload_0
         9: invokevirtual #401                // Method maxIterations:()I
        12: aload_0
        13: invokevirtual #164                // Method forceVersion:()Lscala/collection/immutable/Map;
        16: aload_0
        17: invokevirtual #295                // Method forcedProperties:()Lscala/collection/immutable/Map;
        20: aload_0
        21: invokevirtual #228                // Method profiles:()Lscala/collection/immutable/Set;
        24: aload_0
        25: invokevirtual #210                // Method scalaVersionOpt:()Lscala/Option;
        28: aload_0
        29: invokevirtual #177                // Method forceScalaVersionOpt:()Lscala/Option;
        32: aload_0
        33: invokevirtual #403                // Method typelevel:()Z
        36: aload_0
        37: invokevirtual #391                // Method rules:()Lscala/collection/immutable/Seq;
        40: aload_1
        41: aload_0
        42: invokevirtual #286                // Method properties:()Lscala/collection/immutable/Seq;
        45: aload_0
        46: invokevirtual #361                // Method exclusions:()Lscala/collection/immutable/Set;
        49: aload_0
        50: invokevirtual #405                // Method osInfoOpt:()Lscala/Option;
        53: aload_0
        54: invokevirtual #407                // Method jdkVersionOpt:()Lscala/Option;
        57: aload_0
        58: invokevirtual #409                // Method useSystemOsInfo:()Z
        61: aload_0
        62: invokevirtual #411                // Method useSystemJdkVersion:()Z
        65: aload_0
        66: invokevirtual #413                // Method defaultConfiguration:()Ljava/lang/String;
        69: invokespecial #416                // Method "<init>":(ZILscala/collection/immutable/Map;Lscala/collection/immutable/Map;Lscala/collection/immutable/Set;Lscala/Option;Lscala/Option;ZLscala/collection/immutable/Seq;Lscala/collection/immutable/Seq;Lscala/collection/immutable/Seq;Lscala/collection/immutable/Set;Lscala/Option;Lscala/Option;ZZLjava/lang/String;)V
        72: areturn
      LineNumberTable:
        line 8: 0
      LocalVariableTable:
        Start  Length  Slot  Name   Signature
            0      73     0  this   Lcoursier/params/ResolutionParams;
            0      73     1 reconciliation   Lscala/collection/immutable/Seq;
    Signature: #352                         // (Lscala/collection/immutable/Seq<Lscala/Tuple2<Lcoursier/util/ModuleMatchers;Lcoursier/core/Reconciliation;>;>;)Lcoursier/params/ResolutionParams;
    MethodParameters:
      Name                           Flags
      reconciliation                 final

  public coursier.params.ResolutionParams withProperties(scala.collection.immutable.Seq<scala.Tuple2<java.lang.String, java.lang.String>>);
    descriptor: (Lscala/collection/immutable/Seq;)Lcoursier/params/ResolutionParams;
    flags: (0x0001) ACC_PUBLIC
    Code:
      stack=19, locals=2, args_size=2
         0: new           #2                  // class coursier/params/ResolutionParams
         3: dup
         4: aload_0
         5: invokevirtual #420                // Method keepOptionalDependencies:()Z
         8: aload_0
         9: invokevirtual #401                // Method maxIterations:()I
        12: aload_0
        13: invokevirtual #164                // Method forceVersion:()Lscala/collection/immutable/Map;
        16: aload_0
        17: invokevirtual #295                // Method forcedProperties:()Lscala/collection/immutable/Map;
        20: aload_0
        21: invokevirtual #228                // Method profiles:()Lscala/collection/immutable/Set;
        24: aload_0
        25: invokevirtual #210                // Method scalaVersionOpt:()Lscala/Option;
        28: aload_0
        29: invokevirtual #177                // Method forceScalaVersionOpt:()Lscala/Option;
        32: aload_0
        33: invokevirtual #403                // Method typelevel:()Z
        36: aload_0
        37: invokevirtual #391                // Method rules:()Lscala/collection/immutable/Seq;
        40: aload_0
        41: invokevirtual #354                // Method reconciliation:()Lscala/collection/immutable/Seq;
        44: aload_1
        45: aload_0
        46: invokevirtual #361                // Method exclusions:()Lscala/collection/immutable/Set;
        49: aload_0
        50: invokevirtual #405                // Method osInfoOpt:()Lscala/Option;
        53: aload_0
        54: invokevirtual #407                // Method jdkVersionOpt:()Lscala/Option;
        57: aload_0
        58: invokevirtual #409                // Method useSystemOsInfo:()Z
        61: aload_0
        62: invokevirtual #411                // Method useSystemJdkVersion:()Z
        65: aload_0
        66: invokevirtual #413                // Method defaultConfiguration:()Ljava/lang/String;
        69: invokespecial #416                // Method "<init>":(ZILscala/collection/immutable/Map;Lscala/collection/immutable/Map;Lscala/collection/immutable/Set;Lscala/Option;Lscala/Option;ZLscala/collection/immutable/Seq;Lscala/collection/immutable/Seq;Lscala/collection/immutable/Seq;Lscala/collection/immutable/Set;Lscala/Option;Lscala/Option;ZZLjava/lang/String;)V
        72: areturn
      LineNumberTable:
        line 8: 0
      LocalVariableTable:
        Start  Length  Slot  Name   Signature
            0      73     0  this   Lcoursier/params/ResolutionParams;
            0      73     1 properties   Lscala/collection/immutable/Seq;
    Signature: #283                         // (Lscala/collection/immutable/Seq<Lscala/Tuple2<Ljava/lang/String;Ljava/lang/String;>;>;)Lcoursier/params/ResolutionParams;
    MethodParameters:
      Name                           Flags
      properties                     final

  public coursier.params.ResolutionParams withExclusions(scala.collection.immutable.Set<scala.Tuple2<coursier.core.Organization, coursier.core.ModuleName>>);
    descriptor: (Lscala/collection/immutable/Set;)Lcoursier/params/ResolutionParams;
    flags: (0x0001) ACC_PUBLIC
    Code:
      stack=19, locals=2, args_size=2
         0: new           #2                  // class coursier/params/ResolutionParams
         3: dup
         4: aload_0
         5: invokevirtual #420                // Method keepOptionalDependencies:()Z
         8: aload_0
         9: invokevirtual #401                // Method maxIterations:()I
        12: aload_0
        13: invokevirtual #164                // Method forceVersion:()Lscala/collection/immutable/Map;
        16: aload_0
        17: invokevirtual #295                // Method forcedProperties:()Lscala/collection/immutable/Map;
        20: aload_0
        21: invokevirtual #228                // Method profiles:()Lscala/collection/immutable/Set;
        24: aload_0
        25: invokevirtual #210                // Method scalaVersionOpt:()Lscala/Option;
        28: aload_0
        29: invokevirtual #177                // Method forceScalaVersionOpt:()Lscala/Option;
        32: aload_0
        33: invokevirtual #403                // Method typelevel:()Z
        36: aload_0
        37: invokevirtual #391                // Method rules:()Lscala/collection/immutable/Seq;
        40: aload_0
        41: invokevirtual #354                // Method reconciliation:()Lscala/collection/immutable/Seq;
        44: aload_0
        45: invokevirtual #286                // Method properties:()Lscala/collection/immutable/Seq;
        48: aload_1
        49: aload_0
        50: invokevirtual #405                // Method osInfoOpt:()Lscala/Option;
        53: aload_0
        54: invokevirtual #407                // Method jdkVersionOpt:()Lscala/Option;
        57: aload_0
        58: invokevirtual #409                // Method useSystemOsInfo:()Z
        61: aload_0
        62: invokevirtual #411                // Method useSystemJdkVersion:()Z
        65: aload_0
        66: invokevirtual #413                // Method defaultConfiguration:()Ljava/lang/String;
        69: invokespecial #416                // Method "<init>":(ZILscala/collection/immutable/Map;Lscala/collection/immutable/Map;Lscala/collection/immutable/Set;Lscala/Option;Lscala/Option;ZLscala/collection/immutable/Seq;Lscala/collection/immutable/Seq;Lscala/collection/immutable/Seq;Lscala/collection/immutable/Set;Lscala/Option;Lscala/Option;ZZLjava/lang/String;)V
        72: areturn
      LineNumberTable:
        line 8: 0
      LocalVariableTable:
        Start  Length  Slot  Name   Signature
            0      73     0  this   Lcoursier/params/ResolutionParams;
            0      73     1 exclusions   Lscala/collection/immutable/Set;
    Signature: #428                         // (Lscala/collection/immutable/Set<Lscala/Tuple2<Lcoursier/core/Organization;Lcoursier/core/ModuleName;>;>;)Lcoursier/params/ResolutionParams;
    MethodParameters:
      Name                           Flags
      exclusions                     final

  public coursier.params.ResolutionParams withOsInfoOpt(scala.Option<coursier.core.Activation$Os>);
    descriptor: (Lscala/Option;)Lcoursier/params/ResolutionParams;
    flags: (0x0001) ACC_PUBLIC
    Code:
      stack=19, locals=2, args_size=2
         0: new           #2                  // class coursier/params/ResolutionParams
         3: dup
         4: aload_0
         5: invokevirtual #420                // Method keepOptionalDependencies:()Z
         8: aload_0
         9: invokevirtual #401                // Method maxIterations:()I
        12: aload_0
        13: invokevirtual #164                // Method forceVersion:()Lscala/collection/immutable/Map;
        16: aload_0
        17: invokevirtual #295                // Method forcedProperties:()Lscala/collection/immutable/Map;
        20: aload_0
        21: invokevirtual #228                // Method profiles:()Lscala/collection/immutable/Set;
        24: aload_0
        25: invokevirtual #210                // Method scalaVersionOpt:()Lscala/Option;
        28: aload_0
        29: invokevirtual #177                // Method forceScalaVersionOpt:()Lscala/Option;
        32: aload_0
        33: invokevirtual #403                // Method typelevel:()Z
        36: aload_0
        37: invokevirtual #391                // Method rules:()Lscala/collection/immutable/Seq;
        40: aload_0
        41: invokevirtual #354                // Method reconciliation:()Lscala/collection/immutable/Seq;
        44: aload_0
        45: invokevirtual #286                // Method properties:()Lscala/collection/immutable/Seq;
        48: aload_0
        49: invokevirtual #361                // Method exclusions:()Lscala/collection/immutable/Set;
        52: aload_1
        53: aload_0
        54: invokevirtual #407                // Method jdkVersionOpt:()Lscala/Option;
        57: aload_0
        58: invokevirtual #409                // Method useSystemOsInfo:()Z
        61: aload_0
        62: invokevirtual #411                // Method useSystemJdkVersion:()Z
        65: aload_0
        66: invokevirtual #413                // Method defaultConfiguration:()Ljava/lang/String;
        69: invokespecial #416                // Method "<init>":(ZILscala/collection/immutable/Map;Lscala/collection/immutable/Map;Lscala/collection/immutable/Set;Lscala/Option;Lscala/Option;ZLscala/collection/immutable/Seq;Lscala/collection/immutable/Seq;Lscala/collection/immutable/Seq;Lscala/collection/immutable/Set;Lscala/Option;Lscala/Option;ZZLjava/lang/String;)V
        72: areturn
      LineNumberTable:
        line 8: 0
      LocalVariableTable:
        Start  Length  Slot  Name   Signature
            0      73     0  this   Lcoursier/params/ResolutionParams;
            0      73     1 osInfoOpt   Lscala/Option;
    Signature: #429                         // (Lscala/Option<Lcoursier/core/Activation$Os;>;)Lcoursier/params/ResolutionParams;
    MethodParameters:
      Name                           Flags
      osInfoOpt                      final

  public coursier.params.ResolutionParams withJdkVersionOpt(scala.Option<coursier.core.Version>);
    descriptor: (Lscala/Option;)Lcoursier/params/ResolutionParams;
    flags: (0x0001) ACC_PUBLIC
    Code:
      stack=19, locals=2, args_size=2
         0: new           #2                  // class coursier/params/ResolutionParams
         3: dup
         4: aload_0
         5: invokevirtual #420                // Method keepOptionalDependencies:()Z
         8: aload_0
         9: invokevirtual #401                // Method maxIterations:()I
        12: aload_0
        13: invokevirtual #164                // Method forceVersion:()Lscala/collection/immutable/Map;
        16: aload_0
        17: invokevirtual #295                // Method forcedProperties:()Lscala/collection/immutable/Map;
        20: aload_0
        21: invokevirtual #228                // Method profiles:()Lscala/collection/immutable/Set;
        24: aload_0
        25: invokevirtual #210                // Method scalaVersionOpt:()Lscala/Option;
        28: aload_0
        29: invokevirtual #177                // Method forceScalaVersionOpt:()Lscala/Option;
        32: aload_0
        33: invokevirtual #403                // Method typelevel:()Z
        36: aload_0
        37: invokevirtual #391                // Method rules:()Lscala/collection/immutable/Seq;
        40: aload_0
        41: invokevirtual #354                // Method reconciliation:()Lscala/collection/immutable/Seq;
        44: aload_0
        45: invokevirtual #286                // Method properties:()Lscala/collection/immutable/Seq;
        48: aload_0
        49: invokevirtual #361                // Method exclusions:()Lscala/collection/immutable/Set;
        52: aload_0
        53: invokevirtual #405                // Method osInfoOpt:()Lscala/Option;
        56: aload_1
        57: aload_0
        58: invokevirtual #409                // Method useSystemOsInfo:()Z
        61: aload_0
        62: invokevirtual #411                // Method useSystemJdkVersion:()Z
        65: aload_0
        66: invokevirtual #413                // Method defaultConfiguration:()Ljava/lang/String;
        69: invokespecial #416                // Method "<init>":(ZILscala/collection/immutable/Map;Lscala/collection/immutable/Map;Lscala/collection/immutable/Set;Lscala/Option;Lscala/Option;ZLscala/collection/immutable/Seq;Lscala/collection/immutable/Seq;Lscala/collection/immutable/Seq;Lscala/collection/immutable/Set;Lscala/Option;Lscala/Option;ZZLjava/lang/String;)V
        72: areturn
      LineNumberTable:
        line 8: 0
      LocalVariableTable:
        Start  Length  Slot  Name   Signature
            0      73     0  this   Lcoursier/params/ResolutionParams;
            0      73     1 jdkVersionOpt   Lscala/Option;
    Signature: #430                         // (Lscala/Option<Lcoursier/core/Version;>;)Lcoursier/params/ResolutionParams;
    MethodParameters:
      Name                           Flags
      jdkVersionOpt                  final

  public coursier.params.ResolutionParams withUseSystemOsInfo(boolean);
    descriptor: (Z)Lcoursier/params/ResolutionParams;
    flags: (0x0001) ACC_PUBLIC
    Code:
      stack=19, locals=2, args_size=2
         0: new           #2                  // class coursier/params/ResolutionParams
         3: dup
         4: aload_0
         5: invokevirtual #420                // Method keepOptionalDependencies:()Z
         8: aload_0
         9: invokevirtual #401                // Method maxIterations:()I
        12: aload_0
        13: invokevirtual #164                // Method forceVersion:()Lscala/collection/immutable/Map;
        16: aload_0
        17: invokevirtual #295                // Method forcedProperties:()Lscala/collection/immutable/Map;
        20: aload_0
        21: invokevirtual #228                // Method profiles:()Lscala/collection/immutable/Set;
        24: aload_0
        25: invokevirtual #210                // Method scalaVersionOpt:()Lscala/Option;
        28: aload_0
        29: invokevirtual #177                // Method forceScalaVersionOpt:()Lscala/Option;
        32: aload_0
        33: invokevirtual #403                // Method typelevel:()Z
        36: aload_0
        37: invokevirtual #391                // Method rules:()Lscala/collection/immutable/Seq;
        40: aload_0
        41: invokevirtual #354                // Method reconciliation:()Lscala/collection/immutable/Seq;
        44: aload_0
        45: invokevirtual #286                // Method properties:()Lscala/collection/immutable/Seq;
        48: aload_0
        49: invokevirtual #361                // Method exclusions:()Lscala/collection/immutable/Set;
        52: aload_0
        53: invokevirtual #405                // Method osInfoOpt:()Lscala/Option;
        56: aload_0
        57: invokevirtual #407                // Method jdkVersionOpt:()Lscala/Option;
        60: iload_1
        61: aload_0
        62: invokevirtual #411                // Method useSystemJdkVersion:()Z
        65: aload_0
        66: invokevirtual #413                // Method defaultConfiguration:()Ljava/lang/String;
        69: invokespecial #416                // Method "<init>":(ZILscala/collection/immutable/Map;Lscala/collection/immutable/Map;Lscala/collection/immutable/Set;Lscala/Option;Lscala/Option;ZLscala/collection/immutable/Seq;Lscala/collection/immutable/Seq;Lscala/collection/immutable/Seq;Lscala/collection/immutable/Set;Lscala/Option;Lscala/Option;ZZLjava/lang/String;)V
        72: areturn
      LineNumberTable:
        line 8: 0
      LocalVariableTable:
        Start  Length  Slot  Name   Signature
            0      73     0  this   Lcoursier/params/ResolutionParams;
            0      73     1 useSystemOsInfo   Z
    MethodParameters:
      Name                           Flags
      useSystemOsInfo                final

  public coursier.params.ResolutionParams withUseSystemJdkVersion(boolean);
    descriptor: (Z)Lcoursier/params/ResolutionParams;
    flags: (0x0001) ACC_PUBLIC
    Code:
      stack=19, locals=2, args_size=2
         0: new           #2                  // class coursier/params/ResolutionParams
         3: dup
         4: aload_0
         5: invokevirtual #420                // Method keepOptionalDependencies:()Z
         8: aload_0
         9: invokevirtual #401                // Method maxIterations:()I
        12: aload_0
        13: invokevirtual #164                // Method forceVersion:()Lscala/collection/immutable/Map;
        16: aload_0
        17: invokevirtual #295                // Method forcedProperties:()Lscala/collection/immutable/Map;
        20: aload_0
        21: invokevirtual #228                // Method profiles:()Lscala/collection/immutable/Set;
        24: aload_0
        25: invokevirtual #210                // Method scalaVersionOpt:()Lscala/Option;
        28: aload_0
        29: invokevirtual #177                // Method forceScalaVersionOpt:()Lscala/Option;
        32: aload_0
        33: invokevirtual #403                // Method typelevel:()Z
        36: aload_0
        37: invokevirtual #391                // Method rules:()Lscala/collection/immutable/Seq;
        40: aload_0
        41: invokevirtual #354                // Method reconciliation:()Lscala/collection/immutable/Seq;
        44: aload_0
        45: invokevirtual #286                // Method properties:()Lscala/collection/immutable/Seq;
        48: aload_0
        49: invokevirtual #361                // Method exclusions:()Lscala/collection/immutable/Set;
        52: aload_0
        53: invokevirtual #405                // Method osInfoOpt:()Lscala/Option;
        56: aload_0
        57: invokevirtual #407                // Method jdkVersionOpt:()Lscala/Option;
        60: aload_0
        61: invokevirtual #409                // Method useSystemOsInfo:()Z
        64: iload_1
        65: aload_0
        66: invokevirtual #413                // Method defaultConfiguration:()Ljava/lang/String;
        69: invokespecial #416                // Method "<init>":(ZILscala/collection/immutable/Map;Lscala/collection/immutable/Map;Lscala/collection/immutable/Set;Lscala/Option;Lscala/Option;ZLscala/collection/immutable/Seq;Lscala/collection/immutable/Seq;Lscala/collection/immutable/Seq;Lscala/collection/immutable/Set;Lscala/Option;Lscala/Option;ZZLjava/lang/String;)V
        72: areturn
      LineNumberTable:
        line 8: 0
      LocalVariableTable:
        Start  Length  Slot  Name   Signature
            0      73     0  this   Lcoursier/params/ResolutionParams;
            0      73     1 useSystemJdkVersion   Z
    MethodParameters:
      Name                           Flags
      useSystemJdkVersion            final

  public coursier.params.ResolutionParams withDefaultConfiguration(java.lang.String);
    descriptor: (Ljava/lang/String;)Lcoursier/params/ResolutionParams;
    flags: (0x0001) ACC_PUBLIC
    Code:
      stack=19, locals=2, args_size=2
         0: new           #2                  // class coursier/params/ResolutionParams
         3: dup
         4: aload_0
         5: invokevirtual #420                // Method keepOptionalDependencies:()Z
         8: aload_0
         9: invokevirtual #401                // Method maxIterations:()I
        12: aload_0
        13: invokevirtual #164                // Method forceVersion:()Lscala/collection/immutable/Map;
        16: aload_0
        17: invokevirtual #295                // Method forcedProperties:()Lscala/collection/immutable/Map;
        20: aload_0
        21: invokevirtual #228                // Method profiles:()Lscala/collection/immutable/Set;
        24: aload_0
        25: invokevirtual #210                // Method scalaVersionOpt:()Lscala/Option;
        28: aload_0
        29: invokevirtual #177                // Method forceScalaVersionOpt:()Lscala/Option;
        32: aload_0
        33: invokevirtual #403                // Method typelevel:()Z
        36: aload_0
        37: invokevirtual #391                // Method rules:()Lscala/collection/immutable/Seq;
        40: aload_0
        41: invokevirtual #354                // Method reconciliation:()Lscala/collection/immutable/Seq;
        44: aload_0
        45: invokevirtual #286                // Method properties:()Lscala/collection/immutable/Seq;
        48: aload_0
        49: invokevirtual #361                // Method exclusions:()Lscala/collection/immutable/Set;
        52: aload_0
        53: invokevirtual #405                // Method osInfoOpt:()Lscala/Option;
        56: aload_0
        57: invokevirtual #407                // Method jdkVersionOpt:()Lscala/Option;
        60: aload_0
        61: invokevirtual #409                // Method useSystemOsInfo:()Z
        64: aload_0
        65: invokevirtual #411                // Method useSystemJdkVersion:()Z
        68: aload_1
        69: invokespecial #416                // Method "<init>":(ZILscala/collection/immutable/Map;Lscala/collection/immutable/Map;Lscala/collection/immutable/Set;Lscala/Option;Lscala/Option;ZLscala/collection/immutable/Seq;Lscala/collection/immutable/Seq;Lscala/collection/immutable/Seq;Lscala/collection/immutable/Set;Lscala/Option;Lscala/Option;ZZLjava/lang/String;)V
        72: areturn
      LineNumberTable:
        line 8: 0
      LocalVariableTable:
        Start  Length  Slot  Name   Signature
            0      73     0  this   Lcoursier/params/ResolutionParams;
            0      73     1 defaultConfiguration   Ljava/lang/String;
    MethodParameters:
      Name                           Flags
      defaultConfiguration           final

  public java.lang.String toString();
    descriptor: ()Ljava/lang/String;
    flags: (0x0001) ACC_PUBLIC
    Code:
      stack=4, locals=2, args_size=1
         0: new           #436                // class java/lang/StringBuilder
         3: dup
         4: ldc_w         #438                // String ResolutionParams(
         7: invokespecial #441                // Method java/lang/StringBuilder."<init>":(Ljava/lang/String;)V
        10: astore_1
        11: aload_1
        12: aload_0
        13: invokevirtual #420                // Method keepOptionalDependencies:()Z
        16: invokestatic  #445                // Method java/lang/String.valueOf:(Z)Ljava/lang/String;
        19: invokevirtual #449                // Method java/lang/StringBuilder.append:(Ljava/lang/String;)Ljava/lang/StringBuilder;
        22: pop
        23: aload_1
        24: ldc_w         #451                // String ,
        27: invokevirtual #449                // Method java/lang/StringBuilder.append:(Ljava/lang/String;)Ljava/lang/StringBuilder;
        30: pop
        31: aload_1
        32: aload_0
        33: invokevirtual #401                // Method maxIterations:()I
        36: invokestatic  #454                // Method java/lang/String.valueOf:(I)Ljava/lang/String;
        39: invokevirtual #449                // Method java/lang/StringBuilder.append:(Ljava/lang/String;)Ljava/lang/StringBuilder;
        42: pop
        43: aload_1
        44: ldc_w         #451                // String ,
        47: invokevirtual #449                // Method java/lang/StringBuilder.append:(Ljava/lang/String;)Ljava/lang/StringBuilder;
        50: pop
        51: aload_1
        52: aload_0
        53: invokevirtual #164                // Method forceVersion:()Lscala/collection/immutable/Map;
        56: invokestatic  #457                // Method java/lang/String.valueOf:(Ljava/lang/Object;)Ljava/lang/String;
        59: invokevirtual #449                // Method java/lang/StringBuilder.append:(Ljava/lang/String;)Ljava/lang/StringBuilder;
        62: pop
        63: aload_1
        64: ldc_w         #451                // String ,
        67: invokevirtual #449                // Method java/lang/StringBuilder.append:(Ljava/lang/String;)Ljava/lang/StringBuilder;
        70: pop
        71: aload_1
        72: aload_0
        73: invokevirtual #295                // Method forcedProperties:()Lscala/collection/immutable/Map;
        76: invokestatic  #457                // Method java/lang/String.valueOf:(Ljava/lang/Object;)Ljava/lang/String;
        79: invokevirtual #449                // Method java/lang/StringBuilder.append:(Ljava/lang/String;)Ljava/lang/StringBuilder;
        82: pop
        83: aload_1
        84: ldc_w         #451                // String ,
        87: invokevirtual #449                // Method java/lang/StringBuilder.append:(Ljava/lang/String;)Ljava/lang/StringBuilder;
        90: pop
        91: aload_1
        92: aload_0
        93: invokevirtual #228                // Method profiles:()Lscala/collection/immutable/Set;
        96: invokestatic  #457                // Method java/lang/String.valueOf:(Ljava/lang/Object;)Ljava/lang/String;
        99: invokevirtual #449                // Method java/lang/StringBuilder.append:(Ljava/lang/String;)Ljava/lang/StringBuilder;
       102: pop
       103: aload_1
       104: ldc_w         #451                // String ,
       107: invokevirtual #449                // Method java/lang/StringBuilder.append:(Ljava/lang/String;)Ljava/lang/StringBuilder;
       110: pop
       111: aload_1
       112: aload_0
       113: invokevirtual #210                // Method scalaVersionOpt:()Lscala/Option;
       116: invokestatic  #457                // Method java/lang/String.valueOf:(Ljava/lang/Object;)Ljava/lang/String;
       119: invokevirtual #449                // Method java/lang/StringBuilder.append:(Ljava/lang/String;)Ljava/lang/StringBuilder;
       122: pop
       123: aload_1
       124: ldc_w         #451                // String ,
       127: invokevirtual #449                // Method java/lang/StringBuilder.append:(Ljava/lang/String;)Ljava/lang/StringBuilder;
       130: pop
       131: aload_1
       132: aload_0
       133: invokevirtual #177                // Method forceScalaVersionOpt:()Lscala/Option;
       136: invokestatic  #457                // Method java/lang/String.valueOf:(Ljava/lang/Object;)Ljava/lang/String;
       139: invokevirtual #449                // Method java/lang/StringBuilder.append:(Ljava/lang/String;)Ljava/lang/StringBuilder;
       142: pop
       143: aload_1
       144: ldc_w         #451                // String ,
       147: invokevirtual #449                // Method java/lang/StringBuilder.append:(Ljava/lang/String;)Ljava/lang/StringBuilder;
       150: pop
       151: aload_1
       152: aload_0
       153: invokevirtual #403                // Method typelevel:()Z
       156: invokestatic  #445                // Method java/lang/String.valueOf:(Z)Ljava/lang/String;
       159: invokevirtual #449                // Method java/lang/StringBuilder.append:(Ljava/lang/String;)Ljava/lang/StringBuilder;
       162: pop
       163: aload_1
       164: ldc_w         #451                // String ,
       167: invokevirtual #449                // Method java/lang/StringBuilder.append:(Ljava/lang/String;)Ljava/lang/StringBuilder;
       170: pop
       171: aload_1
       172: aload_0
       173: invokevirtual #391                // Method rules:()Lscala/collection/immutable/Seq;
       176: invokestatic  #457                // Method java/lang/String.valueOf:(Ljava/lang/Object;)Ljava/lang/String;
       179: invokevirtual #449                // Method java/lang/StringBuilder.append:(Ljava/lang/String;)Ljava/lang/StringBuilder;
       182: pop
       183: aload_1
       184: ldc_w         #451                // String ,
       187: invokevirtual #449                // Method java/lang/StringBuilder.append:(Ljava/lang/String;)Ljava/lang/StringBuilder;
       190: pop
       191: aload_1
       192: aload_0
       193: invokevirtual #354                // Method reconciliation:()Lscala/collection/immutable/Seq;
       196: invokestatic  #457                // Method java/lang/String.valueOf:(Ljava/lang/Object;)Ljava/lang/String;
       199: invokevirtual #449                // Method java/lang/StringBuilder.append:(Ljava/lang/String;)Ljava/lang/StringBuilder;
       202: pop
       203: aload_1
       204: ldc_w         #451                // String ,
       207: invokevirtual #449                // Method java/lang/StringBuilder.append:(Ljava/lang/String;)Ljava/lang/StringBuilder;
       210: pop
       211: aload_1
       212: aload_0
       213: invokevirtual #286                // Method properties:()Lscala/collection/immutable/Seq;
       216: invokestatic  #457                // Method java/lang/String.valueOf:(Ljava/lang/Object;)Ljava/lang/String;
       219: invokevirtual #449                // Method java/lang/StringBuilder.append:(Ljava/lang/String;)Ljava/lang/StringBuilder;
       222: pop
       223: aload_1
       224: ldc_w         #451                // String ,
       227: invokevirtual #449                // Method java/lang/StringBuilder.append:(Ljava/lang/String;)Ljava/lang/StringBuilder;
       230: pop
       231: aload_1
       232: aload_0
       233: invokevirtual #361                // Method exclusions:()Lscala/collection/immutable/Set;
       236: invokestatic  #457                // Method java/lang/String.valueOf:(Ljava/lang/Object;)Ljava/lang/String;
       239: invokevirtual #449                // Method java/lang/StringBuilder.append:(Ljava/lang/String;)Ljava/lang/StringBuilder;
       242: pop
       243: aload_1
       244: ldc_w         #451                // String ,
       247: invokevirtual #449                // Method java/lang/StringBuilder.append:(Ljava/lang/String;)Ljava/lang/StringBuilder;
       250: pop
       251: aload_1
       252: aload_0
       253: invokevirtual #405                // Method osInfoOpt:()Lscala/Option;
       256: invokestatic  #457                // Method java/lang/String.valueOf:(Ljava/lang/Object;)Ljava/lang/String;
       259: invokevirtual #449                // Method java/lang/StringBuilder.append:(Ljava/lang/String;)Ljava/lang/StringBuilder;
       262: pop
       263: aload_1
       264: ldc_w         #451                // String ,
       267: invokevirtual #449                // Method java/lang/StringBuilder.append:(Ljava/lang/String;)Ljava/lang/StringBuilder;
       270: pop
       271: aload_1
       272: aload_0
       273: invokevirtual #407                // Method jdkVersionOpt:()Lscala/Option;
       276: invokestatic  #457                // Method java/lang/String.valueOf:(Ljava/lang/Object;)Ljava/lang/String;
       279: invokevirtual #449                // Method java/lang/StringBuilder.append:(Ljava/lang/String;)Ljava/lang/StringBuilder;
       282: pop
       283: aload_1
       284: ldc_w         #451                // String ,
       287: invokevirtual #449                // Method java/lang/StringBuilder.append:(Ljava/lang/String;)Ljava/lang/StringBuilder;
       290: pop
       291: aload_1
       292: aload_0
       293: invokevirtual #409                // Method useSystemOsInfo:()Z
       296: invokestatic  #445                // Method java/lang/String.valueOf:(Z)Ljava/lang/String;
       299: invokevirtual #449                // Method java/lang/StringBuilder.append:(Ljava/lang/String;)Ljava/lang/StringBuilder;
       302: pop
       303: aload_1
       304: ldc_w         #451                // String ,
       307: invokevirtual #449                // Method java/lang/StringBuilder.append:(Ljava/lang/String;)Ljava/lang/StringBuilder;
       310: pop
       311: aload_1
       312: aload_0
       313: invokevirtual #411                // Method useSystemJdkVersion:()Z
       316: invokestatic  #445                // Method java/lang/String.valueOf:(Z)Ljava/lang/String;
       319: invokevirtual #449                // Method java/lang/StringBuilder.append:(Ljava/lang/String;)Ljava/lang/StringBuilder;
       322: pop
       323: aload_1
       324: ldc_w         #451                // String ,
       327: invokevirtual #449                // Method java/lang/StringBuilder.append:(Ljava/lang/String;)Ljava/lang/StringBuilder;
       330: pop
       331: aload_1
       332: new           #459                // class coursier/core/Configuration
       335: dup
       336: aload_0
       337: invokevirtual #413                // Method defaultConfiguration:()Ljava/lang/String;
       340: invokespecial #460                // Method coursier/core/Configuration."<init>":(Ljava/lang/String;)V
       343: invokestatic  #457                // Method java/lang/String.valueOf:(Ljava/lang/Object;)Ljava/lang/String;
       346: invokevirtual #449                // Method java/lang/StringBuilder.append:(Ljava/lang/String;)Ljava/lang/StringBuilder;
       349: pop
       350: aload_1
       351: ldc_w         #462                // String )
       354: invokevirtual #449                // Method java/lang/StringBuilder.append:(Ljava/lang/String;)Ljava/lang/StringBuilder;
       357: pop
       358: aload_1
       359: invokevirtual #464                // Method java/lang/StringBuilder.toString:()Ljava/lang/String;
       362: areturn
      LineNumberTable:
        line 8: 0
      LocalVariableTable:
        Start  Length  Slot  Name   Signature
           11     351     1     b   Ljava/lang/StringBuilder;
            0     363     0  this   Lcoursier/params/ResolutionParams;

  public boolean canEqual(java.lang.Object);
    descriptor: (Ljava/lang/Object;)Z
    flags: (0x0001) ACC_PUBLIC
    Code:
      stack=1, locals=2, args_size=2
         0: aload_1
         1: ifnull        15
         4: aload_1
         5: instanceof    #2                  // class coursier/params/ResolutionParams
         8: ifeq          15
        11: iconst_1
        12: goto          16
        15: iconst_0
        16: ireturn
      StackMapTable: number_of_entries = 2
        frame_type = 15 /* same */
        frame_type = 64 /* same_locals_1_stack_item */
          stack = [ int ]
      LineNumberTable:
        line 8: 0
      LocalVariableTable:
        Start  Length  Slot  Name   Signature
            0      17     0  this   Lcoursier/params/ResolutionParams;
            0      17     1   obj   Ljava/lang/Object;
    MethodParameters:
      Name                           Flags
      obj                            final

  public boolean equals(java.lang.Object);
    descriptor: (Ljava/lang/Object;)Z
    flags: (0x0001) ACC_PUBLIC
    Code:
      stack=2, locals=15, args_size=2
         0: aload_0
         1: aload_1
         2: if_acmpeq     454
         5: aload_0
         6: aload_1
         7: invokevirtual #472                // Method canEqual:(Ljava/lang/Object;)Z
        10: ifeq          458
        13: aload_1
        14: checkcast     #2                  // class coursier/params/ResolutionParams
        17: astore_2
        18: iconst_1
        19: ifeq          450
        22: aload_0
        23: invokevirtual #420                // Method keepOptionalDependencies:()Z
        26: aload_2
        27: invokevirtual #420                // Method keepOptionalDependencies:()Z
        30: if_icmpne     450
        33: aload_0
        34: invokevirtual #401                // Method maxIterations:()I
        37: aload_2
        38: invokevirtual #401                // Method maxIterations:()I
        41: if_icmpne     450
        44: aload_0
        45: invokevirtual #164                // Method forceVersion:()Lscala/collection/immutable/Map;
        48: aload_2
        49: invokevirtual #164                // Method forceVersion:()Lscala/collection/immutable/Map;
        52: astore_3
        53: dup
        54: ifnonnull     65
        57: pop
        58: aload_3
        59: ifnull        72
        62: goto          450
        65: aload_3
        66: invokevirtual #474                // Method java/lang/Object.equals:(Ljava/lang/Object;)Z
        69: ifeq          450
        72: aload_0
        73: invokevirtual #295                // Method forcedProperties:()Lscala/collection/immutable/Map;
        76: aload_2
        77: invokevirtual #295                // Method forcedProperties:()Lscala/collection/immutable/Map;
        80: astore        4
        82: dup
        83: ifnonnull     95
        86: pop
        87: aload         4
        89: ifnull        103
        92: goto          450
        95: aload         4
        97: invokevirtual #474                // Method java/lang/Object.equals:(Ljava/lang/Object;)Z
       100: ifeq          450
       103: aload_0
       104: invokevirtual #228                // Method profiles:()Lscala/collection/immutable/Set;
       107: aload_2
       108: invokevirtual #228                // Method profiles:()Lscala/collection/immutable/Set;
       111: astore        5
       113: dup
       114: ifnonnull     126
       117: pop
       118: aload         5
       120: ifnull        134
       123: goto          450
       126: aload         5
       128: invokevirtual #474                // Method java/lang/Object.equals:(Ljava/lang/Object;)Z
       131: ifeq          450
       134: aload_0
       135: invokevirtual #210                // Method scalaVersionOpt:()Lscala/Option;
       138: aload_2
       139: invokevirtual #210                // Method scalaVersionOpt:()Lscala/Option;
       142: astore        6
       144: dup
       145: ifnonnull     157
       148: pop
       149: aload         6
       151: ifnull        165
       154: goto          450
       157: aload         6
       159: invokevirtual #474                // Method java/lang/Object.equals:(Ljava/lang/Object;)Z
       162: ifeq          450
       165: aload_0
       166: invokevirtual #177                // Method forceScalaVersionOpt:()Lscala/Option;
       169: aload_2
       170: invokevirtual #177                // Method forceScalaVersionOpt:()Lscala/Option;
       173: astore        7
       175: dup
       176: ifnonnull     188
       179: pop
       180: aload         7
       182: ifnull        196
       185: goto          450
       188: aload         7
       190: invokevirtual #474                // Method java/lang/Object.equals:(Ljava/lang/Object;)Z
       193: ifeq          450
       196: aload_0
       197: invokevirtual #403                // Method typelevel:()Z
       200: aload_2
       201: invokevirtual #403                // Method typelevel:()Z
       204: if_icmpne     450
       207: aload_0
       208: invokevirtual #391                // Method rules:()Lscala/collection/immutable/Seq;
       211: aload_2
       212: invokevirtual #391                // Method rules:()Lscala/collection/immutable/Seq;
       215: astore        8
       217: dup
       218: ifnonnull     230
       221: pop
       222: aload         8
       224: ifnull        238
       227: goto          450
       230: aload         8
       232: invokevirtual #474                // Method java/lang/Object.equals:(Ljava/lang/Object;)Z
       235: ifeq          450
       238: aload_0
       239: invokevirtual #354                // Method reconciliation:()Lscala/collection/immutable/Seq;
       242: aload_2
       243: invokevirtual #354                // Method reconciliation:()Lscala/collection/immutable/Seq;
       246: astore        9
       248: dup
       249: ifnonnull     261
       252: pop
       253: aload         9
       255: ifnull        269
       258: goto          450
       261: aload         9
       263: invokevirtual #474                // Method java/lang/Object.equals:(Ljava/lang/Object;)Z
       266: ifeq          450
       269: aload_0
       270: invokevirtual #286                // Method properties:()Lscala/collection/immutable/Seq;
       273: aload_2
       274: invokevirtual #286                // Method properties:()Lscala/collection/immutable/Seq;
       277: astore        10
       279: dup
       280: ifnonnull     292
       283: pop
       284: aload         10
       286: ifnull        300
       289: goto          450
       292: aload         10
       294: invokevirtual #474                // Method java/lang/Object.equals:(Ljava/lang/Object;)Z
       297: ifeq          450
       300: aload_0
       301: invokevirtual #361                // Method exclusions:()Lscala/collection/immutable/Set;
       304: aload_2
       305: invokevirtual #361                // Method exclusions:()Lscala/collection/immutable/Set;
       308: astore        11
       310: dup
       311: ifnonnull     323
       314: pop
       315: aload         11
       317: ifnull        331
       320: goto          450
       323: aload         11
       325: invokevirtual #474                // Method java/lang/Object.equals:(Ljava/lang/Object;)Z
       328: ifeq          450
       331: aload_0
       332: invokevirtual #405                // Method osInfoOpt:()Lscala/Option;
       335: aload_2
       336: invokevirtual #405                // Method osInfoOpt:()Lscala/Option;
       339: astore        12
       341: dup
       342: ifnonnull     354
       345: pop
       346: aload         12
       348: ifnull        362
       351: goto          450
       354: aload         12
       356: invokevirtual #474                // Method java/lang/Object.equals:(Ljava/lang/Object;)Z
       359: ifeq          450
       362: aload_0
       363: invokevirtual #407                // Method jdkVersionOpt:()Lscala/Option;
       366: aload_2
       367: invokevirtual #407                // Method jdkVersionOpt:()Lscala/Option;
       370: astore        13
       372: dup
       373: ifnonnull     385
       376: pop
       377: aload         13
       379: ifnull        393
       382: goto          450
       385: aload         13
       387: invokevirtual #474                // Method java/lang/Object.equals:(Ljava/lang/Object;)Z
       390: ifeq          450
       393: aload_0
       394: invokevirtual #409                // Method useSystemOsInfo:()Z
       397: aload_2
       398: invokevirtual #409                // Method useSystemOsInfo:()Z
       401: if_icmpne     450
       404: aload_0
       405: invokevirtual #411                // Method useSystemJdkVersion:()Z
       408: aload_2
       409: invokevirtual #411                // Method useSystemJdkVersion:()Z
       412: if_icmpne     450
       415: aload_0
       416: invokevirtual #413                // Method defaultConfiguration:()Ljava/lang/String;
       419: aload_2
       420: invokevirtual #413                // Method defaultConfiguration:()Ljava/lang/String;
       423: astore        14
       425: dup
       426: ifnonnull     438
       429: pop
       430: aload         14
       432: ifnull        446
       435: goto          450
       438: aload         14
       440: invokevirtual #474                // Method java/lang/Object.equals:(Ljava/lang/Object;)Z
       443: ifeq          450
       446: iconst_1
       447: goto          451
       450: iconst_0
       451: ifeq          458
       454: iconst_1
       455: goto          459
       458: iconst_0
       459: ireturn
      StackMapTable: number_of_entries = 29
        frame_type = 255 /* full_frame */
          offset_delta = 65
          locals = [ class coursier/params/ResolutionParams, class java/lang/Object, class coursier/params/ResolutionParams, class scala/collection/immutable/Map ]
          stack = [ class scala/collection/immutable/Map ]
        frame_type = 6 /* same */
        frame_type = 255 /* full_frame */
          offset_delta = 22
          locals = [ class coursier/params/ResolutionParams, class java/lang/Object, class coursier/params/ResolutionParams, class scala/collection/immutable/Map, class scala/collection/immutable/Map ]
          stack = [ class scala/collection/immutable/Map ]
        frame_type = 7 /* same */
        frame_type = 255 /* full_frame */
          offset_delta = 22
          locals = [ class coursier/params/ResolutionParams, class java/lang/Object, class coursier/params/ResolutionParams, class scala/collection/immutable/Map, class scala/collection/immutable/Map, class scala/collection/immutable/Set ]
          stack = [ class scala/collection/immutable/Set ]
        frame_type = 7 /* same */
        frame_type = 255 /* full_frame */
          offset_delta = 22
          locals = [ class coursier/params/ResolutionParams, class java/lang/Object, class coursier/params/ResolutionParams, class scala/collection/immutable/Map, class scala/collection/immutable/Map, class scala/collection/immutable/Set, class scala/Option ]
          stack = [ class scala/Option ]
        frame_type = 7 /* same */
        frame_type = 255 /* full_frame */
          offset_delta = 22
          locals = [ class coursier/params/ResolutionParams, class java/lang/Object, class coursier/params/ResolutionParams, class scala/collection/immutable/Map, class scala/collection/immutable/Map, class scala/collection/immutable/Set, class scala/Option, class scala/Option ]
          stack = [ class scala/Option ]
        frame_type = 7 /* same */
        frame_type = 255 /* full_frame */
          offset_delta = 33
          locals = [ class coursier/params/ResolutionParams, class java/lang/Object, class coursier/params/ResolutionParams, class scala/collection/immutable/Map, class scala/collection/immutable/Map, class scala/collection/immutable/Set, class scala/Option, class scala/Option, class scala/collection/immutable/Seq ]
          stack = [ class scala/collection/immutable/Seq ]
        frame_type = 7 /* same */
        frame_type = 255 /* full_frame */
          offset_delta = 22
          locals = [ class coursier/params/ResolutionParams, class java/lang/Object, class coursier/params/ResolutionParams, class scala/collection/immutable/Map, class scala/collection/immutable/Map, class scala/collection/immutable/Set, class scala/Option, class scala/Option, class scala/collection/immutable/Seq, class scala/collection/immutable/Seq ]
          stack = [ class scala/collection/immutable/Seq ]
        frame_type = 7 /* same */
        frame_type = 255 /* full_frame */
          offset_delta = 22
          locals = [ class coursier/params/ResolutionParams, class java/lang/Object, class coursier/params/ResolutionParams, class scala/collection/immutable/Map, class scala/collection/immutable/Map, class scala/collection/immutable/Set, class scala/Option, class scala/Option, class scala/collection/immutable/Seq, class scala/collection/immutable/Seq, class scala/collection/immutable/Seq ]
          stack = [ class scala/collection/immutable/Seq ]
        frame_type = 7 /* same */
        frame_type = 255 /* full_frame */
          offset_delta = 22
          locals = [ class coursier/params/ResolutionParams, class java/lang/Object, class coursier/params/ResolutionParams, class scala/collection/immutable/Map, class scala/collection/immutable/Map, class scala/collection/immutable/Set, class scala/Option, class scala/Option, class scala/collection/immutable/Seq, class scala/collection/immutable/Seq, class scala/collection/immutable/Seq, class scala/collection/immutable/Set ]
          stack = [ class scala/collection/immutable/Set ]
        frame_type = 7 /* same */
        frame_type = 255 /* full_frame */
          offset_delta = 22
          locals = [ class coursier/params/ResolutionParams, class java/lang/Object, class coursier/params/ResolutionParams, class scala/collection/immutable/Map, class scala/collection/immutable/Map, class scala/collection/immutable/Set, class scala/Option, class scala/Option, class scala/collection/immutable/Seq, class scala/collection/immutable/Seq, class scala/collection/immutable/Seq, class scala/collection/immutable/Set, class scala/Option ]
          stack = [ class scala/Option ]
        frame_type = 7 /* same */
        frame_type = 255 /* full_frame */
          offset_delta = 22
          locals = [ class coursier/params/ResolutionParams, class java/lang/Object, class coursier/params/ResolutionParams, class scala/collection/immutable/Map, class scala/collection/immutable/Map, class scala/collection/immutable/Set, class scala/Option, class scala/Option, class scala/collection/immutable/Seq, class scala/collection/immutable/Seq, class scala/collection/immutable/Seq, class scala/collection/immutable/Set, class scala/Option, class scala/Option ]
          stack = [ class scala/Option ]
        frame_type = 7 /* same */
        frame_type = 255 /* full_frame */
          offset_delta = 44
          locals = [ class coursier/params/ResolutionParams, class java/lang/Object, class coursier/params/ResolutionParams, class scala/collection/immutable/Map, class scala/collection/immutable/Map, class scala/collection/immutable/Set, class scala/Option, class scala/Option, class scala/collection/immutable/Seq, class scala/collection/immutable/Seq, class scala/collection/immutable/Seq, class scala/collection/immutable/Set, class scala/Option, class scala/Option, class java/lang/String ]
          stack = [ class java/lang/String ]
        frame_type = 7 /* same */
        frame_type = 255 /* full_frame */
          offset_delta = 3
          locals = [ class coursier/params/ResolutionParams, class java/lang/Object, class coursier/params/ResolutionParams ]
          stack = []
        frame_type = 64 /* same_locals_1_stack_item */
          stack = [ int ]
        frame_type = 250 /* chop */
          offset_delta = 2
        frame_type = 3 /* same */
        frame_type = 64 /* same_locals_1_stack_item */
          stack = [ int ]
      LineNumberTable:
        line 8: 0
      LocalVariableTable:
        Start  Length  Slot  Name   Signature
           18     433     2 other   Lcoursier/params/ResolutionParams;
            0     460     0  this   Lcoursier/params/ResolutionParams;
            0     460     1   obj   Ljava/lang/Object;
    MethodParameters:
      Name                           Flags
      obj                            final

  public int hashCode();
    descriptor: ()I
    flags: (0x0001) ACC_PUBLIC
    Code:
      stack=4, locals=2, args_size=1
         0: bipush        17
         2: ldc_w         #478                // String ResolutionParams
         5: invokestatic  #484                // Method scala/runtime/Statics.anyHash:(Ljava/lang/Object;)I
         8: iadd
         9: istore_1
        10: bipush        37
        12: iload_1
        13: imul
        14: aload_0
        15: invokevirtual #420                // Method keepOptionalDependencies:()Z
        18: ifeq          27
        21: sipush        1231
        24: goto          30
        27: sipush        1237
        30: iadd
        31: istore_1
        32: bipush        37
        34: iload_1
        35: imul
        36: aload_0
        37: invokevirtual #401                // Method maxIterations:()I
        40: iadd
        41: istore_1
        42: bipush        37
        44: iload_1
        45: imul
        46: aload_0
        47: invokevirtual #164                // Method forceVersion:()Lscala/collection/immutable/Map;
        50: invokestatic  #484                // Method scala/runtime/Statics.anyHash:(Ljava/lang/Object;)I
        53: iadd
        54: istore_1
        55: bipush        37
        57: iload_1
        58: imul
        59: aload_0
        60: invokevirtual #295                // Method forcedProperties:()Lscala/collection/immutable/Map;
        63: invokestatic  #484                // Method scala/runtime/Statics.anyHash:(Ljava/lang/Object;)I
        66: iadd
        67: istore_1
        68: bipush        37
        70: iload_1
        71: imul
        72: aload_0
        73: invokevirtual #228                // Method profiles:()Lscala/collection/immutable/Set;
        76: invokestatic  #484                // Method scala/runtime/Statics.anyHash:(Ljava/lang/Object;)I
        79: iadd
        80: istore_1
        81: bipush        37
        83: iload_1
        84: imul
        85: aload_0
        86: invokevirtual #210                // Method scalaVersionOpt:()Lscala/Option;
        89: invokestatic  #484                // Method scala/runtime/Statics.anyHash:(Ljava/lang/Object;)I
        92: iadd
        93: istore_1
        94: bipush        37
        96: iload_1
        97: imul
        98: aload_0
        99: invokevirtual #177                // Method forceScalaVersionOpt:()Lscala/Option;
       102: invokestatic  #484                // Method scala/runtime/Statics.anyHash:(Ljava/lang/Object;)I
       105: iadd
       106: istore_1
       107: bipush        37
       109: iload_1
       110: imul
       111: aload_0
       112: invokevirtual #403                // Method typelevel:()Z
       115: ifeq          124
       118: sipush        1231
       121: goto          127
       124: sipush        1237
       127: iadd
       128: istore_1
       129: bipush        37
       131: iload_1
       132: imul
       133: aload_0
       134: invokevirtual #391                // Method rules:()Lscala/collection/immutable/Seq;
       137: invokestatic  #484                // Method scala/runtime/Statics.anyHash:(Ljava/lang/Object;)I
       140: iadd
       141: istore_1
       142: bipush        37
       144: iload_1
       145: imul
       146: aload_0
       147: invokevirtual #354                // Method reconciliation:()Lscala/collection/immutable/Seq;
       150: invokestatic  #484                // Method scala/runtime/Statics.anyHash:(Ljava/lang/Object;)I
       153: iadd
       154: istore_1
       155: bipush        37
       157: iload_1
       158: imul
       159: aload_0
       160: invokevirtual #286                // Method properties:()Lscala/collection/immutable/Seq;
       163: invokestatic  #484                // Method scala/runtime/Statics.anyHash:(Ljava/lang/Object;)I
       166: iadd
       167: istore_1
       168: bipush        37
       170: iload_1
       171: imul
       172: aload_0
       173: invokevirtual #361                // Method exclusions:()Lscala/collection/immutable/Set;
       176: invokestatic  #484                // Method scala/runtime/Statics.anyHash:(Ljava/lang/Object;)I
       179: iadd
       180: istore_1
       181: bipush        37
       183: iload_1
       184: imul
       185: aload_0
       186: invokevirtual #405                // Method osInfoOpt:()Lscala/Option;
       189: invokestatic  #484                // Method scala/runtime/Statics.anyHash:(Ljava/lang/Object;)I
       192: iadd
       193: istore_1
       194: bipush        37
       196: iload_1
       197: imul
       198: aload_0
       199: invokevirtual #407                // Method jdkVersionOpt:()Lscala/Option;
       202: invokestatic  #484                // Method scala/runtime/Statics.anyHash:(Ljava/lang/Object;)I
       205: iadd
       206: istore_1
       207: bipush        37
       209: iload_1
       210: imul
       211: aload_0
       212: invokevirtual #409                // Method useSystemOsInfo:()Z
       215: ifeq          224
       218: sipush        1231
       221: goto          227
       224: sipush        1237
       227: iadd
       228: istore_1
       229: bipush        37
       231: iload_1
       232: imul
       233: aload_0
       234: invokevirtual #411                // Method useSystemJdkVersion:()Z
       237: ifeq          246
       240: sipush        1231
       243: goto          249
       246: sipush        1237
       249: iadd
       250: istore_1
       251: bipush        37
       253: iload_1
       254: imul
       255: new           #459                // class coursier/core/Configuration
       258: dup
       259: aload_0
       260: invokevirtual #413                // Method defaultConfiguration:()Ljava/lang/String;
       263: invokespecial #460                // Method coursier/core/Configuration."<init>":(Ljava/lang/String;)V
       266: invokestatic  #484                // Method scala/runtime/Statics.anyHash:(Ljava/lang/Object;)I
       269: iadd
       270: istore_1
       271: bipush        37
       273: iload_1
       274: imul
       275: ireturn
      StackMapTable: number_of_entries = 8
        frame_type = 255 /* full_frame */
          offset_delta = 27
          locals = [ class coursier/params/ResolutionParams, int ]
          stack = [ int ]
        frame_type = 255 /* full_frame */
          offset_delta = 2
          locals = [ class coursier/params/ResolutionParams, int ]
          stack = [ int, int ]
        frame_type = 247 /* same_locals_1_stack_item_frame_extended */
          offset_delta = 93
          stack = [ int ]
        frame_type = 255 /* full_frame */
          offset_delta = 2
          locals = [ class coursier/params/ResolutionParams, int ]
          stack = [ int, int ]
        frame_type = 247 /* same_locals_1_stack_item_frame_extended */
          offset_delta = 96
          stack = [ int ]
        frame_type = 255 /* full_frame */
          offset_delta = 2
          locals = [ class coursier/params/ResolutionParams, int ]
          stack = [ int, int ]
        frame_type = 82 /* same_locals_1_stack_item */
          stack = [ int ]
        frame_type = 255 /* full_frame */
          offset_delta = 2
          locals = [ class coursier/params/ResolutionParams, int ]
          stack = [ int, int ]
      LineNumberTable:
        line 8: 0
      LocalVariableTable:
        Start  Length  Slot  Name   Signature
           10     265     1  code   I
            0     276     0  this   Lcoursier/params/ResolutionParams;

  private scala.Tuple17<java.lang.Object, java.lang.Object, scala.collection.immutable.Map<coursier.core.Module, java.lang.String>, scala.collection.immutable.Map<java.lang.String, java.lang.String>, scala.collection.immutable.Set<java.lang.String>, scala.Option<java.lang.String>, scala.Option<java.lang.Object>, java.lang.Object, scala.collection.immutable.Seq<scala.Tuple2<coursier.params.rule.Rule, coursier.params.rule.RuleResolution>>, scala.collection.immutable.Seq<scala.Tuple2<coursier.util.ModuleMatchers, coursier.core.Reconciliation>>, scala.collection.immutable.Seq<scala.Tuple2<java.lang.String, java.lang.String>>, scala.collection.immutable.Set<scala.Tuple2<coursier.core.Organization, coursier.core.ModuleName>>, scala.Option<coursier.core.Activation$Os>, scala.Option<coursier.core.Version>, java.lang.Object, java.lang.Object, coursier.core.Configuration> tuple();
    descriptor: ()Lscala/Tuple17;
    flags: (0x0002) ACC_PRIVATE
    Code:
      stack=21, locals=1, args_size=1
         0: new           #490                // class scala/Tuple17
         3: dup
         4: aload_0
         5: invokevirtual #420                // Method keepOptionalDependencies:()Z
         8: invokestatic  #320                // Method scala/runtime/BoxesRunTime.boxToBoolean:(Z)Ljava/lang/Boolean;
        11: aload_0
        12: invokevirtual #401                // Method maxIterations:()I
        15: invokestatic  #494                // Method scala/runtime/BoxesRunTime.boxToInteger:(I)Ljava/lang/Integer;
        18: aload_0
        19: invokevirtual #164                // Method forceVersion:()Lscala/collection/immutable/Map;
        22: aload_0
        23: invokevirtual #295                // Method forcedProperties:()Lscala/collection/immutable/Map;
        26: aload_0
        27: invokevirtual #228                // Method profiles:()Lscala/collection/immutable/Set;
        30: aload_0
        31: invokevirtual #210                // Method scalaVersionOpt:()Lscala/Option;
        34: aload_0
        35: invokevirtual #177                // Method forceScalaVersionOpt:()Lscala/Option;
        38: aload_0
        39: invokevirtual #403                // Method typelevel:()Z
        42: invokestatic  #320                // Method scala/runtime/BoxesRunTime.boxToBoolean:(Z)Ljava/lang/Boolean;
        45: aload_0
        46: invokevirtual #391                // Method rules:()Lscala/collection/immutable/Seq;
        49: aload_0
        50: invokevirtual #354                // Method reconciliation:()Lscala/collection/immutable/Seq;
        53: aload_0
        54: invokevirtual #286                // Method properties:()Lscala/collection/immutable/Seq;
        57: aload_0
        58: invokevirtual #361                // Method exclusions:()Lscala/collection/immutable/Set;
        61: aload_0
        62: invokevirtual #405                // Method osInfoOpt:()Lscala/Option;
        65: aload_0
        66: invokevirtual #407                // Method jdkVersionOpt:()Lscala/Option;
        69: aload_0
        70: invokevirtual #409                // Method useSystemOsInfo:()Z
        73: invokestatic  #320                // Method scala/runtime/BoxesRunTime.boxToBoolean:(Z)Ljava/lang/Boolean;
        76: aload_0
        77: invokevirtual #411                // Method useSystemJdkVersion:()Z
        80: invokestatic  #320                // Method scala/runtime/BoxesRunTime.boxToBoolean:(Z)Ljava/lang/Boolean;
        83: new           #459                // class coursier/core/Configuration
        86: dup
        87: aload_0
        88: invokevirtual #413                // Method defaultConfiguration:()Ljava/lang/String;
        91: invokespecial #460                // Method coursier/core/Configuration."<init>":(Ljava/lang/String;)V
        94: invokespecial #497                // Method scala/Tuple17."<init>":(Ljava/lang/Object;Ljava/lang/Object;Ljava/lang/Object;Ljava/lang/Object;Ljava/lang/Object;Ljava/lang/Object;Ljava/lang/Object;Ljava/lang/Object;Ljava/lang/Object;Ljava/lang/Object;Ljava/lang/Object;Ljava/lang/Object;Ljava/lang/Object;Ljava/lang/Object;Ljava/lang/Object;Ljava/lang/Object;Ljava/lang/Object;)V
        97: areturn
      LineNumberTable:
        line 8: 0
      LocalVariableTable:
        Start  Length  Slot  Name   Signature
            0      98     0  this   Lcoursier/params/ResolutionParams;
    Signature: #488                         // ()Lscala/Tuple17<Ljava/lang/Object;Ljava/lang/Object;Lscala/collection/immutable/Map<Lcoursier/core/Module;Ljava/lang/String;>;Lscala/collection/immutable/Map<Ljava/lang/String;Ljava/lang/String;>;Lscala/collection/immutable/Set<Ljava/lang/String;>;Lscala/Option<Ljava/lang/String;>;Lscala/Option<Ljava/lang/Object;>;Ljava/lang/Object;Lscala/collection/immutable/Seq<Lscala/Tuple2<Lcoursier/params/rule/Rule;Lcoursier/params/rule/RuleResolution;>;>;Lscala/collection/immutable/Seq<Lscala/Tuple2<Lcoursier/util/ModuleMatchers;Lcoursier/core/Reconciliation;>;>;Lscala/collection/immutable/Seq<Lscala/Tuple2<Ljava/lang/String;Ljava/lang/String;>;>;Lscala/collection/immutable/Set<Lscala/Tuple2<Lcoursier/core/Organization;Lcoursier/core/ModuleName;>;>;Lscala/Option<Lcoursier/core/Activation$Os;>;Lscala/Option<Lcoursier/core/Version;>;Ljava/lang/Object;Ljava/lang/Object;Lcoursier/core/Configuration;>;

  public java.lang.String productPrefix();
    descriptor: ()Ljava/lang/String;
    flags: (0x0001) ACC_PUBLIC
    Code:
      stack=1, locals=1, args_size=1
         0: ldc_w         #478                // String ResolutionParams
         3: areturn
      LineNumberTable:
        line 8: 0
      LocalVariableTable:
        Start  Length  Slot  Name   Signature
            0       4     0  this   Lcoursier/params/ResolutionParams;

  public int productArity();
    descriptor: ()I
    flags: (0x0001) ACC_PUBLIC
    Code:
      stack=1, locals=1, args_size=1
         0: bipush        17
         2: ireturn
      LineNumberTable:
        line 8: 0
      LocalVariableTable:
        Start  Length  Slot  Name   Signature
            0       3     0  this   Lcoursier/params/ResolutionParams;

  public java.lang.Object productElement(int);
    descriptor: (I)Ljava/lang/Object;
    flags: (0x0001) ACC_PUBLIC
    Code:
      stack=3, locals=3, args_size=2
         0: iload_1
         1: istore_2
         2: iload_2
         3: tableswitch   { // 0 to 16
                       0: 84
                       1: 94
                       2: 104
                       3: 111
                       4: 118
                       5: 125
                       6: 132
                       7: 139
                       8: 149
                       9: 156
                      10: 163
                      11: 170
                      12: 177
                      13: 184
                      14: 191
                      15: 201
                      16: 211
                 default: 225
            }
        84: aload_0
        85: invokevirtual #420                // Method keepOptionalDependencies:()Z
        88: invokestatic  #320                // Method scala/runtime/BoxesRunTime.boxToBoolean:(Z)Ljava/lang/Boolean;
        91: goto          240
        94: aload_0
        95: invokevirtual #401                // Method maxIterations:()I
        98: invokestatic  #494                // Method scala/runtime/BoxesRunTime.boxToInteger:(I)Ljava/lang/Integer;
       101: goto          240
       104: aload_0
       105: invokevirtual #164                // Method forceVersion:()Lscala/collection/immutable/Map;
       108: goto          240
       111: aload_0
       112: invokevirtual #295                // Method forcedProperties:()Lscala/collection/immutable/Map;
       115: goto          240
       118: aload_0
       119: invokevirtual #228                // Method profiles:()Lscala/collection/immutable/Set;
       122: goto          240
       125: aload_0
       126: invokevirtual #210                // Method scalaVersionOpt:()Lscala/Option;
       129: goto          240
       132: aload_0
       133: invokevirtual #177                // Method forceScalaVersionOpt:()Lscala/Option;
       136: goto          240
       139: aload_0
       140: invokevirtual #403                // Method typelevel:()Z
       143: invokestatic  #320                // Method scala/runtime/BoxesRunTime.boxToBoolean:(Z)Ljava/lang/Boolean;
       146: goto          240
       149: aload_0
       150: invokevirtual #391                // Method rules:()Lscala/collection/immutable/Seq;
       153: goto          240
       156: aload_0
       157: invokevirtual #354                // Method reconciliation:()Lscala/collection/immutable/Seq;
       160: goto          240
       163: aload_0
       164: invokevirtual #286                // Method properties:()Lscala/collection/immutable/Seq;
       167: goto          240
       170: aload_0
       171: invokevirtual #361                // Method exclusions:()Lscala/collection/immutable/Set;
       174: goto          240
       177: aload_0
       178: invokevirtual #405                // Method osInfoOpt:()Lscala/Option;
       181: goto          240
       184: aload_0
       185: invokevirtual #407                // Method jdkVersionOpt:()Lscala/Option;
       188: goto          240
       191: aload_0
       192: invokevirtual #409                // Method useSystemOsInfo:()Z
       195: invokestatic  #320                // Method scala/runtime/BoxesRunTime.boxToBoolean:(Z)Ljava/lang/Boolean;
       198: goto          240
       201: aload_0
       202: invokevirtual #411                // Method useSystemJdkVersion:()Z
       205: invokestatic  #320                // Method scala/runtime/BoxesRunTime.boxToBoolean:(Z)Ljava/lang/Boolean;
       208: goto          240
       211: new           #459                // class coursier/core/Configuration
       214: dup
       215: aload_0
       216: invokevirtual #413                // Method defaultConfiguration:()Ljava/lang/String;
       219: invokespecial #460                // Method coursier/core/Configuration."<init>":(Ljava/lang/String;)V
       222: goto          240
       225: new           #504                // class java/lang/IndexOutOfBoundsException
       228: dup
       229: iload_2
       230: invokestatic  #494                // Method scala/runtime/BoxesRunTime.boxToInteger:(I)Ljava/lang/Integer;
       233: invokevirtual #505                // Method java/lang/Object.toString:()Ljava/lang/String;
       236: invokespecial #506                // Method java/lang/IndexOutOfBoundsException."<init>":(Ljava/lang/String;)V
       239: athrow
       240: areturn
      StackMapTable: number_of_entries = 19
        frame_type = 252 /* append */
          offset_delta = 84
          locals = [ int ]
        frame_type = 9 /* same */
        frame_type = 9 /* same */
        frame_type = 6 /* same */
        frame_type = 6 /* same */
        frame_type = 6 /* same */
        frame_type = 6 /* same */
        frame_type = 6 /* same */
        frame_type = 9 /* same */
        frame_type = 6 /* same */
        frame_type = 6 /* same */
        frame_type = 6 /* same */
        frame_type = 6 /* same */
        frame_type = 6 /* same */
        frame_type = 6 /* same */
        frame_type = 9 /* same */
        frame_type = 9 /* same */
        frame_type = 13 /* same */
        frame_type = 78 /* same_locals_1_stack_item */
          stack = [ class java/lang/Object ]
      LineNumberTable:
        line 8: 0
      LocalVariableTable:
        Start  Length  Slot  Name   Signature
            0     241     0  this   Lcoursier/params/ResolutionParams;
            0     241     1     n   I
    MethodParameters:
      Name                           Flags
      n                              final

  public java.lang.String productElementName(int);
    descriptor: (I)Ljava/lang/String;
    flags: (0x0001) ACC_PUBLIC
    Code:
      stack=3, locals=3, args_size=2
         0: iload_1
         1: istore_2
         2: iload_2
         3: tableswitch   { // 0 to 16
                       0: 84
                       1: 90
                       2: 96
                       3: 102
                       4: 108
                       5: 114
                       6: 120
                       7: 126
                       8: 132
                       9: 138
                      10: 144
                      11: 150
                      12: 156
                      13: 162
                      14: 168
                      15: 174
                      16: 180
                 default: 186
            }
        84: ldc_w         #508                // String keepOptionalDependencies
        87: goto          201
        90: ldc_w         #509                // String maxIterations
        93: goto          201
        96: ldc_w         #510                // String forceVersion
        99: goto          201
       102: ldc_w         #511                // String forcedProperties
       105: goto          201
       108: ldc_w         #512                // String profiles
       111: goto          201
       114: ldc_w         #513                // String scalaVersionOpt
       117: goto          201
       120: ldc_w         #514                // String forceScalaVersionOpt
       123: goto          201
       126: ldc_w         #515                // String typelevel
       129: goto          201
       132: ldc_w         #516                // String rules
       135: goto          201
       138: ldc_w         #517                // String reconciliation
       141: goto          201
       144: ldc_w         #518                // String properties
       147: goto          201
       150: ldc_w         #519                // String exclusions
       153: goto          201
       156: ldc_w         #520                // String osInfoOpt
       159: goto          201
       162: ldc_w         #521                // String jdkVersionOpt
       165: goto          201
       168: ldc_w         #522                // String useSystemOsInfo
       171: goto          201
       174: ldc_w         #523                // String useSystemJdkVersion
       177: goto          201
       180: ldc_w         #524                // String defaultConfiguration
       183: goto          201
       186: new           #504                // class java/lang/IndexOutOfBoundsException
       189: dup
       190: iload_2
       191: invokestatic  #494                // Method scala/runtime/BoxesRunTime.boxToInteger:(I)Ljava/lang/Integer;
       194: invokevirtual #505                // Method java/lang/Object.toString:()Ljava/lang/String;
       197: invokespecial #506                // Method java/lang/IndexOutOfBoundsException."<init>":(Ljava/lang/String;)V
       200: athrow
       201: areturn
      StackMapTable: number_of_entries = 19
        frame_type = 252 /* append */
          offset_delta = 84
          locals = [ int ]
        frame_type = 5 /* same */
        frame_type = 5 /* same */
        frame_type = 5 /* same */
        frame_type = 5 /* same */
        frame_type = 5 /* same */
        frame_type = 5 /* same */
        frame_type = 5 /* same */
        frame_type = 5 /* same */
        frame_type = 5 /* same */
        frame_type = 5 /* same */
        frame_type = 5 /* same */
        frame_type = 5 /* same */
        frame_type = 5 /* same */
        frame_type = 5 /* same */
        frame_type = 5 /* same */
        frame_type = 5 /* same */
        frame_type = 5 /* same */
        frame_type = 78 /* same_locals_1_stack_item */
          stack = [ class java/lang/String ]
      LineNumberTable:
        line 8: 0
      LocalVariableTable:
        Start  Length  Slot  Name   Signature
            0     202     0  this   Lcoursier/params/ResolutionParams;
            0     202     1     n   I
    MethodParameters:
      Name                           Flags
      n                              final

  public static final boolean $anonfun$doForceScalaVersion$1(coursier.params.ResolutionParams);
    descriptor: (Lcoursier/params/ResolutionParams;)Z
    flags: (0x1019) ACC_PUBLIC, ACC_STATIC, ACC_FINAL, ACC_SYNTHETIC
    Code:
      stack=1, locals=1, args_size=1
         0: aload_0
         1: invokevirtual #210                // Method scalaVersionOpt:()Lscala/Option;
         4: invokevirtual #528                // Method scala/Option.nonEmpty:()Z
         7: ireturn
      LineNumberTable:
        line 33: 0
      LocalVariableTable:
        Start  Length  Slot  Name   Signature
            0       8     0 $this   Lcoursier/params/ResolutionParams;
    MethodParameters:
      Name                           Flags
      $this                          final synthetic

  public static final java.lang.String $anonfun$selectedScalaVersion$1();
    descriptor: ()Ljava/lang/String;
    flags: (0x1019) ACC_PUBLIC, ACC_STATIC, ACC_FINAL, ACC_SYNTHETIC
    Code:
      stack=1, locals=0, args_size=0
         0: getstatic     #533                // Field coursier/internal/Defaults$.MODULE$:Lcoursier/internal/Defaults$;
         3: invokevirtual #535                // Method coursier/internal/Defaults$.scalaVersion:()Ljava/lang/String;
         6: areturn
      LineNumberTable:
        line 37: 0

  public static final scala.Tuple2 $anonfun$actualReconciliation$1(scala.Tuple2);
    descriptor: (Lscala/Tuple2;)Lscala/Tuple2;
    flags: (0x1019) ACC_PUBLIC, ACC_STATIC, ACC_FINAL, ACC_SYNTHETIC
    Code:
      stack=4, locals=6, args_size=1
         0: aload_0
         1: astore_3
         2: aload_3
         3: ifnull        90
         6: aload_3
         7: invokevirtual #541                // Method scala/Tuple2._1:()Ljava/lang/Object;
        10: checkcast     #543                // class coursier/util/ModuleMatchers
        13: astore        4
        15: aload_3
        16: invokevirtual #546                // Method scala/Tuple2._2:()Ljava/lang/Object;
        19: checkcast     #21                 // class coursier/core/Reconciliation
        22: astore        5
        24: getstatic     #549                // Field coursier/core/Reconciliation$Strict$.MODULE$:Lcoursier/core/Reconciliation$Strict$;
        27: aload         5
        29: invokevirtual #474                // Method java/lang/Object.equals:(Ljava/lang/Object;)Z
        32: ifeq          40
        35: iconst_1
        36: istore_2
        37: goto          67
        40: goto          43
        43: getstatic     #552                // Field coursier/core/Reconciliation$SemVer$.MODULE$:Lcoursier/core/Reconciliation$SemVer$;
        46: aload         5
        48: invokevirtual #474                // Method java/lang/Object.equals:(Ljava/lang/Object;)Z
        51: ifeq          59
        54: iconst_1
        55: istore_2
        56: goto          67
        59: goto          62
        62: iconst_0
        63: istore_2
        64: goto          67
        67: iload_2
        68: ifeq          87
        71: new           #538                // class scala/Tuple2
        74: dup
        75: aload         4
        77: getstatic     #555                // Field coursier/core/Reconciliation$Default$.MODULE$:Lcoursier/core/Reconciliation$Default$;
        80: invokespecial #558                // Method scala/Tuple2."<init>":(Ljava/lang/Object;Ljava/lang/Object;)V
        83: astore_1
        84: goto          98
        87: goto          93
        90: goto          93
        93: aload_3
        94: astore_1
        95: goto          98
        98: aload_1
        99: areturn
      StackMapTable: number_of_entries = 9
        frame_type = 255 /* full_frame */
          offset_delta = 40
          locals = [ class scala/Tuple2, top, top, class scala/Tuple2, class coursier/util/ModuleMatchers, class coursier/core/Reconciliation ]
          stack = []
        frame_type = 2 /* same */
        frame_type = 15 /* same */
        frame_type = 2 /* same */
        frame_type = 255 /* full_frame */
          offset_delta = 4
          locals = [ class scala/Tuple2, top, int, class scala/Tuple2, class coursier/util/ModuleMatchers, class coursier/core/Reconciliation ]
          stack = []
        frame_type = 19 /* same */
        frame_type = 255 /* full_frame */
          offset_delta = 2
          locals = [ class scala/Tuple2, top, top, class scala/Tuple2 ]
          stack = []
        frame_type = 2 /* same */
        frame_type = 255 /* full_frame */
          offset_delta = 4
          locals = [ class scala/Tuple2, class scala/Tuple2, top, class scala/Tuple2 ]
          stack = []
      LineNumberTable:
        line 70: 0
        line 71: 2
        line 72: 93
        line 70: 98
      LocalVariableTable:
        Start  Length  Slot  Name   Signature
           15      75     4     m   Lcoursier/util/ModuleMatchers;
            0     100     0  x0$1   Lscala/Tuple2;
    MethodParameters:
      Name                           Flags
      x0$1                           final

  public coursier.params.ResolutionParams(boolean, int, scala.collection.immutable.Map<coursier.core.Module, java.lang.String>, scala.collection.immutable.Map<java.lang.String, java.lang.String>, scala.collection.immutable.Set<java.lang.String>, scala.Option<java.lang.String>, scala.Option<java.lang.Object>, boolean, scala.collection.immutable.Seq<scala.Tuple2<coursier.params.rule.Rule, coursier.params.rule.RuleResolution>>, scala.collection.immutable.Seq<scala.Tuple2<coursier.util.ModuleMatchers, coursier.core.Reconciliation>>, scala.collection.immutable.Seq<scala.Tuple2<java.lang.String, java.lang.String>>, scala.collection.immutable.Set<scala.Tuple2<coursier.core.Organization, coursier.core.ModuleName>>, scala.Option<coursier.core.Activation$Os>, scala.Option<coursier.core.Version>, boolean, boolean, java.lang.String);
    descriptor: (ZILscala/collection/immutable/Map;Lscala/collection/immutable/Map;Lscala/collection/immutable/Set;Lscala/Option;Lscala/Option;ZLscala/collection/immutable/Seq;Lscala/collection/immutable/Seq;Lscala/collection/immutable/Seq;Lscala/collection/immutable/Set;Lscala/Option;Lscala/Option;ZZLjava/lang/String;)V
    flags: (0x0001) ACC_PUBLIC
    Code:
      stack=2, locals=18, args_size=18
         0: aload_0
         1: iload_1
         2: putfield      #109                // Field keepOptionalDependencies:Z
         5: aload_0
         6: iload_2
         7: putfield      #112                // Field maxIterations:I
        10: aload_0
        11: aload_3
        12: putfield      #116                // Field forceVersion:Lscala/collection/immutable/Map;
        15: aload_0
        16: aload         4
        18: putfield      #119                // Field forcedProperties:Lscala/collection/immutable/Map;
        21: aload_0
        22: aload         5
        24: putfield      #123                // Field profiles:Lscala/collection/immutable/Set;
        27: aload_0
        28: aload         6
        30: putfield      #127                // Field scalaVersionOpt:Lscala/Option;
        33: aload_0
        34: aload         7
        36: putfield      #130                // Field forceScalaVersionOpt:Lscala/Option;
        39: aload_0
        40: iload         8
        42: putfield      #132                // Field typelevel:Z
        45: aload_0
        46: aload         9
        48: putfield      #136                // Field rules:Lscala/collection/immutable/Seq;
        51: aload_0
        52: aload         10
        54: putfield      #139                // Field reconciliation:Lscala/collection/immutable/Seq;
        57: aload_0
        58: aload         11
        60: putfield      #142                // Field properties:Lscala/collection/immutable/Seq;
        63: aload_0
        64: aload         12
        66: putfield      #145                // Field exclusions:Lscala/collection/immutable/Set;
        69: aload_0
        70: aload         13
        72: putfield      #148                // Field osInfoOpt:Lscala/Option;
        75: aload_0
        76: aload         14
        78: putfield      #151                // Field jdkVersionOpt:Lscala/Option;
        81: aload_0
        82: iload         15
        84: putfield      #153                // Field useSystemOsInfo:Z
        87: aload_0
        88: iload         16
        90: putfield      #155                // Field useSystemJdkVersion:Z
        93: aload_0
        94: aload         17
        96: putfield      #158                // Field defaultConfiguration:Ljava/lang/String;
        99: aload_0
       100: invokespecial #565                // Method java/lang/Object."<init>":()V
       103: aload_0
       104: invokestatic  #569                // InterfaceMethod scala/Product.$init$:(Lscala/Product;)V
       107: return
      LineNumberTable:
        line 8: 0
        line 86: 99
        line 8: 107
      LocalVariableTable:
        Start  Length  Slot  Name   Signature
            0     108     0  this   Lcoursier/params/ResolutionParams;
            0     108     1 keepOptionalDependencies   Z
            0     108     2 maxIterations   I
            0     108     3 forceVersion   Lscala/collection/immutable/Map;
            0     108     4 forcedProperties   Lscala/collection/immutable/Map;
            0     108     5 profiles   Lscala/collection/immutable/Set;
            0     108     6 scalaVersionOpt   Lscala/Option;
            0     108     7 forceScalaVersionOpt   Lscala/Option;
            0     108     8 typelevel   Z
            0     108     9 rules   Lscala/collection/immutable/Seq;
            0     108    10 reconciliation   Lscala/collection/immutable/Seq;
            0     108    11 properties   Lscala/collection/immutable/Seq;
            0     108    12 exclusions   Lscala/collection/immutable/Set;
            0     108    13 osInfoOpt   Lscala/Option;
            0     108    14 jdkVersionOpt   Lscala/Option;
            0     108    15 useSystemOsInfo   Z
            0     108    16 useSystemJdkVersion   Z
            0     108    17 defaultConfiguration   Ljava/lang/String;
    Signature: #562                         // (ZILscala/collection/immutable/Map<Lcoursier/core/Module;Ljava/lang/String;>;Lscala/collection/immutable/Map<Ljava/lang/String;Ljava/lang/String;>;Lscala/collection/immutable/Set<Ljava/lang/String;>;Lscala/Option<Ljava/lang/String;>;Lscala/Option<Ljava/lang/Object;>;ZLscala/collection/immutable/Seq<Lscala/Tuple2<Lcoursier/params/rule/Rule;Lcoursier/params/rule/RuleResolution;>;>;Lscala/collection/immutable/Seq<Lscala/Tuple2<Lcoursier/util/ModuleMatchers;Lcoursier/core/Reconciliation;>;>;Lscala/collection/immutable/Seq<Lscala/Tuple2<Ljava/lang/String;Ljava/lang/String;>;>;Lscala/collection/immutable/Set<Lscala/Tuple2<Lcoursier/core/Organization;Lcoursier/core/ModuleName;>;>;Lscala/Option<Lcoursier/core/Activation$Os;>;Lscala/Option<Lcoursier/core/Version;>;ZZLjava/lang/String;)V
    MethodParameters:
      Name                           Flags
      keepOptionalDependencies       final
      maxIterations                  final
      forceVersion                   final
      forcedProperties               final
      profiles                       final
      scalaVersionOpt                final
      forceScalaVersionOpt           final
      typelevel                      final
      rules                          final
      reconciliation                 final
      properties                     final
      exclusions                     final
      osInfoOpt                      final
      jdkVersionOpt                  final
      useSystemOsInfo                final
      useSystemJdkVersion            final
      defaultConfiguration           final

  public coursier.params.ResolutionParams();
    descriptor: ()V
    flags: (0x0001) ACC_PUBLIC
    Code:
      stack=18, locals=1, args_size=1
         0: aload_0
         1: iconst_0
         2: sipush        200
         5: getstatic     #251                // Field scala/Predef$.MODULE$:Lscala/Predef$;
         8: invokevirtual #573                // Method scala/Predef$.Map:()Lscala/collection/immutable/Map$;
        11: invokevirtual #578                // Method scala/collection/immutable/Map$.empty:()Lscala/collection/immutable/Map;
        14: getstatic     #251                // Field scala/Predef$.MODULE$:Lscala/Predef$;
        17: invokevirtual #573                // Method scala/Predef$.Map:()Lscala/collection/immutable/Map$;
        20: invokevirtual #578                // Method scala/collection/immutable/Map$.empty:()Lscala/collection/immutable/Map;
        23: getstatic     #251                // Field scala/Predef$.MODULE$:Lscala/Predef$;
        26: invokevirtual #582                // Method scala/Predef$.Set:()Lscala/collection/immutable/Set$;
        29: invokevirtual #586                // Method scala/collection/immutable/Set$.empty:()Lscala/collection/immutable/Set;
        32: getstatic     #591                // Field scala/None$.MODULE$:Lscala/None$;
        35: getstatic     #591                // Field scala/None$.MODULE$:Lscala/None$;
        38: iconst_0
        39: getstatic     #596                // Field scala/collection/immutable/Seq$.MODULE$:Lscala/collection/immutable/Seq$;
        42: invokevirtual #599                // Method scala/collection/immutable/Seq$.empty:()Lscala/collection/SeqOps;
        45: checkcast     #270                // class scala/collection/immutable/Seq
        48: getstatic     #264                // Field scala/collection/immutable/Nil$.MODULE$:Lscala/collection/immutable/Nil$;
        51: getstatic     #264                // Field scala/collection/immutable/Nil$.MODULE$:Lscala/collection/immutable/Nil$;
        54: getstatic     #251                // Field scala/Predef$.MODULE$:Lscala/Predef$;
        57: invokevirtual #582                // Method scala/Predef$.Set:()Lscala/collection/immutable/Set$;
        60: invokevirtual #586                // Method scala/collection/immutable/Set$.empty:()Lscala/collection/immutable/Set;
        63: getstatic     #591                // Field scala/None$.MODULE$:Lscala/None$;
        66: getstatic     #591                // Field scala/None$.MODULE$:Lscala/None$;
        69: iconst_1
        70: iconst_1
        71: getstatic     #604                // Field coursier/core/Configuration$.MODULE$:Lcoursier/core/Configuration$;
        74: invokevirtual #607                // Method coursier/core/Configuration$.defaultCompile:()Ljava/lang/String;
        77: invokespecial #416                // Method "<init>":(ZILscala/collection/immutable/Map;Lscala/collection/immutable/Map;Lscala/collection/immutable/Set;Lscala/Option;Lscala/Option;ZLscala/collection/immutable/Seq;Lscala/collection/immutable/Seq;Lscala/collection/immutable/Seq;Lscala/collection/immutable/Set;Lscala/Option;Lscala/Option;ZZLjava/lang/String;)V
        80: return
      LineNumberTable:
        line 8: 0
        line 9: 1
        line 10: 2
        line 11: 5
        line 12: 14
        line 13: 23
        line 14: 32
        line 15: 35
        line 16: 38
        line 17: 39
        line 18: 48
        line 19: 51
        line 20: 54
        line 21: 63
        line 22: 66
        line 23: 69
        line 24: 70
        line 25: 71
        line 8: 80
      LocalVariableTable:
        Start  Length  Slot  Name   Signature
            0      81     0  this   Lcoursier/params/ResolutionParams;

  private static java.lang.Object $deserializeLambda$(java.lang.invoke.SerializedLambda);
    descriptor: (Ljava/lang/invoke/SerializedLambda;)Ljava/lang/Object;
    flags: (0x100a) ACC_PRIVATE, ACC_STATIC, ACC_SYNTHETIC
    Code:
      stack=1, locals=1, args_size=1
         0: aload_0
         1: invokedynamic #619,  0            // InvokeDynamic #3:lambdaDeserialize:(Ljava/lang/invoke/SerializedLambda;)Ljava/lang/Object;
         6: areturn
}
InnerClasses:
  public static final #17= #14 of #16;    // Os=class coursier/core/Activation$Os of class coursier/core/Activation
  public static #22= #19 of #21;          // =class coursier/core/Reconciliation$Default$ of class coursier/core/Reconciliation
  public static #22= #24 of #21;          // =class coursier/core/Reconciliation$SemVer$ of class coursier/core/Reconciliation
  public static #22= #26 of #21;          // =class coursier/core/Reconciliation$Strict$ of class coursier/core/Reconciliation
  public final #28;                       // class coursier/params/ResolutionParams$$anonfun$1
  public static #22= #30 of #32;          // =class coursier/params/rule/RuleResolution$TryResolve$ of class coursier/params/rule/RuleResolution
  public static final #37= #34 of #36;    // Lookup=class java/lang/invoke/MethodHandles$Lookup of class java/lang/invoke/MethodHandles
  public static #22= #39 of #41;          // =class scala/Predef$ArrowAssoc$ of class scala/Predef
SourceFile: "ResolutionParams.scala"
RuntimeVisibleAnnotations:
  0: #10(#11=s#12)
    scala.reflect.ScalaSignature(
      bytes="\u0006\u0005\rmd\u0001\u0002,X\u0005qC\u0001B\u001d\u0001\u0003\u0006\u0004%\ta\u001d\u0005\to\u0002\u0011\t\u0011)A\u0005i\"A\u0001\u0010\u0001BC\u0002\u0013\u0005\u0011\u0010\u0003\u0005~\u0001\t\u0005\t\u0015!\u0003{\u0011!q\bA!b\u0001\n\u0003y\bBCA\u0012\u0001\t\u0005\t\u0015!\u0003\u0002\u0002!Q\u0011Q\u0005\u0001\u0003\u0006\u0004%\t!a\n\t\u0015\u0005-\u0002A!A!\u0002\u0013\tI\u0003\u0003\u0006\u0002.\u0001\u0011)\u0019!C\u0001\u0003_A!\"a\u000e\u0001\u0005\u0003\u0005\u000b\u0011BA\u0019\u0011)\tI\u0004\u0001BC\u0002\u0013\u0005\u00111\b\u0005\u000b\u0003\u0007\u0002!\u0011!Q\u0001\n\u0005u\u0002BCA#\u0001\t\u0015\r\u0011\"\u0001\u0002H!Q\u00111\n\u0001\u0003\u0002\u0003\u0006I!!\u0013\t\u0013\u00055\u0003A!b\u0001\n\u0003\u0019\b\"CA(\u0001\t\u0005\t\u0015!\u0003u\u0011)\t\t\u0006\u0001BC\u0002\u0013\u0005\u00111\u000b\u0005\u000b\u0003g\u0002!\u0011!Q\u0001\n\u0005U\u0003BCA;\u0001\t\u0015\r\u0011\"\u0001\u0002x!Q\u0011q\u0012\u0001\u0003\u0002\u0003\u0006I!!\u001f\t\u0015\u0005E\u0005A!b\u0001\n\u0003\t\u0019\n\u0003\u0006\u0002\u001a\u0002\u0011\t\u0011)A\u0005\u0003+C!\"a\'\u0001\u0005\u000b\u0007I\u0011AAO\u0011)\ty\u000b\u0001B\u0001B\u0003%\u0011q\u0014\u0005\u000b\u0003c\u0003!Q1A\u0005\u0002\u0005M\u0006BCAc\u0001\t\u0005\t\u0015!\u0003\u00026\"Q\u0011q\u0019\u0001\u0003\u0006\u0004%\t!!3\t\u0015\u0005M\u0007A!A!\u0002\u0013\tY\rC\u0005\u0002V\u0002\u0011)\u0019!C\u0001g\"I\u0011q\u001b\u0001\u0003\u0002\u0003\u0006I\u0001\u001e\u0005\n\u00033\u0004!Q1A\u0005\u0002MD\u0011\"a7\u0001\u0005\u0003\u0005\u000b\u0011\u0002;\t\u0015\u0005u\u0007A!b\u0001\n\u0003\ty\u000e\u0003\u0006\u0002h\u0002\u0011\t\u0011)A\u0005\u0003CDq!!;\u0001\t\u0003\tY\u000fC\u0004\u0002j\u0002!\tAa\u0005\t\u000f\tU\u0001\u0001\"\u0001\u0003\u0018!1!Q\u0005\u0001\u0005\u0002MDqAa\n\u0001\t\u0003\u0011I\u0003C\u0004\u0003,\u0001!\tA!\f\t\u000f\tU\u0002\u0001\"\u0002\u00038!9!Q\u0007\u0001\u0005\u0006\t}\u0002b\u0002B\"\u0001\u0011\u0005!Q\t\u0005\b\u0005\u001b\u0002A\u0011\u0001B(\u0011\u001d\u0011\u0019\u0006\u0001C\u0001\u0005+BqAa\u0017\u0001\t\u0003\u0011i\u0006C\u0004\u0003d\u0001!\tA!\u001a\t\u000f\t-\u0004\u0001\"\u0001\u0003n!9!1\u000e\u0001\u0005\u0002\tM\u0004b\u0002B<\u0001\u0011\u0005!\u0011\u0010\u0005\b\u0005\u007f\u0002A\u0011\u0001BA\u0011\u001d\u00119\t\u0001C\u0001\u0003oB!B!#\u0001\u0011\u000b\u0007I\u0011AA*\u0011\u001d\u0011Y\t\u0001C\u0001\u0005\u001bCqA!%\u0001\t\u0003\u0011\u0019\nC\u0004\u0003\u0018\u0002!\tA!\'\t\u000f\tu\u0005\u0001\"\u0001\u0003 \"9!1\u0015\u0001\u0005\u0002\t\u0015\u0006b\u0002BU\u0001\u0011\u0005!1\u0016\u0005\b\u0005_\u0003A\u0011\u0001BY\u0011\u001d\u0011)\f\u0001C\u0001\u0005oCqAa/\u0001\t\u0003\u0011i\fC\u0004\u0003B\u0002!\tAa1\t\u000f\t\u001d\u0007\u0001\"\u0001\u0003J\"9!Q\u001a\u0001\u0005\u0002\t=\u0007b\u0002Bj\u0001\u0011\u0005!Q\u001b\u0005\b\u00053\u0004A\u0011\u0001Bn\u0011\u001d\u0011y\u000e\u0001C\u0001\u0005CDqA!:\u0001\t\u0003\u00119\u000fC\u0004\u0003l\u0002!\tA!<\t\u000f\tE\b\u0001\"\u0011\u0003t\"911\u0001\u0001\u0005B\r\u0015\u0001bBB\t\u0001\u0011\u000531\u0003\u0005\b\u0007/\u0001A\u0011IB\r\u0011\u001d\u0019Y\u0002\u0001C\u0005\u0007;Aqa!\n\u0001\t\u0003\u001a9\u0003\u0003\u0004\u0004*\u0001!\t%\u001f\u0005\b\u0007W\u0001A\u0011IB\u0017\u0011\u001d\u0019\u0019\u0004\u0001C!\u0007k9qa!\u000fX\u0011\u0003\u0019YD\u0002\u0004W/\"\u00051Q\b\u0005\b\u0003S\fF\u0011AB%\u0011\u001d\u0019Y%\u0015C\u0001\u0005\'Aqaa\u0013R\t\u0003\u0019i\u0005C\u0005\u0004rE\u000b\t\u0011\"\u0003\u0004t\t\u0001\"+Z:pYV$\u0018n\u001c8QCJ\fWn\u001d\u0006\u00031f\u000ba\u0001]1sC6\u001c(\"\u0001.\u0002\u0011\r|WO]:jKJ\u001c\u0001a\u0005\u0003\u0001;\u000e4\u0007C\u00010b\u001b\u0005y&\"\u00011\u0002\u000bM\u001c\u0017\r\\1\n\u0005\t|&AB!osJ+g\r\u0005\u0002_I&\u0011Qm\u0018\u0002\b!J|G-^2u!\t9wN\u0004\u0002i[:\u0011\u0011\u000e\\\u0007\u0002U*\u00111nW\u0001\u0007yI|w\u000e\u001e \n\u0003\u0001L!A\\0\u0002\u000fA\f7m[1hK&\u0011\u0001/\u001d\u0002\r\'\u0016\u0014\u0018.\u00197ju\u0006\u0014G.\u001a\u0006\u0003]~\u000b\u0001d[3fa>\u0003H/[8oC2$U\r]3oI\u0016t7-[3t+\u0005!\bC\u00010v\u0013\t1xLA\u0004C_>dW-\u00198\u00023-,W\r](qi&|g.\u00197EKB,g\u000eZ3oG&,7\u000fI\u0001\u000e[\u0006D\u0018\n^3sCRLwN\\:\u0016\u0003i\u0004\"AX>\n\u0005q|&aA%oi\u0006qQ.\u0019=Ji\u0016\u0014\u0018\r^5p]N\u0004\u0013\u0001\u00044pe\u000e,g+\u001a:tS>tWCAA\u0001!!\t\u0019!a\u0003\u0002\u0012\u0005ua\u0002BA\u0003\u0003\u000f\u0001\"![0\n\u0007\u0005%q,\u0001\u0004Qe\u0016$WMZ\u0005\u0005\u0003\u001b\tyAA\u0002NCBT1!!\u0003`!\u0011\t\u0019\"!\u0007\u000e\u0005\u0005U!bAA\f3\u0006!1m\u001c:f\u0013\u0011\tY\"!\u0006\u0003\r5{G-\u001e7f!\u0011\t\u0019!a\b\n\t\u0005\u0005\u0012q\u0002\u0002\u0007\'R\u0014\u0018N\\4\u0002\u001b\u0019|\'oY3WKJ\u001c\u0018n\u001c8!\u0003A1wN]2fIB\u0013x\u000e]3si&,7/\u0006\u0002\u0002*AA\u00111AA\u0006\u0003;\ti\"A\tg_J\u001cW\r\u001a)s_B,\'\u000f^5fg\u0002\n\u0001\u0002\u001d:pM&dWm]\u000b\u0003\u0003c\u0001b!a\u0001\u00024\u0005u\u0011\u0002BA\u001b\u0003\u001f\u00111aU3u\u0003%\u0001(o\u001c4jY\u0016\u001c\b%A\btG\u0006d\u0017MV3sg&|gn\u00149u+\t\ti\u0004E\u0003_\u0003\u007f\ti\"C\u0002\u0002B}\u0013aa\u00149uS>t\u0017\u0001E:dC2\fg+\u001a:tS>tw\n\u001d;!\u0003Q1wN]2f\'\u000e\fG.\u0019,feNLwN\\(qiV\u0011\u0011\u0011\n\t\u0005=\u0006}B/A\u000bg_J\u001cWmU2bY\u00064VM]:j_:|\u0005\u000f\u001e\u0011\u0002\u0013QL\b/\u001a7fm\u0016d\u0017A\u0003;za\u0016dWM^3mA\u0005)!/\u001e7fgV\u0011\u0011Q\u000b\t\u0006O\u0006]\u00131L\u0005\u0004\u00033\n(aA*fcB9a,!\u0018\u0002b\u00055\u0014bAA0?\n1A+\u001e9mKJ\u0002B!a\u0019\u0002j5\u0011\u0011Q\r\u0006\u0004\u0003O:\u0016\u0001\u0002:vY\u0016LA!a\u001b\u0002f\t!!+\u001e7f!\u0011\t\u0019\'a\u001c\n\t\u0005E\u0014Q\r\u0002\u000f%VdWMU3t_2,H/[8o\u0003\u0019\u0011X\u000f\\3tA\u0005q!/Z2p]\u000eLG.[1uS>tWCAA=!\u00159\u0017qKA>!\u001dq\u0016QLA?\u0003\u0013\u0003B!a \u0002\u00066\u0011\u0011\u0011\u0011\u0006\u0004\u0003\u0007K\u0016\u0001B;uS2LA!a\"\u0002\u0002\nqQj\u001c3vY\u0016l\u0015\r^2iKJ\u001c\b\u0003BA\n\u0003\u0017KA!!$\u0002\u0016\tq!+Z2p]\u000eLG.[1uS>t\u0017a\u0004:fG>t7-\u001b7jCRLwN\u001c\u0011\u0002\u0015A\u0014x\u000e]3si&,7/\u0006\u0002\u0002\u0016B)q-a\u0016\u0002\u0018B9a,!\u0018\u0002\u001e\u0005u\u0011a\u00039s_B,\'\u000f^5fg\u0002\n!\"\u001a=dYV\u001c\u0018n\u001c8t+\t\ty\n\u0005\u0004\u0002\u0004\u0005M\u0012\u0011\u0015\t\b=\u0006u\u00131UAU!\u0011\t\u0019\"!*\n\t\u0005\u001d\u0016Q\u0003\u0002\r\u001fJ<\u0017M\\5{CRLwN\u001c\t\u0005\u0003\'\tY+\u0003\u0003\u0002.\u0006U!AC\'pIVdWMT1nK\u0006YQ\r_2mkNLwN\\:!\u0003%y7/\u00138g_>\u0003H/\u0006\u0002\u00026B)a,a\u0010\u00028B!\u0011\u0011XA`\u001d\u0011\t\u0019\"a/\n\t\u0005u\u0016QC\u0001\u000b\u0003\u000e$\u0018N^1uS>t\u0017\u0002BAa\u0003\u0007\u0014!aT:\u000b\t\u0005u\u0016QC\u0001\u000b_NLeNZ8PaR\u0004\u0013!\u00046eWZ+\'o]5p]>\u0003H/\u0006\u0002\u0002LB)a,a\u0010\u0002NB!\u00111CAh\u0013\u0011\t\t.!\u0006\u0003\u000fY+\'o]5p]\u0006q!\u000eZ6WKJ\u001c\u0018n\u001c8PaR\u0004\u0013aD;tKNK8\u000f^3n\u001fNLeNZ8\u0002!U\u001cXmU=ti\u0016lwj]%oM>\u0004\u0013aE;tKNK8\u000f^3n\u0015\u0012\\g+\u001a:tS>t\u0017\u0001F;tKNK8\u000f^3n\u0015\u0012\\g+\u001a:tS>t\u0007%\u0001\u000beK\u001a\fW\u000f\u001c;D_:4\u0017nZ;sCRLwN\\\u000b\u0003\u0003C\u0004B!a\u0005\u0002d&!\u0011Q]A\u000b\u00055\u0019uN\u001c4jOV\u0014\u0018\r^5p]\u0006)B-\u001a4bk2$8i\u001c8gS\u001e,(/\u0019;j_:\u0004\u0013A\u0002\u001fj]&$h\b\u0006\u0013\u0002n\u0006E\u00181_A{\u0003o\fI0a?\u0002~\u0006}(\u0011\u0001B\u0002\u0005\u000b\u00119A!\u0003\u0003\f\t5!q\u0002B\t!\r\ty\u000fA\u0007\u0002/\")!o\ta\u0001i\")\u0001p\ta\u0001u\"1ap\ta\u0001\u0003\u0003Aq!!\n$\u0001\u0004\tI\u0003C\u0004\u0002.\r\u0002\r!!\r\t\u000f\u0005e2\u00051\u0001\u0002>!9\u0011QI\u0012A\u0002\u0005%\u0003BBA\'G\u0001\u0007A\u000fC\u0004\u0002R\r\u0002\r!!\u0016\t\u000f\u0005U4\u00051\u0001\u0002z!9\u0011\u0011S\u0012A\u0002\u0005U\u0005bBANG\u0001\u0007\u0011q\u0014\u0005\b\u0003c\u001b\u0003\u0019AA[\u0011\u001d\t9m\ta\u0001\u0003\u0017Da!!6$\u0001\u0004!\bBBAmG\u0001\u0007A\u000fC\u0004\u0002^\u000e\u0002\r!!9\u0015\u0005\u00055\u0018aD1eI\u001a{\'oY3WKJ\u001c\u0018n\u001c8\u0015\t\u00055(\u0011\u0004\u0005\b\u00057)\u0003\u0019\u0001B\u000f\u0003\t1g\u000fE\u0003_\u0005?\u0011\u0019#C\u0002\u0003\"}\u0013!\u0002\u0010:fa\u0016\fG/\u001a3?!\u001dq\u0016QLA\t\u0003;\t1\u0003Z8G_J\u001cWmU2bY\u00064VM]:j_:\fAc]3mK\u000e$X\rZ*dC2\fg+\u001a:tS>tWCAA\u000f\u0003)\tG\r\u001a)s_\u001aLG.\u001a\u000b\u0005\u0003[\u0014y\u0003C\u0004\u00032!\u0002\rAa\r\u0002\u000fA\u0014xNZ5mKB)aLa\b\u0002\u001e\u00059\u0011\r\u001a3Sk2,GCBAw\u0005s\u0011Y\u0004C\u0004\u0002h%\u0002\r!!\u0019\t\u000f\tu\u0012\u00061\u0001\u0002n\u0005Q!/Z:pYV$\u0018n\u001c8\u0015\t\u00055(\u0011\t\u0005\b\u0003OR\u0003\u0019AA1\u00035\tG\r\u001a)s_B,\'\u000f^5fgR!\u0011Q\u001eB$\u0011\u001d\u0011Ie\u000ba\u0001\u0005\u0017\nQ\u0001\u001d:paN\u0004RA\u0018B\u0010\u0003/\u000b1#\u00193e\r>\u00148-\u001a3Qe>\u0004XM\u001d;jKN$B!!<\u0003R!9!\u0011\n\u0017A\u0002\t-\u0013\u0001E<ji\"\u001c6-\u00197b-\u0016\u00148/[8o)\u0011\tiOa\u0016\t\u000f\teS\u00061\u0001\u0002\u001e\u0005a1oY1mCZ+\'o]5p]\u0006)r/\u001b;i\r>\u00148-Z*dC2\fg+\u001a:tS>tG\u0003BAw\u0005?BaA!\u0019/\u0001\u0004!\u0018!\u00054pe\u000e,7kY1mCZ+\'o]5p]\u0006Qq/\u001b;i\u001fNLeNZ8\u0015\t\u00055(q\r\u0005\b\u0005Sz\u0003\u0019AA\\\u0003\u0019y7/\u00138g_\u0006qq/\u001b;i\u0015\u0012\\g+\u001a:tS>tG\u0003BAw\u0005_BqA!\u001d1\u0001\u0004\ti\"A\u0004wKJ\u001c\u0018n\u001c8\u0015\t\u00055(Q\u000f\u0005\b\u0005c\n\u0004\u0019AAg\u0003E\tG\r\u001a*fG>t7-\u001b7jCRLwN\u001c\u000b\u0005\u0003[\u0014Y\bC\u0004\u0002vI\u0002\rA! \u0011\u000by\u0013y\"a\u001f\u0002\u001b\u0005$G-\u0012=dYV\u001c\u0018n\u001c8t)\u0011\tiOa!\t\u000f\u0005m5\u00071\u0001\u0003\u0006B)aLa\b\u0002\"\u0006!\u0012m\u0019;vC2\u0014VmY8oG&d\u0017.\u0019;j_:\f1\"Y2uk\u0006d\'+\u001e7fg\u0006ar/\u001b;i\u0017\u0016,\u0007o\u00149uS>t\u0017\r\u001c#fa\u0016tG-\u001a8dS\u0016\u001cH\u0003BAw\u0005\u001fCQA\u001d\u001cA\u0002Q\f\u0011c^5uQ6\u000b\u00070\u0013;fe\u0006$\u0018n\u001c8t)\u0011\tiO!&\t\u000ba<\u0004\u0019\u0001>\u0002!]LG\u000f\u001b$pe\u000e,g+\u001a:tS>tG\u0003BAw\u00057CaA \u001dA\u0002\u0005\u0005\u0011\u0001F<ji\"4uN]2fIB\u0013x\u000e]3si&,7\u000f\u0006\u0003\u0002n\n\u0005\u0006bBA\u0013s\u0001\u0007\u0011\u0011F\u0001\ro&$\b\u000e\u0015:pM&dWm\u001d\u000b\u0005\u0003[\u00149\u000bC\u0004\u0002.i\u0002\r!!\r\u0002\']LG\u000f[*dC2\fg+\u001a:tS>tw\n\u001d;\u0015\t\u00055(Q\u0016\u0005\b\u0003sY\u0004\u0019AA\u001f\u0003a9\u0018\u000e\u001e5G_J\u001cWmU2bY\u00064VM]:j_:|\u0005\u000f\u001e\u000b\u0005\u0003[\u0014\u0019\fC\u0004\u0002Fq\u0002\r!!\u0013\u0002\u001b]LG\u000f\u001b+za\u0016dWM^3m)\u0011\tiO!/\t\r\u00055S\b1\u0001u\u0003%9\u0018\u000e\u001e5Sk2,7\u000f\u0006\u0003\u0002n\n}\u0006bBA)}\u0001\u0007\u0011QK\u0001\u0013o&$\bNU3d_:\u001c\u0017\u000e\\5bi&|g\u000e\u0006\u0003\u0002n\n\u0015\u0007bBA;\u007f\u0001\u0007\u0011\u0011P\u0001\u000fo&$\b\u000e\u0015:pa\u0016\u0014H/[3t)\u0011\tiOa3\t\u000f\u0005E\u0005\t1\u0001\u0002\u0016\u0006qq/\u001b;i\u000bb\u001cG.^:j_:\u001cH\u0003BAw\u0005#Dq!a\'B\u0001\u0004\ty*A\u0007xSRDwj]%oM>|\u0005\u000f\u001e\u000b\u0005\u0003[\u00149\u000eC\u0004\u00022\n\u0003\r!!.\u0002#]LG\u000f\u001b&eWZ+\'o]5p]>\u0003H\u000f\u0006\u0003\u0002n\nu\u0007bBAd\u0007\u0002\u0007\u00111Z\u0001\u0014o&$\b.V:f\'f\u001cH/Z7Pg&sgm\u001c\u000b\u0005\u0003[\u0014\u0019\u000f\u0003\u0004\u0002V\u0012\u0003\r\u0001^\u0001\u0018o&$\b.V:f\'f\u001cH/Z7KI.4VM]:j_:$B!!<\u0003j\"1\u0011\u0011\\#A\u0002Q\f\u0001d^5uQ\u0012+g-Y;mi\u000e{gNZ5hkJ\fG/[8o)\u0011\tiOa<\t\u000f\u0005ug\t1\u0001\u0002b\u0006AAo\\*ue&tw\r\u0006\u0002\u0003vB!!q_B\u0001\u001b\t\u0011IP\u0003\u0003\u0003|\nu\u0018\u0001\u00027b]\u001eT!Aa@\u0002\t)\fg/Y\u0005\u0005\u0003C\u0011I0\u0001\u0005dC:,\u0015/^1m)\r!8q\u0001\u0005\b\u0007\u0013A\u0005\u0019AB\u0006\u0003\ry\'M\u001b\t\u0004=\u000e5\u0011bAB\b?\n\u0019\u0011I\\=\u0002\r\u0015\fX/\u00197t)\r!8Q\u0003\u0005\b\u0007\u0013I\u0005\u0019AB\u0006\u0003!A\u0017m\u001d5D_\u0012,G#\u0001>\u0002\u000bQ,\b\u000f\\3\u0016\u0005\r}\u0001\u0003\t0\u0004\"QT\u0018\u0011AA\u0015\u0003c\ti$!\u0013u\u0003+\nI(!&\u0002 \u0006U\u00161\u001a;u\u0003CL1aa\t`\u0005\u001d!V\u000f\u001d7fc]\nQ\u0002\u001d:pIV\u001cG\u000f\u0015:fM&DXC\u0001B{\u00031\u0001(o\u001c3vGR\f%/\u001b;z\u00039\u0001(o\u001c3vGR,E.Z7f]R$Baa\u0003\u00040!11\u0011\u0007(A\u0002i\f\u0011A\\\u0001\u0013aJ|G-^2u\u000b2,W.\u001a8u\u001d\u0006lW\r\u0006\u0003\u0003v\u000e]\u0002BBB\u0019\u001f\u0002\u0007!0\u0001\tSKN|G.\u001e;j_:\u0004\u0016M]1ngB\u0019\u0011q^)\u0014\tEk6q\b\t\u0005\u0007\u0003\u001a9%\u0004\u0002\u0004D)!1Q\tB\u007f\u0003\tIw.C\u0002q\u0007\u0007\"\"aa\u000f\u0002\u000b\u0005\u0004\b\u000f\\=\u0015I\u000558qJB)\u0007\'\u001a)fa\u0016\u0004Z\rm3QLB0\u0007C\u001a\u0019g!\u001a\u0004h\r%41NB7\u0007_BQA\u001d+A\u0002QDQ\u0001\u001f+A\u0002iDaA +A\u0002\u0005\u0005\u0001bBA\u0013)\u0002\u0007\u0011\u0011\u0006\u0005\b\u0003[!\u0006\u0019AA\u0019\u0011\u001d\tI\u0004\u0016a\u0001\u0003{Aq!!\u0012U\u0001\u0004\tI\u0005\u0003\u0004\u0002NQ\u0003\r\u0001\u001e\u0005\b\u0003#\"\u0006\u0019AA+\u0011\u001d\t)\b\u0016a\u0001\u0003sBq!!%U\u0001\u0004\t)\nC\u0004\u0002\u001cR\u0003\r!a(\t\u000f\u0005EF\u000b1\u0001\u00026\"9\u0011q\u0019+A\u0002\u0005-\u0007BBAk)\u0002\u0007A\u000f\u0003\u0004\u0002ZR\u0003\r\u0001\u001e\u0005\b\u0003;$\u0006\u0019AAq\u000319(/\u001b;f%\u0016\u0004H.Y2f)\t\u0019)\b\u0005\u0003\u0003x\u000e]\u0014\u0002BB=\u0005s\u0014aa\u00142kK\u000e$\b"
    )
BootstrapMethods:
  0: #191 REF_invokeStatic java/lang/invoke/LambdaMetafactory.altMetafactory:(Ljava/lang/invoke/MethodHandles$Lookup;Ljava/lang/String;Ljava/lang/invoke/MethodType;[Ljava/lang/Object;)Ljava/lang/invoke/CallSite;
    Method arguments:
      #178 ()Z
      #183 REF_invokeStatic coursier/params/ResolutionParams.$anonfun$doForceScalaVersion$1:(Lcoursier/params/ResolutionParams;)Z
      #178 ()Z
      #184 1
  1: #191 REF_invokeStatic java/lang/invoke/LambdaMetafactory.altMetafactory:(Ljava/lang/invoke/MethodHandles$Lookup;Ljava/lang/String;Ljava/lang/invoke/MethodType;[Ljava/lang/Object;)Ljava/lang/invoke/CallSite;
    Method arguments:
      #212 ()Ljava/lang/Object;
      #216 REF_invokeStatic coursier/params/ResolutionParams.$anonfun$selectedScalaVersion$1:()Ljava/lang/String;
      #217 ()Ljava/lang/String;
      #218 5
      #184 1
      #217 ()Ljava/lang/String;
  2: #191 REF_invokeStatic java/lang/invoke/LambdaMetafactory.altMetafactory:(Ljava/lang/invoke/MethodHandles$Lookup;Ljava/lang/String;Ljava/lang/invoke/MethodType;[Ljava/lang/Object;)Ljava/lang/invoke/CallSite;
    Method arguments:
      #366 (Ljava/lang/Object;)Ljava/lang/Object;
      #371 REF_invokeStatic coursier/params/ResolutionParams.$anonfun$actualReconciliation$1:(Lscala/Tuple2;)Lscala/Tuple2;
      #372 (Lscala/Tuple2;)Lscala/Tuple2;
      #218 5
      #184 1
      #372 (Lscala/Tuple2;)Lscala/Tuple2;
  3: #616 REF_invokeStatic scala/runtime/LambdaDeserialize.bootstrap:(Ljava/lang/invoke/MethodHandles$Lookup;Ljava/lang/String;Ljava/lang/invoke/MethodType;[Ljava/lang/invoke/MethodHandle;)Ljava/lang/invoke/CallSite;
    Method arguments:
      #371 REF_invokeStatic coursier/params/ResolutionParams.$anonfun$actualReconciliation$1:(Lscala/Tuple2;)Lscala/Tuple2;
      #183 REF_invokeStatic coursier/params/ResolutionParams.$anonfun$doForceScalaVersion$1:(Lcoursier/params/ResolutionParams;)Z
      #216 REF_invokeStatic coursier/params/ResolutionParams.$anonfun$selectedScalaVersion$1:()Ljava/lang/String;
  ScalaInlineInfo: length = 0x158 (unknown attribute)
   01 01 00 44 01 73 01 74 01 00 B7 00 B8 01 00 D9
   00 A0 01 01 0D 02 37 01 01 0D 01 A2 01 01 71 00
   89 01 00 2E 00 89 01 01 80 00 89 01 01 6A 00 A4
   01 00 A3 00 A4 01 01 29 00 A4 01 00 E4 00 A4 01
   01 1E 00 A4 01 01 63 00 A4 01 00 F2 01 18 01 00
   F2 00 F3 01 01 D7 00 D1 01 00 50 00 A0 01 00 B3
   00 6F 01 01 DA 00 D1 01 00 48 00 7C 01 00 40 00
   80 01 00 35 00 75 01 00 38 00 75 01 01 E0 00 72
   01 00 4C 00 80 01 00 31 00 6F 01 00 33 00 72 01
   00 4A 00 80 01 01 F7 00 72 01 01 F8 01 F9 01 01
   FF 01 C8 01 00 6A 00 62 01 00 61 00 62 01 01 F6
   00 A0 01 00 3A 00 7C 01 00 46 00 89 01 00 44 00
   89 01 00 43 00 89 01 00 3D 00 80 01 00 D4 00 A0
   01 01 B6 00 A0 01 01 EA 01 EB 01 00 42 00 6F 01
   00 4F 00 6F 01 00 4E 00 6F 01 01 B5 01 30 01 01
   6E 00 EF 01 01 3E 01 3F 01 01 45 01 3B 01 00 AF
   00 B0 01 01 2C 00 B0 01 01 54 01 61 01 01 54 01
   30 01 01 5E 01 3B 01 01 93 01 3F 01 01 A5 01 A6
   01 01 48 01 49 01 01 50 01 3B 01 00 EE 00 EF 01
   01 26 00 A4 01 01 67 00 A4 01 01 13 00 A4 01 01
   2F 01 30 01 01 3A 01 3B 01 01 AE 01 3F 01 01 B4
   01 3F 01 01 B3 01 3F 01
  ScalaSig: length = 0x3 (unknown attribute)
   05 02 00
