Classfile /Users/mw/Projects/slang-braindump/.jar/jar8/assemble/slang-braindump/assemble/content/org/scalatest/fixture/FixtureNodeFamily$Branch.class
  Last modified May 29, 2022; size 1416 bytes
  SHA-256 checksum 23ff791dc6df6b3c3507a719bbd12b54ef0371e147b37fc10b35fe2f5f0cf02a
  Compiled from "FixtureNodeFamily.scala"
public abstract class org.scalatest.fixture.FixtureNodeFamily$Branch extends org.scalatest.fixture.FixtureNodeFamily$Node
  minor version: 0
  major version: 52
  flags: (0x0421) ACC_PUBLIC, ACC_SUPER, ACC_ABSTRACT
  this_class: #2                          // org/scalatest/fixture/FixtureNodeFamily$Branch
  super_class: #4                         // org/scalatest/fixture/FixtureNodeFamily$Node
  interfaces: 0, fields: 1, methods: 3, attributes: 4
Constant pool:
   #1 = Utf8               org/scalatest/fixture/FixtureNodeFamily$Branch
   #2 = Class              #1             // org/scalatest/fixture/FixtureNodeFamily$Branch
   #3 = Utf8               org/scalatest/fixture/FixtureNodeFamily$Node
   #4 = Class              #3             // org/scalatest/fixture/FixtureNodeFamily$Node
   #5 = Utf8               FixtureNodeFamily.scala
   #6 = Utf8               org/scalatest/fixture/FixtureNodeFamily
   #7 = Class              #6             // org/scalatest/fixture/FixtureNodeFamily
   #8 = Utf8               Branch
   #9 = Utf8               Node
  #10 = Utf8               subNodes
  #11 = Utf8               Lscala/collection/immutable/List;
  #12 = Utf8               Lscala/collection/immutable/List<Lorg/scalatest/fixture/FixtureNodeFamily$Node;>;
  #13 = Utf8               ()Lscala/collection/immutable/List;
  #14 = Utf8               ()Lscala/collection/immutable/List<Lorg/scalatest/fixture/FixtureNodeFamily$Node;>;
  #15 = NameAndType        #10:#11        // subNodes:Lscala/collection/immutable/List;
  #16 = Fieldref           #2.#15         // org/scalatest/fixture/FixtureNodeFamily$Branch.subNodes:Lscala/collection/immutable/List;
  #17 = Utf8               this
  #18 = Utf8               Lorg/scalatest/fixture/FixtureNodeFamily$Branch;
  #19 = Utf8               subNodes_$eq
  #20 = Utf8               (Lscala/collection/immutable/List;)V
  #21 = Utf8               (Lscala/collection/immutable/List<Lorg/scalatest/fixture/FixtureNodeFamily$Node;>;)V
  #22 = Utf8               x$1
  #23 = Utf8               <init>
  #24 = Utf8               (Lscala/Option;)V
  #25 = Utf8               (Lscala/Option<Lorg/scalatest/fixture/FixtureNodeFamily$Branch;>;)V
  #26 = Utf8               parentOption
  #27 = NameAndType        #23:#24        // "<init>":(Lscala/Option;)V
  #28 = Methodref          #4.#27         // org/scalatest/fixture/FixtureNodeFamily$Node."<init>":(Lscala/Option;)V
  #29 = Utf8               scala/package$
  #30 = Class              #29            // scala/package$
  #31 = Utf8               MODULE$
  #32 = Utf8               Lscala/package$;
  #33 = NameAndType        #31:#32        // MODULE$:Lscala/package$;
  #34 = Fieldref           #30.#33        // scala/package$.MODULE$:Lscala/package$;
  #35 = Utf8               Nil
  #36 = Utf8               ()Lscala/collection/immutable/Nil$;
  #37 = NameAndType        #35:#36        // Nil:()Lscala/collection/immutable/Nil$;
  #38 = Methodref          #30.#37        // scala/package$.Nil:()Lscala/collection/immutable/Nil$;
  #39 = Utf8               Lscala/Option;
  #40 = Utf8               Signature
  #41 = Utf8               Code
  #42 = Utf8               LineNumberTable
  #43 = Utf8               LocalVariableTable
  #44 = Utf8               MethodParameters
  #45 = Utf8               InnerClasses
  #46 = Utf8               SourceFile
  #47 = Utf8               ScalaInlineInfo
  #48 = Utf8               Scala
{
  private scala.collection.immutable.List<org.scalatest.fixture.FixtureNodeFamily$Node> subNodes;
    descriptor: Lscala/collection/immutable/List;
    flags: (0x0002) ACC_PRIVATE
    Signature: #12                          // Lscala/collection/immutable/List<Lorg/scalatest/fixture/FixtureNodeFamily$Node;>;

  public scala.collection.immutable.List<org.scalatest.fixture.FixtureNodeFamily$Node> subNodes();
    descriptor: ()Lscala/collection/immutable/List;
    flags: (0x0001) ACC_PUBLIC
    Code:
      stack=1, locals=1, args_size=1
         0: aload_0
         1: getfield      #16                 // Field subNodes:Lscala/collection/immutable/List;
         4: areturn
      LineNumberTable:
        line 27: 0
      LocalVariableTable:
        Start  Length  Slot  Name   Signature
            0       5     0  this   Lorg/scalatest/fixture/FixtureNodeFamily$Branch;
    Signature: #14                          // ()Lscala/collection/immutable/List<Lorg/scalatest/fixture/FixtureNodeFamily$Node;>;

  public void subNodes_$eq(scala.collection.immutable.List<org.scalatest.fixture.FixtureNodeFamily$Node>);
    descriptor: (Lscala/collection/immutable/List;)V
    flags: (0x0001) ACC_PUBLIC
    Code:
      stack=2, locals=2, args_size=2
         0: aload_0
         1: aload_1
         2: putfield      #16                 // Field subNodes:Lscala/collection/immutable/List;
         5: return
      LineNumberTable:
        line 27: 0
      LocalVariableTable:
        Start  Length  Slot  Name   Signature
            0       6     0  this   Lorg/scalatest/fixture/FixtureNodeFamily$Branch;
            0       6     1   x$1   Lscala/collection/immutable/List;
    Signature: #21                          // (Lscala/collection/immutable/List<Lorg/scalatest/fixture/FixtureNodeFamily$Node;>;)V
    MethodParameters:
      Name                           Flags
      x$1                            final

  public org.scalatest.fixture.FixtureNodeFamily$Branch(scala.Option<org.scalatest.fixture.FixtureNodeFamily$Branch>);
    descriptor: (Lscala/Option;)V
    flags: (0x0001) ACC_PUBLIC
    Code:
      stack=2, locals=2, args_size=2
         0: aload_0
         1: aload_1
         2: invokespecial #28                 // Method org/scalatest/fixture/FixtureNodeFamily$Node."<init>":(Lscala/Option;)V
         5: aload_0
         6: getstatic     #34                 // Field scala/package$.MODULE$:Lscala/package$;
         9: invokevirtual #38                 // Method scala/package$.Nil:()Lscala/collection/immutable/Nil$;
        12: putfield      #16                 // Field subNodes:Lscala/collection/immutable/List;
        15: return
      LineNumberTable:
        line 26: 0
        line 27: 5
        line 26: 15
      LocalVariableTable:
        Start  Length  Slot  Name   Signature
            0      16     0  this   Lorg/scalatest/fixture/FixtureNodeFamily$Branch;
            0      16     1 parentOption   Lscala/Option;
    Signature: #25                          // (Lscala/Option<Lorg/scalatest/fixture/FixtureNodeFamily$Branch;>;)V
    MethodParameters:
      Name                           Flags
      parentOption                   final
}
InnerClasses:
  public static abstract #8= #2 of #7;    // Branch=class org/scalatest/fixture/FixtureNodeFamily$Branch of class org/scalatest/fixture/FixtureNodeFamily
  public static abstract #9= #4 of #7;    // Node=class org/scalatest/fixture/FixtureNodeFamily$Node of class org/scalatest/fixture/FixtureNodeFamily
SourceFile: "FixtureNodeFamily.scala"
  ScalaInlineInfo: length = 0x13 (unknown attribute)
   01 00 00 03 00 17 00 18 00 00 0A 00 0D 00 00 13
   00 14 00
  Scala: length = 0x0 (unknown attribute)

