Classfile /Users/mw/Projects/slang-braindump/.jar/jar8/assemble/slang-braindump/assemble/content/org/scalatest/fixture/NoArg.class
  Last modified May 29, 2022; size 2217 bytes
  SHA-256 checksum c9a23cab112d1be11308942c680864277ab220ae950e4c1de4c621122ac5dac3
  Compiled from "NoArg.scala"
public interface org.scalatest.fixture.NoArg extends scala.DelayedInit,scala.Function0$mcV$sp
  minor version: 0
  major version: 52
  flags: (0x0601) ACC_PUBLIC, ACC_INTERFACE, ACC_ABSTRACT
  this_class: #2                          // org/scalatest/fixture/NoArg
  super_class: #4                         // java/lang/Object
  interfaces: 2, fields: 0, methods: 11, attributes: 4
Constant pool:
   #1 = Utf8               org/scalatest/fixture/NoArg
   #2 = Class              #1             // org/scalatest/fixture/NoArg
   #3 = Utf8               java/lang/Object
   #4 = Class              #3             // java/lang/Object
   #5 = Utf8               scala/DelayedInit
   #6 = Class              #5             // scala/DelayedInit
   #7 = Utf8               scala/Function0$mcV$sp
   #8 = Class              #7             // scala/Function0$mcV$sp
   #9 = Utf8               NoArg.scala
  #10 = Utf8               Lscala/reflect/ScalaSignature;
  #11 = Utf8               bytes
  #12 = Utf8               \u0006\u0005Q2qa\u0002\u0005\u0011\u0002\u0007\u0005q\u0002C\u0003 \u0001\u0011\u0005\u0001\u0005C\u0005\"\u0001\u0001\u0007\t\u0019!C\u0005E!I1\u0005\u0001a\u0001\u0002\u0004%I\u0001\n\u0005\u0006O\u0001!)\u0001\u000b\u0005\u0006]\u0001!\t\u0001\t\u0005\b_\u0001\u0011\r\u0011\"\u00021\u0005\u0015qu.\u0011:h\u0015\tI!\"A\u0004gSb$XO]3\u000b\u0005-a\u0011!C:dC2\fG/Z:u\u0015\u0005i\u0011aA8sO\u000e\u00011\u0003\u0002\u0001\u0011-e\u0001\"!\u0005\u000b\u000e\u0003IQ\u0011aE\u0001\u0006g\u000e\fG.Y\u0005\u0003+I\u0011a!\u00118z%\u00164\u0007CA\t\u0018\u0013\tA\"CA\u0006EK2\f\u00170\u001a3J]&$\bcA\t\u001b9%\u00111D\u0005\u0002\n\rVt7\r^5p]B\u0002\"!E\u000f\n\u0005y\u0011\"\u0001B+oSR\fa\u0001J5oSR$C#\u0001\u000f\u0002\u000fQDWMQ8esV\t\u0011$A\u0006uQ\u0016\u0014u\u000eZ=`I\u0015\fHC\u0001\u000f&\u0011\u001d13!!AA\u0002e\t1\u0001\u001f\u00132\u0003-!W\r\\1zK\u0012Le.\u001b;\u0015\u0005qI\u0003B\u0002\u0016\u0005\t\u0003\u00071&\u0001\u0003c_\u0012L\bcA\t-9%\u0011QF\u0005\u0002\ty\tLh.Y7f}\u0005)\u0011\r\u001d9ms\u0006I1\u000f^=mK:\u000bW.Z\u000b\u0002cA\u0011\u0011CM\u0005\u0003gI\u00111!\u00138u\u0001
  #13 = Utf8               org$scalatest$fixture$NoArg$_setter_$styleName_$eq
  #14 = Utf8               (I)V
  #15 = Utf8               x$1
  #16 = Utf8               org$scalatest$fixture$NoArg$$theBody
  #17 = Utf8               ()Lscala/Function0;
  #18 = Utf8               ()Lscala/Function0<Lscala/runtime/BoxedUnit;>;
  #19 = Utf8               org$scalatest$fixture$NoArg$$theBody_$eq
  #20 = Utf8               (Lscala/Function0;)V
  #21 = Utf8               (Lscala/Function0<Lscala/runtime/BoxedUnit;>;)V
  #22 = Utf8               delayedInit$
  #23 = Utf8               (Lorg/scalatest/fixture/NoArg;Lscala/Function0;)V
  #24 = Utf8               $this
  #25 = Utf8               body
  #26 = Utf8               delayedInit
  #27 = NameAndType        #26:#20        // delayedInit:(Lscala/Function0;)V
  #28 = InterfaceMethodref #2.#27         // org/scalatest/fixture/NoArg.delayedInit:(Lscala/Function0;)V
  #29 = Utf8               Lorg/scalatest/fixture/NoArg;
  #30 = Utf8               Lscala/Function0;
  #31 = NameAndType        #19:#20        // org$scalatest$fixture$NoArg$$theBody_$eq:(Lscala/Function0;)V
  #32 = InterfaceMethodref #2.#31         // org/scalatest/fixture/NoArg.org$scalatest$fixture$NoArg$$theBody_$eq:(Lscala/Function0;)V
  #33 = Utf8               this
  #34 = Utf8               scala/Function0
  #35 = Class              #34            // scala/Function0
  #36 = Utf8               java/lang/Throwable
  #37 = Class              #36            // java/lang/Throwable
  #38 = Utf8               apply$
  #39 = Utf8               (Lorg/scalatest/fixture/NoArg;)V
  #40 = Utf8               apply
  #41 = Utf8               ()V
  #42 = NameAndType        #40:#41        // apply:()V
  #43 = InterfaceMethodref #2.#42         // org/scalatest/fixture/NoArg.apply:()V
  #44 = Utf8               apply$mcV$sp
  #45 = NameAndType        #44:#41        // apply$mcV$sp:()V
  #46 = InterfaceMethodref #2.#45         // org/scalatest/fixture/NoArg.apply$mcV$sp:()V
  #47 = Utf8               styleName
  #48 = Utf8               ()I
  #49 = Utf8               apply$mcV$sp$
  #50 = NameAndType        #16:#17        // org$scalatest$fixture$NoArg$$theBody:()Lscala/Function0;
  #51 = InterfaceMethodref #2.#50         // org/scalatest/fixture/NoArg.org$scalatest$fixture$NoArg$$theBody:()Lscala/Function0;
  #52 = InterfaceMethodref #35.#45        // scala/Function0.apply$mcV$sp:()V
  #53 = Utf8               $init$
  #54 = NameAndType        #13:#14        // org$scalatest$fixture$NoArg$_setter_$styleName_$eq:(I)V
  #55 = InterfaceMethodref #2.#54         // org/scalatest/fixture/NoArg.org$scalatest$fixture$NoArg$_setter_$styleName_$eq:(I)V
  #56 = Utf8               MethodParameters
  #57 = Utf8               Signature
  #58 = Utf8               Code
  #59 = Utf8               LineNumberTable
  #60 = Utf8               LocalVariableTable
  #61 = Utf8               StackMapTable
  #62 = Utf8               SourceFile
  #63 = Utf8               RuntimeVisibleAnnotations
  #64 = Utf8               ScalaInlineInfo
  #65 = Utf8               ScalaSig
{
  public abstract void org$scalatest$fixture$NoArg$_setter_$styleName_$eq(int);
    descriptor: (I)V
    flags: (0x0401) ACC_PUBLIC, ACC_ABSTRACT
    MethodParameters:
      Name                           Flags
      x$1                            final

  public abstract scala.Function0<scala.runtime.BoxedUnit> org$scalatest$fixture$NoArg$$theBody();
    descriptor: ()Lscala/Function0;
    flags: (0x0401) ACC_PUBLIC, ACC_ABSTRACT
    Signature: #18                          // ()Lscala/Function0<Lscala/runtime/BoxedUnit;>;

  public abstract void org$scalatest$fixture$NoArg$$theBody_$eq(scala.Function0<scala.runtime.BoxedUnit>);
    descriptor: (Lscala/Function0;)V
    flags: (0x0401) ACC_PUBLIC, ACC_ABSTRACT
    Signature: #21                          // (Lscala/Function0<Lscala/runtime/BoxedUnit;>;)V
    MethodParameters:
      Name                           Flags
      x$1                            final

  public static void delayedInit$(org.scalatest.fixture.NoArg, scala.Function0);
    descriptor: (Lorg/scalatest/fixture/NoArg;Lscala/Function0;)V
    flags: (0x1009) ACC_PUBLIC, ACC_STATIC, ACC_SYNTHETIC
    Code:
      stack=2, locals=2, args_size=2
         0: aload_0
         1: aload_1
         2: invokespecial #28                 // InterfaceMethod delayedInit:(Lscala/Function0;)V
         5: return
      LineNumberTable:
        line 220: 0
      LocalVariableTable:
        Start  Length  Slot  Name   Signature
            0       6     0 $this   Lorg/scalatest/fixture/NoArg;
            0       6     1  body   Lscala/Function0;
    MethodParameters:
      Name                           Flags
      $this                          final synthetic
      body                           final

  public default void delayedInit(scala.Function0<scala.runtime.BoxedUnit>);
    descriptor: (Lscala/Function0;)V
    flags: (0x0001) ACC_PUBLIC
    Code:
      stack=2, locals=3, args_size=2
         0: aload_0
         1: dup
         2: astore_2
         3: monitorenter
         4: aload_0
         5: aload_1
         6: invokeinterface #32,  2           // InterfaceMethod org$scalatest$fixture$NoArg$$theBody_$eq:(Lscala/Function0;)V
        11: aload_2
        12: monitorexit
        13: goto          19
        16: aload_2
        17: monitorexit
        18: athrow
        19: return
      Exception table:
         from    to  target type
             4    11    16   any
      StackMapTable: number_of_entries = 2
        frame_type = 255 /* full_frame */
          offset_delta = 16
          locals = [ class org/scalatest/fixture/NoArg, class scala/Function0, class org/scalatest/fixture/NoArg ]
          stack = [ class java/lang/Throwable ]
        frame_type = 2 /* same */
      LineNumberTable:
        line 221: 0
      LocalVariableTable:
        Start  Length  Slot  Name   Signature
            0      20     0  this   Lorg/scalatest/fixture/NoArg;
            0      20     1  body   Lscala/Function0;
    Signature: #21                          // (Lscala/Function0<Lscala/runtime/BoxedUnit;>;)V
    MethodParameters:
      Name                           Flags
      body                           final

  public static void apply$(org.scalatest.fixture.NoArg);
    descriptor: (Lorg/scalatest/fixture/NoArg;)V
    flags: (0x1009) ACC_PUBLIC, ACC_STATIC, ACC_SYNTHETIC
    Code:
      stack=1, locals=1, args_size=1
         0: aload_0
         1: invokespecial #43                 // InterfaceMethod apply:()V
         4: return
      LineNumberTable:
        line 227: 0
      LocalVariableTable:
        Start  Length  Slot  Name   Signature
            0       5     0 $this   Lorg/scalatest/fixture/NoArg;
    MethodParameters:
      Name                           Flags
      $this                          final synthetic

  public default void apply();
    descriptor: ()V
    flags: (0x0001) ACC_PUBLIC
    Code:
      stack=1, locals=1, args_size=1
         0: aload_0
         1: invokeinterface #46,  1           // InterfaceMethod apply$mcV$sp:()V
         6: return
      LineNumberTable:
        line 227: 0
      LocalVariableTable:
        Start  Length  Slot  Name   Signature
            0       7     0  this   Lorg/scalatest/fixture/NoArg;

  public abstract int styleName();
    descriptor: ()I
    flags: (0x0401) ACC_PUBLIC, ACC_ABSTRACT

  public static void apply$mcV$sp$(org.scalatest.fixture.NoArg);
    descriptor: (Lorg/scalatest/fixture/NoArg;)V
    flags: (0x1009) ACC_PUBLIC, ACC_STATIC, ACC_SYNTHETIC
    Code:
      stack=1, locals=1, args_size=1
         0: aload_0
         1: invokespecial #46                 // InterfaceMethod apply$mcV$sp:()V
         4: return
      LineNumberTable:
        line 227: 0
      LocalVariableTable:
        Start  Length  Slot  Name   Signature
            0       5     0 $this   Lorg/scalatest/fixture/NoArg;
    MethodParameters:
      Name                           Flags
      $this                          final synthetic

  public default void apply$mcV$sp();
    descriptor: ()V
    flags: (0x0001) ACC_PUBLIC
    Code:
      stack=2, locals=2, args_size=1
         0: aload_0
         1: dup
         2: astore_1
         3: monitorenter
         4: aload_0
         5: invokeinterface #51,  1           // InterfaceMethod org$scalatest$fixture$NoArg$$theBody:()Lscala/Function0;
        10: ifnull        27
        13: aload_0
        14: invokeinterface #51,  1           // InterfaceMethod org$scalatest$fixture$NoArg$$theBody:()Lscala/Function0;
        19: invokeinterface #52,  1           // InterfaceMethod scala/Function0.apply$mcV$sp:()V
        24: goto          27
        27: aload_1
        28: monitorexit
        29: goto          35
        32: aload_1
        33: monitorexit
        34: athrow
        35: return
      Exception table:
         from    to  target type
             4    27    32   any
      StackMapTable: number_of_entries = 3
        frame_type = 252 /* append */
          offset_delta = 27
          locals = [ class org/scalatest/fixture/NoArg ]
        frame_type = 68 /* same_locals_1_stack_item */
          stack = [ class java/lang/Throwable ]
        frame_type = 2 /* same */
      LineNumberTable:
        line 227: 0
      LocalVariableTable:
        Start  Length  Slot  Name   Signature
            0      36     0  this   Lorg/scalatest/fixture/NoArg;

  public static void $init$(org.scalatest.fixture.NoArg);
    descriptor: (Lorg/scalatest/fixture/NoArg;)V
    flags: (0x0009) ACC_PUBLIC, ACC_STATIC
    Code:
      stack=2, locals=1, args_size=1
         0: aload_0
         1: iconst_0
         2: invokeinterface #55,  2           // InterfaceMethod org$scalatest$fixture$NoArg$_setter_$styleName_$eq:(I)V
         7: return
      LineNumberTable:
        line 239: 0
        line 213: 7
      LocalVariableTable:
        Start  Length  Slot  Name   Signature
            0       8     0 $this   Lorg/scalatest/fixture/NoArg;
    MethodParameters:
      Name                           Flags
      $this                          final synthetic
}
SourceFile: "NoArg.scala"
RuntimeVisibleAnnotations:
  0: #10(#11=s#12)
    scala.reflect.ScalaSignature(
      bytes="\u0006\u0005Q2qa\u0002\u0005\u0011\u0002\u0007\u0005q\u0002C\u0003 \u0001\u0011\u0005\u0001\u0005C\u0005\"\u0001\u0001\u0007\t\u0019!C\u0005E!I1\u0005\u0001a\u0001\u0002\u0004%I\u0001\n\u0005\u0006O\u0001!)\u0001\u000b\u0005\u0006]\u0001!\t\u0001\t\u0005\b_\u0001\u0011\r\u0011\"\u00021\u0005\u0015qu.\u0011:h\u0015\tI!\"A\u0004gSb$XO]3\u000b\u0005-a\u0011!C:dC2\fG/Z:u\u0015\u0005i\u0011aA8sO\u000e\u00011\u0003\u0002\u0001\u0011-e\u0001\"!\u0005\u000b\u000e\u0003IQ\u0011aE\u0001\u0006g\u000e\fG.Y\u0005\u0003+I\u0011a!\u00118z%\u00164\u0007CA\t\u0018\u0013\tA\"CA\u0006EK2\f\u00170\u001a3J]&$\bcA\t\u001b9%\u00111D\u0005\u0002\n\rVt7\r^5p]B\u0002\"!E\u000f\n\u0005y\u0011\"\u0001B+oSR\fa\u0001J5oSR$C#\u0001\u000f\u0002\u000fQDWMQ8esV\t\u0011$A\u0006uQ\u0016\u0014u\u000eZ=`I\u0015\fHC\u0001\u000f&\u0011\u001d13!!AA\u0002e\t1\u0001\u001f\u00132\u0003-!W\r\\1zK\u0012Le.\u001b;\u0015\u0005qI\u0003B\u0002\u0016\u0005\t\u0003\u00071&\u0001\u0003c_\u0012L\bcA\t-9%\u0011QF\u0005\u0002\ty\tLh.Y7f}\u0005)\u0011\r\u001d9ms\u0006I1\u000f^=mK:\u000bW.Z\u000b\u0002cA\u0011\u0011CM\u0005\u0003gI\u00111!\u00138u\u0001"
    )
  ScalaInlineInfo: length = 0x3B (unknown attribute)
   01 00 00 0B 00 35 00 27 01 00 28 00 29 00 00 26
   00 27 01 00 2C 00 29 00 00 31 00 27 01 00 1A 00
   14 01 00 16 00 17 01 00 10 00 11 00 00 13 00 14
   00 00 0D 00 0E 00 00 2F 00 30 00
  ScalaSig: length = 0x3 (unknown attribute)
   05 02 00
