Classfile /Users/mw/Projects/slang-braindump/.jar/jar11/assemble/slang-braindump/assemble/content/org/apache/commons/lang3/concurrent/AbstractCircuitBreaker$State$2.class
  Last modified May 29, 2022; size 984 bytes
  SHA-256 checksum c327f80654e76eb36ffd22f9e912c88c06a27202f4934d9bc2418b168e4336c3
  Compiled from "AbstractCircuitBreaker.java"
final class org.apache.commons.lang3.concurrent.AbstractCircuitBreaker$State$2 extends org.apache.commons.lang3.concurrent.AbstractCircuitBreaker$State
  minor version: 0
  major version: 52
  flags: (0x4030) ACC_FINAL, ACC_SUPER, ACC_ENUM
  this_class: #3                          // org/apache/commons/lang3/concurrent/AbstractCircuitBreaker$State$2
  super_class: #4                         // org/apache/commons/lang3/concurrent/AbstractCircuitBreaker$State
  interfaces: 0, fields: 0, methods: 2, attributes: 3
Constant pool:
   #1 = Methodref          #4.#19         // org/apache/commons/lang3/concurrent/AbstractCircuitBreaker$State."<init>":(Ljava/lang/String;ILorg/apache/commons/lang3/concurrent/AbstractCircuitBreaker$1;)V
   #2 = Fieldref           #3.#20         // org/apache/commons/lang3/concurrent/AbstractCircuitBreaker$State$2.CLOSED:Lorg/apache/commons/lang3/concurrent/AbstractCircuitBreaker$State;
   #3 = Class              #21            // org/apache/commons/lang3/concurrent/AbstractCircuitBreaker$State$2
   #4 = Class              #23            // org/apache/commons/lang3/concurrent/AbstractCircuitBreaker$State
   #5 = Utf8               <init>
   #6 = Utf8               (Ljava/lang/String;I)V
   #7 = Utf8               Code
   #8 = Utf8               LineNumberTable
   #9 = Utf8               LocalVariableTable
  #10 = Utf8               this
  #11 = Utf8               State
  #12 = Utf8               InnerClasses
  #13 = Utf8               Lorg/apache/commons/lang3/concurrent/AbstractCircuitBreaker$State$2;
  #14 = Utf8               oppositeState
  #15 = Utf8               ()Lorg/apache/commons/lang3/concurrent/AbstractCircuitBreaker$State;
  #16 = Utf8               SourceFile
  #17 = Utf8               AbstractCircuitBreaker.java
  #18 = Utf8               EnclosingMethod
  #19 = NameAndType        #5:#25         // "<init>":(Ljava/lang/String;ILorg/apache/commons/lang3/concurrent/AbstractCircuitBreaker$1;)V
  #20 = NameAndType        #26:#27        // CLOSED:Lorg/apache/commons/lang3/concurrent/AbstractCircuitBreaker$State;
  #21 = Utf8               org/apache/commons/lang3/concurrent/AbstractCircuitBreaker$State$2
  #22 = Class              #28            // org/apache/commons/lang3/concurrent/AbstractCircuitBreaker
  #23 = Utf8               org/apache/commons/lang3/concurrent/AbstractCircuitBreaker$State
  #24 = Class              #29            // org/apache/commons/lang3/concurrent/AbstractCircuitBreaker$1
  #25 = Utf8               (Ljava/lang/String;ILorg/apache/commons/lang3/concurrent/AbstractCircuitBreaker$1;)V
  #26 = Utf8               CLOSED
  #27 = Utf8               Lorg/apache/commons/lang3/concurrent/AbstractCircuitBreaker$State;
  #28 = Utf8               org/apache/commons/lang3/concurrent/AbstractCircuitBreaker
  #29 = Utf8               org/apache/commons/lang3/concurrent/AbstractCircuitBreaker$1
{
  org.apache.commons.lang3.concurrent.AbstractCircuitBreaker$State$2(java.lang.String, int);
    descriptor: (Ljava/lang/String;I)V
    flags: (0x0000)
    Code:
      stack=4, locals=3, args_size=3
         0: aload_0
         1: aload_1
         2: iload_2
         3: aconst_null
         4: invokespecial #1                  // Method org/apache/commons/lang3/concurrent/AbstractCircuitBreaker$State."<init>":(Ljava/lang/String;ILorg/apache/commons/lang3/concurrent/AbstractCircuitBreaker$1;)V
         7: return
      LineNumberTable:
        line 152: 0
      LocalVariableTable:
        Start  Length  Slot  Name   Signature
            0       8     0  this   Lorg/apache/commons/lang3/concurrent/AbstractCircuitBreaker$State$2;

  public org.apache.commons.lang3.concurrent.AbstractCircuitBreaker$State oppositeState();
    descriptor: ()Lorg/apache/commons/lang3/concurrent/AbstractCircuitBreaker$State;
    flags: (0x0001) ACC_PUBLIC
    Code:
      stack=1, locals=1, args_size=1
         0: getstatic     #2                  // Field CLOSED:Lorg/apache/commons/lang3/concurrent/AbstractCircuitBreaker$State;
         3: areturn
      LineNumberTable:
        line 158: 0
      LocalVariableTable:
        Start  Length  Slot  Name   Signature
            0       4     0  this   Lorg/apache/commons/lang3/concurrent/AbstractCircuitBreaker$State$2;
}
SourceFile: "AbstractCircuitBreaker.java"
EnclosingMethod: #4.#0                  // org.apache.commons.lang3.concurrent.AbstractCircuitBreaker$State
InnerClasses:
  protected static abstract #11= #4 of #22; // State=class org/apache/commons/lang3/concurrent/AbstractCircuitBreaker$State of class org/apache/commons/lang3/concurrent/AbstractCircuitBreaker
  final #3;                               // class org/apache/commons/lang3/concurrent/AbstractCircuitBreaker$State$2
  static #24;                             // class org/apache/commons/lang3/concurrent/AbstractCircuitBreaker$1
