Classfile /Users/mw/Projects/slang-braindump/.jar/jar11/assemble/slang-braindump/assemble/content/org/apache/commons/lang3/concurrent/MultiBackgroundInitializer.class
  Last modified May 29, 2022; size 4642 bytes
  SHA-256 checksum c20d373604275de7378299e1e22e05a95f559ed2658c2653913c13d97a4b3509
  Compiled from "MultiBackgroundInitializer.java"
public class org.apache.commons.lang3.concurrent.MultiBackgroundInitializer extends org.apache.commons.lang3.concurrent.BackgroundInitializer<org.apache.commons.lang3.concurrent.MultiBackgroundInitializer$MultiBackgroundInitializerResults>
  minor version: 0
  major version: 52
  flags: (0x0021) ACC_PUBLIC, ACC_SUPER
  this_class: #37                         // org/apache/commons/lang3/concurrent/MultiBackgroundInitializer
  super_class: #19                        // org/apache/commons/lang3/concurrent/BackgroundInitializer
  interfaces: 0, fields: 1, methods: 6, attributes: 3
Constant pool:
    #1 = Methodref          #19.#93       // org/apache/commons/lang3/concurrent/BackgroundInitializer."<init>":()V
    #2 = Class              #94           // java/util/HashMap
    #3 = Methodref          #2.#93        // java/util/HashMap."<init>":()V
    #4 = Fieldref           #37.#95       // org/apache/commons/lang3/concurrent/MultiBackgroundInitializer.childInitializers:Ljava/util/Map;
    #5 = Methodref          #19.#96       // org/apache/commons/lang3/concurrent/BackgroundInitializer."<init>":(Ljava/util/concurrent/ExecutorService;)V
    #6 = String             #97           // Name of child initializer must not be null!
    #7 = Class              #98           // java/lang/Object
    #8 = Methodref          #99.#100      // org/apache/commons/lang3/Validate.isTrue:(ZLjava/lang/String;[Ljava/lang/Object;)V
    #9 = String             #101          // Child initializer must not be null!
   #10 = Methodref          #37.#102      // org/apache/commons/lang3/concurrent/MultiBackgroundInitializer.isStarted:()Z
   #11 = Class              #103          // java/lang/IllegalStateException
   #12 = String             #104          // addInitializer() must not be called after start()!
   #13 = Methodref          #11.#105      // java/lang/IllegalStateException."<init>":(Ljava/lang/String;)V
   #14 = InterfaceMethodref #85.#106      // java/util/Map.put:(Ljava/lang/Object;Ljava/lang/Object;)Ljava/lang/Object;
   #15 = InterfaceMethodref #85.#107      // java/util/Map.values:()Ljava/util/Collection;
   #16 = InterfaceMethodref #108.#109     // java/util/Collection.iterator:()Ljava/util/Iterator;
   #17 = InterfaceMethodref #71.#110      // java/util/Iterator.hasNext:()Z
   #18 = InterfaceMethodref #71.#111      // java/util/Iterator.next:()Ljava/lang/Object;
   #19 = Class              #112          // org/apache/commons/lang3/concurrent/BackgroundInitializer
   #20 = Methodref          #19.#113      // org/apache/commons/lang3/concurrent/BackgroundInitializer.getTaskCount:()I
   #21 = Methodref          #2.#114       // java/util/HashMap."<init>":(Ljava/util/Map;)V
   #22 = Methodref          #37.#115      // org/apache/commons/lang3/concurrent/MultiBackgroundInitializer.getActiveExecutor:()Ljava/util/concurrent/ExecutorService;
   #23 = Methodref          #19.#116      // org/apache/commons/lang3/concurrent/BackgroundInitializer.getExternalExecutor:()Ljava/util/concurrent/ExecutorService;
   #24 = Methodref          #19.#117      // org/apache/commons/lang3/concurrent/BackgroundInitializer.setExternalExecutor:(Ljava/util/concurrent/ExecutorService;)V
   #25 = Methodref          #19.#118      // org/apache/commons/lang3/concurrent/BackgroundInitializer.start:()Z
   #26 = InterfaceMethodref #85.#119      // java/util/Map.entrySet:()Ljava/util/Set;
   #27 = InterfaceMethodref #120.#109     // java/util/Set.iterator:()Ljava/util/Iterator;
   #28 = Class              #121          // java/util/Map$Entry
   #29 = InterfaceMethodref #28.#122      // java/util/Map$Entry.getKey:()Ljava/lang/Object;
   #30 = Class              #123          // java/lang/String
   #31 = InterfaceMethodref #28.#124      // java/util/Map$Entry.getValue:()Ljava/lang/Object;
   #32 = Methodref          #19.#125      // org/apache/commons/lang3/concurrent/BackgroundInitializer.get:()Ljava/lang/Object;
   #33 = Class              #126          // org/apache/commons/lang3/concurrent/ConcurrentException
   #34 = Class              #127          // org/apache/commons/lang3/concurrent/MultiBackgroundInitializer$MultiBackgroundInitializerResults
   #35 = Methodref          #34.#128      // org/apache/commons/lang3/concurrent/MultiBackgroundInitializer$MultiBackgroundInitializerResults."<init>":(Ljava/util/Map;Ljava/util/Map;Ljava/util/Map;Lorg/apache/commons/lang3/concurrent/MultiBackgroundInitializer$1;)V
   #36 = Methodref          #37.#129      // org/apache/commons/lang3/concurrent/MultiBackgroundInitializer.initialize:()Lorg/apache/commons/lang3/concurrent/MultiBackgroundInitializer$MultiBackgroundInitializerResults;
   #37 = Class              #130          // org/apache/commons/lang3/concurrent/MultiBackgroundInitializer
   #38 = Class              #131          // org/apache/commons/lang3/concurrent/MultiBackgroundInitializer$1
   #39 = Utf8               InnerClasses
   #40 = Utf8               MultiBackgroundInitializerResults
   #41 = Utf8               childInitializers
   #42 = Utf8               Ljava/util/Map;
   #43 = Utf8               Signature
   #44 = Utf8               Ljava/util/Map<Ljava/lang/String;Lorg/apache/commons/lang3/concurrent/BackgroundInitializer<*>;>;
   #45 = Utf8               <init>
   #46 = Utf8               ()V
   #47 = Utf8               Code
   #48 = Utf8               LineNumberTable
   #49 = Utf8               LocalVariableTable
   #50 = Utf8               this
   #51 = Utf8               Lorg/apache/commons/lang3/concurrent/MultiBackgroundInitializer;
   #52 = Utf8               (Ljava/util/concurrent/ExecutorService;)V
   #53 = Utf8               exec
   #54 = Utf8               Ljava/util/concurrent/ExecutorService;
   #55 = Utf8               addInitializer
   #56 = Utf8               (Ljava/lang/String;Lorg/apache/commons/lang3/concurrent/BackgroundInitializer;)V
   #57 = Utf8               name
   #58 = Utf8               Ljava/lang/String;
   #59 = Utf8               init
   #60 = Utf8               Lorg/apache/commons/lang3/concurrent/BackgroundInitializer;
   #61 = Utf8               LocalVariableTypeTable
   #62 = Utf8               Lorg/apache/commons/lang3/concurrent/BackgroundInitializer<*>;
   #63 = Utf8               StackMapTable
   #64 = Class              #132          // java/lang/Throwable
   #65 = Utf8               (Ljava/lang/String;Lorg/apache/commons/lang3/concurrent/BackgroundInitializer<*>;)V
   #66 = Utf8               getTaskCount
   #67 = Utf8               ()I
   #68 = Utf8               bi
   #69 = Utf8               result
   #70 = Utf8               I
   #71 = Class              #133          // java/util/Iterator
   #72 = Utf8               initialize
   #73 = Utf8               ()Lorg/apache/commons/lang3/concurrent/MultiBackgroundInitializer$MultiBackgroundInitializerResults;
   #74 = Utf8               inits
   #75 = Utf8               cex
   #76 = Utf8               Lorg/apache/commons/lang3/concurrent/ConcurrentException;
   #77 = Utf8               e
   #78 = Utf8               Entry
   #79 = Utf8               Ljava/util/Map$Entry;
   #80 = Utf8               results
   #81 = Utf8               excepts
   #82 = Utf8               Ljava/util/Map$Entry<Ljava/lang/String;Lorg/apache/commons/lang3/concurrent/BackgroundInitializer<*>;>;
   #83 = Utf8               Ljava/util/Map<Ljava/lang/String;Ljava/lang/Object;>;
   #84 = Utf8               Ljava/util/Map<Ljava/lang/String;Lorg/apache/commons/lang3/concurrent/ConcurrentException;>;
   #85 = Class              #134          // java/util/Map
   #86 = Class              #135          // java/util/concurrent/ExecutorService
   #87 = Utf8               Exceptions
   #88 = Class              #136          // java/lang/Exception
   #89 = Utf8               ()Ljava/lang/Object;
   #90 = Utf8               Lorg/apache/commons/lang3/concurrent/BackgroundInitializer<Lorg/apache/commons/lang3/concurrent/MultiBackgroundInitializer$MultiBackgroundInitializerResults;>;
   #91 = Utf8               SourceFile
   #92 = Utf8               MultiBackgroundInitializer.java
   #93 = NameAndType        #45:#46       // "<init>":()V
   #94 = Utf8               java/util/HashMap
   #95 = NameAndType        #41:#42       // childInitializers:Ljava/util/Map;
   #96 = NameAndType        #45:#52       // "<init>":(Ljava/util/concurrent/ExecutorService;)V
   #97 = Utf8               Name of child initializer must not be null!
   #98 = Utf8               java/lang/Object
   #99 = Class              #137          // org/apache/commons/lang3/Validate
  #100 = NameAndType        #138:#139     // isTrue:(ZLjava/lang/String;[Ljava/lang/Object;)V
  #101 = Utf8               Child initializer must not be null!
  #102 = NameAndType        #140:#141     // isStarted:()Z
  #103 = Utf8               java/lang/IllegalStateException
  #104 = Utf8               addInitializer() must not be called after start()!
  #105 = NameAndType        #45:#142      // "<init>":(Ljava/lang/String;)V
  #106 = NameAndType        #143:#144     // put:(Ljava/lang/Object;Ljava/lang/Object;)Ljava/lang/Object;
  #107 = NameAndType        #145:#146     // values:()Ljava/util/Collection;
  #108 = Class              #147          // java/util/Collection
  #109 = NameAndType        #148:#149     // iterator:()Ljava/util/Iterator;
  #110 = NameAndType        #150:#141     // hasNext:()Z
  #111 = NameAndType        #151:#89      // next:()Ljava/lang/Object;
  #112 = Utf8               org/apache/commons/lang3/concurrent/BackgroundInitializer
  #113 = NameAndType        #66:#67       // getTaskCount:()I
  #114 = NameAndType        #45:#152      // "<init>":(Ljava/util/Map;)V
  #115 = NameAndType        #153:#154     // getActiveExecutor:()Ljava/util/concurrent/ExecutorService;
  #116 = NameAndType        #155:#154     // getExternalExecutor:()Ljava/util/concurrent/ExecutorService;
  #117 = NameAndType        #156:#52      // setExternalExecutor:(Ljava/util/concurrent/ExecutorService;)V
  #118 = NameAndType        #157:#141     // start:()Z
  #119 = NameAndType        #158:#159     // entrySet:()Ljava/util/Set;
  #120 = Class              #160          // java/util/Set
  #121 = Utf8               java/util/Map$Entry
  #122 = NameAndType        #161:#89      // getKey:()Ljava/lang/Object;
  #123 = Utf8               java/lang/String
  #124 = NameAndType        #162:#89      // getValue:()Ljava/lang/Object;
  #125 = NameAndType        #163:#89      // get:()Ljava/lang/Object;
  #126 = Utf8               org/apache/commons/lang3/concurrent/ConcurrentException
  #127 = Utf8               org/apache/commons/lang3/concurrent/MultiBackgroundInitializer$MultiBackgroundInitializerResults
  #128 = NameAndType        #45:#164      // "<init>":(Ljava/util/Map;Ljava/util/Map;Ljava/util/Map;Lorg/apache/commons/lang3/concurrent/MultiBackgroundInitializer$1;)V
  #129 = NameAndType        #72:#73       // initialize:()Lorg/apache/commons/lang3/concurrent/MultiBackgroundInitializer$MultiBackgroundInitializerResults;
  #130 = Utf8               org/apache/commons/lang3/concurrent/MultiBackgroundInitializer
  #131 = Utf8               org/apache/commons/lang3/concurrent/MultiBackgroundInitializer$1
  #132 = Utf8               java/lang/Throwable
  #133 = Utf8               java/util/Iterator
  #134 = Utf8               java/util/Map
  #135 = Utf8               java/util/concurrent/ExecutorService
  #136 = Utf8               java/lang/Exception
  #137 = Utf8               org/apache/commons/lang3/Validate
  #138 = Utf8               isTrue
  #139 = Utf8               (ZLjava/lang/String;[Ljava/lang/Object;)V
  #140 = Utf8               isStarted
  #141 = Utf8               ()Z
  #142 = Utf8               (Ljava/lang/String;)V
  #143 = Utf8               put
  #144 = Utf8               (Ljava/lang/Object;Ljava/lang/Object;)Ljava/lang/Object;
  #145 = Utf8               values
  #146 = Utf8               ()Ljava/util/Collection;
  #147 = Utf8               java/util/Collection
  #148 = Utf8               iterator
  #149 = Utf8               ()Ljava/util/Iterator;
  #150 = Utf8               hasNext
  #151 = Utf8               next
  #152 = Utf8               (Ljava/util/Map;)V
  #153 = Utf8               getActiveExecutor
  #154 = Utf8               ()Ljava/util/concurrent/ExecutorService;
  #155 = Utf8               getExternalExecutor
  #156 = Utf8               setExternalExecutor
  #157 = Utf8               start
  #158 = Utf8               entrySet
  #159 = Utf8               ()Ljava/util/Set;
  #160 = Utf8               java/util/Set
  #161 = Utf8               getKey
  #162 = Utf8               getValue
  #163 = Utf8               get
  #164 = Utf8               (Ljava/util/Map;Ljava/util/Map;Ljava/util/Map;Lorg/apache/commons/lang3/concurrent/MultiBackgroundInitializer$1;)V
{
  private final java.util.Map<java.lang.String, org.apache.commons.lang3.concurrent.BackgroundInitializer<?>> childInitializers;
    descriptor: Ljava/util/Map;
    flags: (0x0012) ACC_PRIVATE, ACC_FINAL
    Signature: #44                          // Ljava/util/Map<Ljava/lang/String;Lorg/apache/commons/lang3/concurrent/BackgroundInitializer<*>;>;

  public org.apache.commons.lang3.concurrent.MultiBackgroundInitializer();
    descriptor: ()V
    flags: (0x0001) ACC_PUBLIC
    Code:
      stack=3, locals=1, args_size=1
         0: aload_0
         1: invokespecial #1                  // Method org/apache/commons/lang3/concurrent/BackgroundInitializer."<init>":()V
         4: aload_0
         5: new           #2                  // class java/util/HashMap
         8: dup
         9: invokespecial #3                  // Method java/util/HashMap."<init>":()V
        12: putfield      #4                  // Field childInitializers:Ljava/util/Map;
        15: return
      LineNumberTable:
        line 109: 0
        line 102: 4
        line 110: 15
      LocalVariableTable:
        Start  Length  Slot  Name   Signature
            0      16     0  this   Lorg/apache/commons/lang3/concurrent/MultiBackgroundInitializer;

  public org.apache.commons.lang3.concurrent.MultiBackgroundInitializer(java.util.concurrent.ExecutorService);
    descriptor: (Ljava/util/concurrent/ExecutorService;)V
    flags: (0x0001) ACC_PUBLIC
    Code:
      stack=3, locals=2, args_size=2
         0: aload_0
         1: aload_1
         2: invokespecial #5                  // Method org/apache/commons/lang3/concurrent/BackgroundInitializer."<init>":(Ljava/util/concurrent/ExecutorService;)V
         5: aload_0
         6: new           #2                  // class java/util/HashMap
         9: dup
        10: invokespecial #3                  // Method java/util/HashMap."<init>":()V
        13: putfield      #4                  // Field childInitializers:Ljava/util/Map;
        16: return
      LineNumberTable:
        line 120: 0
        line 102: 5
        line 121: 16
      LocalVariableTable:
        Start  Length  Slot  Name   Signature
            0      17     0  this   Lorg/apache/commons/lang3/concurrent/MultiBackgroundInitializer;
            0      17     1  exec   Ljava/util/concurrent/ExecutorService;

  public void addInitializer(java.lang.String, org.apache.commons.lang3.concurrent.BackgroundInitializer<?>);
    descriptor: (Ljava/lang/String;Lorg/apache/commons/lang3/concurrent/BackgroundInitializer;)V
    flags: (0x0001) ACC_PUBLIC
    Code:
      stack=3, locals=5, args_size=3
         0: aload_1
         1: ifnull        8
         4: iconst_1
         5: goto          9
         8: iconst_0
         9: ldc           #6                  // String Name of child initializer must not be null!
        11: iconst_0
        12: anewarray     #7                  // class java/lang/Object
        15: invokestatic  #8                  // Method org/apache/commons/lang3/Validate.isTrue:(ZLjava/lang/String;[Ljava/lang/Object;)V
        18: aload_2
        19: ifnull        26
        22: iconst_1
        23: goto          27
        26: iconst_0
        27: ldc           #9                  // String Child initializer must not be null!
        29: iconst_0
        30: anewarray     #7                  // class java/lang/Object
        33: invokestatic  #8                  // Method org/apache/commons/lang3/Validate.isTrue:(ZLjava/lang/String;[Ljava/lang/Object;)V
        36: aload_0
        37: dup
        38: astore_3
        39: monitorenter
        40: aload_0
        41: invokevirtual #10                 // Method isStarted:()Z
        44: ifeq          57
        47: new           #11                 // class java/lang/IllegalStateException
        50: dup
        51: ldc           #12                 // String addInitializer() must not be called after start()!
        53: invokespecial #13                 // Method java/lang/IllegalStateException."<init>":(Ljava/lang/String;)V
        56: athrow
        57: aload_0
        58: getfield      #4                  // Field childInitializers:Ljava/util/Map;
        61: aload_1
        62: aload_2
        63: invokeinterface #14,  3           // InterfaceMethod java/util/Map.put:(Ljava/lang/Object;Ljava/lang/Object;)Ljava/lang/Object;
        68: pop
        69: aload_3
        70: monitorexit
        71: goto          81
        74: astore        4
        76: aload_3
        77: monitorexit
        78: aload         4
        80: athrow
        81: return
      Exception table:
         from    to  target type
            40    71    74   any
            74    78    74   any
      LineNumberTable:
        line 136: 0
        line 137: 18
        line 139: 36
        line 140: 40
        line 141: 47
        line 144: 57
        line 145: 69
        line 146: 81
      LocalVariableTable:
        Start  Length  Slot  Name   Signature
            0      82     0  this   Lorg/apache/commons/lang3/concurrent/MultiBackgroundInitializer;
            0      82     1  name   Ljava/lang/String;
            0      82     2  init   Lorg/apache/commons/lang3/concurrent/BackgroundInitializer;
      LocalVariableTypeTable:
        Start  Length  Slot  Name   Signature
            0      82     2  init   Lorg/apache/commons/lang3/concurrent/BackgroundInitializer<*>;
      StackMapTable: number_of_entries = 7
        frame_type = 8 /* same */
        frame_type = 64 /* same_locals_1_stack_item */
          stack = [ int ]
        frame_type = 16 /* same */
        frame_type = 64 /* same_locals_1_stack_item */
          stack = [ int ]
        frame_type = 252 /* append */
          offset_delta = 29
          locals = [ class java/lang/Object ]
        frame_type = 80 /* same_locals_1_stack_item */
          stack = [ class java/lang/Throwable ]
        frame_type = 250 /* chop */
          offset_delta = 6
    Signature: #65                          // (Ljava/lang/String;Lorg/apache/commons/lang3/concurrent/BackgroundInitializer<*>;)V

  protected int getTaskCount();
    descriptor: ()I
    flags: (0x0004) ACC_PROTECTED
    Code:
      stack=2, locals=4, args_size=1
         0: iconst_1
         1: istore_1
         2: aload_0
         3: getfield      #4                  // Field childInitializers:Ljava/util/Map;
         6: invokeinterface #15,  1           // InterfaceMethod java/util/Map.values:()Ljava/util/Collection;
        11: invokeinterface #16,  1           // InterfaceMethod java/util/Collection.iterator:()Ljava/util/Iterator;
        16: astore_2
        17: aload_2
        18: invokeinterface #17,  1           // InterfaceMethod java/util/Iterator.hasNext:()Z
        23: ifeq          46
        26: aload_2
        27: invokeinterface #18,  1           // InterfaceMethod java/util/Iterator.next:()Ljava/lang/Object;
        32: checkcast     #19                 // class org/apache/commons/lang3/concurrent/BackgroundInitializer
        35: astore_3
        36: iload_1
        37: aload_3
        38: invokevirtual #20                 // Method org/apache/commons/lang3/concurrent/BackgroundInitializer.getTaskCount:()I
        41: iadd
        42: istore_1
        43: goto          17
        46: iload_1
        47: ireturn
      LineNumberTable:
        line 160: 0
        line 162: 2
        line 163: 36
        line 164: 43
        line 166: 46
      LocalVariableTable:
        Start  Length  Slot  Name   Signature
           36       7     3    bi   Lorg/apache/commons/lang3/concurrent/BackgroundInitializer;
            0      48     0  this   Lorg/apache/commons/lang3/concurrent/MultiBackgroundInitializer;
            2      46     1 result   I
      LocalVariableTypeTable:
        Start  Length  Slot  Name   Signature
           36       7     3    bi   Lorg/apache/commons/lang3/concurrent/BackgroundInitializer<*>;
      StackMapTable: number_of_entries = 2
        frame_type = 253 /* append */
          offset_delta = 17
          locals = [ int, class java/util/Iterator ]
        frame_type = 250 /* chop */
          offset_delta = 28

  protected org.apache.commons.lang3.concurrent.MultiBackgroundInitializer$MultiBackgroundInitializerResults initialize() throws java.lang.Exception;
    descriptor: ()Lorg/apache/commons/lang3/concurrent/MultiBackgroundInitializer$MultiBackgroundInitializerResults;
    flags: (0x0004) ACC_PROTECTED
    Code:
      stack=6, locals=8, args_size=1
         0: aload_0
         1: dup
         2: astore_2
         3: monitorenter
         4: new           #2                  // class java/util/HashMap
         7: dup
         8: aload_0
         9: getfield      #4                  // Field childInitializers:Ljava/util/Map;
        12: invokespecial #21                 // Method java/util/HashMap."<init>":(Ljava/util/Map;)V
        15: astore_1
        16: aload_2
        17: monitorexit
        18: goto          26
        21: astore_3
        22: aload_2
        23: monitorexit
        24: aload_3
        25: athrow
        26: aload_0
        27: invokevirtual #22                 // Method getActiveExecutor:()Ljava/util/concurrent/ExecutorService;
        30: astore_2
        31: aload_1
        32: invokeinterface #15,  1           // InterfaceMethod java/util/Map.values:()Ljava/util/Collection;
        37: invokeinterface #16,  1           // InterfaceMethod java/util/Collection.iterator:()Ljava/util/Iterator;
        42: astore_3
        43: aload_3
        44: invokeinterface #17,  1           // InterfaceMethod java/util/Iterator.hasNext:()Z
        49: ifeq          86
        52: aload_3
        53: invokeinterface #18,  1           // InterfaceMethod java/util/Iterator.next:()Ljava/lang/Object;
        58: checkcast     #19                 // class org/apache/commons/lang3/concurrent/BackgroundInitializer
        61: astore        4
        63: aload         4
        65: invokevirtual #23                 // Method org/apache/commons/lang3/concurrent/BackgroundInitializer.getExternalExecutor:()Ljava/util/concurrent/ExecutorService;
        68: ifnonnull     77
        71: aload         4
        73: aload_2
        74: invokevirtual #24                 // Method org/apache/commons/lang3/concurrent/BackgroundInitializer.setExternalExecutor:(Ljava/util/concurrent/ExecutorService;)V
        77: aload         4
        79: invokevirtual #25                 // Method org/apache/commons/lang3/concurrent/BackgroundInitializer.start:()Z
        82: pop
        83: goto          43
        86: new           #2                  // class java/util/HashMap
        89: dup
        90: invokespecial #3                  // Method java/util/HashMap."<init>":()V
        93: astore_3
        94: new           #2                  // class java/util/HashMap
        97: dup
        98: invokespecial #3                  // Method java/util/HashMap."<init>":()V
       101: astore        4
       103: aload_1
       104: invokeinterface #26,  1           // InterfaceMethod java/util/Map.entrySet:()Ljava/util/Set;
       109: invokeinterface #27,  1           // InterfaceMethod java/util/Set.iterator:()Ljava/util/Iterator;
       114: astore        5
       116: aload         5
       118: invokeinterface #17,  1           // InterfaceMethod java/util/Iterator.hasNext:()Z
       123: ifeq          196
       126: aload         5
       128: invokeinterface #18,  1           // InterfaceMethod java/util/Iterator.next:()Ljava/lang/Object;
       133: checkcast     #28                 // class java/util/Map$Entry
       136: astore        6
       138: aload_3
       139: aload         6
       141: invokeinterface #29,  1           // InterfaceMethod java/util/Map$Entry.getKey:()Ljava/lang/Object;
       146: checkcast     #30                 // class java/lang/String
       149: aload         6
       151: invokeinterface #31,  1           // InterfaceMethod java/util/Map$Entry.getValue:()Ljava/lang/Object;
       156: checkcast     #19                 // class org/apache/commons/lang3/concurrent/BackgroundInitializer
       159: invokevirtual #32                 // Method org/apache/commons/lang3/concurrent/BackgroundInitializer.get:()Ljava/lang/Object;
       162: invokeinterface #14,  3           // InterfaceMethod java/util/Map.put:(Ljava/lang/Object;Ljava/lang/Object;)Ljava/lang/Object;
       167: pop
       168: goto          193
       171: astore        7
       173: aload         4
       175: aload         6
       177: invokeinterface #29,  1           // InterfaceMethod java/util/Map$Entry.getKey:()Ljava/lang/Object;
       182: checkcast     #30                 // class java/lang/String
       185: aload         7
       187: invokeinterface #14,  3           // InterfaceMethod java/util/Map.put:(Ljava/lang/Object;Ljava/lang/Object;)Ljava/lang/Object;
       192: pop
       193: goto          116
       196: new           #34                 // class org/apache/commons/lang3/concurrent/MultiBackgroundInitializer$MultiBackgroundInitializerResults
       199: dup
       200: aload_1
       201: aload_3
       202: aload         4
       204: aconst_null
       205: invokespecial #35                 // Method org/apache/commons/lang3/concurrent/MultiBackgroundInitializer$MultiBackgroundInitializerResults."<init>":(Ljava/util/Map;Ljava/util/Map;Ljava/util/Map;Lorg/apache/commons/lang3/concurrent/MultiBackgroundInitializer$1;)V
       208: areturn
      Exception table:
         from    to  target type
             4    18    21   any
            21    24    21   any
           138   168   171   Class org/apache/commons/lang3/concurrent/ConcurrentException
      LineNumberTable:
        line 182: 0
        line 184: 4
        line 186: 16
        line 189: 26
        line 190: 31
        line 191: 63
        line 193: 71
        line 195: 77
        line 196: 83
        line 199: 86
        line 200: 94
        line 201: 103
        line 203: 138
        line 206: 168
        line 204: 171
        line 205: 173
        line 207: 193
        line 209: 196
      LocalVariableTable:
        Start  Length  Slot  Name   Signature
           16       5     1 inits   Ljava/util/Map;
           63      20     4    bi   Lorg/apache/commons/lang3/concurrent/BackgroundInitializer;
          173      20     7   cex   Lorg/apache/commons/lang3/concurrent/ConcurrentException;
          138      55     6     e   Ljava/util/Map$Entry;
            0     209     0  this   Lorg/apache/commons/lang3/concurrent/MultiBackgroundInitializer;
           26     183     1 inits   Ljava/util/Map;
           31     178     2  exec   Ljava/util/concurrent/ExecutorService;
           94     115     3 results   Ljava/util/Map;
          103     106     4 excepts   Ljava/util/Map;
      LocalVariableTypeTable:
        Start  Length  Slot  Name   Signature
           16       5     1 inits   Ljava/util/Map<Ljava/lang/String;Lorg/apache/commons/lang3/concurrent/BackgroundInitializer<*>;>;
           63      20     4    bi   Lorg/apache/commons/lang3/concurrent/BackgroundInitializer<*>;
          138      55     6     e   Ljava/util/Map$Entry<Ljava/lang/String;Lorg/apache/commons/lang3/concurrent/BackgroundInitializer<*>;>;
           26     183     1 inits   Ljava/util/Map<Ljava/lang/String;Lorg/apache/commons/lang3/concurrent/BackgroundInitializer<*>;>;
           94     115     3 results   Ljava/util/Map<Ljava/lang/String;Ljava/lang/Object;>;
          103     106     4 excepts   Ljava/util/Map<Ljava/lang/String;Lorg/apache/commons/lang3/concurrent/ConcurrentException;>;
      StackMapTable: number_of_entries = 9
        frame_type = 255 /* full_frame */
          offset_delta = 21
          locals = [ class org/apache/commons/lang3/concurrent/MultiBackgroundInitializer, top, class java/lang/Object ]
          stack = [ class java/lang/Throwable ]
        frame_type = 255 /* full_frame */
          offset_delta = 4
          locals = [ class org/apache/commons/lang3/concurrent/MultiBackgroundInitializer, class java/util/Map ]
          stack = []
        frame_type = 253 /* append */
          offset_delta = 16
          locals = [ class java/util/concurrent/ExecutorService, class java/util/Iterator ]
        frame_type = 252 /* append */
          offset_delta = 33
          locals = [ class org/apache/commons/lang3/concurrent/BackgroundInitializer ]
        frame_type = 249 /* chop */
          offset_delta = 8
        frame_type = 254 /* append */
          offset_delta = 29
          locals = [ class java/util/Map, class java/util/Map, class java/util/Iterator ]
        frame_type = 255 /* full_frame */
          offset_delta = 54
          locals = [ class org/apache/commons/lang3/concurrent/MultiBackgroundInitializer, class java/util/Map, class java/util/concurrent/ExecutorService, class java/util/Map, class java/util/Map, class java/util/Iterator, class java/util/Map$Entry ]
          stack = [ class org/apache/commons/lang3/concurrent/ConcurrentException ]
        frame_type = 250 /* chop */
          offset_delta = 21
        frame_type = 250 /* chop */
          offset_delta = 2
    Exceptions:
      throws java.lang.Exception

  protected java.lang.Object initialize() throws java.lang.Exception;
    descriptor: ()Ljava/lang/Object;
    flags: (0x1044) ACC_PROTECTED, ACC_BRIDGE, ACC_SYNTHETIC
    Code:
      stack=1, locals=1, args_size=1
         0: aload_0
         1: invokevirtual #36                 // Method initialize:()Lorg/apache/commons/lang3/concurrent/MultiBackgroundInitializer$MultiBackgroundInitializerResults;
         4: areturn
      LineNumberTable:
        line 98: 0
      LocalVariableTable:
        Start  Length  Slot  Name   Signature
            0       5     0  this   Lorg/apache/commons/lang3/concurrent/MultiBackgroundInitializer;
    Exceptions:
      throws java.lang.Exception
}
Signature: #90                          // Lorg/apache/commons/lang3/concurrent/BackgroundInitializer<Lorg/apache/commons/lang3/concurrent/MultiBackgroundInitializer$MultiBackgroundInitializerResults;>;
SourceFile: "MultiBackgroundInitializer.java"
InnerClasses:
  static #38;                             // class org/apache/commons/lang3/concurrent/MultiBackgroundInitializer$1
  public static #40= #34 of #37;          // MultiBackgroundInitializerResults=class org/apache/commons/lang3/concurrent/MultiBackgroundInitializer$MultiBackgroundInitializerResults of class org/apache/commons/lang3/concurrent/MultiBackgroundInitializer
  public static #78= #28 of #85;          // Entry=class java/util/Map$Entry of class java/util/Map
