Classfile /Users/mw/Projects/slang-braindump/.jar/jar11/assemble/slang-braindump/assemble/content/scala/collection/AnyStepper$$anon$5.class
  Last modified May 29, 2022; size 832 bytes
  SHA-256 checksum 2cacef0e7a45523af6fa5790ed4526c384361c8bb6e1f9684bb520802928c6d5
  Compiled from "Stepper.scala"
public final class scala.collection.AnyStepper$$anon$5 extends scala.collection.AnyStepper$BoxedLongStepper implements scala.collection.Stepper$EfficientSplit
  minor version: 0
  major version: 52
  flags: (0x0031) ACC_PUBLIC, ACC_FINAL, ACC_SUPER
  this_class: #2                          // scala/collection/AnyStepper$$anon$5
  super_class: #4                         // scala/collection/AnyStepper$BoxedLongStepper
  interfaces: 1, fields: 0, methods: 1, attributes: 5
Constant pool:
   #1 = Utf8               scala/collection/AnyStepper$$anon$5
   #2 = Class              #1             // scala/collection/AnyStepper$$anon$5
   #3 = Utf8               scala/collection/AnyStepper$BoxedLongStepper
   #4 = Class              #3             // scala/collection/AnyStepper$BoxedLongStepper
   #5 = Utf8               scala/collection/Stepper$EfficientSplit
   #6 = Class              #5             // scala/collection/Stepper$EfficientSplit
   #7 = Utf8               Stepper.scala
   #8 = Utf8               scala/collection/AnyStepper$
   #9 = Class              #8             // scala/collection/AnyStepper$
  #10 = Utf8               ofParLongStepper
  #11 = Utf8               (Lscala/collection/LongStepper;)Lscala/collection/AnyStepper;
  #12 = NameAndType        #10:#11        // ofParLongStepper:(Lscala/collection/LongStepper;)Lscala/collection/AnyStepper;
  #13 = Utf8               scala/collection/AnyStepper
  #14 = Class              #13            // scala/collection/AnyStepper
  #15 = Utf8               BoxedLongStepper
  #16 = Utf8               scala/collection/Stepper
  #17 = Class              #16            // scala/collection/Stepper
  #18 = Utf8               EfficientSplit
  #19 = Utf8               <init>
  #20 = Utf8               (Lscala/collection/LongStepper;)V
  #21 = Utf8               st$3
  #22 = NameAndType        #19:#20        // "<init>":(Lscala/collection/LongStepper;)V
  #23 = Methodref          #4.#22         // scala/collection/AnyStepper$BoxedLongStepper."<init>":(Lscala/collection/LongStepper;)V
  #24 = Utf8               this
  #25 = Utf8               Lscala/collection/AnyStepper$$anon$5;
  #26 = Utf8               Lscala/collection/LongStepper;
  #27 = Utf8               Code
  #28 = Utf8               LineNumberTable
  #29 = Utf8               LocalVariableTable
  #30 = Utf8               MethodParameters
  #31 = Utf8               InnerClasses
  #32 = Utf8               EnclosingMethod
  #33 = Utf8               SourceFile
  #34 = Utf8               ScalaInlineInfo
  #35 = Utf8               Scala
{
  public scala.collection.AnyStepper$$anon$5(scala.collection.LongStepper);
    descriptor: (Lscala/collection/LongStepper;)V
    flags: (0x0001) ACC_PUBLIC
    Code:
      stack=2, locals=2, args_size=2
         0: aload_0
         1: aload_1
         2: invokespecial #23                 // Method scala/collection/AnyStepper$BoxedLongStepper."<init>":(Lscala/collection/LongStepper;)V
         5: return
      LineNumberTable:
        line 218: 0
      LocalVariableTable:
        Start  Length  Slot  Name   Signature
            0       6     0  this   Lscala/collection/AnyStepper$$anon$5;
            0       6     1  st$3   Lscala/collection/LongStepper;
    MethodParameters:
      Name                           Flags
      st$3                           final
}
InnerClasses:
  public final #2;                        // class scala/collection/AnyStepper$$anon$5
  public static #15= #4 of #14;           // BoxedLongStepper=class scala/collection/AnyStepper$BoxedLongStepper of class scala/collection/AnyStepper
  public static #18= #6 of #17;           // EfficientSplit=class scala/collection/Stepper$EfficientSplit of class scala/collection/Stepper
EnclosingMethod: #9.#12                 // scala.collection.AnyStepper$.ofParLongStepper
SourceFile: "Stepper.scala"
  ScalaInlineInfo: length = 0x9 (unknown attribute)
   01 01 00 01 00 13 00 14 01
  Scala: length = 0x0 (unknown attribute)

