Classfile /Users/mw/Projects/slang-braindump/.jar/jar11/assemble/slang-braindump/assemble/content/scala/collection/ArrayOps$ArrayView.class
  Last modified May 29, 2022; size 1910 bytes
  SHA-256 checksum 39d67760843f86cdf19cb87d856703c7e7dcbaa7743c35aa7fbe28281b3bf735
  Compiled from "ArrayOps.scala"
public class scala.collection.ArrayOps$ArrayView<A extends java.lang.Object> extends scala.collection.AbstractIndexedSeqView<A>
  minor version: 0
  major version: 52
  flags: (0x0021) ACC_PUBLIC, ACC_SUPER
  this_class: #2                          // scala/collection/ArrayOps$ArrayView
  super_class: #5                         // scala/collection/AbstractIndexedSeqView
  interfaces: 0, fields: 2, methods: 4, attributes: 5
Constant pool:
   #1 = Utf8               scala/collection/ArrayOps$ArrayView
   #2 = Class              #1             // scala/collection/ArrayOps$ArrayView
   #3 = Utf8               <A:Ljava/lang/Object;>Lscala/collection/AbstractIndexedSeqView<TA;>;
   #4 = Utf8               scala/collection/AbstractIndexedSeqView
   #5 = Class              #4             // scala/collection/AbstractIndexedSeqView
   #6 = Utf8               ArrayOps.scala
   #7 = Utf8               scala/collection/ArrayOps
   #8 = Class              #7             // scala/collection/ArrayOps
   #9 = Utf8               ArrayView
  #10 = Utf8               serialVersionUID
  #11 = Utf8               J
  #12 = Long               3l
  #14 = Utf8               xs
  #15 = Utf8               Ljava/lang/Object;
  #16 = Utf8               length
  #17 = Utf8               ()I
  #18 = NameAndType        #14:#15        // xs:Ljava/lang/Object;
  #19 = Fieldref           #2.#18         // scala/collection/ArrayOps$ArrayView.xs:Ljava/lang/Object;
  #20 = Utf8               java/lang/reflect/Array
  #21 = Class              #20            // java/lang/reflect/Array
  #22 = Utf8               getLength
  #23 = Utf8               (Ljava/lang/Object;)I
  #24 = NameAndType        #22:#23        // getLength:(Ljava/lang/Object;)I
  #25 = Methodref          #21.#24        // java/lang/reflect/Array.getLength:(Ljava/lang/Object;)I
  #26 = Utf8               this
  #27 = Utf8               Lscala/collection/ArrayOps$ArrayView;
  #28 = Utf8               apply
  #29 = Utf8               (I)Ljava/lang/Object;
  #30 = Utf8               (I)TA;
  #31 = Utf8               n
  #32 = Utf8               scala/runtime/ScalaRunTime$
  #33 = Class              #32            // scala/runtime/ScalaRunTime$
  #34 = Utf8               MODULE$
  #35 = Utf8               Lscala/runtime/ScalaRunTime$;
  #36 = NameAndType        #34:#35        // MODULE$:Lscala/runtime/ScalaRunTime$;
  #37 = Fieldref           #33.#36        // scala/runtime/ScalaRunTime$.MODULE$:Lscala/runtime/ScalaRunTime$;
  #38 = Utf8               array_apply
  #39 = Utf8               (Ljava/lang/Object;I)Ljava/lang/Object;
  #40 = NameAndType        #38:#39        // array_apply:(Ljava/lang/Object;I)Ljava/lang/Object;
  #41 = Methodref          #33.#40        // scala/runtime/ScalaRunTime$.array_apply:(Ljava/lang/Object;I)Ljava/lang/Object;
  #42 = Utf8               I
  #43 = Utf8               toString
  #44 = Utf8               ()Ljava/lang/String;
  #45 = Utf8               scala/collection/immutable/ArraySeq$
  #46 = Class              #45            // scala/collection/immutable/ArraySeq$
  #47 = Utf8               Lscala/collection/immutable/ArraySeq$;
  #48 = NameAndType        #34:#47        // MODULE$:Lscala/collection/immutable/ArraySeq$;
  #49 = Fieldref           #46.#48        // scala/collection/immutable/ArraySeq$.MODULE$:Lscala/collection/immutable/ArraySeq$;
  #50 = Utf8               unsafeWrapArray
  #51 = Utf8               (Ljava/lang/Object;)Lscala/collection/immutable/ArraySeq;
  #52 = NameAndType        #50:#51        // unsafeWrapArray:(Ljava/lang/Object;)Lscala/collection/immutable/ArraySeq;
  #53 = Methodref          #46.#52        // scala/collection/immutable/ArraySeq$.unsafeWrapArray:(Ljava/lang/Object;)Lscala/collection/immutable/ArraySeq;
  #54 = Utf8               ArrayView(
  #55 = String             #54            // ArrayView(
  #56 = Utf8               ,
  #57 = String             #56            // ,
  #58 = Utf8               )
  #59 = String             #58            // )
  #60 = Utf8               scala/collection/IterableOnceOps
  #61 = Class              #60            // scala/collection/IterableOnceOps
  #62 = Utf8               mkString$
  #63 = Utf8               (Lscala/collection/IterableOnceOps;Ljava/lang/String;Ljava/lang/String;Ljava/lang/String;)Ljava/lang/String;
  #64 = NameAndType        #62:#63        // mkString$:(Lscala/collection/IterableOnceOps;Ljava/lang/String;Ljava/lang/String;Ljava/lang/String;)Ljava/lang/String;
  #65 = InterfaceMethodref #61.#64        // scala/collection/IterableOnceOps.mkString$:(Lscala/collection/IterableOnceOps;Ljava/lang/String;Ljava/lang/String;Ljava/lang/String;)Ljava/lang/String;
  #66 = Utf8               mkString_start
  #67 = Utf8               Ljava/lang/String;
  #68 = Utf8               mkString_sep
  #69 = Utf8               mkString_end
  #70 = Utf8               java/lang/String
  #71 = Class              #70            // java/lang/String
  #72 = Utf8               scala/collection/immutable/ArraySeq
  #73 = Class              #72            // scala/collection/immutable/ArraySeq
  #74 = Utf8               <init>
  #75 = Utf8               (Ljava/lang/Object;)V
  #76 = Utf8               ()V
  #77 = NameAndType        #74:#76        // "<init>":()V
  #78 = Methodref          #5.#77         // scala/collection/AbstractIndexedSeqView."<init>":()V
  #79 = Utf8               ConstantValue
  #80 = Utf8               Signature
  #81 = Utf8               Code
  #82 = Utf8               LineNumberTable
  #83 = Utf8               LocalVariableTable
  #84 = Utf8               MethodParameters
  #85 = Utf8               StackMapTable
  #86 = Utf8               InnerClasses
  #87 = Utf8               SourceFile
  #88 = Utf8               ScalaInlineInfo
  #89 = Utf8               Scala
{
  private static final long serialVersionUID;
    descriptor: J
    flags: (0x001a) ACC_PRIVATE, ACC_STATIC, ACC_FINAL
    ConstantValue: long 3l

  private final java.lang.Object xs;
    descriptor: Ljava/lang/Object;
    flags: (0x0012) ACC_PRIVATE, ACC_FINAL
    Signature: #15                          // Ljava/lang/Object;

  public int length();
    descriptor: ()I
    flags: (0x0001) ACC_PUBLIC
    Code:
      stack=1, locals=1, args_size=1
         0: aload_0
         1: getfield      #19                 // Field xs:Ljava/lang/Object;
         4: invokestatic  #25                 // Method java/lang/reflect/Array.getLength:(Ljava/lang/Object;)I
         7: ireturn
      LineNumberTable:
        line 57: 0
      LocalVariableTable:
        Start  Length  Slot  Name   Signature
            0       8     0  this   Lscala/collection/ArrayOps$ArrayView;

  public A apply(int);
    descriptor: (I)Ljava/lang/Object;
    flags: (0x0001) ACC_PUBLIC
    Code:
      stack=3, locals=2, args_size=2
         0: getstatic     #37                 // Field scala/runtime/ScalaRunTime$.MODULE$:Lscala/runtime/ScalaRunTime$;
         3: aload_0
         4: getfield      #19                 // Field xs:Ljava/lang/Object;
         7: iload_1
         8: invokevirtual #41                 // Method scala/runtime/ScalaRunTime$.array_apply:(Ljava/lang/Object;I)Ljava/lang/Object;
        11: areturn
      LineNumberTable:
        line 58: 0
      LocalVariableTable:
        Start  Length  Slot  Name   Signature
            0      12     0  this   Lscala/collection/ArrayOps$ArrayView;
            0      12     1     n   I
    Signature: #30                          // (I)TA;
    MethodParameters:
      Name                           Flags
      n                              final

  public java.lang.String toString();
    descriptor: ()Ljava/lang/String;
    flags: (0x0001) ACC_PUBLIC
    Code:
      stack=4, locals=4, args_size=1
         0: getstatic     #49                 // Field scala/collection/immutable/ArraySeq$.MODULE$:Lscala/collection/immutable/ArraySeq$;
         3: aload_0
         4: getfield      #19                 // Field xs:Ljava/lang/Object;
         7: invokevirtual #53                 // Method scala/collection/immutable/ArraySeq$.unsafeWrapArray:(Ljava/lang/Object;)Lscala/collection/immutable/ArraySeq;
        10: ldc           #55                 // String ArrayView(
        12: ldc           #57                 // String ,
        14: ldc           #59                 // String )
        16: astore_3
        17: astore_2
        18: astore_1
        19: dup
        20: ifnonnull     25
        23: aconst_null
        24: athrow
        25: aload_1
        26: aload_2
        27: aload_3
        28: invokestatic  #65                 // InterfaceMethod scala/collection/IterableOnceOps.mkString$:(Lscala/collection/IterableOnceOps;Ljava/lang/String;Ljava/lang/String;Ljava/lang/String;)Ljava/lang/String;
        31: areturn
      StackMapTable: number_of_entries = 1
        frame_type = 255 /* full_frame */
          offset_delta = 25
          locals = [ class scala/collection/ArrayOps$ArrayView, class java/lang/String, class java/lang/String, class java/lang/String ]
          stack = [ class scala/collection/immutable/ArraySeq ]
      LineNumberTable:
        line 59: 0
      LocalVariableTable:
        Start  Length  Slot  Name   Signature
            0      32     0  this   Lscala/collection/ArrayOps$ArrayView;
           25       6     1 mkString_start   Ljava/lang/String;
           25       6     2 mkString_sep   Ljava/lang/String;
           25       6     3 mkString_end   Ljava/lang/String;

  public scala.collection.ArrayOps$ArrayView(java.lang.Object);
    descriptor: (Ljava/lang/Object;)V
    flags: (0x0001) ACC_PUBLIC
    Code:
      stack=2, locals=2, args_size=2
         0: aload_0
         1: aload_1
         2: putfield      #19                 // Field xs:Ljava/lang/Object;
         5: aload_0
         6: invokespecial #78                 // Method scala/collection/AbstractIndexedSeqView."<init>":()V
         9: return
      LineNumberTable:
        line 56: 0
      LocalVariableTable:
        Start  Length  Slot  Name   Signature
            0      10     0  this   Lscala/collection/ArrayOps$ArrayView;
            0      10     1    xs   Ljava/lang/Object;
    Signature: #75                          // (Ljava/lang/Object;)V
    MethodParameters:
      Name                           Flags
      xs                             final
}
InnerClasses:
  private static #9= #2 of #8;            // ArrayView=class scala/collection/ArrayOps$ArrayView of class scala/collection/ArrayOps
Signature: #3                           // <A:Ljava/lang/Object;>Lscala/collection/AbstractIndexedSeqView<TA;>;
SourceFile: "ArrayOps.scala"
  ScalaInlineInfo: length = 0x18 (unknown attribute)
   01 00 00 04 00 4A 00 4B 00 00 1C 00 1D 00 00 10
   00 11 00 00 2B 00 2C 00
  Scala: length = 0x0 (unknown attribute)

