Classfile /Users/mw/Projects/slang-braindump/.jar/jar11/assemble/slang-braindump/assemble/content/scala/collection/BufferedIterator.class
  Last modified May 29, 2022; size 1825 bytes
  SHA-256 checksum e8c7ab16c4f527de40607c16ccc2f7a229127dc6c6e84a492873c4ed970dea78
  Compiled from "BufferedIterator.scala"
public interface scala.collection.BufferedIterator<A extends java.lang.Object> extends scala.collection.Iterator<A>
  minor version: 0
  major version: 52
  flags: (0x0601) ACC_PUBLIC, ACC_INTERFACE, ACC_ABSTRACT
  this_class: #2                          // scala/collection/BufferedIterator
  super_class: #5                         // java/lang/Object
  interfaces: 1, fields: 0, methods: 6, attributes: 5
Constant pool:
   #1 = Utf8               scala/collection/BufferedIterator
   #2 = Class              #1             // scala/collection/BufferedIterator
   #3 = Utf8               <A:Ljava/lang/Object;>Ljava/lang/Object;Lscala/collection/Iterator<TA;>;
   #4 = Utf8               java/lang/Object
   #5 = Class              #4             // java/lang/Object
   #6 = Utf8               scala/collection/Iterator
   #7 = Class              #6             // scala/collection/Iterator
   #8 = Utf8               BufferedIterator.scala
   #9 = Utf8               Lscala/reflect/ScalaSignature;
  #10 = Utf8               bytes
  #11 = Utf8               \u0006\u0005=2q!\u0002\u0004\u0011\u0002\u0007\u00051\u0002C\u0003!\u0001\u0011\u0005\u0011\u0005C\u0003&\u0001\u0019\u0005a\u0005C\u0003(\u0001\u0011\u0005\u0001\u0006C\u0003-\u0001\u0011\u0005SF\u0001\tCk\u001a4WM]3e\u0013R,\'/\u0019;pe*\u0011q\u0001C\u0001\u000bG>dG.Z2uS>t\'\"A\u0005\u0002\u000bM\u001c\u0017\r\\1\u0004\u0001U\u0011AbF\n\u0004\u00015\t\u0002C\u0001\b\u0010\u001b\u0005A\u0011B\u0001\t\t\u0005\u0019\te.\u001f*fMB\u0019!cE\u000b\u000e\u0003\u0019I!\u0001\u0006\u0004\u0003\u0011%#XM]1u_J\u0004\"AF\f\r\u0001\u00111\u0001\u0004\u0001CC\u0002e\u0011\u0011!Q\t\u00035u\u0001\"AD\u000e\n\u0005qA!a\u0002(pi\"Lgn\u001a\t\u0003\u001dyI!a\b\u0005\u0003\u0007\u0005s\u00170\u0001\u0004%S:LG\u000f\n\u000b\u0002EA\u0011abI\u0005\u0003I!\u0011A!\u00168ji\u0006!\u0001.Z1e+\u0005)\u0012A\u00035fC\u0012|\u0005\u000f^5p]V\t\u0011\u0006E\u0002\u000fUUI!a\u000b\u0005\u0003\r=\u0003H/[8o\u0003!\u0011WO\u001a4fe\u0016$W#\u0001\u0018\u000e\u0003\u0001\u0001
  #12 = Utf8               head
  #13 = Utf8               ()Ljava/lang/Object;
  #14 = Utf8               ()TA;
  #15 = Utf8               headOption$
  #16 = Utf8               (Lscala/collection/BufferedIterator;)Lscala/Option;
  #17 = Utf8               $this
  #18 = Utf8               headOption
  #19 = Utf8               ()Lscala/Option;
  #20 = NameAndType        #18:#19        // headOption:()Lscala/Option;
  #21 = InterfaceMethodref #2.#20         // scala/collection/BufferedIterator.headOption:()Lscala/Option;
  #22 = Utf8               Lscala/collection/BufferedIterator;
  #23 = Utf8               ()Lscala/Option<TA;>;
  #24 = Utf8               hasNext
  #25 = Utf8               ()Z
  #26 = NameAndType        #24:#25        // hasNext:()Z
  #27 = InterfaceMethodref #2.#26         // scala/collection/BufferedIterator.hasNext:()Z
  #28 = Utf8               scala/Some
  #29 = Class              #28            // scala/Some
  #30 = NameAndType        #12:#13        // head:()Ljava/lang/Object;
  #31 = InterfaceMethodref #2.#30         // scala/collection/BufferedIterator.head:()Ljava/lang/Object;
  #32 = Utf8               <init>
  #33 = Utf8               (Ljava/lang/Object;)V
  #34 = NameAndType        #32:#33        // "<init>":(Ljava/lang/Object;)V
  #35 = Methodref          #29.#34        // scala/Some."<init>":(Ljava/lang/Object;)V
  #36 = Utf8               scala/None$
  #37 = Class              #36            // scala/None$
  #38 = Utf8               MODULE$
  #39 = Utf8               Lscala/None$;
  #40 = NameAndType        #38:#39        // MODULE$:Lscala/None$;
  #41 = Fieldref           #37.#40        // scala/None$.MODULE$:Lscala/None$;
  #42 = Utf8               this
  #43 = Utf8               buffered$
  #44 = Utf8               (Lscala/collection/BufferedIterator;)Lscala/collection/BufferedIterator;
  #45 = Utf8               buffered
  #46 = Utf8               ()Lscala/collection/BufferedIterator;
  #47 = NameAndType        #45:#46        // buffered:()Lscala/collection/BufferedIterator;
  #48 = InterfaceMethodref #2.#47         // scala/collection/BufferedIterator.buffered:()Lscala/collection/BufferedIterator;
  #49 = Utf8               ()Lscala/collection/BufferedIterator<TA;>;
  #50 = Utf8               $init$
  #51 = Utf8               (Lscala/collection/BufferedIterator;)V
  #52 = Utf8               Signature
  #53 = Utf8               Code
  #54 = Utf8               LineNumberTable
  #55 = Utf8               LocalVariableTable
  #56 = Utf8               MethodParameters
  #57 = Utf8               StackMapTable
  #58 = Utf8               SourceFile
  #59 = Utf8               RuntimeVisibleAnnotations
  #60 = Utf8               ScalaInlineInfo
  #61 = Utf8               ScalaSig
{
  public abstract A head();
    descriptor: ()Ljava/lang/Object;
    flags: (0x0401) ACC_PUBLIC, ACC_ABSTRACT
    Signature: #14                          // ()TA;

  public static scala.Option headOption$(scala.collection.BufferedIterator);
    descriptor: (Lscala/collection/BufferedIterator;)Lscala/Option;
    flags: (0x1009) ACC_PUBLIC, ACC_STATIC, ACC_SYNTHETIC
    Code:
      stack=1, locals=1, args_size=1
         0: aload_0
         1: invokespecial #21                 // InterfaceMethod headOption:()Lscala/Option;
         4: areturn
      LineNumberTable:
        line 29: 0
      LocalVariableTable:
        Start  Length  Slot  Name   Signature
            0       5     0 $this   Lscala/collection/BufferedIterator;
    MethodParameters:
      Name                           Flags
      $this                          final synthetic

  public default scala.Option<A> headOption();
    descriptor: ()Lscala/Option;
    flags: (0x0001) ACC_PUBLIC
    Code:
      stack=3, locals=1, args_size=1
         0: aload_0
         1: invokeinterface #27,  1           // InterfaceMethod hasNext:()Z
         6: ifeq          23
         9: new           #29                 // class scala/Some
        12: dup
        13: aload_0
        14: invokeinterface #31,  1           // InterfaceMethod head:()Ljava/lang/Object;
        19: invokespecial #35                 // Method scala/Some."<init>":(Ljava/lang/Object;)V
        22: areturn
        23: getstatic     #41                 // Field scala/None$.MODULE$:Lscala/None$;
        26: areturn
      StackMapTable: number_of_entries = 1
        frame_type = 23 /* same */
      LineNumberTable:
        line 29: 0
      LocalVariableTable:
        Start  Length  Slot  Name   Signature
            0      27     0  this   Lscala/collection/BufferedIterator;
    Signature: #23                          // ()Lscala/Option<TA;>;

  public static scala.collection.BufferedIterator buffered$(scala.collection.BufferedIterator);
    descriptor: (Lscala/collection/BufferedIterator;)Lscala/collection/BufferedIterator;
    flags: (0x1009) ACC_PUBLIC, ACC_STATIC, ACC_SYNTHETIC
    Code:
      stack=1, locals=1, args_size=1
         0: aload_0
         1: invokespecial #48                 // InterfaceMethod buffered:()Lscala/collection/BufferedIterator;
         4: areturn
      LineNumberTable:
        line 31: 0
      LocalVariableTable:
        Start  Length  Slot  Name   Signature
            0       5     0 $this   Lscala/collection/BufferedIterator;
    MethodParameters:
      Name                           Flags
      $this                          final synthetic

  public default scala.collection.BufferedIterator<A> buffered();
    descriptor: ()Lscala/collection/BufferedIterator;
    flags: (0x0001) ACC_PUBLIC
    Code:
      stack=1, locals=1, args_size=1
         0: aload_0
         1: areturn
      LineNumberTable:
        line 31: 0
      LocalVariableTable:
        Start  Length  Slot  Name   Signature
            0       2     0  this   Lscala/collection/BufferedIterator;
    Signature: #49                          // ()Lscala/collection/BufferedIterator<TA;>;

  public static void $init$(scala.collection.BufferedIterator);
    descriptor: (Lscala/collection/BufferedIterator;)V
    flags: (0x0009) ACC_PUBLIC, ACC_STATIC
    Code:
      stack=0, locals=1, args_size=1
         0: return
      LineNumberTable:
        line 19: 0
      LocalVariableTable:
        Start  Length  Slot  Name   Signature
            0       1     0 $this   Lscala/collection/BufferedIterator;
    MethodParameters:
      Name                           Flags
      $this                          final synthetic
}
Signature: #3                           // <A:Ljava/lang/Object;>Ljava/lang/Object;Lscala/collection/Iterator<TA;>;
SourceFile: "BufferedIterator.scala"
RuntimeVisibleAnnotations:
  0: #9(#10=s#11)
    scala.reflect.ScalaSignature(
      bytes="\u0006\u0005=2q!\u0002\u0004\u0011\u0002\u0007\u00051\u0002C\u0003!\u0001\u0011\u0005\u0011\u0005C\u0003&\u0001\u0019\u0005a\u0005C\u0003(\u0001\u0011\u0005\u0001\u0006C\u0003-\u0001\u0011\u0005SF\u0001\tCk\u001a4WM]3e\u0013R,\'/\u0019;pe*\u0011q\u0001C\u0001\u000bG>dG.Z2uS>t\'\"A\u0005\u0002\u000bM\u001c\u0017\r\\1\u0004\u0001U\u0011AbF\n\u0004\u00015\t\u0002C\u0001\b\u0010\u001b\u0005A\u0011B\u0001\t\t\u0005\u0019\te.\u001f*fMB\u0019!cE\u000b\u000e\u0003\u0019I!\u0001\u0006\u0004\u0003\u0011%#XM]1u_J\u0004\"AF\f\r\u0001\u00111\u0001\u0004\u0001CC\u0002e\u0011\u0011!Q\t\u00035u\u0001\"AD\u000e\n\u0005qA!a\u0002(pi\"Lgn\u001a\t\u0003\u001dyI!a\b\u0005\u0003\u0007\u0005s\u00170\u0001\u0004%S:LG\u000f\n\u000b\u0002EA\u0011abI\u0005\u0003I!\u0011A!\u00168ji\u0006!\u0001.Z1e+\u0005)\u0012A\u00035fC\u0012|\u0005\u000f^5p]V\t\u0011\u0006E\u0002\u000fUUI!a\u000b\u0005\u0003\r=\u0003H/[8o\u0003!\u0011WO\u001a4fe\u0016$W#\u0001\u0018\u000e\u0003\u0001\u0001"
    )
  ScalaInlineInfo: length = 0x22 (unknown attribute)
   01 00 00 06 00 32 00 33 01 00 2D 00 2E 00 00 2B
   00 2C 01 00 0C 00 0D 00 00 12 00 13 00 00 0F 00
   10 01
  ScalaSig: length = 0x3 (unknown attribute)
   05 02 00
