Classfile /Users/mw/Projects/slang-braindump/.jar/jar11/assemble/slang-braindump/assemble/content/scala/collection/BuildFromLowPriority2$$anon$12.class
  Last modified May 29, 2022; size 2625 bytes
  SHA-256 checksum e7f6daf547a0b2cc3a265a3cc464dbf4dba8abc06525c9bf6dd92188acc536bb
  Compiled from "BuildFrom.scala"
public final class scala.collection.BuildFromLowPriority2$$anon$12 extends java.lang.Object implements scala.collection.BuildFrom<scala.collection.Iterator<?>, A, scala.collection.Iterator<A>>
  minor version: 0
  major version: 52
  flags: (0x0031) ACC_PUBLIC, ACC_FINAL, ACC_SUPER
  this_class: #2                          // scala/collection/BuildFromLowPriority2$$anon$12
  super_class: #5                         // java/lang/Object
  interfaces: 1, fields: 0, methods: 7, attributes: 6
Constant pool:
   #1 = Utf8               scala/collection/BuildFromLowPriority2$$anon$12
   #2 = Class              #1             // scala/collection/BuildFromLowPriority2$$anon$12
   #3 = Utf8               Ljava/lang/Object;Lscala/collection/BuildFrom<Lscala/collection/Iterator<*>;TA;Lscala/collection/Iterator<TA;>;>;
   #4 = Utf8               java/lang/Object
   #5 = Class              #4             // java/lang/Object
   #6 = Utf8               scala/collection/BuildFrom
   #7 = Class              #6             // scala/collection/BuildFrom
   #8 = Utf8               BuildFrom.scala
   #9 = Utf8               scala/collection/BuildFromLowPriority2
  #10 = Class              #9             // scala/collection/BuildFromLowPriority2
  #11 = Utf8               buildFromIterator
  #12 = Utf8               ()Lscala/collection/BuildFrom;
  #13 = NameAndType        #11:#12        // buildFromIterator:()Lscala/collection/BuildFrom;
  #14 = Utf8               scala/collection/Iterator$$anon$21
  #15 = Class              #14            // scala/collection/Iterator$$anon$21
  #16 = Utf8               apply
  #17 = Utf8               (Ljava/lang/Object;)Lscala/collection/mutable/Builder;
  #18 = Utf8               from
  #19 = Utf8               apply$
  #20 = Utf8               (Lscala/collection/BuildFrom;Ljava/lang/Object;)Lscala/collection/mutable/Builder;
  #21 = NameAndType        #19:#20        // apply$:(Lscala/collection/BuildFrom;Ljava/lang/Object;)Lscala/collection/mutable/Builder;
  #22 = InterfaceMethodref #7.#21         // scala/collection/BuildFrom.apply$:(Lscala/collection/BuildFrom;Ljava/lang/Object;)Lscala/collection/mutable/Builder;
  #23 = Utf8               this
  #24 = Utf8               Lscala/collection/BuildFromLowPriority2$$anon$12;
  #25 = Utf8               Ljava/lang/Object;
  #26 = Utf8               toFactory
  #27 = Utf8               (Ljava/lang/Object;)Lscala/collection/Factory;
  #28 = Utf8               toFactory$
  #29 = Utf8               (Lscala/collection/BuildFrom;Ljava/lang/Object;)Lscala/collection/Factory;
  #30 = NameAndType        #28:#29        // toFactory$:(Lscala/collection/BuildFrom;Ljava/lang/Object;)Lscala/collection/Factory;
  #31 = InterfaceMethodref #7.#30         // scala/collection/BuildFrom.toFactory$:(Lscala/collection/BuildFrom;Ljava/lang/Object;)Lscala/collection/Factory;
  #32 = Utf8               newBuilder
  #33 = Utf8               (Lscala/collection/Iterator;)Lscala/collection/mutable/Builder;
  #34 = Utf8               (Lscala/collection/Iterator<*>;)Lscala/collection/mutable/Builder<TA;Lscala/collection/Iterator<TA;>;>;
  #35 = Utf8               scala/collection/Iterator$
  #36 = Class              #35            // scala/collection/Iterator$
  #37 = Utf8               MODULE$
  #38 = Utf8               Lscala/collection/Iterator$;
  #39 = NameAndType        #37:#38        // MODULE$:Lscala/collection/Iterator$;
  #40 = Fieldref           #36.#39        // scala/collection/Iterator$.MODULE$:Lscala/collection/Iterator$;
  #41 = Utf8               <init>
  #42 = Utf8               ()V
  #43 = NameAndType        #41:#42        // "<init>":()V
  #44 = Methodref          #15.#43        // scala/collection/Iterator$$anon$21."<init>":()V
  #45 = Utf8               Lscala/collection/Iterator;
  #46 = Utf8               fromSpecific
  #47 = Utf8               (Lscala/collection/Iterator;Lscala/collection/IterableOnce;)Lscala/collection/Iterator;
  #48 = Utf8               (Lscala/collection/Iterator<*>;Lscala/collection/IterableOnce<TA;>;)Lscala/collection/Iterator<TA;>;
  #49 = Utf8               it
  #50 = Utf8               scala/collection/IterableOnce
  #51 = Class              #50            // scala/collection/IterableOnce
  #52 = Utf8               iterator
  #53 = Utf8               ()Lscala/collection/Iterator;
  #54 = NameAndType        #52:#53        // iterator:()Lscala/collection/Iterator;
  #55 = InterfaceMethodref #51.#54        // scala/collection/IterableOnce.iterator:()Lscala/collection/Iterator;
  #56 = Utf8               Lscala/collection/IterableOnce;
  #57 = Utf8               (Ljava/lang/Object;Lscala/collection/IterableOnce;)Ljava/lang/Object;
  #58 = Utf8               scala/collection/Iterator
  #59 = Class              #58            // scala/collection/Iterator
  #60 = NameAndType        #46:#47        // fromSpecific:(Lscala/collection/Iterator;Lscala/collection/IterableOnce;)Lscala/collection/Iterator;
  #61 = Methodref          #2.#60         // scala/collection/BuildFromLowPriority2$$anon$12.fromSpecific:(Lscala/collection/Iterator;Lscala/collection/IterableOnce;)Lscala/collection/Iterator;
  #62 = NameAndType        #32:#33        // newBuilder:(Lscala/collection/Iterator;)Lscala/collection/mutable/Builder;
  #63 = Methodref          #2.#62         // scala/collection/BuildFromLowPriority2$$anon$12.newBuilder:(Lscala/collection/Iterator;)Lscala/collection/mutable/Builder;
  #64 = Utf8               (Lscala/collection/BuildFromLowPriority2;)V
  #65 = Utf8               $outer
  #66 = Methodref          #5.#43         // java/lang/Object."<init>":()V
  #67 = Utf8               Lscala/collection/BuildFromLowPriority2;
  #68 = Utf8               Code
  #69 = Utf8               LineNumberTable
  #70 = Utf8               LocalVariableTable
  #71 = Utf8               Deprecated
  #72 = Utf8               MethodParameters
  #73 = Utf8               Signature
  #74 = Utf8               InnerClasses
  #75 = Utf8               EnclosingMethod
  #76 = Utf8               SourceFile
  #77 = Utf8               ScalaInlineInfo
  #78 = Utf8               Scala
{
  public scala.collection.mutable.Builder apply(java.lang.Object);
    descriptor: (Ljava/lang/Object;)Lscala/collection/mutable/Builder;
    flags: (0x0001) ACC_PUBLIC
    Code:
      stack=2, locals=2, args_size=2
         0: aload_0
         1: aload_1
         2: invokestatic  #22                 // InterfaceMethod scala/collection/BuildFrom.apply$:(Lscala/collection/BuildFrom;Ljava/lang/Object;)Lscala/collection/mutable/Builder;
         5: areturn
      LineNumberTable:
        line 115: 0
      LocalVariableTable:
        Start  Length  Slot  Name   Signature
            0       6     0  this   Lscala/collection/BuildFromLowPriority2$$anon$12;
            0       6     1  from   Ljava/lang/Object;
    Deprecated: true
    MethodParameters:
      Name                           Flags
      from                           final

  public scala.collection.Factory toFactory(java.lang.Object);
    descriptor: (Ljava/lang/Object;)Lscala/collection/Factory;
    flags: (0x0001) ACC_PUBLIC
    Code:
      stack=2, locals=2, args_size=2
         0: aload_0
         1: aload_1
         2: invokestatic  #31                 // InterfaceMethod scala/collection/BuildFrom.toFactory$:(Lscala/collection/BuildFrom;Ljava/lang/Object;)Lscala/collection/Factory;
         5: areturn
      LineNumberTable:
        line 115: 0
      LocalVariableTable:
        Start  Length  Slot  Name   Signature
            0       6     0  this   Lscala/collection/BuildFromLowPriority2$$anon$12;
            0       6     1  from   Ljava/lang/Object;
    MethodParameters:
      Name                           Flags
      from                           final

  public scala.collection.mutable.Builder<A, scala.collection.Iterator<A>> newBuilder(scala.collection.Iterator<?>);
    descriptor: (Lscala/collection/Iterator;)Lscala/collection/mutable/Builder;
    flags: (0x0001) ACC_PUBLIC
    Code:
      stack=2, locals=2, args_size=2
         0: getstatic     #40                 // Field scala/collection/Iterator$.MODULE$:Lscala/collection/Iterator$;
         3: pop
         4: new           #15                 // class scala/collection/Iterator$$anon$21
         7: dup
         8: invokespecial #44                 // Method scala/collection/Iterator$$anon$21."<init>":()V
        11: areturn
      LineNumberTable:
        line 116: 0
      LocalVariableTable:
        Start  Length  Slot  Name   Signature
            0      12     0  this   Lscala/collection/BuildFromLowPriority2$$anon$12;
            0      12     1  from   Lscala/collection/Iterator;
    Signature: #34                          // (Lscala/collection/Iterator<*>;)Lscala/collection/mutable/Builder<TA;Lscala/collection/Iterator<TA;>;>;
    MethodParameters:
      Name                           Flags
      from                           final

  public scala.collection.Iterator<A> fromSpecific(scala.collection.Iterator<?>, scala.collection.IterableOnce<A>);
    descriptor: (Lscala/collection/Iterator;Lscala/collection/IterableOnce;)Lscala/collection/Iterator;
    flags: (0x0001) ACC_PUBLIC
    Code:
      stack=1, locals=3, args_size=3
         0: getstatic     #40                 // Field scala/collection/Iterator$.MODULE$:Lscala/collection/Iterator$;
         3: pop
         4: aload_2
         5: invokeinterface #55,  1           // InterfaceMethod scala/collection/IterableOnce.iterator:()Lscala/collection/Iterator;
        10: areturn
      LineNumberTable:
        line 117: 0
      LocalVariableTable:
        Start  Length  Slot  Name   Signature
            0      11     0  this   Lscala/collection/BuildFromLowPriority2$$anon$12;
            0      11     1  from   Lscala/collection/Iterator;
            0      11     2    it   Lscala/collection/IterableOnce;
    Signature: #48                          // (Lscala/collection/Iterator<*>;Lscala/collection/IterableOnce<TA;>;)Lscala/collection/Iterator<TA;>;
    MethodParameters:
      Name                           Flags
      from                           final
      it                             final

  public java.lang.Object fromSpecific(java.lang.Object, scala.collection.IterableOnce);
    descriptor: (Ljava/lang/Object;Lscala/collection/IterableOnce;)Ljava/lang/Object;
    flags: (0x1041) ACC_PUBLIC, ACC_BRIDGE, ACC_SYNTHETIC
    Code:
      stack=3, locals=3, args_size=3
         0: aload_0
         1: aload_1
         2: checkcast     #59                 // class scala/collection/Iterator
         5: aload_2
         6: invokevirtual #61                 // Method fromSpecific:(Lscala/collection/Iterator;Lscala/collection/IterableOnce;)Lscala/collection/Iterator;
         9: areturn
      LineNumberTable:
        line 115: 0
      LocalVariableTable:
        Start  Length  Slot  Name   Signature
            0      10     0  this   Lscala/collection/BuildFromLowPriority2$$anon$12;
            0      10     1  from   Ljava/lang/Object;
            0      10     2    it   Lscala/collection/IterableOnce;
    MethodParameters:
      Name                           Flags
      from                           final
      it                             final

  public scala.collection.mutable.Builder newBuilder(java.lang.Object);
    descriptor: (Ljava/lang/Object;)Lscala/collection/mutable/Builder;
    flags: (0x1041) ACC_PUBLIC, ACC_BRIDGE, ACC_SYNTHETIC
    Code:
      stack=2, locals=2, args_size=2
         0: aload_0
         1: aload_1
         2: checkcast     #59                 // class scala/collection/Iterator
         5: invokevirtual #63                 // Method newBuilder:(Lscala/collection/Iterator;)Lscala/collection/mutable/Builder;
         8: areturn
      LineNumberTable:
        line 115: 0
      LocalVariableTable:
        Start  Length  Slot  Name   Signature
            0       9     0  this   Lscala/collection/BuildFromLowPriority2$$anon$12;
            0       9     1  from   Ljava/lang/Object;
    MethodParameters:
      Name                           Flags
      from                           final

  public scala.collection.BuildFromLowPriority2$$anon$12(scala.collection.BuildFromLowPriority2);
    descriptor: (Lscala/collection/BuildFromLowPriority2;)V
    flags: (0x0001) ACC_PUBLIC
    Code:
      stack=1, locals=2, args_size=2
         0: aload_0
         1: invokespecial #66                 // Method java/lang/Object."<init>":()V
         4: return
      LineNumberTable:
        line 115: 0
        line 115: 4
      LocalVariableTable:
        Start  Length  Slot  Name   Signature
            0       5     0  this   Lscala/collection/BuildFromLowPriority2$$anon$12;
            0       5     1 $outer   Lscala/collection/BuildFromLowPriority2;
    MethodParameters:
      Name                           Flags
      $outer                         final synthetic
}
InnerClasses:
  public final #2;                        // class scala/collection/BuildFromLowPriority2$$anon$12
  public final #15;                       // class scala/collection/Iterator$$anon$21
EnclosingMethod: #10.#13                // scala.collection.BuildFromLowPriority2.buildFromIterator
Signature: #3                           // Ljava/lang/Object;Lscala/collection/BuildFrom<Lscala/collection/Iterator<*>;TA;Lscala/collection/Iterator<TA;>;>;
SourceFile: "BuildFrom.scala"
  ScalaInlineInfo: length = 0x27 (unknown attribute)
   01 01 00 07 00 29 00 40 01 00 10 00 11 05 00 2E
   00 39 01 00 2E 00 2F 01 00 20 00 11 01 00 20 00
   21 01 00 1A 00 1B 01
  Scala: length = 0x0 (unknown attribute)

