Classfile /Users/mw/Projects/slang-braindump/.jar/jar11/assemble/slang-braindump/assemble/content/scala/collection/ClassTagSeqFactory$AnySeqDelegate.class
  Last modified May 29, 2022; size 1581 bytes
  SHA-256 checksum 50fedee93208a18085f0dd0a76c2b19b93c3f5591bd09cb793930742e3016e83
  Compiled from "Factory.scala"
public class scala.collection.ClassTagSeqFactory$AnySeqDelegate<CC extends scala.collection.SeqOps<java.lang.Object, scala.collection.Seq, scala.collection.Seq<java.lang.Object>>> extends scala.collection.ClassTagIterableFactory$AnyIterableDelegate<CC> implements scala.collection.SeqFactory<CC>
  minor version: 0
  major version: 52
  flags: (0x0021) ACC_PUBLIC, ACC_SUPER
  this_class: #2                          // scala/collection/ClassTagSeqFactory$AnySeqDelegate
  super_class: #5                         // scala/collection/ClassTagIterableFactory$AnyIterableDelegate
  interfaces: 1, fields: 1, methods: 2, attributes: 5
Constant pool:
   #1 = Utf8               scala/collection/ClassTagSeqFactory$AnySeqDelegate
   #2 = Class              #1             // scala/collection/ClassTagSeqFactory$AnySeqDelegate
   #3 = Utf8               <CC::Lscala/collection/SeqOps<Ljava/lang/Object;Lscala/collection/Seq;Lscala/collection/Seq<Ljava/lang/Object;>;>;>Lscala/collection/ClassTagIterableFactory$AnyIterableDelegate<TCC;>;Lscala/collection/SeqFactory<TCC;>;
   #4 = Utf8               scala/collection/ClassTagIterableFactory$AnyIterableDelegate
   #5 = Class              #4             // scala/collection/ClassTagIterableFactory$AnyIterableDelegate
   #6 = Utf8               scala/collection/SeqFactory
   #7 = Class              #6             // scala/collection/SeqFactory
   #8 = Utf8               Factory.scala
   #9 = Utf8               scala/collection/ClassTagIterableFactory
  #10 = Class              #9             // scala/collection/ClassTagIterableFactory
  #11 = Utf8               AnyIterableDelegate
  #12 = Utf8               scala/collection/ClassTagSeqFactory
  #13 = Class              #12            // scala/collection/ClassTagSeqFactory
  #14 = Utf8               AnySeqDelegate
  #15 = Utf8               serialVersionUID
  #16 = Utf8               J
  #17 = Long               3l
  #19 = Utf8               unapplySeq
  #20 = Utf8               (Lscala/collection/SeqOps;)Lscala/collection/SeqOps;
  #21 = Utf8               <A:Ljava/lang/Object;>(TCC;)Lscala/collection/SeqOps<TA;Lscala/collection/Seq;Lscala/collection/Seq<TA;>;>;
  #22 = Utf8               x
  #23 = Utf8               unapplySeq$
  #24 = Utf8               (Lscala/collection/SeqFactory;Lscala/collection/SeqOps;)Lscala/collection/SeqOps;
  #25 = NameAndType        #23:#24        // unapplySeq$:(Lscala/collection/SeqFactory;Lscala/collection/SeqOps;)Lscala/collection/SeqOps;
  #26 = InterfaceMethodref #7.#25         // scala/collection/SeqFactory.unapplySeq$:(Lscala/collection/SeqFactory;Lscala/collection/SeqOps;)Lscala/collection/SeqOps;
  #27 = Utf8               this
  #28 = Utf8               Lscala/collection/ClassTagSeqFactory$AnySeqDelegate;
  #29 = Utf8               Lscala/collection/SeqOps;
  #30 = Utf8               <init>
  #31 = Utf8               (Lscala/collection/ClassTagSeqFactory;)V
  #32 = Utf8               (Lscala/collection/ClassTagSeqFactory<TCC;>;)V
  #33 = Utf8               delegate
  #34 = Utf8               (Lscala/collection/ClassTagIterableFactory;)V
  #35 = NameAndType        #30:#34        // "<init>":(Lscala/collection/ClassTagIterableFactory;)V
  #36 = Methodref          #5.#35         // scala/collection/ClassTagIterableFactory$AnyIterableDelegate."<init>":(Lscala/collection/ClassTagIterableFactory;)V
  #37 = Utf8               Lscala/collection/ClassTagSeqFactory;
  #38 = Utf8               ConstantValue
  #39 = Utf8               Code
  #40 = Utf8               LineNumberTable
  #41 = Utf8               LocalVariableTable
  #42 = Utf8               Signature
  #43 = Utf8               MethodParameters
  #44 = Utf8               InnerClasses
  #45 = Utf8               SourceFile
  #46 = Utf8               ScalaInlineInfo
  #47 = Utf8               Scala
{
  private static final long serialVersionUID;
    descriptor: J
    flags: (0x001a) ACC_PRIVATE, ACC_STATIC, ACC_FINAL
    ConstantValue: long 3l

  public final <A extends java.lang.Object> scala.collection.SeqOps<A, scala.collection.Seq, scala.collection.Seq<A>> unapplySeq(CC);
    descriptor: (Lscala/collection/SeqOps;)Lscala/collection/SeqOps;
    flags: (0x0011) ACC_PUBLIC, ACC_FINAL
    Code:
      stack=2, locals=2, args_size=2
         0: aload_0
         1: aload_1
         2: invokestatic  #26                 // InterfaceMethod scala/collection/SeqFactory.unapplySeq$:(Lscala/collection/SeqFactory;Lscala/collection/SeqOps;)Lscala/collection/SeqOps;
         5: areturn
      LineNumberTable:
        line 699: 0
      LocalVariableTable:
        Start  Length  Slot  Name   Signature
            0       6     0  this   Lscala/collection/ClassTagSeqFactory$AnySeqDelegate;
            0       6     1     x   Lscala/collection/SeqOps;
    Signature: #21                          // <A:Ljava/lang/Object;>(TCC;)Lscala/collection/SeqOps<TA;Lscala/collection/Seq;Lscala/collection/Seq<TA;>;>;
    MethodParameters:
      Name                           Flags
      x                              final

  public scala.collection.ClassTagSeqFactory$AnySeqDelegate(scala.collection.ClassTagSeqFactory<CC>);
    descriptor: (Lscala/collection/ClassTagSeqFactory;)V
    flags: (0x0001) ACC_PUBLIC
    Code:
      stack=2, locals=2, args_size=2
         0: aload_0
         1: aload_1
         2: invokespecial #36                 // Method scala/collection/ClassTagIterableFactory$AnyIterableDelegate."<init>":(Lscala/collection/ClassTagIterableFactory;)V
         5: return
      LineNumberTable:
        line 700: 0
        line 699: 5
      LocalVariableTable:
        Start  Length  Slot  Name   Signature
            0       6     0  this   Lscala/collection/ClassTagSeqFactory$AnySeqDelegate;
            0       6     1 delegate   Lscala/collection/ClassTagSeqFactory;
    Signature: #32                          // (Lscala/collection/ClassTagSeqFactory<TCC;>;)V
    MethodParameters:
      Name                           Flags
      delegate                       final
}
InnerClasses:
  public static #11= #5 of #10;           // AnyIterableDelegate=class scala/collection/ClassTagIterableFactory$AnyIterableDelegate of class scala/collection/ClassTagIterableFactory
  public static #14= #2 of #13;           // AnySeqDelegate=class scala/collection/ClassTagSeqFactory$AnySeqDelegate of class scala/collection/ClassTagSeqFactory
Signature: #3                           // <CC::Lscala/collection/SeqOps<Ljava/lang/Object;Lscala/collection/Seq;Lscala/collection/Seq<Ljava/lang/Object;>;>;>Lscala/collection/ClassTagIterableFactory$AnyIterableDelegate<TCC;>;Lscala/collection/SeqFactory<TCC;>;
SourceFile: "Factory.scala"
  ScalaInlineInfo: length = 0xE (unknown attribute)
   01 00 00 02 00 1E 00 1F 00 00 13 00 14 01
  Scala: length = 0x0 (unknown attribute)

