Classfile /Users/mw/Projects/slang-braindump/.jar/jar11/assemble/slang-braindump/assemble/content/scala/collection/ClassTagSeqFactory.class
  Last modified May 29, 2022; size 2593 bytes
  SHA-256 checksum 08b0e30588d929a0426f9a6964fb8498befce69f71df056a5b29a85530ba58bb
  Compiled from "Factory.scala"
public interface scala.collection.ClassTagSeqFactory<CC extends scala.collection.SeqOps<java.lang.Object, scala.collection.Seq, scala.collection.Seq<java.lang.Object>>> extends scala.collection.ClassTagIterableFactory<CC>
  minor version: 0
  major version: 52
  flags: (0x0601) ACC_PUBLIC, ACC_INTERFACE, ACC_ABSTRACT
  this_class: #2                          // scala/collection/ClassTagSeqFactory
  super_class: #5                         // java/lang/Object
  interfaces: 1, fields: 0, methods: 3, attributes: 6
Constant pool:
   #1 = Utf8               scala/collection/ClassTagSeqFactory
   #2 = Class              #1             // scala/collection/ClassTagSeqFactory
   #3 = Utf8               <CC::Lscala/collection/SeqOps<Ljava/lang/Object;Lscala/collection/Seq;Lscala/collection/Seq<Ljava/lang/Object;>;>;>Ljava/lang/Object;Lscala/collection/ClassTagIterableFactory<TCC;>;
   #4 = Utf8               java/lang/Object
   #5 = Class              #4             // java/lang/Object
   #6 = Utf8               scala/collection/ClassTagIterableFactory
   #7 = Class              #6             // scala/collection/ClassTagIterableFactory
   #8 = Utf8               Factory.scala
   #9 = Utf8               Lscala/reflect/ScalaSignature;
  #10 = Utf8               bytes
  #11 = Utf8               \u0006\u0005\u0005UbaB\u0007\u000f!\u0003\r\ta\u0005\u0005\u0006i\u0001!\t!\u000e\u0005\u0006s\u0001!)AO\u0004\u0006%:A\ta\u0015\u0004\u0006\u001b9A\t\u0001\u0016\u0005\u0006;\u0012!\tA\u0018\u0004\u0005?\u0012\u0001\u0001\r\u0003\u0005r\r\t\u0005\t\u0015!\u0003q\u0011\u0015if\u0001\"\u0001s\r\u0011aH\u0001A?\t\u0013EL!\u0011!Q\u0001\n\u0005m\u0001BB/\n\t\u0003\ti\u0002C\u0005\u0002&\u0011\t\t\u0011\"\u0003\u0002(\t\u00112\t\\1tgR\u000bwmU3r\r\u0006\u001cGo\u001c:z\u0015\ty\u0001#\u0001\u0006d_2dWm\u0019;j_:T\u0011!E\u0001\u0006g\u000e\fG.Y\u0002\u0001+\t!rdE\u0002\u0001+e\u0001\"AF\f\u000e\u0003AI!\u0001\u0007\t\u0003\r\u0005s\u0017PU3g!\rQ2$H\u0007\u0002\u001d%\u0011AD\u0004\u0002\u0018\u00072\f7o\u001d+bO&#XM]1cY\u00164\u0015m\u0019;pef\u0004\"AH\u0010\r\u0001\u00111\u0001\u0005\u0001CC\u0002\u0005\u0012!aQ\"\u0016\u0005\tR\u0013CA\u0012\'!\t1B%\u0003\u0002&!\t9aj\u001c;iS:<\u0007#\u0002\u000e(SA\u001a\u0014B\u0001\u0015\u000f\u0005\u0019\u0019V-](qgB\u0011aD\u000b\u0003\u0006W}\u0011\r\u0001\f\u0002\u0002\u0003F\u00111%\f\t\u0003-9J!a\f\t\u0003\u0007\u0005s\u0017\u0010\u0005\u0002\u001bc%\u0011!G\u0004\u0002\u0004\'\u0016\f\bc\u0001\u000e2S\u00051A%\u001b8ji\u0012\"\u0012A\u000e\t\u0003-]J!\u0001\u000f\t\u0003\tUs\u0017\u000e^\u0001\u000bk:\f\u0007\u000f\u001d7z\'\u0016\fXCA\u001eE)\taT\tE\u0002>\u0001\u000es!A\u0007 \n\u0005}r\u0011AC*fc\u001a\u000b7\r^8ss&\u0011\u0011I\u0011\u0002\u0012+:\f\u0007\u000f\u001d7z\'\u0016\fxK]1qa\u0016\u0014(BA \u000f!\tqB\tB\u0003,\u0005\t\u0007A\u0006C\u0003G\u0005\u0001\u0007q)A\u0001yU\tA\u0015\nE\u0002\u001f?\r[\u0013A\u0013\t\u0003\u0017Bk\u0011\u0001\u0014\u0006\u0003\u001b:\u000b\u0011\"\u001e8dQ\u0016\u001c7.\u001a3\u000b\u0005=\u0003\u0012AC1o]>$\u0018\r^5p]&\u0011\u0011\u000b\u0014\u0002\u0012k:\u001c\u0007.Z2lK\u00124\u0016M]5b]\u000e,\u0017AE\"mCN\u001cH+Y4TKF4\u0015m\u0019;pef\u0004\"A\u0007\u0003\u0014\u0007\u0011)R\u000b\u0005\u0002W76\tqK\u0003\u0002Y3\u0006\u0011\u0011n\u001c\u0006\u00025\u0006!!.\u0019<b\u0013\tavK\u0001\u0007TKJL\u0017\r\\5{C\ndW-\u0001\u0004=S:LGO\u0010\u000b\u0002\'\nAA)\u001a7fO\u0006$X-\u0006\u0002bSN\u0019aA\u00199\u0011\u0007\r4\u0007N\u0004\u0002\u001bI&\u0011QMD\u0001\u0018\u00072\f7o\u001d+bO&#XM]1cY\u00164\u0015m\u0019;pefL!aX4\u000b\u0005\u0015t\u0001C\u0001\u0010j\t\u0015\u0001cA1\u0001k+\tYg.\u0005\u0002$YB)!dJ71_B\u0011aD\u001c\u0003\u0006W%\u0014\r\u0001\f\t\u00045Ej\u0007c\u0001\u000e\u0001Q\u0006AA-\u001a7fO\u0006$X\r\u0006\u0002tkB\u0019AO\u00025\u000e\u0003\u0011AQ!\u001d\u0005A\u0002ADCAB<{wB\u0011a\u0003_\u0005\u0003sB\u0011\u0001cU3sS\u0006dg+\u001a:tS>tW+\u0013#\u0002\u000bY\fG.^3\u001f\u0003\r\u0011a\"\u00118z\'\u0016\fH)\u001a7fO\u0006$X-F\u0002\u007f\u0003\u000f\u0019B!C@\u0002\u0016A)1-!\u0001\u0002\u0006%\u0019\u00111A4\u0003\'\u0005s\u00170\u0013;fe\u0006\u0014G.\u001a#fY\u0016<\u0017\r^3\u0011\u0007y\t9\u0001\u0002\u0004!\u0013\t\u0007\u0011\u0011B\u000b\u0005\u0003\u0017\t\t\"E\u0002$\u0003\u001b\u0001rAG\u0014\u0002\u0010A\n\u0019\u0002E\u0002\u001f\u0003#!aaKA\u0004\u0005\u0004a\u0003\u0003\u0002\u000e2\u0003\u001f\u0001RAGA\f\u0003\u000bI1!!\u0007\u000f\u0005)\u0019V-\u001d$bGR|\'/\u001f\t\u00055\u0001\t)\u0001\u0006\u0003\u0002 \u0005\u0005\u0002\u0003\u0002;\n\u0003\u000bAa!]\u0006A\u0002\u0005m\u0001\u0006B\u0005xun\fAb\u001e:ji\u0016\u0014V\r\u001d7bG\u0016$\"!!\u000b\u0011\t\u0005-\u0012\u0011G\u0007\u0003\u0003[Q1!a\fZ\u0003\u0011a\u0017M\\4\n\t\u0005M\u0012Q\u0006\u0002\u0007\u001f\nTWm\u0019;
  #12 = Utf8               scala/collection/ClassTagSeqFactory$AnySeqDelegate
  #13 = Class              #12            // scala/collection/ClassTagSeqFactory$AnySeqDelegate
  #14 = Utf8               AnySeqDelegate
  #15 = Utf8               scala/collection/ClassTagSeqFactory$Delegate
  #16 = Class              #15            // scala/collection/ClassTagSeqFactory$Delegate
  #17 = Utf8               Delegate
  #18 = Utf8               unapplySeq$
  #19 = Utf8               (Lscala/collection/ClassTagSeqFactory;Lscala/collection/SeqOps;)Lscala/collection/SeqOps;
  #20 = Utf8               $this
  #21 = Utf8               x
  #22 = Utf8               unapplySeq
  #23 = Utf8               (Lscala/collection/SeqOps;)Lscala/collection/SeqOps;
  #24 = NameAndType        #22:#23        // unapplySeq:(Lscala/collection/SeqOps;)Lscala/collection/SeqOps;
  #25 = InterfaceMethodref #2.#24         // scala/collection/ClassTagSeqFactory.unapplySeq:(Lscala/collection/SeqOps;)Lscala/collection/SeqOps;
  #26 = Utf8               Lscala/collection/ClassTagSeqFactory;
  #27 = Utf8               Lscala/collection/SeqOps;
  #28 = Utf8               <A:Ljava/lang/Object;>(TCC;)Lscala/collection/SeqOps<TA;Lscala/collection/Seq;Lscala/collection/Seq<TA;>;>;
  #29 = Utf8               this
  #30 = Utf8               $init$
  #31 = Utf8               (Lscala/collection/ClassTagSeqFactory;)V
  #32 = Utf8               Code
  #33 = Utf8               LineNumberTable
  #34 = Utf8               LocalVariableTable
  #35 = Utf8               MethodParameters
  #36 = Utf8               Signature
  #37 = Utf8               InnerClasses
  #38 = Utf8               SourceFile
  #39 = Utf8               RuntimeVisibleAnnotations
  #40 = Utf8               ScalaInlineInfo
  #41 = Utf8               ScalaSig
{
  public static scala.collection.SeqOps unapplySeq$(scala.collection.ClassTagSeqFactory, scala.collection.SeqOps);
    descriptor: (Lscala/collection/ClassTagSeqFactory;Lscala/collection/SeqOps;)Lscala/collection/SeqOps;
    flags: (0x1009) ACC_PUBLIC, ACC_STATIC, ACC_SYNTHETIC
    Code:
      stack=2, locals=2, args_size=2
         0: aload_0
         1: aload_1
         2: invokespecial #25                 // InterfaceMethod unapplySeq:(Lscala/collection/SeqOps;)Lscala/collection/SeqOps;
         5: areturn
      LineNumberTable:
        line 688: 0
      LocalVariableTable:
        Start  Length  Slot  Name   Signature
            0       6     0 $this   Lscala/collection/ClassTagSeqFactory;
            0       6     1     x   Lscala/collection/SeqOps;
    MethodParameters:
      Name                           Flags
      $this                          final synthetic
      x                              final

  public default <A extends java.lang.Object> scala.collection.SeqOps<A, scala.collection.Seq, scala.collection.Seq<A>> unapplySeq(CC);
    descriptor: (Lscala/collection/SeqOps;)Lscala/collection/SeqOps;
    flags: (0x0001) ACC_PUBLIC
    Code:
      stack=1, locals=2, args_size=2
         0: aload_1
         1: areturn
      LineNumberTable:
        line 688: 0
      LocalVariableTable:
        Start  Length  Slot  Name   Signature
            0       2     0  this   Lscala/collection/ClassTagSeqFactory;
            0       2     1     x   Lscala/collection/SeqOps;
    Signature: #28                          // <A:Ljava/lang/Object;>(TCC;)Lscala/collection/SeqOps<TA;Lscala/collection/Seq;Lscala/collection/Seq<TA;>;>;
    MethodParameters:
      Name                           Flags
      x                              final

  public static void $init$(scala.collection.ClassTagSeqFactory);
    descriptor: (Lscala/collection/ClassTagSeqFactory;)V
    flags: (0x0009) ACC_PUBLIC, ACC_STATIC
    Code:
      stack=0, locals=1, args_size=1
         0: return
      LineNumberTable:
        line 686: 0
      LocalVariableTable:
        Start  Length  Slot  Name   Signature
            0       1     0 $this   Lscala/collection/ClassTagSeqFactory;
    MethodParameters:
      Name                           Flags
      $this                          final synthetic
}
InnerClasses:
  public static #14= #13 of #2;           // AnySeqDelegate=class scala/collection/ClassTagSeqFactory$AnySeqDelegate of class scala/collection/ClassTagSeqFactory
  public static #17= #16 of #2;           // Delegate=class scala/collection/ClassTagSeqFactory$Delegate of class scala/collection/ClassTagSeqFactory
Signature: #3                           // <CC::Lscala/collection/SeqOps<Ljava/lang/Object;Lscala/collection/Seq;Lscala/collection/Seq<Ljava/lang/Object;>;>;>Ljava/lang/Object;Lscala/collection/ClassTagIterableFactory<TCC;>;
SourceFile: "Factory.scala"
RuntimeVisibleAnnotations:
  0: #9(#10=s#11)
    scala.reflect.ScalaSignature(
      bytes="\u0006\u0005\u0005UbaB\u0007\u000f!\u0003\r\ta\u0005\u0005\u0006i\u0001!\t!\u000e\u0005\u0006s\u0001!)AO\u0004\u0006%:A\ta\u0015\u0004\u0006\u001b9A\t\u0001\u0016\u0005\u0006;\u0012!\tA\u0018\u0004\u0005?\u0012\u0001\u0001\r\u0003\u0005r\r\t\u0005\t\u0015!\u0003q\u0011\u0015if\u0001\"\u0001s\r\u0011aH\u0001A?\t\u0013EL!\u0011!Q\u0001\n\u0005m\u0001BB/\n\t\u0003\ti\u0002C\u0005\u0002&\u0011\t\t\u0011\"\u0003\u0002(\t\u00112\t\\1tgR\u000bwmU3r\r\u0006\u001cGo\u001c:z\u0015\ty\u0001#\u0001\u0006d_2dWm\u0019;j_:T\u0011!E\u0001\u0006g\u000e\fG.Y\u0002\u0001+\t!rdE\u0002\u0001+e\u0001\"AF\f\u000e\u0003AI!\u0001\u0007\t\u0003\r\u0005s\u0017PU3g!\rQ2$H\u0007\u0002\u001d%\u0011AD\u0004\u0002\u0018\u00072\f7o\u001d+bO&#XM]1cY\u00164\u0015m\u0019;pef\u0004\"AH\u0010\r\u0001\u00111\u0001\u0005\u0001CC\u0002\u0005\u0012!aQ\"\u0016\u0005\tR\u0013CA\u0012\'!\t1B%\u0003\u0002&!\t9aj\u001c;iS:<\u0007#\u0002\u000e(SA\u001a\u0014B\u0001\u0015\u000f\u0005\u0019\u0019V-](qgB\u0011aD\u000b\u0003\u0006W}\u0011\r\u0001\f\u0002\u0002\u0003F\u00111%\f\t\u0003-9J!a\f\t\u0003\u0007\u0005s\u0017\u0010\u0005\u0002\u001bc%\u0011!G\u0004\u0002\u0004\'\u0016\f\bc\u0001\u000e2S\u00051A%\u001b8ji\u0012\"\u0012A\u000e\t\u0003-]J!\u0001\u000f\t\u0003\tUs\u0017\u000e^\u0001\u000bk:\f\u0007\u000f\u001d7z\'\u0016\fXCA\u001eE)\taT\tE\u0002>\u0001\u000es!A\u0007 \n\u0005}r\u0011AC*fc\u001a\u000b7\r^8ss&\u0011\u0011I\u0011\u0002\u0012+:\f\u0007\u000f\u001d7z\'\u0016\fxK]1qa\u0016\u0014(BA \u000f!\tqB\tB\u0003,\u0005\t\u0007A\u0006C\u0003G\u0005\u0001\u0007q)A\u0001yU\tA\u0015\nE\u0002\u001f?\r[\u0013A\u0013\t\u0003\u0017Bk\u0011\u0001\u0014\u0006\u0003\u001b:\u000b\u0011\"\u001e8dQ\u0016\u001c7.\u001a3\u000b\u0005=\u0003\u0012AC1o]>$\u0018\r^5p]&\u0011\u0011\u000b\u0014\u0002\u0012k:\u001c\u0007.Z2lK\u00124\u0016M]5b]\u000e,\u0017AE\"mCN\u001cH+Y4TKF4\u0015m\u0019;pef\u0004\"A\u0007\u0003\u0014\u0007\u0011)R\u000b\u0005\u0002W76\tqK\u0003\u0002Y3\u0006\u0011\u0011n\u001c\u0006\u00025\u0006!!.\u0019<b\u0013\tavK\u0001\u0007TKJL\u0017\r\\5{C\ndW-\u0001\u0004=S:LGO\u0010\u000b\u0002\'\nAA)\u001a7fO\u0006$X-\u0006\u0002bSN\u0019aA\u00199\u0011\u0007\r4\u0007N\u0004\u0002\u001bI&\u0011QMD\u0001\u0018\u00072\f7o\u001d+bO&#XM]1cY\u00164\u0015m\u0019;pefL!aX4\u000b\u0005\u0015t\u0001C\u0001\u0010j\t\u0015\u0001cA1\u0001k+\tYg.\u0005\u0002$YB)!dJ71_B\u0011aD\u001c\u0003\u0006W%\u0014\r\u0001\f\t\u00045Ej\u0007c\u0001\u000e\u0001Q\u0006AA-\u001a7fO\u0006$X\r\u0006\u0002tkB\u0019AO\u00025\u000e\u0003\u0011AQ!\u001d\u0005A\u0002ADCAB<{wB\u0011a\u0003_\u0005\u0003sB\u0011\u0001cU3sS\u0006dg+\u001a:tS>tW+\u0013#\u0002\u000bY\fG.^3\u001f\u0003\r\u0011a\"\u00118z\'\u0016\fH)\u001a7fO\u0006$X-F\u0002\u007f\u0003\u000f\u0019B!C@\u0002\u0016A)1-!\u0001\u0002\u0006%\u0019\u00111A4\u0003\'\u0005s\u00170\u0013;fe\u0006\u0014G.\u001a#fY\u0016<\u0017\r^3\u0011\u0007y\t9\u0001\u0002\u0004!\u0013\t\u0007\u0011\u0011B\u000b\u0005\u0003\u0017\t\t\"E\u0002$\u0003\u001b\u0001rAG\u0014\u0002\u0010A\n\u0019\u0002E\u0002\u001f\u0003#!aaKA\u0004\u0005\u0004a\u0003\u0003\u0002\u000e2\u0003\u001f\u0001RAGA\f\u0003\u000bI1!!\u0007\u000f\u0005)\u0019V-\u001d$bGR|\'/\u001f\t\u00055\u0001\t)\u0001\u0006\u0003\u0002 \u0005\u0005\u0002\u0003\u0002;\n\u0003\u000bAa!]\u0006A\u0002\u0005m\u0001\u0006B\u0005xun\fAb\u001e:ji\u0016\u0014V\r\u001d7bG\u0016$\"!!\u000b\u0011\t\u0005-\u0012\u0011G\u0007\u0003\u0003[Q1!a\fZ\u0003\u0011a\u0017M\\4\n\t\u0005M\u0012Q\u0006\u0002\u0007\u001f\nTWm\u0019;"
    )
  ScalaInlineInfo: length = 0x13 (unknown attribute)
   01 00 00 03 00 1E 00 1F 01 00 16 00 17 01 00 12
   00 13 01
  ScalaSig: length = 0x3 (unknown attribute)
   05 02 00
