Classfile /Users/mw/Projects/slang-braindump/.jar/jar11/assemble/slang-braindump/assemble/content/scala/collection/ClassTagIterableFactory$Delegate.class
  Last modified May 29, 2022; size 6282 bytes
  SHA-256 checksum 7231cab03618d432077ef516ffc8eb299a99b78f116a60d455b28d4b2da6d6eb
  Compiled from "Factory.scala"
public class scala.collection.ClassTagIterableFactory$Delegate<CC extends java.lang.Object> extends scala.collection.EvidenceIterableFactory$Delegate<CC, scala.reflect.ClassTag> implements scala.collection.ClassTagIterableFactory<CC>
  minor version: 0
  major version: 52
  flags: (0x0021) ACC_PUBLIC, ACC_SUPER
  this_class: #2                          // scala/collection/ClassTagIterableFactory$Delegate
  super_class: #5                         // scala/collection/EvidenceIterableFactory$Delegate
  interfaces: 1, fields: 1, methods: 11, attributes: 5
Constant pool:
    #1 = Utf8               scala/collection/ClassTagIterableFactory$Delegate
    #2 = Class              #1            // scala/collection/ClassTagIterableFactory$Delegate
    #3 = Utf8               <CC:Ljava/lang/Object;>Lscala/collection/EvidenceIterableFactory$Delegate<TCC;Lscala/reflect/ClassTag;>;Lscala/collection/ClassTagIterableFactory<TCC;>;
    #4 = Utf8               scala/collection/EvidenceIterableFactory$Delegate
    #5 = Class              #4            // scala/collection/EvidenceIterableFactory$Delegate
    #6 = Utf8               scala/collection/ClassTagIterableFactory
    #7 = Class              #6            // scala/collection/ClassTagIterableFactory
    #8 = Utf8               Factory.scala
    #9 = Utf8               Delegate
   #10 = Utf8               scala/collection/EvidenceIterableFactory
   #11 = Class              #10           // scala/collection/EvidenceIterableFactory
   #12 = Utf8               serialVersionUID
   #13 = Utf8               J
   #14 = Long               3l
   #16 = Utf8               range
   #17 = Utf8               (Ljava/lang/Object;Ljava/lang/Object;Lscala/math/Integral;Lscala/reflect/ClassTag;)Ljava/lang/Object;
   #18 = Utf8               <A:Ljava/lang/Object;>(TA;TA;Lscala/math/Integral<TA;>;Lscala/reflect/ClassTag<TA;>;)TCC;
   #19 = Utf8               start
   #20 = Utf8               end
   #21 = Utf8               evidence$22
   #22 = Utf8               evidence$23
   #23 = Utf8               range$
   #24 = Utf8               (Lscala/collection/ClassTagIterableFactory;Ljava/lang/Object;Ljava/lang/Object;Lscala/math/Integral;Lscala/reflect/ClassTag;)Ljava/lang/Object;
   #25 = NameAndType        #23:#24       // range$:(Lscala/collection/ClassTagIterableFactory;Ljava/lang/Object;Ljava/lang/Object;Lscala/math/Integral;Lscala/reflect/ClassTag;)Ljava/lang/Object;
   #26 = InterfaceMethodref #7.#25        // scala/collection/ClassTagIterableFactory.range$:(Lscala/collection/ClassTagIterableFactory;Ljava/lang/Object;Ljava/lang/Object;Lscala/math/Integral;Lscala/reflect/ClassTag;)Ljava/lang/Object;
   #27 = Utf8               this
   #28 = Utf8               Lscala/collection/ClassTagIterableFactory$Delegate;
   #29 = Utf8               Ljava/lang/Object;
   #30 = Utf8               Lscala/math/Integral;
   #31 = Utf8               Lscala/reflect/ClassTag;
   #32 = Utf8               (Ljava/lang/Object;Ljava/lang/Object;Ljava/lang/Object;Lscala/math/Integral;Lscala/reflect/ClassTag;)Ljava/lang/Object;
   #33 = Utf8               <A:Ljava/lang/Object;>(TA;TA;TA;Lscala/math/Integral<TA;>;Lscala/reflect/ClassTag<TA;>;)TCC;
   #34 = Utf8               step
   #35 = Utf8               evidence$24
   #36 = Utf8               evidence$25
   #37 = Utf8               (Lscala/collection/ClassTagIterableFactory;Ljava/lang/Object;Ljava/lang/Object;Ljava/lang/Object;Lscala/math/Integral;Lscala/reflect/ClassTag;)Ljava/lang/Object;
   #38 = NameAndType        #23:#37       // range$:(Lscala/collection/ClassTagIterableFactory;Ljava/lang/Object;Ljava/lang/Object;Ljava/lang/Object;Lscala/math/Integral;Lscala/reflect/ClassTag;)Ljava/lang/Object;
   #39 = InterfaceMethodref #7.#38        // scala/collection/ClassTagIterableFactory.range$:(Lscala/collection/ClassTagIterableFactory;Ljava/lang/Object;Ljava/lang/Object;Ljava/lang/Object;Lscala/math/Integral;Lscala/reflect/ClassTag;)Ljava/lang/Object;
   #40 = Utf8               fill
   #41 = Utf8               (IILscala/Function0;Lscala/reflect/ClassTag;)Ljava/lang/Object;
   #42 = Utf8               <A:Ljava/lang/Object;>(IILscala/Function0<TA;>;Lscala/reflect/ClassTag<TA;>;)TCC;
   #43 = Utf8               n1
   #44 = Utf8               n2
   #45 = Utf8               elem
   #46 = Utf8               evidence$26
   #47 = Utf8               fill$
   #48 = Utf8               (Lscala/collection/ClassTagIterableFactory;IILscala/Function0;Lscala/reflect/ClassTag;)Ljava/lang/Object;
   #49 = NameAndType        #47:#48       // fill$:(Lscala/collection/ClassTagIterableFactory;IILscala/Function0;Lscala/reflect/ClassTag;)Ljava/lang/Object;
   #50 = InterfaceMethodref #7.#49        // scala/collection/ClassTagIterableFactory.fill$:(Lscala/collection/ClassTagIterableFactory;IILscala/Function0;Lscala/reflect/ClassTag;)Ljava/lang/Object;
   #51 = Utf8               I
   #52 = Utf8               Lscala/Function0;
   #53 = Utf8               (IIILscala/Function0;Lscala/reflect/ClassTag;)Ljava/lang/Object;
   #54 = Utf8               <A:Ljava/lang/Object;>(IIILscala/Function0<TA;>;Lscala/reflect/ClassTag<TA;>;)TCC;
   #55 = Utf8               n3
   #56 = Utf8               evidence$27
   #57 = Utf8               (Lscala/collection/ClassTagIterableFactory;IIILscala/Function0;Lscala/reflect/ClassTag;)Ljava/lang/Object;
   #58 = NameAndType        #47:#57       // fill$:(Lscala/collection/ClassTagIterableFactory;IIILscala/Function0;Lscala/reflect/ClassTag;)Ljava/lang/Object;
   #59 = InterfaceMethodref #7.#58        // scala/collection/ClassTagIterableFactory.fill$:(Lscala/collection/ClassTagIterableFactory;IIILscala/Function0;Lscala/reflect/ClassTag;)Ljava/lang/Object;
   #60 = Utf8               (IIIILscala/Function0;Lscala/reflect/ClassTag;)Ljava/lang/Object;
   #61 = Utf8               <A:Ljava/lang/Object;>(IIIILscala/Function0<TA;>;Lscala/reflect/ClassTag<TA;>;)TCC;
   #62 = Utf8               n4
   #63 = Utf8               evidence$28
   #64 = Utf8               (Lscala/collection/ClassTagIterableFactory;IIIILscala/Function0;Lscala/reflect/ClassTag;)Ljava/lang/Object;
   #65 = NameAndType        #47:#64       // fill$:(Lscala/collection/ClassTagIterableFactory;IIIILscala/Function0;Lscala/reflect/ClassTag;)Ljava/lang/Object;
   #66 = InterfaceMethodref #7.#65        // scala/collection/ClassTagIterableFactory.fill$:(Lscala/collection/ClassTagIterableFactory;IIIILscala/Function0;Lscala/reflect/ClassTag;)Ljava/lang/Object;
   #67 = Utf8               (IIIIILscala/Function0;Lscala/reflect/ClassTag;)Ljava/lang/Object;
   #68 = Utf8               <A:Ljava/lang/Object;>(IIIIILscala/Function0<TA;>;Lscala/reflect/ClassTag<TA;>;)TCC;
   #69 = Utf8               n5
   #70 = Utf8               evidence$29
   #71 = Utf8               (Lscala/collection/ClassTagIterableFactory;IIIIILscala/Function0;Lscala/reflect/ClassTag;)Ljava/lang/Object;
   #72 = NameAndType        #47:#71       // fill$:(Lscala/collection/ClassTagIterableFactory;IIIIILscala/Function0;Lscala/reflect/ClassTag;)Ljava/lang/Object;
   #73 = InterfaceMethodref #7.#72        // scala/collection/ClassTagIterableFactory.fill$:(Lscala/collection/ClassTagIterableFactory;IIIIILscala/Function0;Lscala/reflect/ClassTag;)Ljava/lang/Object;
   #74 = Utf8               tabulate
   #75 = Utf8               (IILscala/Function2;Lscala/reflect/ClassTag;)Ljava/lang/Object;
   #76 = Utf8               <A:Ljava/lang/Object;>(IILscala/Function2<Ljava/lang/Object;Ljava/lang/Object;TA;>;Lscala/reflect/ClassTag<TA;>;)TCC;
   #77 = Utf8               f
   #78 = Utf8               evidence$30
   #79 = Utf8               tabulate$
   #80 = Utf8               (Lscala/collection/ClassTagIterableFactory;IILscala/Function2;Lscala/reflect/ClassTag;)Ljava/lang/Object;
   #81 = NameAndType        #79:#80       // tabulate$:(Lscala/collection/ClassTagIterableFactory;IILscala/Function2;Lscala/reflect/ClassTag;)Ljava/lang/Object;
   #82 = InterfaceMethodref #7.#81        // scala/collection/ClassTagIterableFactory.tabulate$:(Lscala/collection/ClassTagIterableFactory;IILscala/Function2;Lscala/reflect/ClassTag;)Ljava/lang/Object;
   #83 = Utf8               Lscala/Function2;
   #84 = Utf8               (IIILscala/Function3;Lscala/reflect/ClassTag;)Ljava/lang/Object;
   #85 = Utf8               <A:Ljava/lang/Object;>(IIILscala/Function3<Ljava/lang/Object;Ljava/lang/Object;Ljava/lang/Object;TA;>;Lscala/reflect/ClassTag<TA;>;)TCC;
   #86 = Utf8               evidence$31
   #87 = Utf8               (Lscala/collection/ClassTagIterableFactory;IIILscala/Function3;Lscala/reflect/ClassTag;)Ljava/lang/Object;
   #88 = NameAndType        #79:#87       // tabulate$:(Lscala/collection/ClassTagIterableFactory;IIILscala/Function3;Lscala/reflect/ClassTag;)Ljava/lang/Object;
   #89 = InterfaceMethodref #7.#88        // scala/collection/ClassTagIterableFactory.tabulate$:(Lscala/collection/ClassTagIterableFactory;IIILscala/Function3;Lscala/reflect/ClassTag;)Ljava/lang/Object;
   #90 = Utf8               Lscala/Function3;
   #91 = Utf8               (IIIILscala/Function4;Lscala/reflect/ClassTag;)Ljava/lang/Object;
   #92 = Utf8               <A:Ljava/lang/Object;>(IIIILscala/Function4<Ljava/lang/Object;Ljava/lang/Object;Ljava/lang/Object;Ljava/lang/Object;TA;>;Lscala/reflect/ClassTag<TA;>;)TCC;
   #93 = Utf8               evidence$32
   #94 = Utf8               (Lscala/collection/ClassTagIterableFactory;IIIILscala/Function4;Lscala/reflect/ClassTag;)Ljava/lang/Object;
   #95 = NameAndType        #79:#94       // tabulate$:(Lscala/collection/ClassTagIterableFactory;IIIILscala/Function4;Lscala/reflect/ClassTag;)Ljava/lang/Object;
   #96 = InterfaceMethodref #7.#95        // scala/collection/ClassTagIterableFactory.tabulate$:(Lscala/collection/ClassTagIterableFactory;IIIILscala/Function4;Lscala/reflect/ClassTag;)Ljava/lang/Object;
   #97 = Utf8               Lscala/Function4;
   #98 = Utf8               (IIIIILscala/Function5;Lscala/reflect/ClassTag;)Ljava/lang/Object;
   #99 = Utf8               <A:Ljava/lang/Object;>(IIIIILscala/Function5<Ljava/lang/Object;Ljava/lang/Object;Ljava/lang/Object;Ljava/lang/Object;Ljava/lang/Object;TA;>;Lscala/reflect/ClassTag<TA;>;)TCC;
  #100 = Utf8               evidence$33
  #101 = Utf8               (Lscala/collection/ClassTagIterableFactory;IIIIILscala/Function5;Lscala/reflect/ClassTag;)Ljava/lang/Object;
  #102 = NameAndType        #79:#101      // tabulate$:(Lscala/collection/ClassTagIterableFactory;IIIIILscala/Function5;Lscala/reflect/ClassTag;)Ljava/lang/Object;
  #103 = InterfaceMethodref #7.#102       // scala/collection/ClassTagIterableFactory.tabulate$:(Lscala/collection/ClassTagIterableFactory;IIIIILscala/Function5;Lscala/reflect/ClassTag;)Ljava/lang/Object;
  #104 = Utf8               Lscala/Function5;
  #105 = Utf8               <init>
  #106 = Utf8               (Lscala/collection/EvidenceIterableFactory;)V
  #107 = Utf8               (Lscala/collection/EvidenceIterableFactory<TCC;Lscala/reflect/ClassTag;>;)V
  #108 = Utf8               delegate
  #109 = NameAndType        #105:#106     // "<init>":(Lscala/collection/EvidenceIterableFactory;)V
  #110 = Methodref          #5.#109       // scala/collection/EvidenceIterableFactory$Delegate."<init>":(Lscala/collection/EvidenceIterableFactory;)V
  #111 = Utf8               Lscala/collection/EvidenceIterableFactory;
  #112 = Utf8               ConstantValue
  #113 = Utf8               Code
  #114 = Utf8               LineNumberTable
  #115 = Utf8               LocalVariableTable
  #116 = Utf8               Signature
  #117 = Utf8               MethodParameters
  #118 = Utf8               InnerClasses
  #119 = Utf8               SourceFile
  #120 = Utf8               ScalaInlineInfo
  #121 = Utf8               Scala
{
  private static final long serialVersionUID;
    descriptor: J
    flags: (0x001a) ACC_PRIVATE, ACC_STATIC, ACC_FINAL
    ConstantValue: long 3l

  public <A extends java.lang.Object> CC range(A, A, scala.math.Integral<A>, scala.reflect.ClassTag<A>);
    descriptor: (Ljava/lang/Object;Ljava/lang/Object;Lscala/math/Integral;Lscala/reflect/ClassTag;)Ljava/lang/Object;
    flags: (0x0001) ACC_PUBLIC
    Code:
      stack=5, locals=5, args_size=5
         0: aload_0
         1: aload_1
         2: aload_2
         3: aload_3
         4: aload         4
         6: invokestatic  #26                 // InterfaceMethod scala/collection/ClassTagIterableFactory.range$:(Lscala/collection/ClassTagIterableFactory;Ljava/lang/Object;Ljava/lang/Object;Lscala/math/Integral;Lscala/reflect/ClassTag;)Ljava/lang/Object;
         9: areturn
      LineNumberTable:
        line 663: 0
      LocalVariableTable:
        Start  Length  Slot  Name   Signature
            0      10     0  this   Lscala/collection/ClassTagIterableFactory$Delegate;
            0      10     1 start   Ljava/lang/Object;
            0      10     2   end   Ljava/lang/Object;
            0      10     3 evidence$22   Lscala/math/Integral;
            0      10     4 evidence$23   Lscala/reflect/ClassTag;
    Signature: #18                          // <A:Ljava/lang/Object;>(TA;TA;Lscala/math/Integral<TA;>;Lscala/reflect/ClassTag<TA;>;)TCC;
    MethodParameters:
      Name                           Flags
      start                          final
      end                            final
      evidence$22                    final
      evidence$23                    final

  public <A extends java.lang.Object> CC range(A, A, A, scala.math.Integral<A>, scala.reflect.ClassTag<A>);
    descriptor: (Ljava/lang/Object;Ljava/lang/Object;Ljava/lang/Object;Lscala/math/Integral;Lscala/reflect/ClassTag;)Ljava/lang/Object;
    flags: (0x0001) ACC_PUBLIC
    Code:
      stack=6, locals=6, args_size=6
         0: aload_0
         1: aload_1
         2: aload_2
         3: aload_3
         4: aload         4
         6: aload         5
         8: invokestatic  #39                 // InterfaceMethod scala/collection/ClassTagIterableFactory.range$:(Lscala/collection/ClassTagIterableFactory;Ljava/lang/Object;Ljava/lang/Object;Ljava/lang/Object;Lscala/math/Integral;Lscala/reflect/ClassTag;)Ljava/lang/Object;
        11: areturn
      LineNumberTable:
        line 663: 0
      LocalVariableTable:
        Start  Length  Slot  Name   Signature
            0      12     0  this   Lscala/collection/ClassTagIterableFactory$Delegate;
            0      12     1 start   Ljava/lang/Object;
            0      12     2   end   Ljava/lang/Object;
            0      12     3  step   Ljava/lang/Object;
            0      12     4 evidence$24   Lscala/math/Integral;
            0      12     5 evidence$25   Lscala/reflect/ClassTag;
    Signature: #33                          // <A:Ljava/lang/Object;>(TA;TA;TA;Lscala/math/Integral<TA;>;Lscala/reflect/ClassTag<TA;>;)TCC;
    MethodParameters:
      Name                           Flags
      start                          final
      end                            final
      step                           final
      evidence$24                    final
      evidence$25                    final

  public <A extends java.lang.Object> CC fill(int, int, scala.Function0<A>, scala.reflect.ClassTag<A>);
    descriptor: (IILscala/Function0;Lscala/reflect/ClassTag;)Ljava/lang/Object;
    flags: (0x0001) ACC_PUBLIC
    Code:
      stack=5, locals=5, args_size=5
         0: aload_0
         1: iload_1
         2: iload_2
         3: aload_3
         4: aload         4
         6: invokestatic  #50                 // InterfaceMethod scala/collection/ClassTagIterableFactory.fill$:(Lscala/collection/ClassTagIterableFactory;IILscala/Function0;Lscala/reflect/ClassTag;)Ljava/lang/Object;
         9: areturn
      LineNumberTable:
        line 663: 0
      LocalVariableTable:
        Start  Length  Slot  Name   Signature
            0      10     0  this   Lscala/collection/ClassTagIterableFactory$Delegate;
            0      10     1    n1   I
            0      10     2    n2   I
            0      10     3  elem   Lscala/Function0;
            0      10     4 evidence$26   Lscala/reflect/ClassTag;
    Signature: #42                          // <A:Ljava/lang/Object;>(IILscala/Function0<TA;>;Lscala/reflect/ClassTag<TA;>;)TCC;
    MethodParameters:
      Name                           Flags
      n1                             final
      n2                             final
      elem                           final
      evidence$26                    final

  public <A extends java.lang.Object> CC fill(int, int, int, scala.Function0<A>, scala.reflect.ClassTag<A>);
    descriptor: (IIILscala/Function0;Lscala/reflect/ClassTag;)Ljava/lang/Object;
    flags: (0x0001) ACC_PUBLIC
    Code:
      stack=6, locals=6, args_size=6
         0: aload_0
         1: iload_1
         2: iload_2
         3: iload_3
         4: aload         4
         6: aload         5
         8: invokestatic  #59                 // InterfaceMethod scala/collection/ClassTagIterableFactory.fill$:(Lscala/collection/ClassTagIterableFactory;IIILscala/Function0;Lscala/reflect/ClassTag;)Ljava/lang/Object;
        11: areturn
      LineNumberTable:
        line 663: 0
      LocalVariableTable:
        Start  Length  Slot  Name   Signature
            0      12     0  this   Lscala/collection/ClassTagIterableFactory$Delegate;
            0      12     1    n1   I
            0      12     2    n2   I
            0      12     3    n3   I
            0      12     4  elem   Lscala/Function0;
            0      12     5 evidence$27   Lscala/reflect/ClassTag;
    Signature: #54                          // <A:Ljava/lang/Object;>(IIILscala/Function0<TA;>;Lscala/reflect/ClassTag<TA;>;)TCC;
    MethodParameters:
      Name                           Flags
      n1                             final
      n2                             final
      n3                             final
      elem                           final
      evidence$27                    final

  public <A extends java.lang.Object> CC fill(int, int, int, int, scala.Function0<A>, scala.reflect.ClassTag<A>);
    descriptor: (IIIILscala/Function0;Lscala/reflect/ClassTag;)Ljava/lang/Object;
    flags: (0x0001) ACC_PUBLIC
    Code:
      stack=7, locals=7, args_size=7
         0: aload_0
         1: iload_1
         2: iload_2
         3: iload_3
         4: iload         4
         6: aload         5
         8: aload         6
        10: invokestatic  #66                 // InterfaceMethod scala/collection/ClassTagIterableFactory.fill$:(Lscala/collection/ClassTagIterableFactory;IIIILscala/Function0;Lscala/reflect/ClassTag;)Ljava/lang/Object;
        13: areturn
      LineNumberTable:
        line 663: 0
      LocalVariableTable:
        Start  Length  Slot  Name   Signature
            0      14     0  this   Lscala/collection/ClassTagIterableFactory$Delegate;
            0      14     1    n1   I
            0      14     2    n2   I
            0      14     3    n3   I
            0      14     4    n4   I
            0      14     5  elem   Lscala/Function0;
            0      14     6 evidence$28   Lscala/reflect/ClassTag;
    Signature: #61                          // <A:Ljava/lang/Object;>(IIIILscala/Function0<TA;>;Lscala/reflect/ClassTag<TA;>;)TCC;
    MethodParameters:
      Name                           Flags
      n1                             final
      n2                             final
      n3                             final
      n4                             final
      elem                           final
      evidence$28                    final

  public <A extends java.lang.Object> CC fill(int, int, int, int, int, scala.Function0<A>, scala.reflect.ClassTag<A>);
    descriptor: (IIIIILscala/Function0;Lscala/reflect/ClassTag;)Ljava/lang/Object;
    flags: (0x0001) ACC_PUBLIC
    Code:
      stack=8, locals=8, args_size=8
         0: aload_0
         1: iload_1
         2: iload_2
         3: iload_3
         4: iload         4
         6: iload         5
         8: aload         6
        10: aload         7
        12: invokestatic  #73                 // InterfaceMethod scala/collection/ClassTagIterableFactory.fill$:(Lscala/collection/ClassTagIterableFactory;IIIIILscala/Function0;Lscala/reflect/ClassTag;)Ljava/lang/Object;
        15: areturn
      LineNumberTable:
        line 663: 0
      LocalVariableTable:
        Start  Length  Slot  Name   Signature
            0      16     0  this   Lscala/collection/ClassTagIterableFactory$Delegate;
            0      16     1    n1   I
            0      16     2    n2   I
            0      16     3    n3   I
            0      16     4    n4   I
            0      16     5    n5   I
            0      16     6  elem   Lscala/Function0;
            0      16     7 evidence$29   Lscala/reflect/ClassTag;
    Signature: #68                          // <A:Ljava/lang/Object;>(IIIIILscala/Function0<TA;>;Lscala/reflect/ClassTag<TA;>;)TCC;
    MethodParameters:
      Name                           Flags
      n1                             final
      n2                             final
      n3                             final
      n4                             final
      n5                             final
      elem                           final
      evidence$29                    final

  public <A extends java.lang.Object> CC tabulate(int, int, scala.Function2<java.lang.Object, java.lang.Object, A>, scala.reflect.ClassTag<A>);
    descriptor: (IILscala/Function2;Lscala/reflect/ClassTag;)Ljava/lang/Object;
    flags: (0x0001) ACC_PUBLIC
    Code:
      stack=5, locals=5, args_size=5
         0: aload_0
         1: iload_1
         2: iload_2
         3: aload_3
         4: aload         4
         6: invokestatic  #82                 // InterfaceMethod scala/collection/ClassTagIterableFactory.tabulate$:(Lscala/collection/ClassTagIterableFactory;IILscala/Function2;Lscala/reflect/ClassTag;)Ljava/lang/Object;
         9: areturn
      LineNumberTable:
        line 663: 0
      LocalVariableTable:
        Start  Length  Slot  Name   Signature
            0      10     0  this   Lscala/collection/ClassTagIterableFactory$Delegate;
            0      10     1    n1   I
            0      10     2    n2   I
            0      10     3     f   Lscala/Function2;
            0      10     4 evidence$30   Lscala/reflect/ClassTag;
    Signature: #76                          // <A:Ljava/lang/Object;>(IILscala/Function2<Ljava/lang/Object;Ljava/lang/Object;TA;>;Lscala/reflect/ClassTag<TA;>;)TCC;
    MethodParameters:
      Name                           Flags
      n1                             final
      n2                             final
      f                              final
      evidence$30                    final

  public <A extends java.lang.Object> CC tabulate(int, int, int, scala.Function3<java.lang.Object, java.lang.Object, java.lang.Object, A>, scala.reflect.ClassTag<A>);
    descriptor: (IIILscala/Function3;Lscala/reflect/ClassTag;)Ljava/lang/Object;
    flags: (0x0001) ACC_PUBLIC
    Code:
      stack=6, locals=6, args_size=6
         0: aload_0
         1: iload_1
         2: iload_2
         3: iload_3
         4: aload         4
         6: aload         5
         8: invokestatic  #89                 // InterfaceMethod scala/collection/ClassTagIterableFactory.tabulate$:(Lscala/collection/ClassTagIterableFactory;IIILscala/Function3;Lscala/reflect/ClassTag;)Ljava/lang/Object;
        11: areturn
      LineNumberTable:
        line 663: 0
      LocalVariableTable:
        Start  Length  Slot  Name   Signature
            0      12     0  this   Lscala/collection/ClassTagIterableFactory$Delegate;
            0      12     1    n1   I
            0      12     2    n2   I
            0      12     3    n3   I
            0      12     4     f   Lscala/Function3;
            0      12     5 evidence$31   Lscala/reflect/ClassTag;
    Signature: #85                          // <A:Ljava/lang/Object;>(IIILscala/Function3<Ljava/lang/Object;Ljava/lang/Object;Ljava/lang/Object;TA;>;Lscala/reflect/ClassTag<TA;>;)TCC;
    MethodParameters:
      Name                           Flags
      n1                             final
      n2                             final
      n3                             final
      f                              final
      evidence$31                    final

  public <A extends java.lang.Object> CC tabulate(int, int, int, int, scala.Function4<java.lang.Object, java.lang.Object, java.lang.Object, java.lang.Object, A>, scala.reflect.ClassTag<A>);
    descriptor: (IIIILscala/Function4;Lscala/reflect/ClassTag;)Ljava/lang/Object;
    flags: (0x0001) ACC_PUBLIC
    Code:
      stack=7, locals=7, args_size=7
         0: aload_0
         1: iload_1
         2: iload_2
         3: iload_3
         4: iload         4
         6: aload         5
         8: aload         6
        10: invokestatic  #96                 // InterfaceMethod scala/collection/ClassTagIterableFactory.tabulate$:(Lscala/collection/ClassTagIterableFactory;IIIILscala/Function4;Lscala/reflect/ClassTag;)Ljava/lang/Object;
        13: areturn
      LineNumberTable:
        line 663: 0
      LocalVariableTable:
        Start  Length  Slot  Name   Signature
            0      14     0  this   Lscala/collection/ClassTagIterableFactory$Delegate;
            0      14     1    n1   I
            0      14     2    n2   I
            0      14     3    n3   I
            0      14     4    n4   I
            0      14     5     f   Lscala/Function4;
            0      14     6 evidence$32   Lscala/reflect/ClassTag;
    Signature: #92                          // <A:Ljava/lang/Object;>(IIIILscala/Function4<Ljava/lang/Object;Ljava/lang/Object;Ljava/lang/Object;Ljava/lang/Object;TA;>;Lscala/reflect/ClassTag<TA;>;)TCC;
    MethodParameters:
      Name                           Flags
      n1                             final
      n2                             final
      n3                             final
      n4                             final
      f                              final
      evidence$32                    final

  public <A extends java.lang.Object> CC tabulate(int, int, int, int, int, scala.Function5<java.lang.Object, java.lang.Object, java.lang.Object, java.lang.Object, java.lang.Object, A>, scala.reflect.ClassTag<A>);
    descriptor: (IIIIILscala/Function5;Lscala/reflect/ClassTag;)Ljava/lang/Object;
    flags: (0x0001) ACC_PUBLIC
    Code:
      stack=8, locals=8, args_size=8
         0: aload_0
         1: iload_1
         2: iload_2
         3: iload_3
         4: iload         4
         6: iload         5
         8: aload         6
        10: aload         7
        12: invokestatic  #103                // InterfaceMethod scala/collection/ClassTagIterableFactory.tabulate$:(Lscala/collection/ClassTagIterableFactory;IIIIILscala/Function5;Lscala/reflect/ClassTag;)Ljava/lang/Object;
        15: areturn
      LineNumberTable:
        line 663: 0
      LocalVariableTable:
        Start  Length  Slot  Name   Signature
            0      16     0  this   Lscala/collection/ClassTagIterableFactory$Delegate;
            0      16     1    n1   I
            0      16     2    n2   I
            0      16     3    n3   I
            0      16     4    n4   I
            0      16     5    n5   I
            0      16     6     f   Lscala/Function5;
            0      16     7 evidence$33   Lscala/reflect/ClassTag;
    Signature: #99                          // <A:Ljava/lang/Object;>(IIIIILscala/Function5<Ljava/lang/Object;Ljava/lang/Object;Ljava/lang/Object;Ljava/lang/Object;Ljava/lang/Object;TA;>;Lscala/reflect/ClassTag<TA;>;)TCC;
    MethodParameters:
      Name                           Flags
      n1                             final
      n2                             final
      n3                             final
      n4                             final
      n5                             final
      f                              final
      evidence$33                    final

  public scala.collection.ClassTagIterableFactory$Delegate(scala.collection.EvidenceIterableFactory<CC, scala.reflect.ClassTag>);
    descriptor: (Lscala/collection/EvidenceIterableFactory;)V
    flags: (0x0001) ACC_PUBLIC
    Code:
      stack=2, locals=2, args_size=2
         0: aload_0
         1: aload_1
         2: invokespecial #110                // Method scala/collection/EvidenceIterableFactory$Delegate."<init>":(Lscala/collection/EvidenceIterableFactory;)V
         5: return
      LineNumberTable:
        line 664: 0
        line 663: 5
      LocalVariableTable:
        Start  Length  Slot  Name   Signature
            0       6     0  this   Lscala/collection/ClassTagIterableFactory$Delegate;
            0       6     1 delegate   Lscala/collection/EvidenceIterableFactory;
    Signature: #107                         // (Lscala/collection/EvidenceIterableFactory<TCC;Lscala/reflect/ClassTag;>;)V
    MethodParameters:
      Name                           Flags
      delegate                       final
}
InnerClasses:
  public static #9= #2 of #7;             // Delegate=class scala/collection/ClassTagIterableFactory$Delegate of class scala/collection/ClassTagIterableFactory
  public static #9= #5 of #11;            // Delegate=class scala/collection/EvidenceIterableFactory$Delegate of class scala/collection/EvidenceIterableFactory
Signature: #3                           // <CC:Ljava/lang/Object;>Lscala/collection/EvidenceIterableFactory$Delegate<TCC;Lscala/reflect/ClassTag;>;Lscala/collection/ClassTagIterableFactory<TCC;>;
SourceFile: "Factory.scala"
  ScalaInlineInfo: length = 0x3B (unknown attribute)
   01 00 00 0B 00 69 00 6A 00 00 28 00 43 00 00 28
   00 3C 00 00 28 00 35 00 00 28 00 29 00 00 10 00
   20 00 00 10 00 11 00 00 4A 00 62 00 00 4A 00 5B
   00 00 4A 00 54 00 00 4A 00 4B 00
  Scala: length = 0x0 (unknown attribute)

