Classfile /Users/mw/Projects/slang-braindump/.jar/jar11/assemble/slang-braindump/assemble/content/scala/collection/DoubleStepper$DoubleStepperSpliterator.class
  Last modified May 29, 2022; size 2909 bytes
  SHA-256 checksum b2f676f07fc1e51fef31cd6c83e9657e0c12600a13d793d04ac474e74307c531
  Compiled from "Stepper.scala"
public class scala.collection.DoubleStepper$DoubleStepperSpliterator implements java.util.Spliterator$OfDouble
  minor version: 0
  major version: 52
  flags: (0x0021) ACC_PUBLIC, ACC_SUPER
  this_class: #2                          // scala/collection/DoubleStepper$DoubleStepperSpliterator
  super_class: #4                         // java/lang/Object
  interfaces: 1, fields: 1, methods: 12, attributes: 4
Constant pool:
    #1 = Utf8               scala/collection/DoubleStepper$DoubleStepperSpliterator
    #2 = Class              #1            // scala/collection/DoubleStepper$DoubleStepperSpliterator
    #3 = Utf8               java/lang/Object
    #4 = Class              #3            // java/lang/Object
    #5 = Utf8               java/util/Spliterator$OfDouble
    #6 = Class              #5            // java/util/Spliterator$OfDouble
    #7 = Utf8               Stepper.scala
    #8 = Utf8               java/util/Spliterator
    #9 = Class              #8            // java/util/Spliterator
   #10 = Utf8               OfDouble
   #11 = Utf8               java/util/Spliterator$OfPrimitive
   #12 = Class              #11           // java/util/Spliterator$OfPrimitive
   #13 = Utf8               OfPrimitive
   #14 = Utf8               scala/collection/DoubleStepper
   #15 = Class              #14           // scala/collection/DoubleStepper
   #16 = Utf8               DoubleStepperSpliterator
   #17 = Utf8               s
   #18 = Utf8               Lscala/collection/DoubleStepper;
   #19 = Utf8               tryAdvance
   #20 = Utf8               (Ljava/util/function/DoubleConsumer;)Z
   #21 = Utf8               c
   #22 = NameAndType        #17:#18       // s:Lscala/collection/DoubleStepper;
   #23 = Fieldref           #2.#22        // scala/collection/DoubleStepper$DoubleStepperSpliterator.s:Lscala/collection/DoubleStepper;
   #24 = Utf8               hasStep
   #25 = Utf8               ()Z
   #26 = NameAndType        #24:#25       // hasStep:()Z
   #27 = InterfaceMethodref #15.#26       // scala/collection/DoubleStepper.hasStep:()Z
   #28 = Utf8               nextStep$mcD$sp
   #29 = Utf8               ()D
   #30 = NameAndType        #28:#29       // nextStep$mcD$sp:()D
   #31 = InterfaceMethodref #15.#30       // scala/collection/DoubleStepper.nextStep$mcD$sp:()D
   #32 = Utf8               java/util/function/DoubleConsumer
   #33 = Class              #32           // java/util/function/DoubleConsumer
   #34 = Utf8               accept
   #35 = Utf8               (D)V
   #36 = NameAndType        #34:#35       // accept:(D)V
   #37 = InterfaceMethodref #33.#36       // java/util/function/DoubleConsumer.accept:(D)V
   #38 = Utf8               this
   #39 = Utf8               Lscala/collection/DoubleStepper$DoubleStepperSpliterator;
   #40 = Utf8               Ljava/util/function/DoubleConsumer;
   #41 = Utf8               (Ljava/util/function/Consumer;)Z
   #42 = Utf8               (Ljava/util/function/Consumer<-Ljava/lang/Double;>;)Z
   #43 = NameAndType        #19:#20       // tryAdvance:(Ljava/util/function/DoubleConsumer;)Z
   #44 = Methodref          #2.#43        // scala/collection/DoubleStepper$DoubleStepperSpliterator.tryAdvance:(Ljava/util/function/DoubleConsumer;)Z
   #45 = Utf8               java/lang/Double
   #46 = Class              #45           // java/lang/Double
   #47 = Utf8               valueOf
   #48 = Utf8               (D)Ljava/lang/Double;
   #49 = NameAndType        #47:#48       // valueOf:(D)Ljava/lang/Double;
   #50 = Methodref          #46.#49       // java/lang/Double.valueOf:(D)Ljava/lang/Double;
   #51 = Utf8               java/util/function/Consumer
   #52 = Class              #51           // java/util/function/Consumer
   #53 = Utf8               (Ljava/lang/Object;)V
   #54 = NameAndType        #34:#53       // accept:(Ljava/lang/Object;)V
   #55 = InterfaceMethodref #52.#54       // java/util/function/Consumer.accept:(Ljava/lang/Object;)V
   #56 = Utf8               Ljava/util/function/Consumer;
   #57 = Utf8               trySplit
   #58 = Utf8               ()Ljava/util/Spliterator$OfDouble;
   #59 = Utf8               ()Lscala/collection/DoubleStepper;
   #60 = NameAndType        #57:#59       // trySplit:()Lscala/collection/DoubleStepper;
   #61 = InterfaceMethodref #15.#60       // scala/collection/DoubleStepper.trySplit:()Lscala/collection/DoubleStepper;
   #62 = Utf8               spliterator
   #63 = NameAndType        #62:#58       // spliterator:()Ljava/util/Spliterator$OfDouble;
   #64 = InterfaceMethodref #15.#63       // scala/collection/DoubleStepper.spliterator:()Ljava/util/Spliterator$OfDouble;
   #65 = Utf8               sp
   #66 = Utf8               estimateSize
   #67 = Utf8               ()J
   #68 = NameAndType        #66:#67       // estimateSize:()J
   #69 = InterfaceMethodref #15.#68       // scala/collection/DoubleStepper.estimateSize:()J
   #70 = Utf8               characteristics
   #71 = Utf8               ()I
   #72 = NameAndType        #70:#71       // characteristics:()I
   #73 = InterfaceMethodref #15.#72       // scala/collection/DoubleStepper.characteristics:()I
   #74 = Utf8               forEachRemaining
   #75 = Utf8               (Ljava/util/function/DoubleConsumer;)V
   #76 = Utf8               (Ljava/util/function/Consumer;)V
   #77 = Utf8               (Ljava/util/function/Consumer<-Ljava/lang/Double;>;)V
   #78 = NameAndType        #74:#75       // forEachRemaining:(Ljava/util/function/DoubleConsumer;)V
   #79 = Methodref          #2.#78        // scala/collection/DoubleStepper$DoubleStepperSpliterator.forEachRemaining:(Ljava/util/function/DoubleConsumer;)V
   #80 = Utf8               x$1
   #81 = Utf8               Ljava/lang/Object;
   #82 = Utf8               ()Ljava/util/Spliterator;
   #83 = NameAndType        #57:#58       // trySplit:()Ljava/util/Spliterator$OfDouble;
   #84 = Methodref          #2.#83        // scala/collection/DoubleStepper$DoubleStepperSpliterator.trySplit:()Ljava/util/Spliterator$OfDouble;
   #85 = Utf8               ()Ljava/util/Spliterator$OfPrimitive;
   #86 = Utf8               (Ljava/lang/Object;)Z
   #87 = Utf8               <init>
   #88 = Utf8               (Lscala/collection/DoubleStepper;)V
   #89 = Utf8               ()V
   #90 = NameAndType        #87:#89       // "<init>":()V
   #91 = Methodref          #4.#90        // java/lang/Object."<init>":()V
   #92 = Utf8               Code
   #93 = Utf8               StackMapTable
   #94 = Utf8               LineNumberTable
   #95 = Utf8               LocalVariableTable
   #96 = Utf8               MethodParameters
   #97 = Utf8               Signature
   #98 = Utf8               InnerClasses
   #99 = Utf8               SourceFile
  #100 = Utf8               ScalaInlineInfo
  #101 = Utf8               Scala
{
  private final scala.collection.DoubleStepper s;
    descriptor: Lscala/collection/DoubleStepper;
    flags: (0x0012) ACC_PRIVATE, ACC_FINAL

  public boolean tryAdvance(java.util.function.DoubleConsumer);
    descriptor: (Ljava/util/function/DoubleConsumer;)Z
    flags: (0x0001) ACC_PUBLIC
    Code:
      stack=3, locals=2, args_size=2
         0: aload_0
         1: getfield      #23                 // Field s:Lscala/collection/DoubleStepper;
         4: invokeinterface #27,  1           // InterfaceMethod scala/collection/DoubleStepper.hasStep:()Z
         9: ifeq          29
        12: aload_1
        13: aload_0
        14: getfield      #23                 // Field s:Lscala/collection/DoubleStepper;
        17: invokeinterface #31,  1           // InterfaceMethod scala/collection/DoubleStepper.nextStep$mcD$sp:()D
        22: invokeinterface #37,  3           // InterfaceMethod java/util/function/DoubleConsumer.accept:(D)V
        27: iconst_1
        28: ireturn
        29: iconst_0
        30: ireturn
      StackMapTable: number_of_entries = 1
        frame_type = 29 /* same */
      LineNumberTable:
        line 307: 0
      LocalVariableTable:
        Start  Length  Slot  Name   Signature
            0      31     0  this   Lscala/collection/DoubleStepper$DoubleStepperSpliterator;
            0      31     1     c   Ljava/util/function/DoubleConsumer;
    MethodParameters:
      Name                           Flags
      c                              final

  public boolean tryAdvance(java.util.function.Consumer<? super java.lang.Double>);
    descriptor: (Ljava/util/function/Consumer;)Z
    flags: (0x0001) ACC_PUBLIC
    Code:
      stack=3, locals=4, args_size=2
         0: aload_1
         1: instanceof    #33                 // class java/util/function/DoubleConsumer
         4: ifeq          21
         7: aload_1
         8: checkcast     #33                 // class java/util/function/DoubleConsumer
        11: astore_3
        12: aload_0
        13: aload_3
        14: invokevirtual #44                 // Method tryAdvance:(Ljava/util/function/DoubleConsumer;)Z
        17: istore_2
        18: goto          57
        21: aload_0
        22: getfield      #23                 // Field s:Lscala/collection/DoubleStepper;
        25: invokeinterface #27,  1           // InterfaceMethod scala/collection/DoubleStepper.hasStep:()Z
        30: ifeq          55
        33: aload_1
        34: aload_0
        35: getfield      #23                 // Field s:Lscala/collection/DoubleStepper;
        38: invokeinterface #31,  1           // InterfaceMethod scala/collection/DoubleStepper.nextStep$mcD$sp:()D
        43: invokestatic  #50                 // Method java/lang/Double.valueOf:(D)Ljava/lang/Double;
        46: invokeinterface #55,  2           // InterfaceMethod java/util/function/Consumer.accept:(Ljava/lang/Object;)V
        51: iconst_1
        52: goto          56
        55: iconst_0
        56: istore_2
        57: iload_2
        58: ireturn
      StackMapTable: number_of_entries = 4
        frame_type = 21 /* same */
        frame_type = 33 /* same */
        frame_type = 64 /* same_locals_1_stack_item */
          stack = [ int ]
        frame_type = 252 /* append */
          offset_delta = 0
          locals = [ int ]
      LineNumberTable:
        line 310: 0
        line 311: 21
        line 309: 57
      LocalVariableTable:
        Start  Length  Slot  Name   Signature
            0      59     0  this   Lscala/collection/DoubleStepper$DoubleStepperSpliterator;
            0      59     1     c   Ljava/util/function/Consumer;
    Signature: #42                          // (Ljava/util/function/Consumer<-Ljava/lang/Double;>;)Z
    MethodParameters:
      Name                           Flags
      c                              final

  public java.util.Spliterator$OfDouble trySplit();
    descriptor: ()Ljava/util/Spliterator$OfDouble;
    flags: (0x0001) ACC_PUBLIC
    Code:
      stack=1, locals=2, args_size=1
         0: aload_0
         1: getfield      #23                 // Field s:Lscala/collection/DoubleStepper;
         4: invokeinterface #61,  1           // InterfaceMethod scala/collection/DoubleStepper.trySplit:()Lscala/collection/DoubleStepper;
         9: astore_1
        10: aload_1
        11: ifnonnull     16
        14: aconst_null
        15: areturn
        16: aload_1
        17: invokeinterface #64,  1           // InterfaceMethod scala/collection/DoubleStepper.spliterator:()Ljava/util/Spliterator$OfDouble;
        22: areturn
      StackMapTable: number_of_entries = 1
        frame_type = 252 /* append */
          offset_delta = 16
          locals = [ class scala/collection/DoubleStepper ]
      LineNumberTable:
        line 315: 0
        line 316: 10
      LocalVariableTable:
        Start  Length  Slot  Name   Signature
           10      12     1    sp   Lscala/collection/DoubleStepper;
            0      23     0  this   Lscala/collection/DoubleStepper$DoubleStepperSpliterator;

  public long estimateSize();
    descriptor: ()J
    flags: (0x0001) ACC_PUBLIC
    Code:
      stack=2, locals=1, args_size=1
         0: aload_0
         1: getfield      #23                 // Field s:Lscala/collection/DoubleStepper;
         4: invokeinterface #69,  1           // InterfaceMethod scala/collection/DoubleStepper.estimateSize:()J
         9: lreturn
      LineNumberTable:
        line 318: 0
      LocalVariableTable:
        Start  Length  Slot  Name   Signature
            0      10     0  this   Lscala/collection/DoubleStepper$DoubleStepperSpliterator;

  public int characteristics();
    descriptor: ()I
    flags: (0x0001) ACC_PUBLIC
    Code:
      stack=1, locals=1, args_size=1
         0: aload_0
         1: getfield      #23                 // Field s:Lscala/collection/DoubleStepper;
         4: invokeinterface #73,  1           // InterfaceMethod scala/collection/DoubleStepper.characteristics:()I
         9: ireturn
      LineNumberTable:
        line 319: 0
      LocalVariableTable:
        Start  Length  Slot  Name   Signature
            0      10     0  this   Lscala/collection/DoubleStepper$DoubleStepperSpliterator;

  public void forEachRemaining(java.util.function.DoubleConsumer);
    descriptor: (Ljava/util/function/DoubleConsumer;)V
    flags: (0x0001) ACC_PUBLIC
    Code:
      stack=3, locals=2, args_size=2
         0: aload_0
         1: getfield      #23                 // Field s:Lscala/collection/DoubleStepper;
         4: invokeinterface #27,  1           // InterfaceMethod scala/collection/DoubleStepper.hasStep:()Z
         9: ifeq          30
        12: aload_1
        13: aload_0
        14: getfield      #23                 // Field s:Lscala/collection/DoubleStepper;
        17: invokeinterface #31,  1           // InterfaceMethod scala/collection/DoubleStepper.nextStep$mcD$sp:()D
        22: invokeinterface #37,  3           // InterfaceMethod java/util/function/DoubleConsumer.accept:(D)V
        27: goto          0
        30: return
      StackMapTable: number_of_entries = 2
        frame_type = 0 /* same */
        frame_type = 29 /* same */
      LineNumberTable:
        line 322: 0
      LocalVariableTable:
        Start  Length  Slot  Name   Signature
            0      31     0  this   Lscala/collection/DoubleStepper$DoubleStepperSpliterator;
            0      31     1     c   Ljava/util/function/DoubleConsumer;
    MethodParameters:
      Name                           Flags
      c                              final

  public void forEachRemaining(java.util.function.Consumer<? super java.lang.Double>);
    descriptor: (Ljava/util/function/Consumer;)V
    flags: (0x0001) ACC_PUBLIC
    Code:
      stack=3, locals=3, args_size=2
         0: aload_1
         1: instanceof    #33                 // class java/util/function/DoubleConsumer
         4: ifeq          18
         7: aload_1
         8: checkcast     #33                 // class java/util/function/DoubleConsumer
        11: astore_2
        12: aload_0
        13: aload_2
        14: invokevirtual #79                 // Method forEachRemaining:(Ljava/util/function/DoubleConsumer;)V
        17: return
        18: aload_0
        19: getfield      #23                 // Field s:Lscala/collection/DoubleStepper;
        22: invokeinterface #27,  1           // InterfaceMethod scala/collection/DoubleStepper.hasStep:()Z
        27: ifeq          51
        30: aload_1
        31: aload_0
        32: getfield      #23                 // Field s:Lscala/collection/DoubleStepper;
        35: invokeinterface #31,  1           // InterfaceMethod scala/collection/DoubleStepper.nextStep$mcD$sp:()D
        40: invokestatic  #50                 // Method java/lang/Double.valueOf:(D)Ljava/lang/Double;
        43: invokeinterface #55,  2           // InterfaceMethod java/util/function/Consumer.accept:(Ljava/lang/Object;)V
        48: goto          18
        51: return
      StackMapTable: number_of_entries = 2
        frame_type = 18 /* same */
        frame_type = 32 /* same */
      LineNumberTable:
        line 325: 0
        line 326: 18
        line 324: 51
      LocalVariableTable:
        Start  Length  Slot  Name   Signature
            0      52     0  this   Lscala/collection/DoubleStepper$DoubleStepperSpliterator;
            0      52     1     c   Ljava/util/function/Consumer;
    Signature: #77                          // (Ljava/util/function/Consumer<-Ljava/lang/Double;>;)V
    MethodParameters:
      Name                           Flags
      c                              final

  public void forEachRemaining(java.lang.Object);
    descriptor: (Ljava/lang/Object;)V
    flags: (0x1041) ACC_PUBLIC, ACC_BRIDGE, ACC_SYNTHETIC
    Code:
      stack=2, locals=2, args_size=2
         0: aload_0
         1: aload_1
         2: checkcast     #33                 // class java/util/function/DoubleConsumer
         5: invokevirtual #79                 // Method forEachRemaining:(Ljava/util/function/DoubleConsumer;)V
         8: return
      LineNumberTable:
        line 305: 0
      LocalVariableTable:
        Start  Length  Slot  Name   Signature
            0       9     0  this   Lscala/collection/DoubleStepper$DoubleStepperSpliterator;
            0       9     1   x$1   Ljava/lang/Object;
    MethodParameters:
      Name                           Flags
      x$1                            final

  public java.util.Spliterator trySplit();
    descriptor: ()Ljava/util/Spliterator;
    flags: (0x1041) ACC_PUBLIC, ACC_BRIDGE, ACC_SYNTHETIC
    Code:
      stack=1, locals=1, args_size=1
         0: aload_0
         1: invokevirtual #84                 // Method trySplit:()Ljava/util/Spliterator$OfDouble;
         4: areturn
      LineNumberTable:
        line 305: 0
      LocalVariableTable:
        Start  Length  Slot  Name   Signature
            0       5     0  this   Lscala/collection/DoubleStepper$DoubleStepperSpliterator;

  public java.util.Spliterator$OfPrimitive trySplit();
    descriptor: ()Ljava/util/Spliterator$OfPrimitive;
    flags: (0x1041) ACC_PUBLIC, ACC_BRIDGE, ACC_SYNTHETIC
    Code:
      stack=1, locals=1, args_size=1
         0: aload_0
         1: invokevirtual #84                 // Method trySplit:()Ljava/util/Spliterator$OfDouble;
         4: areturn
      LineNumberTable:
        line 305: 0
      LocalVariableTable:
        Start  Length  Slot  Name   Signature
            0       5     0  this   Lscala/collection/DoubleStepper$DoubleStepperSpliterator;

  public boolean tryAdvance(java.lang.Object);
    descriptor: (Ljava/lang/Object;)Z
    flags: (0x1041) ACC_PUBLIC, ACC_BRIDGE, ACC_SYNTHETIC
    Code:
      stack=2, locals=2, args_size=2
         0: aload_0
         1: aload_1
         2: checkcast     #33                 // class java/util/function/DoubleConsumer
         5: invokevirtual #44                 // Method tryAdvance:(Ljava/util/function/DoubleConsumer;)Z
         8: ireturn
      LineNumberTable:
        line 305: 0
      LocalVariableTable:
        Start  Length  Slot  Name   Signature
            0       9     0  this   Lscala/collection/DoubleStepper$DoubleStepperSpliterator;
            0       9     1   x$1   Ljava/lang/Object;
    MethodParameters:
      Name                           Flags
      x$1                            final

  public scala.collection.DoubleStepper$DoubleStepperSpliterator(scala.collection.DoubleStepper);
    descriptor: (Lscala/collection/DoubleStepper;)V
    flags: (0x0001) ACC_PUBLIC
    Code:
      stack=2, locals=2, args_size=2
         0: aload_0
         1: aload_1
         2: putfield      #23                 // Field s:Lscala/collection/DoubleStepper;
         5: aload_0
         6: invokespecial #91                 // Method java/lang/Object."<init>":()V
         9: return
      LineNumberTable:
        line 305: 0
      LocalVariableTable:
        Start  Length  Slot  Name   Signature
            0      10     0  this   Lscala/collection/DoubleStepper$DoubleStepperSpliterator;
            0      10     1     s   Lscala/collection/DoubleStepper;
    MethodParameters:
      Name                           Flags
      s                              final
}
InnerClasses:
  public static #10= #6 of #9;            // OfDouble=class java/util/Spliterator$OfDouble of class java/util/Spliterator
  public static #13= #12 of #9;           // OfPrimitive=class java/util/Spliterator$OfPrimitive of class java/util/Spliterator
  public static #16= #2 of #15;           // DoubleStepperSpliterator=class scala/collection/DoubleStepper$DoubleStepperSpliterator of class scala/collection/DoubleStepper
SourceFile: "Stepper.scala"
  ScalaInlineInfo: length = 0x40 (unknown attribute)
   01 00 00 0C 00 57 00 58 00 00 46 00 47 00 00 42
   00 43 00 00 4A 00 35 00 00 4A 00 4C 00 00 4A 00
   4B 00 00 13 00 56 00 00 13 00 29 00 00 13 00 14
   00 00 39 00 3A 00 00 39 00 55 00 00 39 00 52 00

  Scala: length = 0x0 (unknown attribute)

