Classfile /Users/mw/Projects/slang-braindump/.jar/jar11/assemble/slang-braindump/assemble/content/scala/collection/EvidenceIterableFactory$ToFactory.class
  Last modified May 29, 2022; size 1756 bytes
  SHA-256 checksum 1f604b2fbb1b077cfd3a68b5476551a908df9930279562bc0f399861aef0e6cc
  Compiled from "Factory.scala"
public class scala.collection.EvidenceIterableFactory$ToFactory<Ev extends java.lang.Object, A extends java.lang.Object, CC extends java.lang.Object> extends java.lang.Object implements scala.collection.Factory<A, CC>, java.io.Serializable
  minor version: 0
  major version: 52
  flags: (0x0021) ACC_PUBLIC, ACC_SUPER
  this_class: #2                          // scala/collection/EvidenceIterableFactory$ToFactory
  super_class: #5                         // java/lang/Object
  interfaces: 2, fields: 3, methods: 3, attributes: 5
Constant pool:
   #1 = Utf8               scala/collection/EvidenceIterableFactory$ToFactory
   #2 = Class              #1             // scala/collection/EvidenceIterableFactory$ToFactory
   #3 = Utf8               <Ev:Ljava/lang/Object;A:Ljava/lang/Object;CC:Ljava/lang/Object;>Ljava/lang/Object;Lscala/collection/Factory<TA;TCC;>;Ljava/io/Serializable;
   #4 = Utf8               java/lang/Object
   #5 = Class              #4             // java/lang/Object
   #6 = Utf8               scala/collection/Factory
   #7 = Class              #6             // scala/collection/Factory
   #8 = Utf8               java/io/Serializable
   #9 = Class              #8             // java/io/Serializable
  #10 = Utf8               Factory.scala
  #11 = Utf8               scala/collection/EvidenceIterableFactory
  #12 = Class              #11            // scala/collection/EvidenceIterableFactory
  #13 = Utf8               ToFactory
  #14 = Utf8               serialVersionUID
  #15 = Utf8               J
  #16 = Long               3l
  #18 = Utf8               factory
  #19 = Utf8               Lscala/collection/EvidenceIterableFactory;
  #20 = Utf8               Lscala/collection/EvidenceIterableFactory<TCC;TEv;>;
  #21 = Utf8               evidence$15
  #22 = Utf8               Ljava/lang/Object;
  #23 = Utf8               TEv;
  #24 = Utf8               fromSpecific
  #25 = Utf8               (Lscala/collection/IterableOnce;)Ljava/lang/Object;
  #26 = Utf8               (Lscala/collection/IterableOnce<TA;>;)TCC;
  #27 = Utf8               it
  #28 = NameAndType        #18:#19        // factory:Lscala/collection/EvidenceIterableFactory;
  #29 = Fieldref           #2.#28         // scala/collection/EvidenceIterableFactory$ToFactory.factory:Lscala/collection/EvidenceIterableFactory;
  #30 = NameAndType        #21:#22        // evidence$15:Ljava/lang/Object;
  #31 = Fieldref           #2.#30         // scala/collection/EvidenceIterableFactory$ToFactory.evidence$15:Ljava/lang/Object;
  #32 = Utf8               from
  #33 = Utf8               (Lscala/collection/IterableOnce;Ljava/lang/Object;)Ljava/lang/Object;
  #34 = NameAndType        #32:#33        // from:(Lscala/collection/IterableOnce;Ljava/lang/Object;)Ljava/lang/Object;
  #35 = InterfaceMethodref #12.#34        // scala/collection/EvidenceIterableFactory.from:(Lscala/collection/IterableOnce;Ljava/lang/Object;)Ljava/lang/Object;
  #36 = Utf8               this
  #37 = Utf8               Lscala/collection/EvidenceIterableFactory$ToFactory;
  #38 = Utf8               Lscala/collection/IterableOnce;
  #39 = Utf8               newBuilder
  #40 = Utf8               ()Lscala/collection/mutable/Builder;
  #41 = Utf8               ()Lscala/collection/mutable/Builder<TA;TCC;>;
  #42 = Utf8               (Ljava/lang/Object;)Lscala/collection/mutable/Builder;
  #43 = NameAndType        #39:#42        // newBuilder:(Ljava/lang/Object;)Lscala/collection/mutable/Builder;
  #44 = InterfaceMethodref #12.#43        // scala/collection/EvidenceIterableFactory.newBuilder:(Ljava/lang/Object;)Lscala/collection/mutable/Builder;
  #45 = Utf8               <init>
  #46 = Utf8               (Lscala/collection/EvidenceIterableFactory;Ljava/lang/Object;)V
  #47 = Utf8               (Lscala/collection/EvidenceIterableFactory<TCC;TEv;>;TEv;)V
  #48 = Utf8               ()V
  #49 = NameAndType        #45:#48        // "<init>":()V
  #50 = Methodref          #5.#49         // java/lang/Object."<init>":()V
  #51 = Utf8               ConstantValue
  #52 = Utf8               Signature
  #53 = Utf8               Code
  #54 = Utf8               LineNumberTable
  #55 = Utf8               LocalVariableTable
  #56 = Utf8               MethodParameters
  #57 = Utf8               InnerClasses
  #58 = Utf8               SourceFile
  #59 = Utf8               ScalaInlineInfo
  #60 = Utf8               Scala
{
  private static final long serialVersionUID;
    descriptor: J
    flags: (0x001a) ACC_PRIVATE, ACC_STATIC, ACC_FINAL
    ConstantValue: long 3l

  private final scala.collection.EvidenceIterableFactory<CC, Ev> factory;
    descriptor: Lscala/collection/EvidenceIterableFactory;
    flags: (0x0012) ACC_PRIVATE, ACC_FINAL
    Signature: #20                          // Lscala/collection/EvidenceIterableFactory<TCC;TEv;>;

  private final Ev evidence$15;
    descriptor: Ljava/lang/Object;
    flags: (0x0012) ACC_PRIVATE, ACC_FINAL
    Signature: #23                          // TEv;

  public CC fromSpecific(scala.collection.IterableOnce<A>);
    descriptor: (Lscala/collection/IterableOnce;)Ljava/lang/Object;
    flags: (0x0001) ACC_PUBLIC
    Code:
      stack=3, locals=2, args_size=2
         0: aload_0
         1: getfield      #29                 // Field factory:Lscala/collection/EvidenceIterableFactory;
         4: aload_1
         5: aload_0
         6: getfield      #31                 // Field evidence$15:Ljava/lang/Object;
         9: invokeinterface #35,  3           // InterfaceMethod scala/collection/EvidenceIterableFactory.from:(Lscala/collection/IterableOnce;Ljava/lang/Object;)Ljava/lang/Object;
        14: areturn
      LineNumberTable:
        line 520: 0
      LocalVariableTable:
        Start  Length  Slot  Name   Signature
            0      15     0  this   Lscala/collection/EvidenceIterableFactory$ToFactory;
            0      15     1    it   Lscala/collection/IterableOnce;
    Signature: #26                          // (Lscala/collection/IterableOnce<TA;>;)TCC;
    MethodParameters:
      Name                           Flags
      it                             final

  public scala.collection.mutable.Builder<A, CC> newBuilder();
    descriptor: ()Lscala/collection/mutable/Builder;
    flags: (0x0001) ACC_PUBLIC
    Code:
      stack=2, locals=1, args_size=1
         0: aload_0
         1: getfield      #29                 // Field factory:Lscala/collection/EvidenceIterableFactory;
         4: aload_0
         5: getfield      #31                 // Field evidence$15:Ljava/lang/Object;
         8: invokeinterface #44,  2           // InterfaceMethod scala/collection/EvidenceIterableFactory.newBuilder:(Ljava/lang/Object;)Lscala/collection/mutable/Builder;
        13: areturn
      LineNumberTable:
        line 521: 0
      LocalVariableTable:
        Start  Length  Slot  Name   Signature
            0      14     0  this   Lscala/collection/EvidenceIterableFactory$ToFactory;
    Signature: #41                          // ()Lscala/collection/mutable/Builder<TA;TCC;>;

  public scala.collection.EvidenceIterableFactory$ToFactory(scala.collection.EvidenceIterableFactory<CC, Ev>, Ev);
    descriptor: (Lscala/collection/EvidenceIterableFactory;Ljava/lang/Object;)V
    flags: (0x0001) ACC_PUBLIC
    Code:
      stack=2, locals=3, args_size=3
         0: aload_0
         1: aload_1
         2: putfield      #29                 // Field factory:Lscala/collection/EvidenceIterableFactory;
         5: aload_0
         6: aload_2
         7: putfield      #31                 // Field evidence$15:Ljava/lang/Object;
        10: aload_0
        11: invokespecial #50                 // Method java/lang/Object."<init>":()V
        14: return
      LineNumberTable:
        line 519: 0
      LocalVariableTable:
        Start  Length  Slot  Name   Signature
            0      15     0  this   Lscala/collection/EvidenceIterableFactory$ToFactory;
            0      15     1 factory   Lscala/collection/EvidenceIterableFactory;
            0      15     2 evidence$15   Ljava/lang/Object;
    Signature: #47                          // (Lscala/collection/EvidenceIterableFactory<TCC;TEv;>;TEv;)V
    MethodParameters:
      Name                           Flags
      factory                        final
      evidence$15                    final
}
InnerClasses:
  private static #13= #2 of #12;          // ToFactory=class scala/collection/EvidenceIterableFactory$ToFactory of class scala/collection/EvidenceIterableFactory
Signature: #3                           // <Ev:Ljava/lang/Object;A:Ljava/lang/Object;CC:Ljava/lang/Object;>Ljava/lang/Object;Lscala/collection/Factory<TA;TCC;>;Ljava/io/Serializable;
SourceFile: "Factory.scala"
  ScalaInlineInfo: length = 0x13 (unknown attribute)
   01 00 00 03 00 2D 00 2E 00 00 18 00 19 00 00 27
   00 28 00
  Scala: length = 0x0 (unknown attribute)

