Classfile /Users/mw/Projects/slang-braindump/.jar/jar11/assemble/slang-braindump/assemble/content/scala/collection/Factory$.class
  Last modified May 29, 2022; size 1329 bytes
  SHA-256 checksum a08c77f8da77d5e36544169592960be650a688a57ee36a45c82caf78f1819935
  Compiled from "Factory.scala"
public final class scala.collection.Factory$
  minor version: 0
  major version: 52
  flags: (0x0031) ACC_PUBLIC, ACC_FINAL, ACC_SUPER
  this_class: #2                          // scala/collection/Factory$
  super_class: #4                         // java/lang/Object
  interfaces: 0, fields: 2, methods: 4, attributes: 4
Constant pool:
   #1 = Utf8               scala/collection/Factory$
   #2 = Class              #1             // scala/collection/Factory$
   #3 = Utf8               java/lang/Object
   #4 = Class              #3             // java/lang/Object
   #5 = Utf8               Factory.scala
   #6 = Utf8               scala/collection/Factory$ArrayFactory
   #7 = Class              #6             // scala/collection/Factory$ArrayFactory
   #8 = Utf8               scala/collection/Factory
   #9 = Class              #8             // scala/collection/Factory
  #10 = Utf8               ArrayFactory
  #11 = Utf8               scala/collection/Factory$StringFactory
  #12 = Class              #11            // scala/collection/Factory$StringFactory
  #13 = Utf8               StringFactory
  #14 = Utf8               MODULE$
  #15 = Utf8               Lscala/collection/Factory$;
  #16 = Utf8               stringFactory
  #17 = Utf8               Lscala/collection/Factory;
  #18 = Utf8               Lscala/collection/Factory<Ljava/lang/Object;Ljava/lang/String;>;
  #19 = Utf8               <clinit>
  #20 = Utf8               ()V
  #21 = Utf8               <init>
  #22 = NameAndType        #21:#20        // "<init>":()V
  #23 = Methodref          #2.#22         // scala/collection/Factory$."<init>":()V
  #24 = NameAndType        #14:#15        // MODULE$:Lscala/collection/Factory$;
  #25 = Fieldref           #2.#24         // scala/collection/Factory$.MODULE$:Lscala/collection/Factory$;
  #26 = Methodref          #12.#22        // scala/collection/Factory$StringFactory."<init>":()V
  #27 = NameAndType        #16:#17        // stringFactory:Lscala/collection/Factory;
  #28 = Fieldref           #2.#27         // scala/collection/Factory$.stringFactory:Lscala/collection/Factory;
  #29 = Utf8               ()Lscala/collection/Factory;
  #30 = Utf8               ()Lscala/collection/Factory<Ljava/lang/Object;Ljava/lang/String;>;
  #31 = Utf8               this
  #32 = Utf8               arrayFactory
  #33 = Utf8               (Lscala/reflect/ClassTag;)Lscala/collection/Factory;
  #34 = Utf8               <A:Ljava/lang/Object;>(Lscala/reflect/ClassTag<TA;>;)Lscala/collection/Factory<TA;Ljava/lang/Object;>;
  #35 = Utf8               evidence$1
  #36 = Utf8               (Lscala/reflect/ClassTag;)V
  #37 = NameAndType        #21:#36        // "<init>":(Lscala/reflect/ClassTag;)V
  #38 = Methodref          #7.#37         // scala/collection/Factory$ArrayFactory."<init>":(Lscala/reflect/ClassTag;)V
  #39 = Utf8               Lscala/reflect/ClassTag;
  #40 = Methodref          #4.#22         // java/lang/Object."<init>":()V
  #41 = Utf8               Signature
  #42 = Utf8               Code
  #43 = Utf8               LineNumberTable
  #44 = Utf8               LocalVariableTable
  #45 = Utf8               MethodParameters
  #46 = Utf8               InnerClasses
  #47 = Utf8               SourceFile
  #48 = Utf8               ScalaInlineInfo
  #49 = Utf8               Scala
{
  public static final scala.collection.Factory$ MODULE$;
    descriptor: Lscala/collection/Factory$;
    flags: (0x0019) ACC_PUBLIC, ACC_STATIC, ACC_FINAL

  private static final scala.collection.Factory<java.lang.Object, java.lang.String> stringFactory;
    descriptor: Lscala/collection/Factory;
    flags: (0x001a) ACC_PRIVATE, ACC_STATIC, ACC_FINAL
    Signature: #18                          // Lscala/collection/Factory<Ljava/lang/Object;Ljava/lang/String;>;

  public static {};
    descriptor: ()V
    flags: (0x0009) ACC_PUBLIC, ACC_STATIC
    Code:
      stack=2, locals=0, args_size=0
         0: new           #2                  // class scala/collection/Factory$
         3: dup
         4: invokespecial #23                 // Method "<init>":()V
         7: putstatic     #25                 // Field MODULE$:Lscala/collection/Factory$;
        10: new           #12                 // class scala/collection/Factory$StringFactory
        13: dup
        14: invokespecial #26                 // Method scala/collection/Factory$StringFactory."<init>":()V
        17: putstatic     #28                 // Field stringFactory:Lscala/collection/Factory;
        20: return
      LineNumberTable:
        line 46: 0
        line 48: 10
        line 46: 20

  public scala.collection.Factory<java.lang.Object, java.lang.String> stringFactory();
    descriptor: ()Lscala/collection/Factory;
    flags: (0x0001) ACC_PUBLIC
    Code:
      stack=1, locals=1, args_size=1
         0: getstatic     #28                 // Field stringFactory:Lscala/collection/Factory;
         3: areturn
      LineNumberTable:
        line 48: 0
      LocalVariableTable:
        Start  Length  Slot  Name   Signature
            0       4     0  this   Lscala/collection/Factory$;
    Signature: #30                          // ()Lscala/collection/Factory<Ljava/lang/Object;Ljava/lang/String;>;

  public <A extends java.lang.Object> scala.collection.Factory<A, java.lang.Object> arrayFactory(scala.reflect.ClassTag<A>);
    descriptor: (Lscala/reflect/ClassTag;)Lscala/collection/Factory;
    flags: (0x0001) ACC_PUBLIC
    Code:
      stack=3, locals=2, args_size=2
         0: new           #7                  // class scala/collection/Factory$ArrayFactory
         3: dup
         4: aload_1
         5: invokespecial #38                 // Method scala/collection/Factory$ArrayFactory."<init>":(Lscala/reflect/ClassTag;)V
         8: areturn
      LineNumberTable:
        line 59: 0
      LocalVariableTable:
        Start  Length  Slot  Name   Signature
            0       9     0  this   Lscala/collection/Factory$;
            0       9     1 evidence$1   Lscala/reflect/ClassTag;
    Signature: #34                          // <A:Ljava/lang/Object;>(Lscala/reflect/ClassTag<TA;>;)Lscala/collection/Factory<TA;Ljava/lang/Object;>;
    MethodParameters:
      Name                           Flags
      evidence$1                     final

  private scala.collection.Factory$();
    descriptor: ()V
    flags: (0x0002) ACC_PRIVATE
    Code:
      stack=1, locals=1, args_size=1
         0: aload_0
         1: invokespecial #40                 // Method java/lang/Object."<init>":()V
         4: return
      LineNumberTable:
        line 46: 0
      LocalVariableTable:
        Start  Length  Slot  Name   Signature
            0       5     0  this   Lscala/collection/Factory$;
}
InnerClasses:
  private static #10= #7 of #9;           // ArrayFactory=class scala/collection/Factory$ArrayFactory of class scala/collection/Factory
  private static #13= #12 of #9;          // StringFactory=class scala/collection/Factory$StringFactory of class scala/collection/Factory
SourceFile: "Factory.scala"
  ScalaInlineInfo: length = 0x13 (unknown attribute)
   01 01 00 03 00 15 00 14 01 00 20 00 21 01 00 10
   00 1D 01
  Scala: length = 0x0 (unknown attribute)

