Classfile /Users/mw/Projects/slang-braindump/.jar/jar11/assemble/slang-braindump/assemble/content/scala/collection/Factory$ArrayFactory.class
  Last modified May 29, 2022; size 3591 bytes
  SHA-256 checksum 9281371dbb534c2e49a3fc7a614b0869f5b9e79c805401e91a1cfef379b2bddd
  Compiled from "Factory.scala"
public class scala.collection.Factory$ArrayFactory<A extends java.lang.Object> extends java.lang.Object implements scala.collection.Factory<A, java.lang.Object>, java.io.Serializable
  minor version: 0
  major version: 52
  flags: (0x0021) ACC_PUBLIC, ACC_SUPER
  this_class: #2                          // scala/collection/Factory$ArrayFactory
  super_class: #5                         // java/lang/Object
  interfaces: 2, fields: 2, methods: 3, attributes: 5
Constant pool:
    #1 = Utf8               scala/collection/Factory$ArrayFactory
    #2 = Class              #1            // scala/collection/Factory$ArrayFactory
    #3 = Utf8               <A:Ljava/lang/Object;>Ljava/lang/Object;Lscala/collection/Factory<TA;Ljava/lang/Object;>;Ljava/io/Serializable;
    #4 = Utf8               java/lang/Object
    #5 = Class              #4            // java/lang/Object
    #6 = Utf8               scala/collection/Factory
    #7 = Class              #6            // scala/collection/Factory
    #8 = Utf8               java/io/Serializable
    #9 = Class              #8            // java/io/Serializable
   #10 = Utf8               Factory.scala
   #11 = Utf8               ArrayFactory
   #12 = Utf8               scala/collection/mutable/ArrayBuilder$ofBoolean
   #13 = Class              #12           // scala/collection/mutable/ArrayBuilder$ofBoolean
   #14 = Utf8               scala/collection/mutable/ArrayBuilder
   #15 = Class              #14           // scala/collection/mutable/ArrayBuilder
   #16 = Utf8               ofBoolean
   #17 = Utf8               scala/collection/mutable/ArrayBuilder$ofByte
   #18 = Class              #17           // scala/collection/mutable/ArrayBuilder$ofByte
   #19 = Utf8               ofByte
   #20 = Utf8               scala/collection/mutable/ArrayBuilder$ofChar
   #21 = Class              #20           // scala/collection/mutable/ArrayBuilder$ofChar
   #22 = Utf8               ofChar
   #23 = Utf8               scala/collection/mutable/ArrayBuilder$ofDouble
   #24 = Class              #23           // scala/collection/mutable/ArrayBuilder$ofDouble
   #25 = Utf8               ofDouble
   #26 = Utf8               scala/collection/mutable/ArrayBuilder$ofFloat
   #27 = Class              #26           // scala/collection/mutable/ArrayBuilder$ofFloat
   #28 = Utf8               ofFloat
   #29 = Utf8               scala/collection/mutable/ArrayBuilder$ofInt
   #30 = Class              #29           // scala/collection/mutable/ArrayBuilder$ofInt
   #31 = Utf8               ofInt
   #32 = Utf8               scala/collection/mutable/ArrayBuilder$ofLong
   #33 = Class              #32           // scala/collection/mutable/ArrayBuilder$ofLong
   #34 = Utf8               ofLong
   #35 = Utf8               scala/collection/mutable/ArrayBuilder$ofRef
   #36 = Class              #35           // scala/collection/mutable/ArrayBuilder$ofRef
   #37 = Utf8               ofRef
   #38 = Utf8               scala/collection/mutable/ArrayBuilder$ofShort
   #39 = Class              #38           // scala/collection/mutable/ArrayBuilder$ofShort
   #40 = Utf8               ofShort
   #41 = Utf8               scala/collection/mutable/ArrayBuilder$ofUnit
   #42 = Class              #41           // scala/collection/mutable/ArrayBuilder$ofUnit
   #43 = Utf8               ofUnit
   #44 = Utf8               serialVersionUID
   #45 = Utf8               J
   #46 = Long               3l
   #48 = Utf8               evidence$2
   #49 = Utf8               Lscala/reflect/ClassTag;
   #50 = Utf8               Lscala/reflect/ClassTag<TA;>;
   #51 = Utf8               fromSpecific
   #52 = Utf8               (Lscala/collection/IterableOnce;)Ljava/lang/Object;
   #53 = Utf8               (Lscala/collection/IterableOnce<TA;>;)Ljava/lang/Object;
   #54 = Utf8               it
   #55 = Utf8               newBuilder
   #56 = Utf8               ()Lscala/collection/mutable/Builder;
   #57 = NameAndType        #55:#56       // newBuilder:()Lscala/collection/mutable/Builder;
   #58 = Methodref          #2.#57        // scala/collection/Factory$ArrayFactory.newBuilder:()Lscala/collection/mutable/Builder;
   #59 = Utf8               scala/math/package$
   #60 = Class              #59           // scala/math/package$
   #61 = Utf8               MODULE$
   #62 = Utf8               Lscala/math/package$;
   #63 = NameAndType        #61:#62       // MODULE$:Lscala/math/package$;
   #64 = Fieldref           #60.#63       // scala/math/package$.MODULE$:Lscala/math/package$;
   #65 = Utf8               scala/collection/IterableOnce
   #66 = Class              #65           // scala/collection/IterableOnce
   #67 = Utf8               knownSize
   #68 = Utf8               ()I
   #69 = NameAndType        #67:#68       // knownSize:()I
   #70 = InterfaceMethodref #66.#69       // scala/collection/IterableOnce.knownSize:()I
   #71 = Utf8               java/lang/Math
   #72 = Class              #71           // java/lang/Math
   #73 = Utf8               max
   #74 = Utf8               (II)I
   #75 = NameAndType        #73:#74       // max:(II)I
   #76 = Methodref          #72.#75       // java/lang/Math.max:(II)I
   #77 = Utf8               scala/collection/mutable/Builder
   #78 = Class              #77           // scala/collection/mutable/Builder
   #79 = Utf8               sizeHint
   #80 = Utf8               (I)V
   #81 = NameAndType        #79:#80       // sizeHint:(I)V
   #82 = InterfaceMethodref #78.#81       // scala/collection/mutable/Builder.sizeHint:(I)V
   #83 = Utf8               scala/collection/mutable/Growable
   #84 = Class              #83           // scala/collection/mutable/Growable
   #85 = Utf8               addAll
   #86 = Utf8               (Lscala/collection/IterableOnce;)Lscala/collection/mutable/Growable;
   #87 = NameAndType        #85:#86       // addAll:(Lscala/collection/IterableOnce;)Lscala/collection/mutable/Growable;
   #88 = InterfaceMethodref #84.#87       // scala/collection/mutable/Growable.addAll:(Lscala/collection/IterableOnce;)Lscala/collection/mutable/Growable;
   #89 = Utf8               result
   #90 = Utf8               ()Ljava/lang/Object;
   #91 = NameAndType        #89:#90       // result:()Ljava/lang/Object;
   #92 = InterfaceMethodref #78.#91       // scala/collection/mutable/Builder.result:()Ljava/lang/Object;
   #93 = Utf8               b
   #94 = Utf8               Lscala/collection/mutable/Builder;
   #95 = Utf8               this
   #96 = Utf8               Lscala/collection/Factory$ArrayFactory;
   #97 = Utf8               Lscala/collection/IterableOnce;
   #98 = Utf8               ()Lscala/collection/mutable/Builder<TA;Ljava/lang/Object;>;
   #99 = Utf8               scala/collection/mutable/ArrayBuilder$
  #100 = Class              #99           // scala/collection/mutable/ArrayBuilder$
  #101 = Utf8               Lscala/collection/mutable/ArrayBuilder$;
  #102 = NameAndType        #61:#101      // MODULE$:Lscala/collection/mutable/ArrayBuilder$;
  #103 = Fieldref           #100.#102     // scala/collection/mutable/ArrayBuilder$.MODULE$:Lscala/collection/mutable/ArrayBuilder$;
  #104 = NameAndType        #48:#49       // evidence$2:Lscala/reflect/ClassTag;
  #105 = Fieldref           #2.#104       // scala/collection/Factory$ArrayFactory.evidence$2:Lscala/reflect/ClassTag;
  #106 = Utf8               scala/reflect/ClassTag
  #107 = Class              #106          // scala/reflect/ClassTag
  #108 = Utf8               runtimeClass
  #109 = Utf8               ()Ljava/lang/Class;
  #110 = NameAndType        #108:#109     // runtimeClass:()Ljava/lang/Class;
  #111 = InterfaceMethodref #107.#110     // scala/reflect/ClassTag.runtimeClass:()Ljava/lang/Class;
  #112 = Utf8               java/lang/Byte
  #113 = Class              #112          // java/lang/Byte
  #114 = Utf8               TYPE
  #115 = Utf8               Ljava/lang/Class;
  #116 = NameAndType        #114:#115     // TYPE:Ljava/lang/Class;
  #117 = Fieldref           #113.#116     // java/lang/Byte.TYPE:Ljava/lang/Class;
  #118 = Utf8               equals
  #119 = Utf8               (Ljava/lang/Object;)Z
  #120 = NameAndType        #118:#119     // equals:(Ljava/lang/Object;)Z
  #121 = Methodref          #5.#120       // java/lang/Object.equals:(Ljava/lang/Object;)Z
  #122 = Utf8               <init>
  #123 = Utf8               ()V
  #124 = NameAndType        #122:#123     // "<init>":()V
  #125 = Methodref          #18.#124      // scala/collection/mutable/ArrayBuilder$ofByte."<init>":()V
  #126 = Utf8               java/lang/Short
  #127 = Class              #126          // java/lang/Short
  #128 = Fieldref           #127.#116     // java/lang/Short.TYPE:Ljava/lang/Class;
  #129 = Methodref          #39.#124      // scala/collection/mutable/ArrayBuilder$ofShort."<init>":()V
  #130 = Utf8               java/lang/Character
  #131 = Class              #130          // java/lang/Character
  #132 = Fieldref           #131.#116     // java/lang/Character.TYPE:Ljava/lang/Class;
  #133 = Methodref          #21.#124      // scala/collection/mutable/ArrayBuilder$ofChar."<init>":()V
  #134 = Utf8               java/lang/Integer
  #135 = Class              #134          // java/lang/Integer
  #136 = Fieldref           #135.#116     // java/lang/Integer.TYPE:Ljava/lang/Class;
  #137 = Methodref          #30.#124      // scala/collection/mutable/ArrayBuilder$ofInt."<init>":()V
  #138 = Utf8               java/lang/Long
  #139 = Class              #138          // java/lang/Long
  #140 = Fieldref           #139.#116     // java/lang/Long.TYPE:Ljava/lang/Class;
  #141 = Methodref          #33.#124      // scala/collection/mutable/ArrayBuilder$ofLong."<init>":()V
  #142 = Utf8               java/lang/Float
  #143 = Class              #142          // java/lang/Float
  #144 = Fieldref           #143.#116     // java/lang/Float.TYPE:Ljava/lang/Class;
  #145 = Methodref          #27.#124      // scala/collection/mutable/ArrayBuilder$ofFloat."<init>":()V
  #146 = Utf8               java/lang/Double
  #147 = Class              #146          // java/lang/Double
  #148 = Fieldref           #147.#116     // java/lang/Double.TYPE:Ljava/lang/Class;
  #149 = Methodref          #24.#124      // scala/collection/mutable/ArrayBuilder$ofDouble."<init>":()V
  #150 = Utf8               java/lang/Boolean
  #151 = Class              #150          // java/lang/Boolean
  #152 = Fieldref           #151.#116     // java/lang/Boolean.TYPE:Ljava/lang/Class;
  #153 = Methodref          #13.#124      // scala/collection/mutable/ArrayBuilder$ofBoolean."<init>":()V
  #154 = Utf8               java/lang/Void
  #155 = Class              #154          // java/lang/Void
  #156 = Fieldref           #155.#116     // java/lang/Void.TYPE:Ljava/lang/Class;
  #157 = Methodref          #42.#124      // scala/collection/mutable/ArrayBuilder$ofUnit."<init>":()V
  #158 = Utf8               (Lscala/reflect/ClassTag;)V
  #159 = NameAndType        #122:#158     // "<init>":(Lscala/reflect/ClassTag;)V
  #160 = Methodref          #36.#159      // scala/collection/mutable/ArrayBuilder$ofRef."<init>":(Lscala/reflect/ClassTag;)V
  #161 = Utf8               make_evidence$1
  #162 = Utf8               java/lang/Class
  #163 = Class              #162          // java/lang/Class
  #164 = Utf8               (Lscala/reflect/ClassTag<TA;>;)V
  #165 = Methodref          #5.#124       // java/lang/Object."<init>":()V
  #166 = Utf8               ConstantValue
  #167 = Utf8               Signature
  #168 = Utf8               Code
  #169 = Utf8               LineNumberTable
  #170 = Utf8               LocalVariableTable
  #171 = Utf8               MethodParameters
  #172 = Utf8               StackMapTable
  #173 = Utf8               InnerClasses
  #174 = Utf8               SourceFile
  #175 = Utf8               ScalaInlineInfo
  #176 = Utf8               Scala
{
  private static final long serialVersionUID;
    descriptor: J
    flags: (0x001a) ACC_PRIVATE, ACC_STATIC, ACC_FINAL
    ConstantValue: long 3l

  private final scala.reflect.ClassTag<A> evidence$2;
    descriptor: Lscala/reflect/ClassTag;
    flags: (0x0012) ACC_PRIVATE, ACC_FINAL
    Signature: #50                          // Lscala/reflect/ClassTag<TA;>;

  public java.lang.Object fromSpecific(scala.collection.IterableOnce<A>);
    descriptor: (Lscala/collection/IterableOnce;)Ljava/lang/Object;
    flags: (0x0001) ACC_PUBLIC
    Code:
      stack=3, locals=3, args_size=2
         0: aload_0
         1: invokevirtual #58                 // Method newBuilder:()Lscala/collection/mutable/Builder;
         4: astore_2
         5: aload_2
         6: getstatic     #64                 // Field scala/math/package$.MODULE$:Lscala/math/package$;
         9: pop
        10: iconst_0
        11: aload_1
        12: invokeinterface #70,  1           // InterfaceMethod scala/collection/IterableOnce.knownSize:()I
        17: invokestatic  #76                 // Method java/lang/Math.max:(II)I
        20: invokeinterface #82,  2           // InterfaceMethod scala/collection/mutable/Builder.sizeHint:(I)V
        25: aload_2
        26: aload_1
        27: invokeinterface #88,  2           // InterfaceMethod scala/collection/mutable/Growable.addAll:(Lscala/collection/IterableOnce;)Lscala/collection/mutable/Growable;
        32: pop
        33: aload_2
        34: invokeinterface #92,  1           // InterfaceMethod scala/collection/mutable/Builder.result:()Ljava/lang/Object;
        39: areturn
      LineNumberTable:
        line 63: 0
        line 64: 5
        line 65: 25
        line 66: 33
      LocalVariableTable:
        Start  Length  Slot  Name   Signature
            5      34     2     b   Lscala/collection/mutable/Builder;
            0      40     0  this   Lscala/collection/Factory$ArrayFactory;
            0      40     1    it   Lscala/collection/IterableOnce;
    Signature: #53                          // (Lscala/collection/IterableOnce<TA;>;)Ljava/lang/Object;
    MethodParameters:
      Name                           Flags
      it                             final

  public scala.collection.mutable.Builder<A, java.lang.Object> newBuilder();
    descriptor: ()Lscala/collection/mutable/Builder;
    flags: (0x0001) ACC_PUBLIC
    Code:
      stack=3, locals=4, args_size=1
         0: getstatic     #103                // Field scala/collection/mutable/ArrayBuilder$.MODULE$:Lscala/collection/mutable/ArrayBuilder$;
         3: pop
         4: aload_0
         5: getfield      #105                // Field evidence$2:Lscala/reflect/ClassTag;
         8: astore_1
         9: aload_1
        10: invokeinterface #111,  1          // InterfaceMethod scala/reflect/ClassTag.runtimeClass:()Ljava/lang/Class;
        15: astore_3
        16: getstatic     #117                // Field java/lang/Byte.TYPE:Ljava/lang/Class;
        19: dup
        20: ifnonnull     31
        23: pop
        24: aload_3
        25: ifnull        38
        28: goto          49
        31: aload_3
        32: invokevirtual #121                // Method java/lang/Object.equals:(Ljava/lang/Object;)Z
        35: ifeq          49
        38: new           #18                 // class scala/collection/mutable/ArrayBuilder$ofByte
        41: dup
        42: invokespecial #125                // Method scala/collection/mutable/ArrayBuilder$ofByte."<init>":()V
        45: astore_2
        46: goto          322
        49: getstatic     #128                // Field java/lang/Short.TYPE:Ljava/lang/Class;
        52: dup
        53: ifnonnull     64
        56: pop
        57: aload_3
        58: ifnull        71
        61: goto          82
        64: aload_3
        65: invokevirtual #121                // Method java/lang/Object.equals:(Ljava/lang/Object;)Z
        68: ifeq          82
        71: new           #39                 // class scala/collection/mutable/ArrayBuilder$ofShort
        74: dup
        75: invokespecial #129                // Method scala/collection/mutable/ArrayBuilder$ofShort."<init>":()V
        78: astore_2
        79: goto          322
        82: getstatic     #132                // Field java/lang/Character.TYPE:Ljava/lang/Class;
        85: dup
        86: ifnonnull     97
        89: pop
        90: aload_3
        91: ifnull        104
        94: goto          115
        97: aload_3
        98: invokevirtual #121                // Method java/lang/Object.equals:(Ljava/lang/Object;)Z
       101: ifeq          115
       104: new           #21                 // class scala/collection/mutable/ArrayBuilder$ofChar
       107: dup
       108: invokespecial #133                // Method scala/collection/mutable/ArrayBuilder$ofChar."<init>":()V
       111: astore_2
       112: goto          322
       115: getstatic     #136                // Field java/lang/Integer.TYPE:Ljava/lang/Class;
       118: dup
       119: ifnonnull     130
       122: pop
       123: aload_3
       124: ifnull        137
       127: goto          148
       130: aload_3
       131: invokevirtual #121                // Method java/lang/Object.equals:(Ljava/lang/Object;)Z
       134: ifeq          148
       137: new           #30                 // class scala/collection/mutable/ArrayBuilder$ofInt
       140: dup
       141: invokespecial #137                // Method scala/collection/mutable/ArrayBuilder$ofInt."<init>":()V
       144: astore_2
       145: goto          322
       148: getstatic     #140                // Field java/lang/Long.TYPE:Ljava/lang/Class;
       151: dup
       152: ifnonnull     163
       155: pop
       156: aload_3
       157: ifnull        170
       160: goto          181
       163: aload_3
       164: invokevirtual #121                // Method java/lang/Object.equals:(Ljava/lang/Object;)Z
       167: ifeq          181
       170: new           #33                 // class scala/collection/mutable/ArrayBuilder$ofLong
       173: dup
       174: invokespecial #141                // Method scala/collection/mutable/ArrayBuilder$ofLong."<init>":()V
       177: astore_2
       178: goto          322
       181: getstatic     #144                // Field java/lang/Float.TYPE:Ljava/lang/Class;
       184: dup
       185: ifnonnull     196
       188: pop
       189: aload_3
       190: ifnull        203
       193: goto          214
       196: aload_3
       197: invokevirtual #121                // Method java/lang/Object.equals:(Ljava/lang/Object;)Z
       200: ifeq          214
       203: new           #27                 // class scala/collection/mutable/ArrayBuilder$ofFloat
       206: dup
       207: invokespecial #145                // Method scala/collection/mutable/ArrayBuilder$ofFloat."<init>":()V
       210: astore_2
       211: goto          322
       214: getstatic     #148                // Field java/lang/Double.TYPE:Ljava/lang/Class;
       217: dup
       218: ifnonnull     229
       221: pop
       222: aload_3
       223: ifnull        236
       226: goto          247
       229: aload_3
       230: invokevirtual #121                // Method java/lang/Object.equals:(Ljava/lang/Object;)Z
       233: ifeq          247
       236: new           #24                 // class scala/collection/mutable/ArrayBuilder$ofDouble
       239: dup
       240: invokespecial #149                // Method scala/collection/mutable/ArrayBuilder$ofDouble."<init>":()V
       243: astore_2
       244: goto          322
       247: getstatic     #152                // Field java/lang/Boolean.TYPE:Ljava/lang/Class;
       250: dup
       251: ifnonnull     262
       254: pop
       255: aload_3
       256: ifnull        269
       259: goto          280
       262: aload_3
       263: invokevirtual #121                // Method java/lang/Object.equals:(Ljava/lang/Object;)Z
       266: ifeq          280
       269: new           #13                 // class scala/collection/mutable/ArrayBuilder$ofBoolean
       272: dup
       273: invokespecial #153                // Method scala/collection/mutable/ArrayBuilder$ofBoolean."<init>":()V
       276: astore_2
       277: goto          322
       280: getstatic     #156                // Field java/lang/Void.TYPE:Ljava/lang/Class;
       283: dup
       284: ifnonnull     295
       287: pop
       288: aload_3
       289: ifnull        302
       292: goto          313
       295: aload_3
       296: invokevirtual #121                // Method java/lang/Object.equals:(Ljava/lang/Object;)Z
       299: ifeq          313
       302: new           #42                 // class scala/collection/mutable/ArrayBuilder$ofUnit
       305: dup
       306: invokespecial #157                // Method scala/collection/mutable/ArrayBuilder$ofUnit."<init>":()V
       309: astore_2
       310: goto          322
       313: new           #36                 // class scala/collection/mutable/ArrayBuilder$ofRef
       316: dup
       317: aload_1
       318: invokespecial #160                // Method scala/collection/mutable/ArrayBuilder$ofRef."<init>":(Lscala/reflect/ClassTag;)V
       321: astore_2
       322: aload_2
       323: areturn
      StackMapTable: number_of_entries = 28
        frame_type = 255 /* full_frame */
          offset_delta = 31
          locals = [ class scala/collection/Factory$ArrayFactory, class scala/reflect/ClassTag, top, class java/lang/Class ]
          stack = [ class java/lang/Class ]
        frame_type = 6 /* same */
        frame_type = 10 /* same */
        frame_type = 78 /* same_locals_1_stack_item */
          stack = [ class java/lang/Class ]
        frame_type = 6 /* same */
        frame_type = 10 /* same */
        frame_type = 78 /* same_locals_1_stack_item */
          stack = [ class java/lang/Class ]
        frame_type = 6 /* same */
        frame_type = 10 /* same */
        frame_type = 78 /* same_locals_1_stack_item */
          stack = [ class java/lang/Class ]
        frame_type = 6 /* same */
        frame_type = 10 /* same */
        frame_type = 78 /* same_locals_1_stack_item */
          stack = [ class java/lang/Class ]
        frame_type = 6 /* same */
        frame_type = 10 /* same */
        frame_type = 78 /* same_locals_1_stack_item */
          stack = [ class java/lang/Class ]
        frame_type = 6 /* same */
        frame_type = 10 /* same */
        frame_type = 78 /* same_locals_1_stack_item */
          stack = [ class java/lang/Class ]
        frame_type = 6 /* same */
        frame_type = 10 /* same */
        frame_type = 78 /* same_locals_1_stack_item */
          stack = [ class java/lang/Class ]
        frame_type = 6 /* same */
        frame_type = 10 /* same */
        frame_type = 78 /* same_locals_1_stack_item */
          stack = [ class java/lang/Class ]
        frame_type = 6 /* same */
        frame_type = 10 /* same */
        frame_type = 255 /* full_frame */
          offset_delta = 8
          locals = [ class scala/collection/Factory$ArrayFactory, class scala/reflect/ClassTag, class scala/collection/mutable/ArrayBuilder, class java/lang/Class ]
          stack = []
      LineNumberTable:
        line 68: 0
      LocalVariableTable:
        Start  Length  Slot  Name   Signature
            0     324     0  this   Lscala/collection/Factory$ArrayFactory;
            9     313     1 make_evidence$1   Lscala/reflect/ClassTag;
    Signature: #98                          // ()Lscala/collection/mutable/Builder<TA;Ljava/lang/Object;>;

  public scala.collection.Factory$ArrayFactory(scala.reflect.ClassTag<A>);
    descriptor: (Lscala/reflect/ClassTag;)V
    flags: (0x0001) ACC_PUBLIC
    Code:
      stack=2, locals=2, args_size=2
         0: aload_0
         1: aload_1
         2: putfield      #105                // Field evidence$2:Lscala/reflect/ClassTag;
         5: aload_0
         6: invokespecial #165                // Method java/lang/Object."<init>":()V
         9: return
      LineNumberTable:
        line 61: 0
      LocalVariableTable:
        Start  Length  Slot  Name   Signature
            0      10     0  this   Lscala/collection/Factory$ArrayFactory;
            0      10     1 evidence$2   Lscala/reflect/ClassTag;
    Signature: #164                         // (Lscala/reflect/ClassTag<TA;>;)V
    MethodParameters:
      Name                           Flags
      evidence$2                     final
}
InnerClasses:
  private static #11= #2 of #7;           // ArrayFactory=class scala/collection/Factory$ArrayFactory of class scala/collection/Factory
  public static #16= #13 of #15;          // ofBoolean=class scala/collection/mutable/ArrayBuilder$ofBoolean of class scala/collection/mutable/ArrayBuilder
  public static final #19= #18 of #15;    // ofByte=class scala/collection/mutable/ArrayBuilder$ofByte of class scala/collection/mutable/ArrayBuilder
  public static final #22= #21 of #15;    // ofChar=class scala/collection/mutable/ArrayBuilder$ofChar of class scala/collection/mutable/ArrayBuilder
  public static final #25= #24 of #15;    // ofDouble=class scala/collection/mutable/ArrayBuilder$ofDouble of class scala/collection/mutable/ArrayBuilder
  public static final #28= #27 of #15;    // ofFloat=class scala/collection/mutable/ArrayBuilder$ofFloat of class scala/collection/mutable/ArrayBuilder
  public static final #31= #30 of #15;    // ofInt=class scala/collection/mutable/ArrayBuilder$ofInt of class scala/collection/mutable/ArrayBuilder
  public static final #34= #33 of #15;    // ofLong=class scala/collection/mutable/ArrayBuilder$ofLong of class scala/collection/mutable/ArrayBuilder
  public static final #37= #36 of #15;    // ofRef=class scala/collection/mutable/ArrayBuilder$ofRef of class scala/collection/mutable/ArrayBuilder
  public static final #40= #39 of #15;    // ofShort=class scala/collection/mutable/ArrayBuilder$ofShort of class scala/collection/mutable/ArrayBuilder
  public static final #43= #42 of #15;    // ofUnit=class scala/collection/mutable/ArrayBuilder$ofUnit of class scala/collection/mutable/ArrayBuilder
Signature: #3                           // <A:Ljava/lang/Object;>Ljava/lang/Object;Lscala/collection/Factory<TA;Ljava/lang/Object;>;Ljava/io/Serializable;
SourceFile: "Factory.scala"
  ScalaInlineInfo: length = 0x13 (unknown attribute)
   01 00 00 03 00 7A 00 9E 00 00 33 00 34 00 00 37
   00 38 00
  Scala: length = 0x0 (unknown attribute)

