Classfile /Users/mw/Projects/slang-braindump/.jar/jar11/assemble/slang-braindump/assemble/content/scala/collection/IndexedSeq.class
  Last modified May 29, 2022; size 8846 bytes
  SHA-256 checksum 5aefd5373b630f927cf178a941bc97adad6eb585ae510d04844f8f7da1f9b3fa
  Compiled from "IndexedSeq.scala"
public interface scala.collection.IndexedSeq<A extends java.lang.Object> extends scala.collection.Seq<A>, scala.collection.IndexedSeqOps<A, scala.collection.IndexedSeq, scala.collection.IndexedSeq<A>>
  minor version: 0
  major version: 52
  flags: (0x0601) ACC_PUBLIC, ACC_INTERFACE, ACC_ABSTRACT
  this_class: #2                          // scala/collection/IndexedSeq
  super_class: #5                         // java/lang/Object
  interfaces: 2, fields: 0, methods: 23, attributes: 7
Constant pool:
    #1 = Utf8               scala/collection/IndexedSeq
    #2 = Class              #1            // scala/collection/IndexedSeq
    #3 = Utf8               <A:Ljava/lang/Object;>Ljava/lang/Object;Lscala/collection/Seq<TA;>;Lscala/collection/IndexedSeqOps<TA;Lscala/collection/IndexedSeq;Lscala/collection/IndexedSeq<TA;>;>;
    #4 = Utf8               java/lang/Object
    #5 = Class              #4            // java/lang/Object
    #6 = Utf8               scala/collection/Seq
    #7 = Class              #6            // scala/collection/Seq
    #8 = Utf8               scala/collection/IndexedSeqOps
    #9 = Class              #8            // scala/collection/IndexedSeqOps
   #10 = Utf8               IndexedSeq.scala
   #11 = Utf8               Lscala/reflect/ScalaSignature;
   #12 = Utf8               bytes
   #13 = Utf8               \u0006\u0005}3q\u0001C\u0005\u0011\u0002\u0007\u0005a\u0002C\u0003,\u0001\u0011\u0005A\u0006\u0003\u00041\u0001\u0001&\t&\r\u0005\u0006{\u0001!\tEP\u0004\u0006\u0005&A\ta\u0011\u0004\u0006\u0011%A\t\u0001\u0012\u0005\u0006\u0019\u0016!\t!\u0014\u0005\b\u001d\u0016\t\t\u0011\"\u0003P\u0005)Ie\u000eZ3yK\u0012\u001cV-\u001d\u0006\u0003\u0015-\t!bY8mY\u0016\u001cG/[8o\u0015\u0005a\u0011!B:dC2\f7\u0001A\u000b\u0003\u001fi\u0019R\u0001\u0001\t\u0015G!\u0002\"!\u0005\n\u000e\u0003-I!aE\u0006\u0003\r\u0005s\u0017PU3g!\r)b\u0003G\u0007\u0002\u0013%\u0011q#\u0003\u0002\u0004\'\u0016\f\bCA\r\u001b\u0019\u0001!aa\u0007\u0001\u0005\u0006\u0004a\"!A!\u0012\u0005u\u0001\u0003CA\t\u001f\u0013\ty2BA\u0004O_RD\u0017N\\4\u0011\u0005E\t\u0013B\u0001\u0012\f\u0005\r\te.\u001f\t\u0006+\u0011BbeJ\u0005\u0003K%\u0011Q\"\u00138eKb,GmU3r\u001fB\u001c\bCA\u000b\u0001!\r)\u0002\u0001\u0007\t\u0005+%Bb%\u0003\u0002+\u0013\t9\u0012\n^3sC\ndWMR1di>\u0014\u0018\u0010R3gCVdGo]\u0001\u0007I%t\u0017\u000e\u001e\u0013\u0015\u00035\u0002\"!\u0005\u0018\n\u0005=Z!\u0001B+oSR\fAb\u001d;sS:<\u0007K]3gSb,\u0012A\r\t\u0003gir!\u0001\u000e\u001d\u0011\u0005UZQ\"\u0001\u001c\u000b\u0005]j\u0011A\u0002\u001fs_>$h(\u0003\u0002:\u0017\u00051\u0001K]3eK\u001aL!a\u000f\u001f\u0003\rM#(/\u001b8h\u0015\tI4\"A\bji\u0016\u0014\u0018M\u00197f\r\u0006\u001cGo\u001c:z+\u0005y\u0004cA\u000bAM%\u0011\u0011)\u0003\u0002\u000b\'\u0016\fh)Y2u_JL\u0018AC%oI\u0016DX\rZ*fcB\u0011Q#B\n\u0003\u000b\u0015\u00032AR%\'\u001d\t)r)\u0003\u0002I\u0013\u0005Q1+Z9GC\u000e$xN]=\n\u0005)[%\u0001\u0003#fY\u0016<\u0017\r^3\u000b\u0005!K\u0011A\u0002\u001fj]&$h\bF\u0001D\u000319(/\u001b;f%\u0016\u0004H.Y2f)\u0005\u0001\u0006CA)W\u001b\u0005\u0011&BA*U\u0003\u0011a\u0017M\\4\u000b\u0003U\u000bAA[1wC&\u0011qK\u0015\u0002\u0007\u001f\nTWm\u0019;)\t\u0015IF,\u0018\t\u0003#iK!aW\u0006\u0003!M+\'/[1m-\u0016\u00148/[8o+&#\u0015!\u0002<bYV,g$A\u0002)\t\u0011IF,\u0018
   #14 = Utf8               java/lang/invoke/MethodHandles$Lookup
   #15 = Class              #14           // java/lang/invoke/MethodHandles$Lookup
   #16 = Utf8               java/lang/invoke/MethodHandles
   #17 = Class              #16           // java/lang/invoke/MethodHandles
   #18 = Utf8               Lookup
   #19 = Utf8               scala/collection/View$Fill
   #20 = Class              #19           // scala/collection/View$Fill
   #21 = Utf8               scala/collection/View
   #22 = Class              #21           // scala/collection/View
   #23 = Utf8               Fill
   #24 = Utf8               scala/collection/View$Iterate
   #25 = Class              #24           // scala/collection/View$Iterate
   #26 = Utf8               Iterate
   #27 = Utf8               scala/collection/View$Tabulate
   #28 = Class              #27           // scala/collection/View$Tabulate
   #29 = Utf8               Tabulate
   #30 = Utf8               scala/collection/View$Unfold
   #31 = Class              #30           // scala/collection/View$Unfold
   #32 = Utf8               Unfold
   #33 = Utf8               newBuilder
   #34 = Utf8               ()Lscala/collection/mutable/Builder;
   #35 = Utf8               <A:Ljava/lang/Object;>()Lscala/collection/mutable/Builder<TA;Lscala/collection/IndexedSeq<TA;>;>;
   #36 = Utf8               scala/collection/IndexedSeq$
   #37 = Class              #36           // scala/collection/IndexedSeq$
   #38 = Utf8               MODULE$
   #39 = Utf8               Lscala/collection/IndexedSeq$;
   #40 = NameAndType        #38:#39       // MODULE$:Lscala/collection/IndexedSeq$;
   #41 = Fieldref           #37.#40       // scala/collection/IndexedSeq$.MODULE$:Lscala/collection/IndexedSeq$;
   #42 = NameAndType        #33:#34       // newBuilder:()Lscala/collection/mutable/Builder;
   #43 = Methodref          #37.#42       // scala/collection/IndexedSeq$.newBuilder:()Lscala/collection/mutable/Builder;
   #44 = Utf8               from
   #45 = Utf8               (Lscala/collection/IterableOnce;)Lscala/collection/SeqOps;
   #46 = Utf8               it
   #47 = NameAndType        #44:#45       // from:(Lscala/collection/IterableOnce;)Lscala/collection/SeqOps;
   #48 = Methodref          #37.#47       // scala/collection/IndexedSeq$.from:(Lscala/collection/IterableOnce;)Lscala/collection/SeqOps;
   #49 = Utf8               Lscala/collection/IterableOnce;
   #50 = Utf8               unapplySeq
   #51 = Utf8               (Lscala/collection/SeqOps;)Lscala/collection/SeqOps;
   #52 = Utf8               x
   #53 = Utf8               Lscala/collection/SeqOps;
   #54 = Utf8               tabulate
   #55 = Utf8               (IIIIILscala/Function5;)Ljava/lang/Object;
   #56 = Utf8               n1
   #57 = Utf8               n2
   #58 = Utf8               n3
   #59 = Utf8               n4
   #60 = Utf8               n5
   #61 = Utf8               f
   #62 = Utf8               (Ljava/lang/Object;)Ljava/lang/Object;
   #63 = MethodType         #62           //  (Ljava/lang/Object;)Ljava/lang/Object;
   #64 = Utf8               scala/collection/IterableFactory
   #65 = Class              #64           // scala/collection/IterableFactory
   #66 = Utf8               $anonfun$tabulate$7$adapted
   #67 = Utf8               (Lscala/collection/IterableFactory;IIIILscala/Function5;Ljava/lang/Object;)Ljava/lang/Object;
   #68 = NameAndType        #66:#67       // $anonfun$tabulate$7$adapted:(Lscala/collection/IterableFactory;IIIILscala/Function5;Ljava/lang/Object;)Ljava/lang/Object;
   #69 = InterfaceMethodref #65.#68       // scala/collection/IterableFactory.$anonfun$tabulate$7$adapted:(Lscala/collection/IterableFactory;IIIILscala/Function5;Ljava/lang/Object;)Ljava/lang/Object;
   #70 = MethodHandle       6:#69         // REF_invokeStatic scala/collection/IterableFactory.$anonfun$tabulate$7$adapted:(Lscala/collection/IterableFactory;IIIILscala/Function5;Ljava/lang/Object;)Ljava/lang/Object;
   #71 = Integer            1
   #72 = Utf8               java/lang/invoke/LambdaMetafactory
   #73 = Class              #72           // java/lang/invoke/LambdaMetafactory
   #74 = Utf8               altMetafactory
   #75 = Utf8               (Ljava/lang/invoke/MethodHandles$Lookup;Ljava/lang/String;Ljava/lang/invoke/MethodType;[Ljava/lang/Object;)Ljava/lang/invoke/CallSite;
   #76 = NameAndType        #74:#75       // altMetafactory:(Ljava/lang/invoke/MethodHandles$Lookup;Ljava/lang/String;Ljava/lang/invoke/MethodType;[Ljava/lang/Object;)Ljava/lang/invoke/CallSite;
   #77 = Methodref          #73.#76       // java/lang/invoke/LambdaMetafactory.altMetafactory:(Ljava/lang/invoke/MethodHandles$Lookup;Ljava/lang/String;Ljava/lang/invoke/MethodType;[Ljava/lang/Object;)Ljava/lang/invoke/CallSite;
   #78 = MethodHandle       6:#77         // REF_invokeStatic java/lang/invoke/LambdaMetafactory.altMetafactory:(Ljava/lang/invoke/MethodHandles$Lookup;Ljava/lang/String;Ljava/lang/invoke/MethodType;[Ljava/lang/Object;)Ljava/lang/invoke/CallSite;
   #79 = Utf8               apply
   #80 = Utf8               (Lscala/collection/IterableFactory;IIIILscala/Function5;)Lscala/Function1;
   #81 = NameAndType        #79:#80       // apply:(Lscala/collection/IterableFactory;IIIILscala/Function5;)Lscala/Function1;
   #82 = InvokeDynamic      #0:#81        // #0:apply:(Lscala/collection/IterableFactory;IIIILscala/Function5;)Lscala/Function1;
   #83 = Utf8               (ILscala/Function1;)Ljava/lang/Object;
   #84 = NameAndType        #54:#83       // tabulate:(ILscala/Function1;)Ljava/lang/Object;
   #85 = InterfaceMethodref #65.#84       // scala/collection/IterableFactory.tabulate:(ILscala/Function1;)Ljava/lang/Object;
   #86 = Utf8               I
   #87 = Utf8               Lscala/Function5;
   #88 = Utf8               tabulate_this
   #89 = Utf8               Lscala/collection/SeqFactory$Delegate;
   #90 = Utf8               (IIIILscala/Function4;)Ljava/lang/Object;
   #91 = Utf8               $anonfun$tabulate$5$adapted
   #92 = Utf8               (Lscala/collection/IterableFactory;IIILscala/Function4;Ljava/lang/Object;)Ljava/lang/Object;
   #93 = NameAndType        #91:#92       // $anonfun$tabulate$5$adapted:(Lscala/collection/IterableFactory;IIILscala/Function4;Ljava/lang/Object;)Ljava/lang/Object;
   #94 = InterfaceMethodref #65.#93       // scala/collection/IterableFactory.$anonfun$tabulate$5$adapted:(Lscala/collection/IterableFactory;IIILscala/Function4;Ljava/lang/Object;)Ljava/lang/Object;
   #95 = MethodHandle       6:#94         // REF_invokeStatic scala/collection/IterableFactory.$anonfun$tabulate$5$adapted:(Lscala/collection/IterableFactory;IIILscala/Function4;Ljava/lang/Object;)Ljava/lang/Object;
   #96 = Utf8               (Lscala/collection/IterableFactory;IIILscala/Function4;)Lscala/Function1;
   #97 = NameAndType        #79:#96       // apply:(Lscala/collection/IterableFactory;IIILscala/Function4;)Lscala/Function1;
   #98 = InvokeDynamic      #1:#97        // #1:apply:(Lscala/collection/IterableFactory;IIILscala/Function4;)Lscala/Function1;
   #99 = Utf8               Lscala/Function4;
  #100 = Utf8               (IIILscala/Function3;)Ljava/lang/Object;
  #101 = Utf8               $anonfun$tabulate$3$adapted
  #102 = Utf8               (Lscala/collection/IterableFactory;IILscala/Function3;Ljava/lang/Object;)Ljava/lang/Object;
  #103 = NameAndType        #101:#102     // $anonfun$tabulate$3$adapted:(Lscala/collection/IterableFactory;IILscala/Function3;Ljava/lang/Object;)Ljava/lang/Object;
  #104 = InterfaceMethodref #65.#103      // scala/collection/IterableFactory.$anonfun$tabulate$3$adapted:(Lscala/collection/IterableFactory;IILscala/Function3;Ljava/lang/Object;)Ljava/lang/Object;
  #105 = MethodHandle       6:#104        // REF_invokeStatic scala/collection/IterableFactory.$anonfun$tabulate$3$adapted:(Lscala/collection/IterableFactory;IILscala/Function3;Ljava/lang/Object;)Ljava/lang/Object;
  #106 = Utf8               (Lscala/collection/IterableFactory;IILscala/Function3;)Lscala/Function1;
  #107 = NameAndType        #79:#106      // apply:(Lscala/collection/IterableFactory;IILscala/Function3;)Lscala/Function1;
  #108 = InvokeDynamic      #2:#107       // #2:apply:(Lscala/collection/IterableFactory;IILscala/Function3;)Lscala/Function1;
  #109 = Utf8               Lscala/Function3;
  #110 = Utf8               (IILscala/Function2;)Ljava/lang/Object;
  #111 = Utf8               $anonfun$tabulate$1$adapted
  #112 = Utf8               (Lscala/collection/IterableFactory;ILscala/Function2;Ljava/lang/Object;)Ljava/lang/Object;
  #113 = NameAndType        #111:#112     // $anonfun$tabulate$1$adapted:(Lscala/collection/IterableFactory;ILscala/Function2;Ljava/lang/Object;)Ljava/lang/Object;
  #114 = InterfaceMethodref #65.#113      // scala/collection/IterableFactory.$anonfun$tabulate$1$adapted:(Lscala/collection/IterableFactory;ILscala/Function2;Ljava/lang/Object;)Ljava/lang/Object;
  #115 = MethodHandle       6:#114        // REF_invokeStatic scala/collection/IterableFactory.$anonfun$tabulate$1$adapted:(Lscala/collection/IterableFactory;ILscala/Function2;Ljava/lang/Object;)Ljava/lang/Object;
  #116 = Utf8               (Lscala/collection/IterableFactory;ILscala/Function2;)Lscala/Function1;
  #117 = NameAndType        #79:#116      // apply:(Lscala/collection/IterableFactory;ILscala/Function2;)Lscala/Function1;
  #118 = InvokeDynamic      #3:#117       // #3:apply:(Lscala/collection/IterableFactory;ILscala/Function2;)Lscala/Function1;
  #119 = Utf8               Lscala/Function2;
  #120 = Utf8               n
  #121 = Utf8               <init>
  #122 = Utf8               (ILscala/Function1;)V
  #123 = NameAndType        #121:#122     // "<init>":(ILscala/Function1;)V
  #124 = Methodref          #28.#123      // scala/collection/View$Tabulate."<init>":(ILscala/Function1;)V
  #125 = Utf8               (Lscala/collection/IterableOnce;)Ljava/lang/Object;
  #126 = NameAndType        #44:#125      // from:(Lscala/collection/IterableOnce;)Ljava/lang/Object;
  #127 = InterfaceMethodref #65.#126      // scala/collection/IterableFactory.from:(Lscala/collection/IterableOnce;)Ljava/lang/Object;
  #128 = Utf8               Lscala/Function1;
  #129 = Utf8               fill
  #130 = Utf8               (IIIIILscala/Function0;)Ljava/lang/Object;
  #131 = Utf8               elem
  #132 = Utf8               ()Ljava/lang/Object;
  #133 = MethodType         #132          //  ()Ljava/lang/Object;
  #134 = Utf8               $anonfun$fill$4
  #135 = Utf8               (Lscala/collection/IterableFactory;IIIILscala/Function0;)Ljava/lang/Object;
  #136 = NameAndType        #134:#135     // $anonfun$fill$4:(Lscala/collection/IterableFactory;IIIILscala/Function0;)Ljava/lang/Object;
  #137 = InterfaceMethodref #65.#136      // scala/collection/IterableFactory.$anonfun$fill$4:(Lscala/collection/IterableFactory;IIIILscala/Function0;)Ljava/lang/Object;
  #138 = MethodHandle       6:#137        // REF_invokeStatic scala/collection/IterableFactory.$anonfun$fill$4:(Lscala/collection/IterableFactory;IIIILscala/Function0;)Ljava/lang/Object;
  #139 = Utf8               (Lscala/collection/IterableFactory;IIIILscala/Function0;)Lscala/Function0;
  #140 = NameAndType        #79:#139      // apply:(Lscala/collection/IterableFactory;IIIILscala/Function0;)Lscala/Function0;
  #141 = InvokeDynamic      #4:#140       // #4:apply:(Lscala/collection/IterableFactory;IIIILscala/Function0;)Lscala/Function0;
  #142 = Utf8               (ILscala/Function0;)Ljava/lang/Object;
  #143 = NameAndType        #129:#142     // fill:(ILscala/Function0;)Ljava/lang/Object;
  #144 = InterfaceMethodref #65.#143      // scala/collection/IterableFactory.fill:(ILscala/Function0;)Ljava/lang/Object;
  #145 = Utf8               Lscala/Function0;
  #146 = Utf8               fill_this
  #147 = Utf8               (IIIILscala/Function0;)Ljava/lang/Object;
  #148 = Utf8               $anonfun$fill$3
  #149 = Utf8               (Lscala/collection/IterableFactory;IIILscala/Function0;)Ljava/lang/Object;
  #150 = NameAndType        #148:#149     // $anonfun$fill$3:(Lscala/collection/IterableFactory;IIILscala/Function0;)Ljava/lang/Object;
  #151 = InterfaceMethodref #65.#150      // scala/collection/IterableFactory.$anonfun$fill$3:(Lscala/collection/IterableFactory;IIILscala/Function0;)Ljava/lang/Object;
  #152 = MethodHandle       6:#151        // REF_invokeStatic scala/collection/IterableFactory.$anonfun$fill$3:(Lscala/collection/IterableFactory;IIILscala/Function0;)Ljava/lang/Object;
  #153 = Utf8               (Lscala/collection/IterableFactory;IIILscala/Function0;)Lscala/Function0;
  #154 = NameAndType        #79:#153      // apply:(Lscala/collection/IterableFactory;IIILscala/Function0;)Lscala/Function0;
  #155 = InvokeDynamic      #5:#154       // #5:apply:(Lscala/collection/IterableFactory;IIILscala/Function0;)Lscala/Function0;
  #156 = Utf8               (IIILscala/Function0;)Ljava/lang/Object;
  #157 = Utf8               $anonfun$fill$2
  #158 = Utf8               (Lscala/collection/IterableFactory;IILscala/Function0;)Ljava/lang/Object;
  #159 = NameAndType        #157:#158     // $anonfun$fill$2:(Lscala/collection/IterableFactory;IILscala/Function0;)Ljava/lang/Object;
  #160 = InterfaceMethodref #65.#159      // scala/collection/IterableFactory.$anonfun$fill$2:(Lscala/collection/IterableFactory;IILscala/Function0;)Ljava/lang/Object;
  #161 = MethodHandle       6:#160        // REF_invokeStatic scala/collection/IterableFactory.$anonfun$fill$2:(Lscala/collection/IterableFactory;IILscala/Function0;)Ljava/lang/Object;
  #162 = Utf8               (Lscala/collection/IterableFactory;IILscala/Function0;)Lscala/Function0;
  #163 = NameAndType        #79:#162      // apply:(Lscala/collection/IterableFactory;IILscala/Function0;)Lscala/Function0;
  #164 = InvokeDynamic      #6:#163       // #6:apply:(Lscala/collection/IterableFactory;IILscala/Function0;)Lscala/Function0;
  #165 = Utf8               (IILscala/Function0;)Ljava/lang/Object;
  #166 = Utf8               $anonfun$fill$1
  #167 = Utf8               (Lscala/collection/IterableFactory;ILscala/Function0;)Ljava/lang/Object;
  #168 = NameAndType        #166:#167     // $anonfun$fill$1:(Lscala/collection/IterableFactory;ILscala/Function0;)Ljava/lang/Object;
  #169 = InterfaceMethodref #65.#168      // scala/collection/IterableFactory.$anonfun$fill$1:(Lscala/collection/IterableFactory;ILscala/Function0;)Ljava/lang/Object;
  #170 = MethodHandle       6:#169        // REF_invokeStatic scala/collection/IterableFactory.$anonfun$fill$1:(Lscala/collection/IterableFactory;ILscala/Function0;)Ljava/lang/Object;
  #171 = Utf8               (Lscala/collection/IterableFactory;ILscala/Function0;)Lscala/Function0;
  #172 = NameAndType        #79:#171      // apply:(Lscala/collection/IterableFactory;ILscala/Function0;)Lscala/Function0;
  #173 = InvokeDynamic      #7:#172       // #7:apply:(Lscala/collection/IterableFactory;ILscala/Function0;)Lscala/Function0;
  #174 = Utf8               (ILscala/Function0;)V
  #175 = NameAndType        #121:#174     // "<init>":(ILscala/Function0;)V
  #176 = Methodref          #20.#175      // scala/collection/View$Fill."<init>":(ILscala/Function0;)V
  #177 = Utf8               range
  #178 = Utf8               (Ljava/lang/Object;Ljava/lang/Object;Ljava/lang/Object;Lscala/math/Integral;)Ljava/lang/Object;
  #179 = Utf8               start
  #180 = Utf8               end
  #181 = Utf8               step
  #182 = Utf8               evidence$4
  #183 = Utf8               range$
  #184 = Utf8               (Lscala/collection/IterableFactory;Ljava/lang/Object;Ljava/lang/Object;Ljava/lang/Object;Lscala/math/Integral;)Ljava/lang/Object;
  #185 = NameAndType        #183:#184     // range$:(Lscala/collection/IterableFactory;Ljava/lang/Object;Ljava/lang/Object;Ljava/lang/Object;Lscala/math/Integral;)Ljava/lang/Object;
  #186 = InterfaceMethodref #65.#185      // scala/collection/IterableFactory.range$:(Lscala/collection/IterableFactory;Ljava/lang/Object;Ljava/lang/Object;Ljava/lang/Object;Lscala/math/Integral;)Ljava/lang/Object;
  #187 = Utf8               Ljava/lang/Object;
  #188 = Utf8               Lscala/math/Integral;
  #189 = Utf8               (Ljava/lang/Object;Ljava/lang/Object;Lscala/math/Integral;)Ljava/lang/Object;
  #190 = Utf8               evidence$3
  #191 = Utf8               (Lscala/collection/IterableFactory;Ljava/lang/Object;Ljava/lang/Object;Lscala/math/Integral;)Ljava/lang/Object;
  #192 = NameAndType        #183:#191     // range$:(Lscala/collection/IterableFactory;Ljava/lang/Object;Ljava/lang/Object;Lscala/math/Integral;)Ljava/lang/Object;
  #193 = InterfaceMethodref #65.#192      // scala/collection/IterableFactory.range$:(Lscala/collection/IterableFactory;Ljava/lang/Object;Ljava/lang/Object;Lscala/math/Integral;)Ljava/lang/Object;
  #194 = Utf8               unfold
  #195 = Utf8               (Ljava/lang/Object;Lscala/Function1;)Ljava/lang/Object;
  #196 = Utf8               init
  #197 = Utf8               (Ljava/lang/Object;Lscala/Function1;)V
  #198 = NameAndType        #121:#197     // "<init>":(Ljava/lang/Object;Lscala/Function1;)V
  #199 = Methodref          #31.#198      // scala/collection/View$Unfold."<init>":(Ljava/lang/Object;Lscala/Function1;)V
  #200 = Utf8               iterate
  #201 = Utf8               (Ljava/lang/Object;ILscala/Function1;)Ljava/lang/Object;
  #202 = Utf8               len
  #203 = Utf8               (Ljava/lang/Object;ILscala/Function1;)V
  #204 = NameAndType        #121:#203     // "<init>":(Ljava/lang/Object;ILscala/Function1;)V
  #205 = Methodref          #25.#204      // scala/collection/View$Iterate."<init>":(Ljava/lang/Object;ILscala/Function1;)V
  #206 = Utf8               stringPrefix$
  #207 = Utf8               (Lscala/collection/IndexedSeq;)Ljava/lang/String;
  #208 = Utf8               $this
  #209 = Utf8               stringPrefix
  #210 = Utf8               ()Ljava/lang/String;
  #211 = NameAndType        #209:#210     // stringPrefix:()Ljava/lang/String;
  #212 = InterfaceMethodref #2.#211       // scala/collection/IndexedSeq.stringPrefix:()Ljava/lang/String;
  #213 = Utf8               Lscala/collection/IndexedSeq;
  #214 = Utf8               IndexedSeq
  #215 = String             #214          // IndexedSeq
  #216 = Utf8               this
  #217 = Utf8               iterableFactory$
  #218 = Utf8               (Lscala/collection/IndexedSeq;)Lscala/collection/SeqFactory;
  #219 = Utf8               iterableFactory
  #220 = Utf8               ()Lscala/collection/SeqFactory;
  #221 = NameAndType        #219:#220     // iterableFactory:()Lscala/collection/SeqFactory;
  #222 = InterfaceMethodref #2.#221       // scala/collection/IndexedSeq.iterableFactory:()Lscala/collection/SeqFactory;
  #223 = Utf8               ()Lscala/collection/SeqFactory<Lscala/collection/IndexedSeq;>;
  #224 = Utf8               $init$
  #225 = Utf8               (Lscala/collection/IndexedSeq;)V
  #226 = Utf8               $deserializeLambda$
  #227 = Utf8               (Ljava/lang/invoke/SerializedLambda;)Ljava/lang/Object;
  #228 = Utf8               scala/runtime/LambdaDeserialize
  #229 = Class              #228          // scala/runtime/LambdaDeserialize
  #230 = Utf8               bootstrap
  #231 = Utf8               (Ljava/lang/invoke/MethodHandles$Lookup;Ljava/lang/String;Ljava/lang/invoke/MethodType;[Ljava/lang/invoke/MethodHandle;)Ljava/lang/invoke/CallSite;
  #232 = NameAndType        #230:#231     // bootstrap:(Ljava/lang/invoke/MethodHandles$Lookup;Ljava/lang/String;Ljava/lang/invoke/MethodType;[Ljava/lang/invoke/MethodHandle;)Ljava/lang/invoke/CallSite;
  #233 = Methodref          #229.#232     // scala/runtime/LambdaDeserialize.bootstrap:(Ljava/lang/invoke/MethodHandles$Lookup;Ljava/lang/String;Ljava/lang/invoke/MethodType;[Ljava/lang/invoke/MethodHandle;)Ljava/lang/invoke/CallSite;
  #234 = MethodHandle       6:#233        // REF_invokeStatic scala/runtime/LambdaDeserialize.bootstrap:(Ljava/lang/invoke/MethodHandles$Lookup;Ljava/lang/String;Ljava/lang/invoke/MethodType;[Ljava/lang/invoke/MethodHandle;)Ljava/lang/invoke/CallSite;
  #235 = Utf8               lambdaDeserialize
  #236 = NameAndType        #235:#227     // lambdaDeserialize:(Ljava/lang/invoke/SerializedLambda;)Ljava/lang/Object;
  #237 = InvokeDynamic      #8:#236       // #8:lambdaDeserialize:(Ljava/lang/invoke/SerializedLambda;)Ljava/lang/Object;
  #238 = Utf8               Code
  #239 = Utf8               Signature
  #240 = Utf8               LocalVariableTable
  #241 = Utf8               MethodParameters
  #242 = Utf8               LineNumberTable
  #243 = Utf8               InnerClasses
  #244 = Utf8               SourceFile
  #245 = Utf8               RuntimeVisibleAnnotations
  #246 = Utf8               BootstrapMethods
  #247 = Utf8               ScalaInlineInfo
  #248 = Utf8               ScalaSig
{
  public static <A extends java.lang.Object> scala.collection.mutable.Builder<A, scala.collection.IndexedSeq<A>> newBuilder();
    descriptor: ()Lscala/collection/mutable/Builder;
    flags: (0x0009) ACC_PUBLIC, ACC_STATIC
    Code:
      stack=1, locals=0, args_size=0
         0: getstatic     #41                 // Field scala/collection/IndexedSeq$.MODULE$:Lscala/collection/IndexedSeq$;
         3: invokevirtual #43                 // Method scala/collection/IndexedSeq$.newBuilder:()Lscala/collection/mutable/Builder;
         6: areturn
    Signature: #35                          // <A:Ljava/lang/Object;>()Lscala/collection/mutable/Builder<TA;Lscala/collection/IndexedSeq<TA;>;>;

  public static scala.collection.SeqOps from(scala.collection.IterableOnce);
    descriptor: (Lscala/collection/IterableOnce;)Lscala/collection/SeqOps;
    flags: (0x0009) ACC_PUBLIC, ACC_STATIC
    Code:
      stack=2, locals=1, args_size=1
         0: getstatic     #41                 // Field scala/collection/IndexedSeq$.MODULE$:Lscala/collection/IndexedSeq$;
         3: aload_0
         4: invokevirtual #48                 // Method scala/collection/IndexedSeq$.from:(Lscala/collection/IterableOnce;)Lscala/collection/SeqOps;
         7: areturn
      LocalVariableTable:
        Start  Length  Slot  Name   Signature
            0       8     0    it   Lscala/collection/IterableOnce;
    MethodParameters:
      Name                           Flags
      it                             final

  public static scala.collection.SeqOps unapplySeq(scala.collection.SeqOps);
    descriptor: (Lscala/collection/SeqOps;)Lscala/collection/SeqOps;
    flags: (0x0009) ACC_PUBLIC, ACC_STATIC
    Code:
      stack=1, locals=1, args_size=1
         0: getstatic     #41                 // Field scala/collection/IndexedSeq$.MODULE$:Lscala/collection/IndexedSeq$;
         3: pop
         4: aload_0
         5: areturn
      LocalVariableTable:
        Start  Length  Slot  Name   Signature
            0       6     0     x   Lscala/collection/SeqOps;
    MethodParameters:
      Name                           Flags
      x                              final

  public static java.lang.Object tabulate(int, int, int, int, int, scala.Function5);
    descriptor: (IIIIILscala/Function5;)Ljava/lang/Object;
    flags: (0x0009) ACC_PUBLIC, ACC_STATIC
    Code:
      stack=8, locals=7, args_size=6
         0: getstatic     #41                 // Field scala/collection/IndexedSeq$.MODULE$:Lscala/collection/IndexedSeq$;
         3: astore        6
         5: aload         6
         7: iload_0
         8: aload         6
        10: iload_1
        11: iload_2
        12: iload_3
        13: iload         4
        15: aload         5
        17: invokedynamic #82,  0             // InvokeDynamic #0:apply:(Lscala/collection/IterableFactory;IIIILscala/Function5;)Lscala/Function1;
        22: invokeinterface #85,  3           // InterfaceMethod scala/collection/IterableFactory.tabulate:(ILscala/Function1;)Ljava/lang/Object;
        27: areturn
      LocalVariableTable:
        Start  Length  Slot  Name   Signature
            0      28     0    n1   I
            0      28     1    n2   I
            0      28     2    n3   I
            0      28     3    n4   I
            0      28     4    n5   I
            0      28     5     f   Lscala/Function5;
            5      22     6 tabulate_this   Lscala/collection/SeqFactory$Delegate;
    MethodParameters:
      Name                           Flags
      n1                             final
      n2                             final
      n3                             final
      n4                             final
      n5                             final
      f                              final

  public static java.lang.Object tabulate(int, int, int, int, scala.Function4);
    descriptor: (IIIILscala/Function4;)Ljava/lang/Object;
    flags: (0x0009) ACC_PUBLIC, ACC_STATIC
    Code:
      stack=7, locals=6, args_size=5
         0: getstatic     #41                 // Field scala/collection/IndexedSeq$.MODULE$:Lscala/collection/IndexedSeq$;
         3: astore        5
         5: aload         5
         7: iload_0
         8: aload         5
        10: iload_1
        11: iload_2
        12: iload_3
        13: aload         4
        15: invokedynamic #98,  0             // InvokeDynamic #1:apply:(Lscala/collection/IterableFactory;IIILscala/Function4;)Lscala/Function1;
        20: invokeinterface #85,  3           // InterfaceMethod scala/collection/IterableFactory.tabulate:(ILscala/Function1;)Ljava/lang/Object;
        25: areturn
      LocalVariableTable:
        Start  Length  Slot  Name   Signature
            0      26     0    n1   I
            0      26     1    n2   I
            0      26     2    n3   I
            0      26     3    n4   I
            0      26     4     f   Lscala/Function4;
            5      20     5 tabulate_this   Lscala/collection/SeqFactory$Delegate;
    MethodParameters:
      Name                           Flags
      n1                             final
      n2                             final
      n3                             final
      n4                             final
      f                              final

  public static java.lang.Object tabulate(int, int, int, scala.Function3);
    descriptor: (IIILscala/Function3;)Ljava/lang/Object;
    flags: (0x0009) ACC_PUBLIC, ACC_STATIC
    Code:
      stack=6, locals=5, args_size=4
         0: getstatic     #41                 // Field scala/collection/IndexedSeq$.MODULE$:Lscala/collection/IndexedSeq$;
         3: astore        4
         5: aload         4
         7: iload_0
         8: aload         4
        10: iload_1
        11: iload_2
        12: aload_3
        13: invokedynamic #108,  0            // InvokeDynamic #2:apply:(Lscala/collection/IterableFactory;IILscala/Function3;)Lscala/Function1;
        18: invokeinterface #85,  3           // InterfaceMethod scala/collection/IterableFactory.tabulate:(ILscala/Function1;)Ljava/lang/Object;
        23: areturn
      LocalVariableTable:
        Start  Length  Slot  Name   Signature
            0      24     0    n1   I
            0      24     1    n2   I
            0      24     2    n3   I
            0      24     3     f   Lscala/Function3;
            5      18     4 tabulate_this   Lscala/collection/SeqFactory$Delegate;
    MethodParameters:
      Name                           Flags
      n1                             final
      n2                             final
      n3                             final
      f                              final

  public static java.lang.Object tabulate(int, int, scala.Function2);
    descriptor: (IILscala/Function2;)Ljava/lang/Object;
    flags: (0x0009) ACC_PUBLIC, ACC_STATIC
    Code:
      stack=5, locals=4, args_size=3
         0: getstatic     #41                 // Field scala/collection/IndexedSeq$.MODULE$:Lscala/collection/IndexedSeq$;
         3: astore_3
         4: aload_3
         5: iload_0
         6: aload_3
         7: iload_1
         8: aload_2
         9: invokedynamic #118,  0            // InvokeDynamic #3:apply:(Lscala/collection/IterableFactory;ILscala/Function2;)Lscala/Function1;
        14: invokeinterface #85,  3           // InterfaceMethod scala/collection/IterableFactory.tabulate:(ILscala/Function1;)Ljava/lang/Object;
        19: areturn
      LocalVariableTable:
        Start  Length  Slot  Name   Signature
            0      20     0    n1   I
            0      20     1    n2   I
            0      20     2     f   Lscala/Function2;
            4      15     3 tabulate_this   Lscala/collection/SeqFactory$Delegate;
    MethodParameters:
      Name                           Flags
      n1                             final
      n2                             final
      f                              final

  public static java.lang.Object tabulate(int, scala.Function1);
    descriptor: (ILscala/Function1;)Ljava/lang/Object;
    flags: (0x0009) ACC_PUBLIC, ACC_STATIC
    Code:
      stack=5, locals=2, args_size=2
         0: getstatic     #41                 // Field scala/collection/IndexedSeq$.MODULE$:Lscala/collection/IndexedSeq$;
         3: new           #28                 // class scala/collection/View$Tabulate
         6: dup
         7: iload_0
         8: aload_1
         9: invokespecial #124                // Method scala/collection/View$Tabulate."<init>":(ILscala/Function1;)V
        12: invokeinterface #127,  2          // InterfaceMethod scala/collection/IterableFactory.from:(Lscala/collection/IterableOnce;)Ljava/lang/Object;
        17: areturn
      LocalVariableTable:
        Start  Length  Slot  Name   Signature
            0      18     0     n   I
            0      18     1     f   Lscala/Function1;
    MethodParameters:
      Name                           Flags
      n                              final
      f                              final

  public static java.lang.Object fill(int, int, int, int, int, scala.Function0);
    descriptor: (IIIIILscala/Function0;)Ljava/lang/Object;
    flags: (0x0009) ACC_PUBLIC, ACC_STATIC
    Code:
      stack=8, locals=7, args_size=6
         0: getstatic     #41                 // Field scala/collection/IndexedSeq$.MODULE$:Lscala/collection/IndexedSeq$;
         3: astore        6
         5: aload         6
         7: iload_0
         8: aload         6
        10: iload_1
        11: iload_2
        12: iload_3
        13: iload         4
        15: aload         5
        17: invokedynamic #141,  0            // InvokeDynamic #4:apply:(Lscala/collection/IterableFactory;IIIILscala/Function0;)Lscala/Function0;
        22: invokeinterface #144,  3          // InterfaceMethod scala/collection/IterableFactory.fill:(ILscala/Function0;)Ljava/lang/Object;
        27: areturn
      LocalVariableTable:
        Start  Length  Slot  Name   Signature
            0      28     0    n1   I
            0      28     1    n2   I
            0      28     2    n3   I
            0      28     3    n4   I
            0      28     4    n5   I
            0      28     5  elem   Lscala/Function0;
            5      22     6 fill_this   Lscala/collection/SeqFactory$Delegate;
    MethodParameters:
      Name                           Flags
      n1                             final
      n2                             final
      n3                             final
      n4                             final
      n5                             final
      elem                           final

  public static java.lang.Object fill(int, int, int, int, scala.Function0);
    descriptor: (IIIILscala/Function0;)Ljava/lang/Object;
    flags: (0x0009) ACC_PUBLIC, ACC_STATIC
    Code:
      stack=7, locals=6, args_size=5
         0: getstatic     #41                 // Field scala/collection/IndexedSeq$.MODULE$:Lscala/collection/IndexedSeq$;
         3: astore        5
         5: aload         5
         7: iload_0
         8: aload         5
        10: iload_1
        11: iload_2
        12: iload_3
        13: aload         4
        15: invokedynamic #155,  0            // InvokeDynamic #5:apply:(Lscala/collection/IterableFactory;IIILscala/Function0;)Lscala/Function0;
        20: invokeinterface #144,  3          // InterfaceMethod scala/collection/IterableFactory.fill:(ILscala/Function0;)Ljava/lang/Object;
        25: areturn
      LocalVariableTable:
        Start  Length  Slot  Name   Signature
            0      26     0    n1   I
            0      26     1    n2   I
            0      26     2    n3   I
            0      26     3    n4   I
            0      26     4  elem   Lscala/Function0;
            5      20     5 fill_this   Lscala/collection/SeqFactory$Delegate;
    MethodParameters:
      Name                           Flags
      n1                             final
      n2                             final
      n3                             final
      n4                             final
      elem                           final

  public static java.lang.Object fill(int, int, int, scala.Function0);
    descriptor: (IIILscala/Function0;)Ljava/lang/Object;
    flags: (0x0009) ACC_PUBLIC, ACC_STATIC
    Code:
      stack=6, locals=5, args_size=4
         0: getstatic     #41                 // Field scala/collection/IndexedSeq$.MODULE$:Lscala/collection/IndexedSeq$;
         3: astore        4
         5: aload         4
         7: iload_0
         8: aload         4
        10: iload_1
        11: iload_2
        12: aload_3
        13: invokedynamic #164,  0            // InvokeDynamic #6:apply:(Lscala/collection/IterableFactory;IILscala/Function0;)Lscala/Function0;
        18: invokeinterface #144,  3          // InterfaceMethod scala/collection/IterableFactory.fill:(ILscala/Function0;)Ljava/lang/Object;
        23: areturn
      LocalVariableTable:
        Start  Length  Slot  Name   Signature
            0      24     0    n1   I
            0      24     1    n2   I
            0      24     2    n3   I
            0      24     3  elem   Lscala/Function0;
            5      18     4 fill_this   Lscala/collection/SeqFactory$Delegate;
    MethodParameters:
      Name                           Flags
      n1                             final
      n2                             final
      n3                             final
      elem                           final

  public static java.lang.Object fill(int, int, scala.Function0);
    descriptor: (IILscala/Function0;)Ljava/lang/Object;
    flags: (0x0009) ACC_PUBLIC, ACC_STATIC
    Code:
      stack=5, locals=4, args_size=3
         0: getstatic     #41                 // Field scala/collection/IndexedSeq$.MODULE$:Lscala/collection/IndexedSeq$;
         3: astore_3
         4: aload_3
         5: iload_0
         6: aload_3
         7: iload_1
         8: aload_2
         9: invokedynamic #173,  0            // InvokeDynamic #7:apply:(Lscala/collection/IterableFactory;ILscala/Function0;)Lscala/Function0;
        14: invokeinterface #144,  3          // InterfaceMethod scala/collection/IterableFactory.fill:(ILscala/Function0;)Ljava/lang/Object;
        19: areturn
      LocalVariableTable:
        Start  Length  Slot  Name   Signature
            0      20     0    n1   I
            0      20     1    n2   I
            0      20     2  elem   Lscala/Function0;
            4      15     3 fill_this   Lscala/collection/SeqFactory$Delegate;
    MethodParameters:
      Name                           Flags
      n1                             final
      n2                             final
      elem                           final

  public static java.lang.Object fill(int, scala.Function0);
    descriptor: (ILscala/Function0;)Ljava/lang/Object;
    flags: (0x0009) ACC_PUBLIC, ACC_STATIC
    Code:
      stack=5, locals=2, args_size=2
         0: getstatic     #41                 // Field scala/collection/IndexedSeq$.MODULE$:Lscala/collection/IndexedSeq$;
         3: new           #20                 // class scala/collection/View$Fill
         6: dup
         7: iload_0
         8: aload_1
         9: invokespecial #176                // Method scala/collection/View$Fill."<init>":(ILscala/Function0;)V
        12: invokeinterface #127,  2          // InterfaceMethod scala/collection/IterableFactory.from:(Lscala/collection/IterableOnce;)Ljava/lang/Object;
        17: areturn
      LocalVariableTable:
        Start  Length  Slot  Name   Signature
            0      18     0     n   I
            0      18     1  elem   Lscala/Function0;
    MethodParameters:
      Name                           Flags
      n                              final
      elem                           final

  public static java.lang.Object range(java.lang.Object, java.lang.Object, java.lang.Object, scala.math.Integral);
    descriptor: (Ljava/lang/Object;Ljava/lang/Object;Ljava/lang/Object;Lscala/math/Integral;)Ljava/lang/Object;
    flags: (0x0009) ACC_PUBLIC, ACC_STATIC
    Code:
      stack=5, locals=4, args_size=4
         0: getstatic     #41                 // Field scala/collection/IndexedSeq$.MODULE$:Lscala/collection/IndexedSeq$;
         3: aload_0
         4: aload_1
         5: aload_2
         6: aload_3
         7: invokestatic  #186                // InterfaceMethod scala/collection/IterableFactory.range$:(Lscala/collection/IterableFactory;Ljava/lang/Object;Ljava/lang/Object;Ljava/lang/Object;Lscala/math/Integral;)Ljava/lang/Object;
        10: areturn
      LocalVariableTable:
        Start  Length  Slot  Name   Signature
            0      11     0 start   Ljava/lang/Object;
            0      11     1   end   Ljava/lang/Object;
            0      11     2  step   Ljava/lang/Object;
            0      11     3 evidence$4   Lscala/math/Integral;
    MethodParameters:
      Name                           Flags
      start                          final
      end                            final
      step                           final
      evidence$4                     final

  public static java.lang.Object range(java.lang.Object, java.lang.Object, scala.math.Integral);
    descriptor: (Ljava/lang/Object;Ljava/lang/Object;Lscala/math/Integral;)Ljava/lang/Object;
    flags: (0x0009) ACC_PUBLIC, ACC_STATIC
    Code:
      stack=4, locals=3, args_size=3
         0: getstatic     #41                 // Field scala/collection/IndexedSeq$.MODULE$:Lscala/collection/IndexedSeq$;
         3: aload_0
         4: aload_1
         5: aload_2
         6: invokestatic  #193                // InterfaceMethod scala/collection/IterableFactory.range$:(Lscala/collection/IterableFactory;Ljava/lang/Object;Ljava/lang/Object;Lscala/math/Integral;)Ljava/lang/Object;
         9: areturn
      LocalVariableTable:
        Start  Length  Slot  Name   Signature
            0      10     0 start   Ljava/lang/Object;
            0      10     1   end   Ljava/lang/Object;
            0      10     2 evidence$3   Lscala/math/Integral;
    MethodParameters:
      Name                           Flags
      start                          final
      end                            final
      evidence$3                     final

  public static java.lang.Object unfold(java.lang.Object, scala.Function1);
    descriptor: (Ljava/lang/Object;Lscala/Function1;)Ljava/lang/Object;
    flags: (0x0009) ACC_PUBLIC, ACC_STATIC
    Code:
      stack=5, locals=2, args_size=2
         0: getstatic     #41                 // Field scala/collection/IndexedSeq$.MODULE$:Lscala/collection/IndexedSeq$;
         3: new           #31                 // class scala/collection/View$Unfold
         6: dup
         7: aload_0
         8: aload_1
         9: invokespecial #199                // Method scala/collection/View$Unfold."<init>":(Ljava/lang/Object;Lscala/Function1;)V
        12: invokeinterface #127,  2          // InterfaceMethod scala/collection/IterableFactory.from:(Lscala/collection/IterableOnce;)Ljava/lang/Object;
        17: areturn
      LocalVariableTable:
        Start  Length  Slot  Name   Signature
            0      18     0  init   Ljava/lang/Object;
            0      18     1     f   Lscala/Function1;
    MethodParameters:
      Name                           Flags
      init                           final
      f                              final

  public static java.lang.Object iterate(java.lang.Object, int, scala.Function1);
    descriptor: (Ljava/lang/Object;ILscala/Function1;)Ljava/lang/Object;
    flags: (0x0009) ACC_PUBLIC, ACC_STATIC
    Code:
      stack=6, locals=3, args_size=3
         0: getstatic     #41                 // Field scala/collection/IndexedSeq$.MODULE$:Lscala/collection/IndexedSeq$;
         3: new           #25                 // class scala/collection/View$Iterate
         6: dup
         7: aload_0
         8: iload_1
         9: aload_2
        10: invokespecial #205                // Method scala/collection/View$Iterate."<init>":(Ljava/lang/Object;ILscala/Function1;)V
        13: invokeinterface #127,  2          // InterfaceMethod scala/collection/IterableFactory.from:(Lscala/collection/IterableOnce;)Ljava/lang/Object;
        18: areturn
      LocalVariableTable:
        Start  Length  Slot  Name   Signature
            0      19     0 start   Ljava/lang/Object;
            0      19     1   len   I
            0      19     2     f   Lscala/Function1;
    MethodParameters:
      Name                           Flags
      start                          final
      len                            final
      f                              final

  public static java.lang.String stringPrefix$(scala.collection.IndexedSeq);
    descriptor: (Lscala/collection/IndexedSeq;)Ljava/lang/String;
    flags: (0x1009) ACC_PUBLIC, ACC_STATIC, ACC_SYNTHETIC
    Code:
      stack=1, locals=1, args_size=1
         0: aload_0
         1: invokespecial #212                // InterfaceMethod stringPrefix:()Ljava/lang/String;
         4: areturn
      LineNumberTable:
        line 26: 0
      LocalVariableTable:
        Start  Length  Slot  Name   Signature
            0       5     0 $this   Lscala/collection/IndexedSeq;
    MethodParameters:
      Name                           Flags
      $this                          final synthetic

  public default java.lang.String stringPrefix();
    descriptor: ()Ljava/lang/String;
    flags: (0x0001) ACC_PUBLIC
    Code:
      stack=1, locals=1, args_size=1
         0: ldc           #215                // String IndexedSeq
         2: areturn
      LineNumberTable:
        line 26: 0
      LocalVariableTable:
        Start  Length  Slot  Name   Signature
            0       3     0  this   Lscala/collection/IndexedSeq;

  public static scala.collection.SeqFactory iterableFactory$(scala.collection.IndexedSeq);
    descriptor: (Lscala/collection/IndexedSeq;)Lscala/collection/SeqFactory;
    flags: (0x1009) ACC_PUBLIC, ACC_STATIC, ACC_SYNTHETIC
    Code:
      stack=1, locals=1, args_size=1
         0: aload_0
         1: invokespecial #222                // InterfaceMethod iterableFactory:()Lscala/collection/SeqFactory;
         4: areturn
      LineNumberTable:
        line 28: 0
      LocalVariableTable:
        Start  Length  Slot  Name   Signature
            0       5     0 $this   Lscala/collection/IndexedSeq;
    MethodParameters:
      Name                           Flags
      $this                          final synthetic

  public default scala.collection.SeqFactory<scala.collection.IndexedSeq> iterableFactory();
    descriptor: ()Lscala/collection/SeqFactory;
    flags: (0x0001) ACC_PUBLIC
    Code:
      stack=1, locals=1, args_size=1
         0: getstatic     #41                 // Field scala/collection/IndexedSeq$.MODULE$:Lscala/collection/IndexedSeq$;
         3: areturn
      LineNumberTable:
        line 28: 0
      LocalVariableTable:
        Start  Length  Slot  Name   Signature
            0       4     0  this   Lscala/collection/IndexedSeq;
    Signature: #223                         // ()Lscala/collection/SeqFactory<Lscala/collection/IndexedSeq;>;

  public static void $init$(scala.collection.IndexedSeq);
    descriptor: (Lscala/collection/IndexedSeq;)V
    flags: (0x0009) ACC_PUBLIC, ACC_STATIC
    Code:
      stack=0, locals=1, args_size=1
         0: return
      LineNumberTable:
        line 22: 0
      LocalVariableTable:
        Start  Length  Slot  Name   Signature
            0       1     0 $this   Lscala/collection/IndexedSeq;
    MethodParameters:
      Name                           Flags
      $this                          final synthetic

  private static java.lang.Object $deserializeLambda$(java.lang.invoke.SerializedLambda);
    descriptor: (Ljava/lang/invoke/SerializedLambda;)Ljava/lang/Object;
    flags: (0x100a) ACC_PRIVATE, ACC_STATIC, ACC_SYNTHETIC
    Code:
      stack=1, locals=1, args_size=1
         0: aload_0
         1: invokedynamic #237,  0            // InvokeDynamic #8:lambdaDeserialize:(Ljava/lang/invoke/SerializedLambda;)Ljava/lang/Object;
         6: areturn
}
InnerClasses:
  public static final #18= #15 of #17;    // Lookup=class java/lang/invoke/MethodHandles$Lookup of class java/lang/invoke/MethodHandles
  public static #23= #20 of #22;          // Fill=class scala/collection/View$Fill of class scala/collection/View
  public static #26= #25 of #22;          // Iterate=class scala/collection/View$Iterate of class scala/collection/View
  public static #29= #28 of #22;          // Tabulate=class scala/collection/View$Tabulate of class scala/collection/View
  public static #32= #31 of #22;          // Unfold=class scala/collection/View$Unfold of class scala/collection/View
Signature: #3                           // <A:Ljava/lang/Object;>Ljava/lang/Object;Lscala/collection/Seq<TA;>;Lscala/collection/IndexedSeqOps<TA;Lscala/collection/IndexedSeq;Lscala/collection/IndexedSeq<TA;>;>;
SourceFile: "IndexedSeq.scala"
RuntimeVisibleAnnotations:
  0: #11(#12=s#13)
    scala.reflect.ScalaSignature(
      bytes="\u0006\u0005}3q\u0001C\u0005\u0011\u0002\u0007\u0005a\u0002C\u0003,\u0001\u0011\u0005A\u0006\u0003\u00041\u0001\u0001&\t&\r\u0005\u0006{\u0001!\tEP\u0004\u0006\u0005&A\ta\u0011\u0004\u0006\u0011%A\t\u0001\u0012\u0005\u0006\u0019\u0016!\t!\u0014\u0005\b\u001d\u0016\t\t\u0011\"\u0003P\u0005)Ie\u000eZ3yK\u0012\u001cV-\u001d\u0006\u0003\u0015-\t!bY8mY\u0016\u001cG/[8o\u0015\u0005a\u0011!B:dC2\f7\u0001A\u000b\u0003\u001fi\u0019R\u0001\u0001\t\u0015G!\u0002\"!\u0005\n\u000e\u0003-I!aE\u0006\u0003\r\u0005s\u0017PU3g!\r)b\u0003G\u0007\u0002\u0013%\u0011q#\u0003\u0002\u0004\'\u0016\f\bCA\r\u001b\u0019\u0001!aa\u0007\u0001\u0005\u0006\u0004a\"!A!\u0012\u0005u\u0001\u0003CA\t\u001f\u0013\ty2BA\u0004O_RD\u0017N\\4\u0011\u0005E\t\u0013B\u0001\u0012\f\u0005\r\te.\u001f\t\u0006+\u0011BbeJ\u0005\u0003K%\u0011Q\"\u00138eKb,GmU3r\u001fB\u001c\bCA\u000b\u0001!\r)\u0002\u0001\u0007\t\u0005+%Bb%\u0003\u0002+\u0013\t9\u0012\n^3sC\ndWMR1di>\u0014\u0018\u0010R3gCVdGo]\u0001\u0007I%t\u0017\u000e\u001e\u0013\u0015\u00035\u0002\"!\u0005\u0018\n\u0005=Z!\u0001B+oSR\fAb\u001d;sS:<\u0007K]3gSb,\u0012A\r\t\u0003gir!\u0001\u000e\u001d\u0011\u0005UZQ\"\u0001\u001c\u000b\u0005]j\u0011A\u0002\u001fs_>$h(\u0003\u0002:\u0017\u00051\u0001K]3eK\u001aL!a\u000f\u001f\u0003\rM#(/\u001b8h\u0015\tI4\"A\bji\u0016\u0014\u0018M\u00197f\r\u0006\u001cGo\u001c:z+\u0005y\u0004cA\u000bAM%\u0011\u0011)\u0003\u0002\u000b\'\u0016\fh)Y2u_JL\u0018AC%oI\u0016DX\rZ*fcB\u0011Q#B\n\u0003\u000b\u0015\u00032AR%\'\u001d\t)r)\u0003\u0002I\u0013\u0005Q1+Z9GC\u000e$xN]=\n\u0005)[%\u0001\u0003#fY\u0016<\u0017\r^3\u000b\u0005!K\u0011A\u0002\u001fj]&$h\bF\u0001D\u000319(/\u001b;f%\u0016\u0004H.Y2f)\u0005\u0001\u0006CA)W\u001b\u0005\u0011&BA*U\u0003\u0011a\u0017M\\4\u000b\u0003U\u000bAA[1wC&\u0011qK\u0015\u0002\u0007\u001f\nTWm\u0019;)\t\u0015IF,\u0018\t\u0003#iK!aW\u0006\u0003!M+\'/[1m-\u0016\u00148/[8o+&#\u0015!\u0002<bYV,g$A\u0002)\t\u0011IF,\u0018"
    )
BootstrapMethods:
  0: #78 REF_invokeStatic java/lang/invoke/LambdaMetafactory.altMetafactory:(Ljava/lang/invoke/MethodHandles$Lookup;Ljava/lang/String;Ljava/lang/invoke/MethodType;[Ljava/lang/Object;)Ljava/lang/invoke/CallSite;
    Method arguments:
      #63 (Ljava/lang/Object;)Ljava/lang/Object;
      #70 REF_invokeStatic scala/collection/IterableFactory.$anonfun$tabulate$7$adapted:(Lscala/collection/IterableFactory;IIIILscala/Function5;Ljava/lang/Object;)Ljava/lang/Object;
      #63 (Ljava/lang/Object;)Ljava/lang/Object;
      #71 1
  1: #78 REF_invokeStatic java/lang/invoke/LambdaMetafactory.altMetafactory:(Ljava/lang/invoke/MethodHandles$Lookup;Ljava/lang/String;Ljava/lang/invoke/MethodType;[Ljava/lang/Object;)Ljava/lang/invoke/CallSite;
    Method arguments:
      #63 (Ljava/lang/Object;)Ljava/lang/Object;
      #95 REF_invokeStatic scala/collection/IterableFactory.$anonfun$tabulate$5$adapted:(Lscala/collection/IterableFactory;IIILscala/Function4;Ljava/lang/Object;)Ljava/lang/Object;
      #63 (Ljava/lang/Object;)Ljava/lang/Object;
      #71 1
  2: #78 REF_invokeStatic java/lang/invoke/LambdaMetafactory.altMetafactory:(Ljava/lang/invoke/MethodHandles$Lookup;Ljava/lang/String;Ljava/lang/invoke/MethodType;[Ljava/lang/Object;)Ljava/lang/invoke/CallSite;
    Method arguments:
      #63 (Ljava/lang/Object;)Ljava/lang/Object;
      #105 REF_invokeStatic scala/collection/IterableFactory.$anonfun$tabulate$3$adapted:(Lscala/collection/IterableFactory;IILscala/Function3;Ljava/lang/Object;)Ljava/lang/Object;
      #63 (Ljava/lang/Object;)Ljava/lang/Object;
      #71 1
  3: #78 REF_invokeStatic java/lang/invoke/LambdaMetafactory.altMetafactory:(Ljava/lang/invoke/MethodHandles$Lookup;Ljava/lang/String;Ljava/lang/invoke/MethodType;[Ljava/lang/Object;)Ljava/lang/invoke/CallSite;
    Method arguments:
      #63 (Ljava/lang/Object;)Ljava/lang/Object;
      #115 REF_invokeStatic scala/collection/IterableFactory.$anonfun$tabulate$1$adapted:(Lscala/collection/IterableFactory;ILscala/Function2;Ljava/lang/Object;)Ljava/lang/Object;
      #63 (Ljava/lang/Object;)Ljava/lang/Object;
      #71 1
  4: #78 REF_invokeStatic java/lang/invoke/LambdaMetafactory.altMetafactory:(Ljava/lang/invoke/MethodHandles$Lookup;Ljava/lang/String;Ljava/lang/invoke/MethodType;[Ljava/lang/Object;)Ljava/lang/invoke/CallSite;
    Method arguments:
      #133 ()Ljava/lang/Object;
      #138 REF_invokeStatic scala/collection/IterableFactory.$anonfun$fill$4:(Lscala/collection/IterableFactory;IIIILscala/Function0;)Ljava/lang/Object;
      #133 ()Ljava/lang/Object;
      #71 1
  5: #78 REF_invokeStatic java/lang/invoke/LambdaMetafactory.altMetafactory:(Ljava/lang/invoke/MethodHandles$Lookup;Ljava/lang/String;Ljava/lang/invoke/MethodType;[Ljava/lang/Object;)Ljava/lang/invoke/CallSite;
    Method arguments:
      #133 ()Ljava/lang/Object;
      #152 REF_invokeStatic scala/collection/IterableFactory.$anonfun$fill$3:(Lscala/collection/IterableFactory;IIILscala/Function0;)Ljava/lang/Object;
      #133 ()Ljava/lang/Object;
      #71 1
  6: #78 REF_invokeStatic java/lang/invoke/LambdaMetafactory.altMetafactory:(Ljava/lang/invoke/MethodHandles$Lookup;Ljava/lang/String;Ljava/lang/invoke/MethodType;[Ljava/lang/Object;)Ljava/lang/invoke/CallSite;
    Method arguments:
      #133 ()Ljava/lang/Object;
      #161 REF_invokeStatic scala/collection/IterableFactory.$anonfun$fill$2:(Lscala/collection/IterableFactory;IILscala/Function0;)Ljava/lang/Object;
      #133 ()Ljava/lang/Object;
      #71 1
  7: #78 REF_invokeStatic java/lang/invoke/LambdaMetafactory.altMetafactory:(Ljava/lang/invoke/MethodHandles$Lookup;Ljava/lang/String;Ljava/lang/invoke/MethodType;[Ljava/lang/Object;)Ljava/lang/invoke/CallSite;
    Method arguments:
      #133 ()Ljava/lang/Object;
      #170 REF_invokeStatic scala/collection/IterableFactory.$anonfun$fill$1:(Lscala/collection/IterableFactory;ILscala/Function0;)Ljava/lang/Object;
      #133 ()Ljava/lang/Object;
      #71 1
  8: #234 REF_invokeStatic scala/runtime/LambdaDeserialize.bootstrap:(Ljava/lang/invoke/MethodHandles$Lookup;Ljava/lang/String;Ljava/lang/invoke/MethodType;[Ljava/lang/invoke/MethodHandle;)Ljava/lang/invoke/CallSite;
    Method arguments:
      #170 REF_invokeStatic scala/collection/IterableFactory.$anonfun$fill$1:(Lscala/collection/IterableFactory;ILscala/Function0;)Ljava/lang/Object;
      #161 REF_invokeStatic scala/collection/IterableFactory.$anonfun$fill$2:(Lscala/collection/IterableFactory;IILscala/Function0;)Ljava/lang/Object;
      #152 REF_invokeStatic scala/collection/IterableFactory.$anonfun$fill$3:(Lscala/collection/IterableFactory;IIILscala/Function0;)Ljava/lang/Object;
      #138 REF_invokeStatic scala/collection/IterableFactory.$anonfun$fill$4:(Lscala/collection/IterableFactory;IIIILscala/Function0;)Ljava/lang/Object;
      #115 REF_invokeStatic scala/collection/IterableFactory.$anonfun$tabulate$1$adapted:(Lscala/collection/IterableFactory;ILscala/Function2;Ljava/lang/Object;)Ljava/lang/Object;
      #105 REF_invokeStatic scala/collection/IterableFactory.$anonfun$tabulate$3$adapted:(Lscala/collection/IterableFactory;IILscala/Function3;Ljava/lang/Object;)Ljava/lang/Object;
      #95 REF_invokeStatic scala/collection/IterableFactory.$anonfun$tabulate$5$adapted:(Lscala/collection/IterableFactory;IIILscala/Function4;Ljava/lang/Object;)Ljava/lang/Object;
      #70 REF_invokeStatic scala/collection/IterableFactory.$anonfun$tabulate$7$adapted:(Lscala/collection/IterableFactory;IIIILscala/Function5;Ljava/lang/Object;)Ljava/lang/Object;
  ScalaInlineInfo: length = 0x1D (unknown attribute)
   01 00 00 05 00 E0 00 E1 01 00 DB 00 DC 00 00 D9
   00 DA 01 00 D1 00 D2 00 00 CE 00 CF 01
  ScalaSig: length = 0x3 (unknown attribute)
   05 02 00
