Classfile /Users/mw/Projects/slang-braindump/.jar/jar11/assemble/slang-braindump/assemble/content/scala/collection/LazyZip4$.class
  Last modified May 29, 2022; size 1033 bytes
  SHA-256 checksum af42db77b695a4b3b4f3acc89b543782ac01a635004d8311871e07e3f33795c7
  Compiled from "LazyZipOps.scala"
public final class scala.collection.LazyZip4$
  minor version: 0
  major version: 52
  flags: (0x0031) ACC_PUBLIC, ACC_FINAL, ACC_SUPER
  this_class: #2                          // scala/collection/LazyZip4$
  super_class: #4                         // java/lang/Object
  interfaces: 0, fields: 1, methods: 3, attributes: 4
Constant pool:
   #1 = Utf8               scala/collection/LazyZip4$
   #2 = Class              #1             // scala/collection/LazyZip4$
   #3 = Utf8               java/lang/Object
   #4 = Class              #3             // java/lang/Object
   #5 = Utf8               LazyZipOps.scala
   #6 = Utf8               scala/collection/LazyZip4$$anon$23
   #7 = Class              #6             // scala/collection/LazyZip4$$anon$23
   #8 = Utf8               MODULE$
   #9 = Utf8               Lscala/collection/LazyZip4$;
  #10 = Utf8               <clinit>
  #11 = Utf8               ()V
  #12 = Utf8               <init>
  #13 = NameAndType        #12:#11        // "<init>":()V
  #14 = Methodref          #2.#13         // scala/collection/LazyZip4$."<init>":()V
  #15 = NameAndType        #8:#9          // MODULE$:Lscala/collection/LazyZip4$;
  #16 = Fieldref           #2.#15         // scala/collection/LazyZip4$.MODULE$:Lscala/collection/LazyZip4$;
  #17 = Utf8               lazyZip4ToIterable
  #18 = Utf8               (Lscala/collection/LazyZip4;)Lscala/collection/View;
  #19 = Utf8               <El1:Ljava/lang/Object;El2:Ljava/lang/Object;El3:Ljava/lang/Object;El4:Ljava/lang/Object;>(Lscala/collection/LazyZip4<TEl1;TEl2;TEl3;TEl4;*>;)Lscala/collection/View<Lscala/Tuple4<TEl1;TEl2;TEl3;TEl4;>;>;
  #20 = Utf8               zipped4
  #21 = Utf8               (Lscala/collection/LazyZip4;)V
  #22 = NameAndType        #12:#21        // "<init>":(Lscala/collection/LazyZip4;)V
  #23 = Methodref          #7.#22         // scala/collection/LazyZip4$$anon$23."<init>":(Lscala/collection/LazyZip4;)V
  #24 = Utf8               this
  #25 = Utf8               Lscala/collection/LazyZip4;
  #26 = Methodref          #4.#13         // java/lang/Object."<init>":()V
  #27 = Utf8               Code
  #28 = Utf8               LineNumberTable
  #29 = Utf8               StackMapTable
  #30 = Utf8               LocalVariableTable
  #31 = Utf8               Signature
  #32 = Utf8               MethodParameters
  #33 = Utf8               InnerClasses
  #34 = Utf8               SourceFile
  #35 = Utf8               ScalaInlineInfo
  #36 = Utf8               Scala
{
  public static final scala.collection.LazyZip4$ MODULE$;
    descriptor: Lscala/collection/LazyZip4$;
    flags: (0x0019) ACC_PUBLIC, ACC_STATIC, ACC_FINAL

  public static {};
    descriptor: ()V
    flags: (0x0009) ACC_PUBLIC, ACC_STATIC
    Code:
      stack=2, locals=0, args_size=0
         0: new           #2                  // class scala/collection/LazyZip4$
         3: dup
         4: invokespecial #14                 // Method "<init>":()V
         7: putstatic     #16                 // Field MODULE$:Lscala/collection/LazyZip4$;
        10: return
      LineNumberTable:
        line 419: 0

  public <El1 extends java.lang.Object, El2 extends java.lang.Object, El3 extends java.lang.Object, El4 extends java.lang.Object> scala.collection.View<scala.Tuple4<El1, El2, El3, El4>> lazyZip4ToIterable(scala.collection.LazyZip4<El1, El2, El3, El4, ?>);
    descriptor: (Lscala/collection/LazyZip4;)Lscala/collection/View;
    flags: (0x0001) ACC_PUBLIC
    Code:
      stack=3, locals=2, args_size=2
         0: aload_1
         1: ifnonnull     6
         4: aconst_null
         5: athrow
         6: new           #7                  // class scala/collection/LazyZip4$$anon$23
         9: dup
        10: aload_1
        11: invokespecial #23                 // Method scala/collection/LazyZip4$$anon$23."<init>":(Lscala/collection/LazyZip4;)V
        14: areturn
      StackMapTable: number_of_entries = 1
        frame_type = 6 /* same */
      LineNumberTable:
        line 421: 0
        line 389: 6
        line 421: 14
      LocalVariableTable:
        Start  Length  Slot  Name   Signature
            0      15     0  this   Lscala/collection/LazyZip4$;
            0      15     1 zipped4   Lscala/collection/LazyZip4;
    Signature: #19                          // <El1:Ljava/lang/Object;El2:Ljava/lang/Object;El3:Ljava/lang/Object;El4:Ljava/lang/Object;>(Lscala/collection/LazyZip4<TEl1;TEl2;TEl3;TEl4;*>;)Lscala/collection/View<Lscala/Tuple4<TEl1;TEl2;TEl3;TEl4;>;>;
    MethodParameters:
      Name                           Flags
      zipped4                        final

  private scala.collection.LazyZip4$();
    descriptor: ()V
    flags: (0x0002) ACC_PRIVATE
    Code:
      stack=1, locals=1, args_size=1
         0: aload_0
         1: invokespecial #26                 // Method java/lang/Object."<init>":()V
         4: return
      LineNumberTable:
        line 419: 0
      LocalVariableTable:
        Start  Length  Slot  Name   Signature
            0       5     0  this   Lscala/collection/LazyZip4$;
}
InnerClasses:
  public final #7;                        // class scala/collection/LazyZip4$$anon$23
SourceFile: "LazyZipOps.scala"
  ScalaInlineInfo: length = 0xE (unknown attribute)
   01 01 00 02 00 0C 00 0B 01 00 11 00 12 01
  Scala: length = 0x0 (unknown attribute)

