Classfile /Users/mw/Projects/slang-braindump/.jar/jar11/assemble/slang-braindump/assemble/content/scala/collection/package$$colon$plus$.class
  Last modified May 29, 2022; size 1435 bytes
  SHA-256 checksum c9930092f0f61cf971e5b5d315a2a79006fae58bebb60affd2b562336c8a5182
  Compiled from "package.scala"
public class scala.collection.package$$colon$plus$
  minor version: 0
  major version: 52
  flags: (0x0021) ACC_PUBLIC, ACC_SUPER
  this_class: #2                          // scala/collection/package$$colon$plus$
  super_class: #4                         // java/lang/Object
  interfaces: 0, fields: 1, methods: 3, attributes: 4
Constant pool:
   #1 = Utf8               scala/collection/package$$colon$plus$
   #2 = Class              #1             // scala/collection/package$$colon$plus$
   #3 = Utf8               java/lang/Object
   #4 = Class              #3             // java/lang/Object
   #5 = Utf8               package.scala
   #6 = Utf8               scala/Predef$ArrowAssoc$
   #7 = Class              #6             // scala/Predef$ArrowAssoc$
   #8 = Utf8               scala/Predef
   #9 = Class              #8             // scala/Predef
  #10 = Utf8               ArrowAssoc$
  #11 = Utf8               scala/collection/package
  #12 = Class              #11            // scala/collection/package
  #13 = Utf8               $colon$plus$
  #14 = Utf8               MODULE$
  #15 = Utf8               Lscala/collection/package$$colon$plus$;
  #16 = Utf8               <clinit>
  #17 = Utf8               ()V
  #18 = Utf8               <init>
  #19 = NameAndType        #18:#17        // "<init>":()V
  #20 = Methodref          #2.#19         // scala/collection/package$$colon$plus$."<init>":()V
  #21 = NameAndType        #14:#15        // MODULE$:Lscala/collection/package$$colon$plus$;
  #22 = Fieldref           #2.#21         // scala/collection/package$$colon$plus$.MODULE$:Lscala/collection/package$$colon$plus$;
  #23 = Utf8               unapply
  #24 = Utf8               (Lscala/collection/SeqOps;)Lscala/Option;
  #25 = Utf8               <A:Ljava/lang/Object;CC::Lscala/collection/Seq<*>;C::Lscala/collection/SeqOps<TA;TCC;TC;>;>(TC;)Lscala/Option<Lscala/Tuple2<TC;TA;>;>;
  #26 = Utf8               t
  #27 = Utf8               scala/collection/SeqOps
  #28 = Class              #27            // scala/collection/SeqOps
  #29 = Utf8               isEmpty
  #30 = Utf8               ()Z
  #31 = NameAndType        #29:#30        // isEmpty:()Z
  #32 = InterfaceMethodref #28.#31        // scala/collection/SeqOps.isEmpty:()Z
  #33 = Utf8               scala/None$
  #34 = Class              #33            // scala/None$
  #35 = Utf8               Lscala/None$;
  #36 = NameAndType        #14:#35        // MODULE$:Lscala/None$;
  #37 = Fieldref           #34.#36        // scala/None$.MODULE$:Lscala/None$;
  #38 = Utf8               scala/Some
  #39 = Class              #38            // scala/Some
  #40 = Utf8               Lscala/Predef$ArrowAssoc$;
  #41 = NameAndType        #14:#40        // MODULE$:Lscala/Predef$ArrowAssoc$;
  #42 = Fieldref           #7.#41         // scala/Predef$ArrowAssoc$.MODULE$:Lscala/Predef$ArrowAssoc$;
  #43 = Utf8               init
  #44 = Utf8               ()Ljava/lang/Object;
  #45 = NameAndType        #43:#44        // init:()Ljava/lang/Object;
  #46 = InterfaceMethodref #28.#45        // scala/collection/SeqOps.init:()Ljava/lang/Object;
  #47 = Utf8               last
  #48 = NameAndType        #47:#44        // last:()Ljava/lang/Object;
  #49 = InterfaceMethodref #28.#48        // scala/collection/SeqOps.last:()Ljava/lang/Object;
  #50 = Utf8               scala/Tuple2
  #51 = Class              #50            // scala/Tuple2
  #52 = Utf8               (Ljava/lang/Object;Ljava/lang/Object;)V
  #53 = NameAndType        #18:#52        // "<init>":(Ljava/lang/Object;Ljava/lang/Object;)V
  #54 = Methodref          #51.#53        // scala/Tuple2."<init>":(Ljava/lang/Object;Ljava/lang/Object;)V
  #55 = Utf8               (Ljava/lang/Object;)V
  #56 = NameAndType        #18:#55        // "<init>":(Ljava/lang/Object;)V
  #57 = Methodref          #39.#56        // scala/Some."<init>":(Ljava/lang/Object;)V
  #58 = Utf8               this
  #59 = Utf8               Lscala/collection/SeqOps;
  #60 = Utf8               $minus$greater$extension_$this
  #61 = Utf8               Ljava/lang/Object;
  #62 = Utf8               $minus$greater$extension_y
  #63 = Methodref          #4.#19         // java/lang/Object."<init>":()V
  #64 = Utf8               Code
  #65 = Utf8               LineNumberTable
  #66 = Utf8               StackMapTable
  #67 = Utf8               LocalVariableTable
  #68 = Utf8               Signature
  #69 = Utf8               MethodParameters
  #70 = Utf8               InnerClasses
  #71 = Utf8               SourceFile
  #72 = Utf8               ScalaInlineInfo
  #73 = Utf8               Scala
{
  public static final scala.collection.package$$colon$plus$ MODULE$;
    descriptor: Lscala/collection/package$$colon$plus$;
    flags: (0x0019) ACC_PUBLIC, ACC_STATIC, ACC_FINAL

  public static {};
    descriptor: ()V
    flags: (0x0009) ACC_PUBLIC, ACC_STATIC
    Code:
      stack=2, locals=0, args_size=0
         0: new           #2                  // class scala/collection/package$$colon$plus$
         3: dup
         4: invokespecial #20                 // Method "<init>":()V
         7: putstatic     #22                 // Field MODULE$:Lscala/collection/package$$colon$plus$;
        10: return
      LineNumberTable:
        line 72: 0

  public <A extends java.lang.Object, CC extends scala.collection.Seq<?>, C extends scala.collection.SeqOps<A, CC, C>> scala.Option<scala.Tuple2<C, A>> unapply(C);
    descriptor: (Lscala/collection/SeqOps;)Lscala/Option;
    flags: (0x0001) ACC_PUBLIC
    Code:
      stack=6, locals=4, args_size=2
         0: aload_1
         1: invokeinterface #32,  1           // InterfaceMethod scala/collection/SeqOps.isEmpty:()Z
         6: ifeq          13
         9: getstatic     #37                 // Field scala/None$.MODULE$:Lscala/None$;
        12: areturn
        13: new           #39                 // class scala/Some
        16: dup
        17: getstatic     #42                 // Field scala/Predef$ArrowAssoc$.MODULE$:Lscala/Predef$ArrowAssoc$;
        20: pop
        21: aload_1
        22: invokeinterface #46,  1           // InterfaceMethod scala/collection/SeqOps.init:()Ljava/lang/Object;
        27: aload_1
        28: invokeinterface #49,  1           // InterfaceMethod scala/collection/SeqOps.last:()Ljava/lang/Object;
        33: astore_3
        34: astore_2
        35: new           #51                 // class scala/Tuple2
        38: dup
        39: aload_2
        40: aload_3
        41: invokespecial #54                 // Method scala/Tuple2."<init>":(Ljava/lang/Object;Ljava/lang/Object;)V
        44: aconst_null
        45: astore_2
        46: aconst_null
        47: astore_3
        48: invokespecial #57                 // Method scala/Some."<init>":(Ljava/lang/Object;)V
        51: areturn
      StackMapTable: number_of_entries = 1
        frame_type = 13 /* same */
      LineNumberTable:
        line 77: 0
        line 78: 13
      LocalVariableTable:
        Start  Length  Slot  Name   Signature
            0      52     0  this   Lscala/collection/package$$colon$plus$;
            0      52     1     t   Lscala/collection/SeqOps;
           35       9     2 $minus$greater$extension_$this   Ljava/lang/Object;
           35       9     3 $minus$greater$extension_y   Ljava/lang/Object;
    Signature: #25                          // <A:Ljava/lang/Object;CC::Lscala/collection/Seq<*>;C::Lscala/collection/SeqOps<TA;TCC;TC;>;>(TC;)Lscala/Option<Lscala/Tuple2<TC;TA;>;>;
    MethodParameters:
      Name                           Flags
      t                              final

  public scala.collection.package$$colon$plus$();
    descriptor: ()V
    flags: (0x0001) ACC_PUBLIC
    Code:
      stack=1, locals=1, args_size=1
         0: aload_0
         1: invokespecial #63                 // Method java/lang/Object."<init>":()V
         4: return
      LineNumberTable:
        line 72: 0
      LocalVariableTable:
        Start  Length  Slot  Name   Signature
            0       5     0  this   Lscala/collection/package$$colon$plus$;
}
InnerClasses:
  public static #10= #7 of #9;            // ArrowAssoc$=class scala/Predef$ArrowAssoc$ of class scala/Predef
  public static #13= #2 of #12;           // $colon$plus$=class scala/collection/package$$colon$plus$ of class scala/collection/package
SourceFile: "package.scala"
  ScalaInlineInfo: length = 0xE (unknown attribute)
   01 01 00 02 00 12 00 11 01 00 17 00 18 01
  Scala: length = 0x0 (unknown attribute)

