Classfile /Users/mw/Projects/slang-braindump/.jar/jar11/assemble/slang-braindump/assemble/content/scala/collection/SeqFactory$Delegate.class
  Last modified May 29, 2022; size 7509 bytes
  SHA-256 checksum 27bbcb68c7c202fc5b2ab34e62686d2084d988c895f5df0d14d5c6c72ec922bd
  Compiled from "Factory.scala"
public class scala.collection.SeqFactory$Delegate<CC extends scala.collection.SeqOps<java.lang.Object, scala.collection.Seq, scala.collection.Seq<java.lang.Object>>> extends java.lang.Object implements scala.collection.SeqFactory<CC>
  minor version: 0
  major version: 52
  flags: (0x0021) ACC_PUBLIC, ACC_SUPER
  this_class: #2                          // scala/collection/SeqFactory$Delegate
  super_class: #5                         // java/lang/Object
  interfaces: 1, fields: 2, methods: 25, attributes: 5
Constant pool:
    #1 = Utf8               scala/collection/SeqFactory$Delegate
    #2 = Class              #1            // scala/collection/SeqFactory$Delegate
    #3 = Utf8               <CC::Lscala/collection/SeqOps<Ljava/lang/Object;Lscala/collection/Seq;Lscala/collection/Seq<Ljava/lang/Object;>;>;>Ljava/lang/Object;Lscala/collection/SeqFactory<TCC;>;
    #4 = Utf8               java/lang/Object
    #5 = Class              #4            // java/lang/Object
    #6 = Utf8               scala/collection/SeqFactory
    #7 = Class              #6            // scala/collection/SeqFactory
    #8 = Utf8               Factory.scala
    #9 = Utf8               Delegate
   #10 = Utf8               serialVersionUID
   #11 = Utf8               J
   #12 = Long               3l
   #14 = Utf8               delegate
   #15 = Utf8               Lscala/collection/SeqFactory;
   #16 = Utf8               Lscala/collection/SeqFactory<TCC;>;
   #17 = Utf8               unapplySeq
   #18 = Utf8               (Lscala/collection/SeqOps;)Lscala/collection/SeqOps;
   #19 = Utf8               <A:Ljava/lang/Object;>(TCC;)Lscala/collection/SeqOps<TA;Lscala/collection/Seq;Lscala/collection/Seq<TA;>;>;
   #20 = Utf8               x
   #21 = Utf8               unapplySeq$
   #22 = Utf8               (Lscala/collection/SeqFactory;Lscala/collection/SeqOps;)Lscala/collection/SeqOps;
   #23 = NameAndType        #21:#22       // unapplySeq$:(Lscala/collection/SeqFactory;Lscala/collection/SeqOps;)Lscala/collection/SeqOps;
   #24 = InterfaceMethodref #7.#23        // scala/collection/SeqFactory.unapplySeq$:(Lscala/collection/SeqFactory;Lscala/collection/SeqOps;)Lscala/collection/SeqOps;
   #25 = Utf8               this
   #26 = Utf8               Lscala/collection/SeqFactory$Delegate;
   #27 = Utf8               Lscala/collection/SeqOps;
   #28 = Utf8               iterate
   #29 = Utf8               (Ljava/lang/Object;ILscala/Function1;)Ljava/lang/Object;
   #30 = Utf8               start
   #31 = Utf8               len
   #32 = Utf8               f
   #33 = Utf8               scala/collection/IterableFactory
   #34 = Class              #33           // scala/collection/IterableFactory
   #35 = Utf8               iterate$
   #36 = Utf8               (Lscala/collection/IterableFactory;Ljava/lang/Object;ILscala/Function1;)Ljava/lang/Object;
   #37 = NameAndType        #35:#36       // iterate$:(Lscala/collection/IterableFactory;Ljava/lang/Object;ILscala/Function1;)Ljava/lang/Object;
   #38 = InterfaceMethodref #34.#37       // scala/collection/IterableFactory.iterate$:(Lscala/collection/IterableFactory;Ljava/lang/Object;ILscala/Function1;)Ljava/lang/Object;
   #39 = Utf8               Ljava/lang/Object;
   #40 = Utf8               I
   #41 = Utf8               Lscala/Function1;
   #42 = Utf8               unfold
   #43 = Utf8               (Ljava/lang/Object;Lscala/Function1;)Ljava/lang/Object;
   #44 = Utf8               init
   #45 = Utf8               unfold$
   #46 = Utf8               (Lscala/collection/IterableFactory;Ljava/lang/Object;Lscala/Function1;)Ljava/lang/Object;
   #47 = NameAndType        #45:#46       // unfold$:(Lscala/collection/IterableFactory;Ljava/lang/Object;Lscala/Function1;)Ljava/lang/Object;
   #48 = InterfaceMethodref #34.#47       // scala/collection/IterableFactory.unfold$:(Lscala/collection/IterableFactory;Ljava/lang/Object;Lscala/Function1;)Ljava/lang/Object;
   #49 = Utf8               range
   #50 = Utf8               (Ljava/lang/Object;Ljava/lang/Object;Lscala/math/Integral;)Ljava/lang/Object;
   #51 = Utf8               end
   #52 = Utf8               evidence$3
   #53 = Utf8               range$
   #54 = Utf8               (Lscala/collection/IterableFactory;Ljava/lang/Object;Ljava/lang/Object;Lscala/math/Integral;)Ljava/lang/Object;
   #55 = NameAndType        #53:#54       // range$:(Lscala/collection/IterableFactory;Ljava/lang/Object;Ljava/lang/Object;Lscala/math/Integral;)Ljava/lang/Object;
   #56 = InterfaceMethodref #34.#55       // scala/collection/IterableFactory.range$:(Lscala/collection/IterableFactory;Ljava/lang/Object;Ljava/lang/Object;Lscala/math/Integral;)Ljava/lang/Object;
   #57 = Utf8               Lscala/math/Integral;
   #58 = Utf8               (Ljava/lang/Object;Ljava/lang/Object;Ljava/lang/Object;Lscala/math/Integral;)Ljava/lang/Object;
   #59 = Utf8               step
   #60 = Utf8               evidence$4
   #61 = Utf8               (Lscala/collection/IterableFactory;Ljava/lang/Object;Ljava/lang/Object;Ljava/lang/Object;Lscala/math/Integral;)Ljava/lang/Object;
   #62 = NameAndType        #53:#61       // range$:(Lscala/collection/IterableFactory;Ljava/lang/Object;Ljava/lang/Object;Ljava/lang/Object;Lscala/math/Integral;)Ljava/lang/Object;
   #63 = InterfaceMethodref #34.#62       // scala/collection/IterableFactory.range$:(Lscala/collection/IterableFactory;Ljava/lang/Object;Ljava/lang/Object;Ljava/lang/Object;Lscala/math/Integral;)Ljava/lang/Object;
   #64 = Utf8               fill
   #65 = Utf8               (ILscala/Function0;)Ljava/lang/Object;
   #66 = Utf8               n
   #67 = Utf8               elem
   #68 = Utf8               fill$
   #69 = Utf8               (Lscala/collection/IterableFactory;ILscala/Function0;)Ljava/lang/Object;
   #70 = NameAndType        #68:#69       // fill$:(Lscala/collection/IterableFactory;ILscala/Function0;)Ljava/lang/Object;
   #71 = InterfaceMethodref #34.#70       // scala/collection/IterableFactory.fill$:(Lscala/collection/IterableFactory;ILscala/Function0;)Ljava/lang/Object;
   #72 = Utf8               Lscala/Function0;
   #73 = Utf8               (IILscala/Function0;)Ljava/lang/Object;
   #74 = Utf8               n1
   #75 = Utf8               n2
   #76 = Utf8               (Lscala/collection/IterableFactory;IILscala/Function0;)Ljava/lang/Object;
   #77 = NameAndType        #68:#76       // fill$:(Lscala/collection/IterableFactory;IILscala/Function0;)Ljava/lang/Object;
   #78 = InterfaceMethodref #34.#77       // scala/collection/IterableFactory.fill$:(Lscala/collection/IterableFactory;IILscala/Function0;)Ljava/lang/Object;
   #79 = Utf8               (IIILscala/Function0;)Ljava/lang/Object;
   #80 = Utf8               n3
   #81 = Utf8               (Lscala/collection/IterableFactory;IIILscala/Function0;)Ljava/lang/Object;
   #82 = NameAndType        #68:#81       // fill$:(Lscala/collection/IterableFactory;IIILscala/Function0;)Ljava/lang/Object;
   #83 = InterfaceMethodref #34.#82       // scala/collection/IterableFactory.fill$:(Lscala/collection/IterableFactory;IIILscala/Function0;)Ljava/lang/Object;
   #84 = Utf8               (IIIILscala/Function0;)Ljava/lang/Object;
   #85 = Utf8               n4
   #86 = Utf8               (Lscala/collection/IterableFactory;IIIILscala/Function0;)Ljava/lang/Object;
   #87 = NameAndType        #68:#86       // fill$:(Lscala/collection/IterableFactory;IIIILscala/Function0;)Ljava/lang/Object;
   #88 = InterfaceMethodref #34.#87       // scala/collection/IterableFactory.fill$:(Lscala/collection/IterableFactory;IIIILscala/Function0;)Ljava/lang/Object;
   #89 = Utf8               (IIIIILscala/Function0;)Ljava/lang/Object;
   #90 = Utf8               n5
   #91 = Utf8               (Lscala/collection/IterableFactory;IIIIILscala/Function0;)Ljava/lang/Object;
   #92 = NameAndType        #68:#91       // fill$:(Lscala/collection/IterableFactory;IIIIILscala/Function0;)Ljava/lang/Object;
   #93 = InterfaceMethodref #34.#92       // scala/collection/IterableFactory.fill$:(Lscala/collection/IterableFactory;IIIIILscala/Function0;)Ljava/lang/Object;
   #94 = Utf8               tabulate
   #95 = Utf8               (ILscala/Function1;)Ljava/lang/Object;
   #96 = Utf8               tabulate$
   #97 = Utf8               (Lscala/collection/IterableFactory;ILscala/Function1;)Ljava/lang/Object;
   #98 = NameAndType        #96:#97       // tabulate$:(Lscala/collection/IterableFactory;ILscala/Function1;)Ljava/lang/Object;
   #99 = InterfaceMethodref #34.#98       // scala/collection/IterableFactory.tabulate$:(Lscala/collection/IterableFactory;ILscala/Function1;)Ljava/lang/Object;
  #100 = Utf8               (IILscala/Function2;)Ljava/lang/Object;
  #101 = Utf8               (Lscala/collection/IterableFactory;IILscala/Function2;)Ljava/lang/Object;
  #102 = NameAndType        #96:#101      // tabulate$:(Lscala/collection/IterableFactory;IILscala/Function2;)Ljava/lang/Object;
  #103 = InterfaceMethodref #34.#102      // scala/collection/IterableFactory.tabulate$:(Lscala/collection/IterableFactory;IILscala/Function2;)Ljava/lang/Object;
  #104 = Utf8               Lscala/Function2;
  #105 = Utf8               (IIILscala/Function3;)Ljava/lang/Object;
  #106 = Utf8               (Lscala/collection/IterableFactory;IIILscala/Function3;)Ljava/lang/Object;
  #107 = NameAndType        #96:#106      // tabulate$:(Lscala/collection/IterableFactory;IIILscala/Function3;)Ljava/lang/Object;
  #108 = InterfaceMethodref #34.#107      // scala/collection/IterableFactory.tabulate$:(Lscala/collection/IterableFactory;IIILscala/Function3;)Ljava/lang/Object;
  #109 = Utf8               Lscala/Function3;
  #110 = Utf8               (IIIILscala/Function4;)Ljava/lang/Object;
  #111 = Utf8               (Lscala/collection/IterableFactory;IIIILscala/Function4;)Ljava/lang/Object;
  #112 = NameAndType        #96:#111      // tabulate$:(Lscala/collection/IterableFactory;IIIILscala/Function4;)Ljava/lang/Object;
  #113 = InterfaceMethodref #34.#112      // scala/collection/IterableFactory.tabulate$:(Lscala/collection/IterableFactory;IIIILscala/Function4;)Ljava/lang/Object;
  #114 = Utf8               Lscala/Function4;
  #115 = Utf8               (IIIIILscala/Function5;)Ljava/lang/Object;
  #116 = Utf8               (Lscala/collection/IterableFactory;IIIIILscala/Function5;)Ljava/lang/Object;
  #117 = NameAndType        #96:#116      // tabulate$:(Lscala/collection/IterableFactory;IIIIILscala/Function5;)Ljava/lang/Object;
  #118 = InterfaceMethodref #34.#117      // scala/collection/IterableFactory.tabulate$:(Lscala/collection/IterableFactory;IIIIILscala/Function5;)Ljava/lang/Object;
  #119 = Utf8               Lscala/Function5;
  #120 = Utf8               concat
  #121 = Utf8               (Lscala/collection/immutable/Seq;)Ljava/lang/Object;
  #122 = Utf8               xss
  #123 = Utf8               concat$
  #124 = Utf8               (Lscala/collection/IterableFactory;Lscala/collection/immutable/Seq;)Ljava/lang/Object;
  #125 = NameAndType        #123:#124     // concat$:(Lscala/collection/IterableFactory;Lscala/collection/immutable/Seq;)Ljava/lang/Object;
  #126 = InterfaceMethodref #34.#125      // scala/collection/IterableFactory.concat$:(Lscala/collection/IterableFactory;Lscala/collection/immutable/Seq;)Ljava/lang/Object;
  #127 = Utf8               Lscala/collection/immutable/Seq;
  #128 = Utf8               iterableFactory
  #129 = Utf8               ()Lscala/collection/Factory;
  #130 = Utf8               <A:Ljava/lang/Object;>()Lscala/collection/Factory<TA;TCC;>;
  #131 = Utf8               iterableFactory$
  #132 = Utf8               (Lscala/collection/IterableFactory;)Lscala/collection/Factory;
  #133 = NameAndType        #131:#132     // iterableFactory$:(Lscala/collection/IterableFactory;)Lscala/collection/Factory;
  #134 = InterfaceMethodref #34.#133      // scala/collection/IterableFactory.iterableFactory$:(Lscala/collection/IterableFactory;)Lscala/collection/Factory;
  #135 = Utf8               apply
  #136 = Utf8               (Lscala/collection/immutable/Seq;)Lscala/collection/SeqOps;
  #137 = Utf8               <A:Ljava/lang/Object;>(Lscala/collection/immutable/Seq<TA;>;)TCC;
  #138 = Utf8               elems
  #139 = NameAndType        #14:#15       // delegate:Lscala/collection/SeqFactory;
  #140 = Fieldref           #2.#139       // scala/collection/SeqFactory$Delegate.delegate:Lscala/collection/SeqFactory;
  #141 = NameAndType        #135:#121     // apply:(Lscala/collection/immutable/Seq;)Ljava/lang/Object;
  #142 = InterfaceMethodref #7.#141       // scala/collection/SeqFactory.apply:(Lscala/collection/immutable/Seq;)Ljava/lang/Object;
  #143 = Utf8               scala/collection/SeqOps
  #144 = Class              #143          // scala/collection/SeqOps
  #145 = Utf8               empty
  #146 = Utf8               ()Lscala/collection/SeqOps;
  #147 = Utf8               <A:Ljava/lang/Object;>()TCC;
  #148 = Utf8               ()Ljava/lang/Object;
  #149 = NameAndType        #145:#148     // empty:()Ljava/lang/Object;
  #150 = InterfaceMethodref #7.#149       // scala/collection/SeqFactory.empty:()Ljava/lang/Object;
  #151 = Utf8               from
  #152 = Utf8               (Lscala/collection/IterableOnce;)Lscala/collection/SeqOps;
  #153 = Utf8               <E:Ljava/lang/Object;>(Lscala/collection/IterableOnce<TE;>;)TCC;
  #154 = Utf8               it
  #155 = Utf8               (Lscala/collection/IterableOnce;)Ljava/lang/Object;
  #156 = NameAndType        #151:#155     // from:(Lscala/collection/IterableOnce;)Ljava/lang/Object;
  #157 = InterfaceMethodref #7.#156       // scala/collection/SeqFactory.from:(Lscala/collection/IterableOnce;)Ljava/lang/Object;
  #158 = Utf8               Lscala/collection/IterableOnce;
  #159 = Utf8               newBuilder
  #160 = Utf8               ()Lscala/collection/mutable/Builder;
  #161 = Utf8               <A:Ljava/lang/Object;>()Lscala/collection/mutable/Builder<TA;TCC;>;
  #162 = NameAndType        #159:#160     // newBuilder:()Lscala/collection/mutable/Builder;
  #163 = InterfaceMethodref #7.#162       // scala/collection/SeqFactory.newBuilder:()Lscala/collection/mutable/Builder;
  #164 = Utf8               source
  #165 = NameAndType        #151:#152     // from:(Lscala/collection/IterableOnce;)Lscala/collection/SeqOps;
  #166 = Methodref          #2.#165       // scala/collection/SeqFactory$Delegate.from:(Lscala/collection/IterableOnce;)Lscala/collection/SeqOps;
  #167 = NameAndType        #145:#146     // empty:()Lscala/collection/SeqOps;
  #168 = Methodref          #2.#167       // scala/collection/SeqFactory$Delegate.empty:()Lscala/collection/SeqOps;
  #169 = NameAndType        #135:#136     // apply:(Lscala/collection/immutable/Seq;)Lscala/collection/SeqOps;
  #170 = Methodref          #2.#169       // scala/collection/SeqFactory$Delegate.apply:(Lscala/collection/immutable/Seq;)Lscala/collection/SeqOps;
  #171 = Utf8               <init>
  #172 = Utf8               (Lscala/collection/SeqFactory;)V
  #173 = Utf8               (Lscala/collection/SeqFactory<TCC;>;)V
  #174 = Utf8               ()V
  #175 = NameAndType        #171:#174     // "<init>":()V
  #176 = Methodref          #5.#175       // java/lang/Object."<init>":()V
  #177 = Utf8               ConstantValue
  #178 = Utf8               Signature
  #179 = Utf8               Code
  #180 = Utf8               LineNumberTable
  #181 = Utf8               LocalVariableTable
  #182 = Utf8               MethodParameters
  #183 = Utf8               InnerClasses
  #184 = Utf8               SourceFile
  #185 = Utf8               ScalaInlineInfo
  #186 = Utf8               Scala
{
  private static final long serialVersionUID;
    descriptor: J
    flags: (0x001a) ACC_PRIVATE, ACC_STATIC, ACC_FINAL
    ConstantValue: long 3l

  private final scala.collection.SeqFactory<CC> delegate;
    descriptor: Lscala/collection/SeqFactory;
    flags: (0x0012) ACC_PRIVATE, ACC_FINAL
    Signature: #16                          // Lscala/collection/SeqFactory<TCC;>;

  public final <A extends java.lang.Object> scala.collection.SeqOps<A, scala.collection.Seq, scala.collection.Seq<A>> unapplySeq(CC);
    descriptor: (Lscala/collection/SeqOps;)Lscala/collection/SeqOps;
    flags: (0x0011) ACC_PUBLIC, ACC_FINAL
    Code:
      stack=2, locals=2, args_size=2
         0: aload_0
         1: aload_1
         2: invokestatic  #24                 // InterfaceMethod scala/collection/SeqFactory.unapplySeq$:(Lscala/collection/SeqFactory;Lscala/collection/SeqOps;)Lscala/collection/SeqOps;
         5: areturn
      LineNumberTable:
        line 303: 0
      LocalVariableTable:
        Start  Length  Slot  Name   Signature
            0       6     0  this   Lscala/collection/SeqFactory$Delegate;
            0       6     1     x   Lscala/collection/SeqOps;
    Signature: #19                          // <A:Ljava/lang/Object;>(TCC;)Lscala/collection/SeqOps<TA;Lscala/collection/Seq;Lscala/collection/Seq<TA;>;>;
    MethodParameters:
      Name                           Flags
      x                              final

  public java.lang.Object iterate(java.lang.Object, int, scala.Function1);
    descriptor: (Ljava/lang/Object;ILscala/Function1;)Ljava/lang/Object;
    flags: (0x0001) ACC_PUBLIC
    Code:
      stack=4, locals=4, args_size=4
         0: aload_0
         1: aload_1
         2: iload_2
         3: aload_3
         4: invokestatic  #38                 // InterfaceMethod scala/collection/IterableFactory.iterate$:(Lscala/collection/IterableFactory;Ljava/lang/Object;ILscala/Function1;)Ljava/lang/Object;
         7: areturn
      LineNumberTable:
        line 303: 0
      LocalVariableTable:
        Start  Length  Slot  Name   Signature
            0       8     0  this   Lscala/collection/SeqFactory$Delegate;
            0       8     1 start   Ljava/lang/Object;
            0       8     2   len   I
            0       8     3     f   Lscala/Function1;
    MethodParameters:
      Name                           Flags
      start                          final
      len                            final
      f                              final

  public java.lang.Object unfold(java.lang.Object, scala.Function1);
    descriptor: (Ljava/lang/Object;Lscala/Function1;)Ljava/lang/Object;
    flags: (0x0001) ACC_PUBLIC
    Code:
      stack=3, locals=3, args_size=3
         0: aload_0
         1: aload_1
         2: aload_2
         3: invokestatic  #48                 // InterfaceMethod scala/collection/IterableFactory.unfold$:(Lscala/collection/IterableFactory;Ljava/lang/Object;Lscala/Function1;)Ljava/lang/Object;
         6: areturn
      LineNumberTable:
        line 303: 0
      LocalVariableTable:
        Start  Length  Slot  Name   Signature
            0       7     0  this   Lscala/collection/SeqFactory$Delegate;
            0       7     1  init   Ljava/lang/Object;
            0       7     2     f   Lscala/Function1;
    MethodParameters:
      Name                           Flags
      init                           final
      f                              final

  public java.lang.Object range(java.lang.Object, java.lang.Object, scala.math.Integral);
    descriptor: (Ljava/lang/Object;Ljava/lang/Object;Lscala/math/Integral;)Ljava/lang/Object;
    flags: (0x0001) ACC_PUBLIC
    Code:
      stack=4, locals=4, args_size=4
         0: aload_0
         1: aload_1
         2: aload_2
         3: aload_3
         4: invokestatic  #56                 // InterfaceMethod scala/collection/IterableFactory.range$:(Lscala/collection/IterableFactory;Ljava/lang/Object;Ljava/lang/Object;Lscala/math/Integral;)Ljava/lang/Object;
         7: areturn
      LineNumberTable:
        line 303: 0
      LocalVariableTable:
        Start  Length  Slot  Name   Signature
            0       8     0  this   Lscala/collection/SeqFactory$Delegate;
            0       8     1 start   Ljava/lang/Object;
            0       8     2   end   Ljava/lang/Object;
            0       8     3 evidence$3   Lscala/math/Integral;
    MethodParameters:
      Name                           Flags
      start                          final
      end                            final
      evidence$3                     final

  public java.lang.Object range(java.lang.Object, java.lang.Object, java.lang.Object, scala.math.Integral);
    descriptor: (Ljava/lang/Object;Ljava/lang/Object;Ljava/lang/Object;Lscala/math/Integral;)Ljava/lang/Object;
    flags: (0x0001) ACC_PUBLIC
    Code:
      stack=5, locals=5, args_size=5
         0: aload_0
         1: aload_1
         2: aload_2
         3: aload_3
         4: aload         4
         6: invokestatic  #63                 // InterfaceMethod scala/collection/IterableFactory.range$:(Lscala/collection/IterableFactory;Ljava/lang/Object;Ljava/lang/Object;Ljava/lang/Object;Lscala/math/Integral;)Ljava/lang/Object;
         9: areturn
      LineNumberTable:
        line 303: 0
      LocalVariableTable:
        Start  Length  Slot  Name   Signature
            0      10     0  this   Lscala/collection/SeqFactory$Delegate;
            0      10     1 start   Ljava/lang/Object;
            0      10     2   end   Ljava/lang/Object;
            0      10     3  step   Ljava/lang/Object;
            0      10     4 evidence$4   Lscala/math/Integral;
    MethodParameters:
      Name                           Flags
      start                          final
      end                            final
      step                           final
      evidence$4                     final

  public java.lang.Object fill(int, scala.Function0);
    descriptor: (ILscala/Function0;)Ljava/lang/Object;
    flags: (0x0001) ACC_PUBLIC
    Code:
      stack=3, locals=3, args_size=3
         0: aload_0
         1: iload_1
         2: aload_2
         3: invokestatic  #71                 // InterfaceMethod scala/collection/IterableFactory.fill$:(Lscala/collection/IterableFactory;ILscala/Function0;)Ljava/lang/Object;
         6: areturn
      LineNumberTable:
        line 303: 0
      LocalVariableTable:
        Start  Length  Slot  Name   Signature
            0       7     0  this   Lscala/collection/SeqFactory$Delegate;
            0       7     1     n   I
            0       7     2  elem   Lscala/Function0;
    MethodParameters:
      Name                           Flags
      n                              final
      elem                           final

  public java.lang.Object fill(int, int, scala.Function0);
    descriptor: (IILscala/Function0;)Ljava/lang/Object;
    flags: (0x0001) ACC_PUBLIC
    Code:
      stack=4, locals=4, args_size=4
         0: aload_0
         1: iload_1
         2: iload_2
         3: aload_3
         4: invokestatic  #78                 // InterfaceMethod scala/collection/IterableFactory.fill$:(Lscala/collection/IterableFactory;IILscala/Function0;)Ljava/lang/Object;
         7: areturn
      LineNumberTable:
        line 303: 0
      LocalVariableTable:
        Start  Length  Slot  Name   Signature
            0       8     0  this   Lscala/collection/SeqFactory$Delegate;
            0       8     1    n1   I
            0       8     2    n2   I
            0       8     3  elem   Lscala/Function0;
    MethodParameters:
      Name                           Flags
      n1                             final
      n2                             final
      elem                           final

  public java.lang.Object fill(int, int, int, scala.Function0);
    descriptor: (IIILscala/Function0;)Ljava/lang/Object;
    flags: (0x0001) ACC_PUBLIC
    Code:
      stack=5, locals=5, args_size=5
         0: aload_0
         1: iload_1
         2: iload_2
         3: iload_3
         4: aload         4
         6: invokestatic  #83                 // InterfaceMethod scala/collection/IterableFactory.fill$:(Lscala/collection/IterableFactory;IIILscala/Function0;)Ljava/lang/Object;
         9: areturn
      LineNumberTable:
        line 303: 0
      LocalVariableTable:
        Start  Length  Slot  Name   Signature
            0      10     0  this   Lscala/collection/SeqFactory$Delegate;
            0      10     1    n1   I
            0      10     2    n2   I
            0      10     3    n3   I
            0      10     4  elem   Lscala/Function0;
    MethodParameters:
      Name                           Flags
      n1                             final
      n2                             final
      n3                             final
      elem                           final

  public java.lang.Object fill(int, int, int, int, scala.Function0);
    descriptor: (IIIILscala/Function0;)Ljava/lang/Object;
    flags: (0x0001) ACC_PUBLIC
    Code:
      stack=6, locals=6, args_size=6
         0: aload_0
         1: iload_1
         2: iload_2
         3: iload_3
         4: iload         4
         6: aload         5
         8: invokestatic  #88                 // InterfaceMethod scala/collection/IterableFactory.fill$:(Lscala/collection/IterableFactory;IIIILscala/Function0;)Ljava/lang/Object;
        11: areturn
      LineNumberTable:
        line 303: 0
      LocalVariableTable:
        Start  Length  Slot  Name   Signature
            0      12     0  this   Lscala/collection/SeqFactory$Delegate;
            0      12     1    n1   I
            0      12     2    n2   I
            0      12     3    n3   I
            0      12     4    n4   I
            0      12     5  elem   Lscala/Function0;
    MethodParameters:
      Name                           Flags
      n1                             final
      n2                             final
      n3                             final
      n4                             final
      elem                           final

  public java.lang.Object fill(int, int, int, int, int, scala.Function0);
    descriptor: (IIIIILscala/Function0;)Ljava/lang/Object;
    flags: (0x0001) ACC_PUBLIC
    Code:
      stack=7, locals=7, args_size=7
         0: aload_0
         1: iload_1
         2: iload_2
         3: iload_3
         4: iload         4
         6: iload         5
         8: aload         6
        10: invokestatic  #93                 // InterfaceMethod scala/collection/IterableFactory.fill$:(Lscala/collection/IterableFactory;IIIIILscala/Function0;)Ljava/lang/Object;
        13: areturn
      LineNumberTable:
        line 303: 0
      LocalVariableTable:
        Start  Length  Slot  Name   Signature
            0      14     0  this   Lscala/collection/SeqFactory$Delegate;
            0      14     1    n1   I
            0      14     2    n2   I
            0      14     3    n3   I
            0      14     4    n4   I
            0      14     5    n5   I
            0      14     6  elem   Lscala/Function0;
    MethodParameters:
      Name                           Flags
      n1                             final
      n2                             final
      n3                             final
      n4                             final
      n5                             final
      elem                           final

  public java.lang.Object tabulate(int, scala.Function1);
    descriptor: (ILscala/Function1;)Ljava/lang/Object;
    flags: (0x0001) ACC_PUBLIC
    Code:
      stack=3, locals=3, args_size=3
         0: aload_0
         1: iload_1
         2: aload_2
         3: invokestatic  #99                 // InterfaceMethod scala/collection/IterableFactory.tabulate$:(Lscala/collection/IterableFactory;ILscala/Function1;)Ljava/lang/Object;
         6: areturn
      LineNumberTable:
        line 303: 0
      LocalVariableTable:
        Start  Length  Slot  Name   Signature
            0       7     0  this   Lscala/collection/SeqFactory$Delegate;
            0       7     1     n   I
            0       7     2     f   Lscala/Function1;
    MethodParameters:
      Name                           Flags
      n                              final
      f                              final

  public java.lang.Object tabulate(int, int, scala.Function2);
    descriptor: (IILscala/Function2;)Ljava/lang/Object;
    flags: (0x0001) ACC_PUBLIC
    Code:
      stack=4, locals=4, args_size=4
         0: aload_0
         1: iload_1
         2: iload_2
         3: aload_3
         4: invokestatic  #103                // InterfaceMethod scala/collection/IterableFactory.tabulate$:(Lscala/collection/IterableFactory;IILscala/Function2;)Ljava/lang/Object;
         7: areturn
      LineNumberTable:
        line 303: 0
      LocalVariableTable:
        Start  Length  Slot  Name   Signature
            0       8     0  this   Lscala/collection/SeqFactory$Delegate;
            0       8     1    n1   I
            0       8     2    n2   I
            0       8     3     f   Lscala/Function2;
    MethodParameters:
      Name                           Flags
      n1                             final
      n2                             final
      f                              final

  public java.lang.Object tabulate(int, int, int, scala.Function3);
    descriptor: (IIILscala/Function3;)Ljava/lang/Object;
    flags: (0x0001) ACC_PUBLIC
    Code:
      stack=5, locals=5, args_size=5
         0: aload_0
         1: iload_1
         2: iload_2
         3: iload_3
         4: aload         4
         6: invokestatic  #108                // InterfaceMethod scala/collection/IterableFactory.tabulate$:(Lscala/collection/IterableFactory;IIILscala/Function3;)Ljava/lang/Object;
         9: areturn
      LineNumberTable:
        line 303: 0
      LocalVariableTable:
        Start  Length  Slot  Name   Signature
            0      10     0  this   Lscala/collection/SeqFactory$Delegate;
            0      10     1    n1   I
            0      10     2    n2   I
            0      10     3    n3   I
            0      10     4     f   Lscala/Function3;
    MethodParameters:
      Name                           Flags
      n1                             final
      n2                             final
      n3                             final
      f                              final

  public java.lang.Object tabulate(int, int, int, int, scala.Function4);
    descriptor: (IIIILscala/Function4;)Ljava/lang/Object;
    flags: (0x0001) ACC_PUBLIC
    Code:
      stack=6, locals=6, args_size=6
         0: aload_0
         1: iload_1
         2: iload_2
         3: iload_3
         4: iload         4
         6: aload         5
         8: invokestatic  #113                // InterfaceMethod scala/collection/IterableFactory.tabulate$:(Lscala/collection/IterableFactory;IIIILscala/Function4;)Ljava/lang/Object;
        11: areturn
      LineNumberTable:
        line 303: 0
      LocalVariableTable:
        Start  Length  Slot  Name   Signature
            0      12     0  this   Lscala/collection/SeqFactory$Delegate;
            0      12     1    n1   I
            0      12     2    n2   I
            0      12     3    n3   I
            0      12     4    n4   I
            0      12     5     f   Lscala/Function4;
    MethodParameters:
      Name                           Flags
      n1                             final
      n2                             final
      n3                             final
      n4                             final
      f                              final

  public java.lang.Object tabulate(int, int, int, int, int, scala.Function5);
    descriptor: (IIIIILscala/Function5;)Ljava/lang/Object;
    flags: (0x0001) ACC_PUBLIC
    Code:
      stack=7, locals=7, args_size=7
         0: aload_0
         1: iload_1
         2: iload_2
         3: iload_3
         4: iload         4
         6: iload         5
         8: aload         6
        10: invokestatic  #118                // InterfaceMethod scala/collection/IterableFactory.tabulate$:(Lscala/collection/IterableFactory;IIIIILscala/Function5;)Ljava/lang/Object;
        13: areturn
      LineNumberTable:
        line 303: 0
      LocalVariableTable:
        Start  Length  Slot  Name   Signature
            0      14     0  this   Lscala/collection/SeqFactory$Delegate;
            0      14     1    n1   I
            0      14     2    n2   I
            0      14     3    n3   I
            0      14     4    n4   I
            0      14     5    n5   I
            0      14     6     f   Lscala/Function5;
    MethodParameters:
      Name                           Flags
      n1                             final
      n2                             final
      n3                             final
      n4                             final
      n5                             final
      f                              final

  public java.lang.Object concat(scala.collection.immutable.Seq);
    descriptor: (Lscala/collection/immutable/Seq;)Ljava/lang/Object;
    flags: (0x0001) ACC_PUBLIC
    Code:
      stack=2, locals=2, args_size=2
         0: aload_0
         1: aload_1
         2: invokestatic  #126                // InterfaceMethod scala/collection/IterableFactory.concat$:(Lscala/collection/IterableFactory;Lscala/collection/immutable/Seq;)Ljava/lang/Object;
         5: areturn
      LineNumberTable:
        line 303: 0
      LocalVariableTable:
        Start  Length  Slot  Name   Signature
            0       6     0  this   Lscala/collection/SeqFactory$Delegate;
            0       6     1   xss   Lscala/collection/immutable/Seq;
    MethodParameters:
      Name                           Flags
      xss                            final

  public <A extends java.lang.Object> scala.collection.Factory<A, CC> iterableFactory();
    descriptor: ()Lscala/collection/Factory;
    flags: (0x0001) ACC_PUBLIC
    Code:
      stack=1, locals=1, args_size=1
         0: aload_0
         1: invokestatic  #134                // InterfaceMethod scala/collection/IterableFactory.iterableFactory$:(Lscala/collection/IterableFactory;)Lscala/collection/Factory;
         4: areturn
      LineNumberTable:
        line 303: 0
      LocalVariableTable:
        Start  Length  Slot  Name   Signature
            0       5     0  this   Lscala/collection/SeqFactory$Delegate;
    Signature: #130                         // <A:Ljava/lang/Object;>()Lscala/collection/Factory<TA;TCC;>;

  public <A extends java.lang.Object> CC apply(scala.collection.immutable.Seq<A>);
    descriptor: (Lscala/collection/immutable/Seq;)Lscala/collection/SeqOps;
    flags: (0x0001) ACC_PUBLIC
    Code:
      stack=2, locals=2, args_size=2
         0: aload_0
         1: getfield      #140                // Field delegate:Lscala/collection/SeqFactory;
         4: aload_1
         5: invokeinterface #142,  2          // InterfaceMethod scala/collection/SeqFactory.apply:(Lscala/collection/immutable/Seq;)Ljava/lang/Object;
        10: checkcast     #144                // class scala/collection/SeqOps
        13: areturn
      LineNumberTable:
        line 304: 0
      LocalVariableTable:
        Start  Length  Slot  Name   Signature
            0      14     0  this   Lscala/collection/SeqFactory$Delegate;
            0      14     1 elems   Lscala/collection/immutable/Seq;
    Signature: #137                         // <A:Ljava/lang/Object;>(Lscala/collection/immutable/Seq<TA;>;)TCC;
    MethodParameters:
      Name                           Flags
      elems                          final

  public <A extends java.lang.Object> CC empty();
    descriptor: ()Lscala/collection/SeqOps;
    flags: (0x0001) ACC_PUBLIC
    Code:
      stack=1, locals=1, args_size=1
         0: aload_0
         1: getfield      #140                // Field delegate:Lscala/collection/SeqFactory;
         4: invokeinterface #150,  1          // InterfaceMethod scala/collection/SeqFactory.empty:()Ljava/lang/Object;
         9: checkcast     #144                // class scala/collection/SeqOps
        12: areturn
      LineNumberTable:
        line 305: 0
      LocalVariableTable:
        Start  Length  Slot  Name   Signature
            0      13     0  this   Lscala/collection/SeqFactory$Delegate;
    Signature: #147                         // <A:Ljava/lang/Object;>()TCC;

  public <E extends java.lang.Object> CC from(scala.collection.IterableOnce<E>);
    descriptor: (Lscala/collection/IterableOnce;)Lscala/collection/SeqOps;
    flags: (0x0001) ACC_PUBLIC
    Code:
      stack=2, locals=2, args_size=2
         0: aload_0
         1: getfield      #140                // Field delegate:Lscala/collection/SeqFactory;
         4: aload_1
         5: invokeinterface #157,  2          // InterfaceMethod scala/collection/SeqFactory.from:(Lscala/collection/IterableOnce;)Ljava/lang/Object;
        10: checkcast     #144                // class scala/collection/SeqOps
        13: areturn
      LineNumberTable:
        line 306: 0
      LocalVariableTable:
        Start  Length  Slot  Name   Signature
            0      14     0  this   Lscala/collection/SeqFactory$Delegate;
            0      14     1    it   Lscala/collection/IterableOnce;
    Signature: #153                         // <E:Ljava/lang/Object;>(Lscala/collection/IterableOnce<TE;>;)TCC;
    MethodParameters:
      Name                           Flags
      it                             final

  public <A extends java.lang.Object> scala.collection.mutable.Builder<A, CC> newBuilder();
    descriptor: ()Lscala/collection/mutable/Builder;
    flags: (0x0001) ACC_PUBLIC
    Code:
      stack=1, locals=1, args_size=1
         0: aload_0
         1: getfield      #140                // Field delegate:Lscala/collection/SeqFactory;
         4: invokeinterface #163,  1          // InterfaceMethod scala/collection/SeqFactory.newBuilder:()Lscala/collection/mutable/Builder;
         9: areturn
      LineNumberTable:
        line 307: 0
      LocalVariableTable:
        Start  Length  Slot  Name   Signature
            0      10     0  this   Lscala/collection/SeqFactory$Delegate;
    Signature: #161                         // <A:Ljava/lang/Object;>()Lscala/collection/mutable/Builder<TA;TCC;>;

  public java.lang.Object from(scala.collection.IterableOnce);
    descriptor: (Lscala/collection/IterableOnce;)Ljava/lang/Object;
    flags: (0x1041) ACC_PUBLIC, ACC_BRIDGE, ACC_SYNTHETIC
    Code:
      stack=2, locals=2, args_size=2
         0: aload_0
         1: aload_1
         2: invokevirtual #166                // Method from:(Lscala/collection/IterableOnce;)Lscala/collection/SeqOps;
         5: areturn
      LineNumberTable:
        line 303: 0
      LocalVariableTable:
        Start  Length  Slot  Name   Signature
            0       6     0  this   Lscala/collection/SeqFactory$Delegate;
            0       6     1 source   Lscala/collection/IterableOnce;
    MethodParameters:
      Name                           Flags
      source                         final

  public java.lang.Object empty();
    descriptor: ()Ljava/lang/Object;
    flags: (0x1041) ACC_PUBLIC, ACC_BRIDGE, ACC_SYNTHETIC
    Code:
      stack=1, locals=1, args_size=1
         0: aload_0
         1: invokevirtual #168                // Method empty:()Lscala/collection/SeqOps;
         4: areturn
      LineNumberTable:
        line 303: 0
      LocalVariableTable:
        Start  Length  Slot  Name   Signature
            0       5     0  this   Lscala/collection/SeqFactory$Delegate;

  public java.lang.Object apply(scala.collection.immutable.Seq);
    descriptor: (Lscala/collection/immutable/Seq;)Ljava/lang/Object;
    flags: (0x1041) ACC_PUBLIC, ACC_BRIDGE, ACC_SYNTHETIC
    Code:
      stack=2, locals=2, args_size=2
         0: aload_0
         1: aload_1
         2: invokevirtual #170                // Method apply:(Lscala/collection/immutable/Seq;)Lscala/collection/SeqOps;
         5: areturn
      LineNumberTable:
        line 303: 0
      LocalVariableTable:
        Start  Length  Slot  Name   Signature
            0       6     0  this   Lscala/collection/SeqFactory$Delegate;
            0       6     1 elems   Lscala/collection/immutable/Seq;
    MethodParameters:
      Name                           Flags
      elems                          final

  public scala.collection.SeqFactory$Delegate(scala.collection.SeqFactory<CC>);
    descriptor: (Lscala/collection/SeqFactory;)V
    flags: (0x0001) ACC_PUBLIC
    Code:
      stack=2, locals=2, args_size=2
         0: aload_0
         1: aload_1
         2: putfield      #140                // Field delegate:Lscala/collection/SeqFactory;
         5: aload_0
         6: invokespecial #176                // Method java/lang/Object."<init>":()V
         9: return
      LineNumberTable:
        line 303: 0
        line 83: 9
      LocalVariableTable:
        Start  Length  Slot  Name   Signature
            0      10     0  this   Lscala/collection/SeqFactory$Delegate;
            0      10     1 delegate   Lscala/collection/SeqFactory;
    Signature: #173                         // (Lscala/collection/SeqFactory<TCC;>;)V
    MethodParameters:
      Name                           Flags
      delegate                       final
}
InnerClasses:
  public static #9= #2 of #7;             // Delegate=class scala/collection/SeqFactory$Delegate of class scala/collection/SeqFactory
Signature: #3                           // <CC::Lscala/collection/SeqOps<Ljava/lang/Object;Lscala/collection/Seq;Lscala/collection/Seq<Ljava/lang/Object;>;>;>Ljava/lang/Object;Lscala/collection/SeqFactory<TCC;>;
SourceFile: "Factory.scala"
  ScalaInlineInfo: length = 0x81 (unknown attribute)
   01 00 00 19 00 AB 00 AC 00 00 87 00 79 00 00 87
   00 88 00 00 78 00 79 00 00 91 00 94 00 00 91 00
   92 00 00 40 00 59 00 00 40 00 54 00 00 40 00 4F
   00 00 40 00 49 00 00 40 00 41 00 00 97 00 9B 00
   00 97 00 98 00 00 80 00 81 00 00 1C 00 1D 00 00
   9F 00 A0 00 00 31 00 3A 00 00 31 00 32 00 00 5E
   00 73 00 00 5E 00 6E 00 00 5E 00 69 00 00 5E 00
   64 00 00 5E 00 5F 00 00 11 00 12 01 00 2A 00 2B
   00
  Scala: length = 0x0 (unknown attribute)

