Classfile /Users/mw/Projects/slang-braindump/.jar/jar11/assemble/slang-braindump/assemble/content/scala/collection/SeqView$Reverse.class
  Last modified May 29, 2022; size 1550 bytes
  SHA-256 checksum f3bd396fd799a958becbd4a4ea39652ec803b12d6781bb5a0d3fb43d42da5313
  Compiled from "SeqView.scala"
public class scala.collection.SeqView$Reverse<A extends java.lang.Object> extends scala.collection.AbstractSeqView<A>
  minor version: 0
  major version: 52
  flags: (0x0021) ACC_PUBLIC, ACC_SUPER
  this_class: #2                          // scala/collection/SeqView$Reverse
  super_class: #5                         // scala/collection/AbstractSeqView
  interfaces: 0, fields: 2, methods: 6, attributes: 5
Constant pool:
   #1 = Utf8               scala/collection/SeqView$Reverse
   #2 = Class              #1             // scala/collection/SeqView$Reverse
   #3 = Utf8               <A:Ljava/lang/Object;>Lscala/collection/AbstractSeqView<TA;>;
   #4 = Utf8               scala/collection/AbstractSeqView
   #5 = Class              #4             // scala/collection/AbstractSeqView
   #6 = Utf8               SeqView.scala
   #7 = Utf8               scala/collection/SeqView
   #8 = Class              #7             // scala/collection/SeqView
   #9 = Utf8               Reverse
  #10 = Utf8               serialVersionUID
  #11 = Utf8               J
  #12 = Long               3l
  #14 = Utf8               underlying
  #15 = Utf8               Lscala/collection/SeqOps;
  #16 = Utf8               Lscala/collection/SeqOps<TA;*Ljava/lang/Object;>;
  #17 = Utf8               apply
  #18 = Utf8               (I)Ljava/lang/Object;
  #19 = Utf8               (I)TA;
  #20 = Utf8               i
  #21 = NameAndType        #14:#15        // underlying:Lscala/collection/SeqOps;
  #22 = Fieldref           #2.#21         // scala/collection/SeqView$Reverse.underlying:Lscala/collection/SeqOps;
  #23 = Utf8               scala/collection/SeqOps
  #24 = Class              #23            // scala/collection/SeqOps
  #25 = Utf8               length
  #26 = Utf8               ()I
  #27 = NameAndType        #25:#26        // length:()I
  #28 = InterfaceMethodref #24.#27        // scala/collection/SeqOps.length:()I
  #29 = NameAndType        #17:#18        // apply:(I)Ljava/lang/Object;
  #30 = InterfaceMethodref #24.#29        // scala/collection/SeqOps.apply:(I)Ljava/lang/Object;
  #31 = Utf8               this
  #32 = Utf8               Lscala/collection/SeqView$Reverse;
  #33 = Utf8               I
  #34 = Utf8               iterator
  #35 = Utf8               ()Lscala/collection/Iterator;
  #36 = Utf8               ()Lscala/collection/Iterator<TA;>;
  #37 = Utf8               reverseIterator
  #38 = NameAndType        #37:#35        // reverseIterator:()Lscala/collection/Iterator;
  #39 = InterfaceMethodref #24.#38        // scala/collection/SeqOps.reverseIterator:()Lscala/collection/Iterator;
  #40 = Utf8               knownSize
  #41 = NameAndType        #40:#26        // knownSize:()I
  #42 = InterfaceMethodref #24.#41        // scala/collection/SeqOps.knownSize:()I
  #43 = Utf8               isEmpty
  #44 = Utf8               ()Z
  #45 = NameAndType        #43:#44        // isEmpty:()Z
  #46 = InterfaceMethodref #24.#45        // scala/collection/SeqOps.isEmpty:()Z
  #47 = Utf8               <init>
  #48 = Utf8               (Lscala/collection/SeqOps;)V
  #49 = Utf8               (Lscala/collection/SeqOps<TA;*Ljava/lang/Object;>;)V
  #50 = Utf8               ()V
  #51 = NameAndType        #47:#50        // "<init>":()V
  #52 = Methodref          #5.#51         // scala/collection/AbstractSeqView."<init>":()V
  #53 = Utf8               ConstantValue
  #54 = Utf8               Signature
  #55 = Utf8               Code
  #56 = Utf8               LineNumberTable
  #57 = Utf8               LocalVariableTable
  #58 = Utf8               MethodParameters
  #59 = Utf8               StackMapTable
  #60 = Utf8               InnerClasses
  #61 = Utf8               SourceFile
  #62 = Utf8               ScalaInlineInfo
  #63 = Utf8               Scala
{
  private static final long serialVersionUID;
    descriptor: J
    flags: (0x001a) ACC_PRIVATE, ACC_STATIC, ACC_FINAL
    ConstantValue: long 3l

  private final scala.collection.SeqOps<A, ?, java.lang.Object> underlying;
    descriptor: Lscala/collection/SeqOps;
    flags: (0x0012) ACC_PRIVATE, ACC_FINAL
    Signature: #16                          // Lscala/collection/SeqOps<TA;*Ljava/lang/Object;>;

  public A apply(int);
    descriptor: (I)Ljava/lang/Object;
    flags: (0x0001) ACC_PUBLIC
    Code:
      stack=3, locals=2, args_size=2
         0: aload_0
         1: getfield      #22                 // Field underlying:Lscala/collection/SeqOps;
         4: aload_0
         5: invokeinterface #28,  1           // InterfaceMethod scala/collection/SeqOps.length:()I
        10: iconst_1
        11: isub
        12: iload_1
        13: isub
        14: invokeinterface #30,  2           // InterfaceMethod scala/collection/SeqOps.apply:(I)Ljava/lang/Object;
        19: areturn
      LineNumberTable:
        line 86: 0
        line 209: 4
        line 86: 10
      LocalVariableTable:
        Start  Length  Slot  Name   Signature
            0      20     0  this   Lscala/collection/SeqView$Reverse;
            0      20     1     i   I
    Signature: #19                          // (I)TA;
    MethodParameters:
      Name                           Flags
      i                              final

  public int length();
    descriptor: ()I
    flags: (0x0001) ACC_PUBLIC
    Code:
      stack=2, locals=1, args_size=1
         0: aload_0
         1: getfield      #22                 // Field underlying:Lscala/collection/SeqOps;
         4: dup
         5: ifnonnull     10
         8: aconst_null
         9: athrow
        10: invokeinterface #28,  1           // InterfaceMethod scala/collection/SeqOps.length:()I
        15: ireturn
      StackMapTable: number_of_entries = 1
        frame_type = 74 /* same_locals_1_stack_item */
          stack = [ class scala/collection/SeqOps ]
      LineNumberTable:
        line 87: 0
      LocalVariableTable:
        Start  Length  Slot  Name   Signature
            0      16     0  this   Lscala/collection/SeqView$Reverse;

  public scala.collection.Iterator<A> iterator();
    descriptor: ()Lscala/collection/Iterator;
    flags: (0x0001) ACC_PUBLIC
    Code:
      stack=1, locals=1, args_size=1
         0: aload_0
         1: getfield      #22                 // Field underlying:Lscala/collection/SeqOps;
         4: invokeinterface #39,  1           // InterfaceMethod scala/collection/SeqOps.reverseIterator:()Lscala/collection/Iterator;
         9: areturn
      LineNumberTable:
        line 88: 0
      LocalVariableTable:
        Start  Length  Slot  Name   Signature
            0      10     0  this   Lscala/collection/SeqView$Reverse;
    Signature: #36                          // ()Lscala/collection/Iterator<TA;>;

  public int knownSize();
    descriptor: ()I
    flags: (0x0001) ACC_PUBLIC
    Code:
      stack=1, locals=1, args_size=1
         0: aload_0
         1: getfield      #22                 // Field underlying:Lscala/collection/SeqOps;
         4: invokeinterface #42,  1           // InterfaceMethod scala/collection/SeqOps.knownSize:()I
         9: ireturn
      LineNumberTable:
        line 89: 0
      LocalVariableTable:
        Start  Length  Slot  Name   Signature
            0      10     0  this   Lscala/collection/SeqView$Reverse;

  public boolean isEmpty();
    descriptor: ()Z
    flags: (0x0001) ACC_PUBLIC
    Code:
      stack=1, locals=1, args_size=1
         0: aload_0
         1: getfield      #22                 // Field underlying:Lscala/collection/SeqOps;
         4: invokeinterface #46,  1           // InterfaceMethod scala/collection/SeqOps.isEmpty:()Z
         9: ireturn
      LineNumberTable:
        line 90: 0
      LocalVariableTable:
        Start  Length  Slot  Name   Signature
            0      10     0  this   Lscala/collection/SeqView$Reverse;

  public scala.collection.SeqView$Reverse(scala.collection.SeqOps<A, ?, java.lang.Object>);
    descriptor: (Lscala/collection/SeqOps;)V
    flags: (0x0001) ACC_PUBLIC
    Code:
      stack=2, locals=2, args_size=2
         0: aload_0
         1: aload_1
         2: putfield      #22                 // Field underlying:Lscala/collection/SeqOps;
         5: aload_0
         6: invokespecial #52                 // Method scala/collection/AbstractSeqView."<init>":()V
         9: return
      LineNumberTable:
        line 85: 0
      LocalVariableTable:
        Start  Length  Slot  Name   Signature
            0      10     0  this   Lscala/collection/SeqView$Reverse;
            0      10     1 underlying   Lscala/collection/SeqOps;
    Signature: #49                          // (Lscala/collection/SeqOps<TA;*Ljava/lang/Object;>;)V
    MethodParameters:
      Name                           Flags
      underlying                     final
}
InnerClasses:
  public static #9= #2 of #8;             // Reverse=class scala/collection/SeqView$Reverse of class scala/collection/SeqView
Signature: #3                           // <A:Ljava/lang/Object;>Lscala/collection/AbstractSeqView<TA;>;
SourceFile: "SeqView.scala"
  ScalaInlineInfo: length = 0x22 (unknown attribute)
   01 00 00 06 00 2F 00 30 00 00 11 00 12 00 00 2B
   00 2C 00 00 22 00 23 00 00 28 00 1A 00 00 19 00
   1A 00
  Scala: length = 0x0 (unknown attribute)

