Classfile /Users/mw/Projects/slang-braindump/.jar/jar11/assemble/slang-braindump/assemble/content/scala/collection/SortedMapFactoryDefaults.class
  Last modified May 29, 2022; size 4381 bytes
  SHA-256 checksum 54e2f3b19933dd990119d62abece6b2aa57726f2e90b7123b1acb872d65c4bef
  Compiled from "Iterable.scala"
public interface scala.collection.SortedMapFactoryDefaults<K extends java.lang.Object, V extends java.lang.Object, CC extends scala.collection.SortedMapOps<java.lang.Object, java.lang.Object, CC, CC>, WithFilterCC extends scala.collection.Iterable<java.lang.Object>, UnsortedCC extends scala.collection.Map<java.lang.Object, java.lang.Object>> extends scala.collection.SortedMapOps<K, V, CC, CC>
  minor version: 0
  major version: 52
  flags: (0x0601) ACC_PUBLIC, ACC_INTERFACE, ACC_ABSTRACT
  this_class: #2                          // scala/collection/SortedMapFactoryDefaults
  super_class: #5                         // java/lang/Object
  interfaces: 1, fields: 0, methods: 9, attributes: 6
Constant pool:
   #1 = Utf8               scala/collection/SortedMapFactoryDefaults
   #2 = Class              #1             // scala/collection/SortedMapFactoryDefaults
   #3 = Utf8               <K:Ljava/lang/Object;V:Ljava/lang/Object;CC:Lscala/collection/SortedMapOps<Ljava/lang/Object;Ljava/lang/Object;TCC;TCC;>;WithFilterCC:Lscala/collection/Iterable<Ljava/lang/Object;>;UnsortedCC::Lscala/collection/Map<Ljava/lang/Object;Ljava/lang/Object;>;>Ljava/lang/Object;Lscala/collection/SortedMapOps<TK;TV;TCC;TCC;>;
   #4 = Utf8               java/lang/Object
   #5 = Class              #4             // java/lang/Object
   #6 = Utf8               scala/collection/SortedMapOps
   #7 = Class              #6             // scala/collection/SortedMapOps
   #8 = Utf8               Iterable.scala
   #9 = Utf8               Lscala/reflect/ScalaSignature;
  #10 = Utf8               bytes
  #11 = Utf8               \u0006\u0005\u0005-b!\u0003\u0004\b!\u0003\r\t\u0001DA\u000e\u0011\u0015\u0001\u0006\u0001\"\u0001R\u0011\u0015)\u0006\u0001\"\u0011W\u0011\u00159\u0006\u0001\"\u0015Y\u0011\u0015\t\u0007\u0001\"\u0015c\u0011\u0015I\u0007\u0001\"\u0011k\u0005a\u0019vN\u001d;fI6\u000b\u0007OR1di>\u0014\u0018\u0010R3gCVdGo\u001d\u0006\u0003\u0011%\t!bY8mY\u0016\u001cG/[8o\u0015\u0005Q\u0011!B:dC2\f7\u0001A\u000b\u0007\u001ba\u0011S%\u001e\u001d\u0014\t\u0001q!\u0003\u0014\t\u0003\u001fAi\u0011!C\u0005\u0003#%\u0011a!\u00118z%\u00164\u0007CB\n\u0015-\u0005\"\u0013)D\u0001\b\u0013\t)rA\u0001\u0007T_J$X\rZ\'ba>\u00038\u000f\u0005\u0002\u001811\u0001A!B\r\u0001\u0005\u0004Q\"!A&\u0012\u0005mq\u0002CA\b\u001d\u0013\ti\u0012BA\u0004O_RD\u0017N\\4\u0011\u0005=y\u0012B\u0001\u0011\n\u0005\r\te.\u001f\t\u0003/\t\"aa\t\u0001\u0005\u0006\u0004Q\"!\u0001,\u0011\u0005])CA\u0002\u0014\u0001\t\u000b\u0007qE\u0001\u0002D\u0007V\u0019\u0001\u0006M\u001a\u0012\u0005mI#\u0003\u0002\u0016-k]2Aa\u000b\u0001\u0001S\taAH]3gS:,W.\u001a8u}A!1#L\u00183\u0013\tqsAA\u0002NCB\u0004\"a\u0006\u0019\u0005\u000bE*#\u0019\u0001\u000e\u0003\u0003a\u0004\"aF\u001a\u0005\u000bQ*#\u0019\u0001\u000e\u0003\u0003e\u0004ba\u0005\u000b0e\u00112\u0004\u0003B\f&_I\u0002Ba\u0006\u001d0e\u00111\u0011\b\u0001CC\u0002i\u0012!\"\u00168t_J$X\rZ\"D+\rYd\bQ\t\u00037q\u0002BaE\u0017>\u007fA\u0011qC\u0010\u0003\u0006ca\u0012\rA\u0007\t\u0003/\u0001#Q\u0001\u000e\u001dC\u0002i\u0001BaF\u0013\u0017\u0005*\u0012\u0011eQ\u0016\u0002\tB\u0011QIS\u0007\u0002\r*\u0011q\tS\u0001\nk:\u001c\u0007.Z2lK\u0012T!!S\u0005\u0002\u0015\u0005tgn\u001c;bi&|g.\u0003\u0002L\r\n\tRO\\2iK\u000e\\W\r\u001a,be&\fgnY3\u0011\rMie#I(B\u0013\tquA\u0001\u0004NCB|\u0005o\u001d\t\u0003/a\na\u0001J5oSR$C#\u0001*\u0011\u0005=\u0019\u0016B\u0001+\n\u0005\u0011)f.\u001b;\u0002\u000b\u0015l\u0007\u000f^=\u0016\u0003\u0005\u000bAB\u001a:p[N\u0003XmY5gS\u000e$\"!Q-\t\u000bi\u001b\u0001\u0019A.\u0002\t\r|G\u000e\u001c\t\u0004\'qs\u0016BA/\b\u00051IE/\u001a:bE2,wJ\\2f!\u0011yqL\u0006\"\n\u0005\u0001L!A\u0002+va2,\'\'\u0001\noK^\u001c\u0006/Z2jM&\u001c\')^5mI\u0016\u0014X#A2\u0011\t\u0011<g,Q\u0007\u0002K*\u0011amB\u0001\b[V$\u0018M\u00197f\u0013\tAWMA\u0004Ck&dG-\u001a:\u0002\u0015]LG\u000f\u001b$jYR,\'\u000fF\u0002l\u0003\u0013\u0001r\u0001\\9\u0017CQ|EE\u0004\u0002n_:\u0011qB\\\u0005\u0003\u0011%I!\u0001]\u0004\u0002\u0019M{\'\u000f^3e\u001b\u0006\u0004x\n]:\n\u0005I\u001c(AC,ji\"4\u0015\u000e\u001c;fe*\u0011\u0001o\u0002\t\u0003/U$aA\u001e\u0001\u0005\u0006\u00049(\u0001D,ji\"4\u0015\u000e\u001c;fe\u000e\u001bUC\u0001=\u0000#\tY\u0012P\u0005\u0003{w\u0006\ra\u0001B\u0016\u0001\u0001e\u0004ba\u0005?\u007fi\u0006\u0005\u0011BA?\b\u0005-IE/\u001a:bE2,w\n]:\u0011\u0005]yH!B\u0019v\u0005\u0004Q\u0002cA\fv}B!1#!\u0002\u007f\u0013\r\t9a\u0002\u0002\t\u0013R,\'/\u00192mK\"9\u00111B\u0003A\u0002\u00055\u0011!\u00019\u0011\u000f=\ty!a\u0005\u0002\u0016%\u0019\u0011\u0011C\u0005\u0003\u0013\u0019+hn\u0019;j_:\f\u0004\u0003B\b`-\u0005\u00022aDA\f\u0013\r\tI\"\u0003\u0002\b\u0005>|G.Z1o%\u0019\ti\"a\b\u0002\"\u0019)1\u0006\u0001\u0001\u0002\u001cA91\u0003\u0001\f\"IQ|\u0005\u0007BA\u0012\u0003O\u0001ra\u0005?\u0002\u0014Q\f)\u0003E\u0002\u0018\u0003O!!\"!\u000b\u0001\u0003\u0003\u0005\tQ!\u0001\u001b\u0005\ryFE\u000e
  #12 = Utf8               scala/collection/SortedMapOps$WithFilter
  #13 = Class              #12            // scala/collection/SortedMapOps$WithFilter
  #14 = Utf8               WithFilter
  #15 = Utf8               empty$
  #16 = Utf8               (Lscala/collection/SortedMapFactoryDefaults;)Lscala/collection/SortedMapOps;
  #17 = Utf8               $this
  #18 = Utf8               empty
  #19 = Utf8               ()Lscala/collection/SortedMapOps;
  #20 = NameAndType        #18:#19        // empty:()Lscala/collection/SortedMapOps;
  #21 = InterfaceMethodref #2.#20         // scala/collection/SortedMapFactoryDefaults.empty:()Lscala/collection/SortedMapOps;
  #22 = Utf8               Lscala/collection/SortedMapFactoryDefaults;
  #23 = Utf8               ()TCC;
  #24 = Utf8               sortedMapFactory
  #25 = Utf8               ()Lscala/collection/SortedMapFactory;
  #26 = NameAndType        #24:#25        // sortedMapFactory:()Lscala/collection/SortedMapFactory;
  #27 = InterfaceMethodref #2.#26         // scala/collection/SortedMapFactoryDefaults.sortedMapFactory:()Lscala/collection/SortedMapFactory;
  #28 = Utf8               ordering
  #29 = Utf8               ()Lscala/math/Ordering;
  #30 = NameAndType        #28:#29        // ordering:()Lscala/math/Ordering;
  #31 = InterfaceMethodref #2.#30         // scala/collection/SortedMapFactoryDefaults.ordering:()Lscala/math/Ordering;
  #32 = Utf8               scala/collection/SortedMapFactory
  #33 = Class              #32            // scala/collection/SortedMapFactory
  #34 = Utf8               (Lscala/math/Ordering;)Ljava/lang/Object;
  #35 = NameAndType        #18:#34        // empty:(Lscala/math/Ordering;)Ljava/lang/Object;
  #36 = InterfaceMethodref #33.#35        // scala/collection/SortedMapFactory.empty:(Lscala/math/Ordering;)Ljava/lang/Object;
  #37 = Utf8               this
  #38 = Utf8               fromSpecific$
  #39 = Utf8               (Lscala/collection/SortedMapFactoryDefaults;Lscala/collection/IterableOnce;)Lscala/collection/SortedMapOps;
  #40 = Utf8               coll
  #41 = Utf8               fromSpecific
  #42 = Utf8               (Lscala/collection/IterableOnce;)Lscala/collection/SortedMapOps;
  #43 = NameAndType        #41:#42        // fromSpecific:(Lscala/collection/IterableOnce;)Lscala/collection/SortedMapOps;
  #44 = InterfaceMethodref #2.#43         // scala/collection/SortedMapFactoryDefaults.fromSpecific:(Lscala/collection/IterableOnce;)Lscala/collection/SortedMapOps;
  #45 = Utf8               Lscala/collection/IterableOnce;
  #46 = Utf8               (Lscala/collection/IterableOnce<Lscala/Tuple2<TK;TV;>;>;)TCC;
  #47 = Utf8               from
  #48 = Utf8               (Lscala/collection/IterableOnce;Lscala/math/Ordering;)Ljava/lang/Object;
  #49 = NameAndType        #47:#48        // from:(Lscala/collection/IterableOnce;Lscala/math/Ordering;)Ljava/lang/Object;
  #50 = InterfaceMethodref #33.#49        // scala/collection/SortedMapFactory.from:(Lscala/collection/IterableOnce;Lscala/math/Ordering;)Ljava/lang/Object;
  #51 = Utf8               newSpecificBuilder$
  #52 = Utf8               (Lscala/collection/SortedMapFactoryDefaults;)Lscala/collection/mutable/Builder;
  #53 = Utf8               newSpecificBuilder
  #54 = Utf8               ()Lscala/collection/mutable/Builder;
  #55 = NameAndType        #53:#54        // newSpecificBuilder:()Lscala/collection/mutable/Builder;
  #56 = InterfaceMethodref #2.#55         // scala/collection/SortedMapFactoryDefaults.newSpecificBuilder:()Lscala/collection/mutable/Builder;
  #57 = Utf8               ()Lscala/collection/mutable/Builder<Lscala/Tuple2<TK;TV;>;TCC;>;
  #58 = Utf8               newBuilder
  #59 = Utf8               (Lscala/math/Ordering;)Lscala/collection/mutable/Builder;
  #60 = NameAndType        #58:#59        // newBuilder:(Lscala/math/Ordering;)Lscala/collection/mutable/Builder;
  #61 = InterfaceMethodref #33.#60        // scala/collection/SortedMapFactory.newBuilder:(Lscala/math/Ordering;)Lscala/collection/mutable/Builder;
  #62 = Utf8               withFilter$
  #63 = Utf8               (Lscala/collection/SortedMapFactoryDefaults;Lscala/Function1;)Lscala/collection/SortedMapOps$WithFilter;
  #64 = Utf8               p
  #65 = Utf8               withFilter
  #66 = Utf8               (Lscala/Function1;)Lscala/collection/SortedMapOps$WithFilter;
  #67 = NameAndType        #65:#66        // withFilter:(Lscala/Function1;)Lscala/collection/SortedMapOps$WithFilter;
  #68 = InterfaceMethodref #2.#67         // scala/collection/SortedMapFactoryDefaults.withFilter:(Lscala/Function1;)Lscala/collection/SortedMapOps$WithFilter;
  #69 = Utf8               Lscala/Function1;
  #70 = Utf8               (Lscala/Function1<Lscala/Tuple2<TK;TV;>;Ljava/lang/Object;>;)Lscala/collection/SortedMapOps$WithFilter<TK;TV;TWithFilterCC;TUnsortedCC;TCC;>;
  #71 = Utf8               <init>
  #72 = Utf8               (Lscala/collection/SortedMapOps;Lscala/Function1;)V
  #73 = NameAndType        #71:#72        // "<init>":(Lscala/collection/SortedMapOps;Lscala/Function1;)V
  #74 = Methodref          #13.#73        // scala/collection/SortedMapOps$WithFilter."<init>":(Lscala/collection/SortedMapOps;Lscala/Function1;)V
  #75 = Utf8               $init$
  #76 = Utf8               (Lscala/collection/SortedMapFactoryDefaults;)V
  #77 = Utf8               Code
  #78 = Utf8               LineNumberTable
  #79 = Utf8               LocalVariableTable
  #80 = Utf8               MethodParameters
  #81 = Utf8               Signature
  #82 = Utf8               InnerClasses
  #83 = Utf8               SourceFile
  #84 = Utf8               RuntimeVisibleAnnotations
  #85 = Utf8               ScalaInlineInfo
  #86 = Utf8               ScalaSig
{
  public static scala.collection.SortedMapOps empty$(scala.collection.SortedMapFactoryDefaults);
    descriptor: (Lscala/collection/SortedMapFactoryDefaults;)Lscala/collection/SortedMapOps;
    flags: (0x1009) ACC_PUBLIC, ACC_STATIC, ACC_SYNTHETIC
    Code:
      stack=1, locals=1, args_size=1
         0: aload_0
         1: invokespecial #21                 // InterfaceMethod empty:()Lscala/collection/SortedMapOps;
         4: areturn
      LineNumberTable:
        line 1030: 0
      LocalVariableTable:
        Start  Length  Slot  Name   Signature
            0       5     0 $this   Lscala/collection/SortedMapFactoryDefaults;
    MethodParameters:
      Name                           Flags
      $this                          final synthetic

  public default CC empty();
    descriptor: ()Lscala/collection/SortedMapOps;
    flags: (0x0001) ACC_PUBLIC
    Code:
      stack=2, locals=1, args_size=1
         0: aload_0
         1: invokeinterface #27,  1           // InterfaceMethod sortedMapFactory:()Lscala/collection/SortedMapFactory;
         6: aload_0
         7: invokeinterface #31,  1           // InterfaceMethod ordering:()Lscala/math/Ordering;
        12: invokeinterface #36,  2           // InterfaceMethod scala/collection/SortedMapFactory.empty:(Lscala/math/Ordering;)Ljava/lang/Object;
        17: checkcast     #7                  // class scala/collection/SortedMapOps
        20: areturn
      LineNumberTable:
        line 1030: 0
      LocalVariableTable:
        Start  Length  Slot  Name   Signature
            0      21     0  this   Lscala/collection/SortedMapFactoryDefaults;
    Signature: #23                          // ()TCC;

  public static scala.collection.SortedMapOps fromSpecific$(scala.collection.SortedMapFactoryDefaults, scala.collection.IterableOnce);
    descriptor: (Lscala/collection/SortedMapFactoryDefaults;Lscala/collection/IterableOnce;)Lscala/collection/SortedMapOps;
    flags: (0x1009) ACC_PUBLIC, ACC_STATIC, ACC_SYNTHETIC
    Code:
      stack=2, locals=2, args_size=2
         0: aload_0
         1: aload_1
         2: invokespecial #44                 // InterfaceMethod fromSpecific:(Lscala/collection/IterableOnce;)Lscala/collection/SortedMapOps;
         5: areturn
      LineNumberTable:
        line 1031: 0
      LocalVariableTable:
        Start  Length  Slot  Name   Signature
            0       6     0 $this   Lscala/collection/SortedMapFactoryDefaults;
            0       6     1  coll   Lscala/collection/IterableOnce;
    MethodParameters:
      Name                           Flags
      $this                          final synthetic
      coll                           final

  public default CC fromSpecific(scala.collection.IterableOnce<scala.Tuple2<K, V>>);
    descriptor: (Lscala/collection/IterableOnce;)Lscala/collection/SortedMapOps;
    flags: (0x0001) ACC_PUBLIC
    Code:
      stack=3, locals=2, args_size=2
         0: aload_0
         1: invokeinterface #27,  1           // InterfaceMethod sortedMapFactory:()Lscala/collection/SortedMapFactory;
         6: aload_1
         7: aload_0
         8: invokeinterface #31,  1           // InterfaceMethod ordering:()Lscala/math/Ordering;
        13: invokeinterface #50,  3           // InterfaceMethod scala/collection/SortedMapFactory.from:(Lscala/collection/IterableOnce;Lscala/math/Ordering;)Ljava/lang/Object;
        18: checkcast     #7                  // class scala/collection/SortedMapOps
        21: areturn
      LineNumberTable:
        line 1031: 0
      LocalVariableTable:
        Start  Length  Slot  Name   Signature
            0      22     0  this   Lscala/collection/SortedMapFactoryDefaults;
            0      22     1  coll   Lscala/collection/IterableOnce;
    Signature: #46                          // (Lscala/collection/IterableOnce<Lscala/Tuple2<TK;TV;>;>;)TCC;
    MethodParameters:
      Name                           Flags
      coll                           final

  public static scala.collection.mutable.Builder newSpecificBuilder$(scala.collection.SortedMapFactoryDefaults);
    descriptor: (Lscala/collection/SortedMapFactoryDefaults;)Lscala/collection/mutable/Builder;
    flags: (0x1009) ACC_PUBLIC, ACC_STATIC, ACC_SYNTHETIC
    Code:
      stack=1, locals=1, args_size=1
         0: aload_0
         1: invokespecial #56                 // InterfaceMethod newSpecificBuilder:()Lscala/collection/mutable/Builder;
         4: areturn
      LineNumberTable:
        line 1032: 0
      LocalVariableTable:
        Start  Length  Slot  Name   Signature
            0       5     0 $this   Lscala/collection/SortedMapFactoryDefaults;
    MethodParameters:
      Name                           Flags
      $this                          final synthetic

  public default scala.collection.mutable.Builder<scala.Tuple2<K, V>, CC> newSpecificBuilder();
    descriptor: ()Lscala/collection/mutable/Builder;
    flags: (0x0001) ACC_PUBLIC
    Code:
      stack=2, locals=1, args_size=1
         0: aload_0
         1: invokeinterface #27,  1           // InterfaceMethod sortedMapFactory:()Lscala/collection/SortedMapFactory;
         6: aload_0
         7: invokeinterface #31,  1           // InterfaceMethod ordering:()Lscala/math/Ordering;
        12: invokeinterface #61,  2           // InterfaceMethod scala/collection/SortedMapFactory.newBuilder:(Lscala/math/Ordering;)Lscala/collection/mutable/Builder;
        17: areturn
      LineNumberTable:
        line 1032: 0
      LocalVariableTable:
        Start  Length  Slot  Name   Signature
            0      18     0  this   Lscala/collection/SortedMapFactoryDefaults;
    Signature: #57                          // ()Lscala/collection/mutable/Builder<Lscala/Tuple2<TK;TV;>;TCC;>;

  public static scala.collection.SortedMapOps$WithFilter withFilter$(scala.collection.SortedMapFactoryDefaults, scala.Function1);
    descriptor: (Lscala/collection/SortedMapFactoryDefaults;Lscala/Function1;)Lscala/collection/SortedMapOps$WithFilter;
    flags: (0x1009) ACC_PUBLIC, ACC_STATIC, ACC_SYNTHETIC
    Code:
      stack=2, locals=2, args_size=2
         0: aload_0
         1: aload_1
         2: invokespecial #68                 // InterfaceMethod withFilter:(Lscala/Function1;)Lscala/collection/SortedMapOps$WithFilter;
         5: areturn
      LineNumberTable:
        line 1034: 0
      LocalVariableTable:
        Start  Length  Slot  Name   Signature
            0       6     0 $this   Lscala/collection/SortedMapFactoryDefaults;
            0       6     1     p   Lscala/Function1;
    MethodParameters:
      Name                           Flags
      $this                          final synthetic
      p                              final

  public default scala.collection.SortedMapOps$WithFilter<K, V, WithFilterCC, UnsortedCC, CC> withFilter(scala.Function1<scala.Tuple2<K, V>, java.lang.Object>);
    descriptor: (Lscala/Function1;)Lscala/collection/SortedMapOps$WithFilter;
    flags: (0x0001) ACC_PUBLIC
    Code:
      stack=4, locals=2, args_size=2
         0: new           #13                 // class scala/collection/SortedMapOps$WithFilter
         3: dup
         4: aload_0
         5: aload_1
         6: invokespecial #74                 // Method scala/collection/SortedMapOps$WithFilter."<init>":(Lscala/collection/SortedMapOps;Lscala/Function1;)V
         9: areturn
      LineNumberTable:
        line 1035: 0
      LocalVariableTable:
        Start  Length  Slot  Name   Signature
            0      10     0  this   Lscala/collection/SortedMapFactoryDefaults;
            0      10     1     p   Lscala/Function1;
    Signature: #70                          // (Lscala/Function1<Lscala/Tuple2<TK;TV;>;Ljava/lang/Object;>;)Lscala/collection/SortedMapOps$WithFilter<TK;TV;TWithFilterCC;TUnsortedCC;TCC;>;
    MethodParameters:
      Name                           Flags
      p                              final

  public static void $init$(scala.collection.SortedMapFactoryDefaults);
    descriptor: (Lscala/collection/SortedMapFactoryDefaults;)V
    flags: (0x0009) ACC_PUBLIC, ACC_STATIC
    Code:
      stack=0, locals=1, args_size=1
         0: return
      LineNumberTable:
        line 1027: 0
      LocalVariableTable:
        Start  Length  Slot  Name   Signature
            0       1     0 $this   Lscala/collection/SortedMapFactoryDefaults;
    MethodParameters:
      Name                           Flags
      $this                          final synthetic
}
InnerClasses:
  public static #14= #13 of #7;           // WithFilter=class scala/collection/SortedMapOps$WithFilter of class scala/collection/SortedMapOps
Signature: #3                           // <K:Ljava/lang/Object;V:Ljava/lang/Object;CC:Lscala/collection/SortedMapOps<Ljava/lang/Object;Ljava/lang/Object;TCC;TCC;>;WithFilterCC:Lscala/collection/Iterable<Ljava/lang/Object;>;UnsortedCC::Lscala/collection/Map<Ljava/lang/Object;Ljava/lang/Object;>;>Ljava/lang/Object;Lscala/collection/SortedMapOps<TK;TV;TCC;TCC;>;
SourceFile: "Iterable.scala"
RuntimeVisibleAnnotations:
  0: #9(#10=s#11)
    scala.reflect.ScalaSignature(
      bytes="\u0006\u0005\u0005-b!\u0003\u0004\b!\u0003\r\t\u0001DA\u000e\u0011\u0015\u0001\u0006\u0001\"\u0001R\u0011\u0015)\u0006\u0001\"\u0011W\u0011\u00159\u0006\u0001\"\u0015Y\u0011\u0015\t\u0007\u0001\"\u0015c\u0011\u0015I\u0007\u0001\"\u0011k\u0005a\u0019vN\u001d;fI6\u000b\u0007OR1di>\u0014\u0018\u0010R3gCVdGo\u001d\u0006\u0003\u0011%\t!bY8mY\u0016\u001cG/[8o\u0015\u0005Q\u0011!B:dC2\f7\u0001A\u000b\u0007\u001ba\u0011S%\u001e\u001d\u0014\t\u0001q!\u0003\u0014\t\u0003\u001fAi\u0011!C\u0005\u0003#%\u0011a!\u00118z%\u00164\u0007CB\n\u0015-\u0005\"\u0013)D\u0001\b\u0013\t)rA\u0001\u0007T_J$X\rZ\'ba>\u00038\u000f\u0005\u0002\u001811\u0001A!B\r\u0001\u0005\u0004Q\"!A&\u0012\u0005mq\u0002CA\b\u001d\u0013\ti\u0012BA\u0004O_RD\u0017N\\4\u0011\u0005=y\u0012B\u0001\u0011\n\u0005\r\te.\u001f\t\u0003/\t\"aa\t\u0001\u0005\u0006\u0004Q\"!\u0001,\u0011\u0005])CA\u0002\u0014\u0001\t\u000b\u0007qE\u0001\u0002D\u0007V\u0019\u0001\u0006M\u001a\u0012\u0005mI#\u0003\u0002\u0016-k]2Aa\u000b\u0001\u0001S\taAH]3gS:,W.\u001a8u}A!1#L\u00183\u0013\tqsAA\u0002NCB\u0004\"a\u0006\u0019\u0005\u000bE*#\u0019\u0001\u000e\u0003\u0003a\u0004\"aF\u001a\u0005\u000bQ*#\u0019\u0001\u000e\u0003\u0003e\u0004ba\u0005\u000b0e\u00112\u0004\u0003B\f&_I\u0002Ba\u0006\u001d0e\u00111\u0011\b\u0001CC\u0002i\u0012!\"\u00168t_J$X\rZ\"D+\rYd\bQ\t\u00037q\u0002BaE\u0017>\u007fA\u0011qC\u0010\u0003\u0006ca\u0012\rA\u0007\t\u0003/\u0001#Q\u0001\u000e\u001dC\u0002i\u0001BaF\u0013\u0017\u0005*\u0012\u0011eQ\u0016\u0002\tB\u0011QIS\u0007\u0002\r*\u0011q\tS\u0001\nk:\u001c\u0007.Z2lK\u0012T!!S\u0005\u0002\u0015\u0005tgn\u001c;bi&|g.\u0003\u0002L\r\n\tRO\\2iK\u000e\\W\r\u001a,be&\fgnY3\u0011\rMie#I(B\u0013\tquA\u0001\u0004NCB|\u0005o\u001d\t\u0003/a\na\u0001J5oSR$C#\u0001*\u0011\u0005=\u0019\u0016B\u0001+\n\u0005\u0011)f.\u001b;\u0002\u000b\u0015l\u0007\u000f^=\u0016\u0003\u0005\u000bAB\u001a:p[N\u0003XmY5gS\u000e$\"!Q-\t\u000bi\u001b\u0001\u0019A.\u0002\t\r|G\u000e\u001c\t\u0004\'qs\u0016BA/\b\u00051IE/\u001a:bE2,wJ\\2f!\u0011yqL\u0006\"\n\u0005\u0001L!A\u0002+va2,\'\'\u0001\noK^\u001c\u0006/Z2jM&\u001c\')^5mI\u0016\u0014X#A2\u0011\t\u0011<g,Q\u0007\u0002K*\u0011amB\u0001\b[V$\u0018M\u00197f\u0013\tAWMA\u0004Ck&dG-\u001a:\u0002\u0015]LG\u000f\u001b$jYR,\'\u000fF\u0002l\u0003\u0013\u0001r\u0001\\9\u0017CQ|EE\u0004\u0002n_:\u0011qB\\\u0005\u0003\u0011%I!\u0001]\u0004\u0002\u0019M{\'\u000f^3e\u001b\u0006\u0004x\n]:\n\u0005I\u001c(AC,ji\"4\u0015\u000e\u001c;fe*\u0011\u0001o\u0002\t\u0003/U$aA\u001e\u0001\u0005\u0006\u00049(\u0001D,ji\"4\u0015\u000e\u001c;fe\u000e\u001bUC\u0001=\u0000#\tY\u0012P\u0005\u0003{w\u0006\ra\u0001B\u0016\u0001\u0001e\u0004ba\u0005?\u007fi\u0006\u0005\u0011BA?\b\u0005-IE/\u001a:bE2,w\n]:\u0011\u0005]yH!B\u0019v\u0005\u0004Q\u0002cA\fv}B!1#!\u0002\u007f\u0013\r\t9a\u0002\u0002\t\u0013R,\'/\u00192mK\"9\u00111B\u0003A\u0002\u00055\u0011!\u00019\u0011\u000f=\ty!a\u0005\u0002\u0016%\u0019\u0011\u0011C\u0005\u0003\u0013\u0019+hn\u0019;j_:\f\u0004\u0003B\b`-\u0005\u00022aDA\f\u0013\r\tI\"\u0003\u0002\b\u0005>|G.Z1o%\u0019\ti\"a\b\u0002\"\u0019)1\u0006\u0001\u0001\u0002\u001cA91\u0003\u0001\f\"IQ|\u0005\u0007BA\u0012\u0003O\u0001ra\u0005?\u0002\u0014Q\f)\u0003E\u0002\u0018\u0003O!!\"!\u000b\u0001\u0003\u0003\u0005\tQ!\u0001\u001b\u0005\ryFE\u000e"
    )
  ScalaInlineInfo: length = 0x31 (unknown attribute)
   01 00 00 09 00 4B 00 4C 01 00 12 00 13 00 00 0F
   00 10 01 00 29 00 2A 00 00 26 00 27 01 00 35 00
   36 00 00 33 00 34 01 00 41 00 42 00 00 3E 00 3F
   01
  ScalaSig: length = 0x3 (unknown attribute)
   05 02 00
