Classfile /Users/mw/Projects/slang-braindump/.jar/jar11/assemble/slang-braindump/assemble/content/scala/collection/SortedMapFactory.class
  Last modified May 29, 2022; size 6792 bytes
  SHA-256 checksum 580b7b716a3a93082592e53ff8e598b32d997bd0d68cb37e67bffcc301eb2275
  Compiled from "Factory.scala"
public interface scala.collection.SortedMapFactory<CC extends java.lang.Object> extends java.io.Serializable
  minor version: 0
  major version: 52
  flags: (0x0601) ACC_PUBLIC, ACC_INTERFACE, ACC_ABSTRACT
  this_class: #2                          // scala/collection/SortedMapFactory
  super_class: #5                         // java/lang/Object
  interfaces: 1, fields: 0, methods: 10, attributes: 6
Constant pool:
   #1 = Utf8               scala/collection/SortedMapFactory
   #2 = Class              #1             // scala/collection/SortedMapFactory
   #3 = Utf8               <CC:Ljava/lang/Object;>Ljava/lang/Object;Ljava/io/Serializable;
   #4 = Utf8               java/lang/Object
   #5 = Class              #4             // java/lang/Object
   #6 = Utf8               java/io/Serializable
   #7 = Class              #6             // java/io/Serializable
   #8 = Utf8               Factory.scala
   #9 = Utf8               Lscala/reflect/ScalaSignature;
  #10 = Utf8               bytes
  #11 = Utf8               \u0006\u0005\tega\u0002\u0011\"!\u0003\r\tA\n\u0005\u0006g\u0001!\t\u0001\u000e\u0005\u0006q\u00011\t!\u000f\u0005\u0006-\u00021\ta\u0016\u0005\u0006W\u0002!\t\u0001\u001c\u0005\u0006{\u00021\tA \u0005\b\u0003?\u0001A1AA\u0011\u000f\u001d\ti$\tE\u0001\u0003\u007f1a\u0001I\u0011\t\u0002\u0005\u0005\u0003bBA)\u0011\u0011\u0005\u00111\u000b\u0005\b\u0003+BA1AA,\r!\t)\t\u0003Q\u0001\n\u0005\u001d\u0005BCA@\u0017\t\u0005\t\u0015!\u0003\u0002&\"Q\u0011\u0011V\u0006\u0003\u0004\u0003\u0006Y!a+\t\u000f\u0005E3\u0002\"\u0001\u0002.\"9\u0011\u0011X\u0006\u0005\u0002\u0005m\u0006BB?\f\t\u0003\t\t\rC\u0004\u0002R\"!\u0019!a5\u0007\r\t\r\u0001\u0002\u0002B\u0003\u0011)\tyH\u0005B\u0001B\u0003%!1\u0005\u0005\u000b\u0005O\u0011\"1!Q\u0001\f\t%\u0002bBA)%\u0011\u0005!1\u0006\u0005\b\u0003s\u0013B\u0011\u0001B\u001b\u0011\u0019i(\u0003\"\u0001\u0003@\u00191!Q\t\u0005\u0001\u0005\u000fB!Ba\u0017\u0019\u0005\u0003\u0005\u000b\u0011\u0002B&\u0011\u001d\t\t\u0006\u0007C\u0001\u0005;Baa\u001b\r\u0005B\t\r\u0004B\u0002,\u0019\t\u0003\u0011y\b\u0003\u000491\u0011\u0005!1\u0014\u0005\u0007{b!\tAa,\t\u0013\t%\u0007\"!A\u0005\n\t-\'\u0001E*peR,G-T1q\r\u0006\u001cGo\u001c:z\u0015\t\u00113%\u0001\u0006d_2dWm\u0019;j_:T\u0011\u0001J\u0001\u0006g\u000e\fG.Y\u0002\u0001+\t9ShE\u0002\u0001Q1\u0002\"!\u000b\u0016\u000e\u0003\rJ!aK\u0012\u0003\r\u0005s\u0017PU3g!\ti\u0003G\u0004\u0002*]%\u0011qfI\u0001\ba\u0006\u001c7.Y4f\u0013\t\t$G\u0001\u0007TKJL\u0017\r\\5{C\ndWM\u0003\u00020G\u00051A%\u001b8ji\u0012\"\u0012!\u000e\t\u0003SYJ!aN\u0012\u0003\tUs\u0017\u000e^\u0001\u0006K6\u0004H/_\u000b\u0004u1{ECA\u001eR!\u0011aTh\u0013(\r\u0001\u00111a\b\u0001CC\u0002}\u0012!aQ\"\u0016\u0007\u0001;\u0015*\u0005\u0002B\tB\u0011\u0011FQ\u0005\u0003\u0007\u000e\u0012qAT8uQ&tw\r\u0005\u0002*\u000b&\u0011ai\t\u0002\u0004\u0003:LH!\u0002%>\u0005\u0004\u0001%!B0%IM\u001aD!\u0002&>\u0005\u0004\u0001%!B0%IM\"\u0004C\u0001\u001fM\t\u0015i%A1\u0001A\u0005\u0005Y\u0005C\u0001\u001fP\t\u0015\u0001&A1\u0001A\u0005\u00051\u0006b\u0002*\u0003\u0003\u0003\u0005\u001daU\u0001\fKZLG-\u001a8dK\u0012\u001ad\u0007E\u0002.).K!!\u0016\u001a\u0003\u0011=\u0013H-\u001a:j]\u001e\fAA\u001a:p[V\u0019\u0001\f\u00180\u0015\u0005e\u0013GC\u0001.`!\u0011aThW/\u0011\u0005qbF!B\'\u0004\u0005\u0004\u0001\u0005C\u0001\u001f_\t\u0015\u00016A1\u0001A\u0011\u001d\u00017!!AA\u0004\u0005\f1\"\u001a<jI\u0016t7-\u001a\u00134oA\u0019Q\u0006V.\t\u000b\r\u001c\u0001\u0019\u00013\u0002\u0005%$\bcA3gQ6\t\u0011%\u0003\u0002hC\ta\u0011\n^3sC\ndWm\u00148dKB!\u0011&[.^\u0013\tQ7E\u0001\u0004UkBdWMM\u0001\u0006CB\u0004H._\u000b\u0004[F\u001cHC\u00018x)\tyG\u000f\u0005\u0003={A\u0014\bC\u0001\u001fr\t\u0015iEA1\u0001A!\ta4\u000fB\u0003Q\t\t\u0007\u0001\tC\u0004v\t\u0005\u0005\t9\u0001<\u0002\u0017\u00154\u0018\u000eZ3oG\u0016$3\u0007\u000f\t\u0004[Q\u0003\b\"\u0002=\u0005\u0001\u0004I\u0018!B3mK6\u001c\bcA\u0015{y&\u00111p\t\u0002\u000byI,\u0007/Z1uK\u0012t\u0004\u0003B\u0015jaJ\f!B\\3x\u0005VLG\u000eZ3s+\u0015y\u0018\u0011CA\u000b)\u0011\t\t!!\u0007\u0011\u0011\u0005\r\u0011\u0011BA\u0007\u0003/i!!!\u0002\u000b\u0007\u0005\u001d\u0011%A\u0004nkR\f\'\r\\3\n\t\u0005-\u0011Q\u0001\u0002\b\u0005VLG\u000eZ3s!\u0019I\u0013.a\u0004\u0002\u0014A\u0019A(!\u0005\u0005\u000b5+!\u0019\u0001!\u0011\u0007q\n)\u0002B\u0003Q\u000b\t\u0007\u0001\t\u0005\u0004={\u0005=\u00111\u0003\u0005\n\u00037)\u0011\u0011!a\u0002\u0003;\t1\"\u001a<jI\u0016t7-\u001a\u00134sA!Q\u0006VA\b\u0003A\u0019xN\u001d;fI6\u000b\u0007OR1di>\u0014\u00180\u0006\u0004\u0002$\u0005=\u00121\u0007\u000b\u0005\u0003K\t9\u0004E\u0004f\u0003O\tY#!\u000e\n\u0007\u0005%\u0012EA\u0004GC\u000e$xN]=\u0011\r%J\u0017QFA\u0019!\ra\u0014q\u0006\u0003\u0006\u001b\u001a\u0011\r\u0001\u0011\t\u0004y\u0005MB!\u0002)\u0007\u0005\u0004\u0001\u0005C\u0002\u001f>\u0003[\t\t\u0004C\u0005\u0002:\u0019\t\t\u0011q\u0001\u0002<\u0005YQM^5eK:\u001cW\r\n\u001b1!\u0011iC+!\f\u0002!M{\'\u000f^3e\u001b\u0006\u0004h)Y2u_JL\bCA3\t\'\u0011A\u0001&a\u0011\u0011\t\u0005\u0015\u0013qJ\u0007\u0003\u0003\u000fRA!!\u0013\u0002L\u0005\u0011\u0011n\u001c\u0006\u0003\u0003\u001b\nAA[1wC&\u0019\u0011\'a\u0012\u0002\rqJg.\u001b;?)\t\ty$A\u0005u_\u001a\u000b7\r^8ssVA\u0011\u0011LA2\u0003O\nY\u0007\u0006\u0003\u0002\\\u0005uD\u0003BA/\u0003o\u0002r!ZA\u0014\u0003?\nI\u0007\u0005\u0004*S\u0006\u0005\u0014Q\r\t\u0004y\u0005\rD!B\'\u000b\u0005\u0004\u0001\u0005c\u0001\u001f\u0002h\u0011)\u0001K\u0003b\u0001\u0001B9A(a\u001b\u0002b\u0005\u0015DA\u0002 \u000b\u0005\u0004\ti\'F\u0003A\u0003_\n\u0019\bB\u0004\u0002r\u0005-$\u0019\u0001!\u0003\u000b}#CeM\u001b\u0005\u000f\u0005U\u00141\u000eb\u0001\u0001\n)q\f\n\u00134m!I\u0011\u0011\u0010\u0006\u0002\u0002\u0003\u000f\u00111P\u0001\fKZLG-\u001a8dK\u0012\"\u0014\u0007\u0005\u0003.)\u0006\u0005\u0004bBA@\u0015\u0001\u0007\u0011\u0011Q\u0001\bM\u0006\u001cGo\u001c:z!\u0011)\u0007!a!\u0011\u0007q\nYGA\u0005U_\u001a\u000b7\r^8ssVA\u0011\u0011RAI\u0003+\u000bIjE\u0003\fQ\u0005-E\u0006E\u0004f\u0003O\ti)a&\u0011\r%J\u0017qRAJ!\ra\u0014\u0011\u0013\u0003\u0006\u001b.\u0011\r\u0001\u0011\t\u0004y\u0005UE!\u0002)\f\u0005\u0004\u0001\u0005c\u0002\u001f\u0002\u001a\u0006=\u00151\u0013\u0003\u0007}-\u0011\r!a\'\u0016\u000b\u0001\u000bi*!)\u0005\u000f\u0005}\u0015\u0011\u0014b\u0001\u0001\n)q\f\n\u00134o\u00119\u00111UAM\u0005\u0004\u0001%!B0%IMB\u0004\u0003B3\u0001\u0003O\u00032\u0001PAM\u0003-)g/\u001b3f]\u000e,G\u0005\u000e\u001a\u0011\t5\"\u0016q\u0012\u000b\u0005\u0003_\u000b9\f\u0006\u0003\u00022\u0006U\u0006#CAZ\u0017\u0005=\u00151SAT\u001b\u0005A\u0001bBAU\u001d\u0001\u000f\u00111\u0016\u0005\b\u0003\u007fr\u0001\u0019AAS\u000311\'o\\7Ta\u0016\u001c\u0017NZ5d)\u0011\t9*!0\t\r\r|\u0001\u0019AA`!\u0011)g-!$\u0016\u0005\u0005\r\u0007\u0003CA\u0002\u0003\u0013\ti)a&)\u000f-\t9-!4\u0002PB\u0019\u0011&!3\n\u0007\u0005-7E\u0001\tTKJL\u0017\r\u001c,feNLwN\\+J\t\u0006)a/\u00197vKz\t1!A\u0006u_\n+\u0018\u000e\u001c3Ge>lW\u0003CAk\u0003G\f9/a;\u0015\t\u0005]\u0017Q \u000b\u0005\u00033\f9\u0010\u0005\u0005f\u00037$\u0015q\\Au\u0013\r\ti.\t\u0002\n\u0005VLG\u000e\u001a$s_6\u0004b!K5\u0002b\u0006\u0015\bc\u0001\u001f\u0002d\u0012)Q*\u0005b\u0001\u0001B\u0019A(a:\u0005\u000bA\u000b\"\u0019\u0001!\u0011\u000fq\nY/!9\u0002f\u00121a(\u0005b\u0001\u0003[,R\u0001QAx\u0003g$q!!=\u0002l\n\u0007\u0001IA\u0003`I\u0011\u001a\u0014\bB\u0004\u0002v\u0006-(\u0019\u0001!\u0003\u000b}#C\u0005\u000e\u0019\t\u0013\u0005e\u0018#!AA\u0004\u0005m\u0018aC3wS\u0012,gnY3%iM\u0002B!\f+\u0002b\"9\u0011qP\tA\u0002\u0005}\b\u0003B3\u0001\u0005\u0003\u00012\u0001PAv\u0005m\u0019vN\u001d;fI6\u000b\u0007OR1di>\u0014\u0018\u0010V8Ck&dGM\u0012:p[VA!q\u0001B\b\u0005\'\u00119b\u0005\u0003\u0013Q\t%\u0001\u0003C3\u0002\\\u0012\u0013YA!\u0006\u0011\r%J\'Q\u0002B\t!\ra$q\u0002\u0003\u0006\u001bJ\u0011\r\u0001\u0011\t\u0004y\tMA!\u0002)\u0013\u0005\u0004\u0001\u0005c\u0002\u001f\u0003\u0018\t5!\u0011\u0003\u0003\u0007}I\u0011\rA!\u0007\u0016\u000b\u0001\u0013YBa\b\u0005\u000f\tu!q\u0003b\u0001\u0001\n)q\f\n\u00135c\u00119!\u0011\u0005B\f\u0005\u0004\u0001%!B0%IQ\u0012\u0004\u0003B3\u0001\u0005K\u00012\u0001\u0010B\f\u0003-)g/\u001b3f]\u000e,G\u0005\u000e\u001b\u0011\t5\"&Q\u0002\u000b\u0005\u0005[\u0011\u0019\u0004\u0006\u0003\u00030\tE\u0002#CAZ%\t5!\u0011\u0003B\u0013\u0011\u001d\u00119#\u0006a\u0002\u0005SAq!a \u0016\u0001\u0004\u0011\u0019\u0003\u0006\u0003\u00038\tuB\u0003\u0002B\u000b\u0005sAaa\u0019\fA\u0002\tm\u0002\u0003B3g\u0005\u0017AQA\u0016\fA\u0002\u0011#BA!\u0011\u0003DAA\u00111AA\u0005\u0005\u0017\u0011)\u0002C\u0003W/\u0001\u0007AI\u0001\u0005EK2,w-\u0019;f+\u0011\u0011IEa\u0014\u0014\taA#1\n\t\u0005K\u0002\u0011i\u0005E\u0002=\u0005\u001f\"aA\u0010\rC\u0002\tES#\u0002!\u0003T\t]Ca\u0002B+\u0005\u001f\u0012\r\u0001\u0011\u0002\u0006?\u0012\"Cg\r\u0003\b\u00053\u0012yE1\u0001A\u0005\u0015yF\u0005\n\u001b5\u0003!!W\r\\3hCR,G\u0003\u0002B0\u0005C\u0002R!a-\u0019\u0005\u001bBqAa\u0017\u001b\u0001\u0004\u0011Y%\u0006\u0004\u0003f\t5$\u0011\u000f\u000b\u0005\u0005O\u0012I\b\u0006\u0003\u0003j\tM\u0004c\u0002\u001f\u0003P\t-$q\u000e\t\u0004y\t5D!B\'\u001c\u0005\u0004\u0001\u0005c\u0001\u001f\u0003r\u0011)\u0001k\u0007b\u0001\u0001\"I!QO\u000e\u0002\u0002\u0003\u000f!qO\u0001\fKZLG-\u001a8dK\u0012\"T\u0007\u0005\u0003.)\n-\u0004B\u0002=\u001c\u0001\u0004\u0011Y\b\u0005\u0003*u\nu\u0004CB\u0015j\u0005W\u0012y\'\u0006\u0004\u0003\u0002\n%%Q\u0012\u000b\u0005\u0005\u0007\u0013)\n\u0006\u0003\u0003\u0006\n=\u0005c\u0002\u001f\u0003P\t\u001d%1\u0012\t\u0004y\t%E!B\'\u001d\u0005\u0004\u0001\u0005c\u0001\u001f\u0003\u000e\u0012)\u0001\u000b\bb\u0001\u0001\"I!\u0011\u0013\u000f\u0002\u0002\u0003\u000f!1S\u0001\fKZLG-\u001a8dK\u0012\"d\u0007\u0005\u0003.)\n\u001d\u0005BB2\u001d\u0001\u0004\u00119\n\u0005\u0003fM\ne\u0005CB\u0015j\u0005\u000f\u0013Y)\u0006\u0004\u0003\u001e\n\r&q\u0015\u000b\u0005\u0005?\u0013I\u000bE\u0004=\u0005\u001f\u0012\tK!*\u0011\u0007q\u0012\u0019\u000bB\u0003N;\t\u0007\u0001\tE\u0002=\u0005O#Q\u0001U\u000fC\u0002\u0001C\u0011Ba+\u001e\u0003\u0003\u0005\u001dA!,\u0002\u0017\u00154\u0018\u000eZ3oG\u0016$Cg\u000e\t\u0005[Q\u0013\t+\u0006\u0004\u00032\ne&Q\u0018\u000b\u0005\u0005g\u0013\t\r\u0005\u0005\u0002\u0004\u0005%!Q\u0017B`!\u0019I\u0013Na.\u0003<B\u0019AH!/\u0005\u000b5s\"\u0019\u0001!\u0011\u0007q\u0012i\fB\u0003Q=\t\u0007\u0001\tE\u0004=\u0005\u001f\u00129La/\t\u0013\t\rg$!AA\u0004\t\u0015\u0017aC3wS\u0012,gnY3%ia\u0002B!\f+\u00038\":\u0001$a2\u0002N\u0006=\u0017\u0001D<sSR,\'+\u001a9mC\u000e,GC\u0001Bg!\u0011\u0011yM!6\u000e\u0005\tE\'\u0002\u0002Bj\u0003\u0017\nA\u0001\\1oO&!!q\u001bBi\u0005\u0019y%M[3di\u0002
  #12 = Utf8               scala/collection/SortedMapFactory$Delegate
  #13 = Class              #12            // scala/collection/SortedMapFactory$Delegate
  #14 = Utf8               Delegate
  #15 = Utf8               scala/collection/SortedMapFactory$SortedMapFactoryToBuildFrom
  #16 = Class              #15            // scala/collection/SortedMapFactory$SortedMapFactoryToBuildFrom
  #17 = Utf8               SortedMapFactoryToBuildFrom
  #18 = Utf8               scala/collection/SortedMapFactory$ToFactory
  #19 = Class              #18            // scala/collection/SortedMapFactory$ToFactory
  #20 = Utf8               ToFactory
  #21 = Utf8               toBuildFrom
  #22 = Utf8               (Lscala/collection/SortedMapFactory;Lscala/math/Ordering;)Lscala/collection/BuildFrom;
  #23 = Utf8               <K:Ljava/lang/Object;V:Ljava/lang/Object;CC:Ljava/lang/Object;>(Lscala/collection/SortedMapFactory<TCC;>;Lscala/math/Ordering<TK;>;)Lscala/collection/BuildFrom<Ljava/lang/Object;Lscala/Tuple2<TK;TV;>;TCC;>;
  #24 = Utf8               factory
  #25 = Utf8               evidence$43
  #26 = Utf8               scala/collection/SortedMapFactory$
  #27 = Class              #26            // scala/collection/SortedMapFactory$
  #28 = Utf8               MODULE$
  #29 = Utf8               Lscala/collection/SortedMapFactory$;
  #30 = NameAndType        #28:#29        // MODULE$:Lscala/collection/SortedMapFactory$;
  #31 = Fieldref           #27.#30        // scala/collection/SortedMapFactory$.MODULE$:Lscala/collection/SortedMapFactory$;
  #32 = Utf8               <init>
  #33 = Utf8               (Lscala/collection/SortedMapFactory;Lscala/math/Ordering;)V
  #34 = NameAndType        #32:#33        // "<init>":(Lscala/collection/SortedMapFactory;Lscala/math/Ordering;)V
  #35 = Methodref          #16.#34        // scala/collection/SortedMapFactory$SortedMapFactoryToBuildFrom."<init>":(Lscala/collection/SortedMapFactory;Lscala/math/Ordering;)V
  #36 = Utf8               Lscala/collection/SortedMapFactory;
  #37 = Utf8               Lscala/math/Ordering;
  #38 = Utf8               toFactory
  #39 = Utf8               (Lscala/collection/SortedMapFactory;Lscala/math/Ordering;)Lscala/collection/Factory;
  #40 = Utf8               <K:Ljava/lang/Object;V:Ljava/lang/Object;CC:Ljava/lang/Object;>(Lscala/collection/SortedMapFactory<TCC;>;Lscala/math/Ordering<TK;>;)Lscala/collection/Factory<Lscala/Tuple2<TK;TV;>;TCC;>;
  #41 = Utf8               evidence$41
  #42 = Methodref          #19.#34        // scala/collection/SortedMapFactory$ToFactory."<init>":(Lscala/collection/SortedMapFactory;Lscala/math/Ordering;)V
  #43 = Utf8               empty
  #44 = Utf8               (Lscala/math/Ordering;)Ljava/lang/Object;
  #45 = Utf8               <K:Ljava/lang/Object;V:Ljava/lang/Object;>(Lscala/math/Ordering<TK;>;)TCC;
  #46 = Utf8               evidence$36
  #47 = Utf8               from
  #48 = Utf8               (Lscala/collection/IterableOnce;Lscala/math/Ordering;)Ljava/lang/Object;
  #49 = Utf8               <K:Ljava/lang/Object;V:Ljava/lang/Object;>(Lscala/collection/IterableOnce<Lscala/Tuple2<TK;TV;>;>;Lscala/math/Ordering<TK;>;)TCC;
  #50 = Utf8               it
  #51 = Utf8               evidence$37
  #52 = Utf8               apply$
  #53 = Utf8               (Lscala/collection/SortedMapFactory;Lscala/collection/immutable/Seq;Lscala/math/Ordering;)Ljava/lang/Object;
  #54 = Utf8               $this
  #55 = Utf8               elems
  #56 = Utf8               evidence$38
  #57 = Utf8               apply
  #58 = Utf8               (Lscala/collection/immutable/Seq;Lscala/math/Ordering;)Ljava/lang/Object;
  #59 = NameAndType        #57:#58        // apply:(Lscala/collection/immutable/Seq;Lscala/math/Ordering;)Ljava/lang/Object;
  #60 = InterfaceMethodref #2.#59         // scala/collection/SortedMapFactory.apply:(Lscala/collection/immutable/Seq;Lscala/math/Ordering;)Ljava/lang/Object;
  #61 = Utf8               Lscala/collection/immutable/Seq;
  #62 = Utf8               <K:Ljava/lang/Object;V:Ljava/lang/Object;>(Lscala/collection/immutable/Seq<Lscala/Tuple2<TK;TV;>;>;Lscala/math/Ordering<TK;>;)TCC;
  #63 = NameAndType        #47:#48        // from:(Lscala/collection/IterableOnce;Lscala/math/Ordering;)Ljava/lang/Object;
  #64 = InterfaceMethodref #2.#63         // scala/collection/SortedMapFactory.from:(Lscala/collection/IterableOnce;Lscala/math/Ordering;)Ljava/lang/Object;
  #65 = Utf8               this
  #66 = Utf8               newBuilder
  #67 = Utf8               (Lscala/math/Ordering;)Lscala/collection/mutable/Builder;
  #68 = Utf8               <K:Ljava/lang/Object;V:Ljava/lang/Object;>(Lscala/math/Ordering<TK;>;)Lscala/collection/mutable/Builder<Lscala/Tuple2<TK;TV;>;TCC;>;
  #69 = Utf8               evidence$39
  #70 = Utf8               sortedMapFactory$
  #71 = Utf8               evidence$40
  #72 = Utf8               sortedMapFactory
  #73 = Utf8               (Lscala/math/Ordering;)Lscala/collection/Factory;
  #74 = NameAndType        #72:#73        // sortedMapFactory:(Lscala/math/Ordering;)Lscala/collection/Factory;
  #75 = InterfaceMethodref #2.#74         // scala/collection/SortedMapFactory.sortedMapFactory:(Lscala/math/Ordering;)Lscala/collection/Factory;
  #76 = Utf8               <K:Ljava/lang/Object;V:Ljava/lang/Object;>(Lscala/math/Ordering<TK;>;)Lscala/collection/Factory<Lscala/Tuple2<TK;TV;>;TCC;>;
  #77 = Utf8               $init$
  #78 = Utf8               (Lscala/collection/SortedMapFactory;)V
  #79 = Utf8               Code
  #80 = Utf8               LineNumberTable
  #81 = Utf8               LocalVariableTable
  #82 = Utf8               Signature
  #83 = Utf8               MethodParameters
  #84 = Utf8               InnerClasses
  #85 = Utf8               SourceFile
  #86 = Utf8               RuntimeVisibleAnnotations
  #87 = Utf8               ScalaInlineInfo
  #88 = Utf8               ScalaSig
{
  public static <K extends java.lang.Object, V extends java.lang.Object, CC extends java.lang.Object> scala.collection.BuildFrom<java.lang.Object, scala.Tuple2<K, V>, CC> toBuildFrom(scala.collection.SortedMapFactory<CC>, scala.math.Ordering<K>);
    descriptor: (Lscala/collection/SortedMapFactory;Lscala/math/Ordering;)Lscala/collection/BuildFrom;
    flags: (0x0009) ACC_PUBLIC, ACC_STATIC
    Code:
      stack=4, locals=2, args_size=2
         0: getstatic     #31                 // Field scala/collection/SortedMapFactory$.MODULE$:Lscala/collection/SortedMapFactory$;
         3: pop
         4: new           #16                 // class scala/collection/SortedMapFactory$SortedMapFactoryToBuildFrom
         7: dup
         8: aload_0
         9: aload_1
        10: invokespecial #35                 // Method scala/collection/SortedMapFactory$SortedMapFactoryToBuildFrom."<init>":(Lscala/collection/SortedMapFactory;Lscala/math/Ordering;)V
        13: areturn
      LineNumberTable:
        line 771: 4
      LocalVariableTable:
        Start  Length  Slot  Name   Signature
            0      14     0 factory   Lscala/collection/SortedMapFactory;
            0      14     1 evidence$43   Lscala/math/Ordering;
    Signature: #23                          // <K:Ljava/lang/Object;V:Ljava/lang/Object;CC:Ljava/lang/Object;>(Lscala/collection/SortedMapFactory<TCC;>;Lscala/math/Ordering<TK;>;)Lscala/collection/BuildFrom<Ljava/lang/Object;Lscala/Tuple2<TK;TV;>;TCC;>;
    MethodParameters:
      Name                           Flags
      factory                        final
      evidence$43                    final

  public static <K extends java.lang.Object, V extends java.lang.Object, CC extends java.lang.Object> scala.collection.Factory<scala.Tuple2<K, V>, CC> toFactory(scala.collection.SortedMapFactory<CC>, scala.math.Ordering<K>);
    descriptor: (Lscala/collection/SortedMapFactory;Lscala/math/Ordering;)Lscala/collection/Factory;
    flags: (0x0009) ACC_PUBLIC, ACC_STATIC
    Code:
      stack=4, locals=2, args_size=2
         0: getstatic     #31                 // Field scala/collection/SortedMapFactory$.MODULE$:Lscala/collection/SortedMapFactory$;
         3: pop
         4: new           #19                 // class scala/collection/SortedMapFactory$ToFactory
         7: dup
         8: aload_0
         9: aload_1
        10: invokespecial #42                 // Method scala/collection/SortedMapFactory$ToFactory."<init>":(Lscala/collection/SortedMapFactory;Lscala/math/Ordering;)V
        13: areturn
      LineNumberTable:
        line 763: 4
      LocalVariableTable:
        Start  Length  Slot  Name   Signature
            0      14     0 factory   Lscala/collection/SortedMapFactory;
            0      14     1 evidence$41   Lscala/math/Ordering;
    Signature: #40                          // <K:Ljava/lang/Object;V:Ljava/lang/Object;CC:Ljava/lang/Object;>(Lscala/collection/SortedMapFactory<TCC;>;Lscala/math/Ordering<TK;>;)Lscala/collection/Factory<Lscala/Tuple2<TK;TV;>;TCC;>;
    MethodParameters:
      Name                           Flags
      factory                        final
      evidence$41                    final

  public abstract <K extends java.lang.Object, V extends java.lang.Object> CC empty(scala.math.Ordering<K>);
    descriptor: (Lscala/math/Ordering;)Ljava/lang/Object;
    flags: (0x0401) ACC_PUBLIC, ACC_ABSTRACT
    Signature: #45                          // <K:Ljava/lang/Object;V:Ljava/lang/Object;>(Lscala/math/Ordering<TK;>;)TCC;
    MethodParameters:
      Name                           Flags
      evidence$36                    final

  public abstract <K extends java.lang.Object, V extends java.lang.Object> CC from(scala.collection.IterableOnce<scala.Tuple2<K, V>>, scala.math.Ordering<K>);
    descriptor: (Lscala/collection/IterableOnce;Lscala/math/Ordering;)Ljava/lang/Object;
    flags: (0x0401) ACC_PUBLIC, ACC_ABSTRACT
    Signature: #49                          // <K:Ljava/lang/Object;V:Ljava/lang/Object;>(Lscala/collection/IterableOnce<Lscala/Tuple2<TK;TV;>;>;Lscala/math/Ordering<TK;>;)TCC;
    MethodParameters:
      Name                           Flags
      it                             final
      evidence$37                    final

  public static java.lang.Object apply$(scala.collection.SortedMapFactory, scala.collection.immutable.Seq, scala.math.Ordering);
    descriptor: (Lscala/collection/SortedMapFactory;Lscala/collection/immutable/Seq;Lscala/math/Ordering;)Ljava/lang/Object;
    flags: (0x1009) ACC_PUBLIC, ACC_STATIC, ACC_SYNTHETIC
    Code:
      stack=3, locals=3, args_size=3
         0: aload_0
         1: aload_1
         2: aload_2
         3: invokespecial #60                 // InterfaceMethod apply:(Lscala/collection/immutable/Seq;Lscala/math/Ordering;)Ljava/lang/Object;
         6: areturn
      LineNumberTable:
        line 742: 0
      LocalVariableTable:
        Start  Length  Slot  Name   Signature
            0       7     0 $this   Lscala/collection/SortedMapFactory;
            0       7     1 elems   Lscala/collection/immutable/Seq;
            0       7     2 evidence$38   Lscala/math/Ordering;
    MethodParameters:
      Name                           Flags
      $this                          final synthetic
      elems                          final
      evidence$38                    final

  public default <K extends java.lang.Object, V extends java.lang.Object> CC apply(scala.collection.immutable.Seq<scala.Tuple2<K, V>>, scala.math.Ordering<K>);
    descriptor: (Lscala/collection/immutable/Seq;Lscala/math/Ordering;)Ljava/lang/Object;
    flags: (0x0001) ACC_PUBLIC
    Code:
      stack=3, locals=3, args_size=3
         0: aload_0
         1: aload_1
         2: aload_2
         3: invokeinterface #64,  3           // InterfaceMethod from:(Lscala/collection/IterableOnce;Lscala/math/Ordering;)Ljava/lang/Object;
         8: areturn
      LineNumberTable:
        line 742: 0
      LocalVariableTable:
        Start  Length  Slot  Name   Signature
            0       9     0  this   Lscala/collection/SortedMapFactory;
            0       9     1 elems   Lscala/collection/immutable/Seq;
            0       9     2 evidence$38   Lscala/math/Ordering;
    Signature: #62                          // <K:Ljava/lang/Object;V:Ljava/lang/Object;>(Lscala/collection/immutable/Seq<Lscala/Tuple2<TK;TV;>;>;Lscala/math/Ordering<TK;>;)TCC;
    MethodParameters:
      Name                           Flags
      elems                          final
      evidence$38                    final

  public abstract <K extends java.lang.Object, V extends java.lang.Object> scala.collection.mutable.Builder<scala.Tuple2<K, V>, CC> newBuilder(scala.math.Ordering<K>);
    descriptor: (Lscala/math/Ordering;)Lscala/collection/mutable/Builder;
    flags: (0x0401) ACC_PUBLIC, ACC_ABSTRACT
    Signature: #68                          // <K:Ljava/lang/Object;V:Ljava/lang/Object;>(Lscala/math/Ordering<TK;>;)Lscala/collection/mutable/Builder<Lscala/Tuple2<TK;TV;>;TCC;>;
    MethodParameters:
      Name                           Flags
      evidence$39                    final

  public static scala.collection.Factory sortedMapFactory$(scala.collection.SortedMapFactory, scala.math.Ordering);
    descriptor: (Lscala/collection/SortedMapFactory;Lscala/math/Ordering;)Lscala/collection/Factory;
    flags: (0x1009) ACC_PUBLIC, ACC_STATIC, ACC_SYNTHETIC
    Code:
      stack=2, locals=2, args_size=2
         0: aload_0
         1: aload_1
         2: invokespecial #75                 // InterfaceMethod sortedMapFactory:(Lscala/math/Ordering;)Lscala/collection/Factory;
         5: areturn
      LineNumberTable:
        line 746: 0
      LocalVariableTable:
        Start  Length  Slot  Name   Signature
            0       6     0 $this   Lscala/collection/SortedMapFactory;
            0       6     1 evidence$40   Lscala/math/Ordering;
    MethodParameters:
      Name                           Flags
      $this                          final synthetic
      evidence$40                    final

  public default <K extends java.lang.Object, V extends java.lang.Object> scala.collection.Factory<scala.Tuple2<K, V>, CC> sortedMapFactory(scala.math.Ordering<K>);
    descriptor: (Lscala/math/Ordering;)Lscala/collection/Factory;
    flags: (0x0001) ACC_PUBLIC
    Code:
      stack=4, locals=2, args_size=2
         0: getstatic     #31                 // Field scala/collection/SortedMapFactory$.MODULE$:Lscala/collection/SortedMapFactory$;
         3: pop
         4: new           #19                 // class scala/collection/SortedMapFactory$ToFactory
         7: dup
         8: aload_0
         9: aload_1
        10: invokespecial #42                 // Method scala/collection/SortedMapFactory$ToFactory."<init>":(Lscala/collection/SortedMapFactory;Lscala/math/Ordering;)V
        13: areturn
      LineNumberTable:
        line 746: 0
        line 763: 4
        line 746: 13
      LocalVariableTable:
        Start  Length  Slot  Name   Signature
            0      14     0  this   Lscala/collection/SortedMapFactory;
            0      14     1 evidence$40   Lscala/math/Ordering;
    Signature: #76                          // <K:Ljava/lang/Object;V:Ljava/lang/Object;>(Lscala/math/Ordering<TK;>;)Lscala/collection/Factory<Lscala/Tuple2<TK;TV;>;TCC;>;
    MethodParameters:
      Name                           Flags
      evidence$40                    final

  public static void $init$(scala.collection.SortedMapFactory);
    descriptor: (Lscala/collection/SortedMapFactory;)V
    flags: (0x0009) ACC_PUBLIC, ACC_STATIC
    Code:
      stack=0, locals=1, args_size=1
         0: return
      LineNumberTable:
        line 736: 0
      LocalVariableTable:
        Start  Length  Slot  Name   Signature
            0       1     0 $this   Lscala/collection/SortedMapFactory;
    MethodParameters:
      Name                           Flags
      $this                          final synthetic
}
InnerClasses:
  public static #14= #13 of #2;           // Delegate=class scala/collection/SortedMapFactory$Delegate of class scala/collection/SortedMapFactory
  private static #17= #16 of #2;          // SortedMapFactoryToBuildFrom=class scala/collection/SortedMapFactory$SortedMapFactoryToBuildFrom of class scala/collection/SortedMapFactory
  private static #20= #19 of #2;          // ToFactory=class scala/collection/SortedMapFactory$ToFactory of class scala/collection/SortedMapFactory
Signature: #3                           // <CC:Ljava/lang/Object;>Ljava/lang/Object;Ljava/io/Serializable;
SourceFile: "Factory.scala"
RuntimeVisibleAnnotations:
  0: #9(#10=s#11)
    scala.reflect.ScalaSignature(
      bytes="\u0006\u0005\tega\u0002\u0011\"!\u0003\r\tA\n\u0005\u0006g\u0001!\t\u0001\u000e\u0005\u0006q\u00011\t!\u000f\u0005\u0006-\u00021\ta\u0016\u0005\u0006W\u0002!\t\u0001\u001c\u0005\u0006{\u00021\tA \u0005\b\u0003?\u0001A1AA\u0011\u000f\u001d\ti$\tE\u0001\u0003\u007f1a\u0001I\u0011\t\u0002\u0005\u0005\u0003bBA)\u0011\u0011\u0005\u00111\u000b\u0005\b\u0003+BA1AA,\r!\t)\t\u0003Q\u0001\n\u0005\u001d\u0005BCA@\u0017\t\u0005\t\u0015!\u0003\u0002&\"Q\u0011\u0011V\u0006\u0003\u0004\u0003\u0006Y!a+\t\u000f\u0005E3\u0002\"\u0001\u0002.\"9\u0011\u0011X\u0006\u0005\u0002\u0005m\u0006BB?\f\t\u0003\t\t\rC\u0004\u0002R\"!\u0019!a5\u0007\r\t\r\u0001\u0002\u0002B\u0003\u0011)\tyH\u0005B\u0001B\u0003%!1\u0005\u0005\u000b\u0005O\u0011\"1!Q\u0001\f\t%\u0002bBA)%\u0011\u0005!1\u0006\u0005\b\u0003s\u0013B\u0011\u0001B\u001b\u0011\u0019i(\u0003\"\u0001\u0003@\u00191!Q\t\u0005\u0001\u0005\u000fB!Ba\u0017\u0019\u0005\u0003\u0005\u000b\u0011\u0002B&\u0011\u001d\t\t\u0006\u0007C\u0001\u0005;Baa\u001b\r\u0005B\t\r\u0004B\u0002,\u0019\t\u0003\u0011y\b\u0003\u000491\u0011\u0005!1\u0014\u0005\u0007{b!\tAa,\t\u0013\t%\u0007\"!A\u0005\n\t-\'\u0001E*peR,G-T1q\r\u0006\u001cGo\u001c:z\u0015\t\u00113%\u0001\u0006d_2dWm\u0019;j_:T\u0011\u0001J\u0001\u0006g\u000e\fG.Y\u0002\u0001+\t9ShE\u0002\u0001Q1\u0002\"!\u000b\u0016\u000e\u0003\rJ!aK\u0012\u0003\r\u0005s\u0017PU3g!\ti\u0003G\u0004\u0002*]%\u0011qfI\u0001\ba\u0006\u001c7.Y4f\u0013\t\t$G\u0001\u0007TKJL\u0017\r\\5{C\ndWM\u0003\u00020G\u00051A%\u001b8ji\u0012\"\u0012!\u000e\t\u0003SYJ!aN\u0012\u0003\tUs\u0017\u000e^\u0001\u0006K6\u0004H/_\u000b\u0004u1{ECA\u001eR!\u0011aTh\u0013(\r\u0001\u00111a\b\u0001CC\u0002}\u0012!aQ\"\u0016\u0007\u0001;\u0015*\u0005\u0002B\tB\u0011\u0011FQ\u0005\u0003\u0007\u000e\u0012qAT8uQ&tw\r\u0005\u0002*\u000b&\u0011ai\t\u0002\u0004\u0003:LH!\u0002%>\u0005\u0004\u0001%!B0%IM\u001aD!\u0002&>\u0005\u0004\u0001%!B0%IM\"\u0004C\u0001\u001fM\t\u0015i%A1\u0001A\u0005\u0005Y\u0005C\u0001\u001fP\t\u0015\u0001&A1\u0001A\u0005\u00051\u0006b\u0002*\u0003\u0003\u0003\u0005\u001daU\u0001\fKZLG-\u001a8dK\u0012\u001ad\u0007E\u0002.).K!!\u0016\u001a\u0003\u0011=\u0013H-\u001a:j]\u001e\fAA\u001a:p[V\u0019\u0001\f\u00180\u0015\u0005e\u0013GC\u0001.`!\u0011aThW/\u0011\u0005qbF!B\'\u0004\u0005\u0004\u0001\u0005C\u0001\u001f_\t\u0015\u00016A1\u0001A\u0011\u001d\u00017!!AA\u0004\u0005\f1\"\u001a<jI\u0016t7-\u001a\u00134oA\u0019Q\u0006V.\t\u000b\r\u001c\u0001\u0019\u00013\u0002\u0005%$\bcA3gQ6\t\u0011%\u0003\u0002hC\ta\u0011\n^3sC\ndWm\u00148dKB!\u0011&[.^\u0013\tQ7E\u0001\u0004UkBdWMM\u0001\u0006CB\u0004H._\u000b\u0004[F\u001cHC\u00018x)\tyG\u000f\u0005\u0003={A\u0014\bC\u0001\u001fr\t\u0015iEA1\u0001A!\ta4\u000fB\u0003Q\t\t\u0007\u0001\tC\u0004v\t\u0005\u0005\t9\u0001<\u0002\u0017\u00154\u0018\u000eZ3oG\u0016$3\u0007\u000f\t\u0004[Q\u0003\b\"\u0002=\u0005\u0001\u0004I\u0018!B3mK6\u001c\bcA\u0015{y&\u00111p\t\u0002\u000byI,\u0007/Z1uK\u0012t\u0004\u0003B\u0015jaJ\f!B\\3x\u0005VLG\u000eZ3s+\u0015y\u0018\u0011CA\u000b)\u0011\t\t!!\u0007\u0011\u0011\u0005\r\u0011\u0011BA\u0007\u0003/i!!!\u0002\u000b\u0007\u0005\u001d\u0011%A\u0004nkR\f\'\r\\3\n\t\u0005-\u0011Q\u0001\u0002\b\u0005VLG\u000eZ3s!\u0019I\u0013.a\u0004\u0002\u0014A\u0019A(!\u0005\u0005\u000b5+!\u0019\u0001!\u0011\u0007q\n)\u0002B\u0003Q\u000b\t\u0007\u0001\t\u0005\u0004={\u0005=\u00111\u0003\u0005\n\u00037)\u0011\u0011!a\u0002\u0003;\t1\"\u001a<jI\u0016t7-\u001a\u00134sA!Q\u0006VA\b\u0003A\u0019xN\u001d;fI6\u000b\u0007OR1di>\u0014\u00180\u0006\u0004\u0002$\u0005=\u00121\u0007\u000b\u0005\u0003K\t9\u0004E\u0004f\u0003O\tY#!\u000e\n\u0007\u0005%\u0012EA\u0004GC\u000e$xN]=\u0011\r%J\u0017QFA\u0019!\ra\u0014q\u0006\u0003\u0006\u001b\u001a\u0011\r\u0001\u0011\t\u0004y\u0005MB!\u0002)\u0007\u0005\u0004\u0001\u0005C\u0002\u001f>\u0003[\t\t\u0004C\u0005\u0002:\u0019\t\t\u0011q\u0001\u0002<\u0005YQM^5eK:\u001cW\r\n\u001b1!\u0011iC+!\f\u0002!M{\'\u000f^3e\u001b\u0006\u0004h)Y2u_JL\bCA3\t\'\u0011A\u0001&a\u0011\u0011\t\u0005\u0015\u0013qJ\u0007\u0003\u0003\u000fRA!!\u0013\u0002L\u0005\u0011\u0011n\u001c\u0006\u0003\u0003\u001b\nAA[1wC&\u0019\u0011\'a\u0012\u0002\rqJg.\u001b;?)\t\ty$A\u0005u_\u001a\u000b7\r^8ssVA\u0011\u0011LA2\u0003O\nY\u0007\u0006\u0003\u0002\\\u0005uD\u0003BA/\u0003o\u0002r!ZA\u0014\u0003?\nI\u0007\u0005\u0004*S\u0006\u0005\u0014Q\r\t\u0004y\u0005\rD!B\'\u000b\u0005\u0004\u0001\u0005c\u0001\u001f\u0002h\u0011)\u0001K\u0003b\u0001\u0001B9A(a\u001b\u0002b\u0005\u0015DA\u0002 \u000b\u0005\u0004\ti\'F\u0003A\u0003_\n\u0019\bB\u0004\u0002r\u0005-$\u0019\u0001!\u0003\u000b}#CeM\u001b\u0005\u000f\u0005U\u00141\u000eb\u0001\u0001\n)q\f\n\u00134m!I\u0011\u0011\u0010\u0006\u0002\u0002\u0003\u000f\u00111P\u0001\fKZLG-\u001a8dK\u0012\"\u0014\u0007\u0005\u0003.)\u0006\u0005\u0004bBA@\u0015\u0001\u0007\u0011\u0011Q\u0001\bM\u0006\u001cGo\u001c:z!\u0011)\u0007!a!\u0011\u0007q\nYGA\u0005U_\u001a\u000b7\r^8ssVA\u0011\u0011RAI\u0003+\u000bIjE\u0003\fQ\u0005-E\u0006E\u0004f\u0003O\ti)a&\u0011\r%J\u0017qRAJ!\ra\u0014\u0011\u0013\u0003\u0006\u001b.\u0011\r\u0001\u0011\t\u0004y\u0005UE!\u0002)\f\u0005\u0004\u0001\u0005c\u0002\u001f\u0002\u001a\u0006=\u00151\u0013\u0003\u0007}-\u0011\r!a\'\u0016\u000b\u0001\u000bi*!)\u0005\u000f\u0005}\u0015\u0011\u0014b\u0001\u0001\n)q\f\n\u00134o\u00119\u00111UAM\u0005\u0004\u0001%!B0%IMB\u0004\u0003B3\u0001\u0003O\u00032\u0001PAM\u0003-)g/\u001b3f]\u000e,G\u0005\u000e\u001a\u0011\t5\"\u0016q\u0012\u000b\u0005\u0003_\u000b9\f\u0006\u0003\u00022\u0006U\u0006#CAZ\u0017\u0005=\u00151SAT\u001b\u0005A\u0001bBAU\u001d\u0001\u000f\u00111\u0016\u0005\b\u0003\u007fr\u0001\u0019AAS\u000311\'o\\7Ta\u0016\u001c\u0017NZ5d)\u0011\t9*!0\t\r\r|\u0001\u0019AA`!\u0011)g-!$\u0016\u0005\u0005\r\u0007\u0003CA\u0002\u0003\u0013\ti)a&)\u000f-\t9-!4\u0002PB\u0019\u0011&!3\n\u0007\u0005-7E\u0001\tTKJL\u0017\r\u001c,feNLwN\\+J\t\u0006)a/\u00197vKz\t1!A\u0006u_\n+\u0018\u000e\u001c3Ge>lW\u0003CAk\u0003G\f9/a;\u0015\t\u0005]\u0017Q \u000b\u0005\u00033\f9\u0010\u0005\u0005f\u00037$\u0015q\\Au\u0013\r\ti.\t\u0002\n\u0005VLG\u000e\u001a$s_6\u0004b!K5\u0002b\u0006\u0015\bc\u0001\u001f\u0002d\u0012)Q*\u0005b\u0001\u0001B\u0019A(a:\u0005\u000bA\u000b\"\u0019\u0001!\u0011\u000fq\nY/!9\u0002f\u00121a(\u0005b\u0001\u0003[,R\u0001QAx\u0003g$q!!=\u0002l\n\u0007\u0001IA\u0003`I\u0011\u001a\u0014\bB\u0004\u0002v\u0006-(\u0019\u0001!\u0003\u000b}#C\u0005\u000e\u0019\t\u0013\u0005e\u0018#!AA\u0004\u0005m\u0018aC3wS\u0012,gnY3%iM\u0002B!\f+\u0002b\"9\u0011qP\tA\u0002\u0005}\b\u0003B3\u0001\u0005\u0003\u00012\u0001PAv\u0005m\u0019vN\u001d;fI6\u000b\u0007OR1di>\u0014\u0018\u0010V8Ck&dGM\u0012:p[VA!q\u0001B\b\u0005\'\u00119b\u0005\u0003\u0013Q\t%\u0001\u0003C3\u0002\\\u0012\u0013YA!\u0006\u0011\r%J\'Q\u0002B\t!\ra$q\u0002\u0003\u0006\u001bJ\u0011\r\u0001\u0011\t\u0004y\tMA!\u0002)\u0013\u0005\u0004\u0001\u0005c\u0002\u001f\u0003\u0018\t5!\u0011\u0003\u0003\u0007}I\u0011\rA!\u0007\u0016\u000b\u0001\u0013YBa\b\u0005\u000f\tu!q\u0003b\u0001\u0001\n)q\f\n\u00135c\u00119!\u0011\u0005B\f\u0005\u0004\u0001%!B0%IQ\u0012\u0004\u0003B3\u0001\u0005K\u00012\u0001\u0010B\f\u0003-)g/\u001b3f]\u000e,G\u0005\u000e\u001b\u0011\t5\"&Q\u0002\u000b\u0005\u0005[\u0011\u0019\u0004\u0006\u0003\u00030\tE\u0002#CAZ%\t5!\u0011\u0003B\u0013\u0011\u001d\u00119#\u0006a\u0002\u0005SAq!a \u0016\u0001\u0004\u0011\u0019\u0003\u0006\u0003\u00038\tuB\u0003\u0002B\u000b\u0005sAaa\u0019\fA\u0002\tm\u0002\u0003B3g\u0005\u0017AQA\u0016\fA\u0002\u0011#BA!\u0011\u0003DAA\u00111AA\u0005\u0005\u0017\u0011)\u0002C\u0003W/\u0001\u0007AI\u0001\u0005EK2,w-\u0019;f+\u0011\u0011IEa\u0014\u0014\taA#1\n\t\u0005K\u0002\u0011i\u0005E\u0002=\u0005\u001f\"aA\u0010\rC\u0002\tES#\u0002!\u0003T\t]Ca\u0002B+\u0005\u001f\u0012\r\u0001\u0011\u0002\u0006?\u0012\"Cg\r\u0003\b\u00053\u0012yE1\u0001A\u0005\u0015yF\u0005\n\u001b5\u0003!!W\r\\3hCR,G\u0003\u0002B0\u0005C\u0002R!a-\u0019\u0005\u001bBqAa\u0017\u001b\u0001\u0004\u0011Y%\u0006\u0004\u0003f\t5$\u0011\u000f\u000b\u0005\u0005O\u0012I\b\u0006\u0003\u0003j\tM\u0004c\u0002\u001f\u0003P\t-$q\u000e\t\u0004y\t5D!B\'\u001c\u0005\u0004\u0001\u0005c\u0001\u001f\u0003r\u0011)\u0001k\u0007b\u0001\u0001\"I!QO\u000e\u0002\u0002\u0003\u000f!qO\u0001\fKZLG-\u001a8dK\u0012\"T\u0007\u0005\u0003.)\n-\u0004B\u0002=\u001c\u0001\u0004\u0011Y\b\u0005\u0003*u\nu\u0004CB\u0015j\u0005W\u0012y\'\u0006\u0004\u0003\u0002\n%%Q\u0012\u000b\u0005\u0005\u0007\u0013)\n\u0006\u0003\u0003\u0006\n=\u0005c\u0002\u001f\u0003P\t\u001d%1\u0012\t\u0004y\t%E!B\'\u001d\u0005\u0004\u0001\u0005c\u0001\u001f\u0003\u000e\u0012)\u0001\u000b\bb\u0001\u0001\"I!\u0011\u0013\u000f\u0002\u0002\u0003\u000f!1S\u0001\fKZLG-\u001a8dK\u0012\"d\u0007\u0005\u0003.)\n\u001d\u0005BB2\u001d\u0001\u0004\u00119\n\u0005\u0003fM\ne\u0005CB\u0015j\u0005\u000f\u0013Y)\u0006\u0004\u0003\u001e\n\r&q\u0015\u000b\u0005\u0005?\u0013I\u000bE\u0004=\u0005\u001f\u0012\tK!*\u0011\u0007q\u0012\u0019\u000bB\u0003N;\t\u0007\u0001\tE\u0002=\u0005O#Q\u0001U\u000fC\u0002\u0001C\u0011Ba+\u001e\u0003\u0003\u0005\u001dA!,\u0002\u0017\u00154\u0018\u000eZ3oG\u0016$Cg\u000e\t\u0005[Q\u0013\t+\u0006\u0004\u00032\ne&Q\u0018\u000b\u0005\u0005g\u0013\t\r\u0005\u0005\u0002\u0004\u0005%!Q\u0017B`!\u0019I\u0013Na.\u0003<B\u0019AH!/\u0005\u000b5s\"\u0019\u0001!\u0011\u0007q\u0012i\fB\u0003Q=\t\u0007\u0001\tE\u0004=\u0005\u001f\u00129La/\t\u0013\t\rg$!AA\u0004\t\u0015\u0017aC3wS\u0012,gnY3%ia\u0002B!\f+\u00038\":\u0001$a2\u0002N\u0006=\u0017\u0001D<sSR,\'+\u001a9mC\u000e,GC\u0001Bg!\u0011\u0011yM!6\u000e\u0005\tE\'\u0002\u0002Bj\u0003\u0017\nA\u0001\\1oO&!!q\u001bBi\u0005\u0019y%M[3di\u0002"
    )
  ScalaInlineInfo: length = 0x2C (unknown attribute)
   01 00 00 08 00 4D 00 4E 01 00 39 00 3A 00 00 34
   00 35 01 00 2B 00 2C 00 00 2F 00 30 00 00 42 00
   43 00 00 48 00 49 00 00 46 00 27 01
  ScalaSig: length = 0x3 (unknown attribute)
   05 02 00
