Classfile /Users/mw/Projects/slang-braindump/.jar/jar11/assemble/slang-braindump/assemble/content/scala/collection/SortedOps.class
  Last modified May 29, 2022; size 4145 bytes
  SHA-256 checksum f4c3092c426501b67b342cf77ea2804143006d67f35aac88b1eccf1f4d545d8a
  Compiled from "SortedOps.scala"
public interface scala.collection.SortedOps<A extends java.lang.Object, C extends java.lang.Object>
  minor version: 0
  major version: 52
  flags: (0x0601) ACC_PUBLIC, ACC_INTERFACE, ACC_ABSTRACT
  this_class: #2                          // scala/collection/SortedOps
  super_class: #5                         // java/lang/Object
  interfaces: 0, fields: 0, methods: 20, attributes: 5
Constant pool:
   #1 = Utf8               scala/collection/SortedOps
   #2 = Class              #1             // scala/collection/SortedOps
   #3 = Utf8               <A:Ljava/lang/Object;C:Ljava/lang/Object;>Ljava/lang/Object;
   #4 = Utf8               java/lang/Object
   #5 = Class              #4             // java/lang/Object
   #6 = Utf8               SortedOps.scala
   #7 = Utf8               Lscala/reflect/ScalaSignature;
   #8 = Utf8               bytes
   #9 = Utf8               \u0006\u0005}4qAD\b\u0011\u0002\u0007\u0005A\u0003C\u0003\u001b\u0001\u0011\u00051\u0004C\u0003 \u0001\u0019\u0005\u0001\u0005C\u00039\u0001\u0019\u0005\u0011\bC\u0003;\u0001\u0019\u0005\u0011\bC\u0003<\u0001\u0011\u0005A\bC\u0003W\u0001\u0019\u0005q\u000bC\u0003c\u0001\u0011\u00051\rC\u0003]\u0001\u0011\u0015a\rC\u0003l\u0001\u0011\u0005A\u000eC\u0003b\u0001\u0011\u0015a\u000eC\u0003t\u0001\u0011\u0005A\u000fC\u0003w\u0001\u0011\u0015q\u000fC\u0003}\u0001\u0019\u0005QPA\u0005T_J$X\rZ(qg*\u0011\u0001#E\u0001\u000bG>dG.Z2uS>t\'\"\u0001\n\u0002\u000bM\u001c\u0017\r\\1\u0004\u0001U\u0019QcL-\u0014\u0005\u00011\u0002CA\f\u0019\u001b\u0005\t\u0012BA\r\u0012\u0005\u0019\te.\u001f*fM\u00061A%\u001b8ji\u0012\"\u0012\u0001\b\t\u0003/uI!AH\t\u0003\tUs\u0017\u000e^\u0001\t_J$WM]5oOV\t\u0011\u0005E\u0002#U5r!a\t\u0015\u000f\u0005\u0011:S\"A\u0013\u000b\u0005\u0019\u001a\u0012A\u0002\u001fs_>$h(C\u0001\u0013\u0013\tI\u0013#A\u0004qC\u000e\\\u0017mZ3\n\u0005-b#\u0001C(sI\u0016\u0014\u0018N\\4\u000b\u0005%\n\u0002C\u0001\u00180\u0019\u0001!Q\u0001\r\u0001C\u0002E\u0012\u0011!Q\t\u0003eU\u0002\"aF\u001a\n\u0005Q\n\"a\u0002(pi\"Lgn\u001a\t\u0003/YJ!aN\t\u0003\u0007\u0005s\u00170\u0001\u0005gSJ\u001cHoS3z+\u0005i\u0013a\u00027bgR\\U-_\u0001\bG>l\u0007/\u0019:f)\ri\u0004I\u0011\t\u0003/yJ!aP\t\u0003\u0007%sG\u000fC\u0003B\u000b\u0001\u0007Q&\u0001\u0002la!)1)\u0002a\u0001[\u0005\u00111.\r\u0015\u0003\u000b\u0015\u0003\"a\u0006$\n\u0005\u001d\u000b\"AB5oY&tW\r\u000b\u0004\u0006\u00132ku\n\u0015\t\u0003/)K!aS\t\u0003)\u0011,\u0007O]3dCR,Gm\u0014<feJLG-\u001b8h\u0003\u001diWm]:bO\u0016\f\u0013AT\u0001\u001d+N,\u0007e\u001c:eKJLgn\u001a\u0018d_6\u0004\u0018M]3!S:\u001cH/Z1e\u0003\u0015\u0019\u0018N\\2fC\u0005\t\u0016A\u0002\u001a/cMr\u0003\u0007\u000b\u0004\u0006\'2ku\n\u0015\t\u0003/QK!!V\t\u0003\u0015\u0011,\u0007O]3dCR,G-A\u0005sC:<W-S7qYR\u0019\u0001l\u00171\u0011\u00059JFA\u0002.\u0001\t\u000b\u0007\u0011GA\u0001D\u0011\u0015af\u00011\u0001^\u0003\u00111\'o\\7\u0011\u0007]qV&\u0003\u0002`#\t1q\n\u001d;j_:DQ!\u0019\u0004A\u0002u\u000bQ!\u001e8uS2\fQA]1oO\u0016$2\u0001\u00173f\u0011\u0015av\u00011\u0001.\u0011\u0015\tw\u00011\u0001.)\tAv\rC\u0003]\u0011\u0001\u0007Q\u0006\u000b\u0004\t\'2Kw\nU\u0011\u0002U\u0006iQk]3!e\u0006tw-\u001a$s_6\f\u0011B]1oO\u00164%o\\7\u0015\u0005ak\u0007\"\u0002/\n\u0001\u0004iCC\u0001-p\u0011\u0015\t\'\u00021\u0001.Q\u0019Q1\u000bT9P!\u0006\n!/\u0001\bVg\u0016\u0004#/\u00198hKVsG/\u001b7\u0002\u0015I\fgnZ3V]RLG\u000e\u0006\u0002Yk\")\u0011m\u0003a\u0001[\u0005\u0011Ao\u001c\u000b\u00031bDQA\u001e\u0007A\u00025Bc\u0001D*Mu>\u0003\u0016%A>\u0002\u0017U\u001bX\r\t:b]\u001e,Gk\\\u0001\be\u0006tw-\u001a+p)\tAf\u0010C\u0003w\u001b\u0001\u0007Q\u0006
  #10 = Utf8               ordering
  #11 = Utf8               ()Lscala/math/Ordering;
  #12 = Utf8               ()Lscala/math/Ordering<TA;>;
  #13 = Utf8               firstKey
  #14 = Utf8               ()Ljava/lang/Object;
  #15 = Utf8               ()TA;
  #16 = Utf8               lastKey
  #17 = Utf8               compare$
  #18 = Utf8               (Lscala/collection/SortedOps;Ljava/lang/Object;Ljava/lang/Object;)I
  #19 = Utf8               $this
  #20 = Utf8               k0
  #21 = Utf8               k1
  #22 = Utf8               compare
  #23 = Utf8               (Ljava/lang/Object;Ljava/lang/Object;)I
  #24 = NameAndType        #22:#23        // compare:(Ljava/lang/Object;Ljava/lang/Object;)I
  #25 = InterfaceMethodref #2.#24         // scala/collection/SortedOps.compare:(Ljava/lang/Object;Ljava/lang/Object;)I
  #26 = Utf8               Lscala/collection/SortedOps;
  #27 = Utf8               Ljava/lang/Object;
  #28 = Utf8               (TA;TA;)I
  #29 = NameAndType        #10:#11        // ordering:()Lscala/math/Ordering;
  #30 = InterfaceMethodref #2.#29         // scala/collection/SortedOps.ordering:()Lscala/math/Ordering;
  #31 = Utf8               scala/math/Ordering
  #32 = Class              #31            // scala/math/Ordering
  #33 = InterfaceMethodref #32.#24        // scala/math/Ordering.compare:(Ljava/lang/Object;Ljava/lang/Object;)I
  #34 = Utf8               this
  #35 = Utf8               rangeImpl
  #36 = Utf8               (Lscala/Option;Lscala/Option;)Ljava/lang/Object;
  #37 = Utf8               (Lscala/Option<TA;>;Lscala/Option<TA;>;)TC;
  #38 = Utf8               from
  #39 = Utf8               until
  #40 = Utf8               range$
  #41 = Utf8               (Lscala/collection/SortedOps;Ljava/lang/Object;Ljava/lang/Object;)Ljava/lang/Object;
  #42 = Utf8               range
  #43 = Utf8               (Ljava/lang/Object;Ljava/lang/Object;)Ljava/lang/Object;
  #44 = NameAndType        #42:#43        // range:(Ljava/lang/Object;Ljava/lang/Object;)Ljava/lang/Object;
  #45 = InterfaceMethodref #2.#44         // scala/collection/SortedOps.range:(Ljava/lang/Object;Ljava/lang/Object;)Ljava/lang/Object;
  #46 = Utf8               (TA;TA;)TC;
  #47 = Utf8               scala/Some
  #48 = Class              #47            // scala/Some
  #49 = Utf8               <init>
  #50 = Utf8               (Ljava/lang/Object;)V
  #51 = NameAndType        #49:#50        // "<init>":(Ljava/lang/Object;)V
  #52 = Methodref          #48.#51        // scala/Some."<init>":(Ljava/lang/Object;)V
  #53 = NameAndType        #35:#36        // rangeImpl:(Lscala/Option;Lscala/Option;)Ljava/lang/Object;
  #54 = InterfaceMethodref #2.#53         // scala/collection/SortedOps.rangeImpl:(Lscala/Option;Lscala/Option;)Ljava/lang/Object;
  #55 = Utf8               from$
  #56 = Utf8               (Lscala/collection/SortedOps;Ljava/lang/Object;)Ljava/lang/Object;
  #57 = Utf8               (Ljava/lang/Object;)Ljava/lang/Object;
  #58 = NameAndType        #38:#57        // from:(Ljava/lang/Object;)Ljava/lang/Object;
  #59 = InterfaceMethodref #2.#58         // scala/collection/SortedOps.from:(Ljava/lang/Object;)Ljava/lang/Object;
  #60 = Utf8               (TA;)TC;
  #61 = Utf8               rangeFrom
  #62 = NameAndType        #61:#57        // rangeFrom:(Ljava/lang/Object;)Ljava/lang/Object;
  #63 = InterfaceMethodref #2.#62         // scala/collection/SortedOps.rangeFrom:(Ljava/lang/Object;)Ljava/lang/Object;
  #64 = Utf8               rangeFrom$
  #65 = Utf8               scala/None$
  #66 = Class              #65            // scala/None$
  #67 = Utf8               MODULE$
  #68 = Utf8               Lscala/None$;
  #69 = NameAndType        #67:#68        // MODULE$:Lscala/None$;
  #70 = Fieldref           #66.#69        // scala/None$.MODULE$:Lscala/None$;
  #71 = Utf8               until$
  #72 = NameAndType        #39:#57        // until:(Ljava/lang/Object;)Ljava/lang/Object;
  #73 = InterfaceMethodref #2.#72         // scala/collection/SortedOps.until:(Ljava/lang/Object;)Ljava/lang/Object;
  #74 = Utf8               rangeUntil
  #75 = NameAndType        #74:#57        // rangeUntil:(Ljava/lang/Object;)Ljava/lang/Object;
  #76 = InterfaceMethodref #2.#75         // scala/collection/SortedOps.rangeUntil:(Ljava/lang/Object;)Ljava/lang/Object;
  #77 = Utf8               rangeUntil$
  #78 = Utf8               to$
  #79 = Utf8               to
  #80 = NameAndType        #79:#57        // to:(Ljava/lang/Object;)Ljava/lang/Object;
  #81 = InterfaceMethodref #2.#80         // scala/collection/SortedOps.to:(Ljava/lang/Object;)Ljava/lang/Object;
  #82 = Utf8               rangeTo
  #83 = NameAndType        #82:#57        // rangeTo:(Ljava/lang/Object;)Ljava/lang/Object;
  #84 = InterfaceMethodref #2.#83         // scala/collection/SortedOps.rangeTo:(Ljava/lang/Object;)Ljava/lang/Object;
  #85 = Utf8               $init$
  #86 = Utf8               (Lscala/collection/SortedOps;)V
  #87 = Utf8               Signature
  #88 = Utf8               Code
  #89 = Utf8               LineNumberTable
  #90 = Utf8               LocalVariableTable
  #91 = Utf8               MethodParameters
  #92 = Utf8               Deprecated
  #93 = Utf8               SourceFile
  #94 = Utf8               RuntimeVisibleAnnotations
  #95 = Utf8               ScalaInlineInfo
  #96 = Utf8               ScalaSig
{
  public abstract scala.math.Ordering<A> ordering();
    descriptor: ()Lscala/math/Ordering;
    flags: (0x0401) ACC_PUBLIC, ACC_ABSTRACT
    Signature: #12                          // ()Lscala/math/Ordering<TA;>;

  public abstract A firstKey();
    descriptor: ()Ljava/lang/Object;
    flags: (0x0401) ACC_PUBLIC, ACC_ABSTRACT
    Signature: #15                          // ()TA;

  public abstract A lastKey();
    descriptor: ()Ljava/lang/Object;
    flags: (0x0401) ACC_PUBLIC, ACC_ABSTRACT
    Signature: #15                          // ()TA;

  public static int compare$(scala.collection.SortedOps, java.lang.Object, java.lang.Object);
    descriptor: (Lscala/collection/SortedOps;Ljava/lang/Object;Ljava/lang/Object;)I
    flags: (0x1009) ACC_PUBLIC, ACC_STATIC, ACC_SYNTHETIC
    Code:
      stack=3, locals=3, args_size=3
         0: aload_0
         1: aload_1
         2: aload_2
         3: invokespecial #25                 // InterfaceMethod compare:(Ljava/lang/Object;Ljava/lang/Object;)I
         6: ireturn
      LineNumberTable:
        line 30: 0
      LocalVariableTable:
        Start  Length  Slot  Name   Signature
            0       7     0 $this   Lscala/collection/SortedOps;
            0       7     1    k0   Ljava/lang/Object;
            0       7     2    k1   Ljava/lang/Object;
    MethodParameters:
      Name                           Flags
      $this                          final synthetic
      k0                             final
      k1                             final

  public default int compare(A, A);
    descriptor: (Ljava/lang/Object;Ljava/lang/Object;)I
    flags: (0x0001) ACC_PUBLIC
    Code:
      stack=3, locals=3, args_size=3
         0: aload_0
         1: invokeinterface #30,  1           // InterfaceMethod ordering:()Lscala/math/Ordering;
         6: aload_1
         7: aload_2
         8: invokeinterface #33,  3           // InterfaceMethod scala/math/Ordering.compare:(Ljava/lang/Object;Ljava/lang/Object;)I
        13: ireturn
      LineNumberTable:
        line 30: 0
      LocalVariableTable:
        Start  Length  Slot  Name   Signature
            0      14     0  this   Lscala/collection/SortedOps;
            0      14     1    k0   Ljava/lang/Object;
            0      14     2    k1   Ljava/lang/Object;
    Signature: #28                          // (TA;TA;)I
    Deprecated: true
    MethodParameters:
      Name                           Flags
      k0                             final
      k1                             final

  public abstract C rangeImpl(scala.Option<A>, scala.Option<A>);
    descriptor: (Lscala/Option;Lscala/Option;)Ljava/lang/Object;
    flags: (0x0401) ACC_PUBLIC, ACC_ABSTRACT
    Signature: #37                          // (Lscala/Option<TA;>;Lscala/Option<TA;>;)TC;
    MethodParameters:
      Name                           Flags
      from                           final
      until                          final

  public static java.lang.Object range$(scala.collection.SortedOps, java.lang.Object, java.lang.Object);
    descriptor: (Lscala/collection/SortedOps;Ljava/lang/Object;Ljava/lang/Object;)Ljava/lang/Object;
    flags: (0x1009) ACC_PUBLIC, ACC_STATIC, ACC_SYNTHETIC
    Code:
      stack=3, locals=3, args_size=3
         0: aload_0
         1: aload_1
         2: aload_2
         3: invokespecial #45                 // InterfaceMethod range:(Ljava/lang/Object;Ljava/lang/Object;)Ljava/lang/Object;
         6: areturn
      LineNumberTable:
        line 52: 0
      LocalVariableTable:
        Start  Length  Slot  Name   Signature
            0       7     0 $this   Lscala/collection/SortedOps;
            0       7     1  from   Ljava/lang/Object;
            0       7     2 until   Ljava/lang/Object;
    MethodParameters:
      Name                           Flags
      $this                          final synthetic
      from                           final
      until                          final

  public default C range(A, A);
    descriptor: (Ljava/lang/Object;Ljava/lang/Object;)Ljava/lang/Object;
    flags: (0x0001) ACC_PUBLIC
    Code:
      stack=5, locals=3, args_size=3
         0: aload_0
         1: new           #48                 // class scala/Some
         4: dup
         5: aload_1
         6: invokespecial #52                 // Method scala/Some."<init>":(Ljava/lang/Object;)V
         9: new           #48                 // class scala/Some
        12: dup
        13: aload_2
        14: invokespecial #52                 // Method scala/Some."<init>":(Ljava/lang/Object;)V
        17: invokeinterface #54,  3           // InterfaceMethod rangeImpl:(Lscala/Option;Lscala/Option;)Ljava/lang/Object;
        22: areturn
      LineNumberTable:
        line 52: 0
      LocalVariableTable:
        Start  Length  Slot  Name   Signature
            0      23     0  this   Lscala/collection/SortedOps;
            0      23     1  from   Ljava/lang/Object;
            0      23     2 until   Ljava/lang/Object;
    Signature: #46                          // (TA;TA;)TC;
    MethodParameters:
      Name                           Flags
      from                           final
      until                          final

  public static java.lang.Object from$(scala.collection.SortedOps, java.lang.Object);
    descriptor: (Lscala/collection/SortedOps;Ljava/lang/Object;)Ljava/lang/Object;
    flags: (0x1009) ACC_PUBLIC, ACC_STATIC, ACC_SYNTHETIC
    Code:
      stack=2, locals=2, args_size=2
         0: aload_0
         1: aload_1
         2: invokespecial #59                 // InterfaceMethod from:(Ljava/lang/Object;)Ljava/lang/Object;
         5: areturn
      LineNumberTable:
        line 59: 0
      LocalVariableTable:
        Start  Length  Slot  Name   Signature
            0       6     0 $this   Lscala/collection/SortedOps;
            0       6     1  from   Ljava/lang/Object;
    MethodParameters:
      Name                           Flags
      $this                          final synthetic
      from                           final

  public default C from(A);
    descriptor: (Ljava/lang/Object;)Ljava/lang/Object;
    flags: (0x0001) ACC_PUBLIC
    Code:
      stack=2, locals=2, args_size=2
         0: aload_0
         1: aload_1
         2: invokeinterface #63,  2           // InterfaceMethod rangeFrom:(Ljava/lang/Object;)Ljava/lang/Object;
         7: areturn
      LineNumberTable:
        line 59: 0
      LocalVariableTable:
        Start  Length  Slot  Name   Signature
            0       8     0  this   Lscala/collection/SortedOps;
            0       8     1  from   Ljava/lang/Object;
    Signature: #60                          // (TA;)TC;
    Deprecated: true
    MethodParameters:
      Name                           Flags
      from                           final

  public static java.lang.Object rangeFrom$(scala.collection.SortedOps, java.lang.Object);
    descriptor: (Lscala/collection/SortedOps;Ljava/lang/Object;)Ljava/lang/Object;
    flags: (0x1009) ACC_PUBLIC, ACC_STATIC, ACC_SYNTHETIC
    Code:
      stack=2, locals=2, args_size=2
         0: aload_0
         1: aload_1
         2: invokespecial #63                 // InterfaceMethod rangeFrom:(Ljava/lang/Object;)Ljava/lang/Object;
         5: areturn
      LineNumberTable:
        line 65: 0
      LocalVariableTable:
        Start  Length  Slot  Name   Signature
            0       6     0 $this   Lscala/collection/SortedOps;
            0       6     1  from   Ljava/lang/Object;
    MethodParameters:
      Name                           Flags
      $this                          final synthetic
      from                           final

  public default C rangeFrom(A);
    descriptor: (Ljava/lang/Object;)Ljava/lang/Object;
    flags: (0x0001) ACC_PUBLIC
    Code:
      stack=4, locals=2, args_size=2
         0: aload_0
         1: new           #48                 // class scala/Some
         4: dup
         5: aload_1
         6: invokespecial #52                 // Method scala/Some."<init>":(Ljava/lang/Object;)V
         9: getstatic     #70                 // Field scala/None$.MODULE$:Lscala/None$;
        12: invokeinterface #54,  3           // InterfaceMethod rangeImpl:(Lscala/Option;Lscala/Option;)Ljava/lang/Object;
        17: areturn
      LineNumberTable:
        line 65: 0
      LocalVariableTable:
        Start  Length  Slot  Name   Signature
            0      18     0  this   Lscala/collection/SortedOps;
            0      18     1  from   Ljava/lang/Object;
    Signature: #60                          // (TA;)TC;
    MethodParameters:
      Name                           Flags
      from                           final

  public static java.lang.Object until$(scala.collection.SortedOps, java.lang.Object);
    descriptor: (Lscala/collection/SortedOps;Ljava/lang/Object;)Ljava/lang/Object;
    flags: (0x1009) ACC_PUBLIC, ACC_STATIC, ACC_SYNTHETIC
    Code:
      stack=2, locals=2, args_size=2
         0: aload_0
         1: aload_1
         2: invokespecial #73                 // InterfaceMethod until:(Ljava/lang/Object;)Ljava/lang/Object;
         5: areturn
      LineNumberTable:
        line 72: 0
      LocalVariableTable:
        Start  Length  Slot  Name   Signature
            0       6     0 $this   Lscala/collection/SortedOps;
            0       6     1 until   Ljava/lang/Object;
    MethodParameters:
      Name                           Flags
      $this                          final synthetic
      until                          final

  public default C until(A);
    descriptor: (Ljava/lang/Object;)Ljava/lang/Object;
    flags: (0x0001) ACC_PUBLIC
    Code:
      stack=2, locals=2, args_size=2
         0: aload_0
         1: aload_1
         2: invokeinterface #76,  2           // InterfaceMethod rangeUntil:(Ljava/lang/Object;)Ljava/lang/Object;
         7: areturn
      LineNumberTable:
        line 72: 0
      LocalVariableTable:
        Start  Length  Slot  Name   Signature
            0       8     0  this   Lscala/collection/SortedOps;
            0       8     1 until   Ljava/lang/Object;
    Signature: #60                          // (TA;)TC;
    Deprecated: true
    MethodParameters:
      Name                           Flags
      until                          final

  public static java.lang.Object rangeUntil$(scala.collection.SortedOps, java.lang.Object);
    descriptor: (Lscala/collection/SortedOps;Ljava/lang/Object;)Ljava/lang/Object;
    flags: (0x1009) ACC_PUBLIC, ACC_STATIC, ACC_SYNTHETIC
    Code:
      stack=2, locals=2, args_size=2
         0: aload_0
         1: aload_1
         2: invokespecial #76                 // InterfaceMethod rangeUntil:(Ljava/lang/Object;)Ljava/lang/Object;
         5: areturn
      LineNumberTable:
        line 78: 0
      LocalVariableTable:
        Start  Length  Slot  Name   Signature
            0       6     0 $this   Lscala/collection/SortedOps;
            0       6     1 until   Ljava/lang/Object;
    MethodParameters:
      Name                           Flags
      $this                          final synthetic
      until                          final

  public default C rangeUntil(A);
    descriptor: (Ljava/lang/Object;)Ljava/lang/Object;
    flags: (0x0001) ACC_PUBLIC
    Code:
      stack=5, locals=2, args_size=2
         0: aload_0
         1: getstatic     #70                 // Field scala/None$.MODULE$:Lscala/None$;
         4: new           #48                 // class scala/Some
         7: dup
         8: aload_1
         9: invokespecial #52                 // Method scala/Some."<init>":(Ljava/lang/Object;)V
        12: invokeinterface #54,  3           // InterfaceMethod rangeImpl:(Lscala/Option;Lscala/Option;)Ljava/lang/Object;
        17: areturn
      LineNumberTable:
        line 78: 0
      LocalVariableTable:
        Start  Length  Slot  Name   Signature
            0      18     0  this   Lscala/collection/SortedOps;
            0      18     1 until   Ljava/lang/Object;
    Signature: #60                          // (TA;)TC;
    MethodParameters:
      Name                           Flags
      until                          final

  public static java.lang.Object to$(scala.collection.SortedOps, java.lang.Object);
    descriptor: (Lscala/collection/SortedOps;Ljava/lang/Object;)Ljava/lang/Object;
    flags: (0x1009) ACC_PUBLIC, ACC_STATIC, ACC_SYNTHETIC
    Code:
      stack=2, locals=2, args_size=2
         0: aload_0
         1: aload_1
         2: invokespecial #81                 // InterfaceMethod to:(Ljava/lang/Object;)Ljava/lang/Object;
         5: areturn
      LineNumberTable:
        line 84: 0
      LocalVariableTable:
        Start  Length  Slot  Name   Signature
            0       6     0 $this   Lscala/collection/SortedOps;
            0       6     1    to   Ljava/lang/Object;
    MethodParameters:
      Name                           Flags
      $this                          final synthetic
      to                             final

  public default C to(A);
    descriptor: (Ljava/lang/Object;)Ljava/lang/Object;
    flags: (0x0001) ACC_PUBLIC
    Code:
      stack=2, locals=2, args_size=2
         0: aload_0
         1: aload_1
         2: invokeinterface #84,  2           // InterfaceMethod rangeTo:(Ljava/lang/Object;)Ljava/lang/Object;
         7: areturn
      LineNumberTable:
        line 84: 0
      LocalVariableTable:
        Start  Length  Slot  Name   Signature
            0       8     0  this   Lscala/collection/SortedOps;
            0       8     1    to   Ljava/lang/Object;
    Signature: #60                          // (TA;)TC;
    Deprecated: true
    MethodParameters:
      Name                           Flags
      to                             final

  public abstract C rangeTo(A);
    descriptor: (Ljava/lang/Object;)Ljava/lang/Object;
    flags: (0x0401) ACC_PUBLIC, ACC_ABSTRACT
    Signature: #60                          // (TA;)TC;
    MethodParameters:
      Name                           Flags
      to                             final

  public static void $init$(scala.collection.SortedOps);
    descriptor: (Lscala/collection/SortedOps;)V
    flags: (0x0009) ACC_PUBLIC, ACC_STATIC
    Code:
      stack=0, locals=1, args_size=1
         0: return
      LineNumberTable:
        line 17: 0
      LocalVariableTable:
        Start  Length  Slot  Name   Signature
            0       1     0 $this   Lscala/collection/SortedOps;
    MethodParameters:
      Name                           Flags
      $this                          final synthetic
}
Signature: #3                           // <A:Ljava/lang/Object;C:Ljava/lang/Object;>Ljava/lang/Object;
SourceFile: "SortedOps.scala"
RuntimeVisibleAnnotations:
  0: #7(#8=s#9)
    scala.reflect.ScalaSignature(
      bytes="\u0006\u0005}4qAD\b\u0011\u0002\u0007\u0005A\u0003C\u0003\u001b\u0001\u0011\u00051\u0004C\u0003 \u0001\u0019\u0005\u0001\u0005C\u00039\u0001\u0019\u0005\u0011\bC\u0003;\u0001\u0019\u0005\u0011\bC\u0003<\u0001\u0011\u0005A\bC\u0003W\u0001\u0019\u0005q\u000bC\u0003c\u0001\u0011\u00051\rC\u0003]\u0001\u0011\u0015a\rC\u0003l\u0001\u0011\u0005A\u000eC\u0003b\u0001\u0011\u0015a\u000eC\u0003t\u0001\u0011\u0005A\u000fC\u0003w\u0001\u0011\u0015q\u000fC\u0003}\u0001\u0019\u0005QPA\u0005T_J$X\rZ(qg*\u0011\u0001#E\u0001\u000bG>dG.Z2uS>t\'\"\u0001\n\u0002\u000bM\u001c\u0017\r\\1\u0004\u0001U\u0019QcL-\u0014\u0005\u00011\u0002CA\f\u0019\u001b\u0005\t\u0012BA\r\u0012\u0005\u0019\te.\u001f*fM\u00061A%\u001b8ji\u0012\"\u0012\u0001\b\t\u0003/uI!AH\t\u0003\tUs\u0017\u000e^\u0001\t_J$WM]5oOV\t\u0011\u0005E\u0002#U5r!a\t\u0015\u000f\u0005\u0011:S\"A\u0013\u000b\u0005\u0019\u001a\u0012A\u0002\u001fs_>$h(C\u0001\u0013\u0013\tI\u0013#A\u0004qC\u000e\\\u0017mZ3\n\u0005-b#\u0001C(sI\u0016\u0014\u0018N\\4\u000b\u0005%\n\u0002C\u0001\u00180\u0019\u0001!Q\u0001\r\u0001C\u0002E\u0012\u0011!Q\t\u0003eU\u0002\"aF\u001a\n\u0005Q\n\"a\u0002(pi\"Lgn\u001a\t\u0003/YJ!aN\t\u0003\u0007\u0005s\u00170\u0001\u0005gSJ\u001cHoS3z+\u0005i\u0013a\u00027bgR\\U-_\u0001\bG>l\u0007/\u0019:f)\ri\u0004I\u0011\t\u0003/yJ!aP\t\u0003\u0007%sG\u000fC\u0003B\u000b\u0001\u0007Q&\u0001\u0002la!)1)\u0002a\u0001[\u0005\u00111.\r\u0015\u0003\u000b\u0015\u0003\"a\u0006$\n\u0005\u001d\u000b\"AB5oY&tW\r\u000b\u0004\u0006\u00132ku\n\u0015\t\u0003/)K!aS\t\u0003)\u0011,\u0007O]3dCR,Gm\u0014<feJLG-\u001b8h\u0003\u001diWm]:bO\u0016\f\u0013AT\u0001\u001d+N,\u0007e\u001c:eKJLgn\u001a\u0018d_6\u0004\u0018M]3!S:\u001cH/Z1e\u0003\u0015\u0019\u0018N\\2fC\u0005\t\u0016A\u0002\u001a/cMr\u0003\u0007\u000b\u0004\u0006\'2ku\n\u0015\t\u0003/QK!!V\t\u0003\u0015\u0011,\u0007O]3dCR,G-A\u0005sC:<W-S7qYR\u0019\u0001l\u00171\u0011\u00059JFA\u0002.\u0001\t\u000b\u0007\u0011GA\u0001D\u0011\u0015af\u00011\u0001^\u0003\u00111\'o\\7\u0011\u0007]qV&\u0003\u0002`#\t1q\n\u001d;j_:DQ!\u0019\u0004A\u0002u\u000bQ!\u001e8uS2\fQA]1oO\u0016$2\u0001\u00173f\u0011\u0015av\u00011\u0001.\u0011\u0015\tw\u00011\u0001.)\tAv\rC\u0003]\u0011\u0001\u0007Q\u0006\u000b\u0004\t\'2Kw\nU\u0011\u0002U\u0006iQk]3!e\u0006tw-\u001a$s_6\f\u0011B]1oO\u00164%o\\7\u0015\u0005ak\u0007\"\u0002/\n\u0001\u0004iCC\u0001-p\u0011\u0015\t\'\u00021\u0001.Q\u0019Q1\u000bT9P!\u0006\n!/\u0001\bVg\u0016\u0004#/\u00198hKVsG/\u001b7\u0002\u0015I\fgnZ3V]RLG\u000e\u0006\u0002Yk\")\u0011m\u0003a\u0001[\u0005\u0011Ao\u001c\u000b\u00031bDQA\u001e\u0007A\u00025Bc\u0001D*Mu>\u0003\u0016%A>\u0002\u0017U\u001bX\r\t:b]\u001e,Gk\\\u0001\be\u0006tw-\u001a+p)\tAf\u0010C\u0003w\u001b\u0001\u0007Q\u0006"
    )
  ScalaInlineInfo: length = 0x68 (unknown attribute)
   01 00 00 14 00 55 00 56 01 00 16 00 17 04 00 11
   00 12 05 00 0D 00 0E 00 00 26 00 39 01 00 37 00
   38 01 00 10 00 0E 00 00 0A 00 0B 00 00 2A 00 2B
   00 00 28 00 29 01 00 3D 00 39 00 00 40 00 38 01
   00 23 00 24 00 00 52 00 39 00 00 4A 00 39 00 00
   4D 00 38 01 00 4F 00 39 01 00 4E 00 38 01 00 27
   00 39 01 00 47 00 38 01
  ScalaSig: length = 0x3 (unknown attribute)
   05 02 00
