Classfile /Users/mw/Projects/slang-braindump/.jar/jar11/assemble/slang-braindump/assemble/content/scala/collection/SortedSetOps$WithFilter.class
  Last modified May 29, 2022; size 4403 bytes
  SHA-256 checksum f4cfaa74802219bcf184af1cadd63ab757aba7d001b78d285ba354efabe4996b
  Compiled from "SortedSet.scala"
public class scala.collection.SortedSetOps$WithFilter<A extends java.lang.Object, IterableCC extends java.lang.Object, CC extends scala.collection.SortedSet<java.lang.Object>> extends scala.collection.IterableOps$WithFilter<A, IterableCC>
  minor version: 0
  major version: 52
  flags: (0x0021) ACC_PUBLIC, ACC_SUPER
  this_class: #2                          // scala/collection/SortedSetOps$WithFilter
  super_class: #5                         // scala/collection/IterableOps$WithFilter
  interfaces: 0, fields: 2, methods: 9, attributes: 6
Constant pool:
    #1 = Utf8               scala/collection/SortedSetOps$WithFilter
    #2 = Class              #1            // scala/collection/SortedSetOps$WithFilter
    #3 = Utf8               <A:Ljava/lang/Object;IterableCC:Ljava/lang/Object;CC::Lscala/collection/SortedSet<Ljava/lang/Object;>;>Lscala/collection/IterableOps$WithFilter<TA;TIterableCC;>;
    #4 = Utf8               scala/collection/IterableOps$WithFilter
    #5 = Class              #4            // scala/collection/IterableOps$WithFilter
    #6 = Utf8               SortedSet.scala
    #7 = Utf8               java/lang/invoke/MethodHandles$Lookup
    #8 = Class              #7            // java/lang/invoke/MethodHandles$Lookup
    #9 = Utf8               java/lang/invoke/MethodHandles
   #10 = Class              #9            // java/lang/invoke/MethodHandles
   #11 = Utf8               Lookup
   #12 = Utf8               scala/collection/IterableOps
   #13 = Class              #12           // scala/collection/IterableOps
   #14 = Utf8               WithFilter
   #15 = Utf8               scala/collection/SortedSetOps
   #16 = Class              #15           // scala/collection/SortedSetOps
   #17 = Utf8               scala/collection/View$FlatMap
   #18 = Class              #17           // scala/collection/View$FlatMap
   #19 = Utf8               scala/collection/View
   #20 = Class              #19           // scala/collection/View
   #21 = Utf8               FlatMap
   #22 = Utf8               scala/collection/View$Map
   #23 = Class              #22           // scala/collection/View$Map
   #24 = Utf8               Map
   #25 = Utf8               self
   #26 = Utf8               Lscala/collection/SortedSetOps;
   #27 = Utf8               Lscala/collection/SortedSetOps<TA;TCC;*>;
   #28 = Utf8               p
   #29 = Utf8               Lscala/Function1;
   #30 = Utf8               Lscala/Function1<TA;Ljava/lang/Object;>;
   #31 = Utf8               map
   #32 = Utf8               (Lscala/Function1;Lscala/math/Ordering;)Lscala/collection/SortedSet;
   #33 = Utf8               <B:Ljava/lang/Object;>(Lscala/Function1<TA;TB;>;Lscala/math/Ordering<TB;>;)TCC;
   #34 = Utf8               f
   #35 = Utf8               evidence$1
   #36 = NameAndType        #25:#26       // self:Lscala/collection/SortedSetOps;
   #37 = Fieldref           #2.#36        // scala/collection/SortedSetOps$WithFilter.self:Lscala/collection/SortedSetOps;
   #38 = Utf8               sortedIterableFactory
   #39 = Utf8               ()Lscala/collection/SortedIterableFactory;
   #40 = NameAndType        #38:#39       // sortedIterableFactory:()Lscala/collection/SortedIterableFactory;
   #41 = InterfaceMethodref #16.#40       // scala/collection/SortedSetOps.sortedIterableFactory:()Lscala/collection/SortedIterableFactory;
   #42 = Utf8               filtered
   #43 = Utf8               ()Lscala/collection/Iterable;
   #44 = NameAndType        #42:#43       // filtered:()Lscala/collection/Iterable;
   #45 = Methodref          #2.#44        // scala/collection/SortedSetOps$WithFilter.filtered:()Lscala/collection/Iterable;
   #46 = Utf8               <init>
   #47 = Utf8               (Lscala/collection/IterableOps;Lscala/Function1;)V
   #48 = NameAndType        #46:#47       // "<init>":(Lscala/collection/IterableOps;Lscala/Function1;)V
   #49 = Methodref          #23.#48       // scala/collection/View$Map."<init>":(Lscala/collection/IterableOps;Lscala/Function1;)V
   #50 = Utf8               scala/collection/SortedIterableFactory
   #51 = Class              #50           // scala/collection/SortedIterableFactory
   #52 = Utf8               from
   #53 = Utf8               (Lscala/collection/IterableOnce;Ljava/lang/Object;)Ljava/lang/Object;
   #54 = NameAndType        #52:#53       // from:(Lscala/collection/IterableOnce;Ljava/lang/Object;)Ljava/lang/Object;
   #55 = InterfaceMethodref #51.#54       // scala/collection/SortedIterableFactory.from:(Lscala/collection/IterableOnce;Ljava/lang/Object;)Ljava/lang/Object;
   #56 = Utf8               scala/collection/SortedSet
   #57 = Class              #56           // scala/collection/SortedSet
   #58 = Utf8               this
   #59 = Utf8               Lscala/collection/SortedSetOps$WithFilter;
   #60 = Utf8               Lscala/math/Ordering;
   #61 = Utf8               flatMap
   #62 = Utf8               <B:Ljava/lang/Object;>(Lscala/Function1<TA;Lscala/collection/IterableOnce<TB;>;>;Lscala/math/Ordering<TB;>;)TCC;
   #63 = Utf8               evidence$2
   #64 = Methodref          #18.#48       // scala/collection/View$FlatMap."<init>":(Lscala/collection/IterableOps;Lscala/Function1;)V
   #65 = Utf8               withFilter
   #66 = Utf8               (Lscala/Function1;)Lscala/collection/SortedSetOps$WithFilter;
   #67 = Utf8               (Lscala/Function1<TA;Ljava/lang/Object;>;)Lscala/collection/SortedSetOps$WithFilter<TA;TIterableCC;TCC;>;
   #68 = Utf8               q
   #69 = Utf8               (Ljava/lang/Object;)Ljava/lang/Object;
   #70 = MethodType         #69           //  (Ljava/lang/Object;)Ljava/lang/Object;
   #71 = Utf8               $anonfun$withFilter$1$adapted
   #72 = Utf8               (Lscala/collection/SortedSetOps$WithFilter;Lscala/Function1;Ljava/lang/Object;)Ljava/lang/Object;
   #73 = NameAndType        #71:#72       // $anonfun$withFilter$1$adapted:(Lscala/collection/SortedSetOps$WithFilter;Lscala/Function1;Ljava/lang/Object;)Ljava/lang/Object;
   #74 = Methodref          #2.#73        // scala/collection/SortedSetOps$WithFilter.$anonfun$withFilter$1$adapted:(Lscala/collection/SortedSetOps$WithFilter;Lscala/Function1;Ljava/lang/Object;)Ljava/lang/Object;
   #75 = MethodHandle       6:#74         // REF_invokeStatic scala/collection/SortedSetOps$WithFilter.$anonfun$withFilter$1$adapted:(Lscala/collection/SortedSetOps$WithFilter;Lscala/Function1;Ljava/lang/Object;)Ljava/lang/Object;
   #76 = Integer            1
   #77 = Utf8               java/lang/invoke/LambdaMetafactory
   #78 = Class              #77           // java/lang/invoke/LambdaMetafactory
   #79 = Utf8               altMetafactory
   #80 = Utf8               (Ljava/lang/invoke/MethodHandles$Lookup;Ljava/lang/String;Ljava/lang/invoke/MethodType;[Ljava/lang/Object;)Ljava/lang/invoke/CallSite;
   #81 = NameAndType        #79:#80       // altMetafactory:(Ljava/lang/invoke/MethodHandles$Lookup;Ljava/lang/String;Ljava/lang/invoke/MethodType;[Ljava/lang/Object;)Ljava/lang/invoke/CallSite;
   #82 = Methodref          #78.#81       // java/lang/invoke/LambdaMetafactory.altMetafactory:(Ljava/lang/invoke/MethodHandles$Lookup;Ljava/lang/String;Ljava/lang/invoke/MethodType;[Ljava/lang/Object;)Ljava/lang/invoke/CallSite;
   #83 = MethodHandle       6:#82         // REF_invokeStatic java/lang/invoke/LambdaMetafactory.altMetafactory:(Ljava/lang/invoke/MethodHandles$Lookup;Ljava/lang/String;Ljava/lang/invoke/MethodType;[Ljava/lang/Object;)Ljava/lang/invoke/CallSite;
   #84 = Utf8               apply
   #85 = Utf8               (Lscala/collection/SortedSetOps$WithFilter;Lscala/Function1;)Lscala/Function1;
   #86 = NameAndType        #84:#85       // apply:(Lscala/collection/SortedSetOps$WithFilter;Lscala/Function1;)Lscala/Function1;
   #87 = InvokeDynamic      #0:#86        // #0:apply:(Lscala/collection/SortedSetOps$WithFilter;Lscala/Function1;)Lscala/Function1;
   #88 = Utf8               (Lscala/collection/SortedSetOps;Lscala/Function1;)V
   #89 = NameAndType        #46:#88       // "<init>":(Lscala/collection/SortedSetOps;Lscala/Function1;)V
   #90 = Methodref          #2.#89        // scala/collection/SortedSetOps$WithFilter."<init>":(Lscala/collection/SortedSetOps;Lscala/Function1;)V
   #91 = Utf8               (Lscala/Function1;)Lscala/collection/WithFilter;
   #92 = NameAndType        #65:#66       // withFilter:(Lscala/Function1;)Lscala/collection/SortedSetOps$WithFilter;
   #93 = Methodref          #2.#92        // scala/collection/SortedSetOps$WithFilter.withFilter:(Lscala/Function1;)Lscala/collection/SortedSetOps$WithFilter;
   #94 = Utf8               (Lscala/Function1;)Lscala/collection/IterableOps$WithFilter;
   #95 = Utf8               $anonfun$withFilter$1
   #96 = Utf8               (Lscala/collection/SortedSetOps$WithFilter;Lscala/Function1;Ljava/lang/Object;)Z
   #97 = Utf8               $this
   #98 = Utf8               q$1
   #99 = Utf8               a
  #100 = NameAndType        #28:#29       // p:Lscala/Function1;
  #101 = Fieldref           #2.#100       // scala/collection/SortedSetOps$WithFilter.p:Lscala/Function1;
  #102 = Utf8               scala/Function1
  #103 = Class              #102          // scala/Function1
  #104 = NameAndType        #84:#69       // apply:(Ljava/lang/Object;)Ljava/lang/Object;
  #105 = InterfaceMethodref #103.#104     // scala/Function1.apply:(Ljava/lang/Object;)Ljava/lang/Object;
  #106 = Utf8               scala/runtime/BoxesRunTime
  #107 = Class              #106          // scala/runtime/BoxesRunTime
  #108 = Utf8               unboxToBoolean
  #109 = Utf8               (Ljava/lang/Object;)Z
  #110 = NameAndType        #108:#109     // unboxToBoolean:(Ljava/lang/Object;)Z
  #111 = Methodref          #107.#110     // scala/runtime/BoxesRunTime.unboxToBoolean:(Ljava/lang/Object;)Z
  #112 = Utf8               Ljava/lang/Object;
  #113 = Utf8               (Lscala/collection/SortedSetOps<TA;TCC;*>;Lscala/Function1<TA;Ljava/lang/Object;>;)V
  #114 = Methodref          #5.#48        // scala/collection/IterableOps$WithFilter."<init>":(Lscala/collection/IterableOps;Lscala/Function1;)V
  #115 = NameAndType        #95:#96       // $anonfun$withFilter$1:(Lscala/collection/SortedSetOps$WithFilter;Lscala/Function1;Ljava/lang/Object;)Z
  #116 = Methodref          #2.#115       // scala/collection/SortedSetOps$WithFilter.$anonfun$withFilter$1:(Lscala/collection/SortedSetOps$WithFilter;Lscala/Function1;Ljava/lang/Object;)Z
  #117 = Utf8               boxToBoolean
  #118 = Utf8               (Z)Ljava/lang/Boolean;
  #119 = NameAndType        #117:#118     // boxToBoolean:(Z)Ljava/lang/Boolean;
  #120 = Methodref          #107.#119     // scala/runtime/BoxesRunTime.boxToBoolean:(Z)Ljava/lang/Boolean;
  #121 = Utf8               $deserializeLambda$
  #122 = Utf8               (Ljava/lang/invoke/SerializedLambda;)Ljava/lang/Object;
  #123 = Utf8               scala/runtime/LambdaDeserialize
  #124 = Class              #123          // scala/runtime/LambdaDeserialize
  #125 = Utf8               bootstrap
  #126 = Utf8               (Ljava/lang/invoke/MethodHandles$Lookup;Ljava/lang/String;Ljava/lang/invoke/MethodType;[Ljava/lang/invoke/MethodHandle;)Ljava/lang/invoke/CallSite;
  #127 = NameAndType        #125:#126     // bootstrap:(Ljava/lang/invoke/MethodHandles$Lookup;Ljava/lang/String;Ljava/lang/invoke/MethodType;[Ljava/lang/invoke/MethodHandle;)Ljava/lang/invoke/CallSite;
  #128 = Methodref          #124.#127     // scala/runtime/LambdaDeserialize.bootstrap:(Ljava/lang/invoke/MethodHandles$Lookup;Ljava/lang/String;Ljava/lang/invoke/MethodType;[Ljava/lang/invoke/MethodHandle;)Ljava/lang/invoke/CallSite;
  #129 = MethodHandle       6:#128        // REF_invokeStatic scala/runtime/LambdaDeserialize.bootstrap:(Ljava/lang/invoke/MethodHandles$Lookup;Ljava/lang/String;Ljava/lang/invoke/MethodType;[Ljava/lang/invoke/MethodHandle;)Ljava/lang/invoke/CallSite;
  #130 = Utf8               lambdaDeserialize
  #131 = NameAndType        #130:#122     // lambdaDeserialize:(Ljava/lang/invoke/SerializedLambda;)Ljava/lang/Object;
  #132 = InvokeDynamic      #1:#131       // #1:lambdaDeserialize:(Ljava/lang/invoke/SerializedLambda;)Ljava/lang/Object;
  #133 = Utf8               Signature
  #134 = Utf8               Code
  #135 = Utf8               LineNumberTable
  #136 = Utf8               LocalVariableTable
  #137 = Utf8               MethodParameters
  #138 = Utf8               StackMapTable
  #139 = Utf8               InnerClasses
  #140 = Utf8               SourceFile
  #141 = Utf8               BootstrapMethods
  #142 = Utf8               ScalaInlineInfo
  #143 = Utf8               Scala
{
  private final scala.collection.SortedSetOps<A, CC, ?> self;
    descriptor: Lscala/collection/SortedSetOps;
    flags: (0x0012) ACC_PRIVATE, ACC_FINAL
    Signature: #27                          // Lscala/collection/SortedSetOps<TA;TCC;*>;

  private final scala.Function1<A, java.lang.Object> p;
    descriptor: Lscala/Function1;
    flags: (0x0012) ACC_PRIVATE, ACC_FINAL
    Signature: #30                          // Lscala/Function1<TA;Ljava/lang/Object;>;

  public <B extends java.lang.Object> CC map(scala.Function1<A, B>, scala.math.Ordering<B>);
    descriptor: (Lscala/Function1;Lscala/math/Ordering;)Lscala/collection/SortedSet;
    flags: (0x0001) ACC_PUBLIC
    Code:
      stack=5, locals=3, args_size=3
         0: aload_0
         1: getfield      #37                 // Field self:Lscala/collection/SortedSetOps;
         4: invokeinterface #41,  1           // InterfaceMethod scala/collection/SortedSetOps.sortedIterableFactory:()Lscala/collection/SortedIterableFactory;
         9: new           #23                 // class scala/collection/View$Map
        12: dup
        13: aload_0
        14: invokevirtual #45                 // Method filtered:()Lscala/collection/Iterable;
        17: aload_1
        18: invokespecial #49                 // Method scala/collection/View$Map."<init>":(Lscala/collection/IterableOps;Lscala/Function1;)V
        21: aload_2
        22: invokeinterface #55,  3           // InterfaceMethod scala/collection/SortedIterableFactory.from:(Lscala/collection/IterableOnce;Ljava/lang/Object;)Ljava/lang/Object;
        27: checkcast     #57                 // class scala/collection/SortedSet
        30: areturn
      LineNumberTable:
        line 176: 0
      LocalVariableTable:
        Start  Length  Slot  Name   Signature
            0      31     0  this   Lscala/collection/SortedSetOps$WithFilter;
            0      31     1     f   Lscala/Function1;
            0      31     2 evidence$1   Lscala/math/Ordering;
    Signature: #33                          // <B:Ljava/lang/Object;>(Lscala/Function1<TA;TB;>;Lscala/math/Ordering<TB;>;)TCC;
    MethodParameters:
      Name                           Flags
      f                              final
      evidence$1                     final

  public <B extends java.lang.Object> CC flatMap(scala.Function1<A, scala.collection.IterableOnce<B>>, scala.math.Ordering<B>);
    descriptor: (Lscala/Function1;Lscala/math/Ordering;)Lscala/collection/SortedSet;
    flags: (0x0001) ACC_PUBLIC
    Code:
      stack=5, locals=3, args_size=3
         0: aload_0
         1: getfield      #37                 // Field self:Lscala/collection/SortedSetOps;
         4: invokeinterface #41,  1           // InterfaceMethod scala/collection/SortedSetOps.sortedIterableFactory:()Lscala/collection/SortedIterableFactory;
         9: new           #18                 // class scala/collection/View$FlatMap
        12: dup
        13: aload_0
        14: invokevirtual #45                 // Method filtered:()Lscala/collection/Iterable;
        17: aload_1
        18: invokespecial #64                 // Method scala/collection/View$FlatMap."<init>":(Lscala/collection/IterableOps;Lscala/Function1;)V
        21: aload_2
        22: invokeinterface #55,  3           // InterfaceMethod scala/collection/SortedIterableFactory.from:(Lscala/collection/IterableOnce;Ljava/lang/Object;)Ljava/lang/Object;
        27: checkcast     #57                 // class scala/collection/SortedSet
        30: areturn
      LineNumberTable:
        line 179: 0
      LocalVariableTable:
        Start  Length  Slot  Name   Signature
            0      31     0  this   Lscala/collection/SortedSetOps$WithFilter;
            0      31     1     f   Lscala/Function1;
            0      31     2 evidence$2   Lscala/math/Ordering;
    Signature: #62                          // <B:Ljava/lang/Object;>(Lscala/Function1<TA;Lscala/collection/IterableOnce<TB;>;>;Lscala/math/Ordering<TB;>;)TCC;
    MethodParameters:
      Name                           Flags
      f                              final
      evidence$2                     final

  public scala.collection.SortedSetOps$WithFilter<A, IterableCC, CC> withFilter(scala.Function1<A, java.lang.Object>);
    descriptor: (Lscala/Function1;)Lscala/collection/SortedSetOps$WithFilter;
    flags: (0x0001) ACC_PUBLIC
    Code:
      stack=5, locals=2, args_size=2
         0: new           #2                  // class scala/collection/SortedSetOps$WithFilter
         3: dup
         4: aload_0
         5: getfield      #37                 // Field self:Lscala/collection/SortedSetOps;
         8: aload_0
         9: aload_1
        10: invokedynamic #87,  0             // InvokeDynamic #0:apply:(Lscala/collection/SortedSetOps$WithFilter;Lscala/Function1;)Lscala/Function1;
        15: invokespecial #90                 // Method "<init>":(Lscala/collection/SortedSetOps;Lscala/Function1;)V
        18: areturn
      LineNumberTable:
        line 182: 0
      LocalVariableTable:
        Start  Length  Slot  Name   Signature
            0      19     0  this   Lscala/collection/SortedSetOps$WithFilter;
            0      19     1     q   Lscala/Function1;
    Signature: #67                          // (Lscala/Function1<TA;Ljava/lang/Object;>;)Lscala/collection/SortedSetOps$WithFilter<TA;TIterableCC;TCC;>;
    MethodParameters:
      Name                           Flags
      q                              final

  public scala.collection.WithFilter withFilter(scala.Function1);
    descriptor: (Lscala/Function1;)Lscala/collection/WithFilter;
    flags: (0x1041) ACC_PUBLIC, ACC_BRIDGE, ACC_SYNTHETIC
    Code:
      stack=2, locals=2, args_size=2
         0: aload_0
         1: aload_1
         2: invokevirtual #93                 // Method withFilter:(Lscala/Function1;)Lscala/collection/SortedSetOps$WithFilter;
         5: areturn
      LineNumberTable:
        line 170: 0
      LocalVariableTable:
        Start  Length  Slot  Name   Signature
            0       6     0  this   Lscala/collection/SortedSetOps$WithFilter;
            0       6     1     q   Lscala/Function1;
    MethodParameters:
      Name                           Flags
      q                              final

  public scala.collection.IterableOps$WithFilter withFilter(scala.Function1);
    descriptor: (Lscala/Function1;)Lscala/collection/IterableOps$WithFilter;
    flags: (0x1041) ACC_PUBLIC, ACC_BRIDGE, ACC_SYNTHETIC
    Code:
      stack=2, locals=2, args_size=2
         0: aload_0
         1: aload_1
         2: invokevirtual #93                 // Method withFilter:(Lscala/Function1;)Lscala/collection/SortedSetOps$WithFilter;
         5: areturn
      LineNumberTable:
        line 170: 0
      LocalVariableTable:
        Start  Length  Slot  Name   Signature
            0       6     0  this   Lscala/collection/SortedSetOps$WithFilter;
            0       6     1     q   Lscala/Function1;
    MethodParameters:
      Name                           Flags
      q                              final

  public static final boolean $anonfun$withFilter$1(scala.collection.SortedSetOps$WithFilter, scala.Function1, java.lang.Object);
    descriptor: (Lscala/collection/SortedSetOps$WithFilter;Lscala/Function1;Ljava/lang/Object;)Z
    flags: (0x1019) ACC_PUBLIC, ACC_STATIC, ACC_FINAL, ACC_SYNTHETIC
    Code:
      stack=2, locals=3, args_size=3
         0: aload_0
         1: getfield      #101                // Field p:Lscala/Function1;
         4: aload_2
         5: invokeinterface #105,  2          // InterfaceMethod scala/Function1.apply:(Ljava/lang/Object;)Ljava/lang/Object;
        10: invokestatic  #111                // Method scala/runtime/BoxesRunTime.unboxToBoolean:(Ljava/lang/Object;)Z
        13: ifeq          31
        16: aload_1
        17: aload_2
        18: invokeinterface #105,  2          // InterfaceMethod scala/Function1.apply:(Ljava/lang/Object;)Ljava/lang/Object;
        23: invokestatic  #111                // Method scala/runtime/BoxesRunTime.unboxToBoolean:(Ljava/lang/Object;)Z
        26: ifeq          31
        29: iconst_1
        30: ireturn
        31: iconst_0
        32: ireturn
      StackMapTable: number_of_entries = 1
        frame_type = 31 /* same */
      LineNumberTable:
        line 182: 0
      LocalVariableTable:
        Start  Length  Slot  Name   Signature
            0      33     0 $this   Lscala/collection/SortedSetOps$WithFilter;
            0      33     1   q$1   Lscala/Function1;
            0      33     2     a   Ljava/lang/Object;
    MethodParameters:
      Name                           Flags
      $this                          final synthetic
      q$1                            final
      a                              final

  public scala.collection.SortedSetOps$WithFilter(scala.collection.SortedSetOps<A, CC, ?>, scala.Function1<A, java.lang.Object>);
    descriptor: (Lscala/collection/SortedSetOps;Lscala/Function1;)V
    flags: (0x0001) ACC_PUBLIC
    Code:
      stack=3, locals=3, args_size=3
         0: aload_0
         1: aload_1
         2: putfield      #37                 // Field self:Lscala/collection/SortedSetOps;
         5: aload_0
         6: aload_2
         7: putfield      #101                // Field p:Lscala/Function1;
        10: aload_0
        11: aload_1
        12: aload_2
        13: invokespecial #114                // Method scala/collection/IterableOps$WithFilter."<init>":(Lscala/collection/IterableOps;Lscala/Function1;)V
        16: return
      LineNumberTable:
        line 171: 0
        line 172: 5
        line 173: 10
        line 170: 16
      LocalVariableTable:
        Start  Length  Slot  Name   Signature
            0      17     0  this   Lscala/collection/SortedSetOps$WithFilter;
            0      17     1  self   Lscala/collection/SortedSetOps;
            0      17     2     p   Lscala/Function1;
    Signature: #113                         // (Lscala/collection/SortedSetOps<TA;TCC;*>;Lscala/Function1<TA;Ljava/lang/Object;>;)V
    MethodParameters:
      Name                           Flags
      self                           final
      p                              final

  public static final java.lang.Object $anonfun$withFilter$1$adapted(scala.collection.SortedSetOps$WithFilter, scala.Function1, java.lang.Object);
    descriptor: (Lscala/collection/SortedSetOps$WithFilter;Lscala/Function1;Ljava/lang/Object;)Ljava/lang/Object;
    flags: (0x1019) ACC_PUBLIC, ACC_STATIC, ACC_FINAL, ACC_SYNTHETIC
    Code:
      stack=3, locals=3, args_size=3
         0: aload_0
         1: aload_1
         2: aload_2
         3: invokestatic  #116                // Method $anonfun$withFilter$1:(Lscala/collection/SortedSetOps$WithFilter;Lscala/Function1;Ljava/lang/Object;)Z
         6: invokestatic  #120                // Method scala/runtime/BoxesRunTime.boxToBoolean:(Z)Ljava/lang/Boolean;
         9: areturn
      LineNumberTable:
        line 182: 0
      LocalVariableTable:
        Start  Length  Slot  Name   Signature
            0      10     0 $this   Lscala/collection/SortedSetOps$WithFilter;
            0      10     1   q$1   Lscala/Function1;
            0      10     2     a   Ljava/lang/Object;
    MethodParameters:
      Name                           Flags
      $this                          final
      q$1                            final
      a                              final

  private static java.lang.Object $deserializeLambda$(java.lang.invoke.SerializedLambda);
    descriptor: (Ljava/lang/invoke/SerializedLambda;)Ljava/lang/Object;
    flags: (0x100a) ACC_PRIVATE, ACC_STATIC, ACC_SYNTHETIC
    Code:
      stack=1, locals=1, args_size=1
         0: aload_0
         1: invokedynamic #132,  0            // InvokeDynamic #1:lambdaDeserialize:(Ljava/lang/invoke/SerializedLambda;)Ljava/lang/Object;
         6: areturn
}
InnerClasses:
  public static final #11= #8 of #10;     // Lookup=class java/lang/invoke/MethodHandles$Lookup of class java/lang/invoke/MethodHandles
  public static #14= #5 of #13;           // WithFilter=class scala/collection/IterableOps$WithFilter of class scala/collection/IterableOps
  public static #14= #2 of #16;           // WithFilter=class scala/collection/SortedSetOps$WithFilter of class scala/collection/SortedSetOps
  public static #21= #18 of #20;          // FlatMap=class scala/collection/View$FlatMap of class scala/collection/View
  public static #24= #23 of #20;          // Map=class scala/collection/View$Map of class scala/collection/View
Signature: #3                           // <A:Ljava/lang/Object;IterableCC:Ljava/lang/Object;CC::Lscala/collection/SortedSet<Ljava/lang/Object;>;>Lscala/collection/IterableOps$WithFilter<TA;TIterableCC;>;
SourceFile: "SortedSet.scala"
BootstrapMethods:
  0: #83 REF_invokeStatic java/lang/invoke/LambdaMetafactory.altMetafactory:(Ljava/lang/invoke/MethodHandles$Lookup;Ljava/lang/String;Ljava/lang/invoke/MethodType;[Ljava/lang/Object;)Ljava/lang/invoke/CallSite;
    Method arguments:
      #70 (Ljava/lang/Object;)Ljava/lang/Object;
      #75 REF_invokeStatic scala/collection/SortedSetOps$WithFilter.$anonfun$withFilter$1$adapted:(Lscala/collection/SortedSetOps$WithFilter;Lscala/Function1;Ljava/lang/Object;)Ljava/lang/Object;
      #70 (Ljava/lang/Object;)Ljava/lang/Object;
      #76 1
  1: #129 REF_invokeStatic scala/runtime/LambdaDeserialize.bootstrap:(Ljava/lang/invoke/MethodHandles$Lookup;Ljava/lang/String;Ljava/lang/invoke/MethodType;[Ljava/lang/invoke/MethodHandle;)Ljava/lang/invoke/CallSite;
    Method arguments:
      #75 REF_invokeStatic scala/collection/SortedSetOps$WithFilter.$anonfun$withFilter$1$adapted:(Lscala/collection/SortedSetOps$WithFilter;Lscala/Function1;Ljava/lang/Object;)Ljava/lang/Object;
  ScalaInlineInfo: length = 0x2C (unknown attribute)
   01 00 00 08 00 5F 00 60 01 00 47 00 48 01 00 2E
   00 58 00 00 3D 00 20 00 00 1F 00 20 00 00 41 00
   5E 00 00 41 00 42 00 00 41 00 5B 00
  Scala: length = 0x0 (unknown attribute)

