Classfile /Users/mw/Projects/slang-braindump/.jar/jar11/assemble/slang-braindump/assemble/content/scala/collection/StringOps$GroupedIterator.class
  Last modified May 29, 2022; size 1549 bytes
  SHA-256 checksum da8983bcc6d63a9e393ad457452193dade7314888720b1039f72804f83374725
  Compiled from "StringOps.scala"
public class scala.collection.StringOps$GroupedIterator extends scala.collection.AbstractIterator<java.lang.String>
  minor version: 0
  major version: 52
  flags: (0x0021) ACC_PUBLIC, ACC_SUPER
  this_class: #2                          // scala/collection/StringOps$GroupedIterator
  super_class: #5                         // scala/collection/AbstractIterator
  interfaces: 0, fields: 3, methods: 4, attributes: 5
Constant pool:
   #1 = Utf8               scala/collection/StringOps$GroupedIterator
   #2 = Class              #1             // scala/collection/StringOps$GroupedIterator
   #3 = Utf8               Lscala/collection/AbstractIterator<Ljava/lang/String;>;
   #4 = Utf8               scala/collection/AbstractIterator
   #5 = Class              #4             // scala/collection/AbstractIterator
   #6 = Utf8               StringOps.scala
   #7 = Utf8               scala/collection/StringOps
   #8 = Class              #7             // scala/collection/StringOps
   #9 = Utf8               GroupedIterator
  #10 = Utf8               s
  #11 = Utf8               Ljava/lang/String;
  #12 = Utf8               groupSize
  #13 = Utf8               I
  #14 = Utf8               pos
  #15 = Utf8               hasNext
  #16 = Utf8               ()Z
  #17 = NameAndType        #14:#13        // pos:I
  #18 = Fieldref           #2.#17         // scala/collection/StringOps$GroupedIterator.pos:I
  #19 = NameAndType        #10:#11        // s:Ljava/lang/String;
  #20 = Fieldref           #2.#19         // scala/collection/StringOps$GroupedIterator.s:Ljava/lang/String;
  #21 = Utf8               java/lang/String
  #22 = Class              #21            // java/lang/String
  #23 = Utf8               length
  #24 = Utf8               ()I
  #25 = NameAndType        #23:#24        // length:()I
  #26 = Methodref          #22.#25        // java/lang/String.length:()I
  #27 = Utf8               this
  #28 = Utf8               Lscala/collection/StringOps$GroupedIterator;
  #29 = Utf8               next
  #30 = Utf8               ()Ljava/lang/String;
  #31 = Utf8               scala/collection/Iterator$
  #32 = Class              #31            // scala/collection/Iterator$
  #33 = Utf8               MODULE$
  #34 = Utf8               Lscala/collection/Iterator$;
  #35 = NameAndType        #33:#34        // MODULE$:Lscala/collection/Iterator$;
  #36 = Fieldref           #32.#35        // scala/collection/Iterator$.MODULE$:Lscala/collection/Iterator$;
  #37 = Utf8               scala$collection$Iterator$$_empty
  #38 = Utf8               Lscala/collection/Iterator;
  #39 = NameAndType        #37:#38        // scala$collection$Iterator$$_empty:Lscala/collection/Iterator;
  #40 = Fieldref           #32.#39        // scala/collection/Iterator$.scala$collection$Iterator$$_empty:Lscala/collection/Iterator;
  #41 = Utf8               scala/collection/Iterator
  #42 = Class              #41            // scala/collection/Iterator
  #43 = Utf8               ()Ljava/lang/Object;
  #44 = NameAndType        #29:#43        // next:()Ljava/lang/Object;
  #45 = InterfaceMethodref #42.#44        // scala/collection/Iterator.next:()Ljava/lang/Object;
  #46 = Utf8               scala/collection/StringOps$
  #47 = Class              #46            // scala/collection/StringOps$
  #48 = Utf8               Lscala/collection/StringOps$;
  #49 = NameAndType        #33:#48        // MODULE$:Lscala/collection/StringOps$;
  #50 = Fieldref           #47.#49        // scala/collection/StringOps$.MODULE$:Lscala/collection/StringOps$;
  #51 = NameAndType        #12:#13        // groupSize:I
  #52 = Fieldref           #2.#51         // scala/collection/StringOps$GroupedIterator.groupSize:I
  #53 = Utf8               slice$extension
  #54 = Utf8               (Ljava/lang/String;II)Ljava/lang/String;
  #55 = NameAndType        #53:#54        // slice$extension:(Ljava/lang/String;II)Ljava/lang/String;
  #56 = Methodref          #47.#55        // scala/collection/StringOps$.slice$extension:(Ljava/lang/String;II)Ljava/lang/String;
  #57 = Utf8               r
  #58 = NameAndType        #29:#30        // next:()Ljava/lang/String;
  #59 = Methodref          #2.#58         // scala/collection/StringOps$GroupedIterator.next:()Ljava/lang/String;
  #60 = Utf8               <init>
  #61 = Utf8               (Ljava/lang/String;I)V
  #62 = Utf8               ()V
  #63 = NameAndType        #60:#62        // "<init>":()V
  #64 = Methodref          #5.#63         // scala/collection/AbstractIterator."<init>":()V
  #65 = Utf8               Code
  #66 = Utf8               StackMapTable
  #67 = Utf8               LineNumberTable
  #68 = Utf8               LocalVariableTable
  #69 = Utf8               MethodParameters
  #70 = Utf8               InnerClasses
  #71 = Utf8               Signature
  #72 = Utf8               SourceFile
  #73 = Utf8               ScalaInlineInfo
  #74 = Utf8               Scala
{
  private final java.lang.String s;
    descriptor: Ljava/lang/String;
    flags: (0x0012) ACC_PRIVATE, ACC_FINAL

  private final int groupSize;
    descriptor: I
    flags: (0x0012) ACC_PRIVATE, ACC_FINAL

  private int pos;
    descriptor: I
    flags: (0x0002) ACC_PRIVATE

  public boolean hasNext();
    descriptor: ()Z
    flags: (0x0001) ACC_PUBLIC
    Code:
      stack=2, locals=1, args_size=1
         0: aload_0
         1: getfield      #18                 // Field pos:I
         4: aload_0
         5: getfield      #20                 // Field s:Ljava/lang/String;
         8: invokevirtual #26                 // Method java/lang/String.length:()I
        11: if_icmpge     16
        14: iconst_1
        15: ireturn
        16: iconst_0
        17: ireturn
      StackMapTable: number_of_entries = 1
        frame_type = 16 /* same */
      LineNumberTable:
        line 55: 0
      LocalVariableTable:
        Start  Length  Slot  Name   Signature
            0      18     0  this   Lscala/collection/StringOps$GroupedIterator;

  public java.lang.String next();
    descriptor: ()Ljava/lang/String;
    flags: (0x0001) ACC_PUBLIC
    Code:
      stack=5, locals=2, args_size=1
         0: aload_0
         1: getfield      #18                 // Field pos:I
         4: aload_0
         5: getfield      #20                 // Field s:Ljava/lang/String;
         8: invokevirtual #26                 // Method java/lang/String.length:()I
        11: if_icmplt     27
        14: getstatic     #36                 // Field scala/collection/Iterator$.MODULE$:Lscala/collection/Iterator$;
        17: pop
        18: getstatic     #40                 // Field scala/collection/Iterator$.scala$collection$Iterator$$_empty:Lscala/collection/Iterator;
        21: invokeinterface #45,  1           // InterfaceMethod scala/collection/Iterator.next:()Ljava/lang/Object;
        26: pop
        27: getstatic     #50                 // Field scala/collection/StringOps$.MODULE$:Lscala/collection/StringOps$;
        30: aload_0
        31: getfield      #20                 // Field s:Ljava/lang/String;
        34: aload_0
        35: getfield      #18                 // Field pos:I
        38: aload_0
        39: getfield      #18                 // Field pos:I
        42: aload_0
        43: getfield      #52                 // Field groupSize:I
        46: iadd
        47: invokevirtual #56                 // Method scala/collection/StringOps$.slice$extension:(Ljava/lang/String;II)Ljava/lang/String;
        50: astore_1
        51: aload_0
        52: aload_0
        53: getfield      #18                 // Field pos:I
        56: aload_0
        57: getfield      #52                 // Field groupSize:I
        60: iadd
        61: putfield      #18                 // Field pos:I
        64: aload_1
        65: areturn
      StackMapTable: number_of_entries = 1
        frame_type = 27 /* same */
      LineNumberTable:
        line 57: 0
        line 58: 27
        line 59: 51
        line 60: 64
      LocalVariableTable:
        Start  Length  Slot  Name   Signature
           51      14     1     r   Ljava/lang/String;
            0      66     0  this   Lscala/collection/StringOps$GroupedIterator;

  public java.lang.Object next();
    descriptor: ()Ljava/lang/Object;
    flags: (0x1041) ACC_PUBLIC, ACC_BRIDGE, ACC_SYNTHETIC
    Code:
      stack=1, locals=1, args_size=1
         0: aload_0
         1: invokevirtual #59                 // Method next:()Ljava/lang/String;
         4: areturn
      LineNumberTable:
        line 53: 0
      LocalVariableTable:
        Start  Length  Slot  Name   Signature
            0       5     0  this   Lscala/collection/StringOps$GroupedIterator;

  public scala.collection.StringOps$GroupedIterator(java.lang.String, int);
    descriptor: (Ljava/lang/String;I)V
    flags: (0x0001) ACC_PUBLIC
    Code:
      stack=2, locals=3, args_size=3
         0: aload_0
         1: aload_1
         2: putfield      #20                 // Field s:Ljava/lang/String;
         5: aload_0
         6: iload_2
         7: putfield      #52                 // Field groupSize:I
        10: aload_0
        11: invokespecial #64                 // Method scala/collection/AbstractIterator."<init>":()V
        14: aload_0
        15: iconst_0
        16: putfield      #18                 // Field pos:I
        19: return
      LineNumberTable:
        line 53: 0
        line 54: 14
        line 53: 19
      LocalVariableTable:
        Start  Length  Slot  Name   Signature
            0      20     0  this   Lscala/collection/StringOps$GroupedIterator;
            0      20     1     s   Ljava/lang/String;
            0      20     2 groupSize   I
    MethodParameters:
      Name                           Flags
      s                              final
      groupSize                      final
}
InnerClasses:
  private static #9= #2 of #8;            // GroupedIterator=class scala/collection/StringOps$GroupedIterator of class scala/collection/StringOps
Signature: #3                           // Lscala/collection/AbstractIterator<Ljava/lang/String;>;
SourceFile: "StringOps.scala"
  ScalaInlineInfo: length = 0x18 (unknown attribute)
   01 00 00 04 00 3C 00 3D 00 00 0F 00 10 00 00 1D
   00 2B 00 00 1D 00 1E 00
  Scala: length = 0x0 (unknown attribute)

