Classfile /Users/mw/Projects/slang-braindump/.jar/jar11/assemble/slang-braindump/assemble/content/scala/collection/View$TakeRight.class
  Last modified May 29, 2022; size 1991 bytes
  SHA-256 checksum 3e670f4ebbbff97a2b41c61338c43722af631ea3bbf4094ae5865f7a947ab670
  Compiled from "View.scala"
public class scala.collection.View$TakeRight<A extends java.lang.Object> extends scala.collection.AbstractView<A>
  minor version: 0
  major version: 52
  flags: (0x0021) ACC_PUBLIC, ACC_SUPER
  this_class: #2                          // scala/collection/View$TakeRight
  super_class: #5                         // scala/collection/AbstractView
  interfaces: 0, fields: 4, methods: 5, attributes: 5
Constant pool:
   #1 = Utf8               scala/collection/View$TakeRight
   #2 = Class              #1             // scala/collection/View$TakeRight
   #3 = Utf8               <A:Ljava/lang/Object;>Lscala/collection/AbstractView<TA;>;
   #4 = Utf8               scala/collection/AbstractView
   #5 = Class              #4             // scala/collection/AbstractView
   #6 = Utf8               View.scala
   #7 = Utf8               scala/collection/View
   #8 = Class              #7             // scala/collection/View
   #9 = Utf8               TakeRight
  #10 = Utf8               serialVersionUID
  #11 = Utf8               J
  #12 = Long               3l
  #14 = Utf8               underlying
  #15 = Utf8               Lscala/collection/IterableOps;
  #16 = Utf8               Lscala/collection/IterableOps<TA;*Ljava/lang/Object;>;
  #17 = Utf8               n
  #18 = Utf8               I
  #19 = Utf8               normN
  #20 = Utf8               iterator
  #21 = Utf8               ()Lscala/collection/Iterator;
  #22 = Utf8               ()Lscala/collection/Iterator<TA;>;
  #23 = Utf8               scala/collection/View$
  #24 = Class              #23            // scala/collection/View$
  #25 = Utf8               MODULE$
  #26 = Utf8               Lscala/collection/View$;
  #27 = NameAndType        #25:#26        // MODULE$:Lscala/collection/View$;
  #28 = Fieldref           #24.#27        // scala/collection/View$.MODULE$:Lscala/collection/View$;
  #29 = NameAndType        #14:#15        // underlying:Lscala/collection/IterableOps;
  #30 = Fieldref           #2.#29         // scala/collection/View$TakeRight.underlying:Lscala/collection/IterableOps;
  #31 = Utf8               scala/collection/IterableOps
  #32 = Class              #31            // scala/collection/IterableOps
  #33 = NameAndType        #20:#21        // iterator:()Lscala/collection/Iterator;
  #34 = InterfaceMethodref #32.#33        // scala/collection/IterableOps.iterator:()Lscala/collection/Iterator;
  #35 = NameAndType        #17:#18        // n:I
  #36 = Fieldref           #2.#35         // scala/collection/View$TakeRight.n:I
  #37 = Utf8               takeRightIterator
  #38 = Utf8               (Lscala/collection/Iterator;I)Lscala/collection/Iterator;
  #39 = NameAndType        #37:#38        // takeRightIterator:(Lscala/collection/Iterator;I)Lscala/collection/Iterator;
  #40 = Methodref          #24.#39        // scala/collection/View$.takeRightIterator:(Lscala/collection/Iterator;I)Lscala/collection/Iterator;
  #41 = Utf8               this
  #42 = Utf8               Lscala/collection/View$TakeRight;
  #43 = Utf8               ()I
  #44 = NameAndType        #19:#18        // normN:I
  #45 = Fieldref           #2.#44         // scala/collection/View$TakeRight.normN:I
  #46 = Utf8               knownSize
  #47 = NameAndType        #46:#43        // knownSize:()I
  #48 = InterfaceMethodref #32.#47        // scala/collection/IterableOps.knownSize:()I
  #49 = Utf8               scala/runtime/RichInt$
  #50 = Class              #49            // scala/runtime/RichInt$
  #51 = Utf8               Lscala/runtime/RichInt$;
  #52 = NameAndType        #25:#51        // MODULE$:Lscala/runtime/RichInt$;
  #53 = Fieldref           #50.#52        // scala/runtime/RichInt$.MODULE$:Lscala/runtime/RichInt$;
  #54 = NameAndType        #19:#43        // normN:()I
  #55 = Methodref          #2.#54         // scala/collection/View$TakeRight.normN:()I
  #56 = Utf8               scala/math/package$
  #57 = Class              #56            // scala/math/package$
  #58 = Utf8               Lscala/math/package$;
  #59 = NameAndType        #25:#58        // MODULE$:Lscala/math/package$;
  #60 = Fieldref           #57.#59        // scala/math/package$.MODULE$:Lscala/math/package$;
  #61 = Utf8               java/lang/Math
  #62 = Class              #61            // java/lang/Math
  #63 = Utf8               min
  #64 = Utf8               (II)I
  #65 = NameAndType        #63:#64        // min:(II)I
  #66 = Methodref          #62.#65        // java/lang/Math.min:(II)I
  #67 = Utf8               size
  #68 = Utf8               min$extension_that
  #69 = Utf8               isEmpty
  #70 = Utf8               ()Z
  #71 = Methodref          #2.#47         // scala/collection/View$TakeRight.knownSize:()I
  #72 = Methodref          #2.#33         // scala/collection/View$TakeRight.iterator:()Lscala/collection/Iterator;
  #73 = Utf8               scala/collection/Iterator
  #74 = Class              #73            // scala/collection/Iterator
  #75 = NameAndType        #69:#70        // isEmpty:()Z
  #76 = InterfaceMethodref #74.#75        // scala/collection/Iterator.isEmpty:()Z
  #77 = Utf8               <init>
  #78 = Utf8               (Lscala/collection/IterableOps;I)V
  #79 = Utf8               (Lscala/collection/IterableOps<TA;*Ljava/lang/Object;>;I)V
  #80 = Utf8               ()V
  #81 = NameAndType        #77:#80        // "<init>":()V
  #82 = Methodref          #5.#81         // scala/collection/AbstractView."<init>":()V
  #83 = Utf8               max
  #84 = NameAndType        #83:#64        // max:(II)I
  #85 = Methodref          #62.#84        // java/lang/Math.max:(II)I
  #86 = Utf8               max$extension_that
  #87 = Utf8               ConstantValue
  #88 = Utf8               Signature
  #89 = Utf8               Code
  #90 = Utf8               LineNumberTable
  #91 = Utf8               LocalVariableTable
  #92 = Utf8               StackMapTable
  #93 = Utf8               MethodParameters
  #94 = Utf8               InnerClasses
  #95 = Utf8               SourceFile
  #96 = Utf8               ScalaInlineInfo
  #97 = Utf8               Scala
{
  private static final long serialVersionUID;
    descriptor: J
    flags: (0x001a) ACC_PRIVATE, ACC_STATIC, ACC_FINAL
    ConstantValue: long 3l

  private final scala.collection.IterableOps<A, ?, java.lang.Object> underlying;
    descriptor: Lscala/collection/IterableOps;
    flags: (0x0012) ACC_PRIVATE, ACC_FINAL
    Signature: #16                          // Lscala/collection/IterableOps<TA;*Ljava/lang/Object;>;

  private final int n;
    descriptor: I
    flags: (0x0012) ACC_PRIVATE, ACC_FINAL

  private final int normN;
    descriptor: I
    flags: (0x0012) ACC_PRIVATE, ACC_FINAL

  public scala.collection.Iterator<A> iterator();
    descriptor: ()Lscala/collection/Iterator;
    flags: (0x0001) ACC_PUBLIC
    Code:
      stack=3, locals=1, args_size=1
         0: getstatic     #28                 // Field scala/collection/View$.MODULE$:Lscala/collection/View$;
         3: aload_0
         4: getfield      #30                 // Field underlying:Lscala/collection/IterableOps;
         7: invokeinterface #34,  1           // InterfaceMethod scala/collection/IterableOps.iterator:()Lscala/collection/Iterator;
        12: aload_0
        13: getfield      #36                 // Field n:I
        16: invokevirtual #40                 // Method scala/collection/View$.takeRightIterator:(Lscala/collection/Iterator;I)Lscala/collection/Iterator;
        19: areturn
      LineNumberTable:
        line 263: 0
      LocalVariableTable:
        Start  Length  Slot  Name   Signature
            0      20     0  this   Lscala/collection/View$TakeRight;
    Signature: #22                          // ()Lscala/collection/Iterator<TA;>;

  public int normN();
    descriptor: ()I
    flags: (0x0001) ACC_PUBLIC
    Code:
      stack=1, locals=1, args_size=1
         0: aload_0
         1: getfield      #45                 // Field normN:I
         4: ireturn
      LineNumberTable:
        line 264: 0
      LocalVariableTable:
        Start  Length  Slot  Name   Signature
            0       5     0  this   Lscala/collection/View$TakeRight;

  public int knownSize();
    descriptor: ()I
    flags: (0x0001) ACC_PUBLIC
    Code:
      stack=2, locals=3, args_size=1
         0: aload_0
         1: getfield      #30                 // Field underlying:Lscala/collection/IterableOps;
         4: invokeinterface #48,  1           // InterfaceMethod scala/collection/IterableOps.knownSize:()I
         9: istore_1
        10: iload_1
        11: iconst_0
        12: if_icmplt     34
        15: getstatic     #53                 // Field scala/runtime/RichInt$.MODULE$:Lscala/runtime/RichInt$;
        18: pop
        19: aload_0
        20: invokevirtual #55                 // Method normN:()I
        23: istore_2
        24: getstatic     #60                 // Field scala/math/package$.MODULE$:Lscala/math/package$;
        27: pop
        28: iload_1
        29: iload_2
        30: invokestatic  #66                 // Method java/lang/Math.min:(II)I
        33: ireturn
        34: iconst_m1
        35: ireturn
      StackMapTable: number_of_entries = 1
        frame_type = 252 /* append */
          offset_delta = 34
          locals = [ int ]
      LineNumberTable:
        line 266: 0
        line 267: 10
      LocalVariableTable:
        Start  Length  Slot  Name   Signature
           10      25     1  size   I
            0      36     0  this   Lscala/collection/View$TakeRight;
           24       9     2 min$extension_that   I

  public boolean isEmpty();
    descriptor: ()Z
    flags: (0x0001) ACC_PUBLIC
    Code:
      stack=2, locals=1, args_size=1
         0: aload_0
         1: invokevirtual #71                 // Method knownSize:()I
         4: iconst_0
         5: if_icmplt     20
         8: aload_0
         9: invokevirtual #71                 // Method knownSize:()I
        12: iconst_0
        13: if_icmpne     18
        16: iconst_1
        17: ireturn
        18: iconst_0
        19: ireturn
        20: aload_0
        21: invokevirtual #72                 // Method iterator:()Lscala/collection/Iterator;
        24: invokeinterface #76,  1           // InterfaceMethod scala/collection/Iterator.isEmpty:()Z
        29: ireturn
      StackMapTable: number_of_entries = 2
        frame_type = 18 /* same */
        frame_type = 1 /* same */
      LineNumberTable:
        line 270: 0
        line 271: 20
      LocalVariableTable:
        Start  Length  Slot  Name   Signature
            0      30     0  this   Lscala/collection/View$TakeRight;

  public scala.collection.View$TakeRight(scala.collection.IterableOps<A, ?, java.lang.Object>, int);
    descriptor: (Lscala/collection/IterableOps;I)V
    flags: (0x0001) ACC_PUBLIC
    Code:
      stack=3, locals=4, args_size=3
         0: aload_0
         1: aload_1
         2: putfield      #30                 // Field underlying:Lscala/collection/IterableOps;
         5: aload_0
         6: iload_2
         7: putfield      #36                 // Field n:I
        10: aload_0
        11: invokespecial #82                 // Method scala/collection/AbstractView."<init>":()V
        14: aload_0
        15: getstatic     #53                 // Field scala/runtime/RichInt$.MODULE$:Lscala/runtime/RichInt$;
        18: pop
        19: iconst_0
        20: istore_3
        21: getstatic     #60                 // Field scala/math/package$.MODULE$:Lscala/math/package$;
        24: pop
        25: iload_2
        26: iload_3
        27: invokestatic  #85                 // Method java/lang/Math.max:(II)I
        30: putfield      #45                 // Field normN:I
        33: return
      LineNumberTable:
        line 262: 0
        line 264: 14
        line 262: 33
      LocalVariableTable:
        Start  Length  Slot  Name   Signature
            0      34     0  this   Lscala/collection/View$TakeRight;
            0      34     1 underlying   Lscala/collection/IterableOps;
            0      34     2     n   I
           21       9     3 max$extension_that   I
    Signature: #79                          // (Lscala/collection/IterableOps<TA;*Ljava/lang/Object;>;I)V
    MethodParameters:
      Name                           Flags
      underlying                     final
      n                              final
}
InnerClasses:
  public static #9= #2 of #8;             // TakeRight=class scala/collection/View$TakeRight of class scala/collection/View
Signature: #3                           // <A:Ljava/lang/Object;>Lscala/collection/AbstractView<TA;>;
SourceFile: "View.scala"
  ScalaInlineInfo: length = 0x1D (unknown attribute)
   01 00 00 05 00 4D 00 4E 00 00 45 00 46 00 00 14
   00 15 00 00 2E 00 2B 00 00 13 00 2B 00
  Scala: length = 0x0 (unknown attribute)

