Classfile /Users/mw/Projects/slang-braindump/.jar/jar11/assemble/slang-braindump/assemble/content/org/apache/commons/io/file/Counters$BigIntegerPathCounters.class
  Last modified May 29, 2022; size 818 bytes
  SHA-256 checksum b8c4cdd4cd8898365670efa991cb6dd2d6b787cdd4840da1a1d4caa1b6471bf1
  Compiled from "Counters.java"
class org.apache.commons.io.file.Counters$BigIntegerPathCounters extends org.apache.commons.io.file.Counters$AbstractPathCounters
  minor version: 0
  major version: 52
  flags: (0x0020) ACC_SUPER
  this_class: #3                          // org/apache/commons/io/file/Counters$BigIntegerPathCounters
  super_class: #4                         // org/apache/commons/io/file/Counters$AbstractPathCounters
  interfaces: 0, fields: 0, methods: 1, attributes: 2
Constant pool:
   #1 = Methodref          #16.#17        // org/apache/commons/io/file/Counters.bigIntegerCounter:()Lorg/apache/commons/io/file/Counters$Counter;
   #2 = Methodref          #4.#18         // org/apache/commons/io/file/Counters$AbstractPathCounters."<init>":(Lorg/apache/commons/io/file/Counters$Counter;Lorg/apache/commons/io/file/Counters$Counter;Lorg/apache/commons/io/file/Counters$Counter;)V
   #3 = Class              #19            // org/apache/commons/io/file/Counters$BigIntegerPathCounters
   #4 = Class              #20            // org/apache/commons/io/file/Counters$AbstractPathCounters
   #5 = Utf8               <init>
   #6 = Utf8               ()V
   #7 = Utf8               Code
   #8 = Utf8               LineNumberTable
   #9 = Utf8               LocalVariableTable
  #10 = Utf8               this
  #11 = Utf8               BigIntegerPathCounters
  #12 = Utf8               InnerClasses
  #13 = Utf8               Lorg/apache/commons/io/file/Counters$BigIntegerPathCounters;
  #14 = Utf8               SourceFile
  #15 = Utf8               Counters.java
  #16 = Class              #22            // org/apache/commons/io/file/Counters
  #17 = NameAndType        #23:#26        // bigIntegerCounter:()Lorg/apache/commons/io/file/Counters$Counter;
  #18 = NameAndType        #5:#27         // "<init>":(Lorg/apache/commons/io/file/Counters$Counter;Lorg/apache/commons/io/file/Counters$Counter;Lorg/apache/commons/io/file/Counters$Counter;)V
  #19 = Utf8               org/apache/commons/io/file/Counters$BigIntegerPathCounters
  #20 = Utf8               org/apache/commons/io/file/Counters$AbstractPathCounters
  #21 = Utf8               AbstractPathCounters
  #22 = Utf8               org/apache/commons/io/file/Counters
  #23 = Utf8               bigIntegerCounter
  #24 = Class              #28            // org/apache/commons/io/file/Counters$Counter
  #25 = Utf8               Counter
  #26 = Utf8               ()Lorg/apache/commons/io/file/Counters$Counter;
  #27 = Utf8               (Lorg/apache/commons/io/file/Counters$Counter;Lorg/apache/commons/io/file/Counters$Counter;Lorg/apache/commons/io/file/Counters$Counter;)V
  #28 = Utf8               org/apache/commons/io/file/Counters$Counter
{
  protected org.apache.commons.io.file.Counters$BigIntegerPathCounters();
    descriptor: ()V
    flags: (0x0004) ACC_PROTECTED
    Code:
      stack=4, locals=1, args_size=1
         0: aload_0
         1: invokestatic  #1                  // Method org/apache/commons/io/file/Counters.bigIntegerCounter:()Lorg/apache/commons/io/file/Counters$Counter;
         4: invokestatic  #1                  // Method org/apache/commons/io/file/Counters.bigIntegerCounter:()Lorg/apache/commons/io/file/Counters$Counter;
         7: invokestatic  #1                  // Method org/apache/commons/io/file/Counters.bigIntegerCounter:()Lorg/apache/commons/io/file/Counters$Counter;
        10: invokespecial #2                  // Method org/apache/commons/io/file/Counters$AbstractPathCounters."<init>":(Lorg/apache/commons/io/file/Counters$Counter;Lorg/apache/commons/io/file/Counters$Counter;Lorg/apache/commons/io/file/Counters$Counter;)V
        13: return
      LineNumberTable:
        line 166: 0
        line 167: 13
      LocalVariableTable:
        Start  Length  Slot  Name   Signature
            0      14     0  this   Lorg/apache/commons/io/file/Counters$BigIntegerPathCounters;
}
SourceFile: "Counters.java"
InnerClasses:
  private static #11= #3 of #16;          // BigIntegerPathCounters=class org/apache/commons/io/file/Counters$BigIntegerPathCounters of class org/apache/commons/io/file/Counters
  private static #21= #4 of #16;          // AbstractPathCounters=class org/apache/commons/io/file/Counters$AbstractPathCounters of class org/apache/commons/io/file/Counters
  public static #25= #24 of #16;          // Counter=class org/apache/commons/io/file/Counters$Counter of class org/apache/commons/io/file/Counters
