Classfile /Users/mw/Projects/slang-braindump/.jar/jar11/assemble/slang-braindump/assemble/content/org/apache/commons/io/file/DeletingPathVisitor.class
  Last modified May 29, 2022; size 4827 bytes
  SHA-256 checksum 11bf67a18e4de88e136f854cbc8cc1afad63947dff3243988cd0b8a25cb576ba
  Compiled from "DeletingPathVisitor.java"
public class org.apache.commons.io.file.DeletingPathVisitor extends org.apache.commons.io.file.CountingPathVisitor
  minor version: 0
  major version: 52
  flags: (0x0021) ACC_PUBLIC, ACC_SUPER
  this_class: #1                          // org/apache/commons/io/file/DeletingPathVisitor
  super_class: #43                        // org/apache/commons/io/file/CountingPathVisitor
  interfaces: 0, fields: 2, methods: 13, attributes: 2
Constant pool:
    #1 = Class              #103          // org/apache/commons/io/file/DeletingPathVisitor
    #2 = Methodref          #104.#105     // org/apache/commons/io/file/Counters.bigIntegerPathCounters:()Lorg/apache/commons/io/file/Counters$PathCounters;
    #3 = Class              #106          // java/lang/String
    #4 = Methodref          #1.#107       // org/apache/commons/io/file/DeletingPathVisitor."<init>":(Lorg/apache/commons/io/file/Counters$PathCounters;[Ljava/lang/String;)V
    #5 = Methodref          #104.#108     // org/apache/commons/io/file/Counters.longPathCounters:()Lorg/apache/commons/io/file/Counters$PathCounters;
    #6 = Methodref          #43.#109      // org/apache/commons/io/file/CountingPathVisitor."<init>":(Lorg/apache/commons/io/file/Counters$PathCounters;)V
    #7 = Methodref          #110.#111     // "[Ljava/lang/String;".clone:()Ljava/lang/Object;
    #8 = Class              #45           // "[Ljava/lang/String;"
    #9 = Fieldref           #1.#112       // org/apache/commons/io/file/DeletingPathVisitor.EMPTY_STRING_ARRAY:[Ljava/lang/String;
   #10 = Methodref          #113.#114     // java/util/Arrays.sort:([Ljava/lang/Object;)V
   #11 = Fieldref           #1.#115       // org/apache/commons/io/file/DeletingPathVisitor.skip:[Ljava/lang/String;
   #12 = Methodref          #116.#117     // org/apache/commons/io/file/StandardDeleteOption.overrideReadOnly:([Lorg/apache/commons/io/file/DeleteOption;)Z
   #13 = Fieldref           #1.#118       // org/apache/commons/io/file/DeletingPathVisitor.overrideReadOnly:Z
   #14 = Fieldref           #119.#120     // org/apache/commons/io/file/PathUtils.EMPTY_DELETE_OPTION_ARRAY:[Lorg/apache/commons/io/file/DeleteOption;
   #15 = Methodref          #1.#121       // org/apache/commons/io/file/DeletingPathVisitor."<init>":(Lorg/apache/commons/io/file/Counters$PathCounters;[Lorg/apache/commons/io/file/DeleteOption;[Ljava/lang/String;)V
   #16 = InterfaceMethodref #39.#122      // java/nio/file/Path.getFileName:()Ljava/nio/file/Path;
   #17 = Methodref          #123.#124     // java/util/Objects.toString:(Ljava/lang/Object;Ljava/lang/String;)Ljava/lang/String;
   #18 = Methodref          #113.#125     // java/util/Arrays.binarySearch:([Ljava/lang/Object;Ljava/lang/Object;)I
   #19 = Methodref          #43.#126      // org/apache/commons/io/file/CountingPathVisitor.equals:(Ljava/lang/Object;)Z
   #20 = Methodref          #24.#127      // java/lang/Object.getClass:()Ljava/lang/Class;
   #21 = Methodref          #113.#128     // java/util/Arrays.equals:([Ljava/lang/Object;[Ljava/lang/Object;)Z
   #22 = Methodref          #43.#129      // org/apache/commons/io/file/CountingPathVisitor.hashCode:()I
   #23 = Methodref          #113.#130     // java/util/Arrays.hashCode:([Ljava/lang/Object;)I
   #24 = Class              #131          // java/lang/Object
   #25 = Methodref          #132.#133     // java/lang/Boolean.valueOf:(Z)Ljava/lang/Boolean;
   #26 = Methodref          #123.#134     // java/util/Objects.hash:([Ljava/lang/Object;)I
   #27 = Methodref          #119.#135     // org/apache/commons/io/file/PathUtils.isEmptyDirectory:(Ljava/nio/file/Path;)Z
   #28 = Methodref          #136.#137     // java/nio/file/Files.deleteIfExists:(Ljava/nio/file/Path;)Z
   #29 = Methodref          #43.#138      // org/apache/commons/io/file/CountingPathVisitor.postVisitDirectory:(Ljava/nio/file/Path;Ljava/io/IOException;)Ljava/nio/file/FileVisitResult;
   #30 = Methodref          #43.#139      // org/apache/commons/io/file/CountingPathVisitor.preVisitDirectory:(Ljava/lang/Object;Ljava/nio/file/attribute/BasicFileAttributes;)Ljava/nio/file/FileVisitResult;
   #31 = Methodref          #1.#140       // org/apache/commons/io/file/DeletingPathVisitor.accept:(Ljava/nio/file/Path;)Z
   #32 = Fieldref           #141.#142     // java/nio/file/FileVisitResult.CONTINUE:Ljava/nio/file/FileVisitResult;
   #33 = Fieldref           #141.#143     // java/nio/file/FileVisitResult.SKIP_SUBTREE:Ljava/nio/file/FileVisitResult;
   #34 = Class              #144          // java/nio/file/LinkOption
   #35 = Fieldref           #34.#145      // java/nio/file/LinkOption.NOFOLLOW_LINKS:Ljava/nio/file/LinkOption;
   #36 = Methodref          #136.#146     // java/nio/file/Files.exists:(Ljava/nio/file/Path;[Ljava/nio/file/LinkOption;)Z
   #37 = Methodref          #119.#147     // org/apache/commons/io/file/PathUtils.setReadOnly:(Ljava/nio/file/Path;Z[Ljava/nio/file/LinkOption;)Ljava/nio/file/Path;
   #38 = Methodref          #1.#148       // org/apache/commons/io/file/DeletingPathVisitor.updateFileCounters:(Ljava/nio/file/Path;Ljava/nio/file/attribute/BasicFileAttributes;)V
   #39 = Class              #149          // java/nio/file/Path
   #40 = Methodref          #1.#138       // org/apache/commons/io/file/DeletingPathVisitor.postVisitDirectory:(Ljava/nio/file/Path;Ljava/io/IOException;)Ljava/nio/file/FileVisitResult;
   #41 = Methodref          #1.#150       // org/apache/commons/io/file/DeletingPathVisitor.visitFile:(Ljava/nio/file/Path;Ljava/nio/file/attribute/BasicFileAttributes;)Ljava/nio/file/FileVisitResult;
   #42 = Methodref          #1.#151       // org/apache/commons/io/file/DeletingPathVisitor.preVisitDirectory:(Ljava/nio/file/Path;Ljava/nio/file/attribute/BasicFileAttributes;)Ljava/nio/file/FileVisitResult;
   #43 = Class              #152          // org/apache/commons/io/file/CountingPathVisitor
   #44 = Utf8               skip
   #45 = Utf8               [Ljava/lang/String;
   #46 = Utf8               overrideReadOnly
   #47 = Utf8               Z
   #48 = Utf8               withBigIntegerCounters
   #49 = Utf8               ()Lorg/apache/commons/io/file/DeletingPathVisitor;
   #50 = Utf8               Code
   #51 = Utf8               LineNumberTable
   #52 = Utf8               withLongCounters
   #53 = Utf8               <init>
   #54 = Class              #153          // org/apache/commons/io/file/Counters$PathCounters
   #55 = Utf8               PathCounters
   #56 = Utf8               InnerClasses
   #57 = Utf8               (Lorg/apache/commons/io/file/Counters$PathCounters;[Lorg/apache/commons/io/file/DeleteOption;[Ljava/lang/String;)V
   #58 = Utf8               LocalVariableTable
   #59 = Utf8               this
   #60 = Utf8               Lorg/apache/commons/io/file/DeletingPathVisitor;
   #61 = Utf8               pathCounter
   #62 = Utf8               Lorg/apache/commons/io/file/Counters$PathCounters;
   #63 = Utf8               deleteOption
   #64 = Utf8               [Lorg/apache/commons/io/file/DeleteOption;
   #65 = Utf8               temp
   #66 = Utf8               StackMapTable
   #67 = Class              #103          // org/apache/commons/io/file/DeletingPathVisitor
   #68 = Class              #153          // org/apache/commons/io/file/Counters$PathCounters
   #69 = Class              #64           // "[Lorg/apache/commons/io/file/DeleteOption;"
   #70 = Utf8               (Lorg/apache/commons/io/file/Counters$PathCounters;[Ljava/lang/String;)V
   #71 = Utf8               accept
   #72 = Utf8               (Ljava/nio/file/Path;)Z
   #73 = Utf8               path
   #74 = Utf8               Ljava/nio/file/Path;
   #75 = Utf8               equals
   #76 = Utf8               (Ljava/lang/Object;)Z
   #77 = Utf8               obj
   #78 = Utf8               Ljava/lang/Object;
   #79 = Utf8               other
   #80 = Utf8               hashCode
   #81 = Utf8               ()I
   #82 = Utf8               prime
   #83 = Utf8               I
   #84 = Utf8               result
   #85 = Utf8               postVisitDirectory
   #86 = Utf8               (Ljava/nio/file/Path;Ljava/io/IOException;)Ljava/nio/file/FileVisitResult;
   #87 = Utf8               dir
   #88 = Utf8               exc
   #89 = Utf8               Ljava/io/IOException;
   #90 = Utf8               Exceptions
   #91 = Class              #154          // java/io/IOException
   #92 = Utf8               preVisitDirectory
   #93 = Utf8               (Ljava/nio/file/Path;Ljava/nio/file/attribute/BasicFileAttributes;)Ljava/nio/file/FileVisitResult;
   #94 = Utf8               attrs
   #95 = Utf8               Ljava/nio/file/attribute/BasicFileAttributes;
   #96 = Class              #155          // java/nio/file/FileVisitResult
   #97 = Utf8               visitFile
   #98 = Utf8               file
   #99 = Utf8               (Ljava/lang/Object;Ljava/io/IOException;)Ljava/nio/file/FileVisitResult;
  #100 = Utf8               (Ljava/lang/Object;Ljava/nio/file/attribute/BasicFileAttributes;)Ljava/nio/file/FileVisitResult;
  #101 = Utf8               SourceFile
  #102 = Utf8               DeletingPathVisitor.java
  #103 = Utf8               org/apache/commons/io/file/DeletingPathVisitor
  #104 = Class              #156          // org/apache/commons/io/file/Counters
  #105 = NameAndType        #157:#158     // bigIntegerPathCounters:()Lorg/apache/commons/io/file/Counters$PathCounters;
  #106 = Utf8               java/lang/String
  #107 = NameAndType        #53:#70       // "<init>":(Lorg/apache/commons/io/file/Counters$PathCounters;[Ljava/lang/String;)V
  #108 = NameAndType        #159:#158     // longPathCounters:()Lorg/apache/commons/io/file/Counters$PathCounters;
  #109 = NameAndType        #53:#160      // "<init>":(Lorg/apache/commons/io/file/Counters$PathCounters;)V
  #110 = Class              #45           // "[Ljava/lang/String;"
  #111 = NameAndType        #161:#162     // clone:()Ljava/lang/Object;
  #112 = NameAndType        #163:#45      // EMPTY_STRING_ARRAY:[Ljava/lang/String;
  #113 = Class              #164          // java/util/Arrays
  #114 = NameAndType        #165:#166     // sort:([Ljava/lang/Object;)V
  #115 = NameAndType        #44:#45       // skip:[Ljava/lang/String;
  #116 = Class              #167          // org/apache/commons/io/file/StandardDeleteOption
  #117 = NameAndType        #46:#168      // overrideReadOnly:([Lorg/apache/commons/io/file/DeleteOption;)Z
  #118 = NameAndType        #46:#47       // overrideReadOnly:Z
  #119 = Class              #169          // org/apache/commons/io/file/PathUtils
  #120 = NameAndType        #170:#64      // EMPTY_DELETE_OPTION_ARRAY:[Lorg/apache/commons/io/file/DeleteOption;
  #121 = NameAndType        #53:#57       // "<init>":(Lorg/apache/commons/io/file/Counters$PathCounters;[Lorg/apache/commons/io/file/DeleteOption;[Ljava/lang/String;)V
  #122 = NameAndType        #171:#172     // getFileName:()Ljava/nio/file/Path;
  #123 = Class              #173          // java/util/Objects
  #124 = NameAndType        #174:#175     // toString:(Ljava/lang/Object;Ljava/lang/String;)Ljava/lang/String;
  #125 = NameAndType        #176:#177     // binarySearch:([Ljava/lang/Object;Ljava/lang/Object;)I
  #126 = NameAndType        #75:#76       // equals:(Ljava/lang/Object;)Z
  #127 = NameAndType        #178:#179     // getClass:()Ljava/lang/Class;
  #128 = NameAndType        #75:#180      // equals:([Ljava/lang/Object;[Ljava/lang/Object;)Z
  #129 = NameAndType        #80:#81       // hashCode:()I
  #130 = NameAndType        #80:#181      // hashCode:([Ljava/lang/Object;)I
  #131 = Utf8               java/lang/Object
  #132 = Class              #182          // java/lang/Boolean
  #133 = NameAndType        #183:#184     // valueOf:(Z)Ljava/lang/Boolean;
  #134 = NameAndType        #185:#181     // hash:([Ljava/lang/Object;)I
  #135 = NameAndType        #186:#72      // isEmptyDirectory:(Ljava/nio/file/Path;)Z
  #136 = Class              #187          // java/nio/file/Files
  #137 = NameAndType        #188:#72      // deleteIfExists:(Ljava/nio/file/Path;)Z
  #138 = NameAndType        #85:#86       // postVisitDirectory:(Ljava/nio/file/Path;Ljava/io/IOException;)Ljava/nio/file/FileVisitResult;
  #139 = NameAndType        #92:#100      // preVisitDirectory:(Ljava/lang/Object;Ljava/nio/file/attribute/BasicFileAttributes;)Ljava/nio/file/FileVisitResult;
  #140 = NameAndType        #71:#72       // accept:(Ljava/nio/file/Path;)Z
  #141 = Class              #155          // java/nio/file/FileVisitResult
  #142 = NameAndType        #189:#190     // CONTINUE:Ljava/nio/file/FileVisitResult;
  #143 = NameAndType        #191:#190     // SKIP_SUBTREE:Ljava/nio/file/FileVisitResult;
  #144 = Utf8               java/nio/file/LinkOption
  #145 = NameAndType        #192:#193     // NOFOLLOW_LINKS:Ljava/nio/file/LinkOption;
  #146 = NameAndType        #194:#195     // exists:(Ljava/nio/file/Path;[Ljava/nio/file/LinkOption;)Z
  #147 = NameAndType        #196:#197     // setReadOnly:(Ljava/nio/file/Path;Z[Ljava/nio/file/LinkOption;)Ljava/nio/file/Path;
  #148 = NameAndType        #198:#199     // updateFileCounters:(Ljava/nio/file/Path;Ljava/nio/file/attribute/BasicFileAttributes;)V
  #149 = Utf8               java/nio/file/Path
  #150 = NameAndType        #97:#93       // visitFile:(Ljava/nio/file/Path;Ljava/nio/file/attribute/BasicFileAttributes;)Ljava/nio/file/FileVisitResult;
  #151 = NameAndType        #92:#93       // preVisitDirectory:(Ljava/nio/file/Path;Ljava/nio/file/attribute/BasicFileAttributes;)Ljava/nio/file/FileVisitResult;
  #152 = Utf8               org/apache/commons/io/file/CountingPathVisitor
  #153 = Utf8               org/apache/commons/io/file/Counters$PathCounters
  #154 = Utf8               java/io/IOException
  #155 = Utf8               java/nio/file/FileVisitResult
  #156 = Utf8               org/apache/commons/io/file/Counters
  #157 = Utf8               bigIntegerPathCounters
  #158 = Utf8               ()Lorg/apache/commons/io/file/Counters$PathCounters;
  #159 = Utf8               longPathCounters
  #160 = Utf8               (Lorg/apache/commons/io/file/Counters$PathCounters;)V
  #161 = Utf8               clone
  #162 = Utf8               ()Ljava/lang/Object;
  #163 = Utf8               EMPTY_STRING_ARRAY
  #164 = Utf8               java/util/Arrays
  #165 = Utf8               sort
  #166 = Utf8               ([Ljava/lang/Object;)V
  #167 = Utf8               org/apache/commons/io/file/StandardDeleteOption
  #168 = Utf8               ([Lorg/apache/commons/io/file/DeleteOption;)Z
  #169 = Utf8               org/apache/commons/io/file/PathUtils
  #170 = Utf8               EMPTY_DELETE_OPTION_ARRAY
  #171 = Utf8               getFileName
  #172 = Utf8               ()Ljava/nio/file/Path;
  #173 = Utf8               java/util/Objects
  #174 = Utf8               toString
  #175 = Utf8               (Ljava/lang/Object;Ljava/lang/String;)Ljava/lang/String;
  #176 = Utf8               binarySearch
  #177 = Utf8               ([Ljava/lang/Object;Ljava/lang/Object;)I
  #178 = Utf8               getClass
  #179 = Utf8               ()Ljava/lang/Class;
  #180 = Utf8               ([Ljava/lang/Object;[Ljava/lang/Object;)Z
  #181 = Utf8               ([Ljava/lang/Object;)I
  #182 = Utf8               java/lang/Boolean
  #183 = Utf8               valueOf
  #184 = Utf8               (Z)Ljava/lang/Boolean;
  #185 = Utf8               hash
  #186 = Utf8               isEmptyDirectory
  #187 = Utf8               java/nio/file/Files
  #188 = Utf8               deleteIfExists
  #189 = Utf8               CONTINUE
  #190 = Utf8               Ljava/nio/file/FileVisitResult;
  #191 = Utf8               SKIP_SUBTREE
  #192 = Utf8               NOFOLLOW_LINKS
  #193 = Utf8               Ljava/nio/file/LinkOption;
  #194 = Utf8               exists
  #195 = Utf8               (Ljava/nio/file/Path;[Ljava/nio/file/LinkOption;)Z
  #196 = Utf8               setReadOnly
  #197 = Utf8               (Ljava/nio/file/Path;Z[Ljava/nio/file/LinkOption;)Ljava/nio/file/Path;
  #198 = Utf8               updateFileCounters
  #199 = Utf8               (Ljava/nio/file/Path;Ljava/nio/file/attribute/BasicFileAttributes;)V
{
  private final java.lang.String[] skip;
    descriptor: [Ljava/lang/String;
    flags: (0x0012) ACC_PRIVATE, ACC_FINAL

  private final boolean overrideReadOnly;
    descriptor: Z
    flags: (0x0012) ACC_PRIVATE, ACC_FINAL

  public static org.apache.commons.io.file.DeletingPathVisitor withBigIntegerCounters();
    descriptor: ()Lorg/apache/commons/io/file/DeletingPathVisitor;
    flags: (0x0009) ACC_PUBLIC, ACC_STATIC
    Code:
      stack=4, locals=0, args_size=0
         0: new           #1                  // class org/apache/commons/io/file/DeletingPathVisitor
         3: dup
         4: invokestatic  #2                  // Method org/apache/commons/io/file/Counters.bigIntegerPathCounters:()Lorg/apache/commons/io/file/Counters$PathCounters;
         7: iconst_0
         8: anewarray     #3                  // class java/lang/String
        11: invokespecial #4                  // Method "<init>":(Lorg/apache/commons/io/file/Counters$PathCounters;[Ljava/lang/String;)V
        14: areturn
      LineNumberTable:
        line 45: 0

  public static org.apache.commons.io.file.DeletingPathVisitor withLongCounters();
    descriptor: ()Lorg/apache/commons/io/file/DeletingPathVisitor;
    flags: (0x0009) ACC_PUBLIC, ACC_STATIC
    Code:
      stack=4, locals=0, args_size=0
         0: new           #1                  // class org/apache/commons/io/file/DeletingPathVisitor
         3: dup
         4: invokestatic  #5                  // Method org/apache/commons/io/file/Counters.longPathCounters:()Lorg/apache/commons/io/file/Counters$PathCounters;
         7: iconst_0
         8: anewarray     #3                  // class java/lang/String
        11: invokespecial #4                  // Method "<init>":(Lorg/apache/commons/io/file/Counters$PathCounters;[Ljava/lang/String;)V
        14: areturn
      LineNumberTable:
        line 54: 0

  public org.apache.commons.io.file.DeletingPathVisitor(org.apache.commons.io.file.Counters$PathCounters, org.apache.commons.io.file.DeleteOption[], java.lang.String...);
    descriptor: (Lorg/apache/commons/io/file/Counters$PathCounters;[Lorg/apache/commons/io/file/DeleteOption;[Ljava/lang/String;)V
    flags: (0x0081) ACC_PUBLIC, ACC_VARARGS
    Code:
      stack=2, locals=5, args_size=4
         0: aload_0
         1: aload_1
         2: invokespecial #6                  // Method org/apache/commons/io/file/CountingPathVisitor."<init>":(Lorg/apache/commons/io/file/Counters$PathCounters;)V
         5: aload_3
         6: ifnull        19
         9: aload_3
        10: invokevirtual #7                  // Method "[Ljava/lang/String;".clone:()Ljava/lang/Object;
        13: checkcast     #8                  // class "[Ljava/lang/String;"
        16: goto          22
        19: getstatic     #9                  // Field EMPTY_STRING_ARRAY:[Ljava/lang/String;
        22: astore        4
        24: aload         4
        26: invokestatic  #10                 // Method java/util/Arrays.sort:([Ljava/lang/Object;)V
        29: aload_0
        30: aload         4
        32: putfield      #11                 // Field skip:[Ljava/lang/String;
        35: aload_0
        36: aload_2
        37: invokestatic  #12                 // Method org/apache/commons/io/file/StandardDeleteOption.overrideReadOnly:([Lorg/apache/commons/io/file/DeleteOption;)Z
        40: putfield      #13                 // Field overrideReadOnly:Z
        43: return
      LineNumberTable:
        line 69: 0
        line 70: 5
        line 71: 24
        line 72: 29
        line 73: 35
        line 74: 43
      LocalVariableTable:
        Start  Length  Slot  Name   Signature
            0      44     0  this   Lorg/apache/commons/io/file/DeletingPathVisitor;
            0      44     1 pathCounter   Lorg/apache/commons/io/file/Counters$PathCounters;
            0      44     2 deleteOption   [Lorg/apache/commons/io/file/DeleteOption;
            0      44     3  skip   [Ljava/lang/String;
           24      20     4  temp   [Ljava/lang/String;
      StackMapTable: number_of_entries = 2
        frame_type = 255 /* full_frame */
          offset_delta = 19
          locals = [ class org/apache/commons/io/file/DeletingPathVisitor, class org/apache/commons/io/file/Counters$PathCounters, class "[Lorg/apache/commons/io/file/DeleteOption;", class "[Ljava/lang/String;" ]
          stack = []
        frame_type = 66 /* same_locals_1_stack_item */
          stack = [ class "[Ljava/lang/String;" ]

  public org.apache.commons.io.file.DeletingPathVisitor(org.apache.commons.io.file.Counters$PathCounters, java.lang.String...);
    descriptor: (Lorg/apache/commons/io/file/Counters$PathCounters;[Ljava/lang/String;)V
    flags: (0x0081) ACC_PUBLIC, ACC_VARARGS
    Code:
      stack=4, locals=3, args_size=3
         0: aload_0
         1: aload_1
         2: getstatic     #14                 // Field org/apache/commons/io/file/PathUtils.EMPTY_DELETE_OPTION_ARRAY:[Lorg/apache/commons/io/file/DeleteOption;
         5: aload_2
         6: invokespecial #15                 // Method "<init>":(Lorg/apache/commons/io/file/Counters$PathCounters;[Lorg/apache/commons/io/file/DeleteOption;[Ljava/lang/String;)V
         9: return
      LineNumberTable:
        line 84: 0
        line 85: 9
      LocalVariableTable:
        Start  Length  Slot  Name   Signature
            0      10     0  this   Lorg/apache/commons/io/file/DeletingPathVisitor;
            0      10     1 pathCounter   Lorg/apache/commons/io/file/Counters$PathCounters;
            0      10     2  skip   [Ljava/lang/String;

  private boolean accept(java.nio.file.Path);
    descriptor: (Ljava/nio/file/Path;)Z
    flags: (0x0002) ACC_PRIVATE
    Code:
      stack=3, locals=2, args_size=2
         0: aload_0
         1: getfield      #11                 // Field skip:[Ljava/lang/String;
         4: aload_1
         5: invokeinterface #16,  1           // InterfaceMethod java/nio/file/Path.getFileName:()Ljava/nio/file/Path;
        10: aconst_null
        11: invokestatic  #17                 // Method java/util/Objects.toString:(Ljava/lang/Object;Ljava/lang/String;)Ljava/lang/String;
        14: invokestatic  #18                 // Method java/util/Arrays.binarySearch:([Ljava/lang/Object;Ljava/lang/Object;)I
        17: ifge          24
        20: iconst_1
        21: goto          25
        24: iconst_0
        25: ireturn
      LineNumberTable:
        line 94: 0
      LocalVariableTable:
        Start  Length  Slot  Name   Signature
            0      26     0  this   Lorg/apache/commons/io/file/DeletingPathVisitor;
            0      26     1  path   Ljava/nio/file/Path;
      StackMapTable: number_of_entries = 2
        frame_type = 24 /* same */
        frame_type = 64 /* same_locals_1_stack_item */
          stack = [ int ]

  public boolean equals(java.lang.Object);
    descriptor: (Ljava/lang/Object;)Z
    flags: (0x0001) ACC_PUBLIC
    Code:
      stack=2, locals=3, args_size=2
         0: aload_0
         1: aload_1
         2: if_acmpne     7
         5: iconst_1
         6: ireturn
         7: aload_0
         8: aload_1
         9: invokespecial #19                 // Method org/apache/commons/io/file/CountingPathVisitor.equals:(Ljava/lang/Object;)Z
        12: ifne          17
        15: iconst_0
        16: ireturn
        17: aload_0
        18: invokevirtual #20                 // Method java/lang/Object.getClass:()Ljava/lang/Class;
        21: aload_1
        22: invokevirtual #20                 // Method java/lang/Object.getClass:()Ljava/lang/Class;
        25: if_acmpeq     30
        28: iconst_0
        29: ireturn
        30: aload_1
        31: checkcast     #1                  // class org/apache/commons/io/file/DeletingPathVisitor
        34: astore_2
        35: aload_0
        36: getfield      #13                 // Field overrideReadOnly:Z
        39: aload_2
        40: getfield      #13                 // Field overrideReadOnly:Z
        43: if_icmpne     64
        46: aload_0
        47: getfield      #11                 // Field skip:[Ljava/lang/String;
        50: aload_2
        51: getfield      #11                 // Field skip:[Ljava/lang/String;
        54: invokestatic  #21                 // Method java/util/Arrays.equals:([Ljava/lang/Object;[Ljava/lang/Object;)Z
        57: ifeq          64
        60: iconst_1
        61: goto          65
        64: iconst_0
        65: ireturn
      LineNumberTable:
        line 99: 0
        line 100: 5
        line 102: 7
        line 103: 15
        line 105: 17
        line 106: 28
        line 108: 30
        line 109: 35
      LocalVariableTable:
        Start  Length  Slot  Name   Signature
            0      66     0  this   Lorg/apache/commons/io/file/DeletingPathVisitor;
            0      66     1   obj   Ljava/lang/Object;
           35      31     2 other   Lorg/apache/commons/io/file/DeletingPathVisitor;
      StackMapTable: number_of_entries = 5
        frame_type = 7 /* same */
        frame_type = 9 /* same */
        frame_type = 12 /* same */
        frame_type = 252 /* append */
          offset_delta = 33
          locals = [ class org/apache/commons/io/file/DeletingPathVisitor ]
        frame_type = 64 /* same_locals_1_stack_item */
          stack = [ int ]

  public int hashCode();
    descriptor: ()I
    flags: (0x0001) ACC_PUBLIC
    Code:
      stack=5, locals=3, args_size=1
         0: bipush        31
         2: istore_1
         3: aload_0
         4: invokespecial #22                 // Method org/apache/commons/io/file/CountingPathVisitor.hashCode:()I
         7: istore_2
         8: bipush        31
        10: iload_2
        11: imul
        12: aload_0
        13: getfield      #11                 // Field skip:[Ljava/lang/String;
        16: invokestatic  #23                 // Method java/util/Arrays.hashCode:([Ljava/lang/Object;)I
        19: iadd
        20: istore_2
        21: bipush        31
        23: iload_2
        24: imul
        25: iconst_1
        26: anewarray     #24                 // class java/lang/Object
        29: dup
        30: iconst_0
        31: aload_0
        32: getfield      #13                 // Field overrideReadOnly:Z
        35: invokestatic  #25                 // Method java/lang/Boolean.valueOf:(Z)Ljava/lang/Boolean;
        38: aastore
        39: invokestatic  #26                 // Method java/util/Objects.hash:([Ljava/lang/Object;)I
        42: iadd
        43: istore_2
        44: iload_2
        45: ireturn
      LineNumberTable:
        line 114: 0
        line 115: 3
        line 116: 8
        line 117: 21
        line 118: 44
      LocalVariableTable:
        Start  Length  Slot  Name   Signature
            0      46     0  this   Lorg/apache/commons/io/file/DeletingPathVisitor;
            3      43     1 prime   I
            8      38     2 result   I

  public java.nio.file.FileVisitResult postVisitDirectory(java.nio.file.Path, java.io.IOException) throws java.io.IOException;
    descriptor: (Ljava/nio/file/Path;Ljava/io/IOException;)Ljava/nio/file/FileVisitResult;
    flags: (0x0001) ACC_PUBLIC
    Code:
      stack=3, locals=3, args_size=3
         0: aload_1
         1: invokestatic  #27                 // Method org/apache/commons/io/file/PathUtils.isEmptyDirectory:(Ljava/nio/file/Path;)Z
         4: ifeq          12
         7: aload_1
         8: invokestatic  #28                 // Method java/nio/file/Files.deleteIfExists:(Ljava/nio/file/Path;)Z
        11: pop
        12: aload_0
        13: aload_1
        14: aload_2
        15: invokespecial #29                 // Method org/apache/commons/io/file/CountingPathVisitor.postVisitDirectory:(Ljava/nio/file/Path;Ljava/io/IOException;)Ljava/nio/file/FileVisitResult;
        18: areturn
      LineNumberTable:
        line 123: 0
        line 124: 7
        line 126: 12
      LocalVariableTable:
        Start  Length  Slot  Name   Signature
            0      19     0  this   Lorg/apache/commons/io/file/DeletingPathVisitor;
            0      19     1   dir   Ljava/nio/file/Path;
            0      19     2   exc   Ljava/io/IOException;
      StackMapTable: number_of_entries = 1
        frame_type = 12 /* same */
    Exceptions:
      throws java.io.IOException

  public java.nio.file.FileVisitResult preVisitDirectory(java.nio.file.Path, java.nio.file.attribute.BasicFileAttributes) throws java.io.IOException;
    descriptor: (Ljava/nio/file/Path;Ljava/nio/file/attribute/BasicFileAttributes;)Ljava/nio/file/FileVisitResult;
    flags: (0x0001) ACC_PUBLIC
    Code:
      stack=3, locals=3, args_size=3
         0: aload_0
         1: aload_1
         2: aload_2
         3: invokespecial #30                 // Method org/apache/commons/io/file/CountingPathVisitor.preVisitDirectory:(Ljava/lang/Object;Ljava/nio/file/attribute/BasicFileAttributes;)Ljava/nio/file/FileVisitResult;
         6: pop
         7: aload_0
         8: aload_1
         9: invokespecial #31                 // Method accept:(Ljava/nio/file/Path;)Z
        12: ifeq          21
        15: getstatic     #32                 // Field java/nio/file/FileVisitResult.CONTINUE:Ljava/nio/file/FileVisitResult;
        18: goto          24
        21: getstatic     #33                 // Field java/nio/file/FileVisitResult.SKIP_SUBTREE:Ljava/nio/file/FileVisitResult;
        24: areturn
      LineNumberTable:
        line 131: 0
        line 132: 7
      LocalVariableTable:
        Start  Length  Slot  Name   Signature
            0      25     0  this   Lorg/apache/commons/io/file/DeletingPathVisitor;
            0      25     1   dir   Ljava/nio/file/Path;
            0      25     2 attrs   Ljava/nio/file/attribute/BasicFileAttributes;
      StackMapTable: number_of_entries = 2
        frame_type = 21 /* same */
        frame_type = 66 /* same_locals_1_stack_item */
          stack = [ class java/nio/file/FileVisitResult ]
    Exceptions:
      throws java.io.IOException

  public java.nio.file.FileVisitResult visitFile(java.nio.file.Path, java.nio.file.attribute.BasicFileAttributes) throws java.io.IOException;
    descriptor: (Ljava/nio/file/Path;Ljava/nio/file/attribute/BasicFileAttributes;)Ljava/nio/file/FileVisitResult;
    flags: (0x0001) ACC_PUBLIC
    Code:
      stack=6, locals=3, args_size=3
         0: aload_0
         1: aload_1
         2: invokespecial #31                 // Method accept:(Ljava/nio/file/Path;)Z
         5: ifeq          53
         8: aload_1
         9: iconst_1
        10: anewarray     #34                 // class java/nio/file/LinkOption
        13: dup
        14: iconst_0
        15: getstatic     #35                 // Field java/nio/file/LinkOption.NOFOLLOW_LINKS:Ljava/nio/file/LinkOption;
        18: aastore
        19: invokestatic  #36                 // Method java/nio/file/Files.exists:(Ljava/nio/file/Path;[Ljava/nio/file/LinkOption;)Z
        22: ifeq          53
        25: aload_0
        26: getfield      #13                 // Field overrideReadOnly:Z
        29: ifeq          48
        32: aload_1
        33: iconst_0
        34: iconst_1
        35: anewarray     #34                 // class java/nio/file/LinkOption
        38: dup
        39: iconst_0
        40: getstatic     #35                 // Field java/nio/file/LinkOption.NOFOLLOW_LINKS:Ljava/nio/file/LinkOption;
        43: aastore
        44: invokestatic  #37                 // Method org/apache/commons/io/file/PathUtils.setReadOnly:(Ljava/nio/file/Path;Z[Ljava/nio/file/LinkOption;)Ljava/nio/file/Path;
        47: pop
        48: aload_1
        49: invokestatic  #28                 // Method java/nio/file/Files.deleteIfExists:(Ljava/nio/file/Path;)Z
        52: pop
        53: aload_0
        54: aload_1
        55: aload_2
        56: invokevirtual #38                 // Method updateFileCounters:(Ljava/nio/file/Path;Ljava/nio/file/attribute/BasicFileAttributes;)V
        59: getstatic     #32                 // Field java/nio/file/FileVisitResult.CONTINUE:Ljava/nio/file/FileVisitResult;
        62: areturn
      LineNumberTable:
        line 138: 0
        line 139: 25
        line 140: 32
        line 142: 48
        line 144: 53
        line 145: 59
      LocalVariableTable:
        Start  Length  Slot  Name   Signature
            0      63     0  this   Lorg/apache/commons/io/file/DeletingPathVisitor;
            0      63     1  file   Ljava/nio/file/Path;
            0      63     2 attrs   Ljava/nio/file/attribute/BasicFileAttributes;
      StackMapTable: number_of_entries = 2
        frame_type = 48 /* same */
        frame_type = 4 /* same */
    Exceptions:
      throws java.io.IOException

  public java.nio.file.FileVisitResult postVisitDirectory(java.lang.Object, java.io.IOException) throws java.io.IOException;
    descriptor: (Ljava/lang/Object;Ljava/io/IOException;)Ljava/nio/file/FileVisitResult;
    flags: (0x1041) ACC_PUBLIC, ACC_BRIDGE, ACC_SYNTHETIC
    Code:
      stack=3, locals=3, args_size=3
         0: aload_0
         1: aload_1
         2: checkcast     #39                 // class java/nio/file/Path
         5: aload_2
         6: invokevirtual #40                 // Method postVisitDirectory:(Ljava/nio/file/Path;Ljava/io/IOException;)Ljava/nio/file/FileVisitResult;
         9: areturn
      LineNumberTable:
        line 36: 0
      LocalVariableTable:
        Start  Length  Slot  Name   Signature
            0      10     0  this   Lorg/apache/commons/io/file/DeletingPathVisitor;
    Exceptions:
      throws java.io.IOException

  public java.nio.file.FileVisitResult visitFile(java.lang.Object, java.nio.file.attribute.BasicFileAttributes) throws java.io.IOException;
    descriptor: (Ljava/lang/Object;Ljava/nio/file/attribute/BasicFileAttributes;)Ljava/nio/file/FileVisitResult;
    flags: (0x1041) ACC_PUBLIC, ACC_BRIDGE, ACC_SYNTHETIC
    Code:
      stack=3, locals=3, args_size=3
         0: aload_0
         1: aload_1
         2: checkcast     #39                 // class java/nio/file/Path
         5: aload_2
         6: invokevirtual #41                 // Method visitFile:(Ljava/nio/file/Path;Ljava/nio/file/attribute/BasicFileAttributes;)Ljava/nio/file/FileVisitResult;
         9: areturn
      LineNumberTable:
        line 36: 0
      LocalVariableTable:
        Start  Length  Slot  Name   Signature
            0      10     0  this   Lorg/apache/commons/io/file/DeletingPathVisitor;
    Exceptions:
      throws java.io.IOException

  public java.nio.file.FileVisitResult preVisitDirectory(java.lang.Object, java.nio.file.attribute.BasicFileAttributes) throws java.io.IOException;
    descriptor: (Ljava/lang/Object;Ljava/nio/file/attribute/BasicFileAttributes;)Ljava/nio/file/FileVisitResult;
    flags: (0x1041) ACC_PUBLIC, ACC_BRIDGE, ACC_SYNTHETIC
    Code:
      stack=3, locals=3, args_size=3
         0: aload_0
         1: aload_1
         2: checkcast     #39                 // class java/nio/file/Path
         5: aload_2
         6: invokevirtual #42                 // Method preVisitDirectory:(Ljava/nio/file/Path;Ljava/nio/file/attribute/BasicFileAttributes;)Ljava/nio/file/FileVisitResult;
         9: areturn
      LineNumberTable:
        line 36: 0
      LocalVariableTable:
        Start  Length  Slot  Name   Signature
            0      10     0  this   Lorg/apache/commons/io/file/DeletingPathVisitor;
    Exceptions:
      throws java.io.IOException
}
SourceFile: "DeletingPathVisitor.java"
InnerClasses:
  public static #55= #54 of #104;         // PathCounters=class org/apache/commons/io/file/Counters$PathCounters of class org/apache/commons/io/file/Counters
