Classfile /Users/mw/Projects/slang-braindump/.jar/jar11/assemble/slang-braindump/assemble/content/org/apache/commons/io/file/StandardDeleteOption.class
  Last modified May 29, 2022; size 1517 bytes
  SHA-256 checksum 2b2bf539c024dc06781ffeb9605a003056f1001bb41b16c8f65ad6983ea71dff
  Compiled from "StandardDeleteOption.java"
public final class org.apache.commons.io.file.StandardDeleteOption extends java.lang.Enum<org.apache.commons.io.file.StandardDeleteOption> implements org.apache.commons.io.file.DeleteOption
  minor version: 0
  major version: 52
  flags: (0x4031) ACC_PUBLIC, ACC_FINAL, ACC_SUPER, ACC_ENUM
  this_class: #4                          // org/apache/commons/io/file/StandardDeleteOption
  super_class: #10                        // java/lang/Enum
  interfaces: 1, fields: 2, methods: 5, attributes: 2
Constant pool:
   #1 = Fieldref           #4.#42         // org/apache/commons/io/file/StandardDeleteOption.$VALUES:[Lorg/apache/commons/io/file/StandardDeleteOption;
   #2 = Methodref          #43.#44        // "[Lorg/apache/commons/io/file/StandardDeleteOption;".clone:()Ljava/lang/Object;
   #3 = Class              #15            // "[Lorg/apache/commons/io/file/StandardDeleteOption;"
   #4 = Class              #45            // org/apache/commons/io/file/StandardDeleteOption
   #5 = Methodref          #10.#46        // java/lang/Enum.valueOf:(Ljava/lang/Class;Ljava/lang/String;)Ljava/lang/Enum;
   #6 = Methodref          #10.#47        // java/lang/Enum."<init>":(Ljava/lang/String;I)V
   #7 = Fieldref           #4.#48         // org/apache/commons/io/file/StandardDeleteOption.OVERRIDE_READ_ONLY:Lorg/apache/commons/io/file/StandardDeleteOption;
   #8 = String             #12            // OVERRIDE_READ_ONLY
   #9 = Methodref          #4.#47         // org/apache/commons/io/file/StandardDeleteOption."<init>":(Ljava/lang/String;I)V
  #10 = Class              #49            // java/lang/Enum
  #11 = Class              #50            // org/apache/commons/io/file/DeleteOption
  #12 = Utf8               OVERRIDE_READ_ONLY
  #13 = Utf8               Lorg/apache/commons/io/file/StandardDeleteOption;
  #14 = Utf8               $VALUES
  #15 = Utf8               [Lorg/apache/commons/io/file/StandardDeleteOption;
  #16 = Utf8               values
  #17 = Utf8               ()[Lorg/apache/commons/io/file/StandardDeleteOption;
  #18 = Utf8               Code
  #19 = Utf8               LineNumberTable
  #20 = Utf8               valueOf
  #21 = Utf8               (Ljava/lang/String;)Lorg/apache/commons/io/file/StandardDeleteOption;
  #22 = Utf8               LocalVariableTable
  #23 = Utf8               name
  #24 = Utf8               Ljava/lang/String;
  #25 = Utf8               <init>
  #26 = Utf8               (Ljava/lang/String;I)V
  #27 = Utf8               this
  #28 = Utf8               Signature
  #29 = Utf8               ()V
  #30 = Utf8               overrideReadOnly
  #31 = Utf8               ([Lorg/apache/commons/io/file/DeleteOption;)Z
  #32 = Utf8               deleteOption
  #33 = Utf8               Lorg/apache/commons/io/file/DeleteOption;
  #34 = Utf8               options
  #35 = Utf8               [Lorg/apache/commons/io/file/DeleteOption;
  #36 = Utf8               StackMapTable
  #37 = Class              #35            // "[Lorg/apache/commons/io/file/DeleteOption;"
  #38 = Utf8               <clinit>
  #39 = Utf8               Ljava/lang/Enum<Lorg/apache/commons/io/file/StandardDeleteOption;>;Lorg/apache/commons/io/file/DeleteOption;
  #40 = Utf8               SourceFile
  #41 = Utf8               StandardDeleteOption.java
  #42 = NameAndType        #14:#15        // $VALUES:[Lorg/apache/commons/io/file/StandardDeleteOption;
  #43 = Class              #15            // "[Lorg/apache/commons/io/file/StandardDeleteOption;"
  #44 = NameAndType        #51:#52        // clone:()Ljava/lang/Object;
  #45 = Utf8               org/apache/commons/io/file/StandardDeleteOption
  #46 = NameAndType        #20:#53        // valueOf:(Ljava/lang/Class;Ljava/lang/String;)Ljava/lang/Enum;
  #47 = NameAndType        #25:#26        // "<init>":(Ljava/lang/String;I)V
  #48 = NameAndType        #12:#13        // OVERRIDE_READ_ONLY:Lorg/apache/commons/io/file/StandardDeleteOption;
  #49 = Utf8               java/lang/Enum
  #50 = Utf8               org/apache/commons/io/file/DeleteOption
  #51 = Utf8               clone
  #52 = Utf8               ()Ljava/lang/Object;
  #53 = Utf8               (Ljava/lang/Class;Ljava/lang/String;)Ljava/lang/Enum;
{
  public static final org.apache.commons.io.file.StandardDeleteOption OVERRIDE_READ_ONLY;
    descriptor: Lorg/apache/commons/io/file/StandardDeleteOption;
    flags: (0x4019) ACC_PUBLIC, ACC_STATIC, ACC_FINAL, ACC_ENUM

  private static final org.apache.commons.io.file.StandardDeleteOption[] $VALUES;
    descriptor: [Lorg/apache/commons/io/file/StandardDeleteOption;
    flags: (0x101a) ACC_PRIVATE, ACC_STATIC, ACC_FINAL, ACC_SYNTHETIC

  public static org.apache.commons.io.file.StandardDeleteOption[] values();
    descriptor: ()[Lorg/apache/commons/io/file/StandardDeleteOption;
    flags: (0x0009) ACC_PUBLIC, ACC_STATIC
    Code:
      stack=1, locals=0, args_size=0
         0: getstatic     #1                  // Field $VALUES:[Lorg/apache/commons/io/file/StandardDeleteOption;
         3: invokevirtual #2                  // Method "[Lorg/apache/commons/io/file/StandardDeleteOption;".clone:()Ljava/lang/Object;
         6: checkcast     #3                  // class "[Lorg/apache/commons/io/file/StandardDeleteOption;"
         9: areturn
      LineNumberTable:
        line 25: 0

  public static org.apache.commons.io.file.StandardDeleteOption valueOf(java.lang.String);
    descriptor: (Ljava/lang/String;)Lorg/apache/commons/io/file/StandardDeleteOption;
    flags: (0x0009) ACC_PUBLIC, ACC_STATIC
    Code:
      stack=2, locals=1, args_size=1
         0: ldc           #4                  // class org/apache/commons/io/file/StandardDeleteOption
         2: aload_0
         3: invokestatic  #5                  // Method java/lang/Enum.valueOf:(Ljava/lang/Class;Ljava/lang/String;)Ljava/lang/Enum;
         6: checkcast     #4                  // class org/apache/commons/io/file/StandardDeleteOption
         9: areturn
      LineNumberTable:
        line 25: 0
      LocalVariableTable:
        Start  Length  Slot  Name   Signature
            0      10     0  name   Ljava/lang/String;

  private org.apache.commons.io.file.StandardDeleteOption();
    descriptor: (Ljava/lang/String;I)V
    flags: (0x0002) ACC_PRIVATE
    Code:
      stack=3, locals=3, args_size=3
         0: aload_0
         1: aload_1
         2: iload_2
         3: invokespecial #6                  // Method java/lang/Enum."<init>":(Ljava/lang/String;I)V
         6: return
      LineNumberTable:
        line 25: 0
      LocalVariableTable:
        Start  Length  Slot  Name   Signature
            0       7     0  this   Lorg/apache/commons/io/file/StandardDeleteOption;
    Signature: #29                          // ()V

  public static boolean overrideReadOnly(org.apache.commons.io.file.DeleteOption[]);
    descriptor: ([Lorg/apache/commons/io/file/DeleteOption;)Z
    flags: (0x0009) ACC_PUBLIC, ACC_STATIC
    Code:
      stack=2, locals=5, args_size=1
         0: aload_0
         1: ifnull        9
         4: aload_0
         5: arraylength
         6: ifne          11
         9: iconst_0
        10: ireturn
        11: aload_0
        12: astore_1
        13: aload_1
        14: arraylength
        15: istore_2
        16: iconst_0
        17: istore_3
        18: iload_3
        19: iload_2
        20: if_icmpge     44
        23: aload_1
        24: iload_3
        25: aaload
        26: astore        4
        28: aload         4
        30: getstatic     #7                  // Field OVERRIDE_READ_ONLY:Lorg/apache/commons/io/file/StandardDeleteOption;
        33: if_acmpne     38
        36: iconst_1
        37: ireturn
        38: iinc          3, 1
        41: goto          18
        44: iconst_0
        45: ireturn
      LineNumberTable:
        line 41: 0
        line 42: 9
        line 44: 11
        line 45: 28
        line 46: 36
        line 44: 38
        line 49: 44
      LocalVariableTable:
        Start  Length  Slot  Name   Signature
           28      10     4 deleteOption   Lorg/apache/commons/io/file/DeleteOption;
            0      46     0 options   [Lorg/apache/commons/io/file/DeleteOption;
      StackMapTable: number_of_entries = 5
        frame_type = 9 /* same */
        frame_type = 1 /* same */
        frame_type = 254 /* append */
          offset_delta = 6
          locals = [ class "[Lorg/apache/commons/io/file/DeleteOption;", int, int ]
        frame_type = 19 /* same */
        frame_type = 248 /* chop */
          offset_delta = 5

  static {};
    descriptor: ()V
    flags: (0x0008) ACC_STATIC
    Code:
      stack=4, locals=0, args_size=0
         0: new           #4                  // class org/apache/commons/io/file/StandardDeleteOption
         3: dup
         4: ldc           #8                  // String OVERRIDE_READ_ONLY
         6: iconst_0
         7: invokespecial #9                  // Method "<init>":(Ljava/lang/String;I)V
        10: putstatic     #7                  // Field OVERRIDE_READ_ONLY:Lorg/apache/commons/io/file/StandardDeleteOption;
        13: iconst_1
        14: anewarray     #4                  // class org/apache/commons/io/file/StandardDeleteOption
        17: dup
        18: iconst_0
        19: getstatic     #7                  // Field OVERRIDE_READ_ONLY:Lorg/apache/commons/io/file/StandardDeleteOption;
        22: aastore
        23: putstatic     #1                  // Field $VALUES:[Lorg/apache/commons/io/file/StandardDeleteOption;
        26: return
      LineNumberTable:
        line 30: 0
        line 25: 13
}
Signature: #39                          // Ljava/lang/Enum<Lorg/apache/commons/io/file/StandardDeleteOption;>;Lorg/apache/commons/io/file/DeleteOption;
SourceFile: "StandardDeleteOption.java"
