Classfile /Users/mw/Projects/slang-braindump/.jar/jar8/assemble/slang-braindump/assemble/content/scala/xml/dtd/impl/Base$Meta.class
  Last modified May 29, 2022; size 1059 bytes
  SHA-256 checksum f88345af75aa1edebf222ee81748ab5ac743a0fb00afcda35866acd4adfebeda
  Compiled from "Base.scala"
public class scala.xml.dtd.impl.Base$Meta extends scala.xml.dtd.impl.Base$RegExp
  minor version: 0
  major version: 52
  flags: (0x0021) ACC_PUBLIC, ACC_SUPER
  this_class: #2                          // scala/xml/dtd/impl/Base$Meta
  super_class: #4                         // scala/xml/dtd/impl/Base$RegExp
  interfaces: 0, fields: 2, methods: 4, attributes: 4
Constant pool:
   #1 = Utf8               scala/xml/dtd/impl/Base$Meta
   #2 = Class              #1             // scala/xml/dtd/impl/Base$Meta
   #3 = Utf8               scala/xml/dtd/impl/Base$RegExp
   #4 = Class              #3             // scala/xml/dtd/impl/Base$RegExp
   #5 = Utf8               Base.scala
   #6 = Utf8               scala/xml/dtd/impl/Base
   #7 = Class              #6             // scala/xml/dtd/impl/Base
   #8 = Utf8               Meta
   #9 = Utf8               RegExp
  #10 = Utf8               r1
  #11 = Utf8               Lscala/xml/dtd/impl/Base$RegExp;
  #12 = Utf8               isNullable
  #13 = Utf8               Z
  #14 = Utf8               ()Z
  #15 = NameAndType        #12:#13        // isNullable:Z
  #16 = Fieldref           #2.#15         // scala/xml/dtd/impl/Base$Meta.isNullable:Z
  #17 = Utf8               this
  #18 = Utf8               Lscala/xml/dtd/impl/Base$Meta;
  #19 = Utf8               r
  #20 = Utf8               ()Lscala/xml/dtd/impl/Base$RegExp;
  #21 = NameAndType        #10:#11        // r1:Lscala/xml/dtd/impl/Base$RegExp;
  #22 = Fieldref           #2.#21         // scala/xml/dtd/impl/Base$Meta.r1:Lscala/xml/dtd/impl/Base$RegExp;
  #23 = Utf8               scala$xml$dtd$impl$Base$Meta$$$outer
  #24 = Utf8               ()Lscala/xml/dtd/impl/Base;
  #25 = Utf8               $outer
  #26 = Utf8               Lscala/xml/dtd/impl/Base;
  #27 = NameAndType        #25:#26        // $outer:Lscala/xml/dtd/impl/Base;
  #28 = Fieldref           #2.#27         // scala/xml/dtd/impl/Base$Meta.$outer:Lscala/xml/dtd/impl/Base;
  #29 = Utf8               <init>
  #30 = Utf8               (Lscala/xml/dtd/impl/Base;Lscala/xml/dtd/impl/Base$RegExp;)V
  #31 = Utf8               (Lscala/xml/dtd/impl/Base;)V
  #32 = NameAndType        #29:#31        // "<init>":(Lscala/xml/dtd/impl/Base;)V
  #33 = Methodref          #4.#32         // scala/xml/dtd/impl/Base$RegExp."<init>":(Lscala/xml/dtd/impl/Base;)V
  #34 = NameAndType        #12:#14        // isNullable:()Z
  #35 = Methodref          #4.#34         // scala/xml/dtd/impl/Base$RegExp.isNullable:()Z
  #36 = Utf8               Code
  #37 = Utf8               LineNumberTable
  #38 = Utf8               LocalVariableTable
  #39 = Utf8               MethodParameters
  #40 = Utf8               InnerClasses
  #41 = Utf8               SourceFile
  #42 = Utf8               ScalaInlineInfo
  #43 = Utf8               Scala
{
  private final scala.xml.dtd.impl.Base$RegExp r1;
    descriptor: Lscala/xml/dtd/impl/Base$RegExp;
    flags: (0x0012) ACC_PRIVATE, ACC_FINAL

  private final boolean isNullable;
    descriptor: Z
    flags: (0x0012) ACC_PRIVATE, ACC_FINAL

  public final boolean isNullable();
    descriptor: ()Z
    flags: (0x0011) ACC_PUBLIC, ACC_FINAL
    Code:
      stack=1, locals=1, args_size=1
         0: aload_0
         1: getfield      #16                 // Field isNullable:Z
         4: ireturn
      LineNumberTable:
        line 66: 0
      LocalVariableTable:
        Start  Length  Slot  Name   Signature
            0       5     0  this   Lscala/xml/dtd/impl/Base$Meta;

  public scala.xml.dtd.impl.Base$RegExp r();
    descriptor: ()Lscala/xml/dtd/impl/Base$RegExp;
    flags: (0x0001) ACC_PUBLIC
    Code:
      stack=1, locals=1, args_size=1
         0: aload_0
         1: getfield      #22                 // Field r1:Lscala/xml/dtd/impl/Base$RegExp;
         4: areturn
      LineNumberTable:
        line 67: 0
      LocalVariableTable:
        Start  Length  Slot  Name   Signature
            0       5     0  this   Lscala/xml/dtd/impl/Base$Meta;

  public scala.xml.dtd.impl.Base scala$xml$dtd$impl$Base$Meta$$$outer();
    descriptor: ()Lscala/xml/dtd/impl/Base;
    flags: (0x1001) ACC_PUBLIC, ACC_SYNTHETIC
    Code:
      stack=1, locals=1, args_size=1
         0: aload_0
         1: getfield      #28                 // Field $outer:Lscala/xml/dtd/impl/Base;
         4: areturn
      LineNumberTable:
        line 65: 0
      LocalVariableTable:
        Start  Length  Slot  Name   Signature
            0       5     0  this   Lscala/xml/dtd/impl/Base$Meta;

  public scala.xml.dtd.impl.Base$Meta(scala.xml.dtd.impl.Base, scala.xml.dtd.impl.Base$RegExp);
    descriptor: (Lscala/xml/dtd/impl/Base;Lscala/xml/dtd/impl/Base$RegExp;)V
    flags: (0x0001) ACC_PUBLIC
    Code:
      stack=2, locals=3, args_size=3
         0: aload_0
         1: aload_2
         2: putfield      #22                 // Field r1:Lscala/xml/dtd/impl/Base$RegExp;
         5: aload_0
         6: aload_1
         7: invokespecial #33                 // Method scala/xml/dtd/impl/Base$RegExp."<init>":(Lscala/xml/dtd/impl/Base;)V
        10: aload_0
        11: aload_2
        12: invokevirtual #35                 // Method scala/xml/dtd/impl/Base$RegExp.isNullable:()Z
        15: putfield      #16                 // Field isNullable:Z
        18: return
      LineNumberTable:
        line 65: 0
        line 66: 10
        line 65: 18
      LocalVariableTable:
        Start  Length  Slot  Name   Signature
            0      19     0  this   Lscala/xml/dtd/impl/Base$Meta;
            0      19     1 $outer   Lscala/xml/dtd/impl/Base;
            0      19     2    r1   Lscala/xml/dtd/impl/Base$RegExp;
    MethodParameters:
      Name                           Flags
      $outer                         final synthetic
      r1                             final
}
InnerClasses:
  public #8= #2 of #7;                    // Meta=class scala/xml/dtd/impl/Base$Meta of class scala/xml/dtd/impl/Base
  public abstract #9= #4 of #7;           // RegExp=class scala/xml/dtd/impl/Base$RegExp of class scala/xml/dtd/impl/Base
SourceFile: "Base.scala"
  ScalaInlineInfo: length = 0x18 (unknown attribute)
   01 00 00 04 00 1D 00 1E 00 00 0C 00 0E 01 00 13
   00 14 00 00 17 00 18 00
  Scala: length = 0x0 (unknown attribute)

