Classfile /Users/mw/Projects/slang-braindump/.jar/jar8/assemble/slang-braindump/assemble/content/scala/xml/dtd/impl/WordExp$Wildcard$.class
  Last modified May 29, 2022; size 1350 bytes
  SHA-256 checksum 2ef2e1907c2b1ee0f1399a13522bda18b03347fd89f19c7512d694f236e79a47
  Compiled from "WordExp.scala"
public class scala.xml.dtd.impl.WordExp$Wildcard$ extends scala.runtime.AbstractFunction0<scala.xml.dtd.impl.WordExp$Wildcard> implements java.io.Serializable
  minor version: 0
  major version: 52
  flags: (0x0021) ACC_PUBLIC, ACC_SUPER
  this_class: #2                          // scala/xml/dtd/impl/WordExp$Wildcard$
  super_class: #5                         // scala/runtime/AbstractFunction0
  interfaces: 1, fields: 1, methods: 5, attributes: 5
Constant pool:
   #1 = Utf8               scala/xml/dtd/impl/WordExp$Wildcard$
   #2 = Class              #1             // scala/xml/dtd/impl/WordExp$Wildcard$
   #3 = Utf8               Lscala/runtime/AbstractFunction0<Lscala/xml/dtd/impl/WordExp$Wildcard;>;Ljava/io/Serializable;
   #4 = Utf8               scala/runtime/AbstractFunction0
   #5 = Class              #4             // scala/runtime/AbstractFunction0
   #6 = Utf8               java/io/Serializable
   #7 = Class              #6             // java/io/Serializable
   #8 = Utf8               WordExp.scala
   #9 = Utf8               scala/xml/dtd/impl/WordExp$Wildcard
  #10 = Class              #9             // scala/xml/dtd/impl/WordExp$Wildcard
  #11 = Utf8               scala/xml/dtd/impl/WordExp
  #12 = Class              #11            // scala/xml/dtd/impl/WordExp
  #13 = Utf8               Wildcard
  #14 = Utf8               Wildcard$
  #15 = Utf8               $outer
  #16 = Utf8               Lscala/xml/dtd/impl/WordExp;
  #17 = Utf8               toString
  #18 = Utf8               ()Ljava/lang/String;
  #19 = String             #13            // Wildcard
  #20 = Utf8               this
  #21 = Utf8               Lscala/xml/dtd/impl/WordExp$Wildcard$;
  #22 = Utf8               apply
  #23 = Utf8               ()Lscala/xml/dtd/impl/WordExp$Wildcard;
  #24 = NameAndType        #15:#16        // $outer:Lscala/xml/dtd/impl/WordExp;
  #25 = Fieldref           #2.#24         // scala/xml/dtd/impl/WordExp$Wildcard$.$outer:Lscala/xml/dtd/impl/WordExp;
  #26 = Utf8               <init>
  #27 = Utf8               (Lscala/xml/dtd/impl/WordExp;)V
  #28 = NameAndType        #26:#27        // "<init>":(Lscala/xml/dtd/impl/WordExp;)V
  #29 = Methodref          #10.#28        // scala/xml/dtd/impl/WordExp$Wildcard."<init>":(Lscala/xml/dtd/impl/WordExp;)V
  #30 = Utf8               unapply
  #31 = Utf8               (Lscala/xml/dtd/impl/WordExp$Wildcard;)Z
  #32 = Utf8               x$0
  #33 = Utf8               Lscala/xml/dtd/impl/WordExp$Wildcard;
  #34 = Utf8               ()Ljava/lang/Object;
  #35 = NameAndType        #22:#23        // apply:()Lscala/xml/dtd/impl/WordExp$Wildcard;
  #36 = Methodref          #2.#35         // scala/xml/dtd/impl/WordExp$Wildcard$.apply:()Lscala/xml/dtd/impl/WordExp$Wildcard;
  #37 = Utf8               ()V
  #38 = NameAndType        #26:#37        // "<init>":()V
  #39 = Methodref          #5.#38         // scala/runtime/AbstractFunction0."<init>":()V
  #40 = Utf8               Code
  #41 = Utf8               LineNumberTable
  #42 = Utf8               LocalVariableTable
  #43 = Utf8               StackMapTable
  #44 = Utf8               MethodParameters
  #45 = Utf8               InnerClasses
  #46 = Utf8               Signature
  #47 = Utf8               SourceFile
  #48 = Utf8               ScalaInlineInfo
  #49 = Utf8               Scala
{
  private final scala.xml.dtd.impl.WordExp $outer;
    descriptor: Lscala/xml/dtd/impl/WordExp;
    flags: (0x1012) ACC_PRIVATE, ACC_FINAL, ACC_SYNTHETIC

  public final java.lang.String toString();
    descriptor: ()Ljava/lang/String;
    flags: (0x0011) ACC_PUBLIC, ACC_FINAL
    Code:
      stack=1, locals=1, args_size=1
         0: ldc           #19                 // String Wildcard
         2: areturn
      LineNumberTable:
        line 56: 0
      LocalVariableTable:
        Start  Length  Slot  Name   Signature
            0       3     0  this   Lscala/xml/dtd/impl/WordExp$Wildcard$;

  public scala.xml.dtd.impl.WordExp$Wildcard apply();
    descriptor: ()Lscala/xml/dtd/impl/WordExp$Wildcard;
    flags: (0x0001) ACC_PUBLIC
    Code:
      stack=3, locals=1, args_size=1
         0: new           #10                 // class scala/xml/dtd/impl/WordExp$Wildcard
         3: dup
         4: aload_0
         5: getfield      #25                 // Field $outer:Lscala/xml/dtd/impl/WordExp;
         8: invokespecial #29                 // Method scala/xml/dtd/impl/WordExp$Wildcard."<init>":(Lscala/xml/dtd/impl/WordExp;)V
        11: areturn
      LineNumberTable:
        line 56: 0
      LocalVariableTable:
        Start  Length  Slot  Name   Signature
            0      12     0  this   Lscala/xml/dtd/impl/WordExp$Wildcard$;

  public boolean unapply(scala.xml.dtd.impl.WordExp$Wildcard);
    descriptor: (Lscala/xml/dtd/impl/WordExp$Wildcard;)Z
    flags: (0x0001) ACC_PUBLIC
    Code:
      stack=1, locals=2, args_size=2
         0: aload_1
         1: ifnonnull     8
         4: iconst_0
         5: goto          9
         8: iconst_1
         9: ireturn
      StackMapTable: number_of_entries = 2
        frame_type = 8 /* same */
        frame_type = 64 /* same_locals_1_stack_item */
          stack = [ int ]
      LineNumberTable:
        line 56: 0
      LocalVariableTable:
        Start  Length  Slot  Name   Signature
            0      10     0  this   Lscala/xml/dtd/impl/WordExp$Wildcard$;
            0      10     1   x$0   Lscala/xml/dtd/impl/WordExp$Wildcard;
    MethodParameters:
      Name                           Flags
      x$0                            final

  public java.lang.Object apply();
    descriptor: ()Ljava/lang/Object;
    flags: (0x1041) ACC_PUBLIC, ACC_BRIDGE, ACC_SYNTHETIC
    Code:
      stack=1, locals=1, args_size=1
         0: aload_0
         1: invokevirtual #36                 // Method apply:()Lscala/xml/dtd/impl/WordExp$Wildcard;
         4: areturn
      LineNumberTable:
        line 56: 0
      LocalVariableTable:
        Start  Length  Slot  Name   Signature
            0       5     0  this   Lscala/xml/dtd/impl/WordExp$Wildcard$;

  public scala.xml.dtd.impl.WordExp$Wildcard$(scala.xml.dtd.impl.WordExp);
    descriptor: (Lscala/xml/dtd/impl/WordExp;)V
    flags: (0x0001) ACC_PUBLIC
    Code:
      stack=2, locals=2, args_size=2
         0: aload_1
         1: ifnonnull     6
         4: aconst_null
         5: athrow
         6: aload_0
         7: aload_1
         8: putfield      #25                 // Field $outer:Lscala/xml/dtd/impl/WordExp;
        11: aload_0
        12: invokespecial #39                 // Method scala/runtime/AbstractFunction0."<init>":()V
        15: return
      StackMapTable: number_of_entries = 1
        frame_type = 6 /* same */
      LineNumberTable:
        line 56: 0
      LocalVariableTable:
        Start  Length  Slot  Name   Signature
            0      16     0  this   Lscala/xml/dtd/impl/WordExp$Wildcard$;
            0      16     1 $outer   Lscala/xml/dtd/impl/WordExp;
    MethodParameters:
      Name                           Flags
      $outer                         final synthetic
}
InnerClasses:
  public #13= #10 of #12;                 // Wildcard=class scala/xml/dtd/impl/WordExp$Wildcard of class scala/xml/dtd/impl/WordExp
  public #14= #2 of #12;                  // Wildcard$=class scala/xml/dtd/impl/WordExp$Wildcard$ of class scala/xml/dtd/impl/WordExp
Signature: #3                           // Lscala/runtime/AbstractFunction0<Lscala/xml/dtd/impl/WordExp$Wildcard;>;Ljava/io/Serializable;
SourceFile: "WordExp.scala"
  ScalaInlineInfo: length = 0x1D (unknown attribute)
   01 01 00 05 00 1A 00 1B 01 00 16 00 22 01 00 16
   00 17 01 00 11 00 12 01 00 1E 00 1F 01
  Scala: length = 0x0 (unknown attribute)

