Classfile /Users/mw/Projects/slang-braindump/.jar/jar11/assemble/slang-braindump/assemble/content/org/apache/commons/lang3/reflect/InheritanceUtils.class
  Last modified May 29, 2022; size 1015 bytes
  SHA-256 checksum f05988c90e2d1691b1e70593eda7fe5f68f83cf244c5f3c8765cf0a95402e052
  Compiled from "InheritanceUtils.java"
public class org.apache.commons.lang3.reflect.InheritanceUtils
  minor version: 0
  major version: 52
  flags: (0x0021) ACC_PUBLIC, ACC_SUPER
  this_class: #6                          // org/apache/commons/lang3/reflect/InheritanceUtils
  super_class: #7                         // java/lang/Object
  interfaces: 0, fields: 0, methods: 2, attributes: 1
Constant pool:
   #1 = Methodref          #7.#31         // java/lang/Object."<init>":()V
   #2 = Methodref          #7.#32         // java/lang/Object.equals:(Ljava/lang/Object;)Z
   #3 = Methodref          #26.#33        // java/lang/Class.getSuperclass:()Ljava/lang/Class;
   #4 = Methodref          #34.#35        // org/apache/commons/lang3/BooleanUtils.toInteger:(Z)I
   #5 = Methodref          #6.#36         // org/apache/commons/lang3/reflect/InheritanceUtils.distance:(Ljava/lang/Class;Ljava/lang/Class;)I
   #6 = Class              #37            // org/apache/commons/lang3/reflect/InheritanceUtils
   #7 = Class              #38            // java/lang/Object
   #8 = Utf8               <init>
   #9 = Utf8               ()V
  #10 = Utf8               Code
  #11 = Utf8               LineNumberTable
  #12 = Utf8               LocalVariableTable
  #13 = Utf8               this
  #14 = Utf8               Lorg/apache/commons/lang3/reflect/InheritanceUtils;
  #15 = Utf8               distance
  #16 = Utf8               (Ljava/lang/Class;Ljava/lang/Class;)I
  #17 = Utf8               child
  #18 = Utf8               Ljava/lang/Class;
  #19 = Utf8               parent
  #20 = Utf8               cParent
  #21 = Utf8               d
  #22 = Utf8               I
  #23 = Utf8               LocalVariableTypeTable
  #24 = Utf8               Ljava/lang/Class<*>;
  #25 = Utf8               StackMapTable
  #26 = Class              #39            // java/lang/Class
  #27 = Utf8               Signature
  #28 = Utf8               (Ljava/lang/Class<*>;Ljava/lang/Class<*>;)I
  #29 = Utf8               SourceFile
  #30 = Utf8               InheritanceUtils.java
  #31 = NameAndType        #8:#9          // "<init>":()V
  #32 = NameAndType        #40:#41        // equals:(Ljava/lang/Object;)Z
  #33 = NameAndType        #42:#43        // getSuperclass:()Ljava/lang/Class;
  #34 = Class              #44            // org/apache/commons/lang3/BooleanUtils
  #35 = NameAndType        #45:#46        // toInteger:(Z)I
  #36 = NameAndType        #15:#16        // distance:(Ljava/lang/Class;Ljava/lang/Class;)I
  #37 = Utf8               org/apache/commons/lang3/reflect/InheritanceUtils
  #38 = Utf8               java/lang/Object
  #39 = Utf8               java/lang/Class
  #40 = Utf8               equals
  #41 = Utf8               (Ljava/lang/Object;)Z
  #42 = Utf8               getSuperclass
  #43 = Utf8               ()Ljava/lang/Class;
  #44 = Utf8               org/apache/commons/lang3/BooleanUtils
  #45 = Utf8               toInteger
  #46 = Utf8               (Z)I
{
  public org.apache.commons.lang3.reflect.InheritanceUtils();
    descriptor: ()V
    flags: (0x0001) ACC_PUBLIC
    Code:
      stack=1, locals=1, args_size=1
         0: aload_0
         1: invokespecial #1                  // Method java/lang/Object."<init>":()V
         4: return
      LineNumberTable:
        line 37: 0
        line 38: 4
      LocalVariableTable:
        Start  Length  Slot  Name   Signature
            0       5     0  this   Lorg/apache/commons/lang3/reflect/InheritanceUtils;

  public static int distance(java.lang.Class<?>, java.lang.Class<?>);
    descriptor: (Ljava/lang/Class;Ljava/lang/Class;)I
    flags: (0x0009) ACC_PUBLIC, ACC_STATIC
    Code:
      stack=3, locals=4, args_size=2
         0: aload_0
         1: ifnull        8
         4: aload_1
         5: ifnonnull     10
         8: iconst_m1
         9: ireturn
        10: aload_0
        11: aload_1
        12: invokevirtual #2                  // Method java/lang/Object.equals:(Ljava/lang/Object;)Z
        15: ifeq          20
        18: iconst_0
        19: ireturn
        20: aload_0
        21: invokevirtual #3                  // Method java/lang/Class.getSuperclass:()Ljava/lang/Class;
        24: astore_2
        25: aload_1
        26: aload_2
        27: invokevirtual #2                  // Method java/lang/Object.equals:(Ljava/lang/Object;)Z
        30: invokestatic  #4                  // Method org/apache/commons/lang3/BooleanUtils.toInteger:(Z)I
        33: istore_3
        34: iload_3
        35: iconst_1
        36: if_icmpne     41
        39: iload_3
        40: ireturn
        41: iload_3
        42: aload_2
        43: aload_1
        44: invokestatic  #5                  // Method distance:(Ljava/lang/Class;Ljava/lang/Class;)I
        47: iadd
        48: istore_3
        49: iload_3
        50: ifle          59
        53: iload_3
        54: iconst_1
        55: iadd
        56: goto          60
        59: iconst_m1
        60: ireturn
      LineNumberTable:
        line 50: 0
        line 51: 8
        line 54: 10
        line 55: 18
        line 58: 20
        line 59: 25
        line 61: 34
        line 62: 39
        line 64: 41
        line 65: 49
      LocalVariableTable:
        Start  Length  Slot  Name   Signature
            0      61     0 child   Ljava/lang/Class;
            0      61     1 parent   Ljava/lang/Class;
           25      36     2 cParent   Ljava/lang/Class;
           34      27     3     d   I
      LocalVariableTypeTable:
        Start  Length  Slot  Name   Signature
            0      61     0 child   Ljava/lang/Class<*>;
            0      61     1 parent   Ljava/lang/Class<*>;
           25      36     2 cParent   Ljava/lang/Class<*>;
      StackMapTable: number_of_entries = 6
        frame_type = 8 /* same */
        frame_type = 1 /* same */
        frame_type = 9 /* same */
        frame_type = 253 /* append */
          offset_delta = 20
          locals = [ class java/lang/Class, int ]
        frame_type = 17 /* same */
        frame_type = 64 /* same_locals_1_stack_item */
          stack = [ int ]
    Signature: #28                          // (Ljava/lang/Class<*>;Ljava/lang/Class<*>;)I
}
SourceFile: "InheritanceUtils.java"
