Classfile /Users/mw/Projects/slang-braindump/.jar/jar11/assemble/slang-braindump/assemble/content/scala/collection/mutable/AbstractSeq.class
  Last modified May 29, 2022; size 2036 bytes
  SHA-256 checksum dddc89616d38b726e58d5343d20703539018c38095d48124d844d9c159a36e66
  Compiled from "Seq.scala"
public abstract class scala.collection.mutable.AbstractSeq<A extends java.lang.Object> extends scala.collection.AbstractSeq<A> implements scala.collection.mutable.Seq<A>
  minor version: 0
  major version: 52
  flags: (0x0421) ACC_PUBLIC, ACC_SUPER, ACC_ABSTRACT
  this_class: #2                          // scala/collection/mutable/AbstractSeq
  super_class: #5                         // scala/collection/AbstractSeq
  interfaces: 1, fields: 0, methods: 6, attributes: 5
Constant pool:
   #1 = Utf8               scala/collection/mutable/AbstractSeq
   #2 = Class              #1             // scala/collection/mutable/AbstractSeq
   #3 = Utf8               <A:Ljava/lang/Object;>Lscala/collection/AbstractSeq<TA;>;Lscala/collection/mutable/Seq<TA;>;
   #4 = Utf8               scala/collection/AbstractSeq
   #5 = Class              #4             // scala/collection/AbstractSeq
   #6 = Utf8               scala/collection/mutable/Seq
   #7 = Class              #6             // scala/collection/mutable/Seq
   #8 = Utf8               Seq.scala
   #9 = Utf8               Lscala/reflect/ScalaSignature;
  #10 = Utf8               bytes
  #11 = Utf8               \u0006\u0005\t2QAA\u0002\u0002\u0002)AQa\b\u0001\u0005\u0002\u0001\u00121\"\u00112tiJ\f7\r^*fc*\u0011A!B\u0001\b[V$\u0018M\u00197f\u0015\t1q!\u0001\u0006d_2dWm\u0019;j_:T\u0011\u0001C\u0001\u0006g\u000e\fG.Y\u0002\u0001+\tY\u0011cE\u0002\u0001\u0019m\u00012!\u0004\b\u0010\u001b\u0005)\u0011B\u0001\u0002\u0006!\t\u0001\u0012\u0003\u0004\u0001\u0005\u000bI\u0001!\u0019A\n\u0003\u0003\u0005\u000b\"\u0001\u0006\r\u0011\u0005U1R\"A\u0004\n\u0005]9!a\u0002(pi\"Lgn\u001a\t\u0003+eI!AG\u0004\u0003\u0007\u0005s\u0017\u0010E\u0002\u001d;=i\u0011aA\u0005\u0003=\r\u00111aU3r\u0003\u0019a\u0014N\\5u}Q\t\u0011\u0005E\u0002\u001d\u0001=\u0001
  #12 = Utf8               iterableFactory
  #13 = Utf8               ()Lscala/collection/SeqFactory;
  #14 = Utf8               ()Lscala/collection/SeqFactory<Lscala/collection/mutable/Seq;>;
  #15 = Utf8               iterableFactory$
  #16 = Utf8               (Lscala/collection/mutable/Seq;)Lscala/collection/SeqFactory;
  #17 = NameAndType        #15:#16        // iterableFactory$:(Lscala/collection/mutable/Seq;)Lscala/collection/SeqFactory;
  #18 = InterfaceMethodref #7.#17         // scala/collection/mutable/Seq.iterableFactory$:(Lscala/collection/mutable/Seq;)Lscala/collection/SeqFactory;
  #19 = Utf8               this
  #20 = Utf8               Lscala/collection/mutable/AbstractSeq;
  #21 = Utf8               clone
  #22 = Utf8               ()Ljava/lang/Object;
  #23 = Utf8               scala/collection/mutable/SeqOps
  #24 = Class              #23            // scala/collection/mutable/SeqOps
  #25 = Utf8               clone$
  #26 = Utf8               (Lscala/collection/mutable/SeqOps;)Ljava/lang/Object;
  #27 = NameAndType        #25:#26        // clone$:(Lscala/collection/mutable/SeqOps;)Ljava/lang/Object;
  #28 = InterfaceMethodref #24.#27        // scala/collection/mutable/SeqOps.clone$:(Lscala/collection/mutable/SeqOps;)Ljava/lang/Object;
  #29 = Utf8               transform
  #30 = Utf8               (Lscala/Function1;)Lscala/collection/mutable/SeqOps;
  #31 = Utf8               (Lscala/Function1<TA;TA;>;)Lscala/collection/mutable/SeqOps<TA;Lscala/collection/mutable/Seq;Lscala/collection/mutable/Seq<TA;>;>;
  #32 = Utf8               f
  #33 = Utf8               transform$
  #34 = Utf8               (Lscala/collection/mutable/SeqOps;Lscala/Function1;)Lscala/collection/mutable/SeqOps;
  #35 = NameAndType        #33:#34        // transform$:(Lscala/collection/mutable/SeqOps;Lscala/Function1;)Lscala/collection/mutable/SeqOps;
  #36 = InterfaceMethodref #24.#35        // scala/collection/mutable/SeqOps.transform$:(Lscala/collection/mutable/SeqOps;Lscala/Function1;)Lscala/collection/mutable/SeqOps;
  #37 = Utf8               Lscala/Function1;
  #38 = Utf8               scala$collection$mutable$Cloneable$$super$clone
  #39 = Utf8               java/lang/Object
  #40 = Class              #39            // java/lang/Object
  #41 = NameAndType        #21:#22        // clone:()Ljava/lang/Object;
  #42 = Methodref          #40.#41        // java/lang/Object.clone:()Ljava/lang/Object;
  #43 = Utf8               ()Lscala/collection/IterableFactory;
  #44 = NameAndType        #12:#13        // iterableFactory:()Lscala/collection/SeqFactory;
  #45 = Methodref          #2.#44         // scala/collection/mutable/AbstractSeq.iterableFactory:()Lscala/collection/SeqFactory;
  #46 = Utf8               <init>
  #47 = Utf8               ()V
  #48 = NameAndType        #46:#47        // "<init>":()V
  #49 = Methodref          #5.#48         // scala/collection/AbstractSeq."<init>":()V
  #50 = Utf8               Code
  #51 = Utf8               LineNumberTable
  #52 = Utf8               LocalVariableTable
  #53 = Utf8               Signature
  #54 = Utf8               Deprecated
  #55 = Utf8               MethodParameters
  #56 = Utf8               SourceFile
  #57 = Utf8               RuntimeVisibleAnnotations
  #58 = Utf8               ScalaInlineInfo
  #59 = Utf8               ScalaSig
{
  public scala.collection.SeqFactory<scala.collection.mutable.Seq> iterableFactory();
    descriptor: ()Lscala/collection/SeqFactory;
    flags: (0x0001) ACC_PUBLIC
    Code:
      stack=1, locals=1, args_size=1
         0: aload_0
         1: invokestatic  #18                 // InterfaceMethod scala/collection/mutable/Seq.iterableFactory$:(Lscala/collection/mutable/Seq;)Lscala/collection/SeqFactory;
         4: areturn
      LineNumberTable:
        line 67: 0
      LocalVariableTable:
        Start  Length  Slot  Name   Signature
            0       5     0  this   Lscala/collection/mutable/AbstractSeq;
    Signature: #14                          // ()Lscala/collection/SeqFactory<Lscala/collection/mutable/Seq;>;

  public java.lang.Object clone();
    descriptor: ()Ljava/lang/Object;
    flags: (0x0001) ACC_PUBLIC
    Code:
      stack=1, locals=1, args_size=1
         0: aload_0
         1: invokestatic  #28                 // InterfaceMethod scala/collection/mutable/SeqOps.clone$:(Lscala/collection/mutable/SeqOps;)Ljava/lang/Object;
         4: areturn
      LineNumberTable:
        line 67: 0
      LocalVariableTable:
        Start  Length  Slot  Name   Signature
            0       5     0  this   Lscala/collection/mutable/AbstractSeq;

  public final scala.collection.mutable.SeqOps<A, scala.collection.mutable.Seq, scala.collection.mutable.Seq<A>> transform(scala.Function1<A, A>);
    descriptor: (Lscala/Function1;)Lscala/collection/mutable/SeqOps;
    flags: (0x0011) ACC_PUBLIC, ACC_FINAL
    Code:
      stack=2, locals=2, args_size=2
         0: aload_0
         1: aload_1
         2: invokestatic  #36                 // InterfaceMethod scala/collection/mutable/SeqOps.transform$:(Lscala/collection/mutable/SeqOps;Lscala/Function1;)Lscala/collection/mutable/SeqOps;
         5: areturn
      LineNumberTable:
        line 67: 0
      LocalVariableTable:
        Start  Length  Slot  Name   Signature
            0       6     0  this   Lscala/collection/mutable/AbstractSeq;
            0       6     1     f   Lscala/Function1;
    Signature: #31                          // (Lscala/Function1<TA;TA;>;)Lscala/collection/mutable/SeqOps<TA;Lscala/collection/mutable/Seq;Lscala/collection/mutable/Seq<TA;>;>;
    Deprecated: true
    MethodParameters:
      Name                           Flags
      f                              final

  public java.lang.Object scala$collection$mutable$Cloneable$$super$clone();
    descriptor: ()Ljava/lang/Object;
    flags: (0x1001) ACC_PUBLIC, ACC_SYNTHETIC
    Code:
      stack=1, locals=1, args_size=1
         0: aload_0
         1: invokespecial #42                 // Method java/lang/Object.clone:()Ljava/lang/Object;
         4: areturn
      LineNumberTable:
        line 67: 0
      LocalVariableTable:
        Start  Length  Slot  Name   Signature
            0       5     0  this   Lscala/collection/mutable/AbstractSeq;

  public scala.collection.IterableFactory iterableFactory();
    descriptor: ()Lscala/collection/IterableFactory;
    flags: (0x1041) ACC_PUBLIC, ACC_BRIDGE, ACC_SYNTHETIC
    Code:
      stack=1, locals=1, args_size=1
         0: aload_0
         1: invokevirtual #45                 // Method iterableFactory:()Lscala/collection/SeqFactory;
         4: areturn
      LineNumberTable:
        line 67: 0
      LocalVariableTable:
        Start  Length  Slot  Name   Signature
            0       5     0  this   Lscala/collection/mutable/AbstractSeq;

  public scala.collection.mutable.AbstractSeq();
    descriptor: ()V
    flags: (0x0001) ACC_PUBLIC
    Code:
      stack=1, locals=1, args_size=1
         0: aload_0
         1: invokespecial #49                 // Method scala/collection/AbstractSeq."<init>":()V
         4: return
      LineNumberTable:
        line 67: 0
      LocalVariableTable:
        Start  Length  Slot  Name   Signature
            0       5     0  this   Lscala/collection/mutable/AbstractSeq;
}
Signature: #3                           // <A:Ljava/lang/Object;>Lscala/collection/AbstractSeq<TA;>;Lscala/collection/mutable/Seq<TA;>;
SourceFile: "Seq.scala"
RuntimeVisibleAnnotations:
  0: #9(#10=s#11)
    scala.reflect.ScalaSignature(
      bytes="\u0006\u0005\t2QAA\u0002\u0002\u0002)AQa\b\u0001\u0005\u0002\u0001\u00121\"\u00112tiJ\f7\r^*fc*\u0011A!B\u0001\b[V$\u0018M\u00197f\u0015\t1q!\u0001\u0006d_2dWm\u0019;j_:T\u0011\u0001C\u0001\u0006g\u000e\fG.Y\u0002\u0001+\tY\u0011cE\u0002\u0001\u0019m\u00012!\u0004\b\u0010\u001b\u0005)\u0011B\u0001\u0002\u0006!\t\u0001\u0012\u0003\u0004\u0001\u0005\u000bI\u0001!\u0019A\n\u0003\u0003\u0005\u000b\"\u0001\u0006\r\u0011\u0005U1R\"A\u0004\n\u0005]9!a\u0002(pi\"Lgn\u001a\t\u0003+eI!AG\u0004\u0003\u0007\u0005s\u0017\u0010E\u0002\u001d;=i\u0011aA\u0005\u0003=\r\u00111aU3r\u0003\u0019a\u0014N\\5u}Q\t\u0011\u0005E\u0002\u001d\u0001=\u0001"
    )
  ScalaInlineInfo: length = 0x22 (unknown attribute)
   01 00 00 06 00 2E 00 2F 00 00 15 00 16 00 00 0C
   00 2B 00 00 0C 00 0D 00 00 26 00 16 01 00 1D 00
   1E 05
  ScalaSig: length = 0x3 (unknown attribute)
   05 02 00
