Classfile /Users/mw/Projects/slang-braindump/.jar/jar11/assemble/slang-braindump/assemble/content/scala/collection/mutable/AnyRefMap$ToBuildFrom$.class
  Last modified May 29, 2022; size 3122 bytes
  SHA-256 checksum a59db6c72e0eca6f497cf21decc3fb7aa4a7ed8e887ff901ee86fcaf353eabed
  Compiled from "AnyRefMap.scala"
public class scala.collection.mutable.AnyRefMap$ToBuildFrom$ extends java.lang.Object implements scala.collection.BuildFrom<java.lang.Object, scala.Tuple2<java.lang.Object, java.lang.Object>, scala.collection.mutable.AnyRefMap<java.lang.Object, java.lang.Object>>
  minor version: 0
  major version: 52
  flags: (0x0021) ACC_PUBLIC, ACC_SUPER
  this_class: #2                          // scala/collection/mutable/AnyRefMap$ToBuildFrom$
  super_class: #5                         // java/lang/Object
  interfaces: 1, fields: 1, methods: 8, attributes: 5
Constant pool:
   #1 = Utf8               scala/collection/mutable/AnyRefMap$ToBuildFrom$
   #2 = Class              #1             // scala/collection/mutable/AnyRefMap$ToBuildFrom$
   #3 = Utf8               Ljava/lang/Object;Lscala/collection/BuildFrom<Ljava/lang/Object;Lscala/Tuple2<Ljava/lang/Object;Ljava/lang/Object;>;Lscala/collection/mutable/AnyRefMap<Ljava/lang/Object;Ljava/lang/Object;>;>;
   #4 = Utf8               java/lang/Object
   #5 = Class              #4             // java/lang/Object
   #6 = Utf8               scala/collection/BuildFrom
   #7 = Class              #6             // scala/collection/BuildFrom
   #8 = Utf8               AnyRefMap.scala
   #9 = Utf8               scala/collection/mutable/AnyRefMap$AnyRefMapBuilder
  #10 = Class              #9             // scala/collection/mutable/AnyRefMap$AnyRefMapBuilder
  #11 = Utf8               scala/collection/mutable/AnyRefMap
  #12 = Class              #11            // scala/collection/mutable/AnyRefMap
  #13 = Utf8               AnyRefMapBuilder
  #14 = Utf8               ToBuildFrom$
  #15 = Utf8               MODULE$
  #16 = Utf8               Lscala/collection/mutable/AnyRefMap$ToBuildFrom$;
  #17 = Utf8               <clinit>
  #18 = Utf8               ()V
  #19 = Utf8               <init>
  #20 = NameAndType        #19:#18        // "<init>":()V
  #21 = Methodref          #2.#20         // scala/collection/mutable/AnyRefMap$ToBuildFrom$."<init>":()V
  #22 = NameAndType        #15:#16        // MODULE$:Lscala/collection/mutable/AnyRefMap$ToBuildFrom$;
  #23 = Fieldref           #2.#22         // scala/collection/mutable/AnyRefMap$ToBuildFrom$.MODULE$:Lscala/collection/mutable/AnyRefMap$ToBuildFrom$;
  #24 = Utf8               apply
  #25 = Utf8               (Ljava/lang/Object;)Lscala/collection/mutable/Builder;
  #26 = Utf8               (Ljava/lang/Object;)Lscala/collection/mutable/Builder<Lscala/Tuple2<Ljava/lang/Object;Ljava/lang/Object;>;Lscala/collection/mutable/AnyRefMap<Ljava/lang/Object;Ljava/lang/Object;>;>;
  #27 = Utf8               from
  #28 = Utf8               apply$
  #29 = Utf8               (Lscala/collection/BuildFrom;Ljava/lang/Object;)Lscala/collection/mutable/Builder;
  #30 = NameAndType        #28:#29        // apply$:(Lscala/collection/BuildFrom;Ljava/lang/Object;)Lscala/collection/mutable/Builder;
  #31 = InterfaceMethodref #7.#30         // scala/collection/BuildFrom.apply$:(Lscala/collection/BuildFrom;Ljava/lang/Object;)Lscala/collection/mutable/Builder;
  #32 = Utf8               this
  #33 = Utf8               Ljava/lang/Object;
  #34 = Utf8               toFactory
  #35 = Utf8               (Ljava/lang/Object;)Lscala/collection/Factory;
  #36 = Utf8               (Ljava/lang/Object;)Lscala/collection/Factory<Lscala/Tuple2<Ljava/lang/Object;Ljava/lang/Object;>;Lscala/collection/mutable/AnyRefMap<Ljava/lang/Object;Ljava/lang/Object;>;>;
  #37 = Utf8               toFactory$
  #38 = Utf8               (Lscala/collection/BuildFrom;Ljava/lang/Object;)Lscala/collection/Factory;
  #39 = NameAndType        #37:#38        // toFactory$:(Lscala/collection/BuildFrom;Ljava/lang/Object;)Lscala/collection/Factory;
  #40 = InterfaceMethodref #7.#39         // scala/collection/BuildFrom.toFactory$:(Lscala/collection/BuildFrom;Ljava/lang/Object;)Lscala/collection/Factory;
  #41 = Utf8               fromSpecific
  #42 = Utf8               (Ljava/lang/Object;Lscala/collection/IterableOnce;)Lscala/collection/mutable/AnyRefMap;
  #43 = Utf8               (Ljava/lang/Object;Lscala/collection/IterableOnce<Lscala/Tuple2<Ljava/lang/Object;Ljava/lang/Object;>;>;)Lscala/collection/mutable/AnyRefMap<Ljava/lang/Object;Ljava/lang/Object;>;
  #44 = Utf8               it
  #45 = Utf8               scala/collection/mutable/AnyRefMap$
  #46 = Class              #45            // scala/collection/mutable/AnyRefMap$
  #47 = Utf8               Lscala/collection/mutable/AnyRefMap$;
  #48 = NameAndType        #15:#47        // MODULE$:Lscala/collection/mutable/AnyRefMap$;
  #49 = Fieldref           #46.#48        // scala/collection/mutable/AnyRefMap$.MODULE$:Lscala/collection/mutable/AnyRefMap$;
  #50 = Utf8               (Lscala/collection/IterableOnce;)Lscala/collection/mutable/AnyRefMap;
  #51 = NameAndType        #27:#50        // from:(Lscala/collection/IterableOnce;)Lscala/collection/mutable/AnyRefMap;
  #52 = Methodref          #46.#51        // scala/collection/mutable/AnyRefMap$.from:(Lscala/collection/IterableOnce;)Lscala/collection/mutable/AnyRefMap;
  #53 = Utf8               Lscala/collection/IterableOnce;
  #54 = Utf8               newBuilder
  #55 = Utf8               (Ljava/lang/Object;)Lscala/collection/mutable/ReusableBuilder;
  #56 = Utf8               (Ljava/lang/Object;)Lscala/collection/mutable/ReusableBuilder<Lscala/Tuple2<Ljava/lang/Object;Ljava/lang/Object;>;Lscala/collection/mutable/AnyRefMap<Ljava/lang/Object;Ljava/lang/Object;>;>;
  #57 = Methodref          #10.#20        // scala/collection/mutable/AnyRefMap$AnyRefMapBuilder."<init>":()V
  #58 = NameAndType        #54:#55        // newBuilder:(Ljava/lang/Object;)Lscala/collection/mutable/ReusableBuilder;
  #59 = Methodref          #2.#58         // scala/collection/mutable/AnyRefMap$ToBuildFrom$.newBuilder:(Ljava/lang/Object;)Lscala/collection/mutable/ReusableBuilder;
  #60 = Utf8               (Ljava/lang/Object;Lscala/collection/IterableOnce;)Ljava/lang/Object;
  #61 = NameAndType        #41:#42        // fromSpecific:(Ljava/lang/Object;Lscala/collection/IterableOnce;)Lscala/collection/mutable/AnyRefMap;
  #62 = Methodref          #2.#61         // scala/collection/mutable/AnyRefMap$ToBuildFrom$.fromSpecific:(Ljava/lang/Object;Lscala/collection/IterableOnce;)Lscala/collection/mutable/AnyRefMap;
  #63 = Methodref          #5.#20         // java/lang/Object."<init>":()V
  #64 = Utf8               Code
  #65 = Utf8               LineNumberTable
  #66 = Utf8               LocalVariableTable
  #67 = Utf8               Signature
  #68 = Utf8               Deprecated
  #69 = Utf8               MethodParameters
  #70 = Utf8               InnerClasses
  #71 = Utf8               SourceFile
  #72 = Utf8               ScalaInlineInfo
  #73 = Utf8               Scala
{
  public static final scala.collection.mutable.AnyRefMap$ToBuildFrom$ MODULE$;
    descriptor: Lscala/collection/mutable/AnyRefMap$ToBuildFrom$;
    flags: (0x0019) ACC_PUBLIC, ACC_STATIC, ACC_FINAL

  public static {};
    descriptor: ()V
    flags: (0x0009) ACC_PUBLIC, ACC_STATIC
    Code:
      stack=2, locals=0, args_size=0
         0: new           #2                  // class scala/collection/mutable/AnyRefMap$ToBuildFrom$
         3: dup
         4: invokespecial #21                 // Method "<init>":()V
         7: putstatic     #23                 // Field MODULE$:Lscala/collection/mutable/AnyRefMap$ToBuildFrom$;
        10: getstatic     #23                 // Field MODULE$:Lscala/collection/mutable/AnyRefMap$ToBuildFrom$;
        13: pop
        14: return
      LineNumberTable:
        line 594: 0

  public scala.collection.mutable.Builder<scala.Tuple2<java.lang.Object, java.lang.Object>, scala.collection.mutable.AnyRefMap<java.lang.Object, java.lang.Object>> apply(java.lang.Object);
    descriptor: (Ljava/lang/Object;)Lscala/collection/mutable/Builder;
    flags: (0x0001) ACC_PUBLIC
    Code:
      stack=2, locals=2, args_size=2
         0: aload_0
         1: aload_1
         2: invokestatic  #31                 // InterfaceMethod scala/collection/BuildFrom.apply$:(Lscala/collection/BuildFrom;Ljava/lang/Object;)Lscala/collection/mutable/Builder;
         5: areturn
      LineNumberTable:
        line 594: 0
      LocalVariableTable:
        Start  Length  Slot  Name   Signature
            0       6     0  this   Lscala/collection/mutable/AnyRefMap$ToBuildFrom$;
            0       6     1  from   Ljava/lang/Object;
    Signature: #26                          // (Ljava/lang/Object;)Lscala/collection/mutable/Builder<Lscala/Tuple2<Ljava/lang/Object;Ljava/lang/Object;>;Lscala/collection/mutable/AnyRefMap<Ljava/lang/Object;Ljava/lang/Object;>;>;
    Deprecated: true
    MethodParameters:
      Name                           Flags
      from                           final

  public scala.collection.Factory<scala.Tuple2<java.lang.Object, java.lang.Object>, scala.collection.mutable.AnyRefMap<java.lang.Object, java.lang.Object>> toFactory(java.lang.Object);
    descriptor: (Ljava/lang/Object;)Lscala/collection/Factory;
    flags: (0x0001) ACC_PUBLIC
    Code:
      stack=2, locals=2, args_size=2
         0: aload_0
         1: aload_1
         2: invokestatic  #40                 // InterfaceMethod scala/collection/BuildFrom.toFactory$:(Lscala/collection/BuildFrom;Ljava/lang/Object;)Lscala/collection/Factory;
         5: areturn
      LineNumberTable:
        line 594: 0
      LocalVariableTable:
        Start  Length  Slot  Name   Signature
            0       6     0  this   Lscala/collection/mutable/AnyRefMap$ToBuildFrom$;
            0       6     1  from   Ljava/lang/Object;
    Signature: #36                          // (Ljava/lang/Object;)Lscala/collection/Factory<Lscala/Tuple2<Ljava/lang/Object;Ljava/lang/Object;>;Lscala/collection/mutable/AnyRefMap<Ljava/lang/Object;Ljava/lang/Object;>;>;
    MethodParameters:
      Name                           Flags
      from                           final

  public scala.collection.mutable.AnyRefMap<java.lang.Object, java.lang.Object> fromSpecific(java.lang.Object, scala.collection.IterableOnce<scala.Tuple2<java.lang.Object, java.lang.Object>>);
    descriptor: (Ljava/lang/Object;Lscala/collection/IterableOnce;)Lscala/collection/mutable/AnyRefMap;
    flags: (0x0001) ACC_PUBLIC
    Code:
      stack=2, locals=3, args_size=3
         0: getstatic     #49                 // Field scala/collection/mutable/AnyRefMap$.MODULE$:Lscala/collection/mutable/AnyRefMap$;
         3: aload_2
         4: invokevirtual #52                 // Method scala/collection/mutable/AnyRefMap$.from:(Lscala/collection/IterableOnce;)Lscala/collection/mutable/AnyRefMap;
         7: areturn
      LineNumberTable:
        line 595: 0
      LocalVariableTable:
        Start  Length  Slot  Name   Signature
            0       8     0  this   Lscala/collection/mutable/AnyRefMap$ToBuildFrom$;
            0       8     1  from   Ljava/lang/Object;
            0       8     2    it   Lscala/collection/IterableOnce;
    Signature: #43                          // (Ljava/lang/Object;Lscala/collection/IterableOnce<Lscala/Tuple2<Ljava/lang/Object;Ljava/lang/Object;>;>;)Lscala/collection/mutable/AnyRefMap<Ljava/lang/Object;Ljava/lang/Object;>;
    MethodParameters:
      Name                           Flags
      from                           final
      it                             final

  public scala.collection.mutable.ReusableBuilder<scala.Tuple2<java.lang.Object, java.lang.Object>, scala.collection.mutable.AnyRefMap<java.lang.Object, java.lang.Object>> newBuilder(java.lang.Object);
    descriptor: (Ljava/lang/Object;)Lscala/collection/mutable/ReusableBuilder;
    flags: (0x0001) ACC_PUBLIC
    Code:
      stack=2, locals=2, args_size=2
         0: getstatic     #49                 // Field scala/collection/mutable/AnyRefMap$.MODULE$:Lscala/collection/mutable/AnyRefMap$;
         3: pop
         4: new           #10                 // class scala/collection/mutable/AnyRefMap$AnyRefMapBuilder
         7: dup
         8: invokespecial #57                 // Method scala/collection/mutable/AnyRefMap$AnyRefMapBuilder."<init>":()V
        11: areturn
      LineNumberTable:
        line 596: 0
        line 530: 4
        line 596: 11
      LocalVariableTable:
        Start  Length  Slot  Name   Signature
            0      12     0  this   Lscala/collection/mutable/AnyRefMap$ToBuildFrom$;
            0      12     1  from   Ljava/lang/Object;
    Signature: #56                          // (Ljava/lang/Object;)Lscala/collection/mutable/ReusableBuilder<Lscala/Tuple2<Ljava/lang/Object;Ljava/lang/Object;>;Lscala/collection/mutable/AnyRefMap<Ljava/lang/Object;Ljava/lang/Object;>;>;
    MethodParameters:
      Name                           Flags
      from                           final

  public scala.collection.mutable.Builder newBuilder(java.lang.Object);
    descriptor: (Ljava/lang/Object;)Lscala/collection/mutable/Builder;
    flags: (0x1041) ACC_PUBLIC, ACC_BRIDGE, ACC_SYNTHETIC
    Code:
      stack=2, locals=2, args_size=2
         0: aload_0
         1: aload_1
         2: invokevirtual #59                 // Method newBuilder:(Ljava/lang/Object;)Lscala/collection/mutable/ReusableBuilder;
         5: areturn
      LineNumberTable:
        line 594: 0
      LocalVariableTable:
        Start  Length  Slot  Name   Signature
            0       6     0  this   Lscala/collection/mutable/AnyRefMap$ToBuildFrom$;
            0       6     1  from   Ljava/lang/Object;
    MethodParameters:
      Name                           Flags
      from                           final

  public java.lang.Object fromSpecific(java.lang.Object, scala.collection.IterableOnce);
    descriptor: (Ljava/lang/Object;Lscala/collection/IterableOnce;)Ljava/lang/Object;
    flags: (0x1041) ACC_PUBLIC, ACC_BRIDGE, ACC_SYNTHETIC
    Code:
      stack=3, locals=3, args_size=3
         0: aload_0
         1: aload_1
         2: aload_2
         3: invokevirtual #62                 // Method fromSpecific:(Ljava/lang/Object;Lscala/collection/IterableOnce;)Lscala/collection/mutable/AnyRefMap;
         6: areturn
      LineNumberTable:
        line 594: 0
      LocalVariableTable:
        Start  Length  Slot  Name   Signature
            0       7     0  this   Lscala/collection/mutable/AnyRefMap$ToBuildFrom$;
            0       7     1  from   Ljava/lang/Object;
            0       7     2    it   Lscala/collection/IterableOnce;
    MethodParameters:
      Name                           Flags
      from                           final
      it                             final

  public scala.collection.mutable.AnyRefMap$ToBuildFrom$();
    descriptor: ()V
    flags: (0x0001) ACC_PUBLIC
    Code:
      stack=1, locals=1, args_size=1
         0: aload_0
         1: invokespecial #63                 // Method java/lang/Object."<init>":()V
         4: return
      LineNumberTable:
        line 594: 0
      LocalVariableTable:
        Start  Length  Slot  Name   Signature
            0       5     0  this   Lscala/collection/mutable/AnyRefMap$ToBuildFrom$;
}
InnerClasses:
  public static final #13= #10 of #12;    // AnyRefMapBuilder=class scala/collection/mutable/AnyRefMap$AnyRefMapBuilder of class scala/collection/mutable/AnyRefMap
  private static #14= #2 of #12;          // ToBuildFrom$=class scala/collection/mutable/AnyRefMap$ToBuildFrom$ of class scala/collection/mutable/AnyRefMap
Signature: #3                           // Ljava/lang/Object;Lscala/collection/BuildFrom<Ljava/lang/Object;Lscala/Tuple2<Ljava/lang/Object;Ljava/lang/Object;>;Lscala/collection/mutable/AnyRefMap<Ljava/lang/Object;Ljava/lang/Object;>;>;
SourceFile: "AnyRefMap.scala"
  ScalaInlineInfo: length = 0x27 (unknown attribute)
   01 01 00 07 00 13 00 12 01 00 18 00 19 05 00 29
   00 3C 01 00 29 00 2A 01 00 36 00 19 01 00 36 00
   37 01 00 22 00 23 01
  Scala: length = 0x0 (unknown attribute)

