Classfile /Users/mw/Projects/slang-braindump/.jar/jar11/assemble/slang-braindump/assemble/content/scala/collection/mutable/ArraySeq$ofUnit.class
  Last modified May 29, 2022; size 3485 bytes
  SHA-256 checksum 51ffb62e20165b7d5066fda63512e726cfcd7b28623df7026c86c476d942c6f6
  Compiled from "ArraySeq.scala"
public final class scala.collection.mutable.ArraySeq$ofUnit extends scala.collection.mutable.ArraySeq<scala.runtime.BoxedUnit>
  minor version: 0
  major version: 52
  flags: (0x0031) ACC_PUBLIC, ACC_FINAL, ACC_SUPER
  this_class: #2                          // scala/collection/mutable/ArraySeq$ofUnit
  super_class: #5                         // scala/collection/mutable/ArraySeq
  interfaces: 0, fields: 2, methods: 16, attributes: 5
Constant pool:
    #1 = Utf8               scala/collection/mutable/ArraySeq$ofUnit
    #2 = Class              #1            // scala/collection/mutable/ArraySeq$ofUnit
    #3 = Utf8               Lscala/collection/mutable/ArraySeq<Lscala/runtime/BoxedUnit;>;
    #4 = Utf8               scala/collection/mutable/ArraySeq
    #5 = Class              #4            // scala/collection/mutable/ArraySeq
    #6 = Utf8               ArraySeq.scala
    #7 = Utf8               ofUnit
    #8 = Utf8               scala/reflect/ManifestFactory$UnitManifest
    #9 = Class              #8            // scala/reflect/ManifestFactory$UnitManifest
   #10 = Utf8               scala/reflect/ManifestFactory
   #11 = Class              #10           // scala/reflect/ManifestFactory
   #12 = Utf8               UnitManifest
   #13 = Utf8               serialVersionUID
   #14 = Utf8               J
   #15 = Long               3l
   #17 = Utf8               array
   #18 = Utf8               [Lscala/runtime/BoxedUnit;
   #19 = Utf8               ()[Lscala/runtime/BoxedUnit;
   #20 = NameAndType        #17:#18       // array:[Lscala/runtime/BoxedUnit;
   #21 = Fieldref           #2.#20        // scala/collection/mutable/ArraySeq$ofUnit.array:[Lscala/runtime/BoxedUnit;
   #22 = Utf8               this
   #23 = Utf8               Lscala/collection/mutable/ArraySeq$ofUnit;
   #24 = Utf8               elemTag
   #25 = Utf8               ()Lscala/reflect/ManifestFactory$UnitManifest;
   #26 = Utf8               scala/reflect/ClassTag$
   #27 = Class              #26           // scala/reflect/ClassTag$
   #28 = Utf8               MODULE$
   #29 = Utf8               Lscala/reflect/ClassTag$;
   #30 = NameAndType        #28:#29       // MODULE$:Lscala/reflect/ClassTag$;
   #31 = Fieldref           #27.#30       // scala/reflect/ClassTag$.MODULE$:Lscala/reflect/ClassTag$;
   #32 = Utf8               Unit
   #33 = NameAndType        #32:#25       // Unit:()Lscala/reflect/ManifestFactory$UnitManifest;
   #34 = Methodref          #27.#33       // scala/reflect/ClassTag$.Unit:()Lscala/reflect/ManifestFactory$UnitManifest;
   #35 = Utf8               length
   #36 = Utf8               ()I
   #37 = NameAndType        #17:#19       // array:()[Lscala/runtime/BoxedUnit;
   #38 = Methodref          #2.#37        // scala/collection/mutable/ArraySeq$ofUnit.array:()[Lscala/runtime/BoxedUnit;
   #39 = Utf8               apply
   #40 = Utf8               (I)V
   #41 = Utf8               index
   #42 = Utf8               I
   #43 = Utf8               update
   #44 = Utf8               (ILscala/runtime/BoxedUnit;)V
   #45 = Utf8               elem
   #46 = Utf8               Lscala/runtime/BoxedUnit;
   #47 = Utf8               hashCode
   #48 = Utf8               scala/util/hashing/MurmurHash3$
   #49 = Class              #48           // scala/util/hashing/MurmurHash3$
   #50 = Utf8               Lscala/util/hashing/MurmurHash3$;
   #51 = NameAndType        #28:#50       // MODULE$:Lscala/util/hashing/MurmurHash3$;
   #52 = Fieldref           #49.#51       // scala/util/hashing/MurmurHash3$.MODULE$:Lscala/util/hashing/MurmurHash3$;
   #53 = Utf8               arraySeqHash$mVc$sp
   #54 = Utf8               ([Lscala/runtime/BoxedUnit;)I
   #55 = NameAndType        #53:#54       // arraySeqHash$mVc$sp:([Lscala/runtime/BoxedUnit;)I
   #56 = Methodref          #49.#55       // scala/util/hashing/MurmurHash3$.arraySeqHash$mVc$sp:([Lscala/runtime/BoxedUnit;)I
   #57 = Utf8               equals
   #58 = Utf8               (Ljava/lang/Object;)Z
   #59 = Utf8               that
   #60 = NameAndType        #57:#58       // equals:(Ljava/lang/Object;)Z
   #61 = Methodref          #5.#60        // scala/collection/mutable/ArraySeq.equals:(Ljava/lang/Object;)Z
   #62 = Utf8               Ljava/lang/Object;
   #63 = Utf8               iterator
   #64 = Utf8               ()Lscala/collection/Iterator;
   #65 = Utf8               ()Lscala/collection/Iterator<Lscala/runtime/BoxedUnit;>;
   #66 = Utf8               scala/collection/ArrayOps$ArrayIterator$mcV$sp
   #67 = Class              #66           // scala/collection/ArrayOps$ArrayIterator$mcV$sp
   #68 = Utf8               <init>
   #69 = Utf8               ([Lscala/runtime/BoxedUnit;)V
   #70 = NameAndType        #68:#69       // "<init>":([Lscala/runtime/BoxedUnit;)V
   #71 = Methodref          #67.#70       // scala/collection/ArrayOps$ArrayIterator$mcV$sp."<init>":([Lscala/runtime/BoxedUnit;)V
   #72 = Utf8               stepper
   #73 = Utf8               (Lscala/collection/StepperShape;)Lscala/collection/Stepper;
   #74 = Utf8               <S::Lscala/collection/Stepper<*>;>(Lscala/collection/StepperShape<Lscala/runtime/BoxedUnit;TS;>;)TS;
   #75 = Utf8               shape
   #76 = Utf8               scala/collection/convert/impl/ObjectArrayStepper
   #77 = Class              #76           // scala/collection/convert/impl/ObjectArrayStepper
   #78 = Utf8               ([Ljava/lang/Object;II)V
   #79 = NameAndType        #68:#78       // "<init>":([Ljava/lang/Object;II)V
   #80 = Methodref          #77.#79       // scala/collection/convert/impl/ObjectArrayStepper."<init>":([Ljava/lang/Object;II)V
   #81 = Utf8               Lscala/collection/StepperShape;
   #82 = Utf8               apply$mcVI$sp
   #83 = Utf8               (ILjava/lang/Object;)V
   #84 = Utf8               scala/runtime/BoxedUnit
   #85 = Class              #84           // scala/runtime/BoxedUnit
   #86 = NameAndType        #43:#44       // update:(ILscala/runtime/BoxedUnit;)V
   #87 = Methodref          #2.#86        // scala/collection/mutable/ArraySeq$ofUnit.update:(ILscala/runtime/BoxedUnit;)V
   #88 = Utf8               (Ljava/lang/Object;)Ljava/lang/Object;
   #89 = Utf8               v1
   #90 = Utf8               scala/runtime/BoxesRunTime
   #91 = Class              #90           // scala/runtime/BoxesRunTime
   #92 = Utf8               unboxToInt
   #93 = Utf8               (Ljava/lang/Object;)I
   #94 = NameAndType        #92:#93       // unboxToInt:(Ljava/lang/Object;)I
   #95 = Methodref          #91.#94       // scala/runtime/BoxesRunTime.unboxToInt:(Ljava/lang/Object;)I
   #96 = NameAndType        #39:#40       // apply:(I)V
   #97 = Methodref          #2.#96        // scala/collection/mutable/ArraySeq$ofUnit.apply:(I)V
   #98 = Utf8               UNIT
   #99 = NameAndType        #98:#46       // UNIT:Lscala/runtime/BoxedUnit;
  #100 = Fieldref           #85.#99       // scala/runtime/BoxedUnit.UNIT:Lscala/runtime/BoxedUnit;
  #101 = Utf8               (I)Ljava/lang/Object;
  #102 = Utf8               i
  #103 = Utf8               ()Lscala/reflect/ClassTag;
  #104 = NameAndType        #24:#25       // elemTag:()Lscala/reflect/ManifestFactory$UnitManifest;
  #105 = Methodref          #2.#104       // scala/collection/mutable/ArraySeq$ofUnit.elemTag:()Lscala/reflect/ManifestFactory$UnitManifest;
  #106 = Utf8               ()Ljava/lang/Object;
  #107 = Utf8               ()V
  #108 = NameAndType        #68:#107      // "<init>":()V
  #109 = Methodref          #5.#108       // scala/collection/mutable/ArraySeq."<init>":()V
  #110 = Utf8               ConstantValue
  #111 = Utf8               Code
  #112 = Utf8               LineNumberTable
  #113 = Utf8               LocalVariableTable
  #114 = Utf8               MethodParameters
  #115 = Utf8               StackMapTable
  #116 = Utf8               Signature
  #117 = Utf8               InnerClasses
  #118 = Utf8               SourceFile
  #119 = Utf8               ScalaInlineInfo
  #120 = Utf8               Scala
{
  private static final long serialVersionUID;
    descriptor: J
    flags: (0x001a) ACC_PRIVATE, ACC_STATIC, ACC_FINAL
    ConstantValue: long 3l

  private final scala.runtime.BoxedUnit[] array;
    descriptor: [Lscala/runtime/BoxedUnit;
    flags: (0x0012) ACC_PRIVATE, ACC_FINAL

  public scala.runtime.BoxedUnit[] array();
    descriptor: ()[Lscala/runtime/BoxedUnit;
    flags: (0x0001) ACC_PUBLIC
    Code:
      stack=1, locals=1, args_size=1
         0: aload_0
         1: getfield      #21                 // Field array:[Lscala/runtime/BoxedUnit;
         4: areturn
      LineNumberTable:
        line 333: 0
      LocalVariableTable:
        Start  Length  Slot  Name   Signature
            0       5     0  this   Lscala/collection/mutable/ArraySeq$ofUnit;

  public scala.reflect.ManifestFactory$UnitManifest elemTag();
    descriptor: ()Lscala/reflect/ManifestFactory$UnitManifest;
    flags: (0x0001) ACC_PUBLIC
    Code:
      stack=1, locals=1, args_size=1
         0: getstatic     #31                 // Field scala/reflect/ClassTag$.MODULE$:Lscala/reflect/ClassTag$;
         3: invokevirtual #34                 // Method scala/reflect/ClassTag$.Unit:()Lscala/reflect/ManifestFactory$UnitManifest;
         6: areturn
      LineNumberTable:
        line 334: 0
      LocalVariableTable:
        Start  Length  Slot  Name   Signature
            0       7     0  this   Lscala/collection/mutable/ArraySeq$ofUnit;

  public int length();
    descriptor: ()I
    flags: (0x0001) ACC_PUBLIC
    Code:
      stack=1, locals=1, args_size=1
         0: aload_0
         1: invokevirtual #38                 // Method array:()[Lscala/runtime/BoxedUnit;
         4: arraylength
         5: ireturn
      LineNumberTable:
        line 335: 0
      LocalVariableTable:
        Start  Length  Slot  Name   Signature
            0       6     0  this   Lscala/collection/mutable/ArraySeq$ofUnit;

  public void apply(int);
    descriptor: (I)V
    flags: (0x0001) ACC_PUBLIC
    Code:
      stack=2, locals=2, args_size=2
         0: aload_0
         1: invokevirtual #38                 // Method array:()[Lscala/runtime/BoxedUnit;
         4: iload_1
         5: aaload
         6: pop
         7: return
      LineNumberTable:
        line 336: 0
        line 336: 7
      LocalVariableTable:
        Start  Length  Slot  Name   Signature
            0       8     0  this   Lscala/collection/mutable/ArraySeq$ofUnit;
            0       8     1 index   I
    MethodParameters:
      Name                           Flags
      index                          final

  public void update(int, scala.runtime.BoxedUnit);
    descriptor: (ILscala/runtime/BoxedUnit;)V
    flags: (0x0001) ACC_PUBLIC
    Code:
      stack=3, locals=3, args_size=3
         0: aload_0
         1: invokevirtual #38                 // Method array:()[Lscala/runtime/BoxedUnit;
         4: iload_1
         5: aload_2
         6: aastore
         7: return
      LineNumberTable:
        line 337: 0
      LocalVariableTable:
        Start  Length  Slot  Name   Signature
            0       8     0  this   Lscala/collection/mutable/ArraySeq$ofUnit;
            0       8     1 index   I
            0       8     2  elem   Lscala/runtime/BoxedUnit;
    MethodParameters:
      Name                           Flags
      index                          final
      elem                           final

  public int hashCode();
    descriptor: ()I
    flags: (0x0001) ACC_PUBLIC
    Code:
      stack=2, locals=1, args_size=1
         0: getstatic     #52                 // Field scala/util/hashing/MurmurHash3$.MODULE$:Lscala/util/hashing/MurmurHash3$;
         3: aload_0
         4: invokevirtual #38                 // Method array:()[Lscala/runtime/BoxedUnit;
         7: invokevirtual #56                 // Method scala/util/hashing/MurmurHash3$.arraySeqHash$mVc$sp:([Lscala/runtime/BoxedUnit;)I
        10: ireturn
      LineNumberTable:
        line 338: 0
      LocalVariableTable:
        Start  Length  Slot  Name   Signature
            0      11     0  this   Lscala/collection/mutable/ArraySeq$ofUnit;

  public boolean equals(java.lang.Object);
    descriptor: (Ljava/lang/Object;)Z
    flags: (0x0001) ACC_PUBLIC
    Code:
      stack=2, locals=4, args_size=2
         0: aload_1
         1: instanceof    #2                  // class scala/collection/mutable/ArraySeq$ofUnit
         4: ifeq          34
         7: aload_1
         8: checkcast     #2                  // class scala/collection/mutable/ArraySeq$ofUnit
        11: astore_3
        12: aload_0
        13: invokevirtual #38                 // Method array:()[Lscala/runtime/BoxedUnit;
        16: arraylength
        17: aload_3
        18: invokevirtual #38                 // Method array:()[Lscala/runtime/BoxedUnit;
        21: arraylength
        22: if_icmpne     29
        25: iconst_1
        26: goto          30
        29: iconst_0
        30: istore_2
        31: goto          40
        34: aload_0
        35: aload_1
        36: invokespecial #61                 // Method scala/collection/mutable/ArraySeq.equals:(Ljava/lang/Object;)Z
        39: istore_2
        40: iload_2
        41: ireturn
      StackMapTable: number_of_entries = 4
        frame_type = 253 /* append */
          offset_delta = 29
          locals = [ top, class scala/collection/mutable/ArraySeq$ofUnit ]
        frame_type = 64 /* same_locals_1_stack_item */
          stack = [ int ]
        frame_type = 249 /* chop */
          offset_delta = 3
        frame_type = 252 /* append */
          offset_delta = 5
          locals = [ int ]
      LineNumberTable:
        line 340: 0
        line 341: 34
        line 339: 40
      LocalVariableTable:
        Start  Length  Slot  Name   Signature
            0      42     0  this   Lscala/collection/mutable/ArraySeq$ofUnit;
            0      42     1  that   Ljava/lang/Object;
    MethodParameters:
      Name                           Flags
      that                           final

  public scala.collection.Iterator<scala.runtime.BoxedUnit> iterator();
    descriptor: ()Lscala/collection/Iterator;
    flags: (0x0001) ACC_PUBLIC
    Code:
      stack=3, locals=1, args_size=1
         0: new           #67                 // class scala/collection/ArrayOps$ArrayIterator$mcV$sp
         3: dup
         4: aload_0
         5: invokevirtual #38                 // Method array:()[Lscala/runtime/BoxedUnit;
         8: invokespecial #71                 // Method scala/collection/ArrayOps$ArrayIterator$mcV$sp."<init>":([Lscala/runtime/BoxedUnit;)V
        11: areturn
      LineNumberTable:
        line 343: 0
      LocalVariableTable:
        Start  Length  Slot  Name   Signature
            0      12     0  this   Lscala/collection/mutable/ArraySeq$ofUnit;
    Signature: #65                          // ()Lscala/collection/Iterator<Lscala/runtime/BoxedUnit;>;

  public <S extends scala.collection.Stepper<?>> S stepper(scala.collection.StepperShape<scala.runtime.BoxedUnit, S>);
    descriptor: (Lscala/collection/StepperShape;)Lscala/collection/Stepper;
    flags: (0x0001) ACC_PUBLIC
    Code:
      stack=5, locals=2, args_size=2
         0: new           #77                 // class scala/collection/convert/impl/ObjectArrayStepper
         3: dup
         4: aload_0
         5: invokevirtual #38                 // Method array:()[Lscala/runtime/BoxedUnit;
         8: iconst_0
         9: aload_0
        10: invokevirtual #38                 // Method array:()[Lscala/runtime/BoxedUnit;
        13: arraylength
        14: invokespecial #80                 // Method scala/collection/convert/impl/ObjectArrayStepper."<init>":([Ljava/lang/Object;II)V
        17: areturn
      LineNumberTable:
        line 345: 0
      LocalVariableTable:
        Start  Length  Slot  Name   Signature
            0      18     0  this   Lscala/collection/mutable/ArraySeq$ofUnit;
            0      18     1 shape   Lscala/collection/StepperShape;
    Signature: #74                          // <S::Lscala/collection/Stepper<*>;>(Lscala/collection/StepperShape<Lscala/runtime/BoxedUnit;TS;>;)TS;
    MethodParameters:
      Name                           Flags
      shape                          final

  public void apply$mcVI$sp(int);
    descriptor: (I)V
    flags: (0x0001) ACC_PUBLIC
    Code:
      stack=2, locals=2, args_size=2
         0: aload_0
         1: invokevirtual #38                 // Method array:()[Lscala/runtime/BoxedUnit;
         4: iload_1
         5: aaload
         6: pop
         7: return
      LineNumberTable:
        line 336: 0
      LocalVariableTable:
        Start  Length  Slot  Name   Signature
            0       8     0  this   Lscala/collection/mutable/ArraySeq$ofUnit;
            0       8     1 index   I
    MethodParameters:
      Name                           Flags
      index                          final

  public void update(int, java.lang.Object);
    descriptor: (ILjava/lang/Object;)V
    flags: (0x1041) ACC_PUBLIC, ACC_BRIDGE, ACC_SYNTHETIC
    Code:
      stack=3, locals=3, args_size=3
         0: aload_0
         1: iload_1
         2: aload_2
         3: checkcast     #85                 // class scala/runtime/BoxedUnit
         6: invokevirtual #87                 // Method update:(ILscala/runtime/BoxedUnit;)V
         9: return
      LineNumberTable:
        line 333: 0
      LocalVariableTable:
        Start  Length  Slot  Name   Signature
            0      10     0  this   Lscala/collection/mutable/ArraySeq$ofUnit;
            0      10     1 index   I
            0      10     2  elem   Ljava/lang/Object;
    MethodParameters:
      Name                           Flags
      index                          final
      elem                           final

  public java.lang.Object apply(java.lang.Object);
    descriptor: (Ljava/lang/Object;)Ljava/lang/Object;
    flags: (0x1041) ACC_PUBLIC, ACC_BRIDGE, ACC_SYNTHETIC
    Code:
      stack=2, locals=2, args_size=2
         0: aload_0
         1: aload_1
         2: invokestatic  #95                 // Method scala/runtime/BoxesRunTime.unboxToInt:(Ljava/lang/Object;)I
         5: invokevirtual #97                 // Method apply:(I)V
         8: getstatic     #100                // Field scala/runtime/BoxedUnit.UNIT:Lscala/runtime/BoxedUnit;
        11: areturn
      LineNumberTable:
        line 333: 0
      LocalVariableTable:
        Start  Length  Slot  Name   Signature
            0      12     0  this   Lscala/collection/mutable/ArraySeq$ofUnit;
            0      12     1    v1   Ljava/lang/Object;
    MethodParameters:
      Name                           Flags
      v1                             final

  public java.lang.Object apply(int);
    descriptor: (I)Ljava/lang/Object;
    flags: (0x1041) ACC_PUBLIC, ACC_BRIDGE, ACC_SYNTHETIC
    Code:
      stack=2, locals=2, args_size=2
         0: aload_0
         1: iload_1
         2: invokevirtual #97                 // Method apply:(I)V
         5: getstatic     #100                // Field scala/runtime/BoxedUnit.UNIT:Lscala/runtime/BoxedUnit;
         8: areturn
      LineNumberTable:
        line 333: 0
      LocalVariableTable:
        Start  Length  Slot  Name   Signature
            0       9     0  this   Lscala/collection/mutable/ArraySeq$ofUnit;
            0       9     1     i   I
    MethodParameters:
      Name                           Flags
      i                              final

  public scala.reflect.ClassTag elemTag();
    descriptor: ()Lscala/reflect/ClassTag;
    flags: (0x1041) ACC_PUBLIC, ACC_BRIDGE, ACC_SYNTHETIC
    Code:
      stack=1, locals=1, args_size=1
         0: aload_0
         1: invokevirtual #105                // Method elemTag:()Lscala/reflect/ManifestFactory$UnitManifest;
         4: areturn
      LineNumberTable:
        line 333: 0
      LocalVariableTable:
        Start  Length  Slot  Name   Signature
            0       5     0  this   Lscala/collection/mutable/ArraySeq$ofUnit;

  public java.lang.Object array();
    descriptor: ()Ljava/lang/Object;
    flags: (0x1041) ACC_PUBLIC, ACC_BRIDGE, ACC_SYNTHETIC
    Code:
      stack=1, locals=1, args_size=1
         0: aload_0
         1: invokevirtual #38                 // Method array:()[Lscala/runtime/BoxedUnit;
         4: areturn
      LineNumberTable:
        line 333: 0
      LocalVariableTable:
        Start  Length  Slot  Name   Signature
            0       5     0  this   Lscala/collection/mutable/ArraySeq$ofUnit;

  public scala.collection.mutable.ArraySeq$ofUnit(scala.runtime.BoxedUnit[]);
    descriptor: ([Lscala/runtime/BoxedUnit;)V
    flags: (0x0001) ACC_PUBLIC
    Code:
      stack=2, locals=2, args_size=2
         0: aload_0
         1: aload_1
         2: putfield      #21                 // Field array:[Lscala/runtime/BoxedUnit;
         5: aload_0
         6: invokespecial #109                // Method scala/collection/mutable/ArraySeq."<init>":()V
         9: return
      LineNumberTable:
        line 333: 0
      LocalVariableTable:
        Start  Length  Slot  Name   Signature
            0      10     0  this   Lscala/collection/mutable/ArraySeq$ofUnit;
            0      10     1 array   [Lscala/runtime/BoxedUnit;
    MethodParameters:
      Name                           Flags
      array                          final
}
InnerClasses:
  public static final #7= #2 of #5;       // ofUnit=class scala/collection/mutable/ArraySeq$ofUnit of class scala/collection/mutable/ArraySeq
  public static final #12= #9 of #11;     // UnitManifest=class scala/reflect/ManifestFactory$UnitManifest of class scala/reflect/ManifestFactory
Signature: #3                           // Lscala/collection/mutable/ArraySeq<Lscala/runtime/BoxedUnit;>;
SourceFile: "ArraySeq.scala"
  ScalaInlineInfo: length = 0x54 (unknown attribute)
   01 01 00 10 00 44 00 45 01 00 27 00 65 01 00 27
   00 28 01 00 27 00 58 01 00 52 00 28 01 00 11 00
   6A 01 00 11 00 13 01 00 18 00 67 01 00 18 00 19
   01 00 39 00 3A 01 00 2F 00 24 01 00 3F 00 40 01
   00 23 00 24 01 00 48 00 49 01 00 2B 00 53 01 00
   2B 00 2C 01
  Scala: length = 0x0 (unknown attribute)

