Classfile /Users/mw/Projects/slang-braindump/.jar/jar11/assemble/slang-braindump/assemble/content/scala/collection/mutable/ArrayDeque$$anon$1.class
  Last modified May 29, 2022; size 1095 bytes
  SHA-256 checksum 3f075e18603fa33c25e49f73f86cf3c1c00df88c3e4585af107934b238b360aa
  Compiled from "ArrayDeque.scala"
public final class scala.collection.mutable.ArrayDeque$$anon$1 extends scala.collection.mutable.GrowableBuilder<A, scala.collection.mutable.ArrayDeque<A>>
  minor version: 0
  major version: 52
  flags: (0x0031) ACC_PUBLIC, ACC_FINAL, ACC_SUPER
  this_class: #2                          // scala/collection/mutable/ArrayDeque$$anon$1
  super_class: #5                         // scala/collection/mutable/GrowableBuilder
  interfaces: 0, fields: 0, methods: 2, attributes: 6
Constant pool:
   #1 = Utf8               scala/collection/mutable/ArrayDeque$$anon$1
   #2 = Class              #1             // scala/collection/mutable/ArrayDeque$$anon$1
   #3 = Utf8               Lscala/collection/mutable/GrowableBuilder<TA;Lscala/collection/mutable/ArrayDeque<TA;>;>;
   #4 = Utf8               scala/collection/mutable/GrowableBuilder
   #5 = Class              #4             // scala/collection/mutable/GrowableBuilder
   #6 = Utf8               ArrayDeque.scala
   #7 = Utf8               scala/collection/mutable/ArrayDeque$
   #8 = Class              #7             // scala/collection/mutable/ArrayDeque$
   #9 = Utf8               newBuilder
  #10 = Utf8               ()Lscala/collection/mutable/Builder;
  #11 = NameAndType        #9:#10         // newBuilder:()Lscala/collection/mutable/Builder;
  #12 = Utf8               sizeHint
  #13 = Utf8               (I)V
  #14 = Utf8               size
  #15 = Utf8               elems
  #16 = Utf8               ()Lscala/collection/mutable/Growable;
  #17 = NameAndType        #15:#16        // elems:()Lscala/collection/mutable/Growable;
  #18 = Methodref          #2.#17         // scala/collection/mutable/ArrayDeque$$anon$1.elems:()Lscala/collection/mutable/Growable;
  #19 = Utf8               scala/collection/mutable/ArrayDeque
  #20 = Class              #19            // scala/collection/mutable/ArrayDeque
  #21 = Utf8               ensureSize
  #22 = NameAndType        #21:#13        // ensureSize:(I)V
  #23 = Methodref          #20.#22        // scala/collection/mutable/ArrayDeque.ensureSize:(I)V
  #24 = Utf8               this
  #25 = Utf8               Lscala/collection/mutable/ArrayDeque$$anon$1;
  #26 = Utf8               I
  #27 = Utf8               <init>
  #28 = Utf8               ()V
  #29 = Utf8               MODULE$
  #30 = Utf8               Lscala/collection/mutable/ArrayDeque$;
  #31 = NameAndType        #29:#30        // MODULE$:Lscala/collection/mutable/ArrayDeque$;
  #32 = Fieldref           #8.#31         // scala/collection/mutable/ArrayDeque$.MODULE$:Lscala/collection/mutable/ArrayDeque$;
  #33 = Utf8               empty
  #34 = Utf8               ()Lscala/collection/mutable/ArrayDeque;
  #35 = NameAndType        #33:#34        // empty:()Lscala/collection/mutable/ArrayDeque;
  #36 = Methodref          #8.#35         // scala/collection/mutable/ArrayDeque$.empty:()Lscala/collection/mutable/ArrayDeque;
  #37 = Utf8               (Lscala/collection/mutable/Growable;)V
  #38 = NameAndType        #27:#37        // "<init>":(Lscala/collection/mutable/Growable;)V
  #39 = Methodref          #5.#38         // scala/collection/mutable/GrowableBuilder."<init>":(Lscala/collection/mutable/Growable;)V
  #40 = Utf8               Code
  #41 = Utf8               LineNumberTable
  #42 = Utf8               LocalVariableTable
  #43 = Utf8               MethodParameters
  #44 = Utf8               InnerClasses
  #45 = Utf8               EnclosingMethod
  #46 = Utf8               Signature
  #47 = Utf8               SourceFile
  #48 = Utf8               ScalaInlineInfo
  #49 = Utf8               Scala
{
  public void sizeHint(int);
    descriptor: (I)V
    flags: (0x0001) ACC_PUBLIC
    Code:
      stack=2, locals=2, args_size=2
         0: aload_0
         1: invokevirtual #18                 // Method elems:()Lscala/collection/mutable/Growable;
         4: checkcast     #20                 // class scala/collection/mutable/ArrayDeque
         7: iload_1
         8: invokevirtual #23                 // Method scala/collection/mutable/ArrayDeque.ensureSize:(I)V
        11: return
      LineNumberTable:
        line 540: 0
      LocalVariableTable:
        Start  Length  Slot  Name   Signature
            0      12     0  this   Lscala/collection/mutable/ArrayDeque$$anon$1;
            0      12     1  size   I
    MethodParameters:
      Name                           Flags
      size                           final

  public scala.collection.mutable.ArrayDeque$$anon$1();
    descriptor: ()V
    flags: (0x0001) ACC_PUBLIC
    Code:
      stack=2, locals=1, args_size=1
         0: aload_0
         1: getstatic     #32                 // Field scala/collection/mutable/ArrayDeque$.MODULE$:Lscala/collection/mutable/ArrayDeque$;
         4: invokevirtual #36                 // Method scala/collection/mutable/ArrayDeque$.empty:()Lscala/collection/mutable/ArrayDeque;
         7: invokespecial #39                 // Method scala/collection/mutable/GrowableBuilder."<init>":(Lscala/collection/mutable/Growable;)V
        10: return
      LineNumberTable:
        line 538: 0
      LocalVariableTable:
        Start  Length  Slot  Name   Signature
            0      11     0  this   Lscala/collection/mutable/ArrayDeque$$anon$1;
}
InnerClasses:
  public final #2;                        // class scala/collection/mutable/ArrayDeque$$anon$1
EnclosingMethod: #8.#11                 // scala.collection.mutable.ArrayDeque$.newBuilder
Signature: #3                           // Lscala/collection/mutable/GrowableBuilder<TA;Lscala/collection/mutable/ArrayDeque<TA;>;>;
SourceFile: "ArrayDeque.scala"
  ScalaInlineInfo: length = 0xE (unknown attribute)
   01 01 00 02 00 1B 00 1C 01 00 0C 00 0D 01
  Scala: length = 0x0 (unknown attribute)

