Classfile /Users/mw/Projects/slang-braindump/.jar/jar11/assemble/slang-braindump/assemble/content/scala/collection/mutable/ArrayBuilder$ofFloat.class
  Last modified May 29, 2022; size 2505 bytes
  SHA-256 checksum 78c5a5e5d4aa8eeb27084335a5ee9cbf67dd251052f756b9e31475a76d241d6b
  Compiled from "ArrayBuilder.scala"
public final class scala.collection.mutable.ArrayBuilder$ofFloat extends scala.collection.mutable.ArrayBuilder<java.lang.Object>
  minor version: 0
  major version: 52
  flags: (0x0031) ACC_PUBLIC, ACC_FINAL, ACC_SUPER
  this_class: #2                          // scala/collection/mutable/ArrayBuilder$ofFloat
  super_class: #5                         // scala/collection/mutable/ArrayBuilder
  interfaces: 0, fields: 2, methods: 12, attributes: 5
Constant pool:
    #1 = Utf8               scala/collection/mutable/ArrayBuilder$ofFloat
    #2 = Class              #1            // scala/collection/mutable/ArrayBuilder$ofFloat
    #3 = Utf8               Lscala/collection/mutable/ArrayBuilder<Ljava/lang/Object;>;
    #4 = Utf8               scala/collection/mutable/ArrayBuilder
    #5 = Class              #4            // scala/collection/mutable/ArrayBuilder
    #6 = Utf8               ArrayBuilder.scala
    #7 = Utf8               ofFloat
    #8 = Utf8               serialVersionUID
    #9 = Utf8               J
   #10 = Long               3l
   #12 = Utf8               elems
   #13 = Utf8               [F
   #14 = Utf8               ()[F
   #15 = NameAndType        #12:#13       // elems:[F
   #16 = Fieldref           #2.#15        // scala/collection/mutable/ArrayBuilder$ofFloat.elems:[F
   #17 = Utf8               this
   #18 = Utf8               Lscala/collection/mutable/ArrayBuilder$ofFloat;
   #19 = Utf8               elems_$eq
   #20 = Utf8               ([F)V
   #21 = Utf8               x$1
   #22 = Utf8               mkArray
   #23 = Utf8               (I)[F
   #24 = Utf8               size
   #25 = Utf8               ()I
   #26 = NameAndType        #24:#25       // size:()I
   #27 = Methodref          #2.#26        // scala/collection/mutable/ArrayBuilder$ofFloat.size:()I
   #28 = Utf8               scala/Array$
   #29 = Class              #28           // scala/Array$
   #30 = Utf8               MODULE$
   #31 = Utf8               Lscala/Array$;
   #32 = NameAndType        #30:#31       // MODULE$:Lscala/Array$;
   #33 = Fieldref           #29.#32       // scala/Array$.MODULE$:Lscala/Array$;
   #34 = NameAndType        #12:#14       // elems:()[F
   #35 = Methodref          #2.#34        // scala/collection/mutable/ArrayBuilder$ofFloat.elems:()[F
   #36 = Utf8               copy
   #37 = Utf8               (Ljava/lang/Object;ILjava/lang/Object;II)V
   #38 = NameAndType        #36:#37       // copy:(Ljava/lang/Object;ILjava/lang/Object;II)V
   #39 = Methodref          #29.#38       // scala/Array$.copy:(Ljava/lang/Object;ILjava/lang/Object;II)V
   #40 = Utf8               newelems
   #41 = Utf8               I
   #42 = Class              #13           // "[F"
   #43 = Utf8               resize
   #44 = Utf8               (I)V
   #45 = NameAndType        #22:#23       // mkArray:(I)[F
   #46 = Methodref          #2.#45        // scala/collection/mutable/ArrayBuilder$ofFloat.mkArray:(I)[F
   #47 = NameAndType        #19:#20       // elems_$eq:([F)V
   #48 = Methodref          #2.#47        // scala/collection/mutable/ArrayBuilder$ofFloat.elems_$eq:([F)V
   #49 = Utf8               capacity_$eq
   #50 = NameAndType        #49:#44       // capacity_$eq:(I)V
   #51 = Methodref          #2.#50        // scala/collection/mutable/ArrayBuilder$ofFloat.capacity_$eq:(I)V
   #52 = Utf8               addOne
   #53 = Utf8               (F)Lscala/collection/mutable/ArrayBuilder$ofFloat;
   #54 = Utf8               elem
   #55 = Utf8               ensureSize
   #56 = NameAndType        #55:#44       // ensureSize:(I)V
   #57 = Methodref          #2.#56        // scala/collection/mutable/ArrayBuilder$ofFloat.ensureSize:(I)V
   #58 = Utf8               size_$eq
   #59 = NameAndType        #58:#44       // size_$eq:(I)V
   #60 = Methodref          #2.#59        // scala/collection/mutable/ArrayBuilder$ofFloat.size_$eq:(I)V
   #61 = Utf8               F
   #62 = Utf8               result
   #63 = Utf8               capacity
   #64 = NameAndType        #63:#25       // capacity:()I
   #65 = Methodref          #2.#64        // scala/collection/mutable/ArrayBuilder$ofFloat.capacity:()I
   #66 = Utf8               res
   #67 = Utf8               equals
   #68 = Utf8               (Ljava/lang/Object;)Z
   #69 = Utf8               other
   #70 = Utf8               Ljava/lang/Object;
   #71 = Utf8               toString
   #72 = Utf8               ()Ljava/lang/String;
   #73 = Utf8               ArrayBuilder.ofFloat
   #74 = String             #73           // ArrayBuilder.ofFloat
   #75 = Utf8               ()Ljava/lang/Object;
   #76 = NameAndType        #62:#14       // result:()[F
   #77 = Methodref          #2.#76        // scala/collection/mutable/ArrayBuilder$ofFloat.result:()[F
   #78 = Utf8               (Ljava/lang/Object;)Lscala/collection/mutable/Growable;
   #79 = Utf8               scala/runtime/BoxesRunTime
   #80 = Class              #79           // scala/runtime/BoxesRunTime
   #81 = Utf8               unboxToFloat
   #82 = Utf8               (Ljava/lang/Object;)F
   #83 = NameAndType        #81:#82       // unboxToFloat:(Ljava/lang/Object;)F
   #84 = Methodref          #80.#83       // scala/runtime/BoxesRunTime.unboxToFloat:(Ljava/lang/Object;)F
   #85 = NameAndType        #52:#53       // addOne:(F)Lscala/collection/mutable/ArrayBuilder$ofFloat;
   #86 = Methodref          #2.#85        // scala/collection/mutable/ArrayBuilder$ofFloat.addOne:(F)Lscala/collection/mutable/ArrayBuilder$ofFloat;
   #87 = Utf8               <init>
   #88 = Utf8               ()V
   #89 = NameAndType        #87:#88       // "<init>":()V
   #90 = Methodref          #5.#89        // scala/collection/mutable/ArrayBuilder."<init>":()V
   #91 = Utf8               ConstantValue
   #92 = Utf8               Code
   #93 = Utf8               LineNumberTable
   #94 = Utf8               LocalVariableTable
   #95 = Utf8               MethodParameters
   #96 = Utf8               StackMapTable
   #97 = Utf8               InnerClasses
   #98 = Utf8               Signature
   #99 = Utf8               SourceFile
  #100 = Utf8               ScalaInlineInfo
  #101 = Utf8               Scala
{
  private static final long serialVersionUID;
    descriptor: J
    flags: (0x001a) ACC_PRIVATE, ACC_STATIC, ACC_FINAL
    ConstantValue: long 3l

  private float[] elems;
    descriptor: [F
    flags: (0x0002) ACC_PRIVATE

  public float[] elems();
    descriptor: ()[F
    flags: (0x0001) ACC_PUBLIC
    Code:
      stack=1, locals=1, args_size=1
         0: aload_0
         1: getfield      #16                 // Field elems:[F
         4: areturn
      LineNumberTable:
        line 362: 0
      LocalVariableTable:
        Start  Length  Slot  Name   Signature
            0       5     0  this   Lscala/collection/mutable/ArrayBuilder$ofFloat;

  public void elems_$eq(float[]);
    descriptor: ([F)V
    flags: (0x0001) ACC_PUBLIC
    Code:
      stack=2, locals=2, args_size=2
         0: aload_0
         1: aload_1
         2: putfield      #16                 // Field elems:[F
         5: return
      LineNumberTable:
        line 362: 0
      LocalVariableTable:
        Start  Length  Slot  Name   Signature
            0       6     0  this   Lscala/collection/mutable/ArrayBuilder$ofFloat;
            0       6     1   x$1   [F
    MethodParameters:
      Name                           Flags
      x$1                            final

  private float[] mkArray(int);
    descriptor: (I)[F
    flags: (0x0002) ACC_PRIVATE
    Code:
      stack=6, locals=3, args_size=2
         0: iload_1
         1: newarray       float
         3: astore_2
         4: aload_0
         5: invokevirtual #27                 // Method size:()I
         8: iconst_0
         9: if_icmple     29
        12: getstatic     #33                 // Field scala/Array$.MODULE$:Lscala/Array$;
        15: aload_0
        16: invokevirtual #35                 // Method elems:()[F
        19: iconst_0
        20: aload_2
        21: iconst_0
        22: aload_0
        23: invokevirtual #27                 // Method size:()I
        26: invokevirtual #39                 // Method scala/Array$.copy:(Ljava/lang/Object;ILjava/lang/Object;II)V
        29: aload_2
        30: areturn
      StackMapTable: number_of_entries = 1
        frame_type = 252 /* append */
          offset_delta = 29
          locals = [ class "[F" ]
      LineNumberTable:
        line 365: 0
        line 366: 4
        line 367: 29
      LocalVariableTable:
        Start  Length  Slot  Name   Signature
            4      26     2 newelems   [F
            0      31     0  this   Lscala/collection/mutable/ArrayBuilder$ofFloat;
            0      31     1  size   I
    MethodParameters:
      Name                           Flags
      size                           final

  public void resize(int);
    descriptor: (I)V
    flags: (0x0001) ACC_PUBLIC
    Code:
      stack=3, locals=2, args_size=2
         0: aload_0
         1: aload_0
         2: iload_1
         3: invokespecial #46                 // Method mkArray:(I)[F
         6: invokevirtual #48                 // Method elems_$eq:([F)V
         9: aload_0
        10: iload_1
        11: invokevirtual #51                 // Method capacity_$eq:(I)V
        14: return
      LineNumberTable:
        line 371: 0
        line 372: 9
      LocalVariableTable:
        Start  Length  Slot  Name   Signature
            0      15     0  this   Lscala/collection/mutable/ArrayBuilder$ofFloat;
            0      15     1  size   I
    MethodParameters:
      Name                           Flags
      size                           final

  public scala.collection.mutable.ArrayBuilder$ofFloat addOne(float);
    descriptor: (F)Lscala/collection/mutable/ArrayBuilder$ofFloat;
    flags: (0x0001) ACC_PUBLIC
    Code:
      stack=3, locals=2, args_size=2
         0: aload_0
         1: aload_0
         2: invokevirtual #27                 // Method size:()I
         5: iconst_1
         6: iadd
         7: invokevirtual #57                 // Method ensureSize:(I)V
        10: aload_0
        11: invokevirtual #35                 // Method elems:()[F
        14: aload_0
        15: invokevirtual #27                 // Method size:()I
        18: fload_1
        19: fastore
        20: aload_0
        21: aload_0
        22: invokevirtual #27                 // Method size:()I
        25: iconst_1
        26: iadd
        27: invokevirtual #60                 // Method size_$eq:(I)V
        30: aload_0
        31: areturn
      LineNumberTable:
        line 376: 0
        line 377: 10
        line 378: 20
        line 379: 30
      LocalVariableTable:
        Start  Length  Slot  Name   Signature
            0      32     0  this   Lscala/collection/mutable/ArrayBuilder$ofFloat;
            0      32     1  elem   F
    MethodParameters:
      Name                           Flags
      elem                           final

  public float[] result();
    descriptor: ()[F
    flags: (0x0001) ACC_PUBLIC
    Code:
      stack=2, locals=2, args_size=1
         0: aload_0
         1: invokevirtual #65                 // Method capacity:()I
         4: iconst_0
         5: if_icmpeq     36
         8: aload_0
         9: invokevirtual #65                 // Method capacity:()I
        12: aload_0
        13: invokevirtual #27                 // Method size:()I
        16: if_icmpne     36
        19: aload_0
        20: iconst_0
        21: invokevirtual #51                 // Method capacity_$eq:(I)V
        24: aload_0
        25: invokevirtual #35                 // Method elems:()[F
        28: astore_1
        29: aload_0
        30: aconst_null
        31: invokevirtual #48                 // Method elems_$eq:([F)V
        34: aload_1
        35: areturn
        36: aload_0
        37: aload_0
        38: invokevirtual #27                 // Method size:()I
        41: invokespecial #46                 // Method mkArray:(I)[F
        44: areturn
      StackMapTable: number_of_entries = 1
        frame_type = 36 /* same */
      LineNumberTable:
        line 383: 0
        line 384: 19
        line 385: 24
        line 386: 29
        line 387: 34
        line 389: 36
      LocalVariableTable:
        Start  Length  Slot  Name   Signature
           29       6     1   res   [F
            0      45     0  this   Lscala/collection/mutable/ArrayBuilder$ofFloat;

  public boolean equals(java.lang.Object);
    descriptor: (Ljava/lang/Object;)Z
    flags: (0x0001) ACC_PUBLIC
    Code:
      stack=2, locals=4, args_size=2
         0: aload_1
         1: instanceof    #2                  // class scala/collection/mutable/ArrayBuilder$ofFloat
         4: ifeq          43
         7: aload_1
         8: checkcast     #2                  // class scala/collection/mutable/ArrayBuilder$ofFloat
        11: astore_3
        12: aload_0
        13: invokevirtual #27                 // Method size:()I
        16: aload_3
        17: invokevirtual #27                 // Method size:()I
        20: if_icmpne     38
        23: aload_0
        24: invokevirtual #35                 // Method elems:()[F
        27: aload_3
        28: invokevirtual #35                 // Method elems:()[F
        31: if_acmpne     38
        34: iconst_1
        35: goto          39
        38: iconst_0
        39: istore_2
        40: goto          45
        43: iconst_0
        44: istore_2
        45: iload_2
        46: ireturn
      StackMapTable: number_of_entries = 4
        frame_type = 253 /* append */
          offset_delta = 38
          locals = [ top, class scala/collection/mutable/ArrayBuilder$ofFloat ]
        frame_type = 64 /* same_locals_1_stack_item */
          stack = [ int ]
        frame_type = 249 /* chop */
          offset_delta = 3
        frame_type = 252 /* append */
          offset_delta = 1
          locals = [ int ]
      LineNumberTable:
        line 393: 0
        line 394: 43
        line 392: 45
      LocalVariableTable:
        Start  Length  Slot  Name   Signature
            0      47     0  this   Lscala/collection/mutable/ArrayBuilder$ofFloat;
            0      47     1 other   Ljava/lang/Object;
    MethodParameters:
      Name                           Flags
      other                          final

  public java.lang.String toString();
    descriptor: ()Ljava/lang/String;
    flags: (0x0001) ACC_PUBLIC
    Code:
      stack=1, locals=1, args_size=1
         0: ldc           #74                 // String ArrayBuilder.ofFloat
         2: areturn
      LineNumberTable:
        line 397: 0
      LocalVariableTable:
        Start  Length  Slot  Name   Signature
            0       3     0  this   Lscala/collection/mutable/ArrayBuilder$ofFloat;

  public java.lang.Object result();
    descriptor: ()Ljava/lang/Object;
    flags: (0x1041) ACC_PUBLIC, ACC_BRIDGE, ACC_SYNTHETIC
    Code:
      stack=1, locals=1, args_size=1
         0: aload_0
         1: invokevirtual #77                 // Method result:()[F
         4: areturn
      LineNumberTable:
        line 360: 0
      LocalVariableTable:
        Start  Length  Slot  Name   Signature
            0       5     0  this   Lscala/collection/mutable/ArrayBuilder$ofFloat;

  public scala.collection.mutable.Growable addOne(java.lang.Object);
    descriptor: (Ljava/lang/Object;)Lscala/collection/mutable/Growable;
    flags: (0x1041) ACC_PUBLIC, ACC_BRIDGE, ACC_SYNTHETIC
    Code:
      stack=2, locals=2, args_size=2
         0: aload_0
         1: aload_1
         2: invokestatic  #84                 // Method scala/runtime/BoxesRunTime.unboxToFloat:(Ljava/lang/Object;)F
         5: invokevirtual #86                 // Method addOne:(F)Lscala/collection/mutable/ArrayBuilder$ofFloat;
         8: areturn
      LineNumberTable:
        line 360: 0
      LocalVariableTable:
        Start  Length  Slot  Name   Signature
            0       9     0  this   Lscala/collection/mutable/ArrayBuilder$ofFloat;
            0       9     1  elem   Ljava/lang/Object;
    MethodParameters:
      Name                           Flags
      elem                           final

  public java.lang.Object elems();
    descriptor: ()Ljava/lang/Object;
    flags: (0x1041) ACC_PUBLIC, ACC_BRIDGE, ACC_SYNTHETIC
    Code:
      stack=1, locals=1, args_size=1
         0: aload_0
         1: invokevirtual #35                 // Method elems:()[F
         4: areturn
      LineNumberTable:
        line 360: 0
      LocalVariableTable:
        Start  Length  Slot  Name   Signature
            0       5     0  this   Lscala/collection/mutable/ArrayBuilder$ofFloat;

  public scala.collection.mutable.ArrayBuilder$ofFloat();
    descriptor: ()V
    flags: (0x0001) ACC_PUBLIC
    Code:
      stack=1, locals=1, args_size=1
         0: aload_0
         1: invokespecial #90                 // Method scala/collection/mutable/ArrayBuilder."<init>":()V
         4: return
      LineNumberTable:
        line 360: 0
      LocalVariableTable:
        Start  Length  Slot  Name   Signature
            0       5     0  this   Lscala/collection/mutable/ArrayBuilder$ofFloat;
}
InnerClasses:
  public static final #7= #2 of #5;       // ofFloat=class scala/collection/mutable/ArrayBuilder$ofFloat of class scala/collection/mutable/ArrayBuilder
Signature: #3                           // Lscala/collection/mutable/ArrayBuilder<Ljava/lang/Object;>;
SourceFile: "ArrayBuilder.scala"
  ScalaInlineInfo: length = 0x40 (unknown attribute)
   01 01 00 0C 00 57 00 58 01 00 34 00 35 01 00 34
   00 4E 01 00 0C 00 4B 01 00 0C 00 0E 01 00 13 00
   14 01 00 43 00 44 01 00 16 00 17 01 00 2B 00 2C
   01 00 3E 00 4B 01 00 3E 00 0E 01 00 47 00 48 01

  Scala: length = 0x0 (unknown attribute)

