Classfile /Users/mw/Projects/slang-braindump/.jar/jar11/assemble/slang-braindump/assemble/content/scala/collection/mutable/ArrayBufferView$$anonfun$$lessinit$greater$1.class
  Last modified May 29, 2022; size 1106 bytes
  SHA-256 checksum aeb441ff619f5e2824df1cd175c519e3a51baf8b44f5e7d9ec8252227ed7064e
  Compiled from "ArrayBuffer.scala"
public final class scala.collection.mutable.ArrayBufferView$$anonfun$$lessinit$greater$1 extends scala.runtime.AbstractFunction0<java.lang.Object> implements java.io.Serializable
  minor version: 0
  major version: 52
  flags: (0x0031) ACC_PUBLIC, ACC_FINAL, ACC_SUPER
  this_class: #2                          // scala/collection/mutable/ArrayBufferView$$anonfun$$lessinit$greater$1
  super_class: #5                         // scala/runtime/AbstractFunction0
  interfaces: 1, fields: 1, methods: 4, attributes: 6
Constant pool:
   #1 = Utf8               scala/collection/mutable/ArrayBufferView$$anonfun$$lessinit$greater$1
   #2 = Class              #1             // scala/collection/mutable/ArrayBufferView$$anonfun$$lessinit$greater$1
   #3 = Utf8               Lscala/runtime/AbstractFunction0<Ljava/lang/Object;>;Ljava/io/Serializable;
   #4 = Utf8               scala/runtime/AbstractFunction0
   #5 = Class              #4             // scala/runtime/AbstractFunction0
   #6 = Utf8               java/io/Serializable
   #7 = Class              #6             // java/io/Serializable
   #8 = Utf8               ArrayBuffer.scala
   #9 = Utf8               scala/collection/mutable/ArrayBufferView
  #10 = Class              #9             // scala/collection/mutable/ArrayBufferView
  #11 = Utf8               <init>
  #12 = Utf8               ([Ljava/lang/Object;I)V
  #13 = NameAndType        #11:#12        // "<init>":([Ljava/lang/Object;I)V
  #14 = Utf8               serialVersionUID
  #15 = Utf8               J
  #16 = Long               0l
  #18 = Utf8               apply
  #19 = Utf8               ()I
  #20 = Utf8               this
  #21 = Utf8               Lscala/collection/mutable/ArrayBufferView$$anonfun$$lessinit$greater$1;
  #22 = Utf8               apply$mcI$sp
  #23 = Utf8               ()Ljava/lang/Object;
  #24 = NameAndType        #18:#19        // apply:()I
  #25 = Methodref          #2.#24         // scala/collection/mutable/ArrayBufferView$$anonfun$$lessinit$greater$1.apply:()I
  #26 = Utf8               scala/runtime/BoxesRunTime
  #27 = Class              #26            // scala/runtime/BoxesRunTime
  #28 = Utf8               boxToInteger
  #29 = Utf8               (I)Ljava/lang/Integer;
  #30 = NameAndType        #28:#29        // boxToInteger:(I)Ljava/lang/Integer;
  #31 = Methodref          #27.#30        // scala/runtime/BoxesRunTime.boxToInteger:(I)Ljava/lang/Integer;
  #32 = Utf8               ()V
  #33 = NameAndType        #11:#32        // "<init>":()V
  #34 = Methodref          #5.#33         // scala/runtime/AbstractFunction0."<init>":()V
  #35 = Utf8               ConstantValue
  #36 = Utf8               Code
  #37 = Utf8               LineNumberTable
  #38 = Utf8               LocalVariableTable
  #39 = Utf8               InnerClasses
  #40 = Utf8               EnclosingMethod
  #41 = Utf8               Signature
  #42 = Utf8               SourceFile
  #43 = Utf8               ScalaInlineInfo
  #44 = Utf8               Scala
{
  private static final long serialVersionUID;
    descriptor: J
    flags: (0x001a) ACC_PRIVATE, ACC_STATIC, ACC_FINAL
    ConstantValue: long 0l

  public final int apply();
    descriptor: ()I
    flags: (0x0011) ACC_PUBLIC, ACC_FINAL
    Code:
      stack=1, locals=1, args_size=1
         0: iconst_0
         1: ireturn
      LineNumberTable:
        line 332: 0
        line 332: 1
      LocalVariableTable:
        Start  Length  Slot  Name   Signature
            0       2     0  this   Lscala/collection/mutable/ArrayBufferView$$anonfun$$lessinit$greater$1;

  public int apply$mcI$sp();
    descriptor: ()I
    flags: (0x0001) ACC_PUBLIC
    Code:
      stack=1, locals=1, args_size=1
         0: iconst_0
         1: ireturn
      LineNumberTable:
        line 332: 0
      LocalVariableTable:
        Start  Length  Slot  Name   Signature
            0       2     0  this   Lscala/collection/mutable/ArrayBufferView$$anonfun$$lessinit$greater$1;

  public final java.lang.Object apply();
    descriptor: ()Ljava/lang/Object;
    flags: (0x1051) ACC_PUBLIC, ACC_FINAL, ACC_BRIDGE, ACC_SYNTHETIC
    Code:
      stack=1, locals=1, args_size=1
         0: aload_0
         1: invokevirtual #25                 // Method apply:()I
         4: invokestatic  #31                 // Method scala/runtime/BoxesRunTime.boxToInteger:(I)Ljava/lang/Integer;
         7: areturn
      LineNumberTable:
        line 332: 0
      LocalVariableTable:
        Start  Length  Slot  Name   Signature
            0       8     0  this   Lscala/collection/mutable/ArrayBufferView$$anonfun$$lessinit$greater$1;

  public scala.collection.mutable.ArrayBufferView$$anonfun$$lessinit$greater$1();
    descriptor: ()V
    flags: (0x0001) ACC_PUBLIC
    Code:
      stack=1, locals=1, args_size=1
         0: aload_0
         1: invokespecial #34                 // Method scala/runtime/AbstractFunction0."<init>":()V
         4: return
      LineNumberTable:
        line 332: 0
      LocalVariableTable:
        Start  Length  Slot  Name   Signature
            0       5     0  this   Lscala/collection/mutable/ArrayBufferView$$anonfun$$lessinit$greater$1;
}
InnerClasses:
  public final #2;                        // class scala/collection/mutable/ArrayBufferView$$anonfun$$lessinit$greater$1
EnclosingMethod: #10.#13                // scala.collection.mutable.ArrayBufferView.<init>
Signature: #3                           // Lscala/runtime/AbstractFunction0<Ljava/lang/Object;>;Ljava/io/Serializable;
SourceFile: "ArrayBuffer.scala"
  ScalaInlineInfo: length = 0x18 (unknown attribute)
   01 01 00 04 00 0B 00 20 01 00 12 00 13 01 00 12
   00 17 01 00 16 00 13 01
  Scala: length = 0x0 (unknown attribute)

