Classfile /Users/mw/Projects/slang-braindump/.jar/jar11/assemble/slang-braindump/assemble/content/scala/collection/mutable/ArrayBuilder$ofRef.class
  Last modified May 29, 2022; size 3038 bytes
  SHA-256 checksum 9c2c2051f8417012952344c4dabf9e9152d1e7cd6414049d7795a405fb04ff7b
  Compiled from "ArrayBuilder.scala"
public final class scala.collection.mutable.ArrayBuilder$ofRef<T extends java.lang.Object> extends scala.collection.mutable.ArrayBuilder<T>
  minor version: 0
  major version: 52
  flags: (0x0031) ACC_PUBLIC, ACC_FINAL, ACC_SUPER
  this_class: #2                          // scala/collection/mutable/ArrayBuilder$ofRef
  super_class: #5                         // scala/collection/mutable/ArrayBuilder
  interfaces: 0, fields: 3, methods: 13, attributes: 5
Constant pool:
    #1 = Utf8               scala/collection/mutable/ArrayBuilder$ofRef
    #2 = Class              #1            // scala/collection/mutable/ArrayBuilder$ofRef
    #3 = Utf8               <T:Ljava/lang/Object;>Lscala/collection/mutable/ArrayBuilder<TT;>;
    #4 = Utf8               scala/collection/mutable/ArrayBuilder
    #5 = Class              #4            // scala/collection/mutable/ArrayBuilder
    #6 = Utf8               ArrayBuilder.scala
    #7 = Utf8               ofRef
    #8 = Utf8               serialVersionUID
    #9 = Utf8               J
   #10 = Long               3l
   #12 = Utf8               ct
   #13 = Utf8               Lscala/reflect/ClassTag;
   #14 = Utf8               Lscala/reflect/ClassTag<TT;>;
   #15 = Utf8               elems
   #16 = Utf8               [Ljava/lang/Object;
   #17 = Utf8               [TT;
   #18 = Utf8               ()[Ljava/lang/Object;
   #19 = Utf8               ()[TT;
   #20 = NameAndType        #15:#16       // elems:[Ljava/lang/Object;
   #21 = Fieldref           #2.#20        // scala/collection/mutable/ArrayBuilder$ofRef.elems:[Ljava/lang/Object;
   #22 = Utf8               this
   #23 = Utf8               Lscala/collection/mutable/ArrayBuilder$ofRef;
   #24 = Utf8               elems_$eq
   #25 = Utf8               ([Ljava/lang/Object;)V
   #26 = Utf8               ([TT;)V
   #27 = Utf8               x$1
   #28 = Utf8               mkArray
   #29 = Utf8               (I)[Ljava/lang/Object;
   #30 = Utf8               (I)[TT;
   #31 = Utf8               size
   #32 = Utf8               capacity
   #33 = Utf8               ()I
   #34 = NameAndType        #32:#33       // capacity:()I
   #35 = Methodref          #2.#34        // scala/collection/mutable/ArrayBuilder$ofRef.capacity:()I
   #36 = NameAndType        #15:#18       // elems:()[Ljava/lang/Object;
   #37 = Methodref          #2.#36        // scala/collection/mutable/ArrayBuilder$ofRef.elems:()[Ljava/lang/Object;
   #38 = NameAndType        #12:#13       // ct:Lscala/reflect/ClassTag;
   #39 = Fieldref           #2.#38        // scala/collection/mutable/ArrayBuilder$ofRef.ct:Lscala/reflect/ClassTag;
   #40 = Utf8               scala/reflect/ClassTag
   #41 = Class              #40           // scala/reflect/ClassTag
   #42 = Utf8               newArray
   #43 = Utf8               (I)Ljava/lang/Object;
   #44 = NameAndType        #42:#43       // newArray:(I)Ljava/lang/Object;
   #45 = InterfaceMethodref #41.#44       // scala/reflect/ClassTag.newArray:(I)Ljava/lang/Object;
   #46 = Class              #16           // "[Ljava/lang/Object;"
   #47 = Utf8               java/util/Arrays
   #48 = Class              #47           // java/util/Arrays
   #49 = Utf8               copyOf
   #50 = Utf8               ([Ljava/lang/Object;I)[Ljava/lang/Object;
   #51 = NameAndType        #49:#50       // copyOf:([Ljava/lang/Object;I)[Ljava/lang/Object;
   #52 = Methodref          #48.#51       // java/util/Arrays.copyOf:([Ljava/lang/Object;I)[Ljava/lang/Object;
   #53 = Utf8               I
   #54 = Utf8               resize
   #55 = Utf8               (I)V
   #56 = NameAndType        #28:#29       // mkArray:(I)[Ljava/lang/Object;
   #57 = Methodref          #2.#56        // scala/collection/mutable/ArrayBuilder$ofRef.mkArray:(I)[Ljava/lang/Object;
   #58 = NameAndType        #24:#25       // elems_$eq:([Ljava/lang/Object;)V
   #59 = Methodref          #2.#58        // scala/collection/mutable/ArrayBuilder$ofRef.elems_$eq:([Ljava/lang/Object;)V
   #60 = Utf8               capacity_$eq
   #61 = NameAndType        #60:#55       // capacity_$eq:(I)V
   #62 = Methodref          #2.#61        // scala/collection/mutable/ArrayBuilder$ofRef.capacity_$eq:(I)V
   #63 = Utf8               addOne
   #64 = Utf8               (Ljava/lang/Object;)Lscala/collection/mutable/ArrayBuilder$ofRef;
   #65 = Utf8               (TT;)Lscala/collection/mutable/ArrayBuilder$ofRef<TT;>;
   #66 = Utf8               elem
   #67 = NameAndType        #31:#33       // size:()I
   #68 = Methodref          #2.#67        // scala/collection/mutable/ArrayBuilder$ofRef.size:()I
   #69 = Utf8               ensureSize
   #70 = NameAndType        #69:#55       // ensureSize:(I)V
   #71 = Methodref          #2.#70        // scala/collection/mutable/ArrayBuilder$ofRef.ensureSize:(I)V
   #72 = Utf8               size_$eq
   #73 = NameAndType        #72:#55       // size_$eq:(I)V
   #74 = Methodref          #2.#73        // scala/collection/mutable/ArrayBuilder$ofRef.size_$eq:(I)V
   #75 = Utf8               Ljava/lang/Object;
   #76 = Utf8               result
   #77 = Utf8               res
   #78 = Utf8               clear
   #79 = Utf8               ()V
   #80 = NameAndType        #78:#79       // clear:()V
   #81 = Methodref          #5.#80        // scala/collection/mutable/ArrayBuilder.clear:()V
   #82 = Utf8               fill
   #83 = Utf8               ([Ljava/lang/Object;Ljava/lang/Object;)V
   #84 = NameAndType        #82:#83       // fill:([Ljava/lang/Object;Ljava/lang/Object;)V
   #85 = Methodref          #48.#84       // java/util/Arrays.fill:([Ljava/lang/Object;Ljava/lang/Object;)V
   #86 = Utf8               equals
   #87 = Utf8               (Ljava/lang/Object;)Z
   #88 = Utf8               other
   #89 = Utf8               toString
   #90 = Utf8               ()Ljava/lang/String;
   #91 = Utf8               ArrayBuilder.ofRef
   #92 = String             #91           // ArrayBuilder.ofRef
   #93 = Utf8               ()Ljava/lang/Object;
   #94 = NameAndType        #76:#18       // result:()[Ljava/lang/Object;
   #95 = Methodref          #2.#94        // scala/collection/mutable/ArrayBuilder$ofRef.result:()[Ljava/lang/Object;
   #96 = Utf8               (Ljava/lang/Object;)Lscala/collection/mutable/Growable;
   #97 = NameAndType        #63:#64       // addOne:(Ljava/lang/Object;)Lscala/collection/mutable/ArrayBuilder$ofRef;
   #98 = Methodref          #2.#97        // scala/collection/mutable/ArrayBuilder$ofRef.addOne:(Ljava/lang/Object;)Lscala/collection/mutable/ArrayBuilder$ofRef;
   #99 = Utf8               <init>
  #100 = Utf8               (Lscala/reflect/ClassTag;)V
  #101 = Utf8               (Lscala/reflect/ClassTag<TT;>;)V
  #102 = NameAndType        #99:#79       // "<init>":()V
  #103 = Methodref          #5.#102       // scala/collection/mutable/ArrayBuilder."<init>":()V
  #104 = Utf8               ConstantValue
  #105 = Utf8               Signature
  #106 = Utf8               Code
  #107 = Utf8               LineNumberTable
  #108 = Utf8               LocalVariableTable
  #109 = Utf8               MethodParameters
  #110 = Utf8               StackMapTable
  #111 = Utf8               InnerClasses
  #112 = Utf8               SourceFile
  #113 = Utf8               ScalaInlineInfo
  #114 = Utf8               Scala
{
  private static final long serialVersionUID;
    descriptor: J
    flags: (0x001a) ACC_PRIVATE, ACC_STATIC, ACC_FINAL
    ConstantValue: long 3l

  private final scala.reflect.ClassTag<T> ct;
    descriptor: Lscala/reflect/ClassTag;
    flags: (0x0012) ACC_PRIVATE, ACC_FINAL
    Signature: #14                          // Lscala/reflect/ClassTag<TT;>;

  private T[] elems;
    descriptor: [Ljava/lang/Object;
    flags: (0x0002) ACC_PRIVATE
    Signature: #17                          // [TT;

  public T[] elems();
    descriptor: ()[Ljava/lang/Object;
    flags: (0x0001) ACC_PUBLIC
    Code:
      stack=1, locals=1, args_size=1
         0: aload_0
         1: getfield      #21                 // Field elems:[Ljava/lang/Object;
         4: areturn
      LineNumberTable:
        line 105: 0
      LocalVariableTable:
        Start  Length  Slot  Name   Signature
            0       5     0  this   Lscala/collection/mutable/ArrayBuilder$ofRef;
    Signature: #19                          // ()[TT;

  public void elems_$eq(T[]);
    descriptor: ([Ljava/lang/Object;)V
    flags: (0x0001) ACC_PUBLIC
    Code:
      stack=2, locals=2, args_size=2
         0: aload_0
         1: aload_1
         2: putfield      #21                 // Field elems:[Ljava/lang/Object;
         5: return
      LineNumberTable:
        line 105: 0
      LocalVariableTable:
        Start  Length  Slot  Name   Signature
            0       6     0  this   Lscala/collection/mutable/ArrayBuilder$ofRef;
            0       6     1   x$1   [Ljava/lang/Object;
    Signature: #26                          // ([TT;)V
    MethodParameters:
      Name                           Flags
      x$1                            final

  private T[] mkArray(int);
    descriptor: (I)[Ljava/lang/Object;
    flags: (0x0002) ACC_PRIVATE
    Code:
      stack=2, locals=2, args_size=2
         0: aload_0
         1: invokevirtual #35                 // Method capacity:()I
         4: iload_1
         5: if_icmpne     21
         8: aload_0
         9: invokevirtual #35                 // Method capacity:()I
        12: iconst_0
        13: if_icmple     21
        16: aload_0
        17: invokevirtual #37                 // Method elems:()[Ljava/lang/Object;
        20: areturn
        21: aload_0
        22: invokevirtual #37                 // Method elems:()[Ljava/lang/Object;
        25: ifnonnull     42
        28: aload_0
        29: getfield      #39                 // Field ct:Lscala/reflect/ClassTag;
        32: iload_1
        33: invokeinterface #45,  2           // InterfaceMethod scala/reflect/ClassTag.newArray:(I)Ljava/lang/Object;
        38: checkcast     #46                 // class "[Ljava/lang/Object;"
        41: areturn
        42: aload_0
        43: invokevirtual #37                 // Method elems:()[Ljava/lang/Object;
        46: iload_1
        47: invokestatic  #52                 // Method java/util/Arrays.copyOf:([Ljava/lang/Object;I)[Ljava/lang/Object;
        50: areturn
      StackMapTable: number_of_entries = 2
        frame_type = 21 /* same */
        frame_type = 20 /* same */
      LineNumberTable:
        line 108: 0
        line 109: 21
        line 110: 42
      LocalVariableTable:
        Start  Length  Slot  Name   Signature
            0      51     0  this   Lscala/collection/mutable/ArrayBuilder$ofRef;
            0      51     1  size   I
    Signature: #30                          // (I)[TT;
    MethodParameters:
      Name                           Flags
      size                           final

  public void resize(int);
    descriptor: (I)V
    flags: (0x0001) ACC_PUBLIC
    Code:
      stack=3, locals=2, args_size=2
         0: aload_0
         1: aload_0
         2: iload_1
         3: invokespecial #57                 // Method mkArray:(I)[Ljava/lang/Object;
         6: invokevirtual #59                 // Method elems_$eq:([Ljava/lang/Object;)V
         9: aload_0
        10: iload_1
        11: invokevirtual #62                 // Method capacity_$eq:(I)V
        14: return
      LineNumberTable:
        line 114: 0
        line 115: 9
      LocalVariableTable:
        Start  Length  Slot  Name   Signature
            0      15     0  this   Lscala/collection/mutable/ArrayBuilder$ofRef;
            0      15     1  size   I
    MethodParameters:
      Name                           Flags
      size                           final

  public scala.collection.mutable.ArrayBuilder$ofRef<T> addOne(T);
    descriptor: (Ljava/lang/Object;)Lscala/collection/mutable/ArrayBuilder$ofRef;
    flags: (0x0001) ACC_PUBLIC
    Code:
      stack=3, locals=2, args_size=2
         0: aload_0
         1: aload_0
         2: invokevirtual #68                 // Method size:()I
         5: iconst_1
         6: iadd
         7: invokevirtual #71                 // Method ensureSize:(I)V
        10: aload_0
        11: invokevirtual #37                 // Method elems:()[Ljava/lang/Object;
        14: aload_0
        15: invokevirtual #68                 // Method size:()I
        18: aload_1
        19: aastore
        20: aload_0
        21: aload_0
        22: invokevirtual #68                 // Method size:()I
        25: iconst_1
        26: iadd
        27: invokevirtual #74                 // Method size_$eq:(I)V
        30: aload_0
        31: areturn
      LineNumberTable:
        line 119: 0
        line 120: 10
        line 121: 20
        line 122: 30
      LocalVariableTable:
        Start  Length  Slot  Name   Signature
            0      32     0  this   Lscala/collection/mutable/ArrayBuilder$ofRef;
            0      32     1  elem   Ljava/lang/Object;
    Signature: #65                          // (TT;)Lscala/collection/mutable/ArrayBuilder$ofRef<TT;>;
    MethodParameters:
      Name                           Flags
      elem                           final

  public T[] result();
    descriptor: ()[Ljava/lang/Object;
    flags: (0x0001) ACC_PUBLIC
    Code:
      stack=2, locals=2, args_size=1
         0: aload_0
         1: invokevirtual #35                 // Method capacity:()I
         4: iconst_0
         5: if_icmpeq     36
         8: aload_0
         9: invokevirtual #35                 // Method capacity:()I
        12: aload_0
        13: invokevirtual #68                 // Method size:()I
        16: if_icmpne     36
        19: aload_0
        20: iconst_0
        21: invokevirtual #62                 // Method capacity_$eq:(I)V
        24: aload_0
        25: invokevirtual #37                 // Method elems:()[Ljava/lang/Object;
        28: astore_1
        29: aload_0
        30: aconst_null
        31: invokevirtual #59                 // Method elems_$eq:([Ljava/lang/Object;)V
        34: aload_1
        35: areturn
        36: aload_0
        37: aload_0
        38: invokevirtual #68                 // Method size:()I
        41: invokespecial #57                 // Method mkArray:(I)[Ljava/lang/Object;
        44: areturn
      StackMapTable: number_of_entries = 1
        frame_type = 36 /* same */
      LineNumberTable:
        line 126: 0
        line 127: 19
        line 128: 24
        line 129: 29
        line 130: 34
        line 132: 36
      LocalVariableTable:
        Start  Length  Slot  Name   Signature
           29       6     1   res   [Ljava/lang/Object;
            0      45     0  this   Lscala/collection/mutable/ArrayBuilder$ofRef;
    Signature: #19                          // ()[TT;

  public void clear();
    descriptor: ()V
    flags: (0x0001) ACC_PUBLIC
    Code:
      stack=2, locals=1, args_size=1
         0: aload_0
         1: invokespecial #81                 // Method scala/collection/mutable/ArrayBuilder.clear:()V
         4: aload_0
         5: invokevirtual #37                 // Method elems:()[Ljava/lang/Object;
         8: ifnull        19
        11: aload_0
        12: invokevirtual #37                 // Method elems:()[Ljava/lang/Object;
        15: aconst_null
        16: invokestatic  #85                 // Method java/util/Arrays.fill:([Ljava/lang/Object;Ljava/lang/Object;)V
        19: return
      StackMapTable: number_of_entries = 1
        frame_type = 19 /* same */
      LineNumberTable:
        line 136: 0
        line 137: 4
      LocalVariableTable:
        Start  Length  Slot  Name   Signature
            0      20     0  this   Lscala/collection/mutable/ArrayBuilder$ofRef;

  public boolean equals(java.lang.Object);
    descriptor: (Ljava/lang/Object;)Z
    flags: (0x0001) ACC_PUBLIC
    Code:
      stack=2, locals=4, args_size=2
         0: aload_1
         1: instanceof    #2                  // class scala/collection/mutable/ArrayBuilder$ofRef
         4: ifeq          43
         7: aload_1
         8: checkcast     #2                  // class scala/collection/mutable/ArrayBuilder$ofRef
        11: astore_3
        12: aload_0
        13: invokevirtual #68                 // Method size:()I
        16: aload_3
        17: invokevirtual #68                 // Method size:()I
        20: if_icmpne     38
        23: aload_0
        24: invokevirtual #37                 // Method elems:()[Ljava/lang/Object;
        27: aload_3
        28: invokevirtual #37                 // Method elems:()[Ljava/lang/Object;
        31: if_acmpne     38
        34: iconst_1
        35: goto          39
        38: iconst_0
        39: istore_2
        40: goto          45
        43: iconst_0
        44: istore_2
        45: iload_2
        46: ireturn
      StackMapTable: number_of_entries = 4
        frame_type = 253 /* append */
          offset_delta = 38
          locals = [ top, class scala/collection/mutable/ArrayBuilder$ofRef ]
        frame_type = 64 /* same_locals_1_stack_item */
          stack = [ int ]
        frame_type = 249 /* chop */
          offset_delta = 3
        frame_type = 252 /* append */
          offset_delta = 1
          locals = [ int ]
      LineNumberTable:
        line 141: 0
        line 142: 43
        line 140: 45
      LocalVariableTable:
        Start  Length  Slot  Name   Signature
            0      47     0  this   Lscala/collection/mutable/ArrayBuilder$ofRef;
            0      47     1 other   Ljava/lang/Object;
    MethodParameters:
      Name                           Flags
      other                          final

  public java.lang.String toString();
    descriptor: ()Ljava/lang/String;
    flags: (0x0001) ACC_PUBLIC
    Code:
      stack=1, locals=1, args_size=1
         0: ldc           #92                 // String ArrayBuilder.ofRef
         2: areturn
      LineNumberTable:
        line 145: 0
      LocalVariableTable:
        Start  Length  Slot  Name   Signature
            0       3     0  this   Lscala/collection/mutable/ArrayBuilder$ofRef;

  public java.lang.Object result();
    descriptor: ()Ljava/lang/Object;
    flags: (0x1041) ACC_PUBLIC, ACC_BRIDGE, ACC_SYNTHETIC
    Code:
      stack=1, locals=1, args_size=1
         0: aload_0
         1: invokevirtual #95                 // Method result:()[Ljava/lang/Object;
         4: areturn
      LineNumberTable:
        line 103: 0
      LocalVariableTable:
        Start  Length  Slot  Name   Signature
            0       5     0  this   Lscala/collection/mutable/ArrayBuilder$ofRef;

  public scala.collection.mutable.Growable addOne(java.lang.Object);
    descriptor: (Ljava/lang/Object;)Lscala/collection/mutable/Growable;
    flags: (0x1041) ACC_PUBLIC, ACC_BRIDGE, ACC_SYNTHETIC
    Code:
      stack=2, locals=2, args_size=2
         0: aload_0
         1: aload_1
         2: invokevirtual #98                 // Method addOne:(Ljava/lang/Object;)Lscala/collection/mutable/ArrayBuilder$ofRef;
         5: areturn
      LineNumberTable:
        line 103: 0
      LocalVariableTable:
        Start  Length  Slot  Name   Signature
            0       6     0  this   Lscala/collection/mutable/ArrayBuilder$ofRef;
            0       6     1  elem   Ljava/lang/Object;
    MethodParameters:
      Name                           Flags
      elem                           final

  public java.lang.Object elems();
    descriptor: ()Ljava/lang/Object;
    flags: (0x1041) ACC_PUBLIC, ACC_BRIDGE, ACC_SYNTHETIC
    Code:
      stack=1, locals=1, args_size=1
         0: aload_0
         1: invokevirtual #37                 // Method elems:()[Ljava/lang/Object;
         4: areturn
      LineNumberTable:
        line 103: 0
      LocalVariableTable:
        Start  Length  Slot  Name   Signature
            0       5     0  this   Lscala/collection/mutable/ArrayBuilder$ofRef;

  public scala.collection.mutable.ArrayBuilder$ofRef(scala.reflect.ClassTag<T>);
    descriptor: (Lscala/reflect/ClassTag;)V
    flags: (0x0001) ACC_PUBLIC
    Code:
      stack=2, locals=2, args_size=2
         0: aload_0
         1: aload_1
         2: putfield      #39                 // Field ct:Lscala/reflect/ClassTag;
         5: aload_0
         6: invokespecial #103                // Method scala/collection/mutable/ArrayBuilder."<init>":()V
         9: return
      LineNumberTable:
        line 103: 0
      LocalVariableTable:
        Start  Length  Slot  Name   Signature
            0      10     0  this   Lscala/collection/mutable/ArrayBuilder$ofRef;
            0      10     1    ct   Lscala/reflect/ClassTag;
    Signature: #101                         // (Lscala/reflect/ClassTag<TT;>;)V
    MethodParameters:
      Name                           Flags
      ct                             final
}
InnerClasses:
  public static final #7= #2 of #5;       // ofRef=class scala/collection/mutable/ArrayBuilder$ofRef of class scala/collection/mutable/ArrayBuilder
Signature: #3                           // <T:Ljava/lang/Object;>Lscala/collection/mutable/ArrayBuilder<TT;>;
SourceFile: "ArrayBuilder.scala"
  ScalaInlineInfo: length = 0x45 (unknown attribute)
   01 01 00 0D 00 63 00 64 01 00 3F 00 40 01 00 3F
   00 60 01 00 4E 00 4F 01 00 0F 00 5D 01 00 0F 00
   12 01 00 18 00 19 01 00 56 00 57 01 00 1C 00 1D
   01 00 36 00 37 01 00 4C 00 5D 01 00 4C 00 12 01
   00 59 00 5A 01
  Scala: length = 0x0 (unknown attribute)

