Classfile /Users/mw/Projects/slang-braindump/.jar/jar11/assemble/slang-braindump/assemble/content/scala/collection/mutable/CollisionProofHashMap$$anon$3.class
  Last modified May 29, 2022; size 1237 bytes
  SHA-256 checksum cd95fc4ad5897f379d05ec73fc1013221b88a4ca6d876c30c2e210bf444489a8
  Compiled from "CollisionProofHashMap.scala"
public final class scala.collection.mutable.CollisionProofHashMap$$anon$3 extends scala.collection.mutable.GrowableBuilder<scala.Tuple2<K, V>, scala.collection.mutable.CollisionProofHashMap<K, V>>
  minor version: 0
  major version: 52
  flags: (0x0031) ACC_PUBLIC, ACC_FINAL, ACC_SUPER
  this_class: #2                          // scala/collection/mutable/CollisionProofHashMap$$anon$3
  super_class: #5                         // scala/collection/mutable/GrowableBuilder
  interfaces: 0, fields: 0, methods: 2, attributes: 6
Constant pool:
   #1 = Utf8               scala/collection/mutable/CollisionProofHashMap$$anon$3
   #2 = Class              #1             // scala/collection/mutable/CollisionProofHashMap$$anon$3
   #3 = Utf8               Lscala/collection/mutable/GrowableBuilder<Lscala/Tuple2<TK;TV;>;Lscala/collection/mutable/CollisionProofHashMap<TK;TV;>;>;
   #4 = Utf8               scala/collection/mutable/GrowableBuilder
   #5 = Class              #4             // scala/collection/mutable/GrowableBuilder
   #6 = Utf8               CollisionProofHashMap.scala
   #7 = Utf8               scala/collection/mutable/CollisionProofHashMap$
   #8 = Class              #7             // scala/collection/mutable/CollisionProofHashMap$
   #9 = Utf8               newBuilder
  #10 = Utf8               (IDLscala/math/Ordering;)Lscala/collection/mutable/Builder;
  #11 = NameAndType        #9:#10         // newBuilder:(IDLscala/math/Ordering;)Lscala/collection/mutable/Builder;
  #12 = Utf8               sizeHint
  #13 = Utf8               (I)V
  #14 = Utf8               size
  #15 = Utf8               elems
  #16 = Utf8               ()Lscala/collection/mutable/Growable;
  #17 = NameAndType        #15:#16        // elems:()Lscala/collection/mutable/Growable;
  #18 = Methodref          #2.#17         // scala/collection/mutable/CollisionProofHashMap$$anon$3.elems:()Lscala/collection/mutable/Growable;
  #19 = Utf8               scala/collection/mutable/CollisionProofHashMap
  #20 = Class              #19            // scala/collection/mutable/CollisionProofHashMap
  #21 = NameAndType        #12:#13        // sizeHint:(I)V
  #22 = Methodref          #20.#21        // scala/collection/mutable/CollisionProofHashMap.sizeHint:(I)V
  #23 = Utf8               this
  #24 = Utf8               Lscala/collection/mutable/CollisionProofHashMap$$anon$3;
  #25 = Utf8               I
  #26 = Utf8               <init>
  #27 = Utf8               (IDLscala/math/Ordering;)V
  #28 = Utf8               initialCapacity$1
  #29 = Utf8               loadFactor$1
  #30 = Utf8               evidence$4$1
  #31 = NameAndType        #26:#27        // "<init>":(IDLscala/math/Ordering;)V
  #32 = Methodref          #20.#31        // scala/collection/mutable/CollisionProofHashMap."<init>":(IDLscala/math/Ordering;)V
  #33 = Utf8               (Lscala/collection/mutable/Growable;)V
  #34 = NameAndType        #26:#33        // "<init>":(Lscala/collection/mutable/Growable;)V
  #35 = Methodref          #5.#34         // scala/collection/mutable/GrowableBuilder."<init>":(Lscala/collection/mutable/Growable;)V
  #36 = Utf8               D
  #37 = Utf8               Lscala/math/Ordering;
  #38 = Utf8               Code
  #39 = Utf8               LineNumberTable
  #40 = Utf8               LocalVariableTable
  #41 = Utf8               MethodParameters
  #42 = Utf8               InnerClasses
  #43 = Utf8               EnclosingMethod
  #44 = Utf8               Signature
  #45 = Utf8               SourceFile
  #46 = Utf8               ScalaInlineInfo
  #47 = Utf8               Scala
{
  public void sizeHint(int);
    descriptor: (I)V
    flags: (0x0001) ACC_PUBLIC
    Code:
      stack=2, locals=2, args_size=2
         0: aload_0
         1: invokevirtual #18                 // Method elems:()Lscala/collection/mutable/Growable;
         4: checkcast     #20                 // class scala/collection/mutable/CollisionProofHashMap
         7: iload_1
         8: invokevirtual #22                 // Method scala/collection/mutable/CollisionProofHashMap.sizeHint:(I)V
        11: return
      LineNumberTable:
        line 758: 0
      LocalVariableTable:
        Start  Length  Slot  Name   Signature
            0      12     0  this   Lscala/collection/mutable/CollisionProofHashMap$$anon$3;
            0      12     1  size   I
    MethodParameters:
      Name                           Flags
      size                           final

  public scala.collection.mutable.CollisionProofHashMap$$anon$3(int, double, scala.math.Ordering);
    descriptor: (IDLscala/math/Ordering;)V
    flags: (0x0001) ACC_PUBLIC
    Code:
      stack=7, locals=5, args_size=4
         0: aload_0
         1: new           #20                 // class scala/collection/mutable/CollisionProofHashMap
         4: dup
         5: iload_1
         6: dload_2
         7: aload         4
         9: invokespecial #32                 // Method scala/collection/mutable/CollisionProofHashMap."<init>":(IDLscala/math/Ordering;)V
        12: invokespecial #35                 // Method scala/collection/mutable/GrowableBuilder."<init>":(Lscala/collection/mutable/Growable;)V
        15: return
      LineNumberTable:
        line 757: 0
      LocalVariableTable:
        Start  Length  Slot  Name   Signature
            0      16     0  this   Lscala/collection/mutable/CollisionProofHashMap$$anon$3;
            0      16     1 initialCapacity$1   I
            0      16     2 loadFactor$1   D
            0      16     4 evidence$4$1   Lscala/math/Ordering;
    MethodParameters:
      Name                           Flags
      initialCapacity$1              final
      loadFactor$1                   final
      evidence$4$1                   final
}
InnerClasses:
  public final #2;                        // class scala/collection/mutable/CollisionProofHashMap$$anon$3
EnclosingMethod: #8.#11                 // scala.collection.mutable.CollisionProofHashMap$.newBuilder
Signature: #3                           // Lscala/collection/mutable/GrowableBuilder<Lscala/Tuple2<TK;TV;>;Lscala/collection/mutable/CollisionProofHashMap<TK;TV;>;>;
SourceFile: "CollisionProofHashMap.scala"
  ScalaInlineInfo: length = 0xE (unknown attribute)
   01 01 00 02 00 1A 00 1B 01 00 0C 00 0D 01
  Scala: length = 0x0 (unknown attribute)

