Classfile /Users/mw/Projects/slang-braindump/.jar/jar11/assemble/slang-braindump/assemble/content/scala/collection/mutable/CollisionProofHashMap$RBNode.class
  Last modified May 29, 2022; size 5541 bytes
  SHA-256 checksum 5542694822a2fb8a480397b59e1bdff731cf4e3d62574c50e035e5aff1cb3594
  Compiled from "CollisionProofHashMap.scala"
public final class scala.collection.mutable.CollisionProofHashMap$RBNode<K extends java.lang.Object, V extends java.lang.Object> extends scala.collection.mutable.CollisionProofHashMap$Node
  minor version: 0
  major version: 52
  flags: (0x0031) ACC_PUBLIC, ACC_FINAL, ACC_SUPER
  this_class: #2                          // scala/collection/mutable/CollisionProofHashMap$RBNode
  super_class: #5                         // scala/collection/mutable/CollisionProofHashMap$Node
  interfaces: 0, fields: 7, methods: 20, attributes: 5
Constant pool:
    #1 = Utf8               scala/collection/mutable/CollisionProofHashMap$RBNode
    #2 = Class              #1            // scala/collection/mutable/CollisionProofHashMap$RBNode
    #3 = Utf8               <K:Ljava/lang/Object;V:Ljava/lang/Object;>Lscala/collection/mutable/CollisionProofHashMap$Node;
    #4 = Utf8               scala/collection/mutable/CollisionProofHashMap$Node
    #5 = Class              #4            // scala/collection/mutable/CollisionProofHashMap$Node
    #6 = Utf8               CollisionProofHashMap.scala
    #7 = Utf8               scala/collection/mutable/CollisionProofHashMap
    #8 = Class              #7            // scala/collection/mutable/CollisionProofHashMap
    #9 = Utf8               Node
   #10 = Utf8               RBNode
   #11 = Utf8               key
   #12 = Utf8               Ljava/lang/Object;
   #13 = Utf8               TK;
   #14 = Utf8               hash
   #15 = Utf8               I
   #16 = Utf8               value
   #17 = Utf8               TV;
   #18 = Utf8               red
   #19 = Utf8               Z
   #20 = Utf8               left
   #21 = Utf8               Lscala/collection/mutable/CollisionProofHashMap$RBNode;
   #22 = Utf8               Lscala/collection/mutable/CollisionProofHashMap$RBNode<TK;TV;>;
   #23 = Utf8               right
   #24 = Utf8               parent
   #25 = Utf8               ()Ljava/lang/Object;
   #26 = Utf8               ()TK;
   #27 = NameAndType        #11:#12       // key:Ljava/lang/Object;
   #28 = Fieldref           #2.#27        // scala/collection/mutable/CollisionProofHashMap$RBNode.key:Ljava/lang/Object;
   #29 = Utf8               this
   #30 = Utf8               key_$eq
   #31 = Utf8               (Ljava/lang/Object;)V
   #32 = Utf8               (TK;)V
   #33 = Utf8               x$1
   #34 = Utf8               ()I
   #35 = NameAndType        #14:#15       // hash:I
   #36 = Fieldref           #2.#35        // scala/collection/mutable/CollisionProofHashMap$RBNode.hash:I
   #37 = Utf8               hash_$eq
   #38 = Utf8               (I)V
   #39 = Utf8               ()TV;
   #40 = NameAndType        #16:#12       // value:Ljava/lang/Object;
   #41 = Fieldref           #2.#40        // scala/collection/mutable/CollisionProofHashMap$RBNode.value:Ljava/lang/Object;
   #42 = Utf8               value_$eq
   #43 = Utf8               (TV;)V
   #44 = Utf8               ()Z
   #45 = NameAndType        #18:#19       // red:Z
   #46 = Fieldref           #2.#45        // scala/collection/mutable/CollisionProofHashMap$RBNode.red:Z
   #47 = Utf8               red_$eq
   #48 = Utf8               (Z)V
   #49 = Utf8               ()Lscala/collection/mutable/CollisionProofHashMap$RBNode;
   #50 = Utf8               ()Lscala/collection/mutable/CollisionProofHashMap$RBNode<TK;TV;>;
   #51 = NameAndType        #20:#21       // left:Lscala/collection/mutable/CollisionProofHashMap$RBNode;
   #52 = Fieldref           #2.#51        // scala/collection/mutable/CollisionProofHashMap$RBNode.left:Lscala/collection/mutable/CollisionProofHashMap$RBNode;
   #53 = Utf8               left_$eq
   #54 = Utf8               (Lscala/collection/mutable/CollisionProofHashMap$RBNode;)V
   #55 = Utf8               (Lscala/collection/mutable/CollisionProofHashMap$RBNode<TK;TV;>;)V
   #56 = NameAndType        #23:#21       // right:Lscala/collection/mutable/CollisionProofHashMap$RBNode;
   #57 = Fieldref           #2.#56        // scala/collection/mutable/CollisionProofHashMap$RBNode.right:Lscala/collection/mutable/CollisionProofHashMap$RBNode;
   #58 = Utf8               right_$eq
   #59 = NameAndType        #24:#21       // parent:Lscala/collection/mutable/CollisionProofHashMap$RBNode;
   #60 = Fieldref           #2.#59        // scala/collection/mutable/CollisionProofHashMap$RBNode.parent:Lscala/collection/mutable/CollisionProofHashMap$RBNode;
   #61 = Utf8               parent_$eq
   #62 = Utf8               toString
   #63 = Utf8               ()Ljava/lang/String;
   #64 = Utf8               java/lang/StringBuilder
   #65 = Class              #64           // java/lang/StringBuilder
   #66 = Integer            18
   #67 = Utf8               <init>
   #68 = NameAndType        #67:#38       // "<init>":(I)V
   #69 = Methodref          #65.#68       // java/lang/StringBuilder."<init>":(I)V
   #70 = Utf8               RBNode(
   #71 = String             #70           // RBNode(
   #72 = Utf8               append
   #73 = Utf8               (Ljava/lang/String;)Ljava/lang/StringBuilder;
   #74 = NameAndType        #72:#73       // append:(Ljava/lang/String;)Ljava/lang/StringBuilder;
   #75 = Methodref          #65.#74       // java/lang/StringBuilder.append:(Ljava/lang/String;)Ljava/lang/StringBuilder;
   #76 = NameAndType        #11:#25       // key:()Ljava/lang/Object;
   #77 = Methodref          #2.#76        // scala/collection/mutable/CollisionProofHashMap$RBNode.key:()Ljava/lang/Object;
   #78 = Utf8               (Ljava/lang/Object;)Ljava/lang/StringBuilder;
   #79 = NameAndType        #72:#78       // append:(Ljava/lang/Object;)Ljava/lang/StringBuilder;
   #80 = Methodref          #65.#79       // java/lang/StringBuilder.append:(Ljava/lang/Object;)Ljava/lang/StringBuilder;
   #81 = Utf8               ,
   #82 = String             #81           // ,
   #83 = NameAndType        #14:#34       // hash:()I
   #84 = Methodref          #2.#83        // scala/collection/mutable/CollisionProofHashMap$RBNode.hash:()I
   #85 = Utf8               (I)Ljava/lang/StringBuilder;
   #86 = NameAndType        #72:#85       // append:(I)Ljava/lang/StringBuilder;
   #87 = Methodref          #65.#86       // java/lang/StringBuilder.append:(I)Ljava/lang/StringBuilder;
   #88 = NameAndType        #16:#25       // value:()Ljava/lang/Object;
   #89 = Methodref          #2.#88        // scala/collection/mutable/CollisionProofHashMap$RBNode.value:()Ljava/lang/Object;
   #90 = NameAndType        #18:#44       // red:()Z
   #91 = Methodref          #2.#90        // scala/collection/mutable/CollisionProofHashMap$RBNode.red:()Z
   #92 = Utf8               (Z)Ljava/lang/StringBuilder;
   #93 = NameAndType        #72:#92       // append:(Z)Ljava/lang/StringBuilder;
   #94 = Methodref          #65.#93       // java/lang/StringBuilder.append:(Z)Ljava/lang/StringBuilder;
   #95 = NameAndType        #20:#49       // left:()Lscala/collection/mutable/CollisionProofHashMap$RBNode;
   #96 = Methodref          #2.#95        // scala/collection/mutable/CollisionProofHashMap$RBNode.left:()Lscala/collection/mutable/CollisionProofHashMap$RBNode;
   #97 = NameAndType        #23:#49       // right:()Lscala/collection/mutable/CollisionProofHashMap$RBNode;
   #98 = Methodref          #2.#97        // scala/collection/mutable/CollisionProofHashMap$RBNode.right:()Lscala/collection/mutable/CollisionProofHashMap$RBNode;
   #99 = Utf8               )
  #100 = String             #99           // )
  #101 = NameAndType        #62:#63       // toString:()Ljava/lang/String;
  #102 = Methodref          #65.#101      // java/lang/StringBuilder.toString:()Ljava/lang/String;
  #103 = Utf8               getNode
  #104 = Utf8               (Ljava/lang/Object;ILscala/math/Ordering;)Lscala/collection/mutable/CollisionProofHashMap$RBNode;
  #105 = Utf8               (TK;ILscala/math/Ordering<TK;>;)Lscala/collection/mutable/CollisionProofHashMap$RBNode<TK;TV;>;
  #106 = Utf8               k
  #107 = Utf8               h
  #108 = Utf8               ord
  #109 = Utf8               scala/collection/mutable/CollisionProofHashMap$
  #110 = Class              #109          // scala/collection/mutable/CollisionProofHashMap$
  #111 = Utf8               MODULE$
  #112 = Utf8               Lscala/collection/mutable/CollisionProofHashMap$;
  #113 = NameAndType        #111:#112     // MODULE$:Lscala/collection/mutable/CollisionProofHashMap$;
  #114 = Fieldref           #110.#113     // scala/collection/mutable/CollisionProofHashMap$.MODULE$:Lscala/collection/mutable/CollisionProofHashMap$;
  #115 = Utf8               scala/math/Ordering
  #116 = Class              #115          // scala/math/Ordering
  #117 = Utf8               compare
  #118 = Utf8               (Ljava/lang/Object;Ljava/lang/Object;)I
  #119 = NameAndType        #117:#118     // compare:(Ljava/lang/Object;Ljava/lang/Object;)I
  #120 = InterfaceMethodref #116.#119     // scala/math/Ordering.compare:(Ljava/lang/Object;Ljava/lang/Object;)I
  #121 = Utf8               Lscala/math/Ordering;
  #122 = Utf8               foreach
  #123 = Utf8               (Lscala/Function1;)V
  #124 = Utf8               <U:Ljava/lang/Object;>(Lscala/Function1<Lscala/Tuple2<TK;TV;>;TU;>;)V
  #125 = Utf8               f
  #126 = NameAndType        #122:#123     // foreach:(Lscala/Function1;)V
  #127 = Methodref          #2.#126       // scala/collection/mutable/CollisionProofHashMap$RBNode.foreach:(Lscala/Function1;)V
  #128 = Utf8               scala/Tuple2
  #129 = Class              #128          // scala/Tuple2
  #130 = Utf8               (Ljava/lang/Object;Ljava/lang/Object;)V
  #131 = NameAndType        #67:#130      // "<init>":(Ljava/lang/Object;Ljava/lang/Object;)V
  #132 = Methodref          #129.#131     // scala/Tuple2."<init>":(Ljava/lang/Object;Ljava/lang/Object;)V
  #133 = Utf8               scala/Function1
  #134 = Class              #133          // scala/Function1
  #135 = Utf8               apply
  #136 = Utf8               (Ljava/lang/Object;)Ljava/lang/Object;
  #137 = NameAndType        #135:#136     // apply:(Ljava/lang/Object;)Ljava/lang/Object;
  #138 = InterfaceMethodref #134.#137     // scala/Function1.apply:(Ljava/lang/Object;)Ljava/lang/Object;
  #139 = Utf8               Lscala/Function1;
  #140 = Utf8               foreachEntry
  #141 = Utf8               (Lscala/Function2;)V
  #142 = Utf8               <U:Ljava/lang/Object;>(Lscala/Function2<TK;TV;TU;>;)V
  #143 = NameAndType        #140:#141     // foreachEntry:(Lscala/Function2;)V
  #144 = Methodref          #2.#143       // scala/collection/mutable/CollisionProofHashMap$RBNode.foreachEntry:(Lscala/Function2;)V
  #145 = Utf8               scala/Function2
  #146 = Class              #145          // scala/Function2
  #147 = Utf8               (Ljava/lang/Object;Ljava/lang/Object;)Ljava/lang/Object;
  #148 = NameAndType        #135:#147     // apply:(Ljava/lang/Object;Ljava/lang/Object;)Ljava/lang/Object;
  #149 = InterfaceMethodref #146.#148     // scala/Function2.apply:(Ljava/lang/Object;Ljava/lang/Object;)Ljava/lang/Object;
  #150 = Utf8               Lscala/Function2;
  #151 = Utf8               foreachNode
  #152 = Utf8               <U:Ljava/lang/Object;>(Lscala/Function1<Lscala/collection/mutable/CollisionProofHashMap$RBNode<TK;TV;>;TU;>;)V
  #153 = NameAndType        #151:#123     // foreachNode:(Lscala/Function1;)V
  #154 = Methodref          #2.#153       // scala/collection/mutable/CollisionProofHashMap$RBNode.foreachNode:(Lscala/Function1;)V
  #155 = Utf8               (Ljava/lang/Object;ILjava/lang/Object;ZLscala/collection/mutable/CollisionProofHashMap$RBNode;Lscala/collection/mutable/CollisionProofHashMap$RBNode;Lscala/collection/mutable/CollisionProofHashMap$RBNode;)V
  #156 = Utf8               (TK;ITV;ZLscala/collection/mutable/CollisionProofHashMap$RBNode<TK;TV;>;Lscala/collection/mutable/CollisionProofHashMap$RBNode<TK;TV;>;Lscala/collection/mutable/CollisionProofHashMap$RBNode<TK;TV;>;)V
  #157 = Utf8               ()V
  #158 = NameAndType        #67:#157      // "<init>":()V
  #159 = Methodref          #5.#158       // scala/collection/mutable/CollisionProofHashMap$Node."<init>":()V
  #160 = Utf8               Signature
  #161 = Utf8               Code
  #162 = Utf8               LineNumberTable
  #163 = Utf8               LocalVariableTable
  #164 = Utf8               MethodParameters
  #165 = Utf8               StackMapTable
  #166 = Utf8               InnerClasses
  #167 = Utf8               SourceFile
  #168 = Utf8               ScalaInlineInfo
  #169 = Utf8               Scala
{
  private K key;
    descriptor: Ljava/lang/Object;
    flags: (0x0002) ACC_PRIVATE
    Signature: #13                          // TK;

  private int hash;
    descriptor: I
    flags: (0x0002) ACC_PRIVATE

  private V value;
    descriptor: Ljava/lang/Object;
    flags: (0x0002) ACC_PRIVATE
    Signature: #17                          // TV;

  private boolean red;
    descriptor: Z
    flags: (0x0002) ACC_PRIVATE

  private scala.collection.mutable.CollisionProofHashMap$RBNode<K, V> left;
    descriptor: Lscala/collection/mutable/CollisionProofHashMap$RBNode;
    flags: (0x0002) ACC_PRIVATE
    Signature: #22                          // Lscala/collection/mutable/CollisionProofHashMap$RBNode<TK;TV;>;

  private scala.collection.mutable.CollisionProofHashMap$RBNode<K, V> right;
    descriptor: Lscala/collection/mutable/CollisionProofHashMap$RBNode;
    flags: (0x0002) ACC_PRIVATE
    Signature: #22                          // Lscala/collection/mutable/CollisionProofHashMap$RBNode<TK;TV;>;

  private scala.collection.mutable.CollisionProofHashMap$RBNode<K, V> parent;
    descriptor: Lscala/collection/mutable/CollisionProofHashMap$RBNode;
    flags: (0x0002) ACC_PRIVATE
    Signature: #22                          // Lscala/collection/mutable/CollisionProofHashMap$RBNode<TK;TV;>;

  public K key();
    descriptor: ()Ljava/lang/Object;
    flags: (0x0001) ACC_PUBLIC
    Code:
      stack=1, locals=1, args_size=1
         0: aload_0
         1: getfield      #28                 // Field key:Ljava/lang/Object;
         4: areturn
      LineNumberTable:
        line 791: 0
      LocalVariableTable:
        Start  Length  Slot  Name   Signature
            0       5     0  this   Lscala/collection/mutable/CollisionProofHashMap$RBNode;
    Signature: #26                          // ()TK;

  public void key_$eq(K);
    descriptor: (Ljava/lang/Object;)V
    flags: (0x0001) ACC_PUBLIC
    Code:
      stack=2, locals=2, args_size=2
         0: aload_0
         1: aload_1
         2: putfield      #28                 // Field key:Ljava/lang/Object;
         5: return
      LineNumberTable:
        line 791: 0
      LocalVariableTable:
        Start  Length  Slot  Name   Signature
            0       6     0  this   Lscala/collection/mutable/CollisionProofHashMap$RBNode;
            0       6     1   x$1   Ljava/lang/Object;
    Signature: #32                          // (TK;)V
    MethodParameters:
      Name                           Flags
      x$1                            final

  public int hash();
    descriptor: ()I
    flags: (0x0001) ACC_PUBLIC
    Code:
      stack=1, locals=1, args_size=1
         0: aload_0
         1: getfield      #36                 // Field hash:I
         4: ireturn
      LineNumberTable:
        line 791: 0
      LocalVariableTable:
        Start  Length  Slot  Name   Signature
            0       5     0  this   Lscala/collection/mutable/CollisionProofHashMap$RBNode;

  public void hash_$eq(int);
    descriptor: (I)V
    flags: (0x0001) ACC_PUBLIC
    Code:
      stack=2, locals=2, args_size=2
         0: aload_0
         1: iload_1
         2: putfield      #36                 // Field hash:I
         5: return
      LineNumberTable:
        line 791: 0
      LocalVariableTable:
        Start  Length  Slot  Name   Signature
            0       6     0  this   Lscala/collection/mutable/CollisionProofHashMap$RBNode;
            0       6     1   x$1   I
    MethodParameters:
      Name                           Flags
      x$1                            final

  public V value();
    descriptor: ()Ljava/lang/Object;
    flags: (0x0001) ACC_PUBLIC
    Code:
      stack=1, locals=1, args_size=1
         0: aload_0
         1: getfield      #41                 // Field value:Ljava/lang/Object;
         4: areturn
      LineNumberTable:
        line 791: 0
      LocalVariableTable:
        Start  Length  Slot  Name   Signature
            0       5     0  this   Lscala/collection/mutable/CollisionProofHashMap$RBNode;
    Signature: #39                          // ()TV;

  public void value_$eq(V);
    descriptor: (Ljava/lang/Object;)V
    flags: (0x0001) ACC_PUBLIC
    Code:
      stack=2, locals=2, args_size=2
         0: aload_0
         1: aload_1
         2: putfield      #41                 // Field value:Ljava/lang/Object;
         5: return
      LineNumberTable:
        line 791: 0
      LocalVariableTable:
        Start  Length  Slot  Name   Signature
            0       6     0  this   Lscala/collection/mutable/CollisionProofHashMap$RBNode;
            0       6     1   x$1   Ljava/lang/Object;
    Signature: #43                          // (TV;)V
    MethodParameters:
      Name                           Flags
      x$1                            final

  public boolean red();
    descriptor: ()Z
    flags: (0x0001) ACC_PUBLIC
    Code:
      stack=1, locals=1, args_size=1
         0: aload_0
         1: getfield      #46                 // Field red:Z
         4: ireturn
      LineNumberTable:
        line 791: 0
      LocalVariableTable:
        Start  Length  Slot  Name   Signature
            0       5     0  this   Lscala/collection/mutable/CollisionProofHashMap$RBNode;

  public void red_$eq(boolean);
    descriptor: (Z)V
    flags: (0x0001) ACC_PUBLIC
    Code:
      stack=2, locals=2, args_size=2
         0: aload_0
         1: iload_1
         2: putfield      #46                 // Field red:Z
         5: return
      LineNumberTable:
        line 791: 0
      LocalVariableTable:
        Start  Length  Slot  Name   Signature
            0       6     0  this   Lscala/collection/mutable/CollisionProofHashMap$RBNode;
            0       6     1   x$1   Z
    MethodParameters:
      Name                           Flags
      x$1                            final

  public scala.collection.mutable.CollisionProofHashMap$RBNode<K, V> left();
    descriptor: ()Lscala/collection/mutable/CollisionProofHashMap$RBNode;
    flags: (0x0001) ACC_PUBLIC
    Code:
      stack=1, locals=1, args_size=1
         0: aload_0
         1: getfield      #52                 // Field left:Lscala/collection/mutable/CollisionProofHashMap$RBNode;
         4: areturn
      LineNumberTable:
        line 791: 0
      LocalVariableTable:
        Start  Length  Slot  Name   Signature
            0       5     0  this   Lscala/collection/mutable/CollisionProofHashMap$RBNode;
    Signature: #50                          // ()Lscala/collection/mutable/CollisionProofHashMap$RBNode<TK;TV;>;

  public void left_$eq(scala.collection.mutable.CollisionProofHashMap$RBNode<K, V>);
    descriptor: (Lscala/collection/mutable/CollisionProofHashMap$RBNode;)V
    flags: (0x0001) ACC_PUBLIC
    Code:
      stack=2, locals=2, args_size=2
         0: aload_0
         1: aload_1
         2: putfield      #52                 // Field left:Lscala/collection/mutable/CollisionProofHashMap$RBNode;
         5: return
      LineNumberTable:
        line 791: 0
      LocalVariableTable:
        Start  Length  Slot  Name   Signature
            0       6     0  this   Lscala/collection/mutable/CollisionProofHashMap$RBNode;
            0       6     1   x$1   Lscala/collection/mutable/CollisionProofHashMap$RBNode;
    Signature: #55                          // (Lscala/collection/mutable/CollisionProofHashMap$RBNode<TK;TV;>;)V
    MethodParameters:
      Name                           Flags
      x$1                            final

  public scala.collection.mutable.CollisionProofHashMap$RBNode<K, V> right();
    descriptor: ()Lscala/collection/mutable/CollisionProofHashMap$RBNode;
    flags: (0x0001) ACC_PUBLIC
    Code:
      stack=1, locals=1, args_size=1
         0: aload_0
         1: getfield      #57                 // Field right:Lscala/collection/mutable/CollisionProofHashMap$RBNode;
         4: areturn
      LineNumberTable:
        line 791: 0
      LocalVariableTable:
        Start  Length  Slot  Name   Signature
            0       5     0  this   Lscala/collection/mutable/CollisionProofHashMap$RBNode;
    Signature: #50                          // ()Lscala/collection/mutable/CollisionProofHashMap$RBNode<TK;TV;>;

  public void right_$eq(scala.collection.mutable.CollisionProofHashMap$RBNode<K, V>);
    descriptor: (Lscala/collection/mutable/CollisionProofHashMap$RBNode;)V
    flags: (0x0001) ACC_PUBLIC
    Code:
      stack=2, locals=2, args_size=2
         0: aload_0
         1: aload_1
         2: putfield      #57                 // Field right:Lscala/collection/mutable/CollisionProofHashMap$RBNode;
         5: return
      LineNumberTable:
        line 791: 0
      LocalVariableTable:
        Start  Length  Slot  Name   Signature
            0       6     0  this   Lscala/collection/mutable/CollisionProofHashMap$RBNode;
            0       6     1   x$1   Lscala/collection/mutable/CollisionProofHashMap$RBNode;
    Signature: #55                          // (Lscala/collection/mutable/CollisionProofHashMap$RBNode<TK;TV;>;)V
    MethodParameters:
      Name                           Flags
      x$1                            final

  public scala.collection.mutable.CollisionProofHashMap$RBNode<K, V> parent();
    descriptor: ()Lscala/collection/mutable/CollisionProofHashMap$RBNode;
    flags: (0x0001) ACC_PUBLIC
    Code:
      stack=1, locals=1, args_size=1
         0: aload_0
         1: getfield      #60                 // Field parent:Lscala/collection/mutable/CollisionProofHashMap$RBNode;
         4: areturn
      LineNumberTable:
        line 791: 0
      LocalVariableTable:
        Start  Length  Slot  Name   Signature
            0       5     0  this   Lscala/collection/mutable/CollisionProofHashMap$RBNode;
    Signature: #50                          // ()Lscala/collection/mutable/CollisionProofHashMap$RBNode<TK;TV;>;

  public void parent_$eq(scala.collection.mutable.CollisionProofHashMap$RBNode<K, V>);
    descriptor: (Lscala/collection/mutable/CollisionProofHashMap$RBNode;)V
    flags: (0x0001) ACC_PUBLIC
    Code:
      stack=2, locals=2, args_size=2
         0: aload_0
         1: aload_1
         2: putfield      #60                 // Field parent:Lscala/collection/mutable/CollisionProofHashMap$RBNode;
         5: return
      LineNumberTable:
        line 791: 0
      LocalVariableTable:
        Start  Length  Slot  Name   Signature
            0       6     0  this   Lscala/collection/mutable/CollisionProofHashMap$RBNode;
            0       6     1   x$1   Lscala/collection/mutable/CollisionProofHashMap$RBNode;
    Signature: #55                          // (Lscala/collection/mutable/CollisionProofHashMap$RBNode<TK;TV;>;)V
    MethodParameters:
      Name                           Flags
      x$1                            final

  public java.lang.String toString();
    descriptor: ()Ljava/lang/String;
    flags: (0x0001) ACC_PUBLIC
    Code:
      stack=3, locals=1, args_size=1
         0: new           #65                 // class java/lang/StringBuilder
         3: dup
         4: ldc           #66                 // int 18
         6: invokespecial #69                 // Method java/lang/StringBuilder."<init>":(I)V
         9: ldc           #71                 // String RBNode(
        11: invokevirtual #75                 // Method java/lang/StringBuilder.append:(Ljava/lang/String;)Ljava/lang/StringBuilder;
        14: aload_0
        15: invokevirtual #77                 // Method key:()Ljava/lang/Object;
        18: invokevirtual #80                 // Method java/lang/StringBuilder.append:(Ljava/lang/Object;)Ljava/lang/StringBuilder;
        21: ldc           #82                 // String ,
        23: invokevirtual #75                 // Method java/lang/StringBuilder.append:(Ljava/lang/String;)Ljava/lang/StringBuilder;
        26: aload_0
        27: invokevirtual #84                 // Method hash:()I
        30: invokevirtual #87                 // Method java/lang/StringBuilder.append:(I)Ljava/lang/StringBuilder;
        33: ldc           #82                 // String ,
        35: invokevirtual #75                 // Method java/lang/StringBuilder.append:(Ljava/lang/String;)Ljava/lang/StringBuilder;
        38: aload_0
        39: invokevirtual #89                 // Method value:()Ljava/lang/Object;
        42: invokevirtual #80                 // Method java/lang/StringBuilder.append:(Ljava/lang/Object;)Ljava/lang/StringBuilder;
        45: ldc           #82                 // String ,
        47: invokevirtual #75                 // Method java/lang/StringBuilder.append:(Ljava/lang/String;)Ljava/lang/StringBuilder;
        50: aload_0
        51: invokevirtual #91                 // Method red:()Z
        54: invokevirtual #94                 // Method java/lang/StringBuilder.append:(Z)Ljava/lang/StringBuilder;
        57: ldc           #82                 // String ,
        59: invokevirtual #75                 // Method java/lang/StringBuilder.append:(Ljava/lang/String;)Ljava/lang/StringBuilder;
        62: aload_0
        63: invokevirtual #96                 // Method left:()Lscala/collection/mutable/CollisionProofHashMap$RBNode;
        66: invokevirtual #80                 // Method java/lang/StringBuilder.append:(Ljava/lang/Object;)Ljava/lang/StringBuilder;
        69: ldc           #82                 // String ,
        71: invokevirtual #75                 // Method java/lang/StringBuilder.append:(Ljava/lang/String;)Ljava/lang/StringBuilder;
        74: aload_0
        75: invokevirtual #98                 // Method right:()Lscala/collection/mutable/CollisionProofHashMap$RBNode;
        78: invokevirtual #80                 // Method java/lang/StringBuilder.append:(Ljava/lang/Object;)Ljava/lang/StringBuilder;
        81: ldc           #100                // String )
        83: invokevirtual #75                 // Method java/lang/StringBuilder.append:(Ljava/lang/String;)Ljava/lang/StringBuilder;
        86: invokevirtual #102                // Method java/lang/StringBuilder.toString:()Ljava/lang/String;
        89: areturn
      LineNumberTable:
        line 792: 0
      LocalVariableTable:
        Start  Length  Slot  Name   Signature
            0      90     0  this   Lscala/collection/mutable/CollisionProofHashMap$RBNode;

  public scala.collection.mutable.CollisionProofHashMap$RBNode<K, V> getNode(K, int, scala.math.Ordering<K>);
    descriptor: (Ljava/lang/Object;ILscala/math/Ordering;)Lscala/collection/mutable/CollisionProofHashMap$RBNode;
    flags: (0x0001) ACC_PUBLIC
    Code:
      stack=4, locals=5, args_size=4
         0: getstatic     #114                // Field scala/collection/mutable/CollisionProofHashMap$.MODULE$:Lscala/collection/mutable/CollisionProofHashMap$;
         3: pop
         4: aload_3
         5: aload_1
         6: aload_0
         7: invokevirtual #77                 // Method key:()Ljava/lang/Object;
        10: invokeinterface #120,  3          // InterfaceMethod scala/math/Ordering.compare:(Ljava/lang/Object;Ljava/lang/Object;)I
        15: istore        4
        17: iload         4
        19: iconst_0
        20: if_icmpge     46
        23: aload_0
        24: invokevirtual #96                 // Method left:()Lscala/collection/mutable/CollisionProofHashMap$RBNode;
        27: ifnull        44
        30: aload_0
        31: invokevirtual #96                 // Method left:()Lscala/collection/mutable/CollisionProofHashMap$RBNode;
        34: aload_1
        35: iload_2
        36: aload_3
        37: astore_3
        38: istore_2
        39: astore_1
        40: astore_0
        41: goto          0
        44: aconst_null
        45: areturn
        46: iload         4
        48: iconst_0
        49: if_icmple     75
        52: aload_0
        53: invokevirtual #98                 // Method right:()Lscala/collection/mutable/CollisionProofHashMap$RBNode;
        56: ifnull        73
        59: aload_0
        60: invokevirtual #98                 // Method right:()Lscala/collection/mutable/CollisionProofHashMap$RBNode;
        63: aload_1
        64: iload_2
        65: aload_3
        66: astore_3
        67: istore_2
        68: astore_1
        69: astore_0
        70: goto          0
        73: aconst_null
        74: areturn
        75: aload_0
        76: areturn
      StackMapTable: number_of_entries = 5
        frame_type = 0 /* same */
        frame_type = 252 /* append */
          offset_delta = 43
          locals = [ int ]
        frame_type = 1 /* same */
        frame_type = 26 /* same */
        frame_type = 1 /* same */
      LineNumberTable:
        line 795: 0
        line 780: 4
        line 796: 17
        line 797: 23
        line 798: 46
        line 799: 52
        line 800: 75
      LocalVariableTable:
        Start  Length  Slot  Name   Signature
            0      77     0  this   Lscala/collection/mutable/CollisionProofHashMap$RBNode;
            0      77     1     k   Ljava/lang/Object;
            0      77     2     h   I
            0      77     3   ord   Lscala/math/Ordering;
    Signature: #105                         // (TK;ILscala/math/Ordering<TK;>;)Lscala/collection/mutable/CollisionProofHashMap$RBNode<TK;TV;>;
    MethodParameters:
      Name                           Flags
      k                              final
      h                              final
      ord                            final

  public <U extends java.lang.Object> void foreach(scala.Function1<scala.Tuple2<K, V>, U>);
    descriptor: (Lscala/Function1;)V
    flags: (0x0001) ACC_PUBLIC
    Code:
      stack=5, locals=2, args_size=2
         0: aload_0
         1: invokevirtual #96                 // Method left:()Lscala/collection/mutable/CollisionProofHashMap$RBNode;
         4: ifnull        15
         7: aload_0
         8: invokevirtual #96                 // Method left:()Lscala/collection/mutable/CollisionProofHashMap$RBNode;
        11: aload_1
        12: invokevirtual #127                // Method foreach:(Lscala/Function1;)V
        15: aload_1
        16: new           #129                // class scala/Tuple2
        19: dup
        20: aload_0
        21: invokevirtual #77                 // Method key:()Ljava/lang/Object;
        24: aload_0
        25: invokevirtual #89                 // Method value:()Ljava/lang/Object;
        28: invokespecial #132                // Method scala/Tuple2."<init>":(Ljava/lang/Object;Ljava/lang/Object;)V
        31: invokeinterface #138,  2          // InterfaceMethod scala/Function1.apply:(Ljava/lang/Object;)Ljava/lang/Object;
        36: pop
        37: aload_0
        38: invokevirtual #98                 // Method right:()Lscala/collection/mutable/CollisionProofHashMap$RBNode;
        41: ifnull        54
        44: aload_0
        45: invokevirtual #98                 // Method right:()Lscala/collection/mutable/CollisionProofHashMap$RBNode;
        48: aload_1
        49: astore_1
        50: astore_0
        51: goto          0
        54: return
      StackMapTable: number_of_entries = 3
        frame_type = 0 /* same */
        frame_type = 14 /* same */
        frame_type = 38 /* same */
      LineNumberTable:
        line 804: 0
        line 805: 15
        line 806: 37
        line 803: 54
      LocalVariableTable:
        Start  Length  Slot  Name   Signature
            0      55     0  this   Lscala/collection/mutable/CollisionProofHashMap$RBNode;
            0      55     1     f   Lscala/Function1;
    Signature: #124                         // <U:Ljava/lang/Object;>(Lscala/Function1<Lscala/Tuple2<TK;TV;>;TU;>;)V
    MethodParameters:
      Name                           Flags
      f                              final

  public <U extends java.lang.Object> void foreachEntry(scala.Function2<K, V, U>);
    descriptor: (Lscala/Function2;)V
    flags: (0x0001) ACC_PUBLIC
    Code:
      stack=3, locals=2, args_size=2
         0: aload_0
         1: invokevirtual #96                 // Method left:()Lscala/collection/mutable/CollisionProofHashMap$RBNode;
         4: ifnull        15
         7: aload_0
         8: invokevirtual #96                 // Method left:()Lscala/collection/mutable/CollisionProofHashMap$RBNode;
        11: aload_1
        12: invokevirtual #144                // Method foreachEntry:(Lscala/Function2;)V
        15: aload_1
        16: aload_0
        17: invokevirtual #77                 // Method key:()Ljava/lang/Object;
        20: aload_0
        21: invokevirtual #89                 // Method value:()Ljava/lang/Object;
        24: invokeinterface #149,  3          // InterfaceMethod scala/Function2.apply:(Ljava/lang/Object;Ljava/lang/Object;)Ljava/lang/Object;
        29: pop
        30: aload_0
        31: invokevirtual #98                 // Method right:()Lscala/collection/mutable/CollisionProofHashMap$RBNode;
        34: ifnull        47
        37: aload_0
        38: invokevirtual #98                 // Method right:()Lscala/collection/mutable/CollisionProofHashMap$RBNode;
        41: aload_1
        42: astore_1
        43: astore_0
        44: goto          0
        47: return
      StackMapTable: number_of_entries = 3
        frame_type = 0 /* same */
        frame_type = 14 /* same */
        frame_type = 31 /* same */
      LineNumberTable:
        line 810: 0
        line 811: 15
        line 812: 30
        line 809: 47
      LocalVariableTable:
        Start  Length  Slot  Name   Signature
            0      48     0  this   Lscala/collection/mutable/CollisionProofHashMap$RBNode;
            0      48     1     f   Lscala/Function2;
    Signature: #142                         // <U:Ljava/lang/Object;>(Lscala/Function2<TK;TV;TU;>;)V
    MethodParameters:
      Name                           Flags
      f                              final

  public <U extends java.lang.Object> void foreachNode(scala.Function1<scala.collection.mutable.CollisionProofHashMap$RBNode<K, V>, U>);
    descriptor: (Lscala/Function1;)V
    flags: (0x0001) ACC_PUBLIC
    Code:
      stack=2, locals=2, args_size=2
         0: aload_0
         1: invokevirtual #96                 // Method left:()Lscala/collection/mutable/CollisionProofHashMap$RBNode;
         4: ifnull        15
         7: aload_0
         8: invokevirtual #96                 // Method left:()Lscala/collection/mutable/CollisionProofHashMap$RBNode;
        11: aload_1
        12: invokevirtual #154                // Method foreachNode:(Lscala/Function1;)V
        15: aload_1
        16: aload_0
        17: invokeinterface #138,  2          // InterfaceMethod scala/Function1.apply:(Ljava/lang/Object;)Ljava/lang/Object;
        22: pop
        23: aload_0
        24: invokevirtual #98                 // Method right:()Lscala/collection/mutable/CollisionProofHashMap$RBNode;
        27: ifnull        40
        30: aload_0
        31: invokevirtual #98                 // Method right:()Lscala/collection/mutable/CollisionProofHashMap$RBNode;
        34: aload_1
        35: astore_1
        36: astore_0
        37: goto          0
        40: return
      StackMapTable: number_of_entries = 3
        frame_type = 0 /* same */
        frame_type = 14 /* same */
        frame_type = 24 /* same */
      LineNumberTable:
        line 816: 0
        line 817: 15
        line 818: 23
        line 815: 40
      LocalVariableTable:
        Start  Length  Slot  Name   Signature
            0      41     0  this   Lscala/collection/mutable/CollisionProofHashMap$RBNode;
            0      41     1     f   Lscala/Function1;
    Signature: #152                         // <U:Ljava/lang/Object;>(Lscala/Function1<Lscala/collection/mutable/CollisionProofHashMap$RBNode<TK;TV;>;TU;>;)V
    MethodParameters:
      Name                           Flags
      f                              final

  public scala.collection.mutable.CollisionProofHashMap$RBNode(K, int, V, boolean, scala.collection.mutable.CollisionProofHashMap$RBNode<K, V>, scala.collection.mutable.CollisionProofHashMap$RBNode<K, V>, scala.collection.mutable.CollisionProofHashMap$RBNode<K, V>);
    descriptor: (Ljava/lang/Object;ILjava/lang/Object;ZLscala/collection/mutable/CollisionProofHashMap$RBNode;Lscala/collection/mutable/CollisionProofHashMap$RBNode;Lscala/collection/mutable/CollisionProofHashMap$RBNode;)V
    flags: (0x0001) ACC_PUBLIC
    Code:
      stack=2, locals=8, args_size=8
         0: aload_0
         1: aload_1
         2: putfield      #28                 // Field key:Ljava/lang/Object;
         5: aload_0
         6: iload_2
         7: putfield      #36                 // Field hash:I
        10: aload_0
        11: aload_3
        12: putfield      #41                 // Field value:Ljava/lang/Object;
        15: aload_0
        16: iload         4
        18: putfield      #46                 // Field red:Z
        21: aload_0
        22: aload         5
        24: putfield      #52                 // Field left:Lscala/collection/mutable/CollisionProofHashMap$RBNode;
        27: aload_0
        28: aload         6
        30: putfield      #57                 // Field right:Lscala/collection/mutable/CollisionProofHashMap$RBNode;
        33: aload_0
        34: aload         7
        36: putfield      #60                 // Field parent:Lscala/collection/mutable/CollisionProofHashMap$RBNode;
        39: aload_0
        40: invokespecial #159                // Method scala/collection/mutable/CollisionProofHashMap$Node."<init>":()V
        43: return
      LineNumberTable:
        line 791: 0
      LocalVariableTable:
        Start  Length  Slot  Name   Signature
            0      44     0  this   Lscala/collection/mutable/CollisionProofHashMap$RBNode;
            0      44     1   key   Ljava/lang/Object;
            0      44     2  hash   I
            0      44     3 value   Ljava/lang/Object;
            0      44     4   red   Z
            0      44     5  left   Lscala/collection/mutable/CollisionProofHashMap$RBNode;
            0      44     6 right   Lscala/collection/mutable/CollisionProofHashMap$RBNode;
            0      44     7 parent   Lscala/collection/mutable/CollisionProofHashMap$RBNode;
    Signature: #156                         // (TK;ITV;ZLscala/collection/mutable/CollisionProofHashMap$RBNode<TK;TV;>;Lscala/collection/mutable/CollisionProofHashMap$RBNode<TK;TV;>;Lscala/collection/mutable/CollisionProofHashMap$RBNode<TK;TV;>;)V
    MethodParameters:
      Name                           Flags
      key                            final
      hash                           final
      value                          final
      red                            final
      left                           final
      right                          final
      parent                         final
}
InnerClasses:
  public static abstract #9= #5 of #8;    // Node=class scala/collection/mutable/CollisionProofHashMap$Node of class scala/collection/mutable/CollisionProofHashMap
  public static final #10= #2 of #8;      // RBNode=class scala/collection/mutable/CollisionProofHashMap$RBNode of class scala/collection/mutable/CollisionProofHashMap
Signature: #3                           // <K:Ljava/lang/Object;V:Ljava/lang/Object;>Lscala/collection/mutable/CollisionProofHashMap$Node;
SourceFile: "CollisionProofHashMap.scala"
  ScalaInlineInfo: length = 0x68 (unknown attribute)
   01 01 00 14 00 43 00 9B 01 00 7A 00 7B 01 00 8C
   00 8D 01 00 97 00 7B 01 00 67 00 68 01 00 0E 00
   22 01 00 25 00 26 01 00 0B 00 19 01 00 1E 00 1F
   01 00 14 00 31 01 00 35 00 36 01 00 18 00 31 01
   00 3D 00 36 01 00 12 00 2C 01 00 2F 00 30 01 00
   17 00 31 01 00 3A 00 36 01 00 3E 00 3F 01 00 10
   00 19 01 00 2A 00 1F 01
  Scala: length = 0x0 (unknown attribute)

