Classfile /Users/mw/Projects/slang-braindump/.jar/jar11/assemble/slang-braindump/assemble/content/scala/collection/mutable/FlatHashTable$$anon$2.class
  Last modified May 29, 2022; size 838 bytes
  SHA-256 checksum 6fbc8fe78e25f05de968300117b24b9714f8b7c5a88832bc2fccdff2d2174d58
  Compiled from "FlatHashTable.scala"
public final class scala.collection.mutable.FlatHashTable$$anon$2 extends java.lang.ThreadLocal<scala.util.Random>
  minor version: 0
  major version: 52
  flags: (0x0031) ACC_PUBLIC, ACC_FINAL, ACC_SUPER
  this_class: #2                          // scala/collection/mutable/FlatHashTable$$anon$2
  super_class: #5                         // java/lang/ThreadLocal
  interfaces: 0, fields: 0, methods: 3, attributes: 6
Constant pool:
   #1 = Utf8               scala/collection/mutable/FlatHashTable$$anon$2
   #2 = Class              #1             // scala/collection/mutable/FlatHashTable$$anon$2
   #3 = Utf8               Ljava/lang/ThreadLocal<Lscala/util/Random;>;
   #4 = Utf8               java/lang/ThreadLocal
   #5 = Class              #4             // java/lang/ThreadLocal
   #6 = Utf8               FlatHashTable.scala
   #7 = Utf8               scala/collection/mutable/FlatHashTable$
   #8 = Class              #7             // scala/collection/mutable/FlatHashTable$
   #9 = Utf8               seedGenerator
  #10 = Utf8               ()Ljava/lang/ThreadLocal;
  #11 = NameAndType        #9:#10         // seedGenerator:()Ljava/lang/ThreadLocal;
  #12 = Utf8               initialValue
  #13 = Utf8               ()Lscala/util/Random;
  #14 = Utf8               scala/util/Random
  #15 = Class              #14            // scala/util/Random
  #16 = Utf8               <init>
  #17 = Utf8               ()V
  #18 = NameAndType        #16:#17        // "<init>":()V
  #19 = Methodref          #15.#18        // scala/util/Random."<init>":()V
  #20 = Utf8               this
  #21 = Utf8               Lscala/collection/mutable/FlatHashTable$$anon$2;
  #22 = Utf8               ()Ljava/lang/Object;
  #23 = NameAndType        #12:#13        // initialValue:()Lscala/util/Random;
  #24 = Methodref          #2.#23         // scala/collection/mutable/FlatHashTable$$anon$2.initialValue:()Lscala/util/Random;
  #25 = Methodref          #5.#18         // java/lang/ThreadLocal."<init>":()V
  #26 = Utf8               Code
  #27 = Utf8               LineNumberTable
  #28 = Utf8               LocalVariableTable
  #29 = Utf8               InnerClasses
  #30 = Utf8               EnclosingMethod
  #31 = Utf8               Signature
  #32 = Utf8               SourceFile
  #33 = Utf8               ScalaInlineInfo
  #34 = Utf8               Scala
{
  public scala.util.Random initialValue();
    descriptor: ()Lscala/util/Random;
    flags: (0x0001) ACC_PUBLIC
    Code:
      stack=2, locals=1, args_size=1
         0: new           #15                 // class scala/util/Random
         3: dup
         4: invokespecial #19                 // Method scala/util/Random."<init>":()V
         7: areturn
      LineNumberTable:
        line 381: 0
      LocalVariableTable:
        Start  Length  Slot  Name   Signature
            0       8     0  this   Lscala/collection/mutable/FlatHashTable$$anon$2;

  public java.lang.Object initialValue();
    descriptor: ()Ljava/lang/Object;
    flags: (0x1041) ACC_PUBLIC, ACC_BRIDGE, ACC_SYNTHETIC
    Code:
      stack=1, locals=1, args_size=1
         0: aload_0
         1: invokevirtual #24                 // Method initialValue:()Lscala/util/Random;
         4: areturn
      LineNumberTable:
        line 380: 0
      LocalVariableTable:
        Start  Length  Slot  Name   Signature
            0       5     0  this   Lscala/collection/mutable/FlatHashTable$$anon$2;

  public scala.collection.mutable.FlatHashTable$$anon$2();
    descriptor: ()V
    flags: (0x0001) ACC_PUBLIC
    Code:
      stack=1, locals=1, args_size=1
         0: aload_0
         1: invokespecial #25                 // Method java/lang/ThreadLocal."<init>":()V
         4: return
      LineNumberTable:
        line 380: 0
      LocalVariableTable:
        Start  Length  Slot  Name   Signature
            0       5     0  this   Lscala/collection/mutable/FlatHashTable$$anon$2;
}
InnerClasses:
  public final #2;                        // class scala/collection/mutable/FlatHashTable$$anon$2
EnclosingMethod: #8.#11                 // scala.collection.mutable.FlatHashTable$.seedGenerator
Signature: #3                           // Ljava/lang/ThreadLocal<Lscala/util/Random;>;
SourceFile: "FlatHashTable.scala"
  ScalaInlineInfo: length = 0x13 (unknown attribute)
   01 01 00 03 00 10 00 11 01 00 0C 00 16 01 00 0C
   00 0D 01
  Scala: length = 0x0 (unknown attribute)

