Classfile /Users/mw/Projects/slang-braindump/.jar/jar11/assemble/slang-braindump/assemble/content/scala/collection/mutable/FlatHashTable$HashUtils.class
  Last modified May 29, 2022; size 2434 bytes
  SHA-256 checksum c87f5129814ee21d37e4831b51b79e9acb397432426172a71838576bbfdc2392
  Compiled from "FlatHashTable.scala"
public interface scala.collection.mutable.FlatHashTable$HashUtils<A extends java.lang.Object>
  minor version: 0
  major version: 52
  flags: (0x0601) ACC_PUBLIC, ACC_INTERFACE, ACC_ABSTRACT
  this_class: #2                          // scala/collection/mutable/FlatHashTable$HashUtils
  super_class: #5                         // java/lang/Object
  interfaces: 0, fields: 0, methods: 11, attributes: 5
Constant pool:
   #1 = Utf8               scala/collection/mutable/FlatHashTable$HashUtils
   #2 = Class              #1             // scala/collection/mutable/FlatHashTable$HashUtils
   #3 = Utf8               <A:Ljava/lang/Object;>Ljava/lang/Object;
   #4 = Utf8               java/lang/Object
   #5 = Class              #4             // java/lang/Object
   #6 = Utf8               FlatHashTable.scala
   #7 = Utf8               scala/collection/mutable/FlatHashTable
   #8 = Class              #7             // scala/collection/mutable/FlatHashTable
   #9 = Utf8               HashUtils
  #10 = Utf8               scala/collection/mutable/FlatHashTable$NullSentinel$
  #11 = Class              #10            // scala/collection/mutable/FlatHashTable$NullSentinel$
  #12 = Utf8               NullSentinel$
  #13 = Utf8               sizeMapBucketBitSize$
  #14 = Utf8               (Lscala/collection/mutable/FlatHashTable$HashUtils;)I
  #15 = Utf8               $this
  #16 = Utf8               sizeMapBucketBitSize
  #17 = Utf8               ()I
  #18 = NameAndType        #16:#17        // sizeMapBucketBitSize:()I
  #19 = InterfaceMethodref #2.#18         // scala/collection/mutable/FlatHashTable$HashUtils.sizeMapBucketBitSize:()I
  #20 = Utf8               Lscala/collection/mutable/FlatHashTable$HashUtils;
  #21 = Utf8               this
  #22 = Utf8               sizeMapBucketSize$
  #23 = Utf8               sizeMapBucketSize
  #24 = NameAndType        #23:#17        // sizeMapBucketSize:()I
  #25 = InterfaceMethodref #2.#24         // scala/collection/mutable/FlatHashTable$HashUtils.sizeMapBucketSize:()I
  #26 = Utf8               improve$
  #27 = Utf8               (Lscala/collection/mutable/FlatHashTable$HashUtils;II)I
  #28 = Utf8               hcode
  #29 = Utf8               seed
  #30 = Utf8               improve
  #31 = Utf8               (II)I
  #32 = NameAndType        #30:#31        // improve:(II)I
  #33 = InterfaceMethodref #2.#32         // scala/collection/mutable/FlatHashTable$HashUtils.improve:(II)I
  #34 = Utf8               I
  #35 = Utf8               scala/util/hashing/package$
  #36 = Class              #35            // scala/util/hashing/package$
  #37 = Utf8               MODULE$
  #38 = Utf8               Lscala/util/hashing/package$;
  #39 = NameAndType        #37:#38        // MODULE$:Lscala/util/hashing/package$;
  #40 = Fieldref           #36.#39        // scala/util/hashing/package$.MODULE$:Lscala/util/hashing/package$;
  #41 = Utf8               byteswap32
  #42 = Utf8               (I)I
  #43 = NameAndType        #41:#42        // byteswap32:(I)I
  #44 = Methodref          #36.#43        // scala/util/hashing/package$.byteswap32:(I)I
  #45 = Utf8               java/lang/Integer
  #46 = Class              #45            // java/lang/Integer
  #47 = Utf8               rotateRight
  #48 = NameAndType        #47:#31        // rotateRight:(II)I
  #49 = Methodref          #46.#48        // java/lang/Integer.rotateRight:(II)I
  #50 = Utf8               elemToEntry$
  #51 = Utf8               (Lscala/collection/mutable/FlatHashTable$HashUtils;Ljava/lang/Object;)Ljava/lang/Object;
  #52 = Utf8               elem
  #53 = Utf8               elemToEntry
  #54 = Utf8               (Ljava/lang/Object;)Ljava/lang/Object;
  #55 = NameAndType        #53:#54        // elemToEntry:(Ljava/lang/Object;)Ljava/lang/Object;
  #56 = InterfaceMethodref #2.#55         // scala/collection/mutable/FlatHashTable$HashUtils.elemToEntry:(Ljava/lang/Object;)Ljava/lang/Object;
  #57 = Utf8               Ljava/lang/Object;
  #58 = Utf8               (TA;)Ljava/lang/Object;
  #59 = Utf8               Lscala/collection/mutable/FlatHashTable$NullSentinel$;
  #60 = NameAndType        #37:#59        // MODULE$:Lscala/collection/mutable/FlatHashTable$NullSentinel$;
  #61 = Fieldref           #11.#60        // scala/collection/mutable/FlatHashTable$NullSentinel$.MODULE$:Lscala/collection/mutable/FlatHashTable$NullSentinel$;
  #62 = Utf8               entryToElem$
  #63 = Utf8               entry
  #64 = Utf8               entryToElem
  #65 = NameAndType        #64:#54        // entryToElem:(Ljava/lang/Object;)Ljava/lang/Object;
  #66 = InterfaceMethodref #2.#65         // scala/collection/mutable/FlatHashTable$HashUtils.entryToElem:(Ljava/lang/Object;)Ljava/lang/Object;
  #67 = Utf8               (Ljava/lang/Object;)TA;
  #68 = Utf8               $init$
  #69 = Utf8               (Lscala/collection/mutable/FlatHashTable$HashUtils;)V
  #70 = Utf8               Code
  #71 = Utf8               LineNumberTable
  #72 = Utf8               LocalVariableTable
  #73 = Utf8               MethodParameters
  #74 = Utf8               StackMapTable
  #75 = Utf8               Signature
  #76 = Utf8               InnerClasses
  #77 = Utf8               SourceFile
  #78 = Utf8               ScalaInlineInfo
  #79 = Utf8               Scala
{
  public static int sizeMapBucketBitSize$(scala.collection.mutable.FlatHashTable$HashUtils);
    descriptor: (Lscala/collection/mutable/FlatHashTable$HashUtils;)I
    flags: (0x1009) ACC_PUBLIC, ACC_STATIC, ACC_SYNTHETIC
    Code:
      stack=1, locals=1, args_size=1
         0: aload_0
         1: invokespecial #19                 // InterfaceMethod sizeMapBucketBitSize:()I
         4: ireturn
      LineNumberTable:
        line 412: 0
      LocalVariableTable:
        Start  Length  Slot  Name   Signature
            0       5     0 $this   Lscala/collection/mutable/FlatHashTable$HashUtils;
    MethodParameters:
      Name                           Flags
      $this                          final synthetic

  public default int sizeMapBucketBitSize();
    descriptor: ()I
    flags: (0x0001) ACC_PUBLIC
    Code:
      stack=1, locals=1, args_size=1
         0: iconst_5
         1: ireturn
      LineNumberTable:
        line 412: 0
      LocalVariableTable:
        Start  Length  Slot  Name   Signature
            0       2     0  this   Lscala/collection/mutable/FlatHashTable$HashUtils;

  public static int sizeMapBucketSize$(scala.collection.mutable.FlatHashTable$HashUtils);
    descriptor: (Lscala/collection/mutable/FlatHashTable$HashUtils;)I
    flags: (0x1009) ACC_PUBLIC, ACC_STATIC, ACC_SYNTHETIC
    Code:
      stack=1, locals=1, args_size=1
         0: aload_0
         1: invokespecial #25                 // InterfaceMethod sizeMapBucketSize:()I
         4: ireturn
      LineNumberTable:
        line 414: 0
      LocalVariableTable:
        Start  Length  Slot  Name   Signature
            0       5     0 $this   Lscala/collection/mutable/FlatHashTable$HashUtils;
    MethodParameters:
      Name                           Flags
      $this                          final synthetic

  public default int sizeMapBucketSize();
    descriptor: ()I
    flags: (0x0001) ACC_PUBLIC
    Code:
      stack=2, locals=1, args_size=1
         0: iconst_1
         1: aload_0
         2: invokeinterface #19,  1           // InterfaceMethod sizeMapBucketBitSize:()I
         7: ishl
         8: ireturn
      LineNumberTable:
        line 414: 0
      LocalVariableTable:
        Start  Length  Slot  Name   Signature
            0       9     0  this   Lscala/collection/mutable/FlatHashTable$HashUtils;

  public static int improve$(scala.collection.mutable.FlatHashTable$HashUtils, int, int);
    descriptor: (Lscala/collection/mutable/FlatHashTable$HashUtils;II)I
    flags: (0x1009) ACC_PUBLIC, ACC_STATIC, ACC_SYNTHETIC
    Code:
      stack=3, locals=3, args_size=3
         0: aload_0
         1: iload_1
         2: iload_2
         3: invokespecial #33                 // InterfaceMethod improve:(II)I
         6: ireturn
      LineNumberTable:
        line 416: 0
      LocalVariableTable:
        Start  Length  Slot  Name   Signature
            0       7     0 $this   Lscala/collection/mutable/FlatHashTable$HashUtils;
            0       7     1 hcode   I
            0       7     2  seed   I
    MethodParameters:
      Name                           Flags
      $this                          final synthetic
      hcode                          final
      seed                           final

  public default int improve(int, int);
    descriptor: (II)I
    flags: (0x0001) ACC_PUBLIC
    Code:
      stack=2, locals=3, args_size=3
         0: getstatic     #40                 // Field scala/util/hashing/package$.MODULE$:Lscala/util/hashing/package$;
         3: iload_1
         4: invokevirtual #44                 // Method scala/util/hashing/package$.byteswap32:(I)I
         7: iload_2
         8: invokestatic  #49                 // Method java/lang/Integer.rotateRight:(II)I
        11: ireturn
      LineNumberTable:
        line 416: 0
      LocalVariableTable:
        Start  Length  Slot  Name   Signature
            0      12     0  this   Lscala/collection/mutable/FlatHashTable$HashUtils;
            0      12     1 hcode   I
            0      12     2  seed   I
    MethodParameters:
      Name                           Flags
      hcode                          final
      seed                           final

  public static java.lang.Object elemToEntry$(scala.collection.mutable.FlatHashTable$HashUtils, java.lang.Object);
    descriptor: (Lscala/collection/mutable/FlatHashTable$HashUtils;Ljava/lang/Object;)Ljava/lang/Object;
    flags: (0x1009) ACC_PUBLIC, ACC_STATIC, ACC_SYNTHETIC
    Code:
      stack=2, locals=2, args_size=2
         0: aload_0
         1: aload_1
         2: invokespecial #56                 // InterfaceMethod elemToEntry:(Ljava/lang/Object;)Ljava/lang/Object;
         5: areturn
      LineNumberTable:
        line 422: 0
      LocalVariableTable:
        Start  Length  Slot  Name   Signature
            0       6     0 $this   Lscala/collection/mutable/FlatHashTable$HashUtils;
            0       6     1  elem   Ljava/lang/Object;
    MethodParameters:
      Name                           Flags
      $this                          final synthetic
      elem                           final

  public default java.lang.Object elemToEntry(A);
    descriptor: (Ljava/lang/Object;)Ljava/lang/Object;
    flags: (0x0001) ACC_PUBLIC
    Code:
      stack=1, locals=2, args_size=2
         0: aload_1
         1: ifnonnull     10
         4: getstatic     #61                 // Field scala/collection/mutable/FlatHashTable$NullSentinel$.MODULE$:Lscala/collection/mutable/FlatHashTable$NullSentinel$;
         7: goto          11
        10: aload_1
        11: areturn
      StackMapTable: number_of_entries = 2
        frame_type = 10 /* same */
        frame_type = 64 /* same_locals_1_stack_item */
          stack = [ class java/lang/Object ]
      LineNumberTable:
        line 423: 0
      LocalVariableTable:
        Start  Length  Slot  Name   Signature
            0      12     0  this   Lscala/collection/mutable/FlatHashTable$HashUtils;
            0      12     1  elem   Ljava/lang/Object;
    Signature: #58                          // (TA;)Ljava/lang/Object;
    MethodParameters:
      Name                           Flags
      elem                           final

  public static java.lang.Object entryToElem$(scala.collection.mutable.FlatHashTable$HashUtils, java.lang.Object);
    descriptor: (Lscala/collection/mutable/FlatHashTable$HashUtils;Ljava/lang/Object;)Ljava/lang/Object;
    flags: (0x1009) ACC_PUBLIC, ACC_STATIC, ACC_SYNTHETIC
    Code:
      stack=2, locals=2, args_size=2
         0: aload_0
         1: aload_1
         2: invokespecial #66                 // InterfaceMethod entryToElem:(Ljava/lang/Object;)Ljava/lang/Object;
         5: areturn
      LineNumberTable:
        line 428: 0
      LocalVariableTable:
        Start  Length  Slot  Name   Signature
            0       6     0 $this   Lscala/collection/mutable/FlatHashTable$HashUtils;
            0       6     1 entry   Ljava/lang/Object;
    MethodParameters:
      Name                           Flags
      $this                          final synthetic
      entry                          final

  public default A entryToElem(java.lang.Object);
    descriptor: (Ljava/lang/Object;)Ljava/lang/Object;
    flags: (0x0001) ACC_PUBLIC
    Code:
      stack=2, locals=2, args_size=2
         0: getstatic     #61                 // Field scala/collection/mutable/FlatHashTable$NullSentinel$.MODULE$:Lscala/collection/mutable/FlatHashTable$NullSentinel$;
         3: aload_1
         4: if_acmpne     11
         7: aconst_null
         8: goto          12
        11: aload_1
        12: areturn
      StackMapTable: number_of_entries = 2
        frame_type = 11 /* same */
        frame_type = 64 /* same_locals_1_stack_item */
          stack = [ class java/lang/Object ]
      LineNumberTable:
        line 429: 0
      LocalVariableTable:
        Start  Length  Slot  Name   Signature
            0      13     0  this   Lscala/collection/mutable/FlatHashTable$HashUtils;
            0      13     1 entry   Ljava/lang/Object;
    Signature: #67                          // (Ljava/lang/Object;)TA;
    MethodParameters:
      Name                           Flags
      entry                          final

  public static void $init$(scala.collection.mutable.FlatHashTable$HashUtils);
    descriptor: (Lscala/collection/mutable/FlatHashTable$HashUtils;)V
    flags: (0x0009) ACC_PUBLIC, ACC_STATIC
    Code:
      stack=0, locals=1, args_size=1
         0: return
      LineNumberTable:
        line 411: 0
      LocalVariableTable:
        Start  Length  Slot  Name   Signature
            0       1     0 $this   Lscala/collection/mutable/FlatHashTable$HashUtils;
    MethodParameters:
      Name                           Flags
      $this                          final synthetic
}
InnerClasses:
  public static #9= #2 of #8;             // HashUtils=class scala/collection/mutable/FlatHashTable$HashUtils of class scala/collection/mutable/FlatHashTable
  private static #12= #11 of #8;          // NullSentinel$=class scala/collection/mutable/FlatHashTable$NullSentinel$ of class scala/collection/mutable/FlatHashTable
Signature: #3                           // <A:Ljava/lang/Object;>Ljava/lang/Object;
SourceFile: "FlatHashTable.scala"
  ScalaInlineInfo: length = 0x3B (unknown attribute)
   01 00 00 0B 00 44 00 45 01 00 35 00 36 01 00 32
   00 33 01 00 40 00 36 01 00 3E 00 33 01 00 1E 00
   1F 01 00 1A 00 1B 01 00 10 00 11 01 00 0D 00 0E
   01 00 17 00 11 01 00 16 00 0E 01
  Scala: length = 0x0 (unknown attribute)

