Classfile /Users/mw/Projects/slang-braindump/.jar/jar11/assemble/slang-braindump/assemble/content/scala/collection/mutable/HashMap$$anon$5.class
  Last modified May 29, 2022; size 1872 bytes
  SHA-256 checksum 6ffd608722f3c5d7c655fa674123cd6652736b87a42aecf2a9a42661c3766ac5
  Compiled from "HashMap.scala"
public final class scala.collection.mutable.HashMap$$anon$5 extends scala.collection.mutable.HashMap<K, V>.HashMapIterator<java.lang.Object>
  minor version: 0
  major version: 52
  flags: (0x0031) ACC_PUBLIC, ACC_FINAL, ACC_SUPER
  this_class: #2                          // scala/collection/mutable/HashMap$$anon$5
  super_class: #5                         // scala/collection/mutable/HashMap$HashMapIterator
  interfaces: 0, fields: 2, methods: 5, attributes: 6
Constant pool:
   #1 = Utf8               scala/collection/mutable/HashMap$$anon$5
   #2 = Class              #1             // scala/collection/mutable/HashMap$$anon$5
   #3 = Utf8               Lscala/collection/mutable/HashMap<TK;TV;>.HashMapIterator<Ljava/lang/Object;>;
   #4 = Utf8               scala/collection/mutable/HashMap$HashMapIterator
   #5 = Class              #4             // scala/collection/mutable/HashMap$HashMapIterator
   #6 = Utf8               HashMap.scala
   #7 = Utf8               scala/collection/mutable/HashMap
   #8 = Class              #7             // scala/collection/mutable/HashMap
   #9 = Utf8               hashCode
  #10 = Utf8               ()I
  #11 = NameAndType        #9:#10         // hashCode:()I
  #12 = Utf8               HashMapIterator
  #13 = Utf8               scala/collection/mutable/HashMap$Node
  #14 = Class              #13            // scala/collection/mutable/HashMap$Node
  #15 = Utf8               Node
  #16 = Utf8               hash
  #17 = Utf8               I
  #18 = Utf8               $outer
  #19 = Utf8               Lscala/collection/mutable/HashMap;
  #20 = NameAndType        #16:#17        // hash:I
  #21 = Fieldref           #2.#20         // scala/collection/mutable/HashMap$$anon$5.hash:I
  #22 = Utf8               this
  #23 = Utf8               Lscala/collection/mutable/HashMap$$anon$5;
  #24 = Utf8               hash_$eq
  #25 = Utf8               (I)V
  #26 = Utf8               x$1
  #27 = NameAndType        #16:#10        // hash:()I
  #28 = Methodref          #2.#27         // scala/collection/mutable/HashMap$$anon$5.hash:()I
  #29 = Utf8               extract
  #30 = Utf8               (Lscala/collection/mutable/HashMap$Node;)Ljava/lang/Object;
  #31 = Utf8               (Lscala/collection/mutable/HashMap$Node<TK;TV;>;)Ljava/lang/Object;
  #32 = Utf8               nd
  #33 = Utf8               scala/util/hashing/MurmurHash3$
  #34 = Class              #33            // scala/util/hashing/MurmurHash3$
  #35 = Utf8               MODULE$
  #36 = Utf8               Lscala/util/hashing/MurmurHash3$;
  #37 = NameAndType        #35:#36        // MODULE$:Lscala/util/hashing/MurmurHash3$;
  #38 = Fieldref           #34.#37        // scala/util/hashing/MurmurHash3$.MODULE$:Lscala/util/hashing/MurmurHash3$;
  #39 = NameAndType        #18:#19        // $outer:Lscala/collection/mutable/HashMap;
  #40 = Fieldref           #2.#39         // scala/collection/mutable/HashMap$$anon$5.$outer:Lscala/collection/mutable/HashMap;
  #41 = Methodref          #14.#27        // scala/collection/mutable/HashMap$Node.hash:()I
  #42 = Utf8               unimproveHash
  #43 = Utf8               (I)I
  #44 = NameAndType        #42:#43        // unimproveHash:(I)I
  #45 = Methodref          #8.#44         // scala/collection/mutable/HashMap.unimproveHash:(I)I
  #46 = Utf8               java/lang/Integer
  #47 = Class              #46            // java/lang/Integer
  #48 = Utf8               valueOf
  #49 = Utf8               (I)Ljava/lang/Integer;
  #50 = NameAndType        #48:#49        // valueOf:(I)Ljava/lang/Integer;
  #51 = Methodref          #47.#50        // java/lang/Integer.valueOf:(I)Ljava/lang/Integer;
  #52 = Utf8               value
  #53 = Utf8               ()Ljava/lang/Object;
  #54 = NameAndType        #52:#53        // value:()Ljava/lang/Object;
  #55 = Methodref          #14.#54        // scala/collection/mutable/HashMap$Node.value:()Ljava/lang/Object;
  #56 = Utf8               scala/runtime/Statics
  #57 = Class              #56            // scala/runtime/Statics
  #58 = Utf8               anyHash
  #59 = Utf8               (Ljava/lang/Object;)I
  #60 = NameAndType        #58:#59        // anyHash:(Ljava/lang/Object;)I
  #61 = Methodref          #57.#60        // scala/runtime/Statics.anyHash:(Ljava/lang/Object;)I
  #62 = Utf8               tuple2Hash
  #63 = Utf8               (Ljava/lang/Object;Ljava/lang/Object;)I
  #64 = NameAndType        #62:#63        // tuple2Hash:(Ljava/lang/Object;Ljava/lang/Object;)I
  #65 = Methodref          #34.#64        // scala/util/hashing/MurmurHash3$.tuple2Hash:(Ljava/lang/Object;Ljava/lang/Object;)I
  #66 = NameAndType        #24:#25        // hash_$eq:(I)V
  #67 = Methodref          #2.#66         // scala/collection/mutable/HashMap$$anon$5.hash_$eq:(I)V
  #68 = Utf8               Lscala/collection/mutable/HashMap$Node;
  #69 = Utf8               <init>
  #70 = Utf8               (Lscala/collection/mutable/HashMap;)V
  #71 = NameAndType        #69:#70        // "<init>":(Lscala/collection/mutable/HashMap;)V
  #72 = Methodref          #5.#71         // scala/collection/mutable/HashMap$HashMapIterator."<init>":(Lscala/collection/mutable/HashMap;)V
  #73 = Utf8               Code
  #74 = Utf8               LineNumberTable
  #75 = Utf8               LocalVariableTable
  #76 = Utf8               MethodParameters
  #77 = Utf8               Signature
  #78 = Utf8               StackMapTable
  #79 = Utf8               InnerClasses
  #80 = Utf8               EnclosingMethod
  #81 = Utf8               SourceFile
  #82 = Utf8               ScalaInlineInfo
  #83 = Utf8               Scala
{
  private int hash;
    descriptor: I
    flags: (0x0002) ACC_PRIVATE

  private final scala.collection.mutable.HashMap $outer;
    descriptor: Lscala/collection/mutable/HashMap;
    flags: (0x1012) ACC_PRIVATE, ACC_FINAL, ACC_SYNTHETIC

  public int hash();
    descriptor: ()I
    flags: (0x0001) ACC_PUBLIC
    Code:
      stack=1, locals=1, args_size=1
         0: aload_0
         1: getfield      #21                 // Field hash:I
         4: ireturn
      LineNumberTable:
        line 564: 0
      LocalVariableTable:
        Start  Length  Slot  Name   Signature
            0       5     0  this   Lscala/collection/mutable/HashMap$$anon$5;

  public void hash_$eq(int);
    descriptor: (I)V
    flags: (0x0001) ACC_PUBLIC
    Code:
      stack=2, locals=2, args_size=2
         0: aload_0
         1: iload_1
         2: putfield      #21                 // Field hash:I
         5: return
      LineNumberTable:
        line 564: 0
      LocalVariableTable:
        Start  Length  Slot  Name   Signature
            0       6     0  this   Lscala/collection/mutable/HashMap$$anon$5;
            0       6     1   x$1   I
    MethodParameters:
      Name                           Flags
      x$1                            final

  public int hashCode();
    descriptor: ()I
    flags: (0x0001) ACC_PUBLIC
    Code:
      stack=1, locals=1, args_size=1
         0: aload_0
         1: invokevirtual #28                 // Method hash:()I
         4: ireturn
      LineNumberTable:
        line 565: 0
      LocalVariableTable:
        Start  Length  Slot  Name   Signature
            0       5     0  this   Lscala/collection/mutable/HashMap$$anon$5;

  public java.lang.Object extract(scala.collection.mutable.HashMap$Node<K, V>);
    descriptor: (Lscala/collection/mutable/HashMap$Node;)Ljava/lang/Object;
    flags: (0x0001) ACC_PUBLIC
    Code:
      stack=4, locals=2, args_size=2
         0: aload_0
         1: getstatic     #38                 // Field scala/util/hashing/MurmurHash3$.MODULE$:Lscala/util/hashing/MurmurHash3$;
         4: aload_0
         5: getfield      #40                 // Field $outer:Lscala/collection/mutable/HashMap;
         8: aload_1
         9: invokevirtual #41                 // Method scala/collection/mutable/HashMap$Node.hash:()I
        12: invokevirtual #45                 // Method scala/collection/mutable/HashMap.unimproveHash:(I)I
        15: invokestatic  #51                 // Method java/lang/Integer.valueOf:(I)Ljava/lang/Integer;
        18: aload_1
        19: invokevirtual #55                 // Method scala/collection/mutable/HashMap$Node.value:()Ljava/lang/Object;
        22: invokestatic  #61                 // Method scala/runtime/Statics.anyHash:(Ljava/lang/Object;)I
        25: invokestatic  #51                 // Method java/lang/Integer.valueOf:(I)Ljava/lang/Integer;
        28: invokevirtual #65                 // Method scala/util/hashing/MurmurHash3$.tuple2Hash:(Ljava/lang/Object;Ljava/lang/Object;)I
        31: invokevirtual #67                 // Method hash_$eq:(I)V
        34: aload_0
        35: areturn
      LineNumberTable:
        line 567: 0
        line 568: 34
      LocalVariableTable:
        Start  Length  Slot  Name   Signature
            0      36     0  this   Lscala/collection/mutable/HashMap$$anon$5;
            0      36     1    nd   Lscala/collection/mutable/HashMap$Node;
    Signature: #31                          // (Lscala/collection/mutable/HashMap$Node<TK;TV;>;)Ljava/lang/Object;
    MethodParameters:
      Name                           Flags
      nd                             final

  public scala.collection.mutable.HashMap$$anon$5(scala.collection.mutable.HashMap);
    descriptor: (Lscala/collection/mutable/HashMap;)V
    flags: (0x0001) ACC_PUBLIC
    Code:
      stack=2, locals=2, args_size=2
         0: aload_1
         1: ifnonnull     6
         4: aconst_null
         5: athrow
         6: aload_0
         7: aload_1
         8: putfield      #40                 // Field $outer:Lscala/collection/mutable/HashMap;
        11: aload_0
        12: aload_1
        13: invokespecial #72                 // Method scala/collection/mutable/HashMap$HashMapIterator."<init>":(Lscala/collection/mutable/HashMap;)V
        16: aload_0
        17: iconst_0
        18: putfield      #21                 // Field hash:I
        21: return
      StackMapTable: number_of_entries = 1
        frame_type = 6 /* same */
      LineNumberTable:
        line 563: 0
        line 564: 16
        line 563: 21
      LocalVariableTable:
        Start  Length  Slot  Name   Signature
            0      22     0  this   Lscala/collection/mutable/HashMap$$anon$5;
            0      22     1 $outer   Lscala/collection/mutable/HashMap;
    MethodParameters:
      Name                           Flags
      $outer                         final synthetic
}
InnerClasses:
  public final #2;                        // class scala/collection/mutable/HashMap$$anon$5
  private abstract #12= #5 of #8;         // HashMapIterator=class scala/collection/mutable/HashMap$HashMapIterator of class scala/collection/mutable/HashMap
  public static final #15= #14 of #8;     // Node=class scala/collection/mutable/HashMap$Node of class scala/collection/mutable/HashMap
EnclosingMethod: #8.#11                 // scala.collection.mutable.HashMap.hashCode
Signature: #3                           // Lscala/collection/mutable/HashMap<TK;TV;>.HashMapIterator<Ljava/lang/Object;>;
SourceFile: "HashMap.scala"
  ScalaInlineInfo: length = 0x1D (unknown attribute)
   01 01 00 05 00 45 00 46 01 00 1D 00 1E 01 00 10
   00 0A 01 00 09 00 0A 01 00 18 00 19 01
  Scala: length = 0x0 (unknown attribute)

