Classfile /Users/mw/Projects/slang-braindump/.jar/jar11/assemble/slang-braindump/assemble/content/scala/collection/mutable/HashTable.class
  Last modified May 29, 2022; size 18268 bytes
  SHA-256 checksum c98c63d73373162de4fc05b20fc31754c078848594fe83eac8a231716034b069
  Compiled from "HashTable.scala"
public interface scala.collection.mutable.HashTable<A extends java.lang.Object, B extends java.lang.Object, Entry extends scala.collection.mutable.HashEntry<A, Entry>> extends scala.collection.mutable.HashTable$HashUtils<A>
  minor version: 0
  major version: 52
  flags: (0x0601) ACC_PUBLIC, ACC_INTERFACE, ACC_ABSTRACT
  this_class: #2                          // scala/collection/mutable/HashTable
  super_class: #5                         // java/lang/Object
  interfaces: 1, fields: 0, methods: 75, attributes: 6
Constant pool:
    #1 = Utf8               scala/collection/mutable/HashTable
    #2 = Class              #1            // scala/collection/mutable/HashTable
    #3 = Utf8               <A:Ljava/lang/Object;B:Ljava/lang/Object;Entry::Lscala/collection/mutable/HashEntry<TA;TEntry;>;>Ljava/lang/Object;Lscala/collection/mutable/HashTable$HashUtils<TA;>;
    #4 = Utf8               java/lang/Object
    #5 = Class              #4            // java/lang/Object
    #6 = Utf8               scala/collection/mutable/HashTable$HashUtils
    #7 = Class              #6            // scala/collection/mutable/HashTable$HashUtils
    #8 = Utf8               HashTable.scala
    #9 = Utf8               Lscala/reflect/ScalaSignature;
   #10 = Utf8               bytes
   #11 = Utf8               \u0006\u0005\t-d\u0001\u0003 @!\u0003\r\t!Q#\t\u000b1\u0004A\u0011A7\t\u000fu\u0003\u0001\u0019!C\t+\"I\u0011q\u0004\u0001A\u0002\u0013E\u0011\u0011\u0005\u0005\u000b\u0003O\u0001\u0001\u0019!C\t\u0003\u0006%\u0002BCA#\u0001\u0001\u0007I\u0011C!\u0002H!I\u00111\n\u0001A\u0002\u0013E\u0011)\u0016\u0005\u000b\u0003\u001b\u0002\u0001\u0019!C\t\u0003\u0006=\u0003\"B0\u0001\t\u000b)\u0006\"CA*\u0001\u0001\u0007I\u0011C!V\u0011)\t)\u0006\u0001a\u0001\n#\t\u0015q\u000b\u0005\n\u00037\u0002\u0001\u0019!C\t\u0003;B\u0011\"!\u0019\u0001\u0001\u0004%\t\"a\u0019\t\u0011\u0005\u001d\u0004\u00011A\u0005\u0012UC\u0011\"!\u001b\u0001\u0001\u0004%\t\"a\u001b\t\r\u0005=\u0004\u0001\"\u0005V\u0011\u0019\t\t\b\u0001C\t+\"9\u00111\u000f\u0001\u0005\n\u0005U\u0004BBA=\u0001\u0011%Q\u000b\u0003\u0004\u0002|\u0001!I!\u0016\u0005\t\u0003{\u0002A\u0011A!\u0002\u0000!A\u0011q\u0014\u0001\u0005\u0002\u0005\u000b\t\u000bC\u0004\u00028\u0002!)!!/\t\u0011\u0005u\u0006\u0001\"\u0006B\u0003\u007fC\u0001\"a2\u0001\t+\t\u0015\u0011\u001a\u0005\t\u0003\u001f\u0004AQC!\u0002R\"9\u0011q\u001b\u0001\u0005\u0002\u0005e\u0007bBAt\u0001\u0019\u0005\u0011\u0011\u001e\u0005\b\u0003_\u0004AQAAy\u0011!\t)\u0010\u0001C\u0003\u0003\u0006]\bbBA\u007f\u0001\u0011\u0005\u0011q \u0005\b\u0005\u0013\u0001A\u0011\u0001B\u0006\u0011\u0019\u0011Y\u0002\u0001C\u0001[\"9!Q\u0004\u0001\u0005\n\t}\u0001b\u0002B\u0013\u0001\u0011U!q\u0005\u0005\b\u0005W\u0001AQ\u0003B\u0017\u0011\u001d\u0011\t\u0004\u0001C\u000b\u0005gAqA!\u000f\u0001\t\u000b\tU\u000bC\u0004\u0003<\u0001!)B!\u0010\t\u000f\t\u0005\u0003\u0001\"\u0005\u0003D!1!q\t\u0001\u0005\u00165DqA!\u0013\u0001\t\u0003\tU\u000e\u0003\u0004\u0003L\u0001!)\"\u001c\u0005\b\u0005\u001b\u0002AQ\u0003B(\u0011\u001d\u00119\u0006\u0001C\t\u0005\u001fBqA!\u0017\u0001\t#\u0011Y\u0006\u0003\u0005\u0003f\u0001!)\"\u0011B4\u000f\u0019qu\b#\u0001B\u001f\u001a1ah\u0010E\u0001\u0003BCQ!\u0015\u0019\u0005\u0002MCa\u0001\u0016\u0019\u0005\u0006\u0005+\u0006BB-1\t\u000b\tU\u000b\u0003\u0004[a\u0011\u0015\u0011i\u0017\u0005\u0007AB\")!Q1\t\r\u0015\u0004DQA!g\r\u001dI\u0007\u0007%A\u0002\u0002)DQ\u0001\\\u001c\u0005\u00025DQ!]\u001c\u0005\u0016UCQA]\u001c\u0005\u0016UCaa]\u001c\u0005\u0012\u0005#\bbBA\u0003o\u0011U\u0011q\u0001\u0005\t\u0003#\u0001D\u0011A!\u0002\u0014\tI\u0001*Y:i)\u0006\u0014G.\u001a\u0006\u0003\u0001\u0006\u000bq!\\;uC\ndWM\u0003\u0002C\u0007\u0006Q1m\u001c7mK\u000e$\u0018n\u001c8\u000b\u0003\u0011\u000bQa]2bY\u0006,rARA\u000e\u0003G\fIdE\u0002\u0001\u000f.\u0003\"\u0001S%\u000e\u0003\rK!AS\"\u0003\r\u0005s\u0017PU3g!\u0011au\'!\u0007\u000f\u00055{S\"A \u0002\u0013!\u000b7\u000f\u001b+bE2,\u0007CA\'1\'\t\u0001t)\u0001\u0004=S:LGOP\u0002\u0001)\u0005y\u0015!\u00053fM\u0006,H\u000e\u001e\'pC\u00124\u0015m\u0019;peV\ta\u000b\u0005\u0002I/&\u0011\u0001l\u0011\u0002\u0004\u0013:$\u0018a\u00047pC\u00124\u0015m\u0019;pe\u0012+g.^7\u0002\u00199,w\u000f\u00165sKNDw\u000e\u001c3\u0015\u0007Ycf\fC\u0003^i\u0001\u0007a+A\u0006`Y>\fGMR1di>\u0014\b\"B05\u0001\u00041\u0016\u0001B:ju\u0016\f\u0001c]5{K\u001a{\'\u000f\u00165sKNDw\u000e\u001c3\u0015\u0007Y\u00137\rC\u0003^k\u0001\u0007a\u000bC\u0003ek\u0001\u0007a+A\u0002uQJ\f\u0001bY1qC\u000eLG/\u001f\u000b\u0003-\u001eDQ\u0001\u001b\u001cA\u0002Y\u000bA\"\u001a=qK\u000e$X\rZ*ju\u0016\u0014\u0011\u0002S1tQV#\u0018\u000e\\:\u0016\u0005-L8CA\u001cH\u0003\u0019!\u0013N\\5uIQ\ta\u000e\u0005\u0002I_&\u0011\u0001o\u0011\u0002\u0005+:LG/\u0001\u000btSj,W*\u00199Ck\u000e\\W\r\u001e\"jiNK\'0Z\u0001\u0012g&TX-T1q\u0005V\u001c7.\u001a;TSj,\u0017\u0001D3mK6D\u0015m\u001d5D_\u0012,GC\u0001,v\u0011\u001518\b1\u0001x\u0003\rYW-\u001f\t\u0003qfd\u0001\u0001B\u0003{o\t\u00071PA\u0004LKf$\u0016\u0010]3\u0012\u0005q|\bC\u0001%~\u0013\tq8IA\u0004O_RD\u0017N\\4\u0011\u0007!\u000b\t!C\u0002\u0002\u0004\r\u00131!\u00118z\u0003\u001dIW\u000e\u001d:pm\u0016$RAVA\u0005\u0003\u001bAa!a\u0003=\u0001\u00041\u0016!\u00025d_\u0012,\u0007BBA\by\u0001\u0007a+\u0001\u0003tK\u0016$\u0017A\u00068fqR\u0004vn]5uSZ,\u0007k\\<fe>3Gk^8\u0015\u0007Y\u000b)\u0002\u0003\u0004\u0002\u0018u\u0002\rAV\u0001\u0007i\u0006\u0014x-\u001a;\u0011\u0007a\fY\u0002\u0002\u0004\u0002\u001e\u0001\u0011\ra\u001f\u0002\u0002\u0003\u0006yq\f\\8bI\u001a\u000b7\r^8s?\u0012*\u0017\u000fF\u0002o\u0003GA\u0001\"!\n\u0004\u0003\u0003\u0005\rAV\u0001\u0004q\u0012\n\u0014!\u0002;bE2,WCAA\u0016!\u0015A\u0015QFA\u0019\u0013\r\tyc\u0011\u0002\u0006\u0003J\u0014\u0018-\u001f\t\b\u001b\u0006M\u0012\u0011DA\u001c\u0013\r\t)d\u0010\u0002\n\u0011\u0006\u001c\b.\u00128uef\u00042\u0001_A\u001d\t\u001d\tY\u0004\u0001b\u0001\u0003{\u0011Q!\u00128uef\fB!a\u0010\u00022A\u0019\u0001*!\u0011\n\u0007\u0005\r3I\u0001\u0003Ok2d\u0017!\u0003;bE2,w\fJ3r)\rq\u0017\u0011\n\u0005\n\u0003K)\u0011\u0011!a\u0001\u0003W\t\u0011\u0002^1cY\u0016\u001c\u0016N_3\u0002\u001bQ\f\'\r\\3TSj,w\fJ3r)\rq\u0017\u0011\u000b\u0005\t\u0003K9\u0011\u0011!a\u0001-\u0006IA\u000f\u001b:fg\"|G\u000eZ\u0001\u000ei\"\u0014Xm\u001d5pY\u0012|F%Z9\u0015\u00079\fI\u0006\u0003\u0005\u0002&)\t\t\u00111\u0001W\u0003\u001d\u0019\u0018N_3nCB,\"!a\u0018\u0011\t!\u000biCV\u0001\fg&TX-\\1q?\u0012*\u0017\u000fF\u0002o\u0003KB\u0011\"!\n\r\u0003\u0003\u0005\r!a\u0018\u0002\u0013M,W\r\u001a<bYV,\u0017!D:fK\u00124\u0018\r\\;f?\u0012*\u0017\u000fF\u0002o\u0003[B\u0001\"!\n\u000f\u0003\u0003\u0005\rAV\u0001\u000ei\u0006\u0014G.Z*ju\u0016\u001cV-\u001a3\u0002\u0017%t\u0017\u000e^5bYNK\'0Z\u0001\u0011S:LG/[1m)\"\u0014Xm\u001d5pY\u0012$2AVA<\u0011\u0015i\u0016\u00031\u0001W\u0003=Ig.\u001b;jC2\u001c\u0015\r]1dSRL\u0018A\u00057bgR\u0004v\u000e];mCR,G-\u00138eKb\fA!\u001b8jiR)a.!!\u0002\u0016\"9\u00111\u0011\u000bA\u0002\u0005\u0015\u0015AA5o!\u0011\t9)!%\u000e\u0005\u0005%%\u0002BAF\u0003\u001b\u000b!![8\u000b\u0005\u0005=\u0015\u0001\u00026bm\u0006LA!a%\u0002\n\n\trJ\u00196fGRLe\u000e];u\'R\u0014X-Y7\t\u0011\u0005]E\u0003\"a\u0001\u00033\u000b\u0011B]3bI\u0016sGO]=\u0011\u000b!\u000bY*a\u000e\n\u0007\u0005u5I\u0001\u0005=Eft\u0017-\\3?\u0003-\u0019XM]5bY&TX\rV8\u0015\u000b9\f\u0019+!,\t\u000f\u0005\u0015V\u00031\u0001\u0002(\u0006\u0019q.\u001e;\u0011\t\u0005\u001d\u0015\u0011V\u0005\u0005\u0003W\u000bII\u0001\nPE*,7\r^(viB,Ho\u0015;sK\u0006l\u0007bBAX+\u0001\u0007\u0011\u0011W\u0001\u000boJLG/Z#oiJL\bC\u0002%\u00024\u0006]b.C\u0002\u00026\u000e\u0013\u0011BR;oGRLwN\\\u0019\u0002\u0013\u0019Lg\u000eZ#oiJLH\u0003BA\u001c\u0003wCaA\u001e\fA\u0002\u0005e\u0011A\u00034j]\u0012,e\u000e\u001e:zaQ1\u0011qGAa\u0003\u0007DaA^\fA\u0002\u0005e\u0001BBAc/\u0001\u0007a+A\u0001i\u0003!\tG\rZ#oiJLHc\u00018\u0002L\"9\u0011Q\u001a\rA\u0002\u0005]\u0012!A3\u0002\u0013\u0005$G-\u00128uef\u0004D#\u00028\u0002T\u0006U\u0007bBAg3\u0001\u0007\u0011q\u0007\u0005\u0007\u0003\u000bL\u0002\u0019\u0001,\u0002\u001d\u0019Lg\u000eZ(s\u0003\u0012$WI\u001c;ssR1\u0011qGAn\u0003;DaA\u001e\u000eA\u0002\u0005e\u0001bBAp5\u0001\u0007\u0011\u0011]\u0001\u0006m\u0006dW/\u001a\t\u0004q\u0006\rHABAs\u0001\t\u00071PA\u0001C\u00039\u0019\'/Z1uK:+w/\u00128uef$b!a\u000e\u0002l\u00065\bB\u0002<\u001c\u0001\u0004\tI\u0002C\u0004\u0002`n\u0001\r!!9\u0002\u0017I,Wn\u001c<f\u000b:$(/\u001f\u000b\u0005\u0003o\t\u0019\u0010\u0003\u0004w9\u0001\u0007\u0011\u0011D\u0001\re\u0016lwN^3F]R\u0014\u0018\u0010\r\u000b\u0007\u0003o\tI0a?\t\rYl\u0002\u0019AA\r\u0011\u0019\t)-\ba\u0001-\u0006yQM\u001c;sS\u0016\u001c\u0018\n^3sCR|\'/\u0006\u0002\u0003\u0002A1!1\u0001B\u0003\u0003oi\u0011!Q\u0005\u0004\u0005\u000f\t%\u0001C%uKJ\fGo\u001c:\u0002\u0019\u0019|\'/Z1dQ\u0016sGO]=\u0016\t\t5!q\u0003\u000b\u0004]\n=\u0001b\u0002B\t?\u0001\u0007!1C\u0001\u0002MB9\u0001*a-\u00028\tU\u0001c\u0001=\u0003\u0018\u00111!\u0011D\u0010C\u0002m\u0014\u0011!V\u0001\u000bG2,\u0017M\u001d+bE2,\u0017A\u0002:fg&TX\rF\u0002o\u0005CAaAa\t\"\u0001\u00041\u0016a\u00028foNK\'0Z\u0001\r]:\u001c\u0016N_3NCB\fE\r\u001a\u000b\u0004]\n%\u0002BBAcE\u0001\u0007a+A\bo]NK\'0Z\'baJ+Wn\u001c<f)\rq\'q\u0006\u0005\u0007\u0003\u000b\u001c\u0003\u0019\u0001,\u0002\u001d9t7+\u001b>f\u001b\u0006\u0004(+Z:fiR\u0019aN!\u000e\t\r\t]B\u00051\u0001W\u0003-!\u0018M\u00197f\u0019\u0016tw\r\u001e5\u0002\'Q|G/\u00197TSj,W*\u00199Ck\u000e\\W\r^:\u0002\u001f\r\fGnY*ju\u0016l\u0015\r]*ju\u0016$2A\u0016B \u0011\u0019\u00119D\na\u0001-\u0006Y1/\u001b>f\u001b\u0006\u0004\u0018J\\5u)\rq\'Q\t\u0005\u0007\u0005o9\u0003\u0019\u0001,\u0002+ML\'0Z\'ba&s\u0017\u000e^!oIJ+\'-^5mI\u0006a\u0001O]5oiNK\'0Z\'ba\u0006q1/\u001b>f\u001b\u0006\u0004H)[:bE2,\u0017\u0001E5t\'&TX-T1q\t\u00164\u0017N\\3e+\t\u0011\t\u0006E\u0002I\u0005\'J1A!\u0016D\u0005\u001d\u0011un\u001c7fC:\f\u0011#\u00197xCf\u001c\u0018J\\5u\'&TX-T1q\u0003))G.Z7FcV\fGn\u001d\u000b\u0007\u0005#\u0012iF!\u0019\t\u000f\t}S\u00061\u0001\u0002\u001a\u0005!1.Z=2\u0011\u001d\u0011\u0019\'\fa\u0001\u00033\tAa[3ze\u0005)\u0011N\u001c3fqR\u0019aK!\u001b\t\r\u0005-a\u00061\u0001W\u0001
   #12 = Utf8               scala/collection/IterableFactory$ToFactory
   #13 = Class              #12           // scala/collection/IterableFactory$ToFactory
   #14 = Utf8               scala/collection/IterableFactory
   #15 = Class              #14           // scala/collection/IterableFactory
   #16 = Utf8               ToFactory
   #17 = Utf8               scala/collection/mutable/ArraySeq$ofInt
   #18 = Class              #17           // scala/collection/mutable/ArraySeq$ofInt
   #19 = Utf8               scala/collection/mutable/ArraySeq
   #20 = Class              #19           // scala/collection/mutable/ArraySeq
   #21 = Utf8               ofInt
   #22 = Utf8               scala/collection/mutable/HashTable$$anon$1
   #23 = Class              #22           // scala/collection/mutable/HashTable$$anon$1
   #24 = Utf8               HashUtils
   #25 = Utf8               _loadFactor
   #26 = Utf8               ()I
   #27 = Utf8               _loadFactor_$eq
   #28 = Utf8               (I)V
   #29 = Utf8               x$1
   #30 = Utf8               table
   #31 = Utf8               ()[Lscala/collection/mutable/HashEntry;
   #32 = Utf8               ()[Lscala/collection/mutable/HashEntry<TA;TEntry;>;
   #33 = Utf8               table_$eq
   #34 = Utf8               ([Lscala/collection/mutable/HashEntry;)V
   #35 = Utf8               ([Lscala/collection/mutable/HashEntry<TA;TEntry;>;)V
   #36 = Utf8               tableSize
   #37 = Utf8               tableSize_$eq
   #38 = Utf8               size$
   #39 = Utf8               (Lscala/collection/mutable/HashTable;)I
   #40 = Utf8               $this
   #41 = Utf8               size
   #42 = NameAndType        #41:#26       // size:()I
   #43 = InterfaceMethodref #2.#42        // scala/collection/mutable/HashTable.size:()I
   #44 = Utf8               Lscala/collection/mutable/HashTable;
   #45 = NameAndType        #36:#26       // tableSize:()I
   #46 = InterfaceMethodref #2.#45        // scala/collection/mutable/HashTable.tableSize:()I
   #47 = Utf8               this
   #48 = Utf8               threshold
   #49 = Utf8               threshold_$eq
   #50 = Utf8               sizemap
   #51 = Utf8               ()[I
   #52 = Utf8               sizemap_$eq
   #53 = Utf8               ([I)V
   #54 = Utf8               seedvalue
   #55 = Utf8               seedvalue_$eq
   #56 = Utf8               tableSizeSeed$
   #57 = Utf8               tableSizeSeed
   #58 = NameAndType        #57:#26       // tableSizeSeed:()I
   #59 = InterfaceMethodref #2.#58        // scala/collection/mutable/HashTable.tableSizeSeed:()I
   #60 = NameAndType        #30:#31       // table:()[Lscala/collection/mutable/HashEntry;
   #61 = InterfaceMethodref #2.#60        // scala/collection/mutable/HashTable.table:()[Lscala/collection/mutable/HashEntry;
   #62 = Utf8               java/lang/Integer
   #63 = Class              #62           // java/lang/Integer
   #64 = Utf8               bitCount
   #65 = Utf8               (I)I
   #66 = NameAndType        #64:#65       // bitCount:(I)I
   #67 = Methodref          #63.#66       // java/lang/Integer.bitCount:(I)I
   #68 = Utf8               initialSize$
   #69 = Utf8               initialSize
   #70 = NameAndType        #69:#26       // initialSize:()I
   #71 = InterfaceMethodref #2.#70        // scala/collection/mutable/HashTable.initialSize:()I
   #72 = Utf8               initialThreshold
   #73 = Utf8               scala/collection/mutable/HashTable$
   #74 = Class              #73           // scala/collection/mutable/HashTable$
   #75 = Utf8               MODULE$
   #76 = Utf8               Lscala/collection/mutable/HashTable$;
   #77 = NameAndType        #75:#76       // MODULE$:Lscala/collection/mutable/HashTable$;
   #78 = Fieldref           #74.#77       // scala/collection/mutable/HashTable$.MODULE$:Lscala/collection/mutable/HashTable$;
   #79 = Utf8               initialCapacity
   #80 = NameAndType        #79:#26       // initialCapacity:()I
   #81 = InterfaceMethodref #2.#80        // scala/collection/mutable/HashTable.initialCapacity:()I
   #82 = Utf8               I
   #83 = Utf8               numberOfLeadingZeros
   #84 = NameAndType        #83:#65       // numberOfLeadingZeros:(I)I
   #85 = Methodref          #63.#84       // java/lang/Integer.numberOfLeadingZeros:(I)I
   #86 = Utf8               capacity_expectedSize
   #87 = Utf8               scala$collection$mutable$HashTable$$lastPopulatedIndex$
   #88 = Utf8               scala$collection$mutable$HashTable$$lastPopulatedIndex
   #89 = NameAndType        #88:#26       // scala$collection$mutable$HashTable$$lastPopulatedIndex:()I
   #90 = InterfaceMethodref #2.#89        // scala/collection/mutable/HashTable.scala$collection$mutable$HashTable$$lastPopulatedIndex:()I
   #91 = Utf8               idx
   #92 = Utf8               init$
   #93 = Utf8               (Lscala/collection/mutable/HashTable;Ljava/io/ObjectInputStream;Lscala/Function0;)V
   #94 = Utf8               in
   #95 = Utf8               readEntry
   #96 = Utf8               init
   #97 = Utf8               (Ljava/io/ObjectInputStream;Lscala/Function0;)V
   #98 = NameAndType        #96:#97       // init:(Ljava/io/ObjectInputStream;Lscala/Function0;)V
   #99 = InterfaceMethodref #2.#98        // scala/collection/mutable/HashTable.init:(Ljava/io/ObjectInputStream;Lscala/Function0;)V
  #100 = Utf8               Ljava/io/ObjectInputStream;
  #101 = Utf8               Lscala/Function0;
  #102 = Utf8               (Ljava/io/ObjectInputStream;Lscala/Function0<TEntry;>;)V
  #103 = Utf8               java/io/ObjectInputStream
  #104 = Class              #103          // java/io/ObjectInputStream
  #105 = Utf8               readInt
  #106 = NameAndType        #105:#26      // readInt:()I
  #107 = Methodref          #104.#106     // java/io/ObjectInputStream.readInt:()I
  #108 = NameAndType        #27:#28       // _loadFactor_$eq:(I)V
  #109 = InterfaceMethodref #2.#108       // scala/collection/mutable/HashTable._loadFactor_$eq:(I)V
  #110 = Utf8               scala/Predef$
  #111 = Class              #110          // scala/Predef$
  #112 = Utf8               Lscala/Predef$;
  #113 = NameAndType        #75:#112      // MODULE$:Lscala/Predef$;
  #114 = Fieldref           #111.#113     // scala/Predef$.MODULE$:Lscala/Predef$;
  #115 = NameAndType        #25:#26       // _loadFactor:()I
  #116 = InterfaceMethodref #2.#115       // scala/collection/mutable/HashTable._loadFactor:()I
  #117 = Utf8               assert
  #118 = Utf8               (Z)V
  #119 = NameAndType        #117:#118     // assert:(Z)V
  #120 = Methodref          #111.#119     // scala/Predef$.assert:(Z)V
  #121 = NameAndType        #37:#28       // tableSize_$eq:(I)V
  #122 = InterfaceMethodref #2.#121       // scala/collection/mutable/HashTable.tableSize_$eq:(I)V
  #123 = NameAndType        #55:#28       // seedvalue_$eq:(I)V
  #124 = InterfaceMethodref #2.#123       // scala/collection/mutable/HashTable.seedvalue_$eq:(I)V
  #125 = Utf8               readBoolean
  #126 = Utf8               ()Z
  #127 = NameAndType        #125:#126     // readBoolean:()Z
  #128 = Methodref          #104.#127     // java/io/ObjectInputStream.readBoolean:()Z
  #129 = Utf8               scala/collection/mutable/HashEntry
  #130 = Class              #129          // scala/collection/mutable/HashEntry
  #131 = NameAndType        #33:#34       // table_$eq:([Lscala/collection/mutable/HashEntry;)V
  #132 = InterfaceMethodref #2.#131       // scala/collection/mutable/HashTable.table_$eq:([Lscala/collection/mutable/HashEntry;)V
  #133 = NameAndType        #49:#28       // threshold_$eq:(I)V
  #134 = InterfaceMethodref #2.#133       // scala/collection/mutable/HashTable.threshold_$eq:(I)V
  #135 = Utf8               sizeMapInit
  #136 = NameAndType        #135:#28      // sizeMapInit:(I)V
  #137 = InterfaceMethodref #2.#136       // scala/collection/mutable/HashTable.sizeMapInit:(I)V
  #138 = NameAndType        #52:#53       // sizemap_$eq:([I)V
  #139 = InterfaceMethodref #2.#138       // scala/collection/mutable/HashTable.sizemap_$eq:([I)V
  #140 = Utf8               scala/Function0
  #141 = Class              #140          // scala/Function0
  #142 = Utf8               apply
  #143 = Utf8               ()Ljava/lang/Object;
  #144 = NameAndType        #142:#143     // apply:()Ljava/lang/Object;
  #145 = InterfaceMethodref #141.#144     // scala/Function0.apply:()Ljava/lang/Object;
  #146 = Utf8               addEntry
  #147 = Utf8               (Lscala/collection/mutable/HashEntry;)V
  #148 = NameAndType        #146:#147     // addEntry:(Lscala/collection/mutable/HashEntry;)V
  #149 = InterfaceMethodref #2.#148       // scala/collection/mutable/HashTable.addEntry:(Lscala/collection/mutable/HashEntry;)V
  #150 = Utf8               smDefined
  #151 = Utf8               Z
  #152 = Utf8               index
  #153 = Utf8               sizeForThreshold__loadFactor
  #154 = Utf8               newThreshold__loadFactor
  #155 = Utf8               newThreshold_size
  #156 = Utf8               serializeTo$
  #157 = Utf8               (Lscala/collection/mutable/HashTable;Ljava/io/ObjectOutputStream;Lscala/Function1;)V
  #158 = Utf8               out
  #159 = Utf8               writeEntry
  #160 = Utf8               serializeTo
  #161 = Utf8               (Ljava/io/ObjectOutputStream;Lscala/Function1;)V
  #162 = NameAndType        #160:#161     // serializeTo:(Ljava/io/ObjectOutputStream;Lscala/Function1;)V
  #163 = InterfaceMethodref #2.#162       // scala/collection/mutable/HashTable.serializeTo:(Ljava/io/ObjectOutputStream;Lscala/Function1;)V
  #164 = Utf8               Ljava/io/ObjectOutputStream;
  #165 = Utf8               Lscala/Function1;
  #166 = Utf8               (Ljava/io/ObjectOutputStream;Lscala/Function1<TEntry;Lscala/runtime/BoxedUnit;>;)V
  #167 = Utf8               java/io/ObjectOutputStream
  #168 = Class              #167          // java/io/ObjectOutputStream
  #169 = Utf8               writeInt
  #170 = NameAndType        #169:#28      // writeInt:(I)V
  #171 = Methodref          #168.#170     // java/io/ObjectOutputStream.writeInt:(I)V
  #172 = NameAndType        #54:#26       // seedvalue:()I
  #173 = InterfaceMethodref #2.#172       // scala/collection/mutable/HashTable.seedvalue:()I
  #174 = Utf8               isSizeMapDefined
  #175 = NameAndType        #174:#126     // isSizeMapDefined:()Z
  #176 = InterfaceMethodref #2.#175       // scala/collection/mutable/HashTable.isSizeMapDefined:()Z
  #177 = Utf8               writeBoolean
  #178 = NameAndType        #177:#118     // writeBoolean:(Z)V
  #179 = Methodref          #168.#178     // java/io/ObjectOutputStream.writeBoolean:(Z)V
  #180 = Utf8               foreachEntry
  #181 = Utf8               (Lscala/Function1;)V
  #182 = NameAndType        #180:#181     // foreachEntry:(Lscala/Function1;)V
  #183 = InterfaceMethodref #2.#182       // scala/collection/mutable/HashTable.foreachEntry:(Lscala/Function1;)V
  #184 = Utf8               findEntry$
  #185 = Utf8               (Lscala/collection/mutable/HashTable;Ljava/lang/Object;)Lscala/collection/mutable/HashEntry;
  #186 = Utf8               key
  #187 = Utf8               findEntry
  #188 = Utf8               (Ljava/lang/Object;)Lscala/collection/mutable/HashEntry;
  #189 = NameAndType        #187:#188     // findEntry:(Ljava/lang/Object;)Lscala/collection/mutable/HashEntry;
  #190 = InterfaceMethodref #2.#189       // scala/collection/mutable/HashTable.findEntry:(Ljava/lang/Object;)Lscala/collection/mutable/HashEntry;
  #191 = Utf8               Ljava/lang/Object;
  #192 = Utf8               (TA;)TEntry;
  #193 = Utf8               elemHashCode
  #194 = Utf8               (Ljava/lang/Object;)I
  #195 = NameAndType        #193:#194     // elemHashCode:(Ljava/lang/Object;)I
  #196 = InterfaceMethodref #2.#195       // scala/collection/mutable/HashTable.elemHashCode:(Ljava/lang/Object;)I
  #197 = NameAndType        #152:#65      // index:(I)I
  #198 = InterfaceMethodref #2.#197       // scala/collection/mutable/HashTable.index:(I)I
  #199 = Utf8               findEntry0
  #200 = Utf8               (Ljava/lang/Object;I)Lscala/collection/mutable/HashEntry;
  #201 = NameAndType        #199:#200     // findEntry0:(Ljava/lang/Object;I)Lscala/collection/mutable/HashEntry;
  #202 = InterfaceMethodref #2.#201       // scala/collection/mutable/HashTable.findEntry0:(Ljava/lang/Object;I)Lscala/collection/mutable/HashEntry;
  #203 = Utf8               findEntry0$
  #204 = Utf8               (Lscala/collection/mutable/HashTable;Ljava/lang/Object;I)Lscala/collection/mutable/HashEntry;
  #205 = Utf8               h
  #206 = Utf8               (TA;I)TEntry;
  #207 = NameAndType        #186:#143     // key:()Ljava/lang/Object;
  #208 = InterfaceMethodref #130.#207     // scala/collection/mutable/HashEntry.key:()Ljava/lang/Object;
  #209 = Utf8               elemEquals
  #210 = Utf8               (Ljava/lang/Object;Ljava/lang/Object;)Z
  #211 = NameAndType        #209:#210     // elemEquals:(Ljava/lang/Object;Ljava/lang/Object;)Z
  #212 = InterfaceMethodref #2.#211       // scala/collection/mutable/HashTable.elemEquals:(Ljava/lang/Object;Ljava/lang/Object;)Z
  #213 = Utf8               next
  #214 = Utf8               ()Lscala/collection/mutable/HashEntry;
  #215 = NameAndType        #213:#214     // next:()Lscala/collection/mutable/HashEntry;
  #216 = InterfaceMethodref #130.#215     // scala/collection/mutable/HashEntry.next:()Lscala/collection/mutable/HashEntry;
  #217 = Utf8               e
  #218 = Utf8               Lscala/collection/mutable/HashEntry;
  #219 = Utf8               addEntry$
  #220 = Utf8               (Lscala/collection/mutable/HashTable;Lscala/collection/mutable/HashEntry;)V
  #221 = Utf8               (TEntry;)V
  #222 = Utf8               addEntry0
  #223 = Utf8               (Lscala/collection/mutable/HashEntry;I)V
  #224 = NameAndType        #222:#223     // addEntry0:(Lscala/collection/mutable/HashEntry;I)V
  #225 = InterfaceMethodref #2.#224       // scala/collection/mutable/HashTable.addEntry0:(Lscala/collection/mutable/HashEntry;I)V
  #226 = Utf8               addEntry0$
  #227 = Utf8               (Lscala/collection/mutable/HashTable;Lscala/collection/mutable/HashEntry;I)V
  #228 = Utf8               (TEntry;I)V
  #229 = Utf8               next_$eq
  #230 = NameAndType        #229:#147     // next_$eq:(Lscala/collection/mutable/HashEntry;)V
  #231 = InterfaceMethodref #130.#230     // scala/collection/mutable/HashEntry.next_$eq:(Lscala/collection/mutable/HashEntry;)V
  #232 = Utf8               nnSizeMapAdd
  #233 = NameAndType        #232:#28      // nnSizeMapAdd:(I)V
  #234 = InterfaceMethodref #2.#233       // scala/collection/mutable/HashTable.nnSizeMapAdd:(I)V
  #235 = NameAndType        #48:#26       // threshold:()I
  #236 = InterfaceMethodref #2.#235       // scala/collection/mutable/HashTable.threshold:()I
  #237 = Utf8               resize
  #238 = NameAndType        #237:#28      // resize:(I)V
  #239 = InterfaceMethodref #2.#238       // scala/collection/mutable/HashTable.resize:(I)V
  #240 = Utf8               findOrAddEntry$
  #241 = Utf8               (Lscala/collection/mutable/HashTable;Ljava/lang/Object;Ljava/lang/Object;)Lscala/collection/mutable/HashEntry;
  #242 = Utf8               value
  #243 = Utf8               findOrAddEntry
  #244 = Utf8               (Ljava/lang/Object;Ljava/lang/Object;)Lscala/collection/mutable/HashEntry;
  #245 = NameAndType        #243:#244     // findOrAddEntry:(Ljava/lang/Object;Ljava/lang/Object;)Lscala/collection/mutable/HashEntry;
  #246 = InterfaceMethodref #2.#245       // scala/collection/mutable/HashTable.findOrAddEntry:(Ljava/lang/Object;Ljava/lang/Object;)Lscala/collection/mutable/HashEntry;
  #247 = Utf8               (TA;TB;)TEntry;
  #248 = Utf8               createNewEntry
  #249 = NameAndType        #248:#244     // createNewEntry:(Ljava/lang/Object;Ljava/lang/Object;)Lscala/collection/mutable/HashEntry;
  #250 = InterfaceMethodref #2.#249       // scala/collection/mutable/HashTable.createNewEntry:(Ljava/lang/Object;Ljava/lang/Object;)Lscala/collection/mutable/HashEntry;
  #251 = Utf8               removeEntry$
  #252 = Utf8               removeEntry
  #253 = NameAndType        #252:#188     // removeEntry:(Ljava/lang/Object;)Lscala/collection/mutable/HashEntry;
  #254 = InterfaceMethodref #2.#253       // scala/collection/mutable/HashTable.removeEntry:(Ljava/lang/Object;)Lscala/collection/mutable/HashEntry;
  #255 = Utf8               removeEntry0
  #256 = NameAndType        #255:#200     // removeEntry0:(Ljava/lang/Object;I)Lscala/collection/mutable/HashEntry;
  #257 = InterfaceMethodref #2.#256       // scala/collection/mutable/HashTable.removeEntry0:(Ljava/lang/Object;I)Lscala/collection/mutable/HashEntry;
  #258 = Utf8               removeEntry0$
  #259 = Utf8               nnSizeMapRemove
  #260 = NameAndType        #259:#28      // nnSizeMapRemove:(I)V
  #261 = InterfaceMethodref #2.#260       // scala/collection/mutable/HashTable.nnSizeMapRemove:(I)V
  #262 = Utf8               e1
  #263 = Utf8               entriesIterator$
  #264 = Utf8               (Lscala/collection/mutable/HashTable;)Lscala/collection/Iterator;
  #265 = Utf8               entriesIterator
  #266 = Utf8               ()Lscala/collection/Iterator;
  #267 = NameAndType        #265:#266     // entriesIterator:()Lscala/collection/Iterator;
  #268 = InterfaceMethodref #2.#267       // scala/collection/mutable/HashTable.entriesIterator:()Lscala/collection/Iterator;
  #269 = Utf8               ()Lscala/collection/Iterator<TEntry;>;
  #270 = Utf8               <init>
  #271 = Utf8               (Lscala/collection/mutable/HashTable;)V
  #272 = NameAndType        #270:#271     // "<init>":(Lscala/collection/mutable/HashTable;)V
  #273 = Methodref          #23.#272      // scala/collection/mutable/HashTable$$anon$1."<init>":(Lscala/collection/mutable/HashTable;)V
  #274 = Utf8               foreachEntry$
  #275 = Utf8               (Lscala/collection/mutable/HashTable;Lscala/Function1;)V
  #276 = Utf8               f
  #277 = Utf8               <U:Ljava/lang/Object;>(Lscala/Function1<TEntry;TU;>;)V
  #278 = Utf8               scala/Function1
  #279 = Class              #278          // scala/Function1
  #280 = Utf8               (Ljava/lang/Object;)Ljava/lang/Object;
  #281 = NameAndType        #142:#280     // apply:(Ljava/lang/Object;)Ljava/lang/Object;
  #282 = InterfaceMethodref #279.#281     // scala/Function1.apply:(Ljava/lang/Object;)Ljava/lang/Object;
  #283 = Utf8               iterTable
  #284 = Utf8               [Lscala/collection/mutable/HashEntry;
  #285 = Utf8               es
  #286 = Class              #284          // "[Lscala/collection/mutable/HashEntry;"
  #287 = Utf8               clearTable$
  #288 = Utf8               clearTable
  #289 = Utf8               ()V
  #290 = NameAndType        #288:#289     // clearTable:()V
  #291 = InterfaceMethodref #2.#290       // scala/collection/mutable/HashTable.clearTable:()V
  #292 = Utf8               nnSizeMapReset
  #293 = NameAndType        #292:#28      // nnSizeMapReset:(I)V
  #294 = InterfaceMethodref #2.#293       // scala/collection/mutable/HashTable.nnSizeMapReset:(I)V
  #295 = Utf8               i
  #296 = Utf8               newSize
  #297 = Utf8               oldTable
  #298 = Utf8               nnSizeMapAdd$
  #299 = Utf8               (Lscala/collection/mutable/HashTable;I)V
  #300 = NameAndType        #50:#51       // sizemap:()[I
  #301 = InterfaceMethodref #2.#300       // scala/collection/mutable/HashTable.sizemap:()[I
  #302 = Utf8               nnSizeMapRemove$
  #303 = Utf8               nnSizeMapReset$
  #304 = Utf8               tableLength
  #305 = Utf8               java/util/Arrays
  #306 = Class              #305          // java/util/Arrays
  #307 = Utf8               fill
  #308 = Utf8               ([II)V
  #309 = NameAndType        #307:#308     // fill:([II)V
  #310 = Methodref          #306.#309     // java/util/Arrays.fill:([II)V
  #311 = Utf8               totalSizeMapBuckets$
  #312 = Utf8               totalSizeMapBuckets
  #313 = NameAndType        #312:#26      // totalSizeMapBuckets:()I
  #314 = InterfaceMethodref #2.#313       // scala/collection/mutable/HashTable.totalSizeMapBuckets:()I
  #315 = Utf8               calcSizeMapSize$
  #316 = Utf8               (Lscala/collection/mutable/HashTable;I)I
  #317 = Utf8               calcSizeMapSize
  #318 = NameAndType        #317:#65      // calcSizeMapSize:(I)I
  #319 = InterfaceMethodref #2.#318       // scala/collection/mutable/HashTable.calcSizeMapSize:(I)I
  #320 = Utf8               sizeMapInit$
  #321 = Utf8               sizeMapInitAndRebuild$
  #322 = Utf8               sizeMapInitAndRebuild
  #323 = NameAndType        #322:#289     // sizeMapInitAndRebuild:()V
  #324 = InterfaceMethodref #2.#323       // scala/collection/mutable/HashTable.sizeMapInitAndRebuild:()V
  #325 = Utf8               currbucketsize
  #326 = Utf8               tableidx
  #327 = Utf8               bucketidx
  #328 = Utf8               tbl
  #329 = Utf8               tableuntil
  #330 = Utf8               totalbuckets
  #331 = Utf8               printSizeMap$
  #332 = Utf8               printSizeMap
  #333 = NameAndType        #332:#289     // printSizeMap:()V
  #334 = InterfaceMethodref #2.#333       // scala/collection/mutable/HashTable.printSizeMap:()V
  #335 = Utf8               wrapIntArray
  #336 = Utf8               ([I)Lscala/collection/mutable/ArraySeq$ofInt;
  #337 = NameAndType        #335:#336     // wrapIntArray:([I)Lscala/collection/mutable/ArraySeq$ofInt;
  #338 = Methodref          #111.#337     // scala/Predef$.wrapIntArray:([I)Lscala/collection/mutable/ArraySeq$ofInt;
  #339 = Utf8               scala/collection/IterableFactory$
  #340 = Class              #339          // scala/collection/IterableFactory$
  #341 = Utf8               Lscala/collection/IterableFactory$;
  #342 = NameAndType        #75:#341      // MODULE$:Lscala/collection/IterableFactory$;
  #343 = Fieldref           #340.#342     // scala/collection/IterableFactory$.MODULE$:Lscala/collection/IterableFactory$;
  #344 = Utf8               scala/collection/immutable/List$
  #345 = Class              #344          // scala/collection/immutable/List$
  #346 = Utf8               Lscala/collection/immutable/List$;
  #347 = NameAndType        #75:#346      // MODULE$:Lscala/collection/immutable/List$;
  #348 = Fieldref           #345.#347     // scala/collection/immutable/List$.MODULE$:Lscala/collection/immutable/List$;
  #349 = Utf8               (Lscala/collection/IterableFactory;)V
  #350 = NameAndType        #270:#349     // "<init>":(Lscala/collection/IterableFactory;)V
  #351 = Methodref          #13.#350      // scala/collection/IterableFactory$ToFactory."<init>":(Lscala/collection/IterableFactory;)V
  #352 = Utf8               scala/collection/Factory
  #353 = Class              #352          // scala/collection/Factory
  #354 = Utf8               fromSpecific
  #355 = Utf8               (Lscala/collection/IterableOnce;)Ljava/lang/Object;
  #356 = NameAndType        #354:#355     // fromSpecific:(Lscala/collection/IterableOnce;)Ljava/lang/Object;
  #357 = InterfaceMethodref #353.#356     // scala/collection/Factory.fromSpecific:(Lscala/collection/IterableOnce;)Ljava/lang/Object;
  #358 = Utf8               scala/Console$
  #359 = Class              #358          // scala/Console$
  #360 = Utf8               Lscala/Console$;
  #361 = NameAndType        #75:#360      // MODULE$:Lscala/Console$;
  #362 = Fieldref           #359.#361     // scala/Console$.MODULE$:Lscala/Console$;
  #363 = Utf8               println
  #364 = Utf8               (Ljava/lang/Object;)V
  #365 = NameAndType        #363:#364     // println:(Ljava/lang/Object;)V
  #366 = Methodref          #359.#365     // scala/Console$.println:(Ljava/lang/Object;)V
  #367 = Utf8               to_this
  #368 = Utf8               Lscala/collection/AbstractIterable;
  #369 = Utf8               to_factory
  #370 = Utf8               Lscala/collection/Factory;
  #371 = Utf8               toFactory_factory
  #372 = Utf8               Lscala/collection/IterableFactory;
  #373 = Utf8               println_x
  #374 = Utf8               sizeMapDisable$
  #375 = Utf8               sizeMapDisable
  #376 = NameAndType        #375:#289     // sizeMapDisable:()V
  #377 = InterfaceMethodref #2.#376       // scala/collection/mutable/HashTable.sizeMapDisable:()V
  #378 = Utf8               isSizeMapDefined$
  #379 = Utf8               (Lscala/collection/mutable/HashTable;)Z
  #380 = Utf8               alwaysInitSizeMap$
  #381 = Utf8               alwaysInitSizeMap
  #382 = NameAndType        #381:#126     // alwaysInitSizeMap:()Z
  #383 = InterfaceMethodref #2.#382       // scala/collection/mutable/HashTable.alwaysInitSizeMap:()Z
  #384 = Utf8               elemEquals$
  #385 = Utf8               (Lscala/collection/mutable/HashTable;Ljava/lang/Object;Ljava/lang/Object;)Z
  #386 = Utf8               key1
  #387 = Utf8               key2
  #388 = Utf8               (TA;TA;)Z
  #389 = Utf8               scala/runtime/BoxesRunTime
  #390 = Class              #389          // scala/runtime/BoxesRunTime
  #391 = Utf8               equals
  #392 = NameAndType        #391:#210     // equals:(Ljava/lang/Object;Ljava/lang/Object;)Z
  #393 = Methodref          #390.#392     // scala/runtime/BoxesRunTime.equals:(Ljava/lang/Object;Ljava/lang/Object;)Z
  #394 = Utf8               index$
  #395 = Utf8               hcode
  #396 = Utf8               improve
  #397 = Utf8               (II)I
  #398 = NameAndType        #396:#397     // improve:(II)I
  #399 = InterfaceMethodref #2.#398       // scala/collection/mutable/HashTable.improve:(II)I
  #400 = Utf8               ones
  #401 = Utf8               exponent
  #402 = Utf8               $init$
  #403 = NameAndType        #72:#65       // initialThreshold:(I)I
  #404 = InterfaceMethodref #2.#403       // scala/collection/mutable/HashTable.initialThreshold:(I)I
  #405 = Utf8               MethodParameters
  #406 = Utf8               Signature
  #407 = Utf8               Code
  #408 = Utf8               LineNumberTable
  #409 = Utf8               LocalVariableTable
  #410 = Utf8               StackMapTable
  #411 = Utf8               InnerClasses
  #412 = Utf8               SourceFile
  #413 = Utf8               RuntimeVisibleAnnotations
  #414 = Utf8               ScalaInlineInfo
  #415 = Utf8               ScalaSig
{
  public abstract int _loadFactor();
    descriptor: ()I
    flags: (0x0401) ACC_PUBLIC, ACC_ABSTRACT

  public abstract void _loadFactor_$eq(int);
    descriptor: (I)V
    flags: (0x0401) ACC_PUBLIC, ACC_ABSTRACT
    MethodParameters:
      Name                           Flags
      x$1                            final

  public abstract scala.collection.mutable.HashEntry<A, Entry>[] table();
    descriptor: ()[Lscala/collection/mutable/HashEntry;
    flags: (0x0401) ACC_PUBLIC, ACC_ABSTRACT
    Signature: #32                          // ()[Lscala/collection/mutable/HashEntry<TA;TEntry;>;

  public abstract void table_$eq(scala.collection.mutable.HashEntry<A, Entry>[]);
    descriptor: ([Lscala/collection/mutable/HashEntry;)V
    flags: (0x0401) ACC_PUBLIC, ACC_ABSTRACT
    Signature: #35                          // ([Lscala/collection/mutable/HashEntry<TA;TEntry;>;)V
    MethodParameters:
      Name                           Flags
      x$1                            final

  public abstract int tableSize();
    descriptor: ()I
    flags: (0x0401) ACC_PUBLIC, ACC_ABSTRACT

  public abstract void tableSize_$eq(int);
    descriptor: (I)V
    flags: (0x0401) ACC_PUBLIC, ACC_ABSTRACT
    MethodParameters:
      Name                           Flags
      x$1                            final

  public static int size$(scala.collection.mutable.HashTable);
    descriptor: (Lscala/collection/mutable/HashTable;)I
    flags: (0x1009) ACC_PUBLIC, ACC_STATIC, ACC_SYNTHETIC
    Code:
      stack=1, locals=1, args_size=1
         0: aload_0
         1: invokespecial #43                 // InterfaceMethod size:()I
         4: ireturn
      LineNumberTable:
        line 55: 0
      LocalVariableTable:
        Start  Length  Slot  Name   Signature
            0       5     0 $this   Lscala/collection/mutable/HashTable;
    MethodParameters:
      Name                           Flags
      $this                          final synthetic

  public default int size();
    descriptor: ()I
    flags: (0x0001) ACC_PUBLIC
    Code:
      stack=1, locals=1, args_size=1
         0: aload_0
         1: invokeinterface #46,  1           // InterfaceMethod tableSize:()I
         6: ireturn
      LineNumberTable:
        line 55: 0
      LocalVariableTable:
        Start  Length  Slot  Name   Signature
            0       7     0  this   Lscala/collection/mutable/HashTable;

  public abstract int threshold();
    descriptor: ()I
    flags: (0x0401) ACC_PUBLIC, ACC_ABSTRACT

  public abstract void threshold_$eq(int);
    descriptor: (I)V
    flags: (0x0401) ACC_PUBLIC, ACC_ABSTRACT
    MethodParameters:
      Name                           Flags
      x$1                            final

  public abstract int[] sizemap();
    descriptor: ()[I
    flags: (0x0401) ACC_PUBLIC, ACC_ABSTRACT

  public abstract void sizemap_$eq(int[]);
    descriptor: ([I)V
    flags: (0x0401) ACC_PUBLIC, ACC_ABSTRACT
    MethodParameters:
      Name                           Flags
      x$1                            final

  public abstract int seedvalue();
    descriptor: ()I
    flags: (0x0401) ACC_PUBLIC, ACC_ABSTRACT

  public abstract void seedvalue_$eq(int);
    descriptor: (I)V
    flags: (0x0401) ACC_PUBLIC, ACC_ABSTRACT
    MethodParameters:
      Name                           Flags
      x$1                            final

  public static int tableSizeSeed$(scala.collection.mutable.HashTable);
    descriptor: (Lscala/collection/mutable/HashTable;)I
    flags: (0x1009) ACC_PUBLIC, ACC_STATIC, ACC_SYNTHETIC
    Code:
      stack=1, locals=1, args_size=1
         0: aload_0
         1: invokespecial #59                 // InterfaceMethod tableSizeSeed:()I
         4: ireturn
      LineNumberTable:
        line 67: 0
      LocalVariableTable:
        Start  Length  Slot  Name   Signature
            0       5     0 $this   Lscala/collection/mutable/HashTable;
    MethodParameters:
      Name                           Flags
      $this                          final synthetic

  public default int tableSizeSeed();
    descriptor: ()I
    flags: (0x0001) ACC_PUBLIC
    Code:
      stack=2, locals=1, args_size=1
         0: aload_0
         1: invokeinterface #61,  1           // InterfaceMethod table:()[Lscala/collection/mutable/HashEntry;
         6: arraylength
         7: iconst_1
         8: isub
         9: invokestatic  #67                 // Method java/lang/Integer.bitCount:(I)I
        12: ireturn
      LineNumberTable:
        line 67: 0
      LocalVariableTable:
        Start  Length  Slot  Name   Signature
            0      13     0  this   Lscala/collection/mutable/HashTable;

  public static int initialSize$(scala.collection.mutable.HashTable);
    descriptor: (Lscala/collection/mutable/HashTable;)I
    flags: (0x1009) ACC_PUBLIC, ACC_STATIC, ACC_SYNTHETIC
    Code:
      stack=1, locals=1, args_size=1
         0: aload_0
         1: invokespecial #71                 // InterfaceMethod initialSize:()I
         4: ireturn
      LineNumberTable:
        line 71: 0
      LocalVariableTable:
        Start  Length  Slot  Name   Signature
            0       5     0 $this   Lscala/collection/mutable/HashTable;
    MethodParameters:
      Name                           Flags
      $this                          final synthetic

  public default int initialSize();
    descriptor: ()I
    flags: (0x0001) ACC_PUBLIC
    Code:
      stack=1, locals=1, args_size=1
         0: bipush        16
         2: ireturn
      LineNumberTable:
        line 71: 0
      LocalVariableTable:
        Start  Length  Slot  Name   Signature
            0       3     0  this   Lscala/collection/mutable/HashTable;

  private int initialThreshold(int);
    descriptor: (I)I
    flags: (0x0002) ACC_PRIVATE
    Code:
      stack=4, locals=2, args_size=2
         0: getstatic     #78                 // Field scala/collection/mutable/HashTable$.MODULE$:Lscala/collection/mutable/HashTable$;
         3: pop
         4: aload_0
         5: invokespecial #81                 // InterfaceMethod initialCapacity:()I
         8: i2l
         9: iload_1
        10: i2l
        11: lmul
        12: sipush        1000
        15: i2l
        16: ldiv
        17: l2i
        18: ireturn
      LineNumberTable:
        line 75: 0
        line 377: 8
        line 375: 12
        line 377: 15
        line 75: 18
      LocalVariableTable:
        Start  Length  Slot  Name   Signature
            0      19     0  this   Lscala/collection/mutable/HashTable;
            0      19     1 _loadFactor   I
    MethodParameters:
      Name                           Flags
      _loadFactor                    final

  private int initialCapacity();
    descriptor: ()I
    flags: (0x0002) ACC_PRIVATE
    Code:
      stack=3, locals=2, args_size=1
         0: getstatic     #78                 // Field scala/collection/mutable/HashTable$.MODULE$:Lscala/collection/mutable/HashTable$;
         3: pop
         4: aload_0
         5: invokeinterface #71,  1           // InterfaceMethod initialSize:()I
        10: istore_1
        11: iconst_1
        12: iload_1
        13: iconst_1
        14: isub
        15: invokestatic  #85                 // Method java/lang/Integer.numberOfLeadingZeros:(I)I
        18: ineg
        19: ishl
        20: ireturn
      LineNumberTable:
        line 77: 0
        line 409: 11
        line 77: 20
      LocalVariableTable:
        Start  Length  Slot  Name   Signature
            0      21     0  this   Lscala/collection/mutable/HashTable;
           11       9     1 capacity_expectedSize   I

  public static int scala$collection$mutable$HashTable$$lastPopulatedIndex$(scala.collection.mutable.HashTable);
    descriptor: (Lscala/collection/mutable/HashTable;)I
    flags: (0x1009) ACC_PUBLIC, ACC_STATIC, ACC_SYNTHETIC
    Code:
      stack=1, locals=1, args_size=1
         0: aload_0
         1: invokespecial #90                 // InterfaceMethod scala$collection$mutable$HashTable$$lastPopulatedIndex:()I
         4: ireturn
      LineNumberTable:
        line 79: 0
      LocalVariableTable:
        Start  Length  Slot  Name   Signature
            0       5     0 $this   Lscala/collection/mutable/HashTable;
    MethodParameters:
      Name                           Flags
      $this                          final synthetic

  public default int scala$collection$mutable$HashTable$$lastPopulatedIndex();
    descriptor: ()I
    flags: (0x0001) ACC_PUBLIC
    Code:
      stack=2, locals=2, args_size=1
         0: aload_0
         1: invokeinterface #61,  1           // InterfaceMethod table:()[Lscala/collection/mutable/HashEntry;
         6: arraylength
         7: iconst_1
         8: isub
         9: istore_1
        10: aload_0
        11: invokeinterface #61,  1           // InterfaceMethod table:()[Lscala/collection/mutable/HashEntry;
        16: iload_1
        17: aaload
        18: ifnonnull     32
        21: iload_1
        22: iconst_0
        23: if_icmple     32
        26: iinc          1, -1
        29: goto          10
        32: iload_1
        33: ireturn
      StackMapTable: number_of_entries = 2
        frame_type = 252 /* append */
          offset_delta = 10
          locals = [ int ]
        frame_type = 21 /* same */
      LineNumberTable:
        line 80: 0
        line 81: 10
        line 82: 26
        line 84: 32
      LocalVariableTable:
        Start  Length  Slot  Name   Signature
           10      23     1   idx   I
            0      34     0  this   Lscala/collection/mutable/HashTable;

  public static void init$(scala.collection.mutable.HashTable, java.io.ObjectInputStream, scala.Function0);
    descriptor: (Lscala/collection/mutable/HashTable;Ljava/io/ObjectInputStream;Lscala/Function0;)V
    flags: (0x1009) ACC_PUBLIC, ACC_STATIC, ACC_SYNTHETIC
    Code:
      stack=3, locals=3, args_size=3
         0: aload_0
         1: aload_1
         2: aload_2
         3: invokespecial #99                 // InterfaceMethod init:(Ljava/io/ObjectInputStream;Lscala/Function0;)V
         6: return
      LineNumberTable:
        line 91: 0
      LocalVariableTable:
        Start  Length  Slot  Name   Signature
            0       7     0 $this   Lscala/collection/mutable/HashTable;
            0       7     1    in   Ljava/io/ObjectInputStream;
            0       7     2 readEntry   Lscala/Function0;
    MethodParameters:
      Name                           Flags
      $this                          final synthetic
      in                             final
      readEntry                      final

  public default void init(java.io.ObjectInputStream, scala.Function0<Entry>);
    descriptor: (Ljava/io/ObjectInputStream;Lscala/Function0;)V
    flags: (0x0001) ACC_PUBLIC
    Code:
      stack=5, locals=10, args_size=3
         0: aload_0
         1: aload_1
         2: invokevirtual #107                // Method java/io/ObjectInputStream.readInt:()I
         5: invokeinterface #109,  2          // InterfaceMethod _loadFactor_$eq:(I)V
        10: getstatic     #114                // Field scala/Predef$.MODULE$:Lscala/Predef$;
        13: aload_0
        14: invokeinterface #116,  1          // InterfaceMethod _loadFactor:()I
        19: iconst_0
        20: if_icmple     27
        23: iconst_1
        24: goto          28
        27: iconst_0
        28: invokevirtual #120                // Method scala/Predef$.assert:(Z)V
        31: aload_1
        32: invokevirtual #107                // Method java/io/ObjectInputStream.readInt:()I
        35: istore_3
        36: aload_0
        37: iconst_0
        38: invokeinterface #122,  2          // InterfaceMethod tableSize_$eq:(I)V
        43: getstatic     #114                // Field scala/Predef$.MODULE$:Lscala/Predef$;
        46: iload_3
        47: iconst_0
        48: if_icmplt     55
        51: iconst_1
        52: goto          56
        55: iconst_0
        56: invokevirtual #120                // Method scala/Predef$.assert:(Z)V
        59: aload_0
        60: aload_1
        61: invokevirtual #107                // Method java/io/ObjectInputStream.readInt:()I
        64: invokeinterface #124,  2          // InterfaceMethod seedvalue_$eq:(I)V
        69: aload_1
        70: invokevirtual #128                // Method java/io/ObjectInputStream.readBoolean:()Z
        73: istore        4
        75: aload_0
        76: getstatic     #78                 // Field scala/collection/mutable/HashTable$.MODULE$:Lscala/collection/mutable/HashTable$;
        79: pop
        80: getstatic     #78                 // Field scala/collection/mutable/HashTable$.MODULE$:Lscala/collection/mutable/HashTable$;
        83: pop
        84: aload_0
        85: invokeinterface #116,  1          // InterfaceMethod _loadFactor:()I
        90: istore        6
        92: iload_3
        93: i2l
        94: sipush        1000
        97: i2l
        98: lmul
        99: iload         6
       101: i2l
       102: ldiv
       103: l2i
       104: istore        7
       106: iconst_1
       107: iload         7
       109: iconst_1
       110: isub
       111: invokestatic  #85                 // Method java/lang/Integer.numberOfLeadingZeros:(I)I
       114: ineg
       115: ishl
       116: anewarray     #130                // class scala/collection/mutable/HashEntry
       119: invokeinterface #132,  2          // InterfaceMethod table_$eq:([Lscala/collection/mutable/HashEntry;)V
       124: aload_0
       125: getstatic     #78                 // Field scala/collection/mutable/HashTable$.MODULE$:Lscala/collection/mutable/HashTable$;
       128: pop
       129: aload_0
       130: invokeinterface #116,  1          // InterfaceMethod _loadFactor:()I
       135: aload_0
       136: invokeinterface #61,  1           // InterfaceMethod table:()[Lscala/collection/mutable/HashEntry;
       141: arraylength
       142: istore        9
       144: istore        8
       146: iload         9
       148: i2l
       149: iload         8
       151: i2l
       152: lmul
       153: sipush        1000
       156: i2l
       157: ldiv
       158: l2i
       159: invokeinterface #134,  2          // InterfaceMethod threshold_$eq:(I)V
       164: iload         4
       166: ifeq          185
       169: aload_0
       170: aload_0
       171: invokeinterface #61,  1           // InterfaceMethod table:()[Lscala/collection/mutable/HashEntry;
       176: arraylength
       177: invokeinterface #137,  2          // InterfaceMethod sizeMapInit:(I)V
       182: goto          192
       185: aload_0
       186: aconst_null
       187: invokeinterface #139,  2          // InterfaceMethod sizemap_$eq:([I)V
       192: iconst_0
       193: istore        5
       195: iload         5
       197: iload_3
       198: if_icmpge     222
       201: aload_0
       202: aload_2
       203: invokeinterface #145,  1          // InterfaceMethod scala/Function0.apply:()Ljava/lang/Object;
       208: checkcast     #130                // class scala/collection/mutable/HashEntry
       211: invokeinterface #149,  2          // InterfaceMethod addEntry:(Lscala/collection/mutable/HashEntry;)V
       216: iinc          5, 1
       219: goto          195
       222: return
      StackMapTable: number_of_entries = 8
        frame_type = 91 /* same_locals_1_stack_item */
          stack = [ class scala/Predef$ ]
        frame_type = 255 /* full_frame */
          offset_delta = 0
          locals = [ class scala/collection/mutable/HashTable, class java/io/ObjectInputStream, class scala/Function0 ]
          stack = [ class scala/Predef$, int ]
        frame_type = 255 /* full_frame */
          offset_delta = 26
          locals = [ class scala/collection/mutable/HashTable, class java/io/ObjectInputStream, class scala/Function0, int ]
          stack = [ class scala/Predef$ ]
        frame_type = 255 /* full_frame */
          offset_delta = 0
          locals = [ class scala/collection/mutable/HashTable, class java/io/ObjectInputStream, class scala/Function0, int ]
          stack = [ class scala/Predef$, int ]
        frame_type = 255 /* full_frame */
          offset_delta = 128
          locals = [ class scala/collection/mutable/HashTable, class java/io/ObjectInputStream, class scala/Function0, int, int, top, int, int, int, int ]
          stack = []
        frame_type = 6 /* same */
        frame_type = 255 /* full_frame */
          offset_delta = 2
          locals = [ class scala/collection/mutable/HashTable, class java/io/ObjectInputStream, class scala/Function0, int, int, int, int, int, int, int ]
          stack = []
        frame_type = 26 /* same */
      LineNumberTable:
        line 92: 0
        line 93: 10
        line 95: 31
        line 96: 36
        line 97: 43
        line 99: 59
        line 101: 69
        line 103: 75
        line 379: 92
        line 375: 94
        line 379: 97
        line 409: 106
        line 103: 116
        line 104: 124
        line 377: 146
        line 375: 153
        line 377: 156
        line 104: 159
        line 106: 164
        line 108: 192
        line 109: 195
        line 110: 201
        line 111: 216
        line 109: 219
      LocalVariableTable:
        Start  Length  Slot  Name   Signature
           36     186     3  size   I
           75     147     4 smDefined   Z
          195      27     5 index   I
            0     223     0  this   Lscala/collection/mutable/HashTable;
            0     223     1    in   Ljava/io/ObjectInputStream;
            0     223     2 readEntry   Lscala/Function0;
           92      14     6 sizeForThreshold__loadFactor   I
          146      13     8 newThreshold__loadFactor   I
          146      13     9 newThreshold_size   I
    Signature: #102                         // (Ljava/io/ObjectInputStream;Lscala/Function0<TEntry;>;)V
    MethodParameters:
      Name                           Flags
      in                             final
      readEntry                      final

  public static void serializeTo$(scala.collection.mutable.HashTable, java.io.ObjectOutputStream, scala.Function1);
    descriptor: (Lscala/collection/mutable/HashTable;Ljava/io/ObjectOutputStream;Lscala/Function1;)V
    flags: (0x1009) ACC_PUBLIC, ACC_STATIC, ACC_SYNTHETIC
    Code:
      stack=3, locals=3, args_size=3
         0: aload_0
         1: aload_1
         2: aload_2
         3: invokespecial #163                // InterfaceMethod serializeTo:(Ljava/io/ObjectOutputStream;Lscala/Function1;)V
         6: return
      LineNumberTable:
        line 122: 0
      LocalVariableTable:
        Start  Length  Slot  Name   Signature
            0       7     0 $this   Lscala/collection/mutable/HashTable;
            0       7     1   out   Ljava/io/ObjectOutputStream;
            0       7     2 writeEntry   Lscala/Function1;
    MethodParameters:
      Name                           Flags
      $this                          final synthetic
      out                            final
      writeEntry                     final

  public default void serializeTo(java.io.ObjectOutputStream, scala.Function1<Entry, scala.runtime.BoxedUnit>);
    descriptor: (Ljava/io/ObjectOutputStream;Lscala/Function1;)V
    flags: (0x0001) ACC_PUBLIC
    Code:
      stack=2, locals=3, args_size=3
         0: aload_1
         1: aload_0
         2: invokeinterface #116,  1          // InterfaceMethod _loadFactor:()I
         7: invokevirtual #171                // Method java/io/ObjectOutputStream.writeInt:(I)V
        10: aload_1
        11: aload_0
        12: invokeinterface #46,  1           // InterfaceMethod tableSize:()I
        17: invokevirtual #171                // Method java/io/ObjectOutputStream.writeInt:(I)V
        20: aload_1
        21: aload_0
        22: invokeinterface #173,  1          // InterfaceMethod seedvalue:()I
        27: invokevirtual #171                // Method java/io/ObjectOutputStream.writeInt:(I)V
        30: aload_1
        31: aload_0
        32: invokeinterface #176,  1          // InterfaceMethod isSizeMapDefined:()Z
        37: invokevirtual #179                // Method java/io/ObjectOutputStream.writeBoolean:(Z)V
        40: aload_0
        41: aload_2
        42: invokeinterface #183,  2          // InterfaceMethod foreachEntry:(Lscala/Function1;)V
        47: return
      LineNumberTable:
        line 123: 0
        line 124: 10
        line 125: 20
        line 126: 30
        line 128: 40
      LocalVariableTable:
        Start  Length  Slot  Name   Signature
            0      48     0  this   Lscala/collection/mutable/HashTable;
            0      48     1   out   Ljava/io/ObjectOutputStream;
            0      48     2 writeEntry   Lscala/Function1;
    Signature: #166                         // (Ljava/io/ObjectOutputStream;Lscala/Function1<TEntry;Lscala/runtime/BoxedUnit;>;)V
    MethodParameters:
      Name                           Flags
      out                            final
      writeEntry                     final

  public static scala.collection.mutable.HashEntry findEntry$(scala.collection.mutable.HashTable, java.lang.Object);
    descriptor: (Lscala/collection/mutable/HashTable;Ljava/lang/Object;)Lscala/collection/mutable/HashEntry;
    flags: (0x1009) ACC_PUBLIC, ACC_STATIC, ACC_SYNTHETIC
    Code:
      stack=2, locals=2, args_size=2
         0: aload_0
         1: aload_1
         2: invokespecial #190                // InterfaceMethod findEntry:(Ljava/lang/Object;)Lscala/collection/mutable/HashEntry;
         5: areturn
      LineNumberTable:
        line 133: 0
      LocalVariableTable:
        Start  Length  Slot  Name   Signature
            0       6     0 $this   Lscala/collection/mutable/HashTable;
            0       6     1   key   Ljava/lang/Object;
    MethodParameters:
      Name                           Flags
      $this                          final synthetic
      key                            final

  public default Entry findEntry(A);
    descriptor: (Ljava/lang/Object;)Lscala/collection/mutable/HashEntry;
    flags: (0x0001) ACC_PUBLIC
    Code:
      stack=5, locals=2, args_size=2
         0: aload_0
         1: aload_1
         2: aload_0
         3: aload_0
         4: aload_1
         5: invokeinterface #196,  2          // InterfaceMethod elemHashCode:(Ljava/lang/Object;)I
        10: invokeinterface #198,  2          // InterfaceMethod index:(I)I
        15: invokeinterface #202,  3          // InterfaceMethod findEntry0:(Ljava/lang/Object;I)Lscala/collection/mutable/HashEntry;
        20: areturn
      LineNumberTable:
        line 134: 0
      LocalVariableTable:
        Start  Length  Slot  Name   Signature
            0      21     0  this   Lscala/collection/mutable/HashTable;
            0      21     1   key   Ljava/lang/Object;
    Signature: #192                         // (TA;)TEntry;
    MethodParameters:
      Name                           Flags
      key                            final

  public static scala.collection.mutable.HashEntry findEntry0$(scala.collection.mutable.HashTable, java.lang.Object, int);
    descriptor: (Lscala/collection/mutable/HashTable;Ljava/lang/Object;I)Lscala/collection/mutable/HashEntry;
    flags: (0x1009) ACC_PUBLIC, ACC_STATIC, ACC_SYNTHETIC
    Code:
      stack=3, locals=3, args_size=3
         0: aload_0
         1: aload_1
         2: iload_2
         3: invokespecial #202                // InterfaceMethod findEntry0:(Ljava/lang/Object;I)Lscala/collection/mutable/HashEntry;
         6: areturn
      LineNumberTable:
        line 136: 0
      LocalVariableTable:
        Start  Length  Slot  Name   Signature
            0       7     0 $this   Lscala/collection/mutable/HashTable;
            0       7     1   key   Ljava/lang/Object;
            0       7     2     h   I
    MethodParameters:
      Name                           Flags
      $this                          final synthetic
      key                            final
      h                              final

  public default Entry findEntry0(A, int);
    descriptor: (Ljava/lang/Object;I)Lscala/collection/mutable/HashEntry;
    flags: (0x0001) ACC_PUBLIC
    Code:
      stack=3, locals=4, args_size=3
         0: aload_0
         1: invokeinterface #61,  1           // InterfaceMethod table:()[Lscala/collection/mutable/HashEntry;
         6: iload_2
         7: aaload
         8: astore_3
         9: aload_3
        10: ifnull        39
        13: aload_0
        14: aload_3
        15: invokeinterface #208,  1          // InterfaceMethod scala/collection/mutable/HashEntry.key:()Ljava/lang/Object;
        20: aload_1
        21: invokeinterface #212,  3          // InterfaceMethod elemEquals:(Ljava/lang/Object;Ljava/lang/Object;)Z
        26: ifne          39
        29: aload_3
        30: invokeinterface #216,  1          // InterfaceMethod scala/collection/mutable/HashEntry.next:()Lscala/collection/mutable/HashEntry;
        35: astore_3
        36: goto          9
        39: aload_3
        40: areturn
      StackMapTable: number_of_entries = 2
        frame_type = 252 /* append */
          offset_delta = 9
          locals = [ class scala/collection/mutable/HashEntry ]
        frame_type = 29 /* same */
      LineNumberTable:
        line 137: 0
        line 138: 9
        line 139: 39
      LocalVariableTable:
        Start  Length  Slot  Name   Signature
            9      31     3     e   Lscala/collection/mutable/HashEntry;
            0      41     0  this   Lscala/collection/mutable/HashTable;
            0      41     1   key   Ljava/lang/Object;
            0      41     2     h   I
    Signature: #206                         // (TA;I)TEntry;
    MethodParameters:
      Name                           Flags
      key                            final
      h                              final

  public static void addEntry$(scala.collection.mutable.HashTable, scala.collection.mutable.HashEntry);
    descriptor: (Lscala/collection/mutable/HashTable;Lscala/collection/mutable/HashEntry;)V
    flags: (0x1009) ACC_PUBLIC, ACC_STATIC, ACC_SYNTHETIC
    Code:
      stack=2, locals=2, args_size=2
         0: aload_0
         1: aload_1
         2: invokespecial #149                // InterfaceMethod addEntry:(Lscala/collection/mutable/HashEntry;)V
         5: return
      LineNumberTable:
        line 145: 0
      LocalVariableTable:
        Start  Length  Slot  Name   Signature
            0       6     0 $this   Lscala/collection/mutable/HashTable;
            0       6     1     e   Lscala/collection/mutable/HashEntry;
    MethodParameters:
      Name                           Flags
      $this                          final synthetic
      e                              final

  public default void addEntry(Entry);
    descriptor: (Lscala/collection/mutable/HashEntry;)V
    flags: (0x0001) ACC_PUBLIC
    Code:
      stack=5, locals=2, args_size=2
         0: aload_0
         1: aload_1
         2: aload_0
         3: aload_0
         4: aload_1
         5: invokeinterface #208,  1          // InterfaceMethod scala/collection/mutable/HashEntry.key:()Ljava/lang/Object;
        10: invokeinterface #196,  2          // InterfaceMethod elemHashCode:(Ljava/lang/Object;)I
        15: invokeinterface #198,  2          // InterfaceMethod index:(I)I
        20: invokeinterface #225,  3          // InterfaceMethod addEntry0:(Lscala/collection/mutable/HashEntry;I)V
        25: return
      LineNumberTable:
        line 146: 0
      LocalVariableTable:
        Start  Length  Slot  Name   Signature
            0      26     0  this   Lscala/collection/mutable/HashTable;
            0      26     1     e   Lscala/collection/mutable/HashEntry;
    Signature: #221                         // (TEntry;)V
    MethodParameters:
      Name                           Flags
      e                              final

  public static void addEntry0$(scala.collection.mutable.HashTable, scala.collection.mutable.HashEntry, int);
    descriptor: (Lscala/collection/mutable/HashTable;Lscala/collection/mutable/HashEntry;I)V
    flags: (0x1009) ACC_PUBLIC, ACC_STATIC, ACC_SYNTHETIC
    Code:
      stack=3, locals=3, args_size=3
         0: aload_0
         1: aload_1
         2: iload_2
         3: invokespecial #225                // InterfaceMethod addEntry0:(Lscala/collection/mutable/HashEntry;I)V
         6: return
      LineNumberTable:
        line 149: 0
      LocalVariableTable:
        Start  Length  Slot  Name   Signature
            0       7     0 $this   Lscala/collection/mutable/HashTable;
            0       7     1     e   Lscala/collection/mutable/HashEntry;
            0       7     2     h   I
    MethodParameters:
      Name                           Flags
      $this                          final synthetic
      e                              final
      h                              final

  public default void addEntry0(Entry, int);
    descriptor: (Lscala/collection/mutable/HashEntry;I)V
    flags: (0x0001) ACC_PUBLIC
    Code:
      stack=3, locals=3, args_size=3
         0: aload_1
         1: aload_0
         2: invokeinterface #61,  1           // InterfaceMethod table:()[Lscala/collection/mutable/HashEntry;
         7: iload_2
         8: aaload
         9: invokeinterface #231,  2          // InterfaceMethod scala/collection/mutable/HashEntry.next_$eq:(Lscala/collection/mutable/HashEntry;)V
        14: aload_0
        15: invokeinterface #61,  1           // InterfaceMethod table:()[Lscala/collection/mutable/HashEntry;
        20: iload_2
        21: aload_1
        22: aastore
        23: aload_0
        24: aload_0
        25: invokeinterface #46,  1           // InterfaceMethod tableSize:()I
        30: iconst_1
        31: iadd
        32: invokeinterface #122,  2          // InterfaceMethod tableSize_$eq:(I)V
        37: aload_0
        38: iload_2
        39: invokeinterface #234,  2          // InterfaceMethod nnSizeMapAdd:(I)V
        44: aload_0
        45: invokeinterface #46,  1           // InterfaceMethod tableSize:()I
        50: aload_0
        51: invokeinterface #236,  1          // InterfaceMethod threshold:()I
        56: if_icmple     72
        59: aload_0
        60: iconst_2
        61: aload_0
        62: invokeinterface #61,  1           // InterfaceMethod table:()[Lscala/collection/mutable/HashEntry;
        67: arraylength
        68: imul
        69: invokespecial #239                // InterfaceMethod resize:(I)V
        72: return
      StackMapTable: number_of_entries = 1
        frame_type = 251 /* same_frame_extended */
          offset_delta = 72
      LineNumberTable:
        line 150: 0
        line 151: 14
        line 152: 23
        line 153: 37
        line 154: 44
        line 155: 59
        line 154: 72
      LocalVariableTable:
        Start  Length  Slot  Name   Signature
            0      73     0  this   Lscala/collection/mutable/HashTable;
            0      73     1     e   Lscala/collection/mutable/HashEntry;
            0      73     2     h   I
    Signature: #228                         // (TEntry;I)V
    MethodParameters:
      Name                           Flags
      e                              final
      h                              final

  public static scala.collection.mutable.HashEntry findOrAddEntry$(scala.collection.mutable.HashTable, java.lang.Object, java.lang.Object);
    descriptor: (Lscala/collection/mutable/HashTable;Ljava/lang/Object;Ljava/lang/Object;)Lscala/collection/mutable/HashEntry;
    flags: (0x1009) ACC_PUBLIC, ACC_STATIC, ACC_SYNTHETIC
    Code:
      stack=3, locals=3, args_size=3
         0: aload_0
         1: aload_1
         2: aload_2
         3: invokespecial #246                // InterfaceMethod findOrAddEntry:(Ljava/lang/Object;Ljava/lang/Object;)Lscala/collection/mutable/HashEntry;
         6: areturn
      LineNumberTable:
        line 164: 0
      LocalVariableTable:
        Start  Length  Slot  Name   Signature
            0       7     0 $this   Lscala/collection/mutable/HashTable;
            0       7     1   key   Ljava/lang/Object;
            0       7     2 value   Ljava/lang/Object;
    MethodParameters:
      Name                           Flags
      $this                          final synthetic
      key                            final
      value                          final

  public default Entry findOrAddEntry(A, B);
    descriptor: (Ljava/lang/Object;Ljava/lang/Object;)Lscala/collection/mutable/HashEntry;
    flags: (0x0001) ACC_PUBLIC
    Code:
      stack=4, locals=5, args_size=3
         0: aload_0
         1: aload_0
         2: aload_1
         3: invokeinterface #196,  2          // InterfaceMethod elemHashCode:(Ljava/lang/Object;)I
         8: invokeinterface #198,  2          // InterfaceMethod index:(I)I
        13: istore_3
        14: aload_0
        15: aload_1
        16: iload_3
        17: invokeinterface #202,  3          // InterfaceMethod findEntry0:(Ljava/lang/Object;I)Lscala/collection/mutable/HashEntry;
        22: astore        4
        24: aload         4
        26: ifnull        32
        29: aload         4
        31: areturn
        32: aload_0
        33: aload_0
        34: aload_1
        35: aload_2
        36: invokeinterface #250,  3          // InterfaceMethod createNewEntry:(Ljava/lang/Object;Ljava/lang/Object;)Lscala/collection/mutable/HashEntry;
        41: iload_3
        42: invokeinterface #225,  3          // InterfaceMethod addEntry0:(Lscala/collection/mutable/HashEntry;I)V
        47: aconst_null
        48: areturn
      StackMapTable: number_of_entries = 1
        frame_type = 253 /* append */
          offset_delta = 32
          locals = [ int, class scala/collection/mutable/HashEntry ]
      LineNumberTable:
        line 165: 0
        line 166: 14
        line 167: 24
      LocalVariableTable:
        Start  Length  Slot  Name   Signature
           14      34     3     h   I
           24      24     4     e   Lscala/collection/mutable/HashEntry;
            0      49     0  this   Lscala/collection/mutable/HashTable;
            0      49     1   key   Ljava/lang/Object;
            0      49     2 value   Ljava/lang/Object;
    Signature: #247                         // (TA;TB;)TEntry;
    MethodParameters:
      Name                           Flags
      key                            final
      value                          final

  public abstract Entry createNewEntry(A, B);
    descriptor: (Ljava/lang/Object;Ljava/lang/Object;)Lscala/collection/mutable/HashEntry;
    flags: (0x0401) ACC_PUBLIC, ACC_ABSTRACT
    Signature: #247                         // (TA;TB;)TEntry;
    MethodParameters:
      Name                           Flags
      key                            final
      value                          final

  public static scala.collection.mutable.HashEntry removeEntry$(scala.collection.mutable.HashTable, java.lang.Object);
    descriptor: (Lscala/collection/mutable/HashTable;Ljava/lang/Object;)Lscala/collection/mutable/HashEntry;
    flags: (0x1009) ACC_PUBLIC, ACC_STATIC, ACC_SYNTHETIC
    Code:
      stack=2, locals=2, args_size=2
         0: aload_0
         1: aload_1
         2: invokespecial #254                // InterfaceMethod removeEntry:(Ljava/lang/Object;)Lscala/collection/mutable/HashEntry;
         5: areturn
      LineNumberTable:
        line 178: 0
      LocalVariableTable:
        Start  Length  Slot  Name   Signature
            0       6     0 $this   Lscala/collection/mutable/HashTable;
            0       6     1   key   Ljava/lang/Object;
    MethodParameters:
      Name                           Flags
      $this                          final synthetic
      key                            final

  public default Entry removeEntry(A);
    descriptor: (Ljava/lang/Object;)Lscala/collection/mutable/HashEntry;
    flags: (0x0001) ACC_PUBLIC
    Code:
      stack=5, locals=2, args_size=2
         0: aload_0
         1: aload_1
         2: aload_0
         3: aload_0
         4: aload_1
         5: invokeinterface #196,  2          // InterfaceMethod elemHashCode:(Ljava/lang/Object;)I
        10: invokeinterface #198,  2          // InterfaceMethod index:(I)I
        15: invokeinterface #257,  3          // InterfaceMethod removeEntry0:(Ljava/lang/Object;I)Lscala/collection/mutable/HashEntry;
        20: areturn
      LineNumberTable:
        line 179: 0
      LocalVariableTable:
        Start  Length  Slot  Name   Signature
            0      21     0  this   Lscala/collection/mutable/HashTable;
            0      21     1   key   Ljava/lang/Object;
    Signature: #192                         // (TA;)TEntry;
    MethodParameters:
      Name                           Flags
      key                            final

  public static scala.collection.mutable.HashEntry removeEntry0$(scala.collection.mutable.HashTable, java.lang.Object, int);
    descriptor: (Lscala/collection/mutable/HashTable;Ljava/lang/Object;I)Lscala/collection/mutable/HashEntry;
    flags: (0x1009) ACC_PUBLIC, ACC_STATIC, ACC_SYNTHETIC
    Code:
      stack=3, locals=3, args_size=3
         0: aload_0
         1: aload_1
         2: iload_2
         3: invokespecial #257                // InterfaceMethod removeEntry0:(Ljava/lang/Object;I)Lscala/collection/mutable/HashEntry;
         6: areturn
      LineNumberTable:
        line 183: 0
      LocalVariableTable:
        Start  Length  Slot  Name   Signature
            0       7     0 $this   Lscala/collection/mutable/HashTable;
            0       7     1   key   Ljava/lang/Object;
            0       7     2     h   I
    MethodParameters:
      Name                           Flags
      $this                          final synthetic
      key                            final
      h                              final

  public default Entry removeEntry0(A, int);
    descriptor: (Ljava/lang/Object;I)Lscala/collection/mutable/HashEntry;
    flags: (0x0001) ACC_PUBLIC
    Code:
      stack=3, locals=5, args_size=3
         0: aload_0
         1: invokeinterface #61,  1           // InterfaceMethod table:()[Lscala/collection/mutable/HashEntry;
         6: iload_2
         7: aaload
         8: astore_3
         9: aload_3
        10: ifnull        168
        13: aload_0
        14: aload_3
        15: invokeinterface #208,  1          // InterfaceMethod scala/collection/mutable/HashEntry.key:()Ljava/lang/Object;
        20: aload_1
        21: invokeinterface #212,  3          // InterfaceMethod elemEquals:(Ljava/lang/Object;Ljava/lang/Object;)Z
        26: ifeq          73
        29: aload_0
        30: invokeinterface #61,  1           // InterfaceMethod table:()[Lscala/collection/mutable/HashEntry;
        35: iload_2
        36: aload_3
        37: invokeinterface #216,  1          // InterfaceMethod scala/collection/mutable/HashEntry.next:()Lscala/collection/mutable/HashEntry;
        42: aastore
        43: aload_0
        44: aload_0
        45: invokeinterface #46,  1           // InterfaceMethod tableSize:()I
        50: iconst_1
        51: isub
        52: invokeinterface #122,  2          // InterfaceMethod tableSize_$eq:(I)V
        57: aload_0
        58: iload_2
        59: invokeinterface #261,  2          // InterfaceMethod nnSizeMapRemove:(I)V
        64: aload_3
        65: aconst_null
        66: invokeinterface #231,  2          // InterfaceMethod scala/collection/mutable/HashEntry.next_$eq:(Lscala/collection/mutable/HashEntry;)V
        71: aload_3
        72: areturn
        73: aload_3
        74: invokeinterface #216,  1          // InterfaceMethod scala/collection/mutable/HashEntry.next:()Lscala/collection/mutable/HashEntry;
        79: astore        4
        81: aload         4
        83: ifnull        118
        86: aload_0
        87: aload         4
        89: invokeinterface #208,  1          // InterfaceMethod scala/collection/mutable/HashEntry.key:()Ljava/lang/Object;
        94: aload_1
        95: invokeinterface #212,  3          // InterfaceMethod elemEquals:(Ljava/lang/Object;Ljava/lang/Object;)Z
       100: ifne          118
       103: aload         4
       105: astore_3
       106: aload         4
       108: invokeinterface #216,  1          // InterfaceMethod scala/collection/mutable/HashEntry.next:()Lscala/collection/mutable/HashEntry;
       113: astore        4
       115: goto          81
       118: aload         4
       120: ifnull        168
       123: aload_3
       124: aload         4
       126: invokeinterface #216,  1          // InterfaceMethod scala/collection/mutable/HashEntry.next:()Lscala/collection/mutable/HashEntry;
       131: invokeinterface #231,  2          // InterfaceMethod scala/collection/mutable/HashEntry.next_$eq:(Lscala/collection/mutable/HashEntry;)V
       136: aload_0
       137: aload_0
       138: invokeinterface #46,  1           // InterfaceMethod tableSize:()I
       143: iconst_1
       144: isub
       145: invokeinterface #122,  2          // InterfaceMethod tableSize_$eq:(I)V
       150: aload_0
       151: iload_2
       152: invokeinterface #261,  2          // InterfaceMethod nnSizeMapRemove:(I)V
       157: aload         4
       159: aconst_null
       160: invokeinterface #231,  2          // InterfaceMethod scala/collection/mutable/HashEntry.next_$eq:(Lscala/collection/mutable/HashEntry;)V
       165: aload         4
       167: areturn
       168: aconst_null
       169: areturn
      StackMapTable: number_of_entries = 4
        frame_type = 252 /* append */
          offset_delta = 73
          locals = [ class scala/collection/mutable/HashEntry ]
        frame_type = 252 /* append */
          offset_delta = 7
          locals = [ class scala/collection/mutable/HashEntry ]
        frame_type = 36 /* same */
        frame_type = 250 /* chop */
          offset_delta = 49
      LineNumberTable:
        line 184: 0
        line 185: 9
        line 186: 13
        line 187: 29
        line 188: 43
        line 189: 57
        line 190: 64
        line 191: 71
        line 193: 73
        line 194: 81
        line 195: 103
        line 196: 106
        line 194: 115
        line 198: 118
        line 199: 123
        line 200: 136
        line 201: 150
        line 202: 157
        line 203: 165
        line 207: 168
      LocalVariableTable:
        Start  Length  Slot  Name   Signature
           81      87     4    e1   Lscala/collection/mutable/HashEntry;
            9     160     3     e   Lscala/collection/mutable/HashEntry;
            0     170     0  this   Lscala/collection/mutable/HashTable;
            0     170     1   key   Ljava/lang/Object;
            0     170     2     h   I
    Signature: #206                         // (TA;I)TEntry;
    MethodParameters:
      Name                           Flags
      key                            final
      h                              final

  public static scala.collection.Iterator entriesIterator$(scala.collection.mutable.HashTable);
    descriptor: (Lscala/collection/mutable/HashTable;)Lscala/collection/Iterator;
    flags: (0x1009) ACC_PUBLIC, ACC_STATIC, ACC_SYNTHETIC
    Code:
      stack=1, locals=1, args_size=1
         0: aload_0
         1: invokespecial #268                // InterfaceMethod entriesIterator:()Lscala/collection/Iterator;
         4: areturn
      LineNumberTable:
        line 212: 0
      LocalVariableTable:
        Start  Length  Slot  Name   Signature
            0       5     0 $this   Lscala/collection/mutable/HashTable;
    MethodParameters:
      Name                           Flags
      $this                          final synthetic

  public default scala.collection.Iterator<Entry> entriesIterator();
    descriptor: ()Lscala/collection/Iterator;
    flags: (0x0001) ACC_PUBLIC
    Code:
      stack=3, locals=1, args_size=1
         0: new           #23                 // class scala/collection/mutable/HashTable$$anon$1
         3: dup
         4: aload_0
         5: invokespecial #273                // Method scala/collection/mutable/HashTable$$anon$1."<init>":(Lscala/collection/mutable/HashTable;)V
         8: areturn
      LineNumberTable:
        line 212: 0
      LocalVariableTable:
        Start  Length  Slot  Name   Signature
            0       9     0  this   Lscala/collection/mutable/HashTable;
    Signature: #269                         // ()Lscala/collection/Iterator<TEntry;>;

  public static void foreachEntry$(scala.collection.mutable.HashTable, scala.Function1);
    descriptor: (Lscala/collection/mutable/HashTable;Lscala/Function1;)V
    flags: (0x1009) ACC_PUBLIC, ACC_STATIC, ACC_SYNTHETIC
    Code:
      stack=2, locals=2, args_size=2
         0: aload_0
         1: aload_1
         2: invokespecial #183                // InterfaceMethod foreachEntry:(Lscala/Function1;)V
         5: return
      LineNumberTable:
        line 230: 0
      LocalVariableTable:
        Start  Length  Slot  Name   Signature
            0       6     0 $this   Lscala/collection/mutable/HashTable;
            0       6     1     f   Lscala/Function1;
    MethodParameters:
      Name                           Flags
      $this                          final synthetic
      f                              final

  public default <U extends java.lang.Object> void foreachEntry(scala.Function1<Entry, U>);
    descriptor: (Lscala/Function1;)V
    flags: (0x0001) ACC_PUBLIC
    Code:
      stack=2, locals=6, args_size=2
         0: aload_0
         1: invokeinterface #61,  1           // InterfaceMethod table:()[Lscala/collection/mutable/HashEntry;
         6: astore_2
         7: aload_0
         8: invokeinterface #90,  1           // InterfaceMethod scala$collection$mutable$HashTable$$lastPopulatedIndex:()I
        13: istore_3
        14: aload_2
        15: iload_3
        16: aaload
        17: astore        4
        19: aload         4
        21: ifnull        67
        24: aload         4
        26: invokeinterface #216,  1          // InterfaceMethod scala/collection/mutable/HashEntry.next:()Lscala/collection/mutable/HashEntry;
        31: astore        5
        33: aload_1
        34: aload         4
        36: invokeinterface #282,  2          // InterfaceMethod scala/Function1.apply:(Ljava/lang/Object;)Ljava/lang/Object;
        41: pop
        42: aload         5
        44: astore        4
        46: aload         4
        48: ifnonnull     19
        51: iload_3
        52: iconst_0
        53: if_icmple     19
        56: iinc          3, -1
        59: aload_2
        60: iload_3
        61: aaload
        62: astore        4
        64: goto          46
        67: return
      StackMapTable: number_of_entries = 3
        frame_type = 254 /* append */
          offset_delta = 19
          locals = [ class "[Lscala/collection/mutable/HashEntry;", int, class scala/collection/mutable/HashEntry ]
        frame_type = 252 /* append */
          offset_delta = 26
          locals = [ class scala/collection/mutable/HashEntry ]
        frame_type = 250 /* chop */
          offset_delta = 20
      LineNumberTable:
        line 231: 0
        line 232: 7
        line 233: 14
        line 235: 19
        line 236: 24
        line 237: 33
        line 238: 42
        line 240: 46
        line 241: 56
        line 242: 59
        line 240: 64
        line 235: 67
      LocalVariableTable:
        Start  Length  Slot  Name   Signature
           33      34     5  next   Lscala/collection/mutable/HashEntry;
            7      60     2 iterTable   [Lscala/collection/mutable/HashEntry;
           14      53     3   idx   I
           19      48     4    es   Lscala/collection/mutable/HashEntry;
            0      68     0  this   Lscala/collection/mutable/HashTable;
            0      68     1     f   Lscala/Function1;
    Signature: #277                         // <U:Ljava/lang/Object;>(Lscala/Function1<TEntry;TU;>;)V
    MethodParameters:
      Name                           Flags
      f                              final

  public static void clearTable$(scala.collection.mutable.HashTable);
    descriptor: (Lscala/collection/mutable/HashTable;)V
    flags: (0x1009) ACC_PUBLIC, ACC_STATIC, ACC_SYNTHETIC
    Code:
      stack=1, locals=1, args_size=1
         0: aload_0
         1: invokespecial #291                // InterfaceMethod clearTable:()V
         4: return
      LineNumberTable:
        line 249: 0
      LocalVariableTable:
        Start  Length  Slot  Name   Signature
            0       5     0 $this   Lscala/collection/mutable/HashTable;
    MethodParameters:
      Name                           Flags
      $this                          final synthetic

  public default void clearTable();
    descriptor: ()V
    flags: (0x0001) ACC_PUBLIC
    Code:
      stack=3, locals=2, args_size=1
         0: aload_0
         1: invokeinterface #61,  1           // InterfaceMethod table:()[Lscala/collection/mutable/HashEntry;
         6: arraylength
         7: iconst_1
         8: isub
         9: istore_1
        10: iload_1
        11: iconst_0
        12: if_icmplt     30
        15: aload_0
        16: invokeinterface #61,  1           // InterfaceMethod table:()[Lscala/collection/mutable/HashEntry;
        21: iload_1
        22: aconst_null
        23: aastore
        24: iinc          1, -1
        27: goto          10
        30: aload_0
        31: iconst_0
        32: invokeinterface #122,  2          // InterfaceMethod tableSize_$eq:(I)V
        37: aload_0
        38: iconst_0
        39: invokeinterface #294,  2          // InterfaceMethod nnSizeMapReset:(I)V
        44: return
      StackMapTable: number_of_entries = 2
        frame_type = 252 /* append */
          offset_delta = 10
          locals = [ int ]
        frame_type = 19 /* same */
      LineNumberTable:
        line 250: 0
        line 251: 10
        line 252: 30
        line 253: 37
      LocalVariableTable:
        Start  Length  Slot  Name   Signature
           10      34     1     i   I
            0      45     0  this   Lscala/collection/mutable/HashTable;

  private void resize(int);
    descriptor: (I)V
    flags: (0x0002) ACC_PRIVATE
    Code:
      stack=5, locals=8, args_size=2
         0: aload_0
         1: invokeinterface #61,  1           // InterfaceMethod table:()[Lscala/collection/mutable/HashEntry;
         6: astore_2
         7: aload_0
         8: iload_1
         9: anewarray     #130                // class scala/collection/mutable/HashEntry
        12: invokeinterface #132,  2          // InterfaceMethod table_$eq:([Lscala/collection/mutable/HashEntry;)V
        17: aload_0
        18: aload_0
        19: invokeinterface #61,  1           // InterfaceMethod table:()[Lscala/collection/mutable/HashEntry;
        24: arraylength
        25: invokeinterface #294,  2          // InterfaceMethod nnSizeMapReset:(I)V
        30: aload_2
        31: arraylength
        32: iconst_1
        33: isub
        34: istore_3
        35: iload_3
        36: iconst_0
        37: if_icmplt     128
        40: aload_2
        41: iload_3
        42: aaload
        43: astore        4
        45: aload         4
        47: ifnull        122
        50: aload_0
        51: aload_0
        52: aload         4
        54: invokeinterface #208,  1          // InterfaceMethod scala/collection/mutable/HashEntry.key:()Ljava/lang/Object;
        59: invokeinterface #196,  2          // InterfaceMethod elemHashCode:(Ljava/lang/Object;)I
        64: invokeinterface #198,  2          // InterfaceMethod index:(I)I
        69: istore        5
        71: aload         4
        73: invokeinterface #216,  1          // InterfaceMethod scala/collection/mutable/HashEntry.next:()Lscala/collection/mutable/HashEntry;
        78: astore        6
        80: aload         4
        82: aload_0
        83: invokeinterface #61,  1           // InterfaceMethod table:()[Lscala/collection/mutable/HashEntry;
        88: iload         5
        90: aaload
        91: invokeinterface #231,  2          // InterfaceMethod scala/collection/mutable/HashEntry.next_$eq:(Lscala/collection/mutable/HashEntry;)V
        96: aload_0
        97: invokeinterface #61,  1           // InterfaceMethod table:()[Lscala/collection/mutable/HashEntry;
       102: iload         5
       104: aload         4
       106: aastore
       107: aload         6
       109: astore        4
       111: aload_0
       112: iload         5
       114: invokeinterface #234,  2          // InterfaceMethod nnSizeMapAdd:(I)V
       119: goto          45
       122: iinc          3, -1
       125: goto          35
       128: aload_0
       129: getstatic     #78                 // Field scala/collection/mutable/HashTable$.MODULE$:Lscala/collection/mutable/HashTable$;
       132: pop
       133: aload_0
       134: invokeinterface #116,  1          // InterfaceMethod _loadFactor:()I
       139: istore        7
       141: iload_1
       142: i2l
       143: iload         7
       145: i2l
       146: lmul
       147: sipush        1000
       150: i2l
       151: ldiv
       152: l2i
       153: invokeinterface #134,  2          // InterfaceMethod threshold_$eq:(I)V
       158: return
      StackMapTable: number_of_entries = 4
        frame_type = 253 /* append */
          offset_delta = 35
          locals = [ class "[Lscala/collection/mutable/HashEntry;", int ]
        frame_type = 252 /* append */
          offset_delta = 9
          locals = [ class scala/collection/mutable/HashEntry ]
        frame_type = 251 /* same_frame_extended */
          offset_delta = 76
        frame_type = 250 /* chop */
          offset_delta = 5
      LineNumberTable:
        line 257: 0
        line 258: 7
        line 259: 17
        line 260: 30
        line 261: 35
        line 262: 40
        line 263: 45
        line 264: 50
        line 265: 71
        line 266: 80
        line 267: 96
        line 268: 107
        line 269: 111
        line 263: 119
        line 271: 122
        line 261: 125
        line 273: 128
        line 377: 141
        line 375: 147
        line 377: 150
        line 273: 153
      LocalVariableTable:
        Start  Length  Slot  Name   Signature
           71      48     5     h   I
           80      39     6    e1   Lscala/collection/mutable/HashEntry;
           45      80     4     e   Lscala/collection/mutable/HashEntry;
            7     151     2 oldTable   [Lscala/collection/mutable/HashEntry;
           35     123     3     i   I
            0     159     0  this   Lscala/collection/mutable/HashTable;
            0     159     1 newSize   I
          141      12     7 newThreshold__loadFactor   I
    MethodParameters:
      Name                           Flags
      newSize                        final

  public static void nnSizeMapAdd$(scala.collection.mutable.HashTable, int);
    descriptor: (Lscala/collection/mutable/HashTable;I)V
    flags: (0x1009) ACC_PUBLIC, ACC_STATIC, ACC_SYNTHETIC
    Code:
      stack=2, locals=2, args_size=2
         0: aload_0
         1: iload_1
         2: invokespecial #234                // InterfaceMethod nnSizeMapAdd:(I)V
         5: return
      LineNumberTable:
        line 295: 0
      LocalVariableTable:
        Start  Length  Slot  Name   Signature
            0       6     0 $this   Lscala/collection/mutable/HashTable;
            0       6     1     h   I
    MethodParameters:
      Name                           Flags
      $this                          final synthetic
      h                              final

  public default void nnSizeMapAdd(int);
    descriptor: (I)V
    flags: (0x0001) ACC_PUBLIC
    Code:
      stack=4, locals=4, args_size=2
         0: aload_0
         1: invokeinterface #301,  1          // InterfaceMethod sizemap:()[I
         6: ifnull        28
         9: aload_0
        10: invokeinterface #301,  1          // InterfaceMethod sizemap:()[I
        15: astore_2
        16: iload_1
        17: iconst_5
        18: ishr
        19: istore_3
        20: aload_2
        21: iload_3
        22: aload_2
        23: iload_3
        24: iaload
        25: iconst_1
        26: iadd
        27: iastore
        28: return
      StackMapTable: number_of_entries = 1
        frame_type = 28 /* same */
      LineNumberTable:
        line 295: 0
        line 296: 9
        line 384: 17
        line 296: 18
        line 295: 28
      LocalVariableTable:
        Start  Length  Slot  Name   Signature
            0      29     0  this   Lscala/collection/mutable/HashTable;
            0      29     1     h   I
    MethodParameters:
      Name                           Flags
      h                              final

  public static void nnSizeMapRemove$(scala.collection.mutable.HashTable, int);
    descriptor: (Lscala/collection/mutable/HashTable;I)V
    flags: (0x1009) ACC_PUBLIC, ACC_STATIC, ACC_SYNTHETIC
    Code:
      stack=2, locals=2, args_size=2
         0: aload_0
         1: iload_1
         2: invokespecial #261                // InterfaceMethod nnSizeMapRemove:(I)V
         5: return
      LineNumberTable:
        line 299: 0
      LocalVariableTable:
        Start  Length  Slot  Name   Signature
            0       6     0 $this   Lscala/collection/mutable/HashTable;
            0       6     1     h   I
    MethodParameters:
      Name                           Flags
      $this                          final synthetic
      h                              final

  public default void nnSizeMapRemove(int);
    descriptor: (I)V
    flags: (0x0001) ACC_PUBLIC
    Code:
      stack=4, locals=4, args_size=2
         0: aload_0
         1: invokeinterface #301,  1          // InterfaceMethod sizemap:()[I
         6: ifnull        28
         9: aload_0
        10: invokeinterface #301,  1          // InterfaceMethod sizemap:()[I
        15: astore_2
        16: iload_1
        17: iconst_5
        18: ishr
        19: istore_3
        20: aload_2
        21: iload_3
        22: aload_2
        23: iload_3
        24: iaload
        25: iconst_1
        26: isub
        27: iastore
        28: return
      StackMapTable: number_of_entries = 1
        frame_type = 28 /* same */
      LineNumberTable:
        line 299: 0
        line 300: 9
        line 384: 17
        line 300: 18
        line 299: 28
      LocalVariableTable:
        Start  Length  Slot  Name   Signature
            0      29     0  this   Lscala/collection/mutable/HashTable;
            0      29     1     h   I
    MethodParameters:
      Name                           Flags
      h                              final

  public static void nnSizeMapReset$(scala.collection.mutable.HashTable, int);
    descriptor: (Lscala/collection/mutable/HashTable;I)V
    flags: (0x1009) ACC_PUBLIC, ACC_STATIC, ACC_SYNTHETIC
    Code:
      stack=2, locals=2, args_size=2
         0: aload_0
         1: iload_1
         2: invokespecial #294                // InterfaceMethod nnSizeMapReset:(I)V
         5: return
      LineNumberTable:
        line 303: 0
      LocalVariableTable:
        Start  Length  Slot  Name   Signature
            0       6     0 $this   Lscala/collection/mutable/HashTable;
            0       6     1 tableLength   I
    MethodParameters:
      Name                           Flags
      $this                          final synthetic
      tableLength                    final

  public default void nnSizeMapReset(int);
    descriptor: (I)V
    flags: (0x0001) ACC_PUBLIC
    Code:
      stack=2, locals=3, args_size=2
         0: aload_0
         1: invokeinterface #301,  1          // InterfaceMethod sizemap:()[I
         6: ifnull        46
         9: iload_1
        10: iconst_5
        11: ishr
        12: iconst_1
        13: iadd
        14: istore_2
        15: aload_0
        16: invokeinterface #301,  1          // InterfaceMethod sizemap:()[I
        21: arraylength
        22: iload_2
        23: if_icmpeq     36
        26: aload_0
        27: iload_2
        28: newarray       int
        30: invokeinterface #139,  2          // InterfaceMethod sizemap_$eq:([I)V
        35: return
        36: aload_0
        37: invokeinterface #301,  1          // InterfaceMethod sizemap:()[I
        42: iconst_0
        43: invokestatic  #310                // Method java/util/Arrays.fill:([II)V
        46: return
      StackMapTable: number_of_entries = 2
        frame_type = 252 /* append */
          offset_delta = 36
          locals = [ int ]
        frame_type = 250 /* chop */
          offset_delta = 9
      LineNumberTable:
        line 303: 0
        line 311: 9
        line 384: 10
        line 311: 11
        line 305: 15
        line 306: 36
        line 303: 46
      LocalVariableTable:
        Start  Length  Slot  Name   Signature
            0      47     0  this   Lscala/collection/mutable/HashTable;
            0      47     1 tableLength   I
    MethodParameters:
      Name                           Flags
      tableLength                    final

  public static int totalSizeMapBuckets$(scala.collection.mutable.HashTable);
    descriptor: (Lscala/collection/mutable/HashTable;)I
    flags: (0x1009) ACC_PUBLIC, ACC_STATIC, ACC_SYNTHETIC
    Code:
      stack=1, locals=1, args_size=1
         0: aload_0
         1: invokespecial #314                // InterfaceMethod totalSizeMapBuckets:()I
         4: ireturn
      LineNumberTable:
        line 309: 0
      LocalVariableTable:
        Start  Length  Slot  Name   Signature
            0       5     0 $this   Lscala/collection/mutable/HashTable;
    MethodParameters:
      Name                           Flags
      $this                          final synthetic

  public default int totalSizeMapBuckets();
    descriptor: ()I
    flags: (0x0001) ACC_PUBLIC
    Code:
      stack=3, locals=1, args_size=1
         0: iconst_1
         1: iconst_5
         2: ishl
         3: aload_0
         4: invokeinterface #61,  1           // InterfaceMethod table:()[Lscala/collection/mutable/HashEntry;
         9: arraylength
        10: if_icmpge     15
        13: iconst_1
        14: ireturn
        15: aload_0
        16: invokeinterface #61,  1           // InterfaceMethod table:()[Lscala/collection/mutable/HashEntry;
        21: arraylength
        22: iconst_1
        23: iconst_5
        24: ishl
        25: idiv
        26: ireturn
      StackMapTable: number_of_entries = 1
        frame_type = 15 /* same */
      LineNumberTable:
        line 386: 0
        line 384: 1
        line 386: 2
        line 309: 3
        line 386: 22
        line 384: 23
        line 386: 24
        line 309: 25
      LocalVariableTable:
        Start  Length  Slot  Name   Signature
            0      27     0  this   Lscala/collection/mutable/HashTable;

  public static int calcSizeMapSize$(scala.collection.mutable.HashTable, int);
    descriptor: (Lscala/collection/mutable/HashTable;I)I
    flags: (0x1009) ACC_PUBLIC, ACC_STATIC, ACC_SYNTHETIC
    Code:
      stack=2, locals=2, args_size=2
         0: aload_0
         1: iload_1
         2: invokespecial #319                // InterfaceMethod calcSizeMapSize:(I)I
         5: ireturn
      LineNumberTable:
        line 311: 0
      LocalVariableTable:
        Start  Length  Slot  Name   Signature
            0       6     0 $this   Lscala/collection/mutable/HashTable;
            0       6     1 tableLength   I
    MethodParameters:
      Name                           Flags
      $this                          final synthetic
      tableLength                    final

  public default int calcSizeMapSize(int);
    descriptor: (I)I
    flags: (0x0001) ACC_PUBLIC
    Code:
      stack=2, locals=2, args_size=2
         0: iload_1
         1: iconst_5
         2: ishr
         3: iconst_1
         4: iadd
         5: ireturn
      LineNumberTable:
        line 311: 0
        line 384: 1
        line 311: 2
      LocalVariableTable:
        Start  Length  Slot  Name   Signature
            0       6     0  this   Lscala/collection/mutable/HashTable;
            0       6     1 tableLength   I
    MethodParameters:
      Name                           Flags
      tableLength                    final

  public static void sizeMapInit$(scala.collection.mutable.HashTable, int);
    descriptor: (Lscala/collection/mutable/HashTable;I)V
    flags: (0x1009) ACC_PUBLIC, ACC_STATIC, ACC_SYNTHETIC
    Code:
      stack=2, locals=2, args_size=2
         0: aload_0
         1: iload_1
         2: invokespecial #137                // InterfaceMethod sizeMapInit:(I)V
         5: return
      LineNumberTable:
        line 314: 0
      LocalVariableTable:
        Start  Length  Slot  Name   Signature
            0       6     0 $this   Lscala/collection/mutable/HashTable;
            0       6     1 tableLength   I
    MethodParameters:
      Name                           Flags
      $this                          final synthetic
      tableLength                    final

  public default void sizeMapInit(int);
    descriptor: (I)V
    flags: (0x0001) ACC_PUBLIC
    Code:
      stack=3, locals=2, args_size=2
         0: aload_0
         1: iload_1
         2: iconst_5
         3: ishr
         4: iconst_1
         5: iadd
         6: newarray       int
         8: invokeinterface #139,  2          // InterfaceMethod sizemap_$eq:([I)V
        13: return
      LineNumberTable:
        line 315: 0
        line 311: 1
        line 384: 2
        line 311: 3
        line 315: 6
      LocalVariableTable:
        Start  Length  Slot  Name   Signature
            0      14     0  this   Lscala/collection/mutable/HashTable;
            0      14     1 tableLength   I
    MethodParameters:
      Name                           Flags
      tableLength                    final

  public static void sizeMapInitAndRebuild$(scala.collection.mutable.HashTable);
    descriptor: (Lscala/collection/mutable/HashTable;)V
    flags: (0x1009) ACC_PUBLIC, ACC_STATIC, ACC_SYNTHETIC
    Code:
      stack=1, locals=1, args_size=1
         0: aload_0
         1: invokespecial #324                // InterfaceMethod sizeMapInitAndRebuild:()V
         4: return
      LineNumberTable:
        line 319: 0
      LocalVariableTable:
        Start  Length  Slot  Name   Signature
            0       5     0 $this   Lscala/collection/mutable/HashTable;
    MethodParameters:
      Name                           Flags
      $this                          final synthetic

  public default void sizeMapInitAndRebuild();
    descriptor: ()V
    flags: (0x0001) ACC_PUBLIC
    Code:
      stack=3, locals=8, args_size=1
         0: aload_0
         1: aload_0
         2: invokeinterface #61,  1           // InterfaceMethod table:()[Lscala/collection/mutable/HashEntry;
         7: arraylength
         8: invokeinterface #137,  2          // InterfaceMethod sizeMapInit:(I)V
        13: iconst_0
        14: istore_1
        15: iconst_0
        16: istore_2
        17: aload_0
        18: invokeinterface #61,  1           // InterfaceMethod table:()[Lscala/collection/mutable/HashEntry;
        23: astore_3
        24: aload_3
        25: arraylength
        26: iconst_1
        27: iconst_5
        28: ishl
        29: if_icmpge     39
        32: aload_3
        33: arraylength
        34: istore        4
        36: goto          44
        39: iconst_1
        40: iconst_5
        41: ishl
        42: istore        4
        44: aload_0
        45: invokeinterface #314,  1          // InterfaceMethod totalSizeMapBuckets:()I
        50: istore        5
        52: iload_2
        53: iload         5
        55: if_icmpge     122
        58: iconst_0
        59: istore        6
        61: iload_1
        62: iload         4
        64: if_icmpge     98
        67: aload_3
        68: iload_1
        69: aaload
        70: astore        7
        72: aload         7
        74: ifnull        92
        77: iinc          6, 1
        80: aload         7
        82: invokeinterface #216,  1          // InterfaceMethod scala/collection/mutable/HashEntry.next:()Lscala/collection/mutable/HashEntry;
        87: astore        7
        89: goto          72
        92: iinc          1, 1
        95: goto          61
        98: aload_0
        99: invokeinterface #301,  1          // InterfaceMethod sizemap:()[I
       104: iload_2
       105: iload         6
       107: iastore
       108: iload         4
       110: iconst_1
       111: iconst_5
       112: ishl
       113: iadd
       114: istore        4
       116: iinc          2, 1
       119: goto          52
       122: return
      StackMapTable: number_of_entries = 8
        frame_type = 254 /* append */
          offset_delta = 39
          locals = [ int, int, class "[Lscala/collection/mutable/HashEntry;" ]
        frame_type = 252 /* append */
          offset_delta = 4
          locals = [ int ]
        frame_type = 252 /* append */
          offset_delta = 7
          locals = [ int ]
        frame_type = 252 /* append */
          offset_delta = 8
          locals = [ int ]
        frame_type = 252 /* append */
          offset_delta = 10
          locals = [ class scala/collection/mutable/HashEntry ]
        frame_type = 19 /* same */
        frame_type = 250 /* chop */
          offset_delta = 5
        frame_type = 250 /* chop */
          offset_delta = 23
      LineNumberTable:
        line 320: 0
        line 323: 13
        line 324: 15
        line 325: 17
        line 327: 24
        line 386: 26
        line 384: 27
        line 386: 28
        line 327: 29
        line 386: 39
        line 384: 40
        line 386: 41
        line 327: 42
        line 328: 44
        line 329: 52
        line 330: 58
        line 331: 61
        line 332: 67
        line 333: 72
        line 334: 77
        line 335: 80
        line 333: 89
        line 337: 92
        line 331: 95
        line 339: 98
        line 340: 108
        line 386: 110
        line 384: 111
        line 386: 112
        line 340: 113
        line 341: 116
        line 329: 119
      LocalVariableTable:
        Start  Length  Slot  Name   Signature
           72      23     7     e   Lscala/collection/mutable/HashEntry;
           61      58     6 currbucketsize   I
           15     107     1 tableidx   I
           17     105     2 bucketidx   I
           24      98     3   tbl   [Lscala/collection/mutable/HashEntry;
           24      98     4 tableuntil   I
           52      70     5 totalbuckets   I
            0     123     0  this   Lscala/collection/mutable/HashTable;

  public static void printSizeMap$(scala.collection.mutable.HashTable);
    descriptor: (Lscala/collection/mutable/HashTable;)V
    flags: (0x1009) ACC_PUBLIC, ACC_STATIC, ACC_SYNTHETIC
    Code:
      stack=1, locals=1, args_size=1
         0: aload_0
         1: invokespecial #334                // InterfaceMethod printSizeMap:()V
         4: return
      LineNumberTable:
        line 345: 0
      LocalVariableTable:
        Start  Length  Slot  Name   Signature
            0       5     0 $this   Lscala/collection/mutable/HashTable;
    MethodParameters:
      Name                           Flags
      $this                          final synthetic

  public default void printSizeMap();
    descriptor: ()V
    flags: (0x0001) ACC_PUBLIC
    Code:
      stack=4, locals=9, args_size=1
         0: getstatic     #114                // Field scala/Predef$.MODULE$:Lscala/Predef$;
         3: aload_0
         4: invokeinterface #301,  1          // InterfaceMethod sizemap:()[I
         9: invokevirtual #338                // Method scala/Predef$.wrapIntArray:([I)Lscala/collection/mutable/ArraySeq$ofInt;
        12: getstatic     #343                // Field scala/collection/IterableFactory$.MODULE$:Lscala/collection/IterableFactory$;
        15: pop
        16: getstatic     #348                // Field scala/collection/immutable/List$.MODULE$:Lscala/collection/immutable/List$;
        19: astore        4
        21: new           #13                 // class scala/collection/IterableFactory$ToFactory
        24: dup
        25: aload         4
        27: invokespecial #351                // Method scala/collection/IterableFactory$ToFactory."<init>":(Lscala/collection/IterableFactory;)V
        30: astore        5
        32: aload         5
        34: aconst_null
        35: astore        4
        37: aconst_null
        38: astore        5
        40: astore_2
        41: dup
        42: ifnonnull     47
        45: aconst_null
        46: athrow
        47: astore_1
        48: aload_2
        49: aload_1
        50: invokeinterface #357,  2          // InterfaceMethod scala/collection/Factory.fromSpecific:(Lscala/collection/IterableOnce;)Ljava/lang/Object;
        55: astore        8
        57: aload         8
        59: aconst_null
        60: astore        8
        62: astore        7
        64: aload         7
        66: aconst_null
        67: astore        7
        69: astore_3
        70: aload_3
        71: aconst_null
        72: astore_1
        73: aconst_null
        74: astore_2
        75: aconst_null
        76: astore_3
        77: astore        6
        79: getstatic     #362                // Field scala/Console$.MODULE$:Lscala/Console$;
        82: aload         6
        84: invokevirtual #366                // Method scala/Console$.println:(Ljava/lang/Object;)V
        87: return
      StackMapTable: number_of_entries = 1
        frame_type = 255 /* full_frame */
          offset_delta = 47
          locals = [ class scala/collection/mutable/HashTable, top, class scala/collection/IterableFactory$ToFactory, top, null, null ]
          stack = [ class scala/collection/mutable/ArraySeq$ofInt ]
      LineNumberTable:
        line 346: 0
      LocalVariableTable:
        Start  Length  Slot  Name   Signature
            0      88     0  this   Lscala/collection/mutable/HashTable;
           48      22     1 to_this   Lscala/collection/AbstractIterable;
           48      22     2 to_factory   Lscala/collection/Factory;
           21      11     4 toFactory_factory   Lscala/collection/IterableFactory;
           79       8     6 println_x   Ljava/lang/Object;

  public static void sizeMapDisable$(scala.collection.mutable.HashTable);
    descriptor: (Lscala/collection/mutable/HashTable;)V
    flags: (0x1009) ACC_PUBLIC, ACC_STATIC, ACC_SYNTHETIC
    Code:
      stack=1, locals=1, args_size=1
         0: aload_0
         1: invokespecial #377                // InterfaceMethod sizeMapDisable:()V
         4: return
      LineNumberTable:
        line 349: 0
      LocalVariableTable:
        Start  Length  Slot  Name   Signature
            0       5     0 $this   Lscala/collection/mutable/HashTable;
    MethodParameters:
      Name                           Flags
      $this                          final synthetic

  public default void sizeMapDisable();
    descriptor: ()V
    flags: (0x0001) ACC_PUBLIC
    Code:
      stack=2, locals=1, args_size=1
         0: aload_0
         1: aconst_null
         2: invokeinterface #139,  2          // InterfaceMethod sizemap_$eq:([I)V
         7: return
      LineNumberTable:
        line 349: 0
      LocalVariableTable:
        Start  Length  Slot  Name   Signature
            0       8     0  this   Lscala/collection/mutable/HashTable;

  public static boolean isSizeMapDefined$(scala.collection.mutable.HashTable);
    descriptor: (Lscala/collection/mutable/HashTable;)Z
    flags: (0x1009) ACC_PUBLIC, ACC_STATIC, ACC_SYNTHETIC
    Code:
      stack=1, locals=1, args_size=1
         0: aload_0
         1: invokespecial #176                // InterfaceMethod isSizeMapDefined:()Z
         4: ireturn
      LineNumberTable:
        line 351: 0
      LocalVariableTable:
        Start  Length  Slot  Name   Signature
            0       5     0 $this   Lscala/collection/mutable/HashTable;
    MethodParameters:
      Name                           Flags
      $this                          final synthetic

  public default boolean isSizeMapDefined();
    descriptor: ()Z
    flags: (0x0001) ACC_PUBLIC
    Code:
      stack=1, locals=1, args_size=1
         0: aload_0
         1: invokeinterface #301,  1          // InterfaceMethod sizemap:()[I
         6: ifnull        11
         9: iconst_1
        10: ireturn
        11: iconst_0
        12: ireturn
      StackMapTable: number_of_entries = 1
        frame_type = 11 /* same */
      LineNumberTable:
        line 351: 0
      LocalVariableTable:
        Start  Length  Slot  Name   Signature
            0      13     0  this   Lscala/collection/mutable/HashTable;

  public static boolean alwaysInitSizeMap$(scala.collection.mutable.HashTable);
    descriptor: (Lscala/collection/mutable/HashTable;)Z
    flags: (0x1009) ACC_PUBLIC, ACC_STATIC, ACC_SYNTHETIC
    Code:
      stack=1, locals=1, args_size=1
         0: aload_0
         1: invokespecial #383                // InterfaceMethod alwaysInitSizeMap:()Z
         4: ireturn
      LineNumberTable:
        line 354: 0
      LocalVariableTable:
        Start  Length  Slot  Name   Signature
            0       5     0 $this   Lscala/collection/mutable/HashTable;
    MethodParameters:
      Name                           Flags
      $this                          final synthetic

  public default boolean alwaysInitSizeMap();
    descriptor: ()Z
    flags: (0x0001) ACC_PUBLIC
    Code:
      stack=1, locals=1, args_size=1
         0: iconst_0
         1: ireturn
      LineNumberTable:
        line 354: 0
      LocalVariableTable:
        Start  Length  Slot  Name   Signature
            0       2     0  this   Lscala/collection/mutable/HashTable;

  public static boolean elemEquals$(scala.collection.mutable.HashTable, java.lang.Object, java.lang.Object);
    descriptor: (Lscala/collection/mutable/HashTable;Ljava/lang/Object;Ljava/lang/Object;)Z
    flags: (0x1009) ACC_PUBLIC, ACC_STATIC, ACC_SYNTHETIC
    Code:
      stack=3, locals=3, args_size=3
         0: aload_0
         1: aload_1
         2: aload_2
         3: invokespecial #212                // InterfaceMethod elemEquals:(Ljava/lang/Object;Ljava/lang/Object;)Z
         6: ireturn
      LineNumberTable:
        line 358: 0
      LocalVariableTable:
        Start  Length  Slot  Name   Signature
            0       7     0 $this   Lscala/collection/mutable/HashTable;
            0       7     1  key1   Ljava/lang/Object;
            0       7     2  key2   Ljava/lang/Object;
    MethodParameters:
      Name                           Flags
      $this                          final synthetic
      key1                           final
      key2                           final

  public default boolean elemEquals(A, A);
    descriptor: (Ljava/lang/Object;Ljava/lang/Object;)Z
    flags: (0x0001) ACC_PUBLIC
    Code:
      stack=2, locals=3, args_size=3
         0: aload_1
         1: aload_2
         2: invokestatic  #393                // Method scala/runtime/BoxesRunTime.equals:(Ljava/lang/Object;Ljava/lang/Object;)Z
         5: ifeq          10
         8: iconst_1
         9: ireturn
        10: iconst_0
        11: ireturn
      StackMapTable: number_of_entries = 1
        frame_type = 10 /* same */
      LineNumberTable:
        line 358: 0
      LocalVariableTable:
        Start  Length  Slot  Name   Signature
            0      12     0  this   Lscala/collection/mutable/HashTable;
            0      12     1  key1   Ljava/lang/Object;
            0      12     2  key2   Ljava/lang/Object;
    Signature: #388                         // (TA;TA;)Z
    MethodParameters:
      Name                           Flags
      key1                           final
      key2                           final

  public static int index$(scala.collection.mutable.HashTable, int);
    descriptor: (Lscala/collection/mutable/HashTable;I)I
    flags: (0x1009) ACC_PUBLIC, ACC_STATIC, ACC_SYNTHETIC
    Code:
      stack=2, locals=2, args_size=2
         0: aload_0
         1: iload_1
         2: invokespecial #198                // InterfaceMethod index:(I)I
         5: ireturn
      LineNumberTable:
        line 364: 0
      LocalVariableTable:
        Start  Length  Slot  Name   Signature
            0       6     0 $this   Lscala/collection/mutable/HashTable;
            0       6     1 hcode   I
    MethodParameters:
      Name                           Flags
      $this                          final synthetic
      hcode                          final

  public default int index(int);
    descriptor: (I)I
    flags: (0x0001) ACC_PUBLIC
    Code:
      stack=3, locals=4, args_size=2
         0: aload_0
         1: invokeinterface #61,  1           // InterfaceMethod table:()[Lscala/collection/mutable/HashEntry;
         6: arraylength
         7: iconst_1
         8: isub
         9: istore_2
        10: iload_2
        11: invokestatic  #85                 // Method java/lang/Integer.numberOfLeadingZeros:(I)I
        14: istore_3
        15: aload_0
        16: iload_1
        17: aload_0
        18: invokeinterface #173,  1          // InterfaceMethod seedvalue:()I
        23: invokeinterface #399,  3          // InterfaceMethod improve:(II)I
        28: iload_3
        29: iushr
        30: iload_2
        31: iand
        32: ireturn
      LineNumberTable:
        line 365: 0
        line 366: 10
        line 367: 15
      LocalVariableTable:
        Start  Length  Slot  Name   Signature
           10      22     2  ones   I
           15      17     3 exponent   I
            0      33     0  this   Lscala/collection/mutable/HashTable;
            0      33     1 hcode   I
    MethodParameters:
      Name                           Flags
      hcode                          final

  public static void $init$(scala.collection.mutable.HashTable);
    descriptor: (Lscala/collection/mutable/HashTable;)V
    flags: (0x0009) ACC_PUBLIC, ACC_STATIC
    Code:
      stack=3, locals=1, args_size=1
         0: aload_0
         1: getstatic     #78                 // Field scala/collection/mutable/HashTable$.MODULE$:Lscala/collection/mutable/HashTable$;
         4: pop
         5: sipush        750
         8: invokeinterface #109,  2          // InterfaceMethod _loadFactor_$eq:(I)V
        13: aload_0
        14: aload_0
        15: invokespecial #81                 // InterfaceMethod initialCapacity:()I
        18: anewarray     #130                // class scala/collection/mutable/HashEntry
        21: invokeinterface #132,  2          // InterfaceMethod table_$eq:([Lscala/collection/mutable/HashEntry;)V
        26: aload_0
        27: iconst_0
        28: invokeinterface #122,  2          // InterfaceMethod tableSize_$eq:(I)V
        33: aload_0
        34: aload_0
        35: aload_0
        36: invokeinterface #116,  1          // InterfaceMethod _loadFactor:()I
        41: invokespecial #404                // InterfaceMethod initialThreshold:(I)I
        44: invokeinterface #134,  2          // InterfaceMethod threshold_$eq:(I)V
        49: aload_0
        50: aconst_null
        51: invokeinterface #139,  2          // InterfaceMethod sizemap_$eq:([I)V
        56: aload_0
        57: aload_0
        58: invokeinterface #59,  1           // InterfaceMethod tableSizeSeed:()I
        63: invokeinterface #124,  2          // InterfaceMethod seedvalue_$eq:(I)V
        68: return
      LineNumberTable:
        line 45: 0
        line 374: 5
        line 45: 8
        line 49: 13
        line 53: 26
        line 59: 33
        line 63: 49
        line 65: 56
        line 39: 68
      LocalVariableTable:
        Start  Length  Slot  Name   Signature
            0      69     0 $this   Lscala/collection/mutable/HashTable;
    MethodParameters:
      Name                           Flags
      $this                          final synthetic
}
InnerClasses:
  private static #16= #13 of #15;         // ToFactory=class scala/collection/IterableFactory$ToFactory of class scala/collection/IterableFactory
  public static final #21= #18 of #20;    // ofInt=class scala/collection/mutable/ArraySeq$ofInt of class scala/collection/mutable/ArraySeq
  public final #23;                       // class scala/collection/mutable/HashTable$$anon$1
  public static #24= #7 of #2;            // HashUtils=class scala/collection/mutable/HashTable$HashUtils of class scala/collection/mutable/HashTable
Signature: #3                           // <A:Ljava/lang/Object;B:Ljava/lang/Object;Entry::Lscala/collection/mutable/HashEntry<TA;TEntry;>;>Ljava/lang/Object;Lscala/collection/mutable/HashTable$HashUtils<TA;>;
SourceFile: "HashTable.scala"
RuntimeVisibleAnnotations:
  0: #9(#10=s#11)
    scala.reflect.ScalaSignature(
      bytes="\u0006\u0005\t-d\u0001\u0003 @!\u0003\r\t!Q#\t\u000b1\u0004A\u0011A7\t\u000fu\u0003\u0001\u0019!C\t+\"I\u0011q\u0004\u0001A\u0002\u0013E\u0011\u0011\u0005\u0005\u000b\u0003O\u0001\u0001\u0019!C\t\u0003\u0006%\u0002BCA#\u0001\u0001\u0007I\u0011C!\u0002H!I\u00111\n\u0001A\u0002\u0013E\u0011)\u0016\u0005\u000b\u0003\u001b\u0002\u0001\u0019!C\t\u0003\u0006=\u0003\"B0\u0001\t\u000b)\u0006\"CA*\u0001\u0001\u0007I\u0011C!V\u0011)\t)\u0006\u0001a\u0001\n#\t\u0015q\u000b\u0005\n\u00037\u0002\u0001\u0019!C\t\u0003;B\u0011\"!\u0019\u0001\u0001\u0004%\t\"a\u0019\t\u0011\u0005\u001d\u0004\u00011A\u0005\u0012UC\u0011\"!\u001b\u0001\u0001\u0004%\t\"a\u001b\t\r\u0005=\u0004\u0001\"\u0005V\u0011\u0019\t\t\b\u0001C\t+\"9\u00111\u000f\u0001\u0005\n\u0005U\u0004BBA=\u0001\u0011%Q\u000b\u0003\u0004\u0002|\u0001!I!\u0016\u0005\t\u0003{\u0002A\u0011A!\u0002\u0000!A\u0011q\u0014\u0001\u0005\u0002\u0005\u000b\t\u000bC\u0004\u00028\u0002!)!!/\t\u0011\u0005u\u0006\u0001\"\u0006B\u0003\u007fC\u0001\"a2\u0001\t+\t\u0015\u0011\u001a\u0005\t\u0003\u001f\u0004AQC!\u0002R\"9\u0011q\u001b\u0001\u0005\u0002\u0005e\u0007bBAt\u0001\u0019\u0005\u0011\u0011\u001e\u0005\b\u0003_\u0004AQAAy\u0011!\t)\u0010\u0001C\u0003\u0003\u0006]\bbBA\u007f\u0001\u0011\u0005\u0011q \u0005\b\u0005\u0013\u0001A\u0011\u0001B\u0006\u0011\u0019\u0011Y\u0002\u0001C\u0001[\"9!Q\u0004\u0001\u0005\n\t}\u0001b\u0002B\u0013\u0001\u0011U!q\u0005\u0005\b\u0005W\u0001AQ\u0003B\u0017\u0011\u001d\u0011\t\u0004\u0001C\u000b\u0005gAqA!\u000f\u0001\t\u000b\tU\u000bC\u0004\u0003<\u0001!)B!\u0010\t\u000f\t\u0005\u0003\u0001\"\u0005\u0003D!1!q\t\u0001\u0005\u00165DqA!\u0013\u0001\t\u0003\tU\u000e\u0003\u0004\u0003L\u0001!)\"\u001c\u0005\b\u0005\u001b\u0002AQ\u0003B(\u0011\u001d\u00119\u0006\u0001C\t\u0005\u001fBqA!\u0017\u0001\t#\u0011Y\u0006\u0003\u0005\u0003f\u0001!)\"\u0011B4\u000f\u0019qu\b#\u0001B\u001f\u001a1ah\u0010E\u0001\u0003BCQ!\u0015\u0019\u0005\u0002MCa\u0001\u0016\u0019\u0005\u0006\u0005+\u0006BB-1\t\u000b\tU\u000b\u0003\u0004[a\u0011\u0015\u0011i\u0017\u0005\u0007AB\")!Q1\t\r\u0015\u0004DQA!g\r\u001dI\u0007\u0007%A\u0002\u0002)DQ\u0001\\\u001c\u0005\u00025DQ!]\u001c\u0005\u0016UCQA]\u001c\u0005\u0016UCaa]\u001c\u0005\u0012\u0005#\bbBA\u0003o\u0011U\u0011q\u0001\u0005\t\u0003#\u0001D\u0011A!\u0002\u0014\tI\u0001*Y:i)\u0006\u0014G.\u001a\u0006\u0003\u0001\u0006\u000bq!\\;uC\ndWM\u0003\u0002C\u0007\u0006Q1m\u001c7mK\u000e$\u0018n\u001c8\u000b\u0003\u0011\u000bQa]2bY\u0006,rARA\u000e\u0003G\fIdE\u0002\u0001\u000f.\u0003\"\u0001S%\u000e\u0003\rK!AS\"\u0003\r\u0005s\u0017PU3g!\u0011au\'!\u0007\u000f\u00055{S\"A \u0002\u0013!\u000b7\u000f\u001b+bE2,\u0007CA\'1\'\t\u0001t)\u0001\u0004=S:LGOP\u0002\u0001)\u0005y\u0015!\u00053fM\u0006,H\u000e\u001e\'pC\u00124\u0015m\u0019;peV\ta\u000b\u0005\u0002I/&\u0011\u0001l\u0011\u0002\u0004\u0013:$\u0018a\u00047pC\u00124\u0015m\u0019;pe\u0012+g.^7\u0002\u00199,w\u000f\u00165sKNDw\u000e\u001c3\u0015\u0007Ycf\fC\u0003^i\u0001\u0007a+A\u0006`Y>\fGMR1di>\u0014\b\"B05\u0001\u00041\u0016\u0001B:ju\u0016\f\u0001c]5{K\u001a{\'\u000f\u00165sKNDw\u000e\u001c3\u0015\u0007Y\u00137\rC\u0003^k\u0001\u0007a\u000bC\u0003ek\u0001\u0007a+A\u0002uQJ\f\u0001bY1qC\u000eLG/\u001f\u000b\u0003-\u001eDQ\u0001\u001b\u001cA\u0002Y\u000bA\"\u001a=qK\u000e$X\rZ*ju\u0016\u0014\u0011\u0002S1tQV#\u0018\u000e\\:\u0016\u0005-L8CA\u001cH\u0003\u0019!\u0013N\\5uIQ\ta\u000e\u0005\u0002I_&\u0011\u0001o\u0011\u0002\u0005+:LG/\u0001\u000btSj,W*\u00199Ck\u000e\\W\r\u001e\"jiNK\'0Z\u0001\u0012g&TX-T1q\u0005V\u001c7.\u001a;TSj,\u0017\u0001D3mK6D\u0015m\u001d5D_\u0012,GC\u0001,v\u0011\u001518\b1\u0001x\u0003\rYW-\u001f\t\u0003qfd\u0001\u0001B\u0003{o\t\u00071PA\u0004LKf$\u0016\u0010]3\u0012\u0005q|\bC\u0001%~\u0013\tq8IA\u0004O_RD\u0017N\\4\u0011\u0007!\u000b\t!C\u0002\u0002\u0004\r\u00131!\u00118z\u0003\u001dIW\u000e\u001d:pm\u0016$RAVA\u0005\u0003\u001bAa!a\u0003=\u0001\u00041\u0016!\u00025d_\u0012,\u0007BBA\by\u0001\u0007a+\u0001\u0003tK\u0016$\u0017A\u00068fqR\u0004vn]5uSZ,\u0007k\\<fe>3Gk^8\u0015\u0007Y\u000b)\u0002\u0003\u0004\u0002\u0018u\u0002\rAV\u0001\u0007i\u0006\u0014x-\u001a;\u0011\u0007a\fY\u0002\u0002\u0004\u0002\u001e\u0001\u0011\ra\u001f\u0002\u0002\u0003\u0006yq\f\\8bI\u001a\u000b7\r^8s?\u0012*\u0017\u000fF\u0002o\u0003GA\u0001\"!\n\u0004\u0003\u0003\u0005\rAV\u0001\u0004q\u0012\n\u0014!\u0002;bE2,WCAA\u0016!\u0015A\u0015QFA\u0019\u0013\r\tyc\u0011\u0002\u0006\u0003J\u0014\u0018-\u001f\t\b\u001b\u0006M\u0012\u0011DA\u001c\u0013\r\t)d\u0010\u0002\n\u0011\u0006\u001c\b.\u00128uef\u00042\u0001_A\u001d\t\u001d\tY\u0004\u0001b\u0001\u0003{\u0011Q!\u00128uef\fB!a\u0010\u00022A\u0019\u0001*!\u0011\n\u0007\u0005\r3I\u0001\u0003Ok2d\u0017!\u0003;bE2,w\fJ3r)\rq\u0017\u0011\n\u0005\n\u0003K)\u0011\u0011!a\u0001\u0003W\t\u0011\u0002^1cY\u0016\u001c\u0016N_3\u0002\u001bQ\f\'\r\\3TSj,w\fJ3r)\rq\u0017\u0011\u000b\u0005\t\u0003K9\u0011\u0011!a\u0001-\u0006IA\u000f\u001b:fg\"|G\u000eZ\u0001\u000ei\"\u0014Xm\u001d5pY\u0012|F%Z9\u0015\u00079\fI\u0006\u0003\u0005\u0002&)\t\t\u00111\u0001W\u0003\u001d\u0019\u0018N_3nCB,\"!a\u0018\u0011\t!\u000biCV\u0001\fg&TX-\\1q?\u0012*\u0017\u000fF\u0002o\u0003KB\u0011\"!\n\r\u0003\u0003\u0005\r!a\u0018\u0002\u0013M,W\r\u001a<bYV,\u0017!D:fK\u00124\u0018\r\\;f?\u0012*\u0017\u000fF\u0002o\u0003[B\u0001\"!\n\u000f\u0003\u0003\u0005\rAV\u0001\u000ei\u0006\u0014G.Z*ju\u0016\u001cV-\u001a3\u0002\u0017%t\u0017\u000e^5bYNK\'0Z\u0001\u0011S:LG/[1m)\"\u0014Xm\u001d5pY\u0012$2AVA<\u0011\u0015i\u0016\u00031\u0001W\u0003=Ig.\u001b;jC2\u001c\u0015\r]1dSRL\u0018A\u00057bgR\u0004v\u000e];mCR,G-\u00138eKb\fA!\u001b8jiR)a.!!\u0002\u0016\"9\u00111\u0011\u000bA\u0002\u0005\u0015\u0015AA5o!\u0011\t9)!%\u000e\u0005\u0005%%\u0002BAF\u0003\u001b\u000b!![8\u000b\u0005\u0005=\u0015\u0001\u00026bm\u0006LA!a%\u0002\n\n\trJ\u00196fGRLe\u000e];u\'R\u0014X-Y7\t\u0011\u0005]E\u0003\"a\u0001\u00033\u000b\u0011B]3bI\u0016sGO]=\u0011\u000b!\u000bY*a\u000e\n\u0007\u0005u5I\u0001\u0005=Eft\u0017-\\3?\u0003-\u0019XM]5bY&TX\rV8\u0015\u000b9\f\u0019+!,\t\u000f\u0005\u0015V\u00031\u0001\u0002(\u0006\u0019q.\u001e;\u0011\t\u0005\u001d\u0015\u0011V\u0005\u0005\u0003W\u000bII\u0001\nPE*,7\r^(viB,Ho\u0015;sK\u0006l\u0007bBAX+\u0001\u0007\u0011\u0011W\u0001\u000boJLG/Z#oiJL\bC\u0002%\u00024\u0006]b.C\u0002\u00026\u000e\u0013\u0011BR;oGRLwN\\\u0019\u0002\u0013\u0019Lg\u000eZ#oiJLH\u0003BA\u001c\u0003wCaA\u001e\fA\u0002\u0005e\u0011A\u00034j]\u0012,e\u000e\u001e:zaQ1\u0011qGAa\u0003\u0007DaA^\fA\u0002\u0005e\u0001BBAc/\u0001\u0007a+A\u0001i\u0003!\tG\rZ#oiJLHc\u00018\u0002L\"9\u0011Q\u001a\rA\u0002\u0005]\u0012!A3\u0002\u0013\u0005$G-\u00128uef\u0004D#\u00028\u0002T\u0006U\u0007bBAg3\u0001\u0007\u0011q\u0007\u0005\u0007\u0003\u000bL\u0002\u0019\u0001,\u0002\u001d\u0019Lg\u000eZ(s\u0003\u0012$WI\u001c;ssR1\u0011qGAn\u0003;DaA\u001e\u000eA\u0002\u0005e\u0001bBAp5\u0001\u0007\u0011\u0011]\u0001\u0006m\u0006dW/\u001a\t\u0004q\u0006\rHABAs\u0001\t\u00071PA\u0001C\u00039\u0019\'/Z1uK:+w/\u00128uef$b!a\u000e\u0002l\u00065\bB\u0002<\u001c\u0001\u0004\tI\u0002C\u0004\u0002`n\u0001\r!!9\u0002\u0017I,Wn\u001c<f\u000b:$(/\u001f\u000b\u0005\u0003o\t\u0019\u0010\u0003\u0004w9\u0001\u0007\u0011\u0011D\u0001\re\u0016lwN^3F]R\u0014\u0018\u0010\r\u000b\u0007\u0003o\tI0a?\t\rYl\u0002\u0019AA\r\u0011\u0019\t)-\ba\u0001-\u0006yQM\u001c;sS\u0016\u001c\u0018\n^3sCR|\'/\u0006\u0002\u0003\u0002A1!1\u0001B\u0003\u0003oi\u0011!Q\u0005\u0004\u0005\u000f\t%\u0001C%uKJ\fGo\u001c:\u0002\u0019\u0019|\'/Z1dQ\u0016sGO]=\u0016\t\t5!q\u0003\u000b\u0004]\n=\u0001b\u0002B\t?\u0001\u0007!1C\u0001\u0002MB9\u0001*a-\u00028\tU\u0001c\u0001=\u0003\u0018\u00111!\u0011D\u0010C\u0002m\u0014\u0011!V\u0001\u000bG2,\u0017M\u001d+bE2,\u0017A\u0002:fg&TX\rF\u0002o\u0005CAaAa\t\"\u0001\u00041\u0016a\u00028foNK\'0Z\u0001\r]:\u001c\u0016N_3NCB\fE\r\u001a\u000b\u0004]\n%\u0002BBAcE\u0001\u0007a+A\bo]NK\'0Z\'baJ+Wn\u001c<f)\rq\'q\u0006\u0005\u0007\u0003\u000b\u001c\u0003\u0019\u0001,\u0002\u001d9t7+\u001b>f\u001b\u0006\u0004(+Z:fiR\u0019aN!\u000e\t\r\t]B\u00051\u0001W\u0003-!\u0018M\u00197f\u0019\u0016tw\r\u001e5\u0002\'Q|G/\u00197TSj,W*\u00199Ck\u000e\\W\r^:\u0002\u001f\r\fGnY*ju\u0016l\u0015\r]*ju\u0016$2A\u0016B \u0011\u0019\u00119D\na\u0001-\u0006Y1/\u001b>f\u001b\u0006\u0004\u0018J\\5u)\rq\'Q\t\u0005\u0007\u0005o9\u0003\u0019\u0001,\u0002+ML\'0Z\'ba&s\u0017\u000e^!oIJ+\'-^5mI\u0006a\u0001O]5oiNK\'0Z\'ba\u0006q1/\u001b>f\u001b\u0006\u0004H)[:bE2,\u0017\u0001E5t\'&TX-T1q\t\u00164\u0017N\\3e+\t\u0011\t\u0006E\u0002I\u0005\'J1A!\u0016D\u0005\u001d\u0011un\u001c7fC:\f\u0011#\u00197xCf\u001c\u0018J\\5u\'&TX-T1q\u0003))G.Z7FcV\fGn\u001d\u000b\u0007\u0005#\u0012iF!\u0019\t\u000f\t}S\u00061\u0001\u0002\u001a\u0005!1.Z=2\u0011\u001d\u0011\u0019\'\fa\u0001\u00033\tAa[3ze\u0005)\u0011N\u001c3fqR\u0019aK!\u001b\t\r\u0005-a\u00061\u0001W\u0001"
    )
  ScalaInlineInfo: length = 0x17B (unknown attribute)
   01 00 00 4B 01 92 01 0F 01 00 19 00 1A 00 00 1B
   00 1C 00 00 92 00 93 01 00 DB 00 DC 01 00 DE 00
   DF 01 00 E2 00 E3 01 01 7D 00 7E 00 01 7C 01 7B
   01 01 3D 00 41 01 01 3B 01 3C 01 01 20 01 21 00
   01 1F 01 0F 01 00 F8 00 F4 00 00 D1 00 D2 00 01
   80 01 81 01 01 09 01 0A 00 01 07 01 08 01 00 BB
   00 BC 01 00 B8 00 B9 01 00 C7 00 C8 01 00 CB 00
   CC 01 00 F3 00 F4 00 00 F0 00 F1 01 00 B4 00 B5
   00 01 12 01 13 01 00 98 00 41 01 01 8A 01 3C 01
   00 60 00 61 00 00 5C 00 5D 01 00 4F 00 1A 01 00
   45 00 1A 00 00 44 00 27 01 00 48 00 41 01 00 AE
   00 7E 01 01 7A 01 7B 01 00 E8 00 1C 01 01 2A 01
   2B 01 01 03 00 1C 01 01 2E 01 2B 01 01 24 00 1C
   01 01 2F 01 2B 01 01 4C 01 21 00 01 4B 01 0F 01
   00 FC 00 BC 01 00 FB 00 B9 01 00 FF 00 C8 01 01
   02 00 CC 01 00 ED 00 1C 01 00 58 00 1A 01 00 57
   00 27 01 00 36 00 1A 00 00 37 00 1C 00 00 A0 00
   A1 00 00 9C 00 9D 01 00 29 00 1A 01 00 26 00 27
   01 01 77 01 21 01 01 76 01 0F 01 00 87 00 1C 00
   01 40 01 2B 01 01 42 01 21 01 01 41 01 0F 01 00
   32 00 33 00 00 34 00 35 00 00 1E 00 1F 00 00 24
   00 1A 00 00 39 00 1A 00 00 38 00 27 01 00 25 00
   1C 00 00 21 00 22 00 00 30 00 1A 00 00 31 00 1C
   00 01 38 00 1A 01 01 37 00 27 01
  ScalaSig: length = 0x3 (unknown attribute)
   05 02 00
