Classfile /Users/mw/Projects/slang-braindump/.jar/jar11/assemble/slang-braindump/assemble/content/scala/collection/mutable/ImmutableBuilder.class
  Last modified May 29, 2022; size 4931 bytes
  SHA-256 checksum a5cdc5b4e95b3e8585b4d0279f2b6ee1d7357a2eb8bfb12d669f379ab84dc5a6
  Compiled from "ImmutableBuilder.scala"
public abstract class scala.collection.mutable.ImmutableBuilder<A extends java.lang.Object, C extends scala.collection.IterableOnce<?>> extends java.lang.Object implements scala.collection.mutable.ReusableBuilder<A, C>
  minor version: 0
  major version: 52
  flags: (0x0421) ACC_PUBLIC, ACC_SUPER, ACC_ABSTRACT
  this_class: #2                          // scala/collection/mutable/ImmutableBuilder
  super_class: #5                         // java/lang/Object
  interfaces: 1, fields: 2, methods: 16, attributes: 5
Constant pool:
    #1 = Utf8               scala/collection/mutable/ImmutableBuilder
    #2 = Class              #1            // scala/collection/mutable/ImmutableBuilder
    #3 = Utf8               <A:Ljava/lang/Object;C::Lscala/collection/IterableOnce<*>;>Ljava/lang/Object;Lscala/collection/mutable/ReusableBuilder<TA;TC;>;
    #4 = Utf8               java/lang/Object
    #5 = Class              #4            // java/lang/Object
    #6 = Utf8               scala/collection/mutable/ReusableBuilder
    #7 = Class              #6            // scala/collection/mutable/ReusableBuilder
    #8 = Utf8               ImmutableBuilder.scala
    #9 = Utf8               Lscala/reflect/ScalaSignature;
   #10 = Utf8               bytes
   #11 = Utf8               \u0006\u0005)3Q!\u0003\u0006\u0002\u0002EA\u0001B\r\u0001\u0003\u0002\u0003\u0006IA\n\u0005\u0006g\u0001!\t\u0001\u000e\u0005\bo\u0001\u0001\r\u0011\"\u00059\u0011\u001dI\u0004\u00011A\u0005\u0012iBa\u0001\u0011\u0001!B\u00131\u0003\"B!\u0001\t\u0003\u0011\u0005\"B\"\u0001\t\u0003!\u0005\"B#\u0001\t\u00032%\u0001E%n[V$\u0018M\u00197f\u0005VLG\u000eZ3s\u0015\tYA\"A\u0004nkR\f\'\r\\3\u000b\u00055q\u0011AC2pY2,7\r^5p]*\tq\"A\u0003tG\u0006d\u0017m\u0001\u0001\u0016\u0007IireE\u0002\u0001\']\u0001\"\u0001F\u000b\u000e\u00039I!A\u0006\b\u0003\r\u0005s\u0017PU3g!\u0011A\u0012d\u0007\u0014\u000e\u0003)I!A\u0007\u0006\u0003\u001fI+Wo]1cY\u0016\u0014U/\u001b7eKJ\u0004\"\u0001H\u000f\r\u0001\u00111a\u0004\u0001EC\u0002}\u0011\u0011!Q\t\u0003A\r\u0002\"\u0001F\u0011\n\u0005\tr!a\u0002(pi\"Lgn\u001a\t\u0003)\u0011J!!\n\b\u0003\u0007\u0005s\u0017\u0010\u0005\u0002\u001dO\u0011)\u0001\u0006\u0001b\u0001S\t\t1)\u0005\u0002!UA\u00121\u0006\r\t\u0004Y5zS\"\u0001\u0007\n\u00059b!\u0001D%uKJ\f\'\r\\3P]\u000e,\u0007C\u0001\u000f1\t%\tt%!A\u0001\u0002\u000b\u0005qDA\u0002`IE\nQ!Z7qif\fa\u0001P5oSRtDCA\u001b7!\u0011A\u0002a\u0007\u0014\t\u000bI\u0012\u0001\u0019\u0001\u0014\u0002\u000b\u0015dW-\\:\u0016\u0003\u0019\n\u0011\"\u001a7f[N|F%Z9\u0015\u0005mr\u0004C\u0001\u000b=\u0013\tidB\u0001\u0003V]&$\bbB \u0005\u0003\u0003\u0005\rAJ\u0001\u0004q\u0012\n\u0014AB3mK6\u001c\b%A\u0003dY\u0016\f\'\u000fF\u0001<\u0003\u0019\u0011Xm];miR\ta%A\u0005l]><hnU5{KV\tq\t\u0005\u0002\u0015\u0011&\u0011\u0011J\u0004\u0002\u0004\u0013:$\b
   #12 = Utf8               empty
   #13 = Utf8               Lscala/collection/IterableOnce;
   #14 = Utf8               TC;
   #15 = Utf8               elems
   #16 = Utf8               sizeHint
   #17 = Utf8               (I)V
   #18 = Utf8               size
   #19 = Utf8               scala/collection/mutable/Builder
   #20 = Class              #19           // scala/collection/mutable/Builder
   #21 = Utf8               sizeHint$
   #22 = Utf8               (Lscala/collection/mutable/Builder;I)V
   #23 = NameAndType        #21:#22       // sizeHint$:(Lscala/collection/mutable/Builder;I)V
   #24 = InterfaceMethodref #20.#23       // scala/collection/mutable/Builder.sizeHint$:(Lscala/collection/mutable/Builder;I)V
   #25 = Utf8               this
   #26 = Utf8               Lscala/collection/mutable/ImmutableBuilder;
   #27 = Utf8               I
   #28 = Utf8               (Lscala/collection/IterableOnce;I)V
   #29 = Utf8               (Lscala/collection/IterableOnce<*>;I)V
   #30 = Utf8               coll
   #31 = Utf8               delta
   #32 = Utf8               (Lscala/collection/mutable/Builder;Lscala/collection/IterableOnce;I)V
   #33 = NameAndType        #21:#32       // sizeHint$:(Lscala/collection/mutable/Builder;Lscala/collection/IterableOnce;I)V
   #34 = InterfaceMethodref #20.#33       // scala/collection/mutable/Builder.sizeHint$:(Lscala/collection/mutable/Builder;Lscala/collection/IterableOnce;I)V
   #35 = Utf8               sizeHint$default$2
   #36 = Utf8               ()I
   #37 = Utf8               sizeHint$default$2$
   #38 = Utf8               (Lscala/collection/mutable/Builder;)I
   #39 = NameAndType        #37:#38       // sizeHint$default$2$:(Lscala/collection/mutable/Builder;)I
   #40 = InterfaceMethodref #20.#39       // scala/collection/mutable/Builder.sizeHint$default$2$:(Lscala/collection/mutable/Builder;)I
   #41 = Utf8               sizeHintBounded
   #42 = Utf8               (ILscala/collection/Iterable;)V
   #43 = Utf8               (ILscala/collection/Iterable<*>;)V
   #44 = Utf8               boundingColl
   #45 = Utf8               sizeHintBounded$
   #46 = Utf8               (Lscala/collection/mutable/Builder;ILscala/collection/Iterable;)V
   #47 = NameAndType        #45:#46       // sizeHintBounded$:(Lscala/collection/mutable/Builder;ILscala/collection/Iterable;)V
   #48 = InterfaceMethodref #20.#47       // scala/collection/mutable/Builder.sizeHintBounded$:(Lscala/collection/mutable/Builder;ILscala/collection/Iterable;)V
   #49 = Utf8               Lscala/collection/Iterable;
   #50 = Utf8               mapResult
   #51 = Utf8               (Lscala/Function1;)Lscala/collection/mutable/Builder;
   #52 = Utf8               <NewTo:Ljava/lang/Object;>(Lscala/Function1<TC;TNewTo;>;)Lscala/collection/mutable/Builder<TA;TNewTo;>;
   #53 = Utf8               f
   #54 = Utf8               mapResult$
   #55 = Utf8               (Lscala/collection/mutable/Builder;Lscala/Function1;)Lscala/collection/mutable/Builder;
   #56 = NameAndType        #54:#55       // mapResult$:(Lscala/collection/mutable/Builder;Lscala/Function1;)Lscala/collection/mutable/Builder;
   #57 = InterfaceMethodref #20.#56       // scala/collection/mutable/Builder.mapResult$:(Lscala/collection/mutable/Builder;Lscala/Function1;)Lscala/collection/mutable/Builder;
   #58 = Utf8               Lscala/Function1;
   #59 = Utf8               $plus$eq
   #60 = Utf8               (Ljava/lang/Object;)Lscala/collection/mutable/Growable;
   #61 = Utf8               (TA;)Lscala/collection/mutable/Growable<TA;>;
   #62 = Utf8               elem
   #63 = Utf8               scala/collection/mutable/Growable
   #64 = Class              #63           // scala/collection/mutable/Growable
   #65 = Utf8               $plus$eq$
   #66 = Utf8               (Lscala/collection/mutable/Growable;Ljava/lang/Object;)Lscala/collection/mutable/Growable;
   #67 = NameAndType        #65:#66       // $plus$eq$:(Lscala/collection/mutable/Growable;Ljava/lang/Object;)Lscala/collection/mutable/Growable;
   #68 = InterfaceMethodref #64.#67       // scala/collection/mutable/Growable.$plus$eq$:(Lscala/collection/mutable/Growable;Ljava/lang/Object;)Lscala/collection/mutable/Growable;
   #69 = Utf8               Ljava/lang/Object;
   #70 = Utf8               (Ljava/lang/Object;Ljava/lang/Object;Lscala/collection/immutable/Seq;)Lscala/collection/mutable/Growable;
   #71 = Utf8               (TA;TA;Lscala/collection/immutable/Seq<TA;>;)Lscala/collection/mutable/Growable<TA;>;
   #72 = Utf8               elem1
   #73 = Utf8               elem2
   #74 = Utf8               (Lscala/collection/mutable/Growable;Ljava/lang/Object;Ljava/lang/Object;Lscala/collection/immutable/Seq;)Lscala/collection/mutable/Growable;
   #75 = NameAndType        #65:#74       // $plus$eq$:(Lscala/collection/mutable/Growable;Ljava/lang/Object;Ljava/lang/Object;Lscala/collection/immutable/Seq;)Lscala/collection/mutable/Growable;
   #76 = InterfaceMethodref #64.#75       // scala/collection/mutable/Growable.$plus$eq$:(Lscala/collection/mutable/Growable;Ljava/lang/Object;Ljava/lang/Object;Lscala/collection/immutable/Seq;)Lscala/collection/mutable/Growable;
   #77 = Utf8               Lscala/collection/immutable/Seq;
   #78 = Utf8               addAll
   #79 = Utf8               (Lscala/collection/IterableOnce;)Lscala/collection/mutable/Growable;
   #80 = Utf8               (Lscala/collection/IterableOnce<TA;>;)Lscala/collection/mutable/Growable<TA;>;
   #81 = Utf8               xs
   #82 = Utf8               addAll$
   #83 = Utf8               (Lscala/collection/mutable/Growable;Lscala/collection/IterableOnce;)Lscala/collection/mutable/Growable;
   #84 = NameAndType        #82:#83       // addAll$:(Lscala/collection/mutable/Growable;Lscala/collection/IterableOnce;)Lscala/collection/mutable/Growable;
   #85 = InterfaceMethodref #64.#84       // scala/collection/mutable/Growable.addAll$:(Lscala/collection/mutable/Growable;Lscala/collection/IterableOnce;)Lscala/collection/mutable/Growable;
   #86 = Utf8               $plus$plus$eq
   #87 = Utf8               $plus$plus$eq$
   #88 = NameAndType        #87:#83       // $plus$plus$eq$:(Lscala/collection/mutable/Growable;Lscala/collection/IterableOnce;)Lscala/collection/mutable/Growable;
   #89 = InterfaceMethodref #64.#88       // scala/collection/mutable/Growable.$plus$plus$eq$:(Lscala/collection/mutable/Growable;Lscala/collection/IterableOnce;)Lscala/collection/mutable/Growable;
   #90 = Utf8               ()Lscala/collection/IterableOnce;
   #91 = Utf8               ()TC;
   #92 = NameAndType        #15:#13       // elems:Lscala/collection/IterableOnce;
   #93 = Fieldref           #2.#92        // scala/collection/mutable/ImmutableBuilder.elems:Lscala/collection/IterableOnce;
   #94 = Utf8               elems_$eq
   #95 = Utf8               (Lscala/collection/IterableOnce;)V
   #96 = Utf8               (TC;)V
   #97 = Utf8               x$1
   #98 = Utf8               clear
   #99 = Utf8               ()V
  #100 = NameAndType        #12:#13       // empty:Lscala/collection/IterableOnce;
  #101 = Fieldref           #2.#100       // scala/collection/mutable/ImmutableBuilder.empty:Lscala/collection/IterableOnce;
  #102 = NameAndType        #94:#95       // elems_$eq:(Lscala/collection/IterableOnce;)V
  #103 = Methodref          #2.#102       // scala/collection/mutable/ImmutableBuilder.elems_$eq:(Lscala/collection/IterableOnce;)V
  #104 = Utf8               result
  #105 = NameAndType        #15:#90       // elems:()Lscala/collection/IterableOnce;
  #106 = Methodref          #2.#105       // scala/collection/mutable/ImmutableBuilder.elems:()Lscala/collection/IterableOnce;
  #107 = Utf8               knownSize
  #108 = Utf8               scala/collection/IterableOnce
  #109 = Class              #108          // scala/collection/IterableOnce
  #110 = NameAndType        #107:#36      // knownSize:()I
  #111 = InterfaceMethodref #109.#110     // scala/collection/IterableOnce.knownSize:()I
  #112 = Utf8               ()Ljava/lang/Object;
  #113 = NameAndType        #104:#90      // result:()Lscala/collection/IterableOnce;
  #114 = Methodref          #2.#113       // scala/collection/mutable/ImmutableBuilder.result:()Lscala/collection/IterableOnce;
  #115 = Utf8               <init>
  #116 = NameAndType        #115:#99      // "<init>":()V
  #117 = Methodref          #5.#116       // java/lang/Object."<init>":()V
  #118 = Utf8               Signature
  #119 = Utf8               Code
  #120 = Utf8               LineNumberTable
  #121 = Utf8               LocalVariableTable
  #122 = Utf8               MethodParameters
  #123 = Utf8               Deprecated
  #124 = Utf8               SourceFile
  #125 = Utf8               RuntimeVisibleAnnotations
  #126 = Utf8               ScalaInlineInfo
  #127 = Utf8               ScalaSig
{
  private final C empty;
    descriptor: Lscala/collection/IterableOnce;
    flags: (0x0012) ACC_PRIVATE, ACC_FINAL
    Signature: #14                          // TC;

  private C elems;
    descriptor: Lscala/collection/IterableOnce;
    flags: (0x0002) ACC_PRIVATE
    Signature: #14                          // TC;

  public void sizeHint(int);
    descriptor: (I)V
    flags: (0x0001) ACC_PUBLIC
    Code:
      stack=2, locals=2, args_size=2
         0: aload_0
         1: iload_1
         2: invokestatic  #24                 // InterfaceMethod scala/collection/mutable/Builder.sizeHint$:(Lscala/collection/mutable/Builder;I)V
         5: return
      LineNumberTable:
        line 21: 0
      LocalVariableTable:
        Start  Length  Slot  Name   Signature
            0       6     0  this   Lscala/collection/mutable/ImmutableBuilder;
            0       6     1  size   I
    MethodParameters:
      Name                           Flags
      size                           final

  public final void sizeHint(scala.collection.IterableOnce<?>, int);
    descriptor: (Lscala/collection/IterableOnce;I)V
    flags: (0x0011) ACC_PUBLIC, ACC_FINAL
    Code:
      stack=3, locals=3, args_size=3
         0: aload_0
         1: aload_1
         2: iload_2
         3: invokestatic  #34                 // InterfaceMethod scala/collection/mutable/Builder.sizeHint$:(Lscala/collection/mutable/Builder;Lscala/collection/IterableOnce;I)V
         6: return
      LineNumberTable:
        line 21: 0
      LocalVariableTable:
        Start  Length  Slot  Name   Signature
            0       7     0  this   Lscala/collection/mutable/ImmutableBuilder;
            0       7     1  coll   Lscala/collection/IterableOnce;
            0       7     2 delta   I
    Signature: #29                          // (Lscala/collection/IterableOnce<*>;I)V
    MethodParameters:
      Name                           Flags
      coll                           final
      delta                          final

  public final int sizeHint$default$2();
    descriptor: ()I
    flags: (0x0011) ACC_PUBLIC, ACC_FINAL
    Code:
      stack=1, locals=1, args_size=1
         0: aload_0
         1: invokestatic  #40                 // InterfaceMethod scala/collection/mutable/Builder.sizeHint$default$2$:(Lscala/collection/mutable/Builder;)I
         4: ireturn
      LineNumberTable:
        line 21: 0
      LocalVariableTable:
        Start  Length  Slot  Name   Signature
            0       5     0  this   Lscala/collection/mutable/ImmutableBuilder;

  public final void sizeHintBounded(int, scala.collection.Iterable<?>);
    descriptor: (ILscala/collection/Iterable;)V
    flags: (0x0011) ACC_PUBLIC, ACC_FINAL
    Code:
      stack=3, locals=3, args_size=3
         0: aload_0
         1: iload_1
         2: aload_2
         3: invokestatic  #48                 // InterfaceMethod scala/collection/mutable/Builder.sizeHintBounded$:(Lscala/collection/mutable/Builder;ILscala/collection/Iterable;)V
         6: return
      LineNumberTable:
        line 21: 0
      LocalVariableTable:
        Start  Length  Slot  Name   Signature
            0       7     0  this   Lscala/collection/mutable/ImmutableBuilder;
            0       7     1  size   I
            0       7     2 boundingColl   Lscala/collection/Iterable;
    Signature: #43                          // (ILscala/collection/Iterable<*>;)V
    MethodParameters:
      Name                           Flags
      size                           final
      boundingColl                   final

  public <NewTo extends java.lang.Object> scala.collection.mutable.Builder<A, NewTo> mapResult(scala.Function1<C, NewTo>);
    descriptor: (Lscala/Function1;)Lscala/collection/mutable/Builder;
    flags: (0x0001) ACC_PUBLIC
    Code:
      stack=2, locals=2, args_size=2
         0: aload_0
         1: aload_1
         2: invokestatic  #57                 // InterfaceMethod scala/collection/mutable/Builder.mapResult$:(Lscala/collection/mutable/Builder;Lscala/Function1;)Lscala/collection/mutable/Builder;
         5: areturn
      LineNumberTable:
        line 21: 0
      LocalVariableTable:
        Start  Length  Slot  Name   Signature
            0       6     0  this   Lscala/collection/mutable/ImmutableBuilder;
            0       6     1     f   Lscala/Function1;
    Signature: #52                          // <NewTo:Ljava/lang/Object;>(Lscala/Function1<TC;TNewTo;>;)Lscala/collection/mutable/Builder<TA;TNewTo;>;
    MethodParameters:
      Name                           Flags
      f                              final

  public final scala.collection.mutable.Growable<A> $plus$eq(A);
    descriptor: (Ljava/lang/Object;)Lscala/collection/mutable/Growable;
    flags: (0x0011) ACC_PUBLIC, ACC_FINAL
    Code:
      stack=2, locals=2, args_size=2
         0: aload_0
         1: aload_1
         2: invokestatic  #68                 // InterfaceMethod scala/collection/mutable/Growable.$plus$eq$:(Lscala/collection/mutable/Growable;Ljava/lang/Object;)Lscala/collection/mutable/Growable;
         5: areturn
      LineNumberTable:
        line 21: 0
      LocalVariableTable:
        Start  Length  Slot  Name   Signature
            0       6     0  this   Lscala/collection/mutable/ImmutableBuilder;
            0       6     1  elem   Ljava/lang/Object;
    Signature: #61                          // (TA;)Lscala/collection/mutable/Growable<TA;>;
    MethodParameters:
      Name                           Flags
      elem                           final

  public final scala.collection.mutable.Growable<A> $plus$eq(A, A, scala.collection.immutable.Seq<A>);
    descriptor: (Ljava/lang/Object;Ljava/lang/Object;Lscala/collection/immutable/Seq;)Lscala/collection/mutable/Growable;
    flags: (0x0011) ACC_PUBLIC, ACC_FINAL
    Code:
      stack=4, locals=4, args_size=4
         0: aload_0
         1: aload_1
         2: aload_2
         3: aload_3
         4: invokestatic  #76                 // InterfaceMethod scala/collection/mutable/Growable.$plus$eq$:(Lscala/collection/mutable/Growable;Ljava/lang/Object;Ljava/lang/Object;Lscala/collection/immutable/Seq;)Lscala/collection/mutable/Growable;
         7: areturn
      LineNumberTable:
        line 21: 0
      LocalVariableTable:
        Start  Length  Slot  Name   Signature
            0       8     0  this   Lscala/collection/mutable/ImmutableBuilder;
            0       8     1 elem1   Ljava/lang/Object;
            0       8     2 elem2   Ljava/lang/Object;
            0       8     3 elems   Lscala/collection/immutable/Seq;
    Signature: #71                          // (TA;TA;Lscala/collection/immutable/Seq<TA;>;)Lscala/collection/mutable/Growable<TA;>;
    Deprecated: true
    MethodParameters:
      Name                           Flags
      elem1                          final
      elem2                          final
      elems                          final

  public scala.collection.mutable.Growable<A> addAll(scala.collection.IterableOnce<A>);
    descriptor: (Lscala/collection/IterableOnce;)Lscala/collection/mutable/Growable;
    flags: (0x0001) ACC_PUBLIC
    Code:
      stack=2, locals=2, args_size=2
         0: aload_0
         1: aload_1
         2: invokestatic  #85                 // InterfaceMethod scala/collection/mutable/Growable.addAll$:(Lscala/collection/mutable/Growable;Lscala/collection/IterableOnce;)Lscala/collection/mutable/Growable;
         5: areturn
      LineNumberTable:
        line 21: 0
      LocalVariableTable:
        Start  Length  Slot  Name   Signature
            0       6     0  this   Lscala/collection/mutable/ImmutableBuilder;
            0       6     1    xs   Lscala/collection/IterableOnce;
    Signature: #80                          // (Lscala/collection/IterableOnce<TA;>;)Lscala/collection/mutable/Growable<TA;>;
    MethodParameters:
      Name                           Flags
      xs                             final

  public final scala.collection.mutable.Growable<A> $plus$plus$eq(scala.collection.IterableOnce<A>);
    descriptor: (Lscala/collection/IterableOnce;)Lscala/collection/mutable/Growable;
    flags: (0x0011) ACC_PUBLIC, ACC_FINAL
    Code:
      stack=2, locals=2, args_size=2
         0: aload_0
         1: aload_1
         2: invokestatic  #89                 // InterfaceMethod scala/collection/mutable/Growable.$plus$plus$eq$:(Lscala/collection/mutable/Growable;Lscala/collection/IterableOnce;)Lscala/collection/mutable/Growable;
         5: areturn
      LineNumberTable:
        line 21: 0
      LocalVariableTable:
        Start  Length  Slot  Name   Signature
            0       6     0  this   Lscala/collection/mutable/ImmutableBuilder;
            0       6     1    xs   Lscala/collection/IterableOnce;
    Signature: #80                          // (Lscala/collection/IterableOnce<TA;>;)Lscala/collection/mutable/Growable<TA;>;
    MethodParameters:
      Name                           Flags
      xs                             final

  public C elems();
    descriptor: ()Lscala/collection/IterableOnce;
    flags: (0x0001) ACC_PUBLIC
    Code:
      stack=1, locals=1, args_size=1
         0: aload_0
         1: getfield      #93                 // Field elems:Lscala/collection/IterableOnce;
         4: areturn
      LineNumberTable:
        line 24: 0
      LocalVariableTable:
        Start  Length  Slot  Name   Signature
            0       5     0  this   Lscala/collection/mutable/ImmutableBuilder;
    Signature: #91                          // ()TC;

  public void elems_$eq(C);
    descriptor: (Lscala/collection/IterableOnce;)V
    flags: (0x0001) ACC_PUBLIC
    Code:
      stack=2, locals=2, args_size=2
         0: aload_0
         1: aload_1
         2: putfield      #93                 // Field elems:Lscala/collection/IterableOnce;
         5: return
      LineNumberTable:
        line 24: 0
      LocalVariableTable:
        Start  Length  Slot  Name   Signature
            0       6     0  this   Lscala/collection/mutable/ImmutableBuilder;
            0       6     1   x$1   Lscala/collection/IterableOnce;
    Signature: #96                          // (TC;)V
    MethodParameters:
      Name                           Flags
      x$1                            final

  public void clear();
    descriptor: ()V
    flags: (0x0001) ACC_PUBLIC
    Code:
      stack=2, locals=1, args_size=1
         0: aload_0
         1: aload_0
         2: getfield      #101                // Field empty:Lscala/collection/IterableOnce;
         5: invokevirtual #103                // Method elems_$eq:(Lscala/collection/IterableOnce;)V
         8: return
      LineNumberTable:
        line 26: 0
      LocalVariableTable:
        Start  Length  Slot  Name   Signature
            0       9     0  this   Lscala/collection/mutable/ImmutableBuilder;

  public C result();
    descriptor: ()Lscala/collection/IterableOnce;
    flags: (0x0001) ACC_PUBLIC
    Code:
      stack=1, locals=1, args_size=1
         0: aload_0
         1: invokevirtual #106                // Method elems:()Lscala/collection/IterableOnce;
         4: areturn
      LineNumberTable:
        line 28: 0
      LocalVariableTable:
        Start  Length  Slot  Name   Signature
            0       5     0  this   Lscala/collection/mutable/ImmutableBuilder;
    Signature: #91                          // ()TC;

  public int knownSize();
    descriptor: ()I
    flags: (0x0001) ACC_PUBLIC
    Code:
      stack=1, locals=1, args_size=1
         0: aload_0
         1: invokevirtual #106                // Method elems:()Lscala/collection/IterableOnce;
         4: invokeinterface #111,  1          // InterfaceMethod scala/collection/IterableOnce.knownSize:()I
         9: ireturn
      LineNumberTable:
        line 30: 0
      LocalVariableTable:
        Start  Length  Slot  Name   Signature
            0      10     0  this   Lscala/collection/mutable/ImmutableBuilder;

  public java.lang.Object result();
    descriptor: ()Ljava/lang/Object;
    flags: (0x1041) ACC_PUBLIC, ACC_BRIDGE, ACC_SYNTHETIC
    Code:
      stack=1, locals=1, args_size=1
         0: aload_0
         1: invokevirtual #114                // Method result:()Lscala/collection/IterableOnce;
         4: areturn
      LineNumberTable:
        line 21: 0
      LocalVariableTable:
        Start  Length  Slot  Name   Signature
            0       5     0  this   Lscala/collection/mutable/ImmutableBuilder;

  public scala.collection.mutable.ImmutableBuilder(C);
    descriptor: (Lscala/collection/IterableOnce;)V
    flags: (0x0001) ACC_PUBLIC
    Code:
      stack=2, locals=2, args_size=2
         0: aload_0
         1: aload_1
         2: putfield      #101                // Field empty:Lscala/collection/IterableOnce;
         5: aload_0
         6: invokespecial #117                // Method java/lang/Object."<init>":()V
         9: aload_0
        10: aload_1
        11: putfield      #93                 // Field elems:Lscala/collection/IterableOnce;
        14: return
      LineNumberTable:
        line 21: 0
        line 22: 5
        line 24: 9
        line 21: 14
      LocalVariableTable:
        Start  Length  Slot  Name   Signature
            0      15     0  this   Lscala/collection/mutable/ImmutableBuilder;
            0      15     1 empty   Lscala/collection/IterableOnce;
    Signature: #96                          // (TC;)V
    MethodParameters:
      Name                           Flags
      empty                          final
}
Signature: #3                           // <A:Ljava/lang/Object;C::Lscala/collection/IterableOnce<*>;>Ljava/lang/Object;Lscala/collection/mutable/ReusableBuilder<TA;TC;>;
SourceFile: "ImmutableBuilder.scala"
RuntimeVisibleAnnotations:
  0: #9(#10=s#11)
    scala.reflect.ScalaSignature(
      bytes="\u0006\u0005)3Q!\u0003\u0006\u0002\u0002EA\u0001B\r\u0001\u0003\u0002\u0003\u0006IA\n\u0005\u0006g\u0001!\t\u0001\u000e\u0005\bo\u0001\u0001\r\u0011\"\u00059\u0011\u001dI\u0004\u00011A\u0005\u0012iBa\u0001\u0011\u0001!B\u00131\u0003\"B!\u0001\t\u0003\u0011\u0005\"B\"\u0001\t\u0003!\u0005\"B#\u0001\t\u00032%\u0001E%n[V$\u0018M\u00197f\u0005VLG\u000eZ3s\u0015\tYA\"A\u0004nkR\f\'\r\\3\u000b\u00055q\u0011AC2pY2,7\r^5p]*\tq\"A\u0003tG\u0006d\u0017m\u0001\u0001\u0016\u0007IireE\u0002\u0001\']\u0001\"\u0001F\u000b\u000e\u00039I!A\u0006\b\u0003\r\u0005s\u0017PU3g!\u0011A\u0012d\u0007\u0014\u000e\u0003)I!A\u0007\u0006\u0003\u001fI+Wo]1cY\u0016\u0014U/\u001b7eKJ\u0004\"\u0001H\u000f\r\u0001\u00111a\u0004\u0001EC\u0002}\u0011\u0011!Q\t\u0003A\r\u0002\"\u0001F\u0011\n\u0005\tr!a\u0002(pi\"Lgn\u001a\t\u0003)\u0011J!!\n\b\u0003\u0007\u0005s\u0017\u0010\u0005\u0002\u001dO\u0011)\u0001\u0006\u0001b\u0001S\t\t1)\u0005\u0002!UA\u00121\u0006\r\t\u0004Y5zS\"\u0001\u0007\n\u00059b!\u0001D%uKJ\f\'\r\\3P]\u000e,\u0007C\u0001\u000f1\t%\tt%!A\u0001\u0002\u000b\u0005qDA\u0002`IE\nQ!Z7qif\fa\u0001P5oSRtDCA\u001b7!\u0011A\u0002a\u0007\u0014\t\u000bI\u0012\u0001\u0019\u0001\u0014\u0002\u000b\u0015dW-\\:\u0016\u0003\u0019\n\u0011\"\u001a7f[N|F%Z9\u0015\u0005mr\u0004C\u0001\u000b=\u0013\tidB\u0001\u0003V]&$\bbB \u0005\u0003\u0003\u0005\rAJ\u0001\u0004q\u0012\n\u0014AB3mK6\u001c\b%A\u0003dY\u0016\f\'\u000fF\u0001<\u0003\u0019\u0011Xm];miR\ta%A\u0005l]><hnU5{KV\tq\t\u0005\u0002\u0015\u0011&\u0011\u0011J\u0004\u0002\u0004\u0013:$\b"
    )
  ScalaInlineInfo: length = 0x54 (unknown attribute)
   01 00 00 10 00 3B 00 3C 05 00 3B 00 46 05 00 56
   00 4F 05 00 73 00 5F 00 00 4E 00 4F 00 00 62 00
   63 00 00 0F 00 5A 00 00 5E 00 5F 00 00 6B 00 24
   00 00 32 00 33 00 00 68 00 70 00 00 68 00 5A 00
   00 10 00 11 00 00 10 00 1C 01 00 23 00 24 01 00
   29 00 2A 01
  ScalaSig: length = 0x3 (unknown attribute)
   05 02 00
