Classfile /Users/mw/Projects/slang-braindump/.jar/jar11/assemble/slang-braindump/assemble/content/scala/collection/mutable/LinkedHashMap$$anon$4.class
  Last modified May 29, 2022; size 1634 bytes
  SHA-256 checksum c221b79895c6e6b6d1622e6b10b68d8f514425680f69960a241c312760034f4f
  Compiled from "LinkedHashMap.scala"
public final class scala.collection.mutable.LinkedHashMap$$anon$4 extends scala.collection.AbstractIterator<V>
  minor version: 0
  major version: 52
  flags: (0x0031) ACC_PUBLIC, ACC_FINAL, ACC_SUPER
  this_class: #2                          // scala/collection/mutable/LinkedHashMap$$anon$4
  super_class: #5                         // scala/collection/AbstractIterator
  interfaces: 0, fields: 1, methods: 3, attributes: 6
Constant pool:
   #1 = Utf8               scala/collection/mutable/LinkedHashMap$$anon$4
   #2 = Class              #1             // scala/collection/mutable/LinkedHashMap$$anon$4
   #3 = Utf8               Lscala/collection/AbstractIterator<TV;>;
   #4 = Utf8               scala/collection/AbstractIterator
   #5 = Class              #4             // scala/collection/AbstractIterator
   #6 = Utf8               LinkedHashMap.scala
   #7 = Utf8               scala/collection/mutable/LinkedHashMap
   #8 = Class              #7             // scala/collection/mutable/LinkedHashMap
   #9 = Utf8               valuesIterator
  #10 = Utf8               ()Lscala/collection/Iterator;
  #11 = NameAndType        #9:#10         // valuesIterator:()Lscala/collection/Iterator;
  #12 = Utf8               scala/collection/mutable/LinkedHashMap$LinkedEntry
  #13 = Class              #12            // scala/collection/mutable/LinkedHashMap$LinkedEntry
  #14 = Utf8               LinkedEntry
  #15 = Utf8               cur
  #16 = Utf8               Lscala/collection/mutable/LinkedHashMap$LinkedEntry;
  #17 = Utf8               Lscala/collection/mutable/LinkedHashMap$LinkedEntry<TK;TV;>;
  #18 = Utf8               hasNext
  #19 = Utf8               ()Z
  #20 = NameAndType        #15:#16        // cur:Lscala/collection/mutable/LinkedHashMap$LinkedEntry;
  #21 = Fieldref           #2.#20         // scala/collection/mutable/LinkedHashMap$$anon$4.cur:Lscala/collection/mutable/LinkedHashMap$LinkedEntry;
  #22 = Utf8               this
  #23 = Utf8               Lscala/collection/mutable/LinkedHashMap$$anon$4;
  #24 = Utf8               next
  #25 = Utf8               ()Ljava/lang/Object;
  #26 = Utf8               ()TV;
  #27 = NameAndType        #18:#19        // hasNext:()Z
  #28 = Methodref          #2.#27         // scala/collection/mutable/LinkedHashMap$$anon$4.hasNext:()Z
  #29 = Utf8               value
  #30 = NameAndType        #29:#25        // value:()Ljava/lang/Object;
  #31 = Methodref          #13.#30        // scala/collection/mutable/LinkedHashMap$LinkedEntry.value:()Ljava/lang/Object;
  #32 = Utf8               later
  #33 = Utf8               ()Lscala/collection/mutable/LinkedHashMap$LinkedEntry;
  #34 = NameAndType        #32:#33        // later:()Lscala/collection/mutable/LinkedHashMap$LinkedEntry;
  #35 = Methodref          #13.#34        // scala/collection/mutable/LinkedHashMap$LinkedEntry.later:()Lscala/collection/mutable/LinkedHashMap$LinkedEntry;
  #36 = Utf8               scala/collection/Iterator$
  #37 = Class              #36            // scala/collection/Iterator$
  #38 = Utf8               MODULE$
  #39 = Utf8               Lscala/collection/Iterator$;
  #40 = NameAndType        #38:#39        // MODULE$:Lscala/collection/Iterator$;
  #41 = Fieldref           #37.#40        // scala/collection/Iterator$.MODULE$:Lscala/collection/Iterator$;
  #42 = Utf8               scala$collection$Iterator$$_empty
  #43 = Utf8               Lscala/collection/Iterator;
  #44 = NameAndType        #42:#43        // scala$collection$Iterator$$_empty:Lscala/collection/Iterator;
  #45 = Fieldref           #37.#44        // scala/collection/Iterator$.scala$collection$Iterator$$_empty:Lscala/collection/Iterator;
  #46 = Utf8               scala/collection/Iterator
  #47 = Class              #46            // scala/collection/Iterator
  #48 = NameAndType        #24:#25        // next:()Ljava/lang/Object;
  #49 = InterfaceMethodref #47.#48        // scala/collection/Iterator.next:()Ljava/lang/Object;
  #50 = Utf8               res
  #51 = Utf8               Ljava/lang/Object;
  #52 = Utf8               <init>
  #53 = Utf8               (Lscala/collection/mutable/LinkedHashMap;)V
  #54 = Utf8               $outer
  #55 = Utf8               ()V
  #56 = NameAndType        #52:#55        // "<init>":()V
  #57 = Methodref          #5.#56         // scala/collection/AbstractIterator."<init>":()V
  #58 = Utf8               firstEntry
  #59 = NameAndType        #58:#33        // firstEntry:()Lscala/collection/mutable/LinkedHashMap$LinkedEntry;
  #60 = Methodref          #8.#59         // scala/collection/mutable/LinkedHashMap.firstEntry:()Lscala/collection/mutable/LinkedHashMap$LinkedEntry;
  #61 = Utf8               Lscala/collection/mutable/LinkedHashMap;
  #62 = Utf8               Signature
  #63 = Utf8               Code
  #64 = Utf8               StackMapTable
  #65 = Utf8               LineNumberTable
  #66 = Utf8               LocalVariableTable
  #67 = Utf8               MethodParameters
  #68 = Utf8               InnerClasses
  #69 = Utf8               EnclosingMethod
  #70 = Utf8               SourceFile
  #71 = Utf8               ScalaInlineInfo
  #72 = Utf8               Scala
{
  private scala.collection.mutable.LinkedHashMap$LinkedEntry<K, V> cur;
    descriptor: Lscala/collection/mutable/LinkedHashMap$LinkedEntry;
    flags: (0x0002) ACC_PRIVATE
    Signature: #17                          // Lscala/collection/mutable/LinkedHashMap$LinkedEntry<TK;TV;>;

  public boolean hasNext();
    descriptor: ()Z
    flags: (0x0001) ACC_PUBLIC
    Code:
      stack=1, locals=1, args_size=1
         0: aload_0
         1: getfield      #21                 // Field cur:Lscala/collection/mutable/LinkedHashMap$LinkedEntry;
         4: ifnull        9
         7: iconst_1
         8: ireturn
         9: iconst_0
        10: ireturn
      StackMapTable: number_of_entries = 1
        frame_type = 9 /* same */
      LineNumberTable:
        line 219: 0
      LocalVariableTable:
        Start  Length  Slot  Name   Signature
            0      11     0  this   Lscala/collection/mutable/LinkedHashMap$$anon$4;

  public V next();
    descriptor: ()Ljava/lang/Object;
    flags: (0x0001) ACC_PUBLIC
    Code:
      stack=2, locals=2, args_size=1
         0: aload_0
         1: invokevirtual #28                 // Method hasNext:()Z
         4: ifeq          28
         7: aload_0
         8: getfield      #21                 // Field cur:Lscala/collection/mutable/LinkedHashMap$LinkedEntry;
        11: invokevirtual #31                 // Method scala/collection/mutable/LinkedHashMap$LinkedEntry.value:()Ljava/lang/Object;
        14: astore_1
        15: aload_0
        16: aload_0
        17: getfield      #21                 // Field cur:Lscala/collection/mutable/LinkedHashMap$LinkedEntry;
        20: invokevirtual #35                 // Method scala/collection/mutable/LinkedHashMap$LinkedEntry.later:()Lscala/collection/mutable/LinkedHashMap$LinkedEntry;
        23: putfield      #21                 // Field cur:Lscala/collection/mutable/LinkedHashMap$LinkedEntry;
        26: aload_1
        27: areturn
        28: getstatic     #41                 // Field scala/collection/Iterator$.MODULE$:Lscala/collection/Iterator$;
        31: pop
        32: getstatic     #45                 // Field scala/collection/Iterator$.scala$collection$Iterator$$_empty:Lscala/collection/Iterator;
        35: invokeinterface #49,  1           // InterfaceMethod scala/collection/Iterator.next:()Ljava/lang/Object;
        40: areturn
      StackMapTable: number_of_entries = 1
        frame_type = 28 /* same */
      LineNumberTable:
        line 221: 0
        line 222: 28
      LocalVariableTable:
        Start  Length  Slot  Name   Signature
           15      12     1   res   Ljava/lang/Object;
            0      41     0  this   Lscala/collection/mutable/LinkedHashMap$$anon$4;
    Signature: #26                          // ()TV;

  public scala.collection.mutable.LinkedHashMap$$anon$4(scala.collection.mutable.LinkedHashMap);
    descriptor: (Lscala/collection/mutable/LinkedHashMap;)V
    flags: (0x0001) ACC_PUBLIC
    Code:
      stack=2, locals=2, args_size=2
         0: aload_0
         1: invokespecial #57                 // Method scala/collection/AbstractIterator."<init>":()V
         4: aload_0
         5: aload_1
         6: invokevirtual #60                 // Method scala/collection/mutable/LinkedHashMap.firstEntry:()Lscala/collection/mutable/LinkedHashMap$LinkedEntry;
         9: putfield      #21                 // Field cur:Lscala/collection/mutable/LinkedHashMap$LinkedEntry;
        12: return
      LineNumberTable:
        line 217: 0
        line 218: 4
        line 217: 12
      LocalVariableTable:
        Start  Length  Slot  Name   Signature
            0      13     0  this   Lscala/collection/mutable/LinkedHashMap$$anon$4;
            0      13     1 $outer   Lscala/collection/mutable/LinkedHashMap;
    MethodParameters:
      Name                           Flags
      $outer                         final synthetic
}
InnerClasses:
  public final #2;                        // class scala/collection/mutable/LinkedHashMap$$anon$4
  public static final #14= #13 of #8;     // LinkedEntry=class scala/collection/mutable/LinkedHashMap$LinkedEntry of class scala/collection/mutable/LinkedHashMap
EnclosingMethod: #8.#11                 // scala.collection.mutable.LinkedHashMap.valuesIterator
Signature: #3                           // Lscala/collection/AbstractIterator<TV;>;
SourceFile: "LinkedHashMap.scala"
  ScalaInlineInfo: length = 0x13 (unknown attribute)
   01 01 00 03 00 34 00 35 01 00 12 00 13 01 00 18
   00 19 01
  Scala: length = 0x0 (unknown attribute)

