Classfile /Users/mw/Projects/slang-braindump/.jar/jar11/assemble/slang-braindump/assemble/content/scala/collection/mutable/MutationTracker$CheckedIterator.class
  Last modified May 29, 2022; size 1598 bytes
  SHA-256 checksum 08ac5dffa44bf02bc6a01de265aac828d8e11e883bf5affe4d453b182c95a785
  Compiled from "MutationTracker.scala"
public final class scala.collection.mutable.MutationTracker$CheckedIterator<A extends java.lang.Object> extends scala.collection.AbstractIterator<A>
  minor version: 0
  major version: 52
  flags: (0x0031) ACC_PUBLIC, ACC_FINAL, ACC_SUPER
  this_class: #2                          // scala/collection/mutable/MutationTracker$CheckedIterator
  super_class: #5                         // scala/collection/AbstractIterator
  interfaces: 0, fields: 3, methods: 3, attributes: 5
Constant pool:
   #1 = Utf8               scala/collection/mutable/MutationTracker$CheckedIterator
   #2 = Class              #1             // scala/collection/mutable/MutationTracker$CheckedIterator
   #3 = Utf8               <A:Ljava/lang/Object;>Lscala/collection/AbstractIterator<TA;>;
   #4 = Utf8               scala/collection/AbstractIterator
   #5 = Class              #4             // scala/collection/AbstractIterator
   #6 = Utf8               MutationTracker.scala
   #7 = Utf8               scala/collection/mutable/MutationTracker
   #8 = Class              #7             // scala/collection/mutable/MutationTracker
   #9 = Utf8               CheckedIterator
  #10 = Utf8               underlying
  #11 = Utf8               Lscala/collection/Iterator;
  #12 = Utf8               Lscala/collection/Iterator<TA;>;
  #13 = Utf8               mutationCount
  #14 = Utf8               Lscala/Function0;
  #15 = Utf8               Lscala/Function0<Ljava/lang/Object;>;
  #16 = Utf8               expectedCount
  #17 = Utf8               I
  #18 = Utf8               hasNext
  #19 = Utf8               ()Z
  #20 = Utf8               scala/collection/mutable/MutationTracker$
  #21 = Class              #20            // scala/collection/mutable/MutationTracker$
  #22 = Utf8               MODULE$
  #23 = Utf8               Lscala/collection/mutable/MutationTracker$;
  #24 = NameAndType        #22:#23        // MODULE$:Lscala/collection/mutable/MutationTracker$;
  #25 = Fieldref           #21.#24        // scala/collection/mutable/MutationTracker$.MODULE$:Lscala/collection/mutable/MutationTracker$;
  #26 = NameAndType        #16:#17        // expectedCount:I
  #27 = Fieldref           #2.#26         // scala/collection/mutable/MutationTracker$CheckedIterator.expectedCount:I
  #28 = NameAndType        #13:#14        // mutationCount:Lscala/Function0;
  #29 = Fieldref           #2.#28         // scala/collection/mutable/MutationTracker$CheckedIterator.mutationCount:Lscala/Function0;
  #30 = Utf8               scala/Function0
  #31 = Class              #30            // scala/Function0
  #32 = Utf8               apply$mcI$sp
  #33 = Utf8               ()I
  #34 = NameAndType        #32:#33        // apply$mcI$sp:()I
  #35 = InterfaceMethodref #31.#34        // scala/Function0.apply$mcI$sp:()I
  #36 = Utf8               mutation occurred during iteration
  #37 = String             #36            // mutation occurred during iteration
  #38 = Utf8               checkMutations
  #39 = Utf8               (IILjava/lang/String;)V
  #40 = NameAndType        #38:#39        // checkMutations:(IILjava/lang/String;)V
  #41 = Methodref          #21.#40        // scala/collection/mutable/MutationTracker$.checkMutations:(IILjava/lang/String;)V
  #42 = NameAndType        #10:#11        // underlying:Lscala/collection/Iterator;
  #43 = Fieldref           #2.#42         // scala/collection/mutable/MutationTracker$CheckedIterator.underlying:Lscala/collection/Iterator;
  #44 = Utf8               scala/collection/Iterator
  #45 = Class              #44            // scala/collection/Iterator
  #46 = NameAndType        #18:#19        // hasNext:()Z
  #47 = InterfaceMethodref #45.#46        // scala/collection/Iterator.hasNext:()Z
  #48 = Utf8               this
  #49 = Utf8               Lscala/collection/mutable/MutationTracker$CheckedIterator;
  #50 = Utf8               next
  #51 = Utf8               ()Ljava/lang/Object;
  #52 = Utf8               ()TA;
  #53 = NameAndType        #50:#51        // next:()Ljava/lang/Object;
  #54 = InterfaceMethodref #45.#53        // scala/collection/Iterator.next:()Ljava/lang/Object;
  #55 = Utf8               <init>
  #56 = Utf8               (Lscala/collection/Iterator;Lscala/Function0;)V
  #57 = Utf8               (Lscala/collection/Iterator<TA;>;Lscala/Function0<Ljava/lang/Object;>;)V
  #58 = Utf8               ()V
  #59 = NameAndType        #55:#58        // "<init>":()V
  #60 = Methodref          #5.#59         // scala/collection/AbstractIterator."<init>":()V
  #61 = Utf8               Signature
  #62 = Utf8               Code
  #63 = Utf8               LineNumberTable
  #64 = Utf8               LocalVariableTable
  #65 = Utf8               MethodParameters
  #66 = Utf8               InnerClasses
  #67 = Utf8               SourceFile
  #68 = Utf8               ScalaInlineInfo
  #69 = Utf8               Scala
{
  private final scala.collection.Iterator<A> underlying;
    descriptor: Lscala/collection/Iterator;
    flags: (0x0012) ACC_PRIVATE, ACC_FINAL
    Signature: #12                          // Lscala/collection/Iterator<TA;>;

  private final scala.Function0<java.lang.Object> mutationCount;
    descriptor: Lscala/Function0;
    flags: (0x0012) ACC_PRIVATE, ACC_FINAL
    Signature: #15                          // Lscala/Function0<Ljava/lang/Object;>;

  private final int expectedCount;
    descriptor: I
    flags: (0x0012) ACC_PRIVATE, ACC_FINAL

  public boolean hasNext();
    descriptor: ()Z
    flags: (0x0001) ACC_PUBLIC
    Code:
      stack=4, locals=1, args_size=1
         0: getstatic     #25                 // Field scala/collection/mutable/MutationTracker$.MODULE$:Lscala/collection/mutable/MutationTracker$;
         3: aload_0
         4: getfield      #27                 // Field expectedCount:I
         7: aload_0
         8: getfield      #29                 // Field mutationCount:Lscala/Function0;
        11: invokeinterface #35,  1           // InterfaceMethod scala/Function0.apply$mcI$sp:()I
        16: ldc           #37                 // String mutation occurred during iteration
        18: invokevirtual #41                 // Method scala/collection/mutable/MutationTracker$.checkMutations:(IILjava/lang/String;)V
        21: aload_0
        22: getfield      #43                 // Field underlying:Lscala/collection/Iterator;
        25: invokeinterface #47,  1           // InterfaceMethod scala/collection/Iterator.hasNext:()Z
        30: ireturn
      LineNumberTable:
        line 73: 0
        line 59: 16
        line 74: 21
      LocalVariableTable:
        Start  Length  Slot  Name   Signature
            0      31     0  this   Lscala/collection/mutable/MutationTracker$CheckedIterator;

  public A next();
    descriptor: ()Ljava/lang/Object;
    flags: (0x0001) ACC_PUBLIC
    Code:
      stack=1, locals=1, args_size=1
         0: aload_0
         1: getfield      #43                 // Field underlying:Lscala/collection/Iterator;
         4: invokeinterface #54,  1           // InterfaceMethod scala/collection/Iterator.next:()Ljava/lang/Object;
         9: areturn
      LineNumberTable:
        line 76: 0
      LocalVariableTable:
        Start  Length  Slot  Name   Signature
            0      10     0  this   Lscala/collection/mutable/MutationTracker$CheckedIterator;
    Signature: #52                          // ()TA;

  public scala.collection.mutable.MutationTracker$CheckedIterator(scala.collection.Iterator<A>, scala.Function0<java.lang.Object>);
    descriptor: (Lscala/collection/Iterator;Lscala/Function0;)V
    flags: (0x0001) ACC_PUBLIC
    Code:
      stack=2, locals=3, args_size=3
         0: aload_0
         1: aload_1
         2: putfield      #43                 // Field underlying:Lscala/collection/Iterator;
         5: aload_0
         6: aload_2
         7: putfield      #29                 // Field mutationCount:Lscala/Function0;
        10: aload_0
        11: invokespecial #60                 // Method scala/collection/AbstractIterator."<init>":()V
        14: aload_0
        15: aload_2
        16: invokeinterface #35,  1           // InterfaceMethod scala/Function0.apply$mcI$sp:()I
        21: putfield      #27                 // Field expectedCount:I
        24: return
      LineNumberTable:
        line 69: 0
        line 70: 14
        line 69: 24
      LocalVariableTable:
        Start  Length  Slot  Name   Signature
            0      25     0  this   Lscala/collection/mutable/MutationTracker$CheckedIterator;
            0      25     1 underlying   Lscala/collection/Iterator;
            0      25     2 mutationCount   Lscala/Function0;
    Signature: #57                          // (Lscala/collection/Iterator<TA;>;Lscala/Function0<Ljava/lang/Object;>;)V
    MethodParameters:
      Name                           Flags
      underlying                     final
      mutationCount                  final
}
InnerClasses:
  public static final #9= #2 of #8;       // CheckedIterator=class scala/collection/mutable/MutationTracker$CheckedIterator of class scala/collection/mutable/MutationTracker
Signature: #3                           // <A:Ljava/lang/Object;>Lscala/collection/AbstractIterator<TA;>;
SourceFile: "MutationTracker.scala"
  ScalaInlineInfo: length = 0x13 (unknown attribute)
   01 01 00 03 00 37 00 38 01 00 12 00 13 01 00 32
   00 33 01
  Scala: length = 0x0 (unknown attribute)

