Classfile /Users/mw/Projects/slang-braindump/.jar/jar11/assemble/slang-braindump/assemble/content/scala/collection/mutable/MutationTracker$.class
  Last modified May 29, 2022; size 1046 bytes
  SHA-256 checksum 967df19bb237c4c3557dec794474005fbc65f20974b5877c8203fb6782c3252e
  Compiled from "MutationTracker.scala"
public final class scala.collection.mutable.MutationTracker$
  minor version: 0
  major version: 52
  flags: (0x0031) ACC_PUBLIC, ACC_FINAL, ACC_SUPER
  this_class: #2                          // scala/collection/mutable/MutationTracker$
  super_class: #4                         // java/lang/Object
  interfaces: 0, fields: 1, methods: 4, attributes: 3
Constant pool:
   #1 = Utf8               scala/collection/mutable/MutationTracker$
   #2 = Class              #1             // scala/collection/mutable/MutationTracker$
   #3 = Utf8               java/lang/Object
   #4 = Class              #3             // java/lang/Object
   #5 = Utf8               MutationTracker.scala
   #6 = Utf8               MODULE$
   #7 = Utf8               Lscala/collection/mutable/MutationTracker$;
   #8 = Utf8               <clinit>
   #9 = Utf8               ()V
  #10 = Utf8               <init>
  #11 = NameAndType        #10:#9         // "<init>":()V
  #12 = Methodref          #2.#11         // scala/collection/mutable/MutationTracker$."<init>":()V
  #13 = NameAndType        #6:#7          // MODULE$:Lscala/collection/mutable/MutationTracker$;
  #14 = Fieldref           #2.#13         // scala/collection/mutable/MutationTracker$.MODULE$:Lscala/collection/mutable/MutationTracker$;
  #15 = Utf8               checkMutations
  #16 = Utf8               (IILjava/lang/String;)V
  #17 = Utf8               java/util/ConcurrentModificationException
  #18 = Class              #17            // java/util/ConcurrentModificationException
  #19 = Utf8               expectedCount
  #20 = Utf8               actualCount
  #21 = Utf8               message
  #22 = Utf8               (Ljava/lang/String;)V
  #23 = NameAndType        #10:#22        // "<init>":(Ljava/lang/String;)V
  #24 = Methodref          #18.#23        // java/util/ConcurrentModificationException."<init>":(Ljava/lang/String;)V
  #25 = Utf8               this
  #26 = Utf8               I
  #27 = Utf8               Ljava/lang/String;
  #28 = Utf8               checkMutationsForIteration
  #29 = Utf8               (II)V
  #30 = Utf8               mutation occurred during iteration
  #31 = String             #30            // mutation occurred during iteration
  #32 = NameAndType        #15:#16        // checkMutations:(IILjava/lang/String;)V
  #33 = Methodref          #2.#32         // scala/collection/mutable/MutationTracker$.checkMutations:(IILjava/lang/String;)V
  #34 = Methodref          #4.#11         // java/lang/Object."<init>":()V
  #35 = Utf8               Code
  #36 = Utf8               LineNumberTable
  #37 = Utf8               StackMapTable
  #38 = Utf8               LocalVariableTable
  #39 = Utf8               Exceptions
  #40 = Utf8               MethodParameters
  #41 = Utf8               SourceFile
  #42 = Utf8               ScalaInlineInfo
  #43 = Utf8               Scala
{
  public static final scala.collection.mutable.MutationTracker$ MODULE$;
    descriptor: Lscala/collection/mutable/MutationTracker$;
    flags: (0x0019) ACC_PUBLIC, ACC_STATIC, ACC_FINAL

  public static {};
    descriptor: ()V
    flags: (0x0009) ACC_PUBLIC, ACC_STATIC
    Code:
      stack=2, locals=0, args_size=0
         0: new           #2                  // class scala/collection/mutable/MutationTracker$
         3: dup
         4: invokespecial #12                 // Method "<init>":()V
         7: putstatic     #14                 // Field MODULE$:Lscala/collection/mutable/MutationTracker$;
        10: return
      LineNumberTable:
        line 29: 0

  public void checkMutations(int, int, java.lang.String) throws java.util.ConcurrentModificationException;
    descriptor: (IILjava/lang/String;)V
    flags: (0x0001) ACC_PUBLIC
    Code:
      stack=3, locals=4, args_size=4
         0: iload_2
         1: iload_1
         2: if_icmpeq     14
         5: new           #18                 // class java/util/ConcurrentModificationException
         8: dup
         9: aload_3
        10: invokespecial #24                 // Method java/util/ConcurrentModificationException."<init>":(Ljava/lang/String;)V
        13: athrow
        14: return
      StackMapTable: number_of_entries = 1
        frame_type = 14 /* same */
      LineNumberTable:
        line 43: 0
      LocalVariableTable:
        Start  Length  Slot  Name   Signature
            0      15     0  this   Lscala/collection/mutable/MutationTracker$;
            0      15     1 expectedCount   I
            0      15     2 actualCount   I
            0      15     3 message   Ljava/lang/String;
    Exceptions:
      throws java.util.ConcurrentModificationException
    MethodParameters:
      Name                           Flags
      expectedCount                  final
      actualCount                    final
      message                        final

  public void checkMutationsForIteration(int, int) throws java.util.ConcurrentModificationException;
    descriptor: (II)V
    flags: (0x0001) ACC_PUBLIC
    Code:
      stack=4, locals=3, args_size=3
         0: aload_0
         1: iload_1
         2: iload_2
         3: ldc           #31                 // String mutation occurred during iteration
         5: invokevirtual #33                 // Method checkMutations:(IILjava/lang/String;)V
         8: return
      LineNumberTable:
        line 59: 0
      LocalVariableTable:
        Start  Length  Slot  Name   Signature
            0       9     0  this   Lscala/collection/mutable/MutationTracker$;
            0       9     1 expectedCount   I
            0       9     2 actualCount   I
    Exceptions:
      throws java.util.ConcurrentModificationException
    MethodParameters:
      Name                           Flags
      expectedCount                  final
      actualCount                    final

  private scala.collection.mutable.MutationTracker$();
    descriptor: ()V
    flags: (0x0002) ACC_PRIVATE
    Code:
      stack=1, locals=1, args_size=1
         0: aload_0
         1: invokespecial #34                 // Method java/lang/Object."<init>":()V
         4: return
      LineNumberTable:
        line 29: 0
      LocalVariableTable:
        Start  Length  Slot  Name   Signature
            0       5     0  this   Lscala/collection/mutable/MutationTracker$;
}
SourceFile: "MutationTracker.scala"
  ScalaInlineInfo: length = 0x13 (unknown attribute)
   01 01 00 03 00 0A 00 09 01 00 0F 00 10 01 00 1C
   00 1D 05
  Scala: length = 0x0 (unknown attribute)

