Classfile /Users/mw/Projects/slang-braindump/.jar/jar11/assemble/slang-braindump/assemble/content/scala/collection/mutable/RedBlackTree$Node$.class
  Last modified May 29, 2022; size 2835 bytes
  SHA-256 checksum ecce48bacda0121cb557855e9e1383229f8469de75b65c3fe8e225c8f39637b5
  Compiled from "RedBlackTree.scala"
public class scala.collection.mutable.RedBlackTree$Node$
  minor version: 0
  major version: 52
  flags: (0x0021) ACC_PUBLIC, ACC_SUPER
  this_class: #2                          // scala/collection/mutable/RedBlackTree$Node$
  super_class: #4                         // java/lang/Object
  interfaces: 0, fields: 1, methods: 5, attributes: 4
Constant pool:
   #1 = Utf8               scala/collection/mutable/RedBlackTree$Node$
   #2 = Class              #1             // scala/collection/mutable/RedBlackTree$Node$
   #3 = Utf8               java/lang/Object
   #4 = Class              #3             // java/lang/Object
   #5 = Utf8               RedBlackTree.scala
   #6 = Utf8               scala/collection/mutable/RedBlackTree$Node
   #7 = Class              #6             // scala/collection/mutable/RedBlackTree$Node
   #8 = Utf8               scala/collection/mutable/RedBlackTree
   #9 = Class              #8             // scala/collection/mutable/RedBlackTree
  #10 = Utf8               Node
  #11 = Utf8               Node$
  #12 = Utf8               MODULE$
  #13 = Utf8               Lscala/collection/mutable/RedBlackTree$Node$;
  #14 = Utf8               <clinit>
  #15 = Utf8               ()V
  #16 = Utf8               <init>
  #17 = NameAndType        #16:#15        // "<init>":()V
  #18 = Methodref          #2.#17         // scala/collection/mutable/RedBlackTree$Node$."<init>":()V
  #19 = NameAndType        #12:#13        // MODULE$:Lscala/collection/mutable/RedBlackTree$Node$;
  #20 = Fieldref           #2.#19         // scala/collection/mutable/RedBlackTree$Node$.MODULE$:Lscala/collection/mutable/RedBlackTree$Node$;
  #21 = Utf8               apply
  #22 = Utf8               (Ljava/lang/Object;Ljava/lang/Object;ZLscala/collection/mutable/RedBlackTree$Node;Lscala/collection/mutable/RedBlackTree$Node;Lscala/collection/mutable/RedBlackTree$Node;)Lscala/collection/mutable/RedBlackTree$Node;
  #23 = Utf8               <A:Ljava/lang/Object;B:Ljava/lang/Object;>(TA;TB;ZLscala/collection/mutable/RedBlackTree$Node<TA;TB;>;Lscala/collection/mutable/RedBlackTree$Node<TA;TB;>;Lscala/collection/mutable/RedBlackTree$Node<TA;TB;>;)Lscala/collection/mutable/RedBlackTree$Node<TA;TB;>;
  #24 = Utf8               key
  #25 = Utf8               value
  #26 = Utf8               red
  #27 = Utf8               left
  #28 = Utf8               right
  #29 = Utf8               parent
  #30 = Utf8               (Ljava/lang/Object;Ljava/lang/Object;ZLscala/collection/mutable/RedBlackTree$Node;Lscala/collection/mutable/RedBlackTree$Node;Lscala/collection/mutable/RedBlackTree$Node;)V
  #31 = NameAndType        #16:#30        // "<init>":(Ljava/lang/Object;Ljava/lang/Object;ZLscala/collection/mutable/RedBlackTree$Node;Lscala/collection/mutable/RedBlackTree$Node;Lscala/collection/mutable/RedBlackTree$Node;)V
  #32 = Methodref          #7.#31         // scala/collection/mutable/RedBlackTree$Node."<init>":(Ljava/lang/Object;Ljava/lang/Object;ZLscala/collection/mutable/RedBlackTree$Node;Lscala/collection/mutable/RedBlackTree$Node;Lscala/collection/mutable/RedBlackTree$Node;)V
  #33 = Utf8               this
  #34 = Utf8               Ljava/lang/Object;
  #35 = Utf8               Z
  #36 = Utf8               Lscala/collection/mutable/RedBlackTree$Node;
  #37 = Utf8               leaf
  #38 = Utf8               (Ljava/lang/Object;Ljava/lang/Object;ZLscala/collection/mutable/RedBlackTree$Node;)Lscala/collection/mutable/RedBlackTree$Node;
  #39 = Utf8               <A:Ljava/lang/Object;B:Ljava/lang/Object;>(TA;TB;ZLscala/collection/mutable/RedBlackTree$Node<TA;TB;>;)Lscala/collection/mutable/RedBlackTree$Node<TA;TB;>;
  #40 = Utf8               unapply
  #41 = Utf8               (Lscala/collection/mutable/RedBlackTree$Node;)Lscala/Some;
  #42 = Utf8               <A:Ljava/lang/Object;B:Ljava/lang/Object;>(Lscala/collection/mutable/RedBlackTree$Node<TA;TB;>;)Lscala/Some<Lscala/Tuple5<TA;TB;Lscala/collection/mutable/RedBlackTree$Node<TA;TB;>;Lscala/collection/mutable/RedBlackTree$Node<TA;TB;>;Lscala/collection/mutable/RedBlackTree$Node<TA;TB;>;>;>;
  #43 = Utf8               t
  #44 = Utf8               scala/Some
  #45 = Class              #44            // scala/Some
  #46 = Utf8               scala/Tuple5
  #47 = Class              #46            // scala/Tuple5
  #48 = Utf8               ()Ljava/lang/Object;
  #49 = NameAndType        #24:#48        // key:()Ljava/lang/Object;
  #50 = Methodref          #7.#49         // scala/collection/mutable/RedBlackTree$Node.key:()Ljava/lang/Object;
  #51 = NameAndType        #25:#48        // value:()Ljava/lang/Object;
  #52 = Methodref          #7.#51         // scala/collection/mutable/RedBlackTree$Node.value:()Ljava/lang/Object;
  #53 = Utf8               ()Lscala/collection/mutable/RedBlackTree$Node;
  #54 = NameAndType        #27:#53        // left:()Lscala/collection/mutable/RedBlackTree$Node;
  #55 = Methodref          #7.#54         // scala/collection/mutable/RedBlackTree$Node.left:()Lscala/collection/mutable/RedBlackTree$Node;
  #56 = NameAndType        #28:#53        // right:()Lscala/collection/mutable/RedBlackTree$Node;
  #57 = Methodref          #7.#56         // scala/collection/mutable/RedBlackTree$Node.right:()Lscala/collection/mutable/RedBlackTree$Node;
  #58 = NameAndType        #29:#53        // parent:()Lscala/collection/mutable/RedBlackTree$Node;
  #59 = Methodref          #7.#58         // scala/collection/mutable/RedBlackTree$Node.parent:()Lscala/collection/mutable/RedBlackTree$Node;
  #60 = Utf8               (Ljava/lang/Object;Ljava/lang/Object;Ljava/lang/Object;Ljava/lang/Object;Ljava/lang/Object;)V
  #61 = NameAndType        #16:#60        // "<init>":(Ljava/lang/Object;Ljava/lang/Object;Ljava/lang/Object;Ljava/lang/Object;Ljava/lang/Object;)V
  #62 = Methodref          #47.#61        // scala/Tuple5."<init>":(Ljava/lang/Object;Ljava/lang/Object;Ljava/lang/Object;Ljava/lang/Object;Ljava/lang/Object;)V
  #63 = Utf8               (Ljava/lang/Object;)V
  #64 = NameAndType        #16:#63        // "<init>":(Ljava/lang/Object;)V
  #65 = Methodref          #45.#64        // scala/Some."<init>":(Ljava/lang/Object;)V
  #66 = Methodref          #4.#17         // java/lang/Object."<init>":()V
  #67 = Utf8               Code
  #68 = Utf8               LineNumberTable
  #69 = Utf8               LocalVariableTable
  #70 = Utf8               Signature
  #71 = Utf8               MethodParameters
  #72 = Utf8               InnerClasses
  #73 = Utf8               SourceFile
  #74 = Utf8               ScalaInlineInfo
  #75 = Utf8               Scala
{
  public static final scala.collection.mutable.RedBlackTree$Node$ MODULE$;
    descriptor: Lscala/collection/mutable/RedBlackTree$Node$;
    flags: (0x0019) ACC_PUBLIC, ACC_STATIC, ACC_FINAL

  public static {};
    descriptor: ()V
    flags: (0x0009) ACC_PUBLIC, ACC_STATIC
    Code:
      stack=2, locals=0, args_size=0
         0: new           #2                  // class scala/collection/mutable/RedBlackTree$Node$
         3: dup
         4: invokespecial #18                 // Method "<init>":()V
         7: putstatic     #20                 // Field MODULE$:Lscala/collection/mutable/RedBlackTree$Node$;
        10: return
      LineNumberTable:
        line 46: 0

  public <A extends java.lang.Object, B extends java.lang.Object> scala.collection.mutable.RedBlackTree$Node<A, B> apply(A, B, boolean, scala.collection.mutable.RedBlackTree$Node<A, B>, scala.collection.mutable.RedBlackTree$Node<A, B>, scala.collection.mutable.RedBlackTree$Node<A, B>);
    descriptor: (Ljava/lang/Object;Ljava/lang/Object;ZLscala/collection/mutable/RedBlackTree$Node;Lscala/collection/mutable/RedBlackTree$Node;Lscala/collection/mutable/RedBlackTree$Node;)Lscala/collection/mutable/RedBlackTree$Node;
    flags: (0x0001) ACC_PUBLIC
    Code:
      stack=8, locals=7, args_size=7
         0: new           #7                  // class scala/collection/mutable/RedBlackTree$Node
         3: dup
         4: aload_1
         5: aload_2
         6: iload_3
         7: aload         4
         9: aload         5
        11: aload         6
        13: invokespecial #32                 // Method scala/collection/mutable/RedBlackTree$Node."<init>":(Ljava/lang/Object;Ljava/lang/Object;ZLscala/collection/mutable/RedBlackTree$Node;Lscala/collection/mutable/RedBlackTree$Node;Lscala/collection/mutable/RedBlackTree$Node;)V
        16: areturn
      LineNumberTable:
        line 50: 0
      LocalVariableTable:
        Start  Length  Slot  Name   Signature
            0      17     0  this   Lscala/collection/mutable/RedBlackTree$Node$;
            0      17     1   key   Ljava/lang/Object;
            0      17     2 value   Ljava/lang/Object;
            0      17     3   red   Z
            0      17     4  left   Lscala/collection/mutable/RedBlackTree$Node;
            0      17     5 right   Lscala/collection/mutable/RedBlackTree$Node;
            0      17     6 parent   Lscala/collection/mutable/RedBlackTree$Node;
    Signature: #23                          // <A:Ljava/lang/Object;B:Ljava/lang/Object;>(TA;TB;ZLscala/collection/mutable/RedBlackTree$Node<TA;TB;>;Lscala/collection/mutable/RedBlackTree$Node<TA;TB;>;Lscala/collection/mutable/RedBlackTree$Node<TA;TB;>;)Lscala/collection/mutable/RedBlackTree$Node<TA;TB;>;
    MethodParameters:
      Name                           Flags
      key                            final
      value                          final
      red                            final
      left                           final
      right                          final
      parent                         final

  public <A extends java.lang.Object, B extends java.lang.Object> scala.collection.mutable.RedBlackTree$Node<A, B> leaf(A, B, boolean, scala.collection.mutable.RedBlackTree$Node<A, B>);
    descriptor: (Ljava/lang/Object;Ljava/lang/Object;ZLscala/collection/mutable/RedBlackTree$Node;)Lscala/collection/mutable/RedBlackTree$Node;
    flags: (0x0001) ACC_PUBLIC
    Code:
      stack=8, locals=5, args_size=5
         0: new           #7                  // class scala/collection/mutable/RedBlackTree$Node
         3: dup
         4: aload_1
         5: aload_2
         6: iload_3
         7: aconst_null
         8: aconst_null
         9: aload         4
        11: invokespecial #32                 // Method scala/collection/mutable/RedBlackTree$Node."<init>":(Ljava/lang/Object;Ljava/lang/Object;ZLscala/collection/mutable/RedBlackTree$Node;Lscala/collection/mutable/RedBlackTree$Node;Lscala/collection/mutable/RedBlackTree$Node;)V
        14: areturn
      LineNumberTable:
        line 53: 0
      LocalVariableTable:
        Start  Length  Slot  Name   Signature
            0      15     0  this   Lscala/collection/mutable/RedBlackTree$Node$;
            0      15     1   key   Ljava/lang/Object;
            0      15     2 value   Ljava/lang/Object;
            0      15     3   red   Z
            0      15     4 parent   Lscala/collection/mutable/RedBlackTree$Node;
    Signature: #39                          // <A:Ljava/lang/Object;B:Ljava/lang/Object;>(TA;TB;ZLscala/collection/mutable/RedBlackTree$Node<TA;TB;>;)Lscala/collection/mutable/RedBlackTree$Node<TA;TB;>;
    MethodParameters:
      Name                           Flags
      key                            final
      value                          final
      red                            final
      parent                         final

  public <A extends java.lang.Object, B extends java.lang.Object> scala.Some<scala.Tuple5<A, B, scala.collection.mutable.RedBlackTree$Node<A, B>, scala.collection.mutable.RedBlackTree$Node<A, B>, scala.collection.mutable.RedBlackTree$Node<A, B>>> unapply(scala.collection.mutable.RedBlackTree$Node<A, B>);
    descriptor: (Lscala/collection/mutable/RedBlackTree$Node;)Lscala/Some;
    flags: (0x0001) ACC_PUBLIC
    Code:
      stack=9, locals=2, args_size=2
         0: new           #45                 // class scala/Some
         3: dup
         4: new           #47                 // class scala/Tuple5
         7: dup
         8: aload_1
         9: invokevirtual #50                 // Method scala/collection/mutable/RedBlackTree$Node.key:()Ljava/lang/Object;
        12: aload_1
        13: invokevirtual #52                 // Method scala/collection/mutable/RedBlackTree$Node.value:()Ljava/lang/Object;
        16: aload_1
        17: invokevirtual #55                 // Method scala/collection/mutable/RedBlackTree$Node.left:()Lscala/collection/mutable/RedBlackTree$Node;
        20: aload_1
        21: invokevirtual #57                 // Method scala/collection/mutable/RedBlackTree$Node.right:()Lscala/collection/mutable/RedBlackTree$Node;
        24: aload_1
        25: invokevirtual #59                 // Method scala/collection/mutable/RedBlackTree$Node.parent:()Lscala/collection/mutable/RedBlackTree$Node;
        28: invokespecial #62                 // Method scala/Tuple5."<init>":(Ljava/lang/Object;Ljava/lang/Object;Ljava/lang/Object;Ljava/lang/Object;Ljava/lang/Object;)V
        31: invokespecial #65                 // Method scala/Some."<init>":(Ljava/lang/Object;)V
        34: areturn
      LineNumberTable:
        line 55: 0
      LocalVariableTable:
        Start  Length  Slot  Name   Signature
            0      35     0  this   Lscala/collection/mutable/RedBlackTree$Node$;
            0      35     1     t   Lscala/collection/mutable/RedBlackTree$Node;
    Signature: #42                          // <A:Ljava/lang/Object;B:Ljava/lang/Object;>(Lscala/collection/mutable/RedBlackTree$Node<TA;TB;>;)Lscala/Some<Lscala/Tuple5<TA;TB;Lscala/collection/mutable/RedBlackTree$Node<TA;TB;>;Lscala/collection/mutable/RedBlackTree$Node<TA;TB;>;Lscala/collection/mutable/RedBlackTree$Node<TA;TB;>;>;>;
    MethodParameters:
      Name                           Flags
      t                              final

  public scala.collection.mutable.RedBlackTree$Node$();
    descriptor: ()V
    flags: (0x0001) ACC_PUBLIC
    Code:
      stack=1, locals=1, args_size=1
         0: aload_0
         1: invokespecial #66                 // Method java/lang/Object."<init>":()V
         4: return
      LineNumberTable:
        line 46: 0
      LocalVariableTable:
        Start  Length  Slot  Name   Signature
            0       5     0  this   Lscala/collection/mutable/RedBlackTree$Node$;
}
InnerClasses:
  public static final #10= #7 of #9;      // Node=class scala/collection/mutable/RedBlackTree$Node of class scala/collection/mutable/RedBlackTree
  public static #11= #2 of #9;            // Node$=class scala/collection/mutable/RedBlackTree$Node$ of class scala/collection/mutable/RedBlackTree
SourceFile: "RedBlackTree.scala"
  ScalaInlineInfo: length = 0x18 (unknown attribute)
   01 01 00 04 00 10 00 0F 01 00 15 00 16 05 00 25
   00 26 05 00 28 00 29 01
  Scala: length = 0x0 (unknown attribute)

