Classfile /Users/mw/Projects/slang-braindump/.jar/jar11/assemble/slang-braindump/assemble/content/scala/collection/mutable/SortedMap.class
  Last modified May 29, 2022; size 6055 bytes
  SHA-256 checksum 478d0e9a176b59d179b5eedfc5310c093b98b4a655faa766c030eeabe8c924d7
  Compiled from "SortedMap.scala"
public interface scala.collection.mutable.SortedMap<K extends java.lang.Object, V extends java.lang.Object> extends scala.collection.SortedMap<K, V>, scala.collection.mutable.Map<K, V>, scala.collection.mutable.SortedMapOps<K, V, scala.collection.mutable.SortedMap, scala.collection.mutable.SortedMap<K, V>>
  minor version: 0
  major version: 52
  flags: (0x0601) ACC_PUBLIC, ACC_INTERFACE, ACC_ABSTRACT
  this_class: #2                          // scala/collection/mutable/SortedMap
  super_class: #5                         // java/lang/Object
  interfaces: 3, fields: 0, methods: 12, attributes: 7
Constant pool:
    #1 = Utf8               scala/collection/mutable/SortedMap
    #2 = Class              #1            // scala/collection/mutable/SortedMap
    #3 = Utf8               <K:Ljava/lang/Object;V:Ljava/lang/Object;>Ljava/lang/Object;Lscala/collection/SortedMap<TK;TV;>;Lscala/collection/mutable/Map<TK;TV;>;Lscala/collection/mutable/SortedMapOps<TK;TV;Lscala/collection/mutable/SortedMap;Lscala/collection/mutable/SortedMap<TK;TV;>;>;
    #4 = Utf8               java/lang/Object
    #5 = Class              #4            // java/lang/Object
    #6 = Utf8               scala/collection/SortedMap
    #7 = Class              #6            // scala/collection/SortedMap
    #8 = Utf8               scala/collection/mutable/Map
    #9 = Class              #8            // scala/collection/mutable/Map
   #10 = Utf8               scala/collection/mutable/SortedMapOps
   #11 = Class              #10           // scala/collection/mutable/SortedMapOps
   #12 = Utf8               SortedMap.scala
   #13 = Utf8               Lscala/reflect/ScalaSignature;
   #14 = Utf8               bytes
   #15 = Utf8               \u0006\u0005\u0005mfa\u0002\u000e\u001c!\u0003\r\tA\t\u0005\u0006\u0013\u0002!\tA\u0013\u0005\u0006\u001d\u0002!\te\u0014\u0005\u0006!\u0002!\t%\u0015\u0005\u0006+\u0002!\tE\u0016\u0005\u00069\u0002!\t%X\u0004\u0006?nA\t\u0001\u0019\u0004\u00065mA\t!\u0019\u0005\u0006S\u001e!\tA\u001b\u0004\u0005W\u001e\u0011A\u000eC\u0006\u0002\b%\u0011\t\u0011)A\u0005q\u0006%\u0001\u0002DA\u0006\u0013\t\u0005\t\u0015!\u0003\u0002\u000e\u0005=\u0001BB5\n\t\u0003\t\t\u0002C\u0003Q\u0013\u0011\u0005\u0013\u000bC\u0004\u0002\u0018%!\t!!\u0007\t\u000f\u0005-\u0012\u0002\"\u0001\u0002.!9\u00111G\u0005\u0005\u0004\u0005U\u0002bBA\u001f\u0013\u0011\u0005\u0011q\b\u0005\b\u0003\u001fJA\u0011IA)\u0011\u001d\tI&\u0003C!\u00037Bq!a\u0018\n\t\u0003\n\t\u0007C\u0004\u0002d%!\t%!\u001a\t\u000f\u0005}\u0014\u0002\"\u0015\u0002\u0002\"9\u0011\u0011R\u0005\u0005R\u0005-\u0005BDAJ\u0013A\u0005\u0019\u0011!A\u0005\n\u0005U\u0015q\u0002\u0005\n\u0003G;\u0011\u0011!C\u0005\u0003K\u0013\u0011bU8si\u0016$W*\u00199\u000b\u0005qi\u0012aB7vi\u0006\u0014G.\u001a\u0006\u0003=}\t!bY8mY\u0016\u001cG/[8o\u0015\u0005\u0001\u0013!B:dC2\f7\u0001A\u000b\u0004G5:4C\u0002\u0001%Qej$\t\u0005\u0002&M5\tq$\u0003\u0002(?\t1\u0011I\\=SK\u001a\u0004B!\u000b\u0016,m5\tQ$\u0003\u0002\u001b;A\u0011A&\f\u0007\u0001\t\u0015q\u0003A1\u00010\u0005\u0005Y\u0015C\u0001\u00194!\t)\u0013\'\u0003\u00023?\t9aj\u001c;iS:<\u0007CA\u00135\u0013\t)tDA\u0002B]f\u0004\"\u0001L\u001c\u0005\u000ba\u0002!\u0019A\u0018\u0003\u0003Y\u0003BAO\u001e,m5\t1$\u0003\u0002=7\t\u0019Q*\u00199\u0011\rir4F\u000e!B\u0013\ty4D\u0001\u0007T_J$X\rZ\'ba>\u00038\u000f\u0005\u0002;\u0001A!!\bA\u00167!\u001dI3i\u000b\u001cA\u000b\"K!\u0001R\u000f\u00031M{\'\u000f^3e\u001b\u0006\u0004h)Y2u_JLH)\u001a4bk2$8\u000f\u0005\u0002;\r&\u0011qi\u0007\u0002\t\u0013R,\'/\u00192mKB\u0011!hO\u0001\u0007I%t\u0017\u000e\u001e\u0013\u0015\u0003-\u0003\"!\n\'\n\u00055{\"\u0001B+oSR\f\u0001\"\u001e8t_J$X\rZ\u000b\u0002s\u0005\u00012o\u001c:uK\u0012l\u0015\r\u001d$bGR|\'/_\u000b\u0002%B\u0019\u0011f\u0015!\n\u0005Qk\"\u0001E*peR,G-T1q\r\u0006\u001cGo\u001c:z\u0003-9\u0018\u000e\u001e5EK\u001a\fW\u000f\u001c;\u0015\u0005\u0005;\u0006\"\u0002-\u0005\u0001\u0004I\u0016!\u00013\u0011\t\u0015R6FN\u0005\u00037~\u0011\u0011BR;oGRLwN\\\u0019\u0002!]LG\u000f\u001b#fM\u0006,H\u000e\u001e,bYV,GCA!_\u0011\u0015AV\u00011\u00017\u0003%\u0019vN\u001d;fI6\u000b\u0007\u000f\u0005\u0002;\u000fM\u0011qA\u0019\t\u0004G\u001a\u0004eBA\u0015e\u0013\t)W$\u0001\tT_J$X\rZ\'ba\u001a\u000b7\r^8ss&\u0011q\r\u001b\u0002\t\t\u0016dWmZ1uK*\u0011Q-H\u0001\u0007y%t\u0017\u000e\u001e \u0015\u0003\u0001\u00141bV5uQ\u0012+g-Y;miV\u0019Q.^<\u0014\u000b%q\u00070\u001f?\u0011\t=\u0014HO\u001e\b\u0003uAL!!]\u000e\u0002\u00075\u000b\u0007/\u0003\u0002lg*\u0011\u0011o\u0007\t\u0003YU$QAL\u0005C\u0002=\u0002\"\u0001L<\u0005\u000baJ!\u0019A\u0018\u0011\ti\u0002AO\u001e\t\u0007uy\"h\u000f\u0011>\u0011\tmLAO^\u0007\u0002\u000fA\u0019Q0!\u0001\u000f\u0005\u0015r\u0018BA@ \u0003\u001d\u0001\u0018mY6bO\u0016LA!a\u0001\u0002\u0006\ta1+\u001a:jC2L\'0\u00192mK*\u0011qpH\u0001\u000bk:$WM\u001d7zS:<\u0017bAA\u0004e\u0006aA-\u001a4bk2$h+\u00197vKB!QE\u0017;w\u0013\r\tYA\u001d\u000b\u0006u\u0006M\u0011Q\u0003\u0005\u0007\u0003\u000fa\u0001\u0019\u0001=\t\u000f\u0005-A\u00021\u0001\u0002\u000e\u0005a\u0011\u000e^3sCR|\'O\u0012:p[R!\u00111DA\u0014!\u0015I\u0013QDA\u0011\u0013\r\ty\"\b\u0002\t\u0013R,\'/\u0019;peB)Q%a\tum&\u0019\u0011QE\u0010\u0003\rQ+\b\u000f\\33\u0011\u0019\tIC\u0004a\u0001i\u0006)1\u000f^1si\u0006\u00012.Z=t\u0013R,\'/\u0019;pe\u001a\u0013x.\u001c\u000b\u0005\u0003_\t\t\u0004\u0005\u0003*\u0003;!\bBBA\u0015\u001f\u0001\u0007A/\u0001\u0005pe\u0012,\'/\u001b8h+\t\t9\u0004\u0005\u0003~\u0003s!\u0018\u0002BA\u001e\u0003\u000b\u0011\u0001b\u0014:eKJLgnZ\u0001\ne\u0006tw-Z%na2$RA_A!\u0003\u0017Bq!a\u0011\u0012\u0001\u0004\t)%\u0001\u0003ge>l\u0007\u0003B\u0013\u0002HQL1!!\u0013 \u0005\u0019y\u0005\u000f^5p]\"9\u0011QJ\tA\u0002\u0005\u0015\u0013!B;oi&d\u0017aC:vER\u0014\u0018m\u0019;P]\u0016$B!a\u0015\u0002V5\t\u0011\u0002\u0003\u0004\u0002XI\u0001\r\u0001^\u0001\u0005K2,W.\u0001\u0004bI\u0012|e.\u001a\u000b\u0005\u0003\'\ni\u0006C\u0004\u0002XM\u0001\r!!\t\u0002\u000b\u0015l\u0007\u000f^=\u0016\u0003i\faaY8oG\u0006$X\u0003BA4\u0003[\"B!!\u001b\u0002tA)!\b\u0001;\u0002lA\u0019A&!\u001c\u0005\u000f\u0005=TC1\u0001\u0002r\t\u0011aKM\t\u0003mNBq!!\u001e\u0016\u0001\u0004\t9(\u0001\u0004tk\u001a4\u0017\u000e\u001f\t\u0006S\u0005e\u0014QP\u0005\u0004\u0003wj\"\u0001D%uKJ\f\'\r\\3P]\u000e,\u0007CB\u0013\u0002$Q\fY\'\u0001\u0007ge>l7\u000b]3dS\u001aL7\rF\u0002{\u0003\u0007Cq!!\"\u0017\u0001\u0004\t9)\u0001\u0003d_2d\u0007#B\u0015\u0002z\u0005\u0005\u0012A\u00058foN\u0003XmY5gS\u000e\u0014U/\u001b7eKJ,\"!!$\u0011\ri\ny)!\t{\u0013\r\t\tj\u0007\u0002\b\u0005VLG\u000eZ3s\u0003I\u0019X\u000f]3sI\u0011,g-Y;miZ\u000bG.^3\u0016\u0005\u00055\u0001fB\u0005\u0002\u001a\u0006}\u0015\u0011\u0015\t\u0004K\u0005m\u0015bAAO?\t\u00012+\u001a:jC24VM]:j_:,\u0016\nR\u0001\u0006m\u0006dW/\u001a\u0010\u0002\u0007\u0005aqO]5uKJ+\u0007\u000f\\1dKR\u0011\u0011q\u0015\t\u0005\u0003S\u000b\u0019,\u0004\u0002\u0002,*!\u0011QVAX\u0003\u0011a\u0017M\\4\u000b\u0005\u0005E\u0016\u0001\u00026bm\u0006LA!!.\u0002,\n1qJ\u00196fGRDsaBAM\u0003?\u000b\t\u000bK\u0004\u0007\u00033\u000by*!)
   #16 = Utf8               java/lang/invoke/MethodHandles$Lookup
   #17 = Class              #16           // java/lang/invoke/MethodHandles$Lookup
   #18 = Utf8               java/lang/invoke/MethodHandles
   #19 = Class              #18           // java/lang/invoke/MethodHandles
   #20 = Utf8               Lookup
   #21 = Utf8               scala/collection/mutable/SortedMap$WithDefault
   #22 = Class              #21           // scala/collection/mutable/SortedMap$WithDefault
   #23 = Utf8               WithDefault
   #24 = Utf8               newBuilder
   #25 = Utf8               (Lscala/math/Ordering;)Lscala/collection/mutable/Builder;
   #26 = Utf8               <K:Ljava/lang/Object;V:Ljava/lang/Object;>(Lscala/math/Ordering<TK;>;)Lscala/collection/mutable/Builder<Lscala/Tuple2<TK;TV;>;Lscala/collection/mutable/SortedMap<TK;TV;>;>;
   #27 = Utf8               evidence$48
   #28 = Utf8               scala/collection/mutable/SortedMap$
   #29 = Class              #28           // scala/collection/mutable/SortedMap$
   #30 = Utf8               MODULE$
   #31 = Utf8               Lscala/collection/mutable/SortedMap$;
   #32 = NameAndType        #30:#31       // MODULE$:Lscala/collection/mutable/SortedMap$;
   #33 = Fieldref           #29.#32       // scala/collection/mutable/SortedMap$.MODULE$:Lscala/collection/mutable/SortedMap$;
   #34 = NameAndType        #24:#25       // newBuilder:(Lscala/math/Ordering;)Lscala/collection/mutable/Builder;
   #35 = Methodref          #29.#34       // scala/collection/mutable/SortedMap$.newBuilder:(Lscala/math/Ordering;)Lscala/collection/mutable/Builder;
   #36 = Utf8               Lscala/math/Ordering;
   #37 = Utf8               unsorted$
   #38 = Utf8               (Lscala/collection/mutable/SortedMap;)Lscala/collection/mutable/Map;
   #39 = Utf8               $this
   #40 = Utf8               unsorted
   #41 = Utf8               ()Lscala/collection/mutable/Map;
   #42 = NameAndType        #40:#41       // unsorted:()Lscala/collection/mutable/Map;
   #43 = InterfaceMethodref #2.#42        // scala/collection/mutable/SortedMap.unsorted:()Lscala/collection/mutable/Map;
   #44 = Utf8               Lscala/collection/mutable/SortedMap;
   #45 = Utf8               ()Lscala/collection/mutable/Map<TK;TV;>;
   #46 = Utf8               this
   #47 = Utf8               sortedMapFactory$
   #48 = Utf8               (Lscala/collection/mutable/SortedMap;)Lscala/collection/SortedMapFactory;
   #49 = Utf8               sortedMapFactory
   #50 = Utf8               ()Lscala/collection/SortedMapFactory;
   #51 = NameAndType        #49:#50       // sortedMapFactory:()Lscala/collection/SortedMapFactory;
   #52 = InterfaceMethodref #2.#51        // scala/collection/mutable/SortedMap.sortedMapFactory:()Lscala/collection/SortedMapFactory;
   #53 = Utf8               ()Lscala/collection/SortedMapFactory<Lscala/collection/mutable/SortedMap;>;
   #54 = Utf8               withDefault$
   #55 = Utf8               (Lscala/collection/mutable/SortedMap;Lscala/Function1;)Lscala/collection/mutable/SortedMap;
   #56 = Utf8               d
   #57 = Utf8               withDefault
   #58 = Utf8               (Lscala/Function1;)Lscala/collection/mutable/SortedMap;
   #59 = NameAndType        #57:#58       // withDefault:(Lscala/Function1;)Lscala/collection/mutable/SortedMap;
   #60 = InterfaceMethodref #2.#59        // scala/collection/mutable/SortedMap.withDefault:(Lscala/Function1;)Lscala/collection/mutable/SortedMap;
   #61 = Utf8               Lscala/Function1;
   #62 = Utf8               (Lscala/Function1<TK;TV;>;)Lscala/collection/mutable/SortedMap<TK;TV;>;
   #63 = Utf8               <init>
   #64 = Utf8               (Lscala/collection/mutable/SortedMap;Lscala/Function1;)V
   #65 = NameAndType        #63:#64       // "<init>":(Lscala/collection/mutable/SortedMap;Lscala/Function1;)V
   #66 = Methodref          #22.#65       // scala/collection/mutable/SortedMap$WithDefault."<init>":(Lscala/collection/mutable/SortedMap;Lscala/Function1;)V
   #67 = Utf8               withDefaultValue$
   #68 = Utf8               (Lscala/collection/mutable/SortedMap;Ljava/lang/Object;)Lscala/collection/mutable/SortedMap;
   #69 = Utf8               withDefaultValue
   #70 = Utf8               (Ljava/lang/Object;)Lscala/collection/mutable/SortedMap;
   #71 = NameAndType        #69:#70       // withDefaultValue:(Ljava/lang/Object;)Lscala/collection/mutable/SortedMap;
   #72 = InterfaceMethodref #2.#71        // scala/collection/mutable/SortedMap.withDefaultValue:(Ljava/lang/Object;)Lscala/collection/mutable/SortedMap;
   #73 = Utf8               Ljava/lang/Object;
   #74 = Utf8               (TV;)Lscala/collection/mutable/SortedMap<TK;TV;>;
   #75 = Utf8               (Ljava/lang/Object;)Ljava/lang/Object;
   #76 = MethodType         #75           //  (Ljava/lang/Object;)Ljava/lang/Object;
   #77 = Utf8               $anonfun$withDefaultValue$1
   #78 = Utf8               (Ljava/lang/Object;Ljava/lang/Object;)Ljava/lang/Object;
   #79 = NameAndType        #77:#78       // $anonfun$withDefaultValue$1:(Ljava/lang/Object;Ljava/lang/Object;)Ljava/lang/Object;
   #80 = InterfaceMethodref #2.#79        // scala/collection/mutable/SortedMap.$anonfun$withDefaultValue$1:(Ljava/lang/Object;Ljava/lang/Object;)Ljava/lang/Object;
   #81 = MethodHandle       6:#80         // REF_invokeStatic scala/collection/mutable/SortedMap.$anonfun$withDefaultValue$1:(Ljava/lang/Object;Ljava/lang/Object;)Ljava/lang/Object;
   #82 = Integer            1
   #83 = Utf8               java/lang/invoke/LambdaMetafactory
   #84 = Class              #83           // java/lang/invoke/LambdaMetafactory
   #85 = Utf8               altMetafactory
   #86 = Utf8               (Ljava/lang/invoke/MethodHandles$Lookup;Ljava/lang/String;Ljava/lang/invoke/MethodType;[Ljava/lang/Object;)Ljava/lang/invoke/CallSite;
   #87 = NameAndType        #85:#86       // altMetafactory:(Ljava/lang/invoke/MethodHandles$Lookup;Ljava/lang/String;Ljava/lang/invoke/MethodType;[Ljava/lang/Object;)Ljava/lang/invoke/CallSite;
   #88 = Methodref          #84.#87       // java/lang/invoke/LambdaMetafactory.altMetafactory:(Ljava/lang/invoke/MethodHandles$Lookup;Ljava/lang/String;Ljava/lang/invoke/MethodType;[Ljava/lang/Object;)Ljava/lang/invoke/CallSite;
   #89 = MethodHandle       6:#88         // REF_invokeStatic java/lang/invoke/LambdaMetafactory.altMetafactory:(Ljava/lang/invoke/MethodHandles$Lookup;Ljava/lang/String;Ljava/lang/invoke/MethodType;[Ljava/lang/Object;)Ljava/lang/invoke/CallSite;
   #90 = Utf8               apply
   #91 = Utf8               (Ljava/lang/Object;)Lscala/Function1;
   #92 = NameAndType        #90:#91       // apply:(Ljava/lang/Object;)Lscala/Function1;
   #93 = InvokeDynamic      #0:#92        // #0:apply:(Ljava/lang/Object;)Lscala/Function1;
   #94 = Utf8               d$1
   #95 = Utf8               x$1
   #96 = Utf8               $init$
   #97 = Utf8               (Lscala/collection/mutable/SortedMap;)V
   #98 = Utf8               $deserializeLambda$
   #99 = Utf8               (Ljava/lang/invoke/SerializedLambda;)Ljava/lang/Object;
  #100 = Utf8               scala/runtime/LambdaDeserialize
  #101 = Class              #100          // scala/runtime/LambdaDeserialize
  #102 = Utf8               bootstrap
  #103 = Utf8               (Ljava/lang/invoke/MethodHandles$Lookup;Ljava/lang/String;Ljava/lang/invoke/MethodType;[Ljava/lang/invoke/MethodHandle;)Ljava/lang/invoke/CallSite;
  #104 = NameAndType        #102:#103     // bootstrap:(Ljava/lang/invoke/MethodHandles$Lookup;Ljava/lang/String;Ljava/lang/invoke/MethodType;[Ljava/lang/invoke/MethodHandle;)Ljava/lang/invoke/CallSite;
  #105 = Methodref          #101.#104     // scala/runtime/LambdaDeserialize.bootstrap:(Ljava/lang/invoke/MethodHandles$Lookup;Ljava/lang/String;Ljava/lang/invoke/MethodType;[Ljava/lang/invoke/MethodHandle;)Ljava/lang/invoke/CallSite;
  #106 = MethodHandle       6:#105        // REF_invokeStatic scala/runtime/LambdaDeserialize.bootstrap:(Ljava/lang/invoke/MethodHandles$Lookup;Ljava/lang/String;Ljava/lang/invoke/MethodType;[Ljava/lang/invoke/MethodHandle;)Ljava/lang/invoke/CallSite;
  #107 = Utf8               lambdaDeserialize
  #108 = NameAndType        #107:#99      // lambdaDeserialize:(Ljava/lang/invoke/SerializedLambda;)Ljava/lang/Object;
  #109 = InvokeDynamic      #1:#108       // #1:lambdaDeserialize:(Ljava/lang/invoke/SerializedLambda;)Ljava/lang/Object;
  #110 = Utf8               Code
  #111 = Utf8               LocalVariableTable
  #112 = Utf8               Signature
  #113 = Utf8               MethodParameters
  #114 = Utf8               LineNumberTable
  #115 = Utf8               InnerClasses
  #116 = Utf8               SourceFile
  #117 = Utf8               RuntimeVisibleAnnotations
  #118 = Utf8               BootstrapMethods
  #119 = Utf8               ScalaInlineInfo
  #120 = Utf8               ScalaSig
{
  public static <K extends java.lang.Object, V extends java.lang.Object> scala.collection.mutable.Builder<scala.Tuple2<K, V>, scala.collection.mutable.SortedMap<K, V>> newBuilder(scala.math.Ordering<K>);
    descriptor: (Lscala/math/Ordering;)Lscala/collection/mutable/Builder;
    flags: (0x0009) ACC_PUBLIC, ACC_STATIC
    Code:
      stack=2, locals=1, args_size=1
         0: getstatic     #33                 // Field scala/collection/mutable/SortedMap$.MODULE$:Lscala/collection/mutable/SortedMap$;
         3: aload_0
         4: invokevirtual #35                 // Method scala/collection/mutable/SortedMap$.newBuilder:(Lscala/math/Ordering;)Lscala/collection/mutable/Builder;
         7: areturn
      LocalVariableTable:
        Start  Length  Slot  Name   Signature
            0       8     0 evidence$48   Lscala/math/Ordering;
    Signature: #26                          // <K:Ljava/lang/Object;V:Ljava/lang/Object;>(Lscala/math/Ordering<TK;>;)Lscala/collection/mutable/Builder<Lscala/Tuple2<TK;TV;>;Lscala/collection/mutable/SortedMap<TK;TV;>;>;
    MethodParameters:
      Name                           Flags
      evidence$48                    final

  public static scala.collection.mutable.Map unsorted$(scala.collection.mutable.SortedMap);
    descriptor: (Lscala/collection/mutable/SortedMap;)Lscala/collection/mutable/Map;
    flags: (0x1009) ACC_PUBLIC, ACC_STATIC, ACC_SYNTHETIC
    Code:
      stack=1, locals=1, args_size=1
         0: aload_0
         1: invokespecial #43                 // InterfaceMethod unsorted:()Lscala/collection/mutable/Map;
         4: areturn
      LineNumberTable:
        line 27: 0
      LocalVariableTable:
        Start  Length  Slot  Name   Signature
            0       5     0 $this   Lscala/collection/mutable/SortedMap;
    MethodParameters:
      Name                           Flags
      $this                          final synthetic

  public default scala.collection.mutable.Map<K, V> unsorted();
    descriptor: ()Lscala/collection/mutable/Map;
    flags: (0x0001) ACC_PUBLIC
    Code:
      stack=1, locals=1, args_size=1
         0: aload_0
         1: areturn
      LineNumberTable:
        line 27: 0
      LocalVariableTable:
        Start  Length  Slot  Name   Signature
            0       2     0  this   Lscala/collection/mutable/SortedMap;
    Signature: #45                          // ()Lscala/collection/mutable/Map<TK;TV;>;

  public static scala.collection.SortedMapFactory sortedMapFactory$(scala.collection.mutable.SortedMap);
    descriptor: (Lscala/collection/mutable/SortedMap;)Lscala/collection/SortedMapFactory;
    flags: (0x1009) ACC_PUBLIC, ACC_STATIC, ACC_SYNTHETIC
    Code:
      stack=1, locals=1, args_size=1
         0: aload_0
         1: invokespecial #52                 // InterfaceMethod sortedMapFactory:()Lscala/collection/SortedMapFactory;
         4: areturn
      LineNumberTable:
        line 29: 0
      LocalVariableTable:
        Start  Length  Slot  Name   Signature
            0       5     0 $this   Lscala/collection/mutable/SortedMap;
    MethodParameters:
      Name                           Flags
      $this                          final synthetic

  public default scala.collection.SortedMapFactory<scala.collection.mutable.SortedMap> sortedMapFactory();
    descriptor: ()Lscala/collection/SortedMapFactory;
    flags: (0x0001) ACC_PUBLIC
    Code:
      stack=1, locals=1, args_size=1
         0: getstatic     #33                 // Field scala/collection/mutable/SortedMap$.MODULE$:Lscala/collection/mutable/SortedMap$;
         3: areturn
      LineNumberTable:
        line 29: 0
      LocalVariableTable:
        Start  Length  Slot  Name   Signature
            0       4     0  this   Lscala/collection/mutable/SortedMap;
    Signature: #53                          // ()Lscala/collection/SortedMapFactory<Lscala/collection/mutable/SortedMap;>;

  public static scala.collection.mutable.SortedMap withDefault$(scala.collection.mutable.SortedMap, scala.Function1);
    descriptor: (Lscala/collection/mutable/SortedMap;Lscala/Function1;)Lscala/collection/mutable/SortedMap;
    flags: (0x1009) ACC_PUBLIC, ACC_STATIC, ACC_SYNTHETIC
    Code:
      stack=2, locals=2, args_size=2
         0: aload_0
         1: aload_1
         2: invokespecial #60                 // InterfaceMethod withDefault:(Lscala/Function1;)Lscala/collection/mutable/SortedMap;
         5: areturn
      LineNumberTable:
        line 40: 0
      LocalVariableTable:
        Start  Length  Slot  Name   Signature
            0       6     0 $this   Lscala/collection/mutable/SortedMap;
            0       6     1     d   Lscala/Function1;
    MethodParameters:
      Name                           Flags
      $this                          final synthetic
      d                              final

  public default scala.collection.mutable.SortedMap<K, V> withDefault(scala.Function1<K, V>);
    descriptor: (Lscala/Function1;)Lscala/collection/mutable/SortedMap;
    flags: (0x0001) ACC_PUBLIC
    Code:
      stack=4, locals=2, args_size=2
         0: new           #22                 // class scala/collection/mutable/SortedMap$WithDefault
         3: dup
         4: aload_0
         5: aload_1
         6: invokespecial #66                 // Method scala/collection/mutable/SortedMap$WithDefault."<init>":(Lscala/collection/mutable/SortedMap;Lscala/Function1;)V
         9: areturn
      LineNumberTable:
        line 40: 0
      LocalVariableTable:
        Start  Length  Slot  Name   Signature
            0      10     0  this   Lscala/collection/mutable/SortedMap;
            0      10     1     d   Lscala/Function1;
    Signature: #62                          // (Lscala/Function1<TK;TV;>;)Lscala/collection/mutable/SortedMap<TK;TV;>;
    MethodParameters:
      Name                           Flags
      d                              final

  public static scala.collection.mutable.SortedMap withDefaultValue$(scala.collection.mutable.SortedMap, java.lang.Object);
    descriptor: (Lscala/collection/mutable/SortedMap;Ljava/lang/Object;)Lscala/collection/mutable/SortedMap;
    flags: (0x1009) ACC_PUBLIC, ACC_STATIC, ACC_SYNTHETIC
    Code:
      stack=2, locals=2, args_size=2
         0: aload_0
         1: aload_1
         2: invokespecial #72                 // InterfaceMethod withDefaultValue:(Ljava/lang/Object;)Lscala/collection/mutable/SortedMap;
         5: areturn
      LineNumberTable:
        line 51: 0
      LocalVariableTable:
        Start  Length  Slot  Name   Signature
            0       6     0 $this   Lscala/collection/mutable/SortedMap;
            0       6     1     d   Ljava/lang/Object;
    MethodParameters:
      Name                           Flags
      $this                          final synthetic
      d                              final

  public default scala.collection.mutable.SortedMap<K, V> withDefaultValue(V);
    descriptor: (Ljava/lang/Object;)Lscala/collection/mutable/SortedMap;
    flags: (0x0001) ACC_PUBLIC
    Code:
      stack=4, locals=2, args_size=2
         0: new           #22                 // class scala/collection/mutable/SortedMap$WithDefault
         3: dup
         4: aload_0
         5: aload_1
         6: invokedynamic #93,  0             // InvokeDynamic #0:apply:(Ljava/lang/Object;)Lscala/Function1;
        11: invokespecial #66                 // Method scala/collection/mutable/SortedMap$WithDefault."<init>":(Lscala/collection/mutable/SortedMap;Lscala/Function1;)V
        14: areturn
      LineNumberTable:
        line 51: 0
      LocalVariableTable:
        Start  Length  Slot  Name   Signature
            0      15     0  this   Lscala/collection/mutable/SortedMap;
            0      15     1     d   Ljava/lang/Object;
    Signature: #74                          // (TV;)Lscala/collection/mutable/SortedMap<TK;TV;>;
    MethodParameters:
      Name                           Flags
      d                              final

  public static java.lang.Object $anonfun$withDefaultValue$1(java.lang.Object, java.lang.Object);
    descriptor: (Ljava/lang/Object;Ljava/lang/Object;)Ljava/lang/Object;
    flags: (0x1009) ACC_PUBLIC, ACC_STATIC, ACC_SYNTHETIC
    Code:
      stack=1, locals=2, args_size=2
         0: aload_0
         1: areturn
      LineNumberTable:
        line 51: 0
      LocalVariableTable:
        Start  Length  Slot  Name   Signature
            0       2     0   d$1   Ljava/lang/Object;
            0       2     1   x$1   Ljava/lang/Object;
    MethodParameters:
      Name                           Flags
      d$1                            final
      x$1                            final

  public static void $init$(scala.collection.mutable.SortedMap);
    descriptor: (Lscala/collection/mutable/SortedMap;)V
    flags: (0x0009) ACC_PUBLIC, ACC_STATIC
    Code:
      stack=0, locals=1, args_size=1
         0: return
      LineNumberTable:
        line 22: 0
      LocalVariableTable:
        Start  Length  Slot  Name   Signature
            0       1     0 $this   Lscala/collection/mutable/SortedMap;
    MethodParameters:
      Name                           Flags
      $this                          final synthetic

  private static java.lang.Object $deserializeLambda$(java.lang.invoke.SerializedLambda);
    descriptor: (Ljava/lang/invoke/SerializedLambda;)Ljava/lang/Object;
    flags: (0x100a) ACC_PRIVATE, ACC_STATIC, ACC_SYNTHETIC
    Code:
      stack=1, locals=1, args_size=1
         0: aload_0
         1: invokedynamic #109,  0            // InvokeDynamic #1:lambdaDeserialize:(Ljava/lang/invoke/SerializedLambda;)Ljava/lang/Object;
         6: areturn
}
InnerClasses:
  public static final #20= #17 of #19;    // Lookup=class java/lang/invoke/MethodHandles$Lookup of class java/lang/invoke/MethodHandles
  public static final #23= #22 of #2;     // WithDefault=class scala/collection/mutable/SortedMap$WithDefault of class scala/collection/mutable/SortedMap
Signature: #3                           // <K:Ljava/lang/Object;V:Ljava/lang/Object;>Ljava/lang/Object;Lscala/collection/SortedMap<TK;TV;>;Lscala/collection/mutable/Map<TK;TV;>;Lscala/collection/mutable/SortedMapOps<TK;TV;Lscala/collection/mutable/SortedMap;Lscala/collection/mutable/SortedMap<TK;TV;>;>;
SourceFile: "SortedMap.scala"
RuntimeVisibleAnnotations:
  0: #13(#14=s#15)
    scala.reflect.ScalaSignature(
      bytes="\u0006\u0005\u0005mfa\u0002\u000e\u001c!\u0003\r\tA\t\u0005\u0006\u0013\u0002!\tA\u0013\u0005\u0006\u001d\u0002!\te\u0014\u0005\u0006!\u0002!\t%\u0015\u0005\u0006+\u0002!\tE\u0016\u0005\u00069\u0002!\t%X\u0004\u0006?nA\t\u0001\u0019\u0004\u00065mA\t!\u0019\u0005\u0006S\u001e!\tA\u001b\u0004\u0005W\u001e\u0011A\u000eC\u0006\u0002\b%\u0011\t\u0011)A\u0005q\u0006%\u0001\u0002DA\u0006\u0013\t\u0005\t\u0015!\u0003\u0002\u000e\u0005=\u0001BB5\n\t\u0003\t\t\u0002C\u0003Q\u0013\u0011\u0005\u0013\u000bC\u0004\u0002\u0018%!\t!!\u0007\t\u000f\u0005-\u0012\u0002\"\u0001\u0002.!9\u00111G\u0005\u0005\u0004\u0005U\u0002bBA\u001f\u0013\u0011\u0005\u0011q\b\u0005\b\u0003\u001fJA\u0011IA)\u0011\u001d\tI&\u0003C!\u00037Bq!a\u0018\n\t\u0003\n\t\u0007C\u0004\u0002d%!\t%!\u001a\t\u000f\u0005}\u0014\u0002\"\u0015\u0002\u0002\"9\u0011\u0011R\u0005\u0005R\u0005-\u0005BDAJ\u0013A\u0005\u0019\u0011!A\u0005\n\u0005U\u0015q\u0002\u0005\n\u0003G;\u0011\u0011!C\u0005\u0003K\u0013\u0011bU8si\u0016$W*\u00199\u000b\u0005qi\u0012aB7vi\u0006\u0014G.\u001a\u0006\u0003=}\t!bY8mY\u0016\u001cG/[8o\u0015\u0005\u0001\u0013!B:dC2\f7\u0001A\u000b\u0004G5:4C\u0002\u0001%Qej$\t\u0005\u0002&M5\tq$\u0003\u0002(?\t1\u0011I\\=SK\u001a\u0004B!\u000b\u0016,m5\tQ$\u0003\u0002\u001b;A\u0011A&\f\u0007\u0001\t\u0015q\u0003A1\u00010\u0005\u0005Y\u0015C\u0001\u00194!\t)\u0013\'\u0003\u00023?\t9aj\u001c;iS:<\u0007CA\u00135\u0013\t)tDA\u0002B]f\u0004\"\u0001L\u001c\u0005\u000ba\u0002!\u0019A\u0018\u0003\u0003Y\u0003BAO\u001e,m5\t1$\u0003\u0002=7\t\u0019Q*\u00199\u0011\rir4F\u000e!B\u0013\ty4D\u0001\u0007T_J$X\rZ\'ba>\u00038\u000f\u0005\u0002;\u0001A!!\bA\u00167!\u001dI3i\u000b\u001cA\u000b\"K!\u0001R\u000f\u00031M{\'\u000f^3e\u001b\u0006\u0004h)Y2u_JLH)\u001a4bk2$8\u000f\u0005\u0002;\r&\u0011qi\u0007\u0002\t\u0013R,\'/\u00192mKB\u0011!hO\u0001\u0007I%t\u0017\u000e\u001e\u0013\u0015\u0003-\u0003\"!\n\'\n\u00055{\"\u0001B+oSR\f\u0001\"\u001e8t_J$X\rZ\u000b\u0002s\u0005\u00012o\u001c:uK\u0012l\u0015\r\u001d$bGR|\'/_\u000b\u0002%B\u0019\u0011f\u0015!\n\u0005Qk\"\u0001E*peR,G-T1q\r\u0006\u001cGo\u001c:z\u0003-9\u0018\u000e\u001e5EK\u001a\fW\u000f\u001c;\u0015\u0005\u0005;\u0006\"\u0002-\u0005\u0001\u0004I\u0016!\u00013\u0011\t\u0015R6FN\u0005\u00037~\u0011\u0011BR;oGRLwN\\\u0019\u0002!]LG\u000f\u001b#fM\u0006,H\u000e\u001e,bYV,GCA!_\u0011\u0015AV\u00011\u00017\u0003%\u0019vN\u001d;fI6\u000b\u0007\u000f\u0005\u0002;\u000fM\u0011qA\u0019\t\u0004G\u001a\u0004eBA\u0015e\u0013\t)W$\u0001\tT_J$X\rZ\'ba\u001a\u000b7\r^8ss&\u0011q\r\u001b\u0002\t\t\u0016dWmZ1uK*\u0011Q-H\u0001\u0007y%t\u0017\u000e\u001e \u0015\u0003\u0001\u00141bV5uQ\u0012+g-Y;miV\u0019Q.^<\u0014\u000b%q\u00070\u001f?\u0011\t=\u0014HO\u001e\b\u0003uAL!!]\u000e\u0002\u00075\u000b\u0007/\u0003\u0002lg*\u0011\u0011o\u0007\t\u0003YU$QAL\u0005C\u0002=\u0002\"\u0001L<\u0005\u000baJ!\u0019A\u0018\u0011\ti\u0002AO\u001e\t\u0007uy\"h\u000f\u0011>\u0011\tmLAO^\u0007\u0002\u000fA\u0019Q0!\u0001\u000f\u0005\u0015r\u0018BA@ \u0003\u001d\u0001\u0018mY6bO\u0016LA!a\u0001\u0002\u0006\ta1+\u001a:jC2L\'0\u00192mK*\u0011qpH\u0001\u000bk:$WM\u001d7zS:<\u0017bAA\u0004e\u0006aA-\u001a4bk2$h+\u00197vKB!QE\u0017;w\u0013\r\tYA\u001d\u000b\u0006u\u0006M\u0011Q\u0003\u0005\u0007\u0003\u000fa\u0001\u0019\u0001=\t\u000f\u0005-A\u00021\u0001\u0002\u000e\u0005a\u0011\u000e^3sCR|\'O\u0012:p[R!\u00111DA\u0014!\u0015I\u0013QDA\u0011\u0013\r\ty\"\b\u0002\t\u0013R,\'/\u0019;peB)Q%a\tum&\u0019\u0011QE\u0010\u0003\rQ+\b\u000f\\33\u0011\u0019\tIC\u0004a\u0001i\u0006)1\u000f^1si\u0006\u00012.Z=t\u0013R,\'/\u0019;pe\u001a\u0013x.\u001c\u000b\u0005\u0003_\t\t\u0004\u0005\u0003*\u0003;!\bBBA\u0015\u001f\u0001\u0007A/\u0001\u0005pe\u0012,\'/\u001b8h+\t\t9\u0004\u0005\u0003~\u0003s!\u0018\u0002BA\u001e\u0003\u000b\u0011\u0001b\u0014:eKJLgnZ\u0001\ne\u0006tw-Z%na2$RA_A!\u0003\u0017Bq!a\u0011\u0012\u0001\u0004\t)%\u0001\u0003ge>l\u0007\u0003B\u0013\u0002HQL1!!\u0013 \u0005\u0019y\u0005\u000f^5p]\"9\u0011QJ\tA\u0002\u0005\u0015\u0013!B;oi&d\u0017aC:vER\u0014\u0018m\u0019;P]\u0016$B!a\u0015\u0002V5\t\u0011\u0002\u0003\u0004\u0002XI\u0001\r\u0001^\u0001\u0005K2,W.\u0001\u0004bI\u0012|e.\u001a\u000b\u0005\u0003\'\ni\u0006C\u0004\u0002XM\u0001\r!!\t\u0002\u000b\u0015l\u0007\u000f^=\u0016\u0003i\faaY8oG\u0006$X\u0003BA4\u0003[\"B!!\u001b\u0002tA)!\b\u0001;\u0002lA\u0019A&!\u001c\u0005\u000f\u0005=TC1\u0001\u0002r\t\u0011aKM\t\u0003mNBq!!\u001e\u0016\u0001\u0004\t9(\u0001\u0004tk\u001a4\u0017\u000e\u001f\t\u0006S\u0005e\u0014QP\u0005\u0004\u0003wj\"\u0001D%uKJ\f\'\r\\3P]\u000e,\u0007CB\u0013\u0002$Q\fY\'\u0001\u0007ge>l7\u000b]3dS\u001aL7\rF\u0002{\u0003\u0007Cq!!\"\u0017\u0001\u0004\t9)\u0001\u0003d_2d\u0007#B\u0015\u0002z\u0005\u0005\u0012A\u00058foN\u0003XmY5gS\u000e\u0014U/\u001b7eKJ,\"!!$\u0011\ri\ny)!\t{\u0013\r\t\tj\u0007\u0002\b\u0005VLG\u000eZ3s\u0003I\u0019X\u000f]3sI\u0011,g-Y;miZ\u000bG.^3\u0016\u0005\u00055\u0001fB\u0005\u0002\u001a\u0006}\u0015\u0011\u0015\t\u0004K\u0005m\u0015bAAO?\t\u00012+\u001a:jC24VM]:j_:,\u0016\nR\u0001\u0006m\u0006dW/\u001a\u0010\u0002\u0007\u0005aqO]5uKJ+\u0007\u000f\\1dKR\u0011\u0011q\u0015\t\u0005\u0003S\u000b\u0019,\u0004\u0002\u0002,*!\u0011QVAX\u0003\u0011a\u0017M\\4\u000b\u0005\u0005E\u0016\u0001\u00026bm\u0006LA!!.\u0002,\n1qJ\u00196fGRDsaBAM\u0003?\u000b\t\u000bK\u0004\u0007\u00033\u000by*!)"
    )
BootstrapMethods:
  0: #89 REF_invokeStatic java/lang/invoke/LambdaMetafactory.altMetafactory:(Ljava/lang/invoke/MethodHandles$Lookup;Ljava/lang/String;Ljava/lang/invoke/MethodType;[Ljava/lang/Object;)Ljava/lang/invoke/CallSite;
    Method arguments:
      #76 (Ljava/lang/Object;)Ljava/lang/Object;
      #81 REF_invokeStatic scala/collection/mutable/SortedMap.$anonfun$withDefaultValue$1:(Ljava/lang/Object;Ljava/lang/Object;)Ljava/lang/Object;
      #76 (Ljava/lang/Object;)Ljava/lang/Object;
      #82 1
  1: #106 REF_invokeStatic scala/runtime/LambdaDeserialize.bootstrap:(Ljava/lang/invoke/MethodHandles$Lookup;Ljava/lang/String;Ljava/lang/invoke/MethodType;[Ljava/lang/invoke/MethodHandle;)Ljava/lang/invoke/CallSite;
    Method arguments:
      #81 REF_invokeStatic scala/collection/mutable/SortedMap.$anonfun$withDefaultValue$1:(Ljava/lang/Object;Ljava/lang/Object;)Ljava/lang/Object;
  ScalaInlineInfo: length = 0x36 (unknown attribute)
   01 00 00 0A 00 4D 00 4E 01 00 60 00 61 01 00 31
   00 32 00 00 2F 00 30 01 00 28 00 29 00 00 25 00
   26 01 00 39 00 3A 00 00 36 00 37 01 00 45 00 46
   00 00 43 00 44 01
  ScalaSig: length = 0x3 (unknown attribute)
   05 02 00
