Classfile /Users/mw/Projects/slang-braindump/.jar/jar11/assemble/slang-braindump/assemble/content/scala/collection/mutable/UnrolledBuffer$Unrolled.class
  Last modified May 29, 2022; size 12282 bytes
  SHA-256 checksum 84ef71df390d18878fe62bd54ac15e7ac95bc3d0c44b60c8b186ff4accbe99cd
  Compiled from "UnrolledBuffer.scala"
public class scala.collection.mutable.UnrolledBuffer$Unrolled<T extends java.lang.Object> extends java.lang.Object
  minor version: 0
  major version: 52
  flags: (0x0021) ACC_PUBLIC, ACC_SUPER
  this_class: #2                          // scala/collection/mutable/UnrolledBuffer$Unrolled
  super_class: #5                         // java/lang/Object
  interfaces: 0, fields: 5, methods: 32, attributes: 6
Constant pool:
    #1 = Utf8               scala/collection/mutable/UnrolledBuffer$Unrolled
    #2 = Class              #1            // scala/collection/mutable/UnrolledBuffer$Unrolled
    #3 = Utf8               <T:Ljava/lang/Object;>Ljava/lang/Object;
    #4 = Utf8               java/lang/Object
    #5 = Class              #4            // java/lang/Object
    #6 = Utf8               UnrolledBuffer.scala
    #7 = Utf8               java/lang/invoke/MethodHandles$Lookup
    #8 = Class              #7            // java/lang/invoke/MethodHandles$Lookup
    #9 = Utf8               java/lang/invoke/MethodHandles
   #10 = Class              #9            // java/lang/invoke/MethodHandles
   #11 = Utf8               Lookup
   #12 = Utf8               scala/collection/mutable/UnrolledBuffer
   #13 = Class              #12           // scala/collection/mutable/UnrolledBuffer
   #14 = Utf8               Unrolled
   #15 = Utf8               size
   #16 = Utf8               I
   #17 = Utf8               array
   #18 = Utf8               Ljava/lang/Object;
   #19 = Utf8               next
   #20 = Utf8               Lscala/collection/mutable/UnrolledBuffer$Unrolled;
   #21 = Utf8               Lscala/collection/mutable/UnrolledBuffer$Unrolled<TT;>;
   #22 = Utf8               buff
   #23 = Utf8               Lscala/collection/mutable/UnrolledBuffer;
   #24 = Utf8               Lscala/collection/mutable/UnrolledBuffer<TT;>;
   #25 = Utf8               evidence$4
   #26 = Utf8               Lscala/reflect/ClassTag;
   #27 = Utf8               Lscala/reflect/ClassTag<TT;>;
   #28 = Utf8               ()I
   #29 = NameAndType        #15:#16       // size:I
   #30 = Fieldref           #2.#29        // scala/collection/mutable/UnrolledBuffer$Unrolled.size:I
   #31 = Utf8               this
   #32 = Utf8               size_$eq
   #33 = Utf8               (I)V
   #34 = Utf8               x$1
   #35 = Utf8               ()Ljava/lang/Object;
   #36 = NameAndType        #17:#18       // array:Ljava/lang/Object;
   #37 = Fieldref           #2.#36        // scala/collection/mutable/UnrolledBuffer$Unrolled.array:Ljava/lang/Object;
   #38 = Utf8               array_$eq
   #39 = Utf8               (Ljava/lang/Object;)V
   #40 = Utf8               ()Lscala/collection/mutable/UnrolledBuffer$Unrolled;
   #41 = Utf8               ()Lscala/collection/mutable/UnrolledBuffer$Unrolled<TT;>;
   #42 = NameAndType        #19:#20       // next:Lscala/collection/mutable/UnrolledBuffer$Unrolled;
   #43 = Fieldref           #2.#42        // scala/collection/mutable/UnrolledBuffer$Unrolled.next:Lscala/collection/mutable/UnrolledBuffer$Unrolled;
   #44 = Utf8               next_$eq
   #45 = Utf8               (Lscala/collection/mutable/UnrolledBuffer$Unrolled;)V
   #46 = Utf8               (Lscala/collection/mutable/UnrolledBuffer$Unrolled<TT;>;)V
   #47 = Utf8               ()Lscala/collection/mutable/UnrolledBuffer;
   #48 = Utf8               ()Lscala/collection/mutable/UnrolledBuffer<TT;>;
   #49 = NameAndType        #22:#23       // buff:Lscala/collection/mutable/UnrolledBuffer;
   #50 = Fieldref           #2.#49        // scala/collection/mutable/UnrolledBuffer$Unrolled.buff:Lscala/collection/mutable/UnrolledBuffer;
   #51 = Utf8               nextlength
   #52 = NameAndType        #22:#47       // buff:()Lscala/collection/mutable/UnrolledBuffer;
   #53 = Methodref          #2.#52        // scala/collection/mutable/UnrolledBuffer$Unrolled.buff:()Lscala/collection/mutable/UnrolledBuffer;
   #54 = Utf8               scala/collection/mutable/UnrolledBuffer$
   #55 = Class              #54           // scala/collection/mutable/UnrolledBuffer$
   #56 = Utf8               MODULE$
   #57 = Utf8               Lscala/collection/mutable/UnrolledBuffer$;
   #58 = NameAndType        #56:#57       // MODULE$:Lscala/collection/mutable/UnrolledBuffer$;
   #59 = Fieldref           #55.#58       // scala/collection/mutable/UnrolledBuffer$.MODULE$:Lscala/collection/mutable/UnrolledBuffer$;
   #60 = Utf8               unrolledlength
   #61 = NameAndType        #60:#28       // unrolledlength:()I
   #62 = Methodref          #55.#61       // scala/collection/mutable/UnrolledBuffer$.unrolledlength:()I
   #63 = NameAndType        #17:#35       // array:()Ljava/lang/Object;
   #64 = Methodref          #2.#63        // scala/collection/mutable/UnrolledBuffer$Unrolled.array:()Ljava/lang/Object;
   #65 = Utf8               java/lang/reflect/Array
   #66 = Class              #65           // java/lang/reflect/Array
   #67 = Utf8               getLength
   #68 = Utf8               (Ljava/lang/Object;)I
   #69 = NameAndType        #67:#68       // getLength:(Ljava/lang/Object;)I
   #70 = Methodref          #66.#69       // java/lang/reflect/Array.getLength:(Ljava/lang/Object;)I
   #71 = Utf8               calcNextLength
   #72 = Utf8               (I)I
   #73 = NameAndType        #71:#72       // calcNextLength:(I)I
   #74 = Methodref          #13.#73       // scala/collection/mutable/UnrolledBuffer.calcNextLength:(I)I
   #75 = Utf8               append
   #76 = Utf8               (Ljava/lang/Object;)Lscala/collection/mutable/UnrolledBuffer$Unrolled;
   #77 = Utf8               (TT;)Lscala/collection/mutable/UnrolledBuffer$Unrolled<TT;>;
   #78 = Utf8               elem
   #79 = NameAndType        #15:#28       // size:()I
   #80 = Methodref          #2.#79        // scala/collection/mutable/UnrolledBuffer$Unrolled.size:()I
   #81 = Utf8               scala/runtime/ScalaRunTime$
   #82 = Class              #81           // scala/runtime/ScalaRunTime$
   #83 = Utf8               Lscala/runtime/ScalaRunTime$;
   #84 = NameAndType        #56:#83       // MODULE$:Lscala/runtime/ScalaRunTime$;
   #85 = Fieldref           #82.#84       // scala/runtime/ScalaRunTime$.MODULE$:Lscala/runtime/ScalaRunTime$;
   #86 = Utf8               array_update
   #87 = Utf8               (Ljava/lang/Object;ILjava/lang/Object;)V
   #88 = NameAndType        #86:#87       // array_update:(Ljava/lang/Object;ILjava/lang/Object;)V
   #89 = Methodref          #82.#88       // scala/runtime/ScalaRunTime$.array_update:(Ljava/lang/Object;ILjava/lang/Object;)V
   #90 = NameAndType        #32:#33       // size_$eq:(I)V
   #91 = Methodref          #2.#90        // scala/collection/mutable/UnrolledBuffer$Unrolled.size_$eq:(I)V
   #92 = NameAndType        #25:#26       // evidence$4:Lscala/reflect/ClassTag;
   #93 = Fieldref           #2.#92        // scala/collection/mutable/UnrolledBuffer$Unrolled.evidence$4:Lscala/reflect/ClassTag;
   #94 = NameAndType        #51:#28       // nextlength:()I
   #95 = Methodref          #2.#94        // scala/collection/mutable/UnrolledBuffer$Unrolled.nextlength:()I
   #96 = Utf8               scala/reflect/ClassTag
   #97 = Class              #96           // scala/reflect/ClassTag
   #98 = Utf8               newArray
   #99 = Utf8               (I)Ljava/lang/Object;
  #100 = NameAndType        #98:#99       // newArray:(I)Ljava/lang/Object;
  #101 = InterfaceMethodref #97.#100      // scala/reflect/ClassTag.newArray:(I)Ljava/lang/Object;
  #102 = Utf8               <init>
  #103 = Utf8               (ILjava/lang/Object;Lscala/collection/mutable/UnrolledBuffer$Unrolled;Lscala/collection/mutable/UnrolledBuffer;Lscala/reflect/ClassTag;)V
  #104 = NameAndType        #102:#103     // "<init>":(ILjava/lang/Object;Lscala/collection/mutable/UnrolledBuffer$Unrolled;Lscala/collection/mutable/UnrolledBuffer;Lscala/reflect/ClassTag;)V
  #105 = Methodref          #2.#104       // scala/collection/mutable/UnrolledBuffer$Unrolled."<init>":(ILjava/lang/Object;Lscala/collection/mutable/UnrolledBuffer$Unrolled;Lscala/collection/mutable/UnrolledBuffer;Lscala/reflect/ClassTag;)V
  #106 = NameAndType        #44:#45       // next_$eq:(Lscala/collection/mutable/UnrolledBuffer$Unrolled;)V
  #107 = Methodref          #2.#106       // scala/collection/mutable/UnrolledBuffer$Unrolled.next_$eq:(Lscala/collection/mutable/UnrolledBuffer$Unrolled;)V
  #108 = NameAndType        #19:#40       // next:()Lscala/collection/mutable/UnrolledBuffer$Unrolled;
  #109 = Methodref          #2.#108       // scala/collection/mutable/UnrolledBuffer$Unrolled.next:()Lscala/collection/mutable/UnrolledBuffer$Unrolled;
  #110 = Utf8               foreach
  #111 = Utf8               (Lscala/Function1;)V
  #112 = Utf8               <U:Ljava/lang/Object;>(Lscala/Function1<TT;TU;>;)V
  #113 = Utf8               f
  #114 = Utf8               array_apply
  #115 = Utf8               (Ljava/lang/Object;I)Ljava/lang/Object;
  #116 = NameAndType        #114:#115     // array_apply:(Ljava/lang/Object;I)Ljava/lang/Object;
  #117 = Methodref          #82.#116      // scala/runtime/ScalaRunTime$.array_apply:(Ljava/lang/Object;I)Ljava/lang/Object;
  #118 = Utf8               scala/Function1
  #119 = Class              #118          // scala/Function1
  #120 = Utf8               apply
  #121 = Utf8               (Ljava/lang/Object;)Ljava/lang/Object;
  #122 = NameAndType        #120:#121     // apply:(Ljava/lang/Object;)Ljava/lang/Object;
  #123 = InterfaceMethodref #119.#122     // scala/Function1.apply:(Ljava/lang/Object;)Ljava/lang/Object;
  #124 = Utf8               chunkarr
  #125 = Utf8               chunksz
  #126 = Utf8               unrolled
  #127 = Utf8               i
  #128 = Utf8               Lscala/Function1;
  #129 = Utf8               mapInPlace
  #130 = Utf8               (Lscala/Function1<TT;TT;>;)V
  #131 = Utf8               (I)TT;
  #132 = Utf8               idx
  #133 = Utf8               update
  #134 = Utf8               (ILjava/lang/Object;)V
  #135 = Utf8               (ITT;)V
  #136 = Utf8               newelem
  #137 = Utf8               locate
  #138 = Utf8               (I)Lscala/collection/mutable/UnrolledBuffer$Unrolled;
  #139 = Utf8               (I)Lscala/collection/mutable/UnrolledBuffer$Unrolled<TT;>;
  #140 = Utf8               prepend
  #141 = Utf8               shiftright
  #142 = Utf8               ()V
  #143 = NameAndType        #141:#142     // shiftright:()V
  #144 = Methodref          #2.#143       // scala/collection/mutable/UnrolledBuffer$Unrolled.shiftright:()V
  #145 = Utf8               (Lscala/collection/mutable/UnrolledBuffer;Lscala/reflect/ClassTag;)V
  #146 = NameAndType        #102:#145     // "<init>":(Lscala/collection/mutable/UnrolledBuffer;Lscala/reflect/ClassTag;)V
  #147 = Methodref          #2.#146       // scala/collection/mutable/UnrolledBuffer$Unrolled."<init>":(Lscala/collection/mutable/UnrolledBuffer;Lscala/reflect/ClassTag;)V
  #148 = NameAndType        #75:#76       // append:(Ljava/lang/Object;)Lscala/collection/mutable/UnrolledBuffer$Unrolled;
  #149 = Methodref          #2.#148       // scala/collection/mutable/UnrolledBuffer$Unrolled.append:(Ljava/lang/Object;)Lscala/collection/mutable/UnrolledBuffer$Unrolled;
  #150 = Utf8               newhead
  #151 = Utf8               remove
  #152 = Utf8               (ILscala/collection/mutable/UnrolledBuffer;)Ljava/lang/Object;
  #153 = Utf8               (ILscala/collection/mutable/UnrolledBuffer<TT;>;)TT;
  #154 = Utf8               buffer
  #155 = Utf8               shiftleft
  #156 = NameAndType        #155:#33      // shiftleft:(I)V
  #157 = Methodref          #2.#156       // scala/collection/mutable/UnrolledBuffer$Unrolled.shiftleft:(I)V
  #158 = Utf8               tryMergeWithNext
  #159 = Utf8               ()Z
  #160 = NameAndType        #158:#159     // tryMergeWithNext:()Z
  #161 = Methodref          #2.#160       // scala/collection/mutable/UnrolledBuffer$Unrolled.tryMergeWithNext:()Z
  #162 = Utf8               lastPtr_$eq
  #163 = NameAndType        #162:#45      // lastPtr_$eq:(Lscala/collection/mutable/UnrolledBuffer$Unrolled;)V
  #164 = Methodref          #13.#163      // scala/collection/mutable/UnrolledBuffer.lastPtr_$eq:(Lscala/collection/mutable/UnrolledBuffer$Unrolled;)V
  #165 = Utf8               r
  #166 = Utf8               subtractOne
  #167 = Utf8               (Ljava/lang/Object;Lscala/collection/mutable/UnrolledBuffer;)Z
  #168 = Utf8               (TT;Lscala/collection/mutable/UnrolledBuffer<TT;>;)Z
  #169 = Utf8               scala/runtime/BoxesRunTime
  #170 = Class              #169          // scala/runtime/BoxesRunTime
  #171 = Utf8               equals
  #172 = Utf8               (Ljava/lang/Object;Ljava/lang/Object;)Z
  #173 = NameAndType        #171:#172     // equals:(Ljava/lang/Object;Ljava/lang/Object;)Z
  #174 = Methodref          #170.#173     // scala/runtime/BoxesRunTime.equals:(Ljava/lang/Object;Ljava/lang/Object;)Z
  #175 = NameAndType        #151:#152     // remove:(ILscala/collection/mutable/UnrolledBuffer;)Ljava/lang/Object;
  #176 = Methodref          #2.#175       // scala/collection/mutable/UnrolledBuffer$Unrolled.remove:(ILscala/collection/mutable/UnrolledBuffer;)Ljava/lang/Object;
  #177 = Utf8               leftb
  #178 = Utf8               nullout
  #179 = Utf8               (II)V
  #180 = NameAndType        #178:#179     // nullout:(II)V
  #181 = Methodref          #2.#180       // scala/collection/mutable/UnrolledBuffer$Unrolled.nullout:(II)V
  #182 = Utf8               waterline
  #183 = NameAndType        #182:#28      // waterline:()I
  #184 = Methodref          #55.#183      // scala/collection/mutable/UnrolledBuffer$.waterline:()I
  #185 = Utf8               scala/Array$
  #186 = Class              #185          // scala/Array$
  #187 = Utf8               Lscala/Array$;
  #188 = NameAndType        #56:#187      // MODULE$:Lscala/Array$;
  #189 = Fieldref           #186.#188     // scala/Array$.MODULE$:Lscala/Array$;
  #190 = Utf8               copy
  #191 = Utf8               (Ljava/lang/Object;ILjava/lang/Object;II)V
  #192 = NameAndType        #190:#191     // copy:(Ljava/lang/Object;ILjava/lang/Object;II)V
  #193 = Methodref          #186.#192     // scala/Array$.copy:(Ljava/lang/Object;ILjava/lang/Object;II)V
  #194 = Utf8               insertAll
  #195 = Utf8               (ILscala/collection/IterableOnce;Lscala/collection/mutable/UnrolledBuffer;)I
  #196 = Utf8               (ILscala/collection/IterableOnce<TT;>;Lscala/collection/mutable/UnrolledBuffer<TT;>;)I
  #197 = Utf8               t
  #198 = Utf8               scala/runtime/ObjectRef
  #199 = Class              #198          // scala/runtime/ObjectRef
  #200 = NameAndType        #102:#39      // "<init>":(Ljava/lang/Object;)V
  #201 = Methodref          #199.#200     // scala/runtime/ObjectRef."<init>":(Ljava/lang/Object;)V
  #202 = Utf8               scala/runtime/IntRef
  #203 = Class              #202          // scala/runtime/IntRef
  #204 = NameAndType        #102:#33      // "<init>":(I)V
  #205 = Methodref          #203.#204     // scala/runtime/IntRef."<init>":(I)V
  #206 = Utf8               scala/collection/IterableOnce
  #207 = Class              #206          // scala/collection/IterableOnce
  #208 = Utf8               iterator
  #209 = Utf8               ()Lscala/collection/Iterator;
  #210 = NameAndType        #208:#209     // iterator:()Lscala/collection/Iterator;
  #211 = InterfaceMethodref #207.#210     // scala/collection/IterableOnce.iterator:()Lscala/collection/Iterator;
  #212 = MethodType         #121          //  (Ljava/lang/Object;)Ljava/lang/Object;
  #213 = Utf8               $anonfun$insertAll$1$adapted
  #214 = Utf8               (Lscala/runtime/ObjectRef;Lscala/runtime/IntRef;Ljava/lang/Object;)Ljava/lang/Object;
  #215 = NameAndType        #213:#214     // $anonfun$insertAll$1$adapted:(Lscala/runtime/ObjectRef;Lscala/runtime/IntRef;Ljava/lang/Object;)Ljava/lang/Object;
  #216 = Methodref          #2.#215       // scala/collection/mutable/UnrolledBuffer$Unrolled.$anonfun$insertAll$1$adapted:(Lscala/runtime/ObjectRef;Lscala/runtime/IntRef;Ljava/lang/Object;)Ljava/lang/Object;
  #217 = MethodHandle       6:#216        // REF_invokeStatic scala/collection/mutable/UnrolledBuffer$Unrolled.$anonfun$insertAll$1$adapted:(Lscala/runtime/ObjectRef;Lscala/runtime/IntRef;Ljava/lang/Object;)Ljava/lang/Object;
  #218 = Integer            1
  #219 = Utf8               java/lang/invoke/LambdaMetafactory
  #220 = Class              #219          // java/lang/invoke/LambdaMetafactory
  #221 = Utf8               altMetafactory
  #222 = Utf8               (Ljava/lang/invoke/MethodHandles$Lookup;Ljava/lang/String;Ljava/lang/invoke/MethodType;[Ljava/lang/Object;)Ljava/lang/invoke/CallSite;
  #223 = NameAndType        #221:#222     // altMetafactory:(Ljava/lang/invoke/MethodHandles$Lookup;Ljava/lang/String;Ljava/lang/invoke/MethodType;[Ljava/lang/Object;)Ljava/lang/invoke/CallSite;
  #224 = Methodref          #220.#223     // java/lang/invoke/LambdaMetafactory.altMetafactory:(Ljava/lang/invoke/MethodHandles$Lookup;Ljava/lang/String;Ljava/lang/invoke/MethodType;[Ljava/lang/Object;)Ljava/lang/invoke/CallSite;
  #225 = MethodHandle       6:#224        // REF_invokeStatic java/lang/invoke/LambdaMetafactory.altMetafactory:(Ljava/lang/invoke/MethodHandles$Lookup;Ljava/lang/String;Ljava/lang/invoke/MethodType;[Ljava/lang/Object;)Ljava/lang/invoke/CallSite;
  #226 = Utf8               (Lscala/runtime/ObjectRef;Lscala/runtime/IntRef;)Lscala/Function1;
  #227 = NameAndType        #120:#226     // apply:(Lscala/runtime/ObjectRef;Lscala/runtime/IntRef;)Lscala/Function1;
  #228 = InvokeDynamic      #0:#227       // #0:apply:(Lscala/runtime/ObjectRef;Lscala/runtime/IntRef;)Lscala/Function1;
  #229 = Utf8               scala/collection/Iterator
  #230 = Class              #229          // scala/collection/Iterator
  #231 = NameAndType        #110:#111     // foreach:(Lscala/Function1;)V
  #232 = InterfaceMethodref #230.#231     // scala/collection/Iterator.foreach:(Lscala/Function1;)V
  #233 = NameAndType        #78:#18       // elem:Ljava/lang/Object;
  #234 = Fieldref           #199.#233     // scala/runtime/ObjectRef.elem:Ljava/lang/Object;
  #235 = NameAndType        #78:#16       // elem:I
  #236 = Fieldref           #203.#235     // scala/runtime/IntRef.elem:I
  #237 = Utf8               $anonfun$insertAll$2$adapted
  #238 = NameAndType        #237:#214     // $anonfun$insertAll$2$adapted:(Lscala/runtime/ObjectRef;Lscala/runtime/IntRef;Ljava/lang/Object;)Ljava/lang/Object;
  #239 = Methodref          #2.#238       // scala/collection/mutable/UnrolledBuffer$Unrolled.$anonfun$insertAll$2$adapted:(Lscala/runtime/ObjectRef;Lscala/runtime/IntRef;Ljava/lang/Object;)Ljava/lang/Object;
  #240 = MethodHandle       6:#239        // REF_invokeStatic scala/collection/mutable/UnrolledBuffer$Unrolled.$anonfun$insertAll$2$adapted:(Lscala/runtime/ObjectRef;Lscala/runtime/IntRef;Ljava/lang/Object;)Ljava/lang/Object;
  #241 = InvokeDynamic      #1:#227       // #1:apply:(Lscala/runtime/ObjectRef;Lscala/runtime/IntRef;)Lscala/Function1;
  #242 = Utf8               newnextnode
  #243 = Utf8               curr
  #244 = Utf8               Lscala/runtime/ObjectRef;
  #245 = Utf8               appended
  #246 = Utf8               Lscala/runtime/IntRef;
  #247 = Utf8               Lscala/collection/IterableOnce;
  #248 = Utf8               create_e
  #249 = Utf8               from
  #250 = Utf8               until
  #251 = Utf8               bind
  #252 = Utf8               (Lscala/collection/mutable/UnrolledBuffer$Unrolled;)Z
  #253 = Utf8               (Lscala/collection/mutable/UnrolledBuffer$Unrolled<TT;>;)Z
  #254 = Utf8               thathead
  #255 = Utf8               scala/Predef$
  #256 = Class              #255          // scala/Predef$
  #257 = Utf8               Lscala/Predef$;
  #258 = NameAndType        #56:#257      // MODULE$:Lscala/Predef$;
  #259 = Fieldref           #256.#258     // scala/Predef$.MODULE$:Lscala/Predef$;
  #260 = Utf8               assert
  #261 = Utf8               (Z)V
  #262 = NameAndType        #260:#261     // assert:(Z)V
  #263 = Methodref          #256.#262     // scala/Predef$.assert:(Z)V
  #264 = Utf8               toString
  #265 = Utf8               ()Ljava/lang/String;
  #266 = Utf8               java/lang/StringBuilder
  #267 = Class              #266          // java/lang/StringBuilder
  #268 = Integer            4
  #269 = Methodref          #267.#204     // java/lang/StringBuilder."<init>":(I)V
  #270 = Utf8               scala/collection/ArrayOps$
  #271 = Class              #270          // scala/collection/ArrayOps$
  #272 = Utf8               Lscala/collection/ArrayOps$;
  #273 = NameAndType        #56:#272      // MODULE$:Lscala/collection/ArrayOps$;
  #274 = Fieldref           #271.#273     // scala/collection/ArrayOps$.MODULE$:Lscala/collection/ArrayOps$;
  #275 = Utf8               slice$extension
  #276 = Utf8               (Ljava/lang/Object;II)Ljava/lang/Object;
  #277 = NameAndType        #275:#276     // slice$extension:(Ljava/lang/Object;II)Ljava/lang/Object;
  #278 = Methodref          #271.#277     // scala/collection/ArrayOps$.slice$extension:(Ljava/lang/Object;II)Ljava/lang/Object;
  #279 = Utf8               genericWrapArray
  #280 = Utf8               (Ljava/lang/Object;)Lscala/collection/mutable/ArraySeq;
  #281 = NameAndType        #279:#280     // genericWrapArray:(Ljava/lang/Object;)Lscala/collection/mutable/ArraySeq;
  #282 = Methodref          #256.#281     // scala/Predef$.genericWrapArray:(Ljava/lang/Object;)Lscala/collection/mutable/ArraySeq;
  #283 = Utf8               scala/collection/StringOps$
  #284 = Class              #283          // scala/collection/StringOps$
  #285 = Utf8               Lscala/collection/StringOps$;
  #286 = NameAndType        #56:#285      // MODULE$:Lscala/collection/StringOps$;
  #287 = Fieldref           #284.#286     // scala/collection/StringOps$.MODULE$:Lscala/collection/StringOps$;
  #288 = Utf8               Unrolled@%08x
  #289 = String             #288          // Unrolled@%08x
  #290 = Utf8               java/lang/System
  #291 = Class              #290          // java/lang/System
  #292 = Utf8               identityHashCode
  #293 = NameAndType        #292:#68      // identityHashCode:(Ljava/lang/Object;)I
  #294 = Methodref          #291.#293     // java/lang/System.identityHashCode:(Ljava/lang/Object;)I
  #295 = Utf8               java/lang/Integer
  #296 = Class              #295          // java/lang/Integer
  #297 = Utf8               valueOf
  #298 = Utf8               (I)Ljava/lang/Integer;
  #299 = NameAndType        #297:#298     // valueOf:(I)Ljava/lang/Integer;
  #300 = Methodref          #296.#299     // java/lang/Integer.valueOf:(I)Ljava/lang/Integer;
  #301 = Utf8               (Ljava/lang/Object;)Lscala/collection/immutable/ArraySeq;
  #302 = NameAndType        #279:#301     // genericWrapArray:(Ljava/lang/Object;)Lscala/collection/immutable/ArraySeq;
  #303 = Methodref          #82.#302      // scala/runtime/ScalaRunTime$.genericWrapArray:(Ljava/lang/Object;)Lscala/collection/immutable/ArraySeq;
  #304 = Utf8               format$extension
  #305 = Utf8               (Ljava/lang/String;Lscala/collection/immutable/Seq;)Ljava/lang/String;
  #306 = NameAndType        #304:#305     // format$extension:(Ljava/lang/String;Lscala/collection/immutable/Seq;)Ljava/lang/String;
  #307 = Methodref          #284.#306     // scala/collection/StringOps$.format$extension:(Ljava/lang/String;Lscala/collection/immutable/Seq;)Ljava/lang/String;
  #308 = Utf8               (Ljava/lang/String;)Ljava/lang/StringBuilder;
  #309 = NameAndType        #75:#308      // append:(Ljava/lang/String;)Ljava/lang/StringBuilder;
  #310 = Methodref          #267.#309     // java/lang/StringBuilder.append:(Ljava/lang/String;)Ljava/lang/StringBuilder;
  #311 = Utf8               [
  #312 = String             #311          // [
  #313 = Utf8               (I)Ljava/lang/StringBuilder;
  #314 = NameAndType        #75:#313      // append:(I)Ljava/lang/StringBuilder;
  #315 = Methodref          #267.#314     // java/lang/StringBuilder.append:(I)Ljava/lang/StringBuilder;
  #316 = Utf8               /
  #317 = String             #316          // /
  #318 = Utf8               ](
  #319 = String             #318          // ](
  #320 = NameAndType        #264:#265     // toString:()Ljava/lang/String;
  #321 = Methodref          #267.#320     // java/lang/StringBuilder.toString:()Ljava/lang/String;
  #322 = Utf8               ,
  #323 = String             #322          // ,
  #324 = Utf8               )
  #325 = String             #324          // )
  #326 = Utf8               scala/collection/IterableOnceOps
  #327 = Class              #326          // scala/collection/IterableOnceOps
  #328 = Utf8               mkString$
  #329 = Utf8               (Lscala/collection/IterableOnceOps;Ljava/lang/String;Ljava/lang/String;Ljava/lang/String;)Ljava/lang/String;
  #330 = NameAndType        #328:#329     // mkString$:(Lscala/collection/IterableOnceOps;Ljava/lang/String;Ljava/lang/String;Ljava/lang/String;)Ljava/lang/String;
  #331 = InterfaceMethodref #327.#330     // scala/collection/IterableOnceOps.mkString$:(Lscala/collection/IterableOnceOps;Ljava/lang/String;Ljava/lang/String;Ljava/lang/String;)Ljava/lang/String;
  #332 = Utf8                ->
  #333 = String             #332          //  ->
  #334 = Methodref          #2.#320       // scala/collection/mutable/UnrolledBuffer$Unrolled.toString:()Ljava/lang/String;
  #335 = Utf8
  #336 = String             #335          //
  #337 = Utf8               (Ljava/lang/Object;)Ljava/lang/StringBuilder;
  #338 = NameAndType        #75:#337      // append:(Ljava/lang/Object;)Ljava/lang/StringBuilder;
  #339 = Methodref          #267.#338     // java/lang/StringBuilder.append:(Ljava/lang/Object;)Ljava/lang/StringBuilder;
  #340 = Utf8               mkString_start
  #341 = Utf8               Ljava/lang/String;
  #342 = Utf8               mkString_sep
  #343 = Utf8               mkString_end
  #344 = Utf8               take$extension_n
  #345 = Utf8               java/lang/String
  #346 = Class              #345          // java/lang/String
  #347 = Utf8               scala/collection/mutable/ArraySeq
  #348 = Class              #347          // scala/collection/mutable/ArraySeq
  #349 = Utf8               $anonfun$insertAll$1
  #350 = Utf8               (Lscala/runtime/ObjectRef;Lscala/runtime/IntRef;Ljava/lang/Object;)V
  #351 = Utf8               curr$1
  #352 = Utf8               appended$1
  #353 = Utf8               $anonfun$insertAll$2
  #354 = Utf8               curr$2
  #355 = Utf8               appended$2
  #356 = Utf8               (ILjava/lang/Object;Lscala/collection/mutable/UnrolledBuffer$Unrolled<TT;>;Lscala/collection/mutable/UnrolledBuffer<TT;>;Lscala/reflect/ClassTag<TT;>;)V
  #357 = NameAndType        #102:#142     // "<init>":()V
  #358 = Methodref          #5.#357       // java/lang/Object."<init>":()V
  #359 = Utf8               (Lscala/reflect/ClassTag;)V
  #360 = Utf8               (Lscala/reflect/ClassTag<TT;>;)V
  #361 = Utf8               evidence$5
  #362 = Utf8               (Lscala/collection/mutable/UnrolledBuffer<TT;>;Lscala/reflect/ClassTag<TT;>;)V
  #363 = Utf8               b
  #364 = Utf8               evidence$6
  #365 = NameAndType        #349:#350     // $anonfun$insertAll$1:(Lscala/runtime/ObjectRef;Lscala/runtime/IntRef;Ljava/lang/Object;)V
  #366 = Methodref          #2.#365       // scala/collection/mutable/UnrolledBuffer$Unrolled.$anonfun$insertAll$1:(Lscala/runtime/ObjectRef;Lscala/runtime/IntRef;Ljava/lang/Object;)V
  #367 = Utf8               scala/runtime/BoxedUnit
  #368 = Class              #367          // scala/runtime/BoxedUnit
  #369 = Utf8               UNIT
  #370 = Utf8               Lscala/runtime/BoxedUnit;
  #371 = NameAndType        #369:#370     // UNIT:Lscala/runtime/BoxedUnit;
  #372 = Fieldref           #368.#371     // scala/runtime/BoxedUnit.UNIT:Lscala/runtime/BoxedUnit;
  #373 = NameAndType        #353:#350     // $anonfun$insertAll$2:(Lscala/runtime/ObjectRef;Lscala/runtime/IntRef;Ljava/lang/Object;)V
  #374 = Methodref          #2.#373       // scala/collection/mutable/UnrolledBuffer$Unrolled.$anonfun$insertAll$2:(Lscala/runtime/ObjectRef;Lscala/runtime/IntRef;Ljava/lang/Object;)V
  #375 = Utf8               $deserializeLambda$
  #376 = Utf8               (Ljava/lang/invoke/SerializedLambda;)Ljava/lang/Object;
  #377 = Utf8               scala/runtime/LambdaDeserialize
  #378 = Class              #377          // scala/runtime/LambdaDeserialize
  #379 = Utf8               bootstrap
  #380 = Utf8               (Ljava/lang/invoke/MethodHandles$Lookup;Ljava/lang/String;Ljava/lang/invoke/MethodType;[Ljava/lang/invoke/MethodHandle;)Ljava/lang/invoke/CallSite;
  #381 = NameAndType        #379:#380     // bootstrap:(Ljava/lang/invoke/MethodHandles$Lookup;Ljava/lang/String;Ljava/lang/invoke/MethodType;[Ljava/lang/invoke/MethodHandle;)Ljava/lang/invoke/CallSite;
  #382 = Methodref          #378.#381     // scala/runtime/LambdaDeserialize.bootstrap:(Ljava/lang/invoke/MethodHandles$Lookup;Ljava/lang/String;Ljava/lang/invoke/MethodType;[Ljava/lang/invoke/MethodHandle;)Ljava/lang/invoke/CallSite;
  #383 = MethodHandle       6:#382        // REF_invokeStatic scala/runtime/LambdaDeserialize.bootstrap:(Ljava/lang/invoke/MethodHandles$Lookup;Ljava/lang/String;Ljava/lang/invoke/MethodType;[Ljava/lang/invoke/MethodHandle;)Ljava/lang/invoke/CallSite;
  #384 = Utf8               lambdaDeserialize
  #385 = NameAndType        #384:#376     // lambdaDeserialize:(Ljava/lang/invoke/SerializedLambda;)Ljava/lang/Object;
  #386 = InvokeDynamic      #2:#385       // #2:lambdaDeserialize:(Ljava/lang/invoke/SerializedLambda;)Ljava/lang/Object;
  #387 = Utf8               Signature
  #388 = Utf8               Code
  #389 = Utf8               LineNumberTable
  #390 = Utf8               LocalVariableTable
  #391 = Utf8               MethodParameters
  #392 = Utf8               StackMapTable
  #393 = Utf8               InnerClasses
  #394 = Utf8               SourceFile
  #395 = Utf8               BootstrapMethods
  #396 = Utf8               ScalaInlineInfo
  #397 = Utf8               Scala
{
  private int size;
    descriptor: I
    flags: (0x0002) ACC_PRIVATE

  private java.lang.Object array;
    descriptor: Ljava/lang/Object;
    flags: (0x0002) ACC_PRIVATE
    Signature: #18                          // Ljava/lang/Object;

  private scala.collection.mutable.UnrolledBuffer$Unrolled<T> next;
    descriptor: Lscala/collection/mutable/UnrolledBuffer$Unrolled;
    flags: (0x0002) ACC_PRIVATE
    Signature: #21                          // Lscala/collection/mutable/UnrolledBuffer$Unrolled<TT;>;

  private final scala.collection.mutable.UnrolledBuffer<T> buff;
    descriptor: Lscala/collection/mutable/UnrolledBuffer;
    flags: (0x0012) ACC_PRIVATE, ACC_FINAL
    Signature: #24                          // Lscala/collection/mutable/UnrolledBuffer<TT;>;

  private final scala.reflect.ClassTag<T> evidence$4;
    descriptor: Lscala/reflect/ClassTag;
    flags: (0x0012) ACC_PRIVATE, ACC_FINAL
    Signature: #27                          // Lscala/reflect/ClassTag<TT;>;

  public int size();
    descriptor: ()I
    flags: (0x0001) ACC_PUBLIC
    Code:
      stack=1, locals=1, args_size=1
         0: aload_0
         1: getfield      #30                 // Field size:I
         4: ireturn
      LineNumberTable:
        line 260: 0
      LocalVariableTable:
        Start  Length  Slot  Name   Signature
            0       5     0  this   Lscala/collection/mutable/UnrolledBuffer$Unrolled;

  public void size_$eq(int);
    descriptor: (I)V
    flags: (0x0001) ACC_PUBLIC
    Code:
      stack=2, locals=2, args_size=2
         0: aload_0
         1: iload_1
         2: putfield      #30                 // Field size:I
         5: return
      LineNumberTable:
        line 260: 0
      LocalVariableTable:
        Start  Length  Slot  Name   Signature
            0       6     0  this   Lscala/collection/mutable/UnrolledBuffer$Unrolled;
            0       6     1   x$1   I
    MethodParameters:
      Name                           Flags
      x$1                            final

  public java.lang.Object array();
    descriptor: ()Ljava/lang/Object;
    flags: (0x0001) ACC_PUBLIC
    Code:
      stack=1, locals=1, args_size=1
         0: aload_0
         1: getfield      #37                 // Field array:Ljava/lang/Object;
         4: areturn
      LineNumberTable:
        line 260: 0
      LocalVariableTable:
        Start  Length  Slot  Name   Signature
            0       5     0  this   Lscala/collection/mutable/UnrolledBuffer$Unrolled;
    Signature: #35                          // ()Ljava/lang/Object;

  public void array_$eq(java.lang.Object);
    descriptor: (Ljava/lang/Object;)V
    flags: (0x0001) ACC_PUBLIC
    Code:
      stack=2, locals=2, args_size=2
         0: aload_0
         1: aload_1
         2: putfield      #37                 // Field array:Ljava/lang/Object;
         5: return
      LineNumberTable:
        line 260: 0
      LocalVariableTable:
        Start  Length  Slot  Name   Signature
            0       6     0  this   Lscala/collection/mutable/UnrolledBuffer$Unrolled;
            0       6     1   x$1   Ljava/lang/Object;
    Signature: #39                          // (Ljava/lang/Object;)V
    MethodParameters:
      Name                           Flags
      x$1                            final

  public scala.collection.mutable.UnrolledBuffer$Unrolled<T> next();
    descriptor: ()Lscala/collection/mutable/UnrolledBuffer$Unrolled;
    flags: (0x0001) ACC_PUBLIC
    Code:
      stack=1, locals=1, args_size=1
         0: aload_0
         1: getfield      #43                 // Field next:Lscala/collection/mutable/UnrolledBuffer$Unrolled;
         4: areturn
      LineNumberTable:
        line 260: 0
      LocalVariableTable:
        Start  Length  Slot  Name   Signature
            0       5     0  this   Lscala/collection/mutable/UnrolledBuffer$Unrolled;
    Signature: #41                          // ()Lscala/collection/mutable/UnrolledBuffer$Unrolled<TT;>;

  public void next_$eq(scala.collection.mutable.UnrolledBuffer$Unrolled<T>);
    descriptor: (Lscala/collection/mutable/UnrolledBuffer$Unrolled;)V
    flags: (0x0001) ACC_PUBLIC
    Code:
      stack=2, locals=2, args_size=2
         0: aload_0
         1: aload_1
         2: putfield      #43                 // Field next:Lscala/collection/mutable/UnrolledBuffer$Unrolled;
         5: return
      LineNumberTable:
        line 260: 0
      LocalVariableTable:
        Start  Length  Slot  Name   Signature
            0       6     0  this   Lscala/collection/mutable/UnrolledBuffer$Unrolled;
            0       6     1   x$1   Lscala/collection/mutable/UnrolledBuffer$Unrolled;
    Signature: #46                          // (Lscala/collection/mutable/UnrolledBuffer$Unrolled<TT;>;)V
    MethodParameters:
      Name                           Flags
      x$1                            final

  public scala.collection.mutable.UnrolledBuffer<T> buff();
    descriptor: ()Lscala/collection/mutable/UnrolledBuffer;
    flags: (0x0001) ACC_PUBLIC
    Code:
      stack=1, locals=1, args_size=1
         0: aload_0
         1: getfield      #50                 // Field buff:Lscala/collection/mutable/UnrolledBuffer;
         4: areturn
      LineNumberTable:
        line 260: 0
      LocalVariableTable:
        Start  Length  Slot  Name   Signature
            0       5     0  this   Lscala/collection/mutable/UnrolledBuffer$Unrolled;
    Signature: #48                          // ()Lscala/collection/mutable/UnrolledBuffer<TT;>;

  private int nextlength();
    descriptor: ()I
    flags: (0x0002) ACC_PRIVATE
    Code:
      stack=2, locals=1, args_size=1
         0: aload_0
         1: invokevirtual #53                 // Method buff:()Lscala/collection/mutable/UnrolledBuffer;
         4: ifnonnull     14
         7: getstatic     #59                 // Field scala/collection/mutable/UnrolledBuffer$.MODULE$:Lscala/collection/mutable/UnrolledBuffer$;
        10: invokevirtual #62                 // Method scala/collection/mutable/UnrolledBuffer$.unrolledlength:()I
        13: ireturn
        14: aload_0
        15: invokevirtual #53                 // Method buff:()Lscala/collection/mutable/UnrolledBuffer;
        18: aload_0
        19: invokevirtual #64                 // Method array:()Ljava/lang/Object;
        22: invokestatic  #70                 // Method java/lang/reflect/Array.getLength:(Ljava/lang/Object;)I
        25: invokevirtual #74                 // Method scala/collection/mutable/UnrolledBuffer.calcNextLength:(I)I
        28: ireturn
      StackMapTable: number_of_entries = 1
        frame_type = 14 /* same */
      LineNumberTable:
        line 264: 0
      LocalVariableTable:
        Start  Length  Slot  Name   Signature
            0      29     0  this   Lscala/collection/mutable/UnrolledBuffer$Unrolled;

  public final scala.collection.mutable.UnrolledBuffer$Unrolled<T> append(T);
    descriptor: (Ljava/lang/Object;)Lscala/collection/mutable/UnrolledBuffer$Unrolled;
    flags: (0x0011) ACC_PUBLIC, ACC_FINAL
    Code:
      stack=8, locals=2, args_size=2
         0: aload_0
         1: invokevirtual #80                 // Method size:()I
         4: aload_0
         5: invokevirtual #64                 // Method array:()Ljava/lang/Object;
         8: invokestatic  #70                 // Method java/lang/reflect/Array.getLength:(Ljava/lang/Object;)I
        11: if_icmpge     41
        14: getstatic     #85                 // Field scala/runtime/ScalaRunTime$.MODULE$:Lscala/runtime/ScalaRunTime$;
        17: aload_0
        18: invokevirtual #64                 // Method array:()Ljava/lang/Object;
        21: aload_0
        22: invokevirtual #80                 // Method size:()I
        25: aload_1
        26: invokevirtual #89                 // Method scala/runtime/ScalaRunTime$.array_update:(Ljava/lang/Object;ILjava/lang/Object;)V
        29: aload_0
        30: aload_0
        31: invokevirtual #80                 // Method size:()I
        34: iconst_1
        35: iadd
        36: invokevirtual #91                 // Method size_$eq:(I)V
        39: aload_0
        40: areturn
        41: aload_0
        42: new           #2                  // class scala/collection/mutable/UnrolledBuffer$Unrolled
        45: dup
        46: iconst_0
        47: aload_0
        48: getfield      #93                 // Field evidence$4:Lscala/reflect/ClassTag;
        51: aload_0
        52: invokespecial #95                 // Method nextlength:()I
        55: invokeinterface #101,  2          // InterfaceMethod scala/reflect/ClassTag.newArray:(I)Ljava/lang/Object;
        60: aconst_null
        61: aload_0
        62: invokevirtual #53                 // Method buff:()Lscala/collection/mutable/UnrolledBuffer;
        65: aload_0
        66: getfield      #93                 // Field evidence$4:Lscala/reflect/ClassTag;
        69: invokespecial #105                // Method "<init>":(ILjava/lang/Object;Lscala/collection/mutable/UnrolledBuffer$Unrolled;Lscala/collection/mutable/UnrolledBuffer;Lscala/reflect/ClassTag;)V
        72: invokevirtual #107                // Method next_$eq:(Lscala/collection/mutable/UnrolledBuffer$Unrolled;)V
        75: aload_0
        76: invokevirtual #109                // Method next:()Lscala/collection/mutable/UnrolledBuffer$Unrolled;
        79: aload_1
        80: astore_1
        81: astore_0
        82: goto          0
      StackMapTable: number_of_entries = 2
        frame_type = 0 /* same */
        frame_type = 40 /* same */
      LineNumberTable:
        line 267: 0
        line 268: 14
        line 269: 29
        line 270: 39
        line 272: 41
        line 273: 75
      LocalVariableTable:
        Start  Length  Slot  Name   Signature
            0      85     0  this   Lscala/collection/mutable/UnrolledBuffer$Unrolled;
            0      85     1  elem   Ljava/lang/Object;
    Signature: #77                          // (TT;)Lscala/collection/mutable/UnrolledBuffer$Unrolled<TT;>;
    MethodParameters:
      Name                           Flags
      elem                           final

  public <U extends java.lang.Object> void foreach(scala.Function1<T, U>);
    descriptor: (Lscala/Function1;)V
    flags: (0x0001) ACC_PUBLIC
    Code:
      stack=3, locals=7, args_size=2
         0: aload_0
         1: astore_2
         2: iconst_0
         3: istore_3
         4: aload_2
         5: ifnull        62
         8: aload_2
         9: invokevirtual #64                 // Method array:()Ljava/lang/Object;
        12: astore        4
        14: aload_2
        15: invokevirtual #80                 // Method size:()I
        18: istore        5
        20: iload_3
        21: iload         5
        23: if_icmpge     52
        26: getstatic     #85                 // Field scala/runtime/ScalaRunTime$.MODULE$:Lscala/runtime/ScalaRunTime$;
        29: aload         4
        31: iload_3
        32: invokevirtual #117                // Method scala/runtime/ScalaRunTime$.array_apply:(Ljava/lang/Object;I)Ljava/lang/Object;
        35: astore        6
        37: aload_1
        38: aload         6
        40: invokeinterface #123,  2          // InterfaceMethod scala/Function1.apply:(Ljava/lang/Object;)Ljava/lang/Object;
        45: pop
        46: iinc          3, 1
        49: goto          20
        52: iconst_0
        53: istore_3
        54: aload_2
        55: invokevirtual #109                // Method next:()Lscala/collection/mutable/UnrolledBuffer$Unrolled;
        58: astore_2
        59: goto          4
        62: return
      StackMapTable: number_of_entries = 4
        frame_type = 253 /* append */
          offset_delta = 4
          locals = [ class scala/collection/mutable/UnrolledBuffer$Unrolled, int ]
        frame_type = 253 /* append */
          offset_delta = 15
          locals = [ class java/lang/Object, int ]
        frame_type = 31 /* same */
        frame_type = 249 /* chop */
          offset_delta = 9
      LineNumberTable:
        line 276: 0
        line 277: 2
        line 278: 4
        line 279: 8
        line 280: 14
        line 281: 20
        line 282: 26
        line 283: 37
        line 284: 46
        line 281: 49
        line 286: 52
        line 287: 54
        line 278: 59
      LocalVariableTable:
        Start  Length  Slot  Name   Signature
           37      12     6  elem   Ljava/lang/Object;
           14      45     4 chunkarr   Ljava/lang/Object;
           20      39     5 chunksz   I
            2      60     2 unrolled   Lscala/collection/mutable/UnrolledBuffer$Unrolled;
            4      58     3     i   I
            0      63     0  this   Lscala/collection/mutable/UnrolledBuffer$Unrolled;
            0      63     1     f   Lscala/Function1;
    Signature: #112                         // <U:Ljava/lang/Object;>(Lscala/Function1<TT;TU;>;)V
    MethodParameters:
      Name                           Flags
      f                              final

  public void mapInPlace(scala.Function1<T, T>);
    descriptor: (Lscala/Function1;)V
    flags: (0x0001) ACC_PUBLIC
    Code:
      stack=5, locals=7, args_size=2
         0: aload_0
         1: astore_2
         2: iconst_0
         3: istore_3
         4: aload_2
         5: ifnull        70
         8: aload_2
         9: invokevirtual #64                 // Method array:()Ljava/lang/Object;
        12: astore        4
        14: aload_2
        15: invokevirtual #80                 // Method size:()I
        18: istore        5
        20: iload_3
        21: iload         5
        23: if_icmpge     60
        26: getstatic     #85                 // Field scala/runtime/ScalaRunTime$.MODULE$:Lscala/runtime/ScalaRunTime$;
        29: aload         4
        31: iload_3
        32: invokevirtual #117                // Method scala/runtime/ScalaRunTime$.array_apply:(Ljava/lang/Object;I)Ljava/lang/Object;
        35: astore        6
        37: getstatic     #85                 // Field scala/runtime/ScalaRunTime$.MODULE$:Lscala/runtime/ScalaRunTime$;
        40: aload         4
        42: iload_3
        43: aload_1
        44: aload         6
        46: invokeinterface #123,  2          // InterfaceMethod scala/Function1.apply:(Ljava/lang/Object;)Ljava/lang/Object;
        51: invokevirtual #89                 // Method scala/runtime/ScalaRunTime$.array_update:(Ljava/lang/Object;ILjava/lang/Object;)V
        54: iinc          3, 1
        57: goto          20
        60: iconst_0
        61: istore_3
        62: aload_2
        63: invokevirtual #109                // Method next:()Lscala/collection/mutable/UnrolledBuffer$Unrolled;
        66: astore_2
        67: goto          4
        70: return
      StackMapTable: number_of_entries = 4
        frame_type = 253 /* append */
          offset_delta = 4
          locals = [ class scala/collection/mutable/UnrolledBuffer$Unrolled, int ]
        frame_type = 253 /* append */
          offset_delta = 15
          locals = [ class java/lang/Object, int ]
        frame_type = 39 /* same */
        frame_type = 249 /* chop */
          offset_delta = 9
      LineNumberTable:
        line 291: 0
        line 292: 2
        line 293: 4
        line 294: 8
        line 295: 14
        line 296: 20
        line 297: 26
        line 298: 37
        line 299: 54
        line 296: 57
        line 301: 60
        line 302: 62
        line 293: 67
      LocalVariableTable:
        Start  Length  Slot  Name   Signature
           37      20     6  elem   Ljava/lang/Object;
           14      53     4 chunkarr   Ljava/lang/Object;
           20      47     5 chunksz   I
            2      68     2 unrolled   Lscala/collection/mutable/UnrolledBuffer$Unrolled;
            4      66     3     i   I
            0      71     0  this   Lscala/collection/mutable/UnrolledBuffer$Unrolled;
            0      71     1     f   Lscala/Function1;
    Signature: #130                         // (Lscala/Function1<TT;TT;>;)V
    MethodParameters:
      Name                           Flags
      f                              final

  public final T apply(int);
    descriptor: (I)Ljava/lang/Object;
    flags: (0x0011) ACC_PUBLIC, ACC_FINAL
    Code:
      stack=3, locals=2, args_size=2
         0: iload_1
         1: aload_0
         2: invokevirtual #80                 // Method size:()I
         5: if_icmpge     20
         8: getstatic     #85                 // Field scala/runtime/ScalaRunTime$.MODULE$:Lscala/runtime/ScalaRunTime$;
        11: aload_0
        12: invokevirtual #64                 // Method array:()Ljava/lang/Object;
        15: iload_1
        16: invokevirtual #117                // Method scala/runtime/ScalaRunTime$.array_apply:(Ljava/lang/Object;I)Ljava/lang/Object;
        19: areturn
        20: aload_0
        21: invokevirtual #109                // Method next:()Lscala/collection/mutable/UnrolledBuffer$Unrolled;
        24: iload_1
        25: aload_0
        26: invokevirtual #80                 // Method size:()I
        29: isub
        30: istore_1
        31: astore_0
        32: goto          0
      StackMapTable: number_of_entries = 2
        frame_type = 0 /* same */
        frame_type = 19 /* same */
      LineNumberTable:
        line 306: 0
      LocalVariableTable:
        Start  Length  Slot  Name   Signature
            0      35     0  this   Lscala/collection/mutable/UnrolledBuffer$Unrolled;
            0      35     1   idx   I
    Signature: #131                         // (I)TT;
    MethodParameters:
      Name                           Flags
      idx                            final

  public final void update(int, T);
    descriptor: (ILjava/lang/Object;)V
    flags: (0x0011) ACC_PUBLIC, ACC_FINAL
    Code:
      stack=4, locals=3, args_size=3
         0: iload_1
         1: aload_0
         2: invokevirtual #80                 // Method size:()I
         5: if_icmpge     21
         8: getstatic     #85                 // Field scala/runtime/ScalaRunTime$.MODULE$:Lscala/runtime/ScalaRunTime$;
        11: aload_0
        12: invokevirtual #64                 // Method array:()Ljava/lang/Object;
        15: iload_1
        16: aload_2
        17: invokevirtual #89                 // Method scala/runtime/ScalaRunTime$.array_update:(Ljava/lang/Object;ILjava/lang/Object;)V
        20: return
        21: aload_0
        22: invokevirtual #109                // Method next:()Lscala/collection/mutable/UnrolledBuffer$Unrolled;
        25: iload_1
        26: aload_0
        27: invokevirtual #80                 // Method size:()I
        30: isub
        31: aload_2
        32: astore_2
        33: istore_1
        34: astore_0
        35: goto          0
      StackMapTable: number_of_entries = 2
        frame_type = 0 /* same */
        frame_type = 20 /* same */
      LineNumberTable:
        line 308: 0
      LocalVariableTable:
        Start  Length  Slot  Name   Signature
            0      38     0  this   Lscala/collection/mutable/UnrolledBuffer$Unrolled;
            0      38     1   idx   I
            0      38     2 newelem   Ljava/lang/Object;
    Signature: #135                         // (ITT;)V
    MethodParameters:
      Name                           Flags
      idx                            final
      newelem                        final

  public final scala.collection.mutable.UnrolledBuffer$Unrolled<T> locate(int);
    descriptor: (I)Lscala/collection/mutable/UnrolledBuffer$Unrolled;
    flags: (0x0011) ACC_PUBLIC, ACC_FINAL
    Code:
      stack=3, locals=2, args_size=2
         0: iload_1
         1: aload_0
         2: invokevirtual #80                 // Method size:()I
         5: if_icmpge     10
         8: aload_0
         9: areturn
        10: aload_0
        11: invokevirtual #109                // Method next:()Lscala/collection/mutable/UnrolledBuffer$Unrolled;
        14: iload_1
        15: aload_0
        16: invokevirtual #80                 // Method size:()I
        19: isub
        20: istore_1
        21: astore_0
        22: goto          0
      StackMapTable: number_of_entries = 2
        frame_type = 0 /* same */
        frame_type = 9 /* same */
      LineNumberTable:
        line 310: 0
      LocalVariableTable:
        Start  Length  Slot  Name   Signature
            0      25     0  this   Lscala/collection/mutable/UnrolledBuffer$Unrolled;
            0      25     1   idx   I
    Signature: #139                         // (I)Lscala/collection/mutable/UnrolledBuffer$Unrolled<TT;>;
    MethodParameters:
      Name                           Flags
      idx                            final

  public scala.collection.mutable.UnrolledBuffer$Unrolled<T> prepend(T);
    descriptor: (Ljava/lang/Object;)Lscala/collection/mutable/UnrolledBuffer$Unrolled;
    flags: (0x0001) ACC_PUBLIC
    Code:
      stack=4, locals=3, args_size=2
         0: aload_0
         1: invokevirtual #80                 // Method size:()I
         4: aload_0
         5: invokevirtual #64                 // Method array:()Ljava/lang/Object;
         8: invokestatic  #70                 // Method java/lang/reflect/Array.getLength:(Ljava/lang/Object;)I
        11: if_icmpge     42
        14: aload_0
        15: invokespecial #144                // Method shiftright:()V
        18: getstatic     #85                 // Field scala/runtime/ScalaRunTime$.MODULE$:Lscala/runtime/ScalaRunTime$;
        21: aload_0
        22: invokevirtual #64                 // Method array:()Ljava/lang/Object;
        25: iconst_0
        26: aload_1
        27: invokevirtual #89                 // Method scala/runtime/ScalaRunTime$.array_update:(Ljava/lang/Object;ILjava/lang/Object;)V
        30: aload_0
        31: aload_0
        32: invokevirtual #80                 // Method size:()I
        35: iconst_1
        36: iadd
        37: invokevirtual #91                 // Method size_$eq:(I)V
        40: aload_0
        41: areturn
        42: new           #2                  // class scala/collection/mutable/UnrolledBuffer$Unrolled
        45: dup
        46: aload_0
        47: invokevirtual #53                 // Method buff:()Lscala/collection/mutable/UnrolledBuffer;
        50: aload_0
        51: getfield      #93                 // Field evidence$4:Lscala/reflect/ClassTag;
        54: invokespecial #147                // Method "<init>":(Lscala/collection/mutable/UnrolledBuffer;Lscala/reflect/ClassTag;)V
        57: astore_2
        58: aload_2
        59: aload_1
        60: invokevirtual #149                // Method append:(Ljava/lang/Object;)Lscala/collection/mutable/UnrolledBuffer$Unrolled;
        63: pop
        64: aload_2
        65: aload_0
        66: invokevirtual #107                // Method next_$eq:(Lscala/collection/mutable/UnrolledBuffer$Unrolled;)V
        69: aload_2
        70: areturn
      StackMapTable: number_of_entries = 1
        frame_type = 42 /* same */
      LineNumberTable:
        line 311: 0
        line 314: 14
        line 315: 18
        line 316: 30
        line 317: 40
        line 321: 42
        line 322: 58
        line 323: 64
        line 324: 69
      LocalVariableTable:
        Start  Length  Slot  Name   Signature
           58      12     2 newhead   Lscala/collection/mutable/UnrolledBuffer$Unrolled;
            0      71     0  this   Lscala/collection/mutable/UnrolledBuffer$Unrolled;
            0      71     1  elem   Ljava/lang/Object;
    Signature: #77                          // (TT;)Lscala/collection/mutable/UnrolledBuffer$Unrolled<TT;>;
    MethodParameters:
      Name                           Flags
      elem                           final

  private void shiftright();
    descriptor: ()V
    flags: (0x0002) ACC_PRIVATE
    Code:
      stack=6, locals=2, args_size=1
         0: aload_0
         1: invokevirtual #80                 // Method size:()I
         4: iconst_1
         5: isub
         6: istore_1
         7: iload_1
         8: iconst_0
         9: if_icmplt     42
        12: getstatic     #85                 // Field scala/runtime/ScalaRunTime$.MODULE$:Lscala/runtime/ScalaRunTime$;
        15: aload_0
        16: invokevirtual #64                 // Method array:()Ljava/lang/Object;
        19: iload_1
        20: iconst_1
        21: iadd
        22: getstatic     #85                 // Field scala/runtime/ScalaRunTime$.MODULE$:Lscala/runtime/ScalaRunTime$;
        25: aload_0
        26: invokevirtual #64                 // Method array:()Ljava/lang/Object;
        29: iload_1
        30: invokevirtual #117                // Method scala/runtime/ScalaRunTime$.array_apply:(Ljava/lang/Object;I)Ljava/lang/Object;
        33: invokevirtual #89                 // Method scala/runtime/ScalaRunTime$.array_update:(Ljava/lang/Object;ILjava/lang/Object;)V
        36: iinc          1, -1
        39: goto          7
        42: return
      StackMapTable: number_of_entries = 2
        frame_type = 252 /* append */
          offset_delta = 7
          locals = [ int ]
        frame_type = 34 /* same */
      LineNumberTable:
        line 328: 0
        line 329: 7
        line 330: 12
        line 331: 36
        line 329: 39
      LocalVariableTable:
        Start  Length  Slot  Name   Signature
            7      35     1     i   I
            0      43     0  this   Lscala/collection/mutable/UnrolledBuffer$Unrolled;

  public final T remove(int, scala.collection.mutable.UnrolledBuffer<T>);
    descriptor: (ILscala/collection/mutable/UnrolledBuffer;)Ljava/lang/Object;
    flags: (0x0011) ACC_PUBLIC, ACC_FINAL
    Code:
      stack=3, locals=4, args_size=3
         0: iload_1
         1: aload_0
         2: invokevirtual #80                 // Method size:()I
         5: if_icmpge     49
         8: getstatic     #85                 // Field scala/runtime/ScalaRunTime$.MODULE$:Lscala/runtime/ScalaRunTime$;
        11: aload_0
        12: invokevirtual #64                 // Method array:()Ljava/lang/Object;
        15: iload_1
        16: invokevirtual #117                // Method scala/runtime/ScalaRunTime$.array_apply:(Ljava/lang/Object;I)Ljava/lang/Object;
        19: astore_3
        20: aload_0
        21: iload_1
        22: invokespecial #157                // Method shiftleft:(I)V
        25: aload_0
        26: aload_0
        27: invokevirtual #80                 // Method size:()I
        30: iconst_1
        31: isub
        32: invokevirtual #91                 // Method size_$eq:(I)V
        35: aload_0
        36: invokevirtual #161                // Method tryMergeWithNext:()Z
        39: ifeq          47
        42: aload_2
        43: aload_0
        44: invokevirtual #164                // Method scala/collection/mutable/UnrolledBuffer.lastPtr_$eq:(Lscala/collection/mutable/UnrolledBuffer$Unrolled;)V
        47: aload_3
        48: areturn
        49: aload_0
        50: invokevirtual #109                // Method next:()Lscala/collection/mutable/UnrolledBuffer$Unrolled;
        53: iload_1
        54: aload_0
        55: invokevirtual #80                 // Method size:()I
        58: isub
        59: aload_2
        60: astore_2
        61: istore_1
        62: astore_0
        63: goto          0
      StackMapTable: number_of_entries = 3
        frame_type = 0 /* same */
        frame_type = 252 /* append */
          offset_delta = 46
          locals = [ class java/lang/Object ]
        frame_type = 250 /* chop */
          offset_delta = 1
      LineNumberTable:
        line 336: 0
        line 339: 8
        line 340: 20
        line 341: 25
        line 342: 35
        line 343: 47
        line 344: 49
      LocalVariableTable:
        Start  Length  Slot  Name   Signature
           20      28     3     r   Ljava/lang/Object;
            0      66     0  this   Lscala/collection/mutable/UnrolledBuffer$Unrolled;
            0      66     1   idx   I
            0      66     2 buffer   Lscala/collection/mutable/UnrolledBuffer;
    Signature: #153                         // (ILscala/collection/mutable/UnrolledBuffer<TT;>;)TT;
    MethodParameters:
      Name                           Flags
      idx                            final
      buffer                         final

  public final boolean subtractOne(T, scala.collection.mutable.UnrolledBuffer<T>);
    descriptor: (Ljava/lang/Object;Lscala/collection/mutable/UnrolledBuffer;)Z
    flags: (0x0011) ACC_PUBLIC, ACC_FINAL
    Code:
      stack=3, locals=4, args_size=3
         0: iconst_0
         1: istore_3
         2: iload_3
         3: aload_0
         4: invokevirtual #80                 // Method size:()I
         7: if_icmpge     43
        10: getstatic     #85                 // Field scala/runtime/ScalaRunTime$.MODULE$:Lscala/runtime/ScalaRunTime$;
        13: aload_0
        14: invokevirtual #64                 // Method array:()Ljava/lang/Object;
        17: iload_3
        18: invokevirtual #117                // Method scala/runtime/ScalaRunTime$.array_apply:(Ljava/lang/Object;I)Ljava/lang/Object;
        21: aload_1
        22: invokestatic  #174                // Method scala/runtime/BoxesRunTime.equals:(Ljava/lang/Object;Ljava/lang/Object;)Z
        25: ifeq          37
        28: aload_0
        29: iload_3
        30: aload_2
        31: invokevirtual #176                // Method remove:(ILscala/collection/mutable/UnrolledBuffer;)Ljava/lang/Object;
        34: pop
        35: iconst_1
        36: ireturn
        37: iinc          3, 1
        40: goto          2
        43: aload_0
        44: invokevirtual #109                // Method next:()Lscala/collection/mutable/UnrolledBuffer$Unrolled;
        47: ifnull        62
        50: aload_0
        51: invokevirtual #109                // Method next:()Lscala/collection/mutable/UnrolledBuffer$Unrolled;
        54: aload_1
        55: aload_2
        56: astore_2
        57: astore_1
        58: astore_0
        59: goto          0
        62: iconst_0
        63: ireturn
      StackMapTable: number_of_entries = 5
        frame_type = 0 /* same */
        frame_type = 252 /* append */
          offset_delta = 1
          locals = [ int ]
        frame_type = 34 /* same */
        frame_type = 5 /* same */
        frame_type = 18 /* same */
      LineNumberTable:
        line 347: 0
        line 348: 2
        line 349: 10
        line 350: 28
        line 351: 35
        line 353: 37
        line 348: 40
        line 355: 43
      LocalVariableTable:
        Start  Length  Slot  Name   Signature
            2      61     3     i   I
            0      64     0  this   Lscala/collection/mutable/UnrolledBuffer$Unrolled;
            0      64     1  elem   Ljava/lang/Object;
            0      64     2 buffer   Lscala/collection/mutable/UnrolledBuffer;
    Signature: #168                         // (TT;Lscala/collection/mutable/UnrolledBuffer<TT;>;)Z
    MethodParameters:
      Name                           Flags
      elem                           final
      buffer                         final

  private void shiftleft(int);
    descriptor: (I)V
    flags: (0x0002) ACC_PRIVATE
    Code:
      stack=7, locals=3, args_size=2
         0: iload_1
         1: istore_2
         2: iload_2
         3: aload_0
         4: invokevirtual #80                 // Method size:()I
         7: iconst_1
         8: isub
         9: if_icmpge     42
        12: getstatic     #85                 // Field scala/runtime/ScalaRunTime$.MODULE$:Lscala/runtime/ScalaRunTime$;
        15: aload_0
        16: invokevirtual #64                 // Method array:()Ljava/lang/Object;
        19: iload_2
        20: getstatic     #85                 // Field scala/runtime/ScalaRunTime$.MODULE$:Lscala/runtime/ScalaRunTime$;
        23: aload_0
        24: invokevirtual #64                 // Method array:()Ljava/lang/Object;
        27: iload_2
        28: iconst_1
        29: iadd
        30: invokevirtual #117                // Method scala/runtime/ScalaRunTime$.array_apply:(Ljava/lang/Object;I)Ljava/lang/Object;
        33: invokevirtual #89                 // Method scala/runtime/ScalaRunTime$.array_update:(Ljava/lang/Object;ILjava/lang/Object;)V
        36: iinc          2, 1
        39: goto          2
        42: aload_0
        43: iload_2
        44: iload_2
        45: iconst_1
        46: iadd
        47: invokespecial #181                // Method nullout:(II)V
        50: return
      StackMapTable: number_of_entries = 2
        frame_type = 252 /* append */
          offset_delta = 2
          locals = [ int ]
        frame_type = 39 /* same */
      LineNumberTable:
        line 360: 0
        line 361: 2
        line 362: 12
        line 363: 36
        line 361: 39
        line 365: 42
      LocalVariableTable:
        Start  Length  Slot  Name   Signature
            2      48     2     i   I
            0      51     0  this   Lscala/collection/mutable/UnrolledBuffer$Unrolled;
            0      51     1 leftb   I
    MethodParameters:
      Name                           Flags
      leftb                          final

  public boolean tryMergeWithNext();
    descriptor: ()Z
    flags: (0x0001) ACC_PUBLIC
    Code:
      stack=6, locals=1, args_size=1
         0: aload_0
         1: invokevirtual #109                // Method next:()Lscala/collection/mutable/UnrolledBuffer$Unrolled;
         4: ifnull        110
         7: aload_0
         8: invokevirtual #80                 // Method size:()I
        11: aload_0
        12: invokevirtual #109                // Method next:()Lscala/collection/mutable/UnrolledBuffer$Unrolled;
        15: invokevirtual #80                 // Method size:()I
        18: iadd
        19: aload_0
        20: invokevirtual #64                 // Method array:()Ljava/lang/Object;
        23: invokestatic  #70                 // Method java/lang/reflect/Array.getLength:(Ljava/lang/Object;)I
        26: getstatic     #59                 // Field scala/collection/mutable/UnrolledBuffer$.MODULE$:Lscala/collection/mutable/UnrolledBuffer$;
        29: invokevirtual #184                // Method scala/collection/mutable/UnrolledBuffer$.waterline:()I
        32: imul
        33: getstatic     #59                 // Field scala/collection/mutable/UnrolledBuffer$.MODULE$:Lscala/collection/mutable/UnrolledBuffer$;
        36: pop
        37: bipush        100
        39: idiv
        40: if_icmpge     110
        43: getstatic     #189                // Field scala/Array$.MODULE$:Lscala/Array$;
        46: aload_0
        47: invokevirtual #109                // Method next:()Lscala/collection/mutable/UnrolledBuffer$Unrolled;
        50: invokevirtual #64                 // Method array:()Ljava/lang/Object;
        53: iconst_0
        54: aload_0
        55: invokevirtual #64                 // Method array:()Ljava/lang/Object;
        58: aload_0
        59: invokevirtual #80                 // Method size:()I
        62: aload_0
        63: invokevirtual #109                // Method next:()Lscala/collection/mutable/UnrolledBuffer$Unrolled;
        66: invokevirtual #80                 // Method size:()I
        69: invokevirtual #193                // Method scala/Array$.copy:(Ljava/lang/Object;ILjava/lang/Object;II)V
        72: aload_0
        73: aload_0
        74: invokevirtual #80                 // Method size:()I
        77: aload_0
        78: invokevirtual #109                // Method next:()Lscala/collection/mutable/UnrolledBuffer$Unrolled;
        81: invokevirtual #80                 // Method size:()I
        84: iadd
        85: invokevirtual #91                 // Method size_$eq:(I)V
        88: aload_0
        89: aload_0
        90: invokevirtual #109                // Method next:()Lscala/collection/mutable/UnrolledBuffer$Unrolled;
        93: invokevirtual #109                // Method next:()Lscala/collection/mutable/UnrolledBuffer$Unrolled;
        96: invokevirtual #107                // Method next_$eq:(Lscala/collection/mutable/UnrolledBuffer$Unrolled;)V
        99: aload_0
       100: invokevirtual #109                // Method next:()Lscala/collection/mutable/UnrolledBuffer$Unrolled;
       103: ifnonnull     108
       106: iconst_1
       107: ireturn
       108: iconst_0
       109: ireturn
       110: iconst_0
       111: ireturn
      StackMapTable: number_of_entries = 2
        frame_type = 251 /* same_frame_extended */
          offset_delta = 108
        frame_type = 1 /* same */
      LineNumberTable:
        line 367: 0
        line 251: 37
        line 367: 39
        line 369: 43
        line 370: 72
        line 371: 88
        line 372: 99
        line 373: 110
      LocalVariableTable:
        Start  Length  Slot  Name   Signature
            0     112     0  this   Lscala/collection/mutable/UnrolledBuffer$Unrolled;

  public final int insertAll(int, scala.collection.IterableOnce<T>, scala.collection.mutable.UnrolledBuffer<T>);
    descriptor: (ILscala/collection/IterableOnce;Lscala/collection/mutable/UnrolledBuffer;)I
    flags: (0x0011) ACC_PUBLIC, ACC_FINAL
    Code:
      stack=7, locals=15, args_size=4
         0: iload_1
         1: aload_0
         2: invokevirtual #80                 // Method size:()I
         5: if_icmpge     225
         8: new           #2                  // class scala/collection/mutable/UnrolledBuffer$Unrolled
        11: dup
        12: iconst_0
        13: aload_0
        14: getfield      #93                 // Field evidence$4:Lscala/reflect/ClassTag;
        17: aload_0
        18: invokevirtual #64                 // Method array:()Ljava/lang/Object;
        21: invokestatic  #70                 // Method java/lang/reflect/Array.getLength:(Ljava/lang/Object;)I
        24: invokeinterface #101,  2          // InterfaceMethod scala/reflect/ClassTag.newArray:(I)Ljava/lang/Object;
        29: aconst_null
        30: aload_0
        31: invokevirtual #53                 // Method buff:()Lscala/collection/mutable/UnrolledBuffer;
        34: aload_0
        35: getfield      #93                 // Field evidence$4:Lscala/reflect/ClassTag;
        38: invokespecial #105                // Method "<init>":(ILjava/lang/Object;Lscala/collection/mutable/UnrolledBuffer$Unrolled;Lscala/collection/mutable/UnrolledBuffer;Lscala/reflect/ClassTag;)V
        41: astore        4
        43: getstatic     #189                // Field scala/Array$.MODULE$:Lscala/Array$;
        46: aload_0
        47: invokevirtual #64                 // Method array:()Ljava/lang/Object;
        50: iload_1
        51: aload         4
        53: invokevirtual #64                 // Method array:()Ljava/lang/Object;
        56: iconst_0
        57: aload_0
        58: invokevirtual #80                 // Method size:()I
        61: iload_1
        62: isub
        63: invokevirtual #193                // Method scala/Array$.copy:(Ljava/lang/Object;ILjava/lang/Object;II)V
        66: aload         4
        68: aload_0
        69: invokevirtual #80                 // Method size:()I
        72: iload_1
        73: isub
        74: invokevirtual #91                 // Method size_$eq:(I)V
        77: aload         4
        79: aload_0
        80: invokevirtual #109                // Method next:()Lscala/collection/mutable/UnrolledBuffer$Unrolled;
        83: invokevirtual #107                // Method next_$eq:(Lscala/collection/mutable/UnrolledBuffer$Unrolled;)V
        86: aload_0
        87: iload_1
        88: aload_0
        89: invokevirtual #80                 // Method size:()I
        92: invokespecial #181                // Method nullout:(II)V
        95: aload_0
        96: iload_1
        97: invokevirtual #91                 // Method size_$eq:(I)V
       100: aload_0
       101: aconst_null
       102: invokevirtual #107                // Method next_$eq:(Lscala/collection/mutable/UnrolledBuffer$Unrolled;)V
       105: new           #199                // class scala/runtime/ObjectRef
       108: dup
       109: aload_0
       110: invokespecial #201                // Method scala/runtime/ObjectRef."<init>":(Ljava/lang/Object;)V
       113: astore        9
       115: aload         9
       117: aconst_null
       118: astore        9
       120: astore        5
       122: iconst_0
       123: istore        10
       125: new           #203                // class scala/runtime/IntRef
       128: dup
       129: iload         10
       131: invokespecial #205                // Method scala/runtime/IntRef."<init>":(I)V
       134: astore        11
       136: aload         11
       138: aconst_null
       139: astore        11
       141: astore        6
       143: aload_2
       144: invokeinterface #211,  1          // InterfaceMethod scala/collection/IterableOnce.iterator:()Lscala/collection/Iterator;
       149: aload         5
       151: aload         6
       153: invokedynamic #228,  0            // InvokeDynamic #0:apply:(Lscala/runtime/ObjectRef;Lscala/runtime/IntRef;)Lscala/Function1;
       158: invokeinterface #232,  2          // InterfaceMethod scala/collection/Iterator.foreach:(Lscala/Function1;)V
       163: aload         5
       165: getfield      #234                // Field scala/runtime/ObjectRef.elem:Ljava/lang/Object;
       168: checkcast     #2                  // class scala/collection/mutable/UnrolledBuffer$Unrolled
       171: aload         4
       173: invokevirtual #107                // Method next_$eq:(Lscala/collection/mutable/UnrolledBuffer$Unrolled;)V
       176: aload         5
       178: getfield      #234                // Field scala/runtime/ObjectRef.elem:Ljava/lang/Object;
       181: checkcast     #2                  // class scala/collection/mutable/UnrolledBuffer$Unrolled
       184: invokevirtual #161                // Method tryMergeWithNext:()Z
       187: ifeq          205
       190: aload_3
       191: aload         5
       193: getfield      #234                // Field scala/runtime/ObjectRef.elem:Ljava/lang/Object;
       196: checkcast     #2                  // class scala/collection/mutable/UnrolledBuffer$Unrolled
       199: invokevirtual #164                // Method scala/collection/mutable/UnrolledBuffer.lastPtr_$eq:(Lscala/collection/mutable/UnrolledBuffer$Unrolled;)V
       202: goto          219
       205: aload         4
       207: invokevirtual #109                // Method next:()Lscala/collection/mutable/UnrolledBuffer$Unrolled;
       210: ifnonnull     219
       213: aload_3
       214: aload         4
       216: invokevirtual #164                // Method scala/collection/mutable/UnrolledBuffer.lastPtr_$eq:(Lscala/collection/mutable/UnrolledBuffer$Unrolled;)V
       219: aload         6
       221: getfield      #236                // Field scala/runtime/IntRef.elem:I
       224: ireturn
       225: iload_1
       226: aload_0
       227: invokevirtual #80                 // Method size:()I
       230: if_icmpeq     240
       233: aload_0
       234: invokevirtual #109                // Method next:()Lscala/collection/mutable/UnrolledBuffer$Unrolled;
       237: ifnonnull     304
       240: new           #199                // class scala/runtime/ObjectRef
       243: dup
       244: aload_0
       245: invokespecial #201                // Method scala/runtime/ObjectRef."<init>":(Ljava/lang/Object;)V
       248: astore        12
       250: aload         12
       252: aconst_null
       253: astore        12
       255: astore        7
       257: iconst_0
       258: istore        13
       260: new           #203                // class scala/runtime/IntRef
       263: dup
       264: iload         13
       266: invokespecial #205                // Method scala/runtime/IntRef."<init>":(I)V
       269: astore        14
       271: aload         14
       273: aconst_null
       274: astore        14
       276: astore        8
       278: aload_2
       279: invokeinterface #211,  1          // InterfaceMethod scala/collection/IterableOnce.iterator:()Lscala/collection/Iterator;
       284: aload         7
       286: aload         8
       288: invokedynamic #241,  0            // InvokeDynamic #1:apply:(Lscala/runtime/ObjectRef;Lscala/runtime/IntRef;)Lscala/Function1;
       293: invokeinterface #232,  2          // InterfaceMethod scala/collection/Iterator.foreach:(Lscala/Function1;)V
       298: aload         8
       300: getfield      #236                // Field scala/runtime/IntRef.elem:I
       303: ireturn
       304: aload_0
       305: invokevirtual #109                // Method next:()Lscala/collection/mutable/UnrolledBuffer$Unrolled;
       308: iload_1
       309: aload_0
       310: invokevirtual #80                 // Method size:()I
       313: isub
       314: aload_2
       315: aload_3
       316: astore_3
       317: astore_2
       318: istore_1
       319: astore_0
       320: goto          0
      StackMapTable: number_of_entries = 6
        frame_type = 0 /* same */
        frame_type = 255 /* full_frame */
          offset_delta = 204
          locals = [ class scala/collection/mutable/UnrolledBuffer$Unrolled, int, class scala/collection/IterableOnce, class scala/collection/mutable/UnrolledBuffer, class scala/collection/mutable/UnrolledBuffer$Unrolled, class scala/runtime/ObjectRef, class scala/runtime/IntRef, top, top, null, int, null ]
          stack = []
        frame_type = 13 /* same */
        frame_type = 255 /* full_frame */
          offset_delta = 5
          locals = [ class scala/collection/mutable/UnrolledBuffer$Unrolled, int, class scala/collection/IterableOnce, class scala/collection/mutable/UnrolledBuffer ]
          stack = []
        frame_type = 14 /* same */
        frame_type = 63 /* same */
      LineNumberTable:
        line 376: 0
        line 379: 8
        line 380: 43
        line 381: 66
        line 382: 77
        line 385: 86
        line 386: 95
        line 387: 100
        line 390: 105
        line 391: 122
        line 392: 143
        line 396: 163
        line 399: 176
        line 400: 205
        line 401: 219
        line 403: 225
        line 404: 240
        line 405: 257
        line 406: 278
        line 410: 298
        line 412: 304
      LocalVariableTable:
        Start  Length  Slot  Name   Signature
           43     181     4 newnextnode   Lscala/collection/mutable/UnrolledBuffer$Unrolled;
          122     102     5  curr   Lscala/runtime/ObjectRef;
          143      81     6 appended   Lscala/runtime/IntRef;
          257      46     7  curr   Lscala/runtime/ObjectRef;
          278      25     8 appended   Lscala/runtime/IntRef;
            0     323     0  this   Lscala/collection/mutable/UnrolledBuffer$Unrolled;
            0     323     1   idx   I
            0     323     2     t   Lscala/collection/IterableOnce;
            0     323     3 buffer   Lscala/collection/mutable/UnrolledBuffer;
          125      11    10 create_e   I
          260      11    13 create_e   I
    Signature: #196                         // (ILscala/collection/IterableOnce<TT;>;Lscala/collection/mutable/UnrolledBuffer<TT;>;)I
    MethodParameters:
      Name                           Flags
      idx                            final
      t                              final
      buffer                         final

  private void nullout(int, int);
    descriptor: (II)V
    flags: (0x0002) ACC_PRIVATE
    Code:
      stack=4, locals=4, args_size=3
         0: iload_1
         1: istore_3
         2: iload_3
         3: iload_2
         4: if_icmpge     25
         7: getstatic     #85                 // Field scala/runtime/ScalaRunTime$.MODULE$:Lscala/runtime/ScalaRunTime$;
        10: aload_0
        11: invokevirtual #64                 // Method array:()Ljava/lang/Object;
        14: iload_3
        15: aconst_null
        16: invokevirtual #89                 // Method scala/runtime/ScalaRunTime$.array_update:(Ljava/lang/Object;ILjava/lang/Object;)V
        19: iinc          3, 1
        22: goto          2
        25: return
      StackMapTable: number_of_entries = 2
        frame_type = 252 /* append */
          offset_delta = 2
          locals = [ int ]
        frame_type = 22 /* same */
      LineNumberTable:
        line 416: 0
        line 417: 2
        line 418: 7
        line 419: 19
        line 417: 22
      LocalVariableTable:
        Start  Length  Slot  Name   Signature
            2      23     3   idx   I
            0      26     0  this   Lscala/collection/mutable/UnrolledBuffer$Unrolled;
            0      26     1  from   I
            0      26     2 until   I
    MethodParameters:
      Name                           Flags
      from                           final
      until                          final

  public boolean bind(scala.collection.mutable.UnrolledBuffer$Unrolled<T>);
    descriptor: (Lscala/collection/mutable/UnrolledBuffer$Unrolled;)Z
    flags: (0x0001) ACC_PUBLIC
    Code:
      stack=2, locals=2, args_size=2
         0: getstatic     #259                // Field scala/Predef$.MODULE$:Lscala/Predef$;
         3: aload_0
         4: invokevirtual #109                // Method next:()Lscala/collection/mutable/UnrolledBuffer$Unrolled;
         7: ifnonnull     14
        10: iconst_1
        11: goto          15
        14: iconst_0
        15: invokevirtual #263                // Method scala/Predef$.assert:(Z)V
        18: aload_0
        19: aload_1
        20: invokevirtual #107                // Method next_$eq:(Lscala/collection/mutable/UnrolledBuffer$Unrolled;)V
        23: aload_0
        24: invokevirtual #161                // Method tryMergeWithNext:()Z
        27: ireturn
      StackMapTable: number_of_entries = 2
        frame_type = 78 /* same_locals_1_stack_item */
          stack = [ class scala/Predef$ ]
        frame_type = 255 /* full_frame */
          offset_delta = 0
          locals = [ class scala/collection/mutable/UnrolledBuffer$Unrolled, class scala/collection/mutable/UnrolledBuffer$Unrolled ]
          stack = [ class scala/Predef$, int ]
      LineNumberTable:
        line 427: 0
        line 428: 18
        line 429: 23
      LocalVariableTable:
        Start  Length  Slot  Name   Signature
            0      28     0  this   Lscala/collection/mutable/UnrolledBuffer$Unrolled;
            0      28     1 thathead   Lscala/collection/mutable/UnrolledBuffer$Unrolled;
    Signature: #253                         // (Lscala/collection/mutable/UnrolledBuffer$Unrolled<TT;>;)Z
    MethodParameters:
      Name                           Flags
      thathead                       final

  public java.lang.String toString();
    descriptor: ()Ljava/lang/String;
    flags: (0x0001) ACC_PUBLIC
    Code:
      stack=10, locals=5, args_size=1
         0: new           #267                // class java/lang/StringBuilder
         3: dup
         4: ldc_w         #268                // int 4
         7: invokespecial #269                // Method java/lang/StringBuilder."<init>":(I)V
        10: getstatic     #259                // Field scala/Predef$.MODULE$:Lscala/Predef$;
        13: getstatic     #274                // Field scala/collection/ArrayOps$.MODULE$:Lscala/collection/ArrayOps$;
        16: aload_0
        17: invokevirtual #64                 // Method array:()Ljava/lang/Object;
        20: aload_0
        21: invokevirtual #80                 // Method size:()I
        24: istore        4
        26: iconst_0
        27: iload         4
        29: invokevirtual #278                // Method scala/collection/ArrayOps$.slice$extension:(Ljava/lang/Object;II)Ljava/lang/Object;
        32: invokevirtual #282                // Method scala/Predef$.genericWrapArray:(Ljava/lang/Object;)Lscala/collection/mutable/ArraySeq;
        35: new           #267                // class java/lang/StringBuilder
        38: dup
        39: ldc_w         #268                // int 4
        42: invokespecial #269                // Method java/lang/StringBuilder."<init>":(I)V
        45: getstatic     #287                // Field scala/collection/StringOps$.MODULE$:Lscala/collection/StringOps$;
        48: ldc_w         #289                // String Unrolled@%08x
        51: getstatic     #85                 // Field scala/runtime/ScalaRunTime$.MODULE$:Lscala/runtime/ScalaRunTime$;
        54: iconst_1
        55: anewarray     #5                  // class java/lang/Object
        58: dup
        59: iconst_0
        60: aload_0
        61: invokestatic  #294                // Method java/lang/System.identityHashCode:(Ljava/lang/Object;)I
        64: invokestatic  #300                // Method java/lang/Integer.valueOf:(I)Ljava/lang/Integer;
        67: aastore
        68: invokevirtual #303                // Method scala/runtime/ScalaRunTime$.genericWrapArray:(Ljava/lang/Object;)Lscala/collection/immutable/ArraySeq;
        71: invokevirtual #307                // Method scala/collection/StringOps$.format$extension:(Ljava/lang/String;Lscala/collection/immutable/Seq;)Ljava/lang/String;
        74: invokevirtual #310                // Method java/lang/StringBuilder.append:(Ljava/lang/String;)Ljava/lang/StringBuilder;
        77: ldc_w         #312                // String [
        80: invokevirtual #310                // Method java/lang/StringBuilder.append:(Ljava/lang/String;)Ljava/lang/StringBuilder;
        83: aload_0
        84: invokevirtual #80                 // Method size:()I
        87: invokevirtual #315                // Method java/lang/StringBuilder.append:(I)Ljava/lang/StringBuilder;
        90: ldc_w         #317                // String /
        93: invokevirtual #310                // Method java/lang/StringBuilder.append:(Ljava/lang/String;)Ljava/lang/StringBuilder;
        96: aload_0
        97: invokevirtual #64                 // Method array:()Ljava/lang/Object;
       100: invokestatic  #70                 // Method java/lang/reflect/Array.getLength:(Ljava/lang/Object;)I
       103: invokevirtual #315                // Method java/lang/StringBuilder.append:(I)Ljava/lang/StringBuilder;
       106: ldc_w         #319                // String ](
       109: invokevirtual #310                // Method java/lang/StringBuilder.append:(Ljava/lang/String;)Ljava/lang/StringBuilder;
       112: invokevirtual #321                // Method java/lang/StringBuilder.toString:()Ljava/lang/String;
       115: ldc_w         #323                // String ,
       118: ldc_w         #325                // String )
       121: astore_3
       122: astore_2
       123: astore_1
       124: dup
       125: ifnonnull     130
       128: aconst_null
       129: athrow
       130: aload_1
       131: aload_2
       132: aload_3
       133: invokestatic  #331                // InterfaceMethod scala/collection/IterableOnceOps.mkString$:(Lscala/collection/IterableOnceOps;Ljava/lang/String;Ljava/lang/String;Ljava/lang/String;)Ljava/lang/String;
       136: aconst_null
       137: astore_1
       138: aconst_null
       139: astore_2
       140: aconst_null
       141: astore_3
       142: invokevirtual #310                // Method java/lang/StringBuilder.append:(Ljava/lang/String;)Ljava/lang/StringBuilder;
       145: ldc_w         #333                // String  ->
       148: invokevirtual #310                // Method java/lang/StringBuilder.append:(Ljava/lang/String;)Ljava/lang/StringBuilder;
       151: aload_0
       152: invokevirtual #109                // Method next:()Lscala/collection/mutable/UnrolledBuffer$Unrolled;
       155: ifnull        168
       158: aload_0
       159: invokevirtual #109                // Method next:()Lscala/collection/mutable/UnrolledBuffer$Unrolled;
       162: invokevirtual #334                // Method toString:()Ljava/lang/String;
       165: goto          171
       168: ldc_w         #336                // String
       171: invokevirtual #339                // Method java/lang/StringBuilder.append:(Ljava/lang/Object;)Ljava/lang/StringBuilder;
       174: invokevirtual #321                // Method java/lang/StringBuilder.toString:()Ljava/lang/String;
       177: areturn
      StackMapTable: number_of_entries = 3
        frame_type = 255 /* full_frame */
          offset_delta = 130
          locals = [ class scala/collection/mutable/UnrolledBuffer$Unrolled, class java/lang/String, class java/lang/String, class java/lang/String, int ]
          stack = [ class java/lang/StringBuilder, class scala/collection/mutable/ArraySeq ]
        frame_type = 255 /* full_frame */
          offset_delta = 37
          locals = [ class scala/collection/mutable/UnrolledBuffer$Unrolled, null, null, null, int ]
          stack = [ class java/lang/StringBuilder ]
        frame_type = 255 /* full_frame */
          offset_delta = 2
          locals = [ class scala/collection/mutable/UnrolledBuffer$Unrolled, null, null, null, int ]
          stack = [ class java/lang/StringBuilder, class java/lang/String ]
      LineNumberTable:
        line 433: 0
      LocalVariableTable:
        Start  Length  Slot  Name   Signature
            0     178     0  this   Lscala/collection/mutable/UnrolledBuffer$Unrolled;
          130       6     1 mkString_start   Ljava/lang/String;
          130       6     2 mkString_sep   Ljava/lang/String;
          130       6     3 mkString_end   Ljava/lang/String;
           26       6     4 take$extension_n   I

  public static final void $anonfun$insertAll$1(scala.runtime.ObjectRef, scala.runtime.IntRef, java.lang.Object);
    descriptor: (Lscala/runtime/ObjectRef;Lscala/runtime/IntRef;Ljava/lang/Object;)V
    flags: (0x1019) ACC_PUBLIC, ACC_STATIC, ACC_FINAL, ACC_SYNTHETIC
    Code:
      stack=3, locals=3, args_size=3
         0: aload_0
         1: aload_0
         2: getfield      #234                // Field scala/runtime/ObjectRef.elem:Ljava/lang/Object;
         5: checkcast     #2                  // class scala/collection/mutable/UnrolledBuffer$Unrolled
         8: aload_2
         9: invokevirtual #149                // Method append:(Ljava/lang/Object;)Lscala/collection/mutable/UnrolledBuffer$Unrolled;
        12: putfield      #234                // Field scala/runtime/ObjectRef.elem:Ljava/lang/Object;
        15: aload_1
        16: aload_1
        17: getfield      #236                // Field scala/runtime/IntRef.elem:I
        20: iconst_1
        21: iadd
        22: putfield      #236                // Field scala/runtime/IntRef.elem:I
        25: return
      LineNumberTable:
        line 393: 0
        line 394: 15
      LocalVariableTable:
        Start  Length  Slot  Name   Signature
            0      26     0 curr$1   Lscala/runtime/ObjectRef;
            0      26     1 appended$1   Lscala/runtime/IntRef;
            0      26     2  elem   Ljava/lang/Object;
    MethodParameters:
      Name                           Flags
      curr$1                         final
      appended$1                     final
      elem                           final

  public static final void $anonfun$insertAll$2(scala.runtime.ObjectRef, scala.runtime.IntRef, java.lang.Object);
    descriptor: (Lscala/runtime/ObjectRef;Lscala/runtime/IntRef;Ljava/lang/Object;)V
    flags: (0x1019) ACC_PUBLIC, ACC_STATIC, ACC_FINAL, ACC_SYNTHETIC
    Code:
      stack=3, locals=3, args_size=3
         0: aload_0
         1: aload_0
         2: getfield      #234                // Field scala/runtime/ObjectRef.elem:Ljava/lang/Object;
         5: checkcast     #2                  // class scala/collection/mutable/UnrolledBuffer$Unrolled
         8: aload_2
         9: invokevirtual #149                // Method append:(Ljava/lang/Object;)Lscala/collection/mutable/UnrolledBuffer$Unrolled;
        12: putfield      #234                // Field scala/runtime/ObjectRef.elem:Ljava/lang/Object;
        15: aload_1
        16: aload_1
        17: getfield      #236                // Field scala/runtime/IntRef.elem:I
        20: iconst_1
        21: iadd
        22: putfield      #236                // Field scala/runtime/IntRef.elem:I
        25: return
      LineNumberTable:
        line 407: 0
        line 408: 15
      LocalVariableTable:
        Start  Length  Slot  Name   Signature
            0      26     0 curr$2   Lscala/runtime/ObjectRef;
            0      26     1 appended$2   Lscala/runtime/IntRef;
            0      26     2  elem   Ljava/lang/Object;
    MethodParameters:
      Name                           Flags
      curr$2                         final
      appended$2                     final
      elem                           final

  public scala.collection.mutable.UnrolledBuffer$Unrolled(int, java.lang.Object, scala.collection.mutable.UnrolledBuffer$Unrolled<T>, scala.collection.mutable.UnrolledBuffer<T>, scala.reflect.ClassTag<T>);
    descriptor: (ILjava/lang/Object;Lscala/collection/mutable/UnrolledBuffer$Unrolled;Lscala/collection/mutable/UnrolledBuffer;Lscala/reflect/ClassTag;)V
    flags: (0x0001) ACC_PUBLIC
    Code:
      stack=2, locals=6, args_size=6
         0: aload_0
         1: iload_1
         2: putfield      #30                 // Field size:I
         5: aload_0
         6: aload_2
         7: putfield      #37                 // Field array:Ljava/lang/Object;
        10: aload_0
        11: aload_3
        12: putfield      #43                 // Field next:Lscala/collection/mutable/UnrolledBuffer$Unrolled;
        15: aload_0
        16: aload         4
        18: putfield      #50                 // Field buff:Lscala/collection/mutable/UnrolledBuffer;
        21: aload_0
        22: aload         5
        24: putfield      #93                 // Field evidence$4:Lscala/reflect/ClassTag;
        27: aload_0
        28: invokespecial #358                // Method java/lang/Object."<init>":()V
        31: return
      LineNumberTable:
        line 260: 0
      LocalVariableTable:
        Start  Length  Slot  Name   Signature
            0      32     0  this   Lscala/collection/mutable/UnrolledBuffer$Unrolled;
            0      32     1  size   I
            0      32     2 array   Ljava/lang/Object;
            0      32     3  next   Lscala/collection/mutable/UnrolledBuffer$Unrolled;
            0      32     4  buff   Lscala/collection/mutable/UnrolledBuffer;
            0      32     5 evidence$4   Lscala/reflect/ClassTag;
    Signature: #356                         // (ILjava/lang/Object;Lscala/collection/mutable/UnrolledBuffer$Unrolled<TT;>;Lscala/collection/mutable/UnrolledBuffer<TT;>;Lscala/reflect/ClassTag<TT;>;)V
    MethodParameters:
      Name                           Flags
      size                           final
      array                          final
      next                           final
      buff                           final
      evidence$4                     final

  public scala.collection.mutable.UnrolledBuffer$Unrolled(scala.reflect.ClassTag<T>);
    descriptor: (Lscala/reflect/ClassTag;)V
    flags: (0x0001) ACC_PUBLIC
    Code:
      stack=6, locals=2, args_size=2
         0: aload_0
         1: iconst_0
         2: aload_1
         3: getstatic     #59                 // Field scala/collection/mutable/UnrolledBuffer$.MODULE$:Lscala/collection/mutable/UnrolledBuffer$;
         6: invokevirtual #62                 // Method scala/collection/mutable/UnrolledBuffer$.unrolledlength:()I
         9: invokeinterface #101,  2          // InterfaceMethod scala/reflect/ClassTag.newArray:(I)Ljava/lang/Object;
        14: aconst_null
        15: aconst_null
        16: aload_1
        17: invokespecial #105                // Method "<init>":(ILjava/lang/Object;Lscala/collection/mutable/UnrolledBuffer$Unrolled;Lscala/collection/mutable/UnrolledBuffer;Lscala/reflect/ClassTag;)V
        20: return
      LineNumberTable:
        line 261: 0
      LocalVariableTable:
        Start  Length  Slot  Name   Signature
            0      21     0  this   Lscala/collection/mutable/UnrolledBuffer$Unrolled;
            0      21     1 evidence$5   Lscala/reflect/ClassTag;
    Signature: #360                         // (Lscala/reflect/ClassTag<TT;>;)V
    MethodParameters:
      Name                           Flags
      evidence$5                     final

  public scala.collection.mutable.UnrolledBuffer$Unrolled(scala.collection.mutable.UnrolledBuffer<T>, scala.reflect.ClassTag<T>);
    descriptor: (Lscala/collection/mutable/UnrolledBuffer;Lscala/reflect/ClassTag;)V
    flags: (0x0001) ACC_PUBLIC
    Code:
      stack=6, locals=3, args_size=3
         0: aload_0
         1: iconst_0
         2: aload_2
         3: getstatic     #59                 // Field scala/collection/mutable/UnrolledBuffer$.MODULE$:Lscala/collection/mutable/UnrolledBuffer$;
         6: invokevirtual #62                 // Method scala/collection/mutable/UnrolledBuffer$.unrolledlength:()I
         9: invokeinterface #101,  2          // InterfaceMethod scala/reflect/ClassTag.newArray:(I)Ljava/lang/Object;
        14: aconst_null
        15: aload_1
        16: aload_2
        17: invokespecial #105                // Method "<init>":(ILjava/lang/Object;Lscala/collection/mutable/UnrolledBuffer$Unrolled;Lscala/collection/mutable/UnrolledBuffer;Lscala/reflect/ClassTag;)V
        20: return
      LineNumberTable:
        line 262: 0
      LocalVariableTable:
        Start  Length  Slot  Name   Signature
            0      21     0  this   Lscala/collection/mutable/UnrolledBuffer$Unrolled;
            0      21     1     b   Lscala/collection/mutable/UnrolledBuffer;
            0      21     2 evidence$6   Lscala/reflect/ClassTag;
    Signature: #362                         // (Lscala/collection/mutable/UnrolledBuffer<TT;>;Lscala/reflect/ClassTag<TT;>;)V
    MethodParameters:
      Name                           Flags
      b                              final
      evidence$6                     final

  public static final java.lang.Object $anonfun$insertAll$1$adapted(scala.runtime.ObjectRef, scala.runtime.IntRef, java.lang.Object);
    descriptor: (Lscala/runtime/ObjectRef;Lscala/runtime/IntRef;Ljava/lang/Object;)Ljava/lang/Object;
    flags: (0x1019) ACC_PUBLIC, ACC_STATIC, ACC_FINAL, ACC_SYNTHETIC
    Code:
      stack=3, locals=3, args_size=3
         0: aload_0
         1: aload_1
         2: aload_2
         3: invokestatic  #366                // Method $anonfun$insertAll$1:(Lscala/runtime/ObjectRef;Lscala/runtime/IntRef;Ljava/lang/Object;)V
         6: getstatic     #372                // Field scala/runtime/BoxedUnit.UNIT:Lscala/runtime/BoxedUnit;
         9: areturn
      LineNumberTable:
        line 392: 0
      LocalVariableTable:
        Start  Length  Slot  Name   Signature
            0      10     0 curr$1   Lscala/runtime/ObjectRef;
            0      10     1 appended$1   Lscala/runtime/IntRef;
            0      10     2  elem   Ljava/lang/Object;
    MethodParameters:
      Name                           Flags
      curr$1                         final
      appended$1                     final
      elem                           final

  public static final java.lang.Object $anonfun$insertAll$2$adapted(scala.runtime.ObjectRef, scala.runtime.IntRef, java.lang.Object);
    descriptor: (Lscala/runtime/ObjectRef;Lscala/runtime/IntRef;Ljava/lang/Object;)Ljava/lang/Object;
    flags: (0x1019) ACC_PUBLIC, ACC_STATIC, ACC_FINAL, ACC_SYNTHETIC
    Code:
      stack=3, locals=3, args_size=3
         0: aload_0
         1: aload_1
         2: aload_2
         3: invokestatic  #374                // Method $anonfun$insertAll$2:(Lscala/runtime/ObjectRef;Lscala/runtime/IntRef;Ljava/lang/Object;)V
         6: getstatic     #372                // Field scala/runtime/BoxedUnit.UNIT:Lscala/runtime/BoxedUnit;
         9: areturn
      LineNumberTable:
        line 406: 0
      LocalVariableTable:
        Start  Length  Slot  Name   Signature
            0      10     0 curr$2   Lscala/runtime/ObjectRef;
            0      10     1 appended$2   Lscala/runtime/IntRef;
            0      10     2  elem   Ljava/lang/Object;
    MethodParameters:
      Name                           Flags
      curr$2                         final
      appended$2                     final
      elem                           final

  private static java.lang.Object $deserializeLambda$(java.lang.invoke.SerializedLambda);
    descriptor: (Ljava/lang/invoke/SerializedLambda;)Ljava/lang/Object;
    flags: (0x100a) ACC_PRIVATE, ACC_STATIC, ACC_SYNTHETIC
    Code:
      stack=1, locals=1, args_size=1
         0: aload_0
         1: invokedynamic #386,  0            // InvokeDynamic #2:lambdaDeserialize:(Ljava/lang/invoke/SerializedLambda;)Ljava/lang/Object;
         6: areturn
}
InnerClasses:
  public static final #11= #8 of #10;     // Lookup=class java/lang/invoke/MethodHandles$Lookup of class java/lang/invoke/MethodHandles
  public static #14= #2 of #13;           // Unrolled=class scala/collection/mutable/UnrolledBuffer$Unrolled of class scala/collection/mutable/UnrolledBuffer
Signature: #3                           // <T:Ljava/lang/Object;>Ljava/lang/Object;
SourceFile: "UnrolledBuffer.scala"
BootstrapMethods:
  0: #225 REF_invokeStatic java/lang/invoke/LambdaMetafactory.altMetafactory:(Ljava/lang/invoke/MethodHandles$Lookup;Ljava/lang/String;Ljava/lang/invoke/MethodType;[Ljava/lang/Object;)Ljava/lang/invoke/CallSite;
    Method arguments:
      #212 (Ljava/lang/Object;)Ljava/lang/Object;
      #217 REF_invokeStatic scala/collection/mutable/UnrolledBuffer$Unrolled.$anonfun$insertAll$1$adapted:(Lscala/runtime/ObjectRef;Lscala/runtime/IntRef;Ljava/lang/Object;)Ljava/lang/Object;
      #212 (Ljava/lang/Object;)Ljava/lang/Object;
      #218 1
  1: #225 REF_invokeStatic java/lang/invoke/LambdaMetafactory.altMetafactory:(Ljava/lang/invoke/MethodHandles$Lookup;Ljava/lang/String;Ljava/lang/invoke/MethodType;[Ljava/lang/Object;)Ljava/lang/invoke/CallSite;
    Method arguments:
      #212 (Ljava/lang/Object;)Ljava/lang/Object;
      #240 REF_invokeStatic scala/collection/mutable/UnrolledBuffer$Unrolled.$anonfun$insertAll$2$adapted:(Lscala/runtime/ObjectRef;Lscala/runtime/IntRef;Ljava/lang/Object;)Ljava/lang/Object;
      #212 (Ljava/lang/Object;)Ljava/lang/Object;
      #218 1
  2: #383 REF_invokeStatic scala/runtime/LambdaDeserialize.bootstrap:(Ljava/lang/invoke/MethodHandles$Lookup;Ljava/lang/String;Ljava/lang/invoke/MethodType;[Ljava/lang/invoke/MethodHandle;)Ljava/lang/invoke/CallSite;
    Method arguments:
      #217 REF_invokeStatic scala/collection/mutable/UnrolledBuffer$Unrolled.$anonfun$insertAll$1$adapted:(Lscala/runtime/ObjectRef;Lscala/runtime/IntRef;Ljava/lang/Object;)Ljava/lang/Object;
      #240 REF_invokeStatic scala/collection/mutable/UnrolledBuffer$Unrolled.$anonfun$insertAll$2$adapted:(Lscala/runtime/ObjectRef;Lscala/runtime/IntRef;Ljava/lang/Object;)Ljava/lang/Object;
  ScalaInlineInfo: length = 0x9F (unknown attribute)
   01 00 00 1F 01 5D 01 5E 01 00 D5 00 D6 01 01 61
   01 5E 01 00 ED 00 D6 01 00 66 00 67 00 00 66 00
   91 00 00 66 01 67 00 00 4B 00 4C 01 00 78 00 63
   01 00 11 00 23 00 00 26 00 27 00 00 FB 00 FC 00
   00 16 00 2F 00 00 6E 00 6F 00 00 C2 00 C3 01 00
   89 00 8A 01 00 81 00 6F 00 00 13 00 28 00 00 2C
   00 2D 00 00 33 00 1C 01 00 B2 00 B3 01 00 8C 00
   4C 00 00 97 00 98 01 00 9B 00 21 01 00 8D 00 8E
   01 00 0F 00 1C 00 00 20 00 21 00 00 A6 00 A7 01
   01 08 01 09 00 00 9E 00 9F 00 00 85 00 86 01
  Scala: length = 0x0 (unknown attribute)

