Classfile /Users/mw/Projects/slang-braindump/.jar/jar11/assemble/slang-braindump/assemble/content/com/fasterxml/jackson/databind/introspect/AnnotatedAndMetadata.class
  Last modified May 29, 2022; size 1366 bytes
  SHA-256 checksum b954d7622fe5f487fc3229e0e69c7eada395b44cb537fc356d75c065f41335f5
  Compiled from "AnnotatedAndMetadata.java"
public class com.fasterxml.jackson.databind.introspect.AnnotatedAndMetadata<A extends com.fasterxml.jackson.databind.introspect.Annotated, M extends java.lang.Object> extends java.lang.Object
  minor version: 0
  major version: 52
  flags: (0x0021) ACC_PUBLIC, ACC_SUPER
  this_class: #4                          // com/fasterxml/jackson/databind/introspect/AnnotatedAndMetadata
  super_class: #6                         // java/lang/Object
  interfaces: 0, fields: 2, methods: 2, attributes: 2
Constant pool:
   #1 = Methodref          #6.#32         // java/lang/Object."<init>":()V
   #2 = Fieldref           #4.#33         // com/fasterxml/jackson/databind/introspect/AnnotatedAndMetadata.annotated:Lcom/fasterxml/jackson/databind/introspect/Annotated;
   #3 = Fieldref           #4.#34         // com/fasterxml/jackson/databind/introspect/AnnotatedAndMetadata.metadata:Ljava/lang/Object;
   #4 = Class              #35            // com/fasterxml/jackson/databind/introspect/AnnotatedAndMetadata
   #5 = Methodref          #4.#36         // com/fasterxml/jackson/databind/introspect/AnnotatedAndMetadata."<init>":(Lcom/fasterxml/jackson/databind/introspect/Annotated;Ljava/lang/Object;)V
   #6 = Class              #37            // java/lang/Object
   #7 = Utf8               annotated
   #8 = Utf8               Lcom/fasterxml/jackson/databind/introspect/Annotated;
   #9 = Utf8               Signature
  #10 = Utf8               TA;
  #11 = Utf8               metadata
  #12 = Utf8               Ljava/lang/Object;
  #13 = Utf8               TM;
  #14 = Utf8               <init>
  #15 = Utf8               (Lcom/fasterxml/jackson/databind/introspect/Annotated;Ljava/lang/Object;)V
  #16 = Utf8               Code
  #17 = Utf8               LineNumberTable
  #18 = Utf8               LocalVariableTable
  #19 = Utf8               this
  #20 = Utf8               Lcom/fasterxml/jackson/databind/introspect/AnnotatedAndMetadata;
  #21 = Utf8               ann
  #22 = Utf8               md
  #23 = Utf8               LocalVariableTypeTable
  #24 = Utf8               Lcom/fasterxml/jackson/databind/introspect/AnnotatedAndMetadata<TA;TM;>;
  #25 = Utf8               (TA;TM;)V
  #26 = Utf8               of
  #27 = Utf8               (Lcom/fasterxml/jackson/databind/introspect/Annotated;Ljava/lang/Object;)Lcom/fasterxml/jackson/databind/introspect/AnnotatedAndMetadata;
  #28 = Utf8               <A:Lcom/fasterxml/jackson/databind/introspect/Annotated;M:Ljava/lang/Object;>(TA;TM;)Lcom/fasterxml/jackson/databind/introspect/AnnotatedAndMetadata<TA;TM;>;
  #29 = Utf8               <A:Lcom/fasterxml/jackson/databind/introspect/Annotated;M:Ljava/lang/Object;>Ljava/lang/Object;
  #30 = Utf8               SourceFile
  #31 = Utf8               AnnotatedAndMetadata.java
  #32 = NameAndType        #14:#38        // "<init>":()V
  #33 = NameAndType        #7:#8          // annotated:Lcom/fasterxml/jackson/databind/introspect/Annotated;
  #34 = NameAndType        #11:#12        // metadata:Ljava/lang/Object;
  #35 = Utf8               com/fasterxml/jackson/databind/introspect/AnnotatedAndMetadata
  #36 = NameAndType        #14:#15        // "<init>":(Lcom/fasterxml/jackson/databind/introspect/Annotated;Ljava/lang/Object;)V
  #37 = Utf8               java/lang/Object
  #38 = Utf8               ()V
{
  public final A annotated;
    descriptor: Lcom/fasterxml/jackson/databind/introspect/Annotated;
    flags: (0x0011) ACC_PUBLIC, ACC_FINAL
    Signature: #10                          // TA;

  public final M metadata;
    descriptor: Ljava/lang/Object;
    flags: (0x0011) ACC_PUBLIC, ACC_FINAL
    Signature: #13                          // TM;

  public com.fasterxml.jackson.databind.introspect.AnnotatedAndMetadata(A, M);
    descriptor: (Lcom/fasterxml/jackson/databind/introspect/Annotated;Ljava/lang/Object;)V
    flags: (0x0001) ACC_PUBLIC
    Code:
      stack=2, locals=3, args_size=3
         0: aload_0
         1: invokespecial #1                  // Method java/lang/Object."<init>":()V
         4: aload_0
         5: aload_1
         6: putfield      #2                  // Field annotated:Lcom/fasterxml/jackson/databind/introspect/Annotated;
         9: aload_0
        10: aload_2
        11: putfield      #3                  // Field metadata:Ljava/lang/Object;
        14: return
      LineNumberTable:
        line 14: 0
        line 15: 4
        line 16: 9
        line 17: 14
      LocalVariableTable:
        Start  Length  Slot  Name   Signature
            0      15     0  this   Lcom/fasterxml/jackson/databind/introspect/AnnotatedAndMetadata;
            0      15     1   ann   Lcom/fasterxml/jackson/databind/introspect/Annotated;
            0      15     2    md   Ljava/lang/Object;
      LocalVariableTypeTable:
        Start  Length  Slot  Name   Signature
            0      15     0  this   Lcom/fasterxml/jackson/databind/introspect/AnnotatedAndMetadata<TA;TM;>;
            0      15     1   ann   TA;
            0      15     2    md   TM;
    Signature: #25                          // (TA;TM;)V

  public static <A extends com.fasterxml.jackson.databind.introspect.Annotated, M extends java.lang.Object> com.fasterxml.jackson.databind.introspect.AnnotatedAndMetadata<A, M> of(A, M);
    descriptor: (Lcom/fasterxml/jackson/databind/introspect/Annotated;Ljava/lang/Object;)Lcom/fasterxml/jackson/databind/introspect/AnnotatedAndMetadata;
    flags: (0x0009) ACC_PUBLIC, ACC_STATIC
    Code:
      stack=4, locals=2, args_size=2
         0: new           #4                  // class com/fasterxml/jackson/databind/introspect/AnnotatedAndMetadata
         3: dup
         4: aload_0
         5: aload_1
         6: invokespecial #5                  // Method "<init>":(Lcom/fasterxml/jackson/databind/introspect/Annotated;Ljava/lang/Object;)V
         9: areturn
      LineNumberTable:
        line 20: 0
      LocalVariableTable:
        Start  Length  Slot  Name   Signature
            0      10     0   ann   Lcom/fasterxml/jackson/databind/introspect/Annotated;
            0      10     1    md   Ljava/lang/Object;
      LocalVariableTypeTable:
        Start  Length  Slot  Name   Signature
            0      10     0   ann   TA;
            0      10     1    md   TM;
    Signature: #28                          // <A:Lcom/fasterxml/jackson/databind/introspect/Annotated;M:Ljava/lang/Object;>(TA;TM;)Lcom/fasterxml/jackson/databind/introspect/AnnotatedAndMetadata<TA;TM;>;
}
Signature: #29                          // <A:Lcom/fasterxml/jackson/databind/introspect/Annotated;M:Ljava/lang/Object;>Ljava/lang/Object;
SourceFile: "AnnotatedAndMetadata.java"
