Classfile /Users/mw/Projects/slang-braindump/.jar/jar11/assemble/slang-braindump/assemble/content/com/fasterxml/jackson/databind/introspect/AnnotationCollector$TwoAnnotations.class
  Last modified May 29, 2022; size 2258 bytes
  SHA-256 checksum 5e4fb7b5abcf4504317333b8d16c7df14398475cd750b720ad70b972e52b2c5b
  Compiled from "AnnotationCollector.java"
public class com.fasterxml.jackson.databind.introspect.AnnotationCollector$TwoAnnotations implements com.fasterxml.jackson.databind.util.Annotations,java.io.Serializable
  minor version: 0
  major version: 52
  flags: (0x0021) ACC_PUBLIC, ACC_SUPER
  this_class: #6                          // com/fasterxml/jackson/databind/introspect/AnnotationCollector$TwoAnnotations
  super_class: #7                         // java/lang/Object
  interfaces: 2, fields: 5, methods: 5, attributes: 2
Constant pool:
   #1 = Methodref          #7.#59         // java/lang/Object."<init>":()V
   #2 = Fieldref           #6.#60         // com/fasterxml/jackson/databind/introspect/AnnotationCollector$TwoAnnotations._type1:Ljava/lang/Class;
   #3 = Fieldref           #6.#61         // com/fasterxml/jackson/databind/introspect/AnnotationCollector$TwoAnnotations._value1:Ljava/lang/annotation/Annotation;
   #4 = Fieldref           #6.#62         // com/fasterxml/jackson/databind/introspect/AnnotationCollector$TwoAnnotations._type2:Ljava/lang/Class;
   #5 = Fieldref           #6.#63         // com/fasterxml/jackson/databind/introspect/AnnotationCollector$TwoAnnotations._value2:Ljava/lang/annotation/Annotation;
   #6 = Class              #65            // com/fasterxml/jackson/databind/introspect/AnnotationCollector$TwoAnnotations
   #7 = Class              #66            // java/lang/Object
   #8 = Class              #67            // com/fasterxml/jackson/databind/util/Annotations
   #9 = Class              #68            // java/io/Serializable
  #10 = Utf8               serialVersionUID
  #11 = Utf8               J
  #12 = Utf8               ConstantValue
  #13 = Long               1l
  #15 = Utf8               _type1
  #16 = Utf8               Ljava/lang/Class;
  #17 = Utf8               Signature
  #18 = Utf8               Ljava/lang/Class<*>;
  #19 = Utf8               _type2
  #20 = Utf8               _value1
  #21 = Utf8               Ljava/lang/annotation/Annotation;
  #22 = Utf8               _value2
  #23 = Utf8               <init>
  #24 = Utf8               (Ljava/lang/Class;Ljava/lang/annotation/Annotation;Ljava/lang/Class;Ljava/lang/annotation/Annotation;)V
  #25 = Utf8               Code
  #26 = Utf8               LineNumberTable
  #27 = Utf8               LocalVariableTable
  #28 = Utf8               this
  #29 = Utf8               TwoAnnotations
  #30 = Utf8               InnerClasses
  #31 = Utf8               Lcom/fasterxml/jackson/databind/introspect/AnnotationCollector$TwoAnnotations;
  #32 = Utf8               type1
  #33 = Utf8               value1
  #34 = Utf8               type2
  #35 = Utf8               value2
  #36 = Utf8               LocalVariableTypeTable
  #37 = Utf8               (Ljava/lang/Class<*>;Ljava/lang/annotation/Annotation;Ljava/lang/Class<*>;Ljava/lang/annotation/Annotation;)V
  #38 = Utf8               get
  #39 = Utf8               (Ljava/lang/Class;)Ljava/lang/annotation/Annotation;
  #40 = Utf8               cls
  #41 = Utf8               Ljava/lang/Class<TA;>;
  #42 = Utf8               StackMapTable
  #43 = Utf8               <A::Ljava/lang/annotation/Annotation;>(Ljava/lang/Class<TA;>;)TA;
  #44 = Utf8               has
  #45 = Utf8               (Ljava/lang/Class;)Z
  #46 = Utf8               (Ljava/lang/Class<*>;)Z
  #47 = Utf8               hasOneOf
  #48 = Utf8               ([Ljava/lang/Class;)Z
  #49 = Utf8               annoClasses
  #50 = Utf8               [Ljava/lang/Class;
  #51 = Utf8               [Ljava/lang/Class<+Ljava/lang/annotation/Annotation;>;
  #52 = Class              #50            // "[Ljava/lang/Class;"
  #53 = Class              #69            // java/lang/Class
  #54 = Utf8               ([Ljava/lang/Class<+Ljava/lang/annotation/Annotation;>;)Z
  #55 = Utf8               size
  #56 = Utf8               ()I
  #57 = Utf8               SourceFile
  #58 = Utf8               AnnotationCollector.java
  #59 = NameAndType        #23:#70        // "<init>":()V
  #60 = NameAndType        #15:#16        // _type1:Ljava/lang/Class;
  #61 = NameAndType        #20:#21        // _value1:Ljava/lang/annotation/Annotation;
  #62 = NameAndType        #19:#16        // _type2:Ljava/lang/Class;
  #63 = NameAndType        #22:#21        // _value2:Ljava/lang/annotation/Annotation;
  #64 = Class              #71            // com/fasterxml/jackson/databind/introspect/AnnotationCollector
  #65 = Utf8               com/fasterxml/jackson/databind/introspect/AnnotationCollector$TwoAnnotations
  #66 = Utf8               java/lang/Object
  #67 = Utf8               com/fasterxml/jackson/databind/util/Annotations
  #68 = Utf8               java/io/Serializable
  #69 = Utf8               java/lang/Class
  #70 = Utf8               ()V
  #71 = Utf8               com/fasterxml/jackson/databind/introspect/AnnotationCollector
{
  private static final long serialVersionUID;
    descriptor: J
    flags: (0x001a) ACC_PRIVATE, ACC_STATIC, ACC_FINAL
    ConstantValue: long 1l

  private final java.lang.Class<?> _type1;
    descriptor: Ljava/lang/Class;
    flags: (0x0012) ACC_PRIVATE, ACC_FINAL
    Signature: #18                          // Ljava/lang/Class<*>;

  private final java.lang.Class<?> _type2;
    descriptor: Ljava/lang/Class;
    flags: (0x0012) ACC_PRIVATE, ACC_FINAL
    Signature: #18                          // Ljava/lang/Class<*>;

  private final java.lang.annotation.Annotation _value1;
    descriptor: Ljava/lang/annotation/Annotation;
    flags: (0x0012) ACC_PRIVATE, ACC_FINAL

  private final java.lang.annotation.Annotation _value2;
    descriptor: Ljava/lang/annotation/Annotation;
    flags: (0x0012) ACC_PRIVATE, ACC_FINAL

  public com.fasterxml.jackson.databind.introspect.AnnotationCollector$TwoAnnotations(java.lang.Class<?>, java.lang.annotation.Annotation, java.lang.Class<?>, java.lang.annotation.Annotation);
    descriptor: (Ljava/lang/Class;Ljava/lang/annotation/Annotation;Ljava/lang/Class;Ljava/lang/annotation/Annotation;)V
    flags: (0x0001) ACC_PUBLIC
    Code:
      stack=2, locals=5, args_size=5
         0: aload_0
         1: invokespecial #1                  // Method java/lang/Object."<init>":()V
         4: aload_0
         5: aload_1
         6: putfield      #2                  // Field _type1:Ljava/lang/Class;
         9: aload_0
        10: aload_2
        11: putfield      #3                  // Field _value1:Ljava/lang/annotation/Annotation;
        14: aload_0
        15: aload_3
        16: putfield      #4                  // Field _type2:Ljava/lang/Class;
        19: aload_0
        20: aload         4
        22: putfield      #5                  // Field _value2:Ljava/lang/annotation/Annotation;
        25: return
      LineNumberTable:
        line 263: 0
        line 264: 4
        line 265: 9
        line 266: 14
        line 267: 19
        line 268: 25
      LocalVariableTable:
        Start  Length  Slot  Name   Signature
            0      26     0  this   Lcom/fasterxml/jackson/databind/introspect/AnnotationCollector$TwoAnnotations;
            0      26     1 type1   Ljava/lang/Class;
            0      26     2 value1   Ljava/lang/annotation/Annotation;
            0      26     3 type2   Ljava/lang/Class;
            0      26     4 value2   Ljava/lang/annotation/Annotation;
      LocalVariableTypeTable:
        Start  Length  Slot  Name   Signature
            0      26     1 type1   Ljava/lang/Class<*>;
            0      26     3 type2   Ljava/lang/Class<*>;
    Signature: #37                          // (Ljava/lang/Class<*>;Ljava/lang/annotation/Annotation;Ljava/lang/Class<*>;Ljava/lang/annotation/Annotation;)V

  public <A extends java.lang.annotation.Annotation> A get(java.lang.Class<A>);
    descriptor: (Ljava/lang/Class;)Ljava/lang/annotation/Annotation;
    flags: (0x0001) ACC_PUBLIC
    Code:
      stack=2, locals=2, args_size=2
         0: aload_0
         1: getfield      #2                  // Field _type1:Ljava/lang/Class;
         4: aload_1
         5: if_acmpne     13
         8: aload_0
         9: getfield      #3                  // Field _value1:Ljava/lang/annotation/Annotation;
        12: areturn
        13: aload_0
        14: getfield      #4                  // Field _type2:Ljava/lang/Class;
        17: aload_1
        18: if_acmpne     26
        21: aload_0
        22: getfield      #5                  // Field _value2:Ljava/lang/annotation/Annotation;
        25: areturn
        26: aconst_null
        27: areturn
      LineNumberTable:
        line 273: 0
        line 274: 8
        line 276: 13
        line 277: 21
        line 279: 26
      LocalVariableTable:
        Start  Length  Slot  Name   Signature
            0      28     0  this   Lcom/fasterxml/jackson/databind/introspect/AnnotationCollector$TwoAnnotations;
            0      28     1   cls   Ljava/lang/Class;
      LocalVariableTypeTable:
        Start  Length  Slot  Name   Signature
            0      28     1   cls   Ljava/lang/Class<TA;>;
      StackMapTable: number_of_entries = 2
        frame_type = 13 /* same */
        frame_type = 12 /* same */
    Signature: #43                          // <A::Ljava/lang/annotation/Annotation;>(Ljava/lang/Class<TA;>;)TA;

  public boolean has(java.lang.Class<?>);
    descriptor: (Ljava/lang/Class;)Z
    flags: (0x0001) ACC_PUBLIC
    Code:
      stack=2, locals=2, args_size=2
         0: aload_0
         1: getfield      #2                  // Field _type1:Ljava/lang/Class;
         4: aload_1
         5: if_acmpeq     16
         8: aload_0
         9: getfield      #4                  // Field _type2:Ljava/lang/Class;
        12: aload_1
        13: if_acmpne     20
        16: iconst_1
        17: goto          21
        20: iconst_0
        21: ireturn
      LineNumberTable:
        line 284: 0
      LocalVariableTable:
        Start  Length  Slot  Name   Signature
            0      22     0  this   Lcom/fasterxml/jackson/databind/introspect/AnnotationCollector$TwoAnnotations;
            0      22     1   cls   Ljava/lang/Class;
      LocalVariableTypeTable:
        Start  Length  Slot  Name   Signature
            0      22     1   cls   Ljava/lang/Class<*>;
      StackMapTable: number_of_entries = 3
        frame_type = 16 /* same */
        frame_type = 3 /* same */
        frame_type = 64 /* same_locals_1_stack_item */
          stack = [ int ]
    Signature: #46                          // (Ljava/lang/Class<*>;)Z

  public boolean hasOneOf(java.lang.Class<? extends java.lang.annotation.Annotation>[]);
    descriptor: ([Ljava/lang/Class;)Z
    flags: (0x0001) ACC_PUBLIC
    Code:
      stack=2, locals=6, args_size=2
         0: aload_1
         1: astore_2
         2: aload_2
         3: arraylength
         4: istore_3
         5: iconst_0
         6: istore        4
         8: iload         4
        10: iload_3
        11: if_icmpge     46
        14: aload_2
        15: iload         4
        17: aaload
        18: astore        5
        20: aload         5
        22: aload_0
        23: getfield      #2                  // Field _type1:Ljava/lang/Class;
        26: if_acmpeq     38
        29: aload         5
        31: aload_0
        32: getfield      #4                  // Field _type2:Ljava/lang/Class;
        35: if_acmpne     40
        38: iconst_1
        39: ireturn
        40: iinc          4, 1
        43: goto          8
        46: iconst_0
        47: ireturn
      LineNumberTable:
        line 289: 0
        line 290: 20
        line 291: 38
        line 289: 40
        line 294: 46
      LocalVariableTable:
        Start  Length  Slot  Name   Signature
           20      20     5   cls   Ljava/lang/Class;
            0      48     0  this   Lcom/fasterxml/jackson/databind/introspect/AnnotationCollector$TwoAnnotations;
            0      48     1 annoClasses   [Ljava/lang/Class;
      LocalVariableTypeTable:
        Start  Length  Slot  Name   Signature
           20      20     5   cls   Ljava/lang/Class<*>;
            0      48     1 annoClasses   [Ljava/lang/Class<+Ljava/lang/annotation/Annotation;>;
      StackMapTable: number_of_entries = 4
        frame_type = 254 /* append */
          offset_delta = 8
          locals = [ class "[Ljava/lang/Class;", int, int ]
        frame_type = 252 /* append */
          offset_delta = 29
          locals = [ class java/lang/Class ]
        frame_type = 250 /* chop */
          offset_delta = 1
        frame_type = 248 /* chop */
          offset_delta = 5
    Signature: #54                          // ([Ljava/lang/Class<+Ljava/lang/annotation/Annotation;>;)Z

  public int size();
    descriptor: ()I
    flags: (0x0001) ACC_PUBLIC
    Code:
      stack=1, locals=1, args_size=1
         0: iconst_2
         1: ireturn
      LineNumberTable:
        line 299: 0
      LocalVariableTable:
        Start  Length  Slot  Name   Signature
            0       2     0  this   Lcom/fasterxml/jackson/databind/introspect/AnnotationCollector$TwoAnnotations;
}
SourceFile: "AnnotationCollector.java"
InnerClasses:
  public static #29= #6 of #64;           // TwoAnnotations=class com/fasterxml/jackson/databind/introspect/AnnotationCollector$TwoAnnotations of class com/fasterxml/jackson/databind/introspect/AnnotationCollector
