Classfile /Users/mw/Projects/slang-braindump/.jar/jar11/assemble/slang-braindump/assemble/content/com/fasterxml/jackson/databind/introspect/VisibilityChecker$1.class
  Last modified May 29, 2022; size 1041 bytes
  SHA-256 checksum e22df6b51aaf9982be88c65df722b3dbb956da677d5b036269191191b3671bd3
  Compiled from "VisibilityChecker.java"
class com.fasterxml.jackson.databind.introspect.VisibilityChecker$1
  minor version: 0
  major version: 52
  flags: (0x1020) ACC_SUPER, ACC_SYNTHETIC
  this_class: #11                         // com/fasterxml/jackson/databind/introspect/VisibilityChecker$1
  super_class: #12                        // java/lang/Object
  interfaces: 0, fields: 1, methods: 1, attributes: 3
Constant pool:
   #1 = Methodref          #26.#27        // com/fasterxml/jackson/annotation/PropertyAccessor.values:()[Lcom/fasterxml/jackson/annotation/PropertyAccessor;
   #2 = Fieldref           #11.#28        // com/fasterxml/jackson/databind/introspect/VisibilityChecker$1.$SwitchMap$com$fasterxml$jackson$annotation$PropertyAccessor:[I
   #3 = Fieldref           #26.#29        // com/fasterxml/jackson/annotation/PropertyAccessor.GETTER:Lcom/fasterxml/jackson/annotation/PropertyAccessor;
   #4 = Methodref          #26.#30        // com/fasterxml/jackson/annotation/PropertyAccessor.ordinal:()I
   #5 = Class              #31            // java/lang/NoSuchFieldError
   #6 = Fieldref           #26.#32        // com/fasterxml/jackson/annotation/PropertyAccessor.SETTER:Lcom/fasterxml/jackson/annotation/PropertyAccessor;
   #7 = Fieldref           #26.#33        // com/fasterxml/jackson/annotation/PropertyAccessor.CREATOR:Lcom/fasterxml/jackson/annotation/PropertyAccessor;
   #8 = Fieldref           #26.#34        // com/fasterxml/jackson/annotation/PropertyAccessor.FIELD:Lcom/fasterxml/jackson/annotation/PropertyAccessor;
   #9 = Fieldref           #26.#35        // com/fasterxml/jackson/annotation/PropertyAccessor.IS_GETTER:Lcom/fasterxml/jackson/annotation/PropertyAccessor;
  #10 = Fieldref           #26.#36        // com/fasterxml/jackson/annotation/PropertyAccessor.ALL:Lcom/fasterxml/jackson/annotation/PropertyAccessor;
  #11 = Class              #37            // com/fasterxml/jackson/databind/introspect/VisibilityChecker$1
  #12 = Class              #39            // java/lang/Object
  #13 = Utf8               $SwitchMap$com$fasterxml$jackson$annotation$PropertyAccessor
  #14 = Utf8               [I
  #15 = Utf8               <clinit>
  #16 = Utf8               ()V
  #17 = Utf8               Code
  #18 = Utf8               LineNumberTable
  #19 = Utf8               LocalVariableTable
  #20 = Utf8               StackMapTable
  #21 = Class              #31            // java/lang/NoSuchFieldError
  #22 = Utf8               SourceFile
  #23 = Utf8               VisibilityChecker.java
  #24 = Utf8               EnclosingMethod
  #25 = Class              #40            // com/fasterxml/jackson/databind/introspect/VisibilityChecker
  #26 = Class              #41            // com/fasterxml/jackson/annotation/PropertyAccessor
  #27 = NameAndType        #42:#43        // values:()[Lcom/fasterxml/jackson/annotation/PropertyAccessor;
  #28 = NameAndType        #13:#14        // $SwitchMap$com$fasterxml$jackson$annotation$PropertyAccessor:[I
  #29 = NameAndType        #44:#45        // GETTER:Lcom/fasterxml/jackson/annotation/PropertyAccessor;
  #30 = NameAndType        #46:#47        // ordinal:()I
  #31 = Utf8               java/lang/NoSuchFieldError
  #32 = NameAndType        #48:#45        // SETTER:Lcom/fasterxml/jackson/annotation/PropertyAccessor;
  #33 = NameAndType        #49:#45        // CREATOR:Lcom/fasterxml/jackson/annotation/PropertyAccessor;
  #34 = NameAndType        #50:#45        // FIELD:Lcom/fasterxml/jackson/annotation/PropertyAccessor;
  #35 = NameAndType        #51:#45        // IS_GETTER:Lcom/fasterxml/jackson/annotation/PropertyAccessor;
  #36 = NameAndType        #52:#45        // ALL:Lcom/fasterxml/jackson/annotation/PropertyAccessor;
  #37 = Utf8               com/fasterxml/jackson/databind/introspect/VisibilityChecker$1
  #38 = Utf8               InnerClasses
  #39 = Utf8               java/lang/Object
  #40 = Utf8               com/fasterxml/jackson/databind/introspect/VisibilityChecker
  #41 = Utf8               com/fasterxml/jackson/annotation/PropertyAccessor
  #42 = Utf8               values
  #43 = Utf8               ()[Lcom/fasterxml/jackson/annotation/PropertyAccessor;
  #44 = Utf8               GETTER
  #45 = Utf8               Lcom/fasterxml/jackson/annotation/PropertyAccessor;
  #46 = Utf8               ordinal
  #47 = Utf8               ()I
  #48 = Utf8               SETTER
  #49 = Utf8               CREATOR
  #50 = Utf8               FIELD
  #51 = Utf8               IS_GETTER
  #52 = Utf8               ALL
{
  static final int[] $SwitchMap$com$fasterxml$jackson$annotation$PropertyAccessor;
    descriptor: [I
    flags: (0x1018) ACC_STATIC, ACC_FINAL, ACC_SYNTHETIC

  static {};
    descriptor: ()V
    flags: (0x0008) ACC_STATIC
    Code:
      stack=3, locals=1, args_size=0
         0: invokestatic  #1                  // Method com/fasterxml/jackson/annotation/PropertyAccessor.values:()[Lcom/fasterxml/jackson/annotation/PropertyAccessor;
         3: arraylength
         4: newarray       int
         6: putstatic     #2                  // Field $SwitchMap$com$fasterxml$jackson$annotation$PropertyAccessor:[I
         9: getstatic     #2                  // Field $SwitchMap$com$fasterxml$jackson$annotation$PropertyAccessor:[I
        12: getstatic     #3                  // Field com/fasterxml/jackson/annotation/PropertyAccessor.GETTER:Lcom/fasterxml/jackson/annotation/PropertyAccessor;
        15: invokevirtual #4                  // Method com/fasterxml/jackson/annotation/PropertyAccessor.ordinal:()I
        18: iconst_1
        19: iastore
        20: goto          24
        23: astore_0
        24: getstatic     #2                  // Field $SwitchMap$com$fasterxml$jackson$annotation$PropertyAccessor:[I
        27: getstatic     #6                  // Field com/fasterxml/jackson/annotation/PropertyAccessor.SETTER:Lcom/fasterxml/jackson/annotation/PropertyAccessor;
        30: invokevirtual #4                  // Method com/fasterxml/jackson/annotation/PropertyAccessor.ordinal:()I
        33: iconst_2
        34: iastore
        35: goto          39
        38: astore_0
        39: getstatic     #2                  // Field $SwitchMap$com$fasterxml$jackson$annotation$PropertyAccessor:[I
        42: getstatic     #7                  // Field com/fasterxml/jackson/annotation/PropertyAccessor.CREATOR:Lcom/fasterxml/jackson/annotation/PropertyAccessor;
        45: invokevirtual #4                  // Method com/fasterxml/jackson/annotation/PropertyAccessor.ordinal:()I
        48: iconst_3
        49: iastore
        50: goto          54
        53: astore_0
        54: getstatic     #2                  // Field $SwitchMap$com$fasterxml$jackson$annotation$PropertyAccessor:[I
        57: getstatic     #8                  // Field com/fasterxml/jackson/annotation/PropertyAccessor.FIELD:Lcom/fasterxml/jackson/annotation/PropertyAccessor;
        60: invokevirtual #4                  // Method com/fasterxml/jackson/annotation/PropertyAccessor.ordinal:()I
        63: iconst_4
        64: iastore
        65: goto          69
        68: astore_0
        69: getstatic     #2                  // Field $SwitchMap$com$fasterxml$jackson$annotation$PropertyAccessor:[I
        72: getstatic     #9                  // Field com/fasterxml/jackson/annotation/PropertyAccessor.IS_GETTER:Lcom/fasterxml/jackson/annotation/PropertyAccessor;
        75: invokevirtual #4                  // Method com/fasterxml/jackson/annotation/PropertyAccessor.ordinal:()I
        78: iconst_5
        79: iastore
        80: goto          84
        83: astore_0
        84: getstatic     #2                  // Field $SwitchMap$com$fasterxml$jackson$annotation$PropertyAccessor:[I
        87: getstatic     #10                 // Field com/fasterxml/jackson/annotation/PropertyAccessor.ALL:Lcom/fasterxml/jackson/annotation/PropertyAccessor;
        90: invokevirtual #4                  // Method com/fasterxml/jackson/annotation/PropertyAccessor.ordinal:()I
        93: bipush        6
        95: iastore
        96: goto          100
        99: astore_0
       100: return
      Exception table:
         from    to  target type
             9    20    23   Class java/lang/NoSuchFieldError
            24    35    38   Class java/lang/NoSuchFieldError
            39    50    53   Class java/lang/NoSuchFieldError
            54    65    68   Class java/lang/NoSuchFieldError
            69    80    83   Class java/lang/NoSuchFieldError
            84    96    99   Class java/lang/NoSuchFieldError
      LineNumberTable:
        line 336: 0
      LocalVariableTable:
        Start  Length  Slot  Name   Signature
      StackMapTable: number_of_entries = 12
        frame_type = 87 /* same_locals_1_stack_item */
          stack = [ class java/lang/NoSuchFieldError ]
        frame_type = 0 /* same */
        frame_type = 77 /* same_locals_1_stack_item */
          stack = [ class java/lang/NoSuchFieldError ]
        frame_type = 0 /* same */
        frame_type = 77 /* same_locals_1_stack_item */
          stack = [ class java/lang/NoSuchFieldError ]
        frame_type = 0 /* same */
        frame_type = 77 /* same_locals_1_stack_item */
          stack = [ class java/lang/NoSuchFieldError ]
        frame_type = 0 /* same */
        frame_type = 77 /* same_locals_1_stack_item */
          stack = [ class java/lang/NoSuchFieldError ]
        frame_type = 0 /* same */
        frame_type = 78 /* same_locals_1_stack_item */
          stack = [ class java/lang/NoSuchFieldError ]
        frame_type = 0 /* same */
}
SourceFile: "VisibilityChecker.java"
EnclosingMethod: #25.#0                 // com.fasterxml.jackson.databind.introspect.VisibilityChecker
InnerClasses:
  static #11;                             // class com/fasterxml/jackson/databind/introspect/VisibilityChecker$1
