Classfile /Users/mw/Projects/slang-braindump/.jar/jar8/assemble/slang-braindump/assemble/content/coursier/util/PlatformSyncCompanion.class
  Last modified May 29, 2022; size 1477 bytes
  SHA-256 checksum 1911627d3ed525dd91bee0dfd3fd453ebfc53c63d60c1ec4450a362b29150b25
  Compiled from "PlatformSyncCompanion.scala"
public abstract class coursier.util.PlatformSyncCompanion
  minor version: 0
  major version: 52
  flags: (0x0421) ACC_PUBLIC, ACC_SUPER, ACC_ABSTRACT
  this_class: #2                          // coursier/util/PlatformSyncCompanion
  super_class: #4                         // java/lang/Object
  interfaces: 0, fields: 0, methods: 3, attributes: 4
Constant pool:
   #1 = Utf8               coursier/util/PlatformSyncCompanion
   #2 = Class              #1             // coursier/util/PlatformSyncCompanion
   #3 = Utf8               java/lang/Object
   #4 = Class              #3             // java/lang/Object
   #5 = Utf8               PlatformSyncCompanion.scala
   #6 = Utf8               Lscala/reflect/ScalaSignature;
   #7 = Utf8               bytes
   #8 = Utf8               \u0006\u0005i2Q\u0001B\u0003\u0002\u0002)AQ!\u0005\u0001\u0005\u0002IAa!\u0006\u0001\u0005\u0002\u001d1\u0002BB\u0013\u0001\t\u00039aEA\u000bQY\u0006$hm\u001c:n\'ft7mQ8na\u0006t\u0017n\u001c8\u000b\u0005\u00199\u0011\u0001B;uS2T\u0011\u0001C\u0001\tG>,(o]5fe\u000e\u00011C\u0001\u0001\f!\taq\"D\u0001\u000e\u0015\u0005q\u0011!B:dC2\f\u0017B\u0001\t\u000e\u0005\u0019\te.\u001f*fM\u00061A(\u001b8jiz\"\u0012a\u0005\t\u0003)\u0001i\u0011!B\u0001\u0010M&DX\r\u001a+ie\u0016\fG\rU8pYR\u0011q\u0003\t\t\u00031yi\u0011!\u0007\u0006\u00035m\t!bY8oGV\u0014(/\u001a8u\u0015\t1ADC\u0001\u001e\u0003\u0011Q\u0017M^1\n\u0005}I\"aD#yK\u000e,Ho\u001c:TKJ4\u0018nY3\t\u000b\u0005\u0012\u0001\u0019\u0001\u0012\u0002\tML\'0\u001a\t\u0003\u0019\rJ!\u0001J\u0007\u0003\u0007%sG/A\nxSRDg)\u001b=fIRC\'/Z1e!>|G.\u0006\u0002(WQ\u0011\u0001&\u000f\u000b\u0003SQ\u0002\"AK\u0016\r\u0001\u0011)Af\u0001b\u0001[\t\tA+\u0005\u0002/cA\u0011AbL\u0005\u0003a5\u0011qAT8uQ&tw\r\u0005\u0002\re%\u00111\'\u0004\u0002\u0004\u0003:L\b\"B\u001b\u0004\u0001\u00041\u0014!\u00014\u0011\t19t#K\u0005\u0003q5\u0011\u0011BR;oGRLwN\\\u0019\t\u000b\u0005\u001a\u0001\u0019\u0001\u0012
   #9 = Utf8               fixedThreadPool
  #10 = Utf8               (I)Ljava/util/concurrent/ExecutorService;
  #11 = Utf8               size
  #12 = Utf8               coursier/cache/internal/ThreadUtil$
  #13 = Class              #12            // coursier/cache/internal/ThreadUtil$
  #14 = Utf8               MODULE$
  #15 = Utf8               Lcoursier/cache/internal/ThreadUtil$;
  #16 = NameAndType        #14:#15        // MODULE$:Lcoursier/cache/internal/ThreadUtil$;
  #17 = Fieldref           #13.#16        // coursier/cache/internal/ThreadUtil$.MODULE$:Lcoursier/cache/internal/ThreadUtil$;
  #18 = NameAndType        #9:#10         // fixedThreadPool:(I)Ljava/util/concurrent/ExecutorService;
  #19 = Methodref          #13.#18        // coursier/cache/internal/ThreadUtil$.fixedThreadPool:(I)Ljava/util/concurrent/ExecutorService;
  #20 = Utf8               this
  #21 = Utf8               Lcoursier/util/PlatformSyncCompanion;
  #22 = Utf8               I
  #23 = Utf8               withFixedThreadPool
  #24 = Utf8               (ILscala/Function1;)Ljava/lang/Object;
  #25 = Utf8               <T:Ljava/lang/Object;>(ILscala/Function1<Ljava/util/concurrent/ExecutorService;TT;>;)TT;
  #26 = Utf8               f
  #27 = NameAndType        #23:#24        // withFixedThreadPool:(ILscala/Function1;)Ljava/lang/Object;
  #28 = Methodref          #13.#27        // coursier/cache/internal/ThreadUtil$.withFixedThreadPool:(ILscala/Function1;)Ljava/lang/Object;
  #29 = Utf8               Lscala/Function1;
  #30 = Utf8               <init>
  #31 = Utf8               ()V
  #32 = NameAndType        #30:#31        // "<init>":()V
  #33 = Methodref          #4.#32         // java/lang/Object."<init>":()V
  #34 = Utf8               Code
  #35 = Utf8               LineNumberTable
  #36 = Utf8               LocalVariableTable
  #37 = Utf8               MethodParameters
  #38 = Utf8               Signature
  #39 = Utf8               SourceFile
  #40 = Utf8               RuntimeVisibleAnnotations
  #41 = Utf8               ScalaInlineInfo
  #42 = Utf8               ScalaSig
{
  public java.util.concurrent.ExecutorService fixedThreadPool(int);
    descriptor: (I)Ljava/util/concurrent/ExecutorService;
    flags: (0x0001) ACC_PUBLIC
    Code:
      stack=2, locals=2, args_size=2
         0: getstatic     #17                 // Field coursier/cache/internal/ThreadUtil$.MODULE$:Lcoursier/cache/internal/ThreadUtil$;
         3: iload_1
         4: invokevirtual #19                 // Method coursier/cache/internal/ThreadUtil$.fixedThreadPool:(I)Ljava/util/concurrent/ExecutorService;
         7: areturn
      LineNumberTable:
        line 10: 0
      LocalVariableTable:
        Start  Length  Slot  Name   Signature
            0       8     0  this   Lcoursier/util/PlatformSyncCompanion;
            0       8     1  size   I
    MethodParameters:
      Name                           Flags
      size                           final

  public <T extends java.lang.Object> T withFixedThreadPool(int, scala.Function1<java.util.concurrent.ExecutorService, T>);
    descriptor: (ILscala/Function1;)Ljava/lang/Object;
    flags: (0x0001) ACC_PUBLIC
    Code:
      stack=3, locals=3, args_size=3
         0: getstatic     #17                 // Field coursier/cache/internal/ThreadUtil$.MODULE$:Lcoursier/cache/internal/ThreadUtil$;
         3: iload_1
         4: aload_2
         5: invokevirtual #28                 // Method coursier/cache/internal/ThreadUtil$.withFixedThreadPool:(ILscala/Function1;)Ljava/lang/Object;
         8: areturn
      LineNumberTable:
        line 13: 0
      LocalVariableTable:
        Start  Length  Slot  Name   Signature
            0       9     0  this   Lcoursier/util/PlatformSyncCompanion;
            0       9     1  size   I
            0       9     2     f   Lscala/Function1;
    Signature: #25                          // <T:Ljava/lang/Object;>(ILscala/Function1<Ljava/util/concurrent/ExecutorService;TT;>;)TT;
    MethodParameters:
      Name                           Flags
      size                           final
      f                              final

  public coursier.util.PlatformSyncCompanion();
    descriptor: ()V
    flags: (0x0001) ACC_PUBLIC
    Code:
      stack=1, locals=1, args_size=1
         0: aload_0
         1: invokespecial #33                 // Method java/lang/Object."<init>":()V
         4: return
      LineNumberTable:
        line 15: 0
        line 7: 4
      LocalVariableTable:
        Start  Length  Slot  Name   Signature
            0       5     0  this   Lcoursier/util/PlatformSyncCompanion;
}
SourceFile: "PlatformSyncCompanion.scala"
RuntimeVisibleAnnotations:
  0: #6(#7=s#8)
    scala.reflect.ScalaSignature(
      bytes="\u0006\u0005i2Q\u0001B\u0003\u0002\u0002)AQ!\u0005\u0001\u0005\u0002IAa!\u0006\u0001\u0005\u0002\u001d1\u0002BB\u0013\u0001\t\u00039aEA\u000bQY\u0006$hm\u001c:n\'ft7mQ8na\u0006t\u0017n\u001c8\u000b\u0005\u00199\u0011\u0001B;uS2T\u0011\u0001C\u0001\tG>,(o]5fe\u000e\u00011C\u0001\u0001\f!\taq\"D\u0001\u000e\u0015\u0005q\u0011!B:dC2\f\u0017B\u0001\t\u000e\u0005\u0019\te.\u001f*fM\u00061A(\u001b8jiz\"\u0012a\u0005\t\u0003)\u0001i\u0011!B\u0001\u0010M&DX\r\u001a+ie\u0016\fG\rU8pYR\u0011q\u0003\t\t\u00031yi\u0011!\u0007\u0006\u00035m\t!bY8oGV\u0014(/\u001a8u\u0015\t1ADC\u0001\u001e\u0003\u0011Q\u0017M^1\n\u0005}I\"aD#yK\u000e,Ho\u001c:TKJ4\u0018nY3\t\u000b\u0005\u0012\u0001\u0019\u0001\u0012\u0002\tML\'0\u001a\t\u0003\u0019\rJ!\u0001J\u0007\u0003\u0007%sG/A\nxSRDg)\u001b=fIRC\'/Z1e!>|G.\u0006\u0002(WQ\u0011\u0001&\u000f\u000b\u0003SQ\u0002\"AK\u0016\r\u0001\u0011)Af\u0001b\u0001[\t\tA+\u0005\u0002/cA\u0011AbL\u0005\u0003a5\u0011qAT8uQ&tw\r\u0005\u0002\re%\u00111\'\u0004\u0002\u0004\u0003:L\b\"B\u001b\u0004\u0001\u00041\u0014!\u00014\u0011\t19t#K\u0005\u0003q5\u0011\u0011BR;oGRLwN\\\u0019\t\u000b\u0005\u001a\u0001\u0019\u0001\u0012"
    )
  ScalaInlineInfo: length = 0x13 (unknown attribute)
   01 00 00 03 00 1E 00 1F 00 00 09 00 0A 00 00 17
   00 18 00
  ScalaSig: length = 0x3 (unknown attribute)
   05 02 00
