Classfile /Users/mw/Projects/slang-braindump/.jar/jar8/assemble/slang-braindump/assemble/content/coursier/util/Print$Colors.class
  Last modified May 29, 2022; size 4024 bytes
  SHA-256 checksum 817ba334134f2183357086c3953645af4ed756b3407caed90c384043ebf1eb2e
  Compiled from "Print.scala"
public final class coursier.util.Print$Colors implements scala.Product,java.io.Serializable
  minor version: 0
  major version: 52
  flags: (0x0031) ACC_PUBLIC, ACC_FINAL, ACC_SUPER
  this_class: #2                          // coursier/util/Print$Colors
  super_class: #4                         // java/lang/Object
  interfaces: 2, fields: 3, methods: 18, attributes: 4
Constant pool:
    #1 = Utf8               coursier/util/Print$Colors
    #2 = Class              #1            // coursier/util/Print$Colors
    #3 = Utf8               java/lang/Object
    #4 = Class              #3            // java/lang/Object
    #5 = Utf8               scala/Product
    #6 = Class              #5            // scala/Product
    #7 = Utf8               java/io/Serializable
    #8 = Class              #7            // java/io/Serializable
    #9 = Utf8               Print.scala
   #10 = Utf8               coursier/util/Print
   #11 = Class              #10           // coursier/util/Print
   #12 = Utf8               Colors
   #13 = Utf8               red
   #14 = Utf8               Ljava/lang/String;
   #15 = Utf8               yellow
   #16 = Utf8               reset
   #17 = Utf8               productIterator
   #18 = Utf8               ()Lscala/collection/Iterator;
   #19 = Utf8               ()Lscala/collection/Iterator<Ljava/lang/Object;>;
   #20 = Utf8               productIterator$
   #21 = Utf8               (Lscala/Product;)Lscala/collection/Iterator;
   #22 = NameAndType        #20:#21       // productIterator$:(Lscala/Product;)Lscala/collection/Iterator;
   #23 = InterfaceMethodref #6.#22        // scala/Product.productIterator$:(Lscala/Product;)Lscala/collection/Iterator;
   #24 = Utf8               this
   #25 = Utf8               Lcoursier/util/Print$Colors;
   #26 = Utf8               productElementNames
   #27 = Utf8               ()Lscala/collection/Iterator<Ljava/lang/String;>;
   #28 = Utf8               productElementNames$
   #29 = NameAndType        #28:#21       // productElementNames$:(Lscala/Product;)Lscala/collection/Iterator;
   #30 = InterfaceMethodref #6.#29        // scala/Product.productElementNames$:(Lscala/Product;)Lscala/collection/Iterator;
   #31 = Utf8               ()Ljava/lang/String;
   #32 = NameAndType        #13:#14       // red:Ljava/lang/String;
   #33 = Fieldref           #2.#32        // coursier/util/Print$Colors.red:Ljava/lang/String;
   #34 = NameAndType        #15:#14       // yellow:Ljava/lang/String;
   #35 = Fieldref           #2.#34        // coursier/util/Print$Colors.yellow:Ljava/lang/String;
   #36 = NameAndType        #16:#14       // reset:Ljava/lang/String;
   #37 = Fieldref           #2.#36        // coursier/util/Print$Colors.reset:Ljava/lang/String;
   #38 = Utf8               withRed
   #39 = Utf8               (Ljava/lang/String;)Lcoursier/util/Print$Colors;
   #40 = NameAndType        #15:#31       // yellow:()Ljava/lang/String;
   #41 = Methodref          #2.#40        // coursier/util/Print$Colors.yellow:()Ljava/lang/String;
   #42 = NameAndType        #16:#31       // reset:()Ljava/lang/String;
   #43 = Methodref          #2.#42        // coursier/util/Print$Colors.reset:()Ljava/lang/String;
   #44 = Utf8               <init>
   #45 = Utf8               (Ljava/lang/String;Ljava/lang/String;Ljava/lang/String;)V
   #46 = NameAndType        #44:#45       // "<init>":(Ljava/lang/String;Ljava/lang/String;Ljava/lang/String;)V
   #47 = Methodref          #2.#46        // coursier/util/Print$Colors."<init>":(Ljava/lang/String;Ljava/lang/String;Ljava/lang/String;)V
   #48 = Utf8               withYellow
   #49 = NameAndType        #13:#31       // red:()Ljava/lang/String;
   #50 = Methodref          #2.#49        // coursier/util/Print$Colors.red:()Ljava/lang/String;
   #51 = Utf8               withReset
   #52 = Utf8               toString
   #53 = Utf8               java/lang/StringBuilder
   #54 = Class              #53           // java/lang/StringBuilder
   #55 = Utf8               Colors(
   #56 = String             #55           // Colors(
   #57 = Utf8               (Ljava/lang/String;)V
   #58 = NameAndType        #44:#57       // "<init>":(Ljava/lang/String;)V
   #59 = Methodref          #54.#58       // java/lang/StringBuilder."<init>":(Ljava/lang/String;)V
   #60 = Utf8               java/lang/String
   #61 = Class              #60           // java/lang/String
   #62 = Utf8               valueOf
   #63 = Utf8               (Ljava/lang/Object;)Ljava/lang/String;
   #64 = NameAndType        #62:#63       // valueOf:(Ljava/lang/Object;)Ljava/lang/String;
   #65 = Methodref          #61.#64       // java/lang/String.valueOf:(Ljava/lang/Object;)Ljava/lang/String;
   #66 = Utf8               append
   #67 = Utf8               (Ljava/lang/String;)Ljava/lang/StringBuilder;
   #68 = NameAndType        #66:#67       // append:(Ljava/lang/String;)Ljava/lang/StringBuilder;
   #69 = Methodref          #54.#68       // java/lang/StringBuilder.append:(Ljava/lang/String;)Ljava/lang/StringBuilder;
   #70 = Utf8               ,
   #71 = String             #70           // ,
   #72 = Utf8               )
   #73 = String             #72           // )
   #74 = NameAndType        #52:#31       // toString:()Ljava/lang/String;
   #75 = Methodref          #54.#74       // java/lang/StringBuilder.toString:()Ljava/lang/String;
   #76 = Utf8               b
   #77 = Utf8               Ljava/lang/StringBuilder;
   #78 = Utf8               canEqual
   #79 = Utf8               (Ljava/lang/Object;)Z
   #80 = Utf8               obj
   #81 = Utf8               Ljava/lang/Object;
   #82 = Utf8               equals
   #83 = NameAndType        #78:#79       // canEqual:(Ljava/lang/Object;)Z
   #84 = Methodref          #2.#83        // coursier/util/Print$Colors.canEqual:(Ljava/lang/Object;)Z
   #85 = NameAndType        #82:#79       // equals:(Ljava/lang/Object;)Z
   #86 = Methodref          #4.#85        // java/lang/Object.equals:(Ljava/lang/Object;)Z
   #87 = Utf8               other
   #88 = Utf8               hashCode
   #89 = Utf8               ()I
   #90 = String             #12           // Colors
   #91 = Utf8               scala/runtime/Statics
   #92 = Class              #91           // scala/runtime/Statics
   #93 = Utf8               anyHash
   #94 = Utf8               (Ljava/lang/Object;)I
   #95 = NameAndType        #93:#94       // anyHash:(Ljava/lang/Object;)I
   #96 = Methodref          #92.#95       // scala/runtime/Statics.anyHash:(Ljava/lang/Object;)I
   #97 = Utf8               code
   #98 = Utf8               I
   #99 = Utf8               tuple
  #100 = Utf8               ()Lscala/Tuple3;
  #101 = Utf8               ()Lscala/Tuple3<Ljava/lang/String;Ljava/lang/String;Ljava/lang/String;>;
  #102 = Utf8               scala/Tuple3
  #103 = Class              #102          // scala/Tuple3
  #104 = Utf8               (Ljava/lang/Object;Ljava/lang/Object;Ljava/lang/Object;)V
  #105 = NameAndType        #44:#104      // "<init>":(Ljava/lang/Object;Ljava/lang/Object;Ljava/lang/Object;)V
  #106 = Methodref          #103.#105     // scala/Tuple3."<init>":(Ljava/lang/Object;Ljava/lang/Object;Ljava/lang/Object;)V
  #107 = Utf8               productPrefix
  #108 = Utf8               productArity
  #109 = Utf8               productElement
  #110 = Utf8               (I)Ljava/lang/Object;
  #111 = Utf8               n
  #112 = Utf8               java/lang/IndexOutOfBoundsException
  #113 = Class              #112          // java/lang/IndexOutOfBoundsException
  #114 = Utf8               scala/runtime/BoxesRunTime
  #115 = Class              #114          // scala/runtime/BoxesRunTime
  #116 = Utf8               boxToInteger
  #117 = Utf8               (I)Ljava/lang/Integer;
  #118 = NameAndType        #116:#117     // boxToInteger:(I)Ljava/lang/Integer;
  #119 = Methodref          #115.#118     // scala/runtime/BoxesRunTime.boxToInteger:(I)Ljava/lang/Integer;
  #120 = Methodref          #4.#74        // java/lang/Object.toString:()Ljava/lang/String;
  #121 = Methodref          #113.#58      // java/lang/IndexOutOfBoundsException."<init>":(Ljava/lang/String;)V
  #122 = Utf8               productElementName
  #123 = Utf8               (I)Ljava/lang/String;
  #124 = String             #13           // red
  #125 = String             #15           // yellow
  #126 = String             #16           // reset
  #127 = Utf8               ()V
  #128 = NameAndType        #44:#127      // "<init>":()V
  #129 = Methodref          #4.#128       // java/lang/Object."<init>":()V
  #130 = Utf8               $init$
  #131 = Utf8               (Lscala/Product;)V
  #132 = NameAndType        #130:#131     // $init$:(Lscala/Product;)V
  #133 = InterfaceMethodref #6.#132       // scala/Product.$init$:(Lscala/Product;)V
  #134 = Utf8               Code
  #135 = Utf8               LineNumberTable
  #136 = Utf8               LocalVariableTable
  #137 = Utf8               Signature
  #138 = Utf8               MethodParameters
  #139 = Utf8               StackMapTable
  #140 = Utf8               InnerClasses
  #141 = Utf8               SourceFile
  #142 = Utf8               ScalaInlineInfo
  #143 = Utf8               Scala
{
  private final java.lang.String red;
    descriptor: Ljava/lang/String;
    flags: (0x0012) ACC_PRIVATE, ACC_FINAL

  private final java.lang.String yellow;
    descriptor: Ljava/lang/String;
    flags: (0x0012) ACC_PRIVATE, ACC_FINAL

  private final java.lang.String reset;
    descriptor: Ljava/lang/String;
    flags: (0x0012) ACC_PRIVATE, ACC_FINAL

  public scala.collection.Iterator<java.lang.Object> productIterator();
    descriptor: ()Lscala/collection/Iterator;
    flags: (0x0001) ACC_PUBLIC
    Code:
      stack=1, locals=1, args_size=1
         0: aload_0
         1: invokestatic  #23                 // InterfaceMethod scala/Product.productIterator$:(Lscala/Product;)Lscala/collection/Iterator;
         4: areturn
      LineNumberTable:
        line 16: 0
      LocalVariableTable:
        Start  Length  Slot  Name   Signature
            0       5     0  this   Lcoursier/util/Print$Colors;
    Signature: #19                          // ()Lscala/collection/Iterator<Ljava/lang/Object;>;

  public scala.collection.Iterator<java.lang.String> productElementNames();
    descriptor: ()Lscala/collection/Iterator;
    flags: (0x0001) ACC_PUBLIC
    Code:
      stack=1, locals=1, args_size=1
         0: aload_0
         1: invokestatic  #30                 // InterfaceMethod scala/Product.productElementNames$:(Lscala/Product;)Lscala/collection/Iterator;
         4: areturn
      LineNumberTable:
        line 16: 0
      LocalVariableTable:
        Start  Length  Slot  Name   Signature
            0       5     0  this   Lcoursier/util/Print$Colors;
    Signature: #27                          // ()Lscala/collection/Iterator<Ljava/lang/String;>;

  public java.lang.String red();
    descriptor: ()Ljava/lang/String;
    flags: (0x0001) ACC_PUBLIC
    Code:
      stack=1, locals=1, args_size=1
         0: aload_0
         1: getfield      #33                 // Field red:Ljava/lang/String;
         4: areturn
      LineNumberTable:
        line 16: 0
      LocalVariableTable:
        Start  Length  Slot  Name   Signature
            0       5     0  this   Lcoursier/util/Print$Colors;

  public java.lang.String yellow();
    descriptor: ()Ljava/lang/String;
    flags: (0x0001) ACC_PUBLIC
    Code:
      stack=1, locals=1, args_size=1
         0: aload_0
         1: getfield      #35                 // Field yellow:Ljava/lang/String;
         4: areturn
      LineNumberTable:
        line 16: 0
      LocalVariableTable:
        Start  Length  Slot  Name   Signature
            0       5     0  this   Lcoursier/util/Print$Colors;

  public java.lang.String reset();
    descriptor: ()Ljava/lang/String;
    flags: (0x0001) ACC_PUBLIC
    Code:
      stack=1, locals=1, args_size=1
         0: aload_0
         1: getfield      #37                 // Field reset:Ljava/lang/String;
         4: areturn
      LineNumberTable:
        line 16: 0
      LocalVariableTable:
        Start  Length  Slot  Name   Signature
            0       5     0  this   Lcoursier/util/Print$Colors;

  public coursier.util.Print$Colors withRed(java.lang.String);
    descriptor: (Ljava/lang/String;)Lcoursier/util/Print$Colors;
    flags: (0x0001) ACC_PUBLIC
    Code:
      stack=5, locals=2, args_size=2
         0: new           #2                  // class coursier/util/Print$Colors
         3: dup
         4: aload_1
         5: aload_0
         6: invokevirtual #41                 // Method yellow:()Ljava/lang/String;
         9: aload_0
        10: invokevirtual #43                 // Method reset:()Ljava/lang/String;
        13: invokespecial #47                 // Method "<init>":(Ljava/lang/String;Ljava/lang/String;Ljava/lang/String;)V
        16: areturn
      LineNumberTable:
        line 16: 0
      LocalVariableTable:
        Start  Length  Slot  Name   Signature
            0      17     0  this   Lcoursier/util/Print$Colors;
            0      17     1   red   Ljava/lang/String;
    MethodParameters:
      Name                           Flags
      red                            final

  public coursier.util.Print$Colors withYellow(java.lang.String);
    descriptor: (Ljava/lang/String;)Lcoursier/util/Print$Colors;
    flags: (0x0001) ACC_PUBLIC
    Code:
      stack=5, locals=2, args_size=2
         0: new           #2                  // class coursier/util/Print$Colors
         3: dup
         4: aload_0
         5: invokevirtual #50                 // Method red:()Ljava/lang/String;
         8: aload_1
         9: aload_0
        10: invokevirtual #43                 // Method reset:()Ljava/lang/String;
        13: invokespecial #47                 // Method "<init>":(Ljava/lang/String;Ljava/lang/String;Ljava/lang/String;)V
        16: areturn
      LineNumberTable:
        line 16: 0
      LocalVariableTable:
        Start  Length  Slot  Name   Signature
            0      17     0  this   Lcoursier/util/Print$Colors;
            0      17     1 yellow   Ljava/lang/String;
    MethodParameters:
      Name                           Flags
      yellow                         final

  public coursier.util.Print$Colors withReset(java.lang.String);
    descriptor: (Ljava/lang/String;)Lcoursier/util/Print$Colors;
    flags: (0x0001) ACC_PUBLIC
    Code:
      stack=5, locals=2, args_size=2
         0: new           #2                  // class coursier/util/Print$Colors
         3: dup
         4: aload_0
         5: invokevirtual #50                 // Method red:()Ljava/lang/String;
         8: aload_0
         9: invokevirtual #41                 // Method yellow:()Ljava/lang/String;
        12: aload_1
        13: invokespecial #47                 // Method "<init>":(Ljava/lang/String;Ljava/lang/String;Ljava/lang/String;)V
        16: areturn
      LineNumberTable:
        line 16: 0
      LocalVariableTable:
        Start  Length  Slot  Name   Signature
            0      17     0  this   Lcoursier/util/Print$Colors;
            0      17     1 reset   Ljava/lang/String;
    MethodParameters:
      Name                           Flags
      reset                          final

  public java.lang.String toString();
    descriptor: ()Ljava/lang/String;
    flags: (0x0001) ACC_PUBLIC
    Code:
      stack=3, locals=2, args_size=1
         0: new           #54                 // class java/lang/StringBuilder
         3: dup
         4: ldc           #56                 // String Colors(
         6: invokespecial #59                 // Method java/lang/StringBuilder."<init>":(Ljava/lang/String;)V
         9: astore_1
        10: aload_1
        11: aload_0
        12: invokevirtual #50                 // Method red:()Ljava/lang/String;
        15: invokestatic  #65                 // Method java/lang/String.valueOf:(Ljava/lang/Object;)Ljava/lang/String;
        18: invokevirtual #69                 // Method java/lang/StringBuilder.append:(Ljava/lang/String;)Ljava/lang/StringBuilder;
        21: pop
        22: aload_1
        23: ldc           #71                 // String ,
        25: invokevirtual #69                 // Method java/lang/StringBuilder.append:(Ljava/lang/String;)Ljava/lang/StringBuilder;
        28: pop
        29: aload_1
        30: aload_0
        31: invokevirtual #41                 // Method yellow:()Ljava/lang/String;
        34: invokestatic  #65                 // Method java/lang/String.valueOf:(Ljava/lang/Object;)Ljava/lang/String;
        37: invokevirtual #69                 // Method java/lang/StringBuilder.append:(Ljava/lang/String;)Ljava/lang/StringBuilder;
        40: pop
        41: aload_1
        42: ldc           #71                 // String ,
        44: invokevirtual #69                 // Method java/lang/StringBuilder.append:(Ljava/lang/String;)Ljava/lang/StringBuilder;
        47: pop
        48: aload_1
        49: aload_0
        50: invokevirtual #43                 // Method reset:()Ljava/lang/String;
        53: invokestatic  #65                 // Method java/lang/String.valueOf:(Ljava/lang/Object;)Ljava/lang/String;
        56: invokevirtual #69                 // Method java/lang/StringBuilder.append:(Ljava/lang/String;)Ljava/lang/StringBuilder;
        59: pop
        60: aload_1
        61: ldc           #73                 // String )
        63: invokevirtual #69                 // Method java/lang/StringBuilder.append:(Ljava/lang/String;)Ljava/lang/StringBuilder;
        66: pop
        67: aload_1
        68: invokevirtual #75                 // Method java/lang/StringBuilder.toString:()Ljava/lang/String;
        71: areturn
      LineNumberTable:
        line 16: 0
      LocalVariableTable:
        Start  Length  Slot  Name   Signature
           10      61     1     b   Ljava/lang/StringBuilder;
            0      72     0  this   Lcoursier/util/Print$Colors;

  public boolean canEqual(java.lang.Object);
    descriptor: (Ljava/lang/Object;)Z
    flags: (0x0001) ACC_PUBLIC
    Code:
      stack=1, locals=2, args_size=2
         0: aload_1
         1: ifnull        15
         4: aload_1
         5: instanceof    #2                  // class coursier/util/Print$Colors
         8: ifeq          15
        11: iconst_1
        12: goto          16
        15: iconst_0
        16: ireturn
      StackMapTable: number_of_entries = 2
        frame_type = 15 /* same */
        frame_type = 64 /* same_locals_1_stack_item */
          stack = [ int ]
      LineNumberTable:
        line 16: 0
      LocalVariableTable:
        Start  Length  Slot  Name   Signature
            0      17     0  this   Lcoursier/util/Print$Colors;
            0      17     1   obj   Ljava/lang/Object;
    MethodParameters:
      Name                           Flags
      obj                            final

  public boolean equals(java.lang.Object);
    descriptor: (Ljava/lang/Object;)Z
    flags: (0x0001) ACC_PUBLIC
    Code:
      stack=2, locals=6, args_size=2
         0: aload_0
         1: aload_1
         2: if_acmpeq     120
         5: aload_0
         6: aload_1
         7: invokevirtual #84                 // Method canEqual:(Ljava/lang/Object;)Z
        10: ifeq          124
        13: aload_1
        14: checkcast     #2                  // class coursier/util/Print$Colors
        17: astore_2
        18: iconst_1
        19: ifeq          116
        22: aload_0
        23: invokevirtual #50                 // Method red:()Ljava/lang/String;
        26: aload_2
        27: invokevirtual #50                 // Method red:()Ljava/lang/String;
        30: astore_3
        31: dup
        32: ifnonnull     43
        35: pop
        36: aload_3
        37: ifnull        50
        40: goto          116
        43: aload_3
        44: invokevirtual #86                 // Method java/lang/Object.equals:(Ljava/lang/Object;)Z
        47: ifeq          116
        50: aload_0
        51: invokevirtual #41                 // Method yellow:()Ljava/lang/String;
        54: aload_2
        55: invokevirtual #41                 // Method yellow:()Ljava/lang/String;
        58: astore        4
        60: dup
        61: ifnonnull     73
        64: pop
        65: aload         4
        67: ifnull        81
        70: goto          116
        73: aload         4
        75: invokevirtual #86                 // Method java/lang/Object.equals:(Ljava/lang/Object;)Z
        78: ifeq          116
        81: aload_0
        82: invokevirtual #43                 // Method reset:()Ljava/lang/String;
        85: aload_2
        86: invokevirtual #43                 // Method reset:()Ljava/lang/String;
        89: astore        5
        91: dup
        92: ifnonnull     104
        95: pop
        96: aload         5
        98: ifnull        112
       101: goto          116
       104: aload         5
       106: invokevirtual #86                 // Method java/lang/Object.equals:(Ljava/lang/Object;)Z
       109: ifeq          116
       112: iconst_1
       113: goto          117
       116: iconst_0
       117: ifeq          124
       120: iconst_1
       121: goto          125
       124: iconst_0
       125: ireturn
      StackMapTable: number_of_entries = 11
        frame_type = 255 /* full_frame */
          offset_delta = 43
          locals = [ class coursier/util/Print$Colors, class java/lang/Object, class coursier/util/Print$Colors, class java/lang/String ]
          stack = [ class java/lang/String ]
        frame_type = 6 /* same */
        frame_type = 255 /* full_frame */
          offset_delta = 22
          locals = [ class coursier/util/Print$Colors, class java/lang/Object, class coursier/util/Print$Colors, class java/lang/String, class java/lang/String ]
          stack = [ class java/lang/String ]
        frame_type = 7 /* same */
        frame_type = 255 /* full_frame */
          offset_delta = 22
          locals = [ class coursier/util/Print$Colors, class java/lang/Object, class coursier/util/Print$Colors, class java/lang/String, class java/lang/String, class java/lang/String ]
          stack = [ class java/lang/String ]
        frame_type = 7 /* same */
        frame_type = 248 /* chop */
          offset_delta = 3
        frame_type = 64 /* same_locals_1_stack_item */
          stack = [ int ]
        frame_type = 250 /* chop */
          offset_delta = 2
        frame_type = 3 /* same */
        frame_type = 64 /* same_locals_1_stack_item */
          stack = [ int ]
      LineNumberTable:
        line 16: 0
      LocalVariableTable:
        Start  Length  Slot  Name   Signature
           18      99     2 other   Lcoursier/util/Print$Colors;
            0     126     0  this   Lcoursier/util/Print$Colors;
            0     126     1   obj   Ljava/lang/Object;
    MethodParameters:
      Name                           Flags
      obj                            final

  public int hashCode();
    descriptor: ()I
    flags: (0x0001) ACC_PUBLIC
    Code:
      stack=2, locals=2, args_size=1
         0: bipush        17
         2: ldc           #90                 // String Colors
         4: invokestatic  #96                 // Method scala/runtime/Statics.anyHash:(Ljava/lang/Object;)I
         7: iadd
         8: istore_1
         9: bipush        37
        11: iload_1
        12: imul
        13: aload_0
        14: invokevirtual #50                 // Method red:()Ljava/lang/String;
        17: invokestatic  #96                 // Method scala/runtime/Statics.anyHash:(Ljava/lang/Object;)I
        20: iadd
        21: istore_1
        22: bipush        37
        24: iload_1
        25: imul
        26: aload_0
        27: invokevirtual #41                 // Method yellow:()Ljava/lang/String;
        30: invokestatic  #96                 // Method scala/runtime/Statics.anyHash:(Ljava/lang/Object;)I
        33: iadd
        34: istore_1
        35: bipush        37
        37: iload_1
        38: imul
        39: aload_0
        40: invokevirtual #43                 // Method reset:()Ljava/lang/String;
        43: invokestatic  #96                 // Method scala/runtime/Statics.anyHash:(Ljava/lang/Object;)I
        46: iadd
        47: istore_1
        48: bipush        37
        50: iload_1
        51: imul
        52: ireturn
      LineNumberTable:
        line 16: 0
      LocalVariableTable:
        Start  Length  Slot  Name   Signature
            9      43     1  code   I
            0      53     0  this   Lcoursier/util/Print$Colors;

  private scala.Tuple3<java.lang.String, java.lang.String, java.lang.String> tuple();
    descriptor: ()Lscala/Tuple3;
    flags: (0x0002) ACC_PRIVATE
    Code:
      stack=5, locals=1, args_size=1
         0: new           #103                // class scala/Tuple3
         3: dup
         4: aload_0
         5: invokevirtual #50                 // Method red:()Ljava/lang/String;
         8: aload_0
         9: invokevirtual #41                 // Method yellow:()Ljava/lang/String;
        12: aload_0
        13: invokevirtual #43                 // Method reset:()Ljava/lang/String;
        16: invokespecial #106                // Method scala/Tuple3."<init>":(Ljava/lang/Object;Ljava/lang/Object;Ljava/lang/Object;)V
        19: areturn
      LineNumberTable:
        line 16: 0
      LocalVariableTable:
        Start  Length  Slot  Name   Signature
            0      20     0  this   Lcoursier/util/Print$Colors;
    Signature: #101                         // ()Lscala/Tuple3<Ljava/lang/String;Ljava/lang/String;Ljava/lang/String;>;

  public java.lang.String productPrefix();
    descriptor: ()Ljava/lang/String;
    flags: (0x0001) ACC_PUBLIC
    Code:
      stack=1, locals=1, args_size=1
         0: ldc           #90                 // String Colors
         2: areturn
      LineNumberTable:
        line 16: 0
      LocalVariableTable:
        Start  Length  Slot  Name   Signature
            0       3     0  this   Lcoursier/util/Print$Colors;

  public int productArity();
    descriptor: ()I
    flags: (0x0001) ACC_PUBLIC
    Code:
      stack=1, locals=1, args_size=1
         0: iconst_3
         1: ireturn
      LineNumberTable:
        line 16: 0
      LocalVariableTable:
        Start  Length  Slot  Name   Signature
            0       2     0  this   Lcoursier/util/Print$Colors;

  public java.lang.Object productElement(int);
    descriptor: (I)Ljava/lang/Object;
    flags: (0x0001) ACC_PUBLIC
    Code:
      stack=3, locals=3, args_size=2
         0: iload_1
         1: istore_2
         2: iload_2
         3: tableswitch   { // 0 to 2
                       0: 28
                       1: 35
                       2: 42
                 default: 49
            }
        28: aload_0
        29: invokevirtual #50                 // Method red:()Ljava/lang/String;
        32: goto          64
        35: aload_0
        36: invokevirtual #41                 // Method yellow:()Ljava/lang/String;
        39: goto          64
        42: aload_0
        43: invokevirtual #43                 // Method reset:()Ljava/lang/String;
        46: goto          64
        49: new           #113                // class java/lang/IndexOutOfBoundsException
        52: dup
        53: iload_2
        54: invokestatic  #119                // Method scala/runtime/BoxesRunTime.boxToInteger:(I)Ljava/lang/Integer;
        57: invokevirtual #120                // Method java/lang/Object.toString:()Ljava/lang/String;
        60: invokespecial #121                // Method java/lang/IndexOutOfBoundsException."<init>":(Ljava/lang/String;)V
        63: athrow
        64: areturn
      StackMapTable: number_of_entries = 5
        frame_type = 252 /* append */
          offset_delta = 28
          locals = [ int ]
        frame_type = 6 /* same */
        frame_type = 6 /* same */
        frame_type = 6 /* same */
        frame_type = 78 /* same_locals_1_stack_item */
          stack = [ class java/lang/String ]
      LineNumberTable:
        line 16: 0
      LocalVariableTable:
        Start  Length  Slot  Name   Signature
            0      65     0  this   Lcoursier/util/Print$Colors;
            0      65     1     n   I
    MethodParameters:
      Name                           Flags
      n                              final

  public java.lang.String productElementName(int);
    descriptor: (I)Ljava/lang/String;
    flags: (0x0001) ACC_PUBLIC
    Code:
      stack=3, locals=3, args_size=2
         0: iload_1
         1: istore_2
         2: iload_2
         3: tableswitch   { // 0 to 2
                       0: 28
                       1: 33
                       2: 38
                 default: 43
            }
        28: ldc           #124                // String red
        30: goto          58
        33: ldc           #125                // String yellow
        35: goto          58
        38: ldc           #126                // String reset
        40: goto          58
        43: new           #113                // class java/lang/IndexOutOfBoundsException
        46: dup
        47: iload_2
        48: invokestatic  #119                // Method scala/runtime/BoxesRunTime.boxToInteger:(I)Ljava/lang/Integer;
        51: invokevirtual #120                // Method java/lang/Object.toString:()Ljava/lang/String;
        54: invokespecial #121                // Method java/lang/IndexOutOfBoundsException."<init>":(Ljava/lang/String;)V
        57: athrow
        58: areturn
      StackMapTable: number_of_entries = 5
        frame_type = 252 /* append */
          offset_delta = 28
          locals = [ int ]
        frame_type = 4 /* same */
        frame_type = 4 /* same */
        frame_type = 4 /* same */
        frame_type = 78 /* same_locals_1_stack_item */
          stack = [ class java/lang/String ]
      LineNumberTable:
        line 16: 0
      LocalVariableTable:
        Start  Length  Slot  Name   Signature
            0      59     0  this   Lcoursier/util/Print$Colors;
            0      59     1     n   I
    MethodParameters:
      Name                           Flags
      n                              final

  public coursier.util.Print$Colors(java.lang.String, java.lang.String, java.lang.String);
    descriptor: (Ljava/lang/String;Ljava/lang/String;Ljava/lang/String;)V
    flags: (0x0001) ACC_PUBLIC
    Code:
      stack=2, locals=4, args_size=4
         0: aload_0
         1: aload_1
         2: putfield      #33                 // Field red:Ljava/lang/String;
         5: aload_0
         6: aload_2
         7: putfield      #35                 // Field yellow:Ljava/lang/String;
        10: aload_0
        11: aload_3
        12: putfield      #37                 // Field reset:Ljava/lang/String;
        15: aload_0
        16: invokespecial #129                // Method java/lang/Object."<init>":()V
        19: aload_0
        20: invokestatic  #133                // InterfaceMethod scala/Product.$init$:(Lscala/Product;)V
        23: return
      LineNumberTable:
        line 16: 0
        line 18: 15
        line 16: 23
      LocalVariableTable:
        Start  Length  Slot  Name   Signature
            0      24     0  this   Lcoursier/util/Print$Colors;
            0      24     1   red   Ljava/lang/String;
            0      24     2 yellow   Ljava/lang/String;
            0      24     3 reset   Ljava/lang/String;
    MethodParameters:
      Name                           Flags
      red                            final
      yellow                         final
      reset                          final
}
InnerClasses:
  public static final #12= #2 of #11;     // Colors=class coursier/util/Print$Colors of class coursier/util/Print
SourceFile: "Print.scala"
  ScalaInlineInfo: length = 0x5E (unknown attribute)
   01 01 00 12 00 2C 00 2D 01 00 4E 00 4F 01 00 52
   00 4F 01 00 58 00 59 01 00 6C 00 59 01 00 6D 00
   6E 01 00 7A 00 7B 01 00 1A 00 12 01 00 11 00 12
   01 00 6B 00 1F 01 00 0D 00 1F 01 00 10 00 1F 01
   00 34 00 1F 01 00 63 00 64 01 00 26 00 27 01 00
   33 00 27 01 00 30 00 27 01 00 0F 00 1F 01
  Scala: length = 0x0 (unknown attribute)

