Classfile /Users/mw/Projects/slang-braindump/.jar/jar8/assemble/slang-braindump/assemble/content/coursier/util/Properties.class
  Last modified May 29, 2022; size 721 bytes
  SHA-256 checksum 4c3ea9a25a01c39705d831fc2a029bc143bfae69b50d3d429c1c627a0a0a17d4
  Compiled from "Properties.scala"
public final class coursier.util.Properties
  minor version: 0
  major version: 52
  flags: (0x0031) ACC_PUBLIC, ACC_FINAL, ACC_SUPER
  this_class: #2                          // coursier/util/Properties
  super_class: #4                         // java/lang/Object
  interfaces: 0, fields: 0, methods: 2, attributes: 3
Constant pool:
   #1 = Utf8               coursier/util/Properties
   #2 = Class              #1             // coursier/util/Properties
   #3 = Utf8               java/lang/Object
   #4 = Class              #3             // java/lang/Object
   #5 = Utf8               Properties.scala
   #6 = Utf8               Lscala/reflect/ScalaSignature;
   #7 = Utf8               bytes
   #8 = Utf8               \u0006\u0005%:QAB\u0004\t\u000211QAD\u0004\t\u0002=AQAF\u0001\u0005\u0002]A\u0001\u0002G\u0001\t\u0006\u0004%I!\u0007\u0005\tA\u0005A)\u0019!C\u0001C!A\u0001&\u0001EC\u0002\u0013\u0005\u0011%\u0001\u0006Qe>\u0004XM\u001d;jKNT!\u0001C\u0005\u0002\tU$\u0018\u000e\u001c\u0006\u0002\u0015\u0005A1m\\;sg&,\'o\u0001\u0001\u0011\u00055\tQ\"A\u0004\u0003\u0015A\u0013x\u000e]3si&,7o\u0005\u0002\u0002!A\u0011\u0011\u0003F\u0007\u0002%)\t1#A\u0003tG\u0006d\u0017-\u0003\u0002\u0016%\t1\u0011I\\=SK\u001a\fa\u0001P5oSRtD#\u0001\u0007\u0002\u000bA\u0014x\u000e]:\u0016\u0003i\u0001\"aG\u0010\u000e\u0003qQ!\u0001C\u000f\u000b\u0003y\tAA[1wC&\u0011a\u0002H\u0001\bm\u0016\u00148/[8o+\u0005\u0011\u0003CA\u0012\'\u001b\u0005!#BA\u0013\u001e\u0003\u0011a\u0017M\\4\n\u0005\u001d\"#AB*ue&tw-\u0001\u0006d_6l\u0017\u000e\u001e%bg\"\u0004
   #9 = Utf8               commitHash
  #10 = Utf8               ()Ljava/lang/String;
  #11 = Utf8               coursier/util/Properties$
  #12 = Class              #11            // coursier/util/Properties$
  #13 = Utf8               MODULE$
  #14 = Utf8               Lcoursier/util/Properties$;
  #15 = NameAndType        #13:#14        // MODULE$:Lcoursier/util/Properties$;
  #16 = Fieldref           #12.#15        // coursier/util/Properties$.MODULE$:Lcoursier/util/Properties$;
  #17 = NameAndType        #9:#10         // commitHash:()Ljava/lang/String;
  #18 = Methodref          #12.#17        // coursier/util/Properties$.commitHash:()Ljava/lang/String;
  #19 = Utf8               version
  #20 = NameAndType        #19:#10        // version:()Ljava/lang/String;
  #21 = Methodref          #12.#20        // coursier/util/Properties$.version:()Ljava/lang/String;
  #22 = Utf8               Code
  #23 = Utf8               SourceFile
  #24 = Utf8               RuntimeVisibleAnnotations
  #25 = Utf8               ScalaSig
{
  public static java.lang.String commitHash();
    descriptor: ()Ljava/lang/String;
    flags: (0x0009) ACC_PUBLIC, ACC_STATIC
    Code:
      stack=1, locals=0, args_size=0
         0: getstatic     #16                 // Field coursier/util/Properties$.MODULE$:Lcoursier/util/Properties$;
         3: invokevirtual #18                 // Method coursier/util/Properties$.commitHash:()Ljava/lang/String;
         6: areturn

  public static java.lang.String version();
    descriptor: ()Ljava/lang/String;
    flags: (0x0009) ACC_PUBLIC, ACC_STATIC
    Code:
      stack=1, locals=0, args_size=0
         0: getstatic     #16                 // Field coursier/util/Properties$.MODULE$:Lcoursier/util/Properties$;
         3: invokevirtual #21                 // Method coursier/util/Properties$.version:()Ljava/lang/String;
         6: areturn
}
SourceFile: "Properties.scala"
RuntimeVisibleAnnotations:
  0: #6(#7=s#8)
    scala.reflect.ScalaSignature(
      bytes="\u0006\u0005%:QAB\u0004\t\u000211QAD\u0004\t\u0002=AQAF\u0001\u0005\u0002]A\u0001\u0002G\u0001\t\u0006\u0004%I!\u0007\u0005\tA\u0005A)\u0019!C\u0001C!A\u0001&\u0001EC\u0002\u0013\u0005\u0011%\u0001\u0006Qe>\u0004XM\u001d;jKNT!\u0001C\u0005\u0002\tU$\u0018\u000e\u001c\u0006\u0002\u0015\u0005A1m\\;sg&,\'o\u0001\u0001\u0011\u00055\tQ\"A\u0004\u0003\u0015A\u0013x\u000e]3si&,7o\u0005\u0002\u0002!A\u0011\u0011\u0003F\u0007\u0002%)\t1#A\u0003tG\u0006d\u0017-\u0003\u0002\u0016%\t1\u0011I\\=SK\u001a\fa\u0001P5oSRtD#\u0001\u0007\u0002\u000bA\u0014x\u000e]:\u0016\u0003i\u0001\"aG\u0010\u000e\u0003qQ!\u0001C\u000f\u000b\u0003y\tAA[1wC&\u0011a\u0002H\u0001\bm\u0016\u00148/[8o+\u0005\u0011\u0003CA\u0012\'\u001b\u0005!#BA\u0013\u001e\u0003\u0011a\u0017M\\4\n\u0005\u001d\"#AB*ue&tw-\u0001\u0006d_6l\u0017\u000e\u001e%bg\"\u0004"
    )
  ScalaSig: length = 0x3 (unknown attribute)
   05 02 00
