Classfile /Users/mw/Projects/slang-braindump/.jar/jar8/assemble/slang-braindump/assemble/content/coursier/util/Sync$.class
  Last modified May 29, 2022; size 924 bytes
  SHA-256 checksum 8afd9f8e0eff610d7009fab86432f10c84a50c42f633ef5f30e052a28acdd5df
  Compiled from "Sync.scala"
public final class coursier.util.Sync$ extends coursier.util.PlatformSyncCompanion implements java.io.Serializable
  minor version: 0
  major version: 52
  flags: (0x0031) ACC_PUBLIC, ACC_FINAL, ACC_SUPER
  this_class: #2                          // coursier/util/Sync$
  super_class: #4                         // coursier/util/PlatformSyncCompanion
  interfaces: 1, fields: 1, methods: 4, attributes: 3
Constant pool:
   #1 = Utf8               coursier/util/Sync$
   #2 = Class              #1             // coursier/util/Sync$
   #3 = Utf8               coursier/util/PlatformSyncCompanion
   #4 = Class              #3             // coursier/util/PlatformSyncCompanion
   #5 = Utf8               java/io/Serializable
   #6 = Class              #5             // java/io/Serializable
   #7 = Utf8               Sync.scala
   #8 = Utf8               MODULE$
   #9 = Utf8               Lcoursier/util/Sync$;
  #10 = Utf8               <clinit>
  #11 = Utf8               ()V
  #12 = Utf8               <init>
  #13 = NameAndType        #12:#11        // "<init>":()V
  #14 = Methodref          #2.#13         // coursier/util/Sync$."<init>":()V
  #15 = NameAndType        #8:#9          // MODULE$:Lcoursier/util/Sync$;
  #16 = Fieldref           #2.#15         // coursier/util/Sync$.MODULE$:Lcoursier/util/Sync$;
  #17 = Utf8               apply
  #18 = Utf8               (Lcoursier/util/Sync;)Lcoursier/util/Sync;
  #19 = Utf8               <F:Ljava/lang/Object;>(Lcoursier/util/Sync<TF;>;)Lcoursier/util/Sync<TF;>;
  #20 = Utf8               sync
  #21 = Utf8               this
  #22 = Utf8               Lcoursier/util/Sync;
  #23 = Utf8               writeReplace
  #24 = Utf8               ()Ljava/lang/Object;
  #25 = Utf8               scala/runtime/ModuleSerializationProxy
  #26 = Class              #25            // scala/runtime/ModuleSerializationProxy
  #27 = Utf8               (Ljava/lang/Class;)V
  #28 = NameAndType        #12:#27        // "<init>":(Ljava/lang/Class;)V
  #29 = Methodref          #26.#28        // scala/runtime/ModuleSerializationProxy."<init>":(Ljava/lang/Class;)V
  #30 = Methodref          #4.#13         // coursier/util/PlatformSyncCompanion."<init>":()V
  #31 = Utf8               Code
  #32 = Utf8               LineNumberTable
  #33 = Utf8               LocalVariableTable
  #34 = Utf8               Signature
  #35 = Utf8               MethodParameters
  #36 = Utf8               SourceFile
  #37 = Utf8               ScalaInlineInfo
  #38 = Utf8               Scala
{
  public static final coursier.util.Sync$ MODULE$;
    descriptor: Lcoursier/util/Sync$;
    flags: (0x0019) ACC_PUBLIC, ACC_STATIC, ACC_FINAL

  public static {};
    descriptor: ()V
    flags: (0x0009) ACC_PUBLIC, ACC_STATIC
    Code:
      stack=2, locals=0, args_size=0
         0: new           #2                  // class coursier/util/Sync$
         3: dup
         4: invokespecial #14                 // Method "<init>":()V
         7: putstatic     #16                 // Field MODULE$:Lcoursier/util/Sync$;
        10: return
      LineNumberTable:
        line 17: 0

  public <F extends java.lang.Object> coursier.util.Sync<F> apply(coursier.util.Sync<F>);
    descriptor: (Lcoursier/util/Sync;)Lcoursier/util/Sync;
    flags: (0x0001) ACC_PUBLIC
    Code:
      stack=1, locals=2, args_size=2
         0: aload_1
         1: areturn
      LineNumberTable:
        line 20: 0
      LocalVariableTable:
        Start  Length  Slot  Name   Signature
            0       2     0  this   Lcoursier/util/Sync$;
            0       2     1  sync   Lcoursier/util/Sync;
    Signature: #19                          // <F:Ljava/lang/Object;>(Lcoursier/util/Sync<TF;>;)Lcoursier/util/Sync<TF;>;
    MethodParameters:
      Name                           Flags
      sync                           final

  private java.lang.Object writeReplace();
    descriptor: ()Ljava/lang/Object;
    flags: (0x0002) ACC_PRIVATE
    Code:
      stack=3, locals=1, args_size=1
         0: new           #26                 // class scala/runtime/ModuleSerializationProxy
         3: dup
         4: ldc           #2                  // class coursier/util/Sync$
         6: invokespecial #29                 // Method scala/runtime/ModuleSerializationProxy."<init>":(Ljava/lang/Class;)V
         9: areturn
      LineNumberTable:
        line 17: 0
      LocalVariableTable:
        Start  Length  Slot  Name   Signature
            0      10     0  this   Lcoursier/util/Sync$;

  private coursier.util.Sync$();
    descriptor: ()V
    flags: (0x0002) ACC_PRIVATE
    Code:
      stack=1, locals=1, args_size=1
         0: aload_0
         1: invokespecial #30                 // Method coursier/util/PlatformSyncCompanion."<init>":()V
         4: return
      LineNumberTable:
        line 17: 0
      LocalVariableTable:
        Start  Length  Slot  Name   Signature
            0       5     0  this   Lcoursier/util/Sync$;
}
SourceFile: "Sync.scala"
  ScalaInlineInfo: length = 0x13 (unknown attribute)
   01 01 00 03 00 0C 00 0B 01 00 11 00 12 01 00 17
   00 18 01
  Scala: length = 0x0 (unknown attribute)

