Classfile /Users/mw/Projects/slang-braindump/.jar/jar8/assemble/slang-braindump/assemble/content/coursier/util/Task$WrappedException.class
  Last modified May 29, 2022; size 518 bytes
  SHA-256 checksum 94103a7d7a6b374b8fbb32abcd3a290abc599ddd975d8158c68985cd6f6563f1
  Compiled from "Task.scala"
public final class coursier.util.Task$WrappedException extends java.lang.Throwable
  minor version: 0
  major version: 52
  flags: (0x0031) ACC_PUBLIC, ACC_FINAL, ACC_SUPER
  this_class: #2                          // coursier/util/Task$WrappedException
  super_class: #4                         // java/lang/Throwable
  interfaces: 0, fields: 0, methods: 1, attributes: 4
Constant pool:
   #1 = Utf8               coursier/util/Task$WrappedException
   #2 = Class              #1             // coursier/util/Task$WrappedException
   #3 = Utf8               java/lang/Throwable
   #4 = Class              #3             // java/lang/Throwable
   #5 = Utf8               Task.scala
   #6 = Utf8               coursier/util/Task
   #7 = Class              #6             // coursier/util/Task
   #8 = Utf8               WrappedException
   #9 = Utf8               <init>
  #10 = Utf8               (Ljava/lang/Throwable;)V
  #11 = Utf8               cause
  #12 = NameAndType        #9:#10         // "<init>":(Ljava/lang/Throwable;)V
  #13 = Methodref          #4.#12         // java/lang/Throwable."<init>":(Ljava/lang/Throwable;)V
  #14 = Utf8               this
  #15 = Utf8               Lcoursier/util/Task$WrappedException;
  #16 = Utf8               Ljava/lang/Throwable;
  #17 = Utf8               Code
  #18 = Utf8               LineNumberTable
  #19 = Utf8               LocalVariableTable
  #20 = Utf8               MethodParameters
  #21 = Utf8               InnerClasses
  #22 = Utf8               SourceFile
  #23 = Utf8               ScalaInlineInfo
  #24 = Utf8               Scala
{
  public coursier.util.Task$WrappedException(java.lang.Throwable);
    descriptor: (Ljava/lang/Throwable;)V
    flags: (0x0001) ACC_PUBLIC
    Code:
      stack=2, locals=2, args_size=2
         0: aload_0
         1: aload_1
         2: invokespecial #13                 // Method java/lang/Throwable."<init>":(Ljava/lang/Throwable;)V
         5: return
      LineNumberTable:
        line 81: 0
      LocalVariableTable:
        Start  Length  Slot  Name   Signature
            0       6     0  this   Lcoursier/util/Task$WrappedException;
            0       6     1 cause   Ljava/lang/Throwable;
    MethodParameters:
      Name                           Flags
      cause                          final
}
InnerClasses:
  public static final #8= #2 of #7;       // WrappedException=class coursier/util/Task$WrappedException of class coursier/util/Task
SourceFile: "Task.scala"
  ScalaInlineInfo: length = 0x9 (unknown attribute)
   01 01 00 01 00 09 00 0A 01
  Scala: length = 0x0 (unknown attribute)

