Classfile /Users/mw/Projects/slang-braindump/.jar/jar8/assemble/slang-braindump/assemble/content/coursier/util/Traverse.class
  Last modified May 29, 2022; size 1356 bytes
  SHA-256 checksum d008cbaef89109ec31ca535bf81b48466f97edb4e8b216b9daeaebc96fada51f
  Compiled from "Traverse.scala"
public final class coursier.util.Traverse
  minor version: 0
  major version: 52
  flags: (0x0031) ACC_PUBLIC, ACC_FINAL, ACC_SUPER
  this_class: #2                          // coursier/util/Traverse
  super_class: #4                         // java/lang/Object
  interfaces: 0, fields: 0, methods: 1, attributes: 4
Constant pool:
   #1 = Utf8               coursier/util/Traverse
   #2 = Class              #1             // coursier/util/Traverse
   #3 = Utf8               java/lang/Object
   #4 = Class              #3             // java/lang/Object
   #5 = Utf8               Traverse.scala
   #6 = Utf8               Lscala/reflect/ScalaSignature;
   #7 = Utf8               bytes
   #8 = Utf8               \u0006\u0005\u0019<QAC\u0006\t\u0002A1QAE\u0006\t\u0002MAQAG\u0001\u0005\u0002m1A\u0001H\u0001\u0002;!Aqd\u0001BC\u0002\u0013\u0005\u0001\u0005\u0003\u00059\u0007\t\u0005\t\u0015!\u0003\"\u0011\u0015Q2\u0001\"\u0001:\u0011\u0015i4\u0001\"\u0001?\u0011\u0015\u00016\u0001\"\u0001R\u0011\u001dq\u0016!!A\u0005\u0004}\u000b\u0001\u0002\u0016:bm\u0016\u00148/\u001a\u0006\u0003\u00195\tA!\u001e;jY*\ta\"\u0001\u0005d_V\u00148/[3s\u0007\u0001\u0001\"!E\u0001\u000e\u0003-\u0011\u0001\u0002\u0016:bm\u0016\u00148/Z\n\u0003\u0003Q\u0001\"!\u0006\r\u000e\u0003YQ\u0011aF\u0001\u0006g\u000e\fG.Y\u0005\u00033Y\u0011a!\u00118z%\u00164\u0017A\u0002\u001fj]&$h\bF\u0001\u0011\u0005-!&/\u0019<feN,w\n]:\u0016\u0005yy3CA\u0002\u0015\u0003\r\u0019X-]\u000b\u0002CA\u0019!EK\u0017\u000f\u0005\rBcB\u0001\u0013(\u001b\u0005)#B\u0001\u0014\u0010\u0003\u0019a$o\\8u}%\tq#\u0003\u0002*-\u00059\u0001/Y2lC\u001e,\u0017BA\u0016-\u0005\r\u0019V-\u001d\u0006\u0003SY\u0001\"AL\u0018\r\u0001\u0011)\u0001g\u0001b\u0001c\t\tA+\u0005\u00023kA\u0011QcM\u0005\u0003iY\u0011qAT8uQ&tw\r\u0005\u0002\u0016m%\u0011qG\u0006\u0002\u0004\u0003:L\u0018\u0001B:fc\u0002\"\"A\u000f\u001f\u0011\u0007m\u001aQ&D\u0001\u0002\u0011\u0015yb\u00011\u0001\"\u00039)\u0017\u000e\u001e5feR\u0013\u0018M^3sg\u0016,2a\u0010#I)\t\u0001%\n\u0005\u0003#\u0003\u000e3\u0015B\u0001\"-\u0005\u0019)\u0015\u000e\u001e5feB\u0011a\u0006\u0012\u0003\u0006\u000b\u001e\u0011\r!\r\u0002\u0002\u0019B\u0019!EK$\u0011\u00059BE!B%\b\u0005\u0004\t$!\u0001*\t\u000b-;\u0001\u0019\u0001\'\u0002\u0003\u0019\u0004B!F\'.\u001f&\u0011aJ\u0006\u0002\n\rVt7\r^5p]F\u0002BAI!D\u000f\u0006)b/\u00197jI\u0006$\u0018n\u001c8OK2$&/\u0019<feN,Wc\u0001*X5R\u00111k\u0017\t\u0005#Q3\u0006,\u0003\u0002V\u0017\tia+\u00197jI\u0006$\u0018n\u001c8OK2\u0004\"AL,\u0005\u000b\u0015C!\u0019A\u0019\u0011\u0007\tR\u0013\f\u0005\u0002/5\u0012)\u0011\n\u0003b\u0001c!)1\n\u0003a\u00019B!Q#T\u0017^!\u0011\tBKV-\u0002\u0017Q\u0013\u0018M^3sg\u0016|\u0005o]\u000b\u0003A\u000e$\"!\u00193\u0011\u0007m\u001a!\r\u0005\u0002/G\u0012)\u0001\'\u0003b\u0001c!)q$\u0003a\u0001KB\u0019!E\u000b2
   #9 = Utf8               coursier/util/Traverse$TraverseOps
  #10 = Class              #9             // coursier/util/Traverse$TraverseOps
  #11 = Utf8               TraverseOps
  #12 = Utf8               (Lscala/collection/immutable/Seq;)Lcoursier/util/Traverse$TraverseOps;
  #13 = Utf8               <T:Ljava/lang/Object;>(Lscala/collection/immutable/Seq<TT;>;)Lcoursier/util/Traverse$TraverseOps<TT;>;
  #14 = Utf8               seq
  #15 = Utf8               coursier/util/Traverse$
  #16 = Class              #15            // coursier/util/Traverse$
  #17 = Utf8               MODULE$
  #18 = Utf8               Lcoursier/util/Traverse$;
  #19 = NameAndType        #17:#18        // MODULE$:Lcoursier/util/Traverse$;
  #20 = Fieldref           #16.#19        // coursier/util/Traverse$.MODULE$:Lcoursier/util/Traverse$;
  #21 = NameAndType        #11:#12        // TraverseOps:(Lscala/collection/immutable/Seq;)Lcoursier/util/Traverse$TraverseOps;
  #22 = Methodref          #16.#21        // coursier/util/Traverse$.TraverseOps:(Lscala/collection/immutable/Seq;)Lcoursier/util/Traverse$TraverseOps;
  #23 = Utf8               Code
  #24 = Utf8               Signature
  #25 = Utf8               MethodParameters
  #26 = Utf8               InnerClasses
  #27 = Utf8               SourceFile
  #28 = Utf8               RuntimeVisibleAnnotations
  #29 = Utf8               ScalaSig
{
  public static <T extends java.lang.Object> coursier.util.Traverse$TraverseOps<T> TraverseOps(scala.collection.immutable.Seq<T>);
    descriptor: (Lscala/collection/immutable/Seq;)Lcoursier/util/Traverse$TraverseOps;
    flags: (0x0009) ACC_PUBLIC, ACC_STATIC
    Code:
      stack=2, locals=1, args_size=1
         0: getstatic     #20                 // Field coursier/util/Traverse$.MODULE$:Lcoursier/util/Traverse$;
         3: aload_0
         4: invokevirtual #22                 // Method coursier/util/Traverse$.TraverseOps:(Lscala/collection/immutable/Seq;)Lcoursier/util/Traverse$TraverseOps;
         7: areturn
    Signature: #13                          // <T:Ljava/lang/Object;>(Lscala/collection/immutable/Seq<TT;>;)Lcoursier/util/Traverse$TraverseOps<TT;>;
    MethodParameters:
      Name                           Flags
      seq                            final
}
InnerClasses:
  public static #11= #10 of #2;           // TraverseOps=class coursier/util/Traverse$TraverseOps of class coursier/util/Traverse
SourceFile: "Traverse.scala"
RuntimeVisibleAnnotations:
  0: #6(#7=s#8)
    scala.reflect.ScalaSignature(
      bytes="\u0006\u0005\u0019<QAC\u0006\t\u0002A1QAE\u0006\t\u0002MAQAG\u0001\u0005\u0002m1A\u0001H\u0001\u0002;!Aqd\u0001BC\u0002\u0013\u0005\u0001\u0005\u0003\u00059\u0007\t\u0005\t\u0015!\u0003\"\u0011\u0015Q2\u0001\"\u0001:\u0011\u0015i4\u0001\"\u0001?\u0011\u0015\u00016\u0001\"\u0001R\u0011\u001dq\u0016!!A\u0005\u0004}\u000b\u0001\u0002\u0016:bm\u0016\u00148/\u001a\u0006\u0003\u00195\tA!\u001e;jY*\ta\"\u0001\u0005d_V\u00148/[3s\u0007\u0001\u0001\"!E\u0001\u000e\u0003-\u0011\u0001\u0002\u0016:bm\u0016\u00148/Z\n\u0003\u0003Q\u0001\"!\u0006\r\u000e\u0003YQ\u0011aF\u0001\u0006g\u000e\fG.Y\u0005\u00033Y\u0011a!\u00118z%\u00164\u0017A\u0002\u001fj]&$h\bF\u0001\u0011\u0005-!&/\u0019<feN,w\n]:\u0016\u0005yy3CA\u0002\u0015\u0003\r\u0019X-]\u000b\u0002CA\u0019!EK\u0017\u000f\u0005\rBcB\u0001\u0013(\u001b\u0005)#B\u0001\u0014\u0010\u0003\u0019a$o\\8u}%\tq#\u0003\u0002*-\u00059\u0001/Y2lC\u001e,\u0017BA\u0016-\u0005\r\u0019V-\u001d\u0006\u0003SY\u0001\"AL\u0018\r\u0001\u0011)\u0001g\u0001b\u0001c\t\tA+\u0005\u00023kA\u0011QcM\u0005\u0003iY\u0011qAT8uQ&tw\r\u0005\u0002\u0016m%\u0011qG\u0006\u0002\u0004\u0003:L\u0018\u0001B:fc\u0002\"\"A\u000f\u001f\u0011\u0007m\u001aQ&D\u0001\u0002\u0011\u0015yb\u00011\u0001\"\u00039)\u0017\u000e\u001e5feR\u0013\u0018M^3sg\u0016,2a\u0010#I)\t\u0001%\n\u0005\u0003#\u0003\u000e3\u0015B\u0001\"-\u0005\u0019)\u0015\u000e\u001e5feB\u0011a\u0006\u0012\u0003\u0006\u000b\u001e\u0011\r!\r\u0002\u0002\u0019B\u0019!EK$\u0011\u00059BE!B%\b\u0005\u0004\t$!\u0001*\t\u000b-;\u0001\u0019\u0001\'\u0002\u0003\u0019\u0004B!F\'.\u001f&\u0011aJ\u0006\u0002\n\rVt7\r^5p]F\u0002BAI!D\u000f\u0006)b/\u00197jI\u0006$\u0018n\u001c8OK2$&/\u0019<feN,Wc\u0001*X5R\u00111k\u0017\t\u0005#Q3\u0006,\u0003\u0002V\u0017\tia+\u00197jI\u0006$\u0018n\u001c8OK2\u0004\"AL,\u0005\u000b\u0015C!\u0019A\u0019\u0011\u0007\tR\u0013\f\u0005\u0002/5\u0012)\u0011\n\u0003b\u0001c!)1\n\u0003a\u00019B!Q#T\u0017^!\u0011\tBKV-\u0002\u0017Q\u0013\u0018M^3sg\u0016|\u0005o]\u000b\u0003A\u000e$\"!\u00193\u0011\u0007m\u001a!\r\u0005\u0002/G\u0012)\u0001\'\u0003b\u0001c!)q$\u0003a\u0001KB\u0019!E\u000b2"
    )
  ScalaSig: length = 0x3 (unknown attribute)
   05 02 00
