Classfile /Users/mw/Projects/slang-braindump/.jar/jar8/assemble/slang-braindump/assemble/content/coursier/util/Tree$.class
  Last modified May 29, 2022; size 978 bytes
  SHA-256 checksum 30bc8c3b324b0686aed043a4b6d409bfb38128e5f49da473ebb6d1991c93a2a7
  Compiled from "Tree.scala"
public final class coursier.util.Tree$
  minor version: 0
  major version: 52
  flags: (0x0031) ACC_PUBLIC, ACC_FINAL, ACC_SUPER
  this_class: #2                          // coursier/util/Tree$
  super_class: #4                         // java/lang/Object
  interfaces: 0, fields: 1, methods: 3, attributes: 3
Constant pool:
   #1 = Utf8               coursier/util/Tree$
   #2 = Class              #1             // coursier/util/Tree$
   #3 = Utf8               java/lang/Object
   #4 = Class              #3             // java/lang/Object
   #5 = Utf8               Tree.scala
   #6 = Utf8               MODULE$
   #7 = Utf8               Lcoursier/util/Tree$;
   #8 = Utf8               <clinit>
   #9 = Utf8               ()V
  #10 = Utf8               <init>
  #11 = NameAndType        #10:#9         // "<init>":()V
  #12 = Methodref          #2.#11         // coursier/util/Tree$."<init>":()V
  #13 = NameAndType        #6:#7          // MODULE$:Lcoursier/util/Tree$;
  #14 = Fieldref           #2.#13         // coursier/util/Tree$.MODULE$:Lcoursier/util/Tree$;
  #15 = Utf8               apply
  #16 = Utf8               (Lscala/collection/immutable/IndexedSeq;Lscala/Function1;)Lcoursier/util/Tree;
  #17 = Utf8               <A:Ljava/lang/Object;>(Lscala/collection/immutable/IndexedSeq<TA;>;Lscala/Function1<TA;Lscala/collection/immutable/Seq<TA;>;>;)Lcoursier/util/Tree<TA;>;
  #18 = Utf8               roots
  #19 = Utf8               children
  #20 = Utf8               coursier/util/Tree
  #21 = Class              #20            // coursier/util/Tree
  #22 = Utf8               (Lscala/collection/immutable/IndexedSeq;Lscala/Function1;)V
  #23 = NameAndType        #10:#22        // "<init>":(Lscala/collection/immutable/IndexedSeq;Lscala/Function1;)V
  #24 = Methodref          #21.#23        // coursier/util/Tree."<init>":(Lscala/collection/immutable/IndexedSeq;Lscala/Function1;)V
  #25 = Utf8               this
  #26 = Utf8               Lscala/collection/immutable/IndexedSeq;
  #27 = Utf8               Lscala/Function1;
  #28 = Methodref          #4.#11         // java/lang/Object."<init>":()V
  #29 = Utf8               Code
  #30 = Utf8               LineNumberTable
  #31 = Utf8               LocalVariableTable
  #32 = Utf8               Signature
  #33 = Utf8               MethodParameters
  #34 = Utf8               SourceFile
  #35 = Utf8               ScalaInlineInfo
  #36 = Utf8               Scala
{
  public static final coursier.util.Tree$ MODULE$;
    descriptor: Lcoursier/util/Tree$;
    flags: (0x0019) ACC_PUBLIC, ACC_STATIC, ACC_FINAL

  public static {};
    descriptor: ()V
    flags: (0x0009) ACC_PUBLIC, ACC_STATIC
    Code:
      stack=2, locals=0, args_size=0
         0: new           #2                  // class coursier/util/Tree$
         3: dup
         4: invokespecial #12                 // Method "<init>":()V
         7: putstatic     #14                 // Field MODULE$:Lcoursier/util/Tree$;
        10: return
      LineNumberTable:
        line 5: 0

  public <A extends java.lang.Object> coursier.util.Tree<A> apply(scala.collection.immutable.IndexedSeq<A>, scala.Function1<A, scala.collection.immutable.Seq<A>>);
    descriptor: (Lscala/collection/immutable/IndexedSeq;Lscala/Function1;)Lcoursier/util/Tree;
    flags: (0x0001) ACC_PUBLIC
    Code:
      stack=4, locals=3, args_size=3
         0: new           #21                 // class coursier/util/Tree
         3: dup
         4: aload_1
         5: aload_2
         6: invokespecial #24                 // Method coursier/util/Tree."<init>":(Lscala/collection/immutable/IndexedSeq;Lscala/Function1;)V
         9: areturn
      LineNumberTable:
        line 8: 0
      LocalVariableTable:
        Start  Length  Slot  Name   Signature
            0      10     0  this   Lcoursier/util/Tree$;
            0      10     1 roots   Lscala/collection/immutable/IndexedSeq;
            0      10     2 children   Lscala/Function1;
    Signature: #17                          // <A:Ljava/lang/Object;>(Lscala/collection/immutable/IndexedSeq<TA;>;Lscala/Function1<TA;Lscala/collection/immutable/Seq<TA;>;>;)Lcoursier/util/Tree<TA;>;
    MethodParameters:
      Name                           Flags
      roots                          final
      children                       final

  private coursier.util.Tree$();
    descriptor: ()V
    flags: (0x0002) ACC_PRIVATE
    Code:
      stack=1, locals=1, args_size=1
         0: aload_0
         1: invokespecial #28                 // Method java/lang/Object."<init>":()V
         4: return
      LineNumberTable:
        line 12: 0
        line 5: 4
      LocalVariableTable:
        Start  Length  Slot  Name   Signature
            0       5     0  this   Lcoursier/util/Tree$;
}
SourceFile: "Tree.scala"
  ScalaInlineInfo: length = 0xE (unknown attribute)
   01 01 00 02 00 0A 00 09 01 00 0F 00 10 01
  Scala: length = 0x0 (unknown attribute)

