Classfile /Users/mw/Projects/slang-braindump/.jar/jar8/assemble/slang-braindump/assemble/content/coursier/util/ValidationNel$.class
  Last modified May 29, 2022; size 4348 bytes
  SHA-256 checksum e9c06f2fc3d7da69cf07bc75838a76d432c9c8c58086c321bcd2d48ed715c529
  Compiled from "ValidationNel.scala"
public final class coursier.util.ValidationNel$ implements java.io.Serializable
  minor version: 0
  major version: 52
  flags: (0x0031) ACC_PUBLIC, ACC_FINAL, ACC_SUPER
  this_class: #2                          // coursier/util/ValidationNel$
  super_class: #4                         // java/lang/Object
  interfaces: 1, fields: 1, methods: 11, attributes: 5
Constant pool:
    #1 = Utf8               coursier/util/ValidationNel$
    #2 = Class              #1            // coursier/util/ValidationNel$
    #3 = Utf8               java/lang/Object
    #4 = Class              #3            // java/lang/Object
    #5 = Utf8               java/io/Serializable
    #6 = Class              #5            // java/io/Serializable
    #7 = Utf8               ValidationNel.scala
    #8 = Utf8               coursier/util/ValidationNel$FailureBuilder
    #9 = Class              #8            // coursier/util/ValidationNel$FailureBuilder
   #10 = Utf8               coursier/util/ValidationNel
   #11 = Class              #10           // coursier/util/ValidationNel
   #12 = Utf8               FailureBuilder
   #13 = Utf8               coursier/util/ValidationNel$FailuresBuilder
   #14 = Class              #13           // coursier/util/ValidationNel$FailuresBuilder
   #15 = Utf8               FailuresBuilder
   #16 = Utf8               coursier/util/ValidationNel$SuccessBuilder
   #17 = Class              #16           // coursier/util/ValidationNel$SuccessBuilder
   #18 = Utf8               SuccessBuilder
   #19 = Utf8               java/lang/invoke/MethodHandles$Lookup
   #20 = Class              #19           // java/lang/invoke/MethodHandles$Lookup
   #21 = Utf8               java/lang/invoke/MethodHandles
   #22 = Class              #21           // java/lang/invoke/MethodHandles
   #23 = Utf8               Lookup
   #24 = Utf8               scala/util/Either$LeftProjection
   #25 = Class              #24           // scala/util/Either$LeftProjection
   #26 = Utf8               scala/util/Either
   #27 = Class              #26           // scala/util/Either
   #28 = Utf8               LeftProjection
   #29 = Utf8               MODULE$
   #30 = Utf8               Lcoursier/util/ValidationNel$;
   #31 = Utf8               <clinit>
   #32 = Utf8               ()V
   #33 = Utf8               <init>
   #34 = NameAndType        #33:#32       // "<init>":()V
   #35 = Methodref          #2.#34        // coursier/util/ValidationNel$."<init>":()V
   #36 = NameAndType        #29:#30       // MODULE$:Lcoursier/util/ValidationNel$;
   #37 = Fieldref           #2.#36        // coursier/util/ValidationNel$.MODULE$:Lcoursier/util/ValidationNel$;
   #38 = Utf8               fromEither
   #39 = Utf8               (Lscala/util/Either;)Lcoursier/util/ValidationNel;
   #40 = Utf8               <L:Ljava/lang/Object;R:Ljava/lang/Object;>(Lscala/util/Either<TL;TR;>;)Lcoursier/util/ValidationNel<TL;TR;>;
   #41 = Utf8               either
   #42 = Utf8               left
   #43 = Utf8               ()Lscala/util/Either$LeftProjection;
   #44 = NameAndType        #42:#43       // left:()Lscala/util/Either$LeftProjection;
   #45 = Methodref          #27.#44       // scala/util/Either.left:()Lscala/util/Either$LeftProjection;
   #46 = Utf8               (Ljava/lang/Object;)Ljava/lang/Object;
   #47 = MethodType         #46           //  (Ljava/lang/Object;)Ljava/lang/Object;
   #48 = Utf8               $anonfun$fromEither$1
   #49 = Utf8               (Ljava/lang/Object;)Lscala/collection/immutable/$colon$colon;
   #50 = NameAndType        #48:#49       // $anonfun$fromEither$1:(Ljava/lang/Object;)Lscala/collection/immutable/$colon$colon;
   #51 = Methodref          #2.#50        // coursier/util/ValidationNel$.$anonfun$fromEither$1:(Ljava/lang/Object;)Lscala/collection/immutable/$colon$colon;
   #52 = MethodHandle       6:#51         // REF_invokeStatic coursier/util/ValidationNel$.$anonfun$fromEither$1:(Ljava/lang/Object;)Lscala/collection/immutable/$colon$colon;
   #53 = MethodType         #49           //  (Ljava/lang/Object;)Lscala/collection/immutable/$colon$colon;
   #54 = Integer            5
   #55 = Integer            1
   #56 = Utf8               java/lang/invoke/LambdaMetafactory
   #57 = Class              #56           // java/lang/invoke/LambdaMetafactory
   #58 = Utf8               altMetafactory
   #59 = Utf8               (Ljava/lang/invoke/MethodHandles$Lookup;Ljava/lang/String;Ljava/lang/invoke/MethodType;[Ljava/lang/Object;)Ljava/lang/invoke/CallSite;
   #60 = NameAndType        #58:#59       // altMetafactory:(Ljava/lang/invoke/MethodHandles$Lookup;Ljava/lang/String;Ljava/lang/invoke/MethodType;[Ljava/lang/Object;)Ljava/lang/invoke/CallSite;
   #61 = Methodref          #57.#60       // java/lang/invoke/LambdaMetafactory.altMetafactory:(Ljava/lang/invoke/MethodHandles$Lookup;Ljava/lang/String;Ljava/lang/invoke/MethodType;[Ljava/lang/Object;)Ljava/lang/invoke/CallSite;
   #62 = MethodHandle       6:#61         // REF_invokeStatic java/lang/invoke/LambdaMetafactory.altMetafactory:(Ljava/lang/invoke/MethodHandles$Lookup;Ljava/lang/String;Ljava/lang/invoke/MethodType;[Ljava/lang/Object;)Ljava/lang/invoke/CallSite;
   #63 = Utf8               apply
   #64 = Utf8               ()Lscala/Function1;
   #65 = NameAndType        #63:#64       // apply:()Lscala/Function1;
   #66 = InvokeDynamic      #0:#65        // #0:apply:()Lscala/Function1;
   #67 = Utf8               map
   #68 = Utf8               (Lscala/Function1;)Lscala/util/Either;
   #69 = NameAndType        #67:#68       // map:(Lscala/Function1;)Lscala/util/Either;
   #70 = Methodref          #25.#69       // scala/util/Either$LeftProjection.map:(Lscala/Function1;)Lscala/util/Either;
   #71 = Utf8               (Lscala/util/Either;)V
   #72 = NameAndType        #33:#71       // "<init>":(Lscala/util/Either;)V
   #73 = Methodref          #11.#72       // coursier/util/ValidationNel."<init>":(Lscala/util/Either;)V
   #74 = Utf8               this
   #75 = Utf8               Lscala/util/Either;
   #76 = Utf8               success
   #77 = Utf8               ()Lcoursier/util/ValidationNel$SuccessBuilder;
   #78 = Utf8               <L:Ljava/lang/Object;>()Lcoursier/util/ValidationNel$SuccessBuilder<TL;>;
   #79 = Methodref          #17.#34       // coursier/util/ValidationNel$SuccessBuilder."<init>":()V
   #80 = Utf8               failure
   #81 = Utf8               ()Lcoursier/util/ValidationNel$FailureBuilder;
   #82 = Utf8               <R:Ljava/lang/Object;>()Lcoursier/util/ValidationNel$FailureBuilder<TR;>;
   #83 = Methodref          #9.#34        // coursier/util/ValidationNel$FailureBuilder."<init>":()V
   #84 = Utf8               failures
   #85 = Utf8               ()Lcoursier/util/ValidationNel$FailuresBuilder;
   #86 = Utf8               <R:Ljava/lang/Object;>()Lcoursier/util/ValidationNel$FailuresBuilder<TR;>;
   #87 = Methodref          #14.#34       // coursier/util/ValidationNel$FailuresBuilder."<init>":()V
   #88 = Utf8               <L:Ljava/lang/Object;R:Ljava/lang/Object;>(Lscala/util/Either<Lscala/collection/immutable/$colon$colon<TL;>;TR;>;)Lcoursier/util/ValidationNel<TL;TR;>;
   #89 = Utf8               unapply
   #90 = Utf8               (Lcoursier/util/ValidationNel;)Lscala/Option;
   #91 = Utf8               <L:Ljava/lang/Object;R:Ljava/lang/Object;>(Lcoursier/util/ValidationNel<TL;TR;>;)Lscala/Option<Lscala/util/Either<Lscala/collection/immutable/$colon$colon<TL;>;TR;>;>;
   #92 = Utf8               x$0
   #93 = Utf8               scala/None$
   #94 = Class              #93           // scala/None$
   #95 = Utf8               Lscala/None$;
   #96 = NameAndType        #29:#95       // MODULE$:Lscala/None$;
   #97 = Fieldref           #94.#96       // scala/None$.MODULE$:Lscala/None$;
   #98 = Utf8               scala/Some
   #99 = Class              #98           // scala/Some
  #100 = Utf8               ()Lscala/util/Either;
  #101 = NameAndType        #41:#100      // either:()Lscala/util/Either;
  #102 = Methodref          #11.#101      // coursier/util/ValidationNel.either:()Lscala/util/Either;
  #103 = Utf8               (Ljava/lang/Object;)V
  #104 = NameAndType        #33:#103      // "<init>":(Ljava/lang/Object;)V
  #105 = Methodref          #99.#104      // scala/Some."<init>":(Ljava/lang/Object;)V
  #106 = Utf8               scala/Option
  #107 = Class              #106          // scala/Option
  #108 = Utf8               Lcoursier/util/ValidationNel;
  #109 = Utf8               writeReplace
  #110 = Utf8               ()Ljava/lang/Object;
  #111 = Utf8               scala/runtime/ModuleSerializationProxy
  #112 = Class              #111          // scala/runtime/ModuleSerializationProxy
  #113 = Utf8               (Ljava/lang/Class;)V
  #114 = NameAndType        #33:#113      // "<init>":(Ljava/lang/Class;)V
  #115 = Methodref          #112.#114     // scala/runtime/ModuleSerializationProxy."<init>":(Ljava/lang/Class;)V
  #116 = Utf8               l
  #117 = Utf8               scala/package$
  #118 = Class              #117          // scala/package$
  #119 = Utf8               Lscala/package$;
  #120 = NameAndType        #29:#119      // MODULE$:Lscala/package$;
  #121 = Fieldref           #118.#120     // scala/package$.MODULE$:Lscala/package$;
  #122 = Utf8               $colon$colon
  #123 = Utf8               ()Lscala/collection/immutable/$colon$colon$;
  #124 = NameAndType        #122:#123     // $colon$colon:()Lscala/collection/immutable/$colon$colon$;
  #125 = Methodref          #118.#124     // scala/package$.$colon$colon:()Lscala/collection/immutable/$colon$colon$;
  #126 = Utf8               scala/collection/immutable/Nil$
  #127 = Class              #126          // scala/collection/immutable/Nil$
  #128 = Utf8               Lscala/collection/immutable/Nil$;
  #129 = NameAndType        #29:#128      // MODULE$:Lscala/collection/immutable/Nil$;
  #130 = Fieldref           #127.#129     // scala/collection/immutable/Nil$.MODULE$:Lscala/collection/immutable/Nil$;
  #131 = Utf8               scala/collection/immutable/$colon$colon$
  #132 = Class              #131          // scala/collection/immutable/$colon$colon$
  #133 = Utf8               (Ljava/lang/Object;Lscala/collection/immutable/List;)Lscala/collection/immutable/$colon$colon;
  #134 = NameAndType        #63:#133      // apply:(Ljava/lang/Object;Lscala/collection/immutable/List;)Lscala/collection/immutable/$colon$colon;
  #135 = Methodref          #132.#134     // scala/collection/immutable/$colon$colon$.apply:(Ljava/lang/Object;Lscala/collection/immutable/List;)Lscala/collection/immutable/$colon$colon;
  #136 = Utf8               Ljava/lang/Object;
  #137 = Methodref          #4.#34        // java/lang/Object."<init>":()V
  #138 = Utf8               $deserializeLambda$
  #139 = Utf8               (Ljava/lang/invoke/SerializedLambda;)Ljava/lang/Object;
  #140 = Utf8               scala/runtime/LambdaDeserialize
  #141 = Class              #140          // scala/runtime/LambdaDeserialize
  #142 = Utf8               bootstrap
  #143 = Utf8               (Ljava/lang/invoke/MethodHandles$Lookup;Ljava/lang/String;Ljava/lang/invoke/MethodType;[Ljava/lang/invoke/MethodHandle;)Ljava/lang/invoke/CallSite;
  #144 = NameAndType        #142:#143     // bootstrap:(Ljava/lang/invoke/MethodHandles$Lookup;Ljava/lang/String;Ljava/lang/invoke/MethodType;[Ljava/lang/invoke/MethodHandle;)Ljava/lang/invoke/CallSite;
  #145 = Methodref          #141.#144     // scala/runtime/LambdaDeserialize.bootstrap:(Ljava/lang/invoke/MethodHandles$Lookup;Ljava/lang/String;Ljava/lang/invoke/MethodType;[Ljava/lang/invoke/MethodHandle;)Ljava/lang/invoke/CallSite;
  #146 = MethodHandle       6:#145        // REF_invokeStatic scala/runtime/LambdaDeserialize.bootstrap:(Ljava/lang/invoke/MethodHandles$Lookup;Ljava/lang/String;Ljava/lang/invoke/MethodType;[Ljava/lang/invoke/MethodHandle;)Ljava/lang/invoke/CallSite;
  #147 = Utf8               lambdaDeserialize
  #148 = NameAndType        #147:#139     // lambdaDeserialize:(Ljava/lang/invoke/SerializedLambda;)Ljava/lang/Object;
  #149 = InvokeDynamic      #1:#148       // #1:lambdaDeserialize:(Ljava/lang/invoke/SerializedLambda;)Ljava/lang/Object;
  #150 = Utf8               Code
  #151 = Utf8               LineNumberTable
  #152 = Utf8               LocalVariableTable
  #153 = Utf8               Signature
  #154 = Utf8               MethodParameters
  #155 = Utf8               StackMapTable
  #156 = Utf8               InnerClasses
  #157 = Utf8               SourceFile
  #158 = Utf8               BootstrapMethods
  #159 = Utf8               ScalaInlineInfo
  #160 = Utf8               Scala
{
  public static final coursier.util.ValidationNel$ MODULE$;
    descriptor: Lcoursier/util/ValidationNel$;
    flags: (0x0019) ACC_PUBLIC, ACC_STATIC, ACC_FINAL

  public static {};
    descriptor: ()V
    flags: (0x0009) ACC_PUBLIC, ACC_STATIC
    Code:
      stack=2, locals=0, args_size=0
         0: new           #2                  // class coursier/util/ValidationNel$
         3: dup
         4: invokespecial #35                 // Method "<init>":()V
         7: putstatic     #37                 // Field MODULE$:Lcoursier/util/ValidationNel$;
        10: return
      LineNumberTable:
        line 41: 0

  public <L extends java.lang.Object, R extends java.lang.Object> coursier.util.ValidationNel<L, R> fromEither(scala.util.Either<L, R>);
    descriptor: (Lscala/util/Either;)Lcoursier/util/ValidationNel;
    flags: (0x0001) ACC_PUBLIC
    Code:
      stack=4, locals=2, args_size=2
         0: new           #11                 // class coursier/util/ValidationNel
         3: dup
         4: aload_1
         5: invokevirtual #45                 // Method scala/util/Either.left:()Lscala/util/Either$LeftProjection;
         8: invokedynamic #66,  0             // InvokeDynamic #0:apply:()Lscala/Function1;
        13: invokevirtual #70                 // Method scala/util/Either$LeftProjection.map:(Lscala/Function1;)Lscala/util/Either;
        16: invokespecial #73                 // Method coursier/util/ValidationNel."<init>":(Lscala/util/Either;)V
        19: areturn
      LineNumberTable:
        line 43: 0
      LocalVariableTable:
        Start  Length  Slot  Name   Signature
            0      20     0  this   Lcoursier/util/ValidationNel$;
            0      20     1 either   Lscala/util/Either;
    Signature: #40                          // <L:Ljava/lang/Object;R:Ljava/lang/Object;>(Lscala/util/Either<TL;TR;>;)Lcoursier/util/ValidationNel<TL;TR;>;
    MethodParameters:
      Name                           Flags
      either                         final

  public <L extends java.lang.Object> coursier.util.ValidationNel$SuccessBuilder<L> success();
    descriptor: ()Lcoursier/util/ValidationNel$SuccessBuilder;
    flags: (0x0001) ACC_PUBLIC
    Code:
      stack=2, locals=1, args_size=1
         0: new           #17                 // class coursier/util/ValidationNel$SuccessBuilder
         3: dup
         4: invokespecial #79                 // Method coursier/util/ValidationNel$SuccessBuilder."<init>":()V
         7: areturn
      LineNumberTable:
        line 45: 0
      LocalVariableTable:
        Start  Length  Slot  Name   Signature
            0       8     0  this   Lcoursier/util/ValidationNel$;
    Signature: #78                          // <L:Ljava/lang/Object;>()Lcoursier/util/ValidationNel$SuccessBuilder<TL;>;

  public <R extends java.lang.Object> coursier.util.ValidationNel$FailureBuilder<R> failure();
    descriptor: ()Lcoursier/util/ValidationNel$FailureBuilder;
    flags: (0x0001) ACC_PUBLIC
    Code:
      stack=2, locals=1, args_size=1
         0: new           #9                  // class coursier/util/ValidationNel$FailureBuilder
         3: dup
         4: invokespecial #83                 // Method coursier/util/ValidationNel$FailureBuilder."<init>":()V
         7: areturn
      LineNumberTable:
        line 47: 0
      LocalVariableTable:
        Start  Length  Slot  Name   Signature
            0       8     0  this   Lcoursier/util/ValidationNel$;
    Signature: #82                          // <R:Ljava/lang/Object;>()Lcoursier/util/ValidationNel$FailureBuilder<TR;>;

  public <R extends java.lang.Object> coursier.util.ValidationNel$FailuresBuilder<R> failures();
    descriptor: ()Lcoursier/util/ValidationNel$FailuresBuilder;
    flags: (0x0001) ACC_PUBLIC
    Code:
      stack=2, locals=1, args_size=1
         0: new           #14                 // class coursier/util/ValidationNel$FailuresBuilder
         3: dup
         4: invokespecial #87                 // Method coursier/util/ValidationNel$FailuresBuilder."<init>":()V
         7: areturn
      LineNumberTable:
        line 49: 0
      LocalVariableTable:
        Start  Length  Slot  Name   Signature
            0       8     0  this   Lcoursier/util/ValidationNel$;
    Signature: #86                          // <R:Ljava/lang/Object;>()Lcoursier/util/ValidationNel$FailuresBuilder<TR;>;

  public <L extends java.lang.Object, R extends java.lang.Object> coursier.util.ValidationNel<L, R> apply(scala.util.Either<scala.collection.immutable.$colon$colon<L>, R>);
    descriptor: (Lscala/util/Either;)Lcoursier/util/ValidationNel;
    flags: (0x0001) ACC_PUBLIC
    Code:
      stack=3, locals=2, args_size=2
         0: new           #11                 // class coursier/util/ValidationNel
         3: dup
         4: aload_1
         5: invokespecial #73                 // Method coursier/util/ValidationNel."<init>":(Lscala/util/Either;)V
         8: areturn
      LineNumberTable:
        line 4: 0
      LocalVariableTable:
        Start  Length  Slot  Name   Signature
            0       9     0  this   Lcoursier/util/ValidationNel$;
            0       9     1 either   Lscala/util/Either;
    Signature: #88                          // <L:Ljava/lang/Object;R:Ljava/lang/Object;>(Lscala/util/Either<Lscala/collection/immutable/$colon$colon<TL;>;TR;>;)Lcoursier/util/ValidationNel<TL;TR;>;
    MethodParameters:
      Name                           Flags
      either                         final

  public <L extends java.lang.Object, R extends java.lang.Object> scala.Option<scala.util.Either<scala.collection.immutable.$colon$colon<L>, R>> unapply(coursier.util.ValidationNel<L, R>);
    descriptor: (Lcoursier/util/ValidationNel;)Lscala/Option;
    flags: (0x0001) ACC_PUBLIC
    Code:
      stack=3, locals=2, args_size=2
         0: aload_1
         1: ifnonnull     10
         4: getstatic     #97                 // Field scala/None$.MODULE$:Lscala/None$;
         7: goto          21
        10: new           #99                 // class scala/Some
        13: dup
        14: aload_1
        15: invokevirtual #102                // Method coursier/util/ValidationNel.either:()Lscala/util/Either;
        18: invokespecial #105                // Method scala/Some."<init>":(Ljava/lang/Object;)V
        21: areturn
      StackMapTable: number_of_entries = 2
        frame_type = 10 /* same */
        frame_type = 74 /* same_locals_1_stack_item */
          stack = [ class scala/Option ]
      LineNumberTable:
        line 4: 0
      LocalVariableTable:
        Start  Length  Slot  Name   Signature
            0      22     0  this   Lcoursier/util/ValidationNel$;
            0      22     1   x$0   Lcoursier/util/ValidationNel;
    Signature: #91                          // <L:Ljava/lang/Object;R:Ljava/lang/Object;>(Lcoursier/util/ValidationNel<TL;TR;>;)Lscala/Option<Lscala/util/Either<Lscala/collection/immutable/$colon$colon<TL;>;TR;>;>;
    MethodParameters:
      Name                           Flags
      x$0                            final

  private java.lang.Object writeReplace();
    descriptor: ()Ljava/lang/Object;
    flags: (0x0002) ACC_PRIVATE
    Code:
      stack=3, locals=1, args_size=1
         0: new           #112                // class scala/runtime/ModuleSerializationProxy
         3: dup
         4: ldc           #2                  // class coursier/util/ValidationNel$
         6: invokespecial #115                // Method scala/runtime/ModuleSerializationProxy."<init>":(Ljava/lang/Class;)V
         9: areturn
      LineNumberTable:
        line 41: 0
      LocalVariableTable:
        Start  Length  Slot  Name   Signature
            0      10     0  this   Lcoursier/util/ValidationNel$;

  public static final scala.collection.immutable.$colon$colon $anonfun$fromEither$1(java.lang.Object);
    descriptor: (Ljava/lang/Object;)Lscala/collection/immutable/$colon$colon;
    flags: (0x1019) ACC_PUBLIC, ACC_STATIC, ACC_FINAL, ACC_SYNTHETIC
    Code:
      stack=3, locals=1, args_size=1
         0: getstatic     #121                // Field scala/package$.MODULE$:Lscala/package$;
         3: invokevirtual #125                // Method scala/package$.$colon$colon:()Lscala/collection/immutable/$colon$colon$;
         6: aload_0
         7: getstatic     #130                // Field scala/collection/immutable/Nil$.MODULE$:Lscala/collection/immutable/Nil$;
        10: invokevirtual #135                // Method scala/collection/immutable/$colon$colon$.apply:(Ljava/lang/Object;Lscala/collection/immutable/List;)Lscala/collection/immutable/$colon$colon;
        13: areturn
      LineNumberTable:
        line 43: 0
      LocalVariableTable:
        Start  Length  Slot  Name   Signature
            0      14     0     l   Ljava/lang/Object;
    MethodParameters:
      Name                           Flags
      l                              final

  private coursier.util.ValidationNel$();
    descriptor: ()V
    flags: (0x0002) ACC_PRIVATE
    Code:
      stack=1, locals=1, args_size=1
         0: aload_0
         1: invokespecial #137                // Method java/lang/Object."<init>":()V
         4: return
      LineNumberTable:
        line 63: 0
        line 41: 4
      LocalVariableTable:
        Start  Length  Slot  Name   Signature
            0       5     0  this   Lcoursier/util/ValidationNel$;

  private static java.lang.Object $deserializeLambda$(java.lang.invoke.SerializedLambda);
    descriptor: (Ljava/lang/invoke/SerializedLambda;)Ljava/lang/Object;
    flags: (0x100a) ACC_PRIVATE, ACC_STATIC, ACC_SYNTHETIC
    Code:
      stack=1, locals=1, args_size=1
         0: aload_0
         1: invokedynamic #149,  0            // InvokeDynamic #1:lambdaDeserialize:(Ljava/lang/invoke/SerializedLambda;)Ljava/lang/Object;
         6: areturn
}
InnerClasses:
  public static final #12= #9 of #11;     // FailureBuilder=class coursier/util/ValidationNel$FailureBuilder of class coursier/util/ValidationNel
  public static final #15= #14 of #11;    // FailuresBuilder=class coursier/util/ValidationNel$FailuresBuilder of class coursier/util/ValidationNel
  public static final #18= #17 of #11;    // SuccessBuilder=class coursier/util/ValidationNel$SuccessBuilder of class coursier/util/ValidationNel
  public static final #23= #20 of #22;    // Lookup=class java/lang/invoke/MethodHandles$Lookup of class java/lang/invoke/MethodHandles
  public static final #28= #25 of #27;    // LeftProjection=class scala/util/Either$LeftProjection of class scala/util/Either
SourceFile: "ValidationNel.scala"
BootstrapMethods:
  0: #62 REF_invokeStatic java/lang/invoke/LambdaMetafactory.altMetafactory:(Ljava/lang/invoke/MethodHandles$Lookup;Ljava/lang/String;Ljava/lang/invoke/MethodType;[Ljava/lang/Object;)Ljava/lang/invoke/CallSite;
    Method arguments:
      #47 (Ljava/lang/Object;)Ljava/lang/Object;
      #52 REF_invokeStatic coursier/util/ValidationNel$.$anonfun$fromEither$1:(Ljava/lang/Object;)Lscala/collection/immutable/$colon$colon;
      #53 (Ljava/lang/Object;)Lscala/collection/immutable/$colon$colon;
      #54 5
      #55 1
      #53 (Ljava/lang/Object;)Lscala/collection/immutable/$colon$colon;
  1: #146 REF_invokeStatic scala/runtime/LambdaDeserialize.bootstrap:(Ljava/lang/invoke/MethodHandles$Lookup;Ljava/lang/String;Ljava/lang/invoke/MethodType;[Ljava/lang/invoke/MethodHandle;)Ljava/lang/invoke/CallSite;
    Method arguments:
      #52 REF_invokeStatic coursier/util/ValidationNel$.$anonfun$fromEither$1:(Ljava/lang/Object;)Lscala/collection/immutable/$colon$colon;
  ScalaInlineInfo: length = 0x31 (unknown attribute)
   01 01 00 09 00 30 00 31 01 00 21 00 20 01 00 3F
   00 27 01 00 50 00 51 01 00 54 00 55 01 00 26 00
   27 01 00 4C 00 4D 01 00 59 00 5A 01 00 6D 00 6E
   01
  Scala: length = 0x0 (unknown attribute)

