Classfile /Users/mw/Projects/slang-braindump/.jar/jar8/assemble/slang-braindump/assemble/content/coursier/util/WebPage.class
  Last modified May 29, 2022; size 1374 bytes
  SHA-256 checksum 52564bee3bdf968b98fffdd91f087b5ec71228bba98173eaea056ae168c0ab44
  Compiled from "WebPage.scala"
public final class coursier.util.WebPage
  minor version: 0
  major version: 52
  flags: (0x0031) ACC_PUBLIC, ACC_FINAL, ACC_SUPER
  this_class: #2                          // coursier/util/WebPage
  super_class: #4                         // java/lang/Object
  interfaces: 0, fields: 0, methods: 4, attributes: 3
Constant pool:
   #1 = Utf8               coursier/util/WebPage
   #2 = Class              #1             // coursier/util/WebPage
   #3 = Utf8               java/lang/Object
   #4 = Class              #3             // java/lang/Object
   #5 = Utf8               WebPage.scala
   #6 = Utf8               Lscala/reflect/ScalaSignature;
   #7 = Utf8               bytes
   #8 = Utf8               \u0006\u0005e:aAB\u0004\t\u0002%YaAB\u0007\b\u0011\u0003Ia\u0002C\u0003\u0013\u0003\u0011\u0005A\u0003C\u0003\u0016\u0003\u0011\u0005a\u0003C\u00032\u0003\u0011\u0005!\u0007C\u00036\u0003\u0011\u0005a\'A\u0004XK\n\u0004\u0016mZ3\u000b\u0005!I\u0011\u0001B;uS2T\u0011AC\u0001\tG>,(o]5feB\u0011A\"A\u0007\u0002\u000f\t9q+\u001a2QC\u001e,7CA\u0001\u0010!\ta\u0001#\u0003\u0002\u0012\u000f\t!r+\u001a2QC\u001e,7i\\7qCRL\'-\u001b7jif\fa\u0001P5oSRt4\u0001\u0001\u000b\u0002\u0017\u0005aA.[:u\u000b2,W.\u001a8ugR\u0019q#L\u0018\u0011\u0007a\u0011SE\u0004\u0002\u001a?9\u0011!$H\u0007\u00027)\u0011AdE\u0001\u0007yI|w\u000e\u001e \n\u0003y\tQa]2bY\u0006L!\u0001I\u0011\u0002\u000fA\f7m[1hK*\ta$\u0003\u0002$I\tA\u0011\n^3sCR|\'O\u0003\u0002!CA\u0011aE\u000b\b\u0003O!\u0002\"AG\u0011\n\u0005%\n\u0013A\u0002)sK\u0012,g-\u0003\u0002,Y\t11\u000b\u001e:j]\u001eT!!K\u0011\t\u000b9\u001a\u0001\u0019A\u0013\u0002\u0007U\u0014H\u000eC\u00031\u0007\u0001\u0007Q%\u0001\u0003qC\u001e,\u0017a\u00047jgR$\u0015N]3di>\u0014\u0018.Z:\u0015\u0007]\u0019D\u0007C\u0003/\t\u0001\u0007Q\u0005C\u00031\t\u0001\u0007Q%A\u0005mSN$h)\u001b7fgR\u0019qc\u000e\u001d\t\u000b9*\u0001\u0019A\u0013\t\u000bA*\u0001\u0019A\u0013
   #9 = Utf8               listFiles
  #10 = Utf8               (Ljava/lang/String;Ljava/lang/String;)Lscala/collection/Iterator;
  #11 = Utf8               (Ljava/lang/String;Ljava/lang/String;)Lscala/collection/Iterator<Ljava/lang/String;>;
  #12 = Utf8               url
  #13 = Utf8               page
  #14 = Utf8               coursier/util/WebPage$
  #15 = Class              #14            // coursier/util/WebPage$
  #16 = Utf8               MODULE$
  #17 = Utf8               Lcoursier/util/WebPage$;
  #18 = NameAndType        #16:#17        // MODULE$:Lcoursier/util/WebPage$;
  #19 = Fieldref           #15.#18        // coursier/util/WebPage$.MODULE$:Lcoursier/util/WebPage$;
  #20 = NameAndType        #9:#10         // listFiles:(Ljava/lang/String;Ljava/lang/String;)Lscala/collection/Iterator;
  #21 = Methodref          #15.#20        // coursier/util/WebPage$.listFiles:(Ljava/lang/String;Ljava/lang/String;)Lscala/collection/Iterator;
  #22 = Utf8               listDirectories
  #23 = NameAndType        #22:#10        // listDirectories:(Ljava/lang/String;Ljava/lang/String;)Lscala/collection/Iterator;
  #24 = Methodref          #15.#23        // coursier/util/WebPage$.listDirectories:(Ljava/lang/String;Ljava/lang/String;)Lscala/collection/Iterator;
  #25 = Utf8               listElements
  #26 = NameAndType        #25:#10        // listElements:(Ljava/lang/String;Ljava/lang/String;)Lscala/collection/Iterator;
  #27 = Methodref          #15.#26        // coursier/util/WebPage$.listElements:(Ljava/lang/String;Ljava/lang/String;)Lscala/collection/Iterator;
  #28 = Utf8               listWebPageRawElements
  #29 = Utf8               (Ljava/lang/String;)Lscala/collection/Iterator;
  #30 = Utf8               (Ljava/lang/String;)Lscala/collection/Iterator<Ljava/lang/String;>;
  #31 = NameAndType        #28:#29        // listWebPageRawElements:(Ljava/lang/String;)Lscala/collection/Iterator;
  #32 = Methodref          #15.#31        // coursier/util/WebPage$.listWebPageRawElements:(Ljava/lang/String;)Lscala/collection/Iterator;
  #33 = Utf8               Code
  #34 = Utf8               Signature
  #35 = Utf8               MethodParameters
  #36 = Utf8               SourceFile
  #37 = Utf8               RuntimeVisibleAnnotations
  #38 = Utf8               ScalaSig
{
  public static scala.collection.Iterator<java.lang.String> listFiles(java.lang.String, java.lang.String);
    descriptor: (Ljava/lang/String;Ljava/lang/String;)Lscala/collection/Iterator;
    flags: (0x0009) ACC_PUBLIC, ACC_STATIC
    Code:
      stack=3, locals=2, args_size=2
         0: getstatic     #19                 // Field coursier/util/WebPage$.MODULE$:Lcoursier/util/WebPage$;
         3: aload_0
         4: aload_1
         5: invokevirtual #21                 // Method coursier/util/WebPage$.listFiles:(Ljava/lang/String;Ljava/lang/String;)Lscala/collection/Iterator;
         8: areturn
    Signature: #11                          // (Ljava/lang/String;Ljava/lang/String;)Lscala/collection/Iterator<Ljava/lang/String;>;
    MethodParameters:
      Name                           Flags
      url                            final
      page                           final

  public static scala.collection.Iterator<java.lang.String> listDirectories(java.lang.String, java.lang.String);
    descriptor: (Ljava/lang/String;Ljava/lang/String;)Lscala/collection/Iterator;
    flags: (0x0009) ACC_PUBLIC, ACC_STATIC
    Code:
      stack=3, locals=2, args_size=2
         0: getstatic     #19                 // Field coursier/util/WebPage$.MODULE$:Lcoursier/util/WebPage$;
         3: aload_0
         4: aload_1
         5: invokevirtual #24                 // Method coursier/util/WebPage$.listDirectories:(Ljava/lang/String;Ljava/lang/String;)Lscala/collection/Iterator;
         8: areturn
    Signature: #11                          // (Ljava/lang/String;Ljava/lang/String;)Lscala/collection/Iterator<Ljava/lang/String;>;
    MethodParameters:
      Name                           Flags
      url                            final
      page                           final

  public static scala.collection.Iterator<java.lang.String> listElements(java.lang.String, java.lang.String);
    descriptor: (Ljava/lang/String;Ljava/lang/String;)Lscala/collection/Iterator;
    flags: (0x0009) ACC_PUBLIC, ACC_STATIC
    Code:
      stack=3, locals=2, args_size=2
         0: getstatic     #19                 // Field coursier/util/WebPage$.MODULE$:Lcoursier/util/WebPage$;
         3: aload_0
         4: aload_1
         5: invokevirtual #27                 // Method coursier/util/WebPage$.listElements:(Ljava/lang/String;Ljava/lang/String;)Lscala/collection/Iterator;
         8: areturn
    Signature: #11                          // (Ljava/lang/String;Ljava/lang/String;)Lscala/collection/Iterator<Ljava/lang/String;>;
    MethodParameters:
      Name                           Flags
      url                            final
      page                           final

  public static scala.collection.Iterator<java.lang.String> listWebPageRawElements(java.lang.String);
    descriptor: (Ljava/lang/String;)Lscala/collection/Iterator;
    flags: (0x0009) ACC_PUBLIC, ACC_STATIC
    Code:
      stack=2, locals=1, args_size=1
         0: getstatic     #19                 // Field coursier/util/WebPage$.MODULE$:Lcoursier/util/WebPage$;
         3: aload_0
         4: invokevirtual #32                 // Method coursier/util/WebPage$.listWebPageRawElements:(Ljava/lang/String;)Lscala/collection/Iterator;
         7: areturn
    Signature: #30                          // (Ljava/lang/String;)Lscala/collection/Iterator<Ljava/lang/String;>;
    MethodParameters:
      Name                           Flags
      page                           final
}
SourceFile: "WebPage.scala"
RuntimeVisibleAnnotations:
  0: #6(#7=s#8)
    scala.reflect.ScalaSignature(
      bytes="\u0006\u0005e:aAB\u0004\t\u0002%YaAB\u0007\b\u0011\u0003Ia\u0002C\u0003\u0013\u0003\u0011\u0005A\u0003C\u0003\u0016\u0003\u0011\u0005a\u0003C\u00032\u0003\u0011\u0005!\u0007C\u00036\u0003\u0011\u0005a\'A\u0004XK\n\u0004\u0016mZ3\u000b\u0005!I\u0011\u0001B;uS2T\u0011AC\u0001\tG>,(o]5feB\u0011A\"A\u0007\u0002\u000f\t9q+\u001a2QC\u001e,7CA\u0001\u0010!\ta\u0001#\u0003\u0002\u0012\u000f\t!r+\u001a2QC\u001e,7i\\7qCRL\'-\u001b7jif\fa\u0001P5oSRt4\u0001\u0001\u000b\u0002\u0017\u0005aA.[:u\u000b2,W.\u001a8ugR\u0019q#L\u0018\u0011\u0007a\u0011SE\u0004\u0002\u001a?9\u0011!$H\u0007\u00027)\u0011AdE\u0001\u0007yI|w\u000e\u001e \n\u0003y\tQa]2bY\u0006L!\u0001I\u0011\u0002\u000fA\f7m[1hK*\ta$\u0003\u0002$I\tA\u0011\n^3sCR|\'O\u0003\u0002!CA\u0011aE\u000b\b\u0003O!\u0002\"AG\u0011\n\u0005%\n\u0013A\u0002)sK\u0012,g-\u0003\u0002,Y\t11\u000b\u001e:j]\u001eT!!K\u0011\t\u000b9\u001a\u0001\u0019A\u0013\u0002\u0007U\u0014H\u000eC\u00031\u0007\u0001\u0007Q%\u0001\u0003qC\u001e,\u0017a\u00047jgR$\u0015N]3di>\u0014\u0018.Z:\u0015\u0007]\u0019D\u0007C\u0003/\t\u0001\u0007Q\u0005C\u00031\t\u0001\u0007Q%A\u0005mSN$h)\u001b7fgR\u0019qc\u000e\u001d\t\u000b9*\u0001\u0019A\u0013\t\u000bA*\u0001\u0019A\u0013"
    )
  ScalaSig: length = 0x3 (unknown attribute)
   05 02 00
