Classfile /Users/mw/Projects/slang-braindump/.jar/jar8/assemble/slang-braindump/assemble/content/coursier/util/WebPage$.class
  Last modified May 29, 2022; size 4639 bytes
  SHA-256 checksum 3ed254d926b8598c91f1c29e8a83caf72810832ea3028d8fac6aaab830119084
  Compiled from "WebPage.scala"
public final class coursier.util.WebPage$ extends coursier.util.WebPageCompatibility
  minor version: 0
  major version: 52
  flags: (0x0031) ACC_PUBLIC, ACC_FINAL, ACC_SUPER
  this_class: #2                          // coursier/util/WebPage$
  super_class: #4                         // coursier/util/WebPageCompatibility
  interfaces: 0, fields: 1, methods: 15, attributes: 5
Constant pool:
    #1 = Utf8               coursier/util/WebPage$
    #2 = Class              #1            // coursier/util/WebPage$
    #3 = Utf8               coursier/util/WebPageCompatibility
    #4 = Class              #3            // coursier/util/WebPageCompatibility
    #5 = Utf8               WebPage.scala
    #6 = Utf8               coursier/util/WebPage$$anonfun$listElements$1
    #7 = Class              #6            // coursier/util/WebPage$$anonfun$listElements$1
    #8 = Utf8               java/lang/invoke/MethodHandles$Lookup
    #9 = Class              #8            // java/lang/invoke/MethodHandles$Lookup
   #10 = Utf8               java/lang/invoke/MethodHandles
   #11 = Class              #10           // java/lang/invoke/MethodHandles
   #12 = Utf8               Lookup
   #13 = Utf8               MODULE$
   #14 = Utf8               Lcoursier/util/WebPage$;
   #15 = Utf8               <clinit>
   #16 = Utf8               ()V
   #17 = Utf8               <init>
   #18 = NameAndType        #17:#16       // "<init>":()V
   #19 = Methodref          #2.#18        // coursier/util/WebPage$."<init>":()V
   #20 = NameAndType        #13:#14       // MODULE$:Lcoursier/util/WebPage$;
   #21 = Fieldref           #2.#20        // coursier/util/WebPage$.MODULE$:Lcoursier/util/WebPage$;
   #22 = Utf8               listElements
   #23 = Utf8               (Ljava/lang/String;Ljava/lang/String;)Lscala/collection/Iterator;
   #24 = Utf8               (Ljava/lang/String;Ljava/lang/String;)Lscala/collection/Iterator<Ljava/lang/String;>;
   #25 = Utf8               url
   #26 = Utf8               page
   #27 = Utf8               listWebPageRawElements
   #28 = Utf8               (Ljava/lang/String;)Lscala/collection/Iterator;
   #29 = NameAndType        #27:#28       // listWebPageRawElements:(Ljava/lang/String;)Lscala/collection/Iterator;
   #30 = Methodref          #2.#29        // coursier/util/WebPage$.listWebPageRawElements:(Ljava/lang/String;)Lscala/collection/Iterator;
   #31 = Utf8               (Ljava/lang/String;)V
   #32 = NameAndType        #17:#31       // "<init>":(Ljava/lang/String;)V
   #33 = Methodref          #7.#32        // coursier/util/WebPage$$anonfun$listElements$1."<init>":(Ljava/lang/String;)V
   #34 = Utf8               scala/collection/Iterator
   #35 = Class              #34           // scala/collection/Iterator
   #36 = Utf8               collect
   #37 = Utf8               (Lscala/PartialFunction;)Lscala/collection/Iterator;
   #38 = NameAndType        #36:#37       // collect:(Lscala/PartialFunction;)Lscala/collection/Iterator;
   #39 = InterfaceMethodref #35.#38       // scala/collection/Iterator.collect:(Lscala/PartialFunction;)Lscala/collection/Iterator;
   #40 = Utf8               (Ljava/lang/Object;)Ljava/lang/Object;
   #41 = MethodType         #40           //  (Ljava/lang/Object;)Ljava/lang/Object;
   #42 = Utf8               $anonfun$listElements$2$adapted
   #43 = Utf8               (Ljava/lang/String;)Ljava/lang/Object;
   #44 = NameAndType        #42:#43       // $anonfun$listElements$2$adapted:(Ljava/lang/String;)Ljava/lang/Object;
   #45 = Methodref          #2.#44        // coursier/util/WebPage$.$anonfun$listElements$2$adapted:(Ljava/lang/String;)Ljava/lang/Object;
   #46 = MethodHandle       6:#45         // REF_invokeStatic coursier/util/WebPage$.$anonfun$listElements$2$adapted:(Ljava/lang/String;)Ljava/lang/Object;
   #47 = MethodType         #43           //  (Ljava/lang/String;)Ljava/lang/Object;
   #48 = Integer            5
   #49 = Integer            1
   #50 = Utf8               java/lang/invoke/LambdaMetafactory
   #51 = Class              #50           // java/lang/invoke/LambdaMetafactory
   #52 = Utf8               altMetafactory
   #53 = Utf8               (Ljava/lang/invoke/MethodHandles$Lookup;Ljava/lang/String;Ljava/lang/invoke/MethodType;[Ljava/lang/Object;)Ljava/lang/invoke/CallSite;
   #54 = NameAndType        #52:#53       // altMetafactory:(Ljava/lang/invoke/MethodHandles$Lookup;Ljava/lang/String;Ljava/lang/invoke/MethodType;[Ljava/lang/Object;)Ljava/lang/invoke/CallSite;
   #55 = Methodref          #51.#54       // java/lang/invoke/LambdaMetafactory.altMetafactory:(Ljava/lang/invoke/MethodHandles$Lookup;Ljava/lang/String;Ljava/lang/invoke/MethodType;[Ljava/lang/Object;)Ljava/lang/invoke/CallSite;
   #56 = MethodHandle       6:#55         // REF_invokeStatic java/lang/invoke/LambdaMetafactory.altMetafactory:(Ljava/lang/invoke/MethodHandles$Lookup;Ljava/lang/String;Ljava/lang/invoke/MethodType;[Ljava/lang/Object;)Ljava/lang/invoke/CallSite;
   #57 = Utf8               apply
   #58 = Utf8               ()Lscala/Function1;
   #59 = NameAndType        #57:#58       // apply:()Lscala/Function1;
   #60 = InvokeDynamic      #0:#59        // #0:apply:()Lscala/Function1;
   #61 = Utf8               filter
   #62 = Utf8               (Lscala/Function1;)Lscala/collection/Iterator;
   #63 = NameAndType        #61:#62       // filter:(Lscala/Function1;)Lscala/collection/Iterator;
   #64 = InterfaceMethodref #35.#63       // scala/collection/Iterator.filter:(Lscala/Function1;)Lscala/collection/Iterator;
   #65 = Utf8               this
   #66 = Utf8               Ljava/lang/String;
   #67 = Utf8               listDirectories
   #68 = NameAndType        #22:#23       // listElements:(Ljava/lang/String;Ljava/lang/String;)Lscala/collection/Iterator;
   #69 = Methodref          #2.#68        // coursier/util/WebPage$.listElements:(Ljava/lang/String;Ljava/lang/String;)Lscala/collection/Iterator;
   #70 = Utf8               $anonfun$listDirectories$1$adapted
   #71 = NameAndType        #70:#43       // $anonfun$listDirectories$1$adapted:(Ljava/lang/String;)Ljava/lang/Object;
   #72 = Methodref          #2.#71        // coursier/util/WebPage$.$anonfun$listDirectories$1$adapted:(Ljava/lang/String;)Ljava/lang/Object;
   #73 = MethodHandle       6:#72         // REF_invokeStatic coursier/util/WebPage$.$anonfun$listDirectories$1$adapted:(Ljava/lang/String;)Ljava/lang/Object;
   #74 = InvokeDynamic      #1:#59        // #1:apply:()Lscala/Function1;
   #75 = Utf8               $anonfun$listDirectories$2
   #76 = Utf8               (Ljava/lang/String;)Ljava/lang/String;
   #77 = NameAndType        #75:#76       // $anonfun$listDirectories$2:(Ljava/lang/String;)Ljava/lang/String;
   #78 = Methodref          #2.#77        // coursier/util/WebPage$.$anonfun$listDirectories$2:(Ljava/lang/String;)Ljava/lang/String;
   #79 = MethodHandle       6:#78         // REF_invokeStatic coursier/util/WebPage$.$anonfun$listDirectories$2:(Ljava/lang/String;)Ljava/lang/String;
   #80 = MethodType         #76           //  (Ljava/lang/String;)Ljava/lang/String;
   #81 = InvokeDynamic      #2:#59        // #2:apply:()Lscala/Function1;
   #82 = Utf8               map
   #83 = NameAndType        #82:#62       // map:(Lscala/Function1;)Lscala/collection/Iterator;
   #84 = InterfaceMethodref #35.#83       // scala/collection/Iterator.map:(Lscala/Function1;)Lscala/collection/Iterator;
   #85 = Utf8               listFiles
   #86 = Utf8               $anonfun$listFiles$1$adapted
   #87 = NameAndType        #86:#43       // $anonfun$listFiles$1$adapted:(Ljava/lang/String;)Ljava/lang/Object;
   #88 = Methodref          #2.#87        // coursier/util/WebPage$.$anonfun$listFiles$1$adapted:(Ljava/lang/String;)Ljava/lang/Object;
   #89 = MethodHandle       6:#88         // REF_invokeStatic coursier/util/WebPage$.$anonfun$listFiles$1$adapted:(Ljava/lang/String;)Ljava/lang/Object;
   #90 = InvokeDynamic      #3:#59        // #3:apply:()Lscala/Function1;
   #91 = Utf8               slashIdx$lzycompute$1
   #92 = Utf8               (Lscala/runtime/LazyInt;Ljava/lang/String;)I
   #93 = Utf8               slashIdx$lzy$1
   #94 = Utf8               n$1
   #95 = Utf8               scala/runtime/LazyInt
   #96 = Class              #95           // scala/runtime/LazyInt
   #97 = Utf8               initialized
   #98 = Utf8               ()Z
   #99 = NameAndType        #97:#98       // initialized:()Z
  #100 = Methodref          #96.#99       // scala/runtime/LazyInt.initialized:()Z
  #101 = Utf8               value
  #102 = Utf8               ()I
  #103 = NameAndType        #101:#102     // value:()I
  #104 = Methodref          #96.#103      // scala/runtime/LazyInt.value:()I
  #105 = Utf8               java/lang/String
  #106 = Class              #105          // java/lang/String
  #107 = Utf8               indexOf
  #108 = Utf8               (I)I
  #109 = NameAndType        #107:#108     // indexOf:(I)I
  #110 = Methodref          #106.#109     // java/lang/String.indexOf:(I)I
  #111 = Utf8               initialize
  #112 = NameAndType        #111:#108     // initialize:(I)I
  #113 = Methodref          #96.#112      // scala/runtime/LazyInt.initialize:(I)I
  #114 = Utf8               java/lang/Throwable
  #115 = Class              #114          // java/lang/Throwable
  #116 = Utf8               Lscala/runtime/LazyInt;
  #117 = Utf8               slashIdx$1
  #118 = NameAndType        #91:#92       // slashIdx$lzycompute$1:(Lscala/runtime/LazyInt;Ljava/lang/String;)I
  #119 = Methodref          #2.#118       // coursier/util/WebPage$.slashIdx$lzycompute$1:(Lscala/runtime/LazyInt;Ljava/lang/String;)I
  #120 = Utf8               $anonfun$listElements$2
  #121 = Utf8               (Ljava/lang/String;)Z
  #122 = Utf8               n
  #123 = Methodref          #96.#18       // scala/runtime/LazyInt."<init>":()V
  #124 = Utf8               ./
  #125 = String             #124          // ./
  #126 = Utf8               java/lang/Object
  #127 = Class              #126          // java/lang/Object
  #128 = Utf8               equals
  #129 = Utf8               (Ljava/lang/Object;)Z
  #130 = NameAndType        #128:#129     // equals:(Ljava/lang/Object;)Z
  #131 = Methodref          #127.#130     // java/lang/Object.equals:(Ljava/lang/Object;)Z
  #132 = Utf8               ../
  #133 = String             #132          // ../
  #134 = Utf8               .
  #135 = String             #134          // .
  #136 = Utf8               ..
  #137 = String             #136          // ..
  #138 = Utf8               /
  #139 = String             #138          // /
  #140 = NameAndType        #117:#92      // slashIdx$1:(Lscala/runtime/LazyInt;Ljava/lang/String;)I
  #141 = Methodref          #2.#140       // coursier/util/WebPage$.slashIdx$1:(Lscala/runtime/LazyInt;Ljava/lang/String;)I
  #142 = Utf8               length
  #143 = NameAndType        #142:#102     // length:()I
  #144 = Methodref          #106.#143     // java/lang/String.length:()I
  #145 = Utf8               slashIdx$lzy
  #146 = Utf8               $anonfun$listDirectories$1
  #147 = Utf8               x$1
  #148 = Utf8               endsWith
  #149 = NameAndType        #148:#121     // endsWith:(Ljava/lang/String;)Z
  #150 = Methodref          #106.#149     // java/lang/String.endsWith:(Ljava/lang/String;)Z
  #151 = Utf8               s
  #152 = Utf8               substring
  #153 = Utf8               (II)Ljava/lang/String;
  #154 = NameAndType        #152:#153     // substring:(II)Ljava/lang/String;
  #155 = Methodref          #106.#154     // java/lang/String.substring:(II)Ljava/lang/String;
  #156 = Utf8               $anonfun$listFiles$1
  #157 = Utf8               x$2
  #158 = Methodref          #4.#18        // coursier/util/WebPageCompatibility."<init>":()V
  #159 = NameAndType        #120:#121     // $anonfun$listElements$2:(Ljava/lang/String;)Z
  #160 = Methodref          #2.#159       // coursier/util/WebPage$.$anonfun$listElements$2:(Ljava/lang/String;)Z
  #161 = Utf8               scala/runtime/BoxesRunTime
  #162 = Class              #161          // scala/runtime/BoxesRunTime
  #163 = Utf8               boxToBoolean
  #164 = Utf8               (Z)Ljava/lang/Boolean;
  #165 = NameAndType        #163:#164     // boxToBoolean:(Z)Ljava/lang/Boolean;
  #166 = Methodref          #162.#165     // scala/runtime/BoxesRunTime.boxToBoolean:(Z)Ljava/lang/Boolean;
  #167 = NameAndType        #146:#121     // $anonfun$listDirectories$1:(Ljava/lang/String;)Z
  #168 = Methodref          #2.#167       // coursier/util/WebPage$.$anonfun$listDirectories$1:(Ljava/lang/String;)Z
  #169 = NameAndType        #156:#121     // $anonfun$listFiles$1:(Ljava/lang/String;)Z
  #170 = Methodref          #2.#169       // coursier/util/WebPage$.$anonfun$listFiles$1:(Ljava/lang/String;)Z
  #171 = Utf8               $deserializeLambda$
  #172 = Utf8               (Ljava/lang/invoke/SerializedLambda;)Ljava/lang/Object;
  #173 = Utf8               scala/runtime/LambdaDeserialize
  #174 = Class              #173          // scala/runtime/LambdaDeserialize
  #175 = Utf8               bootstrap
  #176 = Utf8               (Ljava/lang/invoke/MethodHandles$Lookup;Ljava/lang/String;Ljava/lang/invoke/MethodType;[Ljava/lang/invoke/MethodHandle;)Ljava/lang/invoke/CallSite;
  #177 = NameAndType        #175:#176     // bootstrap:(Ljava/lang/invoke/MethodHandles$Lookup;Ljava/lang/String;Ljava/lang/invoke/MethodType;[Ljava/lang/invoke/MethodHandle;)Ljava/lang/invoke/CallSite;
  #178 = Methodref          #174.#177     // scala/runtime/LambdaDeserialize.bootstrap:(Ljava/lang/invoke/MethodHandles$Lookup;Ljava/lang/String;Ljava/lang/invoke/MethodType;[Ljava/lang/invoke/MethodHandle;)Ljava/lang/invoke/CallSite;
  #179 = MethodHandle       6:#178        // REF_invokeStatic scala/runtime/LambdaDeserialize.bootstrap:(Ljava/lang/invoke/MethodHandles$Lookup;Ljava/lang/String;Ljava/lang/invoke/MethodType;[Ljava/lang/invoke/MethodHandle;)Ljava/lang/invoke/CallSite;
  #180 = Utf8               lambdaDeserialize
  #181 = NameAndType        #180:#172     // lambdaDeserialize:(Ljava/lang/invoke/SerializedLambda;)Ljava/lang/Object;
  #182 = InvokeDynamic      #4:#181       // #4:lambdaDeserialize:(Ljava/lang/invoke/SerializedLambda;)Ljava/lang/Object;
  #183 = Utf8               Code
  #184 = Utf8               LineNumberTable
  #185 = Utf8               LocalVariableTable
  #186 = Utf8               Signature
  #187 = Utf8               MethodParameters
  #188 = Utf8               StackMapTable
  #189 = Utf8               InnerClasses
  #190 = Utf8               SourceFile
  #191 = Utf8               BootstrapMethods
  #192 = Utf8               ScalaInlineInfo
  #193 = Utf8               Scala
{
  public static final coursier.util.WebPage$ MODULE$;
    descriptor: Lcoursier/util/WebPage$;
    flags: (0x0019) ACC_PUBLIC, ACC_STATIC, ACC_FINAL

  public static {};
    descriptor: ()V
    flags: (0x0009) ACC_PUBLIC, ACC_STATIC
    Code:
      stack=2, locals=0, args_size=0
         0: new           #2                  // class coursier/util/WebPage$
         3: dup
         4: invokespecial #19                 // Method "<init>":()V
         7: putstatic     #21                 // Field MODULE$:Lcoursier/util/WebPage$;
        10: return
      LineNumberTable:
        line 3: 0

  public scala.collection.Iterator<java.lang.String> listElements(java.lang.String, java.lang.String);
    descriptor: (Ljava/lang/String;Ljava/lang/String;)Lscala/collection/Iterator;
    flags: (0x0001) ACC_PUBLIC
    Code:
      stack=4, locals=3, args_size=3
         0: aload_0
         1: aload_2
         2: invokevirtual #30                 // Method listWebPageRawElements:(Ljava/lang/String;)Lscala/collection/Iterator;
         5: new           #7                  // class coursier/util/WebPage$$anonfun$listElements$1
         8: dup
         9: aload_1
        10: invokespecial #33                 // Method coursier/util/WebPage$$anonfun$listElements$1."<init>":(Ljava/lang/String;)V
        13: invokeinterface #39,  2           // InterfaceMethod scala/collection/Iterator.collect:(Lscala/PartialFunction;)Lscala/collection/Iterator;
        18: invokedynamic #60,  0             // InvokeDynamic #0:apply:()Lscala/Function1;
        23: invokeinterface #64,  2           // InterfaceMethod scala/collection/Iterator.filter:(Lscala/Function1;)Lscala/collection/Iterator;
        28: areturn
      LineNumberTable:
        line 6: 0
        line 7: 5
        line 13: 18
      LocalVariableTable:
        Start  Length  Slot  Name   Signature
            0      29     0  this   Lcoursier/util/WebPage$;
            0      29     1   url   Ljava/lang/String;
            0      29     2  page   Ljava/lang/String;
    Signature: #24                          // (Ljava/lang/String;Ljava/lang/String;)Lscala/collection/Iterator<Ljava/lang/String;>;
    MethodParameters:
      Name                           Flags
      url                            final
      page                           final

  public scala.collection.Iterator<java.lang.String> listDirectories(java.lang.String, java.lang.String);
    descriptor: (Ljava/lang/String;Ljava/lang/String;)Lscala/collection/Iterator;
    flags: (0x0001) ACC_PUBLIC
    Code:
      stack=3, locals=3, args_size=3
         0: aload_0
         1: aload_1
         2: aload_2
         3: invokevirtual #69                 // Method listElements:(Ljava/lang/String;Ljava/lang/String;)Lscala/collection/Iterator;
         6: invokedynamic #74,  0             // InvokeDynamic #1:apply:()Lscala/Function1;
        11: invokeinterface #64,  2           // InterfaceMethod scala/collection/Iterator.filter:(Lscala/Function1;)Lscala/collection/Iterator;
        16: invokedynamic #81,  0             // InvokeDynamic #2:apply:()Lscala/Function1;
        21: invokeinterface #84,  2           // InterfaceMethod scala/collection/Iterator.map:(Lscala/Function1;)Lscala/collection/Iterator;
        26: areturn
      LineNumberTable:
        line 19: 0
        line 20: 6
        line 21: 16
      LocalVariableTable:
        Start  Length  Slot  Name   Signature
            0      27     0  this   Lcoursier/util/WebPage$;
            0      27     1   url   Ljava/lang/String;
            0      27     2  page   Ljava/lang/String;
    Signature: #24                          // (Ljava/lang/String;Ljava/lang/String;)Lscala/collection/Iterator<Ljava/lang/String;>;
    MethodParameters:
      Name                           Flags
      url                            final
      page                           final

  public scala.collection.Iterator<java.lang.String> listFiles(java.lang.String, java.lang.String);
    descriptor: (Ljava/lang/String;Ljava/lang/String;)Lscala/collection/Iterator;
    flags: (0x0001) ACC_PUBLIC
    Code:
      stack=3, locals=3, args_size=3
         0: aload_0
         1: aload_1
         2: aload_2
         3: invokevirtual #69                 // Method listElements:(Ljava/lang/String;Ljava/lang/String;)Lscala/collection/Iterator;
         6: invokedynamic #90,  0             // InvokeDynamic #3:apply:()Lscala/Function1;
        11: invokeinterface #64,  2           // InterfaceMethod scala/collection/Iterator.filter:(Lscala/Function1;)Lscala/collection/Iterator;
        16: areturn
      LineNumberTable:
        line 24: 0
        line 25: 6
      LocalVariableTable:
        Start  Length  Slot  Name   Signature
            0      17     0  this   Lcoursier/util/WebPage$;
            0      17     1   url   Ljava/lang/String;
            0      17     2  page   Ljava/lang/String;
    Signature: #24                          // (Ljava/lang/String;Ljava/lang/String;)Lscala/collection/Iterator<Ljava/lang/String;>;
    MethodParameters:
      Name                           Flags
      url                            final
      page                           final

  private static final int slashIdx$lzycompute$1(scala.runtime.LazyInt, java.lang.String);
    descriptor: (Lscala/runtime/LazyInt;Ljava/lang/String;)I
    flags: (0x101a) ACC_PRIVATE, ACC_STATIC, ACC_FINAL, ACC_SYNTHETIC
    Code:
      stack=3, locals=4, args_size=2
         0: aload_0
         1: dup
         2: astore_2
         3: monitorenter
         4: aload_0
         5: invokevirtual #100                // Method scala/runtime/LazyInt.initialized:()Z
         8: ifeq          18
        11: aload_0
        12: invokevirtual #104                // Method scala/runtime/LazyInt.value:()I
        15: goto          28
        18: aload_0
        19: aload_1
        20: bipush        47
        22: invokevirtual #110                // Method java/lang/String.indexOf:(I)I
        25: invokevirtual #113                // Method scala/runtime/LazyInt.initialize:(I)I
        28: istore_3
        29: aload_2
        30: monitorexit
        31: iload_3
        32: goto          38
        35: aload_2
        36: monitorexit
        37: athrow
        38: ireturn
      Exception table:
         from    to  target type
             4    29    35   any
      StackMapTable: number_of_entries = 4
        frame_type = 252 /* append */
          offset_delta = 18
          locals = [ class scala/runtime/LazyInt ]
        frame_type = 73 /* same_locals_1_stack_item */
          stack = [ int ]
        frame_type = 70 /* same_locals_1_stack_item */
          stack = [ class java/lang/Throwable ]
        frame_type = 255 /* full_frame */
          offset_delta = 2
          locals = [ class scala/runtime/LazyInt, class java/lang/String, class scala/runtime/LazyInt, int ]
          stack = [ int ]
      LineNumberTable:
        line 14: 0
      LocalVariableTable:
        Start  Length  Slot  Name   Signature
            0      39     0 slashIdx$lzy$1   Lscala/runtime/LazyInt;
            0      39     1   n$1   Ljava/lang/String;
    MethodParameters:
      Name                           Flags
      slashIdx$lzy$1                 final
      n$1                            final

  private static final int slashIdx$1(scala.runtime.LazyInt, java.lang.String);
    descriptor: (Lscala/runtime/LazyInt;Ljava/lang/String;)I
    flags: (0x001a) ACC_PRIVATE, ACC_STATIC, ACC_FINAL
    Code:
      stack=2, locals=2, args_size=2
         0: aload_0
         1: invokevirtual #100                // Method scala/runtime/LazyInt.initialized:()Z
         4: ifeq          14
         7: aload_0
         8: invokevirtual #104                // Method scala/runtime/LazyInt.value:()I
        11: goto          19
        14: aload_0
        15: aload_1
        16: invokestatic  #119                // Method slashIdx$lzycompute$1:(Lscala/runtime/LazyInt;Ljava/lang/String;)I
        19: ireturn
      StackMapTable: number_of_entries = 2
        frame_type = 14 /* same */
        frame_type = 68 /* same_locals_1_stack_item */
          stack = [ int ]
      LineNumberTable:
        line 14: 0
      LocalVariableTable:
        Start  Length  Slot  Name   Signature
            0      20     0 slashIdx$lzy$1   Lscala/runtime/LazyInt;
            0      20     1   n$1   Ljava/lang/String;
    MethodParameters:
      Name                           Flags
      slashIdx$lzy$1                 final
      n$1                            final

  public static final boolean $anonfun$listElements$2(java.lang.String);
    descriptor: (Ljava/lang/String;)Z
    flags: (0x1019) ACC_PUBLIC, ACC_STATIC, ACC_FINAL, ACC_SYNTHETIC
    Code:
      stack=3, locals=7, args_size=1
         0: new           #96                 // class scala/runtime/LazyInt
         3: dup
         4: invokespecial #123                // Method scala/runtime/LazyInt."<init>":()V
         7: astore_1
         8: aload_0
         9: ldc           #125                // String ./
        11: astore_2
        12: dup
        13: ifnonnull     24
        16: pop
        17: aload_2
        18: ifnull        159
        21: goto          31
        24: aload_2
        25: invokevirtual #131                // Method java/lang/Object.equals:(Ljava/lang/Object;)Z
        28: ifne          159
        31: aload_0
        32: ldc           #133                // String ../
        34: astore_3
        35: dup
        36: ifnonnull     47
        39: pop
        40: aload_3
        41: ifnull        159
        44: goto          54
        47: aload_3
        48: invokevirtual #131                // Method java/lang/Object.equals:(Ljava/lang/Object;)Z
        51: ifne          159
        54: aload_0
        55: ldc           #135                // String .
        57: astore        4
        59: dup
        60: ifnonnull     72
        63: pop
        64: aload         4
        66: ifnull        159
        69: goto          80
        72: aload         4
        74: invokevirtual #131                // Method java/lang/Object.equals:(Ljava/lang/Object;)Z
        77: ifne          159
        80: aload_0
        81: ldc           #137                // String ..
        83: astore        5
        85: dup
        86: ifnonnull     98
        89: pop
        90: aload         5
        92: ifnull        159
        95: goto          106
        98: aload         5
       100: invokevirtual #131                // Method java/lang/Object.equals:(Ljava/lang/Object;)Z
       103: ifne          159
       106: aload_0
       107: ldc           #139                // String /
       109: astore        6
       111: dup
       112: ifnonnull     124
       115: pop
       116: aload         6
       118: ifnull        159
       121: goto          132
       124: aload         6
       126: invokevirtual #131                // Method java/lang/Object.equals:(Ljava/lang/Object;)Z
       129: ifne          159
       132: aload_1
       133: aload_0
       134: invokestatic  #141                // Method slashIdx$1:(Lscala/runtime/LazyInt;Ljava/lang/String;)I
       137: iconst_0
       138: if_icmplt     155
       141: aload_1
       142: aload_0
       143: invokestatic  #141                // Method slashIdx$1:(Lscala/runtime/LazyInt;Ljava/lang/String;)I
       146: aload_0
       147: invokevirtual #144                // Method java/lang/String.length:()I
       150: iconst_1
       151: isub
       152: if_icmpne     159
       155: iconst_1
       156: goto          160
       159: iconst_0
       160: ireturn
      StackMapTable: number_of_entries = 13
        frame_type = 255 /* full_frame */
          offset_delta = 24
          locals = [ class java/lang/String, class scala/runtime/LazyInt, class java/lang/String ]
          stack = [ class java/lang/String ]
        frame_type = 6 /* same */
        frame_type = 255 /* full_frame */
          offset_delta = 15
          locals = [ class java/lang/String, class scala/runtime/LazyInt, class java/lang/String, class java/lang/String ]
          stack = [ class java/lang/String ]
        frame_type = 6 /* same */
        frame_type = 255 /* full_frame */
          offset_delta = 17
          locals = [ class java/lang/String, class scala/runtime/LazyInt, class java/lang/String, class java/lang/String, class java/lang/String ]
          stack = [ class java/lang/String ]
        frame_type = 7 /* same */
        frame_type = 255 /* full_frame */
          offset_delta = 17
          locals = [ class java/lang/String, class scala/runtime/LazyInt, class java/lang/String, class java/lang/String, class java/lang/String, class java/lang/String ]
          stack = [ class java/lang/String ]
        frame_type = 7 /* same */
        frame_type = 255 /* full_frame */
          offset_delta = 17
          locals = [ class java/lang/String, class scala/runtime/LazyInt, class java/lang/String, class java/lang/String, class java/lang/String, class java/lang/String, class java/lang/String ]
          stack = [ class java/lang/String ]
        frame_type = 7 /* same */
        frame_type = 22 /* same */
        frame_type = 255 /* full_frame */
          offset_delta = 3
          locals = [ class java/lang/String, class scala/runtime/LazyInt, class java/lang/String ]
          stack = []
        frame_type = 64 /* same_locals_1_stack_item */
          stack = [ int ]
      LineNumberTable:
        line 14: 0
        line 15: 8
      LocalVariableTable:
        Start  Length  Slot  Name   Signature
            8     152     1 slashIdx$lzy   Lscala/runtime/LazyInt;
            0     161     0     n   Ljava/lang/String;
    MethodParameters:
      Name                           Flags
      n                              final

  public static final boolean $anonfun$listDirectories$1(java.lang.String);
    descriptor: (Ljava/lang/String;)Z
    flags: (0x1019) ACC_PUBLIC, ACC_STATIC, ACC_FINAL, ACC_SYNTHETIC
    Code:
      stack=2, locals=1, args_size=1
         0: aload_0
         1: ldc           #139                // String /
         3: invokevirtual #150                // Method java/lang/String.endsWith:(Ljava/lang/String;)Z
         6: ireturn
      LineNumberTable:
        line 20: 0
      LocalVariableTable:
        Start  Length  Slot  Name   Signature
            0       7     0   x$1   Ljava/lang/String;
    MethodParameters:
      Name                           Flags
      x$1                            final

  public static final java.lang.String $anonfun$listDirectories$2(java.lang.String);
    descriptor: (Ljava/lang/String;)Ljava/lang/String;
    flags: (0x1019) ACC_PUBLIC, ACC_STATIC, ACC_FINAL, ACC_SYNTHETIC
    Code:
      stack=4, locals=1, args_size=1
         0: aload_0
         1: iconst_0
         2: aload_0
         3: invokevirtual #144                // Method java/lang/String.length:()I
         6: iconst_1
         7: isub
         8: invokevirtual #155                // Method java/lang/String.substring:(II)Ljava/lang/String;
        11: areturn
      LineNumberTable:
        line 21: 0
      LocalVariableTable:
        Start  Length  Slot  Name   Signature
            0      12     0     s   Ljava/lang/String;
    MethodParameters:
      Name                           Flags
      s                              final

  public static final boolean $anonfun$listFiles$1(java.lang.String);
    descriptor: (Ljava/lang/String;)Z
    flags: (0x1019) ACC_PUBLIC, ACC_STATIC, ACC_FINAL, ACC_SYNTHETIC
    Code:
      stack=2, locals=1, args_size=1
         0: aload_0
         1: ldc           #139                // String /
         3: invokevirtual #150                // Method java/lang/String.endsWith:(Ljava/lang/String;)Z
         6: ifne          13
         9: iconst_1
        10: goto          14
        13: iconst_0
        14: ireturn
      StackMapTable: number_of_entries = 2
        frame_type = 13 /* same */
        frame_type = 64 /* same_locals_1_stack_item */
          stack = [ int ]
      LineNumberTable:
        line 25: 0
      LocalVariableTable:
        Start  Length  Slot  Name   Signature
            0      15     0   x$2   Ljava/lang/String;
    MethodParameters:
      Name                           Flags
      x$2                            final

  private coursier.util.WebPage$();
    descriptor: ()V
    flags: (0x0002) ACC_PRIVATE
    Code:
      stack=1, locals=1, args_size=1
         0: aload_0
         1: invokespecial #158                // Method coursier/util/WebPageCompatibility."<init>":()V
         4: return
      LineNumberTable:
        line 3: 0
      LocalVariableTable:
        Start  Length  Slot  Name   Signature
            0       5     0  this   Lcoursier/util/WebPage$;

  public static final java.lang.Object $anonfun$listElements$2$adapted(java.lang.String);
    descriptor: (Ljava/lang/String;)Ljava/lang/Object;
    flags: (0x1019) ACC_PUBLIC, ACC_STATIC, ACC_FINAL, ACC_SYNTHETIC
    Code:
      stack=1, locals=1, args_size=1
         0: aload_0
         1: invokestatic  #160                // Method $anonfun$listElements$2:(Ljava/lang/String;)Z
         4: invokestatic  #166                // Method scala/runtime/BoxesRunTime.boxToBoolean:(Z)Ljava/lang/Boolean;
         7: areturn
      LineNumberTable:
        line 13: 0
      LocalVariableTable:
        Start  Length  Slot  Name   Signature
            0       8     0     n   Ljava/lang/String;
    MethodParameters:
      Name                           Flags
      n                              final

  public static final java.lang.Object $anonfun$listDirectories$1$adapted(java.lang.String);
    descriptor: (Ljava/lang/String;)Ljava/lang/Object;
    flags: (0x1019) ACC_PUBLIC, ACC_STATIC, ACC_FINAL, ACC_SYNTHETIC
    Code:
      stack=1, locals=1, args_size=1
         0: aload_0
         1: invokestatic  #168                // Method $anonfun$listDirectories$1:(Ljava/lang/String;)Z
         4: invokestatic  #166                // Method scala/runtime/BoxesRunTime.boxToBoolean:(Z)Ljava/lang/Boolean;
         7: areturn
      LineNumberTable:
        line 20: 0
      LocalVariableTable:
        Start  Length  Slot  Name   Signature
            0       8     0   x$1   Ljava/lang/String;
    MethodParameters:
      Name                           Flags
      x$1                            final

  public static final java.lang.Object $anonfun$listFiles$1$adapted(java.lang.String);
    descriptor: (Ljava/lang/String;)Ljava/lang/Object;
    flags: (0x1019) ACC_PUBLIC, ACC_STATIC, ACC_FINAL, ACC_SYNTHETIC
    Code:
      stack=1, locals=1, args_size=1
         0: aload_0
         1: invokestatic  #170                // Method $anonfun$listFiles$1:(Ljava/lang/String;)Z
         4: invokestatic  #166                // Method scala/runtime/BoxesRunTime.boxToBoolean:(Z)Ljava/lang/Boolean;
         7: areturn
      LineNumberTable:
        line 25: 0
      LocalVariableTable:
        Start  Length  Slot  Name   Signature
            0       8     0   x$2   Ljava/lang/String;
    MethodParameters:
      Name                           Flags
      x$2                            final

  private static java.lang.Object $deserializeLambda$(java.lang.invoke.SerializedLambda);
    descriptor: (Ljava/lang/invoke/SerializedLambda;)Ljava/lang/Object;
    flags: (0x100a) ACC_PRIVATE, ACC_STATIC, ACC_SYNTHETIC
    Code:
      stack=1, locals=1, args_size=1
         0: aload_0
         1: invokedynamic #182,  0            // InvokeDynamic #4:lambdaDeserialize:(Ljava/lang/invoke/SerializedLambda;)Ljava/lang/Object;
         6: areturn
}
InnerClasses:
  public final #7;                        // class coursier/util/WebPage$$anonfun$listElements$1
  public static final #12= #9 of #11;     // Lookup=class java/lang/invoke/MethodHandles$Lookup of class java/lang/invoke/MethodHandles
SourceFile: "WebPage.scala"
BootstrapMethods:
  0: #56 REF_invokeStatic java/lang/invoke/LambdaMetafactory.altMetafactory:(Ljava/lang/invoke/MethodHandles$Lookup;Ljava/lang/String;Ljava/lang/invoke/MethodType;[Ljava/lang/Object;)Ljava/lang/invoke/CallSite;
    Method arguments:
      #41 (Ljava/lang/Object;)Ljava/lang/Object;
      #46 REF_invokeStatic coursier/util/WebPage$.$anonfun$listElements$2$adapted:(Ljava/lang/String;)Ljava/lang/Object;
      #47 (Ljava/lang/String;)Ljava/lang/Object;
      #48 5
      #49 1
      #47 (Ljava/lang/String;)Ljava/lang/Object;
  1: #56 REF_invokeStatic java/lang/invoke/LambdaMetafactory.altMetafactory:(Ljava/lang/invoke/MethodHandles$Lookup;Ljava/lang/String;Ljava/lang/invoke/MethodType;[Ljava/lang/Object;)Ljava/lang/invoke/CallSite;
    Method arguments:
      #41 (Ljava/lang/Object;)Ljava/lang/Object;
      #73 REF_invokeStatic coursier/util/WebPage$.$anonfun$listDirectories$1$adapted:(Ljava/lang/String;)Ljava/lang/Object;
      #47 (Ljava/lang/String;)Ljava/lang/Object;
      #48 5
      #49 1
      #47 (Ljava/lang/String;)Ljava/lang/Object;
  2: #56 REF_invokeStatic java/lang/invoke/LambdaMetafactory.altMetafactory:(Ljava/lang/invoke/MethodHandles$Lookup;Ljava/lang/String;Ljava/lang/invoke/MethodType;[Ljava/lang/Object;)Ljava/lang/invoke/CallSite;
    Method arguments:
      #41 (Ljava/lang/Object;)Ljava/lang/Object;
      #79 REF_invokeStatic coursier/util/WebPage$.$anonfun$listDirectories$2:(Ljava/lang/String;)Ljava/lang/String;
      #80 (Ljava/lang/String;)Ljava/lang/String;
      #48 5
      #49 1
      #80 (Ljava/lang/String;)Ljava/lang/String;
  3: #56 REF_invokeStatic java/lang/invoke/LambdaMetafactory.altMetafactory:(Ljava/lang/invoke/MethodHandles$Lookup;Ljava/lang/String;Ljava/lang/invoke/MethodType;[Ljava/lang/Object;)Ljava/lang/invoke/CallSite;
    Method arguments:
      #41 (Ljava/lang/Object;)Ljava/lang/Object;
      #89 REF_invokeStatic coursier/util/WebPage$.$anonfun$listFiles$1$adapted:(Ljava/lang/String;)Ljava/lang/Object;
      #47 (Ljava/lang/String;)Ljava/lang/Object;
      #48 5
      #49 1
      #47 (Ljava/lang/String;)Ljava/lang/Object;
  4: #179 REF_invokeStatic scala/runtime/LambdaDeserialize.bootstrap:(Ljava/lang/invoke/MethodHandles$Lookup;Ljava/lang/String;Ljava/lang/invoke/MethodType;[Ljava/lang/invoke/MethodHandle;)Ljava/lang/invoke/CallSite;
    Method arguments:
      #73 REF_invokeStatic coursier/util/WebPage$.$anonfun$listDirectories$1$adapted:(Ljava/lang/String;)Ljava/lang/Object;
      #79 REF_invokeStatic coursier/util/WebPage$.$anonfun$listDirectories$2:(Ljava/lang/String;)Ljava/lang/String;
      #46 REF_invokeStatic coursier/util/WebPage$.$anonfun$listElements$2$adapted:(Ljava/lang/String;)Ljava/lang/Object;
      #89 REF_invokeStatic coursier/util/WebPage$.$anonfun$listFiles$1$adapted:(Ljava/lang/String;)Ljava/lang/Object;
  ScalaInlineInfo: length = 0x45 (unknown attribute)
   01 01 00 0D 00 92 00 79 01 00 46 00 2B 01 00 4B
   00 4C 01 00 78 00 79 01 00 2A 00 2B 01 00 9C 00
   79 01 00 56 00 2B 01 00 11 00 10 01 00 43 00 17
   01 00 16 00 17 01 00 55 00 17 01 00 75 00 5C 01
   00 5B 00 5C 01
  Scala: length = 0x0 (unknown attribute)

