Classfile /Users/mw/Projects/slang-braindump/.jar/jar8/assemble/slang-braindump/assemble/content/coursier/util/Xml$Text$.class
  Last modified May 29, 2022; size 1032 bytes
  SHA-256 checksum 33d0654abf212cc7086b7aba076a9faaf63e903abef5b54fe571c2e7ba3369a8
  Compiled from "Xml.scala"
public class coursier.util.Xml$Text$
  minor version: 0
  major version: 52
  flags: (0x0021) ACC_PUBLIC, ACC_SUPER
  this_class: #2                          // coursier/util/Xml$Text$
  super_class: #4                         // java/lang/Object
  interfaces: 0, fields: 1, methods: 3, attributes: 4
Constant pool:
   #1 = Utf8               coursier/util/Xml$Text$
   #2 = Class              #1             // coursier/util/Xml$Text$
   #3 = Utf8               java/lang/Object
   #4 = Class              #3             // java/lang/Object
   #5 = Utf8               Xml.scala
   #6 = Utf8               coursier/util/Xml$Node
   #7 = Class              #6             // coursier/util/Xml$Node
   #8 = Utf8               coursier/util/Xml
   #9 = Class              #8             // coursier/util/Xml
  #10 = Utf8               Node
  #11 = Utf8
  #12 = Utf8               MODULE$
  #13 = Utf8               Lcoursier/util/Xml$Text$;
  #14 = Utf8               <clinit>
  #15 = Utf8               ()V
  #16 = Utf8               <init>
  #17 = NameAndType        #16:#15        // "<init>":()V
  #18 = Methodref          #2.#17         // coursier/util/Xml$Text$."<init>":()V
  #19 = NameAndType        #12:#13        // MODULE$:Lcoursier/util/Xml$Text$;
  #20 = Fieldref           #2.#19         // coursier/util/Xml$Text$.MODULE$:Lcoursier/util/Xml$Text$;
  #21 = Utf8               unapply
  #22 = Utf8               (Lcoursier/util/Xml$Node;)Lscala/Option;
  #23 = Utf8               (Lcoursier/util/Xml$Node;)Lscala/Option<Ljava/lang/String;>;
  #24 = Utf8               n
  #25 = Utf8               isText
  #26 = Utf8               ()Z
  #27 = NameAndType        #25:#26        // isText:()Z
  #28 = InterfaceMethodref #7.#27         // coursier/util/Xml$Node.isText:()Z
  #29 = Utf8               scala/Some
  #30 = Class              #29            // scala/Some
  #31 = Utf8               textContent
  #32 = Utf8               ()Ljava/lang/String;
  #33 = NameAndType        #31:#32        // textContent:()Ljava/lang/String;
  #34 = InterfaceMethodref #7.#33         // coursier/util/Xml$Node.textContent:()Ljava/lang/String;
  #35 = Utf8               (Ljava/lang/Object;)V
  #36 = NameAndType        #16:#35        // "<init>":(Ljava/lang/Object;)V
  #37 = Methodref          #30.#36        // scala/Some."<init>":(Ljava/lang/Object;)V
  #38 = Utf8               scala/None$
  #39 = Class              #38            // scala/None$
  #40 = Utf8               Lscala/None$;
  #41 = NameAndType        #12:#40        // MODULE$:Lscala/None$;
  #42 = Fieldref           #39.#41        // scala/None$.MODULE$:Lscala/None$;
  #43 = Utf8               scala/Option
  #44 = Class              #43            // scala/Option
  #45 = Utf8               this
  #46 = Utf8               Lcoursier/util/Xml$Node;
  #47 = Methodref          #4.#17         // java/lang/Object."<init>":()V
  #48 = Utf8               Code
  #49 = Utf8               LineNumberTable
  #50 = Utf8               StackMapTable
  #51 = Utf8               LocalVariableTable
  #52 = Utf8               Signature
  #53 = Utf8               MethodParameters
  #54 = Utf8               InnerClasses
  #55 = Utf8               SourceFile
  #56 = Utf8               ScalaInlineInfo
  #57 = Utf8               Scala
{
  public static final coursier.util.Xml$Text$ MODULE$;
    descriptor: Lcoursier/util/Xml$Text$;
    flags: (0x0019) ACC_PUBLIC, ACC_STATIC, ACC_FINAL

  public static {};
    descriptor: ()V
    flags: (0x0009) ACC_PUBLIC, ACC_STATIC
    Code:
      stack=2, locals=0, args_size=0
         0: new           #2                  // class coursier/util/Xml$Text$
         3: dup
         4: invokespecial #18                 // Method "<init>":()V
         7: putstatic     #20                 // Field MODULE$:Lcoursier/util/Xml$Text$;
        10: return
      LineNumberTable:
        line 43: 0

  public scala.Option<java.lang.String> unapply(coursier.util.Xml$Node);
    descriptor: (Lcoursier/util/Xml$Node;)Lscala/Option;
    flags: (0x0001) ACC_PUBLIC
    Code:
      stack=3, locals=2, args_size=2
         0: aload_1
         1: invokeinterface #28,  1           // InterfaceMethod coursier/util/Xml$Node.isText:()Z
         6: ifeq          25
         9: new           #30                 // class scala/Some
        12: dup
        13: aload_1
        14: invokeinterface #34,  1           // InterfaceMethod coursier/util/Xml$Node.textContent:()Ljava/lang/String;
        19: invokespecial #37                 // Method scala/Some."<init>":(Ljava/lang/Object;)V
        22: goto          28
        25: getstatic     #42                 // Field scala/None$.MODULE$:Lscala/None$;
        28: areturn
      StackMapTable: number_of_entries = 2
        frame_type = 25 /* same */
        frame_type = 66 /* same_locals_1_stack_item */
          stack = [ class scala/Option ]
      LineNumberTable:
        line 45: 0
        line 46: 25
      LocalVariableTable:
        Start  Length  Slot  Name   Signature
            0      29     0  this   Lcoursier/util/Xml$Text$;
            0      29     1     n   Lcoursier/util/Xml$Node;
    Signature: #23                          // (Lcoursier/util/Xml$Node;)Lscala/Option<Ljava/lang/String;>;
    MethodParameters:
      Name                           Flags
      n                              final

  public coursier.util.Xml$Text$();
    descriptor: ()V
    flags: (0x0001) ACC_PUBLIC
    Code:
      stack=1, locals=1, args_size=1
         0: aload_0
         1: invokespecial #47                 // Method java/lang/Object."<init>":()V
         4: return
      LineNumberTable:
        line 49: 0
        line 43: 4
      LocalVariableTable:
        Start  Length  Slot  Name   Signature
            0       5     0  this   Lcoursier/util/Xml$Text$;
}
InnerClasses:
  public static #10= #7 of #9;            // Node=class coursier/util/Xml$Node of class coursier/util/Xml
  public static #11= #2 of #9;            // =class coursier/util/Xml$Text$ of class coursier/util/Xml
SourceFile: "Xml.scala"
  ScalaInlineInfo: length = 0xE (unknown attribute)
   01 01 00 02 00 10 00 0F 01 00 15 00 16 01
  Scala: length = 0x0 (unknown attribute)

