Classfile /Users/mw/Projects/slang-braindump/.jar/jar8/assemble/slang-braindump/assemble/content/org/sireum/conversions/C.class
  Last modified May 29, 2022; size 1130 bytes
  SHA-256 checksum 49794c9830bdd4e4510f3279e1d2aecdffde932ca65bceea31befe0869e41fc4
  Compiled from "conversions.scala"
public final class org.sireum.conversions.C
  minor version: 0
  major version: 52
  flags: (0x0031) ACC_PUBLIC, ACC_FINAL, ACC_SUPER
  this_class: #2                          // org/sireum/conversions/C
  super_class: #4                         // java/lang/Object
  interfaces: 0, fields: 0, methods: 2, attributes: 3
Constant pool:
   #1 = Utf8               org/sireum/conversions/C
   #2 = Class              #1             // org/sireum/conversions/C
   #3 = Utf8               java/lang/Object
   #4 = Class              #3             // java/lang/Object
   #5 = Utf8               conversions.scala
   #6 = Utf8               Lscala/reflect/ScalaSignature;
   #7 = Utf8               bytes
   #8 = Utf8               \u0006\u00059;Q!\u0002\u0004\t\u000251Qa\u0004\u0004\t\u0002AAQaF\u0001\u0005\u0002aAQ!G\u0001\u0005\u0002iAQaJ\u0001\u0005\u0002!\n\u0011a\u0011\u0006\u0003\u000f!\t1bY8om\u0016\u00148/[8og*\u0011\u0011BC\u0001\u0007g&\u0014X-^7\u000b\u0003-\t1a\u001c:h\u0007\u0001\u0001\"AD\u0001\u000e\u0003\u0019\u0011\u0011aQ\n\u0003\u0003E\u0001\"AE\u000b\u000e\u0003MQ\u0011\u0001F\u0001\u0006g\u000e\fG.Y\u0005\u0003-M\u0011a!\u00118z%\u00164\u0017A\u0002\u001fj]&$h\bF\u0001\u000e\u0003\u0015!x.V\u001a3)\tYr\u0004\u0005\u0002\u001d;5\t\u0001\"\u0003\u0002\u001f\u0011\t\u0019Qk\r\u001a\t\u000b\u0001\u001a\u0001\u0019A\u0011\u0002\u0003\r\u0004\"\u0001\b\u0012\n\u0005=A\u0001FA\u0002%!\taR%\u0003\u0002\'\u0011\t!\u0001/\u001e:f\u00031!xnQ8eKB{\u0017N\u001c;t)\tI#\bE\u0002+i\u0005r!a\u000b\u001a\u000f\u00051\ndBA\u00171\u001b\u0005q#BA\u0018\r\u0003\u0019a$o\\8u}%\t1\"\u0003\u0002\n\u0015%\u00111\u0007C\u0001\ba\u0006\u001c7.Y4f\u0013\t)dGA\u0002J\'jK!a\u000e\u001d\u0003\u0019A\u000b7m[1hKR\u0013\u0018-\u001b;\u000b\u0005eB\u0011!\u0003\u0013j]R,\'O\\1m\u0011\u0015\u0001C\u00011\u0001\"Q\t!A\u0005K\u0002\u0002{\u0001\u0003\"\u0001\b \n\u0005}B!aA3yiF*1%\u0011#I\u000bB\u0011ADQ\u0005\u0003\u0007\"\u0011aa\u0015;sS:<\u0017BA#G\u0003m!C.Z:tS:LG\u000fJ4sK\u0006$XM\u001d\u0013eK\u001a\fW\u000f\u001c;%c)\u0011q\tC\u0001\u0004Kb$\u0018\'B\u0012J\u0015.;eB\u0001\u000fK\u0013\t9\u0005\"\r\u0003#9!a%AB:je\u0016,X\u000eK\u0002\u0001{\u0001\u0003
   #9 = Utf8               toCodePoints
  #10 = Utf8               (I)Lorg/sireum/IS;
  #11 = Utf8               (I)Lorg/sireum/IS<Lorg/sireum/Z;Lorg/sireum/C;>;
  #12 = Utf8               c
  #13 = Utf8               org/sireum/conversions/C$
  #14 = Class              #13            // org/sireum/conversions/C$
  #15 = Utf8               MODULE$
  #16 = Utf8               Lorg/sireum/conversions/C$;
  #17 = NameAndType        #15:#16        // MODULE$:Lorg/sireum/conversions/C$;
  #18 = Fieldref           #14.#17        // org/sireum/conversions/C$.MODULE$:Lorg/sireum/conversions/C$;
  #19 = NameAndType        #9:#10         // toCodePoints:(I)Lorg/sireum/IS;
  #20 = Methodref          #14.#19        // org/sireum/conversions/C$.toCodePoints:(I)Lorg/sireum/IS;
  #21 = Utf8               I
  #22 = Utf8               toU32
  #23 = Utf8               (I)I
  #24 = NameAndType        #22:#23        // toU32:(I)I
  #25 = Methodref          #14.#24        // org/sireum/conversions/C$.toU32:(I)I
  #26 = Utf8               Code
  #27 = Utf8               LocalVariableTable
  #28 = Utf8               Signature
  #29 = Utf8               MethodParameters
  #30 = Utf8               SourceFile
  #31 = Utf8               RuntimeVisibleAnnotations
  #32 = Utf8               ScalaSig
{
  public static org.sireum.IS<org.sireum.Z, org.sireum.C> toCodePoints(int);
    descriptor: (I)Lorg/sireum/IS;
    flags: (0x0009) ACC_PUBLIC, ACC_STATIC
    Code:
      stack=2, locals=1, args_size=1
         0: getstatic     #18                 // Field org/sireum/conversions/C$.MODULE$:Lorg/sireum/conversions/C$;
         3: iload_0
         4: invokevirtual #20                 // Method org/sireum/conversions/C$.toCodePoints:(I)Lorg/sireum/IS;
         7: areturn
      LocalVariableTable:
        Start  Length  Slot  Name   Signature
            0       8     0     c   I
    Signature: #11                          // (I)Lorg/sireum/IS<Lorg/sireum/Z;Lorg/sireum/C;>;
    MethodParameters:
      Name                           Flags
      c                              final

  public static int toU32(int);
    descriptor: (I)I
    flags: (0x0009) ACC_PUBLIC, ACC_STATIC
    Code:
      stack=2, locals=1, args_size=1
         0: getstatic     #18                 // Field org/sireum/conversions/C$.MODULE$:Lorg/sireum/conversions/C$;
         3: iload_0
         4: invokevirtual #25                 // Method org/sireum/conversions/C$.toU32:(I)I
         7: ireturn
      LocalVariableTable:
        Start  Length  Slot  Name   Signature
            0       8     0     c   I
    MethodParameters:
      Name                           Flags
      c                              final
}
SourceFile: "conversions.scala"
RuntimeVisibleAnnotations:
  0: #6(#7=s#8)
    scala.reflect.ScalaSignature(
      bytes="\u0006\u00059;Q!\u0002\u0004\t\u000251Qa\u0004\u0004\t\u0002AAQaF\u0001\u0005\u0002aAQ!G\u0001\u0005\u0002iAQaJ\u0001\u0005\u0002!\n\u0011a\u0011\u0006\u0003\u000f!\t1bY8om\u0016\u00148/[8og*\u0011\u0011BC\u0001\u0007g&\u0014X-^7\u000b\u0003-\t1a\u001c:h\u0007\u0001\u0001\"AD\u0001\u000e\u0003\u0019\u0011\u0011aQ\n\u0003\u0003E\u0001\"AE\u000b\u000e\u0003MQ\u0011\u0001F\u0001\u0006g\u000e\fG.Y\u0005\u0003-M\u0011a!\u00118z%\u00164\u0017A\u0002\u001fj]&$h\bF\u0001\u000e\u0003\u0015!x.V\u001a3)\tYr\u0004\u0005\u0002\u001d;5\t\u0001\"\u0003\u0002\u001f\u0011\t\u0019Qk\r\u001a\t\u000b\u0001\u001a\u0001\u0019A\u0011\u0002\u0003\r\u0004\"\u0001\b\u0012\n\u0005=A\u0001FA\u0002%!\taR%\u0003\u0002\'\u0011\t!\u0001/\u001e:f\u00031!xnQ8eKB{\u0017N\u001c;t)\tI#\bE\u0002+i\u0005r!a\u000b\u001a\u000f\u00051\ndBA\u00171\u001b\u0005q#BA\u0018\r\u0003\u0019a$o\\8u}%\t1\"\u0003\u0002\n\u0015%\u00111\u0007C\u0001\ba\u0006\u001c7.Y4f\u0013\t)dGA\u0002J\'jK!a\u000e\u001d\u0003\u0019A\u000b7m[1hKR\u0013\u0018-\u001b;\u000b\u0005eB\u0011!\u0003\u0013j]R,\'O\\1m\u0011\u0015\u0001C\u00011\u0001\"Q\t!A\u0005K\u0002\u0002{\u0001\u0003\"\u0001\b \n\u0005}B!aA3yiF*1%\u0011#I\u000bB\u0011ADQ\u0005\u0003\u0007\"\u0011aa\u0015;sS:<\u0017BA#G\u0003m!C.Z:tS:LG\u000fJ4sK\u0006$XM\u001d\u0013eK\u001a\fW\u000f\u001c;%c)\u0011q\tC\u0001\u0004Kb$\u0018\'B\u0012J\u0015.;eB\u0001\u000fK\u0013\t9\u0005\"\r\u0003#9!a%AB:je\u0016,X\u000eK\u0002\u0001{\u0001\u0003"
    )
  ScalaSig: length = 0x3 (unknown attribute)
   05 02 00
