Classfile /Users/mw/Projects/slang-braindump/.jar/jar8/assemble/slang-braindump/assemble/content/org/sireum/conversions/F64.class
  Last modified May 29, 2022; size 1220 bytes
  SHA-256 checksum 02c993ba2b56e618c6fd1feb74a5cfc52ba4f8647f84a7b90f951082e93d4ee3
  Compiled from "conversions.scala"
public final class org.sireum.conversions.F64
  minor version: 0
  major version: 52
  flags: (0x0031) ACC_PUBLIC, ACC_FINAL, ACC_SUPER
  this_class: #2                          // org/sireum/conversions/F64
  super_class: #4                         // java/lang/Object
  interfaces: 0, fields: 0, methods: 4, attributes: 3
Constant pool:
   #1 = Utf8               org/sireum/conversions/F64
   #2 = Class              #1             // org/sireum/conversions/F64
   #3 = Utf8               java/lang/Object
   #4 = Class              #3             // java/lang/Object
   #5 = Utf8               conversions.scala
   #6 = Utf8               Lscala/reflect/ScalaSignature;
   #7 = Utf8               bytes
   #8 = Utf8               \u0006\u00055;Qa\u0002\u0005\t\u0002=1Q!\u0005\u0005\t\u0002IAQ!G\u0001\u0005\u0002iAQaG\u0001\u0005\u0002qAQ!K\u0001\u0005\u0002)BQ\u0001M\u0001\u0005\u0002EBQ\u0001N\u0001\u0005\u0002U\n1A\u0012\u001c5\u0015\tI!\"A\u0006d_:4XM]:j_:\u001c(BA\u0006\r\u0003\u0019\u0019\u0018N]3v[*\tQ\"A\u0002pe\u001e\u001c\u0001\u0001\u0005\u0002\u0011\u00035\t\u0001BA\u0002GmQ\u001a\"!A\n\u0011\u0005Q9R\"A\u000b\u000b\u0003Y\tQa]2bY\u0006L!\u0001G\u000b\u0003\r\u0005s\u0017PU3g\u0003\u0019a\u0014N\\5u}Q\tq\"A\u0002u_\n#\"!H\u0011\u0011\u0005yyR\"\u0001\u0006\n\u0005\u0001R!!\u0001\"\t\u000b\t\u001a\u0001\u0019A\u0012\u0002\u00039\u0004\"A\b\u0013\n\u0005EQ\u0001FA\u0002\'!\tqr%\u0003\u0002)\u0015\t!\u0001/\u001e:f\u0003!!xNU1x+Z\"DCA\u0016/!\tqB&\u0003\u0002.\u0015\t\u0019QK\u000e\u001b\t\u000b\t\"\u0001\u0019A\u0012)\u0005\u00111\u0013!\u0002;p\rZ\"DCA\u00123\u0011\u0015\u0011S\u00011\u0001$Q\t)a%A\u0002u_J#\"AN\u001d\u0011\u0005y9\u0014B\u0001\u001d\u000b\u0005\u0005\u0011\u0006\"\u0002\u0012\u0007\u0001\u0004\u0019\u0003F\u0001\u0004\'Q\r\tAh\u0010\t\u0003=uJ!A\u0010\u0006\u0003\u0007\u0015DH/M\u0003$\u0001\u000e;E\t\u0005\u0002\u001f\u0003&\u0011!I\u0003\u0002\u0007\'R\u0014\u0018N\\4\n\u0005\u0011+\u0015a\u0007\u0013mKN\u001c\u0018N\\5uI\u001d\u0014X-\u0019;fe\u0012\"WMZ1vYR$\u0013G\u0003\u0002G\u0015\u0005\u0019Q\r\u001f;2\u000b\rB\u0015J\u0013$\u000f\u0005yI\u0015B\u0001$\u000bc\u0011\u0011cDC&\u0003\rML\'/Z;nQ\r\u0001Ah\u0010
   #9 = Utf8               toR
  #10 = Utf8               (D)Lscala/math/BigDecimal;
  #11 = Utf8               n
  #12 = Utf8               org/sireum/conversions/F64$
  #13 = Class              #12            // org/sireum/conversions/F64$
  #14 = Utf8               MODULE$
  #15 = Utf8               Lorg/sireum/conversions/F64$;
  #16 = NameAndType        #14:#15        // MODULE$:Lorg/sireum/conversions/F64$;
  #17 = Fieldref           #13.#16        // org/sireum/conversions/F64$.MODULE$:Lorg/sireum/conversions/F64$;
  #18 = NameAndType        #9:#10         // toR:(D)Lscala/math/BigDecimal;
  #19 = Methodref          #13.#18        // org/sireum/conversions/F64$.toR:(D)Lscala/math/BigDecimal;
  #20 = Utf8               D
  #21 = Utf8               toF64
  #22 = Utf8               (D)D
  #23 = NameAndType        #21:#22        // toF64:(D)D
  #24 = Methodref          #13.#23        // org/sireum/conversions/F64$.toF64:(D)D
  #25 = Utf8               toRawU64
  #26 = Utf8               (D)J
  #27 = NameAndType        #25:#26        // toRawU64:(D)J
  #28 = Methodref          #13.#27        // org/sireum/conversions/F64$.toRawU64:(D)J
  #29 = Utf8               toB
  #30 = Utf8               (D)Z
  #31 = NameAndType        #29:#30        // toB:(D)Z
  #32 = Methodref          #13.#31        // org/sireum/conversions/F64$.toB:(D)Z
  #33 = Utf8               Code
  #34 = Utf8               LocalVariableTable
  #35 = Utf8               MethodParameters
  #36 = Utf8               SourceFile
  #37 = Utf8               RuntimeVisibleAnnotations
  #38 = Utf8               ScalaSig
{
  public static scala.math.BigDecimal toR(double);
    descriptor: (D)Lscala/math/BigDecimal;
    flags: (0x0009) ACC_PUBLIC, ACC_STATIC
    Code:
      stack=3, locals=2, args_size=1
         0: getstatic     #17                 // Field org/sireum/conversions/F64$.MODULE$:Lorg/sireum/conversions/F64$;
         3: dload_0
         4: invokevirtual #19                 // Method org/sireum/conversions/F64$.toR:(D)Lscala/math/BigDecimal;
         7: areturn
      LocalVariableTable:
        Start  Length  Slot  Name   Signature
            0       8     0     n   D
    MethodParameters:
      Name                           Flags
      n                              final

  public static double toF64(double);
    descriptor: (D)D
    flags: (0x0009) ACC_PUBLIC, ACC_STATIC
    Code:
      stack=3, locals=2, args_size=1
         0: getstatic     #17                 // Field org/sireum/conversions/F64$.MODULE$:Lorg/sireum/conversions/F64$;
         3: dload_0
         4: invokevirtual #24                 // Method org/sireum/conversions/F64$.toF64:(D)D
         7: dreturn
      LocalVariableTable:
        Start  Length  Slot  Name   Signature
            0       8     0     n   D
    MethodParameters:
      Name                           Flags
      n                              final

  public static long toRawU64(double);
    descriptor: (D)J
    flags: (0x0009) ACC_PUBLIC, ACC_STATIC
    Code:
      stack=3, locals=2, args_size=1
         0: getstatic     #17                 // Field org/sireum/conversions/F64$.MODULE$:Lorg/sireum/conversions/F64$;
         3: dload_0
         4: invokevirtual #28                 // Method org/sireum/conversions/F64$.toRawU64:(D)J
         7: lreturn
      LocalVariableTable:
        Start  Length  Slot  Name   Signature
            0       8     0     n   D
    MethodParameters:
      Name                           Flags
      n                              final

  public static boolean toB(double);
    descriptor: (D)Z
    flags: (0x0009) ACC_PUBLIC, ACC_STATIC
    Code:
      stack=3, locals=2, args_size=1
         0: getstatic     #17                 // Field org/sireum/conversions/F64$.MODULE$:Lorg/sireum/conversions/F64$;
         3: dload_0
         4: invokevirtual #32                 // Method org/sireum/conversions/F64$.toB:(D)Z
         7: ireturn
      LocalVariableTable:
        Start  Length  Slot  Name   Signature
            0       8     0     n   D
    MethodParameters:
      Name                           Flags
      n                              final
}
SourceFile: "conversions.scala"
RuntimeVisibleAnnotations:
  0: #6(#7=s#8)
    scala.reflect.ScalaSignature(
      bytes="\u0006\u00055;Qa\u0002\u0005\t\u0002=1Q!\u0005\u0005\t\u0002IAQ!G\u0001\u0005\u0002iAQaG\u0001\u0005\u0002qAQ!K\u0001\u0005\u0002)BQ\u0001M\u0001\u0005\u0002EBQ\u0001N\u0001\u0005\u0002U\n1A\u0012\u001c5\u0015\tI!\"A\u0006d_:4XM]:j_:\u001c(BA\u0006\r\u0003\u0019\u0019\u0018N]3v[*\tQ\"A\u0002pe\u001e\u001c\u0001\u0001\u0005\u0002\u0011\u00035\t\u0001BA\u0002GmQ\u001a\"!A\n\u0011\u0005Q9R\"A\u000b\u000b\u0003Y\tQa]2bY\u0006L!\u0001G\u000b\u0003\r\u0005s\u0017PU3g\u0003\u0019a\u0014N\\5u}Q\tq\"A\u0002u_\n#\"!H\u0011\u0011\u0005yyR\"\u0001\u0006\n\u0005\u0001R!!\u0001\"\t\u000b\t\u001a\u0001\u0019A\u0012\u0002\u00039\u0004\"A\b\u0013\n\u0005EQ\u0001FA\u0002\'!\tqr%\u0003\u0002)\u0015\t!\u0001/\u001e:f\u0003!!xNU1x+Z\"DCA\u0016/!\tqB&\u0003\u0002.\u0015\t\u0019QK\u000e\u001b\t\u000b\t\"\u0001\u0019A\u0012)\u0005\u00111\u0013!\u0002;p\rZ\"DCA\u00123\u0011\u0015\u0011S\u00011\u0001$Q\t)a%A\u0002u_J#\"AN\u001d\u0011\u0005y9\u0014B\u0001\u001d\u000b\u0005\u0005\u0011\u0006\"\u0002\u0012\u0007\u0001\u0004\u0019\u0003F\u0001\u0004\'Q\r\tAh\u0010\t\u0003=uJ!A\u0010\u0006\u0003\u0007\u0015DH/M\u0003$\u0001\u000e;E\t\u0005\u0002\u001f\u0003&\u0011!I\u0003\u0002\u0007\'R\u0014\u0018N\\4\n\u0005\u0011+\u0015a\u0007\u0013mKN\u001c\u0018N\\5uI\u001d\u0014X-\u0019;fe\u0012\"WMZ1vYR$\u0013G\u0003\u0002G\u0015\u0005\u0019Q\r\u001f;2\u000b\rB\u0015J\u0013$\u000f\u0005yI\u0015B\u0001$\u000bc\u0011\u0011cDC&\u0003\rML\'/Z;nQ\r\u0001Ah\u0010"
    )
  ScalaSig: length = 0x3 (unknown attribute)
   05 02 00
