Classfile /Users/mw/Projects/slang-braindump/.jar/jar8/assemble/slang-braindump/assemble/content/org/sireum/conversions/ISB.class
  Last modified May 29, 2022; size 1610 bytes
  SHA-256 checksum 423922a2b59e5430445b82d89b02751f55d2ee4b5e7fb39b7c85979679958e51
  Compiled from "conversions.scala"
public final class org.sireum.conversions.ISB
  minor version: 0
  major version: 52
  flags: (0x0031) ACC_PUBLIC, ACC_FINAL, ACC_SUPER
  this_class: #2                          // org/sireum/conversions/ISB
  super_class: #4                         // java/lang/Object
  interfaces: 0, fields: 0, methods: 3, attributes: 3
Constant pool:
   #1 = Utf8               org/sireum/conversions/ISB
   #2 = Class              #1             // org/sireum/conversions/ISB
   #3 = Utf8               java/lang/Object
   #4 = Class              #3             // java/lang/Object
   #5 = Utf8               conversions.scala
   #6 = Utf8               Lscala/reflect/ScalaSignature;
   #7 = Utf8               bytes
   #8 = Utf8               \u0006\u0005};QAB\u0004\t\u000291Q\u0001E\u0004\t\u0002EAQ\u0001G\u0001\u0005\u0002eAQAG\u0001\u0005\u0002mAQ!O\u0001\u0005\u0002iBQAQ\u0001\u0005\u0002\r\u000b1!S*C\u0015\tA\u0011\"A\u0006d_:4XM]:j_:\u001c(B\u0001\u0006\f\u0003\u0019\u0019\u0018N]3v[*\tA\"A\u0002pe\u001e\u001c\u0001\u0001\u0005\u0002\u0010\u00035\tqAA\u0002J\'\n\u001b\"!\u0001\n\u0011\u0005M1R\"\u0001\u000b\u000b\u0003U\tQa]2bY\u0006L!a\u0006\u000b\u0003\r\u0005s\u0017PU3g\u0003\u0019a\u0014N\\5u}Q\ta\"\u0001\u0005ge>l\u0017jU+9+\ta2\u0005\u0006\u0002\u001e_A!adH\u0011-\u001b\u0005I\u0011B\u0001\u0011\n\u0005\tI5\u000b\u0005\u0002#G1\u0001A!\u0002\u0013\u0004\u0005\u0004)#!A%\u0012\u0005\u0019J\u0003CA\n(\u0013\tACCA\u0004O_RD\u0017N\\4\u0011\u0005MQ\u0013BA\u0016\u0015\u0005\r\te.\u001f\t\u0003=5J!AL\u0005\u0003\u0003\tCQ\u0001M\u0002A\u0002E\n\u0011a\u001d\t\u0005=}\t#\u0007\u0005\u0002\u001fg%\u0011A\'\u0003\u0002\u0003+bB#a\u0001\u001c\u0011\u0005y9\u0014B\u0001\u001d\n\u0005\u0011\u0001XO]3\u0002\rQ|\u0017jU+9+\tYd\b\u0006\u0002=\u007fA!adH\u001f3!\t\u0011c\bB\u0003%\t\t\u0007Q\u0005C\u00031\t\u0001\u0007\u0001\t\u0005\u0003\u001f?ub\u0003F\u0001\u00037\u0003\u0019!x.T*VqU\u0011A)\u0013\u000b\u0003\u000b*\u0003BA\b$Ie%\u0011q)\u0003\u0002\u0003\u001bN\u0003\"AI%\u0005\u000b\u0011*!\u0019A\u0013\t\u000bA*\u0001\u0019A&\u0011\tyy\u0002\n\f\u0015\u0003\u000bYB3!\u0001(R!\tqr*\u0003\u0002Q\u0013\t\u0019Q\r\u001f;2\u000b\r\u0012V+\u0017,\u0011\u0005y\u0019\u0016B\u0001+\n\u0005\u0019\u0019FO]5oO&\u0011akV\u0001\u001cI1,7o]5oSR$sM]3bi\u0016\u0014H\u0005Z3gCVdG\u000fJ\u0019\u000b\u0005aK\u0011aA3yiF*1EW.]1:\u0011adW\u0005\u00031&\tDA\t\u0010\n;\n11/\u001b:fk6D3\u0001\u0001(R\u0001
   #9 = Utf8               toMSU8
  #10 = Utf8               (Lorg/sireum/IS;)Lorg/sireum/MS;
  #11 = Utf8               <I:Ljava/lang/Object;>(Lorg/sireum/IS<TI;Lorg/sireum/B;>;)Lorg/sireum/MS<TI;Lorg/sireum/U8;>;
  #12 = Utf8               s
  #13 = Utf8               org/sireum/conversions/ISB$
  #14 = Class              #13            // org/sireum/conversions/ISB$
  #15 = Utf8               MODULE$
  #16 = Utf8               Lorg/sireum/conversions/ISB$;
  #17 = NameAndType        #15:#16        // MODULE$:Lorg/sireum/conversions/ISB$;
  #18 = Fieldref           #14.#17        // org/sireum/conversions/ISB$.MODULE$:Lorg/sireum/conversions/ISB$;
  #19 = NameAndType        #9:#10         // toMSU8:(Lorg/sireum/IS;)Lorg/sireum/MS;
  #20 = Methodref          #14.#19        // org/sireum/conversions/ISB$.toMSU8:(Lorg/sireum/IS;)Lorg/sireum/MS;
  #21 = Utf8               Lorg/sireum/IS;
  #22 = Utf8               toISU8
  #23 = Utf8               (Lorg/sireum/IS;)Lorg/sireum/IS;
  #24 = Utf8               <I:Ljava/lang/Object;>(Lorg/sireum/IS<TI;Lorg/sireum/B;>;)Lorg/sireum/IS<TI;Lorg/sireum/U8;>;
  #25 = NameAndType        #22:#23        // toISU8:(Lorg/sireum/IS;)Lorg/sireum/IS;
  #26 = Methodref          #14.#25        // org/sireum/conversions/ISB$.toISU8:(Lorg/sireum/IS;)Lorg/sireum/IS;
  #27 = Utf8               fromISU8
  #28 = Utf8               <I:Ljava/lang/Object;>(Lorg/sireum/IS<TI;Lorg/sireum/U8;>;)Lorg/sireum/IS<TI;Lorg/sireum/B;>;
  #29 = NameAndType        #27:#23        // fromISU8:(Lorg/sireum/IS;)Lorg/sireum/IS;
  #30 = Methodref          #14.#29        // org/sireum/conversions/ISB$.fromISU8:(Lorg/sireum/IS;)Lorg/sireum/IS;
  #31 = Utf8               Code
  #32 = Utf8               LocalVariableTable
  #33 = Utf8               Signature
  #34 = Utf8               MethodParameters
  #35 = Utf8               SourceFile
  #36 = Utf8               RuntimeVisibleAnnotations
  #37 = Utf8               ScalaSig
{
  public static <I extends java.lang.Object> org.sireum.MS<I, org.sireum.U8> toMSU8(org.sireum.IS<I, org.sireum.B>);
    descriptor: (Lorg/sireum/IS;)Lorg/sireum/MS;
    flags: (0x0009) ACC_PUBLIC, ACC_STATIC
    Code:
      stack=2, locals=1, args_size=1
         0: getstatic     #18                 // Field org/sireum/conversions/ISB$.MODULE$:Lorg/sireum/conversions/ISB$;
         3: aload_0
         4: invokevirtual #20                 // Method org/sireum/conversions/ISB$.toMSU8:(Lorg/sireum/IS;)Lorg/sireum/MS;
         7: areturn
      LocalVariableTable:
        Start  Length  Slot  Name   Signature
            0       8     0     s   Lorg/sireum/IS;
    Signature: #11                          // <I:Ljava/lang/Object;>(Lorg/sireum/IS<TI;Lorg/sireum/B;>;)Lorg/sireum/MS<TI;Lorg/sireum/U8;>;
    MethodParameters:
      Name                           Flags
      s                              final

  public static <I extends java.lang.Object> org.sireum.IS<I, org.sireum.U8> toISU8(org.sireum.IS<I, org.sireum.B>);
    descriptor: (Lorg/sireum/IS;)Lorg/sireum/IS;
    flags: (0x0009) ACC_PUBLIC, ACC_STATIC
    Code:
      stack=2, locals=1, args_size=1
         0: getstatic     #18                 // Field org/sireum/conversions/ISB$.MODULE$:Lorg/sireum/conversions/ISB$;
         3: aload_0
         4: invokevirtual #26                 // Method org/sireum/conversions/ISB$.toISU8:(Lorg/sireum/IS;)Lorg/sireum/IS;
         7: areturn
      LocalVariableTable:
        Start  Length  Slot  Name   Signature
            0       8     0     s   Lorg/sireum/IS;
    Signature: #24                          // <I:Ljava/lang/Object;>(Lorg/sireum/IS<TI;Lorg/sireum/B;>;)Lorg/sireum/IS<TI;Lorg/sireum/U8;>;
    MethodParameters:
      Name                           Flags
      s                              final

  public static <I extends java.lang.Object> org.sireum.IS<I, org.sireum.B> fromISU8(org.sireum.IS<I, org.sireum.U8>);
    descriptor: (Lorg/sireum/IS;)Lorg/sireum/IS;
    flags: (0x0009) ACC_PUBLIC, ACC_STATIC
    Code:
      stack=2, locals=1, args_size=1
         0: getstatic     #18                 // Field org/sireum/conversions/ISB$.MODULE$:Lorg/sireum/conversions/ISB$;
         3: aload_0
         4: invokevirtual #30                 // Method org/sireum/conversions/ISB$.fromISU8:(Lorg/sireum/IS;)Lorg/sireum/IS;
         7: areturn
      LocalVariableTable:
        Start  Length  Slot  Name   Signature
            0       8     0     s   Lorg/sireum/IS;
    Signature: #28                          // <I:Ljava/lang/Object;>(Lorg/sireum/IS<TI;Lorg/sireum/U8;>;)Lorg/sireum/IS<TI;Lorg/sireum/B;>;
    MethodParameters:
      Name                           Flags
      s                              final
}
SourceFile: "conversions.scala"
RuntimeVisibleAnnotations:
  0: #6(#7=s#8)
    scala.reflect.ScalaSignature(
      bytes="\u0006\u0005};QAB\u0004\t\u000291Q\u0001E\u0004\t\u0002EAQ\u0001G\u0001\u0005\u0002eAQAG\u0001\u0005\u0002mAQ!O\u0001\u0005\u0002iBQAQ\u0001\u0005\u0002\r\u000b1!S*C\u0015\tA\u0011\"A\u0006d_:4XM]:j_:\u001c(B\u0001\u0006\f\u0003\u0019\u0019\u0018N]3v[*\tA\"A\u0002pe\u001e\u001c\u0001\u0001\u0005\u0002\u0010\u00035\tqAA\u0002J\'\n\u001b\"!\u0001\n\u0011\u0005M1R\"\u0001\u000b\u000b\u0003U\tQa]2bY\u0006L!a\u0006\u000b\u0003\r\u0005s\u0017PU3g\u0003\u0019a\u0014N\\5u}Q\ta\"\u0001\u0005ge>l\u0017jU+9+\ta2\u0005\u0006\u0002\u001e_A!adH\u0011-\u001b\u0005I\u0011B\u0001\u0011\n\u0005\tI5\u000b\u0005\u0002#G1\u0001A!\u0002\u0013\u0004\u0005\u0004)#!A%\u0012\u0005\u0019J\u0003CA\n(\u0013\tACCA\u0004O_RD\u0017N\\4\u0011\u0005MQ\u0013BA\u0016\u0015\u0005\r\te.\u001f\t\u0003=5J!AL\u0005\u0003\u0003\tCQ\u0001M\u0002A\u0002E\n\u0011a\u001d\t\u0005=}\t#\u0007\u0005\u0002\u001fg%\u0011A\'\u0003\u0002\u0003+bB#a\u0001\u001c\u0011\u0005y9\u0014B\u0001\u001d\n\u0005\u0011\u0001XO]3\u0002\rQ|\u0017jU+9+\tYd\b\u0006\u0002=\u007fA!adH\u001f3!\t\u0011c\bB\u0003%\t\t\u0007Q\u0005C\u00031\t\u0001\u0007\u0001\t\u0005\u0003\u001f?ub\u0003F\u0001\u00037\u0003\u0019!x.T*VqU\u0011A)\u0013\u000b\u0003\u000b*\u0003BA\b$Ie%\u0011q)\u0003\u0002\u0003\u001bN\u0003\"AI%\u0005\u000b\u0011*!\u0019A\u0013\t\u000bA*\u0001\u0019A&\u0011\tyy\u0002\n\f\u0015\u0003\u000bYB3!\u0001(R!\tqr*\u0003\u0002Q\u0013\t\u0019Q\r\u001f;2\u000b\r\u0012V+\u0017,\u0011\u0005y\u0019\u0016B\u0001+\n\u0005\u0019\u0019FO]5oO&\u0011akV\u0001\u001cI1,7o]5oSR$sM]3bi\u0016\u0014H\u0005Z3gCVdG\u000fJ\u0019\u000b\u0005aK\u0011aA3yiF*1EW.]1:\u0011adW\u0005\u00031&\tDA\t\u0010\n;\n11/\u001b:fk6D3\u0001\u0001(R\u0001"
    )
  ScalaSig: length = 0x3 (unknown attribute)
   05 02 00
