Classfile /Users/mw/Projects/slang-braindump/.jar/jar8/assemble/slang-braindump/assemble/content/org/sireum/conversions/ISB_Ext.class
  Last modified May 29, 2022; size 1629 bytes
  SHA-256 checksum d85b9ebb49bd6710aa4eb79d3b2dad7c6c623f3d7be621737f28791490e8b271
  Compiled from "extension.scala"
public final class org.sireum.conversions.ISB_Ext
  minor version: 0
  major version: 52
  flags: (0x0031) ACC_PUBLIC, ACC_FINAL, ACC_SUPER
  this_class: #2                          // org/sireum/conversions/ISB_Ext
  super_class: #4                         // java/lang/Object
  interfaces: 0, fields: 0, methods: 3, attributes: 3
Constant pool:
   #1 = Utf8               org/sireum/conversions/ISB_Ext
   #2 = Class              #1             // org/sireum/conversions/ISB_Ext
   #3 = Utf8               java/lang/Object
   #4 = Class              #3             // java/lang/Object
   #5 = Utf8               extension.scala
   #6 = Utf8               Lscala/reflect/ScalaSignature;
   #7 = Utf8               bytes
   #8 = Utf8               \u0006\u0005};QAB\u0004\t\u000291Q\u0001E\u0004\t\u0002EAQ\u0001G\u0001\u0005\u0002eAQAG\u0001\u0005\u0002mAQ!O\u0001\u0005\u0002iBQAQ\u0001\u0005\u0002\r\u000bq!S*C?\u0016CHO\u0003\u0002\t\u0013\u0005Y1m\u001c8wKJ\u001c\u0018n\u001c8t\u0015\tQ1\"\u0001\u0004tSJ,W/\u001c\u0006\u0002\u0019\u0005\u0019qN]4\u0004\u0001A\u0011q\"A\u0007\u0002\u000f\t9\u0011j\u0015\"`\u000bb$8CA\u0001\u0013!\t\u0019b#D\u0001\u0015\u0015\u0005)\u0012!B:dC2\f\u0017BA\f\u0015\u0005\u0019\te.\u001f*fM\u00061A(\u001b8jiz\"\u0012AD\u0001\tMJ|W.S*VqU\u0011Ad\t\u000b\u0003;=\u0002BAH\u0010\"Y5\t\u0011\"\u0003\u0002!\u0013\t\u0011\u0011j\u0015\t\u0003E\rb\u0001\u0001B\u0003%\u0007\t\u0007QEA\u0001J#\t1\u0013\u0006\u0005\u0002\u0014O%\u0011\u0001\u0006\u0006\u0002\b\u001d>$\b.\u001b8h!\t\u0019\"&\u0003\u0002,)\t\u0019\u0011I\\=\u0011\u0005yi\u0013B\u0001\u0018\n\u0005\u0005\u0011\u0005\"\u0002\u0019\u0004\u0001\u0004\t\u0014!A:\u0011\tyy\u0012E\r\t\u0003=MJ!\u0001N\u0005\u0003\u0005UC\u0004FA\u00027!\tqr\'\u0003\u00029\u0013\t!\u0001/\u001e:f\u0003\u0019!x.S*VqU\u00111H\u0010\u000b\u0003y}\u0002BAH\u0010>eA\u0011!E\u0010\u0003\u0006I\u0011\u0011\r!\n\u0005\u0006a\u0011\u0001\r\u0001\u0011\t\u0005=}iD\u0006\u000b\u0002\u0005m\u00051Ao\\\'T+b*\"\u0001R%\u0015\u0005\u0015S\u0005\u0003\u0002\u0010G\u0011JJ!aR\u0005\u0003\u00055\u001b\u0006C\u0001\u0012J\t\u0015!SA1\u0001&\u0011\u0015\u0001T\u00011\u0001L!\u0011qr\u0004\u0013\u0017)\u0005\u00151\u0004fA\u0001O#B\u0011adT\u0005\u0003!&\u00111!\u001a=uc\u0015\u0019#+V-W!\tq2+\u0003\u0002U\u0013\t11\u000b\u001e:j]\u001eL!AV,\u00027\u0011bWm]:j]&$He\u001a:fCR,\'\u000f\n3fM\u0006,H\u000e\u001e\u00132\u0015\tA\u0016\"A\u0002fqR\fTa\t.\\9bs!AH.\n\u0005aK\u0011\u0007\u0002\u0012\u001f\u0013u\u0013aa]5sKVl\u0007f\u0001\u0001O#\u0002
   #9 = Utf8               toMSU8
  #10 = Utf8               (Lorg/sireum/IS;)Lorg/sireum/MS;
  #11 = Utf8               <I:Ljava/lang/Object;>(Lorg/sireum/IS<TI;Lorg/sireum/B;>;)Lorg/sireum/MS<TI;Lorg/sireum/U8;>;
  #12 = Utf8               s
  #13 = Utf8               org/sireum/conversions/ISB_Ext$
  #14 = Class              #13            // org/sireum/conversions/ISB_Ext$
  #15 = Utf8               MODULE$
  #16 = Utf8               Lorg/sireum/conversions/ISB_Ext$;
  #17 = NameAndType        #15:#16        // MODULE$:Lorg/sireum/conversions/ISB_Ext$;
  #18 = Fieldref           #14.#17        // org/sireum/conversions/ISB_Ext$.MODULE$:Lorg/sireum/conversions/ISB_Ext$;
  #19 = NameAndType        #9:#10         // toMSU8:(Lorg/sireum/IS;)Lorg/sireum/MS;
  #20 = Methodref          #14.#19        // org/sireum/conversions/ISB_Ext$.toMSU8:(Lorg/sireum/IS;)Lorg/sireum/MS;
  #21 = Utf8               Lorg/sireum/IS;
  #22 = Utf8               toISU8
  #23 = Utf8               (Lorg/sireum/IS;)Lorg/sireum/IS;
  #24 = Utf8               <I:Ljava/lang/Object;>(Lorg/sireum/IS<TI;Lorg/sireum/B;>;)Lorg/sireum/IS<TI;Lorg/sireum/U8;>;
  #25 = NameAndType        #22:#23        // toISU8:(Lorg/sireum/IS;)Lorg/sireum/IS;
  #26 = Methodref          #14.#25        // org/sireum/conversions/ISB_Ext$.toISU8:(Lorg/sireum/IS;)Lorg/sireum/IS;
  #27 = Utf8               fromISU8
  #28 = Utf8               <I:Ljava/lang/Object;>(Lorg/sireum/IS<TI;Lorg/sireum/U8;>;)Lorg/sireum/IS<TI;Lorg/sireum/B;>;
  #29 = NameAndType        #27:#23        // fromISU8:(Lorg/sireum/IS;)Lorg/sireum/IS;
  #30 = Methodref          #14.#29        // org/sireum/conversions/ISB_Ext$.fromISU8:(Lorg/sireum/IS;)Lorg/sireum/IS;
  #31 = Utf8               Code
  #32 = Utf8               LocalVariableTable
  #33 = Utf8               Signature
  #34 = Utf8               MethodParameters
  #35 = Utf8               SourceFile
  #36 = Utf8               RuntimeVisibleAnnotations
  #37 = Utf8               ScalaSig
{
  public static <I extends java.lang.Object> org.sireum.MS<I, org.sireum.U8> toMSU8(org.sireum.IS<I, org.sireum.B>);
    descriptor: (Lorg/sireum/IS;)Lorg/sireum/MS;
    flags: (0x0009) ACC_PUBLIC, ACC_STATIC
    Code:
      stack=2, locals=1, args_size=1
         0: getstatic     #18                 // Field org/sireum/conversions/ISB_Ext$.MODULE$:Lorg/sireum/conversions/ISB_Ext$;
         3: aload_0
         4: invokevirtual #20                 // Method org/sireum/conversions/ISB_Ext$.toMSU8:(Lorg/sireum/IS;)Lorg/sireum/MS;
         7: areturn
      LocalVariableTable:
        Start  Length  Slot  Name   Signature
            0       8     0     s   Lorg/sireum/IS;
    Signature: #11                          // <I:Ljava/lang/Object;>(Lorg/sireum/IS<TI;Lorg/sireum/B;>;)Lorg/sireum/MS<TI;Lorg/sireum/U8;>;
    MethodParameters:
      Name                           Flags
      s                              final

  public static <I extends java.lang.Object> org.sireum.IS<I, org.sireum.U8> toISU8(org.sireum.IS<I, org.sireum.B>);
    descriptor: (Lorg/sireum/IS;)Lorg/sireum/IS;
    flags: (0x0009) ACC_PUBLIC, ACC_STATIC
    Code:
      stack=2, locals=1, args_size=1
         0: getstatic     #18                 // Field org/sireum/conversions/ISB_Ext$.MODULE$:Lorg/sireum/conversions/ISB_Ext$;
         3: aload_0
         4: invokevirtual #26                 // Method org/sireum/conversions/ISB_Ext$.toISU8:(Lorg/sireum/IS;)Lorg/sireum/IS;
         7: areturn
      LocalVariableTable:
        Start  Length  Slot  Name   Signature
            0       8     0     s   Lorg/sireum/IS;
    Signature: #24                          // <I:Ljava/lang/Object;>(Lorg/sireum/IS<TI;Lorg/sireum/B;>;)Lorg/sireum/IS<TI;Lorg/sireum/U8;>;
    MethodParameters:
      Name                           Flags
      s                              final

  public static <I extends java.lang.Object> org.sireum.IS<I, org.sireum.B> fromISU8(org.sireum.IS<I, org.sireum.U8>);
    descriptor: (Lorg/sireum/IS;)Lorg/sireum/IS;
    flags: (0x0009) ACC_PUBLIC, ACC_STATIC
    Code:
      stack=2, locals=1, args_size=1
         0: getstatic     #18                 // Field org/sireum/conversions/ISB_Ext$.MODULE$:Lorg/sireum/conversions/ISB_Ext$;
         3: aload_0
         4: invokevirtual #30                 // Method org/sireum/conversions/ISB_Ext$.fromISU8:(Lorg/sireum/IS;)Lorg/sireum/IS;
         7: areturn
      LocalVariableTable:
        Start  Length  Slot  Name   Signature
            0       8     0     s   Lorg/sireum/IS;
    Signature: #28                          // <I:Ljava/lang/Object;>(Lorg/sireum/IS<TI;Lorg/sireum/U8;>;)Lorg/sireum/IS<TI;Lorg/sireum/B;>;
    MethodParameters:
      Name                           Flags
      s                              final
}
SourceFile: "extension.scala"
RuntimeVisibleAnnotations:
  0: #6(#7=s#8)
    scala.reflect.ScalaSignature(
      bytes="\u0006\u0005};QAB\u0004\t\u000291Q\u0001E\u0004\t\u0002EAQ\u0001G\u0001\u0005\u0002eAQAG\u0001\u0005\u0002mAQ!O\u0001\u0005\u0002iBQAQ\u0001\u0005\u0002\r\u000bq!S*C?\u0016CHO\u0003\u0002\t\u0013\u0005Y1m\u001c8wKJ\u001c\u0018n\u001c8t\u0015\tQ1\"\u0001\u0004tSJ,W/\u001c\u0006\u0002\u0019\u0005\u0019qN]4\u0004\u0001A\u0011q\"A\u0007\u0002\u000f\t9\u0011j\u0015\"`\u000bb$8CA\u0001\u0013!\t\u0019b#D\u0001\u0015\u0015\u0005)\u0012!B:dC2\f\u0017BA\f\u0015\u0005\u0019\te.\u001f*fM\u00061A(\u001b8jiz\"\u0012AD\u0001\tMJ|W.S*VqU\u0011Ad\t\u000b\u0003;=\u0002BAH\u0010\"Y5\t\u0011\"\u0003\u0002!\u0013\t\u0011\u0011j\u0015\t\u0003E\rb\u0001\u0001B\u0003%\u0007\t\u0007QEA\u0001J#\t1\u0013\u0006\u0005\u0002\u0014O%\u0011\u0001\u0006\u0006\u0002\b\u001d>$\b.\u001b8h!\t\u0019\"&\u0003\u0002,)\t\u0019\u0011I\\=\u0011\u0005yi\u0013B\u0001\u0018\n\u0005\u0005\u0011\u0005\"\u0002\u0019\u0004\u0001\u0004\t\u0014!A:\u0011\tyy\u0012E\r\t\u0003=MJ!\u0001N\u0005\u0003\u0005UC\u0004FA\u00027!\tqr\'\u0003\u00029\u0013\t!\u0001/\u001e:f\u0003\u0019!x.S*VqU\u00111H\u0010\u000b\u0003y}\u0002BAH\u0010>eA\u0011!E\u0010\u0003\u0006I\u0011\u0011\r!\n\u0005\u0006a\u0011\u0001\r\u0001\u0011\t\u0005=}iD\u0006\u000b\u0002\u0005m\u00051Ao\\\'T+b*\"\u0001R%\u0015\u0005\u0015S\u0005\u0003\u0002\u0010G\u0011JJ!aR\u0005\u0003\u00055\u001b\u0006C\u0001\u0012J\t\u0015!SA1\u0001&\u0011\u0015\u0001T\u00011\u0001L!\u0011qr\u0004\u0013\u0017)\u0005\u00151\u0004fA\u0001O#B\u0011adT\u0005\u0003!&\u00111!\u001a=uc\u0015\u0019#+V-W!\tq2+\u0003\u0002U\u0013\t11\u000b\u001e:j]\u001eL!AV,\u00027\u0011bWm]:j]&$He\u001a:fCR,\'\u000f\n3fM\u0006,H\u000e\u001e\u00132\u0015\tA\u0016\"A\u0002fqR\fTa\t.\\9bs!AH.\n\u0005aK\u0011\u0007\u0002\u0012\u001f\u0013u\u0013aa]5sKVl\u0007f\u0001\u0001O#\u0002"
    )
  ScalaSig: length = 0x3 (unknown attribute)
   05 02 00
