Classfile /Users/mw/Projects/slang-braindump/.jar/jar8/assemble/slang-braindump/assemble/content/org/sireum/conversions/N.class
  Last modified May 29, 2022; size 3466 bytes
  SHA-256 checksum 1eb53756be7b9f7de42a3210eff71d886ac697ed5a854bfca9454caf6a7d7238
  Compiled from "conversions.scala"
public final class org.sireum.conversions.N
  minor version: 0
  major version: 52
  flags: (0x0031) ACC_PUBLIC, ACC_FINAL, ACC_SUPER
  this_class: #2                          // org/sireum/conversions/N
  super_class: #4                         // java/lang/Object
  interfaces: 0, fields: 0, methods: 20, attributes: 3
Constant pool:
   #1 = Utf8               org/sireum/conversions/N
   #2 = Class              #1             // org/sireum/conversions/N
   #3 = Utf8               java/lang/Object
   #4 = Class              #3             // java/lang/Object
   #5 = Utf8               conversions.scala
   #6 = Utf8               Lscala/reflect/ScalaSignature;
   #7 = Utf8               bytes
   #8 = Utf8               \u0006\u0005\u0005mu!B\f\u0019\u0011\u0003yb!B\u0011\u0019\u0011\u0003\u0011\u0003\"B\u0015\u0002\t\u0003Q\u0003\"B\u0016\u0002\t\u0003a\u0003\"B\u001d\u0002\t\u0003Q\u0004\"\u0002!\u0002\t\u0003\t\u0005\"B$\u0002\t\u0003A\u0005\"\u0002(\u0002\t\u0003y\u0005\"B+\u0002\t\u00031\u0006\"\u0002/\u0002\t\u0003i\u0006\"\u00021\u0002\t\u0003\t\u0007\"B4\u0002\t\u0003A\u0007\"\u00028\u0002\t\u0003y\u0007\"B;\u0002\t\u00031\b\"\u0002?\u0002\t\u0003i\bbBA\u0004\u0003\u0011\u0005\u0011\u0011\u0002\u0005\b\u0003+\tA\u0011AA\f\u0011\u001d\t\u0019#\u0001C\u0001\u0003KAq!!\r\u0002\t\u0003\t\u0019\u0004C\u0004\u0002@\u0005!\t!!\u0011\t\u000f\u00055\u0013\u0001\"\u0001\u0002P!9\u00111L\u0001\u0005\u0002\u0005u\u0003bBA5\u0003\u0011\u0005\u00111N\u0001\u0002\u001d*\u0011\u0011DG\u0001\fG>tg/\u001a:tS>t7O\u0003\u0002\u001c9\u000511/\u001b:fk6T\u0011!H\u0001\u0004_J<7\u0001\u0001\t\u0003A\u0005i\u0011\u0001\u0007\u0002\u0002\u001dN\u0011\u0011a\t\t\u0003I\u001dj\u0011!\n\u0006\u0002M\u0005)1oY1mC&\u0011\u0001&\n\u0002\u0007\u0003:L(+\u001a4\u0002\rqJg.\u001b;?)\u0005y\u0012a\u0001;p\u0005R\u0011Q&\r\t\u0003]=j\u0011AG\u0005\u0003ai\u0011\u0011A\u0011\u0005\u0006e\r\u0001\raM\u0001\u0002]B\u0011a\u0006N\u0005\u0003CiA#a\u0001\u001c\u0011\u00059:\u0014B\u0001\u001d\u001b\u0005\u0011\u0001XO]3\u0002\u0007Q|\'\f\u0006\u0002<}A\u0011a\u0006P\u0005\u0003{i\u0011\u0011A\u0017\u0005\u0006e\u0011\u0001\ra\r\u0015\u0003\tY\nA\u0001^8[qQ\u0011!)\u0012\t\u0003]\rK!\u0001\u0012\u000e\u0003\u0005iC\u0004\"\u0002\u001a\u0006\u0001\u0004\u0019\u0004FA\u00037\u0003\u0015!xNW\u00197)\tIE\n\u0005\u0002/\u0015&\u00111J\u0007\u0002\u00045F2\u0004\"\u0002\u001a\u0007\u0001\u0004\u0019\u0004F\u0001\u00047\u0003\u0015!xNW\u001a3)\t\u00016\u000b\u0005\u0002/#&\u0011!K\u0007\u0002\u00045N\u0012\u0004\"\u0002\u001a\b\u0001\u0004\u0019\u0004FA\u00047\u0003\u0015!xN\u0017\u001c5)\t9&\f\u0005\u0002/1&\u0011\u0011L\u0007\u0002\u00045Z\"\u0004\"\u0002\u001a\t\u0001\u0004\u0019\u0004F\u0001\u00057\u0003\r!xN\u0014\u000b\u0003gyCQAM\u0005A\u0002MB#!\u0003\u001c\u0002\tQ|g\n\u000f\u000b\u0003E\u0016\u0004\"AL2\n\u0005\u0011T\"A\u0001(9\u0011\u0015\u0011$\u00021\u00014Q\tQa\'A\u0003u_:\u000bd\u0007\u0006\u0002jYB\u0011aF[\u0005\u0003Wj\u00111AT\u00197\u0011\u0015\u00114\u00021\u00014Q\tYa\'A\u0003u_:\u001b$\u0007\u0006\u0002qgB\u0011a&]\u0005\u0003ej\u00111AT\u001a3\u0011\u0015\u0011D\u00021\u00014Q\taa\'A\u0003u_:3D\u0007\u0006\u0002xuB\u0011a\u0006_\u0005\u0003sj\u00111A\u0014\u001c5\u0011\u0015\u0011T\u00021\u00014Q\tia\'\u0001\u0003u_NCDc\u0001@\u0002\u0004A\u0011af`\u0005\u0004\u0003\u0003Q\"AA*9\u0011\u0015\u0011d\u00021\u00014Q\tqa\'A\u0003u_N\u000bd\u0007\u0006\u0003\u0002\f\u0005E\u0001c\u0001\u0018\u0002\u000e%\u0019\u0011q\u0002\u000e\u0003\u0007M\u000bd\u0007C\u00033\u001f\u0001\u00071\u0007\u000b\u0002\u0010m\u0005)Ao\\*4eQ!\u0011\u0011DA\u0010!\rq\u00131D\u0005\u0004\u0003;Q\"aA*4e!)!\u0007\u0005a\u0001g!\u0012\u0001CN\u0001\u0006i>\u001cf\u0007\u000e\u000b\u0005\u0003O\ti\u0003E\u0002/\u0003SI1!a\u000b\u001b\u0005\r\u0019f\u0007\u000e\u0005\u0006eE\u0001\ra\r\u0015\u0003#Y\nA\u0001^8VqQ!\u0011QGA\u001e!\rq\u0013qG\u0005\u0004\u0003sQ\"AA+9\u0011\u0015\u0011$\u00031\u00014Q\t\u0011b\'A\u0003u_V\u000bd\u0007\u0006\u0003\u0002D\u0005%\u0003c\u0001\u0018\u0002F%\u0019\u0011q\t\u000e\u0003\u0007U\u000bd\u0007C\u00033\'\u0001\u00071\u0007\u000b\u0002\u0014m\u0005)Ao\\+4eQ!\u0011\u0011KA,!\rq\u00131K\u0005\u0004\u0003+R\"aA+4e!)!\u0007\u0006a\u0001g!\u0012ACN\u0001\u0006i>,f\u0007\u000e\u000b\u0005\u0003?\n)\u0007E\u0002/\u0003CJ1!a\u0019\u001b\u0005\r)f\u0007\u000e\u0005\u0006eU\u0001\ra\r\u0015\u0003+Y\n1\u0001^8S)\u0011\ti\'a\u001d\u0011\u00079\ny\'C\u0002\u0002ri\u0011\u0011A\u0015\u0005\u0006eY\u0001\ra\r\u0015\u0003-YBS!AA=\u0003\u007f\u00022ALA>\u0013\r\tiH\u0007\u0002\u0004Kb$\u0018\'C\u0012\u0002\u0002\u0006\u001d\u0015qRAE!\rq\u00131Q\u0005\u0004\u0003\u000bS\"AB*ue&tw-\u0003\u0003\u0002\n\u0006-\u0015a\u0007\u0013mKN\u001c\u0018N\\5uI\u001d\u0014X-\u0019;fe\u0012\"WMZ1vYR$\u0013GC\u0002\u0002\u000ej\t1!\u001a=uc%\u0019\u0013\u0011SAJ\u0003+\u000biID\u0002/\u0003\'K1!!$\u001bc\u0015\u0011cFGAL\u0005\u0019\u0019\u0018N]3v[\"*\u0001!!\u001f\u0002\u0000\u0001
   #9 = Utf8               toR
  #10 = Utf8               (Lorg/sireum/Z;)Lscala/math/BigDecimal;
  #11 = Utf8               n
  #12 = Utf8               org/sireum/conversions/N$
  #13 = Class              #12            // org/sireum/conversions/N$
  #14 = Utf8               MODULE$
  #15 = Utf8               Lorg/sireum/conversions/N$;
  #16 = NameAndType        #14:#15        // MODULE$:Lorg/sireum/conversions/N$;
  #17 = Fieldref           #13.#16        // org/sireum/conversions/N$.MODULE$:Lorg/sireum/conversions/N$;
  #18 = NameAndType        #9:#10         // toR:(Lorg/sireum/Z;)Lscala/math/BigDecimal;
  #19 = Methodref          #13.#18        // org/sireum/conversions/N$.toR:(Lorg/sireum/Z;)Lscala/math/BigDecimal;
  #20 = Utf8               Lorg/sireum/Z;
  #21 = Utf8               toU64
  #22 = Utf8               (Lorg/sireum/Z;)J
  #23 = NameAndType        #21:#22        // toU64:(Lorg/sireum/Z;)J
  #24 = Methodref          #13.#23        // org/sireum/conversions/N$.toU64:(Lorg/sireum/Z;)J
  #25 = Utf8               toU32
  #26 = Utf8               (Lorg/sireum/Z;)I
  #27 = NameAndType        #25:#26        // toU32:(Lorg/sireum/Z;)I
  #28 = Methodref          #13.#27        // org/sireum/conversions/N$.toU32:(Lorg/sireum/Z;)I
  #29 = Utf8               toU16
  #30 = Utf8               (Lorg/sireum/Z;)S
  #31 = NameAndType        #29:#30        // toU16:(Lorg/sireum/Z;)S
  #32 = Methodref          #13.#31        // org/sireum/conversions/N$.toU16:(Lorg/sireum/Z;)S
  #33 = Utf8               toU8
  #34 = Utf8               (Lorg/sireum/Z;)B
  #35 = NameAndType        #33:#34        // toU8:(Lorg/sireum/Z;)B
  #36 = Methodref          #13.#35        // org/sireum/conversions/N$.toU8:(Lorg/sireum/Z;)B
  #37 = Utf8               toS64
  #38 = NameAndType        #37:#22        // toS64:(Lorg/sireum/Z;)J
  #39 = Methodref          #13.#38        // org/sireum/conversions/N$.toS64:(Lorg/sireum/Z;)J
  #40 = Utf8               toS32
  #41 = NameAndType        #40:#26        // toS32:(Lorg/sireum/Z;)I
  #42 = Methodref          #13.#41        // org/sireum/conversions/N$.toS32:(Lorg/sireum/Z;)I
  #43 = Utf8               toS16
  #44 = NameAndType        #43:#30        // toS16:(Lorg/sireum/Z;)S
  #45 = Methodref          #13.#44        // org/sireum/conversions/N$.toS16:(Lorg/sireum/Z;)S
  #46 = Utf8               toS8
  #47 = NameAndType        #46:#34        // toS8:(Lorg/sireum/Z;)B
  #48 = Methodref          #13.#47        // org/sireum/conversions/N$.toS8:(Lorg/sireum/Z;)B
  #49 = Utf8               toN64
  #50 = Utf8               (Lorg/sireum/Z;)Lorg/sireum/Z;
  #51 = NameAndType        #49:#50        // toN64:(Lorg/sireum/Z;)Lorg/sireum/Z;
  #52 = Methodref          #13.#51        // org/sireum/conversions/N$.toN64:(Lorg/sireum/Z;)Lorg/sireum/Z;
  #53 = Utf8               toN32
  #54 = NameAndType        #53:#50        // toN32:(Lorg/sireum/Z;)Lorg/sireum/Z;
  #55 = Methodref          #13.#54        // org/sireum/conversions/N$.toN32:(Lorg/sireum/Z;)Lorg/sireum/Z;
  #56 = Utf8               toN16
  #57 = NameAndType        #56:#50        // toN16:(Lorg/sireum/Z;)Lorg/sireum/Z;
  #58 = Methodref          #13.#57        // org/sireum/conversions/N$.toN16:(Lorg/sireum/Z;)Lorg/sireum/Z;
  #59 = Utf8               toN8
  #60 = NameAndType        #59:#50        // toN8:(Lorg/sireum/Z;)Lorg/sireum/Z;
  #61 = Methodref          #13.#60        // org/sireum/conversions/N$.toN8:(Lorg/sireum/Z;)Lorg/sireum/Z;
  #62 = Utf8               toN
  #63 = NameAndType        #62:#50        // toN:(Lorg/sireum/Z;)Lorg/sireum/Z;
  #64 = Methodref          #13.#63        // org/sireum/conversions/N$.toN:(Lorg/sireum/Z;)Lorg/sireum/Z;
  #65 = Utf8               toZ64
  #66 = NameAndType        #65:#50        // toZ64:(Lorg/sireum/Z;)Lorg/sireum/Z;
  #67 = Methodref          #13.#66        // org/sireum/conversions/N$.toZ64:(Lorg/sireum/Z;)Lorg/sireum/Z;
  #68 = Utf8               toZ32
  #69 = NameAndType        #68:#50        // toZ32:(Lorg/sireum/Z;)Lorg/sireum/Z;
  #70 = Methodref          #13.#69        // org/sireum/conversions/N$.toZ32:(Lorg/sireum/Z;)Lorg/sireum/Z;
  #71 = Utf8               toZ16
  #72 = NameAndType        #71:#50        // toZ16:(Lorg/sireum/Z;)Lorg/sireum/Z;
  #73 = Methodref          #13.#72        // org/sireum/conversions/N$.toZ16:(Lorg/sireum/Z;)Lorg/sireum/Z;
  #74 = Utf8               toZ8
  #75 = NameAndType        #74:#50        // toZ8:(Lorg/sireum/Z;)Lorg/sireum/Z;
  #76 = Methodref          #13.#75        // org/sireum/conversions/N$.toZ8:(Lorg/sireum/Z;)Lorg/sireum/Z;
  #77 = Utf8               toZ
  #78 = NameAndType        #77:#50        // toZ:(Lorg/sireum/Z;)Lorg/sireum/Z;
  #79 = Methodref          #13.#78        // org/sireum/conversions/N$.toZ:(Lorg/sireum/Z;)Lorg/sireum/Z;
  #80 = Utf8               toB
  #81 = Utf8               (Lorg/sireum/Z;)Z
  #82 = NameAndType        #80:#81        // toB:(Lorg/sireum/Z;)Z
  #83 = Methodref          #13.#82        // org/sireum/conversions/N$.toB:(Lorg/sireum/Z;)Z
  #84 = Utf8               Code
  #85 = Utf8               LocalVariableTable
  #86 = Utf8               MethodParameters
  #87 = Utf8               SourceFile
  #88 = Utf8               RuntimeVisibleAnnotations
  #89 = Utf8               ScalaSig
{
  public static scala.math.BigDecimal toR(org.sireum.Z);
    descriptor: (Lorg/sireum/Z;)Lscala/math/BigDecimal;
    flags: (0x0009) ACC_PUBLIC, ACC_STATIC
    Code:
      stack=2, locals=1, args_size=1
         0: getstatic     #17                 // Field org/sireum/conversions/N$.MODULE$:Lorg/sireum/conversions/N$;
         3: aload_0
         4: invokevirtual #19                 // Method org/sireum/conversions/N$.toR:(Lorg/sireum/Z;)Lscala/math/BigDecimal;
         7: areturn
      LocalVariableTable:
        Start  Length  Slot  Name   Signature
            0       8     0     n   Lorg/sireum/Z;
    MethodParameters:
      Name                           Flags
      n                              final

  public static long toU64(org.sireum.Z);
    descriptor: (Lorg/sireum/Z;)J
    flags: (0x0009) ACC_PUBLIC, ACC_STATIC
    Code:
      stack=2, locals=1, args_size=1
         0: getstatic     #17                 // Field org/sireum/conversions/N$.MODULE$:Lorg/sireum/conversions/N$;
         3: aload_0
         4: invokevirtual #24                 // Method org/sireum/conversions/N$.toU64:(Lorg/sireum/Z;)J
         7: lreturn
      LocalVariableTable:
        Start  Length  Slot  Name   Signature
            0       8     0     n   Lorg/sireum/Z;
    MethodParameters:
      Name                           Flags
      n                              final

  public static int toU32(org.sireum.Z);
    descriptor: (Lorg/sireum/Z;)I
    flags: (0x0009) ACC_PUBLIC, ACC_STATIC
    Code:
      stack=2, locals=1, args_size=1
         0: getstatic     #17                 // Field org/sireum/conversions/N$.MODULE$:Lorg/sireum/conversions/N$;
         3: aload_0
         4: invokevirtual #28                 // Method org/sireum/conversions/N$.toU32:(Lorg/sireum/Z;)I
         7: ireturn
      LocalVariableTable:
        Start  Length  Slot  Name   Signature
            0       8     0     n   Lorg/sireum/Z;
    MethodParameters:
      Name                           Flags
      n                              final

  public static short toU16(org.sireum.Z);
    descriptor: (Lorg/sireum/Z;)S
    flags: (0x0009) ACC_PUBLIC, ACC_STATIC
    Code:
      stack=2, locals=1, args_size=1
         0: getstatic     #17                 // Field org/sireum/conversions/N$.MODULE$:Lorg/sireum/conversions/N$;
         3: aload_0
         4: invokevirtual #32                 // Method org/sireum/conversions/N$.toU16:(Lorg/sireum/Z;)S
         7: ireturn
      LocalVariableTable:
        Start  Length  Slot  Name   Signature
            0       8     0     n   Lorg/sireum/Z;
    MethodParameters:
      Name                           Flags
      n                              final

  public static byte toU8(org.sireum.Z);
    descriptor: (Lorg/sireum/Z;)B
    flags: (0x0009) ACC_PUBLIC, ACC_STATIC
    Code:
      stack=2, locals=1, args_size=1
         0: getstatic     #17                 // Field org/sireum/conversions/N$.MODULE$:Lorg/sireum/conversions/N$;
         3: aload_0
         4: invokevirtual #36                 // Method org/sireum/conversions/N$.toU8:(Lorg/sireum/Z;)B
         7: ireturn
      LocalVariableTable:
        Start  Length  Slot  Name   Signature
            0       8     0     n   Lorg/sireum/Z;
    MethodParameters:
      Name                           Flags
      n                              final

  public static long toS64(org.sireum.Z);
    descriptor: (Lorg/sireum/Z;)J
    flags: (0x0009) ACC_PUBLIC, ACC_STATIC
    Code:
      stack=2, locals=1, args_size=1
         0: getstatic     #17                 // Field org/sireum/conversions/N$.MODULE$:Lorg/sireum/conversions/N$;
         3: aload_0
         4: invokevirtual #39                 // Method org/sireum/conversions/N$.toS64:(Lorg/sireum/Z;)J
         7: lreturn
      LocalVariableTable:
        Start  Length  Slot  Name   Signature
            0       8     0     n   Lorg/sireum/Z;
    MethodParameters:
      Name                           Flags
      n                              final

  public static int toS32(org.sireum.Z);
    descriptor: (Lorg/sireum/Z;)I
    flags: (0x0009) ACC_PUBLIC, ACC_STATIC
    Code:
      stack=2, locals=1, args_size=1
         0: getstatic     #17                 // Field org/sireum/conversions/N$.MODULE$:Lorg/sireum/conversions/N$;
         3: aload_0
         4: invokevirtual #42                 // Method org/sireum/conversions/N$.toS32:(Lorg/sireum/Z;)I
         7: ireturn
      LocalVariableTable:
        Start  Length  Slot  Name   Signature
            0       8     0     n   Lorg/sireum/Z;
    MethodParameters:
      Name                           Flags
      n                              final

  public static short toS16(org.sireum.Z);
    descriptor: (Lorg/sireum/Z;)S
    flags: (0x0009) ACC_PUBLIC, ACC_STATIC
    Code:
      stack=2, locals=1, args_size=1
         0: getstatic     #17                 // Field org/sireum/conversions/N$.MODULE$:Lorg/sireum/conversions/N$;
         3: aload_0
         4: invokevirtual #45                 // Method org/sireum/conversions/N$.toS16:(Lorg/sireum/Z;)S
         7: ireturn
      LocalVariableTable:
        Start  Length  Slot  Name   Signature
            0       8     0     n   Lorg/sireum/Z;
    MethodParameters:
      Name                           Flags
      n                              final

  public static byte toS8(org.sireum.Z);
    descriptor: (Lorg/sireum/Z;)B
    flags: (0x0009) ACC_PUBLIC, ACC_STATIC
    Code:
      stack=2, locals=1, args_size=1
         0: getstatic     #17                 // Field org/sireum/conversions/N$.MODULE$:Lorg/sireum/conversions/N$;
         3: aload_0
         4: invokevirtual #48                 // Method org/sireum/conversions/N$.toS8:(Lorg/sireum/Z;)B
         7: ireturn
      LocalVariableTable:
        Start  Length  Slot  Name   Signature
            0       8     0     n   Lorg/sireum/Z;
    MethodParameters:
      Name                           Flags
      n                              final

  public static org.sireum.Z toN64(org.sireum.Z);
    descriptor: (Lorg/sireum/Z;)Lorg/sireum/Z;
    flags: (0x0009) ACC_PUBLIC, ACC_STATIC
    Code:
      stack=2, locals=1, args_size=1
         0: getstatic     #17                 // Field org/sireum/conversions/N$.MODULE$:Lorg/sireum/conversions/N$;
         3: aload_0
         4: invokevirtual #52                 // Method org/sireum/conversions/N$.toN64:(Lorg/sireum/Z;)Lorg/sireum/Z;
         7: areturn
      LocalVariableTable:
        Start  Length  Slot  Name   Signature
            0       8     0     n   Lorg/sireum/Z;
    MethodParameters:
      Name                           Flags
      n                              final

  public static org.sireum.Z toN32(org.sireum.Z);
    descriptor: (Lorg/sireum/Z;)Lorg/sireum/Z;
    flags: (0x0009) ACC_PUBLIC, ACC_STATIC
    Code:
      stack=2, locals=1, args_size=1
         0: getstatic     #17                 // Field org/sireum/conversions/N$.MODULE$:Lorg/sireum/conversions/N$;
         3: aload_0
         4: invokevirtual #55                 // Method org/sireum/conversions/N$.toN32:(Lorg/sireum/Z;)Lorg/sireum/Z;
         7: areturn
      LocalVariableTable:
        Start  Length  Slot  Name   Signature
            0       8     0     n   Lorg/sireum/Z;
    MethodParameters:
      Name                           Flags
      n                              final

  public static org.sireum.Z toN16(org.sireum.Z);
    descriptor: (Lorg/sireum/Z;)Lorg/sireum/Z;
    flags: (0x0009) ACC_PUBLIC, ACC_STATIC
    Code:
      stack=2, locals=1, args_size=1
         0: getstatic     #17                 // Field org/sireum/conversions/N$.MODULE$:Lorg/sireum/conversions/N$;
         3: aload_0
         4: invokevirtual #58                 // Method org/sireum/conversions/N$.toN16:(Lorg/sireum/Z;)Lorg/sireum/Z;
         7: areturn
      LocalVariableTable:
        Start  Length  Slot  Name   Signature
            0       8     0     n   Lorg/sireum/Z;
    MethodParameters:
      Name                           Flags
      n                              final

  public static org.sireum.Z toN8(org.sireum.Z);
    descriptor: (Lorg/sireum/Z;)Lorg/sireum/Z;
    flags: (0x0009) ACC_PUBLIC, ACC_STATIC
    Code:
      stack=2, locals=1, args_size=1
         0: getstatic     #17                 // Field org/sireum/conversions/N$.MODULE$:Lorg/sireum/conversions/N$;
         3: aload_0
         4: invokevirtual #61                 // Method org/sireum/conversions/N$.toN8:(Lorg/sireum/Z;)Lorg/sireum/Z;
         7: areturn
      LocalVariableTable:
        Start  Length  Slot  Name   Signature
            0       8     0     n   Lorg/sireum/Z;
    MethodParameters:
      Name                           Flags
      n                              final

  public static org.sireum.Z toN(org.sireum.Z);
    descriptor: (Lorg/sireum/Z;)Lorg/sireum/Z;
    flags: (0x0009) ACC_PUBLIC, ACC_STATIC
    Code:
      stack=2, locals=1, args_size=1
         0: getstatic     #17                 // Field org/sireum/conversions/N$.MODULE$:Lorg/sireum/conversions/N$;
         3: aload_0
         4: invokevirtual #64                 // Method org/sireum/conversions/N$.toN:(Lorg/sireum/Z;)Lorg/sireum/Z;
         7: areturn
      LocalVariableTable:
        Start  Length  Slot  Name   Signature
            0       8     0     n   Lorg/sireum/Z;
    MethodParameters:
      Name                           Flags
      n                              final

  public static org.sireum.Z toZ64(org.sireum.Z);
    descriptor: (Lorg/sireum/Z;)Lorg/sireum/Z;
    flags: (0x0009) ACC_PUBLIC, ACC_STATIC
    Code:
      stack=2, locals=1, args_size=1
         0: getstatic     #17                 // Field org/sireum/conversions/N$.MODULE$:Lorg/sireum/conversions/N$;
         3: aload_0
         4: invokevirtual #67                 // Method org/sireum/conversions/N$.toZ64:(Lorg/sireum/Z;)Lorg/sireum/Z;
         7: areturn
      LocalVariableTable:
        Start  Length  Slot  Name   Signature
            0       8     0     n   Lorg/sireum/Z;
    MethodParameters:
      Name                           Flags
      n                              final

  public static org.sireum.Z toZ32(org.sireum.Z);
    descriptor: (Lorg/sireum/Z;)Lorg/sireum/Z;
    flags: (0x0009) ACC_PUBLIC, ACC_STATIC
    Code:
      stack=2, locals=1, args_size=1
         0: getstatic     #17                 // Field org/sireum/conversions/N$.MODULE$:Lorg/sireum/conversions/N$;
         3: aload_0
         4: invokevirtual #70                 // Method org/sireum/conversions/N$.toZ32:(Lorg/sireum/Z;)Lorg/sireum/Z;
         7: areturn
      LocalVariableTable:
        Start  Length  Slot  Name   Signature
            0       8     0     n   Lorg/sireum/Z;
    MethodParameters:
      Name                           Flags
      n                              final

  public static org.sireum.Z toZ16(org.sireum.Z);
    descriptor: (Lorg/sireum/Z;)Lorg/sireum/Z;
    flags: (0x0009) ACC_PUBLIC, ACC_STATIC
    Code:
      stack=2, locals=1, args_size=1
         0: getstatic     #17                 // Field org/sireum/conversions/N$.MODULE$:Lorg/sireum/conversions/N$;
         3: aload_0
         4: invokevirtual #73                 // Method org/sireum/conversions/N$.toZ16:(Lorg/sireum/Z;)Lorg/sireum/Z;
         7: areturn
      LocalVariableTable:
        Start  Length  Slot  Name   Signature
            0       8     0     n   Lorg/sireum/Z;
    MethodParameters:
      Name                           Flags
      n                              final

  public static org.sireum.Z toZ8(org.sireum.Z);
    descriptor: (Lorg/sireum/Z;)Lorg/sireum/Z;
    flags: (0x0009) ACC_PUBLIC, ACC_STATIC
    Code:
      stack=2, locals=1, args_size=1
         0: getstatic     #17                 // Field org/sireum/conversions/N$.MODULE$:Lorg/sireum/conversions/N$;
         3: aload_0
         4: invokevirtual #76                 // Method org/sireum/conversions/N$.toZ8:(Lorg/sireum/Z;)Lorg/sireum/Z;
         7: areturn
      LocalVariableTable:
        Start  Length  Slot  Name   Signature
            0       8     0     n   Lorg/sireum/Z;
    MethodParameters:
      Name                           Flags
      n                              final

  public static org.sireum.Z toZ(org.sireum.Z);
    descriptor: (Lorg/sireum/Z;)Lorg/sireum/Z;
    flags: (0x0009) ACC_PUBLIC, ACC_STATIC
    Code:
      stack=2, locals=1, args_size=1
         0: getstatic     #17                 // Field org/sireum/conversions/N$.MODULE$:Lorg/sireum/conversions/N$;
         3: aload_0
         4: invokevirtual #79                 // Method org/sireum/conversions/N$.toZ:(Lorg/sireum/Z;)Lorg/sireum/Z;
         7: areturn
      LocalVariableTable:
        Start  Length  Slot  Name   Signature
            0       8     0     n   Lorg/sireum/Z;
    MethodParameters:
      Name                           Flags
      n                              final

  public static boolean toB(org.sireum.Z);
    descriptor: (Lorg/sireum/Z;)Z
    flags: (0x0009) ACC_PUBLIC, ACC_STATIC
    Code:
      stack=2, locals=1, args_size=1
         0: getstatic     #17                 // Field org/sireum/conversions/N$.MODULE$:Lorg/sireum/conversions/N$;
         3: aload_0
         4: invokevirtual #83                 // Method org/sireum/conversions/N$.toB:(Lorg/sireum/Z;)Z
         7: ireturn
      LocalVariableTable:
        Start  Length  Slot  Name   Signature
            0       8     0     n   Lorg/sireum/Z;
    MethodParameters:
      Name                           Flags
      n                              final
}
SourceFile: "conversions.scala"
RuntimeVisibleAnnotations:
  0: #6(#7=s#8)
    scala.reflect.ScalaSignature(
      bytes="\u0006\u0005\u0005mu!B\f\u0019\u0011\u0003yb!B\u0011\u0019\u0011\u0003\u0011\u0003\"B\u0015\u0002\t\u0003Q\u0003\"B\u0016\u0002\t\u0003a\u0003\"B\u001d\u0002\t\u0003Q\u0004\"\u0002!\u0002\t\u0003\t\u0005\"B$\u0002\t\u0003A\u0005\"\u0002(\u0002\t\u0003y\u0005\"B+\u0002\t\u00031\u0006\"\u0002/\u0002\t\u0003i\u0006\"\u00021\u0002\t\u0003\t\u0007\"B4\u0002\t\u0003A\u0007\"\u00028\u0002\t\u0003y\u0007\"B;\u0002\t\u00031\b\"\u0002?\u0002\t\u0003i\bbBA\u0004\u0003\u0011\u0005\u0011\u0011\u0002\u0005\b\u0003+\tA\u0011AA\f\u0011\u001d\t\u0019#\u0001C\u0001\u0003KAq!!\r\u0002\t\u0003\t\u0019\u0004C\u0004\u0002@\u0005!\t!!\u0011\t\u000f\u00055\u0013\u0001\"\u0001\u0002P!9\u00111L\u0001\u0005\u0002\u0005u\u0003bBA5\u0003\u0011\u0005\u00111N\u0001\u0002\u001d*\u0011\u0011DG\u0001\fG>tg/\u001a:tS>t7O\u0003\u0002\u001c9\u000511/\u001b:fk6T\u0011!H\u0001\u0004_J<7\u0001\u0001\t\u0003A\u0005i\u0011\u0001\u0007\u0002\u0002\u001dN\u0011\u0011a\t\t\u0003I\u001dj\u0011!\n\u0006\u0002M\u0005)1oY1mC&\u0011\u0001&\n\u0002\u0007\u0003:L(+\u001a4\u0002\rqJg.\u001b;?)\u0005y\u0012a\u0001;p\u0005R\u0011Q&\r\t\u0003]=j\u0011AG\u0005\u0003ai\u0011\u0011A\u0011\u0005\u0006e\r\u0001\raM\u0001\u0002]B\u0011a\u0006N\u0005\u0003CiA#a\u0001\u001c\u0011\u00059:\u0014B\u0001\u001d\u001b\u0005\u0011\u0001XO]3\u0002\u0007Q|\'\f\u0006\u0002<}A\u0011a\u0006P\u0005\u0003{i\u0011\u0011A\u0017\u0005\u0006e\u0011\u0001\ra\r\u0015\u0003\tY\nA\u0001^8[qQ\u0011!)\u0012\t\u0003]\rK!\u0001\u0012\u000e\u0003\u0005iC\u0004\"\u0002\u001a\u0006\u0001\u0004\u0019\u0004FA\u00037\u0003\u0015!xNW\u00197)\tIE\n\u0005\u0002/\u0015&\u00111J\u0007\u0002\u00045F2\u0004\"\u0002\u001a\u0007\u0001\u0004\u0019\u0004F\u0001\u00047\u0003\u0015!xNW\u001a3)\t\u00016\u000b\u0005\u0002/#&\u0011!K\u0007\u0002\u00045N\u0012\u0004\"\u0002\u001a\b\u0001\u0004\u0019\u0004FA\u00047\u0003\u0015!xN\u0017\u001c5)\t9&\f\u0005\u0002/1&\u0011\u0011L\u0007\u0002\u00045Z\"\u0004\"\u0002\u001a\t\u0001\u0004\u0019\u0004F\u0001\u00057\u0003\r!xN\u0014\u000b\u0003gyCQAM\u0005A\u0002MB#!\u0003\u001c\u0002\tQ|g\n\u000f\u000b\u0003E\u0016\u0004\"AL2\n\u0005\u0011T\"A\u0001(9\u0011\u0015\u0011$\u00021\u00014Q\tQa\'A\u0003u_:\u000bd\u0007\u0006\u0002jYB\u0011aF[\u0005\u0003Wj\u00111AT\u00197\u0011\u0015\u00114\u00021\u00014Q\tYa\'A\u0003u_:\u001b$\u0007\u0006\u0002qgB\u0011a&]\u0005\u0003ej\u00111AT\u001a3\u0011\u0015\u0011D\u00021\u00014Q\taa\'A\u0003u_:3D\u0007\u0006\u0002xuB\u0011a\u0006_\u0005\u0003sj\u00111A\u0014\u001c5\u0011\u0015\u0011T\u00021\u00014Q\tia\'\u0001\u0003u_NCDc\u0001@\u0002\u0004A\u0011af`\u0005\u0004\u0003\u0003Q\"AA*9\u0011\u0015\u0011d\u00021\u00014Q\tqa\'A\u0003u_N\u000bd\u0007\u0006\u0003\u0002\f\u0005E\u0001c\u0001\u0018\u0002\u000e%\u0019\u0011q\u0002\u000e\u0003\u0007M\u000bd\u0007C\u00033\u001f\u0001\u00071\u0007\u000b\u0002\u0010m\u0005)Ao\\*4eQ!\u0011\u0011DA\u0010!\rq\u00131D\u0005\u0004\u0003;Q\"aA*4e!)!\u0007\u0005a\u0001g!\u0012\u0001CN\u0001\u0006i>\u001cf\u0007\u000e\u000b\u0005\u0003O\ti\u0003E\u0002/\u0003SI1!a\u000b\u001b\u0005\r\u0019f\u0007\u000e\u0005\u0006eE\u0001\ra\r\u0015\u0003#Y\nA\u0001^8VqQ!\u0011QGA\u001e!\rq\u0013qG\u0005\u0004\u0003sQ\"AA+9\u0011\u0015\u0011$\u00031\u00014Q\t\u0011b\'A\u0003u_V\u000bd\u0007\u0006\u0003\u0002D\u0005%\u0003c\u0001\u0018\u0002F%\u0019\u0011q\t\u000e\u0003\u0007U\u000bd\u0007C\u00033\'\u0001\u00071\u0007\u000b\u0002\u0014m\u0005)Ao\\+4eQ!\u0011\u0011KA,!\rq\u00131K\u0005\u0004\u0003+R\"aA+4e!)!\u0007\u0006a\u0001g!\u0012ACN\u0001\u0006i>,f\u0007\u000e\u000b\u0005\u0003?\n)\u0007E\u0002/\u0003CJ1!a\u0019\u001b\u0005\r)f\u0007\u000e\u0005\u0006eU\u0001\ra\r\u0015\u0003+Y\n1\u0001^8S)\u0011\ti\'a\u001d\u0011\u00079\ny\'C\u0002\u0002ri\u0011\u0011A\u0015\u0005\u0006eY\u0001\ra\r\u0015\u0003-YBS!AA=\u0003\u007f\u00022ALA>\u0013\r\tiH\u0007\u0002\u0004Kb$\u0018\'C\u0012\u0002\u0002\u0006\u001d\u0015qRAE!\rq\u00131Q\u0005\u0004\u0003\u000bS\"AB*ue&tw-\u0003\u0003\u0002\n\u0006-\u0015a\u0007\u0013mKN\u001c\u0018N\\5uI\u001d\u0014X-\u0019;fe\u0012\"WMZ1vYR$\u0013GC\u0002\u0002\u000ej\t1!\u001a=uc%\u0019\u0013\u0011SAJ\u0003+\u000biID\u0002/\u0003\'K1!!$\u001bc\u0015\u0011cFGAL\u0005\u0019\u0019\u0018N]3v[\"*\u0001!!\u001f\u0002\u0000\u0001"
    )
  ScalaSig: length = 0x3 (unknown attribute)
   05 02 00
