Classfile /Users/mw/Projects/slang-braindump/.jar/jar8/assemble/slang-braindump/assemble/content/org/sireum/conversions/R_Ext.class
  Last modified May 29, 2022; size 1175 bytes
  SHA-256 checksum 0bb79d73e136b220e725468017f68271488a1a67a835dd267a6447c1b290be72
  Compiled from "extension.scala"
public final class org.sireum.conversions.R_Ext
  minor version: 0
  major version: 52
  flags: (0x0031) ACC_PUBLIC, ACC_FINAL, ACC_SUPER
  this_class: #2                          // org/sireum/conversions/R_Ext
  super_class: #4                         // java/lang/Object
  interfaces: 0, fields: 0, methods: 4, attributes: 3
Constant pool:
   #1 = Utf8               org/sireum/conversions/R_Ext
   #2 = Class              #1             // org/sireum/conversions/R_Ext
   #3 = Utf8               java/lang/Object
   #4 = Class              #3             // java/lang/Object
   #5 = Utf8               extension.scala
   #6 = Utf8               Lscala/reflect/ScalaSignature;
   #7 = Utf8               bytes
   #8 = Utf8               \u0006\u0005q:Qa\u0002\u0005\t\u0002=1Q!\u0005\u0005\t\u0002IAQ!G\u0001\u0005\u0002iAQaG\u0001\u0005\u0002qAQAK\u0001\u0005\u0002-BQ!M\u0001\u0005\u0002IBQ\u0001O\u0001\u0005\u0002e\nQAU0FqRT!!\u0003\u0006\u0002\u0017\r|gN^3sg&|gn\u001d\u0006\u0003\u00171\taa]5sKVl\'\"A\u0007\u0002\u0007=\u0014xm\u0001\u0001\u0011\u0005A\tQ\"\u0001\u0005\u0003\u000bI{V\t\u001f;\u0014\u0005\u0005\u0019\u0002C\u0001\u000b\u0018\u001b\u0005)\"\"\u0001\f\u0002\u000bM\u001c\u0017\r\\1\n\u0005a)\"AB!osJ+g-\u0001\u0004=S:LGO\u0010\u000b\u0002\u001f\u0005\u0019Ao\u001c\"\u0015\u0005u\t\u0003C\u0001\u0010 \u001b\u0005Q\u0011B\u0001\u0011\u000b\u0005\u0005\u0011\u0005\"\u0002\u0012\u0004\u0001\u0004\u0019\u0013!\u00018\u0011\u0005y!\u0013BA\u0013\u000b\u0005\u0005\u0011\u0006FA\u0002(!\tq\u0002&\u0003\u0002*\u0015\t!\u0001/\u001e:f\u0003\r!xN\u0017\u000b\u0003Y=\u0002\"AH\u0017\n\u00059R!!\u0001.\t\u000b\t\"\u0001\u0019A\u0012)\u0005\u00119\u0013a\u0001;p\u001dR\u00111G\u000e\t\u0003=QJ!!\u000e\u0006\u0003\u00039CQAI\u0003A\u0002\rB#!B\u0014\u0002\u0007Q|\'\u000b\u0006\u0002$u!)!E\u0002a\u0001G!\u0012aa\n
   #9 = Utf8               toR
  #10 = Utf8               (Lscala/math/BigDecimal;)Lscala/math/BigDecimal;
  #11 = Utf8               n
  #12 = Utf8               org/sireum/conversions/R_Ext$
  #13 = Class              #12            // org/sireum/conversions/R_Ext$
  #14 = Utf8               MODULE$
  #15 = Utf8               Lorg/sireum/conversions/R_Ext$;
  #16 = NameAndType        #14:#15        // MODULE$:Lorg/sireum/conversions/R_Ext$;
  #17 = Fieldref           #13.#16        // org/sireum/conversions/R_Ext$.MODULE$:Lorg/sireum/conversions/R_Ext$;
  #18 = NameAndType        #9:#10         // toR:(Lscala/math/BigDecimal;)Lscala/math/BigDecimal;
  #19 = Methodref          #13.#18        // org/sireum/conversions/R_Ext$.toR:(Lscala/math/BigDecimal;)Lscala/math/BigDecimal;
  #20 = Utf8               Lscala/math/BigDecimal;
  #21 = Utf8               toN
  #22 = Utf8               (Lscala/math/BigDecimal;)Lorg/sireum/Z;
  #23 = NameAndType        #21:#22        // toN:(Lscala/math/BigDecimal;)Lorg/sireum/Z;
  #24 = Methodref          #13.#23        // org/sireum/conversions/R_Ext$.toN:(Lscala/math/BigDecimal;)Lorg/sireum/Z;
  #25 = Utf8               toZ
  #26 = NameAndType        #25:#22        // toZ:(Lscala/math/BigDecimal;)Lorg/sireum/Z;
  #27 = Methodref          #13.#26        // org/sireum/conversions/R_Ext$.toZ:(Lscala/math/BigDecimal;)Lorg/sireum/Z;
  #28 = Utf8               toB
  #29 = Utf8               (Lscala/math/BigDecimal;)Z
  #30 = NameAndType        #28:#29        // toB:(Lscala/math/BigDecimal;)Z
  #31 = Methodref          #13.#30        // org/sireum/conversions/R_Ext$.toB:(Lscala/math/BigDecimal;)Z
  #32 = Utf8               Code
  #33 = Utf8               LocalVariableTable
  #34 = Utf8               MethodParameters
  #35 = Utf8               SourceFile
  #36 = Utf8               RuntimeVisibleAnnotations
  #37 = Utf8               ScalaSig
{
  public static scala.math.BigDecimal toR(scala.math.BigDecimal);
    descriptor: (Lscala/math/BigDecimal;)Lscala/math/BigDecimal;
    flags: (0x0009) ACC_PUBLIC, ACC_STATIC
    Code:
      stack=2, locals=1, args_size=1
         0: getstatic     #17                 // Field org/sireum/conversions/R_Ext$.MODULE$:Lorg/sireum/conversions/R_Ext$;
         3: aload_0
         4: invokevirtual #19                 // Method org/sireum/conversions/R_Ext$.toR:(Lscala/math/BigDecimal;)Lscala/math/BigDecimal;
         7: areturn
      LocalVariableTable:
        Start  Length  Slot  Name   Signature
            0       8     0     n   Lscala/math/BigDecimal;
    MethodParameters:
      Name                           Flags
      n                              final

  public static org.sireum.Z toN(scala.math.BigDecimal);
    descriptor: (Lscala/math/BigDecimal;)Lorg/sireum/Z;
    flags: (0x0009) ACC_PUBLIC, ACC_STATIC
    Code:
      stack=2, locals=1, args_size=1
         0: getstatic     #17                 // Field org/sireum/conversions/R_Ext$.MODULE$:Lorg/sireum/conversions/R_Ext$;
         3: aload_0
         4: invokevirtual #24                 // Method org/sireum/conversions/R_Ext$.toN:(Lscala/math/BigDecimal;)Lorg/sireum/Z;
         7: areturn
      LocalVariableTable:
        Start  Length  Slot  Name   Signature
            0       8     0     n   Lscala/math/BigDecimal;
    MethodParameters:
      Name                           Flags
      n                              final

  public static org.sireum.Z toZ(scala.math.BigDecimal);
    descriptor: (Lscala/math/BigDecimal;)Lorg/sireum/Z;
    flags: (0x0009) ACC_PUBLIC, ACC_STATIC
    Code:
      stack=2, locals=1, args_size=1
         0: getstatic     #17                 // Field org/sireum/conversions/R_Ext$.MODULE$:Lorg/sireum/conversions/R_Ext$;
         3: aload_0
         4: invokevirtual #27                 // Method org/sireum/conversions/R_Ext$.toZ:(Lscala/math/BigDecimal;)Lorg/sireum/Z;
         7: areturn
      LocalVariableTable:
        Start  Length  Slot  Name   Signature
            0       8     0     n   Lscala/math/BigDecimal;
    MethodParameters:
      Name                           Flags
      n                              final

  public static boolean toB(scala.math.BigDecimal);
    descriptor: (Lscala/math/BigDecimal;)Z
    flags: (0x0009) ACC_PUBLIC, ACC_STATIC
    Code:
      stack=2, locals=1, args_size=1
         0: getstatic     #17                 // Field org/sireum/conversions/R_Ext$.MODULE$:Lorg/sireum/conversions/R_Ext$;
         3: aload_0
         4: invokevirtual #31                 // Method org/sireum/conversions/R_Ext$.toB:(Lscala/math/BigDecimal;)Z
         7: ireturn
      LocalVariableTable:
        Start  Length  Slot  Name   Signature
            0       8     0     n   Lscala/math/BigDecimal;
    MethodParameters:
      Name                           Flags
      n                              final
}
SourceFile: "extension.scala"
RuntimeVisibleAnnotations:
  0: #6(#7=s#8)
    scala.reflect.ScalaSignature(
      bytes="\u0006\u0005q:Qa\u0002\u0005\t\u0002=1Q!\u0005\u0005\t\u0002IAQ!G\u0001\u0005\u0002iAQaG\u0001\u0005\u0002qAQAK\u0001\u0005\u0002-BQ!M\u0001\u0005\u0002IBQ\u0001O\u0001\u0005\u0002e\nQAU0FqRT!!\u0003\u0006\u0002\u0017\r|gN^3sg&|gn\u001d\u0006\u0003\u00171\taa]5sKVl\'\"A\u0007\u0002\u0007=\u0014xm\u0001\u0001\u0011\u0005A\tQ\"\u0001\u0005\u0003\u000bI{V\t\u001f;\u0014\u0005\u0005\u0019\u0002C\u0001\u000b\u0018\u001b\u0005)\"\"\u0001\f\u0002\u000bM\u001c\u0017\r\\1\n\u0005a)\"AB!osJ+g-\u0001\u0004=S:LGO\u0010\u000b\u0002\u001f\u0005\u0019Ao\u001c\"\u0015\u0005u\t\u0003C\u0001\u0010 \u001b\u0005Q\u0011B\u0001\u0011\u000b\u0005\u0005\u0011\u0005\"\u0002\u0012\u0004\u0001\u0004\u0019\u0013!\u00018\u0011\u0005y!\u0013BA\u0013\u000b\u0005\u0005\u0011\u0006FA\u0002(!\tq\u0002&\u0003\u0002*\u0015\t!\u0001/\u001e:f\u0003\r!xN\u0017\u000b\u0003Y=\u0002\"AH\u0017\n\u00059R!!\u0001.\t\u000b\t\"\u0001\u0019A\u0012)\u0005\u00119\u0013a\u0001;p\u001dR\u00111G\u000e\t\u0003=QJ!!\u000e\u0006\u0003\u00039CQAI\u0003A\u0002\rB#!B\u0014\u0002\u0007Q|\'\u000b\u0006\u0002$u!)!E\u0002a\u0001G!\u0012aa\n"
    )
  ScalaSig: length = 0x3 (unknown attribute)
   05 02 00
