Classfile /Users/mw/Projects/slang-braindump/.jar/jar8/assemble/slang-braindump/assemble/content/org/sireum/conversions/U32_Ext.class
  Last modified May 29, 2022; size 5696 bytes
  SHA-256 checksum 3736111967d7d6e82a133db8b6a215932dda8d94399fe320a012dc13e986b11d
  Compiled from "extension.scala"
public final class org.sireum.conversions.U32_Ext
  minor version: 0
  major version: 52
  flags: (0x0031) ACC_PUBLIC, ACC_FINAL, ACC_SUPER
  this_class: #2                          // org/sireum/conversions/U32_Ext
  super_class: #4                         // java/lang/Object
  interfaces: 0, fields: 0, methods: 38, attributes: 3
Constant pool:
    #1 = Utf8               org/sireum/conversions/U32_Ext
    #2 = Class              #1            // org/sireum/conversions/U32_Ext
    #3 = Utf8               java/lang/Object
    #4 = Class              #3            // java/lang/Object
    #5 = Utf8               extension.scala
    #6 = Utf8               Lscala/reflect/ScalaSignature;
    #7 = Utf8               bytes
    #8 = Utf8               \u0006\u0005\tMu!B\u0015+\u0011\u0003\td!B\u001a+\u0011\u0003!\u0004\"B\u001e\u0002\t\u0003a\u0004\"B\u001f\u0002\t\u0003q\u0004\"\u0002\'\u0002\t\u0003i\u0005\"B*\u0002\t\u0003!\u0006\"\u0002.\u0002\t\u0003Y\u0006\"B1\u0002\t\u0003\u0011\u0007\"\u00025\u0002\t\u0003I\u0007\"B8\u0002\t\u0003\u0001\b\"\u0002<\u0002\t\u00039\b\"B?\u0002\t\u0003q\bbBA\u0005\u0003\u0011\u0005\u00111\u0002\u0005\b\u0003/\tA\u0011AA\r\u0011\u001d\t)#\u0001C\u0001\u0003OAq!a\r\u0002\t\u0003\t)\u0004C\u0004\u0002B\u0005!\t!a\u0011\t\u000f\u0005=\u0013\u0001\"\u0001\u0002R!9\u0011QL\u0001\u0005\u0002\u0005}\u0003bBA6\u0003\u0011\u0005\u0011Q\u000e\u0005\b\u0003s\nA\u0011AA>\u0011\u001d\t9)\u0001C\u0001\u0003\u0013Cq!!&\u0002\t\u0003\t9\nC\u0004\u0002$\u0006!\t!!*\t\u000f\u0005E\u0016\u0001\"\u0001\u00024\"9\u0011qX\u0001\u0005\u0002\u0005\u0005\u0007bBAg\u0003\u0011\u0005\u0011q\u001a\u0005\b\u00037\fA\u0011AAo\u0011\u001d\tI/\u0001C\u0001\u0003WDq!a>\u0002\t\u0003\tI\u0010C\u0004\u0003\u0006\u0005!\tAa\u0002\t\u000f\tM\u0011\u0001\"\u0001\u0003\u0016!9!\u0011E\u0001\u0005\u0002\t\r\u0002b\u0002B\u0018\u0003\u0011\u0005!\u0011\u0007\u0005\b\u0005{\tA\u0011\u0001B \u0011\u001d\u0011Y%\u0001C\u0001\u0005\u001bBqAa\u0015\u0002\t\u0003\u0011)\u0006C\u0004\u0003b\u0005!\tAa\u0019\t\u000f\t=\u0014\u0001\"\u0001\u0003r!9!qO\u0001\u0005\u0002\te\u0004b\u0002BC\u0003\u0011\u0005!qQ\u0001\b+N\u0012t,\u0012=u\u0015\tYC&A\u0006d_:4XM]:j_:\u001c(BA\u0017/\u0003\u0019\u0019\u0018N]3v[*\tq&A\u0002pe\u001e\u001c\u0001\u0001\u0005\u00023\u00035\t!FA\u0004VgIzV\t\u001f;\u0014\u0005\u0005)\u0004C\u0001\u001c:\u001b\u00059$\"\u0001\u001d\u0002\u000bM\u001c\u0017\r\\1\n\u0005i:$AB!osJ+g-\u0001\u0004=S:LGO\u0010\u000b\u0002c\u0005\u0019Ao\u001c\"\u0015\u0005}\u001a\u0005C\u0001!B\u001b\u0005a\u0013B\u0001\"-\u0005\u0005\u0011\u0005\"\u0002#\u0004\u0001\u0004)\u0015!\u00018\u0011\u0005\u00013\u0015BA$-\u0005\r)6G\r\u0015\u0003\u0007%\u0003\"\u0001\u0011&\n\u0005-c#\u0001\u00029ve\u0016\f1\u0001^8[)\tq\u0015\u000b\u0005\u0002A\u001f&\u0011\u0001\u000b\f\u0002\u00025\")A\t\u0002a\u0001\u000b\"\u0012A!S\u0001\u0005i>T\u0006\b\u0006\u0002V1B\u0011\u0001IV\u0005\u0003/2\u0012!A\u0017\u001d\t\u000b\u0011+\u0001\u0019A#)\u0005\u0015I\u0015!\u0002;p5F2DC\u0001/`!\t\u0001U,\u0003\u0002_Y\t\u0019!,\r\u001c\t\u000b\u00113\u0001\u0019A#)\u0005\u0019I\u0015!\u0002;p5N\u0012DCA2g!\t\u0001E-\u0003\u0002fY\t\u0019!l\r\u001a\t\u000b\u0011;\u0001\u0019A#)\u0005\u001dI\u0015!\u0002;p5Z\"DC\u00016n!\t\u00015.\u0003\u0002mY\t\u0019!L\u000e\u001b\t\u000b\u0011C\u0001\u0019A#)\u0005!I\u0015a\u0001;p\u001dR\u0011\u0011\u000f\u001e\t\u0003\u0001JL!a\u001d\u0017\u0003\u00039CQ\u0001R\u0005A\u0002\u0015C#!C%\u0002\tQ|g\n\u000f\u000b\u0003qn\u0004\"\u0001Q=\n\u0005id#A\u0001(9\u0011\u0015!%\u00021\u0001FQ\tQ\u0011*A\u0003u_:\u000bd\u0007F\u0002\u0000\u0003\u000b\u00012\u0001QA\u0001\u0013\r\t\u0019\u0001\f\u0002\u0004\u001dF2\u0004\"\u0002#\f\u0001\u0004)\u0005FA\u0006J\u0003\u0015!xNT\u001a3)\u0011\ti!a\u0005\u0011\u0007\u0001\u000by!C\u0002\u0002\u00121\u00121AT\u001a3\u0011\u0015!E\u00021\u0001FQ\ta\u0011*A\u0003u_:3D\u0007\u0006\u0003\u0002\u001c\u0005\u0005\u0002c\u0001!\u0002\u001e%\u0019\u0011q\u0004\u0017\u0003\u000793D\u0007C\u0003E\u001b\u0001\u0007Q\t\u000b\u0002\u000e\u0013\u0006!Ao\\*9)\u0011\tI#a\f\u0011\u0007\u0001\u000bY#C\u0002\u0002.1\u0012!a\u0015\u001d\t\u000b\u0011s\u0001\u0019A#)\u00059I\u0015!\u0002;p\'F2D\u0003BA\u001c\u0003{\u00012\u0001QA\u001d\u0013\r\tY\u0004\f\u0002\u0004\'F2\u0004\"\u0002#\u0010\u0001\u0004)\u0005FA\bJ\u0003\u0015!xnU\u001a3)\u0011\t)%a\u0013\u0011\u0007\u0001\u000b9%C\u0002\u0002J1\u00121aU\u001a3\u0011\u0015!\u0005\u00031\u0001FQ\t\u0001\u0012*A\u0003u_N3D\u0007\u0006\u0003\u0002T\u0005e\u0003c\u0001!\u0002V%\u0019\u0011q\u000b\u0017\u0003\u0007M3D\u0007C\u0003E#\u0001\u0007Q\t\u000b\u0002\u0012\u0013\u0006!Ao\\+9)\u0011\t\t\'a\u001a\u0011\u0007\u0001\u000b\u0019\'C\u0002\u0002f1\u0012!!\u0016\u001d\t\u000b\u0011\u0013\u0002\u0019A#)\u0005II\u0015!\u0002;p+F2D\u0003BA8\u0003k\u00022\u0001QA9\u0013\r\t\u0019\b\f\u0002\u0004+F2\u0004\"\u0002#\u0014\u0001\u0004)\u0005FA\nJ\u0003\u0015!x.V\u00198)\u0011\ti(a!\u0011\u0007\u0001\u000by(C\u0002\u0002\u00022\u00121!V\u00198\u0011\u0015!E\u00031\u0001FQ\t!\u0012*A\u0003u_V\u000b\u0004\b\u0006\u0003\u0002\f\u0006E\u0005c\u0001!\u0002\u000e&\u0019\u0011q\u0012\u0017\u0003\u0007U\u000b\u0004\bC\u0003E+\u0001\u0007Q\t\u000b\u0002\u0016\u0013\u0006)Ao\\+2sQ!\u0011\u0011TAP!\r\u0001\u00151T\u0005\u0004\u0003;c#aA+2s!)AI\u0006a\u0001\u000b\"\u0012a#S\u0001\u0006i>,&\u0007\r\u000b\u0005\u0003O\u000bi\u000bE\u0002A\u0003SK1!a+-\u0005\r)&\u0007\r\u0005\u0006\t^\u0001\r!\u0012\u0015\u0003/%\u000bQ\u0001^8VeE\"B!!.\u0002<B\u0019\u0001)a.\n\u0007\u0005eFFA\u0002VeEBQ\u0001\u0012\rA\u0002\u0015C#\u0001G%\u0002\u000bQ|WK\r\u001a\u0015\t\u0005\r\u0017\u0011\u001a\t\u0004\u0001\u0006\u0015\u0017bAAdY\t\u0019QK\r\u001a\t\u000b\u0011K\u0002\u0019A#)\u0005eI\u0015!\u0002;p+J\u001aD\u0003BAi\u0003/\u00042\u0001QAj\u0013\r\t)\u000e\f\u0002\u0004+J\u001a\u0004\"\u0002#\u001b\u0001\u0004)\u0005F\u0001\u000eJ\u0003\u0015!x.\u0016\u001a5)\u0011\ty.!:\u0011\u0007\u0001\u000b\t/C\u0002\u0002d2\u00121!\u0016\u001a5\u0011\u0015!5\u00041\u0001FQ\tY\u0012*A\u0003u_V\u0013T\u0007\u0006\u0003\u0002n\u0006M\bc\u0001!\u0002p&\u0019\u0011\u0011\u001f\u0017\u0003\u0007U\u0013T\u0007C\u0003E9\u0001\u0007Q\t\u000b\u0002\u001d\u0013\u0006)Ao\\+3mQ!\u00111 B\u0001!\r\u0001\u0015Q`\u0005\u0004\u0003\u007fd#aA+3m!)A)\ba\u0001\u000b\"\u0012Q$S\u0001\u0006i>,&g\u000e\u000b\u0005\u0005\u0013\u0011y\u0001E\u0002A\u0005\u0017I1A!\u0004-\u0005\r)&g\u000e\u0005\u0006\tz\u0001\r!\u0012\u0015\u0003=%\u000bQ\u0001^8Vea\"BAa\u0006\u0003\u001eA\u0019\u0001I!\u0007\n\u0007\tmAFA\u0002VeaBQ\u0001R\u0010A\u0002\u0015C#aH%\u0002\u000bQ|WKM\u001d\u0015\t\t\u0015\"1\u0006\t\u0004\u0001\n\u001d\u0012b\u0001B\u0015Y\t\u0019QKM\u001d\t\u000b\u0011\u0003\u0003\u0019A#)\u0005\u0001J\u0015!\u0002;p+N\u0002D\u0003\u0002B\u001a\u0005s\u00012\u0001\u0011B\u001b\u0013\r\u00119\u0004\f\u0002\u0004+N\u0002\u0004\"\u0002#\"\u0001\u0004)\u0005FA\u0011J\u0003\u0015!x.V\u001a2)\u0011\u0011\tEa\u0012\u0011\u0007\u0001\u0013\u0019%C\u0002\u0003F1\u00121!V\u001a2\u0011\u0015!%\u00051\u0001FQ\t\u0011\u0013*A\u0003u_V\u001b$\u0007F\u0002F\u0005\u001fBQ\u0001R\u0012A\u0002\u0015C#aI%\u0002\u000bQ|WK\u000e\u001b\u0015\t\t]#Q\f\t\u0004\u0001\ne\u0013b\u0001B.Y\t\u0019QK\u000e\u001b\t\u000b\u0011#\u0003\u0019A#)\u0005\u0011J\u0015a\u0001;p%R!!Q\rB6!\r\u0001%qM\u0005\u0004\u0005Sb#!\u0001*\t\u000b\u0011+\u0003\u0019A#)\u0005\u0015J\u0015\u0001\u0003;p%\u0006<8k\r\u001a\u0015\t\u0005\u0015#1\u000f\u0005\u0006\t\u001a\u0002\r!\u0012\u0015\u0003M%\u000b\u0001\u0002^8SC^45G\r\u000b\u0005\u0005w\u0012\t\tE\u0002A\u0005{J1Aa -\u0005\r15G\r\u0005\u0006\t\u001e\u0002\r!\u0012\u0015\u0003O%\u000b1\u0001^8D)\u0011\u0011IIa$\u0011\u0007\u0001\u0013Y)C\u0002\u0003\u000e2\u0012\u0011a\u0011\u0005\u0006\t\"\u0002\r!\u0012\u0015\u0003Q%\u0003
    #9 = Utf8               toC
   #10 = Utf8               (I)I
   #11 = Utf8               n
   #12 = Utf8               org/sireum/conversions/U32_Ext$
   #13 = Class              #12           // org/sireum/conversions/U32_Ext$
   #14 = Utf8               MODULE$
   #15 = Utf8               Lorg/sireum/conversions/U32_Ext$;
   #16 = NameAndType        #14:#15       // MODULE$:Lorg/sireum/conversions/U32_Ext$;
   #17 = Fieldref           #13.#16       // org/sireum/conversions/U32_Ext$.MODULE$:Lorg/sireum/conversions/U32_Ext$;
   #18 = NameAndType        #9:#10        // toC:(I)I
   #19 = Methodref          #13.#18       // org/sireum/conversions/U32_Ext$.toC:(I)I
   #20 = Utf8               I
   #21 = Utf8               toRawF32
   #22 = Utf8               (I)F
   #23 = NameAndType        #21:#22       // toRawF32:(I)F
   #24 = Methodref          #13.#23       // org/sireum/conversions/U32_Ext$.toRawF32:(I)F
   #25 = Utf8               toRawS32
   #26 = NameAndType        #25:#10       // toRawS32:(I)I
   #27 = Methodref          #13.#26       // org/sireum/conversions/U32_Ext$.toRawS32:(I)I
   #28 = Utf8               toR
   #29 = Utf8               (I)Lscala/math/BigDecimal;
   #30 = NameAndType        #28:#29       // toR:(I)Lscala/math/BigDecimal;
   #31 = Methodref          #13.#30       // org/sireum/conversions/U32_Ext$.toR:(I)Lscala/math/BigDecimal;
   #32 = Utf8               toU64
   #33 = Utf8               (I)J
   #34 = NameAndType        #32:#33       // toU64:(I)J
   #35 = Methodref          #13.#34       // org/sireum/conversions/U32_Ext$.toU64:(I)J
   #36 = Utf8               toU32
   #37 = NameAndType        #36:#10       // toU32:(I)I
   #38 = Methodref          #13.#37       // org/sireum/conversions/U32_Ext$.toU32:(I)I
   #39 = Utf8               toU31
   #40 = NameAndType        #39:#10       // toU31:(I)I
   #41 = Methodref          #13.#40       // org/sireum/conversions/U32_Ext$.toU31:(I)I
   #42 = Utf8               toU30
   #43 = NameAndType        #42:#10       // toU30:(I)I
   #44 = Methodref          #13.#43       // org/sireum/conversions/U32_Ext$.toU30:(I)I
   #45 = Utf8               toU29
   #46 = NameAndType        #45:#10       // toU29:(I)I
   #47 = Methodref          #13.#46       // org/sireum/conversions/U32_Ext$.toU29:(I)I
   #48 = Utf8               toU28
   #49 = NameAndType        #48:#10       // toU28:(I)I
   #50 = Methodref          #13.#49       // org/sireum/conversions/U32_Ext$.toU28:(I)I
   #51 = Utf8               toU27
   #52 = NameAndType        #51:#10       // toU27:(I)I
   #53 = Methodref          #13.#52       // org/sireum/conversions/U32_Ext$.toU27:(I)I
   #54 = Utf8               toU26
   #55 = NameAndType        #54:#10       // toU26:(I)I
   #56 = Methodref          #13.#55       // org/sireum/conversions/U32_Ext$.toU26:(I)I
   #57 = Utf8               toU25
   #58 = NameAndType        #57:#10       // toU25:(I)I
   #59 = Methodref          #13.#58       // org/sireum/conversions/U32_Ext$.toU25:(I)I
   #60 = Utf8               toU24
   #61 = NameAndType        #60:#10       // toU24:(I)I
   #62 = Methodref          #13.#61       // org/sireum/conversions/U32_Ext$.toU24:(I)I
   #63 = Utf8               toU23
   #64 = NameAndType        #63:#10       // toU23:(I)I
   #65 = Methodref          #13.#64       // org/sireum/conversions/U32_Ext$.toU23:(I)I
   #66 = Utf8               toU22
   #67 = NameAndType        #66:#10       // toU22:(I)I
   #68 = Methodref          #13.#67       // org/sireum/conversions/U32_Ext$.toU22:(I)I
   #69 = Utf8               toU21
   #70 = NameAndType        #69:#10       // toU21:(I)I
   #71 = Methodref          #13.#70       // org/sireum/conversions/U32_Ext$.toU21:(I)I
   #72 = Utf8               toU20
   #73 = NameAndType        #72:#10       // toU20:(I)I
   #74 = Methodref          #13.#73       // org/sireum/conversions/U32_Ext$.toU20:(I)I
   #75 = Utf8               toU19
   #76 = NameAndType        #75:#10       // toU19:(I)I
   #77 = Methodref          #13.#76       // org/sireum/conversions/U32_Ext$.toU19:(I)I
   #78 = Utf8               toU18
   #79 = NameAndType        #78:#10       // toU18:(I)I
   #80 = Methodref          #13.#79       // org/sireum/conversions/U32_Ext$.toU18:(I)I
   #81 = Utf8               toU17
   #82 = NameAndType        #81:#10       // toU17:(I)I
   #83 = Methodref          #13.#82       // org/sireum/conversions/U32_Ext$.toU17:(I)I
   #84 = Utf8               toU16
   #85 = Utf8               (I)S
   #86 = NameAndType        #84:#85       // toU16:(I)S
   #87 = Methodref          #13.#86       // org/sireum/conversions/U32_Ext$.toU16:(I)S
   #88 = Utf8               toU8
   #89 = Utf8               (I)B
   #90 = NameAndType        #88:#89       // toU8:(I)B
   #91 = Methodref          #13.#90       // org/sireum/conversions/U32_Ext$.toU8:(I)B
   #92 = Utf8               toS64
   #93 = NameAndType        #92:#33       // toS64:(I)J
   #94 = Methodref          #13.#93       // org/sireum/conversions/U32_Ext$.toS64:(I)J
   #95 = Utf8               toS32
   #96 = NameAndType        #95:#10       // toS32:(I)I
   #97 = Methodref          #13.#96       // org/sireum/conversions/U32_Ext$.toS32:(I)I
   #98 = Utf8               toS16
   #99 = NameAndType        #98:#85       // toS16:(I)S
  #100 = Methodref          #13.#99       // org/sireum/conversions/U32_Ext$.toS16:(I)S
  #101 = Utf8               toS8
  #102 = NameAndType        #101:#89      // toS8:(I)B
  #103 = Methodref          #13.#102      // org/sireum/conversions/U32_Ext$.toS8:(I)B
  #104 = Utf8               toN64
  #105 = Utf8               (I)Lorg/sireum/Z;
  #106 = NameAndType        #104:#105     // toN64:(I)Lorg/sireum/Z;
  #107 = Methodref          #13.#106      // org/sireum/conversions/U32_Ext$.toN64:(I)Lorg/sireum/Z;
  #108 = Utf8               toN32
  #109 = NameAndType        #108:#105     // toN32:(I)Lorg/sireum/Z;
  #110 = Methodref          #13.#109      // org/sireum/conversions/U32_Ext$.toN32:(I)Lorg/sireum/Z;
  #111 = Utf8               toN16
  #112 = NameAndType        #111:#105     // toN16:(I)Lorg/sireum/Z;
  #113 = Methodref          #13.#112      // org/sireum/conversions/U32_Ext$.toN16:(I)Lorg/sireum/Z;
  #114 = Utf8               toN8
  #115 = NameAndType        #114:#105     // toN8:(I)Lorg/sireum/Z;
  #116 = Methodref          #13.#115      // org/sireum/conversions/U32_Ext$.toN8:(I)Lorg/sireum/Z;
  #117 = Utf8               toN
  #118 = NameAndType        #117:#105     // toN:(I)Lorg/sireum/Z;
  #119 = Methodref          #13.#118      // org/sireum/conversions/U32_Ext$.toN:(I)Lorg/sireum/Z;
  #120 = Utf8               toZ64
  #121 = NameAndType        #120:#105     // toZ64:(I)Lorg/sireum/Z;
  #122 = Methodref          #13.#121      // org/sireum/conversions/U32_Ext$.toZ64:(I)Lorg/sireum/Z;
  #123 = Utf8               toZ32
  #124 = NameAndType        #123:#105     // toZ32:(I)Lorg/sireum/Z;
  #125 = Methodref          #13.#124      // org/sireum/conversions/U32_Ext$.toZ32:(I)Lorg/sireum/Z;
  #126 = Utf8               toZ16
  #127 = NameAndType        #126:#105     // toZ16:(I)Lorg/sireum/Z;
  #128 = Methodref          #13.#127      // org/sireum/conversions/U32_Ext$.toZ16:(I)Lorg/sireum/Z;
  #129 = Utf8               toZ8
  #130 = NameAndType        #129:#105     // toZ8:(I)Lorg/sireum/Z;
  #131 = Methodref          #13.#130      // org/sireum/conversions/U32_Ext$.toZ8:(I)Lorg/sireum/Z;
  #132 = Utf8               toZ
  #133 = NameAndType        #132:#105     // toZ:(I)Lorg/sireum/Z;
  #134 = Methodref          #13.#133      // org/sireum/conversions/U32_Ext$.toZ:(I)Lorg/sireum/Z;
  #135 = Utf8               toB
  #136 = Utf8               (I)Z
  #137 = NameAndType        #135:#136     // toB:(I)Z
  #138 = Methodref          #13.#137      // org/sireum/conversions/U32_Ext$.toB:(I)Z
  #139 = Utf8               Code
  #140 = Utf8               LocalVariableTable
  #141 = Utf8               MethodParameters
  #142 = Utf8               SourceFile
  #143 = Utf8               RuntimeVisibleAnnotations
  #144 = Utf8               ScalaSig
{
  public static int toC(int);
    descriptor: (I)I
    flags: (0x0009) ACC_PUBLIC, ACC_STATIC
    Code:
      stack=2, locals=1, args_size=1
         0: getstatic     #17                 // Field org/sireum/conversions/U32_Ext$.MODULE$:Lorg/sireum/conversions/U32_Ext$;
         3: iload_0
         4: invokevirtual #19                 // Method org/sireum/conversions/U32_Ext$.toC:(I)I
         7: ireturn
      LocalVariableTable:
        Start  Length  Slot  Name   Signature
            0       8     0     n   I
    MethodParameters:
      Name                           Flags
      n                              final

  public static float toRawF32(int);
    descriptor: (I)F
    flags: (0x0009) ACC_PUBLIC, ACC_STATIC
    Code:
      stack=2, locals=1, args_size=1
         0: getstatic     #17                 // Field org/sireum/conversions/U32_Ext$.MODULE$:Lorg/sireum/conversions/U32_Ext$;
         3: iload_0
         4: invokevirtual #24                 // Method org/sireum/conversions/U32_Ext$.toRawF32:(I)F
         7: freturn
      LocalVariableTable:
        Start  Length  Slot  Name   Signature
            0       8     0     n   I
    MethodParameters:
      Name                           Flags
      n                              final

  public static int toRawS32(int);
    descriptor: (I)I
    flags: (0x0009) ACC_PUBLIC, ACC_STATIC
    Code:
      stack=2, locals=1, args_size=1
         0: getstatic     #17                 // Field org/sireum/conversions/U32_Ext$.MODULE$:Lorg/sireum/conversions/U32_Ext$;
         3: iload_0
         4: invokevirtual #27                 // Method org/sireum/conversions/U32_Ext$.toRawS32:(I)I
         7: ireturn
      LocalVariableTable:
        Start  Length  Slot  Name   Signature
            0       8     0     n   I
    MethodParameters:
      Name                           Flags
      n                              final

  public static scala.math.BigDecimal toR(int);
    descriptor: (I)Lscala/math/BigDecimal;
    flags: (0x0009) ACC_PUBLIC, ACC_STATIC
    Code:
      stack=2, locals=1, args_size=1
         0: getstatic     #17                 // Field org/sireum/conversions/U32_Ext$.MODULE$:Lorg/sireum/conversions/U32_Ext$;
         3: iload_0
         4: invokevirtual #31                 // Method org/sireum/conversions/U32_Ext$.toR:(I)Lscala/math/BigDecimal;
         7: areturn
      LocalVariableTable:
        Start  Length  Slot  Name   Signature
            0       8     0     n   I
    MethodParameters:
      Name                           Flags
      n                              final

  public static long toU64(int);
    descriptor: (I)J
    flags: (0x0009) ACC_PUBLIC, ACC_STATIC
    Code:
      stack=2, locals=1, args_size=1
         0: getstatic     #17                 // Field org/sireum/conversions/U32_Ext$.MODULE$:Lorg/sireum/conversions/U32_Ext$;
         3: iload_0
         4: invokevirtual #35                 // Method org/sireum/conversions/U32_Ext$.toU64:(I)J
         7: lreturn
      LocalVariableTable:
        Start  Length  Slot  Name   Signature
            0       8     0     n   I
    MethodParameters:
      Name                           Flags
      n                              final

  public static int toU32(int);
    descriptor: (I)I
    flags: (0x0009) ACC_PUBLIC, ACC_STATIC
    Code:
      stack=2, locals=1, args_size=1
         0: getstatic     #17                 // Field org/sireum/conversions/U32_Ext$.MODULE$:Lorg/sireum/conversions/U32_Ext$;
         3: iload_0
         4: invokevirtual #38                 // Method org/sireum/conversions/U32_Ext$.toU32:(I)I
         7: ireturn
      LocalVariableTable:
        Start  Length  Slot  Name   Signature
            0       8     0     n   I
    MethodParameters:
      Name                           Flags
      n                              final

  public static int toU31(int);
    descriptor: (I)I
    flags: (0x0009) ACC_PUBLIC, ACC_STATIC
    Code:
      stack=2, locals=1, args_size=1
         0: getstatic     #17                 // Field org/sireum/conversions/U32_Ext$.MODULE$:Lorg/sireum/conversions/U32_Ext$;
         3: iload_0
         4: invokevirtual #41                 // Method org/sireum/conversions/U32_Ext$.toU31:(I)I
         7: ireturn
      LocalVariableTable:
        Start  Length  Slot  Name   Signature
            0       8     0     n   I
    MethodParameters:
      Name                           Flags
      n                              final

  public static int toU30(int);
    descriptor: (I)I
    flags: (0x0009) ACC_PUBLIC, ACC_STATIC
    Code:
      stack=2, locals=1, args_size=1
         0: getstatic     #17                 // Field org/sireum/conversions/U32_Ext$.MODULE$:Lorg/sireum/conversions/U32_Ext$;
         3: iload_0
         4: invokevirtual #44                 // Method org/sireum/conversions/U32_Ext$.toU30:(I)I
         7: ireturn
      LocalVariableTable:
        Start  Length  Slot  Name   Signature
            0       8     0     n   I
    MethodParameters:
      Name                           Flags
      n                              final

  public static int toU29(int);
    descriptor: (I)I
    flags: (0x0009) ACC_PUBLIC, ACC_STATIC
    Code:
      stack=2, locals=1, args_size=1
         0: getstatic     #17                 // Field org/sireum/conversions/U32_Ext$.MODULE$:Lorg/sireum/conversions/U32_Ext$;
         3: iload_0
         4: invokevirtual #47                 // Method org/sireum/conversions/U32_Ext$.toU29:(I)I
         7: ireturn
      LocalVariableTable:
        Start  Length  Slot  Name   Signature
            0       8     0     n   I
    MethodParameters:
      Name                           Flags
      n                              final

  public static int toU28(int);
    descriptor: (I)I
    flags: (0x0009) ACC_PUBLIC, ACC_STATIC
    Code:
      stack=2, locals=1, args_size=1
         0: getstatic     #17                 // Field org/sireum/conversions/U32_Ext$.MODULE$:Lorg/sireum/conversions/U32_Ext$;
         3: iload_0
         4: invokevirtual #50                 // Method org/sireum/conversions/U32_Ext$.toU28:(I)I
         7: ireturn
      LocalVariableTable:
        Start  Length  Slot  Name   Signature
            0       8     0     n   I
    MethodParameters:
      Name                           Flags
      n                              final

  public static int toU27(int);
    descriptor: (I)I
    flags: (0x0009) ACC_PUBLIC, ACC_STATIC
    Code:
      stack=2, locals=1, args_size=1
         0: getstatic     #17                 // Field org/sireum/conversions/U32_Ext$.MODULE$:Lorg/sireum/conversions/U32_Ext$;
         3: iload_0
         4: invokevirtual #53                 // Method org/sireum/conversions/U32_Ext$.toU27:(I)I
         7: ireturn
      LocalVariableTable:
        Start  Length  Slot  Name   Signature
            0       8     0     n   I
    MethodParameters:
      Name                           Flags
      n                              final

  public static int toU26(int);
    descriptor: (I)I
    flags: (0x0009) ACC_PUBLIC, ACC_STATIC
    Code:
      stack=2, locals=1, args_size=1
         0: getstatic     #17                 // Field org/sireum/conversions/U32_Ext$.MODULE$:Lorg/sireum/conversions/U32_Ext$;
         3: iload_0
         4: invokevirtual #56                 // Method org/sireum/conversions/U32_Ext$.toU26:(I)I
         7: ireturn
      LocalVariableTable:
        Start  Length  Slot  Name   Signature
            0       8     0     n   I
    MethodParameters:
      Name                           Flags
      n                              final

  public static int toU25(int);
    descriptor: (I)I
    flags: (0x0009) ACC_PUBLIC, ACC_STATIC
    Code:
      stack=2, locals=1, args_size=1
         0: getstatic     #17                 // Field org/sireum/conversions/U32_Ext$.MODULE$:Lorg/sireum/conversions/U32_Ext$;
         3: iload_0
         4: invokevirtual #59                 // Method org/sireum/conversions/U32_Ext$.toU25:(I)I
         7: ireturn
      LocalVariableTable:
        Start  Length  Slot  Name   Signature
            0       8     0     n   I
    MethodParameters:
      Name                           Flags
      n                              final

  public static int toU24(int);
    descriptor: (I)I
    flags: (0x0009) ACC_PUBLIC, ACC_STATIC
    Code:
      stack=2, locals=1, args_size=1
         0: getstatic     #17                 // Field org/sireum/conversions/U32_Ext$.MODULE$:Lorg/sireum/conversions/U32_Ext$;
         3: iload_0
         4: invokevirtual #62                 // Method org/sireum/conversions/U32_Ext$.toU24:(I)I
         7: ireturn
      LocalVariableTable:
        Start  Length  Slot  Name   Signature
            0       8     0     n   I
    MethodParameters:
      Name                           Flags
      n                              final

  public static int toU23(int);
    descriptor: (I)I
    flags: (0x0009) ACC_PUBLIC, ACC_STATIC
    Code:
      stack=2, locals=1, args_size=1
         0: getstatic     #17                 // Field org/sireum/conversions/U32_Ext$.MODULE$:Lorg/sireum/conversions/U32_Ext$;
         3: iload_0
         4: invokevirtual #65                 // Method org/sireum/conversions/U32_Ext$.toU23:(I)I
         7: ireturn
      LocalVariableTable:
        Start  Length  Slot  Name   Signature
            0       8     0     n   I
    MethodParameters:
      Name                           Flags
      n                              final

  public static int toU22(int);
    descriptor: (I)I
    flags: (0x0009) ACC_PUBLIC, ACC_STATIC
    Code:
      stack=2, locals=1, args_size=1
         0: getstatic     #17                 // Field org/sireum/conversions/U32_Ext$.MODULE$:Lorg/sireum/conversions/U32_Ext$;
         3: iload_0
         4: invokevirtual #68                 // Method org/sireum/conversions/U32_Ext$.toU22:(I)I
         7: ireturn
      LocalVariableTable:
        Start  Length  Slot  Name   Signature
            0       8     0     n   I
    MethodParameters:
      Name                           Flags
      n                              final

  public static int toU21(int);
    descriptor: (I)I
    flags: (0x0009) ACC_PUBLIC, ACC_STATIC
    Code:
      stack=2, locals=1, args_size=1
         0: getstatic     #17                 // Field org/sireum/conversions/U32_Ext$.MODULE$:Lorg/sireum/conversions/U32_Ext$;
         3: iload_0
         4: invokevirtual #71                 // Method org/sireum/conversions/U32_Ext$.toU21:(I)I
         7: ireturn
      LocalVariableTable:
        Start  Length  Slot  Name   Signature
            0       8     0     n   I
    MethodParameters:
      Name                           Flags
      n                              final

  public static int toU20(int);
    descriptor: (I)I
    flags: (0x0009) ACC_PUBLIC, ACC_STATIC
    Code:
      stack=2, locals=1, args_size=1
         0: getstatic     #17                 // Field org/sireum/conversions/U32_Ext$.MODULE$:Lorg/sireum/conversions/U32_Ext$;
         3: iload_0
         4: invokevirtual #74                 // Method org/sireum/conversions/U32_Ext$.toU20:(I)I
         7: ireturn
      LocalVariableTable:
        Start  Length  Slot  Name   Signature
            0       8     0     n   I
    MethodParameters:
      Name                           Flags
      n                              final

  public static int toU19(int);
    descriptor: (I)I
    flags: (0x0009) ACC_PUBLIC, ACC_STATIC
    Code:
      stack=2, locals=1, args_size=1
         0: getstatic     #17                 // Field org/sireum/conversions/U32_Ext$.MODULE$:Lorg/sireum/conversions/U32_Ext$;
         3: iload_0
         4: invokevirtual #77                 // Method org/sireum/conversions/U32_Ext$.toU19:(I)I
         7: ireturn
      LocalVariableTable:
        Start  Length  Slot  Name   Signature
            0       8     0     n   I
    MethodParameters:
      Name                           Flags
      n                              final

  public static int toU18(int);
    descriptor: (I)I
    flags: (0x0009) ACC_PUBLIC, ACC_STATIC
    Code:
      stack=2, locals=1, args_size=1
         0: getstatic     #17                 // Field org/sireum/conversions/U32_Ext$.MODULE$:Lorg/sireum/conversions/U32_Ext$;
         3: iload_0
         4: invokevirtual #80                 // Method org/sireum/conversions/U32_Ext$.toU18:(I)I
         7: ireturn
      LocalVariableTable:
        Start  Length  Slot  Name   Signature
            0       8     0     n   I
    MethodParameters:
      Name                           Flags
      n                              final

  public static int toU17(int);
    descriptor: (I)I
    flags: (0x0009) ACC_PUBLIC, ACC_STATIC
    Code:
      stack=2, locals=1, args_size=1
         0: getstatic     #17                 // Field org/sireum/conversions/U32_Ext$.MODULE$:Lorg/sireum/conversions/U32_Ext$;
         3: iload_0
         4: invokevirtual #83                 // Method org/sireum/conversions/U32_Ext$.toU17:(I)I
         7: ireturn
      LocalVariableTable:
        Start  Length  Slot  Name   Signature
            0       8     0     n   I
    MethodParameters:
      Name                           Flags
      n                              final

  public static short toU16(int);
    descriptor: (I)S
    flags: (0x0009) ACC_PUBLIC, ACC_STATIC
    Code:
      stack=2, locals=1, args_size=1
         0: getstatic     #17                 // Field org/sireum/conversions/U32_Ext$.MODULE$:Lorg/sireum/conversions/U32_Ext$;
         3: iload_0
         4: invokevirtual #87                 // Method org/sireum/conversions/U32_Ext$.toU16:(I)S
         7: ireturn
      LocalVariableTable:
        Start  Length  Slot  Name   Signature
            0       8     0     n   I
    MethodParameters:
      Name                           Flags
      n                              final

  public static byte toU8(int);
    descriptor: (I)B
    flags: (0x0009) ACC_PUBLIC, ACC_STATIC
    Code:
      stack=2, locals=1, args_size=1
         0: getstatic     #17                 // Field org/sireum/conversions/U32_Ext$.MODULE$:Lorg/sireum/conversions/U32_Ext$;
         3: iload_0
         4: invokevirtual #91                 // Method org/sireum/conversions/U32_Ext$.toU8:(I)B
         7: ireturn
      LocalVariableTable:
        Start  Length  Slot  Name   Signature
            0       8     0     n   I
    MethodParameters:
      Name                           Flags
      n                              final

  public static long toS64(int);
    descriptor: (I)J
    flags: (0x0009) ACC_PUBLIC, ACC_STATIC
    Code:
      stack=2, locals=1, args_size=1
         0: getstatic     #17                 // Field org/sireum/conversions/U32_Ext$.MODULE$:Lorg/sireum/conversions/U32_Ext$;
         3: iload_0
         4: invokevirtual #94                 // Method org/sireum/conversions/U32_Ext$.toS64:(I)J
         7: lreturn
      LocalVariableTable:
        Start  Length  Slot  Name   Signature
            0       8     0     n   I
    MethodParameters:
      Name                           Flags
      n                              final

  public static int toS32(int);
    descriptor: (I)I
    flags: (0x0009) ACC_PUBLIC, ACC_STATIC
    Code:
      stack=2, locals=1, args_size=1
         0: getstatic     #17                 // Field org/sireum/conversions/U32_Ext$.MODULE$:Lorg/sireum/conversions/U32_Ext$;
         3: iload_0
         4: invokevirtual #97                 // Method org/sireum/conversions/U32_Ext$.toS32:(I)I
         7: ireturn
      LocalVariableTable:
        Start  Length  Slot  Name   Signature
            0       8     0     n   I
    MethodParameters:
      Name                           Flags
      n                              final

  public static short toS16(int);
    descriptor: (I)S
    flags: (0x0009) ACC_PUBLIC, ACC_STATIC
    Code:
      stack=2, locals=1, args_size=1
         0: getstatic     #17                 // Field org/sireum/conversions/U32_Ext$.MODULE$:Lorg/sireum/conversions/U32_Ext$;
         3: iload_0
         4: invokevirtual #100                // Method org/sireum/conversions/U32_Ext$.toS16:(I)S
         7: ireturn
      LocalVariableTable:
        Start  Length  Slot  Name   Signature
            0       8     0     n   I
    MethodParameters:
      Name                           Flags
      n                              final

  public static byte toS8(int);
    descriptor: (I)B
    flags: (0x0009) ACC_PUBLIC, ACC_STATIC
    Code:
      stack=2, locals=1, args_size=1
         0: getstatic     #17                 // Field org/sireum/conversions/U32_Ext$.MODULE$:Lorg/sireum/conversions/U32_Ext$;
         3: iload_0
         4: invokevirtual #103                // Method org/sireum/conversions/U32_Ext$.toS8:(I)B
         7: ireturn
      LocalVariableTable:
        Start  Length  Slot  Name   Signature
            0       8     0     n   I
    MethodParameters:
      Name                           Flags
      n                              final

  public static org.sireum.Z toN64(int);
    descriptor: (I)Lorg/sireum/Z;
    flags: (0x0009) ACC_PUBLIC, ACC_STATIC
    Code:
      stack=2, locals=1, args_size=1
         0: getstatic     #17                 // Field org/sireum/conversions/U32_Ext$.MODULE$:Lorg/sireum/conversions/U32_Ext$;
         3: iload_0
         4: invokevirtual #107                // Method org/sireum/conversions/U32_Ext$.toN64:(I)Lorg/sireum/Z;
         7: areturn
      LocalVariableTable:
        Start  Length  Slot  Name   Signature
            0       8     0     n   I
    MethodParameters:
      Name                           Flags
      n                              final

  public static org.sireum.Z toN32(int);
    descriptor: (I)Lorg/sireum/Z;
    flags: (0x0009) ACC_PUBLIC, ACC_STATIC
    Code:
      stack=2, locals=1, args_size=1
         0: getstatic     #17                 // Field org/sireum/conversions/U32_Ext$.MODULE$:Lorg/sireum/conversions/U32_Ext$;
         3: iload_0
         4: invokevirtual #110                // Method org/sireum/conversions/U32_Ext$.toN32:(I)Lorg/sireum/Z;
         7: areturn
      LocalVariableTable:
        Start  Length  Slot  Name   Signature
            0       8     0     n   I
    MethodParameters:
      Name                           Flags
      n                              final

  public static org.sireum.Z toN16(int);
    descriptor: (I)Lorg/sireum/Z;
    flags: (0x0009) ACC_PUBLIC, ACC_STATIC
    Code:
      stack=2, locals=1, args_size=1
         0: getstatic     #17                 // Field org/sireum/conversions/U32_Ext$.MODULE$:Lorg/sireum/conversions/U32_Ext$;
         3: iload_0
         4: invokevirtual #113                // Method org/sireum/conversions/U32_Ext$.toN16:(I)Lorg/sireum/Z;
         7: areturn
      LocalVariableTable:
        Start  Length  Slot  Name   Signature
            0       8     0     n   I
    MethodParameters:
      Name                           Flags
      n                              final

  public static org.sireum.Z toN8(int);
    descriptor: (I)Lorg/sireum/Z;
    flags: (0x0009) ACC_PUBLIC, ACC_STATIC
    Code:
      stack=2, locals=1, args_size=1
         0: getstatic     #17                 // Field org/sireum/conversions/U32_Ext$.MODULE$:Lorg/sireum/conversions/U32_Ext$;
         3: iload_0
         4: invokevirtual #116                // Method org/sireum/conversions/U32_Ext$.toN8:(I)Lorg/sireum/Z;
         7: areturn
      LocalVariableTable:
        Start  Length  Slot  Name   Signature
            0       8     0     n   I
    MethodParameters:
      Name                           Flags
      n                              final

  public static org.sireum.Z toN(int);
    descriptor: (I)Lorg/sireum/Z;
    flags: (0x0009) ACC_PUBLIC, ACC_STATIC
    Code:
      stack=2, locals=1, args_size=1
         0: getstatic     #17                 // Field org/sireum/conversions/U32_Ext$.MODULE$:Lorg/sireum/conversions/U32_Ext$;
         3: iload_0
         4: invokevirtual #119                // Method org/sireum/conversions/U32_Ext$.toN:(I)Lorg/sireum/Z;
         7: areturn
      LocalVariableTable:
        Start  Length  Slot  Name   Signature
            0       8     0     n   I
    MethodParameters:
      Name                           Flags
      n                              final

  public static org.sireum.Z toZ64(int);
    descriptor: (I)Lorg/sireum/Z;
    flags: (0x0009) ACC_PUBLIC, ACC_STATIC
    Code:
      stack=2, locals=1, args_size=1
         0: getstatic     #17                 // Field org/sireum/conversions/U32_Ext$.MODULE$:Lorg/sireum/conversions/U32_Ext$;
         3: iload_0
         4: invokevirtual #122                // Method org/sireum/conversions/U32_Ext$.toZ64:(I)Lorg/sireum/Z;
         7: areturn
      LocalVariableTable:
        Start  Length  Slot  Name   Signature
            0       8     0     n   I
    MethodParameters:
      Name                           Flags
      n                              final

  public static org.sireum.Z toZ32(int);
    descriptor: (I)Lorg/sireum/Z;
    flags: (0x0009) ACC_PUBLIC, ACC_STATIC
    Code:
      stack=2, locals=1, args_size=1
         0: getstatic     #17                 // Field org/sireum/conversions/U32_Ext$.MODULE$:Lorg/sireum/conversions/U32_Ext$;
         3: iload_0
         4: invokevirtual #125                // Method org/sireum/conversions/U32_Ext$.toZ32:(I)Lorg/sireum/Z;
         7: areturn
      LocalVariableTable:
        Start  Length  Slot  Name   Signature
            0       8     0     n   I
    MethodParameters:
      Name                           Flags
      n                              final

  public static org.sireum.Z toZ16(int);
    descriptor: (I)Lorg/sireum/Z;
    flags: (0x0009) ACC_PUBLIC, ACC_STATIC
    Code:
      stack=2, locals=1, args_size=1
         0: getstatic     #17                 // Field org/sireum/conversions/U32_Ext$.MODULE$:Lorg/sireum/conversions/U32_Ext$;
         3: iload_0
         4: invokevirtual #128                // Method org/sireum/conversions/U32_Ext$.toZ16:(I)Lorg/sireum/Z;
         7: areturn
      LocalVariableTable:
        Start  Length  Slot  Name   Signature
            0       8     0     n   I
    MethodParameters:
      Name                           Flags
      n                              final

  public static org.sireum.Z toZ8(int);
    descriptor: (I)Lorg/sireum/Z;
    flags: (0x0009) ACC_PUBLIC, ACC_STATIC
    Code:
      stack=2, locals=1, args_size=1
         0: getstatic     #17                 // Field org/sireum/conversions/U32_Ext$.MODULE$:Lorg/sireum/conversions/U32_Ext$;
         3: iload_0
         4: invokevirtual #131                // Method org/sireum/conversions/U32_Ext$.toZ8:(I)Lorg/sireum/Z;
         7: areturn
      LocalVariableTable:
        Start  Length  Slot  Name   Signature
            0       8     0     n   I
    MethodParameters:
      Name                           Flags
      n                              final

  public static org.sireum.Z toZ(int);
    descriptor: (I)Lorg/sireum/Z;
    flags: (0x0009) ACC_PUBLIC, ACC_STATIC
    Code:
      stack=2, locals=1, args_size=1
         0: getstatic     #17                 // Field org/sireum/conversions/U32_Ext$.MODULE$:Lorg/sireum/conversions/U32_Ext$;
         3: iload_0
         4: invokevirtual #134                // Method org/sireum/conversions/U32_Ext$.toZ:(I)Lorg/sireum/Z;
         7: areturn
      LocalVariableTable:
        Start  Length  Slot  Name   Signature
            0       8     0     n   I
    MethodParameters:
      Name                           Flags
      n                              final

  public static boolean toB(int);
    descriptor: (I)Z
    flags: (0x0009) ACC_PUBLIC, ACC_STATIC
    Code:
      stack=2, locals=1, args_size=1
         0: getstatic     #17                 // Field org/sireum/conversions/U32_Ext$.MODULE$:Lorg/sireum/conversions/U32_Ext$;
         3: iload_0
         4: invokevirtual #138                // Method org/sireum/conversions/U32_Ext$.toB:(I)Z
         7: ireturn
      LocalVariableTable:
        Start  Length  Slot  Name   Signature
            0       8     0     n   I
    MethodParameters:
      Name                           Flags
      n                              final
}
SourceFile: "extension.scala"
RuntimeVisibleAnnotations:
  0: #6(#7=s#8)
    scala.reflect.ScalaSignature(
      bytes="\u0006\u0005\tMu!B\u0015+\u0011\u0003\td!B\u001a+\u0011\u0003!\u0004\"B\u001e\u0002\t\u0003a\u0004\"B\u001f\u0002\t\u0003q\u0004\"\u0002\'\u0002\t\u0003i\u0005\"B*\u0002\t\u0003!\u0006\"\u0002.\u0002\t\u0003Y\u0006\"B1\u0002\t\u0003\u0011\u0007\"\u00025\u0002\t\u0003I\u0007\"B8\u0002\t\u0003\u0001\b\"\u0002<\u0002\t\u00039\b\"B?\u0002\t\u0003q\bbBA\u0005\u0003\u0011\u0005\u00111\u0002\u0005\b\u0003/\tA\u0011AA\r\u0011\u001d\t)#\u0001C\u0001\u0003OAq!a\r\u0002\t\u0003\t)\u0004C\u0004\u0002B\u0005!\t!a\u0011\t\u000f\u0005=\u0013\u0001\"\u0001\u0002R!9\u0011QL\u0001\u0005\u0002\u0005}\u0003bBA6\u0003\u0011\u0005\u0011Q\u000e\u0005\b\u0003s\nA\u0011AA>\u0011\u001d\t9)\u0001C\u0001\u0003\u0013Cq!!&\u0002\t\u0003\t9\nC\u0004\u0002$\u0006!\t!!*\t\u000f\u0005E\u0016\u0001\"\u0001\u00024\"9\u0011qX\u0001\u0005\u0002\u0005\u0005\u0007bBAg\u0003\u0011\u0005\u0011q\u001a\u0005\b\u00037\fA\u0011AAo\u0011\u001d\tI/\u0001C\u0001\u0003WDq!a>\u0002\t\u0003\tI\u0010C\u0004\u0003\u0006\u0005!\tAa\u0002\t\u000f\tM\u0011\u0001\"\u0001\u0003\u0016!9!\u0011E\u0001\u0005\u0002\t\r\u0002b\u0002B\u0018\u0003\u0011\u0005!\u0011\u0007\u0005\b\u0005{\tA\u0011\u0001B \u0011\u001d\u0011Y%\u0001C\u0001\u0005\u001bBqAa\u0015\u0002\t\u0003\u0011)\u0006C\u0004\u0003b\u0005!\tAa\u0019\t\u000f\t=\u0014\u0001\"\u0001\u0003r!9!qO\u0001\u0005\u0002\te\u0004b\u0002BC\u0003\u0011\u0005!qQ\u0001\b+N\u0012t,\u0012=u\u0015\tYC&A\u0006d_:4XM]:j_:\u001c(BA\u0017/\u0003\u0019\u0019\u0018N]3v[*\tq&A\u0002pe\u001e\u001c\u0001\u0001\u0005\u00023\u00035\t!FA\u0004VgIzV\t\u001f;\u0014\u0005\u0005)\u0004C\u0001\u001c:\u001b\u00059$\"\u0001\u001d\u0002\u000bM\u001c\u0017\r\\1\n\u0005i:$AB!osJ+g-\u0001\u0004=S:LGO\u0010\u000b\u0002c\u0005\u0019Ao\u001c\"\u0015\u0005}\u001a\u0005C\u0001!B\u001b\u0005a\u0013B\u0001\"-\u0005\u0005\u0011\u0005\"\u0002#\u0004\u0001\u0004)\u0015!\u00018\u0011\u0005\u00013\u0015BA$-\u0005\r)6G\r\u0015\u0003\u0007%\u0003\"\u0001\u0011&\n\u0005-c#\u0001\u00029ve\u0016\f1\u0001^8[)\tq\u0015\u000b\u0005\u0002A\u001f&\u0011\u0001\u000b\f\u0002\u00025\")A\t\u0002a\u0001\u000b\"\u0012A!S\u0001\u0005i>T\u0006\b\u0006\u0002V1B\u0011\u0001IV\u0005\u0003/2\u0012!A\u0017\u001d\t\u000b\u0011+\u0001\u0019A#)\u0005\u0015I\u0015!\u0002;p5F2DC\u0001/`!\t\u0001U,\u0003\u0002_Y\t\u0019!,\r\u001c\t\u000b\u00113\u0001\u0019A#)\u0005\u0019I\u0015!\u0002;p5N\u0012DCA2g!\t\u0001E-\u0003\u0002fY\t\u0019!l\r\u001a\t\u000b\u0011;\u0001\u0019A#)\u0005\u001dI\u0015!\u0002;p5Z\"DC\u00016n!\t\u00015.\u0003\u0002mY\t\u0019!L\u000e\u001b\t\u000b\u0011C\u0001\u0019A#)\u0005!I\u0015a\u0001;p\u001dR\u0011\u0011\u000f\u001e\t\u0003\u0001JL!a\u001d\u0017\u0003\u00039CQ\u0001R\u0005A\u0002\u0015C#!C%\u0002\tQ|g\n\u000f\u000b\u0003qn\u0004\"\u0001Q=\n\u0005id#A\u0001(9\u0011\u0015!%\u00021\u0001FQ\tQ\u0011*A\u0003u_:\u000bd\u0007F\u0002\u0000\u0003\u000b\u00012\u0001QA\u0001\u0013\r\t\u0019\u0001\f\u0002\u0004\u001dF2\u0004\"\u0002#\f\u0001\u0004)\u0005FA\u0006J\u0003\u0015!xNT\u001a3)\u0011\ti!a\u0005\u0011\u0007\u0001\u000by!C\u0002\u0002\u00121\u00121AT\u001a3\u0011\u0015!E\u00021\u0001FQ\ta\u0011*A\u0003u_:3D\u0007\u0006\u0003\u0002\u001c\u0005\u0005\u0002c\u0001!\u0002\u001e%\u0019\u0011q\u0004\u0017\u0003\u000793D\u0007C\u0003E\u001b\u0001\u0007Q\t\u000b\u0002\u000e\u0013\u0006!Ao\\*9)\u0011\tI#a\f\u0011\u0007\u0001\u000bY#C\u0002\u0002.1\u0012!a\u0015\u001d\t\u000b\u0011s\u0001\u0019A#)\u00059I\u0015!\u0002;p\'F2D\u0003BA\u001c\u0003{\u00012\u0001QA\u001d\u0013\r\tY\u0004\f\u0002\u0004\'F2\u0004\"\u0002#\u0010\u0001\u0004)\u0005FA\bJ\u0003\u0015!xnU\u001a3)\u0011\t)%a\u0013\u0011\u0007\u0001\u000b9%C\u0002\u0002J1\u00121aU\u001a3\u0011\u0015!\u0005\u00031\u0001FQ\t\u0001\u0012*A\u0003u_N3D\u0007\u0006\u0003\u0002T\u0005e\u0003c\u0001!\u0002V%\u0019\u0011q\u000b\u0017\u0003\u0007M3D\u0007C\u0003E#\u0001\u0007Q\t\u000b\u0002\u0012\u0013\u0006!Ao\\+9)\u0011\t\t\'a\u001a\u0011\u0007\u0001\u000b\u0019\'C\u0002\u0002f1\u0012!!\u0016\u001d\t\u000b\u0011\u0013\u0002\u0019A#)\u0005II\u0015!\u0002;p+F2D\u0003BA8\u0003k\u00022\u0001QA9\u0013\r\t\u0019\b\f\u0002\u0004+F2\u0004\"\u0002#\u0014\u0001\u0004)\u0005FA\nJ\u0003\u0015!x.V\u00198)\u0011\ti(a!\u0011\u0007\u0001\u000by(C\u0002\u0002\u00022\u00121!V\u00198\u0011\u0015!E\u00031\u0001FQ\t!\u0012*A\u0003u_V\u000b\u0004\b\u0006\u0003\u0002\f\u0006E\u0005c\u0001!\u0002\u000e&\u0019\u0011q\u0012\u0017\u0003\u0007U\u000b\u0004\bC\u0003E+\u0001\u0007Q\t\u000b\u0002\u0016\u0013\u0006)Ao\\+2sQ!\u0011\u0011TAP!\r\u0001\u00151T\u0005\u0004\u0003;c#aA+2s!)AI\u0006a\u0001\u000b\"\u0012a#S\u0001\u0006i>,&\u0007\r\u000b\u0005\u0003O\u000bi\u000bE\u0002A\u0003SK1!a+-\u0005\r)&\u0007\r\u0005\u0006\t^\u0001\r!\u0012\u0015\u0003/%\u000bQ\u0001^8VeE\"B!!.\u0002<B\u0019\u0001)a.\n\u0007\u0005eFFA\u0002VeEBQ\u0001\u0012\rA\u0002\u0015C#\u0001G%\u0002\u000bQ|WK\r\u001a\u0015\t\u0005\r\u0017\u0011\u001a\t\u0004\u0001\u0006\u0015\u0017bAAdY\t\u0019QK\r\u001a\t\u000b\u0011K\u0002\u0019A#)\u0005eI\u0015!\u0002;p+J\u001aD\u0003BAi\u0003/\u00042\u0001QAj\u0013\r\t)\u000e\f\u0002\u0004+J\u001a\u0004\"\u0002#\u001b\u0001\u0004)\u0005F\u0001\u000eJ\u0003\u0015!x.\u0016\u001a5)\u0011\ty.!:\u0011\u0007\u0001\u000b\t/C\u0002\u0002d2\u00121!\u0016\u001a5\u0011\u0015!5\u00041\u0001FQ\tY\u0012*A\u0003u_V\u0013T\u0007\u0006\u0003\u0002n\u0006M\bc\u0001!\u0002p&\u0019\u0011\u0011\u001f\u0017\u0003\u0007U\u0013T\u0007C\u0003E9\u0001\u0007Q\t\u000b\u0002\u001d\u0013\u0006)Ao\\+3mQ!\u00111 B\u0001!\r\u0001\u0015Q`\u0005\u0004\u0003\u007fd#aA+3m!)A)\ba\u0001\u000b\"\u0012Q$S\u0001\u0006i>,&g\u000e\u000b\u0005\u0005\u0013\u0011y\u0001E\u0002A\u0005\u0017I1A!\u0004-\u0005\r)&g\u000e\u0005\u0006\tz\u0001\r!\u0012\u0015\u0003=%\u000bQ\u0001^8Vea\"BAa\u0006\u0003\u001eA\u0019\u0001I!\u0007\n\u0007\tmAFA\u0002VeaBQ\u0001R\u0010A\u0002\u0015C#aH%\u0002\u000bQ|WKM\u001d\u0015\t\t\u0015\"1\u0006\t\u0004\u0001\n\u001d\u0012b\u0001B\u0015Y\t\u0019QKM\u001d\t\u000b\u0011\u0003\u0003\u0019A#)\u0005\u0001J\u0015!\u0002;p+N\u0002D\u0003\u0002B\u001a\u0005s\u00012\u0001\u0011B\u001b\u0013\r\u00119\u0004\f\u0002\u0004+N\u0002\u0004\"\u0002#\"\u0001\u0004)\u0005FA\u0011J\u0003\u0015!x.V\u001a2)\u0011\u0011\tEa\u0012\u0011\u0007\u0001\u0013\u0019%C\u0002\u0003F1\u00121!V\u001a2\u0011\u0015!%\u00051\u0001FQ\t\u0011\u0013*A\u0003u_V\u001b$\u0007F\u0002F\u0005\u001fBQ\u0001R\u0012A\u0002\u0015C#aI%\u0002\u000bQ|WK\u000e\u001b\u0015\t\t]#Q\f\t\u0004\u0001\ne\u0013b\u0001B.Y\t\u0019QK\u000e\u001b\t\u000b\u0011#\u0003\u0019A#)\u0005\u0011J\u0015a\u0001;p%R!!Q\rB6!\r\u0001%qM\u0005\u0004\u0005Sb#!\u0001*\t\u000b\u0011+\u0003\u0019A#)\u0005\u0015J\u0015\u0001\u0003;p%\u0006<8k\r\u001a\u0015\t\u0005\u0015#1\u000f\u0005\u0006\t\u001a\u0002\r!\u0012\u0015\u0003M%\u000b\u0001\u0002^8SC^45G\r\u000b\u0005\u0005w\u0012\t\tE\u0002A\u0005{J1Aa -\u0005\r15G\r\u0005\u0006\t\u001e\u0002\r!\u0012\u0015\u0003O%\u000b1\u0001^8D)\u0011\u0011IIa$\u0011\u0007\u0001\u0013Y)C\u0002\u0003\u000e2\u0012\u0011a\u0011\u0005\u0006\t\"\u0002\r!\u0012\u0015\u0003Q%\u0003"
    )
  ScalaSig: length = 0x3 (unknown attribute)
   05 02 00
