Classfile /Users/mw/Projects/slang-braindump/.jar/jar8/assemble/slang-braindump/assemble/content/org/kohsuke/github/authorization/ImmutableAuthorizationProvider$UserProvider.class
  Last modified May 29, 2022; size 979 bytes
  SHA-256 checksum a637956b649d301732b6580a733984d42f036b0ec7d528f13089266499745b30
  Compiled from "ImmutableAuthorizationProvider.java"
class org.kohsuke.github.authorization.ImmutableAuthorizationProvider$UserProvider extends org.kohsuke.github.authorization.ImmutableAuthorizationProvider implements org.kohsuke.github.authorization.UserAuthorizationProvider
  minor version: 0
  major version: 52
  flags: (0x0020) ACC_SUPER
  this_class: #4                          // org/kohsuke/github/authorization/ImmutableAuthorizationProvider$UserProvider
  super_class: #5                         // org/kohsuke/github/authorization/ImmutableAuthorizationProvider
  interfaces: 1, fields: 1, methods: 3, attributes: 2
Constant pool:
   #1 = Methodref          #4.#26         // org/kohsuke/github/authorization/ImmutableAuthorizationProvider$UserProvider."<init>":(Ljava/lang/String;Ljava/lang/String;)V
   #2 = Methodref          #5.#27         // org/kohsuke/github/authorization/ImmutableAuthorizationProvider."<init>":(Ljava/lang/String;)V
   #3 = Fieldref           #4.#28         // org/kohsuke/github/authorization/ImmutableAuthorizationProvider$UserProvider.login:Ljava/lang/String;
   #4 = Class              #29            // org/kohsuke/github/authorization/ImmutableAuthorizationProvider$UserProvider
   #5 = Class              #30            // org/kohsuke/github/authorization/ImmutableAuthorizationProvider
   #6 = Class              #31            // org/kohsuke/github/authorization/UserAuthorizationProvider
   #7 = Utf8               login
   #8 = Utf8               Ljava/lang/String;
   #9 = Utf8               <init>
  #10 = Utf8               (Ljava/lang/String;)V
  #11 = Utf8               Code
  #12 = Utf8               LineNumberTable
  #13 = Utf8               LocalVariableTable
  #14 = Utf8               this
  #15 = Utf8               UserProvider
  #16 = Utf8               InnerClasses
  #17 = Utf8               Lorg/kohsuke/github/authorization/ImmutableAuthorizationProvider$UserProvider;
  #18 = Utf8               authorization
  #19 = Utf8               (Ljava/lang/String;Ljava/lang/String;)V
  #20 = Utf8               getLogin
  #21 = Utf8               ()Ljava/lang/String;
  #22 = Utf8               RuntimeVisibleAnnotations
  #23 = Utf8               Ljavax/annotation/CheckForNull;
  #24 = Utf8               SourceFile
  #25 = Utf8               ImmutableAuthorizationProvider.java
  #26 = NameAndType        #9:#19         // "<init>":(Ljava/lang/String;Ljava/lang/String;)V
  #27 = NameAndType        #9:#10         // "<init>":(Ljava/lang/String;)V
  #28 = NameAndType        #7:#8          // login:Ljava/lang/String;
  #29 = Utf8               org/kohsuke/github/authorization/ImmutableAuthorizationProvider$UserProvider
  #30 = Utf8               org/kohsuke/github/authorization/ImmutableAuthorizationProvider
  #31 = Utf8               org/kohsuke/github/authorization/UserAuthorizationProvider
{
  private final java.lang.String login;
    descriptor: Ljava/lang/String;
    flags: (0x0012) ACC_PRIVATE, ACC_FINAL

  org.kohsuke.github.authorization.ImmutableAuthorizationProvider$UserProvider(java.lang.String);
    descriptor: (Ljava/lang/String;)V
    flags: (0x0000)
    Code:
      stack=3, locals=2, args_size=2
         0: aload_0
         1: aload_1
         2: aconst_null
         3: invokespecial #1                  // Method "<init>":(Ljava/lang/String;Ljava/lang/String;)V
         6: return
      LineNumberTable:
        line 110: 0
        line 111: 6
      LocalVariableTable:
        Start  Length  Slot  Name   Signature
            0       7     0  this   Lorg/kohsuke/github/authorization/ImmutableAuthorizationProvider$UserProvider;
            0       7     1 authorization   Ljava/lang/String;

  org.kohsuke.github.authorization.ImmutableAuthorizationProvider$UserProvider(java.lang.String, java.lang.String);
    descriptor: (Ljava/lang/String;Ljava/lang/String;)V
    flags: (0x0000)
    Code:
      stack=2, locals=3, args_size=3
         0: aload_0
         1: aload_1
         2: invokespecial #2                  // Method org/kohsuke/github/authorization/ImmutableAuthorizationProvider."<init>":(Ljava/lang/String;)V
         5: aload_0
         6: aload_2
         7: putfield      #3                  // Field login:Ljava/lang/String;
        10: return
      LineNumberTable:
        line 114: 0
        line 115: 5
        line 116: 10
      LocalVariableTable:
        Start  Length  Slot  Name   Signature
            0      11     0  this   Lorg/kohsuke/github/authorization/ImmutableAuthorizationProvider$UserProvider;
            0      11     1 authorization   Ljava/lang/String;
            0      11     2 login   Ljava/lang/String;

  public java.lang.String getLogin();
    descriptor: ()Ljava/lang/String;
    flags: (0x0001) ACC_PUBLIC
    Code:
      stack=1, locals=1, args_size=1
         0: aload_0
         1: getfield      #3                  // Field login:Ljava/lang/String;
         4: areturn
      LineNumberTable:
        line 121: 0
      LocalVariableTable:
        Start  Length  Slot  Name   Signature
            0       5     0  this   Lorg/kohsuke/github/authorization/ImmutableAuthorizationProvider$UserProvider;
    RuntimeVisibleAnnotations:
      0: #23()
        javax.annotation.CheckForNull
}
SourceFile: "ImmutableAuthorizationProvider.java"
InnerClasses:
  private static #15= #4 of #5;           // UserProvider=class org/kohsuke/github/authorization/ImmutableAuthorizationProvider$UserProvider of class org/kohsuke/github/authorization/ImmutableAuthorizationProvider
