Classfile /Users/mw/Projects/slang-braindump/.jar/jar8/assemble/slang-braindump/assemble/content/org/kohsuke/github/authorization/OrgAppInstallationAuthorizationProvider.class
  Last modified May 29, 2022; size 2887 bytes
  SHA-256 checksum 0370d805082dcb7cc8089503bc88182a4e7fc36adc239634a1245781b6aea21e
  Compiled from "OrgAppInstallationAuthorizationProvider.java"
public class org.kohsuke.github.authorization.OrgAppInstallationAuthorizationProvider extends org.kohsuke.github.GitHub$DependentAuthorizationProvider
  minor version: 0
  major version: 52
  flags: (0x0021) ACC_PUBLIC, ACC_SUPER
  this_class: #26                         // org/kohsuke/github/authorization/OrgAppInstallationAuthorizationProvider
  super_class: #27                        // org/kohsuke/github/GitHub$DependentAuthorizationProvider
  interfaces: 0, fields: 3, methods: 3, attributes: 2
Constant pool:
    #1 = Methodref          #27.#61       // org/kohsuke/github/GitHub$DependentAuthorizationProvider."<init>":(Lorg/kohsuke/github/authorization/AuthorizationProvider;)V
    #2 = Fieldref           #62.#63       // java/time/Instant.MIN:Ljava/time/Instant;
    #3 = Fieldref           #26.#64       // org/kohsuke/github/authorization/OrgAppInstallationAuthorizationProvider.validUntil:Ljava/time/Instant;
    #4 = Fieldref           #26.#65       // org/kohsuke/github/authorization/OrgAppInstallationAuthorizationProvider.organizationName:Ljava/lang/String;
    #5 = Fieldref           #26.#66       // org/kohsuke/github/authorization/OrgAppInstallationAuthorizationProvider.authorization:Ljava/lang/String;
    #6 = Methodref          #62.#67       // java/time/Instant.now:()Ljava/time/Instant;
    #7 = Methodref          #62.#68       // java/time/Instant.isAfter:(Ljava/time/Instant;)Z
    #8 = Methodref          #26.#69       // org/kohsuke/github/authorization/OrgAppInstallationAuthorizationProvider.refreshToken:()Ljava/lang/String;
    #9 = String             #70           // token %s
   #10 = Class              #71           // java/lang/Object
   #11 = Methodref          #25.#72       // java/lang/String.format:(Ljava/lang/String;[Ljava/lang/Object;)Ljava/lang/String;
   #12 = Methodref          #26.#73       // org/kohsuke/github/authorization/OrgAppInstallationAuthorizationProvider.gitHub:()Lorg/kohsuke/github/GitHub;
   #13 = Methodref          #74.#75       // org/kohsuke/github/GitHub.getApp:()Lorg/kohsuke/github/GHApp;
   #14 = Methodref          #76.#77       // org/kohsuke/github/GHApp.getInstallationByOrganization:(Ljava/lang/String;)Lorg/kohsuke/github/GHAppInstallation;
   #15 = Methodref          #78.#79       // org/kohsuke/github/GHAppInstallation.createToken:()Lorg/kohsuke/github/GHAppCreateTokenBuilder;
   #16 = Methodref          #80.#81       // org/kohsuke/github/GHAppCreateTokenBuilder.create:()Lorg/kohsuke/github/GHAppInstallationToken;
   #17 = Methodref          #82.#83       // org/kohsuke/github/GHAppInstallationToken.getExpiresAt:()Ljava/util/Date;
   #18 = Methodref          #84.#85       // java/util/Date.toInstant:()Ljava/time/Instant;
   #19 = Long               5l
   #21 = Methodref          #86.#87       // java/time/Duration.ofMinutes:(J)Ljava/time/Duration;
   #22 = Methodref          #62.#88       // java/time/Instant.minus:(Ljava/time/temporal/TemporalAmount;)Ljava/time/Instant;
   #23 = Methodref          #82.#89       // org/kohsuke/github/GHAppInstallationToken.getToken:()Ljava/lang/String;
   #24 = Methodref          #90.#91       // java/util/Objects.requireNonNull:(Ljava/lang/Object;)Ljava/lang/Object;
   #25 = Class              #92           // java/lang/String
   #26 = Class              #93           // org/kohsuke/github/authorization/OrgAppInstallationAuthorizationProvider
   #27 = Class              #94           // org/kohsuke/github/GitHub$DependentAuthorizationProvider
   #28 = Utf8               organizationName
   #29 = Utf8               Ljava/lang/String;
   #30 = Utf8               authorization
   #31 = Utf8               validUntil
   #32 = Utf8               Ljava/time/Instant;
   #33 = Utf8               RuntimeVisibleAnnotations
   #34 = Utf8               Ljavax/annotation/Nonnull;
   #35 = Utf8               <init>
   #36 = Utf8               (Ljava/lang/String;Lorg/kohsuke/github/authorization/AuthorizationProvider;)V
   #37 = Utf8               Code
   #38 = Utf8               LineNumberTable
   #39 = Utf8               LocalVariableTable
   #40 = Utf8               this
   #41 = Utf8               Lorg/kohsuke/github/authorization/OrgAppInstallationAuthorizationProvider;
   #42 = Utf8               authorizationProvider
   #43 = Utf8               Lorg/kohsuke/github/authorization/AuthorizationProvider;
   #44 = Utf8               Lorg/kohsuke/github/BetaApi;
   #45 = Utf8               getEncodedAuthorization
   #46 = Utf8               ()Ljava/lang/String;
   #47 = Utf8               token
   #48 = Utf8               StackMapTable
   #49 = Class              #97           // java/lang/Throwable
   #50 = Utf8               Exceptions
   #51 = Class              #98           // java/io/IOException
   #52 = Utf8               refreshToken
   #53 = Utf8               gitHub
   #54 = Utf8               Lorg/kohsuke/github/GitHub;
   #55 = Utf8               installationByOrganization
   #56 = Utf8               Lorg/kohsuke/github/GHAppInstallation;
   #57 = Utf8               ghAppInstallationToken
   #58 = Utf8               Lorg/kohsuke/github/GHAppInstallationToken;
   #59 = Utf8               SourceFile
   #60 = Utf8               OrgAppInstallationAuthorizationProvider.java
   #61 = NameAndType        #35:#99       // "<init>":(Lorg/kohsuke/github/authorization/AuthorizationProvider;)V
   #62 = Class              #100          // java/time/Instant
   #63 = NameAndType        #101:#32      // MIN:Ljava/time/Instant;
   #64 = NameAndType        #31:#32       // validUntil:Ljava/time/Instant;
   #65 = NameAndType        #28:#29       // organizationName:Ljava/lang/String;
   #66 = NameAndType        #30:#29       // authorization:Ljava/lang/String;
   #67 = NameAndType        #102:#103     // now:()Ljava/time/Instant;
   #68 = NameAndType        #104:#105     // isAfter:(Ljava/time/Instant;)Z
   #69 = NameAndType        #52:#46       // refreshToken:()Ljava/lang/String;
   #70 = Utf8               token %s
   #71 = Utf8               java/lang/Object
   #72 = NameAndType        #106:#107     // format:(Ljava/lang/String;[Ljava/lang/Object;)Ljava/lang/String;
   #73 = NameAndType        #53:#108      // gitHub:()Lorg/kohsuke/github/GitHub;
   #74 = Class              #109          // org/kohsuke/github/GitHub
   #75 = NameAndType        #110:#111     // getApp:()Lorg/kohsuke/github/GHApp;
   #76 = Class              #112          // org/kohsuke/github/GHApp
   #77 = NameAndType        #113:#114     // getInstallationByOrganization:(Ljava/lang/String;)Lorg/kohsuke/github/GHAppInstallation;
   #78 = Class              #115          // org/kohsuke/github/GHAppInstallation
   #79 = NameAndType        #116:#117     // createToken:()Lorg/kohsuke/github/GHAppCreateTokenBuilder;
   #80 = Class              #118          // org/kohsuke/github/GHAppCreateTokenBuilder
   #81 = NameAndType        #119:#120     // create:()Lorg/kohsuke/github/GHAppInstallationToken;
   #82 = Class              #121          // org/kohsuke/github/GHAppInstallationToken
   #83 = NameAndType        #122:#123     // getExpiresAt:()Ljava/util/Date;
   #84 = Class              #124          // java/util/Date
   #85 = NameAndType        #125:#103     // toInstant:()Ljava/time/Instant;
   #86 = Class              #126          // java/time/Duration
   #87 = NameAndType        #127:#128     // ofMinutes:(J)Ljava/time/Duration;
   #88 = NameAndType        #129:#130     // minus:(Ljava/time/temporal/TemporalAmount;)Ljava/time/Instant;
   #89 = NameAndType        #131:#46      // getToken:()Ljava/lang/String;
   #90 = Class              #132          // java/util/Objects
   #91 = NameAndType        #133:#134     // requireNonNull:(Ljava/lang/Object;)Ljava/lang/Object;
   #92 = Utf8               java/lang/String
   #93 = Utf8               org/kohsuke/github/authorization/OrgAppInstallationAuthorizationProvider
   #94 = Utf8               org/kohsuke/github/GitHub$DependentAuthorizationProvider
   #95 = Utf8               DependentAuthorizationProvider
   #96 = Utf8               InnerClasses
   #97 = Utf8               java/lang/Throwable
   #98 = Utf8               java/io/IOException
   #99 = Utf8               (Lorg/kohsuke/github/authorization/AuthorizationProvider;)V
  #100 = Utf8               java/time/Instant
  #101 = Utf8               MIN
  #102 = Utf8               now
  #103 = Utf8               ()Ljava/time/Instant;
  #104 = Utf8               isAfter
  #105 = Utf8               (Ljava/time/Instant;)Z
  #106 = Utf8               format
  #107 = Utf8               (Ljava/lang/String;[Ljava/lang/Object;)Ljava/lang/String;
  #108 = Utf8               ()Lorg/kohsuke/github/GitHub;
  #109 = Utf8               org/kohsuke/github/GitHub
  #110 = Utf8               getApp
  #111 = Utf8               ()Lorg/kohsuke/github/GHApp;
  #112 = Utf8               org/kohsuke/github/GHApp
  #113 = Utf8               getInstallationByOrganization
  #114 = Utf8               (Ljava/lang/String;)Lorg/kohsuke/github/GHAppInstallation;
  #115 = Utf8               org/kohsuke/github/GHAppInstallation
  #116 = Utf8               createToken
  #117 = Utf8               ()Lorg/kohsuke/github/GHAppCreateTokenBuilder;
  #118 = Utf8               org/kohsuke/github/GHAppCreateTokenBuilder
  #119 = Utf8               create
  #120 = Utf8               ()Lorg/kohsuke/github/GHAppInstallationToken;
  #121 = Utf8               org/kohsuke/github/GHAppInstallationToken
  #122 = Utf8               getExpiresAt
  #123 = Utf8               ()Ljava/util/Date;
  #124 = Utf8               java/util/Date
  #125 = Utf8               toInstant
  #126 = Utf8               java/time/Duration
  #127 = Utf8               ofMinutes
  #128 = Utf8               (J)Ljava/time/Duration;
  #129 = Utf8               minus
  #130 = Utf8               (Ljava/time/temporal/TemporalAmount;)Ljava/time/Instant;
  #131 = Utf8               getToken
  #132 = Utf8               java/util/Objects
  #133 = Utf8               requireNonNull
  #134 = Utf8               (Ljava/lang/Object;)Ljava/lang/Object;
{
  private final java.lang.String organizationName;
    descriptor: Ljava/lang/String;
    flags: (0x0012) ACC_PRIVATE, ACC_FINAL

  private java.lang.String authorization;
    descriptor: Ljava/lang/String;
    flags: (0x0002) ACC_PRIVATE

  private java.time.Instant validUntil;
    descriptor: Ljava/time/Instant;
    flags: (0x0002) ACC_PRIVATE
    RuntimeVisibleAnnotations:
      0: #34()
        javax.annotation.Nonnull

  public org.kohsuke.github.authorization.OrgAppInstallationAuthorizationProvider(java.lang.String, org.kohsuke.github.authorization.AuthorizationProvider);
    descriptor: (Ljava/lang/String;Lorg/kohsuke/github/authorization/AuthorizationProvider;)V
    flags: (0x0001) ACC_PUBLIC
    Code:
      stack=2, locals=3, args_size=3
         0: aload_0
         1: aload_2
         2: invokespecial #1                  // Method org/kohsuke/github/GitHub$DependentAuthorizationProvider."<init>":(Lorg/kohsuke/github/authorization/AuthorizationProvider;)V
         5: aload_0
         6: getstatic     #2                  // Field java/time/Instant.MIN:Ljava/time/Instant;
         9: putfield      #3                  // Field validUntil:Ljava/time/Instant;
        12: aload_0
        13: aload_1
        14: putfield      #4                  // Field organizationName:Ljava/lang/String;
        17: return
      LineNumberTable:
        line 40: 0
        line 24: 5
        line 41: 12
        line 42: 17
      LocalVariableTable:
        Start  Length  Slot  Name   Signature
            0      18     0  this   Lorg/kohsuke/github/authorization/OrgAppInstallationAuthorizationProvider;
            0      18     1 organizationName   Ljava/lang/String;
            0      18     2 authorizationProvider   Lorg/kohsuke/github/authorization/AuthorizationProvider;
    RuntimeVisibleAnnotations:
      0: #44()
        org.kohsuke.github.BetaApi

  public java.lang.String getEncodedAuthorization() throws java.io.IOException;
    descriptor: ()Ljava/lang/String;
    flags: (0x0001) ACC_PUBLIC
    Code:
      stack=6, locals=4, args_size=1
         0: aload_0
         1: dup
         2: astore_1
         3: monitorenter
         4: aload_0
         5: getfield      #5                  // Field authorization:Ljava/lang/String;
         8: ifnull        24
        11: invokestatic  #6                  // Method java/time/Instant.now:()Ljava/time/Instant;
        14: aload_0
        15: getfield      #3                  // Field validUntil:Ljava/time/Instant;
        18: invokevirtual #7                  // Method java/time/Instant.isAfter:(Ljava/time/Instant;)Z
        21: ifeq          46
        24: aload_0
        25: invokespecial #8                  // Method refreshToken:()Ljava/lang/String;
        28: astore_2
        29: aload_0
        30: ldc           #9                  // String token %s
        32: iconst_1
        33: anewarray     #10                 // class java/lang/Object
        36: dup
        37: iconst_0
        38: aload_2
        39: aastore
        40: invokestatic  #11                 // Method java/lang/String.format:(Ljava/lang/String;[Ljava/lang/Object;)Ljava/lang/String;
        43: putfield      #5                  // Field authorization:Ljava/lang/String;
        46: aload_0
        47: getfield      #5                  // Field authorization:Ljava/lang/String;
        50: aload_1
        51: monitorexit
        52: areturn
        53: astore_3
        54: aload_1
        55: monitorexit
        56: aload_3
        57: athrow
      Exception table:
         from    to  target type
             4    52    53   any
            53    56    53   any
      LineNumberTable:
        line 46: 0
        line 47: 4
        line 48: 24
        line 49: 29
        line 51: 46
        line 52: 53
      LocalVariableTable:
        Start  Length  Slot  Name   Signature
           29      17     2 token   Ljava/lang/String;
            0      58     0  this   Lorg/kohsuke/github/authorization/OrgAppInstallationAuthorizationProvider;
      StackMapTable: number_of_entries = 3
        frame_type = 252 /* append */
          offset_delta = 24
          locals = [ class java/lang/Object ]
        frame_type = 21 /* same */
        frame_type = 70 /* same_locals_1_stack_item */
          stack = [ class java/lang/Throwable ]
    Exceptions:
      throws java.io.IOException

  private java.lang.String refreshToken() throws java.io.IOException;
    descriptor: ()Ljava/lang/String;
    flags: (0x0002) ACC_PRIVATE
    Code:
      stack=4, locals=4, args_size=1
         0: aload_0
         1: invokevirtual #12                 // Method gitHub:()Lorg/kohsuke/github/GitHub;
         4: astore_1
         5: aload_1
         6: invokevirtual #13                 // Method org/kohsuke/github/GitHub.getApp:()Lorg/kohsuke/github/GHApp;
         9: aload_0
        10: getfield      #4                  // Field organizationName:Ljava/lang/String;
        13: invokevirtual #14                 // Method org/kohsuke/github/GHApp.getInstallationByOrganization:(Ljava/lang/String;)Lorg/kohsuke/github/GHAppInstallation;
        16: astore_2
        17: aload_2
        18: invokevirtual #15                 // Method org/kohsuke/github/GHAppInstallation.createToken:()Lorg/kohsuke/github/GHAppCreateTokenBuilder;
        21: invokevirtual #16                 // Method org/kohsuke/github/GHAppCreateTokenBuilder.create:()Lorg/kohsuke/github/GHAppInstallationToken;
        24: astore_3
        25: aload_0
        26: aload_3
        27: invokevirtual #17                 // Method org/kohsuke/github/GHAppInstallationToken.getExpiresAt:()Ljava/util/Date;
        30: invokevirtual #18                 // Method java/util/Date.toInstant:()Ljava/time/Instant;
        33: ldc2_w        #19                 // long 5l
        36: invokestatic  #21                 // Method java/time/Duration.ofMinutes:(J)Ljava/time/Duration;
        39: invokevirtual #22                 // Method java/time/Instant.minus:(Ljava/time/temporal/TemporalAmount;)Ljava/time/Instant;
        42: putfield      #3                  // Field validUntil:Ljava/time/Instant;
        45: aload_3
        46: invokevirtual #23                 // Method org/kohsuke/github/GHAppInstallationToken.getToken:()Ljava/lang/String;
        49: invokestatic  #24                 // Method java/util/Objects.requireNonNull:(Ljava/lang/Object;)Ljava/lang/Object;
        52: checkcast     #25                 // class java/lang/String
        55: areturn
      LineNumberTable:
        line 56: 0
        line 57: 5
        line 58: 13
        line 59: 17
        line 60: 25
        line 61: 45
      LocalVariableTable:
        Start  Length  Slot  Name   Signature
            0      56     0  this   Lorg/kohsuke/github/authorization/OrgAppInstallationAuthorizationProvider;
            5      51     1 gitHub   Lorg/kohsuke/github/GitHub;
           17      39     2 installationByOrganization   Lorg/kohsuke/github/GHAppInstallation;
           25      31     3 ghAppInstallationToken   Lorg/kohsuke/github/GHAppInstallationToken;
    Exceptions:
      throws java.io.IOException
}
SourceFile: "OrgAppInstallationAuthorizationProvider.java"
InnerClasses:
  public static abstract #95= #27 of #74; // DependentAuthorizationProvider=class org/kohsuke/github/GitHub$DependentAuthorizationProvider of class org/kohsuke/github/GitHub
