Classfile /Users/mw/Projects/slang-braindump/.jar/jar8/assemble/slang-braindump/assemble/content/scala/util/hashing/Hashing$$anon$1.class
  Last modified May 29, 2022; size 1034 bytes
  SHA-256 checksum f9d29f20e936ff4d34a30fa5428e17a72792860996000f57b174f4baa73e413d
  Compiled from "Hashing.scala"
public final class scala.util.hashing.Hashing$$anon$1 extends java.lang.Object implements scala.util.hashing.Hashing<T>
  minor version: 0
  major version: 52
  flags: (0x0031) ACC_PUBLIC, ACC_FINAL, ACC_SUPER
  this_class: #2                          // scala/util/hashing/Hashing$$anon$1
  super_class: #5                         // java/lang/Object
  interfaces: 1, fields: 1, methods: 2, attributes: 6
Constant pool:
   #1 = Utf8               scala/util/hashing/Hashing$$anon$1
   #2 = Class              #1             // scala/util/hashing/Hashing$$anon$1
   #3 = Utf8               Ljava/lang/Object;Lscala/util/hashing/Hashing<TT;>;
   #4 = Utf8               java/lang/Object
   #5 = Class              #4             // java/lang/Object
   #6 = Utf8               scala/util/hashing/Hashing
   #7 = Class              #6             // scala/util/hashing/Hashing
   #8 = Utf8               Hashing.scala
   #9 = Utf8               scala/util/hashing/Hashing$
  #10 = Class              #9             // scala/util/hashing/Hashing$
  #11 = Utf8               fromFunction
  #12 = Utf8               (Lscala/Function1;)Lscala/util/hashing/Hashing;
  #13 = NameAndType        #11:#12        // fromFunction:(Lscala/Function1;)Lscala/util/hashing/Hashing;
  #14 = Utf8               f$1
  #15 = Utf8               Lscala/Function1;
  #16 = Utf8               hash
  #17 = Utf8               (Ljava/lang/Object;)I
  #18 = Utf8               (TT;)I
  #19 = Utf8               x
  #20 = NameAndType        #14:#15        // f$1:Lscala/Function1;
  #21 = Fieldref           #2.#20         // scala/util/hashing/Hashing$$anon$1.f$1:Lscala/Function1;
  #22 = Utf8               scala/Function1
  #23 = Class              #22            // scala/Function1
  #24 = Utf8               apply
  #25 = Utf8               (Ljava/lang/Object;)Ljava/lang/Object;
  #26 = NameAndType        #24:#25        // apply:(Ljava/lang/Object;)Ljava/lang/Object;
  #27 = InterfaceMethodref #23.#26        // scala/Function1.apply:(Ljava/lang/Object;)Ljava/lang/Object;
  #28 = Utf8               scala/runtime/BoxesRunTime
  #29 = Class              #28            // scala/runtime/BoxesRunTime
  #30 = Utf8               unboxToInt
  #31 = NameAndType        #30:#17        // unboxToInt:(Ljava/lang/Object;)I
  #32 = Methodref          #29.#31        // scala/runtime/BoxesRunTime.unboxToInt:(Ljava/lang/Object;)I
  #33 = Utf8               this
  #34 = Utf8               Lscala/util/hashing/Hashing$$anon$1;
  #35 = Utf8               Ljava/lang/Object;
  #36 = Utf8               <init>
  #37 = Utf8               (Lscala/Function1;)V
  #38 = Utf8               ()V
  #39 = NameAndType        #36:#38        // "<init>":()V
  #40 = Methodref          #5.#39         // java/lang/Object."<init>":()V
  #41 = Utf8               Code
  #42 = Utf8               LineNumberTable
  #43 = Utf8               LocalVariableTable
  #44 = Utf8               Signature
  #45 = Utf8               MethodParameters
  #46 = Utf8               InnerClasses
  #47 = Utf8               EnclosingMethod
  #48 = Utf8               SourceFile
  #49 = Utf8               ScalaInlineInfo
  #50 = Utf8               Scala
{
  private final scala.Function1 f$1;
    descriptor: Lscala/Function1;
    flags: (0x0012) ACC_PRIVATE, ACC_FINAL

  public int hash(T);
    descriptor: (Ljava/lang/Object;)I
    flags: (0x0001) ACC_PUBLIC
    Code:
      stack=2, locals=2, args_size=2
         0: aload_0
         1: getfield      #21                 // Field f$1:Lscala/Function1;
         4: aload_1
         5: invokeinterface #27,  2           // InterfaceMethod scala/Function1.apply:(Ljava/lang/Object;)Ljava/lang/Object;
        10: invokestatic  #32                 // Method scala/runtime/BoxesRunTime.unboxToInt:(Ljava/lang/Object;)I
        13: ireturn
      LineNumberTable:
        line 40: 0
      LocalVariableTable:
        Start  Length  Slot  Name   Signature
            0      14     0  this   Lscala/util/hashing/Hashing$$anon$1;
            0      14     1     x   Ljava/lang/Object;
    Signature: #18                          // (TT;)I
    MethodParameters:
      Name                           Flags
      x                              final

  public scala.util.hashing.Hashing$$anon$1(scala.Function1);
    descriptor: (Lscala/Function1;)V
    flags: (0x0001) ACC_PUBLIC
    Code:
      stack=2, locals=2, args_size=2
         0: aload_0
         1: aload_1
         2: putfield      #21                 // Field f$1:Lscala/Function1;
         5: aload_0
         6: invokespecial #40                 // Method java/lang/Object."<init>":()V
         9: return
      LineNumberTable:
        line 39: 0
      LocalVariableTable:
        Start  Length  Slot  Name   Signature
            0      10     0  this   Lscala/util/hashing/Hashing$$anon$1;
            0      10     1   f$1   Lscala/Function1;
    MethodParameters:
      Name                           Flags
      f$1                            final
}
InnerClasses:
  public final #2;                        // class scala/util/hashing/Hashing$$anon$1
EnclosingMethod: #10.#13                // scala.util.hashing.Hashing$.fromFunction
Signature: #3                           // Ljava/lang/Object;Lscala/util/hashing/Hashing<TT;>;
SourceFile: "Hashing.scala"
  ScalaInlineInfo: length = 0xE (unknown attribute)
   01 01 00 02 00 24 00 25 01 00 10 00 11 01
  Scala: length = 0x0 (unknown attribute)

