Classfile /Users/mw/Projects/slang-braindump/.jar/jar8/assemble/slang-braindump/assemble/content/com/fasterxml/jackson/databind/jsontype/impl/ClassNameIdResolver.class
  Last modified May 29, 2022; size 6558 bytes
  SHA-256 checksum 7879a0197c09dc85ca7fcd9709cc75333ef82bee0eb998b08e5077813b5c5536
  Compiled from "ClassNameIdResolver.java"
public class com.fasterxml.jackson.databind.jsontype.impl.ClassNameIdResolver extends com.fasterxml.jackson.databind.jsontype.impl.TypeIdResolverBase
  minor version: 0
  major version: 52
  flags: (0x0021) ACC_PUBLIC, ACC_SUPER
  this_class: #5                          // com/fasterxml/jackson/databind/jsontype/impl/ClassNameIdResolver
  super_class: #36                        // com/fasterxml/jackson/databind/jsontype/impl/TypeIdResolverBase
  interfaces: 0, fields: 2, methods: 11, attributes: 2
Constant pool:
    #1 = Fieldref           #112.#113     // com/fasterxml/jackson/databind/jsontype/impl/LaissezFaireSubTypeValidator.instance:Lcom/fasterxml/jackson/databind/jsontype/impl/LaissezFaireSubTypeValidator;
    #2 = Methodref          #5.#114       // com/fasterxml/jackson/databind/jsontype/impl/ClassNameIdResolver."<init>":(Lcom/fasterxml/jackson/databind/JavaType;Lcom/fasterxml/jackson/databind/type/TypeFactory;Lcom/fasterxml/jackson/databind/jsontype/PolymorphicTypeValidator;)V
    #3 = Methodref          #36.#115      // com/fasterxml/jackson/databind/jsontype/impl/TypeIdResolverBase."<init>":(Lcom/fasterxml/jackson/databind/JavaType;Lcom/fasterxml/jackson/databind/type/TypeFactory;)V
    #4 = Fieldref           #5.#116       // com/fasterxml/jackson/databind/jsontype/impl/ClassNameIdResolver._subTypeValidator:Lcom/fasterxml/jackson/databind/jsontype/PolymorphicTypeValidator;
    #5 = Class              #117          // com/fasterxml/jackson/databind/jsontype/impl/ClassNameIdResolver
    #6 = Methodref          #118.#119     // com/fasterxml/jackson/databind/cfg/MapperConfig.getTypeFactory:()Lcom/fasterxml/jackson/databind/type/TypeFactory;
    #7 = Fieldref           #67.#120      // com/fasterxml/jackson/annotation/JsonTypeInfo$Id.CLASS:Lcom/fasterxml/jackson/annotation/JsonTypeInfo$Id;
    #8 = Methodref          #29.#121      // java/lang/Object.getClass:()Ljava/lang/Class;
    #9 = Fieldref           #5.#122       // com/fasterxml/jackson/databind/jsontype/impl/ClassNameIdResolver._typeFactory:Lcom/fasterxml/jackson/databind/type/TypeFactory;
   #10 = Methodref          #5.#123       // com/fasterxml/jackson/databind/jsontype/impl/ClassNameIdResolver._idFrom:(Ljava/lang/Object;Ljava/lang/Class;Lcom/fasterxml/jackson/databind/type/TypeFactory;)Ljava/lang/String;
   #11 = Methodref          #5.#124       // com/fasterxml/jackson/databind/jsontype/impl/ClassNameIdResolver._typeFromId:(Ljava/lang/String;Lcom/fasterxml/jackson/databind/DatabindContext;)Lcom/fasterxml/jackson/databind/JavaType;
   #12 = Fieldref           #5.#125       // com/fasterxml/jackson/databind/jsontype/impl/ClassNameIdResolver._baseType:Lcom/fasterxml/jackson/databind/JavaType;
   #13 = Methodref          #126.#127     // com/fasterxml/jackson/databind/DatabindContext.resolveAndValidateSubType:(Lcom/fasterxml/jackson/databind/JavaType;Ljava/lang/String;Lcom/fasterxml/jackson/databind/jsontype/PolymorphicTypeValidator;)Lcom/fasterxml/jackson/databind/JavaType;
   #14 = Class              #128          // com/fasterxml/jackson/databind/DeserializationContext
   #15 = String             #129          // no such class found
   #16 = Methodref          #14.#130      // com/fasterxml/jackson/databind/DeserializationContext.handleUnknownTypeId:(Lcom/fasterxml/jackson/databind/JavaType;Ljava/lang/String;Lcom/fasterxml/jackson/databind/jsontype/TypeIdResolver;Ljava/lang/String;)Lcom/fasterxml/jackson/databind/JavaType;
   #17 = Methodref          #131.#132     // com/fasterxml/jackson/databind/util/ClassUtil.isEnumType:(Ljava/lang/Class;)Z
   #18 = Methodref          #133.#134     // java/lang/Class.isEnum:()Z
   #19 = Methodref          #133.#135     // java/lang/Class.getSuperclass:()Ljava/lang/Class;
   #20 = Methodref          #133.#136     // java/lang/Class.getName:()Ljava/lang/String;
   #21 = String             #137          // java.util.
   #22 = Methodref          #138.#139     // java/lang/String.startsWith:(Ljava/lang/String;)Z
   #23 = Class              #140          // java/util/EnumSet
   #24 = Methodref          #131.#141     // com/fasterxml/jackson/databind/util/ClassUtil.findEnumType:(Ljava/util/EnumSet;)Ljava/lang/Class;
   #25 = Methodref          #142.#143     // com/fasterxml/jackson/databind/type/TypeFactory.constructCollectionType:(Ljava/lang/Class;Ljava/lang/Class;)Lcom/fasterxml/jackson/databind/type/CollectionType;
   #26 = Methodref          #144.#145     // com/fasterxml/jackson/databind/type/CollectionType.toCanonical:()Ljava/lang/String;
   #27 = Class              #146          // java/util/EnumMap
   #28 = Methodref          #131.#147     // com/fasterxml/jackson/databind/util/ClassUtil.findEnumType:(Ljava/util/EnumMap;)Ljava/lang/Class;
   #29 = Class              #148          // java/lang/Object
   #30 = Methodref          #142.#149     // com/fasterxml/jackson/databind/type/TypeFactory.constructMapType:(Ljava/lang/Class;Ljava/lang/Class;Ljava/lang/Class;)Lcom/fasterxml/jackson/databind/type/MapType;
   #31 = Methodref          #150.#145     // com/fasterxml/jackson/databind/type/MapType.toCanonical:()Ljava/lang/String;
   #32 = Methodref          #138.#151     // java/lang/String.indexOf:(I)I
   #33 = Methodref          #131.#152     // com/fasterxml/jackson/databind/util/ClassUtil.getOuterClass:(Ljava/lang/Class;)Ljava/lang/Class;
   #34 = Methodref          #153.#154     // com/fasterxml/jackson/databind/JavaType.getRawClass:()Ljava/lang/Class;
   #35 = String             #155          // class name used as type id
   #36 = Class              #156          // com/fasterxml/jackson/databind/jsontype/impl/TypeIdResolverBase
   #37 = Utf8               JAVA_UTIL_PKG
   #38 = Utf8               Ljava/lang/String;
   #39 = Utf8               ConstantValue
   #40 = Utf8               _subTypeValidator
   #41 = Utf8               Lcom/fasterxml/jackson/databind/jsontype/PolymorphicTypeValidator;
   #42 = Utf8               <init>
   #43 = Utf8               (Lcom/fasterxml/jackson/databind/JavaType;Lcom/fasterxml/jackson/databind/type/TypeFactory;)V
   #44 = Utf8               Code
   #45 = Utf8               LineNumberTable
   #46 = Utf8               LocalVariableTable
   #47 = Utf8               this
   #48 = Utf8               Lcom/fasterxml/jackson/databind/jsontype/impl/ClassNameIdResolver;
   #49 = Utf8               baseType
   #50 = Utf8               Lcom/fasterxml/jackson/databind/JavaType;
   #51 = Utf8               typeFactory
   #52 = Utf8               Lcom/fasterxml/jackson/databind/type/TypeFactory;
   #53 = Utf8               Deprecated
   #54 = Utf8               RuntimeVisibleAnnotations
   #55 = Utf8               Ljava/lang/Deprecated;
   #56 = Utf8               (Lcom/fasterxml/jackson/databind/JavaType;Lcom/fasterxml/jackson/databind/type/TypeFactory;Lcom/fasterxml/jackson/databind/jsontype/PolymorphicTypeValidator;)V
   #57 = Utf8               ptv
   #58 = Utf8               construct
   #59 = Utf8               (Lcom/fasterxml/jackson/databind/JavaType;Lcom/fasterxml/jackson/databind/cfg/MapperConfig;Lcom/fasterxml/jackson/databind/jsontype/PolymorphicTypeValidator;)Lcom/fasterxml/jackson/databind/jsontype/impl/ClassNameIdResolver;
   #60 = Utf8               config
   #61 = Utf8               Lcom/fasterxml/jackson/databind/cfg/MapperConfig;
   #62 = Utf8               LocalVariableTypeTable
   #63 = Utf8               Lcom/fasterxml/jackson/databind/cfg/MapperConfig<*>;
   #64 = Utf8               Signature
   #65 = Utf8               (Lcom/fasterxml/jackson/databind/JavaType;Lcom/fasterxml/jackson/databind/cfg/MapperConfig<*>;Lcom/fasterxml/jackson/databind/jsontype/PolymorphicTypeValidator;)Lcom/fasterxml/jackson/databind/jsontype/impl/ClassNameIdResolver;
   #66 = Utf8               getMechanism
   #67 = Class              #158          // com/fasterxml/jackson/annotation/JsonTypeInfo$Id
   #68 = Utf8               Id
   #69 = Utf8               InnerClasses
   #70 = Utf8               ()Lcom/fasterxml/jackson/annotation/JsonTypeInfo$Id;
   #71 = Utf8               registerSubtype
   #72 = Utf8               (Ljava/lang/Class;Ljava/lang/String;)V
   #73 = Utf8               type
   #74 = Utf8               Ljava/lang/Class;
   #75 = Utf8               name
   #76 = Utf8               Ljava/lang/Class<*>;
   #77 = Utf8               (Ljava/lang/Class<*>;Ljava/lang/String;)V
   #78 = Utf8               idFromValue
   #79 = Utf8               (Ljava/lang/Object;)Ljava/lang/String;
   #80 = Utf8               value
   #81 = Utf8               Ljava/lang/Object;
   #82 = Utf8               idFromValueAndType
   #83 = Utf8               (Ljava/lang/Object;Ljava/lang/Class;)Ljava/lang/String;
   #84 = Utf8               (Ljava/lang/Object;Ljava/lang/Class<*>;)Ljava/lang/String;
   #85 = Utf8               typeFromId
   #86 = Utf8               (Lcom/fasterxml/jackson/databind/DatabindContext;Ljava/lang/String;)Lcom/fasterxml/jackson/databind/JavaType;
   #87 = Utf8               context
   #88 = Utf8               Lcom/fasterxml/jackson/databind/DatabindContext;
   #89 = Utf8               id
   #90 = Utf8               Exceptions
   #91 = Class              #159          // java/io/IOException
   #92 = Utf8               _typeFromId
   #93 = Utf8               (Ljava/lang/String;Lcom/fasterxml/jackson/databind/DatabindContext;)Lcom/fasterxml/jackson/databind/JavaType;
   #94 = Utf8               ctxt
   #95 = Utf8               t
   #96 = Utf8               StackMapTable
   #97 = Class              #160          // com/fasterxml/jackson/databind/JavaType
   #98 = Utf8               _idFrom
   #99 = Utf8               (Ljava/lang/Object;Ljava/lang/Class;Lcom/fasterxml/jackson/databind/type/TypeFactory;)Ljava/lang/String;
  #100 = Utf8               enumClass
  #101 = Utf8               valueClass
  #102 = Utf8               staticType
  #103 = Utf8               outer
  #104 = Utf8               cls
  #105 = Utf8               str
  #106 = Class              #161          // java/lang/String
  #107 = Utf8               (Ljava/lang/Object;Ljava/lang/Class<*>;Lcom/fasterxml/jackson/databind/type/TypeFactory;)Ljava/lang/String;
  #108 = Utf8               getDescForKnownTypeIds
  #109 = Utf8               ()Ljava/lang/String;
  #110 = Utf8               SourceFile
  #111 = Utf8               ClassNameIdResolver.java
  #112 = Class              #162          // com/fasterxml/jackson/databind/jsontype/impl/LaissezFaireSubTypeValidator
  #113 = NameAndType        #163:#164     // instance:Lcom/fasterxml/jackson/databind/jsontype/impl/LaissezFaireSubTypeValidator;
  #114 = NameAndType        #42:#56       // "<init>":(Lcom/fasterxml/jackson/databind/JavaType;Lcom/fasterxml/jackson/databind/type/TypeFactory;Lcom/fasterxml/jackson/databind/jsontype/PolymorphicTypeValidator;)V
  #115 = NameAndType        #42:#43       // "<init>":(Lcom/fasterxml/jackson/databind/JavaType;Lcom/fasterxml/jackson/databind/type/TypeFactory;)V
  #116 = NameAndType        #40:#41       // _subTypeValidator:Lcom/fasterxml/jackson/databind/jsontype/PolymorphicTypeValidator;
  #117 = Utf8               com/fasterxml/jackson/databind/jsontype/impl/ClassNameIdResolver
  #118 = Class              #165          // com/fasterxml/jackson/databind/cfg/MapperConfig
  #119 = NameAndType        #166:#167     // getTypeFactory:()Lcom/fasterxml/jackson/databind/type/TypeFactory;
  #120 = NameAndType        #168:#169     // CLASS:Lcom/fasterxml/jackson/annotation/JsonTypeInfo$Id;
  #121 = NameAndType        #170:#171     // getClass:()Ljava/lang/Class;
  #122 = NameAndType        #172:#52      // _typeFactory:Lcom/fasterxml/jackson/databind/type/TypeFactory;
  #123 = NameAndType        #98:#99       // _idFrom:(Ljava/lang/Object;Ljava/lang/Class;Lcom/fasterxml/jackson/databind/type/TypeFactory;)Ljava/lang/String;
  #124 = NameAndType        #92:#93       // _typeFromId:(Ljava/lang/String;Lcom/fasterxml/jackson/databind/DatabindContext;)Lcom/fasterxml/jackson/databind/JavaType;
  #125 = NameAndType        #173:#50      // _baseType:Lcom/fasterxml/jackson/databind/JavaType;
  #126 = Class              #174          // com/fasterxml/jackson/databind/DatabindContext
  #127 = NameAndType        #175:#176     // resolveAndValidateSubType:(Lcom/fasterxml/jackson/databind/JavaType;Ljava/lang/String;Lcom/fasterxml/jackson/databind/jsontype/PolymorphicTypeValidator;)Lcom/fasterxml/jackson/databind/JavaType;
  #128 = Utf8               com/fasterxml/jackson/databind/DeserializationContext
  #129 = Utf8               no such class found
  #130 = NameAndType        #177:#178     // handleUnknownTypeId:(Lcom/fasterxml/jackson/databind/JavaType;Ljava/lang/String;Lcom/fasterxml/jackson/databind/jsontype/TypeIdResolver;Ljava/lang/String;)Lcom/fasterxml/jackson/databind/JavaType;
  #131 = Class              #179          // com/fasterxml/jackson/databind/util/ClassUtil
  #132 = NameAndType        #180:#181     // isEnumType:(Ljava/lang/Class;)Z
  #133 = Class              #182          // java/lang/Class
  #134 = NameAndType        #183:#184     // isEnum:()Z
  #135 = NameAndType        #185:#171     // getSuperclass:()Ljava/lang/Class;
  #136 = NameAndType        #186:#109     // getName:()Ljava/lang/String;
  #137 = Utf8               java.util.
  #138 = Class              #161          // java/lang/String
  #139 = NameAndType        #187:#188     // startsWith:(Ljava/lang/String;)Z
  #140 = Utf8               java/util/EnumSet
  #141 = NameAndType        #189:#190     // findEnumType:(Ljava/util/EnumSet;)Ljava/lang/Class;
  #142 = Class              #191          // com/fasterxml/jackson/databind/type/TypeFactory
  #143 = NameAndType        #192:#193     // constructCollectionType:(Ljava/lang/Class;Ljava/lang/Class;)Lcom/fasterxml/jackson/databind/type/CollectionType;
  #144 = Class              #194          // com/fasterxml/jackson/databind/type/CollectionType
  #145 = NameAndType        #195:#109     // toCanonical:()Ljava/lang/String;
  #146 = Utf8               java/util/EnumMap
  #147 = NameAndType        #189:#196     // findEnumType:(Ljava/util/EnumMap;)Ljava/lang/Class;
  #148 = Utf8               java/lang/Object
  #149 = NameAndType        #197:#198     // constructMapType:(Ljava/lang/Class;Ljava/lang/Class;Ljava/lang/Class;)Lcom/fasterxml/jackson/databind/type/MapType;
  #150 = Class              #199          // com/fasterxml/jackson/databind/type/MapType
  #151 = NameAndType        #200:#201     // indexOf:(I)I
  #152 = NameAndType        #202:#203     // getOuterClass:(Ljava/lang/Class;)Ljava/lang/Class;
  #153 = Class              #160          // com/fasterxml/jackson/databind/JavaType
  #154 = NameAndType        #204:#171     // getRawClass:()Ljava/lang/Class;
  #155 = Utf8               class name used as type id
  #156 = Utf8               com/fasterxml/jackson/databind/jsontype/impl/TypeIdResolverBase
  #157 = Class              #205          // com/fasterxml/jackson/annotation/JsonTypeInfo
  #158 = Utf8               com/fasterxml/jackson/annotation/JsonTypeInfo$Id
  #159 = Utf8               java/io/IOException
  #160 = Utf8               com/fasterxml/jackson/databind/JavaType
  #161 = Utf8               java/lang/String
  #162 = Utf8               com/fasterxml/jackson/databind/jsontype/impl/LaissezFaireSubTypeValidator
  #163 = Utf8               instance
  #164 = Utf8               Lcom/fasterxml/jackson/databind/jsontype/impl/LaissezFaireSubTypeValidator;
  #165 = Utf8               com/fasterxml/jackson/databind/cfg/MapperConfig
  #166 = Utf8               getTypeFactory
  #167 = Utf8               ()Lcom/fasterxml/jackson/databind/type/TypeFactory;
  #168 = Utf8               CLASS
  #169 = Utf8               Lcom/fasterxml/jackson/annotation/JsonTypeInfo$Id;
  #170 = Utf8               getClass
  #171 = Utf8               ()Ljava/lang/Class;
  #172 = Utf8               _typeFactory
  #173 = Utf8               _baseType
  #174 = Utf8               com/fasterxml/jackson/databind/DatabindContext
  #175 = Utf8               resolveAndValidateSubType
  #176 = Utf8               (Lcom/fasterxml/jackson/databind/JavaType;Ljava/lang/String;Lcom/fasterxml/jackson/databind/jsontype/PolymorphicTypeValidator;)Lcom/fasterxml/jackson/databind/JavaType;
  #177 = Utf8               handleUnknownTypeId
  #178 = Utf8               (Lcom/fasterxml/jackson/databind/JavaType;Ljava/lang/String;Lcom/fasterxml/jackson/databind/jsontype/TypeIdResolver;Ljava/lang/String;)Lcom/fasterxml/jackson/databind/JavaType;
  #179 = Utf8               com/fasterxml/jackson/databind/util/ClassUtil
  #180 = Utf8               isEnumType
  #181 = Utf8               (Ljava/lang/Class;)Z
  #182 = Utf8               java/lang/Class
  #183 = Utf8               isEnum
  #184 = Utf8               ()Z
  #185 = Utf8               getSuperclass
  #186 = Utf8               getName
  #187 = Utf8               startsWith
  #188 = Utf8               (Ljava/lang/String;)Z
  #189 = Utf8               findEnumType
  #190 = Utf8               (Ljava/util/EnumSet;)Ljava/lang/Class;
  #191 = Utf8               com/fasterxml/jackson/databind/type/TypeFactory
  #192 = Utf8               constructCollectionType
  #193 = Utf8               (Ljava/lang/Class;Ljava/lang/Class;)Lcom/fasterxml/jackson/databind/type/CollectionType;
  #194 = Utf8               com/fasterxml/jackson/databind/type/CollectionType
  #195 = Utf8               toCanonical
  #196 = Utf8               (Ljava/util/EnumMap;)Ljava/lang/Class;
  #197 = Utf8               constructMapType
  #198 = Utf8               (Ljava/lang/Class;Ljava/lang/Class;Ljava/lang/Class;)Lcom/fasterxml/jackson/databind/type/MapType;
  #199 = Utf8               com/fasterxml/jackson/databind/type/MapType
  #200 = Utf8               indexOf
  #201 = Utf8               (I)I
  #202 = Utf8               getOuterClass
  #203 = Utf8               (Ljava/lang/Class;)Ljava/lang/Class;
  #204 = Utf8               getRawClass
  #205 = Utf8               com/fasterxml/jackson/annotation/JsonTypeInfo
{
  private static final java.lang.String JAVA_UTIL_PKG;
    descriptor: Ljava/lang/String;
    flags: (0x001a) ACC_PRIVATE, ACC_STATIC, ACC_FINAL
    ConstantValue: String java.util.

  protected final com.fasterxml.jackson.databind.jsontype.PolymorphicTypeValidator _subTypeValidator;
    descriptor: Lcom/fasterxml/jackson/databind/jsontype/PolymorphicTypeValidator;
    flags: (0x0014) ACC_PROTECTED, ACC_FINAL

  protected com.fasterxml.jackson.databind.jsontype.impl.ClassNameIdResolver(com.fasterxml.jackson.databind.JavaType, com.fasterxml.jackson.databind.type.TypeFactory);
    descriptor: (Lcom/fasterxml/jackson/databind/JavaType;Lcom/fasterxml/jackson/databind/type/TypeFactory;)V
    flags: (0x0004) ACC_PROTECTED
    Code:
      stack=4, locals=3, args_size=3
         0: aload_0
         1: aload_1
         2: aload_2
         3: getstatic     #1                  // Field com/fasterxml/jackson/databind/jsontype/impl/LaissezFaireSubTypeValidator.instance:Lcom/fasterxml/jackson/databind/jsontype/impl/LaissezFaireSubTypeValidator;
         6: invokespecial #2                  // Method "<init>":(Lcom/fasterxml/jackson/databind/JavaType;Lcom/fasterxml/jackson/databind/type/TypeFactory;Lcom/fasterxml/jackson/databind/jsontype/PolymorphicTypeValidator;)V
         9: return
      LineNumberTable:
        line 30: 0
        line 31: 9
      LocalVariableTable:
        Start  Length  Slot  Name   Signature
            0      10     0  this   Lcom/fasterxml/jackson/databind/jsontype/impl/ClassNameIdResolver;
            0      10     1 baseType   Lcom/fasterxml/jackson/databind/JavaType;
            0      10     2 typeFactory   Lcom/fasterxml/jackson/databind/type/TypeFactory;
    Deprecated: true
    RuntimeVisibleAnnotations:
      0: #55()
        java.lang.Deprecated

  public com.fasterxml.jackson.databind.jsontype.impl.ClassNameIdResolver(com.fasterxml.jackson.databind.JavaType, com.fasterxml.jackson.databind.type.TypeFactory, com.fasterxml.jackson.databind.jsontype.PolymorphicTypeValidator);
    descriptor: (Lcom/fasterxml/jackson/databind/JavaType;Lcom/fasterxml/jackson/databind/type/TypeFactory;Lcom/fasterxml/jackson/databind/jsontype/PolymorphicTypeValidator;)V
    flags: (0x0001) ACC_PUBLIC
    Code:
      stack=3, locals=4, args_size=4
         0: aload_0
         1: aload_1
         2: aload_2
         3: invokespecial #3                  // Method com/fasterxml/jackson/databind/jsontype/impl/TypeIdResolverBase."<init>":(Lcom/fasterxml/jackson/databind/JavaType;Lcom/fasterxml/jackson/databind/type/TypeFactory;)V
         6: aload_0
         7: aload_3
         8: putfield      #4                  // Field _subTypeValidator:Lcom/fasterxml/jackson/databind/jsontype/PolymorphicTypeValidator;
        11: return
      LineNumberTable:
        line 38: 0
        line 39: 6
        line 40: 11
      LocalVariableTable:
        Start  Length  Slot  Name   Signature
            0      12     0  this   Lcom/fasterxml/jackson/databind/jsontype/impl/ClassNameIdResolver;
            0      12     1 baseType   Lcom/fasterxml/jackson/databind/JavaType;
            0      12     2 typeFactory   Lcom/fasterxml/jackson/databind/type/TypeFactory;
            0      12     3   ptv   Lcom/fasterxml/jackson/databind/jsontype/PolymorphicTypeValidator;

  public static com.fasterxml.jackson.databind.jsontype.impl.ClassNameIdResolver construct(com.fasterxml.jackson.databind.JavaType, com.fasterxml.jackson.databind.cfg.MapperConfig<?>, com.fasterxml.jackson.databind.jsontype.PolymorphicTypeValidator);
    descriptor: (Lcom/fasterxml/jackson/databind/JavaType;Lcom/fasterxml/jackson/databind/cfg/MapperConfig;Lcom/fasterxml/jackson/databind/jsontype/PolymorphicTypeValidator;)Lcom/fasterxml/jackson/databind/jsontype/impl/ClassNameIdResolver;
    flags: (0x0009) ACC_PUBLIC, ACC_STATIC
    Code:
      stack=5, locals=3, args_size=3
         0: new           #5                  // class com/fasterxml/jackson/databind/jsontype/impl/ClassNameIdResolver
         3: dup
         4: aload_0
         5: aload_1
         6: invokevirtual #6                  // Method com/fasterxml/jackson/databind/cfg/MapperConfig.getTypeFactory:()Lcom/fasterxml/jackson/databind/type/TypeFactory;
         9: aload_2
        10: invokespecial #2                  // Method "<init>":(Lcom/fasterxml/jackson/databind/JavaType;Lcom/fasterxml/jackson/databind/type/TypeFactory;Lcom/fasterxml/jackson/databind/jsontype/PolymorphicTypeValidator;)V
        13: areturn
      LineNumberTable:
        line 44: 0
      LocalVariableTable:
        Start  Length  Slot  Name   Signature
            0      14     0 baseType   Lcom/fasterxml/jackson/databind/JavaType;
            0      14     1 config   Lcom/fasterxml/jackson/databind/cfg/MapperConfig;
            0      14     2   ptv   Lcom/fasterxml/jackson/databind/jsontype/PolymorphicTypeValidator;
      LocalVariableTypeTable:
        Start  Length  Slot  Name   Signature
            0      14     1 config   Lcom/fasterxml/jackson/databind/cfg/MapperConfig<*>;
    Signature: #65                          // (Lcom/fasterxml/jackson/databind/JavaType;Lcom/fasterxml/jackson/databind/cfg/MapperConfig<*>;Lcom/fasterxml/jackson/databind/jsontype/PolymorphicTypeValidator;)Lcom/fasterxml/jackson/databind/jsontype/impl/ClassNameIdResolver;

  public com.fasterxml.jackson.annotation.JsonTypeInfo$Id getMechanism();
    descriptor: ()Lcom/fasterxml/jackson/annotation/JsonTypeInfo$Id;
    flags: (0x0001) ACC_PUBLIC
    Code:
      stack=1, locals=1, args_size=1
         0: getstatic     #7                  // Field com/fasterxml/jackson/annotation/JsonTypeInfo$Id.CLASS:Lcom/fasterxml/jackson/annotation/JsonTypeInfo$Id;
         3: areturn
      LineNumberTable:
        line 48: 0
      LocalVariableTable:
        Start  Length  Slot  Name   Signature
            0       4     0  this   Lcom/fasterxml/jackson/databind/jsontype/impl/ClassNameIdResolver;

  public void registerSubtype(java.lang.Class<?>, java.lang.String);
    descriptor: (Ljava/lang/Class;Ljava/lang/String;)V
    flags: (0x0001) ACC_PUBLIC
    Code:
      stack=0, locals=3, args_size=3
         0: return
      LineNumberTable:
        line 52: 0
      LocalVariableTable:
        Start  Length  Slot  Name   Signature
            0       1     0  this   Lcom/fasterxml/jackson/databind/jsontype/impl/ClassNameIdResolver;
            0       1     1  type   Ljava/lang/Class;
            0       1     2  name   Ljava/lang/String;
      LocalVariableTypeTable:
        Start  Length  Slot  Name   Signature
            0       1     1  type   Ljava/lang/Class<*>;
    Signature: #77                          // (Ljava/lang/Class<*>;Ljava/lang/String;)V

  public java.lang.String idFromValue(java.lang.Object);
    descriptor: (Ljava/lang/Object;)Ljava/lang/String;
    flags: (0x0001) ACC_PUBLIC
    Code:
      stack=4, locals=2, args_size=2
         0: aload_0
         1: aload_1
         2: aload_1
         3: invokevirtual #8                  // Method java/lang/Object.getClass:()Ljava/lang/Class;
         6: aload_0
         7: getfield      #9                  // Field _typeFactory:Lcom/fasterxml/jackson/databind/type/TypeFactory;
        10: invokevirtual #10                 // Method _idFrom:(Ljava/lang/Object;Ljava/lang/Class;Lcom/fasterxml/jackson/databind/type/TypeFactory;)Ljava/lang/String;
        13: areturn
      LineNumberTable:
        line 56: 0
      LocalVariableTable:
        Start  Length  Slot  Name   Signature
            0      14     0  this   Lcom/fasterxml/jackson/databind/jsontype/impl/ClassNameIdResolver;
            0      14     1 value   Ljava/lang/Object;

  public java.lang.String idFromValueAndType(java.lang.Object, java.lang.Class<?>);
    descriptor: (Ljava/lang/Object;Ljava/lang/Class;)Ljava/lang/String;
    flags: (0x0001) ACC_PUBLIC
    Code:
      stack=4, locals=3, args_size=3
         0: aload_0
         1: aload_1
         2: aload_2
         3: aload_0
         4: getfield      #9                  // Field _typeFactory:Lcom/fasterxml/jackson/databind/type/TypeFactory;
         7: invokevirtual #10                 // Method _idFrom:(Ljava/lang/Object;Ljava/lang/Class;Lcom/fasterxml/jackson/databind/type/TypeFactory;)Ljava/lang/String;
        10: areturn
      LineNumberTable:
        line 61: 0
      LocalVariableTable:
        Start  Length  Slot  Name   Signature
            0      11     0  this   Lcom/fasterxml/jackson/databind/jsontype/impl/ClassNameIdResolver;
            0      11     1 value   Ljava/lang/Object;
            0      11     2  type   Ljava/lang/Class;
      LocalVariableTypeTable:
        Start  Length  Slot  Name   Signature
            0      11     2  type   Ljava/lang/Class<*>;
    Signature: #84                          // (Ljava/lang/Object;Ljava/lang/Class<*>;)Ljava/lang/String;

  public com.fasterxml.jackson.databind.JavaType typeFromId(com.fasterxml.jackson.databind.DatabindContext, java.lang.String) throws java.io.IOException;
    descriptor: (Lcom/fasterxml/jackson/databind/DatabindContext;Ljava/lang/String;)Lcom/fasterxml/jackson/databind/JavaType;
    flags: (0x0001) ACC_PUBLIC
    Code:
      stack=3, locals=3, args_size=3
         0: aload_0
         1: aload_2
         2: aload_1
         3: invokevirtual #11                 // Method _typeFromId:(Ljava/lang/String;Lcom/fasterxml/jackson/databind/DatabindContext;)Lcom/fasterxml/jackson/databind/JavaType;
         6: areturn
      LineNumberTable:
        line 66: 0
      LocalVariableTable:
        Start  Length  Slot  Name   Signature
            0       7     0  this   Lcom/fasterxml/jackson/databind/jsontype/impl/ClassNameIdResolver;
            0       7     1 context   Lcom/fasterxml/jackson/databind/DatabindContext;
            0       7     2    id   Ljava/lang/String;
    Exceptions:
      throws java.io.IOException

  protected com.fasterxml.jackson.databind.JavaType _typeFromId(java.lang.String, com.fasterxml.jackson.databind.DatabindContext) throws java.io.IOException;
    descriptor: (Ljava/lang/String;Lcom/fasterxml/jackson/databind/DatabindContext;)Lcom/fasterxml/jackson/databind/JavaType;
    flags: (0x0004) ACC_PROTECTED
    Code:
      stack=5, locals=4, args_size=3
         0: aload_2
         1: aload_0
         2: getfield      #12                 // Field _baseType:Lcom/fasterxml/jackson/databind/JavaType;
         5: aload_1
         6: aload_0
         7: getfield      #4                  // Field _subTypeValidator:Lcom/fasterxml/jackson/databind/jsontype/PolymorphicTypeValidator;
        10: invokevirtual #13                 // Method com/fasterxml/jackson/databind/DatabindContext.resolveAndValidateSubType:(Lcom/fasterxml/jackson/databind/JavaType;Ljava/lang/String;Lcom/fasterxml/jackson/databind/jsontype/PolymorphicTypeValidator;)Lcom/fasterxml/jackson/databind/JavaType;
        13: astore_3
        14: aload_3
        15: ifnonnull     41
        18: aload_2
        19: instanceof    #14                 // class com/fasterxml/jackson/databind/DeserializationContext
        22: ifeq          41
        25: aload_2
        26: checkcast     #14                 // class com/fasterxml/jackson/databind/DeserializationContext
        29: aload_0
        30: getfield      #12                 // Field _baseType:Lcom/fasterxml/jackson/databind/JavaType;
        33: aload_1
        34: aload_0
        35: ldc           #15                 // String no such class found
        37: invokevirtual #16                 // Method com/fasterxml/jackson/databind/DeserializationContext.handleUnknownTypeId:(Lcom/fasterxml/jackson/databind/JavaType;Ljava/lang/String;Lcom/fasterxml/jackson/databind/jsontype/TypeIdResolver;Ljava/lang/String;)Lcom/fasterxml/jackson/databind/JavaType;
        40: areturn
        41: aload_3
        42: areturn
      LineNumberTable:
        line 72: 0
        line 73: 14
        line 74: 18
        line 76: 25
        line 80: 41
      LocalVariableTable:
        Start  Length  Slot  Name   Signature
            0      43     0  this   Lcom/fasterxml/jackson/databind/jsontype/impl/ClassNameIdResolver;
            0      43     1    id   Ljava/lang/String;
            0      43     2  ctxt   Lcom/fasterxml/jackson/databind/DatabindContext;
           14      29     3     t   Lcom/fasterxml/jackson/databind/JavaType;
      StackMapTable: number_of_entries = 1
        frame_type = 252 /* append */
          offset_delta = 41
          locals = [ class com/fasterxml/jackson/databind/JavaType ]
    Exceptions:
      throws java.io.IOException

  protected java.lang.String _idFrom(java.lang.Object, java.lang.Class<?>, com.fasterxml.jackson.databind.type.TypeFactory);
    descriptor: (Ljava/lang/Object;Ljava/lang/Class;Lcom/fasterxml/jackson/databind/type/TypeFactory;)Ljava/lang/String;
    flags: (0x0004) ACC_PROTECTED
    Code:
      stack=4, locals=7, args_size=4
         0: aload_2
         1: invokestatic  #17                 // Method com/fasterxml/jackson/databind/util/ClassUtil.isEnumType:(Ljava/lang/Class;)Z
         4: ifeq          19
         7: aload_2
         8: invokevirtual #18                 // Method java/lang/Class.isEnum:()Z
        11: ifne          19
        14: aload_2
        15: invokevirtual #19                 // Method java/lang/Class.getSuperclass:()Ljava/lang/Class;
        18: astore_2
        19: aload_2
        20: invokevirtual #20                 // Method java/lang/Class.getName:()Ljava/lang/String;
        23: astore        4
        25: aload         4
        27: ldc           #21                 // String java.util.
        29: invokevirtual #22                 // Method java/lang/String.startsWith:(Ljava/lang/String;)Z
        32: ifeq          105
        35: aload_1
        36: instanceof    #23                 // class java/util/EnumSet
        39: ifeq          67
        42: aload_1
        43: checkcast     #23                 // class java/util/EnumSet
        46: invokestatic  #24                 // Method com/fasterxml/jackson/databind/util/ClassUtil.findEnumType:(Ljava/util/EnumSet;)Ljava/lang/Class;
        49: astore        5
        51: aload_3
        52: ldc           #23                 // class java/util/EnumSet
        54: aload         5
        56: invokevirtual #25                 // Method com/fasterxml/jackson/databind/type/TypeFactory.constructCollectionType:(Ljava/lang/Class;Ljava/lang/Class;)Lcom/fasterxml/jackson/databind/type/CollectionType;
        59: invokevirtual #26                 // Method com/fasterxml/jackson/databind/type/CollectionType.toCanonical:()Ljava/lang/String;
        62: astore        4
        64: goto          157
        67: aload_1
        68: instanceof    #27                 // class java/util/EnumMap
        71: ifeq          157
        74: aload_1
        75: checkcast     #27                 // class java/util/EnumMap
        78: invokestatic  #28                 // Method com/fasterxml/jackson/databind/util/ClassUtil.findEnumType:(Ljava/util/EnumMap;)Ljava/lang/Class;
        81: astore        5
        83: ldc           #29                 // class java/lang/Object
        85: astore        6
        87: aload_3
        88: ldc           #27                 // class java/util/EnumMap
        90: aload         5
        92: aload         6
        94: invokevirtual #30                 // Method com/fasterxml/jackson/databind/type/TypeFactory.constructMapType:(Ljava/lang/Class;Ljava/lang/Class;Ljava/lang/Class;)Lcom/fasterxml/jackson/databind/type/MapType;
        97: invokevirtual #31                 // Method com/fasterxml/jackson/databind/type/MapType.toCanonical:()Ljava/lang/String;
       100: astore        4
       102: goto          157
       105: aload         4
       107: bipush        36
       109: invokevirtual #32                 // Method java/lang/String.indexOf:(I)I
       112: iflt          157
       115: aload_2
       116: invokestatic  #33                 // Method com/fasterxml/jackson/databind/util/ClassUtil.getOuterClass:(Ljava/lang/Class;)Ljava/lang/Class;
       119: astore        5
       121: aload         5
       123: ifnull        157
       126: aload_0
       127: getfield      #12                 // Field _baseType:Lcom/fasterxml/jackson/databind/JavaType;
       130: invokevirtual #34                 // Method com/fasterxml/jackson/databind/JavaType.getRawClass:()Ljava/lang/Class;
       133: astore        6
       135: aload         6
       137: invokestatic  #33                 // Method com/fasterxml/jackson/databind/util/ClassUtil.getOuterClass:(Ljava/lang/Class;)Ljava/lang/Class;
       140: ifnonnull     157
       143: aload_0
       144: getfield      #12                 // Field _baseType:Lcom/fasterxml/jackson/databind/JavaType;
       147: invokevirtual #34                 // Method com/fasterxml/jackson/databind/JavaType.getRawClass:()Ljava/lang/Class;
       150: astore_2
       151: aload_2
       152: invokevirtual #20                 // Method java/lang/Class.getName:()Ljava/lang/String;
       155: astore        4
       157: aload         4
       159: areturn
      LineNumberTable:
        line 92: 0
        line 97: 7
        line 99: 14
        line 102: 19
        line 103: 25
        line 110: 35
        line 111: 42
        line 113: 51
        line 114: 64
        line 115: 74
        line 116: 83
        line 118: 87
        line 119: 102
        line 122: 105
        line 130: 115
        line 131: 121
        line 134: 126
        line 135: 135
        line 137: 143
        line 138: 151
        line 142: 157
      LocalVariableTable:
        Start  Length  Slot  Name   Signature
           51      13     5 enumClass   Ljava/lang/Class;
           83      19     5 enumClass   Ljava/lang/Class;
           87      15     6 valueClass   Ljava/lang/Class;
          135      22     6 staticType   Ljava/lang/Class;
          121      36     5 outer   Ljava/lang/Class;
            0     160     0  this   Lcom/fasterxml/jackson/databind/jsontype/impl/ClassNameIdResolver;
            0     160     1 value   Ljava/lang/Object;
            0     160     2   cls   Ljava/lang/Class;
            0     160     3 typeFactory   Lcom/fasterxml/jackson/databind/type/TypeFactory;
           25     135     4   str   Ljava/lang/String;
      LocalVariableTypeTable:
        Start  Length  Slot  Name   Signature
           51      13     5 enumClass   Ljava/lang/Class<*>;
           83      19     5 enumClass   Ljava/lang/Class<*>;
           87      15     6 valueClass   Ljava/lang/Class<*>;
          135      22     6 staticType   Ljava/lang/Class<*>;
          121      36     5 outer   Ljava/lang/Class<*>;
            0     160     2   cls   Ljava/lang/Class<*>;
      StackMapTable: number_of_entries = 4
        frame_type = 19 /* same */
        frame_type = 252 /* append */
          offset_delta = 47
          locals = [ class java/lang/String ]
        frame_type = 37 /* same */
        frame_type = 51 /* same */
    Signature: #107                         // (Ljava/lang/Object;Ljava/lang/Class<*>;Lcom/fasterxml/jackson/databind/type/TypeFactory;)Ljava/lang/String;

  public java.lang.String getDescForKnownTypeIds();
    descriptor: ()Ljava/lang/String;
    flags: (0x0001) ACC_PUBLIC
    Code:
      stack=1, locals=1, args_size=1
         0: ldc           #35                 // String class name used as type id
         2: areturn
      LineNumberTable:
        line 147: 0
      LocalVariableTable:
        Start  Length  Slot  Name   Signature
            0       3     0  this   Lcom/fasterxml/jackson/databind/jsontype/impl/ClassNameIdResolver;
}
SourceFile: "ClassNameIdResolver.java"
InnerClasses:
  public static final #68= #67 of #157;   // Id=class com/fasterxml/jackson/annotation/JsonTypeInfo$Id of class com/fasterxml/jackson/annotation/JsonTypeInfo
