Classfile /Users/mw/Projects/slang-braindump/.jar/jar8/assemble/slang-braindump/assemble/content/scala/ref/Reference.class
  Last modified May 29, 2022; size 2075 bytes
  SHA-256 checksum 37c53cb4dee76fa41586db87b86ffb3f5d737c754e93d03a5f67a1ee7e8d1fb2
  Compiled from "Reference.scala"
public interface scala.ref.Reference<T extends java.lang.Object> extends scala.Function0<T>
  minor version: 0
  major version: 52
  flags: (0x0601) ACC_PUBLIC, ACC_INTERFACE, ACC_ABSTRACT
  this_class: #2                          // scala/ref/Reference
  super_class: #5                         // java/lang/Object
  interfaces: 1, fields: 0, methods: 10, attributes: 5
Constant pool:
   #1 = Utf8               scala/ref/Reference
   #2 = Class              #1             // scala/ref/Reference
   #3 = Utf8               <T:Ljava/lang/Object;>Ljava/lang/Object;Lscala/Function0<TT;>;
   #4 = Utf8               java/lang/Object
   #5 = Class              #4             // java/lang/Object
   #6 = Utf8               scala/Function0
   #7 = Class              #6             // scala/Function0
   #8 = Utf8               Reference.scala
   #9 = Utf8               Lscala/reflect/ScalaSignature;
  #10 = Utf8               bytes
  #11 = Utf8               \u0006\u0005\u00013q\u0001C\u0005\u0011\u0002\u0007\u0005a\u0002C\u0003 \u0001\u0011\u0005\u0001\u0005C\u0003%\u0001\u0019\u0005Q\u0005C\u0003\'\u0001\u0019\u0005q\u0005C\u0003,\u0001\u0011\u0005C\u0006C\u00039\u0001\u0019\u0005\u0001\u0005C\u0003:\u0001\u0019\u0005!\bC\u0003?\u0001\u0019\u0005qHA\u0005SK\u001a,\'/\u001a8dK*\u0011!bC\u0001\u0004e\u00164\'\"\u0001\u0007\u0002\u000bM\u001c\u0017\r\\1\u0004\u0001U\u0011q\"G\n\u0004\u0001A!\u0002CA\t\u0013\u001b\u0005Y\u0011BA\n\f\u0005\u0019\te.\u001f*fMB\u0019\u0011#F\f\n\u0005YY!!\u0003$v]\u000e$\u0018n\u001c81!\tA\u0012\u0004\u0004\u0001\u0005\ri\u0001AQ1\u0001\u001c\u0005\u0005!\u0016C\u0001\u000f\u0011!\t\tR$\u0003\u0002\u001f\u0017\t9aj\u001c;iS:<\u0017A\u0002\u0013j]&$H\u0005F\u0001\"!\t\t\"%\u0003\u0002$\u0017\t!QK\\5u\u0003\u0015\t\u0007\u000f\u001d7z)\u00059\u0012aA4fiV\t\u0001\u0006E\u0002\u0012S]I!AK\u0006\u0003\r=\u0003H/[8o\u0003!!xn\u0015;sS:<G#A\u0017\u0011\u00059*dBA\u00184!\t\u00014\"D\u00012\u0015\t\u0011T\"\u0001\u0004=e>|GOP\u0005\u0003i-\ta\u0001\u0015:fI\u00164\u0017B\u0001\u001c8\u0005\u0019\u0019FO]5oO*\u0011AgC\u0001\u0006G2,\u0017M]\u0001\bK:\fX/Z;f)\u0005Y\u0004CA\t=\u0013\ti4BA\u0004C_>dW-\u00198\u0002\u0015%\u001cXI\\9vKV,G-F\u0001<\u0001
  #12 = Utf8               apply
  #13 = Utf8               ()Ljava/lang/Object;
  #14 = Utf8               ()TT;
  #15 = Utf8               get
  #16 = Utf8               ()Lscala/Option;
  #17 = Utf8               ()Lscala/Option<TT;>;
  #18 = Utf8               toString$
  #19 = Utf8               (Lscala/ref/Reference;)Ljava/lang/String;
  #20 = Utf8               $this
  #21 = Utf8               toString
  #22 = Utf8               ()Ljava/lang/String;
  #23 = NameAndType        #21:#22        // toString:()Ljava/lang/String;
  #24 = InterfaceMethodref #2.#23         // scala/ref/Reference.toString:()Ljava/lang/String;
  #25 = Utf8               Lscala/ref/Reference;
  #26 = NameAndType        #15:#16        // get:()Lscala/Option;
  #27 = InterfaceMethodref #2.#26         // scala/ref/Reference.get:()Lscala/Option;
  #28 = Utf8               scala/Option
  #29 = Class              #28            // scala/Option
  #30 = Utf8               isEmpty
  #31 = Utf8               ()Z
  #32 = NameAndType        #30:#31        // isEmpty:()Z
  #33 = Methodref          #29.#32        // scala/Option.isEmpty:()Z
  #34 = Utf8               scala/None$
  #35 = Class              #34            // scala/None$
  #36 = Utf8               MODULE$
  #37 = Utf8               Lscala/None$;
  #38 = NameAndType        #36:#37        // MODULE$:Lscala/None$;
  #39 = Fieldref           #35.#38        // scala/None$.MODULE$:Lscala/None$;
  #40 = Utf8               scala/Some
  #41 = Class              #40            // scala/Some
  #42 = NameAndType        #15:#13        // get:()Ljava/lang/Object;
  #43 = Methodref          #29.#42        // scala/Option.get:()Ljava/lang/Object;
  #44 = Methodref          #5.#23         // java/lang/Object.toString:()Ljava/lang/String;
  #45 = Utf8               <init>
  #46 = Utf8               (Ljava/lang/Object;)V
  #47 = NameAndType        #45:#46        // "<init>":(Ljava/lang/Object;)V
  #48 = Methodref          #41.#47        // scala/Some."<init>":(Ljava/lang/Object;)V
  #49 = Utf8               <deleted>
  #50 = String             #49            // <deleted>
  #51 = Utf8               java/lang/String
  #52 = Class              #51            // java/lang/String
  #53 = Utf8               this
  #54 = Utf8               map_this
  #55 = Utf8               Lscala/Option;
  #56 = Utf8               getOrElse_this
  #57 = Utf8               clear
  #58 = Utf8               ()V
  #59 = Utf8               enqueue
  #60 = Utf8               isEnqueued
  #61 = Utf8               $anonfun$toString$1
  #62 = Utf8               (Ljava/lang/Object;)Ljava/lang/String;
  #63 = Utf8               x$1
  #64 = Utf8               Ljava/lang/Object;
  #65 = Utf8               $anonfun$toString$2
  #66 = Utf8               $init$
  #67 = Utf8               (Lscala/ref/Reference;)V
  #68 = Utf8               Signature
  #69 = Utf8               Code
  #70 = Utf8               LineNumberTable
  #71 = Utf8               LocalVariableTable
  #72 = Utf8               MethodParameters
  #73 = Utf8               StackMapTable
  #74 = Utf8               SourceFile
  #75 = Utf8               RuntimeVisibleAnnotations
  #76 = Utf8               ScalaInlineInfo
  #77 = Utf8               ScalaSig
{
  public abstract T apply();
    descriptor: ()Ljava/lang/Object;
    flags: (0x0401) ACC_PUBLIC, ACC_ABSTRACT
    Signature: #14                          // ()TT;

  public abstract scala.Option<T> get();
    descriptor: ()Lscala/Option;
    flags: (0x0401) ACC_PUBLIC, ACC_ABSTRACT
    Signature: #17                          // ()Lscala/Option<TT;>;

  public static java.lang.String toString$(scala.ref.Reference);
    descriptor: (Lscala/ref/Reference;)Ljava/lang/String;
    flags: (0x1009) ACC_PUBLIC, ACC_STATIC, ACC_SYNTHETIC
    Code:
      stack=1, locals=1, args_size=1
         0: aload_0
         1: invokespecial #24                 // InterfaceMethod toString:()Ljava/lang/String;
         4: areturn
      LineNumberTable:
        line 23: 0
      LocalVariableTable:
        Start  Length  Slot  Name   Signature
            0       5     0 $this   Lscala/ref/Reference;
    MethodParameters:
      Name                           Flags
      $this                          final synthetic

  public default java.lang.String toString();
    descriptor: ()Ljava/lang/String;
    flags: (0x0001) ACC_PUBLIC
    Code:
      stack=3, locals=3, args_size=1
         0: aload_0
         1: invokeinterface #27,  1           // InterfaceMethod get:()Lscala/Option;
         6: dup
         7: ifnonnull     12
        10: aconst_null
        11: athrow
        12: astore_1
        13: aload_1
        14: invokevirtual #33                 // Method scala/Option.isEmpty:()Z
        17: ifeq          26
        20: getstatic     #39                 // Field scala/None$.MODULE$:Lscala/None$;
        23: goto          40
        26: new           #41                 // class scala/Some
        29: dup
        30: aload_1
        31: invokevirtual #43                 // Method scala/Option.get:()Ljava/lang/Object;
        34: invokevirtual #44                 // Method java/lang/Object.toString:()Ljava/lang/String;
        37: invokespecial #48                 // Method scala/Some."<init>":(Ljava/lang/Object;)V
        40: aconst_null
        41: astore_1
        42: astore_2
        43: aload_2
        44: invokevirtual #33                 // Method scala/Option.isEmpty:()Z
        47: ifeq          55
        50: ldc           #50                 // String <deleted>
        52: goto          59
        55: aload_2
        56: invokevirtual #43                 // Method scala/Option.get:()Ljava/lang/Object;
        59: checkcast     #52                 // class java/lang/String
        62: areturn
      StackMapTable: number_of_entries = 5
        frame_type = 76 /* same_locals_1_stack_item */
          stack = [ class scala/Option ]
        frame_type = 252 /* append */
          offset_delta = 13
          locals = [ class scala/Option ]
        frame_type = 77 /* same_locals_1_stack_item */
          stack = [ class scala/Option ]
        frame_type = 255 /* full_frame */
          offset_delta = 14
          locals = [ class scala/ref/Reference, null, class scala/Option ]
          stack = []
        frame_type = 67 /* same_locals_1_stack_item */
          stack = [ class java/lang/Object ]
      LineNumberTable:
        line 23: 0
        line 23: 34
        line 23: 37
        line 23: 50
        line 23: 52
      LocalVariableTable:
        Start  Length  Slot  Name   Signature
            0      63     0  this   Lscala/ref/Reference;
           13      27     1 map_this   Lscala/Option;
           43      16     2 getOrElse_this   Lscala/Option;

  public abstract void clear();
    descriptor: ()V
    flags: (0x0401) ACC_PUBLIC, ACC_ABSTRACT

  public abstract boolean enqueue();
    descriptor: ()Z
    flags: (0x0401) ACC_PUBLIC, ACC_ABSTRACT

  public abstract boolean isEnqueued();
    descriptor: ()Z
    flags: (0x0401) ACC_PUBLIC, ACC_ABSTRACT

  public static java.lang.String $anonfun$toString$1(java.lang.Object);
    descriptor: (Ljava/lang/Object;)Ljava/lang/String;
    flags: (0x1009) ACC_PUBLIC, ACC_STATIC, ACC_SYNTHETIC
    Code:
      stack=1, locals=1, args_size=1
         0: aload_0
         1: invokevirtual #44                 // Method java/lang/Object.toString:()Ljava/lang/String;
         4: areturn
      LineNumberTable:
        line 23: 0
      LocalVariableTable:
        Start  Length  Slot  Name   Signature
            0       5     0   x$1   Ljava/lang/Object;
    MethodParameters:
      Name                           Flags
      x$1                            final

  public static java.lang.String $anonfun$toString$2();
    descriptor: ()Ljava/lang/String;
    flags: (0x1009) ACC_PUBLIC, ACC_STATIC, ACC_SYNTHETIC
    Code:
      stack=1, locals=0, args_size=0
         0: ldc           #50                 // String <deleted>
         2: areturn
      LineNumberTable:
        line 23: 0

  public static void $init$(scala.ref.Reference);
    descriptor: (Lscala/ref/Reference;)V
    flags: (0x0009) ACC_PUBLIC, ACC_STATIC
    Code:
      stack=0, locals=1, args_size=1
         0: return
      LineNumberTable:
        line 18: 0
      LocalVariableTable:
        Start  Length  Slot  Name   Signature
            0       1     0 $this   Lscala/ref/Reference;
    MethodParameters:
      Name                           Flags
      $this                          final synthetic
}
Signature: #3                           // <T:Ljava/lang/Object;>Ljava/lang/Object;Lscala/Function0<TT;>;
SourceFile: "Reference.scala"
RuntimeVisibleAnnotations:
  0: #9(#10=s#11)
    scala.reflect.ScalaSignature(
      bytes="\u0006\u0005\u00013q\u0001C\u0005\u0011\u0002\u0007\u0005a\u0002C\u0003 \u0001\u0011\u0005\u0001\u0005C\u0003%\u0001\u0019\u0005Q\u0005C\u0003\'\u0001\u0019\u0005q\u0005C\u0003,\u0001\u0011\u0005C\u0006C\u00039\u0001\u0019\u0005\u0001\u0005C\u0003:\u0001\u0019\u0005!\bC\u0003?\u0001\u0019\u0005qHA\u0005SK\u001a,\'/\u001a8dK*\u0011!bC\u0001\u0004e\u00164\'\"\u0001\u0007\u0002\u000bM\u001c\u0017\r\\1\u0004\u0001U\u0011q\"G\n\u0004\u0001A!\u0002CA\t\u0013\u001b\u0005Y\u0011BA\n\f\u0005\u0019\te.\u001f*fMB\u0019\u0011#F\f\n\u0005YY!!\u0003$v]\u000e$\u0018n\u001c81!\tA\u0012\u0004\u0004\u0001\u0005\ri\u0001AQ1\u0001\u001c\u0005\u0005!\u0016C\u0001\u000f\u0011!\t\tR$\u0003\u0002\u001f\u0017\t9aj\u001c;iS:<\u0017A\u0002\u0013j]&$H\u0005F\u0001\"!\t\t\"%\u0003\u0002$\u0017\t!QK\\5u\u0003\u0015\t\u0007\u000f\u001d7z)\u00059\u0012aA4fiV\t\u0001\u0006E\u0002\u0012S]I!AK\u0006\u0003\r=\u0003H/[8o\u0003!!xn\u0015;sS:<G#A\u0017\u0011\u00059*dBA\u00184!\t\u00014\"D\u00012\u0015\t\u0011T\"\u0001\u0004=e>|GOP\u0005\u0003i-\ta\u0001\u0015:fI\u00164\u0017B\u0001\u001c8\u0005\u0019\u0019FO]5oO*\u0011AgC\u0001\u0006G2,\u0017M]\u0001\bK:\fX/Z;f)\u0005Y\u0004CA\t=\u0013\ti4BA\u0004C_>dW-\u00198\u0002\u0015%\u001cXI\\9vKV,G-F\u0001<\u0001"
    )
  ScalaInlineInfo: length = 0x36 (unknown attribute)
   01 00 00 0A 00 3D 00 3E 01 00 41 00 16 01 00 42
   00 43 01 00 0C 00 0D 00 00 39 00 3A 00 00 3B 00
   1F 00 00 0F 00 10 00 00 3C 00 1F 00 00 15 00 16
   00 00 12 00 13 01
  ScalaSig: length = 0x3 (unknown attribute)
   05 02 00
