Classfile /Users/mw/Projects/slang-braindump/.jar/jar11/assemble/slang-braindump/assemble/content/scala/collection/convert/impl/BitSetStepper.class
  Last modified May 29, 2022; size 9492 bytes
  SHA-256 checksum 81c2cb81edb74b52fd4a76daaaeff8f1ee261b7f2f8245bb43adb1561fc49d3c
  Compiled from "BitSetStepper.scala"
public final class scala.collection.convert.impl.BitSetStepper extends scala.collection.convert.impl.InOrderStepperBase<scala.collection.IntStepper, scala.collection.convert.impl.BitSetStepper> implements scala.collection.IntStepper
  minor version: 0
  major version: 52
  flags: (0x0031) ACC_PUBLIC, ACC_FINAL, ACC_SUPER
  this_class: #2                          // scala/collection/convert/impl/BitSetStepper
  super_class: #5                         // scala/collection/convert/impl/InOrderStepperBase
  interfaces: 1, fields: 5, methods: 37, attributes: 6
Constant pool:
    #1 = Utf8               scala/collection/convert/impl/BitSetStepper
    #2 = Class              #1            // scala/collection/convert/impl/BitSetStepper
    #3 = Utf8               Lscala/collection/convert/impl/InOrderStepperBase<Lscala/collection/IntStepper;Lscala/collection/convert/impl/BitSetStepper;>;Lscala/collection/IntStepper;
    #4 = Utf8               scala/collection/convert/impl/InOrderStepperBase
    #5 = Class              #4            // scala/collection/convert/impl/InOrderStepperBase
    #6 = Utf8               scala/collection/IntStepper
    #7 = Class              #6            // scala/collection/IntStepper
    #8 = Utf8               BitSetStepper.scala
    #9 = Utf8               Lscala/reflect/ScalaSignature;
   #10 = Utf8               bytes
   #11 = Utf8               \u0006\u0005\u0005mc!B\u000e\u001d\u0005\u0001\"\u0003\u0002\u0003\u0018\u0001\u0005\u0003\u0007I\u0011\u0002\u0019\t\u0011\t\u0003!\u00111A\u0005\n\rC\u0001\"\u000f\u0001\u0003\u0002\u0003\u0006K!\r\u0005\t\u0013\u0002\u0011\t\u0019!C\u0005\u0015\"Aa\n\u0001BA\u0002\u0013%q\n\u0003\u0005R\u0001\t\u0005\t\u0015)\u0003L\u0011!\u0011\u0006A!a\u0001\n\u0013Q\u0005\u0002C*\u0001\u0005\u0003\u0007I\u0011\u0002+\t\u0011Y\u0003!\u0011!Q!\n-C\u0001b\u0016\u0001\u0003\u0002\u0003\u0006I\u0001\u0017\u0005\t7\u0002\u0011\t\u0011)A\u00051\"AA\f\u0001BA\u0002\u0013%Q\f\u0003\u0005_\u0001\t\u0005\r\u0011\"\u0003`\u0011!\t\u0007A!A!B\u0013A\u0006\"\u00022\u0001\t\u0003\u0019\u0007b\u00028\u0001\u0001\u0004%\tb\u001c\u0005\bg\u0002\u0001\r\u0011\"\u0005u\u0011\u00191\b\u0001)Q\u0005a\")q\u000f\u0001C\tq\"9\u0011\u0011\u0001\u0001\u0005\u0002\u0005\r\u0001\u0002CA\u0005\u0001\u0001&I!a\u0003\t\u000f\u0005]\u0001\u0001\"\u0001\u0002\u001a\u001dA\u00111\u0004\u000f\t\u0002\u0001\niBB\u0004\u001c9!\u0005\u0001%a\b\t\r\tDB\u0011AA\u0014\u0011\u001d\t\u0019\u0002\u0007C\u0001\u0003S\u0011QBQ5u\'\u0016$8\u000b^3qa\u0016\u0014(BA\u000f\u001f\u0003\u0011IW\u000e\u001d7\u000b\u0005}\u0001\u0013aB2p]Z,\'\u000f\u001e\u0006\u0003C\t\n!bY8mY\u0016\u001cG/[8o\u0015\u0005\u0019\u0013!B:dC2\f7c\u0001\u0001&SA!aeJ\u0015.\u001b\u0005a\u0012B\u0001\u0015\u001d\u0005IIen\u0014:eKJ\u001cF/\u001a9qKJ\u0014\u0015m]3\u0011\u0005)ZS\"\u0001\u0011\n\u00051\u0002#AC%oiN#X\r\u001d9feB\u0011a\u0005A\u0001\u000bk:$WM\u001d7zS:<7\u0001A\u000b\u0002cA\u0012!g\u000e\t\u0004UM*\u0014B\u0001\u001b!\u0005%\u0011\u0015\u000e^*fi>\u00038\u000f\u0005\u00027o1\u0001A!\u0003\u001d\u0004\u0003\u0003\u0005\tQ!\u0001;\u0005\ryF%M\u0001\fk:$WM\u001d7zS:<\u0007%\u0005\u0002<\u007fA\u0011A(P\u0007\u0002E%\u0011aH\t\u0002\b\u001d>$\b.\u001b8h!\ta\u0004)\u0003\u0002BE\t\u0019\u0011I\\=\u0002\u001dUtG-\u001a:ms&twm\u0018\u0013fcR\u0011Ai\u0012\t\u0003y\u0015K!A\u0012\u0012\u0003\tUs\u0017\u000e\u001e\u0005\b\u0011\n\t\t\u00111\u00012\u0003\rAH%M\u0001\u0007G\u0006\u001c\u0007.\u001a\u0019\u0016\u0003-\u0003\"\u0001\u0010\'\n\u00055\u0013#\u0001\u0002\'p]\u001e\f!bY1dQ\u0016\u0004t\fJ3r)\t!\u0005\u000bC\u0004I\u000b\u0005\u0005\t\u0019A&\u0002\u000f\r\f7\r[31A\u000511-Y2iKF\n!bY1dQ\u0016\ft\fJ3r)\t!U\u000bC\u0004I\u0011\u0005\u0005\t\u0019A&\u0002\u000f\r\f7\r[32A\u0005\u0019q,\u001b\u0019\u0011\u0005qJ\u0016B\u0001.#\u0005\rIe\u000e^\u0001\u0004?&t\u0015AC2bG\",\u0017J\u001c3fqV\t\u0001,\u0001\bdC\u000eDW-\u00138eKb|F%Z9\u0015\u0005\u0011\u0003\u0007b\u0002%\u000e\u0003\u0003\u0005\r\u0001W\u0001\fG\u0006\u001c\u0007.Z%oI\u0016D\b%\u0001\u0004=S:LGO\u0010\u000b\b[\u0011L\'n\u001b7n\u0011\u0015qs\u00021\u0001fa\t1\u0007\u000eE\u0002+g\u001d\u0004\"A\u000e5\u0005\u0013a\"\u0017\u0011!A\u0001\u0006\u0003Q\u0004\"B%\u0010\u0001\u0004Y\u0005\"\u0002*\u0010\u0001\u0004Y\u0005\"B,\u0010\u0001\u0004A\u0006\"B.\u0010\u0001\u0004A\u0006\"\u0002/\u0010\u0001\u0004A\u0016!\u00024pk:$W#\u00019\u0011\u0005q\n\u0018B\u0001:#\u0005\u001d\u0011un\u001c7fC:\f\u0011BZ8v]\u0012|F%Z9\u0015\u0005\u0011+\bb\u0002%\u0012\u0003\u0003\u0005\r\u0001]\u0001\u0007M>,h\u000e\u001a\u0011\u0002\u0011\u0019Lg\u000e\u001a(fqR$\u0012\u0001\u001d\u0015\u0003\'i\u0004\"a\u001f@\u000e\u0003qT!! \u0012\u0002\u0015\u0005tgn\u001c;bi&|g.\u0003\u0002\u0000y\n9A/Y5me\u0016\u001c\u0017!C:f[&\u001cGn\u001c8f)\ri\u0013Q\u0001\u0005\u0007\u0003\u000f!\u0002\u0019\u0001-\u0002\t!\fGNZ\u0001\tg\u000e\fg\u000eT8oOR)\u0001,!\u0004\u0002\u0012!1\u0011qB\u000bA\u0002-\u000bAAY5ug\"1\u00111C\u000bA\u0002a\u000bAA\u001a:p[\"\u0012QC_\u0001\t]\u0016DHo\u0015;faR\t\u0001,A\u0007CSR\u001cV\r^*uKB\u0004XM\u001d\t\u0003Ma\u00192\u0001GA\u0011!\ra\u00141E\u0005\u0004\u0003K\u0011#AB!osJ+g\r\u0006\u0002\u0002\u001eQ!\u00111FA\'%\u0015\ti#KA\u0019\r\u0019\ty\u0003\u0007\u0001\u0002,\taAH]3gS:,W.\u001a8u}A!\u00111GA$\u001d\u0011\t)$a\u0011\u000f\t\u0005]\u0012\u0011\t\b\u0005\u0003s\ty$\u0004\u0002\u0002<)\u0019\u0011QH\u0018\u0002\rq\u0012xn\u001c;?\u0013\u0005\u0019\u0013BA\u0011#\u0013\r\t)\u0005I\u0001\b\'R,\u0007\u000f]3s\u0013\u0011\tI%a\u0013\u0003\u001d\u00153g-[2jK:$8\u000b\u001d7ji*\u0019\u0011Q\t\u0011\t\u000f\u0005=#\u00041\u0001\u0002R\u0005\u0011!m\u001d\u0019\u0005\u0003\'\n9\u0006\u0005\u0003+g\u0005U\u0003c\u0001\u001c\u0002X\u0011Y\u0011\u0011LA\'\u0003\u0003\u0005\tQ!\u0001;\u0005\ryFE\r
   #12 = Utf8               java/util/PrimitiveIterator$OfInt
   #13 = Class              #12           // java/util/PrimitiveIterator$OfInt
   #14 = Utf8               java/util/PrimitiveIterator
   #15 = Class              #14           // java/util/PrimitiveIterator
   #16 = Utf8               OfInt
   #17 = Utf8               java/util/Spliterator$OfInt
   #18 = Class              #17           // java/util/Spliterator$OfInt
   #19 = Utf8               java/util/Spliterator
   #20 = Class              #19           // java/util/Spliterator
   #21 = Utf8               underlying
   #22 = Utf8               Lscala/collection/BitSetOps;
   #23 = Utf8               Lscala/collection/BitSetOps<*>;
   #24 = Utf8               cache0
   #25 = Utf8               J
   #26 = Utf8               cache1
   #27 = Utf8               cacheIndex
   #28 = Utf8               I
   #29 = Utf8               found
   #30 = Utf8               Z
   #31 = Utf8               from
   #32 = Utf8               (Lscala/collection/BitSetOps;)Lscala/collection/IntStepper;
   #33 = Utf8               (Lscala/collection/BitSetOps<*>;)Lscala/collection/IntStepper;
   #34 = Utf8               bs
   #35 = Utf8               scala/collection/convert/impl/BitSetStepper$
   #36 = Class              #35           // scala/collection/convert/impl/BitSetStepper$
   #37 = Utf8               MODULE$
   #38 = Utf8               Lscala/collection/convert/impl/BitSetStepper$;
   #39 = NameAndType        #37:#38       // MODULE$:Lscala/collection/convert/impl/BitSetStepper$;
   #40 = Fieldref           #36.#39       // scala/collection/convert/impl/BitSetStepper$.MODULE$:Lscala/collection/convert/impl/BitSetStepper$;
   #41 = NameAndType        #31:#32       // from:(Lscala/collection/BitSetOps;)Lscala/collection/IntStepper;
   #42 = Methodref          #36.#41       // scala/collection/convert/impl/BitSetStepper$.from:(Lscala/collection/BitSetOps;)Lscala/collection/IntStepper;
   #43 = Utf8               spliterator
   #44 = Utf8               ()Ljava/util/Spliterator$OfInt;
   #45 = Utf8               <B:Ljava/lang/Object;>()Ljava/util/Spliterator$OfInt;
   #46 = Utf8               spliterator$
   #47 = Utf8               (Lscala/collection/IntStepper;)Ljava/util/Spliterator$OfInt;
   #48 = NameAndType        #46:#47       // spliterator$:(Lscala/collection/IntStepper;)Ljava/util/Spliterator$OfInt;
   #49 = InterfaceMethodref #7.#48        // scala/collection/IntStepper.spliterator$:(Lscala/collection/IntStepper;)Ljava/util/Spliterator$OfInt;
   #50 = Utf8               this
   #51 = Utf8               Lscala/collection/convert/impl/BitSetStepper;
   #52 = Utf8               javaIterator
   #53 = Utf8               ()Ljava/util/PrimitiveIterator$OfInt;
   #54 = Utf8               <B:Ljava/lang/Object;>()Ljava/util/PrimitiveIterator$OfInt;
   #55 = Utf8               javaIterator$
   #56 = Utf8               (Lscala/collection/IntStepper;)Ljava/util/PrimitiveIterator$OfInt;
   #57 = NameAndType        #55:#56       // javaIterator$:(Lscala/collection/IntStepper;)Ljava/util/PrimitiveIterator$OfInt;
   #58 = InterfaceMethodref #7.#57        // scala/collection/IntStepper.javaIterator$:(Lscala/collection/IntStepper;)Ljava/util/PrimitiveIterator$OfInt;
   #59 = Utf8               spliterator$mcI$sp
   #60 = Utf8               ()Ljava/util/Spliterator;
   #61 = Utf8               <B:Ljava/lang/Object;>()Ljava/util/Spliterator<*>;
   #62 = Utf8               spliterator$mcI$sp$
   #63 = Utf8               (Lscala/collection/IntStepper;)Ljava/util/Spliterator;
   #64 = NameAndType        #62:#63       // spliterator$mcI$sp$:(Lscala/collection/IntStepper;)Ljava/util/Spliterator;
   #65 = InterfaceMethodref #7.#64        // scala/collection/IntStepper.spliterator$mcI$sp$:(Lscala/collection/IntStepper;)Ljava/util/Spliterator;
   #66 = Utf8               javaIterator$mcI$sp
   #67 = Utf8               ()Ljava/util/Iterator;
   #68 = Utf8               <B:Ljava/lang/Object;>()Ljava/util/Iterator<*>;
   #69 = Utf8               javaIterator$mcI$sp$
   #70 = Utf8               (Lscala/collection/IntStepper;)Ljava/util/Iterator;
   #71 = NameAndType        #69:#70       // javaIterator$mcI$sp$:(Lscala/collection/IntStepper;)Ljava/util/Iterator;
   #72 = InterfaceMethodref #7.#71        // scala/collection/IntStepper.javaIterator$mcI$sp$:(Lscala/collection/IntStepper;)Ljava/util/Iterator;
   #73 = Utf8               nextStep$mcD$sp
   #74 = Utf8               ()D
   #75 = Utf8               scala/collection/Stepper
   #76 = Class              #75           // scala/collection/Stepper
   #77 = Utf8               nextStep$mcD$sp$
   #78 = Utf8               (Lscala/collection/Stepper;)D
   #79 = NameAndType        #77:#78       // nextStep$mcD$sp$:(Lscala/collection/Stepper;)D
   #80 = InterfaceMethodref #76.#79       // scala/collection/Stepper.nextStep$mcD$sp$:(Lscala/collection/Stepper;)D
   #81 = Utf8               nextStep$mcJ$sp
   #82 = Utf8               ()J
   #83 = Utf8               nextStep$mcJ$sp$
   #84 = Utf8               (Lscala/collection/Stepper;)J
   #85 = NameAndType        #83:#84       // nextStep$mcJ$sp$:(Lscala/collection/Stepper;)J
   #86 = InterfaceMethodref #76.#85       // scala/collection/Stepper.nextStep$mcJ$sp$:(Lscala/collection/Stepper;)J
   #87 = Utf8               trySplit$mcD$sp
   #88 = Utf8               ()Lscala/collection/Stepper;
   #89 = Utf8               ()Lscala/collection/Stepper<Ljava/lang/Object;>;
   #90 = Utf8               trySplit$mcD$sp$
   #91 = Utf8               (Lscala/collection/Stepper;)Lscala/collection/Stepper;
   #92 = NameAndType        #90:#91       // trySplit$mcD$sp$:(Lscala/collection/Stepper;)Lscala/collection/Stepper;
   #93 = InterfaceMethodref #76.#92       // scala/collection/Stepper.trySplit$mcD$sp$:(Lscala/collection/Stepper;)Lscala/collection/Stepper;
   #94 = Utf8               trySplit$mcI$sp
   #95 = Utf8               trySplit$mcI$sp$
   #96 = NameAndType        #95:#91       // trySplit$mcI$sp$:(Lscala/collection/Stepper;)Lscala/collection/Stepper;
   #97 = InterfaceMethodref #76.#96       // scala/collection/Stepper.trySplit$mcI$sp$:(Lscala/collection/Stepper;)Lscala/collection/Stepper;
   #98 = Utf8               trySplit$mcJ$sp
   #99 = Utf8               trySplit$mcJ$sp$
  #100 = NameAndType        #99:#91       // trySplit$mcJ$sp$:(Lscala/collection/Stepper;)Lscala/collection/Stepper;
  #101 = InterfaceMethodref #76.#100      // scala/collection/Stepper.trySplit$mcJ$sp$:(Lscala/collection/Stepper;)Lscala/collection/Stepper;
  #102 = Utf8               spliterator$mcD$sp
  #103 = Utf8               spliterator$mcD$sp$
  #104 = Utf8               (Lscala/collection/Stepper;)Ljava/util/Spliterator;
  #105 = NameAndType        #103:#104     // spliterator$mcD$sp$:(Lscala/collection/Stepper;)Ljava/util/Spliterator;
  #106 = InterfaceMethodref #76.#105      // scala/collection/Stepper.spliterator$mcD$sp$:(Lscala/collection/Stepper;)Ljava/util/Spliterator;
  #107 = Utf8               spliterator$mcJ$sp
  #108 = Utf8               spliterator$mcJ$sp$
  #109 = NameAndType        #108:#104     // spliterator$mcJ$sp$:(Lscala/collection/Stepper;)Ljava/util/Spliterator;
  #110 = InterfaceMethodref #76.#109      // scala/collection/Stepper.spliterator$mcJ$sp$:(Lscala/collection/Stepper;)Ljava/util/Spliterator;
  #111 = Utf8               javaIterator$mcD$sp
  #112 = Utf8               javaIterator$mcD$sp$
  #113 = Utf8               (Lscala/collection/Stepper;)Ljava/util/Iterator;
  #114 = NameAndType        #112:#113     // javaIterator$mcD$sp$:(Lscala/collection/Stepper;)Ljava/util/Iterator;
  #115 = InterfaceMethodref #76.#114      // scala/collection/Stepper.javaIterator$mcD$sp$:(Lscala/collection/Stepper;)Ljava/util/Iterator;
  #116 = Utf8               javaIterator$mcJ$sp
  #117 = Utf8               javaIterator$mcJ$sp$
  #118 = NameAndType        #117:#113     // javaIterator$mcJ$sp$:(Lscala/collection/Stepper;)Ljava/util/Iterator;
  #119 = InterfaceMethodref #76.#118      // scala/collection/Stepper.javaIterator$mcJ$sp$:(Lscala/collection/Stepper;)Ljava/util/Iterator;
  #120 = Utf8               iterator
  #121 = Utf8               ()Lscala/collection/Iterator;
  #122 = Utf8               ()Lscala/collection/Iterator<Ljava/lang/Object;>;
  #123 = Utf8               iterator$
  #124 = Utf8               (Lscala/collection/Stepper;)Lscala/collection/Iterator;
  #125 = NameAndType        #123:#124     // iterator$:(Lscala/collection/Stepper;)Lscala/collection/Iterator;
  #126 = InterfaceMethodref #76.#125      // scala/collection/Stepper.iterator$:(Lscala/collection/Stepper;)Lscala/collection/Iterator;
  #127 = Utf8               ()Lscala/collection/BitSetOps;
  #128 = Utf8               ()Lscala/collection/BitSetOps<*>;
  #129 = NameAndType        #21:#22       // underlying:Lscala/collection/BitSetOps;
  #130 = Fieldref           #2.#129       // scala/collection/convert/impl/BitSetStepper.underlying:Lscala/collection/BitSetOps;
  #131 = Utf8               underlying_$eq
  #132 = Utf8               (Lscala/collection/BitSetOps;)V
  #133 = Utf8               (Lscala/collection/BitSetOps<*>;)V
  #134 = Utf8               x$1
  #135 = NameAndType        #24:#25       // cache0:J
  #136 = Fieldref           #2.#135       // scala/collection/convert/impl/BitSetStepper.cache0:J
  #137 = Utf8               cache0_$eq
  #138 = Utf8               (J)V
  #139 = NameAndType        #26:#25       // cache1:J
  #140 = Fieldref           #2.#139       // scala/collection/convert/impl/BitSetStepper.cache1:J
  #141 = Utf8               cache1_$eq
  #142 = Utf8               ()I
  #143 = NameAndType        #27:#28       // cacheIndex:I
  #144 = Fieldref           #2.#143       // scala/collection/convert/impl/BitSetStepper.cacheIndex:I
  #145 = Utf8               cacheIndex_$eq
  #146 = Utf8               (I)V
  #147 = Utf8               ()Z
  #148 = NameAndType        #29:#30       // found:Z
  #149 = Fieldref           #2.#148       // scala/collection/convert/impl/BitSetStepper.found:Z
  #150 = Utf8               found_$eq
  #151 = Utf8               (Z)V
  #152 = Utf8               findNext
  #153 = Utf8               i0
  #154 = NameAndType        #153:#142     // i0:()I
  #155 = Methodref          #2.#154       // scala/collection/convert/impl/BitSetStepper.i0:()I
  #156 = Utf8               iN
  #157 = NameAndType        #156:#142     // iN:()I
  #158 = Methodref          #2.#157       // scala/collection/convert/impl/BitSetStepper.iN:()I
  #159 = NameAndType        #27:#142      // cacheIndex:()I
  #160 = Methodref          #2.#159       // scala/collection/convert/impl/BitSetStepper.cacheIndex:()I
  #161 = NameAndType        #24:#82       // cache0:()J
  #162 = Methodref          #2.#161       // scala/collection/convert/impl/BitSetStepper.cache0:()J
  #163 = NameAndType        #26:#82       // cache1:()J
  #164 = Methodref          #2.#163       // scala/collection/convert/impl/BitSetStepper.cache1:()J
  #165 = Utf8               scanLong
  #166 = Utf8               (JI)I
  #167 = NameAndType        #165:#166     // scanLong:(JI)I
  #168 = Methodref          #2.#167       // scala/collection/convert/impl/BitSetStepper.scanLong:(JI)I
  #169 = Utf8               i0_$eq
  #170 = NameAndType        #169:#146     // i0_$eq:(I)V
  #171 = Methodref          #2.#170       // scala/collection/convert/impl/BitSetStepper.i0_$eq:(I)V
  #172 = NameAndType        #150:#151     // found_$eq:(Z)V
  #173 = Methodref          #2.#172       // scala/collection/convert/impl/BitSetStepper.found_$eq:(Z)V
  #174 = NameAndType        #29:#147      // found:()Z
  #175 = Methodref          #2.#174       // scala/collection/convert/impl/BitSetStepper.found:()Z
  #176 = NameAndType        #21:#127      // underlying:()Lscala/collection/BitSetOps;
  #177 = Methodref          #2.#176       // scala/collection/convert/impl/BitSetStepper.underlying:()Lscala/collection/BitSetOps;
  #178 = NameAndType        #145:#146     // cacheIndex_$eq:(I)V
  #179 = Methodref          #2.#178       // scala/collection/convert/impl/BitSetStepper.cacheIndex_$eq:(I)V
  #180 = Utf8               scala/collection/BitSetOps
  #181 = Class              #180          // scala/collection/BitSetOps
  #182 = Utf8               word
  #183 = Utf8               (I)J
  #184 = NameAndType        #182:#183     // word:(I)J
  #185 = InterfaceMethodref #181.#184     // scala/collection/BitSetOps.word:(I)J
  #186 = NameAndType        #137:#138     // cache0_$eq:(J)V
  #187 = Methodref          #2.#186       // scala/collection/convert/impl/BitSetStepper.cache0_$eq:(J)V
  #188 = Long               -1l
  #190 = NameAndType        #141:#138     // cache1_$eq:(J)V
  #191 = Methodref          #2.#190       // scala/collection/convert/impl/BitSetStepper.cache1_$eq:(J)V
  #192 = Utf8               i
  #193 = Utf8               ix
  #194 = Utf8               semiclone
  #195 = Utf8               (I)Lscala/collection/convert/impl/BitSetStepper;
  #196 = Utf8               half
  #197 = Utf8               <init>
  #198 = Utf8               (Lscala/collection/BitSetOps;JJIII)V
  #199 = NameAndType        #197:#198     // "<init>":(Lscala/collection/BitSetOps;JJIII)V
  #200 = Methodref          #2.#199       // scala/collection/convert/impl/BitSetStepper."<init>":(Lscala/collection/BitSetOps;JJIII)V
  #201 = Utf8               ans
  #202 = Utf8               ixNewN
  #203 = Utf8               ixOld0
  #204 = Utf8               bits
  #205 = Utf8               nextStep
  #206 = Utf8               nextStep$mcI$sp
  #207 = NameAndType        #206:#142     // nextStep$mcI$sp:()I
  #208 = Methodref          #2.#207       // scala/collection/convert/impl/BitSetStepper.nextStep$mcI$sp:()I
  #209 = NameAndType        #152:#147     // findNext:()Z
  #210 = Methodref          #2.#209       // scala/collection/convert/impl/BitSetStepper.findNext:()Z
  #211 = Utf8               scala/collection/Stepper$
  #212 = Class              #211          // scala/collection/Stepper$
  #213 = Utf8               Lscala/collection/Stepper$;
  #214 = NameAndType        #37:#213      // MODULE$:Lscala/collection/Stepper$;
  #215 = Fieldref           #212.#214     // scala/collection/Stepper$.MODULE$:Lscala/collection/Stepper$;
  #216 = Utf8               java/util/NoSuchElementException
  #217 = Class              #216          // java/util/NoSuchElementException
  #218 = Utf8               Empty Stepper
  #219 = String             #218          // Empty Stepper
  #220 = Utf8               (Ljava/lang/String;)V
  #221 = NameAndType        #197:#220     // "<init>":(Ljava/lang/String;)V
  #222 = Methodref          #217.#221     // java/util/NoSuchElementException."<init>":(Ljava/lang/String;)V
  #223 = Utf8               trySplit
  #224 = Utf8               ()Ljava/lang/Object;
  #225 = NameAndType        #223:#224     // trySplit:()Ljava/lang/Object;
  #226 = Methodref          #2.#225       // scala/collection/convert/impl/BitSetStepper.trySplit:()Ljava/lang/Object;
  #227 = Utf8               ()Lscala/collection/IntStepper;
  #228 = NameAndType        #52:#53       // javaIterator:()Ljava/util/PrimitiveIterator$OfInt;
  #229 = Methodref          #2.#228       // scala/collection/convert/impl/BitSetStepper.javaIterator:()Ljava/util/PrimitiveIterator$OfInt;
  #230 = NameAndType        #43:#44       // spliterator:()Ljava/util/Spliterator$OfInt;
  #231 = Methodref          #2.#230       // scala/collection/convert/impl/BitSetStepper.spliterator:()Ljava/util/Spliterator$OfInt;
  #232 = NameAndType        #205:#142     // nextStep:()I
  #233 = Methodref          #2.#232       // scala/collection/convert/impl/BitSetStepper.nextStep:()I
  #234 = Utf8               scala/runtime/BoxesRunTime
  #235 = Class              #234          // scala/runtime/BoxesRunTime
  #236 = Utf8               boxToInteger
  #237 = Utf8               (I)Ljava/lang/Integer;
  #238 = NameAndType        #236:#237     // boxToInteger:(I)Ljava/lang/Integer;
  #239 = Methodref          #235.#238     // scala/runtime/BoxesRunTime.boxToInteger:(I)Ljava/lang/Integer;
  #240 = Utf8               (I)Ljava/lang/Object;
  #241 = NameAndType        #194:#195     // semiclone:(I)Lscala/collection/convert/impl/BitSetStepper;
  #242 = Methodref          #2.#241       // scala/collection/convert/impl/BitSetStepper.semiclone:(I)Lscala/collection/convert/impl/BitSetStepper;
  #243 = Utf8               (Lscala/collection/BitSetOps<*>;JJIII)V
  #244 = Utf8               _i0
  #245 = Utf8               _iN
  #246 = Utf8               (II)V
  #247 = NameAndType        #197:#246     // "<init>":(II)V
  #248 = Methodref          #5.#247       // scala/collection/convert/impl/InOrderStepperBase."<init>":(II)V
  #249 = Utf8               Signature
  #250 = Utf8               Code
  #251 = Utf8               LocalVariableTable
  #252 = Utf8               MethodParameters
  #253 = Utf8               LineNumberTable
  #254 = Utf8               StackMapTable
  #255 = Utf8               InnerClasses
  #256 = Utf8               SourceFile
  #257 = Utf8               RuntimeVisibleAnnotations
  #258 = Utf8               ScalaInlineInfo
  #259 = Utf8               ScalaSig
{
  private scala.collection.BitSetOps<?> underlying;
    descriptor: Lscala/collection/BitSetOps;
    flags: (0x0002) ACC_PRIVATE
    Signature: #23                          // Lscala/collection/BitSetOps<*>;

  private long cache0;
    descriptor: J
    flags: (0x0002) ACC_PRIVATE

  private long cache1;
    descriptor: J
    flags: (0x0002) ACC_PRIVATE

  private int cacheIndex;
    descriptor: I
    flags: (0x0002) ACC_PRIVATE

  private boolean found;
    descriptor: Z
    flags: (0x0002) ACC_PRIVATE

  public static scala.collection.IntStepper from(scala.collection.BitSetOps<?>);
    descriptor: (Lscala/collection/BitSetOps;)Lscala/collection/IntStepper;
    flags: (0x0009) ACC_PUBLIC, ACC_STATIC
    Code:
      stack=2, locals=1, args_size=1
         0: getstatic     #40                 // Field scala/collection/convert/impl/BitSetStepper$.MODULE$:Lscala/collection/convert/impl/BitSetStepper$;
         3: aload_0
         4: invokevirtual #42                 // Method scala/collection/convert/impl/BitSetStepper$.from:(Lscala/collection/BitSetOps;)Lscala/collection/IntStepper;
         7: areturn
      LocalVariableTable:
        Start  Length  Slot  Name   Signature
            0       8     0    bs   Lscala/collection/BitSetOps;
    Signature: #33                          // (Lscala/collection/BitSetOps<*>;)Lscala/collection/IntStepper;
    MethodParameters:
      Name                           Flags
      bs                             final

  public <B extends java.lang.Object> java.util.Spliterator$OfInt spliterator();
    descriptor: ()Ljava/util/Spliterator$OfInt;
    flags: (0x0001) ACC_PUBLIC
    Code:
      stack=1, locals=1, args_size=1
         0: aload_0
         1: invokestatic  #49                 // InterfaceMethod scala/collection/IntStepper.spliterator$:(Lscala/collection/IntStepper;)Ljava/util/Spliterator$OfInt;
         4: areturn
      LineNumberTable:
        line 20: 0
      LocalVariableTable:
        Start  Length  Slot  Name   Signature
            0       5     0  this   Lscala/collection/convert/impl/BitSetStepper;
    Signature: #45                          // <B:Ljava/lang/Object;>()Ljava/util/Spliterator$OfInt;

  public <B extends java.lang.Object> java.util.PrimitiveIterator$OfInt javaIterator();
    descriptor: ()Ljava/util/PrimitiveIterator$OfInt;
    flags: (0x0001) ACC_PUBLIC
    Code:
      stack=1, locals=1, args_size=1
         0: aload_0
         1: invokestatic  #58                 // InterfaceMethod scala/collection/IntStepper.javaIterator$:(Lscala/collection/IntStepper;)Ljava/util/PrimitiveIterator$OfInt;
         4: areturn
      LineNumberTable:
        line 20: 0
      LocalVariableTable:
        Start  Length  Slot  Name   Signature
            0       5     0  this   Lscala/collection/convert/impl/BitSetStepper;
    Signature: #54                          // <B:Ljava/lang/Object;>()Ljava/util/PrimitiveIterator$OfInt;

  public <B extends java.lang.Object> java.util.Spliterator<?> spliterator$mcI$sp();
    descriptor: ()Ljava/util/Spliterator;
    flags: (0x0001) ACC_PUBLIC
    Code:
      stack=1, locals=1, args_size=1
         0: aload_0
         1: invokestatic  #65                 // InterfaceMethod scala/collection/IntStepper.spliterator$mcI$sp$:(Lscala/collection/IntStepper;)Ljava/util/Spliterator;
         4: areturn
      LineNumberTable:
        line 20: 0
      LocalVariableTable:
        Start  Length  Slot  Name   Signature
            0       5     0  this   Lscala/collection/convert/impl/BitSetStepper;
    Signature: #61                          // <B:Ljava/lang/Object;>()Ljava/util/Spliterator<*>;

  public <B extends java.lang.Object> java.util.Iterator<?> javaIterator$mcI$sp();
    descriptor: ()Ljava/util/Iterator;
    flags: (0x0001) ACC_PUBLIC
    Code:
      stack=1, locals=1, args_size=1
         0: aload_0
         1: invokestatic  #72                 // InterfaceMethod scala/collection/IntStepper.javaIterator$mcI$sp$:(Lscala/collection/IntStepper;)Ljava/util/Iterator;
         4: areturn
      LineNumberTable:
        line 20: 0
      LocalVariableTable:
        Start  Length  Slot  Name   Signature
            0       5     0  this   Lscala/collection/convert/impl/BitSetStepper;
    Signature: #68                          // <B:Ljava/lang/Object;>()Ljava/util/Iterator<*>;

  public double nextStep$mcD$sp();
    descriptor: ()D
    flags: (0x0001) ACC_PUBLIC
    Code:
      stack=2, locals=1, args_size=1
         0: aload_0
         1: invokestatic  #80                 // InterfaceMethod scala/collection/Stepper.nextStep$mcD$sp$:(Lscala/collection/Stepper;)D
         4: dreturn
      LineNumberTable:
        line 20: 0
      LocalVariableTable:
        Start  Length  Slot  Name   Signature
            0       5     0  this   Lscala/collection/convert/impl/BitSetStepper;

  public long nextStep$mcJ$sp();
    descriptor: ()J
    flags: (0x0001) ACC_PUBLIC
    Code:
      stack=2, locals=1, args_size=1
         0: aload_0
         1: invokestatic  #86                 // InterfaceMethod scala/collection/Stepper.nextStep$mcJ$sp$:(Lscala/collection/Stepper;)J
         4: lreturn
      LineNumberTable:
        line 20: 0
      LocalVariableTable:
        Start  Length  Slot  Name   Signature
            0       5     0  this   Lscala/collection/convert/impl/BitSetStepper;

  public scala.collection.Stepper<java.lang.Object> trySplit$mcD$sp();
    descriptor: ()Lscala/collection/Stepper;
    flags: (0x0001) ACC_PUBLIC
    Code:
      stack=1, locals=1, args_size=1
         0: aload_0
         1: invokestatic  #93                 // InterfaceMethod scala/collection/Stepper.trySplit$mcD$sp$:(Lscala/collection/Stepper;)Lscala/collection/Stepper;
         4: areturn
      LineNumberTable:
        line 20: 0
      LocalVariableTable:
        Start  Length  Slot  Name   Signature
            0       5     0  this   Lscala/collection/convert/impl/BitSetStepper;
    Signature: #89                          // ()Lscala/collection/Stepper<Ljava/lang/Object;>;

  public scala.collection.Stepper<java.lang.Object> trySplit$mcI$sp();
    descriptor: ()Lscala/collection/Stepper;
    flags: (0x0001) ACC_PUBLIC
    Code:
      stack=1, locals=1, args_size=1
         0: aload_0
         1: invokestatic  #97                 // InterfaceMethod scala/collection/Stepper.trySplit$mcI$sp$:(Lscala/collection/Stepper;)Lscala/collection/Stepper;
         4: areturn
      LineNumberTable:
        line 20: 0
      LocalVariableTable:
        Start  Length  Slot  Name   Signature
            0       5     0  this   Lscala/collection/convert/impl/BitSetStepper;
    Signature: #89                          // ()Lscala/collection/Stepper<Ljava/lang/Object;>;

  public scala.collection.Stepper<java.lang.Object> trySplit$mcJ$sp();
    descriptor: ()Lscala/collection/Stepper;
    flags: (0x0001) ACC_PUBLIC
    Code:
      stack=1, locals=1, args_size=1
         0: aload_0
         1: invokestatic  #101                // InterfaceMethod scala/collection/Stepper.trySplit$mcJ$sp$:(Lscala/collection/Stepper;)Lscala/collection/Stepper;
         4: areturn
      LineNumberTable:
        line 20: 0
      LocalVariableTable:
        Start  Length  Slot  Name   Signature
            0       5     0  this   Lscala/collection/convert/impl/BitSetStepper;
    Signature: #89                          // ()Lscala/collection/Stepper<Ljava/lang/Object;>;

  public <B extends java.lang.Object> java.util.Spliterator<?> spliterator$mcD$sp();
    descriptor: ()Ljava/util/Spliterator;
    flags: (0x0001) ACC_PUBLIC
    Code:
      stack=1, locals=1, args_size=1
         0: aload_0
         1: invokestatic  #106                // InterfaceMethod scala/collection/Stepper.spliterator$mcD$sp$:(Lscala/collection/Stepper;)Ljava/util/Spliterator;
         4: areturn
      LineNumberTable:
        line 20: 0
      LocalVariableTable:
        Start  Length  Slot  Name   Signature
            0       5     0  this   Lscala/collection/convert/impl/BitSetStepper;
    Signature: #61                          // <B:Ljava/lang/Object;>()Ljava/util/Spliterator<*>;

  public <B extends java.lang.Object> java.util.Spliterator<?> spliterator$mcJ$sp();
    descriptor: ()Ljava/util/Spliterator;
    flags: (0x0001) ACC_PUBLIC
    Code:
      stack=1, locals=1, args_size=1
         0: aload_0
         1: invokestatic  #110                // InterfaceMethod scala/collection/Stepper.spliterator$mcJ$sp$:(Lscala/collection/Stepper;)Ljava/util/Spliterator;
         4: areturn
      LineNumberTable:
        line 20: 0
      LocalVariableTable:
        Start  Length  Slot  Name   Signature
            0       5     0  this   Lscala/collection/convert/impl/BitSetStepper;
    Signature: #61                          // <B:Ljava/lang/Object;>()Ljava/util/Spliterator<*>;

  public <B extends java.lang.Object> java.util.Iterator<?> javaIterator$mcD$sp();
    descriptor: ()Ljava/util/Iterator;
    flags: (0x0001) ACC_PUBLIC
    Code:
      stack=1, locals=1, args_size=1
         0: aload_0
         1: invokestatic  #115                // InterfaceMethod scala/collection/Stepper.javaIterator$mcD$sp$:(Lscala/collection/Stepper;)Ljava/util/Iterator;
         4: areturn
      LineNumberTable:
        line 20: 0
      LocalVariableTable:
        Start  Length  Slot  Name   Signature
            0       5     0  this   Lscala/collection/convert/impl/BitSetStepper;
    Signature: #68                          // <B:Ljava/lang/Object;>()Ljava/util/Iterator<*>;

  public <B extends java.lang.Object> java.util.Iterator<?> javaIterator$mcJ$sp();
    descriptor: ()Ljava/util/Iterator;
    flags: (0x0001) ACC_PUBLIC
    Code:
      stack=1, locals=1, args_size=1
         0: aload_0
         1: invokestatic  #119                // InterfaceMethod scala/collection/Stepper.javaIterator$mcJ$sp$:(Lscala/collection/Stepper;)Ljava/util/Iterator;
         4: areturn
      LineNumberTable:
        line 20: 0
      LocalVariableTable:
        Start  Length  Slot  Name   Signature
            0       5     0  this   Lscala/collection/convert/impl/BitSetStepper;
    Signature: #68                          // <B:Ljava/lang/Object;>()Ljava/util/Iterator<*>;

  public scala.collection.Iterator<java.lang.Object> iterator();
    descriptor: ()Lscala/collection/Iterator;
    flags: (0x0001) ACC_PUBLIC
    Code:
      stack=1, locals=1, args_size=1
         0: aload_0
         1: invokestatic  #126                // InterfaceMethod scala/collection/Stepper.iterator$:(Lscala/collection/Stepper;)Lscala/collection/Iterator;
         4: areturn
      LineNumberTable:
        line 20: 0
      LocalVariableTable:
        Start  Length  Slot  Name   Signature
            0       5     0  this   Lscala/collection/convert/impl/BitSetStepper;
    Signature: #122                         // ()Lscala/collection/Iterator<Ljava/lang/Object;>;

  private scala.collection.BitSetOps<?> underlying();
    descriptor: ()Lscala/collection/BitSetOps;
    flags: (0x0002) ACC_PRIVATE
    Code:
      stack=1, locals=1, args_size=1
         0: aload_0
         1: getfield      #130                // Field underlying:Lscala/collection/BitSetOps;
         4: areturn
      LineNumberTable:
        line 21: 0
      LocalVariableTable:
        Start  Length  Slot  Name   Signature
            0       5     0  this   Lscala/collection/convert/impl/BitSetStepper;
    Signature: #128                         // ()Lscala/collection/BitSetOps<*>;

  private void underlying_$eq(scala.collection.BitSetOps<?>);
    descriptor: (Lscala/collection/BitSetOps;)V
    flags: (0x0002) ACC_PRIVATE
    Code:
      stack=2, locals=2, args_size=2
         0: aload_0
         1: aload_1
         2: putfield      #130                // Field underlying:Lscala/collection/BitSetOps;
         5: return
      LineNumberTable:
        line 21: 0
      LocalVariableTable:
        Start  Length  Slot  Name   Signature
            0       6     0  this   Lscala/collection/convert/impl/BitSetStepper;
            0       6     1   x$1   Lscala/collection/BitSetOps;
    Signature: #133                         // (Lscala/collection/BitSetOps<*>;)V
    MethodParameters:
      Name                           Flags
      x$1                            final

  private long cache0();
    descriptor: ()J
    flags: (0x0002) ACC_PRIVATE
    Code:
      stack=2, locals=1, args_size=1
         0: aload_0
         1: getfield      #136                // Field cache0:J
         4: lreturn
      LineNumberTable:
        line 22: 0
      LocalVariableTable:
        Start  Length  Slot  Name   Signature
            0       5     0  this   Lscala/collection/convert/impl/BitSetStepper;

  private void cache0_$eq(long);
    descriptor: (J)V
    flags: (0x0002) ACC_PRIVATE
    Code:
      stack=3, locals=3, args_size=2
         0: aload_0
         1: lload_1
         2: putfield      #136                // Field cache0:J
         5: return
      LineNumberTable:
        line 22: 0
      LocalVariableTable:
        Start  Length  Slot  Name   Signature
            0       6     0  this   Lscala/collection/convert/impl/BitSetStepper;
            0       6     1   x$1   J
    MethodParameters:
      Name                           Flags
      x$1                            final

  private long cache1();
    descriptor: ()J
    flags: (0x0002) ACC_PRIVATE
    Code:
      stack=2, locals=1, args_size=1
         0: aload_0
         1: getfield      #140                // Field cache1:J
         4: lreturn
      LineNumberTable:
        line 22: 0
      LocalVariableTable:
        Start  Length  Slot  Name   Signature
            0       5     0  this   Lscala/collection/convert/impl/BitSetStepper;

  private void cache1_$eq(long);
    descriptor: (J)V
    flags: (0x0002) ACC_PRIVATE
    Code:
      stack=3, locals=3, args_size=2
         0: aload_0
         1: lload_1
         2: putfield      #140                // Field cache1:J
         5: return
      LineNumberTable:
        line 22: 0
      LocalVariableTable:
        Start  Length  Slot  Name   Signature
            0       6     0  this   Lscala/collection/convert/impl/BitSetStepper;
            0       6     1   x$1   J
    MethodParameters:
      Name                           Flags
      x$1                            final

  private int cacheIndex();
    descriptor: ()I
    flags: (0x0002) ACC_PRIVATE
    Code:
      stack=1, locals=1, args_size=1
         0: aload_0
         1: getfield      #144                // Field cacheIndex:I
         4: ireturn
      LineNumberTable:
        line 24: 0
      LocalVariableTable:
        Start  Length  Slot  Name   Signature
            0       5     0  this   Lscala/collection/convert/impl/BitSetStepper;

  private void cacheIndex_$eq(int);
    descriptor: (I)V
    flags: (0x0002) ACC_PRIVATE
    Code:
      stack=2, locals=2, args_size=2
         0: aload_0
         1: iload_1
         2: putfield      #144                // Field cacheIndex:I
         5: return
      LineNumberTable:
        line 24: 0
      LocalVariableTable:
        Start  Length  Slot  Name   Signature
            0       6     0  this   Lscala/collection/convert/impl/BitSetStepper;
            0       6     1   x$1   I
    MethodParameters:
      Name                           Flags
      x$1                            final

  public boolean found();
    descriptor: ()Z
    flags: (0x0001) ACC_PUBLIC
    Code:
      stack=1, locals=1, args_size=1
         0: aload_0
         1: getfield      #149                // Field found:Z
         4: ireturn
      LineNumberTable:
        line 31: 0
      LocalVariableTable:
        Start  Length  Slot  Name   Signature
            0       5     0  this   Lscala/collection/convert/impl/BitSetStepper;

  public void found_$eq(boolean);
    descriptor: (Z)V
    flags: (0x0001) ACC_PUBLIC
    Code:
      stack=2, locals=2, args_size=2
         0: aload_0
         1: iload_1
         2: putfield      #149                // Field found:Z
         5: return
      LineNumberTable:
        line 31: 0
      LocalVariableTable:
        Start  Length  Slot  Name   Signature
            0       6     0  this   Lscala/collection/convert/impl/BitSetStepper;
            0       6     1   x$1   Z
    MethodParameters:
      Name                           Flags
      x$1                            final

  public boolean findNext();
    descriptor: ()Z
    flags: (0x0001) ACC_PUBLIC
    Code:
      stack=5, locals=3, args_size=1
         0: aload_0
         1: invokevirtual #155                // Method i0:()I
         4: aload_0
         5: invokevirtual #158                // Method iN:()I
         8: if_icmplt     13
        11: iconst_0
        12: ireturn
        13: aload_0
        14: invokevirtual #155                // Method i0:()I
        17: bipush        6
        19: ishr
        20: istore_1
        21: iload_1
        22: aload_0
        23: invokespecial #160                // Method cacheIndex:()I
        26: if_icmpeq     39
        29: iload_1
        30: aload_0
        31: invokespecial #160                // Method cacheIndex:()I
        34: iconst_1
        35: iadd
        36: if_icmpne     134
        39: aload_0
        40: iload_1
        41: aload_0
        42: invokespecial #160                // Method cacheIndex:()I
        45: if_icmpne     55
        48: aload_0
        49: invokespecial #162                // Method cache0:()J
        52: goto          59
        55: aload_0
        56: invokespecial #164                // Method cache1:()J
        59: aload_0
        60: invokevirtual #155                // Method i0:()I
        63: bipush        63
        65: iand
        66: invokespecial #168                // Method scanLong:(JI)I
        69: istore_2
        70: iload_2
        71: iconst_0
        72: if_icmplt     115
        75: aload_0
        76: aload_0
        77: invokevirtual #155                // Method i0:()I
        80: bipush        63
        82: iconst_m1
        83: ixor
        84: iand
        85: iload_2
        86: ior
        87: invokevirtual #171                // Method i0_$eq:(I)V
        90: aload_0
        91: aload_0
        92: invokevirtual #155                // Method i0:()I
        95: aload_0
        96: invokevirtual #158                // Method iN:()I
        99: if_icmpge     106
       102: iconst_1
       103: goto          107
       106: iconst_0
       107: invokevirtual #173                // Method found_$eq:(Z)V
       110: aload_0
       111: invokevirtual #175                // Method found:()Z
       114: ireturn
       115: aload_0
       116: aload_0
       117: invokevirtual #155                // Method i0:()I
       120: bipush        63
       122: iconst_m1
       123: ixor
       124: iand
       125: bipush        64
       127: iadd
       128: invokevirtual #171                // Method i0_$eq:(I)V
       131: goto          0
       134: aload_0
       135: invokespecial #177                // Method underlying:()Lscala/collection/BitSetOps;
       138: ifnonnull     159
       141: aload_0
       142: aload_0
       143: invokevirtual #158                // Method iN:()I
       146: invokevirtual #171                // Method i0_$eq:(I)V
       149: aload_0
       150: iconst_0
       151: invokevirtual #173                // Method found_$eq:(Z)V
       154: aload_0
       155: invokevirtual #175                // Method found:()Z
       158: ireturn
       159: aload_0
       160: iload_1
       161: invokespecial #179                // Method cacheIndex_$eq:(I)V
       164: aload_0
       165: aload_0
       166: invokespecial #177                // Method underlying:()Lscala/collection/BitSetOps;
       169: aload_0
       170: invokespecial #160                // Method cacheIndex:()I
       173: invokeinterface #185,  2          // InterfaceMethod scala/collection/BitSetOps.word:(I)J
       178: invokespecial #187                // Method cache0_$eq:(J)V
       181: aload_0
       182: aload_0
       183: invokevirtual #158                // Method iN:()I
       186: iconst_1
       187: isub
       188: bipush        6
       190: ishr
       191: iload_1
       192: if_icmpne     201
       195: ldc2_w        #188                // long -1l
       198: goto          216
       201: aload_0
       202: invokespecial #177                // Method underlying:()Lscala/collection/BitSetOps;
       205: aload_0
       206: invokespecial #160                // Method cacheIndex:()I
       209: iconst_1
       210: iadd
       211: invokeinterface #185,  2          // InterfaceMethod scala/collection/BitSetOps.word:(I)J
       216: invokespecial #191                // Method cache1_$eq:(J)V
       219: goto          0
      StackMapTable: number_of_entries = 12
        frame_type = 0 /* same */
        frame_type = 12 /* same */
        frame_type = 252 /* append */
          offset_delta = 25
          locals = [ int ]
        frame_type = 79 /* same_locals_1_stack_item */
          stack = [ class scala/collection/convert/impl/BitSetStepper ]
        frame_type = 255 /* full_frame */
          offset_delta = 3
          locals = [ class scala/collection/convert/impl/BitSetStepper, int ]
          stack = [ class scala/collection/convert/impl/BitSetStepper, long ]
        frame_type = 255 /* full_frame */
          offset_delta = 46
          locals = [ class scala/collection/convert/impl/BitSetStepper, int, int ]
          stack = [ class scala/collection/convert/impl/BitSetStepper ]
        frame_type = 255 /* full_frame */
          offset_delta = 0
          locals = [ class scala/collection/convert/impl/BitSetStepper, int, int ]
          stack = [ class scala/collection/convert/impl/BitSetStepper, int ]
        frame_type = 7 /* same */
        frame_type = 250 /* chop */
          offset_delta = 18
        frame_type = 24 /* same */
        frame_type = 105 /* same_locals_1_stack_item */
          stack = [ class scala/collection/convert/impl/BitSetStepper ]
        frame_type = 255 /* full_frame */
          offset_delta = 14
          locals = [ class scala/collection/convert/impl/BitSetStepper, int ]
          stack = [ class scala/collection/convert/impl/BitSetStepper, long ]
      LineNumberTable:
        line 35: 0
        line 37: 13
        line 38: 21
        line 39: 39
        line 40: 70
        line 41: 75
        line 42: 90
        line 43: 110
        line 46: 115
        line 47: 131
        line 50: 134
        line 51: 141
        line 52: 149
        line 53: 154
        line 56: 159
        line 57: 164
        line 58: 181
        line 59: 219
      LocalVariableTable:
        Start  Length  Slot  Name   Signature
           70      64     2     i   I
           21     201     1    ix   I
            0     222     0  this   Lscala/collection/convert/impl/BitSetStepper;

  public scala.collection.convert.impl.BitSetStepper semiclone(int);
    descriptor: (I)Lscala/collection/convert/impl/BitSetStepper;
    flags: (0x0001) ACC_PUBLIC
    Code:
      stack=10, locals=6, args_size=2
         0: aload_0
         1: invokespecial #177                // Method underlying:()Lscala/collection/BitSetOps;
         4: ifnonnull     53
         7: new           #2                  // class scala/collection/convert/impl/BitSetStepper
        10: dup
        11: aconst_null
        12: aload_0
        13: invokespecial #162                // Method cache0:()J
        16: aload_0
        17: invokespecial #164                // Method cache1:()J
        20: aload_0
        21: invokevirtual #155                // Method i0:()I
        24: iload_1
        25: aload_0
        26: invokespecial #160                // Method cacheIndex:()I
        29: invokespecial #200                // Method "<init>":(Lscala/collection/BitSetOps;JJIII)V
        32: astore_2
        33: aload_2
        34: aload_0
        35: invokevirtual #175                // Method found:()Z
        38: invokevirtual #173                // Method found_$eq:(Z)V
        41: aload_0
        42: iload_1
        43: invokevirtual #171                // Method i0_$eq:(I)V
        46: aload_0
        47: iconst_0
        48: invokevirtual #173                // Method found_$eq:(Z)V
        51: aload_2
        52: areturn
        53: iload_1
        54: iconst_1
        55: isub
        56: bipush        6
        58: ishr
        59: istore_3
        60: new           #2                  // class scala/collection/convert/impl/BitSetStepper
        63: dup
        64: iload_3
        65: aload_0
        66: invokespecial #160                // Method cacheIndex:()I
        69: iconst_1
        70: iadd
        71: if_icmpgt     78
        74: aconst_null
        75: goto          82
        78: aload_0
        79: invokespecial #177                // Method underlying:()Lscala/collection/BitSetOps;
        82: aload_0
        83: invokespecial #162                // Method cache0:()J
        86: aload_0
        87: invokespecial #164                // Method cache1:()J
        90: aload_0
        91: invokevirtual #155                // Method i0:()I
        94: iload_1
        95: aload_0
        96: invokespecial #160                // Method cacheIndex:()I
        99: invokespecial #200                // Method "<init>":(Lscala/collection/BitSetOps;JJIII)V
       102: astore        4
       104: aload_0
       105: invokevirtual #175                // Method found:()Z
       108: ifeq          117
       111: aload         4
       113: iconst_1
       114: invokevirtual #173                // Method found_$eq:(Z)V
       117: iload_1
       118: bipush        6
       120: ishr
       121: istore        5
       123: iload         5
       125: aload_0
       126: invokespecial #160                // Method cacheIndex:()I
       129: iconst_1
       130: iadd
       131: if_icmple     202
       134: aload_0
       135: aload_0
       136: invokespecial #177                // Method underlying:()Lscala/collection/BitSetOps;
       139: iload         5
       141: invokeinterface #185,  2          // InterfaceMethod scala/collection/BitSetOps.word:(I)J
       146: invokespecial #187                // Method cache0_$eq:(J)V
       149: aload_0
       150: aload_0
       151: invokevirtual #158                // Method iN:()I
       154: iconst_1
       155: isub
       156: bipush        6
       158: ishr
       159: iload         5
       161: if_icmpne     170
       164: ldc2_w        #188                // long -1l
       167: goto          183
       170: aload_0
       171: invokespecial #177                // Method underlying:()Lscala/collection/BitSetOps;
       174: iload         5
       176: iconst_1
       177: iadd
       178: invokeinterface #185,  2          // InterfaceMethod scala/collection/BitSetOps.word:(I)J
       183: invokespecial #191                // Method cache1_$eq:(J)V
       186: aload_0
       187: iload         5
       189: invokespecial #179                // Method cacheIndex_$eq:(I)V
       192: aload_0
       193: iload_1
       194: invokevirtual #171                // Method i0_$eq:(I)V
       197: aload_0
       198: iconst_0
       199: invokevirtual #173                // Method found_$eq:(Z)V
       202: aload         4
       204: areturn
      StackMapTable: number_of_entries = 7
        frame_type = 53 /* same */
        frame_type = 255 /* full_frame */
          offset_delta = 24
          locals = [ class scala/collection/convert/impl/BitSetStepper, int, top, int ]
          stack = [ uninitialized 60, uninitialized 60 ]
        frame_type = 255 /* full_frame */
          offset_delta = 3
          locals = [ class scala/collection/convert/impl/BitSetStepper, int, top, int ]
          stack = [ uninitialized 60, uninitialized 60, class scala/collection/BitSetOps ]
        frame_type = 252 /* append */
          offset_delta = 34
          locals = [ class scala/collection/convert/impl/BitSetStepper ]
        frame_type = 255 /* full_frame */
          offset_delta = 52
          locals = [ class scala/collection/convert/impl/BitSetStepper, int, top, int, class scala/collection/convert/impl/BitSetStepper, int ]
          stack = [ class scala/collection/convert/impl/BitSetStepper ]
        frame_type = 255 /* full_frame */
          offset_delta = 12
          locals = [ class scala/collection/convert/impl/BitSetStepper, int, top, int, class scala/collection/convert/impl/BitSetStepper, int ]
          stack = [ class scala/collection/convert/impl/BitSetStepper, long ]
        frame_type = 18 /* same */
      LineNumberTable:
        line 64: 0
        line 65: 7
        line 66: 33
        line 67: 41
        line 68: 46
        line 69: 51
        line 73: 53
        line 75: 60
        line 76: 104
        line 79: 117
        line 80: 123
        line 81: 134
        line 82: 149
        line 83: 186
        line 84: 192
        line 85: 197
        line 89: 202
      LocalVariableTable:
        Start  Length  Slot  Name   Signature
           33      19     2   ans   Lscala/collection/convert/impl/BitSetStepper;
           60     144     3 ixNewN   I
          104     100     4   ans   Lscala/collection/convert/impl/BitSetStepper;
          123      81     5 ixOld0   I
            0     205     0  this   Lscala/collection/convert/impl/BitSetStepper;
            0     205     1  half   I
    MethodParameters:
      Name                           Flags
      half                           final

  private int scanLong(long, int);
    descriptor: (JI)I
    flags: (0x0002) ACC_PRIVATE
    Code:
      stack=5, locals=4, args_size=3
         0: iload_3
         1: bipush        64
         3: if_icmplt     8
         6: iconst_m1
         7: ireturn
         8: lload_1
         9: lconst_1
        10: iload_3
        11: lshl
        12: land
        13: lconst_0
        14: lcmp
        15: ifeq          20
        18: iload_3
        19: ireturn
        20: lload_1
        21: iload_3
        22: iconst_1
        23: iadd
        24: istore_3
        25: lstore_1
        26: goto          0
      StackMapTable: number_of_entries = 3
        frame_type = 0 /* same */
        frame_type = 7 /* same */
        frame_type = 11 /* same */
      LineNumberTable:
        line 94: 0
        line 95: 8
        line 96: 20
      LocalVariableTable:
        Start  Length  Slot  Name   Signature
            0      29     0  this   Lscala/collection/convert/impl/BitSetStepper;
            0      29     1  bits   J
            0      29     3  from   I
    MethodParameters:
      Name                           Flags
      bits                           final
      from                           final

  public int nextStep();
    descriptor: ()I
    flags: (0x0001) ACC_PUBLIC
    Code:
      stack=1, locals=1, args_size=1
         0: aload_0
         1: invokevirtual #208                // Method nextStep$mcI$sp:()I
         4: ireturn
      LineNumberTable:
        line 98: 0
      LocalVariableTable:
        Start  Length  Slot  Name   Signature
            0       5     0  this   Lscala/collection/convert/impl/BitSetStepper;

  public int nextStep$mcI$sp();
    descriptor: ()I
    flags: (0x0001) ACC_PUBLIC
    Code:
      stack=3, locals=2, args_size=1
         0: aload_0
         1: invokevirtual #175                // Method found:()Z
         4: ifne          14
         7: aload_0
         8: invokevirtual #210                // Method findNext:()Z
        11: ifeq          36
        14: aload_0
        15: iconst_0
        16: invokevirtual #173                // Method found_$eq:(Z)V
        19: aload_0
        20: invokevirtual #155                // Method i0:()I
        23: istore_1
        24: aload_0
        25: aload_0
        26: invokevirtual #155                // Method i0:()I
        29: iconst_1
        30: iadd
        31: invokevirtual #171                // Method i0_$eq:(I)V
        34: iload_1
        35: ireturn
        36: getstatic     #215                // Field scala/collection/Stepper$.MODULE$:Lscala/collection/Stepper$;
        39: pop
        40: new           #217                // class java/util/NoSuchElementException
        43: dup
        44: ldc           #219                // String Empty Stepper
        46: invokespecial #222                // Method java/util/NoSuchElementException."<init>":(Ljava/lang/String;)V
        49: athrow
      StackMapTable: number_of_entries = 2
        frame_type = 14 /* same */
        frame_type = 21 /* same */
      LineNumberTable:
        line 99: 0
        line 100: 14
        line 101: 19
        line 102: 24
        line 103: 34
        line 105: 36
      LocalVariableTable:
        Start  Length  Slot  Name   Signature
           24      11     1   ans   I
            0      50     0  this   Lscala/collection/convert/impl/BitSetStepper;

  public scala.collection.Stepper trySplit();
    descriptor: ()Lscala/collection/Stepper;
    flags: (0x1041) ACC_PUBLIC, ACC_BRIDGE, ACC_SYNTHETIC
    Code:
      stack=1, locals=1, args_size=1
         0: aload_0
         1: invokevirtual #226                // Method trySplit:()Ljava/lang/Object;
         4: checkcast     #76                 // class scala/collection/Stepper
         7: areturn
      LineNumberTable:
        line 20: 0
      LocalVariableTable:
        Start  Length  Slot  Name   Signature
            0       8     0  this   Lscala/collection/convert/impl/BitSetStepper;

  public scala.collection.IntStepper trySplit();
    descriptor: ()Lscala/collection/IntStepper;
    flags: (0x1041) ACC_PUBLIC, ACC_BRIDGE, ACC_SYNTHETIC
    Code:
      stack=1, locals=1, args_size=1
         0: aload_0
         1: invokevirtual #226                // Method trySplit:()Ljava/lang/Object;
         4: checkcast     #7                  // class scala/collection/IntStepper
         7: areturn
      LineNumberTable:
        line 20: 0
      LocalVariableTable:
        Start  Length  Slot  Name   Signature
            0       8     0  this   Lscala/collection/convert/impl/BitSetStepper;

  public java.util.Iterator javaIterator();
    descriptor: ()Ljava/util/Iterator;
    flags: (0x1041) ACC_PUBLIC, ACC_BRIDGE, ACC_SYNTHETIC
    Code:
      stack=1, locals=1, args_size=1
         0: aload_0
         1: invokevirtual #229                // Method javaIterator:()Ljava/util/PrimitiveIterator$OfInt;
         4: areturn
      LineNumberTable:
        line 20: 0
      LocalVariableTable:
        Start  Length  Slot  Name   Signature
            0       5     0  this   Lscala/collection/convert/impl/BitSetStepper;

  public java.util.Spliterator spliterator();
    descriptor: ()Ljava/util/Spliterator;
    flags: (0x1041) ACC_PUBLIC, ACC_BRIDGE, ACC_SYNTHETIC
    Code:
      stack=1, locals=1, args_size=1
         0: aload_0
         1: invokevirtual #231                // Method spliterator:()Ljava/util/Spliterator$OfInt;
         4: areturn
      LineNumberTable:
        line 20: 0
      LocalVariableTable:
        Start  Length  Slot  Name   Signature
            0       5     0  this   Lscala/collection/convert/impl/BitSetStepper;

  public java.lang.Object nextStep();
    descriptor: ()Ljava/lang/Object;
    flags: (0x1041) ACC_PUBLIC, ACC_BRIDGE, ACC_SYNTHETIC
    Code:
      stack=1, locals=1, args_size=1
         0: aload_0
         1: invokevirtual #233                // Method nextStep:()I
         4: invokestatic  #239                // Method scala/runtime/BoxesRunTime.boxToInteger:(I)Ljava/lang/Integer;
         7: areturn
      LineNumberTable:
        line 20: 0
      LocalVariableTable:
        Start  Length  Slot  Name   Signature
            0       8     0  this   Lscala/collection/convert/impl/BitSetStepper;

  public java.lang.Object semiclone(int);
    descriptor: (I)Ljava/lang/Object;
    flags: (0x1041) ACC_PUBLIC, ACC_BRIDGE, ACC_SYNTHETIC
    Code:
      stack=2, locals=2, args_size=2
         0: aload_0
         1: iload_1
         2: invokevirtual #242                // Method semiclone:(I)Lscala/collection/convert/impl/BitSetStepper;
         5: areturn
      LineNumberTable:
        line 20: 0
      LocalVariableTable:
        Start  Length  Slot  Name   Signature
            0       6     0  this   Lscala/collection/convert/impl/BitSetStepper;
            0       6     1  half   I
    MethodParameters:
      Name                           Flags
      half                           final

  public scala.collection.convert.impl.BitSetStepper(scala.collection.BitSetOps<?>, long, long, int, int, int);
    descriptor: (Lscala/collection/BitSetOps;JJIII)V
    flags: (0x0001) ACC_PUBLIC
    Code:
      stack=3, locals=9, args_size=7
         0: aload_0
         1: aload_1
         2: putfield      #130                // Field underlying:Lscala/collection/BitSetOps;
         5: aload_0
         6: lload_2
         7: putfield      #136                // Field cache0:J
        10: aload_0
        11: lload         4
        13: putfield      #140                // Field cache1:J
        16: aload_0
        17: iload         8
        19: putfield      #144                // Field cacheIndex:I
        22: aload_0
        23: iload         6
        25: iload         7
        27: invokespecial #248                // Method scala/collection/convert/impl/InOrderStepperBase."<init>":(II)V
        30: aload_0
        31: iconst_0
        32: putfield      #149                // Field found:Z
        35: return
      LineNumberTable:
        line 21: 0
        line 22: 5
        line 24: 16
        line 26: 22
        line 31: 30
        line 20: 35
      LocalVariableTable:
        Start  Length  Slot  Name   Signature
            0      36     0  this   Lscala/collection/convert/impl/BitSetStepper;
            0      36     1 underlying   Lscala/collection/BitSetOps;
            0      36     2 cache0   J
            0      36     4 cache1   J
            0      36     6   _i0   I
            0      36     7   _iN   I
            0      36     8 cacheIndex   I
    Signature: #243                         // (Lscala/collection/BitSetOps<*>;JJIII)V
    MethodParameters:
      Name                           Flags
      underlying                     final
      cache0                         final
      cache1                         final
      _i0                            final
      _iN                            final
      cacheIndex                     final
}
InnerClasses:
  public static #16= #13 of #15;          // OfInt=class java/util/PrimitiveIterator$OfInt of class java/util/PrimitiveIterator
  public static #16= #18 of #20;          // OfInt=class java/util/Spliterator$OfInt of class java/util/Spliterator
Signature: #3                           // Lscala/collection/convert/impl/InOrderStepperBase<Lscala/collection/IntStepper;Lscala/collection/convert/impl/BitSetStepper;>;Lscala/collection/IntStepper;
SourceFile: "BitSetStepper.scala"
RuntimeVisibleAnnotations:
  0: #9(#10=s#11)
    scala.reflect.ScalaSignature(
      bytes="\u0006\u0005\u0005mc!B\u000e\u001d\u0005\u0001\"\u0003\u0002\u0003\u0018\u0001\u0005\u0003\u0007I\u0011\u0002\u0019\t\u0011\t\u0003!\u00111A\u0005\n\rC\u0001\"\u000f\u0001\u0003\u0002\u0003\u0006K!\r\u0005\t\u0013\u0002\u0011\t\u0019!C\u0005\u0015\"Aa\n\u0001BA\u0002\u0013%q\n\u0003\u0005R\u0001\t\u0005\t\u0015)\u0003L\u0011!\u0011\u0006A!a\u0001\n\u0013Q\u0005\u0002C*\u0001\u0005\u0003\u0007I\u0011\u0002+\t\u0011Y\u0003!\u0011!Q!\n-C\u0001b\u0016\u0001\u0003\u0002\u0003\u0006I\u0001\u0017\u0005\t7\u0002\u0011\t\u0011)A\u00051\"AA\f\u0001BA\u0002\u0013%Q\f\u0003\u0005_\u0001\t\u0005\r\u0011\"\u0003`\u0011!\t\u0007A!A!B\u0013A\u0006\"\u00022\u0001\t\u0003\u0019\u0007b\u00028\u0001\u0001\u0004%\tb\u001c\u0005\bg\u0002\u0001\r\u0011\"\u0005u\u0011\u00191\b\u0001)Q\u0005a\")q\u000f\u0001C\tq\"9\u0011\u0011\u0001\u0001\u0005\u0002\u0005\r\u0001\u0002CA\u0005\u0001\u0001&I!a\u0003\t\u000f\u0005]\u0001\u0001\"\u0001\u0002\u001a\u001dA\u00111\u0004\u000f\t\u0002\u0001\niBB\u0004\u001c9!\u0005\u0001%a\b\t\r\tDB\u0011AA\u0014\u0011\u001d\t\u0019\u0002\u0007C\u0001\u0003S\u0011QBQ5u\'\u0016$8\u000b^3qa\u0016\u0014(BA\u000f\u001f\u0003\u0011IW\u000e\u001d7\u000b\u0005}\u0001\u0013aB2p]Z,\'\u000f\u001e\u0006\u0003C\t\n!bY8mY\u0016\u001cG/[8o\u0015\u0005\u0019\u0013!B:dC2\f7c\u0001\u0001&SA!aeJ\u0015.\u001b\u0005a\u0012B\u0001\u0015\u001d\u0005IIen\u0014:eKJ\u001cF/\u001a9qKJ\u0014\u0015m]3\u0011\u0005)ZS\"\u0001\u0011\n\u00051\u0002#AC%oiN#X\r\u001d9feB\u0011a\u0005A\u0001\u000bk:$WM\u001d7zS:<7\u0001A\u000b\u0002cA\u0012!g\u000e\t\u0004UM*\u0014B\u0001\u001b!\u0005%\u0011\u0015\u000e^*fi>\u00038\u000f\u0005\u00027o1\u0001A!\u0003\u001d\u0004\u0003\u0003\u0005\tQ!\u0001;\u0005\ryF%M\u0001\fk:$WM\u001d7zS:<\u0007%\u0005\u0002<\u007fA\u0011A(P\u0007\u0002E%\u0011aH\t\u0002\b\u001d>$\b.\u001b8h!\ta\u0004)\u0003\u0002BE\t\u0019\u0011I\\=\u0002\u001dUtG-\u001a:ms&twm\u0018\u0013fcR\u0011Ai\u0012\t\u0003y\u0015K!A\u0012\u0012\u0003\tUs\u0017\u000e\u001e\u0005\b\u0011\n\t\t\u00111\u00012\u0003\rAH%M\u0001\u0007G\u0006\u001c\u0007.\u001a\u0019\u0016\u0003-\u0003\"\u0001\u0010\'\n\u00055\u0013#\u0001\u0002\'p]\u001e\f!bY1dQ\u0016\u0004t\fJ3r)\t!\u0005\u000bC\u0004I\u000b\u0005\u0005\t\u0019A&\u0002\u000f\r\f7\r[31A\u000511-Y2iKF\n!bY1dQ\u0016\ft\fJ3r)\t!U\u000bC\u0004I\u0011\u0005\u0005\t\u0019A&\u0002\u000f\r\f7\r[32A\u0005\u0019q,\u001b\u0019\u0011\u0005qJ\u0016B\u0001.#\u0005\rIe\u000e^\u0001\u0004?&t\u0015AC2bG\",\u0017J\u001c3fqV\t\u0001,\u0001\bdC\u000eDW-\u00138eKb|F%Z9\u0015\u0005\u0011\u0003\u0007b\u0002%\u000e\u0003\u0003\u0005\r\u0001W\u0001\fG\u0006\u001c\u0007.Z%oI\u0016D\b%\u0001\u0004=S:LGO\u0010\u000b\b[\u0011L\'n\u001b7n\u0011\u0015qs\u00021\u0001fa\t1\u0007\u000eE\u0002+g\u001d\u0004\"A\u000e5\u0005\u0013a\"\u0017\u0011!A\u0001\u0006\u0003Q\u0004\"B%\u0010\u0001\u0004Y\u0005\"\u0002*\u0010\u0001\u0004Y\u0005\"B,\u0010\u0001\u0004A\u0006\"B.\u0010\u0001\u0004A\u0006\"\u0002/\u0010\u0001\u0004A\u0016!\u00024pk:$W#\u00019\u0011\u0005q\n\u0018B\u0001:#\u0005\u001d\u0011un\u001c7fC:\f\u0011BZ8v]\u0012|F%Z9\u0015\u0005\u0011+\bb\u0002%\u0012\u0003\u0003\u0005\r\u0001]\u0001\u0007M>,h\u000e\u001a\u0011\u0002\u0011\u0019Lg\u000e\u001a(fqR$\u0012\u0001\u001d\u0015\u0003\'i\u0004\"a\u001f@\u000e\u0003qT!! \u0012\u0002\u0015\u0005tgn\u001c;bi&|g.\u0003\u0002\u0000y\n9A/Y5me\u0016\u001c\u0017!C:f[&\u001cGn\u001c8f)\ri\u0013Q\u0001\u0005\u0007\u0003\u000f!\u0002\u0019\u0001-\u0002\t!\fGNZ\u0001\tg\u000e\fg\u000eT8oOR)\u0001,!\u0004\u0002\u0012!1\u0011qB\u000bA\u0002-\u000bAAY5ug\"1\u00111C\u000bA\u0002a\u000bAA\u001a:p[\"\u0012QC_\u0001\t]\u0016DHo\u0015;faR\t\u0001,A\u0007CSR\u001cV\r^*uKB\u0004XM\u001d\t\u0003Ma\u00192\u0001GA\u0011!\ra\u00141E\u0005\u0004\u0003K\u0011#AB!osJ+g\r\u0006\u0002\u0002\u001eQ!\u00111FA\'%\u0015\ti#KA\u0019\r\u0019\ty\u0003\u0007\u0001\u0002,\taAH]3gS:,W.\u001a8u}A!\u00111GA$\u001d\u0011\t)$a\u0011\u000f\t\u0005]\u0012\u0011\t\b\u0005\u0003s\ty$\u0004\u0002\u0002<)\u0019\u0011QH\u0018\u0002\rq\u0012xn\u001c;?\u0013\u0005\u0019\u0013BA\u0011#\u0013\r\t)\u0005I\u0001\b\'R,\u0007\u000f]3s\u0013\u0011\tI%a\u0013\u0003\u001d\u00153g-[2jK:$8\u000b\u001d7ji*\u0019\u0011Q\t\u0011\t\u000f\u0005=#\u00041\u0001\u0002R\u0005\u0011!m\u001d\u0019\u0005\u0003\'\n9\u0006\u0005\u0003+g\u0005U\u0003c\u0001\u001c\u0002X\u0011Y\u0011\u0011LA\'\u0003\u0003\u0005\tQ!\u0001;\u0005\ryFE\r"
    )
  ScalaInlineInfo: length = 0xB8 (unknown attribute)
   01 01 00 24 00 C5 00 C6 01 00 18 00 52 01 00 89
   00 8A 01 00 1A 00 52 01 00 8D 00 8A 01 00 1B 00
   8E 01 00 91 00 92 01 00 98 00 93 01 00 1D 00 93
   01 00 96 00 97 01 00 78 00 79 01 00 34 00 43 01
   00 34 00 35 01 00 6F 00 43 01 00 42 00 43 01 00
   74 00 43 01 00 CD 00 8E 01 00 CD 00 E0 01 00 49
   00 4A 01 00 CE 00 8E 01 00 51 00 52 01 00 A5 00
   A6 01 00 C2 00 F0 01 00 C2 00 C3 01 00 2B 00 2C
   01 00 2B 00 3C 01 00 66 00 3C 01 00 3B 00 3C 01
   00 6B 00 3C 01 00 DF 00 E3 01 00 DF 00 58 01 00
   57 00 58 01 00 5E 00 58 01 00 62 00 58 01 00 15
   00 7F 01 00 83 00 84 01
  ScalaSig: length = 0x3 (unknown attribute)
   05 02 00
