Classfile /Users/mw/Projects/slang-braindump/.jar/jar11/assemble/slang-braindump/assemble/content/scala/collection/convert/impl/IteratorStepperBase.class
  Last modified May 29, 2022; size 2868 bytes
  SHA-256 checksum d280a426a1279c9c2f17a31ba440231e9a7f2a6c9dd7bc929dd7524ce9efef80
  Compiled from "IteratorStepper.scala"
public abstract class scala.collection.convert.impl.IteratorStepperBase<A extends java.lang.Object, SP extends scala.collection.Stepper<A>, Semi extends SP> extends java.lang.Object
  minor version: 0
  major version: 52
  flags: (0x0421) ACC_PUBLIC, ACC_SUPER, ACC_ABSTRACT
  this_class: #2                          // scala/collection/convert/impl/IteratorStepperBase
  super_class: #5                         // java/lang/Object
  interfaces: 0, fields: 3, methods: 10, attributes: 5
Constant pool:
   #1 = Utf8               scala/collection/convert/impl/IteratorStepperBase
   #2 = Class              #1             // scala/collection/convert/impl/IteratorStepperBase
   #3 = Utf8               <A:Ljava/lang/Object;SP::Lscala/collection/Stepper<TA;>;Semi:TSP;>Ljava/lang/Object;
   #4 = Utf8               java/lang/Object
   #5 = Class              #4             // java/lang/Object
   #6 = Utf8               IteratorStepper.scala
   #7 = Utf8               Lscala/reflect/ScalaSignature;
   #8 = Utf8               bytes
   #9 = Utf8               \u0006\u000514aAD\b\u0002\u0002E9\u0002\u0002C\u000f\u0001\u0005\u000b\u0007IQC\u0010\t\u0011]\u0002!\u0011!Q\u0001\u000e\u0001BQ\u0001\u000f\u0001\u0005\u0002eBq\u0001\u0014\u0001A\u0002\u0013UQ\nC\u0004R\u0001\u0001\u0007IQ\u0003*\t\ra\u0003\u0001\u0015)\u0004O\u0011\u001dI\u0006\u00011A\u0005\u0016iCqa\u0017\u0001A\u0002\u0013UA\f\u0003\u0004_\u0001\u0001\u0006k\u0001\u0010\u0005\u0006?\u00021\t\u0002\u0019\u0005\u0006C\u0002!\t!\u0014\u0005\u0006E\u0002!\ta\u0019\u0005\u0006O\u0002!\t\u0001\u001b\u0002\u0014\u0013R,\'/\u0019;peN#X\r\u001d9fe\n\u000b7/\u001a\u0006\u0003!E\tA![7qY*\u0011!cE\u0001\bG>tg/\u001a:u\u0015\t!R#\u0001\u0006d_2dWm\u0019;j_:T\u0011AF\u0001\u0006g\u000e\fG.Y\u000b\u000519j\u0004j\u0005\u0002\u00013A\u0011!dG\u0007\u0002+%\u0011A$\u0006\u0002\u0007\u0003:L(+\u001a4\u0002\u0015UtG-\u001a:ms&twm\u0001\u0001\u0016\u0003\u0001\u00022!I\u0015-\u001d\t\u0011sE\u0004\u0002$M5\tAE\u0003\u0002&=\u00051AH]8pizJ\u0011AF\u0005\u0003QU\tq\u0001]1dW\u0006<W-\u0003\u0002+W\tA\u0011\n^3sCR|\'O\u0003\u0002)+A\u0011QF\f\u0007\u0001\t\u0015y\u0003A1\u00011\u0005\u0005\t\u0015CA\u00195!\tQ\"\'\u0003\u00024+\t9aj\u001c;iS:<\u0007C\u0001\u000e6\u0013\t1TCA\u0002B]f\f1\"\u001e8eKJd\u00170\u001b8hA\u00051A(\u001b8jiz\"\"AO&\u0011\u000bm\u0002A\u0006P$\u000e\u0003=\u0001\"!L\u001f\u0005\u000by\u0002!\u0019A \u0003\u0005M\u0003\u0016C\u0001!D!\tQ\u0012)\u0003\u0002C+\t!a*\u001e7m!\r!U\tL\u0007\u0002\'%\u0011ai\u0005\u0002\b\'R,\u0007\u000f]3s!\ti\u0003\nB\u0003J\u0001\t\u0007!J\u0001\u0003TK6L\u0017CA\u0019=\u0011\u0015i2\u00011\u0001!\u00035qW\r\u001f;DQVt7nU5{KV\ta\n\u0005\u0002\u001b\u001f&\u0011\u0001+\u0006\u0002\u0004\u0013:$\u0018!\u00058fqR\u001c\u0005.\u001e8l\'&TXm\u0018\u0013fcR\u00111K\u0016\t\u00035QK!!V\u000b\u0003\tUs\u0017\u000e\u001e\u0005\b/\u0016\t\t\u00111\u0001O\u0003\rAH%M\u0001\u000f]\u0016DHo\u00115v].\u001c\u0016N_3!\u0003\u001d\u0001(o\u001c=jK\u0012,\u0012\u0001P\u0001\faJ|\u00070[3e?\u0012*\u0017\u000f\u0006\u0002T;\"9q\u000bCA\u0001\u0002\u0004a\u0014\u0001\u00039s_bLW\r\u001a\u0011\u0002\u0013M,W.[2m_:,G#A$\u0002\u001f\rD\u0017M]1di\u0016\u0014\u0018n\u001d;jGN\fA\"Z:uS6\fG/Z*ju\u0016,\u0012\u0001\u001a\t\u00035\u0015L!AZ\u000b\u0003\t1{gnZ\u0001\bQ\u0006\u001c8\u000b^3q+\u0005I\u0007C\u0001\u000ek\u0013\tYWCA\u0004C_>dW-\u00198
  #10 = Utf8               underlying
  #11 = Utf8               Lscala/collection/Iterator;
  #12 = Utf8               Lscala/collection/Iterator<TA;>;
  #13 = Utf8               nextChunkSize
  #14 = Utf8               I
  #15 = Utf8               proxied
  #16 = Utf8               Lscala/collection/Stepper;
  #17 = Utf8               TSP;
  #18 = Utf8               ()Lscala/collection/Iterator;
  #19 = Utf8               ()Lscala/collection/Iterator<TA;>;
  #20 = NameAndType        #10:#11        // underlying:Lscala/collection/Iterator;
  #21 = Fieldref           #2.#20         // scala/collection/convert/impl/IteratorStepperBase.underlying:Lscala/collection/Iterator;
  #22 = Utf8               this
  #23 = Utf8               Lscala/collection/convert/impl/IteratorStepperBase;
  #24 = Utf8               ()I
  #25 = NameAndType        #13:#14        // nextChunkSize:I
  #26 = Fieldref           #2.#25         // scala/collection/convert/impl/IteratorStepperBase.nextChunkSize:I
  #27 = Utf8               nextChunkSize_$eq
  #28 = Utf8               (I)V
  #29 = Utf8               x$1
  #30 = Utf8               ()Lscala/collection/Stepper;
  #31 = Utf8               ()TSP;
  #32 = NameAndType        #15:#16        // proxied:Lscala/collection/Stepper;
  #33 = Fieldref           #2.#32         // scala/collection/convert/impl/IteratorStepperBase.proxied:Lscala/collection/Stepper;
  #34 = Utf8               proxied_$eq
  #35 = Utf8               (Lscala/collection/Stepper;)V
  #36 = Utf8               (TSP;)V
  #37 = Utf8               semiclone
  #38 = Utf8               ()TSemi;
  #39 = Utf8               characteristics
  #40 = NameAndType        #15:#30        // proxied:()Lscala/collection/Stepper;
  #41 = Methodref          #2.#40         // scala/collection/convert/impl/IteratorStepperBase.proxied:()Lscala/collection/Stepper;
  #42 = Utf8               estimateSize
  #43 = Utf8               ()J
  #44 = Utf8               scala/collection/Stepper
  #45 = Class              #44            // scala/collection/Stepper
  #46 = NameAndType        #42:#43        // estimateSize:()J
  #47 = InterfaceMethodref #45.#46        // scala/collection/Stepper.estimateSize:()J
  #48 = Long               9223372036854775807l
  #50 = Utf8               hasStep
  #51 = Utf8               ()Z
  #52 = NameAndType        #50:#51        // hasStep:()Z
  #53 = InterfaceMethodref #45.#52        // scala/collection/Stepper.hasStep:()Z
  #54 = NameAndType        #10:#18        // underlying:()Lscala/collection/Iterator;
  #55 = Methodref          #2.#54         // scala/collection/convert/impl/IteratorStepperBase.underlying:()Lscala/collection/Iterator;
  #56 = Utf8               scala/collection/Iterator
  #57 = Class              #56            // scala/collection/Iterator
  #58 = Utf8               hasNext
  #59 = NameAndType        #58:#51        // hasNext:()Z
  #60 = InterfaceMethodref #57.#59        // scala/collection/Iterator.hasNext:()Z
  #61 = Utf8               <init>
  #62 = Utf8               (Lscala/collection/Iterator;)V
  #63 = Utf8               (Lscala/collection/Iterator<TA;>;)V
  #64 = Utf8               ()V
  #65 = NameAndType        #61:#64        // "<init>":()V
  #66 = Methodref          #5.#65         // java/lang/Object."<init>":()V
  #67 = Utf8               Signature
  #68 = Utf8               Code
  #69 = Utf8               LineNumberTable
  #70 = Utf8               LocalVariableTable
  #71 = Utf8               MethodParameters
  #72 = Utf8               StackMapTable
  #73 = Utf8               SourceFile
  #74 = Utf8               RuntimeVisibleAnnotations
  #75 = Utf8               ScalaInlineInfo
  #76 = Utf8               ScalaSig
{
  private final scala.collection.Iterator<A> underlying;
    descriptor: Lscala/collection/Iterator;
    flags: (0x0012) ACC_PRIVATE, ACC_FINAL
    Signature: #12                          // Lscala/collection/Iterator<TA;>;

  private int nextChunkSize;
    descriptor: I
    flags: (0x0002) ACC_PRIVATE

  private SP proxied;
    descriptor: Lscala/collection/Stepper;
    flags: (0x0002) ACC_PRIVATE
    Signature: #17                          // TSP;

  public final scala.collection.Iterator<A> underlying();
    descriptor: ()Lscala/collection/Iterator;
    flags: (0x0011) ACC_PUBLIC, ACC_FINAL
    Code:
      stack=1, locals=1, args_size=1
         0: aload_0
         1: getfield      #21                 // Field underlying:Lscala/collection/Iterator;
         4: areturn
      LineNumberTable:
        line 122: 0
      LocalVariableTable:
        Start  Length  Slot  Name   Signature
            0       5     0  this   Lscala/collection/convert/impl/IteratorStepperBase;
    Signature: #19                          // ()Lscala/collection/Iterator<TA;>;

  public final int nextChunkSize();
    descriptor: ()I
    flags: (0x0011) ACC_PUBLIC, ACC_FINAL
    Code:
      stack=1, locals=1, args_size=1
         0: aload_0
         1: getfield      #26                 // Field nextChunkSize:I
         4: ireturn
      LineNumberTable:
        line 123: 0
      LocalVariableTable:
        Start  Length  Slot  Name   Signature
            0       5     0  this   Lscala/collection/convert/impl/IteratorStepperBase;

  public final void nextChunkSize_$eq(int);
    descriptor: (I)V
    flags: (0x0011) ACC_PUBLIC, ACC_FINAL
    Code:
      stack=2, locals=2, args_size=2
         0: aload_0
         1: iload_1
         2: putfield      #26                 // Field nextChunkSize:I
         5: return
      LineNumberTable:
        line 123: 0
      LocalVariableTable:
        Start  Length  Slot  Name   Signature
            0       6     0  this   Lscala/collection/convert/impl/IteratorStepperBase;
            0       6     1   x$1   I
    MethodParameters:
      Name                           Flags
      x$1                            final

  public final SP proxied();
    descriptor: ()Lscala/collection/Stepper;
    flags: (0x0011) ACC_PUBLIC, ACC_FINAL
    Code:
      stack=1, locals=1, args_size=1
         0: aload_0
         1: getfield      #33                 // Field proxied:Lscala/collection/Stepper;
         4: areturn
      LineNumberTable:
        line 124: 0
      LocalVariableTable:
        Start  Length  Slot  Name   Signature
            0       5     0  this   Lscala/collection/convert/impl/IteratorStepperBase;
    Signature: #31                          // ()TSP;

  public final void proxied_$eq(SP);
    descriptor: (Lscala/collection/Stepper;)V
    flags: (0x0011) ACC_PUBLIC, ACC_FINAL
    Code:
      stack=2, locals=2, args_size=2
         0: aload_0
         1: aload_1
         2: putfield      #33                 // Field proxied:Lscala/collection/Stepper;
         5: return
      LineNumberTable:
        line 124: 0
      LocalVariableTable:
        Start  Length  Slot  Name   Signature
            0       6     0  this   Lscala/collection/convert/impl/IteratorStepperBase;
            0       6     1   x$1   Lscala/collection/Stepper;
    Signature: #36                          // (TSP;)V
    MethodParameters:
      Name                           Flags
      x$1                            final

  public abstract Semi semiclone();
    descriptor: ()Lscala/collection/Stepper;
    flags: (0x0401) ACC_PUBLIC, ACC_ABSTRACT
    Signature: #38                          // ()TSemi;

  public int characteristics();
    descriptor: ()I
    flags: (0x0001) ACC_PUBLIC
    Code:
      stack=1, locals=1, args_size=1
         0: aload_0
         1: invokevirtual #41                 // Method proxied:()Lscala/collection/Stepper;
         4: ifnull        11
         7: sipush        16464
        10: ireturn
        11: bipush        16
        13: ireturn
      StackMapTable: number_of_entries = 1
        frame_type = 11 /* same */
      LineNumberTable:
        line 126: 0
      LocalVariableTable:
        Start  Length  Slot  Name   Signature
            0      14     0  this   Lscala/collection/convert/impl/IteratorStepperBase;

  public long estimateSize();
    descriptor: ()J
    flags: (0x0001) ACC_PUBLIC
    Code:
      stack=2, locals=1, args_size=1
         0: aload_0
         1: invokevirtual #41                 // Method proxied:()Lscala/collection/Stepper;
         4: ifnull        17
         7: aload_0
         8: invokevirtual #41                 // Method proxied:()Lscala/collection/Stepper;
        11: invokeinterface #47,  1           // InterfaceMethod scala/collection/Stepper.estimateSize:()J
        16: lreturn
        17: ldc2_w        #48                 // long 9223372036854775807l
        20: lreturn
      StackMapTable: number_of_entries = 1
        frame_type = 17 /* same */
      LineNumberTable:
        line 127: 0
      LocalVariableTable:
        Start  Length  Slot  Name   Signature
            0      21     0  this   Lscala/collection/convert/impl/IteratorStepperBase;

  public boolean hasStep();
    descriptor: ()Z
    flags: (0x0001) ACC_PUBLIC
    Code:
      stack=1, locals=1, args_size=1
         0: aload_0
         1: invokevirtual #41                 // Method proxied:()Lscala/collection/Stepper;
         4: ifnull        17
         7: aload_0
         8: invokevirtual #41                 // Method proxied:()Lscala/collection/Stepper;
        11: invokeinterface #53,  1           // InterfaceMethod scala/collection/Stepper.hasStep:()Z
        16: ireturn
        17: aload_0
        18: invokevirtual #55                 // Method underlying:()Lscala/collection/Iterator;
        21: invokeinterface #60,  1           // InterfaceMethod scala/collection/Iterator.hasNext:()Z
        26: ireturn
      StackMapTable: number_of_entries = 1
        frame_type = 17 /* same */
      LineNumberTable:
        line 128: 0
      LocalVariableTable:
        Start  Length  Slot  Name   Signature
            0      27     0  this   Lscala/collection/convert/impl/IteratorStepperBase;

  public scala.collection.convert.impl.IteratorStepperBase(scala.collection.Iterator<A>);
    descriptor: (Lscala/collection/Iterator;)V
    flags: (0x0001) ACC_PUBLIC
    Code:
      stack=2, locals=2, args_size=2
         0: aload_0
         1: aload_1
         2: putfield      #21                 // Field underlying:Lscala/collection/Iterator;
         5: aload_0
         6: invokespecial #66                 // Method java/lang/Object."<init>":()V
         9: aload_0
        10: bipush        16
        12: putfield      #26                 // Field nextChunkSize:I
        15: aload_0
        16: aconst_null
        17: putfield      #33                 // Field proxied:Lscala/collection/Stepper;
        20: return
      LineNumberTable:
        line 122: 0
        line 123: 9
        line 124: 15
        line 122: 20
      LocalVariableTable:
        Start  Length  Slot  Name   Signature
            0      21     0  this   Lscala/collection/convert/impl/IteratorStepperBase;
            0      21     1 underlying   Lscala/collection/Iterator;
    Signature: #63                          // (Lscala/collection/Iterator<TA;>;)V
    MethodParameters:
      Name                           Flags
      underlying                     final
}
Signature: #3                           // <A:Ljava/lang/Object;SP::Lscala/collection/Stepper<TA;>;Semi:TSP;>Ljava/lang/Object;
SourceFile: "IteratorStepper.scala"
RuntimeVisibleAnnotations:
  0: #7(#8=s#9)
    scala.reflect.ScalaSignature(
      bytes="\u0006\u000514aAD\b\u0002\u0002E9\u0002\u0002C\u000f\u0001\u0005\u000b\u0007IQC\u0010\t\u0011]\u0002!\u0011!Q\u0001\u000e\u0001BQ\u0001\u000f\u0001\u0005\u0002eBq\u0001\u0014\u0001A\u0002\u0013UQ\nC\u0004R\u0001\u0001\u0007IQ\u0003*\t\ra\u0003\u0001\u0015)\u0004O\u0011\u001dI\u0006\u00011A\u0005\u0016iCqa\u0017\u0001A\u0002\u0013UA\f\u0003\u0004_\u0001\u0001\u0006k\u0001\u0010\u0005\u0006?\u00021\t\u0002\u0019\u0005\u0006C\u0002!\t!\u0014\u0005\u0006E\u0002!\ta\u0019\u0005\u0006O\u0002!\t\u0001\u001b\u0002\u0014\u0013R,\'/\u0019;peN#X\r\u001d9fe\n\u000b7/\u001a\u0006\u0003!E\tA![7qY*\u0011!cE\u0001\bG>tg/\u001a:u\u0015\t!R#\u0001\u0006d_2dWm\u0019;j_:T\u0011AF\u0001\u0006g\u000e\fG.Y\u000b\u000519j\u0004j\u0005\u0002\u00013A\u0011!dG\u0007\u0002+%\u0011A$\u0006\u0002\u0007\u0003:L(+\u001a4\u0002\u0015UtG-\u001a:ms&twm\u0001\u0001\u0016\u0003\u0001\u00022!I\u0015-\u001d\t\u0011sE\u0004\u0002$M5\tAE\u0003\u0002&=\u00051AH]8pizJ\u0011AF\u0005\u0003QU\tq\u0001]1dW\u0006<W-\u0003\u0002+W\tA\u0011\n^3sCR|\'O\u0003\u0002)+A\u0011QF\f\u0007\u0001\t\u0015y\u0003A1\u00011\u0005\u0005\t\u0015CA\u00195!\tQ\"\'\u0003\u00024+\t9aj\u001c;iS:<\u0007C\u0001\u000e6\u0013\t1TCA\u0002B]f\f1\"\u001e8eKJd\u00170\u001b8hA\u00051A(\u001b8jiz\"\"AO&\u0011\u000bm\u0002A\u0006P$\u000e\u0003=\u0001\"!L\u001f\u0005\u000by\u0002!\u0019A \u0003\u0005M\u0003\u0016C\u0001!D!\tQ\u0012)\u0003\u0002C+\t!a*\u001e7m!\r!U\tL\u0007\u0002\'%\u0011ai\u0005\u0002\b\'R,\u0007\u000f]3s!\ti\u0003\nB\u0003J\u0001\t\u0007!J\u0001\u0003TK6L\u0017CA\u0019=\u0011\u0015i2\u00011\u0001!\u00035qW\r\u001f;DQVt7nU5{KV\ta\n\u0005\u0002\u001b\u001f&\u0011\u0001+\u0006\u0002\u0004\u0013:$\u0018!\u00058fqR\u001c\u0005.\u001e8l\'&TXm\u0018\u0013fcR\u00111K\u0016\t\u00035QK!!V\u000b\u0003\tUs\u0017\u000e\u001e\u0005\b/\u0016\t\t\u00111\u0001O\u0003\rAH%M\u0001\u000f]\u0016DHo\u00115v].\u001c\u0016N_3!\u0003\u001d\u0001(o\u001c=jK\u0012,\u0012\u0001P\u0001\faJ|\u00070[3e?\u0012*\u0017\u000f\u0006\u0002T;\"9q\u000bCA\u0001\u0002\u0004a\u0014\u0001\u00039s_bLW\r\u001a\u0011\u0002\u0013M,W.[2m_:,G#A$\u0002\u001f\rD\u0017M]1di\u0016\u0014\u0018n\u001d;jGN\fA\"Z:uS6\fG/Z*ju\u0016,\u0012\u0001\u001a\t\u00035\u0015L!AZ\u000b\u0003\t1{gnZ\u0001\bQ\u0006\u001c8\u000b^3q+\u0005I\u0007C\u0001\u000ek\u0013\tYWCA\u0004C_>dW-\u00198"
    )
  ScalaInlineInfo: length = 0x36 (unknown attribute)
   01 00 00 0A 00 3D 00 3E 00 00 27 00 18 00 00 2A
   00 2B 00 00 32 00 33 00 00 0D 00 18 01 00 1B 00
   1C 01 00 0F 00 1E 01 00 22 00 23 01 00 25 00 1E
   00 00 0A 00 12 01
  ScalaSig: length = 0x3 (unknown attribute)
   05 02 00
