Classfile /Users/mw/Projects/slang-braindump/.jar/jar11/assemble/slang-braindump/assemble/content/scala/collection/convert/impl/LongIndexedSeqStepper.class
  Last modified May 29, 2022; size 6187 bytes
  SHA-256 checksum 05f1c99b15ead91e2bba153190ee4ce4aeda9f15b5cf7980b5cbef81d4115fb9
  Compiled from "IndexedSeqStepper.scala"
public class scala.collection.convert.impl.LongIndexedSeqStepper<CC extends scala.collection.IndexedSeqOps<java.lang.Object, java.lang.Object, ?>> extends scala.collection.convert.impl.IndexedStepperBase<scala.collection.LongStepper, scala.collection.convert.impl.LongIndexedSeqStepper<CC>> implements scala.collection.LongStepper
  minor version: 0
  major version: 52
  flags: (0x0021) ACC_PUBLIC, ACC_SUPER
  this_class: #2                          // scala/collection/convert/impl/LongIndexedSeqStepper
  super_class: #5                         // scala/collection/convert/impl/IndexedStepperBase
  interfaces: 1, fields: 1, methods: 24, attributes: 6
Constant pool:
    #1 = Utf8               scala/collection/convert/impl/LongIndexedSeqStepper
    #2 = Class              #1            // scala/collection/convert/impl/LongIndexedSeqStepper
    #3 = Utf8               <CC::Lscala/collection/IndexedSeqOps<Ljava/lang/Object;Ljava/lang/Object;*>;>Lscala/collection/convert/impl/IndexedStepperBase<Lscala/collection/LongStepper;Lscala/collection/convert/impl/LongIndexedSeqStepper<TCC;>;>;Lscala/collection/LongStepper;
    #4 = Utf8               scala/collection/convert/impl/IndexedStepperBase
    #5 = Class              #4            // scala/collection/convert/impl/IndexedStepperBase
    #6 = Utf8               scala/collection/LongStepper
    #7 = Class              #6            // scala/collection/LongStepper
    #8 = Utf8               IndexedSeqStepper.scala
    #9 = Utf8               Lscala/reflect/ScalaSignature;
   #10 = Utf8               bytes
   #11 = Utf8               \u0006\u0005I3Qa\u0002\u0005\u0001\u0019AA\u0001\"\u0011\u0001\u0003\u0002\u0003\u0006Ia\u0007\u0005\t\u0005\u0002\u0011\t\u0011)A\u0005\u0007\"Aa\t\u0001B\u0001B\u0003%1\tC\u0003H\u0001\u0011\u0005\u0001\nC\u0003M\u0001\u0011\u0005Q\nC\u0003O\u0001\u0011EqJA\u000bM_:<\u0017J\u001c3fq\u0016$7+Z9Ti\u0016\u0004\b/\u001a:\u000b\u0005%Q\u0011\u0001B5na2T!a\u0003\u0007\u0002\u000f\r|gN^3si*\u0011QBD\u0001\u000bG>dG.Z2uS>t\'\"A\b\u0002\u000bM\u001c\u0017\r\\1\u0016\u0005Ei2c\u0001\u0001\u0013-A!1\u0003\u0006\f\u001b\u001b\u0005A\u0011BA\u000b\t\u0005IIe\u000eZ3yK\u0012\u001cF/\u001a9qKJ\u0014\u0015m]3\u0011\u0005]AR\"\u0001\u0007\n\u0005ea!a\u0003\'p]\u001e\u001cF/\u001a9qKJ\u00042a\u0005\u0001\u001c!\taR\u0004\u0004\u0001\u0005\u000by\u0001!\u0019\u0001\u0011\u0003\u0005\r\u001b5\u0001A\t\u0003C\u0015\u0002\"AI\u0012\u000e\u00039I!\u0001\n\b\u0003\u000f9{G\u000f[5oOB\u0012ae\u000f\t\u0006/\u001dJCFO\u0005\u0003Q1\u0011Q\"\u00138eKb,GmU3r\u001fB\u001c\bC\u0001\u0012+\u0013\tYcB\u0001\u0003M_:<\u0007CA\u00178\u001d\tqSG\u0004\u00020i9\u0011\u0001gM\u0007\u0002c)\u0011!gH\u0001\u0007yI|w\u000e\u001e \n\u0003=I!!\u0004\b\n\u0005Yb\u0011a\u00029bG.\fw-Z\u0005\u0003qe\u0012\u0011\"\u00118z\u0007>t7\u000f\u001e:\u000b\u0005Yb\u0001C\u0001\u000f<\t%aT$!A\u0001\u0002\u000b\u0005QHA\u0002`IQ\n\"!\t \u0011\u0005\tz\u0014B\u0001!\u000f\u0005\r\te._\u0001\u000bk:$WM\u001d7zS:<\u0017aA0jaA\u0011!\u0005R\u0005\u0003\u000b:\u00111!\u00138u\u0003\ry\u0016NT\u0001\u0007y%t\u0017\u000e\u001e \u0015\tiI%j\u0013\u0005\u0006\u0003\u0012\u0001\ra\u0007\u0005\u0006\u0005\u0012\u0001\ra\u0011\u0005\u0006\r\u0012\u0001\raQ\u0001\t]\u0016DHo\u0015;faR\t\u0011&A\u0005tK6L7\r\\8oKR\u0011!\u0004\u0015\u0005\u0006#\u001a\u0001\raQ\u0001\u0005Q\u0006dg\r
   #12 = Utf8               java/util/PrimitiveIterator$OfLong
   #13 = Class              #12           // java/util/PrimitiveIterator$OfLong
   #14 = Utf8               java/util/PrimitiveIterator
   #15 = Class              #14           // java/util/PrimitiveIterator
   #16 = Utf8               OfLong
   #17 = Utf8               java/util/Spliterator$OfLong
   #18 = Class              #17           // java/util/Spliterator$OfLong
   #19 = Utf8               java/util/Spliterator
   #20 = Class              #19           // java/util/Spliterator
   #21 = Utf8               scala$collection$convert$impl$LongIndexedSeqStepper$$underlying
   #22 = Utf8               Lscala/collection/IndexedSeqOps;
   #23 = Utf8               TCC;
   #24 = Utf8               spliterator
   #25 = Utf8               ()Ljava/util/Spliterator$OfLong;
   #26 = Utf8               <B:Ljava/lang/Object;>()Ljava/util/Spliterator$OfLong;
   #27 = Utf8               spliterator$
   #28 = Utf8               (Lscala/collection/LongStepper;)Ljava/util/Spliterator$OfLong;
   #29 = NameAndType        #27:#28       // spliterator$:(Lscala/collection/LongStepper;)Ljava/util/Spliterator$OfLong;
   #30 = InterfaceMethodref #7.#29        // scala/collection/LongStepper.spliterator$:(Lscala/collection/LongStepper;)Ljava/util/Spliterator$OfLong;
   #31 = Utf8               this
   #32 = Utf8               Lscala/collection/convert/impl/LongIndexedSeqStepper;
   #33 = Utf8               javaIterator
   #34 = Utf8               ()Ljava/util/PrimitiveIterator$OfLong;
   #35 = Utf8               <B:Ljava/lang/Object;>()Ljava/util/PrimitiveIterator$OfLong;
   #36 = Utf8               javaIterator$
   #37 = Utf8               (Lscala/collection/LongStepper;)Ljava/util/PrimitiveIterator$OfLong;
   #38 = NameAndType        #36:#37       // javaIterator$:(Lscala/collection/LongStepper;)Ljava/util/PrimitiveIterator$OfLong;
   #39 = InterfaceMethodref #7.#38        // scala/collection/LongStepper.javaIterator$:(Lscala/collection/LongStepper;)Ljava/util/PrimitiveIterator$OfLong;
   #40 = Utf8               spliterator$mcJ$sp
   #41 = Utf8               ()Ljava/util/Spliterator;
   #42 = Utf8               <B:Ljava/lang/Object;>()Ljava/util/Spliterator<*>;
   #43 = Utf8               spliterator$mcJ$sp$
   #44 = Utf8               (Lscala/collection/LongStepper;)Ljava/util/Spliterator;
   #45 = NameAndType        #43:#44       // spliterator$mcJ$sp$:(Lscala/collection/LongStepper;)Ljava/util/Spliterator;
   #46 = InterfaceMethodref #7.#45        // scala/collection/LongStepper.spliterator$mcJ$sp$:(Lscala/collection/LongStepper;)Ljava/util/Spliterator;
   #47 = Utf8               javaIterator$mcJ$sp
   #48 = Utf8               ()Ljava/util/Iterator;
   #49 = Utf8               <B:Ljava/lang/Object;>()Ljava/util/Iterator<*>;
   #50 = Utf8               javaIterator$mcJ$sp$
   #51 = Utf8               (Lscala/collection/LongStepper;)Ljava/util/Iterator;
   #52 = NameAndType        #50:#51       // javaIterator$mcJ$sp$:(Lscala/collection/LongStepper;)Ljava/util/Iterator;
   #53 = InterfaceMethodref #7.#52        // scala/collection/LongStepper.javaIterator$mcJ$sp$:(Lscala/collection/LongStepper;)Ljava/util/Iterator;
   #54 = Utf8               nextStep$mcD$sp
   #55 = Utf8               ()D
   #56 = Utf8               scala/collection/Stepper
   #57 = Class              #56           // scala/collection/Stepper
   #58 = Utf8               nextStep$mcD$sp$
   #59 = Utf8               (Lscala/collection/Stepper;)D
   #60 = NameAndType        #58:#59       // nextStep$mcD$sp$:(Lscala/collection/Stepper;)D
   #61 = InterfaceMethodref #57.#60       // scala/collection/Stepper.nextStep$mcD$sp$:(Lscala/collection/Stepper;)D
   #62 = Utf8               nextStep$mcI$sp
   #63 = Utf8               ()I
   #64 = Utf8               nextStep$mcI$sp$
   #65 = Utf8               (Lscala/collection/Stepper;)I
   #66 = NameAndType        #64:#65       // nextStep$mcI$sp$:(Lscala/collection/Stepper;)I
   #67 = InterfaceMethodref #57.#66       // scala/collection/Stepper.nextStep$mcI$sp$:(Lscala/collection/Stepper;)I
   #68 = Utf8               trySplit$mcD$sp
   #69 = Utf8               ()Lscala/collection/Stepper;
   #70 = Utf8               ()Lscala/collection/Stepper<Ljava/lang/Object;>;
   #71 = Utf8               trySplit$mcD$sp$
   #72 = Utf8               (Lscala/collection/Stepper;)Lscala/collection/Stepper;
   #73 = NameAndType        #71:#72       // trySplit$mcD$sp$:(Lscala/collection/Stepper;)Lscala/collection/Stepper;
   #74 = InterfaceMethodref #57.#73       // scala/collection/Stepper.trySplit$mcD$sp$:(Lscala/collection/Stepper;)Lscala/collection/Stepper;
   #75 = Utf8               trySplit$mcI$sp
   #76 = Utf8               trySplit$mcI$sp$
   #77 = NameAndType        #76:#72       // trySplit$mcI$sp$:(Lscala/collection/Stepper;)Lscala/collection/Stepper;
   #78 = InterfaceMethodref #57.#77       // scala/collection/Stepper.trySplit$mcI$sp$:(Lscala/collection/Stepper;)Lscala/collection/Stepper;
   #79 = Utf8               trySplit$mcJ$sp
   #80 = Utf8               trySplit$mcJ$sp$
   #81 = NameAndType        #80:#72       // trySplit$mcJ$sp$:(Lscala/collection/Stepper;)Lscala/collection/Stepper;
   #82 = InterfaceMethodref #57.#81       // scala/collection/Stepper.trySplit$mcJ$sp$:(Lscala/collection/Stepper;)Lscala/collection/Stepper;
   #83 = Utf8               spliterator$mcD$sp
   #84 = Utf8               spliterator$mcD$sp$
   #85 = Utf8               (Lscala/collection/Stepper;)Ljava/util/Spliterator;
   #86 = NameAndType        #84:#85       // spliterator$mcD$sp$:(Lscala/collection/Stepper;)Ljava/util/Spliterator;
   #87 = InterfaceMethodref #57.#86       // scala/collection/Stepper.spliterator$mcD$sp$:(Lscala/collection/Stepper;)Ljava/util/Spliterator;
   #88 = Utf8               spliterator$mcI$sp
   #89 = Utf8               spliterator$mcI$sp$
   #90 = NameAndType        #89:#85       // spliterator$mcI$sp$:(Lscala/collection/Stepper;)Ljava/util/Spliterator;
   #91 = InterfaceMethodref #57.#90       // scala/collection/Stepper.spliterator$mcI$sp$:(Lscala/collection/Stepper;)Ljava/util/Spliterator;
   #92 = Utf8               javaIterator$mcD$sp
   #93 = Utf8               javaIterator$mcD$sp$
   #94 = Utf8               (Lscala/collection/Stepper;)Ljava/util/Iterator;
   #95 = NameAndType        #93:#94       // javaIterator$mcD$sp$:(Lscala/collection/Stepper;)Ljava/util/Iterator;
   #96 = InterfaceMethodref #57.#95       // scala/collection/Stepper.javaIterator$mcD$sp$:(Lscala/collection/Stepper;)Ljava/util/Iterator;
   #97 = Utf8               javaIterator$mcI$sp
   #98 = Utf8               javaIterator$mcI$sp$
   #99 = NameAndType        #98:#94       // javaIterator$mcI$sp$:(Lscala/collection/Stepper;)Ljava/util/Iterator;
  #100 = InterfaceMethodref #57.#99       // scala/collection/Stepper.javaIterator$mcI$sp$:(Lscala/collection/Stepper;)Ljava/util/Iterator;
  #101 = Utf8               iterator
  #102 = Utf8               ()Lscala/collection/Iterator;
  #103 = Utf8               ()Lscala/collection/Iterator<Ljava/lang/Object;>;
  #104 = Utf8               iterator$
  #105 = Utf8               (Lscala/collection/Stepper;)Lscala/collection/Iterator;
  #106 = NameAndType        #104:#105     // iterator$:(Lscala/collection/Stepper;)Lscala/collection/Iterator;
  #107 = InterfaceMethodref #57.#106      // scala/collection/Stepper.iterator$:(Lscala/collection/Stepper;)Lscala/collection/Iterator;
  #108 = Utf8               nextStep
  #109 = Utf8               ()J
  #110 = Utf8               nextStep$mcJ$sp
  #111 = NameAndType        #110:#109     // nextStep$mcJ$sp:()J
  #112 = Methodref          #2.#111       // scala/collection/convert/impl/LongIndexedSeqStepper.nextStep$mcJ$sp:()J
  #113 = Utf8               semiclone
  #114 = Utf8               (I)Lscala/collection/convert/impl/LongIndexedSeqStepper;
  #115 = Utf8               (I)Lscala/collection/convert/impl/LongIndexedSeqStepper<TCC;>;
  #116 = Utf8               half
  #117 = NameAndType        #21:#22       // scala$collection$convert$impl$LongIndexedSeqStepper$$underlying:Lscala/collection/IndexedSeqOps;
  #118 = Fieldref           #2.#117       // scala/collection/convert/impl/LongIndexedSeqStepper.scala$collection$convert$impl$LongIndexedSeqStepper$$underlying:Lscala/collection/IndexedSeqOps;
  #119 = Utf8               i0
  #120 = NameAndType        #119:#63      // i0:()I
  #121 = Methodref          #2.#120       // scala/collection/convert/impl/LongIndexedSeqStepper.i0:()I
  #122 = Utf8               <init>
  #123 = Utf8               (Lscala/collection/IndexedSeqOps;II)V
  #124 = NameAndType        #122:#123     // "<init>":(Lscala/collection/IndexedSeqOps;II)V
  #125 = Methodref          #2.#124       // scala/collection/convert/impl/LongIndexedSeqStepper."<init>":(Lscala/collection/IndexedSeqOps;II)V
  #126 = Utf8               I
  #127 = Utf8               hasStep
  #128 = Utf8               ()Z
  #129 = NameAndType        #127:#128     // hasStep:()Z
  #130 = Methodref          #2.#129       // scala/collection/convert/impl/LongIndexedSeqStepper.hasStep:()Z
  #131 = Utf8               i0_$eq
  #132 = Utf8               (I)V
  #133 = NameAndType        #131:#132     // i0_$eq:(I)V
  #134 = Methodref          #2.#133       // scala/collection/convert/impl/LongIndexedSeqStepper.i0_$eq:(I)V
  #135 = Utf8               scala/collection/IndexedSeqOps
  #136 = Class              #135          // scala/collection/IndexedSeqOps
  #137 = Utf8               apply
  #138 = Utf8               (I)Ljava/lang/Object;
  #139 = NameAndType        #137:#138     // apply:(I)Ljava/lang/Object;
  #140 = InterfaceMethodref #136.#139     // scala/collection/IndexedSeqOps.apply:(I)Ljava/lang/Object;
  #141 = Utf8               scala/runtime/BoxesRunTime
  #142 = Class              #141          // scala/runtime/BoxesRunTime
  #143 = Utf8               unboxToLong
  #144 = Utf8               (Ljava/lang/Object;)J
  #145 = NameAndType        #143:#144     // unboxToLong:(Ljava/lang/Object;)J
  #146 = Methodref          #142.#145     // scala/runtime/BoxesRunTime.unboxToLong:(Ljava/lang/Object;)J
  #147 = Utf8               scala/collection/Stepper$
  #148 = Class              #147          // scala/collection/Stepper$
  #149 = Utf8               MODULE$
  #150 = Utf8               Lscala/collection/Stepper$;
  #151 = NameAndType        #149:#150     // MODULE$:Lscala/collection/Stepper$;
  #152 = Fieldref           #148.#151     // scala/collection/Stepper$.MODULE$:Lscala/collection/Stepper$;
  #153 = Utf8               java/util/NoSuchElementException
  #154 = Class              #153          // java/util/NoSuchElementException
  #155 = Utf8               Empty Stepper
  #156 = String             #155          // Empty Stepper
  #157 = Utf8               (Ljava/lang/String;)V
  #158 = NameAndType        #122:#157     // "<init>":(Ljava/lang/String;)V
  #159 = Methodref          #154.#158     // java/util/NoSuchElementException."<init>":(Ljava/lang/String;)V
  #160 = Utf8               j
  #161 = Utf8               trySplit
  #162 = Utf8               ()Ljava/lang/Object;
  #163 = NameAndType        #161:#162     // trySplit:()Ljava/lang/Object;
  #164 = Methodref          #2.#163       // scala/collection/convert/impl/LongIndexedSeqStepper.trySplit:()Ljava/lang/Object;
  #165 = Utf8               ()Lscala/collection/LongStepper;
  #166 = NameAndType        #33:#34       // javaIterator:()Ljava/util/PrimitiveIterator$OfLong;
  #167 = Methodref          #2.#166       // scala/collection/convert/impl/LongIndexedSeqStepper.javaIterator:()Ljava/util/PrimitiveIterator$OfLong;
  #168 = NameAndType        #24:#25       // spliterator:()Ljava/util/Spliterator$OfLong;
  #169 = Methodref          #2.#168       // scala/collection/convert/impl/LongIndexedSeqStepper.spliterator:()Ljava/util/Spliterator$OfLong;
  #170 = NameAndType        #113:#114     // semiclone:(I)Lscala/collection/convert/impl/LongIndexedSeqStepper;
  #171 = Methodref          #2.#170       // scala/collection/convert/impl/LongIndexedSeqStepper.semiclone:(I)Lscala/collection/convert/impl/LongIndexedSeqStepper;
  #172 = NameAndType        #108:#109     // nextStep:()J
  #173 = Methodref          #2.#172       // scala/collection/convert/impl/LongIndexedSeqStepper.nextStep:()J
  #174 = Utf8               boxToLong
  #175 = Utf8               (J)Ljava/lang/Long;
  #176 = NameAndType        #174:#175     // boxToLong:(J)Ljava/lang/Long;
  #177 = Methodref          #142.#176     // scala/runtime/BoxesRunTime.boxToLong:(J)Ljava/lang/Long;
  #178 = Utf8               (TCC;II)V
  #179 = Utf8               underlying
  #180 = Utf8               _i0
  #181 = Utf8               _iN
  #182 = Utf8               (II)V
  #183 = NameAndType        #122:#182     // "<init>":(II)V
  #184 = Methodref          #5.#183       // scala/collection/convert/impl/IndexedStepperBase."<init>":(II)V
  #185 = Utf8               Signature
  #186 = Utf8               Code
  #187 = Utf8               LineNumberTable
  #188 = Utf8               LocalVariableTable
  #189 = Utf8               MethodParameters
  #190 = Utf8               StackMapTable
  #191 = Utf8               InnerClasses
  #192 = Utf8               SourceFile
  #193 = Utf8               RuntimeVisibleAnnotations
  #194 = Utf8               ScalaInlineInfo
  #195 = Utf8               ScalaSig
{
  public final CC scala$collection$convert$impl$LongIndexedSeqStepper$$underlying;
    descriptor: Lscala/collection/IndexedSeqOps;
    flags: (0x0011) ACC_PUBLIC, ACC_FINAL
    Signature: #23                          // TCC;

  public <B extends java.lang.Object> java.util.Spliterator$OfLong spliterator();
    descriptor: ()Ljava/util/Spliterator$OfLong;
    flags: (0x0001) ACC_PUBLIC
    Code:
      stack=1, locals=1, args_size=1
         0: aload_0
         1: invokestatic  #30                 // InterfaceMethod scala/collection/LongStepper.spliterator$:(Lscala/collection/LongStepper;)Ljava/util/Spliterator$OfLong;
         4: areturn
      LineNumberTable:
        line 39: 0
      LocalVariableTable:
        Start  Length  Slot  Name   Signature
            0       5     0  this   Lscala/collection/convert/impl/LongIndexedSeqStepper;
    Signature: #26                          // <B:Ljava/lang/Object;>()Ljava/util/Spliterator$OfLong;

  public <B extends java.lang.Object> java.util.PrimitiveIterator$OfLong javaIterator();
    descriptor: ()Ljava/util/PrimitiveIterator$OfLong;
    flags: (0x0001) ACC_PUBLIC
    Code:
      stack=1, locals=1, args_size=1
         0: aload_0
         1: invokestatic  #39                 // InterfaceMethod scala/collection/LongStepper.javaIterator$:(Lscala/collection/LongStepper;)Ljava/util/PrimitiveIterator$OfLong;
         4: areturn
      LineNumberTable:
        line 39: 0
      LocalVariableTable:
        Start  Length  Slot  Name   Signature
            0       5     0  this   Lscala/collection/convert/impl/LongIndexedSeqStepper;
    Signature: #35                          // <B:Ljava/lang/Object;>()Ljava/util/PrimitiveIterator$OfLong;

  public <B extends java.lang.Object> java.util.Spliterator<?> spliterator$mcJ$sp();
    descriptor: ()Ljava/util/Spliterator;
    flags: (0x0001) ACC_PUBLIC
    Code:
      stack=1, locals=1, args_size=1
         0: aload_0
         1: invokestatic  #46                 // InterfaceMethod scala/collection/LongStepper.spliterator$mcJ$sp$:(Lscala/collection/LongStepper;)Ljava/util/Spliterator;
         4: areturn
      LineNumberTable:
        line 39: 0
      LocalVariableTable:
        Start  Length  Slot  Name   Signature
            0       5     0  this   Lscala/collection/convert/impl/LongIndexedSeqStepper;
    Signature: #42                          // <B:Ljava/lang/Object;>()Ljava/util/Spliterator<*>;

  public <B extends java.lang.Object> java.util.Iterator<?> javaIterator$mcJ$sp();
    descriptor: ()Ljava/util/Iterator;
    flags: (0x0001) ACC_PUBLIC
    Code:
      stack=1, locals=1, args_size=1
         0: aload_0
         1: invokestatic  #53                 // InterfaceMethod scala/collection/LongStepper.javaIterator$mcJ$sp$:(Lscala/collection/LongStepper;)Ljava/util/Iterator;
         4: areturn
      LineNumberTable:
        line 39: 0
      LocalVariableTable:
        Start  Length  Slot  Name   Signature
            0       5     0  this   Lscala/collection/convert/impl/LongIndexedSeqStepper;
    Signature: #49                          // <B:Ljava/lang/Object;>()Ljava/util/Iterator<*>;

  public double nextStep$mcD$sp();
    descriptor: ()D
    flags: (0x0001) ACC_PUBLIC
    Code:
      stack=2, locals=1, args_size=1
         0: aload_0
         1: invokestatic  #61                 // InterfaceMethod scala/collection/Stepper.nextStep$mcD$sp$:(Lscala/collection/Stepper;)D
         4: dreturn
      LineNumberTable:
        line 39: 0
      LocalVariableTable:
        Start  Length  Slot  Name   Signature
            0       5     0  this   Lscala/collection/convert/impl/LongIndexedSeqStepper;

  public int nextStep$mcI$sp();
    descriptor: ()I
    flags: (0x0001) ACC_PUBLIC
    Code:
      stack=1, locals=1, args_size=1
         0: aload_0
         1: invokestatic  #67                 // InterfaceMethod scala/collection/Stepper.nextStep$mcI$sp$:(Lscala/collection/Stepper;)I
         4: ireturn
      LineNumberTable:
        line 39: 0
      LocalVariableTable:
        Start  Length  Slot  Name   Signature
            0       5     0  this   Lscala/collection/convert/impl/LongIndexedSeqStepper;

  public scala.collection.Stepper<java.lang.Object> trySplit$mcD$sp();
    descriptor: ()Lscala/collection/Stepper;
    flags: (0x0001) ACC_PUBLIC
    Code:
      stack=1, locals=1, args_size=1
         0: aload_0
         1: invokestatic  #74                 // InterfaceMethod scala/collection/Stepper.trySplit$mcD$sp$:(Lscala/collection/Stepper;)Lscala/collection/Stepper;
         4: areturn
      LineNumberTable:
        line 39: 0
      LocalVariableTable:
        Start  Length  Slot  Name   Signature
            0       5     0  this   Lscala/collection/convert/impl/LongIndexedSeqStepper;
    Signature: #70                          // ()Lscala/collection/Stepper<Ljava/lang/Object;>;

  public scala.collection.Stepper<java.lang.Object> trySplit$mcI$sp();
    descriptor: ()Lscala/collection/Stepper;
    flags: (0x0001) ACC_PUBLIC
    Code:
      stack=1, locals=1, args_size=1
         0: aload_0
         1: invokestatic  #78                 // InterfaceMethod scala/collection/Stepper.trySplit$mcI$sp$:(Lscala/collection/Stepper;)Lscala/collection/Stepper;
         4: areturn
      LineNumberTable:
        line 39: 0
      LocalVariableTable:
        Start  Length  Slot  Name   Signature
            0       5     0  this   Lscala/collection/convert/impl/LongIndexedSeqStepper;
    Signature: #70                          // ()Lscala/collection/Stepper<Ljava/lang/Object;>;

  public scala.collection.Stepper<java.lang.Object> trySplit$mcJ$sp();
    descriptor: ()Lscala/collection/Stepper;
    flags: (0x0001) ACC_PUBLIC
    Code:
      stack=1, locals=1, args_size=1
         0: aload_0
         1: invokestatic  #82                 // InterfaceMethod scala/collection/Stepper.trySplit$mcJ$sp$:(Lscala/collection/Stepper;)Lscala/collection/Stepper;
         4: areturn
      LineNumberTable:
        line 39: 0
      LocalVariableTable:
        Start  Length  Slot  Name   Signature
            0       5     0  this   Lscala/collection/convert/impl/LongIndexedSeqStepper;
    Signature: #70                          // ()Lscala/collection/Stepper<Ljava/lang/Object;>;

  public <B extends java.lang.Object> java.util.Spliterator<?> spliterator$mcD$sp();
    descriptor: ()Ljava/util/Spliterator;
    flags: (0x0001) ACC_PUBLIC
    Code:
      stack=1, locals=1, args_size=1
         0: aload_0
         1: invokestatic  #87                 // InterfaceMethod scala/collection/Stepper.spliterator$mcD$sp$:(Lscala/collection/Stepper;)Ljava/util/Spliterator;
         4: areturn
      LineNumberTable:
        line 39: 0
      LocalVariableTable:
        Start  Length  Slot  Name   Signature
            0       5     0  this   Lscala/collection/convert/impl/LongIndexedSeqStepper;
    Signature: #42                          // <B:Ljava/lang/Object;>()Ljava/util/Spliterator<*>;

  public <B extends java.lang.Object> java.util.Spliterator<?> spliterator$mcI$sp();
    descriptor: ()Ljava/util/Spliterator;
    flags: (0x0001) ACC_PUBLIC
    Code:
      stack=1, locals=1, args_size=1
         0: aload_0
         1: invokestatic  #91                 // InterfaceMethod scala/collection/Stepper.spliterator$mcI$sp$:(Lscala/collection/Stepper;)Ljava/util/Spliterator;
         4: areturn
      LineNumberTable:
        line 39: 0
      LocalVariableTable:
        Start  Length  Slot  Name   Signature
            0       5     0  this   Lscala/collection/convert/impl/LongIndexedSeqStepper;
    Signature: #42                          // <B:Ljava/lang/Object;>()Ljava/util/Spliterator<*>;

  public <B extends java.lang.Object> java.util.Iterator<?> javaIterator$mcD$sp();
    descriptor: ()Ljava/util/Iterator;
    flags: (0x0001) ACC_PUBLIC
    Code:
      stack=1, locals=1, args_size=1
         0: aload_0
         1: invokestatic  #96                 // InterfaceMethod scala/collection/Stepper.javaIterator$mcD$sp$:(Lscala/collection/Stepper;)Ljava/util/Iterator;
         4: areturn
      LineNumberTable:
        line 39: 0
      LocalVariableTable:
        Start  Length  Slot  Name   Signature
            0       5     0  this   Lscala/collection/convert/impl/LongIndexedSeqStepper;
    Signature: #49                          // <B:Ljava/lang/Object;>()Ljava/util/Iterator<*>;

  public <B extends java.lang.Object> java.util.Iterator<?> javaIterator$mcI$sp();
    descriptor: ()Ljava/util/Iterator;
    flags: (0x0001) ACC_PUBLIC
    Code:
      stack=1, locals=1, args_size=1
         0: aload_0
         1: invokestatic  #100                // InterfaceMethod scala/collection/Stepper.javaIterator$mcI$sp$:(Lscala/collection/Stepper;)Ljava/util/Iterator;
         4: areturn
      LineNumberTable:
        line 39: 0
      LocalVariableTable:
        Start  Length  Slot  Name   Signature
            0       5     0  this   Lscala/collection/convert/impl/LongIndexedSeqStepper;
    Signature: #49                          // <B:Ljava/lang/Object;>()Ljava/util/Iterator<*>;

  public scala.collection.Iterator<java.lang.Object> iterator();
    descriptor: ()Lscala/collection/Iterator;
    flags: (0x0001) ACC_PUBLIC
    Code:
      stack=1, locals=1, args_size=1
         0: aload_0
         1: invokestatic  #107                // InterfaceMethod scala/collection/Stepper.iterator$:(Lscala/collection/Stepper;)Lscala/collection/Iterator;
         4: areturn
      LineNumberTable:
        line 39: 0
      LocalVariableTable:
        Start  Length  Slot  Name   Signature
            0       5     0  this   Lscala/collection/convert/impl/LongIndexedSeqStepper;
    Signature: #103                         // ()Lscala/collection/Iterator<Ljava/lang/Object;>;

  public long nextStep();
    descriptor: ()J
    flags: (0x0001) ACC_PUBLIC
    Code:
      stack=2, locals=1, args_size=1
         0: aload_0
         1: invokevirtual #112                // Method nextStep$mcJ$sp:()J
         4: lreturn
      LineNumberTable:
        line 42: 0
      LocalVariableTable:
        Start  Length  Slot  Name   Signature
            0       5     0  this   Lscala/collection/convert/impl/LongIndexedSeqStepper;

  public scala.collection.convert.impl.LongIndexedSeqStepper<CC> semiclone(int);
    descriptor: (I)Lscala/collection/convert/impl/LongIndexedSeqStepper;
    flags: (0x0001) ACC_PUBLIC
    Code:
      stack=5, locals=2, args_size=2
         0: new           #2                  // class scala/collection/convert/impl/LongIndexedSeqStepper
         3: dup
         4: aload_0
         5: getfield      #118                // Field scala$collection$convert$impl$LongIndexedSeqStepper$$underlying:Lscala/collection/IndexedSeqOps;
         8: aload_0
         9: invokevirtual #121                // Method i0:()I
        12: iload_1
        13: invokespecial #125                // Method "<init>":(Lscala/collection/IndexedSeqOps;II)V
        16: areturn
      LineNumberTable:
        line 43: 0
      LocalVariableTable:
        Start  Length  Slot  Name   Signature
            0      17     0  this   Lscala/collection/convert/impl/LongIndexedSeqStepper;
            0      17     1  half   I
    Signature: #115                         // (I)Lscala/collection/convert/impl/LongIndexedSeqStepper<TCC;>;
    MethodParameters:
      Name                           Flags
      half                           final

  public long nextStep$mcJ$sp();
    descriptor: ()J
    flags: (0x0001) ACC_PUBLIC
    Code:
      stack=3, locals=2, args_size=1
         0: aload_0
         1: invokevirtual #130                // Method hasStep:()Z
         4: ifeq          36
         7: aload_0
         8: invokevirtual #121                // Method i0:()I
        11: istore_1
        12: aload_0
        13: aload_0
        14: invokevirtual #121                // Method i0:()I
        17: iconst_1
        18: iadd
        19: invokevirtual #134                // Method i0_$eq:(I)V
        22: aload_0
        23: getfield      #118                // Field scala$collection$convert$impl$LongIndexedSeqStepper$$underlying:Lscala/collection/IndexedSeqOps;
        26: iload_1
        27: invokeinterface #140,  2          // InterfaceMethod scala/collection/IndexedSeqOps.apply:(I)Ljava/lang/Object;
        32: invokestatic  #146                // Method scala/runtime/BoxesRunTime.unboxToLong:(Ljava/lang/Object;)J
        35: lreturn
        36: getstatic     #152                // Field scala/collection/Stepper$.MODULE$:Lscala/collection/Stepper$;
        39: pop
        40: new           #154                // class java/util/NoSuchElementException
        43: dup
        44: ldc           #156                // String Empty Stepper
        46: invokespecial #159                // Method java/util/NoSuchElementException."<init>":(Ljava/lang/String;)V
        49: athrow
      StackMapTable: number_of_entries = 1
        frame_type = 36 /* same */
      LineNumberTable:
        line 42: 0
      LocalVariableTable:
        Start  Length  Slot  Name   Signature
           12      23     1     j   I
            0      50     0  this   Lscala/collection/convert/impl/LongIndexedSeqStepper;

  public scala.collection.Stepper trySplit();
    descriptor: ()Lscala/collection/Stepper;
    flags: (0x1041) ACC_PUBLIC, ACC_BRIDGE, ACC_SYNTHETIC
    Code:
      stack=1, locals=1, args_size=1
         0: aload_0
         1: invokevirtual #164                // Method trySplit:()Ljava/lang/Object;
         4: checkcast     #57                 // class scala/collection/Stepper
         7: areturn
      LineNumberTable:
        line 39: 0
      LocalVariableTable:
        Start  Length  Slot  Name   Signature
            0       8     0  this   Lscala/collection/convert/impl/LongIndexedSeqStepper;

  public scala.collection.LongStepper trySplit();
    descriptor: ()Lscala/collection/LongStepper;
    flags: (0x1041) ACC_PUBLIC, ACC_BRIDGE, ACC_SYNTHETIC
    Code:
      stack=1, locals=1, args_size=1
         0: aload_0
         1: invokevirtual #164                // Method trySplit:()Ljava/lang/Object;
         4: checkcast     #7                  // class scala/collection/LongStepper
         7: areturn
      LineNumberTable:
        line 39: 0
      LocalVariableTable:
        Start  Length  Slot  Name   Signature
            0       8     0  this   Lscala/collection/convert/impl/LongIndexedSeqStepper;

  public java.util.Iterator javaIterator();
    descriptor: ()Ljava/util/Iterator;
    flags: (0x1041) ACC_PUBLIC, ACC_BRIDGE, ACC_SYNTHETIC
    Code:
      stack=1, locals=1, args_size=1
         0: aload_0
         1: invokevirtual #167                // Method javaIterator:()Ljava/util/PrimitiveIterator$OfLong;
         4: areturn
      LineNumberTable:
        line 39: 0
      LocalVariableTable:
        Start  Length  Slot  Name   Signature
            0       5     0  this   Lscala/collection/convert/impl/LongIndexedSeqStepper;

  public java.util.Spliterator spliterator();
    descriptor: ()Ljava/util/Spliterator;
    flags: (0x1041) ACC_PUBLIC, ACC_BRIDGE, ACC_SYNTHETIC
    Code:
      stack=1, locals=1, args_size=1
         0: aload_0
         1: invokevirtual #169                // Method spliterator:()Ljava/util/Spliterator$OfLong;
         4: areturn
      LineNumberTable:
        line 39: 0
      LocalVariableTable:
        Start  Length  Slot  Name   Signature
            0       5     0  this   Lscala/collection/convert/impl/LongIndexedSeqStepper;

  public java.lang.Object semiclone(int);
    descriptor: (I)Ljava/lang/Object;
    flags: (0x1041) ACC_PUBLIC, ACC_BRIDGE, ACC_SYNTHETIC
    Code:
      stack=2, locals=2, args_size=2
         0: aload_0
         1: iload_1
         2: invokevirtual #171                // Method semiclone:(I)Lscala/collection/convert/impl/LongIndexedSeqStepper;
         5: areturn
      LineNumberTable:
        line 39: 0
      LocalVariableTable:
        Start  Length  Slot  Name   Signature
            0       6     0  this   Lscala/collection/convert/impl/LongIndexedSeqStepper;
            0       6     1  half   I
    MethodParameters:
      Name                           Flags
      half                           final

  public java.lang.Object nextStep();
    descriptor: ()Ljava/lang/Object;
    flags: (0x1041) ACC_PUBLIC, ACC_BRIDGE, ACC_SYNTHETIC
    Code:
      stack=2, locals=1, args_size=1
         0: aload_0
         1: invokevirtual #173                // Method nextStep:()J
         4: invokestatic  #177                // Method scala/runtime/BoxesRunTime.boxToLong:(J)Ljava/lang/Long;
         7: areturn
      LineNumberTable:
        line 39: 0
      LocalVariableTable:
        Start  Length  Slot  Name   Signature
            0       8     0  this   Lscala/collection/convert/impl/LongIndexedSeqStepper;

  public scala.collection.convert.impl.LongIndexedSeqStepper(CC, int, int);
    descriptor: (Lscala/collection/IndexedSeqOps;II)V
    flags: (0x0001) ACC_PUBLIC
    Code:
      stack=3, locals=4, args_size=4
         0: aload_0
         1: aload_1
         2: putfield      #118                // Field scala$collection$convert$impl$LongIndexedSeqStepper$$underlying:Lscala/collection/IndexedSeqOps;
         5: aload_0
         6: iload_2
         7: iload_3
         8: invokespecial #184                // Method scala/collection/convert/impl/IndexedStepperBase."<init>":(II)V
        11: return
      LineNumberTable:
        line 39: 0
        line 40: 5
      LocalVariableTable:
        Start  Length  Slot  Name   Signature
            0      12     0  this   Lscala/collection/convert/impl/LongIndexedSeqStepper;
            0      12     1 underlying   Lscala/collection/IndexedSeqOps;
            0      12     2   _i0   I
            0      12     3   _iN   I
    Signature: #178                         // (TCC;II)V
    MethodParameters:
      Name                           Flags
      underlying                     final
      _i0                            final
      _iN                            final
}
InnerClasses:
  public static #16= #13 of #15;          // OfLong=class java/util/PrimitiveIterator$OfLong of class java/util/PrimitiveIterator
  public static #16= #18 of #20;          // OfLong=class java/util/Spliterator$OfLong of class java/util/Spliterator
Signature: #3                           // <CC::Lscala/collection/IndexedSeqOps<Ljava/lang/Object;Ljava/lang/Object;*>;>Lscala/collection/convert/impl/IndexedStepperBase<Lscala/collection/LongStepper;Lscala/collection/convert/impl/LongIndexedSeqStepper<TCC;>;>;Lscala/collection/LongStepper;
SourceFile: "IndexedSeqStepper.scala"
RuntimeVisibleAnnotations:
  0: #9(#10=s#11)
    scala.reflect.ScalaSignature(
      bytes="\u0006\u0005I3Qa\u0002\u0005\u0001\u0019AA\u0001\"\u0011\u0001\u0003\u0002\u0003\u0006Ia\u0007\u0005\t\u0005\u0002\u0011\t\u0011)A\u0005\u0007\"Aa\t\u0001B\u0001B\u0003%1\tC\u0003H\u0001\u0011\u0005\u0001\nC\u0003M\u0001\u0011\u0005Q\nC\u0003O\u0001\u0011EqJA\u000bM_:<\u0017J\u001c3fq\u0016$7+Z9Ti\u0016\u0004\b/\u001a:\u000b\u0005%Q\u0011\u0001B5na2T!a\u0003\u0007\u0002\u000f\r|gN^3si*\u0011QBD\u0001\u000bG>dG.Z2uS>t\'\"A\b\u0002\u000bM\u001c\u0017\r\\1\u0016\u0005Ei2c\u0001\u0001\u0013-A!1\u0003\u0006\f\u001b\u001b\u0005A\u0011BA\u000b\t\u0005IIe\u000eZ3yK\u0012\u001cF/\u001a9qKJ\u0014\u0015m]3\u0011\u0005]AR\"\u0001\u0007\n\u0005ea!a\u0003\'p]\u001e\u001cF/\u001a9qKJ\u00042a\u0005\u0001\u001c!\taR\u0004\u0004\u0001\u0005\u000by\u0001!\u0019\u0001\u0011\u0003\u0005\r\u001b5\u0001A\t\u0003C\u0015\u0002\"AI\u0012\u000e\u00039I!\u0001\n\b\u0003\u000f9{G\u000f[5oOB\u0012ae\u000f\t\u0006/\u001dJCFO\u0005\u0003Q1\u0011Q\"\u00138eKb,GmU3r\u001fB\u001c\bC\u0001\u0012+\u0013\tYcB\u0001\u0003M_:<\u0007CA\u00178\u001d\tqSG\u0004\u00020i9\u0011\u0001gM\u0007\u0002c)\u0011!gH\u0001\u0007yI|w\u000e\u001e \n\u0003=I!!\u0004\b\n\u0005Yb\u0011a\u00029bG.\fw-Z\u0005\u0003qe\u0012\u0011\"\u00118z\u0007>t7\u000f\u001e:\u000b\u0005Yb\u0001C\u0001\u000f<\t%aT$!A\u0001\u0002\u000b\u0005QHA\u0002`IQ\n\"!\t \u0011\u0005\tz\u0014B\u0001!\u000f\u0005\r\te._\u0001\u000bk:$WM\u001d7zS:<\u0017aA0jaA\u0011!\u0005R\u0005\u0003\u000b:\u00111!\u00138u\u0003\ry\u0016NT\u0001\u0007y%t\u0017\u000e\u001e \u0015\tiI%j\u0013\u0005\u0006\u0003\u0012\u0001\ra\u0007\u0005\u0006\u0005\u0012\u0001\ra\u0011\u0005\u0006\r\u0012\u0001\raQ\u0001\t]\u0016DHo\u0015;faR\t\u0011&A\u0005tK6L7\r\\8oKR\u0011!\u0004\u0015\u0005\u0006#\u001a\u0001\raQ\u0001\u0005Q\u0006dg\r"
    )
  ScalaInlineInfo: length = 0x7C (unknown attribute)
   01 00 00 18 00 7A 00 7B 00 00 65 00 66 00 00 21
   00 30 00 00 21 00 22 00 00 5C 00 30 00 00 61 00
   30 00 00 2F 00 30 00 00 6C 00 6D 00 00 6C 00 A2
   00 00 36 00 37 00 00 3E 00 3F 00 00 6E 00 6D 00
   00 71 00 8A 00 00 71 00 72 00 00 18 00 19 00 00
   18 00 29 00 00 53 00 29 00 00 58 00 29 00 00 28
   00 29 00 00 A1 00 A5 00 00 A1 00 45 00 00 44 00
   45 00 00 4B 00 45 00 00 4F 00 45 00
  ScalaSig: length = 0x3 (unknown attribute)
   05 02 00
