Classfile /Users/mw/Projects/slang-braindump/.jar/jar11/assemble/slang-braindump/assemble/content/scala/collection/convert/impl/VectorStepperBase.class
  Last modified May 29, 2022; size 3402 bytes
  SHA-256 checksum 0d1402aaef5a4025b230808e9abbe46ecead239205ecb0970351088033d9f912
  Compiled from "VectorStepper.scala"
public abstract class scala.collection.convert.impl.VectorStepperBase<Sub extends java.lang.Object, Semi extends Sub> extends scala.collection.convert.impl.IndexedStepperBase<Sub, Semi>
  minor version: 0
  major version: 52
  flags: (0x0421) ACC_PUBLIC, ACC_SUPER, ACC_ABSTRACT
  this_class: #2                          // scala/collection/convert/impl/VectorStepperBase
  super_class: #5                         // scala/collection/convert/impl/IndexedStepperBase
  interfaces: 0, fields: 6, methods: 13, attributes: 5
Constant pool:
   #1 = Utf8               scala/collection/convert/impl/VectorStepperBase
   #2 = Class              #1             // scala/collection/convert/impl/VectorStepperBase
   #3 = Utf8               <Sub:Ljava/lang/Object;Semi:TSub;>Lscala/collection/convert/impl/IndexedStepperBase<TSub;TSemi;>;
   #4 = Utf8               scala/collection/convert/impl/IndexedStepperBase
   #5 = Class              #4             // scala/collection/convert/impl/IndexedStepperBase
   #6 = Utf8               VectorStepper.scala
   #7 = Utf8               Lscala/reflect/ScalaSignature;
   #8 = Utf8               bytes
   #9 = Utf8               \u0006\u0005A4aAF\f\u0002\u0002ey\u0002\u0002C\u001d\u0001\u0005\u0003\u0005\u000b\u0011\u0002\u001e\t\u0011u\u0002!\u0011!Q\u0001\niB\u0001B\u0010\u0001\u0003\u0006\u0004%\tb\u0010\u0005\t\u0001\u0002\u0011\t\u0011)A\u0005u!A\u0011\t\u0001BC\u0002\u0013E!\t\u0003\u0005J\u0001\t\u0005\t\u0015!\u0003D\u0011\u0015Q\u0005\u0001\"\u0001L\u0011\u001d\t\u0006\u00011A\u0005\u0012}BqA\u0015\u0001A\u0002\u0013E1\u000b\u0003\u0004Z\u0001\u0001\u0006KA\u000f\u0005\b5\u0002\u0001\r\u0011\"\u0005C\u0011\u001dY\u0006\u00011A\u0005\u0012qCaA\u0018\u0001!B\u0013\u0019\u0005bB0\u0001\u0001\u0004%\tb\u0010\u0005\bA\u0002\u0001\r\u0011\"\u0005b\u0011\u0019\u0019\u0007\u0001)Q\u0005u!9A\r\u0001a\u0001\n#\u0011\u0005bB3\u0001\u0001\u0004%\tB\u001a\u0005\u0007Q\u0002\u0001\u000b\u0015B\"\t\u000b%\u0004AQ\u00036\t\u000b5\u0004AQ\u00038\u0003#Y+7\r^8s\'R,\u0007\u000f]3s\u0005\u0006\u001cXM\u0003\u0002\u00193\u0005!\u0011.\u001c9m\u0015\tQ2$A\u0004d_:4XM\u001d;\u000b\u0005qi\u0012AC2pY2,7\r^5p]*\ta$A\u0003tG\u0006d\u0017-F\u0002!OM\u001a\"\u0001A\u0011\u0011\t\t\u001aSEM\u0007\u0002/%\u0011Ae\u0006\u0002\u0013\u0013:$W\r_3e\'R,\u0007\u000f]3s\u0005\u0006\u001cX\r\u0005\u0002\'O1\u0001A!\u0002\u0015\u0001\u0005\u0004Q#aA*vE\u000e\u0001\u0011CA\u00160!\taS&D\u0001\u001e\u0013\tqSD\u0001\u0003Ok2d\u0007C\u0001\u00171\u0013\t\tTDA\u0002B]f\u0004\"AJ\u001a\u0005\u000bQ\u0002!\u0019A\u001b\u0003\tM+W.[\t\u0003m\u0015\u0002\"\u0001L\u001c\n\u0005aj\"a\u0002(pi\"LgnZ\u0001\u0004?&\u0004\u0004C\u0001\u0017<\u0013\taTDA\u0002J]R\f1aX5O\u0003!!\u0017n\u001d9mCftU#\u0001\u001e\u0002\u0013\u0011L7\u000f\u001d7bs:\u0003\u0013!\u0002;sk:\\W#A\"\u0011\u00071\"e)\u0003\u0002F;\t)\u0011I\u001d:bsB\u0011AfR\u0005\u0003\u0011v\u0011a!\u00118z%\u00164\u0017A\u0002;sk:\\\u0007%\u0001\u0004=S:LGO\u0010\u000b\u0006\u00196su\n\u0015\t\u0005E\u0001)#\u0007C\u0003:\u000f\u0001\u0007!\bC\u0003>\u000f\u0001\u0007!\bC\u0003?\u000f\u0001\u0007!\bC\u0003B\u000f\u0001\u00071)A\u0003j]\u0012,\u00070A\u0005j]\u0012,\u0007p\u0018\u0013fcR\u0011Ak\u0016\t\u0003YUK!AV\u000f\u0003\tUs\u0017\u000e\u001e\u0005\b1&\t\t\u00111\u0001;\u0003\rAH%M\u0001\u0007S:$W\r\u001f\u0011\u0002\r1,\u0017M^3t\u0003)aW-\u0019<fg~#S-\u001d\u000b\u0003)vCq\u0001\u0017\u0007\u0002\u0002\u0003\u00071)A\u0004mK\u00064Xm\u001d\u0011\u0002\r%tG-\u001a=2\u0003)Ig\u000eZ3yc}#S-\u001d\u000b\u0003)\nDq\u0001W\b\u0002\u0002\u0003\u0007!(A\u0004j]\u0012,\u00070\r\u0011\u0002\u000bQ<\u0018nZ:\u0002\u0013Q<\u0018nZ:`I\u0015\fHC\u0001+h\u0011\u001dA&#!AA\u0002\r\u000ba\u0001^<jON\u0004\u0013aC1em\u0006t7-\u001a#bi\u0006$\"\u0001V6\t\u000b1$\u0002\u0019\u0001\u001e\u0002\u0005%D\u0016AB5oSR$v\u000e\u0006\u0002U_\")A.\u0006a\u0001u\u0001
  #10 = Utf8               displayN
  #11 = Utf8               I
  #12 = Utf8               trunk
  #13 = Utf8               [Ljava/lang/Object;
  #14 = Utf8               index
  #15 = Utf8               leaves
  #16 = Utf8               index1
  #17 = Utf8               twigs
  #18 = Utf8               ()I
  #19 = NameAndType        #10:#11        // displayN:I
  #20 = Fieldref           #2.#19         // scala/collection/convert/impl/VectorStepperBase.displayN:I
  #21 = Utf8               this
  #22 = Utf8               Lscala/collection/convert/impl/VectorStepperBase;
  #23 = Utf8               ()[Ljava/lang/Object;
  #24 = NameAndType        #12:#13        // trunk:[Ljava/lang/Object;
  #25 = Fieldref           #2.#24         // scala/collection/convert/impl/VectorStepperBase.trunk:[Ljava/lang/Object;
  #26 = NameAndType        #14:#11        // index:I
  #27 = Fieldref           #2.#26         // scala/collection/convert/impl/VectorStepperBase.index:I
  #28 = Utf8               index_$eq
  #29 = Utf8               (I)V
  #30 = Utf8               x$1
  #31 = NameAndType        #15:#13        // leaves:[Ljava/lang/Object;
  #32 = Fieldref           #2.#31         // scala/collection/convert/impl/VectorStepperBase.leaves:[Ljava/lang/Object;
  #33 = Utf8               leaves_$eq
  #34 = Utf8               ([Ljava/lang/Object;)V
  #35 = NameAndType        #16:#11        // index1:I
  #36 = Fieldref           #2.#35         // scala/collection/convert/impl/VectorStepperBase.index1:I
  #37 = Utf8               index1_$eq
  #38 = NameAndType        #17:#13        // twigs:[Ljava/lang/Object;
  #39 = Fieldref           #2.#38         // scala/collection/convert/impl/VectorStepperBase.twigs:[Ljava/lang/Object;
  #40 = Utf8               twigs_$eq
  #41 = Utf8               advanceData
  #42 = Utf8               iX
  #43 = NameAndType        #16:#18        // index1:()I
  #44 = Methodref          #2.#43         // scala/collection/convert/impl/VectorStepperBase.index1:()I
  #45 = NameAndType        #37:#29        // index1_$eq:(I)V
  #46 = Methodref          #2.#45         // scala/collection/convert/impl/VectorStepperBase.index1_$eq:(I)V
  #47 = Utf8               initTo
  #48 = NameAndType        #47:#29        // initTo:(I)V
  #49 = Methodref          #2.#48         // scala/collection/convert/impl/VectorStepperBase.initTo:(I)V
  #50 = NameAndType        #17:#23        // twigs:()[Ljava/lang/Object;
  #51 = Methodref          #2.#50         // scala/collection/convert/impl/VectorStepperBase.twigs:()[Ljava/lang/Object;
  #52 = Class              #13            // "[Ljava/lang/Object;"
  #53 = NameAndType        #33:#34        // leaves_$eq:([Ljava/lang/Object;)V
  #54 = Methodref          #2.#53         // scala/collection/convert/impl/VectorStepperBase.leaves_$eq:([Ljava/lang/Object;)V
  #55 = NameAndType        #28:#29        // index_$eq:(I)V
  #56 = Methodref          #2.#55         // scala/collection/convert/impl/VectorStepperBase.index_$eq:(I)V
  #57 = NameAndType        #10:#18        // displayN:()I
  #58 = Methodref          #2.#57         // scala/collection/convert/impl/VectorStepperBase.displayN:()I
  #59 = NameAndType        #12:#23        // trunk:()[Ljava/lang/Object;
  #60 = Methodref          #2.#59         // scala/collection/convert/impl/VectorStepperBase.trunk:()[Ljava/lang/Object;
  #61 = NameAndType        #40:#34        // twigs_$eq:([Ljava/lang/Object;)V
  #62 = Methodref          #2.#61         // scala/collection/convert/impl/VectorStepperBase.twigs_$eq:([Ljava/lang/Object;)V
  #63 = Utf8               n
  #64 = Utf8               dataN
  #65 = Utf8               <init>
  #66 = Utf8               (III[Ljava/lang/Object;)V
  #67 = Utf8               _i0
  #68 = Utf8               _iN
  #69 = Utf8               (II)V
  #70 = NameAndType        #65:#69        // "<init>":(II)V
  #71 = Methodref          #5.#70         // scala/collection/convert/impl/IndexedStepperBase."<init>":(II)V
  #72 = Utf8               Code
  #73 = Utf8               LineNumberTable
  #74 = Utf8               LocalVariableTable
  #75 = Utf8               MethodParameters
  #76 = Utf8               StackMapTable
  #77 = Utf8               Signature
  #78 = Utf8               SourceFile
  #79 = Utf8               RuntimeVisibleAnnotations
  #80 = Utf8               ScalaInlineInfo
  #81 = Utf8               ScalaSig
{
  private final int displayN;
    descriptor: I
    flags: (0x0012) ACC_PRIVATE, ACC_FINAL

  private final java.lang.Object[] trunk;
    descriptor: [Ljava/lang/Object;
    flags: (0x0012) ACC_PRIVATE, ACC_FINAL

  private int index;
    descriptor: I
    flags: (0x0002) ACC_PRIVATE

  private java.lang.Object[] leaves;
    descriptor: [Ljava/lang/Object;
    flags: (0x0002) ACC_PRIVATE

  private int index1;
    descriptor: I
    flags: (0x0002) ACC_PRIVATE

  private java.lang.Object[] twigs;
    descriptor: [Ljava/lang/Object;
    flags: (0x0002) ACC_PRIVATE

  public int displayN();
    descriptor: ()I
    flags: (0x0001) ACC_PUBLIC
    Code:
      stack=1, locals=1, args_size=1
         0: aload_0
         1: getfield      #20                 // Field displayN:I
         4: ireturn
      LineNumberTable:
        line 21: 0
      LocalVariableTable:
        Start  Length  Slot  Name   Signature
            0       5     0  this   Lscala/collection/convert/impl/VectorStepperBase;

  public java.lang.Object[] trunk();
    descriptor: ()[Ljava/lang/Object;
    flags: (0x0001) ACC_PUBLIC
    Code:
      stack=1, locals=1, args_size=1
         0: aload_0
         1: getfield      #25                 // Field trunk:[Ljava/lang/Object;
         4: areturn
      LineNumberTable:
        line 22: 0
      LocalVariableTable:
        Start  Length  Slot  Name   Signature
            0       5     0  this   Lscala/collection/convert/impl/VectorStepperBase;

  public int index();
    descriptor: ()I
    flags: (0x0001) ACC_PUBLIC
    Code:
      stack=1, locals=1, args_size=1
         0: aload_0
         1: getfield      #27                 // Field index:I
         4: ireturn
      LineNumberTable:
        line 25: 0
      LocalVariableTable:
        Start  Length  Slot  Name   Signature
            0       5     0  this   Lscala/collection/convert/impl/VectorStepperBase;

  public void index_$eq(int);
    descriptor: (I)V
    flags: (0x0001) ACC_PUBLIC
    Code:
      stack=2, locals=2, args_size=2
         0: aload_0
         1: iload_1
         2: putfield      #27                 // Field index:I
         5: return
      LineNumberTable:
        line 25: 0
      LocalVariableTable:
        Start  Length  Slot  Name   Signature
            0       6     0  this   Lscala/collection/convert/impl/VectorStepperBase;
            0       6     1   x$1   I
    MethodParameters:
      Name                           Flags
      x$1                            final

  public java.lang.Object[] leaves();
    descriptor: ()[Ljava/lang/Object;
    flags: (0x0001) ACC_PUBLIC
    Code:
      stack=1, locals=1, args_size=1
         0: aload_0
         1: getfield      #32                 // Field leaves:[Ljava/lang/Object;
         4: areturn
      LineNumberTable:
        line 26: 0
      LocalVariableTable:
        Start  Length  Slot  Name   Signature
            0       5     0  this   Lscala/collection/convert/impl/VectorStepperBase;

  public void leaves_$eq(java.lang.Object[]);
    descriptor: ([Ljava/lang/Object;)V
    flags: (0x0001) ACC_PUBLIC
    Code:
      stack=2, locals=2, args_size=2
         0: aload_0
         1: aload_1
         2: putfield      #32                 // Field leaves:[Ljava/lang/Object;
         5: return
      LineNumberTable:
        line 26: 0
      LocalVariableTable:
        Start  Length  Slot  Name   Signature
            0       6     0  this   Lscala/collection/convert/impl/VectorStepperBase;
            0       6     1   x$1   [Ljava/lang/Object;
    MethodParameters:
      Name                           Flags
      x$1                            final

  public int index1();
    descriptor: ()I
    flags: (0x0001) ACC_PUBLIC
    Code:
      stack=1, locals=1, args_size=1
         0: aload_0
         1: getfield      #36                 // Field index1:I
         4: ireturn
      LineNumberTable:
        line 27: 0
      LocalVariableTable:
        Start  Length  Slot  Name   Signature
            0       5     0  this   Lscala/collection/convert/impl/VectorStepperBase;

  public void index1_$eq(int);
    descriptor: (I)V
    flags: (0x0001) ACC_PUBLIC
    Code:
      stack=2, locals=2, args_size=2
         0: aload_0
         1: iload_1
         2: putfield      #36                 // Field index1:I
         5: return
      LineNumberTable:
        line 27: 0
      LocalVariableTable:
        Start  Length  Slot  Name   Signature
            0       6     0  this   Lscala/collection/convert/impl/VectorStepperBase;
            0       6     1   x$1   I
    MethodParameters:
      Name                           Flags
      x$1                            final

  public java.lang.Object[] twigs();
    descriptor: ()[Ljava/lang/Object;
    flags: (0x0001) ACC_PUBLIC
    Code:
      stack=1, locals=1, args_size=1
         0: aload_0
         1: getfield      #39                 // Field twigs:[Ljava/lang/Object;
         4: areturn
      LineNumberTable:
        line 28: 0
      LocalVariableTable:
        Start  Length  Slot  Name   Signature
            0       5     0  this   Lscala/collection/convert/impl/VectorStepperBase;

  public void twigs_$eq(java.lang.Object[]);
    descriptor: ([Ljava/lang/Object;)V
    flags: (0x0001) ACC_PUBLIC
    Code:
      stack=2, locals=2, args_size=2
         0: aload_0
         1: aload_1
         2: putfield      #39                 // Field twigs:[Ljava/lang/Object;
         5: return
      LineNumberTable:
        line 28: 0
      LocalVariableTable:
        Start  Length  Slot  Name   Signature
            0       6     0  this   Lscala/collection/convert/impl/VectorStepperBase;
            0       6     1   x$1   [Ljava/lang/Object;
    MethodParameters:
      Name                           Flags
      x$1                            final

  public final void advanceData(int);
    descriptor: (I)V
    flags: (0x0011) ACC_PUBLIC, ACC_FINAL
    Code:
      stack=3, locals=2, args_size=2
         0: aload_0
         1: aload_0
         2: invokevirtual #44                 // Method index1:()I
         5: iconst_1
         6: iadd
         7: invokevirtual #46                 // Method index1_$eq:(I)V
        10: aload_0
        11: invokevirtual #44                 // Method index1:()I
        14: bipush        32
        16: if_icmplt     25
        19: aload_0
        20: iload_1
        21: invokevirtual #49                 // Method initTo:(I)V
        24: return
        25: aload_0
        26: aload_0
        27: invokevirtual #51                 // Method twigs:()[Ljava/lang/Object;
        30: aload_0
        31: invokevirtual #44                 // Method index1:()I
        34: aaload
        35: checkcast     #52                 // class "[Ljava/lang/Object;"
        38: invokevirtual #54                 // Method leaves_$eq:([Ljava/lang/Object;)V
        41: aload_0
        42: iconst_0
        43: invokevirtual #56                 // Method index_$eq:(I)V
        46: return
      StackMapTable: number_of_entries = 1
        frame_type = 25 /* same */
      LineNumberTable:
        line 31: 0
        line 32: 10
        line 34: 25
        line 35: 41
      LocalVariableTable:
        Start  Length  Slot  Name   Signature
            0      47     0  this   Lscala/collection/convert/impl/VectorStepperBase;
            0      47     1    iX   I
    MethodParameters:
      Name                           Flags
      iX                             final

  public final void initTo(int);
    descriptor: (I)V
    flags: (0x0011) ACC_PUBLIC, ACC_FINAL
    Code:
      stack=4, locals=4, args_size=2
         0: aload_0
         1: invokevirtual #58                 // Method displayN:()I
         4: tableswitch   { // 0 to 1
                       0: 28
                       1: 42
                 default: 82
            }
        28: aload_0
        29: aload_0
        30: invokevirtual #60                 // Method trunk:()[Ljava/lang/Object;
        33: invokevirtual #54                 // Method leaves_$eq:([Ljava/lang/Object;)V
        36: aload_0
        37: iload_1
        38: invokevirtual #56                 // Method index_$eq:(I)V
        41: return
        42: aload_0
        43: aload_0
        44: invokevirtual #60                 // Method trunk:()[Ljava/lang/Object;
        47: invokevirtual #62                 // Method twigs_$eq:([Ljava/lang/Object;)V
        50: aload_0
        51: iload_1
        52: iconst_5
        53: iushr
        54: invokevirtual #46                 // Method index1_$eq:(I)V
        57: aload_0
        58: aload_0
        59: invokevirtual #51                 // Method twigs:()[Ljava/lang/Object;
        62: aload_0
        63: invokevirtual #44                 // Method index1:()I
        66: aaload
        67: checkcast     #52                 // class "[Ljava/lang/Object;"
        70: invokevirtual #54                 // Method leaves_$eq:([Ljava/lang/Object;)V
        73: aload_0
        74: iload_1
        75: bipush        31
        77: iand
        78: invokevirtual #56                 // Method index_$eq:(I)V
        81: return
        82: aload_0
        83: invokevirtual #58                 // Method displayN:()I
        86: istore_2
        87: aload_0
        88: invokevirtual #60                 // Method trunk:()[Ljava/lang/Object;
        91: astore_3
        92: iload_2
        93: iconst_2
        94: if_icmple     117
        97: aload_3
        98: iload_1
        99: iconst_5
       100: iload_2
       101: imul
       102: ishr
       103: bipush        31
       105: iand
       106: aaload
       107: checkcast     #52                 // class "[Ljava/lang/Object;"
       110: astore_3
       111: iinc          2, -1
       114: goto          92
       117: aload_0
       118: aload_3
       119: iload_1
       120: bipush        10
       122: iushr
       123: bipush        31
       125: iand
       126: aaload
       127: checkcast     #52                 // class "[Ljava/lang/Object;"
       130: invokevirtual #62                 // Method twigs_$eq:([Ljava/lang/Object;)V
       133: aload_0
       134: iload_1
       135: iconst_5
       136: ishr
       137: bipush        31
       139: iand
       140: invokevirtual #46                 // Method index1_$eq:(I)V
       143: aload_0
       144: aload_0
       145: invokevirtual #51                 // Method twigs:()[Ljava/lang/Object;
       148: aload_0
       149: invokevirtual #44                 // Method index1:()I
       152: aaload
       153: checkcast     #52                 // class "[Ljava/lang/Object;"
       156: invokevirtual #54                 // Method leaves_$eq:([Ljava/lang/Object;)V
       159: aload_0
       160: iload_1
       161: bipush        31
       163: iand
       164: invokevirtual #56                 // Method index_$eq:(I)V
       167: return
      StackMapTable: number_of_entries = 5
        frame_type = 28 /* same */
        frame_type = 13 /* same */
        frame_type = 39 /* same */
        frame_type = 253 /* append */
          offset_delta = 9
          locals = [ int, class "[Ljava/lang/Object;" ]
        frame_type = 24 /* same */
      LineNumberTable:
        line 38: 0
        line 40: 28
        line 41: 36
        line 43: 42
        line 44: 50
        line 45: 57
        line 46: 73
        line 48: 82
        line 49: 87
        line 50: 92
        line 51: 97
        line 52: 111
        line 50: 114
        line 54: 117
        line 55: 133
        line 56: 143
        line 57: 159
      LocalVariableTable:
        Start  Length  Slot  Name   Signature
           87      80     2     n   I
           92      75     3 dataN   [Ljava/lang/Object;
            0     168     0  this   Lscala/collection/convert/impl/VectorStepperBase;
            0     168     1    iX   I
    MethodParameters:
      Name                           Flags
      iX                             final

  public scala.collection.convert.impl.VectorStepperBase(int, int, int, java.lang.Object[]);
    descriptor: (III[Ljava/lang/Object;)V
    flags: (0x0001) ACC_PUBLIC
    Code:
      stack=3, locals=5, args_size=5
         0: aload_0
         1: iload_3
         2: putfield      #20                 // Field displayN:I
         5: aload_0
         6: aload         4
         8: putfield      #25                 // Field trunk:[Ljava/lang/Object;
        11: aload_0
        12: iload_1
        13: iload_2
        14: invokespecial #71                 // Method scala/collection/convert/impl/IndexedStepperBase."<init>":(II)V
        17: aload_0
        18: bipush        32
        20: putfield      #27                 // Field index:I
        23: aload_0
        24: aconst_null
        25: putfield      #32                 // Field leaves:[Ljava/lang/Object;
        28: aload_0
        29: bipush        32
        31: putfield      #36                 // Field index1:I
        34: aload_0
        35: aconst_null
        36: putfield      #39                 // Field twigs:[Ljava/lang/Object;
        39: return
      LineNumberTable:
        line 21: 0
        line 22: 5
        line 24: 11
        line 25: 17
        line 26: 23
        line 27: 28
        line 28: 34
        line 18: 39
      LocalVariableTable:
        Start  Length  Slot  Name   Signature
            0      40     0  this   Lscala/collection/convert/impl/VectorStepperBase;
            0      40     1   _i0   I
            0      40     2   _iN   I
            0      40     3 displayN   I
            0      40     4 trunk   [Ljava/lang/Object;
    MethodParameters:
      Name                           Flags
      _i0                            final
      _iN                            final
      displayN                       final
      trunk                          final
}
Signature: #3                           // <Sub:Ljava/lang/Object;Semi:TSub;>Lscala/collection/convert/impl/IndexedStepperBase<TSub;TSemi;>;
SourceFile: "VectorStepper.scala"
RuntimeVisibleAnnotations:
  0: #7(#8=s#9)
    scala.reflect.ScalaSignature(
      bytes="\u0006\u0005A4aAF\f\u0002\u0002ey\u0002\u0002C\u001d\u0001\u0005\u0003\u0005\u000b\u0011\u0002\u001e\t\u0011u\u0002!\u0011!Q\u0001\niB\u0001B\u0010\u0001\u0003\u0006\u0004%\tb\u0010\u0005\t\u0001\u0002\u0011\t\u0011)A\u0005u!A\u0011\t\u0001BC\u0002\u0013E!\t\u0003\u0005J\u0001\t\u0005\t\u0015!\u0003D\u0011\u0015Q\u0005\u0001\"\u0001L\u0011\u001d\t\u0006\u00011A\u0005\u0012}BqA\u0015\u0001A\u0002\u0013E1\u000b\u0003\u0004Z\u0001\u0001\u0006KA\u000f\u0005\b5\u0002\u0001\r\u0011\"\u0005C\u0011\u001dY\u0006\u00011A\u0005\u0012qCaA\u0018\u0001!B\u0013\u0019\u0005bB0\u0001\u0001\u0004%\tb\u0010\u0005\bA\u0002\u0001\r\u0011\"\u0005b\u0011\u0019\u0019\u0007\u0001)Q\u0005u!9A\r\u0001a\u0001\n#\u0011\u0005bB3\u0001\u0001\u0004%\tB\u001a\u0005\u0007Q\u0002\u0001\u000b\u0015B\"\t\u000b%\u0004AQ\u00036\t\u000b5\u0004AQ\u00038\u0003#Y+7\r^8s\'R,\u0007\u000f]3s\u0005\u0006\u001cXM\u0003\u0002\u00193\u0005!\u0011.\u001c9m\u0015\tQ2$A\u0004d_:4XM\u001d;\u000b\u0005qi\u0012AC2pY2,7\r^5p]*\ta$A\u0003tG\u0006d\u0017-F\u0002!OM\u001a\"\u0001A\u0011\u0011\t\t\u001aSEM\u0007\u0002/%\u0011Ae\u0006\u0002\u0013\u0013:$W\r_3e\'R,\u0007\u000f]3s\u0005\u0006\u001cX\r\u0005\u0002\'O1\u0001A!\u0002\u0015\u0001\u0005\u0004Q#aA*vE\u000e\u0001\u0011CA\u00160!\taS&D\u0001\u001e\u0013\tqSD\u0001\u0003Ok2d\u0007C\u0001\u00171\u0013\t\tTDA\u0002B]f\u0004\"AJ\u001a\u0005\u000bQ\u0002!\u0019A\u001b\u0003\tM+W.[\t\u0003m\u0015\u0002\"\u0001L\u001c\n\u0005aj\"a\u0002(pi\"LgnZ\u0001\u0004?&\u0004\u0004C\u0001\u0017<\u0013\taTDA\u0002J]R\f1aX5O\u0003!!\u0017n\u001d9mCftU#\u0001\u001e\u0002\u0013\u0011L7\u000f\u001d7bs:\u0003\u0013!\u0002;sk:\\W#A\"\u0011\u00071\"e)\u0003\u0002F;\t)\u0011I\u001d:bsB\u0011AfR\u0005\u0003\u0011v\u0011a!\u00118z%\u00164\u0017A\u0002;sk:\\\u0007%\u0001\u0004=S:LGO\u0010\u000b\u0006\u00196su\n\u0015\t\u0005E\u0001)#\u0007C\u0003:\u000f\u0001\u0007!\bC\u0003>\u000f\u0001\u0007!\bC\u0003?\u000f\u0001\u0007!\bC\u0003B\u000f\u0001\u00071)A\u0003j]\u0012,\u00070A\u0005j]\u0012,\u0007p\u0018\u0013fcR\u0011Ak\u0016\t\u0003YUK!AV\u000f\u0003\tUs\u0017\u000e\u001e\u0005\b1&\t\t\u00111\u0001;\u0003\rAH%M\u0001\u0007S:$W\r\u001f\u0011\u0002\r1,\u0017M^3t\u0003)aW-\u0019<fg~#S-\u001d\u000b\u0003)vCq\u0001\u0017\u0007\u0002\u0002\u0003\u00071)A\u0004mK\u00064Xm\u001d\u0011\u0002\r%tG-\u001a=2\u0003)Ig\u000eZ3yc}#S-\u001d\u000b\u0003)\nDq\u0001W\b\u0002\u0002\u0003\u0007!(A\u0004j]\u0012,\u00070\r\u0011\u0002\u000bQ<\u0018nZ:\u0002\u0013Q<\u0018nZ:`I\u0015\fHC\u0001+h\u0011\u001dA&#!AA\u0002\r\u000ba\u0001^<jON\u0004\u0013aC1em\u0006t7-\u001a#bi\u0006$\"\u0001V6\t\u000b1$\u0002\u0019\u0001\u001e\u0002\u0005%D\u0016AB5oSR$v\u000e\u0006\u0002U_\")A.\u0006a\u0001u\u0001"
    )
  ScalaInlineInfo: length = 0x45 (unknown attribute)
   01 00 00 0D 00 41 00 42 00 00 29 00 1D 01 00 0A
   00 12 00 00 0E 00 12 00 00 10 00 12 00 00 25 00
   1D 00 00 1C 00 1D 00 00 2F 00 1D 01 00 0F 00 17
   00 00 21 00 22 00 00 0C 00 17 00 00 11 00 17 00
   00 28 00 22 00
  ScalaSig: length = 0x3 (unknown attribute)
   05 02 00
