Classfile /Users/mw/Projects/slang-braindump/.jar/jar11/assemble/slang-braindump/assemble/content/scala/xml/dtd/impl/Base$Sequ$.class
  Last modified May 29, 2022; size 1688 bytes
  SHA-256 checksum 2c7eef59452f26bdcfb069fd0af686e68e7f4b013378ecdae75cda6a37cdc214
  Compiled from "Base.scala"
public class scala.xml.dtd.impl.Base$Sequ$
  minor version: 0
  major version: 52
  flags: (0x0021) ACC_PUBLIC, ACC_SUPER
  this_class: #2                          // scala/xml/dtd/impl/Base$Sequ$
  super_class: #4                         // java/lang/Object
  interfaces: 0, fields: 1, methods: 3, attributes: 4
Constant pool:
   #1 = Utf8               scala/xml/dtd/impl/Base$Sequ$
   #2 = Class              #1             // scala/xml/dtd/impl/Base$Sequ$
   #3 = Utf8               java/lang/Object
   #4 = Class              #3             // java/lang/Object
   #5 = Utf8               Base.scala
   #6 = Utf8               scala/xml/dtd/impl/Base$Eps$
   #7 = Class              #6             // scala/xml/dtd/impl/Base$Eps$
   #8 = Utf8               scala/xml/dtd/impl/Base
   #9 = Class              #8             // scala/xml/dtd/impl/Base
  #10 = Utf8               Eps$
  #11 = Utf8               scala/xml/dtd/impl/Base$RegExp
  #12 = Class              #11            // scala/xml/dtd/impl/Base$RegExp
  #13 = Utf8               RegExp
  #14 = Utf8               scala/xml/dtd/impl/Base$Sequ
  #15 = Class              #14            // scala/xml/dtd/impl/Base$Sequ
  #16 = Utf8               Sequ
  #17 = Utf8               Sequ$
  #18 = Utf8               $outer
  #19 = Utf8               Lscala/xml/dtd/impl/Base;
  #20 = Utf8               apply
  #21 = Utf8               (Lscala/collection/immutable/Seq;)Lscala/xml/dtd/impl/Base$RegExp;
  #22 = Utf8               (Lscala/collection/immutable/Seq<Lscala/xml/dtd/impl/Base$RegExp;>;)Lscala/xml/dtd/impl/Base$RegExp;
  #23 = Utf8               rs
  #24 = Utf8               scala/collection/immutable/Seq
  #25 = Class              #24            // scala/collection/immutable/Seq
  #26 = Utf8               isEmpty
  #27 = Utf8               ()Z
  #28 = NameAndType        #26:#27        // isEmpty:()Z
  #29 = InterfaceMethodref #25.#28        // scala/collection/immutable/Seq.isEmpty:()Z
  #30 = NameAndType        #18:#19        // $outer:Lscala/xml/dtd/impl/Base;
  #31 = Fieldref           #2.#30         // scala/xml/dtd/impl/Base$Sequ$.$outer:Lscala/xml/dtd/impl/Base;
  #32 = Utf8               Eps
  #33 = Utf8               ()Lscala/xml/dtd/impl/Base$Eps$;
  #34 = NameAndType        #32:#33        // Eps:()Lscala/xml/dtd/impl/Base$Eps$;
  #35 = Methodref          #9.#34         // scala/xml/dtd/impl/Base.Eps:()Lscala/xml/dtd/impl/Base$Eps$;
  #36 = Utf8               <init>
  #37 = Utf8               (Lscala/xml/dtd/impl/Base;Lscala/collection/immutable/Seq;)V
  #38 = NameAndType        #36:#37        // "<init>":(Lscala/xml/dtd/impl/Base;Lscala/collection/immutable/Seq;)V
  #39 = Methodref          #15.#38        // scala/xml/dtd/impl/Base$Sequ."<init>":(Lscala/xml/dtd/impl/Base;Lscala/collection/immutable/Seq;)V
  #40 = Utf8               this
  #41 = Utf8               Lscala/xml/dtd/impl/Base$Sequ$;
  #42 = Utf8               Lscala/collection/immutable/Seq;
  #43 = Utf8               unapplySeq
  #44 = Utf8               (Lscala/xml/dtd/impl/Base$Sequ;)Lscala/Some;
  #45 = Utf8               (Lscala/xml/dtd/impl/Base$Sequ;)Lscala/Some<Lscala/collection/immutable/Seq<Lscala/xml/dtd/impl/Base$RegExp;>;>;
  #46 = Utf8               x
  #47 = Utf8               scala/Some
  #48 = Class              #47            // scala/Some
  #49 = Utf8               ()Lscala/collection/immutable/Seq;
  #50 = NameAndType        #23:#49        // rs:()Lscala/collection/immutable/Seq;
  #51 = Methodref          #15.#50        // scala/xml/dtd/impl/Base$Sequ.rs:()Lscala/collection/immutable/Seq;
  #52 = Utf8               (Ljava/lang/Object;)V
  #53 = NameAndType        #36:#52        // "<init>":(Ljava/lang/Object;)V
  #54 = Methodref          #48.#53        // scala/Some."<init>":(Ljava/lang/Object;)V
  #55 = Utf8               Lscala/xml/dtd/impl/Base$Sequ;
  #56 = Utf8               (Lscala/xml/dtd/impl/Base;)V
  #57 = Utf8               ()V
  #58 = NameAndType        #36:#57        // "<init>":()V
  #59 = Methodref          #4.#58         // java/lang/Object."<init>":()V
  #60 = Utf8               Code
  #61 = Utf8               StackMapTable
  #62 = Utf8               LineNumberTable
  #63 = Utf8               LocalVariableTable
  #64 = Utf8               Signature
  #65 = Utf8               MethodParameters
  #66 = Utf8               InnerClasses
  #67 = Utf8               SourceFile
  #68 = Utf8               ScalaInlineInfo
  #69 = Utf8               Scala
{
  private final scala.xml.dtd.impl.Base $outer;
    descriptor: Lscala/xml/dtd/impl/Base;
    flags: (0x1012) ACC_PRIVATE, ACC_FINAL, ACC_SYNTHETIC

  public scala.xml.dtd.impl.Base$RegExp apply(scala.collection.immutable.Seq<scala.xml.dtd.impl.Base$RegExp>);
    descriptor: (Lscala/collection/immutable/Seq;)Lscala/xml/dtd/impl/Base$RegExp;
    flags: (0x0001) ACC_PUBLIC
    Code:
      stack=4, locals=2, args_size=2
         0: aload_1
         1: invokeinterface #29,  1           // InterfaceMethod scala/collection/immutable/Seq.isEmpty:()Z
         6: ifeq          19
         9: aload_0
        10: getfield      #31                 // Field $outer:Lscala/xml/dtd/impl/Base;
        13: invokevirtual #35                 // Method scala/xml/dtd/impl/Base.Eps:()Lscala/xml/dtd/impl/Base$Eps$;
        16: goto          31
        19: new           #15                 // class scala/xml/dtd/impl/Base$Sequ
        22: dup
        23: aload_0
        24: getfield      #31                 // Field $outer:Lscala/xml/dtd/impl/Base;
        27: aload_1
        28: invokespecial #39                 // Method scala/xml/dtd/impl/Base$Sequ."<init>":(Lscala/xml/dtd/impl/Base;Lscala/collection/immutable/Seq;)V
        31: areturn
      StackMapTable: number_of_entries = 2
        frame_type = 19 /* same */
        frame_type = 75 /* same_locals_1_stack_item */
          stack = [ class scala/xml/dtd/impl/Base$RegExp ]
      LineNumberTable:
        line 46: 0
      LocalVariableTable:
        Start  Length  Slot  Name   Signature
            0      32     0  this   Lscala/xml/dtd/impl/Base$Sequ$;
            0      32     1    rs   Lscala/collection/immutable/Seq;
    Signature: #22                          // (Lscala/collection/immutable/Seq<Lscala/xml/dtd/impl/Base$RegExp;>;)Lscala/xml/dtd/impl/Base$RegExp;
    MethodParameters:
      Name                           Flags
      rs                             final

  public scala.Some<scala.collection.immutable.Seq<scala.xml.dtd.impl.Base$RegExp>> unapplySeq(scala.xml.dtd.impl.Base$Sequ);
    descriptor: (Lscala/xml/dtd/impl/Base$Sequ;)Lscala/Some;
    flags: (0x0001) ACC_PUBLIC
    Code:
      stack=3, locals=2, args_size=2
         0: new           #48                 // class scala/Some
         3: dup
         4: aload_1
         5: invokevirtual #51                 // Method scala/xml/dtd/impl/Base$Sequ.rs:()Lscala/collection/immutable/Seq;
         8: invokespecial #54                 // Method scala/Some."<init>":(Ljava/lang/Object;)V
        11: areturn
      LineNumberTable:
        line 47: 0
      LocalVariableTable:
        Start  Length  Slot  Name   Signature
            0      12     0  this   Lscala/xml/dtd/impl/Base$Sequ$;
            0      12     1     x   Lscala/xml/dtd/impl/Base$Sequ;
    Signature: #45                          // (Lscala/xml/dtd/impl/Base$Sequ;)Lscala/Some<Lscala/collection/immutable/Seq<Lscala/xml/dtd/impl/Base$RegExp;>;>;
    MethodParameters:
      Name                           Flags
      x                              final

  public scala.xml.dtd.impl.Base$Sequ$(scala.xml.dtd.impl.Base);
    descriptor: (Lscala/xml/dtd/impl/Base;)V
    flags: (0x0001) ACC_PUBLIC
    Code:
      stack=2, locals=2, args_size=2
         0: aload_1
         1: ifnonnull     6
         4: aconst_null
         5: athrow
         6: aload_0
         7: aload_1
         8: putfield      #31                 // Field $outer:Lscala/xml/dtd/impl/Base;
        11: aload_0
        12: invokespecial #59                 // Method java/lang/Object."<init>":()V
        15: return
      StackMapTable: number_of_entries = 1
        frame_type = 6 /* same */
      LineNumberTable:
        line 44: 0
        line 50: 11
        line 44: 15
      LocalVariableTable:
        Start  Length  Slot  Name   Signature
            0      16     0  this   Lscala/xml/dtd/impl/Base$Sequ$;
            0      16     1 $outer   Lscala/xml/dtd/impl/Base;
    MethodParameters:
      Name                           Flags
      $outer                         final synthetic
}
InnerClasses:
  public #10= #7 of #9;                   // Eps$=class scala/xml/dtd/impl/Base$Eps$ of class scala/xml/dtd/impl/Base
  public abstract #13= #12 of #9;         // RegExp=class scala/xml/dtd/impl/Base$RegExp of class scala/xml/dtd/impl/Base
  public #16= #15 of #9;                  // Sequ=class scala/xml/dtd/impl/Base$Sequ of class scala/xml/dtd/impl/Base
  public #17= #2 of #9;                   // Sequ$=class scala/xml/dtd/impl/Base$Sequ$ of class scala/xml/dtd/impl/Base
SourceFile: "Base.scala"
  ScalaInlineInfo: length = 0x13 (unknown attribute)
   01 01 00 03 00 24 00 38 01 00 14 00 15 01 00 2B
   00 2C 01
  Scala: length = 0x0 (unknown attribute)

