Classfile /Users/mw/Projects/slang-braindump/.jar/jar11/assemble/slang-braindump/assemble/content/scala/xml/dtd/impl/WordExp$Letter$.class
  Last modified May 29, 2022; size 1949 bytes
  SHA-256 checksum 5749e8156c5c63f1b1d215f1f3402c356950033a555858273fa77e1dde9389c4
  Compiled from "WordExp.scala"
public class scala.xml.dtd.impl.WordExp$Letter$ extends scala.runtime.AbstractFunction1<scala.xml.dtd.impl.WordExp$Label, scala.xml.dtd.impl.WordExp$Letter> implements java.io.Serializable
  minor version: 0
  major version: 52
  flags: (0x0021) ACC_PUBLIC, ACC_SUPER
  this_class: #2                          // scala/xml/dtd/impl/WordExp$Letter$
  super_class: #5                         // scala/runtime/AbstractFunction1
  interfaces: 1, fields: 1, methods: 5, attributes: 5
Constant pool:
   #1 = Utf8               scala/xml/dtd/impl/WordExp$Letter$
   #2 = Class              #1             // scala/xml/dtd/impl/WordExp$Letter$
   #3 = Utf8               Lscala/runtime/AbstractFunction1<Lscala/xml/dtd/impl/WordExp$Label;Lscala/xml/dtd/impl/WordExp$Letter;>;Ljava/io/Serializable;
   #4 = Utf8               scala/runtime/AbstractFunction1
   #5 = Class              #4             // scala/runtime/AbstractFunction1
   #6 = Utf8               java/io/Serializable
   #7 = Class              #6             // java/io/Serializable
   #8 = Utf8               WordExp.scala
   #9 = Utf8               scala/xml/dtd/impl/WordExp$Label
  #10 = Class              #9             // scala/xml/dtd/impl/WordExp$Label
  #11 = Utf8               scala/xml/dtd/impl/WordExp
  #12 = Class              #11            // scala/xml/dtd/impl/WordExp
  #13 = Utf8               Label
  #14 = Utf8               scala/xml/dtd/impl/WordExp$Letter
  #15 = Class              #14            // scala/xml/dtd/impl/WordExp$Letter
  #16 = Utf8               Letter
  #17 = Utf8               Letter$
  #18 = Utf8               $outer
  #19 = Utf8               Lscala/xml/dtd/impl/WordExp;
  #20 = Utf8               toString
  #21 = Utf8               ()Ljava/lang/String;
  #22 = String             #16            // Letter
  #23 = Utf8               this
  #24 = Utf8               Lscala/xml/dtd/impl/WordExp$Letter$;
  #25 = Utf8               apply
  #26 = Utf8               (Lscala/xml/dtd/impl/WordExp$Label;)Lscala/xml/dtd/impl/WordExp$Letter;
  #27 = Utf8               a
  #28 = NameAndType        #18:#19        // $outer:Lscala/xml/dtd/impl/WordExp;
  #29 = Fieldref           #2.#28         // scala/xml/dtd/impl/WordExp$Letter$.$outer:Lscala/xml/dtd/impl/WordExp;
  #30 = Utf8               <init>
  #31 = Utf8               (Lscala/xml/dtd/impl/WordExp;Lscala/xml/dtd/impl/WordExp$Label;)V
  #32 = NameAndType        #30:#31        // "<init>":(Lscala/xml/dtd/impl/WordExp;Lscala/xml/dtd/impl/WordExp$Label;)V
  #33 = Methodref          #15.#32        // scala/xml/dtd/impl/WordExp$Letter."<init>":(Lscala/xml/dtd/impl/WordExp;Lscala/xml/dtd/impl/WordExp$Label;)V
  #34 = Utf8               Lscala/xml/dtd/impl/WordExp$Label;
  #35 = Utf8               unapply
  #36 = Utf8               (Lscala/xml/dtd/impl/WordExp$Letter;)Lscala/Option;
  #37 = Utf8               (Lscala/xml/dtd/impl/WordExp$Letter;)Lscala/Option<Lscala/xml/dtd/impl/WordExp$Label;>;
  #38 = Utf8               x$0
  #39 = Utf8               scala/None$
  #40 = Class              #39            // scala/None$
  #41 = Utf8               MODULE$
  #42 = Utf8               Lscala/None$;
  #43 = NameAndType        #41:#42        // MODULE$:Lscala/None$;
  #44 = Fieldref           #40.#43        // scala/None$.MODULE$:Lscala/None$;
  #45 = Utf8               scala/Some
  #46 = Class              #45            // scala/Some
  #47 = Utf8               ()Lscala/xml/dtd/impl/WordExp$Label;
  #48 = NameAndType        #27:#47        // a:()Lscala/xml/dtd/impl/WordExp$Label;
  #49 = Methodref          #15.#48        // scala/xml/dtd/impl/WordExp$Letter.a:()Lscala/xml/dtd/impl/WordExp$Label;
  #50 = Utf8               (Ljava/lang/Object;)V
  #51 = NameAndType        #30:#50        // "<init>":(Ljava/lang/Object;)V
  #52 = Methodref          #46.#51        // scala/Some."<init>":(Ljava/lang/Object;)V
  #53 = Utf8               Lscala/xml/dtd/impl/WordExp$Letter;
  #54 = Utf8               scala/Option
  #55 = Class              #54            // scala/Option
  #56 = Utf8               (Ljava/lang/Object;)Ljava/lang/Object;
  #57 = Utf8               v1
  #58 = NameAndType        #25:#26        // apply:(Lscala/xml/dtd/impl/WordExp$Label;)Lscala/xml/dtd/impl/WordExp$Letter;
  #59 = Methodref          #2.#58         // scala/xml/dtd/impl/WordExp$Letter$.apply:(Lscala/xml/dtd/impl/WordExp$Label;)Lscala/xml/dtd/impl/WordExp$Letter;
  #60 = Utf8               Ljava/lang/Object;
  #61 = Utf8               (Lscala/xml/dtd/impl/WordExp;)V
  #62 = Utf8               ()V
  #63 = NameAndType        #30:#62        // "<init>":()V
  #64 = Methodref          #5.#63         // scala/runtime/AbstractFunction1."<init>":()V
  #65 = Utf8               Code
  #66 = Utf8               LineNumberTable
  #67 = Utf8               LocalVariableTable
  #68 = Utf8               MethodParameters
  #69 = Utf8               StackMapTable
  #70 = Utf8               Signature
  #71 = Utf8               InnerClasses
  #72 = Utf8               SourceFile
  #73 = Utf8               ScalaInlineInfo
  #74 = Utf8               Scala
{
  private final scala.xml.dtd.impl.WordExp $outer;
    descriptor: Lscala/xml/dtd/impl/WordExp;
    flags: (0x1012) ACC_PRIVATE, ACC_FINAL, ACC_SYNTHETIC

  public final java.lang.String toString();
    descriptor: ()Ljava/lang/String;
    flags: (0x0011) ACC_PUBLIC, ACC_FINAL
    Code:
      stack=1, locals=1, args_size=1
         0: ldc           #22                 // String Letter
         2: areturn
      LineNumberTable:
        line 51: 0
      LocalVariableTable:
        Start  Length  Slot  Name   Signature
            0       3     0  this   Lscala/xml/dtd/impl/WordExp$Letter$;

  public scala.xml.dtd.impl.WordExp$Letter apply(scala.xml.dtd.impl.WordExp$Label);
    descriptor: (Lscala/xml/dtd/impl/WordExp$Label;)Lscala/xml/dtd/impl/WordExp$Letter;
    flags: (0x0001) ACC_PUBLIC
    Code:
      stack=4, locals=2, args_size=2
         0: new           #15                 // class scala/xml/dtd/impl/WordExp$Letter
         3: dup
         4: aload_0
         5: getfield      #29                 // Field $outer:Lscala/xml/dtd/impl/WordExp;
         8: aload_1
         9: invokespecial #33                 // Method scala/xml/dtd/impl/WordExp$Letter."<init>":(Lscala/xml/dtd/impl/WordExp;Lscala/xml/dtd/impl/WordExp$Label;)V
        12: areturn
      LineNumberTable:
        line 51: 0
      LocalVariableTable:
        Start  Length  Slot  Name   Signature
            0      13     0  this   Lscala/xml/dtd/impl/WordExp$Letter$;
            0      13     1     a   Lscala/xml/dtd/impl/WordExp$Label;
    MethodParameters:
      Name                           Flags
      a                              final

  public scala.Option<scala.xml.dtd.impl.WordExp$Label> unapply(scala.xml.dtd.impl.WordExp$Letter);
    descriptor: (Lscala/xml/dtd/impl/WordExp$Letter;)Lscala/Option;
    flags: (0x0001) ACC_PUBLIC
    Code:
      stack=3, locals=2, args_size=2
         0: aload_1
         1: ifnonnull     10
         4: getstatic     #44                 // Field scala/None$.MODULE$:Lscala/None$;
         7: goto          21
        10: new           #46                 // class scala/Some
        13: dup
        14: aload_1
        15: invokevirtual #49                 // Method scala/xml/dtd/impl/WordExp$Letter.a:()Lscala/xml/dtd/impl/WordExp$Label;
        18: invokespecial #52                 // Method scala/Some."<init>":(Ljava/lang/Object;)V
        21: areturn
      StackMapTable: number_of_entries = 2
        frame_type = 10 /* same */
        frame_type = 74 /* same_locals_1_stack_item */
          stack = [ class scala/Option ]
      LineNumberTable:
        line 51: 0
      LocalVariableTable:
        Start  Length  Slot  Name   Signature
            0      22     0  this   Lscala/xml/dtd/impl/WordExp$Letter$;
            0      22     1   x$0   Lscala/xml/dtd/impl/WordExp$Letter;
    Signature: #37                          // (Lscala/xml/dtd/impl/WordExp$Letter;)Lscala/Option<Lscala/xml/dtd/impl/WordExp$Label;>;
    MethodParameters:
      Name                           Flags
      x$0                            final

  public java.lang.Object apply(java.lang.Object);
    descriptor: (Ljava/lang/Object;)Ljava/lang/Object;
    flags: (0x1041) ACC_PUBLIC, ACC_BRIDGE, ACC_SYNTHETIC
    Code:
      stack=2, locals=2, args_size=2
         0: aload_0
         1: aload_1
         2: checkcast     #10                 // class scala/xml/dtd/impl/WordExp$Label
         5: invokevirtual #59                 // Method apply:(Lscala/xml/dtd/impl/WordExp$Label;)Lscala/xml/dtd/impl/WordExp$Letter;
         8: areturn
      LineNumberTable:
        line 51: 0
      LocalVariableTable:
        Start  Length  Slot  Name   Signature
            0       9     0  this   Lscala/xml/dtd/impl/WordExp$Letter$;
            0       9     1    v1   Ljava/lang/Object;
    MethodParameters:
      Name                           Flags
      v1                             final

  public scala.xml.dtd.impl.WordExp$Letter$(scala.xml.dtd.impl.WordExp);
    descriptor: (Lscala/xml/dtd/impl/WordExp;)V
    flags: (0x0001) ACC_PUBLIC
    Code:
      stack=2, locals=2, args_size=2
         0: aload_1
         1: ifnonnull     6
         4: aconst_null
         5: athrow
         6: aload_0
         7: aload_1
         8: putfield      #29                 // Field $outer:Lscala/xml/dtd/impl/WordExp;
        11: aload_0
        12: invokespecial #64                 // Method scala/runtime/AbstractFunction1."<init>":()V
        15: return
      StackMapTable: number_of_entries = 1
        frame_type = 6 /* same */
      LineNumberTable:
        line 51: 0
      LocalVariableTable:
        Start  Length  Slot  Name   Signature
            0      16     0  this   Lscala/xml/dtd/impl/WordExp$Letter$;
            0      16     1 $outer   Lscala/xml/dtd/impl/WordExp;
    MethodParameters:
      Name                           Flags
      $outer                         final synthetic
}
InnerClasses:
  public abstract #13= #10 of #12;        // Label=class scala/xml/dtd/impl/WordExp$Label of class scala/xml/dtd/impl/WordExp
  public #16= #15 of #12;                 // Letter=class scala/xml/dtd/impl/WordExp$Letter of class scala/xml/dtd/impl/WordExp
  public #17= #2 of #12;                  // Letter$=class scala/xml/dtd/impl/WordExp$Letter$ of class scala/xml/dtd/impl/WordExp
Signature: #3                           // Lscala/runtime/AbstractFunction1<Lscala/xml/dtd/impl/WordExp$Label;Lscala/xml/dtd/impl/WordExp$Letter;>;Ljava/io/Serializable;
SourceFile: "WordExp.scala"
  ScalaInlineInfo: length = 0x1D (unknown attribute)
   01 01 00 05 00 1E 00 3D 01 00 19 00 38 01 00 19
   00 1A 01 00 14 00 15 01 00 23 00 24 01
  Scala: length = 0x0 (unknown attribute)

