Classfile /Users/mw/Projects/slang-braindump/.jar/jar8/assemble/slang-braindump/assemble/content/org/scalatest/enablers/AggregatingImpls.class
  Last modified May 29, 2022; size 20442 bytes
  SHA-256 checksum 310e73fbf190519b0f0bd9526de827fed54bf2a28c65a0f3318ed302b36e0287
  Compiled from "Aggregating.scala"
public interface org.scalatest.enablers.AggregatingImpls
  minor version: 0
  major version: 52
  flags: (0x0601) ACC_PUBLIC, ACC_INTERFACE, ACC_ABSTRACT
  this_class: #2                          // org/scalatest/enablers/AggregatingImpls
  super_class: #4                         // java/lang/Object
  interfaces: 0, fields: 0, methods: 48, attributes: 6
Constant pool:
    #1 = Utf8               org/scalatest/enablers/AggregatingImpls
    #2 = Class              #1            // org/scalatest/enablers/AggregatingImpls
    #3 = Utf8               java/lang/Object
    #4 = Class              #3            // java/lang/Object
    #5 = Utf8               Aggregating.scala
    #6 = Utf8               Lscala/reflect/ScalaSignature;
    #7 = Utf8               bytes
    #8 = Utf8               \u0006\u0005A4qa\u0002\u0005\u0011\u0002\u0007\u0005q\u0002C\u0003\u0017\u0001\u0011\u0005q\u0003\u0003\u0004\u001c\u0001\u0011\u0005!\u0002\b\u0005\u0007q\u0001!\tAC\u001d\t\rI\u0003A\u0011\u0001\u0006T\u0011\u0019a\u0006\u0001\"\u0001\u000b;\"1a\r\u0001C\u0001\u0015\u001d\u0014\u0001#Q4he\u0016<\u0017\r^5oO&k\u0007\u000f\\:\u000b\u0005%Q\u0011\u0001C3oC\ndWM]:\u000b\u0005-a\u0011!C:dC2\fG/Z:u\u0015\u0005i\u0011aA8sO\u000e\u00011C\u0001\u0001\u0011!\t\tB#D\u0001\u0013\u0015\u0005\u0019\u0012!B:dC2\f\u0017BA\u000b\u0013\u0005\u0019\te.\u001f*fM\u00061A%\u001b8ji\u0012\"\u0012\u0001\u0007\t\u0003#eI!A\u0007\n\u0003\tUs\u0017\u000e^\u0001\fiJLX)];bY&$\u00180\u0006\u0002\u001eeQ!a$\t\u0014)!\t\tr$\u0003\u0002!%\t9!i\\8mK\u0006t\u0007\"\u0002\u0012\u0003\u0001\u0004\u0019\u0013\u0001\u00027fMR\u0004\"!\u0005\u0013\n\u0005\u0015\u0012\"aA!os\")qE\u0001a\u0001G\u0005)!/[4ii\")\u0011F\u0001a\u0001U\u0005AQ-];bY&$\u0018\u0010E\u0002,]Aj\u0011\u0001\f\u0006\u0003[1\t\u0011b]2bY\u0006\u001cG/[2\n\u0005=b#\u0001C#rk\u0006d\u0017\u000e^=\u0011\u0005E\u0012D\u0002\u0001\u0003\u0006g\t\u0011\r\u0001\u000e\u0002\u0002)F\u0011Qg\t\t\u0003#YJ!a\u000e\n\u0003\u000f9{G\u000f[5oO\u000612\r[3dWRCWmU1nK\u0016cW-\\3oiN\f5/\u0006\u0002;\u001bR!ad\u000f(Q\u0011\u0015\u00113\u00011\u0001=!\ri\u0014\n\u0014\b\u0003}\u0019s!a\u0010#\u000f\u0005\u0001\u001bU\"A!\u000b\u0005\ts\u0011A\u0002\u001fs_>$h(C\u0001\u0014\u0013\t)%#\u0001\u0006d_2dWm\u0019;j_:L!a\u0012%\u0002\u000fA\f7m[1hK*\u0011QIE\u0005\u0003\u0015.\u0013abR3o)J\fg/\u001a:tC\ndWM\u0003\u0002H\u0011B\u0011\u0011\'\u0014\u0003\u0006g\r\u0011\r\u0001\u000e\u0005\u0006O\r\u0001\ra\u0014\t\u0004{%\u001b\u0003\"B\u0015\u0004\u0001\u0004\t\u0006cA\u0016/\u0019\u0006I1\r[3dW>sG._\u000b\u0003)b#BAH+Z5\")!\u0005\u0002a\u0001-B\u0019Q(S,\u0011\u0005EBF!B\u001a\u0005\u0005\u0004!\u0004\"B\u0014\u0005\u0001\u0004y\u0005\"B\u0015\u0005\u0001\u0004Y\u0006cA\u0016//\u0006Q1\r[3dW\u0006cGn\u00144\u0016\u0005y\u0013G\u0003\u0002\u0010`G\u0012DQAI\u0003A\u0002\u0001\u00042!P%b!\t\t$\rB\u00034\u000b\t\u0007A\u0007C\u0003(\u000b\u0001\u0007q\nC\u0003*\u000b\u0001\u0007Q\rE\u0002,]\u0005\f\u0001c\u00195fG.\fE/T8ti>sWm\u00144\u0016\u0005!dG\u0003\u0002\u0010j[:DQA\t\u0004A\u0002)\u00042!P%l!\t\tD\u000eB\u00034\r\t\u0007A\u0007C\u0003(\r\u0001\u0007q\nC\u0003*\r\u0001\u0007q\u000eE\u0002,]-\u0004
    #9 = Utf8               java/lang/invoke/MethodHandles$Lookup
   #10 = Class              #9            // java/lang/invoke/MethodHandles$Lookup
   #11 = Utf8               java/lang/invoke/MethodHandles
   #12 = Class              #11           // java/lang/invoke/MethodHandles
   #13 = Utf8               Lookup
   #14 = Utf8               org/scalatest/enablers/AggregatingImpls$ElementCount$1
   #15 = Class              #14           // org/scalatest/enablers/AggregatingImpls$ElementCount$1
   #16 = Utf8               ElementCount$1
   #17 = Utf8               org/scalatest/enablers/AggregatingImpls$ElementCount$2$
   #18 = Class              #17           // org/scalatest/enablers/AggregatingImpls$ElementCount$2$
   #19 = Utf8               ElementCount$2$
   #20 = Utf8               org/scalatest/enablers/AggregatingImpls$ZipNoMatch$1$
   #21 = Class              #20           // org/scalatest/enablers/AggregatingImpls$ZipNoMatch$1$
   #22 = Utf8               ZipNoMatch$1$
   #23 = Utf8               tryEquality$
   #24 = Utf8               (Lorg/scalatest/enablers/AggregatingImpls;Ljava/lang/Object;Ljava/lang/Object;Lorg/scalactic/Equality;)Z
   #25 = Utf8               $this
   #26 = Utf8               left
   #27 = Utf8               right
   #28 = Utf8               equality
   #29 = Utf8               tryEquality
   #30 = Utf8               (Ljava/lang/Object;Ljava/lang/Object;Lorg/scalactic/Equality;)Z
   #31 = NameAndType        #29:#30       // tryEquality:(Ljava/lang/Object;Ljava/lang/Object;Lorg/scalactic/Equality;)Z
   #32 = InterfaceMethodref #2.#31        // org/scalatest/enablers/AggregatingImpls.tryEquality:(Ljava/lang/Object;Ljava/lang/Object;Lorg/scalactic/Equality;)Z
   #33 = Utf8               Lorg/scalatest/enablers/AggregatingImpls;
   #34 = Utf8               Ljava/lang/Object;
   #35 = Utf8               Lorg/scalactic/Equality;
   #36 = Utf8               <T:Ljava/lang/Object;>(Ljava/lang/Object;Ljava/lang/Object;Lorg/scalactic/Equality<TT;>;)Z
   #37 = Utf8               java/lang/ClassCastException
   #38 = Class              #37           // java/lang/ClassCastException
   #39 = Utf8               org/scalactic/Equality
   #40 = Class              #39           // org/scalactic/Equality
   #41 = Utf8               areEqual
   #42 = Utf8               (Ljava/lang/Object;Ljava/lang/Object;)Z
   #43 = NameAndType        #41:#42       // areEqual:(Ljava/lang/Object;Ljava/lang/Object;)Z
   #44 = InterfaceMethodref #40.#43       // org/scalactic/Equality.areEqual:(Ljava/lang/Object;Ljava/lang/Object;)Z
   #45 = Utf8               cce
   #46 = Utf8               Ljava/lang/ClassCastException;
   #47 = Utf8               this
   #48 = Utf8               checkTheSameElementsAs$
   #49 = Utf8               (Lorg/scalatest/enablers/AggregatingImpls;Lscala/collection/Iterable;Lscala/collection/Iterable;Lorg/scalactic/Equality;)Z
   #50 = Utf8               checkTheSameElementsAs
   #51 = Utf8               (Lscala/collection/Iterable;Lscala/collection/Iterable;Lorg/scalactic/Equality;)Z
   #52 = NameAndType        #50:#51       // checkTheSameElementsAs:(Lscala/collection/Iterable;Lscala/collection/Iterable;Lorg/scalactic/Equality;)Z
   #53 = InterfaceMethodref #2.#52        // org/scalatest/enablers/AggregatingImpls.checkTheSameElementsAs:(Lscala/collection/Iterable;Lscala/collection/Iterable;Lorg/scalactic/Equality;)Z
   #54 = Utf8               Lscala/collection/Iterable;
   #55 = Utf8               <T:Ljava/lang/Object;>(Lscala/collection/Iterable<TT;>;Lscala/collection/Iterable<Ljava/lang/Object;>;Lorg/scalactic/Equality<TT;>;)Z
   #56 = Utf8               scala/runtime/NonLocalReturnControl
   #57 = Class              #56           // scala/runtime/NonLocalReturnControl
   #58 = Utf8               <init>
   #59 = Utf8               ()V
   #60 = NameAndType        #58:#59       // "<init>":()V
   #61 = Methodref          #4.#60        // java/lang/Object."<init>":()V
   #62 = Utf8               scala/runtime/LazyRef
   #63 = Class              #62           // scala/runtime/LazyRef
   #64 = Methodref          #63.#60       // scala/runtime/LazyRef."<init>":()V
   #65 = Utf8               org/scalactic/ColCompatHelper$
   #66 = Class              #65           // org/scalactic/ColCompatHelper$
   #67 = Utf8               MODULE$
   #68 = Utf8               Lorg/scalactic/ColCompatHelper$;
   #69 = NameAndType        #67:#68       // MODULE$:Lorg/scalactic/ColCompatHelper$;
   #70 = Fieldref           #66.#69       // org/scalactic/ColCompatHelper$.MODULE$:Lorg/scalactic/ColCompatHelper$;
   #71 = Utf8               scala/collection/Iterable
   #72 = Class              #71           // scala/collection/Iterable
   #73 = Utf8               toIterable
   #74 = Utf8               ()Lscala/collection/Iterable;
   #75 = NameAndType        #73:#74       // toIterable:()Lscala/collection/Iterable;
   #76 = InterfaceMethodref #72.#75       // scala/collection/Iterable.toIterable:()Lscala/collection/Iterable;
   #77 = Utf8               ZipNoMatch$2
   #78 = Utf8               (Lscala/runtime/LazyRef;)Lorg/scalatest/enablers/AggregatingImpls$ZipNoMatch$1$;
   #79 = NameAndType        #77:#78       // ZipNoMatch$2:(Lscala/runtime/LazyRef;)Lorg/scalatest/enablers/AggregatingImpls$ZipNoMatch$1$;
   #80 = InterfaceMethodref #2.#79        // org/scalatest/enablers/AggregatingImpls.ZipNoMatch$2:(Lscala/runtime/LazyRef;)Lorg/scalatest/enablers/AggregatingImpls$ZipNoMatch$1$;
   #81 = Utf8               zipAll
   #82 = Utf8               (Lscala/collection/Iterable;Ljava/lang/Object;Ljava/lang/Object;)Ljava/lang/Object;
   #83 = NameAndType        #81:#82       // zipAll:(Lscala/collection/Iterable;Ljava/lang/Object;Ljava/lang/Object;)Ljava/lang/Object;
   #84 = InterfaceMethodref #72.#83       // scala/collection/Iterable.zipAll:(Lscala/collection/Iterable;Ljava/lang/Object;Ljava/lang/Object;)Ljava/lang/Object;
   #85 = Utf8               ()Ljava/lang/Object;
   #86 = MethodType         #85           //  ()Ljava/lang/Object;
   #87 = Utf8               $anonfun$checkTheSameElementsAs$3
   #88 = Utf8               ()Lscala/collection/immutable/IndexedSeq;
   #89 = NameAndType        #87:#88       // $anonfun$checkTheSameElementsAs$3:()Lscala/collection/immutable/IndexedSeq;
   #90 = InterfaceMethodref #2.#89        // org/scalatest/enablers/AggregatingImpls.$anonfun$checkTheSameElementsAs$3:()Lscala/collection/immutable/IndexedSeq;
   #91 = MethodHandle       6:#90         // REF_invokeStatic org/scalatest/enablers/AggregatingImpls.$anonfun$checkTheSameElementsAs$3:()Lscala/collection/immutable/IndexedSeq;
   #92 = MethodType         #88           //  ()Lscala/collection/immutable/IndexedSeq;
   #93 = Integer            5
   #94 = Integer            1
   #95 = Utf8               java/lang/invoke/LambdaMetafactory
   #96 = Class              #95           // java/lang/invoke/LambdaMetafactory
   #97 = Utf8               altMetafactory
   #98 = Utf8               (Ljava/lang/invoke/MethodHandles$Lookup;Ljava/lang/String;Ljava/lang/invoke/MethodType;[Ljava/lang/Object;)Ljava/lang/invoke/CallSite;
   #99 = NameAndType        #97:#98       // altMetafactory:(Ljava/lang/invoke/MethodHandles$Lookup;Ljava/lang/String;Ljava/lang/invoke/MethodType;[Ljava/lang/Object;)Ljava/lang/invoke/CallSite;
  #100 = Methodref          #96.#99       // java/lang/invoke/LambdaMetafactory.altMetafactory:(Ljava/lang/invoke/MethodHandles$Lookup;Ljava/lang/String;Ljava/lang/invoke/MethodType;[Ljava/lang/Object;)Ljava/lang/invoke/CallSite;
  #101 = MethodHandle       6:#100        // REF_invokeStatic java/lang/invoke/LambdaMetafactory.altMetafactory:(Ljava/lang/invoke/MethodHandles$Lookup;Ljava/lang/String;Ljava/lang/invoke/MethodType;[Ljava/lang/Object;)Ljava/lang/invoke/CallSite;
  #102 = Utf8               apply
  #103 = Utf8               ()Lscala/Function0;
  #104 = NameAndType        #102:#103     // apply:()Lscala/Function0;
  #105 = InvokeDynamic      #0:#104       // #0:apply:()Lscala/Function0;
  #106 = Utf8               (Ljava/lang/Object;Ljava/lang/Object;)Ljava/lang/Object;
  #107 = MethodType         #106          //  (Ljava/lang/Object;Ljava/lang/Object;)Ljava/lang/Object;
  #108 = Utf8               $anonfun$checkTheSameElementsAs$4
  #109 = Utf8               (Lorg/scalatest/enablers/AggregatingImpls;Ljava/lang/Object;Lscala/runtime/LazyRef;Lorg/scalactic/Equality;Lscala/runtime/LazyRef;Lscala/collection/immutable/IndexedSeq;Lscala/Tuple2;)Lscala/collection/immutable/IndexedSeq;
  #110 = NameAndType        #108:#109     // $anonfun$checkTheSameElementsAs$4:(Lorg/scalatest/enablers/AggregatingImpls;Ljava/lang/Object;Lscala/runtime/LazyRef;Lorg/scalactic/Equality;Lscala/runtime/LazyRef;Lscala/collection/immutable/IndexedSeq;Lscala/Tuple2;)Lscala/collection/immutable/IndexedSeq;
  #111 = InterfaceMethodref #2.#110       // org/scalatest/enablers/AggregatingImpls.$anonfun$checkTheSameElementsAs$4:(Lorg/scalatest/enablers/AggregatingImpls;Ljava/lang/Object;Lscala/runtime/LazyRef;Lorg/scalactic/Equality;Lscala/runtime/LazyRef;Lscala/collection/immutable/IndexedSeq;Lscala/Tuple2;)Lscala/collection/immutable/IndexedSeq;
  #112 = MethodHandle       6:#111        // REF_invokeStatic org/scalatest/enablers/AggregatingImpls.$anonfun$checkTheSameElementsAs$4:(Lorg/scalatest/enablers/AggregatingImpls;Ljava/lang/Object;Lscala/runtime/LazyRef;Lorg/scalactic/Equality;Lscala/runtime/LazyRef;Lscala/collection/immutable/IndexedSeq;Lscala/Tuple2;)Lscala/collection/immutable/IndexedSeq;
  #113 = Utf8               (Lscala/collection/immutable/IndexedSeq;Lscala/Tuple2;)Lscala/collection/immutable/IndexedSeq;
  #114 = MethodType         #113          //  (Lscala/collection/immutable/IndexedSeq;Lscala/Tuple2;)Lscala/collection/immutable/IndexedSeq;
  #115 = Utf8               (Lorg/scalatest/enablers/AggregatingImpls;Ljava/lang/Object;Lscala/runtime/LazyRef;Lorg/scalactic/Equality;Lscala/runtime/LazyRef;)Lscala/Function2;
  #116 = NameAndType        #102:#115     // apply:(Lorg/scalatest/enablers/AggregatingImpls;Ljava/lang/Object;Lscala/runtime/LazyRef;Lorg/scalactic/Equality;Lscala/runtime/LazyRef;)Lscala/Function2;
  #117 = InvokeDynamic      #1:#116       // #1:apply:(Lorg/scalatest/enablers/AggregatingImpls;Ljava/lang/Object;Lscala/runtime/LazyRef;Lorg/scalactic/Equality;Lscala/runtime/LazyRef;)Lscala/Function2;
  #118 = Utf8               $anonfun$checkTheSameElementsAs$5
  #119 = Utf8               (Lorg/scalatest/enablers/AggregatingImpls;Lorg/scalactic/Equality;Lscala/runtime/LazyRef;Lscala/collection/immutable/IndexedSeq;Lscala/collection/immutable/IndexedSeq;)Lscala/collection/immutable/IndexedSeq;
  #120 = NameAndType        #118:#119     // $anonfun$checkTheSameElementsAs$5:(Lorg/scalatest/enablers/AggregatingImpls;Lorg/scalactic/Equality;Lscala/runtime/LazyRef;Lscala/collection/immutable/IndexedSeq;Lscala/collection/immutable/IndexedSeq;)Lscala/collection/immutable/IndexedSeq;
  #121 = InterfaceMethodref #2.#120       // org/scalatest/enablers/AggregatingImpls.$anonfun$checkTheSameElementsAs$5:(Lorg/scalatest/enablers/AggregatingImpls;Lorg/scalactic/Equality;Lscala/runtime/LazyRef;Lscala/collection/immutable/IndexedSeq;Lscala/collection/immutable/IndexedSeq;)Lscala/collection/immutable/IndexedSeq;
  #122 = MethodHandle       6:#121        // REF_invokeStatic org/scalatest/enablers/AggregatingImpls.$anonfun$checkTheSameElementsAs$5:(Lorg/scalatest/enablers/AggregatingImpls;Lorg/scalactic/Equality;Lscala/runtime/LazyRef;Lscala/collection/immutable/IndexedSeq;Lscala/collection/immutable/IndexedSeq;)Lscala/collection/immutable/IndexedSeq;
  #123 = Utf8               (Lscala/collection/immutable/IndexedSeq;Lscala/collection/immutable/IndexedSeq;)Lscala/collection/immutable/IndexedSeq;
  #124 = MethodType         #123          //  (Lscala/collection/immutable/IndexedSeq;Lscala/collection/immutable/IndexedSeq;)Lscala/collection/immutable/IndexedSeq;
  #125 = Utf8               (Lorg/scalatest/enablers/AggregatingImpls;Lorg/scalactic/Equality;Lscala/runtime/LazyRef;)Lscala/Function2;
  #126 = NameAndType        #102:#125     // apply:(Lorg/scalatest/enablers/AggregatingImpls;Lorg/scalactic/Equality;Lscala/runtime/LazyRef;)Lscala/Function2;
  #127 = InvokeDynamic      #2:#126       // #2:apply:(Lorg/scalatest/enablers/AggregatingImpls;Lorg/scalactic/Equality;Lscala/runtime/LazyRef;)Lscala/Function2;
  #128 = Utf8               aggregate
  #129 = Utf8               (Lscala/collection/Iterable;Lscala/Function0;Lscala/Function2;Lscala/Function2;)Ljava/lang/Object;
  #130 = NameAndType        #128:#129     // aggregate:(Lscala/collection/Iterable;Lscala/Function0;Lscala/Function2;Lscala/Function2;)Ljava/lang/Object;
  #131 = Methodref          #66.#130      // org/scalactic/ColCompatHelper$.aggregate:(Lscala/collection/Iterable;Lscala/Function0;Lscala/Function2;Lscala/Function2;)Ljava/lang/Object;
  #132 = Utf8               scala/collection/immutable/IndexedSeq
  #133 = Class              #132          // scala/collection/immutable/IndexedSeq
  #134 = Utf8               (Ljava/lang/Object;)Ljava/lang/Object;
  #135 = MethodType         #134          //  (Ljava/lang/Object;)Ljava/lang/Object;
  #136 = Utf8               $anonfun$checkTheSameElementsAs$8$adapted
  #137 = Utf8               (Lorg/scalatest/enablers/AggregatingImpls$ElementCount$1;)Ljava/lang/Object;
  #138 = NameAndType        #136:#137     // $anonfun$checkTheSameElementsAs$8$adapted:(Lorg/scalatest/enablers/AggregatingImpls$ElementCount$1;)Ljava/lang/Object;
  #139 = InterfaceMethodref #2.#138       // org/scalatest/enablers/AggregatingImpls.$anonfun$checkTheSameElementsAs$8$adapted:(Lorg/scalatest/enablers/AggregatingImpls$ElementCount$1;)Ljava/lang/Object;
  #140 = MethodHandle       6:#139        // REF_invokeStatic org/scalatest/enablers/AggregatingImpls.$anonfun$checkTheSameElementsAs$8$adapted:(Lorg/scalatest/enablers/AggregatingImpls$ElementCount$1;)Ljava/lang/Object;
  #141 = MethodType         #137          //  (Lorg/scalatest/enablers/AggregatingImpls$ElementCount$1;)Ljava/lang/Object;
  #142 = Utf8               ()Lscala/Function1;
  #143 = NameAndType        #102:#142     // apply:()Lscala/Function1;
  #144 = InvokeDynamic      #3:#143       // #3:apply:()Lscala/Function1;
  #145 = Utf8               exists
  #146 = Utf8               (Lscala/Function1;)Z
  #147 = NameAndType        #145:#146     // exists:(Lscala/Function1;)Z
  #148 = InterfaceMethodref #133.#147     // scala/collection/immutable/IndexedSeq.exists:(Lscala/Function1;)Z
  #149 = Utf8               key
  #150 = NameAndType        #149:#85      // key:()Ljava/lang/Object;
  #151 = Methodref          #57.#150      // scala/runtime/NonLocalReturnControl.key:()Ljava/lang/Object;
  #152 = Utf8               value$mcZ$sp
  #153 = Utf8               ()Z
  #154 = NameAndType        #152:#153     // value$mcZ$sp:()Z
  #155 = Methodref          #57.#154      // scala/runtime/NonLocalReturnControl.value$mcZ$sp:()Z
  #156 = Utf8               ElementCount$module
  #157 = Utf8               Lscala/runtime/LazyRef;
  #158 = Utf8               ZipNoMatch$module
  #159 = Utf8               counts
  #160 = Utf8               Lscala/collection/immutable/IndexedSeq;
  #161 = Utf8               ex
  #162 = Utf8               Lscala/runtime/NonLocalReturnControl;
  #163 = Utf8               checkOnly$
  #164 = Utf8               checkOnly
  #165 = NameAndType        #164:#51      // checkOnly:(Lscala/collection/Iterable;Lscala/collection/Iterable;Lorg/scalactic/Equality;)Z
  #166 = InterfaceMethodref #2.#165       // org/scalatest/enablers/AggregatingImpls.checkOnly:(Lscala/collection/Iterable;Lscala/collection/Iterable;Lorg/scalactic/Equality;)Z
  #167 = Utf8               $anonfun$checkOnly$1$adapted
  #168 = Utf8               (Lorg/scalatest/enablers/AggregatingImpls;Lscala/collection/Iterable;Lorg/scalactic/Equality;Ljava/lang/Object;)Ljava/lang/Object;
  #169 = NameAndType        #167:#168     // $anonfun$checkOnly$1$adapted:(Lorg/scalatest/enablers/AggregatingImpls;Lscala/collection/Iterable;Lorg/scalactic/Equality;Ljava/lang/Object;)Ljava/lang/Object;
  #170 = InterfaceMethodref #2.#169       // org/scalatest/enablers/AggregatingImpls.$anonfun$checkOnly$1$adapted:(Lorg/scalatest/enablers/AggregatingImpls;Lscala/collection/Iterable;Lorg/scalactic/Equality;Ljava/lang/Object;)Ljava/lang/Object;
  #171 = MethodHandle       6:#170        // REF_invokeStatic org/scalatest/enablers/AggregatingImpls.$anonfun$checkOnly$1$adapted:(Lorg/scalatest/enablers/AggregatingImpls;Lscala/collection/Iterable;Lorg/scalactic/Equality;Ljava/lang/Object;)Ljava/lang/Object;
  #172 = Utf8               (Lorg/scalatest/enablers/AggregatingImpls;Lscala/collection/Iterable;Lorg/scalactic/Equality;)Lscala/Function1;
  #173 = NameAndType        #102:#172     // apply:(Lorg/scalatest/enablers/AggregatingImpls;Lscala/collection/Iterable;Lorg/scalactic/Equality;)Lscala/Function1;
  #174 = InvokeDynamic      #4:#173       // #4:apply:(Lorg/scalatest/enablers/AggregatingImpls;Lscala/collection/Iterable;Lorg/scalactic/Equality;)Lscala/Function1;
  #175 = Utf8               forall
  #176 = NameAndType        #175:#146     // forall:(Lscala/Function1;)Z
  #177 = InterfaceMethodref #72.#176      // scala/collection/Iterable.forall:(Lscala/Function1;)Z
  #178 = Utf8               $anonfun$checkOnly$3$adapted
  #179 = NameAndType        #178:#168     // $anonfun$checkOnly$3$adapted:(Lorg/scalatest/enablers/AggregatingImpls;Lscala/collection/Iterable;Lorg/scalactic/Equality;Ljava/lang/Object;)Ljava/lang/Object;
  #180 = InterfaceMethodref #2.#179       // org/scalatest/enablers/AggregatingImpls.$anonfun$checkOnly$3$adapted:(Lorg/scalatest/enablers/AggregatingImpls;Lscala/collection/Iterable;Lorg/scalactic/Equality;Ljava/lang/Object;)Ljava/lang/Object;
  #181 = MethodHandle       6:#180        // REF_invokeStatic org/scalatest/enablers/AggregatingImpls.$anonfun$checkOnly$3$adapted:(Lorg/scalatest/enablers/AggregatingImpls;Lscala/collection/Iterable;Lorg/scalactic/Equality;Ljava/lang/Object;)Ljava/lang/Object;
  #182 = InvokeDynamic      #5:#173       // #5:apply:(Lorg/scalatest/enablers/AggregatingImpls;Lscala/collection/Iterable;Lorg/scalactic/Equality;)Lscala/Function1;
  #183 = Utf8               checkAllOf$
  #184 = Utf8               checkAllOf
  #185 = NameAndType        #184:#51      // checkAllOf:(Lscala/collection/Iterable;Lscala/collection/Iterable;Lorg/scalactic/Equality;)Z
  #186 = InterfaceMethodref #2.#185       // org/scalatest/enablers/AggregatingImpls.checkAllOf:(Lscala/collection/Iterable;Lscala/collection/Iterable;Lorg/scalactic/Equality;)Z
  #187 = Utf8               toIterator
  #188 = Utf8               ()Lscala/collection/Iterator;
  #189 = NameAndType        #187:#188     // toIterator:()Lscala/collection/Iterator;
  #190 = InterfaceMethodref #72.#189      // scala/collection/Iterable.toIterator:()Lscala/collection/Iterator;
  #191 = Utf8               checkEqual$1
  #192 = Utf8               (Lscala/collection/Iterable;Lscala/collection/Iterator;Lorg/scalactic/Equality;)Z
  #193 = NameAndType        #191:#192     // checkEqual$1:(Lscala/collection/Iterable;Lscala/collection/Iterator;Lorg/scalactic/Equality;)Z
  #194 = InterfaceMethodref #2.#193       // org/scalatest/enablers/AggregatingImpls.checkEqual$1:(Lscala/collection/Iterable;Lscala/collection/Iterator;Lorg/scalactic/Equality;)Z
  #195 = Utf8               checkAtMostOneOf$
  #196 = Utf8               checkAtMostOneOf
  #197 = NameAndType        #196:#51      // checkAtMostOneOf:(Lscala/collection/Iterable;Lscala/collection/Iterable;Lorg/scalactic/Equality;)Z
  #198 = InterfaceMethodref #2.#197       // org/scalatest/enablers/AggregatingImpls.checkAtMostOneOf:(Lscala/collection/Iterable;Lscala/collection/Iterable;Lorg/scalactic/Equality;)Z
  #199 = Utf8               countElements$1
  #200 = Utf8               (Lscala/collection/Iterable;Lscala/collection/Iterable;Lorg/scalactic/Equality;)I
  #201 = NameAndType        #199:#200     // countElements$1:(Lscala/collection/Iterable;Lscala/collection/Iterable;Lorg/scalactic/Equality;)I
  #202 = InterfaceMethodref #2.#201       // org/scalatest/enablers/AggregatingImpls.countElements$1:(Lscala/collection/Iterable;Lscala/collection/Iterable;Lorg/scalactic/Equality;)I
  #203 = Utf8               count
  #204 = Utf8               I
  #205 = Utf8               ElementCount$lzycompute$1
  #206 = Utf8               (Lscala/runtime/LazyRef;)Lorg/scalatest/enablers/AggregatingImpls$ElementCount$2$;
  #207 = Utf8               ElementCount$module$1
  #208 = Utf8               initialized
  #209 = NameAndType        #208:#153     // initialized:()Z
  #210 = Methodref          #63.#209      // scala/runtime/LazyRef.initialized:()Z
  #211 = Utf8               value
  #212 = NameAndType        #211:#85      // value:()Ljava/lang/Object;
  #213 = Methodref          #63.#212      // scala/runtime/LazyRef.value:()Ljava/lang/Object;
  #214 = Utf8               (Lorg/scalatest/enablers/AggregatingImpls;)V
  #215 = NameAndType        #58:#214      // "<init>":(Lorg/scalatest/enablers/AggregatingImpls;)V
  #216 = Methodref          #18.#215      // org/scalatest/enablers/AggregatingImpls$ElementCount$2$."<init>":(Lorg/scalatest/enablers/AggregatingImpls;)V
  #217 = Utf8               initialize
  #218 = NameAndType        #217:#134     // initialize:(Ljava/lang/Object;)Ljava/lang/Object;
  #219 = Methodref          #63.#218      // scala/runtime/LazyRef.initialize:(Ljava/lang/Object;)Ljava/lang/Object;
  #220 = Utf8               java/lang/Throwable
  #221 = Class              #220          // java/lang/Throwable
  #222 = Utf8               ElementCount$3
  #223 = NameAndType        #205:#206     // ElementCount$lzycompute$1:(Lscala/runtime/LazyRef;)Lorg/scalatest/enablers/AggregatingImpls$ElementCount$2$;
  #224 = InterfaceMethodref #2.#223       // org/scalatest/enablers/AggregatingImpls.ElementCount$lzycompute$1:(Lscala/runtime/LazyRef;)Lorg/scalatest/enablers/AggregatingImpls$ElementCount$2$;
  #225 = Utf8               ZipNoMatch$lzycompute$1
  #226 = Utf8               ZipNoMatch$module$1
  #227 = Methodref          #21.#215      // org/scalatest/enablers/AggregatingImpls$ZipNoMatch$1$."<init>":(Lorg/scalatest/enablers/AggregatingImpls;)V
  #228 = NameAndType        #225:#78      // ZipNoMatch$lzycompute$1:(Lscala/runtime/LazyRef;)Lorg/scalatest/enablers/AggregatingImpls$ZipNoMatch$1$;
  #229 = InterfaceMethodref #2.#228       // org/scalatest/enablers/AggregatingImpls.ZipNoMatch$lzycompute$1:(Lscala/runtime/LazyRef;)Lorg/scalatest/enablers/AggregatingImpls$ZipNoMatch$1$;
  #230 = Utf8               $anonfun$checkTheSameElementsAs$1
  #231 = Utf8               (Lorg/scalatest/enablers/AggregatingImpls;Ljava/lang/Object;Lorg/scalactic/Equality;Lorg/scalatest/enablers/AggregatingImpls$ElementCount$1;)Z
  #232 = Utf8               next$1
  #233 = Utf8               equality$1
  #234 = Utf8               ec
  #235 = Utf8               element
  #236 = NameAndType        #235:#85      // element:()Ljava/lang/Object;
  #237 = Methodref          #15.#236      // org/scalatest/enablers/AggregatingImpls$ElementCount$1.element:()Ljava/lang/Object;
  #238 = Utf8               Lorg/scalatest/enablers/AggregatingImpls$ElementCount$1;
  #239 = Utf8               leftNewCount$1
  #240 = Utf8               (Ljava/lang/Object;Lscala/collection/immutable/IndexedSeq;Lorg/scalactic/Equality;Lscala/runtime/LazyRef;)Lscala/collection/immutable/IndexedSeq;
  #241 = Utf8               next
  #242 = Utf8               $anonfun$checkTheSameElementsAs$1$adapted
  #243 = Utf8               (Lorg/scalatest/enablers/AggregatingImpls;Ljava/lang/Object;Lorg/scalactic/Equality;Lorg/scalatest/enablers/AggregatingImpls$ElementCount$1;)Ljava/lang/Object;
  #244 = NameAndType        #242:#243     // $anonfun$checkTheSameElementsAs$1$adapted:(Lorg/scalatest/enablers/AggregatingImpls;Ljava/lang/Object;Lorg/scalactic/Equality;Lorg/scalatest/enablers/AggregatingImpls$ElementCount$1;)Ljava/lang/Object;
  #245 = InterfaceMethodref #2.#244       // org/scalatest/enablers/AggregatingImpls.$anonfun$checkTheSameElementsAs$1$adapted:(Lorg/scalatest/enablers/AggregatingImpls;Ljava/lang/Object;Lorg/scalactic/Equality;Lorg/scalatest/enablers/AggregatingImpls$ElementCount$1;)Ljava/lang/Object;
  #246 = MethodHandle       6:#245        // REF_invokeStatic org/scalatest/enablers/AggregatingImpls.$anonfun$checkTheSameElementsAs$1$adapted:(Lorg/scalatest/enablers/AggregatingImpls;Ljava/lang/Object;Lorg/scalactic/Equality;Lorg/scalatest/enablers/AggregatingImpls$ElementCount$1;)Ljava/lang/Object;
  #247 = Utf8               (Lorg/scalatest/enablers/AggregatingImpls;Ljava/lang/Object;Lorg/scalactic/Equality;)Lscala/Function1;
  #248 = NameAndType        #102:#247     // apply:(Lorg/scalatest/enablers/AggregatingImpls;Ljava/lang/Object;Lorg/scalactic/Equality;)Lscala/Function1;
  #249 = InvokeDynamic      #6:#248       // #6:apply:(Lorg/scalatest/enablers/AggregatingImpls;Ljava/lang/Object;Lorg/scalactic/Equality;)Lscala/Function1;
  #250 = Utf8               indexWhere
  #251 = Utf8               (Lscala/Function1;)I
  #252 = NameAndType        #250:#251     // indexWhere:(Lscala/Function1;)I
  #253 = InterfaceMethodref #133.#252     // scala/collection/immutable/IndexedSeq.indexWhere:(Lscala/Function1;)I
  #254 = Utf8               (I)Ljava/lang/Object;
  #255 = NameAndType        #102:#254     // apply:(I)Ljava/lang/Object;
  #256 = InterfaceMethodref #133.#255     // scala/collection/immutable/IndexedSeq.apply:(I)Ljava/lang/Object;
  #257 = NameAndType        #222:#206     // ElementCount$3:(Lscala/runtime/LazyRef;)Lorg/scalatest/enablers/AggregatingImpls$ElementCount$2$;
  #258 = InterfaceMethodref #2.#257       // org/scalatest/enablers/AggregatingImpls.ElementCount$3:(Lscala/runtime/LazyRef;)Lorg/scalatest/enablers/AggregatingImpls$ElementCount$2$;
  #259 = Utf8               leftCount
  #260 = Utf8               ()I
  #261 = NameAndType        #259:#260     // leftCount:()I
  #262 = Methodref          #15.#261      // org/scalatest/enablers/AggregatingImpls$ElementCount$1.leftCount:()I
  #263 = Utf8               rightCount
  #264 = NameAndType        #263:#260     // rightCount:()I
  #265 = Methodref          #15.#264      // org/scalatest/enablers/AggregatingImpls$ElementCount$1.rightCount:()I
  #266 = Utf8               (Ljava/lang/Object;II)Lorg/scalatest/enablers/AggregatingImpls$ElementCount$1;
  #267 = NameAndType        #102:#266     // apply:(Ljava/lang/Object;II)Lorg/scalatest/enablers/AggregatingImpls$ElementCount$1;
  #268 = Methodref          #18.#267      // org/scalatest/enablers/AggregatingImpls$ElementCount$2$.apply:(Ljava/lang/Object;II)Lorg/scalatest/enablers/AggregatingImpls$ElementCount$1;
  #269 = Utf8               updated
  #270 = Utf8               (ILjava/lang/Object;)Ljava/lang/Object;
  #271 = NameAndType        #269:#270     // updated:(ILjava/lang/Object;)Ljava/lang/Object;
  #272 = InterfaceMethodref #133.#271     // scala/collection/immutable/IndexedSeq.updated:(ILjava/lang/Object;)Ljava/lang/Object;
  #273 = Utf8               $colon$plus
  #274 = NameAndType        #273:#134     // $colon$plus:(Ljava/lang/Object;)Ljava/lang/Object;
  #275 = InterfaceMethodref #133.#274     // scala/collection/immutable/IndexedSeq.$colon$plus:(Ljava/lang/Object;)Ljava/lang/Object;
  #276 = Utf8               currentElementCount
  #277 = Utf8               idx
  #278 = Utf8               $anonfun$checkTheSameElementsAs$2
  #279 = Utf8               next$2
  #280 = Utf8               rightNewCount$1
  #281 = Utf8               $anonfun$checkTheSameElementsAs$2$adapted
  #282 = NameAndType        #281:#243     // $anonfun$checkTheSameElementsAs$2$adapted:(Lorg/scalatest/enablers/AggregatingImpls;Ljava/lang/Object;Lorg/scalactic/Equality;Lorg/scalatest/enablers/AggregatingImpls$ElementCount$1;)Ljava/lang/Object;
  #283 = InterfaceMethodref #2.#282       // org/scalatest/enablers/AggregatingImpls.$anonfun$checkTheSameElementsAs$2$adapted:(Lorg/scalatest/enablers/AggregatingImpls;Ljava/lang/Object;Lorg/scalactic/Equality;Lorg/scalatest/enablers/AggregatingImpls$ElementCount$1;)Ljava/lang/Object;
  #284 = MethodHandle       6:#283        // REF_invokeStatic org/scalatest/enablers/AggregatingImpls.$anonfun$checkTheSameElementsAs$2$adapted:(Lorg/scalatest/enablers/AggregatingImpls;Ljava/lang/Object;Lorg/scalactic/Equality;Lorg/scalatest/enablers/AggregatingImpls$ElementCount$1;)Ljava/lang/Object;
  #285 = InvokeDynamic      #7:#248       // #7:apply:(Lorg/scalatest/enablers/AggregatingImpls;Ljava/lang/Object;Lorg/scalactic/Equality;)Lscala/Function1;
  #286 = Utf8               scala/package$
  #287 = Class              #286          // scala/package$
  #288 = Utf8               Lscala/package$;
  #289 = NameAndType        #67:#288      // MODULE$:Lscala/package$;
  #290 = Fieldref           #287.#289     // scala/package$.MODULE$:Lscala/package$;
  #291 = Utf8               IndexedSeq
  #292 = Utf8               ()Lscala/collection/immutable/IndexedSeq$;
  #293 = NameAndType        #291:#292     // IndexedSeq:()Lscala/collection/immutable/IndexedSeq$;
  #294 = Methodref          #287.#293     // scala/package$.IndexedSeq:()Lscala/collection/immutable/IndexedSeq$;
  #295 = Utf8               scala/collection/immutable/IndexedSeq$
  #296 = Class              #295          // scala/collection/immutable/IndexedSeq$
  #297 = Utf8               empty
  #298 = Utf8               ()Lscala/collection/SeqOps;
  #299 = NameAndType        #297:#298     // empty:()Lscala/collection/SeqOps;
  #300 = Methodref          #296.#299     // scala/collection/immutable/IndexedSeq$.empty:()Lscala/collection/SeqOps;
  #301 = Utf8               nonLocalReturnKey1$1
  #302 = Utf8               x0$1
  #303 = Utf8               x1$1
  #304 = Utf8               scala/Tuple2
  #305 = Class              #304          // scala/Tuple2
  #306 = Utf8               (Ljava/lang/Object;Ljava/lang/Object;)V
  #307 = NameAndType        #58:#306      // "<init>":(Ljava/lang/Object;Ljava/lang/Object;)V
  #308 = Methodref          #305.#307     // scala/Tuple2."<init>":(Ljava/lang/Object;Ljava/lang/Object;)V
  #309 = Utf8               _1
  #310 = NameAndType        #309:#85      // _1:()Ljava/lang/Object;
  #311 = Methodref          #305.#310     // scala/Tuple2._1:()Ljava/lang/Object;
  #312 = Utf8               _2
  #313 = NameAndType        #312:#85      // _2:()Ljava/lang/Object;
  #314 = Methodref          #305.#313     // scala/Tuple2._2:()Ljava/lang/Object;
  #315 = Utf8               equals
  #316 = Utf8               (Ljava/lang/Object;)Z
  #317 = NameAndType        #315:#316     // equals:(Ljava/lang/Object;)Z
  #318 = Methodref          #4.#317       // java/lang/Object.equals:(Ljava/lang/Object;)Z
  #319 = Utf8               scala/runtime/NonLocalReturnControl$mcZ$sp
  #320 = Class              #319          // scala/runtime/NonLocalReturnControl$mcZ$sp
  #321 = Utf8               (Ljava/lang/Object;Z)V
  #322 = NameAndType        #58:#321      // "<init>":(Ljava/lang/Object;Z)V
  #323 = Methodref          #320.#322     // scala/runtime/NonLocalReturnControl$mcZ$sp."<init>":(Ljava/lang/Object;Z)V
  #324 = NameAndType        #239:#240     // leftNewCount$1:(Ljava/lang/Object;Lscala/collection/immutable/IndexedSeq;Lorg/scalactic/Equality;Lscala/runtime/LazyRef;)Lscala/collection/immutable/IndexedSeq;
  #325 = InterfaceMethodref #2.#324       // org/scalatest/enablers/AggregatingImpls.leftNewCount$1:(Ljava/lang/Object;Lscala/collection/immutable/IndexedSeq;Lorg/scalactic/Equality;Lscala/runtime/LazyRef;)Lscala/collection/immutable/IndexedSeq;
  #326 = NameAndType        #280:#240     // rightNewCount$1:(Ljava/lang/Object;Lscala/collection/immutable/IndexedSeq;Lorg/scalactic/Equality;Lscala/runtime/LazyRef;)Lscala/collection/immutable/IndexedSeq;
  #327 = InterfaceMethodref #2.#326       // org/scalatest/enablers/AggregatingImpls.rightNewCount$1:(Ljava/lang/Object;Lscala/collection/immutable/IndexedSeq;Lorg/scalactic/Equality;Lscala/runtime/LazyRef;)Lscala/collection/immutable/IndexedSeq;
  #328 = Utf8               scala/MatchError
  #329 = Class              #328          // scala/MatchError
  #330 = Utf8               (Ljava/lang/Object;)V
  #331 = NameAndType        #58:#330      // "<init>":(Ljava/lang/Object;)V
  #332 = Methodref          #329.#331     // scala/MatchError."<init>":(Ljava/lang/Object;)V
  #333 = Utf8               nextLeft
  #334 = Utf8               nextRight
  #335 = Utf8               Lscala/Tuple2;
  #336 = Utf8               $anonfun$checkTheSameElementsAs$7
  #337 = Utf8               (Lorg/scalatest/enablers/AggregatingImpls;Lorg/scalatest/enablers/AggregatingImpls$ElementCount$1;Lorg/scalactic/Equality;Lorg/scalatest/enablers/AggregatingImpls$ElementCount$1;)Z
  #338 = Utf8               next$3
  #339 = Utf8               $anonfun$checkTheSameElementsAs$6
  #340 = Utf8               (Lorg/scalatest/enablers/AggregatingImpls;Lorg/scalactic/Equality;Lscala/runtime/LazyRef;Lscala/collection/immutable/IndexedSeq;Lorg/scalatest/enablers/AggregatingImpls$ElementCount$1;)Lscala/collection/immutable/IndexedSeq;
  #341 = Utf8               x0$3
  #342 = Utf8               x1$3
  #343 = Utf8               $anonfun$checkTheSameElementsAs$7$adapted
  #344 = Utf8               (Lorg/scalatest/enablers/AggregatingImpls;Lorg/scalatest/enablers/AggregatingImpls$ElementCount$1;Lorg/scalactic/Equality;Lorg/scalatest/enablers/AggregatingImpls$ElementCount$1;)Ljava/lang/Object;
  #345 = NameAndType        #343:#344     // $anonfun$checkTheSameElementsAs$7$adapted:(Lorg/scalatest/enablers/AggregatingImpls;Lorg/scalatest/enablers/AggregatingImpls$ElementCount$1;Lorg/scalactic/Equality;Lorg/scalatest/enablers/AggregatingImpls$ElementCount$1;)Ljava/lang/Object;
  #346 = InterfaceMethodref #2.#345       // org/scalatest/enablers/AggregatingImpls.$anonfun$checkTheSameElementsAs$7$adapted:(Lorg/scalatest/enablers/AggregatingImpls;Lorg/scalatest/enablers/AggregatingImpls$ElementCount$1;Lorg/scalactic/Equality;Lorg/scalatest/enablers/AggregatingImpls$ElementCount$1;)Ljava/lang/Object;
  #347 = MethodHandle       6:#346        // REF_invokeStatic org/scalatest/enablers/AggregatingImpls.$anonfun$checkTheSameElementsAs$7$adapted:(Lorg/scalatest/enablers/AggregatingImpls;Lorg/scalatest/enablers/AggregatingImpls$ElementCount$1;Lorg/scalactic/Equality;Lorg/scalatest/enablers/AggregatingImpls$ElementCount$1;)Ljava/lang/Object;
  #348 = Utf8               (Lorg/scalatest/enablers/AggregatingImpls;Lorg/scalatest/enablers/AggregatingImpls$ElementCount$1;Lorg/scalactic/Equality;)Lscala/Function1;
  #349 = NameAndType        #102:#348     // apply:(Lorg/scalatest/enablers/AggregatingImpls;Lorg/scalatest/enablers/AggregatingImpls$ElementCount$1;Lorg/scalactic/Equality;)Lscala/Function1;
  #350 = InvokeDynamic      #8:#349       // #8:apply:(Lorg/scalatest/enablers/AggregatingImpls;Lorg/scalatest/enablers/AggregatingImpls$ElementCount$1;Lorg/scalactic/Equality;)Lscala/Function1;
  #351 = Utf8               x0$2
  #352 = Utf8               x1$2
  #353 = NameAndType        #339:#340     // $anonfun$checkTheSameElementsAs$6:(Lorg/scalatest/enablers/AggregatingImpls;Lorg/scalactic/Equality;Lscala/runtime/LazyRef;Lscala/collection/immutable/IndexedSeq;Lorg/scalatest/enablers/AggregatingImpls$ElementCount$1;)Lscala/collection/immutable/IndexedSeq;
  #354 = InterfaceMethodref #2.#353       // org/scalatest/enablers/AggregatingImpls.$anonfun$checkTheSameElementsAs$6:(Lorg/scalatest/enablers/AggregatingImpls;Lorg/scalactic/Equality;Lscala/runtime/LazyRef;Lscala/collection/immutable/IndexedSeq;Lorg/scalatest/enablers/AggregatingImpls$ElementCount$1;)Lscala/collection/immutable/IndexedSeq;
  #355 = MethodHandle       6:#354        // REF_invokeStatic org/scalatest/enablers/AggregatingImpls.$anonfun$checkTheSameElementsAs$6:(Lorg/scalatest/enablers/AggregatingImpls;Lorg/scalactic/Equality;Lscala/runtime/LazyRef;Lscala/collection/immutable/IndexedSeq;Lorg/scalatest/enablers/AggregatingImpls$ElementCount$1;)Lscala/collection/immutable/IndexedSeq;
  #356 = Utf8               (Lscala/collection/immutable/IndexedSeq;Lorg/scalatest/enablers/AggregatingImpls$ElementCount$1;)Lscala/collection/immutable/IndexedSeq;
  #357 = MethodType         #356          //  (Lscala/collection/immutable/IndexedSeq;Lorg/scalatest/enablers/AggregatingImpls$ElementCount$1;)Lscala/collection/immutable/IndexedSeq;
  #358 = InvokeDynamic      #9:#126       // #9:apply:(Lorg/scalatest/enablers/AggregatingImpls;Lorg/scalactic/Equality;Lscala/runtime/LazyRef;)Lscala/Function2;
  #359 = Utf8               foldLeft
  #360 = Utf8               (Ljava/lang/Object;Lscala/Function2;)Ljava/lang/Object;
  #361 = NameAndType        #359:#360     // foldLeft:(Ljava/lang/Object;Lscala/Function2;)Ljava/lang/Object;
  #362 = InterfaceMethodref #133.#361     // scala/collection/immutable/IndexedSeq.foldLeft:(Ljava/lang/Object;Lscala/Function2;)Ljava/lang/Object;
  #363 = Utf8               count1
  #364 = Utf8               count2
  #365 = Utf8               $anonfun$checkTheSameElementsAs$8
  #366 = Utf8               (Lorg/scalatest/enablers/AggregatingImpls$ElementCount$1;)Z
  #367 = Utf8               e
  #368 = Utf8               $anonfun$checkOnly$2
  #369 = Utf8               (Lorg/scalatest/enablers/AggregatingImpls;Ljava/lang/Object;Lorg/scalactic/Equality;Ljava/lang/Object;)Z
  #370 = Utf8               l$1
  #371 = Utf8               equality$2
  #372 = Utf8               r
  #373 = Utf8               $anonfun$checkOnly$1
  #374 = Utf8               (Lorg/scalatest/enablers/AggregatingImpls;Lscala/collection/Iterable;Lorg/scalactic/Equality;Ljava/lang/Object;)Z
  #375 = Utf8               right$1
  #376 = Utf8               l
  #377 = Utf8               $anonfun$checkOnly$2$adapted
  #378 = Utf8               (Lorg/scalatest/enablers/AggregatingImpls;Ljava/lang/Object;Lorg/scalactic/Equality;Ljava/lang/Object;)Ljava/lang/Object;
  #379 = NameAndType        #377:#378     // $anonfun$checkOnly$2$adapted:(Lorg/scalatest/enablers/AggregatingImpls;Ljava/lang/Object;Lorg/scalactic/Equality;Ljava/lang/Object;)Ljava/lang/Object;
  #380 = InterfaceMethodref #2.#379       // org/scalatest/enablers/AggregatingImpls.$anonfun$checkOnly$2$adapted:(Lorg/scalatest/enablers/AggregatingImpls;Ljava/lang/Object;Lorg/scalactic/Equality;Ljava/lang/Object;)Ljava/lang/Object;
  #381 = MethodHandle       6:#380        // REF_invokeStatic org/scalatest/enablers/AggregatingImpls.$anonfun$checkOnly$2$adapted:(Lorg/scalatest/enablers/AggregatingImpls;Ljava/lang/Object;Lorg/scalactic/Equality;Ljava/lang/Object;)Ljava/lang/Object;
  #382 = InvokeDynamic      #10:#248      // #10:apply:(Lorg/scalatest/enablers/AggregatingImpls;Ljava/lang/Object;Lorg/scalactic/Equality;)Lscala/Function1;
  #383 = Utf8               find
  #384 = Utf8               (Lscala/Function1;)Lscala/Option;
  #385 = NameAndType        #383:#384     // find:(Lscala/Function1;)Lscala/Option;
  #386 = InterfaceMethodref #72.#385      // scala/collection/Iterable.find:(Lscala/Function1;)Lscala/Option;
  #387 = Utf8               scala/Option
  #388 = Class              #387          // scala/Option
  #389 = Utf8               isDefined
  #390 = NameAndType        #389:#153     // isDefined:()Z
  #391 = Methodref          #388.#390     // scala/Option.isDefined:()Z
  #392 = Utf8               $anonfun$checkOnly$4
  #393 = Utf8               r$1
  #394 = Utf8               $anonfun$checkOnly$3
  #395 = Utf8               left$1
  #396 = Utf8               $anonfun$checkOnly$4$adapted
  #397 = NameAndType        #396:#378     // $anonfun$checkOnly$4$adapted:(Lorg/scalatest/enablers/AggregatingImpls;Ljava/lang/Object;Lorg/scalactic/Equality;Ljava/lang/Object;)Ljava/lang/Object;
  #398 = InterfaceMethodref #2.#397       // org/scalatest/enablers/AggregatingImpls.$anonfun$checkOnly$4$adapted:(Lorg/scalatest/enablers/AggregatingImpls;Ljava/lang/Object;Lorg/scalactic/Equality;Ljava/lang/Object;)Ljava/lang/Object;
  #399 = MethodHandle       6:#398        // REF_invokeStatic org/scalatest/enablers/AggregatingImpls.$anonfun$checkOnly$4$adapted:(Lorg/scalatest/enablers/AggregatingImpls;Ljava/lang/Object;Lorg/scalactic/Equality;Ljava/lang/Object;)Ljava/lang/Object;
  #400 = InvokeDynamic      #11:#248      // #11:apply:(Lorg/scalatest/enablers/AggregatingImpls;Ljava/lang/Object;Lorg/scalactic/Equality;)Lscala/Function1;
  #401 = Utf8               $anonfun$checkAllOf$1
  #402 = Utf8               (Lorg/scalactic/Equality;Ljava/lang/Object;Ljava/lang/Object;)Z
  #403 = Utf8               equality$3
  #404 = Utf8               nextRight$1
  #405 = Utf8               t
  #406 = Utf8               rightItr
  #407 = Utf8               scala/collection/Iterator
  #408 = Class              #407          // scala/collection/Iterator
  #409 = Utf8               hasNext
  #410 = NameAndType        #409:#153     // hasNext:()Z
  #411 = InterfaceMethodref #408.#410     // scala/collection/Iterator.hasNext:()Z
  #412 = NameAndType        #241:#85      // next:()Ljava/lang/Object;
  #413 = InterfaceMethodref #408.#412     // scala/collection/Iterator.next:()Ljava/lang/Object;
  #414 = Utf8               $anonfun$checkAllOf$1$adapted
  #415 = Utf8               (Lorg/scalactic/Equality;Ljava/lang/Object;Ljava/lang/Object;)Ljava/lang/Object;
  #416 = NameAndType        #414:#415     // $anonfun$checkAllOf$1$adapted:(Lorg/scalactic/Equality;Ljava/lang/Object;Ljava/lang/Object;)Ljava/lang/Object;
  #417 = InterfaceMethodref #2.#416       // org/scalatest/enablers/AggregatingImpls.$anonfun$checkAllOf$1$adapted:(Lorg/scalactic/Equality;Ljava/lang/Object;Ljava/lang/Object;)Ljava/lang/Object;
  #418 = MethodHandle       6:#417        // REF_invokeStatic org/scalatest/enablers/AggregatingImpls.$anonfun$checkAllOf$1$adapted:(Lorg/scalactic/Equality;Ljava/lang/Object;Ljava/lang/Object;)Ljava/lang/Object;
  #419 = Utf8               (Lorg/scalactic/Equality;Ljava/lang/Object;)Lscala/Function1;
  #420 = NameAndType        #102:#419     // apply:(Lorg/scalactic/Equality;Ljava/lang/Object;)Lscala/Function1;
  #421 = InvokeDynamic      #12:#420      // #12:apply:(Lorg/scalactic/Equality;Ljava/lang/Object;)Lscala/Function1;
  #422 = InterfaceMethodref #72.#147      // scala/collection/Iterable.exists:(Lscala/Function1;)Z
  #423 = Utf8               Lscala/collection/Iterator;
  #424 = Utf8               $anonfun$checkAtMostOneOf$1
  #425 = Utf8               $anonfun$checkAtMostOneOf$3
  #426 = Utf8               equality$4
  #427 = Utf8               nextRight$2
  #428 = Utf8               $anonfun$checkAtMostOneOf$2
  #429 = Utf8               (Lscala/collection/Iterable;Lorg/scalactic/Equality;Ljava/lang/Object;ILjava/lang/Object;)I
  #430 = Utf8               left$2
  #431 = Utf8               nonLocalReturnKey2$1
  #432 = Utf8               scala/runtime/BoxesRunTime
  #433 = Class              #432          // scala/runtime/BoxesRunTime
  #434 = Utf8               boxToInteger
  #435 = Utf8               (I)Ljava/lang/Integer;
  #436 = NameAndType        #434:#435     // boxToInteger:(I)Ljava/lang/Integer;
  #437 = Methodref          #433.#436     // scala/runtime/BoxesRunTime.boxToInteger:(I)Ljava/lang/Integer;
  #438 = Utf8               _1$mcI$sp
  #439 = NameAndType        #438:#260     // _1$mcI$sp:()I
  #440 = Methodref          #305.#439     // scala/Tuple2._1$mcI$sp:()I
  #441 = Utf8               $anonfun$checkAtMostOneOf$3$adapted
  #442 = NameAndType        #441:#415     // $anonfun$checkAtMostOneOf$3$adapted:(Lorg/scalactic/Equality;Ljava/lang/Object;Ljava/lang/Object;)Ljava/lang/Object;
  #443 = InterfaceMethodref #2.#442       // org/scalatest/enablers/AggregatingImpls.$anonfun$checkAtMostOneOf$3$adapted:(Lorg/scalactic/Equality;Ljava/lang/Object;Ljava/lang/Object;)Ljava/lang/Object;
  #444 = MethodHandle       6:#443        // REF_invokeStatic org/scalatest/enablers/AggregatingImpls.$anonfun$checkAtMostOneOf$3$adapted:(Lorg/scalactic/Equality;Ljava/lang/Object;Ljava/lang/Object;)Ljava/lang/Object;
  #445 = InvokeDynamic      #13:#420      // #13:apply:(Lorg/scalactic/Equality;Ljava/lang/Object;)Lscala/Function1;
  #446 = Utf8               scala/runtime/NonLocalReturnControl$mcI$sp
  #447 = Class              #446          // scala/runtime/NonLocalReturnControl$mcI$sp
  #448 = Utf8               (Ljava/lang/Object;I)V
  #449 = NameAndType        #58:#448      // "<init>":(Ljava/lang/Object;I)V
  #450 = Methodref          #447.#449     // scala/runtime/NonLocalReturnControl$mcI$sp."<init>":(Ljava/lang/Object;I)V
  #451 = Utf8               newCount
  #452 = Utf8               $anonfun$checkAtMostOneOf$4
  #453 = Utf8               (II)I
  #454 = Utf8               scala/Tuple2$mcII$sp
  #455 = Class              #454          // scala/Tuple2$mcII$sp
  #456 = Utf8               (II)V
  #457 = NameAndType        #58:#456      // "<init>":(II)V
  #458 = Methodref          #455.#457     // scala/Tuple2$mcII$sp."<init>":(II)V
  #459 = Utf8               _2$mcI$sp
  #460 = NameAndType        #459:#260     // _2$mcI$sp:()I
  #461 = Methodref          #305.#460     // scala/Tuple2._2$mcI$sp:()I
  #462 = Utf8               right$2
  #463 = MethodType         #260          //  ()I
  #464 = NameAndType        #424:#260     // $anonfun$checkAtMostOneOf$1:()I
  #465 = InterfaceMethodref #2.#464       // org/scalatest/enablers/AggregatingImpls.$anonfun$checkAtMostOneOf$1:()I
  #466 = MethodHandle       6:#465        // REF_invokeStatic org/scalatest/enablers/AggregatingImpls.$anonfun$checkAtMostOneOf$1:()I
  #467 = Utf8               apply$mcI$sp
  #468 = Utf8               ()Lscala/runtime/java8/JFunction0$mcI$sp;
  #469 = NameAndType        #467:#468     // apply$mcI$sp:()Lscala/runtime/java8/JFunction0$mcI$sp;
  #470 = InvokeDynamic      #14:#469      // #14:apply$mcI$sp:()Lscala/runtime/java8/JFunction0$mcI$sp;
  #471 = Utf8               $anonfun$checkAtMostOneOf$2$adapted
  #472 = Utf8               (Lscala/collection/Iterable;Lorg/scalactic/Equality;Ljava/lang/Object;Ljava/lang/Object;Ljava/lang/Object;)Ljava/lang/Object;
  #473 = NameAndType        #471:#472     // $anonfun$checkAtMostOneOf$2$adapted:(Lscala/collection/Iterable;Lorg/scalactic/Equality;Ljava/lang/Object;Ljava/lang/Object;Ljava/lang/Object;)Ljava/lang/Object;
  #474 = InterfaceMethodref #2.#473       // org/scalatest/enablers/AggregatingImpls.$anonfun$checkAtMostOneOf$2$adapted:(Lscala/collection/Iterable;Lorg/scalactic/Equality;Ljava/lang/Object;Ljava/lang/Object;Ljava/lang/Object;)Ljava/lang/Object;
  #475 = MethodHandle       6:#474        // REF_invokeStatic org/scalatest/enablers/AggregatingImpls.$anonfun$checkAtMostOneOf$2$adapted:(Lscala/collection/Iterable;Lorg/scalactic/Equality;Ljava/lang/Object;Ljava/lang/Object;Ljava/lang/Object;)Ljava/lang/Object;
  #476 = Utf8               (Lscala/collection/Iterable;Lorg/scalactic/Equality;Ljava/lang/Object;)Lscala/Function2;
  #477 = NameAndType        #102:#476     // apply:(Lscala/collection/Iterable;Lorg/scalactic/Equality;Ljava/lang/Object;)Lscala/Function2;
  #478 = InvokeDynamic      #15:#477      // #15:apply:(Lscala/collection/Iterable;Lorg/scalactic/Equality;Ljava/lang/Object;)Lscala/Function2;
  #479 = MethodType         #453          //  (II)I
  #480 = NameAndType        #452:#453     // $anonfun$checkAtMostOneOf$4:(II)I
  #481 = InterfaceMethodref #2.#480       // org/scalatest/enablers/AggregatingImpls.$anonfun$checkAtMostOneOf$4:(II)I
  #482 = MethodHandle       6:#481        // REF_invokeStatic org/scalatest/enablers/AggregatingImpls.$anonfun$checkAtMostOneOf$4:(II)I
  #483 = Utf8               apply$mcIII$sp
  #484 = Utf8               ()Lscala/runtime/java8/JFunction2$mcIII$sp;
  #485 = NameAndType        #483:#484     // apply$mcIII$sp:()Lscala/runtime/java8/JFunction2$mcIII$sp;
  #486 = InvokeDynamic      #16:#485      // #16:apply$mcIII$sp:()Lscala/runtime/java8/JFunction2$mcIII$sp;
  #487 = Utf8               unboxToInt
  #488 = Utf8               (Ljava/lang/Object;)I
  #489 = NameAndType        #487:#488     // unboxToInt:(Ljava/lang/Object;)I
  #490 = Methodref          #433.#489     // scala/runtime/BoxesRunTime.unboxToInt:(Ljava/lang/Object;)I
  #491 = Utf8               value$mcI$sp
  #492 = NameAndType        #491:#260     // value$mcI$sp:()I
  #493 = Methodref          #57.#492      // scala/runtime/NonLocalReturnControl.value$mcI$sp:()I
  #494 = Utf8               $init$
  #495 = NameAndType        #365:#366     // $anonfun$checkTheSameElementsAs$8:(Lorg/scalatest/enablers/AggregatingImpls$ElementCount$1;)Z
  #496 = InterfaceMethodref #2.#495       // org/scalatest/enablers/AggregatingImpls.$anonfun$checkTheSameElementsAs$8:(Lorg/scalatest/enablers/AggregatingImpls$ElementCount$1;)Z
  #497 = Utf8               boxToBoolean
  #498 = Utf8               (Z)Ljava/lang/Boolean;
  #499 = NameAndType        #497:#498     // boxToBoolean:(Z)Ljava/lang/Boolean;
  #500 = Methodref          #433.#499     // scala/runtime/BoxesRunTime.boxToBoolean:(Z)Ljava/lang/Boolean;
  #501 = NameAndType        #373:#374     // $anonfun$checkOnly$1:(Lorg/scalatest/enablers/AggregatingImpls;Lscala/collection/Iterable;Lorg/scalactic/Equality;Ljava/lang/Object;)Z
  #502 = InterfaceMethodref #2.#501       // org/scalatest/enablers/AggregatingImpls.$anonfun$checkOnly$1:(Lorg/scalatest/enablers/AggregatingImpls;Lscala/collection/Iterable;Lorg/scalactic/Equality;Ljava/lang/Object;)Z
  #503 = NameAndType        #394:#374     // $anonfun$checkOnly$3:(Lorg/scalatest/enablers/AggregatingImpls;Lscala/collection/Iterable;Lorg/scalactic/Equality;Ljava/lang/Object;)Z
  #504 = InterfaceMethodref #2.#503       // org/scalatest/enablers/AggregatingImpls.$anonfun$checkOnly$3:(Lorg/scalatest/enablers/AggregatingImpls;Lscala/collection/Iterable;Lorg/scalactic/Equality;Ljava/lang/Object;)Z
  #505 = NameAndType        #230:#231     // $anonfun$checkTheSameElementsAs$1:(Lorg/scalatest/enablers/AggregatingImpls;Ljava/lang/Object;Lorg/scalactic/Equality;Lorg/scalatest/enablers/AggregatingImpls$ElementCount$1;)Z
  #506 = InterfaceMethodref #2.#505       // org/scalatest/enablers/AggregatingImpls.$anonfun$checkTheSameElementsAs$1:(Lorg/scalatest/enablers/AggregatingImpls;Ljava/lang/Object;Lorg/scalactic/Equality;Lorg/scalatest/enablers/AggregatingImpls$ElementCount$1;)Z
  #507 = NameAndType        #278:#231     // $anonfun$checkTheSameElementsAs$2:(Lorg/scalatest/enablers/AggregatingImpls;Ljava/lang/Object;Lorg/scalactic/Equality;Lorg/scalatest/enablers/AggregatingImpls$ElementCount$1;)Z
  #508 = InterfaceMethodref #2.#507       // org/scalatest/enablers/AggregatingImpls.$anonfun$checkTheSameElementsAs$2:(Lorg/scalatest/enablers/AggregatingImpls;Ljava/lang/Object;Lorg/scalactic/Equality;Lorg/scalatest/enablers/AggregatingImpls$ElementCount$1;)Z
  #509 = NameAndType        #336:#337     // $anonfun$checkTheSameElementsAs$7:(Lorg/scalatest/enablers/AggregatingImpls;Lorg/scalatest/enablers/AggregatingImpls$ElementCount$1;Lorg/scalactic/Equality;Lorg/scalatest/enablers/AggregatingImpls$ElementCount$1;)Z
  #510 = InterfaceMethodref #2.#509       // org/scalatest/enablers/AggregatingImpls.$anonfun$checkTheSameElementsAs$7:(Lorg/scalatest/enablers/AggregatingImpls;Lorg/scalatest/enablers/AggregatingImpls$ElementCount$1;Lorg/scalactic/Equality;Lorg/scalatest/enablers/AggregatingImpls$ElementCount$1;)Z
  #511 = NameAndType        #368:#369     // $anonfun$checkOnly$2:(Lorg/scalatest/enablers/AggregatingImpls;Ljava/lang/Object;Lorg/scalactic/Equality;Ljava/lang/Object;)Z
  #512 = InterfaceMethodref #2.#511       // org/scalatest/enablers/AggregatingImpls.$anonfun$checkOnly$2:(Lorg/scalatest/enablers/AggregatingImpls;Ljava/lang/Object;Lorg/scalactic/Equality;Ljava/lang/Object;)Z
  #513 = NameAndType        #392:#369     // $anonfun$checkOnly$4:(Lorg/scalatest/enablers/AggregatingImpls;Ljava/lang/Object;Lorg/scalactic/Equality;Ljava/lang/Object;)Z
  #514 = InterfaceMethodref #2.#513       // org/scalatest/enablers/AggregatingImpls.$anonfun$checkOnly$4:(Lorg/scalatest/enablers/AggregatingImpls;Ljava/lang/Object;Lorg/scalactic/Equality;Ljava/lang/Object;)Z
  #515 = NameAndType        #401:#402     // $anonfun$checkAllOf$1:(Lorg/scalactic/Equality;Ljava/lang/Object;Ljava/lang/Object;)Z
  #516 = InterfaceMethodref #2.#515       // org/scalatest/enablers/AggregatingImpls.$anonfun$checkAllOf$1:(Lorg/scalactic/Equality;Ljava/lang/Object;Ljava/lang/Object;)Z
  #517 = NameAndType        #425:#402     // $anonfun$checkAtMostOneOf$3:(Lorg/scalactic/Equality;Ljava/lang/Object;Ljava/lang/Object;)Z
  #518 = InterfaceMethodref #2.#517       // org/scalatest/enablers/AggregatingImpls.$anonfun$checkAtMostOneOf$3:(Lorg/scalactic/Equality;Ljava/lang/Object;Ljava/lang/Object;)Z
  #519 = NameAndType        #428:#429     // $anonfun$checkAtMostOneOf$2:(Lscala/collection/Iterable;Lorg/scalactic/Equality;Ljava/lang/Object;ILjava/lang/Object;)I
  #520 = InterfaceMethodref #2.#519       // org/scalatest/enablers/AggregatingImpls.$anonfun$checkAtMostOneOf$2:(Lscala/collection/Iterable;Lorg/scalactic/Equality;Ljava/lang/Object;ILjava/lang/Object;)I
  #521 = Utf8               $deserializeLambda$
  #522 = Utf8               (Ljava/lang/invoke/SerializedLambda;)Ljava/lang/Object;
  #523 = Utf8               scala/runtime/LambdaDeserialize
  #524 = Class              #523          // scala/runtime/LambdaDeserialize
  #525 = Utf8               bootstrap
  #526 = Utf8               (Ljava/lang/invoke/MethodHandles$Lookup;Ljava/lang/String;Ljava/lang/invoke/MethodType;[Ljava/lang/invoke/MethodHandle;)Ljava/lang/invoke/CallSite;
  #527 = NameAndType        #525:#526     // bootstrap:(Ljava/lang/invoke/MethodHandles$Lookup;Ljava/lang/String;Ljava/lang/invoke/MethodType;[Ljava/lang/invoke/MethodHandle;)Ljava/lang/invoke/CallSite;
  #528 = Methodref          #524.#527     // scala/runtime/LambdaDeserialize.bootstrap:(Ljava/lang/invoke/MethodHandles$Lookup;Ljava/lang/String;Ljava/lang/invoke/MethodType;[Ljava/lang/invoke/MethodHandle;)Ljava/lang/invoke/CallSite;
  #529 = MethodHandle       6:#528        // REF_invokeStatic scala/runtime/LambdaDeserialize.bootstrap:(Ljava/lang/invoke/MethodHandles$Lookup;Ljava/lang/String;Ljava/lang/invoke/MethodType;[Ljava/lang/invoke/MethodHandle;)Ljava/lang/invoke/CallSite;
  #530 = Utf8               lambdaDeserialize
  #531 = NameAndType        #530:#522     // lambdaDeserialize:(Ljava/lang/invoke/SerializedLambda;)Ljava/lang/Object;
  #532 = InvokeDynamic      #17:#531      // #17:lambdaDeserialize:(Ljava/lang/invoke/SerializedLambda;)Ljava/lang/Object;
  #533 = Utf8               Code
  #534 = Utf8               LineNumberTable
  #535 = Utf8               LocalVariableTable
  #536 = Utf8               MethodParameters
  #537 = Utf8               StackMapTable
  #538 = Utf8               Signature
  #539 = Utf8               InnerClasses
  #540 = Utf8               SourceFile
  #541 = Utf8               RuntimeVisibleAnnotations
  #542 = Utf8               BootstrapMethods
  #543 = Utf8               ScalaInlineInfo
  #544 = Utf8               ScalaSig
{
  public static boolean tryEquality$(org.scalatest.enablers.AggregatingImpls, java.lang.Object, java.lang.Object, org.scalactic.Equality);
    descriptor: (Lorg/scalatest/enablers/AggregatingImpls;Ljava/lang/Object;Ljava/lang/Object;Lorg/scalactic/Equality;)Z
    flags: (0x1009) ACC_PUBLIC, ACC_STATIC, ACC_SYNTHETIC
    Code:
      stack=4, locals=4, args_size=4
         0: aload_0
         1: aload_1
         2: aload_2
         3: aload_3
         4: invokespecial #32                 // InterfaceMethod tryEquality:(Ljava/lang/Object;Ljava/lang/Object;Lorg/scalactic/Equality;)Z
         7: ireturn
      LineNumberTable:
        line 120: 0
      LocalVariableTable:
        Start  Length  Slot  Name   Signature
            0       8     0 $this   Lorg/scalatest/enablers/AggregatingImpls;
            0       8     1  left   Ljava/lang/Object;
            0       8     2 right   Ljava/lang/Object;
            0       8     3 equality   Lorg/scalactic/Equality;
    MethodParameters:
      Name                           Flags
      $this                          final synthetic
      left                           final
      right                          final
      equality                       final

  public default <T extends java.lang.Object> boolean tryEquality(java.lang.Object, java.lang.Object, org.scalactic.Equality<T>);
    descriptor: (Ljava/lang/Object;Ljava/lang/Object;Lorg/scalactic/Equality;)Z
    flags: (0x0001) ACC_PUBLIC
    Code:
      stack=3, locals=5, args_size=4
         0: aload_3
         1: aload_1
         2: aload_2
         3: invokeinterface #44,  3           // InterfaceMethod org/scalactic/Equality.areEqual:(Ljava/lang/Object;Ljava/lang/Object;)Z
         8: goto          17
        11: astore        4
        13: iconst_0
        14: goto          17
        17: ireturn
      Exception table:
         from    to  target type
             0     8    11   Class java/lang/ClassCastException
      StackMapTable: number_of_entries = 2
        frame_type = 75 /* same_locals_1_stack_item */
          stack = [ class java/lang/ClassCastException ]
        frame_type = 69 /* same_locals_1_stack_item */
          stack = [ int ]
      LineNumberTable:
        line 121: 0
        line 123: 13
      LocalVariableTable:
        Start  Length  Slot  Name   Signature
           11       3     4   cce   Ljava/lang/ClassCastException;
            0      18     0  this   Lorg/scalatest/enablers/AggregatingImpls;
            0      18     1  left   Ljava/lang/Object;
            0      18     2 right   Ljava/lang/Object;
            0      18     3 equality   Lorg/scalactic/Equality;
    Signature: #36                          // <T:Ljava/lang/Object;>(Ljava/lang/Object;Ljava/lang/Object;Lorg/scalactic/Equality<TT;>;)Z
    MethodParameters:
      Name                           Flags
      left                           final
      right                          final
      equality                       final

  public static boolean checkTheSameElementsAs$(org.scalatest.enablers.AggregatingImpls, scala.collection.Iterable, scala.collection.Iterable, org.scalactic.Equality);
    descriptor: (Lorg/scalatest/enablers/AggregatingImpls;Lscala/collection/Iterable;Lscala/collection/Iterable;Lorg/scalactic/Equality;)Z
    flags: (0x1009) ACC_PUBLIC, ACC_STATIC, ACC_SYNTHETIC
    Code:
      stack=4, locals=4, args_size=4
         0: aload_0
         1: aload_1
         2: aload_2
         3: aload_3
         4: invokespecial #53                 // InterfaceMethod checkTheSameElementsAs:(Lscala/collection/Iterable;Lscala/collection/Iterable;Lorg/scalactic/Equality;)Z
         7: ireturn
      LineNumberTable:
        line 126: 0
      LocalVariableTable:
        Start  Length  Slot  Name   Signature
            0       8     0 $this   Lorg/scalatest/enablers/AggregatingImpls;
            0       8     1  left   Lscala/collection/Iterable;
            0       8     2 right   Lscala/collection/Iterable;
            0       8     3 equality   Lorg/scalactic/Equality;
    MethodParameters:
      Name                           Flags
      $this                          final synthetic
      left                           final
      right                          final
      equality                       final

  public default <T extends java.lang.Object> boolean checkTheSameElementsAs(scala.collection.Iterable<T>, scala.collection.Iterable<java.lang.Object>, org.scalactic.Equality<T>);
    descriptor: (Lscala/collection/Iterable;Lscala/collection/Iterable;Lorg/scalactic/Equality;)Z
    flags: (0x0001) ACC_PUBLIC
    Code:
      stack=8, locals=9, args_size=4
         0: new           #4                  // class java/lang/Object
         3: dup
         4: invokespecial #61                 // Method java/lang/Object."<init>":()V
         7: astore        4
         9: new           #63                 // class scala/runtime/LazyRef
        12: dup
        13: invokespecial #64                 // Method scala/runtime/LazyRef."<init>":()V
        16: astore        5
        18: new           #63                 // class scala/runtime/LazyRef
        21: dup
        22: invokespecial #64                 // Method scala/runtime/LazyRef."<init>":()V
        25: astore        6
        27: getstatic     #70                 // Field org/scalactic/ColCompatHelper$.MODULE$:Lorg/scalactic/ColCompatHelper$;
        30: aload_2
        31: invokeinterface #76,  1           // InterfaceMethod scala/collection/Iterable.toIterable:()Lscala/collection/Iterable;
        36: aload_1
        37: invokeinterface #76,  1           // InterfaceMethod scala/collection/Iterable.toIterable:()Lscala/collection/Iterable;
        42: aload_0
        43: aload         6
        45: invokespecial #80                 // InterfaceMethod ZipNoMatch$2:(Lscala/runtime/LazyRef;)Lorg/scalatest/enablers/AggregatingImpls$ZipNoMatch$1$;
        48: aload_0
        49: aload         6
        51: invokespecial #80                 // InterfaceMethod ZipNoMatch$2:(Lscala/runtime/LazyRef;)Lorg/scalatest/enablers/AggregatingImpls$ZipNoMatch$1$;
        54: invokeinterface #84,  4           // InterfaceMethod scala/collection/Iterable.zipAll:(Lscala/collection/Iterable;Ljava/lang/Object;Ljava/lang/Object;)Ljava/lang/Object;
        59: checkcast     #72                 // class scala/collection/Iterable
        62: invokedynamic #105,  0            // InvokeDynamic #0:apply:()Lscala/Function0;
        67: aload_0
        68: aload         4
        70: aload         6
        72: aload_3
        73: aload         5
        75: invokedynamic #117,  0            // InvokeDynamic #1:apply:(Lorg/scalatest/enablers/AggregatingImpls;Ljava/lang/Object;Lscala/runtime/LazyRef;Lorg/scalactic/Equality;Lscala/runtime/LazyRef;)Lscala/Function2;
        80: aload_0
        81: aload_3
        82: aload         5
        84: invokedynamic #127,  0            // InvokeDynamic #2:apply:(Lorg/scalatest/enablers/AggregatingImpls;Lorg/scalactic/Equality;Lscala/runtime/LazyRef;)Lscala/Function2;
        89: invokevirtual #131                // Method org/scalactic/ColCompatHelper$.aggregate:(Lscala/collection/Iterable;Lscala/Function0;Lscala/Function2;Lscala/Function2;)Ljava/lang/Object;
        92: checkcast     #133                // class scala/collection/immutable/IndexedSeq
        95: astore        7
        97: aload         7
        99: invokedynamic #144,  0            // InvokeDynamic #3:apply:()Lscala/Function1;
       104: invokeinterface #148,  2          // InterfaceMethod scala/collection/immutable/IndexedSeq.exists:(Lscala/Function1;)Z
       109: ifne          116
       112: iconst_1
       113: goto          117
       116: iconst_0
       117: goto          146
       120: astore        8
       122: aload         8
       124: invokevirtual #151                // Method scala/runtime/NonLocalReturnControl.key:()Ljava/lang/Object;
       127: aload         4
       129: if_acmpne     140
       132: aload         8
       134: invokevirtual #155                // Method scala/runtime/NonLocalReturnControl.value$mcZ$sp:()Z
       137: goto          143
       140: aload         8
       142: athrow
       143: goto          146
       146: ireturn
      Exception table:
         from    to  target type
             9   117   120   Class scala/runtime/NonLocalReturnControl
      StackMapTable: number_of_entries = 6
        frame_type = 255 /* full_frame */
          offset_delta = 116
          locals = [ class org/scalatest/enablers/AggregatingImpls, class scala/collection/Iterable, class scala/collection/Iterable, class org/scalactic/Equality, class java/lang/Object, class scala/runtime/LazyRef, class scala/runtime/LazyRef, class scala/collection/immutable/IndexedSeq ]
          stack = []
        frame_type = 64 /* same_locals_1_stack_item */
          stack = [ int ]
        frame_type = 255 /* full_frame */
          offset_delta = 2
          locals = [ class org/scalatest/enablers/AggregatingImpls, class scala/collection/Iterable, class scala/collection/Iterable, class org/scalactic/Equality, class java/lang/Object ]
          stack = [ class scala/runtime/NonLocalReturnControl ]
        frame_type = 255 /* full_frame */
          offset_delta = 19
          locals = [ class org/scalatest/enablers/AggregatingImpls, class scala/collection/Iterable, class scala/collection/Iterable, class org/scalactic/Equality, class java/lang/Object, top, top, top, class scala/runtime/NonLocalReturnControl ]
          stack = []
        frame_type = 66 /* same_locals_1_stack_item */
          stack = [ int ]
        frame_type = 255 /* full_frame */
          offset_delta = 2
          locals = [ class org/scalatest/enablers/AggregatingImpls, class scala/collection/Iterable, class scala/collection/Iterable, class org/scalactic/Equality, class java/lang/Object ]
          stack = [ int ]
      LineNumberTable:
        line 126: 0
        line 127: 9
        line 128: 18
        line 150: 27
        line 151: 67
        line 156: 80
        line 169: 97
        line 126: 122
      LocalVariableTable:
        Start  Length  Slot  Name   Signature
           18      99     5 ElementCount$module   Lscala/runtime/LazyRef;
           27      90     6 ZipNoMatch$module   Lscala/runtime/LazyRef;
           97      20     7 counts   Lscala/collection/immutable/IndexedSeq;
          120      23     8    ex   Lscala/runtime/NonLocalReturnControl;
            0     147     0  this   Lorg/scalatest/enablers/AggregatingImpls;
            0     147     1  left   Lscala/collection/Iterable;
            0     147     2 right   Lscala/collection/Iterable;
            0     147     3 equality   Lorg/scalactic/Equality;
    Signature: #55                          // <T:Ljava/lang/Object;>(Lscala/collection/Iterable<TT;>;Lscala/collection/Iterable<Ljava/lang/Object;>;Lorg/scalactic/Equality<TT;>;)Z
    MethodParameters:
      Name                           Flags
      left                           final
      right                          final
      equality                       final

  public static boolean checkOnly$(org.scalatest.enablers.AggregatingImpls, scala.collection.Iterable, scala.collection.Iterable, org.scalactic.Equality);
    descriptor: (Lorg/scalatest/enablers/AggregatingImpls;Lscala/collection/Iterable;Lscala/collection/Iterable;Lorg/scalactic/Equality;)Z
    flags: (0x1009) ACC_PUBLIC, ACC_STATIC, ACC_SYNTHETIC
    Code:
      stack=4, locals=4, args_size=4
         0: aload_0
         1: aload_1
         2: aload_2
         3: aload_3
         4: invokespecial #166                // InterfaceMethod checkOnly:(Lscala/collection/Iterable;Lscala/collection/Iterable;Lorg/scalactic/Equality;)Z
         7: ireturn
      LineNumberTable:
        line 172: 0
      LocalVariableTable:
        Start  Length  Slot  Name   Signature
            0       8     0 $this   Lorg/scalatest/enablers/AggregatingImpls;
            0       8     1  left   Lscala/collection/Iterable;
            0       8     2 right   Lscala/collection/Iterable;
            0       8     3 equality   Lorg/scalactic/Equality;
    MethodParameters:
      Name                           Flags
      $this                          final synthetic
      left                           final
      right                          final
      equality                       final

  public default <T extends java.lang.Object> boolean checkOnly(scala.collection.Iterable<T>, scala.collection.Iterable<java.lang.Object>, org.scalactic.Equality<T>);
    descriptor: (Lscala/collection/Iterable;Lscala/collection/Iterable;Lorg/scalactic/Equality;)Z
    flags: (0x0001) ACC_PUBLIC
    Code:
      stack=4, locals=4, args_size=4
         0: aload_1
         1: aload_0
         2: aload_2
         3: aload_3
         4: invokedynamic #174,  0            // InvokeDynamic #4:apply:(Lorg/scalatest/enablers/AggregatingImpls;Lscala/collection/Iterable;Lorg/scalactic/Equality;)Lscala/Function1;
         9: invokeinterface #177,  2          // InterfaceMethod scala/collection/Iterable.forall:(Lscala/Function1;)Z
        14: ifeq          38
        17: aload_2
        18: aload_0
        19: aload_1
        20: aload_3
        21: invokedynamic #182,  0            // InvokeDynamic #5:apply:(Lorg/scalatest/enablers/AggregatingImpls;Lscala/collection/Iterable;Lorg/scalactic/Equality;)Lscala/Function1;
        26: invokeinterface #177,  2          // InterfaceMethod scala/collection/Iterable.forall:(Lscala/Function1;)Z
        31: ifeq          38
        34: iconst_1
        35: goto          39
        38: iconst_0
        39: ireturn
      StackMapTable: number_of_entries = 2
        frame_type = 38 /* same */
        frame_type = 64 /* same_locals_1_stack_item */
          stack = [ int ]
      LineNumberTable:
        line 173: 0
        line 174: 17
      LocalVariableTable:
        Start  Length  Slot  Name   Signature
            0      40     0  this   Lorg/scalatest/enablers/AggregatingImpls;
            0      40     1  left   Lscala/collection/Iterable;
            0      40     2 right   Lscala/collection/Iterable;
            0      40     3 equality   Lorg/scalactic/Equality;
    Signature: #55                          // <T:Ljava/lang/Object;>(Lscala/collection/Iterable<TT;>;Lscala/collection/Iterable<Ljava/lang/Object;>;Lorg/scalactic/Equality<TT;>;)Z
    MethodParameters:
      Name                           Flags
      left                           final
      right                          final
      equality                       final

  public static boolean checkAllOf$(org.scalatest.enablers.AggregatingImpls, scala.collection.Iterable, scala.collection.Iterable, org.scalactic.Equality);
    descriptor: (Lorg/scalatest/enablers/AggregatingImpls;Lscala/collection/Iterable;Lscala/collection/Iterable;Lorg/scalactic/Equality;)Z
    flags: (0x1009) ACC_PUBLIC, ACC_STATIC, ACC_SYNTHETIC
    Code:
      stack=4, locals=4, args_size=4
         0: aload_0
         1: aload_1
         2: aload_2
         3: aload_3
         4: invokespecial #186                // InterfaceMethod checkAllOf:(Lscala/collection/Iterable;Lscala/collection/Iterable;Lorg/scalactic/Equality;)Z
         7: ireturn
      LineNumberTable:
        line 176: 0
      LocalVariableTable:
        Start  Length  Slot  Name   Signature
            0       8     0 $this   Lorg/scalatest/enablers/AggregatingImpls;
            0       8     1  left   Lscala/collection/Iterable;
            0       8     2 right   Lscala/collection/Iterable;
            0       8     3 equality   Lorg/scalactic/Equality;
    MethodParameters:
      Name                           Flags
      $this                          final synthetic
      left                           final
      right                          final
      equality                       final

  public default <T extends java.lang.Object> boolean checkAllOf(scala.collection.Iterable<T>, scala.collection.Iterable<java.lang.Object>, org.scalactic.Equality<T>);
    descriptor: (Lscala/collection/Iterable;Lscala/collection/Iterable;Lorg/scalactic/Equality;)Z
    flags: (0x0001) ACC_PUBLIC
    Code:
      stack=4, locals=4, args_size=4
         0: aload_0
         1: aload_1
         2: aload_2
         3: invokeinterface #190,  1          // InterfaceMethod scala/collection/Iterable.toIterator:()Lscala/collection/Iterator;
         8: aload_3
         9: invokespecial #194                // InterfaceMethod checkEqual$1:(Lscala/collection/Iterable;Lscala/collection/Iterator;Lorg/scalactic/Equality;)Z
        12: ireturn
      LineNumberTable:
        line 189: 0
      LocalVariableTable:
        Start  Length  Slot  Name   Signature
            0      13     0  this   Lorg/scalatest/enablers/AggregatingImpls;
            0      13     1  left   Lscala/collection/Iterable;
            0      13     2 right   Lscala/collection/Iterable;
            0      13     3 equality   Lorg/scalactic/Equality;
    Signature: #55                          // <T:Ljava/lang/Object;>(Lscala/collection/Iterable<TT;>;Lscala/collection/Iterable<Ljava/lang/Object;>;Lorg/scalactic/Equality<TT;>;)Z
    MethodParameters:
      Name                           Flags
      left                           final
      right                          final
      equality                       final

  public static boolean checkAtMostOneOf$(org.scalatest.enablers.AggregatingImpls, scala.collection.Iterable, scala.collection.Iterable, org.scalactic.Equality);
    descriptor: (Lorg/scalatest/enablers/AggregatingImpls;Lscala/collection/Iterable;Lscala/collection/Iterable;Lorg/scalactic/Equality;)Z
    flags: (0x1009) ACC_PUBLIC, ACC_STATIC, ACC_SYNTHETIC
    Code:
      stack=4, locals=4, args_size=4
         0: aload_0
         1: aload_1
         2: aload_2
         3: aload_3
         4: invokespecial #198                // InterfaceMethod checkAtMostOneOf:(Lscala/collection/Iterable;Lscala/collection/Iterable;Lorg/scalactic/Equality;)Z
         7: ireturn
      LineNumberTable:
        line 192: 0
      LocalVariableTable:
        Start  Length  Slot  Name   Signature
            0       8     0 $this   Lorg/scalatest/enablers/AggregatingImpls;
            0       8     1  left   Lscala/collection/Iterable;
            0       8     2 right   Lscala/collection/Iterable;
            0       8     3 equality   Lorg/scalactic/Equality;
    MethodParameters:
      Name                           Flags
      $this                          final synthetic
      left                           final
      right                          final
      equality                       final

  public default <T extends java.lang.Object> boolean checkAtMostOneOf(scala.collection.Iterable<T>, scala.collection.Iterable<java.lang.Object>, org.scalactic.Equality<T>);
    descriptor: (Lscala/collection/Iterable;Lscala/collection/Iterable;Lorg/scalactic/Equality;)Z
    flags: (0x0001) ACC_PUBLIC
    Code:
      stack=3, locals=5, args_size=4
         0: aload_2
         1: aload_1
         2: aload_3
         3: invokestatic  #202                // InterfaceMethod countElements$1:(Lscala/collection/Iterable;Lscala/collection/Iterable;Lorg/scalactic/Equality;)I
         6: istore        4
         8: iload         4
        10: iconst_1
        11: if_icmpgt     18
        14: iconst_1
        15: goto          19
        18: iconst_0
        19: ireturn
      StackMapTable: number_of_entries = 2
        frame_type = 252 /* append */
          offset_delta = 18
          locals = [ int ]
        frame_type = 64 /* same_locals_1_stack_item */
          stack = [ int ]
      LineNumberTable:
        line 209: 0
        line 210: 8
      LocalVariableTable:
        Start  Length  Slot  Name   Signature
            8      11     4 count   I
            0      20     0  this   Lorg/scalatest/enablers/AggregatingImpls;
            0      20     1  left   Lscala/collection/Iterable;
            0      20     2 right   Lscala/collection/Iterable;
            0      20     3 equality   Lorg/scalactic/Equality;
    Signature: #55                          // <T:Ljava/lang/Object;>(Lscala/collection/Iterable<TT;>;Lscala/collection/Iterable<Ljava/lang/Object;>;Lorg/scalactic/Equality<TT;>;)Z
    MethodParameters:
      Name                           Flags
      left                           final
      right                          final
      equality                       final

  private org.scalatest.enablers.AggregatingImpls$ElementCount$2$ ElementCount$lzycompute$1(scala.runtime.LazyRef);
    descriptor: (Lscala/runtime/LazyRef;)Lorg/scalatest/enablers/AggregatingImpls$ElementCount$2$;
    flags: (0x1002) ACC_PRIVATE, ACC_SYNTHETIC
    Code:
      stack=4, locals=4, args_size=2
         0: aload_1
         1: dup
         2: astore_2
         3: monitorenter
         4: aload_1
         5: invokevirtual #210                // Method scala/runtime/LazyRef.initialized:()Z
         8: ifeq          21
        11: aload_1
        12: invokevirtual #213                // Method scala/runtime/LazyRef.value:()Ljava/lang/Object;
        15: checkcast     #18                 // class org/scalatest/enablers/AggregatingImpls$ElementCount$2$
        18: goto          36
        21: aload_1
        22: new           #18                 // class org/scalatest/enablers/AggregatingImpls$ElementCount$2$
        25: dup
        26: aload_0
        27: invokespecial #216                // Method org/scalatest/enablers/AggregatingImpls$ElementCount$2$."<init>":(Lorg/scalatest/enablers/AggregatingImpls;)V
        30: invokevirtual #219                // Method scala/runtime/LazyRef.initialize:(Ljava/lang/Object;)Ljava/lang/Object;
        33: checkcast     #18                 // class org/scalatest/enablers/AggregatingImpls$ElementCount$2$
        36: astore_3
        37: aload_2
        38: monitorexit
        39: aload_3
        40: goto          46
        43: aload_2
        44: monitorexit
        45: athrow
        46: areturn
      Exception table:
         from    to  target type
             4    37    43   any
      StackMapTable: number_of_entries = 4
        frame_type = 252 /* append */
          offset_delta = 21
          locals = [ class scala/runtime/LazyRef ]
        frame_type = 78 /* same_locals_1_stack_item */
          stack = [ class org/scalatest/enablers/AggregatingImpls$ElementCount$2$ ]
        frame_type = 70 /* same_locals_1_stack_item */
          stack = [ class java/lang/Throwable ]
        frame_type = 255 /* full_frame */
          offset_delta = 2
          locals = [ class org/scalatest/enablers/AggregatingImpls, class scala/runtime/LazyRef, class scala/runtime/LazyRef, class org/scalatest/enablers/AggregatingImpls$ElementCount$2$ ]
          stack = [ class org/scalatest/enablers/AggregatingImpls$ElementCount$2$ ]
      LineNumberTable:
        line 127: 0
      LocalVariableTable:
        Start  Length  Slot  Name   Signature
            0      47     0  this   Lorg/scalatest/enablers/AggregatingImpls;
            0      47     1 ElementCount$module$1   Lscala/runtime/LazyRef;
    MethodParameters:
      Name                           Flags
      ElementCount$module$1          final

  private org.scalatest.enablers.AggregatingImpls$ElementCount$2$ ElementCount$3(scala.runtime.LazyRef);
    descriptor: (Lscala/runtime/LazyRef;)Lorg/scalatest/enablers/AggregatingImpls$ElementCount$2$;
    flags: (0x0002) ACC_PRIVATE
    Code:
      stack=2, locals=2, args_size=2
         0: aload_1
         1: invokevirtual #210                // Method scala/runtime/LazyRef.initialized:()Z
         4: ifeq          17
         7: aload_1
         8: invokevirtual #213                // Method scala/runtime/LazyRef.value:()Ljava/lang/Object;
        11: checkcast     #18                 // class org/scalatest/enablers/AggregatingImpls$ElementCount$2$
        14: goto          22
        17: aload_0
        18: aload_1
        19: invokespecial #224                // InterfaceMethod ElementCount$lzycompute$1:(Lscala/runtime/LazyRef;)Lorg/scalatest/enablers/AggregatingImpls$ElementCount$2$;
        22: areturn
      StackMapTable: number_of_entries = 2
        frame_type = 17 /* same */
        frame_type = 68 /* same_locals_1_stack_item */
          stack = [ class org/scalatest/enablers/AggregatingImpls$ElementCount$2$ ]
      LineNumberTable:
        line 127: 0
      LocalVariableTable:
        Start  Length  Slot  Name   Signature
            0      23     0  this   Lorg/scalatest/enablers/AggregatingImpls;
            0      23     1 ElementCount$module$1   Lscala/runtime/LazyRef;
    MethodParameters:
      Name                           Flags
      ElementCount$module$1          final

  private static org.scalatest.enablers.AggregatingImpls$ZipNoMatch$1$ ZipNoMatch$lzycompute$1(scala.runtime.LazyRef);
    descriptor: (Lscala/runtime/LazyRef;)Lorg/scalatest/enablers/AggregatingImpls$ZipNoMatch$1$;
    flags: (0x100a) ACC_PRIVATE, ACC_STATIC, ACC_SYNTHETIC
    Code:
      stack=4, locals=3, args_size=1
         0: aload_0
         1: dup
         2: astore_1
         3: monitorenter
         4: aload_0
         5: invokevirtual #210                // Method scala/runtime/LazyRef.initialized:()Z
         8: ifeq          21
        11: aload_0
        12: invokevirtual #213                // Method scala/runtime/LazyRef.value:()Ljava/lang/Object;
        15: checkcast     #21                 // class org/scalatest/enablers/AggregatingImpls$ZipNoMatch$1$
        18: goto          36
        21: aload_0
        22: new           #21                 // class org/scalatest/enablers/AggregatingImpls$ZipNoMatch$1$
        25: dup
        26: aconst_null
        27: invokespecial #227                // Method org/scalatest/enablers/AggregatingImpls$ZipNoMatch$1$."<init>":(Lorg/scalatest/enablers/AggregatingImpls;)V
        30: invokevirtual #219                // Method scala/runtime/LazyRef.initialize:(Ljava/lang/Object;)Ljava/lang/Object;
        33: checkcast     #21                 // class org/scalatest/enablers/AggregatingImpls$ZipNoMatch$1$
        36: astore_2
        37: aload_1
        38: monitorexit
        39: aload_2
        40: goto          46
        43: aload_1
        44: monitorexit
        45: athrow
        46: areturn
      Exception table:
         from    to  target type
             4    37    43   any
      StackMapTable: number_of_entries = 4
        frame_type = 252 /* append */
          offset_delta = 21
          locals = [ class scala/runtime/LazyRef ]
        frame_type = 78 /* same_locals_1_stack_item */
          stack = [ class org/scalatest/enablers/AggregatingImpls$ZipNoMatch$1$ ]
        frame_type = 70 /* same_locals_1_stack_item */
          stack = [ class java/lang/Throwable ]
        frame_type = 255 /* full_frame */
          offset_delta = 2
          locals = [ class scala/runtime/LazyRef, class scala/runtime/LazyRef, class org/scalatest/enablers/AggregatingImpls$ZipNoMatch$1$ ]
          stack = [ class org/scalatest/enablers/AggregatingImpls$ZipNoMatch$1$ ]
      LineNumberTable:
        line 128: 0
      LocalVariableTable:
        Start  Length  Slot  Name   Signature
            0      47     0 ZipNoMatch$module$1   Lscala/runtime/LazyRef;
    MethodParameters:
      Name                           Flags
      ZipNoMatch$module$1            final

  private org.scalatest.enablers.AggregatingImpls$ZipNoMatch$1$ ZipNoMatch$2(scala.runtime.LazyRef);
    descriptor: (Lscala/runtime/LazyRef;)Lorg/scalatest/enablers/AggregatingImpls$ZipNoMatch$1$;
    flags: (0x0002) ACC_PRIVATE
    Code:
      stack=1, locals=2, args_size=2
         0: aload_1
         1: invokevirtual #210                // Method scala/runtime/LazyRef.initialized:()Z
         4: ifeq          17
         7: aload_1
         8: invokevirtual #213                // Method scala/runtime/LazyRef.value:()Ljava/lang/Object;
        11: checkcast     #21                 // class org/scalatest/enablers/AggregatingImpls$ZipNoMatch$1$
        14: goto          21
        17: aload_1
        18: invokestatic  #229                // InterfaceMethod ZipNoMatch$lzycompute$1:(Lscala/runtime/LazyRef;)Lorg/scalatest/enablers/AggregatingImpls$ZipNoMatch$1$;
        21: areturn
      StackMapTable: number_of_entries = 2
        frame_type = 17 /* same */
        frame_type = 67 /* same_locals_1_stack_item */
          stack = [ class org/scalatest/enablers/AggregatingImpls$ZipNoMatch$1$ ]
      LineNumberTable:
        line 128: 0
      LocalVariableTable:
        Start  Length  Slot  Name   Signature
            0      22     0  this   Lorg/scalatest/enablers/AggregatingImpls;
            0      22     1 ZipNoMatch$module$1   Lscala/runtime/LazyRef;
    MethodParameters:
      Name                           Flags
      ZipNoMatch$module$1            final

  public static boolean $anonfun$checkTheSameElementsAs$1(org.scalatest.enablers.AggregatingImpls, java.lang.Object, org.scalactic.Equality, org.scalatest.enablers.AggregatingImpls$ElementCount$1);
    descriptor: (Lorg/scalatest/enablers/AggregatingImpls;Ljava/lang/Object;Lorg/scalactic/Equality;Lorg/scalatest/enablers/AggregatingImpls$ElementCount$1;)Z
    flags: (0x1009) ACC_PUBLIC, ACC_STATIC, ACC_SYNTHETIC
    Code:
      stack=4, locals=4, args_size=4
         0: aload_0
         1: aload_1
         2: aload_3
         3: invokevirtual #237                // Method org/scalatest/enablers/AggregatingImpls$ElementCount$1.element:()Ljava/lang/Object;
         6: aload_2
         7: invokeinterface #32,  4           // InterfaceMethod tryEquality:(Ljava/lang/Object;Ljava/lang/Object;Lorg/scalactic/Equality;)Z
        12: ireturn
      LineNumberTable:
        line 131: 0
      LocalVariableTable:
        Start  Length  Slot  Name   Signature
            0      13     0 $this   Lorg/scalatest/enablers/AggregatingImpls;
            0      13     1 next$1   Ljava/lang/Object;
            0      13     2 equality$1   Lorg/scalactic/Equality;
            0      13     3    ec   Lorg/scalatest/enablers/AggregatingImpls$ElementCount$1;
    MethodParameters:
      Name                           Flags
      $this                          final synthetic
      next$1                         final
      equality$1                     final
      ec                             final

  private scala.collection.immutable.IndexedSeq leftNewCount$1(java.lang.Object, scala.collection.immutable.IndexedSeq, org.scalactic.Equality, scala.runtime.LazyRef);
    descriptor: (Ljava/lang/Object;Lscala/collection/immutable/IndexedSeq;Lorg/scalactic/Equality;Lscala/runtime/LazyRef;)Lscala/collection/immutable/IndexedSeq;
    flags: (0x0002) ACC_PRIVATE
    Code:
      stack=6, locals=7, args_size=5
         0: aload_2
         1: aload_0
         2: aload_1
         3: aload_3
         4: invokedynamic #249,  0            // InvokeDynamic #6:apply:(Lorg/scalatest/enablers/AggregatingImpls;Ljava/lang/Object;Lorg/scalactic/Equality;)Lscala/Function1;
         9: invokeinterface #253,  2          // InterfaceMethod scala/collection/immutable/IndexedSeq.indexWhere:(Lscala/Function1;)I
        14: istore        5
        16: iload         5
        18: iconst_0
        19: if_icmplt     75
        22: aload_2
        23: iload         5
        25: invokeinterface #256,  2          // InterfaceMethod scala/collection/immutable/IndexedSeq.apply:(I)Ljava/lang/Object;
        30: checkcast     #15                 // class org/scalatest/enablers/AggregatingImpls$ElementCount$1
        33: astore        6
        35: aload_2
        36: iload         5
        38: aload_0
        39: aload         4
        41: invokespecial #258                // InterfaceMethod ElementCount$3:(Lscala/runtime/LazyRef;)Lorg/scalatest/enablers/AggregatingImpls$ElementCount$2$;
        44: aload         6
        46: invokevirtual #237                // Method org/scalatest/enablers/AggregatingImpls$ElementCount$1.element:()Ljava/lang/Object;
        49: aload         6
        51: invokevirtual #262                // Method org/scalatest/enablers/AggregatingImpls$ElementCount$1.leftCount:()I
        54: iconst_1
        55: iadd
        56: aload         6
        58: invokevirtual #265                // Method org/scalatest/enablers/AggregatingImpls$ElementCount$1.rightCount:()I
        61: invokevirtual #268                // Method org/scalatest/enablers/AggregatingImpls$ElementCount$2$.apply:(Ljava/lang/Object;II)Lorg/scalatest/enablers/AggregatingImpls$ElementCount$1;
        64: invokeinterface #272,  3          // InterfaceMethod scala/collection/immutable/IndexedSeq.updated:(ILjava/lang/Object;)Ljava/lang/Object;
        69: checkcast     #133                // class scala/collection/immutable/IndexedSeq
        72: goto          96
        75: aload_2
        76: aload_0
        77: aload         4
        79: invokespecial #258                // InterfaceMethod ElementCount$3:(Lscala/runtime/LazyRef;)Lorg/scalatest/enablers/AggregatingImpls$ElementCount$2$;
        82: aload_1
        83: iconst_1
        84: iconst_0
        85: invokevirtual #268                // Method org/scalatest/enablers/AggregatingImpls$ElementCount$2$.apply:(Ljava/lang/Object;II)Lorg/scalatest/enablers/AggregatingImpls$ElementCount$1;
        88: invokeinterface #275,  2          // InterfaceMethod scala/collection/immutable/IndexedSeq.$colon$plus:(Ljava/lang/Object;)Ljava/lang/Object;
        93: checkcast     #133                // class scala/collection/immutable/IndexedSeq
        96: areturn
      StackMapTable: number_of_entries = 2
        frame_type = 252 /* append */
          offset_delta = 75
          locals = [ int ]
        frame_type = 84 /* same_locals_1_stack_item */
          stack = [ class scala/collection/immutable/IndexedSeq ]
      LineNumberTable:
        line 131: 0
        line 132: 16
        line 133: 22
        line 134: 35
        line 137: 75
      LocalVariableTable:
        Start  Length  Slot  Name   Signature
           35      37     6 currentElementCount   Lorg/scalatest/enablers/AggregatingImpls$ElementCount$1;
           16      80     5   idx   I
            0      97     0  this   Lorg/scalatest/enablers/AggregatingImpls;
            0      97     1  next   Ljava/lang/Object;
            0      97     2 count   Lscala/collection/immutable/IndexedSeq;
            0      97     3 equality$1   Lorg/scalactic/Equality;
            0      97     4 ElementCount$module$1   Lscala/runtime/LazyRef;
    MethodParameters:
      Name                           Flags
      next                           final
      count                          final
      equality$1                     final
      ElementCount$module$1          final

  public static boolean $anonfun$checkTheSameElementsAs$2(org.scalatest.enablers.AggregatingImpls, java.lang.Object, org.scalactic.Equality, org.scalatest.enablers.AggregatingImpls$ElementCount$1);
    descriptor: (Lorg/scalatest/enablers/AggregatingImpls;Ljava/lang/Object;Lorg/scalactic/Equality;Lorg/scalatest/enablers/AggregatingImpls$ElementCount$1;)Z
    flags: (0x1009) ACC_PUBLIC, ACC_STATIC, ACC_SYNTHETIC
    Code:
      stack=4, locals=4, args_size=4
         0: aload_0
         1: aload_1
         2: aload_3
         3: invokevirtual #237                // Method org/scalatest/enablers/AggregatingImpls$ElementCount$1.element:()Ljava/lang/Object;
         6: aload_2
         7: invokeinterface #32,  4           // InterfaceMethod tryEquality:(Ljava/lang/Object;Ljava/lang/Object;Lorg/scalactic/Equality;)Z
        12: ireturn
      LineNumberTable:
        line 141: 0
      LocalVariableTable:
        Start  Length  Slot  Name   Signature
            0      13     0 $this   Lorg/scalatest/enablers/AggregatingImpls;
            0      13     1 next$2   Ljava/lang/Object;
            0      13     2 equality$1   Lorg/scalactic/Equality;
            0      13     3    ec   Lorg/scalatest/enablers/AggregatingImpls$ElementCount$1;
    MethodParameters:
      Name                           Flags
      $this                          final synthetic
      next$2                         final
      equality$1                     final
      ec                             final

  private scala.collection.immutable.IndexedSeq rightNewCount$1(java.lang.Object, scala.collection.immutable.IndexedSeq, org.scalactic.Equality, scala.runtime.LazyRef);
    descriptor: (Ljava/lang/Object;Lscala/collection/immutable/IndexedSeq;Lorg/scalactic/Equality;Lscala/runtime/LazyRef;)Lscala/collection/immutable/IndexedSeq;
    flags: (0x0002) ACC_PRIVATE
    Code:
      stack=7, locals=7, args_size=5
         0: aload_2
         1: aload_0
         2: aload_1
         3: aload_3
         4: invokedynamic #285,  0            // InvokeDynamic #7:apply:(Lorg/scalatest/enablers/AggregatingImpls;Ljava/lang/Object;Lorg/scalactic/Equality;)Lscala/Function1;
         9: invokeinterface #253,  2          // InterfaceMethod scala/collection/immutable/IndexedSeq.indexWhere:(Lscala/Function1;)I
        14: istore        5
        16: iload         5
        18: iconst_0
        19: if_icmplt     75
        22: aload_2
        23: iload         5
        25: invokeinterface #256,  2          // InterfaceMethod scala/collection/immutable/IndexedSeq.apply:(I)Ljava/lang/Object;
        30: checkcast     #15                 // class org/scalatest/enablers/AggregatingImpls$ElementCount$1
        33: astore        6
        35: aload_2
        36: iload         5
        38: aload_0
        39: aload         4
        41: invokespecial #258                // InterfaceMethod ElementCount$3:(Lscala/runtime/LazyRef;)Lorg/scalatest/enablers/AggregatingImpls$ElementCount$2$;
        44: aload         6
        46: invokevirtual #237                // Method org/scalatest/enablers/AggregatingImpls$ElementCount$1.element:()Ljava/lang/Object;
        49: aload         6
        51: invokevirtual #262                // Method org/scalatest/enablers/AggregatingImpls$ElementCount$1.leftCount:()I
        54: aload         6
        56: invokevirtual #265                // Method org/scalatest/enablers/AggregatingImpls$ElementCount$1.rightCount:()I
        59: iconst_1
        60: iadd
        61: invokevirtual #268                // Method org/scalatest/enablers/AggregatingImpls$ElementCount$2$.apply:(Ljava/lang/Object;II)Lorg/scalatest/enablers/AggregatingImpls$ElementCount$1;
        64: invokeinterface #272,  3          // InterfaceMethod scala/collection/immutable/IndexedSeq.updated:(ILjava/lang/Object;)Ljava/lang/Object;
        69: checkcast     #133                // class scala/collection/immutable/IndexedSeq
        72: goto          96
        75: aload_2
        76: aload_0
        77: aload         4
        79: invokespecial #258                // InterfaceMethod ElementCount$3:(Lscala/runtime/LazyRef;)Lorg/scalatest/enablers/AggregatingImpls$ElementCount$2$;
        82: aload_1
        83: iconst_0
        84: iconst_1
        85: invokevirtual #268                // Method org/scalatest/enablers/AggregatingImpls$ElementCount$2$.apply:(Ljava/lang/Object;II)Lorg/scalatest/enablers/AggregatingImpls$ElementCount$1;
        88: invokeinterface #275,  2          // InterfaceMethod scala/collection/immutable/IndexedSeq.$colon$plus:(Ljava/lang/Object;)Ljava/lang/Object;
        93: checkcast     #133                // class scala/collection/immutable/IndexedSeq
        96: areturn
      StackMapTable: number_of_entries = 2
        frame_type = 252 /* append */
          offset_delta = 75
          locals = [ int ]
        frame_type = 84 /* same_locals_1_stack_item */
          stack = [ class scala/collection/immutable/IndexedSeq ]
      LineNumberTable:
        line 141: 0
        line 142: 16
        line 143: 22
        line 144: 35
        line 147: 75
      LocalVariableTable:
        Start  Length  Slot  Name   Signature
           35      37     6 currentElementCount   Lorg/scalatest/enablers/AggregatingImpls$ElementCount$1;
           16      80     5   idx   I
            0      97     0  this   Lorg/scalatest/enablers/AggregatingImpls;
            0      97     1  next   Ljava/lang/Object;
            0      97     2 count   Lscala/collection/immutable/IndexedSeq;
            0      97     3 equality$1   Lorg/scalactic/Equality;
            0      97     4 ElementCount$module$1   Lscala/runtime/LazyRef;
    MethodParameters:
      Name                           Flags
      next                           final
      count                          final
      equality$1                     final
      ElementCount$module$1          final

  public static scala.collection.immutable.IndexedSeq $anonfun$checkTheSameElementsAs$3();
    descriptor: ()Lscala/collection/immutable/IndexedSeq;
    flags: (0x1009) ACC_PUBLIC, ACC_STATIC, ACC_SYNTHETIC
    Code:
      stack=1, locals=0, args_size=0
         0: getstatic     #290                // Field scala/package$.MODULE$:Lscala/package$;
         3: invokevirtual #294                // Method scala/package$.IndexedSeq:()Lscala/collection/immutable/IndexedSeq$;
         6: invokevirtual #300                // Method scala/collection/immutable/IndexedSeq$.empty:()Lscala/collection/SeqOps;
         9: checkcast     #133                // class scala/collection/immutable/IndexedSeq
        12: areturn
      LineNumberTable:
        line 150: 0

  public static scala.collection.immutable.IndexedSeq $anonfun$checkTheSameElementsAs$4(org.scalatest.enablers.AggregatingImpls, java.lang.Object, scala.runtime.LazyRef, org.scalactic.Equality, scala.runtime.LazyRef, scala.collection.immutable.IndexedSeq, scala.Tuple2);
    descriptor: (Lorg/scalatest/enablers/AggregatingImpls;Ljava/lang/Object;Lscala/runtime/LazyRef;Lorg/scalactic/Equality;Lscala/runtime/LazyRef;Lscala/collection/immutable/IndexedSeq;Lscala/Tuple2;)Lscala/collection/immutable/IndexedSeq;
    flags: (0x1009) ACC_PUBLIC, ACC_STATIC, ACC_SYNTHETIC
    Code:
      stack=7, locals=15, args_size=7
         0: new           #305                // class scala/Tuple2
         3: dup
         4: aload         5
         6: aload         6
         8: invokespecial #308                // Method scala/Tuple2."<init>":(Ljava/lang/Object;Ljava/lang/Object;)V
        11: astore        8
        13: aload         8
        15: ifnull        155
        18: aload         8
        20: invokevirtual #311                // Method scala/Tuple2._1:()Ljava/lang/Object;
        23: checkcast     #133                // class scala/collection/immutable/IndexedSeq
        26: astore        9
        28: aload         8
        30: invokevirtual #314                // Method scala/Tuple2._2:()Ljava/lang/Object;
        33: checkcast     #305                // class scala/Tuple2
        36: astore        10
        38: aload         10
        40: ifnull        152
        43: aload         10
        45: invokevirtual #311                // Method scala/Tuple2._1:()Ljava/lang/Object;
        48: astore        11
        50: aload         10
        52: invokevirtual #314                // Method scala/Tuple2._2:()Ljava/lang/Object;
        55: astore        12
        57: aload         11
        59: aload_0
        60: aload_2
        61: invokespecial #80                 // InterfaceMethod ZipNoMatch$2:(Lscala/runtime/LazyRef;)Lorg/scalatest/enablers/AggregatingImpls$ZipNoMatch$1$;
        64: astore        13
        66: dup
        67: ifnonnull     79
        70: pop
        71: aload         13
        73: ifnull        117
        76: goto          87
        79: aload         13
        81: invokevirtual #318                // Method java/lang/Object.equals:(Ljava/lang/Object;)Z
        84: ifne          117
        87: aload         12
        89: aload_0
        90: aload_2
        91: invokespecial #80                 // InterfaceMethod ZipNoMatch$2:(Lscala/runtime/LazyRef;)Lorg/scalatest/enablers/AggregatingImpls$ZipNoMatch$1$;
        94: astore        14
        96: dup
        97: ifnonnull     109
       100: pop
       101: aload         14
       103: ifnull        117
       106: goto          127
       109: aload         14
       111: invokevirtual #318                // Method java/lang/Object.equals:(Ljava/lang/Object;)Z
       114: ifeq          127
       117: new           #320                // class scala/runtime/NonLocalReturnControl$mcZ$sp
       120: dup
       121: aload_1
       122: iconst_0
       123: invokespecial #323                // Method scala/runtime/NonLocalReturnControl$mcZ$sp."<init>":(Ljava/lang/Object;Z)V
       126: athrow
       127: aload_0
       128: aload         12
       130: aload_0
       131: aload         11
       133: aload         9
       135: aload_3
       136: aload         4
       138: invokespecial #325                // InterfaceMethod leftNewCount$1:(Ljava/lang/Object;Lscala/collection/immutable/IndexedSeq;Lorg/scalactic/Equality;Lscala/runtime/LazyRef;)Lscala/collection/immutable/IndexedSeq;
       141: aload_3
       142: aload         4
       144: invokespecial #327                // InterfaceMethod rightNewCount$1:(Ljava/lang/Object;Lscala/collection/immutable/IndexedSeq;Lorg/scalactic/Equality;Lscala/runtime/LazyRef;)Lscala/collection/immutable/IndexedSeq;
       147: astore        7
       149: goto          168
       152: goto          158
       155: goto          158
       158: new           #329                // class scala/MatchError
       161: dup
       162: aload         8
       164: invokespecial #332                // Method scala/MatchError."<init>":(Ljava/lang/Object;)V
       167: athrow
       168: aload         7
       170: areturn
      StackMapTable: number_of_entries = 9
        frame_type = 255 /* full_frame */
          offset_delta = 79
          locals = [ class org/scalatest/enablers/AggregatingImpls, class java/lang/Object, class scala/runtime/LazyRef, class org/scalactic/Equality, class scala/runtime/LazyRef, class scala/collection/immutable/IndexedSeq, class scala/Tuple2, top, class scala/Tuple2, class scala/collection/immutable/IndexedSeq, class scala/Tuple2, class java/lang/Object, class java/lang/Object, class org/scalatest/enablers/AggregatingImpls$ZipNoMatch$1$ ]
          stack = [ class java/lang/Object ]
        frame_type = 7 /* same */
        frame_type = 255 /* full_frame */
          offset_delta = 21
          locals = [ class org/scalatest/enablers/AggregatingImpls, class java/lang/Object, class scala/runtime/LazyRef, class org/scalactic/Equality, class scala/runtime/LazyRef, class scala/collection/immutable/IndexedSeq, class scala/Tuple2, top, class scala/Tuple2, class scala/collection/immutable/IndexedSeq, class scala/Tuple2, class java/lang/Object, class java/lang/Object, class org/scalatest/enablers/AggregatingImpls$ZipNoMatch$1$, class org/scalatest/enablers/AggregatingImpls$ZipNoMatch$1$ ]
          stack = [ class java/lang/Object ]
        frame_type = 250 /* chop */
          offset_delta = 7
        frame_type = 252 /* append */
          offset_delta = 9
          locals = [ class org/scalatest/enablers/AggregatingImpls$ZipNoMatch$1$ ]
        frame_type = 255 /* full_frame */
          offset_delta = 24
          locals = [ class org/scalatest/enablers/AggregatingImpls, class java/lang/Object, class scala/runtime/LazyRef, class org/scalactic/Equality, class scala/runtime/LazyRef, class scala/collection/immutable/IndexedSeq, class scala/Tuple2, top, class scala/Tuple2, class scala/collection/immutable/IndexedSeq, class scala/Tuple2 ]
          stack = []
        frame_type = 249 /* chop */
          offset_delta = 2
        frame_type = 2 /* same */
        frame_type = 255 /* full_frame */
          offset_delta = 9
          locals = [ class org/scalatest/enablers/AggregatingImpls, class java/lang/Object, class scala/runtime/LazyRef, class org/scalactic/Equality, class scala/runtime/LazyRef, class scala/collection/immutable/IndexedSeq, class scala/Tuple2, class scala/collection/immutable/IndexedSeq, class scala/Tuple2, class scala/collection/immutable/IndexedSeq, class scala/Tuple2, class java/lang/Object, class java/lang/Object, class org/scalatest/enablers/AggregatingImpls$ZipNoMatch$1$, class org/scalatest/enablers/AggregatingImpls$ZipNoMatch$1$ ]
          stack = []
      LineNumberTable:
        line 151: 0
        line 152: 57
        line 153: 117
        line 154: 127
        line 151: 152
      LocalVariableTable:
        Start  Length  Slot  Name   Signature
           50     102    11 nextLeft   Ljava/lang/Object;
           57      95    12 nextRight   Ljava/lang/Object;
           28     127     9 count   Lscala/collection/immutable/IndexedSeq;
            0     171     0 $this   Lorg/scalatest/enablers/AggregatingImpls;
            0     171     1 nonLocalReturnKey1$1   Ljava/lang/Object;
            0     171     2 ZipNoMatch$module$1   Lscala/runtime/LazyRef;
            0     171     3 equality$1   Lorg/scalactic/Equality;
            0     171     4 ElementCount$module$1   Lscala/runtime/LazyRef;
            0     171     5  x0$1   Lscala/collection/immutable/IndexedSeq;
            0     171     6  x1$1   Lscala/Tuple2;
    MethodParameters:
      Name                           Flags
      $this                          final synthetic
      nonLocalReturnKey1$1           final
      ZipNoMatch$module$1            final
      equality$1                     final
      ElementCount$module$1          final
      x0$1                           final
      x1$1                           final

  public static boolean $anonfun$checkTheSameElementsAs$7(org.scalatest.enablers.AggregatingImpls, org.scalatest.enablers.AggregatingImpls$ElementCount$1, org.scalactic.Equality, org.scalatest.enablers.AggregatingImpls$ElementCount$1);
    descriptor: (Lorg/scalatest/enablers/AggregatingImpls;Lorg/scalatest/enablers/AggregatingImpls$ElementCount$1;Lorg/scalactic/Equality;Lorg/scalatest/enablers/AggregatingImpls$ElementCount$1;)Z
    flags: (0x1009) ACC_PUBLIC, ACC_STATIC, ACC_SYNTHETIC
    Code:
      stack=4, locals=4, args_size=4
         0: aload_0
         1: aload_1
         2: invokevirtual #237                // Method org/scalatest/enablers/AggregatingImpls$ElementCount$1.element:()Ljava/lang/Object;
         5: aload_3
         6: invokevirtual #237                // Method org/scalatest/enablers/AggregatingImpls$ElementCount$1.element:()Ljava/lang/Object;
         9: aload_2
        10: invokeinterface #32,  4           // InterfaceMethod tryEquality:(Ljava/lang/Object;Ljava/lang/Object;Lorg/scalactic/Equality;)Z
        15: ireturn
      LineNumberTable:
        line 158: 0
      LocalVariableTable:
        Start  Length  Slot  Name   Signature
            0      16     0 $this   Lorg/scalatest/enablers/AggregatingImpls;
            0      16     1 next$3   Lorg/scalatest/enablers/AggregatingImpls$ElementCount$1;
            0      16     2 equality$1   Lorg/scalactic/Equality;
            0      16     3    ec   Lorg/scalatest/enablers/AggregatingImpls$ElementCount$1;
    MethodParameters:
      Name                           Flags
      $this                          final synthetic
      next$3                         final
      equality$1                     final
      ec                             final

  public static scala.collection.immutable.IndexedSeq $anonfun$checkTheSameElementsAs$6(org.scalatest.enablers.AggregatingImpls, org.scalactic.Equality, scala.runtime.LazyRef, scala.collection.immutable.IndexedSeq, org.scalatest.enablers.AggregatingImpls$ElementCount$1);
    descriptor: (Lorg/scalatest/enablers/AggregatingImpls;Lorg/scalactic/Equality;Lscala/runtime/LazyRef;Lscala/collection/immutable/IndexedSeq;Lorg/scalatest/enablers/AggregatingImpls$ElementCount$1;)Lscala/collection/immutable/IndexedSeq;
    flags: (0x1009) ACC_PUBLIC, ACC_STATIC, ACC_SYNTHETIC
    Code:
      stack=7, locals=11, args_size=5
         0: new           #305                // class scala/Tuple2
         3: dup
         4: aload_3
         5: aload         4
         7: invokespecial #308                // Method scala/Tuple2."<init>":(Ljava/lang/Object;Ljava/lang/Object;)V
        10: astore        6
        12: aload         6
        14: ifnull        142
        17: aload         6
        19: invokevirtual #311                // Method scala/Tuple2._1:()Ljava/lang/Object;
        22: checkcast     #133                // class scala/collection/immutable/IndexedSeq
        25: astore        7
        27: aload         6
        29: invokevirtual #314                // Method scala/Tuple2._2:()Ljava/lang/Object;
        32: checkcast     #15                 // class org/scalatest/enablers/AggregatingImpls$ElementCount$1
        35: astore        8
        37: aload         7
        39: aload_0
        40: aload         8
        42: aload_1
        43: invokedynamic #350,  0            // InvokeDynamic #8:apply:(Lorg/scalatest/enablers/AggregatingImpls;Lorg/scalatest/enablers/AggregatingImpls$ElementCount$1;Lorg/scalactic/Equality;)Lscala/Function1;
        48: invokeinterface #253,  2          // InterfaceMethod scala/collection/immutable/IndexedSeq.indexWhere:(Lscala/Function1;)I
        53: istore        9
        55: iload         9
        57: iconst_0
        58: if_icmplt     125
        61: aload         7
        63: iload         9
        65: invokeinterface #256,  2          // InterfaceMethod scala/collection/immutable/IndexedSeq.apply:(I)Ljava/lang/Object;
        70: checkcast     #15                 // class org/scalatest/enablers/AggregatingImpls$ElementCount$1
        73: astore        10
        75: aload         7
        77: iload         9
        79: aload_0
        80: aload_2
        81: invokespecial #258                // InterfaceMethod ElementCount$3:(Lscala/runtime/LazyRef;)Lorg/scalatest/enablers/AggregatingImpls$ElementCount$2$;
        84: aload         10
        86: invokevirtual #237                // Method org/scalatest/enablers/AggregatingImpls$ElementCount$1.element:()Ljava/lang/Object;
        89: aload         10
        91: invokevirtual #262                // Method org/scalatest/enablers/AggregatingImpls$ElementCount$1.leftCount:()I
        94: aload         8
        96: invokevirtual #262                // Method org/scalatest/enablers/AggregatingImpls$ElementCount$1.leftCount:()I
        99: iadd
       100: aload         10
       102: invokevirtual #265                // Method org/scalatest/enablers/AggregatingImpls$ElementCount$1.rightCount:()I
       105: aload         8
       107: invokevirtual #265                // Method org/scalatest/enablers/AggregatingImpls$ElementCount$1.rightCount:()I
       110: iadd
       111: invokevirtual #268                // Method org/scalatest/enablers/AggregatingImpls$ElementCount$2$.apply:(Ljava/lang/Object;II)Lorg/scalatest/enablers/AggregatingImpls$ElementCount$1;
       114: invokeinterface #272,  3          // InterfaceMethod scala/collection/immutable/IndexedSeq.updated:(ILjava/lang/Object;)Ljava/lang/Object;
       119: checkcast     #133                // class scala/collection/immutable/IndexedSeq
       122: goto          137
       125: aload         7
       127: aload         8
       129: invokeinterface #275,  2          // InterfaceMethod scala/collection/immutable/IndexedSeq.$colon$plus:(Ljava/lang/Object;)Ljava/lang/Object;
       134: checkcast     #133                // class scala/collection/immutable/IndexedSeq
       137: astore        5
       139: goto          155
       142: goto          145
       145: new           #329                // class scala/MatchError
       148: dup
       149: aload         6
       151: invokespecial #332                // Method scala/MatchError."<init>":(Ljava/lang/Object;)V
       154: athrow
       155: aload         5
       157: areturn
      StackMapTable: number_of_entries = 5
        frame_type = 255 /* full_frame */
          offset_delta = 125
          locals = [ class org/scalatest/enablers/AggregatingImpls, class org/scalactic/Equality, class scala/runtime/LazyRef, class scala/collection/immutable/IndexedSeq, class org/scalatest/enablers/AggregatingImpls$ElementCount$1, top, class scala/Tuple2, class scala/collection/immutable/IndexedSeq, class org/scalatest/enablers/AggregatingImpls$ElementCount$1, int ]
          stack = []
        frame_type = 75 /* same_locals_1_stack_item */
          stack = [ class scala/collection/immutable/IndexedSeq ]
        frame_type = 248 /* chop */
          offset_delta = 4
        frame_type = 2 /* same */
        frame_type = 255 /* full_frame */
          offset_delta = 9
          locals = [ class org/scalatest/enablers/AggregatingImpls, class org/scalactic/Equality, class scala/runtime/LazyRef, class scala/collection/immutable/IndexedSeq, class org/scalatest/enablers/AggregatingImpls$ElementCount$1, class scala/collection/immutable/IndexedSeq, class scala/Tuple2, class scala/collection/immutable/IndexedSeq, class org/scalatest/enablers/AggregatingImpls$ElementCount$1, int ]
          stack = []
      LineNumberTable:
        line 157: 0
        line 158: 37
        line 159: 55
        line 160: 61
        line 161: 75
        line 164: 125
        line 157: 142
      LocalVariableTable:
        Start  Length  Slot  Name   Signature
           75      47    10 currentElementCount   Lorg/scalatest/enablers/AggregatingImpls$ElementCount$1;
           55      82     9   idx   I
           27     115     7 count   Lscala/collection/immutable/IndexedSeq;
           37     105     8  next   Lorg/scalatest/enablers/AggregatingImpls$ElementCount$1;
            0     158     0 $this   Lorg/scalatest/enablers/AggregatingImpls;
            0     158     1 equality$1   Lorg/scalactic/Equality;
            0     158     2 ElementCount$module$1   Lscala/runtime/LazyRef;
            0     158     3  x0$3   Lscala/collection/immutable/IndexedSeq;
            0     158     4  x1$3   Lorg/scalatest/enablers/AggregatingImpls$ElementCount$1;
    MethodParameters:
      Name                           Flags
      $this                          final synthetic
      equality$1                     final
      ElementCount$module$1          final
      x0$3                           final
      x1$3                           final

  public static scala.collection.immutable.IndexedSeq $anonfun$checkTheSameElementsAs$5(org.scalatest.enablers.AggregatingImpls, org.scalactic.Equality, scala.runtime.LazyRef, scala.collection.immutable.IndexedSeq, scala.collection.immutable.IndexedSeq);
    descriptor: (Lorg/scalatest/enablers/AggregatingImpls;Lorg/scalactic/Equality;Lscala/runtime/LazyRef;Lscala/collection/immutable/IndexedSeq;Lscala/collection/immutable/IndexedSeq;)Lscala/collection/immutable/IndexedSeq;
    flags: (0x1009) ACC_PUBLIC, ACC_STATIC, ACC_SYNTHETIC
    Code:
      stack=5, locals=9, args_size=5
         0: new           #305                // class scala/Tuple2
         3: dup
         4: aload_3
         5: aload         4
         7: invokespecial #308                // Method scala/Tuple2."<init>":(Ljava/lang/Object;Ljava/lang/Object;)V
        10: astore        6
        12: aload         6
        14: ifnull        62
        17: aload         6
        19: invokevirtual #311                // Method scala/Tuple2._1:()Ljava/lang/Object;
        22: checkcast     #133                // class scala/collection/immutable/IndexedSeq
        25: astore        7
        27: aload         6
        29: invokevirtual #314                // Method scala/Tuple2._2:()Ljava/lang/Object;
        32: checkcast     #133                // class scala/collection/immutable/IndexedSeq
        35: astore        8
        37: aload         8
        39: aload         7
        41: aload_0
        42: aload_1
        43: aload_2
        44: invokedynamic #358,  0            // InvokeDynamic #9:apply:(Lorg/scalatest/enablers/AggregatingImpls;Lorg/scalactic/Equality;Lscala/runtime/LazyRef;)Lscala/Function2;
        49: invokeinterface #362,  3          // InterfaceMethod scala/collection/immutable/IndexedSeq.foldLeft:(Ljava/lang/Object;Lscala/Function2;)Ljava/lang/Object;
        54: checkcast     #133                // class scala/collection/immutable/IndexedSeq
        57: astore        5
        59: goto          75
        62: goto          65
        65: new           #329                // class scala/MatchError
        68: dup
        69: aload         6
        71: invokespecial #332                // Method scala/MatchError."<init>":(Ljava/lang/Object;)V
        74: athrow
        75: aload         5
        77: areturn
      StackMapTable: number_of_entries = 3
        frame_type = 253 /* append */
          offset_delta = 62
          locals = [ top, class scala/Tuple2 ]
        frame_type = 2 /* same */
        frame_type = 255 /* full_frame */
          offset_delta = 9
          locals = [ class org/scalatest/enablers/AggregatingImpls, class org/scalactic/Equality, class scala/runtime/LazyRef, class scala/collection/immutable/IndexedSeq, class scala/collection/immutable/IndexedSeq, class scala/collection/immutable/IndexedSeq, class scala/Tuple2, class scala/collection/immutable/IndexedSeq, class scala/collection/immutable/IndexedSeq ]
          stack = []
      LineNumberTable:
        line 156: 0
        line 157: 37
        line 156: 62
      LocalVariableTable:
        Start  Length  Slot  Name   Signature
           27      35     7 count1   Lscala/collection/immutable/IndexedSeq;
           37      25     8 count2   Lscala/collection/immutable/IndexedSeq;
            0      78     0 $this   Lorg/scalatest/enablers/AggregatingImpls;
            0      78     1 equality$1   Lorg/scalactic/Equality;
            0      78     2 ElementCount$module$1   Lscala/runtime/LazyRef;
            0      78     3  x0$2   Lscala/collection/immutable/IndexedSeq;
            0      78     4  x1$2   Lscala/collection/immutable/IndexedSeq;
    MethodParameters:
      Name                           Flags
      $this                          final synthetic
      equality$1                     final
      ElementCount$module$1          final
      x0$2                           final
      x1$2                           final

  public static boolean $anonfun$checkTheSameElementsAs$8(org.scalatest.enablers.AggregatingImpls$ElementCount$1);
    descriptor: (Lorg/scalatest/enablers/AggregatingImpls$ElementCount$1;)Z
    flags: (0x1009) ACC_PUBLIC, ACC_STATIC, ACC_SYNTHETIC
    Code:
      stack=2, locals=1, args_size=1
         0: aload_0
         1: invokevirtual #262                // Method org/scalatest/enablers/AggregatingImpls$ElementCount$1.leftCount:()I
         4: aload_0
         5: invokevirtual #265                // Method org/scalatest/enablers/AggregatingImpls$ElementCount$1.rightCount:()I
         8: if_icmpeq     15
        11: iconst_1
        12: goto          16
        15: iconst_0
        16: ireturn
      StackMapTable: number_of_entries = 2
        frame_type = 15 /* same */
        frame_type = 64 /* same_locals_1_stack_item */
          stack = [ int ]
      LineNumberTable:
        line 169: 0
      LocalVariableTable:
        Start  Length  Slot  Name   Signature
            0      17     0     e   Lorg/scalatest/enablers/AggregatingImpls$ElementCount$1;
    MethodParameters:
      Name                           Flags
      e                              final

  public static boolean $anonfun$checkOnly$2(org.scalatest.enablers.AggregatingImpls, java.lang.Object, org.scalactic.Equality, java.lang.Object);
    descriptor: (Lorg/scalatest/enablers/AggregatingImpls;Ljava/lang/Object;Lorg/scalactic/Equality;Ljava/lang/Object;)Z
    flags: (0x1009) ACC_PUBLIC, ACC_STATIC, ACC_SYNTHETIC
    Code:
      stack=4, locals=4, args_size=4
         0: aload_0
         1: aload_1
         2: aload_3
         3: aload_2
         4: invokeinterface #32,  4           // InterfaceMethod tryEquality:(Ljava/lang/Object;Ljava/lang/Object;Lorg/scalactic/Equality;)Z
         9: ireturn
      LineNumberTable:
        line 173: 0
      LocalVariableTable:
        Start  Length  Slot  Name   Signature
            0      10     0 $this   Lorg/scalatest/enablers/AggregatingImpls;
            0      10     1   l$1   Ljava/lang/Object;
            0      10     2 equality$2   Lorg/scalactic/Equality;
            0      10     3     r   Ljava/lang/Object;
    MethodParameters:
      Name                           Flags
      $this                          final synthetic
      l$1                            final
      equality$2                     final
      r                              final

  public static boolean $anonfun$checkOnly$1(org.scalatest.enablers.AggregatingImpls, scala.collection.Iterable, org.scalactic.Equality, java.lang.Object);
    descriptor: (Lorg/scalatest/enablers/AggregatingImpls;Lscala/collection/Iterable;Lorg/scalactic/Equality;Ljava/lang/Object;)Z
    flags: (0x1009) ACC_PUBLIC, ACC_STATIC, ACC_SYNTHETIC
    Code:
      stack=4, locals=4, args_size=4
         0: aload_1
         1: aload_0
         2: aload_3
         3: aload_2
         4: invokedynamic #382,  0            // InvokeDynamic #10:apply:(Lorg/scalatest/enablers/AggregatingImpls;Ljava/lang/Object;Lorg/scalactic/Equality;)Lscala/Function1;
         9: invokeinterface #386,  2          // InterfaceMethod scala/collection/Iterable.find:(Lscala/Function1;)Lscala/Option;
        14: invokevirtual #391                // Method scala/Option.isDefined:()Z
        17: ireturn
      LineNumberTable:
        line 173: 0
      LocalVariableTable:
        Start  Length  Slot  Name   Signature
            0      18     0 $this   Lorg/scalatest/enablers/AggregatingImpls;
            0      18     1 right$1   Lscala/collection/Iterable;
            0      18     2 equality$2   Lorg/scalactic/Equality;
            0      18     3     l   Ljava/lang/Object;
    MethodParameters:
      Name                           Flags
      $this                          final synthetic
      right$1                        final
      equality$2                     final
      l                              final

  public static boolean $anonfun$checkOnly$4(org.scalatest.enablers.AggregatingImpls, java.lang.Object, org.scalactic.Equality, java.lang.Object);
    descriptor: (Lorg/scalatest/enablers/AggregatingImpls;Ljava/lang/Object;Lorg/scalactic/Equality;Ljava/lang/Object;)Z
    flags: (0x1009) ACC_PUBLIC, ACC_STATIC, ACC_SYNTHETIC
    Code:
      stack=4, locals=4, args_size=4
         0: aload_0
         1: aload_3
         2: aload_1
         3: aload_2
         4: invokeinterface #32,  4           // InterfaceMethod tryEquality:(Ljava/lang/Object;Ljava/lang/Object;Lorg/scalactic/Equality;)Z
         9: ireturn
      LineNumberTable:
        line 174: 0
      LocalVariableTable:
        Start  Length  Slot  Name   Signature
            0      10     0 $this   Lorg/scalatest/enablers/AggregatingImpls;
            0      10     1   r$1   Ljava/lang/Object;
            0      10     2 equality$2   Lorg/scalactic/Equality;
            0      10     3     l   Ljava/lang/Object;
    MethodParameters:
      Name                           Flags
      $this                          final synthetic
      r$1                            final
      equality$2                     final
      l                              final

  public static boolean $anonfun$checkOnly$3(org.scalatest.enablers.AggregatingImpls, scala.collection.Iterable, org.scalactic.Equality, java.lang.Object);
    descriptor: (Lorg/scalatest/enablers/AggregatingImpls;Lscala/collection/Iterable;Lorg/scalactic/Equality;Ljava/lang/Object;)Z
    flags: (0x1009) ACC_PUBLIC, ACC_STATIC, ACC_SYNTHETIC
    Code:
      stack=4, locals=4, args_size=4
         0: aload_1
         1: aload_0
         2: aload_3
         3: aload_2
         4: invokedynamic #400,  0            // InvokeDynamic #11:apply:(Lorg/scalatest/enablers/AggregatingImpls;Ljava/lang/Object;Lorg/scalactic/Equality;)Lscala/Function1;
         9: invokeinterface #386,  2          // InterfaceMethod scala/collection/Iterable.find:(Lscala/Function1;)Lscala/Option;
        14: invokevirtual #391                // Method scala/Option.isDefined:()Z
        17: ireturn
      LineNumberTable:
        line 174: 0
      LocalVariableTable:
        Start  Length  Slot  Name   Signature
            0      18     0 $this   Lorg/scalatest/enablers/AggregatingImpls;
            0      18     1 left$1   Lscala/collection/Iterable;
            0      18     2 equality$2   Lorg/scalactic/Equality;
            0      18     3     r   Ljava/lang/Object;
    MethodParameters:
      Name                           Flags
      $this                          final synthetic
      left$1                         final
      equality$2                     final
      r                              final

  public static boolean $anonfun$checkAllOf$1(org.scalactic.Equality, java.lang.Object, java.lang.Object);
    descriptor: (Lorg/scalactic/Equality;Ljava/lang/Object;Ljava/lang/Object;)Z
    flags: (0x1009) ACC_PUBLIC, ACC_STATIC, ACC_SYNTHETIC
    Code:
      stack=3, locals=3, args_size=3
         0: aload_0
         1: aload_2
         2: aload_1
         3: invokeinterface #44,  3           // InterfaceMethod org/scalactic/Equality.areEqual:(Ljava/lang/Object;Ljava/lang/Object;)Z
         8: ireturn
      LineNumberTable:
        line 181: 0
      LocalVariableTable:
        Start  Length  Slot  Name   Signature
            0       9     0 equality$3   Lorg/scalactic/Equality;
            0       9     1 nextRight$1   Ljava/lang/Object;
            0       9     2     t   Ljava/lang/Object;
    MethodParameters:
      Name                           Flags
      equality$3                     final
      nextRight$1                    final
      t                              final

  private boolean checkEqual$1(scala.collection.Iterable, scala.collection.Iterator, org.scalactic.Equality);
    descriptor: (Lscala/collection/Iterable;Lscala/collection/Iterator;Lorg/scalactic/Equality;)Z
    flags: (0x0002) ACC_PRIVATE
    Code:
      stack=3, locals=6, args_size=4
         0: aload_2
         1: invokeinterface #411,  1          // InterfaceMethod scala/collection/Iterator.hasNext:()Z
         6: ifeq          45
         9: aload_2
        10: invokeinterface #413,  1          // InterfaceMethod scala/collection/Iterator.next:()Ljava/lang/Object;
        15: astore        5
        17: aload_1
        18: aload_3
        19: aload         5
        21: invokedynamic #421,  0            // InvokeDynamic #12:apply:(Lorg/scalactic/Equality;Ljava/lang/Object;)Lscala/Function1;
        26: invokeinterface #422,  2          // InterfaceMethod scala/collection/Iterable.exists:(Lscala/Function1;)Z
        31: ifeq          41
        34: aload_1
        35: aload_2
        36: astore_2
        37: astore_1
        38: goto          0
        41: iconst_0
        42: goto          46
        45: iconst_1
        46: ireturn
      StackMapTable: number_of_entries = 4
        frame_type = 0 /* same */
        frame_type = 253 /* append */
          offset_delta = 40
          locals = [ top, class java/lang/Object ]
        frame_type = 249 /* chop */
          offset_delta = 3
        frame_type = 64 /* same_locals_1_stack_item */
          stack = [ int ]
      LineNumberTable:
        line 179: 0
        line 180: 9
        line 181: 17
        line 182: 34
        line 184: 41
        line 187: 45
      LocalVariableTable:
        Start  Length  Slot  Name   Signature
           17      25     5 nextRight   Ljava/lang/Object;
            0      47     0  this   Lorg/scalatest/enablers/AggregatingImpls;
            0      47     1  left   Lscala/collection/Iterable;
            0      47     2 rightItr   Lscala/collection/Iterator;
            0      47     3 equality$3   Lorg/scalactic/Equality;
    MethodParameters:
      Name                           Flags
      left                           final
      rightItr                       final
      equality$3                     final

  public static int $anonfun$checkAtMostOneOf$1();
    descriptor: ()I
    flags: (0x1009) ACC_PUBLIC, ACC_STATIC, ACC_SYNTHETIC
    Code:
      stack=1, locals=0, args_size=0
         0: iconst_0
         1: ireturn
      LineNumberTable:
        line 195: 0

  public static boolean $anonfun$checkAtMostOneOf$3(org.scalactic.Equality, java.lang.Object, java.lang.Object);
    descriptor: (Lorg/scalactic/Equality;Ljava/lang/Object;Ljava/lang/Object;)Z
    flags: (0x1009) ACC_PUBLIC, ACC_STATIC, ACC_SYNTHETIC
    Code:
      stack=3, locals=3, args_size=3
         0: aload_0
         1: aload_2
         2: aload_1
         3: invokeinterface #44,  3           // InterfaceMethod org/scalactic/Equality.areEqual:(Ljava/lang/Object;Ljava/lang/Object;)Z
         8: ireturn
      LineNumberTable:
        line 197: 0
      LocalVariableTable:
        Start  Length  Slot  Name   Signature
            0       9     0 equality$4   Lorg/scalactic/Equality;
            0       9     1 nextRight$2   Ljava/lang/Object;
            0       9     2     l   Ljava/lang/Object;
    MethodParameters:
      Name                           Flags
      equality$4                     final
      nextRight$2                    final
      l                              final

  public static int $anonfun$checkAtMostOneOf$2(scala.collection.Iterable, org.scalactic.Equality, java.lang.Object, int, java.lang.Object);
    descriptor: (Lscala/collection/Iterable;Lorg/scalactic/Equality;Ljava/lang/Object;ILjava/lang/Object;)I
    flags: (0x1009) ACC_PUBLIC, ACC_STATIC, ACC_SYNTHETIC
    Code:
      stack=4, locals=10, args_size=5
         0: new           #305                // class scala/Tuple2
         3: dup
         4: iload_3
         5: invokestatic  #437                // Method scala/runtime/BoxesRunTime.boxToInteger:(I)Ljava/lang/Integer;
         8: aload         4
        10: invokespecial #308                // Method scala/Tuple2."<init>":(Ljava/lang/Object;Ljava/lang/Object;)V
        13: astore        6
        15: aload         6
        17: ifnull        86
        20: aload         6
        22: invokevirtual #440                // Method scala/Tuple2._1$mcI$sp:()I
        25: istore        7
        27: aload         6
        29: invokevirtual #314                // Method scala/Tuple2._2:()Ljava/lang/Object;
        32: astore        8
        34: aload_0
        35: aload_1
        36: aload         8
        38: invokedynamic #445,  0            // InvokeDynamic #13:apply:(Lorg/scalactic/Equality;Ljava/lang/Object;)Lscala/Function1;
        43: invokeinterface #422,  2          // InterfaceMethod scala/collection/Iterable.exists:(Lscala/Function1;)Z
        48: ifeq          79
        51: iload         7
        53: iconst_1
        54: iadd
        55: istore        9
        57: iload         9
        59: iconst_1
        60: if_icmple     74
        63: new           #447                // class scala/runtime/NonLocalReturnControl$mcI$sp
        66: dup
        67: aload_2
        68: iload         9
        70: invokespecial #450                // Method scala/runtime/NonLocalReturnControl$mcI$sp."<init>":(Ljava/lang/Object;I)V
        73: athrow
        74: iload         9
        76: goto          81
        79: iload         7
        81: istore        5
        83: goto          99
        86: goto          89
        89: new           #329                // class scala/MatchError
        92: dup
        93: aload         6
        95: invokespecial #332                // Method scala/MatchError."<init>":(Ljava/lang/Object;)V
        98: athrow
        99: iload         5
       101: ireturn
      StackMapTable: number_of_entries = 6
        frame_type = 255 /* full_frame */
          offset_delta = 74
          locals = [ class scala/collection/Iterable, class org/scalactic/Equality, class java/lang/Object, int, class java/lang/Object, top, class scala/Tuple2, int, class java/lang/Object, int ]
          stack = []
        frame_type = 250 /* chop */
          offset_delta = 4
        frame_type = 65 /* same_locals_1_stack_item */
          stack = [ int ]
        frame_type = 249 /* chop */
          offset_delta = 4
        frame_type = 2 /* same */
        frame_type = 255 /* full_frame */
          offset_delta = 9
          locals = [ class scala/collection/Iterable, class org/scalactic/Equality, class java/lang/Object, int, class java/lang/Object, int, class scala/Tuple2, int, class java/lang/Object ]
          stack = []
      LineNumberTable:
        line 196: 0
        line 197: 34
        line 198: 51
        line 199: 57
        line 200: 63
        line 202: 74
        line 205: 79
        line 196: 86
      LocalVariableTable:
        Start  Length  Slot  Name   Signature
           57      19     9 newCount   I
           27      59     7 count   I
           34      52     8 nextRight   Ljava/lang/Object;
            0     102     0 left$2   Lscala/collection/Iterable;
            0     102     1 equality$4   Lorg/scalactic/Equality;
            0     102     2 nonLocalReturnKey2$1   Ljava/lang/Object;
            0     102     3  x0$1   I
            0     102     4  x1$1   Ljava/lang/Object;
    MethodParameters:
      Name                           Flags
      left$2                         final
      equality$4                     final
      nonLocalReturnKey2$1           final
      x0$1                           final
      x1$1                           final

  public static int $anonfun$checkAtMostOneOf$4(int, int);
    descriptor: (II)I
    flags: (0x1009) ACC_PUBLIC, ACC_STATIC, ACC_SYNTHETIC
    Code:
      stack=4, locals=6, args_size=2
         0: new           #455                // class scala/Tuple2$mcII$sp
         3: dup
         4: iload_0
         5: iload_1
         6: invokespecial #458                // Method scala/Tuple2$mcII$sp."<init>":(II)V
         9: astore_3
        10: aload_3
        11: ifnull        35
        14: aload_3
        15: invokevirtual #440                // Method scala/Tuple2._1$mcI$sp:()I
        18: istore        4
        20: aload_3
        21: invokevirtual #461                // Method scala/Tuple2._2$mcI$sp:()I
        24: istore        5
        26: iload         4
        28: iload         5
        30: iadd
        31: istore_2
        32: goto          47
        35: goto          38
        38: new           #329                // class scala/MatchError
        41: dup
        42: aload_3
        43: invokespecial #332                // Method scala/MatchError."<init>":(Ljava/lang/Object;)V
        46: athrow
        47: iload_2
        48: ireturn
      StackMapTable: number_of_entries = 3
        frame_type = 253 /* append */
          offset_delta = 35
          locals = [ top, class scala/Tuple2$mcII$sp ]
        frame_type = 2 /* same */
        frame_type = 255 /* full_frame */
          offset_delta = 8
          locals = [ int, int, int, class scala/Tuple2$mcII$sp, int, int ]
          stack = []
      LineNumberTable:
        line 207: 0
      LocalVariableTable:
        Start  Length  Slot  Name   Signature
           20      15     4 count1   I
           26       9     5 count2   I
            0      49     0  x0$2   I
            0      49     1  x1$2   I
    MethodParameters:
      Name                           Flags
      x0$2                           final
      x1$2                           final

  private static int countElements$1(scala.collection.Iterable, scala.collection.Iterable, org.scalactic.Equality);
    descriptor: (Lscala/collection/Iterable;Lscala/collection/Iterable;Lorg/scalactic/Equality;)I
    flags: (0x000a) ACC_PRIVATE, ACC_STATIC
    Code:
      stack=6, locals=5, args_size=3
         0: new           #4                  // class java/lang/Object
         3: dup
         4: invokespecial #61                 // Method java/lang/Object."<init>":()V
         7: astore_3
         8: getstatic     #70                 // Field org/scalactic/ColCompatHelper$.MODULE$:Lorg/scalactic/ColCompatHelper$;
        11: aload_0
        12: invokedynamic #470,  0            // InvokeDynamic #14:apply$mcI$sp:()Lscala/runtime/java8/JFunction0$mcI$sp;
        17: aload_1
        18: aload_2
        19: aload_3
        20: invokedynamic #478,  0            // InvokeDynamic #15:apply:(Lscala/collection/Iterable;Lorg/scalactic/Equality;Ljava/lang/Object;)Lscala/Function2;
        25: invokedynamic #486,  0            // InvokeDynamic #16:apply$mcIII$sp:()Lscala/runtime/java8/JFunction2$mcIII$sp;
        30: invokevirtual #131                // Method org/scalactic/ColCompatHelper$.aggregate:(Lscala/collection/Iterable;Lscala/Function0;Lscala/Function2;Lscala/Function2;)Ljava/lang/Object;
        33: invokestatic  #490                // Method scala/runtime/BoxesRunTime.unboxToInt:(Ljava/lang/Object;)I
        36: goto          64
        39: astore        4
        41: aload         4
        43: invokevirtual #151                // Method scala/runtime/NonLocalReturnControl.key:()Ljava/lang/Object;
        46: aload_3
        47: if_acmpne     58
        50: aload         4
        52: invokevirtual #493                // Method scala/runtime/NonLocalReturnControl.value$mcI$sp:()I
        55: goto          61
        58: aload         4
        60: athrow
        61: goto          64
        64: ireturn
      Exception table:
         from    to  target type
             8    36    39   Class scala/runtime/NonLocalReturnControl
      StackMapTable: number_of_entries = 4
        frame_type = 255 /* full_frame */
          offset_delta = 39
          locals = [ class scala/collection/Iterable, class scala/collection/Iterable, class org/scalactic/Equality, class java/lang/Object ]
          stack = [ class scala/runtime/NonLocalReturnControl ]
        frame_type = 252 /* append */
          offset_delta = 18
          locals = [ class scala/runtime/NonLocalReturnControl ]
        frame_type = 66 /* same_locals_1_stack_item */
          stack = [ int ]
        frame_type = 255 /* full_frame */
          offset_delta = 2
          locals = [ class scala/collection/Iterable, class scala/collection/Iterable, class org/scalactic/Equality, class java/lang/Object ]
          stack = [ int ]
      LineNumberTable:
        line 194: 0
        line 195: 8
        line 196: 17
        line 207: 25
        line 195: 41
      LocalVariableTable:
        Start  Length  Slot  Name   Signature
           39      22     4    ex   Lscala/runtime/NonLocalReturnControl;
            0      65     0 right$2   Lscala/collection/Iterable;
            0      65     1 left$2   Lscala/collection/Iterable;
            0      65     2 equality$4   Lorg/scalactic/Equality;
    MethodParameters:
      Name                           Flags
      right$2                        final
      left$2                         final
      equality$4                     final

  public static void $init$(org.scalatest.enablers.AggregatingImpls);
    descriptor: (Lorg/scalatest/enablers/AggregatingImpls;)V
    flags: (0x0009) ACC_PUBLIC, ACC_STATIC
    Code:
      stack=0, locals=1, args_size=1
         0: return
      LineNumberTable:
        line 118: 0
      LocalVariableTable:
        Start  Length  Slot  Name   Signature
            0       1     0 $this   Lorg/scalatest/enablers/AggregatingImpls;
    MethodParameters:
      Name                           Flags
      $this                          final synthetic

  public static java.lang.Object $anonfun$checkTheSameElementsAs$8$adapted(org.scalatest.enablers.AggregatingImpls$ElementCount$1);
    descriptor: (Lorg/scalatest/enablers/AggregatingImpls$ElementCount$1;)Ljava/lang/Object;
    flags: (0x1009) ACC_PUBLIC, ACC_STATIC, ACC_SYNTHETIC
    Code:
      stack=1, locals=1, args_size=1
         0: aload_0
         1: invokestatic  #496                // InterfaceMethod $anonfun$checkTheSameElementsAs$8:(Lorg/scalatest/enablers/AggregatingImpls$ElementCount$1;)Z
         4: invokestatic  #500                // Method scala/runtime/BoxesRunTime.boxToBoolean:(Z)Ljava/lang/Boolean;
         7: areturn
      LineNumberTable:
        line 169: 0
      LocalVariableTable:
        Start  Length  Slot  Name   Signature
            0       8     0     e   Lorg/scalatest/enablers/AggregatingImpls$ElementCount$1;
    MethodParameters:
      Name                           Flags
      e                              final

  public static java.lang.Object $anonfun$checkOnly$1$adapted(org.scalatest.enablers.AggregatingImpls, scala.collection.Iterable, org.scalactic.Equality, java.lang.Object);
    descriptor: (Lorg/scalatest/enablers/AggregatingImpls;Lscala/collection/Iterable;Lorg/scalactic/Equality;Ljava/lang/Object;)Ljava/lang/Object;
    flags: (0x1009) ACC_PUBLIC, ACC_STATIC, ACC_SYNTHETIC
    Code:
      stack=4, locals=4, args_size=4
         0: aload_0
         1: aload_1
         2: aload_2
         3: aload_3
         4: invokestatic  #502                // InterfaceMethod $anonfun$checkOnly$1:(Lorg/scalatest/enablers/AggregatingImpls;Lscala/collection/Iterable;Lorg/scalactic/Equality;Ljava/lang/Object;)Z
         7: invokestatic  #500                // Method scala/runtime/BoxesRunTime.boxToBoolean:(Z)Ljava/lang/Boolean;
        10: areturn
      LineNumberTable:
        line 173: 0
      LocalVariableTable:
        Start  Length  Slot  Name   Signature
            0      11     0 $this   Lorg/scalatest/enablers/AggregatingImpls;
            0      11     1 right$1   Lscala/collection/Iterable;
            0      11     2 equality$2   Lorg/scalactic/Equality;
            0      11     3     l   Ljava/lang/Object;
    MethodParameters:
      Name                           Flags
      $this                          final
      right$1                        final
      equality$2                     final
      l                              final

  public static java.lang.Object $anonfun$checkOnly$3$adapted(org.scalatest.enablers.AggregatingImpls, scala.collection.Iterable, org.scalactic.Equality, java.lang.Object);
    descriptor: (Lorg/scalatest/enablers/AggregatingImpls;Lscala/collection/Iterable;Lorg/scalactic/Equality;Ljava/lang/Object;)Ljava/lang/Object;
    flags: (0x1009) ACC_PUBLIC, ACC_STATIC, ACC_SYNTHETIC
    Code:
      stack=4, locals=4, args_size=4
         0: aload_0
         1: aload_1
         2: aload_2
         3: aload_3
         4: invokestatic  #504                // InterfaceMethod $anonfun$checkOnly$3:(Lorg/scalatest/enablers/AggregatingImpls;Lscala/collection/Iterable;Lorg/scalactic/Equality;Ljava/lang/Object;)Z
         7: invokestatic  #500                // Method scala/runtime/BoxesRunTime.boxToBoolean:(Z)Ljava/lang/Boolean;
        10: areturn
      LineNumberTable:
        line 174: 0
      LocalVariableTable:
        Start  Length  Slot  Name   Signature
            0      11     0 $this   Lorg/scalatest/enablers/AggregatingImpls;
            0      11     1 left$1   Lscala/collection/Iterable;
            0      11     2 equality$2   Lorg/scalactic/Equality;
            0      11     3     r   Ljava/lang/Object;
    MethodParameters:
      Name                           Flags
      $this                          final
      left$1                         final
      equality$2                     final
      r                              final

  public static java.lang.Object $anonfun$checkTheSameElementsAs$1$adapted(org.scalatest.enablers.AggregatingImpls, java.lang.Object, org.scalactic.Equality, org.scalatest.enablers.AggregatingImpls$ElementCount$1);
    descriptor: (Lorg/scalatest/enablers/AggregatingImpls;Ljava/lang/Object;Lorg/scalactic/Equality;Lorg/scalatest/enablers/AggregatingImpls$ElementCount$1;)Ljava/lang/Object;
    flags: (0x1009) ACC_PUBLIC, ACC_STATIC, ACC_SYNTHETIC
    Code:
      stack=4, locals=4, args_size=4
         0: aload_0
         1: aload_1
         2: aload_2
         3: aload_3
         4: invokestatic  #506                // InterfaceMethod $anonfun$checkTheSameElementsAs$1:(Lorg/scalatest/enablers/AggregatingImpls;Ljava/lang/Object;Lorg/scalactic/Equality;Lorg/scalatest/enablers/AggregatingImpls$ElementCount$1;)Z
         7: invokestatic  #500                // Method scala/runtime/BoxesRunTime.boxToBoolean:(Z)Ljava/lang/Boolean;
        10: areturn
      LineNumberTable:
        line 131: 0
      LocalVariableTable:
        Start  Length  Slot  Name   Signature
            0      11     0 $this   Lorg/scalatest/enablers/AggregatingImpls;
            0      11     1 next$1   Ljava/lang/Object;
            0      11     2 equality$1   Lorg/scalactic/Equality;
            0      11     3    ec   Lorg/scalatest/enablers/AggregatingImpls$ElementCount$1;
    MethodParameters:
      Name                           Flags
      $this                          final
      next$1                         final
      equality$1                     final
      ec                             final

  public static java.lang.Object $anonfun$checkTheSameElementsAs$2$adapted(org.scalatest.enablers.AggregatingImpls, java.lang.Object, org.scalactic.Equality, org.scalatest.enablers.AggregatingImpls$ElementCount$1);
    descriptor: (Lorg/scalatest/enablers/AggregatingImpls;Ljava/lang/Object;Lorg/scalactic/Equality;Lorg/scalatest/enablers/AggregatingImpls$ElementCount$1;)Ljava/lang/Object;
    flags: (0x1009) ACC_PUBLIC, ACC_STATIC, ACC_SYNTHETIC
    Code:
      stack=4, locals=4, args_size=4
         0: aload_0
         1: aload_1
         2: aload_2
         3: aload_3
         4: invokestatic  #508                // InterfaceMethod $anonfun$checkTheSameElementsAs$2:(Lorg/scalatest/enablers/AggregatingImpls;Ljava/lang/Object;Lorg/scalactic/Equality;Lorg/scalatest/enablers/AggregatingImpls$ElementCount$1;)Z
         7: invokestatic  #500                // Method scala/runtime/BoxesRunTime.boxToBoolean:(Z)Ljava/lang/Boolean;
        10: areturn
      LineNumberTable:
        line 141: 0
      LocalVariableTable:
        Start  Length  Slot  Name   Signature
            0      11     0 $this   Lorg/scalatest/enablers/AggregatingImpls;
            0      11     1 next$2   Ljava/lang/Object;
            0      11     2 equality$1   Lorg/scalactic/Equality;
            0      11     3    ec   Lorg/scalatest/enablers/AggregatingImpls$ElementCount$1;
    MethodParameters:
      Name                           Flags
      $this                          final
      next$2                         final
      equality$1                     final
      ec                             final

  public static java.lang.Object $anonfun$checkTheSameElementsAs$7$adapted(org.scalatest.enablers.AggregatingImpls, org.scalatest.enablers.AggregatingImpls$ElementCount$1, org.scalactic.Equality, org.scalatest.enablers.AggregatingImpls$ElementCount$1);
    descriptor: (Lorg/scalatest/enablers/AggregatingImpls;Lorg/scalatest/enablers/AggregatingImpls$ElementCount$1;Lorg/scalactic/Equality;Lorg/scalatest/enablers/AggregatingImpls$ElementCount$1;)Ljava/lang/Object;
    flags: (0x1009) ACC_PUBLIC, ACC_STATIC, ACC_SYNTHETIC
    Code:
      stack=4, locals=4, args_size=4
         0: aload_0
         1: aload_1
         2: aload_2
         3: aload_3
         4: invokestatic  #510                // InterfaceMethod $anonfun$checkTheSameElementsAs$7:(Lorg/scalatest/enablers/AggregatingImpls;Lorg/scalatest/enablers/AggregatingImpls$ElementCount$1;Lorg/scalactic/Equality;Lorg/scalatest/enablers/AggregatingImpls$ElementCount$1;)Z
         7: invokestatic  #500                // Method scala/runtime/BoxesRunTime.boxToBoolean:(Z)Ljava/lang/Boolean;
        10: areturn
      LineNumberTable:
        line 158: 0
      LocalVariableTable:
        Start  Length  Slot  Name   Signature
            0      11     0 $this   Lorg/scalatest/enablers/AggregatingImpls;
            0      11     1 next$3   Lorg/scalatest/enablers/AggregatingImpls$ElementCount$1;
            0      11     2 equality$1   Lorg/scalactic/Equality;
            0      11     3    ec   Lorg/scalatest/enablers/AggregatingImpls$ElementCount$1;
    MethodParameters:
      Name                           Flags
      $this                          final
      next$3                         final
      equality$1                     final
      ec                             final

  public static java.lang.Object $anonfun$checkOnly$2$adapted(org.scalatest.enablers.AggregatingImpls, java.lang.Object, org.scalactic.Equality, java.lang.Object);
    descriptor: (Lorg/scalatest/enablers/AggregatingImpls;Ljava/lang/Object;Lorg/scalactic/Equality;Ljava/lang/Object;)Ljava/lang/Object;
    flags: (0x1009) ACC_PUBLIC, ACC_STATIC, ACC_SYNTHETIC
    Code:
      stack=4, locals=4, args_size=4
         0: aload_0
         1: aload_1
         2: aload_2
         3: aload_3
         4: invokestatic  #512                // InterfaceMethod $anonfun$checkOnly$2:(Lorg/scalatest/enablers/AggregatingImpls;Ljava/lang/Object;Lorg/scalactic/Equality;Ljava/lang/Object;)Z
         7: invokestatic  #500                // Method scala/runtime/BoxesRunTime.boxToBoolean:(Z)Ljava/lang/Boolean;
        10: areturn
      LineNumberTable:
        line 173: 0
      LocalVariableTable:
        Start  Length  Slot  Name   Signature
            0      11     0 $this   Lorg/scalatest/enablers/AggregatingImpls;
            0      11     1   l$1   Ljava/lang/Object;
            0      11     2 equality$2   Lorg/scalactic/Equality;
            0      11     3     r   Ljava/lang/Object;
    MethodParameters:
      Name                           Flags
      $this                          final
      l$1                            final
      equality$2                     final
      r                              final

  public static java.lang.Object $anonfun$checkOnly$4$adapted(org.scalatest.enablers.AggregatingImpls, java.lang.Object, org.scalactic.Equality, java.lang.Object);
    descriptor: (Lorg/scalatest/enablers/AggregatingImpls;Ljava/lang/Object;Lorg/scalactic/Equality;Ljava/lang/Object;)Ljava/lang/Object;
    flags: (0x1009) ACC_PUBLIC, ACC_STATIC, ACC_SYNTHETIC
    Code:
      stack=4, locals=4, args_size=4
         0: aload_0
         1: aload_1
         2: aload_2
         3: aload_3
         4: invokestatic  #514                // InterfaceMethod $anonfun$checkOnly$4:(Lorg/scalatest/enablers/AggregatingImpls;Ljava/lang/Object;Lorg/scalactic/Equality;Ljava/lang/Object;)Z
         7: invokestatic  #500                // Method scala/runtime/BoxesRunTime.boxToBoolean:(Z)Ljava/lang/Boolean;
        10: areturn
      LineNumberTable:
        line 174: 0
      LocalVariableTable:
        Start  Length  Slot  Name   Signature
            0      11     0 $this   Lorg/scalatest/enablers/AggregatingImpls;
            0      11     1   r$1   Ljava/lang/Object;
            0      11     2 equality$2   Lorg/scalactic/Equality;
            0      11     3     l   Ljava/lang/Object;
    MethodParameters:
      Name                           Flags
      $this                          final
      r$1                            final
      equality$2                     final
      l                              final

  public static java.lang.Object $anonfun$checkAllOf$1$adapted(org.scalactic.Equality, java.lang.Object, java.lang.Object);
    descriptor: (Lorg/scalactic/Equality;Ljava/lang/Object;Ljava/lang/Object;)Ljava/lang/Object;
    flags: (0x1009) ACC_PUBLIC, ACC_STATIC, ACC_SYNTHETIC
    Code:
      stack=3, locals=3, args_size=3
         0: aload_0
         1: aload_1
         2: aload_2
         3: invokestatic  #516                // InterfaceMethod $anonfun$checkAllOf$1:(Lorg/scalactic/Equality;Ljava/lang/Object;Ljava/lang/Object;)Z
         6: invokestatic  #500                // Method scala/runtime/BoxesRunTime.boxToBoolean:(Z)Ljava/lang/Boolean;
         9: areturn
      LineNumberTable:
        line 181: 0
      LocalVariableTable:
        Start  Length  Slot  Name   Signature
            0      10     0 equality$3   Lorg/scalactic/Equality;
            0      10     1 nextRight$1   Ljava/lang/Object;
            0      10     2     t   Ljava/lang/Object;
    MethodParameters:
      Name                           Flags
      equality$3                     final
      nextRight$1                    final
      t                              final

  public static java.lang.Object $anonfun$checkAtMostOneOf$3$adapted(org.scalactic.Equality, java.lang.Object, java.lang.Object);
    descriptor: (Lorg/scalactic/Equality;Ljava/lang/Object;Ljava/lang/Object;)Ljava/lang/Object;
    flags: (0x1009) ACC_PUBLIC, ACC_STATIC, ACC_SYNTHETIC
    Code:
      stack=3, locals=3, args_size=3
         0: aload_0
         1: aload_1
         2: aload_2
         3: invokestatic  #518                // InterfaceMethod $anonfun$checkAtMostOneOf$3:(Lorg/scalactic/Equality;Ljava/lang/Object;Ljava/lang/Object;)Z
         6: invokestatic  #500                // Method scala/runtime/BoxesRunTime.boxToBoolean:(Z)Ljava/lang/Boolean;
         9: areturn
      LineNumberTable:
        line 197: 0
      LocalVariableTable:
        Start  Length  Slot  Name   Signature
            0      10     0 equality$4   Lorg/scalactic/Equality;
            0      10     1 nextRight$2   Ljava/lang/Object;
            0      10     2     l   Ljava/lang/Object;
    MethodParameters:
      Name                           Flags
      equality$4                     final
      nextRight$2                    final
      l                              final

  public static java.lang.Object $anonfun$checkAtMostOneOf$2$adapted(scala.collection.Iterable, org.scalactic.Equality, java.lang.Object, java.lang.Object, java.lang.Object);
    descriptor: (Lscala/collection/Iterable;Lorg/scalactic/Equality;Ljava/lang/Object;Ljava/lang/Object;Ljava/lang/Object;)Ljava/lang/Object;
    flags: (0x1009) ACC_PUBLIC, ACC_STATIC, ACC_SYNTHETIC
    Code:
      stack=5, locals=5, args_size=5
         0: aload_0
         1: aload_1
         2: aload_2
         3: aload_3
         4: invokestatic  #490                // Method scala/runtime/BoxesRunTime.unboxToInt:(Ljava/lang/Object;)I
         7: aload         4
         9: invokestatic  #520                // InterfaceMethod $anonfun$checkAtMostOneOf$2:(Lscala/collection/Iterable;Lorg/scalactic/Equality;Ljava/lang/Object;ILjava/lang/Object;)I
        12: invokestatic  #437                // Method scala/runtime/BoxesRunTime.boxToInteger:(I)Ljava/lang/Integer;
        15: areturn
      LineNumberTable:
        line 196: 0
      LocalVariableTable:
        Start  Length  Slot  Name   Signature
            0      16     0 left$2   Lscala/collection/Iterable;
            0      16     1 equality$4   Lorg/scalactic/Equality;
            0      16     2 nonLocalReturnKey2$1   Ljava/lang/Object;
            0      16     3  x0$1   Ljava/lang/Object;
            0      16     4  x1$1   Ljava/lang/Object;
    MethodParameters:
      Name                           Flags
      left$2                         final
      equality$4                     final
      nonLocalReturnKey2$1           final
      x0$1                           final
      x1$1                           final

  private static java.lang.Object $deserializeLambda$(java.lang.invoke.SerializedLambda);
    descriptor: (Ljava/lang/invoke/SerializedLambda;)Ljava/lang/Object;
    flags: (0x100a) ACC_PRIVATE, ACC_STATIC, ACC_SYNTHETIC
    Code:
      stack=1, locals=1, args_size=1
         0: aload_0
         1: invokedynamic #532,  0            // InvokeDynamic #17:lambdaDeserialize:(Ljava/lang/invoke/SerializedLambda;)Ljava/lang/Object;
         6: areturn
}
InnerClasses:
  public static final #13= #10 of #12;    // Lookup=class java/lang/invoke/MethodHandles$Lookup of class java/lang/invoke/MethodHandles
  public #16= #15;                        // ElementCount$1=class org/scalatest/enablers/AggregatingImpls$ElementCount$1
  public #19= #18;                        // ElementCount$2$=class org/scalatest/enablers/AggregatingImpls$ElementCount$2$
  public #22= #21;                        // ZipNoMatch$1$=class org/scalatest/enablers/AggregatingImpls$ZipNoMatch$1$
SourceFile: "Aggregating.scala"
RuntimeVisibleAnnotations:
  0: #6(#7=s#8)
    scala.reflect.ScalaSignature(
      bytes="\u0006\u0005A4qa\u0002\u0005\u0011\u0002\u0007\u0005q\u0002C\u0003\u0017\u0001\u0011\u0005q\u0003\u0003\u0004\u001c\u0001\u0011\u0005!\u0002\b\u0005\u0007q\u0001!\tAC\u001d\t\rI\u0003A\u0011\u0001\u0006T\u0011\u0019a\u0006\u0001\"\u0001\u000b;\"1a\r\u0001C\u0001\u0015\u001d\u0014\u0001#Q4he\u0016<\u0017\r^5oO&k\u0007\u000f\\:\u000b\u0005%Q\u0011\u0001C3oC\ndWM]:\u000b\u0005-a\u0011!C:dC2\fG/Z:u\u0015\u0005i\u0011aA8sO\u000e\u00011C\u0001\u0001\u0011!\t\tB#D\u0001\u0013\u0015\u0005\u0019\u0012!B:dC2\f\u0017BA\u000b\u0013\u0005\u0019\te.\u001f*fM\u00061A%\u001b8ji\u0012\"\u0012\u0001\u0007\t\u0003#eI!A\u0007\n\u0003\tUs\u0017\u000e^\u0001\fiJLX)];bY&$\u00180\u0006\u0002\u001eeQ!a$\t\u0014)!\t\tr$\u0003\u0002!%\t9!i\\8mK\u0006t\u0007\"\u0002\u0012\u0003\u0001\u0004\u0019\u0013\u0001\u00027fMR\u0004\"!\u0005\u0013\n\u0005\u0015\u0012\"aA!os\")qE\u0001a\u0001G\u0005)!/[4ii\")\u0011F\u0001a\u0001U\u0005AQ-];bY&$\u0018\u0010E\u0002,]Aj\u0011\u0001\f\u0006\u0003[1\t\u0011b]2bY\u0006\u001cG/[2\n\u0005=b#\u0001C#rk\u0006d\u0017\u000e^=\u0011\u0005E\u0012D\u0002\u0001\u0003\u0006g\t\u0011\r\u0001\u000e\u0002\u0002)F\u0011Qg\t\t\u0003#YJ!a\u000e\n\u0003\u000f9{G\u000f[5oO\u000612\r[3dWRCWmU1nK\u0016cW-\\3oiN\f5/\u0006\u0002;\u001bR!ad\u000f(Q\u0011\u0015\u00113\u00011\u0001=!\ri\u0014\n\u0014\b\u0003}\u0019s!a\u0010#\u000f\u0005\u0001\u001bU\"A!\u000b\u0005\ts\u0011A\u0002\u001fs_>$h(C\u0001\u0014\u0013\t)%#\u0001\u0006d_2dWm\u0019;j_:L!a\u0012%\u0002\u000fA\f7m[1hK*\u0011QIE\u0005\u0003\u0015.\u0013abR3o)J\fg/\u001a:tC\ndWM\u0003\u0002H\u0011B\u0011\u0011\'\u0014\u0003\u0006g\r\u0011\r\u0001\u000e\u0005\u0006O\r\u0001\ra\u0014\t\u0004{%\u001b\u0003\"B\u0015\u0004\u0001\u0004\t\u0006cA\u0016/\u0019\u0006I1\r[3dW>sG._\u000b\u0003)b#BAH+Z5\")!\u0005\u0002a\u0001-B\u0019Q(S,\u0011\u0005EBF!B\u001a\u0005\u0005\u0004!\u0004\"B\u0014\u0005\u0001\u0004y\u0005\"B\u0015\u0005\u0001\u0004Y\u0006cA\u0016//\u0006Q1\r[3dW\u0006cGn\u00144\u0016\u0005y\u0013G\u0003\u0002\u0010`G\u0012DQAI\u0003A\u0002\u0001\u00042!P%b!\t\t$\rB\u00034\u000b\t\u0007A\u0007C\u0003(\u000b\u0001\u0007q\nC\u0003*\u000b\u0001\u0007Q\rE\u0002,]\u0005\f\u0001c\u00195fG.\fE/T8ti>sWm\u00144\u0016\u0005!dG\u0003\u0002\u0010j[:DQA\t\u0004A\u0002)\u00042!P%l!\t\tD\u000eB\u00034\r\t\u0007A\u0007C\u0003(\r\u0001\u0007q\nC\u0003*\r\u0001\u0007q\u000eE\u0002,]-\u0004"
    )
BootstrapMethods:
  0: #101 REF_invokeStatic java/lang/invoke/LambdaMetafactory.altMetafactory:(Ljava/lang/invoke/MethodHandles$Lookup;Ljava/lang/String;Ljava/lang/invoke/MethodType;[Ljava/lang/Object;)Ljava/lang/invoke/CallSite;
    Method arguments:
      #86 ()Ljava/lang/Object;
      #91 REF_invokeStatic org/scalatest/enablers/AggregatingImpls.$anonfun$checkTheSameElementsAs$3:()Lscala/collection/immutable/IndexedSeq;
      #92 ()Lscala/collection/immutable/IndexedSeq;
      #93 5
      #94 1
      #92 ()Lscala/collection/immutable/IndexedSeq;
  1: #101 REF_invokeStatic java/lang/invoke/LambdaMetafactory.altMetafactory:(Ljava/lang/invoke/MethodHandles$Lookup;Ljava/lang/String;Ljava/lang/invoke/MethodType;[Ljava/lang/Object;)Ljava/lang/invoke/CallSite;
    Method arguments:
      #107 (Ljava/lang/Object;Ljava/lang/Object;)Ljava/lang/Object;
      #112 REF_invokeStatic org/scalatest/enablers/AggregatingImpls.$anonfun$checkTheSameElementsAs$4:(Lorg/scalatest/enablers/AggregatingImpls;Ljava/lang/Object;Lscala/runtime/LazyRef;Lorg/scalactic/Equality;Lscala/runtime/LazyRef;Lscala/collection/immutable/IndexedSeq;Lscala/Tuple2;)Lscala/collection/immutable/IndexedSeq;
      #114 (Lscala/collection/immutable/IndexedSeq;Lscala/Tuple2;)Lscala/collection/immutable/IndexedSeq;
      #93 5
      #94 1
      #114 (Lscala/collection/immutable/IndexedSeq;Lscala/Tuple2;)Lscala/collection/immutable/IndexedSeq;
  2: #101 REF_invokeStatic java/lang/invoke/LambdaMetafactory.altMetafactory:(Ljava/lang/invoke/MethodHandles$Lookup;Ljava/lang/String;Ljava/lang/invoke/MethodType;[Ljava/lang/Object;)Ljava/lang/invoke/CallSite;
    Method arguments:
      #107 (Ljava/lang/Object;Ljava/lang/Object;)Ljava/lang/Object;
      #122 REF_invokeStatic org/scalatest/enablers/AggregatingImpls.$anonfun$checkTheSameElementsAs$5:(Lorg/scalatest/enablers/AggregatingImpls;Lorg/scalactic/Equality;Lscala/runtime/LazyRef;Lscala/collection/immutable/IndexedSeq;Lscala/collection/immutable/IndexedSeq;)Lscala/collection/immutable/IndexedSeq;
      #124 (Lscala/collection/immutable/IndexedSeq;Lscala/collection/immutable/IndexedSeq;)Lscala/collection/immutable/IndexedSeq;
      #93 5
      #94 1
      #124 (Lscala/collection/immutable/IndexedSeq;Lscala/collection/immutable/IndexedSeq;)Lscala/collection/immutable/IndexedSeq;
  3: #101 REF_invokeStatic java/lang/invoke/LambdaMetafactory.altMetafactory:(Ljava/lang/invoke/MethodHandles$Lookup;Ljava/lang/String;Ljava/lang/invoke/MethodType;[Ljava/lang/Object;)Ljava/lang/invoke/CallSite;
    Method arguments:
      #135 (Ljava/lang/Object;)Ljava/lang/Object;
      #140 REF_invokeStatic org/scalatest/enablers/AggregatingImpls.$anonfun$checkTheSameElementsAs$8$adapted:(Lorg/scalatest/enablers/AggregatingImpls$ElementCount$1;)Ljava/lang/Object;
      #141 (Lorg/scalatest/enablers/AggregatingImpls$ElementCount$1;)Ljava/lang/Object;
      #93 5
      #94 1
      #141 (Lorg/scalatest/enablers/AggregatingImpls$ElementCount$1;)Ljava/lang/Object;
  4: #101 REF_invokeStatic java/lang/invoke/LambdaMetafactory.altMetafactory:(Ljava/lang/invoke/MethodHandles$Lookup;Ljava/lang/String;Ljava/lang/invoke/MethodType;[Ljava/lang/Object;)Ljava/lang/invoke/CallSite;
    Method arguments:
      #135 (Ljava/lang/Object;)Ljava/lang/Object;
      #171 REF_invokeStatic org/scalatest/enablers/AggregatingImpls.$anonfun$checkOnly$1$adapted:(Lorg/scalatest/enablers/AggregatingImpls;Lscala/collection/Iterable;Lorg/scalactic/Equality;Ljava/lang/Object;)Ljava/lang/Object;
      #135 (Ljava/lang/Object;)Ljava/lang/Object;
      #94 1
  5: #101 REF_invokeStatic java/lang/invoke/LambdaMetafactory.altMetafactory:(Ljava/lang/invoke/MethodHandles$Lookup;Ljava/lang/String;Ljava/lang/invoke/MethodType;[Ljava/lang/Object;)Ljava/lang/invoke/CallSite;
    Method arguments:
      #135 (Ljava/lang/Object;)Ljava/lang/Object;
      #181 REF_invokeStatic org/scalatest/enablers/AggregatingImpls.$anonfun$checkOnly$3$adapted:(Lorg/scalatest/enablers/AggregatingImpls;Lscala/collection/Iterable;Lorg/scalactic/Equality;Ljava/lang/Object;)Ljava/lang/Object;
      #135 (Ljava/lang/Object;)Ljava/lang/Object;
      #94 1
  6: #101 REF_invokeStatic java/lang/invoke/LambdaMetafactory.altMetafactory:(Ljava/lang/invoke/MethodHandles$Lookup;Ljava/lang/String;Ljava/lang/invoke/MethodType;[Ljava/lang/Object;)Ljava/lang/invoke/CallSite;
    Method arguments:
      #135 (Ljava/lang/Object;)Ljava/lang/Object;
      #246 REF_invokeStatic org/scalatest/enablers/AggregatingImpls.$anonfun$checkTheSameElementsAs$1$adapted:(Lorg/scalatest/enablers/AggregatingImpls;Ljava/lang/Object;Lorg/scalactic/Equality;Lorg/scalatest/enablers/AggregatingImpls$ElementCount$1;)Ljava/lang/Object;
      #141 (Lorg/scalatest/enablers/AggregatingImpls$ElementCount$1;)Ljava/lang/Object;
      #93 5
      #94 1
      #141 (Lorg/scalatest/enablers/AggregatingImpls$ElementCount$1;)Ljava/lang/Object;
  7: #101 REF_invokeStatic java/lang/invoke/LambdaMetafactory.altMetafactory:(Ljava/lang/invoke/MethodHandles$Lookup;Ljava/lang/String;Ljava/lang/invoke/MethodType;[Ljava/lang/Object;)Ljava/lang/invoke/CallSite;
    Method arguments:
      #135 (Ljava/lang/Object;)Ljava/lang/Object;
      #284 REF_invokeStatic org/scalatest/enablers/AggregatingImpls.$anonfun$checkTheSameElementsAs$2$adapted:(Lorg/scalatest/enablers/AggregatingImpls;Ljava/lang/Object;Lorg/scalactic/Equality;Lorg/scalatest/enablers/AggregatingImpls$ElementCount$1;)Ljava/lang/Object;
      #141 (Lorg/scalatest/enablers/AggregatingImpls$ElementCount$1;)Ljava/lang/Object;
      #93 5
      #94 1
      #141 (Lorg/scalatest/enablers/AggregatingImpls$ElementCount$1;)Ljava/lang/Object;
  8: #101 REF_invokeStatic java/lang/invoke/LambdaMetafactory.altMetafactory:(Ljava/lang/invoke/MethodHandles$Lookup;Ljava/lang/String;Ljava/lang/invoke/MethodType;[Ljava/lang/Object;)Ljava/lang/invoke/CallSite;
    Method arguments:
      #135 (Ljava/lang/Object;)Ljava/lang/Object;
      #347 REF_invokeStatic org/scalatest/enablers/AggregatingImpls.$anonfun$checkTheSameElementsAs$7$adapted:(Lorg/scalatest/enablers/AggregatingImpls;Lorg/scalatest/enablers/AggregatingImpls$ElementCount$1;Lorg/scalactic/Equality;Lorg/scalatest/enablers/AggregatingImpls$ElementCount$1;)Ljava/lang/Object;
      #141 (Lorg/scalatest/enablers/AggregatingImpls$ElementCount$1;)Ljava/lang/Object;
      #93 5
      #94 1
      #141 (Lorg/scalatest/enablers/AggregatingImpls$ElementCount$1;)Ljava/lang/Object;
  9: #101 REF_invokeStatic java/lang/invoke/LambdaMetafactory.altMetafactory:(Ljava/lang/invoke/MethodHandles$Lookup;Ljava/lang/String;Ljava/lang/invoke/MethodType;[Ljava/lang/Object;)Ljava/lang/invoke/CallSite;
    Method arguments:
      #107 (Ljava/lang/Object;Ljava/lang/Object;)Ljava/lang/Object;
      #355 REF_invokeStatic org/scalatest/enablers/AggregatingImpls.$anonfun$checkTheSameElementsAs$6:(Lorg/scalatest/enablers/AggregatingImpls;Lorg/scalactic/Equality;Lscala/runtime/LazyRef;Lscala/collection/immutable/IndexedSeq;Lorg/scalatest/enablers/AggregatingImpls$ElementCount$1;)Lscala/collection/immutable/IndexedSeq;
      #357 (Lscala/collection/immutable/IndexedSeq;Lorg/scalatest/enablers/AggregatingImpls$ElementCount$1;)Lscala/collection/immutable/IndexedSeq;
      #93 5
      #94 1
      #357 (Lscala/collection/immutable/IndexedSeq;Lorg/scalatest/enablers/AggregatingImpls$ElementCount$1;)Lscala/collection/immutable/IndexedSeq;
  10: #101 REF_invokeStatic java/lang/invoke/LambdaMetafactory.altMetafactory:(Ljava/lang/invoke/MethodHandles$Lookup;Ljava/lang/String;Ljava/lang/invoke/MethodType;[Ljava/lang/Object;)Ljava/lang/invoke/CallSite;
    Method arguments:
      #135 (Ljava/lang/Object;)Ljava/lang/Object;
      #381 REF_invokeStatic org/scalatest/enablers/AggregatingImpls.$anonfun$checkOnly$2$adapted:(Lorg/scalatest/enablers/AggregatingImpls;Ljava/lang/Object;Lorg/scalactic/Equality;Ljava/lang/Object;)Ljava/lang/Object;
      #135 (Ljava/lang/Object;)Ljava/lang/Object;
      #94 1
  11: #101 REF_invokeStatic java/lang/invoke/LambdaMetafactory.altMetafactory:(Ljava/lang/invoke/MethodHandles$Lookup;Ljava/lang/String;Ljava/lang/invoke/MethodType;[Ljava/lang/Object;)Ljava/lang/invoke/CallSite;
    Method arguments:
      #135 (Ljava/lang/Object;)Ljava/lang/Object;
      #399 REF_invokeStatic org/scalatest/enablers/AggregatingImpls.$anonfun$checkOnly$4$adapted:(Lorg/scalatest/enablers/AggregatingImpls;Ljava/lang/Object;Lorg/scalactic/Equality;Ljava/lang/Object;)Ljava/lang/Object;
      #135 (Ljava/lang/Object;)Ljava/lang/Object;
      #94 1
  12: #101 REF_invokeStatic java/lang/invoke/LambdaMetafactory.altMetafactory:(Ljava/lang/invoke/MethodHandles$Lookup;Ljava/lang/String;Ljava/lang/invoke/MethodType;[Ljava/lang/Object;)Ljava/lang/invoke/CallSite;
    Method arguments:
      #135 (Ljava/lang/Object;)Ljava/lang/Object;
      #418 REF_invokeStatic org/scalatest/enablers/AggregatingImpls.$anonfun$checkAllOf$1$adapted:(Lorg/scalactic/Equality;Ljava/lang/Object;Ljava/lang/Object;)Ljava/lang/Object;
      #135 (Ljava/lang/Object;)Ljava/lang/Object;
      #94 1
  13: #101 REF_invokeStatic java/lang/invoke/LambdaMetafactory.altMetafactory:(Ljava/lang/invoke/MethodHandles$Lookup;Ljava/lang/String;Ljava/lang/invoke/MethodType;[Ljava/lang/Object;)Ljava/lang/invoke/CallSite;
    Method arguments:
      #135 (Ljava/lang/Object;)Ljava/lang/Object;
      #444 REF_invokeStatic org/scalatest/enablers/AggregatingImpls.$anonfun$checkAtMostOneOf$3$adapted:(Lorg/scalactic/Equality;Ljava/lang/Object;Ljava/lang/Object;)Ljava/lang/Object;
      #135 (Ljava/lang/Object;)Ljava/lang/Object;
      #94 1
  14: #101 REF_invokeStatic java/lang/invoke/LambdaMetafactory.altMetafactory:(Ljava/lang/invoke/MethodHandles$Lookup;Ljava/lang/String;Ljava/lang/invoke/MethodType;[Ljava/lang/Object;)Ljava/lang/invoke/CallSite;
    Method arguments:
      #463 ()I
      #466 REF_invokeStatic org/scalatest/enablers/AggregatingImpls.$anonfun$checkAtMostOneOf$1:()I
      #463 ()I
      #94 1
  15: #101 REF_invokeStatic java/lang/invoke/LambdaMetafactory.altMetafactory:(Ljava/lang/invoke/MethodHandles$Lookup;Ljava/lang/String;Ljava/lang/invoke/MethodType;[Ljava/lang/Object;)Ljava/lang/invoke/CallSite;
    Method arguments:
      #107 (Ljava/lang/Object;Ljava/lang/Object;)Ljava/lang/Object;
      #475 REF_invokeStatic org/scalatest/enablers/AggregatingImpls.$anonfun$checkAtMostOneOf$2$adapted:(Lscala/collection/Iterable;Lorg/scalactic/Equality;Ljava/lang/Object;Ljava/lang/Object;Ljava/lang/Object;)Ljava/lang/Object;
      #107 (Ljava/lang/Object;Ljava/lang/Object;)Ljava/lang/Object;
      #94 1
  16: #101 REF_invokeStatic java/lang/invoke/LambdaMetafactory.altMetafactory:(Ljava/lang/invoke/MethodHandles$Lookup;Ljava/lang/String;Ljava/lang/invoke/MethodType;[Ljava/lang/Object;)Ljava/lang/invoke/CallSite;
    Method arguments:
      #479 (II)I
      #482 REF_invokeStatic org/scalatest/enablers/AggregatingImpls.$anonfun$checkAtMostOneOf$4:(II)I
      #479 (II)I
      #94 1
  17: #529 REF_invokeStatic scala/runtime/LambdaDeserialize.bootstrap:(Ljava/lang/invoke/MethodHandles$Lookup;Ljava/lang/String;Ljava/lang/invoke/MethodType;[Ljava/lang/invoke/MethodHandle;)Ljava/lang/invoke/CallSite;
    Method arguments:
      #418 REF_invokeStatic org/scalatest/enablers/AggregatingImpls.$anonfun$checkAllOf$1$adapted:(Lorg/scalactic/Equality;Ljava/lang/Object;Ljava/lang/Object;)Ljava/lang/Object;
      #466 REF_invokeStatic org/scalatest/enablers/AggregatingImpls.$anonfun$checkAtMostOneOf$1:()I
      #475 REF_invokeStatic org/scalatest/enablers/AggregatingImpls.$anonfun$checkAtMostOneOf$2$adapted:(Lscala/collection/Iterable;Lorg/scalactic/Equality;Ljava/lang/Object;Ljava/lang/Object;Ljava/lang/Object;)Ljava/lang/Object;
      #444 REF_invokeStatic org/scalatest/enablers/AggregatingImpls.$anonfun$checkAtMostOneOf$3$adapted:(Lorg/scalactic/Equality;Ljava/lang/Object;Ljava/lang/Object;)Ljava/lang/Object;
      #482 REF_invokeStatic org/scalatest/enablers/AggregatingImpls.$anonfun$checkAtMostOneOf$4:(II)I
      #171 REF_invokeStatic org/scalatest/enablers/AggregatingImpls.$anonfun$checkOnly$1$adapted:(Lorg/scalatest/enablers/AggregatingImpls;Lscala/collection/Iterable;Lorg/scalactic/Equality;Ljava/lang/Object;)Ljava/lang/Object;
      #381 REF_invokeStatic org/scalatest/enablers/AggregatingImpls.$anonfun$checkOnly$2$adapted:(Lorg/scalatest/enablers/AggregatingImpls;Ljava/lang/Object;Lorg/scalactic/Equality;Ljava/lang/Object;)Ljava/lang/Object;
      #181 REF_invokeStatic org/scalatest/enablers/AggregatingImpls.$anonfun$checkOnly$3$adapted:(Lorg/scalatest/enablers/AggregatingImpls;Lscala/collection/Iterable;Lorg/scalactic/Equality;Ljava/lang/Object;)Ljava/lang/Object;
      #399 REF_invokeStatic org/scalatest/enablers/AggregatingImpls.$anonfun$checkOnly$4$adapted:(Lorg/scalatest/enablers/AggregatingImpls;Ljava/lang/Object;Lorg/scalactic/Equality;Ljava/lang/Object;)Ljava/lang/Object;
      #246 REF_invokeStatic org/scalatest/enablers/AggregatingImpls.$anonfun$checkTheSameElementsAs$1$adapted:(Lorg/scalatest/enablers/AggregatingImpls;Ljava/lang/Object;Lorg/scalactic/Equality;Lorg/scalatest/enablers/AggregatingImpls$ElementCount$1;)Ljava/lang/Object;
      #284 REF_invokeStatic org/scalatest/enablers/AggregatingImpls.$anonfun$checkTheSameElementsAs$2$adapted:(Lorg/scalatest/enablers/AggregatingImpls;Ljava/lang/Object;Lorg/scalactic/Equality;Lorg/scalatest/enablers/AggregatingImpls$ElementCount$1;)Ljava/lang/Object;
      #91 REF_invokeStatic org/scalatest/enablers/AggregatingImpls.$anonfun$checkTheSameElementsAs$3:()Lscala/collection/immutable/IndexedSeq;
      #112 REF_invokeStatic org/scalatest/enablers/AggregatingImpls.$anonfun$checkTheSameElementsAs$4:(Lorg/scalatest/enablers/AggregatingImpls;Ljava/lang/Object;Lscala/runtime/LazyRef;Lorg/scalactic/Equality;Lscala/runtime/LazyRef;Lscala/collection/immutable/IndexedSeq;Lscala/Tuple2;)Lscala/collection/immutable/IndexedSeq;
      #122 REF_invokeStatic org/scalatest/enablers/AggregatingImpls.$anonfun$checkTheSameElementsAs$5:(Lorg/scalatest/enablers/AggregatingImpls;Lorg/scalactic/Equality;Lscala/runtime/LazyRef;Lscala/collection/immutable/IndexedSeq;Lscala/collection/immutable/IndexedSeq;)Lscala/collection/immutable/IndexedSeq;
      #355 REF_invokeStatic org/scalatest/enablers/AggregatingImpls.$anonfun$checkTheSameElementsAs$6:(Lorg/scalatest/enablers/AggregatingImpls;Lorg/scalactic/Equality;Lscala/runtime/LazyRef;Lscala/collection/immutable/IndexedSeq;Lorg/scalatest/enablers/AggregatingImpls$ElementCount$1;)Lscala/collection/immutable/IndexedSeq;
      #347 REF_invokeStatic org/scalatest/enablers/AggregatingImpls.$anonfun$checkTheSameElementsAs$7$adapted:(Lorg/scalatest/enablers/AggregatingImpls;Lorg/scalatest/enablers/AggregatingImpls$ElementCount$1;Lorg/scalactic/Equality;Lorg/scalatest/enablers/AggregatingImpls$ElementCount$1;)Ljava/lang/Object;
      #140 REF_invokeStatic org/scalatest/enablers/AggregatingImpls.$anonfun$checkTheSameElementsAs$8$adapted:(Lorg/scalatest/enablers/AggregatingImpls$ElementCount$1;)Ljava/lang/Object;
  ScalaInlineInfo: length = 0xEF (unknown attribute)
   01 00 00 2F 01 91 01 92 01 01 9E 01 9F 01 01 A8
   01 04 01 01 AC 01 AD 01 01 D7 01 D8 01 01 A9 01
   92 01 01 B9 01 9F 01 01 C4 01 C5 01 01 75 01 76
   01 00 A7 00 A8 01 01 70 01 71 01 01 79 01 7A 01
   01 8A 01 76 01 00 B2 00 A8 01 01 88 01 71 01 01
   8C 01 7A 01 00 E6 00 E7 01 00 F2 00 F3 01 01 16
   00 E7 01 01 19 00 F3 01 00 57 00 58 01 00 6C 00
   6D 01 00 76 00 77 01 01 53 01 54 01 01 50 01 51
   01 01 57 01 58 01 01 6D 01 6E 01 00 88 00 89 01
   01 EE 00 D6 01 00 DE 00 CE 01 00 CD 00 CE 01 00
   4D 00 4E 01 00 E1 00 4E 01 00 B8 00 33 00 00 B7
   00 31 01 00 C4 00 33 00 00 C3 00 31 01 00 BF 00
   C0 01 00 A4 00 33 00 00 A3 00 31 01 00 32 00 33
   00 00 30 00 31 01 00 C7 00 C8 01 00 EF 00 F0 01
   01 18 00 F0 01 00 1D 00 1E 00 00 17 00 18 01
  ScalaSig: length = 0x3 (unknown attribute)
   05 02 00
