Classfile /Users/mw/Projects/slang-braindump/.jar/jar8/assemble/slang-braindump/assemble/content/org/scalatest/enablers/Collecting.class
  Last modified May 29, 2022; size 3460 bytes
  SHA-256 checksum c384dc468815115b7cb4a799c53c3db01abbdf3f83dc670cf84bd8afcd39d864
  Compiled from "Collecting.scala"
public interface org.scalatest.enablers.Collecting<E extends java.lang.Object, C extends java.lang.Object>
  minor version: 0
  major version: 52
  flags: (0x0601) ACC_PUBLIC, ACC_INTERFACE, ACC_ABSTRACT
  this_class: #2                          // org/scalatest/enablers/Collecting
  super_class: #5                         // java/lang/Object
  interfaces: 0, fields: 0, methods: 9, attributes: 5
Constant pool:
   #1 = Utf8               org/scalatest/enablers/Collecting
   #2 = Class              #1             // org/scalatest/enablers/Collecting
   #3 = Utf8               <E:Ljava/lang/Object;C:Ljava/lang/Object;>Ljava/lang/Object;
   #4 = Utf8               java/lang/Object
   #5 = Class              #4             // java/lang/Object
   #6 = Utf8               Collecting.scala
   #7 = Utf8               Lscala/reflect/ScalaSignature;
   #8 = Utf8               bytes
   #9 = Utf8               \u0006\u0005\u0005UdaB\u0007\u000f!\u0003\r\n!\u0006\u0005\u0006;\u00011\tA\b\u0005\u0006e\u00011\ta\r\u0005\u0006q\u00011\t!O\u0004\u0006\u0015:A\ta\u0013\u0004\u0006\u001b9A\t!\u0014\u0005\u0006\u001d\u0016!\ta\u0014\u0005\u0006!\u0016!\u0019!\u0015\u0005\u0006?\u0016!\u0019\u0001\u0019\u0005\u0006Q\u0016!\u0019!\u001b\u0005\u0006m\u0016!\u0019a\u001e\u0005\b\u0003/)A1AA\r\u0011\u001d\ty%\u0002C\u0002\u0003#\u0012!bQ8mY\u0016\u001cG/\u001b8h\u0015\ty\u0001#\u0001\u0005f]\u0006\u0014G.\u001a:t\u0015\t\t\"#A\u0005tG\u0006d\u0017\r^3ti*\t1#A\u0002pe\u001e\u001c\u0001!F\u0002\u0017IA\u001a\"\u0001A\f\u0011\u0005aYR\"A\r\u000b\u0003i\tQa]2bY\u0006L!\u0001H\r\u0003\r\u0005s\u0017PU3g\u00035awN\\3FY\u0016lWM\u001c;PMR\u0011q$\f\t\u00041\u0001\u0012\u0013BA\u0011\u001a\u0005\u0019y\u0005\u000f^5p]B\u00111\u0005\n\u0007\u0001\t\u0015)\u0003A1\u0001\'\u0005\u0005)\u0015CA\u0014+!\tA\u0002&\u0003\u0002*3\t9aj\u001c;iS:<\u0007C\u0001\r,\u0013\ta\u0013DA\u0002B]fDQAL\u0001A\u0002=\n!bY8mY\u0016\u001cG/[8o!\t\u0019\u0003\u0007B\u00032\u0001\t\u0007aEA\u0001D\u0003\u0019\u0019\u0018N_3PMR\u0011Ag\u000e\t\u00031UJ!AN\r\u0003\u0007%sG\u000fC\u0003/\u0005\u0001\u0007q&\u0001\nhK:$&/\u0019<feN\f\'\r\\3Ge>lGC\u0001\u001eJ!\rYdI\t\b\u0003y\rs!!\u0010\"\u000f\u0005y\nU\"A \u000b\u0005\u0001#\u0012A\u0002\u001fs_>$h(C\u0001\u001b\u0013\tq\u0013$\u0003\u0002E\u000b\u00069\u0001/Y2lC\u001e,\'B\u0001\u0018\u001a\u0013\t9\u0005J\u0001\bHK:$&/\u0019<feN\f\'\r\\3\u000b\u0005\u0011+\u0005\"\u0002\u0018\u0004\u0001\u0004y\u0013AC\"pY2,7\r^5oOB\u0011A*B\u0007\u0002\u001dM\u0011QaF\u0001\u0007y%t\u0017\u000e\u001e \u0015\u0003-\u000b\u0001eY8mY\u0016\u001cG/\u001b8h\u001d\u0006$XO]3PM\u001e+g\u000e\u0016:bm\u0016\u00148/\u00192mKV\u0019!+V,\u0016\u0003M\u0003B\u0001\u0014\u0001U-B\u00111%\u0016\u0003\u0006K\u001d\u0011\rA\n\t\u0004G]#F!\u0002-\b\u0005\u0004I&\u0001\u0002+S\u0003Z+\"AW/\u0012\u0005\u001dZ\u0006cA\u001eG9B\u00111%\u0018\u0003\u0006=^\u0013\rA\n\u0002\u0002K\u000692m\u001c7mK\u000e$\u0018N\\4OCR,(/Z(g\u0003J\u0014\u0018-_\u000b\u0003C\u0012,\u0012A\u0019\t\u0005\u0019\u0002\u0019W\r\u0005\u0002$I\u0012)Q\u0005\u0003b\u0001MA\u0019\u0001DZ2\n\u0005\u001dL\"!B!se\u0006L\u0018\u0001G2pY2,7\r^5oO:\u000bG/\u001e:f\u001f\u001a\u001cFO]5oOV\t!\u000e\u0005\u0003M\u0001-t\u0007C\u0001\rm\u0013\ti\u0017D\u0001\u0003DQ\u0006\u0014\bCA8t\u001d\t\u0001\u0018\u000f\u0005\u0002?3%\u0011!/G\u0001\u0007!J,G-\u001a4\n\u0005Q,(AB*ue&twM\u0003\u0002s3\u0005\u00013m\u001c7mK\u000e$\u0018N\\4OCR,(/Z(g\u0015\u00064\u0018mQ8mY\u0016\u001cG/[8o+\rA80`\u000b\u0002sB!A\n\u0001>}!\t\u00193\u0010B\u0003&\u0015\t\u0007a\u0005E\u0002${j$QA \u0006C\u0002}\u0014AAS\"P\u0019V!\u0011\u0011AA\u000b#\r9\u00131\u0001\t\u0007\u0003\u000b\ty!a\u0005\u000e\u0005\u0005\u001d!\u0002BA\u0005\u0003\u0017\tA!\u001e;jY*\u0011\u0011QB\u0001\u0005U\u00064\u0018-\u0003\u0003\u0002\u0012\u0005\u001d!AC\"pY2,7\r^5p]B\u00191%!\u0006\u0005\u000byk(\u0019\u0001\u0014\u00023\r|G\u000e\\3di&twMT1ukJ,wJ\u001a&bm\u0006l\u0015\r]\u000b\t\u00037\tI#a\f\u00026U\u0011\u0011Q\u0004\t\u0007\u0019\u0002\ty\"a\r\u0011\u0011\u0005\u0005\u00121EA\u0014\u0003[i\u0011\u0001E\u0005\u0004\u0003K\u0001\"!B#oiJL\bcA\u0012\u0002*\u00111\u00111F\u0006C\u0002\u0019\u0012\u0011a\u0013\t\u0004G\u0005=BABA\u0019\u0017\t\u0007aEA\u0001W!\u001d\u0019\u0013QGA\u0014\u0003[!q!a\u000e\f\u0005\u0004\tID\u0001\u0003K\u001b\u0006\u0003VCBA\u001e\u0003\u000b\nY%E\u0002(\u0003{\u0001\u0002\"!\u0002\u0002@\u0005\r\u0013\u0011J\u0005\u0005\u0003\u0003\n9AA\u0002NCB\u00042aIA#\t\u001d\t9%!\u000eC\u0002\u0019\u0012\u0011a\u001b\t\u0004G\u0005-CaBA\'\u0003k\u0011\rA\n\u0002\u0002m\u000692m\u001c7mK\u000e$\u0018N\\4OCR,(/Z(g\u000bZ,\'/_\u000b\u0007\u0003\'\nI&!\u0018\u0016\u0005\u0005U\u0003C\u0002\'\u0001\u0003/\nY\u0006E\u0002$\u00033\"Q!\n\u0007C\u0002\u0019\u0002RaIA/\u0003/\"q!a\u0018\r\u0005\u0004\t\tGA\u0003F-\u0016\u0013\u0016,\u0006\u0003\u0002d\u0005M\u0014cA\u0014\u0002fA1\u0011qMA7\u0003cj!!!\u001b\u000b\u0007\u0005-$#A\u0005tG\u0006d\u0017m\u0019;jG&!\u0011qNA5\u0005\u0015)e/\u001a:z!\r\u0019\u00131\u000f\u0003\u0007=\u0006u#\u0019\u0001\u0014
  #10 = Utf8               collectingNatureOfEvery
  #11 = Utf8               ()Lorg/scalatest/enablers/Collecting;
  #12 = Utf8               <E:Ljava/lang/Object;EVERY:Lorg/scalactic/Every<Ljava/lang/Object;>;>()Lorg/scalatest/enablers/Collecting<TE;TEVERY;>;
  #13 = Utf8               org/scalatest/enablers/Collecting$
  #14 = Class              #13            // org/scalatest/enablers/Collecting$
  #15 = Utf8               MODULE$
  #16 = Utf8               Lorg/scalatest/enablers/Collecting$;
  #17 = NameAndType        #15:#16        // MODULE$:Lorg/scalatest/enablers/Collecting$;
  #18 = Fieldref           #14.#17        // org/scalatest/enablers/Collecting$.MODULE$:Lorg/scalatest/enablers/Collecting$;
  #19 = NameAndType        #10:#11        // collectingNatureOfEvery:()Lorg/scalatest/enablers/Collecting;
  #20 = Methodref          #14.#19        // org/scalatest/enablers/Collecting$.collectingNatureOfEvery:()Lorg/scalatest/enablers/Collecting;
  #21 = Utf8               collectingNatureOfJavaMap
  #22 = Utf8               <K:Ljava/lang/Object;V:Ljava/lang/Object;JMAP::Ljava/util/Map<Ljava/lang/Object;Ljava/lang/Object;>;>()Lorg/scalatest/enablers/Collecting<Lorg/scalatest/Entry<TK;TV;>;TJMAP;>;
  #23 = NameAndType        #21:#11        // collectingNatureOfJavaMap:()Lorg/scalatest/enablers/Collecting;
  #24 = Methodref          #14.#23        // org/scalatest/enablers/Collecting$.collectingNatureOfJavaMap:()Lorg/scalatest/enablers/Collecting;
  #25 = Utf8               collectingNatureOfJavaCollection
  #26 = Utf8               <E:Ljava/lang/Object;JCOL::Ljava/util/Collection<Ljava/lang/Object;>;>()Lorg/scalatest/enablers/Collecting<TE;TJCOL;>;
  #27 = NameAndType        #25:#11        // collectingNatureOfJavaCollection:()Lorg/scalatest/enablers/Collecting;
  #28 = Methodref          #14.#27        // org/scalatest/enablers/Collecting$.collectingNatureOfJavaCollection:()Lorg/scalatest/enablers/Collecting;
  #29 = Utf8               collectingNatureOfString
  #30 = Utf8               ()Lorg/scalatest/enablers/Collecting<Ljava/lang/Object;Ljava/lang/String;>;
  #31 = NameAndType        #29:#11        // collectingNatureOfString:()Lorg/scalatest/enablers/Collecting;
  #32 = Methodref          #14.#31        // org/scalatest/enablers/Collecting$.collectingNatureOfString:()Lorg/scalatest/enablers/Collecting;
  #33 = Utf8               collectingNatureOfArray
  #34 = Utf8               <E:Ljava/lang/Object;>()Lorg/scalatest/enablers/Collecting<TE;Ljava/lang/Object;>;
  #35 = NameAndType        #33:#11        // collectingNatureOfArray:()Lorg/scalatest/enablers/Collecting;
  #36 = Methodref          #14.#35        // org/scalatest/enablers/Collecting$.collectingNatureOfArray:()Lorg/scalatest/enablers/Collecting;
  #37 = Utf8               collectingNatureOfGenTraversable
  #38 = Utf8               <E:Ljava/lang/Object;TRAV::Lscala/collection/Iterable<Ljava/lang/Object;>;>()Lorg/scalatest/enablers/Collecting<TE;TTRAV;>;
  #39 = NameAndType        #37:#11        // collectingNatureOfGenTraversable:()Lorg/scalatest/enablers/Collecting;
  #40 = Methodref          #14.#39        // org/scalatest/enablers/Collecting$.collectingNatureOfGenTraversable:()Lorg/scalatest/enablers/Collecting;
  #41 = Utf8               loneElementOf
  #42 = Utf8               (Ljava/lang/Object;)Lscala/Option;
  #43 = Utf8               (TC;)Lscala/Option<TE;>;
  #44 = Utf8               collection
  #45 = Utf8               sizeOf
  #46 = Utf8               (Ljava/lang/Object;)I
  #47 = Utf8               (TC;)I
  #48 = Utf8               genTraversableFrom
  #49 = Utf8               (Ljava/lang/Object;)Lscala/collection/Iterable;
  #50 = Utf8               (TC;)Lscala/collection/Iterable<TE;>;
  #51 = Utf8               Code
  #52 = Utf8               Signature
  #53 = Utf8               MethodParameters
  #54 = Utf8               SourceFile
  #55 = Utf8               RuntimeVisibleAnnotations
  #56 = Utf8               ScalaInlineInfo
  #57 = Utf8               ScalaSig
{
  public static <E extends java.lang.Object, EVERY extends org.scalactic.Every<java.lang.Object>> org.scalatest.enablers.Collecting<E, EVERY> collectingNatureOfEvery();
    descriptor: ()Lorg/scalatest/enablers/Collecting;
    flags: (0x0009) ACC_PUBLIC, ACC_STATIC
    Code:
      stack=1, locals=0, args_size=0
         0: getstatic     #18                 // Field org/scalatest/enablers/Collecting$.MODULE$:Lorg/scalatest/enablers/Collecting$;
         3: invokevirtual #20                 // Method org/scalatest/enablers/Collecting$.collectingNatureOfEvery:()Lorg/scalatest/enablers/Collecting;
         6: areturn
    Signature: #12                          // <E:Ljava/lang/Object;EVERY:Lorg/scalactic/Every<Ljava/lang/Object;>;>()Lorg/scalatest/enablers/Collecting<TE;TEVERY;>;

  public static <K extends java.lang.Object, V extends java.lang.Object, JMAP extends java.util.Map<java.lang.Object, java.lang.Object>> org.scalatest.enablers.Collecting<org.scalatest.Entry<K, V>, JMAP> collectingNatureOfJavaMap();
    descriptor: ()Lorg/scalatest/enablers/Collecting;
    flags: (0x0009) ACC_PUBLIC, ACC_STATIC
    Code:
      stack=1, locals=0, args_size=0
         0: getstatic     #18                 // Field org/scalatest/enablers/Collecting$.MODULE$:Lorg/scalatest/enablers/Collecting$;
         3: invokevirtual #24                 // Method org/scalatest/enablers/Collecting$.collectingNatureOfJavaMap:()Lorg/scalatest/enablers/Collecting;
         6: areturn
    Signature: #22                          // <K:Ljava/lang/Object;V:Ljava/lang/Object;JMAP::Ljava/util/Map<Ljava/lang/Object;Ljava/lang/Object;>;>()Lorg/scalatest/enablers/Collecting<Lorg/scalatest/Entry<TK;TV;>;TJMAP;>;

  public static <E extends java.lang.Object, JCOL extends java.util.Collection<java.lang.Object>> org.scalatest.enablers.Collecting<E, JCOL> collectingNatureOfJavaCollection();
    descriptor: ()Lorg/scalatest/enablers/Collecting;
    flags: (0x0009) ACC_PUBLIC, ACC_STATIC
    Code:
      stack=1, locals=0, args_size=0
         0: getstatic     #18                 // Field org/scalatest/enablers/Collecting$.MODULE$:Lorg/scalatest/enablers/Collecting$;
         3: invokevirtual #28                 // Method org/scalatest/enablers/Collecting$.collectingNatureOfJavaCollection:()Lorg/scalatest/enablers/Collecting;
         6: areturn
    Signature: #26                          // <E:Ljava/lang/Object;JCOL::Ljava/util/Collection<Ljava/lang/Object;>;>()Lorg/scalatest/enablers/Collecting<TE;TJCOL;>;

  public static org.scalatest.enablers.Collecting<java.lang.Object, java.lang.String> collectingNatureOfString();
    descriptor: ()Lorg/scalatest/enablers/Collecting;
    flags: (0x0009) ACC_PUBLIC, ACC_STATIC
    Code:
      stack=1, locals=0, args_size=0
         0: getstatic     #18                 // Field org/scalatest/enablers/Collecting$.MODULE$:Lorg/scalatest/enablers/Collecting$;
         3: invokevirtual #32                 // Method org/scalatest/enablers/Collecting$.collectingNatureOfString:()Lorg/scalatest/enablers/Collecting;
         6: areturn
    Signature: #30                          // ()Lorg/scalatest/enablers/Collecting<Ljava/lang/Object;Ljava/lang/String;>;

  public static <E extends java.lang.Object> org.scalatest.enablers.Collecting<E, java.lang.Object> collectingNatureOfArray();
    descriptor: ()Lorg/scalatest/enablers/Collecting;
    flags: (0x0009) ACC_PUBLIC, ACC_STATIC
    Code:
      stack=1, locals=0, args_size=0
         0: getstatic     #18                 // Field org/scalatest/enablers/Collecting$.MODULE$:Lorg/scalatest/enablers/Collecting$;
         3: invokevirtual #36                 // Method org/scalatest/enablers/Collecting$.collectingNatureOfArray:()Lorg/scalatest/enablers/Collecting;
         6: areturn
    Signature: #34                          // <E:Ljava/lang/Object;>()Lorg/scalatest/enablers/Collecting<TE;Ljava/lang/Object;>;

  public static <E extends java.lang.Object, TRAV extends scala.collection.Iterable<java.lang.Object>> org.scalatest.enablers.Collecting<E, TRAV> collectingNatureOfGenTraversable();
    descriptor: ()Lorg/scalatest/enablers/Collecting;
    flags: (0x0009) ACC_PUBLIC, ACC_STATIC
    Code:
      stack=1, locals=0, args_size=0
         0: getstatic     #18                 // Field org/scalatest/enablers/Collecting$.MODULE$:Lorg/scalatest/enablers/Collecting$;
         3: invokevirtual #40                 // Method org/scalatest/enablers/Collecting$.collectingNatureOfGenTraversable:()Lorg/scalatest/enablers/Collecting;
         6: areturn
    Signature: #38                          // <E:Ljava/lang/Object;TRAV::Lscala/collection/Iterable<Ljava/lang/Object;>;>()Lorg/scalatest/enablers/Collecting<TE;TTRAV;>;

  public abstract scala.Option<E> loneElementOf(C);
    descriptor: (Ljava/lang/Object;)Lscala/Option;
    flags: (0x0401) ACC_PUBLIC, ACC_ABSTRACT
    Signature: #43                          // (TC;)Lscala/Option<TE;>;
    MethodParameters:
      Name                           Flags
      collection                     final

  public abstract int sizeOf(C);
    descriptor: (Ljava/lang/Object;)I
    flags: (0x0401) ACC_PUBLIC, ACC_ABSTRACT
    Signature: #47                          // (TC;)I
    MethodParameters:
      Name                           Flags
      collection                     final

  public abstract scala.collection.Iterable<E> genTraversableFrom(C);
    descriptor: (Ljava/lang/Object;)Lscala/collection/Iterable;
    flags: (0x0401) ACC_PUBLIC, ACC_ABSTRACT
    Signature: #50                          // (TC;)Lscala/collection/Iterable<TE;>;
    MethodParameters:
      Name                           Flags
      collection                     final
}
Signature: #3                           // <E:Ljava/lang/Object;C:Ljava/lang/Object;>Ljava/lang/Object;
SourceFile: "Collecting.scala"
RuntimeVisibleAnnotations:
  0: #7(#8=s#9)
    scala.reflect.ScalaSignature(
      bytes="\u0006\u0005\u0005UdaB\u0007\u000f!\u0003\r\n!\u0006\u0005\u0006;\u00011\tA\b\u0005\u0006e\u00011\ta\r\u0005\u0006q\u00011\t!O\u0004\u0006\u0015:A\ta\u0013\u0004\u0006\u001b9A\t!\u0014\u0005\u0006\u001d\u0016!\ta\u0014\u0005\u0006!\u0016!\u0019!\u0015\u0005\u0006?\u0016!\u0019\u0001\u0019\u0005\u0006Q\u0016!\u0019!\u001b\u0005\u0006m\u0016!\u0019a\u001e\u0005\b\u0003/)A1AA\r\u0011\u001d\ty%\u0002C\u0002\u0003#\u0012!bQ8mY\u0016\u001cG/\u001b8h\u0015\ty\u0001#\u0001\u0005f]\u0006\u0014G.\u001a:t\u0015\t\t\"#A\u0005tG\u0006d\u0017\r^3ti*\t1#A\u0002pe\u001e\u001c\u0001!F\u0002\u0017IA\u001a\"\u0001A\f\u0011\u0005aYR\"A\r\u000b\u0003i\tQa]2bY\u0006L!\u0001H\r\u0003\r\u0005s\u0017PU3g\u00035awN\\3FY\u0016lWM\u001c;PMR\u0011q$\f\t\u00041\u0001\u0012\u0013BA\u0011\u001a\u0005\u0019y\u0005\u000f^5p]B\u00111\u0005\n\u0007\u0001\t\u0015)\u0003A1\u0001\'\u0005\u0005)\u0015CA\u0014+!\tA\u0002&\u0003\u0002*3\t9aj\u001c;iS:<\u0007C\u0001\r,\u0013\ta\u0013DA\u0002B]fDQAL\u0001A\u0002=\n!bY8mY\u0016\u001cG/[8o!\t\u0019\u0003\u0007B\u00032\u0001\t\u0007aEA\u0001D\u0003\u0019\u0019\u0018N_3PMR\u0011Ag\u000e\t\u00031UJ!AN\r\u0003\u0007%sG\u000fC\u0003/\u0005\u0001\u0007q&\u0001\nhK:$&/\u0019<feN\f\'\r\\3Ge>lGC\u0001\u001eJ!\rYdI\t\b\u0003y\rs!!\u0010\"\u000f\u0005y\nU\"A \u000b\u0005\u0001#\u0012A\u0002\u001fs_>$h(C\u0001\u001b\u0013\tq\u0013$\u0003\u0002E\u000b\u00069\u0001/Y2lC\u001e,\'B\u0001\u0018\u001a\u0013\t9\u0005J\u0001\bHK:$&/\u0019<feN\f\'\r\\3\u000b\u0005\u0011+\u0005\"\u0002\u0018\u0004\u0001\u0004y\u0013AC\"pY2,7\r^5oOB\u0011A*B\u0007\u0002\u001dM\u0011QaF\u0001\u0007y%t\u0017\u000e\u001e \u0015\u0003-\u000b\u0001eY8mY\u0016\u001cG/\u001b8h\u001d\u0006$XO]3PM\u001e+g\u000e\u0016:bm\u0016\u00148/\u00192mKV\u0019!+V,\u0016\u0003M\u0003B\u0001\u0014\u0001U-B\u00111%\u0016\u0003\u0006K\u001d\u0011\rA\n\t\u0004G]#F!\u0002-\b\u0005\u0004I&\u0001\u0002+S\u0003Z+\"AW/\u0012\u0005\u001dZ\u0006cA\u001eG9B\u00111%\u0018\u0003\u0006=^\u0013\rA\n\u0002\u0002K\u000692m\u001c7mK\u000e$\u0018N\\4OCR,(/Z(g\u0003J\u0014\u0018-_\u000b\u0003C\u0012,\u0012A\u0019\t\u0005\u0019\u0002\u0019W\r\u0005\u0002$I\u0012)Q\u0005\u0003b\u0001MA\u0019\u0001DZ2\n\u0005\u001dL\"!B!se\u0006L\u0018\u0001G2pY2,7\r^5oO:\u000bG/\u001e:f\u001f\u001a\u001cFO]5oOV\t!\u000e\u0005\u0003M\u0001-t\u0007C\u0001\rm\u0013\ti\u0017D\u0001\u0003DQ\u0006\u0014\bCA8t\u001d\t\u0001\u0018\u000f\u0005\u0002?3%\u0011!/G\u0001\u0007!J,G-\u001a4\n\u0005Q,(AB*ue&twM\u0003\u0002s3\u0005\u00013m\u001c7mK\u000e$\u0018N\\4OCR,(/Z(g\u0015\u00064\u0018mQ8mY\u0016\u001cG/[8o+\rA80`\u000b\u0002sB!A\n\u0001>}!\t\u00193\u0010B\u0003&\u0015\t\u0007a\u0005E\u0002${j$QA \u0006C\u0002}\u0014AAS\"P\u0019V!\u0011\u0011AA\u000b#\r9\u00131\u0001\t\u0007\u0003\u000b\ty!a\u0005\u000e\u0005\u0005\u001d!\u0002BA\u0005\u0003\u0017\tA!\u001e;jY*\u0011\u0011QB\u0001\u0005U\u00064\u0018-\u0003\u0003\u0002\u0012\u0005\u001d!AC\"pY2,7\r^5p]B\u00191%!\u0006\u0005\u000byk(\u0019\u0001\u0014\u00023\r|G\u000e\\3di&twMT1ukJ,wJ\u001a&bm\u0006l\u0015\r]\u000b\t\u00037\tI#a\f\u00026U\u0011\u0011Q\u0004\t\u0007\u0019\u0002\ty\"a\r\u0011\u0011\u0005\u0005\u00121EA\u0014\u0003[i\u0011\u0001E\u0005\u0004\u0003K\u0001\"!B#oiJL\bcA\u0012\u0002*\u00111\u00111F\u0006C\u0002\u0019\u0012\u0011a\u0013\t\u0004G\u0005=BABA\u0019\u0017\t\u0007aEA\u0001W!\u001d\u0019\u0013QGA\u0014\u0003[!q!a\u000e\f\u0005\u0004\tID\u0001\u0003K\u001b\u0006\u0003VCBA\u001e\u0003\u000b\nY%E\u0002(\u0003{\u0001\u0002\"!\u0002\u0002@\u0005\r\u0013\u0011J\u0005\u0005\u0003\u0003\n9AA\u0002NCB\u00042aIA#\t\u001d\t9%!\u000eC\u0002\u0019\u0012\u0011a\u001b\t\u0004G\u0005-CaBA\'\u0003k\u0011\rA\n\u0002\u0002m\u000692m\u001c7mK\u000e$\u0018N\\4OCR,(/Z(g\u000bZ,\'/_\u000b\u0007\u0003\'\nI&!\u0018\u0016\u0005\u0005U\u0003C\u0002\'\u0001\u0003/\nY\u0006E\u0002$\u00033\"Q!\n\u0007C\u0002\u0019\u0002RaIA/\u0003/\"q!a\u0018\r\u0005\u0004\t\tGA\u0003F-\u0016\u0013\u0016,\u0006\u0003\u0002d\u0005M\u0014cA\u0014\u0002fA1\u0011qMA7\u0003cj!!!\u001b\u000b\u0007\u0005-$#A\u0005tG\u0006d\u0017m\u0019;jG&!\u0011qNA5\u0005\u0015)e/\u001a:z!\r\u0019\u00131\u000f\u0003\u0007=\u0006u#\u0019\u0001\u0014"
    )
  ScalaInlineInfo: length = 0x13 (unknown attribute)
   01 00 00 03 00 30 00 31 00 00 29 00 2A 00 00 2D
   00 2E 00
  ScalaSig: length = 0x3 (unknown attribute)
   05 02 00
