Classfile /Users/mw/Projects/slang-braindump/.jar/jar8/assemble/slang-braindump/assemble/content/org/scalatest/enablers/Collecting$$anon$5.class
  Last modified May 29, 2022; size 3885 bytes
  SHA-256 checksum 4d623bce2ae798522b0975e43a49cc8104e86d34f91c02e3908f7dded0977f8f
  Compiled from "Collecting.scala"
public final class org.scalatest.enablers.Collecting$$anon$5 extends java.lang.Object implements org.scalatest.enablers.Collecting<org.scalatest.Entry<K, V>, JMAP>
  minor version: 0
  major version: 52
  flags: (0x0031) ACC_PUBLIC, ACC_FINAL, ACC_SUPER
  this_class: #2                          // org/scalatest/enablers/Collecting$$anon$5
  super_class: #5                         // java/lang/Object
  interfaces: 1, fields: 0, methods: 9, attributes: 7
Constant pool:
    #1 = Utf8               org/scalatest/enablers/Collecting$$anon$5
    #2 = Class              #1            // org/scalatest/enablers/Collecting$$anon$5
    #3 = Utf8               Ljava/lang/Object;Lorg/scalatest/enablers/Collecting<Lorg/scalatest/Entry<TK;TV;>;TJMAP;>;
    #4 = Utf8               java/lang/Object
    #5 = Class              #4            // java/lang/Object
    #6 = Utf8               org/scalatest/enablers/Collecting
    #7 = Class              #6            // org/scalatest/enablers/Collecting
    #8 = Utf8               Collecting.scala
    #9 = Utf8               org/scalatest/enablers/Collecting$
   #10 = Class              #9            // org/scalatest/enablers/Collecting$
   #11 = Utf8               collectingNatureOfJavaMap
   #12 = Utf8               ()Lorg/scalatest/enablers/Collecting;
   #13 = NameAndType        #11:#12       // collectingNatureOfJavaMap:()Lorg/scalatest/enablers/Collecting;
   #14 = Utf8               java/lang/invoke/MethodHandles$Lookup
   #15 = Class              #14           // java/lang/invoke/MethodHandles$Lookup
   #16 = Utf8               java/lang/invoke/MethodHandles
   #17 = Class              #16           // java/lang/invoke/MethodHandles
   #18 = Utf8               Lookup
   #19 = Utf8               java/util/Map$Entry
   #20 = Class              #19           // java/util/Map$Entry
   #21 = Utf8               java/util/Map
   #22 = Class              #21           // java/util/Map
   #23 = Utf8               Entry
   #24 = Utf8               scala/collection/JavaConverters$AsScala
   #25 = Class              #24           // scala/collection/JavaConverters$AsScala
   #26 = Utf8               scala/collection/JavaConverters
   #27 = Class              #26           // scala/collection/JavaConverters
   #28 = Utf8               AsScala
   #29 = Utf8               loneElementOf
   #30 = Utf8               (Ljava/util/Map;)Lscala/Option;
   #31 = Utf8               (TJMAP;)Lscala/Option<Lorg/scalatest/Entry<TK;TV;>;>;
   #32 = Utf8               jmap
   #33 = Utf8               size
   #34 = Utf8               ()I
   #35 = NameAndType        #33:#34       // size:()I
   #36 = InterfaceMethodref #22.#35       // java/util/Map.size:()I
   #37 = Utf8               entrySet
   #38 = Utf8               ()Ljava/util/Set;
   #39 = NameAndType        #37:#38       // entrySet:()Ljava/util/Set;
   #40 = InterfaceMethodref #22.#39       // java/util/Map.entrySet:()Ljava/util/Set;
   #41 = Utf8               java/util/Set
   #42 = Class              #41           // java/util/Set
   #43 = Utf8               iterator
   #44 = Utf8               ()Ljava/util/Iterator;
   #45 = NameAndType        #43:#44       // iterator:()Ljava/util/Iterator;
   #46 = InterfaceMethodref #42.#45       // java/util/Set.iterator:()Ljava/util/Iterator;
   #47 = Utf8               java/util/Iterator
   #48 = Class              #47           // java/util/Iterator
   #49 = Utf8               next
   #50 = Utf8               ()Ljava/lang/Object;
   #51 = NameAndType        #49:#50       // next:()Ljava/lang/Object;
   #52 = InterfaceMethodref #48.#51       // java/util/Iterator.next:()Ljava/lang/Object;
   #53 = Utf8               scala/Some
   #54 = Class              #53           // scala/Some
   #55 = Utf8               org/scalatest/Entry
   #56 = Class              #55           // org/scalatest/Entry
   #57 = Utf8               getKey
   #58 = NameAndType        #57:#50       // getKey:()Ljava/lang/Object;
   #59 = InterfaceMethodref #20.#58       // java/util/Map$Entry.getKey:()Ljava/lang/Object;
   #60 = Utf8               getValue
   #61 = NameAndType        #60:#50       // getValue:()Ljava/lang/Object;
   #62 = InterfaceMethodref #20.#61       // java/util/Map$Entry.getValue:()Ljava/lang/Object;
   #63 = Utf8               <init>
   #64 = Utf8               (Ljava/lang/Object;Ljava/lang/Object;)V
   #65 = NameAndType        #63:#64       // "<init>":(Ljava/lang/Object;Ljava/lang/Object;)V
   #66 = Methodref          #56.#65       // org/scalatest/Entry."<init>":(Ljava/lang/Object;Ljava/lang/Object;)V
   #67 = Utf8               (Ljava/lang/Object;)V
   #68 = NameAndType        #63:#67       // "<init>":(Ljava/lang/Object;)V
   #69 = Methodref          #54.#68       // scala/Some."<init>":(Ljava/lang/Object;)V
   #70 = Utf8               scala/None$
   #71 = Class              #70           // scala/None$
   #72 = Utf8               MODULE$
   #73 = Utf8               Lscala/None$;
   #74 = NameAndType        #72:#73       // MODULE$:Lscala/None$;
   #75 = Fieldref           #71.#74       // scala/None$.MODULE$:Lscala/None$;
   #76 = Utf8               loneEntry
   #77 = Utf8               Ljava/util/Map$Entry;
   #78 = Utf8               this
   #79 = Utf8               Lorg/scalatest/enablers/Collecting$$anon$5;
   #80 = Utf8               Ljava/util/Map;
   #81 = Utf8               scala/Option
   #82 = Class              #81           // scala/Option
   #83 = Utf8               sizeOf
   #84 = Utf8               (Ljava/util/Map;)I
   #85 = Utf8               (TJMAP;)I
   #86 = Utf8               genTraversableFrom
   #87 = Utf8               (Ljava/util/Map;)Lscala/collection/Iterable;
   #88 = Utf8               (TJMAP;)Lscala/collection/Iterable<Lorg/scalatest/Entry<TK;TV;>;>;
   #89 = Utf8               collection
   #90 = Utf8               scala/collection/JavaConverters$
   #91 = Class              #90           // scala/collection/JavaConverters$
   #92 = Utf8               Lscala/collection/JavaConverters$;
   #93 = NameAndType        #72:#92       // MODULE$:Lscala/collection/JavaConverters$;
   #94 = Fieldref           #91.#93       // scala/collection/JavaConverters$.MODULE$:Lscala/collection/JavaConverters$;
   #95 = Utf8               asScalaIteratorConverter
   #96 = Utf8               (Ljava/util/Iterator;)Lscala/collection/JavaConverters$AsScala;
   #97 = NameAndType        #95:#96       // asScalaIteratorConverter:(Ljava/util/Iterator;)Lscala/collection/JavaConverters$AsScala;
   #98 = Methodref          #91.#97       // scala/collection/JavaConverters$.asScalaIteratorConverter:(Ljava/util/Iterator;)Lscala/collection/JavaConverters$AsScala;
   #99 = Utf8               asScala
  #100 = NameAndType        #99:#50       // asScala:()Ljava/lang/Object;
  #101 = Methodref          #25.#100      // scala/collection/JavaConverters$AsScala.asScala:()Ljava/lang/Object;
  #102 = Utf8               scala/collection/Iterator
  #103 = Class              #102          // scala/collection/Iterator
  #104 = Utf8               (Ljava/lang/Object;)Ljava/lang/Object;
  #105 = MethodType         #104          //  (Ljava/lang/Object;)Ljava/lang/Object;
  #106 = Utf8               $anonfun$genTraversableFrom$1
  #107 = Utf8               (Ljava/util/Map$Entry;)Lorg/scalatest/Entry;
  #108 = NameAndType        #106:#107     // $anonfun$genTraversableFrom$1:(Ljava/util/Map$Entry;)Lorg/scalatest/Entry;
  #109 = Methodref          #2.#108       // org/scalatest/enablers/Collecting$$anon$5.$anonfun$genTraversableFrom$1:(Ljava/util/Map$Entry;)Lorg/scalatest/Entry;
  #110 = MethodHandle       6:#109        // REF_invokeStatic org/scalatest/enablers/Collecting$$anon$5.$anonfun$genTraversableFrom$1:(Ljava/util/Map$Entry;)Lorg/scalatest/Entry;
  #111 = MethodType         #107          //  (Ljava/util/Map$Entry;)Lorg/scalatest/Entry;
  #112 = Integer            5
  #113 = Integer            1
  #114 = Utf8               java/lang/invoke/LambdaMetafactory
  #115 = Class              #114          // java/lang/invoke/LambdaMetafactory
  #116 = Utf8               altMetafactory
  #117 = Utf8               (Ljava/lang/invoke/MethodHandles$Lookup;Ljava/lang/String;Ljava/lang/invoke/MethodType;[Ljava/lang/Object;)Ljava/lang/invoke/CallSite;
  #118 = NameAndType        #116:#117     // altMetafactory:(Ljava/lang/invoke/MethodHandles$Lookup;Ljava/lang/String;Ljava/lang/invoke/MethodType;[Ljava/lang/Object;)Ljava/lang/invoke/CallSite;
  #119 = Methodref          #115.#118     // java/lang/invoke/LambdaMetafactory.altMetafactory:(Ljava/lang/invoke/MethodHandles$Lookup;Ljava/lang/String;Ljava/lang/invoke/MethodType;[Ljava/lang/Object;)Ljava/lang/invoke/CallSite;
  #120 = MethodHandle       6:#119        // REF_invokeStatic java/lang/invoke/LambdaMetafactory.altMetafactory:(Ljava/lang/invoke/MethodHandles$Lookup;Ljava/lang/String;Ljava/lang/invoke/MethodType;[Ljava/lang/Object;)Ljava/lang/invoke/CallSite;
  #121 = Utf8               apply
  #122 = Utf8               ()Lscala/Function1;
  #123 = NameAndType        #121:#122     // apply:()Lscala/Function1;
  #124 = InvokeDynamic      #0:#123       // #0:apply:()Lscala/Function1;
  #125 = Utf8               map
  #126 = Utf8               (Lscala/Function1;)Lscala/collection/Iterator;
  #127 = NameAndType        #125:#126     // map:(Lscala/Function1;)Lscala/collection/Iterator;
  #128 = InterfaceMethodref #103.#127     // scala/collection/Iterator.map:(Lscala/Function1;)Lscala/collection/Iterator;
  #129 = Utf8               toList
  #130 = Utf8               ()Lscala/collection/immutable/List;
  #131 = NameAndType        #129:#130     // toList:()Lscala/collection/immutable/List;
  #132 = InterfaceMethodref #103.#131     // scala/collection/Iterator.toList:()Lscala/collection/immutable/List;
  #133 = Utf8               (Ljava/lang/Object;)Lscala/collection/Iterable;
  #134 = NameAndType        #86:#87       // genTraversableFrom:(Ljava/util/Map;)Lscala/collection/Iterable;
  #135 = Methodref          #2.#134       // org/scalatest/enablers/Collecting$$anon$5.genTraversableFrom:(Ljava/util/Map;)Lscala/collection/Iterable;
  #136 = Utf8               Ljava/lang/Object;
  #137 = Utf8               (Ljava/lang/Object;)I
  #138 = NameAndType        #83:#84       // sizeOf:(Ljava/util/Map;)I
  #139 = Methodref          #2.#138       // org/scalatest/enablers/Collecting$$anon$5.sizeOf:(Ljava/util/Map;)I
  #140 = Utf8               (Ljava/lang/Object;)Lscala/Option;
  #141 = NameAndType        #29:#30       // loneElementOf:(Ljava/util/Map;)Lscala/Option;
  #142 = Methodref          #2.#141       // org/scalatest/enablers/Collecting$$anon$5.loneElementOf:(Ljava/util/Map;)Lscala/Option;
  #143 = Utf8               entry
  #144 = Utf8               ()V
  #145 = NameAndType        #63:#144      // "<init>":()V
  #146 = Methodref          #5.#145       // java/lang/Object."<init>":()V
  #147 = Utf8               $deserializeLambda$
  #148 = Utf8               (Ljava/lang/invoke/SerializedLambda;)Ljava/lang/Object;
  #149 = Utf8               scala/runtime/LambdaDeserialize
  #150 = Class              #149          // scala/runtime/LambdaDeserialize
  #151 = Utf8               bootstrap
  #152 = Utf8               (Ljava/lang/invoke/MethodHandles$Lookup;Ljava/lang/String;Ljava/lang/invoke/MethodType;[Ljava/lang/invoke/MethodHandle;)Ljava/lang/invoke/CallSite;
  #153 = NameAndType        #151:#152     // bootstrap:(Ljava/lang/invoke/MethodHandles$Lookup;Ljava/lang/String;Ljava/lang/invoke/MethodType;[Ljava/lang/invoke/MethodHandle;)Ljava/lang/invoke/CallSite;
  #154 = Methodref          #150.#153     // scala/runtime/LambdaDeserialize.bootstrap:(Ljava/lang/invoke/MethodHandles$Lookup;Ljava/lang/String;Ljava/lang/invoke/MethodType;[Ljava/lang/invoke/MethodHandle;)Ljava/lang/invoke/CallSite;
  #155 = MethodHandle       6:#154        // REF_invokeStatic scala/runtime/LambdaDeserialize.bootstrap:(Ljava/lang/invoke/MethodHandles$Lookup;Ljava/lang/String;Ljava/lang/invoke/MethodType;[Ljava/lang/invoke/MethodHandle;)Ljava/lang/invoke/CallSite;
  #156 = Utf8               lambdaDeserialize
  #157 = NameAndType        #156:#148     // lambdaDeserialize:(Ljava/lang/invoke/SerializedLambda;)Ljava/lang/Object;
  #158 = InvokeDynamic      #1:#157       // #1:lambdaDeserialize:(Ljava/lang/invoke/SerializedLambda;)Ljava/lang/Object;
  #159 = Utf8               Code
  #160 = Utf8               StackMapTable
  #161 = Utf8               LineNumberTable
  #162 = Utf8               LocalVariableTable
  #163 = Utf8               Signature
  #164 = Utf8               MethodParameters
  #165 = Utf8               InnerClasses
  #166 = Utf8               EnclosingMethod
  #167 = Utf8               SourceFile
  #168 = Utf8               BootstrapMethods
  #169 = Utf8               ScalaInlineInfo
  #170 = Utf8               Scala
{
  public scala.Option<org.scalatest.Entry<K, V>> loneElementOf(JMAP);
    descriptor: (Ljava/util/Map;)Lscala/Option;
    flags: (0x0001) ACC_PUBLIC
    Code:
      stack=6, locals=3, args_size=2
         0: aload_1
         1: invokeinterface #36,  1           // InterfaceMethod java/util/Map.size:()I
         6: iconst_1
         7: if_icmpne     59
        10: aload_1
        11: invokeinterface #40,  1           // InterfaceMethod java/util/Map.entrySet:()Ljava/util/Set;
        16: invokeinterface #46,  1           // InterfaceMethod java/util/Set.iterator:()Ljava/util/Iterator;
        21: invokeinterface #52,  1           // InterfaceMethod java/util/Iterator.next:()Ljava/lang/Object;
        26: checkcast     #20                 // class java/util/Map$Entry
        29: astore_2
        30: new           #54                 // class scala/Some
        33: dup
        34: new           #56                 // class org/scalatest/Entry
        37: dup
        38: aload_2
        39: invokeinterface #59,  1           // InterfaceMethod java/util/Map$Entry.getKey:()Ljava/lang/Object;
        44: aload_2
        45: invokeinterface #62,  1           // InterfaceMethod java/util/Map$Entry.getValue:()Ljava/lang/Object;
        50: invokespecial #66                 // Method org/scalatest/Entry."<init>":(Ljava/lang/Object;Ljava/lang/Object;)V
        53: invokespecial #69                 // Method scala/Some."<init>":(Ljava/lang/Object;)V
        56: goto          62
        59: getstatic     #75                 // Field scala/None$.MODULE$:Lscala/None$;
        62: areturn
      StackMapTable: number_of_entries = 2
        frame_type = 59 /* same */
        frame_type = 66 /* same_locals_1_stack_item */
          stack = [ class scala/Option ]
      LineNumberTable:
        line 172: 0
        line 173: 10
        line 174: 30
        line 175: 59
      LocalVariableTable:
        Start  Length  Slot  Name   Signature
           30      26     2 loneEntry   Ljava/util/Map$Entry;
            0      63     0  this   Lorg/scalatest/enablers/Collecting$$anon$5;
            0      63     1  jmap   Ljava/util/Map;
    Signature: #31                          // (TJMAP;)Lscala/Option<Lorg/scalatest/Entry<TK;TV;>;>;
    MethodParameters:
      Name                           Flags
      jmap                           final

  public int sizeOf(JMAP);
    descriptor: (Ljava/util/Map;)I
    flags: (0x0001) ACC_PUBLIC
    Code:
      stack=1, locals=2, args_size=2
         0: aload_1
         1: invokeinterface #36,  1           // InterfaceMethod java/util/Map.size:()I
         6: ireturn
      LineNumberTable:
        line 177: 0
      LocalVariableTable:
        Start  Length  Slot  Name   Signature
            0       7     0  this   Lorg/scalatest/enablers/Collecting$$anon$5;
            0       7     1  jmap   Ljava/util/Map;
    Signature: #85                          // (TJMAP;)I
    MethodParameters:
      Name                           Flags
      jmap                           final

  public scala.collection.Iterable<org.scalatest.Entry<K, V>> genTraversableFrom(JMAP);
    descriptor: (Ljava/util/Map;)Lscala/collection/Iterable;
    flags: (0x0001) ACC_PUBLIC
    Code:
      stack=2, locals=2, args_size=2
         0: getstatic     #94                 // Field scala/collection/JavaConverters$.MODULE$:Lscala/collection/JavaConverters$;
         3: aload_1
         4: invokeinterface #40,  1           // InterfaceMethod java/util/Map.entrySet:()Ljava/util/Set;
         9: invokeinterface #46,  1           // InterfaceMethod java/util/Set.iterator:()Ljava/util/Iterator;
        14: invokevirtual #98                 // Method scala/collection/JavaConverters$.asScalaIteratorConverter:(Ljava/util/Iterator;)Lscala/collection/JavaConverters$AsScala;
        17: invokevirtual #101                // Method scala/collection/JavaConverters$AsScala.asScala:()Ljava/lang/Object;
        20: checkcast     #103                // class scala/collection/Iterator
        23: invokedynamic #124,  0            // InvokeDynamic #0:apply:()Lscala/Function1;
        28: invokeinterface #128,  2          // InterfaceMethod scala/collection/Iterator.map:(Lscala/Function1;)Lscala/collection/Iterator;
        33: invokeinterface #132,  1          // InterfaceMethod scala/collection/Iterator.toList:()Lscala/collection/immutable/List;
        38: areturn
      LineNumberTable:
        line 183: 0
      LocalVariableTable:
        Start  Length  Slot  Name   Signature
            0      39     0  this   Lorg/scalatest/enablers/Collecting$$anon$5;
            0      39     1 collection   Ljava/util/Map;
    Signature: #88                          // (TJMAP;)Lscala/collection/Iterable<Lorg/scalatest/Entry<TK;TV;>;>;
    MethodParameters:
      Name                           Flags
      collection                     final

  public scala.collection.Iterable genTraversableFrom(java.lang.Object);
    descriptor: (Ljava/lang/Object;)Lscala/collection/Iterable;
    flags: (0x1041) ACC_PUBLIC, ACC_BRIDGE, ACC_SYNTHETIC
    Code:
      stack=2, locals=2, args_size=2
         0: aload_0
         1: aload_1
         2: checkcast     #22                 // class java/util/Map
         5: invokevirtual #135                // Method genTraversableFrom:(Ljava/util/Map;)Lscala/collection/Iterable;
         8: areturn
      LineNumberTable:
        line 170: 0
      LocalVariableTable:
        Start  Length  Slot  Name   Signature
            0       9     0  this   Lorg/scalatest/enablers/Collecting$$anon$5;
            0       9     1 collection   Ljava/lang/Object;
    MethodParameters:
      Name                           Flags
      collection                     final

  public int sizeOf(java.lang.Object);
    descriptor: (Ljava/lang/Object;)I
    flags: (0x1041) ACC_PUBLIC, ACC_BRIDGE, ACC_SYNTHETIC
    Code:
      stack=2, locals=2, args_size=2
         0: aload_0
         1: aload_1
         2: checkcast     #22                 // class java/util/Map
         5: invokevirtual #139                // Method sizeOf:(Ljava/util/Map;)I
         8: ireturn
      LineNumberTable:
        line 170: 0
      LocalVariableTable:
        Start  Length  Slot  Name   Signature
            0       9     0  this   Lorg/scalatest/enablers/Collecting$$anon$5;
            0       9     1 collection   Ljava/lang/Object;
    MethodParameters:
      Name                           Flags
      collection                     final

  public scala.Option loneElementOf(java.lang.Object);
    descriptor: (Ljava/lang/Object;)Lscala/Option;
    flags: (0x1041) ACC_PUBLIC, ACC_BRIDGE, ACC_SYNTHETIC
    Code:
      stack=2, locals=2, args_size=2
         0: aload_0
         1: aload_1
         2: checkcast     #22                 // class java/util/Map
         5: invokevirtual #142                // Method loneElementOf:(Ljava/util/Map;)Lscala/Option;
         8: areturn
      LineNumberTable:
        line 170: 0
      LocalVariableTable:
        Start  Length  Slot  Name   Signature
            0       9     0  this   Lorg/scalatest/enablers/Collecting$$anon$5;
            0       9     1 collection   Ljava/lang/Object;
    MethodParameters:
      Name                           Flags
      collection                     final

  public static final org.scalatest.Entry $anonfun$genTraversableFrom$1(java.util.Map$Entry);
    descriptor: (Ljava/util/Map$Entry;)Lorg/scalatest/Entry;
    flags: (0x1019) ACC_PUBLIC, ACC_STATIC, ACC_FINAL, ACC_SYNTHETIC
    Code:
      stack=4, locals=1, args_size=1
         0: new           #56                 // class org/scalatest/Entry
         3: dup
         4: aload_0
         5: invokeinterface #59,  1           // InterfaceMethod java/util/Map$Entry.getKey:()Ljava/lang/Object;
        10: aload_0
        11: invokeinterface #62,  1           // InterfaceMethod java/util/Map$Entry.getValue:()Ljava/lang/Object;
        16: invokespecial #66                 // Method org/scalatest/Entry."<init>":(Ljava/lang/Object;Ljava/lang/Object;)V
        19: areturn
      LineNumberTable:
        line 183: 0
      LocalVariableTable:
        Start  Length  Slot  Name   Signature
            0      20     0 entry   Ljava/util/Map$Entry;
    MethodParameters:
      Name                           Flags
      entry                          final

  public org.scalatest.enablers.Collecting$$anon$5();
    descriptor: ()V
    flags: (0x0001) ACC_PUBLIC
    Code:
      stack=1, locals=1, args_size=1
         0: aload_0
         1: invokespecial #146                // Method java/lang/Object."<init>":()V
         4: return
      LineNumberTable:
        line 170: 0
      LocalVariableTable:
        Start  Length  Slot  Name   Signature
            0       5     0  this   Lorg/scalatest/enablers/Collecting$$anon$5;

  private static java.lang.Object $deserializeLambda$(java.lang.invoke.SerializedLambda);
    descriptor: (Ljava/lang/invoke/SerializedLambda;)Ljava/lang/Object;
    flags: (0x100a) ACC_PRIVATE, ACC_STATIC, ACC_SYNTHETIC
    Code:
      stack=1, locals=1, args_size=1
         0: aload_0
         1: invokedynamic #158,  0            // InvokeDynamic #1:lambdaDeserialize:(Ljava/lang/invoke/SerializedLambda;)Ljava/lang/Object;
         6: areturn
}
InnerClasses:
  public static final #18= #15 of #17;    // Lookup=class java/lang/invoke/MethodHandles$Lookup of class java/lang/invoke/MethodHandles
  public static #23= #20 of #22;          // Entry=class java/util/Map$Entry of class java/util/Map
  public final #2;                        // class org/scalatest/enablers/Collecting$$anon$5
  public static #28= #25 of #27;          // AsScala=class scala/collection/JavaConverters$AsScala of class scala/collection/JavaConverters
EnclosingMethod: #10.#13                // org.scalatest.enablers.Collecting$.collectingNatureOfJavaMap
Signature: #3                           // Ljava/lang/Object;Lorg/scalatest/enablers/Collecting<Lorg/scalatest/Entry<TK;TV;>;TJMAP;>;
SourceFile: "Collecting.scala"
BootstrapMethods:
  0: #120 REF_invokeStatic java/lang/invoke/LambdaMetafactory.altMetafactory:(Ljava/lang/invoke/MethodHandles$Lookup;Ljava/lang/String;Ljava/lang/invoke/MethodType;[Ljava/lang/Object;)Ljava/lang/invoke/CallSite;
    Method arguments:
      #105 (Ljava/lang/Object;)Ljava/lang/Object;
      #110 REF_invokeStatic org/scalatest/enablers/Collecting$$anon$5.$anonfun$genTraversableFrom$1:(Ljava/util/Map$Entry;)Lorg/scalatest/Entry;
      #111 (Ljava/util/Map$Entry;)Lorg/scalatest/Entry;
      #112 5
      #113 1
      #111 (Ljava/util/Map$Entry;)Lorg/scalatest/Entry;
  1: #155 REF_invokeStatic scala/runtime/LambdaDeserialize.bootstrap:(Ljava/lang/invoke/MethodHandles$Lookup;Ljava/lang/String;Ljava/lang/invoke/MethodType;[Ljava/lang/invoke/MethodHandle;)Ljava/lang/invoke/CallSite;
    Method arguments:
      #110 REF_invokeStatic org/scalatest/enablers/Collecting$$anon$5.$anonfun$genTraversableFrom$1:(Ljava/util/Map$Entry;)Lorg/scalatest/Entry;
  ScalaInlineInfo: length = 0x2C (unknown attribute)
   01 01 00 08 00 6A 00 6B 01 00 3F 00 90 01 00 56
   00 85 01 00 56 00 57 01 00 1D 00 8C 01 00 1D 00
   1E 01 00 53 00 89 01 00 53 00 54 01
  Scala: length = 0x0 (unknown attribute)

