Classfile /Users/mw/Projects/slang-braindump/.jar/jar8/assemble/slang-braindump/assemble/content/org/scalatest/enablers/Definition.class
  Last modified May 29, 2022; size 1682 bytes
  SHA-256 checksum c8f7f0a4b3f91d178d21eeafd28febc39169df119245aeec276edaab3412fe0e
  Compiled from "Definition.scala"
public interface org.scalatest.enablers.Definition<T extends java.lang.Object>
  minor version: 0
  major version: 52
  flags: (0x0601) ACC_PUBLIC, ACC_INTERFACE, ACC_ABSTRACT
  this_class: #2                          // org/scalatest/enablers/Definition
  super_class: #5                         // java/lang/Object
  interfaces: 0, fields: 0, methods: 4, attributes: 5
Constant pool:
   #1 = Utf8               org/scalatest/enablers/Definition
   #2 = Class              #1             // org/scalatest/enablers/Definition
   #3 = Utf8               <T:Ljava/lang/Object;>Ljava/lang/Object;
   #4 = Utf8               java/lang/Object
   #5 = Class              #4             // java/lang/Object
   #6 = Utf8               Definition.scala
   #7 = Utf8               Lscala/reflect/ScalaSignature;
   #8 = Utf8               bytes
   #9 = Utf8               \u0006\u0005e3q\u0001C\u0005\u0011\u0002G\u0005\u0001\u0003C\u0003\u0019\u0001\u0019\u0005\u0011dB\u0003+\u0013!\u00051FB\u0003\t\u0013!\u0005Q\u0006C\u0003/\u0007\u0011\u0005q\u0006C\u00031\u0007\u0011\r\u0011\u0007C\u0003C\u0007\u0011\r1\tC\u0003O\u0007\u0011\rqJ\u0001\u0006EK\u001aLg.\u001b;j_:T!AC\u0006\u0002\u0011\u0015t\u0017M\u00197feNT!\u0001D\u0007\u0002\u0013M\u001c\u0017\r\\1uKN$(\"\u0001\b\u0002\u0007=\u0014xm\u0001\u0001\u0016\u0005E\t3C\u0001\u0001\u0013!\t\u0019b#D\u0001\u0015\u0015\u0005)\u0012!B:dC2\f\u0017BA\f\u0015\u0005\u0019\te.\u001f*fM\u0006I\u0011n\u001d#fM&tW\r\u001a\u000b\u00035u\u0001\"aE\u000e\n\u0005q!\"a\u0002\"p_2,\u0017M\u001c\u0005\u0006=\u0005\u0001\raH\u0001\u0006i\"Lgn\u001a\t\u0003A\u0005b\u0001\u0001\u0002\u0004#\u0001!\u0015\ra\t\u0002\u0002)F\u0011Ae\n\t\u0003\'\u0015J!A\n\u000b\u0003\u000f9{G\u000f[5oOB\u00111\u0003K\u0005\u0003SQ\u00111!\u00118z\u0003)!UMZ5oSRLwN\u001c\t\u0003Y\ri\u0011!C\n\u0003\u0007I\ta\u0001P5oSRtD#A\u0016\u0002%\u0011,g-\u001b8ji&|gn\u00144PaRLwN\\\u000b\u0004e\u0001+T#A\u001a\u0011\u00071\u0002A\u0007E\u0002!k}\"QAN\u0003C\u0002]\u00121a\u0014)U+\tAT(\u0005\u0002%sA\u00191C\u000f\u001f\n\u0005m\"\"AB(qi&|g\u000e\u0005\u0002!{\u0011)a(\u000eb\u0001G\t\tQ\r\u0005\u0002!\u0001\u0012)\u0011)\u0002b\u0001G\t\tQ)A\u0013eK\u001aLg.\u001b;j_:|e-\u00118z%\u00164w+\u001b;i\u0013N$UMZ5oK\u0012lU\r\u001e5pIV\u0011AiR\u000b\u0002\u000bB\u0019A\u0006\u0001$\u0011\u0005\u0001:E!\u0002\u0012\u0007\u0005\u0004A\u0015C\u0001\u0013J%\tQ%C\u0002\u0003L\u0007\u0001I%\u0001\u0004\u001fsK\u001aLg.Z7f]Rt\u0004\"\u0002\rK\r\u0003iE#\u0001\u000e\u0002e\u0011,g-\u001b8ji&|gn\u00144B]f\u0014VMZ,ji\"\u0004\u0016M]1nKR,\'\u000f\\3tg&\u001bH)\u001a4j]\u0016$W*\u001a;i_\u0012,\"\u0001U*\u0016\u0003E\u00032\u0001\f\u0001S!\t\u00013\u000bB\u0003#\u000f\t\u0007A+\u0005\u0002%+J\u0011aK\u0005\u0004\u0005\u0017\u000e\u0001Q\u000bC\u0003\u0019-\u001a\u0005\u0001,F\u0001\u001b\u0001
  #10 = Utf8               definitionOfAnyRefWithParameterlessIsDefinedMethod
  #11 = Utf8               ()Lorg/scalatest/enablers/Definition;
  #12 = Utf8               <T:Ljava/lang/Object;>()Lorg/scalatest/enablers/Definition<TT;>;
  #13 = Utf8               org/scalatest/enablers/Definition$
  #14 = Class              #13            // org/scalatest/enablers/Definition$
  #15 = Utf8               MODULE$
  #16 = Utf8               Lorg/scalatest/enablers/Definition$;
  #17 = NameAndType        #15:#16        // MODULE$:Lorg/scalatest/enablers/Definition$;
  #18 = Fieldref           #14.#17        // org/scalatest/enablers/Definition$.MODULE$:Lorg/scalatest/enablers/Definition$;
  #19 = NameAndType        #10:#11        // definitionOfAnyRefWithParameterlessIsDefinedMethod:()Lorg/scalatest/enablers/Definition;
  #20 = Methodref          #14.#19        // org/scalatest/enablers/Definition$.definitionOfAnyRefWithParameterlessIsDefinedMethod:()Lorg/scalatest/enablers/Definition;
  #21 = Utf8               definitionOfAnyRefWithIsDefinedMethod
  #22 = NameAndType        #21:#11        // definitionOfAnyRefWithIsDefinedMethod:()Lorg/scalatest/enablers/Definition;
  #23 = Methodref          #14.#22        // org/scalatest/enablers/Definition$.definitionOfAnyRefWithIsDefinedMethod:()Lorg/scalatest/enablers/Definition;
  #24 = Utf8               definitionOfOption
  #25 = Utf8               <E:Ljava/lang/Object;OPT:Lscala/Option<Ljava/lang/Object;>;>()Lorg/scalatest/enablers/Definition<TOPT;>;
  #26 = NameAndType        #24:#11        // definitionOfOption:()Lorg/scalatest/enablers/Definition;
  #27 = Methodref          #14.#26        // org/scalatest/enablers/Definition$.definitionOfOption:()Lorg/scalatest/enablers/Definition;
  #28 = Utf8               isDefined
  #29 = Utf8               (Ljava/lang/Object;)Z
  #30 = Utf8               (TT;)Z
  #31 = Utf8               thing
  #32 = Utf8               Code
  #33 = Utf8               Signature
  #34 = Utf8               MethodParameters
  #35 = Utf8               SourceFile
  #36 = Utf8               RuntimeVisibleAnnotations
  #37 = Utf8               ScalaInlineInfo
  #38 = Utf8               ScalaSig
{
  public static <T extends java.lang.Object> org.scalatest.enablers.Definition<T> definitionOfAnyRefWithParameterlessIsDefinedMethod();
    descriptor: ()Lorg/scalatest/enablers/Definition;
    flags: (0x0009) ACC_PUBLIC, ACC_STATIC
    Code:
      stack=1, locals=0, args_size=0
         0: getstatic     #18                 // Field org/scalatest/enablers/Definition$.MODULE$:Lorg/scalatest/enablers/Definition$;
         3: invokevirtual #20                 // Method org/scalatest/enablers/Definition$.definitionOfAnyRefWithParameterlessIsDefinedMethod:()Lorg/scalatest/enablers/Definition;
         6: areturn
    Signature: #12                          // <T:Ljava/lang/Object;>()Lorg/scalatest/enablers/Definition<TT;>;

  public static <T extends java.lang.Object> org.scalatest.enablers.Definition<T> definitionOfAnyRefWithIsDefinedMethod();
    descriptor: ()Lorg/scalatest/enablers/Definition;
    flags: (0x0009) ACC_PUBLIC, ACC_STATIC
    Code:
      stack=1, locals=0, args_size=0
         0: getstatic     #18                 // Field org/scalatest/enablers/Definition$.MODULE$:Lorg/scalatest/enablers/Definition$;
         3: invokevirtual #23                 // Method org/scalatest/enablers/Definition$.definitionOfAnyRefWithIsDefinedMethod:()Lorg/scalatest/enablers/Definition;
         6: areturn
    Signature: #12                          // <T:Ljava/lang/Object;>()Lorg/scalatest/enablers/Definition<TT;>;

  public static <E extends java.lang.Object, OPT extends scala.Option<java.lang.Object>> org.scalatest.enablers.Definition<OPT> definitionOfOption();
    descriptor: ()Lorg/scalatest/enablers/Definition;
    flags: (0x0009) ACC_PUBLIC, ACC_STATIC
    Code:
      stack=1, locals=0, args_size=0
         0: getstatic     #18                 // Field org/scalatest/enablers/Definition$.MODULE$:Lorg/scalatest/enablers/Definition$;
         3: invokevirtual #27                 // Method org/scalatest/enablers/Definition$.definitionOfOption:()Lorg/scalatest/enablers/Definition;
         6: areturn
    Signature: #25                          // <E:Ljava/lang/Object;OPT:Lscala/Option<Ljava/lang/Object;>;>()Lorg/scalatest/enablers/Definition<TOPT;>;

  public abstract boolean isDefined(T);
    descriptor: (Ljava/lang/Object;)Z
    flags: (0x0401) ACC_PUBLIC, ACC_ABSTRACT
    Signature: #30                          // (TT;)Z
    MethodParameters:
      Name                           Flags
      thing                          final
}
Signature: #3                           // <T:Ljava/lang/Object;>Ljava/lang/Object;
SourceFile: "Definition.scala"
RuntimeVisibleAnnotations:
  0: #7(#8=s#9)
    scala.reflect.ScalaSignature(
      bytes="\u0006\u0005e3q\u0001C\u0005\u0011\u0002G\u0005\u0001\u0003C\u0003\u0019\u0001\u0019\u0005\u0011dB\u0003+\u0013!\u00051FB\u0003\t\u0013!\u0005Q\u0006C\u0003/\u0007\u0011\u0005q\u0006C\u00031\u0007\u0011\r\u0011\u0007C\u0003C\u0007\u0011\r1\tC\u0003O\u0007\u0011\rqJ\u0001\u0006EK\u001aLg.\u001b;j_:T!AC\u0006\u0002\u0011\u0015t\u0017M\u00197feNT!\u0001D\u0007\u0002\u0013M\u001c\u0017\r\\1uKN$(\"\u0001\b\u0002\u0007=\u0014xm\u0001\u0001\u0016\u0005E\t3C\u0001\u0001\u0013!\t\u0019b#D\u0001\u0015\u0015\u0005)\u0012!B:dC2\f\u0017BA\f\u0015\u0005\u0019\te.\u001f*fM\u0006I\u0011n\u001d#fM&tW\r\u001a\u000b\u00035u\u0001\"aE\u000e\n\u0005q!\"a\u0002\"p_2,\u0017M\u001c\u0005\u0006=\u0005\u0001\raH\u0001\u0006i\"Lgn\u001a\t\u0003A\u0005b\u0001\u0001\u0002\u0004#\u0001!\u0015\ra\t\u0002\u0002)F\u0011Ae\n\t\u0003\'\u0015J!A\n\u000b\u0003\u000f9{G\u000f[5oOB\u00111\u0003K\u0005\u0003SQ\u00111!\u00118z\u0003)!UMZ5oSRLwN\u001c\t\u0003Y\ri\u0011!C\n\u0003\u0007I\ta\u0001P5oSRtD#A\u0016\u0002%\u0011,g-\u001b8ji&|gn\u00144PaRLwN\\\u000b\u0004e\u0001+T#A\u001a\u0011\u00071\u0002A\u0007E\u0002!k}\"QAN\u0003C\u0002]\u00121a\u0014)U+\tAT(\u0005\u0002%sA\u00191C\u000f\u001f\n\u0005m\"\"AB(qi&|g\u000e\u0005\u0002!{\u0011)a(\u000eb\u0001G\t\tQ\r\u0005\u0002!\u0001\u0012)\u0011)\u0002b\u0001G\t\tQ)A\u0013eK\u001aLg.\u001b;j_:|e-\u00118z%\u00164w+\u001b;i\u0013N$UMZ5oK\u0012lU\r\u001e5pIV\u0011AiR\u000b\u0002\u000bB\u0019A\u0006\u0001$\u0011\u0005\u0001:E!\u0002\u0012\u0007\u0005\u0004A\u0015C\u0001\u0013J%\tQ%C\u0002\u0003L\u0007\u0001I%\u0001\u0004\u001fsK\u001aLg.Z7f]Rt\u0004\"\u0002\rK\r\u0003iE#\u0001\u000e\u0002e\u0011,g-\u001b8ji&|gn\u00144B]f\u0014VMZ,ji\"\u0004\u0016M]1nKR,\'\u000f\\3tg&\u001bH)\u001a4j]\u0016$W*\u001a;i_\u0012,\"\u0001U*\u0016\u0003E\u00032\u0001\f\u0001S!\t\u00013\u000bB\u0003#\u000f\t\u0007A+\u0005\u0002%+J\u0011aK\u0005\u0004\u0005\u0017\u000e\u0001Q\u000bC\u0003\u0019-\u001a\u0005\u0001,F\u0001\u001b\u0001"
    )
  ScalaInlineInfo: length = 0x9 (unknown attribute)
   01 00 00 01 00 1C 00 1D 00
  ScalaSig: length = 0x3 (unknown attribute)
   05 02 00
