Classfile /Users/mw/Projects/slang-braindump/.jar/jar8/assemble/slang-braindump/assemble/content/org/scalatest/enablers/ExpectationWheneverAsserting.class
  Last modified May 29, 2022; size 1382 bytes
  SHA-256 checksum fad1f94119737214fa9cb4b2aee0e1ec966b9dc70b1ca3beddeeb0d555f20735
  Compiled from "WheneverAsserting.scala"
public abstract class org.scalatest.enablers.ExpectationWheneverAsserting extends org.scalatest.enablers.UnitWheneverAsserting
  minor version: 0
  major version: 52
  flags: (0x0421) ACC_PUBLIC, ACC_SUPER, ACC_ABSTRACT
  this_class: #2                          // org/scalatest/enablers/ExpectationWheneverAsserting
  super_class: #4                         // org/scalatest/enablers/UnitWheneverAsserting
  interfaces: 0, fields: 0, methods: 2, attributes: 5
Constant pool:
   #1 = Utf8               org/scalatest/enablers/ExpectationWheneverAsserting
   #2 = Class              #1             // org/scalatest/enablers/ExpectationWheneverAsserting
   #3 = Utf8               org/scalatest/enablers/UnitWheneverAsserting
   #4 = Class              #3             // org/scalatest/enablers/UnitWheneverAsserting
   #5 = Utf8               WheneverAsserting.scala
   #6 = Utf8               Lscala/reflect/ScalaSignature;
   #7 = Utf8               bytes
   #8 = Utf8               \u0006\u0005M2Qa\u0001\u0003\u0002\u0002-AQ\u0001\u0005\u0001\u0005\u0002EAQa\u0005\u0001\u0005\u0004Q\u0011A$\u0012=qK\u000e$\u0018\r^5p]^CWM\\3wKJ\f5o]3si&twM\u0003\u0002\u0006\r\u0005AQM\\1cY\u0016\u00148O\u0003\u0002\b\u0011\u0005I1oY1mCR,7\u000f\u001e\u0006\u0002\u0013\u0005\u0019qN]4\u0004\u0001M\u0011\u0001\u0001\u0004\t\u0003\u001b9i\u0011\u0001B\u0005\u0003\u001f\u0011\u0011Q#\u00168ji^CWM\\3wKJ\f5o]3si&tw-\u0001\u0004=S:LGO\u0010\u000b\u0002%A\u0011Q\u0002A\u0001!CN\u001cXM\u001d;j]\u001et\u0015\r^;sK>3g)\u001e;ve\u0016\f5o]3si&|g.F\u0001\u0016%\t1\u0002D\u0002\u0003\u0018\u0001\u0001)\"\u0001\u0004\u001fsK\u001aLg.Z7f]Rt\u0004cA\u0007\u001a7%\u0011!\u0004\u0002\u0002\u0012/\",g.\u001a<fe\u0006\u001b8/\u001a:uS:<\u0007c\u0001\u000f\"G5\tQD\u0003\u0002\u001f?\u0005Q1m\u001c8dkJ\u0014XM\u001c;\u000b\u0003\u0001\nQa]2bY\u0006L!AI\u000f\u0003\r\u0019+H/\u001e:f!\t!cF\u0004\u0002&Y9\u0011ae\u000b\b\u0003O)j\u0011\u0001\u000b\u0006\u0003S)\ta\u0001\u0010:p_Rt\u0014\"A\u0005\n\u0005\u001dA\u0011BA\u0017\u0007\u0003\u001d\u0001\u0018mY6bO\u0016L!a\f\u0019\u0003\u0013\u0005\u001b8/\u001a:uS>t\'BA\u0017\u0007\u000b\u0011\u0011d\u0003I\u000e\u0003\rI+7/\u001e7u\u0001
   #9 = Utf8               org/scalatest/enablers/ExpectationWheneverAsserting$$anon$2
  #10 = Class              #9             // org/scalatest/enablers/ExpectationWheneverAsserting$$anon$2
  #11 = Utf8               assertingNatureOfFutureAssertion
  #12 = Utf8               ()Lorg/scalatest/enablers/WheneverAsserting;
  #13 = Utf8               ()Lorg/scalatest/enablers/WheneverAsserting<Lscala/concurrent/Future<Lorg/scalatest/compatible/Assertion;>;>;
  #14 = Utf8               <init>
  #15 = Utf8               (Lorg/scalatest/enablers/ExpectationWheneverAsserting;)V
  #16 = NameAndType        #14:#15        // "<init>":(Lorg/scalatest/enablers/ExpectationWheneverAsserting;)V
  #17 = Methodref          #10.#16        // org/scalatest/enablers/ExpectationWheneverAsserting$$anon$2."<init>":(Lorg/scalatest/enablers/ExpectationWheneverAsserting;)V
  #18 = Utf8               this
  #19 = Utf8               Lorg/scalatest/enablers/ExpectationWheneverAsserting;
  #20 = Utf8               ()V
  #21 = NameAndType        #14:#20        // "<init>":()V
  #22 = Methodref          #4.#21         // org/scalatest/enablers/UnitWheneverAsserting."<init>":()V
  #23 = Utf8               Code
  #24 = Utf8               LineNumberTable
  #25 = Utf8               LocalVariableTable
  #26 = Utf8               Signature
  #27 = Utf8               InnerClasses
  #28 = Utf8               SourceFile
  #29 = Utf8               RuntimeVisibleAnnotations
  #30 = Utf8               ScalaInlineInfo
  #31 = Utf8               ScalaSig
{
  public org.scalatest.enablers.WheneverAsserting<scala.concurrent.Future<org.scalatest.compatible.Assertion>> assertingNatureOfFutureAssertion();
    descriptor: ()Lorg/scalatest/enablers/WheneverAsserting;
    flags: (0x0001) ACC_PUBLIC
    Code:
      stack=3, locals=1, args_size=1
         0: new           #10                 // class org/scalatest/enablers/ExpectationWheneverAsserting$$anon$2
         3: dup
         4: aconst_null
         5: invokespecial #17                 // Method org/scalatest/enablers/ExpectationWheneverAsserting$$anon$2."<init>":(Lorg/scalatest/enablers/ExpectationWheneverAsserting;)V
         8: areturn
      LineNumberTable:
        line 85: 0
      LocalVariableTable:
        Start  Length  Slot  Name   Signature
            0       9     0  this   Lorg/scalatest/enablers/ExpectationWheneverAsserting;
    Signature: #13                          // ()Lorg/scalatest/enablers/WheneverAsserting<Lscala/concurrent/Future<Lorg/scalatest/compatible/Assertion;>;>;

  public org.scalatest.enablers.ExpectationWheneverAsserting();
    descriptor: ()V
    flags: (0x0001) ACC_PUBLIC
    Code:
      stack=1, locals=1, args_size=1
         0: aload_0
         1: invokespecial #22                 // Method org/scalatest/enablers/UnitWheneverAsserting."<init>":()V
         4: return
      LineNumberTable:
        line 73: 0
      LocalVariableTable:
        Start  Length  Slot  Name   Signature
            0       5     0  this   Lorg/scalatest/enablers/ExpectationWheneverAsserting;
}
InnerClasses:
  public final #10;                       // class org/scalatest/enablers/ExpectationWheneverAsserting$$anon$2
SourceFile: "WheneverAsserting.scala"
RuntimeVisibleAnnotations:
  0: #6(#7=s#8)
    scala.reflect.ScalaSignature(
      bytes="\u0006\u0005M2Qa\u0001\u0003\u0002\u0002-AQ\u0001\u0005\u0001\u0005\u0002EAQa\u0005\u0001\u0005\u0004Q\u0011A$\u0012=qK\u000e$\u0018\r^5p]^CWM\\3wKJ\f5o]3si&twM\u0003\u0002\u0006\r\u0005AQM\\1cY\u0016\u00148O\u0003\u0002\b\u0011\u0005I1oY1mCR,7\u000f\u001e\u0006\u0002\u0013\u0005\u0019qN]4\u0004\u0001M\u0011\u0001\u0001\u0004\t\u0003\u001b9i\u0011\u0001B\u0005\u0003\u001f\u0011\u0011Q#\u00168ji^CWM\\3wKJ\f5o]3si&tw-\u0001\u0004=S:LGO\u0010\u000b\u0002%A\u0011Q\u0002A\u0001!CN\u001cXM\u001d;j]\u001et\u0015\r^;sK>3g)\u001e;ve\u0016\f5o]3si&|g.F\u0001\u0016%\t1\u0002D\u0002\u0003\u0018\u0001\u0001)\"\u0001\u0004\u001fsK\u001aLg.Z7f]Rt\u0004cA\u0007\u001a7%\u0011!\u0004\u0002\u0002\u0012/\",g.\u001a<fe\u0006\u001b8/\u001a:uS:<\u0007c\u0001\u000f\"G5\tQD\u0003\u0002\u001f?\u0005Q1m\u001c8dkJ\u0014XM\u001c;\u000b\u0003\u0001\nQa]2bY\u0006L!AI\u000f\u0003\r\u0019+H/\u001e:f!\t!cF\u0004\u0002&Y9\u0011ae\u000b\b\u0003O)j\u0011\u0001\u000b\u0006\u0003S)\ta\u0001\u0010:p_Rt\u0014\"A\u0005\n\u0005\u001dA\u0011BA\u0017\u0007\u0003\u001d\u0001\u0018mY6bO\u0016L!a\f\u0019\u0003\u0013\u0005\u001b8/\u001a:uS>t\'BA\u0017\u0007\u000b\u0011\u0011d\u0003I\u000e\u0003\rI+7/\u001e7u\u0001"
    )
  ScalaInlineInfo: length = 0xE (unknown attribute)
   01 00 00 02 00 0E 00 14 00 00 0B 00 0C 00
  ScalaSig: length = 0x3 (unknown attribute)
   05 02 00
