Classfile /Users/mw/Projects/slang-braindump/.jar/jar8/assemble/slang-braindump/assemble/content/org/scalatest/enablers/ExpectationWheneverAsserting$$anon$2.class
  Last modified May 29, 2022; size 1691 bytes
  SHA-256 checksum 186bdec6bc5a2360e83cd7e76f3329386fa58b64ced1b1667f3d1a2021d8badc
  Compiled from "WheneverAsserting.scala"
public final class org.scalatest.enablers.ExpectationWheneverAsserting$$anon$2 extends java.lang.Object implements org.scalatest.enablers.WheneverAsserting<scala.concurrent.Future<org.scalatest.compatible.Assertion>>
  minor version: 0
  major version: 52
  flags: (0x0031) ACC_PUBLIC, ACC_FINAL, ACC_SUPER
  this_class: #2                          // org/scalatest/enablers/ExpectationWheneverAsserting$$anon$2
  super_class: #5                         // java/lang/Object
  interfaces: 1, fields: 0, methods: 3, attributes: 6
Constant pool:
   #1 = Utf8               org/scalatest/enablers/ExpectationWheneverAsserting$$anon$2
   #2 = Class              #1             // org/scalatest/enablers/ExpectationWheneverAsserting$$anon$2
   #3 = Utf8               Ljava/lang/Object;Lorg/scalatest/enablers/WheneverAsserting<Lscala/concurrent/Future<Lorg/scalatest/compatible/Assertion;>;>;
   #4 = Utf8               java/lang/Object
   #5 = Class              #4             // java/lang/Object
   #6 = Utf8               org/scalatest/enablers/WheneverAsserting
   #7 = Class              #6             // org/scalatest/enablers/WheneverAsserting
   #8 = Utf8               WheneverAsserting.scala
   #9 = Utf8               org/scalatest/enablers/ExpectationWheneverAsserting
  #10 = Class              #9             // org/scalatest/enablers/ExpectationWheneverAsserting
  #11 = Utf8               assertingNatureOfFutureAssertion
  #12 = Utf8               ()Lorg/scalatest/enablers/WheneverAsserting;
  #13 = NameAndType        #11:#12        // assertingNatureOfFutureAssertion:()Lorg/scalatest/enablers/WheneverAsserting;
  #14 = Utf8               whenever
  #15 = Utf8               (ZLscala/Function0;)Lscala/concurrent/Future;
  #16 = Utf8               (ZLscala/Function0<Lscala/concurrent/Future<Lorg/scalatest/compatible/Assertion;>;>;)Lscala/concurrent/Future<Lorg/scalatest/compatible/Assertion;>;
  #17 = Utf8               condition
  #18 = Utf8               fun
  #19 = Utf8               org/scalatest/exceptions/DiscardedEvaluationException
  #20 = Class              #19            // org/scalatest/exceptions/DiscardedEvaluationException
  #21 = Utf8               <init>
  #22 = Utf8               ()V
  #23 = NameAndType        #21:#22        // "<init>":()V
  #24 = Methodref          #20.#23        // org/scalatest/exceptions/DiscardedEvaluationException."<init>":()V
  #25 = Utf8               scala/Function0
  #26 = Class              #25            // scala/Function0
  #27 = Utf8               apply
  #28 = Utf8               ()Ljava/lang/Object;
  #29 = NameAndType        #27:#28        // apply:()Ljava/lang/Object;
  #30 = InterfaceMethodref #26.#29        // scala/Function0.apply:()Ljava/lang/Object;
  #31 = Utf8               scala/concurrent/Future
  #32 = Class              #31            // scala/concurrent/Future
  #33 = Utf8               this
  #34 = Utf8               Lorg/scalatest/enablers/ExpectationWheneverAsserting$$anon$2;
  #35 = Utf8               Z
  #36 = Utf8               Lscala/Function0;
  #37 = Utf8               (ZLscala/Function0;)Ljava/lang/Object;
  #38 = NameAndType        #14:#15        // whenever:(ZLscala/Function0;)Lscala/concurrent/Future;
  #39 = Methodref          #2.#38         // org/scalatest/enablers/ExpectationWheneverAsserting$$anon$2.whenever:(ZLscala/Function0;)Lscala/concurrent/Future;
  #40 = Utf8               (Lorg/scalatest/enablers/ExpectationWheneverAsserting;)V
  #41 = Utf8               $outer
  #42 = Methodref          #5.#23         // java/lang/Object."<init>":()V
  #43 = Utf8               Lorg/scalatest/enablers/ExpectationWheneverAsserting;
  #44 = Utf8               Code
  #45 = Utf8               StackMapTable
  #46 = Utf8               LineNumberTable
  #47 = Utf8               LocalVariableTable
  #48 = Utf8               Signature
  #49 = Utf8               MethodParameters
  #50 = Utf8               InnerClasses
  #51 = Utf8               EnclosingMethod
  #52 = Utf8               SourceFile
  #53 = Utf8               ScalaInlineInfo
  #54 = Utf8               Scala
{
  public scala.concurrent.Future<org.scalatest.compatible.Assertion> whenever(boolean, scala.Function0<scala.concurrent.Future<org.scalatest.compatible.Assertion>>);
    descriptor: (ZLscala/Function0;)Lscala/concurrent/Future;
    flags: (0x0001) ACC_PUBLIC
    Code:
      stack=2, locals=3, args_size=3
         0: iload_1
         1: ifne          12
         4: new           #20                 // class org/scalatest/exceptions/DiscardedEvaluationException
         7: dup
         8: invokespecial #24                 // Method org/scalatest/exceptions/DiscardedEvaluationException."<init>":()V
        11: athrow
        12: aload_2
        13: invokeinterface #30,  1           // InterfaceMethod scala/Function0.apply:()Ljava/lang/Object;
        18: checkcast     #32                 // class scala/concurrent/Future
        21: areturn
      StackMapTable: number_of_entries = 1
        frame_type = 12 /* same */
      LineNumberTable:
        line 88: 0
        line 89: 4
        line 91: 12
      LocalVariableTable:
        Start  Length  Slot  Name   Signature
            0      22     0  this   Lorg/scalatest/enablers/ExpectationWheneverAsserting$$anon$2;
            0      22     1 condition   Z
            0      22     2   fun   Lscala/Function0;
    Signature: #16                          // (ZLscala/Function0<Lscala/concurrent/Future<Lorg/scalatest/compatible/Assertion;>;>;)Lscala/concurrent/Future<Lorg/scalatest/compatible/Assertion;>;
    MethodParameters:
      Name                           Flags
      condition                      final
      fun                            final

  public java.lang.Object whenever(boolean, scala.Function0);
    descriptor: (ZLscala/Function0;)Ljava/lang/Object;
    flags: (0x1041) ACC_PUBLIC, ACC_BRIDGE, ACC_SYNTHETIC
    Code:
      stack=3, locals=3, args_size=3
         0: aload_0
         1: iload_1
         2: aload_2
         3: invokevirtual #39                 // Method whenever:(ZLscala/Function0;)Lscala/concurrent/Future;
         6: areturn
      LineNumberTable:
        line 85: 0
      LocalVariableTable:
        Start  Length  Slot  Name   Signature
            0       7     0  this   Lorg/scalatest/enablers/ExpectationWheneverAsserting$$anon$2;
            0       7     1 condition   Z
            0       7     2   fun   Lscala/Function0;
    MethodParameters:
      Name                           Flags
      condition                      final
      fun                            final

  public org.scalatest.enablers.ExpectationWheneverAsserting$$anon$2(org.scalatest.enablers.ExpectationWheneverAsserting);
    descriptor: (Lorg/scalatest/enablers/ExpectationWheneverAsserting;)V
    flags: (0x0001) ACC_PUBLIC
    Code:
      stack=1, locals=2, args_size=2
         0: aload_0
         1: invokespecial #42                 // Method java/lang/Object."<init>":()V
         4: return
      LineNumberTable:
        line 85: 0
      LocalVariableTable:
        Start  Length  Slot  Name   Signature
            0       5     0  this   Lorg/scalatest/enablers/ExpectationWheneverAsserting$$anon$2;
            0       5     1 $outer   Lorg/scalatest/enablers/ExpectationWheneverAsserting;
    MethodParameters:
      Name                           Flags
      $outer                         final synthetic
}
InnerClasses:
  public final #2;                        // class org/scalatest/enablers/ExpectationWheneverAsserting$$anon$2
EnclosingMethod: #10.#13                // org.scalatest.enablers.ExpectationWheneverAsserting.assertingNatureOfFutureAssertion
Signature: #3                           // Ljava/lang/Object;Lorg/scalatest/enablers/WheneverAsserting<Lscala/concurrent/Future<Lorg/scalatest/compatible/Assertion;>;>;
SourceFile: "WheneverAsserting.scala"
  ScalaInlineInfo: length = 0x13 (unknown attribute)
   01 01 00 03 00 15 00 28 01 00 0E 00 25 01 00 0E
   00 0F 01
  Scala: length = 0x0 (unknown attribute)

