Classfile /Users/mw/Projects/slang-braindump/.jar/jar8/assemble/slang-braindump/assemble/content/org/scalatest/enablers/Length.class
  Last modified May 29, 2022; size 3846 bytes
  SHA-256 checksum a82e1a82a4a07512c586b257478365b78ece96843745ac3ec7bc919fd4fec4a5
  Compiled from "Length.scala"
public interface org.scalatest.enablers.Length<T extends java.lang.Object>
  minor version: 0
  major version: 52
  flags: (0x0601) ACC_PUBLIC, ACC_INTERFACE, ACC_ABSTRACT
  this_class: #2                          // org/scalatest/enablers/Length
  super_class: #5                         // java/lang/Object
  interfaces: 0, fields: 0, methods: 13, attributes: 5
Constant pool:
   #1 = Utf8               org/scalatest/enablers/Length
   #2 = Class              #1             // org/scalatest/enablers/Length
   #3 = Utf8               <T:Ljava/lang/Object;>Ljava/lang/Object;
   #4 = Utf8               java/lang/Object
   #5 = Class              #4             // java/lang/Object
   #6 = Utf8               Length.scala
   #7 = Utf8               Lscala/reflect/ScalaSignature;
   #8 = Utf8               bytes
   #9 = Utf8               \u0006\u0005\u0005Ufa\u0002\n\u0014!\u0003\r\nA\u0007\u0005\u0006E\u00011\taI\u0004\u0006iMA\t!\u000e\u0004\u0006%MA\ta\u000e\u0005\u0006q\r!\t!\u000f\u0005\u0006u\r!\u0019a\u000f\u0005\u0006\u001d\u000e!\u0019a\u0014\u0005\u0006U\u000e!\u0019a\u001b\u0005\bi\u000e\u0011\r\u0011b\u0001v\u0011\u0019y8\u0001)A\u0005m\"9\u0011\u0011A\u0002\u0005\u0004\u0005\r\u0001bBA\u0011\u0007\u0011\r\u00111\u0005\u0005\b\u0003o\u0019A1AA\u001d\u0011\u001d\tie\u0001C\u0002\u0003\u001fBq!!\u0019\u0004\t\u0007\t\u0019\u0007C\u0004\u0002x\r!\u0019!!\u001f\t\u000f\u000555\u0001b\u0001\u0002\u0010\"9\u0011\u0011U\u0002\u0005\u0004\u0005\r&A\u0002\'f]\u001e$\bN\u0003\u0002\u0015+\u0005AQM\\1cY\u0016\u00148O\u0003\u0002\u0017/\u0005I1oY1mCR,7\u000f\u001e\u0006\u00021\u0005\u0019qN]4\u0004\u0001U\u00111dK\n\u0003\u0001q\u0001\"!\b\u0011\u000e\u0003yQ\u0011aH\u0001\u0006g\u000e\fG.Y\u0005\u0003Cy\u0011a!\u00118z%\u00164\u0017\u0001\u00037f]\u001e$\bn\u00144\u0015\u0005\u0011:\u0003CA\u000f&\u0013\t1cD\u0001\u0003M_:<\u0007\"\u0002\u0015\u0002\u0001\u0004I\u0013aA8cUB\u0011!f\u000b\u0007\u0001\t\u0015a\u0003A1\u0001.\u0005\u0005!\u0016C\u0001\u00182!\tir&\u0003\u00021=\t9aj\u001c;iS:<\u0007CA\u000f3\u0013\t\u0019dDA\u0002B]f\fa\u0001T3oORD\u0007C\u0001\u001c\u0004\u001b\u0005\u00192CA\u0002\u001d\u0003\u0019a\u0014N\\5u}Q\tQ\'\u0001\tmK:<G\u000f[(g\u0015\u00064\u0018\rT5tiV\u0011AhP\u000b\u0002{A\u0019a\u0007\u0001 \u0011\u0005)zD!\u0002!\u0006\u0005\u0004\t%!\u0002&M\u0013N#\u0016C\u0001\u0018Ca\t\u0019E\nE\u0002E\u0013.k\u0011!\u0012\u0006\u0003\r\u001e\u000bA!\u001e;jY*\t\u0001*\u0001\u0003kCZ\f\u0017B\u0001&F\u0005\u0011a\u0015n\u001d;\u0011\u0005)bE!C\'@\u0003\u0003\u0005\tQ!\u0001.\u0005\ryF%M\u0001\u000fY\u0016tw\r\u001e5PM\u001e+gnU3r+\t\u00016+F\u0001R!\r1\u0004A\u0015\t\u0003UM#Q\u0001\u0016\u0004C\u0002U\u00131aU#R#\tqc\u000b\r\u0002XQB\u0019\u0001\fZ4\u000f\u0005e\u000bgB\u0001.`\u001d\tYf,D\u0001]\u0015\ti\u0016$\u0001\u0004=e>|GOP\u0005\u0002?%\u0011\u0001MH\u0001\u000bG>dG.Z2uS>t\u0017B\u00012d\u0003\u001d\u0001\u0018mY6bO\u0016T!\u0001\u0019\u0010\n\u0005\u00154\'AB$f]N+\u0017O\u0003\u0002cGB\u0011!\u0006\u001b\u0003\nSN\u000b\t\u0011!A\u0003\u00025\u00121a\u0018\u00133\u00035aWM\\4uQ>3\u0017I\u001d:bsV\u0011AN]\u000b\u0002[B\u0019a\u0007\u00018\u0011\u0007uy\u0017/\u0003\u0002q=\t)\u0011I\u001d:bsB\u0011!F\u001d\u0003\u0006g\u001e\u0011\r!\f\u0002\u0002\u000b\u0006qA.\u001a8hi\"|em\u0015;sS:<W#\u0001<\u0011\u0007Y\u0002q\u000f\u0005\u0002yy:\u0011\u0011P\u001f\t\u00037zI!a\u001f\u0010\u0002\rA\u0013X\rZ3g\u0013\tihP\u0001\u0004TiJLgn\u001a\u0006\u0003wz\tq\u0002\\3oORDwJZ*ue&tw\rI\u0001%Y\u0016tw\r\u001e5PM\u0006s\u0017PU3g/&$\b\u000eT3oORDW*\u001a;i_\u00124uN]%oiV!\u0011QAA\u0006+\t\t9\u0001\u0005\u00037\u0001\u0005%\u0001c\u0001\u0016\u0002\f\u00111AF\u0003b\u0001\u0003\u001b\t2ALA\b%\r\t\t\u0002\b\u0004\u0007\u0003\'\u0019\u0001!a\u0004\u0003\u0019q\u0012XMZ5oK6,g\u000e\u001e \t\u0011\u0005]\u0011\u0011\u0003D\u0001\u00033\ta\u0001\\3oORDGCAA\u000e!\ri\u0012QD\u0005\u0004\u0003?q\"aA%oi\u0006\tD.\u001a8hi\"|e-\u00118z%\u00164w+\u001b;i!\u0006\u0014\u0018-\\3uKJdWm]:MK:<G\u000f[\'fi\"|GMR8s\u0013:$X\u0003BA\u0013\u0003W)\"!a\n\u0011\tY\u0002\u0011\u0011\u0006\t\u0004U\u0005-BA\u0002\u0017\f\u0005\u0004\ti#E\u0002/\u0003_\u00112!!\r\u001d\r\u0019\t\u0019b\u0001\u0001\u00020!A\u0011qCA\u0019\r\u0003\t)$\u0006\u0002\u0002\u001c\u00059C.\u001a8hi\"|e-\u00118z%\u00164w+\u001b;i\u000f\u0016$H*\u001a8hi\"lU\r\u001e5pI\u001a{\'/\u00138u+\u0011\tY$!\u0011\u0016\u0005\u0005u\u0002\u0003\u0002\u001c\u0001\u0003\u007f\u00012AKA!\t\u0019aCB1\u0001\u0002DE\u0019a&!\u0012\u0013\u0007\u0005\u001dCD\u0002\u0004\u0002\u0014\r\u0001\u0011Q\t\u0005\t\u0003\u0017\n9E\"\u0001\u0002\u001a\u0005Iq-\u001a;MK:<G\u000f[\u00015Y\u0016tw\r\u001e5PM\u0006s\u0017PU3g/&$\b\u000eU1sC6,G/\u001a:mKN\u001cx)\u001a;MK:<G\u000f[\'fi\"|GMR8s\u0013:$X\u0003BA)\u0003/*\"!a\u0015\u0011\tY\u0002\u0011Q\u000b\t\u0004U\u0005]CA\u0002\u0017\u000e\u0005\u0004\tI&E\u0002/\u00037\u00122!!\u0018\u001d\r\u0019\t\u0019b\u0001\u0001\u0002\\!A\u00111JA/\r\u0003\t)$A\u0013mK:<G\u000f[(g\u0003:L(+\u001a4XSRDG*\u001a8hi\"lU\r\u001e5pI\u001a{\'\u000fT8oOV!\u0011QMA6+\t\t9\u0007\u0005\u00037\u0001\u0005%\u0004c\u0001\u0016\u0002l\u00111AF\u0004b\u0001\u0003[\n2ALA8%\r\t\t\b\b\u0004\u0007\u0003\'\u0019\u0001!a\u001c\t\u0011\u0005]\u0011\u0011\u000fD\u0001\u0003k\"\u0012\u0001J\u00013Y\u0016tw\r\u001e5PM\u0006s\u0017PU3g/&$\b\u000eU1sC6,G/\u001a:mKN\u001cH*\u001a8hi\"lU\r\u001e5pI\u001a{\'\u000fT8oOV!\u00111PAA+\t\ti\b\u0005\u00037\u0001\u0005}\u0004c\u0001\u0016\u0002\u0002\u00121Af\u0004b\u0001\u0003\u0007\u000b2ALAC%\r\t9\t\b\u0004\u0007\u0003\'\u0019\u0001!!\"\t\u0011\u0005]\u0011q\u0011D\u0001\u0003\u0017+\u0012\u0001J\u0001)Y\u0016tw\r\u001e5PM\u0006s\u0017PU3g/&$\bnR3u\u0019\u0016tw\r\u001e5NKRDw\u000e\u001a$pe2{gnZ\u000b\u0005\u0003#\u000b9*\u0006\u0002\u0002\u0014B!a\u0007AAK!\rQ\u0013q\u0013\u0003\u0007YA\u0011\r!!\'\u0012\u00079\nYJE\u0002\u0002\u001er1a!a\u0005\u0004\u0001\u0005m\u0005\u0002CA&\u0003;3\t!!\u001e\u0002k1,gn\u001a;i\u001f\u001a\fe.\u001f*fM^KG\u000f\u001b)be\u0006lW\r^3sY\u0016\u001c8oR3u\u0019\u0016tw\r\u001e5NKRDw\u000e\u001a$pe2{gnZ\u000b\u0005\u0003K\u000bY+\u0006\u0002\u0002(B!a\u0007AAU!\rQ\u00131\u0016\u0003\u0007YE\u0011\r!!,\u0012\u00079\nyKE\u0002\u00022r1a!a\u0005\u0004\u0001\u0005=\u0006\u0002CA&\u0003c3\t!a#
  #10 = Utf8               lengthOfAnyRefWithParameterlessGetLengthMethodForLong
  #11 = Utf8               ()Lorg/scalatest/enablers/Length;
  #12 = Utf8               <T:Ljava/lang/Object;>()Lorg/scalatest/enablers/Length<TT;>;
  #13 = Utf8               org/scalatest/enablers/Length$
  #14 = Class              #13            // org/scalatest/enablers/Length$
  #15 = Utf8               MODULE$
  #16 = Utf8               Lorg/scalatest/enablers/Length$;
  #17 = NameAndType        #15:#16        // MODULE$:Lorg/scalatest/enablers/Length$;
  #18 = Fieldref           #14.#17        // org/scalatest/enablers/Length$.MODULE$:Lorg/scalatest/enablers/Length$;
  #19 = NameAndType        #10:#11        // lengthOfAnyRefWithParameterlessGetLengthMethodForLong:()Lorg/scalatest/enablers/Length;
  #20 = Methodref          #14.#19        // org/scalatest/enablers/Length$.lengthOfAnyRefWithParameterlessGetLengthMethodForLong:()Lorg/scalatest/enablers/Length;
  #21 = Utf8               lengthOfAnyRefWithGetLengthMethodForLong
  #22 = NameAndType        #21:#11        // lengthOfAnyRefWithGetLengthMethodForLong:()Lorg/scalatest/enablers/Length;
  #23 = Methodref          #14.#22        // org/scalatest/enablers/Length$.lengthOfAnyRefWithGetLengthMethodForLong:()Lorg/scalatest/enablers/Length;
  #24 = Utf8               lengthOfAnyRefWithParameterlessLengthMethodForLong
  #25 = NameAndType        #24:#11        // lengthOfAnyRefWithParameterlessLengthMethodForLong:()Lorg/scalatest/enablers/Length;
  #26 = Methodref          #14.#25        // org/scalatest/enablers/Length$.lengthOfAnyRefWithParameterlessLengthMethodForLong:()Lorg/scalatest/enablers/Length;
  #27 = Utf8               lengthOfAnyRefWithLengthMethodForLong
  #28 = NameAndType        #27:#11        // lengthOfAnyRefWithLengthMethodForLong:()Lorg/scalatest/enablers/Length;
  #29 = Methodref          #14.#28        // org/scalatest/enablers/Length$.lengthOfAnyRefWithLengthMethodForLong:()Lorg/scalatest/enablers/Length;
  #30 = Utf8               lengthOfAnyRefWithParameterlessGetLengthMethodForInt
  #31 = NameAndType        #30:#11        // lengthOfAnyRefWithParameterlessGetLengthMethodForInt:()Lorg/scalatest/enablers/Length;
  #32 = Methodref          #14.#31        // org/scalatest/enablers/Length$.lengthOfAnyRefWithParameterlessGetLengthMethodForInt:()Lorg/scalatest/enablers/Length;
  #33 = Utf8               lengthOfAnyRefWithGetLengthMethodForInt
  #34 = NameAndType        #33:#11        // lengthOfAnyRefWithGetLengthMethodForInt:()Lorg/scalatest/enablers/Length;
  #35 = Methodref          #14.#34        // org/scalatest/enablers/Length$.lengthOfAnyRefWithGetLengthMethodForInt:()Lorg/scalatest/enablers/Length;
  #36 = Utf8               lengthOfAnyRefWithParameterlessLengthMethodForInt
  #37 = NameAndType        #36:#11        // lengthOfAnyRefWithParameterlessLengthMethodForInt:()Lorg/scalatest/enablers/Length;
  #38 = Methodref          #14.#37        // org/scalatest/enablers/Length$.lengthOfAnyRefWithParameterlessLengthMethodForInt:()Lorg/scalatest/enablers/Length;
  #39 = Utf8               lengthOfAnyRefWithLengthMethodForInt
  #40 = NameAndType        #39:#11        // lengthOfAnyRefWithLengthMethodForInt:()Lorg/scalatest/enablers/Length;
  #41 = Methodref          #14.#40        // org/scalatest/enablers/Length$.lengthOfAnyRefWithLengthMethodForInt:()Lorg/scalatest/enablers/Length;
  #42 = Utf8               lengthOfString
  #43 = Utf8               ()Lorg/scalatest/enablers/Length<Ljava/lang/String;>;
  #44 = NameAndType        #42:#11        // lengthOfString:()Lorg/scalatest/enablers/Length;
  #45 = Methodref          #14.#44        // org/scalatest/enablers/Length$.lengthOfString:()Lorg/scalatest/enablers/Length;
  #46 = Utf8               lengthOfArray
  #47 = Utf8               <E:Ljava/lang/Object;>()Lorg/scalatest/enablers/Length<Ljava/lang/Object;>;
  #48 = NameAndType        #46:#11        // lengthOfArray:()Lorg/scalatest/enablers/Length;
  #49 = Methodref          #14.#48        // org/scalatest/enablers/Length$.lengthOfArray:()Lorg/scalatest/enablers/Length;
  #50 = Utf8               lengthOfGenSeq
  #51 = Utf8               <SEQ::Lscala/collection/Seq<*>;>()Lorg/scalatest/enablers/Length<TSEQ;>;
  #52 = NameAndType        #50:#11        // lengthOfGenSeq:()Lorg/scalatest/enablers/Length;
  #53 = Methodref          #14.#52        // org/scalatest/enablers/Length$.lengthOfGenSeq:()Lorg/scalatest/enablers/Length;
  #54 = Utf8               lengthOfJavaList
  #55 = Utf8               <JLIST::Ljava/util/List<*>;>()Lorg/scalatest/enablers/Length<TJLIST;>;
  #56 = NameAndType        #54:#11        // lengthOfJavaList:()Lorg/scalatest/enablers/Length;
  #57 = Methodref          #14.#56        // org/scalatest/enablers/Length$.lengthOfJavaList:()Lorg/scalatest/enablers/Length;
  #58 = Utf8               lengthOf
  #59 = Utf8               (Ljava/lang/Object;)J
  #60 = Utf8               (TT;)J
  #61 = Utf8               obj
  #62 = Utf8               Code
  #63 = Utf8               Signature
  #64 = Utf8               MethodParameters
  #65 = Utf8               SourceFile
  #66 = Utf8               RuntimeVisibleAnnotations
  #67 = Utf8               ScalaInlineInfo
  #68 = Utf8               ScalaSig
{
  public static <T extends java.lang.Object> org.scalatest.enablers.Length<T> lengthOfAnyRefWithParameterlessGetLengthMethodForLong();
    descriptor: ()Lorg/scalatest/enablers/Length;
    flags: (0x0009) ACC_PUBLIC, ACC_STATIC
    Code:
      stack=1, locals=0, args_size=0
         0: getstatic     #18                 // Field org/scalatest/enablers/Length$.MODULE$:Lorg/scalatest/enablers/Length$;
         3: invokevirtual #20                 // Method org/scalatest/enablers/Length$.lengthOfAnyRefWithParameterlessGetLengthMethodForLong:()Lorg/scalatest/enablers/Length;
         6: areturn
    Signature: #12                          // <T:Ljava/lang/Object;>()Lorg/scalatest/enablers/Length<TT;>;

  public static <T extends java.lang.Object> org.scalatest.enablers.Length<T> lengthOfAnyRefWithGetLengthMethodForLong();
    descriptor: ()Lorg/scalatest/enablers/Length;
    flags: (0x0009) ACC_PUBLIC, ACC_STATIC
    Code:
      stack=1, locals=0, args_size=0
         0: getstatic     #18                 // Field org/scalatest/enablers/Length$.MODULE$:Lorg/scalatest/enablers/Length$;
         3: invokevirtual #23                 // Method org/scalatest/enablers/Length$.lengthOfAnyRefWithGetLengthMethodForLong:()Lorg/scalatest/enablers/Length;
         6: areturn
    Signature: #12                          // <T:Ljava/lang/Object;>()Lorg/scalatest/enablers/Length<TT;>;

  public static <T extends java.lang.Object> org.scalatest.enablers.Length<T> lengthOfAnyRefWithParameterlessLengthMethodForLong();
    descriptor: ()Lorg/scalatest/enablers/Length;
    flags: (0x0009) ACC_PUBLIC, ACC_STATIC
    Code:
      stack=1, locals=0, args_size=0
         0: getstatic     #18                 // Field org/scalatest/enablers/Length$.MODULE$:Lorg/scalatest/enablers/Length$;
         3: invokevirtual #26                 // Method org/scalatest/enablers/Length$.lengthOfAnyRefWithParameterlessLengthMethodForLong:()Lorg/scalatest/enablers/Length;
         6: areturn
    Signature: #12                          // <T:Ljava/lang/Object;>()Lorg/scalatest/enablers/Length<TT;>;

  public static <T extends java.lang.Object> org.scalatest.enablers.Length<T> lengthOfAnyRefWithLengthMethodForLong();
    descriptor: ()Lorg/scalatest/enablers/Length;
    flags: (0x0009) ACC_PUBLIC, ACC_STATIC
    Code:
      stack=1, locals=0, args_size=0
         0: getstatic     #18                 // Field org/scalatest/enablers/Length$.MODULE$:Lorg/scalatest/enablers/Length$;
         3: invokevirtual #29                 // Method org/scalatest/enablers/Length$.lengthOfAnyRefWithLengthMethodForLong:()Lorg/scalatest/enablers/Length;
         6: areturn
    Signature: #12                          // <T:Ljava/lang/Object;>()Lorg/scalatest/enablers/Length<TT;>;

  public static <T extends java.lang.Object> org.scalatest.enablers.Length<T> lengthOfAnyRefWithParameterlessGetLengthMethodForInt();
    descriptor: ()Lorg/scalatest/enablers/Length;
    flags: (0x0009) ACC_PUBLIC, ACC_STATIC
    Code:
      stack=1, locals=0, args_size=0
         0: getstatic     #18                 // Field org/scalatest/enablers/Length$.MODULE$:Lorg/scalatest/enablers/Length$;
         3: invokevirtual #32                 // Method org/scalatest/enablers/Length$.lengthOfAnyRefWithParameterlessGetLengthMethodForInt:()Lorg/scalatest/enablers/Length;
         6: areturn
    Signature: #12                          // <T:Ljava/lang/Object;>()Lorg/scalatest/enablers/Length<TT;>;

  public static <T extends java.lang.Object> org.scalatest.enablers.Length<T> lengthOfAnyRefWithGetLengthMethodForInt();
    descriptor: ()Lorg/scalatest/enablers/Length;
    flags: (0x0009) ACC_PUBLIC, ACC_STATIC
    Code:
      stack=1, locals=0, args_size=0
         0: getstatic     #18                 // Field org/scalatest/enablers/Length$.MODULE$:Lorg/scalatest/enablers/Length$;
         3: invokevirtual #35                 // Method org/scalatest/enablers/Length$.lengthOfAnyRefWithGetLengthMethodForInt:()Lorg/scalatest/enablers/Length;
         6: areturn
    Signature: #12                          // <T:Ljava/lang/Object;>()Lorg/scalatest/enablers/Length<TT;>;

  public static <T extends java.lang.Object> org.scalatest.enablers.Length<T> lengthOfAnyRefWithParameterlessLengthMethodForInt();
    descriptor: ()Lorg/scalatest/enablers/Length;
    flags: (0x0009) ACC_PUBLIC, ACC_STATIC
    Code:
      stack=1, locals=0, args_size=0
         0: getstatic     #18                 // Field org/scalatest/enablers/Length$.MODULE$:Lorg/scalatest/enablers/Length$;
         3: invokevirtual #38                 // Method org/scalatest/enablers/Length$.lengthOfAnyRefWithParameterlessLengthMethodForInt:()Lorg/scalatest/enablers/Length;
         6: areturn
    Signature: #12                          // <T:Ljava/lang/Object;>()Lorg/scalatest/enablers/Length<TT;>;

  public static <T extends java.lang.Object> org.scalatest.enablers.Length<T> lengthOfAnyRefWithLengthMethodForInt();
    descriptor: ()Lorg/scalatest/enablers/Length;
    flags: (0x0009) ACC_PUBLIC, ACC_STATIC
    Code:
      stack=1, locals=0, args_size=0
         0: getstatic     #18                 // Field org/scalatest/enablers/Length$.MODULE$:Lorg/scalatest/enablers/Length$;
         3: invokevirtual #41                 // Method org/scalatest/enablers/Length$.lengthOfAnyRefWithLengthMethodForInt:()Lorg/scalatest/enablers/Length;
         6: areturn
    Signature: #12                          // <T:Ljava/lang/Object;>()Lorg/scalatest/enablers/Length<TT;>;

  public static org.scalatest.enablers.Length<java.lang.String> lengthOfString();
    descriptor: ()Lorg/scalatest/enablers/Length;
    flags: (0x0009) ACC_PUBLIC, ACC_STATIC
    Code:
      stack=1, locals=0, args_size=0
         0: getstatic     #18                 // Field org/scalatest/enablers/Length$.MODULE$:Lorg/scalatest/enablers/Length$;
         3: invokevirtual #45                 // Method org/scalatest/enablers/Length$.lengthOfString:()Lorg/scalatest/enablers/Length;
         6: areturn
    Signature: #43                          // ()Lorg/scalatest/enablers/Length<Ljava/lang/String;>;

  public static <E extends java.lang.Object> org.scalatest.enablers.Length<java.lang.Object> lengthOfArray();
    descriptor: ()Lorg/scalatest/enablers/Length;
    flags: (0x0009) ACC_PUBLIC, ACC_STATIC
    Code:
      stack=1, locals=0, args_size=0
         0: getstatic     #18                 // Field org/scalatest/enablers/Length$.MODULE$:Lorg/scalatest/enablers/Length$;
         3: invokevirtual #49                 // Method org/scalatest/enablers/Length$.lengthOfArray:()Lorg/scalatest/enablers/Length;
         6: areturn
    Signature: #47                          // <E:Ljava/lang/Object;>()Lorg/scalatest/enablers/Length<Ljava/lang/Object;>;

  public static <SEQ extends scala.collection.Seq<?>> org.scalatest.enablers.Length<SEQ> lengthOfGenSeq();
    descriptor: ()Lorg/scalatest/enablers/Length;
    flags: (0x0009) ACC_PUBLIC, ACC_STATIC
    Code:
      stack=1, locals=0, args_size=0
         0: getstatic     #18                 // Field org/scalatest/enablers/Length$.MODULE$:Lorg/scalatest/enablers/Length$;
         3: invokevirtual #53                 // Method org/scalatest/enablers/Length$.lengthOfGenSeq:()Lorg/scalatest/enablers/Length;
         6: areturn
    Signature: #51                          // <SEQ::Lscala/collection/Seq<*>;>()Lorg/scalatest/enablers/Length<TSEQ;>;

  public static <JLIST extends java.util.List<?>> org.scalatest.enablers.Length<JLIST> lengthOfJavaList();
    descriptor: ()Lorg/scalatest/enablers/Length;
    flags: (0x0009) ACC_PUBLIC, ACC_STATIC
    Code:
      stack=1, locals=0, args_size=0
         0: getstatic     #18                 // Field org/scalatest/enablers/Length$.MODULE$:Lorg/scalatest/enablers/Length$;
         3: invokevirtual #57                 // Method org/scalatest/enablers/Length$.lengthOfJavaList:()Lorg/scalatest/enablers/Length;
         6: areturn
    Signature: #55                          // <JLIST::Ljava/util/List<*>;>()Lorg/scalatest/enablers/Length<TJLIST;>;

  public abstract long lengthOf(T);
    descriptor: (Ljava/lang/Object;)J
    flags: (0x0401) ACC_PUBLIC, ACC_ABSTRACT
    Signature: #60                          // (TT;)J
    MethodParameters:
      Name                           Flags
      obj                            final
}
Signature: #3                           // <T:Ljava/lang/Object;>Ljava/lang/Object;
SourceFile: "Length.scala"
RuntimeVisibleAnnotations:
  0: #7(#8=s#9)
    scala.reflect.ScalaSignature(
      bytes="\u0006\u0005\u0005Ufa\u0002\n\u0014!\u0003\r\nA\u0007\u0005\u0006E\u00011\taI\u0004\u0006iMA\t!\u000e\u0004\u0006%MA\ta\u000e\u0005\u0006q\r!\t!\u000f\u0005\u0006u\r!\u0019a\u000f\u0005\u0006\u001d\u000e!\u0019a\u0014\u0005\u0006U\u000e!\u0019a\u001b\u0005\bi\u000e\u0011\r\u0011b\u0001v\u0011\u0019y8\u0001)A\u0005m\"9\u0011\u0011A\u0002\u0005\u0004\u0005\r\u0001bBA\u0011\u0007\u0011\r\u00111\u0005\u0005\b\u0003o\u0019A1AA\u001d\u0011\u001d\tie\u0001C\u0002\u0003\u001fBq!!\u0019\u0004\t\u0007\t\u0019\u0007C\u0004\u0002x\r!\u0019!!\u001f\t\u000f\u000555\u0001b\u0001\u0002\u0010\"9\u0011\u0011U\u0002\u0005\u0004\u0005\r&A\u0002\'f]\u001e$\bN\u0003\u0002\u0015+\u0005AQM\\1cY\u0016\u00148O\u0003\u0002\u0017/\u0005I1oY1mCR,7\u000f\u001e\u0006\u00021\u0005\u0019qN]4\u0004\u0001U\u00111dK\n\u0003\u0001q\u0001\"!\b\u0011\u000e\u0003yQ\u0011aH\u0001\u0006g\u000e\fG.Y\u0005\u0003Cy\u0011a!\u00118z%\u00164\u0017\u0001\u00037f]\u001e$\bn\u00144\u0015\u0005\u0011:\u0003CA\u000f&\u0013\t1cD\u0001\u0003M_:<\u0007\"\u0002\u0015\u0002\u0001\u0004I\u0013aA8cUB\u0011!f\u000b\u0007\u0001\t\u0015a\u0003A1\u0001.\u0005\u0005!\u0016C\u0001\u00182!\tir&\u0003\u00021=\t9aj\u001c;iS:<\u0007CA\u000f3\u0013\t\u0019dDA\u0002B]f\fa\u0001T3oORD\u0007C\u0001\u001c\u0004\u001b\u0005\u00192CA\u0002\u001d\u0003\u0019a\u0014N\\5u}Q\tQ\'\u0001\tmK:<G\u000f[(g\u0015\u00064\u0018\rT5tiV\u0011AhP\u000b\u0002{A\u0019a\u0007\u0001 \u0011\u0005)zD!\u0002!\u0006\u0005\u0004\t%!\u0002&M\u0013N#\u0016C\u0001\u0018Ca\t\u0019E\nE\u0002E\u0013.k\u0011!\u0012\u0006\u0003\r\u001e\u000bA!\u001e;jY*\t\u0001*\u0001\u0003kCZ\f\u0017B\u0001&F\u0005\u0011a\u0015n\u001d;\u0011\u0005)bE!C\'@\u0003\u0003\u0005\tQ!\u0001.\u0005\ryF%M\u0001\u000fY\u0016tw\r\u001e5PM\u001e+gnU3r+\t\u00016+F\u0001R!\r1\u0004A\u0015\t\u0003UM#Q\u0001\u0016\u0004C\u0002U\u00131aU#R#\tqc\u000b\r\u0002XQB\u0019\u0001\fZ4\u000f\u0005e\u000bgB\u0001.`\u001d\tYf,D\u0001]\u0015\ti\u0016$\u0001\u0004=e>|GOP\u0005\u0002?%\u0011\u0001MH\u0001\u000bG>dG.Z2uS>t\u0017B\u00012d\u0003\u001d\u0001\u0018mY6bO\u0016T!\u0001\u0019\u0010\n\u0005\u00154\'AB$f]N+\u0017O\u0003\u0002cGB\u0011!\u0006\u001b\u0003\nSN\u000b\t\u0011!A\u0003\u00025\u00121a\u0018\u00133\u00035aWM\\4uQ>3\u0017I\u001d:bsV\u0011AN]\u000b\u0002[B\u0019a\u0007\u00018\u0011\u0007uy\u0017/\u0003\u0002q=\t)\u0011I\u001d:bsB\u0011!F\u001d\u0003\u0006g\u001e\u0011\r!\f\u0002\u0002\u000b\u0006qA.\u001a8hi\"|em\u0015;sS:<W#\u0001<\u0011\u0007Y\u0002q\u000f\u0005\u0002yy:\u0011\u0011P\u001f\t\u00037zI!a\u001f\u0010\u0002\rA\u0013X\rZ3g\u0013\tihP\u0001\u0004TiJLgn\u001a\u0006\u0003wz\tq\u0002\\3oORDwJZ*ue&tw\rI\u0001%Y\u0016tw\r\u001e5PM\u0006s\u0017PU3g/&$\b\u000eT3oORDW*\u001a;i_\u00124uN]%oiV!\u0011QAA\u0006+\t\t9\u0001\u0005\u00037\u0001\u0005%\u0001c\u0001\u0016\u0002\f\u00111AF\u0003b\u0001\u0003\u001b\t2ALA\b%\r\t\t\u0002\b\u0004\u0007\u0003\'\u0019\u0001!a\u0004\u0003\u0019q\u0012XMZ5oK6,g\u000e\u001e \t\u0011\u0005]\u0011\u0011\u0003D\u0001\u00033\ta\u0001\\3oORDGCAA\u000e!\ri\u0012QD\u0005\u0004\u0003?q\"aA%oi\u0006\tD.\u001a8hi\"|e-\u00118z%\u00164w+\u001b;i!\u0006\u0014\u0018-\\3uKJdWm]:MK:<G\u000f[\'fi\"|GMR8s\u0013:$X\u0003BA\u0013\u0003W)\"!a\n\u0011\tY\u0002\u0011\u0011\u0006\t\u0004U\u0005-BA\u0002\u0017\f\u0005\u0004\ti#E\u0002/\u0003_\u00112!!\r\u001d\r\u0019\t\u0019b\u0001\u0001\u00020!A\u0011qCA\u0019\r\u0003\t)$\u0006\u0002\u0002\u001c\u00059C.\u001a8hi\"|e-\u00118z%\u00164w+\u001b;i\u000f\u0016$H*\u001a8hi\"lU\r\u001e5pI\u001a{\'/\u00138u+\u0011\tY$!\u0011\u0016\u0005\u0005u\u0002\u0003\u0002\u001c\u0001\u0003\u007f\u00012AKA!\t\u0019aCB1\u0001\u0002DE\u0019a&!\u0012\u0013\u0007\u0005\u001dCD\u0002\u0004\u0002\u0014\r\u0001\u0011Q\t\u0005\t\u0003\u0017\n9E\"\u0001\u0002\u001a\u0005Iq-\u001a;MK:<G\u000f[\u00015Y\u0016tw\r\u001e5PM\u0006s\u0017PU3g/&$\b\u000eU1sC6,G/\u001a:mKN\u001cx)\u001a;MK:<G\u000f[\'fi\"|GMR8s\u0013:$X\u0003BA)\u0003/*\"!a\u0015\u0011\tY\u0002\u0011Q\u000b\t\u0004U\u0005]CA\u0002\u0017\u000e\u0005\u0004\tI&E\u0002/\u00037\u00122!!\u0018\u001d\r\u0019\t\u0019b\u0001\u0001\u0002\\!A\u00111JA/\r\u0003\t)$A\u0013mK:<G\u000f[(g\u0003:L(+\u001a4XSRDG*\u001a8hi\"lU\r\u001e5pI\u001a{\'\u000fT8oOV!\u0011QMA6+\t\t9\u0007\u0005\u00037\u0001\u0005%\u0004c\u0001\u0016\u0002l\u00111AF\u0004b\u0001\u0003[\n2ALA8%\r\t\t\b\b\u0004\u0007\u0003\'\u0019\u0001!a\u001c\t\u0011\u0005]\u0011\u0011\u000fD\u0001\u0003k\"\u0012\u0001J\u00013Y\u0016tw\r\u001e5PM\u0006s\u0017PU3g/&$\b\u000eU1sC6,G/\u001a:mKN\u001cH*\u001a8hi\"lU\r\u001e5pI\u001a{\'\u000fT8oOV!\u00111PAA+\t\ti\b\u0005\u00037\u0001\u0005}\u0004c\u0001\u0016\u0002\u0002\u00121Af\u0004b\u0001\u0003\u0007\u000b2ALAC%\r\t9\t\b\u0004\u0007\u0003\'\u0019\u0001!!\"\t\u0011\u0005]\u0011q\u0011D\u0001\u0003\u0017+\u0012\u0001J\u0001)Y\u0016tw\r\u001e5PM\u0006s\u0017PU3g/&$\bnR3u\u0019\u0016tw\r\u001e5NKRDw\u000e\u001a$pe2{gnZ\u000b\u0005\u0003#\u000b9*\u0006\u0002\u0002\u0014B!a\u0007AAK!\rQ\u0013q\u0013\u0003\u0007YA\u0011\r!!\'\u0012\u00079\nYJE\u0002\u0002\u001er1a!a\u0005\u0004\u0001\u0005m\u0005\u0002CA&\u0003;3\t!!\u001e\u0002k1,gn\u001a;i\u001f\u001a\fe.\u001f*fM^KG\u000f\u001b)be\u0006lW\r^3sY\u0016\u001c8oR3u\u0019\u0016tw\r\u001e5NKRDw\u000e\u001a$pe2{gnZ\u000b\u0005\u0003K\u000bY+\u0006\u0002\u0002(B!a\u0007AAU!\rQ\u00131\u0016\u0003\u0007YE\u0011\r!!,\u0012\u00079\nyKE\u0002\u00022r1a!a\u0005\u0004\u0001\u0005=\u0006\u0002CA&\u0003c3\t!a#"
    )
  ScalaInlineInfo: length = 0x9 (unknown attribute)
   01 00 00 01 00 3A 00 3B 00
  ScalaSig: length = 0x3 (unknown attribute)
   05 02 00
