Classfile /Users/mw/Projects/slang-braindump/.jar/jar8/assemble/slang-braindump/assemble/content/org/scalatest/enablers/Sortable.class
  Last modified May 29, 2022; size 2500 bytes
  SHA-256 checksum ab81150fc6de3282c78647dd6a5103f90c335f7dcf6ab7b58583bf74f1aa8ee9
  Compiled from "Sortable.scala"
public interface org.scalatest.enablers.Sortable<S extends java.lang.Object>
  minor version: 0
  major version: 52
  flags: (0x0601) ACC_PUBLIC, ACC_INTERFACE, ACC_ABSTRACT
  this_class: #2                          // org/scalatest/enablers/Sortable
  super_class: #5                         // java/lang/Object
  interfaces: 0, fields: 0, methods: 5, attributes: 5
Constant pool:
   #1 = Utf8               org/scalatest/enablers/Sortable
   #2 = Class              #1             // org/scalatest/enablers/Sortable
   #3 = Utf8               <S:Ljava/lang/Object;>Ljava/lang/Object;
   #4 = Utf8               java/lang/Object
   #5 = Class              #4             // java/lang/Object
   #6 = Utf8               Sortable.scala
   #7 = Utf8               Lscala/reflect/ScalaSignature;
   #8 = Utf8               bytes
   #9 = Utf8               \u0006\u0005\u0005UaaB\u0005\u000b!\u0003\r\n!\u0005\u0005\u00063\u00011\tAG\u0004\u0006W)A\t\u0001\f\u0004\u0006\u0013)A\tA\f\u0005\u0006_\r!\t\u0001\r\u0005\u0006c\r!\u0019A\r\u0005\u00061\u000e!\u0019!\u0017\u0005\u0006G\u000e!\u0019\u0001\u001a\u0005\u0006g\u000e!\u0019\u0001\u001e\u0002\t\'>\u0014H/\u00192mK*\u00111\u0002D\u0001\tK:\f\'\r\\3sg*\u0011QBD\u0001\ng\u000e\fG.\u0019;fgRT\u0011aD\u0001\u0004_J<7\u0001A\u000b\u0003%\t\u001a\"\u0001A\n\u0011\u0005Q9R\"A\u000b\u000b\u0003Y\tQa]2bY\u0006L!\u0001G\u000b\u0003\r\u0005s\u0017PU3g\u0003!I7oU8si\u0016$GCA\u000e\u001f!\t!B$\u0003\u0002\u001e+\t9!i\\8mK\u0006t\u0007\"B\u0010\u0002\u0001\u0004\u0001\u0013\u0001C:fcV,gnY3\u0011\u0005\u0005\u0012C\u0002\u0001\u0003\u0007G\u0001A)\u0019\u0001\u0013\u0003\u0003M\u000b\"!\n\u0015\u0011\u0005Q1\u0013BA\u0014\u0016\u0005\u001dqu\u000e\u001e5j]\u001e\u0004\"\u0001F\u0015\n\u0005)*\"aA!os\u0006A1k\u001c:uC\ndW\r\u0005\u0002.\u00075\t!b\u0005\u0002\u0004\'\u00051A(\u001b8jiz\"\u0012\u0001L\u0001\u0014g>\u0014H/\u00192mK:\u000bG/\u001e:f\u001f\u001a\u001cV-]\u000b\u0004g93DC\u0001\u001bQ!\ri\u0003!\u000e\t\u0004CYjE!B\u001c\u0006\u0005\u0004A$aA*F#V\u0011\u0011hS\t\u0003Ki\u00022aO$K\u001d\taDI\u0004\u0002>\u0005:\u0011a(Q\u0007\u0002\u007f)\u0011\u0001\tE\u0001\u0007yI|w\u000e\u001e \n\u0003YI!aQ\u000b\u0002\u0015\r|G\u000e\\3di&|g.\u0003\u0002F\r\u00069\u0001/Y2lC\u001e,\'BA\"\u0016\u0013\tA\u0015J\u0001\u0004HK:\u001cV-\u001d\u0006\u0003\u000b\u001a\u0003\"!I&\u0005\u000b13$\u0019\u0001\u0013\u0003\u0003\u0015\u0004\"!\t(\u0005\u000b=+!\u0019\u0001\u0013\u0003\u0003\u0015CQ!U\u0003A\u0004I\u000b\u0001b\u001c:eKJLgn\u001a\t\u0004\'VkeBA\u001fU\u0013\t)U#\u0003\u0002W/\nAqJ\u001d3fe&twM\u0003\u0002F+\u0005)2o\u001c:uC\ndWMT1ukJ,wJZ!se\u0006LXC\u0001.a)\tY\u0016\rE\u0002.\u0001q\u00032\u0001F/`\u0013\tqVCA\u0003BeJ\f\u0017\u0010\u0005\u0002\"A\u0012)qJ\u0002b\u0001I!)\u0011K\u0002a\u0002EB\u00191+V0\u0002-M|\'\u000f^1cY\u0016t\u0015\r^;sK>37\u000b\u001e:j]\u001e$\"!\u001a8\u0011\u00075\u0002a\r\u0005\u0002hW:\u0011\u0001.\u001b\t\u0003}UI!A[\u000b\u0002\rA\u0013X\rZ3g\u0013\taWN\u0001\u0004TiJLgn\u001a\u0006\u0003UVAQ!U\u0004A\u0004=\u00042aU+q!\t!\u0012/\u0003\u0002s+\t!1\t[1s\u0003a\u0019xN\u001d;bE2,g*\u0019;ve\u0016|eMS1wC2K7\u000f^\u000b\u0005k\u0006=\u0001\u0010F\u0002w\u0003#\u00012!\f\u0001x!\u0011\t\u00030!\u0004\u0005\u000beD!\u0019\u0001>\u0003\u000b)c\u0015j\u0015+\u0016\u0007m\fY!\u0005\u0002&yB)Q0!\u0002\u0002\n5\taPC\u0002\u0000\u0003\u0003\tA!\u001e;jY*\u0011\u00111A\u0001\u0005U\u00064\u0018-C\u0002\u0002\by\u0014A\u0001T5tiB\u0019\u0011%a\u0003\u0005\u000b1C(\u0019\u0001\u0013\u0011\u0007\u0005\ny\u0001B\u0003P\u0011\t\u0007A\u0005\u0003\u0004R\u0011\u0001\u000f\u00111\u0003\t\u0005\'V\u000bi\u0001
  #10 = Utf8               sortableNatureOfJavaList
  #11 = Utf8               (Lscala/math/Ordering;)Lorg/scalatest/enablers/Sortable;
  #12 = Utf8               <E:Ljava/lang/Object;JLIST::Ljava/util/List<Ljava/lang/Object;>;>(Lscala/math/Ordering<TE;>;)Lorg/scalatest/enablers/Sortable<TJLIST;>;
  #13 = Utf8               ordering
  #14 = Utf8               org/scalatest/enablers/Sortable$
  #15 = Class              #14            // org/scalatest/enablers/Sortable$
  #16 = Utf8               MODULE$
  #17 = Utf8               Lorg/scalatest/enablers/Sortable$;
  #18 = NameAndType        #16:#17        // MODULE$:Lorg/scalatest/enablers/Sortable$;
  #19 = Fieldref           #15.#18        // org/scalatest/enablers/Sortable$.MODULE$:Lorg/scalatest/enablers/Sortable$;
  #20 = NameAndType        #10:#11        // sortableNatureOfJavaList:(Lscala/math/Ordering;)Lorg/scalatest/enablers/Sortable;
  #21 = Methodref          #15.#20        // org/scalatest/enablers/Sortable$.sortableNatureOfJavaList:(Lscala/math/Ordering;)Lorg/scalatest/enablers/Sortable;
  #22 = Utf8               Lscala/math/Ordering;
  #23 = Utf8               sortableNatureOfString
  #24 = Utf8               (Lscala/math/Ordering<Ljava/lang/Object;>;)Lorg/scalatest/enablers/Sortable<Ljava/lang/String;>;
  #25 = NameAndType        #23:#11        // sortableNatureOfString:(Lscala/math/Ordering;)Lorg/scalatest/enablers/Sortable;
  #26 = Methodref          #15.#25        // org/scalatest/enablers/Sortable$.sortableNatureOfString:(Lscala/math/Ordering;)Lorg/scalatest/enablers/Sortable;
  #27 = Utf8               sortableNatureOfArray
  #28 = Utf8               <E:Ljava/lang/Object;>(Lscala/math/Ordering<TE;>;)Lorg/scalatest/enablers/Sortable<Ljava/lang/Object;>;
  #29 = NameAndType        #27:#11        // sortableNatureOfArray:(Lscala/math/Ordering;)Lorg/scalatest/enablers/Sortable;
  #30 = Methodref          #15.#29        // org/scalatest/enablers/Sortable$.sortableNatureOfArray:(Lscala/math/Ordering;)Lorg/scalatest/enablers/Sortable;
  #31 = Utf8               sortableNatureOfSeq
  #32 = Utf8               <E:Ljava/lang/Object;SEQ::Lscala/collection/Seq<Ljava/lang/Object;>;>(Lscala/math/Ordering<TE;>;)Lorg/scalatest/enablers/Sortable<TSEQ;>;
  #33 = NameAndType        #31:#11        // sortableNatureOfSeq:(Lscala/math/Ordering;)Lorg/scalatest/enablers/Sortable;
  #34 = Methodref          #15.#33        // org/scalatest/enablers/Sortable$.sortableNatureOfSeq:(Lscala/math/Ordering;)Lorg/scalatest/enablers/Sortable;
  #35 = Utf8               isSorted
  #36 = Utf8               (Ljava/lang/Object;)Z
  #37 = Utf8               (TS;)Z
  #38 = Utf8               sequence
  #39 = Utf8               Code
  #40 = Utf8               LocalVariableTable
  #41 = Utf8               Signature
  #42 = Utf8               MethodParameters
  #43 = Utf8               SourceFile
  #44 = Utf8               RuntimeVisibleAnnotations
  #45 = Utf8               ScalaInlineInfo
  #46 = Utf8               ScalaSig
{
  public static <E extends java.lang.Object, JLIST extends java.util.List<java.lang.Object>> org.scalatest.enablers.Sortable<JLIST> sortableNatureOfJavaList(scala.math.Ordering<E>);
    descriptor: (Lscala/math/Ordering;)Lorg/scalatest/enablers/Sortable;
    flags: (0x0009) ACC_PUBLIC, ACC_STATIC
    Code:
      stack=2, locals=1, args_size=1
         0: getstatic     #19                 // Field org/scalatest/enablers/Sortable$.MODULE$:Lorg/scalatest/enablers/Sortable$;
         3: aload_0
         4: invokevirtual #21                 // Method org/scalatest/enablers/Sortable$.sortableNatureOfJavaList:(Lscala/math/Ordering;)Lorg/scalatest/enablers/Sortable;
         7: areturn
      LocalVariableTable:
        Start  Length  Slot  Name   Signature
            0       8     0 ordering   Lscala/math/Ordering;
    Signature: #12                          // <E:Ljava/lang/Object;JLIST::Ljava/util/List<Ljava/lang/Object;>;>(Lscala/math/Ordering<TE;>;)Lorg/scalatest/enablers/Sortable<TJLIST;>;
    MethodParameters:
      Name                           Flags
      ordering                       final

  public static org.scalatest.enablers.Sortable<java.lang.String> sortableNatureOfString(scala.math.Ordering<java.lang.Object>);
    descriptor: (Lscala/math/Ordering;)Lorg/scalatest/enablers/Sortable;
    flags: (0x0009) ACC_PUBLIC, ACC_STATIC
    Code:
      stack=2, locals=1, args_size=1
         0: getstatic     #19                 // Field org/scalatest/enablers/Sortable$.MODULE$:Lorg/scalatest/enablers/Sortable$;
         3: aload_0
         4: invokevirtual #26                 // Method org/scalatest/enablers/Sortable$.sortableNatureOfString:(Lscala/math/Ordering;)Lorg/scalatest/enablers/Sortable;
         7: areturn
      LocalVariableTable:
        Start  Length  Slot  Name   Signature
            0       8     0 ordering   Lscala/math/Ordering;
    Signature: #24                          // (Lscala/math/Ordering<Ljava/lang/Object;>;)Lorg/scalatest/enablers/Sortable<Ljava/lang/String;>;
    MethodParameters:
      Name                           Flags
      ordering                       final

  public static <E extends java.lang.Object> org.scalatest.enablers.Sortable<java.lang.Object> sortableNatureOfArray(scala.math.Ordering<E>);
    descriptor: (Lscala/math/Ordering;)Lorg/scalatest/enablers/Sortable;
    flags: (0x0009) ACC_PUBLIC, ACC_STATIC
    Code:
      stack=2, locals=1, args_size=1
         0: getstatic     #19                 // Field org/scalatest/enablers/Sortable$.MODULE$:Lorg/scalatest/enablers/Sortable$;
         3: aload_0
         4: invokevirtual #30                 // Method org/scalatest/enablers/Sortable$.sortableNatureOfArray:(Lscala/math/Ordering;)Lorg/scalatest/enablers/Sortable;
         7: areturn
      LocalVariableTable:
        Start  Length  Slot  Name   Signature
            0       8     0 ordering   Lscala/math/Ordering;
    Signature: #28                          // <E:Ljava/lang/Object;>(Lscala/math/Ordering<TE;>;)Lorg/scalatest/enablers/Sortable<Ljava/lang/Object;>;
    MethodParameters:
      Name                           Flags
      ordering                       final

  public static <E extends java.lang.Object, SEQ extends scala.collection.Seq<java.lang.Object>> org.scalatest.enablers.Sortable<SEQ> sortableNatureOfSeq(scala.math.Ordering<E>);
    descriptor: (Lscala/math/Ordering;)Lorg/scalatest/enablers/Sortable;
    flags: (0x0009) ACC_PUBLIC, ACC_STATIC
    Code:
      stack=2, locals=1, args_size=1
         0: getstatic     #19                 // Field org/scalatest/enablers/Sortable$.MODULE$:Lorg/scalatest/enablers/Sortable$;
         3: aload_0
         4: invokevirtual #34                 // Method org/scalatest/enablers/Sortable$.sortableNatureOfSeq:(Lscala/math/Ordering;)Lorg/scalatest/enablers/Sortable;
         7: areturn
      LocalVariableTable:
        Start  Length  Slot  Name   Signature
            0       8     0 ordering   Lscala/math/Ordering;
    Signature: #32                          // <E:Ljava/lang/Object;SEQ::Lscala/collection/Seq<Ljava/lang/Object;>;>(Lscala/math/Ordering<TE;>;)Lorg/scalatest/enablers/Sortable<TSEQ;>;
    MethodParameters:
      Name                           Flags
      ordering                       final

  public abstract boolean isSorted(S);
    descriptor: (Ljava/lang/Object;)Z
    flags: (0x0401) ACC_PUBLIC, ACC_ABSTRACT
    Signature: #37                          // (TS;)Z
    MethodParameters:
      Name                           Flags
      sequence                       final
}
Signature: #3                           // <S:Ljava/lang/Object;>Ljava/lang/Object;
SourceFile: "Sortable.scala"
RuntimeVisibleAnnotations:
  0: #7(#8=s#9)
    scala.reflect.ScalaSignature(
      bytes="\u0006\u0005\u0005UaaB\u0005\u000b!\u0003\r\n!\u0005\u0005\u00063\u00011\tAG\u0004\u0006W)A\t\u0001\f\u0004\u0006\u0013)A\tA\f\u0005\u0006_\r!\t\u0001\r\u0005\u0006c\r!\u0019A\r\u0005\u00061\u000e!\u0019!\u0017\u0005\u0006G\u000e!\u0019\u0001\u001a\u0005\u0006g\u000e!\u0019\u0001\u001e\u0002\t\'>\u0014H/\u00192mK*\u00111\u0002D\u0001\tK:\f\'\r\\3sg*\u0011QBD\u0001\ng\u000e\fG.\u0019;fgRT\u0011aD\u0001\u0004_J<7\u0001A\u000b\u0003%\t\u001a\"\u0001A\n\u0011\u0005Q9R\"A\u000b\u000b\u0003Y\tQa]2bY\u0006L!\u0001G\u000b\u0003\r\u0005s\u0017PU3g\u0003!I7oU8si\u0016$GCA\u000e\u001f!\t!B$\u0003\u0002\u001e+\t9!i\\8mK\u0006t\u0007\"B\u0010\u0002\u0001\u0004\u0001\u0013\u0001C:fcV,gnY3\u0011\u0005\u0005\u0012C\u0002\u0001\u0003\u0007G\u0001A)\u0019\u0001\u0013\u0003\u0003M\u000b\"!\n\u0015\u0011\u0005Q1\u0013BA\u0014\u0016\u0005\u001dqu\u000e\u001e5j]\u001e\u0004\"\u0001F\u0015\n\u0005)*\"aA!os\u0006A1k\u001c:uC\ndW\r\u0005\u0002.\u00075\t!b\u0005\u0002\u0004\'\u00051A(\u001b8jiz\"\u0012\u0001L\u0001\u0014g>\u0014H/\u00192mK:\u000bG/\u001e:f\u001f\u001a\u001cV-]\u000b\u0004g93DC\u0001\u001bQ!\ri\u0003!\u000e\t\u0004CYjE!B\u001c\u0006\u0005\u0004A$aA*F#V\u0011\u0011hS\t\u0003Ki\u00022aO$K\u001d\taDI\u0004\u0002>\u0005:\u0011a(Q\u0007\u0002\u007f)\u0011\u0001\tE\u0001\u0007yI|w\u000e\u001e \n\u0003YI!aQ\u000b\u0002\u0015\r|G\u000e\\3di&|g.\u0003\u0002F\r\u00069\u0001/Y2lC\u001e,\'BA\"\u0016\u0013\tA\u0015J\u0001\u0004HK:\u001cV-\u001d\u0006\u0003\u000b\u001a\u0003\"!I&\u0005\u000b13$\u0019\u0001\u0013\u0003\u0003\u0015\u0004\"!\t(\u0005\u000b=+!\u0019\u0001\u0013\u0003\u0003\u0015CQ!U\u0003A\u0004I\u000b\u0001b\u001c:eKJLgn\u001a\t\u0004\'VkeBA\u001fU\u0013\t)U#\u0003\u0002W/\nAqJ\u001d3fe&twM\u0003\u0002F+\u0005)2o\u001c:uC\ndWMT1ukJ,wJZ!se\u0006LXC\u0001.a)\tY\u0016\rE\u0002.\u0001q\u00032\u0001F/`\u0013\tqVCA\u0003BeJ\f\u0017\u0010\u0005\u0002\"A\u0012)qJ\u0002b\u0001I!)\u0011K\u0002a\u0002EB\u00191+V0\u0002-M|\'\u000f^1cY\u0016t\u0015\r^;sK>37\u000b\u001e:j]\u001e$\"!\u001a8\u0011\u00075\u0002a\r\u0005\u0002hW:\u0011\u0001.\u001b\t\u0003}UI!A[\u000b\u0002\rA\u0013X\rZ3g\u0013\taWN\u0001\u0004TiJLgn\u001a\u0006\u0003UVAQ!U\u0004A\u0004=\u00042aU+q!\t!\u0012/\u0003\u0002s+\t!1\t[1s\u0003a\u0019xN\u001d;bE2,g*\u0019;ve\u0016|eMS1wC2K7\u000f^\u000b\u0005k\u0006=\u0001\u0010F\u0002w\u0003#\u00012!\f\u0001x!\u0011\t\u00030!\u0004\u0005\u000beD!\u0019\u0001>\u0003\u000b)c\u0015j\u0015+\u0016\u0007m\fY!\u0005\u0002&yB)Q0!\u0002\u0002\n5\taPC\u0002\u0000\u0003\u0003\tA!\u001e;jY*\u0011\u00111A\u0001\u0005U\u00064\u0018-C\u0002\u0002\by\u0014A\u0001T5tiB\u0019\u0011%a\u0003\u0005\u000b1C(\u0019\u0001\u0013\u0011\u0007\u0005\ny\u0001B\u0003P\u0011\t\u0007A\u0005\u0003\u0004R\u0011\u0001\u000f\u00111\u0003\t\u0005\'V\u000bi\u0001"
    )
  ScalaInlineInfo: length = 0x9 (unknown attribute)
   01 00 00 01 00 23 00 24 00
  ScalaSig: length = 0x3 (unknown attribute)
   05 02 00
