Classfile /Users/mw/Projects/slang-braindump/.jar/jar8/assemble/slang-braindump/assemble/content/org/scalatest/enablers/Timed$.class
  Last modified May 29, 2022; size 1467 bytes
  SHA-256 checksum f47d7a19f390361809cf504b99ca975eef50c07ae673584373712355ddd0f15c
  Compiled from "Timed.scala"
public final class org.scalatest.enablers.Timed$
  minor version: 0
  major version: 52
  flags: (0x0031) ACC_PUBLIC, ACC_FINAL, ACC_SUPER
  this_class: #2                          // org/scalatest/enablers/Timed$
  super_class: #4                         // java/lang/Object
  interfaces: 0, fields: 1, methods: 5, attributes: 4
Constant pool:
   #1 = Utf8               org/scalatest/enablers/Timed$
   #2 = Class              #1             // org/scalatest/enablers/Timed$
   #3 = Utf8               java/lang/Object
   #4 = Class              #3             // java/lang/Object
   #5 = Utf8               Timed.scala
   #6 = Utf8               org/scalatest/enablers/Timed$$anon$1
   #7 = Class              #6             // org/scalatest/enablers/Timed$$anon$1
   #8 = Utf8               org/scalatest/enablers/Timed$$anon$2
   #9 = Class              #8             // org/scalatest/enablers/Timed$$anon$2
  #10 = Utf8               org/scalatest/enablers/Timed$$anon$3
  #11 = Class              #10            // org/scalatest/enablers/Timed$$anon$3
  #12 = Utf8               MODULE$
  #13 = Utf8               Lorg/scalatest/enablers/Timed$;
  #14 = Utf8               <clinit>
  #15 = Utf8               ()V
  #16 = Utf8               <init>
  #17 = NameAndType        #16:#15        // "<init>":()V
  #18 = Methodref          #2.#17         // org/scalatest/enablers/Timed$."<init>":()V
  #19 = NameAndType        #12:#13        // MODULE$:Lorg/scalatest/enablers/Timed$;
  #20 = Fieldref           #2.#19         // org/scalatest/enablers/Timed$.MODULE$:Lorg/scalatest/enablers/Timed$;
  #21 = Utf8               timed
  #22 = Utf8               ()Lorg/scalatest/enablers/Timed;
  #23 = Utf8               <T:Ljava/lang/Object;>()Lorg/scalatest/enablers/Timed<TT;>;
  #24 = Methodref          #7.#17         // org/scalatest/enablers/Timed$$anon$1."<init>":()V
  #25 = Utf8               this
  #26 = Utf8               timedFutureOf
  #27 = Utf8               (Lscala/concurrent/ExecutionContext;)Lorg/scalatest/enablers/Timed;
  #28 = Utf8               <T:Ljava/lang/Object;>(Lscala/concurrent/ExecutionContext;)Lorg/scalatest/enablers/Timed<Lscala/concurrent/Future<TT;>;>;
  #29 = Utf8               executionContext
  #30 = Utf8               (Lscala/concurrent/ExecutionContext;)V
  #31 = NameAndType        #16:#30        // "<init>":(Lscala/concurrent/ExecutionContext;)V
  #32 = Methodref          #9.#31         // org/scalatest/enablers/Timed$$anon$2."<init>":(Lscala/concurrent/ExecutionContext;)V
  #33 = Utf8               Lscala/concurrent/ExecutionContext;
  #34 = Utf8               timedFutureOutcome
  #35 = Utf8               (Lscala/concurrent/ExecutionContext;)Lorg/scalatest/enablers/Timed<Lorg/scalatest/FutureOutcome;>;
  #36 = Methodref          #11.#31        // org/scalatest/enablers/Timed$$anon$3."<init>":(Lscala/concurrent/ExecutionContext;)V
  #37 = Methodref          #4.#17         // java/lang/Object."<init>":()V
  #38 = Utf8               Code
  #39 = Utf8               LineNumberTable
  #40 = Utf8               LocalVariableTable
  #41 = Utf8               Signature
  #42 = Utf8               MethodParameters
  #43 = Utf8               InnerClasses
  #44 = Utf8               SourceFile
  #45 = Utf8               ScalaInlineInfo
  #46 = Utf8               Scala
{
  public static final org.scalatest.enablers.Timed$ MODULE$;
    descriptor: Lorg/scalatest/enablers/Timed$;
    flags: (0x0019) ACC_PUBLIC, ACC_STATIC, ACC_FINAL

  public static {};
    descriptor: ()V
    flags: (0x0009) ACC_PUBLIC, ACC_STATIC
    Code:
      stack=2, locals=0, args_size=0
         0: new           #2                  // class org/scalatest/enablers/Timed$
         3: dup
         4: invokespecial #18                 // Method "<init>":()V
         7: putstatic     #20                 // Field MODULE$:Lorg/scalatest/enablers/Timed$;
        10: return
      LineNumberTable:
        line 74: 0

  public <T extends java.lang.Object> org.scalatest.enablers.Timed<T> timed();
    descriptor: ()Lorg/scalatest/enablers/Timed;
    flags: (0x0001) ACC_PUBLIC
    Code:
      stack=2, locals=1, args_size=1
         0: new           #7                  // class org/scalatest/enablers/Timed$$anon$1
         3: dup
         4: invokespecial #24                 // Method org/scalatest/enablers/Timed$$anon$1."<init>":()V
         7: areturn
      LineNumberTable:
        line 114: 0
      LocalVariableTable:
        Start  Length  Slot  Name   Signature
            0       8     0  this   Lorg/scalatest/enablers/Timed$;
    Signature: #23                          // <T:Ljava/lang/Object;>()Lorg/scalatest/enablers/Timed<TT;>;

  public <T extends java.lang.Object> org.scalatest.enablers.Timed<scala.concurrent.Future<T>> timedFutureOf(scala.concurrent.ExecutionContext);
    descriptor: (Lscala/concurrent/ExecutionContext;)Lorg/scalatest/enablers/Timed;
    flags: (0x0001) ACC_PUBLIC
    Code:
      stack=3, locals=2, args_size=2
         0: new           #9                  // class org/scalatest/enablers/Timed$$anon$2
         3: dup
         4: aload_1
         5: invokespecial #32                 // Method org/scalatest/enablers/Timed$$anon$2."<init>":(Lscala/concurrent/ExecutionContext;)V
         8: areturn
      LineNumberTable:
        line 184: 0
      LocalVariableTable:
        Start  Length  Slot  Name   Signature
            0       9     0  this   Lorg/scalatest/enablers/Timed$;
            0       9     1 executionContext   Lscala/concurrent/ExecutionContext;
    Signature: #28                          // <T:Ljava/lang/Object;>(Lscala/concurrent/ExecutionContext;)Lorg/scalatest/enablers/Timed<Lscala/concurrent/Future<TT;>;>;
    MethodParameters:
      Name                           Flags
      executionContext               final

  public org.scalatest.enablers.Timed<org.scalatest.FutureOutcome> timedFutureOutcome(scala.concurrent.ExecutionContext);
    descriptor: (Lscala/concurrent/ExecutionContext;)Lorg/scalatest/enablers/Timed;
    flags: (0x0001) ACC_PUBLIC
    Code:
      stack=3, locals=2, args_size=2
         0: new           #11                 // class org/scalatest/enablers/Timed$$anon$3
         3: dup
         4: aload_1
         5: invokespecial #36                 // Method org/scalatest/enablers/Timed$$anon$3."<init>":(Lscala/concurrent/ExecutionContext;)V
         8: areturn
      LineNumberTable:
        line 288: 0
      LocalVariableTable:
        Start  Length  Slot  Name   Signature
            0       9     0  this   Lorg/scalatest/enablers/Timed$;
            0       9     1 executionContext   Lscala/concurrent/ExecutionContext;
    Signature: #35                          // (Lscala/concurrent/ExecutionContext;)Lorg/scalatest/enablers/Timed<Lorg/scalatest/FutureOutcome;>;
    MethodParameters:
      Name                           Flags
      executionContext               final

  private org.scalatest.enablers.Timed$();
    descriptor: ()V
    flags: (0x0002) ACC_PRIVATE
    Code:
      stack=1, locals=1, args_size=1
         0: aload_0
         1: invokespecial #37                 // Method java/lang/Object."<init>":()V
         4: return
      LineNumberTable:
        line 343: 0
        line 74: 4
      LocalVariableTable:
        Start  Length  Slot  Name   Signature
            0       5     0  this   Lorg/scalatest/enablers/Timed$;
}
InnerClasses:
  public final #7;                        // class org/scalatest/enablers/Timed$$anon$1
  public final #9;                        // class org/scalatest/enablers/Timed$$anon$2
  public final #11;                       // class org/scalatest/enablers/Timed$$anon$3
SourceFile: "Timed.scala"
  ScalaInlineInfo: length = 0x18 (unknown attribute)
   01 01 00 04 00 10 00 0F 01 00 15 00 16 01 00 1A
   00 1B 01 00 22 00 1B 01
  Scala: length = 0x0 (unknown attribute)

