Classfile /Users/mw/Projects/slang-braindump/.jar/jar8/assemble/slang-braindump/assemble/content/org/scalatest/enablers/Timed$$anon$1.class
  Last modified May 29, 2022; size 3374 bytes
  SHA-256 checksum dc27015e712f4e6fd072d135010564167bfff0619035e05769e0d240dd5112db
  Compiled from "Timed.scala"
public final class org.scalatest.enablers.Timed$$anon$1 extends java.lang.Object implements org.scalatest.enablers.Timed<T>
  minor version: 0
  major version: 52
  flags: (0x0031) ACC_PUBLIC, ACC_FINAL, ACC_SUPER
  this_class: #2                          // org/scalatest/enablers/Timed$$anon$1
  super_class: #5                         // java/lang/Object
  interfaces: 1, fields: 0, methods: 2, attributes: 6
Constant pool:
    #1 = Utf8               org/scalatest/enablers/Timed$$anon$1
    #2 = Class              #1            // org/scalatest/enablers/Timed$$anon$1
    #3 = Utf8               Ljava/lang/Object;Lorg/scalatest/enablers/Timed<TT;>;
    #4 = Utf8               java/lang/Object
    #5 = Class              #4            // java/lang/Object
    #6 = Utf8               org/scalatest/enablers/Timed
    #7 = Class              #6            // org/scalatest/enablers/Timed
    #8 = Utf8               Timed.scala
    #9 = Utf8               org/scalatest/enablers/Timed$
   #10 = Class              #9            // org/scalatest/enablers/Timed$
   #11 = Utf8               timed
   #12 = Utf8               ()Lorg/scalatest/enablers/Timed;
   #13 = NameAndType        #11:#12       // timed:()Lorg/scalatest/enablers/Timed;
   #14 = Utf8               timeoutAfter
   #15 = Utf8               (Lorg/scalatest/time/Span;Lscala/Function0;Lorg/scalatest/concurrent/Signaler;Lscala/Function1;)Ljava/lang/Object;
   #16 = Utf8               (Lorg/scalatest/time/Span;Lscala/Function0<TT;>;Lorg/scalatest/concurrent/Signaler;Lscala/Function1<Lscala/Option<Ljava/lang/Throwable;>;Lorg/scalatest/exceptions/StackDepthException;>;)TT;
   #17 = Utf8               timeout
   #18 = Utf8               f
   #19 = Utf8               signaler
   #20 = Utf8               exceptionFun
   #21 = Utf8               java/lang/Throwable
   #22 = Class              #21           // java/lang/Throwable
   #23 = Utf8               org/scalatest/Timer
   #24 = Class              #23           // org/scalatest/Timer
   #25 = Utf8               <init>
   #26 = Utf8               ()V
   #27 = NameAndType        #25:#26       // "<init>":()V
   #28 = Methodref          #24.#27       // org/scalatest/Timer."<init>":()V
   #29 = Utf8               org/scalatest/concurrent/SignalerTimeoutTask
   #30 = Class              #29           // org/scalatest/concurrent/SignalerTimeoutTask
   #31 = Utf8               java/lang/Thread
   #32 = Class              #31           // java/lang/Thread
   #33 = Utf8               currentThread
   #34 = Utf8               ()Ljava/lang/Thread;
   #35 = NameAndType        #33:#34       // currentThread:()Ljava/lang/Thread;
   #36 = Methodref          #32.#35       // java/lang/Thread.currentThread:()Ljava/lang/Thread;
   #37 = Utf8               (Ljava/lang/Thread;Lorg/scalatest/concurrent/Signaler;)V
   #38 = NameAndType        #25:#37       // "<init>":(Ljava/lang/Thread;Lorg/scalatest/concurrent/Signaler;)V
   #39 = Methodref          #30.#38       // org/scalatest/concurrent/SignalerTimeoutTask."<init>":(Ljava/lang/Thread;Lorg/scalatest/concurrent/Signaler;)V
   #40 = Utf8               org/scalatest/time/Span
   #41 = Class              #40           // org/scalatest/time/Span
   #42 = Utf8               totalNanos
   #43 = Utf8               ()J
   #44 = NameAndType        #42:#43       // totalNanos:()J
   #45 = Methodref          #41.#44       // org/scalatest/time/Span.totalNanos:()J
   #46 = Long               1000l
   #48 = Utf8               schedule
   #49 = Utf8               (Lorg/scalatest/TimerTask;J)V
   #50 = NameAndType        #48:#49       // schedule:(Lorg/scalatest/TimerTask;J)V
   #51 = Methodref          #24.#50       // org/scalatest/Timer.schedule:(Lorg/scalatest/TimerTask;J)V
   #52 = Utf8               scala/compat/Platform$
   #53 = Class              #52           // scala/compat/Platform$
   #54 = Utf8               MODULE$
   #55 = Utf8               Lscala/compat/Platform$;
   #56 = NameAndType        #54:#55       // MODULE$:Lscala/compat/Platform$;
   #57 = Fieldref           #53.#56       // scala/compat/Platform$.MODULE$:Lscala/compat/Platform$;
   #58 = Utf8               currentTime
   #59 = NameAndType        #58:#43       // currentTime:()J
   #60 = Methodref          #53.#59       // scala/compat/Platform$.currentTime:()J
   #61 = Utf8               scala/Function0
   #62 = Class              #61           // scala/Function0
   #63 = Utf8               apply
   #64 = Utf8               ()Ljava/lang/Object;
   #65 = NameAndType        #63:#64       // apply:()Ljava/lang/Object;
   #66 = InterfaceMethodref #62.#65       // scala/Function0.apply:()Ljava/lang/Object;
   #67 = Utf8               cancel
   #68 = NameAndType        #67:#26       // cancel:()V
   #69 = Methodref          #30.#68       // org/scalatest/concurrent/SignalerTimeoutTask.cancel:()V
   #70 = Methodref          #24.#68       // org/scalatest/Timer.cancel:()V
   #71 = Utf8               org/scalatest/Outcome
   #72 = Class              #71           // org/scalatest/Outcome
   #73 = Utf8               org/scalatest/Exceptional$
   #74 = Class              #73           // org/scalatest/Exceptional$
   #75 = Utf8               Lorg/scalatest/Exceptional$;
   #76 = NameAndType        #54:#75       // MODULE$:Lorg/scalatest/Exceptional$;
   #77 = Fieldref           #74.#76       // org/scalatest/Exceptional$.MODULE$:Lorg/scalatest/Exceptional$;
   #78 = Utf8               unapply
   #79 = Utf8               (Lorg/scalatest/Outcome;)Lscala/Option;
   #80 = NameAndType        #78:#79       // unapply:(Lorg/scalatest/Outcome;)Lscala/Option;
   #81 = Methodref          #74.#80       // org/scalatest/Exceptional$.unapply:(Lorg/scalatest/Outcome;)Lscala/Option;
   #82 = Utf8               scala/Option
   #83 = Class              #82           // scala/Option
   #84 = Utf8               isEmpty
   #85 = Utf8               ()Z
   #86 = NameAndType        #84:#85       // isEmpty:()Z
   #87 = Methodref          #83.#86       // scala/Option.isEmpty:()Z
   #88 = Utf8               get
   #89 = NameAndType        #88:#64       // get:()Ljava/lang/Object;
   #90 = Methodref          #83.#89       // scala/Option.get:()Ljava/lang/Object;
   #91 = Utf8               timedOut
   #92 = NameAndType        #91:#85       // timedOut:()Z
   #93 = Methodref          #30.#92       // org/scalatest/concurrent/SignalerTimeoutTask.timedOut:()Z
   #94 = Utf8               needToResetInterruptedStatus
   #95 = NameAndType        #94:#85       // needToResetInterruptedStatus:()Z
   #96 = Methodref          #30.#95       // org/scalatest/concurrent/SignalerTimeoutTask.needToResetInterruptedStatus:()Z
   #97 = Utf8               interrupted
   #98 = NameAndType        #97:#85       // interrupted:()Z
   #99 = Methodref          #32.#98       // java/lang/Thread.interrupted:()Z
  #100 = Utf8               scala/runtime/BoxesRunTime
  #101 = Class              #100          // scala/runtime/BoxesRunTime
  #102 = Utf8               boxToBoolean
  #103 = Utf8               (Z)Ljava/lang/Boolean;
  #104 = NameAndType        #102:#103     // boxToBoolean:(Z)Ljava/lang/Boolean;
  #105 = Methodref          #101.#104     // scala/runtime/BoxesRunTime.boxToBoolean:(Z)Ljava/lang/Boolean;
  #106 = Utf8               scala/runtime/BoxedUnit
  #107 = Class              #106          // scala/runtime/BoxedUnit
  #108 = Utf8               UNIT
  #109 = Utf8               Lscala/runtime/BoxedUnit;
  #110 = NameAndType        #108:#109     // UNIT:Lscala/runtime/BoxedUnit;
  #111 = Fieldref           #107.#110     // scala/runtime/BoxedUnit.UNIT:Lscala/runtime/BoxedUnit;
  #112 = Utf8               scala/None$
  #113 = Class              #112          // scala/None$
  #114 = Utf8               Lscala/None$;
  #115 = NameAndType        #54:#114      // MODULE$:Lscala/None$;
  #116 = Fieldref           #113.#115     // scala/None$.MODULE$:Lscala/None$;
  #117 = Utf8               scala/Function1
  #118 = Class              #117          // scala/Function1
  #119 = Utf8               (Ljava/lang/Object;)Ljava/lang/Object;
  #120 = NameAndType        #63:#119      // apply:(Ljava/lang/Object;)Ljava/lang/Object;
  #121 = InterfaceMethodref #118.#120     // scala/Function1.apply:(Ljava/lang/Object;)Ljava/lang/Object;
  #122 = Utf8               scala/Some
  #123 = Class              #122          // scala/Some
  #124 = Utf8               (Ljava/lang/Object;)V
  #125 = NameAndType        #25:#124      // "<init>":(Ljava/lang/Object;)V
  #126 = Methodref          #123.#125     // scala/Some."<init>":(Ljava/lang/Object;)V
  #127 = Utf8               ex
  #128 = Utf8               Ljava/lang/Throwable;
  #129 = Utf8               result
  #130 = Utf8               Ljava/lang/Object;
  #131 = Utf8               endTime
  #132 = Utf8               J
  #133 = Utf8               t
  #134 = Utf8               timer
  #135 = Utf8               Lorg/scalatest/Timer;
  #136 = Utf8               task
  #137 = Utf8               Lorg/scalatest/concurrent/SignalerTimeoutTask;
  #138 = Utf8               maxDuration
  #139 = Utf8               startTime
  #140 = Utf8               this
  #141 = Utf8               Lorg/scalatest/enablers/Timed$$anon$1;
  #142 = Utf8               Lorg/scalatest/time/Span;
  #143 = Utf8               Lscala/Function0;
  #144 = Utf8               Lorg/scalatest/concurrent/Signaler;
  #145 = Utf8               Lscala/Function1;
  #146 = Utf8               org/scalatest/concurrent/Signaler
  #147 = Class              #146          // org/scalatest/concurrent/Signaler
  #148 = Methodref          #5.#27        // java/lang/Object."<init>":()V
  #149 = Utf8               Code
  #150 = Utf8               StackMapTable
  #151 = Utf8               LineNumberTable
  #152 = Utf8               LocalVariableTable
  #153 = Utf8               Signature
  #154 = Utf8               MethodParameters
  #155 = Utf8               InnerClasses
  #156 = Utf8               EnclosingMethod
  #157 = Utf8               SourceFile
  #158 = Utf8               ScalaInlineInfo
  #159 = Utf8               Scala
{
  public T timeoutAfter(org.scalatest.time.Span, scala.Function0<T>, org.scalatest.concurrent.Signaler, scala.Function1<scala.Option<java.lang.Throwable>, org.scalatest.exceptions.StackDepthException>);
    descriptor: (Lorg/scalatest/time/Span;Lscala/Function0;Lorg/scalatest/concurrent/Signaler;Lscala/Function1;)Ljava/lang/Object;
    flags: (0x0001) ACC_PUBLIC
    Code:
      stack=4, locals=22, args_size=5
         0: new           #24                 // class org/scalatest/Timer
         3: dup
         4: invokespecial #28                 // Method org/scalatest/Timer."<init>":()V
         7: astore        6
         9: new           #30                 // class org/scalatest/concurrent/SignalerTimeoutTask
        12: dup
        13: invokestatic  #36                 // Method java/lang/Thread.currentThread:()Ljava/lang/Thread;
        16: aload_3
        17: invokespecial #39                 // Method org/scalatest/concurrent/SignalerTimeoutTask."<init>":(Ljava/lang/Thread;Lorg/scalatest/concurrent/Signaler;)V
        20: astore        7
        22: aload_1
        23: invokevirtual #45                 // Method org/scalatest/time/Span.totalNanos:()J
        26: ldc2_w        #46                 // long 1000l
        29: ldiv
        30: ldc2_w        #46                 // long 1000l
        33: ldiv
        34: lstore        8
        36: aload         6
        38: aload         7
        40: lload         8
        42: invokevirtual #51                 // Method org/scalatest/Timer.schedule:(Lorg/scalatest/TimerTask;J)V
        45: getstatic     #57                 // Field scala/compat/Platform$.MODULE$:Lscala/compat/Platform$;
        48: invokevirtual #60                 // Method scala/compat/Platform$.currentTime:()J
        51: lstore        10
        53: aload_2
        54: invokeinterface #66,  1           // InterfaceMethod scala/Function0.apply:()Ljava/lang/Object;
        59: astore        12
        61: getstatic     #57                 // Field scala/compat/Platform$.MODULE$:Lscala/compat/Platform$;
        64: invokevirtual #60                 // Method scala/compat/Platform$.currentTime:()J
        67: lstore        13
        69: aload         7
        71: invokevirtual #69                 // Method org/scalatest/concurrent/SignalerTimeoutTask.cancel:()V
        74: aload         6
        76: invokevirtual #70                 // Method org/scalatest/Timer.cancel:()V
        79: aload         12
        81: astore        15
        83: aload         15
        85: instanceof    #72                 // class org/scalatest/Outcome
        88: ifeq          132
        91: aload         15
        93: checkcast     #72                 // class org/scalatest/Outcome
        96: astore        16
        98: getstatic     #77                 // Field org/scalatest/Exceptional$.MODULE$:Lorg/scalatest/Exceptional$;
       101: aload         16
       103: invokevirtual #81                 // Method org/scalatest/Exceptional$.unapply:(Lorg/scalatest/Outcome;)Lscala/Option;
       106: astore        17
       108: aload         17
       110: invokevirtual #87                 // Method scala/Option.isEmpty:()Z
       113: ifne          129
       116: aload         17
       118: invokevirtual #90                 // Method scala/Option.get:()Ljava/lang/Object;
       121: checkcast     #22                 // class java/lang/Throwable
       124: astore        18
       126: aload         18
       128: athrow
       129: goto          135
       132: goto          135
       135: aload         7
       137: invokevirtual #93                 // Method org/scalatest/concurrent/SignalerTimeoutTask.timedOut:()Z
       140: ifne          154
       143: lload         13
       145: lload         10
       147: lsub
       148: lload         8
       150: lcmp
       151: ifle          189
       154: aload         7
       156: invokevirtual #96                 // Method org/scalatest/concurrent/SignalerTimeoutTask.needToResetInterruptedStatus:()Z
       159: ifeq          171
       162: invokestatic  #99                 // Method java/lang/Thread.interrupted:()Z
       165: invokestatic  #105                // Method scala/runtime/BoxesRunTime.boxToBoolean:(Z)Ljava/lang/Boolean;
       168: goto          174
       171: getstatic     #111                // Field scala/runtime/BoxedUnit.UNIT:Lscala/runtime/BoxedUnit;
       174: pop
       175: aload         4
       177: getstatic     #116                // Field scala/None$.MODULE$:Lscala/None$;
       180: invokeinterface #121,  2          // InterfaceMethod scala/Function1.apply:(Ljava/lang/Object;)Ljava/lang/Object;
       185: checkcast     #22                 // class java/lang/Throwable
       188: athrow
       189: getstatic     #111                // Field scala/runtime/BoxedUnit.UNIT:Lscala/runtime/BoxedUnit;
       192: astore        5
       194: goto          197
       197: aload         12
       199: goto          285
       202: astore        19
       204: getstatic     #57                 // Field scala/compat/Platform$.MODULE$:Lscala/compat/Platform$;
       207: invokevirtual #60                 // Method scala/compat/Platform$.currentTime:()J
       210: lstore        20
       212: aload         7
       214: invokevirtual #69                 // Method org/scalatest/concurrent/SignalerTimeoutTask.cancel:()V
       217: aload         6
       219: invokevirtual #70                 // Method org/scalatest/Timer.cancel:()V
       222: aload         7
       224: invokevirtual #93                 // Method org/scalatest/concurrent/SignalerTimeoutTask.timedOut:()Z
       227: ifne          241
       230: lload         20
       232: lload         10
       234: lsub
       235: lload         8
       237: lcmp
       238: ifle          282
       241: aload         7
       243: invokevirtual #96                 // Method org/scalatest/concurrent/SignalerTimeoutTask.needToResetInterruptedStatus:()Z
       246: ifeq          258
       249: invokestatic  #99                 // Method java/lang/Thread.interrupted:()Z
       252: invokestatic  #105                // Method scala/runtime/BoxesRunTime.boxToBoolean:(Z)Ljava/lang/Boolean;
       255: goto          261
       258: getstatic     #111                // Field scala/runtime/BoxedUnit.UNIT:Lscala/runtime/BoxedUnit;
       261: pop
       262: aload         4
       264: new           #123                // class scala/Some
       267: dup
       268: aload         19
       270: invokespecial #126                // Method scala/Some."<init>":(Ljava/lang/Object;)V
       273: invokeinterface #121,  2          // InterfaceMethod scala/Function1.apply:(Ljava/lang/Object;)Ljava/lang/Object;
       278: checkcast     #22                 // class java/lang/Throwable
       281: athrow
       282: aload         19
       284: athrow
       285: areturn
      Exception table:
         from    to  target type
            53   199   202   Class java/lang/Throwable
      StackMapTable: number_of_entries = 14
        frame_type = 255 /* full_frame */
          offset_delta = 129
          locals = [ class org/scalatest/enablers/Timed$$anon$1, class org/scalatest/time/Span, class scala/Function0, class org/scalatest/concurrent/Signaler, class scala/Function1, top, class org/scalatest/Timer, class org/scalatest/concurrent/SignalerTimeoutTask, long, long, class java/lang/Object, long, class java/lang/Object, class org/scalatest/Outcome, class scala/Option ]
          stack = []
        frame_type = 249 /* chop */
          offset_delta = 2
        frame_type = 2 /* same */
        frame_type = 18 /* same */
        frame_type = 16 /* same */
        frame_type = 66 /* same_locals_1_stack_item */
          stack = [ class java/lang/Object ]
        frame_type = 14 /* same */
        frame_type = 255 /* full_frame */
          offset_delta = 7
          locals = [ class org/scalatest/enablers/Timed$$anon$1, class org/scalatest/time/Span, class scala/Function0, class org/scalatest/concurrent/Signaler, class scala/Function1, class scala/runtime/BoxedUnit, class org/scalatest/Timer, class org/scalatest/concurrent/SignalerTimeoutTask, long, long, class java/lang/Object, long, class java/lang/Object ]
          stack = []
        frame_type = 255 /* full_frame */
          offset_delta = 4
          locals = [ class org/scalatest/enablers/Timed$$anon$1, class org/scalatest/time/Span, class scala/Function0, class org/scalatest/concurrent/Signaler, class scala/Function1, top, class org/scalatest/Timer, class org/scalatest/concurrent/SignalerTimeoutTask, long, long ]
          stack = [ class java/lang/Throwable ]
        frame_type = 255 /* full_frame */
          offset_delta = 38
          locals = [ class org/scalatest/enablers/Timed$$anon$1, class org/scalatest/time/Span, class scala/Function0, class org/scalatest/concurrent/Signaler, class scala/Function1, top, class org/scalatest/Timer, class org/scalatest/concurrent/SignalerTimeoutTask, long, long, top, top, top, top, top, top, top, class java/lang/Throwable, long ]
          stack = []
        frame_type = 16 /* same */
        frame_type = 66 /* same_locals_1_stack_item */
          stack = [ class java/lang/Object ]
        frame_type = 20 /* same */
        frame_type = 255 /* full_frame */
          offset_delta = 2
          locals = [ class org/scalatest/enablers/Timed$$anon$1, class org/scalatest/time/Span, class scala/Function0, class org/scalatest/concurrent/Signaler, class scala/Function1, class scala/runtime/BoxedUnit, class org/scalatest/Timer, class org/scalatest/concurrent/SignalerTimeoutTask, long, long, class java/lang/Object, long, class java/lang/Object ]
          stack = [ class java/lang/Object ]
      LineNumberTable:
        line 121: 0
        line 122: 9
        line 123: 22
        line 124: 36
        line 125: 45
        line 127: 53
        line 128: 61
        line 129: 69
        line 130: 74
        line 131: 79
        line 132: 83
        line 131: 116
        line 132: 126
        line 134: 135
        line 135: 154
        line 136: 162
        line 135: 171
        line 137: 175
        line 134: 189
        line 140: 197
        line 144: 204
        line 145: 212
        line 146: 217
        line 147: 222
        line 148: 241
        line 149: 249
        line 148: 258
        line 150: 262
        line 153: 282
      LocalVariableTable:
        Start  Length  Slot  Name   Signature
          126       3    18    ex   Ljava/lang/Throwable;
           61     138    12 result   Ljava/lang/Object;
           69     130    13 endTime   J
          212      73    20 endTime   J
          202      83    19     t   Ljava/lang/Throwable;
            9     276     6 timer   Lorg/scalatest/Timer;
           22     263     7  task   Lorg/scalatest/concurrent/SignalerTimeoutTask;
           36     249     8 maxDuration   J
           53     232    10 startTime   J
            0     286     0  this   Lorg/scalatest/enablers/Timed$$anon$1;
            0     286     1 timeout   Lorg/scalatest/time/Span;
            0     286     2     f   Lscala/Function0;
            0     286     3 signaler   Lorg/scalatest/concurrent/Signaler;
            0     286     4 exceptionFun   Lscala/Function1;
    Signature: #16                          // (Lorg/scalatest/time/Span;Lscala/Function0<TT;>;Lorg/scalatest/concurrent/Signaler;Lscala/Function1<Lscala/Option<Ljava/lang/Throwable;>;Lorg/scalatest/exceptions/StackDepthException;>;)TT;
    MethodParameters:
      Name                           Flags
      timeout                        final
      f                              final
      signaler                       final
      exceptionFun                   final

  public org.scalatest.enablers.Timed$$anon$1();
    descriptor: ()V
    flags: (0x0001) ACC_PUBLIC
    Code:
      stack=1, locals=1, args_size=1
         0: aload_0
         1: invokespecial #148                // Method java/lang/Object."<init>":()V
         4: return
      LineNumberTable:
        line 114: 0
      LocalVariableTable:
        Start  Length  Slot  Name   Signature
            0       5     0  this   Lorg/scalatest/enablers/Timed$$anon$1;
}
InnerClasses:
  public final #2;                        // class org/scalatest/enablers/Timed$$anon$1
EnclosingMethod: #10.#13                // org.scalatest.enablers.Timed$.timed
Signature: #3                           // Ljava/lang/Object;Lorg/scalatest/enablers/Timed<TT;>;
SourceFile: "Timed.scala"
  ScalaInlineInfo: length = 0xE (unknown attribute)
   01 01 00 02 00 19 00 1A 01 00 0E 00 0F 01
  Scala: length = 0x0 (unknown attribute)

