Classfile /Users/mw/Projects/slang-braindump/.jar/jar8/assemble/slang-braindump/assemble/content/org/scalatest/enablers/ValueMapping$.class
  Last modified May 29, 2022; size 1682 bytes
  SHA-256 checksum 0ca04704a679db0149da03590aa96afffecade8d29ae8033932e68de3221bc42
  Compiled from "ValueMapping.scala"
public final class org.scalatest.enablers.ValueMapping$
  minor version: 0
  major version: 52
  flags: (0x0031) ACC_PUBLIC, ACC_FINAL, ACC_SUPER
  this_class: #2                          // org/scalatest/enablers/ValueMapping$
  super_class: #4                         // java/lang/Object
  interfaces: 0, fields: 1, methods: 6, attributes: 4
Constant pool:
   #1 = Utf8               org/scalatest/enablers/ValueMapping$
   #2 = Class              #1             // org/scalatest/enablers/ValueMapping$
   #3 = Utf8               java/lang/Object
   #4 = Class              #3             // java/lang/Object
   #5 = Utf8               ValueMapping.scala
   #6 = Utf8               org/scalatest/enablers/ValueMapping$$anon$1
   #7 = Class              #6             // org/scalatest/enablers/ValueMapping$$anon$1
   #8 = Utf8               org/scalatest/enablers/ValueMapping$$anon$2
   #9 = Class              #8             // org/scalatest/enablers/ValueMapping$$anon$2
  #10 = Utf8               MODULE$
  #11 = Utf8               Lorg/scalatest/enablers/ValueMapping$;
  #12 = Utf8               <clinit>
  #13 = Utf8               ()V
  #14 = Utf8               <init>
  #15 = NameAndType        #14:#13        // "<init>":()V
  #16 = Methodref          #2.#15         // org/scalatest/enablers/ValueMapping$."<init>":()V
  #17 = NameAndType        #10:#11        // MODULE$:Lorg/scalatest/enablers/ValueMapping$;
  #18 = Fieldref           #2.#17         // org/scalatest/enablers/ValueMapping$.MODULE$:Lorg/scalatest/enablers/ValueMapping$;
  #19 = Utf8               valueMappingNatureOfGenMap
  #20 = Utf8               (Lorg/scalactic/Equality;)Lorg/scalatest/enablers/ValueMapping;
  #21 = Utf8               <K:Ljava/lang/Object;V:Ljava/lang/Object;MAP::Lscala/collection/Map<Ljava/lang/Object;Ljava/lang/Object;>;>(Lorg/scalactic/Equality<TV;>;)Lorg/scalatest/enablers/ValueMapping<TMAP;>;
  #22 = Utf8               equality
  #23 = Utf8               (Lorg/scalactic/Equality;)V
  #24 = NameAndType        #14:#23        // "<init>":(Lorg/scalactic/Equality;)V
  #25 = Methodref          #7.#24         // org/scalatest/enablers/ValueMapping$$anon$1."<init>":(Lorg/scalactic/Equality;)V
  #26 = Utf8               this
  #27 = Utf8               Lorg/scalactic/Equality;
  #28 = Utf8               convertEqualityToGenMapValueMapping
  #29 = NameAndType        #19:#20        // valueMappingNatureOfGenMap:(Lorg/scalactic/Equality;)Lorg/scalatest/enablers/ValueMapping;
  #30 = Methodref          #2.#29         // org/scalatest/enablers/ValueMapping$.valueMappingNatureOfGenMap:(Lorg/scalactic/Equality;)Lorg/scalatest/enablers/ValueMapping;
  #31 = Utf8               valueMappingNatureOfJavaMap
  #32 = Utf8               <K:Ljava/lang/Object;V:Ljava/lang/Object;JMAP::Ljava/util/Map<Ljava/lang/Object;Ljava/lang/Object;>;>(Lorg/scalactic/Equality<TV;>;)Lorg/scalatest/enablers/ValueMapping<TJMAP;>;
  #33 = Methodref          #9.#24         // org/scalatest/enablers/ValueMapping$$anon$2."<init>":(Lorg/scalactic/Equality;)V
  #34 = Utf8               convertEqualityToJavaMapValueMapping
  #35 = NameAndType        #31:#20        // valueMappingNatureOfJavaMap:(Lorg/scalactic/Equality;)Lorg/scalatest/enablers/ValueMapping;
  #36 = Methodref          #2.#35         // org/scalatest/enablers/ValueMapping$.valueMappingNatureOfJavaMap:(Lorg/scalactic/Equality;)Lorg/scalatest/enablers/ValueMapping;
  #37 = Methodref          #4.#15         // java/lang/Object."<init>":()V
  #38 = Utf8               Code
  #39 = Utf8               LineNumberTable
  #40 = Utf8               LocalVariableTable
  #41 = Utf8               Signature
  #42 = Utf8               MethodParameters
  #43 = Utf8               InnerClasses
  #44 = Utf8               SourceFile
  #45 = Utf8               ScalaInlineInfo
  #46 = Utf8               Scala
{
  public static final org.scalatest.enablers.ValueMapping$ MODULE$;
    descriptor: Lorg/scalatest/enablers/ValueMapping$;
    flags: (0x0019) ACC_PUBLIC, ACC_STATIC, ACC_FINAL

  public static {};
    descriptor: ()V
    flags: (0x0009) ACC_PUBLIC, ACC_STATIC
    Code:
      stack=2, locals=0, args_size=0
         0: new           #2                  // class org/scalatest/enablers/ValueMapping$
         3: dup
         4: invokespecial #16                 // Method "<init>":()V
         7: putstatic     #18                 // Field MODULE$:Lorg/scalatest/enablers/ValueMapping$;
        10: return
      LineNumberTable:
        line 63: 0

  public <K extends java.lang.Object, V extends java.lang.Object, MAP extends scala.collection.Map<java.lang.Object, java.lang.Object>> org.scalatest.enablers.ValueMapping<MAP> valueMappingNatureOfGenMap(org.scalactic.Equality<V>);
    descriptor: (Lorg/scalactic/Equality;)Lorg/scalatest/enablers/ValueMapping;
    flags: (0x0001) ACC_PUBLIC
    Code:
      stack=3, locals=2, args_size=2
         0: new           #7                  // class org/scalatest/enablers/ValueMapping$$anon$1
         3: dup
         4: aload_1
         5: invokespecial #25                 // Method org/scalatest/enablers/ValueMapping$$anon$1."<init>":(Lorg/scalactic/Equality;)V
         8: areturn
      LineNumberTable:
        line 77: 0
      LocalVariableTable:
        Start  Length  Slot  Name   Signature
            0       9     0  this   Lorg/scalatest/enablers/ValueMapping$;
            0       9     1 equality   Lorg/scalactic/Equality;
    Signature: #21                          // <K:Ljava/lang/Object;V:Ljava/lang/Object;MAP::Lscala/collection/Map<Ljava/lang/Object;Ljava/lang/Object;>;>(Lorg/scalactic/Equality<TV;>;)Lorg/scalatest/enablers/ValueMapping<TMAP;>;
    MethodParameters:
      Name                           Flags
      equality                       final

  public <K extends java.lang.Object, V extends java.lang.Object, MAP extends scala.collection.Map<java.lang.Object, java.lang.Object>> org.scalatest.enablers.ValueMapping<MAP> convertEqualityToGenMapValueMapping(org.scalactic.Equality<V>);
    descriptor: (Lorg/scalactic/Equality;)Lorg/scalatest/enablers/ValueMapping;
    flags: (0x0001) ACC_PUBLIC
    Code:
      stack=2, locals=2, args_size=2
         0: aload_0
         1: aload_1
         2: invokevirtual #30                 // Method valueMappingNatureOfGenMap:(Lorg/scalactic/Equality;)Lorg/scalatest/enablers/ValueMapping;
         5: areturn
      LineNumberTable:
        line 105: 0
      LocalVariableTable:
        Start  Length  Slot  Name   Signature
            0       6     0  this   Lorg/scalatest/enablers/ValueMapping$;
            0       6     1 equality   Lorg/scalactic/Equality;
    Signature: #21                          // <K:Ljava/lang/Object;V:Ljava/lang/Object;MAP::Lscala/collection/Map<Ljava/lang/Object;Ljava/lang/Object;>;>(Lorg/scalactic/Equality<TV;>;)Lorg/scalatest/enablers/ValueMapping<TMAP;>;
    MethodParameters:
      Name                           Flags
      equality                       final

  public <K extends java.lang.Object, V extends java.lang.Object, JMAP extends java.util.Map<java.lang.Object, java.lang.Object>> org.scalatest.enablers.ValueMapping<JMAP> valueMappingNatureOfJavaMap(org.scalactic.Equality<V>);
    descriptor: (Lorg/scalactic/Equality;)Lorg/scalatest/enablers/ValueMapping;
    flags: (0x0001) ACC_PUBLIC
    Code:
      stack=3, locals=2, args_size=2
         0: new           #9                  // class org/scalatest/enablers/ValueMapping$$anon$2
         3: dup
         4: aload_1
         5: invokespecial #33                 // Method org/scalatest/enablers/ValueMapping$$anon$2."<init>":(Lorg/scalactic/Equality;)V
         8: areturn
      LineNumberTable:
        line 117: 0
      LocalVariableTable:
        Start  Length  Slot  Name   Signature
            0       9     0  this   Lorg/scalatest/enablers/ValueMapping$;
            0       9     1 equality   Lorg/scalactic/Equality;
    Signature: #32                          // <K:Ljava/lang/Object;V:Ljava/lang/Object;JMAP::Ljava/util/Map<Ljava/lang/Object;Ljava/lang/Object;>;>(Lorg/scalactic/Equality<TV;>;)Lorg/scalatest/enablers/ValueMapping<TJMAP;>;
    MethodParameters:
      Name                           Flags
      equality                       final

  public <K extends java.lang.Object, V extends java.lang.Object, JMAP extends java.util.Map<java.lang.Object, java.lang.Object>> org.scalatest.enablers.ValueMapping<JMAP> convertEqualityToJavaMapValueMapping(org.scalactic.Equality<V>);
    descriptor: (Lorg/scalactic/Equality;)Lorg/scalatest/enablers/ValueMapping;
    flags: (0x0001) ACC_PUBLIC
    Code:
      stack=2, locals=2, args_size=2
         0: aload_0
         1: aload_1
         2: invokevirtual #36                 // Method valueMappingNatureOfJavaMap:(Lorg/scalactic/Equality;)Lorg/scalatest/enablers/ValueMapping;
         5: areturn
      LineNumberTable:
        line 144: 0
      LocalVariableTable:
        Start  Length  Slot  Name   Signature
            0       6     0  this   Lorg/scalatest/enablers/ValueMapping$;
            0       6     1 equality   Lorg/scalactic/Equality;
    Signature: #32                          // <K:Ljava/lang/Object;V:Ljava/lang/Object;JMAP::Ljava/util/Map<Ljava/lang/Object;Ljava/lang/Object;>;>(Lorg/scalactic/Equality<TV;>;)Lorg/scalatest/enablers/ValueMapping<TJMAP;>;
    MethodParameters:
      Name                           Flags
      equality                       final

  private org.scalatest.enablers.ValueMapping$();
    descriptor: ()V
    flags: (0x0002) ACC_PRIVATE
    Code:
      stack=1, locals=1, args_size=1
         0: aload_0
         1: invokespecial #37                 // Method java/lang/Object."<init>":()V
         4: return
      LineNumberTable:
        line 145: 0
        line 63: 4
      LocalVariableTable:
        Start  Length  Slot  Name   Signature
            0       5     0  this   Lorg/scalatest/enablers/ValueMapping$;
}
InnerClasses:
  public final #7;                        // class org/scalatest/enablers/ValueMapping$$anon$1
  public final #9;                        // class org/scalatest/enablers/ValueMapping$$anon$2
SourceFile: "ValueMapping.scala"
  ScalaInlineInfo: length = 0x1D (unknown attribute)
   01 01 00 05 00 0E 00 0D 01 00 1C 00 14 01 00 22
   00 14 01 00 13 00 14 01 00 1F 00 14 01
  Scala: length = 0x0 (unknown attribute)

