Classfile /Users/mw/Projects/slang-braindump/.jar/jar8/assemble/slang-braindump/assemble/content/org/scalatest/matchers/dsl/EndWithWord.class
  Last modified May 29, 2022; size 2986 bytes
  SHA-256 checksum 55a41b0ee0180cce154be60498063fc9fa4ed3db96314efa5a13bc41c9ca7c1c
  Compiled from "EndWithWord.scala"
public final class org.scalatest.matchers.dsl.EndWithWord
  minor version: 0
  major version: 52
  flags: (0x0031) ACC_PUBLIC, ACC_FINAL, ACC_SUPER
  this_class: #2                          // org/scalatest/matchers/dsl/EndWithWord
  super_class: #4                         // java/lang/Object
  interfaces: 0, fields: 0, methods: 6, attributes: 5
Constant pool:
   #1 = Utf8               org/scalatest/matchers/dsl/EndWithWord
   #2 = Class              #1             // org/scalatest/matchers/dsl/EndWithWord
   #3 = Utf8               java/lang/Object
   #4 = Class              #3             // java/lang/Object
   #5 = Utf8               EndWithWord.scala
   #6 = Utf8               Lscala/reflect/ScalaSignature;
   #7 = Utf8               bytes
   #8 = Utf8               \u0006\u0005I3Aa\u0002\u0005\u0003#!)\u0001\u0004\u0001C\u00013!)A\u0004\u0001C\u0001;!)q\u0006\u0001C\u0001a!)q\u0006\u0001C\u0001y!)q\u0006\u0001C\u0001\u000b\")\u0001\u000b\u0001C!#\nYQI\u001c3XSRDwk\u001c:e\u0015\tI!\"A\u0002eg2T!a\u0003\u0007\u0002\u00115\fGo\u00195feNT!!\u0004\b\u0002\u0013M\u001c\u0017\r\\1uKN$(\"A\b\u0002\u0007=\u0014xm\u0001\u0001\u0014\u0005\u0001\u0011\u0002CA\n\u0017\u001b\u0005!\"\"A\u000b\u0002\u000bM\u001c\u0017\r\\1\n\u0005]!\"AB!osJ+g-\u0001\u0004=S:LGO\u0010\u000b\u00025A\u00111\u0004A\u0007\u0002\u0011\u0005)\u0011\r\u001d9msR\u0011a$\f\t\u0004?\u0001\u0012S\"\u0001\u0006\n\u0005\u0005R!aB\'bi\u000eDWM\u001d\t\u0003G)r!\u0001\n\u0015\u0011\u0005\u0015\"R\"\u0001\u0014\u000b\u0005\u001d\u0002\u0012A\u0002\u001fs_>$h(\u0003\u0002*)\u00051\u0001K]3eK\u001aL!a\u000b\u0017\u0003\rM#(/\u001b8h\u0015\tIC\u0003C\u0003/\u0005\u0001\u0007!%A\u0003sS\u001eDG/A\u0003sK\u001e,\u00070\u0006\u00022kQ\u0011!g\u000f\t\u0004?\u0001\u001a\u0004C\u0001\u001b6\u0019\u0001!QAN\u0002C\u0002]\u0012\u0011\u0001V\t\u0003q\t\u0002\"aE\u001d\n\u0005i\"\"a\u0002(pi\"Lgn\u001a\u0005\u0006]\r\u0001\ra\r\u000b\u0003{\u0001\u00132A\u0010\n\u001f\r\u0011yD\u0001A\u001f\u0003\u0019q\u0012XMZ5oK6,g\u000e\u001e \t\u000b\u0005#\u0001\u0019\u0001\"\u0002\u001fI,w-\u001a=XSRDwI]8vaN\u0004\"aG\"\n\u0005\u0011C!a\u0004*fO\u0016Dx+\u001b;i\u000fJ|W\u000f]:\u0015\u0005y1\u0005\"B$\u0006\u0001\u0004A\u0015A\u0003:jO\"$(+Z4fqB\u0011\u0011JT\u0007\u0002\u0015*\u00111\nT\u0001\t[\u0006$8\r[5oO*\u0011Q\nF\u0001\u0005kRLG.\u0003\u0002P\u0015\n)!+Z4fq\u0006AAo\\*ue&tw\rF\u0001#\u0001
   #9 = Utf8               org/scalatest/matchers/dsl/EndWithWord$$anon$1
  #10 = Class              #9             // org/scalatest/matchers/dsl/EndWithWord$$anon$1
  #11 = Utf8               org/scalatest/matchers/dsl/EndWithWord$$anon$2
  #12 = Class              #11            // org/scalatest/matchers/dsl/EndWithWord$$anon$2
  #13 = Utf8               org/scalatest/matchers/dsl/EndWithWord$$anon$3
  #14 = Class              #13            // org/scalatest/matchers/dsl/EndWithWord$$anon$3
  #15 = Utf8               apply
  #16 = Utf8               (Ljava/lang/String;)Lorg/scalatest/matchers/Matcher;
  #17 = Utf8               (Ljava/lang/String;)Lorg/scalatest/matchers/Matcher<Ljava/lang/String;>;
  #18 = Utf8               right
  #19 = Utf8               <init>
  #20 = Utf8               (Lorg/scalatest/matchers/dsl/EndWithWord;Ljava/lang/String;)V
  #21 = NameAndType        #19:#20        // "<init>":(Lorg/scalatest/matchers/dsl/EndWithWord;Ljava/lang/String;)V
  #22 = Methodref          #10.#21        // org/scalatest/matchers/dsl/EndWithWord$$anon$1."<init>":(Lorg/scalatest/matchers/dsl/EndWithWord;Ljava/lang/String;)V
  #23 = Utf8               this
  #24 = Utf8               Lorg/scalatest/matchers/dsl/EndWithWord;
  #25 = Utf8               Ljava/lang/String;
  #26 = Utf8               regex
  #27 = Utf8               <T:Ljava/lang/String;>(TT;)Lorg/scalatest/matchers/Matcher<TT;>;
  #28 = Utf8               scala/collection/StringOps$
  #29 = Class              #28            // scala/collection/StringOps$
  #30 = Utf8               MODULE$
  #31 = Utf8               Lscala/collection/StringOps$;
  #32 = NameAndType        #30:#31        // MODULE$:Lscala/collection/StringOps$;
  #33 = Fieldref           #29.#32        // scala/collection/StringOps$.MODULE$:Lscala/collection/StringOps$;
  #34 = Utf8               scala/Predef$
  #35 = Class              #34            // scala/Predef$
  #36 = Utf8               Lscala/Predef$;
  #37 = NameAndType        #30:#36        // MODULE$:Lscala/Predef$;
  #38 = Fieldref           #35.#37        // scala/Predef$.MODULE$:Lscala/Predef$;
  #39 = Utf8               augmentString
  #40 = Utf8               (Ljava/lang/String;)Ljava/lang/String;
  #41 = NameAndType        #39:#40        // augmentString:(Ljava/lang/String;)Ljava/lang/String;
  #42 = Methodref          #35.#41        // scala/Predef$.augmentString:(Ljava/lang/String;)Ljava/lang/String;
  #43 = Utf8               r$extension
  #44 = Utf8               (Ljava/lang/String;)Lscala/util/matching/Regex;
  #45 = NameAndType        #43:#44        // r$extension:(Ljava/lang/String;)Lscala/util/matching/Regex;
  #46 = Methodref          #29.#45        // scala/collection/StringOps$.r$extension:(Ljava/lang/String;)Lscala/util/matching/Regex;
  #47 = Utf8               (Lscala/util/matching/Regex;)Lorg/scalatest/matchers/Matcher;
  #48 = NameAndType        #26:#47        // regex:(Lscala/util/matching/Regex;)Lorg/scalatest/matchers/Matcher;
  #49 = Methodref          #2.#48         // org/scalatest/matchers/dsl/EndWithWord.regex:(Lscala/util/matching/Regex;)Lorg/scalatest/matchers/Matcher;
  #50 = Utf8               (Lorg/scalatest/matchers/dsl/RegexWithGroups;)Lorg/scalatest/matchers/Matcher;
  #51 = Utf8               (Lorg/scalatest/matchers/dsl/RegexWithGroups;)Lorg/scalatest/matchers/Matcher<Ljava/lang/String;>;
  #52 = Utf8               regexWithGroups
  #53 = Utf8               (Lorg/scalatest/matchers/dsl/EndWithWord;Lorg/scalatest/matchers/dsl/RegexWithGroups;)V
  #54 = NameAndType        #19:#53        // "<init>":(Lorg/scalatest/matchers/dsl/EndWithWord;Lorg/scalatest/matchers/dsl/RegexWithGroups;)V
  #55 = Methodref          #12.#54        // org/scalatest/matchers/dsl/EndWithWord$$anon$2."<init>":(Lorg/scalatest/matchers/dsl/EndWithWord;Lorg/scalatest/matchers/dsl/RegexWithGroups;)V
  #56 = Utf8               Lorg/scalatest/matchers/dsl/RegexWithGroups;
  #57 = Utf8               (Lscala/util/matching/Regex;)Lorg/scalatest/matchers/Matcher<Ljava/lang/String;>;
  #58 = Utf8               rightRegex
  #59 = Utf8               (Lorg/scalatest/matchers/dsl/EndWithWord;Lscala/util/matching/Regex;)V
  #60 = NameAndType        #19:#59        // "<init>":(Lorg/scalatest/matchers/dsl/EndWithWord;Lscala/util/matching/Regex;)V
  #61 = Methodref          #14.#60        // org/scalatest/matchers/dsl/EndWithWord$$anon$3."<init>":(Lorg/scalatest/matchers/dsl/EndWithWord;Lscala/util/matching/Regex;)V
  #62 = Utf8               Lscala/util/matching/Regex;
  #63 = Utf8               toString
  #64 = Utf8               ()Ljava/lang/String;
  #65 = Utf8               endWith
  #66 = String             #65            // endWith
  #67 = Utf8               ()V
  #68 = NameAndType        #19:#67        // "<init>":()V
  #69 = Methodref          #4.#68         // java/lang/Object."<init>":()V
  #70 = Utf8               Code
  #71 = Utf8               LineNumberTable
  #72 = Utf8               LocalVariableTable
  #73 = Utf8               Signature
  #74 = Utf8               MethodParameters
  #75 = Utf8               InnerClasses
  #76 = Utf8               SourceFile
  #77 = Utf8               RuntimeVisibleAnnotations
  #78 = Utf8               ScalaInlineInfo
  #79 = Utf8               ScalaSig
{
  public org.scalatest.matchers.Matcher<java.lang.String> apply(java.lang.String);
    descriptor: (Ljava/lang/String;)Lorg/scalatest/matchers/Matcher;
    flags: (0x0001) ACC_PUBLIC
    Code:
      stack=4, locals=2, args_size=2
         0: new           #10                 // class org/scalatest/matchers/dsl/EndWithWord$$anon$1
         3: dup
         4: aconst_null
         5: aload_1
         6: invokespecial #22                 // Method org/scalatest/matchers/dsl/EndWithWord$$anon$1."<init>":(Lorg/scalatest/matchers/dsl/EndWithWord;Ljava/lang/String;)V
         9: areturn
      LineNumberTable:
        line 43: 0
      LocalVariableTable:
        Start  Length  Slot  Name   Signature
            0      10     0  this   Lorg/scalatest/matchers/dsl/EndWithWord;
            0      10     1 right   Ljava/lang/String;
    Signature: #17                          // (Ljava/lang/String;)Lorg/scalatest/matchers/Matcher<Ljava/lang/String;>;
    MethodParameters:
      Name                           Flags
      right                          final

  public <T extends java.lang.String> org.scalatest.matchers.Matcher<T> regex(T);
    descriptor: (Ljava/lang/String;)Lorg/scalatest/matchers/Matcher;
    flags: (0x0001) ACC_PUBLIC
    Code:
      stack=4, locals=2, args_size=2
         0: aload_0
         1: getstatic     #33                 // Field scala/collection/StringOps$.MODULE$:Lscala/collection/StringOps$;
         4: getstatic     #38                 // Field scala/Predef$.MODULE$:Lscala/Predef$;
         7: aload_1
         8: invokevirtual #42                 // Method scala/Predef$.augmentString:(Ljava/lang/String;)Ljava/lang/String;
        11: invokevirtual #46                 // Method scala/collection/StringOps$.r$extension:(Ljava/lang/String;)Lscala/util/matching/Regex;
        14: invokevirtual #49                 // Method regex:(Lscala/util/matching/Regex;)Lorg/scalatest/matchers/Matcher;
        17: areturn
      LineNumberTable:
        line 63: 0
      LocalVariableTable:
        Start  Length  Slot  Name   Signature
            0      18     0  this   Lorg/scalatest/matchers/dsl/EndWithWord;
            0      18     1 right   Ljava/lang/String;
    Signature: #27                          // <T:Ljava/lang/String;>(TT;)Lorg/scalatest/matchers/Matcher<TT;>;
    MethodParameters:
      Name                           Flags
      right                          final

  public org.scalatest.matchers.Matcher<java.lang.String> regex(org.scalatest.matchers.dsl.RegexWithGroups);
    descriptor: (Lorg/scalatest/matchers/dsl/RegexWithGroups;)Lorg/scalatest/matchers/Matcher;
    flags: (0x0001) ACC_PUBLIC
    Code:
      stack=4, locals=2, args_size=2
         0: new           #12                 // class org/scalatest/matchers/dsl/EndWithWord$$anon$2
         3: dup
         4: aconst_null
         5: aload_1
         6: invokespecial #55                 // Method org/scalatest/matchers/dsl/EndWithWord$$anon$2."<init>":(Lorg/scalatest/matchers/dsl/EndWithWord;Lorg/scalatest/matchers/dsl/RegexWithGroups;)V
         9: areturn
      LineNumberTable:
        line 74: 0
      LocalVariableTable:
        Start  Length  Slot  Name   Signature
            0      10     0  this   Lorg/scalatest/matchers/dsl/EndWithWord;
            0      10     1 regexWithGroups   Lorg/scalatest/matchers/dsl/RegexWithGroups;
    Signature: #51                          // (Lorg/scalatest/matchers/dsl/RegexWithGroups;)Lorg/scalatest/matchers/Matcher<Ljava/lang/String;>;
    MethodParameters:
      Name                           Flags
      regexWithGroups                final

  public org.scalatest.matchers.Matcher<java.lang.String> regex(scala.util.matching.Regex);
    descriptor: (Lscala/util/matching/Regex;)Lorg/scalatest/matchers/Matcher;
    flags: (0x0001) ACC_PUBLIC
    Code:
      stack=4, locals=2, args_size=2
         0: new           #14                 // class org/scalatest/matchers/dsl/EndWithWord$$anon$3
         3: dup
         4: aconst_null
         5: aload_1
         6: invokespecial #61                 // Method org/scalatest/matchers/dsl/EndWithWord$$anon$3."<init>":(Lorg/scalatest/matchers/dsl/EndWithWord;Lscala/util/matching/Regex;)V
         9: areturn
      LineNumberTable:
        line 90: 0
      LocalVariableTable:
        Start  Length  Slot  Name   Signature
            0      10     0  this   Lorg/scalatest/matchers/dsl/EndWithWord;
            0      10     1 rightRegex   Lscala/util/matching/Regex;
    Signature: #57                          // (Lscala/util/matching/Regex;)Lorg/scalatest/matchers/Matcher<Ljava/lang/String;>;
    MethodParameters:
      Name                           Flags
      rightRegex                     final

  public java.lang.String toString();
    descriptor: ()Ljava/lang/String;
    flags: (0x0001) ACC_PUBLIC
    Code:
      stack=1, locals=1, args_size=1
         0: ldc           #66                 // String endWith
         2: areturn
      LineNumberTable:
        line 106: 0
      LocalVariableTable:
        Start  Length  Slot  Name   Signature
            0       3     0  this   Lorg/scalatest/matchers/dsl/EndWithWord;

  public org.scalatest.matchers.dsl.EndWithWord();
    descriptor: ()V
    flags: (0x0001) ACC_PUBLIC
    Code:
      stack=1, locals=1, args_size=1
         0: aload_0
         1: invokespecial #69                 // Method java/lang/Object."<init>":()V
         4: return
      LineNumberTable:
        line 107: 0
        line 32: 4
      LocalVariableTable:
        Start  Length  Slot  Name   Signature
            0       5     0  this   Lorg/scalatest/matchers/dsl/EndWithWord;
}
InnerClasses:
  public final #10;                       // class org/scalatest/matchers/dsl/EndWithWord$$anon$1
  public final #12;                       // class org/scalatest/matchers/dsl/EndWithWord$$anon$2
  public final #14;                       // class org/scalatest/matchers/dsl/EndWithWord$$anon$3
SourceFile: "EndWithWord.scala"
RuntimeVisibleAnnotations:
  0: #6(#7=s#8)
    scala.reflect.ScalaSignature(
      bytes="\u0006\u0005I3Aa\u0002\u0005\u0003#!)\u0001\u0004\u0001C\u00013!)A\u0004\u0001C\u0001;!)q\u0006\u0001C\u0001a!)q\u0006\u0001C\u0001y!)q\u0006\u0001C\u0001\u000b\")\u0001\u000b\u0001C!#\nYQI\u001c3XSRDwk\u001c:e\u0015\tI!\"A\u0002eg2T!a\u0003\u0007\u0002\u00115\fGo\u00195feNT!!\u0004\b\u0002\u0013M\u001c\u0017\r\\1uKN$(\"A\b\u0002\u0007=\u0014xm\u0001\u0001\u0014\u0005\u0001\u0011\u0002CA\n\u0017\u001b\u0005!\"\"A\u000b\u0002\u000bM\u001c\u0017\r\\1\n\u0005]!\"AB!osJ+g-\u0001\u0004=S:LGO\u0010\u000b\u00025A\u00111\u0004A\u0007\u0002\u0011\u0005)\u0011\r\u001d9msR\u0011a$\f\t\u0004?\u0001\u0012S\"\u0001\u0006\n\u0005\u0005R!aB\'bi\u000eDWM\u001d\t\u0003G)r!\u0001\n\u0015\u0011\u0005\u0015\"R\"\u0001\u0014\u000b\u0005\u001d\u0002\u0012A\u0002\u001fs_>$h(\u0003\u0002*)\u00051\u0001K]3eK\u001aL!a\u000b\u0017\u0003\rM#(/\u001b8h\u0015\tIC\u0003C\u0003/\u0005\u0001\u0007!%A\u0003sS\u001eDG/A\u0003sK\u001e,\u00070\u0006\u00022kQ\u0011!g\u000f\t\u0004?\u0001\u001a\u0004C\u0001\u001b6\u0019\u0001!QAN\u0002C\u0002]\u0012\u0011\u0001V\t\u0003q\t\u0002\"aE\u001d\n\u0005i\"\"a\u0002(pi\"Lgn\u001a\u0005\u0006]\r\u0001\ra\r\u000b\u0003{\u0001\u00132A\u0010\n\u001f\r\u0011yD\u0001A\u001f\u0003\u0019q\u0012XMZ5oK6,g\u000e\u001e \t\u000b\u0005#\u0001\u0019\u0001\"\u0002\u001fI,w-\u001a=XSRDwI]8vaN\u0004\"aG\"\n\u0005\u0011C!a\u0004*fO\u0016Dx+\u001b;i\u000fJ|W\u000f]:\u0015\u0005y1\u0005\"B$\u0006\u0001\u0004A\u0015A\u0003:jO\"$(+Z4fqB\u0011\u0011JT\u0007\u0002\u0015*\u00111\nT\u0001\t[\u0006$8\r[5oO*\u0011Q\nF\u0001\u0005kRLG.\u0003\u0002P\u0015\n)!+Z4fq\u0006AAo\\*ue&tw\rF\u0001#\u0001"
    )
  ScalaInlineInfo: length = 0x22 (unknown attribute)
   01 01 00 06 00 13 00 43 01 00 0F 00 10 01 00 1A
   00 10 01 00 1A 00 32 01 00 1A 00 2F 01 00 3F 00
   40 01
  ScalaSig: length = 0x3 (unknown attribute)
   05 02 00
