Classfile /Users/mw/Projects/slang-braindump/.jar/jar8/assemble/slang-braindump/assemble/content/org/scalatest/matchers/dsl/HaveWord.class
  Last modified May 29, 2022; size 4667 bytes
  SHA-256 checksum 524999dd6b12f72c8d1ad6e3b5fd1c8bfe39f8fb5624f4d8ba3e763448c67000
  Compiled from "HaveWord.scala"
public final class org.scalatest.matchers.dsl.HaveWord
  minor version: 0
  major version: 52
  flags: (0x0031) ACC_PUBLIC, ACC_FINAL, ACC_SUPER
  this_class: #2                          // org/scalatest/matchers/dsl/HaveWord
  super_class: #4                         // java/lang/Object
  interfaces: 0, fields: 0, methods: 8, attributes: 5
Constant pool:
   #1 = Utf8               org/scalatest/matchers/dsl/HaveWord
   #2 = Class              #1             // org/scalatest/matchers/dsl/HaveWord
   #3 = Utf8               java/lang/Object
   #4 = Class              #3             // java/lang/Object
   #5 = Utf8               HaveWord.scala
   #6 = Utf8               Lscala/reflect/ScalaSignature;
   #7 = Utf8               bytes
   #8 = Utf8               \u0006\u0005\u0005-a\u0001B\u0005\u000b\u0005MAQA\u0007\u0001\u0005\u0002mAQA\b\u0001\u0005\u0002}AQ!\r\u0001\u0005\u0002IBQ!\u000f\u0001\u0005\u0002iBQ\u0001\u0014\u0001\u0005\u00025CQ\u0001\u0014\u0001\u0005\u0002iCQ\u0001\u0014\u0001\u0005\u0002\tDq!a\u0002\u0001\t\u0003\nIA\u0001\u0005ICZ,wk\u001c:e\u0015\tYA\"A\u0002eg2T!!\u0004\b\u0002\u00115\fGo\u00195feNT!a\u0004\t\u0002\u0013M\u001c\u0017\r\\1uKN$(\"A\t\u0002\u0007=\u0014xm\u0001\u0001\u0014\u0005\u0001!\u0002CA\u000b\u0019\u001b\u00051\"\"A\f\u0002\u000bM\u001c\u0017\r\\1\n\u0005e1\"AB!osJ+g-\u0001\u0004=S:LGO\u0010\u000b\u00029A\u0011Q\u0004A\u0007\u0002\u0015\u00051A.\u001a8hi\"$\"\u0001\t\u0017\u0011\tu\t3EJ\u0005\u0003E)\u0011q\"T1uG\",\'OR1di>\u0014\u00180\r\t\u0003+\u0011J!!\n\f\u0003\u0007\u0005s\u0017\u0010\u0005\u0002(U5\t\u0001F\u0003\u0002*\u001d\u0005AQM\\1cY\u0016\u00148/\u0003\u0002,Q\t1A*\u001a8hi\"DQ!\f\u0002A\u00029\na\"\u001a=qK\u000e$X\r\u001a\'f]\u001e$\b\u000e\u0005\u0002\u0016_%\u0011\u0001G\u0006\u0002\u0005\u0019>tw-\u0001\u0003tSj,GCA\u001a8!\u0011i\u0012e\t\u001b\u0011\u0005\u001d*\u0014B\u0001\u001c)\u0005\u0011\u0019\u0016N_3\t\u000ba\u001a\u0001\u0019\u0001\u0018\u0002\u0019\u0015D\b/Z2uK\u0012\u001c\u0016N_3\u0002\u000f5,7o]1hKR\u00111h\u0010\t\u0005;\u0005\u001aC\b\u0005\u0002({%\u0011a\b\u000b\u0002\n\u001b\u0016\u001c8/Y4j]\u001eDQ\u0001\u0011\u0003A\u0002\u0005\u000bq\"\u001a=qK\u000e$X\rZ\'fgN\fw-\u001a\t\u0003\u0005&s!aQ$\u0011\u0005\u00113R\"A#\u000b\u0005\u0019\u0013\u0012A\u0002\u001fs_>$h(\u0003\u0002I-\u00051\u0001K]3eK\u001aL!AS&\u0003\rM#(/\u001b8h\u0015\tAe#A\u0003baBd\u00170\u0006\u0002O)R\u0011\u0001e\u0014\u0005\u0006!\u0016\u0001\r!U\u0001\u001ee\u0016\u001cX\u000f\u001c;PM2+gn\u001a;i/>\u0014H-\u00119qY&\u001c\u0017\r^5p]B\u0011QDU\u0005\u0003\'*\u0011QDU3tk2$xJ\u001a\'f]\u001e$\bnV8sI\u0006\u0003\b\u000f\\5dCRLwN\u001c\u0003\u0006+\u0016\u0011\rA\u0016\u0002\u0002)F\u0011qk\t\t\u0003+aK!!\u0017\f\u0003\u000f9{G\u000f[5oOV\u00111,\u0019\u000b\u0003gqCQ!\u0018\u0004A\u0002y\u000b1D]3tk2$xJZ*ju\u0016<vN\u001d3BaBd\u0017nY1uS>t\u0007CA\u000f`\u0013\t\u0001\'BA\u000eSKN,H\u000e^(g\'&TXmV8sI\u0006\u0003\b\u000f\\5dCRLwN\u001c\u0003\u0006+\u001a\u0011\rAV\u000b\u0003G*$2\u0001Z6u!\r)g\r[\u0007\u0002\u0019%\u0011q\r\u0004\u0002\b\u001b\u0006$8\r[3s!\tI\'\u000e\u0004\u0001\u0005\u000bU;!\u0019\u0001,\t\u000b1<\u0001\u0019A7\u0002)\u0019L\'o\u001d;Qe>\u0004XM\u001d;z\u001b\u0006$8\r[3sa\tq\'\u000f\u0005\u0003f_\"\f\u0018B\u00019\r\u0005MA\u0015M^3Qe>\u0004XM\u001d;z\u001b\u0006$8\r[3s!\tI\'\u000fB\u0005tW\u0006\u0005\t\u0011!B\u0001-\n\u0019q\fJ\u0019\t\u000bU<\u0001\u0019\u0001<\u0002!A\u0014x\u000e]3sifl\u0015\r^2iKJ\u001c\bcA\u000bxs&\u0011\u0001P\u0006\u0002\u000byI,\u0007/Z1uK\u0012t\u0004G\u0001>}!\u0011)w\u000e[>\u0011\u0005%dH!C?\u007f\u0003\u0003\u0005\tQ!\u0001W\u0005\ryFE\r\u0005\u0006k\u001e\u0001\ra \t\u0005+]\f\t\u0001M\u0002\u0002\u0004q\u0004R!Z8\u0002\u0006m\u0004\"!\u001b6\u0002\u0011Q|7\u000b\u001e:j]\u001e$\u0012!\u0011
   #9 = Utf8               org/scalatest/matchers/dsl/HaveWord$$anon$1
  #10 = Class              #9             // org/scalatest/matchers/dsl/HaveWord$$anon$1
  #11 = Utf8               org/scalatest/matchers/dsl/HaveWord$$anon$3
  #12 = Class              #11            // org/scalatest/matchers/dsl/HaveWord$$anon$3
  #13 = Utf8               org/scalatest/matchers/dsl/HaveWord$$anon$5
  #14 = Class              #13            // org/scalatest/matchers/dsl/HaveWord$$anon$5
  #15 = Utf8               org/scalatest/matchers/dsl/HaveWord$$anon$7
  #16 = Class              #15            // org/scalatest/matchers/dsl/HaveWord$$anon$7
  #17 = Utf8               length
  #18 = Utf8               (J)Lorg/scalatest/matchers/dsl/MatcherFactory1;
  #19 = Utf8               (J)Lorg/scalatest/matchers/dsl/MatcherFactory1<Ljava/lang/Object;Lorg/scalatest/enablers/Length;>;
  #20 = Utf8               expectedLength
  #21 = Utf8               <init>
  #22 = Utf8               (Lorg/scalatest/matchers/dsl/HaveWord;J)V
  #23 = NameAndType        #21:#22        // "<init>":(Lorg/scalatest/matchers/dsl/HaveWord;J)V
  #24 = Methodref          #10.#23        // org/scalatest/matchers/dsl/HaveWord$$anon$1."<init>":(Lorg/scalatest/matchers/dsl/HaveWord;J)V
  #25 = Utf8               this
  #26 = Utf8               Lorg/scalatest/matchers/dsl/HaveWord;
  #27 = Utf8               J
  #28 = Utf8               size
  #29 = Utf8               (J)Lorg/scalatest/matchers/dsl/MatcherFactory1<Ljava/lang/Object;Lorg/scalatest/enablers/Size;>;
  #30 = Utf8               expectedSize
  #31 = Methodref          #12.#23        // org/scalatest/matchers/dsl/HaveWord$$anon$3."<init>":(Lorg/scalatest/matchers/dsl/HaveWord;J)V
  #32 = Utf8               message
  #33 = Utf8               (Ljava/lang/String;)Lorg/scalatest/matchers/dsl/MatcherFactory1;
  #34 = Utf8               (Ljava/lang/String;)Lorg/scalatest/matchers/dsl/MatcherFactory1<Ljava/lang/Object;Lorg/scalatest/enablers/Messaging;>;
  #35 = Utf8               expectedMessage
  #36 = Utf8               (Lorg/scalatest/matchers/dsl/HaveWord;Ljava/lang/String;)V
  #37 = NameAndType        #21:#36        // "<init>":(Lorg/scalatest/matchers/dsl/HaveWord;Ljava/lang/String;)V
  #38 = Methodref          #14.#37        // org/scalatest/matchers/dsl/HaveWord$$anon$5."<init>":(Lorg/scalatest/matchers/dsl/HaveWord;Ljava/lang/String;)V
  #39 = Utf8               Ljava/lang/String;
  #40 = Utf8               apply
  #41 = Utf8               (Lorg/scalatest/matchers/dsl/ResultOfLengthWordApplication;)Lorg/scalatest/matchers/dsl/MatcherFactory1;
  #42 = Utf8               <T:Ljava/lang/Object;>(Lorg/scalatest/matchers/dsl/ResultOfLengthWordApplication;)Lorg/scalatest/matchers/dsl/MatcherFactory1<Ljava/lang/Object;Lorg/scalatest/enablers/Length;>;
  #43 = Utf8               resultOfLengthWordApplication
  #44 = Utf8               org/scalatest/matchers/dsl/ResultOfLengthWordApplication
  #45 = Class              #44            // org/scalatest/matchers/dsl/ResultOfLengthWordApplication
  #46 = Utf8               ()J
  #47 = NameAndType        #20:#46        // expectedLength:()J
  #48 = Methodref          #45.#47        // org/scalatest/matchers/dsl/ResultOfLengthWordApplication.expectedLength:()J
  #49 = NameAndType        #17:#18        // length:(J)Lorg/scalatest/matchers/dsl/MatcherFactory1;
  #50 = Methodref          #2.#49         // org/scalatest/matchers/dsl/HaveWord.length:(J)Lorg/scalatest/matchers/dsl/MatcherFactory1;
  #51 = Utf8               Lorg/scalatest/matchers/dsl/ResultOfLengthWordApplication;
  #52 = Utf8               (Lorg/scalatest/matchers/dsl/ResultOfSizeWordApplication;)Lorg/scalatest/matchers/dsl/MatcherFactory1;
  #53 = Utf8               <T:Ljava/lang/Object;>(Lorg/scalatest/matchers/dsl/ResultOfSizeWordApplication;)Lorg/scalatest/matchers/dsl/MatcherFactory1<Ljava/lang/Object;Lorg/scalatest/enablers/Size;>;
  #54 = Utf8               resultOfSizeWordApplication
  #55 = Utf8               org/scalatest/matchers/dsl/ResultOfSizeWordApplication
  #56 = Class              #55            // org/scalatest/matchers/dsl/ResultOfSizeWordApplication
  #57 = NameAndType        #30:#46        // expectedSize:()J
  #58 = Methodref          #56.#57        // org/scalatest/matchers/dsl/ResultOfSizeWordApplication.expectedSize:()J
  #59 = NameAndType        #28:#18        // size:(J)Lorg/scalatest/matchers/dsl/MatcherFactory1;
  #60 = Methodref          #2.#59         // org/scalatest/matchers/dsl/HaveWord.size:(J)Lorg/scalatest/matchers/dsl/MatcherFactory1;
  #61 = Utf8               Lorg/scalatest/matchers/dsl/ResultOfSizeWordApplication;
  #62 = Utf8               (Lorg/scalatest/matchers/HavePropertyMatcher;Lscala/collection/immutable/Seq;)Lorg/scalatest/matchers/Matcher;
  #63 = Utf8               <T:Ljava/lang/Object;>(Lorg/scalatest/matchers/HavePropertyMatcher<TT;*>;Lscala/collection/immutable/Seq<Lorg/scalatest/matchers/HavePropertyMatcher<TT;*>;>;)Lorg/scalatest/matchers/Matcher<TT;>;
  #64 = Utf8               firstPropertyMatcher
  #65 = Utf8               propertyMatchers
  #66 = Utf8               (Lorg/scalatest/matchers/dsl/HaveWord;Lorg/scalatest/matchers/HavePropertyMatcher;Lscala/collection/immutable/Seq;)V
  #67 = NameAndType        #21:#66        // "<init>":(Lorg/scalatest/matchers/dsl/HaveWord;Lorg/scalatest/matchers/HavePropertyMatcher;Lscala/collection/immutable/Seq;)V
  #68 = Methodref          #16.#67        // org/scalatest/matchers/dsl/HaveWord$$anon$7."<init>":(Lorg/scalatest/matchers/dsl/HaveWord;Lorg/scalatest/matchers/HavePropertyMatcher;Lscala/collection/immutable/Seq;)V
  #69 = Utf8               Lorg/scalatest/matchers/HavePropertyMatcher;
  #70 = Utf8               Lscala/collection/immutable/Seq;
  #71 = Utf8               toString
  #72 = Utf8               ()Ljava/lang/String;
  #73 = Utf8               have
  #74 = String             #73            // have
  #75 = Utf8               ()V
  #76 = NameAndType        #21:#75        // "<init>":()V
  #77 = Methodref          #4.#76         // java/lang/Object."<init>":()V
  #78 = Utf8               Code
  #79 = Utf8               LineNumberTable
  #80 = Utf8               LocalVariableTable
  #81 = Utf8               Signature
  #82 = Utf8               MethodParameters
  #83 = Utf8               InnerClasses
  #84 = Utf8               SourceFile
  #85 = Utf8               RuntimeVisibleAnnotations
  #86 = Utf8               ScalaInlineInfo
  #87 = Utf8               ScalaSig
{
  public org.scalatest.matchers.dsl.MatcherFactory1<java.lang.Object, org.scalatest.enablers.Length> length(long);
    descriptor: (J)Lorg/scalatest/matchers/dsl/MatcherFactory1;
    flags: (0x0001) ACC_PUBLIC
    Code:
      stack=5, locals=3, args_size=2
         0: new           #10                 // class org/scalatest/matchers/dsl/HaveWord$$anon$1
         3: dup
         4: aconst_null
         5: lload_1
         6: invokespecial #24                 // Method org/scalatest/matchers/dsl/HaveWord$$anon$1."<init>":(Lorg/scalatest/matchers/dsl/HaveWord;J)V
         9: areturn
      LineNumberTable:
        line 44: 0
      LocalVariableTable:
        Start  Length  Slot  Name   Signature
            0      10     0  this   Lorg/scalatest/matchers/dsl/HaveWord;
            0      10     1 expectedLength   J
    Signature: #19                          // (J)Lorg/scalatest/matchers/dsl/MatcherFactory1<Ljava/lang/Object;Lorg/scalatest/enablers/Length;>;
    MethodParameters:
      Name                           Flags
      expectedLength                 final

  public org.scalatest.matchers.dsl.MatcherFactory1<java.lang.Object, org.scalatest.enablers.Size> size(long);
    descriptor: (J)Lorg/scalatest/matchers/dsl/MatcherFactory1;
    flags: (0x0001) ACC_PUBLIC
    Code:
      stack=5, locals=3, args_size=2
         0: new           #12                 // class org/scalatest/matchers/dsl/HaveWord$$anon$3
         3: dup
         4: aconst_null
         5: lload_1
         6: invokespecial #31                 // Method org/scalatest/matchers/dsl/HaveWord$$anon$3."<init>":(Lorg/scalatest/matchers/dsl/HaveWord;J)V
         9: areturn
      LineNumberTable:
        line 80: 0
      LocalVariableTable:
        Start  Length  Slot  Name   Signature
            0      10     0  this   Lorg/scalatest/matchers/dsl/HaveWord;
            0      10     1 expectedSize   J
    Signature: #29                          // (J)Lorg/scalatest/matchers/dsl/MatcherFactory1<Ljava/lang/Object;Lorg/scalatest/enablers/Size;>;
    MethodParameters:
      Name                           Flags
      expectedSize                   final

  public org.scalatest.matchers.dsl.MatcherFactory1<java.lang.Object, org.scalatest.enablers.Messaging> message(java.lang.String);
    descriptor: (Ljava/lang/String;)Lorg/scalatest/matchers/dsl/MatcherFactory1;
    flags: (0x0001) ACC_PUBLIC
    Code:
      stack=4, locals=2, args_size=2
         0: new           #14                 // class org/scalatest/matchers/dsl/HaveWord$$anon$5
         3: dup
         4: aconst_null
         5: aload_1
         6: invokespecial #38                 // Method org/scalatest/matchers/dsl/HaveWord$$anon$5."<init>":(Lorg/scalatest/matchers/dsl/HaveWord;Ljava/lang/String;)V
         9: areturn
      LineNumberTable:
        line 109: 0
      LocalVariableTable:
        Start  Length  Slot  Name   Signature
            0      10     0  this   Lorg/scalatest/matchers/dsl/HaveWord;
            0      10     1 expectedMessage   Ljava/lang/String;
    Signature: #34                          // (Ljava/lang/String;)Lorg/scalatest/matchers/dsl/MatcherFactory1<Ljava/lang/Object;Lorg/scalatest/enablers/Messaging;>;
    MethodParameters:
      Name                           Flags
      expectedMessage                final

  public <T extends java.lang.Object> org.scalatest.matchers.dsl.MatcherFactory1<java.lang.Object, org.scalatest.enablers.Length> apply(org.scalatest.matchers.dsl.ResultOfLengthWordApplication);
    descriptor: (Lorg/scalatest/matchers/dsl/ResultOfLengthWordApplication;)Lorg/scalatest/matchers/dsl/MatcherFactory1;
    flags: (0x0001) ACC_PUBLIC
    Code:
      stack=3, locals=2, args_size=2
         0: aload_0
         1: aload_1
         2: invokevirtual #48                 // Method org/scalatest/matchers/dsl/ResultOfLengthWordApplication.expectedLength:()J
         5: invokevirtual #50                 // Method length:(J)Lorg/scalatest/matchers/dsl/MatcherFactory1;
         8: areturn
      LineNumberTable:
        line 132: 0
      LocalVariableTable:
        Start  Length  Slot  Name   Signature
            0       9     0  this   Lorg/scalatest/matchers/dsl/HaveWord;
            0       9     1 resultOfLengthWordApplication   Lorg/scalatest/matchers/dsl/ResultOfLengthWordApplication;
    Signature: #42                          // <T:Ljava/lang/Object;>(Lorg/scalatest/matchers/dsl/ResultOfLengthWordApplication;)Lorg/scalatest/matchers/dsl/MatcherFactory1<Ljava/lang/Object;Lorg/scalatest/enablers/Length;>;
    MethodParameters:
      Name                           Flags
      resultOfLengthWordApplication  final

  public <T extends java.lang.Object> org.scalatest.matchers.dsl.MatcherFactory1<java.lang.Object, org.scalatest.enablers.Size> apply(org.scalatest.matchers.dsl.ResultOfSizeWordApplication);
    descriptor: (Lorg/scalatest/matchers/dsl/ResultOfSizeWordApplication;)Lorg/scalatest/matchers/dsl/MatcherFactory1;
    flags: (0x0001) ACC_PUBLIC
    Code:
      stack=3, locals=2, args_size=2
         0: aload_0
         1: aload_1
         2: invokevirtual #58                 // Method org/scalatest/matchers/dsl/ResultOfSizeWordApplication.expectedSize:()J
         5: invokevirtual #60                 // Method size:(J)Lorg/scalatest/matchers/dsl/MatcherFactory1;
         8: areturn
      LineNumberTable:
        line 138: 0
      LocalVariableTable:
        Start  Length  Slot  Name   Signature
            0       9     0  this   Lorg/scalatest/matchers/dsl/HaveWord;
            0       9     1 resultOfSizeWordApplication   Lorg/scalatest/matchers/dsl/ResultOfSizeWordApplication;
    Signature: #53                          // <T:Ljava/lang/Object;>(Lorg/scalatest/matchers/dsl/ResultOfSizeWordApplication;)Lorg/scalatest/matchers/dsl/MatcherFactory1<Ljava/lang/Object;Lorg/scalatest/enablers/Size;>;
    MethodParameters:
      Name                           Flags
      resultOfSizeWordApplication    final

  public <T extends java.lang.Object> org.scalatest.matchers.Matcher<T> apply(org.scalatest.matchers.HavePropertyMatcher<T, ?>, scala.collection.immutable.Seq<org.scalatest.matchers.HavePropertyMatcher<T, ?>>);
    descriptor: (Lorg/scalatest/matchers/HavePropertyMatcher;Lscala/collection/immutable/Seq;)Lorg/scalatest/matchers/Matcher;
    flags: (0x0001) ACC_PUBLIC
    Code:
      stack=5, locals=3, args_size=3
         0: new           #16                 // class org/scalatest/matchers/dsl/HaveWord$$anon$7
         3: dup
         4: aconst_null
         5: aload_1
         6: aload_2
         7: invokespecial #68                 // Method org/scalatest/matchers/dsl/HaveWord$$anon$7."<init>":(Lorg/scalatest/matchers/dsl/HaveWord;Lorg/scalatest/matchers/HavePropertyMatcher;Lscala/collection/immutable/Seq;)V
        10: areturn
      LineNumberTable:
        line 150: 0
      LocalVariableTable:
        Start  Length  Slot  Name   Signature
            0      11     0  this   Lorg/scalatest/matchers/dsl/HaveWord;
            0      11     1 firstPropertyMatcher   Lorg/scalatest/matchers/HavePropertyMatcher;
            0      11     2 propertyMatchers   Lscala/collection/immutable/Seq;
    Signature: #63                          // <T:Ljava/lang/Object;>(Lorg/scalatest/matchers/HavePropertyMatcher<TT;*>;Lscala/collection/immutable/Seq<Lorg/scalatest/matchers/HavePropertyMatcher<TT;*>;>;)Lorg/scalatest/matchers/Matcher<TT;>;
    MethodParameters:
      Name                           Flags
      firstPropertyMatcher           final
      propertyMatchers               final

  public java.lang.String toString();
    descriptor: ()Ljava/lang/String;
    flags: (0x0001) ACC_PUBLIC
    Code:
      stack=1, locals=1, args_size=1
         0: ldc           #74                 // String have
         2: areturn
      LineNumberTable:
        line 230: 0
      LocalVariableTable:
        Start  Length  Slot  Name   Signature
            0       3     0  this   Lorg/scalatest/matchers/dsl/HaveWord;

  public org.scalatest.matchers.dsl.HaveWord();
    descriptor: ()V
    flags: (0x0001) ACC_PUBLIC
    Code:
      stack=1, locals=1, args_size=1
         0: aload_0
         1: invokespecial #77                 // Method java/lang/Object."<init>":()V
         4: return
      LineNumberTable:
        line 231: 0
        line 33: 4
      LocalVariableTable:
        Start  Length  Slot  Name   Signature
            0       5     0  this   Lorg/scalatest/matchers/dsl/HaveWord;
}
InnerClasses:
  public final #10;                       // class org/scalatest/matchers/dsl/HaveWord$$anon$1
  public final #12;                       // class org/scalatest/matchers/dsl/HaveWord$$anon$3
  public final #14;                       // class org/scalatest/matchers/dsl/HaveWord$$anon$5
  public final #16;                       // class org/scalatest/matchers/dsl/HaveWord$$anon$7
SourceFile: "HaveWord.scala"
RuntimeVisibleAnnotations:
  0: #6(#7=s#8)
    scala.reflect.ScalaSignature(
      bytes="\u0006\u0005\u0005-a\u0001B\u0005\u000b\u0005MAQA\u0007\u0001\u0005\u0002mAQA\b\u0001\u0005\u0002}AQ!\r\u0001\u0005\u0002IBQ!\u000f\u0001\u0005\u0002iBQ\u0001\u0014\u0001\u0005\u00025CQ\u0001\u0014\u0001\u0005\u0002iCQ\u0001\u0014\u0001\u0005\u0002\tDq!a\u0002\u0001\t\u0003\nIA\u0001\u0005ICZ,wk\u001c:e\u0015\tYA\"A\u0002eg2T!!\u0004\b\u0002\u00115\fGo\u00195feNT!a\u0004\t\u0002\u0013M\u001c\u0017\r\\1uKN$(\"A\t\u0002\u0007=\u0014xm\u0001\u0001\u0014\u0005\u0001!\u0002CA\u000b\u0019\u001b\u00051\"\"A\f\u0002\u000bM\u001c\u0017\r\\1\n\u0005e1\"AB!osJ+g-\u0001\u0004=S:LGO\u0010\u000b\u00029A\u0011Q\u0004A\u0007\u0002\u0015\u00051A.\u001a8hi\"$\"\u0001\t\u0017\u0011\tu\t3EJ\u0005\u0003E)\u0011q\"T1uG\",\'OR1di>\u0014\u00180\r\t\u0003+\u0011J!!\n\f\u0003\u0007\u0005s\u0017\u0010\u0005\u0002(U5\t\u0001F\u0003\u0002*\u001d\u0005AQM\\1cY\u0016\u00148/\u0003\u0002,Q\t1A*\u001a8hi\"DQ!\f\u0002A\u00029\na\"\u001a=qK\u000e$X\r\u001a\'f]\u001e$\b\u000e\u0005\u0002\u0016_%\u0011\u0001G\u0006\u0002\u0005\u0019>tw-\u0001\u0003tSj,GCA\u001a8!\u0011i\u0012e\t\u001b\u0011\u0005\u001d*\u0014B\u0001\u001c)\u0005\u0011\u0019\u0016N_3\t\u000ba\u001a\u0001\u0019\u0001\u0018\u0002\u0019\u0015D\b/Z2uK\u0012\u001c\u0016N_3\u0002\u000f5,7o]1hKR\u00111h\u0010\t\u0005;\u0005\u001aC\b\u0005\u0002({%\u0011a\b\u000b\u0002\n\u001b\u0016\u001c8/Y4j]\u001eDQ\u0001\u0011\u0003A\u0002\u0005\u000bq\"\u001a=qK\u000e$X\rZ\'fgN\fw-\u001a\t\u0003\u0005&s!aQ$\u0011\u0005\u00113R\"A#\u000b\u0005\u0019\u0013\u0012A\u0002\u001fs_>$h(\u0003\u0002I-\u00051\u0001K]3eK\u001aL!AS&\u0003\rM#(/\u001b8h\u0015\tAe#A\u0003baBd\u00170\u0006\u0002O)R\u0011\u0001e\u0014\u0005\u0006!\u0016\u0001\r!U\u0001\u001ee\u0016\u001cX\u000f\u001c;PM2+gn\u001a;i/>\u0014H-\u00119qY&\u001c\u0017\r^5p]B\u0011QDU\u0005\u0003\'*\u0011QDU3tk2$xJ\u001a\'f]\u001e$\bnV8sI\u0006\u0003\b\u000f\\5dCRLwN\u001c\u0003\u0006+\u0016\u0011\rA\u0016\u0002\u0002)F\u0011qk\t\t\u0003+aK!!\u0017\f\u0003\u000f9{G\u000f[5oOV\u00111,\u0019\u000b\u0003gqCQ!\u0018\u0004A\u0002y\u000b1D]3tk2$xJZ*ju\u0016<vN\u001d3BaBd\u0017nY1uS>t\u0007CA\u000f`\u0013\t\u0001\'BA\u000eSKN,H\u000e^(g\'&TXmV8sI\u0006\u0003\b\u000f\\5dCRLwN\u001c\u0003\u0006+\u001a\u0011\rAV\u000b\u0003G*$2\u0001Z6u!\r)g\r[\u0007\u0002\u0019%\u0011q\r\u0004\u0002\b\u001b\u0006$8\r[3s!\tI\'\u000e\u0004\u0001\u0005\u000bU;!\u0019\u0001,\t\u000b1<\u0001\u0019A7\u0002)\u0019L\'o\u001d;Qe>\u0004XM\u001d;z\u001b\u0006$8\r[3sa\tq\'\u000f\u0005\u0003f_\"\f\u0018B\u00019\r\u0005MA\u0015M^3Qe>\u0004XM\u001d;z\u001b\u0006$8\r[3s!\tI\'\u000fB\u0005tW\u0006\u0005\t\u0011!B\u0001-\n\u0019q\fJ\u0019\t\u000bU<\u0001\u0019\u0001<\u0002!A\u0014x\u000e]3sifl\u0015\r^2iKJ\u001c\bcA\u000bxs&\u0011\u0001P\u0006\u0002\u000byI,\u0007/Z1uK\u0012t\u0004G\u0001>}!\u0011)w\u000e[>\u0011\u0005%dH!C?\u007f\u0003\u0003\u0005\tQ!\u0001W\u0005\ryFE\r\u0005\u0006k\u001e\u0001\ra \t\u0005+]\f\t\u0001M\u0002\u0002\u0004q\u0004R!Z8\u0002\u0006m\u0004\"!\u001b6\u0002\u0011Q|7\u000b\u001e:j]\u001e$\u0012!\u0011"
    )
  ScalaInlineInfo: length = 0x2C (unknown attribute)
   01 01 00 08 00 15 00 4B 01 00 28 00 3E 01 00 28
   00 29 01 00 28 00 34 01 00 11 00 12 01 00 20 00
   21 01 00 1C 00 12 01 00 47 00 48 01
  ScalaSig: length = 0x3 (unknown attribute)
   05 02 00
