Classfile /Users/mw/Projects/slang-braindump/.jar/jar8/assemble/slang-braindump/assemble/content/org/scalatest/matchers/dsl/IncludeWord.class
  Last modified May 29, 2022; size 3034 bytes
  SHA-256 checksum 9ccfb96356b19a5517b335ef5f8f9062ad1dfc51424a2bd91f6abc5e8a352b03
  Compiled from "IncludeWord.scala"
public final class org.scalatest.matchers.dsl.IncludeWord
  minor version: 0
  major version: 52
  flags: (0x0031) ACC_PUBLIC, ACC_FINAL, ACC_SUPER
  this_class: #2                          // org/scalatest/matchers/dsl/IncludeWord
  super_class: #4                         // java/lang/Object
  interfaces: 0, fields: 0, methods: 6, attributes: 5
Constant pool:
   #1 = Utf8               org/scalatest/matchers/dsl/IncludeWord
   #2 = Class              #1             // org/scalatest/matchers/dsl/IncludeWord
   #3 = Utf8               java/lang/Object
   #4 = Class              #3             // java/lang/Object
   #5 = Utf8               IncludeWord.scala
   #6 = Utf8               Lscala/reflect/ScalaSignature;
   #7 = Utf8               bytes
   #8 = Utf8               \u0006\u0005M3Aa\u0002\u0005\u0003#!)\u0001\u0004\u0001C\u00013!)A\u0004\u0001C\u0001;!)q\u0006\u0001C\u0001a!)q\u0006\u0001C\u0001{!)q\u0006\u0001C\u0001\r\")\u0011\u000b\u0001C!%\nY\u0011J\\2mk\u0012,wk\u001c:e\u0015\tI!\"A\u0002eg2T!a\u0003\u0007\u0002\u00115\fGo\u00195feNT!!\u0004\b\u0002\u0013M\u001c\u0017\r\\1uKN$(\"A\b\u0002\u0007=\u0014xm\u0001\u0001\u0014\u0005\u0001\u0011\u0002CA\n\u0017\u001b\u0005!\"\"A\u000b\u0002\u000bM\u001c\u0017\r\\1\n\u0005]!\"AB!osJ+g-\u0001\u0004=S:LGO\u0010\u000b\u00025A\u00111\u0004A\u0007\u0002\u0011\u0005)\u0011\r\u001d9msR\u0011a$\f\t\u0004?\u0001\u0012S\"\u0001\u0006\n\u0005\u0005R!aB\'bi\u000eDWM\u001d\t\u0003G)r!\u0001\n\u0015\u0011\u0005\u0015\"R\"\u0001\u0014\u000b\u0005\u001d\u0002\u0012A\u0002\u001fs_>$h(\u0003\u0002*)\u00051\u0001K]3eK\u001aL!a\u000b\u0017\u0003\rM#(/\u001b8h\u0015\tIC\u0003C\u0003/\u0005\u0001\u0007!%A\tfqB,7\r^3e\'V\u00147\u000f\u001e:j]\u001e\fQA]3hKb,\"!M\u001b\u0015\u0005IZ\u0004cA\u0010!gA\u0011A\'\u000e\u0007\u0001\t\u001514A1\u00018\u0005\u0005!\u0016C\u0001\u001d#!\t\u0019\u0012(\u0003\u0002;)\t9aj\u001c;iS:<\u0007\"\u0002\u001f\u0004\u0001\u0004\u0019\u0014!\u0002:jO\"$HC\u0001 B%\ry$C\b\u0004\u0005\u0001\u0012\u0001aH\u0001\u0007=e\u00164\u0017N\\3nK:$h\bC\u0003C\t\u0001\u00071)A\bsK\u001e,\u0007pV5uQ\u001e\u0013x.\u001e9t!\tYB)\u0003\u0002F\u0011\ty!+Z4fq^KG\u000f[$s_V\u00048\u000f\u0006\u0002\u001f\u000f\")\u0001*\u0002a\u0001\u0013\u0006iQ\r\u001f9fGR,GMU3hKb\u0004\"AS(\u000e\u0003-S!\u0001T\'\u0002\u00115\fGo\u00195j]\u001eT!A\u0014\u000b\u0002\tU$\u0018\u000e\\\u0005\u0003!.\u0013QAU3hKb\f\u0001\u0002^8TiJLgn\u001a\u000b\u0002E\u0001
   #9 = Utf8               org/scalatest/matchers/dsl/IncludeWord$$anon$1
  #10 = Class              #9             // org/scalatest/matchers/dsl/IncludeWord$$anon$1
  #11 = Utf8               org/scalatest/matchers/dsl/IncludeWord$$anon$2
  #12 = Class              #11            // org/scalatest/matchers/dsl/IncludeWord$$anon$2
  #13 = Utf8               org/scalatest/matchers/dsl/IncludeWord$$anon$3
  #14 = Class              #13            // org/scalatest/matchers/dsl/IncludeWord$$anon$3
  #15 = Utf8               apply
  #16 = Utf8               (Ljava/lang/String;)Lorg/scalatest/matchers/Matcher;
  #17 = Utf8               (Ljava/lang/String;)Lorg/scalatest/matchers/Matcher<Ljava/lang/String;>;
  #18 = Utf8               expectedSubstring
  #19 = Utf8               <init>
  #20 = Utf8               (Lorg/scalatest/matchers/dsl/IncludeWord;Ljava/lang/String;)V
  #21 = NameAndType        #19:#20        // "<init>":(Lorg/scalatest/matchers/dsl/IncludeWord;Ljava/lang/String;)V
  #22 = Methodref          #10.#21        // org/scalatest/matchers/dsl/IncludeWord$$anon$1."<init>":(Lorg/scalatest/matchers/dsl/IncludeWord;Ljava/lang/String;)V
  #23 = Utf8               this
  #24 = Utf8               Lorg/scalatest/matchers/dsl/IncludeWord;
  #25 = Utf8               Ljava/lang/String;
  #26 = Utf8               regex
  #27 = Utf8               <T:Ljava/lang/String;>(TT;)Lorg/scalatest/matchers/Matcher<TT;>;
  #28 = Utf8               right
  #29 = Utf8               scala/collection/StringOps$
  #30 = Class              #29            // scala/collection/StringOps$
  #31 = Utf8               MODULE$
  #32 = Utf8               Lscala/collection/StringOps$;
  #33 = NameAndType        #31:#32        // MODULE$:Lscala/collection/StringOps$;
  #34 = Fieldref           #30.#33        // scala/collection/StringOps$.MODULE$:Lscala/collection/StringOps$;
  #35 = Utf8               scala/Predef$
  #36 = Class              #35            // scala/Predef$
  #37 = Utf8               Lscala/Predef$;
  #38 = NameAndType        #31:#37        // MODULE$:Lscala/Predef$;
  #39 = Fieldref           #36.#38        // scala/Predef$.MODULE$:Lscala/Predef$;
  #40 = Utf8               augmentString
  #41 = Utf8               (Ljava/lang/String;)Ljava/lang/String;
  #42 = NameAndType        #40:#41        // augmentString:(Ljava/lang/String;)Ljava/lang/String;
  #43 = Methodref          #36.#42        // scala/Predef$.augmentString:(Ljava/lang/String;)Ljava/lang/String;
  #44 = Utf8               r$extension
  #45 = Utf8               (Ljava/lang/String;)Lscala/util/matching/Regex;
  #46 = NameAndType        #44:#45        // r$extension:(Ljava/lang/String;)Lscala/util/matching/Regex;
  #47 = Methodref          #30.#46        // scala/collection/StringOps$.r$extension:(Ljava/lang/String;)Lscala/util/matching/Regex;
  #48 = Utf8               (Lscala/util/matching/Regex;)Lorg/scalatest/matchers/Matcher;
  #49 = NameAndType        #26:#48        // regex:(Lscala/util/matching/Regex;)Lorg/scalatest/matchers/Matcher;
  #50 = Methodref          #2.#49         // org/scalatest/matchers/dsl/IncludeWord.regex:(Lscala/util/matching/Regex;)Lorg/scalatest/matchers/Matcher;
  #51 = Utf8               (Lorg/scalatest/matchers/dsl/RegexWithGroups;)Lorg/scalatest/matchers/Matcher;
  #52 = Utf8               (Lorg/scalatest/matchers/dsl/RegexWithGroups;)Lorg/scalatest/matchers/Matcher<Ljava/lang/String;>;
  #53 = Utf8               regexWithGroups
  #54 = Utf8               (Lorg/scalatest/matchers/dsl/IncludeWord;Lorg/scalatest/matchers/dsl/RegexWithGroups;)V
  #55 = NameAndType        #19:#54        // "<init>":(Lorg/scalatest/matchers/dsl/IncludeWord;Lorg/scalatest/matchers/dsl/RegexWithGroups;)V
  #56 = Methodref          #12.#55        // org/scalatest/matchers/dsl/IncludeWord$$anon$2."<init>":(Lorg/scalatest/matchers/dsl/IncludeWord;Lorg/scalatest/matchers/dsl/RegexWithGroups;)V
  #57 = Utf8               Lorg/scalatest/matchers/dsl/RegexWithGroups;
  #58 = Utf8               (Lscala/util/matching/Regex;)Lorg/scalatest/matchers/Matcher<Ljava/lang/String;>;
  #59 = Utf8               expectedRegex
  #60 = Utf8               (Lorg/scalatest/matchers/dsl/IncludeWord;Lscala/util/matching/Regex;)V
  #61 = NameAndType        #19:#60        // "<init>":(Lorg/scalatest/matchers/dsl/IncludeWord;Lscala/util/matching/Regex;)V
  #62 = Methodref          #14.#61        // org/scalatest/matchers/dsl/IncludeWord$$anon$3."<init>":(Lorg/scalatest/matchers/dsl/IncludeWord;Lscala/util/matching/Regex;)V
  #63 = Utf8               Lscala/util/matching/Regex;
  #64 = Utf8               toString
  #65 = Utf8               ()Ljava/lang/String;
  #66 = Utf8               include
  #67 = String             #66            // include
  #68 = Utf8               ()V
  #69 = NameAndType        #19:#68        // "<init>":()V
  #70 = Methodref          #4.#69         // java/lang/Object."<init>":()V
  #71 = Utf8               Code
  #72 = Utf8               LineNumberTable
  #73 = Utf8               LocalVariableTable
  #74 = Utf8               Signature
  #75 = Utf8               MethodParameters
  #76 = Utf8               InnerClasses
  #77 = Utf8               SourceFile
  #78 = Utf8               RuntimeVisibleAnnotations
  #79 = Utf8               ScalaInlineInfo
  #80 = Utf8               ScalaSig
{
  public org.scalatest.matchers.Matcher<java.lang.String> apply(java.lang.String);
    descriptor: (Ljava/lang/String;)Lorg/scalatest/matchers/Matcher;
    flags: (0x0001) ACC_PUBLIC
    Code:
      stack=4, locals=2, args_size=2
         0: new           #10                 // class org/scalatest/matchers/dsl/IncludeWord$$anon$1
         3: dup
         4: aconst_null
         5: aload_1
         6: invokespecial #22                 // Method org/scalatest/matchers/dsl/IncludeWord$$anon$1."<init>":(Lorg/scalatest/matchers/dsl/IncludeWord;Ljava/lang/String;)V
         9: areturn
      LineNumberTable:
        line 42: 0
      LocalVariableTable:
        Start  Length  Slot  Name   Signature
            0      10     0  this   Lorg/scalatest/matchers/dsl/IncludeWord;
            0      10     1 expectedSubstring   Ljava/lang/String;
    Signature: #17                          // (Ljava/lang/String;)Lorg/scalatest/matchers/Matcher<Ljava/lang/String;>;
    MethodParameters:
      Name                           Flags
      expectedSubstring              final

  public <T extends java.lang.String> org.scalatest.matchers.Matcher<T> regex(T);
    descriptor: (Ljava/lang/String;)Lorg/scalatest/matchers/Matcher;
    flags: (0x0001) ACC_PUBLIC
    Code:
      stack=4, locals=2, args_size=2
         0: aload_0
         1: getstatic     #34                 // Field scala/collection/StringOps$.MODULE$:Lscala/collection/StringOps$;
         4: getstatic     #39                 // Field scala/Predef$.MODULE$:Lscala/Predef$;
         7: aload_1
         8: invokevirtual #43                 // Method scala/Predef$.augmentString:(Ljava/lang/String;)Ljava/lang/String;
        11: invokevirtual #47                 // Method scala/collection/StringOps$.r$extension:(Ljava/lang/String;)Lscala/util/matching/Regex;
        14: invokevirtual #50                 // Method regex:(Lscala/util/matching/Regex;)Lorg/scalatest/matchers/Matcher;
        17: areturn
      LineNumberTable:
        line 62: 0
      LocalVariableTable:
        Start  Length  Slot  Name   Signature
            0      18     0  this   Lorg/scalatest/matchers/dsl/IncludeWord;
            0      18     1 right   Ljava/lang/String;
    Signature: #27                          // <T:Ljava/lang/String;>(TT;)Lorg/scalatest/matchers/Matcher<TT;>;
    MethodParameters:
      Name                           Flags
      right                          final

  public org.scalatest.matchers.Matcher<java.lang.String> regex(org.scalatest.matchers.dsl.RegexWithGroups);
    descriptor: (Lorg/scalatest/matchers/dsl/RegexWithGroups;)Lorg/scalatest/matchers/Matcher;
    flags: (0x0001) ACC_PUBLIC
    Code:
      stack=4, locals=2, args_size=2
         0: new           #12                 // class org/scalatest/matchers/dsl/IncludeWord$$anon$2
         3: dup
         4: aconst_null
         5: aload_1
         6: invokespecial #56                 // Method org/scalatest/matchers/dsl/IncludeWord$$anon$2."<init>":(Lorg/scalatest/matchers/dsl/IncludeWord;Lorg/scalatest/matchers/dsl/RegexWithGroups;)V
         9: areturn
      LineNumberTable:
        line 73: 0
      LocalVariableTable:
        Start  Length  Slot  Name   Signature
            0      10     0  this   Lorg/scalatest/matchers/dsl/IncludeWord;
            0      10     1 regexWithGroups   Lorg/scalatest/matchers/dsl/RegexWithGroups;
    Signature: #52                          // (Lorg/scalatest/matchers/dsl/RegexWithGroups;)Lorg/scalatest/matchers/Matcher<Ljava/lang/String;>;
    MethodParameters:
      Name                           Flags
      regexWithGroups                final

  public org.scalatest.matchers.Matcher<java.lang.String> regex(scala.util.matching.Regex);
    descriptor: (Lscala/util/matching/Regex;)Lorg/scalatest/matchers/Matcher;
    flags: (0x0001) ACC_PUBLIC
    Code:
      stack=4, locals=2, args_size=2
         0: new           #14                 // class org/scalatest/matchers/dsl/IncludeWord$$anon$3
         3: dup
         4: aconst_null
         5: aload_1
         6: invokespecial #62                 // Method org/scalatest/matchers/dsl/IncludeWord$$anon$3."<init>":(Lorg/scalatest/matchers/dsl/IncludeWord;Lscala/util/matching/Regex;)V
         9: areturn
      LineNumberTable:
        line 89: 0
      LocalVariableTable:
        Start  Length  Slot  Name   Signature
            0      10     0  this   Lorg/scalatest/matchers/dsl/IncludeWord;
            0      10     1 expectedRegex   Lscala/util/matching/Regex;
    Signature: #58                          // (Lscala/util/matching/Regex;)Lorg/scalatest/matchers/Matcher<Ljava/lang/String;>;
    MethodParameters:
      Name                           Flags
      expectedRegex                  final

  public java.lang.String toString();
    descriptor: ()Ljava/lang/String;
    flags: (0x0001) ACC_PUBLIC
    Code:
      stack=1, locals=1, args_size=1
         0: ldc           #67                 // String include
         2: areturn
      LineNumberTable:
        line 103: 0
      LocalVariableTable:
        Start  Length  Slot  Name   Signature
            0       3     0  this   Lorg/scalatest/matchers/dsl/IncludeWord;

  public org.scalatest.matchers.dsl.IncludeWord();
    descriptor: ()V
    flags: (0x0001) ACC_PUBLIC
    Code:
      stack=1, locals=1, args_size=1
         0: aload_0
         1: invokespecial #70                 // Method java/lang/Object."<init>":()V
         4: return
      LineNumberTable:
        line 104: 0
        line 31: 4
      LocalVariableTable:
        Start  Length  Slot  Name   Signature
            0       5     0  this   Lorg/scalatest/matchers/dsl/IncludeWord;
}
InnerClasses:
  public final #10;                       // class org/scalatest/matchers/dsl/IncludeWord$$anon$1
  public final #12;                       // class org/scalatest/matchers/dsl/IncludeWord$$anon$2
  public final #14;                       // class org/scalatest/matchers/dsl/IncludeWord$$anon$3
SourceFile: "IncludeWord.scala"
RuntimeVisibleAnnotations:
  0: #6(#7=s#8)
    scala.reflect.ScalaSignature(
      bytes="\u0006\u0005M3Aa\u0002\u0005\u0003#!)\u0001\u0004\u0001C\u00013!)A\u0004\u0001C\u0001;!)q\u0006\u0001C\u0001a!)q\u0006\u0001C\u0001{!)q\u0006\u0001C\u0001\r\")\u0011\u000b\u0001C!%\nY\u0011J\\2mk\u0012,wk\u001c:e\u0015\tI!\"A\u0002eg2T!a\u0003\u0007\u0002\u00115\fGo\u00195feNT!!\u0004\b\u0002\u0013M\u001c\u0017\r\\1uKN$(\"A\b\u0002\u0007=\u0014xm\u0001\u0001\u0014\u0005\u0001\u0011\u0002CA\n\u0017\u001b\u0005!\"\"A\u000b\u0002\u000bM\u001c\u0017\r\\1\n\u0005]!\"AB!osJ+g-\u0001\u0004=S:LGO\u0010\u000b\u00025A\u00111\u0004A\u0007\u0002\u0011\u0005)\u0011\r\u001d9msR\u0011a$\f\t\u0004?\u0001\u0012S\"\u0001\u0006\n\u0005\u0005R!aB\'bi\u000eDWM\u001d\t\u0003G)r!\u0001\n\u0015\u0011\u0005\u0015\"R\"\u0001\u0014\u000b\u0005\u001d\u0002\u0012A\u0002\u001fs_>$h(\u0003\u0002*)\u00051\u0001K]3eK\u001aL!a\u000b\u0017\u0003\rM#(/\u001b8h\u0015\tIC\u0003C\u0003/\u0005\u0001\u0007!%A\tfqB,7\r^3e\'V\u00147\u000f\u001e:j]\u001e\fQA]3hKb,\"!M\u001b\u0015\u0005IZ\u0004cA\u0010!gA\u0011A\'\u000e\u0007\u0001\t\u001514A1\u00018\u0005\u0005!\u0016C\u0001\u001d#!\t\u0019\u0012(\u0003\u0002;)\t9aj\u001c;iS:<\u0007\"\u0002\u001f\u0004\u0001\u0004\u0019\u0014!\u0002:jO\"$HC\u0001 B%\ry$C\b\u0004\u0005\u0001\u0012\u0001aH\u0001\u0007=e\u00164\u0017N\\3nK:$h\bC\u0003C\t\u0001\u00071)A\bsK\u001e,\u0007pV5uQ\u001e\u0013x.\u001e9t!\tYB)\u0003\u0002F\u0011\ty!+Z4fq^KG\u000f[$s_V\u00048\u000f\u0006\u0002\u001f\u000f\")\u0001*\u0002a\u0001\u0013\u0006iQ\r\u001f9fGR,GMU3hKb\u0004\"AS(\u000e\u0003-S!\u0001T\'\u0002\u00115\fGo\u00195j]\u001eT!A\u0014\u000b\u0002\tU$\u0018\u000e\\\u0005\u0003!.\u0013QAU3hKb\f\u0001\u0002^8TiJLgn\u001a\u000b\u0002E\u0001"
    )
  ScalaInlineInfo: length = 0x22 (unknown attribute)
   01 01 00 06 00 13 00 44 01 00 0F 00 10 01 00 1A
   00 10 01 00 1A 00 33 01 00 1A 00 30 01 00 40 00
   41 01
  ScalaSig: length = 0x3 (unknown attribute)
   05 02 00
