Classfile /Users/mw/Projects/slang-braindump/.jar/jar8/assemble/slang-braindump/assemble/content/org/scalatest/matchers/dsl/MatcherWords$$anon$1.class
  Last modified May 29, 2022; size 2228 bytes
  SHA-256 checksum d8e263f3994e02fd36a089b9b14c686e586dc750d8a716511937df926ca3ede2
  Compiled from "MatcherWords.scala"
public final class org.scalatest.matchers.dsl.MatcherWords$$anon$1 extends org.scalatest.matchers.dsl.MatcherFactory1<java.lang.Object, org.scalactic.Equality>
  minor version: 0
  major version: 52
  flags: (0x0031) ACC_PUBLIC, ACC_FINAL, ACC_SUPER
  this_class: #2                          // org/scalatest/matchers/dsl/MatcherWords$$anon$1
  super_class: #5                         // org/scalatest/matchers/dsl/MatcherFactory1
  interfaces: 0, fields: 1, methods: 4, attributes: 6
Constant pool:
   #1 = Utf8               org/scalatest/matchers/dsl/MatcherWords$$anon$1
   #2 = Class              #1             // org/scalatest/matchers/dsl/MatcherWords$$anon$1
   #3 = Utf8               Lorg/scalatest/matchers/dsl/MatcherFactory1<Ljava/lang/Object;Lorg/scalactic/Equality;>;
   #4 = Utf8               org/scalatest/matchers/dsl/MatcherFactory1
   #5 = Class              #4             // org/scalatest/matchers/dsl/MatcherFactory1
   #6 = Utf8               MatcherWords.scala
   #7 = Utf8               org/scalatest/matchers/dsl/MatcherWords
   #8 = Class              #7             // org/scalatest/matchers/dsl/MatcherWords
   #9 = Utf8               equal
  #10 = Utf8               (Ljava/lang/Object;)Lorg/scalatest/matchers/dsl/MatcherFactory1;
  #11 = NameAndType        #9:#10         // equal:(Ljava/lang/Object;)Lorg/scalatest/matchers/dsl/MatcherFactory1;
  #12 = Utf8               org/scalatest/matchers/dsl/MatcherWords$$anon$1$$anon$2
  #13 = Class              #12            // org/scalatest/matchers/dsl/MatcherWords$$anon$1$$anon$2
  #14 = Utf8               right$1
  #15 = Utf8               Ljava/lang/Object;
  #16 = Utf8               matcher
  #17 = Utf8               (Lorg/scalactic/Equality;)Lorg/scalatest/matchers/Matcher;
  #18 = Utf8               <T:Ljava/lang/Object;>(Lorg/scalactic/Equality<TT;>;)Lorg/scalatest/matchers/Matcher<TT;>;
  #19 = Utf8               evidence$1
  #20 = Utf8               scala/Predef$
  #21 = Class              #20            // scala/Predef$
  #22 = Utf8               MODULE$
  #23 = Utf8               Lscala/Predef$;
  #24 = NameAndType        #22:#23        // MODULE$:Lscala/Predef$;
  #25 = Fieldref           #21.#24        // scala/Predef$.MODULE$:Lscala/Predef$;
  #26 = Utf8               implicitly
  #27 = Utf8               (Ljava/lang/Object;)Ljava/lang/Object;
  #28 = NameAndType        #26:#27        // implicitly:(Ljava/lang/Object;)Ljava/lang/Object;
  #29 = Methodref          #21.#28        // scala/Predef$.implicitly:(Ljava/lang/Object;)Ljava/lang/Object;
  #30 = Utf8               org/scalactic/Equality
  #31 = Class              #30            // org/scalactic/Equality
  #32 = Utf8               <init>
  #33 = Utf8               (Lorg/scalatest/matchers/dsl/MatcherWords$$anon$1;Lorg/scalactic/Equality;)V
  #34 = NameAndType        #32:#33        // "<init>":(Lorg/scalatest/matchers/dsl/MatcherWords$$anon$1;Lorg/scalactic/Equality;)V
  #35 = Methodref          #13.#34        // org/scalatest/matchers/dsl/MatcherWords$$anon$1$$anon$2."<init>":(Lorg/scalatest/matchers/dsl/MatcherWords$$anon$1;Lorg/scalactic/Equality;)V
  #36 = Utf8               equality
  #37 = Utf8               Lorg/scalactic/Equality;
  #38 = Utf8               this
  #39 = Utf8               Lorg/scalatest/matchers/dsl/MatcherWords$$anon$1;
  #40 = Utf8               toString
  #41 = Utf8               ()Ljava/lang/String;
  #42 = Utf8               java/lang/StringBuilder
  #43 = Class              #42            // java/lang/StringBuilder
  #44 = Integer            8
  #45 = Utf8               (I)V
  #46 = NameAndType        #32:#45        // "<init>":(I)V
  #47 = Methodref          #43.#46        // java/lang/StringBuilder."<init>":(I)V
  #48 = Utf8               equal (
  #49 = String             #48            // equal (
  #50 = Utf8               append
  #51 = Utf8               (Ljava/lang/String;)Ljava/lang/StringBuilder;
  #52 = NameAndType        #50:#51        // append:(Ljava/lang/String;)Ljava/lang/StringBuilder;
  #53 = Methodref          #43.#52        // java/lang/StringBuilder.append:(Ljava/lang/String;)Ljava/lang/StringBuilder;
  #54 = Utf8               org/scalactic/Prettifier$
  #55 = Class              #54            // org/scalactic/Prettifier$
  #56 = Utf8               Lorg/scalactic/Prettifier$;
  #57 = NameAndType        #22:#56        // MODULE$:Lorg/scalactic/Prettifier$;
  #58 = Fieldref           #55.#57        // org/scalactic/Prettifier$.MODULE$:Lorg/scalactic/Prettifier$;
  #59 = Utf8               default
  #60 = Utf8               ()Lorg/scalactic/Prettifier;
  #61 = NameAndType        #59:#60        // default:()Lorg/scalactic/Prettifier;
  #62 = Methodref          #55.#61        // org/scalactic/Prettifier$.default:()Lorg/scalactic/Prettifier;
  #63 = NameAndType        #14:#15        // right$1:Ljava/lang/Object;
  #64 = Fieldref           #2.#63         // org/scalatest/matchers/dsl/MatcherWords$$anon$1.right$1:Ljava/lang/Object;
  #65 = Utf8               org/scalactic/Prettifier
  #66 = Class              #65            // org/scalactic/Prettifier
  #67 = Utf8               apply
  #68 = Utf8               (Ljava/lang/Object;)Ljava/lang/String;
  #69 = NameAndType        #67:#68        // apply:(Ljava/lang/Object;)Ljava/lang/String;
  #70 = InterfaceMethodref #66.#69        // org/scalactic/Prettifier.apply:(Ljava/lang/Object;)Ljava/lang/String;
  #71 = Utf8               )
  #72 = String             #71            // )
  #73 = NameAndType        #40:#41        // toString:()Ljava/lang/String;
  #74 = Methodref          #43.#73        // java/lang/StringBuilder.toString:()Ljava/lang/String;
  #75 = Utf8               (Ljava/lang/Object;)Lorg/scalatest/matchers/Matcher;
  #76 = NameAndType        #16:#17        // matcher:(Lorg/scalactic/Equality;)Lorg/scalatest/matchers/Matcher;
  #77 = Methodref          #2.#76         // org/scalatest/matchers/dsl/MatcherWords$$anon$1.matcher:(Lorg/scalactic/Equality;)Lorg/scalatest/matchers/Matcher;
  #78 = Utf8               (Lorg/scalatest/matchers/dsl/MatcherWords;Ljava/lang/Object;)V
  #79 = Utf8               $outer
  #80 = Utf8               ()V
  #81 = NameAndType        #32:#80        // "<init>":()V
  #82 = Methodref          #5.#81         // org/scalatest/matchers/dsl/MatcherFactory1."<init>":()V
  #83 = Utf8               Lorg/scalatest/matchers/dsl/MatcherWords;
  #84 = Utf8               Code
  #85 = Utf8               LineNumberTable
  #86 = Utf8               LocalVariableTable
  #87 = Utf8               Signature
  #88 = Utf8               MethodParameters
  #89 = Utf8               InnerClasses
  #90 = Utf8               EnclosingMethod
  #91 = Utf8               SourceFile
  #92 = Utf8               ScalaInlineInfo
  #93 = Utf8               Scala
{
  public final java.lang.Object right$1;
    descriptor: Ljava/lang/Object;
    flags: (0x0011) ACC_PUBLIC, ACC_FINAL

  public <T extends java.lang.Object> org.scalatest.matchers.Matcher<T> matcher(org.scalactic.Equality<T>);
    descriptor: (Lorg/scalactic/Equality;)Lorg/scalatest/matchers/Matcher;
    flags: (0x0001) ACC_PUBLIC
    Code:
      stack=4, locals=3, args_size=2
         0: getstatic     #25                 // Field scala/Predef$.MODULE$:Lscala/Predef$;
         3: aload_1
         4: invokevirtual #29                 // Method scala/Predef$.implicitly:(Ljava/lang/Object;)Ljava/lang/Object;
         7: checkcast     #31                 // class org/scalactic/Equality
        10: astore_2
        11: new           #13                 // class org/scalatest/matchers/dsl/MatcherWords$$anon$1$$anon$2
        14: dup
        15: aload_0
        16: aload_2
        17: invokespecial #35                 // Method org/scalatest/matchers/dsl/MatcherWords$$anon$1$$anon$2."<init>":(Lorg/scalatest/matchers/dsl/MatcherWords$$anon$1;Lorg/scalactic/Equality;)V
        20: areturn
      LineNumberTable:
        line 296: 0
        line 297: 11
      LocalVariableTable:
        Start  Length  Slot  Name   Signature
           11       9     2 equality   Lorg/scalactic/Equality;
            0      21     0  this   Lorg/scalatest/matchers/dsl/MatcherWords$$anon$1;
            0      21     1 evidence$1   Lorg/scalactic/Equality;
    Signature: #18                          // <T:Ljava/lang/Object;>(Lorg/scalactic/Equality<TT;>;)Lorg/scalatest/matchers/Matcher<TT;>;
    MethodParameters:
      Name                           Flags
      evidence$1                     final

  public java.lang.String toString();
    descriptor: ()Ljava/lang/String;
    flags: (0x0001) ACC_PUBLIC
    Code:
      stack=3, locals=1, args_size=1
         0: new           #43                 // class java/lang/StringBuilder
         3: dup
         4: ldc           #44                 // int 8
         6: invokespecial #47                 // Method java/lang/StringBuilder."<init>":(I)V
         9: ldc           #49                 // String equal (
        11: invokevirtual #53                 // Method java/lang/StringBuilder.append:(Ljava/lang/String;)Ljava/lang/StringBuilder;
        14: getstatic     #58                 // Field org/scalactic/Prettifier$.MODULE$:Lorg/scalactic/Prettifier$;
        17: invokevirtual #62                 // Method org/scalactic/Prettifier$.default:()Lorg/scalactic/Prettifier;
        20: aload_0
        21: getfield      #64                 // Field right$1:Ljava/lang/Object;
        24: invokeinterface #70,  2           // InterfaceMethod org/scalactic/Prettifier.apply:(Ljava/lang/Object;)Ljava/lang/String;
        29: invokevirtual #53                 // Method java/lang/StringBuilder.append:(Ljava/lang/String;)Ljava/lang/StringBuilder;
        32: ldc           #72                 // String )
        34: invokevirtual #53                 // Method java/lang/StringBuilder.append:(Ljava/lang/String;)Ljava/lang/StringBuilder;
        37: invokevirtual #74                 // Method java/lang/StringBuilder.toString:()Ljava/lang/String;
        40: areturn
      LineNumberTable:
        line 312: 0
      LocalVariableTable:
        Start  Length  Slot  Name   Signature
            0      41     0  this   Lorg/scalatest/matchers/dsl/MatcherWords$$anon$1;

  public org.scalatest.matchers.Matcher matcher(java.lang.Object);
    descriptor: (Ljava/lang/Object;)Lorg/scalatest/matchers/Matcher;
    flags: (0x1041) ACC_PUBLIC, ACC_BRIDGE, ACC_SYNTHETIC
    Code:
      stack=2, locals=2, args_size=2
         0: aload_0
         1: aload_1
         2: checkcast     #31                 // class org/scalactic/Equality
         5: invokevirtual #77                 // Method matcher:(Lorg/scalactic/Equality;)Lorg/scalatest/matchers/Matcher;
         8: areturn
      LineNumberTable:
        line 294: 0
      LocalVariableTable:
        Start  Length  Slot  Name   Signature
            0       9     0  this   Lorg/scalatest/matchers/dsl/MatcherWords$$anon$1;
            0       9     1 evidence$1   Ljava/lang/Object;
    MethodParameters:
      Name                           Flags
      evidence$1                     final

  public org.scalatest.matchers.dsl.MatcherWords$$anon$1(org.scalatest.matchers.dsl.MatcherWords, java.lang.Object);
    descriptor: (Lorg/scalatest/matchers/dsl/MatcherWords;Ljava/lang/Object;)V
    flags: (0x0001) ACC_PUBLIC
    Code:
      stack=2, locals=3, args_size=3
         0: aload_0
         1: aload_2
         2: putfield      #64                 // Field right$1:Ljava/lang/Object;
         5: aload_0
         6: invokespecial #82                 // Method org/scalatest/matchers/dsl/MatcherFactory1."<init>":()V
         9: return
      LineNumberTable:
        line 293: 0
        line 294: 5
      LocalVariableTable:
        Start  Length  Slot  Name   Signature
            0      10     0  this   Lorg/scalatest/matchers/dsl/MatcherWords$$anon$1;
            0      10     1 $outer   Lorg/scalatest/matchers/dsl/MatcherWords;
            0      10     2 right$1   Ljava/lang/Object;
    MethodParameters:
      Name                           Flags
      $outer                         final synthetic
      right$1                        final
}
InnerClasses:
  public final #2;                        // class org/scalatest/matchers/dsl/MatcherWords$$anon$1
  public final #13;                       // class org/scalatest/matchers/dsl/MatcherWords$$anon$1$$anon$2
EnclosingMethod: #8.#11                 // org.scalatest.matchers.dsl.MatcherWords.equal
Signature: #3                           // Lorg/scalatest/matchers/dsl/MatcherFactory1<Ljava/lang/Object;Lorg/scalactic/Equality;>;
SourceFile: "MatcherWords.scala"
  ScalaInlineInfo: length = 0x18 (unknown attribute)
   01 01 00 04 00 20 00 4E 01 00 10 00 4B 01 00 10
   00 11 01 00 28 00 29 01
  Scala: length = 0x0 (unknown attribute)

