Classfile /Users/mw/Projects/slang-braindump/.jar/jar8/assemble/slang-braindump/assemble/content/org/scalatest/matchers/dsl/NotWord$$anon$76.class
  Last modified May 29, 2022; size 22459 bytes
  SHA-256 checksum dcac12727ae611c054ab102410730878a21dcf6c9a5d71294b8d8de94dd91295
  Compiled from "NotWord.scala"
public final class org.scalatest.matchers.dsl.NotWord$$anon$76 extends java.lang.Object implements org.scalatest.matchers.Matcher<scala.collection.Iterable<T>>
  minor version: 0
  major version: 52
  flags: (0x0031) ACC_PUBLIC, ACC_FINAL, ACC_SUPER
  this_class: #2                          // org/scalatest/matchers/dsl/NotWord$$anon$76
  super_class: #5                         // java/lang/Object
  interfaces: 1, fields: 1, methods: 61, attributes: 7
Constant pool:
    #1 = Utf8               org/scalatest/matchers/dsl/NotWord$$anon$76
    #2 = Class              #1            // org/scalatest/matchers/dsl/NotWord$$anon$76
    #3 = Utf8               Ljava/lang/Object;Lorg/scalatest/matchers/Matcher<Lscala/collection/Iterable<TT;>;>;
    #4 = Utf8               java/lang/Object
    #5 = Class              #4            // java/lang/Object
    #6 = Utf8               org/scalatest/matchers/Matcher
    #7 = Class              #6            // org/scalatest/matchers/Matcher
    #8 = Utf8               NotWord.scala
    #9 = Utf8               org/scalatest/matchers/dsl/NotWord
   #10 = Class              #9            // org/scalatest/matchers/dsl/NotWord
   #11 = Utf8               contain
   #12 = Utf8               (Lorg/scalatest/matchers/dsl/ResultOfAWordToAMatcherApplication;)Lorg/scalatest/matchers/Matcher;
   #13 = NameAndType        #11:#12       // contain:(Lorg/scalatest/matchers/dsl/ResultOfAWordToAMatcherApplication;)Lorg/scalatest/matchers/Matcher;
   #14 = Utf8               java/lang/invoke/MethodHandles$Lookup
   #15 = Class              #14           // java/lang/invoke/MethodHandles$Lookup
   #16 = Utf8               java/lang/invoke/MethodHandles
   #17 = Class              #16           // java/lang/invoke/MethodHandles
   #18 = Utf8               Lookup
   #19 = Utf8               org/scalatest/matchers/Matcher$AndBeWord
   #20 = Class              #19           // org/scalatest/matchers/Matcher$AndBeWord
   #21 = Utf8               AndBeWord
   #22 = Utf8               org/scalatest/matchers/Matcher$AndContainWord
   #23 = Class              #22           // org/scalatest/matchers/Matcher$AndContainWord
   #24 = Utf8               AndContainWord
   #25 = Utf8               org/scalatest/matchers/Matcher$AndEndWithWord
   #26 = Class              #25           // org/scalatest/matchers/Matcher$AndEndWithWord
   #27 = Utf8               AndEndWithWord
   #28 = Utf8               org/scalatest/matchers/Matcher$AndFullyMatchWord
   #29 = Class              #28           // org/scalatest/matchers/Matcher$AndFullyMatchWord
   #30 = Utf8               AndFullyMatchWord
   #31 = Utf8               org/scalatest/matchers/Matcher$AndHaveWord
   #32 = Class              #31           // org/scalatest/matchers/Matcher$AndHaveWord
   #33 = Utf8               AndHaveWord
   #34 = Utf8               org/scalatest/matchers/Matcher$AndIncludeWord
   #35 = Class              #34           // org/scalatest/matchers/Matcher$AndIncludeWord
   #36 = Utf8               AndIncludeWord
   #37 = Utf8               org/scalatest/matchers/Matcher$AndNotWord
   #38 = Class              #37           // org/scalatest/matchers/Matcher$AndNotWord
   #39 = Utf8               AndNotWord
   #40 = Utf8               org/scalatest/matchers/Matcher$AndStartWithWord
   #41 = Class              #40           // org/scalatest/matchers/Matcher$AndStartWithWord
   #42 = Utf8               AndStartWithWord
   #43 = Utf8               org/scalatest/matchers/Matcher$OrBeWord
   #44 = Class              #43           // org/scalatest/matchers/Matcher$OrBeWord
   #45 = Utf8               OrBeWord
   #46 = Utf8               org/scalatest/matchers/Matcher$OrContainWord
   #47 = Class              #46           // org/scalatest/matchers/Matcher$OrContainWord
   #48 = Utf8               OrContainWord
   #49 = Utf8               org/scalatest/matchers/Matcher$OrEndWithWord
   #50 = Class              #49           // org/scalatest/matchers/Matcher$OrEndWithWord
   #51 = Utf8               OrEndWithWord
   #52 = Utf8               org/scalatest/matchers/Matcher$OrFullyMatchWord
   #53 = Class              #52           // org/scalatest/matchers/Matcher$OrFullyMatchWord
   #54 = Utf8               OrFullyMatchWord
   #55 = Utf8               org/scalatest/matchers/Matcher$OrHaveWord
   #56 = Class              #55           // org/scalatest/matchers/Matcher$OrHaveWord
   #57 = Utf8               OrHaveWord
   #58 = Utf8               org/scalatest/matchers/Matcher$OrIncludeWord
   #59 = Class              #58           // org/scalatest/matchers/Matcher$OrIncludeWord
   #60 = Utf8               OrIncludeWord
   #61 = Utf8               org/scalatest/matchers/Matcher$OrNotWord
   #62 = Class              #61           // org/scalatest/matchers/Matcher$OrNotWord
   #63 = Utf8               OrNotWord
   #64 = Utf8               org/scalatest/matchers/Matcher$OrStartWithWord
   #65 = Class              #64           // org/scalatest/matchers/Matcher$OrStartWithWord
   #66 = Utf8               OrStartWithWord
   #67 = Utf8               resultOfAWordApplication$4
   #68 = Utf8               Lorg/scalatest/matchers/dsl/ResultOfAWordToAMatcherApplication;
   #69 = Utf8               compose
   #70 = Utf8               (Lscala/Function1;)Lorg/scalatest/matchers/Matcher;
   #71 = Utf8               <U:Ljava/lang/Object;>(Lscala/Function1<TU;Lscala/collection/Iterable<TT;>;>;)Lorg/scalatest/matchers/Matcher<TU;>;
   #72 = Utf8               g
   #73 = Utf8               compose$
   #74 = Utf8               (Lorg/scalatest/matchers/Matcher;Lscala/Function1;)Lorg/scalatest/matchers/Matcher;
   #75 = NameAndType        #73:#74       // compose$:(Lorg/scalatest/matchers/Matcher;Lscala/Function1;)Lorg/scalatest/matchers/Matcher;
   #76 = InterfaceMethodref #7.#75        // org/scalatest/matchers/Matcher.compose$:(Lorg/scalatest/matchers/Matcher;Lscala/Function1;)Lorg/scalatest/matchers/Matcher;
   #77 = Utf8               this
   #78 = Utf8               Lorg/scalatest/matchers/dsl/NotWord$$anon$76;
   #79 = Utf8               Lscala/Function1;
   #80 = Utf8               and
   #81 = Utf8               (Lorg/scalatest/matchers/Matcher;)Lorg/scalatest/matchers/Matcher;
   #82 = Utf8               <U::Lscala/collection/Iterable<TT;>;>(Lorg/scalatest/matchers/Matcher<TU;>;)Lorg/scalatest/matchers/Matcher<TU;>;
   #83 = Utf8               rightMatcher
   #84 = Utf8               and$
   #85 = Utf8               (Lorg/scalatest/matchers/Matcher;Lorg/scalatest/matchers/Matcher;)Lorg/scalatest/matchers/Matcher;
   #86 = NameAndType        #84:#85       // and$:(Lorg/scalatest/matchers/Matcher;Lorg/scalatest/matchers/Matcher;)Lorg/scalatest/matchers/Matcher;
   #87 = InterfaceMethodref #7.#86        // org/scalatest/matchers/Matcher.and$:(Lorg/scalatest/matchers/Matcher;Lorg/scalatest/matchers/Matcher;)Lorg/scalatest/matchers/Matcher;
   #88 = Utf8               Lorg/scalatest/matchers/Matcher;
   #89 = Utf8               (Lorg/scalatest/matchers/dsl/MatcherFactory1;)Lorg/scalatest/matchers/dsl/MatcherFactory1;
   #90 = Utf8               <U:Ljava/lang/Object;TC1:Ljava/lang/Object;>(Lorg/scalatest/matchers/dsl/MatcherFactory1<TU;TTC1;>;)Lorg/scalatest/matchers/dsl/MatcherFactory1<Lscala/collection/Iterable<TT;>;TTC1;>;
   #91 = Utf8               rightMatcherFactory1
   #92 = Utf8               (Lorg/scalatest/matchers/Matcher;Lorg/scalatest/matchers/dsl/MatcherFactory1;)Lorg/scalatest/matchers/dsl/MatcherFactory1;
   #93 = NameAndType        #84:#92       // and$:(Lorg/scalatest/matchers/Matcher;Lorg/scalatest/matchers/dsl/MatcherFactory1;)Lorg/scalatest/matchers/dsl/MatcherFactory1;
   #94 = InterfaceMethodref #7.#93        // org/scalatest/matchers/Matcher.and$:(Lorg/scalatest/matchers/Matcher;Lorg/scalatest/matchers/dsl/MatcherFactory1;)Lorg/scalatest/matchers/dsl/MatcherFactory1;
   #95 = Utf8               Lorg/scalatest/matchers/dsl/MatcherFactory1;
   #96 = Utf8               or
   #97 = Utf8               or$
   #98 = NameAndType        #97:#85       // or$:(Lorg/scalatest/matchers/Matcher;Lorg/scalatest/matchers/Matcher;)Lorg/scalatest/matchers/Matcher;
   #99 = InterfaceMethodref #7.#98        // org/scalatest/matchers/Matcher.or$:(Lorg/scalatest/matchers/Matcher;Lorg/scalatest/matchers/Matcher;)Lorg/scalatest/matchers/Matcher;
  #100 = NameAndType        #97:#92       // or$:(Lorg/scalatest/matchers/Matcher;Lorg/scalatest/matchers/dsl/MatcherFactory1;)Lorg/scalatest/matchers/dsl/MatcherFactory1;
  #101 = InterfaceMethodref #7.#100       // org/scalatest/matchers/Matcher.or$:(Lorg/scalatest/matchers/Matcher;Lorg/scalatest/matchers/dsl/MatcherFactory1;)Lorg/scalatest/matchers/dsl/MatcherFactory1;
  #102 = Utf8               (Lorg/scalatest/matchers/dsl/HaveWord;)Lorg/scalatest/matchers/Matcher$AndHaveWord;
  #103 = Utf8               (Lorg/scalatest/matchers/dsl/HaveWord;)Lorg/scalatest/matchers/Matcher<Lscala/collection/Iterable<TT;>;>.AndHaveWord;
  #104 = Utf8               haveWord
  #105 = Utf8               (Lorg/scalatest/matchers/Matcher;Lorg/scalatest/matchers/dsl/HaveWord;)Lorg/scalatest/matchers/Matcher$AndHaveWord;
  #106 = NameAndType        #84:#105      // and$:(Lorg/scalatest/matchers/Matcher;Lorg/scalatest/matchers/dsl/HaveWord;)Lorg/scalatest/matchers/Matcher$AndHaveWord;
  #107 = InterfaceMethodref #7.#106       // org/scalatest/matchers/Matcher.and$:(Lorg/scalatest/matchers/Matcher;Lorg/scalatest/matchers/dsl/HaveWord;)Lorg/scalatest/matchers/Matcher$AndHaveWord;
  #108 = Utf8               Lorg/scalatest/matchers/dsl/HaveWord;
  #109 = Utf8               (Lorg/scalatest/matchers/dsl/ContainWord;Lorg/scalactic/Prettifier;Lorg/scalactic/source/Position;)Lorg/scalatest/matchers/Matcher$AndContainWord;
  #110 = Utf8               (Lorg/scalatest/matchers/dsl/ContainWord;Lorg/scalactic/Prettifier;Lorg/scalactic/source/Position;)Lorg/scalatest/matchers/Matcher<Lscala/collection/Iterable<TT;>;>.AndContainWord;
  #111 = Utf8               containWord
  #112 = Utf8               prettifier
  #113 = Utf8               pos
  #114 = Utf8               (Lorg/scalatest/matchers/Matcher;Lorg/scalatest/matchers/dsl/ContainWord;Lorg/scalactic/Prettifier;Lorg/scalactic/source/Position;)Lorg/scalatest/matchers/Matcher$AndContainWord;
  #115 = NameAndType        #84:#114      // and$:(Lorg/scalatest/matchers/Matcher;Lorg/scalatest/matchers/dsl/ContainWord;Lorg/scalactic/Prettifier;Lorg/scalactic/source/Position;)Lorg/scalatest/matchers/Matcher$AndContainWord;
  #116 = InterfaceMethodref #7.#115       // org/scalatest/matchers/Matcher.and$:(Lorg/scalatest/matchers/Matcher;Lorg/scalatest/matchers/dsl/ContainWord;Lorg/scalactic/Prettifier;Lorg/scalactic/source/Position;)Lorg/scalatest/matchers/Matcher$AndContainWord;
  #117 = Utf8               Lorg/scalatest/matchers/dsl/ContainWord;
  #118 = Utf8               Lorg/scalactic/Prettifier;
  #119 = Utf8               Lorg/scalactic/source/Position;
  #120 = Utf8               (Lorg/scalatest/matchers/dsl/BeWord;)Lorg/scalatest/matchers/Matcher$AndBeWord;
  #121 = Utf8               (Lorg/scalatest/matchers/dsl/BeWord;)Lorg/scalatest/matchers/Matcher<Lscala/collection/Iterable<TT;>;>.AndBeWord;
  #122 = Utf8               beWord
  #123 = Utf8               (Lorg/scalatest/matchers/Matcher;Lorg/scalatest/matchers/dsl/BeWord;)Lorg/scalatest/matchers/Matcher$AndBeWord;
  #124 = NameAndType        #84:#123      // and$:(Lorg/scalatest/matchers/Matcher;Lorg/scalatest/matchers/dsl/BeWord;)Lorg/scalatest/matchers/Matcher$AndBeWord;
  #125 = InterfaceMethodref #7.#124       // org/scalatest/matchers/Matcher.and$:(Lorg/scalatest/matchers/Matcher;Lorg/scalatest/matchers/dsl/BeWord;)Lorg/scalatest/matchers/Matcher$AndBeWord;
  #126 = Utf8               Lorg/scalatest/matchers/dsl/BeWord;
  #127 = Utf8               (Lorg/scalatest/matchers/dsl/FullyMatchWord;)Lorg/scalatest/matchers/Matcher$AndFullyMatchWord;
  #128 = Utf8               (Lorg/scalatest/matchers/dsl/FullyMatchWord;)Lorg/scalatest/matchers/Matcher<Lscala/collection/Iterable<TT;>;>.AndFullyMatchWord;
  #129 = Utf8               fullyMatchWord
  #130 = Utf8               (Lorg/scalatest/matchers/Matcher;Lorg/scalatest/matchers/dsl/FullyMatchWord;)Lorg/scalatest/matchers/Matcher$AndFullyMatchWord;
  #131 = NameAndType        #84:#130      // and$:(Lorg/scalatest/matchers/Matcher;Lorg/scalatest/matchers/dsl/FullyMatchWord;)Lorg/scalatest/matchers/Matcher$AndFullyMatchWord;
  #132 = InterfaceMethodref #7.#131       // org/scalatest/matchers/Matcher.and$:(Lorg/scalatest/matchers/Matcher;Lorg/scalatest/matchers/dsl/FullyMatchWord;)Lorg/scalatest/matchers/Matcher$AndFullyMatchWord;
  #133 = Utf8               Lorg/scalatest/matchers/dsl/FullyMatchWord;
  #134 = Utf8               (Lorg/scalatest/matchers/dsl/IncludeWord;)Lorg/scalatest/matchers/Matcher$AndIncludeWord;
  #135 = Utf8               (Lorg/scalatest/matchers/dsl/IncludeWord;)Lorg/scalatest/matchers/Matcher<Lscala/collection/Iterable<TT;>;>.AndIncludeWord;
  #136 = Utf8               includeWord
  #137 = Utf8               (Lorg/scalatest/matchers/Matcher;Lorg/scalatest/matchers/dsl/IncludeWord;)Lorg/scalatest/matchers/Matcher$AndIncludeWord;
  #138 = NameAndType        #84:#137      // and$:(Lorg/scalatest/matchers/Matcher;Lorg/scalatest/matchers/dsl/IncludeWord;)Lorg/scalatest/matchers/Matcher$AndIncludeWord;
  #139 = InterfaceMethodref #7.#138       // org/scalatest/matchers/Matcher.and$:(Lorg/scalatest/matchers/Matcher;Lorg/scalatest/matchers/dsl/IncludeWord;)Lorg/scalatest/matchers/Matcher$AndIncludeWord;
  #140 = Utf8               Lorg/scalatest/matchers/dsl/IncludeWord;
  #141 = Utf8               (Lorg/scalatest/matchers/dsl/StartWithWord;)Lorg/scalatest/matchers/Matcher$AndStartWithWord;
  #142 = Utf8               (Lorg/scalatest/matchers/dsl/StartWithWord;)Lorg/scalatest/matchers/Matcher<Lscala/collection/Iterable<TT;>;>.AndStartWithWord;
  #143 = Utf8               startWithWord
  #144 = Utf8               (Lorg/scalatest/matchers/Matcher;Lorg/scalatest/matchers/dsl/StartWithWord;)Lorg/scalatest/matchers/Matcher$AndStartWithWord;
  #145 = NameAndType        #84:#144      // and$:(Lorg/scalatest/matchers/Matcher;Lorg/scalatest/matchers/dsl/StartWithWord;)Lorg/scalatest/matchers/Matcher$AndStartWithWord;
  #146 = InterfaceMethodref #7.#145       // org/scalatest/matchers/Matcher.and$:(Lorg/scalatest/matchers/Matcher;Lorg/scalatest/matchers/dsl/StartWithWord;)Lorg/scalatest/matchers/Matcher$AndStartWithWord;
  #147 = Utf8               Lorg/scalatest/matchers/dsl/StartWithWord;
  #148 = Utf8               (Lorg/scalatest/matchers/dsl/EndWithWord;)Lorg/scalatest/matchers/Matcher$AndEndWithWord;
  #149 = Utf8               (Lorg/scalatest/matchers/dsl/EndWithWord;)Lorg/scalatest/matchers/Matcher<Lscala/collection/Iterable<TT;>;>.AndEndWithWord;
  #150 = Utf8               endWithWord
  #151 = Utf8               (Lorg/scalatest/matchers/Matcher;Lorg/scalatest/matchers/dsl/EndWithWord;)Lorg/scalatest/matchers/Matcher$AndEndWithWord;
  #152 = NameAndType        #84:#151      // and$:(Lorg/scalatest/matchers/Matcher;Lorg/scalatest/matchers/dsl/EndWithWord;)Lorg/scalatest/matchers/Matcher$AndEndWithWord;
  #153 = InterfaceMethodref #7.#152       // org/scalatest/matchers/Matcher.and$:(Lorg/scalatest/matchers/Matcher;Lorg/scalatest/matchers/dsl/EndWithWord;)Lorg/scalatest/matchers/Matcher$AndEndWithWord;
  #154 = Utf8               Lorg/scalatest/matchers/dsl/EndWithWord;
  #155 = Utf8               (Lorg/scalatest/matchers/dsl/NotWord;)Lorg/scalatest/matchers/Matcher$AndNotWord;
  #156 = Utf8               (Lorg/scalatest/matchers/dsl/NotWord;)Lorg/scalatest/matchers/Matcher<Lscala/collection/Iterable<TT;>;>.AndNotWord;
  #157 = Utf8               notWord
  #158 = Utf8               (Lorg/scalatest/matchers/Matcher;Lorg/scalatest/matchers/dsl/NotWord;)Lorg/scalatest/matchers/Matcher$AndNotWord;
  #159 = NameAndType        #84:#158      // and$:(Lorg/scalatest/matchers/Matcher;Lorg/scalatest/matchers/dsl/NotWord;)Lorg/scalatest/matchers/Matcher$AndNotWord;
  #160 = InterfaceMethodref #7.#159       // org/scalatest/matchers/Matcher.and$:(Lorg/scalatest/matchers/Matcher;Lorg/scalatest/matchers/dsl/NotWord;)Lorg/scalatest/matchers/Matcher$AndNotWord;
  #161 = Utf8               Lorg/scalatest/matchers/dsl/NotWord;
  #162 = Utf8               (Lorg/scalatest/matchers/dsl/ExistWord;)Lorg/scalatest/matchers/dsl/MatcherFactory1;
  #163 = Utf8               (Lorg/scalatest/matchers/dsl/ExistWord;)Lorg/scalatest/matchers/dsl/MatcherFactory1<Lscala/collection/Iterable<TT;>;Lorg/scalatest/enablers/Existence;>;
  #164 = Utf8               existWord
  #165 = Utf8               (Lorg/scalatest/matchers/Matcher;Lorg/scalatest/matchers/dsl/ExistWord;)Lorg/scalatest/matchers/dsl/MatcherFactory1;
  #166 = NameAndType        #84:#165      // and$:(Lorg/scalatest/matchers/Matcher;Lorg/scalatest/matchers/dsl/ExistWord;)Lorg/scalatest/matchers/dsl/MatcherFactory1;
  #167 = InterfaceMethodref #7.#166       // org/scalatest/matchers/Matcher.and$:(Lorg/scalatest/matchers/Matcher;Lorg/scalatest/matchers/dsl/ExistWord;)Lorg/scalatest/matchers/dsl/MatcherFactory1;
  #168 = Utf8               Lorg/scalatest/matchers/dsl/ExistWord;
  #169 = Utf8               (Lorg/scalatest/matchers/dsl/ResultOfNotExist;)Lorg/scalatest/matchers/dsl/MatcherFactory1;
  #170 = Utf8               (Lorg/scalatest/matchers/dsl/ResultOfNotExist;)Lorg/scalatest/matchers/dsl/MatcherFactory1<Lscala/collection/Iterable<TT;>;Lorg/scalatest/enablers/Existence;>;
  #171 = Utf8               notExist
  #172 = Utf8               (Lorg/scalatest/matchers/Matcher;Lorg/scalatest/matchers/dsl/ResultOfNotExist;)Lorg/scalatest/matchers/dsl/MatcherFactory1;
  #173 = NameAndType        #84:#172      // and$:(Lorg/scalatest/matchers/Matcher;Lorg/scalatest/matchers/dsl/ResultOfNotExist;)Lorg/scalatest/matchers/dsl/MatcherFactory1;
  #174 = InterfaceMethodref #7.#173       // org/scalatest/matchers/Matcher.and$:(Lorg/scalatest/matchers/Matcher;Lorg/scalatest/matchers/dsl/ResultOfNotExist;)Lorg/scalatest/matchers/dsl/MatcherFactory1;
  #175 = Utf8               Lorg/scalatest/matchers/dsl/ResultOfNotExist;
  #176 = Utf8               (Lorg/scalatest/matchers/dsl/HaveWord;)Lorg/scalatest/matchers/Matcher$OrHaveWord;
  #177 = Utf8               (Lorg/scalatest/matchers/dsl/HaveWord;)Lorg/scalatest/matchers/Matcher<Lscala/collection/Iterable<TT;>;>.OrHaveWord;
  #178 = Utf8               (Lorg/scalatest/matchers/Matcher;Lorg/scalatest/matchers/dsl/HaveWord;)Lorg/scalatest/matchers/Matcher$OrHaveWord;
  #179 = NameAndType        #97:#178      // or$:(Lorg/scalatest/matchers/Matcher;Lorg/scalatest/matchers/dsl/HaveWord;)Lorg/scalatest/matchers/Matcher$OrHaveWord;
  #180 = InterfaceMethodref #7.#179       // org/scalatest/matchers/Matcher.or$:(Lorg/scalatest/matchers/Matcher;Lorg/scalatest/matchers/dsl/HaveWord;)Lorg/scalatest/matchers/Matcher$OrHaveWord;
  #181 = Utf8               (Lorg/scalatest/matchers/dsl/ContainWord;Lorg/scalactic/Prettifier;Lorg/scalactic/source/Position;)Lorg/scalatest/matchers/Matcher$OrContainWord;
  #182 = Utf8               (Lorg/scalatest/matchers/dsl/ContainWord;Lorg/scalactic/Prettifier;Lorg/scalactic/source/Position;)Lorg/scalatest/matchers/Matcher<Lscala/collection/Iterable<TT;>;>.OrContainWord;
  #183 = Utf8               (Lorg/scalatest/matchers/Matcher;Lorg/scalatest/matchers/dsl/ContainWord;Lorg/scalactic/Prettifier;Lorg/scalactic/source/Position;)Lorg/scalatest/matchers/Matcher$OrContainWord;
  #184 = NameAndType        #97:#183      // or$:(Lorg/scalatest/matchers/Matcher;Lorg/scalatest/matchers/dsl/ContainWord;Lorg/scalactic/Prettifier;Lorg/scalactic/source/Position;)Lorg/scalatest/matchers/Matcher$OrContainWord;
  #185 = InterfaceMethodref #7.#184       // org/scalatest/matchers/Matcher.or$:(Lorg/scalatest/matchers/Matcher;Lorg/scalatest/matchers/dsl/ContainWord;Lorg/scalactic/Prettifier;Lorg/scalactic/source/Position;)Lorg/scalatest/matchers/Matcher$OrContainWord;
  #186 = Utf8               (Lorg/scalatest/matchers/dsl/BeWord;)Lorg/scalatest/matchers/Matcher$OrBeWord;
  #187 = Utf8               (Lorg/scalatest/matchers/dsl/BeWord;)Lorg/scalatest/matchers/Matcher<Lscala/collection/Iterable<TT;>;>.OrBeWord;
  #188 = Utf8               (Lorg/scalatest/matchers/Matcher;Lorg/scalatest/matchers/dsl/BeWord;)Lorg/scalatest/matchers/Matcher$OrBeWord;
  #189 = NameAndType        #97:#188      // or$:(Lorg/scalatest/matchers/Matcher;Lorg/scalatest/matchers/dsl/BeWord;)Lorg/scalatest/matchers/Matcher$OrBeWord;
  #190 = InterfaceMethodref #7.#189       // org/scalatest/matchers/Matcher.or$:(Lorg/scalatest/matchers/Matcher;Lorg/scalatest/matchers/dsl/BeWord;)Lorg/scalatest/matchers/Matcher$OrBeWord;
  #191 = Utf8               (Lorg/scalatest/matchers/dsl/FullyMatchWord;)Lorg/scalatest/matchers/Matcher$OrFullyMatchWord;
  #192 = Utf8               (Lorg/scalatest/matchers/dsl/FullyMatchWord;)Lorg/scalatest/matchers/Matcher<Lscala/collection/Iterable<TT;>;>.OrFullyMatchWord;
  #193 = Utf8               (Lorg/scalatest/matchers/Matcher;Lorg/scalatest/matchers/dsl/FullyMatchWord;)Lorg/scalatest/matchers/Matcher$OrFullyMatchWord;
  #194 = NameAndType        #97:#193      // or$:(Lorg/scalatest/matchers/Matcher;Lorg/scalatest/matchers/dsl/FullyMatchWord;)Lorg/scalatest/matchers/Matcher$OrFullyMatchWord;
  #195 = InterfaceMethodref #7.#194       // org/scalatest/matchers/Matcher.or$:(Lorg/scalatest/matchers/Matcher;Lorg/scalatest/matchers/dsl/FullyMatchWord;)Lorg/scalatest/matchers/Matcher$OrFullyMatchWord;
  #196 = Utf8               (Lorg/scalatest/matchers/dsl/IncludeWord;)Lorg/scalatest/matchers/Matcher$OrIncludeWord;
  #197 = Utf8               (Lorg/scalatest/matchers/dsl/IncludeWord;)Lorg/scalatest/matchers/Matcher<Lscala/collection/Iterable<TT;>;>.OrIncludeWord;
  #198 = Utf8               (Lorg/scalatest/matchers/Matcher;Lorg/scalatest/matchers/dsl/IncludeWord;)Lorg/scalatest/matchers/Matcher$OrIncludeWord;
  #199 = NameAndType        #97:#198      // or$:(Lorg/scalatest/matchers/Matcher;Lorg/scalatest/matchers/dsl/IncludeWord;)Lorg/scalatest/matchers/Matcher$OrIncludeWord;
  #200 = InterfaceMethodref #7.#199       // org/scalatest/matchers/Matcher.or$:(Lorg/scalatest/matchers/Matcher;Lorg/scalatest/matchers/dsl/IncludeWord;)Lorg/scalatest/matchers/Matcher$OrIncludeWord;
  #201 = Utf8               (Lorg/scalatest/matchers/dsl/StartWithWord;)Lorg/scalatest/matchers/Matcher$OrStartWithWord;
  #202 = Utf8               (Lorg/scalatest/matchers/dsl/StartWithWord;)Lorg/scalatest/matchers/Matcher<Lscala/collection/Iterable<TT;>;>.OrStartWithWord;
  #203 = Utf8               (Lorg/scalatest/matchers/Matcher;Lorg/scalatest/matchers/dsl/StartWithWord;)Lorg/scalatest/matchers/Matcher$OrStartWithWord;
  #204 = NameAndType        #97:#203      // or$:(Lorg/scalatest/matchers/Matcher;Lorg/scalatest/matchers/dsl/StartWithWord;)Lorg/scalatest/matchers/Matcher$OrStartWithWord;
  #205 = InterfaceMethodref #7.#204       // org/scalatest/matchers/Matcher.or$:(Lorg/scalatest/matchers/Matcher;Lorg/scalatest/matchers/dsl/StartWithWord;)Lorg/scalatest/matchers/Matcher$OrStartWithWord;
  #206 = Utf8               (Lorg/scalatest/matchers/dsl/EndWithWord;)Lorg/scalatest/matchers/Matcher$OrEndWithWord;
  #207 = Utf8               (Lorg/scalatest/matchers/dsl/EndWithWord;)Lorg/scalatest/matchers/Matcher<Lscala/collection/Iterable<TT;>;>.OrEndWithWord;
  #208 = Utf8               (Lorg/scalatest/matchers/Matcher;Lorg/scalatest/matchers/dsl/EndWithWord;)Lorg/scalatest/matchers/Matcher$OrEndWithWord;
  #209 = NameAndType        #97:#208      // or$:(Lorg/scalatest/matchers/Matcher;Lorg/scalatest/matchers/dsl/EndWithWord;)Lorg/scalatest/matchers/Matcher$OrEndWithWord;
  #210 = InterfaceMethodref #7.#209       // org/scalatest/matchers/Matcher.or$:(Lorg/scalatest/matchers/Matcher;Lorg/scalatest/matchers/dsl/EndWithWord;)Lorg/scalatest/matchers/Matcher$OrEndWithWord;
  #211 = Utf8               (Lorg/scalatest/matchers/dsl/NotWord;)Lorg/scalatest/matchers/Matcher$OrNotWord;
  #212 = Utf8               (Lorg/scalatest/matchers/dsl/NotWord;)Lorg/scalatest/matchers/Matcher<Lscala/collection/Iterable<TT;>;>.OrNotWord;
  #213 = Utf8               (Lorg/scalatest/matchers/Matcher;Lorg/scalatest/matchers/dsl/NotWord;)Lorg/scalatest/matchers/Matcher$OrNotWord;
  #214 = NameAndType        #97:#213      // or$:(Lorg/scalatest/matchers/Matcher;Lorg/scalatest/matchers/dsl/NotWord;)Lorg/scalatest/matchers/Matcher$OrNotWord;
  #215 = InterfaceMethodref #7.#214       // org/scalatest/matchers/Matcher.or$:(Lorg/scalatest/matchers/Matcher;Lorg/scalatest/matchers/dsl/NotWord;)Lorg/scalatest/matchers/Matcher$OrNotWord;
  #216 = NameAndType        #97:#165      // or$:(Lorg/scalatest/matchers/Matcher;Lorg/scalatest/matchers/dsl/ExistWord;)Lorg/scalatest/matchers/dsl/MatcherFactory1;
  #217 = InterfaceMethodref #7.#216       // org/scalatest/matchers/Matcher.or$:(Lorg/scalatest/matchers/Matcher;Lorg/scalatest/matchers/dsl/ExistWord;)Lorg/scalatest/matchers/dsl/MatcherFactory1;
  #218 = NameAndType        #97:#172      // or$:(Lorg/scalatest/matchers/Matcher;Lorg/scalatest/matchers/dsl/ResultOfNotExist;)Lorg/scalatest/matchers/dsl/MatcherFactory1;
  #219 = InterfaceMethodref #7.#218       // org/scalatest/matchers/Matcher.or$:(Lorg/scalatest/matchers/Matcher;Lorg/scalatest/matchers/dsl/ResultOfNotExist;)Lorg/scalatest/matchers/dsl/MatcherFactory1;
  #220 = Utf8               mapResult
  #221 = Utf8               (Lscala/Function1<Lorg/scalatest/matchers/MatchResult;Lorg/scalatest/matchers/MatchResult;>;)Lorg/scalatest/matchers/Matcher<Lscala/collection/Iterable<TT;>;>;
  #222 = Utf8               prettify
  #223 = Utf8               mapResult$
  #224 = NameAndType        #223:#74      // mapResult$:(Lorg/scalatest/matchers/Matcher;Lscala/Function1;)Lorg/scalatest/matchers/Matcher;
  #225 = InterfaceMethodref #7.#224       // org/scalatest/matchers/Matcher.mapResult$:(Lorg/scalatest/matchers/Matcher;Lscala/Function1;)Lorg/scalatest/matchers/Matcher;
  #226 = Utf8               mapArgs
  #227 = Utf8               (Lscala/Function1<Ljava/lang/Object;Ljava/lang/String;>;)Lorg/scalatest/matchers/Matcher<Lscala/collection/Iterable<TT;>;>;
  #228 = Utf8               mapArgs$
  #229 = NameAndType        #228:#74      // mapArgs$:(Lorg/scalatest/matchers/Matcher;Lscala/Function1;)Lorg/scalatest/matchers/Matcher;
  #230 = InterfaceMethodref #7.#229       // org/scalatest/matchers/Matcher.mapArgs$:(Lorg/scalatest/matchers/Matcher;Lscala/Function1;)Lorg/scalatest/matchers/Matcher;
  #231 = Utf8               apply$mcZD$sp
  #232 = Utf8               (D)Z
  #233 = Utf8               v1
  #234 = Utf8               scala/Function1
  #235 = Class              #234          // scala/Function1
  #236 = Utf8               apply$mcZD$sp$
  #237 = Utf8               (Lscala/Function1;D)Z
  #238 = NameAndType        #236:#237     // apply$mcZD$sp$:(Lscala/Function1;D)Z
  #239 = InterfaceMethodref #235.#238     // scala/Function1.apply$mcZD$sp$:(Lscala/Function1;D)Z
  #240 = Utf8               D
  #241 = Utf8               apply$mcDD$sp
  #242 = Utf8               (D)D
  #243 = Utf8               apply$mcDD$sp$
  #244 = Utf8               (Lscala/Function1;D)D
  #245 = NameAndType        #243:#244     // apply$mcDD$sp$:(Lscala/Function1;D)D
  #246 = InterfaceMethodref #235.#245     // scala/Function1.apply$mcDD$sp$:(Lscala/Function1;D)D
  #247 = Utf8               apply$mcFD$sp
  #248 = Utf8               (D)F
  #249 = Utf8               apply$mcFD$sp$
  #250 = Utf8               (Lscala/Function1;D)F
  #251 = NameAndType        #249:#250     // apply$mcFD$sp$:(Lscala/Function1;D)F
  #252 = InterfaceMethodref #235.#251     // scala/Function1.apply$mcFD$sp$:(Lscala/Function1;D)F
  #253 = Utf8               apply$mcID$sp
  #254 = Utf8               (D)I
  #255 = Utf8               apply$mcID$sp$
  #256 = Utf8               (Lscala/Function1;D)I
  #257 = NameAndType        #255:#256     // apply$mcID$sp$:(Lscala/Function1;D)I
  #258 = InterfaceMethodref #235.#257     // scala/Function1.apply$mcID$sp$:(Lscala/Function1;D)I
  #259 = Utf8               apply$mcJD$sp
  #260 = Utf8               (D)J
  #261 = Utf8               apply$mcJD$sp$
  #262 = Utf8               (Lscala/Function1;D)J
  #263 = NameAndType        #261:#262     // apply$mcJD$sp$:(Lscala/Function1;D)J
  #264 = InterfaceMethodref #235.#263     // scala/Function1.apply$mcJD$sp$:(Lscala/Function1;D)J
  #265 = Utf8               apply$mcVD$sp
  #266 = Utf8               (D)V
  #267 = Utf8               apply$mcVD$sp$
  #268 = Utf8               (Lscala/Function1;D)V
  #269 = NameAndType        #267:#268     // apply$mcVD$sp$:(Lscala/Function1;D)V
  #270 = InterfaceMethodref #235.#269     // scala/Function1.apply$mcVD$sp$:(Lscala/Function1;D)V
  #271 = Utf8               apply$mcZF$sp
  #272 = Utf8               (F)Z
  #273 = Utf8               apply$mcZF$sp$
  #274 = Utf8               (Lscala/Function1;F)Z
  #275 = NameAndType        #273:#274     // apply$mcZF$sp$:(Lscala/Function1;F)Z
  #276 = InterfaceMethodref #235.#275     // scala/Function1.apply$mcZF$sp$:(Lscala/Function1;F)Z
  #277 = Utf8               F
  #278 = Utf8               apply$mcDF$sp
  #279 = Utf8               (F)D
  #280 = Utf8               apply$mcDF$sp$
  #281 = Utf8               (Lscala/Function1;F)D
  #282 = NameAndType        #280:#281     // apply$mcDF$sp$:(Lscala/Function1;F)D
  #283 = InterfaceMethodref #235.#282     // scala/Function1.apply$mcDF$sp$:(Lscala/Function1;F)D
  #284 = Utf8               apply$mcFF$sp
  #285 = Utf8               (F)F
  #286 = Utf8               apply$mcFF$sp$
  #287 = Utf8               (Lscala/Function1;F)F
  #288 = NameAndType        #286:#287     // apply$mcFF$sp$:(Lscala/Function1;F)F
  #289 = InterfaceMethodref #235.#288     // scala/Function1.apply$mcFF$sp$:(Lscala/Function1;F)F
  #290 = Utf8               apply$mcIF$sp
  #291 = Utf8               (F)I
  #292 = Utf8               apply$mcIF$sp$
  #293 = Utf8               (Lscala/Function1;F)I
  #294 = NameAndType        #292:#293     // apply$mcIF$sp$:(Lscala/Function1;F)I
  #295 = InterfaceMethodref #235.#294     // scala/Function1.apply$mcIF$sp$:(Lscala/Function1;F)I
  #296 = Utf8               apply$mcJF$sp
  #297 = Utf8               (F)J
  #298 = Utf8               apply$mcJF$sp$
  #299 = Utf8               (Lscala/Function1;F)J
  #300 = NameAndType        #298:#299     // apply$mcJF$sp$:(Lscala/Function1;F)J
  #301 = InterfaceMethodref #235.#300     // scala/Function1.apply$mcJF$sp$:(Lscala/Function1;F)J
  #302 = Utf8               apply$mcVF$sp
  #303 = Utf8               (F)V
  #304 = Utf8               apply$mcVF$sp$
  #305 = Utf8               (Lscala/Function1;F)V
  #306 = NameAndType        #304:#305     // apply$mcVF$sp$:(Lscala/Function1;F)V
  #307 = InterfaceMethodref #235.#306     // scala/Function1.apply$mcVF$sp$:(Lscala/Function1;F)V
  #308 = Utf8               apply$mcZI$sp
  #309 = Utf8               (I)Z
  #310 = Utf8               apply$mcZI$sp$
  #311 = Utf8               (Lscala/Function1;I)Z
  #312 = NameAndType        #310:#311     // apply$mcZI$sp$:(Lscala/Function1;I)Z
  #313 = InterfaceMethodref #235.#312     // scala/Function1.apply$mcZI$sp$:(Lscala/Function1;I)Z
  #314 = Utf8               I
  #315 = Utf8               apply$mcDI$sp
  #316 = Utf8               (I)D
  #317 = Utf8               apply$mcDI$sp$
  #318 = Utf8               (Lscala/Function1;I)D
  #319 = NameAndType        #317:#318     // apply$mcDI$sp$:(Lscala/Function1;I)D
  #320 = InterfaceMethodref #235.#319     // scala/Function1.apply$mcDI$sp$:(Lscala/Function1;I)D
  #321 = Utf8               apply$mcFI$sp
  #322 = Utf8               (I)F
  #323 = Utf8               apply$mcFI$sp$
  #324 = Utf8               (Lscala/Function1;I)F
  #325 = NameAndType        #323:#324     // apply$mcFI$sp$:(Lscala/Function1;I)F
  #326 = InterfaceMethodref #235.#325     // scala/Function1.apply$mcFI$sp$:(Lscala/Function1;I)F
  #327 = Utf8               apply$mcII$sp
  #328 = Utf8               (I)I
  #329 = Utf8               apply$mcII$sp$
  #330 = Utf8               (Lscala/Function1;I)I
  #331 = NameAndType        #329:#330     // apply$mcII$sp$:(Lscala/Function1;I)I
  #332 = InterfaceMethodref #235.#331     // scala/Function1.apply$mcII$sp$:(Lscala/Function1;I)I
  #333 = Utf8               apply$mcJI$sp
  #334 = Utf8               (I)J
  #335 = Utf8               apply$mcJI$sp$
  #336 = Utf8               (Lscala/Function1;I)J
  #337 = NameAndType        #335:#336     // apply$mcJI$sp$:(Lscala/Function1;I)J
  #338 = InterfaceMethodref #235.#337     // scala/Function1.apply$mcJI$sp$:(Lscala/Function1;I)J
  #339 = Utf8               apply$mcVI$sp
  #340 = Utf8               (I)V
  #341 = Utf8               apply$mcVI$sp$
  #342 = Utf8               (Lscala/Function1;I)V
  #343 = NameAndType        #341:#342     // apply$mcVI$sp$:(Lscala/Function1;I)V
  #344 = InterfaceMethodref #235.#343     // scala/Function1.apply$mcVI$sp$:(Lscala/Function1;I)V
  #345 = Utf8               apply$mcZJ$sp
  #346 = Utf8               (J)Z
  #347 = Utf8               apply$mcZJ$sp$
  #348 = Utf8               (Lscala/Function1;J)Z
  #349 = NameAndType        #347:#348     // apply$mcZJ$sp$:(Lscala/Function1;J)Z
  #350 = InterfaceMethodref #235.#349     // scala/Function1.apply$mcZJ$sp$:(Lscala/Function1;J)Z
  #351 = Utf8               J
  #352 = Utf8               apply$mcDJ$sp
  #353 = Utf8               (J)D
  #354 = Utf8               apply$mcDJ$sp$
  #355 = Utf8               (Lscala/Function1;J)D
  #356 = NameAndType        #354:#355     // apply$mcDJ$sp$:(Lscala/Function1;J)D
  #357 = InterfaceMethodref #235.#356     // scala/Function1.apply$mcDJ$sp$:(Lscala/Function1;J)D
  #358 = Utf8               apply$mcFJ$sp
  #359 = Utf8               (J)F
  #360 = Utf8               apply$mcFJ$sp$
  #361 = Utf8               (Lscala/Function1;J)F
  #362 = NameAndType        #360:#361     // apply$mcFJ$sp$:(Lscala/Function1;J)F
  #363 = InterfaceMethodref #235.#362     // scala/Function1.apply$mcFJ$sp$:(Lscala/Function1;J)F
  #364 = Utf8               apply$mcIJ$sp
  #365 = Utf8               (J)I
  #366 = Utf8               apply$mcIJ$sp$
  #367 = Utf8               (Lscala/Function1;J)I
  #368 = NameAndType        #366:#367     // apply$mcIJ$sp$:(Lscala/Function1;J)I
  #369 = InterfaceMethodref #235.#368     // scala/Function1.apply$mcIJ$sp$:(Lscala/Function1;J)I
  #370 = Utf8               apply$mcJJ$sp
  #371 = Utf8               (J)J
  #372 = Utf8               apply$mcJJ$sp$
  #373 = Utf8               (Lscala/Function1;J)J
  #374 = NameAndType        #372:#373     // apply$mcJJ$sp$:(Lscala/Function1;J)J
  #375 = InterfaceMethodref #235.#374     // scala/Function1.apply$mcJJ$sp$:(Lscala/Function1;J)J
  #376 = Utf8               apply$mcVJ$sp
  #377 = Utf8               (J)V
  #378 = Utf8               apply$mcVJ$sp$
  #379 = Utf8               (Lscala/Function1;J)V
  #380 = NameAndType        #378:#379     // apply$mcVJ$sp$:(Lscala/Function1;J)V
  #381 = InterfaceMethodref #235.#380     // scala/Function1.apply$mcVJ$sp$:(Lscala/Function1;J)V
  #382 = Utf8               andThen
  #383 = Utf8               (Lscala/Function1;)Lscala/Function1;
  #384 = Utf8               <A:Ljava/lang/Object;>(Lscala/Function1<Lorg/scalatest/matchers/MatchResult;TA;>;)Lscala/Function1<Lscala/collection/Iterable<TT;>;TA;>;
  #385 = Utf8               andThen$
  #386 = Utf8               (Lscala/Function1;Lscala/Function1;)Lscala/Function1;
  #387 = NameAndType        #385:#386     // andThen$:(Lscala/Function1;Lscala/Function1;)Lscala/Function1;
  #388 = InterfaceMethodref #235.#387     // scala/Function1.andThen$:(Lscala/Function1;Lscala/Function1;)Lscala/Function1;
  #389 = Utf8               apply
  #390 = Utf8               (Lscala/collection/Iterable;)Lorg/scalatest/matchers/MatchResult;
  #391 = Utf8               (Lscala/collection/Iterable<TT;>;)Lorg/scalatest/matchers/MatchResult;
  #392 = Utf8               left
  #393 = NameAndType        #67:#68       // resultOfAWordApplication$4:Lorg/scalatest/matchers/dsl/ResultOfAWordToAMatcherApplication;
  #394 = Fieldref           #2.#393       // org/scalatest/matchers/dsl/NotWord$$anon$76.resultOfAWordApplication$4:Lorg/scalatest/matchers/dsl/ResultOfAWordToAMatcherApplication;
  #395 = Utf8               org/scalatest/matchers/dsl/ResultOfAWordToAMatcherApplication
  #396 = Class              #395          // org/scalatest/matchers/dsl/ResultOfAWordToAMatcherApplication
  #397 = Utf8               aMatcher
  #398 = Utf8               ()Lorg/scalatest/matchers/AMatcher;
  #399 = NameAndType        #397:#398     // aMatcher:()Lorg/scalatest/matchers/AMatcher;
  #400 = Methodref          #396.#399     // org/scalatest/matchers/dsl/ResultOfAWordToAMatcherApplication.aMatcher:()Lorg/scalatest/matchers/AMatcher;
  #401 = Utf8               (Ljava/lang/Object;)Ljava/lang/Object;
  #402 = MethodType         #401          //  (Ljava/lang/Object;)Ljava/lang/Object;
  #403 = Utf8               $anonfun$apply$9$adapted
  #404 = Utf8               (Lorg/scalatest/matchers/AMatcher;Ljava/lang/Object;)Ljava/lang/Object;
  #405 = NameAndType        #403:#404     // $anonfun$apply$9$adapted:(Lorg/scalatest/matchers/AMatcher;Ljava/lang/Object;)Ljava/lang/Object;
  #406 = Methodref          #2.#405       // org/scalatest/matchers/dsl/NotWord$$anon$76.$anonfun$apply$9$adapted:(Lorg/scalatest/matchers/AMatcher;Ljava/lang/Object;)Ljava/lang/Object;
  #407 = MethodHandle       6:#406        // REF_invokeStatic org/scalatest/matchers/dsl/NotWord$$anon$76.$anonfun$apply$9$adapted:(Lorg/scalatest/matchers/AMatcher;Ljava/lang/Object;)Ljava/lang/Object;
  #408 = Integer            1
  #409 = Utf8               java/lang/invoke/LambdaMetafactory
  #410 = Class              #409          // java/lang/invoke/LambdaMetafactory
  #411 = Utf8               altMetafactory
  #412 = Utf8               (Ljava/lang/invoke/MethodHandles$Lookup;Ljava/lang/String;Ljava/lang/invoke/MethodType;[Ljava/lang/Object;)Ljava/lang/invoke/CallSite;
  #413 = NameAndType        #411:#412     // altMetafactory:(Ljava/lang/invoke/MethodHandles$Lookup;Ljava/lang/String;Ljava/lang/invoke/MethodType;[Ljava/lang/Object;)Ljava/lang/invoke/CallSite;
  #414 = Methodref          #410.#413     // java/lang/invoke/LambdaMetafactory.altMetafactory:(Ljava/lang/invoke/MethodHandles$Lookup;Ljava/lang/String;Ljava/lang/invoke/MethodType;[Ljava/lang/Object;)Ljava/lang/invoke/CallSite;
  #415 = MethodHandle       6:#414        // REF_invokeStatic java/lang/invoke/LambdaMetafactory.altMetafactory:(Ljava/lang/invoke/MethodHandles$Lookup;Ljava/lang/String;Ljava/lang/invoke/MethodType;[Ljava/lang/Object;)Ljava/lang/invoke/CallSite;
  #416 = Utf8               (Lorg/scalatest/matchers/AMatcher;)Lscala/Function1;
  #417 = NameAndType        #389:#416     // apply:(Lorg/scalatest/matchers/AMatcher;)Lscala/Function1;
  #418 = InvokeDynamic      #0:#417       // #0:apply:(Lorg/scalatest/matchers/AMatcher;)Lscala/Function1;
  #419 = Utf8               scala/collection/Iterable
  #420 = Class              #419          // scala/collection/Iterable
  #421 = Utf8               find
  #422 = Utf8               (Lscala/Function1;)Lscala/Option;
  #423 = NameAndType        #421:#422     // find:(Lscala/Function1;)Lscala/Option;
  #424 = InterfaceMethodref #420.#423     // scala/collection/Iterable.find:(Lscala/Function1;)Lscala/Option;
  #425 = Utf8               org/scalatest/matchers/MatchResult$
  #426 = Class              #425          // org/scalatest/matchers/MatchResult$
  #427 = Utf8               MODULE$
  #428 = Utf8               Lorg/scalatest/matchers/MatchResult$;
  #429 = NameAndType        #427:#428     // MODULE$:Lorg/scalatest/matchers/MatchResult$;
  #430 = Fieldref           #426.#429     // org/scalatest/matchers/MatchResult$.MODULE$:Lorg/scalatest/matchers/MatchResult$;
  #431 = Utf8               scala/Option
  #432 = Class              #431          // scala/Option
  #433 = Utf8               isDefined
  #434 = Utf8               ()Z
  #435 = NameAndType        #433:#434     // isDefined:()Z
  #436 = Methodref          #432.#435     // scala/Option.isDefined:()Z
  #437 = Utf8               org/scalatest/Resources$
  #438 = Class              #437          // org/scalatest/Resources$
  #439 = Utf8               Lorg/scalatest/Resources$;
  #440 = NameAndType        #427:#439     // MODULE$:Lorg/scalatest/Resources$;
  #441 = Fieldref           #438.#440     // org/scalatest/Resources$.MODULE$:Lorg/scalatest/Resources$;
  #442 = Utf8               rawContainedA
  #443 = Utf8               ()Ljava/lang/String;
  #444 = NameAndType        #442:#443     // rawContainedA:()Ljava/lang/String;
  #445 = Methodref          #438.#444     // org/scalatest/Resources$.rawContainedA:()Ljava/lang/String;
  #446 = Utf8               rawDidNotContainA
  #447 = NameAndType        #446:#443     // rawDidNotContainA:()Ljava/lang/String;
  #448 = Methodref          #438.#447     // org/scalatest/Resources$.rawDidNotContainA:()Ljava/lang/String;
  #449 = Utf8               scala/package$
  #450 = Class              #449          // scala/package$
  #451 = Utf8               Lscala/package$;
  #452 = NameAndType        #427:#451     // MODULE$:Lscala/package$;
  #453 = Fieldref           #450.#452     // scala/package$.MODULE$:Lscala/package$;
  #454 = Utf8               Vector
  #455 = Utf8               ()Lscala/collection/immutable/Vector$;
  #456 = NameAndType        #454:#455     // Vector:()Lscala/collection/immutable/Vector$;
  #457 = Methodref          #450.#456     // scala/package$.Vector:()Lscala/collection/immutable/Vector$;
  #458 = Utf8               scala/runtime/ScalaRunTime$
  #459 = Class              #458          // scala/runtime/ScalaRunTime$
  #460 = Utf8               Lscala/runtime/ScalaRunTime$;
  #461 = NameAndType        #427:#460     // MODULE$:Lscala/runtime/ScalaRunTime$;
  #462 = Fieldref           #459.#461     // scala/runtime/ScalaRunTime$.MODULE$:Lscala/runtime/ScalaRunTime$;
  #463 = Utf8               org/scalatest/UnquotedString$
  #464 = Class              #463          // org/scalatest/UnquotedString$
  #465 = Utf8               Lorg/scalatest/UnquotedString$;
  #466 = NameAndType        #427:#465     // MODULE$:Lorg/scalatest/UnquotedString$;
  #467 = Fieldref           #464.#466     // org/scalatest/UnquotedString$.MODULE$:Lorg/scalatest/UnquotedString$;
  #468 = Utf8               org/scalatest/matchers/AMatcher
  #469 = Class              #468          // org/scalatest/matchers/AMatcher
  #470 = Utf8               nounName
  #471 = NameAndType        #470:#443     // nounName:()Ljava/lang/String;
  #472 = InterfaceMethodref #469.#471     // org/scalatest/matchers/AMatcher.nounName:()Ljava/lang/String;
  #473 = Utf8               (Ljava/lang/String;)Lorg/scalatest/UnquotedString;
  #474 = NameAndType        #389:#473     // apply:(Ljava/lang/String;)Lorg/scalatest/UnquotedString;
  #475 = Methodref          #464.#474     // org/scalatest/UnquotedString$.apply:(Ljava/lang/String;)Lorg/scalatest/UnquotedString;
  #476 = Utf8               get
  #477 = Utf8               ()Ljava/lang/Object;
  #478 = NameAndType        #476:#477     // get:()Ljava/lang/Object;
  #479 = Methodref          #432.#478     // scala/Option.get:()Ljava/lang/Object;
  #480 = Utf8               (Ljava/lang/Object;)Lorg/scalatest/matchers/MatchResult;
  #481 = NameAndType        #389:#480     // apply:(Ljava/lang/Object;)Lorg/scalatest/matchers/MatchResult;
  #482 = InterfaceMethodref #469.#481     // org/scalatest/matchers/AMatcher.apply:(Ljava/lang/Object;)Lorg/scalatest/matchers/MatchResult;
  #483 = Utf8               org/scalactic/Prettifier$
  #484 = Class              #483          // org/scalactic/Prettifier$
  #485 = Utf8               Lorg/scalactic/Prettifier$;
  #486 = NameAndType        #427:#485     // MODULE$:Lorg/scalactic/Prettifier$;
  #487 = Fieldref           #484.#486     // org/scalactic/Prettifier$.MODULE$:Lorg/scalactic/Prettifier$;
  #488 = Utf8               default
  #489 = Utf8               ()Lorg/scalactic/Prettifier;
  #490 = NameAndType        #488:#489     // default:()Lorg/scalactic/Prettifier;
  #491 = Methodref          #484.#490     // org/scalactic/Prettifier$.default:()Lorg/scalactic/Prettifier;
  #492 = Utf8               org/scalatest/matchers/MatchResult
  #493 = Class              #492          // org/scalatest/matchers/MatchResult
  #494 = Utf8               negatedFailureMessage
  #495 = Utf8               (Lorg/scalactic/Prettifier;)Ljava/lang/String;
  #496 = NameAndType        #494:#495     // negatedFailureMessage:(Lorg/scalactic/Prettifier;)Ljava/lang/String;
  #497 = Methodref          #493.#496     // org/scalatest/matchers/MatchResult.negatedFailureMessage:(Lorg/scalactic/Prettifier;)Ljava/lang/String;
  #498 = Utf8               -
  #499 = String             #498          // -
  #500 = Utf8               wrapRefArray
  #501 = Utf8               ([Ljava/lang/Object;)Lscala/collection/immutable/ArraySeq;
  #502 = NameAndType        #500:#501     // wrapRefArray:([Ljava/lang/Object;)Lscala/collection/immutable/ArraySeq;
  #503 = Methodref          #459.#502     // scala/runtime/ScalaRunTime$.wrapRefArray:([Ljava/lang/Object;)Lscala/collection/immutable/ArraySeq;
  #504 = Utf8               scala/collection/immutable/Vector$
  #505 = Class              #504          // scala/collection/immutable/Vector$
  #506 = Utf8               (Lscala/collection/immutable/Seq;)Ljava/lang/Object;
  #507 = NameAndType        #389:#506     // apply:(Lscala/collection/immutable/Seq;)Ljava/lang/Object;
  #508 = Methodref          #505.#507     // scala/collection/immutable/Vector$.apply:(Lscala/collection/immutable/Seq;)Ljava/lang/Object;
  #509 = Utf8               scala/collection/immutable/IndexedSeq
  #510 = Class              #509          // scala/collection/immutable/IndexedSeq
  #511 = Utf8               (ZLjava/lang/String;Ljava/lang/String;Lscala/collection/immutable/IndexedSeq;Lscala/collection/immutable/IndexedSeq;)Lorg/scalatest/matchers/MatchResult;
  #512 = NameAndType        #389:#511     // apply:(ZLjava/lang/String;Ljava/lang/String;Lscala/collection/immutable/IndexedSeq;Lscala/collection/immutable/IndexedSeq;)Lorg/scalatest/matchers/MatchResult;
  #513 = Methodref          #426.#512     // org/scalatest/matchers/MatchResult$.apply:(ZLjava/lang/String;Ljava/lang/String;Lscala/collection/immutable/IndexedSeq;Lscala/collection/immutable/IndexedSeq;)Lorg/scalatest/matchers/MatchResult;
  #514 = Utf8               Lorg/scalatest/matchers/AMatcher;
  #515 = Utf8               matched
  #516 = Utf8               Lscala/Option;
  #517 = Utf8               Lscala/collection/Iterable;
  #518 = Utf8               java/lang/String
  #519 = Class              #518          // java/lang/String
  #520 = Utf8               [Ljava/lang/Object;
  #521 = Class              #520          // "[Ljava/lang/Object;"
  #522 = Utf8               toString
  #523 = Utf8               java/lang/StringBuilder
  #524 = Class              #523          // java/lang/StringBuilder
  #525 = Integer            12
  #526 = Utf8               <init>
  #527 = NameAndType        #526:#340     // "<init>":(I)V
  #528 = Methodref          #524.#527     // java/lang/StringBuilder."<init>":(I)V
  #529 = Utf8               not contain
  #530 = String             #529          // not contain
  #531 = Utf8               append
  #532 = Utf8               (Ljava/lang/String;)Ljava/lang/StringBuilder;
  #533 = NameAndType        #531:#532     // append:(Ljava/lang/String;)Ljava/lang/StringBuilder;
  #534 = Methodref          #524.#533     // java/lang/StringBuilder.append:(Ljava/lang/String;)Ljava/lang/StringBuilder;
  #535 = Utf8               org/scalactic/Prettifier
  #536 = Class              #535          // org/scalactic/Prettifier
  #537 = Utf8               (Ljava/lang/Object;)Ljava/lang/String;
  #538 = NameAndType        #389:#537     // apply:(Ljava/lang/Object;)Ljava/lang/String;
  #539 = InterfaceMethodref #536.#538     // org/scalactic/Prettifier.apply:(Ljava/lang/Object;)Ljava/lang/String;
  #540 = NameAndType        #522:#443     // toString:()Ljava/lang/String;
  #541 = Methodref          #524.#540     // java/lang/StringBuilder.toString:()Ljava/lang/String;
  #542 = NameAndType        #69:#70       // compose:(Lscala/Function1;)Lorg/scalatest/matchers/Matcher;
  #543 = Methodref          #2.#542       // org/scalatest/matchers/dsl/NotWord$$anon$76.compose:(Lscala/Function1;)Lorg/scalatest/matchers/Matcher;
  #544 = NameAndType        #389:#390     // apply:(Lscala/collection/Iterable;)Lorg/scalatest/matchers/MatchResult;
  #545 = Methodref          #2.#544       // org/scalatest/matchers/dsl/NotWord$$anon$76.apply:(Lscala/collection/Iterable;)Lorg/scalatest/matchers/MatchResult;
  #546 = Utf8               Ljava/lang/Object;
  #547 = Utf8               $anonfun$apply$9
  #548 = Utf8               (Lorg/scalatest/matchers/AMatcher;Ljava/lang/Object;)Z
  #549 = Utf8               aMatcher$1
  #550 = Utf8               x$2
  #551 = Utf8               matches
  #552 = NameAndType        #551:#434     // matches:()Z
  #553 = Methodref          #493.#552     // org/scalatest/matchers/MatchResult.matches:()Z
  #554 = Utf8               (Lorg/scalatest/matchers/dsl/NotWord;Lorg/scalatest/matchers/dsl/ResultOfAWordToAMatcherApplication;)V
  #555 = Utf8               $outer
  #556 = Utf8               ()V
  #557 = NameAndType        #526:#556     // "<init>":()V
  #558 = Methodref          #5.#557       // java/lang/Object."<init>":()V
  #559 = Utf8               $init$
  #560 = Utf8               (Lscala/Function1;)V
  #561 = NameAndType        #559:#560     // $init$:(Lscala/Function1;)V
  #562 = InterfaceMethodref #235.#561     // scala/Function1.$init$:(Lscala/Function1;)V
  #563 = Utf8               (Lorg/scalatest/matchers/Matcher;)V
  #564 = NameAndType        #559:#563     // $init$:(Lorg/scalatest/matchers/Matcher;)V
  #565 = InterfaceMethodref #7.#564       // org/scalatest/matchers/Matcher.$init$:(Lorg/scalatest/matchers/Matcher;)V
  #566 = NameAndType        #547:#548     // $anonfun$apply$9:(Lorg/scalatest/matchers/AMatcher;Ljava/lang/Object;)Z
  #567 = Methodref          #2.#566       // org/scalatest/matchers/dsl/NotWord$$anon$76.$anonfun$apply$9:(Lorg/scalatest/matchers/AMatcher;Ljava/lang/Object;)Z
  #568 = Utf8               scala/runtime/BoxesRunTime
  #569 = Class              #568          // scala/runtime/BoxesRunTime
  #570 = Utf8               boxToBoolean
  #571 = Utf8               (Z)Ljava/lang/Boolean;
  #572 = NameAndType        #570:#571     // boxToBoolean:(Z)Ljava/lang/Boolean;
  #573 = Methodref          #569.#572     // scala/runtime/BoxesRunTime.boxToBoolean:(Z)Ljava/lang/Boolean;
  #574 = Utf8               $deserializeLambda$
  #575 = Utf8               (Ljava/lang/invoke/SerializedLambda;)Ljava/lang/Object;
  #576 = Utf8               scala/runtime/LambdaDeserialize
  #577 = Class              #576          // scala/runtime/LambdaDeserialize
  #578 = Utf8               bootstrap
  #579 = Utf8               (Ljava/lang/invoke/MethodHandles$Lookup;Ljava/lang/String;Ljava/lang/invoke/MethodType;[Ljava/lang/invoke/MethodHandle;)Ljava/lang/invoke/CallSite;
  #580 = NameAndType        #578:#579     // bootstrap:(Ljava/lang/invoke/MethodHandles$Lookup;Ljava/lang/String;Ljava/lang/invoke/MethodType;[Ljava/lang/invoke/MethodHandle;)Ljava/lang/invoke/CallSite;
  #581 = Methodref          #577.#580     // scala/runtime/LambdaDeserialize.bootstrap:(Ljava/lang/invoke/MethodHandles$Lookup;Ljava/lang/String;Ljava/lang/invoke/MethodType;[Ljava/lang/invoke/MethodHandle;)Ljava/lang/invoke/CallSite;
  #582 = MethodHandle       6:#581        // REF_invokeStatic scala/runtime/LambdaDeserialize.bootstrap:(Ljava/lang/invoke/MethodHandles$Lookup;Ljava/lang/String;Ljava/lang/invoke/MethodType;[Ljava/lang/invoke/MethodHandle;)Ljava/lang/invoke/CallSite;
  #583 = Utf8               lambdaDeserialize
  #584 = NameAndType        #583:#575     // lambdaDeserialize:(Ljava/lang/invoke/SerializedLambda;)Ljava/lang/Object;
  #585 = InvokeDynamic      #1:#584       // #1:lambdaDeserialize:(Ljava/lang/invoke/SerializedLambda;)Ljava/lang/Object;
  #586 = Utf8               Code
  #587 = Utf8               LineNumberTable
  #588 = Utf8               LocalVariableTable
  #589 = Utf8               Signature
  #590 = Utf8               MethodParameters
  #591 = Utf8               StackMapTable
  #592 = Utf8               InnerClasses
  #593 = Utf8               EnclosingMethod
  #594 = Utf8               SourceFile
  #595 = Utf8               BootstrapMethods
  #596 = Utf8               ScalaInlineInfo
  #597 = Utf8               Scala
{
  private final org.scalatest.matchers.dsl.ResultOfAWordToAMatcherApplication resultOfAWordApplication$4;
    descriptor: Lorg/scalatest/matchers/dsl/ResultOfAWordToAMatcherApplication;
    flags: (0x0012) ACC_PRIVATE, ACC_FINAL

  public <U extends java.lang.Object> org.scalatest.matchers.Matcher<U> compose(scala.Function1<U, scala.collection.Iterable<T>>);
    descriptor: (Lscala/Function1;)Lorg/scalatest/matchers/Matcher;
    flags: (0x0001) ACC_PUBLIC
    Code:
      stack=2, locals=2, args_size=2
         0: aload_0
         1: aload_1
         2: invokestatic  #76                 // InterfaceMethod org/scalatest/matchers/Matcher.compose$:(Lorg/scalatest/matchers/Matcher;Lscala/Function1;)Lorg/scalatest/matchers/Matcher;
         5: areturn
      LineNumberTable:
        line 1572: 0
      LocalVariableTable:
        Start  Length  Slot  Name   Signature
            0       6     0  this   Lorg/scalatest/matchers/dsl/NotWord$$anon$76;
            0       6     1     g   Lscala/Function1;
    Signature: #71                          // <U:Ljava/lang/Object;>(Lscala/Function1<TU;Lscala/collection/Iterable<TT;>;>;)Lorg/scalatest/matchers/Matcher<TU;>;
    MethodParameters:
      Name                           Flags
      g                              final

  public <U extends scala.collection.Iterable<T>> org.scalatest.matchers.Matcher<U> and(org.scalatest.matchers.Matcher<U>);
    descriptor: (Lorg/scalatest/matchers/Matcher;)Lorg/scalatest/matchers/Matcher;
    flags: (0x0001) ACC_PUBLIC
    Code:
      stack=2, locals=2, args_size=2
         0: aload_0
         1: aload_1
         2: invokestatic  #87                 // InterfaceMethod org/scalatest/matchers/Matcher.and$:(Lorg/scalatest/matchers/Matcher;Lorg/scalatest/matchers/Matcher;)Lorg/scalatest/matchers/Matcher;
         5: areturn
      LineNumberTable:
        line 1572: 0
      LocalVariableTable:
        Start  Length  Slot  Name   Signature
            0       6     0  this   Lorg/scalatest/matchers/dsl/NotWord$$anon$76;
            0       6     1 rightMatcher   Lorg/scalatest/matchers/Matcher;
    Signature: #82                          // <U::Lscala/collection/Iterable<TT;>;>(Lorg/scalatest/matchers/Matcher<TU;>;)Lorg/scalatest/matchers/Matcher<TU;>;
    MethodParameters:
      Name                           Flags
      rightMatcher                   final

  public <U extends java.lang.Object, TC1 extends java.lang.Object> org.scalatest.matchers.dsl.MatcherFactory1<scala.collection.Iterable<T>, TC1> and(org.scalatest.matchers.dsl.MatcherFactory1<U, TC1>);
    descriptor: (Lorg/scalatest/matchers/dsl/MatcherFactory1;)Lorg/scalatest/matchers/dsl/MatcherFactory1;
    flags: (0x0001) ACC_PUBLIC
    Code:
      stack=2, locals=2, args_size=2
         0: aload_0
         1: aload_1
         2: invokestatic  #94                 // InterfaceMethod org/scalatest/matchers/Matcher.and$:(Lorg/scalatest/matchers/Matcher;Lorg/scalatest/matchers/dsl/MatcherFactory1;)Lorg/scalatest/matchers/dsl/MatcherFactory1;
         5: areturn
      LineNumberTable:
        line 1572: 0
      LocalVariableTable:
        Start  Length  Slot  Name   Signature
            0       6     0  this   Lorg/scalatest/matchers/dsl/NotWord$$anon$76;
            0       6     1 rightMatcherFactory1   Lorg/scalatest/matchers/dsl/MatcherFactory1;
    Signature: #90                          // <U:Ljava/lang/Object;TC1:Ljava/lang/Object;>(Lorg/scalatest/matchers/dsl/MatcherFactory1<TU;TTC1;>;)Lorg/scalatest/matchers/dsl/MatcherFactory1<Lscala/collection/Iterable<TT;>;TTC1;>;
    MethodParameters:
      Name                           Flags
      rightMatcherFactory1           final

  public <U extends scala.collection.Iterable<T>> org.scalatest.matchers.Matcher<U> or(org.scalatest.matchers.Matcher<U>);
    descriptor: (Lorg/scalatest/matchers/Matcher;)Lorg/scalatest/matchers/Matcher;
    flags: (0x0001) ACC_PUBLIC
    Code:
      stack=2, locals=2, args_size=2
         0: aload_0
         1: aload_1
         2: invokestatic  #99                 // InterfaceMethod org/scalatest/matchers/Matcher.or$:(Lorg/scalatest/matchers/Matcher;Lorg/scalatest/matchers/Matcher;)Lorg/scalatest/matchers/Matcher;
         5: areturn
      LineNumberTable:
        line 1572: 0
      LocalVariableTable:
        Start  Length  Slot  Name   Signature
            0       6     0  this   Lorg/scalatest/matchers/dsl/NotWord$$anon$76;
            0       6     1 rightMatcher   Lorg/scalatest/matchers/Matcher;
    Signature: #82                          // <U::Lscala/collection/Iterable<TT;>;>(Lorg/scalatest/matchers/Matcher<TU;>;)Lorg/scalatest/matchers/Matcher<TU;>;
    MethodParameters:
      Name                           Flags
      rightMatcher                   final

  public <U extends java.lang.Object, TC1 extends java.lang.Object> org.scalatest.matchers.dsl.MatcherFactory1<scala.collection.Iterable<T>, TC1> or(org.scalatest.matchers.dsl.MatcherFactory1<U, TC1>);
    descriptor: (Lorg/scalatest/matchers/dsl/MatcherFactory1;)Lorg/scalatest/matchers/dsl/MatcherFactory1;
    flags: (0x0001) ACC_PUBLIC
    Code:
      stack=2, locals=2, args_size=2
         0: aload_0
         1: aload_1
         2: invokestatic  #101                // InterfaceMethod org/scalatest/matchers/Matcher.or$:(Lorg/scalatest/matchers/Matcher;Lorg/scalatest/matchers/dsl/MatcherFactory1;)Lorg/scalatest/matchers/dsl/MatcherFactory1;
         5: areturn
      LineNumberTable:
        line 1572: 0
      LocalVariableTable:
        Start  Length  Slot  Name   Signature
            0       6     0  this   Lorg/scalatest/matchers/dsl/NotWord$$anon$76;
            0       6     1 rightMatcherFactory1   Lorg/scalatest/matchers/dsl/MatcherFactory1;
    Signature: #90                          // <U:Ljava/lang/Object;TC1:Ljava/lang/Object;>(Lorg/scalatest/matchers/dsl/MatcherFactory1<TU;TTC1;>;)Lorg/scalatest/matchers/dsl/MatcherFactory1<Lscala/collection/Iterable<TT;>;TTC1;>;
    MethodParameters:
      Name                           Flags
      rightMatcherFactory1           final

  public org.scalatest.matchers.Matcher<scala.collection.Iterable<T>>.AndHaveWord and(org.scalatest.matchers.dsl.HaveWord);
    descriptor: (Lorg/scalatest/matchers/dsl/HaveWord;)Lorg/scalatest/matchers/Matcher$AndHaveWord;
    flags: (0x0001) ACC_PUBLIC
    Code:
      stack=2, locals=2, args_size=2
         0: aload_0
         1: aload_1
         2: invokestatic  #107                // InterfaceMethod org/scalatest/matchers/Matcher.and$:(Lorg/scalatest/matchers/Matcher;Lorg/scalatest/matchers/dsl/HaveWord;)Lorg/scalatest/matchers/Matcher$AndHaveWord;
         5: areturn
      LineNumberTable:
        line 1572: 0
      LocalVariableTable:
        Start  Length  Slot  Name   Signature
            0       6     0  this   Lorg/scalatest/matchers/dsl/NotWord$$anon$76;
            0       6     1 haveWord   Lorg/scalatest/matchers/dsl/HaveWord;
    Signature: #103                         // (Lorg/scalatest/matchers/dsl/HaveWord;)Lorg/scalatest/matchers/Matcher<Lscala/collection/Iterable<TT;>;>.AndHaveWord;
    MethodParameters:
      Name                           Flags
      haveWord                       final

  public org.scalatest.matchers.Matcher<scala.collection.Iterable<T>>.AndContainWord and(org.scalatest.matchers.dsl.ContainWord, org.scalactic.Prettifier, org.scalactic.source.Position);
    descriptor: (Lorg/scalatest/matchers/dsl/ContainWord;Lorg/scalactic/Prettifier;Lorg/scalactic/source/Position;)Lorg/scalatest/matchers/Matcher$AndContainWord;
    flags: (0x0001) ACC_PUBLIC
    Code:
      stack=4, locals=4, args_size=4
         0: aload_0
         1: aload_1
         2: aload_2
         3: aload_3
         4: invokestatic  #116                // InterfaceMethod org/scalatest/matchers/Matcher.and$:(Lorg/scalatest/matchers/Matcher;Lorg/scalatest/matchers/dsl/ContainWord;Lorg/scalactic/Prettifier;Lorg/scalactic/source/Position;)Lorg/scalatest/matchers/Matcher$AndContainWord;
         7: areturn
      LineNumberTable:
        line 1572: 0
      LocalVariableTable:
        Start  Length  Slot  Name   Signature
            0       8     0  this   Lorg/scalatest/matchers/dsl/NotWord$$anon$76;
            0       8     1 containWord   Lorg/scalatest/matchers/dsl/ContainWord;
            0       8     2 prettifier   Lorg/scalactic/Prettifier;
            0       8     3   pos   Lorg/scalactic/source/Position;
    Signature: #110                         // (Lorg/scalatest/matchers/dsl/ContainWord;Lorg/scalactic/Prettifier;Lorg/scalactic/source/Position;)Lorg/scalatest/matchers/Matcher<Lscala/collection/Iterable<TT;>;>.AndContainWord;
    MethodParameters:
      Name                           Flags
      containWord                    final
      prettifier                     final
      pos                            final

  public org.scalatest.matchers.Matcher<scala.collection.Iterable<T>>.AndBeWord and(org.scalatest.matchers.dsl.BeWord);
    descriptor: (Lorg/scalatest/matchers/dsl/BeWord;)Lorg/scalatest/matchers/Matcher$AndBeWord;
    flags: (0x0001) ACC_PUBLIC
    Code:
      stack=2, locals=2, args_size=2
         0: aload_0
         1: aload_1
         2: invokestatic  #125                // InterfaceMethod org/scalatest/matchers/Matcher.and$:(Lorg/scalatest/matchers/Matcher;Lorg/scalatest/matchers/dsl/BeWord;)Lorg/scalatest/matchers/Matcher$AndBeWord;
         5: areturn
      LineNumberTable:
        line 1572: 0
      LocalVariableTable:
        Start  Length  Slot  Name   Signature
            0       6     0  this   Lorg/scalatest/matchers/dsl/NotWord$$anon$76;
            0       6     1 beWord   Lorg/scalatest/matchers/dsl/BeWord;
    Signature: #121                         // (Lorg/scalatest/matchers/dsl/BeWord;)Lorg/scalatest/matchers/Matcher<Lscala/collection/Iterable<TT;>;>.AndBeWord;
    MethodParameters:
      Name                           Flags
      beWord                         final

  public org.scalatest.matchers.Matcher<scala.collection.Iterable<T>>.AndFullyMatchWord and(org.scalatest.matchers.dsl.FullyMatchWord);
    descriptor: (Lorg/scalatest/matchers/dsl/FullyMatchWord;)Lorg/scalatest/matchers/Matcher$AndFullyMatchWord;
    flags: (0x0001) ACC_PUBLIC
    Code:
      stack=2, locals=2, args_size=2
         0: aload_0
         1: aload_1
         2: invokestatic  #132                // InterfaceMethod org/scalatest/matchers/Matcher.and$:(Lorg/scalatest/matchers/Matcher;Lorg/scalatest/matchers/dsl/FullyMatchWord;)Lorg/scalatest/matchers/Matcher$AndFullyMatchWord;
         5: areturn
      LineNumberTable:
        line 1572: 0
      LocalVariableTable:
        Start  Length  Slot  Name   Signature
            0       6     0  this   Lorg/scalatest/matchers/dsl/NotWord$$anon$76;
            0       6     1 fullyMatchWord   Lorg/scalatest/matchers/dsl/FullyMatchWord;
    Signature: #128                         // (Lorg/scalatest/matchers/dsl/FullyMatchWord;)Lorg/scalatest/matchers/Matcher<Lscala/collection/Iterable<TT;>;>.AndFullyMatchWord;
    MethodParameters:
      Name                           Flags
      fullyMatchWord                 final

  public org.scalatest.matchers.Matcher<scala.collection.Iterable<T>>.AndIncludeWord and(org.scalatest.matchers.dsl.IncludeWord);
    descriptor: (Lorg/scalatest/matchers/dsl/IncludeWord;)Lorg/scalatest/matchers/Matcher$AndIncludeWord;
    flags: (0x0001) ACC_PUBLIC
    Code:
      stack=2, locals=2, args_size=2
         0: aload_0
         1: aload_1
         2: invokestatic  #139                // InterfaceMethod org/scalatest/matchers/Matcher.and$:(Lorg/scalatest/matchers/Matcher;Lorg/scalatest/matchers/dsl/IncludeWord;)Lorg/scalatest/matchers/Matcher$AndIncludeWord;
         5: areturn
      LineNumberTable:
        line 1572: 0
      LocalVariableTable:
        Start  Length  Slot  Name   Signature
            0       6     0  this   Lorg/scalatest/matchers/dsl/NotWord$$anon$76;
            0       6     1 includeWord   Lorg/scalatest/matchers/dsl/IncludeWord;
    Signature: #135                         // (Lorg/scalatest/matchers/dsl/IncludeWord;)Lorg/scalatest/matchers/Matcher<Lscala/collection/Iterable<TT;>;>.AndIncludeWord;
    MethodParameters:
      Name                           Flags
      includeWord                    final

  public org.scalatest.matchers.Matcher<scala.collection.Iterable<T>>.AndStartWithWord and(org.scalatest.matchers.dsl.StartWithWord);
    descriptor: (Lorg/scalatest/matchers/dsl/StartWithWord;)Lorg/scalatest/matchers/Matcher$AndStartWithWord;
    flags: (0x0001) ACC_PUBLIC
    Code:
      stack=2, locals=2, args_size=2
         0: aload_0
         1: aload_1
         2: invokestatic  #146                // InterfaceMethod org/scalatest/matchers/Matcher.and$:(Lorg/scalatest/matchers/Matcher;Lorg/scalatest/matchers/dsl/StartWithWord;)Lorg/scalatest/matchers/Matcher$AndStartWithWord;
         5: areturn
      LineNumberTable:
        line 1572: 0
      LocalVariableTable:
        Start  Length  Slot  Name   Signature
            0       6     0  this   Lorg/scalatest/matchers/dsl/NotWord$$anon$76;
            0       6     1 startWithWord   Lorg/scalatest/matchers/dsl/StartWithWord;
    Signature: #142                         // (Lorg/scalatest/matchers/dsl/StartWithWord;)Lorg/scalatest/matchers/Matcher<Lscala/collection/Iterable<TT;>;>.AndStartWithWord;
    MethodParameters:
      Name                           Flags
      startWithWord                  final

  public org.scalatest.matchers.Matcher<scala.collection.Iterable<T>>.AndEndWithWord and(org.scalatest.matchers.dsl.EndWithWord);
    descriptor: (Lorg/scalatest/matchers/dsl/EndWithWord;)Lorg/scalatest/matchers/Matcher$AndEndWithWord;
    flags: (0x0001) ACC_PUBLIC
    Code:
      stack=2, locals=2, args_size=2
         0: aload_0
         1: aload_1
         2: invokestatic  #153                // InterfaceMethod org/scalatest/matchers/Matcher.and$:(Lorg/scalatest/matchers/Matcher;Lorg/scalatest/matchers/dsl/EndWithWord;)Lorg/scalatest/matchers/Matcher$AndEndWithWord;
         5: areturn
      LineNumberTable:
        line 1572: 0
      LocalVariableTable:
        Start  Length  Slot  Name   Signature
            0       6     0  this   Lorg/scalatest/matchers/dsl/NotWord$$anon$76;
            0       6     1 endWithWord   Lorg/scalatest/matchers/dsl/EndWithWord;
    Signature: #149                         // (Lorg/scalatest/matchers/dsl/EndWithWord;)Lorg/scalatest/matchers/Matcher<Lscala/collection/Iterable<TT;>;>.AndEndWithWord;
    MethodParameters:
      Name                           Flags
      endWithWord                    final

  public org.scalatest.matchers.Matcher<scala.collection.Iterable<T>>.AndNotWord and(org.scalatest.matchers.dsl.NotWord);
    descriptor: (Lorg/scalatest/matchers/dsl/NotWord;)Lorg/scalatest/matchers/Matcher$AndNotWord;
    flags: (0x0001) ACC_PUBLIC
    Code:
      stack=2, locals=2, args_size=2
         0: aload_0
         1: aload_1
         2: invokestatic  #160                // InterfaceMethod org/scalatest/matchers/Matcher.and$:(Lorg/scalatest/matchers/Matcher;Lorg/scalatest/matchers/dsl/NotWord;)Lorg/scalatest/matchers/Matcher$AndNotWord;
         5: areturn
      LineNumberTable:
        line 1572: 0
      LocalVariableTable:
        Start  Length  Slot  Name   Signature
            0       6     0  this   Lorg/scalatest/matchers/dsl/NotWord$$anon$76;
            0       6     1 notWord   Lorg/scalatest/matchers/dsl/NotWord;
    Signature: #156                         // (Lorg/scalatest/matchers/dsl/NotWord;)Lorg/scalatest/matchers/Matcher<Lscala/collection/Iterable<TT;>;>.AndNotWord;
    MethodParameters:
      Name                           Flags
      notWord                        final

  public org.scalatest.matchers.dsl.MatcherFactory1<scala.collection.Iterable<T>, org.scalatest.enablers.Existence> and(org.scalatest.matchers.dsl.ExistWord);
    descriptor: (Lorg/scalatest/matchers/dsl/ExistWord;)Lorg/scalatest/matchers/dsl/MatcherFactory1;
    flags: (0x0001) ACC_PUBLIC
    Code:
      stack=2, locals=2, args_size=2
         0: aload_0
         1: aload_1
         2: invokestatic  #167                // InterfaceMethod org/scalatest/matchers/Matcher.and$:(Lorg/scalatest/matchers/Matcher;Lorg/scalatest/matchers/dsl/ExistWord;)Lorg/scalatest/matchers/dsl/MatcherFactory1;
         5: areturn
      LineNumberTable:
        line 1572: 0
      LocalVariableTable:
        Start  Length  Slot  Name   Signature
            0       6     0  this   Lorg/scalatest/matchers/dsl/NotWord$$anon$76;
            0       6     1 existWord   Lorg/scalatest/matchers/dsl/ExistWord;
    Signature: #163                         // (Lorg/scalatest/matchers/dsl/ExistWord;)Lorg/scalatest/matchers/dsl/MatcherFactory1<Lscala/collection/Iterable<TT;>;Lorg/scalatest/enablers/Existence;>;
    MethodParameters:
      Name                           Flags
      existWord                      final

  public org.scalatest.matchers.dsl.MatcherFactory1<scala.collection.Iterable<T>, org.scalatest.enablers.Existence> and(org.scalatest.matchers.dsl.ResultOfNotExist);
    descriptor: (Lorg/scalatest/matchers/dsl/ResultOfNotExist;)Lorg/scalatest/matchers/dsl/MatcherFactory1;
    flags: (0x0001) ACC_PUBLIC
    Code:
      stack=2, locals=2, args_size=2
         0: aload_0
         1: aload_1
         2: invokestatic  #174                // InterfaceMethod org/scalatest/matchers/Matcher.and$:(Lorg/scalatest/matchers/Matcher;Lorg/scalatest/matchers/dsl/ResultOfNotExist;)Lorg/scalatest/matchers/dsl/MatcherFactory1;
         5: areturn
      LineNumberTable:
        line 1572: 0
      LocalVariableTable:
        Start  Length  Slot  Name   Signature
            0       6     0  this   Lorg/scalatest/matchers/dsl/NotWord$$anon$76;
            0       6     1 notExist   Lorg/scalatest/matchers/dsl/ResultOfNotExist;
    Signature: #170                         // (Lorg/scalatest/matchers/dsl/ResultOfNotExist;)Lorg/scalatest/matchers/dsl/MatcherFactory1<Lscala/collection/Iterable<TT;>;Lorg/scalatest/enablers/Existence;>;
    MethodParameters:
      Name                           Flags
      notExist                       final

  public org.scalatest.matchers.Matcher<scala.collection.Iterable<T>>.OrHaveWord or(org.scalatest.matchers.dsl.HaveWord);
    descriptor: (Lorg/scalatest/matchers/dsl/HaveWord;)Lorg/scalatest/matchers/Matcher$OrHaveWord;
    flags: (0x0001) ACC_PUBLIC
    Code:
      stack=2, locals=2, args_size=2
         0: aload_0
         1: aload_1
         2: invokestatic  #180                // InterfaceMethod org/scalatest/matchers/Matcher.or$:(Lorg/scalatest/matchers/Matcher;Lorg/scalatest/matchers/dsl/HaveWord;)Lorg/scalatest/matchers/Matcher$OrHaveWord;
         5: areturn
      LineNumberTable:
        line 1572: 0
      LocalVariableTable:
        Start  Length  Slot  Name   Signature
            0       6     0  this   Lorg/scalatest/matchers/dsl/NotWord$$anon$76;
            0       6     1 haveWord   Lorg/scalatest/matchers/dsl/HaveWord;
    Signature: #177                         // (Lorg/scalatest/matchers/dsl/HaveWord;)Lorg/scalatest/matchers/Matcher<Lscala/collection/Iterable<TT;>;>.OrHaveWord;
    MethodParameters:
      Name                           Flags
      haveWord                       final

  public org.scalatest.matchers.Matcher<scala.collection.Iterable<T>>.OrContainWord or(org.scalatest.matchers.dsl.ContainWord, org.scalactic.Prettifier, org.scalactic.source.Position);
    descriptor: (Lorg/scalatest/matchers/dsl/ContainWord;Lorg/scalactic/Prettifier;Lorg/scalactic/source/Position;)Lorg/scalatest/matchers/Matcher$OrContainWord;
    flags: (0x0001) ACC_PUBLIC
    Code:
      stack=4, locals=4, args_size=4
         0: aload_0
         1: aload_1
         2: aload_2
         3: aload_3
         4: invokestatic  #185                // InterfaceMethod org/scalatest/matchers/Matcher.or$:(Lorg/scalatest/matchers/Matcher;Lorg/scalatest/matchers/dsl/ContainWord;Lorg/scalactic/Prettifier;Lorg/scalactic/source/Position;)Lorg/scalatest/matchers/Matcher$OrContainWord;
         7: areturn
      LineNumberTable:
        line 1572: 0
      LocalVariableTable:
        Start  Length  Slot  Name   Signature
            0       8     0  this   Lorg/scalatest/matchers/dsl/NotWord$$anon$76;
            0       8     1 containWord   Lorg/scalatest/matchers/dsl/ContainWord;
            0       8     2 prettifier   Lorg/scalactic/Prettifier;
            0       8     3   pos   Lorg/scalactic/source/Position;
    Signature: #182                         // (Lorg/scalatest/matchers/dsl/ContainWord;Lorg/scalactic/Prettifier;Lorg/scalactic/source/Position;)Lorg/scalatest/matchers/Matcher<Lscala/collection/Iterable<TT;>;>.OrContainWord;
    MethodParameters:
      Name                           Flags
      containWord                    final
      prettifier                     final
      pos                            final

  public org.scalatest.matchers.Matcher<scala.collection.Iterable<T>>.OrBeWord or(org.scalatest.matchers.dsl.BeWord);
    descriptor: (Lorg/scalatest/matchers/dsl/BeWord;)Lorg/scalatest/matchers/Matcher$OrBeWord;
    flags: (0x0001) ACC_PUBLIC
    Code:
      stack=2, locals=2, args_size=2
         0: aload_0
         1: aload_1
         2: invokestatic  #190                // InterfaceMethod org/scalatest/matchers/Matcher.or$:(Lorg/scalatest/matchers/Matcher;Lorg/scalatest/matchers/dsl/BeWord;)Lorg/scalatest/matchers/Matcher$OrBeWord;
         5: areturn
      LineNumberTable:
        line 1572: 0
      LocalVariableTable:
        Start  Length  Slot  Name   Signature
            0       6     0  this   Lorg/scalatest/matchers/dsl/NotWord$$anon$76;
            0       6     1 beWord   Lorg/scalatest/matchers/dsl/BeWord;
    Signature: #187                         // (Lorg/scalatest/matchers/dsl/BeWord;)Lorg/scalatest/matchers/Matcher<Lscala/collection/Iterable<TT;>;>.OrBeWord;
    MethodParameters:
      Name                           Flags
      beWord                         final

  public org.scalatest.matchers.Matcher<scala.collection.Iterable<T>>.OrFullyMatchWord or(org.scalatest.matchers.dsl.FullyMatchWord);
    descriptor: (Lorg/scalatest/matchers/dsl/FullyMatchWord;)Lorg/scalatest/matchers/Matcher$OrFullyMatchWord;
    flags: (0x0001) ACC_PUBLIC
    Code:
      stack=2, locals=2, args_size=2
         0: aload_0
         1: aload_1
         2: invokestatic  #195                // InterfaceMethod org/scalatest/matchers/Matcher.or$:(Lorg/scalatest/matchers/Matcher;Lorg/scalatest/matchers/dsl/FullyMatchWord;)Lorg/scalatest/matchers/Matcher$OrFullyMatchWord;
         5: areturn
      LineNumberTable:
        line 1572: 0
      LocalVariableTable:
        Start  Length  Slot  Name   Signature
            0       6     0  this   Lorg/scalatest/matchers/dsl/NotWord$$anon$76;
            0       6     1 fullyMatchWord   Lorg/scalatest/matchers/dsl/FullyMatchWord;
    Signature: #192                         // (Lorg/scalatest/matchers/dsl/FullyMatchWord;)Lorg/scalatest/matchers/Matcher<Lscala/collection/Iterable<TT;>;>.OrFullyMatchWord;
    MethodParameters:
      Name                           Flags
      fullyMatchWord                 final

  public org.scalatest.matchers.Matcher<scala.collection.Iterable<T>>.OrIncludeWord or(org.scalatest.matchers.dsl.IncludeWord);
    descriptor: (Lorg/scalatest/matchers/dsl/IncludeWord;)Lorg/scalatest/matchers/Matcher$OrIncludeWord;
    flags: (0x0001) ACC_PUBLIC
    Code:
      stack=2, locals=2, args_size=2
         0: aload_0
         1: aload_1
         2: invokestatic  #200                // InterfaceMethod org/scalatest/matchers/Matcher.or$:(Lorg/scalatest/matchers/Matcher;Lorg/scalatest/matchers/dsl/IncludeWord;)Lorg/scalatest/matchers/Matcher$OrIncludeWord;
         5: areturn
      LineNumberTable:
        line 1572: 0
      LocalVariableTable:
        Start  Length  Slot  Name   Signature
            0       6     0  this   Lorg/scalatest/matchers/dsl/NotWord$$anon$76;
            0       6     1 includeWord   Lorg/scalatest/matchers/dsl/IncludeWord;
    Signature: #197                         // (Lorg/scalatest/matchers/dsl/IncludeWord;)Lorg/scalatest/matchers/Matcher<Lscala/collection/Iterable<TT;>;>.OrIncludeWord;
    MethodParameters:
      Name                           Flags
      includeWord                    final

  public org.scalatest.matchers.Matcher<scala.collection.Iterable<T>>.OrStartWithWord or(org.scalatest.matchers.dsl.StartWithWord);
    descriptor: (Lorg/scalatest/matchers/dsl/StartWithWord;)Lorg/scalatest/matchers/Matcher$OrStartWithWord;
    flags: (0x0001) ACC_PUBLIC
    Code:
      stack=2, locals=2, args_size=2
         0: aload_0
         1: aload_1
         2: invokestatic  #205                // InterfaceMethod org/scalatest/matchers/Matcher.or$:(Lorg/scalatest/matchers/Matcher;Lorg/scalatest/matchers/dsl/StartWithWord;)Lorg/scalatest/matchers/Matcher$OrStartWithWord;
         5: areturn
      LineNumberTable:
        line 1572: 0
      LocalVariableTable:
        Start  Length  Slot  Name   Signature
            0       6     0  this   Lorg/scalatest/matchers/dsl/NotWord$$anon$76;
            0       6     1 startWithWord   Lorg/scalatest/matchers/dsl/StartWithWord;
    Signature: #202                         // (Lorg/scalatest/matchers/dsl/StartWithWord;)Lorg/scalatest/matchers/Matcher<Lscala/collection/Iterable<TT;>;>.OrStartWithWord;
    MethodParameters:
      Name                           Flags
      startWithWord                  final

  public org.scalatest.matchers.Matcher<scala.collection.Iterable<T>>.OrEndWithWord or(org.scalatest.matchers.dsl.EndWithWord);
    descriptor: (Lorg/scalatest/matchers/dsl/EndWithWord;)Lorg/scalatest/matchers/Matcher$OrEndWithWord;
    flags: (0x0001) ACC_PUBLIC
    Code:
      stack=2, locals=2, args_size=2
         0: aload_0
         1: aload_1
         2: invokestatic  #210                // InterfaceMethod org/scalatest/matchers/Matcher.or$:(Lorg/scalatest/matchers/Matcher;Lorg/scalatest/matchers/dsl/EndWithWord;)Lorg/scalatest/matchers/Matcher$OrEndWithWord;
         5: areturn
      LineNumberTable:
        line 1572: 0
      LocalVariableTable:
        Start  Length  Slot  Name   Signature
            0       6     0  this   Lorg/scalatest/matchers/dsl/NotWord$$anon$76;
            0       6     1 endWithWord   Lorg/scalatest/matchers/dsl/EndWithWord;
    Signature: #207                         // (Lorg/scalatest/matchers/dsl/EndWithWord;)Lorg/scalatest/matchers/Matcher<Lscala/collection/Iterable<TT;>;>.OrEndWithWord;
    MethodParameters:
      Name                           Flags
      endWithWord                    final

  public org.scalatest.matchers.Matcher<scala.collection.Iterable<T>>.OrNotWord or(org.scalatest.matchers.dsl.NotWord);
    descriptor: (Lorg/scalatest/matchers/dsl/NotWord;)Lorg/scalatest/matchers/Matcher$OrNotWord;
    flags: (0x0001) ACC_PUBLIC
    Code:
      stack=2, locals=2, args_size=2
         0: aload_0
         1: aload_1
         2: invokestatic  #215                // InterfaceMethod org/scalatest/matchers/Matcher.or$:(Lorg/scalatest/matchers/Matcher;Lorg/scalatest/matchers/dsl/NotWord;)Lorg/scalatest/matchers/Matcher$OrNotWord;
         5: areturn
      LineNumberTable:
        line 1572: 0
      LocalVariableTable:
        Start  Length  Slot  Name   Signature
            0       6     0  this   Lorg/scalatest/matchers/dsl/NotWord$$anon$76;
            0       6     1 notWord   Lorg/scalatest/matchers/dsl/NotWord;
    Signature: #212                         // (Lorg/scalatest/matchers/dsl/NotWord;)Lorg/scalatest/matchers/Matcher<Lscala/collection/Iterable<TT;>;>.OrNotWord;
    MethodParameters:
      Name                           Flags
      notWord                        final

  public org.scalatest.matchers.dsl.MatcherFactory1<scala.collection.Iterable<T>, org.scalatest.enablers.Existence> or(org.scalatest.matchers.dsl.ExistWord);
    descriptor: (Lorg/scalatest/matchers/dsl/ExistWord;)Lorg/scalatest/matchers/dsl/MatcherFactory1;
    flags: (0x0001) ACC_PUBLIC
    Code:
      stack=2, locals=2, args_size=2
         0: aload_0
         1: aload_1
         2: invokestatic  #217                // InterfaceMethod org/scalatest/matchers/Matcher.or$:(Lorg/scalatest/matchers/Matcher;Lorg/scalatest/matchers/dsl/ExistWord;)Lorg/scalatest/matchers/dsl/MatcherFactory1;
         5: areturn
      LineNumberTable:
        line 1572: 0
      LocalVariableTable:
        Start  Length  Slot  Name   Signature
            0       6     0  this   Lorg/scalatest/matchers/dsl/NotWord$$anon$76;
            0       6     1 existWord   Lorg/scalatest/matchers/dsl/ExistWord;
    Signature: #163                         // (Lorg/scalatest/matchers/dsl/ExistWord;)Lorg/scalatest/matchers/dsl/MatcherFactory1<Lscala/collection/Iterable<TT;>;Lorg/scalatest/enablers/Existence;>;
    MethodParameters:
      Name                           Flags
      existWord                      final

  public org.scalatest.matchers.dsl.MatcherFactory1<scala.collection.Iterable<T>, org.scalatest.enablers.Existence> or(org.scalatest.matchers.dsl.ResultOfNotExist);
    descriptor: (Lorg/scalatest/matchers/dsl/ResultOfNotExist;)Lorg/scalatest/matchers/dsl/MatcherFactory1;
    flags: (0x0001) ACC_PUBLIC
    Code:
      stack=2, locals=2, args_size=2
         0: aload_0
         1: aload_1
         2: invokestatic  #219                // InterfaceMethod org/scalatest/matchers/Matcher.or$:(Lorg/scalatest/matchers/Matcher;Lorg/scalatest/matchers/dsl/ResultOfNotExist;)Lorg/scalatest/matchers/dsl/MatcherFactory1;
         5: areturn
      LineNumberTable:
        line 1572: 0
      LocalVariableTable:
        Start  Length  Slot  Name   Signature
            0       6     0  this   Lorg/scalatest/matchers/dsl/NotWord$$anon$76;
            0       6     1 notExist   Lorg/scalatest/matchers/dsl/ResultOfNotExist;
    Signature: #170                         // (Lorg/scalatest/matchers/dsl/ResultOfNotExist;)Lorg/scalatest/matchers/dsl/MatcherFactory1<Lscala/collection/Iterable<TT;>;Lorg/scalatest/enablers/Existence;>;
    MethodParameters:
      Name                           Flags
      notExist                       final

  public org.scalatest.matchers.Matcher<scala.collection.Iterable<T>> mapResult(scala.Function1<org.scalatest.matchers.MatchResult, org.scalatest.matchers.MatchResult>);
    descriptor: (Lscala/Function1;)Lorg/scalatest/matchers/Matcher;
    flags: (0x0001) ACC_PUBLIC
    Code:
      stack=2, locals=2, args_size=2
         0: aload_0
         1: aload_1
         2: invokestatic  #225                // InterfaceMethod org/scalatest/matchers/Matcher.mapResult$:(Lorg/scalatest/matchers/Matcher;Lscala/Function1;)Lorg/scalatest/matchers/Matcher;
         5: areturn
      LineNumberTable:
        line 1572: 0
      LocalVariableTable:
        Start  Length  Slot  Name   Signature
            0       6     0  this   Lorg/scalatest/matchers/dsl/NotWord$$anon$76;
            0       6     1 prettify   Lscala/Function1;
    Signature: #221                         // (Lscala/Function1<Lorg/scalatest/matchers/MatchResult;Lorg/scalatest/matchers/MatchResult;>;)Lorg/scalatest/matchers/Matcher<Lscala/collection/Iterable<TT;>;>;
    MethodParameters:
      Name                           Flags
      prettify                       final

  public org.scalatest.matchers.Matcher<scala.collection.Iterable<T>> mapArgs(scala.Function1<java.lang.Object, java.lang.String>);
    descriptor: (Lscala/Function1;)Lorg/scalatest/matchers/Matcher;
    flags: (0x0001) ACC_PUBLIC
    Code:
      stack=2, locals=2, args_size=2
         0: aload_0
         1: aload_1
         2: invokestatic  #230                // InterfaceMethod org/scalatest/matchers/Matcher.mapArgs$:(Lorg/scalatest/matchers/Matcher;Lscala/Function1;)Lorg/scalatest/matchers/Matcher;
         5: areturn
      LineNumberTable:
        line 1572: 0
      LocalVariableTable:
        Start  Length  Slot  Name   Signature
            0       6     0  this   Lorg/scalatest/matchers/dsl/NotWord$$anon$76;
            0       6     1 prettify   Lscala/Function1;
    Signature: #227                         // (Lscala/Function1<Ljava/lang/Object;Ljava/lang/String;>;)Lorg/scalatest/matchers/Matcher<Lscala/collection/Iterable<TT;>;>;
    MethodParameters:
      Name                           Flags
      prettify                       final

  public boolean apply$mcZD$sp(double);
    descriptor: (D)Z
    flags: (0x0001) ACC_PUBLIC
    Code:
      stack=3, locals=3, args_size=2
         0: aload_0
         1: dload_1
         2: invokestatic  #239                // InterfaceMethod scala/Function1.apply$mcZD$sp$:(Lscala/Function1;D)Z
         5: ireturn
      LineNumberTable:
        line 1572: 0
      LocalVariableTable:
        Start  Length  Slot  Name   Signature
            0       6     0  this   Lorg/scalatest/matchers/dsl/NotWord$$anon$76;
            0       6     1    v1   D
    MethodParameters:
      Name                           Flags
      v1                             final

  public double apply$mcDD$sp(double);
    descriptor: (D)D
    flags: (0x0001) ACC_PUBLIC
    Code:
      stack=3, locals=3, args_size=2
         0: aload_0
         1: dload_1
         2: invokestatic  #246                // InterfaceMethod scala/Function1.apply$mcDD$sp$:(Lscala/Function1;D)D
         5: dreturn
      LineNumberTable:
        line 1572: 0
      LocalVariableTable:
        Start  Length  Slot  Name   Signature
            0       6     0  this   Lorg/scalatest/matchers/dsl/NotWord$$anon$76;
            0       6     1    v1   D
    MethodParameters:
      Name                           Flags
      v1                             final

  public float apply$mcFD$sp(double);
    descriptor: (D)F
    flags: (0x0001) ACC_PUBLIC
    Code:
      stack=3, locals=3, args_size=2
         0: aload_0
         1: dload_1
         2: invokestatic  #252                // InterfaceMethod scala/Function1.apply$mcFD$sp$:(Lscala/Function1;D)F
         5: freturn
      LineNumberTable:
        line 1572: 0
      LocalVariableTable:
        Start  Length  Slot  Name   Signature
            0       6     0  this   Lorg/scalatest/matchers/dsl/NotWord$$anon$76;
            0       6     1    v1   D
    MethodParameters:
      Name                           Flags
      v1                             final

  public int apply$mcID$sp(double);
    descriptor: (D)I
    flags: (0x0001) ACC_PUBLIC
    Code:
      stack=3, locals=3, args_size=2
         0: aload_0
         1: dload_1
         2: invokestatic  #258                // InterfaceMethod scala/Function1.apply$mcID$sp$:(Lscala/Function1;D)I
         5: ireturn
      LineNumberTable:
        line 1572: 0
      LocalVariableTable:
        Start  Length  Slot  Name   Signature
            0       6     0  this   Lorg/scalatest/matchers/dsl/NotWord$$anon$76;
            0       6     1    v1   D
    MethodParameters:
      Name                           Flags
      v1                             final

  public long apply$mcJD$sp(double);
    descriptor: (D)J
    flags: (0x0001) ACC_PUBLIC
    Code:
      stack=3, locals=3, args_size=2
         0: aload_0
         1: dload_1
         2: invokestatic  #264                // InterfaceMethod scala/Function1.apply$mcJD$sp$:(Lscala/Function1;D)J
         5: lreturn
      LineNumberTable:
        line 1572: 0
      LocalVariableTable:
        Start  Length  Slot  Name   Signature
            0       6     0  this   Lorg/scalatest/matchers/dsl/NotWord$$anon$76;
            0       6     1    v1   D
    MethodParameters:
      Name                           Flags
      v1                             final

  public void apply$mcVD$sp(double);
    descriptor: (D)V
    flags: (0x0001) ACC_PUBLIC
    Code:
      stack=3, locals=3, args_size=2
         0: aload_0
         1: dload_1
         2: invokestatic  #270                // InterfaceMethod scala/Function1.apply$mcVD$sp$:(Lscala/Function1;D)V
         5: return
      LineNumberTable:
        line 1572: 0
      LocalVariableTable:
        Start  Length  Slot  Name   Signature
            0       6     0  this   Lorg/scalatest/matchers/dsl/NotWord$$anon$76;
            0       6     1    v1   D
    MethodParameters:
      Name                           Flags
      v1                             final

  public boolean apply$mcZF$sp(float);
    descriptor: (F)Z
    flags: (0x0001) ACC_PUBLIC
    Code:
      stack=2, locals=2, args_size=2
         0: aload_0
         1: fload_1
         2: invokestatic  #276                // InterfaceMethod scala/Function1.apply$mcZF$sp$:(Lscala/Function1;F)Z
         5: ireturn
      LineNumberTable:
        line 1572: 0
      LocalVariableTable:
        Start  Length  Slot  Name   Signature
            0       6     0  this   Lorg/scalatest/matchers/dsl/NotWord$$anon$76;
            0       6     1    v1   F
    MethodParameters:
      Name                           Flags
      v1                             final

  public double apply$mcDF$sp(float);
    descriptor: (F)D
    flags: (0x0001) ACC_PUBLIC
    Code:
      stack=2, locals=2, args_size=2
         0: aload_0
         1: fload_1
         2: invokestatic  #283                // InterfaceMethod scala/Function1.apply$mcDF$sp$:(Lscala/Function1;F)D
         5: dreturn
      LineNumberTable:
        line 1572: 0
      LocalVariableTable:
        Start  Length  Slot  Name   Signature
            0       6     0  this   Lorg/scalatest/matchers/dsl/NotWord$$anon$76;
            0       6     1    v1   F
    MethodParameters:
      Name                           Flags
      v1                             final

  public float apply$mcFF$sp(float);
    descriptor: (F)F
    flags: (0x0001) ACC_PUBLIC
    Code:
      stack=2, locals=2, args_size=2
         0: aload_0
         1: fload_1
         2: invokestatic  #289                // InterfaceMethod scala/Function1.apply$mcFF$sp$:(Lscala/Function1;F)F
         5: freturn
      LineNumberTable:
        line 1572: 0
      LocalVariableTable:
        Start  Length  Slot  Name   Signature
            0       6     0  this   Lorg/scalatest/matchers/dsl/NotWord$$anon$76;
            0       6     1    v1   F
    MethodParameters:
      Name                           Flags
      v1                             final

  public int apply$mcIF$sp(float);
    descriptor: (F)I
    flags: (0x0001) ACC_PUBLIC
    Code:
      stack=2, locals=2, args_size=2
         0: aload_0
         1: fload_1
         2: invokestatic  #295                // InterfaceMethod scala/Function1.apply$mcIF$sp$:(Lscala/Function1;F)I
         5: ireturn
      LineNumberTable:
        line 1572: 0
      LocalVariableTable:
        Start  Length  Slot  Name   Signature
            0       6     0  this   Lorg/scalatest/matchers/dsl/NotWord$$anon$76;
            0       6     1    v1   F
    MethodParameters:
      Name                           Flags
      v1                             final

  public long apply$mcJF$sp(float);
    descriptor: (F)J
    flags: (0x0001) ACC_PUBLIC
    Code:
      stack=2, locals=2, args_size=2
         0: aload_0
         1: fload_1
         2: invokestatic  #301                // InterfaceMethod scala/Function1.apply$mcJF$sp$:(Lscala/Function1;F)J
         5: lreturn
      LineNumberTable:
        line 1572: 0
      LocalVariableTable:
        Start  Length  Slot  Name   Signature
            0       6     0  this   Lorg/scalatest/matchers/dsl/NotWord$$anon$76;
            0       6     1    v1   F
    MethodParameters:
      Name                           Flags
      v1                             final

  public void apply$mcVF$sp(float);
    descriptor: (F)V
    flags: (0x0001) ACC_PUBLIC
    Code:
      stack=2, locals=2, args_size=2
         0: aload_0
         1: fload_1
         2: invokestatic  #307                // InterfaceMethod scala/Function1.apply$mcVF$sp$:(Lscala/Function1;F)V
         5: return
      LineNumberTable:
        line 1572: 0
      LocalVariableTable:
        Start  Length  Slot  Name   Signature
            0       6     0  this   Lorg/scalatest/matchers/dsl/NotWord$$anon$76;
            0       6     1    v1   F
    MethodParameters:
      Name                           Flags
      v1                             final

  public boolean apply$mcZI$sp(int);
    descriptor: (I)Z
    flags: (0x0001) ACC_PUBLIC
    Code:
      stack=2, locals=2, args_size=2
         0: aload_0
         1: iload_1
         2: invokestatic  #313                // InterfaceMethod scala/Function1.apply$mcZI$sp$:(Lscala/Function1;I)Z
         5: ireturn
      LineNumberTable:
        line 1572: 0
      LocalVariableTable:
        Start  Length  Slot  Name   Signature
            0       6     0  this   Lorg/scalatest/matchers/dsl/NotWord$$anon$76;
            0       6     1    v1   I
    MethodParameters:
      Name                           Flags
      v1                             final

  public double apply$mcDI$sp(int);
    descriptor: (I)D
    flags: (0x0001) ACC_PUBLIC
    Code:
      stack=2, locals=2, args_size=2
         0: aload_0
         1: iload_1
         2: invokestatic  #320                // InterfaceMethod scala/Function1.apply$mcDI$sp$:(Lscala/Function1;I)D
         5: dreturn
      LineNumberTable:
        line 1572: 0
      LocalVariableTable:
        Start  Length  Slot  Name   Signature
            0       6     0  this   Lorg/scalatest/matchers/dsl/NotWord$$anon$76;
            0       6     1    v1   I
    MethodParameters:
      Name                           Flags
      v1                             final

  public float apply$mcFI$sp(int);
    descriptor: (I)F
    flags: (0x0001) ACC_PUBLIC
    Code:
      stack=2, locals=2, args_size=2
         0: aload_0
         1: iload_1
         2: invokestatic  #326                // InterfaceMethod scala/Function1.apply$mcFI$sp$:(Lscala/Function1;I)F
         5: freturn
      LineNumberTable:
        line 1572: 0
      LocalVariableTable:
        Start  Length  Slot  Name   Signature
            0       6     0  this   Lorg/scalatest/matchers/dsl/NotWord$$anon$76;
            0       6     1    v1   I
    MethodParameters:
      Name                           Flags
      v1                             final

  public int apply$mcII$sp(int);
    descriptor: (I)I
    flags: (0x0001) ACC_PUBLIC
    Code:
      stack=2, locals=2, args_size=2
         0: aload_0
         1: iload_1
         2: invokestatic  #332                // InterfaceMethod scala/Function1.apply$mcII$sp$:(Lscala/Function1;I)I
         5: ireturn
      LineNumberTable:
        line 1572: 0
      LocalVariableTable:
        Start  Length  Slot  Name   Signature
            0       6     0  this   Lorg/scalatest/matchers/dsl/NotWord$$anon$76;
            0       6     1    v1   I
    MethodParameters:
      Name                           Flags
      v1                             final

  public long apply$mcJI$sp(int);
    descriptor: (I)J
    flags: (0x0001) ACC_PUBLIC
    Code:
      stack=2, locals=2, args_size=2
         0: aload_0
         1: iload_1
         2: invokestatic  #338                // InterfaceMethod scala/Function1.apply$mcJI$sp$:(Lscala/Function1;I)J
         5: lreturn
      LineNumberTable:
        line 1572: 0
      LocalVariableTable:
        Start  Length  Slot  Name   Signature
            0       6     0  this   Lorg/scalatest/matchers/dsl/NotWord$$anon$76;
            0       6     1    v1   I
    MethodParameters:
      Name                           Flags
      v1                             final

  public void apply$mcVI$sp(int);
    descriptor: (I)V
    flags: (0x0001) ACC_PUBLIC
    Code:
      stack=2, locals=2, args_size=2
         0: aload_0
         1: iload_1
         2: invokestatic  #344                // InterfaceMethod scala/Function1.apply$mcVI$sp$:(Lscala/Function1;I)V
         5: return
      LineNumberTable:
        line 1572: 0
      LocalVariableTable:
        Start  Length  Slot  Name   Signature
            0       6     0  this   Lorg/scalatest/matchers/dsl/NotWord$$anon$76;
            0       6     1    v1   I
    MethodParameters:
      Name                           Flags
      v1                             final

  public boolean apply$mcZJ$sp(long);
    descriptor: (J)Z
    flags: (0x0001) ACC_PUBLIC
    Code:
      stack=3, locals=3, args_size=2
         0: aload_0
         1: lload_1
         2: invokestatic  #350                // InterfaceMethod scala/Function1.apply$mcZJ$sp$:(Lscala/Function1;J)Z
         5: ireturn
      LineNumberTable:
        line 1572: 0
      LocalVariableTable:
        Start  Length  Slot  Name   Signature
            0       6     0  this   Lorg/scalatest/matchers/dsl/NotWord$$anon$76;
            0       6     1    v1   J
    MethodParameters:
      Name                           Flags
      v1                             final

  public double apply$mcDJ$sp(long);
    descriptor: (J)D
    flags: (0x0001) ACC_PUBLIC
    Code:
      stack=3, locals=3, args_size=2
         0: aload_0
         1: lload_1
         2: invokestatic  #357                // InterfaceMethod scala/Function1.apply$mcDJ$sp$:(Lscala/Function1;J)D
         5: dreturn
      LineNumberTable:
        line 1572: 0
      LocalVariableTable:
        Start  Length  Slot  Name   Signature
            0       6     0  this   Lorg/scalatest/matchers/dsl/NotWord$$anon$76;
            0       6     1    v1   J
    MethodParameters:
      Name                           Flags
      v1                             final

  public float apply$mcFJ$sp(long);
    descriptor: (J)F
    flags: (0x0001) ACC_PUBLIC
    Code:
      stack=3, locals=3, args_size=2
         0: aload_0
         1: lload_1
         2: invokestatic  #363                // InterfaceMethod scala/Function1.apply$mcFJ$sp$:(Lscala/Function1;J)F
         5: freturn
      LineNumberTable:
        line 1572: 0
      LocalVariableTable:
        Start  Length  Slot  Name   Signature
            0       6     0  this   Lorg/scalatest/matchers/dsl/NotWord$$anon$76;
            0       6     1    v1   J
    MethodParameters:
      Name                           Flags
      v1                             final

  public int apply$mcIJ$sp(long);
    descriptor: (J)I
    flags: (0x0001) ACC_PUBLIC
    Code:
      stack=3, locals=3, args_size=2
         0: aload_0
         1: lload_1
         2: invokestatic  #369                // InterfaceMethod scala/Function1.apply$mcIJ$sp$:(Lscala/Function1;J)I
         5: ireturn
      LineNumberTable:
        line 1572: 0
      LocalVariableTable:
        Start  Length  Slot  Name   Signature
            0       6     0  this   Lorg/scalatest/matchers/dsl/NotWord$$anon$76;
            0       6     1    v1   J
    MethodParameters:
      Name                           Flags
      v1                             final

  public long apply$mcJJ$sp(long);
    descriptor: (J)J
    flags: (0x0001) ACC_PUBLIC
    Code:
      stack=3, locals=3, args_size=2
         0: aload_0
         1: lload_1
         2: invokestatic  #375                // InterfaceMethod scala/Function1.apply$mcJJ$sp$:(Lscala/Function1;J)J
         5: lreturn
      LineNumberTable:
        line 1572: 0
      LocalVariableTable:
        Start  Length  Slot  Name   Signature
            0       6     0  this   Lorg/scalatest/matchers/dsl/NotWord$$anon$76;
            0       6     1    v1   J
    MethodParameters:
      Name                           Flags
      v1                             final

  public void apply$mcVJ$sp(long);
    descriptor: (J)V
    flags: (0x0001) ACC_PUBLIC
    Code:
      stack=3, locals=3, args_size=2
         0: aload_0
         1: lload_1
         2: invokestatic  #381                // InterfaceMethod scala/Function1.apply$mcVJ$sp$:(Lscala/Function1;J)V
         5: return
      LineNumberTable:
        line 1572: 0
      LocalVariableTable:
        Start  Length  Slot  Name   Signature
            0       6     0  this   Lorg/scalatest/matchers/dsl/NotWord$$anon$76;
            0       6     1    v1   J
    MethodParameters:
      Name                           Flags
      v1                             final

  public <A extends java.lang.Object> scala.Function1<scala.collection.Iterable<T>, A> andThen(scala.Function1<org.scalatest.matchers.MatchResult, A>);
    descriptor: (Lscala/Function1;)Lscala/Function1;
    flags: (0x0001) ACC_PUBLIC
    Code:
      stack=2, locals=2, args_size=2
         0: aload_0
         1: aload_1
         2: invokestatic  #388                // InterfaceMethod scala/Function1.andThen$:(Lscala/Function1;Lscala/Function1;)Lscala/Function1;
         5: areturn
      LineNumberTable:
        line 1572: 0
      LocalVariableTable:
        Start  Length  Slot  Name   Signature
            0       6     0  this   Lorg/scalatest/matchers/dsl/NotWord$$anon$76;
            0       6     1     g   Lscala/Function1;
    Signature: #384                         // <A:Ljava/lang/Object;>(Lscala/Function1<Lorg/scalatest/matchers/MatchResult;TA;>;)Lscala/Function1<Lscala/collection/Iterable<TT;>;TA;>;
    MethodParameters:
      Name                           Flags
      g                              final

  public org.scalatest.matchers.MatchResult apply(scala.collection.Iterable<T>);
    descriptor: (Lscala/collection/Iterable;)Lorg/scalatest/matchers/MatchResult;
    flags: (0x0001) ACC_PUBLIC
    Code:
      stack=12, locals=4, args_size=2
         0: aload_0
         1: getfield      #394                // Field resultOfAWordApplication$4:Lorg/scalatest/matchers/dsl/ResultOfAWordToAMatcherApplication;
         4: invokevirtual #400                // Method org/scalatest/matchers/dsl/ResultOfAWordToAMatcherApplication.aMatcher:()Lorg/scalatest/matchers/AMatcher;
         7: astore_2
         8: aload_1
         9: aload_2
        10: invokedynamic #418,  0            // InvokeDynamic #0:apply:(Lorg/scalatest/matchers/AMatcher;)Lscala/Function1;
        15: invokeinterface #424,  2          // InterfaceMethod scala/collection/Iterable.find:(Lscala/Function1;)Lscala/Option;
        20: astore_3
        21: getstatic     #430                // Field org/scalatest/matchers/MatchResult$.MODULE$:Lorg/scalatest/matchers/MatchResult$;
        24: aload_3
        25: invokevirtual #436                // Method scala/Option.isDefined:()Z
        28: ifne          35
        31: iconst_1
        32: goto          36
        35: iconst_0
        36: getstatic     #441                // Field org/scalatest/Resources$.MODULE$:Lorg/scalatest/Resources$;
        39: invokevirtual #445                // Method org/scalatest/Resources$.rawContainedA:()Ljava/lang/String;
        42: getstatic     #441                // Field org/scalatest/Resources$.MODULE$:Lorg/scalatest/Resources$;
        45: invokevirtual #448                // Method org/scalatest/Resources$.rawDidNotContainA:()Ljava/lang/String;
        48: getstatic     #453                // Field scala/package$.MODULE$:Lscala/package$;
        51: invokevirtual #457                // Method scala/package$.Vector:()Lscala/collection/immutable/Vector$;
        54: getstatic     #462                // Field scala/runtime/ScalaRunTime$.MODULE$:Lscala/runtime/ScalaRunTime$;
        57: iconst_3
        58: anewarray     #5                  // class java/lang/Object
        61: dup
        62: iconst_0
        63: aload_1
        64: aastore
        65: dup
        66: iconst_1
        67: getstatic     #467                // Field org/scalatest/UnquotedString$.MODULE$:Lorg/scalatest/UnquotedString$;
        70: aload_2
        71: invokeinterface #472,  1          // InterfaceMethod org/scalatest/matchers/AMatcher.nounName:()Ljava/lang/String;
        76: invokevirtual #475                // Method org/scalatest/UnquotedString$.apply:(Ljava/lang/String;)Lorg/scalatest/UnquotedString;
        79: aastore
        80: dup
        81: iconst_2
        82: getstatic     #467                // Field org/scalatest/UnquotedString$.MODULE$:Lorg/scalatest/UnquotedString$;
        85: aload_3
        86: invokevirtual #436                // Method scala/Option.isDefined:()Z
        89: ifeq          114
        92: aload_2
        93: aload_3
        94: invokevirtual #479                // Method scala/Option.get:()Ljava/lang/Object;
        97: invokeinterface #482,  2          // InterfaceMethod org/scalatest/matchers/AMatcher.apply:(Ljava/lang/Object;)Lorg/scalatest/matchers/MatchResult;
       102: getstatic     #487                // Field org/scalactic/Prettifier$.MODULE$:Lorg/scalactic/Prettifier$;
       105: invokevirtual #491                // Method org/scalactic/Prettifier$.default:()Lorg/scalactic/Prettifier;
       108: invokevirtual #497                // Method org/scalatest/matchers/MatchResult.negatedFailureMessage:(Lorg/scalactic/Prettifier;)Ljava/lang/String;
       111: goto          117
       114: ldc_w         #499                // String -
       117: invokevirtual #475                // Method org/scalatest/UnquotedString$.apply:(Ljava/lang/String;)Lorg/scalatest/UnquotedString;
       120: aastore
       121: invokevirtual #503                // Method scala/runtime/ScalaRunTime$.wrapRefArray:([Ljava/lang/Object;)Lscala/collection/immutable/ArraySeq;
       124: invokevirtual #508                // Method scala/collection/immutable/Vector$.apply:(Lscala/collection/immutable/Seq;)Ljava/lang/Object;
       127: checkcast     #510                // class scala/collection/immutable/IndexedSeq
       130: getstatic     #453                // Field scala/package$.MODULE$:Lscala/package$;
       133: invokevirtual #457                // Method scala/package$.Vector:()Lscala/collection/immutable/Vector$;
       136: getstatic     #462                // Field scala/runtime/ScalaRunTime$.MODULE$:Lscala/runtime/ScalaRunTime$;
       139: iconst_2
       140: anewarray     #5                  // class java/lang/Object
       143: dup
       144: iconst_0
       145: aload_1
       146: aastore
       147: dup
       148: iconst_1
       149: getstatic     #467                // Field org/scalatest/UnquotedString$.MODULE$:Lorg/scalatest/UnquotedString$;
       152: aload_2
       153: invokeinterface #472,  1          // InterfaceMethod org/scalatest/matchers/AMatcher.nounName:()Ljava/lang/String;
       158: invokevirtual #475                // Method org/scalatest/UnquotedString$.apply:(Ljava/lang/String;)Lorg/scalatest/UnquotedString;
       161: aastore
       162: invokevirtual #503                // Method scala/runtime/ScalaRunTime$.wrapRefArray:([Ljava/lang/Object;)Lscala/collection/immutable/ArraySeq;
       165: invokevirtual #508                // Method scala/collection/immutable/Vector$.apply:(Lscala/collection/immutable/Seq;)Ljava/lang/Object;
       168: checkcast     #510                // class scala/collection/immutable/IndexedSeq
       171: invokevirtual #513                // Method org/scalatest/matchers/MatchResult$.apply:(ZLjava/lang/String;Ljava/lang/String;Lscala/collection/immutable/IndexedSeq;Lscala/collection/immutable/IndexedSeq;)Lorg/scalatest/matchers/MatchResult;
       174: areturn
      StackMapTable: number_of_entries = 4
        frame_type = 255 /* full_frame */
          offset_delta = 35
          locals = [ class org/scalatest/matchers/dsl/NotWord$$anon$76, class scala/collection/Iterable, class org/scalatest/matchers/AMatcher, class scala/Option ]
          stack = [ class org/scalatest/matchers/MatchResult$ ]
        frame_type = 255 /* full_frame */
          offset_delta = 0
          locals = [ class org/scalatest/matchers/dsl/NotWord$$anon$76, class scala/collection/Iterable, class org/scalatest/matchers/AMatcher, class scala/Option ]
          stack = [ class org/scalatest/matchers/MatchResult$, int ]
        frame_type = 255 /* full_frame */
          offset_delta = 77
          locals = [ class org/scalatest/matchers/dsl/NotWord$$anon$76, class scala/collection/Iterable, class org/scalatest/matchers/AMatcher, class scala/Option ]
          stack = [ class org/scalatest/matchers/MatchResult$, int, class java/lang/String, class java/lang/String, class scala/collection/immutable/Vector$, class scala/runtime/ScalaRunTime$, class "[Ljava/lang/Object;", class "[Ljava/lang/Object;", int, class org/scalatest/UnquotedString$ ]
        frame_type = 255 /* full_frame */
          offset_delta = 2
          locals = [ class org/scalatest/matchers/dsl/NotWord$$anon$76, class scala/collection/Iterable, class org/scalatest/matchers/AMatcher, class scala/Option ]
          stack = [ class org/scalatest/matchers/MatchResult$, int, class java/lang/String, class java/lang/String, class scala/collection/immutable/Vector$, class scala/runtime/ScalaRunTime$, class "[Ljava/lang/Object;", class "[Ljava/lang/Object;", int, class org/scalatest/UnquotedString$, class java/lang/String ]
      LineNumberTable:
        line 1574: 0
        line 1575: 8
        line 1576: 21
        line 1577: 24
        line 1578: 36
        line 1579: 42
        line 1580: 48
        line 1581: 130
      LocalVariableTable:
        Start  Length  Slot  Name   Signature
            8     166     2 aMatcher   Lorg/scalatest/matchers/AMatcher;
           21     153     3 matched   Lscala/Option;
            0     175     0  this   Lorg/scalatest/matchers/dsl/NotWord$$anon$76;
            0     175     1  left   Lscala/collection/Iterable;
    Signature: #391                         // (Lscala/collection/Iterable<TT;>;)Lorg/scalatest/matchers/MatchResult;
    MethodParameters:
      Name                           Flags
      left                           final

  public java.lang.String toString();
    descriptor: ()Ljava/lang/String;
    flags: (0x0001) ACC_PUBLIC
    Code:
      stack=3, locals=1, args_size=1
         0: new           #524                // class java/lang/StringBuilder
         3: dup
         4: ldc_w         #525                // int 12
         7: invokespecial #528                // Method java/lang/StringBuilder."<init>":(I)V
        10: ldc_w         #530                // String not contain
        13: invokevirtual #534                // Method java/lang/StringBuilder.append:(Ljava/lang/String;)Ljava/lang/StringBuilder;
        16: getstatic     #487                // Field org/scalactic/Prettifier$.MODULE$:Lorg/scalactic/Prettifier$;
        19: invokevirtual #491                // Method org/scalactic/Prettifier$.default:()Lorg/scalactic/Prettifier;
        22: aload_0
        23: getfield      #394                // Field resultOfAWordApplication$4:Lorg/scalatest/matchers/dsl/ResultOfAWordToAMatcherApplication;
        26: invokeinterface #539,  2          // InterfaceMethod org/scalactic/Prettifier.apply:(Ljava/lang/Object;)Ljava/lang/String;
        31: invokevirtual #534                // Method java/lang/StringBuilder.append:(Ljava/lang/String;)Ljava/lang/StringBuilder;
        34: invokevirtual #541                // Method java/lang/StringBuilder.toString:()Ljava/lang/String;
        37: areturn
      LineNumberTable:
        line 1584: 0
      LocalVariableTable:
        Start  Length  Slot  Name   Signature
            0      38     0  this   Lorg/scalatest/matchers/dsl/NotWord$$anon$76;

  public scala.Function1 compose(scala.Function1);
    descriptor: (Lscala/Function1;)Lscala/Function1;
    flags: (0x1041) ACC_PUBLIC, ACC_BRIDGE, ACC_SYNTHETIC
    Code:
      stack=2, locals=2, args_size=2
         0: aload_0
         1: aload_1
         2: invokevirtual #543                // Method compose:(Lscala/Function1;)Lorg/scalatest/matchers/Matcher;
         5: areturn
      LineNumberTable:
        line 1572: 0
      LocalVariableTable:
        Start  Length  Slot  Name   Signature
            0       6     0  this   Lorg/scalatest/matchers/dsl/NotWord$$anon$76;
            0       6     1     g   Lscala/Function1;
    MethodParameters:
      Name                           Flags
      g                              final

  public java.lang.Object apply(java.lang.Object);
    descriptor: (Ljava/lang/Object;)Ljava/lang/Object;
    flags: (0x1041) ACC_PUBLIC, ACC_BRIDGE, ACC_SYNTHETIC
    Code:
      stack=2, locals=2, args_size=2
         0: aload_0
         1: aload_1
         2: checkcast     #420                // class scala/collection/Iterable
         5: invokevirtual #545                // Method apply:(Lscala/collection/Iterable;)Lorg/scalatest/matchers/MatchResult;
         8: areturn
      LineNumberTable:
        line 1572: 0
      LocalVariableTable:
        Start  Length  Slot  Name   Signature
            0       9     0  this   Lorg/scalatest/matchers/dsl/NotWord$$anon$76;
            0       9     1    v1   Ljava/lang/Object;
    MethodParameters:
      Name                           Flags
      v1                             final

  public org.scalatest.matchers.MatchResult apply(java.lang.Object);
    descriptor: (Ljava/lang/Object;)Lorg/scalatest/matchers/MatchResult;
    flags: (0x1041) ACC_PUBLIC, ACC_BRIDGE, ACC_SYNTHETIC
    Code:
      stack=2, locals=2, args_size=2
         0: aload_0
         1: aload_1
         2: checkcast     #420                // class scala/collection/Iterable
         5: invokevirtual #545                // Method apply:(Lscala/collection/Iterable;)Lorg/scalatest/matchers/MatchResult;
         8: areturn
      LineNumberTable:
        line 1572: 0
      LocalVariableTable:
        Start  Length  Slot  Name   Signature
            0       9     0  this   Lorg/scalatest/matchers/dsl/NotWord$$anon$76;
            0       9     1  left   Ljava/lang/Object;
    MethodParameters:
      Name                           Flags
      left                           final

  public static final boolean $anonfun$apply$9(org.scalatest.matchers.AMatcher, java.lang.Object);
    descriptor: (Lorg/scalatest/matchers/AMatcher;Ljava/lang/Object;)Z
    flags: (0x1019) ACC_PUBLIC, ACC_STATIC, ACC_FINAL, ACC_SYNTHETIC
    Code:
      stack=2, locals=2, args_size=2
         0: aload_0
         1: aload_1
         2: invokeinterface #482,  2          // InterfaceMethod org/scalatest/matchers/AMatcher.apply:(Ljava/lang/Object;)Lorg/scalatest/matchers/MatchResult;
         7: invokevirtual #553                // Method org/scalatest/matchers/MatchResult.matches:()Z
        10: ireturn
      LineNumberTable:
        line 1575: 0
      LocalVariableTable:
        Start  Length  Slot  Name   Signature
            0      11     0 aMatcher$1   Lorg/scalatest/matchers/AMatcher;
            0      11     1   x$2   Ljava/lang/Object;
    MethodParameters:
      Name                           Flags
      aMatcher$1                     final
      x$2                            final

  public org.scalatest.matchers.dsl.NotWord$$anon$76(org.scalatest.matchers.dsl.NotWord, org.scalatest.matchers.dsl.ResultOfAWordToAMatcherApplication);
    descriptor: (Lorg/scalatest/matchers/dsl/NotWord;Lorg/scalatest/matchers/dsl/ResultOfAWordToAMatcherApplication;)V
    flags: (0x0001) ACC_PUBLIC
    Code:
      stack=2, locals=3, args_size=3
         0: aload_0
         1: aload_2
         2: putfield      #394                // Field resultOfAWordApplication$4:Lorg/scalatest/matchers/dsl/ResultOfAWordToAMatcherApplication;
         5: aload_0
         6: invokespecial #558                // Method java/lang/Object."<init>":()V
         9: aload_0
        10: invokestatic  #562                // InterfaceMethod scala/Function1.$init$:(Lscala/Function1;)V
        13: aload_0
        14: invokestatic  #565                // InterfaceMethod org/scalatest/matchers/Matcher.$init$:(Lorg/scalatest/matchers/Matcher;)V
        17: return
      LineNumberTable:
        line 1571: 0
        line 1572: 5
      LocalVariableTable:
        Start  Length  Slot  Name   Signature
            0      18     0  this   Lorg/scalatest/matchers/dsl/NotWord$$anon$76;
            0      18     1 $outer   Lorg/scalatest/matchers/dsl/NotWord;
            0      18     2 resultOfAWordApplication$4   Lorg/scalatest/matchers/dsl/ResultOfAWordToAMatcherApplication;
    MethodParameters:
      Name                           Flags
      $outer                         final synthetic
      resultOfAWordApplication$4     final

  public static final java.lang.Object $anonfun$apply$9$adapted(org.scalatest.matchers.AMatcher, java.lang.Object);
    descriptor: (Lorg/scalatest/matchers/AMatcher;Ljava/lang/Object;)Ljava/lang/Object;
    flags: (0x1019) ACC_PUBLIC, ACC_STATIC, ACC_FINAL, ACC_SYNTHETIC
    Code:
      stack=2, locals=2, args_size=2
         0: aload_0
         1: aload_1
         2: invokestatic  #567                // Method $anonfun$apply$9:(Lorg/scalatest/matchers/AMatcher;Ljava/lang/Object;)Z
         5: invokestatic  #573                // Method scala/runtime/BoxesRunTime.boxToBoolean:(Z)Ljava/lang/Boolean;
         8: areturn
      LineNumberTable:
        line 1575: 0
      LocalVariableTable:
        Start  Length  Slot  Name   Signature
            0       9     0 aMatcher$1   Lorg/scalatest/matchers/AMatcher;
            0       9     1   x$2   Ljava/lang/Object;
    MethodParameters:
      Name                           Flags
      aMatcher$1                     final
      x$2                            final

  private static java.lang.Object $deserializeLambda$(java.lang.invoke.SerializedLambda);
    descriptor: (Ljava/lang/invoke/SerializedLambda;)Ljava/lang/Object;
    flags: (0x100a) ACC_PRIVATE, ACC_STATIC, ACC_SYNTHETIC
    Code:
      stack=1, locals=1, args_size=1
         0: aload_0
         1: invokedynamic #585,  0            // InvokeDynamic #1:lambdaDeserialize:(Ljava/lang/invoke/SerializedLambda;)Ljava/lang/Object;
         6: areturn
}
InnerClasses:
  public static final #18= #15 of #17;    // Lookup=class java/lang/invoke/MethodHandles$Lookup of class java/lang/invoke/MethodHandles
  public final #21= #20 of #7;            // AndBeWord=class org/scalatest/matchers/Matcher$AndBeWord of class org/scalatest/matchers/Matcher
  public final #24= #23 of #7;            // AndContainWord=class org/scalatest/matchers/Matcher$AndContainWord of class org/scalatest/matchers/Matcher
  public final #27= #26 of #7;            // AndEndWithWord=class org/scalatest/matchers/Matcher$AndEndWithWord of class org/scalatest/matchers/Matcher
  public final #30= #29 of #7;            // AndFullyMatchWord=class org/scalatest/matchers/Matcher$AndFullyMatchWord of class org/scalatest/matchers/Matcher
  public final #33= #32 of #7;            // AndHaveWord=class org/scalatest/matchers/Matcher$AndHaveWord of class org/scalatest/matchers/Matcher
  public final #36= #35 of #7;            // AndIncludeWord=class org/scalatest/matchers/Matcher$AndIncludeWord of class org/scalatest/matchers/Matcher
  public final #39= #38 of #7;            // AndNotWord=class org/scalatest/matchers/Matcher$AndNotWord of class org/scalatest/matchers/Matcher
  public final #42= #41 of #7;            // AndStartWithWord=class org/scalatest/matchers/Matcher$AndStartWithWord of class org/scalatest/matchers/Matcher
  public final #45= #44 of #7;            // OrBeWord=class org/scalatest/matchers/Matcher$OrBeWord of class org/scalatest/matchers/Matcher
  public final #48= #47 of #7;            // OrContainWord=class org/scalatest/matchers/Matcher$OrContainWord of class org/scalatest/matchers/Matcher
  public final #51= #50 of #7;            // OrEndWithWord=class org/scalatest/matchers/Matcher$OrEndWithWord of class org/scalatest/matchers/Matcher
  public final #54= #53 of #7;            // OrFullyMatchWord=class org/scalatest/matchers/Matcher$OrFullyMatchWord of class org/scalatest/matchers/Matcher
  public final #57= #56 of #7;            // OrHaveWord=class org/scalatest/matchers/Matcher$OrHaveWord of class org/scalatest/matchers/Matcher
  public final #60= #59 of #7;            // OrIncludeWord=class org/scalatest/matchers/Matcher$OrIncludeWord of class org/scalatest/matchers/Matcher
  public final #63= #62 of #7;            // OrNotWord=class org/scalatest/matchers/Matcher$OrNotWord of class org/scalatest/matchers/Matcher
  public final #66= #65 of #7;            // OrStartWithWord=class org/scalatest/matchers/Matcher$OrStartWithWord of class org/scalatest/matchers/Matcher
  public final #2;                        // class org/scalatest/matchers/dsl/NotWord$$anon$76
EnclosingMethod: #10.#13                // org.scalatest.matchers.dsl.NotWord.contain
Signature: #3                           // Ljava/lang/Object;Lorg/scalatest/matchers/Matcher<Lscala/collection/Iterable<TT;>;>;
SourceFile: "NotWord.scala"
BootstrapMethods:
  0: #415 REF_invokeStatic java/lang/invoke/LambdaMetafactory.altMetafactory:(Ljava/lang/invoke/MethodHandles$Lookup;Ljava/lang/String;Ljava/lang/invoke/MethodType;[Ljava/lang/Object;)Ljava/lang/invoke/CallSite;
    Method arguments:
      #402 (Ljava/lang/Object;)Ljava/lang/Object;
      #407 REF_invokeStatic org/scalatest/matchers/dsl/NotWord$$anon$76.$anonfun$apply$9$adapted:(Lorg/scalatest/matchers/AMatcher;Ljava/lang/Object;)Ljava/lang/Object;
      #402 (Ljava/lang/Object;)Ljava/lang/Object;
      #408 1
  1: #582 REF_invokeStatic scala/runtime/LambdaDeserialize.bootstrap:(Ljava/lang/invoke/MethodHandles$Lookup;Ljava/lang/String;Ljava/lang/invoke/MethodType;[Ljava/lang/invoke/MethodHandle;)Ljava/lang/invoke/CallSite;
    Method arguments:
      #407 REF_invokeStatic org/scalatest/matchers/dsl/NotWord$$anon$76.$anonfun$apply$9$adapted:(Lorg/scalatest/matchers/AMatcher;Ljava/lang/Object;)Ljava/lang/Object;
  ScalaInlineInfo: length = 0x130 (unknown attribute)
   01 01 00 3C 02 23 02 24 01 01 93 01 94 01 02 0E
   02 2A 01 00 50 00 51 01 00 50 00 78 01 00 50 00
   6D 01 00 50 00 94 01 00 50 00 A2 01 00 50 00 7F
   01 00 50 00 66 01 00 50 00 86 01 00 50 00 59 01
   00 50 00 9B 01 00 50 00 A9 01 00 50 00 8D 01 01
   7E 01 7F 01 01 85 01 91 01 01 85 01 E0 01 01 85
   01 86 01 00 F1 00 F2 01 01 16 01 17 01 01 3B 01
   3C 01 01 60 01 61 01 00 F7 00 F8 01 01 1C 01 1D
   01 01 41 01 42 01 01 66 01 67 01 00 FD 00 FE 01
   01 22 01 23 01 01 47 01 48 01 01 6C 01 6D 01 01
   03 01 04 01 01 28 01 29 01 01 4D 01 4E 01 01 72
   01 73 01 01 09 01 0A 01 01 2E 01 2F 01 01 53 01
   54 01 01 78 01 79 01 00 E7 00 E8 01 01 0F 01 10
   01 01 34 01 35 01 01 59 01 5A 01 00 45 00 46 01
   00 45 01 7F 01 00 E2 00 46 01 00 DC 00 46 01 00
   60 00 51 01 00 60 00 BA 01 00 60 00 B5 01 00 60
   00 CE 01 00 60 00 A2 01 00 60 00 BF 01 00 60 00
   B0 01 00 60 00 C4 01 00 60 00 59 01 00 60 00 D3
   01 00 60 00 A9 01 00 60 00 C9 01 02 0A 01 BB 01

  Scala: length = 0x0 (unknown attribute)

