Classfile /Users/mw/Projects/slang-braindump/.jar/jar8/assemble/slang-braindump/assemble/content/org/scalatest/matchers/dsl/ResultOfBeThrownBy$ResultOfAndBeWord.class
  Last modified May 29, 2022; size 1335 bytes
  SHA-256 checksum 0fd15daeb945e71d52ceb74784fd9eb736af9ea19a7ec7d93491a42b47d18896
  Compiled from "ResultOfBeThrownBy.scala"
public final class org.scalatest.matchers.dsl.ResultOfBeThrownBy$ResultOfAndBeWord
  minor version: 0
  major version: 52
  flags: (0x0031) ACC_PUBLIC, ACC_FINAL, ACC_SUPER
  this_class: #2                          // org/scalatest/matchers/dsl/ResultOfBeThrownBy$ResultOfAndBeWord
  super_class: #4                         // java/lang/Object
  interfaces: 0, fields: 1, methods: 2, attributes: 4
Constant pool:
   #1 = Utf8               org/scalatest/matchers/dsl/ResultOfBeThrownBy$ResultOfAndBeWord
   #2 = Class              #1             // org/scalatest/matchers/dsl/ResultOfBeThrownBy$ResultOfAndBeWord
   #3 = Utf8               java/lang/Object
   #4 = Class              #3             // java/lang/Object
   #5 = Utf8               ResultOfBeThrownBy.scala
   #6 = Utf8               org/scalatest/matchers/dsl/ResultOfBeThrownBy
   #7 = Class              #6             // org/scalatest/matchers/dsl/ResultOfBeThrownBy
   #8 = Utf8               ResultOfAndBeWord
   #9 = Utf8               $outer
  #10 = Utf8               Lorg/scalatest/matchers/dsl/ResultOfBeThrownBy;
  #11 = Utf8               thrownBy
  #12 = Utf8               (Lscala/Function0;)Lorg/scalatest/matchers/dsl/ResultOfBeThrownBy;
  #13 = Utf8               (Lscala/Function0<Lscala/runtime/BoxedUnit;>;)Lorg/scalatest/matchers/dsl/ResultOfBeThrownBy;
  #14 = Utf8               code
  #15 = NameAndType        #9:#10         // $outer:Lorg/scalatest/matchers/dsl/ResultOfBeThrownBy;
  #16 = Fieldref           #2.#15         // org/scalatest/matchers/dsl/ResultOfBeThrownBy$ResultOfAndBeWord.$outer:Lorg/scalatest/matchers/dsl/ResultOfBeThrownBy;
  #17 = Utf8               org$scalatest$matchers$dsl$ResultOfBeThrownBy$$codeList
  #18 = Utf8               Lscala/collection/immutable/IndexedSeq;
  #19 = NameAndType        #17:#18        // org$scalatest$matchers$dsl$ResultOfBeThrownBy$$codeList:Lscala/collection/immutable/IndexedSeq;
  #20 = Fieldref           #7.#19         // org/scalatest/matchers/dsl/ResultOfBeThrownBy.org$scalatest$matchers$dsl$ResultOfBeThrownBy$$codeList:Lscala/collection/immutable/IndexedSeq;
  #21 = Utf8               scala/collection/immutable/IndexedSeq
  #22 = Class              #21            // scala/collection/immutable/IndexedSeq
  #23 = Utf8               $colon$plus
  #24 = Utf8               (Ljava/lang/Object;)Ljava/lang/Object;
  #25 = NameAndType        #23:#24        // $colon$plus:(Ljava/lang/Object;)Ljava/lang/Object;
  #26 = InterfaceMethodref #22.#25        // scala/collection/immutable/IndexedSeq.$colon$plus:(Ljava/lang/Object;)Ljava/lang/Object;
  #27 = Utf8               <init>
  #28 = Utf8               (Lscala/collection/immutable/IndexedSeq;)V
  #29 = NameAndType        #27:#28        // "<init>":(Lscala/collection/immutable/IndexedSeq;)V
  #30 = Methodref          #7.#29         // org/scalatest/matchers/dsl/ResultOfBeThrownBy."<init>":(Lscala/collection/immutable/IndexedSeq;)V
  #31 = Utf8               this
  #32 = Utf8               Lorg/scalatest/matchers/dsl/ResultOfBeThrownBy$ResultOfAndBeWord;
  #33 = Utf8               Lscala/Function0;
  #34 = Utf8               (Lorg/scalatest/matchers/dsl/ResultOfBeThrownBy;)V
  #35 = Utf8               ()V
  #36 = NameAndType        #27:#35        // "<init>":()V
  #37 = Methodref          #4.#36         // java/lang/Object."<init>":()V
  #38 = Utf8               Code
  #39 = Utf8               LineNumberTable
  #40 = Utf8               LocalVariableTable
  #41 = Utf8               Signature
  #42 = Utf8               MethodParameters
  #43 = Utf8               StackMapTable
  #44 = Utf8               InnerClasses
  #45 = Utf8               SourceFile
  #46 = Utf8               ScalaInlineInfo
  #47 = Utf8               Scala
{
  private final org.scalatest.matchers.dsl.ResultOfBeThrownBy $outer;
    descriptor: Lorg/scalatest/matchers/dsl/ResultOfBeThrownBy;
    flags: (0x1012) ACC_PRIVATE, ACC_FINAL, ACC_SYNTHETIC

  public org.scalatest.matchers.dsl.ResultOfBeThrownBy thrownBy(scala.Function0<scala.runtime.BoxedUnit>);
    descriptor: (Lscala/Function0;)Lorg/scalatest/matchers/dsl/ResultOfBeThrownBy;
    flags: (0x0001) ACC_PUBLIC
    Code:
      stack=4, locals=2, args_size=2
         0: new           #7                  // class org/scalatest/matchers/dsl/ResultOfBeThrownBy
         3: dup
         4: aload_0
         5: getfield      #16                 // Field $outer:Lorg/scalatest/matchers/dsl/ResultOfBeThrownBy;
         8: getfield      #20                 // Field org/scalatest/matchers/dsl/ResultOfBeThrownBy.org$scalatest$matchers$dsl$ResultOfBeThrownBy$$codeList:Lscala/collection/immutable/IndexedSeq;
        11: aload_1
        12: invokeinterface #26,  2           // InterfaceMethod scala/collection/immutable/IndexedSeq.$colon$plus:(Ljava/lang/Object;)Ljava/lang/Object;
        17: checkcast     #22                 // class scala/collection/immutable/IndexedSeq
        20: invokespecial #30                 // Method org/scalatest/matchers/dsl/ResultOfBeThrownBy."<init>":(Lscala/collection/immutable/IndexedSeq;)V
        23: areturn
      LineNumberTable:
        line 29: 0
      LocalVariableTable:
        Start  Length  Slot  Name   Signature
            0      24     0  this   Lorg/scalatest/matchers/dsl/ResultOfBeThrownBy$ResultOfAndBeWord;
            0      24     1  code   Lscala/Function0;
    Signature: #13                          // (Lscala/Function0<Lscala/runtime/BoxedUnit;>;)Lorg/scalatest/matchers/dsl/ResultOfBeThrownBy;
    MethodParameters:
      Name                           Flags
      code                           final

  public org.scalatest.matchers.dsl.ResultOfBeThrownBy$ResultOfAndBeWord(org.scalatest.matchers.dsl.ResultOfBeThrownBy);
    descriptor: (Lorg/scalatest/matchers/dsl/ResultOfBeThrownBy;)V
    flags: (0x0001) ACC_PUBLIC
    Code:
      stack=2, locals=2, args_size=2
         0: aload_1
         1: ifnonnull     6
         4: aconst_null
         5: athrow
         6: aload_0
         7: aload_1
         8: putfield      #16                 // Field $outer:Lorg/scalatest/matchers/dsl/ResultOfBeThrownBy;
        11: aload_0
        12: invokespecial #37                 // Method java/lang/Object."<init>":()V
        15: return
      StackMapTable: number_of_entries = 1
        frame_type = 6 /* same */
      LineNumberTable:
        line 27: 0
        line 41: 11
        line 27: 15
      LocalVariableTable:
        Start  Length  Slot  Name   Signature
            0      16     0  this   Lorg/scalatest/matchers/dsl/ResultOfBeThrownBy$ResultOfAndBeWord;
            0      16     1 $outer   Lorg/scalatest/matchers/dsl/ResultOfBeThrownBy;
    MethodParameters:
      Name                           Flags
      $outer                         final synthetic
}
InnerClasses:
  public final #8= #2 of #7;              // ResultOfAndBeWord=class org/scalatest/matchers/dsl/ResultOfBeThrownBy$ResultOfAndBeWord of class org/scalatest/matchers/dsl/ResultOfBeThrownBy
SourceFile: "ResultOfBeThrownBy.scala"
  ScalaInlineInfo: length = 0xE (unknown attribute)
   01 01 00 02 00 1B 00 22 01 00 0B 00 0C 01
  Scala: length = 0x0 (unknown attribute)

