Classfile /Users/mw/Projects/slang-braindump/.jar/jar8/assemble/slang-braindump/assemble/content/org/scalatest/matchers/dsl/ResultOfBeWordForNoException.class
  Last modified May 29, 2022; size 1769 bytes
  SHA-256 checksum ee71eb02f45951670f28d8e8db24985053daa99a6fac6edfdd6fc4946f5b177c
  Compiled from "ResultOfBeWordForNoException.scala"
public final class org.scalatest.matchers.dsl.ResultOfBeWordForNoException
  minor version: 0
  major version: 52
  flags: (0x0031) ACC_PUBLIC, ACC_FINAL, ACC_SUPER
  this_class: #2                          // org/scalatest/matchers/dsl/ResultOfBeWordForNoException
  super_class: #4                         // java/lang/Object
  interfaces: 0, fields: 1, methods: 3, attributes: 4
Constant pool:
   #1 = Utf8               org/scalatest/matchers/dsl/ResultOfBeWordForNoException
   #2 = Class              #1             // org/scalatest/matchers/dsl/ResultOfBeWordForNoException
   #3 = Utf8               java/lang/Object
   #4 = Class              #3             // java/lang/Object
   #5 = Utf8               ResultOfBeWordForNoException.scala
   #6 = Utf8               Lscala/reflect/ScalaSignature;
   #7 = Utf8               bytes
   #8 = Utf8               \u0006\u0005\u00193A!\u0002\u0004\u0003\u001f!Aa\u0003\u0001B\u0001B\u0003%q\u0003C\u0003 \u0001\u0011\u0005\u0001\u0005C\u0003%\u0001\u0011\u0005Q\u0005C\u0003=\u0001\u0011\u0005SH\u0001\u000fSKN,H\u000e^(g\u0005\u0016<vN\u001d3G_Jtu.\u0012=dKB$\u0018n\u001c8\u000b\u0005\u001dA\u0011a\u00013tY*\u0011\u0011BC\u0001\t[\u0006$8\r[3sg*\u00111\u0002D\u0001\ng\u000e\fG.\u0019;fgRT\u0011!D\u0001\u0004_J<7\u0001A\n\u0003\u0001A\u0001\"!\u0005\u000b\u000e\u0003IQ\u0011aE\u0001\u0006g\u000e\fG.Y\u0005\u0003+I\u0011a!\u00118z%\u00164\u0017a\u00019pgB\u0011\u0001$H\u0007\u00023)\u0011!dG\u0001\u0007g>,(oY3\u000b\u0005qa\u0011!C:dC2\f7\r^5d\u0013\tq\u0012D\u0001\u0005Q_NLG/[8o\u0003\u0019a\u0014N\\5u}Q\u0011\u0011e\t\t\u0003E\u0001i\u0011A\u0002\u0005\u0006-\t\u0001\raF\u0001\ti\"\u0014xn\u001e8CsR\u0011a\u0005\u000e\t\u0003OEr!\u0001K\u0018\u000f\u0005%rcB\u0001\u0016.\u001b\u0005Y#B\u0001\u0017\u000f\u0003\u0019a$o\\8u}%\tQ\"\u0003\u0002\f\u0019%\u0011\u0001GC\u0001\ba\u0006\u001c7.Y4f\u0013\t\u00114GA\u0005BgN,\'\u000f^5p]*\u0011\u0001G\u0003\u0005\u0007k\r!\t\u0019\u0001\u001c\u0002\u0007\u0019,h\u000eE\u0002\u0012oeJ!\u0001\u000f\n\u0003\u0011q\u0012\u0017P\\1nKz\u0002\"!\u0005\u001e\n\u0005m\u0012\"aA!os\u0006AAo\\*ue&tw\rF\u0001?!\ty4I\u0004\u0002A\u0003B\u0011!FE\u0005\u0003\u0005J\ta\u0001\u0015:fI\u00164\u0017B\u0001#F\u0005\u0019\u0019FO]5oO*\u0011!I\u0005
   #9 = Utf8               pos
  #10 = Utf8               Lorg/scalactic/source/Position;
  #11 = Utf8               thrownBy
  #12 = Utf8               (Lscala/Function0;)Lorg/scalatest/compatible/Assertion;
  #13 = Utf8               (Lscala/Function0<Ljava/lang/Object;>;)Lorg/scalatest/compatible/Assertion;
  #14 = Utf8               fun
  #15 = Utf8               org/scalatest/matchers/MatchersHelper$
  #16 = Class              #15            // org/scalatest/matchers/MatchersHelper$
  #17 = Utf8               MODULE$
  #18 = Utf8               Lorg/scalatest/matchers/MatchersHelper$;
  #19 = NameAndType        #17:#18        // MODULE$:Lorg/scalatest/matchers/MatchersHelper$;
  #20 = Fieldref           #16.#19        // org/scalatest/matchers/MatchersHelper$.MODULE$:Lorg/scalatest/matchers/MatchersHelper$;
  #21 = NameAndType        #9:#10         // pos:Lorg/scalactic/source/Position;
  #22 = Fieldref           #2.#21         // org/scalatest/matchers/dsl/ResultOfBeWordForNoException.pos:Lorg/scalactic/source/Position;
  #23 = Utf8               checkNoException
  #24 = Utf8               (Lscala/Function0;Lorg/scalactic/source/Position;)Lorg/scalatest/compatible/Assertion;
  #25 = NameAndType        #23:#24        // checkNoException:(Lscala/Function0;Lorg/scalactic/source/Position;)Lorg/scalatest/compatible/Assertion;
  #26 = Methodref          #16.#25        // org/scalatest/matchers/MatchersHelper$.checkNoException:(Lscala/Function0;Lorg/scalactic/source/Position;)Lorg/scalatest/compatible/Assertion;
  #27 = Utf8               this
  #28 = Utf8               Lorg/scalatest/matchers/dsl/ResultOfBeWordForNoException;
  #29 = Utf8               Lscala/Function0;
  #30 = Utf8               toString
  #31 = Utf8               ()Ljava/lang/String;
  #32 = Utf8               ResultOfBeWordForNoException
  #33 = String             #32            // ResultOfBeWordForNoException
  #34 = Utf8               <init>
  #35 = Utf8               (Lorg/scalactic/source/Position;)V
  #36 = Utf8               ()V
  #37 = NameAndType        #34:#36        // "<init>":()V
  #38 = Methodref          #4.#37         // java/lang/Object."<init>":()V
  #39 = Utf8               Code
  #40 = Utf8               LineNumberTable
  #41 = Utf8               LocalVariableTable
  #42 = Utf8               Signature
  #43 = Utf8               MethodParameters
  #44 = Utf8               SourceFile
  #45 = Utf8               RuntimeVisibleAnnotations
  #46 = Utf8               ScalaInlineInfo
  #47 = Utf8               ScalaSig
{
  private final org.scalactic.source.Position pos;
    descriptor: Lorg/scalactic/source/Position;
    flags: (0x0012) ACC_PRIVATE, ACC_FINAL

  public org.scalatest.compatible.Assertion thrownBy(scala.Function0<java.lang.Object>);
    descriptor: (Lscala/Function0;)Lorg/scalatest/compatible/Assertion;
    flags: (0x0001) ACC_PUBLIC
    Code:
      stack=3, locals=2, args_size=2
         0: getstatic     #20                 // Field org/scalatest/matchers/MatchersHelper$.MODULE$:Lorg/scalatest/matchers/MatchersHelper$;
         3: aload_1
         4: aload_0
         5: getfield      #22                 // Field pos:Lorg/scalactic/source/Position;
         8: invokevirtual #26                 // Method org/scalatest/matchers/MatchersHelper$.checkNoException:(Lscala/Function0;Lorg/scalactic/source/Position;)Lorg/scalatest/compatible/Assertion;
        11: areturn
      LineNumberTable:
        line 39: 0
      LocalVariableTable:
        Start  Length  Slot  Name   Signature
            0      12     0  this   Lorg/scalatest/matchers/dsl/ResultOfBeWordForNoException;
            0      12     1   fun   Lscala/Function0;
    Signature: #13                          // (Lscala/Function0<Ljava/lang/Object;>;)Lorg/scalatest/compatible/Assertion;
    MethodParameters:
      Name                           Flags
      fun                            final

  public java.lang.String toString();
    descriptor: ()Ljava/lang/String;
    flags: (0x0001) ACC_PUBLIC
    Code:
      stack=1, locals=1, args_size=1
         0: ldc           #33                 // String ResultOfBeWordForNoException
         2: areturn
      LineNumberTable:
        line 45: 0
      LocalVariableTable:
        Start  Length  Slot  Name   Signature
            0       3     0  this   Lorg/scalatest/matchers/dsl/ResultOfBeWordForNoException;

  public org.scalatest.matchers.dsl.ResultOfBeWordForNoException(org.scalactic.source.Position);
    descriptor: (Lorg/scalactic/source/Position;)V
    flags: (0x0001) ACC_PUBLIC
    Code:
      stack=2, locals=2, args_size=2
         0: aload_0
         1: aload_1
         2: putfield      #22                 // Field pos:Lorg/scalactic/source/Position;
         5: aload_0
         6: invokespecial #38                 // Method java/lang/Object."<init>":()V
         9: return
      LineNumberTable:
        line 28: 0
        line 47: 5
        line 28: 9
      LocalVariableTable:
        Start  Length  Slot  Name   Signature
            0      10     0  this   Lorg/scalatest/matchers/dsl/ResultOfBeWordForNoException;
            0      10     1   pos   Lorg/scalactic/source/Position;
    MethodParameters:
      Name                           Flags
      pos                            final
}
SourceFile: "ResultOfBeWordForNoException.scala"
RuntimeVisibleAnnotations:
  0: #6(#7=s#8)
    scala.reflect.ScalaSignature(
      bytes="\u0006\u0005\u00193A!\u0002\u0004\u0003\u001f!Aa\u0003\u0001B\u0001B\u0003%q\u0003C\u0003 \u0001\u0011\u0005\u0001\u0005C\u0003%\u0001\u0011\u0005Q\u0005C\u0003=\u0001\u0011\u0005SH\u0001\u000fSKN,H\u000e^(g\u0005\u0016<vN\u001d3G_Jtu.\u0012=dKB$\u0018n\u001c8\u000b\u0005\u001dA\u0011a\u00013tY*\u0011\u0011BC\u0001\t[\u0006$8\r[3sg*\u00111\u0002D\u0001\ng\u000e\fG.\u0019;fgRT\u0011!D\u0001\u0004_J<7\u0001A\n\u0003\u0001A\u0001\"!\u0005\u000b\u000e\u0003IQ\u0011aE\u0001\u0006g\u000e\fG.Y\u0005\u0003+I\u0011a!\u00118z%\u00164\u0017a\u00019pgB\u0011\u0001$H\u0007\u00023)\u0011!dG\u0001\u0007g>,(oY3\u000b\u0005qa\u0011!C:dC2\f7\r^5d\u0013\tq\u0012D\u0001\u0005Q_NLG/[8o\u0003\u0019a\u0014N\\5u}Q\u0011\u0011e\t\t\u0003E\u0001i\u0011A\u0002\u0005\u0006-\t\u0001\raF\u0001\ti\"\u0014xn\u001e8CsR\u0011a\u0005\u000e\t\u0003OEr!\u0001K\u0018\u000f\u0005%rcB\u0001\u0016.\u001b\u0005Y#B\u0001\u0017\u000f\u0003\u0019a$o\\8u}%\tQ\"\u0003\u0002\f\u0019%\u0011\u0001GC\u0001\ba\u0006\u001c7.Y4f\u0013\t\u00114GA\u0005BgN,\'\u000f^5p]*\u0011\u0001G\u0003\u0005\u0007k\r!\t\u0019\u0001\u001c\u0002\u0007\u0019,h\u000eE\u0002\u0012oeJ!\u0001\u000f\n\u0003\u0011q\u0012\u0017P\\1nKz\u0002\"!\u0005\u001e\n\u0005m\u0012\"aA!os\u0006AAo\\*ue&tw\rF\u0001?!\ty4I\u0004\u0002A\u0003B\u0011!FE\u0005\u0003\u0005J\ta\u0001\u0015:fI\u00164\u0017B\u0001#F\u0005\u0019\u0019FO]5oO*\u0011!I\u0005"
    )
  ScalaInlineInfo: length = 0x13 (unknown attribute)
   01 01 00 03 00 22 00 23 01 00 0B 00 0C 01 00 1E
   00 1F 01
  ScalaSig: length = 0x3 (unknown attribute)
   05 02 00
