Classfile /Users/mw/Projects/slang-braindump/.jar/jar8/assemble/slang-braindump/assemble/content/org/scalatest/matchers/dsl/StartWithWord.class
  Last modified May 29, 2022; size 3008 bytes
  SHA-256 checksum ad4fa6593767f932111b341a37a75f4bfc23006bc9d3aa80c1c9bc430f45d819
  Compiled from "StartWithWord.scala"
public final class org.scalatest.matchers.dsl.StartWithWord
  minor version: 0
  major version: 52
  flags: (0x0031) ACC_PUBLIC, ACC_FINAL, ACC_SUPER
  this_class: #2                          // org/scalatest/matchers/dsl/StartWithWord
  super_class: #4                         // java/lang/Object
  interfaces: 0, fields: 0, methods: 6, attributes: 5
Constant pool:
   #1 = Utf8               org/scalatest/matchers/dsl/StartWithWord
   #2 = Class              #1             // org/scalatest/matchers/dsl/StartWithWord
   #3 = Utf8               java/lang/Object
   #4 = Class              #3             // java/lang/Object
   #5 = Utf8               StartWithWord.scala
   #6 = Utf8               Lscala/reflect/ScalaSignature;
   #7 = Utf8               bytes
   #8 = Utf8               \u0006\u0005I3Aa\u0002\u0005\u0003#!)\u0001\u0004\u0001C\u00013!)A\u0004\u0001C\u0001;!)q\u0006\u0001C\u0001a!)q\u0006\u0001C\u0001y!)q\u0006\u0001C\u0001\u000b\")\u0001\u000b\u0001C!#\ni1\u000b^1si^KG\u000f[,pe\u0012T!!\u0003\u0006\u0002\u0007\u0011\u001cHN\u0003\u0002\f\u0019\u0005AQ.\u0019;dQ\u0016\u00148O\u0003\u0002\u000e\u001d\u0005I1oY1mCR,7\u000f\u001e\u0006\u0002\u001f\u0005\u0019qN]4\u0004\u0001M\u0011\u0001A\u0005\t\u0003\'Yi\u0011\u0001\u0006\u0006\u0002+\u0005)1oY1mC&\u0011q\u0003\u0006\u0002\u0007\u0003:L(+\u001a4\u0002\rqJg.\u001b;?)\u0005Q\u0002CA\u000e\u0001\u001b\u0005A\u0011!B1qa2LHC\u0001\u0010.!\ry\u0002EI\u0007\u0002\u0015%\u0011\u0011E\u0003\u0002\b\u001b\u0006$8\r[3s!\t\u0019#F\u0004\u0002%QA\u0011Q\u0005F\u0007\u0002M)\u0011q\u0005E\u0001\u0007yI|w\u000e\u001e \n\u0005%\"\u0012A\u0002)sK\u0012,g-\u0003\u0002,Y\t11\u000b\u001e:j]\u001eT!!\u000b\u000b\t\u000b9\u0012\u0001\u0019\u0001\u0012\u0002\u000bILw\r\u001b;\u0002\u000bI,w-\u001a=\u0016\u0005E*DC\u0001\u001a<!\ry\u0002e\r\t\u0003iUb\u0001\u0001B\u00037\u0007\t\u0007qGA\u0001U#\tA$\u0005\u0005\u0002\u0014s%\u0011!\b\u0006\u0002\b\u001d>$\b.\u001b8h\u0011\u0015q3\u00011\u00014)\ti\u0004IE\u0002?%y1Aa\u0010\u0003\u0001{\taAH]3gS:,W.\u001a8u}!)\u0011\t\u0002a\u0001\u0005\u0006y!/Z4fq^KG\u000f[$s_V\u00048\u000f\u0005\u0002\u001c\u0007&\u0011A\t\u0003\u0002\u0010%\u0016<W\r_,ji\"<%o\\;qgR\u0011aD\u0012\u0005\u0006\u000f\u0016\u0001\r\u0001S\u0001\u000be&<\u0007\u000e\u001e*fO\u0016D\bCA%O\u001b\u0005Q%BA&M\u0003!i\u0017\r^2iS:<\'BA\'\u0015\u0003\u0011)H/\u001b7\n\u0005=S%!\u0002*fO\u0016D\u0018\u0001\u0003;p\'R\u0014\u0018N\\4\u0015\u0003\t\u0002
   #9 = Utf8               org/scalatest/matchers/dsl/StartWithWord$$anon$1
  #10 = Class              #9             // org/scalatest/matchers/dsl/StartWithWord$$anon$1
  #11 = Utf8               org/scalatest/matchers/dsl/StartWithWord$$anon$2
  #12 = Class              #11            // org/scalatest/matchers/dsl/StartWithWord$$anon$2
  #13 = Utf8               org/scalatest/matchers/dsl/StartWithWord$$anon$3
  #14 = Class              #13            // org/scalatest/matchers/dsl/StartWithWord$$anon$3
  #15 = Utf8               apply
  #16 = Utf8               (Ljava/lang/String;)Lorg/scalatest/matchers/Matcher;
  #17 = Utf8               (Ljava/lang/String;)Lorg/scalatest/matchers/Matcher<Ljava/lang/String;>;
  #18 = Utf8               right
  #19 = Utf8               <init>
  #20 = Utf8               (Lorg/scalatest/matchers/dsl/StartWithWord;Ljava/lang/String;)V
  #21 = NameAndType        #19:#20        // "<init>":(Lorg/scalatest/matchers/dsl/StartWithWord;Ljava/lang/String;)V
  #22 = Methodref          #10.#21        // org/scalatest/matchers/dsl/StartWithWord$$anon$1."<init>":(Lorg/scalatest/matchers/dsl/StartWithWord;Ljava/lang/String;)V
  #23 = Utf8               this
  #24 = Utf8               Lorg/scalatest/matchers/dsl/StartWithWord;
  #25 = Utf8               Ljava/lang/String;
  #26 = Utf8               regex
  #27 = Utf8               <T:Ljava/lang/String;>(TT;)Lorg/scalatest/matchers/Matcher<TT;>;
  #28 = Utf8               scala/collection/StringOps$
  #29 = Class              #28            // scala/collection/StringOps$
  #30 = Utf8               MODULE$
  #31 = Utf8               Lscala/collection/StringOps$;
  #32 = NameAndType        #30:#31        // MODULE$:Lscala/collection/StringOps$;
  #33 = Fieldref           #29.#32        // scala/collection/StringOps$.MODULE$:Lscala/collection/StringOps$;
  #34 = Utf8               scala/Predef$
  #35 = Class              #34            // scala/Predef$
  #36 = Utf8               Lscala/Predef$;
  #37 = NameAndType        #30:#36        // MODULE$:Lscala/Predef$;
  #38 = Fieldref           #35.#37        // scala/Predef$.MODULE$:Lscala/Predef$;
  #39 = Utf8               augmentString
  #40 = Utf8               (Ljava/lang/String;)Ljava/lang/String;
  #41 = NameAndType        #39:#40        // augmentString:(Ljava/lang/String;)Ljava/lang/String;
  #42 = Methodref          #35.#41        // scala/Predef$.augmentString:(Ljava/lang/String;)Ljava/lang/String;
  #43 = Utf8               r$extension
  #44 = Utf8               (Ljava/lang/String;)Lscala/util/matching/Regex;
  #45 = NameAndType        #43:#44        // r$extension:(Ljava/lang/String;)Lscala/util/matching/Regex;
  #46 = Methodref          #29.#45        // scala/collection/StringOps$.r$extension:(Ljava/lang/String;)Lscala/util/matching/Regex;
  #47 = Utf8               (Lscala/util/matching/Regex;)Lorg/scalatest/matchers/Matcher;
  #48 = NameAndType        #26:#47        // regex:(Lscala/util/matching/Regex;)Lorg/scalatest/matchers/Matcher;
  #49 = Methodref          #2.#48         // org/scalatest/matchers/dsl/StartWithWord.regex:(Lscala/util/matching/Regex;)Lorg/scalatest/matchers/Matcher;
  #50 = Utf8               (Lorg/scalatest/matchers/dsl/RegexWithGroups;)Lorg/scalatest/matchers/Matcher;
  #51 = Utf8               (Lorg/scalatest/matchers/dsl/RegexWithGroups;)Lorg/scalatest/matchers/Matcher<Ljava/lang/String;>;
  #52 = Utf8               regexWithGroups
  #53 = Utf8               (Lorg/scalatest/matchers/dsl/StartWithWord;Lorg/scalatest/matchers/dsl/RegexWithGroups;)V
  #54 = NameAndType        #19:#53        // "<init>":(Lorg/scalatest/matchers/dsl/StartWithWord;Lorg/scalatest/matchers/dsl/RegexWithGroups;)V
  #55 = Methodref          #12.#54        // org/scalatest/matchers/dsl/StartWithWord$$anon$2."<init>":(Lorg/scalatest/matchers/dsl/StartWithWord;Lorg/scalatest/matchers/dsl/RegexWithGroups;)V
  #56 = Utf8               Lorg/scalatest/matchers/dsl/RegexWithGroups;
  #57 = Utf8               (Lscala/util/matching/Regex;)Lorg/scalatest/matchers/Matcher<Ljava/lang/String;>;
  #58 = Utf8               rightRegex
  #59 = Utf8               (Lorg/scalatest/matchers/dsl/StartWithWord;Lscala/util/matching/Regex;)V
  #60 = NameAndType        #19:#59        // "<init>":(Lorg/scalatest/matchers/dsl/StartWithWord;Lscala/util/matching/Regex;)V
  #61 = Methodref          #14.#60        // org/scalatest/matchers/dsl/StartWithWord$$anon$3."<init>":(Lorg/scalatest/matchers/dsl/StartWithWord;Lscala/util/matching/Regex;)V
  #62 = Utf8               Lscala/util/matching/Regex;
  #63 = Utf8               toString
  #64 = Utf8               ()Ljava/lang/String;
  #65 = Utf8               startWith
  #66 = String             #65            // startWith
  #67 = Utf8               ()V
  #68 = NameAndType        #19:#67        // "<init>":()V
  #69 = Methodref          #4.#68         // java/lang/Object."<init>":()V
  #70 = Utf8               Code
  #71 = Utf8               LineNumberTable
  #72 = Utf8               LocalVariableTable
  #73 = Utf8               Signature
  #74 = Utf8               MethodParameters
  #75 = Utf8               InnerClasses
  #76 = Utf8               SourceFile
  #77 = Utf8               RuntimeVisibleAnnotations
  #78 = Utf8               ScalaInlineInfo
  #79 = Utf8               ScalaSig
{
  public org.scalatest.matchers.Matcher<java.lang.String> apply(java.lang.String);
    descriptor: (Ljava/lang/String;)Lorg/scalatest/matchers/Matcher;
    flags: (0x0001) ACC_PUBLIC
    Code:
      stack=4, locals=2, args_size=2
         0: new           #10                 // class org/scalatest/matchers/dsl/StartWithWord$$anon$1
         3: dup
         4: aconst_null
         5: aload_1
         6: invokespecial #22                 // Method org/scalatest/matchers/dsl/StartWithWord$$anon$1."<init>":(Lorg/scalatest/matchers/dsl/StartWithWord;Ljava/lang/String;)V
         9: areturn
      LineNumberTable:
        line 42: 0
      LocalVariableTable:
        Start  Length  Slot  Name   Signature
            0      10     0  this   Lorg/scalatest/matchers/dsl/StartWithWord;
            0      10     1 right   Ljava/lang/String;
    Signature: #17                          // (Ljava/lang/String;)Lorg/scalatest/matchers/Matcher<Ljava/lang/String;>;
    MethodParameters:
      Name                           Flags
      right                          final

  public <T extends java.lang.String> org.scalatest.matchers.Matcher<T> regex(T);
    descriptor: (Ljava/lang/String;)Lorg/scalatest/matchers/Matcher;
    flags: (0x0001) ACC_PUBLIC
    Code:
      stack=4, locals=2, args_size=2
         0: aload_0
         1: getstatic     #33                 // Field scala/collection/StringOps$.MODULE$:Lscala/collection/StringOps$;
         4: getstatic     #38                 // Field scala/Predef$.MODULE$:Lscala/Predef$;
         7: aload_1
         8: invokevirtual #42                 // Method scala/Predef$.augmentString:(Ljava/lang/String;)Ljava/lang/String;
        11: invokevirtual #46                 // Method scala/collection/StringOps$.r$extension:(Ljava/lang/String;)Lscala/util/matching/Regex;
        14: invokevirtual #49                 // Method regex:(Lscala/util/matching/Regex;)Lorg/scalatest/matchers/Matcher;
        17: areturn
      LineNumberTable:
        line 62: 0
      LocalVariableTable:
        Start  Length  Slot  Name   Signature
            0      18     0  this   Lorg/scalatest/matchers/dsl/StartWithWord;
            0      18     1 right   Ljava/lang/String;
    Signature: #27                          // <T:Ljava/lang/String;>(TT;)Lorg/scalatest/matchers/Matcher<TT;>;
    MethodParameters:
      Name                           Flags
      right                          final

  public org.scalatest.matchers.Matcher<java.lang.String> regex(org.scalatest.matchers.dsl.RegexWithGroups);
    descriptor: (Lorg/scalatest/matchers/dsl/RegexWithGroups;)Lorg/scalatest/matchers/Matcher;
    flags: (0x0001) ACC_PUBLIC
    Code:
      stack=4, locals=2, args_size=2
         0: new           #12                 // class org/scalatest/matchers/dsl/StartWithWord$$anon$2
         3: dup
         4: aconst_null
         5: aload_1
         6: invokespecial #55                 // Method org/scalatest/matchers/dsl/StartWithWord$$anon$2."<init>":(Lorg/scalatest/matchers/dsl/StartWithWord;Lorg/scalatest/matchers/dsl/RegexWithGroups;)V
         9: areturn
      LineNumberTable:
        line 73: 0
      LocalVariableTable:
        Start  Length  Slot  Name   Signature
            0      10     0  this   Lorg/scalatest/matchers/dsl/StartWithWord;
            0      10     1 regexWithGroups   Lorg/scalatest/matchers/dsl/RegexWithGroups;
    Signature: #51                          // (Lorg/scalatest/matchers/dsl/RegexWithGroups;)Lorg/scalatest/matchers/Matcher<Ljava/lang/String;>;
    MethodParameters:
      Name                           Flags
      regexWithGroups                final

  public org.scalatest.matchers.Matcher<java.lang.String> regex(scala.util.matching.Regex);
    descriptor: (Lscala/util/matching/Regex;)Lorg/scalatest/matchers/Matcher;
    flags: (0x0001) ACC_PUBLIC
    Code:
      stack=4, locals=2, args_size=2
         0: new           #14                 // class org/scalatest/matchers/dsl/StartWithWord$$anon$3
         3: dup
         4: aconst_null
         5: aload_1
         6: invokespecial #61                 // Method org/scalatest/matchers/dsl/StartWithWord$$anon$3."<init>":(Lorg/scalatest/matchers/dsl/StartWithWord;Lscala/util/matching/Regex;)V
         9: areturn
      LineNumberTable:
        line 89: 0
      LocalVariableTable:
        Start  Length  Slot  Name   Signature
            0      10     0  this   Lorg/scalatest/matchers/dsl/StartWithWord;
            0      10     1 rightRegex   Lscala/util/matching/Regex;
    Signature: #57                          // (Lscala/util/matching/Regex;)Lorg/scalatest/matchers/Matcher<Ljava/lang/String;>;
    MethodParameters:
      Name                           Flags
      rightRegex                     final

  public java.lang.String toString();
    descriptor: ()Ljava/lang/String;
    flags: (0x0001) ACC_PUBLIC
    Code:
      stack=1, locals=1, args_size=1
         0: ldc           #66                 // String startWith
         2: areturn
      LineNumberTable:
        line 103: 0
      LocalVariableTable:
        Start  Length  Slot  Name   Signature
            0       3     0  this   Lorg/scalatest/matchers/dsl/StartWithWord;

  public org.scalatest.matchers.dsl.StartWithWord();
    descriptor: ()V
    flags: (0x0001) ACC_PUBLIC
    Code:
      stack=1, locals=1, args_size=1
         0: aload_0
         1: invokespecial #69                 // Method java/lang/Object."<init>":()V
         4: return
      LineNumberTable:
        line 104: 0
        line 31: 4
      LocalVariableTable:
        Start  Length  Slot  Name   Signature
            0       5     0  this   Lorg/scalatest/matchers/dsl/StartWithWord;
}
InnerClasses:
  public final #10;                       // class org/scalatest/matchers/dsl/StartWithWord$$anon$1
  public final #12;                       // class org/scalatest/matchers/dsl/StartWithWord$$anon$2
  public final #14;                       // class org/scalatest/matchers/dsl/StartWithWord$$anon$3
SourceFile: "StartWithWord.scala"
RuntimeVisibleAnnotations:
  0: #6(#7=s#8)
    scala.reflect.ScalaSignature(
      bytes="\u0006\u0005I3Aa\u0002\u0005\u0003#!)\u0001\u0004\u0001C\u00013!)A\u0004\u0001C\u0001;!)q\u0006\u0001C\u0001a!)q\u0006\u0001C\u0001y!)q\u0006\u0001C\u0001\u000b\")\u0001\u000b\u0001C!#\ni1\u000b^1si^KG\u000f[,pe\u0012T!!\u0003\u0006\u0002\u0007\u0011\u001cHN\u0003\u0002\f\u0019\u0005AQ.\u0019;dQ\u0016\u00148O\u0003\u0002\u000e\u001d\u0005I1oY1mCR,7\u000f\u001e\u0006\u0002\u001f\u0005\u0019qN]4\u0004\u0001M\u0011\u0001A\u0005\t\u0003\'Yi\u0011\u0001\u0006\u0006\u0002+\u0005)1oY1mC&\u0011q\u0003\u0006\u0002\u0007\u0003:L(+\u001a4\u0002\rqJg.\u001b;?)\u0005Q\u0002CA\u000e\u0001\u001b\u0005A\u0011!B1qa2LHC\u0001\u0010.!\ry\u0002EI\u0007\u0002\u0015%\u0011\u0011E\u0003\u0002\b\u001b\u0006$8\r[3s!\t\u0019#F\u0004\u0002%QA\u0011Q\u0005F\u0007\u0002M)\u0011q\u0005E\u0001\u0007yI|w\u000e\u001e \n\u0005%\"\u0012A\u0002)sK\u0012,g-\u0003\u0002,Y\t11\u000b\u001e:j]\u001eT!!\u000b\u000b\t\u000b9\u0012\u0001\u0019\u0001\u0012\u0002\u000bILw\r\u001b;\u0002\u000bI,w-\u001a=\u0016\u0005E*DC\u0001\u001a<!\ry\u0002e\r\t\u0003iUb\u0001\u0001B\u00037\u0007\t\u0007qGA\u0001U#\tA$\u0005\u0005\u0002\u0014s%\u0011!\b\u0006\u0002\b\u001d>$\b.\u001b8h\u0011\u0015q3\u00011\u00014)\ti\u0004IE\u0002?%y1Aa\u0010\u0003\u0001{\taAH]3gS:,W.\u001a8u}!)\u0011\t\u0002a\u0001\u0005\u0006y!/Z4fq^KG\u000f[$s_V\u00048\u000f\u0005\u0002\u001c\u0007&\u0011A\t\u0003\u0002\u0010%\u0016<W\r_,ji\"<%o\\;qgR\u0011aD\u0012\u0005\u0006\u000f\u0016\u0001\r\u0001S\u0001\u000be&<\u0007\u000e\u001e*fO\u0016D\bCA%O\u001b\u0005Q%BA&M\u0003!i\u0017\r^2iS:<\'BA\'\u0015\u0003\u0011)H/\u001b7\n\u0005=S%!\u0002*fO\u0016D\u0018\u0001\u0003;p\'R\u0014\u0018N\\4\u0015\u0003\t\u0002"
    )
  ScalaInlineInfo: length = 0x22 (unknown attribute)
   01 01 00 06 00 13 00 43 01 00 0F 00 10 01 00 1A
   00 10 01 00 1A 00 32 01 00 1A 00 2F 01 00 3F 00
   40 01
  ScalaSig: length = 0x3 (unknown attribute)
   05 02 00
