Classfile /Users/mw/Projects/slang-braindump/.jar/jar11/assemble/slang-braindump/assemble/content/org/kohsuke/github/AbuseLimitHandler$1.class
  Last modified May 29, 2022; size 1458 bytes
  SHA-256 checksum 869d66ee5cd7fd2f8599b7a34d91c03c1a5fa21f7a471bb8a49501dc17e0f5e1
  Compiled from "AbuseLimitHandler.java"
class org.kohsuke.github.AbuseLimitHandler$1 extends org.kohsuke.github.AbuseLimitHandler
  minor version: 0
  major version: 52
  flags: (0x0020) ACC_SUPER
  this_class: #16                         // org/kohsuke/github/AbuseLimitHandler$1
  super_class: #17                        // org/kohsuke/github/AbuseLimitHandler
  interfaces: 0, fields: 0, methods: 3, attributes: 3
Constant pool:
   #1 = Methodref          #17.#45        // org/kohsuke/github/AbuseLimitHandler."<init>":()V
   #2 = Methodref          #16.#46        // org/kohsuke/github/AbuseLimitHandler$1.parseWaitTime:(Ljava/net/HttpURLConnection;)J
   #3 = Methodref          #47.#48        // java/lang/Thread.sleep:(J)V
   #4 = Class              #49            // java/lang/InterruptedException
   #5 = Class              #50            // java/io/InterruptedIOException
   #6 = Methodref          #5.#45         // java/io/InterruptedIOException."<init>":()V
   #7 = Methodref          #5.#51         // java/io/InterruptedIOException.initCause:(Ljava/lang/Throwable;)Ljava/lang/Throwable;
   #8 = String             #52            // Retry-After
   #9 = Methodref          #53.#54        // java/net/HttpURLConnection.getHeaderField:(Ljava/lang/String;)Ljava/lang/String;
  #10 = Long               60000l
  #12 = Long               1000l
  #14 = Methodref          #55.#56        // java/lang/Long.parseLong:(Ljava/lang/String;)J
  #15 = Methodref          #57.#58        // java/lang/Math.max:(JJ)J
  #16 = Class              #59            // org/kohsuke/github/AbuseLimitHandler$1
  #17 = Class              #60            // org/kohsuke/github/AbuseLimitHandler
  #18 = Utf8               <init>
  #19 = Utf8               ()V
  #20 = Utf8               Code
  #21 = Utf8               LineNumberTable
  #22 = Utf8               LocalVariableTable
  #23 = Utf8               this
  #24 = Utf8               InnerClasses
  #25 = Utf8               Lorg/kohsuke/github/AbuseLimitHandler$1;
  #26 = Utf8               onError
  #27 = Utf8               (Ljava/io/IOException;Ljava/net/HttpURLConnection;)V
  #28 = Utf8               ex
  #29 = Utf8               Ljava/lang/InterruptedException;
  #30 = Utf8               e
  #31 = Utf8               Ljava/io/IOException;
  #32 = Utf8               uc
  #33 = Utf8               Ljava/net/HttpURLConnection;
  #34 = Utf8               StackMapTable
  #35 = Utf8               Exceptions
  #36 = Class              #61            // java/io/IOException
  #37 = Utf8               parseWaitTime
  #38 = Utf8               (Ljava/net/HttpURLConnection;)J
  #39 = Utf8               v
  #40 = Utf8               Ljava/lang/String;
  #41 = Class              #62            // java/lang/String
  #42 = Utf8               SourceFile
  #43 = Utf8               AbuseLimitHandler.java
  #44 = Utf8               EnclosingMethod
  #45 = NameAndType        #18:#19        // "<init>":()V
  #46 = NameAndType        #37:#38        // parseWaitTime:(Ljava/net/HttpURLConnection;)J
  #47 = Class              #63            // java/lang/Thread
  #48 = NameAndType        #64:#65        // sleep:(J)V
  #49 = Utf8               java/lang/InterruptedException
  #50 = Utf8               java/io/InterruptedIOException
  #51 = NameAndType        #66:#67        // initCause:(Ljava/lang/Throwable;)Ljava/lang/Throwable;
  #52 = Utf8               Retry-After
  #53 = Class              #68            // java/net/HttpURLConnection
  #54 = NameAndType        #69:#70        // getHeaderField:(Ljava/lang/String;)Ljava/lang/String;
  #55 = Class              #71            // java/lang/Long
  #56 = NameAndType        #72:#73        // parseLong:(Ljava/lang/String;)J
  #57 = Class              #74            // java/lang/Math
  #58 = NameAndType        #75:#76        // max:(JJ)J
  #59 = Utf8               org/kohsuke/github/AbuseLimitHandler$1
  #60 = Utf8               org/kohsuke/github/AbuseLimitHandler
  #61 = Utf8               java/io/IOException
  #62 = Utf8               java/lang/String
  #63 = Utf8               java/lang/Thread
  #64 = Utf8               sleep
  #65 = Utf8               (J)V
  #66 = Utf8               initCause
  #67 = Utf8               (Ljava/lang/Throwable;)Ljava/lang/Throwable;
  #68 = Utf8               java/net/HttpURLConnection
  #69 = Utf8               getHeaderField
  #70 = Utf8               (Ljava/lang/String;)Ljava/lang/String;
  #71 = Utf8               java/lang/Long
  #72 = Utf8               parseLong
  #73 = Utf8               (Ljava/lang/String;)J
  #74 = Utf8               java/lang/Math
  #75 = Utf8               max
  #76 = Utf8               (JJ)J
{
  org.kohsuke.github.AbuseLimitHandler$1();
    descriptor: ()V
    flags: (0x0000)
    Code:
      stack=1, locals=1, args_size=1
         0: aload_0
         1: invokespecial #1                  // Method org/kohsuke/github/AbuseLimitHandler."<init>":()V
         4: return
      LineNumberTable:
        line 78: 0
      LocalVariableTable:
        Start  Length  Slot  Name   Signature
            0       5     0  this   Lorg/kohsuke/github/AbuseLimitHandler$1;

  public void onError(java.io.IOException, java.net.HttpURLConnection) throws java.io.IOException;
    descriptor: (Ljava/io/IOException;Ljava/net/HttpURLConnection;)V
    flags: (0x0001) ACC_PUBLIC
    Code:
      stack=2, locals=4, args_size=3
         0: aload_0
         1: aload_2
         2: invokespecial #2                  // Method parseWaitTime:(Ljava/net/HttpURLConnection;)J
         5: invokestatic  #3                  // Method java/lang/Thread.sleep:(J)V
         8: goto          27
        11: astore_3
        12: new           #5                  // class java/io/InterruptedIOException
        15: dup
        16: invokespecial #6                  // Method java/io/InterruptedIOException."<init>":()V
        19: aload_1
        20: invokevirtual #7                  // Method java/io/InterruptedIOException.initCause:(Ljava/lang/Throwable;)Ljava/lang/Throwable;
        23: checkcast     #5                  // class java/io/InterruptedIOException
        26: athrow
        27: return
      Exception table:
         from    to  target type
             0     8    11   Class java/lang/InterruptedException
      LineNumberTable:
        line 82: 0
        line 85: 8
        line 83: 11
        line 84: 12
        line 86: 27
      LocalVariableTable:
        Start  Length  Slot  Name   Signature
           12      15     3    ex   Ljava/lang/InterruptedException;
            0      28     0  this   Lorg/kohsuke/github/AbuseLimitHandler$1;
            0      28     1     e   Ljava/io/IOException;
            0      28     2    uc   Ljava/net/HttpURLConnection;
      StackMapTable: number_of_entries = 2
        frame_type = 75 /* same_locals_1_stack_item */
          stack = [ class java/lang/InterruptedException ]
        frame_type = 15 /* same */
    Exceptions:
      throws java.io.IOException

  private long parseWaitTime(java.net.HttpURLConnection);
    descriptor: (Ljava/net/HttpURLConnection;)J
    flags: (0x0002) ACC_PRIVATE
    Code:
      stack=6, locals=3, args_size=2
         0: aload_1
         1: ldc           #8                  // String Retry-After
         3: invokevirtual #9                  // Method java/net/HttpURLConnection.getHeaderField:(Ljava/lang/String;)Ljava/lang/String;
         6: astore_2
         7: aload_2
         8: ifnonnull     15
        11: ldc2_w        #10                 // long 60000l
        14: lreturn
        15: ldc2_w        #12                 // long 1000l
        18: aload_2
        19: invokestatic  #14                 // Method java/lang/Long.parseLong:(Ljava/lang/String;)J
        22: ldc2_w        #12                 // long 1000l
        25: lmul
        26: invokestatic  #15                 // Method java/lang/Math.max:(JJ)J
        29: lreturn
      LineNumberTable:
        line 89: 0
        line 90: 7
        line 91: 11
        line 93: 15
      LocalVariableTable:
        Start  Length  Slot  Name   Signature
            0      30     0  this   Lorg/kohsuke/github/AbuseLimitHandler$1;
            0      30     1    uc   Ljava/net/HttpURLConnection;
            7      23     2     v   Ljava/lang/String;
      StackMapTable: number_of_entries = 1
        frame_type = 252 /* append */
          offset_delta = 15
          locals = [ class java/lang/String ]
}
SourceFile: "AbuseLimitHandler.java"
EnclosingMethod: #17.#0                 // org.kohsuke.github.AbuseLimitHandler
InnerClasses:
  #16;                                    // class org/kohsuke/github/AbuseLimitHandler$1
