Classfile /Users/mw/Projects/slang-braindump/.jar/jar11/assemble/slang-braindump/assemble/content/org/kohsuke/github/GHAppInstallation.class
  Last modified May 29, 2022; size 8639 bytes
  SHA-256 checksum 365476352711baf4f24b1d322e306b9404f222a4b826b8f1f9df4b86e8a9453d
  Compiled from "GHAppInstallation.java"
public class org.kohsuke.github.GHAppInstallation extends org.kohsuke.github.GHObject
  minor version: 0
  major version: 52
  flags: (0x0021) ACC_PUBLIC, ACC_SUPER
  this_class: #52                         // org/kohsuke/github/GHAppInstallation
  super_class: #53                        // org/kohsuke/github/GHObject
  interfaces: 0, fields: 11, methods: 28, attributes: 3
Constant pool:
    #1 = Methodref          #53.#169      // org/kohsuke/github/GHObject."<init>":()V
    #2 = Fieldref           #52.#170      // org/kohsuke/github/GHAppInstallation.htmlUrl:Ljava/lang/String;
    #3 = Methodref          #171.#172     // org/kohsuke/github/GitHubClient.parseURL:(Ljava/lang/String;)Ljava/net/URL;
    #4 = Class              #173          // java/lang/RuntimeException
    #5 = String             #174          // Do not use this method.
    #6 = Methodref          #4.#175       // java/lang/RuntimeException."<init>":(Ljava/lang/String;)V
    #7 = Fieldref           #52.#176      // org/kohsuke/github/GHAppInstallation.account:Lorg/kohsuke/github/GHUser;
    #8 = Fieldref           #52.#177      // org/kohsuke/github/GHAppInstallation.accessTokenUrl:Ljava/lang/String;
    #9 = Fieldref           #52.#178      // org/kohsuke/github/GHAppInstallation.repositoriesUrl:Ljava/lang/String;
   #10 = Methodref          #52.#179      // org/kohsuke/github/GHAppInstallation.root:()Lorg/kohsuke/github/GitHub;
   #11 = Methodref          #180.#181     // org/kohsuke/github/GitHub.createRequest:()Lorg/kohsuke/github/Requester;
   #12 = Fieldref           #182.#183     // org/kohsuke/github/internal/Previews.MACHINE_MAN:Lorg/kohsuke/github/internal/Previews;
   #13 = Methodref          #14.#184      // org/kohsuke/github/Requester.withPreview:(Lorg/kohsuke/github/internal/Previews;)Lorg/kohsuke/github/GitHubRequest$Builder;
   #14 = Class              #185          // org/kohsuke/github/Requester
   #15 = String             #186          // /installation/repositories
   #16 = Class              #187          // java/lang/String
   #17 = Methodref          #14.#188      // org/kohsuke/github/Requester.withUrlPath:(Ljava/lang/String;[Ljava/lang/String;)Lorg/kohsuke/github/GitHubRequest$Builder;
   #18 = Methodref          #14.#189      // org/kohsuke/github/Requester.build:()Lorg/kohsuke/github/GitHubRequest;
   #19 = Class              #190          // org/kohsuke/github/PagedSearchIterable
   #20 = Class              #191          // org/kohsuke/github/GHAppInstallation$GHAppInstallationRepositoryResult
   #21 = Methodref          #19.#192      // org/kohsuke/github/PagedSearchIterable."<init>":(Lorg/kohsuke/github/GitHub;Lorg/kohsuke/github/GitHubRequest;Ljava/lang/Class;)V
   #22 = Fieldref           #52.#193      // org/kohsuke/github/GHAppInstallation.appId:J
   #23 = Fieldref           #52.#194      // org/kohsuke/github/GHAppInstallation.targetId:J
   #24 = Fieldref           #52.#195      // org/kohsuke/github/GHAppInstallation.targetType:Lorg/kohsuke/github/GHTargetType;
   #25 = Fieldref           #52.#196      // org/kohsuke/github/GHAppInstallation.permissions:Ljava/util/Map;
   #26 = Methodref          #197.#198     // java/util/Collections.unmodifiableMap:(Ljava/util/Map;)Ljava/util/Map;
   #27 = Fieldref           #52.#199      // org/kohsuke/github/GHAppInstallation.events:Ljava/util/List;
   #28 = InterfaceMethodref #33.#200      // java/util/List.stream:()Ljava/util/stream/Stream;
   #29 = InvokeDynamic      #0:#206       // #0:apply:()Ljava/util/function/Function;
   #30 = InterfaceMethodref #207.#208     // java/util/stream/Stream.map:(Ljava/util/function/Function;)Ljava/util/stream/Stream;
   #31 = Methodref          #209.#210     // java/util/stream/Collectors.toList:()Ljava/util/stream/Collector;
   #32 = InterfaceMethodref #207.#211     // java/util/stream/Stream.collect:(Ljava/util/stream/Collector;)Ljava/lang/Object;
   #33 = Class              #212          // java/util/List
   #34 = Fieldref           #52.#213      // org/kohsuke/github/GHAppInstallation.singleFileName:Ljava/lang/String;
   #35 = Fieldref           #52.#214      // org/kohsuke/github/GHAppInstallation.repositorySelection:Lorg/kohsuke/github/GHRepositorySelection;
   #36 = String             #215          // DELETE
   #37 = Methodref          #14.#216      // org/kohsuke/github/Requester.method:(Ljava/lang/String;)Lorg/kohsuke/github/GitHubRequest$Builder;
   #38 = Fieldref           #182.#217     // org/kohsuke/github/internal/Previews.GAMBIT:Lorg/kohsuke/github/internal/Previews;
   #39 = String             #218          // /app/installations/%d
   #40 = Class              #219          // java/lang/Object
   #41 = Methodref          #52.#220      // org/kohsuke/github/GHAppInstallation.getId:()J
   #42 = Methodref          #221.#222     // java/lang/Long.valueOf:(J)Ljava/lang/Long;
   #43 = Methodref          #16.#223      // java/lang/String.format:(Ljava/lang/String;[Ljava/lang/Object;)Ljava/lang/String;
   #44 = Methodref          #14.#224      // org/kohsuke/github/Requester.send:()V
   #45 = Class              #225          // org/kohsuke/github/GHAppCreateTokenBuilder
   #46 = String             #226          // /app/installations/%d/access_tokens
   #47 = Methodref          #45.#227      // org/kohsuke/github/GHAppCreateTokenBuilder."<init>":(Lorg/kohsuke/github/GitHub;Ljava/lang/String;Ljava/util/Map;)V
   #48 = Methodref          #45.#228      // org/kohsuke/github/GHAppCreateTokenBuilder."<init>":(Lorg/kohsuke/github/GitHub;Ljava/lang/String;)V
   #49 = Class              #229          // org/kohsuke/github/GHEvent
   #50 = Fieldref           #49.#230      // org/kohsuke/github/GHEvent.UNKNOWN:Lorg/kohsuke/github/GHEvent;
   #51 = Methodref          #231.#232     // org/kohsuke/github/internal/EnumUtils.getEnumOrDefault:(Ljava/lang/Class;Ljava/lang/String;Ljava/lang/Enum;)Ljava/lang/Enum;
   #52 = Class              #233          // org/kohsuke/github/GHAppInstallation
   #53 = Class              #234          // org/kohsuke/github/GHObject
   #54 = Utf8               GHAppInstallationRepositoryResult
   #55 = Utf8               InnerClasses
   #56 = Utf8               account
   #57 = Utf8               Lorg/kohsuke/github/GHUser;
   #58 = Utf8               accessTokenUrl
   #59 = Utf8               Ljava/lang/String;
   #60 = Utf8               RuntimeVisibleAnnotations
   #61 = Utf8               Lcom/fasterxml/jackson/annotation/JsonProperty;
   #62 = Utf8               value
   #63 = Utf8               access_tokens_url
   #64 = Utf8               repositoriesUrl
   #65 = Utf8               repositories_url
   #66 = Utf8               appId
   #67 = Utf8               J
   #68 = Utf8               app_id
   #69 = Utf8               targetId
   #70 = Utf8               target_id
   #71 = Utf8               targetType
   #72 = Utf8               Lorg/kohsuke/github/GHTargetType;
   #73 = Utf8               target_type
   #74 = Utf8               permissions
   #75 = Utf8               Ljava/util/Map;
   #76 = Utf8               Signature
   #77 = Utf8               Ljava/util/Map<Ljava/lang/String;Lorg/kohsuke/github/GHPermissionType;>;
   #78 = Utf8               events
   #79 = Utf8               Ljava/util/List;
   #80 = Utf8               Ljava/util/List<Ljava/lang/String;>;
   #81 = Utf8               singleFileName
   #82 = Utf8               single_file_name
   #83 = Utf8               repositorySelection
   #84 = Utf8               Lorg/kohsuke/github/GHRepositorySelection;
   #85 = Utf8               repository_selection
   #86 = Utf8               htmlUrl
   #87 = Utf8               <init>
   #88 = Utf8               ()V
   #89 = Utf8               Code
   #90 = Utf8               LineNumberTable
   #91 = Utf8               LocalVariableTable
   #92 = Utf8               this
   #93 = Utf8               Lorg/kohsuke/github/GHAppInstallation;
   #94 = Utf8               getHtmlUrl
   #95 = Utf8               ()Ljava/net/URL;
   #96 = Utf8               setRoot
   #97 = Utf8               (Lorg/kohsuke/github/GitHub;)V
   #98 = Utf8               root
   #99 = Utf8               Lorg/kohsuke/github/GitHub;
  #100 = Utf8               Deprecated
  #101 = Utf8               Ljava/lang/Deprecated;
  #102 = Utf8               getAccount
  #103 = Utf8               ()Lorg/kohsuke/github/GHUser;
  #104 = Utf8               RuntimeInvisibleAnnotations
  #105 = Utf8               Ledu/umd/cs/findbugs/annotations/SuppressFBWarnings;
  #106 = Utf8               EI_EXPOSE_REP
  #107 = Utf8               justification
  #108 = Utf8               Expected behavior
  #109 = Utf8               setAccount
  #110 = Utf8               (Lorg/kohsuke/github/GHUser;)V
  #111 = Utf8               getAccessTokenUrl
  #112 = Utf8               ()Ljava/lang/String;
  #113 = Utf8               setAccessTokenUrl
  #114 = Utf8               (Ljava/lang/String;)V
  #115 = Utf8               getRepositoriesUrl
  #116 = Utf8               listRepositories
  #117 = Utf8               ()Lorg/kohsuke/github/PagedSearchIterable;
  #118 = Utf8               request
  #119 = Utf8               Lorg/kohsuke/github/GitHubRequest;
  #120 = Utf8               ()Lorg/kohsuke/github/PagedSearchIterable<Lorg/kohsuke/github/GHRepository;>;
  #121 = Utf8               Lorg/kohsuke/github/Preview;
  #122 = Utf8               Lorg/kohsuke/github/internal/Previews;
  #123 = Utf8               MACHINE_MAN
  #124 = Utf8               setRepositoriesUrl
  #125 = Utf8               getAppId
  #126 = Utf8               ()J
  #127 = Utf8               setAppId
  #128 = Utf8               (J)V
  #129 = Utf8               getTargetId
  #130 = Utf8               setTargetId
  #131 = Utf8               getTargetType
  #132 = Utf8               ()Lorg/kohsuke/github/GHTargetType;
  #133 = Utf8               setTargetType
  #134 = Utf8               (Lorg/kohsuke/github/GHTargetType;)V
  #135 = Utf8               getPermissions
  #136 = Utf8               ()Ljava/util/Map;
  #137 = Utf8               ()Ljava/util/Map<Ljava/lang/String;Lorg/kohsuke/github/GHPermissionType;>;
  #138 = Utf8               setPermissions
  #139 = Utf8               (Ljava/util/Map;)V
  #140 = Utf8               LocalVariableTypeTable
  #141 = Utf8               (Ljava/util/Map<Ljava/lang/String;Lorg/kohsuke/github/GHPermissionType;>;)V
  #142 = Utf8               getEvents
  #143 = Utf8               ()Ljava/util/List;
  #144 = Utf8               ()Ljava/util/List<Lorg/kohsuke/github/GHEvent;>;
  #145 = Utf8               setEvents
  #146 = Utf8               (Ljava/util/List;)V
  #147 = Utf8               Ljava/util/List<Lorg/kohsuke/github/GHEvent;>;
  #148 = Utf8               (Ljava/util/List<Lorg/kohsuke/github/GHEvent;>;)V
  #149 = Utf8               getSingleFileName
  #150 = Utf8               setSingleFileName
  #151 = Utf8               getRepositorySelection
  #152 = Utf8               ()Lorg/kohsuke/github/GHRepositorySelection;
  #153 = Utf8               setRepositorySelection
  #154 = Utf8               (Lorg/kohsuke/github/GHRepositorySelection;)V
  #155 = Utf8               deleteInstallation
  #156 = Utf8               Exceptions
  #157 = Class              #235          // java/io/IOException
  #158 = Utf8               GAMBIT
  #159 = Utf8               createToken
  #160 = Utf8               (Ljava/util/Map;)Lorg/kohsuke/github/GHAppCreateTokenBuilder;
  #161 = Utf8               (Ljava/util/Map<Ljava/lang/String;Lorg/kohsuke/github/GHPermissionType;>;)Lorg/kohsuke/github/GHAppCreateTokenBuilder;
  #162 = Utf8               Lorg/kohsuke/github/BetaApi;
  #163 = Utf8               ()Lorg/kohsuke/github/GHAppCreateTokenBuilder;
  #164 = Utf8               lambda$getEvents$0
  #165 = Utf8               (Ljava/lang/String;)Lorg/kohsuke/github/GHEvent;
  #166 = Utf8               e
  #167 = Utf8               SourceFile
  #168 = Utf8               GHAppInstallation.java
  #169 = NameAndType        #87:#88       // "<init>":()V
  #170 = NameAndType        #86:#59       // htmlUrl:Ljava/lang/String;
  #171 = Class              #236          // org/kohsuke/github/GitHubClient
  #172 = NameAndType        #237:#238     // parseURL:(Ljava/lang/String;)Ljava/net/URL;
  #173 = Utf8               java/lang/RuntimeException
  #174 = Utf8               Do not use this method.
  #175 = NameAndType        #87:#114      // "<init>":(Ljava/lang/String;)V
  #176 = NameAndType        #56:#57       // account:Lorg/kohsuke/github/GHUser;
  #177 = NameAndType        #58:#59       // accessTokenUrl:Ljava/lang/String;
  #178 = NameAndType        #64:#59       // repositoriesUrl:Ljava/lang/String;
  #179 = NameAndType        #98:#239      // root:()Lorg/kohsuke/github/GitHub;
  #180 = Class              #240          // org/kohsuke/github/GitHub
  #181 = NameAndType        #241:#242     // createRequest:()Lorg/kohsuke/github/Requester;
  #182 = Class              #243          // org/kohsuke/github/internal/Previews
  #183 = NameAndType        #123:#122     // MACHINE_MAN:Lorg/kohsuke/github/internal/Previews;
  #184 = NameAndType        #244:#247     // withPreview:(Lorg/kohsuke/github/internal/Previews;)Lorg/kohsuke/github/GitHubRequest$Builder;
  #185 = Utf8               org/kohsuke/github/Requester
  #186 = Utf8               /installation/repositories
  #187 = Utf8               java/lang/String
  #188 = NameAndType        #248:#249     // withUrlPath:(Ljava/lang/String;[Ljava/lang/String;)Lorg/kohsuke/github/GitHubRequest$Builder;
  #189 = NameAndType        #250:#251     // build:()Lorg/kohsuke/github/GitHubRequest;
  #190 = Utf8               org/kohsuke/github/PagedSearchIterable
  #191 = Utf8               org/kohsuke/github/GHAppInstallation$GHAppInstallationRepositoryResult
  #192 = NameAndType        #87:#252      // "<init>":(Lorg/kohsuke/github/GitHub;Lorg/kohsuke/github/GitHubRequest;Ljava/lang/Class;)V
  #193 = NameAndType        #66:#67       // appId:J
  #194 = NameAndType        #69:#67       // targetId:J
  #195 = NameAndType        #71:#72       // targetType:Lorg/kohsuke/github/GHTargetType;
  #196 = NameAndType        #74:#75       // permissions:Ljava/util/Map;
  #197 = Class              #253          // java/util/Collections
  #198 = NameAndType        #254:#255     // unmodifiableMap:(Ljava/util/Map;)Ljava/util/Map;
  #199 = NameAndType        #78:#79       // events:Ljava/util/List;
  #200 = NameAndType        #256:#257     // stream:()Ljava/util/stream/Stream;
  #201 = Utf8               BootstrapMethods
  #202 = MethodHandle       6:#258        // REF_invokeStatic java/lang/invoke/LambdaMetafactory.metafactory:(Ljava/lang/invoke/MethodHandles$Lookup;Ljava/lang/String;Ljava/lang/invoke/MethodType;Ljava/lang/invoke/MethodType;Ljava/lang/invoke/MethodHandle;Ljava/lang/invoke/MethodType;)Ljava/lang/invoke/CallSite;
  #203 = MethodType         #259          //  (Ljava/lang/Object;)Ljava/lang/Object;
  #204 = MethodHandle       6:#260        // REF_invokeStatic org/kohsuke/github/GHAppInstallation.lambda$getEvents$0:(Ljava/lang/String;)Lorg/kohsuke/github/GHEvent;
  #205 = MethodType         #165          //  (Ljava/lang/String;)Lorg/kohsuke/github/GHEvent;
  #206 = NameAndType        #261:#262     // apply:()Ljava/util/function/Function;
  #207 = Class              #263          // java/util/stream/Stream
  #208 = NameAndType        #264:#265     // map:(Ljava/util/function/Function;)Ljava/util/stream/Stream;
  #209 = Class              #266          // java/util/stream/Collectors
  #210 = NameAndType        #267:#268     // toList:()Ljava/util/stream/Collector;
  #211 = NameAndType        #269:#270     // collect:(Ljava/util/stream/Collector;)Ljava/lang/Object;
  #212 = Utf8               java/util/List
  #213 = NameAndType        #81:#59       // singleFileName:Ljava/lang/String;
  #214 = NameAndType        #83:#84       // repositorySelection:Lorg/kohsuke/github/GHRepositorySelection;
  #215 = Utf8               DELETE
  #216 = NameAndType        #271:#272     // method:(Ljava/lang/String;)Lorg/kohsuke/github/GitHubRequest$Builder;
  #217 = NameAndType        #158:#122     // GAMBIT:Lorg/kohsuke/github/internal/Previews;
  #218 = Utf8               /app/installations/%d
  #219 = Utf8               java/lang/Object
  #220 = NameAndType        #273:#126     // getId:()J
  #221 = Class              #274          // java/lang/Long
  #222 = NameAndType        #275:#276     // valueOf:(J)Ljava/lang/Long;
  #223 = NameAndType        #277:#278     // format:(Ljava/lang/String;[Ljava/lang/Object;)Ljava/lang/String;
  #224 = NameAndType        #279:#88      // send:()V
  #225 = Utf8               org/kohsuke/github/GHAppCreateTokenBuilder
  #226 = Utf8               /app/installations/%d/access_tokens
  #227 = NameAndType        #87:#280      // "<init>":(Lorg/kohsuke/github/GitHub;Ljava/lang/String;Ljava/util/Map;)V
  #228 = NameAndType        #87:#281      // "<init>":(Lorg/kohsuke/github/GitHub;Ljava/lang/String;)V
  #229 = Utf8               org/kohsuke/github/GHEvent
  #230 = NameAndType        #282:#283     // UNKNOWN:Lorg/kohsuke/github/GHEvent;
  #231 = Class              #284          // org/kohsuke/github/internal/EnumUtils
  #232 = NameAndType        #285:#286     // getEnumOrDefault:(Ljava/lang/Class;Ljava/lang/String;Ljava/lang/Enum;)Ljava/lang/Enum;
  #233 = Utf8               org/kohsuke/github/GHAppInstallation
  #234 = Utf8               org/kohsuke/github/GHObject
  #235 = Utf8               java/io/IOException
  #236 = Utf8               org/kohsuke/github/GitHubClient
  #237 = Utf8               parseURL
  #238 = Utf8               (Ljava/lang/String;)Ljava/net/URL;
  #239 = Utf8               ()Lorg/kohsuke/github/GitHub;
  #240 = Utf8               org/kohsuke/github/GitHub
  #241 = Utf8               createRequest
  #242 = Utf8               ()Lorg/kohsuke/github/Requester;
  #243 = Utf8               org/kohsuke/github/internal/Previews
  #244 = Utf8               withPreview
  #245 = Class              #288          // org/kohsuke/github/GitHubRequest$Builder
  #246 = Utf8               Builder
  #247 = Utf8               (Lorg/kohsuke/github/internal/Previews;)Lorg/kohsuke/github/GitHubRequest$Builder;
  #248 = Utf8               withUrlPath
  #249 = Utf8               (Ljava/lang/String;[Ljava/lang/String;)Lorg/kohsuke/github/GitHubRequest$Builder;
  #250 = Utf8               build
  #251 = Utf8               ()Lorg/kohsuke/github/GitHubRequest;
  #252 = Utf8               (Lorg/kohsuke/github/GitHub;Lorg/kohsuke/github/GitHubRequest;Ljava/lang/Class;)V
  #253 = Utf8               java/util/Collections
  #254 = Utf8               unmodifiableMap
  #255 = Utf8               (Ljava/util/Map;)Ljava/util/Map;
  #256 = Utf8               stream
  #257 = Utf8               ()Ljava/util/stream/Stream;
  #258 = Methodref          #289.#290     // java/lang/invoke/LambdaMetafactory.metafactory:(Ljava/lang/invoke/MethodHandles$Lookup;Ljava/lang/String;Ljava/lang/invoke/MethodType;Ljava/lang/invoke/MethodType;Ljava/lang/invoke/MethodHandle;Ljava/lang/invoke/MethodType;)Ljava/lang/invoke/CallSite;
  #259 = Utf8               (Ljava/lang/Object;)Ljava/lang/Object;
  #260 = Methodref          #52.#291      // org/kohsuke/github/GHAppInstallation.lambda$getEvents$0:(Ljava/lang/String;)Lorg/kohsuke/github/GHEvent;
  #261 = Utf8               apply
  #262 = Utf8               ()Ljava/util/function/Function;
  #263 = Utf8               java/util/stream/Stream
  #264 = Utf8               map
  #265 = Utf8               (Ljava/util/function/Function;)Ljava/util/stream/Stream;
  #266 = Utf8               java/util/stream/Collectors
  #267 = Utf8               toList
  #268 = Utf8               ()Ljava/util/stream/Collector;
  #269 = Utf8               collect
  #270 = Utf8               (Ljava/util/stream/Collector;)Ljava/lang/Object;
  #271 = Utf8               method
  #272 = Utf8               (Ljava/lang/String;)Lorg/kohsuke/github/GitHubRequest$Builder;
  #273 = Utf8               getId
  #274 = Utf8               java/lang/Long
  #275 = Utf8               valueOf
  #276 = Utf8               (J)Ljava/lang/Long;
  #277 = Utf8               format
  #278 = Utf8               (Ljava/lang/String;[Ljava/lang/Object;)Ljava/lang/String;
  #279 = Utf8               send
  #280 = Utf8               (Lorg/kohsuke/github/GitHub;Ljava/lang/String;Ljava/util/Map;)V
  #281 = Utf8               (Lorg/kohsuke/github/GitHub;Ljava/lang/String;)V
  #282 = Utf8               UNKNOWN
  #283 = Utf8               Lorg/kohsuke/github/GHEvent;
  #284 = Utf8               org/kohsuke/github/internal/EnumUtils
  #285 = Utf8               getEnumOrDefault
  #286 = Utf8               (Ljava/lang/Class;Ljava/lang/String;Ljava/lang/Enum;)Ljava/lang/Enum;
  #287 = Class              #292          // org/kohsuke/github/GitHubRequest
  #288 = Utf8               org/kohsuke/github/GitHubRequest$Builder
  #289 = Class              #293          // java/lang/invoke/LambdaMetafactory
  #290 = NameAndType        #294:#297     // metafactory:(Ljava/lang/invoke/MethodHandles$Lookup;Ljava/lang/String;Ljava/lang/invoke/MethodType;Ljava/lang/invoke/MethodType;Ljava/lang/invoke/MethodHandle;Ljava/lang/invoke/MethodType;)Ljava/lang/invoke/CallSite;
  #291 = NameAndType        #164:#165     // lambda$getEvents$0:(Ljava/lang/String;)Lorg/kohsuke/github/GHEvent;
  #292 = Utf8               org/kohsuke/github/GitHubRequest
  #293 = Utf8               java/lang/invoke/LambdaMetafactory
  #294 = Utf8               metafactory
  #295 = Class              #299          // java/lang/invoke/MethodHandles$Lookup
  #296 = Utf8               Lookup
  #297 = Utf8               (Ljava/lang/invoke/MethodHandles$Lookup;Ljava/lang/String;Ljava/lang/invoke/MethodType;Ljava/lang/invoke/MethodType;Ljava/lang/invoke/MethodHandle;Ljava/lang/invoke/MethodType;)Ljava/lang/invoke/CallSite;
  #298 = Class              #300          // java/lang/invoke/MethodHandles
  #299 = Utf8               java/lang/invoke/MethodHandles$Lookup
  #300 = Utf8               java/lang/invoke/MethodHandles
{
  private org.kohsuke.github.GHUser account;
    descriptor: Lorg/kohsuke/github/GHUser;
    flags: (0x0002) ACC_PRIVATE

  private java.lang.String accessTokenUrl;
    descriptor: Ljava/lang/String;
    flags: (0x0002) ACC_PRIVATE
    RuntimeVisibleAnnotations:
      0: #61(#62=s#63)
        com.fasterxml.jackson.annotation.JsonProperty(
          value="access_tokens_url"
        )

  private java.lang.String repositoriesUrl;
    descriptor: Ljava/lang/String;
    flags: (0x0002) ACC_PRIVATE
    RuntimeVisibleAnnotations:
      0: #61(#62=s#65)
        com.fasterxml.jackson.annotation.JsonProperty(
          value="repositories_url"
        )

  private long appId;
    descriptor: J
    flags: (0x0002) ACC_PRIVATE
    RuntimeVisibleAnnotations:
      0: #61(#62=s#68)
        com.fasterxml.jackson.annotation.JsonProperty(
          value="app_id"
        )

  private long targetId;
    descriptor: J
    flags: (0x0002) ACC_PRIVATE
    RuntimeVisibleAnnotations:
      0: #61(#62=s#70)
        com.fasterxml.jackson.annotation.JsonProperty(
          value="target_id"
        )

  private org.kohsuke.github.GHTargetType targetType;
    descriptor: Lorg/kohsuke/github/GHTargetType;
    flags: (0x0002) ACC_PRIVATE
    RuntimeVisibleAnnotations:
      0: #61(#62=s#73)
        com.fasterxml.jackson.annotation.JsonProperty(
          value="target_type"
        )

  private java.util.Map<java.lang.String, org.kohsuke.github.GHPermissionType> permissions;
    descriptor: Ljava/util/Map;
    flags: (0x0002) ACC_PRIVATE
    Signature: #77                          // Ljava/util/Map<Ljava/lang/String;Lorg/kohsuke/github/GHPermissionType;>;

  private java.util.List<java.lang.String> events;
    descriptor: Ljava/util/List;
    flags: (0x0002) ACC_PRIVATE
    Signature: #80                          // Ljava/util/List<Ljava/lang/String;>;

  private java.lang.String singleFileName;
    descriptor: Ljava/lang/String;
    flags: (0x0002) ACC_PRIVATE
    RuntimeVisibleAnnotations:
      0: #61(#62=s#82)
        com.fasterxml.jackson.annotation.JsonProperty(
          value="single_file_name"
        )

  private org.kohsuke.github.GHRepositorySelection repositorySelection;
    descriptor: Lorg/kohsuke/github/GHRepositorySelection;
    flags: (0x0002) ACC_PRIVATE
    RuntimeVisibleAnnotations:
      0: #61(#62=s#85)
        com.fasterxml.jackson.annotation.JsonProperty(
          value="repository_selection"
        )

  private java.lang.String htmlUrl;
    descriptor: Ljava/lang/String;
    flags: (0x0002) ACC_PRIVATE

  public org.kohsuke.github.GHAppInstallation();
    descriptor: ()V
    flags: (0x0001) ACC_PUBLIC
    Code:
      stack=1, locals=1, args_size=1
         0: aload_0
         1: invokespecial #1                  // Method org/kohsuke/github/GHObject."<init>":()V
         4: return
      LineNumberTable:
        line 27: 0
      LocalVariableTable:
        Start  Length  Slot  Name   Signature
            0       5     0  this   Lorg/kohsuke/github/GHAppInstallation;

  public java.net.URL getHtmlUrl();
    descriptor: ()Ljava/net/URL;
    flags: (0x0001) ACC_PUBLIC
    Code:
      stack=1, locals=1, args_size=1
         0: aload_0
         1: getfield      #2                  // Field htmlUrl:Ljava/lang/String;
         4: invokestatic  #3                  // Method org/kohsuke/github/GitHubClient.parseURL:(Ljava/lang/String;)Ljava/net/URL;
         7: areturn
      LineNumberTable:
        line 49: 0
      LocalVariableTable:
        Start  Length  Slot  Name   Signature
            0       8     0  this   Lorg/kohsuke/github/GHAppInstallation;

  public void setRoot(org.kohsuke.github.GitHub);
    descriptor: (Lorg/kohsuke/github/GitHub;)V
    flags: (0x0001) ACC_PUBLIC
    Code:
      stack=3, locals=2, args_size=2
         0: new           #4                  // class java/lang/RuntimeException
         3: dup
         4: ldc           #5                  // String Do not use this method.
         6: invokespecial #6                  // Method java/lang/RuntimeException."<init>":(Ljava/lang/String;)V
         9: athrow
      LineNumberTable:
        line 61: 0
      LocalVariableTable:
        Start  Length  Slot  Name   Signature
            0      10     0  this   Lorg/kohsuke/github/GHAppInstallation;
            0      10     1  root   Lorg/kohsuke/github/GitHub;
    Deprecated: true
    RuntimeVisibleAnnotations:
      0: #101()
        java.lang.Deprecated

  public org.kohsuke.github.GHUser getAccount();
    descriptor: ()Lorg/kohsuke/github/GHUser;
    flags: (0x0001) ACC_PUBLIC
    Code:
      stack=1, locals=1, args_size=1
         0: aload_0
         1: getfield      #7                  // Field account:Lorg/kohsuke/github/GHUser;
         4: areturn
      LineNumberTable:
        line 71: 0
      LocalVariableTable:
        Start  Length  Slot  Name   Signature
            0       5     0  this   Lorg/kohsuke/github/GHAppInstallation;
    RuntimeInvisibleAnnotations:
      0: #105(#62=[s#106],#107=s#108)
        edu.umd.cs.findbugs.annotations.SuppressFBWarnings(
          value=["EI_EXPOSE_REP"]
          justification="Expected behavior"
        )

  public void setAccount(org.kohsuke.github.GHUser);
    descriptor: (Lorg/kohsuke/github/GHUser;)V
    flags: (0x0001) ACC_PUBLIC
    Code:
      stack=3, locals=2, args_size=2
         0: new           #4                  // class java/lang/RuntimeException
         3: dup
         4: ldc           #5                  // String Do not use this method.
         6: invokespecial #6                  // Method java/lang/RuntimeException."<init>":(Ljava/lang/String;)V
         9: athrow
      LineNumberTable:
        line 83: 0
      LocalVariableTable:
        Start  Length  Slot  Name   Signature
            0      10     0  this   Lorg/kohsuke/github/GHAppInstallation;
            0      10     1 account   Lorg/kohsuke/github/GHUser;
    Deprecated: true
    RuntimeVisibleAnnotations:
      0: #101()
        java.lang.Deprecated

  public java.lang.String getAccessTokenUrl();
    descriptor: ()Ljava/lang/String;
    flags: (0x0001) ACC_PUBLIC
    Code:
      stack=1, locals=1, args_size=1
         0: aload_0
         1: getfield      #8                  // Field accessTokenUrl:Ljava/lang/String;
         4: areturn
      LineNumberTable:
        line 92: 0
      LocalVariableTable:
        Start  Length  Slot  Name   Signature
            0       5     0  this   Lorg/kohsuke/github/GHAppInstallation;

  public void setAccessTokenUrl(java.lang.String);
    descriptor: (Ljava/lang/String;)V
    flags: (0x0001) ACC_PUBLIC
    Code:
      stack=3, locals=2, args_size=2
         0: new           #4                  // class java/lang/RuntimeException
         3: dup
         4: ldc           #5                  // String Do not use this method.
         6: invokespecial #6                  // Method java/lang/RuntimeException."<init>":(Ljava/lang/String;)V
         9: athrow
      LineNumberTable:
        line 104: 0
      LocalVariableTable:
        Start  Length  Slot  Name   Signature
            0      10     0  this   Lorg/kohsuke/github/GHAppInstallation;
            0      10     1 accessTokenUrl   Ljava/lang/String;
    Deprecated: true
    RuntimeVisibleAnnotations:
      0: #101()
        java.lang.Deprecated

  public java.lang.String getRepositoriesUrl();
    descriptor: ()Ljava/lang/String;
    flags: (0x0001) ACC_PUBLIC
    Code:
      stack=1, locals=1, args_size=1
         0: aload_0
         1: getfield      #9                  // Field repositoriesUrl:Ljava/lang/String;
         4: areturn
      LineNumberTable:
        line 113: 0
      LocalVariableTable:
        Start  Length  Slot  Name   Signature
            0       5     0  this   Lorg/kohsuke/github/GHAppInstallation;

  public org.kohsuke.github.PagedSearchIterable<org.kohsuke.github.GHRepository> listRepositories();
    descriptor: ()Lorg/kohsuke/github/PagedSearchIterable;
    flags: (0x0001) ACC_PUBLIC
    Code:
      stack=5, locals=2, args_size=1
         0: aload_0
         1: invokevirtual #10                 // Method root:()Lorg/kohsuke/github/GitHub;
         4: invokevirtual #11                 // Method org/kohsuke/github/GitHub.createRequest:()Lorg/kohsuke/github/Requester;
         7: getstatic     #12                 // Field org/kohsuke/github/internal/Previews.MACHINE_MAN:Lorg/kohsuke/github/internal/Previews;
        10: invokevirtual #13                 // Method org/kohsuke/github/Requester.withPreview:(Lorg/kohsuke/github/internal/Previews;)Lorg/kohsuke/github/GitHubRequest$Builder;
        13: checkcast     #14                 // class org/kohsuke/github/Requester
        16: ldc           #15                 // String /installation/repositories
        18: iconst_0
        19: anewarray     #16                 // class java/lang/String
        22: invokevirtual #17                 // Method org/kohsuke/github/Requester.withUrlPath:(Ljava/lang/String;[Ljava/lang/String;)Lorg/kohsuke/github/GitHubRequest$Builder;
        25: checkcast     #14                 // class org/kohsuke/github/Requester
        28: invokevirtual #18                 // Method org/kohsuke/github/Requester.build:()Lorg/kohsuke/github/GitHubRequest;
        31: astore_1
        32: new           #19                 // class org/kohsuke/github/PagedSearchIterable
        35: dup
        36: aload_0
        37: invokevirtual #10                 // Method root:()Lorg/kohsuke/github/GitHub;
        40: aload_1
        41: ldc           #20                 // class org/kohsuke/github/GHAppInstallation$GHAppInstallationRepositoryResult
        43: invokespecial #21                 // Method org/kohsuke/github/PagedSearchIterable."<init>":(Lorg/kohsuke/github/GitHub;Lorg/kohsuke/github/GitHubRequest;Ljava/lang/Class;)V
        46: areturn
      LineNumberTable:
        line 125: 0
        line 127: 32
      LocalVariableTable:
        Start  Length  Slot  Name   Signature
            0      47     0  this   Lorg/kohsuke/github/GHAppInstallation;
           32      15     1 request   Lorg/kohsuke/github/GitHubRequest;
    Signature: #120                         // ()Lorg/kohsuke/github/PagedSearchIterable<Lorg/kohsuke/github/GHRepository;>;
    RuntimeVisibleAnnotations:
      0: #121(#62=[e#122.#123])
        org.kohsuke.github.Preview(
          value=[Lorg/kohsuke/github/internal/Previews;.MACHINE_MAN]
        )

  public void setRepositoriesUrl(java.lang.String);
    descriptor: (Ljava/lang/String;)V
    flags: (0x0001) ACC_PUBLIC
    Code:
      stack=3, locals=2, args_size=2
         0: new           #4                  // class java/lang/RuntimeException
         3: dup
         4: ldc           #5                  // String Do not use this method.
         6: invokespecial #6                  // Method java/lang/RuntimeException."<init>":(Ljava/lang/String;)V
         9: athrow
      LineNumberTable:
        line 148: 0
      LocalVariableTable:
        Start  Length  Slot  Name   Signature
            0      10     0  this   Lorg/kohsuke/github/GHAppInstallation;
            0      10     1 repositoriesUrl   Ljava/lang/String;
    Deprecated: true
    RuntimeVisibleAnnotations:
      0: #101()
        java.lang.Deprecated

  public long getAppId();
    descriptor: ()J
    flags: (0x0001) ACC_PUBLIC
    Code:
      stack=2, locals=1, args_size=1
         0: aload_0
         1: getfield      #22                 // Field appId:J
         4: lreturn
      LineNumberTable:
        line 157: 0
      LocalVariableTable:
        Start  Length  Slot  Name   Signature
            0       5     0  this   Lorg/kohsuke/github/GHAppInstallation;

  public void setAppId(long);
    descriptor: (J)V
    flags: (0x0001) ACC_PUBLIC
    Code:
      stack=3, locals=3, args_size=2
         0: new           #4                  // class java/lang/RuntimeException
         3: dup
         4: ldc           #5                  // String Do not use this method.
         6: invokespecial #6                  // Method java/lang/RuntimeException."<init>":(Ljava/lang/String;)V
         9: athrow
      LineNumberTable:
        line 169: 0
      LocalVariableTable:
        Start  Length  Slot  Name   Signature
            0      10     0  this   Lorg/kohsuke/github/GHAppInstallation;
            0      10     1 appId   J
    Deprecated: true
    RuntimeVisibleAnnotations:
      0: #101()
        java.lang.Deprecated

  public long getTargetId();
    descriptor: ()J
    flags: (0x0001) ACC_PUBLIC
    Code:
      stack=2, locals=1, args_size=1
         0: aload_0
         1: getfield      #23                 // Field targetId:J
         4: lreturn
      LineNumberTable:
        line 178: 0
      LocalVariableTable:
        Start  Length  Slot  Name   Signature
            0       5     0  this   Lorg/kohsuke/github/GHAppInstallation;

  public void setTargetId(long);
    descriptor: (J)V
    flags: (0x0001) ACC_PUBLIC
    Code:
      stack=3, locals=3, args_size=2
         0: new           #4                  // class java/lang/RuntimeException
         3: dup
         4: ldc           #5                  // String Do not use this method.
         6: invokespecial #6                  // Method java/lang/RuntimeException."<init>":(Ljava/lang/String;)V
         9: athrow
      LineNumberTable:
        line 190: 0
      LocalVariableTable:
        Start  Length  Slot  Name   Signature
            0      10     0  this   Lorg/kohsuke/github/GHAppInstallation;
            0      10     1 targetId   J
    Deprecated: true
    RuntimeVisibleAnnotations:
      0: #101()
        java.lang.Deprecated

  public org.kohsuke.github.GHTargetType getTargetType();
    descriptor: ()Lorg/kohsuke/github/GHTargetType;
    flags: (0x0001) ACC_PUBLIC
    Code:
      stack=1, locals=1, args_size=1
         0: aload_0
         1: getfield      #24                 // Field targetType:Lorg/kohsuke/github/GHTargetType;
         4: areturn
      LineNumberTable:
        line 199: 0
      LocalVariableTable:
        Start  Length  Slot  Name   Signature
            0       5     0  this   Lorg/kohsuke/github/GHAppInstallation;

  public void setTargetType(org.kohsuke.github.GHTargetType);
    descriptor: (Lorg/kohsuke/github/GHTargetType;)V
    flags: (0x0001) ACC_PUBLIC
    Code:
      stack=3, locals=2, args_size=2
         0: new           #4                  // class java/lang/RuntimeException
         3: dup
         4: ldc           #5                  // String Do not use this method.
         6: invokespecial #6                  // Method java/lang/RuntimeException."<init>":(Ljava/lang/String;)V
         9: athrow
      LineNumberTable:
        line 211: 0
      LocalVariableTable:
        Start  Length  Slot  Name   Signature
            0      10     0  this   Lorg/kohsuke/github/GHAppInstallation;
            0      10     1 targetType   Lorg/kohsuke/github/GHTargetType;
    Deprecated: true
    RuntimeVisibleAnnotations:
      0: #101()
        java.lang.Deprecated

  public java.util.Map<java.lang.String, org.kohsuke.github.GHPermissionType> getPermissions();
    descriptor: ()Ljava/util/Map;
    flags: (0x0001) ACC_PUBLIC
    Code:
      stack=1, locals=1, args_size=1
         0: aload_0
         1: getfield      #25                 // Field permissions:Ljava/util/Map;
         4: invokestatic  #26                 // Method java/util/Collections.unmodifiableMap:(Ljava/util/Map;)Ljava/util/Map;
         7: areturn
      LineNumberTable:
        line 220: 0
      LocalVariableTable:
        Start  Length  Slot  Name   Signature
            0       8     0  this   Lorg/kohsuke/github/GHAppInstallation;
    Signature: #137                         // ()Ljava/util/Map<Ljava/lang/String;Lorg/kohsuke/github/GHPermissionType;>;

  public void setPermissions(java.util.Map<java.lang.String, org.kohsuke.github.GHPermissionType>);
    descriptor: (Ljava/util/Map;)V
    flags: (0x0001) ACC_PUBLIC
    Code:
      stack=3, locals=2, args_size=2
         0: new           #4                  // class java/lang/RuntimeException
         3: dup
         4: ldc           #5                  // String Do not use this method.
         6: invokespecial #6                  // Method java/lang/RuntimeException."<init>":(Ljava/lang/String;)V
         9: athrow
      LineNumberTable:
        line 232: 0
      LocalVariableTable:
        Start  Length  Slot  Name   Signature
            0      10     0  this   Lorg/kohsuke/github/GHAppInstallation;
            0      10     1 permissions   Ljava/util/Map;
      LocalVariableTypeTable:
        Start  Length  Slot  Name   Signature
            0      10     1 permissions   Ljava/util/Map<Ljava/lang/String;Lorg/kohsuke/github/GHPermissionType;>;
    Deprecated: true
    Signature: #141                         // (Ljava/util/Map<Ljava/lang/String;Lorg/kohsuke/github/GHPermissionType;>;)V
    RuntimeVisibleAnnotations:
      0: #101()
        java.lang.Deprecated

  public java.util.List<org.kohsuke.github.GHEvent> getEvents();
    descriptor: ()Ljava/util/List;
    flags: (0x0001) ACC_PUBLIC
    Code:
      stack=2, locals=1, args_size=1
         0: aload_0
         1: getfield      #27                 // Field events:Ljava/util/List;
         4: invokeinterface #28,  1           // InterfaceMethod java/util/List.stream:()Ljava/util/stream/Stream;
         9: invokedynamic #29,  0             // InvokeDynamic #0:apply:()Ljava/util/function/Function;
        14: invokeinterface #30,  2           // InterfaceMethod java/util/stream/Stream.map:(Ljava/util/function/Function;)Ljava/util/stream/Stream;
        19: invokestatic  #31                 // Method java/util/stream/Collectors.toList:()Ljava/util/stream/Collector;
        22: invokeinterface #32,  2           // InterfaceMethod java/util/stream/Stream.collect:(Ljava/util/stream/Collector;)Ljava/lang/Object;
        27: checkcast     #33                 // class java/util/List
        30: areturn
      LineNumberTable:
        line 241: 0
        line 242: 14
        line 243: 19
        line 241: 30
      LocalVariableTable:
        Start  Length  Slot  Name   Signature
            0      31     0  this   Lorg/kohsuke/github/GHAppInstallation;
    Signature: #144                         // ()Ljava/util/List<Lorg/kohsuke/github/GHEvent;>;

  public void setEvents(java.util.List<org.kohsuke.github.GHEvent>);
    descriptor: (Ljava/util/List;)V
    flags: (0x0001) ACC_PUBLIC
    Code:
      stack=3, locals=2, args_size=2
         0: new           #4                  // class java/lang/RuntimeException
         3: dup
         4: ldc           #5                  // String Do not use this method.
         6: invokespecial #6                  // Method java/lang/RuntimeException."<init>":(Ljava/lang/String;)V
         9: athrow
      LineNumberTable:
        line 255: 0
      LocalVariableTable:
        Start  Length  Slot  Name   Signature
            0      10     0  this   Lorg/kohsuke/github/GHAppInstallation;
            0      10     1 events   Ljava/util/List;
      LocalVariableTypeTable:
        Start  Length  Slot  Name   Signature
            0      10     1 events   Ljava/util/List<Lorg/kohsuke/github/GHEvent;>;
    Deprecated: true
    Signature: #148                         // (Ljava/util/List<Lorg/kohsuke/github/GHEvent;>;)V
    RuntimeVisibleAnnotations:
      0: #101()
        java.lang.Deprecated

  public java.lang.String getSingleFileName();
    descriptor: ()Ljava/lang/String;
    flags: (0x0001) ACC_PUBLIC
    Code:
      stack=1, locals=1, args_size=1
         0: aload_0
         1: getfield      #34                 // Field singleFileName:Ljava/lang/String;
         4: areturn
      LineNumberTable:
        line 264: 0
      LocalVariableTable:
        Start  Length  Slot  Name   Signature
            0       5     0  this   Lorg/kohsuke/github/GHAppInstallation;

  public void setSingleFileName(java.lang.String);
    descriptor: (Ljava/lang/String;)V
    flags: (0x0001) ACC_PUBLIC
    Code:
      stack=3, locals=2, args_size=2
         0: new           #4                  // class java/lang/RuntimeException
         3: dup
         4: ldc           #5                  // String Do not use this method.
         6: invokespecial #6                  // Method java/lang/RuntimeException."<init>":(Ljava/lang/String;)V
         9: athrow
      LineNumberTable:
        line 276: 0
      LocalVariableTable:
        Start  Length  Slot  Name   Signature
            0      10     0  this   Lorg/kohsuke/github/GHAppInstallation;
            0      10     1 singleFileName   Ljava/lang/String;
    Deprecated: true
    RuntimeVisibleAnnotations:
      0: #101()
        java.lang.Deprecated

  public org.kohsuke.github.GHRepositorySelection getRepositorySelection();
    descriptor: ()Lorg/kohsuke/github/GHRepositorySelection;
    flags: (0x0001) ACC_PUBLIC
    Code:
      stack=1, locals=1, args_size=1
         0: aload_0
         1: getfield      #35                 // Field repositorySelection:Lorg/kohsuke/github/GHRepositorySelection;
         4: areturn
      LineNumberTable:
        line 285: 0
      LocalVariableTable:
        Start  Length  Slot  Name   Signature
            0       5     0  this   Lorg/kohsuke/github/GHAppInstallation;

  public void setRepositorySelection(org.kohsuke.github.GHRepositorySelection);
    descriptor: (Lorg/kohsuke/github/GHRepositorySelection;)V
    flags: (0x0001) ACC_PUBLIC
    Code:
      stack=3, locals=2, args_size=2
         0: new           #4                  // class java/lang/RuntimeException
         3: dup
         4: ldc           #5                  // String Do not use this method.
         6: invokespecial #6                  // Method java/lang/RuntimeException."<init>":(Ljava/lang/String;)V
         9: athrow
      LineNumberTable:
        line 297: 0
      LocalVariableTable:
        Start  Length  Slot  Name   Signature
            0      10     0  this   Lorg/kohsuke/github/GHAppInstallation;
            0      10     1 repositorySelection   Lorg/kohsuke/github/GHRepositorySelection;
    Deprecated: true
    RuntimeVisibleAnnotations:
      0: #101()
        java.lang.Deprecated

  public void deleteInstallation() throws java.io.IOException;
    descriptor: ()V
    flags: (0x0001) ACC_PUBLIC
    Code:
      stack=7, locals=1, args_size=1
         0: aload_0
         1: invokevirtual #10                 // Method root:()Lorg/kohsuke/github/GitHub;
         4: invokevirtual #11                 // Method org/kohsuke/github/GitHub.createRequest:()Lorg/kohsuke/github/Requester;
         7: ldc           #36                 // String DELETE
         9: invokevirtual #37                 // Method org/kohsuke/github/Requester.method:(Ljava/lang/String;)Lorg/kohsuke/github/GitHubRequest$Builder;
        12: checkcast     #14                 // class org/kohsuke/github/Requester
        15: getstatic     #38                 // Field org/kohsuke/github/internal/Previews.GAMBIT:Lorg/kohsuke/github/internal/Previews;
        18: invokevirtual #13                 // Method org/kohsuke/github/Requester.withPreview:(Lorg/kohsuke/github/internal/Previews;)Lorg/kohsuke/github/GitHubRequest$Builder;
        21: checkcast     #14                 // class org/kohsuke/github/Requester
        24: ldc           #39                 // String /app/installations/%d
        26: iconst_1
        27: anewarray     #40                 // class java/lang/Object
        30: dup
        31: iconst_0
        32: aload_0
        33: invokevirtual #41                 // Method getId:()J
        36: invokestatic  #42                 // Method java/lang/Long.valueOf:(J)Ljava/lang/Long;
        39: aastore
        40: invokestatic  #43                 // Method java/lang/String.format:(Ljava/lang/String;[Ljava/lang/Object;)Ljava/lang/String;
        43: iconst_0
        44: anewarray     #16                 // class java/lang/String
        47: invokevirtual #17                 // Method org/kohsuke/github/Requester.withUrlPath:(Ljava/lang/String;[Ljava/lang/String;)Lorg/kohsuke/github/GitHubRequest$Builder;
        50: checkcast     #14                 // class org/kohsuke/github/Requester
        53: invokevirtual #44                 // Method org/kohsuke/github/Requester.send:()V
        56: return
      LineNumberTable:
        line 311: 0
        line 312: 9
        line 313: 18
        line 314: 33
        line 315: 53
        line 316: 56
      LocalVariableTable:
        Start  Length  Slot  Name   Signature
            0      57     0  this   Lorg/kohsuke/github/GHAppInstallation;
    Exceptions:
      throws java.io.IOException
    RuntimeVisibleAnnotations:
      0: #121(#62=[e#122.#158])
        org.kohsuke.github.Preview(
          value=[Lorg/kohsuke/github/internal/Previews;.GAMBIT]
        )

  public org.kohsuke.github.GHAppCreateTokenBuilder createToken(java.util.Map<java.lang.String, org.kohsuke.github.GHPermissionType>);
    descriptor: (Ljava/util/Map;)Lorg/kohsuke/github/GHAppCreateTokenBuilder;
    flags: (0x0001) ACC_PUBLIC
    Code:
      stack=9, locals=2, args_size=2
         0: new           #45                 // class org/kohsuke/github/GHAppCreateTokenBuilder
         3: dup
         4: aload_0
         5: invokevirtual #10                 // Method root:()Lorg/kohsuke/github/GitHub;
         8: ldc           #46                 // String /app/installations/%d/access_tokens
        10: iconst_1
        11: anewarray     #40                 // class java/lang/Object
        14: dup
        15: iconst_0
        16: aload_0
        17: invokevirtual #41                 // Method getId:()J
        20: invokestatic  #42                 // Method java/lang/Long.valueOf:(J)Ljava/lang/Long;
        23: aastore
        24: invokestatic  #43                 // Method java/lang/String.format:(Ljava/lang/String;[Ljava/lang/Object;)Ljava/lang/String;
        27: aload_1
        28: invokespecial #47                 // Method org/kohsuke/github/GHAppCreateTokenBuilder."<init>":(Lorg/kohsuke/github/GitHub;Ljava/lang/String;Ljava/util/Map;)V
        31: areturn
      LineNumberTable:
        line 332: 0
        line 333: 17
        line 332: 31
      LocalVariableTable:
        Start  Length  Slot  Name   Signature
            0      32     0  this   Lorg/kohsuke/github/GHAppInstallation;
            0      32     1 permissions   Ljava/util/Map;
      LocalVariableTypeTable:
        Start  Length  Slot  Name   Signature
            0      32     1 permissions   Ljava/util/Map<Ljava/lang/String;Lorg/kohsuke/github/GHPermissionType;>;
    Deprecated: true
    Signature: #161                         // (Ljava/util/Map<Ljava/lang/String;Lorg/kohsuke/github/GHPermissionType;>;)Lorg/kohsuke/github/GHAppCreateTokenBuilder;
    RuntimeVisibleAnnotations:
      0: #162()
        org.kohsuke.github.BetaApi

  public org.kohsuke.github.GHAppCreateTokenBuilder createToken();
    descriptor: ()Lorg/kohsuke/github/GHAppCreateTokenBuilder;
    flags: (0x0001) ACC_PUBLIC
    Code:
      stack=9, locals=1, args_size=1
         0: new           #45                 // class org/kohsuke/github/GHAppCreateTokenBuilder
         3: dup
         4: aload_0
         5: invokevirtual #10                 // Method root:()Lorg/kohsuke/github/GitHub;
         8: ldc           #46                 // String /app/installations/%d/access_tokens
        10: iconst_1
        11: anewarray     #40                 // class java/lang/Object
        14: dup
        15: iconst_0
        16: aload_0
        17: invokevirtual #41                 // Method getId:()J
        20: invokestatic  #42                 // Method java/lang/Long.valueOf:(J)Ljava/lang/Long;
        23: aastore
        24: invokestatic  #43                 // Method java/lang/String.format:(Ljava/lang/String;[Ljava/lang/Object;)Ljava/lang/String;
        27: invokespecial #48                 // Method org/kohsuke/github/GHAppCreateTokenBuilder."<init>":(Lorg/kohsuke/github/GitHub;Ljava/lang/String;)V
        30: areturn
      LineNumberTable:
        line 348: 0
      LocalVariableTable:
        Start  Length  Slot  Name   Signature
            0      31     0  this   Lorg/kohsuke/github/GHAppInstallation;
    RuntimeVisibleAnnotations:
      0: #162()
        org.kohsuke.github.BetaApi

  private static org.kohsuke.github.GHEvent lambda$getEvents$0(java.lang.String);
    descriptor: (Ljava/lang/String;)Lorg/kohsuke/github/GHEvent;
    flags: (0x100a) ACC_PRIVATE, ACC_STATIC, ACC_SYNTHETIC
    Code:
      stack=3, locals=1, args_size=1
         0: ldc           #49                 // class org/kohsuke/github/GHEvent
         2: aload_0
         3: getstatic     #50                 // Field org/kohsuke/github/GHEvent.UNKNOWN:Lorg/kohsuke/github/GHEvent;
         6: invokestatic  #51                 // Method org/kohsuke/github/internal/EnumUtils.getEnumOrDefault:(Ljava/lang/Class;Ljava/lang/String;Ljava/lang/Enum;)Ljava/lang/Enum;
         9: checkcast     #49                 // class org/kohsuke/github/GHEvent
        12: areturn
      LineNumberTable:
        line 242: 0
      LocalVariableTable:
        Start  Length  Slot  Name   Signature
            0      13     0     e   Ljava/lang/String;
}
SourceFile: "GHAppInstallation.java"
InnerClasses:
  private static #54= #20 of #52;         // GHAppInstallationRepositoryResult=class org/kohsuke/github/GHAppInstallation$GHAppInstallationRepositoryResult of class org/kohsuke/github/GHAppInstallation
  static #246= #245 of #287;              // Builder=class org/kohsuke/github/GitHubRequest$Builder of class org/kohsuke/github/GitHubRequest
  public static final #296= #295 of #298; // Lookup=class java/lang/invoke/MethodHandles$Lookup of class java/lang/invoke/MethodHandles
BootstrapMethods:
  0: #202 REF_invokeStatic java/lang/invoke/LambdaMetafactory.metafactory:(Ljava/lang/invoke/MethodHandles$Lookup;Ljava/lang/String;Ljava/lang/invoke/MethodType;Ljava/lang/invoke/MethodType;Ljava/lang/invoke/MethodHandle;Ljava/lang/invoke/MethodType;)Ljava/lang/invoke/CallSite;
    Method arguments:
      #203 (Ljava/lang/Object;)Ljava/lang/Object;
      #204 REF_invokeStatic org/kohsuke/github/GHAppInstallation.lambda$getEvents$0:(Ljava/lang/String;)Lorg/kohsuke/github/GHEvent;
      #205 (Ljava/lang/String;)Lorg/kohsuke/github/GHEvent;
