Classfile /Users/mw/Projects/slang-braindump/.jar/jar11/assemble/slang-braindump/assemble/content/org/kohsuke/github/GHAsset.class
  Last modified May 29, 2022; size 3804 bytes
  SHA-256 checksum 458a897a14ae82bc4f3f4703b74d9ee8081b3db4139a1aced7496470e68d2d9b
  Compiled from "GHAsset.java"
public class org.kohsuke.github.GHAsset extends org.kohsuke.github.GHObject
  minor version: 0
  major version: 52
  flags: (0x0021) ACC_PUBLIC, ACC_SUPER
  this_class: #37                         // org/kohsuke/github/GHAsset
  super_class: #38                        // org/kohsuke/github/GHObject
  interfaces: 0, fields: 8, methods: 17, attributes: 2
Constant pool:
    #1 = Methodref          #38.#101      // org/kohsuke/github/GHObject."<init>":()V
    #2 = Fieldref           #37.#102      // org/kohsuke/github/GHAsset.content_type:Ljava/lang/String;
    #3 = String             #45           // content_type
    #4 = Methodref          #37.#103      // org/kohsuke/github/GHAsset.edit:(Ljava/lang/String;Ljava/lang/Object;)V
    #5 = Fieldref           #37.#104      // org/kohsuke/github/GHAsset.download_count:J
    #6 = Fieldref           #37.#105      // org/kohsuke/github/GHAsset.label:Ljava/lang/String;
    #7 = String             #43           // label
    #8 = Fieldref           #37.#106      // org/kohsuke/github/GHAsset.name:Ljava/lang/String;
    #9 = Fieldref           #37.#107      // org/kohsuke/github/GHAsset.owner:Lorg/kohsuke/github/GHRepository;
   #10 = Fieldref           #37.#108      // org/kohsuke/github/GHAsset.size:J
   #11 = Fieldref           #37.#109      // org/kohsuke/github/GHAsset.state:Ljava/lang/String;
   #12 = Fieldref           #37.#110      // org/kohsuke/github/GHAsset.browser_download_url:Ljava/lang/String;
   #13 = Methodref          #37.#111      // org/kohsuke/github/GHAsset.root:()Lorg/kohsuke/github/GitHub;
   #14 = Methodref          #112.#113     // org/kohsuke/github/GitHub.createRequest:()Lorg/kohsuke/github/Requester;
   #15 = Methodref          #16.#114      // org/kohsuke/github/Requester.with:(Ljava/lang/String;Ljava/lang/Object;)Lorg/kohsuke/github/GitHubRequest$Builder;
   #16 = Class              #115          // org/kohsuke/github/Requester
   #17 = String             #116          // PATCH
   #18 = Methodref          #16.#117      // org/kohsuke/github/Requester.method:(Ljava/lang/String;)Lorg/kohsuke/github/GitHubRequest$Builder;
   #19 = Methodref          #37.#118      // org/kohsuke/github/GHAsset.getApiRoute:()Ljava/lang/String;
   #20 = Class              #119          // java/lang/String
   #21 = Methodref          #16.#120      // org/kohsuke/github/Requester.withUrlPath:(Ljava/lang/String;[Ljava/lang/String;)Lorg/kohsuke/github/GitHubRequest$Builder;
   #22 = Methodref          #16.#121      // org/kohsuke/github/Requester.send:()V
   #23 = String             #122          // DELETE
   #24 = Class              #123          // java/lang/StringBuilder
   #25 = Methodref          #24.#101      // java/lang/StringBuilder."<init>":()V
   #26 = String             #124          // /repos/
   #27 = Methodref          #24.#125      // java/lang/StringBuilder.append:(Ljava/lang/String;)Ljava/lang/StringBuilder;
   #28 = Methodref          #126.#127     // org/kohsuke/github/GHRepository.getOwnerName:()Ljava/lang/String;
   #29 = String             #128          // /
   #30 = Methodref          #126.#129     // org/kohsuke/github/GHRepository.getName:()Ljava/lang/String;
   #31 = String             #130          // /releases/assets/
   #32 = Methodref          #37.#131      // org/kohsuke/github/GHAsset.getId:()J
   #33 = Methodref          #24.#132      // java/lang/StringBuilder.append:(J)Ljava/lang/StringBuilder;
   #34 = Methodref          #24.#133      // java/lang/StringBuilder.toString:()Ljava/lang/String;
   #35 = Methodref          #134.#135     // org/kohsuke/github/GHRelease.getOwner:()Lorg/kohsuke/github/GHRepository;
   #36 = Methodref          #37.#136      // org/kohsuke/github/GHAsset.wrap:(Lorg/kohsuke/github/GHRelease;)Lorg/kohsuke/github/GHAsset;
   #37 = Class              #137          // org/kohsuke/github/GHAsset
   #38 = Class              #138          // org/kohsuke/github/GHObject
   #39 = Utf8               owner
   #40 = Utf8               Lorg/kohsuke/github/GHRepository;
   #41 = Utf8               name
   #42 = Utf8               Ljava/lang/String;
   #43 = Utf8               label
   #44 = Utf8               state
   #45 = Utf8               content_type
   #46 = Utf8               size
   #47 = Utf8               J
   #48 = Utf8               download_count
   #49 = Utf8               browser_download_url
   #50 = Utf8               <init>
   #51 = Utf8               ()V
   #52 = Utf8               Code
   #53 = Utf8               LineNumberTable
   #54 = Utf8               LocalVariableTable
   #55 = Utf8               this
   #56 = Utf8               Lorg/kohsuke/github/GHAsset;
   #57 = Utf8               getContentType
   #58 = Utf8               ()Ljava/lang/String;
   #59 = Utf8               setContentType
   #60 = Utf8               (Ljava/lang/String;)V
   #61 = Utf8               contentType
   #62 = Utf8               Exceptions
   #63 = Class              #139          // java/io/IOException
   #64 = Utf8               getDownloadCount
   #65 = Utf8               ()J
   #66 = Utf8               getLabel
   #67 = Utf8               setLabel
   #68 = Utf8               getName
   #69 = Utf8               getOwner
   #70 = Utf8               ()Lorg/kohsuke/github/GHRepository;
   #71 = Utf8               RuntimeInvisibleAnnotations
   #72 = Utf8               Ledu/umd/cs/findbugs/annotations/SuppressFBWarnings;
   #73 = Utf8               value
   #74 = Utf8               EI_EXPOSE_REP
   #75 = Utf8               justification
   #76 = Utf8               Expected behavior
   #77 = Utf8               getSize
   #78 = Utf8               getState
   #79 = Utf8               getHtmlUrl
   #80 = Utf8               ()Ljava/net/URL;
   #81 = Utf8               Deprecated
   #82 = Utf8               getBrowserDownloadUrl
   #83 = Utf8               edit
   #84 = Utf8               (Ljava/lang/String;Ljava/lang/Object;)V
   #85 = Utf8               key
   #86 = Utf8               Ljava/lang/Object;
   #87 = Utf8               delete
   #88 = Utf8               getApiRoute
   #89 = Utf8               wrap
   #90 = Utf8               (Lorg/kohsuke/github/GHRelease;)Lorg/kohsuke/github/GHAsset;
   #91 = Utf8               release
   #92 = Utf8               Lorg/kohsuke/github/GHRelease;
   #93 = Utf8               ([Lorg/kohsuke/github/GHAsset;Lorg/kohsuke/github/GHRelease;)[Lorg/kohsuke/github/GHAsset;
   #94 = Utf8               aTo
   #95 = Utf8               assets
   #96 = Utf8               [Lorg/kohsuke/github/GHAsset;
   #97 = Utf8               StackMapTable
   #98 = Class              #96           // "[Lorg/kohsuke/github/GHAsset;"
   #99 = Utf8               SourceFile
  #100 = Utf8               GHAsset.java
  #101 = NameAndType        #50:#51       // "<init>":()V
  #102 = NameAndType        #45:#42       // content_type:Ljava/lang/String;
  #103 = NameAndType        #83:#84       // edit:(Ljava/lang/String;Ljava/lang/Object;)V
  #104 = NameAndType        #48:#47       // download_count:J
  #105 = NameAndType        #43:#42       // label:Ljava/lang/String;
  #106 = NameAndType        #41:#42       // name:Ljava/lang/String;
  #107 = NameAndType        #39:#40       // owner:Lorg/kohsuke/github/GHRepository;
  #108 = NameAndType        #46:#47       // size:J
  #109 = NameAndType        #44:#42       // state:Ljava/lang/String;
  #110 = NameAndType        #49:#42       // browser_download_url:Ljava/lang/String;
  #111 = NameAndType        #140:#141     // root:()Lorg/kohsuke/github/GitHub;
  #112 = Class              #142          // org/kohsuke/github/GitHub
  #113 = NameAndType        #143:#144     // createRequest:()Lorg/kohsuke/github/Requester;
  #114 = NameAndType        #145:#149     // with:(Ljava/lang/String;Ljava/lang/Object;)Lorg/kohsuke/github/GitHubRequest$Builder;
  #115 = Utf8               org/kohsuke/github/Requester
  #116 = Utf8               PATCH
  #117 = NameAndType        #150:#151     // method:(Ljava/lang/String;)Lorg/kohsuke/github/GitHubRequest$Builder;
  #118 = NameAndType        #88:#58       // getApiRoute:()Ljava/lang/String;
  #119 = Utf8               java/lang/String
  #120 = NameAndType        #152:#153     // withUrlPath:(Ljava/lang/String;[Ljava/lang/String;)Lorg/kohsuke/github/GitHubRequest$Builder;
  #121 = NameAndType        #154:#51      // send:()V
  #122 = Utf8               DELETE
  #123 = Utf8               java/lang/StringBuilder
  #124 = Utf8               /repos/
  #125 = NameAndType        #155:#156     // append:(Ljava/lang/String;)Ljava/lang/StringBuilder;
  #126 = Class              #157          // org/kohsuke/github/GHRepository
  #127 = NameAndType        #158:#58      // getOwnerName:()Ljava/lang/String;
  #128 = Utf8               /
  #129 = NameAndType        #68:#58       // getName:()Ljava/lang/String;
  #130 = Utf8               /releases/assets/
  #131 = NameAndType        #159:#65      // getId:()J
  #132 = NameAndType        #155:#160     // append:(J)Ljava/lang/StringBuilder;
  #133 = NameAndType        #161:#58      // toString:()Ljava/lang/String;
  #134 = Class              #162          // org/kohsuke/github/GHRelease
  #135 = NameAndType        #69:#70       // getOwner:()Lorg/kohsuke/github/GHRepository;
  #136 = NameAndType        #89:#90       // wrap:(Lorg/kohsuke/github/GHRelease;)Lorg/kohsuke/github/GHAsset;
  #137 = Utf8               org/kohsuke/github/GHAsset
  #138 = Utf8               org/kohsuke/github/GHObject
  #139 = Utf8               java/io/IOException
  #140 = Utf8               root
  #141 = Utf8               ()Lorg/kohsuke/github/GitHub;
  #142 = Utf8               org/kohsuke/github/GitHub
  #143 = Utf8               createRequest
  #144 = Utf8               ()Lorg/kohsuke/github/Requester;
  #145 = Utf8               with
  #146 = Class              #164          // org/kohsuke/github/GitHubRequest$Builder
  #147 = Utf8               Builder
  #148 = Utf8               InnerClasses
  #149 = Utf8               (Ljava/lang/String;Ljava/lang/Object;)Lorg/kohsuke/github/GitHubRequest$Builder;
  #150 = Utf8               method
  #151 = Utf8               (Ljava/lang/String;)Lorg/kohsuke/github/GitHubRequest$Builder;
  #152 = Utf8               withUrlPath
  #153 = Utf8               (Ljava/lang/String;[Ljava/lang/String;)Lorg/kohsuke/github/GitHubRequest$Builder;
  #154 = Utf8               send
  #155 = Utf8               append
  #156 = Utf8               (Ljava/lang/String;)Ljava/lang/StringBuilder;
  #157 = Utf8               org/kohsuke/github/GHRepository
  #158 = Utf8               getOwnerName
  #159 = Utf8               getId
  #160 = Utf8               (J)Ljava/lang/StringBuilder;
  #161 = Utf8               toString
  #162 = Utf8               org/kohsuke/github/GHRelease
  #163 = Class              #165          // org/kohsuke/github/GitHubRequest
  #164 = Utf8               org/kohsuke/github/GitHubRequest$Builder
  #165 = Utf8               org/kohsuke/github/GitHubRequest
{
  org.kohsuke.github.GHRepository owner;
    descriptor: Lorg/kohsuke/github/GHRepository;
    flags: (0x0000)

  private java.lang.String name;
    descriptor: Ljava/lang/String;
    flags: (0x0002) ACC_PRIVATE

  private java.lang.String label;
    descriptor: Ljava/lang/String;
    flags: (0x0002) ACC_PRIVATE

  private java.lang.String state;
    descriptor: Ljava/lang/String;
    flags: (0x0002) ACC_PRIVATE

  private java.lang.String content_type;
    descriptor: Ljava/lang/String;
    flags: (0x0002) ACC_PRIVATE

  private long size;
    descriptor: J
    flags: (0x0002) ACC_PRIVATE

  private long download_count;
    descriptor: J
    flags: (0x0002) ACC_PRIVATE

  private java.lang.String browser_download_url;
    descriptor: Ljava/lang/String;
    flags: (0x0002) ACC_PRIVATE

  public org.kohsuke.github.GHAsset();
    descriptor: ()V
    flags: (0x0001) ACC_PUBLIC
    Code:
      stack=1, locals=1, args_size=1
         0: aload_0
         1: invokespecial #1                  // Method org/kohsuke/github/GHObject."<init>":()V
         4: return
      LineNumberTable:
        line 13: 0
      LocalVariableTable:
        Start  Length  Slot  Name   Signature
            0       5     0  this   Lorg/kohsuke/github/GHAsset;

  public java.lang.String getContentType();
    descriptor: ()Ljava/lang/String;
    flags: (0x0001) ACC_PUBLIC
    Code:
      stack=1, locals=1, args_size=1
         0: aload_0
         1: getfield      #2                  // Field content_type:Ljava/lang/String;
         4: areturn
      LineNumberTable:
        line 29: 0
      LocalVariableTable:
        Start  Length  Slot  Name   Signature
            0       5     0  this   Lorg/kohsuke/github/GHAsset;

  public void setContentType(java.lang.String) throws java.io.IOException;
    descriptor: (Ljava/lang/String;)V
    flags: (0x0001) ACC_PUBLIC
    Code:
      stack=3, locals=2, args_size=2
         0: aload_0
         1: ldc           #3                  // String content_type
         3: aload_1
         4: invokespecial #4                  // Method edit:(Ljava/lang/String;Ljava/lang/Object;)V
         7: aload_0
         8: aload_1
         9: putfield      #2                  // Field content_type:Ljava/lang/String;
        12: return
      LineNumberTable:
        line 41: 0
        line 42: 7
        line 43: 12
      LocalVariableTable:
        Start  Length  Slot  Name   Signature
            0      13     0  this   Lorg/kohsuke/github/GHAsset;
            0      13     1 contentType   Ljava/lang/String;
    Exceptions:
      throws java.io.IOException

  public long getDownloadCount();
    descriptor: ()J
    flags: (0x0001) ACC_PUBLIC
    Code:
      stack=2, locals=1, args_size=1
         0: aload_0
         1: getfield      #5                  // Field download_count:J
         4: lreturn
      LineNumberTable:
        line 51: 0
      LocalVariableTable:
        Start  Length  Slot  Name   Signature
            0       5     0  this   Lorg/kohsuke/github/GHAsset;

  public java.lang.String getLabel();
    descriptor: ()Ljava/lang/String;
    flags: (0x0001) ACC_PUBLIC
    Code:
      stack=1, locals=1, args_size=1
         0: aload_0
         1: getfield      #6                  // Field label:Ljava/lang/String;
         4: areturn
      LineNumberTable:
        line 60: 0
      LocalVariableTable:
        Start  Length  Slot  Name   Signature
            0       5     0  this   Lorg/kohsuke/github/GHAsset;

  public void setLabel(java.lang.String) throws java.io.IOException;
    descriptor: (Ljava/lang/String;)V
    flags: (0x0001) ACC_PUBLIC
    Code:
      stack=3, locals=2, args_size=2
         0: aload_0
         1: ldc           #7                  // String label
         3: aload_1
         4: invokespecial #4                  // Method edit:(Ljava/lang/String;Ljava/lang/Object;)V
         7: aload_0
         8: aload_1
         9: putfield      #6                  // Field label:Ljava/lang/String;
        12: return
      LineNumberTable:
        line 72: 0
        line 73: 7
        line 74: 12
      LocalVariableTable:
        Start  Length  Slot  Name   Signature
            0      13     0  this   Lorg/kohsuke/github/GHAsset;
            0      13     1 label   Ljava/lang/String;
    Exceptions:
      throws java.io.IOException

  public java.lang.String getName();
    descriptor: ()Ljava/lang/String;
    flags: (0x0001) ACC_PUBLIC
    Code:
      stack=1, locals=1, args_size=1
         0: aload_0
         1: getfield      #8                  // Field name:Ljava/lang/String;
         4: areturn
      LineNumberTable:
        line 82: 0
      LocalVariableTable:
        Start  Length  Slot  Name   Signature
            0       5     0  this   Lorg/kohsuke/github/GHAsset;

  public org.kohsuke.github.GHRepository getOwner();
    descriptor: ()Lorg/kohsuke/github/GHRepository;
    flags: (0x0001) ACC_PUBLIC
    Code:
      stack=1, locals=1, args_size=1
         0: aload_0
         1: getfield      #9                  // Field owner:Lorg/kohsuke/github/GHRepository;
         4: areturn
      LineNumberTable:
        line 92: 0
      LocalVariableTable:
        Start  Length  Slot  Name   Signature
            0       5     0  this   Lorg/kohsuke/github/GHAsset;
    RuntimeInvisibleAnnotations:
      0: #72(#73=[s#74],#75=s#76)
        edu.umd.cs.findbugs.annotations.SuppressFBWarnings(
          value=["EI_EXPOSE_REP"]
          justification="Expected behavior"
        )

  public long getSize();
    descriptor: ()J
    flags: (0x0001) ACC_PUBLIC
    Code:
      stack=2, locals=1, args_size=1
         0: aload_0
         1: getfield      #10                 // Field size:J
         4: lreturn
      LineNumberTable:
        line 101: 0
      LocalVariableTable:
        Start  Length  Slot  Name   Signature
            0       5     0  this   Lorg/kohsuke/github/GHAsset;

  public java.lang.String getState();
    descriptor: ()Ljava/lang/String;
    flags: (0x0001) ACC_PUBLIC
    Code:
      stack=1, locals=1, args_size=1
         0: aload_0
         1: getfield      #11                 // Field state:Ljava/lang/String;
         4: areturn
      LineNumberTable:
        line 110: 0
      LocalVariableTable:
        Start  Length  Slot  Name   Signature
            0       5     0  this   Lorg/kohsuke/github/GHAsset;

  public java.net.URL getHtmlUrl();
    descriptor: ()Ljava/net/URL;
    flags: (0x0001) ACC_PUBLIC
    Code:
      stack=1, locals=1, args_size=1
         0: aconst_null
         1: areturn
      LineNumberTable:
        line 118: 0
      LocalVariableTable:
        Start  Length  Slot  Name   Signature
            0       2     0  this   Lorg/kohsuke/github/GHAsset;
    Deprecated: true

  public java.lang.String getBrowserDownloadUrl();
    descriptor: ()Ljava/lang/String;
    flags: (0x0001) ACC_PUBLIC
    Code:
      stack=1, locals=1, args_size=1
         0: aload_0
         1: getfield      #12                 // Field browser_download_url:Ljava/lang/String;
         4: areturn
      LineNumberTable:
        line 127: 0
      LocalVariableTable:
        Start  Length  Slot  Name   Signature
            0       5     0  this   Lorg/kohsuke/github/GHAsset;

  private void edit(java.lang.String, java.lang.Object) throws java.io.IOException;
    descriptor: (Ljava/lang/String;Ljava/lang/Object;)V
    flags: (0x0002) ACC_PRIVATE
    Code:
      stack=3, locals=3, args_size=3
         0: aload_0
         1: invokevirtual #13                 // Method root:()Lorg/kohsuke/github/GitHub;
         4: invokevirtual #14                 // Method org/kohsuke/github/GitHub.createRequest:()Lorg/kohsuke/github/Requester;
         7: aload_1
         8: aload_2
         9: invokevirtual #15                 // Method org/kohsuke/github/Requester.with:(Ljava/lang/String;Ljava/lang/Object;)Lorg/kohsuke/github/GitHubRequest$Builder;
        12: checkcast     #16                 // class org/kohsuke/github/Requester
        15: ldc           #17                 // String PATCH
        17: invokevirtual #18                 // Method org/kohsuke/github/Requester.method:(Ljava/lang/String;)Lorg/kohsuke/github/GitHubRequest$Builder;
        20: checkcast     #16                 // class org/kohsuke/github/Requester
        23: aload_0
        24: invokespecial #19                 // Method getApiRoute:()Ljava/lang/String;
        27: iconst_0
        28: anewarray     #20                 // class java/lang/String
        31: invokevirtual #21                 // Method org/kohsuke/github/Requester.withUrlPath:(Ljava/lang/String;[Ljava/lang/String;)Lorg/kohsuke/github/GitHubRequest$Builder;
        34: checkcast     #16                 // class org/kohsuke/github/Requester
        37: invokevirtual #22                 // Method org/kohsuke/github/Requester.send:()V
        40: return
      LineNumberTable:
        line 131: 0
        line 132: 40
      LocalVariableTable:
        Start  Length  Slot  Name   Signature
            0      41     0  this   Lorg/kohsuke/github/GHAsset;
            0      41     1   key   Ljava/lang/String;
            0      41     2 value   Ljava/lang/Object;
    Exceptions:
      throws java.io.IOException

  public void delete() throws java.io.IOException;
    descriptor: ()V
    flags: (0x0001) ACC_PUBLIC
    Code:
      stack=3, locals=1, args_size=1
         0: aload_0
         1: invokevirtual #13                 // Method root:()Lorg/kohsuke/github/GitHub;
         4: invokevirtual #14                 // Method org/kohsuke/github/GitHub.createRequest:()Lorg/kohsuke/github/Requester;
         7: ldc           #23                 // String DELETE
         9: invokevirtual #18                 // Method org/kohsuke/github/Requester.method:(Ljava/lang/String;)Lorg/kohsuke/github/GitHubRequest$Builder;
        12: checkcast     #16                 // class org/kohsuke/github/Requester
        15: aload_0
        16: invokespecial #19                 // Method getApiRoute:()Ljava/lang/String;
        19: iconst_0
        20: anewarray     #20                 // class java/lang/String
        23: invokevirtual #21                 // Method org/kohsuke/github/Requester.withUrlPath:(Ljava/lang/String;[Ljava/lang/String;)Lorg/kohsuke/github/GitHubRequest$Builder;
        26: checkcast     #16                 // class org/kohsuke/github/Requester
        29: invokevirtual #22                 // Method org/kohsuke/github/Requester.send:()V
        32: return
      LineNumberTable:
        line 141: 0
        line 142: 32
      LocalVariableTable:
        Start  Length  Slot  Name   Signature
            0      33     0  this   Lorg/kohsuke/github/GHAsset;
    Exceptions:
      throws java.io.IOException

  private java.lang.String getApiRoute();
    descriptor: ()Ljava/lang/String;
    flags: (0x0002) ACC_PRIVATE
    Code:
      stack=3, locals=1, args_size=1
         0: new           #24                 // class java/lang/StringBuilder
         3: dup
         4: invokespecial #25                 // Method java/lang/StringBuilder."<init>":()V
         7: ldc           #26                 // String /repos/
         9: invokevirtual #27                 // Method java/lang/StringBuilder.append:(Ljava/lang/String;)Ljava/lang/StringBuilder;
        12: aload_0
        13: getfield      #9                  // Field owner:Lorg/kohsuke/github/GHRepository;
        16: invokevirtual #28                 // Method org/kohsuke/github/GHRepository.getOwnerName:()Ljava/lang/String;
        19: invokevirtual #27                 // Method java/lang/StringBuilder.append:(Ljava/lang/String;)Ljava/lang/StringBuilder;
        22: ldc           #29                 // String /
        24: invokevirtual #27                 // Method java/lang/StringBuilder.append:(Ljava/lang/String;)Ljava/lang/StringBuilder;
        27: aload_0
        28: getfield      #9                  // Field owner:Lorg/kohsuke/github/GHRepository;
        31: invokevirtual #30                 // Method org/kohsuke/github/GHRepository.getName:()Ljava/lang/String;
        34: invokevirtual #27                 // Method java/lang/StringBuilder.append:(Ljava/lang/String;)Ljava/lang/StringBuilder;
        37: ldc           #31                 // String /releases/assets/
        39: invokevirtual #27                 // Method java/lang/StringBuilder.append:(Ljava/lang/String;)Ljava/lang/StringBuilder;
        42: aload_0
        43: invokevirtual #32                 // Method getId:()J
        46: invokevirtual #33                 // Method java/lang/StringBuilder.append:(J)Ljava/lang/StringBuilder;
        49: invokevirtual #34                 // Method java/lang/StringBuilder.toString:()Ljava/lang/String;
        52: areturn
      LineNumberTable:
        line 145: 0
      LocalVariableTable:
        Start  Length  Slot  Name   Signature
            0      53     0  this   Lorg/kohsuke/github/GHAsset;

  org.kohsuke.github.GHAsset wrap(org.kohsuke.github.GHRelease);
    descriptor: (Lorg/kohsuke/github/GHRelease;)Lorg/kohsuke/github/GHAsset;
    flags: (0x0000)
    Code:
      stack=2, locals=2, args_size=2
         0: aload_0
         1: aload_1
         2: invokevirtual #35                 // Method org/kohsuke/github/GHRelease.getOwner:()Lorg/kohsuke/github/GHRepository;
         5: putfield      #9                  // Field owner:Lorg/kohsuke/github/GHRepository;
         8: aload_0
         9: areturn
      LineNumberTable:
        line 149: 0
        line 150: 8
      LocalVariableTable:
        Start  Length  Slot  Name   Signature
            0      10     0  this   Lorg/kohsuke/github/GHAsset;
            0      10     1 release   Lorg/kohsuke/github/GHRelease;

  public static org.kohsuke.github.GHAsset[] wrap(org.kohsuke.github.GHAsset[], org.kohsuke.github.GHRelease);
    descriptor: ([Lorg/kohsuke/github/GHAsset;Lorg/kohsuke/github/GHRelease;)[Lorg/kohsuke/github/GHAsset;
    flags: (0x0009) ACC_PUBLIC, ACC_STATIC
    Code:
      stack=2, locals=6, args_size=2
         0: aload_0
         1: astore_2
         2: aload_2
         3: arraylength
         4: istore_3
         5: iconst_0
         6: istore        4
         8: iload         4
        10: iload_3
        11: if_icmpge     33
        14: aload_2
        15: iload         4
        17: aaload
        18: astore        5
        20: aload         5
        22: aload_1
        23: invokevirtual #36                 // Method wrap:(Lorg/kohsuke/github/GHRelease;)Lorg/kohsuke/github/GHAsset;
        26: pop
        27: iinc          4, 1
        30: goto          8
        33: aload_0
        34: areturn
      LineNumberTable:
        line 163: 0
        line 164: 20
        line 163: 27
        line 166: 33
      LocalVariableTable:
        Start  Length  Slot  Name   Signature
           20       7     5   aTo   Lorg/kohsuke/github/GHAsset;
            0      35     0 assets   [Lorg/kohsuke/github/GHAsset;
            0      35     1 release   Lorg/kohsuke/github/GHRelease;
      StackMapTable: number_of_entries = 2
        frame_type = 254 /* append */
          offset_delta = 8
          locals = [ class "[Lorg/kohsuke/github/GHAsset;", int, int ]
        frame_type = 248 /* chop */
          offset_delta = 24
}
SourceFile: "GHAsset.java"
InnerClasses:
  static #147= #146 of #163;              // Builder=class org/kohsuke/github/GitHubRequest$Builder of class org/kohsuke/github/GitHubRequest
