Classfile /Users/mw/Projects/slang-braindump/.jar/jar11/assemble/slang-braindump/assemble/content/org/kohsuke/github/GHBlobBuilder.class
  Last modified May 29, 2022; size 2327 bytes
  SHA-256 checksum 7dbbf83c417da3ad4a4dc856761a0f32d051e2bf60172908c22f05372adbcc18
  Compiled from "GHBlobBuilder.java"
public class org.kohsuke.github.GHBlobBuilder
  minor version: 0
  major version: 52
  flags: (0x0021) ACC_PUBLIC, ACC_SUPER
  this_class: #26                         // org/kohsuke/github/GHBlobBuilder
  super_class: #14                        // java/lang/Object
  interfaces: 0, fields: 2, methods: 5, attributes: 2
Constant pool:
    #1 = Methodref          #14.#54       // java/lang/Object."<init>":()V
    #2 = Fieldref           #26.#55       // org/kohsuke/github/GHBlobBuilder.repo:Lorg/kohsuke/github/GHRepository;
    #3 = Methodref          #56.#57       // org/kohsuke/github/GHRepository.root:()Lorg/kohsuke/github/GitHub;
    #4 = Methodref          #58.#59       // org/kohsuke/github/GitHub.createRequest:()Lorg/kohsuke/github/Requester;
    #5 = Fieldref           #26.#60       // org/kohsuke/github/GHBlobBuilder.req:Lorg/kohsuke/github/Requester;
    #6 = String             #40           // content
    #7 = Methodref          #20.#61       // org/kohsuke/github/Requester.with:(Ljava/lang/String;Ljava/lang/String;)Lorg/kohsuke/github/GitHubRequest$Builder;
    #8 = String             #62           // encoding
    #9 = String             #63           // utf-8
   #10 = Methodref          #64.#65       // java/util/Base64.getEncoder:()Ljava/util/Base64$Encoder;
   #11 = Methodref          #66.#67       // java/util/Base64$Encoder.encodeToString:([B)Ljava/lang/String;
   #12 = String             #68           // base64
   #13 = String             #69           // /repos/%s/%s/git/blobs
   #14 = Class              #70           // java/lang/Object
   #15 = Methodref          #56.#71       // org/kohsuke/github/GHRepository.getOwnerName:()Ljava/lang/String;
   #16 = Methodref          #56.#72       // org/kohsuke/github/GHRepository.getName:()Ljava/lang/String;
   #17 = Methodref          #22.#73       // java/lang/String.format:(Ljava/lang/String;[Ljava/lang/Object;)Ljava/lang/String;
   #18 = String             #74           // POST
   #19 = Methodref          #20.#75       // org/kohsuke/github/Requester.method:(Ljava/lang/String;)Lorg/kohsuke/github/GitHubRequest$Builder;
   #20 = Class              #76           // org/kohsuke/github/Requester
   #21 = Methodref          #26.#77       // org/kohsuke/github/GHBlobBuilder.getApiTail:()Ljava/lang/String;
   #22 = Class              #78           // java/lang/String
   #23 = Methodref          #20.#79       // org/kohsuke/github/Requester.withUrlPath:(Ljava/lang/String;[Ljava/lang/String;)Lorg/kohsuke/github/GitHubRequest$Builder;
   #24 = Class              #80           // org/kohsuke/github/GHBlob
   #25 = Methodref          #20.#81       // org/kohsuke/github/Requester.fetch:(Ljava/lang/Class;)Ljava/lang/Object;
   #26 = Class              #82           // org/kohsuke/github/GHBlobBuilder
   #27 = Utf8               repo
   #28 = Utf8               Lorg/kohsuke/github/GHRepository;
   #29 = Utf8               req
   #30 = Utf8               Lorg/kohsuke/github/Requester;
   #31 = Utf8               <init>
   #32 = Utf8               (Lorg/kohsuke/github/GHRepository;)V
   #33 = Utf8               Code
   #34 = Utf8               LineNumberTable
   #35 = Utf8               LocalVariableTable
   #36 = Utf8               this
   #37 = Utf8               Lorg/kohsuke/github/GHBlobBuilder;
   #38 = Utf8               textContent
   #39 = Utf8               (Ljava/lang/String;)Lorg/kohsuke/github/GHBlobBuilder;
   #40 = Utf8               content
   #41 = Utf8               Ljava/lang/String;
   #42 = Utf8               binaryContent
   #43 = Utf8               ([B)Lorg/kohsuke/github/GHBlobBuilder;
   #44 = Utf8               [B
   #45 = Utf8               base64Content
   #46 = Utf8               getApiTail
   #47 = Utf8               ()Ljava/lang/String;
   #48 = Utf8               create
   #49 = Utf8               ()Lorg/kohsuke/github/GHBlob;
   #50 = Utf8               Exceptions
   #51 = Class              #83           // java/io/IOException
   #52 = Utf8               SourceFile
   #53 = Utf8               GHBlobBuilder.java
   #54 = NameAndType        #31:#84       // "<init>":()V
   #55 = NameAndType        #27:#28       // repo:Lorg/kohsuke/github/GHRepository;
   #56 = Class              #85           // org/kohsuke/github/GHRepository
   #57 = NameAndType        #86:#87       // root:()Lorg/kohsuke/github/GitHub;
   #58 = Class              #88           // org/kohsuke/github/GitHub
   #59 = NameAndType        #89:#90       // createRequest:()Lorg/kohsuke/github/Requester;
   #60 = NameAndType        #29:#30       // req:Lorg/kohsuke/github/Requester;
   #61 = NameAndType        #91:#95       // with:(Ljava/lang/String;Ljava/lang/String;)Lorg/kohsuke/github/GitHubRequest$Builder;
   #62 = Utf8               encoding
   #63 = Utf8               utf-8
   #64 = Class              #96           // java/util/Base64
   #65 = NameAndType        #97:#99       // getEncoder:()Ljava/util/Base64$Encoder;
   #66 = Class              #100          // java/util/Base64$Encoder
   #67 = NameAndType        #101:#102     // encodeToString:([B)Ljava/lang/String;
   #68 = Utf8               base64
   #69 = Utf8               /repos/%s/%s/git/blobs
   #70 = Utf8               java/lang/Object
   #71 = NameAndType        #103:#47      // getOwnerName:()Ljava/lang/String;
   #72 = NameAndType        #104:#47      // getName:()Ljava/lang/String;
   #73 = NameAndType        #105:#106     // format:(Ljava/lang/String;[Ljava/lang/Object;)Ljava/lang/String;
   #74 = Utf8               POST
   #75 = NameAndType        #107:#108     // method:(Ljava/lang/String;)Lorg/kohsuke/github/GitHubRequest$Builder;
   #76 = Utf8               org/kohsuke/github/Requester
   #77 = NameAndType        #46:#47       // getApiTail:()Ljava/lang/String;
   #78 = Utf8               java/lang/String
   #79 = NameAndType        #109:#110     // withUrlPath:(Ljava/lang/String;[Ljava/lang/String;)Lorg/kohsuke/github/GitHubRequest$Builder;
   #80 = Utf8               org/kohsuke/github/GHBlob
   #81 = NameAndType        #111:#112     // fetch:(Ljava/lang/Class;)Ljava/lang/Object;
   #82 = Utf8               org/kohsuke/github/GHBlobBuilder
   #83 = Utf8               java/io/IOException
   #84 = Utf8               ()V
   #85 = Utf8               org/kohsuke/github/GHRepository
   #86 = Utf8               root
   #87 = Utf8               ()Lorg/kohsuke/github/GitHub;
   #88 = Utf8               org/kohsuke/github/GitHub
   #89 = Utf8               createRequest
   #90 = Utf8               ()Lorg/kohsuke/github/Requester;
   #91 = Utf8               with
   #92 = Class              #114          // org/kohsuke/github/GitHubRequest$Builder
   #93 = Utf8               Builder
   #94 = Utf8               InnerClasses
   #95 = Utf8               (Ljava/lang/String;Ljava/lang/String;)Lorg/kohsuke/github/GitHubRequest$Builder;
   #96 = Utf8               java/util/Base64
   #97 = Utf8               getEncoder
   #98 = Utf8               Encoder
   #99 = Utf8               ()Ljava/util/Base64$Encoder;
  #100 = Utf8               java/util/Base64$Encoder
  #101 = Utf8               encodeToString
  #102 = Utf8               ([B)Ljava/lang/String;
  #103 = Utf8               getOwnerName
  #104 = Utf8               getName
  #105 = Utf8               format
  #106 = Utf8               (Ljava/lang/String;[Ljava/lang/Object;)Ljava/lang/String;
  #107 = Utf8               method
  #108 = Utf8               (Ljava/lang/String;)Lorg/kohsuke/github/GitHubRequest$Builder;
  #109 = Utf8               withUrlPath
  #110 = Utf8               (Ljava/lang/String;[Ljava/lang/String;)Lorg/kohsuke/github/GitHubRequest$Builder;
  #111 = Utf8               fetch
  #112 = Utf8               (Ljava/lang/Class;)Ljava/lang/Object;
  #113 = Class              #115          // org/kohsuke/github/GitHubRequest
  #114 = Utf8               org/kohsuke/github/GitHubRequest$Builder
  #115 = Utf8               org/kohsuke/github/GitHubRequest
{
  private final org.kohsuke.github.GHRepository repo;
    descriptor: Lorg/kohsuke/github/GHRepository;
    flags: (0x0012) ACC_PRIVATE, ACC_FINAL

  private final org.kohsuke.github.Requester req;
    descriptor: Lorg/kohsuke/github/Requester;
    flags: (0x0012) ACC_PRIVATE, ACC_FINAL

  org.kohsuke.github.GHBlobBuilder(org.kohsuke.github.GHRepository);
    descriptor: (Lorg/kohsuke/github/GHRepository;)V
    flags: (0x0000)
    Code:
      stack=2, locals=2, args_size=2
         0: aload_0
         1: invokespecial #1                  // Method java/lang/Object."<init>":()V
         4: aload_0
         5: aload_1
         6: putfield      #2                  // Field repo:Lorg/kohsuke/github/GHRepository;
         9: aload_0
        10: aload_1
        11: invokevirtual #3                  // Method org/kohsuke/github/GHRepository.root:()Lorg/kohsuke/github/GitHub;
        14: invokevirtual #4                  // Method org/kohsuke/github/GitHub.createRequest:()Lorg/kohsuke/github/Requester;
        17: putfield      #5                  // Field req:Lorg/kohsuke/github/Requester;
        20: return
      LineNumberTable:
        line 13: 0
        line 14: 4
        line 15: 9
        line 16: 20
      LocalVariableTable:
        Start  Length  Slot  Name   Signature
            0      21     0  this   Lorg/kohsuke/github/GHBlobBuilder;
            0      21     1  repo   Lorg/kohsuke/github/GHRepository;

  public org.kohsuke.github.GHBlobBuilder textContent(java.lang.String);
    descriptor: (Ljava/lang/String;)Lorg/kohsuke/github/GHBlobBuilder;
    flags: (0x0001) ACC_PUBLIC
    Code:
      stack=3, locals=2, args_size=2
         0: aload_0
         1: getfield      #5                  // Field req:Lorg/kohsuke/github/Requester;
         4: ldc           #6                  // String content
         6: aload_1
         7: invokevirtual #7                  // Method org/kohsuke/github/Requester.with:(Ljava/lang/String;Ljava/lang/String;)Lorg/kohsuke/github/GitHubRequest$Builder;
        10: pop
        11: aload_0
        12: getfield      #5                  // Field req:Lorg/kohsuke/github/Requester;
        15: ldc           #8                  // String encoding
        17: ldc           #9                  // String utf-8
        19: invokevirtual #7                  // Method org/kohsuke/github/Requester.with:(Ljava/lang/String;Ljava/lang/String;)Lorg/kohsuke/github/GitHubRequest$Builder;
        22: pop
        23: aload_0
        24: areturn
      LineNumberTable:
        line 26: 0
        line 27: 11
        line 28: 23
      LocalVariableTable:
        Start  Length  Slot  Name   Signature
            0      25     0  this   Lorg/kohsuke/github/GHBlobBuilder;
            0      25     1 content   Ljava/lang/String;

  public org.kohsuke.github.GHBlobBuilder binaryContent(byte[]);
    descriptor: ([B)Lorg/kohsuke/github/GHBlobBuilder;
    flags: (0x0001) ACC_PUBLIC
    Code:
      stack=3, locals=3, args_size=2
         0: invokestatic  #10                 // Method java/util/Base64.getEncoder:()Ljava/util/Base64$Encoder;
         3: aload_1
         4: invokevirtual #11                 // Method java/util/Base64$Encoder.encodeToString:([B)Ljava/lang/String;
         7: astore_2
         8: aload_0
         9: getfield      #5                  // Field req:Lorg/kohsuke/github/Requester;
        12: ldc           #6                  // String content
        14: aload_2
        15: invokevirtual #7                  // Method org/kohsuke/github/Requester.with:(Ljava/lang/String;Ljava/lang/String;)Lorg/kohsuke/github/GitHubRequest$Builder;
        18: pop
        19: aload_0
        20: getfield      #5                  // Field req:Lorg/kohsuke/github/Requester;
        23: ldc           #8                  // String encoding
        25: ldc           #12                 // String base64
        27: invokevirtual #7                  // Method org/kohsuke/github/Requester.with:(Ljava/lang/String;Ljava/lang/String;)Lorg/kohsuke/github/GitHubRequest$Builder;
        30: pop
        31: aload_0
        32: areturn
      LineNumberTable:
        line 39: 0
        line 40: 8
        line 41: 19
        line 42: 31
      LocalVariableTable:
        Start  Length  Slot  Name   Signature
            0      33     0  this   Lorg/kohsuke/github/GHBlobBuilder;
            0      33     1 content   [B
            8      25     2 base64Content   Ljava/lang/String;

  private java.lang.String getApiTail();
    descriptor: ()Ljava/lang/String;
    flags: (0x0002) ACC_PRIVATE
    Code:
      stack=5, locals=1, args_size=1
         0: ldc           #13                 // String /repos/%s/%s/git/blobs
         2: iconst_2
         3: anewarray     #14                 // class java/lang/Object
         6: dup
         7: iconst_0
         8: aload_0
         9: getfield      #2                  // Field repo:Lorg/kohsuke/github/GHRepository;
        12: invokevirtual #15                 // Method org/kohsuke/github/GHRepository.getOwnerName:()Ljava/lang/String;
        15: aastore
        16: dup
        17: iconst_1
        18: aload_0
        19: getfield      #2                  // Field repo:Lorg/kohsuke/github/GHRepository;
        22: invokevirtual #16                 // Method org/kohsuke/github/GHRepository.getName:()Ljava/lang/String;
        25: aastore
        26: invokestatic  #17                 // Method java/lang/String.format:(Ljava/lang/String;[Ljava/lang/Object;)Ljava/lang/String;
        29: areturn
      LineNumberTable:
        line 46: 0
      LocalVariableTable:
        Start  Length  Slot  Name   Signature
            0      30     0  this   Lorg/kohsuke/github/GHBlobBuilder;

  public org.kohsuke.github.GHBlob create() throws java.io.IOException;
    descriptor: ()Lorg/kohsuke/github/GHBlob;
    flags: (0x0001) ACC_PUBLIC
    Code:
      stack=3, locals=1, args_size=1
         0: aload_0
         1: getfield      #5                  // Field req:Lorg/kohsuke/github/Requester;
         4: ldc           #18                 // String POST
         6: invokevirtual #19                 // Method org/kohsuke/github/Requester.method:(Ljava/lang/String;)Lorg/kohsuke/github/GitHubRequest$Builder;
         9: checkcast     #20                 // class org/kohsuke/github/Requester
        12: aload_0
        13: invokespecial #21                 // Method getApiTail:()Ljava/lang/String;
        16: iconst_0
        17: anewarray     #22                 // class java/lang/String
        20: invokevirtual #23                 // Method org/kohsuke/github/Requester.withUrlPath:(Ljava/lang/String;[Ljava/lang/String;)Lorg/kohsuke/github/GitHubRequest$Builder;
        23: checkcast     #20                 // class org/kohsuke/github/Requester
        26: ldc           #24                 // class org/kohsuke/github/GHBlob
        28: invokevirtual #25                 // Method org/kohsuke/github/Requester.fetch:(Ljava/lang/Class;)Ljava/lang/Object;
        31: checkcast     #24                 // class org/kohsuke/github/GHBlob
        34: areturn
      LineNumberTable:
        line 57: 0
      LocalVariableTable:
        Start  Length  Slot  Name   Signature
            0      35     0  this   Lorg/kohsuke/github/GHBlobBuilder;
    Exceptions:
      throws java.io.IOException
}
SourceFile: "GHBlobBuilder.java"
InnerClasses:
  static #93= #92 of #113;                // Builder=class org/kohsuke/github/GitHubRequest$Builder of class org/kohsuke/github/GitHubRequest
  public static #98= #66 of #64;          // Encoder=class java/util/Base64$Encoder of class java/util/Base64
