Classfile /Users/mw/Projects/slang-braindump/.jar/jar11/assemble/slang-braindump/assemble/content/org/kohsuke/github/GHBranchProtection$RequiredReviews.class
  Last modified May 29, 2022; size 1490 bytes
  SHA-256 checksum 96199f45cb50c7b818cd02f34ec8d19af18020f97cb600aec0e1106e6ce81b3c
  Compiled from "GHBranchProtection.java"
public class org.kohsuke.github.GHBranchProtection$RequiredReviews
  minor version: 0
  major version: 52
  flags: (0x0021) ACC_PUBLIC, ACC_SUPER
  this_class: #7                          // org/kohsuke/github/GHBranchProtection$RequiredReviews
  super_class: #8                         // java/lang/Object
  interfaces: 0, fields: 5, methods: 6, attributes: 2
Constant pool:
   #1 = Methodref          #8.#45         // java/lang/Object."<init>":()V
   #2 = Fieldref           #7.#46         // org/kohsuke/github/GHBranchProtection$RequiredReviews.dismissalRestriction:Lorg/kohsuke/github/GHBranchProtection$Restrictions;
   #3 = Fieldref           #7.#47         // org/kohsuke/github/GHBranchProtection$RequiredReviews.url:Ljava/lang/String;
   #4 = Fieldref           #7.#48         // org/kohsuke/github/GHBranchProtection$RequiredReviews.dismissStaleReviews:Z
   #5 = Fieldref           #7.#49         // org/kohsuke/github/GHBranchProtection$RequiredReviews.requireCodeOwnerReviews:Z
   #6 = Fieldref           #7.#50         // org/kohsuke/github/GHBranchProtection$RequiredReviews.requiredReviewers:I
   #7 = Class              #52            // org/kohsuke/github/GHBranchProtection$RequiredReviews
   #8 = Class              #53            // java/lang/Object
   #9 = Utf8               dismissalRestriction
  #10 = Class              #54            // org/kohsuke/github/GHBranchProtection$Restrictions
  #11 = Utf8               Restrictions
  #12 = Utf8               InnerClasses
  #13 = Utf8               Lorg/kohsuke/github/GHBranchProtection$Restrictions;
  #14 = Utf8               RuntimeVisibleAnnotations
  #15 = Utf8               Lcom/fasterxml/jackson/annotation/JsonProperty;
  #16 = Utf8               value
  #17 = Utf8               dismissal_restrictions
  #18 = Utf8               dismissStaleReviews
  #19 = Utf8               Z
  #20 = Utf8               requireCodeOwnerReviews
  #21 = Utf8               requiredReviewers
  #22 = Utf8               I
  #23 = Utf8               required_approving_review_count
  #24 = Utf8               url
  #25 = Utf8               Ljava/lang/String;
  #26 = Utf8               <init>
  #27 = Utf8               ()V
  #28 = Utf8               Code
  #29 = Utf8               LineNumberTable
  #30 = Utf8               LocalVariableTable
  #31 = Utf8               this
  #32 = Utf8               RequiredReviews
  #33 = Utf8               Lorg/kohsuke/github/GHBranchProtection$RequiredReviews;
  #34 = Utf8               getDismissalRestrictions
  #35 = Utf8               ()Lorg/kohsuke/github/GHBranchProtection$Restrictions;
  #36 = Utf8               getUrl
  #37 = Utf8               ()Ljava/lang/String;
  #38 = Utf8               isDismissStaleReviews
  #39 = Utf8               ()Z
  #40 = Utf8               isRequireCodeOwnerReviews
  #41 = Utf8               getRequiredReviewers
  #42 = Utf8               ()I
  #43 = Utf8               SourceFile
  #44 = Utf8               GHBranchProtection.java
  #45 = NameAndType        #26:#27        // "<init>":()V
  #46 = NameAndType        #9:#13         // dismissalRestriction:Lorg/kohsuke/github/GHBranchProtection$Restrictions;
  #47 = NameAndType        #24:#25        // url:Ljava/lang/String;
  #48 = NameAndType        #18:#19        // dismissStaleReviews:Z
  #49 = NameAndType        #20:#19        // requireCodeOwnerReviews:Z
  #50 = NameAndType        #21:#22        // requiredReviewers:I
  #51 = Class              #55            // org/kohsuke/github/GHBranchProtection
  #52 = Utf8               org/kohsuke/github/GHBranchProtection$RequiredReviews
  #53 = Utf8               java/lang/Object
  #54 = Utf8               org/kohsuke/github/GHBranchProtection$Restrictions
  #55 = Utf8               org/kohsuke/github/GHBranchProtection
{
  private org.kohsuke.github.GHBranchProtection$Restrictions dismissalRestriction;
    descriptor: Lorg/kohsuke/github/GHBranchProtection$Restrictions;
    flags: (0x0002) ACC_PRIVATE
    RuntimeVisibleAnnotations:
      0: #15(#16=s#17)
        com.fasterxml.jackson.annotation.JsonProperty(
          value="dismissal_restrictions"
        )

  private boolean dismissStaleReviews;
    descriptor: Z
    flags: (0x0002) ACC_PRIVATE

  private boolean requireCodeOwnerReviews;
    descriptor: Z
    flags: (0x0002) ACC_PRIVATE

  private int requiredReviewers;
    descriptor: I
    flags: (0x0002) ACC_PRIVATE
    RuntimeVisibleAnnotations:
      0: #15(#16=s#23)
        com.fasterxml.jackson.annotation.JsonProperty(
          value="required_approving_review_count"
        )

  private java.lang.String url;
    descriptor: Ljava/lang/String;
    flags: (0x0002) ACC_PRIVATE
    RuntimeVisibleAnnotations:
      0: #15()
        com.fasterxml.jackson.annotation.JsonProperty

  public org.kohsuke.github.GHBranchProtection$RequiredReviews();
    descriptor: ()V
    flags: (0x0001) ACC_PUBLIC
    Code:
      stack=1, locals=1, args_size=1
         0: aload_0
         1: invokespecial #1                  // Method java/lang/Object."<init>":()V
         4: return
      LineNumberTable:
        line 154: 0
      LocalVariableTable:
        Start  Length  Slot  Name   Signature
            0       5     0  this   Lorg/kohsuke/github/GHBranchProtection$RequiredReviews;

  public org.kohsuke.github.GHBranchProtection$Restrictions getDismissalRestrictions();
    descriptor: ()Lorg/kohsuke/github/GHBranchProtection$Restrictions;
    flags: (0x0001) ACC_PUBLIC
    Code:
      stack=1, locals=1, args_size=1
         0: aload_0
         1: getfield      #2                  // Field dismissalRestriction:Lorg/kohsuke/github/GHBranchProtection$Restrictions;
         4: areturn
      LineNumberTable:
        line 174: 0
      LocalVariableTable:
        Start  Length  Slot  Name   Signature
            0       5     0  this   Lorg/kohsuke/github/GHBranchProtection$RequiredReviews;

  public java.lang.String getUrl();
    descriptor: ()Ljava/lang/String;
    flags: (0x0001) ACC_PUBLIC
    Code:
      stack=1, locals=1, args_size=1
         0: aload_0
         1: getfield      #3                  // Field url:Ljava/lang/String;
         4: areturn
      LineNumberTable:
        line 183: 0
      LocalVariableTable:
        Start  Length  Slot  Name   Signature
            0       5     0  this   Lorg/kohsuke/github/GHBranchProtection$RequiredReviews;

  public boolean isDismissStaleReviews();
    descriptor: ()Z
    flags: (0x0001) ACC_PUBLIC
    Code:
      stack=1, locals=1, args_size=1
         0: aload_0
         1: getfield      #4                  // Field dismissStaleReviews:Z
         4: ireturn
      LineNumberTable:
        line 192: 0
      LocalVariableTable:
        Start  Length  Slot  Name   Signature
            0       5     0  this   Lorg/kohsuke/github/GHBranchProtection$RequiredReviews;

  public boolean isRequireCodeOwnerReviews();
    descriptor: ()Z
    flags: (0x0001) ACC_PUBLIC
    Code:
      stack=1, locals=1, args_size=1
         0: aload_0
         1: getfield      #5                  // Field requireCodeOwnerReviews:Z
         4: ireturn
      LineNumberTable:
        line 201: 0
      LocalVariableTable:
        Start  Length  Slot  Name   Signature
            0       5     0  this   Lorg/kohsuke/github/GHBranchProtection$RequiredReviews;

  public int getRequiredReviewers();
    descriptor: ()I
    flags: (0x0001) ACC_PUBLIC
    Code:
      stack=1, locals=1, args_size=1
         0: aload_0
         1: getfield      #6                  // Field requiredReviewers:I
         4: ireturn
      LineNumberTable:
        line 210: 0
      LocalVariableTable:
        Start  Length  Slot  Name   Signature
            0       5     0  this   Lorg/kohsuke/github/GHBranchProtection$RequiredReviews;
}
SourceFile: "GHBranchProtection.java"
InnerClasses:
  public static #11= #10 of #51;          // Restrictions=class org/kohsuke/github/GHBranchProtection$Restrictions of class org/kohsuke/github/GHBranchProtection
  public static #32= #7 of #51;           // RequiredReviews=class org/kohsuke/github/GHBranchProtection$RequiredReviews of class org/kohsuke/github/GHBranchProtection
