Classfile /Users/mw/Projects/slang-braindump/.jar/jar11/assemble/slang-braindump/assemble/content/org/kohsuke/github/GHBranch.class
  Last modified May 29, 2022; size 6327 bytes
  SHA-256 checksum f8023d63570006be6e17f7f0a2fb3f84f5ba18cd3ea169cc58123dd336c1b49b
  Compiled from "GHBranch.java"
public class org.kohsuke.github.GHBranch extends org.kohsuke.github.GitHubInteractiveObject
  minor version: 0
  major version: 52
  flags: (0x0021) ACC_PUBLIC, ACC_SUPER
  this_class: #55                         // org/kohsuke/github/GHBranch
  super_class: #56                        // org/kohsuke/github/GitHubInteractiveObject
  interfaces: 0, fields: 5, methods: 16, attributes: 3
Constant pool:
    #1 = Methodref          #56.#149      // org/kohsuke/github/GitHubInteractiveObject."<init>":()V
    #2 = Methodref          #150.#151     // java/util/Objects.requireNonNull:(Ljava/lang/Object;)Ljava/lang/Object;
    #3 = Fieldref           #55.#152      // org/kohsuke/github/GHBranch.name:Ljava/lang/String;
    #4 = Fieldref           #55.#153      // org/kohsuke/github/GHBranch.owner:Lorg/kohsuke/github/GHRepository;
    #5 = Fieldref           #55.#154      // org/kohsuke/github/GHBranch.protection:Z
    #6 = Fieldref           #55.#155      // org/kohsuke/github/GHBranch.protection_url:Ljava/lang/String;
    #7 = Methodref          #156.#157     // org/kohsuke/github/GitHubClient.parseURL:(Ljava/lang/String;)Ljava/net/URL;
    #8 = Methodref          #55.#158      // org/kohsuke/github/GHBranch.root:()Lorg/kohsuke/github/GitHub;
    #9 = Methodref          #159.#160     // org/kohsuke/github/GitHub.createRequest:()Lorg/kohsuke/github/Requester;
   #10 = Fieldref           #161.#162     // org/kohsuke/github/internal/Previews.LUKE_CAGE:Lorg/kohsuke/github/internal/Previews;
   #11 = Methodref          #12.#163      // org/kohsuke/github/Requester.withPreview:(Lorg/kohsuke/github/internal/Previews;)Lorg/kohsuke/github/GitHubRequest$Builder;
   #12 = Class              #164          // org/kohsuke/github/Requester
   #13 = Methodref          #12.#165      // org/kohsuke/github/Requester.setRawUrlPath:(Ljava/lang/String;)Lorg/kohsuke/github/GitHubRequest$Builder;
   #14 = Class              #166          // org/kohsuke/github/GHBranchProtection
   #15 = Methodref          #12.#167      // org/kohsuke/github/Requester.fetch:(Ljava/lang/Class;)Ljava/lang/Object;
   #16 = Fieldref           #55.#168      // org/kohsuke/github/GHBranch.commit:Lorg/kohsuke/github/GHBranch$Commit;
   #17 = Fieldref           #59.#169      // org/kohsuke/github/GHBranch$Commit.sha:Ljava/lang/String;
   #18 = String             #170          // DELETE
   #19 = Methodref          #12.#171      // org/kohsuke/github/Requester.method:(Ljava/lang/String;)Lorg/kohsuke/github/GitHubRequest$Builder;
   #20 = Methodref          #12.#172      // org/kohsuke/github/Requester.send:()V
   #21 = Class              #173          // org/kohsuke/github/GHBranchProtectionBuilder
   #22 = Methodref          #21.#174      // org/kohsuke/github/GHBranchProtectionBuilder."<init>":(Lorg/kohsuke/github/GHBranch;)V
   #23 = Fieldref           #57.#175      // org/kohsuke/github/GHBranch$1.$SwitchMap$org$kohsuke$github$EnforcementLevel:[I
   #24 = Methodref          #119.#176     // org/kohsuke/github/EnforcementLevel.ordinal:()I
   #25 = Methodref          #55.#177      // org/kohsuke/github/GHBranch.disableProtection:()V
   #26 = Methodref          #55.#178      // org/kohsuke/github/GHBranch.enableProtection:()Lorg/kohsuke/github/GHBranchProtectionBuilder;
   #27 = Methodref          #21.#179      // org/kohsuke/github/GHBranchProtectionBuilder.addRequiredChecks:(Ljava/util/Collection;)Lorg/kohsuke/github/GHBranchProtectionBuilder;
   #28 = Fieldref           #119.#180     // org/kohsuke/github/EnforcementLevel.EVERYONE:Lorg/kohsuke/github/EnforcementLevel;
   #29 = Methodref          #21.#181      // org/kohsuke/github/GHBranchProtectionBuilder.includeAdmins:(Z)Lorg/kohsuke/github/GHBranchProtectionBuilder;
   #30 = Methodref          #21.#182      // org/kohsuke/github/GHBranchProtectionBuilder.enable:()Lorg/kohsuke/github/GHBranchProtection;
   #31 = Methodref          #55.#183      // org/kohsuke/github/GHBranch.getName:()Ljava/lang/String;
   #32 = Methodref          #55.#184      // org/kohsuke/github/GHBranch.merge:(Ljava/lang/String;Ljava/lang/String;)Lorg/kohsuke/github/GHCommit;
   #33 = String             #185          // merges
   #34 = Methodref          #186.#187     // org/kohsuke/github/GHRepository.getApiTailUrl:(Ljava/lang/String;)Ljava/lang/String;
   #35 = Class              #188          // java/lang/String
   #36 = Methodref          #12.#189      // org/kohsuke/github/Requester.withUrlPath:(Ljava/lang/String;[Ljava/lang/String;)Lorg/kohsuke/github/GitHubRequest$Builder;
   #37 = String             #190          // POST
   #38 = String             #191          // commit_message
   #39 = Methodref          #12.#192      // org/kohsuke/github/Requester.with:(Ljava/lang/String;Ljava/lang/String;)Lorg/kohsuke/github/GitHubRequest$Builder;
   #40 = String             #193          // base
   #41 = String             #131          // head
   #42 = Class              #194          // org/kohsuke/github/GHCommit
   #43 = Methodref          #42.#195      // org/kohsuke/github/GHCommit.wrapUp:(Lorg/kohsuke/github/GHRepository;)Lorg/kohsuke/github/GHCommit;
   #44 = Class              #196          // java/lang/StringBuilder
   #45 = Methodref          #44.#149      // java/lang/StringBuilder."<init>":()V
   #46 = String             #197          // /branches/
   #47 = Methodref          #44.#198      // java/lang/StringBuilder.append:(Ljava/lang/String;)Ljava/lang/StringBuilder;
   #48 = Methodref          #44.#199      // java/lang/StringBuilder.toString:()Ljava/lang/String;
   #49 = Methodref          #186.#200     // org/kohsuke/github/GHRepository.getUrl:()Ljava/net/URL;
   #50 = Methodref          #201.#199     // java/net/URL.toString:()Ljava/lang/String;
   #51 = String             #202          // unknown
   #52 = String             #203          // Branch:
   #53 = String             #204          //  in
   #54 = Methodref          #56.#205      // org/kohsuke/github/GitHubInteractiveObject.getRoot:()Lorg/kohsuke/github/GitHub;
   #55 = Class              #206          // org/kohsuke/github/GHBranch
   #56 = Class              #207          // org/kohsuke/github/GitHubInteractiveObject
   #57 = Class              #208          // org/kohsuke/github/GHBranch$1
   #58 = Utf8               InnerClasses
   #59 = Class              #209          // org/kohsuke/github/GHBranch$Commit
   #60 = Utf8               Commit
   #61 = Utf8               owner
   #62 = Utf8               Lorg/kohsuke/github/GHRepository;
   #63 = Utf8               name
   #64 = Utf8               Ljava/lang/String;
   #65 = Utf8               commit
   #66 = Utf8               Lorg/kohsuke/github/GHBranch$Commit;
   #67 = Utf8               protection
   #68 = Utf8               Z
   #69 = Utf8               RuntimeVisibleAnnotations
   #70 = Utf8               Lcom/fasterxml/jackson/annotation/JsonProperty;
   #71 = Utf8               value
   #72 = Utf8               protected
   #73 = Utf8               protection_url
   #74 = Utf8               <init>
   #75 = Utf8               (Ljava/lang/String;)V
   #76 = Utf8               Code
   #77 = Utf8               LineNumberTable
   #78 = Utf8               LocalVariableTable
   #79 = Utf8               this
   #80 = Utf8               Lorg/kohsuke/github/GHBranch;
   #81 = Utf8               Exceptions
   #82 = Class              #210          // java/lang/Exception
   #83 = Utf8               Lcom/fasterxml/jackson/annotation/JsonCreator;
   #84 = Utf8               RuntimeVisibleParameterAnnotations
   #85 = Utf8               required
   #86 = Integer            1
   #87 = Utf8               getOwner
   #88 = Utf8               ()Lorg/kohsuke/github/GHRepository;
   #89 = Utf8               RuntimeInvisibleAnnotations
   #90 = Utf8               Ledu/umd/cs/findbugs/annotations/SuppressFBWarnings;
   #91 = Utf8               EI_EXPOSE_REP
   #92 = Utf8               justification
   #93 = Utf8               Expected behavior
   #94 = Utf8               getName
   #95 = Utf8               ()Ljava/lang/String;
   #96 = Utf8               isProtected
   #97 = Utf8               ()Z
   #98 = Utf8               Lorg/kohsuke/github/Preview;
   #99 = Utf8               Lorg/kohsuke/github/internal/Previews;
  #100 = Utf8               LUKE_CAGE
  #101 = Utf8               getProtectionUrl
  #102 = Utf8               ()Ljava/net/URL;
  #103 = Utf8               getProtection
  #104 = Utf8               ()Lorg/kohsuke/github/GHBranchProtection;
  #105 = Class              #211          // java/io/IOException
  #106 = Utf8               getSHA1
  #107 = Utf8               disableProtection
  #108 = Utf8               ()V
  #109 = Utf8               enableProtection
  #110 = Utf8               ()Lorg/kohsuke/github/GHBranchProtectionBuilder;
  #111 = Utf8               (Lorg/kohsuke/github/EnforcementLevel;Ljava/util/Collection;)V
  #112 = Utf8               level
  #113 = Utf8               Lorg/kohsuke/github/EnforcementLevel;
  #114 = Utf8               contexts
  #115 = Utf8               Ljava/util/Collection;
  #116 = Utf8               LocalVariableTypeTable
  #117 = Utf8               Ljava/util/Collection<Ljava/lang/String;>;
  #118 = Utf8               StackMapTable
  #119 = Class              #212          // org/kohsuke/github/EnforcementLevel
  #120 = Class              #213          // java/util/Collection
  #121 = Utf8               Deprecated
  #122 = Utf8               Signature
  #123 = Utf8               (Lorg/kohsuke/github/EnforcementLevel;Ljava/util/Collection<Ljava/lang/String;>;)V
  #124 = Utf8               Ljava/lang/Deprecated;
  #125 = Utf8               merge
  #126 = Utf8               (Lorg/kohsuke/github/GHBranch;Ljava/lang/String;)Lorg/kohsuke/github/GHCommit;
  #127 = Utf8               headBranch
  #128 = Utf8               commitMessage
  #129 = Utf8               Ljavax/annotation/CheckForNull;
  #130 = Utf8               (Ljava/lang/String;Ljava/lang/String;)Lorg/kohsuke/github/GHCommit;
  #131 = Utf8               head
  #132 = Utf8               result
  #133 = Utf8               Lorg/kohsuke/github/GHCommit;
  #134 = Utf8               getApiRoute
  #135 = Utf8               toString
  #136 = Utf8               url
  #137 = Utf8               wrap
  #138 = Utf8               (Lorg/kohsuke/github/GHRepository;)Lorg/kohsuke/github/GHBranch;
  #139 = Utf8               repo
  #140 = Utf8               getRoot
  #141 = Utf8               ()Lorg/kohsuke/github/GitHub;
  #142 = Utf8               SourceFile
  #143 = Utf8               GHBranch.java
  #144 = Utf8               UWF_UNWRITTEN_PUBLIC_OR_PROTECTED_FIELD
  #145 = Utf8               UWF_UNWRITTEN_FIELD
  #146 = Utf8               NP_UNWRITTEN_FIELD
  #147 = Utf8               URF_UNREAD_FIELD
  #148 = Utf8               JSON API
  #149 = NameAndType        #74:#108      // "<init>":()V
  #150 = Class              #214          // java/util/Objects
  #151 = NameAndType        #215:#216     // requireNonNull:(Ljava/lang/Object;)Ljava/lang/Object;
  #152 = NameAndType        #63:#64       // name:Ljava/lang/String;
  #153 = NameAndType        #61:#62       // owner:Lorg/kohsuke/github/GHRepository;
  #154 = NameAndType        #67:#68       // protection:Z
  #155 = NameAndType        #73:#64       // protection_url:Ljava/lang/String;
  #156 = Class              #217          // org/kohsuke/github/GitHubClient
  #157 = NameAndType        #218:#219     // parseURL:(Ljava/lang/String;)Ljava/net/URL;
  #158 = NameAndType        #220:#141     // root:()Lorg/kohsuke/github/GitHub;
  #159 = Class              #221          // org/kohsuke/github/GitHub
  #160 = NameAndType        #222:#223     // createRequest:()Lorg/kohsuke/github/Requester;
  #161 = Class              #224          // org/kohsuke/github/internal/Previews
  #162 = NameAndType        #100:#99      // LUKE_CAGE:Lorg/kohsuke/github/internal/Previews;
  #163 = NameAndType        #225:#228     // withPreview:(Lorg/kohsuke/github/internal/Previews;)Lorg/kohsuke/github/GitHubRequest$Builder;
  #164 = Utf8               org/kohsuke/github/Requester
  #165 = NameAndType        #229:#230     // setRawUrlPath:(Ljava/lang/String;)Lorg/kohsuke/github/GitHubRequest$Builder;
  #166 = Utf8               org/kohsuke/github/GHBranchProtection
  #167 = NameAndType        #231:#232     // fetch:(Ljava/lang/Class;)Ljava/lang/Object;
  #168 = NameAndType        #65:#66       // commit:Lorg/kohsuke/github/GHBranch$Commit;
  #169 = NameAndType        #233:#64      // sha:Ljava/lang/String;
  #170 = Utf8               DELETE
  #171 = NameAndType        #234:#230     // method:(Ljava/lang/String;)Lorg/kohsuke/github/GitHubRequest$Builder;
  #172 = NameAndType        #235:#108     // send:()V
  #173 = Utf8               org/kohsuke/github/GHBranchProtectionBuilder
  #174 = NameAndType        #74:#236      // "<init>":(Lorg/kohsuke/github/GHBranch;)V
  #175 = NameAndType        #237:#238     // $SwitchMap$org$kohsuke$github$EnforcementLevel:[I
  #176 = NameAndType        #239:#240     // ordinal:()I
  #177 = NameAndType        #107:#108     // disableProtection:()V
  #178 = NameAndType        #109:#110     // enableProtection:()Lorg/kohsuke/github/GHBranchProtectionBuilder;
  #179 = NameAndType        #241:#242     // addRequiredChecks:(Ljava/util/Collection;)Lorg/kohsuke/github/GHBranchProtectionBuilder;
  #180 = NameAndType        #243:#113     // EVERYONE:Lorg/kohsuke/github/EnforcementLevel;
  #181 = NameAndType        #244:#245     // includeAdmins:(Z)Lorg/kohsuke/github/GHBranchProtectionBuilder;
  #182 = NameAndType        #246:#104     // enable:()Lorg/kohsuke/github/GHBranchProtection;
  #183 = NameAndType        #94:#95       // getName:()Ljava/lang/String;
  #184 = NameAndType        #125:#130     // merge:(Ljava/lang/String;Ljava/lang/String;)Lorg/kohsuke/github/GHCommit;
  #185 = Utf8               merges
  #186 = Class              #247          // org/kohsuke/github/GHRepository
  #187 = NameAndType        #248:#249     // getApiTailUrl:(Ljava/lang/String;)Ljava/lang/String;
  #188 = Utf8               java/lang/String
  #189 = NameAndType        #250:#251     // withUrlPath:(Ljava/lang/String;[Ljava/lang/String;)Lorg/kohsuke/github/GitHubRequest$Builder;
  #190 = Utf8               POST
  #191 = Utf8               commit_message
  #192 = NameAndType        #252:#253     // with:(Ljava/lang/String;Ljava/lang/String;)Lorg/kohsuke/github/GitHubRequest$Builder;
  #193 = Utf8               base
  #194 = Utf8               org/kohsuke/github/GHCommit
  #195 = NameAndType        #254:#255     // wrapUp:(Lorg/kohsuke/github/GHRepository;)Lorg/kohsuke/github/GHCommit;
  #196 = Utf8               java/lang/StringBuilder
  #197 = Utf8               /branches/
  #198 = NameAndType        #256:#257     // append:(Ljava/lang/String;)Ljava/lang/StringBuilder;
  #199 = NameAndType        #135:#95      // toString:()Ljava/lang/String;
  #200 = NameAndType        #258:#102     // getUrl:()Ljava/net/URL;
  #201 = Class              #259          // java/net/URL
  #202 = Utf8               unknown
  #203 = Utf8               Branch:
  #204 = Utf8                in
  #205 = NameAndType        #140:#141     // getRoot:()Lorg/kohsuke/github/GitHub;
  #206 = Utf8               org/kohsuke/github/GHBranch
  #207 = Utf8               org/kohsuke/github/GitHubInteractiveObject
  #208 = Utf8               org/kohsuke/github/GHBranch$1
  #209 = Utf8               org/kohsuke/github/GHBranch$Commit
  #210 = Utf8               java/lang/Exception
  #211 = Utf8               java/io/IOException
  #212 = Utf8               org/kohsuke/github/EnforcementLevel
  #213 = Utf8               java/util/Collection
  #214 = Utf8               java/util/Objects
  #215 = Utf8               requireNonNull
  #216 = Utf8               (Ljava/lang/Object;)Ljava/lang/Object;
  #217 = Utf8               org/kohsuke/github/GitHubClient
  #218 = Utf8               parseURL
  #219 = Utf8               (Ljava/lang/String;)Ljava/net/URL;
  #220 = Utf8               root
  #221 = Utf8               org/kohsuke/github/GitHub
  #222 = Utf8               createRequest
  #223 = Utf8               ()Lorg/kohsuke/github/Requester;
  #224 = Utf8               org/kohsuke/github/internal/Previews
  #225 = Utf8               withPreview
  #226 = Class              #261          // org/kohsuke/github/GitHubRequest$Builder
  #227 = Utf8               Builder
  #228 = Utf8               (Lorg/kohsuke/github/internal/Previews;)Lorg/kohsuke/github/GitHubRequest$Builder;
  #229 = Utf8               setRawUrlPath
  #230 = Utf8               (Ljava/lang/String;)Lorg/kohsuke/github/GitHubRequest$Builder;
  #231 = Utf8               fetch
  #232 = Utf8               (Ljava/lang/Class;)Ljava/lang/Object;
  #233 = Utf8               sha
  #234 = Utf8               method
  #235 = Utf8               send
  #236 = Utf8               (Lorg/kohsuke/github/GHBranch;)V
  #237 = Utf8               $SwitchMap$org$kohsuke$github$EnforcementLevel
  #238 = Utf8               [I
  #239 = Utf8               ordinal
  #240 = Utf8               ()I
  #241 = Utf8               addRequiredChecks
  #242 = Utf8               (Ljava/util/Collection;)Lorg/kohsuke/github/GHBranchProtectionBuilder;
  #243 = Utf8               EVERYONE
  #244 = Utf8               includeAdmins
  #245 = Utf8               (Z)Lorg/kohsuke/github/GHBranchProtectionBuilder;
  #246 = Utf8               enable
  #247 = Utf8               org/kohsuke/github/GHRepository
  #248 = Utf8               getApiTailUrl
  #249 = Utf8               (Ljava/lang/String;)Ljava/lang/String;
  #250 = Utf8               withUrlPath
  #251 = Utf8               (Ljava/lang/String;[Ljava/lang/String;)Lorg/kohsuke/github/GitHubRequest$Builder;
  #252 = Utf8               with
  #253 = Utf8               (Ljava/lang/String;Ljava/lang/String;)Lorg/kohsuke/github/GitHubRequest$Builder;
  #254 = Utf8               wrapUp
  #255 = Utf8               (Lorg/kohsuke/github/GHRepository;)Lorg/kohsuke/github/GHCommit;
  #256 = Utf8               append
  #257 = Utf8               (Ljava/lang/String;)Ljava/lang/StringBuilder;
  #258 = Utf8               getUrl
  #259 = Utf8               java/net/URL
  #260 = Class              #262          // org/kohsuke/github/GitHubRequest
  #261 = Utf8               org/kohsuke/github/GitHubRequest$Builder
  #262 = Utf8               org/kohsuke/github/GitHubRequest
{
  private org.kohsuke.github.GHRepository owner;
    descriptor: Lorg/kohsuke/github/GHRepository;
    flags: (0x0002) ACC_PRIVATE

  private java.lang.String name;
    descriptor: Ljava/lang/String;
    flags: (0x0002) ACC_PRIVATE

  private org.kohsuke.github.GHBranch$Commit commit;
    descriptor: Lorg/kohsuke/github/GHBranch$Commit;
    flags: (0x0002) ACC_PRIVATE

  private boolean protection;
    descriptor: Z
    flags: (0x0002) ACC_PRIVATE
    RuntimeVisibleAnnotations:
      0: #70(#71=s#72)
        com.fasterxml.jackson.annotation.JsonProperty(
          value="protected"
        )

  private java.lang.String protection_url;
    descriptor: Ljava/lang/String;
    flags: (0x0002) ACC_PRIVATE

  org.kohsuke.github.GHBranch(java.lang.String) throws java.lang.Exception;
    descriptor: (Ljava/lang/String;)V
    flags: (0x0000)
    Code:
      stack=2, locals=2, args_size=2
         0: aload_0
         1: invokespecial #1                  // Method org/kohsuke/github/GitHubInteractiveObject."<init>":()V
         4: aload_1
         5: invokestatic  #2                  // Method java/util/Objects.requireNonNull:(Ljava/lang/Object;)Ljava/lang/Object;
         8: pop
         9: aload_0
        10: aload_1
        11: putfield      #3                  // Field name:Ljava/lang/String;
        14: return
      LineNumberTable:
        line 34: 0
        line 35: 4
        line 36: 9
        line 37: 14
      LocalVariableTable:
        Start  Length  Slot  Name   Signature
            0      15     0  this   Lorg/kohsuke/github/GHBranch;
            0      15     1  name   Ljava/lang/String;
    Exceptions:
      throws java.lang.Exception
    RuntimeVisibleAnnotations:
      0: #83()
        com.fasterxml.jackson.annotation.JsonCreator
    RuntimeVisibleParameterAnnotations:
      parameter 0:
        0: #70(#71=s#63,#85=Z#86)
          com.fasterxml.jackson.annotation.JsonProperty(
            value="name"
            required=true
          )

  public org.kohsuke.github.GHRepository getOwner();
    descriptor: ()Lorg/kohsuke/github/GHRepository;
    flags: (0x0001) ACC_PUBLIC
    Code:
      stack=1, locals=1, args_size=1
         0: aload_0
         1: getfield      #4                  // Field owner:Lorg/kohsuke/github/GHRepository;
         4: areturn
      LineNumberTable:
        line 56: 0
      LocalVariableTable:
        Start  Length  Slot  Name   Signature
            0       5     0  this   Lorg/kohsuke/github/GHBranch;
    RuntimeInvisibleAnnotations:
      0: #90(#71=[s#91],#92=s#93)
        edu.umd.cs.findbugs.annotations.SuppressFBWarnings(
          value=["EI_EXPOSE_REP"]
          justification="Expected behavior"
        )

  public java.lang.String getName();
    descriptor: ()Ljava/lang/String;
    flags: (0x0001) ACC_PUBLIC
    Code:
      stack=1, locals=1, args_size=1
         0: aload_0
         1: getfield      #3                  // Field name:Ljava/lang/String;
         4: areturn
      LineNumberTable:
        line 65: 0
      LocalVariableTable:
        Start  Length  Slot  Name   Signature
            0       5     0  this   Lorg/kohsuke/github/GHBranch;

  public boolean isProtected();
    descriptor: ()Z
    flags: (0x0001) ACC_PUBLIC
    Code:
      stack=1, locals=1, args_size=1
         0: aload_0
         1: getfield      #5                  // Field protection:Z
         4: ireturn
      LineNumberTable:
        line 75: 0
      LocalVariableTable:
        Start  Length  Slot  Name   Signature
            0       5     0  this   Lorg/kohsuke/github/GHBranch;
    RuntimeVisibleAnnotations:
      0: #98(#71=[e#99.#100])
        org.kohsuke.github.Preview(
          value=[Lorg/kohsuke/github/internal/Previews;.LUKE_CAGE]
        )

  public java.net.URL getProtectionUrl();
    descriptor: ()Ljava/net/URL;
    flags: (0x0001) ACC_PUBLIC
    Code:
      stack=1, locals=1, args_size=1
         0: aload_0
         1: getfield      #6                  // Field protection_url:Ljava/lang/String;
         4: invokestatic  #7                  // Method org/kohsuke/github/GitHubClient.parseURL:(Ljava/lang/String;)Ljava/net/URL;
         7: areturn
      LineNumberTable:
        line 85: 0
      LocalVariableTable:
        Start  Length  Slot  Name   Signature
            0       8     0  this   Lorg/kohsuke/github/GHBranch;
    RuntimeVisibleAnnotations:
      0: #98(#71=[e#99.#100])
        org.kohsuke.github.Preview(
          value=[Lorg/kohsuke/github/internal/Previews;.LUKE_CAGE]
        )

  public org.kohsuke.github.GHBranchProtection getProtection() throws java.io.IOException;
    descriptor: ()Lorg/kohsuke/github/GHBranchProtection;
    flags: (0x0001) ACC_PUBLIC
    Code:
      stack=2, locals=1, args_size=1
         0: aload_0
         1: invokevirtual #8                  // Method root:()Lorg/kohsuke/github/GitHub;
         4: invokevirtual #9                  // Method org/kohsuke/github/GitHub.createRequest:()Lorg/kohsuke/github/Requester;
         7: getstatic     #10                 // Field org/kohsuke/github/internal/Previews.LUKE_CAGE:Lorg/kohsuke/github/internal/Previews;
        10: invokevirtual #11                 // Method org/kohsuke/github/Requester.withPreview:(Lorg/kohsuke/github/internal/Previews;)Lorg/kohsuke/github/GitHubRequest$Builder;
        13: checkcast     #12                 // class org/kohsuke/github/Requester
        16: aload_0
        17: getfield      #6                  // Field protection_url:Ljava/lang/String;
        20: invokevirtual #13                 // Method org/kohsuke/github/Requester.setRawUrlPath:(Ljava/lang/String;)Lorg/kohsuke/github/GitHubRequest$Builder;
        23: checkcast     #12                 // class org/kohsuke/github/Requester
        26: ldc           #14                 // class org/kohsuke/github/GHBranchProtection
        28: invokevirtual #15                 // Method org/kohsuke/github/Requester.fetch:(Ljava/lang/Class;)Ljava/lang/Object;
        31: checkcast     #14                 // class org/kohsuke/github/GHBranchProtection
        34: areturn
      LineNumberTable:
        line 97: 0
        line 98: 10
        line 99: 20
        line 100: 28
        line 97: 34
      LocalVariableTable:
        Start  Length  Slot  Name   Signature
            0      35     0  this   Lorg/kohsuke/github/GHBranch;
    Exceptions:
      throws java.io.IOException
    RuntimeVisibleAnnotations:
      0: #98(#71=[e#99.#100])
        org.kohsuke.github.Preview(
          value=[Lorg/kohsuke/github/internal/Previews;.LUKE_CAGE]
        )

  public java.lang.String getSHA1();
    descriptor: ()Ljava/lang/String;
    flags: (0x0001) ACC_PUBLIC
    Code:
      stack=1, locals=1, args_size=1
         0: aload_0
         1: getfield      #16                 // Field commit:Lorg/kohsuke/github/GHBranch$Commit;
         4: getfield      #17                 // Field org/kohsuke/github/GHBranch$Commit.sha:Ljava/lang/String;
         7: areturn
      LineNumberTable:
        line 109: 0
      LocalVariableTable:
        Start  Length  Slot  Name   Signature
            0       8     0  this   Lorg/kohsuke/github/GHBranch;

  public void disableProtection() throws java.io.IOException;
    descriptor: ()V
    flags: (0x0001) ACC_PUBLIC
    Code:
      stack=2, locals=1, args_size=1
         0: aload_0
         1: invokevirtual #8                  // Method root:()Lorg/kohsuke/github/GitHub;
         4: invokevirtual #9                  // Method org/kohsuke/github/GitHub.createRequest:()Lorg/kohsuke/github/Requester;
         7: ldc           #18                 // String DELETE
         9: invokevirtual #19                 // Method org/kohsuke/github/Requester.method:(Ljava/lang/String;)Lorg/kohsuke/github/GitHubRequest$Builder;
        12: checkcast     #12                 // class org/kohsuke/github/Requester
        15: aload_0
        16: getfield      #6                  // Field protection_url:Ljava/lang/String;
        19: invokevirtual #13                 // Method org/kohsuke/github/Requester.setRawUrlPath:(Ljava/lang/String;)Lorg/kohsuke/github/GitHubRequest$Builder;
        22: checkcast     #12                 // class org/kohsuke/github/Requester
        25: invokevirtual #20                 // Method org/kohsuke/github/Requester.send:()V
        28: return
      LineNumberTable:
        line 119: 0
        line 120: 28
      LocalVariableTable:
        Start  Length  Slot  Name   Signature
            0      29     0  this   Lorg/kohsuke/github/GHBranch;
    Exceptions:
      throws java.io.IOException

  public org.kohsuke.github.GHBranchProtectionBuilder enableProtection();
    descriptor: ()Lorg/kohsuke/github/GHBranchProtectionBuilder;
    flags: (0x0001) ACC_PUBLIC
    Code:
      stack=3, locals=1, args_size=1
         0: new           #21                 // class org/kohsuke/github/GHBranchProtectionBuilder
         3: dup
         4: aload_0
         5: invokespecial #22                 // Method org/kohsuke/github/GHBranchProtectionBuilder."<init>":(Lorg/kohsuke/github/GHBranch;)V
         8: areturn
      LineNumberTable:
        line 130: 0
      LocalVariableTable:
        Start  Length  Slot  Name   Signature
            0       9     0  this   Lorg/kohsuke/github/GHBranch;
    RuntimeVisibleAnnotations:
      0: #98(#71=[e#99.#100])
        org.kohsuke.github.Preview(
          value=[Lorg/kohsuke/github/internal/Previews;.LUKE_CAGE]
        )

  public void enableProtection(org.kohsuke.github.EnforcementLevel, java.util.Collection<java.lang.String>) throws java.io.IOException;
    descriptor: (Lorg/kohsuke/github/EnforcementLevel;Ljava/util/Collection;)V
    flags: (0x0001) ACC_PUBLIC
    Code:
      stack=3, locals=3, args_size=3
         0: getstatic     #23                 // Field org/kohsuke/github/GHBranch$1.$SwitchMap$org$kohsuke$github$EnforcementLevel:[I
         3: aload_1
         4: invokevirtual #24                 // Method org/kohsuke/github/EnforcementLevel.ordinal:()I
         7: iaload
         8: tableswitch   { // 1 to 3
                       1: 36
                       2: 43
                       3: 43
                 default: 70
            }
        36: aload_0
        37: invokevirtual #25                 // Method disableProtection:()V
        40: goto          70
        43: aload_0
        44: invokevirtual #26                 // Method enableProtection:()Lorg/kohsuke/github/GHBranchProtectionBuilder;
        47: aload_2
        48: invokevirtual #27                 // Method org/kohsuke/github/GHBranchProtectionBuilder.addRequiredChecks:(Ljava/util/Collection;)Lorg/kohsuke/github/GHBranchProtectionBuilder;
        51: aload_1
        52: getstatic     #28                 // Field org/kohsuke/github/EnforcementLevel.EVERYONE:Lorg/kohsuke/github/EnforcementLevel;
        55: if_acmpne     62
        58: iconst_1
        59: goto          63
        62: iconst_0
        63: invokevirtual #29                 // Method org/kohsuke/github/GHBranchProtectionBuilder.includeAdmins:(Z)Lorg/kohsuke/github/GHBranchProtectionBuilder;
        66: invokevirtual #30                 // Method org/kohsuke/github/GHBranchProtectionBuilder.enable:()Lorg/kohsuke/github/GHBranchProtection;
        69: pop
        70: return
      LineNumberTable:
        line 146: 0
        line 148: 36
        line 149: 40
        line 152: 43
        line 153: 63
        line 154: 66
        line 157: 70
      LocalVariableTable:
        Start  Length  Slot  Name   Signature
            0      71     0  this   Lorg/kohsuke/github/GHBranch;
            0      71     1 level   Lorg/kohsuke/github/EnforcementLevel;
            0      71     2 contexts   Ljava/util/Collection;
      LocalVariableTypeTable:
        Start  Length  Slot  Name   Signature
            0      71     2 contexts   Ljava/util/Collection<Ljava/lang/String;>;
      StackMapTable: number_of_entries = 5
        frame_type = 36 /* same */
        frame_type = 6 /* same */
        frame_type = 82 /* same_locals_1_stack_item */
          stack = [ class org/kohsuke/github/GHBranchProtectionBuilder ]
        frame_type = 255 /* full_frame */
          offset_delta = 0
          locals = [ class org/kohsuke/github/GHBranch, class org/kohsuke/github/EnforcementLevel, class java/util/Collection ]
          stack = [ class org/kohsuke/github/GHBranchProtectionBuilder, int ]
        frame_type = 6 /* same */
    Exceptions:
      throws java.io.IOException
    Deprecated: true
    Signature: #123                         // (Lorg/kohsuke/github/EnforcementLevel;Ljava/util/Collection<Ljava/lang/String;>;)V
    RuntimeVisibleAnnotations:
      0: #124()
        java.lang.Deprecated

  public org.kohsuke.github.GHCommit merge(org.kohsuke.github.GHBranch, java.lang.String) throws java.io.IOException;
    descriptor: (Lorg/kohsuke/github/GHBranch;Ljava/lang/String;)Lorg/kohsuke/github/GHCommit;
    flags: (0x0001) ACC_PUBLIC
    Code:
      stack=3, locals=3, args_size=3
         0: aload_0
         1: aload_1
         2: invokevirtual #31                 // Method getName:()Ljava/lang/String;
         5: aload_2
         6: invokevirtual #32                 // Method merge:(Ljava/lang/String;Ljava/lang/String;)Lorg/kohsuke/github/GHCommit;
         9: areturn
      LineNumberTable:
        line 176: 0
      LocalVariableTable:
        Start  Length  Slot  Name   Signature
            0      10     0  this   Lorg/kohsuke/github/GHBranch;
            0      10     1 headBranch   Lorg/kohsuke/github/GHBranch;
            0      10     2 commitMessage   Ljava/lang/String;
    Exceptions:
      throws java.io.IOException
    RuntimeVisibleAnnotations:
      0: #129()
        javax.annotation.CheckForNull

  public org.kohsuke.github.GHCommit merge(java.lang.String, java.lang.String) throws java.io.IOException;
    descriptor: (Ljava/lang/String;Ljava/lang/String;)Lorg/kohsuke/github/GHCommit;
    flags: (0x0001) ACC_PUBLIC
    Code:
      stack=3, locals=4, args_size=3
         0: aload_0
         1: invokevirtual #8                  // Method root:()Lorg/kohsuke/github/GitHub;
         4: invokevirtual #9                  // Method org/kohsuke/github/GitHub.createRequest:()Lorg/kohsuke/github/Requester;
         7: aload_0
         8: getfield      #4                  // Field owner:Lorg/kohsuke/github/GHRepository;
        11: ldc           #33                 // String merges
        13: invokevirtual #34                 // Method org/kohsuke/github/GHRepository.getApiTailUrl:(Ljava/lang/String;)Ljava/lang/String;
        16: iconst_0
        17: anewarray     #35                 // class java/lang/String
        20: invokevirtual #36                 // Method org/kohsuke/github/Requester.withUrlPath:(Ljava/lang/String;[Ljava/lang/String;)Lorg/kohsuke/github/GitHubRequest$Builder;
        23: checkcast     #12                 // class org/kohsuke/github/Requester
        26: ldc           #37                 // String POST
        28: invokevirtual #19                 // Method org/kohsuke/github/Requester.method:(Ljava/lang/String;)Lorg/kohsuke/github/GitHubRequest$Builder;
        31: checkcast     #12                 // class org/kohsuke/github/Requester
        34: ldc           #38                 // String commit_message
        36: aload_2
        37: invokevirtual #39                 // Method org/kohsuke/github/Requester.with:(Ljava/lang/String;Ljava/lang/String;)Lorg/kohsuke/github/GitHubRequest$Builder;
        40: checkcast     #12                 // class org/kohsuke/github/Requester
        43: ldc           #40                 // String base
        45: aload_0
        46: getfield      #3                  // Field name:Ljava/lang/String;
        49: invokevirtual #39                 // Method org/kohsuke/github/Requester.with:(Ljava/lang/String;Ljava/lang/String;)Lorg/kohsuke/github/GitHubRequest$Builder;
        52: checkcast     #12                 // class org/kohsuke/github/Requester
        55: ldc           #41                 // String head
        57: aload_1
        58: invokevirtual #39                 // Method org/kohsuke/github/Requester.with:(Ljava/lang/String;Ljava/lang/String;)Lorg/kohsuke/github/GitHubRequest$Builder;
        61: checkcast     #12                 // class org/kohsuke/github/Requester
        64: ldc           #42                 // class org/kohsuke/github/GHCommit
        66: invokevirtual #15                 // Method org/kohsuke/github/Requester.fetch:(Ljava/lang/Class;)Ljava/lang/Object;
        69: checkcast     #42                 // class org/kohsuke/github/GHCommit
        72: astore_3
        73: aload_3
        74: ifnull        86
        77: aload_3
        78: aload_0
        79: getfield      #4                  // Field owner:Lorg/kohsuke/github/GHRepository;
        82: invokevirtual #43                 // Method org/kohsuke/github/GHCommit.wrapUp:(Lorg/kohsuke/github/GHRepository;)Lorg/kohsuke/github/GHCommit;
        85: pop
        86: aload_3
        87: areturn
      LineNumberTable:
        line 197: 0
        line 198: 13
        line 199: 28
        line 200: 37
        line 201: 49
        line 202: 58
        line 203: 66
        line 205: 73
        line 206: 77
        line 209: 86
      LocalVariableTable:
        Start  Length  Slot  Name   Signature
            0      88     0  this   Lorg/kohsuke/github/GHBranch;
            0      88     1  head   Ljava/lang/String;
            0      88     2 commitMessage   Ljava/lang/String;
           73      15     3 result   Lorg/kohsuke/github/GHCommit;
      StackMapTable: number_of_entries = 1
        frame_type = 252 /* append */
          offset_delta = 86
          locals = [ class org/kohsuke/github/GHCommit ]
    Exceptions:
      throws java.io.IOException
    RuntimeVisibleAnnotations:
      0: #129()
        javax.annotation.CheckForNull

  java.lang.String getApiRoute();
    descriptor: ()Ljava/lang/String;
    flags: (0x0000)
    Code:
      stack=3, locals=1, args_size=1
         0: aload_0
         1: getfield      #4                  // Field owner:Lorg/kohsuke/github/GHRepository;
         4: new           #44                 // class java/lang/StringBuilder
         7: dup
         8: invokespecial #45                 // Method java/lang/StringBuilder."<init>":()V
        11: ldc           #46                 // String /branches/
        13: invokevirtual #47                 // Method java/lang/StringBuilder.append:(Ljava/lang/String;)Ljava/lang/StringBuilder;
        16: aload_0
        17: getfield      #3                  // Field name:Ljava/lang/String;
        20: invokevirtual #47                 // Method java/lang/StringBuilder.append:(Ljava/lang/String;)Ljava/lang/StringBuilder;
        23: invokevirtual #48                 // Method java/lang/StringBuilder.toString:()Ljava/lang/String;
        26: invokevirtual #34                 // Method org/kohsuke/github/GHRepository.getApiTailUrl:(Ljava/lang/String;)Ljava/lang/String;
        29: areturn
      LineNumberTable:
        line 213: 0
      LocalVariableTable:
        Start  Length  Slot  Name   Signature
            0      30     0  this   Lorg/kohsuke/github/GHBranch;

  public java.lang.String toString();
    descriptor: ()Ljava/lang/String;
    flags: (0x0001) ACC_PUBLIC
    Code:
      stack=2, locals=2, args_size=1
         0: aload_0
         1: getfield      #4                  // Field owner:Lorg/kohsuke/github/GHRepository;
         4: ifnull        20
         7: aload_0
         8: getfield      #4                  // Field owner:Lorg/kohsuke/github/GHRepository;
        11: invokevirtual #49                 // Method org/kohsuke/github/GHRepository.getUrl:()Ljava/net/URL;
        14: invokevirtual #50                 // Method java/net/URL.toString:()Ljava/lang/String;
        17: goto          22
        20: ldc           #51                 // String unknown
        22: astore_1
        23: new           #44                 // class java/lang/StringBuilder
        26: dup
        27: invokespecial #45                 // Method java/lang/StringBuilder."<init>":()V
        30: ldc           #52                 // String Branch:
        32: invokevirtual #47                 // Method java/lang/StringBuilder.append:(Ljava/lang/String;)Ljava/lang/StringBuilder;
        35: aload_0
        36: getfield      #3                  // Field name:Ljava/lang/String;
        39: invokevirtual #47                 // Method java/lang/StringBuilder.append:(Ljava/lang/String;)Ljava/lang/StringBuilder;
        42: ldc           #53                 // String  in
        44: invokevirtual #47                 // Method java/lang/StringBuilder.append:(Ljava/lang/String;)Ljava/lang/StringBuilder;
        47: aload_1
        48: invokevirtual #47                 // Method java/lang/StringBuilder.append:(Ljava/lang/String;)Ljava/lang/StringBuilder;
        51: invokevirtual #48                 // Method java/lang/StringBuilder.toString:()Ljava/lang/String;
        54: areturn
      LineNumberTable:
        line 218: 0
        line 219: 23
      LocalVariableTable:
        Start  Length  Slot  Name   Signature
            0      55     0  this   Lorg/kohsuke/github/GHBranch;
           23      32     1   url   Ljava/lang/String;
      StackMapTable: number_of_entries = 2
        frame_type = 20 /* same */
        frame_type = 65 /* same_locals_1_stack_item */
          stack = [ class java/lang/String ]

  org.kohsuke.github.GHBranch wrap(org.kohsuke.github.GHRepository);
    descriptor: (Lorg/kohsuke/github/GHRepository;)Lorg/kohsuke/github/GHBranch;
    flags: (0x0000)
    Code:
      stack=2, locals=2, args_size=2
         0: aload_0
         1: aload_1
         2: putfield      #4                  // Field owner:Lorg/kohsuke/github/GHRepository;
         5: aload_0
         6: areturn
      LineNumberTable:
        line 223: 0
        line 224: 5
      LocalVariableTable:
        Start  Length  Slot  Name   Signature
            0       7     0  this   Lorg/kohsuke/github/GHBranch;
            0       7     1  repo   Lorg/kohsuke/github/GHRepository;

  public org.kohsuke.github.GitHub getRoot();
    descriptor: ()Lorg/kohsuke/github/GitHub;
    flags: (0x1041) ACC_PUBLIC, ACC_BRIDGE, ACC_SYNTHETIC
    Code:
      stack=1, locals=1, args_size=1
         0: aload_0
         1: invokespecial #54                 // Method org/kohsuke/github/GitHubInteractiveObject.getRoot:()Lorg/kohsuke/github/GitHub;
         4: areturn
      LineNumberTable:
        line 20: 0
      LocalVariableTable:
        Start  Length  Slot  Name   Signature
            0       5     0  this   Lorg/kohsuke/github/GHBranch;
    RuntimeVisibleAnnotations:
      0: #124()
        java.lang.Deprecated
    RuntimeInvisibleAnnotations:
      0: #90(#71=[s#91],#92=s#93)
        edu.umd.cs.findbugs.annotations.SuppressFBWarnings(
          value=["EI_EXPOSE_REP"]
          justification="Expected behavior"
        )
}
SourceFile: "GHBranch.java"
RuntimeInvisibleAnnotations:
  0: #90(#71=[s#144,s#145,s#146,s#147],#92=s#148)
    edu.umd.cs.findbugs.annotations.SuppressFBWarnings(
      value=["UWF_UNWRITTEN_PUBLIC_OR_PROTECTED_FIELD","UWF_UNWRITTEN_FIELD","NP_UNWRITTEN_FIELD","URF_UNREAD_FIELD"]
      justification="JSON API"
    )
InnerClasses:
  static #57;                             // class org/kohsuke/github/GHBranch$1
  public static #60= #59 of #55;          // Commit=class org/kohsuke/github/GHBranch$Commit of class org/kohsuke/github/GHBranch
  static #227= #226 of #260;              // Builder=class org/kohsuke/github/GitHubRequest$Builder of class org/kohsuke/github/GitHubRequest
