Classfile /Users/mw/Projects/slang-braindump/.jar/jar11/assemble/slang-braindump/assemble/content/org/kohsuke/github/GHCheckRun.class
  Last modified May 29, 2022; size 6053 bytes
  SHA-256 checksum cfd0024d38e919a3629c4e375ffed499fbbd02652d0a20f5af7931831a340bb3
  Compiled from "GHCheckRun.java"
public class org.kohsuke.github.GHCheckRun extends org.kohsuke.github.GHObject
  minor version: 0
  major version: 52
  flags: (0x0021) ACC_PUBLIC, ACC_SUPER
  this_class: #2                          // org/kohsuke/github/GHCheckRun
  super_class: #4                         // org/kohsuke/github/GHObject
  interfaces: 0, fields: 15, methods: 22, attributes: 3
Constant pool:
    #1 = Utf8               org/kohsuke/github/GHCheckRun
    #2 = Class              #1            // org/kohsuke/github/GHCheckRun
    #3 = Utf8               org/kohsuke/github/GHObject
    #4 = Class              #3            // org/kohsuke/github/GHObject
    #5 = Utf8               GHCheckRun.java
    #6 = Utf8               Ledu/umd/cs/findbugs/annotations/SuppressFBWarnings;
    #7 = Utf8               value
    #8 = Utf8               UWF_UNWRITTEN_FIELD
    #9 = Utf8               NP_UNWRITTEN_FIELD
   #10 = Utf8               URF_UNREAD_FIELD
   #11 = Utf8               justification
   #12 = Utf8               JSON API
   #13 = Utf8               Lcom/infradna/tool/bridge_method_injector/BridgeMethodsAdded;
   #14 = Utf8               org/kohsuke/github/GHCheckRun$AnnotationLevel
   #15 = Class              #14           // org/kohsuke/github/GHCheckRun$AnnotationLevel
   #16 = Utf8               AnnotationLevel
   #17 = Utf8               org/kohsuke/github/GHCheckRun$Output
   #18 = Class              #17           // org/kohsuke/github/GHCheckRun$Output
   #19 = Utf8               Output
   #20 = Utf8               org/kohsuke/github/GHCheckRun$Conclusion
   #21 = Class              #20           // org/kohsuke/github/GHCheckRun$Conclusion
   #22 = Utf8               Conclusion
   #23 = Utf8               org/kohsuke/github/GHCheckRun$Status
   #24 = Class              #23           // org/kohsuke/github/GHCheckRun$Status
   #25 = Utf8               Status
   #26 = Utf8               owner
   #27 = Utf8               Lorg/kohsuke/github/GHRepository;
   #28 = Utf8               Lcom/fasterxml/jackson/annotation/JsonProperty;
   #29 = Utf8               repository
   #30 = Utf8               status
   #31 = Utf8               Ljava/lang/String;
   #32 = Utf8               conclusion
   #33 = Utf8               name
   #34 = Utf8               headSha
   #35 = Utf8               nodeId
   #36 = Utf8               externalId
   #37 = Utf8               startedAt
   #38 = Utf8               completedAt
   #39 = Utf8               htmlUrl
   #40 = Utf8               detailsUrl
   #41 = Utf8               output
   #42 = Utf8               Lorg/kohsuke/github/GHCheckRun$Output;
   #43 = Utf8               app
   #44 = Utf8               Lorg/kohsuke/github/GHApp;
   #45 = Utf8               pullRequests
   #46 = Utf8               [Lorg/kohsuke/github/GHPullRequest;
   #47 = Utf8               checkSuite
   #48 = Utf8               Lorg/kohsuke/github/GHCheckSuite;
   #49 = Utf8               <init>
   #50 = Utf8               ()V
   #51 = NameAndType        #49:#50       // "<init>":()V
   #52 = Methodref          #4.#51        // org/kohsuke/github/GHObject."<init>":()V
   #53 = Utf8               org/kohsuke/github/GHPullRequest
   #54 = Class              #53           // org/kohsuke/github/GHPullRequest
   #55 = NameAndType        #45:#46       // pullRequests:[Lorg/kohsuke/github/GHPullRequest;
   #56 = Fieldref           #2.#55        // org/kohsuke/github/GHCheckRun.pullRequests:[Lorg/kohsuke/github/GHPullRequest;
   #57 = Utf8               this
   #58 = Utf8               Lorg/kohsuke/github/GHCheckRun;
   #59 = Utf8               wrap
   #60 = Utf8               (Lorg/kohsuke/github/GHRepository;)Lorg/kohsuke/github/GHCheckRun;
   #61 = NameAndType        #26:#27       // owner:Lorg/kohsuke/github/GHRepository;
   #62 = Fieldref           #2.#61        // org/kohsuke/github/GHCheckRun.owner:Lorg/kohsuke/github/GHRepository;
   #63 = Utf8               org/kohsuke/github/GHRepository
   #64 = Class              #63           // org/kohsuke/github/GHRepository
   #65 = Utf8               root
   #66 = Utf8               ()Lorg/kohsuke/github/GitHub;
   #67 = NameAndType        #65:#66       // root:()Lorg/kohsuke/github/GitHub;
   #68 = Methodref          #64.#67       // org/kohsuke/github/GHRepository.root:()Lorg/kohsuke/github/GitHub;
   #69 = Utf8               (Lorg/kohsuke/github/GitHub;)Lorg/kohsuke/github/GHCheckRun;
   #70 = NameAndType        #59:#69       // wrap:(Lorg/kohsuke/github/GitHub;)Lorg/kohsuke/github/GHCheckRun;
   #71 = Methodref          #2.#70        // org/kohsuke/github/GHCheckRun.wrap:(Lorg/kohsuke/github/GitHub;)Lorg/kohsuke/github/GHCheckRun;
   #72 = Class              #46           // "[Lorg/kohsuke/github/GHPullRequest;"
   #73 = Utf8               (Lorg/kohsuke/github/GHRepository;)Lorg/kohsuke/github/GHIssue;
   #74 = NameAndType        #59:#73       // wrap:(Lorg/kohsuke/github/GHRepository;)Lorg/kohsuke/github/GHIssue;
   #75 = Methodref          #54.#74       // org/kohsuke/github/GHPullRequest.wrap:(Lorg/kohsuke/github/GHRepository;)Lorg/kohsuke/github/GHIssue;
   #76 = NameAndType        #47:#48       // checkSuite:Lorg/kohsuke/github/GHCheckSuite;
   #77 = Fieldref           #2.#76        // org/kohsuke/github/GHCheckRun.checkSuite:Lorg/kohsuke/github/GHCheckSuite;
   #78 = Utf8               org/kohsuke/github/GHCheckSuite
   #79 = Class              #78           // org/kohsuke/github/GHCheckSuite
   #80 = Utf8               (Lorg/kohsuke/github/GHRepository;)Lorg/kohsuke/github/GHCheckSuite;
   #81 = NameAndType        #59:#80       // wrap:(Lorg/kohsuke/github/GHRepository;)Lorg/kohsuke/github/GHCheckSuite;
   #82 = Methodref          #79.#81       // org/kohsuke/github/GHCheckSuite.wrap:(Lorg/kohsuke/github/GHRepository;)Lorg/kohsuke/github/GHCheckSuite;
   #83 = Utf8               (Lorg/kohsuke/github/GitHub;)Lorg/kohsuke/github/GHCheckSuite;
   #84 = NameAndType        #59:#83       // wrap:(Lorg/kohsuke/github/GitHub;)Lorg/kohsuke/github/GHCheckSuite;
   #85 = Methodref          #79.#84       // org/kohsuke/github/GHCheckSuite.wrap:(Lorg/kohsuke/github/GitHub;)Lorg/kohsuke/github/GHCheckSuite;
   #86 = Utf8               singlePull
   #87 = Utf8               Lorg/kohsuke/github/GHPullRequest;
   #88 = Utf8               Lorg/kohsuke/github/GitHub;
   #89 = Utf8               getStatus
   #90 = Utf8               ()Lorg/kohsuke/github/GHCheckRun$Status;
   #91 = Utf8               Lcom/infradna/tool/bridge_method_injector/WithBridgeMethods;
   #92 = Utf8               adapterMethod
   #93 = Utf8               statusAsStr
   #94 = NameAndType        #30:#31       // status:Ljava/lang/String;
   #95 = Fieldref           #2.#94        // org/kohsuke/github/GHCheckRun.status:Ljava/lang/String;
   #96 = Utf8               from
   #97 = Utf8               (Ljava/lang/String;)Lorg/kohsuke/github/GHCheckRun$Status;
   #98 = NameAndType        #96:#97       // from:(Ljava/lang/String;)Lorg/kohsuke/github/GHCheckRun$Status;
   #99 = Methodref          #24.#98       // org/kohsuke/github/GHCheckRun$Status.from:(Ljava/lang/String;)Lorg/kohsuke/github/GHCheckRun$Status;
  #100 = Utf8               (Lorg/kohsuke/github/GHCheckRun$Status;Ljava/lang/Class;)Ljava/lang/Object;
  #101 = Utf8               UPM_UNCALLED_PRIVATE_METHOD
  #102 = Utf8               Bridge method of getStatus
  #103 = Utf8               Lorg/kohsuke/github/GHCheckRun$Status;
  #104 = Utf8               type
  #105 = Utf8               Ljava/lang/Class;
  #106 = Utf8               getConclusion
  #107 = Utf8               ()Lorg/kohsuke/github/GHCheckRun$Conclusion;
  #108 = Utf8               conclusionAsStr
  #109 = NameAndType        #32:#31       // conclusion:Ljava/lang/String;
  #110 = Fieldref           #2.#109       // org/kohsuke/github/GHCheckRun.conclusion:Ljava/lang/String;
  #111 = Utf8               (Ljava/lang/String;)Lorg/kohsuke/github/GHCheckRun$Conclusion;
  #112 = NameAndType        #96:#111      // from:(Ljava/lang/String;)Lorg/kohsuke/github/GHCheckRun$Conclusion;
  #113 = Methodref          #21.#112      // org/kohsuke/github/GHCheckRun$Conclusion.from:(Ljava/lang/String;)Lorg/kohsuke/github/GHCheckRun$Conclusion;
  #114 = Utf8               (Lorg/kohsuke/github/GHCheckRun$Conclusion;Ljava/lang/Class;)Ljava/lang/Object;
  #115 = Utf8               Bridge method of getConclusion
  #116 = Utf8               Lorg/kohsuke/github/GHCheckRun$Conclusion;
  #117 = Utf8               getName
  #118 = Utf8               ()Ljava/lang/String;
  #119 = NameAndType        #33:#31       // name:Ljava/lang/String;
  #120 = Fieldref           #2.#119       // org/kohsuke/github/GHCheckRun.name:Ljava/lang/String;
  #121 = Utf8               getHeadSha
  #122 = NameAndType        #34:#31       // headSha:Ljava/lang/String;
  #123 = Fieldref           #2.#122       // org/kohsuke/github/GHCheckRun.headSha:Ljava/lang/String;
  #124 = Utf8               getPullRequests
  #125 = Utf8               ()Ljava/util/List;
  #126 = Utf8               ()Ljava/util/List<Lorg/kohsuke/github/GHPullRequest;>;
  #127 = Utf8               java/io/IOException
  #128 = Class              #127          // java/io/IOException
  #129 = Utf8               getTitle
  #130 = NameAndType        #129:#118     // getTitle:()Ljava/lang/String;
  #131 = Methodref          #54.#130      // org/kohsuke/github/GHPullRequest.getTitle:()Ljava/lang/String;
  #132 = Utf8               refresh
  #133 = Utf8               (Ljava/lang/Object;)V
  #134 = NameAndType        #132:#133     // refresh:(Ljava/lang/Object;)V
  #135 = Methodref          #54.#134      // org/kohsuke/github/GHPullRequest.refresh:(Ljava/lang/Object;)V
  #136 = Utf8               java/util/Arrays
  #137 = Class              #136          // java/util/Arrays
  #138 = Utf8               asList
  #139 = Utf8               ([Ljava/lang/Object;)Ljava/util/List;
  #140 = NameAndType        #138:#139     // asList:([Ljava/lang/Object;)Ljava/util/List;
  #141 = Methodref          #137.#140     // java/util/Arrays.asList:([Ljava/lang/Object;)Ljava/util/List;
  #142 = Utf8               java/util/Collections
  #143 = Class              #142          // java/util/Collections
  #144 = Utf8               unmodifiableList
  #145 = Utf8               (Ljava/util/List;)Ljava/util/List;
  #146 = NameAndType        #144:#145     // unmodifiableList:(Ljava/util/List;)Ljava/util/List;
  #147 = Methodref          #143.#146     // java/util/Collections.unmodifiableList:(Ljava/util/List;)Ljava/util/List;
  #148 = Utf8               getHtmlUrl
  #149 = Utf8               ()Ljava/net/URL;
  #150 = NameAndType        #39:#31       // htmlUrl:Ljava/lang/String;
  #151 = Fieldref           #2.#150       // org/kohsuke/github/GHCheckRun.htmlUrl:Ljava/lang/String;
  #152 = Utf8               org/kohsuke/github/GitHubClient
  #153 = Class              #152          // org/kohsuke/github/GitHubClient
  #154 = Utf8               parseURL
  #155 = Utf8               (Ljava/lang/String;)Ljava/net/URL;
  #156 = NameAndType        #154:#155     // parseURL:(Ljava/lang/String;)Ljava/net/URL;
  #157 = Methodref          #153.#156     // org/kohsuke/github/GitHubClient.parseURL:(Ljava/lang/String;)Ljava/net/URL;
  #158 = Utf8               getNodeId
  #159 = NameAndType        #35:#31       // nodeId:Ljava/lang/String;
  #160 = Fieldref           #2.#159       // org/kohsuke/github/GHCheckRun.nodeId:Ljava/lang/String;
  #161 = Utf8               getExternalId
  #162 = NameAndType        #36:#31       // externalId:Ljava/lang/String;
  #163 = Fieldref           #2.#162       // org/kohsuke/github/GHCheckRun.externalId:Ljava/lang/String;
  #164 = Utf8               getDetailsUrl
  #165 = NameAndType        #40:#31       // detailsUrl:Ljava/lang/String;
  #166 = Fieldref           #2.#165       // org/kohsuke/github/GHCheckRun.detailsUrl:Ljava/lang/String;
  #167 = Utf8               getStartedAt
  #168 = Utf8               ()Ljava/util/Date;
  #169 = NameAndType        #37:#31       // startedAt:Ljava/lang/String;
  #170 = Fieldref           #2.#169       // org/kohsuke/github/GHCheckRun.startedAt:Ljava/lang/String;
  #171 = Utf8               parseDate
  #172 = Utf8               (Ljava/lang/String;)Ljava/util/Date;
  #173 = NameAndType        #171:#172     // parseDate:(Ljava/lang/String;)Ljava/util/Date;
  #174 = Methodref          #153.#173     // org/kohsuke/github/GitHubClient.parseDate:(Ljava/lang/String;)Ljava/util/Date;
  #175 = Utf8               getCompletedAt
  #176 = NameAndType        #38:#31       // completedAt:Ljava/lang/String;
  #177 = Fieldref           #2.#176       // org/kohsuke/github/GHCheckRun.completedAt:Ljava/lang/String;
  #178 = Utf8               getApp
  #179 = Utf8               ()Lorg/kohsuke/github/GHApp;
  #180 = Utf8               EI_EXPOSE_REP
  #181 = Utf8               Expected
  #182 = NameAndType        #43:#44       // app:Lorg/kohsuke/github/GHApp;
  #183 = Fieldref           #2.#182       // org/kohsuke/github/GHCheckRun.app:Lorg/kohsuke/github/GHApp;
  #184 = Utf8               getCheckSuite
  #185 = Utf8               ()Lorg/kohsuke/github/GHCheckSuite;
  #186 = Utf8               getOutput
  #187 = Utf8               ()Lorg/kohsuke/github/GHCheckRun$Output;
  #188 = NameAndType        #41:#42       // output:Lorg/kohsuke/github/GHCheckRun$Output;
  #189 = Fieldref           #2.#188       // org/kohsuke/github/GHCheckRun.output:Lorg/kohsuke/github/GHCheckRun$Output;
  #190 = Utf8               update
  #191 = Utf8               ()Lorg/kohsuke/github/GHCheckRunBuilder;
  #192 = Utf8               Lorg/kohsuke/github/Preview;
  #193 = Utf8               Lorg/kohsuke/github/internal/Previews;
  #194 = Utf8               ANTIOPE
  #195 = Utf8               Ledu/umd/cs/findbugs/annotations/NonNull;
  #196 = Utf8               org/kohsuke/github/GHCheckRunBuilder
  #197 = Class              #196          // org/kohsuke/github/GHCheckRunBuilder
  #198 = Utf8               getId
  #199 = Utf8               ()J
  #200 = NameAndType        #198:#199     // getId:()J
  #201 = Methodref          #2.#200       // org/kohsuke/github/GHCheckRun.getId:()J
  #202 = Utf8               (Lorg/kohsuke/github/GHRepository;J)V
  #203 = NameAndType        #49:#202      // "<init>":(Lorg/kohsuke/github/GHRepository;J)V
  #204 = Methodref          #197.#203     // org/kohsuke/github/GHCheckRunBuilder."<init>":(Lorg/kohsuke/github/GHRepository;J)V
  #205 = NameAndType        #89:#90       // getStatus:()Lorg/kohsuke/github/GHCheckRun$Status;
  #206 = Methodref          #2.#205       // org/kohsuke/github/GHCheckRun.getStatus:()Lorg/kohsuke/github/GHCheckRun$Status;
  #207 = Utf8               java/lang/String
  #208 = Class              #207          // java/lang/String
  #209 = NameAndType        #93:#100      // statusAsStr:(Lorg/kohsuke/github/GHCheckRun$Status;Ljava/lang/Class;)Ljava/lang/Object;
  #210 = Methodref          #2.#209       // org/kohsuke/github/GHCheckRun.statusAsStr:(Lorg/kohsuke/github/GHCheckRun$Status;Ljava/lang/Class;)Ljava/lang/Object;
  #211 = NameAndType        #106:#107     // getConclusion:()Lorg/kohsuke/github/GHCheckRun$Conclusion;
  #212 = Methodref          #2.#211       // org/kohsuke/github/GHCheckRun.getConclusion:()Lorg/kohsuke/github/GHCheckRun$Conclusion;
  #213 = NameAndType        #108:#114     // conclusionAsStr:(Lorg/kohsuke/github/GHCheckRun$Conclusion;Ljava/lang/Class;)Ljava/lang/Object;
  #214 = Methodref          #2.#213       // org/kohsuke/github/GHCheckRun.conclusionAsStr:(Lorg/kohsuke/github/GHCheckRun$Conclusion;Ljava/lang/Class;)Ljava/lang/Object;
  #215 = Utf8               RuntimeVisibleAnnotations
  #216 = Utf8               Code
  #217 = Utf8               LineNumberTable
  #218 = Utf8               LocalVariableTable
  #219 = Utf8               StackMapTable
  #220 = Utf8               RuntimeInvisibleAnnotations
  #221 = Utf8               Exceptions
  #222 = Utf8               Signature
  #223 = Utf8               InnerClasses
  #224 = Utf8               SourceFile
{
  org.kohsuke.github.GHRepository owner;
    descriptor: Lorg/kohsuke/github/GHRepository;
    flags: (0x0000)
    RuntimeVisibleAnnotations:
      0: #28(#7=s#29)
        com.fasterxml.jackson.annotation.JsonProperty(
          value="repository"
        )

  private java.lang.String status;
    descriptor: Ljava/lang/String;
    flags: (0x0002) ACC_PRIVATE

  private java.lang.String conclusion;
    descriptor: Ljava/lang/String;
    flags: (0x0002) ACC_PRIVATE

  private java.lang.String name;
    descriptor: Ljava/lang/String;
    flags: (0x0002) ACC_PRIVATE

  private java.lang.String headSha;
    descriptor: Ljava/lang/String;
    flags: (0x0002) ACC_PRIVATE

  private java.lang.String nodeId;
    descriptor: Ljava/lang/String;
    flags: (0x0002) ACC_PRIVATE

  private java.lang.String externalId;
    descriptor: Ljava/lang/String;
    flags: (0x0002) ACC_PRIVATE

  private java.lang.String startedAt;
    descriptor: Ljava/lang/String;
    flags: (0x0002) ACC_PRIVATE

  private java.lang.String completedAt;
    descriptor: Ljava/lang/String;
    flags: (0x0002) ACC_PRIVATE

  private java.lang.String htmlUrl;
    descriptor: Ljava/lang/String;
    flags: (0x0002) ACC_PRIVATE

  private java.lang.String detailsUrl;
    descriptor: Ljava/lang/String;
    flags: (0x0002) ACC_PRIVATE

  private org.kohsuke.github.GHCheckRun$Output output;
    descriptor: Lorg/kohsuke/github/GHCheckRun$Output;
    flags: (0x0002) ACC_PRIVATE

  private org.kohsuke.github.GHApp app;
    descriptor: Lorg/kohsuke/github/GHApp;
    flags: (0x0002) ACC_PRIVATE

  private org.kohsuke.github.GHPullRequest[] pullRequests;
    descriptor: [Lorg/kohsuke/github/GHPullRequest;
    flags: (0x0002) ACC_PRIVATE

  private org.kohsuke.github.GHCheckSuite checkSuite;
    descriptor: Lorg/kohsuke/github/GHCheckSuite;
    flags: (0x0002) ACC_PRIVATE

  public org.kohsuke.github.GHCheckRun();
    descriptor: ()V
    flags: (0x0001) ACC_PUBLIC
    Code:
      stack=2, locals=1, args_size=1
         0: aload_0
         1: invokespecial #52                 // Method org/kohsuke/github/GHObject."<init>":()V
         4: aload_0
         5: iconst_0
         6: anewarray     #54                 // class org/kohsuke/github/GHPullRequest
         9: putfield      #56                 // Field pullRequests:[Lorg/kohsuke/github/GHPullRequest;
        12: return
      LineNumberTable:
        line 25: 0
        line 42: 4
      LocalVariableTable:
        Start  Length  Slot  Name   Signature
            0      13     0  this   Lorg/kohsuke/github/GHCheckRun;

  org.kohsuke.github.GHCheckRun wrap(org.kohsuke.github.GHRepository);
    descriptor: (Lorg/kohsuke/github/GHRepository;)Lorg/kohsuke/github/GHCheckRun;
    flags: (0x0000)
    Code:
      stack=2, locals=2, args_size=2
         0: aload_0
         1: aload_1
         2: putfield      #62                 // Field owner:Lorg/kohsuke/github/GHRepository;
         5: aload_0
         6: aload_1
         7: invokevirtual #68                 // Method org/kohsuke/github/GHRepository.root:()Lorg/kohsuke/github/GitHub;
        10: invokevirtual #71                 // Method wrap:(Lorg/kohsuke/github/GitHub;)Lorg/kohsuke/github/GHCheckRun;
        13: pop
        14: aload_0
        15: areturn
      LineNumberTable:
        line 46: 0
        line 47: 5
        line 48: 14
      LocalVariableTable:
        Start  Length  Slot  Name   Signature
            0      16     0  this   Lorg/kohsuke/github/GHCheckRun;
            0      16     1 owner   Lorg/kohsuke/github/GHRepository;

  org.kohsuke.github.GHCheckRun wrap(org.kohsuke.github.GitHub);
    descriptor: (Lorg/kohsuke/github/GitHub;)Lorg/kohsuke/github/GHCheckRun;
    flags: (0x0000)
    Code:
      stack=2, locals=6, args_size=2
         0: aload_0
         1: getfield      #62                 // Field owner:Lorg/kohsuke/github/GHRepository;
         4: ifnull        46
         7: aload_0
         8: getfield      #56                 // Field pullRequests:[Lorg/kohsuke/github/GHPullRequest;
        11: astore_2
        12: aload_2
        13: arraylength
        14: istore_3
        15: iconst_0
        16: istore        4
        18: iload         4
        20: iload_3
        21: if_icmpge     46
        24: aload_2
        25: iload         4
        27: aaload
        28: astore        5
        30: aload         5
        32: aload_0
        33: getfield      #62                 // Field owner:Lorg/kohsuke/github/GHRepository;
        36: invokevirtual #75                 // Method org/kohsuke/github/GHPullRequest.wrap:(Lorg/kohsuke/github/GHRepository;)Lorg/kohsuke/github/GHIssue;
        39: pop
        40: iinc          4, 1
        43: goto          18
        46: aload_0
        47: getfield      #77                 // Field checkSuite:Lorg/kohsuke/github/GHCheckSuite;
        50: ifnull        84
        53: aload_0
        54: getfield      #62                 // Field owner:Lorg/kohsuke/github/GHRepository;
        57: ifnull        75
        60: aload_0
        61: getfield      #77                 // Field checkSuite:Lorg/kohsuke/github/GHCheckSuite;
        64: aload_0
        65: getfield      #62                 // Field owner:Lorg/kohsuke/github/GHRepository;
        68: invokevirtual #82                 // Method org/kohsuke/github/GHCheckSuite.wrap:(Lorg/kohsuke/github/GHRepository;)Lorg/kohsuke/github/GHCheckSuite;
        71: pop
        72: goto          84
        75: aload_0
        76: getfield      #77                 // Field checkSuite:Lorg/kohsuke/github/GHCheckSuite;
        79: aload_1
        80: invokevirtual #85                 // Method org/kohsuke/github/GHCheckSuite.wrap:(Lorg/kohsuke/github/GitHub;)Lorg/kohsuke/github/GHCheckSuite;
        83: pop
        84: aload_0
        85: areturn
      StackMapTable: number_of_entries = 4
        frame_type = 254 /* append */
          offset_delta = 18
          locals = [ class "[Lorg/kohsuke/github/GHPullRequest;", int, int ]
        frame_type = 248 /* chop */
          offset_delta = 27
        frame_type = 28 /* same */
        frame_type = 8 /* same */
      LineNumberTable:
        line 52: 0
        line 53: 7
        line 54: 30
        line 53: 40
        line 57: 46
        line 58: 53
        line 59: 60
        line 61: 75
        line 65: 84
      LocalVariableTable:
        Start  Length  Slot  Name   Signature
           30      10     5 singlePull   Lorg/kohsuke/github/GHPullRequest;
            0      86     0  this   Lorg/kohsuke/github/GHCheckRun;
            0      86     1  root   Lorg/kohsuke/github/GitHub;

  public org.kohsuke.github.GHCheckRun$Status getStatus();
    descriptor: ()Lorg/kohsuke/github/GHCheckRun$Status;
    flags: (0x0001) ACC_PUBLIC
    Code:
      stack=1, locals=1, args_size=1
         0: aload_0
         1: getfield      #95                 // Field status:Ljava/lang/String;
         4: invokestatic  #99                 // Method org/kohsuke/github/GHCheckRun$Status.from:(Ljava/lang/String;)Lorg/kohsuke/github/GHCheckRun$Status;
         7: areturn
      LineNumberTable:
        line 76: 0
      LocalVariableTable:
        Start  Length  Slot  Name   Signature
            0       8     0  this   Lorg/kohsuke/github/GHCheckRun;
    RuntimeInvisibleAnnotations:
      0: #91(#7=[c#31],#92=s#93)
        com.infradna.tool.bridge_method_injector.WithBridgeMethods(
          value=[class Ljava/lang/String;]
          adapterMethod="statusAsStr"
        )

  private java.lang.Object statusAsStr(org.kohsuke.github.GHCheckRun$Status, java.lang.Class);
    descriptor: (Lorg/kohsuke/github/GHCheckRun$Status;Ljava/lang/Class;)Ljava/lang/Object;
    flags: (0x0002) ACC_PRIVATE
    Code:
      stack=1, locals=3, args_size=3
         0: aload_1
         1: areturn
      LineNumberTable:
        line 81: 0
      LocalVariableTable:
        Start  Length  Slot  Name   Signature
            0       2     0  this   Lorg/kohsuke/github/GHCheckRun;
            0       2     1 status   Lorg/kohsuke/github/GHCheckRun$Status;
            0       2     2  type   Ljava/lang/Class;
    RuntimeInvisibleAnnotations:
      0: #6(#7=[s#101],#11=s#102)
        edu.umd.cs.findbugs.annotations.SuppressFBWarnings(
          value=["UPM_UNCALLED_PRIVATE_METHOD"]
          justification="Bridge method of getStatus"
        )

  public org.kohsuke.github.GHCheckRun$Conclusion getConclusion();
    descriptor: ()Lorg/kohsuke/github/GHCheckRun$Conclusion;
    flags: (0x0001) ACC_PUBLIC
    Code:
      stack=1, locals=1, args_size=1
         0: aload_0
         1: getfield      #110                // Field conclusion:Ljava/lang/String;
         4: invokestatic  #113                // Method org/kohsuke/github/GHCheckRun$Conclusion.from:(Ljava/lang/String;)Lorg/kohsuke/github/GHCheckRun$Conclusion;
         7: areturn
      LineNumberTable:
        line 105: 0
      LocalVariableTable:
        Start  Length  Slot  Name   Signature
            0       8     0  this   Lorg/kohsuke/github/GHCheckRun;
    RuntimeInvisibleAnnotations:
      0: #91(#7=[c#31],#92=s#108)
        com.infradna.tool.bridge_method_injector.WithBridgeMethods(
          value=[class Ljava/lang/String;]
          adapterMethod="conclusionAsStr"
        )

  private java.lang.Object conclusionAsStr(org.kohsuke.github.GHCheckRun$Conclusion, java.lang.Class);
    descriptor: (Lorg/kohsuke/github/GHCheckRun$Conclusion;Ljava/lang/Class;)Ljava/lang/Object;
    flags: (0x0002) ACC_PRIVATE
    Code:
      stack=1, locals=3, args_size=3
         0: aload_1
         1: areturn
      LineNumberTable:
        line 110: 0
      LocalVariableTable:
        Start  Length  Slot  Name   Signature
            0       2     0  this   Lorg/kohsuke/github/GHCheckRun;
            0       2     1 conclusion   Lorg/kohsuke/github/GHCheckRun$Conclusion;
            0       2     2  type   Ljava/lang/Class;
    RuntimeInvisibleAnnotations:
      0: #6(#7=[s#101],#11=s#115)
        edu.umd.cs.findbugs.annotations.SuppressFBWarnings(
          value=["UPM_UNCALLED_PRIVATE_METHOD"]
          justification="Bridge method of getConclusion"
        )

  public java.lang.String getName();
    descriptor: ()Ljava/lang/String;
    flags: (0x0001) ACC_PUBLIC
    Code:
      stack=1, locals=1, args_size=1
         0: aload_0
         1: getfield      #120                // Field name:Ljava/lang/String;
         4: areturn
      LineNumberTable:
        line 138: 0
      LocalVariableTable:
        Start  Length  Slot  Name   Signature
            0       5     0  this   Lorg/kohsuke/github/GHCheckRun;

  public java.lang.String getHeadSha();
    descriptor: ()Ljava/lang/String;
    flags: (0x0001) ACC_PUBLIC
    Code:
      stack=1, locals=1, args_size=1
         0: aload_0
         1: getfield      #123                // Field headSha:Ljava/lang/String;
         4: areturn
      LineNumberTable:
        line 147: 0
      LocalVariableTable:
        Start  Length  Slot  Name   Signature
            0       5     0  this   Lorg/kohsuke/github/GHCheckRun;

  public java.util.List<org.kohsuke.github.GHPullRequest> getPullRequests() throws java.io.IOException;
    descriptor: ()Ljava/util/List;
    flags: (0x0001) ACC_PUBLIC
    Code:
      stack=2, locals=5, args_size=1
         0: aload_0
         1: getfield      #56                 // Field pullRequests:[Lorg/kohsuke/github/GHPullRequest;
         4: astore_1
         5: aload_1
         6: arraylength
         7: istore_2
         8: iconst_0
         9: istore_3
        10: iload_3
        11: iload_2
        12: if_icmpge     36
        15: aload_1
        16: iload_3
        17: aaload
        18: astore        4
        20: aload         4
        22: aload         4
        24: invokevirtual #131                // Method org/kohsuke/github/GHPullRequest.getTitle:()Ljava/lang/String;
        27: invokevirtual #135                // Method org/kohsuke/github/GHPullRequest.refresh:(Ljava/lang/Object;)V
        30: iinc          3, 1
        33: goto          10
        36: aload_0
        37: getfield      #56                 // Field pullRequests:[Lorg/kohsuke/github/GHPullRequest;
        40: invokestatic  #141                // Method java/util/Arrays.asList:([Ljava/lang/Object;)Ljava/util/List;
        43: invokestatic  #147                // Method java/util/Collections.unmodifiableList:(Ljava/util/List;)Ljava/util/List;
        46: areturn
      StackMapTable: number_of_entries = 2
        frame_type = 254 /* append */
          offset_delta = 10
          locals = [ class "[Lorg/kohsuke/github/GHPullRequest;", int, int ]
        frame_type = 248 /* chop */
          offset_delta = 25
      LineNumberTable:
        line 161: 0
        line 163: 20
        line 161: 30
        line 165: 36
      LocalVariableTable:
        Start  Length  Slot  Name   Signature
           20      10     4 singlePull   Lorg/kohsuke/github/GHPullRequest;
            0      47     0  this   Lorg/kohsuke/github/GHCheckRun;
    Exceptions:
      throws java.io.IOException
    Signature: #126                         // ()Ljava/util/List<Lorg/kohsuke/github/GHPullRequest;>;

  public java.net.URL getHtmlUrl();
    descriptor: ()Ljava/net/URL;
    flags: (0x0001) ACC_PUBLIC
    Code:
      stack=1, locals=1, args_size=1
         0: aload_0
         1: getfield      #151                // Field htmlUrl:Ljava/lang/String;
         4: invokestatic  #157                // Method org/kohsuke/github/GitHubClient.parseURL:(Ljava/lang/String;)Ljava/net/URL;
         7: areturn
      LineNumberTable:
        line 176: 0
      LocalVariableTable:
        Start  Length  Slot  Name   Signature
            0       8     0  this   Lorg/kohsuke/github/GHCheckRun;

  public java.lang.String getNodeId();
    descriptor: ()Ljava/lang/String;
    flags: (0x0001) ACC_PUBLIC
    Code:
      stack=1, locals=1, args_size=1
         0: aload_0
         1: getfield      #160                // Field nodeId:Ljava/lang/String;
         4: areturn
      LineNumberTable:
        line 186: 0
      LocalVariableTable:
        Start  Length  Slot  Name   Signature
            0       5     0  this   Lorg/kohsuke/github/GHCheckRun;

  public java.lang.String getExternalId();
    descriptor: ()Ljava/lang/String;
    flags: (0x0001) ACC_PUBLIC
    Code:
      stack=1, locals=1, args_size=1
         0: aload_0
         1: getfield      #163                // Field externalId:Ljava/lang/String;
         4: areturn
      LineNumberTable:
        line 195: 0
      LocalVariableTable:
        Start  Length  Slot  Name   Signature
            0       5     0  this   Lorg/kohsuke/github/GHCheckRun;

  public java.net.URL getDetailsUrl();
    descriptor: ()Ljava/net/URL;
    flags: (0x0001) ACC_PUBLIC
    Code:
      stack=1, locals=1, args_size=1
         0: aload_0
         1: getfield      #166                // Field detailsUrl:Ljava/lang/String;
         4: invokestatic  #157                // Method org/kohsuke/github/GitHubClient.parseURL:(Ljava/lang/String;)Ljava/net/URL;
         7: areturn
      LineNumberTable:
        line 204: 0
      LocalVariableTable:
        Start  Length  Slot  Name   Signature
            0       8     0  this   Lorg/kohsuke/github/GHCheckRun;

  public java.util.Date getStartedAt();
    descriptor: ()Ljava/util/Date;
    flags: (0x0001) ACC_PUBLIC
    Code:
      stack=1, locals=1, args_size=1
         0: aload_0
         1: getfield      #170                // Field startedAt:Ljava/lang/String;
         4: invokestatic  #174                // Method org/kohsuke/github/GitHubClient.parseDate:(Ljava/lang/String;)Ljava/util/Date;
         7: areturn
      LineNumberTable:
        line 213: 0
      LocalVariableTable:
        Start  Length  Slot  Name   Signature
            0       8     0  this   Lorg/kohsuke/github/GHCheckRun;

  public java.util.Date getCompletedAt();
    descriptor: ()Ljava/util/Date;
    flags: (0x0001) ACC_PUBLIC
    Code:
      stack=1, locals=1, args_size=1
         0: aload_0
         1: getfield      #177                // Field completedAt:Ljava/lang/String;
         4: invokestatic  #174                // Method org/kohsuke/github/GitHubClient.parseDate:(Ljava/lang/String;)Ljava/util/Date;
         7: areturn
      LineNumberTable:
        line 222: 0
      LocalVariableTable:
        Start  Length  Slot  Name   Signature
            0       8     0  this   Lorg/kohsuke/github/GHCheckRun;

  public org.kohsuke.github.GHApp getApp();
    descriptor: ()Lorg/kohsuke/github/GHApp;
    flags: (0x0001) ACC_PUBLIC
    Code:
      stack=1, locals=1, args_size=1
         0: aload_0
         1: getfield      #183                // Field app:Lorg/kohsuke/github/GHApp;
         4: areturn
      LineNumberTable:
        line 232: 0
      LocalVariableTable:
        Start  Length  Slot  Name   Signature
            0       5     0  this   Lorg/kohsuke/github/GHCheckRun;
    RuntimeInvisibleAnnotations:
      0: #6(#7=[s#180],#11=s#181)
        edu.umd.cs.findbugs.annotations.SuppressFBWarnings(
          value=["EI_EXPOSE_REP"]
          justification="Expected"
        )

  public org.kohsuke.github.GHCheckSuite getCheckSuite();
    descriptor: ()Lorg/kohsuke/github/GHCheckSuite;
    flags: (0x0001) ACC_PUBLIC
    Code:
      stack=1, locals=1, args_size=1
         0: aload_0
         1: getfield      #77                 // Field checkSuite:Lorg/kohsuke/github/GHCheckSuite;
         4: areturn
      LineNumberTable:
        line 242: 0
      LocalVariableTable:
        Start  Length  Slot  Name   Signature
            0       5     0  this   Lorg/kohsuke/github/GHCheckRun;
    RuntimeInvisibleAnnotations:
      0: #6(#7=[s#180],#11=s#181)
        edu.umd.cs.findbugs.annotations.SuppressFBWarnings(
          value=["EI_EXPOSE_REP"]
          justification="Expected"
        )

  public org.kohsuke.github.GHCheckRun$Output getOutput();
    descriptor: ()Lorg/kohsuke/github/GHCheckRun$Output;
    flags: (0x0001) ACC_PUBLIC
    Code:
      stack=1, locals=1, args_size=1
         0: aload_0
         1: getfield      #189                // Field output:Lorg/kohsuke/github/GHCheckRun$Output;
         4: areturn
      LineNumberTable:
        line 252: 0
      LocalVariableTable:
        Start  Length  Slot  Name   Signature
            0       5     0  this   Lorg/kohsuke/github/GHCheckRun;
    RuntimeInvisibleAnnotations:
      0: #6(#7=[s#180],#11=s#181)
        edu.umd.cs.findbugs.annotations.SuppressFBWarnings(
          value=["EI_EXPOSE_REP"]
          justification="Expected"
        )

  public org.kohsuke.github.GHCheckRunBuilder update();
    descriptor: ()Lorg/kohsuke/github/GHCheckRunBuilder;
    flags: (0x0001) ACC_PUBLIC
    Code:
      stack=5, locals=1, args_size=1
         0: new           #197                // class org/kohsuke/github/GHCheckRunBuilder
         3: dup
         4: aload_0
         5: getfield      #62                 // Field owner:Lorg/kohsuke/github/GHRepository;
         8: aload_0
         9: invokevirtual #201                // Method getId:()J
        12: invokespecial #204                // Method org/kohsuke/github/GHCheckRunBuilder."<init>":(Lorg/kohsuke/github/GHRepository;J)V
        15: areturn
      LineNumberTable:
        line 324: 0
      LocalVariableTable:
        Start  Length  Slot  Name   Signature
            0      16     0  this   Lorg/kohsuke/github/GHCheckRun;
    RuntimeVisibleAnnotations:
      0: #192(#7=[e#193.#194])
        org.kohsuke.github.Preview(
          value=[Lorg/kohsuke/github/internal/Previews;.ANTIOPE]
        )
    RuntimeInvisibleAnnotations:
      0: #195()
        edu.umd.cs.findbugs.annotations.NonNull

  public java.lang.String getStatus();
    descriptor: ()Ljava/lang/String;
    flags: (0x1041) ACC_PUBLIC, ACC_BRIDGE, ACC_SYNTHETIC
    Code:
      stack=3, locals=1, args_size=1
         0: aload_0
         1: aload_0
         2: invokevirtual #206                // Method getStatus:()Lorg/kohsuke/github/GHCheckRun$Status;
         5: ldc           #208                // class java/lang/String
         7: invokevirtual #210                // Method statusAsStr:(Lorg/kohsuke/github/GHCheckRun$Status;Ljava/lang/Class;)Ljava/lang/Object;
        10: checkcast     #208                // class java/lang/String
        13: areturn

  public java.lang.String getConclusion();
    descriptor: ()Ljava/lang/String;
    flags: (0x1041) ACC_PUBLIC, ACC_BRIDGE, ACC_SYNTHETIC
    Code:
      stack=3, locals=1, args_size=1
         0: aload_0
         1: aload_0
         2: invokevirtual #212                // Method getConclusion:()Lorg/kohsuke/github/GHCheckRun$Conclusion;
         5: ldc           #208                // class java/lang/String
         7: invokevirtual #214                // Method conclusionAsStr:(Lorg/kohsuke/github/GHCheckRun$Conclusion;Ljava/lang/Class;)Ljava/lang/Object;
        10: checkcast     #208                // class java/lang/String
        13: areturn
}
InnerClasses:
  public static final #16= #15 of #2;     // AnnotationLevel=class org/kohsuke/github/GHCheckRun$AnnotationLevel of class org/kohsuke/github/GHCheckRun
  public static #19= #18 of #2;           // Output=class org/kohsuke/github/GHCheckRun$Output of class org/kohsuke/github/GHCheckRun
  public static final #22= #21 of #2;     // Conclusion=class org/kohsuke/github/GHCheckRun$Conclusion of class org/kohsuke/github/GHCheckRun
  public static final #25= #24 of #2;     // Status=class org/kohsuke/github/GHCheckRun$Status of class org/kohsuke/github/GHCheckRun
SourceFile: "GHCheckRun.java"
RuntimeInvisibleAnnotations:
  0: #6(#7=[s#8,s#9,s#10],#11=s#12)
    edu.umd.cs.findbugs.annotations.SuppressFBWarnings(
      value=["UWF_UNWRITTEN_FIELD","NP_UNWRITTEN_FIELD","URF_UNREAD_FIELD"]
      justification="JSON API"
    )
  1: #13()
    com.infradna.tool.bridge_method_injector.BridgeMethodsAdded
