Classfile /Users/mw/Projects/slang-braindump/.jar/jar11/assemble/slang-braindump/assemble/content/org/kohsuke/github/GHCheckRun$Output.class
  Last modified May 29, 2022; size 1085 bytes
  SHA-256 checksum b9c41087d71552d0b65d691c0c2ad33c60bea46e3631948e8b394ccad6df83a0
  Compiled from "GHCheckRun.java"
public class org.kohsuke.github.GHCheckRun$Output
  minor version: 0
  major version: 52
  flags: (0x0021) ACC_PUBLIC, ACC_SUPER
  this_class: #8                          // org/kohsuke/github/GHCheckRun$Output
  super_class: #9                         // java/lang/Object
  interfaces: 0, fields: 5, methods: 6, attributes: 2
Constant pool:
   #1 = Methodref          #9.#36         // java/lang/Object."<init>":()V
   #2 = Fieldref           #8.#37         // org/kohsuke/github/GHCheckRun$Output.title:Ljava/lang/String;
   #3 = Fieldref           #8.#38         // org/kohsuke/github/GHCheckRun$Output.summary:Ljava/lang/String;
   #4 = Fieldref           #8.#39         // org/kohsuke/github/GHCheckRun$Output.text:Ljava/lang/String;
   #5 = Fieldref           #8.#40         // org/kohsuke/github/GHCheckRun$Output.annotationsCount:I
   #6 = Fieldref           #8.#41         // org/kohsuke/github/GHCheckRun$Output.annotationsUrl:Ljava/lang/String;
   #7 = Methodref          #42.#43        // org/kohsuke/github/GitHubClient.parseURL:(Ljava/lang/String;)Ljava/net/URL;
   #8 = Class              #45            // org/kohsuke/github/GHCheckRun$Output
   #9 = Class              #46            // java/lang/Object
  #10 = Utf8               title
  #11 = Utf8               Ljava/lang/String;
  #12 = Utf8               summary
  #13 = Utf8               text
  #14 = Utf8               annotationsCount
  #15 = Utf8               I
  #16 = Utf8               annotationsUrl
  #17 = Utf8               <init>
  #18 = Utf8               ()V
  #19 = Utf8               Code
  #20 = Utf8               LineNumberTable
  #21 = Utf8               LocalVariableTable
  #22 = Utf8               this
  #23 = Utf8               Output
  #24 = Utf8               InnerClasses
  #25 = Utf8               Lorg/kohsuke/github/GHCheckRun$Output;
  #26 = Utf8               getTitle
  #27 = Utf8               ()Ljava/lang/String;
  #28 = Utf8               getSummary
  #29 = Utf8               getText
  #30 = Utf8               getAnnotationsCount
  #31 = Utf8               ()I
  #32 = Utf8               getAnnotationsUrl
  #33 = Utf8               ()Ljava/net/URL;
  #34 = Utf8               SourceFile
  #35 = Utf8               GHCheckRun.java
  #36 = NameAndType        #17:#18        // "<init>":()V
  #37 = NameAndType        #10:#11        // title:Ljava/lang/String;
  #38 = NameAndType        #12:#11        // summary:Ljava/lang/String;
  #39 = NameAndType        #13:#11        // text:Ljava/lang/String;
  #40 = NameAndType        #14:#15        // annotationsCount:I
  #41 = NameAndType        #16:#11        // annotationsUrl:Ljava/lang/String;
  #42 = Class              #47            // org/kohsuke/github/GitHubClient
  #43 = NameAndType        #48:#49        // parseURL:(Ljava/lang/String;)Ljava/net/URL;
  #44 = Class              #50            // org/kohsuke/github/GHCheckRun
  #45 = Utf8               org/kohsuke/github/GHCheckRun$Output
  #46 = Utf8               java/lang/Object
  #47 = Utf8               org/kohsuke/github/GitHubClient
  #48 = Utf8               parseURL
  #49 = Utf8               (Ljava/lang/String;)Ljava/net/URL;
  #50 = Utf8               org/kohsuke/github/GHCheckRun
{
  private java.lang.String title;
    descriptor: Ljava/lang/String;
    flags: (0x0002) ACC_PRIVATE

  private java.lang.String summary;
    descriptor: Ljava/lang/String;
    flags: (0x0002) ACC_PRIVATE

  private java.lang.String text;
    descriptor: Ljava/lang/String;
    flags: (0x0002) ACC_PRIVATE

  private int annotationsCount;
    descriptor: I
    flags: (0x0002) ACC_PRIVATE

  private java.lang.String annotationsUrl;
    descriptor: Ljava/lang/String;
    flags: (0x0002) ACC_PRIVATE

  public org.kohsuke.github.GHCheckRun$Output();
    descriptor: ()V
    flags: (0x0001) ACC_PUBLIC
    Code:
      stack=1, locals=1, args_size=1
         0: aload_0
         1: invokespecial #1                  // Method java/lang/Object."<init>":()V
         4: return
      LineNumberTable:
        line 260: 0
      LocalVariableTable:
        Start  Length  Slot  Name   Signature
            0       5     0  this   Lorg/kohsuke/github/GHCheckRun$Output;

  public java.lang.String getTitle();
    descriptor: ()Ljava/lang/String;
    flags: (0x0001) ACC_PUBLIC
    Code:
      stack=1, locals=1, args_size=1
         0: aload_0
         1: getfield      #2                  // Field title:Ljava/lang/String;
         4: areturn
      LineNumberTable:
        line 273: 0
      LocalVariableTable:
        Start  Length  Slot  Name   Signature
            0       5     0  this   Lorg/kohsuke/github/GHCheckRun$Output;

  public java.lang.String getSummary();
    descriptor: ()Ljava/lang/String;
    flags: (0x0001) ACC_PUBLIC
    Code:
      stack=1, locals=1, args_size=1
         0: aload_0
         1: getfield      #3                  // Field summary:Ljava/lang/String;
         4: areturn
      LineNumberTable:
        line 282: 0
      LocalVariableTable:
        Start  Length  Slot  Name   Signature
            0       5     0  this   Lorg/kohsuke/github/GHCheckRun$Output;

  public java.lang.String getText();
    descriptor: ()Ljava/lang/String;
    flags: (0x0001) ACC_PUBLIC
    Code:
      stack=1, locals=1, args_size=1
         0: aload_0
         1: getfield      #4                  // Field text:Ljava/lang/String;
         4: areturn
      LineNumberTable:
        line 291: 0
      LocalVariableTable:
        Start  Length  Slot  Name   Signature
            0       5     0  this   Lorg/kohsuke/github/GHCheckRun$Output;

  public int getAnnotationsCount();
    descriptor: ()I
    flags: (0x0001) ACC_PUBLIC
    Code:
      stack=1, locals=1, args_size=1
         0: aload_0
         1: getfield      #5                  // Field annotationsCount:I
         4: ireturn
      LineNumberTable:
        line 300: 0
      LocalVariableTable:
        Start  Length  Slot  Name   Signature
            0       5     0  this   Lorg/kohsuke/github/GHCheckRun$Output;

  public java.net.URL getAnnotationsUrl();
    descriptor: ()Ljava/net/URL;
    flags: (0x0001) ACC_PUBLIC
    Code:
      stack=1, locals=1, args_size=1
         0: aload_0
         1: getfield      #6                  // Field annotationsUrl:Ljava/lang/String;
         4: invokestatic  #7                  // Method org/kohsuke/github/GitHubClient.parseURL:(Ljava/lang/String;)Ljava/net/URL;
         7: areturn
      LineNumberTable:
        line 309: 0
      LocalVariableTable:
        Start  Length  Slot  Name   Signature
            0       8     0  this   Lorg/kohsuke/github/GHCheckRun$Output;
}
SourceFile: "GHCheckRun.java"
InnerClasses:
  public static #23= #8 of #44;           // Output=class org/kohsuke/github/GHCheckRun$Output of class org/kohsuke/github/GHCheckRun
