Classfile /Users/mw/Projects/slang-braindump/.jar/jar11/assemble/slang-braindump/assemble/content/org/kohsuke/github/GHCommitSearchBuilder$CommitSearchResult.class
  Last modified May 29, 2022; size 1596 bytes
  SHA-256 checksum 41e08e207efff2eb6b8012b6136c940e2a1da2160a5573d1d97fb6e1274c1def
  Compiled from "GHCommitSearchBuilder.java"
class org.kohsuke.github.GHCommitSearchBuilder$CommitSearchResult extends org.kohsuke.github.SearchResult<org.kohsuke.github.GHCommit>
  minor version: 0
  major version: 52
  flags: (0x0020) ACC_SUPER
  this_class: #9                          // org/kohsuke/github/GHCommitSearchBuilder$CommitSearchResult
  super_class: #10                        // org/kohsuke/github/SearchResult
  interfaces: 0, fields: 1, methods: 3, attributes: 3
Constant pool:
   #1 = Methodref          #10.#42        // org/kohsuke/github/SearchResult."<init>":()V
   #2 = Fieldref           #9.#43         // org/kohsuke/github/GHCommitSearchBuilder$CommitSearchResult.items:[Lorg/kohsuke/github/GHCommit;
   #3 = Fieldref           #35.#44        // org/kohsuke/github/GHCommit.url:Ljava/lang/String;
   #4 = Methodref          #45.#46        // org/kohsuke/github/GHCommitSearchBuilder.access$000:(Ljava/lang/String;)Ljava/lang/String;
   #5 = Methodref          #34.#47        // org/kohsuke/github/GitHub.getRepository:(Ljava/lang/String;)Lorg/kohsuke/github/GHRepository;
   #6 = Methodref          #35.#48        // org/kohsuke/github/GHCommit.wrapUp:(Lorg/kohsuke/github/GHRepository;)Lorg/kohsuke/github/GHCommit;
   #7 = Class              #49            // java/io/IOException
   #8 = Methodref          #9.#50         // org/kohsuke/github/GHCommitSearchBuilder$CommitSearchResult.getItems:(Lorg/kohsuke/github/GitHub;)[Lorg/kohsuke/github/GHCommit;
   #9 = Class              #51            // org/kohsuke/github/GHCommitSearchBuilder$CommitSearchResult
  #10 = Class              #52            // org/kohsuke/github/SearchResult
  #11 = Utf8               items
  #12 = Utf8               [Lorg/kohsuke/github/GHCommit;
  #13 = Utf8               <init>
  #14 = Utf8               ()V
  #15 = Utf8               Code
  #16 = Utf8               LineNumberTable
  #17 = Utf8               LocalVariableTable
  #18 = Utf8               this
  #19 = Utf8               CommitSearchResult
  #20 = Utf8               InnerClasses
  #21 = Utf8               Lorg/kohsuke/github/GHCommitSearchBuilder$CommitSearchResult;
  #22 = Utf8               getItems
  #23 = Utf8               (Lorg/kohsuke/github/GitHub;)[Lorg/kohsuke/github/GHCommit;
  #24 = Utf8               repo
  #25 = Utf8               Lorg/kohsuke/github/GHRepository;
  #26 = Utf8               repoName
  #27 = Utf8               Ljava/lang/String;
  #28 = Utf8               commit
  #29 = Utf8               Lorg/kohsuke/github/GHCommit;
  #30 = Utf8               root
  #31 = Utf8               Lorg/kohsuke/github/GitHub;
  #32 = Utf8               StackMapTable
  #33 = Class              #12            // "[Lorg/kohsuke/github/GHCommit;"
  #34 = Class              #53            // org/kohsuke/github/GitHub
  #35 = Class              #54            // org/kohsuke/github/GHCommit
  #36 = Class              #55            // java/lang/String
  #37 = Utf8               (Lorg/kohsuke/github/GitHub;)[Ljava/lang/Object;
  #38 = Utf8               Signature
  #39 = Utf8               Lorg/kohsuke/github/SearchResult<Lorg/kohsuke/github/GHCommit;>;
  #40 = Utf8               SourceFile
  #41 = Utf8               GHCommitSearchBuilder.java
  #42 = NameAndType        #13:#14        // "<init>":()V
  #43 = NameAndType        #11:#12        // items:[Lorg/kohsuke/github/GHCommit;
  #44 = NameAndType        #56:#27        // url:Ljava/lang/String;
  #45 = Class              #57            // org/kohsuke/github/GHCommitSearchBuilder
  #46 = NameAndType        #58:#59        // access$000:(Ljava/lang/String;)Ljava/lang/String;
  #47 = NameAndType        #60:#61        // getRepository:(Ljava/lang/String;)Lorg/kohsuke/github/GHRepository;
  #48 = NameAndType        #62:#63        // wrapUp:(Lorg/kohsuke/github/GHRepository;)Lorg/kohsuke/github/GHCommit;
  #49 = Utf8               java/io/IOException
  #50 = NameAndType        #22:#23        // getItems:(Lorg/kohsuke/github/GitHub;)[Lorg/kohsuke/github/GHCommit;
  #51 = Utf8               org/kohsuke/github/GHCommitSearchBuilder$CommitSearchResult
  #52 = Utf8               org/kohsuke/github/SearchResult
  #53 = Utf8               org/kohsuke/github/GitHub
  #54 = Utf8               org/kohsuke/github/GHCommit
  #55 = Utf8               java/lang/String
  #56 = Utf8               url
  #57 = Utf8               org/kohsuke/github/GHCommitSearchBuilder
  #58 = Utf8               access$000
  #59 = Utf8               (Ljava/lang/String;)Ljava/lang/String;
  #60 = Utf8               getRepository
  #61 = Utf8               (Ljava/lang/String;)Lorg/kohsuke/github/GHRepository;
  #62 = Utf8               wrapUp
  #63 = Utf8               (Lorg/kohsuke/github/GHRepository;)Lorg/kohsuke/github/GHCommit;
{
  private org.kohsuke.github.GHCommit[] items;
    descriptor: [Lorg/kohsuke/github/GHCommit;
    flags: (0x0002) ACC_PRIVATE

  private org.kohsuke.github.GHCommitSearchBuilder$CommitSearchResult();
    descriptor: ()V
    flags: (0x0002) ACC_PRIVATE
    Code:
      stack=1, locals=1, args_size=1
         0: aload_0
         1: invokespecial #1                  // Method org/kohsuke/github/SearchResult."<init>":()V
         4: return
      LineNumberTable:
        line 236: 0
      LocalVariableTable:
        Start  Length  Slot  Name   Signature
            0       5     0  this   Lorg/kohsuke/github/GHCommitSearchBuilder$CommitSearchResult;

  org.kohsuke.github.GHCommit[] getItems(org.kohsuke.github.GitHub);
    descriptor: (Lorg/kohsuke/github/GitHub;)[Lorg/kohsuke/github/GHCommit;
    flags: (0x0000)
    Code:
      stack=2, locals=8, args_size=2
         0: aload_0
         1: getfield      #2                  // Field items:[Lorg/kohsuke/github/GHCommit;
         4: astore_2
         5: aload_2
         6: arraylength
         7: istore_3
         8: iconst_0
         9: istore        4
        11: iload         4
        13: iload_3
        14: if_icmpge     60
        17: aload_2
        18: iload         4
        20: aaload
        21: astore        5
        23: aload         5
        25: getfield      #3                  // Field org/kohsuke/github/GHCommit.url:Ljava/lang/String;
        28: invokestatic  #4                  // Method org/kohsuke/github/GHCommitSearchBuilder.access$000:(Ljava/lang/String;)Ljava/lang/String;
        31: astore        6
        33: aload_1
        34: aload         6
        36: invokevirtual #5                  // Method org/kohsuke/github/GitHub.getRepository:(Ljava/lang/String;)Lorg/kohsuke/github/GHRepository;
        39: astore        7
        41: aload         5
        43: aload         7
        45: invokevirtual #6                  // Method org/kohsuke/github/GHCommit.wrapUp:(Lorg/kohsuke/github/GHRepository;)Lorg/kohsuke/github/GHCommit;
        48: pop
        49: goto          54
        52: astore        7
        54: iinc          4, 1
        57: goto          11
        60: aload_0
        61: getfield      #2                  // Field items:[Lorg/kohsuke/github/GHCommit;
        64: areturn
      Exception table:
         from    to  target type
            33    49    52   Class java/io/IOException
      LineNumberTable:
        line 241: 0
        line 242: 23
        line 244: 33
        line 245: 41
        line 247: 49
        line 246: 52
        line 241: 54
        line 249: 60
      LocalVariableTable:
        Start  Length  Slot  Name   Signature
           41       8     7  repo   Lorg/kohsuke/github/GHRepository;
           33      21     6 repoName   Ljava/lang/String;
           23      31     5 commit   Lorg/kohsuke/github/GHCommit;
            0      65     0  this   Lorg/kohsuke/github/GHCommitSearchBuilder$CommitSearchResult;
            0      65     1  root   Lorg/kohsuke/github/GitHub;
      StackMapTable: number_of_entries = 4
        frame_type = 254 /* append */
          offset_delta = 11
          locals = [ class "[Lorg/kohsuke/github/GHCommit;", int, int ]
        frame_type = 255 /* full_frame */
          offset_delta = 40
          locals = [ class org/kohsuke/github/GHCommitSearchBuilder$CommitSearchResult, class org/kohsuke/github/GitHub, class "[Lorg/kohsuke/github/GHCommit;", int, int, class org/kohsuke/github/GHCommit, class java/lang/String ]
          stack = [ class java/io/IOException ]
        frame_type = 249 /* chop */
          offset_delta = 1
        frame_type = 248 /* chop */
          offset_delta = 5

  java.lang.Object[] getItems(org.kohsuke.github.GitHub);
    descriptor: (Lorg/kohsuke/github/GitHub;)[Ljava/lang/Object;
    flags: (0x1040) ACC_BRIDGE, ACC_SYNTHETIC
    Code:
      stack=2, locals=2, args_size=2
         0: aload_0
         1: aload_1
         2: invokevirtual #8                  // Method getItems:(Lorg/kohsuke/github/GitHub;)[Lorg/kohsuke/github/GHCommit;
         5: areturn
      LineNumberTable:
        line 236: 0
      LocalVariableTable:
        Start  Length  Slot  Name   Signature
            0       6     0  this   Lorg/kohsuke/github/GHCommitSearchBuilder$CommitSearchResult;
}
Signature: #39                          // Lorg/kohsuke/github/SearchResult<Lorg/kohsuke/github/GHCommit;>;
SourceFile: "GHCommitSearchBuilder.java"
InnerClasses:
  private static #19= #9 of #45;          // CommitSearchResult=class org/kohsuke/github/GHCommitSearchBuilder$CommitSearchResult of class org/kohsuke/github/GHCommitSearchBuilder
