Classfile /Users/mw/Projects/slang-braindump/.jar/jar11/assemble/slang-braindump/assemble/content/org/kohsuke/github/GHCompare$1.class
  Last modified May 29, 2022; size 1390 bytes
  SHA-256 checksum ab37f3c2e0b27b1773cfe0e5b9dcedac293a19ba27d46f863377464905c118b8
  Compiled from "GHCompare.java"
class org.kohsuke.github.GHCompare$1 extends org.kohsuke.github.PagedIterable<org.kohsuke.github.GHCompare$Commit>
  minor version: 0
  major version: 52
  flags: (0x0020) ACC_SUPER
  this_class: #8                          // org/kohsuke/github/GHCompare$1
  super_class: #9                         // org/kohsuke/github/PagedIterable
  interfaces: 0, fields: 1, methods: 2, attributes: 4
Constant pool:
   #1 = Fieldref           #8.#36         // org/kohsuke/github/GHCompare$1.this$0:Lorg/kohsuke/github/GHCompare;
   #2 = Methodref          #9.#37         // org/kohsuke/github/PagedIterable."<init>":()V
   #3 = Class              #38            // org/kohsuke/github/PagedIterator
   #4 = Methodref          #34.#39        // org/kohsuke/github/GHCompare.access$000:(Lorg/kohsuke/github/GHCompare;)[Lorg/kohsuke/github/GHCompare$Commit;
   #5 = Methodref          #40.#41        // java/util/Collections.singleton:(Ljava/lang/Object;)Ljava/util/Set;
   #6 = InterfaceMethodref #42.#43        // java/util/Set.iterator:()Ljava/util/Iterator;
   #7 = Methodref          #3.#44         // org/kohsuke/github/PagedIterator."<init>":(Ljava/util/Iterator;Ljava/util/function/Consumer;)V
   #8 = Class              #45            // org/kohsuke/github/GHCompare$1
   #9 = Class              #46            // org/kohsuke/github/PagedIterable
  #10 = Utf8               this$0
  #11 = Utf8               Lorg/kohsuke/github/GHCompare;
  #12 = Utf8               <init>
  #13 = Utf8               (Lorg/kohsuke/github/GHCompare;)V
  #14 = Utf8               Code
  #15 = Utf8               LineNumberTable
  #16 = Utf8               LocalVariableTable
  #17 = Utf8               this
  #18 = Utf8               InnerClasses
  #19 = Utf8               Lorg/kohsuke/github/GHCompare$1;
  #20 = Utf8               _iterator
  #21 = Utf8               (I)Lorg/kohsuke/github/PagedIterator;
  #22 = Utf8               pageSize
  #23 = Utf8               I
  #24 = Utf8               Signature
  #25 = Class              #47            // org/kohsuke/github/GHCompare$Commit
  #26 = Utf8               Commit
  #27 = Utf8               (I)Lorg/kohsuke/github/PagedIterator<Lorg/kohsuke/github/GHCompare$Commit;>;
  #28 = Utf8               RuntimeVisibleAnnotations
  #29 = Utf8               Ljavax/annotation/Nonnull;
  #30 = Utf8               Lorg/kohsuke/github/PagedIterable<Lorg/kohsuke/github/GHCompare$Commit;>;
  #31 = Utf8               SourceFile
  #32 = Utf8               GHCompare.java
  #33 = Utf8               EnclosingMethod
  #34 = Class              #48            // org/kohsuke/github/GHCompare
  #35 = NameAndType        #49:#50        // listCommits:()Lorg/kohsuke/github/PagedIterable;
  #36 = NameAndType        #10:#11        // this$0:Lorg/kohsuke/github/GHCompare;
  #37 = NameAndType        #12:#51        // "<init>":()V
  #38 = Utf8               org/kohsuke/github/PagedIterator
  #39 = NameAndType        #52:#53        // access$000:(Lorg/kohsuke/github/GHCompare;)[Lorg/kohsuke/github/GHCompare$Commit;
  #40 = Class              #54            // java/util/Collections
  #41 = NameAndType        #55:#56        // singleton:(Ljava/lang/Object;)Ljava/util/Set;
  #42 = Class              #57            // java/util/Set
  #43 = NameAndType        #58:#59        // iterator:()Ljava/util/Iterator;
  #44 = NameAndType        #12:#60        // "<init>":(Ljava/util/Iterator;Ljava/util/function/Consumer;)V
  #45 = Utf8               org/kohsuke/github/GHCompare$1
  #46 = Utf8               org/kohsuke/github/PagedIterable
  #47 = Utf8               org/kohsuke/github/GHCompare$Commit
  #48 = Utf8               org/kohsuke/github/GHCompare
  #49 = Utf8               listCommits
  #50 = Utf8               ()Lorg/kohsuke/github/PagedIterable;
  #51 = Utf8               ()V
  #52 = Utf8               access$000
  #53 = Utf8               (Lorg/kohsuke/github/GHCompare;)[Lorg/kohsuke/github/GHCompare$Commit;
  #54 = Utf8               java/util/Collections
  #55 = Utf8               singleton
  #56 = Utf8               (Ljava/lang/Object;)Ljava/util/Set;
  #57 = Utf8               java/util/Set
  #58 = Utf8               iterator
  #59 = Utf8               ()Ljava/util/Iterator;
  #60 = Utf8               (Ljava/util/Iterator;Ljava/util/function/Consumer;)V
{
  final org.kohsuke.github.GHCompare this$0;
    descriptor: Lorg/kohsuke/github/GHCompare;
    flags: (0x1010) ACC_FINAL, ACC_SYNTHETIC

  org.kohsuke.github.GHCompare$1(org.kohsuke.github.GHCompare);
    descriptor: (Lorg/kohsuke/github/GHCompare;)V
    flags: (0x0000)
    Code:
      stack=2, locals=2, args_size=2
         0: aload_0
         1: aload_1
         2: putfield      #1                  // Field this$0:Lorg/kohsuke/github/GHCompare;
         5: aload_0
         6: invokespecial #2                  // Method org/kohsuke/github/PagedIterable."<init>":()V
         9: return
      LineNumberTable:
        line 175: 0
      LocalVariableTable:
        Start  Length  Slot  Name   Signature
            0      10     0  this   Lorg/kohsuke/github/GHCompare$1;
            0      10     1 this$0   Lorg/kohsuke/github/GHCompare;

  public org.kohsuke.github.PagedIterator<org.kohsuke.github.GHCompare$Commit> _iterator(int);
    descriptor: (I)Lorg/kohsuke/github/PagedIterator;
    flags: (0x0001) ACC_PUBLIC
    Code:
      stack=4, locals=2, args_size=2
         0: new           #3                  // class org/kohsuke/github/PagedIterator
         3: dup
         4: aload_0
         5: getfield      #1                  // Field this$0:Lorg/kohsuke/github/GHCompare;
         8: invokestatic  #4                  // Method org/kohsuke/github/GHCompare.access$000:(Lorg/kohsuke/github/GHCompare;)[Lorg/kohsuke/github/GHCompare$Commit;
        11: invokestatic  #5                  // Method java/util/Collections.singleton:(Ljava/lang/Object;)Ljava/util/Set;
        14: invokeinterface #6,  1            // InterfaceMethod java/util/Set.iterator:()Ljava/util/Iterator;
        19: aconst_null
        20: invokespecial #7                  // Method org/kohsuke/github/PagedIterator."<init>":(Ljava/util/Iterator;Ljava/util/function/Consumer;)V
        23: areturn
      LineNumberTable:
        line 179: 0
      LocalVariableTable:
        Start  Length  Slot  Name   Signature
            0      24     0  this   Lorg/kohsuke/github/GHCompare$1;
            0      24     1 pageSize   I
    Signature: #27                          // (I)Lorg/kohsuke/github/PagedIterator<Lorg/kohsuke/github/GHCompare$Commit;>;
    RuntimeVisibleAnnotations:
      0: #29()
        javax.annotation.Nonnull
}
Signature: #30                          // Lorg/kohsuke/github/PagedIterable<Lorg/kohsuke/github/GHCompare$Commit;>;
SourceFile: "GHCompare.java"
EnclosingMethod: #34.#35                // org.kohsuke.github.GHCompare.listCommits
InnerClasses:
  #8;                                     // class org/kohsuke/github/GHCompare$1
  public static #26= #25 of #34;          // Commit=class org/kohsuke/github/GHCompare$Commit of class org/kohsuke/github/GHCompare
