Classfile /Users/mw/Projects/slang-braindump/.jar/jar11/assemble/slang-braindump/assemble/content/org/kohsuke/github/GHContentSearchBuilder$ContentSearchResult.class
  Last modified May 29, 2022; size 937 bytes
  SHA-256 checksum 178e81f9f19d9c2e54eb7b8bdc5e191cc600d9f8b2273c4813b60e4e5bb2bb75
  Compiled from "GHContentSearchBuilder.java"
class org.kohsuke.github.GHContentSearchBuilder$ContentSearchResult extends org.kohsuke.github.SearchResult<org.kohsuke.github.GHContent>
  minor version: 0
  major version: 52
  flags: (0x0020) ACC_SUPER
  this_class: #4                          // org/kohsuke/github/GHContentSearchBuilder$ContentSearchResult
  super_class: #5                         // org/kohsuke/github/SearchResult
  interfaces: 0, fields: 1, methods: 3, attributes: 3
Constant pool:
   #1 = Methodref          #5.#26         // org/kohsuke/github/SearchResult."<init>":()V
   #2 = Fieldref           #4.#27         // org/kohsuke/github/GHContentSearchBuilder$ContentSearchResult.items:[Lorg/kohsuke/github/GHContent;
   #3 = Methodref          #4.#28         // org/kohsuke/github/GHContentSearchBuilder$ContentSearchResult.getItems:(Lorg/kohsuke/github/GitHub;)[Lorg/kohsuke/github/GHContent;
   #4 = Class              #30            // org/kohsuke/github/GHContentSearchBuilder$ContentSearchResult
   #5 = Class              #31            // org/kohsuke/github/SearchResult
   #6 = Utf8               items
   #7 = Utf8               [Lorg/kohsuke/github/GHContent;
   #8 = Utf8               <init>
   #9 = Utf8               ()V
  #10 = Utf8               Code
  #11 = Utf8               LineNumberTable
  #12 = Utf8               LocalVariableTable
  #13 = Utf8               this
  #14 = Utf8               ContentSearchResult
  #15 = Utf8               InnerClasses
  #16 = Utf8               Lorg/kohsuke/github/GHContentSearchBuilder$ContentSearchResult;
  #17 = Utf8               getItems
  #18 = Utf8               (Lorg/kohsuke/github/GitHub;)[Lorg/kohsuke/github/GHContent;
  #19 = Utf8               root
  #20 = Utf8               Lorg/kohsuke/github/GitHub;
  #21 = Utf8               (Lorg/kohsuke/github/GitHub;)[Ljava/lang/Object;
  #22 = Utf8               Signature
  #23 = Utf8               Lorg/kohsuke/github/SearchResult<Lorg/kohsuke/github/GHContent;>;
  #24 = Utf8               SourceFile
  #25 = Utf8               GHContentSearchBuilder.java
  #26 = NameAndType        #8:#9          // "<init>":()V
  #27 = NameAndType        #6:#7          // items:[Lorg/kohsuke/github/GHContent;
  #28 = NameAndType        #17:#18        // getItems:(Lorg/kohsuke/github/GitHub;)[Lorg/kohsuke/github/GHContent;
  #29 = Class              #32            // org/kohsuke/github/GHContentSearchBuilder
  #30 = Utf8               org/kohsuke/github/GHContentSearchBuilder$ContentSearchResult
  #31 = Utf8               org/kohsuke/github/SearchResult
  #32 = Utf8               org/kohsuke/github/GHContentSearchBuilder
{
  private org.kohsuke.github.GHContent[] items;
    descriptor: [Lorg/kohsuke/github/GHContent;
    flags: (0x0002) ACC_PRIVATE

  private org.kohsuke.github.GHContentSearchBuilder$ContentSearchResult();
    descriptor: ()V
    flags: (0x0002) ACC_PRIVATE
    Code:
      stack=1, locals=1, args_size=1
         0: aload_0
         1: invokespecial #1                  // Method org/kohsuke/github/SearchResult."<init>":()V
         4: return
      LineNumberTable:
        line 184: 0
      LocalVariableTable:
        Start  Length  Slot  Name   Signature
            0       5     0  this   Lorg/kohsuke/github/GHContentSearchBuilder$ContentSearchResult;

  org.kohsuke.github.GHContent[] getItems(org.kohsuke.github.GitHub);
    descriptor: (Lorg/kohsuke/github/GitHub;)[Lorg/kohsuke/github/GHContent;
    flags: (0x0000)
    Code:
      stack=1, locals=2, args_size=2
         0: aload_0
         1: getfield      #2                  // Field items:[Lorg/kohsuke/github/GHContent;
         4: areturn
      LineNumberTable:
        line 189: 0
      LocalVariableTable:
        Start  Length  Slot  Name   Signature
            0       5     0  this   Lorg/kohsuke/github/GHContentSearchBuilder$ContentSearchResult;
            0       5     1  root   Lorg/kohsuke/github/GitHub;

  java.lang.Object[] getItems(org.kohsuke.github.GitHub);
    descriptor: (Lorg/kohsuke/github/GitHub;)[Ljava/lang/Object;
    flags: (0x1040) ACC_BRIDGE, ACC_SYNTHETIC
    Code:
      stack=2, locals=2, args_size=2
         0: aload_0
         1: aload_1
         2: invokevirtual #3                  // Method getItems:(Lorg/kohsuke/github/GitHub;)[Lorg/kohsuke/github/GHContent;
         5: areturn
      LineNumberTable:
        line 184: 0
      LocalVariableTable:
        Start  Length  Slot  Name   Signature
            0       6     0  this   Lorg/kohsuke/github/GHContentSearchBuilder$ContentSearchResult;
}
Signature: #23                          // Lorg/kohsuke/github/SearchResult<Lorg/kohsuke/github/GHContent;>;
SourceFile: "GHContentSearchBuilder.java"
InnerClasses:
  private static #14= #4 of #29;          // ContentSearchResult=class org/kohsuke/github/GHContentSearchBuilder$ContentSearchResult of class org/kohsuke/github/GHContentSearchBuilder
