Classfile /Users/mw/Projects/slang-braindump/.jar/jar11/assemble/slang-braindump/assemble/content/org/kohsuke/github/GHCommitPointer.class
  Last modified May 29, 2022; size 1702 bytes
  SHA-256 checksum 6f0e105b88e6ffc07ddae9f2b2daa30f0fc2007a7ccfd96eca1f3d47210266e0
  Compiled from "GHCommitPointer.java"
public class org.kohsuke.github.GHCommitPointer
  minor version: 0
  major version: 52
  flags: (0x0021) ACC_PUBLIC, ACC_SUPER
  this_class: #12                         // org/kohsuke/github/GHCommitPointer
  super_class: #13                        // java/lang/Object
  interfaces: 0, fields: 5, methods: 7, attributes: 1
Constant pool:
   #1 = Methodref          #13.#50        // java/lang/Object."<init>":()V
   #2 = Fieldref           #12.#51        // org/kohsuke/github/GHCommitPointer.user:Lorg/kohsuke/github/GHUser;
   #3 = Methodref          #52.#53        // org/kohsuke/github/GHUser.root:()Lorg/kohsuke/github/GitHub;
   #4 = Methodref          #54.#55        // org/kohsuke/github/GitHub.intern:(Lorg/kohsuke/github/GHUser;)Lorg/kohsuke/github/GHUser;
   #5 = Fieldref           #12.#56        // org/kohsuke/github/GHCommitPointer.repo:Lorg/kohsuke/github/GHRepository;
   #6 = Fieldref           #12.#57        // org/kohsuke/github/GHCommitPointer.ref:Ljava/lang/String;
   #7 = Fieldref           #12.#58        // org/kohsuke/github/GHCommitPointer.sha:Ljava/lang/String;
   #8 = Fieldref           #12.#59        // org/kohsuke/github/GHCommitPointer.label:Ljava/lang/String;
   #9 = Methodref          #12.#60        // org/kohsuke/github/GHCommitPointer.getRepository:()Lorg/kohsuke/github/GHRepository;
  #10 = Methodref          #12.#61        // org/kohsuke/github/GHCommitPointer.getSha:()Ljava/lang/String;
  #11 = Methodref          #62.#63        // org/kohsuke/github/GHRepository.getCommit:(Ljava/lang/String;)Lorg/kohsuke/github/GHCommit;
  #12 = Class              #64            // org/kohsuke/github/GHCommitPointer
  #13 = Class              #65            // java/lang/Object
  #14 = Utf8               ref
  #15 = Utf8               Ljava/lang/String;
  #16 = Utf8               sha
  #17 = Utf8               label
  #18 = Utf8               user
  #19 = Utf8               Lorg/kohsuke/github/GHUser;
  #20 = Utf8               repo
  #21 = Utf8               Lorg/kohsuke/github/GHRepository;
  #22 = Utf8               <init>
  #23 = Utf8               ()V
  #24 = Utf8               Code
  #25 = Utf8               LineNumberTable
  #26 = Utf8               LocalVariableTable
  #27 = Utf8               this
  #28 = Utf8               Lorg/kohsuke/github/GHCommitPointer;
  #29 = Utf8               getUser
  #30 = Utf8               ()Lorg/kohsuke/github/GHUser;
  #31 = Utf8               StackMapTable
  #32 = Utf8               Exceptions
  #33 = Class              #66            // java/io/IOException
  #34 = Utf8               RuntimeInvisibleAnnotations
  #35 = Utf8               Ledu/umd/cs/findbugs/annotations/SuppressFBWarnings;
  #36 = Utf8               value
  #37 = Utf8               EI_EXPOSE_REP
  #38 = Utf8               justification
  #39 = Utf8               Expected behavior
  #40 = Utf8               getRepository
  #41 = Utf8               ()Lorg/kohsuke/github/GHRepository;
  #42 = Utf8               getRef
  #43 = Utf8               ()Ljava/lang/String;
  #44 = Utf8               getSha
  #45 = Utf8               getLabel
  #46 = Utf8               getCommit
  #47 = Utf8               ()Lorg/kohsuke/github/GHCommit;
  #48 = Utf8               SourceFile
  #49 = Utf8               GHCommitPointer.java
  #50 = NameAndType        #22:#23        // "<init>":()V
  #51 = NameAndType        #18:#19        // user:Lorg/kohsuke/github/GHUser;
  #52 = Class              #67            // org/kohsuke/github/GHUser
  #53 = NameAndType        #68:#69        // root:()Lorg/kohsuke/github/GitHub;
  #54 = Class              #70            // org/kohsuke/github/GitHub
  #55 = NameAndType        #71:#72        // intern:(Lorg/kohsuke/github/GHUser;)Lorg/kohsuke/github/GHUser;
  #56 = NameAndType        #20:#21        // repo:Lorg/kohsuke/github/GHRepository;
  #57 = NameAndType        #14:#15        // ref:Ljava/lang/String;
  #58 = NameAndType        #16:#15        // sha:Ljava/lang/String;
  #59 = NameAndType        #17:#15        // label:Ljava/lang/String;
  #60 = NameAndType        #40:#41        // getRepository:()Lorg/kohsuke/github/GHRepository;
  #61 = NameAndType        #44:#43        // getSha:()Ljava/lang/String;
  #62 = Class              #73            // org/kohsuke/github/GHRepository
  #63 = NameAndType        #46:#74        // getCommit:(Ljava/lang/String;)Lorg/kohsuke/github/GHCommit;
  #64 = Utf8               org/kohsuke/github/GHCommitPointer
  #65 = Utf8               java/lang/Object
  #66 = Utf8               java/io/IOException
  #67 = Utf8               org/kohsuke/github/GHUser
  #68 = Utf8               root
  #69 = Utf8               ()Lorg/kohsuke/github/GitHub;
  #70 = Utf8               org/kohsuke/github/GitHub
  #71 = Utf8               intern
  #72 = Utf8               (Lorg/kohsuke/github/GHUser;)Lorg/kohsuke/github/GHUser;
  #73 = Utf8               org/kohsuke/github/GHRepository
  #74 = Utf8               (Ljava/lang/String;)Lorg/kohsuke/github/GHCommit;
{
  private java.lang.String ref;
    descriptor: Ljava/lang/String;
    flags: (0x0002) ACC_PRIVATE

  private java.lang.String sha;
    descriptor: Ljava/lang/String;
    flags: (0x0002) ACC_PRIVATE

  private java.lang.String label;
    descriptor: Ljava/lang/String;
    flags: (0x0002) ACC_PRIVATE

  private org.kohsuke.github.GHUser user;
    descriptor: Lorg/kohsuke/github/GHUser;
    flags: (0x0002) ACC_PRIVATE

  private org.kohsuke.github.GHRepository repo;
    descriptor: Lorg/kohsuke/github/GHRepository;
    flags: (0x0002) ACC_PRIVATE

  public org.kohsuke.github.GHCommitPointer();
    descriptor: ()V
    flags: (0x0001) ACC_PUBLIC
    Code:
      stack=1, locals=1, args_size=1
         0: aload_0
         1: invokespecial #1                  // Method java/lang/Object."<init>":()V
         4: return
      LineNumberTable:
        line 35: 0
      LocalVariableTable:
        Start  Length  Slot  Name   Signature
            0       5     0  this   Lorg/kohsuke/github/GHCommitPointer;

  public org.kohsuke.github.GHUser getUser() throws java.io.IOException;
    descriptor: ()Lorg/kohsuke/github/GHUser;
    flags: (0x0001) ACC_PUBLIC
    Code:
      stack=2, locals=1, args_size=1
         0: aload_0
         1: getfield      #2                  // Field user:Lorg/kohsuke/github/GHUser;
         4: ifnull        22
         7: aload_0
         8: getfield      #2                  // Field user:Lorg/kohsuke/github/GHUser;
        11: invokevirtual #3                  // Method org/kohsuke/github/GHUser.root:()Lorg/kohsuke/github/GitHub;
        14: aload_0
        15: getfield      #2                  // Field user:Lorg/kohsuke/github/GHUser;
        18: invokevirtual #4                  // Method org/kohsuke/github/GitHub.intern:(Lorg/kohsuke/github/GHUser;)Lorg/kohsuke/github/GHUser;
        21: areturn
        22: aload_0
        23: getfield      #2                  // Field user:Lorg/kohsuke/github/GHUser;
        26: areturn
      LineNumberTable:
        line 49: 0
        line 50: 7
        line 51: 22
      LocalVariableTable:
        Start  Length  Slot  Name   Signature
            0      27     0  this   Lorg/kohsuke/github/GHCommitPointer;
      StackMapTable: number_of_entries = 1
        frame_type = 22 /* same */
    Exceptions:
      throws java.io.IOException
    RuntimeInvisibleAnnotations:
      0: #35(#36=[s#37],#38=s#39)
        edu.umd.cs.findbugs.annotations.SuppressFBWarnings(
          value=["EI_EXPOSE_REP"]
          justification="Expected behavior"
        )

  public org.kohsuke.github.GHRepository getRepository();
    descriptor: ()Lorg/kohsuke/github/GHRepository;
    flags: (0x0001) ACC_PUBLIC
    Code:
      stack=1, locals=1, args_size=1
         0: aload_0
         1: getfield      #5                  // Field repo:Lorg/kohsuke/github/GHRepository;
         4: areturn
      LineNumberTable:
        line 61: 0
      LocalVariableTable:
        Start  Length  Slot  Name   Signature
            0       5     0  this   Lorg/kohsuke/github/GHCommitPointer;
    RuntimeInvisibleAnnotations:
      0: #35(#36=[s#37],#38=s#39)
        edu.umd.cs.findbugs.annotations.SuppressFBWarnings(
          value=["EI_EXPOSE_REP"]
          justification="Expected behavior"
        )

  public java.lang.String getRef();
    descriptor: ()Ljava/lang/String;
    flags: (0x0001) ACC_PUBLIC
    Code:
      stack=1, locals=1, args_size=1
         0: aload_0
         1: getfield      #6                  // Field ref:Ljava/lang/String;
         4: areturn
      LineNumberTable:
        line 70: 0
      LocalVariableTable:
        Start  Length  Slot  Name   Signature
            0       5     0  this   Lorg/kohsuke/github/GHCommitPointer;

  public java.lang.String getSha();
    descriptor: ()Ljava/lang/String;
    flags: (0x0001) ACC_PUBLIC
    Code:
      stack=1, locals=1, args_size=1
         0: aload_0
         1: getfield      #7                  // Field sha:Ljava/lang/String;
         4: areturn
      LineNumberTable:
        line 79: 0
      LocalVariableTable:
        Start  Length  Slot  Name   Signature
            0       5     0  this   Lorg/kohsuke/github/GHCommitPointer;

  public java.lang.String getLabel();
    descriptor: ()Ljava/lang/String;
    flags: (0x0001) ACC_PUBLIC
    Code:
      stack=1, locals=1, args_size=1
         0: aload_0
         1: getfield      #8                  // Field label:Ljava/lang/String;
         4: areturn
      LineNumberTable:
        line 88: 0
      LocalVariableTable:
        Start  Length  Slot  Name   Signature
            0       5     0  this   Lorg/kohsuke/github/GHCommitPointer;

  public org.kohsuke.github.GHCommit getCommit() throws java.io.IOException;
    descriptor: ()Lorg/kohsuke/github/GHCommit;
    flags: (0x0001) ACC_PUBLIC
    Code:
      stack=2, locals=1, args_size=1
         0: aload_0
         1: invokevirtual #9                  // Method getRepository:()Lorg/kohsuke/github/GHRepository;
         4: aload_0
         5: invokevirtual #10                 // Method getSha:()Ljava/lang/String;
         8: invokevirtual #11                 // Method org/kohsuke/github/GHRepository.getCommit:(Ljava/lang/String;)Lorg/kohsuke/github/GHCommit;
        11: areturn
      LineNumberTable:
        line 99: 0
      LocalVariableTable:
        Start  Length  Slot  Name   Signature
            0      12     0  this   Lorg/kohsuke/github/GHCommitPointer;
    Exceptions:
      throws java.io.IOException
}
SourceFile: "GHCommitPointer.java"
