Classfile /Users/mw/Projects/slang-braindump/.jar/jar11/assemble/slang-braindump/assemble/content/org/kohsuke/github/GHCompare.class
  Last modified May 29, 2022; size 5099 bytes
  SHA-256 checksum 237f2eec042c816855f5aa70d94f266b2da00495568212ab0a97c8f2a3267420
  Compiled from "GHCompare.java"
public class org.kohsuke.github.GHCompare
  minor version: 0
  major version: 52
  flags: (0x0021) ACC_PUBLIC, ACC_SUPER
  this_class: #36                         // org/kohsuke/github/GHCompare
  super_class: #37                        // java/lang/Object
  interfaces: 0, fields: 15, methods: 21, attributes: 2
Constant pool:
    #1 = Fieldref           #36.#134      // org/kohsuke/github/GHCompare.usePaginatedCommits:Z
    #2 = Fieldref           #36.#135      // org/kohsuke/github/GHCompare.owner:Lorg/kohsuke/github/GHRepository;
    #3 = Fieldref           #36.#136      // org/kohsuke/github/GHCompare.url:Ljava/lang/String;
    #4 = Fieldref           #36.#137      // org/kohsuke/github/GHCompare.commits:[Lorg/kohsuke/github/GHCompare$Commit;
    #5 = Methodref          #37.#138      // java/lang/Object."<init>":()V
    #6 = Methodref          #139.#140     // org/kohsuke/github/GitHubClient.parseURL:(Ljava/lang/String;)Ljava/net/URL;
    #7 = Fieldref           #36.#141      // org/kohsuke/github/GHCompare.html_url:Ljava/lang/String;
    #8 = Fieldref           #36.#142      // org/kohsuke/github/GHCompare.permalink_url:Ljava/lang/String;
    #9 = Fieldref           #36.#143      // org/kohsuke/github/GHCompare.diff_url:Ljava/lang/String;
   #10 = Fieldref           #36.#144      // org/kohsuke/github/GHCompare.patch_url:Ljava/lang/String;
   #11 = Fieldref           #36.#145      // org/kohsuke/github/GHCompare.status:Lorg/kohsuke/github/GHCompare$Status;
   #12 = Fieldref           #36.#146      // org/kohsuke/github/GHCompare.ahead_by:I
   #13 = Fieldref           #36.#147      // org/kohsuke/github/GHCompare.behind_by:I
   #14 = Fieldref           #36.#148      // org/kohsuke/github/GHCompare.total_commits:I
   #15 = Fieldref           #36.#149      // org/kohsuke/github/GHCompare.base_commit:Lorg/kohsuke/github/GHCompare$Commit;
   #16 = Fieldref           #36.#150      // org/kohsuke/github/GHCompare.merge_base_commit:Lorg/kohsuke/github/GHCompare$Commit;
   #17 = Methodref          #36.#151      // org/kohsuke/github/GHCompare.listCommits:()Lorg/kohsuke/github/PagedIterable;
   #18 = Methodref          #152.#153     // org/kohsuke/github/PagedIterable.withPageSize:(I)Lorg/kohsuke/github/PagedIterable;
   #19 = Methodref          #152.#154     // org/kohsuke/github/PagedIterable.toArray:()[Ljava/lang/Object;
   #20 = Class              #66           // "[Lorg/kohsuke/github/GHCompare$Commit;"
   #21 = Class              #155          // java/io/IOException
   #22 = Class              #156          // org/kohsuke/github/GHException
   #23 = Methodref          #21.#157      // java/io/IOException.getMessage:()Ljava/lang/String;
   #24 = Methodref          #22.#158      // org/kohsuke/github/GHException."<init>":(Ljava/lang/String;Ljava/lang/Throwable;)V
   #25 = Class              #159          // org/kohsuke/github/GHCompare$GHCompareCommitsIterable
   #26 = Methodref          #25.#160      // org/kohsuke/github/GHCompare$GHCompareCommitsIterable."<init>":(Lorg/kohsuke/github/GHCompare;)V
   #27 = Class              #161          // org/kohsuke/github/GHCompare$1
   #28 = Methodref          #27.#160      // org/kohsuke/github/GHCompare$1."<init>":(Lorg/kohsuke/github/GHCompare;)V
   #29 = Fieldref           #36.#162      // org/kohsuke/github/GHCompare.files:[Lorg/kohsuke/github/GHCommit$File;
   #30 = Class              #164          // org/kohsuke/github/GHCommit$File
   #31 = Methodref          #165.#166     // java/lang/System.arraycopy:(Ljava/lang/Object;ILjava/lang/Object;II)V
   #32 = Class              #167          // java/lang/RuntimeException
   #33 = String             #168          // Do not use this method.
   #34 = Methodref          #32.#169      // java/lang/RuntimeException."<init>":(Ljava/lang/String;)V
   #35 = Methodref          #48.#170      // org/kohsuke/github/GHCompare$Commit.wrapUp:(Lorg/kohsuke/github/GHRepository;)Lorg/kohsuke/github/GHCommit;
   #36 = Class              #171          // org/kohsuke/github/GHCompare
   #37 = Class              #172          // java/lang/Object
   #38 = Utf8               GHCompareCommitsIterable
   #39 = Utf8               InnerClasses
   #40 = Class              #173          // org/kohsuke/github/GHCompare$Status
   #41 = Utf8               Status
   #42 = Class              #174          // org/kohsuke/github/GHCompare$User
   #43 = Utf8               User
   #44 = Class              #175          // org/kohsuke/github/GHCompare$Tree
   #45 = Utf8               Tree
   #46 = Class              #176          // org/kohsuke/github/GHCompare$InnerCommit
   #47 = Utf8               InnerCommit
   #48 = Class              #177          // org/kohsuke/github/GHCompare$Commit
   #49 = Utf8               Commit
   #50 = Utf8               url
   #51 = Utf8               Ljava/lang/String;
   #52 = Utf8               html_url
   #53 = Utf8               permalink_url
   #54 = Utf8               diff_url
   #55 = Utf8               patch_url
   #56 = Utf8               status
   #57 = Utf8               Lorg/kohsuke/github/GHCompare$Status;
   #58 = Utf8               ahead_by
   #59 = Utf8               I
   #60 = Utf8               behind_by
   #61 = Utf8               total_commits
   #62 = Utf8               base_commit
   #63 = Utf8               Lorg/kohsuke/github/GHCompare$Commit;
   #64 = Utf8               merge_base_commit
   #65 = Utf8               commits
   #66 = Utf8               [Lorg/kohsuke/github/GHCompare$Commit;
   #67 = Utf8               files
   #68 = Utf8               File
   #69 = Utf8               [Lorg/kohsuke/github/GHCommit$File;
   #70 = Utf8               owner
   #71 = Utf8               Lorg/kohsuke/github/GHRepository;
   #72 = Utf8               usePaginatedCommits
   #73 = Utf8               Z
   #74 = Utf8               RuntimeVisibleAnnotations
   #75 = Utf8               Lcom/fasterxml/jackson/annotation/JacksonInject;
   #76 = Utf8               value
   #77 = Utf8               GHCompare_usePaginatedCommits
   #78 = Utf8               <init>
   #79 = Utf8               ()V
   #80 = Utf8               Code
   #81 = Utf8               LineNumberTable
   #82 = Utf8               LocalVariableTable
   #83 = Utf8               this
   #84 = Utf8               Lorg/kohsuke/github/GHCompare;
   #85 = Utf8               getUrl
   #86 = Utf8               ()Ljava/net/URL;
   #87 = Utf8               getHtmlUrl
   #88 = Utf8               getPermalinkUrl
   #89 = Utf8               getDiffUrl
   #90 = Utf8               getPatchUrl
   #91 = Utf8               getStatus
   #92 = Utf8               ()Lorg/kohsuke/github/GHCompare$Status;
   #93 = Utf8               getAheadBy
   #94 = Utf8               ()I
   #95 = Utf8               getBehindBy
   #96 = Utf8               getTotalCommits
   #97 = Utf8               getBaseCommit
   #98 = Utf8               ()Lorg/kohsuke/github/GHCompare$Commit;
   #99 = Utf8               RuntimeInvisibleAnnotations
  #100 = Utf8               Ledu/umd/cs/findbugs/annotations/SuppressFBWarnings;
  #101 = Utf8               EI_EXPOSE_REP
  #102 = Utf8               justification
  #103 = Utf8               Expected behavior
  #104 = Utf8               getMergeBaseCommit
  #105 = Utf8               getCommits
  #106 = Utf8               ()[Lorg/kohsuke/github/GHCompare$Commit;
  #107 = Utf8               e
  #108 = Utf8               Ljava/io/IOException;
  #109 = Utf8               StackMapTable
  #110 = Utf8               listCommits
  #111 = Utf8               ()Lorg/kohsuke/github/PagedIterable;
  #112 = Utf8               Signature
  #113 = Utf8               ()Lorg/kohsuke/github/PagedIterable<Lorg/kohsuke/github/GHCompare$Commit;>;
  #114 = Utf8               getFiles
  #115 = Utf8               ()[Lorg/kohsuke/github/GHCommit$File;
  #116 = Utf8               newValue
  #117 = Utf8               wrap
  #118 = Utf8               (Lorg/kohsuke/github/GHRepository;)Lorg/kohsuke/github/GHCompare;
  #119 = Utf8               Deprecated
  #120 = Utf8               Ljava/lang/Deprecated;
  #121 = Utf8               lateBind
  #122 = Utf8               commit
  #123 = Utf8               access$000
  #124 = Utf8               (Lorg/kohsuke/github/GHCompare;)[Lorg/kohsuke/github/GHCompare$Commit;
  #125 = Utf8               x0
  #126 = Utf8               access$100
  #127 = Utf8               (Lorg/kohsuke/github/GHCompare;)Ljava/lang/String;
  #128 = Utf8               access$200
  #129 = Utf8               (Lorg/kohsuke/github/GHCompare;)Lorg/kohsuke/github/GHRepository;
  #130 = Utf8               access$300
  #131 = Utf8               (Lorg/kohsuke/github/GHCompare;)Z
  #132 = Utf8               SourceFile
  #133 = Utf8               GHCompare.java
  #134 = NameAndType        #72:#73       // usePaginatedCommits:Z
  #135 = NameAndType        #70:#71       // owner:Lorg/kohsuke/github/GHRepository;
  #136 = NameAndType        #50:#51       // url:Ljava/lang/String;
  #137 = NameAndType        #65:#66       // commits:[Lorg/kohsuke/github/GHCompare$Commit;
  #138 = NameAndType        #78:#79       // "<init>":()V
  #139 = Class              #178          // org/kohsuke/github/GitHubClient
  #140 = NameAndType        #179:#180     // parseURL:(Ljava/lang/String;)Ljava/net/URL;
  #141 = NameAndType        #52:#51       // html_url:Ljava/lang/String;
  #142 = NameAndType        #53:#51       // permalink_url:Ljava/lang/String;
  #143 = NameAndType        #54:#51       // diff_url:Ljava/lang/String;
  #144 = NameAndType        #55:#51       // patch_url:Ljava/lang/String;
  #145 = NameAndType        #56:#57       // status:Lorg/kohsuke/github/GHCompare$Status;
  #146 = NameAndType        #58:#59       // ahead_by:I
  #147 = NameAndType        #60:#59       // behind_by:I
  #148 = NameAndType        #61:#59       // total_commits:I
  #149 = NameAndType        #62:#63       // base_commit:Lorg/kohsuke/github/GHCompare$Commit;
  #150 = NameAndType        #64:#63       // merge_base_commit:Lorg/kohsuke/github/GHCompare$Commit;
  #151 = NameAndType        #110:#111     // listCommits:()Lorg/kohsuke/github/PagedIterable;
  #152 = Class              #181          // org/kohsuke/github/PagedIterable
  #153 = NameAndType        #182:#183     // withPageSize:(I)Lorg/kohsuke/github/PagedIterable;
  #154 = NameAndType        #184:#185     // toArray:()[Ljava/lang/Object;
  #155 = Utf8               java/io/IOException
  #156 = Utf8               org/kohsuke/github/GHException
  #157 = NameAndType        #186:#187     // getMessage:()Ljava/lang/String;
  #158 = NameAndType        #78:#188      // "<init>":(Ljava/lang/String;Ljava/lang/Throwable;)V
  #159 = Utf8               org/kohsuke/github/GHCompare$GHCompareCommitsIterable
  #160 = NameAndType        #78:#189      // "<init>":(Lorg/kohsuke/github/GHCompare;)V
  #161 = Utf8               org/kohsuke/github/GHCompare$1
  #162 = NameAndType        #67:#69       // files:[Lorg/kohsuke/github/GHCommit$File;
  #163 = Class              #190          // org/kohsuke/github/GHCommit
  #164 = Utf8               org/kohsuke/github/GHCommit$File
  #165 = Class              #191          // java/lang/System
  #166 = NameAndType        #192:#193     // arraycopy:(Ljava/lang/Object;ILjava/lang/Object;II)V
  #167 = Utf8               java/lang/RuntimeException
  #168 = Utf8               Do not use this method.
  #169 = NameAndType        #78:#194      // "<init>":(Ljava/lang/String;)V
  #170 = NameAndType        #195:#196     // wrapUp:(Lorg/kohsuke/github/GHRepository;)Lorg/kohsuke/github/GHCommit;
  #171 = Utf8               org/kohsuke/github/GHCompare
  #172 = Utf8               java/lang/Object
  #173 = Utf8               org/kohsuke/github/GHCompare$Status
  #174 = Utf8               org/kohsuke/github/GHCompare$User
  #175 = Utf8               org/kohsuke/github/GHCompare$Tree
  #176 = Utf8               org/kohsuke/github/GHCompare$InnerCommit
  #177 = Utf8               org/kohsuke/github/GHCompare$Commit
  #178 = Utf8               org/kohsuke/github/GitHubClient
  #179 = Utf8               parseURL
  #180 = Utf8               (Ljava/lang/String;)Ljava/net/URL;
  #181 = Utf8               org/kohsuke/github/PagedIterable
  #182 = Utf8               withPageSize
  #183 = Utf8               (I)Lorg/kohsuke/github/PagedIterable;
  #184 = Utf8               toArray
  #185 = Utf8               ()[Ljava/lang/Object;
  #186 = Utf8               getMessage
  #187 = Utf8               ()Ljava/lang/String;
  #188 = Utf8               (Ljava/lang/String;Ljava/lang/Throwable;)V
  #189 = Utf8               (Lorg/kohsuke/github/GHCompare;)V
  #190 = Utf8               org/kohsuke/github/GHCommit
  #191 = Utf8               java/lang/System
  #192 = Utf8               arraycopy
  #193 = Utf8               (Ljava/lang/Object;ILjava/lang/Object;II)V
  #194 = Utf8               (Ljava/lang/String;)V
  #195 = Utf8               wrapUp
  #196 = Utf8               (Lorg/kohsuke/github/GHRepository;)Lorg/kohsuke/github/GHCommit;
{
  private java.lang.String url;
    descriptor: Ljava/lang/String;
    flags: (0x0002) ACC_PRIVATE

  private java.lang.String html_url;
    descriptor: Ljava/lang/String;
    flags: (0x0002) ACC_PRIVATE

  private java.lang.String permalink_url;
    descriptor: Ljava/lang/String;
    flags: (0x0002) ACC_PRIVATE

  private java.lang.String diff_url;
    descriptor: Ljava/lang/String;
    flags: (0x0002) ACC_PRIVATE

  private java.lang.String patch_url;
    descriptor: Ljava/lang/String;
    flags: (0x0002) ACC_PRIVATE

  private org.kohsuke.github.GHCompare$Status status;
    descriptor: Lorg/kohsuke/github/GHCompare$Status;
    flags: (0x0002) ACC_PRIVATE

  private int ahead_by;
    descriptor: I
    flags: (0x0002) ACC_PRIVATE

  private int behind_by;
    descriptor: I
    flags: (0x0002) ACC_PRIVATE

  private int total_commits;
    descriptor: I
    flags: (0x0002) ACC_PRIVATE

  private org.kohsuke.github.GHCompare$Commit base_commit;
    descriptor: Lorg/kohsuke/github/GHCompare$Commit;
    flags: (0x0002) ACC_PRIVATE

  private org.kohsuke.github.GHCompare$Commit merge_base_commit;
    descriptor: Lorg/kohsuke/github/GHCompare$Commit;
    flags: (0x0002) ACC_PRIVATE

  private org.kohsuke.github.GHCompare$Commit[] commits;
    descriptor: [Lorg/kohsuke/github/GHCompare$Commit;
    flags: (0x0002) ACC_PRIVATE

  private org.kohsuke.github.GHCommit$File[] files;
    descriptor: [Lorg/kohsuke/github/GHCommit$File;
    flags: (0x0002) ACC_PRIVATE

  private org.kohsuke.github.GHRepository owner;
    descriptor: Lorg/kohsuke/github/GHRepository;
    flags: (0x0002) ACC_PRIVATE

  private boolean usePaginatedCommits;
    descriptor: Z
    flags: (0x0002) ACC_PRIVATE
    RuntimeVisibleAnnotations:
      0: #75(#76=s#77)
        com.fasterxml.jackson.annotation.JacksonInject(
          value="GHCompare_usePaginatedCommits"
        )

  public org.kohsuke.github.GHCompare();
    descriptor: ()V
    flags: (0x0001) ACC_PUBLIC
    Code:
      stack=1, locals=1, args_size=1
         0: aload_0
         1: invokespecial #5                  // Method java/lang/Object."<init>":()V
         4: return
      LineNumberTable:
        line 19: 0
      LocalVariableTable:
        Start  Length  Slot  Name   Signature
            0       5     0  this   Lorg/kohsuke/github/GHCompare;

  public java.net.URL getUrl();
    descriptor: ()Ljava/net/URL;
    flags: (0x0001) ACC_PUBLIC
    Code:
      stack=1, locals=1, args_size=1
         0: aload_0
         1: getfield      #3                  // Field url:Ljava/lang/String;
         4: invokestatic  #6                  // Method org/kohsuke/github/GitHubClient.parseURL:(Ljava/lang/String;)Ljava/net/URL;
         7: areturn
      LineNumberTable:
        line 39: 0
      LocalVariableTable:
        Start  Length  Slot  Name   Signature
            0       8     0  this   Lorg/kohsuke/github/GHCompare;

  public java.net.URL getHtmlUrl();
    descriptor: ()Ljava/net/URL;
    flags: (0x0001) ACC_PUBLIC
    Code:
      stack=1, locals=1, args_size=1
         0: aload_0
         1: getfield      #7                  // Field html_url:Ljava/lang/String;
         4: invokestatic  #6                  // Method org/kohsuke/github/GitHubClient.parseURL:(Ljava/lang/String;)Ljava/net/URL;
         7: areturn
      LineNumberTable:
        line 48: 0
      LocalVariableTable:
        Start  Length  Slot  Name   Signature
            0       8     0  this   Lorg/kohsuke/github/GHCompare;

  public java.net.URL getPermalinkUrl();
    descriptor: ()Ljava/net/URL;
    flags: (0x0001) ACC_PUBLIC
    Code:
      stack=1, locals=1, args_size=1
         0: aload_0
         1: getfield      #8                  // Field permalink_url:Ljava/lang/String;
         4: invokestatic  #6                  // Method org/kohsuke/github/GitHubClient.parseURL:(Ljava/lang/String;)Ljava/net/URL;
         7: areturn
      LineNumberTable:
        line 57: 0
      LocalVariableTable:
        Start  Length  Slot  Name   Signature
            0       8     0  this   Lorg/kohsuke/github/GHCompare;

  public java.net.URL getDiffUrl();
    descriptor: ()Ljava/net/URL;
    flags: (0x0001) ACC_PUBLIC
    Code:
      stack=1, locals=1, args_size=1
         0: aload_0
         1: getfield      #9                  // Field diff_url:Ljava/lang/String;
         4: invokestatic  #6                  // Method org/kohsuke/github/GitHubClient.parseURL:(Ljava/lang/String;)Ljava/net/URL;
         7: areturn
      LineNumberTable:
        line 66: 0
      LocalVariableTable:
        Start  Length  Slot  Name   Signature
            0       8     0  this   Lorg/kohsuke/github/GHCompare;

  public java.net.URL getPatchUrl();
    descriptor: ()Ljava/net/URL;
    flags: (0x0001) ACC_PUBLIC
    Code:
      stack=1, locals=1, args_size=1
         0: aload_0
         1: getfield      #10                 // Field patch_url:Ljava/lang/String;
         4: invokestatic  #6                  // Method org/kohsuke/github/GitHubClient.parseURL:(Ljava/lang/String;)Ljava/net/URL;
         7: areturn
      LineNumberTable:
        line 75: 0
      LocalVariableTable:
        Start  Length  Slot  Name   Signature
            0       8     0  this   Lorg/kohsuke/github/GHCompare;

  public org.kohsuke.github.GHCompare$Status getStatus();
    descriptor: ()Lorg/kohsuke/github/GHCompare$Status;
    flags: (0x0001) ACC_PUBLIC
    Code:
      stack=1, locals=1, args_size=1
         0: aload_0
         1: getfield      #11                 // Field status:Lorg/kohsuke/github/GHCompare$Status;
         4: areturn
      LineNumberTable:
        line 84: 0
      LocalVariableTable:
        Start  Length  Slot  Name   Signature
            0       5     0  this   Lorg/kohsuke/github/GHCompare;

  public int getAheadBy();
    descriptor: ()I
    flags: (0x0001) ACC_PUBLIC
    Code:
      stack=1, locals=1, args_size=1
         0: aload_0
         1: getfield      #12                 // Field ahead_by:I
         4: ireturn
      LineNumberTable:
        line 93: 0
      LocalVariableTable:
        Start  Length  Slot  Name   Signature
            0       5     0  this   Lorg/kohsuke/github/GHCompare;

  public int getBehindBy();
    descriptor: ()I
    flags: (0x0001) ACC_PUBLIC
    Code:
      stack=1, locals=1, args_size=1
         0: aload_0
         1: getfield      #13                 // Field behind_by:I
         4: ireturn
      LineNumberTable:
        line 102: 0
      LocalVariableTable:
        Start  Length  Slot  Name   Signature
            0       5     0  this   Lorg/kohsuke/github/GHCompare;

  public int getTotalCommits();
    descriptor: ()I
    flags: (0x0001) ACC_PUBLIC
    Code:
      stack=1, locals=1, args_size=1
         0: aload_0
         1: getfield      #14                 // Field total_commits:I
         4: ireturn
      LineNumberTable:
        line 111: 0
      LocalVariableTable:
        Start  Length  Slot  Name   Signature
            0       5     0  this   Lorg/kohsuke/github/GHCompare;

  public org.kohsuke.github.GHCompare$Commit getBaseCommit();
    descriptor: ()Lorg/kohsuke/github/GHCompare$Commit;
    flags: (0x0001) ACC_PUBLIC
    Code:
      stack=1, locals=1, args_size=1
         0: aload_0
         1: getfield      #15                 // Field base_commit:Lorg/kohsuke/github/GHCompare$Commit;
         4: areturn
      LineNumberTable:
        line 121: 0
      LocalVariableTable:
        Start  Length  Slot  Name   Signature
            0       5     0  this   Lorg/kohsuke/github/GHCompare;
    RuntimeInvisibleAnnotations:
      0: #100(#76=[s#101],#102=s#103)
        edu.umd.cs.findbugs.annotations.SuppressFBWarnings(
          value=["EI_EXPOSE_REP"]
          justification="Expected behavior"
        )

  public org.kohsuke.github.GHCompare$Commit getMergeBaseCommit();
    descriptor: ()Lorg/kohsuke/github/GHCompare$Commit;
    flags: (0x0001) ACC_PUBLIC
    Code:
      stack=1, locals=1, args_size=1
         0: aload_0
         1: getfield      #16                 // Field merge_base_commit:Lorg/kohsuke/github/GHCompare$Commit;
         4: areturn
      LineNumberTable:
        line 131: 0
      LocalVariableTable:
        Start  Length  Slot  Name   Signature
            0       5     0  this   Lorg/kohsuke/github/GHCompare;
    RuntimeInvisibleAnnotations:
      0: #100(#76=[s#101],#102=s#103)
        edu.umd.cs.findbugs.annotations.SuppressFBWarnings(
          value=["EI_EXPOSE_REP"]
          justification="Expected behavior"
        )

  public org.kohsuke.github.GHCompare$Commit[] getCommits();
    descriptor: ()[Lorg/kohsuke/github/GHCompare$Commit;
    flags: (0x0001) ACC_PUBLIC
    Code:
      stack=4, locals=2, args_size=1
         0: aload_0
         1: invokevirtual #17                 // Method listCommits:()Lorg/kohsuke/github/PagedIterable;
         4: bipush        100
         6: invokevirtual #18                 // Method org/kohsuke/github/PagedIterable.withPageSize:(I)Lorg/kohsuke/github/PagedIterable;
         9: invokevirtual #19                 // Method org/kohsuke/github/PagedIterable.toArray:()[Ljava/lang/Object;
        12: checkcast     #20                 // class "[Lorg/kohsuke/github/GHCompare$Commit;"
        15: areturn
        16: astore_1
        17: new           #22                 // class org/kohsuke/github/GHException
        20: dup
        21: aload_1
        22: invokevirtual #23                 // Method java/io/IOException.getMessage:()Ljava/lang/String;
        25: aload_1
        26: invokespecial #24                 // Method org/kohsuke/github/GHException."<init>":(Ljava/lang/String;Ljava/lang/Throwable;)V
        29: athrow
      Exception table:
         from    to  target type
             0    15    16   Class java/io/IOException
      LineNumberTable:
        line 150: 0
        line 151: 16
        line 152: 17
      LocalVariableTable:
        Start  Length  Slot  Name   Signature
           17      13     1     e   Ljava/io/IOException;
            0      30     0  this   Lorg/kohsuke/github/GHCompare;
      StackMapTable: number_of_entries = 1
        frame_type = 80 /* same_locals_1_stack_item */
          stack = [ class java/io/IOException ]

  public org.kohsuke.github.PagedIterable<org.kohsuke.github.GHCompare$Commit> listCommits();
    descriptor: ()Lorg/kohsuke/github/PagedIterable;
    flags: (0x0001) ACC_PUBLIC
    Code:
      stack=3, locals=1, args_size=1
         0: aload_0
         1: getfield      #1                  // Field usePaginatedCommits:Z
         4: ifeq          16
         7: new           #25                 // class org/kohsuke/github/GHCompare$GHCompareCommitsIterable
        10: dup
        11: aload_0
        12: invokespecial #26                 // Method org/kohsuke/github/GHCompare$GHCompareCommitsIterable."<init>":(Lorg/kohsuke/github/GHCompare;)V
        15: areturn
        16: new           #27                 // class org/kohsuke/github/GHCompare$1
        19: dup
        20: aload_0
        21: invokespecial #28                 // Method org/kohsuke/github/GHCompare$1."<init>":(Lorg/kohsuke/github/GHCompare;)V
        24: areturn
      LineNumberTable:
        line 171: 0
        line 172: 7
        line 175: 16
      LocalVariableTable:
        Start  Length  Slot  Name   Signature
            0      25     0  this   Lorg/kohsuke/github/GHCompare;
      StackMapTable: number_of_entries = 1
        frame_type = 16 /* same */
    Signature: #113                         // ()Lorg/kohsuke/github/PagedIterable<Lorg/kohsuke/github/GHCompare$Commit;>;

  public org.kohsuke.github.GHCommit$File[] getFiles();
    descriptor: ()[Lorg/kohsuke/github/GHCommit$File;
    flags: (0x0001) ACC_PUBLIC
    Code:
      stack=5, locals=2, args_size=1
         0: aload_0
         1: getfield      #29                 // Field files:[Lorg/kohsuke/github/GHCommit$File;
         4: arraylength
         5: anewarray     #30                 // class org/kohsuke/github/GHCommit$File
         8: astore_1
         9: aload_0
        10: getfield      #29                 // Field files:[Lorg/kohsuke/github/GHCommit$File;
        13: iconst_0
        14: aload_1
        15: iconst_0
        16: aload_0
        17: getfield      #29                 // Field files:[Lorg/kohsuke/github/GHCommit$File;
        20: arraylength
        21: invokestatic  #31                 // Method java/lang/System.arraycopy:(Ljava/lang/Object;ILjava/lang/Object;II)V
        24: aload_1
        25: areturn
      LineNumberTable:
        line 191: 0
        line 192: 9
        line 193: 24
      LocalVariableTable:
        Start  Length  Slot  Name   Signature
            0      26     0  this   Lorg/kohsuke/github/GHCompare;
            9      17     1 newValue   [Lorg/kohsuke/github/GHCommit$File;

  public org.kohsuke.github.GHCompare wrap(org.kohsuke.github.GHRepository);
    descriptor: (Lorg/kohsuke/github/GHRepository;)Lorg/kohsuke/github/GHCompare;
    flags: (0x0001) ACC_PUBLIC
    Code:
      stack=3, locals=2, args_size=2
         0: new           #32                 // class java/lang/RuntimeException
         3: dup
         4: ldc           #33                 // String Do not use this method.
         6: invokespecial #34                 // Method java/lang/RuntimeException."<init>":(Ljava/lang/String;)V
         9: athrow
      LineNumberTable:
        line 205: 0
      LocalVariableTable:
        Start  Length  Slot  Name   Signature
            0      10     0  this   Lorg/kohsuke/github/GHCompare;
            0      10     1 owner   Lorg/kohsuke/github/GHRepository;
    Deprecated: true
    RuntimeVisibleAnnotations:
      0: #120()
        java.lang.Deprecated

  org.kohsuke.github.GHCompare lateBind(org.kohsuke.github.GHRepository);
    descriptor: (Lorg/kohsuke/github/GHRepository;)Lorg/kohsuke/github/GHCompare;
    flags: (0x0000)
    Code:
      stack=2, locals=6, args_size=2
         0: aload_0
         1: aload_1
         2: putfield      #2                  // Field owner:Lorg/kohsuke/github/GHRepository;
         5: aload_0
         6: getfield      #4                  // Field commits:[Lorg/kohsuke/github/GHCompare$Commit;
         9: astore_2
        10: aload_2
        11: arraylength
        12: istore_3
        13: iconst_0
        14: istore        4
        16: iload         4
        18: iload_3
        19: if_icmpge     41
        22: aload_2
        23: iload         4
        25: aaload
        26: astore        5
        28: aload         5
        30: aload_1
        31: invokevirtual #35                 // Method org/kohsuke/github/GHCompare$Commit.wrapUp:(Lorg/kohsuke/github/GHRepository;)Lorg/kohsuke/github/GHCommit;
        34: pop
        35: iinc          4, 1
        38: goto          16
        41: aload_0
        42: getfield      #16                 // Field merge_base_commit:Lorg/kohsuke/github/GHCompare$Commit;
        45: aload_1
        46: invokevirtual #35                 // Method org/kohsuke/github/GHCompare$Commit.wrapUp:(Lorg/kohsuke/github/GHRepository;)Lorg/kohsuke/github/GHCommit;
        49: pop
        50: aload_0
        51: getfield      #15                 // Field base_commit:Lorg/kohsuke/github/GHCompare$Commit;
        54: aload_1
        55: invokevirtual #35                 // Method org/kohsuke/github/GHCompare$Commit.wrapUp:(Lorg/kohsuke/github/GHRepository;)Lorg/kohsuke/github/GHCommit;
        58: pop
        59: aload_0
        60: areturn
      LineNumberTable:
        line 216: 0
        line 217: 5
        line 218: 28
        line 217: 35
        line 220: 41
        line 221: 50
        line 222: 59
      LocalVariableTable:
        Start  Length  Slot  Name   Signature
           28       7     5 commit   Lorg/kohsuke/github/GHCompare$Commit;
            0      61     0  this   Lorg/kohsuke/github/GHCompare;
            0      61     1 owner   Lorg/kohsuke/github/GHRepository;
      StackMapTable: number_of_entries = 2
        frame_type = 254 /* append */
          offset_delta = 16
          locals = [ class "[Lorg/kohsuke/github/GHCompare$Commit;", int, int ]
        frame_type = 248 /* chop */
          offset_delta = 24

  static org.kohsuke.github.GHCompare$Commit[] access$000(org.kohsuke.github.GHCompare);
    descriptor: (Lorg/kohsuke/github/GHCompare;)[Lorg/kohsuke/github/GHCompare$Commit;
    flags: (0x1008) ACC_STATIC, ACC_SYNTHETIC
    Code:
      stack=1, locals=1, args_size=1
         0: aload_0
         1: getfield      #4                  // Field commits:[Lorg/kohsuke/github/GHCompare$Commit;
         4: areturn
      LineNumberTable:
        line 19: 0
      LocalVariableTable:
        Start  Length  Slot  Name   Signature
            0       5     0    x0   Lorg/kohsuke/github/GHCompare;

  static java.lang.String access$100(org.kohsuke.github.GHCompare);
    descriptor: (Lorg/kohsuke/github/GHCompare;)Ljava/lang/String;
    flags: (0x1008) ACC_STATIC, ACC_SYNTHETIC
    Code:
      stack=1, locals=1, args_size=1
         0: aload_0
         1: getfield      #3                  // Field url:Ljava/lang/String;
         4: areturn
      LineNumberTable:
        line 19: 0
      LocalVariableTable:
        Start  Length  Slot  Name   Signature
            0       5     0    x0   Lorg/kohsuke/github/GHCompare;

  static org.kohsuke.github.GHRepository access$200(org.kohsuke.github.GHCompare);
    descriptor: (Lorg/kohsuke/github/GHCompare;)Lorg/kohsuke/github/GHRepository;
    flags: (0x1008) ACC_STATIC, ACC_SYNTHETIC
    Code:
      stack=1, locals=1, args_size=1
         0: aload_0
         1: getfield      #2                  // Field owner:Lorg/kohsuke/github/GHRepository;
         4: areturn
      LineNumberTable:
        line 19: 0
      LocalVariableTable:
        Start  Length  Slot  Name   Signature
            0       5     0    x0   Lorg/kohsuke/github/GHCompare;

  static boolean access$300(org.kohsuke.github.GHCompare);
    descriptor: (Lorg/kohsuke/github/GHCompare;)Z
    flags: (0x1008) ACC_STATIC, ACC_SYNTHETIC
    Code:
      stack=1, locals=1, args_size=1
         0: aload_0
         1: getfield      #1                  // Field usePaginatedCommits:Z
         4: ireturn
      LineNumberTable:
        line 19: 0
      LocalVariableTable:
        Start  Length  Slot  Name   Signature
            0       5     0    x0   Lorg/kohsuke/github/GHCompare;
}
SourceFile: "GHCompare.java"
InnerClasses:
  #38= #25 of #36;                        // GHCompareCommitsIterable=class org/kohsuke/github/GHCompare$GHCompareCommitsIterable of class org/kohsuke/github/GHCompare
  public static final #41= #40 of #36;    // Status=class org/kohsuke/github/GHCompare$Status of class org/kohsuke/github/GHCompare
  public static #43= #42 of #36;          // User=class org/kohsuke/github/GHCompare$User of class org/kohsuke/github/GHCompare
  public static #45= #44 of #36;          // Tree=class org/kohsuke/github/GHCompare$Tree of class org/kohsuke/github/GHCompare
  public static #47= #46 of #36;          // InnerCommit=class org/kohsuke/github/GHCompare$InnerCommit of class org/kohsuke/github/GHCompare
  public static #49= #48 of #36;          // Commit=class org/kohsuke/github/GHCompare$Commit of class org/kohsuke/github/GHCompare
  #27;                                    // class org/kohsuke/github/GHCompare$1
  public static #68= #30 of #163;         // File=class org/kohsuke/github/GHCommit$File of class org/kohsuke/github/GHCommit
