Classfile /Users/mw/Projects/slang-braindump/.jar/jar11/assemble/slang-braindump/assemble/content/org/kohsuke/github/GHDeployment.class
  Last modified May 29, 2022; size 5249 bytes
  SHA-256 checksum 4930f3259e2d0059bd7ffb8b4bec814244a1be9158ad03507972be7d658940aa
  Compiled from "GHDeployment.java"
public class org.kohsuke.github.GHDeployment extends org.kohsuke.github.GHObject
  minor version: 0
  major version: 52
  flags: (0x0021) ACC_PUBLIC, ACC_SUPER
  this_class: #33                         // org/kohsuke/github/GHDeployment
  super_class: #34                        // org/kohsuke/github/GHObject
  interfaces: 0, fields: 13, methods: 20, attributes: 3
Constant pool:
    #1 = Methodref          #34.#108      // org/kohsuke/github/GHObject."<init>":()V
    #2 = Fieldref           #33.#109      // org/kohsuke/github/GHDeployment.owner:Lorg/kohsuke/github/GHRepository;
    #3 = Fieldref           #33.#110      // org/kohsuke/github/GHDeployment.statuses_url:Ljava/lang/String;
    #4 = Methodref          #111.#112     // org/kohsuke/github/GitHubClient.parseURL:(Ljava/lang/String;)Ljava/net/URL;
    #5 = Fieldref           #33.#113      // org/kohsuke/github/GHDeployment.repository_url:Ljava/lang/String;
    #6 = Fieldref           #33.#114      // org/kohsuke/github/GHDeployment.task:Ljava/lang/String;
    #7 = Fieldref           #33.#115      // org/kohsuke/github/GHDeployment.payload:Ljava/lang/Object;
    #8 = Class              #116          // java/lang/String
    #9 = Class              #117          // java/util/Map
   #10 = Methodref          #118.#119     // java/util/Collections.unmodifiableMap:(Ljava/util/Map;)Ljava/util/Map;
   #11 = Fieldref           #33.#120      // org/kohsuke/github/GHDeployment.original_environment:Ljava/lang/String;
   #12 = Fieldref           #33.#121      // org/kohsuke/github/GHDeployment.environment:Ljava/lang/String;
   #13 = Fieldref           #33.#122      // org/kohsuke/github/GHDeployment.transient_environment:Z
   #14 = Fieldref           #33.#123      // org/kohsuke/github/GHDeployment.production_environment:Z
   #15 = Methodref          #33.#124      // org/kohsuke/github/GHDeployment.root:()Lorg/kohsuke/github/GitHub;
   #16 = Fieldref           #33.#125      // org/kohsuke/github/GHDeployment.creator:Lorg/kohsuke/github/GHUser;
   #17 = Methodref          #126.#127     // org/kohsuke/github/GitHub.intern:(Lorg/kohsuke/github/GHUser;)Lorg/kohsuke/github/GHUser;
   #18 = Fieldref           #33.#128      // org/kohsuke/github/GHDeployment.ref:Ljava/lang/String;
   #19 = Fieldref           #33.#129      // org/kohsuke/github/GHDeployment.sha:Ljava/lang/String;
   #20 = Class              #130          // org/kohsuke/github/GHDeploymentStatusBuilder
   #21 = Methodref          #33.#131      // org/kohsuke/github/GHDeployment.getId:()J
   #22 = Methodref          #20.#132      // org/kohsuke/github/GHDeploymentStatusBuilder."<init>":(Lorg/kohsuke/github/GHRepository;JLorg/kohsuke/github/GHDeploymentState;)V
   #23 = Methodref          #126.#133     // org/kohsuke/github/GitHub.createRequest:()Lorg/kohsuke/github/Requester;
   #24 = Methodref          #25.#134      // org/kohsuke/github/Requester.withUrlPath:(Ljava/lang/String;[Ljava/lang/String;)Lorg/kohsuke/github/GitHubRequest$Builder;
   #25 = Class              #135          // org/kohsuke/github/Requester
   #26 = Fieldref           #136.#137     // org/kohsuke/github/internal/Previews.ANT_MAN:Lorg/kohsuke/github/internal/Previews;
   #27 = Methodref          #25.#138      // org/kohsuke/github/Requester.withPreview:(Lorg/kohsuke/github/internal/Previews;)Lorg/kohsuke/github/GitHubRequest$Builder;
   #28 = Fieldref           #136.#139     // org/kohsuke/github/internal/Previews.FLASH:Lorg/kohsuke/github/internal/Previews;
   #29 = Class              #140          // "[Lorg/kohsuke/github/GHDeploymentStatus;"
   #30 = InvokeDynamic      #0:#146       // #0:accept:(Lorg/kohsuke/github/GHDeployment;)Ljava/util/function/Consumer;
   #31 = Methodref          #25.#147      // org/kohsuke/github/Requester.toIterable:(Ljava/lang/Class;Ljava/util/function/Consumer;)Lorg/kohsuke/github/PagedIterable;
   #32 = Methodref          #148.#149     // org/kohsuke/github/GHDeploymentStatus.lateBind:(Lorg/kohsuke/github/GHRepository;)Lorg/kohsuke/github/GHDeploymentStatus;
   #33 = Class              #150          // org/kohsuke/github/GHDeployment
   #34 = Class              #151          // org/kohsuke/github/GHObject
   #35 = Utf8               owner
   #36 = Utf8               Lorg/kohsuke/github/GHRepository;
   #37 = Utf8               sha
   #38 = Utf8               Ljava/lang/String;
   #39 = Utf8               ref
   #40 = Utf8               task
   #41 = Utf8               payload
   #42 = Utf8               Ljava/lang/Object;
   #43 = Utf8               environment
   #44 = Utf8               description
   #45 = Utf8               statuses_url
   #46 = Utf8               repository_url
   #47 = Utf8               creator
   #48 = Utf8               Lorg/kohsuke/github/GHUser;
   #49 = Utf8               original_environment
   #50 = Utf8               transient_environment
   #51 = Utf8               Z
   #52 = Utf8               production_environment
   #53 = Utf8               <init>
   #54 = Utf8               ()V
   #55 = Utf8               Code
   #56 = Utf8               LineNumberTable
   #57 = Utf8               LocalVariableTable
   #58 = Utf8               this
   #59 = Utf8               Lorg/kohsuke/github/GHDeployment;
   #60 = Utf8               wrap
   #61 = Utf8               (Lorg/kohsuke/github/GHRepository;)Lorg/kohsuke/github/GHDeployment;
   #62 = Utf8               getStatusesUrl
   #63 = Utf8               ()Ljava/net/URL;
   #64 = Utf8               getRepositoryUrl
   #65 = Utf8               getTask
   #66 = Utf8               ()Ljava/lang/String;
   #67 = Utf8               getPayload
   #68 = Utf8               getPayloadMap
   #69 = Utf8               ()Ljava/util/Map;
   #70 = Utf8               Signature
   #71 = Utf8               ()Ljava/util/Map<Ljava/lang/String;Ljava/lang/Object;>;
   #72 = Utf8               getPayloadObject
   #73 = Utf8               ()Ljava/lang/Object;
   #74 = Utf8               getOriginalEnvironment
   #75 = Utf8               Deprecated
   #76 = Utf8               RuntimeVisibleAnnotations
   #77 = Utf8               Lorg/kohsuke/github/Preview;
   #78 = Utf8               value
   #79 = Utf8               Lorg/kohsuke/github/internal/Previews;
   #80 = Utf8               FLASH
   #81 = Utf8               getEnvironment
   #82 = Utf8               isTransientEnvironment
   #83 = Utf8               ()Z
   #84 = Utf8               ANT_MAN
   #85 = Utf8               isProductionEnvironment
   #86 = Utf8               getCreator
   #87 = Utf8               ()Lorg/kohsuke/github/GHUser;
   #88 = Utf8               Exceptions
   #89 = Class              #152          // java/io/IOException
   #90 = Utf8               getRef
   #91 = Utf8               getSha
   #92 = Utf8               getHtmlUrl
   #93 = Utf8               createStatus
   #94 = Utf8               (Lorg/kohsuke/github/GHDeploymentState;)Lorg/kohsuke/github/GHDeploymentStatusBuilder;
   #95 = Utf8               state
   #96 = Utf8               Lorg/kohsuke/github/GHDeploymentState;
   #97 = Utf8               listStatuses
   #98 = Utf8               ()Lorg/kohsuke/github/PagedIterable;
   #99 = Utf8               ()Lorg/kohsuke/github/PagedIterable<Lorg/kohsuke/github/GHDeploymentStatus;>;
  #100 = Utf8               getOwner
  #101 = Utf8               ()Lorg/kohsuke/github/GHRepository;
  #102 = Utf8               lambda$listStatuses$0
  #103 = Utf8               (Lorg/kohsuke/github/GHDeploymentStatus;)V
  #104 = Utf8               item
  #105 = Utf8               Lorg/kohsuke/github/GHDeploymentStatus;
  #106 = Utf8               SourceFile
  #107 = Utf8               GHDeployment.java
  #108 = NameAndType        #53:#54       // "<init>":()V
  #109 = NameAndType        #35:#36       // owner:Lorg/kohsuke/github/GHRepository;
  #110 = NameAndType        #45:#38       // statuses_url:Ljava/lang/String;
  #111 = Class              #153          // org/kohsuke/github/GitHubClient
  #112 = NameAndType        #154:#155     // parseURL:(Ljava/lang/String;)Ljava/net/URL;
  #113 = NameAndType        #46:#38       // repository_url:Ljava/lang/String;
  #114 = NameAndType        #40:#38       // task:Ljava/lang/String;
  #115 = NameAndType        #41:#42       // payload:Ljava/lang/Object;
  #116 = Utf8               java/lang/String
  #117 = Utf8               java/util/Map
  #118 = Class              #156          // java/util/Collections
  #119 = NameAndType        #157:#158     // unmodifiableMap:(Ljava/util/Map;)Ljava/util/Map;
  #120 = NameAndType        #49:#38       // original_environment:Ljava/lang/String;
  #121 = NameAndType        #43:#38       // environment:Ljava/lang/String;
  #122 = NameAndType        #50:#51       // transient_environment:Z
  #123 = NameAndType        #52:#51       // production_environment:Z
  #124 = NameAndType        #159:#160     // root:()Lorg/kohsuke/github/GitHub;
  #125 = NameAndType        #47:#48       // creator:Lorg/kohsuke/github/GHUser;
  #126 = Class              #161          // org/kohsuke/github/GitHub
  #127 = NameAndType        #162:#163     // intern:(Lorg/kohsuke/github/GHUser;)Lorg/kohsuke/github/GHUser;
  #128 = NameAndType        #39:#38       // ref:Ljava/lang/String;
  #129 = NameAndType        #37:#38       // sha:Ljava/lang/String;
  #130 = Utf8               org/kohsuke/github/GHDeploymentStatusBuilder
  #131 = NameAndType        #164:#165     // getId:()J
  #132 = NameAndType        #53:#166      // "<init>":(Lorg/kohsuke/github/GHRepository;JLorg/kohsuke/github/GHDeploymentState;)V
  #133 = NameAndType        #167:#168     // createRequest:()Lorg/kohsuke/github/Requester;
  #134 = NameAndType        #169:#173     // withUrlPath:(Ljava/lang/String;[Ljava/lang/String;)Lorg/kohsuke/github/GitHubRequest$Builder;
  #135 = Utf8               org/kohsuke/github/Requester
  #136 = Class              #174          // org/kohsuke/github/internal/Previews
  #137 = NameAndType        #84:#79       // ANT_MAN:Lorg/kohsuke/github/internal/Previews;
  #138 = NameAndType        #175:#176     // withPreview:(Lorg/kohsuke/github/internal/Previews;)Lorg/kohsuke/github/GitHubRequest$Builder;
  #139 = NameAndType        #80:#79       // FLASH:Lorg/kohsuke/github/internal/Previews;
  #140 = Utf8               [Lorg/kohsuke/github/GHDeploymentStatus;
  #141 = Utf8               BootstrapMethods
  #142 = MethodHandle       6:#177        // REF_invokeStatic java/lang/invoke/LambdaMetafactory.metafactory:(Ljava/lang/invoke/MethodHandles$Lookup;Ljava/lang/String;Ljava/lang/invoke/MethodType;Ljava/lang/invoke/MethodType;Ljava/lang/invoke/MethodHandle;Ljava/lang/invoke/MethodType;)Ljava/lang/invoke/CallSite;
  #143 = MethodType         #178          //  (Ljava/lang/Object;)V
  #144 = MethodHandle       7:#179        // REF_invokeSpecial org/kohsuke/github/GHDeployment.lambda$listStatuses$0:(Lorg/kohsuke/github/GHDeploymentStatus;)V
  #145 = MethodType         #103          //  (Lorg/kohsuke/github/GHDeploymentStatus;)V
  #146 = NameAndType        #180:#181     // accept:(Lorg/kohsuke/github/GHDeployment;)Ljava/util/function/Consumer;
  #147 = NameAndType        #182:#183     // toIterable:(Ljava/lang/Class;Ljava/util/function/Consumer;)Lorg/kohsuke/github/PagedIterable;
  #148 = Class              #184          // org/kohsuke/github/GHDeploymentStatus
  #149 = NameAndType        #185:#186     // lateBind:(Lorg/kohsuke/github/GHRepository;)Lorg/kohsuke/github/GHDeploymentStatus;
  #150 = Utf8               org/kohsuke/github/GHDeployment
  #151 = Utf8               org/kohsuke/github/GHObject
  #152 = Utf8               java/io/IOException
  #153 = Utf8               org/kohsuke/github/GitHubClient
  #154 = Utf8               parseURL
  #155 = Utf8               (Ljava/lang/String;)Ljava/net/URL;
  #156 = Utf8               java/util/Collections
  #157 = Utf8               unmodifiableMap
  #158 = Utf8               (Ljava/util/Map;)Ljava/util/Map;
  #159 = Utf8               root
  #160 = Utf8               ()Lorg/kohsuke/github/GitHub;
  #161 = Utf8               org/kohsuke/github/GitHub
  #162 = Utf8               intern
  #163 = Utf8               (Lorg/kohsuke/github/GHUser;)Lorg/kohsuke/github/GHUser;
  #164 = Utf8               getId
  #165 = Utf8               ()J
  #166 = Utf8               (Lorg/kohsuke/github/GHRepository;JLorg/kohsuke/github/GHDeploymentState;)V
  #167 = Utf8               createRequest
  #168 = Utf8               ()Lorg/kohsuke/github/Requester;
  #169 = Utf8               withUrlPath
  #170 = Class              #188          // org/kohsuke/github/GitHubRequest$Builder
  #171 = Utf8               Builder
  #172 = Utf8               InnerClasses
  #173 = Utf8               (Ljava/lang/String;[Ljava/lang/String;)Lorg/kohsuke/github/GitHubRequest$Builder;
  #174 = Utf8               org/kohsuke/github/internal/Previews
  #175 = Utf8               withPreview
  #176 = Utf8               (Lorg/kohsuke/github/internal/Previews;)Lorg/kohsuke/github/GitHubRequest$Builder;
  #177 = Methodref          #189.#190     // java/lang/invoke/LambdaMetafactory.metafactory:(Ljava/lang/invoke/MethodHandles$Lookup;Ljava/lang/String;Ljava/lang/invoke/MethodType;Ljava/lang/invoke/MethodType;Ljava/lang/invoke/MethodHandle;Ljava/lang/invoke/MethodType;)Ljava/lang/invoke/CallSite;
  #178 = Utf8               (Ljava/lang/Object;)V
  #179 = Methodref          #33.#191      // org/kohsuke/github/GHDeployment.lambda$listStatuses$0:(Lorg/kohsuke/github/GHDeploymentStatus;)V
  #180 = Utf8               accept
  #181 = Utf8               (Lorg/kohsuke/github/GHDeployment;)Ljava/util/function/Consumer;
  #182 = Utf8               toIterable
  #183 = Utf8               (Ljava/lang/Class;Ljava/util/function/Consumer;)Lorg/kohsuke/github/PagedIterable;
  #184 = Utf8               org/kohsuke/github/GHDeploymentStatus
  #185 = Utf8               lateBind
  #186 = Utf8               (Lorg/kohsuke/github/GHRepository;)Lorg/kohsuke/github/GHDeploymentStatus;
  #187 = Class              #192          // org/kohsuke/github/GitHubRequest
  #188 = Utf8               org/kohsuke/github/GitHubRequest$Builder
  #189 = Class              #193          // java/lang/invoke/LambdaMetafactory
  #190 = NameAndType        #194:#197     // metafactory:(Ljava/lang/invoke/MethodHandles$Lookup;Ljava/lang/String;Ljava/lang/invoke/MethodType;Ljava/lang/invoke/MethodType;Ljava/lang/invoke/MethodHandle;Ljava/lang/invoke/MethodType;)Ljava/lang/invoke/CallSite;
  #191 = NameAndType        #102:#103     // lambda$listStatuses$0:(Lorg/kohsuke/github/GHDeploymentStatus;)V
  #192 = Utf8               org/kohsuke/github/GitHubRequest
  #193 = Utf8               java/lang/invoke/LambdaMetafactory
  #194 = Utf8               metafactory
  #195 = Class              #199          // java/lang/invoke/MethodHandles$Lookup
  #196 = Utf8               Lookup
  #197 = Utf8               (Ljava/lang/invoke/MethodHandles$Lookup;Ljava/lang/String;Ljava/lang/invoke/MethodType;Ljava/lang/invoke/MethodType;Ljava/lang/invoke/MethodHandle;Ljava/lang/invoke/MethodType;)Ljava/lang/invoke/CallSite;
  #198 = Class              #200          // java/lang/invoke/MethodHandles
  #199 = Utf8               java/lang/invoke/MethodHandles$Lookup
  #200 = Utf8               java/lang/invoke/MethodHandles
{
  private org.kohsuke.github.GHRepository owner;
    descriptor: Lorg/kohsuke/github/GHRepository;
    flags: (0x0002) ACC_PRIVATE

  protected java.lang.String sha;
    descriptor: Ljava/lang/String;
    flags: (0x0004) ACC_PROTECTED

  protected java.lang.String ref;
    descriptor: Ljava/lang/String;
    flags: (0x0004) ACC_PROTECTED

  protected java.lang.String task;
    descriptor: Ljava/lang/String;
    flags: (0x0004) ACC_PROTECTED

  protected java.lang.Object payload;
    descriptor: Ljava/lang/Object;
    flags: (0x0004) ACC_PROTECTED

  protected java.lang.String environment;
    descriptor: Ljava/lang/String;
    flags: (0x0004) ACC_PROTECTED

  protected java.lang.String description;
    descriptor: Ljava/lang/String;
    flags: (0x0004) ACC_PROTECTED

  protected java.lang.String statuses_url;
    descriptor: Ljava/lang/String;
    flags: (0x0004) ACC_PROTECTED

  protected java.lang.String repository_url;
    descriptor: Ljava/lang/String;
    flags: (0x0004) ACC_PROTECTED

  protected org.kohsuke.github.GHUser creator;
    descriptor: Lorg/kohsuke/github/GHUser;
    flags: (0x0004) ACC_PROTECTED

  protected java.lang.String original_environment;
    descriptor: Ljava/lang/String;
    flags: (0x0004) ACC_PROTECTED

  protected boolean transient_environment;
    descriptor: Z
    flags: (0x0004) ACC_PROTECTED

  protected boolean production_environment;
    descriptor: Z
    flags: (0x0004) ACC_PROTECTED

  public org.kohsuke.github.GHDeployment();
    descriptor: ()V
    flags: (0x0001) ACC_PUBLIC
    Code:
      stack=1, locals=1, args_size=1
         0: aload_0
         1: invokespecial #1                  // Method org/kohsuke/github/GHObject."<init>":()V
         4: return
      LineNumberTable:
        line 18: 0
      LocalVariableTable:
        Start  Length  Slot  Name   Signature
            0       5     0  this   Lorg/kohsuke/github/GHDeployment;

  org.kohsuke.github.GHDeployment wrap(org.kohsuke.github.GHRepository);
    descriptor: (Lorg/kohsuke/github/GHRepository;)Lorg/kohsuke/github/GHDeployment;
    flags: (0x0000)
    Code:
      stack=2, locals=2, args_size=2
         0: aload_0
         1: aload_1
         2: putfield      #2                  // Field owner:Lorg/kohsuke/github/GHRepository;
         5: aload_0
         6: areturn
      LineNumberTable:
        line 34: 0
        line 35: 5
      LocalVariableTable:
        Start  Length  Slot  Name   Signature
            0       7     0  this   Lorg/kohsuke/github/GHDeployment;
            0       7     1 owner   Lorg/kohsuke/github/GHRepository;

  public java.net.URL getStatusesUrl();
    descriptor: ()Ljava/net/URL;
    flags: (0x0001) ACC_PUBLIC
    Code:
      stack=1, locals=1, args_size=1
         0: aload_0
         1: getfield      #3                  // Field statuses_url:Ljava/lang/String;
         4: invokestatic  #4                  // Method org/kohsuke/github/GitHubClient.parseURL:(Ljava/lang/String;)Ljava/net/URL;
         7: areturn
      LineNumberTable:
        line 44: 0
      LocalVariableTable:
        Start  Length  Slot  Name   Signature
            0       8     0  this   Lorg/kohsuke/github/GHDeployment;

  public java.net.URL getRepositoryUrl();
    descriptor: ()Ljava/net/URL;
    flags: (0x0001) ACC_PUBLIC
    Code:
      stack=1, locals=1, args_size=1
         0: aload_0
         1: getfield      #5                  // Field repository_url:Ljava/lang/String;
         4: invokestatic  #4                  // Method org/kohsuke/github/GitHubClient.parseURL:(Ljava/lang/String;)Ljava/net/URL;
         7: areturn
      LineNumberTable:
        line 53: 0
      LocalVariableTable:
        Start  Length  Slot  Name   Signature
            0       8     0  this   Lorg/kohsuke/github/GHDeployment;

  public java.lang.String getTask();
    descriptor: ()Ljava/lang/String;
    flags: (0x0001) ACC_PUBLIC
    Code:
      stack=1, locals=1, args_size=1
         0: aload_0
         1: getfield      #6                  // Field task:Ljava/lang/String;
         4: areturn
      LineNumberTable:
        line 62: 0
      LocalVariableTable:
        Start  Length  Slot  Name   Signature
            0       5     0  this   Lorg/kohsuke/github/GHDeployment;

  public java.lang.String getPayload();
    descriptor: ()Ljava/lang/String;
    flags: (0x0001) ACC_PUBLIC
    Code:
      stack=1, locals=1, args_size=1
         0: aload_0
         1: getfield      #7                  // Field payload:Ljava/lang/Object;
         4: checkcast     #8                  // class java/lang/String
         7: areturn
      LineNumberTable:
        line 72: 0
      LocalVariableTable:
        Start  Length  Slot  Name   Signature
            0       8     0  this   Lorg/kohsuke/github/GHDeployment;

  public java.util.Map<java.lang.String, java.lang.Object> getPayloadMap();
    descriptor: ()Ljava/util/Map;
    flags: (0x0001) ACC_PUBLIC
    Code:
      stack=1, locals=1, args_size=1
         0: aload_0
         1: getfield      #7                  // Field payload:Ljava/lang/Object;
         4: checkcast     #9                  // class java/util/Map
         7: invokestatic  #10                 // Method java/util/Collections.unmodifiableMap:(Ljava/util/Map;)Ljava/util/Map;
        10: areturn
      LineNumberTable:
        line 82: 0
      LocalVariableTable:
        Start  Length  Slot  Name   Signature
            0      11     0  this   Lorg/kohsuke/github/GHDeployment;
    Signature: #71                          // ()Ljava/util/Map<Ljava/lang/String;Ljava/lang/Object;>;

  public java.lang.Object getPayloadObject();
    descriptor: ()Ljava/lang/Object;
    flags: (0x0001) ACC_PUBLIC
    Code:
      stack=1, locals=1, args_size=1
         0: aload_0
         1: getfield      #7                  // Field payload:Ljava/lang/Object;
         4: areturn
      LineNumberTable:
        line 91: 0
      LocalVariableTable:
        Start  Length  Slot  Name   Signature
            0       5     0  this   Lorg/kohsuke/github/GHDeployment;

  public java.lang.String getOriginalEnvironment();
    descriptor: ()Ljava/lang/String;
    flags: (0x0001) ACC_PUBLIC
    Code:
      stack=1, locals=1, args_size=1
         0: aload_0
         1: getfield      #11                 // Field original_environment:Ljava/lang/String;
         4: areturn
      LineNumberTable:
        line 103: 0
      LocalVariableTable:
        Start  Length  Slot  Name   Signature
            0       5     0  this   Lorg/kohsuke/github/GHDeployment;
    Deprecated: true
    RuntimeVisibleAnnotations:
      0: #77(#78=[e#79.#80])
        org.kohsuke.github.Preview(
          value=[Lorg/kohsuke/github/internal/Previews;.FLASH]
        )

  public java.lang.String getEnvironment();
    descriptor: ()Ljava/lang/String;
    flags: (0x0001) ACC_PUBLIC
    Code:
      stack=1, locals=1, args_size=1
         0: aload_0
         1: getfield      #12                 // Field environment:Ljava/lang/String;
         4: areturn
      LineNumberTable:
        line 112: 0
      LocalVariableTable:
        Start  Length  Slot  Name   Signature
            0       5     0  this   Lorg/kohsuke/github/GHDeployment;

  public boolean isTransientEnvironment();
    descriptor: ()Z
    flags: (0x0001) ACC_PUBLIC
    Code:
      stack=1, locals=1, args_size=1
         0: aload_0
         1: getfield      #13                 // Field transient_environment:Z
         4: ireturn
      LineNumberTable:
        line 125: 0
      LocalVariableTable:
        Start  Length  Slot  Name   Signature
            0       5     0  this   Lorg/kohsuke/github/GHDeployment;
    Deprecated: true
    RuntimeVisibleAnnotations:
      0: #77(#78=[e#79.#84])
        org.kohsuke.github.Preview(
          value=[Lorg/kohsuke/github/internal/Previews;.ANT_MAN]
        )

  public boolean isProductionEnvironment();
    descriptor: ()Z
    flags: (0x0001) ACC_PUBLIC
    Code:
      stack=1, locals=1, args_size=1
         0: aload_0
         1: getfield      #14                 // Field production_environment:Z
         4: ireturn
      LineNumberTable:
        line 137: 0
      LocalVariableTable:
        Start  Length  Slot  Name   Signature
            0       5     0  this   Lorg/kohsuke/github/GHDeployment;
    Deprecated: true
    RuntimeVisibleAnnotations:
      0: #77(#78=[e#79.#84])
        org.kohsuke.github.Preview(
          value=[Lorg/kohsuke/github/internal/Previews;.ANT_MAN]
        )

  public org.kohsuke.github.GHUser getCreator() throws java.io.IOException;
    descriptor: ()Lorg/kohsuke/github/GHUser;
    flags: (0x0001) ACC_PUBLIC
    Code:
      stack=2, locals=1, args_size=1
         0: aload_0
         1: invokevirtual #15                 // Method root:()Lorg/kohsuke/github/GitHub;
         4: aload_0
         5: getfield      #16                 // Field creator:Lorg/kohsuke/github/GHUser;
         8: invokevirtual #17                 // Method org/kohsuke/github/GitHub.intern:(Lorg/kohsuke/github/GHUser;)Lorg/kohsuke/github/GHUser;
        11: areturn
      LineNumberTable:
        line 148: 0
      LocalVariableTable:
        Start  Length  Slot  Name   Signature
            0      12     0  this   Lorg/kohsuke/github/GHDeployment;
    Exceptions:
      throws java.io.IOException

  public java.lang.String getRef();
    descriptor: ()Ljava/lang/String;
    flags: (0x0001) ACC_PUBLIC
    Code:
      stack=1, locals=1, args_size=1
         0: aload_0
         1: getfield      #18                 // Field ref:Ljava/lang/String;
         4: areturn
      LineNumberTable:
        line 157: 0
      LocalVariableTable:
        Start  Length  Slot  Name   Signature
            0       5     0  this   Lorg/kohsuke/github/GHDeployment;

  public java.lang.String getSha();
    descriptor: ()Ljava/lang/String;
    flags: (0x0001) ACC_PUBLIC
    Code:
      stack=1, locals=1, args_size=1
         0: aload_0
         1: getfield      #19                 // Field sha:Ljava/lang/String;
         4: areturn
      LineNumberTable:
        line 166: 0
      LocalVariableTable:
        Start  Length  Slot  Name   Signature
            0       5     0  this   Lorg/kohsuke/github/GHDeployment;

  public java.net.URL getHtmlUrl();
    descriptor: ()Ljava/net/URL;
    flags: (0x0001) ACC_PUBLIC
    Code:
      stack=1, locals=1, args_size=1
         0: aconst_null
         1: areturn
      LineNumberTable:
        line 174: 0
      LocalVariableTable:
        Start  Length  Slot  Name   Signature
            0       2     0  this   Lorg/kohsuke/github/GHDeployment;
    Deprecated: true

  public org.kohsuke.github.GHDeploymentStatusBuilder createStatus(org.kohsuke.github.GHDeploymentState);
    descriptor: (Lorg/kohsuke/github/GHDeploymentState;)Lorg/kohsuke/github/GHDeploymentStatusBuilder;
    flags: (0x0001) ACC_PUBLIC
    Code:
      stack=6, locals=2, args_size=2
         0: new           #20                 // class org/kohsuke/github/GHDeploymentStatusBuilder
         3: dup
         4: aload_0
         5: getfield      #2                  // Field owner:Lorg/kohsuke/github/GHRepository;
         8: aload_0
         9: invokevirtual #21                 // Method getId:()J
        12: aload_1
        13: invokespecial #22                 // Method org/kohsuke/github/GHDeploymentStatusBuilder."<init>":(Lorg/kohsuke/github/GHRepository;JLorg/kohsuke/github/GHDeploymentState;)V
        16: areturn
      LineNumberTable:
        line 185: 0
      LocalVariableTable:
        Start  Length  Slot  Name   Signature
            0      17     0  this   Lorg/kohsuke/github/GHDeployment;
            0      17     1 state   Lorg/kohsuke/github/GHDeploymentState;

  public org.kohsuke.github.PagedIterable<org.kohsuke.github.GHDeploymentStatus> listStatuses();
    descriptor: ()Lorg/kohsuke/github/PagedIterable;
    flags: (0x0001) ACC_PUBLIC
    Code:
      stack=3, locals=1, args_size=1
         0: aload_0
         1: invokevirtual #15                 // Method root:()Lorg/kohsuke/github/GitHub;
         4: invokevirtual #23                 // Method org/kohsuke/github/GitHub.createRequest:()Lorg/kohsuke/github/Requester;
         7: aload_0
         8: getfield      #3                  // Field statuses_url:Ljava/lang/String;
        11: iconst_0
        12: anewarray     #8                  // class java/lang/String
        15: invokevirtual #24                 // Method org/kohsuke/github/Requester.withUrlPath:(Ljava/lang/String;[Ljava/lang/String;)Lorg/kohsuke/github/GitHubRequest$Builder;
        18: checkcast     #25                 // class org/kohsuke/github/Requester
        21: getstatic     #26                 // Field org/kohsuke/github/internal/Previews.ANT_MAN:Lorg/kohsuke/github/internal/Previews;
        24: invokevirtual #27                 // Method org/kohsuke/github/Requester.withPreview:(Lorg/kohsuke/github/internal/Previews;)Lorg/kohsuke/github/GitHubRequest$Builder;
        27: checkcast     #25                 // class org/kohsuke/github/Requester
        30: getstatic     #28                 // Field org/kohsuke/github/internal/Previews.FLASH:Lorg/kohsuke/github/internal/Previews;
        33: invokevirtual #27                 // Method org/kohsuke/github/Requester.withPreview:(Lorg/kohsuke/github/internal/Previews;)Lorg/kohsuke/github/GitHubRequest$Builder;
        36: checkcast     #25                 // class org/kohsuke/github/Requester
        39: ldc           #29                 // class "[Lorg/kohsuke/github/GHDeploymentStatus;"
        41: aload_0
        42: invokedynamic #30,  0             // InvokeDynamic #0:accept:(Lorg/kohsuke/github/GHDeployment;)Ljava/util/function/Consumer;
        47: invokevirtual #31                 // Method org/kohsuke/github/Requester.toIterable:(Ljava/lang/Class;Ljava/util/function/Consumer;)Lorg/kohsuke/github/PagedIterable;
        50: areturn
      LineNumberTable:
        line 194: 0
        line 195: 15
        line 196: 24
        line 197: 33
        line 198: 47
        line 194: 50
      LocalVariableTable:
        Start  Length  Slot  Name   Signature
            0      51     0  this   Lorg/kohsuke/github/GHDeployment;
    Signature: #99                          // ()Lorg/kohsuke/github/PagedIterable<Lorg/kohsuke/github/GHDeploymentStatus;>;

  org.kohsuke.github.GHRepository getOwner();
    descriptor: ()Lorg/kohsuke/github/GHRepository;
    flags: (0x0000)
    Code:
      stack=1, locals=1, args_size=1
         0: aload_0
         1: getfield      #2                  // Field owner:Lorg/kohsuke/github/GHRepository;
         4: areturn
      LineNumberTable:
        line 203: 0
      LocalVariableTable:
        Start  Length  Slot  Name   Signature
            0       5     0  this   Lorg/kohsuke/github/GHDeployment;

  private void lambda$listStatuses$0(org.kohsuke.github.GHDeploymentStatus);
    descriptor: (Lorg/kohsuke/github/GHDeploymentStatus;)V
    flags: (0x1002) ACC_PRIVATE, ACC_SYNTHETIC
    Code:
      stack=2, locals=2, args_size=2
         0: aload_1
         1: aload_0
         2: getfield      #2                  // Field owner:Lorg/kohsuke/github/GHRepository;
         5: invokevirtual #32                 // Method org/kohsuke/github/GHDeploymentStatus.lateBind:(Lorg/kohsuke/github/GHRepository;)Lorg/kohsuke/github/GHDeploymentStatus;
         8: pop
         9: return
      LineNumberTable:
        line 198: 0
      LocalVariableTable:
        Start  Length  Slot  Name   Signature
            0      10     0  this   Lorg/kohsuke/github/GHDeployment;
            0      10     1  item   Lorg/kohsuke/github/GHDeploymentStatus;
}
SourceFile: "GHDeployment.java"
InnerClasses:
  static #171= #170 of #187;              // Builder=class org/kohsuke/github/GitHubRequest$Builder of class org/kohsuke/github/GitHubRequest
  public static final #196= #195 of #198; // Lookup=class java/lang/invoke/MethodHandles$Lookup of class java/lang/invoke/MethodHandles
BootstrapMethods:
  0: #142 REF_invokeStatic java/lang/invoke/LambdaMetafactory.metafactory:(Ljava/lang/invoke/MethodHandles$Lookup;Ljava/lang/String;Ljava/lang/invoke/MethodType;Ljava/lang/invoke/MethodType;Ljava/lang/invoke/MethodHandle;Ljava/lang/invoke/MethodType;)Ljava/lang/invoke/CallSite;
    Method arguments:
      #143 (Ljava/lang/Object;)V
      #144 REF_invokeSpecial org/kohsuke/github/GHDeployment.lambda$listStatuses$0:(Lorg/kohsuke/github/GHDeploymentStatus;)V
      #145 (Lorg/kohsuke/github/GHDeploymentStatus;)V
