Classfile /Users/mw/Projects/slang-braindump/.jar/jar11/assemble/slang-braindump/assemble/content/org/kohsuke/github/GHDeploymentBuilder.class
  Last modified May 29, 2022; size 3938 bytes
  SHA-256 checksum 9a28a49d75c66d5692de199fe5f321640f2ef0ffc1340de11d0f1e94500945c2
  Compiled from "GHDeploymentBuilder.java"
public class org.kohsuke.github.GHDeploymentBuilder
  minor version: 0
  major version: 52
  flags: (0x0021) ACC_PUBLIC, ACC_SUPER
  this_class: #33                         // org/kohsuke/github/GHDeploymentBuilder
  super_class: #34                        // java/lang/Object
  interfaces: 0, fields: 2, methods: 12, attributes: 2
Constant pool:
    #1 = Methodref          #34.#84       // java/lang/Object."<init>":()V
    #2 = Fieldref           #33.#85       // org/kohsuke/github/GHDeploymentBuilder.repo:Lorg/kohsuke/github/GHRepository;
    #3 = Methodref          #86.#87       // org/kohsuke/github/GHRepository.root:()Lorg/kohsuke/github/GitHub;
    #4 = Methodref          #88.#89       // org/kohsuke/github/GitHub.createRequest:()Lorg/kohsuke/github/Requester;
    #5 = Fieldref           #90.#91       // org/kohsuke/github/internal/Previews.ANT_MAN:Lorg/kohsuke/github/internal/Previews;
    #6 = Methodref          #7.#92        // org/kohsuke/github/Requester.withPreview:(Lorg/kohsuke/github/internal/Previews;)Lorg/kohsuke/github/GitHubRequest$Builder;
    #7 = Class              #93           // org/kohsuke/github/Requester
    #8 = Fieldref           #90.#94       // org/kohsuke/github/internal/Previews.FLASH:Lorg/kohsuke/github/internal/Previews;
    #9 = String             #95           // POST
   #10 = Methodref          #7.#96        // org/kohsuke/github/Requester.method:(Ljava/lang/String;)Lorg/kohsuke/github/GitHubRequest$Builder;
   #11 = Fieldref           #33.#97       // org/kohsuke/github/GHDeploymentBuilder.builder:Lorg/kohsuke/github/Requester;
   #12 = Methodref          #33.#98       // org/kohsuke/github/GHDeploymentBuilder."<init>":(Lorg/kohsuke/github/GHRepository;)V
   #13 = Methodref          #33.#99       // org/kohsuke/github/GHDeploymentBuilder.ref:(Ljava/lang/String;)Lorg/kohsuke/github/GHDeploymentBuilder;
   #14 = String             #53           // ref
   #15 = Methodref          #7.#100       // org/kohsuke/github/Requester.with:(Ljava/lang/String;Ljava/lang/String;)Lorg/kohsuke/github/GitHubRequest$Builder;
   #16 = String             #57           // task
   #17 = String             #101          // auto_merge
   #18 = Methodref          #7.#102       // org/kohsuke/github/Requester.with:(Ljava/lang/String;Z)Lorg/kohsuke/github/GitHubRequest$Builder;
   #19 = String             #103          // required_contexts
   #20 = Methodref          #7.#104       // org/kohsuke/github/Requester.with:(Ljava/lang/String;Ljava/util/Collection;)Lorg/kohsuke/github/GitHubRequest$Builder;
   #21 = String             #68           // payload
   #22 = String             #69           // environment
   #23 = String             #105          // transient_environment
   #24 = String             #106          // production_environment
   #25 = String             #77           // description
   #26 = String             #107          // deployments
   #27 = Methodref          #86.#108      // org/kohsuke/github/GHRepository.getApiTailUrl:(Ljava/lang/String;)Ljava/lang/String;
   #28 = Class              #109          // java/lang/String
   #29 = Methodref          #7.#110       // org/kohsuke/github/Requester.withUrlPath:(Ljava/lang/String;[Ljava/lang/String;)Lorg/kohsuke/github/GitHubRequest$Builder;
   #30 = Class              #111          // org/kohsuke/github/GHDeployment
   #31 = Methodref          #7.#112       // org/kohsuke/github/Requester.fetch:(Ljava/lang/Class;)Ljava/lang/Object;
   #32 = Methodref          #30.#113      // org/kohsuke/github/GHDeployment.wrap:(Lorg/kohsuke/github/GHRepository;)Lorg/kohsuke/github/GHDeployment;
   #33 = Class              #114          // org/kohsuke/github/GHDeploymentBuilder
   #34 = Class              #115          // java/lang/Object
   #35 = Utf8               repo
   #36 = Utf8               Lorg/kohsuke/github/GHRepository;
   #37 = Utf8               builder
   #38 = Utf8               Lorg/kohsuke/github/Requester;
   #39 = Utf8               <init>
   #40 = Utf8               (Lorg/kohsuke/github/GHRepository;)V
   #41 = Utf8               Code
   #42 = Utf8               LineNumberTable
   #43 = Utf8               LocalVariableTable
   #44 = Utf8               this
   #45 = Utf8               Lorg/kohsuke/github/GHDeploymentBuilder;
   #46 = Utf8               RuntimeInvisibleAnnotations
   #47 = Utf8               Ledu/umd/cs/findbugs/annotations/SuppressFBWarnings;
   #48 = Utf8               value
   #49 = Utf8               EI_EXPOSE_REP2
   #50 = Utf8               justification
   #51 = Utf8               Acceptable
   #52 = Utf8               (Lorg/kohsuke/github/GHRepository;Ljava/lang/String;)V
   #53 = Utf8               ref
   #54 = Utf8               Ljava/lang/String;
   #55 = Utf8               (Ljava/lang/String;)Lorg/kohsuke/github/GHDeploymentBuilder;
   #56 = Utf8               branch
   #57 = Utf8               task
   #58 = Utf8               autoMerge
   #59 = Utf8               (Z)Lorg/kohsuke/github/GHDeploymentBuilder;
   #60 = Utf8               Z
   #61 = Utf8               requiredContexts
   #62 = Utf8               (Ljava/util/List;)Lorg/kohsuke/github/GHDeploymentBuilder;
   #63 = Utf8               Ljava/util/List;
   #64 = Utf8               LocalVariableTypeTable
   #65 = Utf8               Ljava/util/List<Ljava/lang/String;>;
   #66 = Utf8               Signature
   #67 = Utf8               (Ljava/util/List<Ljava/lang/String;>;)Lorg/kohsuke/github/GHDeploymentBuilder;
   #68 = Utf8               payload
   #69 = Utf8               environment
   #70 = Utf8               transientEnvironment
   #71 = Utf8               Deprecated
   #72 = Utf8               RuntimeVisibleAnnotations
   #73 = Utf8               Lorg/kohsuke/github/Preview;
   #74 = Utf8               Lorg/kohsuke/github/internal/Previews;
   #75 = Utf8               ANT_MAN
   #76 = Utf8               productionEnvironment
   #77 = Utf8               description
   #78 = Utf8               create
   #79 = Utf8               ()Lorg/kohsuke/github/GHDeployment;
   #80 = Utf8               Exceptions
   #81 = Class              #116          // java/io/IOException
   #82 = Utf8               SourceFile
   #83 = Utf8               GHDeploymentBuilder.java
   #84 = NameAndType        #39:#117      // "<init>":()V
   #85 = NameAndType        #35:#36       // repo:Lorg/kohsuke/github/GHRepository;
   #86 = Class              #118          // org/kohsuke/github/GHRepository
   #87 = NameAndType        #119:#120     // root:()Lorg/kohsuke/github/GitHub;
   #88 = Class              #121          // org/kohsuke/github/GitHub
   #89 = NameAndType        #122:#123     // createRequest:()Lorg/kohsuke/github/Requester;
   #90 = Class              #124          // org/kohsuke/github/internal/Previews
   #91 = NameAndType        #75:#74       // ANT_MAN:Lorg/kohsuke/github/internal/Previews;
   #92 = NameAndType        #125:#129     // withPreview:(Lorg/kohsuke/github/internal/Previews;)Lorg/kohsuke/github/GitHubRequest$Builder;
   #93 = Utf8               org/kohsuke/github/Requester
   #94 = NameAndType        #130:#74      // FLASH:Lorg/kohsuke/github/internal/Previews;
   #95 = Utf8               POST
   #96 = NameAndType        #131:#132     // method:(Ljava/lang/String;)Lorg/kohsuke/github/GitHubRequest$Builder;
   #97 = NameAndType        #37:#38       // builder:Lorg/kohsuke/github/Requester;
   #98 = NameAndType        #39:#40       // "<init>":(Lorg/kohsuke/github/GHRepository;)V
   #99 = NameAndType        #53:#55       // ref:(Ljava/lang/String;)Lorg/kohsuke/github/GHDeploymentBuilder;
  #100 = NameAndType        #133:#134     // with:(Ljava/lang/String;Ljava/lang/String;)Lorg/kohsuke/github/GitHubRequest$Builder;
  #101 = Utf8               auto_merge
  #102 = NameAndType        #133:#135     // with:(Ljava/lang/String;Z)Lorg/kohsuke/github/GitHubRequest$Builder;
  #103 = Utf8               required_contexts
  #104 = NameAndType        #133:#136     // with:(Ljava/lang/String;Ljava/util/Collection;)Lorg/kohsuke/github/GitHubRequest$Builder;
  #105 = Utf8               transient_environment
  #106 = Utf8               production_environment
  #107 = Utf8               deployments
  #108 = NameAndType        #137:#138     // getApiTailUrl:(Ljava/lang/String;)Ljava/lang/String;
  #109 = Utf8               java/lang/String
  #110 = NameAndType        #139:#140     // withUrlPath:(Ljava/lang/String;[Ljava/lang/String;)Lorg/kohsuke/github/GitHubRequest$Builder;
  #111 = Utf8               org/kohsuke/github/GHDeployment
  #112 = NameAndType        #141:#142     // fetch:(Ljava/lang/Class;)Ljava/lang/Object;
  #113 = NameAndType        #143:#144     // wrap:(Lorg/kohsuke/github/GHRepository;)Lorg/kohsuke/github/GHDeployment;
  #114 = Utf8               org/kohsuke/github/GHDeploymentBuilder
  #115 = Utf8               java/lang/Object
  #116 = Utf8               java/io/IOException
  #117 = Utf8               ()V
  #118 = Utf8               org/kohsuke/github/GHRepository
  #119 = Utf8               root
  #120 = Utf8               ()Lorg/kohsuke/github/GitHub;
  #121 = Utf8               org/kohsuke/github/GitHub
  #122 = Utf8               createRequest
  #123 = Utf8               ()Lorg/kohsuke/github/Requester;
  #124 = Utf8               org/kohsuke/github/internal/Previews
  #125 = Utf8               withPreview
  #126 = Class              #146          // org/kohsuke/github/GitHubRequest$Builder
  #127 = Utf8               Builder
  #128 = Utf8               InnerClasses
  #129 = Utf8               (Lorg/kohsuke/github/internal/Previews;)Lorg/kohsuke/github/GitHubRequest$Builder;
  #130 = Utf8               FLASH
  #131 = Utf8               method
  #132 = Utf8               (Ljava/lang/String;)Lorg/kohsuke/github/GitHubRequest$Builder;
  #133 = Utf8               with
  #134 = Utf8               (Ljava/lang/String;Ljava/lang/String;)Lorg/kohsuke/github/GitHubRequest$Builder;
  #135 = Utf8               (Ljava/lang/String;Z)Lorg/kohsuke/github/GitHubRequest$Builder;
  #136 = Utf8               (Ljava/lang/String;Ljava/util/Collection;)Lorg/kohsuke/github/GitHubRequest$Builder;
  #137 = Utf8               getApiTailUrl
  #138 = Utf8               (Ljava/lang/String;)Ljava/lang/String;
  #139 = Utf8               withUrlPath
  #140 = Utf8               (Ljava/lang/String;[Ljava/lang/String;)Lorg/kohsuke/github/GitHubRequest$Builder;
  #141 = Utf8               fetch
  #142 = Utf8               (Ljava/lang/Class;)Ljava/lang/Object;
  #143 = Utf8               wrap
  #144 = Utf8               (Lorg/kohsuke/github/GHRepository;)Lorg/kohsuke/github/GHDeployment;
  #145 = Class              #147          // org/kohsuke/github/GitHubRequest
  #146 = Utf8               org/kohsuke/github/GitHubRequest$Builder
  #147 = Utf8               org/kohsuke/github/GitHubRequest
{
  private final org.kohsuke.github.GHRepository repo;
    descriptor: Lorg/kohsuke/github/GHRepository;
    flags: (0x0012) ACC_PRIVATE, ACC_FINAL

  private final org.kohsuke.github.Requester builder;
    descriptor: Lorg/kohsuke/github/Requester;
    flags: (0x0012) ACC_PRIVATE, ACC_FINAL

  public org.kohsuke.github.GHDeploymentBuilder(org.kohsuke.github.GHRepository);
    descriptor: (Lorg/kohsuke/github/GHRepository;)V
    flags: (0x0001) ACC_PUBLIC
    Code:
      stack=3, locals=2, args_size=2
         0: aload_0
         1: invokespecial #1                  // Method java/lang/Object."<init>":()V
         4: aload_0
         5: aload_1
         6: putfield      #2                  // Field repo:Lorg/kohsuke/github/GHRepository;
         9: aload_0
        10: aload_1
        11: invokevirtual #3                  // Method org/kohsuke/github/GHRepository.root:()Lorg/kohsuke/github/GitHub;
        14: invokevirtual #4                  // Method org/kohsuke/github/GitHub.createRequest:()Lorg/kohsuke/github/Requester;
        17: getstatic     #5                  // Field org/kohsuke/github/internal/Previews.ANT_MAN:Lorg/kohsuke/github/internal/Previews;
        20: invokevirtual #6                  // Method org/kohsuke/github/Requester.withPreview:(Lorg/kohsuke/github/internal/Previews;)Lorg/kohsuke/github/GitHubRequest$Builder;
        23: checkcast     #7                  // class org/kohsuke/github/Requester
        26: getstatic     #8                  // Field org/kohsuke/github/internal/Previews.FLASH:Lorg/kohsuke/github/internal/Previews;
        29: invokevirtual #6                  // Method org/kohsuke/github/Requester.withPreview:(Lorg/kohsuke/github/internal/Previews;)Lorg/kohsuke/github/GitHubRequest$Builder;
        32: checkcast     #7                  // class org/kohsuke/github/Requester
        35: ldc           #9                  // String POST
        37: invokevirtual #10                 // Method org/kohsuke/github/Requester.method:(Ljava/lang/String;)Lorg/kohsuke/github/GitHubRequest$Builder;
        40: checkcast     #7                  // class org/kohsuke/github/Requester
        43: putfield      #11                 // Field builder:Lorg/kohsuke/github/Requester;
        46: return
      LineNumberTable:
        line 24: 0
        line 25: 4
        line 26: 9
        line 27: 14
        line 28: 20
        line 29: 29
        line 30: 37
        line 31: 46
      LocalVariableTable:
        Start  Length  Slot  Name   Signature
            0      47     0  this   Lorg/kohsuke/github/GHDeploymentBuilder;
            0      47     1  repo   Lorg/kohsuke/github/GHRepository;
    RuntimeInvisibleAnnotations:
      0: #47(#48=[s#49],#50=s#51)
        edu.umd.cs.findbugs.annotations.SuppressFBWarnings(
          value=["EI_EXPOSE_REP2"]
          justification="Acceptable"
        )

  public org.kohsuke.github.GHDeploymentBuilder(org.kohsuke.github.GHRepository, java.lang.String);
    descriptor: (Lorg/kohsuke/github/GHRepository;Ljava/lang/String;)V
    flags: (0x0001) ACC_PUBLIC
    Code:
      stack=2, locals=3, args_size=3
         0: aload_0
         1: aload_1
         2: invokespecial #12                 // Method "<init>":(Lorg/kohsuke/github/GHRepository;)V
         5: aload_0
         6: aload_2
         7: invokevirtual #13                 // Method ref:(Ljava/lang/String;)Lorg/kohsuke/github/GHDeploymentBuilder;
        10: pop
        11: return
      LineNumberTable:
        line 42: 0
        line 43: 5
        line 44: 11
      LocalVariableTable:
        Start  Length  Slot  Name   Signature
            0      12     0  this   Lorg/kohsuke/github/GHDeploymentBuilder;
            0      12     1  repo   Lorg/kohsuke/github/GHRepository;
            0      12     2   ref   Ljava/lang/String;

  public org.kohsuke.github.GHDeploymentBuilder ref(java.lang.String);
    descriptor: (Ljava/lang/String;)Lorg/kohsuke/github/GHDeploymentBuilder;
    flags: (0x0001) ACC_PUBLIC
    Code:
      stack=3, locals=2, args_size=2
         0: aload_0
         1: getfield      #11                 // Field builder:Lorg/kohsuke/github/Requester;
         4: ldc           #14                 // String ref
         6: aload_1
         7: invokevirtual #15                 // Method org/kohsuke/github/Requester.with:(Ljava/lang/String;Ljava/lang/String;)Lorg/kohsuke/github/GitHubRequest$Builder;
        10: pop
        11: aload_0
        12: areturn
      LineNumberTable:
        line 55: 0
        line 56: 11
      LocalVariableTable:
        Start  Length  Slot  Name   Signature
            0      13     0  this   Lorg/kohsuke/github/GHDeploymentBuilder;
            0      13     1 branch   Ljava/lang/String;

  public org.kohsuke.github.GHDeploymentBuilder task(java.lang.String);
    descriptor: (Ljava/lang/String;)Lorg/kohsuke/github/GHDeploymentBuilder;
    flags: (0x0001) ACC_PUBLIC
    Code:
      stack=3, locals=2, args_size=2
         0: aload_0
         1: getfield      #11                 // Field builder:Lorg/kohsuke/github/Requester;
         4: ldc           #16                 // String task
         6: aload_1
         7: invokevirtual #15                 // Method org/kohsuke/github/Requester.with:(Ljava/lang/String;Ljava/lang/String;)Lorg/kohsuke/github/GitHubRequest$Builder;
        10: pop
        11: aload_0
        12: areturn
      LineNumberTable:
        line 68: 0
        line 69: 11
      LocalVariableTable:
        Start  Length  Slot  Name   Signature
            0      13     0  this   Lorg/kohsuke/github/GHDeploymentBuilder;
            0      13     1  task   Ljava/lang/String;

  public org.kohsuke.github.GHDeploymentBuilder autoMerge(boolean);
    descriptor: (Z)Lorg/kohsuke/github/GHDeploymentBuilder;
    flags: (0x0001) ACC_PUBLIC
    Code:
      stack=3, locals=2, args_size=2
         0: aload_0
         1: getfield      #11                 // Field builder:Lorg/kohsuke/github/Requester;
         4: ldc           #17                 // String auto_merge
         6: iload_1
         7: invokevirtual #18                 // Method org/kohsuke/github/Requester.with:(Ljava/lang/String;Z)Lorg/kohsuke/github/GitHubRequest$Builder;
        10: pop
        11: aload_0
        12: areturn
      LineNumberTable:
        line 81: 0
        line 82: 11
      LocalVariableTable:
        Start  Length  Slot  Name   Signature
            0      13     0  this   Lorg/kohsuke/github/GHDeploymentBuilder;
            0      13     1 autoMerge   Z

  public org.kohsuke.github.GHDeploymentBuilder requiredContexts(java.util.List<java.lang.String>);
    descriptor: (Ljava/util/List;)Lorg/kohsuke/github/GHDeploymentBuilder;
    flags: (0x0001) ACC_PUBLIC
    Code:
      stack=3, locals=2, args_size=2
         0: aload_0
         1: getfield      #11                 // Field builder:Lorg/kohsuke/github/Requester;
         4: ldc           #19                 // String required_contexts
         6: aload_1
         7: invokevirtual #20                 // Method org/kohsuke/github/Requester.with:(Ljava/lang/String;Ljava/util/Collection;)Lorg/kohsuke/github/GitHubRequest$Builder;
        10: pop
        11: aload_0
        12: areturn
      LineNumberTable:
        line 94: 0
        line 95: 11
      LocalVariableTable:
        Start  Length  Slot  Name   Signature
            0      13     0  this   Lorg/kohsuke/github/GHDeploymentBuilder;
            0      13     1 requiredContexts   Ljava/util/List;
      LocalVariableTypeTable:
        Start  Length  Slot  Name   Signature
            0      13     1 requiredContexts   Ljava/util/List<Ljava/lang/String;>;
    Signature: #67                          // (Ljava/util/List<Ljava/lang/String;>;)Lorg/kohsuke/github/GHDeploymentBuilder;

  public org.kohsuke.github.GHDeploymentBuilder payload(java.lang.String);
    descriptor: (Ljava/lang/String;)Lorg/kohsuke/github/GHDeploymentBuilder;
    flags: (0x0001) ACC_PUBLIC
    Code:
      stack=3, locals=2, args_size=2
         0: aload_0
         1: getfield      #11                 // Field builder:Lorg/kohsuke/github/Requester;
         4: ldc           #21                 // String payload
         6: aload_1
         7: invokevirtual #15                 // Method org/kohsuke/github/Requester.with:(Ljava/lang/String;Ljava/lang/String;)Lorg/kohsuke/github/GitHubRequest$Builder;
        10: pop
        11: aload_0
        12: areturn
      LineNumberTable:
        line 107: 0
        line 108: 11
      LocalVariableTable:
        Start  Length  Slot  Name   Signature
            0      13     0  this   Lorg/kohsuke/github/GHDeploymentBuilder;
            0      13     1 payload   Ljava/lang/String;

  public org.kohsuke.github.GHDeploymentBuilder environment(java.lang.String);
    descriptor: (Ljava/lang/String;)Lorg/kohsuke/github/GHDeploymentBuilder;
    flags: (0x0001) ACC_PUBLIC
    Code:
      stack=3, locals=2, args_size=2
         0: aload_0
         1: getfield      #11                 // Field builder:Lorg/kohsuke/github/Requester;
         4: ldc           #22                 // String environment
         6: aload_1
         7: invokevirtual #15                 // Method org/kohsuke/github/Requester.with:(Ljava/lang/String;Ljava/lang/String;)Lorg/kohsuke/github/GitHubRequest$Builder;
        10: pop
        11: aload_0
        12: areturn
      LineNumberTable:
        line 120: 0
        line 121: 11
      LocalVariableTable:
        Start  Length  Slot  Name   Signature
            0      13     0  this   Lorg/kohsuke/github/GHDeploymentBuilder;
            0      13     1 environment   Ljava/lang/String;

  public org.kohsuke.github.GHDeploymentBuilder transientEnvironment(boolean);
    descriptor: (Z)Lorg/kohsuke/github/GHDeploymentBuilder;
    flags: (0x0001) ACC_PUBLIC
    Code:
      stack=3, locals=2, args_size=2
         0: aload_0
         1: getfield      #11                 // Field builder:Lorg/kohsuke/github/Requester;
         4: ldc           #23                 // String transient_environment
         6: iload_1
         7: invokevirtual #18                 // Method org/kohsuke/github/Requester.with:(Ljava/lang/String;Z)Lorg/kohsuke/github/GitHubRequest$Builder;
        10: pop
        11: aload_0
        12: areturn
      LineNumberTable:
        line 137: 0
        line 138: 11
      LocalVariableTable:
        Start  Length  Slot  Name   Signature
            0      13     0  this   Lorg/kohsuke/github/GHDeploymentBuilder;
            0      13     1 transientEnvironment   Z
    Deprecated: true
    RuntimeVisibleAnnotations:
      0: #73(#48=[e#74.#75])
        org.kohsuke.github.Preview(
          value=[Lorg/kohsuke/github/internal/Previews;.ANT_MAN]
        )

  public org.kohsuke.github.GHDeploymentBuilder productionEnvironment(boolean);
    descriptor: (Z)Lorg/kohsuke/github/GHDeploymentBuilder;
    flags: (0x0001) ACC_PUBLIC
    Code:
      stack=3, locals=2, args_size=2
         0: aload_0
         1: getfield      #11                 // Field builder:Lorg/kohsuke/github/Requester;
         4: ldc           #24                 // String production_environment
         6: iload_1
         7: invokevirtual #18                 // Method org/kohsuke/github/Requester.with:(Ljava/lang/String;Z)Lorg/kohsuke/github/GitHubRequest$Builder;
        10: pop
        11: aload_0
        12: areturn
      LineNumberTable:
        line 153: 0
        line 154: 11
      LocalVariableTable:
        Start  Length  Slot  Name   Signature
            0      13     0  this   Lorg/kohsuke/github/GHDeploymentBuilder;
            0      13     1 productionEnvironment   Z
    Deprecated: true
    RuntimeVisibleAnnotations:
      0: #73(#48=[e#74.#75])
        org.kohsuke.github.Preview(
          value=[Lorg/kohsuke/github/internal/Previews;.ANT_MAN]
        )

  public org.kohsuke.github.GHDeploymentBuilder description(java.lang.String);
    descriptor: (Ljava/lang/String;)Lorg/kohsuke/github/GHDeploymentBuilder;
    flags: (0x0001) ACC_PUBLIC
    Code:
      stack=3, locals=2, args_size=2
         0: aload_0
         1: getfield      #11                 // Field builder:Lorg/kohsuke/github/Requester;
         4: ldc           #25                 // String description
         6: aload_1
         7: invokevirtual #15                 // Method org/kohsuke/github/Requester.with:(Ljava/lang/String;Ljava/lang/String;)Lorg/kohsuke/github/GitHubRequest$Builder;
        10: pop
        11: aload_0
        12: areturn
      LineNumberTable:
        line 166: 0
        line 167: 11
      LocalVariableTable:
        Start  Length  Slot  Name   Signature
            0      13     0  this   Lorg/kohsuke/github/GHDeploymentBuilder;
            0      13     1 description   Ljava/lang/String;

  public org.kohsuke.github.GHDeployment create() throws java.io.IOException;
    descriptor: ()Lorg/kohsuke/github/GHDeployment;
    flags: (0x0001) ACC_PUBLIC
    Code:
      stack=3, locals=1, args_size=1
         0: aload_0
         1: getfield      #11                 // Field builder:Lorg/kohsuke/github/Requester;
         4: aload_0
         5: getfield      #2                  // Field repo:Lorg/kohsuke/github/GHRepository;
         8: ldc           #26                 // String deployments
        10: invokevirtual #27                 // Method org/kohsuke/github/GHRepository.getApiTailUrl:(Ljava/lang/String;)Ljava/lang/String;
        13: iconst_0
        14: anewarray     #28                 // class java/lang/String
        17: invokevirtual #29                 // Method org/kohsuke/github/Requester.withUrlPath:(Ljava/lang/String;[Ljava/lang/String;)Lorg/kohsuke/github/GitHubRequest$Builder;
        20: checkcast     #7                  // class org/kohsuke/github/Requester
        23: ldc           #30                 // class org/kohsuke/github/GHDeployment
        25: invokevirtual #31                 // Method org/kohsuke/github/Requester.fetch:(Ljava/lang/Class;)Ljava/lang/Object;
        28: checkcast     #30                 // class org/kohsuke/github/GHDeployment
        31: aload_0
        32: getfield      #2                  // Field repo:Lorg/kohsuke/github/GHRepository;
        35: invokevirtual #32                 // Method org/kohsuke/github/GHDeployment.wrap:(Lorg/kohsuke/github/GHRepository;)Lorg/kohsuke/github/GHDeployment;
        38: areturn
      LineNumberTable:
        line 179: 0
      LocalVariableTable:
        Start  Length  Slot  Name   Signature
            0      39     0  this   Lorg/kohsuke/github/GHDeploymentBuilder;
    Exceptions:
      throws java.io.IOException
}
SourceFile: "GHDeploymentBuilder.java"
InnerClasses:
  static #127= #126 of #145;              // Builder=class org/kohsuke/github/GitHubRequest$Builder of class org/kohsuke/github/GitHubRequest
