Classfile /Users/mw/Projects/slang-braindump/.jar/jar11/assemble/slang-braindump/assemble/content/org/kohsuke/github/GHFileNotFoundException.class
  Last modified May 29, 2022; size 1676 bytes
  SHA-256 checksum eb29b9d98a13f0d9301efb0d846e71df7740d1576cc882054b5ed27e87c8205c
  Compiled from "GHFileNotFoundException.java"
public class org.kohsuke.github.GHFileNotFoundException extends java.io.FileNotFoundException
  minor version: 0
  major version: 52
  flags: (0x0021) ACC_PUBLIC, ACC_SUPER
  this_class: #6                          // org/kohsuke/github/GHFileNotFoundException
  super_class: #7                         // java/io/FileNotFoundException
  interfaces: 0, fields: 1, methods: 5, attributes: 1
Constant pool:
   #1 = Methodref          #7.#39         // java/io/FileNotFoundException."<init>":()V
   #2 = Methodref          #7.#40         // java/io/FileNotFoundException."<init>":(Ljava/lang/String;)V
   #3 = Methodref          #6.#41         // org/kohsuke/github/GHFileNotFoundException.initCause:(Ljava/lang/Throwable;)Ljava/lang/Throwable;
   #4 = Fieldref           #6.#42         // org/kohsuke/github/GHFileNotFoundException.responseHeaderFields:Ljava/util/Map;
   #5 = Methodref          #43.#44        // java/util/Collections.unmodifiableMap:(Ljava/util/Map;)Ljava/util/Map;
   #6 = Class              #45            // org/kohsuke/github/GHFileNotFoundException
   #7 = Class              #46            // java/io/FileNotFoundException
   #8 = Utf8               responseHeaderFields
   #9 = Utf8               Ljava/util/Map;
  #10 = Utf8               Signature
  #11 = Utf8               Ljava/util/Map<Ljava/lang/String;Ljava/util/List<Ljava/lang/String;>;>;
  #12 = Utf8               <init>
  #13 = Utf8               ()V
  #14 = Utf8               Code
  #15 = Utf8               LineNumberTable
  #16 = Utf8               LocalVariableTable
  #17 = Utf8               this
  #18 = Utf8               Lorg/kohsuke/github/GHFileNotFoundException;
  #19 = Utf8               (Ljava/lang/String;)V
  #20 = Utf8               message
  #21 = Utf8               Ljava/lang/String;
  #22 = Utf8               (Ljava/lang/String;Ljava/lang/Throwable;)V
  #23 = Utf8               cause
  #24 = Utf8               Ljava/lang/Throwable;
  #25 = Utf8               getResponseHeaderFields
  #26 = Utf8               ()Ljava/util/Map;
  #27 = Utf8               ()Ljava/util/Map<Ljava/lang/String;Ljava/util/List<Ljava/lang/String;>;>;
  #28 = Utf8               RuntimeVisibleAnnotations
  #29 = Utf8               Ljavax/annotation/CheckForNull;
  #30 = Utf8               withResponseHeaderFields
  #31 = Utf8               (Ljava/util/Map;)Lorg/kohsuke/github/GHFileNotFoundException;
  #32 = Utf8               headerFields
  #33 = Utf8               LocalVariableTypeTable
  #34 = Utf8               (Ljava/util/Map<Ljava/lang/String;Ljava/util/List<Ljava/lang/String;>;>;)Lorg/kohsuke/github/GHFileNotFoundException;
  #35 = Utf8               RuntimeVisibleParameterAnnotations
  #36 = Utf8               Ljavax/annotation/Nonnull;
  #37 = Utf8               SourceFile
  #38 = Utf8               GHFileNotFoundException.java
  #39 = NameAndType        #12:#13        // "<init>":()V
  #40 = NameAndType        #12:#19        // "<init>":(Ljava/lang/String;)V
  #41 = NameAndType        #47:#48        // initCause:(Ljava/lang/Throwable;)Ljava/lang/Throwable;
  #42 = NameAndType        #8:#9          // responseHeaderFields:Ljava/util/Map;
  #43 = Class              #49            // java/util/Collections
  #44 = NameAndType        #50:#51        // unmodifiableMap:(Ljava/util/Map;)Ljava/util/Map;
  #45 = Utf8               org/kohsuke/github/GHFileNotFoundException
  #46 = Utf8               java/io/FileNotFoundException
  #47 = Utf8               initCause
  #48 = Utf8               (Ljava/lang/Throwable;)Ljava/lang/Throwable;
  #49 = Utf8               java/util/Collections
  #50 = Utf8               unmodifiableMap
  #51 = Utf8               (Ljava/util/Map;)Ljava/util/Map;
{
  protected java.util.Map<java.lang.String, java.util.List<java.lang.String>> responseHeaderFields;
    descriptor: Ljava/util/Map;
    flags: (0x0004) ACC_PROTECTED
    Signature: #11                          // Ljava/util/Map<Ljava/lang/String;Ljava/util/List<Ljava/lang/String;>;>;

  public org.kohsuke.github.GHFileNotFoundException();
    descriptor: ()V
    flags: (0x0001) ACC_PUBLIC
    Code:
      stack=1, locals=1, args_size=1
         0: aload_0
         1: invokespecial #1                  // Method java/io/FileNotFoundException."<init>":()V
         4: return
      LineNumberTable:
        line 22: 0
        line 23: 4
      LocalVariableTable:
        Start  Length  Slot  Name   Signature
            0       5     0  this   Lorg/kohsuke/github/GHFileNotFoundException;

  public org.kohsuke.github.GHFileNotFoundException(java.lang.String);
    descriptor: (Ljava/lang/String;)V
    flags: (0x0001) ACC_PUBLIC
    Code:
      stack=2, locals=2, args_size=2
         0: aload_0
         1: aload_1
         2: invokespecial #2                  // Method java/io/FileNotFoundException."<init>":(Ljava/lang/String;)V
         5: return
      LineNumberTable:
        line 32: 0
        line 33: 5
      LocalVariableTable:
        Start  Length  Slot  Name   Signature
            0       6     0  this   Lorg/kohsuke/github/GHFileNotFoundException;
            0       6     1 message   Ljava/lang/String;

  public org.kohsuke.github.GHFileNotFoundException(java.lang.String, java.lang.Throwable);
    descriptor: (Ljava/lang/String;Ljava/lang/Throwable;)V
    flags: (0x0001) ACC_PUBLIC
    Code:
      stack=2, locals=3, args_size=3
         0: aload_0
         1: aload_1
         2: invokespecial #2                  // Method java/io/FileNotFoundException."<init>":(Ljava/lang/String;)V
         5: aload_0
         6: aload_2
         7: invokevirtual #3                  // Method initCause:(Ljava/lang/Throwable;)Ljava/lang/Throwable;
        10: pop
        11: return
      LineNumberTable:
        line 44: 0
        line 45: 5
        line 46: 11
      LocalVariableTable:
        Start  Length  Slot  Name   Signature
            0      12     0  this   Lorg/kohsuke/github/GHFileNotFoundException;
            0      12     1 message   Ljava/lang/String;
            0      12     2 cause   Ljava/lang/Throwable;

  public java.util.Map<java.lang.String, java.util.List<java.lang.String>> getResponseHeaderFields();
    descriptor: ()Ljava/util/Map;
    flags: (0x0001) ACC_PUBLIC
    Code:
      stack=1, locals=1, args_size=1
         0: aload_0
         1: getfield      #4                  // Field responseHeaderFields:Ljava/util/Map;
         4: invokestatic  #5                  // Method java/util/Collections.unmodifiableMap:(Ljava/util/Map;)Ljava/util/Map;
         7: areturn
      LineNumberTable:
        line 55: 0
      LocalVariableTable:
        Start  Length  Slot  Name   Signature
            0       8     0  this   Lorg/kohsuke/github/GHFileNotFoundException;
    Signature: #27                          // ()Ljava/util/Map<Ljava/lang/String;Ljava/util/List<Ljava/lang/String;>;>;
    RuntimeVisibleAnnotations:
      0: #29()
        javax.annotation.CheckForNull

  org.kohsuke.github.GHFileNotFoundException withResponseHeaderFields(java.util.Map<java.lang.String, java.util.List<java.lang.String>>);
    descriptor: (Ljava/util/Map;)Lorg/kohsuke/github/GHFileNotFoundException;
    flags: (0x0000)
    Code:
      stack=2, locals=2, args_size=2
         0: aload_0
         1: aload_1
         2: putfield      #4                  // Field responseHeaderFields:Ljava/util/Map;
         5: aload_0
         6: areturn
      LineNumberTable:
        line 59: 0
        line 60: 5
      LocalVariableTable:
        Start  Length  Slot  Name   Signature
            0       7     0  this   Lorg/kohsuke/github/GHFileNotFoundException;
            0       7     1 headerFields   Ljava/util/Map;
      LocalVariableTypeTable:
        Start  Length  Slot  Name   Signature
            0       7     1 headerFields   Ljava/util/Map<Ljava/lang/String;Ljava/util/List<Ljava/lang/String;>;>;
    Signature: #34                          // (Ljava/util/Map<Ljava/lang/String;Ljava/util/List<Ljava/lang/String;>;>;)Lorg/kohsuke/github/GHFileNotFoundException;
    RuntimeVisibleParameterAnnotations:
      parameter 0:
        0: #36()
          javax.annotation.Nonnull
}
SourceFile: "GHFileNotFoundException.java"
