Classfile /Users/mw/Projects/slang-braindump/.jar/jar11/assemble/slang-braindump/assemble/content/org/kohsuke/github/GHIssueEvent.class
  Last modified May 29, 2022; size 3614 bytes
  SHA-256 checksum b33e1a5e60853d51103b276aee9c424f8db96e81ca1706312530c9da80af73cb
  Compiled from "GHIssueEvent.java"
public class org.kohsuke.github.GHIssueEvent extends org.kohsuke.github.GitHubInteractiveObject
  minor version: 0
  major version: 52
  flags: (0x0021) ACC_PUBLIC, ACC_SUPER
  this_class: #30                         // org/kohsuke/github/GHIssueEvent
  super_class: #31                        // org/kohsuke/github/GitHubInteractiveObject
  interfaces: 0, fields: 15, methods: 19, attributes: 1
Constant pool:
    #1 = Methodref          #31.#100      // org/kohsuke/github/GitHubInteractiveObject."<init>":()V
    #2 = Fieldref           #30.#101      // org/kohsuke/github/GHIssueEvent.id:J
    #3 = Fieldref           #30.#102      // org/kohsuke/github/GHIssueEvent.node_id:Ljava/lang/String;
    #4 = Fieldref           #30.#103      // org/kohsuke/github/GHIssueEvent.url:Ljava/lang/String;
    #5 = Fieldref           #30.#104      // org/kohsuke/github/GHIssueEvent.actor:Lorg/kohsuke/github/GHUser;
    #6 = Fieldref           #30.#105      // org/kohsuke/github/GHIssueEvent.event:Ljava/lang/String;
    #7 = Fieldref           #30.#106      // org/kohsuke/github/GHIssueEvent.commit_id:Ljava/lang/String;
    #8 = Fieldref           #30.#107      // org/kohsuke/github/GHIssueEvent.commit_url:Ljava/lang/String;
    #9 = Fieldref           #30.#108      // org/kohsuke/github/GHIssueEvent.created_at:Ljava/lang/String;
   #10 = Methodref          #109.#110     // org/kohsuke/github/GitHubClient.parseDate:(Ljava/lang/String;)Ljava/util/Date;
   #11 = Fieldref           #30.#111      // org/kohsuke/github/GHIssueEvent.issue:Lorg/kohsuke/github/GHIssue;
   #12 = Fieldref           #30.#112      // org/kohsuke/github/GHIssueEvent.milestone:Lorg/kohsuke/github/GHMilestone;
   #13 = Fieldref           #30.#113      // org/kohsuke/github/GHIssueEvent.label:Lorg/kohsuke/github/GHLabel;
   #14 = Fieldref           #30.#114      // org/kohsuke/github/GHIssueEvent.assignee:Lorg/kohsuke/github/GHUser;
   #15 = Fieldref           #30.#115      // org/kohsuke/github/GHIssueEvent.rename:Lorg/kohsuke/github/GHIssueRename;
   #16 = Fieldref           #30.#116      // org/kohsuke/github/GHIssueEvent.reviewRequester:Lorg/kohsuke/github/GHUser;
   #17 = Fieldref           #30.#117      // org/kohsuke/github/GHIssueEvent.requestedReviewer:Lorg/kohsuke/github/GHUser;
   #18 = String             #118          // Issue %d was %s by %s on %s
   #19 = Class              #119          // java/lang/Object
   #20 = Methodref          #30.#120      // org/kohsuke/github/GHIssueEvent.getIssue:()Lorg/kohsuke/github/GHIssue;
   #21 = Methodref          #121.#122     // org/kohsuke/github/GHIssue.getNumber:()I
   #22 = Methodref          #123.#124     // java/lang/Integer.valueOf:(I)Ljava/lang/Integer;
   #23 = Methodref          #30.#125      // org/kohsuke/github/GHIssueEvent.getEvent:()Ljava/lang/String;
   #24 = Methodref          #30.#126      // org/kohsuke/github/GHIssueEvent.getActor:()Lorg/kohsuke/github/GHUser;
   #25 = Methodref          #127.#128     // org/kohsuke/github/GHUser.getLogin:()Ljava/lang/String;
   #26 = Methodref          #30.#129      // org/kohsuke/github/GHIssueEvent.getCreatedAt:()Ljava/util/Date;
   #27 = Methodref          #130.#131     // java/util/Date.toString:()Ljava/lang/String;
   #28 = Methodref          #132.#133     // java/lang/String.format:(Ljava/lang/String;[Ljava/lang/Object;)Ljava/lang/String;
   #29 = Methodref          #31.#134      // org/kohsuke/github/GitHubInteractiveObject.getRoot:()Lorg/kohsuke/github/GitHub;
   #30 = Class              #135          // org/kohsuke/github/GHIssueEvent
   #31 = Class              #136          // org/kohsuke/github/GitHubInteractiveObject
   #32 = Utf8               id
   #33 = Utf8               J
   #34 = Utf8               node_id
   #35 = Utf8               Ljava/lang/String;
   #36 = Utf8               url
   #37 = Utf8               actor
   #38 = Utf8               Lorg/kohsuke/github/GHUser;
   #39 = Utf8               event
   #40 = Utf8               commit_id
   #41 = Utf8               commit_url
   #42 = Utf8               created_at
   #43 = Utf8               milestone
   #44 = Utf8               Lorg/kohsuke/github/GHMilestone;
   #45 = Utf8               label
   #46 = Utf8               Lorg/kohsuke/github/GHLabel;
   #47 = Utf8               assignee
   #48 = Utf8               rename
   #49 = Utf8               Lorg/kohsuke/github/GHIssueRename;
   #50 = Utf8               reviewRequester
   #51 = Utf8               requestedReviewer
   #52 = Utf8               issue
   #53 = Utf8               Lorg/kohsuke/github/GHIssue;
   #54 = Utf8               <init>
   #55 = Utf8               ()V
   #56 = Utf8               Code
   #57 = Utf8               LineNumberTable
   #58 = Utf8               LocalVariableTable
   #59 = Utf8               this
   #60 = Utf8               Lorg/kohsuke/github/GHIssueEvent;
   #61 = Utf8               getId
   #62 = Utf8               ()J
   #63 = Utf8               getNodeId
   #64 = Utf8               ()Ljava/lang/String;
   #65 = Utf8               getUrl
   #66 = Utf8               getActor
   #67 = Utf8               ()Lorg/kohsuke/github/GHUser;
   #68 = Utf8               RuntimeInvisibleAnnotations
   #69 = Utf8               Ledu/umd/cs/findbugs/annotations/SuppressFBWarnings;
   #70 = Utf8               value
   #71 = Utf8               EI_EXPOSE_REP
   #72 = Utf8               justification
   #73 = Utf8               Expected behavior
   #74 = Utf8               getEvent
   #75 = Utf8               getCommitId
   #76 = Utf8               getCommitUrl
   #77 = Utf8               getCreatedAt
   #78 = Utf8               ()Ljava/util/Date;
   #79 = Utf8               getIssue
   #80 = Utf8               ()Lorg/kohsuke/github/GHIssue;
   #81 = Utf8               getMilestone
   #82 = Utf8               ()Lorg/kohsuke/github/GHMilestone;
   #83 = Utf8               getLabel
   #84 = Utf8               ()Lorg/kohsuke/github/GHLabel;
   #85 = Utf8               getAssignee
   #86 = Utf8               getRename
   #87 = Utf8               ()Lorg/kohsuke/github/GHIssueRename;
   #88 = Utf8               getReviewRequester
   #89 = Utf8               getRequestedReviewer
   #90 = Utf8               wrapUp
   #91 = Utf8               (Lorg/kohsuke/github/GHIssue;)Lorg/kohsuke/github/GHIssueEvent;
   #92 = Utf8               parent
   #93 = Utf8               toString
   #94 = Utf8               getRoot
   #95 = Utf8               ()Lorg/kohsuke/github/GitHub;
   #96 = Utf8               RuntimeVisibleAnnotations
   #97 = Utf8               Ljava/lang/Deprecated;
   #98 = Utf8               SourceFile
   #99 = Utf8               GHIssueEvent.java
  #100 = NameAndType        #54:#55       // "<init>":()V
  #101 = NameAndType        #32:#33       // id:J
  #102 = NameAndType        #34:#35       // node_id:Ljava/lang/String;
  #103 = NameAndType        #36:#35       // url:Ljava/lang/String;
  #104 = NameAndType        #37:#38       // actor:Lorg/kohsuke/github/GHUser;
  #105 = NameAndType        #39:#35       // event:Ljava/lang/String;
  #106 = NameAndType        #40:#35       // commit_id:Ljava/lang/String;
  #107 = NameAndType        #41:#35       // commit_url:Ljava/lang/String;
  #108 = NameAndType        #42:#35       // created_at:Ljava/lang/String;
  #109 = Class              #137          // org/kohsuke/github/GitHubClient
  #110 = NameAndType        #138:#139     // parseDate:(Ljava/lang/String;)Ljava/util/Date;
  #111 = NameAndType        #52:#53       // issue:Lorg/kohsuke/github/GHIssue;
  #112 = NameAndType        #43:#44       // milestone:Lorg/kohsuke/github/GHMilestone;
  #113 = NameAndType        #45:#46       // label:Lorg/kohsuke/github/GHLabel;
  #114 = NameAndType        #47:#38       // assignee:Lorg/kohsuke/github/GHUser;
  #115 = NameAndType        #48:#49       // rename:Lorg/kohsuke/github/GHIssueRename;
  #116 = NameAndType        #50:#38       // reviewRequester:Lorg/kohsuke/github/GHUser;
  #117 = NameAndType        #51:#38       // requestedReviewer:Lorg/kohsuke/github/GHUser;
  #118 = Utf8               Issue %d was %s by %s on %s
  #119 = Utf8               java/lang/Object
  #120 = NameAndType        #79:#80       // getIssue:()Lorg/kohsuke/github/GHIssue;
  #121 = Class              #140          // org/kohsuke/github/GHIssue
  #122 = NameAndType        #141:#142     // getNumber:()I
  #123 = Class              #143          // java/lang/Integer
  #124 = NameAndType        #144:#145     // valueOf:(I)Ljava/lang/Integer;
  #125 = NameAndType        #74:#64       // getEvent:()Ljava/lang/String;
  #126 = NameAndType        #66:#67       // getActor:()Lorg/kohsuke/github/GHUser;
  #127 = Class              #146          // org/kohsuke/github/GHUser
  #128 = NameAndType        #147:#64      // getLogin:()Ljava/lang/String;
  #129 = NameAndType        #77:#78       // getCreatedAt:()Ljava/util/Date;
  #130 = Class              #148          // java/util/Date
  #131 = NameAndType        #93:#64       // toString:()Ljava/lang/String;
  #132 = Class              #149          // java/lang/String
  #133 = NameAndType        #150:#151     // format:(Ljava/lang/String;[Ljava/lang/Object;)Ljava/lang/String;
  #134 = NameAndType        #94:#95       // getRoot:()Lorg/kohsuke/github/GitHub;
  #135 = Utf8               org/kohsuke/github/GHIssueEvent
  #136 = Utf8               org/kohsuke/github/GitHubInteractiveObject
  #137 = Utf8               org/kohsuke/github/GitHubClient
  #138 = Utf8               parseDate
  #139 = Utf8               (Ljava/lang/String;)Ljava/util/Date;
  #140 = Utf8               org/kohsuke/github/GHIssue
  #141 = Utf8               getNumber
  #142 = Utf8               ()I
  #143 = Utf8               java/lang/Integer
  #144 = Utf8               valueOf
  #145 = Utf8               (I)Ljava/lang/Integer;
  #146 = Utf8               org/kohsuke/github/GHUser
  #147 = Utf8               getLogin
  #148 = Utf8               java/util/Date
  #149 = Utf8               java/lang/String
  #150 = Utf8               format
  #151 = Utf8               (Ljava/lang/String;[Ljava/lang/Object;)Ljava/lang/String;
{
  private long id;
    descriptor: J
    flags: (0x0002) ACC_PRIVATE

  private java.lang.String node_id;
    descriptor: Ljava/lang/String;
    flags: (0x0002) ACC_PRIVATE

  private java.lang.String url;
    descriptor: Ljava/lang/String;
    flags: (0x0002) ACC_PRIVATE

  private org.kohsuke.github.GHUser actor;
    descriptor: Lorg/kohsuke/github/GHUser;
    flags: (0x0002) ACC_PRIVATE

  private java.lang.String event;
    descriptor: Ljava/lang/String;
    flags: (0x0002) ACC_PRIVATE

  private java.lang.String commit_id;
    descriptor: Ljava/lang/String;
    flags: (0x0002) ACC_PRIVATE

  private java.lang.String commit_url;
    descriptor: Ljava/lang/String;
    flags: (0x0002) ACC_PRIVATE

  private java.lang.String created_at;
    descriptor: Ljava/lang/String;
    flags: (0x0002) ACC_PRIVATE

  private org.kohsuke.github.GHMilestone milestone;
    descriptor: Lorg/kohsuke/github/GHMilestone;
    flags: (0x0002) ACC_PRIVATE

  private org.kohsuke.github.GHLabel label;
    descriptor: Lorg/kohsuke/github/GHLabel;
    flags: (0x0002) ACC_PRIVATE

  private org.kohsuke.github.GHUser assignee;
    descriptor: Lorg/kohsuke/github/GHUser;
    flags: (0x0002) ACC_PRIVATE

  private org.kohsuke.github.GHIssueRename rename;
    descriptor: Lorg/kohsuke/github/GHIssueRename;
    flags: (0x0002) ACC_PRIVATE

  private org.kohsuke.github.GHUser reviewRequester;
    descriptor: Lorg/kohsuke/github/GHUser;
    flags: (0x0002) ACC_PRIVATE

  private org.kohsuke.github.GHUser requestedReviewer;
    descriptor: Lorg/kohsuke/github/GHUser;
    flags: (0x0002) ACC_PRIVATE

  private org.kohsuke.github.GHIssue issue;
    descriptor: Lorg/kohsuke/github/GHIssue;
    flags: (0x0002) ACC_PRIVATE

  public org.kohsuke.github.GHIssueEvent();
    descriptor: ()V
    flags: (0x0001) ACC_PUBLIC
    Code:
      stack=1, locals=1, args_size=1
         0: aload_0
         1: invokespecial #1                  // Method org/kohsuke/github/GitHubInteractiveObject."<init>":()V
         4: return
      LineNumberTable:
        line 14: 0
      LocalVariableTable:
        Start  Length  Slot  Name   Signature
            0       5     0  this   Lorg/kohsuke/github/GHIssueEvent;

  public long getId();
    descriptor: ()J
    flags: (0x0001) ACC_PUBLIC
    Code:
      stack=2, locals=1, args_size=1
         0: aload_0
         1: getfield      #2                  // Field id:J
         4: lreturn
      LineNumberTable:
        line 38: 0
      LocalVariableTable:
        Start  Length  Slot  Name   Signature
            0       5     0  this   Lorg/kohsuke/github/GHIssueEvent;

  public java.lang.String getNodeId();
    descriptor: ()Ljava/lang/String;
    flags: (0x0001) ACC_PUBLIC
    Code:
      stack=1, locals=1, args_size=1
         0: aload_0
         1: getfield      #3                  // Field node_id:Ljava/lang/String;
         4: areturn
      LineNumberTable:
        line 47: 0
      LocalVariableTable:
        Start  Length  Slot  Name   Signature
            0       5     0  this   Lorg/kohsuke/github/GHIssueEvent;

  public java.lang.String getUrl();
    descriptor: ()Ljava/lang/String;
    flags: (0x0001) ACC_PUBLIC
    Code:
      stack=1, locals=1, args_size=1
         0: aload_0
         1: getfield      #4                  // Field url:Ljava/lang/String;
         4: areturn
      LineNumberTable:
        line 56: 0
      LocalVariableTable:
        Start  Length  Slot  Name   Signature
            0       5     0  this   Lorg/kohsuke/github/GHIssueEvent;

  public org.kohsuke.github.GHUser getActor();
    descriptor: ()Lorg/kohsuke/github/GHUser;
    flags: (0x0001) ACC_PUBLIC
    Code:
      stack=1, locals=1, args_size=1
         0: aload_0
         1: getfield      #5                  // Field actor:Lorg/kohsuke/github/GHUser;
         4: areturn
      LineNumberTable:
        line 66: 0
      LocalVariableTable:
        Start  Length  Slot  Name   Signature
            0       5     0  this   Lorg/kohsuke/github/GHIssueEvent;
    RuntimeInvisibleAnnotations:
      0: #69(#70=[s#71],#72=s#73)
        edu.umd.cs.findbugs.annotations.SuppressFBWarnings(
          value=["EI_EXPOSE_REP"]
          justification="Expected behavior"
        )

  public java.lang.String getEvent();
    descriptor: ()Ljava/lang/String;
    flags: (0x0001) ACC_PUBLIC
    Code:
      stack=1, locals=1, args_size=1
         0: aload_0
         1: getfield      #6                  // Field event:Ljava/lang/String;
         4: areturn
      LineNumberTable:
        line 75: 0
      LocalVariableTable:
        Start  Length  Slot  Name   Signature
            0       5     0  this   Lorg/kohsuke/github/GHIssueEvent;

  public java.lang.String getCommitId();
    descriptor: ()Ljava/lang/String;
    flags: (0x0001) ACC_PUBLIC
    Code:
      stack=1, locals=1, args_size=1
         0: aload_0
         1: getfield      #7                  // Field commit_id:Ljava/lang/String;
         4: areturn
      LineNumberTable:
        line 84: 0
      LocalVariableTable:
        Start  Length  Slot  Name   Signature
            0       5     0  this   Lorg/kohsuke/github/GHIssueEvent;

  public java.lang.String getCommitUrl();
    descriptor: ()Ljava/lang/String;
    flags: (0x0001) ACC_PUBLIC
    Code:
      stack=1, locals=1, args_size=1
         0: aload_0
         1: getfield      #8                  // Field commit_url:Ljava/lang/String;
         4: areturn
      LineNumberTable:
        line 93: 0
      LocalVariableTable:
        Start  Length  Slot  Name   Signature
            0       5     0  this   Lorg/kohsuke/github/GHIssueEvent;

  public java.util.Date getCreatedAt();
    descriptor: ()Ljava/util/Date;
    flags: (0x0001) ACC_PUBLIC
    Code:
      stack=1, locals=1, args_size=1
         0: aload_0
         1: getfield      #9                  // Field created_at:Ljava/lang/String;
         4: invokestatic  #10                 // Method org/kohsuke/github/GitHubClient.parseDate:(Ljava/lang/String;)Ljava/util/Date;
         7: areturn
      LineNumberTable:
        line 102: 0
      LocalVariableTable:
        Start  Length  Slot  Name   Signature
            0       8     0  this   Lorg/kohsuke/github/GHIssueEvent;

  public org.kohsuke.github.GHIssue getIssue();
    descriptor: ()Lorg/kohsuke/github/GHIssue;
    flags: (0x0001) ACC_PUBLIC
    Code:
      stack=1, locals=1, args_size=1
         0: aload_0
         1: getfield      #11                 // Field issue:Lorg/kohsuke/github/GHIssue;
         4: areturn
      LineNumberTable:
        line 112: 0
      LocalVariableTable:
        Start  Length  Slot  Name   Signature
            0       5     0  this   Lorg/kohsuke/github/GHIssueEvent;
    RuntimeInvisibleAnnotations:
      0: #69(#70=[s#71],#72=s#73)
        edu.umd.cs.findbugs.annotations.SuppressFBWarnings(
          value=["EI_EXPOSE_REP"]
          justification="Expected behavior"
        )

  public org.kohsuke.github.GHMilestone getMilestone();
    descriptor: ()Lorg/kohsuke/github/GHMilestone;
    flags: (0x0001) ACC_PUBLIC
    Code:
      stack=1, locals=1, args_size=1
         0: aload_0
         1: getfield      #12                 // Field milestone:Lorg/kohsuke/github/GHMilestone;
         4: areturn
      LineNumberTable:
        line 123: 0
      LocalVariableTable:
        Start  Length  Slot  Name   Signature
            0       5     0  this   Lorg/kohsuke/github/GHIssueEvent;
    RuntimeInvisibleAnnotations:
      0: #69(#70=[s#71],#72=s#73)
        edu.umd.cs.findbugs.annotations.SuppressFBWarnings(
          value=["EI_EXPOSE_REP"]
          justification="Expected behavior"
        )

  public org.kohsuke.github.GHLabel getLabel();
    descriptor: ()Lorg/kohsuke/github/GHLabel;
    flags: (0x0001) ACC_PUBLIC
    Code:
      stack=1, locals=1, args_size=1
         0: aload_0
         1: getfield      #13                 // Field label:Lorg/kohsuke/github/GHLabel;
         4: areturn
      LineNumberTable:
        line 134: 0
      LocalVariableTable:
        Start  Length  Slot  Name   Signature
            0       5     0  this   Lorg/kohsuke/github/GHIssueEvent;
    RuntimeInvisibleAnnotations:
      0: #69(#70=[s#71],#72=s#73)
        edu.umd.cs.findbugs.annotations.SuppressFBWarnings(
          value=["EI_EXPOSE_REP"]
          justification="Expected behavior"
        )

  public org.kohsuke.github.GHUser getAssignee();
    descriptor: ()Lorg/kohsuke/github/GHUser;
    flags: (0x0001) ACC_PUBLIC
    Code:
      stack=1, locals=1, args_size=1
         0: aload_0
         1: getfield      #14                 // Field assignee:Lorg/kohsuke/github/GHUser;
         4: areturn
      LineNumberTable:
        line 145: 0
      LocalVariableTable:
        Start  Length  Slot  Name   Signature
            0       5     0  this   Lorg/kohsuke/github/GHIssueEvent;
    RuntimeInvisibleAnnotations:
      0: #69(#70=[s#71],#72=s#73)
        edu.umd.cs.findbugs.annotations.SuppressFBWarnings(
          value=["EI_EXPOSE_REP"]
          justification="Expected behavior"
        )

  public org.kohsuke.github.GHIssueRename getRename();
    descriptor: ()Lorg/kohsuke/github/GHIssueRename;
    flags: (0x0001) ACC_PUBLIC
    Code:
      stack=1, locals=1, args_size=1
         0: aload_0
         1: getfield      #15                 // Field rename:Lorg/kohsuke/github/GHIssueRename;
         4: areturn
      LineNumberTable:
        line 155: 0
      LocalVariableTable:
        Start  Length  Slot  Name   Signature
            0       5     0  this   Lorg/kohsuke/github/GHIssueEvent;

  public org.kohsuke.github.GHUser getReviewRequester();
    descriptor: ()Lorg/kohsuke/github/GHUser;
    flags: (0x0001) ACC_PUBLIC
    Code:
      stack=1, locals=1, args_size=1
         0: aload_0
         1: getfield      #16                 // Field reviewRequester:Lorg/kohsuke/github/GHUser;
         4: areturn
      LineNumberTable:
        line 172: 0
      LocalVariableTable:
        Start  Length  Slot  Name   Signature
            0       5     0  this   Lorg/kohsuke/github/GHIssueEvent;
    RuntimeInvisibleAnnotations:
      0: #69(#70=[s#71],#72=s#73)
        edu.umd.cs.findbugs.annotations.SuppressFBWarnings(
          value=["EI_EXPOSE_REP"]
          justification="Expected behavior"
        )

  public org.kohsuke.github.GHUser getRequestedReviewer();
    descriptor: ()Lorg/kohsuke/github/GHUser;
    flags: (0x0001) ACC_PUBLIC
    Code:
      stack=1, locals=1, args_size=1
         0: aload_0
         1: getfield      #17                 // Field requestedReviewer:Lorg/kohsuke/github/GHUser;
         4: areturn
      LineNumberTable:
        line 189: 0
      LocalVariableTable:
        Start  Length  Slot  Name   Signature
            0       5     0  this   Lorg/kohsuke/github/GHIssueEvent;
    RuntimeInvisibleAnnotations:
      0: #69(#70=[s#71],#72=s#73)
        edu.umd.cs.findbugs.annotations.SuppressFBWarnings(
          value=["EI_EXPOSE_REP"]
          justification="Expected behavior"
        )

  org.kohsuke.github.GHIssueEvent wrapUp(org.kohsuke.github.GHIssue);
    descriptor: (Lorg/kohsuke/github/GHIssue;)Lorg/kohsuke/github/GHIssueEvent;
    flags: (0x0000)
    Code:
      stack=2, locals=2, args_size=2
         0: aload_0
         1: aload_1
         2: putfield      #11                 // Field issue:Lorg/kohsuke/github/GHIssue;
         5: aload_0
         6: areturn
      LineNumberTable:
        line 193: 0
        line 194: 5
      LocalVariableTable:
        Start  Length  Slot  Name   Signature
            0       7     0  this   Lorg/kohsuke/github/GHIssueEvent;
            0       7     1 parent   Lorg/kohsuke/github/GHIssue;

  public java.lang.String toString();
    descriptor: ()Ljava/lang/String;
    flags: (0x0001) ACC_PUBLIC
    Code:
      stack=5, locals=1, args_size=1
         0: ldc           #18                 // String Issue %d was %s by %s on %s
         2: iconst_4
         3: anewarray     #19                 // class java/lang/Object
         6: dup
         7: iconst_0
         8: aload_0
         9: invokevirtual #20                 // Method getIssue:()Lorg/kohsuke/github/GHIssue;
        12: invokevirtual #21                 // Method org/kohsuke/github/GHIssue.getNumber:()I
        15: invokestatic  #22                 // Method java/lang/Integer.valueOf:(I)Ljava/lang/Integer;
        18: aastore
        19: dup
        20: iconst_1
        21: aload_0
        22: invokevirtual #23                 // Method getEvent:()Ljava/lang/String;
        25: aastore
        26: dup
        27: iconst_2
        28: aload_0
        29: invokevirtual #24                 // Method getActor:()Lorg/kohsuke/github/GHUser;
        32: invokevirtual #25                 // Method org/kohsuke/github/GHUser.getLogin:()Ljava/lang/String;
        35: aastore
        36: dup
        37: iconst_3
        38: aload_0
        39: invokevirtual #26                 // Method getCreatedAt:()Ljava/util/Date;
        42: invokevirtual #27                 // Method java/util/Date.toString:()Ljava/lang/String;
        45: aastore
        46: invokestatic  #28                 // Method java/lang/String.format:(Ljava/lang/String;[Ljava/lang/Object;)Ljava/lang/String;
        49: areturn
      LineNumberTable:
        line 199: 0
        line 200: 9
        line 201: 22
        line 202: 29
        line 203: 39
        line 199: 46
      LocalVariableTable:
        Start  Length  Slot  Name   Signature
            0      50     0  this   Lorg/kohsuke/github/GHIssueEvent;

  public org.kohsuke.github.GitHub getRoot();
    descriptor: ()Lorg/kohsuke/github/GitHub;
    flags: (0x1041) ACC_PUBLIC, ACC_BRIDGE, ACC_SYNTHETIC
    Code:
      stack=1, locals=1, args_size=1
         0: aload_0
         1: invokespecial #29                 // Method org/kohsuke/github/GitHubInteractiveObject.getRoot:()Lorg/kohsuke/github/GitHub;
         4: areturn
      LineNumberTable:
        line 14: 0
      LocalVariableTable:
        Start  Length  Slot  Name   Signature
            0       5     0  this   Lorg/kohsuke/github/GHIssueEvent;
    RuntimeVisibleAnnotations:
      0: #97()
        java.lang.Deprecated
    RuntimeInvisibleAnnotations:
      0: #69(#70=[s#71],#72=s#73)
        edu.umd.cs.findbugs.annotations.SuppressFBWarnings(
          value=["EI_EXPOSE_REP"]
          justification="Expected behavior"
        )
}
SourceFile: "GHIssueEvent.java"
