Classfile /Users/mw/Projects/slang-braindump/.jar/jar11/assemble/slang-braindump/assemble/content/org/kohsuke/github/GHLicense.class
  Last modified May 29, 2022; size 3601 bytes
  SHA-256 checksum fdd6111f1d43f16f21ade339d3f372e7d8b60f611e4172d443b151c9edd3b1b5
  Compiled from "GHLicense.java"
public class org.kohsuke.github.GHLicense extends org.kohsuke.github.GHObject
  minor version: 0
  major version: 52
  flags: (0x0021) ACC_PUBLIC, ACC_SUPER
  this_class: #26                         // org/kohsuke/github/GHLicense
  super_class: #29                        // org/kohsuke/github/GHObject
  interfaces: 0, fields: 11, methods: 15, attributes: 3
Constant pool:
    #1 = Methodref          #29.#93       // org/kohsuke/github/GHObject."<init>":()V
    #2 = Class              #94           // java/util/ArrayList
    #3 = Methodref          #2.#93        // java/util/ArrayList."<init>":()V
    #4 = Fieldref           #26.#95       // org/kohsuke/github/GHLicense.required:Ljava/util/List;
    #5 = Fieldref           #26.#96       // org/kohsuke/github/GHLicense.permitted:Ljava/util/List;
    #6 = Fieldref           #26.#97       // org/kohsuke/github/GHLicense.forbidden:Ljava/util/List;
    #7 = Fieldref           #26.#98       // org/kohsuke/github/GHLicense.key:Ljava/lang/String;
    #8 = Fieldref           #26.#99       // org/kohsuke/github/GHLicense.name:Ljava/lang/String;
    #9 = Methodref          #26.#100      // org/kohsuke/github/GHLicense.populate:()V
   #10 = Fieldref           #26.#101      // org/kohsuke/github/GHLicense.featured:Ljava/lang/Boolean;
   #11 = Fieldref           #26.#102      // org/kohsuke/github/GHLicense.html_url:Ljava/lang/String;
   #12 = Methodref          #103.#104     // org/kohsuke/github/GitHubClient.parseURL:(Ljava/lang/String;)Ljava/net/URL;
   #13 = Fieldref           #26.#105      // org/kohsuke/github/GHLicense.description:Ljava/lang/String;
   #14 = Fieldref           #26.#106      // org/kohsuke/github/GHLicense.category:Ljava/lang/String;
   #15 = Fieldref           #26.#107      // org/kohsuke/github/GHLicense.implementation:Ljava/lang/String;
   #16 = Methodref          #108.#109     // java/util/Collections.unmodifiableList:(Ljava/util/List;)Ljava/util/List;
   #17 = Fieldref           #26.#110      // org/kohsuke/github/GHLicense.body:Ljava/lang/String;
   #18 = Methodref          #26.#111      // org/kohsuke/github/GHLicense.isOffline:()Z
   #19 = Methodref          #26.#112      // org/kohsuke/github/GHLicense.getUrl:()Ljava/net/URL;
   #20 = Methodref          #26.#113      // org/kohsuke/github/GHLicense.root:()Lorg/kohsuke/github/GitHub;
   #21 = Methodref          #114.#115     // org/kohsuke/github/GitHub.createRequest:()Lorg/kohsuke/github/Requester;
   #22 = Methodref          #75.#116      // java/net/URL.toString:()Ljava/lang/String;
   #23 = Methodref          #24.#117      // org/kohsuke/github/Requester.setRawUrlPath:(Ljava/lang/String;)Lorg/kohsuke/github/GitHubRequest$Builder;
   #24 = Class              #118          // org/kohsuke/github/Requester
   #25 = Methodref          #24.#119      // org/kohsuke/github/Requester.fetchInto:(Ljava/lang/Object;)Ljava/lang/Object;
   #26 = Class              #120          // org/kohsuke/github/GHLicense
   #27 = Methodref          #121.#122     // java/util/Objects.equals:(Ljava/lang/Object;Ljava/lang/Object;)Z
   #28 = Methodref          #121.#123     // java/util/Objects.hashCode:(Ljava/lang/Object;)I
   #29 = Class              #124          // org/kohsuke/github/GHObject
   #30 = Utf8               key
   #31 = Utf8               Ljava/lang/String;
   #32 = Utf8               name
   #33 = Utf8               featured
   #34 = Utf8               Ljava/lang/Boolean;
   #35 = Utf8               html_url
   #36 = Utf8               description
   #37 = Utf8               category
   #38 = Utf8               implementation
   #39 = Utf8               body
   #40 = Utf8               required
   #41 = Utf8               Ljava/util/List;
   #42 = Utf8               Signature
   #43 = Utf8               Ljava/util/List<Ljava/lang/String;>;
   #44 = Utf8               permitted
   #45 = Utf8               forbidden
   #46 = Utf8               <init>
   #47 = Utf8               ()V
   #48 = Utf8               Code
   #49 = Utf8               LineNumberTable
   #50 = Utf8               LocalVariableTable
   #51 = Utf8               this
   #52 = Utf8               Lorg/kohsuke/github/GHLicense;
   #53 = Utf8               getKey
   #54 = Utf8               ()Ljava/lang/String;
   #55 = Utf8               getName
   #56 = Utf8               isFeatured
   #57 = Utf8               ()Ljava/lang/Boolean;
   #58 = Utf8               Exceptions
   #59 = Class              #125          // java/io/IOException
   #60 = Utf8               getHtmlUrl
   #61 = Utf8               ()Ljava/net/URL;
   #62 = Utf8               getDescription
   #63 = Utf8               getCategory
   #64 = Utf8               getImplementation
   #65 = Utf8               getRequired
   #66 = Utf8               ()Ljava/util/List;
   #67 = Utf8               ()Ljava/util/List<Ljava/lang/String;>;
   #68 = Utf8               getPermitted
   #69 = Utf8               getForbidden
   #70 = Utf8               getBody
   #71 = Utf8               populate
   #72 = Utf8               url
   #73 = Utf8               Ljava/net/URL;
   #74 = Utf8               StackMapTable
   #75 = Class              #126          // java/net/URL
   #76 = Utf8               equals
   #77 = Utf8               (Ljava/lang/Object;)Z
   #78 = Utf8               o
   #79 = Utf8               Ljava/lang/Object;
   #80 = Utf8               that
   #81 = Utf8               hashCode
   #82 = Utf8               ()I
   #83 = Utf8               SourceFile
   #84 = Utf8               GHLicense.java
   #85 = Utf8               RuntimeInvisibleAnnotations
   #86 = Utf8               Ledu/umd/cs/findbugs/annotations/SuppressFBWarnings;
   #87 = Utf8               value
   #88 = Utf8               UWF_UNWRITTEN_PUBLIC_OR_PROTECTED_FIELD
   #89 = Utf8               UWF_UNWRITTEN_FIELD
   #90 = Utf8               NP_UNWRITTEN_FIELD
   #91 = Utf8               justification
   #92 = Utf8               JSON API
   #93 = NameAndType        #46:#47       // "<init>":()V
   #94 = Utf8               java/util/ArrayList
   #95 = NameAndType        #40:#41       // required:Ljava/util/List;
   #96 = NameAndType        #44:#41       // permitted:Ljava/util/List;
   #97 = NameAndType        #45:#41       // forbidden:Ljava/util/List;
   #98 = NameAndType        #30:#31       // key:Ljava/lang/String;
   #99 = NameAndType        #32:#31       // name:Ljava/lang/String;
  #100 = NameAndType        #71:#47       // populate:()V
  #101 = NameAndType        #33:#34       // featured:Ljava/lang/Boolean;
  #102 = NameAndType        #35:#31       // html_url:Ljava/lang/String;
  #103 = Class              #127          // org/kohsuke/github/GitHubClient
  #104 = NameAndType        #128:#129     // parseURL:(Ljava/lang/String;)Ljava/net/URL;
  #105 = NameAndType        #36:#31       // description:Ljava/lang/String;
  #106 = NameAndType        #37:#31       // category:Ljava/lang/String;
  #107 = NameAndType        #38:#31       // implementation:Ljava/lang/String;
  #108 = Class              #130          // java/util/Collections
  #109 = NameAndType        #131:#132     // unmodifiableList:(Ljava/util/List;)Ljava/util/List;
  #110 = NameAndType        #39:#31       // body:Ljava/lang/String;
  #111 = NameAndType        #133:#134     // isOffline:()Z
  #112 = NameAndType        #135:#61      // getUrl:()Ljava/net/URL;
  #113 = NameAndType        #136:#137     // root:()Lorg/kohsuke/github/GitHub;
  #114 = Class              #138          // org/kohsuke/github/GitHub
  #115 = NameAndType        #139:#140     // createRequest:()Lorg/kohsuke/github/Requester;
  #116 = NameAndType        #141:#54      // toString:()Ljava/lang/String;
  #117 = NameAndType        #142:#146     // setRawUrlPath:(Ljava/lang/String;)Lorg/kohsuke/github/GitHubRequest$Builder;
  #118 = Utf8               org/kohsuke/github/Requester
  #119 = NameAndType        #147:#148     // fetchInto:(Ljava/lang/Object;)Ljava/lang/Object;
  #120 = Utf8               org/kohsuke/github/GHLicense
  #121 = Class              #149          // java/util/Objects
  #122 = NameAndType        #76:#150      // equals:(Ljava/lang/Object;Ljava/lang/Object;)Z
  #123 = NameAndType        #81:#151      // hashCode:(Ljava/lang/Object;)I
  #124 = Utf8               org/kohsuke/github/GHObject
  #125 = Utf8               java/io/IOException
  #126 = Utf8               java/net/URL
  #127 = Utf8               org/kohsuke/github/GitHubClient
  #128 = Utf8               parseURL
  #129 = Utf8               (Ljava/lang/String;)Ljava/net/URL;
  #130 = Utf8               java/util/Collections
  #131 = Utf8               unmodifiableList
  #132 = Utf8               (Ljava/util/List;)Ljava/util/List;
  #133 = Utf8               isOffline
  #134 = Utf8               ()Z
  #135 = Utf8               getUrl
  #136 = Utf8               root
  #137 = Utf8               ()Lorg/kohsuke/github/GitHub;
  #138 = Utf8               org/kohsuke/github/GitHub
  #139 = Utf8               createRequest
  #140 = Utf8               ()Lorg/kohsuke/github/Requester;
  #141 = Utf8               toString
  #142 = Utf8               setRawUrlPath
  #143 = Class              #153          // org/kohsuke/github/GitHubRequest$Builder
  #144 = Utf8               Builder
  #145 = Utf8               InnerClasses
  #146 = Utf8               (Ljava/lang/String;)Lorg/kohsuke/github/GitHubRequest$Builder;
  #147 = Utf8               fetchInto
  #148 = Utf8               (Ljava/lang/Object;)Ljava/lang/Object;
  #149 = Utf8               java/util/Objects
  #150 = Utf8               (Ljava/lang/Object;Ljava/lang/Object;)Z
  #151 = Utf8               (Ljava/lang/Object;)I
  #152 = Class              #154          // org/kohsuke/github/GitHubRequest
  #153 = Utf8               org/kohsuke/github/GitHubRequest$Builder
  #154 = Utf8               org/kohsuke/github/GitHubRequest
{
  protected java.lang.String key;
    descriptor: Ljava/lang/String;
    flags: (0x0004) ACC_PROTECTED

  protected java.lang.String name;
    descriptor: Ljava/lang/String;
    flags: (0x0004) ACC_PROTECTED

  protected java.lang.Boolean featured;
    descriptor: Ljava/lang/Boolean;
    flags: (0x0004) ACC_PROTECTED

  protected java.lang.String html_url;
    descriptor: Ljava/lang/String;
    flags: (0x0004) ACC_PROTECTED

  protected java.lang.String description;
    descriptor: Ljava/lang/String;
    flags: (0x0004) ACC_PROTECTED

  protected java.lang.String category;
    descriptor: Ljava/lang/String;
    flags: (0x0004) ACC_PROTECTED

  protected java.lang.String implementation;
    descriptor: Ljava/lang/String;
    flags: (0x0004) ACC_PROTECTED

  protected java.lang.String body;
    descriptor: Ljava/lang/String;
    flags: (0x0004) ACC_PROTECTED

  protected java.util.List<java.lang.String> required;
    descriptor: Ljava/util/List;
    flags: (0x0004) ACC_PROTECTED
    Signature: #43                          // Ljava/util/List<Ljava/lang/String;>;

  protected java.util.List<java.lang.String> permitted;
    descriptor: Ljava/util/List;
    flags: (0x0004) ACC_PROTECTED
    Signature: #43                          // Ljava/util/List<Ljava/lang/String;>;

  protected java.util.List<java.lang.String> forbidden;
    descriptor: Ljava/util/List;
    flags: (0x0004) ACC_PROTECTED
    Signature: #43                          // Ljava/util/List<Ljava/lang/String;>;

  public org.kohsuke.github.GHLicense();
    descriptor: ()V
    flags: (0x0001) ACC_PUBLIC
    Code:
      stack=3, locals=1, args_size=1
         0: aload_0
         1: invokespecial #1                  // Method org/kohsuke/github/GHObject."<init>":()V
         4: aload_0
         5: new           #2                  // class java/util/ArrayList
         8: dup
         9: invokespecial #3                  // Method java/util/ArrayList."<init>":()V
        12: putfield      #4                  // Field required:Ljava/util/List;
        15: aload_0
        16: new           #2                  // class java/util/ArrayList
        19: dup
        20: invokespecial #3                  // Method java/util/ArrayList."<init>":()V
        23: putfield      #5                  // Field permitted:Ljava/util/List;
        26: aload_0
        27: new           #2                  // class java/util/ArrayList
        30: dup
        31: invokespecial #3                  // Method java/util/ArrayList."<init>":()V
        34: putfield      #6                  // Field forbidden:Ljava/util/List;
        37: return
      LineNumberTable:
        line 47: 0
        line 57: 4
        line 58: 15
        line 59: 26
      LocalVariableTable:
        Start  Length  Slot  Name   Signature
            0      38     0  this   Lorg/kohsuke/github/GHLicense;

  public java.lang.String getKey();
    descriptor: ()Ljava/lang/String;
    flags: (0x0001) ACC_PUBLIC
    Code:
      stack=1, locals=1, args_size=1
         0: aload_0
         1: getfield      #7                  // Field key:Ljava/lang/String;
         4: areturn
      LineNumberTable:
        line 67: 0
      LocalVariableTable:
        Start  Length  Slot  Name   Signature
            0       5     0  this   Lorg/kohsuke/github/GHLicense;

  public java.lang.String getName();
    descriptor: ()Ljava/lang/String;
    flags: (0x0001) ACC_PUBLIC
    Code:
      stack=1, locals=1, args_size=1
         0: aload_0
         1: getfield      #8                  // Field name:Ljava/lang/String;
         4: areturn
      LineNumberTable:
        line 76: 0
      LocalVariableTable:
        Start  Length  Slot  Name   Signature
            0       5     0  this   Lorg/kohsuke/github/GHLicense;

  public java.lang.Boolean isFeatured() throws java.io.IOException;
    descriptor: ()Ljava/lang/Boolean;
    flags: (0x0001) ACC_PUBLIC
    Code:
      stack=1, locals=1, args_size=1
         0: aload_0
         1: invokevirtual #9                  // Method populate:()V
         4: aload_0
         5: getfield      #10                 // Field featured:Ljava/lang/Boolean;
         8: areturn
      LineNumberTable:
        line 87: 0
        line 88: 4
      LocalVariableTable:
        Start  Length  Slot  Name   Signature
            0       9     0  this   Lorg/kohsuke/github/GHLicense;
    Exceptions:
      throws java.io.IOException

  public java.net.URL getHtmlUrl() throws java.io.IOException;
    descriptor: ()Ljava/net/URL;
    flags: (0x0001) ACC_PUBLIC
    Code:
      stack=1, locals=1, args_size=1
         0: aload_0
         1: invokevirtual #9                  // Method populate:()V
         4: aload_0
         5: getfield      #11                 // Field html_url:Ljava/lang/String;
         8: invokestatic  #12                 // Method org/kohsuke/github/GitHubClient.parseURL:(Ljava/lang/String;)Ljava/net/URL;
        11: areturn
      LineNumberTable:
        line 92: 0
        line 93: 4
      LocalVariableTable:
        Start  Length  Slot  Name   Signature
            0      12     0  this   Lorg/kohsuke/github/GHLicense;
    Exceptions:
      throws java.io.IOException

  public java.lang.String getDescription() throws java.io.IOException;
    descriptor: ()Ljava/lang/String;
    flags: (0x0001) ACC_PUBLIC
    Code:
      stack=1, locals=1, args_size=1
         0: aload_0
         1: invokevirtual #9                  // Method populate:()V
         4: aload_0
         5: getfield      #13                 // Field description:Ljava/lang/String;
         8: areturn
      LineNumberTable:
        line 104: 0
        line 105: 4
      LocalVariableTable:
        Start  Length  Slot  Name   Signature
            0       9     0  this   Lorg/kohsuke/github/GHLicense;
    Exceptions:
      throws java.io.IOException

  public java.lang.String getCategory() throws java.io.IOException;
    descriptor: ()Ljava/lang/String;
    flags: (0x0001) ACC_PUBLIC
    Code:
      stack=1, locals=1, args_size=1
         0: aload_0
         1: invokevirtual #9                  // Method populate:()V
         4: aload_0
         5: getfield      #14                 // Field category:Ljava/lang/String;
         8: areturn
      LineNumberTable:
        line 116: 0
        line 117: 4
      LocalVariableTable:
        Start  Length  Slot  Name   Signature
            0       9     0  this   Lorg/kohsuke/github/GHLicense;
    Exceptions:
      throws java.io.IOException

  public java.lang.String getImplementation() throws java.io.IOException;
    descriptor: ()Ljava/lang/String;
    flags: (0x0001) ACC_PUBLIC
    Code:
      stack=1, locals=1, args_size=1
         0: aload_0
         1: invokevirtual #9                  // Method populate:()V
         4: aload_0
         5: getfield      #15                 // Field implementation:Ljava/lang/String;
         8: areturn
      LineNumberTable:
        line 128: 0
        line 129: 4
      LocalVariableTable:
        Start  Length  Slot  Name   Signature
            0       9     0  this   Lorg/kohsuke/github/GHLicense;
    Exceptions:
      throws java.io.IOException

  public java.util.List<java.lang.String> getRequired() throws java.io.IOException;
    descriptor: ()Ljava/util/List;
    flags: (0x0001) ACC_PUBLIC
    Code:
      stack=1, locals=1, args_size=1
         0: aload_0
         1: invokevirtual #9                  // Method populate:()V
         4: aload_0
         5: getfield      #4                  // Field required:Ljava/util/List;
         8: invokestatic  #16                 // Method java/util/Collections.unmodifiableList:(Ljava/util/List;)Ljava/util/List;
        11: areturn
      LineNumberTable:
        line 140: 0
        line 141: 4
      LocalVariableTable:
        Start  Length  Slot  Name   Signature
            0      12     0  this   Lorg/kohsuke/github/GHLicense;
    Exceptions:
      throws java.io.IOException
    Signature: #67                          // ()Ljava/util/List<Ljava/lang/String;>;

  public java.util.List<java.lang.String> getPermitted() throws java.io.IOException;
    descriptor: ()Ljava/util/List;
    flags: (0x0001) ACC_PUBLIC
    Code:
      stack=1, locals=1, args_size=1
         0: aload_0
         1: invokevirtual #9                  // Method populate:()V
         4: aload_0
         5: getfield      #5                  // Field permitted:Ljava/util/List;
         8: invokestatic  #16                 // Method java/util/Collections.unmodifiableList:(Ljava/util/List;)Ljava/util/List;
        11: areturn
      LineNumberTable:
        line 152: 0
        line 153: 4
      LocalVariableTable:
        Start  Length  Slot  Name   Signature
            0      12     0  this   Lorg/kohsuke/github/GHLicense;
    Exceptions:
      throws java.io.IOException
    Signature: #67                          // ()Ljava/util/List<Ljava/lang/String;>;

  public java.util.List<java.lang.String> getForbidden() throws java.io.IOException;
    descriptor: ()Ljava/util/List;
    flags: (0x0001) ACC_PUBLIC
    Code:
      stack=1, locals=1, args_size=1
         0: aload_0
         1: invokevirtual #9                  // Method populate:()V
         4: aload_0
         5: getfield      #6                  // Field forbidden:Ljava/util/List;
         8: invokestatic  #16                 // Method java/util/Collections.unmodifiableList:(Ljava/util/List;)Ljava/util/List;
        11: areturn
      LineNumberTable:
        line 164: 0
        line 165: 4
      LocalVariableTable:
        Start  Length  Slot  Name   Signature
            0      12     0  this   Lorg/kohsuke/github/GHLicense;
    Exceptions:
      throws java.io.IOException
    Signature: #67                          // ()Ljava/util/List<Ljava/lang/String;>;

  public java.lang.String getBody() throws java.io.IOException;
    descriptor: ()Ljava/lang/String;
    flags: (0x0001) ACC_PUBLIC
    Code:
      stack=1, locals=1, args_size=1
         0: aload_0
         1: invokevirtual #9                  // Method populate:()V
         4: aload_0
         5: getfield      #17                 // Field body:Ljava/lang/String;
         8: areturn
      LineNumberTable:
        line 176: 0
        line 177: 4
      LocalVariableTable:
        Start  Length  Slot  Name   Signature
            0       9     0  this   Lorg/kohsuke/github/GHLicense;
    Exceptions:
      throws java.io.IOException

  protected synchronized void populate() throws java.io.IOException;
    descriptor: ()V
    flags: (0x0024) ACC_PROTECTED, ACC_SYNCHRONIZED
    Code:
      stack=2, locals=2, args_size=1
         0: aload_0
         1: getfield      #13                 // Field description:Ljava/lang/String;
         4: ifnull        8
         7: return
         8: aload_0
         9: invokevirtual #18                 // Method isOffline:()Z
        12: ifeq          16
        15: return
        16: aload_0
        17: invokevirtual #19                 // Method getUrl:()Ljava/net/URL;
        20: astore_1
        21: aload_1
        22: ifnull        47
        25: aload_0
        26: invokevirtual #20                 // Method root:()Lorg/kohsuke/github/GitHub;
        29: invokevirtual #21                 // Method org/kohsuke/github/GitHub.createRequest:()Lorg/kohsuke/github/Requester;
        32: aload_1
        33: invokevirtual #22                 // Method java/net/URL.toString:()Ljava/lang/String;
        36: invokevirtual #23                 // Method org/kohsuke/github/Requester.setRawUrlPath:(Ljava/lang/String;)Lorg/kohsuke/github/GitHubRequest$Builder;
        39: checkcast     #24                 // class org/kohsuke/github/Requester
        42: aload_0
        43: invokevirtual #25                 // Method org/kohsuke/github/Requester.fetchInto:(Ljava/lang/Object;)Ljava/lang/Object;
        46: pop
        47: return
      LineNumberTable:
        line 189: 0
        line 190: 7
        line 192: 8
        line 193: 15
        line 196: 16
        line 197: 21
        line 198: 25
        line 200: 47
      LocalVariableTable:
        Start  Length  Slot  Name   Signature
            0      48     0  this   Lorg/kohsuke/github/GHLicense;
           21      27     1   url   Ljava/net/URL;
      StackMapTable: number_of_entries = 3
        frame_type = 8 /* same */
        frame_type = 7 /* same */
        frame_type = 252 /* append */
          offset_delta = 30
          locals = [ class java/net/URL ]
    Exceptions:
      throws java.io.IOException

  public boolean equals(java.lang.Object);
    descriptor: (Ljava/lang/Object;)Z
    flags: (0x0001) ACC_PUBLIC
    Code:
      stack=2, locals=3, args_size=2
         0: aload_0
         1: aload_1
         2: if_acmpne     7
         5: iconst_1
         6: ireturn
         7: aload_1
         8: instanceof    #26                 // class org/kohsuke/github/GHLicense
        11: ifne          16
        14: iconst_0
        15: ireturn
        16: aload_1
        17: checkcast     #26                 // class org/kohsuke/github/GHLicense
        20: astore_2
        21: aload_0
        22: invokevirtual #19                 // Method getUrl:()Ljava/net/URL;
        25: aload_2
        26: invokevirtual #19                 // Method getUrl:()Ljava/net/URL;
        29: invokestatic  #27                 // Method java/util/Objects.equals:(Ljava/lang/Object;Ljava/lang/Object;)Z
        32: ireturn
      LineNumberTable:
        line 204: 0
        line 205: 5
        line 206: 7
        line 207: 14
        line 209: 16
        line 210: 21
      LocalVariableTable:
        Start  Length  Slot  Name   Signature
            0      33     0  this   Lorg/kohsuke/github/GHLicense;
            0      33     1     o   Ljava/lang/Object;
           21      12     2  that   Lorg/kohsuke/github/GHLicense;
      StackMapTable: number_of_entries = 2
        frame_type = 7 /* same */
        frame_type = 8 /* same */

  public int hashCode();
    descriptor: ()I
    flags: (0x0001) ACC_PUBLIC
    Code:
      stack=1, locals=1, args_size=1
         0: aload_0
         1: invokevirtual #19                 // Method getUrl:()Ljava/net/URL;
         4: invokestatic  #28                 // Method java/util/Objects.hashCode:(Ljava/lang/Object;)I
         7: ireturn
      LineNumberTable:
        line 215: 0
      LocalVariableTable:
        Start  Length  Slot  Name   Signature
            0       8     0  this   Lorg/kohsuke/github/GHLicense;
}
SourceFile: "GHLicense.java"
RuntimeInvisibleAnnotations:
  0: #86(#87=[s#88,s#89,s#90],#91=s#92)
    edu.umd.cs.findbugs.annotations.SuppressFBWarnings(
      value=["UWF_UNWRITTEN_PUBLIC_OR_PROTECTED_FIELD","UWF_UNWRITTEN_FIELD","NP_UNWRITTEN_FIELD"]
      justification="JSON API"
    )
InnerClasses:
  static #144= #143 of #152;              // Builder=class org/kohsuke/github/GitHubRequest$Builder of class org/kohsuke/github/GitHubRequest
