Classfile /Users/mw/Projects/slang-braindump/.jar/jar11/assemble/slang-braindump/assemble/content/org/kohsuke/github/GHMarketplaceAccountPlan.class
  Last modified May 29, 2022; size 1035 bytes
  SHA-256 checksum 2ae7a730a54a5527adf7c7f9d6a8f9b80f93674c6ee846b048f14bda1f523596
  Compiled from "GHMarketplaceAccountPlan.java"
public class org.kohsuke.github.GHMarketplaceAccountPlan extends org.kohsuke.github.GHMarketplaceAccount
  minor version: 0
  major version: 52
  flags: (0x0021) ACC_PUBLIC, ACC_SUPER
  this_class: #4                          // org/kohsuke/github/GHMarketplaceAccountPlan
  super_class: #5                         // org/kohsuke/github/GHMarketplaceAccount
  interfaces: 0, fields: 2, methods: 3, attributes: 1
Constant pool:
   #1 = Methodref          #5.#29         // org/kohsuke/github/GHMarketplaceAccount."<init>":()V
   #2 = Fieldref           #4.#30         // org/kohsuke/github/GHMarketplaceAccountPlan.marketplacePendingChange:Lorg/kohsuke/github/GHMarketplacePendingChange;
   #3 = Fieldref           #4.#31         // org/kohsuke/github/GHMarketplaceAccountPlan.marketplacePurchase:Lorg/kohsuke/github/GHMarketplacePurchase;
   #4 = Class              #32            // org/kohsuke/github/GHMarketplaceAccountPlan
   #5 = Class              #33            // org/kohsuke/github/GHMarketplaceAccount
   #6 = Utf8               marketplacePendingChange
   #7 = Utf8               Lorg/kohsuke/github/GHMarketplacePendingChange;
   #8 = Utf8               RuntimeInvisibleAnnotations
   #9 = Utf8               Ledu/umd/cs/findbugs/annotations/SuppressFBWarnings;
  #10 = Utf8               value
  #11 = Utf8               UWF_UNWRITTEN_FIELD
  #12 = Utf8               justification
  #13 = Utf8               Field comes from JSON deserialization
  #14 = Utf8               marketplacePurchase
  #15 = Utf8               Lorg/kohsuke/github/GHMarketplacePurchase;
  #16 = Utf8               <init>
  #17 = Utf8               ()V
  #18 = Utf8               Code
  #19 = Utf8               LineNumberTable
  #20 = Utf8               LocalVariableTable
  #21 = Utf8               this
  #22 = Utf8               Lorg/kohsuke/github/GHMarketplaceAccountPlan;
  #23 = Utf8               getMarketplacePendingChange
  #24 = Utf8               ()Lorg/kohsuke/github/GHMarketplacePendingChange;
  #25 = Utf8               getMarketplacePurchase
  #26 = Utf8               ()Lorg/kohsuke/github/GHMarketplacePurchase;
  #27 = Utf8               SourceFile
  #28 = Utf8               GHMarketplaceAccountPlan.java
  #29 = NameAndType        #16:#17        // "<init>":()V
  #30 = NameAndType        #6:#7          // marketplacePendingChange:Lorg/kohsuke/github/GHMarketplacePendingChange;
  #31 = NameAndType        #14:#15        // marketplacePurchase:Lorg/kohsuke/github/GHMarketplacePurchase;
  #32 = Utf8               org/kohsuke/github/GHMarketplaceAccountPlan
  #33 = Utf8               org/kohsuke/github/GHMarketplaceAccount
{
  private org.kohsuke.github.GHMarketplacePendingChange marketplacePendingChange;
    descriptor: Lorg/kohsuke/github/GHMarketplacePendingChange;
    flags: (0x0002) ACC_PRIVATE
    RuntimeInvisibleAnnotations:
      0: #9(#10=[s#11],#12=s#13)
        edu.umd.cs.findbugs.annotations.SuppressFBWarnings(
          value=["UWF_UNWRITTEN_FIELD"]
          justification="Field comes from JSON deserialization"
        )

  private org.kohsuke.github.GHMarketplacePurchase marketplacePurchase;
    descriptor: Lorg/kohsuke/github/GHMarketplacePurchase;
    flags: (0x0002) ACC_PRIVATE
    RuntimeInvisibleAnnotations:
      0: #9(#10=[s#11],#12=s#13)
        edu.umd.cs.findbugs.annotations.SuppressFBWarnings(
          value=["UWF_UNWRITTEN_FIELD"]
          justification="Field comes from JSON deserialization"
        )

  public org.kohsuke.github.GHMarketplaceAccountPlan();
    descriptor: ()V
    flags: (0x0001) ACC_PUBLIC
    Code:
      stack=1, locals=1, args_size=1
         0: aload_0
         1: invokespecial #1                  // Method org/kohsuke/github/GHMarketplaceAccount."<init>":()V
         4: return
      LineNumberTable:
        line 11: 0
      LocalVariableTable:
        Start  Length  Slot  Name   Signature
            0       5     0  this   Lorg/kohsuke/github/GHMarketplaceAccountPlan;

  public org.kohsuke.github.GHMarketplacePendingChange getMarketplacePendingChange();
    descriptor: ()Lorg/kohsuke/github/GHMarketplacePendingChange;
    flags: (0x0001) ACC_PUBLIC
    Code:
      stack=1, locals=1, args_size=1
         0: aload_0
         1: getfield      #2                  // Field marketplacePendingChange:Lorg/kohsuke/github/GHMarketplacePendingChange;
         4: areturn
      LineNumberTable:
        line 24: 0
      LocalVariableTable:
        Start  Length  Slot  Name   Signature
            0       5     0  this   Lorg/kohsuke/github/GHMarketplaceAccountPlan;

  public org.kohsuke.github.GHMarketplacePurchase getMarketplacePurchase();
    descriptor: ()Lorg/kohsuke/github/GHMarketplacePurchase;
    flags: (0x0001) ACC_PUBLIC
    Code:
      stack=1, locals=1, args_size=1
         0: aload_0
         1: getfield      #3                  // Field marketplacePurchase:Lorg/kohsuke/github/GHMarketplacePurchase;
         4: areturn
      LineNumberTable:
        line 33: 0
      LocalVariableTable:
        Start  Length  Slot  Name   Signature
            0       5     0  this   Lorg/kohsuke/github/GHMarketplaceAccountPlan;
}
SourceFile: "GHMarketplaceAccountPlan.java"
