Classfile /Users/mw/Projects/slang-braindump/.jar/jar11/assemble/slang-braindump/assemble/content/org/kohsuke/github/GHMarketplaceAccount.class
  Last modified May 29, 2022; size 1580 bytes
  SHA-256 checksum 6c3bb0f82d8a3ce39ba63ad2b16e601ffd03428b1527c39f841adce5c5cf4744
  Compiled from "GHMarketplaceAccount.java"
public class org.kohsuke.github.GHMarketplaceAccount extends org.kohsuke.github.GitHubInteractiveObject
  minor version: 0
  major version: 52
  flags: (0x0021) ACC_PUBLIC, ACC_SUPER
  this_class: #10                         // org/kohsuke/github/GHMarketplaceAccount
  super_class: #11                        // org/kohsuke/github/GitHubInteractiveObject
  interfaces: 0, fields: 6, methods: 8, attributes: 1
Constant pool:
   #1 = Methodref          #11.#50        // org/kohsuke/github/GitHubInteractiveObject."<init>":()V
   #2 = Fieldref           #10.#51        // org/kohsuke/github/GHMarketplaceAccount.url:Ljava/lang/String;
   #3 = Methodref          #52.#53        // org/kohsuke/github/GitHubClient.parseURL:(Ljava/lang/String;)Ljava/net/URL;
   #4 = Fieldref           #10.#54        // org/kohsuke/github/GHMarketplaceAccount.id:J
   #5 = Fieldref           #10.#55        // org/kohsuke/github/GHMarketplaceAccount.login:Ljava/lang/String;
   #6 = Fieldref           #10.#56        // org/kohsuke/github/GHMarketplaceAccount.email:Ljava/lang/String;
   #7 = Fieldref           #10.#57        // org/kohsuke/github/GHMarketplaceAccount.organizationBillingEmail:Ljava/lang/String;
   #8 = Fieldref           #10.#58        // org/kohsuke/github/GHMarketplaceAccount.type:Lorg/kohsuke/github/GHMarketplaceAccountType;
   #9 = Methodref          #11.#59        // org/kohsuke/github/GitHubInteractiveObject.getRoot:()Lorg/kohsuke/github/GitHub;
  #10 = Class              #60            // org/kohsuke/github/GHMarketplaceAccount
  #11 = Class              #61            // org/kohsuke/github/GitHubInteractiveObject
  #12 = Utf8               url
  #13 = Utf8               Ljava/lang/String;
  #14 = Utf8               id
  #15 = Utf8               J
  #16 = Utf8               login
  #17 = Utf8               email
  #18 = Utf8               organizationBillingEmail
  #19 = Utf8               type
  #20 = Utf8               Lorg/kohsuke/github/GHMarketplaceAccountType;
  #21 = Utf8               <init>
  #22 = Utf8               ()V
  #23 = Utf8               Code
  #24 = Utf8               LineNumberTable
  #25 = Utf8               LocalVariableTable
  #26 = Utf8               this
  #27 = Utf8               Lorg/kohsuke/github/GHMarketplaceAccount;
  #28 = Utf8               getUrl
  #29 = Utf8               ()Ljava/net/URL;
  #30 = Utf8               getId
  #31 = Utf8               ()J
  #32 = Utf8               getLogin
  #33 = Utf8               ()Ljava/lang/String;
  #34 = Utf8               getEmail
  #35 = Utf8               getOrganizationBillingEmail
  #36 = Utf8               getType
  #37 = Utf8               ()Lorg/kohsuke/github/GHMarketplaceAccountType;
  #38 = Utf8               getRoot
  #39 = Utf8               ()Lorg/kohsuke/github/GitHub;
  #40 = Utf8               RuntimeVisibleAnnotations
  #41 = Utf8               Ljava/lang/Deprecated;
  #42 = Utf8               RuntimeInvisibleAnnotations
  #43 = Utf8               Ledu/umd/cs/findbugs/annotations/SuppressFBWarnings;
  #44 = Utf8               value
  #45 = Utf8               EI_EXPOSE_REP
  #46 = Utf8               justification
  #47 = Utf8               Expected behavior
  #48 = Utf8               SourceFile
  #49 = Utf8               GHMarketplaceAccount.java
  #50 = NameAndType        #21:#22        // "<init>":()V
  #51 = NameAndType        #12:#13        // url:Ljava/lang/String;
  #52 = Class              #62            // org/kohsuke/github/GitHubClient
  #53 = NameAndType        #63:#64        // parseURL:(Ljava/lang/String;)Ljava/net/URL;
  #54 = NameAndType        #14:#15        // id:J
  #55 = NameAndType        #16:#13        // login:Ljava/lang/String;
  #56 = NameAndType        #17:#13        // email:Ljava/lang/String;
  #57 = NameAndType        #18:#13        // organizationBillingEmail:Ljava/lang/String;
  #58 = NameAndType        #19:#20        // type:Lorg/kohsuke/github/GHMarketplaceAccountType;
  #59 = NameAndType        #38:#39        // getRoot:()Lorg/kohsuke/github/GitHub;
  #60 = Utf8               org/kohsuke/github/GHMarketplaceAccount
  #61 = Utf8               org/kohsuke/github/GitHubInteractiveObject
  #62 = Utf8               org/kohsuke/github/GitHubClient
  #63 = Utf8               parseURL
  #64 = Utf8               (Ljava/lang/String;)Ljava/net/URL;
{
  private java.lang.String url;
    descriptor: Ljava/lang/String;
    flags: (0x0002) ACC_PRIVATE

  private long id;
    descriptor: J
    flags: (0x0002) ACC_PRIVATE

  private java.lang.String login;
    descriptor: Ljava/lang/String;
    flags: (0x0002) ACC_PRIVATE

  private java.lang.String email;
    descriptor: Ljava/lang/String;
    flags: (0x0002) ACC_PRIVATE

  private java.lang.String organizationBillingEmail;
    descriptor: Ljava/lang/String;
    flags: (0x0002) ACC_PRIVATE

  private org.kohsuke.github.GHMarketplaceAccountType type;
    descriptor: Lorg/kohsuke/github/GHMarketplaceAccountType;
    flags: (0x0002) ACC_PRIVATE

  public org.kohsuke.github.GHMarketplaceAccount();
    descriptor: ()V
    flags: (0x0001) ACC_PUBLIC
    Code:
      stack=1, locals=1, args_size=1
         0: aload_0
         1: invokespecial #1                  // Method org/kohsuke/github/GitHubInteractiveObject."<init>":()V
         4: return
      LineNumberTable:
        line 12: 0
      LocalVariableTable:
        Start  Length  Slot  Name   Signature
            0       5     0  this   Lorg/kohsuke/github/GHMarketplaceAccount;

  public java.net.URL getUrl();
    descriptor: ()Ljava/net/URL;
    flags: (0x0001) ACC_PUBLIC
    Code:
      stack=1, locals=1, args_size=1
         0: aload_0
         1: getfield      #2                  // Field url:Ljava/lang/String;
         4: invokestatic  #3                  // Method org/kohsuke/github/GitHubClient.parseURL:(Ljava/lang/String;)Ljava/net/URL;
         7: areturn
      LineNumberTable:
        line 26: 0
      LocalVariableTable:
        Start  Length  Slot  Name   Signature
            0       8     0  this   Lorg/kohsuke/github/GHMarketplaceAccount;

  public long getId();
    descriptor: ()J
    flags: (0x0001) ACC_PUBLIC
    Code:
      stack=2, locals=1, args_size=1
         0: aload_0
         1: getfield      #4                  // Field id:J
         4: lreturn
      LineNumberTable:
        line 35: 0
      LocalVariableTable:
        Start  Length  Slot  Name   Signature
            0       5     0  this   Lorg/kohsuke/github/GHMarketplaceAccount;

  public java.lang.String getLogin();
    descriptor: ()Ljava/lang/String;
    flags: (0x0001) ACC_PUBLIC
    Code:
      stack=1, locals=1, args_size=1
         0: aload_0
         1: getfield      #5                  // Field login:Ljava/lang/String;
         4: areturn
      LineNumberTable:
        line 44: 0
      LocalVariableTable:
        Start  Length  Slot  Name   Signature
            0       5     0  this   Lorg/kohsuke/github/GHMarketplaceAccount;

  public java.lang.String getEmail();
    descriptor: ()Ljava/lang/String;
    flags: (0x0001) ACC_PUBLIC
    Code:
      stack=1, locals=1, args_size=1
         0: aload_0
         1: getfield      #6                  // Field email:Ljava/lang/String;
         4: areturn
      LineNumberTable:
        line 53: 0
      LocalVariableTable:
        Start  Length  Slot  Name   Signature
            0       5     0  this   Lorg/kohsuke/github/GHMarketplaceAccount;

  public java.lang.String getOrganizationBillingEmail();
    descriptor: ()Ljava/lang/String;
    flags: (0x0001) ACC_PUBLIC
    Code:
      stack=1, locals=1, args_size=1
         0: aload_0
         1: getfield      #7                  // Field organizationBillingEmail:Ljava/lang/String;
         4: areturn
      LineNumberTable:
        line 62: 0
      LocalVariableTable:
        Start  Length  Slot  Name   Signature
            0       5     0  this   Lorg/kohsuke/github/GHMarketplaceAccount;

  public org.kohsuke.github.GHMarketplaceAccountType getType();
    descriptor: ()Lorg/kohsuke/github/GHMarketplaceAccountType;
    flags: (0x0001) ACC_PUBLIC
    Code:
      stack=1, locals=1, args_size=1
         0: aload_0
         1: getfield      #8                  // Field type:Lorg/kohsuke/github/GHMarketplaceAccountType;
         4: areturn
      LineNumberTable:
        line 71: 0
      LocalVariableTable:
        Start  Length  Slot  Name   Signature
            0       5     0  this   Lorg/kohsuke/github/GHMarketplaceAccount;

  public org.kohsuke.github.GitHub getRoot();
    descriptor: ()Lorg/kohsuke/github/GitHub;
    flags: (0x1041) ACC_PUBLIC, ACC_BRIDGE, ACC_SYNTHETIC
    Code:
      stack=1, locals=1, args_size=1
         0: aload_0
         1: invokespecial #9                  // Method org/kohsuke/github/GitHubInteractiveObject.getRoot:()Lorg/kohsuke/github/GitHub;
         4: areturn
      LineNumberTable:
        line 12: 0
      LocalVariableTable:
        Start  Length  Slot  Name   Signature
            0       5     0  this   Lorg/kohsuke/github/GHMarketplaceAccount;
    RuntimeVisibleAnnotations:
      0: #41()
        java.lang.Deprecated
    RuntimeInvisibleAnnotations:
      0: #43(#44=[s#45],#46=s#47)
        edu.umd.cs.findbugs.annotations.SuppressFBWarnings(
          value=["EI_EXPOSE_REP"]
          justification="Expected behavior"
        )
}
SourceFile: "GHMarketplaceAccount.java"
