Classfile /Users/mw/Projects/slang-braindump/.jar/jar11/assemble/slang-braindump/assemble/content/org/kohsuke/github/GHObject$2.class
  Last modified May 29, 2022; size 1001 bytes
  SHA-256 checksum c2f5e01f869fa37dc0766d4f353a25ddc2c739111f291230d0a614843df66330
  Compiled from "GHObject.java"
class org.kohsuke.github.GHObject$2 extends org.apache.commons.lang3.builder.ToStringStyle
  minor version: 0
  major version: 52
  flags: (0x0020) ACC_SUPER
  this_class: #8                          // org/kohsuke/github/GHObject$2
  super_class: #9                         // org/apache/commons/lang3/builder/ToStringStyle
  interfaces: 0, fields: 0, methods: 2, attributes: 3
Constant pool:
   #1 = Methodref          #9.#32         // org/apache/commons/lang3/builder/ToStringStyle."<init>":()V
   #2 = Methodref          #8.#33         // org/kohsuke/github/GHObject$2.setUseShortClassName:(Z)V
   #3 = String             #34            // _
   #4 = Methodref          #35.#36        // java/lang/String.contains:(Ljava/lang/CharSequence;)Z
   #5 = Class              #37            // org/kohsuke/github/GHObject
   #6 = Class              #38            // org/kohsuke/github/GitHub
   #7 = Methodref          #9.#39         // org/apache/commons/lang3/builder/ToStringStyle.append:(Ljava/lang/StringBuffer;Ljava/lang/String;Ljava/lang/Object;Ljava/lang/Boolean;)V
   #8 = Class              #40            // org/kohsuke/github/GHObject$2
   #9 = Class              #41            // org/apache/commons/lang3/builder/ToStringStyle
  #10 = Utf8               <init>
  #11 = Utf8               ()V
  #12 = Utf8               Code
  #13 = Utf8               LineNumberTable
  #14 = Utf8               LocalVariableTable
  #15 = Utf8               this
  #16 = Utf8               InnerClasses
  #17 = Utf8               Lorg/kohsuke/github/GHObject$2;
  #18 = Utf8               append
  #19 = Utf8               (Ljava/lang/StringBuffer;Ljava/lang/String;Ljava/lang/Object;Ljava/lang/Boolean;)V
  #20 = Utf8               buffer
  #21 = Utf8               Ljava/lang/StringBuffer;
  #22 = Utf8               fieldName
  #23 = Utf8               Ljava/lang/String;
  #24 = Utf8               value
  #25 = Utf8               Ljava/lang/Object;
  #26 = Utf8               fullDetail
  #27 = Utf8               Ljava/lang/Boolean;
  #28 = Utf8               StackMapTable
  #29 = Utf8               SourceFile
  #30 = Utf8               GHObject.java
  #31 = Utf8               EnclosingMethod
  #32 = NameAndType        #10:#11        // "<init>":()V
  #33 = NameAndType        #42:#43        // setUseShortClassName:(Z)V
  #34 = Utf8               _
  #35 = Class              #44            // java/lang/String
  #36 = NameAndType        #45:#46        // contains:(Ljava/lang/CharSequence;)Z
  #37 = Utf8               org/kohsuke/github/GHObject
  #38 = Utf8               org/kohsuke/github/GitHub
  #39 = NameAndType        #18:#19        // append:(Ljava/lang/StringBuffer;Ljava/lang/String;Ljava/lang/Object;Ljava/lang/Boolean;)V
  #40 = Utf8               org/kohsuke/github/GHObject$2
  #41 = Utf8               org/apache/commons/lang3/builder/ToStringStyle
  #42 = Utf8               setUseShortClassName
  #43 = Utf8               (Z)V
  #44 = Utf8               java/lang/String
  #45 = Utf8               contains
  #46 = Utf8               (Ljava/lang/CharSequence;)Z
{
  org.kohsuke.github.GHObject$2();
    descriptor: ()V
    flags: (0x0000)
    Code:
      stack=2, locals=1, args_size=1
         0: aload_0
         1: invokespecial #1                  // Method org/apache/commons/lang3/builder/ToStringStyle."<init>":()V
         4: aload_0
         5: iconst_1
         6: invokevirtual #2                  // Method setUseShortClassName:(Z)V
         9: return
      LineNumberTable:
        line 168: 0
        line 170: 4
        line 171: 9
      LocalVariableTable:
        Start  Length  Slot  Name   Signature
            0      10     0  this   Lorg/kohsuke/github/GHObject$2;

  public void append(java.lang.StringBuffer, java.lang.String, java.lang.Object, java.lang.Boolean);
    descriptor: (Ljava/lang/StringBuffer;Ljava/lang/String;Ljava/lang/Object;Ljava/lang/Boolean;)V
    flags: (0x0001) ACC_PUBLIC
    Code:
      stack=5, locals=5, args_size=5
         0: aload_2
         1: ldc           #3                  // String _
         3: invokevirtual #4                  // Method java/lang/String.contains:(Ljava/lang/CharSequence;)Z
         6: ifeq          10
         9: return
        10: aload_3
        11: instanceof    #5                  // class org/kohsuke/github/GHObject
        14: ifeq          18
        17: return
        18: aload_3
        19: instanceof    #6                  // class org/kohsuke/github/GitHub
        22: ifeq          26
        25: return
        26: aload_0
        27: aload_1
        28: aload_2
        29: aload_3
        30: aload         4
        32: invokespecial #7                  // Method org/apache/commons/lang3/builder/ToStringStyle.append:(Ljava/lang/StringBuffer;Ljava/lang/String;Ljava/lang/Object;Ljava/lang/Boolean;)V
        35: return
      LineNumberTable:
        line 176: 0
        line 177: 9
        line 179: 10
        line 180: 17
        line 182: 18
        line 183: 25
        line 185: 26
        line 186: 35
      LocalVariableTable:
        Start  Length  Slot  Name   Signature
            0      36     0  this   Lorg/kohsuke/github/GHObject$2;
            0      36     1 buffer   Ljava/lang/StringBuffer;
            0      36     2 fieldName   Ljava/lang/String;
            0      36     3 value   Ljava/lang/Object;
            0      36     4 fullDetail   Ljava/lang/Boolean;
      StackMapTable: number_of_entries = 3
        frame_type = 10 /* same */
        frame_type = 7 /* same */
        frame_type = 7 /* same */
}
SourceFile: "GHObject.java"
EnclosingMethod: #5.#0                  // org.kohsuke.github.GHObject
InnerClasses:
  #8;                                     // class org/kohsuke/github/GHObject$2
