Classfile /Users/mw/Projects/slang-braindump/.jar/jar11/assemble/slang-braindump/assemble/content/org/kohsuke/github/GHPermissionType.class
  Last modified May 29, 2022; size 1124 bytes
  SHA-256 checksum 147338464fa58ad84376b7cb9a3ee4e7285fc826bb0dc113a181b1fa8ea09dd0
  Compiled from "GHPermissionType.java"
public final class org.kohsuke.github.GHPermissionType extends java.lang.Enum<org.kohsuke.github.GHPermissionType>
  minor version: 0
  major version: 52
  flags: (0x4031) ACC_PUBLIC, ACC_FINAL, ACC_SUPER, ACC_ENUM
  this_class: #4                          // org/kohsuke/github/GHPermissionType
  super_class: #16                        // java/lang/Enum
  interfaces: 0, fields: 5, methods: 4, attributes: 2
Constant pool:
   #1 = Fieldref           #4.#42         // org/kohsuke/github/GHPermissionType.$VALUES:[Lorg/kohsuke/github/GHPermissionType;
   #2 = Methodref          #43.#44        // "[Lorg/kohsuke/github/GHPermissionType;".clone:()Ljava/lang/Object;
   #3 = Class              #23            // "[Lorg/kohsuke/github/GHPermissionType;"
   #4 = Class              #45            // org/kohsuke/github/GHPermissionType
   #5 = Methodref          #16.#46        // java/lang/Enum.valueOf:(Ljava/lang/Class;Ljava/lang/String;)Ljava/lang/Enum;
   #6 = Methodref          #16.#47        // java/lang/Enum."<init>":(Ljava/lang/String;I)V
   #7 = String             #17            // ADMIN
   #8 = Methodref          #4.#47         // org/kohsuke/github/GHPermissionType."<init>":(Ljava/lang/String;I)V
   #9 = Fieldref           #4.#48         // org/kohsuke/github/GHPermissionType.ADMIN:Lorg/kohsuke/github/GHPermissionType;
  #10 = String             #19            // WRITE
  #11 = Fieldref           #4.#49         // org/kohsuke/github/GHPermissionType.WRITE:Lorg/kohsuke/github/GHPermissionType;
  #12 = String             #20            // READ
  #13 = Fieldref           #4.#50         // org/kohsuke/github/GHPermissionType.READ:Lorg/kohsuke/github/GHPermissionType;
  #14 = String             #21            // NONE
  #15 = Fieldref           #4.#51         // org/kohsuke/github/GHPermissionType.NONE:Lorg/kohsuke/github/GHPermissionType;
  #16 = Class              #52            // java/lang/Enum
  #17 = Utf8               ADMIN
  #18 = Utf8               Lorg/kohsuke/github/GHPermissionType;
  #19 = Utf8               WRITE
  #20 = Utf8               READ
  #21 = Utf8               NONE
  #22 = Utf8               $VALUES
  #23 = Utf8               [Lorg/kohsuke/github/GHPermissionType;
  #24 = Utf8               values
  #25 = Utf8               ()[Lorg/kohsuke/github/GHPermissionType;
  #26 = Utf8               Code
  #27 = Utf8               LineNumberTable
  #28 = Utf8               valueOf
  #29 = Utf8               (Ljava/lang/String;)Lorg/kohsuke/github/GHPermissionType;
  #30 = Utf8               LocalVariableTable
  #31 = Utf8               name
  #32 = Utf8               Ljava/lang/String;
  #33 = Utf8               <init>
  #34 = Utf8               (Ljava/lang/String;I)V
  #35 = Utf8               this
  #36 = Utf8               Signature
  #37 = Utf8               ()V
  #38 = Utf8               <clinit>
  #39 = Utf8               Ljava/lang/Enum<Lorg/kohsuke/github/GHPermissionType;>;
  #40 = Utf8               SourceFile
  #41 = Utf8               GHPermissionType.java
  #42 = NameAndType        #22:#23        // $VALUES:[Lorg/kohsuke/github/GHPermissionType;
  #43 = Class              #23            // "[Lorg/kohsuke/github/GHPermissionType;"
  #44 = NameAndType        #53:#54        // clone:()Ljava/lang/Object;
  #45 = Utf8               org/kohsuke/github/GHPermissionType
  #46 = NameAndType        #28:#55        // valueOf:(Ljava/lang/Class;Ljava/lang/String;)Ljava/lang/Enum;
  #47 = NameAndType        #33:#34        // "<init>":(Ljava/lang/String;I)V
  #48 = NameAndType        #17:#18        // ADMIN:Lorg/kohsuke/github/GHPermissionType;
  #49 = NameAndType        #19:#18        // WRITE:Lorg/kohsuke/github/GHPermissionType;
  #50 = NameAndType        #20:#18        // READ:Lorg/kohsuke/github/GHPermissionType;
  #51 = NameAndType        #21:#18        // NONE:Lorg/kohsuke/github/GHPermissionType;
  #52 = Utf8               java/lang/Enum
  #53 = Utf8               clone
  #54 = Utf8               ()Ljava/lang/Object;
  #55 = Utf8               (Ljava/lang/Class;Ljava/lang/String;)Ljava/lang/Enum;
{
  public static final org.kohsuke.github.GHPermissionType ADMIN;
    descriptor: Lorg/kohsuke/github/GHPermissionType;
    flags: (0x4019) ACC_PUBLIC, ACC_STATIC, ACC_FINAL, ACC_ENUM

  public static final org.kohsuke.github.GHPermissionType WRITE;
    descriptor: Lorg/kohsuke/github/GHPermissionType;
    flags: (0x4019) ACC_PUBLIC, ACC_STATIC, ACC_FINAL, ACC_ENUM

  public static final org.kohsuke.github.GHPermissionType READ;
    descriptor: Lorg/kohsuke/github/GHPermissionType;
    flags: (0x4019) ACC_PUBLIC, ACC_STATIC, ACC_FINAL, ACC_ENUM

  public static final org.kohsuke.github.GHPermissionType NONE;
    descriptor: Lorg/kohsuke/github/GHPermissionType;
    flags: (0x4019) ACC_PUBLIC, ACC_STATIC, ACC_FINAL, ACC_ENUM

  private static final org.kohsuke.github.GHPermissionType[] $VALUES;
    descriptor: [Lorg/kohsuke/github/GHPermissionType;
    flags: (0x101a) ACC_PRIVATE, ACC_STATIC, ACC_FINAL, ACC_SYNTHETIC

  public static org.kohsuke.github.GHPermissionType[] values();
    descriptor: ()[Lorg/kohsuke/github/GHPermissionType;
    flags: (0x0009) ACC_PUBLIC, ACC_STATIC
    Code:
      stack=1, locals=0, args_size=0
         0: getstatic     #1                  // Field $VALUES:[Lorg/kohsuke/github/GHPermissionType;
         3: invokevirtual #2                  // Method "[Lorg/kohsuke/github/GHPermissionType;".clone:()Ljava/lang/Object;
         6: checkcast     #3                  // class "[Lorg/kohsuke/github/GHPermissionType;"
         9: areturn
      LineNumberTable:
        line 8: 0

  public static org.kohsuke.github.GHPermissionType valueOf(java.lang.String);
    descriptor: (Ljava/lang/String;)Lorg/kohsuke/github/GHPermissionType;
    flags: (0x0009) ACC_PUBLIC, ACC_STATIC
    Code:
      stack=2, locals=1, args_size=1
         0: ldc           #4                  // class org/kohsuke/github/GHPermissionType
         2: aload_0
         3: invokestatic  #5                  // Method java/lang/Enum.valueOf:(Ljava/lang/Class;Ljava/lang/String;)Ljava/lang/Enum;
         6: checkcast     #4                  // class org/kohsuke/github/GHPermissionType
         9: areturn
      LineNumberTable:
        line 8: 0
      LocalVariableTable:
        Start  Length  Slot  Name   Signature
            0      10     0  name   Ljava/lang/String;

  private org.kohsuke.github.GHPermissionType();
    descriptor: (Ljava/lang/String;I)V
    flags: (0x0002) ACC_PRIVATE
    Code:
      stack=3, locals=3, args_size=3
         0: aload_0
         1: aload_1
         2: iload_2
         3: invokespecial #6                  // Method java/lang/Enum."<init>":(Ljava/lang/String;I)V
         6: return
      LineNumberTable:
        line 8: 0
      LocalVariableTable:
        Start  Length  Slot  Name   Signature
            0       7     0  this   Lorg/kohsuke/github/GHPermissionType;
    Signature: #37                          // ()V

  static {};
    descriptor: ()V
    flags: (0x0008) ACC_STATIC
    Code:
      stack=4, locals=0, args_size=0
         0: new           #4                  // class org/kohsuke/github/GHPermissionType
         3: dup
         4: ldc           #7                  // String ADMIN
         6: iconst_0
         7: invokespecial #8                  // Method "<init>":(Ljava/lang/String;I)V
        10: putstatic     #9                  // Field ADMIN:Lorg/kohsuke/github/GHPermissionType;
        13: new           #4                  // class org/kohsuke/github/GHPermissionType
        16: dup
        17: ldc           #10                 // String WRITE
        19: iconst_1
        20: invokespecial #8                  // Method "<init>":(Ljava/lang/String;I)V
        23: putstatic     #11                 // Field WRITE:Lorg/kohsuke/github/GHPermissionType;
        26: new           #4                  // class org/kohsuke/github/GHPermissionType
        29: dup
        30: ldc           #12                 // String READ
        32: iconst_2
        33: invokespecial #8                  // Method "<init>":(Ljava/lang/String;I)V
        36: putstatic     #13                 // Field READ:Lorg/kohsuke/github/GHPermissionType;
        39: new           #4                  // class org/kohsuke/github/GHPermissionType
        42: dup
        43: ldc           #14                 // String NONE
        45: iconst_3
        46: invokespecial #8                  // Method "<init>":(Ljava/lang/String;I)V
        49: putstatic     #15                 // Field NONE:Lorg/kohsuke/github/GHPermissionType;
        52: iconst_4
        53: anewarray     #4                  // class org/kohsuke/github/GHPermissionType
        56: dup
        57: iconst_0
        58: getstatic     #9                  // Field ADMIN:Lorg/kohsuke/github/GHPermissionType;
        61: aastore
        62: dup
        63: iconst_1
        64: getstatic     #11                 // Field WRITE:Lorg/kohsuke/github/GHPermissionType;
        67: aastore
        68: dup
        69: iconst_2
        70: getstatic     #13                 // Field READ:Lorg/kohsuke/github/GHPermissionType;
        73: aastore
        74: dup
        75: iconst_3
        76: getstatic     #15                 // Field NONE:Lorg/kohsuke/github/GHPermissionType;
        79: aastore
        80: putstatic     #1                  // Field $VALUES:[Lorg/kohsuke/github/GHPermissionType;
        83: return
      LineNumberTable:
        line 9: 0
        line 8: 52
}
Signature: #39                          // Ljava/lang/Enum<Lorg/kohsuke/github/GHPermissionType;>;
SourceFile: "GHPermissionType.java"
