Classfile /Users/mw/Projects/slang-braindump/.jar/jar11/assemble/slang-braindump/assemble/content/org/kohsuke/github/GHPerson$1.class
  Last modified May 29, 2022; size 1199 bytes
  SHA-256 checksum 2c144caf615910fb6a76237fab72d905d7390e45ecfe64742f3d37aa6385dc15
  Compiled from "GHPerson.java"
class org.kohsuke.github.GHPerson$1 extends java.lang.Object implements java.util.Iterator<java.util.List<org.kohsuke.github.GHRepository>>
  minor version: 0
  major version: 52
  flags: (0x0020) ACC_SUPER
  this_class: #7                          // org/kohsuke/github/GHPerson$1
  super_class: #8                         // java/lang/Object
  interfaces: 1, fields: 2, methods: 4, attributes: 4
Constant pool:
   #1 = Fieldref           #7.#35         // org/kohsuke/github/GHPerson$1.this$0:Lorg/kohsuke/github/GHPerson;
   #2 = Fieldref           #7.#36         // org/kohsuke/github/GHPerson$1.val$pager:Lorg/kohsuke/github/PagedIterator;
   #3 = Methodref          #8.#37         // java/lang/Object."<init>":()V
   #4 = Methodref          #38.#39        // org/kohsuke/github/PagedIterator.hasNext:()Z
   #5 = Methodref          #38.#40        // org/kohsuke/github/PagedIterator.nextPage:()Ljava/util/List;
   #6 = Methodref          #7.#41         // org/kohsuke/github/GHPerson$1.next:()Ljava/util/List;
   #7 = Class              #42            // org/kohsuke/github/GHPerson$1
   #8 = Class              #43            // java/lang/Object
   #9 = Class              #44            // java/util/Iterator
  #10 = Utf8               val$pager
  #11 = Utf8               Lorg/kohsuke/github/PagedIterator;
  #12 = Utf8               this$0
  #13 = Utf8               Lorg/kohsuke/github/GHPerson;
  #14 = Utf8               <init>
  #15 = Utf8               (Lorg/kohsuke/github/GHPerson;Lorg/kohsuke/github/PagedIterator;)V
  #16 = Utf8               Code
  #17 = Utf8               LineNumberTable
  #18 = Utf8               LocalVariableTable
  #19 = Utf8               this
  #20 = Utf8               InnerClasses
  #21 = Utf8               Lorg/kohsuke/github/GHPerson$1;
  #22 = Utf8               hasNext
  #23 = Utf8               ()Z
  #24 = Utf8               next
  #25 = Utf8               ()Ljava/util/List;
  #26 = Utf8               Signature
  #27 = Utf8               ()Ljava/util/List<Lorg/kohsuke/github/GHRepository;>;
  #28 = Utf8               ()Ljava/lang/Object;
  #29 = Utf8               Ljava/lang/Object;Ljava/util/Iterator<Ljava/util/List<Lorg/kohsuke/github/GHRepository;>;>;
  #30 = Utf8               SourceFile
  #31 = Utf8               GHPerson.java
  #32 = Utf8               EnclosingMethod
  #33 = Class              #45            // org/kohsuke/github/GHPerson
  #34 = NameAndType        #46:#47        // lambda$iterateRepositories$0:(I)Ljava/util/Iterator;
  #35 = NameAndType        #12:#13        // this$0:Lorg/kohsuke/github/GHPerson;
  #36 = NameAndType        #10:#11        // val$pager:Lorg/kohsuke/github/PagedIterator;
  #37 = NameAndType        #14:#48        // "<init>":()V
  #38 = Class              #49            // org/kohsuke/github/PagedIterator
  #39 = NameAndType        #22:#23        // hasNext:()Z
  #40 = NameAndType        #50:#25        // nextPage:()Ljava/util/List;
  #41 = NameAndType        #24:#25        // next:()Ljava/util/List;
  #42 = Utf8               org/kohsuke/github/GHPerson$1
  #43 = Utf8               java/lang/Object
  #44 = Utf8               java/util/Iterator
  #45 = Utf8               org/kohsuke/github/GHPerson
  #46 = Utf8               lambda$iterateRepositories$0
  #47 = Utf8               (I)Ljava/util/Iterator;
  #48 = Utf8               ()V
  #49 = Utf8               org/kohsuke/github/PagedIterator
  #50 = Utf8               nextPage
{
  final org.kohsuke.github.PagedIterator val$pager;
    descriptor: Lorg/kohsuke/github/PagedIterator;
    flags: (0x1010) ACC_FINAL, ACC_SYNTHETIC

  final org.kohsuke.github.GHPerson this$0;
    descriptor: Lorg/kohsuke/github/GHPerson;
    flags: (0x1010) ACC_FINAL, ACC_SYNTHETIC

  org.kohsuke.github.GHPerson$1(org.kohsuke.github.GHPerson, org.kohsuke.github.PagedIterator);
    descriptor: (Lorg/kohsuke/github/GHPerson;Lorg/kohsuke/github/PagedIterator;)V
    flags: (0x0000)
    Code:
      stack=2, locals=3, args_size=3
         0: aload_0
         1: aload_1
         2: putfield      #1                  // Field this$0:Lorg/kohsuke/github/GHPerson;
         5: aload_0
         6: aload_2
         7: putfield      #2                  // Field val$pager:Lorg/kohsuke/github/PagedIterator;
        10: aload_0
        11: invokespecial #3                  // Method java/lang/Object."<init>":()V
        14: return
      LineNumberTable:
        line 123: 0
      LocalVariableTable:
        Start  Length  Slot  Name   Signature
            0      15     0  this   Lorg/kohsuke/github/GHPerson$1;
            0      15     1 this$0   Lorg/kohsuke/github/GHPerson;

  public boolean hasNext();
    descriptor: ()Z
    flags: (0x0001) ACC_PUBLIC
    Code:
      stack=1, locals=1, args_size=1
         0: aload_0
         1: getfield      #2                  // Field val$pager:Lorg/kohsuke/github/PagedIterator;
         4: invokevirtual #4                  // Method org/kohsuke/github/PagedIterator.hasNext:()Z
         7: ireturn
      LineNumberTable:
        line 125: 0
      LocalVariableTable:
        Start  Length  Slot  Name   Signature
            0       8     0  this   Lorg/kohsuke/github/GHPerson$1;

  public java.util.List<org.kohsuke.github.GHRepository> next();
    descriptor: ()Ljava/util/List;
    flags: (0x0001) ACC_PUBLIC
    Code:
      stack=1, locals=1, args_size=1
         0: aload_0
         1: getfield      #2                  // Field val$pager:Lorg/kohsuke/github/PagedIterator;
         4: invokevirtual #5                  // Method org/kohsuke/github/PagedIterator.nextPage:()Ljava/util/List;
         7: areturn
      LineNumberTable:
        line 129: 0
      LocalVariableTable:
        Start  Length  Slot  Name   Signature
            0       8     0  this   Lorg/kohsuke/github/GHPerson$1;
    Signature: #27                          // ()Ljava/util/List<Lorg/kohsuke/github/GHRepository;>;

  public java.lang.Object next();
    descriptor: ()Ljava/lang/Object;
    flags: (0x1041) ACC_PUBLIC, ACC_BRIDGE, ACC_SYNTHETIC
    Code:
      stack=1, locals=1, args_size=1
         0: aload_0
         1: invokevirtual #6                  // Method next:()Ljava/util/List;
         4: areturn
      LineNumberTable:
        line 123: 0
      LocalVariableTable:
        Start  Length  Slot  Name   Signature
            0       5     0  this   Lorg/kohsuke/github/GHPerson$1;
}
Signature: #29                          // Ljava/lang/Object;Ljava/util/Iterator<Ljava/util/List<Lorg/kohsuke/github/GHRepository;>;>;
SourceFile: "GHPerson.java"
EnclosingMethod: #33.#34                // org.kohsuke.github.GHPerson.lambda$iterateRepositories$0
InnerClasses:
  #7;                                     // class org/kohsuke/github/GHPerson$1
