Classfile /Users/mw/Projects/slang-braindump/.jar/jar11/assemble/slang-braindump/assemble/content/org/kohsuke/github/GHPullRequestReviewState.class
  Last modified May 29, 2022; size 2116 bytes
  SHA-256 checksum ae9739b637bdb35caf34cf0775206dfbc7aa789e77363038a6d82b19061d53b4
  Compiled from "GHPullRequestReviewState.java"
public final class org.kohsuke.github.GHPullRequestReviewState extends java.lang.Enum<org.kohsuke.github.GHPullRequestReviewState>
  minor version: 0
  major version: 52
  flags: (0x4031) ACC_PUBLIC, ACC_FINAL, ACC_SUPER, ACC_ENUM
  this_class: #4                          // org/kohsuke/github/GHPullRequestReviewState
  super_class: #28                        // java/lang/Enum
  interfaces: 0, fields: 7, methods: 6, attributes: 3
Constant pool:
    #1 = Fieldref           #4.#68        // org/kohsuke/github/GHPullRequestReviewState.$VALUES:[Lorg/kohsuke/github/GHPullRequestReviewState;
    #2 = Methodref          #69.#70       // "[Lorg/kohsuke/github/GHPullRequestReviewState;".clone:()Ljava/lang/Object;
    #3 = Class              #40           // "[Lorg/kohsuke/github/GHPullRequestReviewState;"
    #4 = Class              #71           // org/kohsuke/github/GHPullRequestReviewState
    #5 = Methodref          #28.#72       // java/lang/Enum.valueOf:(Ljava/lang/Class;Ljava/lang/String;)Ljava/lang/Enum;
    #6 = Methodref          #28.#73       // java/lang/Enum."<init>":(Ljava/lang/String;I)V
    #7 = Methodref          #4.#74        // org/kohsuke/github/GHPullRequestReviewState.toEvent:()Lorg/kohsuke/github/GHPullRequestReviewEvent;
    #8 = Methodref          #60.#75       // org/kohsuke/github/GHPullRequestReviewEvent.action:()Ljava/lang/String;
    #9 = Fieldref           #29.#76       // org/kohsuke/github/GHPullRequestReviewState$1.$SwitchMap$org$kohsuke$github$GHPullRequestReviewState:[I
   #10 = Methodref          #4.#77        // org/kohsuke/github/GHPullRequestReviewState.ordinal:()I
   #11 = Fieldref           #60.#78       // org/kohsuke/github/GHPullRequestReviewEvent.PENDING:Lorg/kohsuke/github/GHPullRequestReviewEvent;
   #12 = Fieldref           #60.#79       // org/kohsuke/github/GHPullRequestReviewEvent.APPROVE:Lorg/kohsuke/github/GHPullRequestReviewEvent;
   #13 = Fieldref           #60.#80       // org/kohsuke/github/GHPullRequestReviewEvent.REQUEST_CHANGES:Lorg/kohsuke/github/GHPullRequestReviewEvent;
   #14 = Fieldref           #60.#81       // org/kohsuke/github/GHPullRequestReviewEvent.COMMENT:Lorg/kohsuke/github/GHPullRequestReviewEvent;
   #15 = String             #31           // PENDING
   #16 = Methodref          #4.#73        // org/kohsuke/github/GHPullRequestReviewState."<init>":(Ljava/lang/String;I)V
   #17 = Fieldref           #4.#82        // org/kohsuke/github/GHPullRequestReviewState.PENDING:Lorg/kohsuke/github/GHPullRequestReviewState;
   #18 = String             #33           // APPROVED
   #19 = Fieldref           #4.#83        // org/kohsuke/github/GHPullRequestReviewState.APPROVED:Lorg/kohsuke/github/GHPullRequestReviewState;
   #20 = String             #34           // CHANGES_REQUESTED
   #21 = Fieldref           #4.#84        // org/kohsuke/github/GHPullRequestReviewState.CHANGES_REQUESTED:Lorg/kohsuke/github/GHPullRequestReviewState;
   #22 = String             #35           // REQUEST_CHANGES
   #23 = Fieldref           #4.#85        // org/kohsuke/github/GHPullRequestReviewState.REQUEST_CHANGES:Lorg/kohsuke/github/GHPullRequestReviewState;
   #24 = String             #37           // COMMENTED
   #25 = Fieldref           #4.#86        // org/kohsuke/github/GHPullRequestReviewState.COMMENTED:Lorg/kohsuke/github/GHPullRequestReviewState;
   #26 = String             #38           // DISMISSED
   #27 = Fieldref           #4.#87        // org/kohsuke/github/GHPullRequestReviewState.DISMISSED:Lorg/kohsuke/github/GHPullRequestReviewState;
   #28 = Class              #88           // java/lang/Enum
   #29 = Class              #89           // org/kohsuke/github/GHPullRequestReviewState$1
   #30 = Utf8               InnerClasses
   #31 = Utf8               PENDING
   #32 = Utf8               Lorg/kohsuke/github/GHPullRequestReviewState;
   #33 = Utf8               APPROVED
   #34 = Utf8               CHANGES_REQUESTED
   #35 = Utf8               REQUEST_CHANGES
   #36 = Utf8               Deprecated
   #37 = Utf8               COMMENTED
   #38 = Utf8               DISMISSED
   #39 = Utf8               $VALUES
   #40 = Utf8               [Lorg/kohsuke/github/GHPullRequestReviewState;
   #41 = Utf8               values
   #42 = Utf8               ()[Lorg/kohsuke/github/GHPullRequestReviewState;
   #43 = Utf8               Code
   #44 = Utf8               LineNumberTable
   #45 = Utf8               valueOf
   #46 = Utf8               (Ljava/lang/String;)Lorg/kohsuke/github/GHPullRequestReviewState;
   #47 = Utf8               LocalVariableTable
   #48 = Utf8               name
   #49 = Utf8               Ljava/lang/String;
   #50 = Utf8               <init>
   #51 = Utf8               (Ljava/lang/String;I)V
   #52 = Utf8               this
   #53 = Utf8               Signature
   #54 = Utf8               ()V
   #55 = Utf8               action
   #56 = Utf8               ()Ljava/lang/String;
   #57 = Utf8               e
   #58 = Utf8               Lorg/kohsuke/github/GHPullRequestReviewEvent;
   #59 = Utf8               StackMapTable
   #60 = Class              #90           // org/kohsuke/github/GHPullRequestReviewEvent
   #61 = Class              #91           // java/lang/String
   #62 = Utf8               toEvent
   #63 = Utf8               ()Lorg/kohsuke/github/GHPullRequestReviewEvent;
   #64 = Utf8               <clinit>
   #65 = Utf8               Ljava/lang/Enum<Lorg/kohsuke/github/GHPullRequestReviewState;>;
   #66 = Utf8               SourceFile
   #67 = Utf8               GHPullRequestReviewState.java
   #68 = NameAndType        #39:#40       // $VALUES:[Lorg/kohsuke/github/GHPullRequestReviewState;
   #69 = Class              #40           // "[Lorg/kohsuke/github/GHPullRequestReviewState;"
   #70 = NameAndType        #92:#93       // clone:()Ljava/lang/Object;
   #71 = Utf8               org/kohsuke/github/GHPullRequestReviewState
   #72 = NameAndType        #45:#94       // valueOf:(Ljava/lang/Class;Ljava/lang/String;)Ljava/lang/Enum;
   #73 = NameAndType        #50:#51       // "<init>":(Ljava/lang/String;I)V
   #74 = NameAndType        #62:#63       // toEvent:()Lorg/kohsuke/github/GHPullRequestReviewEvent;
   #75 = NameAndType        #55:#56       // action:()Ljava/lang/String;
   #76 = NameAndType        #95:#96       // $SwitchMap$org$kohsuke$github$GHPullRequestReviewState:[I
   #77 = NameAndType        #97:#98       // ordinal:()I
   #78 = NameAndType        #31:#58       // PENDING:Lorg/kohsuke/github/GHPullRequestReviewEvent;
   #79 = NameAndType        #99:#58       // APPROVE:Lorg/kohsuke/github/GHPullRequestReviewEvent;
   #80 = NameAndType        #35:#58       // REQUEST_CHANGES:Lorg/kohsuke/github/GHPullRequestReviewEvent;
   #81 = NameAndType        #100:#58      // COMMENT:Lorg/kohsuke/github/GHPullRequestReviewEvent;
   #82 = NameAndType        #31:#32       // PENDING:Lorg/kohsuke/github/GHPullRequestReviewState;
   #83 = NameAndType        #33:#32       // APPROVED:Lorg/kohsuke/github/GHPullRequestReviewState;
   #84 = NameAndType        #34:#32       // CHANGES_REQUESTED:Lorg/kohsuke/github/GHPullRequestReviewState;
   #85 = NameAndType        #35:#32       // REQUEST_CHANGES:Lorg/kohsuke/github/GHPullRequestReviewState;
   #86 = NameAndType        #37:#32       // COMMENTED:Lorg/kohsuke/github/GHPullRequestReviewState;
   #87 = NameAndType        #38:#32       // DISMISSED:Lorg/kohsuke/github/GHPullRequestReviewState;
   #88 = Utf8               java/lang/Enum
   #89 = Utf8               org/kohsuke/github/GHPullRequestReviewState$1
   #90 = Utf8               org/kohsuke/github/GHPullRequestReviewEvent
   #91 = Utf8               java/lang/String
   #92 = Utf8               clone
   #93 = Utf8               ()Ljava/lang/Object;
   #94 = Utf8               (Ljava/lang/Class;Ljava/lang/String;)Ljava/lang/Enum;
   #95 = Utf8               $SwitchMap$org$kohsuke$github$GHPullRequestReviewState
   #96 = Utf8               [I
   #97 = Utf8               ordinal
   #98 = Utf8               ()I
   #99 = Utf8               APPROVE
  #100 = Utf8               COMMENT
{
  public static final org.kohsuke.github.GHPullRequestReviewState PENDING;
    descriptor: Lorg/kohsuke/github/GHPullRequestReviewState;
    flags: (0x4019) ACC_PUBLIC, ACC_STATIC, ACC_FINAL, ACC_ENUM

  public static final org.kohsuke.github.GHPullRequestReviewState APPROVED;
    descriptor: Lorg/kohsuke/github/GHPullRequestReviewState;
    flags: (0x4019) ACC_PUBLIC, ACC_STATIC, ACC_FINAL, ACC_ENUM

  public static final org.kohsuke.github.GHPullRequestReviewState CHANGES_REQUESTED;
    descriptor: Lorg/kohsuke/github/GHPullRequestReviewState;
    flags: (0x4019) ACC_PUBLIC, ACC_STATIC, ACC_FINAL, ACC_ENUM

  public static final org.kohsuke.github.GHPullRequestReviewState REQUEST_CHANGES;
    descriptor: Lorg/kohsuke/github/GHPullRequestReviewState;
    flags: (0x4019) ACC_PUBLIC, ACC_STATIC, ACC_FINAL, ACC_ENUM
    Deprecated: true

  public static final org.kohsuke.github.GHPullRequestReviewState COMMENTED;
    descriptor: Lorg/kohsuke/github/GHPullRequestReviewState;
    flags: (0x4019) ACC_PUBLIC, ACC_STATIC, ACC_FINAL, ACC_ENUM

  public static final org.kohsuke.github.GHPullRequestReviewState DISMISSED;
    descriptor: Lorg/kohsuke/github/GHPullRequestReviewState;
    flags: (0x4019) ACC_PUBLIC, ACC_STATIC, ACC_FINAL, ACC_ENUM

  private static final org.kohsuke.github.GHPullRequestReviewState[] $VALUES;
    descriptor: [Lorg/kohsuke/github/GHPullRequestReviewState;
    flags: (0x101a) ACC_PRIVATE, ACC_STATIC, ACC_FINAL, ACC_SYNTHETIC

  public static org.kohsuke.github.GHPullRequestReviewState[] values();
    descriptor: ()[Lorg/kohsuke/github/GHPullRequestReviewState;
    flags: (0x0009) ACC_PUBLIC, ACC_STATIC
    Code:
      stack=1, locals=0, args_size=0
         0: getstatic     #1                  // Field $VALUES:[Lorg/kohsuke/github/GHPullRequestReviewState;
         3: invokevirtual #2                  // Method "[Lorg/kohsuke/github/GHPullRequestReviewState;".clone:()Ljava/lang/Object;
         6: checkcast     #3                  // class "[Lorg/kohsuke/github/GHPullRequestReviewState;"
         9: areturn
      LineNumberTable:
        line 6: 0

  public static org.kohsuke.github.GHPullRequestReviewState valueOf(java.lang.String);
    descriptor: (Ljava/lang/String;)Lorg/kohsuke/github/GHPullRequestReviewState;
    flags: (0x0009) ACC_PUBLIC, ACC_STATIC
    Code:
      stack=2, locals=1, args_size=1
         0: ldc           #4                  // class org/kohsuke/github/GHPullRequestReviewState
         2: aload_0
         3: invokestatic  #5                  // Method java/lang/Enum.valueOf:(Ljava/lang/Class;Ljava/lang/String;)Ljava/lang/Enum;
         6: checkcast     #4                  // class org/kohsuke/github/GHPullRequestReviewState
         9: areturn
      LineNumberTable:
        line 6: 0
      LocalVariableTable:
        Start  Length  Slot  Name   Signature
            0      10     0  name   Ljava/lang/String;

  private org.kohsuke.github.GHPullRequestReviewState();
    descriptor: (Ljava/lang/String;I)V
    flags: (0x0002) ACC_PRIVATE
    Code:
      stack=3, locals=3, args_size=3
         0: aload_0
         1: aload_1
         2: iload_2
         3: invokespecial #6                  // Method java/lang/Enum."<init>":(Ljava/lang/String;I)V
         6: return
      LineNumberTable:
        line 6: 0
      LocalVariableTable:
        Start  Length  Slot  Name   Signature
            0       7     0  this   Lorg/kohsuke/github/GHPullRequestReviewState;
    Signature: #54                          // ()V

  public java.lang.String action();
    descriptor: ()Ljava/lang/String;
    flags: (0x0001) ACC_PUBLIC
    Code:
      stack=1, locals=2, args_size=1
         0: aload_0
         1: invokevirtual #7                  // Method toEvent:()Lorg/kohsuke/github/GHPullRequestReviewEvent;
         4: astore_1
         5: aload_1
         6: ifnonnull     13
         9: aconst_null
        10: goto          17
        13: aload_1
        14: invokevirtual #8                  // Method org/kohsuke/github/GHPullRequestReviewEvent.action:()Ljava/lang/String;
        17: areturn
      LineNumberTable:
        line 25: 0
        line 26: 5
      LocalVariableTable:
        Start  Length  Slot  Name   Signature
            0      18     0  this   Lorg/kohsuke/github/GHPullRequestReviewState;
            5      13     1     e   Lorg/kohsuke/github/GHPullRequestReviewEvent;
      StackMapTable: number_of_entries = 2
        frame_type = 252 /* append */
          offset_delta = 13
          locals = [ class org/kohsuke/github/GHPullRequestReviewEvent ]
        frame_type = 67 /* same_locals_1_stack_item */
          stack = [ class java/lang/String ]
    Deprecated: true

  org.kohsuke.github.GHPullRequestReviewEvent toEvent();
    descriptor: ()Lorg/kohsuke/github/GHPullRequestReviewEvent;
    flags: (0x0000)
    Code:
      stack=2, locals=1, args_size=1
         0: getstatic     #9                  // Field org/kohsuke/github/GHPullRequestReviewState$1.$SwitchMap$org$kohsuke$github$GHPullRequestReviewState:[I
         3: aload_0
         4: invokevirtual #10                 // Method ordinal:()I
         7: iaload
         8: tableswitch   { // 1 to 5
                       1: 44
                       2: 48
                       3: 52
                       4: 56
                       5: 60
                 default: 64
            }
        44: getstatic     #11                 // Field org/kohsuke/github/GHPullRequestReviewEvent.PENDING:Lorg/kohsuke/github/GHPullRequestReviewEvent;
        47: areturn
        48: getstatic     #12                 // Field org/kohsuke/github/GHPullRequestReviewEvent.APPROVE:Lorg/kohsuke/github/GHPullRequestReviewEvent;
        51: areturn
        52: getstatic     #13                 // Field org/kohsuke/github/GHPullRequestReviewEvent.REQUEST_CHANGES:Lorg/kohsuke/github/GHPullRequestReviewEvent;
        55: areturn
        56: getstatic     #13                 // Field org/kohsuke/github/GHPullRequestReviewEvent.REQUEST_CHANGES:Lorg/kohsuke/github/GHPullRequestReviewEvent;
        59: areturn
        60: getstatic     #14                 // Field org/kohsuke/github/GHPullRequestReviewEvent.COMMENT:Lorg/kohsuke/github/GHPullRequestReviewEvent;
        63: areturn
        64: aconst_null
        65: areturn
      LineNumberTable:
        line 30: 0
        line 32: 44
        line 34: 48
        line 36: 52
        line 38: 56
        line 40: 60
        line 42: 64
      LocalVariableTable:
        Start  Length  Slot  Name   Signature
            0      66     0  this   Lorg/kohsuke/github/GHPullRequestReviewState;
      StackMapTable: number_of_entries = 6
        frame_type = 44 /* same */
        frame_type = 3 /* same */
        frame_type = 3 /* same */
        frame_type = 3 /* same */
        frame_type = 3 /* same */
        frame_type = 3 /* same */

  static {};
    descriptor: ()V
    flags: (0x0008) ACC_STATIC
    Code:
      stack=4, locals=0, args_size=0
         0: new           #4                  // class org/kohsuke/github/GHPullRequestReviewState
         3: dup
         4: ldc           #15                 // String PENDING
         6: iconst_0
         7: invokespecial #16                 // Method "<init>":(Ljava/lang/String;I)V
        10: putstatic     #17                 // Field PENDING:Lorg/kohsuke/github/GHPullRequestReviewState;
        13: new           #4                  // class org/kohsuke/github/GHPullRequestReviewState
        16: dup
        17: ldc           #18                 // String APPROVED
        19: iconst_1
        20: invokespecial #16                 // Method "<init>":(Ljava/lang/String;I)V
        23: putstatic     #19                 // Field APPROVED:Lorg/kohsuke/github/GHPullRequestReviewState;
        26: new           #4                  // class org/kohsuke/github/GHPullRequestReviewState
        29: dup
        30: ldc           #20                 // String CHANGES_REQUESTED
        32: iconst_2
        33: invokespecial #16                 // Method "<init>":(Ljava/lang/String;I)V
        36: putstatic     #21                 // Field CHANGES_REQUESTED:Lorg/kohsuke/github/GHPullRequestReviewState;
        39: new           #4                  // class org/kohsuke/github/GHPullRequestReviewState
        42: dup
        43: ldc           #22                 // String REQUEST_CHANGES
        45: iconst_3
        46: invokespecial #16                 // Method "<init>":(Ljava/lang/String;I)V
        49: putstatic     #23                 // Field REQUEST_CHANGES:Lorg/kohsuke/github/GHPullRequestReviewState;
        52: new           #4                  // class org/kohsuke/github/GHPullRequestReviewState
        55: dup
        56: ldc           #24                 // String COMMENTED
        58: iconst_4
        59: invokespecial #16                 // Method "<init>":(Ljava/lang/String;I)V
        62: putstatic     #25                 // Field COMMENTED:Lorg/kohsuke/github/GHPullRequestReviewState;
        65: new           #4                  // class org/kohsuke/github/GHPullRequestReviewState
        68: dup
        69: ldc           #26                 // String DISMISSED
        71: iconst_5
        72: invokespecial #16                 // Method "<init>":(Ljava/lang/String;I)V
        75: putstatic     #27                 // Field DISMISSED:Lorg/kohsuke/github/GHPullRequestReviewState;
        78: bipush        6
        80: anewarray     #4                  // class org/kohsuke/github/GHPullRequestReviewState
        83: dup
        84: iconst_0
        85: getstatic     #17                 // Field PENDING:Lorg/kohsuke/github/GHPullRequestReviewState;
        88: aastore
        89: dup
        90: iconst_1
        91: getstatic     #19                 // Field APPROVED:Lorg/kohsuke/github/GHPullRequestReviewState;
        94: aastore
        95: dup
        96: iconst_2
        97: getstatic     #21                 // Field CHANGES_REQUESTED:Lorg/kohsuke/github/GHPullRequestReviewState;
       100: aastore
       101: dup
       102: iconst_3
       103: getstatic     #23                 // Field REQUEST_CHANGES:Lorg/kohsuke/github/GHPullRequestReviewState;
       106: aastore
       107: dup
       108: iconst_4
       109: getstatic     #25                 // Field COMMENTED:Lorg/kohsuke/github/GHPullRequestReviewState;
       112: aastore
       113: dup
       114: iconst_5
       115: getstatic     #27                 // Field DISMISSED:Lorg/kohsuke/github/GHPullRequestReviewState;
       118: aastore
       119: putstatic     #1                  // Field $VALUES:[Lorg/kohsuke/github/GHPullRequestReviewState;
       122: return
      LineNumberTable:
        line 7: 0
        line 8: 13
        line 9: 26
        line 14: 39
        line 15: 52
        line 16: 65
        line 6: 78
}
Signature: #65                          // Ljava/lang/Enum<Lorg/kohsuke/github/GHPullRequestReviewState;>;
SourceFile: "GHPullRequestReviewState.java"
InnerClasses:
  static #29;                             // class org/kohsuke/github/GHPullRequestReviewState$1
