Classfile /Users/mw/Projects/slang-braindump/.jar/jar11/assemble/slang-braindump/assemble/content/org/kohsuke/github/GHPullRequest$AutoMerge.class
  Last modified May 29, 2022; size 1382 bytes
  SHA-256 checksum 3cc90e05691496349f1dcda021862e089ddb56a35579aa6246adcc0d7120511c
  Compiled from "GHPullRequest.java"
public class org.kohsuke.github.GHPullRequest$AutoMerge
  minor version: 0
  major version: 52
  flags: (0x0021) ACC_PUBLIC, ACC_SUPER
  this_class: #6                          // org/kohsuke/github/GHPullRequest$AutoMerge
  super_class: #7                         // java/lang/Object
  interfaces: 0, fields: 4, methods: 5, attributes: 3
Constant pool:
   #1 = Methodref          #7.#43         // java/lang/Object."<init>":()V
   #2 = Fieldref           #6.#44         // org/kohsuke/github/GHPullRequest$AutoMerge.enabled_by:Lorg/kohsuke/github/GHUser;
   #3 = Fieldref           #6.#45         // org/kohsuke/github/GHPullRequest$AutoMerge.merge_method:Lorg/kohsuke/github/GHPullRequest$MergeMethod;
   #4 = Fieldref           #6.#46         // org/kohsuke/github/GHPullRequest$AutoMerge.commit_title:Ljava/lang/String;
   #5 = Fieldref           #6.#47         // org/kohsuke/github/GHPullRequest$AutoMerge.commit_message:Ljava/lang/String;
   #6 = Class              #49            // org/kohsuke/github/GHPullRequest$AutoMerge
   #7 = Class              #50            // java/lang/Object
   #8 = Utf8               enabled_by
   #9 = Utf8               Lorg/kohsuke/github/GHUser;
  #10 = Utf8               merge_method
  #11 = Class              #51            // org/kohsuke/github/GHPullRequest$MergeMethod
  #12 = Utf8               MergeMethod
  #13 = Utf8               InnerClasses
  #14 = Utf8               Lorg/kohsuke/github/GHPullRequest$MergeMethod;
  #15 = Utf8               commit_title
  #16 = Utf8               Ljava/lang/String;
  #17 = Utf8               commit_message
  #18 = Utf8               <init>
  #19 = Utf8               ()V
  #20 = Utf8               Code
  #21 = Utf8               LineNumberTable
  #22 = Utf8               LocalVariableTable
  #23 = Utf8               this
  #24 = Utf8               AutoMerge
  #25 = Utf8               Lorg/kohsuke/github/GHPullRequest$AutoMerge;
  #26 = Utf8               getEnabledBy
  #27 = Utf8               ()Lorg/kohsuke/github/GHUser;
  #28 = Utf8               RuntimeInvisibleAnnotations
  #29 = Utf8               Ledu/umd/cs/findbugs/annotations/SuppressFBWarnings;
  #30 = Utf8               value
  #31 = Utf8               EI_EXPOSE_REP
  #32 = Utf8               justification
  #33 = Utf8               Expected behavior
  #34 = Utf8               getMergeMethod
  #35 = Utf8               ()Lorg/kohsuke/github/GHPullRequest$MergeMethod;
  #36 = Utf8               getCommitTitle
  #37 = Utf8               ()Ljava/lang/String;
  #38 = Utf8               getCommitMessage
  #39 = Utf8               SourceFile
  #40 = Utf8               GHPullRequest.java
  #41 = Utf8               UWF_UNWRITTEN_FIELD
  #42 = Utf8               Field comes from JSON deserialization
  #43 = NameAndType        #18:#19        // "<init>":()V
  #44 = NameAndType        #8:#9          // enabled_by:Lorg/kohsuke/github/GHUser;
  #45 = NameAndType        #10:#14        // merge_method:Lorg/kohsuke/github/GHPullRequest$MergeMethod;
  #46 = NameAndType        #15:#16        // commit_title:Ljava/lang/String;
  #47 = NameAndType        #17:#16        // commit_message:Ljava/lang/String;
  #48 = Class              #52            // org/kohsuke/github/GHPullRequest
  #49 = Utf8               org/kohsuke/github/GHPullRequest$AutoMerge
  #50 = Utf8               java/lang/Object
  #51 = Utf8               org/kohsuke/github/GHPullRequest$MergeMethod
  #52 = Utf8               org/kohsuke/github/GHPullRequest
{
  private org.kohsuke.github.GHUser enabled_by;
    descriptor: Lorg/kohsuke/github/GHUser;
    flags: (0x0002) ACC_PRIVATE

  private org.kohsuke.github.GHPullRequest$MergeMethod merge_method;
    descriptor: Lorg/kohsuke/github/GHPullRequest$MergeMethod;
    flags: (0x0002) ACC_PRIVATE

  private java.lang.String commit_title;
    descriptor: Ljava/lang/String;
    flags: (0x0002) ACC_PRIVATE

  private java.lang.String commit_message;
    descriptor: Ljava/lang/String;
    flags: (0x0002) ACC_PRIVATE

  public org.kohsuke.github.GHPullRequest$AutoMerge();
    descriptor: ()V
    flags: (0x0001) ACC_PUBLIC
    Code:
      stack=1, locals=1, args_size=1
         0: aload_0
         1: invokespecial #1                  // Method java/lang/Object."<init>":()V
         4: return
      LineNumberTable:
        line 651: 0
      LocalVariableTable:
        Start  Length  Slot  Name   Signature
            0       5     0  this   Lorg/kohsuke/github/GHPullRequest$AutoMerge;

  public org.kohsuke.github.GHUser getEnabledBy();
    descriptor: ()Lorg/kohsuke/github/GHUser;
    flags: (0x0001) ACC_PUBLIC
    Code:
      stack=1, locals=1, args_size=1
         0: aload_0
         1: getfield      #2                  // Field enabled_by:Lorg/kohsuke/github/GHUser;
         4: areturn
      LineNumberTable:
        line 665: 0
      LocalVariableTable:
        Start  Length  Slot  Name   Signature
            0       5     0  this   Lorg/kohsuke/github/GHPullRequest$AutoMerge;
    RuntimeInvisibleAnnotations:
      0: #29(#30=[s#31],#32=s#33)
        edu.umd.cs.findbugs.annotations.SuppressFBWarnings(
          value=["EI_EXPOSE_REP"]
          justification="Expected behavior"
        )

  public org.kohsuke.github.GHPullRequest$MergeMethod getMergeMethod();
    descriptor: ()Lorg/kohsuke/github/GHPullRequest$MergeMethod;
    flags: (0x0001) ACC_PUBLIC
    Code:
      stack=1, locals=1, args_size=1
         0: aload_0
         1: getfield      #3                  // Field merge_method:Lorg/kohsuke/github/GHPullRequest$MergeMethod;
         4: areturn
      LineNumberTable:
        line 674: 0
      LocalVariableTable:
        Start  Length  Slot  Name   Signature
            0       5     0  this   Lorg/kohsuke/github/GHPullRequest$AutoMerge;

  public java.lang.String getCommitTitle();
    descriptor: ()Ljava/lang/String;
    flags: (0x0001) ACC_PUBLIC
    Code:
      stack=1, locals=1, args_size=1
         0: aload_0
         1: getfield      #4                  // Field commit_title:Ljava/lang/String;
         4: areturn
      LineNumberTable:
        line 683: 0
      LocalVariableTable:
        Start  Length  Slot  Name   Signature
            0       5     0  this   Lorg/kohsuke/github/GHPullRequest$AutoMerge;

  public java.lang.String getCommitMessage();
    descriptor: ()Ljava/lang/String;
    flags: (0x0001) ACC_PUBLIC
    Code:
      stack=1, locals=1, args_size=1
         0: aload_0
         1: getfield      #5                  // Field commit_message:Ljava/lang/String;
         4: areturn
      LineNumberTable:
        line 692: 0
      LocalVariableTable:
        Start  Length  Slot  Name   Signature
            0       5     0  this   Lorg/kohsuke/github/GHPullRequest$AutoMerge;
}
SourceFile: "GHPullRequest.java"
RuntimeInvisibleAnnotations:
  0: #29(#30=[s#41],#32=s#42)
    edu.umd.cs.findbugs.annotations.SuppressFBWarnings(
      value=["UWF_UNWRITTEN_FIELD"]
      justification="Field comes from JSON deserialization"
    )
InnerClasses:
  public static final #12= #11 of #48;    // MergeMethod=class org/kohsuke/github/GHPullRequest$MergeMethod of class org/kohsuke/github/GHPullRequest
  public static #24= #6 of #48;           // AutoMerge=class org/kohsuke/github/GHPullRequest$AutoMerge of class org/kohsuke/github/GHPullRequest
