Classfile /Users/mw/Projects/slang-braindump/.jar/jar11/assemble/slang-braindump/assemble/content/org/kohsuke/github/GHPullRequestCommitDetail$Commit.class
  Last modified May 29, 2022; size 1977 bytes
  SHA-256 checksum ebe7509b27e0defd9f35e3a8a961e753405b0aa0d8acb66dde86055f464e292e
  Compiled from "GHPullRequestCommitDetail.java"
public class org.kohsuke.github.GHPullRequestCommitDetail$Commit
  minor version: 0
  major version: 52
  flags: (0x0021) ACC_PUBLIC, ACC_SUPER
  this_class: #2                          // org/kohsuke/github/GHPullRequestCommitDetail$Commit
  super_class: #4                         // java/lang/Object
  interfaces: 0, fields: 6, methods: 9, attributes: 3
Constant pool:
   #1 = Utf8               org/kohsuke/github/GHPullRequestCommitDetail$Commit
   #2 = Class              #1             // org/kohsuke/github/GHPullRequestCommitDetail$Commit
   #3 = Utf8               java/lang/Object
   #4 = Class              #3             // java/lang/Object
   #5 = Utf8               GHPullRequestCommitDetail.java
   #6 = Utf8               Lcom/infradna/tool/bridge_method_injector/BridgeMethodsAdded;
   #7 = Utf8               org/kohsuke/github/GHPullRequestCommitDetail$Authorship
   #8 = Class              #7             // org/kohsuke/github/GHPullRequestCommitDetail$Authorship
   #9 = Utf8               org/kohsuke/github/GHPullRequestCommitDetail
  #10 = Class              #9             // org/kohsuke/github/GHPullRequestCommitDetail
  #11 = Utf8               Authorship
  #12 = Utf8               org/kohsuke/github/GHPullRequestCommitDetail$Tree
  #13 = Class              #12            // org/kohsuke/github/GHPullRequestCommitDetail$Tree
  #14 = Utf8               Tree
  #15 = Utf8               Commit
  #16 = Utf8               author
  #17 = Utf8               Lorg/kohsuke/github/GHPullRequestCommitDetail$Authorship;
  #18 = Utf8               committer
  #19 = Utf8               message
  #20 = Utf8               Ljava/lang/String;
  #21 = Utf8               tree
  #22 = Utf8               Lorg/kohsuke/github/GHPullRequestCommitDetail$Tree;
  #23 = Utf8               url
  #24 = Utf8               comment_count
  #25 = Utf8               I
  #26 = Utf8               <init>
  #27 = Utf8               ()V
  #28 = NameAndType        #26:#27        // "<init>":()V
  #29 = Methodref          #4.#28         // java/lang/Object."<init>":()V
  #30 = Utf8               this
  #31 = Utf8               Lorg/kohsuke/github/GHPullRequestCommitDetail$Commit;
  #32 = Utf8               getAuthor
  #33 = Utf8               ()Lorg/kohsuke/github/GitUser;
  #34 = Utf8               Lcom/infradna/tool/bridge_method_injector/WithBridgeMethods;
  #35 = Utf8               value
  #36 = Utf8               castRequired
  #37 = Integer            1
  #38 = NameAndType        #16:#17        // author:Lorg/kohsuke/github/GHPullRequestCommitDetail$Authorship;
  #39 = Fieldref           #2.#38         // org/kohsuke/github/GHPullRequestCommitDetail$Commit.author:Lorg/kohsuke/github/GHPullRequestCommitDetail$Authorship;
  #40 = Utf8               getCommitter
  #41 = NameAndType        #18:#17        // committer:Lorg/kohsuke/github/GHPullRequestCommitDetail$Authorship;
  #42 = Fieldref           #2.#41         // org/kohsuke/github/GHPullRequestCommitDetail$Commit.committer:Lorg/kohsuke/github/GHPullRequestCommitDetail$Authorship;
  #43 = Utf8               getMessage
  #44 = Utf8               ()Ljava/lang/String;
  #45 = NameAndType        #19:#20        // message:Ljava/lang/String;
  #46 = Fieldref           #2.#45         // org/kohsuke/github/GHPullRequestCommitDetail$Commit.message:Ljava/lang/String;
  #47 = Utf8               getUrl
  #48 = Utf8               ()Ljava/net/URL;
  #49 = NameAndType        #23:#20        // url:Ljava/lang/String;
  #50 = Fieldref           #2.#49         // org/kohsuke/github/GHPullRequestCommitDetail$Commit.url:Ljava/lang/String;
  #51 = Utf8               org/kohsuke/github/GitHubClient
  #52 = Class              #51            // org/kohsuke/github/GitHubClient
  #53 = Utf8               parseURL
  #54 = Utf8               (Ljava/lang/String;)Ljava/net/URL;
  #55 = NameAndType        #53:#54        // parseURL:(Ljava/lang/String;)Ljava/net/URL;
  #56 = Methodref          #52.#55        // org/kohsuke/github/GitHubClient.parseURL:(Ljava/lang/String;)Ljava/net/URL;
  #57 = Utf8               getComment_count
  #58 = Utf8               ()I
  #59 = NameAndType        #24:#25        // comment_count:I
  #60 = Fieldref           #2.#59         // org/kohsuke/github/GHPullRequestCommitDetail$Commit.comment_count:I
  #61 = Utf8               getTree
  #62 = Utf8               ()Lorg/kohsuke/github/GHPullRequestCommitDetail$Tree;
  #63 = NameAndType        #21:#22        // tree:Lorg/kohsuke/github/GHPullRequestCommitDetail$Tree;
  #64 = Fieldref           #2.#63         // org/kohsuke/github/GHPullRequestCommitDetail$Commit.tree:Lorg/kohsuke/github/GHPullRequestCommitDetail$Tree;
  #65 = Utf8               ()Lorg/kohsuke/github/GHPullRequestCommitDetail$Authorship;
  #66 = NameAndType        #32:#33        // getAuthor:()Lorg/kohsuke/github/GitUser;
  #67 = Methodref          #2.#66         // org/kohsuke/github/GHPullRequestCommitDetail$Commit.getAuthor:()Lorg/kohsuke/github/GitUser;
  #68 = NameAndType        #40:#33        // getCommitter:()Lorg/kohsuke/github/GitUser;
  #69 = Methodref          #2.#68         // org/kohsuke/github/GHPullRequestCommitDetail$Commit.getCommitter:()Lorg/kohsuke/github/GitUser;
  #70 = Utf8               Code
  #71 = Utf8               LineNumberTable
  #72 = Utf8               LocalVariableTable
  #73 = Utf8               RuntimeInvisibleAnnotations
  #74 = Utf8               InnerClasses
  #75 = Utf8               SourceFile
{
  org.kohsuke.github.GHPullRequestCommitDetail$Authorship author;
    descriptor: Lorg/kohsuke/github/GHPullRequestCommitDetail$Authorship;
    flags: (0x0000)

  org.kohsuke.github.GHPullRequestCommitDetail$Authorship committer;
    descriptor: Lorg/kohsuke/github/GHPullRequestCommitDetail$Authorship;
    flags: (0x0000)

  java.lang.String message;
    descriptor: Ljava/lang/String;
    flags: (0x0000)

  org.kohsuke.github.GHPullRequestCommitDetail$Tree tree;
    descriptor: Lorg/kohsuke/github/GHPullRequestCommitDetail$Tree;
    flags: (0x0000)

  java.lang.String url;
    descriptor: Ljava/lang/String;
    flags: (0x0000)

  int comment_count;
    descriptor: I
    flags: (0x0000)

  public org.kohsuke.github.GHPullRequestCommitDetail$Commit();
    descriptor: ()V
    flags: (0x0001) ACC_PUBLIC
    Code:
      stack=1, locals=1, args_size=1
         0: aload_0
         1: invokespecial #29                 // Method java/lang/Object."<init>":()V
         4: return
      LineNumberTable:
        line 85: 0
      LocalVariableTable:
        Start  Length  Slot  Name   Signature
            0       5     0  this   Lorg/kohsuke/github/GHPullRequestCommitDetail$Commit;

  public org.kohsuke.github.GitUser getAuthor();
    descriptor: ()Lorg/kohsuke/github/GitUser;
    flags: (0x0001) ACC_PUBLIC
    Code:
      stack=1, locals=1, args_size=1
         0: aload_0
         1: getfield      #39                 // Field author:Lorg/kohsuke/github/GHPullRequestCommitDetail$Authorship;
         4: areturn
      LineNumberTable:
        line 100: 0
      LocalVariableTable:
        Start  Length  Slot  Name   Signature
            0       5     0  this   Lorg/kohsuke/github/GHPullRequestCommitDetail$Commit;
    RuntimeInvisibleAnnotations:
      0: #34(#35=[c#17],#36=Z#37)
        com.infradna.tool.bridge_method_injector.WithBridgeMethods(
          value=[class Lorg/kohsuke/github/GHPullRequestCommitDetail$Authorship;]
          castRequired=true
        )

  public org.kohsuke.github.GitUser getCommitter();
    descriptor: ()Lorg/kohsuke/github/GitUser;
    flags: (0x0001) ACC_PUBLIC
    Code:
      stack=1, locals=1, args_size=1
         0: aload_0
         1: getfield      #42                 // Field committer:Lorg/kohsuke/github/GHPullRequestCommitDetail$Authorship;
         4: areturn
      LineNumberTable:
        line 110: 0
      LocalVariableTable:
        Start  Length  Slot  Name   Signature
            0       5     0  this   Lorg/kohsuke/github/GHPullRequestCommitDetail$Commit;
    RuntimeInvisibleAnnotations:
      0: #34(#35=[c#17],#36=Z#37)
        com.infradna.tool.bridge_method_injector.WithBridgeMethods(
          value=[class Lorg/kohsuke/github/GHPullRequestCommitDetail$Authorship;]
          castRequired=true
        )

  public java.lang.String getMessage();
    descriptor: ()Ljava/lang/String;
    flags: (0x0001) ACC_PUBLIC
    Code:
      stack=1, locals=1, args_size=1
         0: aload_0
         1: getfield      #46                 // Field message:Ljava/lang/String;
         4: areturn
      LineNumberTable:
        line 119: 0
      LocalVariableTable:
        Start  Length  Slot  Name   Signature
            0       5     0  this   Lorg/kohsuke/github/GHPullRequestCommitDetail$Commit;

  public java.net.URL getUrl();
    descriptor: ()Ljava/net/URL;
    flags: (0x0001) ACC_PUBLIC
    Code:
      stack=1, locals=1, args_size=1
         0: aload_0
         1: getfield      #50                 // Field url:Ljava/lang/String;
         4: invokestatic  #56                 // Method org/kohsuke/github/GitHubClient.parseURL:(Ljava/lang/String;)Ljava/net/URL;
         7: areturn
      LineNumberTable:
        line 128: 0
      LocalVariableTable:
        Start  Length  Slot  Name   Signature
            0       8     0  this   Lorg/kohsuke/github/GHPullRequestCommitDetail$Commit;

  public int getComment_count();
    descriptor: ()I
    flags: (0x0001) ACC_PUBLIC
    Code:
      stack=1, locals=1, args_size=1
         0: aload_0
         1: getfield      #60                 // Field comment_count:I
         4: ireturn
      LineNumberTable:
        line 137: 0
      LocalVariableTable:
        Start  Length  Slot  Name   Signature
            0       5     0  this   Lorg/kohsuke/github/GHPullRequestCommitDetail$Commit;

  public org.kohsuke.github.GHPullRequestCommitDetail$Tree getTree();
    descriptor: ()Lorg/kohsuke/github/GHPullRequestCommitDetail$Tree;
    flags: (0x0001) ACC_PUBLIC
    Code:
      stack=1, locals=1, args_size=1
         0: aload_0
         1: getfield      #64                 // Field tree:Lorg/kohsuke/github/GHPullRequestCommitDetail$Tree;
         4: areturn
      LineNumberTable:
        line 146: 0
      LocalVariableTable:
        Start  Length  Slot  Name   Signature
            0       5     0  this   Lorg/kohsuke/github/GHPullRequestCommitDetail$Commit;

  public org.kohsuke.github.GHPullRequestCommitDetail$Authorship getAuthor();
    descriptor: ()Lorg/kohsuke/github/GHPullRequestCommitDetail$Authorship;
    flags: (0x1041) ACC_PUBLIC, ACC_BRIDGE, ACC_SYNTHETIC
    Code:
      stack=1, locals=1, args_size=1
         0: aload_0
         1: invokevirtual #67                 // Method getAuthor:()Lorg/kohsuke/github/GitUser;
         4: checkcast     #8                  // class org/kohsuke/github/GHPullRequestCommitDetail$Authorship
         7: areturn

  public org.kohsuke.github.GHPullRequestCommitDetail$Authorship getCommitter();
    descriptor: ()Lorg/kohsuke/github/GHPullRequestCommitDetail$Authorship;
    flags: (0x1041) ACC_PUBLIC, ACC_BRIDGE, ACC_SYNTHETIC
    Code:
      stack=1, locals=1, args_size=1
         0: aload_0
         1: invokevirtual #69                 // Method getCommitter:()Lorg/kohsuke/github/GitUser;
         4: checkcast     #8                  // class org/kohsuke/github/GHPullRequestCommitDetail$Authorship
         7: areturn
}
InnerClasses:
  public static #11= #8 of #10;           // Authorship=class org/kohsuke/github/GHPullRequestCommitDetail$Authorship of class org/kohsuke/github/GHPullRequestCommitDetail
  public static #14= #13 of #10;          // Tree=class org/kohsuke/github/GHPullRequestCommitDetail$Tree of class org/kohsuke/github/GHPullRequestCommitDetail
  public static #15= #2 of #10;           // Commit=class org/kohsuke/github/GHPullRequestCommitDetail$Commit of class org/kohsuke/github/GHPullRequestCommitDetail
SourceFile: "GHPullRequestCommitDetail.java"
RuntimeInvisibleAnnotations:
  0: #6()
    com.infradna.tool.bridge_method_injector.BridgeMethodsAdded
