Classfile /Users/mw/Projects/slang-braindump/.jar/jar11/assemble/slang-braindump/assemble/content/org/kohsuke/github/GHPullRequestReviewState$1.class
  Last modified May 29, 2022; size 918 bytes
  SHA-256 checksum a9f18b065baf64ba435173b4c357cacc47f333a3f7746e3a2bedce23c1174f81
  Compiled from "GHPullRequestReviewState.java"
class org.kohsuke.github.GHPullRequestReviewState$1
  minor version: 0
  major version: 52
  flags: (0x1020) ACC_SUPER, ACC_SYNTHETIC
  this_class: #10                         // org/kohsuke/github/GHPullRequestReviewState$1
  super_class: #11                        // java/lang/Object
  interfaces: 0, fields: 1, methods: 1, attributes: 3
Constant pool:
   #1 = Methodref          #23.#24        // org/kohsuke/github/GHPullRequestReviewState.values:()[Lorg/kohsuke/github/GHPullRequestReviewState;
   #2 = Fieldref           #10.#25        // org/kohsuke/github/GHPullRequestReviewState$1.$SwitchMap$org$kohsuke$github$GHPullRequestReviewState:[I
   #3 = Fieldref           #23.#26        // org/kohsuke/github/GHPullRequestReviewState.PENDING:Lorg/kohsuke/github/GHPullRequestReviewState;
   #4 = Methodref          #23.#27        // org/kohsuke/github/GHPullRequestReviewState.ordinal:()I
   #5 = Class              #28            // java/lang/NoSuchFieldError
   #6 = Fieldref           #23.#29        // org/kohsuke/github/GHPullRequestReviewState.APPROVED:Lorg/kohsuke/github/GHPullRequestReviewState;
   #7 = Fieldref           #23.#30        // org/kohsuke/github/GHPullRequestReviewState.CHANGES_REQUESTED:Lorg/kohsuke/github/GHPullRequestReviewState;
   #8 = Fieldref           #23.#31        // org/kohsuke/github/GHPullRequestReviewState.REQUEST_CHANGES:Lorg/kohsuke/github/GHPullRequestReviewState;
   #9 = Fieldref           #23.#32        // org/kohsuke/github/GHPullRequestReviewState.COMMENTED:Lorg/kohsuke/github/GHPullRequestReviewState;
  #10 = Class              #33            // org/kohsuke/github/GHPullRequestReviewState$1
  #11 = Class              #35            // java/lang/Object
  #12 = Utf8               $SwitchMap$org$kohsuke$github$GHPullRequestReviewState
  #13 = Utf8               [I
  #14 = Utf8               <clinit>
  #15 = Utf8               ()V
  #16 = Utf8               Code
  #17 = Utf8               LineNumberTable
  #18 = Utf8               LocalVariableTable
  #19 = Utf8               StackMapTable
  #20 = Utf8               SourceFile
  #21 = Utf8               GHPullRequestReviewState.java
  #22 = Utf8               EnclosingMethod
  #23 = Class              #36            // org/kohsuke/github/GHPullRequestReviewState
  #24 = NameAndType        #37:#38        // values:()[Lorg/kohsuke/github/GHPullRequestReviewState;
  #25 = NameAndType        #12:#13        // $SwitchMap$org$kohsuke$github$GHPullRequestReviewState:[I
  #26 = NameAndType        #39:#40        // PENDING:Lorg/kohsuke/github/GHPullRequestReviewState;
  #27 = NameAndType        #41:#42        // ordinal:()I
  #28 = Utf8               java/lang/NoSuchFieldError
  #29 = NameAndType        #43:#40        // APPROVED:Lorg/kohsuke/github/GHPullRequestReviewState;
  #30 = NameAndType        #44:#40        // CHANGES_REQUESTED:Lorg/kohsuke/github/GHPullRequestReviewState;
  #31 = NameAndType        #45:#40        // REQUEST_CHANGES:Lorg/kohsuke/github/GHPullRequestReviewState;
  #32 = NameAndType        #46:#40        // COMMENTED:Lorg/kohsuke/github/GHPullRequestReviewState;
  #33 = Utf8               org/kohsuke/github/GHPullRequestReviewState$1
  #34 = Utf8               InnerClasses
  #35 = Utf8               java/lang/Object
  #36 = Utf8               org/kohsuke/github/GHPullRequestReviewState
  #37 = Utf8               values
  #38 = Utf8               ()[Lorg/kohsuke/github/GHPullRequestReviewState;
  #39 = Utf8               PENDING
  #40 = Utf8               Lorg/kohsuke/github/GHPullRequestReviewState;
  #41 = Utf8               ordinal
  #42 = Utf8               ()I
  #43 = Utf8               APPROVED
  #44 = Utf8               CHANGES_REQUESTED
  #45 = Utf8               REQUEST_CHANGES
  #46 = Utf8               COMMENTED
{
  static final int[] $SwitchMap$org$kohsuke$github$GHPullRequestReviewState;
    descriptor: [I
    flags: (0x1018) ACC_STATIC, ACC_FINAL, ACC_SYNTHETIC

  static {};
    descriptor: ()V
    flags: (0x0008) ACC_STATIC
    Code:
      stack=3, locals=1, args_size=0
         0: invokestatic  #1                  // Method org/kohsuke/github/GHPullRequestReviewState.values:()[Lorg/kohsuke/github/GHPullRequestReviewState;
         3: arraylength
         4: newarray       int
         6: putstatic     #2                  // Field $SwitchMap$org$kohsuke$github$GHPullRequestReviewState:[I
         9: getstatic     #2                  // Field $SwitchMap$org$kohsuke$github$GHPullRequestReviewState:[I
        12: getstatic     #3                  // Field org/kohsuke/github/GHPullRequestReviewState.PENDING:Lorg/kohsuke/github/GHPullRequestReviewState;
        15: invokevirtual #4                  // Method org/kohsuke/github/GHPullRequestReviewState.ordinal:()I
        18: iconst_1
        19: iastore
        20: goto          24
        23: astore_0
        24: getstatic     #2                  // Field $SwitchMap$org$kohsuke$github$GHPullRequestReviewState:[I
        27: getstatic     #6                  // Field org/kohsuke/github/GHPullRequestReviewState.APPROVED:Lorg/kohsuke/github/GHPullRequestReviewState;
        30: invokevirtual #4                  // Method org/kohsuke/github/GHPullRequestReviewState.ordinal:()I
        33: iconst_2
        34: iastore
        35: goto          39
        38: astore_0
        39: getstatic     #2                  // Field $SwitchMap$org$kohsuke$github$GHPullRequestReviewState:[I
        42: getstatic     #7                  // Field org/kohsuke/github/GHPullRequestReviewState.CHANGES_REQUESTED:Lorg/kohsuke/github/GHPullRequestReviewState;
        45: invokevirtual #4                  // Method org/kohsuke/github/GHPullRequestReviewState.ordinal:()I
        48: iconst_3
        49: iastore
        50: goto          54
        53: astore_0
        54: getstatic     #2                  // Field $SwitchMap$org$kohsuke$github$GHPullRequestReviewState:[I
        57: getstatic     #8                  // Field org/kohsuke/github/GHPullRequestReviewState.REQUEST_CHANGES:Lorg/kohsuke/github/GHPullRequestReviewState;
        60: invokevirtual #4                  // Method org/kohsuke/github/GHPullRequestReviewState.ordinal:()I
        63: iconst_4
        64: iastore
        65: goto          69
        68: astore_0
        69: getstatic     #2                  // Field $SwitchMap$org$kohsuke$github$GHPullRequestReviewState:[I
        72: getstatic     #9                  // Field org/kohsuke/github/GHPullRequestReviewState.COMMENTED:Lorg/kohsuke/github/GHPullRequestReviewState;
        75: invokevirtual #4                  // Method org/kohsuke/github/GHPullRequestReviewState.ordinal:()I
        78: iconst_5
        79: iastore
        80: goto          84
        83: astore_0
        84: return
      Exception table:
         from    to  target type
             9    20    23   Class java/lang/NoSuchFieldError
            24    35    38   Class java/lang/NoSuchFieldError
            39    50    53   Class java/lang/NoSuchFieldError
            54    65    68   Class java/lang/NoSuchFieldError
            69    80    83   Class java/lang/NoSuchFieldError
      LineNumberTable:
        line 30: 0
      LocalVariableTable:
        Start  Length  Slot  Name   Signature
      StackMapTable: number_of_entries = 10
        frame_type = 87 /* same_locals_1_stack_item */
          stack = [ class java/lang/NoSuchFieldError ]
        frame_type = 0 /* same */
        frame_type = 77 /* same_locals_1_stack_item */
          stack = [ class java/lang/NoSuchFieldError ]
        frame_type = 0 /* same */
        frame_type = 77 /* same_locals_1_stack_item */
          stack = [ class java/lang/NoSuchFieldError ]
        frame_type = 0 /* same */
        frame_type = 77 /* same_locals_1_stack_item */
          stack = [ class java/lang/NoSuchFieldError ]
        frame_type = 0 /* same */
        frame_type = 77 /* same_locals_1_stack_item */
          stack = [ class java/lang/NoSuchFieldError ]
        frame_type = 0 /* same */
}
SourceFile: "GHPullRequestReviewState.java"
EnclosingMethod: #23.#0                 // org.kohsuke.github.GHPullRequestReviewState
InnerClasses:
  static #10;                             // class org/kohsuke/github/GHPullRequestReviewState$1
