Classfile /Users/mw/Projects/slang-braindump/.jar/jar11/assemble/slang-braindump/assemble/content/org/kohsuke/github/GHRateLimit$UnknownLimitRecord.class
  Last modified May 29, 2022; size 1850 bytes
  SHA-256 checksum d15c47914060ddae5a4e1c152b8548b7edfcdea124fc1c0b1f5594db4f9bc8ca
  Compiled from "GHRateLimit.java"
public class org.kohsuke.github.GHRateLimit$UnknownLimitRecord extends org.kohsuke.github.GHRateLimit$Record
  minor version: 0
  major version: 52
  flags: (0x0021) ACC_PUBLIC, ACC_SUPER
  this_class: #2                          // org/kohsuke/github/GHRateLimit$UnknownLimitRecord
  super_class: #8                         // org/kohsuke/github/GHRateLimit$Record
  interfaces: 0, fields: 6, methods: 5, attributes: 2
Constant pool:
   #1 = Fieldref           #2.#60         // org/kohsuke/github/GHRateLimit$UnknownLimitRecord.DEFAULT:Lorg/kohsuke/github/GHRateLimit$UnknownLimitRecord;
   #2 = Class              #62            // org/kohsuke/github/GHRateLimit$UnknownLimitRecord
   #3 = Integer            1000000
   #4 = Integer            999999
   #5 = Methodref          #8.#63         // org/kohsuke/github/GHRateLimit$Record."<init>":(IIJ)V
   #6 = Fieldref           #2.#64         // org/kohsuke/github/GHRateLimit$UnknownLimitRecord.current:Ljava/util/concurrent/atomic/AtomicReference;
   #7 = Methodref          #24.#65        // java/util/concurrent/atomic/AtomicReference.get:()Ljava/lang/Object;
   #8 = Class              #66            // org/kohsuke/github/GHRateLimit$Record
   #9 = Methodref          #8.#67         // org/kohsuke/github/GHRateLimit$Record.isExpired:()Z
  #10 = Methodref          #68.#69        // java/lang/System.currentTimeMillis:()J
  #11 = Long               1000l
  #13 = Fieldref           #2.#70         // org/kohsuke/github/GHRateLimit$UnknownLimitRecord.unknownLimitResetSeconds:J
  #14 = Methodref          #2.#71         // org/kohsuke/github/GHRateLimit$UnknownLimitRecord."<init>":(J)V
  #15 = Methodref          #24.#72        // java/util/concurrent/atomic/AtomicReference.set:(Ljava/lang/Object;)V
  #16 = Fieldref           #2.#73         // org/kohsuke/github/GHRateLimit$UnknownLimitRecord.defaultUnknownLimitResetSeconds:J
  #17 = Long               30l
  #19 = Methodref          #74.#75        // java/time/Duration.ofSeconds:(J)Ljava/time/Duration;
  #20 = Methodref          #74.#76        // java/time/Duration.getSeconds:()J
  #21 = Class              #77            // java/lang/Long
  #22 = Long               -9223372036854775808l
  #24 = Class              #78            // java/util/concurrent/atomic/AtomicReference
  #25 = Methodref          #24.#79        // java/util/concurrent/atomic/AtomicReference."<init>":(Ljava/lang/Object;)V
  #26 = Utf8               defaultUnknownLimitResetSeconds
  #27 = Utf8               J
  #28 = Utf8               unknownLimitResetSeconds
  #29 = Utf8               unknownLimit
  #30 = Utf8               I
  #31 = Utf8               ConstantValue
  #32 = Utf8               unknownRemaining
  #33 = Utf8               DEFAULT
  #34 = Utf8               UnknownLimitRecord
  #35 = Utf8               InnerClasses
  #36 = Utf8               Lorg/kohsuke/github/GHRateLimit$UnknownLimitRecord;
  #37 = Utf8               current
  #38 = Utf8               Ljava/util/concurrent/atomic/AtomicReference;
  #39 = Utf8               Signature
  #40 = Utf8               Ljava/util/concurrent/atomic/AtomicReference<Lorg/kohsuke/github/GHRateLimit$UnknownLimitRecord;>;
  #41 = Utf8               <init>
  #42 = Utf8               (J)V
  #43 = Utf8               Code
  #44 = Utf8               LineNumberTable
  #45 = Utf8               LocalVariableTable
  #46 = Utf8               this
  #47 = Utf8               resetEpochSeconds
  #48 = Utf8               Record
  #49 = Utf8               ()Lorg/kohsuke/github/GHRateLimit$Record;
  #50 = Utf8               result
  #51 = Utf8               Lorg/kohsuke/github/GHRateLimit$Record;
  #52 = Utf8               StackMapTable
  #53 = Utf8               reset
  #54 = Utf8               ()V
  #55 = Utf8               access$000
  #56 = Utf8               ()Lorg/kohsuke/github/GHRateLimit$UnknownLimitRecord;
  #57 = Utf8               <clinit>
  #58 = Utf8               SourceFile
  #59 = Utf8               GHRateLimit.java
  #60 = NameAndType        #33:#36        // DEFAULT:Lorg/kohsuke/github/GHRateLimit$UnknownLimitRecord;
  #61 = Class              #80            // org/kohsuke/github/GHRateLimit
  #62 = Utf8               org/kohsuke/github/GHRateLimit$UnknownLimitRecord
  #63 = NameAndType        #41:#81        // "<init>":(IIJ)V
  #64 = NameAndType        #37:#38        // current:Ljava/util/concurrent/atomic/AtomicReference;
  #65 = NameAndType        #82:#83        // get:()Ljava/lang/Object;
  #66 = Utf8               org/kohsuke/github/GHRateLimit$Record
  #67 = NameAndType        #84:#85        // isExpired:()Z
  #68 = Class              #86            // java/lang/System
  #69 = NameAndType        #87:#88        // currentTimeMillis:()J
  #70 = NameAndType        #28:#27        // unknownLimitResetSeconds:J
  #71 = NameAndType        #41:#42        // "<init>":(J)V
  #72 = NameAndType        #89:#90        // set:(Ljava/lang/Object;)V
  #73 = NameAndType        #26:#27        // defaultUnknownLimitResetSeconds:J
  #74 = Class              #91            // java/time/Duration
  #75 = NameAndType        #92:#93        // ofSeconds:(J)Ljava/time/Duration;
  #76 = NameAndType        #94:#88        // getSeconds:()J
  #77 = Utf8               java/lang/Long
  #78 = Utf8               java/util/concurrent/atomic/AtomicReference
  #79 = NameAndType        #41:#90        // "<init>":(Ljava/lang/Object;)V
  #80 = Utf8               org/kohsuke/github/GHRateLimit
  #81 = Utf8               (IIJ)V
  #82 = Utf8               get
  #83 = Utf8               ()Ljava/lang/Object;
  #84 = Utf8               isExpired
  #85 = Utf8               ()Z
  #86 = Utf8               java/lang/System
  #87 = Utf8               currentTimeMillis
  #88 = Utf8               ()J
  #89 = Utf8               set
  #90 = Utf8               (Ljava/lang/Object;)V
  #91 = Utf8               java/time/Duration
  #92 = Utf8               ofSeconds
  #93 = Utf8               (J)Ljava/time/Duration;
  #94 = Utf8               getSeconds
{
  private static final long defaultUnknownLimitResetSeconds;
    descriptor: J
    flags: (0x001a) ACC_PRIVATE, ACC_STATIC, ACC_FINAL

  static long unknownLimitResetSeconds;
    descriptor: J
    flags: (0x0008) ACC_STATIC

  static final int unknownLimit;
    descriptor: I
    flags: (0x0018) ACC_STATIC, ACC_FINAL
    ConstantValue: int 1000000

  static final int unknownRemaining;
    descriptor: I
    flags: (0x0018) ACC_STATIC, ACC_FINAL
    ConstantValue: int 999999

  private static final org.kohsuke.github.GHRateLimit$UnknownLimitRecord DEFAULT;
    descriptor: Lorg/kohsuke/github/GHRateLimit$UnknownLimitRecord;
    flags: (0x001a) ACC_PRIVATE, ACC_STATIC, ACC_FINAL

  private static final java.util.concurrent.atomic.AtomicReference<org.kohsuke.github.GHRateLimit$UnknownLimitRecord> current;
    descriptor: Ljava/util/concurrent/atomic/AtomicReference;
    flags: (0x001a) ACC_PRIVATE, ACC_STATIC, ACC_FINAL
    Signature: #40                          // Ljava/util/concurrent/atomic/AtomicReference<Lorg/kohsuke/github/GHRateLimit$UnknownLimitRecord;>;

  private org.kohsuke.github.GHRateLimit$UnknownLimitRecord(long);
    descriptor: (J)V
    flags: (0x0002) ACC_PRIVATE
    Code:
      stack=5, locals=3, args_size=2
         0: aload_0
         1: ldc           #3                  // int 1000000
         3: ldc           #4                  // int 999999
         5: lload_1
         6: invokespecial #5                  // Method org/kohsuke/github/GHRateLimit$Record."<init>":(IIJ)V
         9: return
      LineNumberTable:
        line 358: 0
        line 359: 9
      LocalVariableTable:
        Start  Length  Slot  Name   Signature
            0      10     0  this   Lorg/kohsuke/github/GHRateLimit$UnknownLimitRecord;
            0      10     1 resetEpochSeconds   J

  static org.kohsuke.github.GHRateLimit$Record current();
    descriptor: ()Lorg/kohsuke/github/GHRateLimit$Record;
    flags: (0x0008) ACC_STATIC
    Code:
      stack=7, locals=1, args_size=0
         0: getstatic     #6                  // Field current:Ljava/util/concurrent/atomic/AtomicReference;
         3: invokevirtual #7                  // Method java/util/concurrent/atomic/AtomicReference.get:()Ljava/lang/Object;
         6: checkcast     #8                  // class org/kohsuke/github/GHRateLimit$Record
         9: astore_0
        10: aload_0
        11: invokevirtual #9                  // Method org/kohsuke/github/GHRateLimit$Record.isExpired:()Z
        14: ifeq          51
        17: getstatic     #6                  // Field current:Ljava/util/concurrent/atomic/AtomicReference;
        20: new           #2                  // class org/kohsuke/github/GHRateLimit$UnknownLimitRecord
        23: dup
        24: invokestatic  #10                 // Method java/lang/System.currentTimeMillis:()J
        27: ldc2_w        #11                 // long 1000l
        30: ldiv
        31: getstatic     #13                 // Field unknownLimitResetSeconds:J
        34: ladd
        35: invokespecial #14                 // Method "<init>":(J)V
        38: invokevirtual #15                 // Method java/util/concurrent/atomic/AtomicReference.set:(Ljava/lang/Object;)V
        41: getstatic     #6                  // Field current:Ljava/util/concurrent/atomic/AtomicReference;
        44: invokevirtual #7                  // Method java/util/concurrent/atomic/AtomicReference.get:()Ljava/lang/Object;
        47: checkcast     #8                  // class org/kohsuke/github/GHRateLimit$Record
        50: astore_0
        51: aload_0
        52: areturn
      LineNumberTable:
        line 362: 0
        line 363: 10
        line 364: 17
        line 365: 41
        line 367: 51
      LocalVariableTable:
        Start  Length  Slot  Name   Signature
           10      43     0 result   Lorg/kohsuke/github/GHRateLimit$Record;
      StackMapTable: number_of_entries = 1
        frame_type = 252 /* append */
          offset_delta = 51
          locals = [ class org/kohsuke/github/GHRateLimit$Record ]

  static void reset();
    descriptor: ()V
    flags: (0x0008) ACC_STATIC
    Code:
      stack=2, locals=0, args_size=0
         0: getstatic     #6                  // Field current:Ljava/util/concurrent/atomic/AtomicReference;
         3: getstatic     #1                  // Field DEFAULT:Lorg/kohsuke/github/GHRateLimit$UnknownLimitRecord;
         6: invokevirtual #15                 // Method java/util/concurrent/atomic/AtomicReference.set:(Ljava/lang/Object;)V
         9: getstatic     #16                 // Field defaultUnknownLimitResetSeconds:J
        12: putstatic     #13                 // Field unknownLimitResetSeconds:J
        15: return
      LineNumberTable:
        line 374: 0
        line 375: 9
        line 376: 15

  static org.kohsuke.github.GHRateLimit$UnknownLimitRecord access$000();
    descriptor: ()Lorg/kohsuke/github/GHRateLimit$UnknownLimitRecord;
    flags: (0x1008) ACC_STATIC, ACC_SYNTHETIC
    Code:
      stack=1, locals=0, args_size=0
         0: getstatic     #1                  // Field DEFAULT:Lorg/kohsuke/github/GHRateLimit$UnknownLimitRecord;
         3: areturn
      LineNumberTable:
        line 324: 0

  static {};
    descriptor: ()V
    flags: (0x0008) ACC_STATIC
    Code:
      stack=4, locals=0, args_size=0
         0: ldc2_w        #17                 // long 30l
         3: invokestatic  #19                 // Method java/time/Duration.ofSeconds:(J)Ljava/time/Duration;
         6: invokevirtual #20                 // Method java/time/Duration.getSeconds:()J
         9: putstatic     #16                 // Field defaultUnknownLimitResetSeconds:J
        12: getstatic     #16                 // Field defaultUnknownLimitResetSeconds:J
        15: putstatic     #13                 // Field unknownLimitResetSeconds:J
        18: new           #2                  // class org/kohsuke/github/GHRateLimit$UnknownLimitRecord
        21: dup
        22: ldc2_w        #22                 // long -9223372036854775808l
        25: invokespecial #14                 // Method "<init>":(J)V
        28: putstatic     #1                  // Field DEFAULT:Lorg/kohsuke/github/GHRateLimit$UnknownLimitRecord;
        31: new           #24                 // class java/util/concurrent/atomic/AtomicReference
        34: dup
        35: getstatic     #1                  // Field DEFAULT:Lorg/kohsuke/github/GHRateLimit$UnknownLimitRecord;
        38: invokespecial #25                 // Method java/util/concurrent/atomic/AtomicReference."<init>":(Ljava/lang/Object;)V
        41: putstatic     #6                  // Field current:Ljava/util/concurrent/atomic/AtomicReference;
        44: return
      LineNumberTable:
        line 326: 0
        line 340: 12
        line 346: 18
        line 349: 31
}
SourceFile: "GHRateLimit.java"
InnerClasses:
  public static #34= #2 of #61;           // UnknownLimitRecord=class org/kohsuke/github/GHRateLimit$UnknownLimitRecord of class org/kohsuke/github/GHRateLimit
  public static #48= #8 of #61;           // Record=class org/kohsuke/github/GHRateLimit$Record of class org/kohsuke/github/GHRateLimit
