Classfile /Users/mw/Projects/slang-braindump/.jar/jar11/assemble/slang-braindump/assemble/content/org/kohsuke/github/GHRepository$Contributor.class
  Last modified May 29, 2022; size 762 bytes
  SHA-256 checksum 333e44b2243d021265ff0ab5e7b37d5d4fc34b157453cd6932b9b5e99c3a5356
  Compiled from "GHRepository.java"
public class org.kohsuke.github.GHRepository$Contributor extends org.kohsuke.github.GHUser
  minor version: 0
  major version: 52
  flags: (0x0021) ACC_PUBLIC, ACC_SUPER
  this_class: #5                          // org/kohsuke/github/GHRepository$Contributor
  super_class: #6                         // org/kohsuke/github/GHUser
  interfaces: 0, fields: 1, methods: 4, attributes: 2
Constant pool:
   #1 = Methodref          #6.#27         // org/kohsuke/github/GHUser."<init>":()V
   #2 = Fieldref           #5.#28         // org/kohsuke/github/GHRepository$Contributor.contributions:I
   #3 = Methodref          #6.#29         // org/kohsuke/github/GHUser.hashCode:()I
   #4 = Methodref          #6.#30         // org/kohsuke/github/GHUser.equals:(Ljava/lang/Object;)Z
   #5 = Class              #32            // org/kohsuke/github/GHRepository$Contributor
   #6 = Class              #33            // org/kohsuke/github/GHUser
   #7 = Utf8               contributions
   #8 = Utf8               I
   #9 = Utf8               <init>
  #10 = Utf8               ()V
  #11 = Utf8               Code
  #12 = Utf8               LineNumberTable
  #13 = Utf8               LocalVariableTable
  #14 = Utf8               this
  #15 = Utf8               Contributor
  #16 = Utf8               InnerClasses
  #17 = Utf8               Lorg/kohsuke/github/GHRepository$Contributor;
  #18 = Utf8               getContributions
  #19 = Utf8               ()I
  #20 = Utf8               hashCode
  #21 = Utf8               equals
  #22 = Utf8               (Ljava/lang/Object;)Z
  #23 = Utf8               obj
  #24 = Utf8               Ljava/lang/Object;
  #25 = Utf8               SourceFile
  #26 = Utf8               GHRepository.java
  #27 = NameAndType        #9:#10         // "<init>":()V
  #28 = NameAndType        #7:#8          // contributions:I
  #29 = NameAndType        #20:#19        // hashCode:()I
  #30 = NameAndType        #21:#22        // equals:(Ljava/lang/Object;)Z
  #31 = Class              #34            // org/kohsuke/github/GHRepository
  #32 = Utf8               org/kohsuke/github/GHRepository$Contributor
  #33 = Utf8               org/kohsuke/github/GHUser
  #34 = Utf8               org/kohsuke/github/GHRepository
{
  private int contributions;
    descriptor: I
    flags: (0x0002) ACC_PRIVATE

  public org.kohsuke.github.GHRepository$Contributor();
    descriptor: ()V
    flags: (0x0001) ACC_PUBLIC
    Code:
      stack=1, locals=1, args_size=1
         0: aload_0
         1: invokespecial #1                  // Method org/kohsuke/github/GHUser."<init>":()V
         4: return
      LineNumberTable:
        line 2815: 0
      LocalVariableTable:
        Start  Length  Slot  Name   Signature
            0       5     0  this   Lorg/kohsuke/github/GHRepository$Contributor;

  public int getContributions();
    descriptor: ()I
    flags: (0x0001) ACC_PUBLIC
    Code:
      stack=1, locals=1, args_size=1
         0: aload_0
         1: getfield      #2                  // Field contributions:I
         4: ireturn
      LineNumberTable:
        line 2824: 0
      LocalVariableTable:
        Start  Length  Slot  Name   Signature
            0       5     0  this   Lorg/kohsuke/github/GHRepository$Contributor;

  public int hashCode();
    descriptor: ()I
    flags: (0x0001) ACC_PUBLIC
    Code:
      stack=1, locals=1, args_size=1
         0: aload_0
         1: invokespecial #3                  // Method org/kohsuke/github/GHUser.hashCode:()I
         4: ireturn
      LineNumberTable:
        line 2830: 0
      LocalVariableTable:
        Start  Length  Slot  Name   Signature
            0       5     0  this   Lorg/kohsuke/github/GHRepository$Contributor;

  public boolean equals(java.lang.Object);
    descriptor: (Ljava/lang/Object;)Z
    flags: (0x0001) ACC_PUBLIC
    Code:
      stack=2, locals=2, args_size=2
         0: aload_0
         1: aload_1
         2: invokespecial #4                  // Method org/kohsuke/github/GHUser.equals:(Ljava/lang/Object;)Z
         5: ireturn
      LineNumberTable:
        line 2836: 0
      LocalVariableTable:
        Start  Length  Slot  Name   Signature
            0       6     0  this   Lorg/kohsuke/github/GHRepository$Contributor;
            0       6     1   obj   Ljava/lang/Object;
}
SourceFile: "GHRepository.java"
InnerClasses:
  public static #15= #5 of #31;           // Contributor=class org/kohsuke/github/GHRepository$Contributor of class org/kohsuke/github/GHRepository
