Classfile /Users/mw/Projects/slang-braindump/.jar/jar11/assemble/slang-braindump/assemble/content/org/kohsuke/github/GHRepositoryStatistics$Participation.class
  Last modified May 29, 2022; size 1182 bytes
  SHA-256 checksum e4e952b5dfe346266286035ba87a0cabe24e392b6b7a346f51a93ea71b3e2ed4
  Compiled from "GHRepositoryStatistics.java"
public class org.kohsuke.github.GHRepositoryStatistics$Participation extends org.kohsuke.github.GHObject
  minor version: 0
  major version: 52
  flags: (0x0021) ACC_PUBLIC, ACC_SUPER
  this_class: #8                          // org/kohsuke/github/GHRepositoryStatistics$Participation
  super_class: #9                         // org/kohsuke/github/GHObject
  interfaces: 0, fields: 2, methods: 4, attributes: 2
Constant pool:
   #1 = Methodref          #9.#34         // org/kohsuke/github/GHObject."<init>":()V
   #2 = Class              #35            // java/lang/UnsupportedOperationException
   #3 = String             #36            // Not supported yet.
   #4 = Methodref          #2.#37         // java/lang/UnsupportedOperationException."<init>":(Ljava/lang/String;)V
   #5 = Fieldref           #8.#38         // org/kohsuke/github/GHRepositoryStatistics$Participation.all:Ljava/util/List;
   #6 = Methodref          #39.#40        // java/util/Collections.unmodifiableList:(Ljava/util/List;)Ljava/util/List;
   #7 = Fieldref           #8.#41         // org/kohsuke/github/GHRepositoryStatistics$Participation.owner:Ljava/util/List;
   #8 = Class              #43            // org/kohsuke/github/GHRepositoryStatistics$Participation
   #9 = Class              #44            // org/kohsuke/github/GHObject
  #10 = Utf8               all
  #11 = Utf8               Ljava/util/List;
  #12 = Utf8               Signature
  #13 = Utf8               Ljava/util/List<Ljava/lang/Integer;>;
  #14 = Utf8               owner
  #15 = Utf8               <init>
  #16 = Utf8               ()V
  #17 = Utf8               Code
  #18 = Utf8               LineNumberTable
  #19 = Utf8               LocalVariableTable
  #20 = Utf8               this
  #21 = Utf8               Participation
  #22 = Utf8               InnerClasses
  #23 = Utf8               Lorg/kohsuke/github/GHRepositoryStatistics$Participation;
  #24 = Utf8               getHtmlUrl
  #25 = Utf8               ()Ljava/net/URL;
  #26 = Utf8               Exceptions
  #27 = Class              #45            // java/io/IOException
  #28 = Utf8               getAllCommits
  #29 = Utf8               ()Ljava/util/List;
  #30 = Utf8               ()Ljava/util/List<Ljava/lang/Integer;>;
  #31 = Utf8               getOwnerCommits
  #32 = Utf8               SourceFile
  #33 = Utf8               GHRepositoryStatistics.java
  #34 = NameAndType        #15:#16        // "<init>":()V
  #35 = Utf8               java/lang/UnsupportedOperationException
  #36 = Utf8               Not supported yet.
  #37 = NameAndType        #15:#46        // "<init>":(Ljava/lang/String;)V
  #38 = NameAndType        #10:#11        // all:Ljava/util/List;
  #39 = Class              #47            // java/util/Collections
  #40 = NameAndType        #48:#49        // unmodifiableList:(Ljava/util/List;)Ljava/util/List;
  #41 = NameAndType        #14:#11        // owner:Ljava/util/List;
  #42 = Class              #50            // org/kohsuke/github/GHRepositoryStatistics
  #43 = Utf8               org/kohsuke/github/GHRepositoryStatistics$Participation
  #44 = Utf8               org/kohsuke/github/GHObject
  #45 = Utf8               java/io/IOException
  #46 = Utf8               (Ljava/lang/String;)V
  #47 = Utf8               java/util/Collections
  #48 = Utf8               unmodifiableList
  #49 = Utf8               (Ljava/util/List;)Ljava/util/List;
  #50 = Utf8               org/kohsuke/github/GHRepositoryStatistics
{
  private java.util.List<java.lang.Integer> all;
    descriptor: Ljava/util/List;
    flags: (0x0002) ACC_PRIVATE
    Signature: #13                          // Ljava/util/List<Ljava/lang/Integer;>;

  private java.util.List<java.lang.Integer> owner;
    descriptor: Ljava/util/List;
    flags: (0x0002) ACC_PRIVATE
    Signature: #13                          // Ljava/util/List<Ljava/lang/Integer;>;

  public org.kohsuke.github.GHRepositoryStatistics$Participation();
    descriptor: ()V
    flags: (0x0001) ACC_PUBLIC
    Code:
      stack=1, locals=1, args_size=1
         0: aload_0
         1: invokespecial #1                  // Method org/kohsuke/github/GHObject."<init>":()V
         4: return
      LineNumberTable:
        line 370: 0
      LocalVariableTable:
        Start  Length  Slot  Name   Signature
            0       5     0  this   Lorg/kohsuke/github/GHRepositoryStatistics$Participation;

  public java.net.URL getHtmlUrl() throws java.io.IOException;
    descriptor: ()Ljava/net/URL;
    flags: (0x0001) ACC_PUBLIC
    Code:
      stack=3, locals=1, args_size=1
         0: new           #2                  // class java/lang/UnsupportedOperationException
         3: dup
         4: ldc           #3                  // String Not supported yet.
         6: invokespecial #4                  // Method java/lang/UnsupportedOperationException."<init>":(Ljava/lang/String;)V
         9: athrow
      LineNumberTable:
        line 376: 0
      LocalVariableTable:
        Start  Length  Slot  Name   Signature
            0      10     0  this   Lorg/kohsuke/github/GHRepositoryStatistics$Participation;
    Exceptions:
      throws java.io.IOException

  public java.util.List<java.lang.Integer> getAllCommits();
    descriptor: ()Ljava/util/List;
    flags: (0x0001) ACC_PUBLIC
    Code:
      stack=1, locals=1, args_size=1
         0: aload_0
         1: getfield      #5                  // Field all:Ljava/util/List;
         4: invokestatic  #6                  // Method java/util/Collections.unmodifiableList:(Ljava/util/List;)Ljava/util/List;
         7: areturn
      LineNumberTable:
        line 385: 0
      LocalVariableTable:
        Start  Length  Slot  Name   Signature
            0       8     0  this   Lorg/kohsuke/github/GHRepositoryStatistics$Participation;
    Signature: #30                          // ()Ljava/util/List<Ljava/lang/Integer;>;

  public java.util.List<java.lang.Integer> getOwnerCommits();
    descriptor: ()Ljava/util/List;
    flags: (0x0001) ACC_PUBLIC
    Code:
      stack=1, locals=1, args_size=1
         0: aload_0
         1: getfield      #7                  // Field owner:Ljava/util/List;
         4: invokestatic  #6                  // Method java/util/Collections.unmodifiableList:(Ljava/util/List;)Ljava/util/List;
         7: areturn
      LineNumberTable:
        line 394: 0
      LocalVariableTable:
        Start  Length  Slot  Name   Signature
            0       8     0  this   Lorg/kohsuke/github/GHRepositoryStatistics$Participation;
    Signature: #30                          // ()Ljava/util/List<Ljava/lang/Integer;>;
}
SourceFile: "GHRepositoryStatistics.java"
InnerClasses:
  public static #21= #8 of #42;           // Participation=class org/kohsuke/github/GHRepositoryStatistics$Participation of class org/kohsuke/github/GHRepositoryStatistics
