Classfile /Users/mw/Projects/slang-braindump/.jar/jar11/assemble/slang-braindump/assemble/content/org/kohsuke/github/GHRepositoryViewTraffic.class
  Last modified May 29, 2022; size 1268 bytes
  SHA-256 checksum 0365f3de4db8d0dcc49cd45443e9351d2de3629ff90828731c1b5934f67f16e4
  Compiled from "GHRepositoryViewTraffic.java"
public class org.kohsuke.github.GHRepositoryViewTraffic extends org.kohsuke.github.GHRepositoryTraffic
  minor version: 0
  major version: 52
  flags: (0x0021) ACC_PUBLIC, ACC_SUPER
  this_class: #6                          // org/kohsuke/github/GHRepositoryViewTraffic
  super_class: #7                         // org/kohsuke/github/GHRepositoryTraffic
  interfaces: 0, fields: 1, methods: 4, attributes: 2
Constant pool:
   #1 = Methodref          #7.#34         // org/kohsuke/github/GHRepositoryTraffic."<init>":()V
   #2 = Methodref          #7.#35         // org/kohsuke/github/GHRepositoryTraffic."<init>":(II)V
   #3 = Fieldref           #6.#36         // org/kohsuke/github/GHRepositoryViewTraffic.views:Ljava/util/List;
   #4 = Methodref          #37.#38        // java/util/Collections.unmodifiableList:(Ljava/util/List;)Ljava/util/List;
   #5 = Methodref          #6.#39         // org/kohsuke/github/GHRepositoryViewTraffic.getViews:()Ljava/util/List;
   #6 = Class              #40            // org/kohsuke/github/GHRepositoryViewTraffic
   #7 = Class              #41            // org/kohsuke/github/GHRepositoryTraffic
   #8 = Class              #42            // org/kohsuke/github/GHRepositoryViewTraffic$DailyInfo
   #9 = Utf8               DailyInfo
  #10 = Utf8               InnerClasses
  #11 = Utf8               views
  #12 = Utf8               Ljava/util/List;
  #13 = Utf8               Signature
  #14 = Utf8               Ljava/util/List<Lorg/kohsuke/github/GHRepositoryViewTraffic$DailyInfo;>;
  #15 = Utf8               <init>
  #16 = Utf8               ()V
  #17 = Utf8               Code
  #18 = Utf8               LineNumberTable
  #19 = Utf8               LocalVariableTable
  #20 = Utf8               this
  #21 = Utf8               Lorg/kohsuke/github/GHRepositoryViewTraffic;
  #22 = Utf8               (IILjava/util/List;)V
  #23 = Utf8               count
  #24 = Utf8               I
  #25 = Utf8               uniques
  #26 = Utf8               LocalVariableTypeTable
  #27 = Utf8               (IILjava/util/List<Lorg/kohsuke/github/GHRepositoryViewTraffic$DailyInfo;>;)V
  #28 = Utf8               getViews
  #29 = Utf8               ()Ljava/util/List;
  #30 = Utf8               ()Ljava/util/List<Lorg/kohsuke/github/GHRepositoryViewTraffic$DailyInfo;>;
  #31 = Utf8               getDailyInfo
  #32 = Utf8               SourceFile
  #33 = Utf8               GHRepositoryViewTraffic.java
  #34 = NameAndType        #15:#16        // "<init>":()V
  #35 = NameAndType        #15:#43        // "<init>":(II)V
  #36 = NameAndType        #11:#12        // views:Ljava/util/List;
  #37 = Class              #44            // java/util/Collections
  #38 = NameAndType        #45:#46        // unmodifiableList:(Ljava/util/List;)Ljava/util/List;
  #39 = NameAndType        #28:#29        // getViews:()Ljava/util/List;
  #40 = Utf8               org/kohsuke/github/GHRepositoryViewTraffic
  #41 = Utf8               org/kohsuke/github/GHRepositoryTraffic
  #42 = Utf8               org/kohsuke/github/GHRepositoryViewTraffic$DailyInfo
  #43 = Utf8               (II)V
  #44 = Utf8               java/util/Collections
  #45 = Utf8               unmodifiableList
  #46 = Utf8               (Ljava/util/List;)Ljava/util/List;
{
  private java.util.List<org.kohsuke.github.GHRepositoryViewTraffic$DailyInfo> views;
    descriptor: Ljava/util/List;
    flags: (0x0002) ACC_PRIVATE
    Signature: #14                          // Ljava/util/List<Lorg/kohsuke/github/GHRepositoryViewTraffic$DailyInfo;>;

  org.kohsuke.github.GHRepositoryViewTraffic();
    descriptor: ()V
    flags: (0x0000)
    Code:
      stack=1, locals=1, args_size=1
         0: aload_0
         1: invokespecial #1                  // Method org/kohsuke/github/GHRepositoryTraffic."<init>":()V
         4: return
      LineNumberTable:
        line 14: 0
        line 15: 4
      LocalVariableTable:
        Start  Length  Slot  Name   Signature
            0       5     0  this   Lorg/kohsuke/github/GHRepositoryViewTraffic;

  org.kohsuke.github.GHRepositoryViewTraffic(int, int, java.util.List<org.kohsuke.github.GHRepositoryViewTraffic$DailyInfo>);
    descriptor: (IILjava/util/List;)V
    flags: (0x0000)
    Code:
      stack=3, locals=4, args_size=4
         0: aload_0
         1: iload_1
         2: iload_2
         3: invokespecial #2                  // Method org/kohsuke/github/GHRepositoryTraffic."<init>":(II)V
         6: aload_0
         7: aload_3
         8: putfield      #3                  // Field views:Ljava/util/List;
        11: return
      LineNumberTable:
        line 18: 0
        line 19: 6
        line 20: 11
      LocalVariableTable:
        Start  Length  Slot  Name   Signature
            0      12     0  this   Lorg/kohsuke/github/GHRepositoryViewTraffic;
            0      12     1 count   I
            0      12     2 uniques   I
            0      12     3 views   Ljava/util/List;
      LocalVariableTypeTable:
        Start  Length  Slot  Name   Signature
            0      12     3 views   Ljava/util/List<Lorg/kohsuke/github/GHRepositoryViewTraffic$DailyInfo;>;
    Signature: #27                          // (IILjava/util/List<Lorg/kohsuke/github/GHRepositoryViewTraffic$DailyInfo;>;)V

  public java.util.List<org.kohsuke.github.GHRepositoryViewTraffic$DailyInfo> getViews();
    descriptor: ()Ljava/util/List;
    flags: (0x0001) ACC_PUBLIC
    Code:
      stack=1, locals=1, args_size=1
         0: aload_0
         1: getfield      #3                  // Field views:Ljava/util/List;
         4: invokestatic  #4                  // Method java/util/Collections.unmodifiableList:(Ljava/util/List;)Ljava/util/List;
         7: areturn
      LineNumberTable:
        line 28: 0
      LocalVariableTable:
        Start  Length  Slot  Name   Signature
            0       8     0  this   Lorg/kohsuke/github/GHRepositoryViewTraffic;
    Signature: #30                          // ()Ljava/util/List<Lorg/kohsuke/github/GHRepositoryViewTraffic$DailyInfo;>;

  public java.util.List<org.kohsuke.github.GHRepositoryViewTraffic$DailyInfo> getDailyInfo();
    descriptor: ()Ljava/util/List;
    flags: (0x0001) ACC_PUBLIC
    Code:
      stack=1, locals=1, args_size=1
         0: aload_0
         1: invokevirtual #5                  // Method getViews:()Ljava/util/List;
         4: areturn
      LineNumberTable:
        line 32: 0
      LocalVariableTable:
        Start  Length  Slot  Name   Signature
            0       5     0  this   Lorg/kohsuke/github/GHRepositoryViewTraffic;
    Signature: #30                          // ()Ljava/util/List<Lorg/kohsuke/github/GHRepositoryViewTraffic$DailyInfo;>;
}
SourceFile: "GHRepositoryViewTraffic.java"
InnerClasses:
  public static #9= #8 of #6;             // DailyInfo=class org/kohsuke/github/GHRepositoryViewTraffic$DailyInfo of class org/kohsuke/github/GHRepositoryViewTraffic
