Classfile /Users/mw/Projects/slang-braindump/.jar/jar11/assemble/slang-braindump/assemble/content/org/kohsuke/github/GHReaction.class
  Last modified May 29, 2022; size 2206 bytes
  SHA-256 checksum 6a913af7af5489e25d671ff5f4363baaad32c2d819567daf4b7674ff3a5a7f10
  Compiled from "GHReaction.java"
public class org.kohsuke.github.GHReaction extends org.kohsuke.github.GHObject
  minor version: 0
  major version: 52
  flags: (0x0021) ACC_PUBLIC, ACC_SUPER
  this_class: #21                         // org/kohsuke/github/GHReaction
  super_class: #22                        // org/kohsuke/github/GHObject
  interfaces: 0, fields: 2, methods: 5, attributes: 3
Constant pool:
    #1 = Methodref          #22.#57       // org/kohsuke/github/GHObject."<init>":()V
    #2 = Fieldref           #21.#58       // org/kohsuke/github/GHReaction.content:Lorg/kohsuke/github/ReactionContent;
    #3 = Fieldref           #21.#59       // org/kohsuke/github/GHReaction.user:Lorg/kohsuke/github/GHUser;
    #4 = Methodref          #21.#60       // org/kohsuke/github/GHReaction.root:()Lorg/kohsuke/github/GitHub;
    #5 = Methodref          #61.#62       // org/kohsuke/github/GitHub.createRequest:()Lorg/kohsuke/github/Requester;
    #6 = String             #63           // DELETE
    #7 = Methodref          #8.#64        // org/kohsuke/github/Requester.method:(Ljava/lang/String;)Lorg/kohsuke/github/GitHubRequest$Builder;
    #8 = Class              #65           // org/kohsuke/github/Requester
    #9 = Fieldref           #66.#67       // org/kohsuke/github/internal/Previews.SQUIRREL_GIRL:Lorg/kohsuke/github/internal/Previews;
   #10 = Methodref          #8.#68        // org/kohsuke/github/Requester.withPreview:(Lorg/kohsuke/github/internal/Previews;)Lorg/kohsuke/github/GitHubRequest$Builder;
   #11 = Class              #69           // java/lang/StringBuilder
   #12 = Methodref          #11.#57       // java/lang/StringBuilder."<init>":()V
   #13 = String             #70           // /reactions/
   #14 = Methodref          #11.#71       // java/lang/StringBuilder.append:(Ljava/lang/String;)Ljava/lang/StringBuilder;
   #15 = Methodref          #21.#72       // org/kohsuke/github/GHReaction.getId:()J
   #16 = Methodref          #11.#73       // java/lang/StringBuilder.append:(J)Ljava/lang/StringBuilder;
   #17 = Methodref          #11.#74       // java/lang/StringBuilder.toString:()Ljava/lang/String;
   #18 = Class              #75           // java/lang/String
   #19 = Methodref          #8.#76        // org/kohsuke/github/Requester.withUrlPath:(Ljava/lang/String;[Ljava/lang/String;)Lorg/kohsuke/github/GitHubRequest$Builder;
   #20 = Methodref          #8.#77        // org/kohsuke/github/Requester.send:()V
   #21 = Class              #78           // org/kohsuke/github/GHReaction
   #22 = Class              #79           // org/kohsuke/github/GHObject
   #23 = Utf8               user
   #24 = Utf8               Lorg/kohsuke/github/GHUser;
   #25 = Utf8               content
   #26 = Utf8               Lorg/kohsuke/github/ReactionContent;
   #27 = Utf8               <init>
   #28 = Utf8               ()V
   #29 = Utf8               Code
   #30 = Utf8               LineNumberTable
   #31 = Utf8               LocalVariableTable
   #32 = Utf8               this
   #33 = Utf8               Lorg/kohsuke/github/GHReaction;
   #34 = Utf8               getContent
   #35 = Utf8               ()Lorg/kohsuke/github/ReactionContent;
   #36 = Utf8               getUser
   #37 = Utf8               ()Lorg/kohsuke/github/GHUser;
   #38 = Utf8               RuntimeInvisibleAnnotations
   #39 = Utf8               Ledu/umd/cs/findbugs/annotations/SuppressFBWarnings;
   #40 = Utf8               value
   #41 = Utf8               EI_EXPOSE_REP
   #42 = Utf8               justification
   #43 = Utf8               Expected behavior
   #44 = Utf8               getHtmlUrl
   #45 = Utf8               ()Ljava/net/URL;
   #46 = Utf8               Deprecated
   #47 = Utf8               RuntimeVisibleAnnotations
   #48 = Utf8               Ljava/lang/Deprecated;
   #49 = Utf8               delete
   #50 = Utf8               Exceptions
   #51 = Class              #80           // java/io/IOException
   #52 = Utf8               SourceFile
   #53 = Utf8               GHReaction.java
   #54 = Utf8               Lorg/kohsuke/github/Preview;
   #55 = Utf8               Lorg/kohsuke/github/internal/Previews;
   #56 = Utf8               SQUIRREL_GIRL
   #57 = NameAndType        #27:#28       // "<init>":()V
   #58 = NameAndType        #25:#26       // content:Lorg/kohsuke/github/ReactionContent;
   #59 = NameAndType        #23:#24       // user:Lorg/kohsuke/github/GHUser;
   #60 = NameAndType        #81:#82       // root:()Lorg/kohsuke/github/GitHub;
   #61 = Class              #83           // org/kohsuke/github/GitHub
   #62 = NameAndType        #84:#85       // createRequest:()Lorg/kohsuke/github/Requester;
   #63 = Utf8               DELETE
   #64 = NameAndType        #86:#90       // method:(Ljava/lang/String;)Lorg/kohsuke/github/GitHubRequest$Builder;
   #65 = Utf8               org/kohsuke/github/Requester
   #66 = Class              #91           // org/kohsuke/github/internal/Previews
   #67 = NameAndType        #56:#55       // SQUIRREL_GIRL:Lorg/kohsuke/github/internal/Previews;
   #68 = NameAndType        #92:#93       // withPreview:(Lorg/kohsuke/github/internal/Previews;)Lorg/kohsuke/github/GitHubRequest$Builder;
   #69 = Utf8               java/lang/StringBuilder
   #70 = Utf8               /reactions/
   #71 = NameAndType        #94:#95       // append:(Ljava/lang/String;)Ljava/lang/StringBuilder;
   #72 = NameAndType        #96:#97       // getId:()J
   #73 = NameAndType        #94:#98       // append:(J)Ljava/lang/StringBuilder;
   #74 = NameAndType        #99:#100      // toString:()Ljava/lang/String;
   #75 = Utf8               java/lang/String
   #76 = NameAndType        #101:#102     // withUrlPath:(Ljava/lang/String;[Ljava/lang/String;)Lorg/kohsuke/github/GitHubRequest$Builder;
   #77 = NameAndType        #103:#28      // send:()V
   #78 = Utf8               org/kohsuke/github/GHReaction
   #79 = Utf8               org/kohsuke/github/GHObject
   #80 = Utf8               java/io/IOException
   #81 = Utf8               root
   #82 = Utf8               ()Lorg/kohsuke/github/GitHub;
   #83 = Utf8               org/kohsuke/github/GitHub
   #84 = Utf8               createRequest
   #85 = Utf8               ()Lorg/kohsuke/github/Requester;
   #86 = Utf8               method
   #87 = Class              #105          // org/kohsuke/github/GitHubRequest$Builder
   #88 = Utf8               Builder
   #89 = Utf8               InnerClasses
   #90 = Utf8               (Ljava/lang/String;)Lorg/kohsuke/github/GitHubRequest$Builder;
   #91 = Utf8               org/kohsuke/github/internal/Previews
   #92 = Utf8               withPreview
   #93 = Utf8               (Lorg/kohsuke/github/internal/Previews;)Lorg/kohsuke/github/GitHubRequest$Builder;
   #94 = Utf8               append
   #95 = Utf8               (Ljava/lang/String;)Ljava/lang/StringBuilder;
   #96 = Utf8               getId
   #97 = Utf8               ()J
   #98 = Utf8               (J)Ljava/lang/StringBuilder;
   #99 = Utf8               toString
  #100 = Utf8               ()Ljava/lang/String;
  #101 = Utf8               withUrlPath
  #102 = Utf8               (Ljava/lang/String;[Ljava/lang/String;)Lorg/kohsuke/github/GitHubRequest$Builder;
  #103 = Utf8               send
  #104 = Class              #106          // org/kohsuke/github/GitHubRequest
  #105 = Utf8               org/kohsuke/github/GitHubRequest$Builder
  #106 = Utf8               org/kohsuke/github/GitHubRequest
{
  private org.kohsuke.github.GHUser user;
    descriptor: Lorg/kohsuke/github/GHUser;
    flags: (0x0002) ACC_PRIVATE

  private org.kohsuke.github.ReactionContent content;
    descriptor: Lorg/kohsuke/github/ReactionContent;
    flags: (0x0002) ACC_PRIVATE

  public org.kohsuke.github.GHReaction();
    descriptor: ()V
    flags: (0x0001) ACC_PUBLIC
    Code:
      stack=1, locals=1, args_size=1
         0: aload_0
         1: invokespecial #1                  // Method org/kohsuke/github/GHObject."<init>":()V
         4: return
      LineNumberTable:
        line 17: 0
      LocalVariableTable:
        Start  Length  Slot  Name   Signature
            0       5     0  this   Lorg/kohsuke/github/GHReaction;

  public org.kohsuke.github.ReactionContent getContent();
    descriptor: ()Lorg/kohsuke/github/ReactionContent;
    flags: (0x0001) ACC_PUBLIC
    Code:
      stack=1, locals=1, args_size=1
         0: aload_0
         1: getfield      #2                  // Field content:Lorg/kohsuke/github/ReactionContent;
         4: areturn
      LineNumberTable:
        line 28: 0
      LocalVariableTable:
        Start  Length  Slot  Name   Signature
            0       5     0  this   Lorg/kohsuke/github/GHReaction;

  public org.kohsuke.github.GHUser getUser();
    descriptor: ()Lorg/kohsuke/github/GHUser;
    flags: (0x0001) ACC_PUBLIC
    Code:
      stack=1, locals=1, args_size=1
         0: aload_0
         1: getfield      #3                  // Field user:Lorg/kohsuke/github/GHUser;
         4: areturn
      LineNumberTable:
        line 38: 0
      LocalVariableTable:
        Start  Length  Slot  Name   Signature
            0       5     0  this   Lorg/kohsuke/github/GHReaction;
    RuntimeInvisibleAnnotations:
      0: #39(#40=[s#41],#42=s#43)
        edu.umd.cs.findbugs.annotations.SuppressFBWarnings(
          value=["EI_EXPOSE_REP"]
          justification="Expected behavior"
        )

  public java.net.URL getHtmlUrl();
    descriptor: ()Ljava/net/URL;
    flags: (0x0001) ACC_PUBLIC
    Code:
      stack=1, locals=1, args_size=1
         0: aconst_null
         1: areturn
      LineNumberTable:
        line 46: 0
      LocalVariableTable:
        Start  Length  Slot  Name   Signature
            0       2     0  this   Lorg/kohsuke/github/GHReaction;
    Deprecated: true
    RuntimeVisibleAnnotations:
      0: #48()
        java.lang.Deprecated

  public void delete() throws java.io.IOException;
    descriptor: ()V
    flags: (0x0001) ACC_PUBLIC
    Code:
      stack=4, locals=1, args_size=1
         0: aload_0
         1: invokevirtual #4                  // Method root:()Lorg/kohsuke/github/GitHub;
         4: invokevirtual #5                  // Method org/kohsuke/github/GitHub.createRequest:()Lorg/kohsuke/github/Requester;
         7: ldc           #6                  // String DELETE
         9: invokevirtual #7                  // Method org/kohsuke/github/Requester.method:(Ljava/lang/String;)Lorg/kohsuke/github/GitHubRequest$Builder;
        12: checkcast     #8                  // class org/kohsuke/github/Requester
        15: getstatic     #9                  // Field org/kohsuke/github/internal/Previews.SQUIRREL_GIRL:Lorg/kohsuke/github/internal/Previews;
        18: invokevirtual #10                 // Method org/kohsuke/github/Requester.withPreview:(Lorg/kohsuke/github/internal/Previews;)Lorg/kohsuke/github/GitHubRequest$Builder;
        21: checkcast     #8                  // class org/kohsuke/github/Requester
        24: new           #11                 // class java/lang/StringBuilder
        27: dup
        28: invokespecial #12                 // Method java/lang/StringBuilder."<init>":()V
        31: ldc           #13                 // String /reactions/
        33: invokevirtual #14                 // Method java/lang/StringBuilder.append:(Ljava/lang/String;)Ljava/lang/StringBuilder;
        36: aload_0
        37: invokevirtual #15                 // Method getId:()J
        40: invokevirtual #16                 // Method java/lang/StringBuilder.append:(J)Ljava/lang/StringBuilder;
        43: invokevirtual #17                 // Method java/lang/StringBuilder.toString:()Ljava/lang/String;
        46: iconst_0
        47: anewarray     #18                 // class java/lang/String
        50: invokevirtual #19                 // Method org/kohsuke/github/Requester.withUrlPath:(Ljava/lang/String;[Ljava/lang/String;)Lorg/kohsuke/github/GitHubRequest$Builder;
        53: checkcast     #8                  // class org/kohsuke/github/Requester
        56: invokevirtual #20                 // Method org/kohsuke/github/Requester.send:()V
        59: return
      LineNumberTable:
        line 56: 0
        line 57: 59
      LocalVariableTable:
        Start  Length  Slot  Name   Signature
            0      60     0  this   Lorg/kohsuke/github/GHReaction;
    Exceptions:
      throws java.io.IOException
}
SourceFile: "GHReaction.java"
RuntimeVisibleAnnotations:
  0: #54(#40=[e#55.#56])
    org.kohsuke.github.Preview(
      value=[Lorg/kohsuke/github/internal/Previews;.SQUIRREL_GIRL]
    )
InnerClasses:
  static #88= #87 of #104;                // Builder=class org/kohsuke/github/GitHubRequest$Builder of class org/kohsuke/github/GitHubRequest
