Classfile /Users/mw/Projects/slang-braindump/.jar/jar11/assemble/slang-braindump/assemble/content/org/kohsuke/github/GHReleaseBuilder.class
  Last modified May 29, 2022; size 2702 bytes
  SHA-256 checksum 075def95e27d07bc03e002ce97cf6ec3bb070452316fa6a80dfdf1f7f0670547
  Compiled from "GHReleaseBuilder.java"
public class org.kohsuke.github.GHReleaseBuilder
  minor version: 0
  major version: 52
  flags: (0x0021) ACC_PUBLIC, ACC_SUPER
  this_class: #25                         // org/kohsuke/github/GHReleaseBuilder
  super_class: #26                        // java/lang/Object
  interfaces: 0, fields: 2, methods: 8, attributes: 2
Constant pool:
    #1 = Methodref          #26.#62       // java/lang/Object."<init>":()V
    #2 = Fieldref           #25.#63       // org/kohsuke/github/GHReleaseBuilder.repo:Lorg/kohsuke/github/GHRepository;
    #3 = Methodref          #64.#65       // org/kohsuke/github/GHRepository.root:()Lorg/kohsuke/github/GitHub;
    #4 = Methodref          #66.#67       // org/kohsuke/github/GitHub.createRequest:()Lorg/kohsuke/github/Requester;
    #5 = String             #68           // POST
    #6 = Methodref          #7.#69        // org/kohsuke/github/Requester.method:(Ljava/lang/String;)Lorg/kohsuke/github/GitHubRequest$Builder;
    #7 = Class              #70           // org/kohsuke/github/Requester
    #8 = Fieldref           #25.#71       // org/kohsuke/github/GHReleaseBuilder.builder:Lorg/kohsuke/github/Requester;
    #9 = String             #72           // tag_name
   #10 = Methodref          #7.#73        // org/kohsuke/github/Requester.with:(Ljava/lang/String;Ljava/lang/String;)Lorg/kohsuke/github/GitHubRequest$Builder;
   #11 = String             #47           // body
   #12 = String             #74           // target_commitish
   #13 = String             #50           // draft
   #14 = Methodref          #7.#75        // org/kohsuke/github/Requester.with:(Ljava/lang/String;Z)Lorg/kohsuke/github/GitHubRequest$Builder;
   #15 = String             #53           // name
   #16 = String             #54           // prerelease
   #17 = String             #76           // discussion_category_name
   #18 = String             #77           // releases
   #19 = Methodref          #64.#78       // org/kohsuke/github/GHRepository.getApiTailUrl:(Ljava/lang/String;)Ljava/lang/String;
   #20 = Class              #79           // java/lang/String
   #21 = Methodref          #7.#80        // org/kohsuke/github/Requester.withUrlPath:(Ljava/lang/String;[Ljava/lang/String;)Lorg/kohsuke/github/GitHubRequest$Builder;
   #22 = Class              #81           // org/kohsuke/github/GHRelease
   #23 = Methodref          #7.#82        // org/kohsuke/github/Requester.fetch:(Ljava/lang/Class;)Ljava/lang/Object;
   #24 = Methodref          #22.#83       // org/kohsuke/github/GHRelease.wrap:(Lorg/kohsuke/github/GHRepository;)Lorg/kohsuke/github/GHRelease;
   #25 = Class              #84           // org/kohsuke/github/GHReleaseBuilder
   #26 = Class              #85           // java/lang/Object
   #27 = Utf8               repo
   #28 = Utf8               Lorg/kohsuke/github/GHRepository;
   #29 = Utf8               builder
   #30 = Utf8               Lorg/kohsuke/github/Requester;
   #31 = Utf8               <init>
   #32 = Utf8               (Lorg/kohsuke/github/GHRepository;Ljava/lang/String;)V
   #33 = Utf8               Code
   #34 = Utf8               LineNumberTable
   #35 = Utf8               LocalVariableTable
   #36 = Utf8               this
   #37 = Utf8               Lorg/kohsuke/github/GHReleaseBuilder;
   #38 = Utf8               ghRepository
   #39 = Utf8               tag
   #40 = Utf8               Ljava/lang/String;
   #41 = Utf8               RuntimeInvisibleAnnotations
   #42 = Utf8               Ledu/umd/cs/findbugs/annotations/SuppressFBWarnings;
   #43 = Utf8               value
   #44 = Utf8               EI_EXPOSE_REP2
   #45 = Utf8               justification
   #46 = Utf8               Acceptable risk
   #47 = Utf8               body
   #48 = Utf8               (Ljava/lang/String;)Lorg/kohsuke/github/GHReleaseBuilder;
   #49 = Utf8               commitish
   #50 = Utf8               draft
   #51 = Utf8               (Z)Lorg/kohsuke/github/GHReleaseBuilder;
   #52 = Utf8               Z
   #53 = Utf8               name
   #54 = Utf8               prerelease
   #55 = Utf8               categoryName
   #56 = Utf8               create
   #57 = Utf8               ()Lorg/kohsuke/github/GHRelease;
   #58 = Utf8               Exceptions
   #59 = Class              #86           // java/io/IOException
   #60 = Utf8               SourceFile
   #61 = Utf8               GHReleaseBuilder.java
   #62 = NameAndType        #31:#87       // "<init>":()V
   #63 = NameAndType        #27:#28       // repo:Lorg/kohsuke/github/GHRepository;
   #64 = Class              #88           // org/kohsuke/github/GHRepository
   #65 = NameAndType        #89:#90       // root:()Lorg/kohsuke/github/GitHub;
   #66 = Class              #91           // org/kohsuke/github/GitHub
   #67 = NameAndType        #92:#93       // createRequest:()Lorg/kohsuke/github/Requester;
   #68 = Utf8               POST
   #69 = NameAndType        #94:#98       // method:(Ljava/lang/String;)Lorg/kohsuke/github/GitHubRequest$Builder;
   #70 = Utf8               org/kohsuke/github/Requester
   #71 = NameAndType        #29:#30       // builder:Lorg/kohsuke/github/Requester;
   #72 = Utf8               tag_name
   #73 = NameAndType        #99:#100      // with:(Ljava/lang/String;Ljava/lang/String;)Lorg/kohsuke/github/GitHubRequest$Builder;
   #74 = Utf8               target_commitish
   #75 = NameAndType        #99:#101      // with:(Ljava/lang/String;Z)Lorg/kohsuke/github/GitHubRequest$Builder;
   #76 = Utf8               discussion_category_name
   #77 = Utf8               releases
   #78 = NameAndType        #102:#103     // getApiTailUrl:(Ljava/lang/String;)Ljava/lang/String;
   #79 = Utf8               java/lang/String
   #80 = NameAndType        #104:#105     // withUrlPath:(Ljava/lang/String;[Ljava/lang/String;)Lorg/kohsuke/github/GitHubRequest$Builder;
   #81 = Utf8               org/kohsuke/github/GHRelease
   #82 = NameAndType        #106:#107     // fetch:(Ljava/lang/Class;)Ljava/lang/Object;
   #83 = NameAndType        #108:#109     // wrap:(Lorg/kohsuke/github/GHRepository;)Lorg/kohsuke/github/GHRelease;
   #84 = Utf8               org/kohsuke/github/GHReleaseBuilder
   #85 = Utf8               java/lang/Object
   #86 = Utf8               java/io/IOException
   #87 = Utf8               ()V
   #88 = Utf8               org/kohsuke/github/GHRepository
   #89 = Utf8               root
   #90 = Utf8               ()Lorg/kohsuke/github/GitHub;
   #91 = Utf8               org/kohsuke/github/GitHub
   #92 = Utf8               createRequest
   #93 = Utf8               ()Lorg/kohsuke/github/Requester;
   #94 = Utf8               method
   #95 = Class              #111          // org/kohsuke/github/GitHubRequest$Builder
   #96 = Utf8               Builder
   #97 = Utf8               InnerClasses
   #98 = Utf8               (Ljava/lang/String;)Lorg/kohsuke/github/GitHubRequest$Builder;
   #99 = Utf8               with
  #100 = Utf8               (Ljava/lang/String;Ljava/lang/String;)Lorg/kohsuke/github/GitHubRequest$Builder;
  #101 = Utf8               (Ljava/lang/String;Z)Lorg/kohsuke/github/GitHubRequest$Builder;
  #102 = Utf8               getApiTailUrl
  #103 = Utf8               (Ljava/lang/String;)Ljava/lang/String;
  #104 = Utf8               withUrlPath
  #105 = Utf8               (Ljava/lang/String;[Ljava/lang/String;)Lorg/kohsuke/github/GitHubRequest$Builder;
  #106 = Utf8               fetch
  #107 = Utf8               (Ljava/lang/Class;)Ljava/lang/Object;
  #108 = Utf8               wrap
  #109 = Utf8               (Lorg/kohsuke/github/GHRepository;)Lorg/kohsuke/github/GHRelease;
  #110 = Class              #112          // org/kohsuke/github/GitHubRequest
  #111 = Utf8               org/kohsuke/github/GitHubRequest$Builder
  #112 = Utf8               org/kohsuke/github/GitHubRequest
{
  private final org.kohsuke.github.GHRepository repo;
    descriptor: Lorg/kohsuke/github/GHRepository;
    flags: (0x0012) ACC_PRIVATE, ACC_FINAL

  private final org.kohsuke.github.Requester builder;
    descriptor: Lorg/kohsuke/github/Requester;
    flags: (0x0012) ACC_PRIVATE, ACC_FINAL

  public org.kohsuke.github.GHReleaseBuilder(org.kohsuke.github.GHRepository, java.lang.String);
    descriptor: (Lorg/kohsuke/github/GHRepository;Ljava/lang/String;)V
    flags: (0x0001) ACC_PUBLIC
    Code:
      stack=3, locals=3, args_size=3
         0: aload_0
         1: invokespecial #1                  // Method java/lang/Object."<init>":()V
         4: aload_0
         5: aload_1
         6: putfield      #2                  // Field repo:Lorg/kohsuke/github/GHRepository;
         9: aload_0
        10: aload_0
        11: getfield      #2                  // Field repo:Lorg/kohsuke/github/GHRepository;
        14: invokevirtual #3                  // Method org/kohsuke/github/GHRepository.root:()Lorg/kohsuke/github/GitHub;
        17: invokevirtual #4                  // Method org/kohsuke/github/GitHub.createRequest:()Lorg/kohsuke/github/Requester;
        20: ldc           #5                  // String POST
        22: invokevirtual #6                  // Method org/kohsuke/github/Requester.method:(Ljava/lang/String;)Lorg/kohsuke/github/GitHubRequest$Builder;
        25: checkcast     #7                  // class org/kohsuke/github/Requester
        28: putfield      #8                  // Field builder:Lorg/kohsuke/github/Requester;
        31: aload_0
        32: getfield      #8                  // Field builder:Lorg/kohsuke/github/Requester;
        35: ldc           #9                  // String tag_name
        37: aload_2
        38: invokevirtual #10                 // Method org/kohsuke/github/Requester.with:(Ljava/lang/String;Ljava/lang/String;)Lorg/kohsuke/github/GitHubRequest$Builder;
        41: pop
        42: return
      LineNumberTable:
        line 25: 0
        line 26: 4
        line 27: 9
        line 28: 31
        line 29: 42
      LocalVariableTable:
        Start  Length  Slot  Name   Signature
            0      43     0  this   Lorg/kohsuke/github/GHReleaseBuilder;
            0      43     1 ghRepository   Lorg/kohsuke/github/GHRepository;
            0      43     2   tag   Ljava/lang/String;
    RuntimeInvisibleAnnotations:
      0: #42(#43=[s#44],#45=s#46)
        edu.umd.cs.findbugs.annotations.SuppressFBWarnings(
          value=["EI_EXPOSE_REP2"]
          justification="Acceptable risk"
        )

  public org.kohsuke.github.GHReleaseBuilder body(java.lang.String);
    descriptor: (Ljava/lang/String;)Lorg/kohsuke/github/GHReleaseBuilder;
    flags: (0x0001) ACC_PUBLIC
    Code:
      stack=3, locals=2, args_size=2
         0: aload_0
         1: getfield      #8                  // Field builder:Lorg/kohsuke/github/Requester;
         4: ldc           #11                 // String body
         6: aload_1
         7: invokevirtual #10                 // Method org/kohsuke/github/Requester.with:(Ljava/lang/String;Ljava/lang/String;)Lorg/kohsuke/github/GitHubRequest$Builder;
        10: pop
        11: aload_0
        12: areturn
      LineNumberTable:
        line 39: 0
        line 40: 11
      LocalVariableTable:
        Start  Length  Slot  Name   Signature
            0      13     0  this   Lorg/kohsuke/github/GHReleaseBuilder;
            0      13     1  body   Ljava/lang/String;

  public org.kohsuke.github.GHReleaseBuilder commitish(java.lang.String);
    descriptor: (Ljava/lang/String;)Lorg/kohsuke/github/GHReleaseBuilder;
    flags: (0x0001) ACC_PUBLIC
    Code:
      stack=3, locals=2, args_size=2
         0: aload_0
         1: getfield      #8                  // Field builder:Lorg/kohsuke/github/Requester;
         4: ldc           #12                 // String target_commitish
         6: aload_1
         7: invokevirtual #10                 // Method org/kohsuke/github/Requester.with:(Ljava/lang/String;Ljava/lang/String;)Lorg/kohsuke/github/GitHubRequest$Builder;
        10: pop
        11: aload_0
        12: areturn
      LineNumberTable:
        line 51: 0
        line 52: 11
      LocalVariableTable:
        Start  Length  Slot  Name   Signature
            0      13     0  this   Lorg/kohsuke/github/GHReleaseBuilder;
            0      13     1 commitish   Ljava/lang/String;

  public org.kohsuke.github.GHReleaseBuilder draft(boolean);
    descriptor: (Z)Lorg/kohsuke/github/GHReleaseBuilder;
    flags: (0x0001) ACC_PUBLIC
    Code:
      stack=3, locals=2, args_size=2
         0: aload_0
         1: getfield      #8                  // Field builder:Lorg/kohsuke/github/Requester;
         4: ldc           #13                 // String draft
         6: iload_1
         7: invokevirtual #14                 // Method org/kohsuke/github/Requester.with:(Ljava/lang/String;Z)Lorg/kohsuke/github/GitHubRequest$Builder;
        10: pop
        11: aload_0
        12: areturn
      LineNumberTable:
        line 64: 0
        line 65: 11
      LocalVariableTable:
        Start  Length  Slot  Name   Signature
            0      13     0  this   Lorg/kohsuke/github/GHReleaseBuilder;
            0      13     1 draft   Z

  public org.kohsuke.github.GHReleaseBuilder name(java.lang.String);
    descriptor: (Ljava/lang/String;)Lorg/kohsuke/github/GHReleaseBuilder;
    flags: (0x0001) ACC_PUBLIC
    Code:
      stack=3, locals=2, args_size=2
         0: aload_0
         1: getfield      #8                  // Field builder:Lorg/kohsuke/github/Requester;
         4: ldc           #15                 // String name
         6: aload_1
         7: invokevirtual #10                 // Method org/kohsuke/github/Requester.with:(Ljava/lang/String;Ljava/lang/String;)Lorg/kohsuke/github/GitHubRequest$Builder;
        10: pop
        11: aload_0
        12: areturn
      LineNumberTable:
        line 76: 0
        line 77: 11
      LocalVariableTable:
        Start  Length  Slot  Name   Signature
            0      13     0  this   Lorg/kohsuke/github/GHReleaseBuilder;
            0      13     1  name   Ljava/lang/String;

  public org.kohsuke.github.GHReleaseBuilder prerelease(boolean);
    descriptor: (Z)Lorg/kohsuke/github/GHReleaseBuilder;
    flags: (0x0001) ACC_PUBLIC
    Code:
      stack=3, locals=2, args_size=2
         0: aload_0
         1: getfield      #8                  // Field builder:Lorg/kohsuke/github/Requester;
         4: ldc           #16                 // String prerelease
         6: iload_1
         7: invokevirtual #14                 // Method org/kohsuke/github/Requester.with:(Ljava/lang/String;Z)Lorg/kohsuke/github/GitHubRequest$Builder;
        10: pop
        11: aload_0
        12: areturn
      LineNumberTable:
        line 89: 0
        line 90: 11
      LocalVariableTable:
        Start  Length  Slot  Name   Signature
            0      13     0  this   Lorg/kohsuke/github/GHReleaseBuilder;
            0      13     1 prerelease   Z

  public org.kohsuke.github.GHReleaseBuilder categoryName(java.lang.String);
    descriptor: (Ljava/lang/String;)Lorg/kohsuke/github/GHReleaseBuilder;
    flags: (0x0001) ACC_PUBLIC
    Code:
      stack=3, locals=2, args_size=2
         0: aload_0
         1: getfield      #8                  // Field builder:Lorg/kohsuke/github/Requester;
         4: ldc           #17                 // String discussion_category_name
         6: aload_1
         7: invokevirtual #10                 // Method org/kohsuke/github/Requester.with:(Ljava/lang/String;Ljava/lang/String;)Lorg/kohsuke/github/GitHubRequest$Builder;
        10: pop
        11: aload_0
        12: areturn
      LineNumberTable:
        line 101: 0
        line 102: 11
      LocalVariableTable:
        Start  Length  Slot  Name   Signature
            0      13     0  this   Lorg/kohsuke/github/GHReleaseBuilder;
            0      13     1 categoryName   Ljava/lang/String;

  public org.kohsuke.github.GHRelease create() throws java.io.IOException;
    descriptor: ()Lorg/kohsuke/github/GHRelease;
    flags: (0x0001) ACC_PUBLIC
    Code:
      stack=3, locals=1, args_size=1
         0: aload_0
         1: getfield      #8                  // Field builder:Lorg/kohsuke/github/Requester;
         4: aload_0
         5: getfield      #2                  // Field repo:Lorg/kohsuke/github/GHRepository;
         8: ldc           #18                 // String releases
        10: invokevirtual #19                 // Method org/kohsuke/github/GHRepository.getApiTailUrl:(Ljava/lang/String;)Ljava/lang/String;
        13: iconst_0
        14: anewarray     #20                 // class java/lang/String
        17: invokevirtual #21                 // Method org/kohsuke/github/Requester.withUrlPath:(Ljava/lang/String;[Ljava/lang/String;)Lorg/kohsuke/github/GitHubRequest$Builder;
        20: checkcast     #7                  // class org/kohsuke/github/Requester
        23: ldc           #22                 // class org/kohsuke/github/GHRelease
        25: invokevirtual #23                 // Method org/kohsuke/github/Requester.fetch:(Ljava/lang/Class;)Ljava/lang/Object;
        28: checkcast     #22                 // class org/kohsuke/github/GHRelease
        31: aload_0
        32: getfield      #2                  // Field repo:Lorg/kohsuke/github/GHRepository;
        35: invokevirtual #24                 // Method org/kohsuke/github/GHRelease.wrap:(Lorg/kohsuke/github/GHRepository;)Lorg/kohsuke/github/GHRelease;
        38: areturn
      LineNumberTable:
        line 113: 0
      LocalVariableTable:
        Start  Length  Slot  Name   Signature
            0      39     0  this   Lorg/kohsuke/github/GHReleaseBuilder;
    Exceptions:
      throws java.io.IOException
}
SourceFile: "GHReleaseBuilder.java"
InnerClasses:
  static #96= #95 of #110;                // Builder=class org/kohsuke/github/GitHubRequest$Builder of class org/kohsuke/github/GitHubRequest
