Classfile /Users/mw/Projects/slang-braindump/.jar/jar11/assemble/slang-braindump/assemble/content/org/kohsuke/github/GHStargazer.class
  Last modified May 29, 2022; size 1287 bytes
  SHA-256 checksum 8e54cd168d015354038178f8235682727771d0abff0ea00124f06f56a597569c
  Compiled from "GHStargazer.java"
public class org.kohsuke.github.GHStargazer
  minor version: 0
  major version: 52
  flags: (0x0021) ACC_PUBLIC, ACC_SUPER
  this_class: #6                          // org/kohsuke/github/GHStargazer
  super_class: #7                         // java/lang/Object
  interfaces: 0, fields: 3, methods: 5, attributes: 2
Constant pool:
   #1 = Methodref          #7.#40         // java/lang/Object."<init>":()V
   #2 = Fieldref           #6.#41         // org/kohsuke/github/GHStargazer.repository:Lorg/kohsuke/github/GHRepository;
   #3 = Fieldref           #6.#42         // org/kohsuke/github/GHStargazer.starred_at:Ljava/lang/String;
   #4 = Methodref          #43.#44        // org/kohsuke/github/GitHubClient.parseDate:(Ljava/lang/String;)Ljava/util/Date;
   #5 = Fieldref           #6.#45         // org/kohsuke/github/GHStargazer.user:Lorg/kohsuke/github/GHUser;
   #6 = Class              #46            // org/kohsuke/github/GHStargazer
   #7 = Class              #47            // java/lang/Object
   #8 = Utf8               repository
   #9 = Utf8               Lorg/kohsuke/github/GHRepository;
  #10 = Utf8               starred_at
  #11 = Utf8               Ljava/lang/String;
  #12 = Utf8               user
  #13 = Utf8               Lorg/kohsuke/github/GHUser;
  #14 = Utf8               <init>
  #15 = Utf8               ()V
  #16 = Utf8               Code
  #17 = Utf8               LineNumberTable
  #18 = Utf8               LocalVariableTable
  #19 = Utf8               this
  #20 = Utf8               Lorg/kohsuke/github/GHStargazer;
  #21 = Utf8               getRepository
  #22 = Utf8               ()Lorg/kohsuke/github/GHRepository;
  #23 = Utf8               RuntimeInvisibleAnnotations
  #24 = Utf8               Ledu/umd/cs/findbugs/annotations/SuppressFBWarnings;
  #25 = Utf8               value
  #26 = Utf8               EI_EXPOSE_REP
  #27 = Utf8               justification
  #28 = Utf8               Expected behavior
  #29 = Utf8               getStarredAt
  #30 = Utf8               ()Ljava/util/Date;
  #31 = Utf8               getUser
  #32 = Utf8               ()Lorg/kohsuke/github/GHUser;
  #33 = Utf8               wrapUp
  #34 = Utf8               (Lorg/kohsuke/github/GHRepository;)V
  #35 = Utf8               SourceFile
  #36 = Utf8               GHStargazer.java
  #37 = Utf8               UWF_UNWRITTEN_FIELD
  #38 = Utf8               NP_UNWRITTEN_FIELD
  #39 = Utf8               JSON API
  #40 = NameAndType        #14:#15        // "<init>":()V
  #41 = NameAndType        #8:#9          // repository:Lorg/kohsuke/github/GHRepository;
  #42 = NameAndType        #10:#11        // starred_at:Ljava/lang/String;
  #43 = Class              #48            // org/kohsuke/github/GitHubClient
  #44 = NameAndType        #49:#50        // parseDate:(Ljava/lang/String;)Ljava/util/Date;
  #45 = NameAndType        #12:#13        // user:Lorg/kohsuke/github/GHUser;
  #46 = Utf8               org/kohsuke/github/GHStargazer
  #47 = Utf8               java/lang/Object
  #48 = Utf8               org/kohsuke/github/GitHubClient
  #49 = Utf8               parseDate
  #50 = Utf8               (Ljava/lang/String;)Ljava/util/Date;
{
  private org.kohsuke.github.GHRepository repository;
    descriptor: Lorg/kohsuke/github/GHRepository;
    flags: (0x0002) ACC_PRIVATE

  private java.lang.String starred_at;
    descriptor: Ljava/lang/String;
    flags: (0x0002) ACC_PRIVATE

  private org.kohsuke.github.GHUser user;
    descriptor: Lorg/kohsuke/github/GHUser;
    flags: (0x0002) ACC_PRIVATE

  public org.kohsuke.github.GHStargazer();
    descriptor: ()V
    flags: (0x0001) ACC_PUBLIC
    Code:
      stack=1, locals=1, args_size=1
         0: aload_0
         1: invokespecial #1                  // Method java/lang/Object."<init>":()V
         4: return
      LineNumberTable:
        line 13: 0
      LocalVariableTable:
        Start  Length  Slot  Name   Signature
            0       5     0  this   Lorg/kohsuke/github/GHStargazer;

  public org.kohsuke.github.GHRepository getRepository();
    descriptor: ()Lorg/kohsuke/github/GHRepository;
    flags: (0x0001) ACC_PUBLIC
    Code:
      stack=1, locals=1, args_size=1
         0: aload_0
         1: getfield      #2                  // Field repository:Lorg/kohsuke/github/GHRepository;
         4: areturn
      LineNumberTable:
        line 26: 0
      LocalVariableTable:
        Start  Length  Slot  Name   Signature
            0       5     0  this   Lorg/kohsuke/github/GHStargazer;
    RuntimeInvisibleAnnotations:
      0: #24(#25=[s#26],#27=s#28)
        edu.umd.cs.findbugs.annotations.SuppressFBWarnings(
          value=["EI_EXPOSE_REP"]
          justification="Expected behavior"
        )

  public java.util.Date getStarredAt();
    descriptor: ()Ljava/util/Date;
    flags: (0x0001) ACC_PUBLIC
    Code:
      stack=1, locals=1, args_size=1
         0: aload_0
         1: getfield      #3                  // Field starred_at:Ljava/lang/String;
         4: invokestatic  #4                  // Method org/kohsuke/github/GitHubClient.parseDate:(Ljava/lang/String;)Ljava/util/Date;
         7: areturn
      LineNumberTable:
        line 36: 0
      LocalVariableTable:
        Start  Length  Slot  Name   Signature
            0       8     0  this   Lorg/kohsuke/github/GHStargazer;

  public org.kohsuke.github.GHUser getUser();
    descriptor: ()Lorg/kohsuke/github/GHUser;
    flags: (0x0001) ACC_PUBLIC
    Code:
      stack=1, locals=1, args_size=1
         0: aload_0
         1: getfield      #5                  // Field user:Lorg/kohsuke/github/GHUser;
         4: areturn
      LineNumberTable:
        line 46: 0
      LocalVariableTable:
        Start  Length  Slot  Name   Signature
            0       5     0  this   Lorg/kohsuke/github/GHStargazer;
    RuntimeInvisibleAnnotations:
      0: #24(#25=[s#26],#27=s#28)
        edu.umd.cs.findbugs.annotations.SuppressFBWarnings(
          value=["EI_EXPOSE_REP"]
          justification="Expected behavior"
        )

  void wrapUp(org.kohsuke.github.GHRepository);
    descriptor: (Lorg/kohsuke/github/GHRepository;)V
    flags: (0x0000)
    Code:
      stack=2, locals=2, args_size=2
         0: aload_0
         1: aload_1
         2: putfield      #2                  // Field repository:Lorg/kohsuke/github/GHRepository;
         5: return
      LineNumberTable:
        line 50: 0
        line 51: 5
      LocalVariableTable:
        Start  Length  Slot  Name   Signature
            0       6     0  this   Lorg/kohsuke/github/GHStargazer;
            0       6     1 repository   Lorg/kohsuke/github/GHRepository;
}
SourceFile: "GHStargazer.java"
RuntimeInvisibleAnnotations:
  0: #24(#25=[s#37,s#38],#27=s#39)
    edu.umd.cs.findbugs.annotations.SuppressFBWarnings(
      value=["UWF_UNWRITTEN_FIELD","NP_UNWRITTEN_FIELD"]
      justification="JSON API"
    )
