Classfile /Users/mw/Projects/slang-braindump/.jar/jar11/assemble/slang-braindump/assemble/content/org/kohsuke/github/GHVerifiedKey.class
  Last modified May 29, 2022; size 757 bytes
  SHA-256 checksum c394e5d5c10e102a57992708fccf741354d0e7cb29bcbbfc718cf3f5debfcda2
  Compiled from "GHVerifiedKey.java"
public class org.kohsuke.github.GHVerifiedKey extends org.kohsuke.github.GHKey
  minor version: 0
  major version: 52
  flags: (0x0021) ACC_PUBLIC, ACC_SUPER
  this_class: #11                         // org/kohsuke/github/GHVerifiedKey
  super_class: #12                        // org/kohsuke/github/GHKey
  interfaces: 0, fields: 0, methods: 2, attributes: 1
Constant pool:
   #1 = Methodref          #12.#26        // org/kohsuke/github/GHKey."<init>":()V
   #2 = Fieldref           #11.#27        // org/kohsuke/github/GHVerifiedKey.verified:Z
   #3 = Fieldref           #11.#28        // org/kohsuke/github/GHVerifiedKey.title:Ljava/lang/String;
   #4 = Class              #29            // java/lang/StringBuilder
   #5 = Methodref          #4.#26         // java/lang/StringBuilder."<init>":()V
   #6 = String             #30            // key-
   #7 = Methodref          #4.#31         // java/lang/StringBuilder.append:(Ljava/lang/String;)Ljava/lang/StringBuilder;
   #8 = Fieldref           #11.#32        // org/kohsuke/github/GHVerifiedKey.id:I
   #9 = Methodref          #4.#33         // java/lang/StringBuilder.append:(I)Ljava/lang/StringBuilder;
  #10 = Methodref          #4.#34         // java/lang/StringBuilder.toString:()Ljava/lang/String;
  #11 = Class              #35            // org/kohsuke/github/GHVerifiedKey
  #12 = Class              #36            // org/kohsuke/github/GHKey
  #13 = Utf8               <init>
  #14 = Utf8               ()V
  #15 = Utf8               Code
  #16 = Utf8               LineNumberTable
  #17 = Utf8               LocalVariableTable
  #18 = Utf8               this
  #19 = Utf8               Lorg/kohsuke/github/GHVerifiedKey;
  #20 = Utf8               getTitle
  #21 = Utf8               ()Ljava/lang/String;
  #22 = Utf8               StackMapTable
  #23 = Class              #37            // java/lang/String
  #24 = Utf8               SourceFile
  #25 = Utf8               GHVerifiedKey.java
  #26 = NameAndType        #13:#14        // "<init>":()V
  #27 = NameAndType        #38:#39        // verified:Z
  #28 = NameAndType        #40:#41        // title:Ljava/lang/String;
  #29 = Utf8               java/lang/StringBuilder
  #30 = Utf8               key-
  #31 = NameAndType        #42:#43        // append:(Ljava/lang/String;)Ljava/lang/StringBuilder;
  #32 = NameAndType        #44:#45        // id:I
  #33 = NameAndType        #42:#46        // append:(I)Ljava/lang/StringBuilder;
  #34 = NameAndType        #47:#21        // toString:()Ljava/lang/String;
  #35 = Utf8               org/kohsuke/github/GHVerifiedKey
  #36 = Utf8               org/kohsuke/github/GHKey
  #37 = Utf8               java/lang/String
  #38 = Utf8               verified
  #39 = Utf8               Z
  #40 = Utf8               title
  #41 = Utf8               Ljava/lang/String;
  #42 = Utf8               append
  #43 = Utf8               (Ljava/lang/String;)Ljava/lang/StringBuilder;
  #44 = Utf8               id
  #45 = Utf8               I
  #46 = Utf8               (I)Ljava/lang/StringBuilder;
  #47 = Utf8               toString
{
  public org.kohsuke.github.GHVerifiedKey();
    descriptor: ()V
    flags: (0x0001) ACC_PUBLIC
    Code:
      stack=2, locals=1, args_size=1
         0: aload_0
         1: invokespecial #1                  // Method org/kohsuke/github/GHKey."<init>":()V
         4: aload_0
         5: iconst_1
         6: putfield      #2                  // Field verified:Z
         9: return
      LineNumberTable:
        line 11: 0
        line 12: 4
        line 13: 9
      LocalVariableTable:
        Start  Length  Slot  Name   Signature
            0      10     0  this   Lorg/kohsuke/github/GHVerifiedKey;

  public java.lang.String getTitle();
    descriptor: ()Ljava/lang/String;
    flags: (0x0001) ACC_PUBLIC
    Code:
      stack=2, locals=1, args_size=1
         0: aload_0
         1: getfield      #3                  // Field title:Ljava/lang/String;
         4: ifnonnull     32
         7: new           #4                  // class java/lang/StringBuilder
        10: dup
        11: invokespecial #5                  // Method java/lang/StringBuilder."<init>":()V
        14: ldc           #6                  // String key-
        16: invokevirtual #7                  // Method java/lang/StringBuilder.append:(Ljava/lang/String;)Ljava/lang/StringBuilder;
        19: aload_0
        20: getfield      #8                  // Field id:I
        23: invokevirtual #9                  // Method java/lang/StringBuilder.append:(I)Ljava/lang/StringBuilder;
        26: invokevirtual #10                 // Method java/lang/StringBuilder.toString:()Ljava/lang/String;
        29: goto          36
        32: aload_0
        33: getfield      #3                  // Field title:Ljava/lang/String;
        36: areturn
      LineNumberTable:
        line 17: 0
      LocalVariableTable:
        Start  Length  Slot  Name   Signature
            0      37     0  this   Lorg/kohsuke/github/GHVerifiedKey;
      StackMapTable: number_of_entries = 2
        frame_type = 32 /* same */
        frame_type = 67 /* same_locals_1_stack_item */
          stack = [ class java/lang/String ]
}
SourceFile: "GHVerifiedKey.java"
