Classfile /Users/mw/Projects/slang-braindump/.jar/jar11/assemble/slang-braindump/assemble/content/org/kohsuke/github/GHWorkflowJob$Step.class
  Last modified May 29, 2022; size 1618 bytes
  SHA-256 checksum e5b539db7e97905fee21f98f60df0d2b98b285181829542935099d65fbc64d8d
  Compiled from "GHWorkflowJob.java"
public class org.kohsuke.github.GHWorkflowJob$Step
  minor version: 0
  major version: 52
  flags: (0x0021) ACC_PUBLIC, ACC_SUPER
  this_class: #11                         // org/kohsuke/github/GHWorkflowJob$Step
  super_class: #12                        // java/lang/Object
  interfaces: 0, fields: 6, methods: 7, attributes: 2
Constant pool:
   #1 = Methodref          #12.#47        // java/lang/Object."<init>":()V
   #2 = Fieldref           #11.#48        // org/kohsuke/github/GHWorkflowJob$Step.name:Ljava/lang/String;
   #3 = Fieldref           #11.#49        // org/kohsuke/github/GHWorkflowJob$Step.number:I
   #4 = Fieldref           #11.#50        // org/kohsuke/github/GHWorkflowJob$Step.startedAt:Ljava/lang/String;
   #5 = Methodref          #51.#52        // org/kohsuke/github/GitHubClient.parseDate:(Ljava/lang/String;)Ljava/util/Date;
   #6 = Fieldref           #11.#53        // org/kohsuke/github/GHWorkflowJob$Step.completedAt:Ljava/lang/String;
   #7 = Fieldref           #11.#54        // org/kohsuke/github/GHWorkflowJob$Step.status:Ljava/lang/String;
   #8 = Methodref          #38.#55        // org/kohsuke/github/GHWorkflowRun$Status.from:(Ljava/lang/String;)Lorg/kohsuke/github/GHWorkflowRun$Status;
   #9 = Fieldref           #11.#56        // org/kohsuke/github/GHWorkflowJob$Step.conclusion:Ljava/lang/String;
  #10 = Methodref          #42.#57        // org/kohsuke/github/GHWorkflowRun$Conclusion.from:(Ljava/lang/String;)Lorg/kohsuke/github/GHWorkflowRun$Conclusion;
  #11 = Class              #59            // org/kohsuke/github/GHWorkflowJob$Step
  #12 = Class              #60            // java/lang/Object
  #13 = Utf8               name
  #14 = Utf8               Ljava/lang/String;
  #15 = Utf8               number
  #16 = Utf8               I
  #17 = Utf8               startedAt
  #18 = Utf8               completedAt
  #19 = Utf8               status
  #20 = Utf8               conclusion
  #21 = Utf8               <init>
  #22 = Utf8               ()V
  #23 = Utf8               Code
  #24 = Utf8               LineNumberTable
  #25 = Utf8               LocalVariableTable
  #26 = Utf8               this
  #27 = Utf8               Step
  #28 = Utf8               InnerClasses
  #29 = Utf8               Lorg/kohsuke/github/GHWorkflowJob$Step;
  #30 = Utf8               getName
  #31 = Utf8               ()Ljava/lang/String;
  #32 = Utf8               getNumber
  #33 = Utf8               ()I
  #34 = Utf8               getStartedAt
  #35 = Utf8               ()Ljava/util/Date;
  #36 = Utf8               getCompletedAt
  #37 = Utf8               getStatus
  #38 = Class              #62            // org/kohsuke/github/GHWorkflowRun$Status
  #39 = Utf8               Status
  #40 = Utf8               ()Lorg/kohsuke/github/GHWorkflowRun$Status;
  #41 = Utf8               getConclusion
  #42 = Class              #63            // org/kohsuke/github/GHWorkflowRun$Conclusion
  #43 = Utf8               Conclusion
  #44 = Utf8               ()Lorg/kohsuke/github/GHWorkflowRun$Conclusion;
  #45 = Utf8               SourceFile
  #46 = Utf8               GHWorkflowJob.java
  #47 = NameAndType        #21:#22        // "<init>":()V
  #48 = NameAndType        #13:#14        // name:Ljava/lang/String;
  #49 = NameAndType        #15:#16        // number:I
  #50 = NameAndType        #17:#14        // startedAt:Ljava/lang/String;
  #51 = Class              #64            // org/kohsuke/github/GitHubClient
  #52 = NameAndType        #65:#66        // parseDate:(Ljava/lang/String;)Ljava/util/Date;
  #53 = NameAndType        #18:#14        // completedAt:Ljava/lang/String;
  #54 = NameAndType        #19:#14        // status:Ljava/lang/String;
  #55 = NameAndType        #67:#68        // from:(Ljava/lang/String;)Lorg/kohsuke/github/GHWorkflowRun$Status;
  #56 = NameAndType        #20:#14        // conclusion:Ljava/lang/String;
  #57 = NameAndType        #67:#69        // from:(Ljava/lang/String;)Lorg/kohsuke/github/GHWorkflowRun$Conclusion;
  #58 = Class              #70            // org/kohsuke/github/GHWorkflowJob
  #59 = Utf8               org/kohsuke/github/GHWorkflowJob$Step
  #60 = Utf8               java/lang/Object
  #61 = Class              #71            // org/kohsuke/github/GHWorkflowRun
  #62 = Utf8               org/kohsuke/github/GHWorkflowRun$Status
  #63 = Utf8               org/kohsuke/github/GHWorkflowRun$Conclusion
  #64 = Utf8               org/kohsuke/github/GitHubClient
  #65 = Utf8               parseDate
  #66 = Utf8               (Ljava/lang/String;)Ljava/util/Date;
  #67 = Utf8               from
  #68 = Utf8               (Ljava/lang/String;)Lorg/kohsuke/github/GHWorkflowRun$Status;
  #69 = Utf8               (Ljava/lang/String;)Lorg/kohsuke/github/GHWorkflowRun$Conclusion;
  #70 = Utf8               org/kohsuke/github/GHWorkflowJob
  #71 = Utf8               org/kohsuke/github/GHWorkflowRun
{
  private java.lang.String name;
    descriptor: Ljava/lang/String;
    flags: (0x0002) ACC_PRIVATE

  private int number;
    descriptor: I
    flags: (0x0002) ACC_PRIVATE

  private java.lang.String startedAt;
    descriptor: Ljava/lang/String;
    flags: (0x0002) ACC_PRIVATE

  private java.lang.String completedAt;
    descriptor: Ljava/lang/String;
    flags: (0x0002) ACC_PRIVATE

  private java.lang.String status;
    descriptor: Ljava/lang/String;
    flags: (0x0002) ACC_PRIVATE

  private java.lang.String conclusion;
    descriptor: Ljava/lang/String;
    flags: (0x0002) ACC_PRIVATE

  public org.kohsuke.github.GHWorkflowJob$Step();
    descriptor: ()V
    flags: (0x0001) ACC_PUBLIC
    Code:
      stack=1, locals=1, args_size=1
         0: aload_0
         1: invokespecial #1                  // Method java/lang/Object."<init>":()V
         4: return
      LineNumberTable:
        line 178: 0
      LocalVariableTable:
        Start  Length  Slot  Name   Signature
            0       5     0  this   Lorg/kohsuke/github/GHWorkflowJob$Step;

  public java.lang.String getName();
    descriptor: ()Ljava/lang/String;
    flags: (0x0001) ACC_PUBLIC
    Code:
      stack=1, locals=1, args_size=1
         0: aload_0
         1: getfield      #2                  // Field name:Ljava/lang/String;
         4: areturn
      LineNumberTable:
        line 195: 0
      LocalVariableTable:
        Start  Length  Slot  Name   Signature
            0       5     0  this   Lorg/kohsuke/github/GHWorkflowJob$Step;

  public int getNumber();
    descriptor: ()I
    flags: (0x0001) ACC_PUBLIC
    Code:
      stack=1, locals=1, args_size=1
         0: aload_0
         1: getfield      #3                  // Field number:I
         4: ireturn
      LineNumberTable:
        line 204: 0
      LocalVariableTable:
        Start  Length  Slot  Name   Signature
            0       5     0  this   Lorg/kohsuke/github/GHWorkflowJob$Step;

  public java.util.Date getStartedAt();
    descriptor: ()Ljava/util/Date;
    flags: (0x0001) ACC_PUBLIC
    Code:
      stack=1, locals=1, args_size=1
         0: aload_0
         1: getfield      #4                  // Field startedAt:Ljava/lang/String;
         4: invokestatic  #5                  // Method org/kohsuke/github/GitHubClient.parseDate:(Ljava/lang/String;)Ljava/util/Date;
         7: areturn
      LineNumberTable:
        line 213: 0
      LocalVariableTable:
        Start  Length  Slot  Name   Signature
            0       8     0  this   Lorg/kohsuke/github/GHWorkflowJob$Step;

  public java.util.Date getCompletedAt();
    descriptor: ()Ljava/util/Date;
    flags: (0x0001) ACC_PUBLIC
    Code:
      stack=1, locals=1, args_size=1
         0: aload_0
         1: getfield      #6                  // Field completedAt:Ljava/lang/String;
         4: invokestatic  #5                  // Method org/kohsuke/github/GitHubClient.parseDate:(Ljava/lang/String;)Ljava/util/Date;
         7: areturn
      LineNumberTable:
        line 222: 0
      LocalVariableTable:
        Start  Length  Slot  Name   Signature
            0       8     0  this   Lorg/kohsuke/github/GHWorkflowJob$Step;

  public org.kohsuke.github.GHWorkflowRun$Status getStatus();
    descriptor: ()Lorg/kohsuke/github/GHWorkflowRun$Status;
    flags: (0x0001) ACC_PUBLIC
    Code:
      stack=1, locals=1, args_size=1
         0: aload_0
         1: getfield      #7                  // Field status:Ljava/lang/String;
         4: invokestatic  #8                  // Method org/kohsuke/github/GHWorkflowRun$Status.from:(Ljava/lang/String;)Lorg/kohsuke/github/GHWorkflowRun$Status;
         7: areturn
      LineNumberTable:
        line 233: 0
      LocalVariableTable:
        Start  Length  Slot  Name   Signature
            0       8     0  this   Lorg/kohsuke/github/GHWorkflowJob$Step;

  public org.kohsuke.github.GHWorkflowRun$Conclusion getConclusion();
    descriptor: ()Lorg/kohsuke/github/GHWorkflowRun$Conclusion;
    flags: (0x0001) ACC_PUBLIC
    Code:
      stack=1, locals=1, args_size=1
         0: aload_0
         1: getfield      #9                  // Field conclusion:Ljava/lang/String;
         4: invokestatic  #10                 // Method org/kohsuke/github/GHWorkflowRun$Conclusion.from:(Ljava/lang/String;)Lorg/kohsuke/github/GHWorkflowRun$Conclusion;
         7: areturn
      LineNumberTable:
        line 244: 0
      LocalVariableTable:
        Start  Length  Slot  Name   Signature
            0       8     0  this   Lorg/kohsuke/github/GHWorkflowJob$Step;
}
SourceFile: "GHWorkflowJob.java"
InnerClasses:
  public static #27= #11 of #58;          // Step=class org/kohsuke/github/GHWorkflowJob$Step of class org/kohsuke/github/GHWorkflowJob
  public static final #39= #38 of #61;    // Status=class org/kohsuke/github/GHWorkflowRun$Status of class org/kohsuke/github/GHWorkflowRun
  public static final #43= #42 of #61;    // Conclusion=class org/kohsuke/github/GHWorkflowRun$Conclusion of class org/kohsuke/github/GHWorkflowRun
