Classfile /Users/mw/Projects/slang-braindump/.jar/jar11/assemble/slang-braindump/assemble/content/org/kohsuke/github/GHWorkflowJobQueryBuilder.class
  Last modified May 29, 2022; size 2113 bytes
  SHA-256 checksum c14ed990765c9d3c7427bcf7b19f706228319e9bc36744188a0dec1bbee3caed
  Compiled from "GHWorkflowJobQueryBuilder.java"
public class org.kohsuke.github.GHWorkflowJobQueryBuilder extends org.kohsuke.github.GHQueryBuilder<org.kohsuke.github.GHWorkflowJob>
  minor version: 0
  major version: 52
  flags: (0x0021) ACC_PUBLIC, ACC_SUPER
  this_class: #20                         // org/kohsuke/github/GHWorkflowJobQueryBuilder
  super_class: #21                        // org/kohsuke/github/GHQueryBuilder
  interfaces: 0, fields: 1, methods: 4, attributes: 3
Constant pool:
   #1 = Methodref          #43.#44        // org/kohsuke/github/GHWorkflowRun.getRepository:()Lorg/kohsuke/github/GHRepository;
   #2 = Methodref          #45.#46        // org/kohsuke/github/GHRepository.root:()Lorg/kohsuke/github/GitHub;
   #3 = Methodref          #21.#47        // org/kohsuke/github/GHQueryBuilder."<init>":(Lorg/kohsuke/github/GitHub;)V
   #4 = Fieldref           #20.#48        // org/kohsuke/github/GHWorkflowJobQueryBuilder.repo:Lorg/kohsuke/github/GHRepository;
   #5 = Fieldref           #20.#49        // org/kohsuke/github/GHWorkflowJobQueryBuilder.req:Lorg/kohsuke/github/Requester;
   #6 = String             #50            // actions/runs
   #7 = Methodref          #45.#51        // org/kohsuke/github/GHRepository.getApiTailUrl:(Ljava/lang/String;)Ljava/lang/String;
   #8 = Class              #52            // java/lang/String
   #9 = Methodref          #43.#53        // org/kohsuke/github/GHWorkflowRun.getId:()J
  #10 = Methodref          #8.#54         // java/lang/String.valueOf:(J)Ljava/lang/String;
  #11 = String             #55            // jobs
  #12 = Methodref          #56.#57        // org/kohsuke/github/Requester.withUrlPath:(Ljava/lang/String;[Ljava/lang/String;)Lorg/kohsuke/github/GitHubRequest$Builder;
  #13 = String             #58            // filter
  #14 = String             #33            // latest
  #15 = Methodref          #56.#59        // org/kohsuke/github/Requester.with:(Ljava/lang/String;Ljava/lang/String;)Lorg/kohsuke/github/GitHubRequest$Builder;
  #16 = String             #35            // all
  #17 = Class              #60            // org/kohsuke/github/GHWorkflowJobsIterable
  #18 = Methodref          #56.#61        // org/kohsuke/github/Requester.build:()Lorg/kohsuke/github/GitHubRequest;
  #19 = Methodref          #17.#62        // org/kohsuke/github/GHWorkflowJobsIterable."<init>":(Lorg/kohsuke/github/GHRepository;Lorg/kohsuke/github/GitHubRequest;)V
  #20 = Class              #63            // org/kohsuke/github/GHWorkflowJobQueryBuilder
  #21 = Class              #64            // org/kohsuke/github/GHQueryBuilder
  #22 = Utf8               repo
  #23 = Utf8               Lorg/kohsuke/github/GHRepository;
  #24 = Utf8               <init>
  #25 = Utf8               (Lorg/kohsuke/github/GHWorkflowRun;)V
  #26 = Utf8               Code
  #27 = Utf8               LineNumberTable
  #28 = Utf8               LocalVariableTable
  #29 = Utf8               this
  #30 = Utf8               Lorg/kohsuke/github/GHWorkflowJobQueryBuilder;
  #31 = Utf8               workflowRun
  #32 = Utf8               Lorg/kohsuke/github/GHWorkflowRun;
  #33 = Utf8               latest
  #34 = Utf8               ()Lorg/kohsuke/github/GHWorkflowJobQueryBuilder;
  #35 = Utf8               all
  #36 = Utf8               list
  #37 = Utf8               ()Lorg/kohsuke/github/PagedIterable;
  #38 = Utf8               Signature
  #39 = Utf8               ()Lorg/kohsuke/github/PagedIterable<Lorg/kohsuke/github/GHWorkflowJob;>;
  #40 = Utf8               Lorg/kohsuke/github/GHQueryBuilder<Lorg/kohsuke/github/GHWorkflowJob;>;
  #41 = Utf8               SourceFile
  #42 = Utf8               GHWorkflowJobQueryBuilder.java
  #43 = Class              #65            // org/kohsuke/github/GHWorkflowRun
  #44 = NameAndType        #66:#67        // getRepository:()Lorg/kohsuke/github/GHRepository;
  #45 = Class              #68            // org/kohsuke/github/GHRepository
  #46 = NameAndType        #69:#70        // root:()Lorg/kohsuke/github/GitHub;
  #47 = NameAndType        #24:#71        // "<init>":(Lorg/kohsuke/github/GitHub;)V
  #48 = NameAndType        #22:#23        // repo:Lorg/kohsuke/github/GHRepository;
  #49 = NameAndType        #72:#73        // req:Lorg/kohsuke/github/Requester;
  #50 = Utf8               actions/runs
  #51 = NameAndType        #74:#75        // getApiTailUrl:(Ljava/lang/String;)Ljava/lang/String;
  #52 = Utf8               java/lang/String
  #53 = NameAndType        #76:#77        // getId:()J
  #54 = NameAndType        #78:#79        // valueOf:(J)Ljava/lang/String;
  #55 = Utf8               jobs
  #56 = Class              #80            // org/kohsuke/github/Requester
  #57 = NameAndType        #81:#85        // withUrlPath:(Ljava/lang/String;[Ljava/lang/String;)Lorg/kohsuke/github/GitHubRequest$Builder;
  #58 = Utf8               filter
  #59 = NameAndType        #86:#87        // with:(Ljava/lang/String;Ljava/lang/String;)Lorg/kohsuke/github/GitHubRequest$Builder;
  #60 = Utf8               org/kohsuke/github/GHWorkflowJobsIterable
  #61 = NameAndType        #88:#89        // build:()Lorg/kohsuke/github/GitHubRequest;
  #62 = NameAndType        #24:#90        // "<init>":(Lorg/kohsuke/github/GHRepository;Lorg/kohsuke/github/GitHubRequest;)V
  #63 = Utf8               org/kohsuke/github/GHWorkflowJobQueryBuilder
  #64 = Utf8               org/kohsuke/github/GHQueryBuilder
  #65 = Utf8               org/kohsuke/github/GHWorkflowRun
  #66 = Utf8               getRepository
  #67 = Utf8               ()Lorg/kohsuke/github/GHRepository;
  #68 = Utf8               org/kohsuke/github/GHRepository
  #69 = Utf8               root
  #70 = Utf8               ()Lorg/kohsuke/github/GitHub;
  #71 = Utf8               (Lorg/kohsuke/github/GitHub;)V
  #72 = Utf8               req
  #73 = Utf8               Lorg/kohsuke/github/Requester;
  #74 = Utf8               getApiTailUrl
  #75 = Utf8               (Ljava/lang/String;)Ljava/lang/String;
  #76 = Utf8               getId
  #77 = Utf8               ()J
  #78 = Utf8               valueOf
  #79 = Utf8               (J)Ljava/lang/String;
  #80 = Utf8               org/kohsuke/github/Requester
  #81 = Utf8               withUrlPath
  #82 = Class              #92            // org/kohsuke/github/GitHubRequest$Builder
  #83 = Utf8               Builder
  #84 = Utf8               InnerClasses
  #85 = Utf8               (Ljava/lang/String;[Ljava/lang/String;)Lorg/kohsuke/github/GitHubRequest$Builder;
  #86 = Utf8               with
  #87 = Utf8               (Ljava/lang/String;Ljava/lang/String;)Lorg/kohsuke/github/GitHubRequest$Builder;
  #88 = Utf8               build
  #89 = Utf8               ()Lorg/kohsuke/github/GitHubRequest;
  #90 = Utf8               (Lorg/kohsuke/github/GHRepository;Lorg/kohsuke/github/GitHubRequest;)V
  #91 = Class              #93            // org/kohsuke/github/GitHubRequest
  #92 = Utf8               org/kohsuke/github/GitHubRequest$Builder
  #93 = Utf8               org/kohsuke/github/GitHubRequest
{
  private final org.kohsuke.github.GHRepository repo;
    descriptor: Lorg/kohsuke/github/GHRepository;
    flags: (0x0012) ACC_PRIVATE, ACC_FINAL

  org.kohsuke.github.GHWorkflowJobQueryBuilder(org.kohsuke.github.GHWorkflowRun);
    descriptor: (Lorg/kohsuke/github/GHWorkflowRun;)V
    flags: (0x0000)
    Code:
      stack=7, locals=2, args_size=2
         0: aload_0
         1: aload_1
         2: invokevirtual #1                  // Method org/kohsuke/github/GHWorkflowRun.getRepository:()Lorg/kohsuke/github/GHRepository;
         5: invokevirtual #2                  // Method org/kohsuke/github/GHRepository.root:()Lorg/kohsuke/github/GitHub;
         8: invokespecial #3                  // Method org/kohsuke/github/GHQueryBuilder."<init>":(Lorg/kohsuke/github/GitHub;)V
        11: aload_0
        12: aload_1
        13: invokevirtual #1                  // Method org/kohsuke/github/GHWorkflowRun.getRepository:()Lorg/kohsuke/github/GHRepository;
        16: putfield      #4                  // Field repo:Lorg/kohsuke/github/GHRepository;
        19: aload_0
        20: getfield      #5                  // Field req:Lorg/kohsuke/github/Requester;
        23: aload_0
        24: getfield      #4                  // Field repo:Lorg/kohsuke/github/GHRepository;
        27: ldc           #6                  // String actions/runs
        29: invokevirtual #7                  // Method org/kohsuke/github/GHRepository.getApiTailUrl:(Ljava/lang/String;)Ljava/lang/String;
        32: iconst_2
        33: anewarray     #8                  // class java/lang/String
        36: dup
        37: iconst_0
        38: aload_1
        39: invokevirtual #9                  // Method org/kohsuke/github/GHWorkflowRun.getId:()J
        42: invokestatic  #10                 // Method java/lang/String.valueOf:(J)Ljava/lang/String;
        45: aastore
        46: dup
        47: iconst_1
        48: ldc           #11                 // String jobs
        50: aastore
        51: invokevirtual #12                 // Method org/kohsuke/github/Requester.withUrlPath:(Ljava/lang/String;[Ljava/lang/String;)Lorg/kohsuke/github/GitHubRequest$Builder;
        54: pop
        55: return
      LineNumberTable:
        line 12: 0
        line 13: 11
        line 14: 19
        line 15: 55
      LocalVariableTable:
        Start  Length  Slot  Name   Signature
            0      56     0  this   Lorg/kohsuke/github/GHWorkflowJobQueryBuilder;
            0      56     1 workflowRun   Lorg/kohsuke/github/GHWorkflowRun;

  public org.kohsuke.github.GHWorkflowJobQueryBuilder latest();
    descriptor: ()Lorg/kohsuke/github/GHWorkflowJobQueryBuilder;
    flags: (0x0001) ACC_PUBLIC
    Code:
      stack=3, locals=1, args_size=1
         0: aload_0
         1: getfield      #5                  // Field req:Lorg/kohsuke/github/Requester;
         4: ldc           #13                 // String filter
         6: ldc           #14                 // String latest
         8: invokevirtual #15                 // Method org/kohsuke/github/Requester.with:(Ljava/lang/String;Ljava/lang/String;)Lorg/kohsuke/github/GitHubRequest$Builder;
        11: pop
        12: aload_0
        13: areturn
      LineNumberTable:
        line 23: 0
        line 24: 12
      LocalVariableTable:
        Start  Length  Slot  Name   Signature
            0      14     0  this   Lorg/kohsuke/github/GHWorkflowJobQueryBuilder;

  public org.kohsuke.github.GHWorkflowJobQueryBuilder all();
    descriptor: ()Lorg/kohsuke/github/GHWorkflowJobQueryBuilder;
    flags: (0x0001) ACC_PUBLIC
    Code:
      stack=3, locals=1, args_size=1
         0: aload_0
         1: getfield      #5                  // Field req:Lorg/kohsuke/github/Requester;
         4: ldc           #13                 // String filter
         6: ldc           #16                 // String all
         8: invokevirtual #15                 // Method org/kohsuke/github/Requester.with:(Ljava/lang/String;Ljava/lang/String;)Lorg/kohsuke/github/GitHubRequest$Builder;
        11: pop
        12: aload_0
        13: areturn
      LineNumberTable:
        line 33: 0
        line 34: 12
      LocalVariableTable:
        Start  Length  Slot  Name   Signature
            0      14     0  this   Lorg/kohsuke/github/GHWorkflowJobQueryBuilder;

  public org.kohsuke.github.PagedIterable<org.kohsuke.github.GHWorkflowJob> list();
    descriptor: ()Lorg/kohsuke/github/PagedIterable;
    flags: (0x0001) ACC_PUBLIC
    Code:
      stack=4, locals=1, args_size=1
         0: new           #17                 // class org/kohsuke/github/GHWorkflowJobsIterable
         3: dup
         4: aload_0
         5: getfield      #4                  // Field repo:Lorg/kohsuke/github/GHRepository;
         8: aload_0
         9: getfield      #5                  // Field req:Lorg/kohsuke/github/Requester;
        12: invokevirtual #18                 // Method org/kohsuke/github/Requester.build:()Lorg/kohsuke/github/GitHubRequest;
        15: invokespecial #19                 // Method org/kohsuke/github/GHWorkflowJobsIterable."<init>":(Lorg/kohsuke/github/GHRepository;Lorg/kohsuke/github/GitHubRequest;)V
        18: areturn
      LineNumberTable:
        line 39: 0
      LocalVariableTable:
        Start  Length  Slot  Name   Signature
            0      19     0  this   Lorg/kohsuke/github/GHWorkflowJobQueryBuilder;
    Signature: #39                          // ()Lorg/kohsuke/github/PagedIterable<Lorg/kohsuke/github/GHWorkflowJob;>;
}
Signature: #40                          // Lorg/kohsuke/github/GHQueryBuilder<Lorg/kohsuke/github/GHWorkflowJob;>;
SourceFile: "GHWorkflowJobQueryBuilder.java"
InnerClasses:
  static #83= #82 of #91;                 // Builder=class org/kohsuke/github/GitHubRequest$Builder of class org/kohsuke/github/GitHubRequest
