Classfile /Users/mw/Projects/slang-braindump/.jar/jar11/assemble/slang-braindump/assemble/content/org/kohsuke/github/GitHubRateLimitChecker.class
  Last modified May 29, 2022; size 4108 bytes
  SHA-256 checksum 0bc2eb8243952a95085b7dd752f509406da8093c6698b5f545a1546ffc441b2a
  Compiled from "GitHubRateLimitChecker.java"
class org.kohsuke.github.GitHubRateLimitChecker
  minor version: 0
  major version: 52
  flags: (0x0020) ACC_SUPER
  this_class: #10                         // org/kohsuke/github/GitHubRateLimitChecker
  super_class: #41                        // java/lang/Object
  interfaces: 0, fields: 5, methods: 6, attributes: 2
Constant pool:
    #1 = Fieldref           #5.#90        // org/kohsuke/github/RateLimitChecker.NONE:Lorg/kohsuke/github/RateLimitChecker;
    #2 = Methodref          #10.#91       // org/kohsuke/github/GitHubRateLimitChecker."<init>":(Lorg/kohsuke/github/RateLimitChecker;Lorg/kohsuke/github/RateLimitChecker;Lorg/kohsuke/github/RateLimitChecker;Lorg/kohsuke/github/RateLimitChecker;)V
    #3 = Methodref          #41.#92       // java/lang/Object."<init>":()V
    #4 = Methodref          #93.#94       // java/util/Objects.requireNonNull:(Ljava/lang/Object;)Ljava/lang/Object;
    #5 = Class              #95           // org/kohsuke/github/RateLimitChecker
    #6 = Fieldref           #10.#96       // org/kohsuke/github/GitHubRateLimitChecker.core:Lorg/kohsuke/github/RateLimitChecker;
    #7 = Fieldref           #10.#97       // org/kohsuke/github/GitHubRateLimitChecker.search:Lorg/kohsuke/github/RateLimitChecker;
    #8 = Fieldref           #10.#98       // org/kohsuke/github/GitHubRateLimitChecker.graphql:Lorg/kohsuke/github/RateLimitChecker;
    #9 = Fieldref           #10.#99       // org/kohsuke/github/GitHubRateLimitChecker.integrationManifest:Lorg/kohsuke/github/RateLimitChecker;
   #10 = Class              #100          // org/kohsuke/github/GitHubRateLimitChecker
   #11 = Fieldref           #66.#101      // org/kohsuke/github/RateLimitTarget.CORE:Lorg/kohsuke/github/RateLimitTarget;
   #12 = Fieldref           #66.#102      // org/kohsuke/github/RateLimitTarget.SEARCH:Lorg/kohsuke/github/RateLimitTarget;
   #13 = Fieldref           #66.#103      // org/kohsuke/github/RateLimitTarget.GRAPHQL:Lorg/kohsuke/github/RateLimitTarget;
   #14 = Fieldref           #66.#104      // org/kohsuke/github/RateLimitTarget.INTEGRATION_MANIFEST:Lorg/kohsuke/github/RateLimitTarget;
   #15 = Methodref          #10.#105      // org/kohsuke/github/GitHubRateLimitChecker.selectChecker:(Lorg/kohsuke/github/RateLimitTarget;)Lorg/kohsuke/github/RateLimitChecker;
   #16 = Methodref          #106.#107     // org/kohsuke/github/GitHubClient.rateLimit:(Lorg/kohsuke/github/RateLimitTarget;)Lorg/kohsuke/github/GHRateLimit;
   #17 = Methodref          #83.#108      // org/kohsuke/github/GHRateLimit.getRecord:(Lorg/kohsuke/github/RateLimitTarget;)Lorg/kohsuke/github/GHRateLimit$Record;
   #18 = Methodref          #5.#109       // org/kohsuke/github/RateLimitChecker.checkRateLimit:(Lorg/kohsuke/github/GHRateLimit$Record;J)Z
   #19 = Long               1000l
   #21 = Methodref          #110.#111     // java/lang/Thread.sleep:(J)V
   #22 = Methodref          #106.#112     // org/kohsuke/github/GitHubClient.getRateLimit:(Lorg/kohsuke/github/RateLimitTarget;)Lorg/kohsuke/github/GHRateLimit;
   #23 = Class              #113          // java/lang/InterruptedException
   #24 = Class              #114          // java/io/InterruptedIOException
   #25 = Methodref          #23.#115      // java/lang/InterruptedException.getMessage:()Ljava/lang/String;
   #26 = Methodref          #24.#116      // java/io/InterruptedIOException."<init>":(Ljava/lang/String;)V
   #27 = Methodref          #24.#117      // java/io/InterruptedIOException.initCause:(Ljava/lang/Throwable;)Ljava/lang/Throwable;
   #28 = Class              #118          // java/io/IOException
   #29 = Fieldref           #66.#119      // org/kohsuke/github/RateLimitTarget.NONE:Lorg/kohsuke/github/RateLimitTarget;
   #30 = Class              #120          // java/lang/IllegalArgumentException
   #31 = Class              #121          // java/lang/StringBuilder
   #32 = Methodref          #31.#92       // java/lang/StringBuilder."<init>":()V
   #33 = String             #122          // Unknown rate limit target:
   #34 = Methodref          #31.#123      // java/lang/StringBuilder.append:(Ljava/lang/String;)Ljava/lang/StringBuilder;
   #35 = Methodref          #66.#124      // org/kohsuke/github/RateLimitTarget.toString:()Ljava/lang/String;
   #36 = Methodref          #31.#124      // java/lang/StringBuilder.toString:()Ljava/lang/String;
   #37 = Methodref          #30.#116      // java/lang/IllegalArgumentException."<init>":(Ljava/lang/String;)V
   #38 = Methodref          #125.#126     // java/lang/Class.getName:()Ljava/lang/String;
   #39 = Methodref          #127.#128     // java/util/logging/Logger.getLogger:(Ljava/lang/String;)Ljava/util/logging/Logger;
   #40 = Fieldref           #10.#129      // org/kohsuke/github/GitHubRateLimitChecker.LOGGER:Ljava/util/logging/Logger;
   #41 = Class              #130          // java/lang/Object
   #42 = Utf8               core
   #43 = Utf8               Lorg/kohsuke/github/RateLimitChecker;
   #44 = Utf8               RuntimeVisibleAnnotations
   #45 = Utf8               Ljavax/annotation/Nonnull;
   #46 = Utf8               search
   #47 = Utf8               graphql
   #48 = Utf8               integrationManifest
   #49 = Utf8               LOGGER
   #50 = Utf8               Ljava/util/logging/Logger;
   #51 = Utf8               <init>
   #52 = Utf8               ()V
   #53 = Utf8               Code
   #54 = Utf8               LineNumberTable
   #55 = Utf8               LocalVariableTable
   #56 = Utf8               this
   #57 = Utf8               Lorg/kohsuke/github/GitHubRateLimitChecker;
   #58 = Utf8               (Lorg/kohsuke/github/RateLimitChecker;Lorg/kohsuke/github/RateLimitChecker;Lorg/kohsuke/github/RateLimitChecker;Lorg/kohsuke/github/RateLimitChecker;)V
   #59 = Utf8               RuntimeVisibleParameterAnnotations
   #60 = Utf8               with
   #61 = Utf8               (Lorg/kohsuke/github/RateLimitChecker;Lorg/kohsuke/github/RateLimitTarget;)Lorg/kohsuke/github/GitHubRateLimitChecker;
   #62 = Utf8               checker
   #63 = Utf8               rateLimitTarget
   #64 = Utf8               Lorg/kohsuke/github/RateLimitTarget;
   #65 = Utf8               StackMapTable
   #66 = Class              #131          // org/kohsuke/github/RateLimitTarget
   #67 = Utf8               checkRateLimit
   #68 = Utf8               (Lorg/kohsuke/github/GitHubClient;Lorg/kohsuke/github/RateLimitTarget;)V
   #69 = Utf8               e
   #70 = Utf8               Ljava/lang/InterruptedException;
   #71 = Utf8               client
   #72 = Utf8               Lorg/kohsuke/github/GitHubClient;
   #73 = Utf8               guard
   #74 = Utf8               rateLimit
   #75 = Utf8               Lorg/kohsuke/github/GHRateLimit;
   #76 = Utf8               rateLimitRecord
   #77 = Class              #132          // org/kohsuke/github/GHRateLimit$Record
   #78 = Utf8               Record
   #79 = Utf8               InnerClasses
   #80 = Utf8               Lorg/kohsuke/github/GHRateLimit$Record;
   #81 = Utf8               waitCount
   #82 = Utf8               J
   #83 = Class              #133          // org/kohsuke/github/GHRateLimit
   #84 = Utf8               Exceptions
   #85 = Utf8               selectChecker
   #86 = Utf8               (Lorg/kohsuke/github/RateLimitTarget;)Lorg/kohsuke/github/RateLimitChecker;
   #87 = Utf8               <clinit>
   #88 = Utf8               SourceFile
   #89 = Utf8               GitHubRateLimitChecker.java
   #90 = NameAndType        #134:#43      // NONE:Lorg/kohsuke/github/RateLimitChecker;
   #91 = NameAndType        #51:#58       // "<init>":(Lorg/kohsuke/github/RateLimitChecker;Lorg/kohsuke/github/RateLimitChecker;Lorg/kohsuke/github/RateLimitChecker;Lorg/kohsuke/github/RateLimitChecker;)V
   #92 = NameAndType        #51:#52       // "<init>":()V
   #93 = Class              #135          // java/util/Objects
   #94 = NameAndType        #136:#137     // requireNonNull:(Ljava/lang/Object;)Ljava/lang/Object;
   #95 = Utf8               org/kohsuke/github/RateLimitChecker
   #96 = NameAndType        #42:#43       // core:Lorg/kohsuke/github/RateLimitChecker;
   #97 = NameAndType        #46:#43       // search:Lorg/kohsuke/github/RateLimitChecker;
   #98 = NameAndType        #47:#43       // graphql:Lorg/kohsuke/github/RateLimitChecker;
   #99 = NameAndType        #48:#43       // integrationManifest:Lorg/kohsuke/github/RateLimitChecker;
  #100 = Utf8               org/kohsuke/github/GitHubRateLimitChecker
  #101 = NameAndType        #138:#64      // CORE:Lorg/kohsuke/github/RateLimitTarget;
  #102 = NameAndType        #139:#64      // SEARCH:Lorg/kohsuke/github/RateLimitTarget;
  #103 = NameAndType        #140:#64      // GRAPHQL:Lorg/kohsuke/github/RateLimitTarget;
  #104 = NameAndType        #141:#64      // INTEGRATION_MANIFEST:Lorg/kohsuke/github/RateLimitTarget;
  #105 = NameAndType        #85:#86       // selectChecker:(Lorg/kohsuke/github/RateLimitTarget;)Lorg/kohsuke/github/RateLimitChecker;
  #106 = Class              #142          // org/kohsuke/github/GitHubClient
  #107 = NameAndType        #74:#143      // rateLimit:(Lorg/kohsuke/github/RateLimitTarget;)Lorg/kohsuke/github/GHRateLimit;
  #108 = NameAndType        #144:#145     // getRecord:(Lorg/kohsuke/github/RateLimitTarget;)Lorg/kohsuke/github/GHRateLimit$Record;
  #109 = NameAndType        #67:#146      // checkRateLimit:(Lorg/kohsuke/github/GHRateLimit$Record;J)Z
  #110 = Class              #147          // java/lang/Thread
  #111 = NameAndType        #148:#149     // sleep:(J)V
  #112 = NameAndType        #150:#143     // getRateLimit:(Lorg/kohsuke/github/RateLimitTarget;)Lorg/kohsuke/github/GHRateLimit;
  #113 = Utf8               java/lang/InterruptedException
  #114 = Utf8               java/io/InterruptedIOException
  #115 = NameAndType        #151:#152     // getMessage:()Ljava/lang/String;
  #116 = NameAndType        #51:#153      // "<init>":(Ljava/lang/String;)V
  #117 = NameAndType        #154:#155     // initCause:(Ljava/lang/Throwable;)Ljava/lang/Throwable;
  #118 = Utf8               java/io/IOException
  #119 = NameAndType        #134:#64      // NONE:Lorg/kohsuke/github/RateLimitTarget;
  #120 = Utf8               java/lang/IllegalArgumentException
  #121 = Utf8               java/lang/StringBuilder
  #122 = Utf8               Unknown rate limit target:
  #123 = NameAndType        #156:#157     // append:(Ljava/lang/String;)Ljava/lang/StringBuilder;
  #124 = NameAndType        #158:#152     // toString:()Ljava/lang/String;
  #125 = Class              #159          // java/lang/Class
  #126 = NameAndType        #160:#152     // getName:()Ljava/lang/String;
  #127 = Class              #161          // java/util/logging/Logger
  #128 = NameAndType        #162:#163     // getLogger:(Ljava/lang/String;)Ljava/util/logging/Logger;
  #129 = NameAndType        #49:#50       // LOGGER:Ljava/util/logging/Logger;
  #130 = Utf8               java/lang/Object
  #131 = Utf8               org/kohsuke/github/RateLimitTarget
  #132 = Utf8               org/kohsuke/github/GHRateLimit$Record
  #133 = Utf8               org/kohsuke/github/GHRateLimit
  #134 = Utf8               NONE
  #135 = Utf8               java/util/Objects
  #136 = Utf8               requireNonNull
  #137 = Utf8               (Ljava/lang/Object;)Ljava/lang/Object;
  #138 = Utf8               CORE
  #139 = Utf8               SEARCH
  #140 = Utf8               GRAPHQL
  #141 = Utf8               INTEGRATION_MANIFEST
  #142 = Utf8               org/kohsuke/github/GitHubClient
  #143 = Utf8               (Lorg/kohsuke/github/RateLimitTarget;)Lorg/kohsuke/github/GHRateLimit;
  #144 = Utf8               getRecord
  #145 = Utf8               (Lorg/kohsuke/github/RateLimitTarget;)Lorg/kohsuke/github/GHRateLimit$Record;
  #146 = Utf8               (Lorg/kohsuke/github/GHRateLimit$Record;J)Z
  #147 = Utf8               java/lang/Thread
  #148 = Utf8               sleep
  #149 = Utf8               (J)V
  #150 = Utf8               getRateLimit
  #151 = Utf8               getMessage
  #152 = Utf8               ()Ljava/lang/String;
  #153 = Utf8               (Ljava/lang/String;)V
  #154 = Utf8               initCause
  #155 = Utf8               (Ljava/lang/Throwable;)Ljava/lang/Throwable;
  #156 = Utf8               append
  #157 = Utf8               (Ljava/lang/String;)Ljava/lang/StringBuilder;
  #158 = Utf8               toString
  #159 = Utf8               java/lang/Class
  #160 = Utf8               getName
  #161 = Utf8               java/util/logging/Logger
  #162 = Utf8               getLogger
  #163 = Utf8               (Ljava/lang/String;)Ljava/util/logging/Logger;
{
  private final org.kohsuke.github.RateLimitChecker core;
    descriptor: Lorg/kohsuke/github/RateLimitChecker;
    flags: (0x0012) ACC_PRIVATE, ACC_FINAL
    RuntimeVisibleAnnotations:
      0: #45()
        javax.annotation.Nonnull

  private final org.kohsuke.github.RateLimitChecker search;
    descriptor: Lorg/kohsuke/github/RateLimitChecker;
    flags: (0x0012) ACC_PRIVATE, ACC_FINAL
    RuntimeVisibleAnnotations:
      0: #45()
        javax.annotation.Nonnull

  private final org.kohsuke.github.RateLimitChecker graphql;
    descriptor: Lorg/kohsuke/github/RateLimitChecker;
    flags: (0x0012) ACC_PRIVATE, ACC_FINAL
    RuntimeVisibleAnnotations:
      0: #45()
        javax.annotation.Nonnull

  private final org.kohsuke.github.RateLimitChecker integrationManifest;
    descriptor: Lorg/kohsuke/github/RateLimitChecker;
    flags: (0x0012) ACC_PRIVATE, ACC_FINAL
    RuntimeVisibleAnnotations:
      0: #45()
        javax.annotation.Nonnull

  private static final java.util.logging.Logger LOGGER;
    descriptor: Ljava/util/logging/Logger;
    flags: (0x001a) ACC_PRIVATE, ACC_STATIC, ACC_FINAL

  org.kohsuke.github.GitHubRateLimitChecker();
    descriptor: ()V
    flags: (0x0000)
    Code:
      stack=5, locals=1, args_size=1
         0: aload_0
         1: getstatic     #1                  // Field org/kohsuke/github/RateLimitChecker.NONE:Lorg/kohsuke/github/RateLimitChecker;
         4: getstatic     #1                  // Field org/kohsuke/github/RateLimitChecker.NONE:Lorg/kohsuke/github/RateLimitChecker;
         7: getstatic     #1                  // Field org/kohsuke/github/RateLimitChecker.NONE:Lorg/kohsuke/github/RateLimitChecker;
        10: getstatic     #1                  // Field org/kohsuke/github/RateLimitChecker.NONE:Lorg/kohsuke/github/RateLimitChecker;
        13: invokespecial #2                  // Method "<init>":(Lorg/kohsuke/github/RateLimitChecker;Lorg/kohsuke/github/RateLimitChecker;Lorg/kohsuke/github/RateLimitChecker;Lorg/kohsuke/github/RateLimitChecker;)V
        16: return
      LineNumberTable:
        line 49: 0
        line 50: 16
      LocalVariableTable:
        Start  Length  Slot  Name   Signature
            0      17     0  this   Lorg/kohsuke/github/GitHubRateLimitChecker;

  org.kohsuke.github.GitHubRateLimitChecker(org.kohsuke.github.RateLimitChecker, org.kohsuke.github.RateLimitChecker, org.kohsuke.github.RateLimitChecker, org.kohsuke.github.RateLimitChecker);
    descriptor: (Lorg/kohsuke/github/RateLimitChecker;Lorg/kohsuke/github/RateLimitChecker;Lorg/kohsuke/github/RateLimitChecker;Lorg/kohsuke/github/RateLimitChecker;)V
    flags: (0x0000)
    Code:
      stack=2, locals=5, args_size=5
         0: aload_0
         1: invokespecial #3                  // Method java/lang/Object."<init>":()V
         4: aload_0
         5: aload_1
         6: invokestatic  #4                  // Method java/util/Objects.requireNonNull:(Ljava/lang/Object;)Ljava/lang/Object;
         9: checkcast     #5                  // class org/kohsuke/github/RateLimitChecker
        12: putfield      #6                  // Field core:Lorg/kohsuke/github/RateLimitChecker;
        15: aload_0
        16: aload_2
        17: invokestatic  #4                  // Method java/util/Objects.requireNonNull:(Ljava/lang/Object;)Ljava/lang/Object;
        20: checkcast     #5                  // class org/kohsuke/github/RateLimitChecker
        23: putfield      #7                  // Field search:Lorg/kohsuke/github/RateLimitChecker;
        26: aload_0
        27: aload_3
        28: invokestatic  #4                  // Method java/util/Objects.requireNonNull:(Ljava/lang/Object;)Ljava/lang/Object;
        31: checkcast     #5                  // class org/kohsuke/github/RateLimitChecker
        34: putfield      #8                  // Field graphql:Lorg/kohsuke/github/RateLimitChecker;
        37: aload_0
        38: aload         4
        40: invokestatic  #4                  // Method java/util/Objects.requireNonNull:(Ljava/lang/Object;)Ljava/lang/Object;
        43: checkcast     #5                  // class org/kohsuke/github/RateLimitChecker
        46: putfield      #9                  // Field integrationManifest:Lorg/kohsuke/github/RateLimitChecker;
        49: return
      LineNumberTable:
        line 55: 0
        line 56: 4
        line 57: 15
        line 58: 26
        line 59: 37
        line 60: 49
      LocalVariableTable:
        Start  Length  Slot  Name   Signature
            0      50     0  this   Lorg/kohsuke/github/GitHubRateLimitChecker;
            0      50     1  core   Lorg/kohsuke/github/RateLimitChecker;
            0      50     2 search   Lorg/kohsuke/github/RateLimitChecker;
            0      50     3 graphql   Lorg/kohsuke/github/RateLimitChecker;
            0      50     4 integrationManifest   Lorg/kohsuke/github/RateLimitChecker;
    RuntimeVisibleParameterAnnotations:
      parameter 0:
        0: #45()
          javax.annotation.Nonnull
      parameter 1:
        0: #45()
          javax.annotation.Nonnull
      parameter 2:
        0: #45()
          javax.annotation.Nonnull
      parameter 3:
        0: #45()
          javax.annotation.Nonnull

  org.kohsuke.github.GitHubRateLimitChecker with(org.kohsuke.github.RateLimitChecker, org.kohsuke.github.RateLimitTarget);
    descriptor: (Lorg/kohsuke/github/RateLimitChecker;Lorg/kohsuke/github/RateLimitTarget;)Lorg/kohsuke/github/GitHubRateLimitChecker;
    flags: (0x0000)
    Code:
      stack=7, locals=3, args_size=3
         0: new           #10                 // class org/kohsuke/github/GitHubRateLimitChecker
         3: dup
         4: aload_2
         5: getstatic     #11                 // Field org/kohsuke/github/RateLimitTarget.CORE:Lorg/kohsuke/github/RateLimitTarget;
         8: if_acmpne     15
        11: aload_1
        12: goto          19
        15: aload_0
        16: getfield      #6                  // Field core:Lorg/kohsuke/github/RateLimitChecker;
        19: aload_2
        20: getstatic     #12                 // Field org/kohsuke/github/RateLimitTarget.SEARCH:Lorg/kohsuke/github/RateLimitTarget;
        23: if_acmpne     30
        26: aload_1
        27: goto          34
        30: aload_0
        31: getfield      #7                  // Field search:Lorg/kohsuke/github/RateLimitChecker;
        34: aload_2
        35: getstatic     #13                 // Field org/kohsuke/github/RateLimitTarget.GRAPHQL:Lorg/kohsuke/github/RateLimitTarget;
        38: if_acmpne     45
        41: aload_1
        42: goto          49
        45: aload_0
        46: getfield      #8                  // Field graphql:Lorg/kohsuke/github/RateLimitChecker;
        49: aload_2
        50: getstatic     #14                 // Field org/kohsuke/github/RateLimitTarget.INTEGRATION_MANIFEST:Lorg/kohsuke/github/RateLimitTarget;
        53: if_acmpne     60
        56: aload_1
        57: goto          64
        60: aload_0
        61: getfield      #9                  // Field integrationManifest:Lorg/kohsuke/github/RateLimitChecker;
        64: invokespecial #2                  // Method "<init>":(Lorg/kohsuke/github/RateLimitChecker;Lorg/kohsuke/github/RateLimitChecker;Lorg/kohsuke/github/RateLimitChecker;Lorg/kohsuke/github/RateLimitChecker;)V
        67: areturn
      LineNumberTable:
        line 75: 0
        line 76: 19
        line 77: 34
        line 78: 49
        line 75: 67
      LocalVariableTable:
        Start  Length  Slot  Name   Signature
            0      68     0  this   Lorg/kohsuke/github/GitHubRateLimitChecker;
            0      68     1 checker   Lorg/kohsuke/github/RateLimitChecker;
            0      68     2 rateLimitTarget   Lorg/kohsuke/github/RateLimitTarget;
      StackMapTable: number_of_entries = 8
        frame_type = 255 /* full_frame */
          offset_delta = 15
          locals = [ class org/kohsuke/github/GitHubRateLimitChecker, class org/kohsuke/github/RateLimitChecker, class org/kohsuke/github/RateLimitTarget ]
          stack = [ uninitialized 0, uninitialized 0 ]
        frame_type = 255 /* full_frame */
          offset_delta = 3
          locals = [ class org/kohsuke/github/GitHubRateLimitChecker, class org/kohsuke/github/RateLimitChecker, class org/kohsuke/github/RateLimitTarget ]
          stack = [ uninitialized 0, uninitialized 0, class org/kohsuke/github/RateLimitChecker ]
        frame_type = 255 /* full_frame */
          offset_delta = 10
          locals = [ class org/kohsuke/github/GitHubRateLimitChecker, class org/kohsuke/github/RateLimitChecker, class org/kohsuke/github/RateLimitTarget ]
          stack = [ uninitialized 0, uninitialized 0, class org/kohsuke/github/RateLimitChecker ]
        frame_type = 255 /* full_frame */
          offset_delta = 3
          locals = [ class org/kohsuke/github/GitHubRateLimitChecker, class org/kohsuke/github/RateLimitChecker, class org/kohsuke/github/RateLimitTarget ]
          stack = [ uninitialized 0, uninitialized 0, class org/kohsuke/github/RateLimitChecker, class org/kohsuke/github/RateLimitChecker ]
        frame_type = 255 /* full_frame */
          offset_delta = 10
          locals = [ class org/kohsuke/github/GitHubRateLimitChecker, class org/kohsuke/github/RateLimitChecker, class org/kohsuke/github/RateLimitTarget ]
          stack = [ uninitialized 0, uninitialized 0, class org/kohsuke/github/RateLimitChecker, class org/kohsuke/github/RateLimitChecker ]
        frame_type = 255 /* full_frame */
          offset_delta = 3
          locals = [ class org/kohsuke/github/GitHubRateLimitChecker, class org/kohsuke/github/RateLimitChecker, class org/kohsuke/github/RateLimitTarget ]
          stack = [ uninitialized 0, uninitialized 0, class org/kohsuke/github/RateLimitChecker, class org/kohsuke/github/RateLimitChecker, class org/kohsuke/github/RateLimitChecker ]
        frame_type = 255 /* full_frame */
          offset_delta = 10
          locals = [ class org/kohsuke/github/GitHubRateLimitChecker, class org/kohsuke/github/RateLimitChecker, class org/kohsuke/github/RateLimitTarget ]
          stack = [ uninitialized 0, uninitialized 0, class org/kohsuke/github/RateLimitChecker, class org/kohsuke/github/RateLimitChecker, class org/kohsuke/github/RateLimitChecker ]
        frame_type = 255 /* full_frame */
          offset_delta = 3
          locals = [ class org/kohsuke/github/GitHubRateLimitChecker, class org/kohsuke/github/RateLimitChecker, class org/kohsuke/github/RateLimitTarget ]
          stack = [ uninitialized 0, uninitialized 0, class org/kohsuke/github/RateLimitChecker, class org/kohsuke/github/RateLimitChecker, class org/kohsuke/github/RateLimitChecker, class org/kohsuke/github/RateLimitChecker ]
    RuntimeVisibleParameterAnnotations:
      parameter 0:
        0: #45()
          javax.annotation.Nonnull
      parameter 1:
        0: #45()
          javax.annotation.Nonnull

  void checkRateLimit(org.kohsuke.github.GitHubClient, org.kohsuke.github.RateLimitTarget) throws java.io.IOException;
    descriptor: (Lorg/kohsuke/github/GitHubClient;Lorg/kohsuke/github/RateLimitTarget;)V
    flags: (0x0000)
    Code:
      stack=4, locals=9, args_size=3
         0: aload_0
         1: aload_2
         2: invokespecial #15                 // Method selectChecker:(Lorg/kohsuke/github/RateLimitTarget;)Lorg/kohsuke/github/RateLimitChecker;
         5: astore_3
         6: aload_3
         7: getstatic     #1                  // Field org/kohsuke/github/RateLimitChecker.NONE:Lorg/kohsuke/github/RateLimitChecker;
        10: if_acmpne     14
        13: return
        14: aload_1
        15: aload_2
        16: invokevirtual #16                 // Method org/kohsuke/github/GitHubClient.rateLimit:(Lorg/kohsuke/github/RateLimitTarget;)Lorg/kohsuke/github/GHRateLimit;
        19: astore        4
        21: aload         4
        23: aload_2
        24: invokevirtual #17                 // Method org/kohsuke/github/GHRateLimit.getRecord:(Lorg/kohsuke/github/RateLimitTarget;)Lorg/kohsuke/github/GHRateLimit$Record;
        27: astore        5
        29: lconst_0
        30: lstore        6
        32: aload_3
        33: aload         5
        35: lload         6
        37: invokevirtual #18                 // Method org/kohsuke/github/RateLimitChecker.checkRateLimit:(Lorg/kohsuke/github/GHRateLimit$Record;J)Z
        40: ifeq          73
        43: lload         6
        45: lconst_1
        46: ladd
        47: lstore        6
        49: ldc2_w        #19                 // long 1000l
        52: invokestatic  #21                 // Method java/lang/Thread.sleep:(J)V
        55: aload_1
        56: aload_2
        57: invokevirtual #22                 // Method org/kohsuke/github/GitHubClient.getRateLimit:(Lorg/kohsuke/github/RateLimitTarget;)Lorg/kohsuke/github/GHRateLimit;
        60: astore        4
        62: aload         4
        64: aload_2
        65: invokevirtual #17                 // Method org/kohsuke/github/GHRateLimit.getRecord:(Lorg/kohsuke/github/RateLimitTarget;)Lorg/kohsuke/github/GHRateLimit$Record;
        68: astore        5
        70: goto          32
        73: goto          99
        76: astore        8
        78: new           #24                 // class java/io/InterruptedIOException
        81: dup
        82: aload         8
        84: invokevirtual #25                 // Method java/lang/InterruptedException.getMessage:()Ljava/lang/String;
        87: invokespecial #26                 // Method java/io/InterruptedIOException."<init>":(Ljava/lang/String;)V
        90: aload         8
        92: invokevirtual #27                 // Method java/io/InterruptedIOException.initCause:(Ljava/lang/Throwable;)Ljava/lang/Throwable;
        95: checkcast     #28                 // class java/io/IOException
        98: athrow
        99: return
      Exception table:
         from    to  target type
            32    73    76   Class java/lang/InterruptedException
      LineNumberTable:
        line 118: 0
        line 119: 6
        line 120: 13
        line 124: 14
        line 125: 21
        line 126: 29
        line 128: 32
        line 129: 43
        line 135: 49
        line 138: 55
        line 139: 62
        line 143: 73
        line 141: 76
        line 142: 78
        line 144: 99
      LocalVariableTable:
        Start  Length  Slot  Name   Signature
           78      21     8     e   Ljava/lang/InterruptedException;
            0     100     0  this   Lorg/kohsuke/github/GitHubRateLimitChecker;
            0     100     1 client   Lorg/kohsuke/github/GitHubClient;
            0     100     2 rateLimitTarget   Lorg/kohsuke/github/RateLimitTarget;
            6      94     3 guard   Lorg/kohsuke/github/RateLimitChecker;
           21      79     4 rateLimit   Lorg/kohsuke/github/GHRateLimit;
           29      71     5 rateLimitRecord   Lorg/kohsuke/github/GHRateLimit$Record;
           32      68     6 waitCount   J
      StackMapTable: number_of_entries = 5
        frame_type = 252 /* append */
          offset_delta = 14
          locals = [ class org/kohsuke/github/RateLimitChecker ]
        frame_type = 254 /* append */
          offset_delta = 17
          locals = [ class org/kohsuke/github/GHRateLimit, class org/kohsuke/github/GHRateLimit$Record, long ]
        frame_type = 40 /* same */
        frame_type = 66 /* same_locals_1_stack_item */
          stack = [ class java/lang/InterruptedException ]
        frame_type = 22 /* same */
    Exceptions:
      throws java.io.IOException
    RuntimeVisibleParameterAnnotations:
      parameter 0:
      parameter 1:
        0: #45()
          javax.annotation.Nonnull

  private org.kohsuke.github.RateLimitChecker selectChecker(org.kohsuke.github.RateLimitTarget);
    descriptor: (Lorg/kohsuke/github/RateLimitTarget;)Lorg/kohsuke/github/RateLimitChecker;
    flags: (0x0002) ACC_PRIVATE
    Code:
      stack=4, locals=2, args_size=2
         0: aload_1
         1: getstatic     #29                 // Field org/kohsuke/github/RateLimitTarget.NONE:Lorg/kohsuke/github/RateLimitTarget;
         4: if_acmpne     11
         7: getstatic     #1                  // Field org/kohsuke/github/RateLimitChecker.NONE:Lorg/kohsuke/github/RateLimitChecker;
        10: areturn
        11: aload_1
        12: getstatic     #11                 // Field org/kohsuke/github/RateLimitTarget.CORE:Lorg/kohsuke/github/RateLimitTarget;
        15: if_acmpne     23
        18: aload_0
        19: getfield      #6                  // Field core:Lorg/kohsuke/github/RateLimitChecker;
        22: areturn
        23: aload_1
        24: getstatic     #12                 // Field org/kohsuke/github/RateLimitTarget.SEARCH:Lorg/kohsuke/github/RateLimitTarget;
        27: if_acmpne     35
        30: aload_0
        31: getfield      #7                  // Field search:Lorg/kohsuke/github/RateLimitChecker;
        34: areturn
        35: aload_1
        36: getstatic     #13                 // Field org/kohsuke/github/RateLimitTarget.GRAPHQL:Lorg/kohsuke/github/RateLimitTarget;
        39: if_acmpne     47
        42: aload_0
        43: getfield      #8                  // Field graphql:Lorg/kohsuke/github/RateLimitChecker;
        46: areturn
        47: aload_1
        48: getstatic     #14                 // Field org/kohsuke/github/RateLimitTarget.INTEGRATION_MANIFEST:Lorg/kohsuke/github/RateLimitTarget;
        51: if_acmpne     59
        54: aload_0
        55: getfield      #9                  // Field integrationManifest:Lorg/kohsuke/github/RateLimitChecker;
        58: areturn
        59: new           #30                 // class java/lang/IllegalArgumentException
        62: dup
        63: new           #31                 // class java/lang/StringBuilder
        66: dup
        67: invokespecial #32                 // Method java/lang/StringBuilder."<init>":()V
        70: ldc           #33                 // String Unknown rate limit target:
        72: invokevirtual #34                 // Method java/lang/StringBuilder.append:(Ljava/lang/String;)Ljava/lang/StringBuilder;
        75: aload_1
        76: invokevirtual #35                 // Method org/kohsuke/github/RateLimitTarget.toString:()Ljava/lang/String;
        79: invokevirtual #34                 // Method java/lang/StringBuilder.append:(Ljava/lang/String;)Ljava/lang/StringBuilder;
        82: invokevirtual #36                 // Method java/lang/StringBuilder.toString:()Ljava/lang/String;
        85: invokespecial #37                 // Method java/lang/IllegalArgumentException."<init>":(Ljava/lang/String;)V
        88: athrow
      LineNumberTable:
        line 157: 0
        line 158: 7
        line 159: 11
        line 160: 18
        line 161: 23
        line 162: 30
        line 163: 35
        line 164: 42
        line 165: 47
        line 166: 54
        line 168: 59
      LocalVariableTable:
        Start  Length  Slot  Name   Signature
            0      89     0  this   Lorg/kohsuke/github/GitHubRateLimitChecker;
            0      89     1 rateLimitTarget   Lorg/kohsuke/github/RateLimitTarget;
      StackMapTable: number_of_entries = 5
        frame_type = 11 /* same */
        frame_type = 11 /* same */
        frame_type = 11 /* same */
        frame_type = 11 /* same */
        frame_type = 11 /* same */
    RuntimeVisibleAnnotations:
      0: #45()
        javax.annotation.Nonnull
    RuntimeVisibleParameterAnnotations:
      parameter 0:
        0: #45()
          javax.annotation.Nonnull

  static {};
    descriptor: ()V
    flags: (0x0008) ACC_STATIC
    Code:
      stack=1, locals=0, args_size=0
         0: ldc           #10                 // class org/kohsuke/github/GitHubRateLimitChecker
         2: invokevirtual #38                 // Method java/lang/Class.getName:()Ljava/lang/String;
         5: invokestatic  #39                 // Method java/util/logging/Logger.getLogger:(Ljava/lang/String;)Ljava/util/logging/Logger;
         8: putstatic     #40                 // Field LOGGER:Ljava/util/logging/Logger;
        11: return
      LineNumberTable:
        line 46: 0
}
SourceFile: "GitHubRateLimitChecker.java"
InnerClasses:
  public static #78= #77 of #83;          // Record=class org/kohsuke/github/GHRateLimit$Record of class org/kohsuke/github/GHRateLimit
