Classfile /Users/mw/Projects/slang-braindump/.jar/jar11/assemble/slang-braindump/assemble/content/org/kohsuke/github/GitHubConnectorResponseErrorHandler.class
  Last modified May 29, 2022; size 887 bytes
  SHA-256 checksum 7592081255c2638e2e95e4a79f4ee4214794fb499902cddb230e3413dd836f17
  Compiled from "GitHubConnectorResponseErrorHandler.java"
abstract class org.kohsuke.github.GitHubConnectorResponseErrorHandler
  minor version: 0
  major version: 52
  flags: (0x0420) ACC_SUPER, ACC_ABSTRACT
  this_class: #5                          // org/kohsuke/github/GitHubConnectorResponseErrorHandler
  super_class: #6                         // java/lang/Object
  interfaces: 0, fields: 1, methods: 4, attributes: 2
Constant pool:
   #1 = Methodref          #6.#27         // java/lang/Object."<init>":()V
   #2 = Class              #28            // org/kohsuke/github/GitHubConnectorResponseErrorHandler$1
   #3 = Methodref          #2.#27         // org/kohsuke/github/GitHubConnectorResponseErrorHandler$1."<init>":()V
   #4 = Fieldref           #5.#29         // org/kohsuke/github/GitHubConnectorResponseErrorHandler.STATUS_HTTP_BAD_REQUEST_OR_GREATER:Lorg/kohsuke/github/GitHubConnectorResponseErrorHandler;
   #5 = Class              #30            // org/kohsuke/github/GitHubConnectorResponseErrorHandler
   #6 = Class              #31            // java/lang/Object
   #7 = Utf8               InnerClasses
   #8 = Utf8               STATUS_HTTP_BAD_REQUEST_OR_GREATER
   #9 = Utf8               Lorg/kohsuke/github/GitHubConnectorResponseErrorHandler;
  #10 = Utf8               <init>
  #11 = Utf8               ()V
  #12 = Utf8               Code
  #13 = Utf8               LineNumberTable
  #14 = Utf8               LocalVariableTable
  #15 = Utf8               this
  #16 = Utf8               isError
  #17 = Utf8               (Lorg/kohsuke/github/connector/GitHubConnectorResponse;)Z
  #18 = Utf8               Exceptions
  #19 = Class              #32            // java/io/IOException
  #20 = Utf8               RuntimeVisibleParameterAnnotations
  #21 = Utf8               Ljavax/annotation/Nonnull;
  #22 = Utf8               onError
  #23 = Utf8               (Lorg/kohsuke/github/connector/GitHubConnectorResponse;)V
  #24 = Utf8               <clinit>
  #25 = Utf8               SourceFile
  #26 = Utf8               GitHubConnectorResponseErrorHandler.java
  #27 = NameAndType        #10:#11        // "<init>":()V
  #28 = Utf8               org/kohsuke/github/GitHubConnectorResponseErrorHandler$1
  #29 = NameAndType        #8:#9          // STATUS_HTTP_BAD_REQUEST_OR_GREATER:Lorg/kohsuke/github/GitHubConnectorResponseErrorHandler;
  #30 = Utf8               org/kohsuke/github/GitHubConnectorResponseErrorHandler
  #31 = Utf8               java/lang/Object
  #32 = Utf8               java/io/IOException
{
  static org.kohsuke.github.GitHubConnectorResponseErrorHandler STATUS_HTTP_BAD_REQUEST_OR_GREATER;
    descriptor: Lorg/kohsuke/github/GitHubConnectorResponseErrorHandler;
    flags: (0x0008) ACC_STATIC

  org.kohsuke.github.GitHubConnectorResponseErrorHandler();
    descriptor: ()V
    flags: (0x0000)
    Code:
      stack=1, locals=1, args_size=1
         0: aload_0
         1: invokespecial #1                  // Method java/lang/Object."<init>":()V
         4: return
      LineNumberTable:
        line 19: 0
      LocalVariableTable:
        Start  Length  Slot  Name   Signature
            0       5     0  this   Lorg/kohsuke/github/GitHubConnectorResponseErrorHandler;

  abstract boolean isError(org.kohsuke.github.connector.GitHubConnectorResponse) throws java.io.IOException;
    descriptor: (Lorg/kohsuke/github/connector/GitHubConnectorResponse;)Z
    flags: (0x0400) ACC_ABSTRACT
    Exceptions:
      throws java.io.IOException
    RuntimeVisibleParameterAnnotations:
      parameter 0:
        0: #21()
          javax.annotation.Nonnull

  public abstract void onError(org.kohsuke.github.connector.GitHubConnectorResponse) throws java.io.IOException;
    descriptor: (Lorg/kohsuke/github/connector/GitHubConnectorResponse;)V
    flags: (0x0401) ACC_PUBLIC, ACC_ABSTRACT
    Exceptions:
      throws java.io.IOException
    RuntimeVisibleParameterAnnotations:
      parameter 0:
        0: #21()
          javax.annotation.Nonnull

  static {};
    descriptor: ()V
    flags: (0x0008) ACC_STATIC
    Code:
      stack=2, locals=0, args_size=0
         0: new           #2                  // class org/kohsuke/github/GitHubConnectorResponseErrorHandler$1
         3: dup
         4: invokespecial #3                  // Method org/kohsuke/github/GitHubConnectorResponseErrorHandler$1."<init>":()V
         7: putstatic     #4                  // Field STATUS_HTTP_BAD_REQUEST_OR_GREATER:Lorg/kohsuke/github/GitHubConnectorResponseErrorHandler;
        10: return
      LineNumberTable:
        line 45: 0
}
SourceFile: "GitHubConnectorResponseErrorHandler.java"
InnerClasses:
  #2;                                     // class org/kohsuke/github/GitHubConnectorResponseErrorHandler$1
