Classfile /Users/mw/Projects/slang-braindump/.jar/jar11/assemble/slang-braindump/assemble/content/org/kohsuke/github/GitHubClient$GHApiInfo.class
  Last modified May 29, 2022; size 911 bytes
  SHA-256 checksum 91f8581e9e1783cb01f8709071711cd0bb9e7e546971a96f5dea5c9da130d1ca
  Compiled from "GitHubClient.java"
class org.kohsuke.github.GitHubClient$GHApiInfo
  minor version: 0
  major version: 52
  flags: (0x0020) ACC_SUPER
  this_class: #12                         // org/kohsuke/github/GitHubClient$GHApiInfo
  super_class: #13                        // java/lang/Object
  interfaces: 0, fields: 1, methods: 2, attributes: 2
Constant pool:
   #1 = Methodref          #13.#32        // java/lang/Object."<init>":()V
   #2 = Fieldref           #12.#33        // org/kohsuke/github/GitHubClient$GHApiInfo.rate_limit_url:Ljava/lang/String;
   #3 = Class              #34            // java/io/IOException
   #4 = Class              #35            // java/lang/StringBuilder
   #5 = Methodref          #4.#32         // java/lang/StringBuilder."<init>":()V
   #6 = Methodref          #4.#36         // java/lang/StringBuilder.append:(Ljava/lang/String;)Ljava/lang/StringBuilder;
   #7 = String             #37            //  doesn\'t look like GitHub API URL
   #8 = Methodref          #4.#38         // java/lang/StringBuilder.toString:()Ljava/lang/String;
   #9 = Methodref          #3.#39         // java/io/IOException."<init>":(Ljava/lang/String;)V
  #10 = Class              #40            // java/net/URL
  #11 = Methodref          #10.#39        // java/net/URL."<init>":(Ljava/lang/String;)V
  #12 = Class              #42            // org/kohsuke/github/GitHubClient$GHApiInfo
  #13 = Class              #43            // java/lang/Object
  #14 = Utf8               rate_limit_url
  #15 = Utf8               Ljava/lang/String;
  #16 = Utf8               <init>
  #17 = Utf8               ()V
  #18 = Utf8               Code
  #19 = Utf8               LineNumberTable
  #20 = Utf8               LocalVariableTable
  #21 = Utf8               this
  #22 = Utf8               GHApiInfo
  #23 = Utf8               InnerClasses
  #24 = Utf8               Lorg/kohsuke/github/GitHubClient$GHApiInfo;
  #25 = Utf8               check
  #26 = Utf8               (Ljava/lang/String;)V
  #27 = Utf8               apiUrl
  #28 = Utf8               StackMapTable
  #29 = Utf8               Exceptions
  #30 = Utf8               SourceFile
  #31 = Utf8               GitHubClient.java
  #32 = NameAndType        #16:#17        // "<init>":()V
  #33 = NameAndType        #14:#15        // rate_limit_url:Ljava/lang/String;
  #34 = Utf8               java/io/IOException
  #35 = Utf8               java/lang/StringBuilder
  #36 = NameAndType        #44:#45        // append:(Ljava/lang/String;)Ljava/lang/StringBuilder;
  #37 = Utf8                doesn\'t look like GitHub API URL
  #38 = NameAndType        #46:#47        // toString:()Ljava/lang/String;
  #39 = NameAndType        #16:#26        // "<init>":(Ljava/lang/String;)V
  #40 = Utf8               java/net/URL
  #41 = Class              #48            // org/kohsuke/github/GitHubClient
  #42 = Utf8               org/kohsuke/github/GitHubClient$GHApiInfo
  #43 = Utf8               java/lang/Object
  #44 = Utf8               append
  #45 = Utf8               (Ljava/lang/String;)Ljava/lang/StringBuilder;
  #46 = Utf8               toString
  #47 = Utf8               ()Ljava/lang/String;
  #48 = Utf8               org/kohsuke/github/GitHubClient
{
  private java.lang.String rate_limit_url;
    descriptor: Ljava/lang/String;
    flags: (0x0002) ACC_PRIVATE

  private org.kohsuke.github.GitHubClient$GHApiInfo();
    descriptor: ()V
    flags: (0x0002) ACC_PRIVATE
    Code:
      stack=1, locals=1, args_size=1
         0: aload_0
         1: invokespecial #1                  // Method java/lang/Object."<init>":()V
         4: return
      LineNumberTable:
        line 621: 0
      LocalVariableTable:
        Start  Length  Slot  Name   Signature
            0       5     0  this   Lorg/kohsuke/github/GitHubClient$GHApiInfo;

  void check(java.lang.String) throws java.io.IOException;
    descriptor: (Ljava/lang/String;)V
    flags: (0x0000)
    Code:
      stack=4, locals=2, args_size=2
         0: aload_0
         1: getfield      #2                  // Field rate_limit_url:Ljava/lang/String;
         4: ifnonnull     34
         7: new           #3                  // class java/io/IOException
        10: dup
        11: new           #4                  // class java/lang/StringBuilder
        14: dup
        15: invokespecial #5                  // Method java/lang/StringBuilder."<init>":()V
        18: aload_1
        19: invokevirtual #6                  // Method java/lang/StringBuilder.append:(Ljava/lang/String;)Ljava/lang/StringBuilder;
        22: ldc           #7                  // String  doesn\'t look like GitHub API URL
        24: invokevirtual #6                  // Method java/lang/StringBuilder.append:(Ljava/lang/String;)Ljava/lang/StringBuilder;
        27: invokevirtual #8                  // Method java/lang/StringBuilder.toString:()Ljava/lang/String;
        30: invokespecial #9                  // Method java/io/IOException."<init>":(Ljava/lang/String;)V
        33: athrow
        34: new           #10                 // class java/net/URL
        37: dup
        38: aload_0
        39: getfield      #2                  // Field rate_limit_url:Ljava/lang/String;
        42: invokespecial #11                 // Method java/net/URL."<init>":(Ljava/lang/String;)V
        45: pop
        46: return
      LineNumberTable:
        line 625: 0
        line 626: 7
        line 629: 34
        line 630: 46
      LocalVariableTable:
        Start  Length  Slot  Name   Signature
            0      47     0  this   Lorg/kohsuke/github/GitHubClient$GHApiInfo;
            0      47     1 apiUrl   Ljava/lang/String;
      StackMapTable: number_of_entries = 1
        frame_type = 34 /* same */
    Exceptions:
      throws java.io.IOException
}
SourceFile: "GitHubClient.java"
InnerClasses:
  private static #22= #12 of #41;         // GHApiInfo=class org/kohsuke/github/GitHubClient$GHApiInfo of class org/kohsuke/github/GitHubClient
