Classfile /Users/mw/Projects/slang-braindump/.jar/jar11/assemble/slang-braindump/assemble/content/org/kohsuke/github/Requester.class
  Last modified May 29, 2022; size 5880 bytes
  SHA-256 checksum f3a38b379c6e478863e589b4ce09d0913c883bebe9eba0f8c4f30fe2f7a272f0
  Compiled from "Requester.java"
class org.kohsuke.github.Requester extends org.kohsuke.github.GitHubRequest$Builder<org.kohsuke.github.Requester>
  minor version: 0
  major version: 52
  flags: (0x0020) ACC_SUPER
  this_class: #24                         // org/kohsuke/github/Requester
  super_class: #25                        // org/kohsuke/github/GitHubRequest$Builder
  interfaces: 0, fields: 1, methods: 12, attributes: 4
Constant pool:
    #1 = Methodref          #25.#91       // org/kohsuke/github/GitHubRequest$Builder."<init>":()V
    #2 = Fieldref           #24.#92       // org/kohsuke/github/Requester.client:Lorg/kohsuke/github/GitHubClient;
    #3 = Methodref          #93.#94       // org/kohsuke/github/GitHubClient.getApiUrl:()Ljava/lang/String;
    #4 = Methodref          #24.#95       // org/kohsuke/github/Requester.withApiUrl:(Ljava/lang/String;)Lorg/kohsuke/github/GitHubRequest$Builder;
    #5 = InvokeDynamic      #0:#101       // #0:apply:()Lorg/kohsuke/github/GitHubClient$BodyHandler;
    #6 = Methodref          #93.#102      // org/kohsuke/github/GitHubClient.sendRequest:(Lorg/kohsuke/github/GitHubRequest$Builder;Lorg/kohsuke/github/GitHubClient$BodyHandler;)Lorg/kohsuke/github/GitHubResponse;
    #7 = InvokeDynamic      #1:#105       // #1:apply:(Ljava/lang/Class;)Lorg/kohsuke/github/GitHubClient$BodyHandler;
    #8 = Methodref          #106.#107     // org/kohsuke/github/GitHubResponse.body:()Ljava/lang/Object;
    #9 = InvokeDynamic      #2:#109       // #2:apply:(Ljava/lang/Object;)Lorg/kohsuke/github/GitHubClient$BodyHandler;
   #10 = Methodref          #24.#110      // org/kohsuke/github/Requester.build:()Lorg/kohsuke/github/GitHubRequest;
   #11 = Methodref          #93.#111      // org/kohsuke/github/GitHubClient.sendRequest:(Lorg/kohsuke/github/GitHubRequest;Lorg/kohsuke/github/GitHubClient$BodyHandler;)Lorg/kohsuke/github/GitHubResponse;
   #12 = Methodref          #106.#112     // org/kohsuke/github/GitHubResponse.statusCode:()I
   #13 = InvokeDynamic      #3:#114       // #3:apply:(Lorg/kohsuke/github/function/InputStreamFunction;)Lorg/kohsuke/github/GitHubClient$BodyHandler;
   #14 = Class              #115          // java/io/ByteArrayInputStream
   #15 = Methodref          #116.#117     // org/apache/commons/io/IOUtils.toByteArray:(Ljava/io/InputStream;)[B
   #16 = Methodref          #14.#118      // java/io/ByteArrayInputStream."<init>":([B)V
   #17 = Class              #119          // org/kohsuke/github/GitHubPageContentsIterable
   #18 = Methodref          #17.#120      // org/kohsuke/github/GitHubPageContentsIterable."<init>":(Lorg/kohsuke/github/GitHubClient;Lorg/kohsuke/github/GitHubRequest;Ljava/lang/Class;Ljava/util/function/Consumer;)V
   #19 = Methodref          #121.#122     // org/kohsuke/github/connector/GitHubConnectorResponse.bodyStream:()Ljava/io/InputStream;
   #20 = InterfaceMethodref #123.#124     // org/kohsuke/github/function/InputStreamFunction.apply:(Ljava/lang/Object;)Ljava/lang/Object;
   #21 = Methodref          #106.#125     // org/kohsuke/github/GitHubResponse.parseBody:(Lorg/kohsuke/github/connector/GitHubConnectorResponse;Ljava/lang/Object;)Ljava/lang/Object;
   #22 = Methodref          #106.#126     // org/kohsuke/github/GitHubResponse.parseBody:(Lorg/kohsuke/github/connector/GitHubConnectorResponse;Ljava/lang/Class;)Ljava/lang/Object;
   #23 = Methodref          #106.#127     // org/kohsuke/github/GitHubResponse.getBodyAsString:(Lorg/kohsuke/github/connector/GitHubConnectorResponse;)Ljava/lang/String;
   #24 = Class              #128          // org/kohsuke/github/Requester
   #25 = Class              #130          // org/kohsuke/github/GitHubRequest$Builder
   #26 = Utf8               client
   #27 = Utf8               Lorg/kohsuke/github/GitHubClient;
   #28 = Utf8               <init>
   #29 = Utf8               (Lorg/kohsuke/github/GitHubClient;)V
   #30 = Utf8               Code
   #31 = Utf8               LineNumberTable
   #32 = Utf8               LocalVariableTable
   #33 = Utf8               this
   #34 = Utf8               Lorg/kohsuke/github/Requester;
   #35 = Utf8               send
   #36 = Utf8               ()V
   #37 = Utf8               Exceptions
   #38 = Class              #131          // java/io/IOException
   #39 = Utf8               fetch
   #40 = Utf8               (Ljava/lang/Class;)Ljava/lang/Object;
   #41 = Utf8               type
   #42 = Utf8               Ljava/lang/Class;
   #43 = Utf8               LocalVariableTypeTable
   #44 = Utf8               Ljava/lang/Class<TT;>;
   #45 = Utf8               Signature
   #46 = Utf8               <T:Ljava/lang/Object;>(Ljava/lang/Class<TT;>;)TT;
   #47 = Utf8               RuntimeVisibleParameterAnnotations
   #48 = Utf8               Ljavax/annotation/Nonnull;
   #49 = Utf8               fetchInto
   #50 = Utf8               (Ljava/lang/Object;)Ljava/lang/Object;
   #51 = Utf8               existingInstance
   #52 = Utf8               Ljava/lang/Object;
   #53 = Utf8               TT;
   #54 = Utf8               <T:Ljava/lang/Object;>(TT;)TT;
   #55 = Utf8               fetchHttpStatusCode
   #56 = Utf8               ()I
   #57 = Utf8               fetchStream
   #58 = Utf8               (Lorg/kohsuke/github/function/InputStreamFunction;)Ljava/lang/Object;
   #59 = Utf8               handler
   #60 = Utf8               Lorg/kohsuke/github/function/InputStreamFunction;
   #61 = Utf8               Lorg/kohsuke/github/function/InputStreamFunction<TT;>;
   #62 = Utf8               <T:Ljava/lang/Object;>(Lorg/kohsuke/github/function/InputStreamFunction<TT;>;)TT;
   #63 = Utf8               copyInputStream
   #64 = Utf8               (Ljava/io/InputStream;)Ljava/io/InputStream;
   #65 = Utf8               inputStream
   #66 = Utf8               Ljava/io/InputStream;
   #67 = Utf8               RuntimeInvisibleAnnotations
   #68 = Utf8               Ledu/umd/cs/findbugs/annotations/NonNull;
   #69 = Utf8               toIterable
   #70 = Utf8               (Ljava/lang/Class;Ljava/util/function/Consumer;)Lorg/kohsuke/github/PagedIterable;
   #71 = Utf8               itemInitializer
   #72 = Utf8               Ljava/util/function/Consumer;
   #73 = Utf8               Ljava/lang/Class<[TR;>;
   #74 = Utf8               Ljava/util/function/Consumer<TR;>;
   #75 = Utf8               <R:Ljava/lang/Object;>(Ljava/lang/Class<[TR;>;Ljava/util/function/Consumer<TR;>;)Lorg/kohsuke/github/PagedIterable<TR;>;
   #76 = Utf8               lambda$fetchStream$3
   #77 = Utf8               (Lorg/kohsuke/github/function/InputStreamFunction;Lorg/kohsuke/github/connector/GitHubConnectorResponse;)Ljava/lang/Object;
   #78 = Utf8               connectorResponse
   #79 = Utf8               Lorg/kohsuke/github/connector/GitHubConnectorResponse;
   #80 = Utf8               lambda$fetchInto$2
   #81 = Utf8               (Ljava/lang/Object;Lorg/kohsuke/github/connector/GitHubConnectorResponse;)Ljava/lang/Object;
   #82 = Utf8               lambda$fetch$1
   #83 = Utf8               (Ljava/lang/Class;Lorg/kohsuke/github/connector/GitHubConnectorResponse;)Ljava/lang/Object;
   #84 = Utf8               lambda$send$0
   #85 = Utf8               (Lorg/kohsuke/github/connector/GitHubConnectorResponse;)Ljava/lang/String;
   #86 = Utf8               Builder
   #87 = Utf8               InnerClasses
   #88 = Utf8               Lorg/kohsuke/github/GitHubRequest$Builder<Lorg/kohsuke/github/Requester;>;
   #89 = Utf8               SourceFile
   #90 = Utf8               Requester.java
   #91 = NameAndType        #28:#36       // "<init>":()V
   #92 = NameAndType        #26:#27       // client:Lorg/kohsuke/github/GitHubClient;
   #93 = Class              #132          // org/kohsuke/github/GitHubClient
   #94 = NameAndType        #133:#134     // getApiUrl:()Ljava/lang/String;
   #95 = NameAndType        #135:#136     // withApiUrl:(Ljava/lang/String;)Lorg/kohsuke/github/GitHubRequest$Builder;
   #96 = Utf8               BootstrapMethods
   #97 = MethodHandle       6:#137        // REF_invokeStatic java/lang/invoke/LambdaMetafactory.metafactory:(Ljava/lang/invoke/MethodHandles$Lookup;Ljava/lang/String;Ljava/lang/invoke/MethodType;Ljava/lang/invoke/MethodType;Ljava/lang/invoke/MethodHandle;Ljava/lang/invoke/MethodType;)Ljava/lang/invoke/CallSite;
   #98 = MethodType         #50           //  (Ljava/lang/Object;)Ljava/lang/Object;
   #99 = MethodHandle       6:#138        // REF_invokeStatic org/kohsuke/github/Requester.lambda$send$0:(Lorg/kohsuke/github/connector/GitHubConnectorResponse;)Ljava/lang/String;
  #100 = MethodType         #85           //  (Lorg/kohsuke/github/connector/GitHubConnectorResponse;)Ljava/lang/String;
  #101 = NameAndType        #139:#142     // apply:()Lorg/kohsuke/github/GitHubClient$BodyHandler;
  #102 = NameAndType        #143:#144     // sendRequest:(Lorg/kohsuke/github/GitHubRequest$Builder;Lorg/kohsuke/github/GitHubClient$BodyHandler;)Lorg/kohsuke/github/GitHubResponse;
  #103 = MethodHandle       6:#145        // REF_invokeStatic org/kohsuke/github/Requester.lambda$fetch$1:(Ljava/lang/Class;Lorg/kohsuke/github/connector/GitHubConnectorResponse;)Ljava/lang/Object;
  #104 = MethodType         #146          //  (Lorg/kohsuke/github/connector/GitHubConnectorResponse;)Ljava/lang/Object;
  #105 = NameAndType        #139:#147     // apply:(Ljava/lang/Class;)Lorg/kohsuke/github/GitHubClient$BodyHandler;
  #106 = Class              #148          // org/kohsuke/github/GitHubResponse
  #107 = NameAndType        #149:#150     // body:()Ljava/lang/Object;
  #108 = MethodHandle       6:#151        // REF_invokeStatic org/kohsuke/github/Requester.lambda$fetchInto$2:(Ljava/lang/Object;Lorg/kohsuke/github/connector/GitHubConnectorResponse;)Ljava/lang/Object;
  #109 = NameAndType        #139:#152     // apply:(Ljava/lang/Object;)Lorg/kohsuke/github/GitHubClient$BodyHandler;
  #110 = NameAndType        #153:#154     // build:()Lorg/kohsuke/github/GitHubRequest;
  #111 = NameAndType        #143:#155     // sendRequest:(Lorg/kohsuke/github/GitHubRequest;Lorg/kohsuke/github/GitHubClient$BodyHandler;)Lorg/kohsuke/github/GitHubResponse;
  #112 = NameAndType        #156:#56      // statusCode:()I
  #113 = MethodHandle       6:#157        // REF_invokeStatic org/kohsuke/github/Requester.lambda$fetchStream$3:(Lorg/kohsuke/github/function/InputStreamFunction;Lorg/kohsuke/github/connector/GitHubConnectorResponse;)Ljava/lang/Object;
  #114 = NameAndType        #139:#158     // apply:(Lorg/kohsuke/github/function/InputStreamFunction;)Lorg/kohsuke/github/GitHubClient$BodyHandler;
  #115 = Utf8               java/io/ByteArrayInputStream
  #116 = Class              #159          // org/apache/commons/io/IOUtils
  #117 = NameAndType        #160:#161     // toByteArray:(Ljava/io/InputStream;)[B
  #118 = NameAndType        #28:#162      // "<init>":([B)V
  #119 = Utf8               org/kohsuke/github/GitHubPageContentsIterable
  #120 = NameAndType        #28:#163      // "<init>":(Lorg/kohsuke/github/GitHubClient;Lorg/kohsuke/github/GitHubRequest;Ljava/lang/Class;Ljava/util/function/Consumer;)V
  #121 = Class              #164          // org/kohsuke/github/connector/GitHubConnectorResponse
  #122 = NameAndType        #165:#166     // bodyStream:()Ljava/io/InputStream;
  #123 = Class              #167          // org/kohsuke/github/function/InputStreamFunction
  #124 = NameAndType        #139:#50      // apply:(Ljava/lang/Object;)Ljava/lang/Object;
  #125 = NameAndType        #168:#169     // parseBody:(Lorg/kohsuke/github/connector/GitHubConnectorResponse;Ljava/lang/Object;)Ljava/lang/Object;
  #126 = NameAndType        #168:#170     // parseBody:(Lorg/kohsuke/github/connector/GitHubConnectorResponse;Ljava/lang/Class;)Ljava/lang/Object;
  #127 = NameAndType        #171:#85      // getBodyAsString:(Lorg/kohsuke/github/connector/GitHubConnectorResponse;)Ljava/lang/String;
  #128 = Utf8               org/kohsuke/github/Requester
  #129 = Class              #172          // org/kohsuke/github/GitHubRequest
  #130 = Utf8               org/kohsuke/github/GitHubRequest$Builder
  #131 = Utf8               java/io/IOException
  #132 = Utf8               org/kohsuke/github/GitHubClient
  #133 = Utf8               getApiUrl
  #134 = Utf8               ()Ljava/lang/String;
  #135 = Utf8               withApiUrl
  #136 = Utf8               (Ljava/lang/String;)Lorg/kohsuke/github/GitHubRequest$Builder;
  #137 = Methodref          #173.#174     // java/lang/invoke/LambdaMetafactory.metafactory:(Ljava/lang/invoke/MethodHandles$Lookup;Ljava/lang/String;Ljava/lang/invoke/MethodType;Ljava/lang/invoke/MethodType;Ljava/lang/invoke/MethodHandle;Ljava/lang/invoke/MethodType;)Ljava/lang/invoke/CallSite;
  #138 = Methodref          #24.#175      // org/kohsuke/github/Requester.lambda$send$0:(Lorg/kohsuke/github/connector/GitHubConnectorResponse;)Ljava/lang/String;
  #139 = Utf8               apply
  #140 = Class              #176          // org/kohsuke/github/GitHubClient$BodyHandler
  #141 = Utf8               BodyHandler
  #142 = Utf8               ()Lorg/kohsuke/github/GitHubClient$BodyHandler;
  #143 = Utf8               sendRequest
  #144 = Utf8               (Lorg/kohsuke/github/GitHubRequest$Builder;Lorg/kohsuke/github/GitHubClient$BodyHandler;)Lorg/kohsuke/github/GitHubResponse;
  #145 = Methodref          #24.#177      // org/kohsuke/github/Requester.lambda$fetch$1:(Ljava/lang/Class;Lorg/kohsuke/github/connector/GitHubConnectorResponse;)Ljava/lang/Object;
  #146 = Utf8               (Lorg/kohsuke/github/connector/GitHubConnectorResponse;)Ljava/lang/Object;
  #147 = Utf8               (Ljava/lang/Class;)Lorg/kohsuke/github/GitHubClient$BodyHandler;
  #148 = Utf8               org/kohsuke/github/GitHubResponse
  #149 = Utf8               body
  #150 = Utf8               ()Ljava/lang/Object;
  #151 = Methodref          #24.#178      // org/kohsuke/github/Requester.lambda$fetchInto$2:(Ljava/lang/Object;Lorg/kohsuke/github/connector/GitHubConnectorResponse;)Ljava/lang/Object;
  #152 = Utf8               (Ljava/lang/Object;)Lorg/kohsuke/github/GitHubClient$BodyHandler;
  #153 = Utf8               build
  #154 = Utf8               ()Lorg/kohsuke/github/GitHubRequest;
  #155 = Utf8               (Lorg/kohsuke/github/GitHubRequest;Lorg/kohsuke/github/GitHubClient$BodyHandler;)Lorg/kohsuke/github/GitHubResponse;
  #156 = Utf8               statusCode
  #157 = Methodref          #24.#179      // org/kohsuke/github/Requester.lambda$fetchStream$3:(Lorg/kohsuke/github/function/InputStreamFunction;Lorg/kohsuke/github/connector/GitHubConnectorResponse;)Ljava/lang/Object;
  #158 = Utf8               (Lorg/kohsuke/github/function/InputStreamFunction;)Lorg/kohsuke/github/GitHubClient$BodyHandler;
  #159 = Utf8               org/apache/commons/io/IOUtils
  #160 = Utf8               toByteArray
  #161 = Utf8               (Ljava/io/InputStream;)[B
  #162 = Utf8               ([B)V
  #163 = Utf8               (Lorg/kohsuke/github/GitHubClient;Lorg/kohsuke/github/GitHubRequest;Ljava/lang/Class;Ljava/util/function/Consumer;)V
  #164 = Utf8               org/kohsuke/github/connector/GitHubConnectorResponse
  #165 = Utf8               bodyStream
  #166 = Utf8               ()Ljava/io/InputStream;
  #167 = Utf8               org/kohsuke/github/function/InputStreamFunction
  #168 = Utf8               parseBody
  #169 = Utf8               (Lorg/kohsuke/github/connector/GitHubConnectorResponse;Ljava/lang/Object;)Ljava/lang/Object;
  #170 = Utf8               (Lorg/kohsuke/github/connector/GitHubConnectorResponse;Ljava/lang/Class;)Ljava/lang/Object;
  #171 = Utf8               getBodyAsString
  #172 = Utf8               org/kohsuke/github/GitHubRequest
  #173 = Class              #180          // java/lang/invoke/LambdaMetafactory
  #174 = NameAndType        #181:#184     // metafactory:(Ljava/lang/invoke/MethodHandles$Lookup;Ljava/lang/String;Ljava/lang/invoke/MethodType;Ljava/lang/invoke/MethodType;Ljava/lang/invoke/MethodHandle;Ljava/lang/invoke/MethodType;)Ljava/lang/invoke/CallSite;
  #175 = NameAndType        #84:#85       // lambda$send$0:(Lorg/kohsuke/github/connector/GitHubConnectorResponse;)Ljava/lang/String;
  #176 = Utf8               org/kohsuke/github/GitHubClient$BodyHandler
  #177 = NameAndType        #82:#83       // lambda$fetch$1:(Ljava/lang/Class;Lorg/kohsuke/github/connector/GitHubConnectorResponse;)Ljava/lang/Object;
  #178 = NameAndType        #80:#81       // lambda$fetchInto$2:(Ljava/lang/Object;Lorg/kohsuke/github/connector/GitHubConnectorResponse;)Ljava/lang/Object;
  #179 = NameAndType        #76:#77       // lambda$fetchStream$3:(Lorg/kohsuke/github/function/InputStreamFunction;Lorg/kohsuke/github/connector/GitHubConnectorResponse;)Ljava/lang/Object;
  #180 = Utf8               java/lang/invoke/LambdaMetafactory
  #181 = Utf8               metafactory
  #182 = Class              #186          // java/lang/invoke/MethodHandles$Lookup
  #183 = Utf8               Lookup
  #184 = Utf8               (Ljava/lang/invoke/MethodHandles$Lookup;Ljava/lang/String;Ljava/lang/invoke/MethodType;Ljava/lang/invoke/MethodType;Ljava/lang/invoke/MethodHandle;Ljava/lang/invoke/MethodType;)Ljava/lang/invoke/CallSite;
  #185 = Class              #187          // java/lang/invoke/MethodHandles
  #186 = Utf8               java/lang/invoke/MethodHandles$Lookup
  #187 = Utf8               java/lang/invoke/MethodHandles
{
  final transient org.kohsuke.github.GitHubClient client;
    descriptor: Lorg/kohsuke/github/GitHubClient;
    flags: (0x0090) ACC_FINAL, ACC_TRANSIENT

  org.kohsuke.github.Requester(org.kohsuke.github.GitHubClient);
    descriptor: (Lorg/kohsuke/github/GitHubClient;)V
    flags: (0x0000)
    Code:
      stack=2, locals=2, args_size=2
         0: aload_0
         1: invokespecial #1                  // Method org/kohsuke/github/GitHubRequest$Builder."<init>":()V
         4: aload_0
         5: aload_1
         6: putfield      #2                  // Field client:Lorg/kohsuke/github/GitHubClient;
         9: aload_0
        10: aload_1
        11: invokevirtual #3                  // Method org/kohsuke/github/GitHubClient.getApiUrl:()Ljava/lang/String;
        14: invokevirtual #4                  // Method withApiUrl:(Ljava/lang/String;)Lorg/kohsuke/github/GitHubRequest$Builder;
        17: pop
        18: return
      LineNumberTable:
        line 47: 0
        line 48: 4
        line 49: 9
        line 50: 18
      LocalVariableTable:
        Start  Length  Slot  Name   Signature
            0      19     0  this   Lorg/kohsuke/github/Requester;
            0      19     1 client   Lorg/kohsuke/github/GitHubClient;

  public void send() throws java.io.IOException;
    descriptor: ()V
    flags: (0x0001) ACC_PUBLIC
    Code:
      stack=3, locals=1, args_size=1
         0: aload_0
         1: getfield      #2                  // Field client:Lorg/kohsuke/github/GitHubClient;
         4: aload_0
         5: invokedynamic #5,  0              // InvokeDynamic #0:apply:()Lorg/kohsuke/github/GitHubClient$BodyHandler;
        10: invokevirtual #6                  // Method org/kohsuke/github/GitHubClient.sendRequest:(Lorg/kohsuke/github/GitHubRequest$Builder;Lorg/kohsuke/github/GitHubClient$BodyHandler;)Lorg/kohsuke/github/GitHubResponse;
        13: pop
        14: return
      LineNumberTable:
        line 61: 0
        line 62: 14
      LocalVariableTable:
        Start  Length  Slot  Name   Signature
            0      15     0  this   Lorg/kohsuke/github/Requester;
    Exceptions:
      throws java.io.IOException

  public <T extends java.lang.Object> T fetch(java.lang.Class<T>) throws java.io.IOException;
    descriptor: (Ljava/lang/Class;)Ljava/lang/Object;
    flags: (0x0001) ACC_PUBLIC
    Code:
      stack=3, locals=2, args_size=2
         0: aload_0
         1: getfield      #2                  // Field client:Lorg/kohsuke/github/GitHubClient;
         4: aload_0
         5: aload_1
         6: invokedynamic #7,  0              // InvokeDynamic #1:apply:(Ljava/lang/Class;)Lorg/kohsuke/github/GitHubClient$BodyHandler;
        11: invokevirtual #6                  // Method org/kohsuke/github/GitHubClient.sendRequest:(Lorg/kohsuke/github/GitHubRequest$Builder;Lorg/kohsuke/github/GitHubClient$BodyHandler;)Lorg/kohsuke/github/GitHubResponse;
        14: invokevirtual #8                  // Method org/kohsuke/github/GitHubResponse.body:()Ljava/lang/Object;
        17: areturn
      LineNumberTable:
        line 76: 0
        line 77: 14
        line 76: 17
      LocalVariableTable:
        Start  Length  Slot  Name   Signature
            0      18     0  this   Lorg/kohsuke/github/Requester;
            0      18     1  type   Ljava/lang/Class;
      LocalVariableTypeTable:
        Start  Length  Slot  Name   Signature
            0      18     1  type   Ljava/lang/Class<TT;>;
    Exceptions:
      throws java.io.IOException
    Signature: #46                          // <T:Ljava/lang/Object;>(Ljava/lang/Class<TT;>;)TT;
    RuntimeVisibleParameterAnnotations:
      parameter 0:
        0: #48()
          javax.annotation.Nonnull

  public <T extends java.lang.Object> T fetchInto(T) throws java.io.IOException;
    descriptor: (Ljava/lang/Object;)Ljava/lang/Object;
    flags: (0x0001) ACC_PUBLIC
    Code:
      stack=3, locals=2, args_size=2
         0: aload_0
         1: getfield      #2                  // Field client:Lorg/kohsuke/github/GitHubClient;
         4: aload_0
         5: aload_1
         6: invokedynamic #9,  0              // InvokeDynamic #2:apply:(Ljava/lang/Object;)Lorg/kohsuke/github/GitHubClient$BodyHandler;
        11: invokevirtual #6                  // Method org/kohsuke/github/GitHubClient.sendRequest:(Lorg/kohsuke/github/GitHubRequest$Builder;Lorg/kohsuke/github/GitHubClient$BodyHandler;)Lorg/kohsuke/github/GitHubResponse;
        14: invokevirtual #8                  // Method org/kohsuke/github/GitHubResponse.body:()Ljava/lang/Object;
        17: areturn
      LineNumberTable:
        line 92: 0
        line 93: 11
        line 94: 14
        line 92: 17
      LocalVariableTable:
        Start  Length  Slot  Name   Signature
            0      18     0  this   Lorg/kohsuke/github/Requester;
            0      18     1 existingInstance   Ljava/lang/Object;
      LocalVariableTypeTable:
        Start  Length  Slot  Name   Signature
            0      18     1 existingInstance   TT;
    Exceptions:
      throws java.io.IOException
    Signature: #54                          // <T:Ljava/lang/Object;>(TT;)TT;
    RuntimeVisibleParameterAnnotations:
      parameter 0:
        0: #48()
          javax.annotation.Nonnull

  public int fetchHttpStatusCode() throws java.io.IOException;
    descriptor: ()I
    flags: (0x0001) ACC_PUBLIC
    Code:
      stack=3, locals=1, args_size=1
         0: aload_0
         1: getfield      #2                  // Field client:Lorg/kohsuke/github/GitHubClient;
         4: aload_0
         5: invokevirtual #10                 // Method build:()Lorg/kohsuke/github/GitHubRequest;
         8: aconst_null
         9: invokevirtual #11                 // Method org/kohsuke/github/GitHubClient.sendRequest:(Lorg/kohsuke/github/GitHubRequest;Lorg/kohsuke/github/GitHubClient$BodyHandler;)Lorg/kohsuke/github/GitHubResponse;
        12: invokevirtual #12                 // Method org/kohsuke/github/GitHubResponse.statusCode:()I
        15: ireturn
      LineNumberTable:
        line 106: 0
      LocalVariableTable:
        Start  Length  Slot  Name   Signature
            0      16     0  this   Lorg/kohsuke/github/Requester;
    Exceptions:
      throws java.io.IOException

  public <T extends java.lang.Object> T fetchStream(org.kohsuke.github.function.InputStreamFunction<T>) throws java.io.IOException;
    descriptor: (Lorg/kohsuke/github/function/InputStreamFunction;)Ljava/lang/Object;
    flags: (0x0001) ACC_PUBLIC
    Code:
      stack=3, locals=2, args_size=2
         0: aload_0
         1: getfield      #2                  // Field client:Lorg/kohsuke/github/GitHubClient;
         4: aload_0
         5: aload_1
         6: invokedynamic #13,  0             // InvokeDynamic #3:apply:(Lorg/kohsuke/github/function/InputStreamFunction;)Lorg/kohsuke/github/GitHubClient$BodyHandler;
        11: invokevirtual #6                  // Method org/kohsuke/github/GitHubClient.sendRequest:(Lorg/kohsuke/github/GitHubRequest$Builder;Lorg/kohsuke/github/GitHubClient$BodyHandler;)Lorg/kohsuke/github/GitHubResponse;
        14: invokevirtual #8                  // Method org/kohsuke/github/GitHubResponse.body:()Ljava/lang/Object;
        17: areturn
      LineNumberTable:
        line 117: 0
      LocalVariableTable:
        Start  Length  Slot  Name   Signature
            0      18     0  this   Lorg/kohsuke/github/Requester;
            0      18     1 handler   Lorg/kohsuke/github/function/InputStreamFunction;
      LocalVariableTypeTable:
        Start  Length  Slot  Name   Signature
            0      18     1 handler   Lorg/kohsuke/github/function/InputStreamFunction<TT;>;
    Exceptions:
      throws java.io.IOException
    Signature: #62                          // <T:Ljava/lang/Object;>(Lorg/kohsuke/github/function/InputStreamFunction<TT;>;)TT;
    RuntimeVisibleParameterAnnotations:
      parameter 0:
        0: #48()
          javax.annotation.Nonnull

  public static java.io.InputStream copyInputStream(java.io.InputStream) throws java.io.IOException;
    descriptor: (Ljava/io/InputStream;)Ljava/io/InputStream;
    flags: (0x0009) ACC_PUBLIC, ACC_STATIC
    Code:
      stack=3, locals=1, args_size=1
         0: new           #14                 // class java/io/ByteArrayInputStream
         3: dup
         4: aload_0
         5: invokestatic  #15                 // Method org/apache/commons/io/IOUtils.toByteArray:(Ljava/io/InputStream;)[B
         8: invokespecial #16                 // Method java/io/ByteArrayInputStream."<init>":([B)V
        11: areturn
      LineNumberTable:
        line 137: 0
      LocalVariableTable:
        Start  Length  Slot  Name   Signature
            0      12     0 inputStream   Ljava/io/InputStream;
    Exceptions:
      throws java.io.IOException
    RuntimeInvisibleAnnotations:
      0: #68()
        edu.umd.cs.findbugs.annotations.NonNull

  public <R extends java.lang.Object> org.kohsuke.github.PagedIterable<R> toIterable(java.lang.Class<R[]>, java.util.function.Consumer<R>);
    descriptor: (Ljava/lang/Class;Ljava/util/function/Consumer;)Lorg/kohsuke/github/PagedIterable;
    flags: (0x0001) ACC_PUBLIC
    Code:
      stack=6, locals=3, args_size=3
         0: new           #17                 // class org/kohsuke/github/GitHubPageContentsIterable
         3: dup
         4: aload_0
         5: getfield      #2                  // Field client:Lorg/kohsuke/github/GitHubClient;
         8: aload_0
         9: invokevirtual #10                 // Method build:()Lorg/kohsuke/github/GitHubRequest;
        12: aload_1
        13: aload_2
        14: invokespecial #18                 // Method org/kohsuke/github/GitHubPageContentsIterable."<init>":(Lorg/kohsuke/github/GitHubClient;Lorg/kohsuke/github/GitHubRequest;Ljava/lang/Class;Ljava/util/function/Consumer;)V
        17: areturn
      LineNumberTable:
        line 156: 0
      LocalVariableTable:
        Start  Length  Slot  Name   Signature
            0      18     0  this   Lorg/kohsuke/github/Requester;
            0      18     1  type   Ljava/lang/Class;
            0      18     2 itemInitializer   Ljava/util/function/Consumer;
      LocalVariableTypeTable:
        Start  Length  Slot  Name   Signature
            0      18     1  type   Ljava/lang/Class<[TR;>;
            0      18     2 itemInitializer   Ljava/util/function/Consumer<TR;>;
    Signature: #75                          // <R:Ljava/lang/Object;>(Ljava/lang/Class<[TR;>;Ljava/util/function/Consumer<TR;>;)Lorg/kohsuke/github/PagedIterable<TR;>;

  private static java.lang.Object lambda$fetchStream$3(org.kohsuke.github.function.InputStreamFunction, org.kohsuke.github.connector.GitHubConnectorResponse) throws java.io.IOException;
    descriptor: (Lorg/kohsuke/github/function/InputStreamFunction;Lorg/kohsuke/github/connector/GitHubConnectorResponse;)Ljava/lang/Object;
    flags: (0x100a) ACC_PRIVATE, ACC_STATIC, ACC_SYNTHETIC
    Code:
      stack=2, locals=2, args_size=2
         0: aload_0
         1: aload_1
         2: invokevirtual #19                 // Method org/kohsuke/github/connector/GitHubConnectorResponse.bodyStream:()Ljava/io/InputStream;
         5: invokeinterface #20,  2           // InterfaceMethod org/kohsuke/github/function/InputStreamFunction.apply:(Ljava/lang/Object;)Ljava/lang/Object;
        10: areturn
      LineNumberTable:
        line 117: 0
      LocalVariableTable:
        Start  Length  Slot  Name   Signature
            0      11     0 handler   Lorg/kohsuke/github/function/InputStreamFunction;
            0      11     1 connectorResponse   Lorg/kohsuke/github/connector/GitHubConnectorResponse;
    Exceptions:
      throws java.io.IOException

  private static java.lang.Object lambda$fetchInto$2(java.lang.Object, org.kohsuke.github.connector.GitHubConnectorResponse) throws java.io.IOException;
    descriptor: (Ljava/lang/Object;Lorg/kohsuke/github/connector/GitHubConnectorResponse;)Ljava/lang/Object;
    flags: (0x100a) ACC_PRIVATE, ACC_STATIC, ACC_SYNTHETIC
    Code:
      stack=2, locals=2, args_size=2
         0: aload_1
         1: aload_0
         2: invokestatic  #21                 // Method org/kohsuke/github/GitHubResponse.parseBody:(Lorg/kohsuke/github/connector/GitHubConnectorResponse;Ljava/lang/Object;)Ljava/lang/Object;
         5: areturn
      LineNumberTable:
        line 93: 0
      LocalVariableTable:
        Start  Length  Slot  Name   Signature
            0       6     0 existingInstance   Ljava/lang/Object;
            0       6     1 connectorResponse   Lorg/kohsuke/github/connector/GitHubConnectorResponse;
    Exceptions:
      throws java.io.IOException

  private static java.lang.Object lambda$fetch$1(java.lang.Class, org.kohsuke.github.connector.GitHubConnectorResponse) throws java.io.IOException;
    descriptor: (Ljava/lang/Class;Lorg/kohsuke/github/connector/GitHubConnectorResponse;)Ljava/lang/Object;
    flags: (0x100a) ACC_PRIVATE, ACC_STATIC, ACC_SYNTHETIC
    Code:
      stack=2, locals=2, args_size=2
         0: aload_1
         1: aload_0
         2: invokestatic  #22                 // Method org/kohsuke/github/GitHubResponse.parseBody:(Lorg/kohsuke/github/connector/GitHubConnectorResponse;Ljava/lang/Class;)Ljava/lang/Object;
         5: areturn
      LineNumberTable:
        line 76: 0
      LocalVariableTable:
        Start  Length  Slot  Name   Signature
            0       6     0  type   Ljava/lang/Class;
            0       6     1 connectorResponse   Lorg/kohsuke/github/connector/GitHubConnectorResponse;
    Exceptions:
      throws java.io.IOException

  private static java.lang.String lambda$send$0(org.kohsuke.github.connector.GitHubConnectorResponse) throws java.io.IOException;
    descriptor: (Lorg/kohsuke/github/connector/GitHubConnectorResponse;)Ljava/lang/String;
    flags: (0x100a) ACC_PRIVATE, ACC_STATIC, ACC_SYNTHETIC
    Code:
      stack=1, locals=1, args_size=1
         0: aload_0
         1: invokestatic  #23                 // Method org/kohsuke/github/GitHubResponse.getBodyAsString:(Lorg/kohsuke/github/connector/GitHubConnectorResponse;)Ljava/lang/String;
         4: areturn
      LineNumberTable:
        line 61: 0
      LocalVariableTable:
        Start  Length  Slot  Name   Signature
            0       5     0 connectorResponse   Lorg/kohsuke/github/connector/GitHubConnectorResponse;
    Exceptions:
      throws java.io.IOException
}
Signature: #88                          // Lorg/kohsuke/github/GitHubRequest$Builder<Lorg/kohsuke/github/Requester;>;
SourceFile: "Requester.java"
InnerClasses:
  static #86= #25 of #129;                // Builder=class org/kohsuke/github/GitHubRequest$Builder of class org/kohsuke/github/GitHubRequest
  static #141= #140 of #93;               // BodyHandler=class org/kohsuke/github/GitHubClient$BodyHandler of class org/kohsuke/github/GitHubClient
  public static final #183= #182 of #185; // Lookup=class java/lang/invoke/MethodHandles$Lookup of class java/lang/invoke/MethodHandles
BootstrapMethods:
  0: #97 REF_invokeStatic java/lang/invoke/LambdaMetafactory.metafactory:(Ljava/lang/invoke/MethodHandles$Lookup;Ljava/lang/String;Ljava/lang/invoke/MethodType;Ljava/lang/invoke/MethodType;Ljava/lang/invoke/MethodHandle;Ljava/lang/invoke/MethodType;)Ljava/lang/invoke/CallSite;
    Method arguments:
      #98 (Ljava/lang/Object;)Ljava/lang/Object;
      #99 REF_invokeStatic org/kohsuke/github/Requester.lambda$send$0:(Lorg/kohsuke/github/connector/GitHubConnectorResponse;)Ljava/lang/String;
      #100 (Lorg/kohsuke/github/connector/GitHubConnectorResponse;)Ljava/lang/String;
  1: #97 REF_invokeStatic java/lang/invoke/LambdaMetafactory.metafactory:(Ljava/lang/invoke/MethodHandles$Lookup;Ljava/lang/String;Ljava/lang/invoke/MethodType;Ljava/lang/invoke/MethodType;Ljava/lang/invoke/MethodHandle;Ljava/lang/invoke/MethodType;)Ljava/lang/invoke/CallSite;
    Method arguments:
      #98 (Ljava/lang/Object;)Ljava/lang/Object;
      #103 REF_invokeStatic org/kohsuke/github/Requester.lambda$fetch$1:(Ljava/lang/Class;Lorg/kohsuke/github/connector/GitHubConnectorResponse;)Ljava/lang/Object;
      #104 (Lorg/kohsuke/github/connector/GitHubConnectorResponse;)Ljava/lang/Object;
  2: #97 REF_invokeStatic java/lang/invoke/LambdaMetafactory.metafactory:(Ljava/lang/invoke/MethodHandles$Lookup;Ljava/lang/String;Ljava/lang/invoke/MethodType;Ljava/lang/invoke/MethodType;Ljava/lang/invoke/MethodHandle;Ljava/lang/invoke/MethodType;)Ljava/lang/invoke/CallSite;
    Method arguments:
      #98 (Ljava/lang/Object;)Ljava/lang/Object;
      #108 REF_invokeStatic org/kohsuke/github/Requester.lambda$fetchInto$2:(Ljava/lang/Object;Lorg/kohsuke/github/connector/GitHubConnectorResponse;)Ljava/lang/Object;
      #104 (Lorg/kohsuke/github/connector/GitHubConnectorResponse;)Ljava/lang/Object;
  3: #97 REF_invokeStatic java/lang/invoke/LambdaMetafactory.metafactory:(Ljava/lang/invoke/MethodHandles$Lookup;Ljava/lang/String;Ljava/lang/invoke/MethodType;Ljava/lang/invoke/MethodType;Ljava/lang/invoke/MethodHandle;Ljava/lang/invoke/MethodType;)Ljava/lang/invoke/CallSite;
    Method arguments:
      #98 (Ljava/lang/Object;)Ljava/lang/Object;
      #113 REF_invokeStatic org/kohsuke/github/Requester.lambda$fetchStream$3:(Lorg/kohsuke/github/function/InputStreamFunction;Lorg/kohsuke/github/connector/GitHubConnectorResponse;)Ljava/lang/Object;
      #104 (Lorg/kohsuke/github/connector/GitHubConnectorResponse;)Ljava/lang/Object;
