Classfile /Users/mw/Projects/slang-braindump/.jar/jar11/assemble/slang-braindump/assemble/content/scala/beans/BooleanBeanProperty.class
  Last modified May 29, 2022; size 836 bytes
  SHA-256 checksum 52c01414b8afb55f415f05898509c26ae4f2b422421a9fbad82b0c675d0ac1aa
  Compiled from "BooleanBeanProperty.scala"
public class scala.beans.BooleanBeanProperty extends scala.annotation.Annotation implements scala.annotation.StaticAnnotation
  minor version: 0
  major version: 52
  flags: (0x0021) ACC_PUBLIC, ACC_SUPER
  this_class: #2                          // scala/beans/BooleanBeanProperty
  super_class: #4                         // scala/annotation/Annotation
  interfaces: 1, fields: 0, methods: 1, attributes: 4
Constant pool:
   #1 = Utf8               scala/beans/BooleanBeanProperty
   #2 = Class              #1             // scala/beans/BooleanBeanProperty
   #3 = Utf8               scala/annotation/Annotation
   #4 = Class              #3             // scala/annotation/Annotation
   #5 = Utf8               scala/annotation/StaticAnnotation
   #6 = Class              #5             // scala/annotation/StaticAnnotation
   #7 = Utf8               BooleanBeanProperty.scala
   #8 = Utf8               Lscala/reflect/ScalaSignature;
   #9 = Utf8               bytes
  #10 = Utf8               \u0006\u0005!2AAA\u0002\u0001\u0011!)!\u0003\u0001C\u0001\'\t\u0019\"i\\8mK\u0006t\')Z1o!J|\u0007/\u001a:us*\u0011A!B\u0001\u0006E\u0016\fgn\u001d\u0006\u0002\r\u0005)1oY1mC\u000e\u00011c\u0001\u0001\n\u001fA\u0011!\"D\u0007\u0002\u0017)\u0011A\"B\u0001\u000bC:tw\u000e^1uS>t\u0017B\u0001\b\f\u0005)\teN\\8uCRLwN\u001c\t\u0003\u0015AI!!E\u0006\u0003!M#\u0018\r^5d\u0003:tw\u000e^1uS>t\u0017A\u0002\u001fj]&$h\bF\u0001\u0015!\t)\u0002!D\u0001\u0004Q\u0019\u0001qc\u0007\u000f\u001f?A\u0011\u0001$G\u0007\u0002\u000b%\u0011!$\u0002\u0002\u0016I\u0016\u0004(/Z2bi\u0016$\u0017J\u001c5fe&$\u0018M\\2f\u0003\u001diWm]:bO\u0016\f\u0013!H\u0001(\'\u000eDW\rZ;mK\u0012\u0004cm\u001c:!E\u0016Lgn\u001a\u0011gS:\fG\u000eI5oAQDW\r\t4viV\u0014X-A\u0003tS:\u001cW-I\u0001!\u0003\u0019\u0011d&M\u001a/a!\u0012\u0001A\t\t\u0003G\u0019j\u0011\u0001\n\u0006\u0003K-\tA!\\3uC&\u0011q\u0005\n\u0002\u0006M&,G\u000e\u001a
  #11 = Utf8               <init>
  #12 = Utf8               ()V
  #13 = NameAndType        #11:#12        // "<init>":()V
  #14 = Methodref          #4.#13         // scala/annotation/Annotation."<init>":()V
  #15 = Utf8               this
  #16 = Utf8               Lscala/beans/BooleanBeanProperty;
  #17 = Utf8               Code
  #18 = Utf8               LineNumberTable
  #19 = Utf8               LocalVariableTable
  #20 = Utf8               SourceFile
  #21 = Utf8               RuntimeVisibleAnnotations
  #22 = Utf8               ScalaInlineInfo
  #23 = Utf8               ScalaSig
{
  public scala.beans.BooleanBeanProperty();
    descriptor: ()V
    flags: (0x0001) ACC_PUBLIC
    Code:
      stack=1, locals=1, args_size=1
         0: aload_0
         1: invokespecial #14                 // Method scala/annotation/Annotation."<init>":()V
         4: return
      LineNumberTable:
        line 21: 0
      LocalVariableTable:
        Start  Length  Slot  Name   Signature
            0       5     0  this   Lscala/beans/BooleanBeanProperty;
}
SourceFile: "BooleanBeanProperty.scala"
RuntimeVisibleAnnotations:
  0: #8(#9=s#10)
    scala.reflect.ScalaSignature(
      bytes="\u0006\u0005!2AAA\u0002\u0001\u0011!)!\u0003\u0001C\u0001\'\t\u0019\"i\\8mK\u0006t\')Z1o!J|\u0007/\u001a:us*\u0011A!B\u0001\u0006E\u0016\fgn\u001d\u0006\u0002\r\u0005)1oY1mC\u000e\u00011c\u0001\u0001\n\u001fA\u0011!\"D\u0007\u0002\u0017)\u0011A\"B\u0001\u000bC:tw\u000e^1uS>t\u0017B\u0001\b\f\u0005)\teN\\8uCRLwN\u001c\t\u0003\u0015AI!!E\u0006\u0003!M#\u0018\r^5d\u0003:tw\u000e^1uS>t\u0017A\u0002\u001fj]&$h\bF\u0001\u0015!\t)\u0002!D\u0001\u0004Q\u0019\u0001qc\u0007\u000f\u001f?A\u0011\u0001$G\u0007\u0002\u000b%\u0011!$\u0002\u0002\u0016I\u0016\u0004(/Z2bi\u0016$\u0017J\u001c5fe&$\u0018M\\2f\u0003\u001diWm]:bO\u0016\f\u0013!H\u0001(\'\u000eDW\rZ;mK\u0012\u0004cm\u001c:!E\u0016Lgn\u001a\u0011gS:\fG\u000eI5oAQDW\r\t4viV\u0014X-A\u0003tS:\u001cW-I\u0001!\u0003\u0019\u0011d&M\u001a/a!\u0012\u0001A\t\t\u0003G\u0019j\u0011\u0001\n\u0006\u0003K-\tA!\\3uC&\u0011q\u0005\n\u0002\u0006M&,G\u000e\u001a"
    )
  ScalaInlineInfo: length = 0x9 (unknown attribute)
   01 00 00 01 00 0B 00 0C 00
  ScalaSig: length = 0x3 (unknown attribute)
   05 02 00
