Classfile /Users/mw/Projects/slang-braindump/.jar/jar8/assemble/slang-braindump/assemble/content/scala/collection/mutable/AnyRefMap$AnyRefMapIterator.class
  Last modified May 29, 2022; size 1926 bytes
  SHA-256 checksum 37701f1427d9fe70ccf381f9286de6afd64f0ab6e8f7805b845ceb5af9ba22cd
  Compiled from "AnyRefMap.scala"
public abstract class scala.collection.mutable.AnyRefMap$AnyRefMapIterator<A extends java.lang.Object> extends scala.collection.AbstractIterator<A>
  minor version: 0
  major version: 52
  flags: (0x0421) ACC_PUBLIC, ACC_SUPER, ACC_ABSTRACT
  this_class: #2                          // scala/collection/mutable/AnyRefMap$AnyRefMapIterator
  super_class: #5                         // scala/collection/AbstractIterator
  interfaces: 0, fields: 5, methods: 5, attributes: 5
Constant pool:
   #1 = Utf8               scala/collection/mutable/AnyRefMap$AnyRefMapIterator
   #2 = Class              #1             // scala/collection/mutable/AnyRefMap$AnyRefMapIterator
   #3 = Utf8               <A:Ljava/lang/Object;>Lscala/collection/AbstractIterator<TA;>;
   #4 = Utf8               scala/collection/AbstractIterator
   #5 = Class              #4             // scala/collection/AbstractIterator
   #6 = Utf8               AnyRefMap.scala
   #7 = Utf8               scala/collection/mutable/AnyRefMap
   #8 = Class              #7             // scala/collection/mutable/AnyRefMap
   #9 = Utf8               AnyRefMapIterator
  #10 = Utf8               hz
  #11 = Utf8               [I
  #12 = Utf8               kz
  #13 = Utf8               [Ljava/lang/Object;
  #14 = Utf8               vz
  #15 = Utf8               index
  #16 = Utf8               I
  #17 = Utf8               $outer
  #18 = Utf8               Lscala/collection/mutable/AnyRefMap;
  #19 = Utf8               hasNext
  #20 = Utf8               ()Z
  #21 = NameAndType        #15:#16        // index:I
  #22 = Fieldref           #2.#21         // scala/collection/mutable/AnyRefMap$AnyRefMapIterator.index:I
  #23 = NameAndType        #10:#11        // hz:[I
  #24 = Fieldref           #2.#23         // scala/collection/mutable/AnyRefMap$AnyRefMapIterator.hz:[I
  #25 = Utf8               h
  #26 = Utf8               this
  #27 = Utf8               Lscala/collection/mutable/AnyRefMap$AnyRefMapIterator;
  #28 = Utf8               next
  #29 = Utf8               ()Ljava/lang/Object;
  #30 = Utf8               ()TA;
  #31 = NameAndType        #19:#20        // hasNext:()Z
  #32 = Methodref          #2.#31         // scala/collection/mutable/AnyRefMap$AnyRefMapIterator.hasNext:()Z
  #33 = NameAndType        #12:#13        // kz:[Ljava/lang/Object;
  #34 = Fieldref           #2.#33         // scala/collection/mutable/AnyRefMap$AnyRefMapIterator.kz:[Ljava/lang/Object;
  #35 = NameAndType        #14:#13        // vz:[Ljava/lang/Object;
  #36 = Fieldref           #2.#35         // scala/collection/mutable/AnyRefMap$AnyRefMapIterator.vz:[Ljava/lang/Object;
  #37 = Utf8               nextResult
  #38 = Utf8               (Ljava/lang/Object;Ljava/lang/Object;)Ljava/lang/Object;
  #39 = NameAndType        #37:#38        // nextResult:(Ljava/lang/Object;Ljava/lang/Object;)Ljava/lang/Object;
  #40 = Methodref          #2.#39         // scala/collection/mutable/AnyRefMap$AnyRefMapIterator.nextResult:(Ljava/lang/Object;Ljava/lang/Object;)Ljava/lang/Object;
  #41 = Utf8               java/util/NoSuchElementException
  #42 = Class              #41            // java/util/NoSuchElementException
  #43 = String             #28            // next
  #44 = Utf8               <init>
  #45 = Utf8               (Ljava/lang/String;)V
  #46 = NameAndType        #44:#45        // "<init>":(Ljava/lang/String;)V
  #47 = Methodref          #42.#46        // java/util/NoSuchElementException."<init>":(Ljava/lang/String;)V
  #48 = Utf8               ans
  #49 = Utf8               Ljava/lang/Object;
  #50 = Utf8               (TK;TV;)TA;
  #51 = Utf8               k
  #52 = Utf8               v
  #53 = Utf8               scala$collection$mutable$AnyRefMap$AnyRefMapIterator$$$outer
  #54 = Utf8               ()Lscala/collection/mutable/AnyRefMap;
  #55 = NameAndType        #17:#18        // $outer:Lscala/collection/mutable/AnyRefMap;
  #56 = Fieldref           #2.#55         // scala/collection/mutable/AnyRefMap$AnyRefMapIterator.$outer:Lscala/collection/mutable/AnyRefMap;
  #57 = Utf8               (Lscala/collection/mutable/AnyRefMap;)V
  #58 = Utf8               ()V
  #59 = NameAndType        #44:#58        // "<init>":()V
  #60 = Methodref          #5.#59         // scala/collection/AbstractIterator."<init>":()V
  #61 = Utf8               scala$collection$mutable$AnyRefMap$$_hashes
  #62 = NameAndType        #61:#11        // scala$collection$mutable$AnyRefMap$$_hashes:[I
  #63 = Fieldref           #8.#62         // scala/collection/mutable/AnyRefMap.scala$collection$mutable$AnyRefMap$$_hashes:[I
  #64 = Utf8               scala$collection$mutable$AnyRefMap$$_keys
  #65 = NameAndType        #64:#13        // scala$collection$mutable$AnyRefMap$$_keys:[Ljava/lang/Object;
  #66 = Fieldref           #8.#65         // scala/collection/mutable/AnyRefMap.scala$collection$mutable$AnyRefMap$$_keys:[Ljava/lang/Object;
  #67 = Utf8               scala$collection$mutable$AnyRefMap$$_values
  #68 = NameAndType        #67:#13        // scala$collection$mutable$AnyRefMap$$_values:[Ljava/lang/Object;
  #69 = Fieldref           #8.#68         // scala/collection/mutable/AnyRefMap.scala$collection$mutable$AnyRefMap$$_values:[Ljava/lang/Object;
  #70 = Utf8               Code
  #71 = Utf8               StackMapTable
  #72 = Utf8               LineNumberTable
  #73 = Utf8               LocalVariableTable
  #74 = Utf8               Signature
  #75 = Utf8               MethodParameters
  #76 = Utf8               InnerClasses
  #77 = Utf8               SourceFile
  #78 = Utf8               ScalaInlineInfo
  #79 = Utf8               Scala
{
  private final int[] hz;
    descriptor: [I
    flags: (0x0012) ACC_PRIVATE, ACC_FINAL

  private final java.lang.Object[] kz;
    descriptor: [Ljava/lang/Object;
    flags: (0x0012) ACC_PRIVATE, ACC_FINAL

  private final java.lang.Object[] vz;
    descriptor: [Ljava/lang/Object;
    flags: (0x0012) ACC_PRIVATE, ACC_FINAL

  private int index;
    descriptor: I
    flags: (0x0002) ACC_PRIVATE

  public final scala.collection.mutable.AnyRefMap $outer;
    descriptor: Lscala/collection/mutable/AnyRefMap;
    flags: (0x1011) ACC_PUBLIC, ACC_FINAL, ACC_SYNTHETIC

  public boolean hasNext();
    descriptor: ()Z
    flags: (0x0001) ACC_PUBLIC
    Code:
      stack=3, locals=2, args_size=1
         0: aload_0
         1: getfield      #22                 // Field index:I
         4: aload_0
         5: getfield      #24                 // Field hz:[I
         8: arraylength
         9: if_icmpge     68
        12: aload_0
        13: getfield      #24                 // Field hz:[I
        16: aload_0
        17: getfield      #22                 // Field index:I
        20: iaload
        21: istore_1
        22: iload_1
        23: iload_1
        24: iadd
        25: iconst_0
        26: if_icmpne     66
        29: aload_0
        30: aload_0
        31: getfield      #22                 // Field index:I
        34: iconst_1
        35: iadd
        36: putfield      #22                 // Field index:I
        39: aload_0
        40: getfield      #22                 // Field index:I
        43: aload_0
        44: getfield      #24                 // Field hz:[I
        47: arraylength
        48: if_icmplt     53
        51: iconst_0
        52: ireturn
        53: aload_0
        54: getfield      #24                 // Field hz:[I
        57: aload_0
        58: getfield      #22                 // Field index:I
        61: iaload
        62: istore_1
        63: goto          22
        66: iconst_1
        67: ireturn
        68: iconst_0
        69: ireturn
      StackMapTable: number_of_entries = 4
        frame_type = 252 /* append */
          offset_delta = 22
          locals = [ int ]
        frame_type = 30 /* same */
        frame_type = 12 /* same */
        frame_type = 250 /* chop */
          offset_delta = 1
      LineNumberTable:
        line 335: 0
        line 336: 12
        line 337: 22
        line 338: 29
        line 339: 39
        line 340: 53
        line 337: 63
        line 342: 66
      LocalVariableTable:
        Start  Length  Slot  Name   Signature
           22      44     1     h   I
            0      70     0  this   Lscala/collection/mutable/AnyRefMap$AnyRefMapIterator;

  public A next();
    descriptor: ()Ljava/lang/Object;
    flags: (0x0001) ACC_PUBLIC
    Code:
      stack=4, locals=2, args_size=1
         0: aload_0
         1: invokevirtual #32                 // Method hasNext:()Z
         4: ifeq          42
         7: aload_0
         8: aload_0
         9: getfield      #34                 // Field kz:[Ljava/lang/Object;
        12: aload_0
        13: getfield      #22                 // Field index:I
        16: aaload
        17: aload_0
        18: getfield      #36                 // Field vz:[Ljava/lang/Object;
        21: aload_0
        22: getfield      #22                 // Field index:I
        25: aaload
        26: invokevirtual #40                 // Method nextResult:(Ljava/lang/Object;Ljava/lang/Object;)Ljava/lang/Object;
        29: astore_1
        30: aload_0
        31: aload_0
        32: getfield      #22                 // Field index:I
        35: iconst_1
        36: iadd
        37: putfield      #22                 // Field index:I
        40: aload_1
        41: areturn
        42: new           #42                 // class java/util/NoSuchElementException
        45: dup
        46: ldc           #43                 // String next
        48: invokespecial #47                 // Method java/util/NoSuchElementException."<init>":(Ljava/lang/String;)V
        51: athrow
      StackMapTable: number_of_entries = 1
        frame_type = 42 /* same */
      LineNumberTable:
        line 346: 0
        line 347: 7
        line 348: 30
        line 349: 40
        line 351: 42
      LocalVariableTable:
        Start  Length  Slot  Name   Signature
           30      11     1   ans   Ljava/lang/Object;
            0      52     0  this   Lscala/collection/mutable/AnyRefMap$AnyRefMapIterator;
    Signature: #30                          // ()TA;

  public abstract A nextResult(K, V);
    descriptor: (Ljava/lang/Object;Ljava/lang/Object;)Ljava/lang/Object;
    flags: (0x0401) ACC_PUBLIC, ACC_ABSTRACT
    Signature: #50                          // (TK;TV;)TA;
    MethodParameters:
      Name                           Flags
      k                              final
      v                              final

  public scala.collection.mutable.AnyRefMap scala$collection$mutable$AnyRefMap$AnyRefMapIterator$$$outer();
    descriptor: ()Lscala/collection/mutable/AnyRefMap;
    flags: (0x1001) ACC_PUBLIC, ACC_SYNTHETIC
    Code:
      stack=1, locals=1, args_size=1
         0: aload_0
         1: getfield      #56                 // Field $outer:Lscala/collection/mutable/AnyRefMap;
         4: areturn
      LineNumberTable:
        line 328: 0
      LocalVariableTable:
        Start  Length  Slot  Name   Signature
            0       5     0  this   Lscala/collection/mutable/AnyRefMap$AnyRefMapIterator;

  public scala.collection.mutable.AnyRefMap$AnyRefMapIterator(scala.collection.mutable.AnyRefMap);
    descriptor: (Lscala/collection/mutable/AnyRefMap;)V
    flags: (0x0001) ACC_PUBLIC
    Code:
      stack=2, locals=2, args_size=2
         0: aload_1
         1: ifnonnull     6
         4: aconst_null
         5: athrow
         6: aload_0
         7: aload_1
         8: putfield      #56                 // Field $outer:Lscala/collection/mutable/AnyRefMap;
        11: aload_0
        12: invokespecial #60                 // Method scala/collection/AbstractIterator."<init>":()V
        15: aload_0
        16: aload_1
        17: getfield      #63                 // Field scala/collection/mutable/AnyRefMap.scala$collection$mutable$AnyRefMap$$_hashes:[I
        20: putfield      #24                 // Field hz:[I
        23: aload_0
        24: aload_1
        25: getfield      #66                 // Field scala/collection/mutable/AnyRefMap.scala$collection$mutable$AnyRefMap$$_keys:[Ljava/lang/Object;
        28: putfield      #34                 // Field kz:[Ljava/lang/Object;
        31: aload_0
        32: aload_1
        33: getfield      #69                 // Field scala/collection/mutable/AnyRefMap.scala$collection$mutable$AnyRefMap$$_values:[Ljava/lang/Object;
        36: putfield      #36                 // Field vz:[Ljava/lang/Object;
        39: aload_0
        40: iconst_0
        41: putfield      #22                 // Field index:I
        44: return
      StackMapTable: number_of_entries = 1
        frame_type = 6 /* same */
      LineNumberTable:
        line 328: 0
        line 329: 15
        line 330: 23
        line 331: 31
        line 333: 39
        line 328: 44
      LocalVariableTable:
        Start  Length  Slot  Name   Signature
            0      45     0  this   Lscala/collection/mutable/AnyRefMap$AnyRefMapIterator;
            0      45     1 $outer   Lscala/collection/mutable/AnyRefMap;
    MethodParameters:
      Name                           Flags
      $outer                         final synthetic
}
InnerClasses:
  private abstract #9= #2 of #8;          // AnyRefMapIterator=class scala/collection/mutable/AnyRefMap$AnyRefMapIterator of class scala/collection/mutable/AnyRefMap
Signature: #3                           // <A:Ljava/lang/Object;>Lscala/collection/AbstractIterator<TA;>;
SourceFile: "AnyRefMap.scala"
  ScalaInlineInfo: length = 0x1D (unknown attribute)
   01 00 00 05 00 2C 00 39 00 00 13 00 14 00 00 1C
   00 1D 00 00 25 00 26 00 00 35 00 36 00
  Scala: length = 0x0 (unknown attribute)

