Classfile /Users/mw/Projects/slang-braindump/.jar/jar8/assemble/slang-braindump/assemble/content/scala/collection/mutable/ArrayBuffer$.class
  Last modified May 29, 2022; size 11623 bytes
  SHA-256 checksum e041c6194169c59e70bd5b284c2600aabacf82b1915a15f83249e1a6610258f2
  Compiled from "ArrayBuffer.scala"
public final class scala.collection.mutable.ArrayBuffer$ extends java.lang.Object implements scala.collection.StrictOptimizedSeqFactory<scala.collection.mutable.ArrayBuffer>
  minor version: 0
  major version: 52
  flags: (0x0031) ACC_PUBLIC, ACC_FINAL, ACC_SUPER
  this_class: #2                          // scala/collection/mutable/ArrayBuffer$
  super_class: #5                         // java/lang/Object
  interfaces: 1, fields: 2, methods: 38, attributes: 5
Constant pool:
    #1 = Utf8               scala/collection/mutable/ArrayBuffer$
    #2 = Class              #1            // scala/collection/mutable/ArrayBuffer$
    #3 = Utf8               Ljava/lang/Object;Lscala/collection/StrictOptimizedSeqFactory<Lscala/collection/mutable/ArrayBuffer;>;
    #4 = Utf8               java/lang/Object
    #5 = Class              #4            // java/lang/Object
    #6 = Utf8               scala/collection/StrictOptimizedSeqFactory
    #7 = Class              #6            // scala/collection/StrictOptimizedSeqFactory
    #8 = Utf8               ArrayBuffer.scala
    #9 = Utf8               scala/collection/mutable/ArrayBuffer$$anon$1
   #10 = Class              #9            // scala/collection/mutable/ArrayBuffer$$anon$1
   #11 = Utf8               scala/util/package$chaining$
   #12 = Class              #11           // scala/util/package$chaining$
   #13 = Utf8               scala/util/package
   #14 = Class              #13           // scala/util/package
   #15 = Utf8               chaining$
   #16 = Utf8               MODULE$
   #17 = Utf8               Lscala/collection/mutable/ArrayBuffer$;
   #18 = Utf8               serialVersionUID
   #19 = Utf8               J
   #20 = Long               3l
   #22 = Utf8               <clinit>
   #23 = Utf8               ()V
   #24 = Utf8               <init>
   #25 = NameAndType        #24:#23       // "<init>":()V
   #26 = Methodref          #2.#25        // scala/collection/mutable/ArrayBuffer$."<init>":()V
   #27 = NameAndType        #16:#17       // MODULE$:Lscala/collection/mutable/ArrayBuffer$;
   #28 = Fieldref           #2.#27        // scala/collection/mutable/ArrayBuffer$.MODULE$:Lscala/collection/mutable/ArrayBuffer$;
   #29 = Utf8               fill
   #30 = Utf8               (ILscala/Function0;)Lscala/collection/SeqOps;
   #31 = Utf8               n
   #32 = Utf8               elem
   #33 = Utf8               fill$
   #34 = Utf8               (Lscala/collection/StrictOptimizedSeqFactory;ILscala/Function0;)Lscala/collection/SeqOps;
   #35 = NameAndType        #33:#34       // fill$:(Lscala/collection/StrictOptimizedSeqFactory;ILscala/Function0;)Lscala/collection/SeqOps;
   #36 = InterfaceMethodref #7.#35        // scala/collection/StrictOptimizedSeqFactory.fill$:(Lscala/collection/StrictOptimizedSeqFactory;ILscala/Function0;)Lscala/collection/SeqOps;
   #37 = Utf8               this
   #38 = Utf8               I
   #39 = Utf8               Lscala/Function0;
   #40 = Utf8               tabulate
   #41 = Utf8               (ILscala/Function1;)Lscala/collection/SeqOps;
   #42 = Utf8               f
   #43 = Utf8               tabulate$
   #44 = Utf8               (Lscala/collection/StrictOptimizedSeqFactory;ILscala/Function1;)Lscala/collection/SeqOps;
   #45 = NameAndType        #43:#44       // tabulate$:(Lscala/collection/StrictOptimizedSeqFactory;ILscala/Function1;)Lscala/collection/SeqOps;
   #46 = InterfaceMethodref #7.#45        // scala/collection/StrictOptimizedSeqFactory.tabulate$:(Lscala/collection/StrictOptimizedSeqFactory;ILscala/Function1;)Lscala/collection/SeqOps;
   #47 = Utf8               Lscala/Function1;
   #48 = Utf8               concat
   #49 = Utf8               (Lscala/collection/immutable/Seq;)Lscala/collection/SeqOps;
   #50 = Utf8               xss
   #51 = Utf8               concat$
   #52 = Utf8               (Lscala/collection/StrictOptimizedSeqFactory;Lscala/collection/immutable/Seq;)Lscala/collection/SeqOps;
   #53 = NameAndType        #51:#52       // concat$:(Lscala/collection/StrictOptimizedSeqFactory;Lscala/collection/immutable/Seq;)Lscala/collection/SeqOps;
   #54 = InterfaceMethodref #7.#53        // scala/collection/StrictOptimizedSeqFactory.concat$:(Lscala/collection/StrictOptimizedSeqFactory;Lscala/collection/immutable/Seq;)Lscala/collection/SeqOps;
   #55 = Utf8               Lscala/collection/immutable/Seq;
   #56 = Utf8               unapplySeq
   #57 = Utf8               (Lscala/collection/SeqOps;)Lscala/collection/SeqOps;
   #58 = Utf8               x
   #59 = Utf8               scala/collection/SeqFactory
   #60 = Class              #59           // scala/collection/SeqFactory
   #61 = Utf8               unapplySeq$
   #62 = Utf8               (Lscala/collection/SeqFactory;Lscala/collection/SeqOps;)Lscala/collection/SeqOps;
   #63 = NameAndType        #61:#62       // unapplySeq$:(Lscala/collection/SeqFactory;Lscala/collection/SeqOps;)Lscala/collection/SeqOps;
   #64 = InterfaceMethodref #60.#63       // scala/collection/SeqFactory.unapplySeq$:(Lscala/collection/SeqFactory;Lscala/collection/SeqOps;)Lscala/collection/SeqOps;
   #65 = Utf8               Lscala/collection/SeqOps;
   #66 = Utf8               apply
   #67 = Utf8               (Lscala/collection/immutable/Seq;)Ljava/lang/Object;
   #68 = Utf8               elems
   #69 = Utf8               scala/collection/IterableFactory
   #70 = Class              #69           // scala/collection/IterableFactory
   #71 = Utf8               apply$
   #72 = Utf8               (Lscala/collection/IterableFactory;Lscala/collection/immutable/Seq;)Ljava/lang/Object;
   #73 = NameAndType        #71:#72       // apply$:(Lscala/collection/IterableFactory;Lscala/collection/immutable/Seq;)Ljava/lang/Object;
   #74 = InterfaceMethodref #70.#73       // scala/collection/IterableFactory.apply$:(Lscala/collection/IterableFactory;Lscala/collection/immutable/Seq;)Ljava/lang/Object;
   #75 = Utf8               iterate
   #76 = Utf8               (Ljava/lang/Object;ILscala/Function1;)Ljava/lang/Object;
   #77 = Utf8               start
   #78 = Utf8               len
   #79 = Utf8               iterate$
   #80 = Utf8               (Lscala/collection/IterableFactory;Ljava/lang/Object;ILscala/Function1;)Ljava/lang/Object;
   #81 = NameAndType        #79:#80       // iterate$:(Lscala/collection/IterableFactory;Ljava/lang/Object;ILscala/Function1;)Ljava/lang/Object;
   #82 = InterfaceMethodref #70.#81       // scala/collection/IterableFactory.iterate$:(Lscala/collection/IterableFactory;Ljava/lang/Object;ILscala/Function1;)Ljava/lang/Object;
   #83 = Utf8               Ljava/lang/Object;
   #84 = Utf8               unfold
   #85 = Utf8               (Ljava/lang/Object;Lscala/Function1;)Ljava/lang/Object;
   #86 = Utf8               init
   #87 = Utf8               unfold$
   #88 = Utf8               (Lscala/collection/IterableFactory;Ljava/lang/Object;Lscala/Function1;)Ljava/lang/Object;
   #89 = NameAndType        #87:#88       // unfold$:(Lscala/collection/IterableFactory;Ljava/lang/Object;Lscala/Function1;)Ljava/lang/Object;
   #90 = InterfaceMethodref #70.#89       // scala/collection/IterableFactory.unfold$:(Lscala/collection/IterableFactory;Ljava/lang/Object;Lscala/Function1;)Ljava/lang/Object;
   #91 = Utf8               range
   #92 = Utf8               (Ljava/lang/Object;Ljava/lang/Object;Lscala/math/Integral;)Ljava/lang/Object;
   #93 = Utf8               end
   #94 = Utf8               evidence$3
   #95 = Utf8               range$
   #96 = Utf8               (Lscala/collection/IterableFactory;Ljava/lang/Object;Ljava/lang/Object;Lscala/math/Integral;)Ljava/lang/Object;
   #97 = NameAndType        #95:#96       // range$:(Lscala/collection/IterableFactory;Ljava/lang/Object;Ljava/lang/Object;Lscala/math/Integral;)Ljava/lang/Object;
   #98 = InterfaceMethodref #70.#97       // scala/collection/IterableFactory.range$:(Lscala/collection/IterableFactory;Ljava/lang/Object;Ljava/lang/Object;Lscala/math/Integral;)Ljava/lang/Object;
   #99 = Utf8               Lscala/math/Integral;
  #100 = Utf8               (Ljava/lang/Object;Ljava/lang/Object;Ljava/lang/Object;Lscala/math/Integral;)Ljava/lang/Object;
  #101 = Utf8               step
  #102 = Utf8               evidence$4
  #103 = Utf8               (Lscala/collection/IterableFactory;Ljava/lang/Object;Ljava/lang/Object;Ljava/lang/Object;Lscala/math/Integral;)Ljava/lang/Object;
  #104 = NameAndType        #95:#103      // range$:(Lscala/collection/IterableFactory;Ljava/lang/Object;Ljava/lang/Object;Ljava/lang/Object;Lscala/math/Integral;)Ljava/lang/Object;
  #105 = InterfaceMethodref #70.#104      // scala/collection/IterableFactory.range$:(Lscala/collection/IterableFactory;Ljava/lang/Object;Ljava/lang/Object;Ljava/lang/Object;Lscala/math/Integral;)Ljava/lang/Object;
  #106 = Utf8               (IILscala/Function0;)Ljava/lang/Object;
  #107 = Utf8               n1
  #108 = Utf8               n2
  #109 = Utf8               (Lscala/collection/IterableFactory;IILscala/Function0;)Ljava/lang/Object;
  #110 = NameAndType        #33:#109      // fill$:(Lscala/collection/IterableFactory;IILscala/Function0;)Ljava/lang/Object;
  #111 = InterfaceMethodref #70.#110      // scala/collection/IterableFactory.fill$:(Lscala/collection/IterableFactory;IILscala/Function0;)Ljava/lang/Object;
  #112 = Utf8               (IIILscala/Function0;)Ljava/lang/Object;
  #113 = Utf8               n3
  #114 = Utf8               (Lscala/collection/IterableFactory;IIILscala/Function0;)Ljava/lang/Object;
  #115 = NameAndType        #33:#114      // fill$:(Lscala/collection/IterableFactory;IIILscala/Function0;)Ljava/lang/Object;
  #116 = InterfaceMethodref #70.#115      // scala/collection/IterableFactory.fill$:(Lscala/collection/IterableFactory;IIILscala/Function0;)Ljava/lang/Object;
  #117 = Utf8               (IIIILscala/Function0;)Ljava/lang/Object;
  #118 = Utf8               n4
  #119 = Utf8               (Lscala/collection/IterableFactory;IIIILscala/Function0;)Ljava/lang/Object;
  #120 = NameAndType        #33:#119      // fill$:(Lscala/collection/IterableFactory;IIIILscala/Function0;)Ljava/lang/Object;
  #121 = InterfaceMethodref #70.#120      // scala/collection/IterableFactory.fill$:(Lscala/collection/IterableFactory;IIIILscala/Function0;)Ljava/lang/Object;
  #122 = Utf8               (IIIIILscala/Function0;)Ljava/lang/Object;
  #123 = Utf8               n5
  #124 = Utf8               (Lscala/collection/IterableFactory;IIIIILscala/Function0;)Ljava/lang/Object;
  #125 = NameAndType        #33:#124      // fill$:(Lscala/collection/IterableFactory;IIIIILscala/Function0;)Ljava/lang/Object;
  #126 = InterfaceMethodref #70.#125      // scala/collection/IterableFactory.fill$:(Lscala/collection/IterableFactory;IIIIILscala/Function0;)Ljava/lang/Object;
  #127 = Utf8               (IILscala/Function2;)Ljava/lang/Object;
  #128 = Utf8               (Lscala/collection/IterableFactory;IILscala/Function2;)Ljava/lang/Object;
  #129 = NameAndType        #43:#128      // tabulate$:(Lscala/collection/IterableFactory;IILscala/Function2;)Ljava/lang/Object;
  #130 = InterfaceMethodref #70.#129      // scala/collection/IterableFactory.tabulate$:(Lscala/collection/IterableFactory;IILscala/Function2;)Ljava/lang/Object;
  #131 = Utf8               Lscala/Function2;
  #132 = Utf8               (IIILscala/Function3;)Ljava/lang/Object;
  #133 = Utf8               (Lscala/collection/IterableFactory;IIILscala/Function3;)Ljava/lang/Object;
  #134 = NameAndType        #43:#133      // tabulate$:(Lscala/collection/IterableFactory;IIILscala/Function3;)Ljava/lang/Object;
  #135 = InterfaceMethodref #70.#134      // scala/collection/IterableFactory.tabulate$:(Lscala/collection/IterableFactory;IIILscala/Function3;)Ljava/lang/Object;
  #136 = Utf8               Lscala/Function3;
  #137 = Utf8               (IIIILscala/Function4;)Ljava/lang/Object;
  #138 = Utf8               (Lscala/collection/IterableFactory;IIIILscala/Function4;)Ljava/lang/Object;
  #139 = NameAndType        #43:#138      // tabulate$:(Lscala/collection/IterableFactory;IIIILscala/Function4;)Ljava/lang/Object;
  #140 = InterfaceMethodref #70.#139      // scala/collection/IterableFactory.tabulate$:(Lscala/collection/IterableFactory;IIIILscala/Function4;)Ljava/lang/Object;
  #141 = Utf8               Lscala/Function4;
  #142 = Utf8               (IIIIILscala/Function5;)Ljava/lang/Object;
  #143 = Utf8               (Lscala/collection/IterableFactory;IIIIILscala/Function5;)Ljava/lang/Object;
  #144 = NameAndType        #43:#143      // tabulate$:(Lscala/collection/IterableFactory;IIIIILscala/Function5;)Ljava/lang/Object;
  #145 = InterfaceMethodref #70.#144      // scala/collection/IterableFactory.tabulate$:(Lscala/collection/IterableFactory;IIIIILscala/Function5;)Ljava/lang/Object;
  #146 = Utf8               Lscala/Function5;
  #147 = Utf8               iterableFactory
  #148 = Utf8               ()Lscala/collection/Factory;
  #149 = Utf8               <A:Ljava/lang/Object;>()Lscala/collection/Factory<TA;Lscala/collection/mutable/ArrayBuffer<TA;>;>;
  #150 = Utf8               iterableFactory$
  #151 = Utf8               (Lscala/collection/IterableFactory;)Lscala/collection/Factory;
  #152 = NameAndType        #150:#151     // iterableFactory$:(Lscala/collection/IterableFactory;)Lscala/collection/Factory;
  #153 = InterfaceMethodref #70.#152      // scala/collection/IterableFactory.iterableFactory$:(Lscala/collection/IterableFactory;)Lscala/collection/Factory;
  #154 = Utf8               DefaultInitialSize
  #155 = Utf8               ()I
  #156 = Utf8               from
  #157 = Utf8               (Lscala/collection/IterableOnce;)Lscala/collection/mutable/ArrayBuffer;
  #158 = Utf8               <B:Ljava/lang/Object;>(Lscala/collection/IterableOnce<TB;>;)Lscala/collection/mutable/ArrayBuffer<TB;>;
  #159 = Utf8               coll
  #160 = Utf8               scala/collection/IterableOnce
  #161 = Class              #160          // scala/collection/IterableOnce
  #162 = Utf8               knownSize
  #163 = NameAndType        #162:#155     // knownSize:()I
  #164 = InterfaceMethodref #161.#163     // scala/collection/IterableOnce.knownSize:()I
  #165 = Utf8               scala/runtime/RichInt$
  #166 = Class              #165          // scala/runtime/RichInt$
  #167 = Utf8               Lscala/runtime/RichInt$;
  #168 = NameAndType        #16:#167      // MODULE$:Lscala/runtime/RichInt$;
  #169 = Fieldref           #166.#168     // scala/runtime/RichInt$.MODULE$:Lscala/runtime/RichInt$;
  #170 = Utf8               scala/math/package$
  #171 = Class              #170          // scala/math/package$
  #172 = Utf8               Lscala/math/package$;
  #173 = NameAndType        #16:#172      // MODULE$:Lscala/math/package$;
  #174 = Fieldref           #171.#173     // scala/math/package$.MODULE$:Lscala/math/package$;
  #175 = Utf8               java/lang/Math
  #176 = Class              #175          // java/lang/Math
  #177 = Utf8               max
  #178 = Utf8               (II)I
  #179 = NameAndType        #177:#178     // max:(II)I
  #180 = Methodref          #176.#179     // java/lang/Math.max:(II)I
  #181 = Utf8               scala/collection/IterableOnce$
  #182 = Class              #181          // scala/collection/IterableOnce$
  #183 = Utf8               Lscala/collection/IterableOnce$;
  #184 = NameAndType        #16:#183      // MODULE$:Lscala/collection/IterableOnce$;
  #185 = Fieldref           #182.#184     // scala/collection/IterableOnce$.MODULE$:Lscala/collection/IterableOnce$;
  #186 = Integer            2147483647
  #187 = Utf8               scala/collection/Iterable
  #188 = Class              #187          // scala/collection/Iterable
  #189 = Utf8               copyToArray
  #190 = Utf8               (Ljava/lang/Object;II)I
  #191 = NameAndType        #189:#190     // copyToArray:(Ljava/lang/Object;II)I
  #192 = InterfaceMethodref #188.#191     // scala/collection/Iterable.copyToArray:(Ljava/lang/Object;II)I
  #193 = Utf8               iterator
  #194 = Utf8               ()Lscala/collection/Iterator;
  #195 = NameAndType        #193:#194     // iterator:()Lscala/collection/Iterator;
  #196 = InterfaceMethodref #161.#195     // scala/collection/IterableOnce.iterator:()Lscala/collection/Iterator;
  #197 = Utf8               scala/collection/Iterator
  #198 = Class              #197          // scala/collection/Iterator
  #199 = InterfaceMethodref #198.#191     // scala/collection/Iterator.copyToArray:(Ljava/lang/Object;II)I
  #200 = Utf8               scala/collection/mutable/ArrayBuffer
  #201 = Class              #200          // scala/collection/mutable/ArrayBuffer
  #202 = Utf8               ([Ljava/lang/Object;I)V
  #203 = NameAndType        #24:#202      // "<init>":([Ljava/lang/Object;I)V
  #204 = Methodref          #201.#203     // scala/collection/mutable/ArrayBuffer."<init>":([Ljava/lang/Object;I)V
  #205 = Methodref          #201.#25      // scala/collection/mutable/ArrayBuffer."<init>":()V
  #206 = Utf8               scala/collection/mutable/Growable
  #207 = Class              #206          // scala/collection/mutable/Growable
  #208 = Utf8               addAll
  #209 = Utf8               (Lscala/collection/IterableOnce;)Lscala/collection/mutable/Growable;
  #210 = NameAndType        #208:#209     // addAll:(Lscala/collection/IterableOnce;)Lscala/collection/mutable/Growable;
  #211 = InterfaceMethodref #207.#210     // scala/collection/mutable/Growable.addAll:(Lscala/collection/IterableOnce;)Lscala/collection/mutable/Growable;
  #212 = Utf8               array
  #213 = Utf8               [Ljava/lang/Object;
  #214 = Utf8               k
  #215 = Utf8               Lscala/collection/IterableOnce;
  #216 = Utf8               max$extension_that
  #217 = Class              #213          // "[Ljava/lang/Object;"
  #218 = Utf8               newBuilder
  #219 = Utf8               ()Lscala/collection/mutable/Builder;
  #220 = Utf8               <A:Ljava/lang/Object;>()Lscala/collection/mutable/Builder<TA;Lscala/collection/mutable/ArrayBuffer<TA;>;>;
  #221 = Methodref          #10.#25       // scala/collection/mutable/ArrayBuffer$$anon$1."<init>":()V
  #222 = Utf8               empty
  #223 = Utf8               ()Lscala/collection/mutable/ArrayBuffer;
  #224 = Utf8               <A:Ljava/lang/Object;>()Lscala/collection/mutable/ArrayBuffer<TA;>;
  #225 = Utf8               scala$collection$mutable$ArrayBuffer$$ensureSize
  #226 = Utf8               ([Ljava/lang/Object;II)[Ljava/lang/Object;
  #227 = Utf8               scala/util/ChainingOps$
  #228 = Class              #227          // scala/util/ChainingOps$
  #229 = Utf8               Lscala/util/ChainingOps$;
  #230 = NameAndType        #16:#229      // MODULE$:Lscala/util/ChainingOps$;
  #231 = Fieldref           #228.#230     // scala/util/ChainingOps$.MODULE$:Lscala/util/ChainingOps$;
  #232 = Utf8               Lscala/util/package$chaining$;
  #233 = NameAndType        #16:#232      // MODULE$:Lscala/util/package$chaining$;
  #234 = Fieldref           #12.#233      // scala/util/package$chaining$.MODULE$:Lscala/util/package$chaining$;
  #235 = Utf8               resizeEnsuring$1
  #236 = Utf8               (III)I
  #237 = NameAndType        #235:#236     // resizeEnsuring$1:(III)I
  #238 = Methodref          #2.#237       // scala/collection/mutable/ArrayBuffer$.resizeEnsuring$1:(III)I
  #239 = Utf8               scala/Array$
  #240 = Class              #239          // scala/Array$
  #241 = Utf8               Lscala/Array$;
  #242 = NameAndType        #16:#241      // MODULE$:Lscala/Array$;
  #243 = Fieldref           #240.#242     // scala/Array$.MODULE$:Lscala/Array$;
  #244 = Utf8               copy
  #245 = Utf8               (Ljava/lang/Object;ILjava/lang/Object;II)V
  #246 = NameAndType        #244:#245     // copy:(Ljava/lang/Object;ILjava/lang/Object;II)V
  #247 = Methodref          #240.#246     // scala/Array$.copy:(Ljava/lang/Object;ILjava/lang/Object;II)V
  #248 = Utf8               tap$extension_$this
  #249 = Utf8               scala$collection$mutable$ArrayBuffer$$downsize
  #250 = Utf8               ([Ljava/lang/Object;I)[Ljava/lang/Object;
  #251 = Utf8               requiredLength
  #252 = Utf8               resizeDown$1
  #253 = NameAndType        #252:#178     // resizeDown$1:(II)I
  #254 = Methodref          #2.#253       // scala/collection/mutable/ArrayBuffer$.resizeDown$1:(II)I
  #255 = Utf8               writeReplace
  #256 = Utf8               ()Ljava/lang/Object;
  #257 = Utf8               scala/runtime/ModuleSerializationProxy
  #258 = Class              #257          // scala/runtime/ModuleSerializationProxy
  #259 = Utf8               (Ljava/lang/Class;)V
  #260 = NameAndType        #24:#259      // "<init>":(Ljava/lang/Class;)V
  #261 = Methodref          #258.#260     // scala/runtime/ModuleSerializationProxy."<init>":(Ljava/lang/Class;)V
  #262 = NameAndType        #48:#49       // concat:(Lscala/collection/immutable/Seq;)Lscala/collection/SeqOps;
  #263 = Methodref          #2.#262       // scala/collection/mutable/ArrayBuffer$.concat:(Lscala/collection/immutable/Seq;)Lscala/collection/SeqOps;
  #264 = Utf8               (ILscala/Function1;)Ljava/lang/Object;
  #265 = NameAndType        #40:#41       // tabulate:(ILscala/Function1;)Lscala/collection/SeqOps;
  #266 = Methodref          #2.#265       // scala/collection/mutable/ArrayBuffer$.tabulate:(ILscala/Function1;)Lscala/collection/SeqOps;
  #267 = Utf8               (ILscala/Function0;)Ljava/lang/Object;
  #268 = NameAndType        #29:#30       // fill:(ILscala/Function0;)Lscala/collection/SeqOps;
  #269 = Methodref          #2.#268       // scala/collection/mutable/ArrayBuffer$.fill:(ILscala/Function0;)Lscala/collection/SeqOps;
  #270 = NameAndType        #222:#223     // empty:()Lscala/collection/mutable/ArrayBuffer;
  #271 = Methodref          #2.#270       // scala/collection/mutable/ArrayBuffer$.empty:()Lscala/collection/mutable/ArrayBuffer;
  #272 = Utf8               (Lscala/collection/IterableOnce;)Ljava/lang/Object;
  #273 = Utf8               source
  #274 = NameAndType        #156:#157     // from:(Lscala/collection/IterableOnce;)Lscala/collection/mutable/ArrayBuffer;
  #275 = Methodref          #2.#274       // scala/collection/mutable/ArrayBuffer$.from:(Lscala/collection/IterableOnce;)Lscala/collection/mutable/ArrayBuffer;
  #276 = Utf8               length
  #277 = Long               2l
  #279 = Long               16l
  #281 = Utf8               (JJ)J
  #282 = NameAndType        #177:#281     // max:(JJ)J
  #283 = Methodref          #176.#282     // java/lang/Math.max:(JJ)J
  #284 = Long               2147483647l
  #286 = Utf8               java/lang/Exception
  #287 = Class              #286          // java/lang/Exception
  #288 = Utf8               java/lang/StringBuilder
  #289 = Class              #288          // java/lang/StringBuilder
  #290 = Integer            64
  #291 = Utf8               (I)V
  #292 = NameAndType        #24:#291      // "<init>":(I)V
  #293 = Methodref          #289.#292     // java/lang/StringBuilder."<init>":(I)V
  #294 = Utf8               Collections can not have more than
  #295 = String             #294          // Collections can not have more than
  #296 = Utf8               append
  #297 = Utf8               (Ljava/lang/String;)Ljava/lang/StringBuilder;
  #298 = NameAndType        #296:#297     // append:(Ljava/lang/String;)Ljava/lang/StringBuilder;
  #299 = Methodref          #289.#298     // java/lang/StringBuilder.append:(Ljava/lang/String;)Ljava/lang/StringBuilder;
  #300 = Utf8               (I)Ljava/lang/StringBuilder;
  #301 = NameAndType        #296:#300     // append:(I)Ljava/lang/StringBuilder;
  #302 = Methodref          #289.#301     // java/lang/StringBuilder.append:(I)Ljava/lang/StringBuilder;
  #303 = Utf8                elements
  #304 = String             #303          //  elements
  #305 = Utf8               toString
  #306 = Utf8               ()Ljava/lang/String;
  #307 = NameAndType        #305:#306     // toString:()Ljava/lang/String;
  #308 = Methodref          #289.#307     // java/lang/StringBuilder.toString:()Ljava/lang/String;
  #309 = Utf8               (Ljava/lang/String;)V
  #310 = NameAndType        #24:#309      // "<init>":(Ljava/lang/String;)V
  #311 = Methodref          #287.#310     // java/lang/Exception."<init>":(Ljava/lang/String;)V
  #312 = Utf8               newSize
  #313 = Utf8               $anonfun$ensureSize$1
  #314 = Utf8               ([Ljava/lang/Object;I[Ljava/lang/Object;)V
  #315 = Utf8               array$1
  #316 = Utf8               end$1
  #317 = Utf8               x$1
  #318 = Utf8               max_y
  #319 = Utf8               $anonfun$downsize$1
  #320 = Utf8               array$2
  #321 = Utf8               requiredLength$1
  #322 = Utf8               x$2
  #323 = Methodref          #5.#25        // java/lang/Object."<init>":()V
  #324 = Utf8               $anonfun$ensureSize$1$adapted
  #325 = Utf8               ([Ljava/lang/Object;I[Ljava/lang/Object;)Ljava/lang/Object;
  #326 = NameAndType        #313:#314     // $anonfun$ensureSize$1:([Ljava/lang/Object;I[Ljava/lang/Object;)V
  #327 = Methodref          #2.#326       // scala/collection/mutable/ArrayBuffer$.$anonfun$ensureSize$1:([Ljava/lang/Object;I[Ljava/lang/Object;)V
  #328 = Utf8               scala/runtime/BoxedUnit
  #329 = Class              #328          // scala/runtime/BoxedUnit
  #330 = Utf8               UNIT
  #331 = Utf8               Lscala/runtime/BoxedUnit;
  #332 = NameAndType        #330:#331     // UNIT:Lscala/runtime/BoxedUnit;
  #333 = Fieldref           #329.#332     // scala/runtime/BoxedUnit.UNIT:Lscala/runtime/BoxedUnit;
  #334 = Utf8               $anonfun$downsize$1$adapted
  #335 = NameAndType        #319:#314     // $anonfun$downsize$1:([Ljava/lang/Object;I[Ljava/lang/Object;)V
  #336 = Methodref          #2.#335       // scala/collection/mutable/ArrayBuffer$.$anonfun$downsize$1:([Ljava/lang/Object;I[Ljava/lang/Object;)V
  #337 = Utf8               ConstantValue
  #338 = Utf8               Code
  #339 = Utf8               LineNumberTable
  #340 = Utf8               LocalVariableTable
  #341 = Utf8               MethodParameters
  #342 = Utf8               Signature
  #343 = Utf8               StackMapTable
  #344 = Utf8               InnerClasses
  #345 = Utf8               SourceFile
  #346 = Utf8               ScalaInlineInfo
  #347 = Utf8               Scala
{
  public static final scala.collection.mutable.ArrayBuffer$ MODULE$;
    descriptor: Lscala/collection/mutable/ArrayBuffer$;
    flags: (0x0019) ACC_PUBLIC, ACC_STATIC, ACC_FINAL

  private static final long serialVersionUID;
    descriptor: J
    flags: (0x001a) ACC_PRIVATE, ACC_STATIC, ACC_FINAL
    ConstantValue: long 3l

  public static {};
    descriptor: ()V
    flags: (0x0009) ACC_PUBLIC, ACC_STATIC
    Code:
      stack=2, locals=0, args_size=0
         0: new           #2                  // class scala/collection/mutable/ArrayBuffer$
         3: dup
         4: invokespecial #26                 // Method "<init>":()V
         7: putstatic     #28                 // Field MODULE$:Lscala/collection/mutable/ArrayBuffer$;
        10: getstatic     #28                 // Field MODULE$:Lscala/collection/mutable/ArrayBuffer$;
        13: pop
        14: getstatic     #28                 // Field MODULE$:Lscala/collection/mutable/ArrayBuffer$;
        17: pop
        18: getstatic     #28                 // Field MODULE$:Lscala/collection/mutable/ArrayBuffer$;
        21: pop
        22: return
      LineNumberTable:
        line 266: 0

  public scala.collection.SeqOps fill(int, scala.Function0);
    descriptor: (ILscala/Function0;)Lscala/collection/SeqOps;
    flags: (0x0001) ACC_PUBLIC
    Code:
      stack=3, locals=3, args_size=3
         0: aload_0
         1: iload_1
         2: aload_2
         3: invokestatic  #36                 // InterfaceMethod scala/collection/StrictOptimizedSeqFactory.fill$:(Lscala/collection/StrictOptimizedSeqFactory;ILscala/Function0;)Lscala/collection/SeqOps;
         6: areturn
      LineNumberTable:
        line 266: 0
      LocalVariableTable:
        Start  Length  Slot  Name   Signature
            0       7     0  this   Lscala/collection/mutable/ArrayBuffer$;
            0       7     1     n   I
            0       7     2  elem   Lscala/Function0;
    MethodParameters:
      Name                           Flags
      n                              final
      elem                           final

  public scala.collection.SeqOps tabulate(int, scala.Function1);
    descriptor: (ILscala/Function1;)Lscala/collection/SeqOps;
    flags: (0x0001) ACC_PUBLIC
    Code:
      stack=3, locals=3, args_size=3
         0: aload_0
         1: iload_1
         2: aload_2
         3: invokestatic  #46                 // InterfaceMethod scala/collection/StrictOptimizedSeqFactory.tabulate$:(Lscala/collection/StrictOptimizedSeqFactory;ILscala/Function1;)Lscala/collection/SeqOps;
         6: areturn
      LineNumberTable:
        line 266: 0
      LocalVariableTable:
        Start  Length  Slot  Name   Signature
            0       7     0  this   Lscala/collection/mutable/ArrayBuffer$;
            0       7     1     n   I
            0       7     2     f   Lscala/Function1;
    MethodParameters:
      Name                           Flags
      n                              final
      f                              final

  public scala.collection.SeqOps concat(scala.collection.immutable.Seq);
    descriptor: (Lscala/collection/immutable/Seq;)Lscala/collection/SeqOps;
    flags: (0x0001) ACC_PUBLIC
    Code:
      stack=2, locals=2, args_size=2
         0: aload_0
         1: aload_1
         2: invokestatic  #54                 // InterfaceMethod scala/collection/StrictOptimizedSeqFactory.concat$:(Lscala/collection/StrictOptimizedSeqFactory;Lscala/collection/immutable/Seq;)Lscala/collection/SeqOps;
         5: areturn
      LineNumberTable:
        line 266: 0
      LocalVariableTable:
        Start  Length  Slot  Name   Signature
            0       6     0  this   Lscala/collection/mutable/ArrayBuffer$;
            0       6     1   xss   Lscala/collection/immutable/Seq;
    MethodParameters:
      Name                           Flags
      xss                            final

  public final scala.collection.SeqOps unapplySeq(scala.collection.SeqOps);
    descriptor: (Lscala/collection/SeqOps;)Lscala/collection/SeqOps;
    flags: (0x0011) ACC_PUBLIC, ACC_FINAL
    Code:
      stack=2, locals=2, args_size=2
         0: aload_0
         1: aload_1
         2: invokestatic  #64                 // InterfaceMethod scala/collection/SeqFactory.unapplySeq$:(Lscala/collection/SeqFactory;Lscala/collection/SeqOps;)Lscala/collection/SeqOps;
         5: areturn
      LineNumberTable:
        line 266: 0
      LocalVariableTable:
        Start  Length  Slot  Name   Signature
            0       6     0  this   Lscala/collection/mutable/ArrayBuffer$;
            0       6     1     x   Lscala/collection/SeqOps;
    MethodParameters:
      Name                           Flags
      x                              final

  public java.lang.Object apply(scala.collection.immutable.Seq);
    descriptor: (Lscala/collection/immutable/Seq;)Ljava/lang/Object;
    flags: (0x0001) ACC_PUBLIC
    Code:
      stack=2, locals=2, args_size=2
         0: aload_0
         1: aload_1
         2: invokestatic  #74                 // InterfaceMethod scala/collection/IterableFactory.apply$:(Lscala/collection/IterableFactory;Lscala/collection/immutable/Seq;)Ljava/lang/Object;
         5: areturn
      LineNumberTable:
        line 266: 0
      LocalVariableTable:
        Start  Length  Slot  Name   Signature
            0       6     0  this   Lscala/collection/mutable/ArrayBuffer$;
            0       6     1 elems   Lscala/collection/immutable/Seq;
    MethodParameters:
      Name                           Flags
      elems                          final

  public java.lang.Object iterate(java.lang.Object, int, scala.Function1);
    descriptor: (Ljava/lang/Object;ILscala/Function1;)Ljava/lang/Object;
    flags: (0x0001) ACC_PUBLIC
    Code:
      stack=4, locals=4, args_size=4
         0: aload_0
         1: aload_1
         2: iload_2
         3: aload_3
         4: invokestatic  #82                 // InterfaceMethod scala/collection/IterableFactory.iterate$:(Lscala/collection/IterableFactory;Ljava/lang/Object;ILscala/Function1;)Ljava/lang/Object;
         7: areturn
      LineNumberTable:
        line 266: 0
      LocalVariableTable:
        Start  Length  Slot  Name   Signature
            0       8     0  this   Lscala/collection/mutable/ArrayBuffer$;
            0       8     1 start   Ljava/lang/Object;
            0       8     2   len   I
            0       8     3     f   Lscala/Function1;
    MethodParameters:
      Name                           Flags
      start                          final
      len                            final
      f                              final

  public java.lang.Object unfold(java.lang.Object, scala.Function1);
    descriptor: (Ljava/lang/Object;Lscala/Function1;)Ljava/lang/Object;
    flags: (0x0001) ACC_PUBLIC
    Code:
      stack=3, locals=3, args_size=3
         0: aload_0
         1: aload_1
         2: aload_2
         3: invokestatic  #90                 // InterfaceMethod scala/collection/IterableFactory.unfold$:(Lscala/collection/IterableFactory;Ljava/lang/Object;Lscala/Function1;)Ljava/lang/Object;
         6: areturn
      LineNumberTable:
        line 266: 0
      LocalVariableTable:
        Start  Length  Slot  Name   Signature
            0       7     0  this   Lscala/collection/mutable/ArrayBuffer$;
            0       7     1  init   Ljava/lang/Object;
            0       7     2     f   Lscala/Function1;
    MethodParameters:
      Name                           Flags
      init                           final
      f                              final

  public java.lang.Object range(java.lang.Object, java.lang.Object, scala.math.Integral);
    descriptor: (Ljava/lang/Object;Ljava/lang/Object;Lscala/math/Integral;)Ljava/lang/Object;
    flags: (0x0001) ACC_PUBLIC
    Code:
      stack=4, locals=4, args_size=4
         0: aload_0
         1: aload_1
         2: aload_2
         3: aload_3
         4: invokestatic  #98                 // InterfaceMethod scala/collection/IterableFactory.range$:(Lscala/collection/IterableFactory;Ljava/lang/Object;Ljava/lang/Object;Lscala/math/Integral;)Ljava/lang/Object;
         7: areturn
      LineNumberTable:
        line 266: 0
      LocalVariableTable:
        Start  Length  Slot  Name   Signature
            0       8     0  this   Lscala/collection/mutable/ArrayBuffer$;
            0       8     1 start   Ljava/lang/Object;
            0       8     2   end   Ljava/lang/Object;
            0       8     3 evidence$3   Lscala/math/Integral;
    MethodParameters:
      Name                           Flags
      start                          final
      end                            final
      evidence$3                     final

  public java.lang.Object range(java.lang.Object, java.lang.Object, java.lang.Object, scala.math.Integral);
    descriptor: (Ljava/lang/Object;Ljava/lang/Object;Ljava/lang/Object;Lscala/math/Integral;)Ljava/lang/Object;
    flags: (0x0001) ACC_PUBLIC
    Code:
      stack=5, locals=5, args_size=5
         0: aload_0
         1: aload_1
         2: aload_2
         3: aload_3
         4: aload         4
         6: invokestatic  #105                // InterfaceMethod scala/collection/IterableFactory.range$:(Lscala/collection/IterableFactory;Ljava/lang/Object;Ljava/lang/Object;Ljava/lang/Object;Lscala/math/Integral;)Ljava/lang/Object;
         9: areturn
      LineNumberTable:
        line 266: 0
      LocalVariableTable:
        Start  Length  Slot  Name   Signature
            0      10     0  this   Lscala/collection/mutable/ArrayBuffer$;
            0      10     1 start   Ljava/lang/Object;
            0      10     2   end   Ljava/lang/Object;
            0      10     3  step   Ljava/lang/Object;
            0      10     4 evidence$4   Lscala/math/Integral;
    MethodParameters:
      Name                           Flags
      start                          final
      end                            final
      step                           final
      evidence$4                     final

  public java.lang.Object fill(int, int, scala.Function0);
    descriptor: (IILscala/Function0;)Ljava/lang/Object;
    flags: (0x0001) ACC_PUBLIC
    Code:
      stack=4, locals=4, args_size=4
         0: aload_0
         1: iload_1
         2: iload_2
         3: aload_3
         4: invokestatic  #111                // InterfaceMethod scala/collection/IterableFactory.fill$:(Lscala/collection/IterableFactory;IILscala/Function0;)Ljava/lang/Object;
         7: areturn
      LineNumberTable:
        line 266: 0
      LocalVariableTable:
        Start  Length  Slot  Name   Signature
            0       8     0  this   Lscala/collection/mutable/ArrayBuffer$;
            0       8     1    n1   I
            0       8     2    n2   I
            0       8     3  elem   Lscala/Function0;
    MethodParameters:
      Name                           Flags
      n1                             final
      n2                             final
      elem                           final

  public java.lang.Object fill(int, int, int, scala.Function0);
    descriptor: (IIILscala/Function0;)Ljava/lang/Object;
    flags: (0x0001) ACC_PUBLIC
    Code:
      stack=5, locals=5, args_size=5
         0: aload_0
         1: iload_1
         2: iload_2
         3: iload_3
         4: aload         4
         6: invokestatic  #116                // InterfaceMethod scala/collection/IterableFactory.fill$:(Lscala/collection/IterableFactory;IIILscala/Function0;)Ljava/lang/Object;
         9: areturn
      LineNumberTable:
        line 266: 0
      LocalVariableTable:
        Start  Length  Slot  Name   Signature
            0      10     0  this   Lscala/collection/mutable/ArrayBuffer$;
            0      10     1    n1   I
            0      10     2    n2   I
            0      10     3    n3   I
            0      10     4  elem   Lscala/Function0;
    MethodParameters:
      Name                           Flags
      n1                             final
      n2                             final
      n3                             final
      elem                           final

  public java.lang.Object fill(int, int, int, int, scala.Function0);
    descriptor: (IIIILscala/Function0;)Ljava/lang/Object;
    flags: (0x0001) ACC_PUBLIC
    Code:
      stack=6, locals=6, args_size=6
         0: aload_0
         1: iload_1
         2: iload_2
         3: iload_3
         4: iload         4
         6: aload         5
         8: invokestatic  #121                // InterfaceMethod scala/collection/IterableFactory.fill$:(Lscala/collection/IterableFactory;IIIILscala/Function0;)Ljava/lang/Object;
        11: areturn
      LineNumberTable:
        line 266: 0
      LocalVariableTable:
        Start  Length  Slot  Name   Signature
            0      12     0  this   Lscala/collection/mutable/ArrayBuffer$;
            0      12     1    n1   I
            0      12     2    n2   I
            0      12     3    n3   I
            0      12     4    n4   I
            0      12     5  elem   Lscala/Function0;
    MethodParameters:
      Name                           Flags
      n1                             final
      n2                             final
      n3                             final
      n4                             final
      elem                           final

  public java.lang.Object fill(int, int, int, int, int, scala.Function0);
    descriptor: (IIIIILscala/Function0;)Ljava/lang/Object;
    flags: (0x0001) ACC_PUBLIC
    Code:
      stack=7, locals=7, args_size=7
         0: aload_0
         1: iload_1
         2: iload_2
         3: iload_3
         4: iload         4
         6: iload         5
         8: aload         6
        10: invokestatic  #126                // InterfaceMethod scala/collection/IterableFactory.fill$:(Lscala/collection/IterableFactory;IIIIILscala/Function0;)Ljava/lang/Object;
        13: areturn
      LineNumberTable:
        line 266: 0
      LocalVariableTable:
        Start  Length  Slot  Name   Signature
            0      14     0  this   Lscala/collection/mutable/ArrayBuffer$;
            0      14     1    n1   I
            0      14     2    n2   I
            0      14     3    n3   I
            0      14     4    n4   I
            0      14     5    n5   I
            0      14     6  elem   Lscala/Function0;
    MethodParameters:
      Name                           Flags
      n1                             final
      n2                             final
      n3                             final
      n4                             final
      n5                             final
      elem                           final

  public java.lang.Object tabulate(int, int, scala.Function2);
    descriptor: (IILscala/Function2;)Ljava/lang/Object;
    flags: (0x0001) ACC_PUBLIC
    Code:
      stack=4, locals=4, args_size=4
         0: aload_0
         1: iload_1
         2: iload_2
         3: aload_3
         4: invokestatic  #130                // InterfaceMethod scala/collection/IterableFactory.tabulate$:(Lscala/collection/IterableFactory;IILscala/Function2;)Ljava/lang/Object;
         7: areturn
      LineNumberTable:
        line 266: 0
      LocalVariableTable:
        Start  Length  Slot  Name   Signature
            0       8     0  this   Lscala/collection/mutable/ArrayBuffer$;
            0       8     1    n1   I
            0       8     2    n2   I
            0       8     3     f   Lscala/Function2;
    MethodParameters:
      Name                           Flags
      n1                             final
      n2                             final
      f                              final

  public java.lang.Object tabulate(int, int, int, scala.Function3);
    descriptor: (IIILscala/Function3;)Ljava/lang/Object;
    flags: (0x0001) ACC_PUBLIC
    Code:
      stack=5, locals=5, args_size=5
         0: aload_0
         1: iload_1
         2: iload_2
         3: iload_3
         4: aload         4
         6: invokestatic  #135                // InterfaceMethod scala/collection/IterableFactory.tabulate$:(Lscala/collection/IterableFactory;IIILscala/Function3;)Ljava/lang/Object;
         9: areturn
      LineNumberTable:
        line 266: 0
      LocalVariableTable:
        Start  Length  Slot  Name   Signature
            0      10     0  this   Lscala/collection/mutable/ArrayBuffer$;
            0      10     1    n1   I
            0      10     2    n2   I
            0      10     3    n3   I
            0      10     4     f   Lscala/Function3;
    MethodParameters:
      Name                           Flags
      n1                             final
      n2                             final
      n3                             final
      f                              final

  public java.lang.Object tabulate(int, int, int, int, scala.Function4);
    descriptor: (IIIILscala/Function4;)Ljava/lang/Object;
    flags: (0x0001) ACC_PUBLIC
    Code:
      stack=6, locals=6, args_size=6
         0: aload_0
         1: iload_1
         2: iload_2
         3: iload_3
         4: iload         4
         6: aload         5
         8: invokestatic  #140                // InterfaceMethod scala/collection/IterableFactory.tabulate$:(Lscala/collection/IterableFactory;IIIILscala/Function4;)Ljava/lang/Object;
        11: areturn
      LineNumberTable:
        line 266: 0
      LocalVariableTable:
        Start  Length  Slot  Name   Signature
            0      12     0  this   Lscala/collection/mutable/ArrayBuffer$;
            0      12     1    n1   I
            0      12     2    n2   I
            0      12     3    n3   I
            0      12     4    n4   I
            0      12     5     f   Lscala/Function4;
    MethodParameters:
      Name                           Flags
      n1                             final
      n2                             final
      n3                             final
      n4                             final
      f                              final

  public java.lang.Object tabulate(int, int, int, int, int, scala.Function5);
    descriptor: (IIIIILscala/Function5;)Ljava/lang/Object;
    flags: (0x0001) ACC_PUBLIC
    Code:
      stack=7, locals=7, args_size=7
         0: aload_0
         1: iload_1
         2: iload_2
         3: iload_3
         4: iload         4
         6: iload         5
         8: aload         6
        10: invokestatic  #145                // InterfaceMethod scala/collection/IterableFactory.tabulate$:(Lscala/collection/IterableFactory;IIIIILscala/Function5;)Ljava/lang/Object;
        13: areturn
      LineNumberTable:
        line 266: 0
      LocalVariableTable:
        Start  Length  Slot  Name   Signature
            0      14     0  this   Lscala/collection/mutable/ArrayBuffer$;
            0      14     1    n1   I
            0      14     2    n2   I
            0      14     3    n3   I
            0      14     4    n4   I
            0      14     5    n5   I
            0      14     6     f   Lscala/Function5;
    MethodParameters:
      Name                           Flags
      n1                             final
      n2                             final
      n3                             final
      n4                             final
      n5                             final
      f                              final

  public <A extends java.lang.Object> scala.collection.Factory<A, scala.collection.mutable.ArrayBuffer<A>> iterableFactory();
    descriptor: ()Lscala/collection/Factory;
    flags: (0x0001) ACC_PUBLIC
    Code:
      stack=1, locals=1, args_size=1
         0: aload_0
         1: invokestatic  #153                // InterfaceMethod scala/collection/IterableFactory.iterableFactory$:(Lscala/collection/IterableFactory;)Lscala/collection/Factory;
         4: areturn
      LineNumberTable:
        line 266: 0
      LocalVariableTable:
        Start  Length  Slot  Name   Signature
            0       5     0  this   Lscala/collection/mutable/ArrayBuffer$;
    Signature: #149                         // <A:Ljava/lang/Object;>()Lscala/collection/Factory<TA;Lscala/collection/mutable/ArrayBuffer<TA;>;>;

  public final int DefaultInitialSize();
    descriptor: ()I
    flags: (0x0011) ACC_PUBLIC, ACC_FINAL
    Code:
      stack=1, locals=1, args_size=1
         0: bipush        16
         2: ireturn
      LocalVariableTable:
        Start  Length  Slot  Name   Signature
            0       3     0  this   Lscala/collection/mutable/ArrayBuffer$;

  public <B extends java.lang.Object> scala.collection.mutable.ArrayBuffer<B> from(scala.collection.IterableOnce<B>);
    descriptor: (Lscala/collection/IterableOnce;)Lscala/collection/mutable/ArrayBuffer;
    flags: (0x0001) ACC_PUBLIC
    Code:
      stack=4, locals=7, args_size=2
         0: aload_1
         1: invokeinterface #164,  1          // InterfaceMethod scala/collection/IterableOnce.knownSize:()I
         6: istore_2
         7: iload_2
         8: iconst_0
         9: if_icmplt     105
        12: getstatic     #169                // Field scala/runtime/RichInt$.MODULE$:Lscala/runtime/RichInt$;
        15: pop
        16: bipush        16
        18: istore        4
        20: getstatic     #174                // Field scala/math/package$.MODULE$:Lscala/math/package$;
        23: pop
        24: iload_2
        25: iload         4
        27: invokestatic  #180                // Method java/lang/Math.max:(II)I
        30: anewarray     #5                  // class java/lang/Object
        33: astore_3
        34: getstatic     #185                // Field scala/collection/IterableOnce$.MODULE$:Lscala/collection/IterableOnce$;
        37: pop
        38: getstatic     #185                // Field scala/collection/IterableOnce$.MODULE$:Lscala/collection/IterableOnce$;
        41: pop
        42: iconst_0
        43: istore        5
        45: getstatic     #185                // Field scala/collection/IterableOnce$.MODULE$:Lscala/collection/IterableOnce$;
        48: pop
        49: ldc           #186                // int 2147483647
        51: istore        6
        53: aload_1
        54: instanceof    #188                // class scala/collection/Iterable
        57: ifeq          78
        60: aload_1
        61: checkcast     #188                // class scala/collection/Iterable
        64: aload_3
        65: iload         5
        67: iload         6
        69: invokeinterface #192,  4          // InterfaceMethod scala/collection/Iterable.copyToArray:(Ljava/lang/Object;II)I
        74: pop
        75: goto          95
        78: aload_1
        79: invokeinterface #196,  1          // InterfaceMethod scala/collection/IterableOnce.iterator:()Lscala/collection/Iterator;
        84: aload_3
        85: iload         5
        87: iload         6
        89: invokeinterface #199,  4          // InterfaceMethod scala/collection/Iterator.copyToArray:(Ljava/lang/Object;II)I
        94: pop
        95: new           #201                // class scala/collection/mutable/ArrayBuffer
        98: dup
        99: aload_3
       100: iload_2
       101: invokespecial #204                // Method scala/collection/mutable/ArrayBuffer."<init>":([Ljava/lang/Object;I)V
       104: areturn
       105: new           #201                // class scala/collection/mutable/ArrayBuffer
       108: dup
       109: invokespecial #205                // Method scala/collection/mutable/ArrayBuffer."<init>":()V
       112: aload_1
       113: invokeinterface #211,  2          // InterfaceMethod scala/collection/mutable/Growable.addAll:(Lscala/collection/IterableOnce;)Lscala/collection/mutable/Growable;
       118: checkcast     #201                // class scala/collection/mutable/ArrayBuffer
       121: areturn
      StackMapTable: number_of_entries = 3
        frame_type = 255 /* full_frame */
          offset_delta = 78
          locals = [ class scala/collection/mutable/ArrayBuffer$, class scala/collection/IterableOnce, int, class "[Ljava/lang/Object;", int, int, int ]
          stack = []
        frame_type = 16 /* same */
        frame_type = 255 /* full_frame */
          offset_delta = 9
          locals = [ class scala/collection/mutable/ArrayBuffer$, class scala/collection/IterableOnce, int ]
          stack = []
      LineNumberTable:
        line 271: 0
        line 272: 7
        line 273: 12
        line 274: 34
        line 275: 95
        line 277: 105
      LocalVariableTable:
        Start  Length  Slot  Name   Signature
           34      70     3 array   [Ljava/lang/Object;
            7     114     2     k   I
            0     122     0  this   Lscala/collection/mutable/ArrayBuffer$;
            0     122     1  coll   Lscala/collection/IterableOnce;
           20      10     4 max$extension_that   I
    Signature: #158                         // <B:Ljava/lang/Object;>(Lscala/collection/IterableOnce<TB;>;)Lscala/collection/mutable/ArrayBuffer<TB;>;
    MethodParameters:
      Name                           Flags
      coll                           final

  public <A extends java.lang.Object> scala.collection.mutable.Builder<A, scala.collection.mutable.ArrayBuffer<A>> newBuilder();
    descriptor: ()Lscala/collection/mutable/Builder;
    flags: (0x0001) ACC_PUBLIC
    Code:
      stack=2, locals=1, args_size=1
         0: new           #10                 // class scala/collection/mutable/ArrayBuffer$$anon$1
         3: dup
         4: invokespecial #221                // Method scala/collection/mutable/ArrayBuffer$$anon$1."<init>":()V
         7: areturn
      LineNumberTable:
        line 281: 0
      LocalVariableTable:
        Start  Length  Slot  Name   Signature
            0       8     0  this   Lscala/collection/mutable/ArrayBuffer$;
    Signature: #220                         // <A:Ljava/lang/Object;>()Lscala/collection/mutable/Builder<TA;Lscala/collection/mutable/ArrayBuffer<TA;>;>;

  public <A extends java.lang.Object> scala.collection.mutable.ArrayBuffer<A> empty();
    descriptor: ()Lscala/collection/mutable/ArrayBuffer;
    flags: (0x0001) ACC_PUBLIC
    Code:
      stack=2, locals=1, args_size=1
         0: new           #201                // class scala/collection/mutable/ArrayBuffer
         3: dup
         4: invokespecial #205                // Method scala/collection/mutable/ArrayBuffer."<init>":()V
         7: areturn
      LineNumberTable:
        line 285: 0
      LocalVariableTable:
        Start  Length  Slot  Name   Signature
            0       8     0  this   Lscala/collection/mutable/ArrayBuffer$;
    Signature: #224                         // <A:Ljava/lang/Object;>()Lscala/collection/mutable/ArrayBuffer<TA;>;

  public java.lang.Object[] scala$collection$mutable$ArrayBuffer$$ensureSize(java.lang.Object[], int, int);
    descriptor: ([Ljava/lang/Object;II)[Ljava/lang/Object;
    flags: (0x0001) ACC_PUBLIC
    Code:
      stack=6, locals=6, args_size=4
         0: iload_3
         1: aload_1
         2: arraylength
         3: if_icmpgt     8
         6: aload_1
         7: areturn
         8: getstatic     #231                // Field scala/util/ChainingOps$.MODULE$:Lscala/util/ChainingOps$;
        11: pop
        12: getstatic     #234                // Field scala/util/package$chaining$.MODULE$:Lscala/util/package$chaining$;
        15: pop
        16: aload_1
        17: arraylength
        18: iload_2
        19: iload_3
        20: invokestatic  #238                // Method resizeEnsuring$1:(III)I
        23: anewarray     #5                  // class java/lang/Object
        26: astore        4
        28: aload         4
        30: aconst_null
        31: astore        4
        33: astore        5
        35: getstatic     #243                // Field scala/Array$.MODULE$:Lscala/Array$;
        38: aload_1
        39: iconst_0
        40: aload         5
        42: iconst_0
        43: iload_2
        44: invokevirtual #247                // Method scala/Array$.copy:(Ljava/lang/Object;ILjava/lang/Object;II)V
        47: aload         5
        49: areturn
      StackMapTable: number_of_entries = 1
        frame_type = 8 /* same */
      LineNumberTable:
        line 299: 0
        line 300: 12
        line 300: 35
        line 300: 47
      LocalVariableTable:
        Start  Length  Slot  Name   Signature
            0      50     0  this   Lscala/collection/mutable/ArrayBuffer$;
            0      50     1 array   [Ljava/lang/Object;
            0      50     2   end   I
            0      50     3     n   I
           35      12     5 tap$extension_$this   Ljava/lang/Object;
    MethodParameters:
      Name                           Flags
      array                          final
      end                            final
      n                              final

  public java.lang.Object[] scala$collection$mutable$ArrayBuffer$$downsize(java.lang.Object[], int);
    descriptor: ([Ljava/lang/Object;I)[Ljava/lang/Object;
    flags: (0x0001) ACC_PUBLIC
    Code:
      stack=6, locals=5, args_size=3
         0: iload_2
         1: aload_1
         2: arraylength
         3: if_icmplt     8
         6: aload_1
         7: areturn
         8: getstatic     #231                // Field scala/util/ChainingOps$.MODULE$:Lscala/util/ChainingOps$;
        11: pop
        12: getstatic     #234                // Field scala/util/package$chaining$.MODULE$:Lscala/util/package$chaining$;
        15: pop
        16: aload_1
        17: arraylength
        18: iload_2
        19: invokestatic  #254                // Method resizeDown$1:(II)I
        22: anewarray     #5                  // class java/lang/Object
        25: astore_3
        26: aload_3
        27: aconst_null
        28: astore_3
        29: astore        4
        31: getstatic     #243                // Field scala/Array$.MODULE$:Lscala/Array$;
        34: aload_1
        35: iconst_0
        36: aload         4
        38: iconst_0
        39: iload_2
        40: invokevirtual #247                // Method scala/Array$.copy:(Ljava/lang/Object;ILjava/lang/Object;II)V
        43: aload         4
        45: areturn
      StackMapTable: number_of_entries = 1
        frame_type = 8 /* same */
      LineNumberTable:
        line 312: 0
        line 313: 12
        line 313: 31
        line 313: 43
      LocalVariableTable:
        Start  Length  Slot  Name   Signature
            0      46     0  this   Lscala/collection/mutable/ArrayBuffer$;
            0      46     1 array   [Ljava/lang/Object;
            0      46     2 requiredLength   I
           31      12     4 tap$extension_$this   Ljava/lang/Object;
    MethodParameters:
      Name                           Flags
      array                          final
      requiredLength                 final

  private java.lang.Object writeReplace();
    descriptor: ()Ljava/lang/Object;
    flags: (0x0002) ACC_PRIVATE
    Code:
      stack=3, locals=1, args_size=1
         0: new           #258                // class scala/runtime/ModuleSerializationProxy
         3: dup
         4: ldc           #2                  // class scala/collection/mutable/ArrayBuffer$
         6: invokespecial #261                // Method scala/runtime/ModuleSerializationProxy."<init>":(Ljava/lang/Class;)V
         9: areturn
      LineNumberTable:
        line 266: 0
      LocalVariableTable:
        Start  Length  Slot  Name   Signature
            0      10     0  this   Lscala/collection/mutable/ArrayBuffer$;

  public java.lang.Object concat(scala.collection.immutable.Seq);
    descriptor: (Lscala/collection/immutable/Seq;)Ljava/lang/Object;
    flags: (0x1041) ACC_PUBLIC, ACC_BRIDGE, ACC_SYNTHETIC
    Code:
      stack=2, locals=2, args_size=2
         0: aload_0
         1: aload_1
         2: invokevirtual #263                // Method concat:(Lscala/collection/immutable/Seq;)Lscala/collection/SeqOps;
         5: areturn
      LineNumberTable:
        line 266: 0
      LocalVariableTable:
        Start  Length  Slot  Name   Signature
            0       6     0  this   Lscala/collection/mutable/ArrayBuffer$;
            0       6     1   xss   Lscala/collection/immutable/Seq;
    MethodParameters:
      Name                           Flags
      xss                            final

  public java.lang.Object tabulate(int, scala.Function1);
    descriptor: (ILscala/Function1;)Ljava/lang/Object;
    flags: (0x1041) ACC_PUBLIC, ACC_BRIDGE, ACC_SYNTHETIC
    Code:
      stack=3, locals=3, args_size=3
         0: aload_0
         1: iload_1
         2: aload_2
         3: invokevirtual #266                // Method tabulate:(ILscala/Function1;)Lscala/collection/SeqOps;
         6: areturn
      LineNumberTable:
        line 266: 0
      LocalVariableTable:
        Start  Length  Slot  Name   Signature
            0       7     0  this   Lscala/collection/mutable/ArrayBuffer$;
            0       7     1     n   I
            0       7     2     f   Lscala/Function1;
    MethodParameters:
      Name                           Flags
      n                              final
      f                              final

  public java.lang.Object fill(int, scala.Function0);
    descriptor: (ILscala/Function0;)Ljava/lang/Object;
    flags: (0x1041) ACC_PUBLIC, ACC_BRIDGE, ACC_SYNTHETIC
    Code:
      stack=3, locals=3, args_size=3
         0: aload_0
         1: iload_1
         2: aload_2
         3: invokevirtual #269                // Method fill:(ILscala/Function0;)Lscala/collection/SeqOps;
         6: areturn
      LineNumberTable:
        line 266: 0
      LocalVariableTable:
        Start  Length  Slot  Name   Signature
            0       7     0  this   Lscala/collection/mutable/ArrayBuffer$;
            0       7     1     n   I
            0       7     2  elem   Lscala/Function0;
    MethodParameters:
      Name                           Flags
      n                              final
      elem                           final

  public java.lang.Object empty();
    descriptor: ()Ljava/lang/Object;
    flags: (0x1041) ACC_PUBLIC, ACC_BRIDGE, ACC_SYNTHETIC
    Code:
      stack=1, locals=1, args_size=1
         0: aload_0
         1: invokevirtual #271                // Method empty:()Lscala/collection/mutable/ArrayBuffer;
         4: areturn
      LineNumberTable:
        line 266: 0
      LocalVariableTable:
        Start  Length  Slot  Name   Signature
            0       5     0  this   Lscala/collection/mutable/ArrayBuffer$;

  public java.lang.Object from(scala.collection.IterableOnce);
    descriptor: (Lscala/collection/IterableOnce;)Ljava/lang/Object;
    flags: (0x1041) ACC_PUBLIC, ACC_BRIDGE, ACC_SYNTHETIC
    Code:
      stack=2, locals=2, args_size=2
         0: aload_0
         1: aload_1
         2: invokevirtual #275                // Method from:(Lscala/collection/IterableOnce;)Lscala/collection/mutable/ArrayBuffer;
         5: areturn
      LineNumberTable:
        line 266: 0
      LocalVariableTable:
        Start  Length  Slot  Name   Signature
            0       6     0  this   Lscala/collection/mutable/ArrayBuffer$;
            0       6     1 source   Lscala/collection/IterableOnce;
    MethodParameters:
      Name                           Flags
      source                         final

  private static final int resizeEnsuring$1(int, int, int);
    descriptor: (III)I
    flags: (0x001a) ACC_PRIVATE, ACC_STATIC, ACC_FINAL
    Code:
      stack=5, locals=5, args_size=3
         0: iload_0
         1: i2l
         2: lstore_3
         3: getstatic     #174                // Field scala/math/package$.MODULE$:Lscala/math/package$;
         6: pop
         7: lload_3
         8: ldc2_w        #277                // long 2l
        11: lmul
        12: ldc2_w        #279                // long 16l
        15: invokestatic  #283                // Method java/lang/Math.max:(JJ)J
        18: lstore_3
        19: lload_3
        20: iload_2
        21: i2l
        22: lcmp
        23: ifge          35
        26: lload_3
        27: ldc2_w        #277                // long 2l
        30: lmul
        31: lstore_3
        32: goto          19
        35: lload_3
        36: ldc2_w        #284                // long 2147483647l
        39: lcmp
        40: ifgt          46
        43: lload_3
        44: l2i
        45: ireturn
        46: iload_1
        47: ldc           #186                // int 2147483647
        49: if_icmpne     90
        52: new           #287                // class java/lang/Exception
        55: dup
        56: new           #289                // class java/lang/StringBuilder
        59: dup
        60: ldc_w         #290                // int 64
        63: invokespecial #293                // Method java/lang/StringBuilder."<init>":(I)V
        66: ldc_w         #295                // String Collections can not have more than
        69: invokevirtual #299                // Method java/lang/StringBuilder.append:(Ljava/lang/String;)Ljava/lang/StringBuilder;
        72: ldc           #186                // int 2147483647
        74: invokevirtual #302                // Method java/lang/StringBuilder.append:(I)Ljava/lang/StringBuilder;
        77: ldc_w         #304                // String  elements
        80: invokevirtual #299                // Method java/lang/StringBuilder.append:(Ljava/lang/String;)Ljava/lang/StringBuilder;
        83: invokevirtual #308                // Method java/lang/StringBuilder.toString:()Ljava/lang/String;
        86: invokespecial #311                // Method java/lang/Exception."<init>":(Ljava/lang/String;)V
        89: athrow
        90: ldc           #186                // int 2147483647
        92: ireturn
      StackMapTable: number_of_entries = 4
        frame_type = 252 /* append */
          offset_delta = 19
          locals = [ long ]
        frame_type = 15 /* same */
        frame_type = 10 /* same */
        frame_type = 43 /* same */
      LineNumberTable:
        line 292: 0
        line 293: 3
        line 294: 19
        line 295: 35
        line 296: 46
        line 297: 90
      LocalVariableTable:
        Start  Length  Slot  Name   Signature
            3      89     3 newSize   J
            0      93     0 length   I
            0      93     1   end   I
            0      93     2     n   I
    MethodParameters:
      Name                           Flags
      length                         final
      end                            final
      n                              final

  public static final void $anonfun$ensureSize$1(java.lang.Object[], int, java.lang.Object[]);
    descriptor: ([Ljava/lang/Object;I[Ljava/lang/Object;)V
    flags: (0x1019) ACC_PUBLIC, ACC_STATIC, ACC_FINAL, ACC_SYNTHETIC
    Code:
      stack=6, locals=3, args_size=3
         0: getstatic     #243                // Field scala/Array$.MODULE$:Lscala/Array$;
         3: aload_0
         4: iconst_0
         5: aload_2
         6: iconst_0
         7: iload_1
         8: invokevirtual #247                // Method scala/Array$.copy:(Ljava/lang/Object;ILjava/lang/Object;II)V
        11: return
      LineNumberTable:
        line 300: 0
      LocalVariableTable:
        Start  Length  Slot  Name   Signature
            0      12     0 array$1   [Ljava/lang/Object;
            0      12     1 end$1   I
            0      12     2   x$1   [Ljava/lang/Object;
    MethodParameters:
      Name                           Flags
      array$1                        final
      end$1                          final
      x$1                            final

  private static final int resizeDown$1(int, int);
    descriptor: (II)I
    flags: (0x001a) ACC_PRIVATE, ACC_STATIC, ACC_FINAL
    Code:
      stack=4, locals=6, args_size=2
         0: iload_0
         1: i2l
         2: lstore_2
         3: lload_2
         4: ldc2_w        #284                // long 2147483647l
         7: lcmp
         8: ifne          15
        11: lload_2
        12: lconst_1
        13: ladd
        14: lstore_2
        15: getstatic     #174                // Field scala/math/package$.MODULE$:Lscala/math/package$;
        18: pop
        19: bipush        16
        21: istore        4
        23: iload_1
        24: iload         4
        26: invokestatic  #180                // Method java/lang/Math.max:(II)I
        29: istore        5
        31: lload_2
        32: ldc2_w        #277                // long 2l
        35: ldiv
        36: iload         5
        38: i2l
        39: lcmp
        40: iflt          52
        43: lload_2
        44: ldc2_w        #277                // long 2l
        47: ldiv
        48: lstore_2
        49: goto          31
        52: lload_2
        53: ldc2_w        #284                // long 2147483647l
        56: lcmp
        57: ifgt          63
        60: lload_2
        61: l2i
        62: ireturn
        63: ldc           #186                // int 2147483647
        65: ireturn
      StackMapTable: number_of_entries = 4
        frame_type = 252 /* append */
          offset_delta = 15
          locals = [ long ]
        frame_type = 253 /* append */
          offset_delta = 15
          locals = [ int, int ]
        frame_type = 20 /* same */
        frame_type = 10 /* same */
      LineNumberTable:
        line 304: 0
        line 306: 3
        line 307: 15
        line 308: 31
        line 309: 52
        line 310: 63
      LocalVariableTable:
        Start  Length  Slot  Name   Signature
            3      62     2 newSize   J
            0      66     0 length   I
            0      66     1 requiredLength   I
           23       8     4 max_y   I
    MethodParameters:
      Name                           Flags
      length                         final
      requiredLength                 final

  public static final void $anonfun$downsize$1(java.lang.Object[], int, java.lang.Object[]);
    descriptor: ([Ljava/lang/Object;I[Ljava/lang/Object;)V
    flags: (0x1019) ACC_PUBLIC, ACC_STATIC, ACC_FINAL, ACC_SYNTHETIC
    Code:
      stack=6, locals=3, args_size=3
         0: getstatic     #243                // Field scala/Array$.MODULE$:Lscala/Array$;
         3: aload_0
         4: iconst_0
         5: aload_2
         6: iconst_0
         7: iload_1
         8: invokevirtual #247                // Method scala/Array$.copy:(Ljava/lang/Object;ILjava/lang/Object;II)V
        11: return
      LineNumberTable:
        line 313: 0
      LocalVariableTable:
        Start  Length  Slot  Name   Signature
            0      12     0 array$2   [Ljava/lang/Object;
            0      12     1 requiredLength$1   I
            0      12     2   x$2   [Ljava/lang/Object;
    MethodParameters:
      Name                           Flags
      array$2                        final
      requiredLength$1               final
      x$2                            final

  private scala.collection.mutable.ArrayBuffer$();
    descriptor: ()V
    flags: (0x0002) ACC_PRIVATE
    Code:
      stack=1, locals=1, args_size=1
         0: aload_0
         1: invokespecial #323                // Method java/lang/Object."<init>":()V
         4: return
      LineNumberTable:
        line 266: 0
      LocalVariableTable:
        Start  Length  Slot  Name   Signature
            0       5     0  this   Lscala/collection/mutable/ArrayBuffer$;

  public static final java.lang.Object $anonfun$ensureSize$1$adapted(java.lang.Object[], int, java.lang.Object[]);
    descriptor: ([Ljava/lang/Object;I[Ljava/lang/Object;)Ljava/lang/Object;
    flags: (0x1019) ACC_PUBLIC, ACC_STATIC, ACC_FINAL, ACC_SYNTHETIC
    Code:
      stack=3, locals=3, args_size=3
         0: aload_0
         1: iload_1
         2: aload_2
         3: invokestatic  #327                // Method $anonfun$ensureSize$1:([Ljava/lang/Object;I[Ljava/lang/Object;)V
         6: getstatic     #333                // Field scala/runtime/BoxedUnit.UNIT:Lscala/runtime/BoxedUnit;
         9: areturn
      LineNumberTable:
        line 300: 0
      LocalVariableTable:
        Start  Length  Slot  Name   Signature
            0      10     0 array$1   [Ljava/lang/Object;
            0      10     1 end$1   I
            0      10     2   x$1   [Ljava/lang/Object;
    MethodParameters:
      Name                           Flags
      array$1                        final
      end$1                          final
      x$1                            final

  public static final java.lang.Object $anonfun$downsize$1$adapted(java.lang.Object[], int, java.lang.Object[]);
    descriptor: ([Ljava/lang/Object;I[Ljava/lang/Object;)Ljava/lang/Object;
    flags: (0x1019) ACC_PUBLIC, ACC_STATIC, ACC_FINAL, ACC_SYNTHETIC
    Code:
      stack=3, locals=3, args_size=3
         0: aload_0
         1: iload_1
         2: aload_2
         3: invokestatic  #336                // Method $anonfun$downsize$1:([Ljava/lang/Object;I[Ljava/lang/Object;)V
         6: getstatic     #333                // Field scala/runtime/BoxedUnit.UNIT:Lscala/runtime/BoxedUnit;
         9: areturn
      LineNumberTable:
        line 313: 0
      LocalVariableTable:
        Start  Length  Slot  Name   Signature
            0      10     0 array$2   [Ljava/lang/Object;
            0      10     1 requiredLength$1   I
            0      10     2   x$2   [Ljava/lang/Object;
    MethodParameters:
      Name                           Flags
      array$2                        final
      requiredLength$1               final
      x$2                            final
}
InnerClasses:
  public final #10;                       // class scala/collection/mutable/ArrayBuffer$$anon$1
  public static #15= #12 of #14;          // chaining$=class scala/util/package$chaining$ of class scala/util/package
Signature: #3                           // Ljava/lang/Object;Lscala/collection/StrictOptimizedSeqFactory<Lscala/collection/mutable/ArrayBuffer;>;
SourceFile: "ArrayBuffer.scala"
  ScalaInlineInfo: length = 0xBD (unknown attribute)
   01 01 00 25 01 3F 01 3A 01 01 4E 01 45 01 01 39
   01 3A 01 01 44 01 45 01 00 18 00 17 01 00 9A 00
   9B 01 00 42 00 43 01 00 30 00 43 01 00 30 00 31
   01 00 DE 01 00 01 00 DE 00 DF 01 00 1D 00 7A 01
   00 1D 00 75 01 00 1D 00 70 01 00 1D 00 6A 01 00
   1D 01 0B 01 00 1D 00 1E 01 00 9C 01 10 01 00 9C
   00 9D 01 00 93 00 94 01 00 4B 00 4C 01 00 DA 00
   DB 01 00 5B 00 64 01 00 5B 00 5C 01 00 FC 00 B2
   01 00 EB 00 EC 01 00 F9 00 FA 01 00 E1 00 E2 01
   00 28 00 8E 01 00 28 00 89 01 00 28 00 84 01 00
   28 00 7F 01 00 28 01 08 01 00 28 00 29 01 00 38
   00 39 01 00 54 00 55 01 00 FF 01 00 01
  Scala: length = 0x0 (unknown attribute)

