Classfile /Users/mw/Projects/slang-braindump/.jar/jar8/assemble/slang-braindump/assemble/content/scala/collection/mutable/ArrayBufferView$$anon$2.class
  Last modified May 29, 2022; size 798 bytes
  SHA-256 checksum 84e9acae1eb4c539112cb82598bbcd62335d4a6fd87fe953c1bac468b35df6b3
  Compiled from "ArrayBuffer.scala"
public final class scala.collection.mutable.ArrayBufferView$$anon$2 extends scala.collection.mutable.ArrayBuffer<A>
  minor version: 0
  major version: 52
  flags: (0x0031) ACC_PUBLIC, ACC_FINAL, ACC_SUPER
  this_class: #2                          // scala/collection/mutable/ArrayBufferView$$anon$2
  super_class: #5                         // scala/collection/mutable/ArrayBuffer
  interfaces: 0, fields: 0, methods: 1, attributes: 6
Constant pool:
   #1 = Utf8               scala/collection/mutable/ArrayBufferView$$anon$2
   #2 = Class              #1             // scala/collection/mutable/ArrayBufferView$$anon$2
   #3 = Utf8               Lscala/collection/mutable/ArrayBuffer<TA;>;
   #4 = Utf8               scala/collection/mutable/ArrayBuffer
   #5 = Class              #4             // scala/collection/mutable/ArrayBuffer
   #6 = Utf8               ArrayBuffer.scala
   #7 = Utf8               scala/collection/mutable/ArrayBufferView
   #8 = Class              #7             // scala/collection/mutable/ArrayBufferView
   #9 = Utf8               <init>
  #10 = Utf8               ([Ljava/lang/Object;I)V
  #11 = NameAndType        #9:#10         // "<init>":([Ljava/lang/Object;I)V
  #12 = Utf8               _array$1
  #13 = Utf8               _length$1
  #14 = Utf8               (I)V
  #15 = NameAndType        #9:#14         // "<init>":(I)V
  #16 = Methodref          #5.#15         // scala/collection/mutable/ArrayBuffer."<init>":(I)V
  #17 = Utf8               array_$eq
  #18 = Utf8               ([Ljava/lang/Object;)V
  #19 = NameAndType        #17:#18        // array_$eq:([Ljava/lang/Object;)V
  #20 = Methodref          #2.#19         // scala/collection/mutable/ArrayBufferView$$anon$2.array_$eq:([Ljava/lang/Object;)V
  #21 = Utf8               size0_$eq
  #22 = NameAndType        #21:#14        // size0_$eq:(I)V
  #23 = Methodref          #2.#22         // scala/collection/mutable/ArrayBufferView$$anon$2.size0_$eq:(I)V
  #24 = Utf8               this
  #25 = Utf8               Lscala/collection/mutable/ArrayBufferView$$anon$2;
  #26 = Utf8               [Ljava/lang/Object;
  #27 = Utf8               I
  #28 = Utf8               Code
  #29 = Utf8               LineNumberTable
  #30 = Utf8               LocalVariableTable
  #31 = Utf8               MethodParameters
  #32 = Utf8               InnerClasses
  #33 = Utf8               EnclosingMethod
  #34 = Utf8               Signature
  #35 = Utf8               SourceFile
  #36 = Utf8               ScalaInlineInfo
  #37 = Utf8               Scala
{
  public scala.collection.mutable.ArrayBufferView$$anon$2(java.lang.Object[], int);
    descriptor: ([Ljava/lang/Object;I)V
    flags: (0x0001) ACC_PUBLIC
    Code:
      stack=2, locals=3, args_size=3
         0: aload_0
         1: iconst_0
         2: invokespecial #16                 // Method scala/collection/mutable/ArrayBuffer."<init>":(I)V
         5: aload_0
         6: aload_1
         7: invokevirtual #20                 // Method array_$eq:([Ljava/lang/Object;)V
        10: aload_0
        11: iload_2
        12: invokevirtual #23                 // Method size0_$eq:(I)V
        15: return
      LineNumberTable:
        line 328: 0
        line 329: 5
        line 330: 10
        line 328: 15
      LocalVariableTable:
        Start  Length  Slot  Name   Signature
            0      16     0  this   Lscala/collection/mutable/ArrayBufferView$$anon$2;
            0      16     1 _array$1   [Ljava/lang/Object;
            0      16     2 _length$1   I
    MethodParameters:
      Name                           Flags
      _array$1                       final
      _length$1                      final
}
InnerClasses:
  public final #2;                        // class scala/collection/mutable/ArrayBufferView$$anon$2
EnclosingMethod: #8.#11                 // scala.collection.mutable.ArrayBufferView.<init>
Signature: #3                           // Lscala/collection/mutable/ArrayBuffer<TA;>;
SourceFile: "ArrayBuffer.scala"
  ScalaInlineInfo: length = 0x9 (unknown attribute)
   01 01 00 01 00 09 00 0A 01
  Scala: length = 0x0 (unknown attribute)

