Classfile /Users/mw/Projects/slang-braindump/.jar/jar8/assemble/slang-braindump/assemble/content/scala/collection/mutable/CollisionProofHashMap$.class
  Last modified May 29, 2022; size 7756 bytes
  SHA-256 checksum e958c46e7151c2c01c1cc80b12cee965d80b7f949f76eb5c7fa6e09e3734dbe6
  Compiled from "CollisionProofHashMap.scala"
public final class scala.collection.mutable.CollisionProofHashMap$ extends java.lang.Object implements scala.collection.SortedMapFactory<scala.collection.mutable.CollisionProofHashMap>
  minor version: 0
  major version: 52
  flags: (0x0031) ACC_PUBLIC, ACC_FINAL, ACC_SUPER
  this_class: #2                          // scala/collection/mutable/CollisionProofHashMap$
  super_class: #5                         // java/lang/Object
  interfaces: 1, fields: 2, methods: 20, attributes: 5
Constant pool:
    #1 = Utf8               scala/collection/mutable/CollisionProofHashMap$
    #2 = Class              #1            // scala/collection/mutable/CollisionProofHashMap$
    #3 = Utf8               Ljava/lang/Object;Lscala/collection/SortedMapFactory<Lscala/collection/mutable/CollisionProofHashMap;>;
    #4 = Utf8               java/lang/Object
    #5 = Class              #4            // java/lang/Object
    #6 = Utf8               scala/collection/SortedMapFactory
    #7 = Class              #6            // scala/collection/SortedMapFactory
    #8 = Utf8               CollisionProofHashMap.scala
    #9 = Utf8               scala/collection/mutable/CollisionProofHashMap$$anon$3
   #10 = Class              #9            // scala/collection/mutable/CollisionProofHashMap$$anon$3
   #11 = Utf8               scala/collection/mutable/CollisionProofHashMap$LLNode
   #12 = Class              #11           // scala/collection/mutable/CollisionProofHashMap$LLNode
   #13 = Utf8               scala/collection/mutable/CollisionProofHashMap
   #14 = Class              #13           // scala/collection/mutable/CollisionProofHashMap
   #15 = Utf8               LLNode
   #16 = Utf8               scala/collection/mutable/CollisionProofHashMap$RBNode
   #17 = Class              #16           // scala/collection/mutable/CollisionProofHashMap$RBNode
   #18 = Utf8               RBNode
   #19 = Utf8               MODULE$
   #20 = Utf8               Lscala/collection/mutable/CollisionProofHashMap$;
   #21 = Utf8               serialVersionUID
   #22 = Utf8               J
   #23 = Long               3l
   #25 = Utf8               <clinit>
   #26 = Utf8               ()V
   #27 = Utf8               <init>
   #28 = NameAndType        #27:#26       // "<init>":()V
   #29 = Methodref          #2.#28        // scala/collection/mutable/CollisionProofHashMap$."<init>":()V
   #30 = NameAndType        #19:#20       // MODULE$:Lscala/collection/mutable/CollisionProofHashMap$;
   #31 = Fieldref           #2.#30        // scala/collection/mutable/CollisionProofHashMap$.MODULE$:Lscala/collection/mutable/CollisionProofHashMap$;
   #32 = Utf8               apply
   #33 = Utf8               (Lscala/collection/immutable/Seq;Lscala/math/Ordering;)Ljava/lang/Object;
   #34 = Utf8               elems
   #35 = Utf8               evidence$38
   #36 = Utf8               apply$
   #37 = Utf8               (Lscala/collection/SortedMapFactory;Lscala/collection/immutable/Seq;Lscala/math/Ordering;)Ljava/lang/Object;
   #38 = NameAndType        #36:#37       // apply$:(Lscala/collection/SortedMapFactory;Lscala/collection/immutable/Seq;Lscala/math/Ordering;)Ljava/lang/Object;
   #39 = InterfaceMethodref #7.#38        // scala/collection/SortedMapFactory.apply$:(Lscala/collection/SortedMapFactory;Lscala/collection/immutable/Seq;Lscala/math/Ordering;)Ljava/lang/Object;
   #40 = Utf8               this
   #41 = Utf8               Lscala/collection/immutable/Seq;
   #42 = Utf8               Lscala/math/Ordering;
   #43 = Utf8               sortedMapFactory
   #44 = Utf8               (Lscala/math/Ordering;)Lscala/collection/Factory;
   #45 = Utf8               <K:Ljava/lang/Object;V:Ljava/lang/Object;>(Lscala/math/Ordering<TK;>;)Lscala/collection/Factory<Lscala/Tuple2<TK;TV;>;Lscala/collection/mutable/CollisionProofHashMap<TK;TV;>;>;
   #46 = Utf8               evidence$40
   #47 = Utf8               sortedMapFactory$
   #48 = Utf8               (Lscala/collection/SortedMapFactory;Lscala/math/Ordering;)Lscala/collection/Factory;
   #49 = NameAndType        #47:#48       // sortedMapFactory$:(Lscala/collection/SortedMapFactory;Lscala/math/Ordering;)Lscala/collection/Factory;
   #50 = InterfaceMethodref #7.#49        // scala/collection/SortedMapFactory.sortedMapFactory$:(Lscala/collection/SortedMapFactory;Lscala/math/Ordering;)Lscala/collection/Factory;
   #51 = Utf8               ordMsg
   #52 = Utf8               ()Ljava/lang/String;
   #53 = Utf8               No implicit Ordering[${K2}] found to build a CollisionProofHashMap[${K2}, ${V2}]. You may want to upcast to a Map[${K}, ${V}] first by calling `unsorted`.
   #54 = String             #53           // No implicit Ordering[${K2}] found to build a CollisionProofHashMap[${K2}, ${V2}]. You may want to upcast to a Map[${K}, ${V}] first by calling `unsorted`.
   #55 = Utf8               from
   #56 = Utf8               (Lscala/collection/IterableOnce;Lscala/math/Ordering;)Lscala/collection/mutable/CollisionProofHashMap;
   #57 = Utf8               <K:Ljava/lang/Object;V:Ljava/lang/Object;>(Lscala/collection/IterableOnce<Lscala/Tuple2<TK;TV;>;>;Lscala/math/Ordering<TK;>;)Lscala/collection/mutable/CollisionProofHashMap<TK;TV;>;
   #58 = Utf8               it
   #59 = Utf8               evidence$1
   #60 = Utf8               scala/collection/IterableOnce
   #61 = Class              #60           // scala/collection/IterableOnce
   #62 = Utf8               knownSize
   #63 = Utf8               ()I
   #64 = NameAndType        #62:#63       // knownSize:()I
   #65 = InterfaceMethodref #61.#64       // scala/collection/IterableOnce.knownSize:()I
   #66 = Double             0.75d
   #68 = Utf8               (IDLscala/math/Ordering;)V
   #69 = NameAndType        #27:#68       // "<init>":(IDLscala/math/Ordering;)V
   #70 = Methodref          #14.#69       // scala/collection/mutable/CollisionProofHashMap."<init>":(IDLscala/math/Ordering;)V
   #71 = Utf8               addAll
   #72 = Utf8               (Lscala/collection/IterableOnce;)Lscala/collection/mutable/CollisionProofHashMap;
   #73 = NameAndType        #71:#72       // addAll:(Lscala/collection/IterableOnce;)Lscala/collection/mutable/CollisionProofHashMap;
   #74 = Methodref          #14.#73       // scala/collection/mutable/CollisionProofHashMap.addAll:(Lscala/collection/IterableOnce;)Lscala/collection/mutable/CollisionProofHashMap;
   #75 = Utf8               k
   #76 = Utf8               I
   #77 = Utf8               cap
   #78 = Utf8               Lscala/collection/IterableOnce;
   #79 = Utf8               empty
   #80 = Utf8               (Lscala/math/Ordering;)Lscala/collection/mutable/CollisionProofHashMap;
   #81 = Utf8               <K:Ljava/lang/Object;V:Ljava/lang/Object;>(Lscala/math/Ordering<TK;>;)Lscala/collection/mutable/CollisionProofHashMap<TK;TV;>;
   #82 = Utf8               evidence$2
   #83 = Utf8               (Lscala/math/Ordering;)V
   #84 = NameAndType        #27:#83       // "<init>":(Lscala/math/Ordering;)V
   #85 = Methodref          #14.#84       // scala/collection/mutable/CollisionProofHashMap."<init>":(Lscala/math/Ordering;)V
   #86 = Utf8               newBuilder
   #87 = Utf8               (Lscala/math/Ordering;)Lscala/collection/mutable/Builder;
   #88 = Utf8               <K:Ljava/lang/Object;V:Ljava/lang/Object;>(Lscala/math/Ordering<TK;>;)Lscala/collection/mutable/Builder<Lscala/Tuple2<TK;TV;>;Lscala/collection/mutable/CollisionProofHashMap<TK;TV;>;>;
   #89 = Utf8               evidence$3
   #90 = Methodref          #10.#69       // scala/collection/mutable/CollisionProofHashMap$$anon$3."<init>":(IDLscala/math/Ordering;)V
   #91 = Utf8               (IDLscala/math/Ordering;)Lscala/collection/mutable/Builder;
   #92 = Utf8               <K:Ljava/lang/Object;V:Ljava/lang/Object;>(IDLscala/math/Ordering<TK;>;)Lscala/collection/mutable/Builder<Lscala/Tuple2<TK;TV;>;Lscala/collection/mutable/CollisionProofHashMap<TK;TV;>;>;
   #93 = Utf8               initialCapacity
   #94 = Utf8               loadFactor
   #95 = Utf8               evidence$4
   #96 = Utf8               D
   #97 = Utf8               defaultLoadFactor
   #98 = Utf8               ()D
   #99 = Utf8               defaultInitialCapacity
  #100 = Utf8               compare
  #101 = Utf8               (Ljava/lang/Object;ILscala/collection/mutable/CollisionProofHashMap$LLNode;Lscala/math/Ordering;)I
  #102 = Utf8               <K:Ljava/lang/Object;V:Ljava/lang/Object;>(TK;ILscala/collection/mutable/CollisionProofHashMap$LLNode<TK;TV;>;Lscala/math/Ordering<TK;>;)I
  #103 = Utf8               key
  #104 = Utf8               hash
  #105 = Utf8               node
  #106 = Utf8               ord
  #107 = NameAndType        #104:#63      // hash:()I
  #108 = Methodref          #12.#107      // scala/collection/mutable/CollisionProofHashMap$LLNode.hash:()I
  #109 = Utf8               ()Ljava/lang/Object;
  #110 = NameAndType        #103:#109     // key:()Ljava/lang/Object;
  #111 = Methodref          #12.#110      // scala/collection/mutable/CollisionProofHashMap$LLNode.key:()Ljava/lang/Object;
  #112 = Utf8               scala/math/Ordering
  #113 = Class              #112          // scala/math/Ordering
  #114 = Utf8               (Ljava/lang/Object;Ljava/lang/Object;)I
  #115 = NameAndType        #100:#114     // compare:(Ljava/lang/Object;Ljava/lang/Object;)I
  #116 = InterfaceMethodref #113.#115     // scala/math/Ordering.compare:(Ljava/lang/Object;Ljava/lang/Object;)I
  #117 = Utf8               i
  #118 = Utf8               Ljava/lang/Object;
  #119 = Utf8               Lscala/collection/mutable/CollisionProofHashMap$LLNode;
  #120 = Utf8               scala$collection$mutable$CollisionProofHashMap$$compare
  #121 = Utf8               (Ljava/lang/Object;ILscala/collection/mutable/CollisionProofHashMap$RBNode;Lscala/math/Ordering;)I
  #122 = Utf8               <K:Ljava/lang/Object;V:Ljava/lang/Object;>(TK;ILscala/collection/mutable/CollisionProofHashMap$RBNode<TK;TV;>;Lscala/math/Ordering<TK;>;)I
  #123 = Methodref          #17.#110      // scala/collection/mutable/CollisionProofHashMap$RBNode.key:()Ljava/lang/Object;
  #124 = Utf8               Lscala/collection/mutable/CollisionProofHashMap$RBNode;
  #125 = Utf8               treeifyThreshold
  #126 = Utf8               scala$collection$mutable$CollisionProofHashMap$$leaf
  #127 = Utf8               (Ljava/lang/Object;ILjava/lang/Object;ZLscala/collection/mutable/CollisionProofHashMap$RBNode;)Lscala/collection/mutable/CollisionProofHashMap$RBNode;
  #128 = Utf8               <A:Ljava/lang/Object;B:Ljava/lang/Object;>(TA;ITB;ZLscala/collection/mutable/CollisionProofHashMap$RBNode<TA;TB;>;)Lscala/collection/mutable/CollisionProofHashMap$RBNode<TA;TB;>;
  #129 = Utf8               value
  #130 = Utf8               red
  #131 = Utf8               parent
  #132 = Utf8               (Ljava/lang/Object;ILjava/lang/Object;ZLscala/collection/mutable/CollisionProofHashMap$RBNode;Lscala/collection/mutable/CollisionProofHashMap$RBNode;Lscala/collection/mutable/CollisionProofHashMap$RBNode;)V
  #133 = NameAndType        #27:#132      // "<init>":(Ljava/lang/Object;ILjava/lang/Object;ZLscala/collection/mutable/CollisionProofHashMap$RBNode;Lscala/collection/mutable/CollisionProofHashMap$RBNode;Lscala/collection/mutable/CollisionProofHashMap$RBNode;)V
  #134 = Methodref          #17.#133      // scala/collection/mutable/CollisionProofHashMap$RBNode."<init>":(Ljava/lang/Object;ILjava/lang/Object;ZLscala/collection/mutable/CollisionProofHashMap$RBNode;Lscala/collection/mutable/CollisionProofHashMap$RBNode;Lscala/collection/mutable/CollisionProofHashMap$RBNode;)V
  #135 = Utf8               Z
  #136 = Utf8               scala$collection$mutable$CollisionProofHashMap$$minNodeNonNull
  #137 = Utf8               (Lscala/collection/mutable/CollisionProofHashMap$RBNode;)Lscala/collection/mutable/CollisionProofHashMap$RBNode;
  #138 = Utf8               <A:Ljava/lang/Object;B:Ljava/lang/Object;>(Lscala/collection/mutable/CollisionProofHashMap$RBNode<TA;TB;>;)Lscala/collection/mutable/CollisionProofHashMap$RBNode<TA;TB;>;
  #139 = Utf8               left
  #140 = Utf8               ()Lscala/collection/mutable/CollisionProofHashMap$RBNode;
  #141 = NameAndType        #139:#140     // left:()Lscala/collection/mutable/CollisionProofHashMap$RBNode;
  #142 = Methodref          #17.#141      // scala/collection/mutable/CollisionProofHashMap$RBNode.left:()Lscala/collection/mutable/CollisionProofHashMap$RBNode;
  #143 = Utf8               scala$collection$mutable$CollisionProofHashMap$$successor
  #144 = Utf8               right
  #145 = NameAndType        #144:#140     // right:()Lscala/collection/mutable/CollisionProofHashMap$RBNode;
  #146 = Methodref          #17.#145      // scala/collection/mutable/CollisionProofHashMap$RBNode.right:()Lscala/collection/mutable/CollisionProofHashMap$RBNode;
  #147 = NameAndType        #136:#137     // scala$collection$mutable$CollisionProofHashMap$$minNodeNonNull:(Lscala/collection/mutable/CollisionProofHashMap$RBNode;)Lscala/collection/mutable/CollisionProofHashMap$RBNode;
  #148 = Methodref          #2.#147       // scala/collection/mutable/CollisionProofHashMap$.scala$collection$mutable$CollisionProofHashMap$$minNodeNonNull:(Lscala/collection/mutable/CollisionProofHashMap$RBNode;)Lscala/collection/mutable/CollisionProofHashMap$RBNode;
  #149 = NameAndType        #131:#140     // parent:()Lscala/collection/mutable/CollisionProofHashMap$RBNode;
  #150 = Methodref          #17.#149      // scala/collection/mutable/CollisionProofHashMap$RBNode.parent:()Lscala/collection/mutable/CollisionProofHashMap$RBNode;
  #151 = Utf8               x
  #152 = Utf8               y
  #153 = Utf8               writeReplace
  #154 = Utf8               scala/runtime/ModuleSerializationProxy
  #155 = Class              #154          // scala/runtime/ModuleSerializationProxy
  #156 = Utf8               (Ljava/lang/Class;)V
  #157 = NameAndType        #27:#156      // "<init>":(Ljava/lang/Class;)V
  #158 = Methodref          #155.#157     // scala/runtime/ModuleSerializationProxy."<init>":(Ljava/lang/Class;)V
  #159 = Utf8               (Lscala/math/Ordering;)Ljava/lang/Object;
  #160 = Utf8               evidence$36
  #161 = NameAndType        #79:#80       // empty:(Lscala/math/Ordering;)Lscala/collection/mutable/CollisionProofHashMap;
  #162 = Methodref          #2.#161       // scala/collection/mutable/CollisionProofHashMap$.empty:(Lscala/math/Ordering;)Lscala/collection/mutable/CollisionProofHashMap;
  #163 = Utf8               (Lscala/collection/IterableOnce;Lscala/math/Ordering;)Ljava/lang/Object;
  #164 = Utf8               evidence$37
  #165 = NameAndType        #55:#56       // from:(Lscala/collection/IterableOnce;Lscala/math/Ordering;)Lscala/collection/mutable/CollisionProofHashMap;
  #166 = Methodref          #2.#165       // scala/collection/mutable/CollisionProofHashMap$.from:(Lscala/collection/IterableOnce;Lscala/math/Ordering;)Lscala/collection/mutable/CollisionProofHashMap;
  #167 = Methodref          #5.#28        // java/lang/Object."<init>":()V
  #168 = Utf8               ConstantValue
  #169 = Utf8               Code
  #170 = Utf8               LineNumberTable
  #171 = Utf8               LocalVariableTable
  #172 = Utf8               MethodParameters
  #173 = Utf8               Signature
  #174 = Utf8               StackMapTable
  #175 = Utf8               InnerClasses
  #176 = Utf8               SourceFile
  #177 = Utf8               ScalaInlineInfo
  #178 = Utf8               Scala
{
  public static final scala.collection.mutable.CollisionProofHashMap$ MODULE$;
    descriptor: Lscala/collection/mutable/CollisionProofHashMap$;
    flags: (0x0019) ACC_PUBLIC, ACC_STATIC, ACC_FINAL

  private static final long serialVersionUID;
    descriptor: J
    flags: (0x001a) ACC_PRIVATE, ACC_STATIC, ACC_FINAL
    ConstantValue: long 3l

  public static {};
    descriptor: ()V
    flags: (0x0009) ACC_PUBLIC, ACC_STATIC
    Code:
      stack=2, locals=0, args_size=0
         0: new           #2                  // class scala/collection/mutable/CollisionProofHashMap$
         3: dup
         4: invokespecial #29                 // Method "<init>":()V
         7: putstatic     #31                 // Field MODULE$:Lscala/collection/mutable/CollisionProofHashMap$;
        10: getstatic     #31                 // Field MODULE$:Lscala/collection/mutable/CollisionProofHashMap$;
        13: pop
        14: return
      LineNumberTable:
        line 743: 0

  public java.lang.Object apply(scala.collection.immutable.Seq, scala.math.Ordering);
    descriptor: (Lscala/collection/immutable/Seq;Lscala/math/Ordering;)Ljava/lang/Object;
    flags: (0x0001) ACC_PUBLIC
    Code:
      stack=3, locals=3, args_size=3
         0: aload_0
         1: aload_1
         2: aload_2
         3: invokestatic  #39                 // InterfaceMethod scala/collection/SortedMapFactory.apply$:(Lscala/collection/SortedMapFactory;Lscala/collection/immutable/Seq;Lscala/math/Ordering;)Ljava/lang/Object;
         6: areturn
      LineNumberTable:
        line 743: 0
      LocalVariableTable:
        Start  Length  Slot  Name   Signature
            0       7     0  this   Lscala/collection/mutable/CollisionProofHashMap$;
            0       7     1 elems   Lscala/collection/immutable/Seq;
            0       7     2 evidence$38   Lscala/math/Ordering;
    MethodParameters:
      Name                           Flags
      elems                          final
      evidence$38                    final

  public <K extends java.lang.Object, V extends java.lang.Object> scala.collection.Factory<scala.Tuple2<K, V>, scala.collection.mutable.CollisionProofHashMap<K, V>> sortedMapFactory(scala.math.Ordering<K>);
    descriptor: (Lscala/math/Ordering;)Lscala/collection/Factory;
    flags: (0x0001) ACC_PUBLIC
    Code:
      stack=2, locals=2, args_size=2
         0: aload_0
         1: aload_1
         2: invokestatic  #50                 // InterfaceMethod scala/collection/SortedMapFactory.sortedMapFactory$:(Lscala/collection/SortedMapFactory;Lscala/math/Ordering;)Lscala/collection/Factory;
         5: areturn
      LineNumberTable:
        line 743: 0
      LocalVariableTable:
        Start  Length  Slot  Name   Signature
            0       6     0  this   Lscala/collection/mutable/CollisionProofHashMap$;
            0       6     1 evidence$40   Lscala/math/Ordering;
    Signature: #45                          // <K:Ljava/lang/Object;V:Ljava/lang/Object;>(Lscala/math/Ordering<TK;>;)Lscala/collection/Factory<Lscala/Tuple2<TK;TV;>;Lscala/collection/mutable/CollisionProofHashMap<TK;TV;>;>;
    MethodParameters:
      Name                           Flags
      evidence$40                    final

  public final java.lang.String ordMsg();
    descriptor: ()Ljava/lang/String;
    flags: (0x0011) ACC_PUBLIC, ACC_FINAL
    Code:
      stack=1, locals=1, args_size=1
         0: ldc           #54                 // String No implicit Ordering[${K2}] found to build a CollisionProofHashMap[${K2}, ${V2}]. You may want to upcast to a Map[${K}, ${V}] first by calling `unsorted`.
         2: areturn
      LocalVariableTable:
        Start  Length  Slot  Name   Signature
            0       3     0  this   Lscala/collection/mutable/CollisionProofHashMap$;

  public <K extends java.lang.Object, V extends java.lang.Object> scala.collection.mutable.CollisionProofHashMap<K, V> from(scala.collection.IterableOnce<scala.Tuple2<K, V>>, scala.math.Ordering<K>);
    descriptor: (Lscala/collection/IterableOnce;Lscala/math/Ordering;)Lscala/collection/mutable/CollisionProofHashMap;
    flags: (0x0001) ACC_PUBLIC
    Code:
      stack=6, locals=5, args_size=3
         0: aload_1
         1: invokeinterface #65,  1           // InterfaceMethod scala/collection/IterableOnce.knownSize:()I
         6: istore_3
         7: iload_3
         8: iconst_0
         9: if_icmple     24
        12: iload_3
        13: iconst_1
        14: iadd
        15: i2d
        16: ldc2_w        #66                 // double 0.75d
        19: ddiv
        20: d2i
        21: goto          26
        24: bipush        16
        26: istore        4
        28: new           #14                 // class scala/collection/mutable/CollisionProofHashMap
        31: dup
        32: iload         4
        34: ldc2_w        #66                 // double 0.75d
        37: aload_2
        38: invokespecial #70                 // Method scala/collection/mutable/CollisionProofHashMap."<init>":(IDLscala/math/Ordering;)V
        41: aload_1
        42: invokevirtual #74                 // Method scala/collection/mutable/CollisionProofHashMap.addAll:(Lscala/collection/IterableOnce;)Lscala/collection/mutable/CollisionProofHashMap;
        45: areturn
      StackMapTable: number_of_entries = 2
        frame_type = 252 /* append */
          offset_delta = 24
          locals = [ int ]
        frame_type = 65 /* same_locals_1_stack_item */
          stack = [ int ]
      LineNumberTable:
        line 747: 0
        line 748: 7
        line 762: 16
        line 748: 19
        line 765: 24
        line 748: 26
        line 749: 28
        line 762: 34
        line 749: 37
        line 35: 41
        line 749: 45
      LocalVariableTable:
        Start  Length  Slot  Name   Signature
            7      38     3     k   I
           28      17     4   cap   I
            0      46     0  this   Lscala/collection/mutable/CollisionProofHashMap$;
            0      46     1    it   Lscala/collection/IterableOnce;
            0      46     2 evidence$1   Lscala/math/Ordering;
    Signature: #57                          // <K:Ljava/lang/Object;V:Ljava/lang/Object;>(Lscala/collection/IterableOnce<Lscala/Tuple2<TK;TV;>;>;Lscala/math/Ordering<TK;>;)Lscala/collection/mutable/CollisionProofHashMap<TK;TV;>;
    MethodParameters:
      Name                           Flags
      it                             final
      evidence$1                     final

  public <K extends java.lang.Object, V extends java.lang.Object> scala.collection.mutable.CollisionProofHashMap<K, V> empty(scala.math.Ordering<K>);
    descriptor: (Lscala/math/Ordering;)Lscala/collection/mutable/CollisionProofHashMap;
    flags: (0x0001) ACC_PUBLIC
    Code:
      stack=3, locals=2, args_size=2
         0: new           #14                 // class scala/collection/mutable/CollisionProofHashMap
         3: dup
         4: aload_1
         5: invokespecial #85                 // Method scala/collection/mutable/CollisionProofHashMap."<init>":(Lscala/math/Ordering;)V
         8: areturn
      LineNumberTable:
        line 752: 0
      LocalVariableTable:
        Start  Length  Slot  Name   Signature
            0       9     0  this   Lscala/collection/mutable/CollisionProofHashMap$;
            0       9     1 evidence$2   Lscala/math/Ordering;
    Signature: #81                          // <K:Ljava/lang/Object;V:Ljava/lang/Object;>(Lscala/math/Ordering<TK;>;)Lscala/collection/mutable/CollisionProofHashMap<TK;TV;>;
    MethodParameters:
      Name                           Flags
      evidence$2                     final

  public <K extends java.lang.Object, V extends java.lang.Object> scala.collection.mutable.Builder<scala.Tuple2<K, V>, scala.collection.mutable.CollisionProofHashMap<K, V>> newBuilder(scala.math.Ordering<K>);
    descriptor: (Lscala/math/Ordering;)Lscala/collection/mutable/Builder;
    flags: (0x0001) ACC_PUBLIC
    Code:
      stack=6, locals=5, args_size=2
         0: bipush        16
         2: istore_2
         3: ldc2_w        #66                 // double 0.75d
         6: dstore_3
         7: new           #10                 // class scala/collection/mutable/CollisionProofHashMap$$anon$3
        10: dup
        11: iload_2
        12: dload_3
        13: aload_1
        14: invokespecial #90                 // Method scala/collection/mutable/CollisionProofHashMap$$anon$3."<init>":(IDLscala/math/Ordering;)V
        17: areturn
      LineNumberTable:
        line 765: 0
        line 762: 3
        line 757: 7
        line 754: 17
      LocalVariableTable:
        Start  Length  Slot  Name   Signature
            0      18     0  this   Lscala/collection/mutable/CollisionProofHashMap$;
            0      18     1 evidence$3   Lscala/math/Ordering;
    Signature: #88                          // <K:Ljava/lang/Object;V:Ljava/lang/Object;>(Lscala/math/Ordering<TK;>;)Lscala/collection/mutable/Builder<Lscala/Tuple2<TK;TV;>;Lscala/collection/mutable/CollisionProofHashMap<TK;TV;>;>;
    MethodParameters:
      Name                           Flags
      evidence$3                     final

  public <K extends java.lang.Object, V extends java.lang.Object> scala.collection.mutable.Builder<scala.Tuple2<K, V>, scala.collection.mutable.CollisionProofHashMap<K, V>> newBuilder(int, double, scala.math.Ordering<K>);
    descriptor: (IDLscala/math/Ordering;)Lscala/collection/mutable/Builder;
    flags: (0x0001) ACC_PUBLIC
    Code:
      stack=6, locals=5, args_size=4
         0: new           #10                 // class scala/collection/mutable/CollisionProofHashMap$$anon$3
         3: dup
         4: iload_1
         5: dload_2
         6: aload         4
         8: invokespecial #90                 // Method scala/collection/mutable/CollisionProofHashMap$$anon$3."<init>":(IDLscala/math/Ordering;)V
        11: areturn
      LineNumberTable:
        line 757: 0
      LocalVariableTable:
        Start  Length  Slot  Name   Signature
            0      12     0  this   Lscala/collection/mutable/CollisionProofHashMap$;
            0      12     1 initialCapacity   I
            0      12     2 loadFactor   D
            0      12     4 evidence$4   Lscala/math/Ordering;
    Signature: #92                          // <K:Ljava/lang/Object;V:Ljava/lang/Object;>(IDLscala/math/Ordering<TK;>;)Lscala/collection/mutable/Builder<Lscala/Tuple2<TK;TV;>;Lscala/collection/mutable/CollisionProofHashMap<TK;TV;>;>;
    MethodParameters:
      Name                           Flags
      initialCapacity                final
      loadFactor                     final
      evidence$4                     final

  public final double defaultLoadFactor();
    descriptor: ()D
    flags: (0x0011) ACC_PUBLIC, ACC_FINAL
    Code:
      stack=2, locals=1, args_size=1
         0: ldc2_w        #66                 // double 0.75d
         3: dreturn
      LineNumberTable:
        line 762: 0
      LocalVariableTable:
        Start  Length  Slot  Name   Signature
            0       4     0  this   Lscala/collection/mutable/CollisionProofHashMap$;

  public final int defaultInitialCapacity();
    descriptor: ()I
    flags: (0x0011) ACC_PUBLIC, ACC_FINAL
    Code:
      stack=1, locals=1, args_size=1
         0: bipush        16
         2: ireturn
      LineNumberTable:
        line 765: 0
      LocalVariableTable:
        Start  Length  Slot  Name   Signature
            0       3     0  this   Lscala/collection/mutable/CollisionProofHashMap$;

  private <K extends java.lang.Object, V extends java.lang.Object> int compare(K, int, scala.collection.mutable.CollisionProofHashMap$LLNode<K, V>, scala.math.Ordering<K>);
    descriptor: (Ljava/lang/Object;ILscala/collection/mutable/CollisionProofHashMap$LLNode;Lscala/math/Ordering;)I
    flags: (0x0002) ACC_PRIVATE
    Code:
      stack=3, locals=6, args_size=5
         0: iload_2
         1: aload_3
         2: invokevirtual #108                // Method scala/collection/mutable/CollisionProofHashMap$LLNode.hash:()I
         5: isub
         6: istore        5
         8: iload         5
        10: iconst_0
        11: if_icmpeq     17
        14: iload         5
        16: ireturn
        17: aload         4
        19: aload_1
        20: aload_3
        21: invokevirtual #111                // Method scala/collection/mutable/CollisionProofHashMap$LLNode.key:()Ljava/lang/Object;
        24: invokeinterface #116,  3          // InterfaceMethod scala/math/Ordering.compare:(Ljava/lang/Object;Ljava/lang/Object;)I
        29: ireturn
      StackMapTable: number_of_entries = 1
        frame_type = 252 /* append */
          offset_delta = 17
          locals = [ int ]
      LineNumberTable:
        line 774: 0
        line 775: 8
      LocalVariableTable:
        Start  Length  Slot  Name   Signature
            8      21     5     i   I
            0      30     0  this   Lscala/collection/mutable/CollisionProofHashMap$;
            0      30     1   key   Ljava/lang/Object;
            0      30     2  hash   I
            0      30     3  node   Lscala/collection/mutable/CollisionProofHashMap$LLNode;
            0      30     4   ord   Lscala/math/Ordering;
    Signature: #102                         // <K:Ljava/lang/Object;V:Ljava/lang/Object;>(TK;ILscala/collection/mutable/CollisionProofHashMap$LLNode<TK;TV;>;Lscala/math/Ordering<TK;>;)I
    MethodParameters:
      Name                           Flags
      key                            final
      hash                           final
      node                           final
      ord                            final

  public <K extends java.lang.Object, V extends java.lang.Object> int scala$collection$mutable$CollisionProofHashMap$$compare(K, int, scala.collection.mutable.CollisionProofHashMap$RBNode<K, V>, scala.math.Ordering<K>);
    descriptor: (Ljava/lang/Object;ILscala/collection/mutable/CollisionProofHashMap$RBNode;Lscala/math/Ordering;)I
    flags: (0x0001) ACC_PUBLIC
    Code:
      stack=3, locals=5, args_size=5
         0: aload         4
         2: aload_1
         3: aload_3
         4: invokevirtual #123                // Method scala/collection/mutable/CollisionProofHashMap$RBNode.key:()Ljava/lang/Object;
         7: invokeinterface #116,  3          // InterfaceMethod scala/math/Ordering.compare:(Ljava/lang/Object;Ljava/lang/Object;)I
        12: ireturn
      LineNumberTable:
        line 780: 0
      LocalVariableTable:
        Start  Length  Slot  Name   Signature
            0      13     0  this   Lscala/collection/mutable/CollisionProofHashMap$;
            0      13     1   key   Ljava/lang/Object;
            0      13     2  hash   I
            0      13     3  node   Lscala/collection/mutable/CollisionProofHashMap$RBNode;
            0      13     4   ord   Lscala/math/Ordering;
    Signature: #122                         // <K:Ljava/lang/Object;V:Ljava/lang/Object;>(TK;ILscala/collection/mutable/CollisionProofHashMap$RBNode<TK;TV;>;Lscala/math/Ordering<TK;>;)I
    MethodParameters:
      Name                           Flags
      key                            final
      hash                           final
      node                           final
      ord                            final

  private final int treeifyThreshold();
    descriptor: ()I
    flags: (0x0012) ACC_PRIVATE, ACC_FINAL
    Code:
      stack=1, locals=1, args_size=1
         0: bipush        8
         2: ireturn
      LocalVariableTable:
        Start  Length  Slot  Name   Signature
            0       3     0  this   Lscala/collection/mutable/CollisionProofHashMap$;

  public <A extends java.lang.Object, B extends java.lang.Object> scala.collection.mutable.CollisionProofHashMap$RBNode<A, B> scala$collection$mutable$CollisionProofHashMap$$leaf(A, int, B, boolean, scala.collection.mutable.CollisionProofHashMap$RBNode<A, B>);
    descriptor: (Ljava/lang/Object;ILjava/lang/Object;ZLscala/collection/mutable/CollisionProofHashMap$RBNode;)Lscala/collection/mutable/CollisionProofHashMap$RBNode;
    flags: (0x0001) ACC_PUBLIC
    Code:
      stack=9, locals=6, args_size=6
         0: new           #17                 // class scala/collection/mutable/CollisionProofHashMap$RBNode
         3: dup
         4: aload_1
         5: iload_2
         6: aload_3
         7: iload         4
         9: aconst_null
        10: aconst_null
        11: aload         5
        13: invokespecial #134                // Method scala/collection/mutable/CollisionProofHashMap$RBNode."<init>":(Ljava/lang/Object;ILjava/lang/Object;ZLscala/collection/mutable/CollisionProofHashMap$RBNode;Lscala/collection/mutable/CollisionProofHashMap$RBNode;Lscala/collection/mutable/CollisionProofHashMap$RBNode;)V
        16: areturn
      LineNumberTable:
        line 823: 0
      LocalVariableTable:
        Start  Length  Slot  Name   Signature
            0      17     0  this   Lscala/collection/mutable/CollisionProofHashMap$;
            0      17     1   key   Ljava/lang/Object;
            0      17     2  hash   I
            0      17     3 value   Ljava/lang/Object;
            0      17     4   red   Z
            0      17     5 parent   Lscala/collection/mutable/CollisionProofHashMap$RBNode;
    Signature: #128                         // <A:Ljava/lang/Object;B:Ljava/lang/Object;>(TA;ITB;ZLscala/collection/mutable/CollisionProofHashMap$RBNode<TA;TB;>;)Lscala/collection/mutable/CollisionProofHashMap$RBNode<TA;TB;>;
    MethodParameters:
      Name                           Flags
      key                            final
      hash                           final
      value                          final
      red                            final
      parent                         final

  public <A extends java.lang.Object, B extends java.lang.Object> scala.collection.mutable.CollisionProofHashMap$RBNode<A, B> scala$collection$mutable$CollisionProofHashMap$$minNodeNonNull(scala.collection.mutable.CollisionProofHashMap$RBNode<A, B>);
    descriptor: (Lscala/collection/mutable/CollisionProofHashMap$RBNode;)Lscala/collection/mutable/CollisionProofHashMap$RBNode;
    flags: (0x0001) ACC_PUBLIC
    Code:
      stack=1, locals=2, args_size=2
         0: aload_1
         1: invokevirtual #142                // Method scala/collection/mutable/CollisionProofHashMap$RBNode.left:()Lscala/collection/mutable/CollisionProofHashMap$RBNode;
         4: ifnonnull     9
         7: aload_1
         8: areturn
         9: aload_1
        10: invokevirtual #142                // Method scala/collection/mutable/CollisionProofHashMap$RBNode.left:()Lscala/collection/mutable/CollisionProofHashMap$RBNode;
        13: astore_1
        14: goto          0
      StackMapTable: number_of_entries = 2
        frame_type = 0 /* same */
        frame_type = 8 /* same */
      LineNumberTable:
        line 826: 0
      LocalVariableTable:
        Start  Length  Slot  Name   Signature
            0      17     0  this   Lscala/collection/mutable/CollisionProofHashMap$;
            0      17     1  node   Lscala/collection/mutable/CollisionProofHashMap$RBNode;
    Signature: #138                         // <A:Ljava/lang/Object;B:Ljava/lang/Object;>(Lscala/collection/mutable/CollisionProofHashMap$RBNode<TA;TB;>;)Lscala/collection/mutable/CollisionProofHashMap$RBNode<TA;TB;>;
    MethodParameters:
      Name                           Flags
      node                           final

  public <A extends java.lang.Object, B extends java.lang.Object> scala.collection.mutable.CollisionProofHashMap$RBNode<A, B> scala$collection$mutable$CollisionProofHashMap$$successor(scala.collection.mutable.CollisionProofHashMap$RBNode<A, B>);
    descriptor: (Lscala/collection/mutable/CollisionProofHashMap$RBNode;)Lscala/collection/mutable/CollisionProofHashMap$RBNode;
    flags: (0x0001) ACC_PUBLIC
    Code:
      stack=2, locals=4, args_size=2
         0: aload_1
         1: invokevirtual #146                // Method scala/collection/mutable/CollisionProofHashMap$RBNode.right:()Lscala/collection/mutable/CollisionProofHashMap$RBNode;
         4: ifnull        16
         7: aload_0
         8: aload_1
         9: invokevirtual #146                // Method scala/collection/mutable/CollisionProofHashMap$RBNode.right:()Lscala/collection/mutable/CollisionProofHashMap$RBNode;
        12: invokevirtual #148                // Method scala$collection$mutable$CollisionProofHashMap$$minNodeNonNull:(Lscala/collection/mutable/CollisionProofHashMap$RBNode;)Lscala/collection/mutable/CollisionProofHashMap$RBNode;
        15: areturn
        16: aload_1
        17: astore_2
        18: aload_1
        19: invokevirtual #150                // Method scala/collection/mutable/CollisionProofHashMap$RBNode.parent:()Lscala/collection/mutable/CollisionProofHashMap$RBNode;
        22: astore_3
        23: aload_3
        24: ifnull        45
        27: aload_2
        28: aload_3
        29: invokevirtual #146                // Method scala/collection/mutable/CollisionProofHashMap$RBNode.right:()Lscala/collection/mutable/CollisionProofHashMap$RBNode;
        32: if_acmpne     45
        35: aload_3
        36: astore_2
        37: aload_3
        38: invokevirtual #150                // Method scala/collection/mutable/CollisionProofHashMap$RBNode.parent:()Lscala/collection/mutable/CollisionProofHashMap$RBNode;
        41: astore_3
        42: goto          23
        45: aload_3
        46: areturn
      StackMapTable: number_of_entries = 3
        frame_type = 16 /* same */
        frame_type = 253 /* append */
          offset_delta = 6
          locals = [ class scala/collection/mutable/CollisionProofHashMap$RBNode, class scala/collection/mutable/CollisionProofHashMap$RBNode ]
        frame_type = 21 /* same */
      LineNumberTable:
        line 833: 0
        line 835: 16
        line 836: 18
        line 837: 23
        line 838: 35
        line 839: 37
        line 837: 42
        line 841: 45
      LocalVariableTable:
        Start  Length  Slot  Name   Signature
           18      28     2     x   Lscala/collection/mutable/CollisionProofHashMap$RBNode;
           23      23     3     y   Lscala/collection/mutable/CollisionProofHashMap$RBNode;
            0      47     0  this   Lscala/collection/mutable/CollisionProofHashMap$;
            0      47     1  node   Lscala/collection/mutable/CollisionProofHashMap$RBNode;
    Signature: #138                         // <A:Ljava/lang/Object;B:Ljava/lang/Object;>(Lscala/collection/mutable/CollisionProofHashMap$RBNode<TA;TB;>;)Lscala/collection/mutable/CollisionProofHashMap$RBNode<TA;TB;>;
    MethodParameters:
      Name                           Flags
      node                           final

  private java.lang.Object writeReplace();
    descriptor: ()Ljava/lang/Object;
    flags: (0x0002) ACC_PRIVATE
    Code:
      stack=3, locals=1, args_size=1
         0: new           #155                // class scala/runtime/ModuleSerializationProxy
         3: dup
         4: ldc           #2                  // class scala/collection/mutable/CollisionProofHashMap$
         6: invokespecial #158                // Method scala/runtime/ModuleSerializationProxy."<init>":(Ljava/lang/Class;)V
         9: areturn
      LineNumberTable:
        line 743: 0
      LocalVariableTable:
        Start  Length  Slot  Name   Signature
            0      10     0  this   Lscala/collection/mutable/CollisionProofHashMap$;

  public java.lang.Object empty(scala.math.Ordering);
    descriptor: (Lscala/math/Ordering;)Ljava/lang/Object;
    flags: (0x1041) ACC_PUBLIC, ACC_BRIDGE, ACC_SYNTHETIC
    Code:
      stack=2, locals=2, args_size=2
         0: aload_0
         1: aload_1
         2: invokevirtual #162                // Method empty:(Lscala/math/Ordering;)Lscala/collection/mutable/CollisionProofHashMap;
         5: areturn
      LineNumberTable:
        line 743: 0
      LocalVariableTable:
        Start  Length  Slot  Name   Signature
            0       6     0  this   Lscala/collection/mutable/CollisionProofHashMap$;
            0       6     1 evidence$36   Lscala/math/Ordering;
    MethodParameters:
      Name                           Flags
      evidence$36                    final

  public java.lang.Object from(scala.collection.IterableOnce, scala.math.Ordering);
    descriptor: (Lscala/collection/IterableOnce;Lscala/math/Ordering;)Ljava/lang/Object;
    flags: (0x1041) ACC_PUBLIC, ACC_BRIDGE, ACC_SYNTHETIC
    Code:
      stack=3, locals=3, args_size=3
         0: aload_0
         1: aload_1
         2: aload_2
         3: invokevirtual #166                // Method from:(Lscala/collection/IterableOnce;Lscala/math/Ordering;)Lscala/collection/mutable/CollisionProofHashMap;
         6: areturn
      LineNumberTable:
        line 743: 0
      LocalVariableTable:
        Start  Length  Slot  Name   Signature
            0       7     0  this   Lscala/collection/mutable/CollisionProofHashMap$;
            0       7     1    it   Lscala/collection/IterableOnce;
            0       7     2 evidence$37   Lscala/math/Ordering;
    MethodParameters:
      Name                           Flags
      it                             final
      evidence$37                    final

  private scala.collection.mutable.CollisionProofHashMap$();
    descriptor: ()V
    flags: (0x0002) ACC_PRIVATE
    Code:
      stack=1, locals=1, args_size=1
         0: aload_0
         1: invokespecial #167                // Method java/lang/Object."<init>":()V
         4: return
      LineNumberTable:
        line 743: 0
      LocalVariableTable:
        Start  Length  Slot  Name   Signature
            0       5     0  this   Lscala/collection/mutable/CollisionProofHashMap$;
}
InnerClasses:
  public final #10;                       // class scala/collection/mutable/CollisionProofHashMap$$anon$3
  private static final #15= #12 of #14;   // LLNode=class scala/collection/mutable/CollisionProofHashMap$LLNode of class scala/collection/mutable/CollisionProofHashMap
  public static final #18= #17 of #14;    // RBNode=class scala/collection/mutable/CollisionProofHashMap$RBNode of class scala/collection/mutable/CollisionProofHashMap
Signature: #3                           // Ljava/lang/Object;Lscala/collection/SortedMapFactory<Lscala/collection/mutable/CollisionProofHashMap;>;
SourceFile: "CollisionProofHashMap.scala"
  ScalaInlineInfo: length = 0x63 (unknown attribute)
   01 01 00 13 00 1B 00 1A 01 00 20 00 21 01 00 64
   00 65 05 00 63 00 3F 01 00 61 00 62 01 00 4F 00
   9F 01 00 4F 00 50 01 00 37 00 A3 01 00 37 00 38
   01 00 56 00 5B 01 00 56 00 57 01 00 33 00 34 01
   00 78 00 79 05 00 7E 00 7F 05 00 88 00 89 01 00
   8F 00 89 01 00 2B 00 2C 01 00 7D 00 3F 01 00 99
   00 6D 01
  Scala: length = 0x0 (unknown attribute)

