Classfile /Users/mw/Projects/slang-braindump/.jar/jar8/assemble/slang-braindump/assemble/content/scala/collection/mutable/CollisionProofHashMap$Node.class
  Last modified May 29, 2022; size 486 bytes
  SHA-256 checksum 293ff0f65720e946cd46b34ef8f567ce01334633db7bb4169fb7d5b868d222ed
  Compiled from "CollisionProofHashMap.scala"
public abstract class scala.collection.mutable.CollisionProofHashMap$Node
  minor version: 0
  major version: 52
  flags: (0x0421) ACC_PUBLIC, ACC_SUPER, ACC_ABSTRACT
  this_class: #2                          // scala/collection/mutable/CollisionProofHashMap$Node
  super_class: #4                         // java/lang/Object
  interfaces: 0, fields: 0, methods: 1, attributes: 4
Constant pool:
   #1 = Utf8               scala/collection/mutable/CollisionProofHashMap$Node
   #2 = Class              #1             // scala/collection/mutable/CollisionProofHashMap$Node
   #3 = Utf8               java/lang/Object
   #4 = Class              #3             // java/lang/Object
   #5 = Utf8               CollisionProofHashMap.scala
   #6 = Utf8               scala/collection/mutable/CollisionProofHashMap
   #7 = Class              #6             // scala/collection/mutable/CollisionProofHashMap
   #8 = Utf8               Node
   #9 = Utf8               <init>
  #10 = Utf8               ()V
  #11 = NameAndType        #9:#10         // "<init>":()V
  #12 = Methodref          #4.#11         // java/lang/Object."<init>":()V
  #13 = Utf8               this
  #14 = Utf8               Lscala/collection/mutable/CollisionProofHashMap$Node;
  #15 = Utf8               Code
  #16 = Utf8               LineNumberTable
  #17 = Utf8               LocalVariableTable
  #18 = Utf8               InnerClasses
  #19 = Utf8               SourceFile
  #20 = Utf8               ScalaInlineInfo
  #21 = Utf8               Scala
{
  public scala.collection.mutable.CollisionProofHashMap$Node();
    descriptor: ()V
    flags: (0x0001) ACC_PUBLIC
    Code:
      stack=1, locals=1, args_size=1
         0: aload_0
         1: invokespecial #12                 // Method java/lang/Object."<init>":()V
         4: return
      LineNumberTable:
        line 787: 0
      LocalVariableTable:
        Start  Length  Slot  Name   Signature
            0       5     0  this   Lscala/collection/mutable/CollisionProofHashMap$Node;
}
InnerClasses:
  public static abstract #8= #2 of #7;    // Node=class scala/collection/mutable/CollisionProofHashMap$Node of class scala/collection/mutable/CollisionProofHashMap
SourceFile: "CollisionProofHashMap.scala"
  ScalaInlineInfo: length = 0x9 (unknown attribute)
   01 00 00 01 00 09 00 0A 01
  Scala: length = 0x0 (unknown attribute)

