Classfile /Users/mw/Projects/slang-braindump/.jar/jar8/assemble/slang-braindump/assemble/content/scala/collection/mutable/FlatHashTable$NullSentinel$.class
  Last modified May 29, 2022; size 774 bytes
  SHA-256 checksum a931edbaedaeeeb59bfcdac601f226670f29f56d80f498b9588fb423d04cea5e
  Compiled from "FlatHashTable.scala"
public class scala.collection.mutable.FlatHashTable$NullSentinel$
  minor version: 0
  major version: 52
  flags: (0x0021) ACC_PUBLIC, ACC_SUPER
  this_class: #2                          // scala/collection/mutable/FlatHashTable$NullSentinel$
  super_class: #4                         // java/lang/Object
  interfaces: 0, fields: 1, methods: 4, attributes: 4
Constant pool:
   #1 = Utf8               scala/collection/mutable/FlatHashTable$NullSentinel$
   #2 = Class              #1             // scala/collection/mutable/FlatHashTable$NullSentinel$
   #3 = Utf8               java/lang/Object
   #4 = Class              #3             // java/lang/Object
   #5 = Utf8               FlatHashTable.scala
   #6 = Utf8               scala/collection/mutable/FlatHashTable
   #7 = Class              #6             // scala/collection/mutable/FlatHashTable
   #8 = Utf8               NullSentinel$
   #9 = Utf8               MODULE$
  #10 = Utf8               Lscala/collection/mutable/FlatHashTable$NullSentinel$;
  #11 = Utf8               <clinit>
  #12 = Utf8               ()V
  #13 = Utf8               <init>
  #14 = NameAndType        #13:#12        // "<init>":()V
  #15 = Methodref          #2.#14         // scala/collection/mutable/FlatHashTable$NullSentinel$."<init>":()V
  #16 = NameAndType        #9:#10         // MODULE$:Lscala/collection/mutable/FlatHashTable$NullSentinel$;
  #17 = Fieldref           #2.#16         // scala/collection/mutable/FlatHashTable$NullSentinel$.MODULE$:Lscala/collection/mutable/FlatHashTable$NullSentinel$;
  #18 = Utf8               hashCode
  #19 = Utf8               ()I
  #20 = Utf8               this
  #21 = Utf8               toString
  #22 = Utf8               ()Ljava/lang/String;
  #23 = Utf8               NullSentinel
  #24 = String             #23            // NullSentinel
  #25 = Methodref          #4.#14         // java/lang/Object."<init>":()V
  #26 = Utf8               Code
  #27 = Utf8               LineNumberTable
  #28 = Utf8               LocalVariableTable
  #29 = Utf8               InnerClasses
  #30 = Utf8               SourceFile
  #31 = Utf8               ScalaInlineInfo
  #32 = Utf8               Scala
{
  public static final scala.collection.mutable.FlatHashTable$NullSentinel$ MODULE$;
    descriptor: Lscala/collection/mutable/FlatHashTable$NullSentinel$;
    flags: (0x0019) ACC_PUBLIC, ACC_STATIC, ACC_FINAL

  public static {};
    descriptor: ()V
    flags: (0x0009) ACC_PUBLIC, ACC_STATIC
    Code:
      stack=2, locals=0, args_size=0
         0: new           #2                  // class scala/collection/mutable/FlatHashTable$NullSentinel$
         3: dup
         4: invokespecial #15                 // Method "<init>":()V
         7: putstatic     #17                 // Field MODULE$:Lscala/collection/mutable/FlatHashTable$NullSentinel$;
        10: return
      LineNumberTable:
        line 384: 0

  public int hashCode();
    descriptor: ()I
    flags: (0x0001) ACC_PUBLIC
    Code:
      stack=1, locals=1, args_size=1
         0: iconst_0
         1: ireturn
      LineNumberTable:
        line 385: 0
      LocalVariableTable:
        Start  Length  Slot  Name   Signature
            0       2     0  this   Lscala/collection/mutable/FlatHashTable$NullSentinel$;

  public java.lang.String toString();
    descriptor: ()Ljava/lang/String;
    flags: (0x0001) ACC_PUBLIC
    Code:
      stack=1, locals=1, args_size=1
         0: ldc           #24                 // String NullSentinel
         2: areturn
      LineNumberTable:
        line 386: 0
      LocalVariableTable:
        Start  Length  Slot  Name   Signature
            0       3     0  this   Lscala/collection/mutable/FlatHashTable$NullSentinel$;

  public scala.collection.mutable.FlatHashTable$NullSentinel$();
    descriptor: ()V
    flags: (0x0001) ACC_PUBLIC
    Code:
      stack=1, locals=1, args_size=1
         0: aload_0
         1: invokespecial #25                 // Method java/lang/Object."<init>":()V
         4: return
      LineNumberTable:
        line 391: 0
        line 384: 4
      LocalVariableTable:
        Start  Length  Slot  Name   Signature
            0       5     0  this   Lscala/collection/mutable/FlatHashTable$NullSentinel$;
}
InnerClasses:
  private static #8= #2 of #7;            // NullSentinel$=class scala/collection/mutable/FlatHashTable$NullSentinel$ of class scala/collection/mutable/FlatHashTable
SourceFile: "FlatHashTable.scala"
  ScalaInlineInfo: length = 0x13 (unknown attribute)
   01 01 00 03 00 0D 00 0C 01 00 12 00 13 01 00 15
   00 16 01
  Scala: length = 0x0 (unknown attribute)

