Classfile /Users/mw/Projects/slang-braindump/.jar/jar8/assemble/slang-braindump/assemble/content/scala/collection/mutable/Growable$.class
  Last modified May 29, 2022; size 1094 bytes
  SHA-256 checksum 5f9101b1a1ffb96011d5f7bd79ffa74666d350172038982a38fc45d0375faa98
  Compiled from "Growable.scala"
public final class scala.collection.mutable.Growable$
  minor version: 0
  major version: 52
  flags: (0x0031) ACC_PUBLIC, ACC_FINAL, ACC_SUPER
  this_class: #2                          // scala/collection/mutable/Growable$
  super_class: #4                         // java/lang/Object
  interfaces: 0, fields: 1, methods: 3, attributes: 3
Constant pool:
   #1 = Utf8               scala/collection/mutable/Growable$
   #2 = Class              #1             // scala/collection/mutable/Growable$
   #3 = Utf8               java/lang/Object
   #4 = Class              #3             // java/lang/Object
   #5 = Utf8               Growable.scala
   #6 = Utf8               MODULE$
   #7 = Utf8               Lscala/collection/mutable/Growable$;
   #8 = Utf8               <clinit>
   #9 = Utf8               ()V
  #10 = Utf8               <init>
  #11 = NameAndType        #10:#9         // "<init>":()V
  #12 = Methodref          #2.#11         // scala/collection/mutable/Growable$."<init>":()V
  #13 = NameAndType        #6:#7          // MODULE$:Lscala/collection/mutable/Growable$;
  #14 = Fieldref           #2.#13         // scala/collection/mutable/Growable$.MODULE$:Lscala/collection/mutable/Growable$;
  #15 = Utf8               from
  #16 = Utf8               (Lscala/collection/mutable/Growable;Lscala/collection/IterableOnce;)Lscala/collection/mutable/Growable;
  #17 = Utf8               <A:Ljava/lang/Object;>(Lscala/collection/mutable/Growable<TA;>;Lscala/collection/IterableOnce<TA;>;)Lscala/collection/mutable/Growable<TA;>;
  #18 = Utf8               empty
  #19 = Utf8               it
  #20 = Utf8               scala/collection/mutable/Growable
  #21 = Class              #20            // scala/collection/mutable/Growable
  #22 = Utf8               addAll
  #23 = Utf8               (Lscala/collection/IterableOnce;)Lscala/collection/mutable/Growable;
  #24 = NameAndType        #22:#23        // addAll:(Lscala/collection/IterableOnce;)Lscala/collection/mutable/Growable;
  #25 = InterfaceMethodref #21.#24        // scala/collection/mutable/Growable.addAll:(Lscala/collection/IterableOnce;)Lscala/collection/mutable/Growable;
  #26 = Utf8               this
  #27 = Utf8               Lscala/collection/mutable/Growable;
  #28 = Utf8               Lscala/collection/IterableOnce;
  #29 = Methodref          #4.#11         // java/lang/Object."<init>":()V
  #30 = Utf8               Code
  #31 = Utf8               LineNumberTable
  #32 = Utf8               StackMapTable
  #33 = Utf8               LocalVariableTable
  #34 = Utf8               Signature
  #35 = Utf8               MethodParameters
  #36 = Utf8               SourceFile
  #37 = Utf8               ScalaInlineInfo
  #38 = Utf8               Scala
{
  public static final scala.collection.mutable.Growable$ MODULE$;
    descriptor: Lscala/collection/mutable/Growable$;
    flags: (0x0019) ACC_PUBLIC, ACC_STATIC, ACC_FINAL

  public static {};
    descriptor: ()V
    flags: (0x0009) ACC_PUBLIC, ACC_STATIC
    Code:
      stack=2, locals=0, args_size=0
         0: new           #2                  // class scala/collection/mutable/Growable$
         3: dup
         4: invokespecial #12                 // Method "<init>":()V
         7: putstatic     #14                 // Field MODULE$:Lscala/collection/mutable/Growable$;
        10: return
      LineNumberTable:
        line 77: 0

  public <A extends java.lang.Object> scala.collection.mutable.Growable<A> from(scala.collection.mutable.Growable<A>, scala.collection.IterableOnce<A>);
    descriptor: (Lscala/collection/mutable/Growable;Lscala/collection/IterableOnce;)Lscala/collection/mutable/Growable;
    flags: (0x0001) ACC_PUBLIC
    Code:
      stack=2, locals=3, args_size=3
         0: aload_1
         1: ifnonnull     6
         4: aconst_null
         5: athrow
         6: aload_1
         7: aload_2
         8: invokeinterface #25,  2           // InterfaceMethod scala/collection/mutable/Growable.addAll:(Lscala/collection/IterableOnce;)Lscala/collection/mutable/Growable;
        13: areturn
      StackMapTable: number_of_entries = 1
        frame_type = 6 /* same */
      LineNumberTable:
        line 86: 0
        line 69: 6
        line 86: 13
      LocalVariableTable:
        Start  Length  Slot  Name   Signature
            0      14     0  this   Lscala/collection/mutable/Growable$;
            0      14     1 empty   Lscala/collection/mutable/Growable;
            0      14     2    it   Lscala/collection/IterableOnce;
    Signature: #17                          // <A:Ljava/lang/Object;>(Lscala/collection/mutable/Growable<TA;>;Lscala/collection/IterableOnce<TA;>;)Lscala/collection/mutable/Growable<TA;>;
    MethodParameters:
      Name                           Flags
      empty                          final
      it                             final

  private scala.collection.mutable.Growable$();
    descriptor: ()V
    flags: (0x0002) ACC_PRIVATE
    Code:
      stack=1, locals=1, args_size=1
         0: aload_0
         1: invokespecial #29                 // Method java/lang/Object."<init>":()V
         4: return
      LineNumberTable:
        line 77: 0
      LocalVariableTable:
        Start  Length  Slot  Name   Signature
            0       5     0  this   Lscala/collection/mutable/Growable$;
}
SourceFile: "Growable.scala"
  ScalaInlineInfo: length = 0xE (unknown attribute)
   01 01 00 02 00 0A 00 09 01 00 0F 00 10 01
  Scala: length = 0x0 (unknown attribute)

