Classfile /Users/mw/Projects/slang-braindump/.jar/jar8/assemble/slang-braindump/assemble/content/scala/collection/mutable/LongMap$.class
  Last modified May 29, 2022; size 8726 bytes
  SHA-256 checksum b3a2ab324e4a14353dbf548019228cb114cfc16efdd2b35bb88d2b758c918fa7
  Compiled from "LongMap.scala"
public final class scala.collection.mutable.LongMap$ implements java.io.Serializable
  minor version: 0
  major version: 52
  flags: (0x0031) ACC_PUBLIC, ACC_FINAL, ACC_SUPER
  this_class: #2                          // scala/collection/mutable/LongMap$
  super_class: #4                         // java/lang/Object
  interfaces: 1, fields: 2, methods: 25, attributes: 5
Constant pool:
    #1 = Utf8               scala/collection/mutable/LongMap$
    #2 = Class              #1            // scala/collection/mutable/LongMap$
    #3 = Utf8               java/lang/Object
    #4 = Class              #3            // java/lang/Object
    #5 = Utf8               java/io/Serializable
    #6 = Class              #5            // java/io/Serializable
    #7 = Utf8               LongMap.scala
    #8 = Utf8               java/lang/invoke/MethodHandles$Lookup
    #9 = Class              #8            // java/lang/invoke/MethodHandles$Lookup
   #10 = Utf8               java/lang/invoke/MethodHandles
   #11 = Class              #10           // java/lang/invoke/MethodHandles
   #12 = Utf8               Lookup
   #13 = Utf8               scala/collection/mutable/LongMap$LongMapBuilder
   #14 = Class              #13           // scala/collection/mutable/LongMap$LongMapBuilder
   #15 = Utf8               scala/collection/mutable/LongMap
   #16 = Class              #15           // scala/collection/mutable/LongMap
   #17 = Utf8               LongMapBuilder
   #18 = Utf8               scala/collection/mutable/LongMap$ToBuildFrom$
   #19 = Class              #18           // scala/collection/mutable/LongMap$ToBuildFrom$
   #20 = Utf8               ToBuildFrom$
   #21 = Utf8               scala/collection/mutable/LongMap$ToFactory$
   #22 = Class              #21           // scala/collection/mutable/LongMap$ToFactory$
   #23 = Utf8               ToFactory$
   #24 = Utf8               MODULE$
   #25 = Utf8               Lscala/collection/mutable/LongMap$;
   #26 = Utf8               scala$collection$mutable$LongMap$$exceptionDefault
   #27 = Utf8               Lscala/Function1;
   #28 = Utf8               Lscala/Function1<Ljava/lang/Object;Lscala/runtime/Nothing$;>;
   #29 = Utf8               <clinit>
   #30 = Utf8               ()V
   #31 = Utf8               <init>
   #32 = NameAndType        #31:#30       // "<init>":()V
   #33 = Methodref          #2.#32        // scala/collection/mutable/LongMap$."<init>":()V
   #34 = NameAndType        #24:#25       // MODULE$:Lscala/collection/mutable/LongMap$;
   #35 = Fieldref           #2.#34        // scala/collection/mutable/LongMap$.MODULE$:Lscala/collection/mutable/LongMap$;
   #36 = Utf8               (Ljava/lang/Object;)Ljava/lang/Object;
   #37 = MethodType         #36           //  (Ljava/lang/Object;)Ljava/lang/Object;
   #38 = Utf8               $anonfun$exceptionDefault$1$adapted
   #39 = Utf8               (Ljava/lang/Object;)Lscala/runtime/Nothing$;
   #40 = NameAndType        #38:#39       // $anonfun$exceptionDefault$1$adapted:(Ljava/lang/Object;)Lscala/runtime/Nothing$;
   #41 = Methodref          #2.#40        // scala/collection/mutable/LongMap$.$anonfun$exceptionDefault$1$adapted:(Ljava/lang/Object;)Lscala/runtime/Nothing$;
   #42 = MethodHandle       6:#41         // REF_invokeStatic scala/collection/mutable/LongMap$.$anonfun$exceptionDefault$1$adapted:(Ljava/lang/Object;)Lscala/runtime/Nothing$;
   #43 = MethodType         #39           //  (Ljava/lang/Object;)Lscala/runtime/Nothing$;
   #44 = Integer            5
   #45 = Integer            1
   #46 = Utf8               java/lang/invoke/LambdaMetafactory
   #47 = Class              #46           // java/lang/invoke/LambdaMetafactory
   #48 = Utf8               altMetafactory
   #49 = Utf8               (Ljava/lang/invoke/MethodHandles$Lookup;Ljava/lang/String;Ljava/lang/invoke/MethodType;[Ljava/lang/Object;)Ljava/lang/invoke/CallSite;
   #50 = NameAndType        #48:#49       // altMetafactory:(Ljava/lang/invoke/MethodHandles$Lookup;Ljava/lang/String;Ljava/lang/invoke/MethodType;[Ljava/lang/Object;)Ljava/lang/invoke/CallSite;
   #51 = Methodref          #47.#50       // java/lang/invoke/LambdaMetafactory.altMetafactory:(Ljava/lang/invoke/MethodHandles$Lookup;Ljava/lang/String;Ljava/lang/invoke/MethodType;[Ljava/lang/Object;)Ljava/lang/invoke/CallSite;
   #52 = MethodHandle       6:#51         // REF_invokeStatic java/lang/invoke/LambdaMetafactory.altMetafactory:(Ljava/lang/invoke/MethodHandles$Lookup;Ljava/lang/String;Ljava/lang/invoke/MethodType;[Ljava/lang/Object;)Ljava/lang/invoke/CallSite;
   #53 = Utf8               apply
   #54 = Utf8               ()Lscala/Function1;
   #55 = NameAndType        #53:#54       // apply:()Lscala/Function1;
   #56 = InvokeDynamic      #0:#55        // #0:apply:()Lscala/Function1;
   #57 = NameAndType        #26:#27       // scala$collection$mutable$LongMap$$exceptionDefault:Lscala/Function1;
   #58 = Fieldref           #2.#57        // scala/collection/mutable/LongMap$.scala$collection$mutable$LongMap$$exceptionDefault:Lscala/Function1;
   #59 = Utf8               IndexMask
   #60 = Utf8               ()I
   #61 = Integer            1073741823
   #62 = Utf8               this
   #63 = Utf8               MissingBit
   #64 = Integer            -2147483648
   #65 = Utf8               VacantBit
   #66 = Integer            1073741824
   #67 = Utf8               MissVacant
   #68 = Integer            -1073741824
   #69 = Utf8               ()Lscala/Function1<Ljava/lang/Object;Lscala/runtime/Nothing$;>;
   #70 = Utf8               (Lscala/collection/immutable/Seq;)Lscala/collection/mutable/LongMap;
   #71 = Utf8               <V:Ljava/lang/Object;>(Lscala/collection/immutable/Seq<Lscala/Tuple2<Ljava/lang/Object;TV;>;>;)Lscala/collection/mutable/LongMap<TV;>;
   #72 = Utf8               elems
   #73 = Utf8               buildFromIterableOnce
   #74 = Utf8               (Lscala/collection/IterableOnce;)Lscala/collection/mutable/LongMap;
   #75 = NameAndType        #73:#74       // buildFromIterableOnce:(Lscala/collection/IterableOnce;)Lscala/collection/mutable/LongMap;
   #76 = Methodref          #2.#75        // scala/collection/mutable/LongMap$.buildFromIterableOnce:(Lscala/collection/IterableOnce;)Lscala/collection/mutable/LongMap;
   #77 = Utf8               Lscala/collection/immutable/Seq;
   #78 = Utf8               <V:Ljava/lang/Object;>(Lscala/collection/IterableOnce<Lscala/Tuple2<Ljava/lang/Object;TV;>;>;)Lscala/collection/mutable/LongMap<TV;>;
   #79 = Utf8               scala/collection/IterableOnce
   #80 = Class              #79           // scala/collection/IterableOnce
   #81 = Utf8               knownSize
   #82 = NameAndType        #81:#60       // knownSize:()I
   #83 = InterfaceMethodref #80.#82       // scala/collection/IterableOnce.knownSize:()I
   #84 = Utf8               (I)V
   #85 = NameAndType        #31:#84       // "<init>":(I)V
   #86 = Methodref          #16.#85       // scala/collection/mutable/LongMap."<init>":(I)V
   #87 = Utf8               iterator
   #88 = Utf8               ()Lscala/collection/Iterator;
   #89 = NameAndType        #87:#88       // iterator:()Lscala/collection/Iterator;
   #90 = InterfaceMethodref #80.#89       // scala/collection/IterableOnce.iterator:()Lscala/collection/Iterator;
   #91 = Utf8               $anonfun$buildFromIterableOnce$1$adapted
   #92 = Utf8               (Lscala/collection/mutable/LongMap;Lscala/Tuple2;)Ljava/lang/Object;
   #93 = NameAndType        #91:#92       // $anonfun$buildFromIterableOnce$1$adapted:(Lscala/collection/mutable/LongMap;Lscala/Tuple2;)Ljava/lang/Object;
   #94 = Methodref          #2.#93        // scala/collection/mutable/LongMap$.$anonfun$buildFromIterableOnce$1$adapted:(Lscala/collection/mutable/LongMap;Lscala/Tuple2;)Ljava/lang/Object;
   #95 = MethodHandle       6:#94         // REF_invokeStatic scala/collection/mutable/LongMap$.$anonfun$buildFromIterableOnce$1$adapted:(Lscala/collection/mutable/LongMap;Lscala/Tuple2;)Ljava/lang/Object;
   #96 = Utf8               (Lscala/Tuple2;)Ljava/lang/Object;
   #97 = MethodType         #96           //  (Lscala/Tuple2;)Ljava/lang/Object;
   #98 = Utf8               (Lscala/collection/mutable/LongMap;)Lscala/Function1;
   #99 = NameAndType        #53:#98       // apply:(Lscala/collection/mutable/LongMap;)Lscala/Function1;
  #100 = InvokeDynamic      #1:#99        // #1:apply:(Lscala/collection/mutable/LongMap;)Lscala/Function1;
  #101 = Utf8               scala/collection/Iterator
  #102 = Class              #101          // scala/collection/Iterator
  #103 = Utf8               foreach
  #104 = Utf8               (Lscala/Function1;)V
  #105 = NameAndType        #103:#104     // foreach:(Lscala/Function1;)V
  #106 = InterfaceMethodref #102.#105     // scala/collection/Iterator.foreach:(Lscala/Function1;)V
  #107 = Utf8               size
  #108 = NameAndType        #107:#60      // size:()I
  #109 = Methodref          #16.#108      // scala/collection/mutable/LongMap.size:()I
  #110 = Utf8               repack
  #111 = NameAndType        #110:#30      // repack:()V
  #112 = Methodref          #16.#111      // scala/collection/mutable/LongMap.repack:()V
  #113 = Utf8               sz
  #114 = Utf8               I
  #115 = Utf8               lm
  #116 = Utf8               Lscala/collection/mutable/LongMap;
  #117 = Utf8               Lscala/collection/IterableOnce;
  #118 = Utf8               empty
  #119 = Utf8               ()Lscala/collection/mutable/LongMap;
  #120 = Utf8               <V:Ljava/lang/Object;>()Lscala/collection/mutable/LongMap<TV;>;
  #121 = Methodref          #16.#32       // scala/collection/mutable/LongMap."<init>":()V
  #122 = Utf8               withDefault
  #123 = Utf8               (Lscala/Function1;)Lscala/collection/mutable/LongMap;
  #124 = Utf8               <V:Ljava/lang/Object;>(Lscala/Function1<Ljava/lang/Object;TV;>;)Lscala/collection/mutable/LongMap<TV;>;
  #125 = Utf8               default
  #126 = NameAndType        #31:#104      // "<init>":(Lscala/Function1;)V
  #127 = Methodref          #16.#126      // scala/collection/mutable/LongMap."<init>":(Lscala/Function1;)V
  #128 = Utf8               from
  #129 = Utf8               source
  #130 = Utf8               clone
  #131 = NameAndType        #130:#119     // clone:()Lscala/collection/mutable/LongMap;
  #132 = Methodref          #16.#131      // scala/collection/mutable/LongMap.clone:()Lscala/collection/mutable/LongMap;
  #133 = Utf8               newBuilder
  #134 = Utf8               ()Lscala/collection/mutable/ReusableBuilder;
  #135 = Utf8               <V:Ljava/lang/Object;>()Lscala/collection/mutable/ReusableBuilder<Lscala/Tuple2<Ljava/lang/Object;TV;>;Lscala/collection/mutable/LongMap<TV;>;>;
  #136 = Methodref          #14.#32       // scala/collection/mutable/LongMap$LongMapBuilder."<init>":()V
  #137 = Utf8               fromZip
  #138 = Utf8               ([JLjava/lang/Object;)Lscala/collection/mutable/LongMap;
  #139 = Utf8               <V:Ljava/lang/Object;>([JLjava/lang/Object;)Lscala/collection/mutable/LongMap<TV;>;
  #140 = Utf8               keys
  #141 = Utf8               values
  #142 = Utf8               scala/math/package$
  #143 = Class              #142          // scala/math/package$
  #144 = Utf8               Lscala/math/package$;
  #145 = NameAndType        #24:#144      // MODULE$:Lscala/math/package$;
  #146 = Fieldref           #143.#145     // scala/math/package$.MODULE$:Lscala/math/package$;
  #147 = Utf8               java/lang/reflect/Array
  #148 = Class              #147          // java/lang/reflect/Array
  #149 = Utf8               getLength
  #150 = Utf8               (Ljava/lang/Object;)I
  #151 = NameAndType        #149:#150     // getLength:(Ljava/lang/Object;)I
  #152 = Methodref          #148.#151     // java/lang/reflect/Array.getLength:(Ljava/lang/Object;)I
  #153 = Utf8               java/lang/Math
  #154 = Class              #153          // java/lang/Math
  #155 = Utf8               min
  #156 = Utf8               (II)I
  #157 = NameAndType        #155:#156     // min:(II)I
  #158 = Methodref          #154.#157     // java/lang/Math.min:(II)I
  #159 = Utf8               scala/runtime/ScalaRunTime$
  #160 = Class              #159          // scala/runtime/ScalaRunTime$
  #161 = Utf8               Lscala/runtime/ScalaRunTime$;
  #162 = NameAndType        #24:#161      // MODULE$:Lscala/runtime/ScalaRunTime$;
  #163 = Fieldref           #160.#162     // scala/runtime/ScalaRunTime$.MODULE$:Lscala/runtime/ScalaRunTime$;
  #164 = Utf8               array_apply
  #165 = Utf8               (Ljava/lang/Object;I)Ljava/lang/Object;
  #166 = NameAndType        #164:#165     // array_apply:(Ljava/lang/Object;I)Ljava/lang/Object;
  #167 = Methodref          #160.#166     // scala/runtime/ScalaRunTime$.array_apply:(Ljava/lang/Object;I)Ljava/lang/Object;
  #168 = Utf8               update
  #169 = Utf8               (JLjava/lang/Object;)V
  #170 = NameAndType        #168:#169     // update:(JLjava/lang/Object;)V
  #171 = Methodref          #16.#170      // scala/collection/mutable/LongMap.update:(JLjava/lang/Object;)V
  #172 = Utf8               i
  #173 = Utf8               [J
  #174 = Utf8               Ljava/lang/Object;
  #175 = Utf8               (Lscala/collection/Iterable;Lscala/collection/Iterable;)Lscala/collection/mutable/LongMap;
  #176 = Utf8               <V:Ljava/lang/Object;>(Lscala/collection/Iterable<Ljava/lang/Object;>;Lscala/collection/Iterable<TV;>;)Lscala/collection/mutable/LongMap<TV;>;
  #177 = Utf8               scala/collection/Iterable
  #178 = Class              #177          // scala/collection/Iterable
  #179 = InterfaceMethodref #178.#108     // scala/collection/Iterable.size:()I
  #180 = InterfaceMethodref #178.#89      // scala/collection/Iterable.iterator:()Lscala/collection/Iterator;
  #181 = Utf8               hasNext
  #182 = Utf8               ()Z
  #183 = NameAndType        #181:#182     // hasNext:()Z
  #184 = InterfaceMethodref #102.#183     // scala/collection/Iterator.hasNext:()Z
  #185 = Utf8               next
  #186 = Utf8               ()Ljava/lang/Object;
  #187 = NameAndType        #185:#186     // next:()Ljava/lang/Object;
  #188 = InterfaceMethodref #102.#187     // scala/collection/Iterator.next:()Ljava/lang/Object;
  #189 = Utf8               scala/runtime/BoxesRunTime
  #190 = Class              #189          // scala/runtime/BoxesRunTime
  #191 = Utf8               unboxToLong
  #192 = Utf8               (Ljava/lang/Object;)J
  #193 = NameAndType        #191:#192     // unboxToLong:(Ljava/lang/Object;)J
  #194 = Methodref          #190.#193     // scala/runtime/BoxesRunTime.unboxToLong:(Ljava/lang/Object;)J
  #195 = Utf8               ki
  #196 = Utf8               Lscala/collection/Iterator;
  #197 = Utf8               vi
  #198 = Utf8               Lscala/collection/Iterable;
  #199 = Utf8               toFactory
  #200 = Utf8               (Lscala/collection/mutable/LongMap$;)Lscala/collection/Factory;
  #201 = Utf8               <V:Ljava/lang/Object;>(Lscala/collection/mutable/LongMap$;)Lscala/collection/Factory<Lscala/Tuple2<Ljava/lang/Object;TV;>;Lscala/collection/mutable/LongMap<TV;>;>;
  #202 = Utf8               dummy
  #203 = Utf8               Lscala/collection/mutable/LongMap$ToFactory$;
  #204 = NameAndType        #24:#203      // MODULE$:Lscala/collection/mutable/LongMap$ToFactory$;
  #205 = Fieldref           #22.#204      // scala/collection/mutable/LongMap$ToFactory$.MODULE$:Lscala/collection/mutable/LongMap$ToFactory$;
  #206 = Utf8               toBuildFrom
  #207 = Utf8               (Lscala/collection/mutable/LongMap$;)Lscala/collection/BuildFrom;
  #208 = Utf8               <V:Ljava/lang/Object;>(Lscala/collection/mutable/LongMap$;)Lscala/collection/BuildFrom<Ljava/lang/Object;Lscala/Tuple2<Ljava/lang/Object;TV;>;Lscala/collection/mutable/LongMap<TV;>;>;
  #209 = Utf8               factory
  #210 = Utf8               Lscala/collection/mutable/LongMap$ToBuildFrom$;
  #211 = NameAndType        #24:#210      // MODULE$:Lscala/collection/mutable/LongMap$ToBuildFrom$;
  #212 = Fieldref           #19.#211      // scala/collection/mutable/LongMap$ToBuildFrom$.MODULE$:Lscala/collection/mutable/LongMap$ToBuildFrom$;
  #213 = Utf8               iterableFactory
  #214 = Utf8               ()Lscala/collection/Factory;
  #215 = Utf8               <V:Ljava/lang/Object;>()Lscala/collection/Factory<Lscala/Tuple2<Ljava/lang/Object;TV;>;Lscala/collection/mutable/LongMap<TV;>;>;
  #216 = Utf8               buildFromLongMap
  #217 = Utf8               ()Lscala/collection/BuildFrom;
  #218 = Utf8               <V:Ljava/lang/Object;>()Lscala/collection/BuildFrom<Lscala/collection/mutable/LongMap<*>;Lscala/Tuple2<Ljava/lang/Object;TV;>;Lscala/collection/mutable/LongMap<TV;>;>;
  #219 = Utf8               writeReplace
  #220 = Utf8               scala/runtime/ModuleSerializationProxy
  #221 = Class              #220          // scala/runtime/ModuleSerializationProxy
  #222 = Utf8               (Ljava/lang/Class;)V
  #223 = NameAndType        #31:#222      // "<init>":(Ljava/lang/Class;)V
  #224 = Methodref          #221.#223     // scala/runtime/ModuleSerializationProxy."<init>":(Ljava/lang/Class;)V
  #225 = Utf8               $anonfun$exceptionDefault$1
  #226 = Utf8               (J)Lscala/runtime/Nothing$;
  #227 = Utf8               k
  #228 = Utf8               java/util/NoSuchElementException
  #229 = Class              #228          // java/util/NoSuchElementException
  #230 = Utf8               java/lang/Long
  #231 = Class              #230          // java/lang/Long
  #232 = Utf8               toString
  #233 = Utf8               (J)Ljava/lang/String;
  #234 = NameAndType        #232:#233     // toString:(J)Ljava/lang/String;
  #235 = Methodref          #231.#234     // java/lang/Long.toString:(J)Ljava/lang/String;
  #236 = Utf8               (Ljava/lang/String;)V
  #237 = NameAndType        #31:#236      // "<init>":(Ljava/lang/String;)V
  #238 = Methodref          #229.#237     // java/util/NoSuchElementException."<init>":(Ljava/lang/String;)V
  #239 = Utf8               J
  #240 = Utf8               $anonfun$buildFromIterableOnce$1
  #241 = Utf8               (Lscala/collection/mutable/LongMap;Lscala/Tuple2;)V
  #242 = Utf8               lm$2
  #243 = Utf8               x0$1
  #244 = Utf8               scala/Tuple2
  #245 = Class              #244          // scala/Tuple2
  #246 = Utf8               _1$mcJ$sp
  #247 = Utf8               ()J
  #248 = NameAndType        #246:#247     // _1$mcJ$sp:()J
  #249 = Methodref          #245.#248     // scala/Tuple2._1$mcJ$sp:()J
  #250 = Utf8               _2
  #251 = NameAndType        #250:#186     // _2:()Ljava/lang/Object;
  #252 = Methodref          #245.#251     // scala/Tuple2._2:()Ljava/lang/Object;
  #253 = Utf8               scala/MatchError
  #254 = Class              #253          // scala/MatchError
  #255 = Utf8               (Ljava/lang/Object;)V
  #256 = NameAndType        #31:#255      // "<init>":(Ljava/lang/Object;)V
  #257 = Methodref          #254.#256     // scala/MatchError."<init>":(Ljava/lang/Object;)V
  #258 = Utf8               v
  #259 = Utf8               Lscala/Tuple2;
  #260 = Methodref          #4.#32        // java/lang/Object."<init>":()V
  #261 = NameAndType        #240:#241     // $anonfun$buildFromIterableOnce$1:(Lscala/collection/mutable/LongMap;Lscala/Tuple2;)V
  #262 = Methodref          #2.#261       // scala/collection/mutable/LongMap$.$anonfun$buildFromIterableOnce$1:(Lscala/collection/mutable/LongMap;Lscala/Tuple2;)V
  #263 = Utf8               scala/runtime/BoxedUnit
  #264 = Class              #263          // scala/runtime/BoxedUnit
  #265 = Utf8               UNIT
  #266 = Utf8               Lscala/runtime/BoxedUnit;
  #267 = NameAndType        #265:#266     // UNIT:Lscala/runtime/BoxedUnit;
  #268 = Fieldref           #264.#267     // scala/runtime/BoxedUnit.UNIT:Lscala/runtime/BoxedUnit;
  #269 = NameAndType        #225:#226     // $anonfun$exceptionDefault$1:(J)Lscala/runtime/Nothing$;
  #270 = Methodref          #2.#269       // scala/collection/mutable/LongMap$.$anonfun$exceptionDefault$1:(J)Lscala/runtime/Nothing$;
  #271 = Utf8               $deserializeLambda$
  #272 = Utf8               (Ljava/lang/invoke/SerializedLambda;)Ljava/lang/Object;
  #273 = Utf8               scala/runtime/LambdaDeserialize
  #274 = Class              #273          // scala/runtime/LambdaDeserialize
  #275 = Utf8               bootstrap
  #276 = Utf8               (Ljava/lang/invoke/MethodHandles$Lookup;Ljava/lang/String;Ljava/lang/invoke/MethodType;[Ljava/lang/invoke/MethodHandle;)Ljava/lang/invoke/CallSite;
  #277 = NameAndType        #275:#276     // bootstrap:(Ljava/lang/invoke/MethodHandles$Lookup;Ljava/lang/String;Ljava/lang/invoke/MethodType;[Ljava/lang/invoke/MethodHandle;)Ljava/lang/invoke/CallSite;
  #278 = Methodref          #274.#277     // scala/runtime/LambdaDeserialize.bootstrap:(Ljava/lang/invoke/MethodHandles$Lookup;Ljava/lang/String;Ljava/lang/invoke/MethodType;[Ljava/lang/invoke/MethodHandle;)Ljava/lang/invoke/CallSite;
  #279 = MethodHandle       6:#278        // REF_invokeStatic scala/runtime/LambdaDeserialize.bootstrap:(Ljava/lang/invoke/MethodHandles$Lookup;Ljava/lang/String;Ljava/lang/invoke/MethodType;[Ljava/lang/invoke/MethodHandle;)Ljava/lang/invoke/CallSite;
  #280 = Utf8               lambdaDeserialize
  #281 = NameAndType        #280:#272     // lambdaDeserialize:(Ljava/lang/invoke/SerializedLambda;)Ljava/lang/Object;
  #282 = InvokeDynamic      #2:#281       // #2:lambdaDeserialize:(Ljava/lang/invoke/SerializedLambda;)Ljava/lang/Object;
  #283 = Utf8               Signature
  #284 = Utf8               Code
  #285 = Utf8               LineNumberTable
  #286 = Utf8               LocalVariableTable
  #287 = Utf8               MethodParameters
  #288 = Utf8               StackMapTable
  #289 = Utf8               InnerClasses
  #290 = Utf8               SourceFile
  #291 = Utf8               BootstrapMethods
  #292 = Utf8               ScalaInlineInfo
  #293 = Utf8               Scala
{
  public static final scala.collection.mutable.LongMap$ MODULE$;
    descriptor: Lscala/collection/mutable/LongMap$;
    flags: (0x0019) ACC_PUBLIC, ACC_STATIC, ACC_FINAL

  private static final scala.Function1<java.lang.Object, scala.runtime.Nothing$> scala$collection$mutable$LongMap$$exceptionDefault;
    descriptor: Lscala/Function1;
    flags: (0x001a) ACC_PRIVATE, ACC_STATIC, ACC_FINAL
    Signature: #28                          // Lscala/Function1<Ljava/lang/Object;Lscala/runtime/Nothing$;>;

  public static {};
    descriptor: ()V
    flags: (0x0009) ACC_PUBLIC, ACC_STATIC
    Code:
      stack=2, locals=0, args_size=0
         0: new           #2                  // class scala/collection/mutable/LongMap$
         3: dup
         4: invokespecial #33                 // Method "<init>":()V
         7: putstatic     #35                 // Field MODULE$:Lscala/collection/mutable/LongMap$;
        10: invokedynamic #56,  0             // InvokeDynamic #0:apply:()Lscala/Function1;
        15: putstatic     #58                 // Field scala$collection$mutable$LongMap$$exceptionDefault:Lscala/Function1;
        18: return
      LineNumberTable:
        line 577: 0
        line 583: 10
        line 577: 18

  private final int IndexMask();
    descriptor: ()I
    flags: (0x0012) ACC_PRIVATE, ACC_FINAL
    Code:
      stack=1, locals=1, args_size=1
         0: ldc           #61                 // int 1073741823
         2: ireturn
      LocalVariableTable:
        Start  Length  Slot  Name   Signature
            0       3     0  this   Lscala/collection/mutable/LongMap$;

  private final int MissingBit();
    descriptor: ()I
    flags: (0x0012) ACC_PRIVATE, ACC_FINAL
    Code:
      stack=1, locals=1, args_size=1
         0: ldc           #64                 // int -2147483648
         2: ireturn
      LocalVariableTable:
        Start  Length  Slot  Name   Signature
            0       3     0  this   Lscala/collection/mutable/LongMap$;

  private final int VacantBit();
    descriptor: ()I
    flags: (0x0012) ACC_PRIVATE, ACC_FINAL
    Code:
      stack=1, locals=1, args_size=1
         0: ldc           #66                 // int 1073741824
         2: ireturn
      LocalVariableTable:
        Start  Length  Slot  Name   Signature
            0       3     0  this   Lscala/collection/mutable/LongMap$;

  private final int MissVacant();
    descriptor: ()I
    flags: (0x0012) ACC_PRIVATE, ACC_FINAL
    Code:
      stack=1, locals=1, args_size=1
         0: ldc           #68                 // int -1073741824
         2: ireturn
      LocalVariableTable:
        Start  Length  Slot  Name   Signature
            0       3     0  this   Lscala/collection/mutable/LongMap$;

  public scala.Function1<java.lang.Object, scala.runtime.Nothing$> scala$collection$mutable$LongMap$$exceptionDefault();
    descriptor: ()Lscala/Function1;
    flags: (0x0001) ACC_PUBLIC
    Code:
      stack=1, locals=1, args_size=1
         0: getstatic     #58                 // Field scala$collection$mutable$LongMap$$exceptionDefault:Lscala/Function1;
         3: areturn
      LineNumberTable:
        line 583: 0
      LocalVariableTable:
        Start  Length  Slot  Name   Signature
            0       4     0  this   Lscala/collection/mutable/LongMap$;
    Signature: #69                          // ()Lscala/Function1<Ljava/lang/Object;Lscala/runtime/Nothing$;>;

  public <V extends java.lang.Object> scala.collection.mutable.LongMap<V> apply(scala.collection.immutable.Seq<scala.Tuple2<java.lang.Object, V>>);
    descriptor: (Lscala/collection/immutable/Seq;)Lscala/collection/mutable/LongMap;
    flags: (0x0001) ACC_PUBLIC
    Code:
      stack=2, locals=2, args_size=2
         0: aload_0
         1: aload_1
         2: invokespecial #76                 // Method buildFromIterableOnce:(Lscala/collection/IterableOnce;)Lscala/collection/mutable/LongMap;
         5: areturn
      LineNumberTable:
        line 601: 0
      LocalVariableTable:
        Start  Length  Slot  Name   Signature
            0       6     0  this   Lscala/collection/mutable/LongMap$;
            0       6     1 elems   Lscala/collection/immutable/Seq;
    Signature: #71                          // <V:Ljava/lang/Object;>(Lscala/collection/immutable/Seq<Lscala/Tuple2<Ljava/lang/Object;TV;>;>;)Lscala/collection/mutable/LongMap<TV;>;
    MethodParameters:
      Name                           Flags
      elems                          final

  private <V extends java.lang.Object> scala.collection.mutable.LongMap<V> buildFromIterableOnce(scala.collection.IterableOnce<scala.Tuple2<java.lang.Object, V>>);
    descriptor: (Lscala/collection/IterableOnce;)Lscala/collection/mutable/LongMap;
    flags: (0x0002) ACC_PRIVATE
    Code:
      stack=4, locals=4, args_size=2
         0: aload_1
         1: invokeinterface #83,  1           // InterfaceMethod scala/collection/IterableOnce.knownSize:()I
         6: istore_2
         7: iload_2
         8: iconst_0
         9: if_icmpge     14
        12: iconst_4
        13: istore_2
        14: new           #16                 // class scala/collection/mutable/LongMap
        17: dup
        18: iload_2
        19: iconst_2
        20: imul
        21: invokespecial #86                 // Method scala/collection/mutable/LongMap."<init>":(I)V
        24: astore_3
        25: aload_1
        26: invokeinterface #90,  1           // InterfaceMethod scala/collection/IterableOnce.iterator:()Lscala/collection/Iterator;
        31: aload_3
        32: invokedynamic #100,  0            // InvokeDynamic #1:apply:(Lscala/collection/mutable/LongMap;)Lscala/Function1;
        37: invokeinterface #106,  2          // InterfaceMethod scala/collection/Iterator.foreach:(Lscala/Function1;)V
        42: aload_3
        43: invokevirtual #109                // Method scala/collection/mutable/LongMap.size:()I
        46: iload_2
        47: iconst_3
        48: ishr
        49: if_icmpge     56
        52: aload_3
        53: invokevirtual #112                // Method scala/collection/mutable/LongMap.repack:()V
        56: aload_3
        57: areturn
      StackMapTable: number_of_entries = 2
        frame_type = 252 /* append */
          offset_delta = 14
          locals = [ int ]
        frame_type = 252 /* append */
          offset_delta = 41
          locals = [ class scala/collection/mutable/LongMap ]
      LineNumberTable:
        line 604: 0
        line 605: 7
        line 606: 14
        line 607: 25
        line 608: 42
        line 609: 56
      LocalVariableTable:
        Start  Length  Slot  Name   Signature
            7      50     2    sz   I
           25      32     3    lm   Lscala/collection/mutable/LongMap;
            0      58     0  this   Lscala/collection/mutable/LongMap$;
            0      58     1 elems   Lscala/collection/IterableOnce;
    Signature: #78                          // <V:Ljava/lang/Object;>(Lscala/collection/IterableOnce<Lscala/Tuple2<Ljava/lang/Object;TV;>;>;)Lscala/collection/mutable/LongMap<TV;>;
    MethodParameters:
      Name                           Flags
      elems                          final

  public <V extends java.lang.Object> scala.collection.mutable.LongMap<V> empty();
    descriptor: ()Lscala/collection/mutable/LongMap;
    flags: (0x0001) ACC_PUBLIC
    Code:
      stack=2, locals=1, args_size=1
         0: new           #16                 // class scala/collection/mutable/LongMap
         3: dup
         4: invokespecial #121                // Method scala/collection/mutable/LongMap."<init>":()V
         7: areturn
      LineNumberTable:
        line 613: 0
      LocalVariableTable:
        Start  Length  Slot  Name   Signature
            0       8     0  this   Lscala/collection/mutable/LongMap$;
    Signature: #120                         // <V:Ljava/lang/Object;>()Lscala/collection/mutable/LongMap<TV;>;

  public <V extends java.lang.Object> scala.collection.mutable.LongMap<V> withDefault(scala.Function1<java.lang.Object, V>);
    descriptor: (Lscala/Function1;)Lscala/collection/mutable/LongMap;
    flags: (0x0001) ACC_PUBLIC
    Code:
      stack=3, locals=2, args_size=2
         0: new           #16                 // class scala/collection/mutable/LongMap
         3: dup
         4: aload_1
         5: invokespecial #127                // Method scala/collection/mutable/LongMap."<init>":(Lscala/Function1;)V
         8: areturn
      LineNumberTable:
        line 616: 0
      LocalVariableTable:
        Start  Length  Slot  Name   Signature
            0       9     0  this   Lscala/collection/mutable/LongMap$;
            0       9     1 default   Lscala/Function1;
    Signature: #124                         // <V:Ljava/lang/Object;>(Lscala/Function1<Ljava/lang/Object;TV;>;)Lscala/collection/mutable/LongMap<TV;>;
    MethodParameters:
      Name                           Flags
      default                        final

  public <V extends java.lang.Object> scala.collection.mutable.LongMap<V> from(scala.collection.IterableOnce<scala.Tuple2<java.lang.Object, V>>);
    descriptor: (Lscala/collection/IterableOnce;)Lscala/collection/mutable/LongMap;
    flags: (0x0001) ACC_PUBLIC
    Code:
      stack=2, locals=3, args_size=2
         0: aload_1
         1: instanceof    #16                 // class scala/collection/mutable/LongMap
         4: ifeq          18
         7: aload_1
         8: checkcast     #16                 // class scala/collection/mutable/LongMap
        11: invokevirtual #132                // Method scala/collection/mutable/LongMap.clone:()Lscala/collection/mutable/LongMap;
        14: astore_2
        15: goto          24
        18: aload_0
        19: aload_1
        20: invokespecial #76                 // Method buildFromIterableOnce:(Lscala/collection/IterableOnce;)Lscala/collection/mutable/LongMap;
        23: astore_2
        24: aload_2
        25: areturn
      StackMapTable: number_of_entries = 2
        frame_type = 18 /* same */
        frame_type = 252 /* append */
          offset_delta = 5
          locals = [ class scala/collection/mutable/LongMap ]
      LineNumberTable:
        line 626: 0
        line 627: 18
        line 625: 24
      LocalVariableTable:
        Start  Length  Slot  Name   Signature
            0      26     0  this   Lscala/collection/mutable/LongMap$;
            0      26     1 source   Lscala/collection/IterableOnce;
    Signature: #78                          // <V:Ljava/lang/Object;>(Lscala/collection/IterableOnce<Lscala/Tuple2<Ljava/lang/Object;TV;>;>;)Lscala/collection/mutable/LongMap<TV;>;
    MethodParameters:
      Name                           Flags
      source                         final

  public <V extends java.lang.Object> scala.collection.mutable.ReusableBuilder<scala.Tuple2<java.lang.Object, V>, scala.collection.mutable.LongMap<V>> newBuilder();
    descriptor: ()Lscala/collection/mutable/ReusableBuilder;
    flags: (0x0001) ACC_PUBLIC
    Code:
      stack=2, locals=1, args_size=1
         0: new           #14                 // class scala/collection/mutable/LongMap$LongMapBuilder
         3: dup
         4: invokespecial #136                // Method scala/collection/mutable/LongMap$LongMapBuilder."<init>":()V
         7: areturn
      LineNumberTable:
        line 630: 0
      LocalVariableTable:
        Start  Length  Slot  Name   Signature
            0       8     0  this   Lscala/collection/mutable/LongMap$;
    Signature: #135                         // <V:Ljava/lang/Object;>()Lscala/collection/mutable/ReusableBuilder<Lscala/Tuple2<Ljava/lang/Object;TV;>;Lscala/collection/mutable/LongMap<TV;>;>;

  public <V extends java.lang.Object> scala.collection.mutable.LongMap<V> fromZip(long[], java.lang.Object);
    descriptor: ([JLjava/lang/Object;)Lscala/collection/mutable/LongMap;
    flags: (0x0001) ACC_PUBLIC
    Code:
      stack=6, locals=6, args_size=3
         0: getstatic     #146                // Field scala/math/package$.MODULE$:Lscala/math/package$;
         3: pop
         4: aload_1
         5: arraylength
         6: aload_2
         7: invokestatic  #152                // Method java/lang/reflect/Array.getLength:(Ljava/lang/Object;)I
        10: invokestatic  #158                // Method java/lang/Math.min:(II)I
        13: istore        5
        15: new           #16                 // class scala/collection/mutable/LongMap
        18: dup
        19: iload         5
        21: iconst_2
        22: imul
        23: invokespecial #86                 // Method scala/collection/mutable/LongMap."<init>":(I)V
        26: astore_3
        27: iconst_0
        28: istore        4
        30: iload         4
        32: iload         5
        34: if_icmpge     60
        37: aload_3
        38: aload_1
        39: iload         4
        41: laload
        42: getstatic     #163                // Field scala/runtime/ScalaRunTime$.MODULE$:Lscala/runtime/ScalaRunTime$;
        45: aload_2
        46: iload         4
        48: invokevirtual #167                // Method scala/runtime/ScalaRunTime$.array_apply:(Ljava/lang/Object;I)Ljava/lang/Object;
        51: invokevirtual #171                // Method scala/collection/mutable/LongMap.update:(JLjava/lang/Object;)V
        54: iinc          4, 1
        57: goto          30
        60: aload_3
        61: invokevirtual #109                // Method scala/collection/mutable/LongMap.size:()I
        64: iload         5
        66: iconst_3
        67: ishr
        68: if_icmpge     75
        71: aload_3
        72: invokevirtual #112                // Method scala/collection/mutable/LongMap.repack:()V
        75: aload_3
        76: areturn
      StackMapTable: number_of_entries = 3
        frame_type = 254 /* append */
          offset_delta = 30
          locals = [ class scala/collection/mutable/LongMap, int, int ]
        frame_type = 29 /* same */
        frame_type = 14 /* same */
      LineNumberTable:
        line 636: 0
        line 637: 15
        line 638: 27
        line 639: 30
        line 640: 60
        line 641: 75
      LocalVariableTable:
        Start  Length  Slot  Name   Signature
           27      49     3    lm   Lscala/collection/mutable/LongMap;
           30      46     4     i   I
            0      77     0  this   Lscala/collection/mutable/LongMap$;
            0      77     1  keys   [J
            0      77     2 values   Ljava/lang/Object;
    Signature: #139                         // <V:Ljava/lang/Object;>([JLjava/lang/Object;)Lscala/collection/mutable/LongMap<TV;>;
    MethodParameters:
      Name                           Flags
      keys                           final
      values                         final

  public <V extends java.lang.Object> scala.collection.mutable.LongMap<V> fromZip(scala.collection.Iterable<java.lang.Object>, scala.collection.Iterable<V>);
    descriptor: (Lscala/collection/Iterable;Lscala/collection/Iterable;)Lscala/collection/mutable/LongMap;
    flags: (0x0001) ACC_PUBLIC
    Code:
      stack=4, locals=7, args_size=3
         0: getstatic     #146                // Field scala/math/package$.MODULE$:Lscala/math/package$;
         3: pop
         4: aload_1
         5: invokeinterface #179,  1          // InterfaceMethod scala/collection/Iterable.size:()I
        10: aload_2
        11: invokeinterface #179,  1          // InterfaceMethod scala/collection/Iterable.size:()I
        16: invokestatic  #158                // Method java/lang/Math.min:(II)I
        19: istore        6
        21: new           #16                 // class scala/collection/mutable/LongMap
        24: dup
        25: iload         6
        27: iconst_2
        28: imul
        29: invokespecial #86                 // Method scala/collection/mutable/LongMap."<init>":(I)V
        32: astore_3
        33: aload_1
        34: invokeinterface #180,  1          // InterfaceMethod scala/collection/Iterable.iterator:()Lscala/collection/Iterator;
        39: astore        4
        41: aload_2
        42: invokeinterface #180,  1          // InterfaceMethod scala/collection/Iterable.iterator:()Lscala/collection/Iterator;
        47: astore        5
        49: aload         4
        51: invokeinterface #184,  1          // InterfaceMethod scala/collection/Iterator.hasNext:()Z
        56: ifeq          93
        59: aload         5
        61: invokeinterface #184,  1          // InterfaceMethod scala/collection/Iterator.hasNext:()Z
        66: ifeq          93
        69: aload_3
        70: aload         4
        72: invokeinterface #188,  1          // InterfaceMethod scala/collection/Iterator.next:()Ljava/lang/Object;
        77: invokestatic  #194                // Method scala/runtime/BoxesRunTime.unboxToLong:(Ljava/lang/Object;)J
        80: aload         5
        82: invokeinterface #188,  1          // InterfaceMethod scala/collection/Iterator.next:()Ljava/lang/Object;
        87: invokevirtual #171                // Method scala/collection/mutable/LongMap.update:(JLjava/lang/Object;)V
        90: goto          49
        93: aload_3
        94: invokevirtual #109                // Method scala/collection/mutable/LongMap.size:()I
        97: iload         6
        99: iconst_3
       100: ishr
       101: if_icmpge     108
       104: aload_3
       105: invokevirtual #112                // Method scala/collection/mutable/LongMap.repack:()V
       108: aload_3
       109: areturn
      StackMapTable: number_of_entries = 3
        frame_type = 255 /* full_frame */
          offset_delta = 49
          locals = [ class scala/collection/mutable/LongMap$, class scala/collection/Iterable, class scala/collection/Iterable, class scala/collection/mutable/LongMap, class scala/collection/Iterator, class scala/collection/Iterator, int ]
          stack = []
        frame_type = 43 /* same */
        frame_type = 14 /* same */
      LineNumberTable:
        line 648: 0
        line 649: 21
        line 650: 33
        line 651: 41
        line 652: 49
        line 653: 93
        line 654: 108
      LocalVariableTable:
        Start  Length  Slot  Name   Signature
           33      76     3    lm   Lscala/collection/mutable/LongMap;
           41      68     4    ki   Lscala/collection/Iterator;
           49      60     5    vi   Lscala/collection/Iterator;
            0     110     0  this   Lscala/collection/mutable/LongMap$;
            0     110     1  keys   Lscala/collection/Iterable;
            0     110     2 values   Lscala/collection/Iterable;
    Signature: #176                         // <V:Ljava/lang/Object;>(Lscala/collection/Iterable<Ljava/lang/Object;>;Lscala/collection/Iterable<TV;>;)Lscala/collection/mutable/LongMap<TV;>;
    MethodParameters:
      Name                           Flags
      keys                           final
      values                         final

  public <V extends java.lang.Object> scala.collection.Factory<scala.Tuple2<java.lang.Object, V>, scala.collection.mutable.LongMap<V>> toFactory(scala.collection.mutable.LongMap$);
    descriptor: (Lscala/collection/mutable/LongMap$;)Lscala/collection/Factory;
    flags: (0x0001) ACC_PUBLIC
    Code:
      stack=1, locals=2, args_size=2
         0: getstatic     #205                // Field scala/collection/mutable/LongMap$ToFactory$.MODULE$:Lscala/collection/mutable/LongMap$ToFactory$;
         3: areturn
      LineNumberTable:
        line 657: 0
      LocalVariableTable:
        Start  Length  Slot  Name   Signature
            0       4     0  this   Lscala/collection/mutable/LongMap$;
            0       4     1 dummy   Lscala/collection/mutable/LongMap$;
    Signature: #201                         // <V:Ljava/lang/Object;>(Lscala/collection/mutable/LongMap$;)Lscala/collection/Factory<Lscala/Tuple2<Ljava/lang/Object;TV;>;Lscala/collection/mutable/LongMap<TV;>;>;
    MethodParameters:
      Name                           Flags
      dummy                          final

  public <V extends java.lang.Object> scala.collection.BuildFrom<java.lang.Object, scala.Tuple2<java.lang.Object, V>, scala.collection.mutable.LongMap<V>> toBuildFrom(scala.collection.mutable.LongMap$);
    descriptor: (Lscala/collection/mutable/LongMap$;)Lscala/collection/BuildFrom;
    flags: (0x0001) ACC_PUBLIC
    Code:
      stack=1, locals=2, args_size=2
         0: getstatic     #212                // Field scala/collection/mutable/LongMap$ToBuildFrom$.MODULE$:Lscala/collection/mutable/LongMap$ToBuildFrom$;
         3: areturn
      LineNumberTable:
        line 665: 0
      LocalVariableTable:
        Start  Length  Slot  Name   Signature
            0       4     0  this   Lscala/collection/mutable/LongMap$;
            0       4     1 factory   Lscala/collection/mutable/LongMap$;
    Signature: #208                         // <V:Ljava/lang/Object;>(Lscala/collection/mutable/LongMap$;)Lscala/collection/BuildFrom<Ljava/lang/Object;Lscala/Tuple2<Ljava/lang/Object;TV;>;Lscala/collection/mutable/LongMap<TV;>;>;
    MethodParameters:
      Name                           Flags
      factory                        final

  public <V extends java.lang.Object> scala.collection.Factory<scala.Tuple2<java.lang.Object, V>, scala.collection.mutable.LongMap<V>> iterableFactory();
    descriptor: ()Lscala/collection/Factory;
    flags: (0x0001) ACC_PUBLIC
    Code:
      stack=1, locals=1, args_size=1
         0: getstatic     #205                // Field scala/collection/mutable/LongMap$ToFactory$.MODULE$:Lscala/collection/mutable/LongMap$ToFactory$;
         3: areturn
      LineNumberTable:
        line 657: 0
        line 671: 3
      LocalVariableTable:
        Start  Length  Slot  Name   Signature
            0       4     0  this   Lscala/collection/mutable/LongMap$;
    Signature: #215                         // <V:Ljava/lang/Object;>()Lscala/collection/Factory<Lscala/Tuple2<Ljava/lang/Object;TV;>;Lscala/collection/mutable/LongMap<TV;>;>;

  public <V extends java.lang.Object> scala.collection.BuildFrom<scala.collection.mutable.LongMap<?>, scala.Tuple2<java.lang.Object, V>, scala.collection.mutable.LongMap<V>> buildFromLongMap();
    descriptor: ()Lscala/collection/BuildFrom;
    flags: (0x0001) ACC_PUBLIC
    Code:
      stack=1, locals=1, args_size=1
         0: getstatic     #212                // Field scala/collection/mutable/LongMap$ToBuildFrom$.MODULE$:Lscala/collection/mutable/LongMap$ToBuildFrom$;
         3: areturn
      LineNumberTable:
        line 665: 0
        line 672: 3
      LocalVariableTable:
        Start  Length  Slot  Name   Signature
            0       4     0  this   Lscala/collection/mutable/LongMap$;
    Signature: #218                         // <V:Ljava/lang/Object;>()Lscala/collection/BuildFrom<Lscala/collection/mutable/LongMap<*>;Lscala/Tuple2<Ljava/lang/Object;TV;>;Lscala/collection/mutable/LongMap<TV;>;>;

  private java.lang.Object writeReplace();
    descriptor: ()Ljava/lang/Object;
    flags: (0x0002) ACC_PRIVATE
    Code:
      stack=3, locals=1, args_size=1
         0: new           #221                // class scala/runtime/ModuleSerializationProxy
         3: dup
         4: ldc           #2                  // class scala/collection/mutable/LongMap$
         6: invokespecial #224                // Method scala/runtime/ModuleSerializationProxy."<init>":(Ljava/lang/Class;)V
         9: areturn
      LineNumberTable:
        line 577: 0
      LocalVariableTable:
        Start  Length  Slot  Name   Signature
            0      10     0  this   Lscala/collection/mutable/LongMap$;

  public static final scala.runtime.Nothing$ $anonfun$exceptionDefault$1(long);
    descriptor: (J)Lscala/runtime/Nothing$;
    flags: (0x1019) ACC_PUBLIC, ACC_STATIC, ACC_FINAL, ACC_SYNTHETIC
    Code:
      stack=4, locals=2, args_size=1
         0: new           #229                // class java/util/NoSuchElementException
         3: dup
         4: lload_0
         5: invokestatic  #235                // Method java/lang/Long.toString:(J)Ljava/lang/String;
         8: invokespecial #238                // Method java/util/NoSuchElementException."<init>":(Ljava/lang/String;)V
        11: athrow
      LineNumberTable:
        line 583: 0
      LocalVariableTable:
        Start  Length  Slot  Name   Signature
            0      12     0     k   J
    MethodParameters:
      Name                           Flags
      k                              final

  public static final void $anonfun$buildFromIterableOnce$1(scala.collection.mutable.LongMap, scala.Tuple2);
    descriptor: (Lscala/collection/mutable/LongMap;Lscala/Tuple2;)V
    flags: (0x1019) ACC_PUBLIC, ACC_STATIC, ACC_FINAL, ACC_SYNTHETIC
    Code:
      stack=4, locals=5, args_size=2
         0: aload_1
         1: ifnull        23
         4: aload_1
         5: invokevirtual #249                // Method scala/Tuple2._1$mcJ$sp:()J
         8: lstore_2
         9: aload_1
        10: invokevirtual #252                // Method scala/Tuple2._2:()Ljava/lang/Object;
        13: astore        4
        15: aload_0
        16: lload_2
        17: aload         4
        19: invokevirtual #171                // Method scala/collection/mutable/LongMap.update:(JLjava/lang/Object;)V
        22: return
        23: new           #254                // class scala/MatchError
        26: dup
        27: aconst_null
        28: invokespecial #257                // Method scala/MatchError."<init>":(Ljava/lang/Object;)V
        31: athrow
      StackMapTable: number_of_entries = 1
        frame_type = 23 /* same */
      LineNumberTable:
        line 607: 0
      LocalVariableTable:
        Start  Length  Slot  Name   Signature
            9      14     2     k   J
           15       8     4     v   Ljava/lang/Object;
            0      32     0  lm$2   Lscala/collection/mutable/LongMap;
            0      32     1  x0$1   Lscala/Tuple2;
    MethodParameters:
      Name                           Flags
      lm$2                           final
      x0$1                           final

  private scala.collection.mutable.LongMap$();
    descriptor: ()V
    flags: (0x0002) ACC_PRIVATE
    Code:
      stack=1, locals=1, args_size=1
         0: aload_0
         1: invokespecial #260                // Method java/lang/Object."<init>":()V
         4: return
      LineNumberTable:
        line 577: 0
      LocalVariableTable:
        Start  Length  Slot  Name   Signature
            0       5     0  this   Lscala/collection/mutable/LongMap$;

  public static final java.lang.Object $anonfun$buildFromIterableOnce$1$adapted(scala.collection.mutable.LongMap, scala.Tuple2);
    descriptor: (Lscala/collection/mutable/LongMap;Lscala/Tuple2;)Ljava/lang/Object;
    flags: (0x1019) ACC_PUBLIC, ACC_STATIC, ACC_FINAL, ACC_SYNTHETIC
    Code:
      stack=2, locals=2, args_size=2
         0: aload_0
         1: aload_1
         2: invokestatic  #262                // Method $anonfun$buildFromIterableOnce$1:(Lscala/collection/mutable/LongMap;Lscala/Tuple2;)V
         5: getstatic     #268                // Field scala/runtime/BoxedUnit.UNIT:Lscala/runtime/BoxedUnit;
         8: areturn
      LineNumberTable:
        line 607: 0
      LocalVariableTable:
        Start  Length  Slot  Name   Signature
            0       9     0  lm$2   Lscala/collection/mutable/LongMap;
            0       9     1  x0$1   Lscala/Tuple2;
    MethodParameters:
      Name                           Flags
      lm$2                           final
      x0$1                           final

  public static final scala.runtime.Nothing$ $anonfun$exceptionDefault$1$adapted(java.lang.Object);
    descriptor: (Ljava/lang/Object;)Lscala/runtime/Nothing$;
    flags: (0x1019) ACC_PUBLIC, ACC_STATIC, ACC_FINAL, ACC_SYNTHETIC
    Code:
      stack=2, locals=1, args_size=1
         0: aload_0
         1: invokestatic  #194                // Method scala/runtime/BoxesRunTime.unboxToLong:(Ljava/lang/Object;)J
         4: invokestatic  #270                // Method $anonfun$exceptionDefault$1:(J)Lscala/runtime/Nothing$;
         7: areturn
      LineNumberTable:
        line 583: 0
      LocalVariableTable:
        Start  Length  Slot  Name   Signature
            0       8     0     k   Ljava/lang/Object;
    MethodParameters:
      Name                           Flags
      k                              final

  private static java.lang.Object $deserializeLambda$(java.lang.invoke.SerializedLambda);
    descriptor: (Ljava/lang/invoke/SerializedLambda;)Ljava/lang/Object;
    flags: (0x100a) ACC_PRIVATE, ACC_STATIC, ACC_SYNTHETIC
    Code:
      stack=1, locals=1, args_size=1
         0: aload_0
         1: invokedynamic #282,  0            // InvokeDynamic #2:lambdaDeserialize:(Ljava/lang/invoke/SerializedLambda;)Ljava/lang/Object;
         6: areturn
}
InnerClasses:
  public static final #12= #9 of #11;     // Lookup=class java/lang/invoke/MethodHandles$Lookup of class java/lang/invoke/MethodHandles
  public static final #17= #14 of #16;    // LongMapBuilder=class scala/collection/mutable/LongMap$LongMapBuilder of class scala/collection/mutable/LongMap
  private static #20= #19 of #16;         // ToBuildFrom$=class scala/collection/mutable/LongMap$ToBuildFrom$ of class scala/collection/mutable/LongMap
  private static #23= #22 of #16;         // ToFactory$=class scala/collection/mutable/LongMap$ToFactory$ of class scala/collection/mutable/LongMap
SourceFile: "LongMap.scala"
BootstrapMethods:
  0: #52 REF_invokeStatic java/lang/invoke/LambdaMetafactory.altMetafactory:(Ljava/lang/invoke/MethodHandles$Lookup;Ljava/lang/String;Ljava/lang/invoke/MethodType;[Ljava/lang/Object;)Ljava/lang/invoke/CallSite;
    Method arguments:
      #37 (Ljava/lang/Object;)Ljava/lang/Object;
      #42 REF_invokeStatic scala/collection/mutable/LongMap$.$anonfun$exceptionDefault$1$adapted:(Ljava/lang/Object;)Lscala/runtime/Nothing$;
      #43 (Ljava/lang/Object;)Lscala/runtime/Nothing$;
      #44 5
      #45 1
      #43 (Ljava/lang/Object;)Lscala/runtime/Nothing$;
  1: #52 REF_invokeStatic java/lang/invoke/LambdaMetafactory.altMetafactory:(Ljava/lang/invoke/MethodHandles$Lookup;Ljava/lang/String;Ljava/lang/invoke/MethodType;[Ljava/lang/Object;)Ljava/lang/invoke/CallSite;
    Method arguments:
      #37 (Ljava/lang/Object;)Ljava/lang/Object;
      #95 REF_invokeStatic scala/collection/mutable/LongMap$.$anonfun$buildFromIterableOnce$1$adapted:(Lscala/collection/mutable/LongMap;Lscala/Tuple2;)Ljava/lang/Object;
      #97 (Lscala/Tuple2;)Ljava/lang/Object;
      #44 5
      #45 1
      #97 (Lscala/Tuple2;)Ljava/lang/Object;
  2: #279 REF_invokeStatic scala/runtime/LambdaDeserialize.bootstrap:(Ljava/lang/invoke/MethodHandles$Lookup;Ljava/lang/String;Ljava/lang/invoke/MethodType;[Ljava/lang/invoke/MethodHandle;)Ljava/lang/invoke/CallSite;
    Method arguments:
      #95 REF_invokeStatic scala/collection/mutable/LongMap$.$anonfun$buildFromIterableOnce$1$adapted:(Lscala/collection/mutable/LongMap;Lscala/Tuple2;)Ljava/lang/Object;
      #42 REF_invokeStatic scala/collection/mutable/LongMap$.$anonfun$exceptionDefault$1$adapted:(Ljava/lang/Object;)Lscala/runtime/Nothing$;
  ScalaInlineInfo: length = 0x77 (unknown attribute)
   01 01 00 17 00 F0 00 F1 01 00 5B 00 5C 01 00 E1
   00 E2 01 00 26 00 27 01 00 1F 00 1E 01 00 3B 00
   3C 01 00 43 00 3C 01 00 3F 00 3C 01 00 41 00 3C
   01 00 35 00 46 01 00 49 00 4A 01 00 D8 00 D9 01
   00 76 00 77 01 00 80 00 4A 01 00 89 00 AF 01 00
   89 00 8A 01 00 D5 00 D6 01 00 85 00 86 01 00 1A
   00 36 01 00 CE 00 CF 01 00 C7 00 C8 01 00 7A 00
   7B 01 00 DB 00 BA 01
  Scala: length = 0x0 (unknown attribute)

