Classfile /Users/mw/Projects/slang-braindump/.jar/jar8/assemble/slang-braindump/assemble/content/scala/collection/mutable/MapOps.class
  Last modified May 29, 2022; size 12521 bytes
  SHA-256 checksum ee406b13c4084d80d36cfcc98db0bdcb009ace0f6120bcd3079fcbbeb1fbee07
  Compiled from "Map.scala"
public interface scala.collection.mutable.MapOps<K extends java.lang.Object, V extends java.lang.Object, CC extends scala.collection.mutable.MapOps<java.lang.Object, java.lang.Object, CC, ?>, C extends scala.collection.mutable.MapOps<K, V, CC, C>> extends scala.collection.MapOps<K, V, CC, C>, scala.collection.mutable.Cloneable<C>, scala.collection.mutable.Builder<scala.Tuple2<K, V>, C>, scala.collection.mutable.Shrinkable<K>
  minor version: 0
  major version: 52
  flags: (0x0601) ACC_PUBLIC, ACC_INTERFACE, ACC_ABSTRACT
  this_class: #2                          // scala/collection/mutable/MapOps
  super_class: #5                         // java/lang/Object
  interfaces: 4, fields: 0, methods: 35, attributes: 7
Constant pool:
    #1 = Utf8               scala/collection/mutable/MapOps
    #2 = Class              #1            // scala/collection/mutable/MapOps
    #3 = Utf8               <K:Ljava/lang/Object;V:Ljava/lang/Object;CC::Lscala/collection/mutable/MapOps<Ljava/lang/Object;Ljava/lang/Object;TCC;*>;C::Lscala/collection/mutable/MapOps<TK;TV;TCC;TC;>;>Ljava/lang/Object;Lscala/collection/MapOps<TK;TV;TCC;TC;>;Lscala/collection/mutable/Cloneable<TC;>;Lscala/collection/mutable/Builder<Lscala/Tuple2<TK;TV;>;TC;>;Lscala/collection/mutable/Shrinkable<TK;>;
    #4 = Utf8               java/lang/Object
    #5 = Class              #4            // java/lang/Object
    #6 = Utf8               scala/collection/MapOps
    #7 = Class              #6            // scala/collection/MapOps
    #8 = Utf8               scala/collection/mutable/Cloneable
    #9 = Class              #8            // scala/collection/mutable/Cloneable
   #10 = Utf8               scala/collection/mutable/Builder
   #11 = Class              #10           // scala/collection/mutable/Builder
   #12 = Utf8               scala/collection/mutable/Shrinkable
   #13 = Class              #12           // scala/collection/mutable/Shrinkable
   #14 = Utf8               Map.scala
   #15 = Utf8               Lscala/reflect/ScalaSignature;
   #16 = Utf8               bytes
   #17 = Utf8               \u0006\u0005\u0005\u001dfa\u0002\n\u0014!\u0003\r\tA\u0007\u0005\u00069\u0002!\t!\u0018\u0005\u0006C\u0002!\tA\u0019\u0005\u0006G\u0002!)\u0001\u001a\u0005\u0006G\u0002!)!\u001d\u0005\u0006}\u0002!\ta \u0005\b\u0003\u001b\u0001A\u0011AA\b\u0011\u001d\t)\u0002\u0001C\u0001\u0003/Aq!a\n\u0001\t\u0003\tI\u0003C\u0004\u00028\u0001!\t!!\u000f\t\r\u0005u\u0002\u0001\"\u0001^\u0011\u0019\ty\u0004\u0001C!E\"9\u0011\u0011\t\u0001\u0005\u0006\u0005\r\u0003bBA3\u0001\u0011\u0005\u0011q\r\u0005\b\u0003W\u0002AQAA7\u0011\u001d\ti\b\u0001C\u0001\u0003\u007fBq!a!\u0001\t\u0003\t)\tC\u0004\u0002\u001e\u0002!\t%a(\u0003\r5\u000b\u0007o\u00149t\u0015\t!R#A\u0004nkR\f\'\r\\3\u000b\u0005Y9\u0012AC2pY2,7\r^5p]*\t\u0001$A\u0003tG\u0006d\u0017m\u0001\u0001\u0016\u000bmI3g\u0010\u001e\u0014\u0011\u0001a\u0002E\u0014)T-f\u0003\"!\b\u0010\u000e\u0003]I!aH\f\u0003\r\u0005s\u0017PU3g!\u0015\t#\u0005J\u001b:\u001b\u0005)\u0012BA\u0012\u0016\u0005-IE/\u001a:bE2,w\n]:\u0011\tu)sEM\u0005\u0003M]\u0011a\u0001V;qY\u0016\u0014\u0004C\u0001\u0015*\u0019\u0001!QA\u000b\u0001C\u0002-\u0012\u0011aS\t\u0003Y=\u0002\"!H\u0017\n\u00059:\"a\u0002(pi\"Lgn\u001a\t\u0003;AJ!!M\f\u0003\u0007\u0005s\u0017\u0010\u0005\u0002)g\u0011)A\u0007\u0001b\u0001W\t\ta\u000b\u0005\u00027o5\t1#\u0003\u00029\'\tA\u0011\n^3sC\ndW\r\u0005\u0002)u\u001111\b\u0001CC\u0002q\u0012\u0011aQ\t\u0003Yu\u0002bA\u000e\u0001(eyJ\u0004C\u0001\u0015@\t\u0019\u0001\u0005\u0001\"b\u0001\u0003\n\u00111iQ\u000b\u0004\u0005\u001aK\u0015C\u0001\u0017Da\t!E\n\u0005\u00047\u0001\u0015Ceh\u0013\t\u0003Q\u0019#QaR C\u0002-\u0012\u0011\u0001\u0017\t\u0003Q%#QAS C\u0002-\u0012\u0011!\u0017\t\u0003Q1#\u0011\"T \u0002\u0002\u0003\u0005)\u0011A\u0016\u0003\u0007}#\u0013\u0007\u0005\u0004\"\u001f\u001e\u0012d(O\u0005\u0003%U\u00012AN):\u0013\t\u00116CA\u0005DY>tW-\u00192mKB!a\u0007\u0016\u0013:\u0013\t)6CA\u0004Ck&dG-\u001a:\u0011\u0007Y:F%\u0003\u0002Y\'\tAqI]8xC\ndW\rE\u000275\u001eJ!aW\n\u0003\u0015MC\'/\u001b8lC\ndW-\u0001\u0004%S:LG\u000f\n\u000b\u0002=B\u0011QdX\u0005\u0003A^\u0011A!\u00168ji\u00061!/Z:vYR$\u0012!O\u0001\u0007I5Lg.^:\u0015\u0005e*\u0007\"\u00024\u0004\u0001\u00049\u0013aA6fs\"21\u0001[6m]>\u0004\"!H5\n\u0005)<\"A\u00033faJ,7-\u0019;fI\u00069Q.Z:tC\u001e,\u0017%A7\u0002GU\u001bX\rI\u0017!_J\u0004#/Z7pm\u0016\u0004sN\u001c\u0011b]\u0002JW.\\;uC\ndW\rI\'ba\u0006)1/\u001b8dK\u0006\n\u0001/\u0001\u00043]E\u001ad\u0006\r\u000b\u0005sI$h\u000fC\u0003t\t\u0001\u0007q%\u0001\u0003lKf\f\u0004\"B;\u0005\u0001\u00049\u0013\u0001B6fsJBQa\u001e\u0003A\u0002a\fAa[3zgB\u0019Q$_\u0014\n\u0005i<\"A\u0003\u001fsKB,\u0017\r^3e}!2A\u0001[6}]>\f\u0013!`\u0001(+N,\u0007%L\u0017!_J\u0004#/Z7pm\u0016\fE\u000e\u001c\u0011p]\u0002\ng\u000eI5n[V$\u0018M\u00197fA5\u000b\u0007/A\u0002qkR$b!!\u0001\u0002\b\u0005%\u0001\u0003B\u000f\u0002\u0004IJ1!!\u0002\u0018\u0005\u0019y\u0005\u000f^5p]\")a-\u0002a\u0001O!1\u00111B\u0003A\u0002I\nQA^1mk\u0016\fa!\u001e9eCR,G#\u00020\u0002\u0012\u0005M\u0001\"\u00024\u0007\u0001\u00049\u0003BBA\u0006\r\u0001\u0007!\'\u0001\u0006va\u0012\fG/Z,ji\"$B!!\u0007\u0002&Q!\u0011\u0011AA\u000e\u0011\u001d\tib\u0002a\u0001\u0003?\t\u0011C]3nCB\u0004\u0018N\\4Gk:\u001cG/[8o!\u001di\u0012\u0011EA\u0001\u0003\u0003I1!a\t\u0018\u0005%1UO\\2uS>t\u0017\u0007C\u0003g\u000f\u0001\u0007q%A\bhKR|%/\u00127tKV\u0003H-\u0019;f)\u0015\u0011\u00141FA\u0017\u0011\u00151\u0007\u00021\u0001(\u0011!\ty\u0003\u0003CA\u0002\u0005E\u0012AA8q!\u0011i\u00121\u0007\u001a\n\u0007\u0005UrC\u0001\u0005=Eft\u0017-\\3?\u0003\u0019\u0011X-\\8wKR!\u0011\u0011AA\u001e\u0011\u00151\u0017\u00021\u0001(\u0003\u0015\u0019G.Z1s\u0003\u0015\u0019Gn\u001c8f\u0003\u0019\u0011X\r^1j]R!\u0011QIA$\u001b\u0005\u0001\u0001bBA%\u0019\u0001\u0007\u00111J\u0001\u0002aB9Q$!\u0014(e\u0005E\u0013bAA(/\tIa)\u001e8di&|gN\r\t\u0004;\u0005M\u0013bAA+/\t9!i\\8mK\u0006t\u0007f\u0001\u0007\u0002ZA\u0019Q$a\u0017\n\u0007\u0005usC\u0001\u0004j]2Lg.\u001a\u0015\b\u0019!\\\u0017\u0011\r8pC\t\t\u0019\'A\rVg\u0016\u0004c-\u001b7uKJLe\u000e\u00157bG\u0016\u0004\u0013N\\:uK\u0006$\u0017!\u00044jYR,\'/\u00138QY\u0006\u001cW\r\u0006\u0003\u0002F\u0005%\u0004bBA%\u001b\u0001\u0007\u00111J\u0001\niJ\fgn\u001d4pe6$B!!\u0012\u0002p!9\u0011\u0011\u000f\bA\u0002\u0005M\u0014!\u00014\u0011\ru\tie\n\u001a3Q\rq\u0011\u0011\f\u0015\b\u001d!\\\u0017\u0011\u00108pC\t\tY(\u0001\u000fVg\u0016\u0004S.\u00199WC2,Xm]%o!2\f7-\u001a\u0011j]N$X-\u00193\u0002!5\f\u0007OV1mk\u0016\u001c\u0018J\u001c)mC\u000e,G\u0003BA#\u0003\u0003Cq!!\u001d\u0010\u0001\u0004\t\u0019(A\u0004va\u0012\fG/\u001a3\u0016\t\u0005\u001d\u0015Q\u0012\u000b\u0007\u0003\u0013\u000b\u0019*!&\u0011\u000b!zt%a#\u0011\u0007!\ni\tB\u0004\u0002\u0010B\u0011\r!!%\u0003\u0005Y\u000b\u0014C\u0001\u001a0\u0011\u00151\u0007\u00031\u0001(\u0011\u001d\tY\u0001\u0005a\u0001\u0003\u0017Cs\u0001\u00055l\u00033sw.\t\u0002\u0002\u001c\u00061Tk]3![:\u001aGn\u001c8fQ%r\u0013\r\u001a3P]\u0016D\u0003f\u001b\u0017wS%\u0002\u0013N\\:uK\u0006$\u0007e\u001c4![:*\b\u000fZ1uK\u0012D3\u000e\f\u0011wS\u0005I1N\\8x]NK\'0Z\u000b\u0003\u0003C\u00032!HAR\u0013\r\t)k\u0006\u0002\u0004\u0013:$\b
   #18 = Utf8               java/lang/invoke/MethodHandles$Lookup
   #19 = Class              #18           // java/lang/invoke/MethodHandles$Lookup
   #20 = Utf8               java/lang/invoke/MethodHandles
   #21 = Class              #20           // java/lang/invoke/MethodHandles
   #22 = Utf8               Lookup
   #23 = Utf8               result$
   #24 = Utf8               (Lscala/collection/mutable/MapOps;)Lscala/collection/mutable/MapOps;
   #25 = Utf8               $this
   #26 = Utf8               result
   #27 = Utf8               ()Lscala/collection/mutable/MapOps;
   #28 = NameAndType        #26:#27       // result:()Lscala/collection/mutable/MapOps;
   #29 = InterfaceMethodref #2.#28        // scala/collection/mutable/MapOps.result:()Lscala/collection/mutable/MapOps;
   #30 = Utf8               Lscala/collection/mutable/MapOps;
   #31 = Utf8               ()TC;
   #32 = Utf8               coll
   #33 = Utf8               ()Ljava/lang/Object;
   #34 = NameAndType        #32:#33       // coll:()Ljava/lang/Object;
   #35 = InterfaceMethodref #2.#34        // scala/collection/mutable/MapOps.coll:()Ljava/lang/Object;
   #36 = Utf8               this
   #37 = Utf8               $minus$
   #38 = Utf8               (Lscala/collection/mutable/MapOps;Ljava/lang/Object;)Lscala/collection/mutable/MapOps;
   #39 = Utf8               key
   #40 = Utf8               $minus
   #41 = Utf8               (Ljava/lang/Object;)Lscala/collection/mutable/MapOps;
   #42 = NameAndType        #40:#41       // $minus:(Ljava/lang/Object;)Lscala/collection/mutable/MapOps;
   #43 = InterfaceMethodref #2.#42        // scala/collection/mutable/MapOps.$minus:(Ljava/lang/Object;)Lscala/collection/mutable/MapOps;
   #44 = Utf8               Ljava/lang/Object;
   #45 = Utf8               (TK;)TC;
   #46 = Utf8               clone
   #47 = NameAndType        #46:#27       // clone:()Lscala/collection/mutable/MapOps;
   #48 = InterfaceMethodref #2.#47        // scala/collection/mutable/MapOps.clone:()Lscala/collection/mutable/MapOps;
   #49 = Utf8               subtractOne
   #50 = Utf8               (Ljava/lang/Object;)Lscala/collection/mutable/Shrinkable;
   #51 = NameAndType        #49:#50       // subtractOne:(Ljava/lang/Object;)Lscala/collection/mutable/Shrinkable;
   #52 = InterfaceMethodref #13.#51       // scala/collection/mutable/Shrinkable.subtractOne:(Ljava/lang/Object;)Lscala/collection/mutable/Shrinkable;
   #53 = Utf8               (Lscala/collection/mutable/MapOps;Ljava/lang/Object;Ljava/lang/Object;Lscala/collection/immutable/Seq;)Lscala/collection/mutable/MapOps;
   #54 = Utf8               key1
   #55 = Utf8               key2
   #56 = Utf8               keys
   #57 = Utf8               (Ljava/lang/Object;Ljava/lang/Object;Lscala/collection/immutable/Seq;)Lscala/collection/mutable/MapOps;
   #58 = NameAndType        #40:#57       // $minus:(Ljava/lang/Object;Ljava/lang/Object;Lscala/collection/immutable/Seq;)Lscala/collection/mutable/MapOps;
   #59 = InterfaceMethodref #2.#58        // scala/collection/mutable/MapOps.$minus:(Ljava/lang/Object;Ljava/lang/Object;Lscala/collection/immutable/Seq;)Lscala/collection/mutable/MapOps;
   #60 = Utf8               Lscala/collection/immutable/Seq;
   #61 = Utf8               (TK;TK;Lscala/collection/immutable/Seq<TK;>;)TC;
   #62 = Utf8               subtractAll
   #63 = Utf8               (Lscala/collection/IterableOnce;)Lscala/collection/mutable/Shrinkable;
   #64 = NameAndType        #62:#63       // subtractAll:(Lscala/collection/IterableOnce;)Lscala/collection/mutable/Shrinkable;
   #65 = InterfaceMethodref #13.#64       // scala/collection/mutable/Shrinkable.subtractAll:(Lscala/collection/IterableOnce;)Lscala/collection/mutable/Shrinkable;
   #66 = Utf8               put$
   #67 = Utf8               (Lscala/collection/mutable/MapOps;Ljava/lang/Object;Ljava/lang/Object;)Lscala/Option;
   #68 = Utf8               value
   #69 = Utf8               put
   #70 = Utf8               (Ljava/lang/Object;Ljava/lang/Object;)Lscala/Option;
   #71 = NameAndType        #69:#70       // put:(Ljava/lang/Object;Ljava/lang/Object;)Lscala/Option;
   #72 = InterfaceMethodref #2.#71        // scala/collection/mutable/MapOps.put:(Ljava/lang/Object;Ljava/lang/Object;)Lscala/Option;
   #73 = Utf8               (TK;TV;)Lscala/Option<TV;>;
   #74 = Utf8               get
   #75 = Utf8               (Ljava/lang/Object;)Lscala/Option;
   #76 = NameAndType        #74:#75       // get:(Ljava/lang/Object;)Lscala/Option;
   #77 = InterfaceMethodref #2.#76        // scala/collection/mutable/MapOps.get:(Ljava/lang/Object;)Lscala/Option;
   #78 = Utf8               update
   #79 = Utf8               (Ljava/lang/Object;Ljava/lang/Object;)V
   #80 = NameAndType        #78:#79       // update:(Ljava/lang/Object;Ljava/lang/Object;)V
   #81 = InterfaceMethodref #2.#80        // scala/collection/mutable/MapOps.update:(Ljava/lang/Object;Ljava/lang/Object;)V
   #82 = Utf8               r
   #83 = Utf8               Lscala/Option;
   #84 = Utf8               update$
   #85 = Utf8               (Lscala/collection/mutable/MapOps;Ljava/lang/Object;Ljava/lang/Object;)V
   #86 = Utf8               (TK;TV;)V
   #87 = Utf8               scala/collection/mutable/Growable
   #88 = Class              #87           // scala/collection/mutable/Growable
   #89 = Utf8               scala/Tuple2
   #90 = Class              #89           // scala/Tuple2
   #91 = Utf8               <init>
   #92 = NameAndType        #91:#79       // "<init>":(Ljava/lang/Object;Ljava/lang/Object;)V
   #93 = Methodref          #90.#92       // scala/Tuple2."<init>":(Ljava/lang/Object;Ljava/lang/Object;)V
   #94 = Utf8               addOne
   #95 = Utf8               (Ljava/lang/Object;)Lscala/collection/mutable/Growable;
   #96 = NameAndType        #94:#95       // addOne:(Ljava/lang/Object;)Lscala/collection/mutable/Growable;
   #97 = InterfaceMethodref #88.#96       // scala/collection/mutable/Growable.addOne:(Ljava/lang/Object;)Lscala/collection/mutable/Growable;
   #98 = Utf8               $plus$eq_elem
   #99 = Utf8               updateWith$
  #100 = Utf8               (Lscala/collection/mutable/MapOps;Ljava/lang/Object;Lscala/Function1;)Lscala/Option;
  #101 = Utf8               remappingFunction
  #102 = Utf8               updateWith
  #103 = Utf8               (Ljava/lang/Object;Lscala/Function1;)Lscala/Option;
  #104 = NameAndType        #102:#103     // updateWith:(Ljava/lang/Object;Lscala/Function1;)Lscala/Option;
  #105 = InterfaceMethodref #2.#104       // scala/collection/mutable/MapOps.updateWith:(Ljava/lang/Object;Lscala/Function1;)Lscala/Option;
  #106 = Utf8               Lscala/Function1;
  #107 = Utf8               (TK;Lscala/Function1<Lscala/Option<TV;>;Lscala/Option<TV;>;>;)Lscala/Option<TV;>;
  #108 = Utf8               scala/Function1
  #109 = Class              #108          // scala/Function1
  #110 = Utf8               apply
  #111 = Utf8               (Ljava/lang/Object;)Ljava/lang/Object;
  #112 = NameAndType        #110:#111     // apply:(Ljava/lang/Object;)Ljava/lang/Object;
  #113 = InterfaceMethodref #109.#112     // scala/Function1.apply:(Ljava/lang/Object;)Ljava/lang/Object;
  #114 = Utf8               scala/Option
  #115 = Class              #114          // scala/Option
  #116 = Utf8               scala/None$
  #117 = Class              #116          // scala/None$
  #118 = Utf8               MODULE$
  #119 = Utf8               Lscala/None$;
  #120 = NameAndType        #118:#119     // MODULE$:Lscala/None$;
  #121 = Fieldref           #117.#120     // scala/None$.MODULE$:Lscala/None$;
  #122 = Utf8               equals
  #123 = Utf8               (Ljava/lang/Object;)Z
  #124 = NameAndType        #122:#123     // equals:(Ljava/lang/Object;)Z
  #125 = Methodref          #5.#124       // java/lang/Object.equals:(Ljava/lang/Object;)Z
  #126 = Utf8               scala/Some
  #127 = Class              #126          // scala/Some
  #128 = Utf8               remove
  #129 = NameAndType        #128:#75      // remove:(Ljava/lang/Object;)Lscala/Option;
  #130 = InterfaceMethodref #2.#129       // scala/collection/mutable/MapOps.remove:(Ljava/lang/Object;)Lscala/Option;
  #131 = NameAndType        #68:#33       // value:()Ljava/lang/Object;
  #132 = Methodref          #127.#131     // scala/Some.value:()Ljava/lang/Object;
  #133 = Utf8               scala/MatchError
  #134 = Class              #133          // scala/MatchError
  #135 = Utf8               (Ljava/lang/Object;)V
  #136 = NameAndType        #91:#135      // "<init>":(Ljava/lang/Object;)V
  #137 = Methodref          #134.#136     // scala/MatchError."<init>":(Ljava/lang/Object;)V
  #138 = Utf8               v
  #139 = Utf8               previousValue
  #140 = Utf8               nextValue
  #141 = Utf8               getOrElseUpdate$
  #142 = Utf8               (Lscala/collection/mutable/MapOps;Ljava/lang/Object;Lscala/Function0;)Ljava/lang/Object;
  #143 = Utf8               op
  #144 = Utf8               getOrElseUpdate
  #145 = Utf8               (Ljava/lang/Object;Lscala/Function0;)Ljava/lang/Object;
  #146 = NameAndType        #144:#145     // getOrElseUpdate:(Ljava/lang/Object;Lscala/Function0;)Ljava/lang/Object;
  #147 = InterfaceMethodref #2.#146       // scala/collection/mutable/MapOps.getOrElseUpdate:(Ljava/lang/Object;Lscala/Function0;)Ljava/lang/Object;
  #148 = Utf8               Lscala/Function0;
  #149 = Utf8               (TK;Lscala/Function0<TV;>;)TV;
  #150 = Utf8               scala/Function0
  #151 = Class              #150          // scala/Function0
  #152 = NameAndType        #110:#33      // apply:()Ljava/lang/Object;
  #153 = InterfaceMethodref #151.#152     // scala/Function0.apply:()Ljava/lang/Object;
  #154 = Utf8               d
  #155 = Utf8               remove$
  #156 = Utf8               (Lscala/collection/mutable/MapOps;Ljava/lang/Object;)Lscala/Option;
  #157 = Utf8               (TK;)Lscala/Option<TV;>;
  #158 = Utf8               isDefined
  #159 = Utf8               ()Z
  #160 = NameAndType        #158:#159     // isDefined:()Z
  #161 = Methodref          #115.#160     // scala/Option.isDefined:()Z
  #162 = Utf8               clear$
  #163 = Utf8               (Lscala/collection/mutable/MapOps;)V
  #164 = Utf8               clear
  #165 = Utf8               ()V
  #166 = NameAndType        #164:#165     // clear:()V
  #167 = InterfaceMethodref #2.#166       // scala/collection/mutable/MapOps.clear:()V
  #168 = Utf8               keysIterator
  #169 = Utf8               ()Lscala/collection/Iterator;
  #170 = NameAndType        #168:#169     // keysIterator:()Lscala/collection/Iterator;
  #171 = InterfaceMethodref #2.#170       // scala/collection/mutable/MapOps.keysIterator:()Lscala/collection/Iterator;
  #172 = MethodType         #111          //  (Ljava/lang/Object;)Ljava/lang/Object;
  #173 = Utf8               $anonfun$clear$1
  #174 = NameAndType        #173:#38      // $anonfun$clear$1:(Lscala/collection/mutable/MapOps;Ljava/lang/Object;)Lscala/collection/mutable/MapOps;
  #175 = InterfaceMethodref #2.#174       // scala/collection/mutable/MapOps.$anonfun$clear$1:(Lscala/collection/mutable/MapOps;Ljava/lang/Object;)Lscala/collection/mutable/MapOps;
  #176 = MethodHandle       6:#175        // REF_invokeStatic scala/collection/mutable/MapOps.$anonfun$clear$1:(Lscala/collection/mutable/MapOps;Ljava/lang/Object;)Lscala/collection/mutable/MapOps;
  #177 = MethodType         #41           //  (Ljava/lang/Object;)Lscala/collection/mutable/MapOps;
  #178 = Integer            5
  #179 = Integer            1
  #180 = Utf8               java/lang/invoke/LambdaMetafactory
  #181 = Class              #180          // java/lang/invoke/LambdaMetafactory
  #182 = Utf8               altMetafactory
  #183 = Utf8               (Ljava/lang/invoke/MethodHandles$Lookup;Ljava/lang/String;Ljava/lang/invoke/MethodType;[Ljava/lang/Object;)Ljava/lang/invoke/CallSite;
  #184 = NameAndType        #182:#183     // altMetafactory:(Ljava/lang/invoke/MethodHandles$Lookup;Ljava/lang/String;Ljava/lang/invoke/MethodType;[Ljava/lang/Object;)Ljava/lang/invoke/CallSite;
  #185 = Methodref          #181.#184     // java/lang/invoke/LambdaMetafactory.altMetafactory:(Ljava/lang/invoke/MethodHandles$Lookup;Ljava/lang/String;Ljava/lang/invoke/MethodType;[Ljava/lang/Object;)Ljava/lang/invoke/CallSite;
  #186 = MethodHandle       6:#185        // REF_invokeStatic java/lang/invoke/LambdaMetafactory.altMetafactory:(Ljava/lang/invoke/MethodHandles$Lookup;Ljava/lang/String;Ljava/lang/invoke/MethodType;[Ljava/lang/Object;)Ljava/lang/invoke/CallSite;
  #187 = Utf8               (Lscala/collection/mutable/MapOps;)Lscala/Function1;
  #188 = NameAndType        #110:#187     // apply:(Lscala/collection/mutable/MapOps;)Lscala/Function1;
  #189 = InvokeDynamic      #0:#188       // #0:apply:(Lscala/collection/mutable/MapOps;)Lscala/Function1;
  #190 = Utf8               scala/collection/Iterator
  #191 = Class              #190          // scala/collection/Iterator
  #192 = Utf8               foreach
  #193 = Utf8               (Lscala/Function1;)V
  #194 = NameAndType        #192:#193     // foreach:(Lscala/Function1;)V
  #195 = InterfaceMethodref #191.#194     // scala/collection/Iterator.foreach:(Lscala/Function1;)V
  #196 = Utf8               clone$
  #197 = Utf8               empty
  #198 = NameAndType        #197:#33      // empty:()Ljava/lang/Object;
  #199 = InterfaceMethodref #2.#198       // scala/collection/mutable/MapOps.empty:()Ljava/lang/Object;
  #200 = Utf8               addAll
  #201 = Utf8               (Lscala/collection/IterableOnce;)Lscala/collection/mutable/Growable;
  #202 = NameAndType        #200:#201     // addAll:(Lscala/collection/IterableOnce;)Lscala/collection/mutable/Growable;
  #203 = InterfaceMethodref #88.#202      // scala/collection/mutable/Growable.addAll:(Lscala/collection/IterableOnce;)Lscala/collection/mutable/Growable;
  #204 = Utf8               retain$
  #205 = Utf8               (Lscala/collection/mutable/MapOps;Lscala/Function2;)Lscala/collection/mutable/MapOps;
  #206 = Utf8               p
  #207 = Utf8               retain
  #208 = Utf8               (Lscala/Function2;)Lscala/collection/mutable/MapOps;
  #209 = NameAndType        #207:#208     // retain:(Lscala/Function2;)Lscala/collection/mutable/MapOps;
  #210 = InterfaceMethodref #2.#209       // scala/collection/mutable/MapOps.retain:(Lscala/Function2;)Lscala/collection/mutable/MapOps;
  #211 = Utf8               Lscala/Function2;
  #212 = Utf8               (Lscala/Function2<TK;TV;Ljava/lang/Object;>;)Lscala/collection/mutable/MapOps<TK;TV;TCC;TC;>;
  #213 = Utf8               filterInPlace
  #214 = NameAndType        #213:#208     // filterInPlace:(Lscala/Function2;)Lscala/collection/mutable/MapOps;
  #215 = InterfaceMethodref #2.#214       // scala/collection/mutable/MapOps.filterInPlace:(Lscala/Function2;)Lscala/collection/mutable/MapOps;
  #216 = Utf8               filterInPlace$
  #217 = Utf8               isEmpty
  #218 = NameAndType        #217:#159     // isEmpty:()Z
  #219 = InterfaceMethodref #2.#218       // scala/collection/mutable/MapOps.isEmpty:()Z
  #220 = Utf8               scala/collection/concurrent/Map
  #221 = Class              #220          // scala/collection/concurrent/Map
  #222 = Utf8               filterInPlaceImpl
  #223 = Utf8               (Lscala/Function2;)Lscala/collection/concurrent/Map;
  #224 = NameAndType        #222:#223     // filterInPlaceImpl:(Lscala/Function2;)Lscala/collection/concurrent/Map;
  #225 = InterfaceMethodref #221.#224     // scala/collection/concurrent/Map.filterInPlaceImpl:(Lscala/Function2;)Lscala/collection/concurrent/Map;
  #226 = Utf8               scala/reflect/ClassTag$
  #227 = Class              #226          // scala/reflect/ClassTag$
  #228 = Utf8               Lscala/reflect/ClassTag$;
  #229 = NameAndType        #118:#228     // MODULE$:Lscala/reflect/ClassTag$;
  #230 = Fieldref           #227.#229     // scala/reflect/ClassTag$.MODULE$:Lscala/reflect/ClassTag$;
  #231 = Utf8               Any
  #232 = Utf8               ()Lscala/reflect/ClassTag;
  #233 = NameAndType        #231:#232     // Any:()Lscala/reflect/ClassTag;
  #234 = Methodref          #227.#233     // scala/reflect/ClassTag$.Any:()Lscala/reflect/ClassTag;
  #235 = Utf8               toArray
  #236 = Utf8               (Lscala/reflect/ClassTag;)Ljava/lang/Object;
  #237 = NameAndType        #235:#236     // toArray:(Lscala/reflect/ClassTag;)Ljava/lang/Object;
  #238 = InterfaceMethodref #2.#237       // scala/collection/mutable/MapOps.toArray:(Lscala/reflect/ClassTag;)Ljava/lang/Object;
  #239 = Utf8               [Ljava/lang/Object;
  #240 = Class              #239          // "[Ljava/lang/Object;"
  #241 = Utf8               _1
  #242 = NameAndType        #241:#33      // _1:()Ljava/lang/Object;
  #243 = Methodref          #90.#242      // scala/Tuple2._1:()Ljava/lang/Object;
  #244 = Utf8               _2
  #245 = NameAndType        #244:#33      // _2:()Ljava/lang/Object;
  #246 = Methodref          #90.#245      // scala/Tuple2._2:()Ljava/lang/Object;
  #247 = Utf8               scala/Function2
  #248 = Class              #247          // scala/Function2
  #249 = Utf8               (Ljava/lang/Object;Ljava/lang/Object;)Ljava/lang/Object;
  #250 = NameAndType        #110:#249     // apply:(Ljava/lang/Object;Ljava/lang/Object;)Ljava/lang/Object;
  #251 = InterfaceMethodref #248.#250     // scala/Function2.apply:(Ljava/lang/Object;Ljava/lang/Object;)Ljava/lang/Object;
  #252 = Utf8               scala/runtime/BoxesRunTime
  #253 = Class              #252          // scala/runtime/BoxesRunTime
  #254 = Utf8               unboxToBoolean
  #255 = NameAndType        #254:#123     // unboxToBoolean:(Ljava/lang/Object;)Z
  #256 = Methodref          #253.#255     // scala/runtime/BoxesRunTime.unboxToBoolean:(Ljava/lang/Object;)Z
  #257 = Utf8               k
  #258 = Utf8               array
  #259 = Utf8               arrayLength
  #260 = Utf8               I
  #261 = Utf8               i
  #262 = Utf8               transform$
  #263 = Utf8               f
  #264 = Utf8               transform
  #265 = NameAndType        #264:#208     // transform:(Lscala/Function2;)Lscala/collection/mutable/MapOps;
  #266 = InterfaceMethodref #2.#265       // scala/collection/mutable/MapOps.transform:(Lscala/Function2;)Lscala/collection/mutable/MapOps;
  #267 = Utf8               (Lscala/Function2<TK;TV;TV;>;)Lscala/collection/mutable/MapOps<TK;TV;TCC;TC;>;
  #268 = Utf8               mapValuesInPlace
  #269 = NameAndType        #268:#208     // mapValuesInPlace:(Lscala/Function2;)Lscala/collection/mutable/MapOps;
  #270 = InterfaceMethodref #2.#269       // scala/collection/mutable/MapOps.mapValuesInPlace:(Lscala/Function2;)Lscala/collection/mutable/MapOps;
  #271 = Utf8               mapValuesInPlace$
  #272 = Utf8               scala/collection/mutable/HashMap
  #273 = Class              #272          // scala/collection/mutable/HashMap
  #274 = Utf8               mapValuesInPlaceImpl
  #275 = Utf8               (Lscala/Function2;)Lscala/collection/mutable/HashMap;
  #276 = NameAndType        #274:#275     // mapValuesInPlaceImpl:(Lscala/Function2;)Lscala/collection/mutable/HashMap;
  #277 = Methodref          #273.#276     // scala/collection/mutable/HashMap.mapValuesInPlaceImpl:(Lscala/Function2;)Lscala/collection/mutable/HashMap;
  #278 = NameAndType        #274:#223     // mapValuesInPlaceImpl:(Lscala/Function2;)Lscala/collection/concurrent/Map;
  #279 = InterfaceMethodref #221.#278     // scala/collection/concurrent/Map.mapValuesInPlaceImpl:(Lscala/Function2;)Lscala/collection/concurrent/Map;
  #280 = Utf8               updated$
  #281 = Utf8               (Lscala/collection/mutable/MapOps;Ljava/lang/Object;Ljava/lang/Object;)Lscala/collection/mutable/MapOps;
  #282 = Utf8               updated
  #283 = Utf8               (Ljava/lang/Object;Ljava/lang/Object;)Lscala/collection/mutable/MapOps;
  #284 = NameAndType        #282:#283     // updated:(Ljava/lang/Object;Ljava/lang/Object;)Lscala/collection/mutable/MapOps;
  #285 = InterfaceMethodref #2.#284       // scala/collection/mutable/MapOps.updated:(Ljava/lang/Object;Ljava/lang/Object;)Lscala/collection/mutable/MapOps;
  #286 = Utf8               <V1:Ljava/lang/Object;>(TK;TV1;)TCC;
  #287 = InterfaceMethodref #2.#96        // scala/collection/mutable/MapOps.addOne:(Ljava/lang/Object;)Lscala/collection/mutable/Growable;
  #288 = Utf8               knownSize$
  #289 = Utf8               (Lscala/collection/mutable/MapOps;)I
  #290 = Utf8               knownSize
  #291 = Utf8               ()I
  #292 = NameAndType        #290:#291     // knownSize:()I
  #293 = InterfaceMethodref #2.#292       // scala/collection/mutable/MapOps.knownSize:()I
  #294 = Utf8               elem
  #295 = Utf8               $minus$eq
  #296 = NameAndType        #295:#50      // $minus$eq:(Ljava/lang/Object;)Lscala/collection/mutable/Shrinkable;
  #297 = InterfaceMethodref #2.#296       // scala/collection/mutable/MapOps.$minus$eq:(Ljava/lang/Object;)Lscala/collection/mutable/Shrinkable;
  #298 = Utf8               $init$
  #299 = Utf8               $deserializeLambda$
  #300 = Utf8               (Ljava/lang/invoke/SerializedLambda;)Ljava/lang/Object;
  #301 = Utf8               scala/runtime/LambdaDeserialize
  #302 = Class              #301          // scala/runtime/LambdaDeserialize
  #303 = Utf8               bootstrap
  #304 = Utf8               (Ljava/lang/invoke/MethodHandles$Lookup;Ljava/lang/String;Ljava/lang/invoke/MethodType;[Ljava/lang/invoke/MethodHandle;)Ljava/lang/invoke/CallSite;
  #305 = NameAndType        #303:#304     // bootstrap:(Ljava/lang/invoke/MethodHandles$Lookup;Ljava/lang/String;Ljava/lang/invoke/MethodType;[Ljava/lang/invoke/MethodHandle;)Ljava/lang/invoke/CallSite;
  #306 = Methodref          #302.#305     // scala/runtime/LambdaDeserialize.bootstrap:(Ljava/lang/invoke/MethodHandles$Lookup;Ljava/lang/String;Ljava/lang/invoke/MethodType;[Ljava/lang/invoke/MethodHandle;)Ljava/lang/invoke/CallSite;
  #307 = MethodHandle       6:#306        // REF_invokeStatic scala/runtime/LambdaDeserialize.bootstrap:(Ljava/lang/invoke/MethodHandles$Lookup;Ljava/lang/String;Ljava/lang/invoke/MethodType;[Ljava/lang/invoke/MethodHandle;)Ljava/lang/invoke/CallSite;
  #308 = Utf8               lambdaDeserialize
  #309 = NameAndType        #308:#300     // lambdaDeserialize:(Ljava/lang/invoke/SerializedLambda;)Ljava/lang/Object;
  #310 = InvokeDynamic      #1:#309       // #1:lambdaDeserialize:(Ljava/lang/invoke/SerializedLambda;)Ljava/lang/Object;
  #311 = Utf8               Code
  #312 = Utf8               LineNumberTable
  #313 = Utf8               LocalVariableTable
  #314 = Utf8               MethodParameters
  #315 = Utf8               Signature
  #316 = Utf8               StackMapTable
  #317 = Utf8               Deprecated
  #318 = Utf8               InnerClasses
  #319 = Utf8               SourceFile
  #320 = Utf8               RuntimeVisibleAnnotations
  #321 = Utf8               BootstrapMethods
  #322 = Utf8               ScalaInlineInfo
  #323 = Utf8               ScalaSig
{
  public static scala.collection.mutable.MapOps result$(scala.collection.mutable.MapOps);
    descriptor: (Lscala/collection/mutable/MapOps;)Lscala/collection/mutable/MapOps;
    flags: (0x1009) ACC_PUBLIC, ACC_STATIC, ACC_SYNTHETIC
    Code:
      stack=1, locals=1, args_size=1
         0: aload_0
         1: invokespecial #29                 // InterfaceMethod result:()Lscala/collection/mutable/MapOps;
         4: areturn
      LineNumberTable:
        line 73: 0
      LocalVariableTable:
        Start  Length  Slot  Name   Signature
            0       5     0 $this   Lscala/collection/mutable/MapOps;
    MethodParameters:
      Name                           Flags
      $this                          final synthetic

  public default C result();
    descriptor: ()Lscala/collection/mutable/MapOps;
    flags: (0x0001) ACC_PUBLIC
    Code:
      stack=1, locals=1, args_size=1
         0: aload_0
         1: invokeinterface #35,  1           // InterfaceMethod coll:()Ljava/lang/Object;
         6: checkcast     #2                  // class scala/collection/mutable/MapOps
         9: areturn
      LineNumberTable:
        line 73: 0
      LocalVariableTable:
        Start  Length  Slot  Name   Signature
            0      10     0  this   Lscala/collection/mutable/MapOps;
    Signature: #31                          // ()TC;

  public static scala.collection.mutable.MapOps $minus$(scala.collection.mutable.MapOps, java.lang.Object);
    descriptor: (Lscala/collection/mutable/MapOps;Ljava/lang/Object;)Lscala/collection/mutable/MapOps;
    flags: (0x1009) ACC_PUBLIC, ACC_STATIC, ACC_SYNTHETIC
    Code:
      stack=2, locals=2, args_size=2
         0: aload_0
         1: aload_1
         2: invokespecial #43                 // InterfaceMethod $minus:(Ljava/lang/Object;)Lscala/collection/mutable/MapOps;
         5: areturn
      LineNumberTable:
        line 76: 0
      LocalVariableTable:
        Start  Length  Slot  Name   Signature
            0       6     0 $this   Lscala/collection/mutable/MapOps;
            0       6     1   key   Ljava/lang/Object;
    MethodParameters:
      Name                           Flags
      $this                          final synthetic
      key                            final

  public default C $minus(K);
    descriptor: (Ljava/lang/Object;)Lscala/collection/mutable/MapOps;
    flags: (0x0001) ACC_PUBLIC
    Code:
      stack=2, locals=2, args_size=2
         0: aload_0
         1: invokeinterface #48,  1           // InterfaceMethod clone:()Lscala/collection/mutable/MapOps;
         6: dup
         7: ifnonnull     12
        10: aconst_null
        11: athrow
        12: aload_1
        13: invokeinterface #52,  2           // InterfaceMethod scala/collection/mutable/Shrinkable.subtractOne:(Ljava/lang/Object;)Lscala/collection/mutable/Shrinkable;
        18: checkcast     #2                  // class scala/collection/mutable/MapOps
        21: areturn
      StackMapTable: number_of_entries = 1
        frame_type = 76 /* same_locals_1_stack_item */
          stack = [ class scala/collection/mutable/MapOps ]
      LineNumberTable:
        line 76: 0
      LocalVariableTable:
        Start  Length  Slot  Name   Signature
            0      22     0  this   Lscala/collection/mutable/MapOps;
            0      22     1   key   Ljava/lang/Object;
    Signature: #45                          // (TK;)TC;
    Deprecated: true
    MethodParameters:
      Name                           Flags
      key                            final

  public static scala.collection.mutable.MapOps $minus$(scala.collection.mutable.MapOps, java.lang.Object, java.lang.Object, scala.collection.immutable.Seq);
    descriptor: (Lscala/collection/mutable/MapOps;Ljava/lang/Object;Ljava/lang/Object;Lscala/collection/immutable/Seq;)Lscala/collection/mutable/MapOps;
    flags: (0x1009) ACC_PUBLIC, ACC_STATIC, ACC_SYNTHETIC
    Code:
      stack=4, locals=4, args_size=4
         0: aload_0
         1: aload_1
         2: aload_2
         3: aload_3
         4: invokespecial #59                 // InterfaceMethod $minus:(Ljava/lang/Object;Ljava/lang/Object;Lscala/collection/immutable/Seq;)Lscala/collection/mutable/MapOps;
         7: areturn
      LineNumberTable:
        line 79: 0
      LocalVariableTable:
        Start  Length  Slot  Name   Signature
            0       8     0 $this   Lscala/collection/mutable/MapOps;
            0       8     1  key1   Ljava/lang/Object;
            0       8     2  key2   Ljava/lang/Object;
            0       8     3  keys   Lscala/collection/immutable/Seq;
    MethodParameters:
      Name                           Flags
      $this                          final synthetic
      key1                           final
      key2                           final
      keys                           final

  public default C $minus(K, K, scala.collection.immutable.Seq<K>);
    descriptor: (Ljava/lang/Object;Ljava/lang/Object;Lscala/collection/immutable/Seq;)Lscala/collection/mutable/MapOps;
    flags: (0x0001) ACC_PUBLIC
    Code:
      stack=2, locals=4, args_size=4
         0: aload_0
         1: invokeinterface #48,  1           // InterfaceMethod clone:()Lscala/collection/mutable/MapOps;
         6: dup
         7: ifnonnull     12
        10: aconst_null
        11: athrow
        12: aload_1
        13: invokeinterface #52,  2           // InterfaceMethod scala/collection/mutable/Shrinkable.subtractOne:(Ljava/lang/Object;)Lscala/collection/mutable/Shrinkable;
        18: dup
        19: ifnonnull     24
        22: aconst_null
        23: athrow
        24: aload_2
        25: invokeinterface #52,  2           // InterfaceMethod scala/collection/mutable/Shrinkable.subtractOne:(Ljava/lang/Object;)Lscala/collection/mutable/Shrinkable;
        30: dup
        31: ifnonnull     36
        34: aconst_null
        35: athrow
        36: aload_3
        37: invokeinterface #65,  2           // InterfaceMethod scala/collection/mutable/Shrinkable.subtractAll:(Lscala/collection/IterableOnce;)Lscala/collection/mutable/Shrinkable;
        42: checkcast     #2                  // class scala/collection/mutable/MapOps
        45: areturn
      StackMapTable: number_of_entries = 3
        frame_type = 76 /* same_locals_1_stack_item */
          stack = [ class scala/collection/mutable/MapOps ]
        frame_type = 75 /* same_locals_1_stack_item */
          stack = [ class scala/collection/mutable/Shrinkable ]
        frame_type = 75 /* same_locals_1_stack_item */
          stack = [ class scala/collection/mutable/Shrinkable ]
      LineNumberTable:
        line 79: 0
      LocalVariableTable:
        Start  Length  Slot  Name   Signature
            0      46     0  this   Lscala/collection/mutable/MapOps;
            0      46     1  key1   Ljava/lang/Object;
            0      46     2  key2   Ljava/lang/Object;
            0      46     3  keys   Lscala/collection/immutable/Seq;
    Signature: #61                          // (TK;TK;Lscala/collection/immutable/Seq<TK;>;)TC;
    Deprecated: true
    MethodParameters:
      Name                           Flags
      key1                           final
      key2                           final
      keys                           final

  public static scala.Option put$(scala.collection.mutable.MapOps, java.lang.Object, java.lang.Object);
    descriptor: (Lscala/collection/mutable/MapOps;Ljava/lang/Object;Ljava/lang/Object;)Lscala/Option;
    flags: (0x1009) ACC_PUBLIC, ACC_STATIC, ACC_SYNTHETIC
    Code:
      stack=3, locals=3, args_size=3
         0: aload_0
         1: aload_1
         2: aload_2
         3: invokespecial #72                 // InterfaceMethod put:(Ljava/lang/Object;Ljava/lang/Object;)Lscala/Option;
         6: areturn
      LineNumberTable:
        line 91: 0
      LocalVariableTable:
        Start  Length  Slot  Name   Signature
            0       7     0 $this   Lscala/collection/mutable/MapOps;
            0       7     1   key   Ljava/lang/Object;
            0       7     2 value   Ljava/lang/Object;
    MethodParameters:
      Name                           Flags
      $this                          final synthetic
      key                            final
      value                          final

  public default scala.Option<V> put(K, V);
    descriptor: (Ljava/lang/Object;Ljava/lang/Object;)Lscala/Option;
    flags: (0x0001) ACC_PUBLIC
    Code:
      stack=3, locals=4, args_size=3
         0: aload_0
         1: aload_1
         2: invokeinterface #77,  2           // InterfaceMethod get:(Ljava/lang/Object;)Lscala/Option;
         7: astore_3
         8: aload_0
         9: aload_1
        10: aload_2
        11: invokeinterface #81,  3           // InterfaceMethod update:(Ljava/lang/Object;Ljava/lang/Object;)V
        16: aload_3
        17: areturn
      LineNumberTable:
        line 92: 0
        line 93: 8
        line 94: 16
      LocalVariableTable:
        Start  Length  Slot  Name   Signature
            8       9     3     r   Lscala/Option;
            0      18     0  this   Lscala/collection/mutable/MapOps;
            0      18     1   key   Ljava/lang/Object;
            0      18     2 value   Ljava/lang/Object;
    Signature: #73                          // (TK;TV;)Lscala/Option<TV;>;
    MethodParameters:
      Name                           Flags
      key                            final
      value                          final

  public static void update$(scala.collection.mutable.MapOps, java.lang.Object, java.lang.Object);
    descriptor: (Lscala/collection/mutable/MapOps;Ljava/lang/Object;Ljava/lang/Object;)V
    flags: (0x1009) ACC_PUBLIC, ACC_STATIC, ACC_SYNTHETIC
    Code:
      stack=3, locals=3, args_size=3
         0: aload_0
         1: aload_1
         2: aload_2
         3: invokespecial #81                 // InterfaceMethod update:(Ljava/lang/Object;Ljava/lang/Object;)V
         6: return
      LineNumberTable:
        line 104: 0
      LocalVariableTable:
        Start  Length  Slot  Name   Signature
            0       7     0 $this   Lscala/collection/mutable/MapOps;
            0       7     1   key   Ljava/lang/Object;
            0       7     2 value   Ljava/lang/Object;
    MethodParameters:
      Name                           Flags
      $this                          final synthetic
      key                            final
      value                          final

  public default void update(K, V);
    descriptor: (Ljava/lang/Object;Ljava/lang/Object;)V
    flags: (0x0001) ACC_PUBLIC
    Code:
      stack=5, locals=4, args_size=3
         0: aload_0
         1: invokeinterface #35,  1           // InterfaceMethod coll:()Ljava/lang/Object;
         6: checkcast     #88                 // class scala/collection/mutable/Growable
         9: new           #90                 // class scala/Tuple2
        12: dup
        13: aload_1
        14: aload_2
        15: invokespecial #93                 // Method scala/Tuple2."<init>":(Ljava/lang/Object;Ljava/lang/Object;)V
        18: astore_3
        19: dup
        20: ifnonnull     25
        23: aconst_null
        24: athrow
        25: aload_3
        26: invokeinterface #97,  2           // InterfaceMethod scala/collection/mutable/Growable.addOne:(Ljava/lang/Object;)Lscala/collection/mutable/Growable;
        31: pop
        32: return
      StackMapTable: number_of_entries = 1
        frame_type = 255 /* full_frame */
          offset_delta = 25
          locals = [ class scala/collection/mutable/MapOps, class java/lang/Object, class java/lang/Object, class scala/Tuple2 ]
          stack = [ class scala/collection/mutable/Growable ]
      LineNumberTable:
        line 104: 0
      LocalVariableTable:
        Start  Length  Slot  Name   Signature
            0      33     0  this   Lscala/collection/mutable/MapOps;
            0      33     1   key   Ljava/lang/Object;
            0      33     2 value   Ljava/lang/Object;
           25       7     3 $plus$eq_elem   Ljava/lang/Object;
    Signature: #86                          // (TK;TV;)V
    MethodParameters:
      Name                           Flags
      key                            final
      value                          final

  public static scala.Option updateWith$(scala.collection.mutable.MapOps, java.lang.Object, scala.Function1);
    descriptor: (Lscala/collection/mutable/MapOps;Ljava/lang/Object;Lscala/Function1;)Lscala/Option;
    flags: (0x1009) ACC_PUBLIC, ACC_STATIC, ACC_SYNTHETIC
    Code:
      stack=3, locals=3, args_size=3
         0: aload_0
         1: aload_1
         2: aload_2
         3: invokespecial #105                // InterfaceMethod updateWith:(Ljava/lang/Object;Lscala/Function1;)Lscala/Option;
         6: areturn
      LineNumberTable:
        line 118: 0
      LocalVariableTable:
        Start  Length  Slot  Name   Signature
            0       7     0 $this   Lscala/collection/mutable/MapOps;
            0       7     1   key   Ljava/lang/Object;
            0       7     2 remappingFunction   Lscala/Function1;
    MethodParameters:
      Name                           Flags
      $this                          final synthetic
      key                            final
      remappingFunction              final

  public default scala.Option<V> updateWith(K, scala.Function1<scala.Option<V>, scala.Option<V>>);
    descriptor: (Ljava/lang/Object;Lscala/Function1;)Lscala/Option;
    flags: (0x0001) ACC_PUBLIC
    Code:
      stack=4, locals=7, args_size=3
         0: aload_0
         1: aload_1
         2: invokeinterface #77,  2           // InterfaceMethod get:(Ljava/lang/Object;)Lscala/Option;
         7: astore_3
         8: aload_2
         9: aload_3
        10: invokeinterface #113,  2          // InterfaceMethod scala/Function1.apply:(Ljava/lang/Object;)Ljava/lang/Object;
        15: checkcast     #115                // class scala/Option
        18: astore        4
        20: new           #90                 // class scala/Tuple2
        23: dup
        24: aload_3
        25: aload         4
        27: invokespecial #93                 // Method scala/Tuple2."<init>":(Ljava/lang/Object;Ljava/lang/Object;)V
        30: astore        5
        32: getstatic     #121                // Field scala/None$.MODULE$:Lscala/None$;
        35: aload_3
        36: invokevirtual #125                // Method java/lang/Object.equals:(Ljava/lang/Object;)Z
        39: ifeq          53
        42: getstatic     #121                // Field scala/None$.MODULE$:Lscala/None$;
        45: aload         4
        47: invokevirtual #125                // Method java/lang/Object.equals:(Ljava/lang/Object;)Z
        50: ifne          122
        53: aload_3
        54: instanceof    #127                // class scala/Some
        57: ifeq          82
        60: getstatic     #121                // Field scala/None$.MODULE$:Lscala/None$;
        63: aload         4
        65: invokevirtual #125                // Method java/lang/Object.equals:(Ljava/lang/Object;)Z
        68: ifeq          82
        71: aload_0
        72: aload_1
        73: invokeinterface #130,  2          // InterfaceMethod remove:(Ljava/lang/Object;)Lscala/Option;
        78: pop
        79: goto          122
        82: aload         4
        84: instanceof    #127                // class scala/Some
        87: ifeq          112
        90: aload         4
        92: checkcast     #127                // class scala/Some
        95: invokevirtual #132                // Method scala/Some.value:()Ljava/lang/Object;
        98: astore        6
       100: aload_0
       101: aload_1
       102: aload         6
       104: invokeinterface #81,  3           // InterfaceMethod update:(Ljava/lang/Object;Ljava/lang/Object;)V
       109: goto          122
       112: new           #134                // class scala/MatchError
       115: dup
       116: aload         5
       118: invokespecial #137                // Method scala/MatchError."<init>":(Ljava/lang/Object;)V
       121: athrow
       122: aload         4
       124: areturn
      StackMapTable: number_of_entries = 4
        frame_type = 254 /* append */
          offset_delta = 53
          locals = [ class scala/Option, class scala/Option, class scala/Tuple2 ]
        frame_type = 28 /* same */
        frame_type = 29 /* same */
        frame_type = 9 /* same */
      LineNumberTable:
        line 119: 0
        line 120: 8
        line 121: 20
        line 122: 32
        line 123: 53
        line 124: 82
        line 121: 112
        line 126: 122
      LocalVariableTable:
        Start  Length  Slot  Name   Signature
          100      12     6     v   Ljava/lang/Object;
            8     116     3 previousValue   Lscala/Option;
           20     104     4 nextValue   Lscala/Option;
            0     125     0  this   Lscala/collection/mutable/MapOps;
            0     125     1   key   Ljava/lang/Object;
            0     125     2 remappingFunction   Lscala/Function1;
    Signature: #107                         // (TK;Lscala/Function1<Lscala/Option<TV;>;Lscala/Option<TV;>;>;)Lscala/Option<TV;>;
    MethodParameters:
      Name                           Flags
      key                            final
      remappingFunction              final

  public static java.lang.Object getOrElseUpdate$(scala.collection.mutable.MapOps, java.lang.Object, scala.Function0);
    descriptor: (Lscala/collection/mutable/MapOps;Ljava/lang/Object;Lscala/Function0;)Ljava/lang/Object;
    flags: (0x1009) ACC_PUBLIC, ACC_STATIC, ACC_SYNTHETIC
    Code:
      stack=3, locals=3, args_size=3
         0: aload_0
         1: aload_1
         2: aload_2
         3: invokespecial #147                // InterfaceMethod getOrElseUpdate:(Ljava/lang/Object;Lscala/Function0;)Ljava/lang/Object;
         6: areturn
      LineNumberTable:
        line 143: 0
      LocalVariableTable:
        Start  Length  Slot  Name   Signature
            0       7     0 $this   Lscala/collection/mutable/MapOps;
            0       7     1   key   Ljava/lang/Object;
            0       7     2    op   Lscala/Function0;
    MethodParameters:
      Name                           Flags
      $this                          final synthetic
      key                            final
      op                             final

  public default V getOrElseUpdate(K, scala.Function0<V>);
    descriptor: (Ljava/lang/Object;Lscala/Function0;)Ljava/lang/Object;
    flags: (0x0001) ACC_PUBLIC
    Code:
      stack=3, locals=6, args_size=3
         0: aload_0
         1: aload_1
         2: invokeinterface #77,  2           // InterfaceMethod get:(Ljava/lang/Object;)Lscala/Option;
         7: astore        4
         9: aload         4
        11: instanceof    #127                // class scala/Some
        14: ifeq          29
        17: aload         4
        19: checkcast     #127                // class scala/Some
        22: invokevirtual #132                // Method scala/Some.value:()Ljava/lang/Object;
        25: astore_3
        26: goto          73
        29: getstatic     #121                // Field scala/None$.MODULE$:Lscala/None$;
        32: aload         4
        34: invokevirtual #125                // Method java/lang/Object.equals:(Ljava/lang/Object;)Z
        37: ifeq          63
        40: aload_2
        41: invokeinterface #153,  1          // InterfaceMethod scala/Function0.apply:()Ljava/lang/Object;
        46: astore        5
        48: aload_0
        49: aload_1
        50: aload         5
        52: invokeinterface #81,  3           // InterfaceMethod update:(Ljava/lang/Object;Ljava/lang/Object;)V
        57: aload         5
        59: astore_3
        60: goto          73
        63: new           #134                // class scala/MatchError
        66: dup
        67: aload         4
        69: invokespecial #137                // Method scala/MatchError."<init>":(Ljava/lang/Object;)V
        72: athrow
        73: aload_3
        74: areturn
      StackMapTable: number_of_entries = 3
        frame_type = 253 /* append */
          offset_delta = 29
          locals = [ top, class scala/Option ]
        frame_type = 33 /* same */
        frame_type = 255 /* full_frame */
          offset_delta = 9
          locals = [ class scala/collection/mutable/MapOps, class java/lang/Object, class scala/Function0, class java/lang/Object, class scala/Option ]
          stack = []
      LineNumberTable:
        line 144: 0
        line 145: 9
        line 146: 29
        line 144: 63
      LocalVariableTable:
        Start  Length  Slot  Name   Signature
           48      11     5     d   Ljava/lang/Object;
            0      75     0  this   Lscala/collection/mutable/MapOps;
            0      75     1   key   Ljava/lang/Object;
            0      75     2    op   Lscala/Function0;
    Signature: #149                         // (TK;Lscala/Function0<TV;>;)TV;
    MethodParameters:
      Name                           Flags
      key                            final
      op                             final

  public static scala.Option remove$(scala.collection.mutable.MapOps, java.lang.Object);
    descriptor: (Lscala/collection/mutable/MapOps;Ljava/lang/Object;)Lscala/Option;
    flags: (0x1009) ACC_PUBLIC, ACC_STATIC, ACC_SYNTHETIC
    Code:
      stack=2, locals=2, args_size=2
         0: aload_0
         1: aload_1
         2: invokespecial #130                // InterfaceMethod remove:(Ljava/lang/Object;)Lscala/Option;
         5: areturn
      LineNumberTable:
        line 155: 0
      LocalVariableTable:
        Start  Length  Slot  Name   Signature
            0       6     0 $this   Lscala/collection/mutable/MapOps;
            0       6     1   key   Ljava/lang/Object;
    MethodParameters:
      Name                           Flags
      $this                          final synthetic
      key                            final

  public default scala.Option<V> remove(K);
    descriptor: (Ljava/lang/Object;)Lscala/Option;
    flags: (0x0001) ACC_PUBLIC
    Code:
      stack=2, locals=3, args_size=2
         0: aload_0
         1: aload_1
         2: invokeinterface #77,  2           // InterfaceMethod get:(Ljava/lang/Object;)Lscala/Option;
         7: astore_2
         8: aload_2
         9: invokevirtual #161                // Method scala/Option.isDefined:()Z
        12: ifeq          23
        15: aload_0
        16: aload_1
        17: invokeinterface #52,  2           // InterfaceMethod scala/collection/mutable/Shrinkable.subtractOne:(Ljava/lang/Object;)Lscala/collection/mutable/Shrinkable;
        22: pop
        23: aload_2
        24: areturn
      StackMapTable: number_of_entries = 1
        frame_type = 252 /* append */
          offset_delta = 23
          locals = [ class scala/Option ]
      LineNumberTable:
        line 156: 0
        line 157: 8
        line 158: 23
      LocalVariableTable:
        Start  Length  Slot  Name   Signature
            8      16     2     r   Lscala/Option;
            0      25     0  this   Lscala/collection/mutable/MapOps;
            0      25     1   key   Ljava/lang/Object;
    Signature: #157                         // (TK;)Lscala/Option<TV;>;
    MethodParameters:
      Name                           Flags
      key                            final

  public static void clear$(scala.collection.mutable.MapOps);
    descriptor: (Lscala/collection/mutable/MapOps;)V
    flags: (0x1009) ACC_PUBLIC, ACC_STATIC, ACC_SYNTHETIC
    Code:
      stack=1, locals=1, args_size=1
         0: aload_0
         1: invokespecial #167                // InterfaceMethod clear:()V
         4: return
      LineNumberTable:
        line 161: 0
      LocalVariableTable:
        Start  Length  Slot  Name   Signature
            0       5     0 $this   Lscala/collection/mutable/MapOps;
    MethodParameters:
      Name                           Flags
      $this                          final synthetic

  public default void clear();
    descriptor: ()V
    flags: (0x0001) ACC_PUBLIC
    Code:
      stack=2, locals=1, args_size=1
         0: aload_0
         1: invokeinterface #171,  1          // InterfaceMethod keysIterator:()Lscala/collection/Iterator;
         6: aload_0
         7: invokedynamic #189,  0            // InvokeDynamic #0:apply:(Lscala/collection/mutable/MapOps;)Lscala/Function1;
        12: invokeinterface #195,  2          // InterfaceMethod scala/collection/Iterator.foreach:(Lscala/Function1;)V
        17: return
      LineNumberTable:
        line 161: 0
      LocalVariableTable:
        Start  Length  Slot  Name   Signature
            0      18     0  this   Lscala/collection/mutable/MapOps;

  public static scala.collection.mutable.MapOps clone$(scala.collection.mutable.MapOps);
    descriptor: (Lscala/collection/mutable/MapOps;)Lscala/collection/mutable/MapOps;
    flags: (0x1009) ACC_PUBLIC, ACC_STATIC, ACC_SYNTHETIC
    Code:
      stack=1, locals=1, args_size=1
         0: aload_0
         1: invokespecial #48                 // InterfaceMethod clone:()Lscala/collection/mutable/MapOps;
         4: areturn
      LineNumberTable:
        line 163: 0
      LocalVariableTable:
        Start  Length  Slot  Name   Signature
            0       5     0 $this   Lscala/collection/mutable/MapOps;
    MethodParameters:
      Name                           Flags
      $this                          final synthetic

  public default C clone();
    descriptor: ()Lscala/collection/mutable/MapOps;
    flags: (0x0001) ACC_PUBLIC
    Code:
      stack=2, locals=1, args_size=1
         0: aload_0
         1: invokeinterface #199,  1          // InterfaceMethod empty:()Ljava/lang/Object;
         6: checkcast     #88                 // class scala/collection/mutable/Growable
         9: dup
        10: ifnonnull     15
        13: aconst_null
        14: athrow
        15: aload_0
        16: invokeinterface #203,  2          // InterfaceMethod scala/collection/mutable/Growable.addAll:(Lscala/collection/IterableOnce;)Lscala/collection/mutable/Growable;
        21: checkcast     #2                  // class scala/collection/mutable/MapOps
        24: areturn
      StackMapTable: number_of_entries = 1
        frame_type = 79 /* same_locals_1_stack_item */
          stack = [ class scala/collection/mutable/Growable ]
      LineNumberTable:
        line 163: 0
      LocalVariableTable:
        Start  Length  Slot  Name   Signature
            0      25     0  this   Lscala/collection/mutable/MapOps;
    Signature: #31                          // ()TC;

  public static scala.collection.mutable.MapOps retain$(scala.collection.mutable.MapOps, scala.Function2);
    descriptor: (Lscala/collection/mutable/MapOps;Lscala/Function2;)Lscala/collection/mutable/MapOps;
    flags: (0x1009) ACC_PUBLIC, ACC_STATIC, ACC_SYNTHETIC
    Code:
      stack=2, locals=2, args_size=2
         0: aload_0
         1: aload_1
         2: invokespecial #210                // InterfaceMethod retain:(Lscala/Function2;)Lscala/collection/mutable/MapOps;
         5: areturn
      LineNumberTable:
        line 166: 0
      LocalVariableTable:
        Start  Length  Slot  Name   Signature
            0       6     0 $this   Lscala/collection/mutable/MapOps;
            0       6     1     p   Lscala/Function2;
    MethodParameters:
      Name                           Flags
      $this                          final synthetic
      p                              final

  public default scala.collection.mutable.MapOps<K, V, CC, C> retain(scala.Function2<K, V, java.lang.Object>);
    descriptor: (Lscala/Function2;)Lscala/collection/mutable/MapOps;
    flags: (0x0001) ACC_PUBLIC
    Code:
      stack=2, locals=2, args_size=2
         0: aload_0
         1: aload_1
         2: invokeinterface #215,  2          // InterfaceMethod filterInPlace:(Lscala/Function2;)Lscala/collection/mutable/MapOps;
         7: areturn
      LineNumberTable:
        line 166: 0
      LocalVariableTable:
        Start  Length  Slot  Name   Signature
            0       8     0  this   Lscala/collection/mutable/MapOps;
            0       8     1     p   Lscala/Function2;
    Signature: #212                         // (Lscala/Function2<TK;TV;Ljava/lang/Object;>;)Lscala/collection/mutable/MapOps<TK;TV;TCC;TC;>;
    Deprecated: true
    MethodParameters:
      Name                           Flags
      p                              final

  public static scala.collection.mutable.MapOps filterInPlace$(scala.collection.mutable.MapOps, scala.Function2);
    descriptor: (Lscala/collection/mutable/MapOps;Lscala/Function2;)Lscala/collection/mutable/MapOps;
    flags: (0x1009) ACC_PUBLIC, ACC_STATIC, ACC_SYNTHETIC
    Code:
      stack=2, locals=2, args_size=2
         0: aload_0
         1: aload_1
         2: invokespecial #215                // InterfaceMethod filterInPlace:(Lscala/Function2;)Lscala/collection/mutable/MapOps;
         5: areturn
      LineNumberTable:
        line 173: 0
      LocalVariableTable:
        Start  Length  Slot  Name   Signature
            0       6     0 $this   Lscala/collection/mutable/MapOps;
            0       6     1     p   Lscala/Function2;
    MethodParameters:
      Name                           Flags
      $this                          final synthetic
      p                              final

  public default scala.collection.mutable.MapOps<K, V, CC, C> filterInPlace(scala.Function2<K, V, java.lang.Object>);
    descriptor: (Lscala/Function2;)Lscala/collection/mutable/MapOps;
    flags: (0x0001) ACC_PUBLIC
    Code:
      stack=3, locals=8, args_size=2
         0: aload_0
         1: invokeinterface #219,  1          // InterfaceMethod isEmpty:()Z
         6: ifne          129
         9: aload_0
        10: instanceof    #221                // class scala/collection/concurrent/Map
        13: ifeq          30
        16: aload_0
        17: checkcast     #221                // class scala/collection/concurrent/Map
        20: aload_1
        21: invokeinterface #225,  2          // InterfaceMethod scala/collection/concurrent/Map.filterInPlaceImpl:(Lscala/Function2;)Lscala/collection/concurrent/Map;
        26: pop
        27: goto          129
        30: aload_0
        31: getstatic     #230                // Field scala/reflect/ClassTag$.MODULE$:Lscala/reflect/ClassTag$;
        34: invokevirtual #234                // Method scala/reflect/ClassTag$.Any:()Lscala/reflect/ClassTag;
        37: invokeinterface #238,  2          // InterfaceMethod toArray:(Lscala/reflect/ClassTag;)Ljava/lang/Object;
        42: checkcast     #240                // class "[Ljava/lang/Object;"
        45: astore_2
        46: aload_2
        47: arraylength
        48: istore_3
        49: iconst_0
        50: istore        4
        52: iload         4
        54: iload_3
        55: if_icmpge     129
        58: aload_2
        59: iload         4
        61: aaload
        62: checkcast     #90                 // class scala/Tuple2
        65: astore        5
        67: aload         5
        69: ifnull        89
        72: aload         5
        74: invokevirtual #243                // Method scala/Tuple2._1:()Ljava/lang/Object;
        77: astore        6
        79: aload         5
        81: invokevirtual #246                // Method scala/Tuple2._2:()Ljava/lang/Object;
        84: astore        7
        86: goto          98
        89: new           #134                // class scala/MatchError
        92: dup
        93: aconst_null
        94: invokespecial #137                // Method scala/MatchError."<init>":(Ljava/lang/Object;)V
        97: athrow
        98: aload_1
        99: aload         6
       101: aload         7
       103: invokeinterface #251,  3          // InterfaceMethod scala/Function2.apply:(Ljava/lang/Object;Ljava/lang/Object;)Ljava/lang/Object;
       108: invokestatic  #256                // Method scala/runtime/BoxesRunTime.unboxToBoolean:(Ljava/lang/Object;)Z
       111: ifne          123
       114: aload_0
       115: aload         6
       117: invokeinterface #52,  2           // InterfaceMethod scala/collection/mutable/Shrinkable.subtractOne:(Ljava/lang/Object;)Lscala/collection/mutable/Shrinkable;
       122: pop
       123: iinc          4, 1
       126: goto          52
       129: aload_0
       130: areturn
      StackMapTable: number_of_entries = 6
        frame_type = 30 /* same */
        frame_type = 254 /* append */
          offset_delta = 21
          locals = [ class "[Ljava/lang/Object;", int, int ]
        frame_type = 252 /* append */
          offset_delta = 36
          locals = [ class scala/Tuple2 ]
        frame_type = 253 /* append */
          offset_delta = 8
          locals = [ class java/lang/Object, class java/lang/Object ]
        frame_type = 24 /* same */
        frame_type = 255 /* full_frame */
          offset_delta = 5
          locals = [ class scala/collection/mutable/MapOps, class scala/Function2 ]
          stack = []
      LineNumberTable:
        line 174: 0
        line 175: 9
        line 177: 30
        line 178: 46
        line 179: 49
        line 180: 52
        line 181: 58
        line 182: 98
        line 183: 114
        line 185: 123
        line 180: 126
        line 188: 129
      LocalVariableTable:
        Start  Length  Slot  Name   Signature
           79      10     6     k   Ljava/lang/Object;
           86       3     7     v   Ljava/lang/Object;
           46      83     2 array   [Ljava/lang/Object;
           49      80     3 arrayLength   I
           52      77     4     i   I
            0     131     0  this   Lscala/collection/mutable/MapOps;
            0     131     1     p   Lscala/Function2;
    Signature: #212                         // (Lscala/Function2<TK;TV;Ljava/lang/Object;>;)Lscala/collection/mutable/MapOps<TK;TV;TCC;TC;>;
    MethodParameters:
      Name                           Flags
      p                              final

  public static scala.collection.mutable.MapOps transform$(scala.collection.mutable.MapOps, scala.Function2);
    descriptor: (Lscala/collection/mutable/MapOps;Lscala/Function2;)Lscala/collection/mutable/MapOps;
    flags: (0x1009) ACC_PUBLIC, ACC_STATIC, ACC_SYNTHETIC
    Code:
      stack=2, locals=2, args_size=2
         0: aload_0
         1: aload_1
         2: invokespecial #266                // InterfaceMethod transform:(Lscala/Function2;)Lscala/collection/mutable/MapOps;
         5: areturn
      LineNumberTable:
        line 192: 0
      LocalVariableTable:
        Start  Length  Slot  Name   Signature
            0       6     0 $this   Lscala/collection/mutable/MapOps;
            0       6     1     f   Lscala/Function2;
    MethodParameters:
      Name                           Flags
      $this                          final synthetic
      f                              final

  public default scala.collection.mutable.MapOps<K, V, CC, C> transform(scala.Function2<K, V, V>);
    descriptor: (Lscala/Function2;)Lscala/collection/mutable/MapOps;
    flags: (0x0001) ACC_PUBLIC
    Code:
      stack=2, locals=2, args_size=2
         0: aload_0
         1: aload_1
         2: invokeinterface #270,  2          // InterfaceMethod mapValuesInPlace:(Lscala/Function2;)Lscala/collection/mutable/MapOps;
         7: areturn
      LineNumberTable:
        line 192: 0
      LocalVariableTable:
        Start  Length  Slot  Name   Signature
            0       8     0  this   Lscala/collection/mutable/MapOps;
            0       8     1     f   Lscala/Function2;
    Signature: #267                         // (Lscala/Function2<TK;TV;TV;>;)Lscala/collection/mutable/MapOps<TK;TV;TCC;TC;>;
    Deprecated: true
    MethodParameters:
      Name                           Flags
      f                              final

  public static scala.collection.mutable.MapOps mapValuesInPlace$(scala.collection.mutable.MapOps, scala.Function2);
    descriptor: (Lscala/collection/mutable/MapOps;Lscala/Function2;)Lscala/collection/mutable/MapOps;
    flags: (0x1009) ACC_PUBLIC, ACC_STATIC, ACC_SYNTHETIC
    Code:
      stack=2, locals=2, args_size=2
         0: aload_0
         1: aload_1
         2: invokespecial #270                // InterfaceMethod mapValuesInPlace:(Lscala/Function2;)Lscala/collection/mutable/MapOps;
         5: areturn
      LineNumberTable:
        line 201: 0
      LocalVariableTable:
        Start  Length  Slot  Name   Signature
            0       6     0 $this   Lscala/collection/mutable/MapOps;
            0       6     1     f   Lscala/Function2;
    MethodParameters:
      Name                           Flags
      $this                          final synthetic
      f                              final

  public default scala.collection.mutable.MapOps<K, V, CC, C> mapValuesInPlace(scala.Function2<K, V, V>);
    descriptor: (Lscala/Function2;)Lscala/collection/mutable/MapOps;
    flags: (0x0001) ACC_PUBLIC
    Code:
      stack=5, locals=8, args_size=2
         0: aload_0
         1: invokeinterface #219,  1          // InterfaceMethod isEmpty:()Z
         6: ifne          141
         9: aload_0
        10: instanceof    #273                // class scala/collection/mutable/HashMap
        13: ifeq          28
        16: aload_0
        17: checkcast     #273                // class scala/collection/mutable/HashMap
        20: aload_1
        21: invokevirtual #277                // Method scala/collection/mutable/HashMap.mapValuesInPlaceImpl:(Lscala/Function2;)Lscala/collection/mutable/HashMap;
        24: pop
        25: goto          141
        28: aload_0
        29: instanceof    #221                // class scala/collection/concurrent/Map
        32: ifeq          49
        35: aload_0
        36: checkcast     #221                // class scala/collection/concurrent/Map
        39: aload_1
        40: invokeinterface #279,  2          // InterfaceMethod scala/collection/concurrent/Map.mapValuesInPlaceImpl:(Lscala/Function2;)Lscala/collection/concurrent/Map;
        45: pop
        46: goto          141
        49: aload_0
        50: getstatic     #230                // Field scala/reflect/ClassTag$.MODULE$:Lscala/reflect/ClassTag$;
        53: invokevirtual #234                // Method scala/reflect/ClassTag$.Any:()Lscala/reflect/ClassTag;
        56: invokeinterface #238,  2          // InterfaceMethod toArray:(Lscala/reflect/ClassTag;)Ljava/lang/Object;
        61: checkcast     #240                // class "[Ljava/lang/Object;"
        64: astore_2
        65: aload_2
        66: arraylength
        67: istore_3
        68: iconst_0
        69: istore        4
        71: iload         4
        73: iload_3
        74: if_icmpge     141
        77: aload_2
        78: iload         4
        80: aaload
        81: checkcast     #90                 // class scala/Tuple2
        84: astore        5
        86: aload         5
        88: ifnull        108
        91: aload         5
        93: invokevirtual #243                // Method scala/Tuple2._1:()Ljava/lang/Object;
        96: astore        6
        98: aload         5
       100: invokevirtual #246                // Method scala/Tuple2._2:()Ljava/lang/Object;
       103: astore        7
       105: goto          117
       108: new           #134                // class scala/MatchError
       111: dup
       112: aconst_null
       113: invokespecial #137                // Method scala/MatchError."<init>":(Ljava/lang/Object;)V
       116: athrow
       117: aload_0
       118: aload         6
       120: aload_1
       121: aload         6
       123: aload         7
       125: invokeinterface #251,  3          // InterfaceMethod scala/Function2.apply:(Ljava/lang/Object;Ljava/lang/Object;)Ljava/lang/Object;
       130: invokeinterface #81,  3           // InterfaceMethod update:(Ljava/lang/Object;Ljava/lang/Object;)V
       135: iinc          4, 1
       138: goto          71
       141: aload_0
       142: areturn
      StackMapTable: number_of_entries = 6
        frame_type = 28 /* same */
        frame_type = 20 /* same */
        frame_type = 254 /* append */
          offset_delta = 21
          locals = [ class "[Ljava/lang/Object;", int, int ]
        frame_type = 252 /* append */
          offset_delta = 36
          locals = [ class scala/Tuple2 ]
        frame_type = 253 /* append */
          offset_delta = 8
          locals = [ class java/lang/Object, class java/lang/Object ]
        frame_type = 255 /* full_frame */
          offset_delta = 23
          locals = [ class scala/collection/mutable/MapOps, class scala/Function2 ]
          stack = []
      LineNumberTable:
        line 202: 0
        line 203: 9
        line 204: 28
        line 206: 49
        line 207: 65
        line 208: 68
        line 209: 71
        line 210: 77
        line 211: 117
        line 212: 135
        line 209: 138
        line 215: 141
      LocalVariableTable:
        Start  Length  Slot  Name   Signature
           98      10     6     k   Ljava/lang/Object;
          105       3     7     v   Ljava/lang/Object;
           65      76     2 array   [Ljava/lang/Object;
           68      73     3 arrayLength   I
           71      70     4     i   I
            0     143     0  this   Lscala/collection/mutable/MapOps;
            0     143     1     f   Lscala/Function2;
    Signature: #267                         // (Lscala/Function2<TK;TV;TV;>;)Lscala/collection/mutable/MapOps<TK;TV;TCC;TC;>;
    MethodParameters:
      Name                           Flags
      f                              final

  public static scala.collection.mutable.MapOps updated$(scala.collection.mutable.MapOps, java.lang.Object, java.lang.Object);
    descriptor: (Lscala/collection/mutable/MapOps;Ljava/lang/Object;Ljava/lang/Object;)Lscala/collection/mutable/MapOps;
    flags: (0x1009) ACC_PUBLIC, ACC_STATIC, ACC_SYNTHETIC
    Code:
      stack=3, locals=3, args_size=3
         0: aload_0
         1: aload_1
         2: aload_2
         3: invokespecial #285                // InterfaceMethod updated:(Ljava/lang/Object;Ljava/lang/Object;)Lscala/collection/mutable/MapOps;
         6: areturn
      LineNumberTable:
        line 219: 0
      LocalVariableTable:
        Start  Length  Slot  Name   Signature
            0       7     0 $this   Lscala/collection/mutable/MapOps;
            0       7     1   key   Ljava/lang/Object;
            0       7     2 value   Ljava/lang/Object;
    MethodParameters:
      Name                           Flags
      $this                          final synthetic
      key                            final
      value                          final

  public default <V1 extends java.lang.Object> CC updated(K, V1);
    descriptor: (Ljava/lang/Object;Ljava/lang/Object;)Lscala/collection/mutable/MapOps;
    flags: (0x0001) ACC_PUBLIC
    Code:
      stack=5, locals=3, args_size=3
         0: aload_0
         1: invokeinterface #48,  1           // InterfaceMethod clone:()Lscala/collection/mutable/MapOps;
         6: new           #90                 // class scala/Tuple2
         9: dup
        10: aload_1
        11: aload_2
        12: invokespecial #93                 // Method scala/Tuple2."<init>":(Ljava/lang/Object;Ljava/lang/Object;)V
        15: invokeinterface #287,  2          // InterfaceMethod addOne:(Ljava/lang/Object;)Lscala/collection/mutable/Growable;
        20: checkcast     #2                  // class scala/collection/mutable/MapOps
        23: areturn
      LineNumberTable:
        line 220: 0
      LocalVariableTable:
        Start  Length  Slot  Name   Signature
            0      24     0  this   Lscala/collection/mutable/MapOps;
            0      24     1   key   Ljava/lang/Object;
            0      24     2 value   Ljava/lang/Object;
    Signature: #286                         // <V1:Ljava/lang/Object;>(TK;TV1;)TCC;
    Deprecated: true
    MethodParameters:
      Name                           Flags
      key                            final
      value                          final

  public static int knownSize$(scala.collection.mutable.MapOps);
    descriptor: (Lscala/collection/mutable/MapOps;)I
    flags: (0x1009) ACC_PUBLIC, ACC_STATIC, ACC_SYNTHETIC
    Code:
      stack=1, locals=1, args_size=1
         0: aload_0
         1: invokespecial #293                // InterfaceMethod knownSize:()I
         4: ireturn
      LineNumberTable:
        line 222: 0
      LocalVariableTable:
        Start  Length  Slot  Name   Signature
            0       5     0 $this   Lscala/collection/mutable/MapOps;
    MethodParameters:
      Name                           Flags
      $this                          final synthetic

  public default int knownSize();
    descriptor: ()I
    flags: (0x0001) ACC_PUBLIC
    Code:
      stack=1, locals=1, args_size=1
         0: iconst_m1
         1: ireturn
      LineNumberTable:
        line 222: 0
      LocalVariableTable:
        Start  Length  Slot  Name   Signature
            0       2     0  this   Lscala/collection/mutable/MapOps;

  public static scala.collection.mutable.MapOps $anonfun$clear$1(scala.collection.mutable.MapOps, java.lang.Object);
    descriptor: (Lscala/collection/mutable/MapOps;Ljava/lang/Object;)Lscala/collection/mutable/MapOps;
    flags: (0x1009) ACC_PUBLIC, ACC_STATIC, ACC_SYNTHETIC
    Code:
      stack=2, locals=2, args_size=2
         0: aload_0
         1: aload_1
         2: invokeinterface #297,  2          // InterfaceMethod $minus$eq:(Ljava/lang/Object;)Lscala/collection/mutable/Shrinkable;
         7: checkcast     #2                  // class scala/collection/mutable/MapOps
        10: areturn
      LineNumberTable:
        line 161: 0
      LocalVariableTable:
        Start  Length  Slot  Name   Signature
            0      11     0 $this   Lscala/collection/mutable/MapOps;
            0      11     1  elem   Ljava/lang/Object;
    MethodParameters:
      Name                           Flags
      $this                          final synthetic
      elem                           final

  public static void $init$(scala.collection.mutable.MapOps);
    descriptor: (Lscala/collection/mutable/MapOps;)V
    flags: (0x0009) ACC_PUBLIC, ACC_STATIC
    Code:
      stack=0, locals=1, args_size=1
         0: return
      LineNumberTable:
        line 66: 0
      LocalVariableTable:
        Start  Length  Slot  Name   Signature
            0       1     0 $this   Lscala/collection/mutable/MapOps;
    MethodParameters:
      Name                           Flags
      $this                          final synthetic

  private static java.lang.Object $deserializeLambda$(java.lang.invoke.SerializedLambda);
    descriptor: (Ljava/lang/invoke/SerializedLambda;)Ljava/lang/Object;
    flags: (0x100a) ACC_PRIVATE, ACC_STATIC, ACC_SYNTHETIC
    Code:
      stack=1, locals=1, args_size=1
         0: aload_0
         1: invokedynamic #310,  0            // InvokeDynamic #1:lambdaDeserialize:(Ljava/lang/invoke/SerializedLambda;)Ljava/lang/Object;
         6: areturn
}
InnerClasses:
  public static final #22= #19 of #21;    // Lookup=class java/lang/invoke/MethodHandles$Lookup of class java/lang/invoke/MethodHandles
Signature: #3                           // <K:Ljava/lang/Object;V:Ljava/lang/Object;CC::Lscala/collection/mutable/MapOps<Ljava/lang/Object;Ljava/lang/Object;TCC;*>;C::Lscala/collection/mutable/MapOps<TK;TV;TCC;TC;>;>Ljava/lang/Object;Lscala/collection/MapOps<TK;TV;TCC;TC;>;Lscala/collection/mutable/Cloneable<TC;>;Lscala/collection/mutable/Builder<Lscala/Tuple2<TK;TV;>;TC;>;Lscala/collection/mutable/Shrinkable<TK;>;
SourceFile: "Map.scala"
RuntimeVisibleAnnotations:
  0: #15(#16=s#17)
    scala.reflect.ScalaSignature(
      bytes="\u0006\u0005\u0005\u001dfa\u0002\n\u0014!\u0003\r\tA\u0007\u0005\u00069\u0002!\t!\u0018\u0005\u0006C\u0002!\tA\u0019\u0005\u0006G\u0002!)\u0001\u001a\u0005\u0006G\u0002!)!\u001d\u0005\u0006}\u0002!\ta \u0005\b\u0003\u001b\u0001A\u0011AA\b\u0011\u001d\t)\u0002\u0001C\u0001\u0003/Aq!a\n\u0001\t\u0003\tI\u0003C\u0004\u00028\u0001!\t!!\u000f\t\r\u0005u\u0002\u0001\"\u0001^\u0011\u0019\ty\u0004\u0001C!E\"9\u0011\u0011\t\u0001\u0005\u0006\u0005\r\u0003bBA3\u0001\u0011\u0005\u0011q\r\u0005\b\u0003W\u0002AQAA7\u0011\u001d\ti\b\u0001C\u0001\u0003\u007fBq!a!\u0001\t\u0003\t)\tC\u0004\u0002\u001e\u0002!\t%a(\u0003\r5\u000b\u0007o\u00149t\u0015\t!R#A\u0004nkR\f\'\r\\3\u000b\u0005Y9\u0012AC2pY2,7\r^5p]*\t\u0001$A\u0003tG\u0006d\u0017m\u0001\u0001\u0016\u000bmI3g\u0010\u001e\u0014\u0011\u0001a\u0002E\u0014)T-f\u0003\"!\b\u0010\u000e\u0003]I!aH\f\u0003\r\u0005s\u0017PU3g!\u0015\t#\u0005J\u001b:\u001b\u0005)\u0012BA\u0012\u0016\u0005-IE/\u001a:bE2,w\n]:\u0011\tu)sEM\u0005\u0003M]\u0011a\u0001V;qY\u0016\u0014\u0004C\u0001\u0015*\u0019\u0001!QA\u000b\u0001C\u0002-\u0012\u0011aS\t\u0003Y=\u0002\"!H\u0017\n\u00059:\"a\u0002(pi\"Lgn\u001a\t\u0003;AJ!!M\f\u0003\u0007\u0005s\u0017\u0010\u0005\u0002)g\u0011)A\u0007\u0001b\u0001W\t\ta\u000b\u0005\u00027o5\t1#\u0003\u00029\'\tA\u0011\n^3sC\ndW\r\u0005\u0002)u\u001111\b\u0001CC\u0002q\u0012\u0011aQ\t\u0003Yu\u0002bA\u000e\u0001(eyJ\u0004C\u0001\u0015@\t\u0019\u0001\u0005\u0001\"b\u0001\u0003\n\u00111iQ\u000b\u0004\u0005\u001aK\u0015C\u0001\u0017Da\t!E\n\u0005\u00047\u0001\u0015Ceh\u0013\t\u0003Q\u0019#QaR C\u0002-\u0012\u0011\u0001\u0017\t\u0003Q%#QAS C\u0002-\u0012\u0011!\u0017\t\u0003Q1#\u0011\"T \u0002\u0002\u0003\u0005)\u0011A\u0016\u0003\u0007}#\u0013\u0007\u0005\u0004\"\u001f\u001e\u0012d(O\u0005\u0003%U\u00012AN):\u0013\t\u00116CA\u0005DY>tW-\u00192mKB!a\u0007\u0016\u0013:\u0013\t)6CA\u0004Ck&dG-\u001a:\u0011\u0007Y:F%\u0003\u0002Y\'\tAqI]8xC\ndW\rE\u000275\u001eJ!aW\n\u0003\u0015MC\'/\u001b8lC\ndW-\u0001\u0004%S:LG\u000f\n\u000b\u0002=B\u0011QdX\u0005\u0003A^\u0011A!\u00168ji\u00061!/Z:vYR$\u0012!O\u0001\u0007I5Lg.^:\u0015\u0005e*\u0007\"\u00024\u0004\u0001\u00049\u0013aA6fs\"21\u0001[6m]>\u0004\"!H5\n\u0005)<\"A\u00033faJ,7-\u0019;fI\u00069Q.Z:tC\u001e,\u0017%A7\u0002GU\u001bX\rI\u0017!_J\u0004#/Z7pm\u0016\u0004sN\u001c\u0011b]\u0002JW.\\;uC\ndW\rI\'ba\u0006)1/\u001b8dK\u0006\n\u0001/\u0001\u00043]E\u001ad\u0006\r\u000b\u0005sI$h\u000fC\u0003t\t\u0001\u0007q%\u0001\u0003lKf\f\u0004\"B;\u0005\u0001\u00049\u0013\u0001B6fsJBQa\u001e\u0003A\u0002a\fAa[3zgB\u0019Q$_\u0014\n\u0005i<\"A\u0003\u001fsKB,\u0017\r^3e}!2A\u0001[6}]>\f\u0013!`\u0001(+N,\u0007%L\u0017!_J\u0004#/Z7pm\u0016\fE\u000e\u001c\u0011p]\u0002\ng\u000eI5n[V$\u0018M\u00197fA5\u000b\u0007/A\u0002qkR$b!!\u0001\u0002\b\u0005%\u0001\u0003B\u000f\u0002\u0004IJ1!!\u0002\u0018\u0005\u0019y\u0005\u000f^5p]\")a-\u0002a\u0001O!1\u00111B\u0003A\u0002I\nQA^1mk\u0016\fa!\u001e9eCR,G#\u00020\u0002\u0012\u0005M\u0001\"\u00024\u0007\u0001\u00049\u0003BBA\u0006\r\u0001\u0007!\'\u0001\u0006va\u0012\fG/Z,ji\"$B!!\u0007\u0002&Q!\u0011\u0011AA\u000e\u0011\u001d\tib\u0002a\u0001\u0003?\t\u0011C]3nCB\u0004\u0018N\\4Gk:\u001cG/[8o!\u001di\u0012\u0011EA\u0001\u0003\u0003I1!a\t\u0018\u0005%1UO\\2uS>t\u0017\u0007C\u0003g\u000f\u0001\u0007q%A\bhKR|%/\u00127tKV\u0003H-\u0019;f)\u0015\u0011\u00141FA\u0017\u0011\u00151\u0007\u00021\u0001(\u0011!\ty\u0003\u0003CA\u0002\u0005E\u0012AA8q!\u0011i\u00121\u0007\u001a\n\u0007\u0005UrC\u0001\u0005=Eft\u0017-\\3?\u0003\u0019\u0011X-\\8wKR!\u0011\u0011AA\u001e\u0011\u00151\u0017\u00021\u0001(\u0003\u0015\u0019G.Z1s\u0003\u0015\u0019Gn\u001c8f\u0003\u0019\u0011X\r^1j]R!\u0011QIA$\u001b\u0005\u0001\u0001bBA%\u0019\u0001\u0007\u00111J\u0001\u0002aB9Q$!\u0014(e\u0005E\u0013bAA(/\tIa)\u001e8di&|gN\r\t\u0004;\u0005M\u0013bAA+/\t9!i\\8mK\u0006t\u0007f\u0001\u0007\u0002ZA\u0019Q$a\u0017\n\u0007\u0005usC\u0001\u0004j]2Lg.\u001a\u0015\b\u0019!\\\u0017\u0011\r8pC\t\t\u0019\'A\rVg\u0016\u0004c-\u001b7uKJLe\u000e\u00157bG\u0016\u0004\u0013N\\:uK\u0006$\u0017!\u00044jYR,\'/\u00138QY\u0006\u001cW\r\u0006\u0003\u0002F\u0005%\u0004bBA%\u001b\u0001\u0007\u00111J\u0001\niJ\fgn\u001d4pe6$B!!\u0012\u0002p!9\u0011\u0011\u000f\bA\u0002\u0005M\u0014!\u00014\u0011\ru\tie\n\u001a3Q\rq\u0011\u0011\f\u0015\b\u001d!\\\u0017\u0011\u00108pC\t\tY(\u0001\u000fVg\u0016\u0004S.\u00199WC2,Xm]%o!2\f7-\u001a\u0011j]N$X-\u00193\u0002!5\f\u0007OV1mk\u0016\u001c\u0018J\u001c)mC\u000e,G\u0003BA#\u0003\u0003Cq!!\u001d\u0010\u0001\u0004\t\u0019(A\u0004va\u0012\fG/\u001a3\u0016\t\u0005\u001d\u0015Q\u0012\u000b\u0007\u0003\u0013\u000b\u0019*!&\u0011\u000b!zt%a#\u0011\u0007!\ni\tB\u0004\u0002\u0010B\u0011\r!!%\u0003\u0005Y\u000b\u0014C\u0001\u001a0\u0011\u00151\u0007\u00031\u0001(\u0011\u001d\tY\u0001\u0005a\u0001\u0003\u0017Cs\u0001\u00055l\u00033sw.\t\u0002\u0002\u001c\u00061Tk]3![:\u001aGn\u001c8fQ%r\u0013\r\u001a3P]\u0016D\u0003f\u001b\u0017wS%\u0002\u0013N\\:uK\u0006$\u0007e\u001c4![:*\b\u000fZ1uK\u0012D3\u000e\f\u0011wS\u0005I1N\\8x]NK\'0Z\u000b\u0003\u0003C\u00032!HAR\u0013\r\t)k\u0006\u0002\u0004\u0013:$\b"
    )
BootstrapMethods:
  0: #186 REF_invokeStatic java/lang/invoke/LambdaMetafactory.altMetafactory:(Ljava/lang/invoke/MethodHandles$Lookup;Ljava/lang/String;Ljava/lang/invoke/MethodType;[Ljava/lang/Object;)Ljava/lang/invoke/CallSite;
    Method arguments:
      #172 (Ljava/lang/Object;)Ljava/lang/Object;
      #176 REF_invokeStatic scala/collection/mutable/MapOps.$anonfun$clear$1:(Lscala/collection/mutable/MapOps;Ljava/lang/Object;)Lscala/collection/mutable/MapOps;
      #177 (Ljava/lang/Object;)Lscala/collection/mutable/MapOps;
      #178 5
      #179 1
      #177 (Ljava/lang/Object;)Lscala/collection/mutable/MapOps;
  1: #307 REF_invokeStatic scala/runtime/LambdaDeserialize.bootstrap:(Ljava/lang/invoke/MethodHandles$Lookup;Ljava/lang/String;Ljava/lang/invoke/MethodType;[Ljava/lang/invoke/MethodHandle;)Ljava/lang/invoke/CallSite;
    Method arguments:
      #176 REF_invokeStatic scala/collection/mutable/MapOps.$anonfun$clear$1:(Lscala/collection/mutable/MapOps;Ljava/lang/Object;)Lscala/collection/mutable/MapOps;
  ScalaInlineInfo: length = 0xAE (unknown attribute)
   01 00 00 22 00 AD 00 26 01 01 2A 00 A3 01 00 28
   00 29 01 00 28 00 39 01 00 25 00 26 01 00 25 00
   35 01 00 A4 00 A5 00 00 A2 00 A3 01 00 2E 00 1B
   00 00 C4 00 18 01 00 D5 00 D0 00 00 D8 00 CD 01
   00 90 00 91 00 00 8D 00 8E 01 01 22 01 23 00 01
   20 01 21 01 01 0C 00 D0 00 01 0F 00 CD 01 00 45
   00 46 00 00 42 00 43 01 00 80 00 4B 00 00 9B 00
   9C 01 00 1A 00 1B 00 00 17 00 18 01 00 CF 00 D0
   05 00 CC 00 CD 05 01 08 00 D0 05 01 06 00 CD 05
   00 4E 00 4F 00 00 54 00 55 01 00 66 00 67 00 00
   63 00 64 01 01 1A 01 1B 00 01 18 01 19 01
  ScalaSig: length = 0x3 (unknown attribute)
   05 02 00
