Classfile /Users/mw/Projects/slang-braindump/.jar/jar8/assemble/slang-braindump/assemble/content/scala/collection/mutable/MultiMap.class
  Last modified May 29, 2022; size 4143 bytes
  SHA-256 checksum ca6d6ea0f82dacb00740b9066028fbeb03b091bee97e7fcac09ec4b4769f809e
  Compiled from "MultiMap.scala"
public interface scala.collection.mutable.MultiMap<K extends java.lang.Object, V extends java.lang.Object> extends scala.collection.mutable.Map<K, scala.collection.mutable.Set<V>>
  minor version: 0
  major version: 52
  flags: (0x0601) ACC_PUBLIC, ACC_INTERFACE, ACC_ABSTRACT
  this_class: #2                          // scala/collection/mutable/MultiMap
  super_class: #5                         // java/lang/Object
  interfaces: 1, fields: 0, methods: 9, attributes: 6
Constant pool:
    #1 = Utf8               scala/collection/mutable/MultiMap
    #2 = Class              #1            // scala/collection/mutable/MultiMap
    #3 = Utf8               <K:Ljava/lang/Object;V:Ljava/lang/Object;>Ljava/lang/Object;Lscala/collection/mutable/Map<TK;Lscala/collection/mutable/Set<TV;>;>;
    #4 = Utf8               java/lang/Object
    #5 = Class              #4            // java/lang/Object
    #6 = Utf8               scala/collection/mutable/Map
    #7 = Class              #6            // scala/collection/mutable/Map
    #8 = Utf8               MultiMap.scala
    #9 = Utf8               Lscala/reflect/ScalaSignature;
   #10 = Utf8               bytes
   #11 = Utf8               \u0006\u0005A3qAB\u0004\u0011\u0002\u0007\u0005a\u0002C\u0003*\u0001\u0011\u0005!\u0006C\u0003/\u0001\u0011Eq\u0006C\u00031\u0001\u0011\u0005\u0011\u0007C\u00038\u0001\u0011\u0005\u0001\bC\u0003<\u0001\u0011\u0005AH\u0001\u0005Nk2$\u0018.T1q\u0015\tA\u0011\"A\u0004nkR\f\'\r\\3\u000b\u0005)Y\u0011AC2pY2,7\r^5p]*\tA\"A\u0003tG\u0006d\u0017m\u0001\u0001\u0016\u0007=QreE\u0002\u0001!Q\u0001\"!\u0005\n\u000e\u0003-I!aE\u0006\u0003\r\u0005s\u0017PU3g!\u0011)b\u0003G\u0012\u000e\u0003\u001dI!aF\u0004\u0003\u00075\u000b\u0007\u000f\u0005\u0002\u001a51\u0001A!B\u000e\u0001\u0005\u0004a\"!A&\u0012\u0005u\u0001\u0003CA\t\u001f\u0013\ty2BA\u0004O_RD\u0017N\\4\u0011\u0005E\t\u0013B\u0001\u0012\f\u0005\r\te.\u001f\t\u0004+\u00112\u0013BA\u0013\b\u0005\r\u0019V\r\u001e\t\u00033\u001d\"Q\u0001\u000b\u0001C\u0002q\u0011\u0011AV\u0001\u0007I%t\u0017\u000e\u001e\u0013\u0015\u0003-\u0002\"!\u0005\u0017\n\u00055Z!\u0001B+oSR\fq!\\1lKN+G/F\u0001$\u0003)\tG\r\u001a\"j]\u0012Lgn\u001a\u000b\u0004eM*T\"\u0001\u0001\t\u000bQ\u001a\u0001\u0019\u0001\r\u0002\u0007-,\u0017\u0010C\u00037\u0007\u0001\u0007a%A\u0003wC2,X-A\u0007sK6|g/\u001a\"j]\u0012Lgn\u001a\u000b\u0004eeR\u0004\"\u0002\u001b\u0005\u0001\u0004A\u0002\"\u0002\u001c\u0005\u0001\u00041\u0013aC3oiJLX\t_5tiN$2!\u0010!B!\t\tb(\u0003\u0002@\u0017\t9!i\\8mK\u0006t\u0007\"\u0002\u001b\u0006\u0001\u0004A\u0002\"\u0002\"\u0006\u0001\u0004\u0019\u0015!\u00019\u0011\tE!e%P\u0005\u0003\u000b.\u0011\u0011BR;oGRLwN\\\u0019)\r\u00019%jS\'O!\t\t\u0002*\u0003\u0002J\u0017\tQA-\u001a9sK\u000e\fG/\u001a3\u0002\u000f5,7o]1hK\u0006\nA*A(Vg\u0016\u0004\u0013\rI:dC2\fgfY8mY\u0016\u001cG/[8o]5,H/\u00192mK:jU\u000f\u001c;j\t&\u001cG\u000fI5oAQDW\rI:dC2\fWfY8mY\u0016\u001cG/[8o[\r|g\u000e\u001e:jE\u0002jw\u000eZ;mK\u0006)1/\u001b8dK\u0006\nq*\u0001\u00043]E\u001ad\u0006\r
   #12 = Utf8               makeSet$
   #13 = Utf8               (Lscala/collection/mutable/MultiMap;)Lscala/collection/mutable/Set;
   #14 = Utf8               $this
   #15 = Utf8               makeSet
   #16 = Utf8               ()Lscala/collection/mutable/Set;
   #17 = NameAndType        #15:#16       // makeSet:()Lscala/collection/mutable/Set;
   #18 = InterfaceMethodref #2.#17        // scala/collection/mutable/MultiMap.makeSet:()Lscala/collection/mutable/Set;
   #19 = Utf8               Lscala/collection/mutable/MultiMap;
   #20 = Utf8               ()Lscala/collection/mutable/Set<TV;>;
   #21 = Utf8               scala/collection/mutable/HashSet
   #22 = Class              #21           // scala/collection/mutable/HashSet
   #23 = Utf8               <init>
   #24 = Utf8               ()V
   #25 = NameAndType        #23:#24       // "<init>":()V
   #26 = Methodref          #22.#25       // scala/collection/mutable/HashSet."<init>":()V
   #27 = Utf8               this
   #28 = Utf8               addBinding$
   #29 = Utf8               (Lscala/collection/mutable/MultiMap;Ljava/lang/Object;Ljava/lang/Object;)Lscala/collection/mutable/MultiMap;
   #30 = Utf8               key
   #31 = Utf8               value
   #32 = Utf8               addBinding
   #33 = Utf8               (Ljava/lang/Object;Ljava/lang/Object;)Lscala/collection/mutable/MultiMap;
   #34 = NameAndType        #32:#33       // addBinding:(Ljava/lang/Object;Ljava/lang/Object;)Lscala/collection/mutable/MultiMap;
   #35 = InterfaceMethodref #2.#34        // scala/collection/mutable/MultiMap.addBinding:(Ljava/lang/Object;Ljava/lang/Object;)Lscala/collection/mutable/MultiMap;
   #36 = Utf8               Ljava/lang/Object;
   #37 = Utf8               (TK;TV;)Lscala/collection/mutable/MultiMap<TK;TV;>;
   #38 = Utf8               get
   #39 = Utf8               (Ljava/lang/Object;)Lscala/Option;
   #40 = NameAndType        #38:#39       // get:(Ljava/lang/Object;)Lscala/Option;
   #41 = InterfaceMethodref #2.#40        // scala/collection/mutable/MultiMap.get:(Ljava/lang/Object;)Lscala/Option;
   #42 = Utf8               scala/None$
   #43 = Class              #42           // scala/None$
   #44 = Utf8               MODULE$
   #45 = Utf8               Lscala/None$;
   #46 = NameAndType        #44:#45       // MODULE$:Lscala/None$;
   #47 = Fieldref           #43.#46       // scala/None$.MODULE$:Lscala/None$;
   #48 = Utf8               equals
   #49 = Utf8               (Ljava/lang/Object;)Z
   #50 = NameAndType        #48:#49       // equals:(Ljava/lang/Object;)Z
   #51 = Methodref          #5.#50        // java/lang/Object.equals:(Ljava/lang/Object;)Z
   #52 = Utf8               scala/collection/mutable/Growable
   #53 = Class              #52           // scala/collection/mutable/Growable
   #54 = Utf8               addOne
   #55 = Utf8               (Ljava/lang/Object;)Lscala/collection/mutable/Growable;
   #56 = NameAndType        #54:#55       // addOne:(Ljava/lang/Object;)Lscala/collection/mutable/Growable;
   #57 = InterfaceMethodref #53.#56       // scala/collection/mutable/Growable.addOne:(Ljava/lang/Object;)Lscala/collection/mutable/Growable;
   #58 = Utf8               update
   #59 = Utf8               (Ljava/lang/Object;Ljava/lang/Object;)V
   #60 = NameAndType        #58:#59       // update:(Ljava/lang/Object;Ljava/lang/Object;)V
   #61 = InterfaceMethodref #2.#60        // scala/collection/mutable/MultiMap.update:(Ljava/lang/Object;Ljava/lang/Object;)V
   #62 = Utf8               scala/Some
   #63 = Class              #62           // scala/Some
   #64 = Utf8               ()Ljava/lang/Object;
   #65 = NameAndType        #31:#64       // value:()Ljava/lang/Object;
   #66 = Methodref          #63.#65       // scala/Some.value:()Ljava/lang/Object;
   #67 = Utf8               scala/collection/mutable/Set
   #68 = Class              #67           // scala/collection/mutable/Set
   #69 = Utf8               scala/MatchError
   #70 = Class              #69           // scala/MatchError
   #71 = Utf8               (Ljava/lang/Object;)V
   #72 = NameAndType        #23:#71       // "<init>":(Ljava/lang/Object;)V
   #73 = Methodref          #70.#72       // scala/MatchError."<init>":(Ljava/lang/Object;)V
   #74 = Utf8               set
   #75 = Utf8               Lscala/collection/mutable/Set;
   #76 = Utf8               scala/Option
   #77 = Class              #76           // scala/Option
   #78 = Utf8               removeBinding$
   #79 = Utf8               removeBinding
   #80 = NameAndType        #79:#33       // removeBinding:(Ljava/lang/Object;Ljava/lang/Object;)Lscala/collection/mutable/MultiMap;
   #81 = InterfaceMethodref #2.#80        // scala/collection/mutable/MultiMap.removeBinding:(Ljava/lang/Object;Ljava/lang/Object;)Lscala/collection/mutable/MultiMap;
   #82 = Utf8               scala/collection/mutable/Shrinkable
   #83 = Class              #82           // scala/collection/mutable/Shrinkable
   #84 = Utf8               subtractOne
   #85 = Utf8               (Ljava/lang/Object;)Lscala/collection/mutable/Shrinkable;
   #86 = NameAndType        #84:#85       // subtractOne:(Ljava/lang/Object;)Lscala/collection/mutable/Shrinkable;
   #87 = InterfaceMethodref #83.#86       // scala/collection/mutable/Shrinkable.subtractOne:(Ljava/lang/Object;)Lscala/collection/mutable/Shrinkable;
   #88 = Utf8               isEmpty
   #89 = Utf8               ()Z
   #90 = NameAndType        #88:#89       // isEmpty:()Z
   #91 = InterfaceMethodref #68.#90       // scala/collection/mutable/Set.isEmpty:()Z
   #92 = Utf8               entryExists$
   #93 = Utf8               (Lscala/collection/mutable/MultiMap;Ljava/lang/Object;Lscala/Function1;)Z
   #94 = Utf8               p
   #95 = Utf8               entryExists
   #96 = Utf8               (Ljava/lang/Object;Lscala/Function1;)Z
   #97 = NameAndType        #95:#96       // entryExists:(Ljava/lang/Object;Lscala/Function1;)Z
   #98 = InterfaceMethodref #2.#97        // scala/collection/mutable/MultiMap.entryExists:(Ljava/lang/Object;Lscala/Function1;)Z
   #99 = Utf8               Lscala/Function1;
  #100 = Utf8               (TK;Lscala/Function1<TV;Ljava/lang/Object;>;)Z
  #101 = Utf8               exists
  #102 = Utf8               (Lscala/Function1;)Z
  #103 = NameAndType        #101:#102     // exists:(Lscala/Function1;)Z
  #104 = InterfaceMethodref #68.#103      // scala/collection/mutable/Set.exists:(Lscala/Function1;)Z
  #105 = Utf8               scala/Function1
  #106 = Class              #105          // scala/Function1
  #107 = Utf8               $init$
  #108 = Utf8               (Lscala/collection/mutable/MultiMap;)V
  #109 = Utf8               Code
  #110 = Utf8               LineNumberTable
  #111 = Utf8               LocalVariableTable
  #112 = Utf8               MethodParameters
  #113 = Utf8               Signature
  #114 = Utf8               StackMapTable
  #115 = Utf8               SourceFile
  #116 = Utf8               Deprecated
  #117 = Utf8               RuntimeVisibleAnnotations
  #118 = Utf8               ScalaInlineInfo
  #119 = Utf8               ScalaSig
{
  public static scala.collection.mutable.Set makeSet$(scala.collection.mutable.MultiMap);
    descriptor: (Lscala/collection/mutable/MultiMap;)Lscala/collection/mutable/Set;
    flags: (0x1009) ACC_PUBLIC, ACC_STATIC, ACC_SYNTHETIC
    Code:
      stack=1, locals=1, args_size=1
         0: aload_0
         1: invokespecial #18                 // InterfaceMethod makeSet:()Lscala/collection/mutable/Set;
         4: areturn
      LineNumberTable:
        line 63: 0
      LocalVariableTable:
        Start  Length  Slot  Name   Signature
            0       5     0 $this   Lscala/collection/mutable/MultiMap;
    MethodParameters:
      Name                           Flags
      $this                          final synthetic

  public default scala.collection.mutable.Set<V> makeSet();
    descriptor: ()Lscala/collection/mutable/Set;
    flags: (0x0001) ACC_PUBLIC
    Code:
      stack=2, locals=1, args_size=1
         0: new           #22                 // class scala/collection/mutable/HashSet
         3: dup
         4: invokespecial #26                 // Method scala/collection/mutable/HashSet."<init>":()V
         7: areturn
      LineNumberTable:
        line 63: 0
      LocalVariableTable:
        Start  Length  Slot  Name   Signature
            0       8     0  this   Lscala/collection/mutable/MultiMap;
    Signature: #20                          // ()Lscala/collection/mutable/Set<TV;>;

  public static scala.collection.mutable.MultiMap addBinding$(scala.collection.mutable.MultiMap, java.lang.Object, java.lang.Object);
    descriptor: (Lscala/collection/mutable/MultiMap;Ljava/lang/Object;Ljava/lang/Object;)Lscala/collection/mutable/MultiMap;
    flags: (0x1009) ACC_PUBLIC, ACC_STATIC, ACC_SYNTHETIC
    Code:
      stack=3, locals=3, args_size=3
         0: aload_0
         1: aload_1
         2: aload_2
         3: invokespecial #35                 // InterfaceMethod addBinding:(Ljava/lang/Object;Ljava/lang/Object;)Lscala/collection/mutable/MultiMap;
         6: areturn
      LineNumberTable:
        line 73: 0
      LocalVariableTable:
        Start  Length  Slot  Name   Signature
            0       7     0 $this   Lscala/collection/mutable/MultiMap;
            0       7     1   key   Ljava/lang/Object;
            0       7     2 value   Ljava/lang/Object;
    MethodParameters:
      Name                           Flags
      $this                          final synthetic
      key                            final
      value                          final

  public default scala.collection.mutable.MultiMap<K, V> addBinding(K, V);
    descriptor: (Ljava/lang/Object;Ljava/lang/Object;)Lscala/collection/mutable/MultiMap;
    flags: (0x0001) ACC_PUBLIC
    Code:
      stack=3, locals=6, args_size=3
         0: aload_0
         1: aload_1
         2: invokeinterface #41,  2           // InterfaceMethod get:(Ljava/lang/Object;)Lscala/Option;
         7: astore_3
         8: getstatic     #47                 // Field scala/None$.MODULE$:Lscala/None$;
        11: aload_3
        12: invokevirtual #51                 // Method java/lang/Object.equals:(Ljava/lang/Object;)Z
        15: ifeq          54
        18: aload_0
        19: invokeinterface #18,  1           // InterfaceMethod makeSet:()Lscala/collection/mutable/Set;
        24: astore        4
        26: aload         4
        28: ifnonnull     33
        31: aconst_null
        32: athrow
        33: aload         4
        35: aload_2
        36: invokeinterface #57,  2           // InterfaceMethod scala/collection/mutable/Growable.addOne:(Ljava/lang/Object;)Lscala/collection/mutable/Growable;
        41: pop
        42: aload_0
        43: aload_1
        44: aload         4
        46: invokeinterface #61,  3           // InterfaceMethod update:(Ljava/lang/Object;Ljava/lang/Object;)V
        51: goto          101
        54: aload_3
        55: instanceof    #63                 // class scala/Some
        58: ifeq          92
        61: aload_3
        62: checkcast     #63                 // class scala/Some
        65: invokevirtual #66                 // Method scala/Some.value:()Ljava/lang/Object;
        68: checkcast     #68                 // class scala/collection/mutable/Set
        71: astore        5
        73: aload         5
        75: ifnonnull     80
        78: aconst_null
        79: athrow
        80: aload         5
        82: aload_2
        83: invokeinterface #57,  2           // InterfaceMethod scala/collection/mutable/Growable.addOne:(Ljava/lang/Object;)Lscala/collection/mutable/Growable;
        88: pop
        89: goto          101
        92: new           #70                 // class scala/MatchError
        95: dup
        96: aload_3
        97: invokespecial #73                 // Method scala/MatchError."<init>":(Ljava/lang/Object;)V
       100: athrow
       101: aload_0
       102: areturn
      StackMapTable: number_of_entries = 5
        frame_type = 253 /* append */
          offset_delta = 33
          locals = [ class scala/Option, class scala/collection/mutable/Set ]
        frame_type = 250 /* chop */
          offset_delta = 20
        frame_type = 253 /* append */
          offset_delta = 25
          locals = [ top, class scala/collection/mutable/Set ]
        frame_type = 249 /* chop */
          offset_delta = 11
        frame_type = 8 /* same */
      LineNumberTable:
        line 74: 0
        line 75: 8
        line 76: 18
        line 77: 26
        line 78: 42
        line 79: 54
        line 80: 73
        line 74: 92
        line 82: 101
      LocalVariableTable:
        Start  Length  Slot  Name   Signature
           26      25     4   set   Lscala/collection/mutable/Set;
           73      19     5   set   Lscala/collection/mutable/Set;
            0     103     0  this   Lscala/collection/mutable/MultiMap;
            0     103     1   key   Ljava/lang/Object;
            0     103     2 value   Ljava/lang/Object;
    Signature: #37                          // (TK;TV;)Lscala/collection/mutable/MultiMap<TK;TV;>;
    MethodParameters:
      Name                           Flags
      key                            final
      value                          final

  public static scala.collection.mutable.MultiMap removeBinding$(scala.collection.mutable.MultiMap, java.lang.Object, java.lang.Object);
    descriptor: (Lscala/collection/mutable/MultiMap;Ljava/lang/Object;Ljava/lang/Object;)Lscala/collection/mutable/MultiMap;
    flags: (0x1009) ACC_PUBLIC, ACC_STATIC, ACC_SYNTHETIC
    Code:
      stack=3, locals=3, args_size=3
         0: aload_0
         1: aload_1
         2: aload_2
         3: invokespecial #81                 // InterfaceMethod removeBinding:(Ljava/lang/Object;Ljava/lang/Object;)Lscala/collection/mutable/MultiMap;
         6: areturn
      LineNumberTable:
        line 95: 0
      LocalVariableTable:
        Start  Length  Slot  Name   Signature
            0       7     0 $this   Lscala/collection/mutable/MultiMap;
            0       7     1   key   Ljava/lang/Object;
            0       7     2 value   Ljava/lang/Object;
    MethodParameters:
      Name                           Flags
      $this                          final synthetic
      key                            final
      value                          final

  public default scala.collection.mutable.MultiMap<K, V> removeBinding(K, V);
    descriptor: (Ljava/lang/Object;Ljava/lang/Object;)Lscala/collection/mutable/MultiMap;
    flags: (0x0001) ACC_PUBLIC
    Code:
      stack=3, locals=5, args_size=3
         0: aload_0
         1: aload_1
         2: invokeinterface #41,  2           // InterfaceMethod get:(Ljava/lang/Object;)Lscala/Option;
         7: astore_3
         8: getstatic     #47                 // Field scala/None$.MODULE$:Lscala/None$;
        11: aload_3
        12: invokevirtual #51                 // Method java/lang/Object.equals:(Ljava/lang/Object;)Z
        15: ifne          83
        18: aload_3
        19: instanceof    #63                 // class scala/Some
        22: ifeq          74
        25: aload_3
        26: checkcast     #63                 // class scala/Some
        29: invokevirtual #66                 // Method scala/Some.value:()Ljava/lang/Object;
        32: checkcast     #68                 // class scala/collection/mutable/Set
        35: astore        4
        37: aload         4
        39: ifnonnull     44
        42: aconst_null
        43: athrow
        44: aload         4
        46: aload_2
        47: invokeinterface #87,  2           // InterfaceMethod scala/collection/mutable/Shrinkable.subtractOne:(Ljava/lang/Object;)Lscala/collection/mutable/Shrinkable;
        52: pop
        53: aload         4
        55: invokeinterface #91,  1           // InterfaceMethod scala/collection/mutable/Set.isEmpty:()Z
        60: ifeq          83
        63: aload_0
        64: aload_1
        65: invokeinterface #87,  2           // InterfaceMethod scala/collection/mutable/Shrinkable.subtractOne:(Ljava/lang/Object;)Lscala/collection/mutable/Shrinkable;
        70: pop
        71: goto          83
        74: new           #70                 // class scala/MatchError
        77: dup
        78: aload_3
        79: invokespecial #73                 // Method scala/MatchError."<init>":(Ljava/lang/Object;)V
        82: athrow
        83: aload_0
        84: areturn
      StackMapTable: number_of_entries = 3
        frame_type = 253 /* append */
          offset_delta = 44
          locals = [ class scala/Option, class scala/collection/mutable/Set ]
        frame_type = 250 /* chop */
          offset_delta = 29
        frame_type = 8 /* same */
      LineNumberTable:
        line 96: 0
        line 97: 8
        line 98: 18
        line 99: 37
        line 100: 53
        line 96: 74
        line 102: 83
      LocalVariableTable:
        Start  Length  Slot  Name   Signature
           37      37     4   set   Lscala/collection/mutable/Set;
            0      85     0  this   Lscala/collection/mutable/MultiMap;
            0      85     1   key   Ljava/lang/Object;
            0      85     2 value   Ljava/lang/Object;
    Signature: #37                          // (TK;TV;)Lscala/collection/mutable/MultiMap<TK;TV;>;
    MethodParameters:
      Name                           Flags
      key                            final
      value                          final

  public static boolean entryExists$(scala.collection.mutable.MultiMap, java.lang.Object, scala.Function1);
    descriptor: (Lscala/collection/mutable/MultiMap;Ljava/lang/Object;Lscala/Function1;)Z
    flags: (0x1009) ACC_PUBLIC, ACC_STATIC, ACC_SYNTHETIC
    Code:
      stack=3, locals=3, args_size=3
         0: aload_0
         1: aload_1
         2: aload_2
         3: invokespecial #98                 // InterfaceMethod entryExists:(Ljava/lang/Object;Lscala/Function1;)Z
         6: ireturn
      LineNumberTable:
        line 111: 0
      LocalVariableTable:
        Start  Length  Slot  Name   Signature
            0       7     0 $this   Lscala/collection/mutable/MultiMap;
            0       7     1   key   Ljava/lang/Object;
            0       7     2     p   Lscala/Function1;
    MethodParameters:
      Name                           Flags
      $this                          final synthetic
      key                            final
      p                              final

  public default boolean entryExists(K, scala.Function1<V, java.lang.Object>);
    descriptor: (Ljava/lang/Object;Lscala/Function1;)Z
    flags: (0x0001) ACC_PUBLIC
    Code:
      stack=3, locals=5, args_size=3
         0: aload_0
         1: aload_1
         2: invokeinterface #41,  2           // InterfaceMethod get:(Ljava/lang/Object;)Lscala/Option;
         7: astore        4
         9: getstatic     #47                 // Field scala/None$.MODULE$:Lscala/None$;
        12: aload         4
        14: invokevirtual #51                 // Method java/lang/Object.equals:(Ljava/lang/Object;)Z
        17: ifeq          25
        20: iconst_0
        21: istore_3
        22: goto          64
        25: aload         4
        27: instanceof    #63                 // class scala/Some
        30: ifeq          54
        33: aload         4
        35: checkcast     #63                 // class scala/Some
        38: invokevirtual #66                 // Method scala/Some.value:()Ljava/lang/Object;
        41: checkcast     #68                 // class scala/collection/mutable/Set
        44: aload_2
        45: invokeinterface #104,  2          // InterfaceMethod scala/collection/mutable/Set.exists:(Lscala/Function1;)Z
        50: istore_3
        51: goto          64
        54: new           #70                 // class scala/MatchError
        57: dup
        58: aload         4
        60: invokespecial #73                 // Method scala/MatchError."<init>":(Ljava/lang/Object;)V
        63: athrow
        64: iload_3
        65: ireturn
      StackMapTable: number_of_entries = 3
        frame_type = 253 /* append */
          offset_delta = 25
          locals = [ top, class scala/Option ]
        frame_type = 28 /* same */
        frame_type = 255 /* full_frame */
          offset_delta = 9
          locals = [ class scala/collection/mutable/MultiMap, class java/lang/Object, class scala/Function1, int, class scala/Option ]
          stack = []
      LineNumberTable:
        line 111: 0
        line 112: 9
        line 113: 25
        line 111: 54
      LocalVariableTable:
        Start  Length  Slot  Name   Signature
            0      66     0  this   Lscala/collection/mutable/MultiMap;
            0      66     1   key   Ljava/lang/Object;
            0      66     2     p   Lscala/Function1;
    Signature: #100                         // (TK;Lscala/Function1<TV;Ljava/lang/Object;>;)Z
    MethodParameters:
      Name                           Flags
      key                            final
      p                              final

  public static void $init$(scala.collection.mutable.MultiMap);
    descriptor: (Lscala/collection/mutable/MultiMap;)V
    flags: (0x0009) ACC_PUBLIC, ACC_STATIC
    Code:
      stack=0, locals=1, args_size=1
         0: return
      LineNumberTable:
        line 54: 0
      LocalVariableTable:
        Start  Length  Slot  Name   Signature
            0       1     0 $this   Lscala/collection/mutable/MultiMap;
    MethodParameters:
      Name                           Flags
      $this                          final synthetic
}
Signature: #3                           // <K:Ljava/lang/Object;V:Ljava/lang/Object;>Ljava/lang/Object;Lscala/collection/mutable/Map<TK;Lscala/collection/mutable/Set<TV;>;>;
SourceFile: "MultiMap.scala"
Deprecated: true
RuntimeVisibleAnnotations:
  0: #9(#10=s#11)
    scala.reflect.ScalaSignature(
      bytes="\u0006\u0005A3qAB\u0004\u0011\u0002\u0007\u0005a\u0002C\u0003*\u0001\u0011\u0005!\u0006C\u0003/\u0001\u0011Eq\u0006C\u00031\u0001\u0011\u0005\u0011\u0007C\u00038\u0001\u0011\u0005\u0001\bC\u0003<\u0001\u0011\u0005AH\u0001\u0005Nk2$\u0018.T1q\u0015\tA\u0011\"A\u0004nkR\f\'\r\\3\u000b\u0005)Y\u0011AC2pY2,7\r^5p]*\tA\"A\u0003tG\u0006d\u0017m\u0001\u0001\u0016\u0007=QreE\u0002\u0001!Q\u0001\"!\u0005\n\u000e\u0003-I!aE\u0006\u0003\r\u0005s\u0017PU3g!\u0011)b\u0003G\u0012\u000e\u0003\u001dI!aF\u0004\u0003\u00075\u000b\u0007\u000f\u0005\u0002\u001a51\u0001A!B\u000e\u0001\u0005\u0004a\"!A&\u0012\u0005u\u0001\u0003CA\t\u001f\u0013\ty2BA\u0004O_RD\u0017N\\4\u0011\u0005E\t\u0013B\u0001\u0012\f\u0005\r\te.\u001f\t\u0004+\u00112\u0013BA\u0013\b\u0005\r\u0019V\r\u001e\t\u00033\u001d\"Q\u0001\u000b\u0001C\u0002q\u0011\u0011AV\u0001\u0007I%t\u0017\u000e\u001e\u0013\u0015\u0003-\u0002\"!\u0005\u0017\n\u00055Z!\u0001B+oSR\fq!\\1lKN+G/F\u0001$\u0003)\tG\r\u001a\"j]\u0012Lgn\u001a\u000b\u0004eM*T\"\u0001\u0001\t\u000bQ\u001a\u0001\u0019\u0001\r\u0002\u0007-,\u0017\u0010C\u00037\u0007\u0001\u0007a%A\u0003wC2,X-A\u0007sK6|g/\u001a\"j]\u0012Lgn\u001a\u000b\u0004eeR\u0004\"\u0002\u001b\u0005\u0001\u0004A\u0002\"\u0002\u001c\u0005\u0001\u00041\u0013aC3oiJLX\t_5tiN$2!\u0010!B!\t\tb(\u0003\u0002@\u0017\t9!i\\8mK\u0006t\u0007\"\u0002\u001b\u0006\u0001\u0004A\u0002\"\u0002\"\u0006\u0001\u0004\u0019\u0015!\u00019\u0011\tE!e%P\u0005\u0003\u000b.\u0011\u0011BR;oGRLwN\\\u0019)\r\u00019%jS\'O!\t\t\u0002*\u0003\u0002J\u0017\tQA-\u001a9sK\u000e\fG/\u001a3\u0002\u000f5,7o]1hK\u0006\nA*A(Vg\u0016\u0004\u0013\rI:dC2\fgfY8mY\u0016\u001cG/[8o]5,H/\u00192mK:jU\u000f\u001c;j\t&\u001cG\u000fI5oAQDW\rI:dC2\fWfY8mY\u0016\u001cG/[8o[\r|g\u000e\u001e:jE\u0002jw\u000eZ;mK\u0006)1/\u001b8dK\u0006\nq*\u0001\u00043]E\u001ad\u0006\r"
    )
  ScalaInlineInfo: length = 0x31 (unknown attribute)
   01 00 00 09 00 6B 00 6C 01 00 20 00 21 00 00 1C
   00 1D 01 00 5F 00 60 00 00 5C 00 5D 01 00 0F 00
   10 00 00 0C 00 0D 01 00 4F 00 21 00 00 4E 00 1D
   01
  ScalaSig: length = 0x3 (unknown attribute)
   05 02 00
