Classfile /Users/mw/Projects/slang-braindump/.jar/jar8/assemble/slang-braindump/assemble/content/scala/collection/mutable/package$.class
  Last modified May 29, 2022; size 1194 bytes
  SHA-256 checksum 8dca066d16fb948611c4b799f82d475d925731ab5fea4d1456905dd3e9b91625
  Compiled from "package.scala"
public final class scala.collection.mutable.package$
  minor version: 0
  major version: 52
  flags: (0x0031) ACC_PUBLIC, ACC_FINAL, ACC_SUPER
  this_class: #2                          // scala/collection/mutable/package$
  super_class: #4                         // java/lang/Object
  interfaces: 0, fields: 4, methods: 5, attributes: 3
Constant pool:
   #1 = Utf8               scala/collection/mutable/package$
   #2 = Class              #1             // scala/collection/mutable/package$
   #3 = Utf8               java/lang/Object
   #4 = Class              #3             // java/lang/Object
   #5 = Utf8               package.scala
   #6 = Utf8               MODULE$
   #7 = Utf8               Lscala/collection/mutable/package$;
   #8 = Utf8               WrappedArray
   #9 = Utf8               Lscala/collection/mutable/ArraySeq$;
  #10 = Utf8               Traversable
  #11 = Utf8               Lscala/collection/mutable/Iterable$;
  #12 = Utf8               ArrayStack
  #13 = Utf8               Lscala/collection/mutable/Stack$;
  #14 = Utf8               <clinit>
  #15 = Utf8               ()V
  #16 = Utf8               <init>
  #17 = NameAndType        #16:#15        // "<init>":()V
  #18 = Methodref          #2.#17         // scala/collection/mutable/package$."<init>":()V
  #19 = NameAndType        #6:#7          // MODULE$:Lscala/collection/mutable/package$;
  #20 = Fieldref           #2.#19         // scala/collection/mutable/package$.MODULE$:Lscala/collection/mutable/package$;
  #21 = Utf8               scala/collection/mutable/ArraySeq$
  #22 = Class              #21            // scala/collection/mutable/ArraySeq$
  #23 = NameAndType        #6:#9          // MODULE$:Lscala/collection/mutable/ArraySeq$;
  #24 = Fieldref           #22.#23        // scala/collection/mutable/ArraySeq$.MODULE$:Lscala/collection/mutable/ArraySeq$;
  #25 = NameAndType        #8:#9          // WrappedArray:Lscala/collection/mutable/ArraySeq$;
  #26 = Fieldref           #2.#25         // scala/collection/mutable/package$.WrappedArray:Lscala/collection/mutable/ArraySeq$;
  #27 = Utf8               scala/collection/mutable/Iterable$
  #28 = Class              #27            // scala/collection/mutable/Iterable$
  #29 = NameAndType        #6:#11         // MODULE$:Lscala/collection/mutable/Iterable$;
  #30 = Fieldref           #28.#29        // scala/collection/mutable/Iterable$.MODULE$:Lscala/collection/mutable/Iterable$;
  #31 = NameAndType        #10:#11        // Traversable:Lscala/collection/mutable/Iterable$;
  #32 = Fieldref           #2.#31         // scala/collection/mutable/package$.Traversable:Lscala/collection/mutable/Iterable$;
  #33 = Utf8               scala/collection/mutable/Stack$
  #34 = Class              #33            // scala/collection/mutable/Stack$
  #35 = NameAndType        #6:#13         // MODULE$:Lscala/collection/mutable/Stack$;
  #36 = Fieldref           #34.#35        // scala/collection/mutable/Stack$.MODULE$:Lscala/collection/mutable/Stack$;
  #37 = NameAndType        #12:#13        // ArrayStack:Lscala/collection/mutable/Stack$;
  #38 = Fieldref           #2.#37         // scala/collection/mutable/package$.ArrayStack:Lscala/collection/mutable/Stack$;
  #39 = Utf8               ()Lscala/collection/mutable/ArraySeq$;
  #40 = Utf8               this
  #41 = Utf8               ()Lscala/collection/mutable/Iterable$;
  #42 = Utf8               ()Lscala/collection/mutable/Stack$;
  #43 = Methodref          #4.#17         // java/lang/Object."<init>":()V
  #44 = Utf8               Deprecated
  #45 = Utf8               Code
  #46 = Utf8               LineNumberTable
  #47 = Utf8               LocalVariableTable
  #48 = Utf8               SourceFile
  #49 = Utf8               ScalaInlineInfo
  #50 = Utf8               Scala
{
  public static final scala.collection.mutable.package$ MODULE$;
    descriptor: Lscala/collection/mutable/package$;
    flags: (0x0019) ACC_PUBLIC, ACC_STATIC, ACC_FINAL

  private static final scala.collection.mutable.ArraySeq$ WrappedArray;
    descriptor: Lscala/collection/mutable/ArraySeq$;
    flags: (0x001a) ACC_PRIVATE, ACC_STATIC, ACC_FINAL
    Deprecated: true

  private static final scala.collection.mutable.Iterable$ Traversable;
    descriptor: Lscala/collection/mutable/Iterable$;
    flags: (0x001a) ACC_PRIVATE, ACC_STATIC, ACC_FINAL
    Deprecated: true

  private static final scala.collection.mutable.Stack$ ArrayStack;
    descriptor: Lscala/collection/mutable/Stack$;
    flags: (0x001a) ACC_PRIVATE, ACC_STATIC, ACC_FINAL
    Deprecated: true

  public static {};
    descriptor: ()V
    flags: (0x0009) ACC_PUBLIC, ACC_STATIC
    Code:
      stack=2, locals=0, args_size=0
         0: new           #2                  // class scala/collection/mutable/package$
         3: dup
         4: invokespecial #18                 // Method "<init>":()V
         7: putstatic     #20                 // Field MODULE$:Lscala/collection/mutable/package$;
        10: getstatic     #24                 // Field scala/collection/mutable/ArraySeq$.MODULE$:Lscala/collection/mutable/ArraySeq$;
        13: putstatic     #26                 // Field WrappedArray:Lscala/collection/mutable/ArraySeq$;
        16: getstatic     #30                 // Field scala/collection/mutable/Iterable$.MODULE$:Lscala/collection/mutable/Iterable$;
        19: putstatic     #32                 // Field Traversable:Lscala/collection/mutable/Iterable$;
        22: getstatic     #36                 // Field scala/collection/mutable/Stack$.MODULE$:Lscala/collection/mutable/Stack$;
        25: putstatic     #38                 // Field ArrayStack:Lscala/collection/mutable/Stack$;
        28: return
      LineNumberTable:
        line 16: 0
        line 20: 10
        line 24: 16
        line 28: 22
        line 16: 28

  public scala.collection.mutable.ArraySeq$ WrappedArray();
    descriptor: ()Lscala/collection/mutable/ArraySeq$;
    flags: (0x0001) ACC_PUBLIC
    Code:
      stack=1, locals=1, args_size=1
         0: getstatic     #26                 // Field WrappedArray:Lscala/collection/mutable/ArraySeq$;
         3: areturn
      LineNumberTable:
        line 20: 0
      LocalVariableTable:
        Start  Length  Slot  Name   Signature
            0       4     0  this   Lscala/collection/mutable/package$;
    Deprecated: true

  public scala.collection.mutable.Iterable$ Traversable();
    descriptor: ()Lscala/collection/mutable/Iterable$;
    flags: (0x0001) ACC_PUBLIC
    Code:
      stack=1, locals=1, args_size=1
         0: getstatic     #32                 // Field Traversable:Lscala/collection/mutable/Iterable$;
         3: areturn
      LineNumberTable:
        line 24: 0
      LocalVariableTable:
        Start  Length  Slot  Name   Signature
            0       4     0  this   Lscala/collection/mutable/package$;
    Deprecated: true

  public scala.collection.mutable.Stack$ ArrayStack();
    descriptor: ()Lscala/collection/mutable/Stack$;
    flags: (0x0001) ACC_PUBLIC
    Code:
      stack=1, locals=1, args_size=1
         0: getstatic     #38                 // Field ArrayStack:Lscala/collection/mutable/Stack$;
         3: areturn
      LineNumberTable:
        line 28: 0
      LocalVariableTable:
        Start  Length  Slot  Name   Signature
            0       4     0  this   Lscala/collection/mutable/package$;
    Deprecated: true

  private scala.collection.mutable.package$();
    descriptor: ()V
    flags: (0x0002) ACC_PRIVATE
    Code:
      stack=1, locals=1, args_size=1
         0: aload_0
         1: invokespecial #43                 // Method java/lang/Object."<init>":()V
         4: return
      LineNumberTable:
        line 16: 0
      LocalVariableTable:
        Start  Length  Slot  Name   Signature
            0       5     0  this   Lscala/collection/mutable/package$;
}
SourceFile: "package.scala"
  ScalaInlineInfo: length = 0x18 (unknown attribute)
   01 01 00 04 00 10 00 0F 01 00 0C 00 2A 01 00 0A
   00 29 01 00 08 00 27 01
  Scala: length = 0x0 (unknown attribute)

