Classfile /Users/mw/Projects/slang-braindump/.jar/jar8/assemble/slang-braindump/assemble/content/scala/collection/mutable/SeqMap$.class
  Last modified May 29, 2022; size 955 bytes
  SHA-256 checksum 3a7c9493e8288f83c74d1d6c1b7dcf70d9cb7984f3e0b8998f9e2e2ea44cebc2
  Compiled from "SeqMap.scala"
public final class scala.collection.mutable.SeqMap$ extends scala.collection.MapFactory$Delegate<scala.collection.mutable.SeqMap>
  minor version: 0
  major version: 52
  flags: (0x0031) ACC_PUBLIC, ACC_FINAL, ACC_SUPER
  this_class: #2                          // scala/collection/mutable/SeqMap$
  super_class: #5                         // scala/collection/MapFactory$Delegate
  interfaces: 0, fields: 1, methods: 3, attributes: 5
Constant pool:
   #1 = Utf8               scala/collection/mutable/SeqMap$
   #2 = Class              #1             // scala/collection/mutable/SeqMap$
   #3 = Utf8               Lscala/collection/MapFactory$Delegate<Lscala/collection/mutable/SeqMap;>;
   #4 = Utf8               scala/collection/MapFactory$Delegate
   #5 = Class              #4             // scala/collection/MapFactory$Delegate
   #6 = Utf8               SeqMap.scala
   #7 = Utf8               scala/collection/MapFactory
   #8 = Class              #7             // scala/collection/MapFactory
   #9 = Utf8               Delegate
  #10 = Utf8               MODULE$
  #11 = Utf8               Lscala/collection/mutable/SeqMap$;
  #12 = Utf8               <clinit>
  #13 = Utf8               ()V
  #14 = Utf8               <init>
  #15 = NameAndType        #14:#13        // "<init>":()V
  #16 = Methodref          #2.#15         // scala/collection/mutable/SeqMap$."<init>":()V
  #17 = NameAndType        #10:#11        // MODULE$:Lscala/collection/mutable/SeqMap$;
  #18 = Fieldref           #2.#17         // scala/collection/mutable/SeqMap$.MODULE$:Lscala/collection/mutable/SeqMap$;
  #19 = Utf8               writeReplace
  #20 = Utf8               ()Ljava/lang/Object;
  #21 = Utf8               scala/runtime/ModuleSerializationProxy
  #22 = Class              #21            // scala/runtime/ModuleSerializationProxy
  #23 = Utf8               (Ljava/lang/Class;)V
  #24 = NameAndType        #14:#23        // "<init>":(Ljava/lang/Class;)V
  #25 = Methodref          #22.#24        // scala/runtime/ModuleSerializationProxy."<init>":(Ljava/lang/Class;)V
  #26 = Utf8               this
  #27 = Utf8               scala/collection/mutable/LinkedHashMap$
  #28 = Class              #27            // scala/collection/mutable/LinkedHashMap$
  #29 = Utf8               Lscala/collection/mutable/LinkedHashMap$;
  #30 = NameAndType        #10:#29        // MODULE$:Lscala/collection/mutable/LinkedHashMap$;
  #31 = Fieldref           #28.#30        // scala/collection/mutable/LinkedHashMap$.MODULE$:Lscala/collection/mutable/LinkedHashMap$;
  #32 = Utf8               (Lscala/collection/MapFactory;)V
  #33 = NameAndType        #14:#32        // "<init>":(Lscala/collection/MapFactory;)V
  #34 = Methodref          #5.#33         // scala/collection/MapFactory$Delegate."<init>":(Lscala/collection/MapFactory;)V
  #35 = Utf8               Code
  #36 = Utf8               LineNumberTable
  #37 = Utf8               LocalVariableTable
  #38 = Utf8               InnerClasses
  #39 = Utf8               Signature
  #40 = Utf8               SourceFile
  #41 = Utf8               ScalaInlineInfo
  #42 = Utf8               Scala
{
  public static final scala.collection.mutable.SeqMap$ MODULE$;
    descriptor: Lscala/collection/mutable/SeqMap$;
    flags: (0x0019) ACC_PUBLIC, ACC_STATIC, ACC_FINAL

  public static {};
    descriptor: ()V
    flags: (0x0009) ACC_PUBLIC, ACC_STATIC
    Code:
      stack=2, locals=0, args_size=0
         0: new           #2                  // class scala/collection/mutable/SeqMap$
         3: dup
         4: invokespecial #16                 // Method "<init>":()V
         7: putstatic     #18                 // Field MODULE$:Lscala/collection/mutable/SeqMap$;
        10: return
      LineNumberTable:
        line 38: 0

  private java.lang.Object writeReplace();
    descriptor: ()Ljava/lang/Object;
    flags: (0x0002) ACC_PRIVATE
    Code:
      stack=3, locals=1, args_size=1
         0: new           #22                 // class scala/runtime/ModuleSerializationProxy
         3: dup
         4: ldc           #2                  // class scala/collection/mutable/SeqMap$
         6: invokespecial #25                 // Method scala/runtime/ModuleSerializationProxy."<init>":(Ljava/lang/Class;)V
         9: areturn
      LineNumberTable:
        line 38: 0
      LocalVariableTable:
        Start  Length  Slot  Name   Signature
            0      10     0  this   Lscala/collection/mutable/SeqMap$;

  private scala.collection.mutable.SeqMap$();
    descriptor: ()V
    flags: (0x0002) ACC_PRIVATE
    Code:
      stack=2, locals=1, args_size=1
         0: aload_0
         1: getstatic     #31                 // Field scala/collection/mutable/LinkedHashMap$.MODULE$:Lscala/collection/mutable/LinkedHashMap$;
         4: invokespecial #34                 // Method scala/collection/MapFactory$Delegate."<init>":(Lscala/collection/MapFactory;)V
         7: return
      LineNumberTable:
        line 38: 0
      LocalVariableTable:
        Start  Length  Slot  Name   Signature
            0       8     0  this   Lscala/collection/mutable/SeqMap$;
}
InnerClasses:
  public static #9= #5 of #8;             // Delegate=class scala/collection/MapFactory$Delegate of class scala/collection/MapFactory
Signature: #3                           // Lscala/collection/MapFactory$Delegate<Lscala/collection/mutable/SeqMap;>;
SourceFile: "SeqMap.scala"
  ScalaInlineInfo: length = 0xE (unknown attribute)
   01 01 00 02 00 0E 00 0D 01 00 13 00 14 01
  Scala: length = 0x0 (unknown attribute)

