Classfile /Users/mw/Projects/slang-braindump/.jar/jar8/assemble/slang-braindump/assemble/content/scala/collection/mutable/UnrolledBuffer$Unrolled$.class
  Last modified May 29, 2022; size 753 bytes
  SHA-256 checksum 1ac623a9801822c9b3287d34e421b4bb506087084cf3037da2ab3bf84a6321e1
  Compiled from "UnrolledBuffer.scala"
public class scala.collection.mutable.UnrolledBuffer$Unrolled$
  minor version: 0
  major version: 52
  flags: (0x0021) ACC_PUBLIC, ACC_SUPER
  this_class: #2                          // scala/collection/mutable/UnrolledBuffer$Unrolled$
  super_class: #4                         // java/lang/Object
  interfaces: 0, fields: 1, methods: 3, attributes: 4
Constant pool:
   #1 = Utf8               scala/collection/mutable/UnrolledBuffer$Unrolled$
   #2 = Class              #1             // scala/collection/mutable/UnrolledBuffer$Unrolled$
   #3 = Utf8               java/lang/Object
   #4 = Class              #3             // java/lang/Object
   #5 = Utf8               UnrolledBuffer.scala
   #6 = Utf8               scala/collection/mutable/UnrolledBuffer
   #7 = Class              #6             // scala/collection/mutable/UnrolledBuffer
   #8 = Utf8               Unrolled$
   #9 = Utf8               MODULE$
  #10 = Utf8               Lscala/collection/mutable/UnrolledBuffer$Unrolled$;
  #11 = Utf8               <clinit>
  #12 = Utf8               ()V
  #13 = Utf8               <init>
  #14 = NameAndType        #13:#12        // "<init>":()V
  #15 = Methodref          #2.#14         // scala/collection/mutable/UnrolledBuffer$Unrolled$."<init>":()V
  #16 = NameAndType        #9:#10         // MODULE$:Lscala/collection/mutable/UnrolledBuffer$Unrolled$;
  #17 = Fieldref           #2.#16         // scala/collection/mutable/UnrolledBuffer$Unrolled$.MODULE$:Lscala/collection/mutable/UnrolledBuffer$Unrolled$;
  #18 = Utf8               $lessinit$greater$default$4
  #19 = Utf8               ()Lscala/runtime/Null$;
  #20 = Utf8               <T:Ljava/lang/Object;>()Lscala/runtime/Null$;
  #21 = Utf8               this
  #22 = Methodref          #4.#14         // java/lang/Object."<init>":()V
  #23 = Utf8               Code
  #24 = Utf8               LineNumberTable
  #25 = Utf8               LocalVariableTable
  #26 = Utf8               Signature
  #27 = Utf8               InnerClasses
  #28 = Utf8               SourceFile
  #29 = Utf8               ScalaInlineInfo
  #30 = Utf8               Scala
{
  public static final scala.collection.mutable.UnrolledBuffer$Unrolled$ MODULE$;
    descriptor: Lscala/collection/mutable/UnrolledBuffer$Unrolled$;
    flags: (0x0019) ACC_PUBLIC, ACC_STATIC, ACC_FINAL

  public static {};
    descriptor: ()V
    flags: (0x0009) ACC_PUBLIC, ACC_STATIC
    Code:
      stack=2, locals=0, args_size=0
         0: new           #2                  // class scala/collection/mutable/UnrolledBuffer$Unrolled$
         3: dup
         4: invokespecial #15                 // Method "<init>":()V
         7: putstatic     #17                 // Field MODULE$:Lscala/collection/mutable/UnrolledBuffer$Unrolled$;
        10: return
      LineNumberTable:
        line 260: 0

  public <T extends java.lang.Object> scala.runtime.Null$ $lessinit$greater$default$4();
    descriptor: ()Lscala/runtime/Null$;
    flags: (0x0001) ACC_PUBLIC
    Code:
      stack=1, locals=1, args_size=1
         0: aconst_null
         1: areturn
      LineNumberTable:
        line 260: 0
      LocalVariableTable:
        Start  Length  Slot  Name   Signature
            0       2     0  this   Lscala/collection/mutable/UnrolledBuffer$Unrolled$;
    Signature: #20                          // <T:Ljava/lang/Object;>()Lscala/runtime/Null$;

  public scala.collection.mutable.UnrolledBuffer$Unrolled$();
    descriptor: ()V
    flags: (0x0001) ACC_PUBLIC
    Code:
      stack=1, locals=1, args_size=1
         0: aload_0
         1: invokespecial #22                 // Method java/lang/Object."<init>":()V
         4: return
      LineNumberTable:
        line 260: 0
      LocalVariableTable:
        Start  Length  Slot  Name   Signature
            0       5     0  this   Lscala/collection/mutable/UnrolledBuffer$Unrolled$;
}
InnerClasses:
  public static #8= #2 of #7;             // Unrolled$=class scala/collection/mutable/UnrolledBuffer$Unrolled$ of class scala/collection/mutable/UnrolledBuffer
SourceFile: "UnrolledBuffer.scala"
  ScalaInlineInfo: length = 0xE (unknown attribute)
   01 01 00 02 00 12 00 13 01 00 0D 00 0C 01
  Scala: length = 0x0 (unknown attribute)

