Classfile /Users/mw/Projects/slang-braindump/.jar/jar8/assemble/slang-braindump/assemble/content/com/fasterxml/jackson/annotation/JsonIncludeProperties$Value.class
  Last modified May 29, 2022; size 4071 bytes
  SHA-256 checksum 4ea3cf49f5e21c571d955cc18e10e09e3587b29d29d8242df9e1b6e852bc3dcc
  Compiled from "JsonIncludeProperties.java"
public class com.fasterxml.jackson.annotation.JsonIncludeProperties$Value extends java.lang.Object implements com.fasterxml.jackson.annotation.JacksonAnnotationValue<com.fasterxml.jackson.annotation.JsonIncludeProperties>, java.io.Serializable
  minor version: 0
  major version: 50
  flags: (0x0021) ACC_PUBLIC, ACC_SUPER
  this_class: #4                          // com/fasterxml/jackson/annotation/JsonIncludeProperties$Value
  super_class: #19                        // java/lang/Object
  interfaces: 2, fields: 3, methods: 12, attributes: 3
Constant pool:
    #1 = Methodref          #19.#103      // java/lang/Object."<init>":()V
    #2 = Fieldref           #4.#104       // com/fasterxml/jackson/annotation/JsonIncludeProperties$Value._included:Ljava/util/Set;
    #3 = Fieldref           #4.#105       // com/fasterxml/jackson/annotation/JsonIncludeProperties$Value.ALL:Lcom/fasterxml/jackson/annotation/JsonIncludeProperties$Value;
    #4 = Class              #106          // com/fasterxml/jackson/annotation/JsonIncludeProperties$Value
    #5 = InterfaceMethodref #8.#107       // com/fasterxml/jackson/annotation/JsonIncludeProperties.value:()[Ljava/lang/String;
    #6 = Methodref          #4.#108       // com/fasterxml/jackson/annotation/JsonIncludeProperties$Value._asSet:([Ljava/lang/String;)Ljava/util/Set;
    #7 = Methodref          #4.#109       // com/fasterxml/jackson/annotation/JsonIncludeProperties$Value."<init>":(Ljava/util/Set;)V
    #8 = Class              #110          // com/fasterxml/jackson/annotation/JsonIncludeProperties
    #9 = Methodref          #4.#111       // com/fasterxml/jackson/annotation/JsonIncludeProperties$Value.getIncluded:()Ljava/util/Set;
   #10 = Class              #112          // java/util/HashSet
   #11 = Methodref          #10.#103      // java/util/HashSet."<init>":()V
   #12 = InterfaceMethodref #113.#114     // java/util/Set.iterator:()Ljava/util/Iterator;
   #13 = InterfaceMethodref #115.#116     // java/util/Iterator.hasNext:()Z
   #14 = InterfaceMethodref #115.#117     // java/util/Iterator.next:()Ljava/lang/Object;
   #15 = Class              #118          // java/lang/String
   #16 = InterfaceMethodref #113.#119     // java/util/Set.contains:(Ljava/lang/Object;)Z
   #17 = Methodref          #10.#120      // java/util/HashSet.add:(Ljava/lang/Object;)Z
   #18 = String             #121          // JsonIncludeProperties.Value(included=%s)
   #19 = Class              #122          // java/lang/Object
   #20 = Methodref          #15.#123      // java/lang/String.format:(Ljava/lang/String;[Ljava/lang/Object;)Ljava/lang/String;
   #21 = InterfaceMethodref #113.#124     // java/util/Set.size:()I
   #22 = Methodref          #19.#125      // java/lang/Object.getClass:()Ljava/lang/Class;
   #23 = Methodref          #4.#126       // com/fasterxml/jackson/annotation/JsonIncludeProperties$Value._equals:(Ljava/util/Set;Ljava/util/Set;)Z
   #24 = InterfaceMethodref #113.#127     // java/util/Set.equals:(Ljava/lang/Object;)Z
   #25 = Methodref          #128.#129     // java/util/Collections.emptySet:()Ljava/util/Set;
   #26 = Methodref          #10.#130      // java/util/HashSet."<init>":(I)V
   #27 = InterfaceMethodref #113.#120     // java/util/Set.add:(Ljava/lang/Object;)Z
   #28 = Class              #131          // com/fasterxml/jackson/annotation/JacksonAnnotationValue
   #29 = Class              #132          // java/io/Serializable
   #30 = Utf8               serialVersionUID
   #31 = Utf8               J
   #32 = Utf8               ConstantValue
   #33 = Long               1l
   #35 = Utf8               ALL
   #36 = Utf8               Value
   #37 = Utf8               InnerClasses
   #38 = Utf8               Lcom/fasterxml/jackson/annotation/JsonIncludeProperties$Value;
   #39 = Utf8               _included
   #40 = Utf8               Ljava/util/Set;
   #41 = Utf8               Signature
   #42 = Utf8               Ljava/util/Set<Ljava/lang/String;>;
   #43 = Utf8               <init>
   #44 = Utf8               (Ljava/util/Set;)V
   #45 = Utf8               Code
   #46 = Utf8               LineNumberTable
   #47 = Utf8               LocalVariableTable
   #48 = Utf8               this
   #49 = Utf8               included
   #50 = Utf8               LocalVariableTypeTable
   #51 = Utf8               (Ljava/util/Set<Ljava/lang/String;>;)V
   #52 = Utf8               from
   #53 = Utf8               (Lcom/fasterxml/jackson/annotation/JsonIncludeProperties;)Lcom/fasterxml/jackson/annotation/JsonIncludeProperties$Value;
   #54 = Utf8               src
   #55 = Utf8               Lcom/fasterxml/jackson/annotation/JsonIncludeProperties;
   #56 = Utf8               StackMapTable
   #57 = Utf8               all
   #58 = Utf8               ()Lcom/fasterxml/jackson/annotation/JsonIncludeProperties$Value;
   #59 = Utf8               valueFor
   #60 = Utf8               ()Ljava/lang/Class;
   #61 = Utf8               ()Ljava/lang/Class<Lcom/fasterxml/jackson/annotation/JsonIncludeProperties;>;
   #62 = Utf8               getIncluded
   #63 = Utf8               ()Ljava/util/Set;
   #64 = Utf8               ()Ljava/util/Set<Ljava/lang/String;>;
   #65 = Utf8               withOverrides
   #66 = Utf8               (Lcom/fasterxml/jackson/annotation/JsonIncludeProperties$Value;)Lcom/fasterxml/jackson/annotation/JsonIncludeProperties$Value;
   #67 = Utf8               otherIncluded
   #68 = Utf8               incl
   #69 = Utf8               Ljava/lang/String;
   #70 = Utf8               overrides
   #71 = Utf8               toInclude
   #72 = Utf8               Ljava/util/HashSet;
   #73 = Utf8               Ljava/util/HashSet<Ljava/lang/String;>;
   #74 = Class              #133          // java/util/Set
   #75 = Class              #112          // java/util/HashSet
   #76 = Class              #134          // java/util/Iterator
   #77 = Utf8               toString
   #78 = Utf8               ()Ljava/lang/String;
   #79 = Utf8               hashCode
   #80 = Utf8               ()I
   #81 = Utf8               equals
   #82 = Utf8               (Ljava/lang/Object;)Z
   #83 = Utf8               o
   #84 = Utf8               Ljava/lang/Object;
   #85 = Utf8               _equals
   #86 = Utf8               (Ljava/util/Set;Ljava/util/Set;)Z
   #87 = Utf8               a
   #88 = Utf8               b
   #89 = Utf8               (Ljava/util/Set<Ljava/lang/String;>;Ljava/util/Set<Ljava/lang/String;>;)Z
   #90 = Utf8               _asSet
   #91 = Utf8               ([Ljava/lang/String;)Ljava/util/Set;
   #92 = Utf8               str
   #93 = Utf8               v
   #94 = Utf8               [Ljava/lang/String;
   #95 = Utf8               s
   #96 = Class              #94           // "[Ljava/lang/String;"
   #97 = Utf8               ([Ljava/lang/String;)Ljava/util/Set<Ljava/lang/String;>;
   #98 = Utf8               <clinit>
   #99 = Utf8               ()V
  #100 = Utf8               Ljava/lang/Object;Lcom/fasterxml/jackson/annotation/JacksonAnnotationValue<Lcom/fasterxml/jackson/annotation/JsonIncludeProperties;>;Ljava/io/Serializable;
  #101 = Utf8               SourceFile
  #102 = Utf8               JsonIncludeProperties.java
  #103 = NameAndType        #43:#99       // "<init>":()V
  #104 = NameAndType        #39:#40       // _included:Ljava/util/Set;
  #105 = NameAndType        #35:#38       // ALL:Lcom/fasterxml/jackson/annotation/JsonIncludeProperties$Value;
  #106 = Utf8               com/fasterxml/jackson/annotation/JsonIncludeProperties$Value
  #107 = NameAndType        #135:#136     // value:()[Ljava/lang/String;
  #108 = NameAndType        #90:#91       // _asSet:([Ljava/lang/String;)Ljava/util/Set;
  #109 = NameAndType        #43:#44       // "<init>":(Ljava/util/Set;)V
  #110 = Utf8               com/fasterxml/jackson/annotation/JsonIncludeProperties
  #111 = NameAndType        #62:#63       // getIncluded:()Ljava/util/Set;
  #112 = Utf8               java/util/HashSet
  #113 = Class              #133          // java/util/Set
  #114 = NameAndType        #137:#138     // iterator:()Ljava/util/Iterator;
  #115 = Class              #134          // java/util/Iterator
  #116 = NameAndType        #139:#140     // hasNext:()Z
  #117 = NameAndType        #141:#142     // next:()Ljava/lang/Object;
  #118 = Utf8               java/lang/String
  #119 = NameAndType        #143:#82      // contains:(Ljava/lang/Object;)Z
  #120 = NameAndType        #144:#82      // add:(Ljava/lang/Object;)Z
  #121 = Utf8               JsonIncludeProperties.Value(included=%s)
  #122 = Utf8               java/lang/Object
  #123 = NameAndType        #145:#146     // format:(Ljava/lang/String;[Ljava/lang/Object;)Ljava/lang/String;
  #124 = NameAndType        #147:#80      // size:()I
  #125 = NameAndType        #148:#60      // getClass:()Ljava/lang/Class;
  #126 = NameAndType        #85:#86       // _equals:(Ljava/util/Set;Ljava/util/Set;)Z
  #127 = NameAndType        #81:#82       // equals:(Ljava/lang/Object;)Z
  #128 = Class              #149          // java/util/Collections
  #129 = NameAndType        #150:#63      // emptySet:()Ljava/util/Set;
  #130 = NameAndType        #43:#151      // "<init>":(I)V
  #131 = Utf8               com/fasterxml/jackson/annotation/JacksonAnnotationValue
  #132 = Utf8               java/io/Serializable
  #133 = Utf8               java/util/Set
  #134 = Utf8               java/util/Iterator
  #135 = Utf8               value
  #136 = Utf8               ()[Ljava/lang/String;
  #137 = Utf8               iterator
  #138 = Utf8               ()Ljava/util/Iterator;
  #139 = Utf8               hasNext
  #140 = Utf8               ()Z
  #141 = Utf8               next
  #142 = Utf8               ()Ljava/lang/Object;
  #143 = Utf8               contains
  #144 = Utf8               add
  #145 = Utf8               format
  #146 = Utf8               (Ljava/lang/String;[Ljava/lang/Object;)Ljava/lang/String;
  #147 = Utf8               size
  #148 = Utf8               getClass
  #149 = Utf8               java/util/Collections
  #150 = Utf8               emptySet
  #151 = Utf8               (I)V
{
  private static final long serialVersionUID;
    descriptor: J
    flags: (0x001a) ACC_PRIVATE, ACC_STATIC, ACC_FINAL
    ConstantValue: long 1l

  protected static final com.fasterxml.jackson.annotation.JsonIncludeProperties$Value ALL;
    descriptor: Lcom/fasterxml/jackson/annotation/JsonIncludeProperties$Value;
    flags: (0x001c) ACC_PROTECTED, ACC_STATIC, ACC_FINAL

  protected final java.util.Set<java.lang.String> _included;
    descriptor: Ljava/util/Set;
    flags: (0x0014) ACC_PROTECTED, ACC_FINAL
    Signature: #42                          // Ljava/util/Set<Ljava/lang/String;>;

  protected com.fasterxml.jackson.annotation.JsonIncludeProperties$Value(java.util.Set<java.lang.String>);
    descriptor: (Ljava/util/Set;)V
    flags: (0x0004) ACC_PROTECTED
    Code:
      stack=2, locals=2, args_size=2
         0: aload_0
         1: invokespecial #1                  // Method java/lang/Object."<init>":()V
         4: aload_0
         5: aload_1
         6: putfield      #2                  // Field _included:Ljava/util/Set;
         9: return
      LineNumberTable:
        line 66: 0
        line 67: 4
        line 68: 9
      LocalVariableTable:
        Start  Length  Slot  Name   Signature
            0      10     0  this   Lcom/fasterxml/jackson/annotation/JsonIncludeProperties$Value;
            0      10     1 included   Ljava/util/Set;
      LocalVariableTypeTable:
        Start  Length  Slot  Name   Signature
            0      10     1 included   Ljava/util/Set<Ljava/lang/String;>;
    Signature: #51                          // (Ljava/util/Set<Ljava/lang/String;>;)V

  public static com.fasterxml.jackson.annotation.JsonIncludeProperties$Value from(com.fasterxml.jackson.annotation.JsonIncludeProperties);
    descriptor: (Lcom/fasterxml/jackson/annotation/JsonIncludeProperties;)Lcom/fasterxml/jackson/annotation/JsonIncludeProperties$Value;
    flags: (0x0009) ACC_PUBLIC, ACC_STATIC
    Code:
      stack=3, locals=1, args_size=1
         0: aload_0
         1: ifnonnull     8
         4: getstatic     #3                  // Field ALL:Lcom/fasterxml/jackson/annotation/JsonIncludeProperties$Value;
         7: areturn
         8: new           #4                  // class com/fasterxml/jackson/annotation/JsonIncludeProperties$Value
        11: dup
        12: aload_0
        13: invokeinterface #5,  1            // InterfaceMethod com/fasterxml/jackson/annotation/JsonIncludeProperties.value:()[Ljava/lang/String;
        18: invokestatic  #6                  // Method _asSet:([Ljava/lang/String;)Ljava/util/Set;
        21: invokespecial #7                  // Method "<init>":(Ljava/util/Set;)V
        24: areturn
      LineNumberTable:
        line 72: 0
        line 73: 4
        line 75: 8
      LocalVariableTable:
        Start  Length  Slot  Name   Signature
            0      25     0   src   Lcom/fasterxml/jackson/annotation/JsonIncludeProperties;
      StackMapTable: number_of_entries = 1
        frame_type = 8 /* same */

  public static com.fasterxml.jackson.annotation.JsonIncludeProperties$Value all();
    descriptor: ()Lcom/fasterxml/jackson/annotation/JsonIncludeProperties$Value;
    flags: (0x0009) ACC_PUBLIC, ACC_STATIC
    Code:
      stack=1, locals=0, args_size=0
         0: getstatic     #3                  // Field ALL:Lcom/fasterxml/jackson/annotation/JsonIncludeProperties$Value;
         3: areturn
      LineNumberTable:
        line 80: 0

  public java.lang.Class<com.fasterxml.jackson.annotation.JsonIncludeProperties> valueFor();
    descriptor: ()Ljava/lang/Class;
    flags: (0x0001) ACC_PUBLIC
    Code:
      stack=1, locals=1, args_size=1
         0: ldc           #8                  // class com/fasterxml/jackson/annotation/JsonIncludeProperties
         2: areturn
      LineNumberTable:
        line 86: 0
      LocalVariableTable:
        Start  Length  Slot  Name   Signature
            0       3     0  this   Lcom/fasterxml/jackson/annotation/JsonIncludeProperties$Value;
    Signature: #61                          // ()Ljava/lang/Class<Lcom/fasterxml/jackson/annotation/JsonIncludeProperties;>;

  public java.util.Set<java.lang.String> getIncluded();
    descriptor: ()Ljava/util/Set;
    flags: (0x0001) ACC_PUBLIC
    Code:
      stack=1, locals=1, args_size=1
         0: aload_0
         1: getfield      #2                  // Field _included:Ljava/util/Set;
         4: areturn
      LineNumberTable:
        line 94: 0
      LocalVariableTable:
        Start  Length  Slot  Name   Signature
            0       5     0  this   Lcom/fasterxml/jackson/annotation/JsonIncludeProperties$Value;
    Signature: #64                          // ()Ljava/util/Set<Ljava/lang/String;>;

  public com.fasterxml.jackson.annotation.JsonIncludeProperties$Value withOverrides(com.fasterxml.jackson.annotation.JsonIncludeProperties$Value);
    descriptor: (Lcom/fasterxml/jackson/annotation/JsonIncludeProperties$Value;)Lcom/fasterxml/jackson/annotation/JsonIncludeProperties$Value;
    flags: (0x0001) ACC_PUBLIC
    Code:
      stack=3, locals=6, args_size=2
         0: aload_1
         1: ifnull        13
         4: aload_1
         5: invokevirtual #9                  // Method getIncluded:()Ljava/util/Set;
         8: dup
         9: astore_2
        10: ifnonnull     15
        13: aload_0
        14: areturn
        15: aload_0
        16: getfield      #2                  // Field _included:Ljava/util/Set;
        19: ifnonnull     24
        22: aload_1
        23: areturn
        24: new           #10                 // class java/util/HashSet
        27: dup
        28: invokespecial #11                 // Method java/util/HashSet."<init>":()V
        31: astore_3
        32: aload_2
        33: invokeinterface #12,  1           // InterfaceMethod java/util/Set.iterator:()Ljava/util/Iterator;
        38: astore        4
        40: aload         4
        42: invokeinterface #13,  1           // InterfaceMethod java/util/Iterator.hasNext:()Z
        47: ifeq          86
        50: aload         4
        52: invokeinterface #14,  1           // InterfaceMethod java/util/Iterator.next:()Ljava/lang/Object;
        57: checkcast     #15                 // class java/lang/String
        60: astore        5
        62: aload_0
        63: getfield      #2                  // Field _included:Ljava/util/Set;
        66: aload         5
        68: invokeinterface #16,  2           // InterfaceMethod java/util/Set.contains:(Ljava/lang/Object;)Z
        73: ifeq          83
        76: aload_3
        77: aload         5
        79: invokevirtual #17                 // Method java/util/HashSet.add:(Ljava/lang/Object;)Z
        82: pop
        83: goto          40
        86: new           #4                  // class com/fasterxml/jackson/annotation/JsonIncludeProperties$Value
        89: dup
        90: aload_3
        91: invokespecial #7                  // Method "<init>":(Ljava/util/Set;)V
        94: areturn
      LineNumberTable:
        line 109: 0
        line 110: 13
        line 113: 15
        line 114: 22
        line 117: 24
        line 118: 32
        line 119: 62
        line 120: 76
        line 122: 83
        line 124: 86
      LocalVariableTable:
        Start  Length  Slot  Name   Signature
           10       3     2 otherIncluded   Ljava/util/Set;
           62      21     5  incl   Ljava/lang/String;
            0      95     0  this   Lcom/fasterxml/jackson/annotation/JsonIncludeProperties$Value;
            0      95     1 overrides   Lcom/fasterxml/jackson/annotation/JsonIncludeProperties$Value;
           15      80     2 otherIncluded   Ljava/util/Set;
           32      63     3 toInclude   Ljava/util/HashSet;
      LocalVariableTypeTable:
        Start  Length  Slot  Name   Signature
           10       3     2 otherIncluded   Ljava/util/Set<Ljava/lang/String;>;
           15      80     2 otherIncluded   Ljava/util/Set<Ljava/lang/String;>;
           32      63     3 toInclude   Ljava/util/HashSet<Ljava/lang/String;>;
      StackMapTable: number_of_entries = 6
        frame_type = 13 /* same */
        frame_type = 252 /* append */
          offset_delta = 1
          locals = [ class java/util/Set ]
        frame_type = 8 /* same */
        frame_type = 253 /* append */
          offset_delta = 15
          locals = [ class java/util/HashSet, class java/util/Iterator ]
        frame_type = 42 /* same */
        frame_type = 250 /* chop */
          offset_delta = 2

  public java.lang.String toString();
    descriptor: ()Ljava/lang/String;
    flags: (0x0001) ACC_PUBLIC
    Code:
      stack=5, locals=1, args_size=1
         0: ldc           #18                 // String JsonIncludeProperties.Value(included=%s)
         2: iconst_1
         3: anewarray     #19                 // class java/lang/Object
         6: dup
         7: iconst_0
         8: aload_0
         9: getfield      #2                  // Field _included:Ljava/util/Set;
        12: aastore
        13: invokestatic  #20                 // Method java/lang/String.format:(Ljava/lang/String;[Ljava/lang/Object;)Ljava/lang/String;
        16: areturn
      LineNumberTable:
        line 129: 0
      LocalVariableTable:
        Start  Length  Slot  Name   Signature
            0      17     0  this   Lcom/fasterxml/jackson/annotation/JsonIncludeProperties$Value;

  public int hashCode();
    descriptor: ()I
    flags: (0x0001) ACC_PUBLIC
    Code:
      stack=1, locals=1, args_size=1
         0: aload_0
         1: getfield      #2                  // Field _included:Ljava/util/Set;
         4: ifnonnull     11
         7: iconst_0
         8: goto          20
        11: aload_0
        12: getfield      #2                  // Field _included:Ljava/util/Set;
        15: invokeinterface #21,  1           // InterfaceMethod java/util/Set.size:()I
        20: ireturn
      LineNumberTable:
        line 135: 0
      LocalVariableTable:
        Start  Length  Slot  Name   Signature
            0      21     0  this   Lcom/fasterxml/jackson/annotation/JsonIncludeProperties$Value;
      StackMapTable: number_of_entries = 2
        frame_type = 11 /* same */
        frame_type = 72 /* same_locals_1_stack_item */
          stack = [ int ]

  public boolean equals(java.lang.Object);
    descriptor: (Ljava/lang/Object;)Z
    flags: (0x0001) ACC_PUBLIC
    Code:
      stack=2, locals=2, args_size=2
         0: aload_1
         1: aload_0
         2: if_acmpne     7
         5: iconst_1
         6: ireturn
         7: aload_1
         8: ifnonnull     13
        11: iconst_0
        12: ireturn
        13: aload_1
        14: invokevirtual #22                 // Method java/lang/Object.getClass:()Ljava/lang/Class;
        17: aload_0
        18: invokevirtual #22                 // Method java/lang/Object.getClass:()Ljava/lang/Class;
        21: if_acmpne     45
        24: aload_0
        25: getfield      #2                  // Field _included:Ljava/util/Set;
        28: aload_1
        29: checkcast     #4                  // class com/fasterxml/jackson/annotation/JsonIncludeProperties$Value
        32: getfield      #2                  // Field _included:Ljava/util/Set;
        35: invokestatic  #23                 // Method _equals:(Ljava/util/Set;Ljava/util/Set;)Z
        38: ifeq          45
        41: iconst_1
        42: goto          46
        45: iconst_0
        46: ireturn
      LineNumberTable:
        line 140: 0
        line 141: 7
        line 142: 13
      LocalVariableTable:
        Start  Length  Slot  Name   Signature
            0      47     0  this   Lcom/fasterxml/jackson/annotation/JsonIncludeProperties$Value;
            0      47     1     o   Ljava/lang/Object;
      StackMapTable: number_of_entries = 4
        frame_type = 7 /* same */
        frame_type = 5 /* same */
        frame_type = 31 /* same */
        frame_type = 64 /* same_locals_1_stack_item */
          stack = [ int ]

  private static boolean _equals(java.util.Set<java.lang.String>, java.util.Set<java.lang.String>);
    descriptor: (Ljava/util/Set;Ljava/util/Set;)Z
    flags: (0x000a) ACC_PRIVATE, ACC_STATIC
    Code:
      stack=2, locals=2, args_size=2
         0: aload_0
         1: ifnonnull     16
         4: aload_1
         5: ifnonnull     12
         8: iconst_1
         9: goto          23
        12: iconst_0
        13: goto          23
        16: aload_0
        17: aload_1
        18: invokeinterface #24,  2           // InterfaceMethod java/util/Set.equals:(Ljava/lang/Object;)Z
        23: ireturn
      LineNumberTable:
        line 147: 0
        line 149: 18
        line 147: 23
      LocalVariableTable:
        Start  Length  Slot  Name   Signature
            0      24     0     a   Ljava/util/Set;
            0      24     1     b   Ljava/util/Set;
      LocalVariableTypeTable:
        Start  Length  Slot  Name   Signature
            0      24     0     a   Ljava/util/Set<Ljava/lang/String;>;
            0      24     1     b   Ljava/util/Set<Ljava/lang/String;>;
      StackMapTable: number_of_entries = 3
        frame_type = 12 /* same */
        frame_type = 3 /* same */
        frame_type = 70 /* same_locals_1_stack_item */
          stack = [ int ]
    Signature: #89                          // (Ljava/util/Set<Ljava/lang/String;>;Ljava/util/Set<Ljava/lang/String;>;)Z

  private static java.util.Set<java.lang.String> _asSet(java.lang.String[]);
    descriptor: ([Ljava/lang/String;)Ljava/util/Set;
    flags: (0x000a) ACC_PRIVATE, ACC_STATIC
    Code:
      stack=3, locals=6, args_size=1
         0: aload_0
         1: ifnull        9
         4: aload_0
         5: arraylength
         6: ifne          13
         9: invokestatic  #25                 // Method java/util/Collections.emptySet:()Ljava/util/Set;
        12: areturn
        13: new           #10                 // class java/util/HashSet
        16: dup
        17: aload_0
        18: arraylength
        19: invokespecial #26                 // Method java/util/HashSet."<init>":(I)V
        22: astore_1
        23: aload_0
        24: astore_2
        25: aload_2
        26: arraylength
        27: istore_3
        28: iconst_0
        29: istore        4
        31: iload         4
        33: iload_3
        34: if_icmpge     58
        37: aload_2
        38: iload         4
        40: aaload
        41: astore        5
        43: aload_1
        44: aload         5
        46: invokeinterface #27,  2           // InterfaceMethod java/util/Set.add:(Ljava/lang/Object;)Z
        51: pop
        52: iinc          4, 1
        55: goto          31
        58: aload_1
        59: areturn
      LineNumberTable:
        line 154: 0
        line 155: 9
        line 157: 13
        line 158: 23
        line 159: 43
        line 158: 52
        line 161: 58
      LocalVariableTable:
        Start  Length  Slot  Name   Signature
           43       9     5   str   Ljava/lang/String;
            0      60     0     v   [Ljava/lang/String;
           23      37     1     s   Ljava/util/Set;
      LocalVariableTypeTable:
        Start  Length  Slot  Name   Signature
           23      37     1     s   Ljava/util/Set<Ljava/lang/String;>;
      StackMapTable: number_of_entries = 4
        frame_type = 9 /* same */
        frame_type = 3 /* same */
        frame_type = 255 /* full_frame */
          offset_delta = 17
          locals = [ class "[Ljava/lang/String;", class java/util/Set, class "[Ljava/lang/String;", int, int ]
          stack = []
        frame_type = 248 /* chop */
          offset_delta = 26
    Signature: #97                          // ([Ljava/lang/String;)Ljava/util/Set<Ljava/lang/String;>;

  static {};
    descriptor: ()V
    flags: (0x0008) ACC_STATIC
    Code:
      stack=3, locals=0, args_size=0
         0: new           #4                  // class com/fasterxml/jackson/annotation/JsonIncludeProperties$Value
         3: dup
         4: aconst_null
         5: invokespecial #7                  // Method "<init>":(Ljava/util/Set;)V
         8: putstatic     #3                  // Field ALL:Lcom/fasterxml/jackson/annotation/JsonIncludeProperties$Value;
        11: return
      LineNumberTable:
        line 57: 0
}
Signature: #100                         // Ljava/lang/Object;Lcom/fasterxml/jackson/annotation/JacksonAnnotationValue<Lcom/fasterxml/jackson/annotation/JsonIncludeProperties;>;Ljava/io/Serializable;
SourceFile: "JsonIncludeProperties.java"
InnerClasses:
  public static #36= #4 of #8;            // Value=class com/fasterxml/jackson/annotation/JsonIncludeProperties$Value of class com/fasterxml/jackson/annotation/JsonIncludeProperties
