Classfile /Users/mw/Projects/slang-braindump/.jar/jar8/assemble/slang-braindump/assemble/content/coursier/ivy/Pattern$.class
  Last modified May 29, 2022; size 2855 bytes
  SHA-256 checksum 893e34639860f10707a62825bd1f76f03d08ce5294d3b7609ceea7edbd74e8b2
  Compiled from "Pattern.scala"
public final class coursier.ivy.Pattern$ implements java.io.Serializable
  minor version: 0
  major version: 52
  flags: (0x0031) ACC_PUBLIC, ACC_FINAL, ACC_SUPER
  this_class: #2                          // coursier/ivy/Pattern$
  super_class: #4                         // java/lang/Object
  interfaces: 1, fields: 2, methods: 5, attributes: 4
Constant pool:
    #1 = Utf8               coursier/ivy/Pattern$
    #2 = Class              #1            // coursier/ivy/Pattern$
    #3 = Utf8               java/lang/Object
    #4 = Class              #3            // java/lang/Object
    #5 = Utf8               java/io/Serializable
    #6 = Class              #5            // java/io/Serializable
    #7 = Utf8               Pattern.scala
    #8 = Utf8               coursier/ivy/Pattern$Chunk
    #9 = Class              #8            // coursier/ivy/Pattern$Chunk
   #10 = Utf8               coursier/ivy/Pattern
   #11 = Class              #10           // coursier/ivy/Pattern
   #12 = Utf8               Chunk
   #13 = Utf8               coursier/ivy/Pattern$Chunk$
   #14 = Class              #13           // coursier/ivy/Pattern$Chunk$
   #15 = Utf8
   #16 = Utf8               coursier/ivy/Pattern$Chunk$Opt
   #17 = Class              #16           // coursier/ivy/Pattern$Chunk$Opt
   #18 = Utf8               Opt
   #19 = Utf8               coursier/ivy/Pattern$Chunk$Opt$
   #20 = Class              #19           // coursier/ivy/Pattern$Chunk$Opt$
   #21 = Utf8               coursier/ivy/Pattern$Chunk$Var
   #22 = Class              #21           // coursier/ivy/Pattern$Chunk$Var
   #23 = Utf8               Var
   #24 = Utf8               coursier/ivy/Pattern$Chunk$Var$
   #25 = Class              #24           // coursier/ivy/Pattern$Chunk$Var$
   #26 = Utf8               MODULE$
   #27 = Utf8               Lcoursier/ivy/Pattern$;
   #28 = Utf8               default
   #29 = Utf8               Lcoursier/ivy/Pattern;
   #30 = Utf8               <clinit>
   #31 = Utf8               ()V
   #32 = Utf8               <init>
   #33 = NameAndType        #32:#31       // "<init>":()V
   #34 = Methodref          #2.#33        // coursier/ivy/Pattern$."<init>":()V
   #35 = NameAndType        #26:#27       // MODULE$:Lcoursier/ivy/Pattern$;
   #36 = Fieldref           #2.#35        // coursier/ivy/Pattern$.MODULE$:Lcoursier/ivy/Pattern$;
   #37 = Utf8               scala/collection/immutable/Seq$
   #38 = Class              #37           // scala/collection/immutable/Seq$
   #39 = Utf8               Lscala/collection/immutable/Seq$;
   #40 = NameAndType        #26:#39       // MODULE$:Lscala/collection/immutable/Seq$;
   #41 = Fieldref           #38.#40       // scala/collection/immutable/Seq$.MODULE$:Lscala/collection/immutable/Seq$;
   #42 = Utf8               scala/runtime/ScalaRunTime$
   #43 = Class              #42           // scala/runtime/ScalaRunTime$
   #44 = Utf8               Lscala/runtime/ScalaRunTime$;
   #45 = NameAndType        #26:#44       // MODULE$:Lscala/runtime/ScalaRunTime$;
   #46 = Fieldref           #43.#45       // scala/runtime/ScalaRunTime$.MODULE$:Lscala/runtime/ScalaRunTime$;
   #47 = Utf8               Lcoursier/ivy/Pattern$Chunk$Var$;
   #48 = NameAndType        #26:#47       // MODULE$:Lcoursier/ivy/Pattern$Chunk$Var$;
   #49 = Fieldref           #25.#48       // coursier/ivy/Pattern$Chunk$Var$.MODULE$:Lcoursier/ivy/Pattern$Chunk$Var$;
   #50 = Utf8               organisation
   #51 = String             #50           // organisation
   #52 = Utf8               apply
   #53 = Utf8               (Ljava/lang/String;)Lcoursier/ivy/Pattern$Chunk$Var;
   #54 = NameAndType        #52:#53       // apply:(Ljava/lang/String;)Lcoursier/ivy/Pattern$Chunk$Var;
   #55 = Methodref          #25.#54       // coursier/ivy/Pattern$Chunk$Var$.apply:(Ljava/lang/String;)Lcoursier/ivy/Pattern$Chunk$Var;
   #56 = Utf8               Lcoursier/ivy/Pattern$Chunk$;
   #57 = NameAndType        #26:#56       // MODULE$:Lcoursier/ivy/Pattern$Chunk$;
   #58 = Fieldref           #14.#57       // coursier/ivy/Pattern$Chunk$.MODULE$:Lcoursier/ivy/Pattern$Chunk$;
   #59 = Utf8               /
   #60 = String             #59           // /
   #61 = Utf8               fromString
   #62 = Utf8               (Ljava/lang/String;)Lcoursier/ivy/Pattern$Chunk;
   #63 = NameAndType        #61:#62       // fromString:(Ljava/lang/String;)Lcoursier/ivy/Pattern$Chunk;
   #64 = Methodref          #14.#63       // coursier/ivy/Pattern$Chunk$.fromString:(Ljava/lang/String;)Lcoursier/ivy/Pattern$Chunk;
   #65 = Utf8               module
   #66 = String             #65           // module
   #67 = Utf8               Lcoursier/ivy/Pattern$Chunk$Opt$;
   #68 = NameAndType        #26:#67       // MODULE$:Lcoursier/ivy/Pattern$Chunk$Opt$;
   #69 = Fieldref           #20.#68       // coursier/ivy/Pattern$Chunk$Opt$.MODULE$:Lcoursier/ivy/Pattern$Chunk$Opt$;
   #70 = Utf8               scala_
   #71 = String             #70           // scala_
   #72 = Utf8               scalaVersion
   #73 = String             #72           // scalaVersion
   #74 = Utf8               (Lcoursier/ivy/Pattern$Chunk;Lcoursier/ivy/Pattern$Chunk;Lcoursier/ivy/Pattern$Chunk;)Lcoursier/ivy/Pattern$Chunk$Opt;
   #75 = NameAndType        #52:#74       // apply:(Lcoursier/ivy/Pattern$Chunk;Lcoursier/ivy/Pattern$Chunk;Lcoursier/ivy/Pattern$Chunk;)Lcoursier/ivy/Pattern$Chunk$Opt;
   #76 = Methodref          #20.#75       // coursier/ivy/Pattern$Chunk$Opt$.apply:(Lcoursier/ivy/Pattern$Chunk;Lcoursier/ivy/Pattern$Chunk;Lcoursier/ivy/Pattern$Chunk;)Lcoursier/ivy/Pattern$Chunk$Opt;
   #77 = Utf8               sbt_
   #78 = String             #77           // sbt_
   #79 = Utf8               sbtVersion
   #80 = String             #79           // sbtVersion
   #81 = Utf8               revision
   #82 = String             #81           // revision
   #83 = Utf8               type
   #84 = String             #83           // type
   #85 = Utf8               s/
   #86 = String             #85           // s/
   #87 = Utf8               artifact
   #88 = String             #87           // artifact
   #89 = Utf8               -
   #90 = String             #89           // -
   #91 = Utf8               classifier
   #92 = String             #91           // classifier
   #93 = Utf8               (Lcoursier/ivy/Pattern$Chunk;Lcoursier/ivy/Pattern$Chunk;)Lcoursier/ivy/Pattern$Chunk$Opt;
   #94 = NameAndType        #52:#93       // apply:(Lcoursier/ivy/Pattern$Chunk;Lcoursier/ivy/Pattern$Chunk;)Lcoursier/ivy/Pattern$Chunk$Opt;
   #95 = Methodref          #20.#94       // coursier/ivy/Pattern$Chunk$Opt$.apply:(Lcoursier/ivy/Pattern$Chunk;Lcoursier/ivy/Pattern$Chunk;)Lcoursier/ivy/Pattern$Chunk$Opt;
   #96 = Utf8               .
   #97 = String             #96           // .
   #98 = Utf8               ext
   #99 = String             #98           // ext
  #100 = Utf8               [Ljava/lang/Object;
  #101 = Class              #100          // "[Ljava/lang/Object;"
  #102 = Utf8               wrapRefArray
  #103 = Utf8               ([Ljava/lang/Object;)Lscala/collection/immutable/ArraySeq;
  #104 = NameAndType        #102:#103     // wrapRefArray:([Ljava/lang/Object;)Lscala/collection/immutable/ArraySeq;
  #105 = Methodref          #43.#104      // scala/runtime/ScalaRunTime$.wrapRefArray:([Ljava/lang/Object;)Lscala/collection/immutable/ArraySeq;
  #106 = Utf8               (Lscala/collection/immutable/Seq;)Lscala/collection/SeqOps;
  #107 = NameAndType        #52:#106      // apply:(Lscala/collection/immutable/Seq;)Lscala/collection/SeqOps;
  #108 = Methodref          #38.#107      // scala/collection/immutable/Seq$.apply:(Lscala/collection/immutable/Seq;)Lscala/collection/SeqOps;
  #109 = Utf8               scala/collection/immutable/Seq
  #110 = Class              #109          // scala/collection/immutable/Seq
  #111 = Utf8               (Lscala/collection/immutable/Seq;)Lcoursier/ivy/Pattern;
  #112 = NameAndType        #52:#111      // apply:(Lscala/collection/immutable/Seq;)Lcoursier/ivy/Pattern;
  #113 = Methodref          #2.#112       // coursier/ivy/Pattern$.apply:(Lscala/collection/immutable/Seq;)Lcoursier/ivy/Pattern;
  #114 = NameAndType        #28:#29       // default:Lcoursier/ivy/Pattern;
  #115 = Fieldref           #2.#114       // coursier/ivy/Pattern$.default:Lcoursier/ivy/Pattern;
  #116 = Utf8               ()Lcoursier/ivy/Pattern;
  #117 = Utf8               this
  #118 = Utf8               (Lscala/collection/immutable/Seq<Lcoursier/ivy/Pattern$Chunk;>;)Lcoursier/ivy/Pattern;
  #119 = Utf8               chunks
  #120 = Utf8               (Lscala/collection/immutable/Seq;)V
  #121 = NameAndType        #32:#120      // "<init>":(Lscala/collection/immutable/Seq;)V
  #122 = Methodref          #11.#121      // coursier/ivy/Pattern."<init>":(Lscala/collection/immutable/Seq;)V
  #123 = Utf8               Lscala/collection/immutable/Seq;
  #124 = Utf8               writeReplace
  #125 = Utf8               ()Ljava/lang/Object;
  #126 = Utf8               scala/runtime/ModuleSerializationProxy
  #127 = Class              #126          // scala/runtime/ModuleSerializationProxy
  #128 = Utf8               (Ljava/lang/Class;)V
  #129 = NameAndType        #32:#128      // "<init>":(Ljava/lang/Class;)V
  #130 = Methodref          #127.#129     // scala/runtime/ModuleSerializationProxy."<init>":(Ljava/lang/Class;)V
  #131 = Methodref          #4.#33        // java/lang/Object."<init>":()V
  #132 = Utf8               Code
  #133 = Utf8               LineNumberTable
  #134 = Utf8               LocalVariableTable
  #135 = Utf8               Signature
  #136 = Utf8               MethodParameters
  #137 = Utf8               InnerClasses
  #138 = Utf8               SourceFile
  #139 = Utf8               ScalaInlineInfo
  #140 = Utf8               Scala
{
  public static final coursier.ivy.Pattern$ MODULE$;
    descriptor: Lcoursier/ivy/Pattern$;
    flags: (0x0019) ACC_PUBLIC, ACC_STATIC, ACC_FINAL

  private static final coursier.ivy.Pattern default;
    descriptor: Lcoursier/ivy/Pattern;
    flags: (0x001a) ACC_PRIVATE, ACC_STATIC, ACC_FINAL

  public static {};
    descriptor: ()V
    flags: (0x0009) ACC_PUBLIC, ACC_STATIC
    Code:
      stack=11, locals=0, args_size=0
         0: new           #2                  // class coursier/ivy/Pattern$
         3: dup
         4: invokespecial #34                 // Method "<init>":()V
         7: putstatic     #36                 // Field MODULE$:Lcoursier/ivy/Pattern$;
        10: getstatic     #36                 // Field MODULE$:Lcoursier/ivy/Pattern$;
        13: getstatic     #41                 // Field scala/collection/immutable/Seq$.MODULE$:Lscala/collection/immutable/Seq$;
        16: getstatic     #46                 // Field scala/runtime/ScalaRunTime$.MODULE$:Lscala/runtime/ScalaRunTime$;
        19: bipush        14
        21: anewarray     #9                  // class coursier/ivy/Pattern$Chunk
        24: dup
        25: iconst_0
        26: getstatic     #49                 // Field coursier/ivy/Pattern$Chunk$Var$.MODULE$:Lcoursier/ivy/Pattern$Chunk$Var$;
        29: ldc           #51                 // String organisation
        31: invokevirtual #55                 // Method coursier/ivy/Pattern$Chunk$Var$.apply:(Ljava/lang/String;)Lcoursier/ivy/Pattern$Chunk$Var;
        34: aastore
        35: dup
        36: iconst_1
        37: getstatic     #58                 // Field coursier/ivy/Pattern$Chunk$.MODULE$:Lcoursier/ivy/Pattern$Chunk$;
        40: ldc           #60                 // String /
        42: invokevirtual #64                 // Method coursier/ivy/Pattern$Chunk$.fromString:(Ljava/lang/String;)Lcoursier/ivy/Pattern$Chunk;
        45: aastore
        46: dup
        47: iconst_2
        48: getstatic     #49                 // Field coursier/ivy/Pattern$Chunk$Var$.MODULE$:Lcoursier/ivy/Pattern$Chunk$Var$;
        51: ldc           #66                 // String module
        53: invokevirtual #55                 // Method coursier/ivy/Pattern$Chunk$Var$.apply:(Ljava/lang/String;)Lcoursier/ivy/Pattern$Chunk$Var;
        56: aastore
        57: dup
        58: iconst_3
        59: getstatic     #58                 // Field coursier/ivy/Pattern$Chunk$.MODULE$:Lcoursier/ivy/Pattern$Chunk$;
        62: ldc           #60                 // String /
        64: invokevirtual #64                 // Method coursier/ivy/Pattern$Chunk$.fromString:(Ljava/lang/String;)Lcoursier/ivy/Pattern$Chunk;
        67: aastore
        68: dup
        69: iconst_4
        70: getstatic     #69                 // Field coursier/ivy/Pattern$Chunk$Opt$.MODULE$:Lcoursier/ivy/Pattern$Chunk$Opt$;
        73: getstatic     #58                 // Field coursier/ivy/Pattern$Chunk$.MODULE$:Lcoursier/ivy/Pattern$Chunk$;
        76: ldc           #71                 // String scala_
        78: invokevirtual #64                 // Method coursier/ivy/Pattern$Chunk$.fromString:(Ljava/lang/String;)Lcoursier/ivy/Pattern$Chunk;
        81: getstatic     #49                 // Field coursier/ivy/Pattern$Chunk$Var$.MODULE$:Lcoursier/ivy/Pattern$Chunk$Var$;
        84: ldc           #73                 // String scalaVersion
        86: invokevirtual #55                 // Method coursier/ivy/Pattern$Chunk$Var$.apply:(Ljava/lang/String;)Lcoursier/ivy/Pattern$Chunk$Var;
        89: getstatic     #58                 // Field coursier/ivy/Pattern$Chunk$.MODULE$:Lcoursier/ivy/Pattern$Chunk$;
        92: ldc           #60                 // String /
        94: invokevirtual #64                 // Method coursier/ivy/Pattern$Chunk$.fromString:(Ljava/lang/String;)Lcoursier/ivy/Pattern$Chunk;
        97: invokevirtual #76                 // Method coursier/ivy/Pattern$Chunk$Opt$.apply:(Lcoursier/ivy/Pattern$Chunk;Lcoursier/ivy/Pattern$Chunk;Lcoursier/ivy/Pattern$Chunk;)Lcoursier/ivy/Pattern$Chunk$Opt;
       100: aastore
       101: dup
       102: iconst_5
       103: getstatic     #69                 // Field coursier/ivy/Pattern$Chunk$Opt$.MODULE$:Lcoursier/ivy/Pattern$Chunk$Opt$;
       106: getstatic     #58                 // Field coursier/ivy/Pattern$Chunk$.MODULE$:Lcoursier/ivy/Pattern$Chunk$;
       109: ldc           #78                 // String sbt_
       111: invokevirtual #64                 // Method coursier/ivy/Pattern$Chunk$.fromString:(Ljava/lang/String;)Lcoursier/ivy/Pattern$Chunk;
       114: getstatic     #49                 // Field coursier/ivy/Pattern$Chunk$Var$.MODULE$:Lcoursier/ivy/Pattern$Chunk$Var$;
       117: ldc           #80                 // String sbtVersion
       119: invokevirtual #55                 // Method coursier/ivy/Pattern$Chunk$Var$.apply:(Ljava/lang/String;)Lcoursier/ivy/Pattern$Chunk$Var;
       122: getstatic     #58                 // Field coursier/ivy/Pattern$Chunk$.MODULE$:Lcoursier/ivy/Pattern$Chunk$;
       125: ldc           #60                 // String /
       127: invokevirtual #64                 // Method coursier/ivy/Pattern$Chunk$.fromString:(Ljava/lang/String;)Lcoursier/ivy/Pattern$Chunk;
       130: invokevirtual #76                 // Method coursier/ivy/Pattern$Chunk$Opt$.apply:(Lcoursier/ivy/Pattern$Chunk;Lcoursier/ivy/Pattern$Chunk;Lcoursier/ivy/Pattern$Chunk;)Lcoursier/ivy/Pattern$Chunk$Opt;
       133: aastore
       134: dup
       135: bipush        6
       137: getstatic     #49                 // Field coursier/ivy/Pattern$Chunk$Var$.MODULE$:Lcoursier/ivy/Pattern$Chunk$Var$;
       140: ldc           #82                 // String revision
       142: invokevirtual #55                 // Method coursier/ivy/Pattern$Chunk$Var$.apply:(Ljava/lang/String;)Lcoursier/ivy/Pattern$Chunk$Var;
       145: aastore
       146: dup
       147: bipush        7
       149: getstatic     #58                 // Field coursier/ivy/Pattern$Chunk$.MODULE$:Lcoursier/ivy/Pattern$Chunk$;
       152: ldc           #60                 // String /
       154: invokevirtual #64                 // Method coursier/ivy/Pattern$Chunk$.fromString:(Ljava/lang/String;)Lcoursier/ivy/Pattern$Chunk;
       157: aastore
       158: dup
       159: bipush        8
       161: getstatic     #49                 // Field coursier/ivy/Pattern$Chunk$Var$.MODULE$:Lcoursier/ivy/Pattern$Chunk$Var$;
       164: ldc           #84                 // String type
       166: invokevirtual #55                 // Method coursier/ivy/Pattern$Chunk$Var$.apply:(Ljava/lang/String;)Lcoursier/ivy/Pattern$Chunk$Var;
       169: aastore
       170: dup
       171: bipush        9
       173: getstatic     #58                 // Field coursier/ivy/Pattern$Chunk$.MODULE$:Lcoursier/ivy/Pattern$Chunk$;
       176: ldc           #86                 // String s/
       178: invokevirtual #64                 // Method coursier/ivy/Pattern$Chunk$.fromString:(Ljava/lang/String;)Lcoursier/ivy/Pattern$Chunk;
       181: aastore
       182: dup
       183: bipush        10
       185: getstatic     #49                 // Field coursier/ivy/Pattern$Chunk$Var$.MODULE$:Lcoursier/ivy/Pattern$Chunk$Var$;
       188: ldc           #88                 // String artifact
       190: invokevirtual #55                 // Method coursier/ivy/Pattern$Chunk$Var$.apply:(Ljava/lang/String;)Lcoursier/ivy/Pattern$Chunk$Var;
       193: aastore
       194: dup
       195: bipush        11
       197: getstatic     #69                 // Field coursier/ivy/Pattern$Chunk$Opt$.MODULE$:Lcoursier/ivy/Pattern$Chunk$Opt$;
       200: getstatic     #58                 // Field coursier/ivy/Pattern$Chunk$.MODULE$:Lcoursier/ivy/Pattern$Chunk$;
       203: ldc           #90                 // String -
       205: invokevirtual #64                 // Method coursier/ivy/Pattern$Chunk$.fromString:(Ljava/lang/String;)Lcoursier/ivy/Pattern$Chunk;
       208: getstatic     #49                 // Field coursier/ivy/Pattern$Chunk$Var$.MODULE$:Lcoursier/ivy/Pattern$Chunk$Var$;
       211: ldc           #92                 // String classifier
       213: invokevirtual #55                 // Method coursier/ivy/Pattern$Chunk$Var$.apply:(Ljava/lang/String;)Lcoursier/ivy/Pattern$Chunk$Var;
       216: invokevirtual #95                 // Method coursier/ivy/Pattern$Chunk$Opt$.apply:(Lcoursier/ivy/Pattern$Chunk;Lcoursier/ivy/Pattern$Chunk;)Lcoursier/ivy/Pattern$Chunk$Opt;
       219: aastore
       220: dup
       221: bipush        12
       223: getstatic     #58                 // Field coursier/ivy/Pattern$Chunk$.MODULE$:Lcoursier/ivy/Pattern$Chunk$;
       226: ldc           #97                 // String .
       228: invokevirtual #64                 // Method coursier/ivy/Pattern$Chunk$.fromString:(Ljava/lang/String;)Lcoursier/ivy/Pattern$Chunk;
       231: aastore
       232: dup
       233: bipush        13
       235: getstatic     #49                 // Field coursier/ivy/Pattern$Chunk$Var$.MODULE$:Lcoursier/ivy/Pattern$Chunk$Var$;
       238: ldc           #99                 // String ext
       240: invokevirtual #55                 // Method coursier/ivy/Pattern$Chunk$Var$.apply:(Ljava/lang/String;)Lcoursier/ivy/Pattern$Chunk$Var;
       243: aastore
       244: checkcast     #101                // class "[Ljava/lang/Object;"
       247: invokevirtual #105                // Method scala/runtime/ScalaRunTime$.wrapRefArray:([Ljava/lang/Object;)Lscala/collection/immutable/ArraySeq;
       250: invokevirtual #108                // Method scala/collection/immutable/Seq$.apply:(Lscala/collection/immutable/Seq;)Lscala/collection/SeqOps;
       253: checkcast     #110                // class scala/collection/immutable/Seq
       256: invokevirtual #113                // Method apply:(Lscala/collection/immutable/Seq;)Lcoursier/ivy/Pattern;
       259: putstatic     #115                // Field default:Lcoursier/ivy/Pattern;
       262: return
      LineNumberTable:
        line 55: 0
        line 236: 10
        line 237: 13
        line 238: 26
        line 239: 48
        line 240: 70
        line 241: 103
        line 242: 137
        line 243: 161
        line 244: 185
        line 236: 259
        line 55: 262

  public coursier.ivy.Pattern default();
    descriptor: ()Lcoursier/ivy/Pattern;
    flags: (0x0001) ACC_PUBLIC
    Code:
      stack=1, locals=1, args_size=1
         0: getstatic     #115                // Field default:Lcoursier/ivy/Pattern;
         3: areturn
      LineNumberTable:
        line 236: 0
      LocalVariableTable:
        Start  Length  Slot  Name   Signature
            0       4     0  this   Lcoursier/ivy/Pattern$;

  public coursier.ivy.Pattern apply(scala.collection.immutable.Seq<coursier.ivy.Pattern$Chunk>);
    descriptor: (Lscala/collection/immutable/Seq;)Lcoursier/ivy/Pattern;
    flags: (0x0001) ACC_PUBLIC
    Code:
      stack=3, locals=2, args_size=2
         0: new           #11                 // class coursier/ivy/Pattern
         3: dup
         4: aload_1
         5: invokespecial #122                // Method coursier/ivy/Pattern."<init>":(Lscala/collection/immutable/Seq;)V
         8: areturn
      LineNumberTable:
        line 55: 0
      LocalVariableTable:
        Start  Length  Slot  Name   Signature
            0       9     0  this   Lcoursier/ivy/Pattern$;
            0       9     1 chunks   Lscala/collection/immutable/Seq;
    Signature: #118                         // (Lscala/collection/immutable/Seq<Lcoursier/ivy/Pattern$Chunk;>;)Lcoursier/ivy/Pattern;
    MethodParameters:
      Name                           Flags
      chunks                         final

  private java.lang.Object writeReplace();
    descriptor: ()Ljava/lang/Object;
    flags: (0x0002) ACC_PRIVATE
    Code:
      stack=3, locals=1, args_size=1
         0: new           #127                // class scala/runtime/ModuleSerializationProxy
         3: dup
         4: ldc           #2                  // class coursier/ivy/Pattern$
         6: invokespecial #130                // Method scala/runtime/ModuleSerializationProxy."<init>":(Ljava/lang/Class;)V
         9: areturn
      LineNumberTable:
        line 55: 0
      LocalVariableTable:
        Start  Length  Slot  Name   Signature
            0      10     0  this   Lcoursier/ivy/Pattern$;

  private coursier.ivy.Pattern$();
    descriptor: ()V
    flags: (0x0002) ACC_PRIVATE
    Code:
      stack=1, locals=1, args_size=1
         0: aload_0
         1: invokespecial #131                // Method java/lang/Object."<init>":()V
         4: return
      LineNumberTable:
        line 248: 0
        line 55: 4
      LocalVariableTable:
        Start  Length  Slot  Name   Signature
            0       5     0  this   Lcoursier/ivy/Pattern$;
}
InnerClasses:
  public static abstract #12= #9 of #11;  // Chunk=class coursier/ivy/Pattern$Chunk of class coursier/ivy/Pattern
  public static #15= #14 of #11;          // =class coursier/ivy/Pattern$Chunk$ of class coursier/ivy/Pattern
  public static final #18= #17 of #14;    // Opt=class coursier/ivy/Pattern$Chunk$Opt of class coursier/ivy/Pattern$Chunk$
  public static #15= #20 of #14;          // =class coursier/ivy/Pattern$Chunk$Opt$ of class coursier/ivy/Pattern$Chunk$
  public static final #23= #22 of #14;    // Var=class coursier/ivy/Pattern$Chunk$Var of class coursier/ivy/Pattern$Chunk$
  public static #15= #25 of #14;          // =class coursier/ivy/Pattern$Chunk$Var$ of class coursier/ivy/Pattern$Chunk$
SourceFile: "Pattern.scala"
  ScalaInlineInfo: length = 0x18 (unknown attribute)
   01 01 00 04 00 22 00 21 01 00 36 00 71 01 00 1E
   00 76 01 00 7E 00 7F 01
  Scala: length = 0x0 (unknown attribute)

