Classfile /Users/mw/Projects/slang-braindump/.jar/jar8/assemble/slang-braindump/assemble/content/coursier/ivy/Pattern$Chunk$.class
  Last modified May 29, 2022; size 1365 bytes
  SHA-256 checksum 14cad9eb5f21907295f99c94ea1ce10ffa3e1678bfe864b6c42e4cbc0edae7aa
  Compiled from "Pattern.scala"
public class coursier.ivy.Pattern$Chunk$ implements java.io.Serializable
  minor version: 0
  major version: 52
  flags: (0x0021) ACC_PUBLIC, ACC_SUPER
  this_class: #2                          // coursier/ivy/Pattern$Chunk$
  super_class: #4                         // java/lang/Object
  interfaces: 1, fields: 1, methods: 4, attributes: 4
Constant pool:
   #1 = Utf8               coursier/ivy/Pattern$Chunk$
   #2 = Class              #1             // coursier/ivy/Pattern$Chunk$
   #3 = Utf8               java/lang/Object
   #4 = Class              #3             // java/lang/Object
   #5 = Utf8               java/io/Serializable
   #6 = Class              #5             // java/io/Serializable
   #7 = Utf8               Pattern.scala
   #8 = Utf8               coursier/ivy/Pattern$Chunk
   #9 = Class              #8             // coursier/ivy/Pattern$Chunk
  #10 = Utf8               coursier/ivy/Pattern
  #11 = Class              #10            // coursier/ivy/Pattern
  #12 = Utf8               Chunk
  #13 = Utf8
  #14 = Utf8               coursier/ivy/Pattern$Chunk$Const
  #15 = Class              #14            // coursier/ivy/Pattern$Chunk$Const
  #16 = Utf8               Const
  #17 = Utf8               coursier/ivy/Pattern$Chunk$Const$
  #18 = Class              #17            // coursier/ivy/Pattern$Chunk$Const$
  #19 = Utf8               coursier/ivy/Pattern$Chunk$Opt
  #20 = Class              #19            // coursier/ivy/Pattern$Chunk$Opt
  #21 = Utf8               Opt
  #22 = Utf8               coursier/ivy/Pattern$Chunk$Opt$
  #23 = Class              #22            // coursier/ivy/Pattern$Chunk$Opt$
  #24 = Utf8               coursier/ivy/Pattern$Chunk$Var
  #25 = Class              #24            // coursier/ivy/Pattern$Chunk$Var
  #26 = Utf8               Var
  #27 = Utf8               coursier/ivy/Pattern$Chunk$Var$
  #28 = Class              #27            // coursier/ivy/Pattern$Chunk$Var$
  #29 = Utf8               MODULE$
  #30 = Utf8               Lcoursier/ivy/Pattern$Chunk$;
  #31 = Utf8               <clinit>
  #32 = Utf8               ()V
  #33 = Utf8               <init>
  #34 = NameAndType        #33:#32        // "<init>":()V
  #35 = Methodref          #2.#34         // coursier/ivy/Pattern$Chunk$."<init>":()V
  #36 = NameAndType        #29:#30        // MODULE$:Lcoursier/ivy/Pattern$Chunk$;
  #37 = Fieldref           #2.#36         // coursier/ivy/Pattern$Chunk$.MODULE$:Lcoursier/ivy/Pattern$Chunk$;
  #38 = Utf8               fromString
  #39 = Utf8               (Ljava/lang/String;)Lcoursier/ivy/Pattern$Chunk;
  #40 = Utf8               s
  #41 = Utf8               Lcoursier/ivy/Pattern$Chunk$Const$;
  #42 = NameAndType        #29:#41        // MODULE$:Lcoursier/ivy/Pattern$Chunk$Const$;
  #43 = Fieldref           #18.#42        // coursier/ivy/Pattern$Chunk$Const$.MODULE$:Lcoursier/ivy/Pattern$Chunk$Const$;
  #44 = Utf8               apply
  #45 = Utf8               (Ljava/lang/String;)Lcoursier/ivy/Pattern$Chunk$Const;
  #46 = NameAndType        #44:#45        // apply:(Ljava/lang/String;)Lcoursier/ivy/Pattern$Chunk$Const;
  #47 = Methodref          #18.#46        // coursier/ivy/Pattern$Chunk$Const$.apply:(Ljava/lang/String;)Lcoursier/ivy/Pattern$Chunk$Const;
  #48 = Utf8               this
  #49 = Utf8               Ljava/lang/String;
  #50 = Utf8               writeReplace
  #51 = Utf8               ()Ljava/lang/Object;
  #52 = Utf8               scala/runtime/ModuleSerializationProxy
  #53 = Class              #52            // scala/runtime/ModuleSerializationProxy
  #54 = Utf8               (Ljava/lang/Class;)V
  #55 = NameAndType        #33:#54        // "<init>":(Ljava/lang/Class;)V
  #56 = Methodref          #53.#55        // scala/runtime/ModuleSerializationProxy."<init>":(Ljava/lang/Class;)V
  #57 = Methodref          #4.#34         // java/lang/Object."<init>":()V
  #58 = Utf8               Code
  #59 = Utf8               LineNumberTable
  #60 = Utf8               LocalVariableTable
  #61 = Utf8               MethodParameters
  #62 = Utf8               InnerClasses
  #63 = Utf8               SourceFile
  #64 = Utf8               ScalaInlineInfo
  #65 = Utf8               Scala
{
  public static final coursier.ivy.Pattern$Chunk$ MODULE$;
    descriptor: Lcoursier/ivy/Pattern$Chunk$;
    flags: (0x0019) ACC_PUBLIC, ACC_STATIC, ACC_FINAL

  public static {};
    descriptor: ()V
    flags: (0x0009) ACC_PUBLIC, ACC_STATIC
    Code:
      stack=2, locals=0, args_size=0
         0: new           #2                  // class coursier/ivy/Pattern$Chunk$
         3: dup
         4: invokespecial #35                 // Method "<init>":()V
         7: putstatic     #37                 // Field MODULE$:Lcoursier/ivy/Pattern$Chunk$;
        10: return
      LineNumberTable:
        line 209: 0

  public coursier.ivy.Pattern$Chunk fromString(java.lang.String);
    descriptor: (Ljava/lang/String;)Lcoursier/ivy/Pattern$Chunk;
    flags: (0x0001) ACC_PUBLIC
    Code:
      stack=2, locals=2, args_size=2
         0: getstatic     #43                 // Field coursier/ivy/Pattern$Chunk$Const$.MODULE$:Lcoursier/ivy/Pattern$Chunk$Const$;
         3: aload_1
         4: invokevirtual #47                 // Method coursier/ivy/Pattern$Chunk$Const$.apply:(Ljava/lang/String;)Lcoursier/ivy/Pattern$Chunk$Const;
         7: areturn
      LineNumberTable:
        line 228: 0
      LocalVariableTable:
        Start  Length  Slot  Name   Signature
            0       8     0  this   Lcoursier/ivy/Pattern$Chunk$;
            0       8     1     s   Ljava/lang/String;
    MethodParameters:
      Name                           Flags
      s                              final

  private java.lang.Object writeReplace();
    descriptor: ()Ljava/lang/Object;
    flags: (0x0002) ACC_PRIVATE
    Code:
      stack=3, locals=1, args_size=1
         0: new           #53                 // class scala/runtime/ModuleSerializationProxy
         3: dup
         4: ldc           #2                  // class coursier/ivy/Pattern$Chunk$
         6: invokespecial #56                 // Method scala/runtime/ModuleSerializationProxy."<init>":(Ljava/lang/Class;)V
         9: areturn
      LineNumberTable:
        line 209: 0
      LocalVariableTable:
        Start  Length  Slot  Name   Signature
            0      10     0  this   Lcoursier/ivy/Pattern$Chunk$;

  public coursier.ivy.Pattern$Chunk$();
    descriptor: ()V
    flags: (0x0001) ACC_PUBLIC
    Code:
      stack=1, locals=1, args_size=1
         0: aload_0
         1: invokespecial #57                 // Method java/lang/Object."<init>":()V
         4: return
      LineNumberTable:
        line 231: 0
        line 209: 4
      LocalVariableTable:
        Start  Length  Slot  Name   Signature
            0       5     0  this   Lcoursier/ivy/Pattern$Chunk$;
}
InnerClasses:
  public static abstract #12= #9 of #11;  // Chunk=class coursier/ivy/Pattern$Chunk of class coursier/ivy/Pattern
  public static #13= #2 of #11;           // =class coursier/ivy/Pattern$Chunk$ of class coursier/ivy/Pattern
  public static final #16= #15 of #2;     // Const=class coursier/ivy/Pattern$Chunk$Const of class coursier/ivy/Pattern$Chunk$
  public static #13= #18 of #2;           // =class coursier/ivy/Pattern$Chunk$Const$ of class coursier/ivy/Pattern$Chunk$
  public static final #21= #20 of #2;     // Opt=class coursier/ivy/Pattern$Chunk$Opt of class coursier/ivy/Pattern$Chunk$
  public static #13= #23 of #2;           // =class coursier/ivy/Pattern$Chunk$Opt$ of class coursier/ivy/Pattern$Chunk$
  public static final #26= #25 of #2;     // Var=class coursier/ivy/Pattern$Chunk$Var of class coursier/ivy/Pattern$Chunk$
  public static #13= #28 of #2;           // =class coursier/ivy/Pattern$Chunk$Var$ of class coursier/ivy/Pattern$Chunk$
SourceFile: "Pattern.scala"
  ScalaInlineInfo: length = 0x13 (unknown attribute)
   01 01 00 03 00 24 00 23 01 00 29 00 2A 01 00 35
   00 36 01
  Scala: length = 0x0 (unknown attribute)

