Classfile /Users/mw/Projects/slang-braindump/.jar/jar8/assemble/slang-braindump/assemble/content/coursier/ivy/PropertiesPattern$ChunkOrProperty$.class
  Last modified May 29, 2022; size 1763 bytes
  SHA-256 checksum eb890750ead036e195e3266add449fd7dbd935752637ecb652d02e6dd7e75da9
  Compiled from "Pattern.scala"
public class coursier.ivy.PropertiesPattern$ChunkOrProperty$ implements java.io.Serializable
  minor version: 0
  major version: 52
  flags: (0x0021) ACC_PUBLIC, ACC_SUPER
  this_class: #2                          // coursier/ivy/PropertiesPattern$ChunkOrProperty$
  super_class: #4                         // java/lang/Object
  interfaces: 1, fields: 1, methods: 4, attributes: 4
Constant pool:
   #1 = Utf8               coursier/ivy/PropertiesPattern$ChunkOrProperty$
   #2 = Class              #1             // coursier/ivy/PropertiesPattern$ChunkOrProperty$
   #3 = Utf8               java/lang/Object
   #4 = Class              #3             // java/lang/Object
   #5 = Utf8               java/io/Serializable
   #6 = Class              #5             // java/io/Serializable
   #7 = Utf8               Pattern.scala
   #8 = Utf8               coursier/ivy/PropertiesPattern$ChunkOrProperty
   #9 = Class              #8             // coursier/ivy/PropertiesPattern$ChunkOrProperty
  #10 = Utf8               coursier/ivy/PropertiesPattern
  #11 = Class              #10            // coursier/ivy/PropertiesPattern
  #12 = Utf8               ChunkOrProperty
  #13 = Utf8
  #14 = Utf8               coursier/ivy/PropertiesPattern$ChunkOrProperty$Const
  #15 = Class              #14            // coursier/ivy/PropertiesPattern$ChunkOrProperty$Const
  #16 = Utf8               Const
  #17 = Utf8               coursier/ivy/PropertiesPattern$ChunkOrProperty$Const$
  #18 = Class              #17            // coursier/ivy/PropertiesPattern$ChunkOrProperty$Const$
  #19 = Utf8               coursier/ivy/PropertiesPattern$ChunkOrProperty$Opt
  #20 = Class              #19            // coursier/ivy/PropertiesPattern$ChunkOrProperty$Opt
  #21 = Utf8               Opt
  #22 = Utf8               coursier/ivy/PropertiesPattern$ChunkOrProperty$Opt$
  #23 = Class              #22            // coursier/ivy/PropertiesPattern$ChunkOrProperty$Opt$
  #24 = Utf8               coursier/ivy/PropertiesPattern$ChunkOrProperty$Prop
  #25 = Class              #24            // coursier/ivy/PropertiesPattern$ChunkOrProperty$Prop
  #26 = Utf8               Prop
  #27 = Utf8               coursier/ivy/PropertiesPattern$ChunkOrProperty$Prop$
  #28 = Class              #27            // coursier/ivy/PropertiesPattern$ChunkOrProperty$Prop$
  #29 = Utf8               coursier/ivy/PropertiesPattern$ChunkOrProperty$Var
  #30 = Class              #29            // coursier/ivy/PropertiesPattern$ChunkOrProperty$Var
  #31 = Utf8               Var
  #32 = Utf8               coursier/ivy/PropertiesPattern$ChunkOrProperty$Var$
  #33 = Class              #32            // coursier/ivy/PropertiesPattern$ChunkOrProperty$Var$
  #34 = Utf8               MODULE$
  #35 = Utf8               Lcoursier/ivy/PropertiesPattern$ChunkOrProperty$;
  #36 = Utf8               <clinit>
  #37 = Utf8               ()V
  #38 = Utf8               <init>
  #39 = NameAndType        #38:#37        // "<init>":()V
  #40 = Methodref          #2.#39         // coursier/ivy/PropertiesPattern$ChunkOrProperty$."<init>":()V
  #41 = NameAndType        #34:#35        // MODULE$:Lcoursier/ivy/PropertiesPattern$ChunkOrProperty$;
  #42 = Fieldref           #2.#41         // coursier/ivy/PropertiesPattern$ChunkOrProperty$.MODULE$:Lcoursier/ivy/PropertiesPattern$ChunkOrProperty$;
  #43 = Utf8               fromString
  #44 = Utf8               (Ljava/lang/String;)Lcoursier/ivy/PropertiesPattern$ChunkOrProperty;
  #45 = Utf8               s
  #46 = Utf8               Lcoursier/ivy/PropertiesPattern$ChunkOrProperty$Const$;
  #47 = NameAndType        #34:#46        // MODULE$:Lcoursier/ivy/PropertiesPattern$ChunkOrProperty$Const$;
  #48 = Fieldref           #18.#47        // coursier/ivy/PropertiesPattern$ChunkOrProperty$Const$.MODULE$:Lcoursier/ivy/PropertiesPattern$ChunkOrProperty$Const$;
  #49 = Utf8               apply
  #50 = Utf8               (Ljava/lang/String;)Lcoursier/ivy/PropertiesPattern$ChunkOrProperty$Const;
  #51 = NameAndType        #49:#50        // apply:(Ljava/lang/String;)Lcoursier/ivy/PropertiesPattern$ChunkOrProperty$Const;
  #52 = Methodref          #18.#51        // coursier/ivy/PropertiesPattern$ChunkOrProperty$Const$.apply:(Ljava/lang/String;)Lcoursier/ivy/PropertiesPattern$ChunkOrProperty$Const;
  #53 = Utf8               this
  #54 = Utf8               Ljava/lang/String;
  #55 = Utf8               writeReplace
  #56 = Utf8               ()Ljava/lang/Object;
  #57 = Utf8               scala/runtime/ModuleSerializationProxy
  #58 = Class              #57            // scala/runtime/ModuleSerializationProxy
  #59 = Utf8               (Ljava/lang/Class;)V
  #60 = NameAndType        #38:#59        // "<init>":(Ljava/lang/Class;)V
  #61 = Methodref          #58.#60        // scala/runtime/ModuleSerializationProxy."<init>":(Ljava/lang/Class;)V
  #62 = Methodref          #4.#39         // java/lang/Object."<init>":()V
  #63 = Utf8               Code
  #64 = Utf8               LineNumberTable
  #65 = Utf8               LocalVariableTable
  #66 = Utf8               MethodParameters
  #67 = Utf8               InnerClasses
  #68 = Utf8               SourceFile
  #69 = Utf8               ScalaInlineInfo
  #70 = Utf8               Scala
{
  public static final coursier.ivy.PropertiesPattern$ChunkOrProperty$ MODULE$;
    descriptor: Lcoursier/ivy/PropertiesPattern$ChunkOrProperty$;
    flags: (0x0019) ACC_PUBLIC, ACC_STATIC, ACC_FINAL

  public static {};
    descriptor: ()V
    flags: (0x0009) ACC_PUBLIC, ACC_STATIC
    Code:
      stack=2, locals=0, args_size=0
         0: new           #2                  // class coursier/ivy/PropertiesPattern$ChunkOrProperty$
         3: dup
         4: invokespecial #40                 // Method "<init>":()V
         7: putstatic     #42                 // Field MODULE$:Lcoursier/ivy/PropertiesPattern$ChunkOrProperty$;
        10: return
      LineNumberTable:
        line 137: 0

  public coursier.ivy.PropertiesPattern$ChunkOrProperty fromString(java.lang.String);
    descriptor: (Ljava/lang/String;)Lcoursier/ivy/PropertiesPattern$ChunkOrProperty;
    flags: (0x0001) ACC_PUBLIC
    Code:
      stack=2, locals=2, args_size=2
         0: getstatic     #48                 // Field coursier/ivy/PropertiesPattern$ChunkOrProperty$Const$.MODULE$:Lcoursier/ivy/PropertiesPattern$ChunkOrProperty$Const$;
         3: aload_1
         4: invokevirtual #52                 // Method coursier/ivy/PropertiesPattern$ChunkOrProperty$Const$.apply:(Ljava/lang/String;)Lcoursier/ivy/PropertiesPattern$ChunkOrProperty$Const;
         7: areturn
      LineNumberTable:
        line 160: 0
      LocalVariableTable:
        Start  Length  Slot  Name   Signature
            0       8     0  this   Lcoursier/ivy/PropertiesPattern$ChunkOrProperty$;
            0       8     1     s   Ljava/lang/String;
    MethodParameters:
      Name                           Flags
      s                              final

  private java.lang.Object writeReplace();
    descriptor: ()Ljava/lang/Object;
    flags: (0x0002) ACC_PRIVATE
    Code:
      stack=3, locals=1, args_size=1
         0: new           #58                 // class scala/runtime/ModuleSerializationProxy
         3: dup
         4: ldc           #2                  // class coursier/ivy/PropertiesPattern$ChunkOrProperty$
         6: invokespecial #61                 // Method scala/runtime/ModuleSerializationProxy."<init>":(Ljava/lang/Class;)V
         9: areturn
      LineNumberTable:
        line 137: 0
      LocalVariableTable:
        Start  Length  Slot  Name   Signature
            0      10     0  this   Lcoursier/ivy/PropertiesPattern$ChunkOrProperty$;

  public coursier.ivy.PropertiesPattern$ChunkOrProperty$();
    descriptor: ()V
    flags: (0x0001) ACC_PUBLIC
    Code:
      stack=1, locals=1, args_size=1
         0: aload_0
         1: invokespecial #62                 // Method java/lang/Object."<init>":()V
         4: return
      LineNumberTable:
        line 163: 0
        line 137: 4
      LocalVariableTable:
        Start  Length  Slot  Name   Signature
            0       5     0  this   Lcoursier/ivy/PropertiesPattern$ChunkOrProperty$;
}
InnerClasses:
  public static abstract #12= #9 of #11;  // ChunkOrProperty=class coursier/ivy/PropertiesPattern$ChunkOrProperty of class coursier/ivy/PropertiesPattern
  public static #13= #2 of #11;           // =class coursier/ivy/PropertiesPattern$ChunkOrProperty$ of class coursier/ivy/PropertiesPattern
  public static final #16= #15 of #2;     // Const=class coursier/ivy/PropertiesPattern$ChunkOrProperty$Const of class coursier/ivy/PropertiesPattern$ChunkOrProperty$
  public static #13= #18 of #2;           // =class coursier/ivy/PropertiesPattern$ChunkOrProperty$Const$ of class coursier/ivy/PropertiesPattern$ChunkOrProperty$
  public static final #21= #20 of #2;     // Opt=class coursier/ivy/PropertiesPattern$ChunkOrProperty$Opt of class coursier/ivy/PropertiesPattern$ChunkOrProperty$
  public static #13= #23 of #2;           // =class coursier/ivy/PropertiesPattern$ChunkOrProperty$Opt$ of class coursier/ivy/PropertiesPattern$ChunkOrProperty$
  public static final #26= #25 of #2;     // Prop=class coursier/ivy/PropertiesPattern$ChunkOrProperty$Prop of class coursier/ivy/PropertiesPattern$ChunkOrProperty$
  public static #13= #28 of #2;           // =class coursier/ivy/PropertiesPattern$ChunkOrProperty$Prop$ of class coursier/ivy/PropertiesPattern$ChunkOrProperty$
  public static final #31= #30 of #2;     // Var=class coursier/ivy/PropertiesPattern$ChunkOrProperty$Var of class coursier/ivy/PropertiesPattern$ChunkOrProperty$
  public static #13= #33 of #2;           // =class coursier/ivy/PropertiesPattern$ChunkOrProperty$Var$ of class coursier/ivy/PropertiesPattern$ChunkOrProperty$
SourceFile: "Pattern.scala"
  ScalaInlineInfo: length = 0x13 (unknown attribute)
   01 01 00 03 00 2A 00 29 01 00 2F 00 30 01 00 3B
   00 3C 01
  Scala: length = 0x0 (unknown attribute)

