Classfile /Users/mw/Projects/slang-braindump/.jar/jar8/assemble/slang-braindump/assemble/content/coursier/ivy/PropertiesPattern$ChunkOrProperty$Opt$.class
  Last modified May 29, 2022; size 2574 bytes
  SHA-256 checksum 9597d6cf4b1a7ddf217813c0fdccc473c2c2a14a8b3329ce6a06121406a9b2f7
  Compiled from "Pattern.scala"
public class coursier.ivy.PropertiesPattern$ChunkOrProperty$Opt$ implements java.io.Serializable
  minor version: 0
  major version: 52
  flags: (0x0021) ACC_PUBLIC, ACC_SUPER
  this_class: #2                          // coursier/ivy/PropertiesPattern$ChunkOrProperty$Opt$
  super_class: #4                         // java/lang/Object
  interfaces: 1, fields: 1, methods: 7, attributes: 4
Constant pool:
   #1 = Utf8               coursier/ivy/PropertiesPattern$ChunkOrProperty$Opt$
   #2 = Class              #1             // coursier/ivy/PropertiesPattern$ChunkOrProperty$Opt$
   #3 = Utf8               java/lang/Object
   #4 = Class              #3             // java/lang/Object
   #5 = Utf8               java/io/Serializable
   #6 = Class              #5             // java/io/Serializable
   #7 = Utf8               Pattern.scala
   #8 = Utf8               coursier/ivy/PropertiesPattern$ChunkOrProperty
   #9 = Class              #8             // coursier/ivy/PropertiesPattern$ChunkOrProperty
  #10 = Utf8               coursier/ivy/PropertiesPattern
  #11 = Class              #10            // coursier/ivy/PropertiesPattern
  #12 = Utf8               ChunkOrProperty
  #13 = Utf8               coursier/ivy/PropertiesPattern$ChunkOrProperty$
  #14 = Class              #13            // coursier/ivy/PropertiesPattern$ChunkOrProperty$
  #15 = Utf8
  #16 = Utf8               coursier/ivy/PropertiesPattern$ChunkOrProperty$Opt
  #17 = Class              #16            // coursier/ivy/PropertiesPattern$ChunkOrProperty$Opt
  #18 = Utf8               Opt
  #19 = Utf8               MODULE$
  #20 = Utf8               Lcoursier/ivy/PropertiesPattern$ChunkOrProperty$Opt$;
  #21 = Utf8               <clinit>
  #22 = Utf8               ()V
  #23 = Utf8               <init>
  #24 = NameAndType        #23:#22        // "<init>":()V
  #25 = Methodref          #2.#24         // coursier/ivy/PropertiesPattern$ChunkOrProperty$Opt$."<init>":()V
  #26 = NameAndType        #19:#20        // MODULE$:Lcoursier/ivy/PropertiesPattern$ChunkOrProperty$Opt$;
  #27 = Fieldref           #2.#26         // coursier/ivy/PropertiesPattern$ChunkOrProperty$Opt$.MODULE$:Lcoursier/ivy/PropertiesPattern$ChunkOrProperty$Opt$;
  #28 = Utf8               apply
  #29 = Utf8               (Lcoursier/ivy/PropertiesPattern$ChunkOrProperty;)Lcoursier/ivy/PropertiesPattern$ChunkOrProperty$Opt;
  #30 = Utf8               elem
  #31 = Utf8               scala/collection/immutable/$colon$colon
  #32 = Class              #31            // scala/collection/immutable/$colon$colon
  #33 = Utf8               scala/collection/immutable/Nil$
  #34 = Class              #33            // scala/collection/immutable/Nil$
  #35 = Utf8               Lscala/collection/immutable/Nil$;
  #36 = NameAndType        #19:#35        // MODULE$:Lscala/collection/immutable/Nil$;
  #37 = Fieldref           #34.#36        // scala/collection/immutable/Nil$.MODULE$:Lscala/collection/immutable/Nil$;
  #38 = Utf8               (Ljava/lang/Object;Lscala/collection/immutable/List;)V
  #39 = NameAndType        #23:#38        // "<init>":(Ljava/lang/Object;Lscala/collection/immutable/List;)V
  #40 = Methodref          #32.#39        // scala/collection/immutable/$colon$colon."<init>":(Ljava/lang/Object;Lscala/collection/immutable/List;)V
  #41 = Utf8               scala/collection/immutable/Seq
  #42 = Class              #41            // scala/collection/immutable/Seq
  #43 = Utf8               (Lscala/collection/immutable/Seq;)Lcoursier/ivy/PropertiesPattern$ChunkOrProperty$Opt;
  #44 = NameAndType        #28:#43        // apply:(Lscala/collection/immutable/Seq;)Lcoursier/ivy/PropertiesPattern$ChunkOrProperty$Opt;
  #45 = Methodref          #2.#44         // coursier/ivy/PropertiesPattern$ChunkOrProperty$Opt$.apply:(Lscala/collection/immutable/Seq;)Lcoursier/ivy/PropertiesPattern$ChunkOrProperty$Opt;
  #46 = Utf8               this
  #47 = Utf8               Lcoursier/ivy/PropertiesPattern$ChunkOrProperty;
  #48 = Utf8               (Lcoursier/ivy/PropertiesPattern$ChunkOrProperty;Lcoursier/ivy/PropertiesPattern$ChunkOrProperty;)Lcoursier/ivy/PropertiesPattern$ChunkOrProperty$Opt;
  #49 = Utf8               elem1
  #50 = Utf8               (Lcoursier/ivy/PropertiesPattern$ChunkOrProperty;Lcoursier/ivy/PropertiesPattern$ChunkOrProperty;Lcoursier/ivy/PropertiesPattern$ChunkOrProperty;)Lcoursier/ivy/PropertiesPattern$ChunkOrProperty$Opt;
  #51 = Utf8               elem2
  #52 = Utf8               (Lscala/collection/immutable/Seq<Lcoursier/ivy/PropertiesPattern$ChunkOrProperty;>;)Lcoursier/ivy/PropertiesPattern$ChunkOrProperty$Opt;
  #53 = Utf8               content
  #54 = Utf8               (Lscala/collection/immutable/Seq;)V
  #55 = NameAndType        #23:#54        // "<init>":(Lscala/collection/immutable/Seq;)V
  #56 = Methodref          #17.#55        // coursier/ivy/PropertiesPattern$ChunkOrProperty$Opt."<init>":(Lscala/collection/immutable/Seq;)V
  #57 = Utf8               Lscala/collection/immutable/Seq;
  #58 = Utf8               writeReplace
  #59 = Utf8               ()Ljava/lang/Object;
  #60 = Utf8               scala/runtime/ModuleSerializationProxy
  #61 = Class              #60            // scala/runtime/ModuleSerializationProxy
  #62 = Utf8               (Ljava/lang/Class;)V
  #63 = NameAndType        #23:#62        // "<init>":(Ljava/lang/Class;)V
  #64 = Methodref          #61.#63        // scala/runtime/ModuleSerializationProxy."<init>":(Ljava/lang/Class;)V
  #65 = Methodref          #4.#24         // java/lang/Object."<init>":()V
  #66 = Utf8               Code
  #67 = Utf8               LineNumberTable
  #68 = Utf8               LocalVariableTable
  #69 = Utf8               MethodParameters
  #70 = Utf8               Signature
  #71 = Utf8               InnerClasses
  #72 = Utf8               SourceFile
  #73 = Utf8               ScalaInlineInfo
  #74 = Utf8               Scala
{
  public static final coursier.ivy.PropertiesPattern$ChunkOrProperty$Opt$ MODULE$;
    descriptor: Lcoursier/ivy/PropertiesPattern$ChunkOrProperty$Opt$;
    flags: (0x0019) ACC_PUBLIC, ACC_STATIC, ACC_FINAL

  public static {};
    descriptor: ()V
    flags: (0x0009) ACC_PUBLIC, ACC_STATIC
    Code:
      stack=2, locals=0, args_size=0
         0: new           #2                  // class coursier/ivy/PropertiesPattern$ChunkOrProperty$Opt$
         3: dup
         4: invokespecial #25                 // Method "<init>":()V
         7: putstatic     #27                 // Field MODULE$:Lcoursier/ivy/PropertiesPattern$ChunkOrProperty$Opt$;
        10: return
      LineNumberTable:
        line 145: 0

  public coursier.ivy.PropertiesPattern$ChunkOrProperty$Opt apply(coursier.ivy.PropertiesPattern$ChunkOrProperty);
    descriptor: (Lcoursier/ivy/PropertiesPattern$ChunkOrProperty;)Lcoursier/ivy/PropertiesPattern$ChunkOrProperty$Opt;
    flags: (0x0001) ACC_PUBLIC
    Code:
      stack=5, locals=2, args_size=2
         0: aload_0
         1: new           #32                 // class scala/collection/immutable/$colon$colon
         4: dup
         5: aload_1
         6: getstatic     #37                 // Field scala/collection/immutable/Nil$.MODULE$:Lscala/collection/immutable/Nil$;
         9: invokespecial #40                 // Method scala/collection/immutable/$colon$colon."<init>":(Ljava/lang/Object;Lscala/collection/immutable/List;)V
        12: checkcast     #42                 // class scala/collection/immutable/Seq
        15: invokevirtual #45                 // Method apply:(Lscala/collection/immutable/Seq;)Lcoursier/ivy/PropertiesPattern$ChunkOrProperty$Opt;
        18: areturn
      LineNumberTable:
        line 150: 0
      LocalVariableTable:
        Start  Length  Slot  Name   Signature
            0      19     0  this   Lcoursier/ivy/PropertiesPattern$ChunkOrProperty$Opt$;
            0      19     1  elem   Lcoursier/ivy/PropertiesPattern$ChunkOrProperty;
    MethodParameters:
      Name                           Flags
      elem                           final

  public coursier.ivy.PropertiesPattern$ChunkOrProperty$Opt apply(coursier.ivy.PropertiesPattern$ChunkOrProperty, coursier.ivy.PropertiesPattern$ChunkOrProperty);
    descriptor: (Lcoursier/ivy/PropertiesPattern$ChunkOrProperty;Lcoursier/ivy/PropertiesPattern$ChunkOrProperty;)Lcoursier/ivy/PropertiesPattern$ChunkOrProperty$Opt;
    flags: (0x0001) ACC_PUBLIC
    Code:
      stack=8, locals=3, args_size=3
         0: aload_0
         1: new           #32                 // class scala/collection/immutable/$colon$colon
         4: dup
         5: aload_1
         6: new           #32                 // class scala/collection/immutable/$colon$colon
         9: dup
        10: aload_2
        11: getstatic     #37                 // Field scala/collection/immutable/Nil$.MODULE$:Lscala/collection/immutable/Nil$;
        14: invokespecial #40                 // Method scala/collection/immutable/$colon$colon."<init>":(Ljava/lang/Object;Lscala/collection/immutable/List;)V
        17: invokespecial #40                 // Method scala/collection/immutable/$colon$colon."<init>":(Ljava/lang/Object;Lscala/collection/immutable/List;)V
        20: checkcast     #42                 // class scala/collection/immutable/Seq
        23: invokevirtual #45                 // Method apply:(Lscala/collection/immutable/Seq;)Lcoursier/ivy/PropertiesPattern$ChunkOrProperty$Opt;
        26: areturn
      LineNumberTable:
        line 152: 0
      LocalVariableTable:
        Start  Length  Slot  Name   Signature
            0      27     0  this   Lcoursier/ivy/PropertiesPattern$ChunkOrProperty$Opt$;
            0      27     1  elem   Lcoursier/ivy/PropertiesPattern$ChunkOrProperty;
            0      27     2 elem1   Lcoursier/ivy/PropertiesPattern$ChunkOrProperty;
    MethodParameters:
      Name                           Flags
      elem                           final
      elem1                          final

  public coursier.ivy.PropertiesPattern$ChunkOrProperty$Opt apply(coursier.ivy.PropertiesPattern$ChunkOrProperty, coursier.ivy.PropertiesPattern$ChunkOrProperty, coursier.ivy.PropertiesPattern$ChunkOrProperty);
    descriptor: (Lcoursier/ivy/PropertiesPattern$ChunkOrProperty;Lcoursier/ivy/PropertiesPattern$ChunkOrProperty;Lcoursier/ivy/PropertiesPattern$ChunkOrProperty;)Lcoursier/ivy/PropertiesPattern$ChunkOrProperty$Opt;
    flags: (0x0001) ACC_PUBLIC
    Code:
      stack=11, locals=4, args_size=4
         0: aload_0
         1: new           #32                 // class scala/collection/immutable/$colon$colon
         4: dup
         5: aload_1
         6: new           #32                 // class scala/collection/immutable/$colon$colon
         9: dup
        10: aload_2
        11: new           #32                 // class scala/collection/immutable/$colon$colon
        14: dup
        15: aload_3
        16: getstatic     #37                 // Field scala/collection/immutable/Nil$.MODULE$:Lscala/collection/immutable/Nil$;
        19: invokespecial #40                 // Method scala/collection/immutable/$colon$colon."<init>":(Ljava/lang/Object;Lscala/collection/immutable/List;)V
        22: invokespecial #40                 // Method scala/collection/immutable/$colon$colon."<init>":(Ljava/lang/Object;Lscala/collection/immutable/List;)V
        25: invokespecial #40                 // Method scala/collection/immutable/$colon$colon."<init>":(Ljava/lang/Object;Lscala/collection/immutable/List;)V
        28: checkcast     #42                 // class scala/collection/immutable/Seq
        31: invokevirtual #45                 // Method apply:(Lscala/collection/immutable/Seq;)Lcoursier/ivy/PropertiesPattern$ChunkOrProperty$Opt;
        34: areturn
      LineNumberTable:
        line 154: 0
      LocalVariableTable:
        Start  Length  Slot  Name   Signature
            0      35     0  this   Lcoursier/ivy/PropertiesPattern$ChunkOrProperty$Opt$;
            0      35     1  elem   Lcoursier/ivy/PropertiesPattern$ChunkOrProperty;
            0      35     2 elem1   Lcoursier/ivy/PropertiesPattern$ChunkOrProperty;
            0      35     3 elem2   Lcoursier/ivy/PropertiesPattern$ChunkOrProperty;
    MethodParameters:
      Name                           Flags
      elem                           final
      elem1                          final
      elem2                          final

  public coursier.ivy.PropertiesPattern$ChunkOrProperty$Opt apply(scala.collection.immutable.Seq<coursier.ivy.PropertiesPattern$ChunkOrProperty>);
    descriptor: (Lscala/collection/immutable/Seq;)Lcoursier/ivy/PropertiesPattern$ChunkOrProperty$Opt;
    flags: (0x0001) ACC_PUBLIC
    Code:
      stack=3, locals=2, args_size=2
         0: new           #17                 // class coursier/ivy/PropertiesPattern$ChunkOrProperty$Opt
         3: dup
         4: aload_1
         5: invokespecial #56                 // Method coursier/ivy/PropertiesPattern$ChunkOrProperty$Opt."<init>":(Lscala/collection/immutable/Seq;)V
         8: areturn
      LineNumberTable:
        line 145: 0
      LocalVariableTable:
        Start  Length  Slot  Name   Signature
            0       9     0  this   Lcoursier/ivy/PropertiesPattern$ChunkOrProperty$Opt$;
            0       9     1 content   Lscala/collection/immutable/Seq;
    Signature: #52                          // (Lscala/collection/immutable/Seq<Lcoursier/ivy/PropertiesPattern$ChunkOrProperty;>;)Lcoursier/ivy/PropertiesPattern$ChunkOrProperty$Opt;
    MethodParameters:
      Name                           Flags
      content                        final

  private java.lang.Object writeReplace();
    descriptor: ()Ljava/lang/Object;
    flags: (0x0002) ACC_PRIVATE
    Code:
      stack=3, locals=1, args_size=1
         0: new           #61                 // class scala/runtime/ModuleSerializationProxy
         3: dup
         4: ldc           #2                  // class coursier/ivy/PropertiesPattern$ChunkOrProperty$Opt$
         6: invokespecial #64                 // Method scala/runtime/ModuleSerializationProxy."<init>":(Ljava/lang/Class;)V
         9: areturn
      LineNumberTable:
        line 145: 0
      LocalVariableTable:
        Start  Length  Slot  Name   Signature
            0      10     0  this   Lcoursier/ivy/PropertiesPattern$ChunkOrProperty$Opt$;

  public coursier.ivy.PropertiesPattern$ChunkOrProperty$Opt$();
    descriptor: ()V
    flags: (0x0001) ACC_PUBLIC
    Code:
      stack=1, locals=1, args_size=1
         0: aload_0
         1: invokespecial #65                 // Method java/lang/Object."<init>":()V
         4: return
      LineNumberTable:
        line 156: 0
        line 145: 4
      LocalVariableTable:
        Start  Length  Slot  Name   Signature
            0       5     0  this   Lcoursier/ivy/PropertiesPattern$ChunkOrProperty$Opt$;
}
InnerClasses:
  public static abstract #12= #9 of #11;  // ChunkOrProperty=class coursier/ivy/PropertiesPattern$ChunkOrProperty of class coursier/ivy/PropertiesPattern
  public static #15= #14 of #11;          // =class coursier/ivy/PropertiesPattern$ChunkOrProperty$ of class coursier/ivy/PropertiesPattern
  public static final #18= #17 of #14;    // Opt=class coursier/ivy/PropertiesPattern$ChunkOrProperty$Opt of class coursier/ivy/PropertiesPattern$ChunkOrProperty$
  public static #15= #2 of #14;           // =class coursier/ivy/PropertiesPattern$ChunkOrProperty$Opt$ of class coursier/ivy/PropertiesPattern$ChunkOrProperty$
SourceFile: "Pattern.scala"
  ScalaInlineInfo: length = 0x22 (unknown attribute)
   01 01 00 06 00 18 00 17 01 00 1D 00 1E 01 00 1D
   00 31 01 00 1D 00 33 01 00 1D 00 2C 01 00 3B 00
   3C 01
  Scala: length = 0x0 (unknown attribute)

