Classfile /Users/mw/Projects/slang-braindump/.jar/jar8/assemble/slang-braindump/assemble/content/scala/concurrent/BlockContext.class
  Last modified May 29, 2022; size 2525 bytes
  SHA-256 checksum 69205d5df206a63cbba4e24f6010039e84de9e57c16119dc4f41167805705a0c
  Compiled from "BlockContext.scala"
public interface scala.concurrent.BlockContext
  minor version: 0
  major version: 52
  flags: (0x0601) ACC_PUBLIC, ACC_INTERFACE, ACC_ABSTRACT
  this_class: #2                          // scala/concurrent/BlockContext
  super_class: #4                         // java/lang/Object
  interfaces: 0, fields: 0, methods: 5, attributes: 5
Constant pool:
   #1 = Utf8               scala/concurrent/BlockContext
   #2 = Class              #1             // scala/concurrent/BlockContext
   #3 = Utf8               java/lang/Object
   #4 = Class              #3             // java/lang/Object
   #5 = Utf8               BlockContext.scala
   #6 = Utf8               Lscala/reflect/ScalaSignature;
   #7 = Utf8               bytes
   #8 = Utf8               \u0006\u0005E4qa\u0004\t\u0011\u0002G\u0005Q\u0003C\u0003\u001b\u0001\u0019\u00051dB\u00035!!\u0005QGB\u0003\u0010!!\u0005a\u0007C\u00038\u0007\u0011\u0005\u0001h\u0002\u0004:\u0007\u0001FIA\u000f\u0004\u0007y\r\u0001\u000b\u0012B\u001f\t\u000b]2A\u0011A \t\u000bi1AQ\t!\t\u000b!\u001bAQA%\t\r)\u001b\u0001\u0015!\u0004L\u0011\u0019\u00196\u0001)C\u0007)\")qk\u0001C\u0003\u0013\")\u0001l\u0001C\u00033\")1m\u0001C\u0003I\na!\t\\8dW\u000e{g\u000e^3yi*\u0011\u0011CE\u0001\u000bG>t7-\u001e:sK:$(\"A\n\u0002\u000bM\u001c\u0017\r\\1\u0004\u0001M\u0011\u0001A\u0006\t\u0003/ai\u0011AE\u0005\u00033I\u0011a!\u00118z%\u00164\u0017a\u00022m_\u000e\\wJ\\\u000b\u00039\u0001\"\"!H\u0018\u0015\u0005yI\u0003CA\u0010!\u0019\u0001!Q!I\u0001C\u0002\t\u0012\u0011\u0001V\t\u0003G\u0019\u0002\"a\u0006\u0013\n\u0005\u0015\u0012\"a\u0002(pi\"Lgn\u001a\t\u0003/\u001dJ!\u0001\u000b\n\u0003\u0007\u0005s\u0017\u0010C\u0003+\u0003\u0001\u000f1&\u0001\u0006qKJl\u0017n]:j_:\u0004\"\u0001L\u0017\u000e\u0003AI!A\f\t\u0003\u0011\r\u000bg.Q<bSRDa\u0001M\u0001\u0005\u0002\u0004\t\u0014!\u0002;ik:\\\u0007cA\f3=%\u00111G\u0005\u0002\ty\tLh.Y7f}\u0005a!\t\\8dW\u000e{g\u000e^3yiB\u0011AfA\n\u0003\u0007Y\ta\u0001P5oSRtD#A\u001b\u0002\'\u0011+g-Y;mi\ncwnY6D_:$X\r\u001f;\u0011\u0005m2Q\"A\u0002\u0003\'\u0011+g-Y;mi\ncwnY6D_:$X\r\u001f;\u0014\u0007\u00191b\b\u0005\u0002-\u0001Q\t!(\u0006\u0002B\tR\u0011!I\u0012\u000b\u0003\u0007\u0016\u0003\"a\b#\u0005\u000b\u0005B!\u0019\u0001\u0012\t\u000b)B\u00019A\u0016\t\rABA\u00111\u0001H!\r9\"gQ\u0001\u0014I\u00164\u0017-\u001e7u\u00052|7m[\"p]R,\u0007\u0010^\u000b\u0002}\u0005a1m\u001c8uKb$Hj\\2bYB\u0019A*\u0015 \u000e\u00035S!AT(\u0002\t1\fgn\u001a\u0006\u0002!\u0006!!.\u0019<b\u0013\t\u0011VJA\u0006UQJ,\u0017\r\u001a\'pG\u0006d\u0017A\u00029sK\u001a,\'\u000f\u0006\u0002?+\")ak\u0003a\u0001}\u0005I1-\u00198eS\u0012\fG/Z\u0001\bGV\u0014(/\u001a8u\u0003A9\u0018\u000e\u001e5CY>\u001c7nQ8oi\u0016DH/\u0006\u0002[;R\u00111,\u0019\u000b\u00039z\u0003\"aH/\u0005\u000b\u0005j!\u0019\u0001\u0012\t\r}kA\u00111\u0001a\u0003\u0011\u0011w\u000eZ=\u0011\u0007]\u0011D\fC\u0003c\u001b\u0001\u0007a(\u0001\u0007cY>\u001c7nQ8oi\u0016DH/A\tvg&twM\u00117pG.\u001cuN\u001c;fqR,2!Z8i)\t1g\u000e\u0006\u0002hSB\u0011q\u0004\u001b\u0003\u0006C9\u0011\rA\t\u0005\u0006U:\u0001\ra[\u0001\u0002MB!q\u0003\u001c h\u0013\ti\'CA\u0005Gk:\u001cG/[8oc!)!M\u0004a\u0001}\u0011)\u0001O\u0004b\u0001E\t\t\u0011\n
   #9 = Utf8               scala/concurrent/BlockContext$DefaultBlockContext$
  #10 = Class              #9             // scala/concurrent/BlockContext$DefaultBlockContext$
  #11 = Utf8               DefaultBlockContext$
  #12 = Utf8               usingBlockContext
  #13 = Utf8               (Lscala/concurrent/BlockContext;Lscala/Function1;)Ljava/lang/Object;
  #14 = Utf8               <I:Ljava/lang/Object;T:Ljava/lang/Object;>(Lscala/concurrent/BlockContext;Lscala/Function1<Lscala/concurrent/BlockContext;TT;>;)TT;
  #15 = Utf8               blockContext
  #16 = Utf8               f
  #17 = Utf8               scala/concurrent/BlockContext$
  #18 = Class              #17            // scala/concurrent/BlockContext$
  #19 = Utf8               MODULE$
  #20 = Utf8               Lscala/concurrent/BlockContext$;
  #21 = NameAndType        #19:#20        // MODULE$:Lscala/concurrent/BlockContext$;
  #22 = Fieldref           #18.#21        // scala/concurrent/BlockContext$.MODULE$:Lscala/concurrent/BlockContext$;
  #23 = NameAndType        #12:#13        // usingBlockContext:(Lscala/concurrent/BlockContext;Lscala/Function1;)Ljava/lang/Object;
  #24 = Methodref          #18.#23        // scala/concurrent/BlockContext$.usingBlockContext:(Lscala/concurrent/BlockContext;Lscala/Function1;)Ljava/lang/Object;
  #25 = Utf8               Lscala/concurrent/BlockContext;
  #26 = Utf8               Lscala/Function1;
  #27 = Utf8               withBlockContext
  #28 = Utf8               (Lscala/concurrent/BlockContext;Lscala/Function0;)Ljava/lang/Object;
  #29 = Utf8               <T:Ljava/lang/Object;>(Lscala/concurrent/BlockContext;Lscala/Function0<TT;>;)TT;
  #30 = Utf8               body
  #31 = NameAndType        #27:#28        // withBlockContext:(Lscala/concurrent/BlockContext;Lscala/Function0;)Ljava/lang/Object;
  #32 = Methodref          #18.#31        // scala/concurrent/BlockContext$.withBlockContext:(Lscala/concurrent/BlockContext;Lscala/Function0;)Ljava/lang/Object;
  #33 = Utf8               Lscala/Function0;
  #34 = Utf8               current
  #35 = Utf8               ()Lscala/concurrent/BlockContext;
  #36 = NameAndType        #34:#35        // current:()Lscala/concurrent/BlockContext;
  #37 = Methodref          #18.#36        // scala/concurrent/BlockContext$.current:()Lscala/concurrent/BlockContext;
  #38 = Utf8               defaultBlockContext
  #39 = Utf8               Lscala/concurrent/BlockContext$DefaultBlockContext$;
  #40 = NameAndType        #19:#39        // MODULE$:Lscala/concurrent/BlockContext$DefaultBlockContext$;
  #41 = Fieldref           #10.#40        // scala/concurrent/BlockContext$DefaultBlockContext$.MODULE$:Lscala/concurrent/BlockContext$DefaultBlockContext$;
  #42 = Utf8               blockOn
  #43 = Utf8               (Lscala/Function0;Lscala/concurrent/CanAwait;)Ljava/lang/Object;
  #44 = Utf8               <T:Ljava/lang/Object;>(Lscala/Function0<TT;>;Lscala/concurrent/CanAwait;)TT;
  #45 = Utf8               thunk
  #46 = Utf8               permission
  #47 = Utf8               Code
  #48 = Utf8               LocalVariableTable
  #49 = Utf8               Signature
  #50 = Utf8               MethodParameters
  #51 = Utf8               LineNumberTable
  #52 = Utf8               InnerClasses
  #53 = Utf8               SourceFile
  #54 = Utf8               RuntimeVisibleAnnotations
  #55 = Utf8               ScalaInlineInfo
  #56 = Utf8               ScalaSig
{
  public static <I extends java.lang.Object, T extends java.lang.Object> T usingBlockContext(scala.concurrent.BlockContext, scala.Function1<scala.concurrent.BlockContext, T>);
    descriptor: (Lscala/concurrent/BlockContext;Lscala/Function1;)Ljava/lang/Object;
    flags: (0x0009) ACC_PUBLIC, ACC_STATIC
    Code:
      stack=3, locals=2, args_size=2
         0: getstatic     #22                 // Field scala/concurrent/BlockContext$.MODULE$:Lscala/concurrent/BlockContext$;
         3: aload_0
         4: aload_1
         5: invokevirtual #24                 // Method scala/concurrent/BlockContext$.usingBlockContext:(Lscala/concurrent/BlockContext;Lscala/Function1;)Ljava/lang/Object;
         8: areturn
      LocalVariableTable:
        Start  Length  Slot  Name   Signature
            0       9     0 blockContext   Lscala/concurrent/BlockContext;
            0       9     1     f   Lscala/Function1;
    Signature: #14                          // <I:Ljava/lang/Object;T:Ljava/lang/Object;>(Lscala/concurrent/BlockContext;Lscala/Function1<Lscala/concurrent/BlockContext;TT;>;)TT;
    MethodParameters:
      Name                           Flags
      blockContext                   final
      f                              final

  public static <T extends java.lang.Object> T withBlockContext(scala.concurrent.BlockContext, scala.Function0<T>);
    descriptor: (Lscala/concurrent/BlockContext;Lscala/Function0;)Ljava/lang/Object;
    flags: (0x0009) ACC_PUBLIC, ACC_STATIC
    Code:
      stack=3, locals=2, args_size=2
         0: getstatic     #22                 // Field scala/concurrent/BlockContext$.MODULE$:Lscala/concurrent/BlockContext$;
         3: aload_0
         4: aload_1
         5: invokevirtual #32                 // Method scala/concurrent/BlockContext$.withBlockContext:(Lscala/concurrent/BlockContext;Lscala/Function0;)Ljava/lang/Object;
         8: areturn
      LocalVariableTable:
        Start  Length  Slot  Name   Signature
            0       9     0 blockContext   Lscala/concurrent/BlockContext;
            0       9     1  body   Lscala/Function0;
    Signature: #29                          // <T:Ljava/lang/Object;>(Lscala/concurrent/BlockContext;Lscala/Function0<TT;>;)TT;
    MethodParameters:
      Name                           Flags
      blockContext                   final
      body                           final

  public static scala.concurrent.BlockContext current();
    descriptor: ()Lscala/concurrent/BlockContext;
    flags: (0x0009) ACC_PUBLIC, ACC_STATIC
    Code:
      stack=1, locals=0, args_size=0
         0: getstatic     #22                 // Field scala/concurrent/BlockContext$.MODULE$:Lscala/concurrent/BlockContext$;
         3: invokevirtual #37                 // Method scala/concurrent/BlockContext$.current:()Lscala/concurrent/BlockContext;
         6: areturn

  public static scala.concurrent.BlockContext defaultBlockContext();
    descriptor: ()Lscala/concurrent/BlockContext;
    flags: (0x0009) ACC_PUBLIC, ACC_STATIC
    Code:
      stack=1, locals=0, args_size=0
         0: getstatic     #22                 // Field scala/concurrent/BlockContext$.MODULE$:Lscala/concurrent/BlockContext$;
         3: pop
         4: getstatic     #41                 // Field scala/concurrent/BlockContext$DefaultBlockContext$.MODULE$:Lscala/concurrent/BlockContext$DefaultBlockContext$;
         7: areturn
      LineNumberTable:
        line 69: 4

  public abstract <T extends java.lang.Object> T blockOn(scala.Function0<T>, scala.concurrent.CanAwait);
    descriptor: (Lscala/Function0;Lscala/concurrent/CanAwait;)Ljava/lang/Object;
    flags: (0x0401) ACC_PUBLIC, ACC_ABSTRACT
    Signature: #44                          // <T:Ljava/lang/Object;>(Lscala/Function0<TT;>;Lscala/concurrent/CanAwait;)TT;
    MethodParameters:
      Name                           Flags
      thunk                          final
      permission                     final
}
InnerClasses:
  private static #11= #10 of #2;          // DefaultBlockContext$=class scala/concurrent/BlockContext$DefaultBlockContext$ of class scala/concurrent/BlockContext
SourceFile: "BlockContext.scala"
RuntimeVisibleAnnotations:
  0: #6(#7=s#8)
    scala.reflect.ScalaSignature(
      bytes="\u0006\u0005E4qa\u0004\t\u0011\u0002G\u0005Q\u0003C\u0003\u001b\u0001\u0019\u00051dB\u00035!!\u0005QGB\u0003\u0010!!\u0005a\u0007C\u00038\u0007\u0011\u0005\u0001h\u0002\u0004:\u0007\u0001FIA\u000f\u0004\u0007y\r\u0001\u000b\u0012B\u001f\t\u000b]2A\u0011A \t\u000bi1AQ\t!\t\u000b!\u001bAQA%\t\r)\u001b\u0001\u0015!\u0004L\u0011\u0019\u00196\u0001)C\u0007)\")qk\u0001C\u0003\u0013\")\u0001l\u0001C\u00033\")1m\u0001C\u0003I\na!\t\\8dW\u000e{g\u000e^3yi*\u0011\u0011CE\u0001\u000bG>t7-\u001e:sK:$(\"A\n\u0002\u000bM\u001c\u0017\r\\1\u0004\u0001M\u0011\u0001A\u0006\t\u0003/ai\u0011AE\u0005\u00033I\u0011a!\u00118z%\u00164\u0017a\u00022m_\u000e\\wJ\\\u000b\u00039\u0001\"\"!H\u0018\u0015\u0005yI\u0003CA\u0010!\u0019\u0001!Q!I\u0001C\u0002\t\u0012\u0011\u0001V\t\u0003G\u0019\u0002\"a\u0006\u0013\n\u0005\u0015\u0012\"a\u0002(pi\"Lgn\u001a\t\u0003/\u001dJ!\u0001\u000b\n\u0003\u0007\u0005s\u0017\u0010C\u0003+\u0003\u0001\u000f1&\u0001\u0006qKJl\u0017n]:j_:\u0004\"\u0001L\u0017\u000e\u0003AI!A\f\t\u0003\u0011\r\u000bg.Q<bSRDa\u0001M\u0001\u0005\u0002\u0004\t\u0014!\u0002;ik:\\\u0007cA\f3=%\u00111G\u0005\u0002\ty\tLh.Y7f}\u0005a!\t\\8dW\u000e{g\u000e^3yiB\u0011AfA\n\u0003\u0007Y\ta\u0001P5oSRtD#A\u001b\u0002\'\u0011+g-Y;mi\ncwnY6D_:$X\r\u001f;\u0011\u0005m2Q\"A\u0002\u0003\'\u0011+g-Y;mi\ncwnY6D_:$X\r\u001f;\u0014\u0007\u00191b\b\u0005\u0002-\u0001Q\t!(\u0006\u0002B\tR\u0011!I\u0012\u000b\u0003\u0007\u0016\u0003\"a\b#\u0005\u000b\u0005B!\u0019\u0001\u0012\t\u000b)B\u00019A\u0016\t\rABA\u00111\u0001H!\r9\"gQ\u0001\u0014I\u00164\u0017-\u001e7u\u00052|7m[\"p]R,\u0007\u0010^\u000b\u0002}\u0005a1m\u001c8uKb$Hj\\2bYB\u0019A*\u0015 \u000e\u00035S!AT(\u0002\t1\fgn\u001a\u0006\u0002!\u0006!!.\u0019<b\u0013\t\u0011VJA\u0006UQJ,\u0017\r\u001a\'pG\u0006d\u0017A\u00029sK\u001a,\'\u000f\u0006\u0002?+\")ak\u0003a\u0001}\u0005I1-\u00198eS\u0012\fG/Z\u0001\bGV\u0014(/\u001a8u\u0003A9\u0018\u000e\u001e5CY>\u001c7nQ8oi\u0016DH/\u0006\u0002[;R\u00111,\u0019\u000b\u00039z\u0003\"aH/\u0005\u000b\u0005j!\u0019\u0001\u0012\t\r}kA\u00111\u0001a\u0003\u0011\u0011w\u000eZ=\u0011\u0007]\u0011D\fC\u0003c\u001b\u0001\u0007a(\u0001\u0007cY>\u001c7nQ8oi\u0016DH/A\tvg&twM\u00117pG.\u001cuN\u001c;fqR,2!Z8i)\t1g\u000e\u0006\u0002hSB\u0011q\u0004\u001b\u0003\u0006C9\u0011\rA\t\u0005\u0006U:\u0001\ra[\u0001\u0002MB!q\u0003\u001c h\u0013\ti\'CA\u0005Gk:\u001cG/[8oc!)!M\u0004a\u0001}\u0011)\u0001O\u0004b\u0001E\t\t\u0011\n"
    )
  ScalaInlineInfo: length = 0x9 (unknown attribute)
   01 00 00 01 00 2A 00 2B 00
  ScalaSig: length = 0x3 (unknown attribute)
   05 02 00
