Classfile /Users/mw/Projects/slang-braindump/.jar/jar8/assemble/slang-braindump/assemble/content/scala/concurrent/Channel$LinkedList.class
  Last modified May 29, 2022; size 1493 bytes
  SHA-256 checksum cdb44728e7bea84cc525cc03867993e3283a223c5676e84c2b9a33335d1d64d0
  Compiled from "Channel.scala"
public class scala.concurrent.Channel$LinkedList
  minor version: 0
  major version: 52
  flags: (0x0021) ACC_PUBLIC, ACC_SUPER
  this_class: #2                          // scala/concurrent/Channel$LinkedList
  super_class: #4                         // java/lang/Object
  interfaces: 0, fields: 3, methods: 6, attributes: 4
Constant pool:
   #1 = Utf8               scala/concurrent/Channel$LinkedList
   #2 = Class              #1             // scala/concurrent/Channel$LinkedList
   #3 = Utf8               java/lang/Object
   #4 = Class              #3             // java/lang/Object
   #5 = Utf8               Channel.scala
   #6 = Utf8               scala/concurrent/Channel
   #7 = Class              #6             // scala/concurrent/Channel
   #8 = Utf8               LinkedList
   #9 = Utf8               elem
  #10 = Utf8               Ljava/lang/Object;
  #11 = Utf8               TA;
  #12 = Utf8               next
  #13 = Utf8               Lscala/concurrent/Channel$LinkedList;
  #14 = Utf8               Lscala/concurrent/Channel<TA;>.LinkedList;
  #15 = Utf8               $outer
  #16 = Utf8               Lscala/concurrent/Channel;
  #17 = Utf8               ()Ljava/lang/Object;
  #18 = Utf8               ()TA;
  #19 = NameAndType        #9:#10         // elem:Ljava/lang/Object;
  #20 = Fieldref           #2.#19         // scala/concurrent/Channel$LinkedList.elem:Ljava/lang/Object;
  #21 = Utf8               this
  #22 = Utf8               elem_$eq
  #23 = Utf8               (Ljava/lang/Object;)V
  #24 = Utf8               (TA;)V
  #25 = Utf8               x$1
  #26 = Utf8               ()Lscala/concurrent/Channel$LinkedList;
  #27 = Utf8               ()Lscala/concurrent/Channel<TA;>.LinkedList;
  #28 = NameAndType        #12:#13        // next:Lscala/concurrent/Channel$LinkedList;
  #29 = Fieldref           #2.#28         // scala/concurrent/Channel$LinkedList.next:Lscala/concurrent/Channel$LinkedList;
  #30 = Utf8               next_$eq
  #31 = Utf8               (Lscala/concurrent/Channel$LinkedList;)V
  #32 = Utf8               (Lscala/concurrent/Channel<TA;>.LinkedList;)V
  #33 = Utf8               scala$concurrent$Channel$LinkedList$$$outer
  #34 = Utf8               ()Lscala/concurrent/Channel;
  #35 = NameAndType        #15:#16        // $outer:Lscala/concurrent/Channel;
  #36 = Fieldref           #2.#35         // scala/concurrent/Channel$LinkedList.$outer:Lscala/concurrent/Channel;
  #37 = Utf8               <init>
  #38 = Utf8               (Lscala/concurrent/Channel;)V
  #39 = Utf8               ()V
  #40 = NameAndType        #37:#39        // "<init>":()V
  #41 = Methodref          #4.#40         // java/lang/Object."<init>":()V
  #42 = Utf8               Signature
  #43 = Utf8               Code
  #44 = Utf8               LineNumberTable
  #45 = Utf8               LocalVariableTable
  #46 = Utf8               MethodParameters
  #47 = Utf8               StackMapTable
  #48 = Utf8               InnerClasses
  #49 = Utf8               SourceFile
  #50 = Utf8               ScalaInlineInfo
  #51 = Utf8               Scala
{
  private A elem;
    descriptor: Ljava/lang/Object;
    flags: (0x0002) ACC_PRIVATE
    Signature: #11                          // TA;

  private scala.concurrent.Channel<A>.LinkedList next;
    descriptor: Lscala/concurrent/Channel$LinkedList;
    flags: (0x0002) ACC_PRIVATE
    Signature: #14                          // Lscala/concurrent/Channel<TA;>.LinkedList;

  public final scala.concurrent.Channel $outer;
    descriptor: Lscala/concurrent/Channel;
    flags: (0x1011) ACC_PUBLIC, ACC_FINAL, ACC_SYNTHETIC

  public A elem();
    descriptor: ()Ljava/lang/Object;
    flags: (0x0001) ACC_PUBLIC
    Code:
      stack=1, locals=1, args_size=1
         0: aload_0
         1: getfield      #20                 // Field elem:Ljava/lang/Object;
         4: areturn
      LineNumberTable:
        line 23: 0
      LocalVariableTable:
        Start  Length  Slot  Name   Signature
            0       5     0  this   Lscala/concurrent/Channel$LinkedList;
    Signature: #18                          // ()TA;

  public void elem_$eq(A);
    descriptor: (Ljava/lang/Object;)V
    flags: (0x0001) ACC_PUBLIC
    Code:
      stack=2, locals=2, args_size=2
         0: aload_0
         1: aload_1
         2: putfield      #20                 // Field elem:Ljava/lang/Object;
         5: return
      LineNumberTable:
        line 23: 0
      LocalVariableTable:
        Start  Length  Slot  Name   Signature
            0       6     0  this   Lscala/concurrent/Channel$LinkedList;
            0       6     1   x$1   Ljava/lang/Object;
    Signature: #24                          // (TA;)V
    MethodParameters:
      Name                           Flags
      x$1                            final

  public scala.concurrent.Channel<A>.LinkedList next();
    descriptor: ()Lscala/concurrent/Channel$LinkedList;
    flags: (0x0001) ACC_PUBLIC
    Code:
      stack=1, locals=1, args_size=1
         0: aload_0
         1: getfield      #29                 // Field next:Lscala/concurrent/Channel$LinkedList;
         4: areturn
      LineNumberTable:
        line 24: 0
      LocalVariableTable:
        Start  Length  Slot  Name   Signature
            0       5     0  this   Lscala/concurrent/Channel$LinkedList;
    Signature: #27                          // ()Lscala/concurrent/Channel<TA;>.LinkedList;

  public void next_$eq(scala.concurrent.Channel<A>.LinkedList);
    descriptor: (Lscala/concurrent/Channel$LinkedList;)V
    flags: (0x0001) ACC_PUBLIC
    Code:
      stack=2, locals=2, args_size=2
         0: aload_0
         1: aload_1
         2: putfield      #29                 // Field next:Lscala/concurrent/Channel$LinkedList;
         5: return
      LineNumberTable:
        line 24: 0
      LocalVariableTable:
        Start  Length  Slot  Name   Signature
            0       6     0  this   Lscala/concurrent/Channel$LinkedList;
            0       6     1   x$1   Lscala/concurrent/Channel$LinkedList;
    Signature: #32                          // (Lscala/concurrent/Channel<TA;>.LinkedList;)V
    MethodParameters:
      Name                           Flags
      x$1                            final

  public scala.concurrent.Channel scala$concurrent$Channel$LinkedList$$$outer();
    descriptor: ()Lscala/concurrent/Channel;
    flags: (0x1001) ACC_PUBLIC, ACC_SYNTHETIC
    Code:
      stack=1, locals=1, args_size=1
         0: aload_0
         1: getfield      #36                 // Field $outer:Lscala/concurrent/Channel;
         4: areturn
      LineNumberTable:
        line 22: 0
      LocalVariableTable:
        Start  Length  Slot  Name   Signature
            0       5     0  this   Lscala/concurrent/Channel$LinkedList;

  public scala.concurrent.Channel$LinkedList(scala.concurrent.Channel);
    descriptor: (Lscala/concurrent/Channel;)V
    flags: (0x0001) ACC_PUBLIC
    Code:
      stack=2, locals=2, args_size=2
         0: aload_1
         1: ifnonnull     6
         4: aconst_null
         5: athrow
         6: aload_0
         7: aload_1
         8: putfield      #36                 // Field $outer:Lscala/concurrent/Channel;
        11: aload_0
        12: invokespecial #41                 // Method java/lang/Object."<init>":()V
        15: return
      StackMapTable: number_of_entries = 1
        frame_type = 6 /* same */
      LineNumberTable:
        line 22: 0
      LocalVariableTable:
        Start  Length  Slot  Name   Signature
            0      16     0  this   Lscala/concurrent/Channel$LinkedList;
            0      16     1 $outer   Lscala/concurrent/Channel;
    MethodParameters:
      Name                           Flags
      $outer                         final synthetic
}
InnerClasses:
  private #8= #2 of #7;                   // LinkedList=class scala/concurrent/Channel$LinkedList of class scala/concurrent/Channel
SourceFile: "Channel.scala"
  ScalaInlineInfo: length = 0x22 (unknown attribute)
   01 00 00 06 00 25 00 26 00 00 09 00 11 00 00 16
   00 17 00 00 0C 00 1A 00 00 1E 00 1F 00 00 21 00
   22 00
  Scala: length = 0x0 (unknown attribute)

