Classfile /Users/mw/Projects/slang-braindump/.jar/jar8/assemble/slang-braindump/assemble/content/scala/concurrent/ExecutionContext.class
  Last modified May 29, 2022; size 5017 bytes
  SHA-256 checksum 9c5ebe47c22e2438e5c9dadeeea41ae65a154c158ff413ac04966274abbbcef9
  Compiled from "ExecutionContext.scala"
public interface scala.concurrent.ExecutionContext
  minor version: 0
  major version: 52
  flags: (0x0601) ACC_PUBLIC, ACC_INTERFACE, ACC_ABSTRACT
  this_class: #2                          // scala/concurrent/ExecutionContext
  super_class: #4                         // java/lang/Object
  interfaces: 0, fields: 0, methods: 11, attributes: 5
Constant pool:
   #1 = Utf8               scala/concurrent/ExecutionContext
   #2 = Class              #1             // scala/concurrent/ExecutionContext
   #3 = Utf8               java/lang/Object
   #4 = Class              #3             // java/lang/Object
   #5 = Utf8               ExecutionContext.scala
   #6 = Utf8               Lscala/reflect/ScalaSignature;
   #7 = Utf8               bytes
   #8 = Utf8               \u0006\u0005\u0005Eda\u0002\u000e\u001c!\u0003\r\t\u0001\t\u0005\u0006K\u0001!\tA\n\u0005\u0006U\u00011\ta\u000b\u0005\u0006m\u00011\ta\u000e\u0005\u0006=\u0002!\taX\u0004\u0006mnA\ta\u001e\u0004\u00065mA\t\u0001\u001f\u0005\u0006s\u001a!\tA\u001f\u0005\tw\u001aA)\u0019!C\u0003y\u001e9\u0011\u0011\u0001\u0004\t\u0002\u0005\raaBA\u0004\r!\u0005\u0011\u0011\u0002\u0005\u0007s*!\t!!\u0005\t\u000f\u0005M!\u0002\"\u0012\u0002\u0016!1!F\u0003C#\u00033AaA\u000e\u0006\u0005F\u0005u\u0001BCA\u0011\r!\u0015\r\u0011\"\u0001\u001ey\u001e9\u00111\u0005\u0004\t\u0002\u0005\u0015baBA\u0014\r!\u0005\u0011\u0011\u0006\u0005\u0007sF!\t!a\u000b\t\rm\fBqAA\u0017\u0011\u001d\tyC\u0002C\u0001\u0003cAq!a\f\u0007\t\u0003\t)\u0006C\u0004\u0002Z\u0019!\t!a\u0017\t\u000f\u0005ec\u0001\"\u0001\u0002h!I\u00111\u000e\u0004C\u0002\u0013\u0015\u0011Q\u000e\u0005\t\u0003_2\u0001\u0015!\u0004\u0002P\t\u0001R\t_3dkRLwN\\\"p]R,\u0007\u0010\u001e\u0006\u00039u\t!bY8oGV\u0014(/\u001a8u\u0015\u0005q\u0012!B:dC2\f7\u0001A\n\u0003\u0001\u0005\u0002\"AI\u0012\u000e\u0003uI!\u0001J\u000f\u0003\r\u0005s\u0017PU3g\u0003\u0019!\u0013N\\5uIQ\tq\u0005\u0005\u0002#Q%\u0011\u0011&\b\u0002\u0005+:LG/A\u0004fq\u0016\u001cW\u000f^3\u0015\u0005\u001db\u0003\"B\u0017\u0003\u0001\u0004q\u0013\u0001\u0003:v]:\f\'\r\\3\u0011\u0005=\"T\"\u0001\u0019\u000b\u0005E\u0012\u0014\u0001\u00027b]\u001eT\u0011aM\u0001\u0005U\u00064\u0018-\u0003\u00026a\tA!+\u001e8oC\ndW-A\u0007sKB|\'\u000f\u001e$bS2,(/\u001a\u000b\u0003OaBQ!O\u0002A\u0002i\nQaY1vg\u0016\u0004\"aO\"\u000f\u0005q\neBA\u001fA\u001b\u0005q$BA  \u0003\u0019a$o\\8u}%\ta$\u0003\u0002C;\u00059\u0001/Y2lC\u001e,\u0017B\u0001#F\u0005%!\u0006N]8xC\ndWM\u0003\u0002C;!\"\u0001h\u0012&M!\t\u0011\u0003*\u0003\u0002J;\tqA-\u001a9sK\u000e\fG/\u001a3OC6,\u0017%A&\u0002\u0003Q\fTaI\'V3Z\u0003\"A\u0014*\u000f\u0005=\u0003\u0006CA\u001f\u001e\u0013\t\tV$\u0001\u0004Qe\u0016$WMZ\u0005\u0003\'R\u0013aa\u0015;sS:<\'BA)\u001e\u0013\t1v+A\u000e%Y\u0016\u001c8/\u001b8ji\u0012:\'/Z1uKJ$C-\u001a4bk2$HE\r\u0006\u00031v\ta\u0002Z3qe\u0016\u001c\u0017\r^3e\u001d\u0006lW-M\u0003$5nc\u0006L\u0004\u0002#7&\u0011\u0001,H\u0019\u0005E\tjRLA\u0003tG\u0006d\u0017-A\u0004qe\u0016\u0004\u0018M]3\u0015\u0003\u0001\u0004\"!\u0019\u0001\u000e\u0003mAc\u0001B2gO&T\u0007C\u0001\u0012e\u0013\t)WD\u0001\u0006eKB\u0014XmY1uK\u0012\fq!\\3tg\u0006<W-I\u0001i\u0003A\u0002(/\u001a9be\u0006$\u0018n\u001c8!_\u001a\u0004S\t_3dkRLwN\\\"p]R,\u0007\u0010^:!o&dG\u000e\t2fAI,Wn\u001c<fI\u0006)1/\u001b8dK\u0006\n1.\u0001\u00043]E\u0012d\u0006\r\u0015\u0005\u00015\u001cH\u000f\u0005\u0002oc6\tqN\u0003\u0002q;\u0005Q\u0011M\u001c8pi\u0006$\u0018n\u001c8\n\u0005I|\'\u0001E5na2L7-\u001b;O_R4u.\u001e8e\u0003\ri7oZ\u0011\u0002k\u0006!\u0019dQ1o]>$\bEZ5oI\u0002\ng\u000eI5na2L7-\u001b;!\u000bb,7-\u001e;j_:\u001cuN\u001c;fqRt\u0003%W8vA5Lw\r\u001b;!C\u0012$\'\"\u00198!Q%l\u0007\u000f\\5dSR\u0004Sm\u0019\u001e!\u000bb,7-\u001e;j_:\u001cuN\u001c;fqRL\u0003\u0005]1sC6,G/\u001a:!i>\u0004\u0013p\\;sA5,G\u000f[8e])QA\u000b[3!\u000bb,7-\u001e;j_:\u001cuN\u001c;fqR\u0004\u0013n\u001d\u0011vg\u0016$\u0007\u0005^8!G>tg-[4ve\u0016\u0004\u0003n\\<!C:$\u0007e\u001c8!o\"L7\r\u001b\u0006uQJ,\u0017\r\u001a\u0011q_>d7\u000fI1ts:\u001c\u0007N]8o_V\u001c\b\u0005^1tWN\u0004\u0003f];dQ\u0002\n7\u000f\t$viV\u0014Xm]\u0015!o&dG\u000e\t:v]2R1o\u001c\u0011uQ\u0016\u00043\u000f]3dS\u001aL7\rI#yK\u000e,H/[8o\u0007>tG/\u001a=uAQD\u0017\r\u001e\u0011jg\u0002\u001aX\r\\3di\u0016$\u0007%[:!S6\u0004xN\u001d;b]Rt#BC%gAe|WO\u001d\u0011baBd\u0017nY1uS>t\u0007\u0005Z8fg\u0002rw\u000e\u001e\u0011eK\u001aLg.\u001a\u0011b]\u0002*\u00050Z2vi&|gnQ8oi\u0016DH\u000fI3mg\u0016<\b.\u001a:fY)\u0019wN\\:jI\u0016\u0014\b%^:j]\u001e\u00043kY1mC\u001e\u001a\be\u001a7pE\u0006d\u0007%\u0012=fGV$\u0018n\u001c8D_:$X\r\u001f;!Ef\u0004C-\u001a4j]&twM\u0003;iK\u00022w\u000e\u001c7po&twM\u000f\u0006\u000bS6\u0004H.[2ji\u00022\u0018\r\u001c\u0011fGj\u00023oY1mC:\u001awN\\2veJ,g\u000e\u001e\u0018Fq\u0016\u001cW\u000f^5p]\u000e{g\u000e^3yi\u0002j\u0004e]2bY\u0006t3m\u001c8dkJ\u0014XM\u001c;/\u000bb,7-\u001e;j_:\u001cuN\u001c;fqRts\r\\8cC2\f\u0001#\u0012=fGV$\u0018n\u001c8D_:$X\r\u001f;\u0011\u0005\u000541C\u0001\u0004\"\u0003\u0019a\u0014N\\5u}Q\tq/\u0001\u0004hY>\u0014\u0017\r\\\u000b\u0002{B\u0011\u0011M`\u0005\u0003\u007fn\u0011\u0001$\u0012=fGV$\u0018n\u001c8D_:$X\r\u001f;Fq\u0016\u001cW\u000f^8s\u0003%\u0001\u0018M]1tSRL7\rE\u0002\u0002\u0006)i\u0011A\u0002\u0002\na\u0006\u0014\u0018m]5uS\u000e\u001cRAC\u0011~\u0003\u0017\u00012!YA\u0007\u0013\r\tya\u0007\u0002\u0011\u0005\u0006$8\r[5oO\u0016CXmY;u_J$\"!a\u0001\u0002%M,(-\\5u\r>\u0014X\t_3dkRLwN\u001c\u000b\u0004O\u0005]\u0001\"B\u0017\r\u0001\u0004qCcA\u0014\u0002\u001c!)Q&\u0004a\u0001]Q\u0019q%a\b\t\u000b-s\u0001\u0019\u0001\u001e\u0002\u001b=\u0004\bo\u001c:uk:L7\u000f^5d\u0003%IU\u000e\u001d7jG&$8\u000fE\u0002\u0002\u0006E\u0011\u0011\"S7qY&\u001c\u0017\u000e^:\u0014\u0005E\tCCAA\u0013+\u0005\u0001\u0017a\u00054s_6,\u00050Z2vi>\u00148+\u001a:wS\u000e,GCBA\u001a\u0003s\tY\u0005E\u0002b\u0003kI1!a\u000e\u001c\u0005})\u00050Z2vi&|gnQ8oi\u0016DH/\u0012=fGV$xN]*feZL7-\u001a\u0005\b\u0003w!\u0002\u0019AA\u001f\u0003\u0005)\u0007\u0003BA \u0003\u000fj!!!\u0011\u000b\u0007q\t\u0019EC\u0002\u0002FI\nA!\u001e;jY&!\u0011\u0011JA!\u0005=)\u00050Z2vi>\u00148+\u001a:wS\u000e,\u0007bBA\')\u0001\u0007\u0011qJ\u0001\te\u0016\u0004xN\u001d;feB)!%!\u0015;O%\u0019\u00111K\u000f\u0003\u0013\u0019+hn\u0019;j_:\fD\u0003BA\u001a\u0003/Bq!a\u000f\u0016\u0001\u0004\ti$\u0001\u0007ge>lW\t_3dkR|\'\u000fF\u0003~\u0003;\n)\u0007C\u0004\u0002<Y\u0001\r!a\u0018\u0011\t\u0005}\u0012\u0011M\u0005\u0005\u0003G\n\tE\u0001\u0005Fq\u0016\u001cW\u000f^8s\u0011\u001d\tiE\u0006a\u0001\u0003\u001f\"2!`A5\u0011\u001d\tYd\u0006a\u0001\u0003?\nq\u0002Z3gCVdGOU3q_J$XM]\u000b\u0003\u0003\u001f\n\u0001\u0003Z3gCVdGOU3q_J$XM\u001d\u0011
   #9 = Utf8               scala/concurrent/ExecutionContext$Implicits$
  #10 = Class              #9             // scala/concurrent/ExecutionContext$Implicits$
  #11 = Utf8               Implicits$
  #12 = Utf8               scala/concurrent/ExecutionContext$parasitic$
  #13 = Class              #12            // scala/concurrent/ExecutionContext$parasitic$
  #14 = Utf8               parasitic$
  #15 = Utf8               defaultReporter
  #16 = Utf8               ()Lscala/Function1;
  #17 = Utf8               ()Lscala/Function1<Ljava/lang/Throwable;Lscala/runtime/BoxedUnit;>;
  #18 = Utf8               scala/concurrent/ExecutionContext$
  #19 = Class              #18            // scala/concurrent/ExecutionContext$
  #20 = Utf8               MODULE$
  #21 = Utf8               Lscala/concurrent/ExecutionContext$;
  #22 = NameAndType        #20:#21        // MODULE$:Lscala/concurrent/ExecutionContext$;
  #23 = Fieldref           #19.#22        // scala/concurrent/ExecutionContext$.MODULE$:Lscala/concurrent/ExecutionContext$;
  #24 = NameAndType        #15:#16        // defaultReporter:()Lscala/Function1;
  #25 = Methodref          #19.#24        // scala/concurrent/ExecutionContext$.defaultReporter:()Lscala/Function1;
  #26 = Utf8               fromExecutor
  #27 = Utf8               (Ljava/util/concurrent/Executor;)Lscala/concurrent/ExecutionContextExecutor;
  #28 = Utf8               e
  #29 = NameAndType        #26:#27        // fromExecutor:(Ljava/util/concurrent/Executor;)Lscala/concurrent/ExecutionContextExecutor;
  #30 = Methodref          #19.#29        // scala/concurrent/ExecutionContext$.fromExecutor:(Ljava/util/concurrent/Executor;)Lscala/concurrent/ExecutionContextExecutor;
  #31 = Utf8               Ljava/util/concurrent/Executor;
  #32 = Utf8               (Ljava/util/concurrent/Executor;Lscala/Function1;)Lscala/concurrent/ExecutionContextExecutor;
  #33 = Utf8               (Ljava/util/concurrent/Executor;Lscala/Function1<Ljava/lang/Throwable;Lscala/runtime/BoxedUnit;>;)Lscala/concurrent/ExecutionContextExecutor;
  #34 = Utf8               reporter
  #35 = Utf8               scala/concurrent/impl/ExecutionContextImpl$
  #36 = Class              #35            // scala/concurrent/impl/ExecutionContextImpl$
  #37 = Utf8               Lscala/concurrent/impl/ExecutionContextImpl$;
  #38 = NameAndType        #20:#37        // MODULE$:Lscala/concurrent/impl/ExecutionContextImpl$;
  #39 = Fieldref           #36.#38        // scala/concurrent/impl/ExecutionContextImpl$.MODULE$:Lscala/concurrent/impl/ExecutionContextImpl$;
  #40 = NameAndType        #26:#32        // fromExecutor:(Ljava/util/concurrent/Executor;Lscala/Function1;)Lscala/concurrent/ExecutionContextExecutor;
  #41 = Methodref          #36.#40        // scala/concurrent/impl/ExecutionContextImpl$.fromExecutor:(Ljava/util/concurrent/Executor;Lscala/Function1;)Lscala/concurrent/ExecutionContextExecutor;
  #42 = Utf8               Lscala/Function1;
  #43 = Utf8               fromExecutorService
  #44 = Utf8               (Ljava/util/concurrent/ExecutorService;)Lscala/concurrent/ExecutionContextExecutorService;
  #45 = NameAndType        #43:#44        // fromExecutorService:(Ljava/util/concurrent/ExecutorService;)Lscala/concurrent/ExecutionContextExecutorService;
  #46 = Methodref          #19.#45        // scala/concurrent/ExecutionContext$.fromExecutorService:(Ljava/util/concurrent/ExecutorService;)Lscala/concurrent/ExecutionContextExecutorService;
  #47 = Utf8               Ljava/util/concurrent/ExecutorService;
  #48 = Utf8               (Ljava/util/concurrent/ExecutorService;Lscala/Function1;)Lscala/concurrent/ExecutionContextExecutorService;
  #49 = Utf8               (Ljava/util/concurrent/ExecutorService;Lscala/Function1<Ljava/lang/Throwable;Lscala/runtime/BoxedUnit;>;)Lscala/concurrent/ExecutionContextExecutorService;
  #50 = NameAndType        #43:#48        // fromExecutorService:(Ljava/util/concurrent/ExecutorService;Lscala/Function1;)Lscala/concurrent/ExecutionContextExecutorService;
  #51 = Methodref          #36.#50        // scala/concurrent/impl/ExecutionContextImpl$.fromExecutorService:(Ljava/util/concurrent/ExecutorService;Lscala/Function1;)Lscala/concurrent/ExecutionContextExecutorService;
  #52 = Utf8               global
  #53 = Utf8               ()Lscala/concurrent/ExecutionContextExecutor;
  #54 = NameAndType        #52:#53        // global:()Lscala/concurrent/ExecutionContextExecutor;
  #55 = Methodref          #19.#54        // scala/concurrent/ExecutionContext$.global:()Lscala/concurrent/ExecutionContextExecutor;
  #56 = Utf8               execute
  #57 = Utf8               (Ljava/lang/Runnable;)V
  #58 = Utf8               runnable
  #59 = Utf8               reportFailure
  #60 = Utf8               (Ljava/lang/Throwable;)V
  #61 = Utf8               cause
  #62 = Utf8               prepare$
  #63 = Utf8               (Lscala/concurrent/ExecutionContext;)Lscala/concurrent/ExecutionContext;
  #64 = Utf8               $this
  #65 = Utf8               prepare
  #66 = Utf8               ()Lscala/concurrent/ExecutionContext;
  #67 = NameAndType        #65:#66        // prepare:()Lscala/concurrent/ExecutionContext;
  #68 = InterfaceMethodref #2.#67         // scala/concurrent/ExecutionContext.prepare:()Lscala/concurrent/ExecutionContext;
  #69 = Utf8               Lscala/concurrent/ExecutionContext;
  #70 = Utf8               this
  #71 = Utf8               $init$
  #72 = Utf8               (Lscala/concurrent/ExecutionContext;)V
  #73 = Utf8               Code
  #74 = Utf8               Signature
  #75 = Utf8               LocalVariableTable
  #76 = Utf8               MethodParameters
  #77 = Utf8               LineNumberTable
  #78 = Utf8               Deprecated
  #79 = Utf8               InnerClasses
  #80 = Utf8               SourceFile
  #81 = Utf8               RuntimeVisibleAnnotations
  #82 = Utf8               ScalaInlineInfo
  #83 = Utf8               ScalaSig
{
  public static scala.Function1<java.lang.Throwable, scala.runtime.BoxedUnit> defaultReporter();
    descriptor: ()Lscala/Function1;
    flags: (0x0009) ACC_PUBLIC, ACC_STATIC
    Code:
      stack=1, locals=0, args_size=0
         0: getstatic     #23                 // Field scala/concurrent/ExecutionContext$.MODULE$:Lscala/concurrent/ExecutionContext$;
         3: invokevirtual #25                 // Method scala/concurrent/ExecutionContext$.defaultReporter:()Lscala/Function1;
         6: areturn
    Signature: #17                          // ()Lscala/Function1<Ljava/lang/Throwable;Lscala/runtime/BoxedUnit;>;

  public static scala.concurrent.ExecutionContextExecutor fromExecutor(java.util.concurrent.Executor);
    descriptor: (Ljava/util/concurrent/Executor;)Lscala/concurrent/ExecutionContextExecutor;
    flags: (0x0009) ACC_PUBLIC, ACC_STATIC
    Code:
      stack=2, locals=1, args_size=1
         0: getstatic     #23                 // Field scala/concurrent/ExecutionContext$.MODULE$:Lscala/concurrent/ExecutionContext$;
         3: aload_0
         4: invokevirtual #30                 // Method scala/concurrent/ExecutionContext$.fromExecutor:(Ljava/util/concurrent/Executor;)Lscala/concurrent/ExecutionContextExecutor;
         7: areturn
      LocalVariableTable:
        Start  Length  Slot  Name   Signature
            0       8     0     e   Ljava/util/concurrent/Executor;
    MethodParameters:
      Name                           Flags
      e                              final

  public static scala.concurrent.ExecutionContextExecutor fromExecutor(java.util.concurrent.Executor, scala.Function1<java.lang.Throwable, scala.runtime.BoxedUnit>);
    descriptor: (Ljava/util/concurrent/Executor;Lscala/Function1;)Lscala/concurrent/ExecutionContextExecutor;
    flags: (0x0009) ACC_PUBLIC, ACC_STATIC
    Code:
      stack=3, locals=2, args_size=2
         0: getstatic     #23                 // Field scala/concurrent/ExecutionContext$.MODULE$:Lscala/concurrent/ExecutionContext$;
         3: pop
         4: getstatic     #39                 // Field scala/concurrent/impl/ExecutionContextImpl$.MODULE$:Lscala/concurrent/impl/ExecutionContextImpl$;
         7: aload_0
         8: aload_1
         9: invokevirtual #41                 // Method scala/concurrent/impl/ExecutionContextImpl$.fromExecutor:(Ljava/util/concurrent/Executor;Lscala/Function1;)Lscala/concurrent/ExecutionContextExecutor;
        12: areturn
      LineNumberTable:
        line 281: 4
      LocalVariableTable:
        Start  Length  Slot  Name   Signature
            0      13     0     e   Ljava/util/concurrent/Executor;
            0      13     1 reporter   Lscala/Function1;
    Signature: #33                          // (Ljava/util/concurrent/Executor;Lscala/Function1<Ljava/lang/Throwable;Lscala/runtime/BoxedUnit;>;)Lscala/concurrent/ExecutionContextExecutor;
    MethodParameters:
      Name                           Flags
      e                              final
      reporter                       final

  public static scala.concurrent.ExecutionContextExecutorService fromExecutorService(java.util.concurrent.ExecutorService);
    descriptor: (Ljava/util/concurrent/ExecutorService;)Lscala/concurrent/ExecutionContextExecutorService;
    flags: (0x0009) ACC_PUBLIC, ACC_STATIC
    Code:
      stack=2, locals=1, args_size=1
         0: getstatic     #23                 // Field scala/concurrent/ExecutionContext$.MODULE$:Lscala/concurrent/ExecutionContext$;
         3: aload_0
         4: invokevirtual #46                 // Method scala/concurrent/ExecutionContext$.fromExecutorService:(Ljava/util/concurrent/ExecutorService;)Lscala/concurrent/ExecutionContextExecutorService;
         7: areturn
      LocalVariableTable:
        Start  Length  Slot  Name   Signature
            0       8     0     e   Ljava/util/concurrent/ExecutorService;
    MethodParameters:
      Name                           Flags
      e                              final

  public static scala.concurrent.ExecutionContextExecutorService fromExecutorService(java.util.concurrent.ExecutorService, scala.Function1<java.lang.Throwable, scala.runtime.BoxedUnit>);
    descriptor: (Ljava/util/concurrent/ExecutorService;Lscala/Function1;)Lscala/concurrent/ExecutionContextExecutorService;
    flags: (0x0009) ACC_PUBLIC, ACC_STATIC
    Code:
      stack=3, locals=2, args_size=2
         0: getstatic     #23                 // Field scala/concurrent/ExecutionContext$.MODULE$:Lscala/concurrent/ExecutionContext$;
         3: pop
         4: getstatic     #39                 // Field scala/concurrent/impl/ExecutionContextImpl$.MODULE$:Lscala/concurrent/impl/ExecutionContextImpl$;
         7: aload_0
         8: aload_1
         9: invokevirtual #51                 // Method scala/concurrent/impl/ExecutionContextImpl$.fromExecutorService:(Ljava/util/concurrent/ExecutorService;Lscala/Function1;)Lscala/concurrent/ExecutionContextExecutorService;
        12: areturn
      LineNumberTable:
        line 257: 4
      LocalVariableTable:
        Start  Length  Slot  Name   Signature
            0      13     0     e   Ljava/util/concurrent/ExecutorService;
            0      13     1 reporter   Lscala/Function1;
    Signature: #49                          // (Ljava/util/concurrent/ExecutorService;Lscala/Function1<Ljava/lang/Throwable;Lscala/runtime/BoxedUnit;>;)Lscala/concurrent/ExecutionContextExecutorService;
    MethodParameters:
      Name                           Flags
      e                              final
      reporter                       final

  public static scala.concurrent.ExecutionContextExecutor global();
    descriptor: ()Lscala/concurrent/ExecutionContextExecutor;
    flags: (0x0009) ACC_PUBLIC, ACC_STATIC
    Code:
      stack=1, locals=0, args_size=0
         0: getstatic     #23                 // Field scala/concurrent/ExecutionContext$.MODULE$:Lscala/concurrent/ExecutionContext$;
         3: invokevirtual #55                 // Method scala/concurrent/ExecutionContext$.global:()Lscala/concurrent/ExecutionContextExecutor;
         6: areturn

  public abstract void execute(java.lang.Runnable);
    descriptor: (Ljava/lang/Runnable;)V
    flags: (0x0401) ACC_PUBLIC, ACC_ABSTRACT
    MethodParameters:
      Name                           Flags
      runnable                       final

  public abstract void reportFailure(java.lang.Throwable);
    descriptor: (Ljava/lang/Throwable;)V
    flags: (0x0401) ACC_PUBLIC, ACC_ABSTRACT
    MethodParameters:
      Name                           Flags
      cause                          final

  public static scala.concurrent.ExecutionContext prepare$(scala.concurrent.ExecutionContext);
    descriptor: (Lscala/concurrent/ExecutionContext;)Lscala/concurrent/ExecutionContext;
    flags: (0x1009) ACC_PUBLIC, ACC_STATIC, ACC_SYNTHETIC
    Code:
      stack=1, locals=1, args_size=1
         0: aload_0
         1: invokespecial #68                 // InterfaceMethod prepare:()Lscala/concurrent/ExecutionContext;
         4: areturn
      LineNumberTable:
        line 104: 0
      LocalVariableTable:
        Start  Length  Slot  Name   Signature
            0       5     0 $this   Lscala/concurrent/ExecutionContext;
    MethodParameters:
      Name                           Flags
      $this                          final synthetic

  public default scala.concurrent.ExecutionContext prepare();
    descriptor: ()Lscala/concurrent/ExecutionContext;
    flags: (0x0001) ACC_PUBLIC
    Code:
      stack=1, locals=1, args_size=1
         0: aload_0
         1: areturn
      LineNumberTable:
        line 104: 0
      LocalVariableTable:
        Start  Length  Slot  Name   Signature
            0       2     0  this   Lscala/concurrent/ExecutionContext;
    Deprecated: true

  public static void $init$(scala.concurrent.ExecutionContext);
    descriptor: (Lscala/concurrent/ExecutionContext;)V
    flags: (0x0009) ACC_PUBLIC, ACC_STATIC
    Code:
      stack=0, locals=1, args_size=1
         0: return
      LineNumberTable:
        line 72: 0
      LocalVariableTable:
        Start  Length  Slot  Name   Signature
            0       1     0 $this   Lscala/concurrent/ExecutionContext;
    MethodParameters:
      Name                           Flags
      $this                          final synthetic
}
InnerClasses:
  public static #11= #10 of #2;           // Implicits$=class scala/concurrent/ExecutionContext$Implicits$ of class scala/concurrent/ExecutionContext
  public static #14= #13 of #2;           // parasitic$=class scala/concurrent/ExecutionContext$parasitic$ of class scala/concurrent/ExecutionContext
SourceFile: "ExecutionContext.scala"
RuntimeVisibleAnnotations:
  0: #6(#7=s#8)
    scala.reflect.ScalaSignature(
      bytes="\u0006\u0005\u0005Eda\u0002\u000e\u001c!\u0003\r\t\u0001\t\u0005\u0006K\u0001!\tA\n\u0005\u0006U\u00011\ta\u000b\u0005\u0006m\u00011\ta\u000e\u0005\u0006=\u0002!\taX\u0004\u0006mnA\ta\u001e\u0004\u00065mA\t\u0001\u001f\u0005\u0006s\u001a!\tA\u001f\u0005\tw\u001aA)\u0019!C\u0003y\u001e9\u0011\u0011\u0001\u0004\t\u0002\u0005\raaBA\u0004\r!\u0005\u0011\u0011\u0002\u0005\u0007s*!\t!!\u0005\t\u000f\u0005M!\u0002\"\u0012\u0002\u0016!1!F\u0003C#\u00033AaA\u000e\u0006\u0005F\u0005u\u0001BCA\u0011\r!\u0015\r\u0011\"\u0001\u001ey\u001e9\u00111\u0005\u0004\t\u0002\u0005\u0015baBA\u0014\r!\u0005\u0011\u0011\u0006\u0005\u0007sF!\t!a\u000b\t\rm\fBqAA\u0017\u0011\u001d\tyC\u0002C\u0001\u0003cAq!a\f\u0007\t\u0003\t)\u0006C\u0004\u0002Z\u0019!\t!a\u0017\t\u000f\u0005ec\u0001\"\u0001\u0002h!I\u00111\u000e\u0004C\u0002\u0013\u0015\u0011Q\u000e\u0005\t\u0003_2\u0001\u0015!\u0004\u0002P\t\u0001R\t_3dkRLwN\\\"p]R,\u0007\u0010\u001e\u0006\u00039u\t!bY8oGV\u0014(/\u001a8u\u0015\u0005q\u0012!B:dC2\f7\u0001A\n\u0003\u0001\u0005\u0002\"AI\u0012\u000e\u0003uI!\u0001J\u000f\u0003\r\u0005s\u0017PU3g\u0003\u0019!\u0013N\\5uIQ\tq\u0005\u0005\u0002#Q%\u0011\u0011&\b\u0002\u0005+:LG/A\u0004fq\u0016\u001cW\u000f^3\u0015\u0005\u001db\u0003\"B\u0017\u0003\u0001\u0004q\u0013\u0001\u0003:v]:\f\'\r\\3\u0011\u0005=\"T\"\u0001\u0019\u000b\u0005E\u0012\u0014\u0001\u00027b]\u001eT\u0011aM\u0001\u0005U\u00064\u0018-\u0003\u00026a\tA!+\u001e8oC\ndW-A\u0007sKB|\'\u000f\u001e$bS2,(/\u001a\u000b\u0003OaBQ!O\u0002A\u0002i\nQaY1vg\u0016\u0004\"aO\"\u000f\u0005q\neBA\u001fA\u001b\u0005q$BA  \u0003\u0019a$o\\8u}%\ta$\u0003\u0002C;\u00059\u0001/Y2lC\u001e,\u0017B\u0001#F\u0005%!\u0006N]8xC\ndWM\u0003\u0002C;!\"\u0001h\u0012&M!\t\u0011\u0003*\u0003\u0002J;\tqA-\u001a9sK\u000e\fG/\u001a3OC6,\u0017%A&\u0002\u0003Q\fTaI\'V3Z\u0003\"A\u0014*\u000f\u0005=\u0003\u0006CA\u001f\u001e\u0013\t\tV$\u0001\u0004Qe\u0016$WMZ\u0005\u0003\'R\u0013aa\u0015;sS:<\'BA)\u001e\u0013\t1v+A\u000e%Y\u0016\u001c8/\u001b8ji\u0012:\'/Z1uKJ$C-\u001a4bk2$HE\r\u0006\u00031v\ta\u0002Z3qe\u0016\u001c\u0017\r^3e\u001d\u0006lW-M\u0003$5nc\u0006L\u0004\u0002#7&\u0011\u0001,H\u0019\u0005E\tjRLA\u0003tG\u0006d\u0017-A\u0004qe\u0016\u0004\u0018M]3\u0015\u0003\u0001\u0004\"!\u0019\u0001\u000e\u0003mAc\u0001B2gO&T\u0007C\u0001\u0012e\u0013\t)WD\u0001\u0006eKB\u0014XmY1uK\u0012\fq!\\3tg\u0006<W-I\u0001i\u0003A\u0002(/\u001a9be\u0006$\u0018n\u001c8!_\u001a\u0004S\t_3dkRLwN\\\"p]R,\u0007\u0010^:!o&dG\u000e\t2fAI,Wn\u001c<fI\u0006)1/\u001b8dK\u0006\n1.\u0001\u00043]E\u0012d\u0006\r\u0015\u0005\u00015\u001cH\u000f\u0005\u0002oc6\tqN\u0003\u0002q;\u0005Q\u0011M\u001c8pi\u0006$\u0018n\u001c8\n\u0005I|\'\u0001E5na2L7-\u001b;O_R4u.\u001e8e\u0003\ri7oZ\u0011\u0002k\u0006!\u0019dQ1o]>$\bEZ5oI\u0002\ng\u000eI5na2L7-\u001b;!\u000bb,7-\u001e;j_:\u001cuN\u001c;fqRt\u0003%W8vA5Lw\r\u001b;!C\u0012$\'\"\u00198!Q%l\u0007\u000f\\5dSR\u0004Sm\u0019\u001e!\u000bb,7-\u001e;j_:\u001cuN\u001c;fqRL\u0003\u0005]1sC6,G/\u001a:!i>\u0004\u0013p\\;sA5,G\u000f[8e])QA\u000b[3!\u000bb,7-\u001e;j_:\u001cuN\u001c;fqR\u0004\u0013n\u001d\u0011vg\u0016$\u0007\u0005^8!G>tg-[4ve\u0016\u0004\u0003n\\<!C:$\u0007e\u001c8!o\"L7\r\u001b\u0006uQJ,\u0017\r\u001a\u0011q_>d7\u000fI1ts:\u001c\u0007N]8o_V\u001c\b\u0005^1tWN\u0004\u0003f];dQ\u0002\n7\u000f\t$viV\u0014Xm]\u0015!o&dG\u000e\t:v]2R1o\u001c\u0011uQ\u0016\u00043\u000f]3dS\u001aL7\rI#yK\u000e,H/[8o\u0007>tG/\u001a=uAQD\u0017\r\u001e\u0011jg\u0002\u001aX\r\\3di\u0016$\u0007%[:!S6\u0004xN\u001d;b]Rt#BC%gAe|WO\u001d\u0011baBd\u0017nY1uS>t\u0007\u0005Z8fg\u0002rw\u000e\u001e\u0011eK\u001aLg.\u001a\u0011b]\u0002*\u00050Z2vi&|gnQ8oi\u0016DH\u000fI3mg\u0016<\b.\u001a:fY)\u0019wN\\:jI\u0016\u0014\b%^:j]\u001e\u00043kY1mC\u001e\u001a\be\u001a7pE\u0006d\u0007%\u0012=fGV$\u0018n\u001c8D_:$X\r\u001f;!Ef\u0004C-\u001a4j]&twM\u0003;iK\u00022w\u000e\u001c7po&twM\u000f\u0006\u000bS6\u0004H.[2ji\u00022\u0018\r\u001c\u0011fGj\u00023oY1mC:\u001awN\\2veJ,g\u000e\u001e\u0018Fq\u0016\u001cW\u000f^5p]\u000e{g\u000e^3yi\u0002j\u0004e]2bY\u0006t3m\u001c8dkJ\u0014XM\u001c;/\u000bb,7-\u001e;j_:\u001cuN\u001c;fqRts\r\\8cC2\f\u0001#\u0012=fGV$\u0018n\u001c8D_:$X\r\u001f;\u0011\u0005\u000541C\u0001\u0004\"\u0003\u0019a\u0014N\\5u}Q\tq/\u0001\u0004hY>\u0014\u0017\r\\\u000b\u0002{B\u0011\u0011M`\u0005\u0003\u007fn\u0011\u0001$\u0012=fGV$\u0018n\u001c8D_:$X\r\u001f;Fq\u0016\u001cW\u000f^8s\u0003%\u0001\u0018M]1tSRL7\rE\u0002\u0002\u0006)i\u0011A\u0002\u0002\na\u0006\u0014\u0018m]5uS\u000e\u001cRAC\u0011~\u0003\u0017\u00012!YA\u0007\u0013\r\tya\u0007\u0002\u0011\u0005\u0006$8\r[5oO\u0016CXmY;u_J$\"!a\u0001\u0002%M,(-\\5u\r>\u0014X\t_3dkRLwN\u001c\u000b\u0004O\u0005]\u0001\"B\u0017\r\u0001\u0004qCcA\u0014\u0002\u001c!)Q&\u0004a\u0001]Q\u0019q%a\b\t\u000b-s\u0001\u0019\u0001\u001e\u0002\u001b=\u0004\bo\u001c:uk:L7\u000f^5d\u0003%IU\u000e\u001d7jG&$8\u000fE\u0002\u0002\u0006E\u0011\u0011\"S7qY&\u001c\u0017\u000e^:\u0014\u0005E\tCCAA\u0013+\u0005\u0001\u0017a\u00054s_6,\u00050Z2vi>\u00148+\u001a:wS\u000e,GCBA\u001a\u0003s\tY\u0005E\u0002b\u0003kI1!a\u000e\u001c\u0005})\u00050Z2vi&|gnQ8oi\u0016DH/\u0012=fGV$xN]*feZL7-\u001a\u0005\b\u0003w!\u0002\u0019AA\u001f\u0003\u0005)\u0007\u0003BA \u0003\u000fj!!!\u0011\u000b\u0007q\t\u0019EC\u0002\u0002FI\nA!\u001e;jY&!\u0011\u0011JA!\u0005=)\u00050Z2vi>\u00148+\u001a:wS\u000e,\u0007bBA\')\u0001\u0007\u0011qJ\u0001\te\u0016\u0004xN\u001d;feB)!%!\u0015;O%\u0019\u00111K\u000f\u0003\u0013\u0019+hn\u0019;j_:\fD\u0003BA\u001a\u0003/Bq!a\u000f\u0016\u0001\u0004\ti$\u0001\u0007ge>lW\t_3dkR|\'\u000fF\u0003~\u0003;\n)\u0007C\u0004\u0002<Y\u0001\r!a\u0018\u0011\t\u0005}\u0012\u0011M\u0005\u0005\u0003G\n\tE\u0001\u0005Fq\u0016\u001cW\u000f^8s\u0011\u001d\tiE\u0006a\u0001\u0003\u001f\"2!`A5\u0011\u001d\tYd\u0006a\u0001\u0003?\nq\u0002Z3gCVdGOU3q_J$XM]\u000b\u0003\u0003\u001f\n\u0001\u0003Z3gCVdGOU3q_J$XM\u001d\u0011"
    )
  ScalaInlineInfo: length = 0x1D (unknown attribute)
   01 00 00 05 00 47 00 48 01 00 38 00 39 00 00 41
   00 42 00 00 3E 00 3F 01 00 3B 00 3C 00
  ScalaSig: length = 0x3 (unknown attribute)
   05 02 00
