Classfile /Users/mw/Projects/slang-braindump/.jar/jar8/assemble/slang-braindump/assemble/content/scala/concurrent/Future$.class
  Last modified May 29, 2022; size 22787 bytes
  SHA-256 checksum 42ec2921672fb67bb56c175d0590fe407bdfb6f4dd5477f8d92be1bf059b4283
  Compiled from "Future.scala"
public final class scala.concurrent.Future$
  minor version: 0
  major version: 52
  flags: (0x0031) ACC_PUBLIC, ACC_FINAL, ACC_SUPER
  this_class: #2                          // scala/concurrent/Future$
  super_class: #4                         // java/lang/Object
  interfaces: 0, fields: 13, methods: 46, attributes: 5
Constant pool:
    #1 = Utf8               scala/concurrent/Future$
    #2 = Class              #1            // scala/concurrent/Future$
    #3 = Utf8               java/lang/Object
    #4 = Class              #3            // java/lang/Object
    #5 = Utf8               Future.scala
    #6 = Utf8               java/lang/invoke/MethodHandles$Lookup
    #7 = Class              #6            // java/lang/invoke/MethodHandles$Lookup
    #8 = Utf8               java/lang/invoke/MethodHandles
    #9 = Class              #8            // java/lang/invoke/MethodHandles
   #10 = Utf8               Lookup
   #11 = Utf8               scala/Predef$ArrowAssoc$
   #12 = Class              #11           // scala/Predef$ArrowAssoc$
   #13 = Utf8               scala/Predef
   #14 = Class              #13           // scala/Predef
   #15 = Utf8               ArrowAssoc$
   #16 = Utf8               scala/collection/IterableFactory$$anon$1
   #17 = Class              #16           // scala/collection/IterableFactory$$anon$1
   #18 = Utf8               scala/concurrent/ExecutionContext$parasitic$
   #19 = Class              #18           // scala/concurrent/ExecutionContext$parasitic$
   #20 = Utf8               scala/concurrent/ExecutionContext
   #21 = Class              #20           // scala/concurrent/ExecutionContext
   #22 = Utf8               parasitic$
   #23 = Utf8               scala/concurrent/Future$$anon$1
   #24 = Class              #23           // scala/concurrent/Future$$anon$1
   #25 = Utf8               scala/concurrent/Future$$anon$2
   #26 = Class              #25           // scala/concurrent/Future$$anon$2
   #27 = Utf8               scala/concurrent/Future$$anon$3
   #28 = Class              #27           // scala/concurrent/Future$$anon$3
   #29 = Utf8               scala/concurrent/Future$$anon$4
   #30 = Class              #29           // scala/concurrent/Future$$anon$4
   #31 = Utf8               scala/concurrent/Future$$anon$5
   #32 = Class              #31           // scala/concurrent/Future$$anon$5
   #33 = Utf8               scala/concurrent/Future$never$
   #34 = Class              #33           // scala/concurrent/Future$never$
   #35 = Utf8               scala/concurrent/Future
   #36 = Class              #35           // scala/concurrent/Future
   #37 = Utf8               never$
   #38 = Utf8               scala/concurrent/impl/Promise$DefaultPromise
   #39 = Class              #38           // scala/concurrent/impl/Promise$DefaultPromise
   #40 = Utf8               scala/concurrent/impl/Promise
   #41 = Class              #40           // scala/concurrent/impl/Promise
   #42 = Utf8               DefaultPromise
   #43 = Utf8               MODULE$
   #44 = Utf8               Lscala/concurrent/Future$;
   #45 = Utf8               toBoxed
   #46 = Utf8               Lscala/collection/immutable/Map;
   #47 = Utf8               Lscala/collection/immutable/Map<Ljava/lang/Class<*>;Ljava/lang/Class<*>;>;
   #48 = Utf8               _cachedId
   #49 = Utf8               Lscala/Function1;
   #50 = Utf8               Lscala/Function1<Ljava/lang/Object;Ljava/lang/Object;>;
   #51 = Utf8               collectFailed
   #52 = Utf8               Lscala/Function1<Ljava/lang/Object;Lscala/runtime/Nothing$;>;
   #53 = Utf8               filterFailure
   #54 = Utf8               Lscala/util/Failure;
   #55 = Utf8               Lscala/util/Failure<Lscala/runtime/Nothing$;>;
   #56 = Utf8               failedFailure
   #57 = Utf8               failedFailureFuture
   #58 = Utf8               Lscala/concurrent/Future;
   #59 = Utf8               Lscala/concurrent/Future<Lscala/runtime/Nothing$;>;
   #60 = Utf8               _failedFun
   #61 = Utf8               Lscala/Function1<Lscala/util/Try<Ljava/lang/Object;>;Lscala/util/Try<Ljava/lang/Throwable;>;>;
   #62 = Utf8               recoverWithFailedMarker
   #63 = Utf8               recoverWithFailed
   #64 = Utf8               Lscala/Function1<Ljava/lang/Throwable;Lscala/concurrent/Future<Lscala/runtime/Nothing$;>;>;
   #65 = Utf8               _zipWithTuple2
   #66 = Utf8               Lscala/Function2;
   #67 = Utf8               Lscala/Function2<Ljava/lang/Object;Ljava/lang/Object;Lscala/Tuple2<Ljava/lang/Object;Ljava/lang/Object;>;>;
   #68 = Utf8               _addToBuilderFun
   #69 = Utf8               Lscala/Function2<Lscala/collection/mutable/Builder<Ljava/lang/Object;Lscala/runtime/Nothing$;>;Ljava/lang/Object;Lscala/collection/mutable/Builder<Ljava/lang/Object;Lscala/runtime/Nothing$;>;>;
   #70 = Utf8               unit
   #71 = Utf8               Lscala/concurrent/Future<Lscala/runtime/BoxedUnit;>;
   #72 = Utf8               <clinit>
   #73 = Utf8               ()V
   #74 = Utf8               <init>
   #75 = NameAndType        #74:#73       // "<init>":()V
   #76 = Methodref          #2.#75        // scala/concurrent/Future$."<init>":()V
   #77 = NameAndType        #43:#44       // MODULE$:Lscala/concurrent/Future$;
   #78 = Fieldref           #2.#77        // scala/concurrent/Future$.MODULE$:Lscala/concurrent/Future$;
   #79 = Utf8               scala/Predef$
   #80 = Class              #79           // scala/Predef$
   #81 = Utf8               Lscala/Predef$;
   #82 = NameAndType        #43:#81       // MODULE$:Lscala/Predef$;
   #83 = Fieldref           #80.#82       // scala/Predef$.MODULE$:Lscala/Predef$;
   #84 = Utf8               Map
   #85 = Utf8               ()Lscala/collection/immutable/Map$;
   #86 = NameAndType        #84:#85       // Map:()Lscala/collection/immutable/Map$;
   #87 = Methodref          #80.#86       // scala/Predef$.Map:()Lscala/collection/immutable/Map$;
   #88 = Utf8               scala/runtime/ScalaRunTime$
   #89 = Class              #88           // scala/runtime/ScalaRunTime$
   #90 = Utf8               Lscala/runtime/ScalaRunTime$;
   #91 = NameAndType        #43:#90       // MODULE$:Lscala/runtime/ScalaRunTime$;
   #92 = Fieldref           #89.#91       // scala/runtime/ScalaRunTime$.MODULE$:Lscala/runtime/ScalaRunTime$;
   #93 = Utf8               scala/Tuple2
   #94 = Class              #93           // scala/Tuple2
   #95 = Utf8               Lscala/Predef$ArrowAssoc$;
   #96 = NameAndType        #43:#95       // MODULE$:Lscala/Predef$ArrowAssoc$;
   #97 = Fieldref           #12.#96       // scala/Predef$ArrowAssoc$.MODULE$:Lscala/Predef$ArrowAssoc$;
   #98 = Utf8               java/lang/Boolean
   #99 = Class              #98           // java/lang/Boolean
  #100 = Utf8               TYPE
  #101 = Utf8               Ljava/lang/Class;
  #102 = NameAndType        #100:#101     // TYPE:Ljava/lang/Class;
  #103 = Fieldref           #99.#102      // java/lang/Boolean.TYPE:Ljava/lang/Class;
  #104 = Utf8               (Ljava/lang/Object;Ljava/lang/Object;)V
  #105 = NameAndType        #74:#104      // "<init>":(Ljava/lang/Object;Ljava/lang/Object;)V
  #106 = Methodref          #94.#105      // scala/Tuple2."<init>":(Ljava/lang/Object;Ljava/lang/Object;)V
  #107 = Utf8               java/lang/Byte
  #108 = Class              #107          // java/lang/Byte
  #109 = Fieldref           #108.#102     // java/lang/Byte.TYPE:Ljava/lang/Class;
  #110 = Utf8               java/lang/Character
  #111 = Class              #110          // java/lang/Character
  #112 = Fieldref           #111.#102     // java/lang/Character.TYPE:Ljava/lang/Class;
  #113 = Utf8               java/lang/Short
  #114 = Class              #113          // java/lang/Short
  #115 = Fieldref           #114.#102     // java/lang/Short.TYPE:Ljava/lang/Class;
  #116 = Utf8               java/lang/Integer
  #117 = Class              #116          // java/lang/Integer
  #118 = Fieldref           #117.#102     // java/lang/Integer.TYPE:Ljava/lang/Class;
  #119 = Utf8               java/lang/Long
  #120 = Class              #119          // java/lang/Long
  #121 = Fieldref           #120.#102     // java/lang/Long.TYPE:Ljava/lang/Class;
  #122 = Utf8               java/lang/Float
  #123 = Class              #122          // java/lang/Float
  #124 = Fieldref           #123.#102     // java/lang/Float.TYPE:Ljava/lang/Class;
  #125 = Utf8               java/lang/Double
  #126 = Class              #125          // java/lang/Double
  #127 = Fieldref           #126.#102     // java/lang/Double.TYPE:Ljava/lang/Class;
  #128 = Utf8               scala/runtime/BoxedUnit
  #129 = Class              #128          // scala/runtime/BoxedUnit
  #130 = Fieldref           #129.#102     // scala/runtime/BoxedUnit.TYPE:Ljava/lang/Class;
  #131 = Utf8               wrapRefArray
  #132 = Utf8               ([Ljava/lang/Object;)Lscala/collection/immutable/ArraySeq;
  #133 = NameAndType        #131:#132     // wrapRefArray:([Ljava/lang/Object;)Lscala/collection/immutable/ArraySeq;
  #134 = Methodref          #89.#133      // scala/runtime/ScalaRunTime$.wrapRefArray:([Ljava/lang/Object;)Lscala/collection/immutable/ArraySeq;
  #135 = Utf8               scala/collection/immutable/Map$
  #136 = Class              #135          // scala/collection/immutable/Map$
  #137 = Utf8               from
  #138 = Utf8               (Lscala/collection/IterableOnce;)Lscala/collection/immutable/Map;
  #139 = NameAndType        #137:#138     // from:(Lscala/collection/IterableOnce;)Lscala/collection/immutable/Map;
  #140 = Methodref          #136.#139     // scala/collection/immutable/Map$.from:(Lscala/collection/IterableOnce;)Lscala/collection/immutable/Map;
  #141 = NameAndType        #45:#46       // toBoxed:Lscala/collection/immutable/Map;
  #142 = Fieldref           #2.#141       // scala/concurrent/Future$.toBoxed:Lscala/collection/immutable/Map;
  #143 = Utf8               (Ljava/lang/Object;)Ljava/lang/Object;
  #144 = MethodType         #143          //  (Ljava/lang/Object;)Ljava/lang/Object;
  #145 = Utf8               $anonfun$_cachedId$1
  #146 = NameAndType        #145:#143     // $anonfun$_cachedId$1:(Ljava/lang/Object;)Ljava/lang/Object;
  #147 = Methodref          #2.#146       // scala/concurrent/Future$.$anonfun$_cachedId$1:(Ljava/lang/Object;)Ljava/lang/Object;
  #148 = MethodHandle       6:#147        // REF_invokeStatic scala/concurrent/Future$.$anonfun$_cachedId$1:(Ljava/lang/Object;)Ljava/lang/Object;
  #149 = Integer            1
  #150 = Utf8               java/lang/invoke/LambdaMetafactory
  #151 = Class              #150          // java/lang/invoke/LambdaMetafactory
  #152 = Utf8               altMetafactory
  #153 = Utf8               (Ljava/lang/invoke/MethodHandles$Lookup;Ljava/lang/String;Ljava/lang/invoke/MethodType;[Ljava/lang/Object;)Ljava/lang/invoke/CallSite;
  #154 = NameAndType        #152:#153     // altMetafactory:(Ljava/lang/invoke/MethodHandles$Lookup;Ljava/lang/String;Ljava/lang/invoke/MethodType;[Ljava/lang/Object;)Ljava/lang/invoke/CallSite;
  #155 = Methodref          #151.#154     // java/lang/invoke/LambdaMetafactory.altMetafactory:(Ljava/lang/invoke/MethodHandles$Lookup;Ljava/lang/String;Ljava/lang/invoke/MethodType;[Ljava/lang/Object;)Ljava/lang/invoke/CallSite;
  #156 = MethodHandle       6:#155        // REF_invokeStatic java/lang/invoke/LambdaMetafactory.altMetafactory:(Ljava/lang/invoke/MethodHandles$Lookup;Ljava/lang/String;Ljava/lang/invoke/MethodType;[Ljava/lang/Object;)Ljava/lang/invoke/CallSite;
  #157 = Utf8               apply
  #158 = Utf8               ()Lscala/Function1;
  #159 = NameAndType        #157:#158     // apply:()Lscala/Function1;
  #160 = InvokeDynamic      #0:#159       // #0:apply:()Lscala/Function1;
  #161 = NameAndType        #48:#49       // _cachedId:Lscala/Function1;
  #162 = Fieldref           #2.#161       // scala/concurrent/Future$._cachedId:Lscala/Function1;
  #163 = Utf8               $anonfun$collectFailed$1
  #164 = Utf8               (Ljava/lang/Object;)Lscala/runtime/Nothing$;
  #165 = NameAndType        #163:#164     // $anonfun$collectFailed$1:(Ljava/lang/Object;)Lscala/runtime/Nothing$;
  #166 = Methodref          #2.#165       // scala/concurrent/Future$.$anonfun$collectFailed$1:(Ljava/lang/Object;)Lscala/runtime/Nothing$;
  #167 = MethodHandle       6:#166        // REF_invokeStatic scala/concurrent/Future$.$anonfun$collectFailed$1:(Ljava/lang/Object;)Lscala/runtime/Nothing$;
  #168 = MethodType         #164          //  (Ljava/lang/Object;)Lscala/runtime/Nothing$;
  #169 = Integer            5
  #170 = InvokeDynamic      #1:#159       // #1:apply:()Lscala/Function1;
  #171 = NameAndType        #51:#49       // collectFailed:Lscala/Function1;
  #172 = Fieldref           #2.#171       // scala/concurrent/Future$.collectFailed:Lscala/Function1;
  #173 = Utf8               scala/util/Failure
  #174 = Class              #173          // scala/util/Failure
  #175 = Methodref          #26.#75       // scala/concurrent/Future$$anon$2."<init>":()V
  #176 = Utf8               (Ljava/lang/Throwable;)V
  #177 = NameAndType        #74:#176      // "<init>":(Ljava/lang/Throwable;)V
  #178 = Methodref          #174.#177     // scala/util/Failure."<init>":(Ljava/lang/Throwable;)V
  #179 = NameAndType        #53:#54       // filterFailure:Lscala/util/Failure;
  #180 = Fieldref           #2.#179       // scala/concurrent/Future$.filterFailure:Lscala/util/Failure;
  #181 = Methodref          #28.#75       // scala/concurrent/Future$$anon$3."<init>":()V
  #182 = NameAndType        #56:#54       // failedFailure:Lscala/util/Failure;
  #183 = Fieldref           #2.#182       // scala/concurrent/Future$.failedFailure:Lscala/util/Failure;
  #184 = Utf8               fromTry
  #185 = Utf8               (Lscala/util/Try;)Lscala/concurrent/Future;
  #186 = NameAndType        #184:#185     // fromTry:(Lscala/util/Try;)Lscala/concurrent/Future;
  #187 = Methodref          #2.#186       // scala/concurrent/Future$.fromTry:(Lscala/util/Try;)Lscala/concurrent/Future;
  #188 = NameAndType        #57:#58       // failedFailureFuture:Lscala/concurrent/Future;
  #189 = Fieldref           #2.#188       // scala/concurrent/Future$.failedFailureFuture:Lscala/concurrent/Future;
  #190 = Utf8               $anonfun$_failedFun$1
  #191 = Utf8               (Lscala/util/Try;)Lscala/util/Try;
  #192 = NameAndType        #190:#191     // $anonfun$_failedFun$1:(Lscala/util/Try;)Lscala/util/Try;
  #193 = Methodref          #2.#192       // scala/concurrent/Future$.$anonfun$_failedFun$1:(Lscala/util/Try;)Lscala/util/Try;
  #194 = MethodHandle       6:#193        // REF_invokeStatic scala/concurrent/Future$.$anonfun$_failedFun$1:(Lscala/util/Try;)Lscala/util/Try;
  #195 = MethodType         #191          //  (Lscala/util/Try;)Lscala/util/Try;
  #196 = InvokeDynamic      #2:#159       // #2:apply:()Lscala/Function1;
  #197 = NameAndType        #60:#49       // _failedFun:Lscala/Function1;
  #198 = Fieldref           #2.#197       // scala/concurrent/Future$._failedFun:Lscala/Function1;
  #199 = Methodref          #30.#75       // scala/concurrent/Future$$anon$4."<init>":()V
  #200 = Utf8               failed
  #201 = Utf8               (Ljava/lang/Throwable;)Lscala/concurrent/Future;
  #202 = NameAndType        #200:#201     // failed:(Ljava/lang/Throwable;)Lscala/concurrent/Future;
  #203 = Methodref          #2.#202       // scala/concurrent/Future$.failed:(Ljava/lang/Throwable;)Lscala/concurrent/Future;
  #204 = NameAndType        #62:#58       // recoverWithFailedMarker:Lscala/concurrent/Future;
  #205 = Fieldref           #2.#204       // scala/concurrent/Future$.recoverWithFailedMarker:Lscala/concurrent/Future;
  #206 = Utf8               $anonfun$recoverWithFailed$1
  #207 = NameAndType        #206:#201     // $anonfun$recoverWithFailed$1:(Ljava/lang/Throwable;)Lscala/concurrent/Future;
  #208 = Methodref          #2.#207       // scala/concurrent/Future$.$anonfun$recoverWithFailed$1:(Ljava/lang/Throwable;)Lscala/concurrent/Future;
  #209 = MethodHandle       6:#208        // REF_invokeStatic scala/concurrent/Future$.$anonfun$recoverWithFailed$1:(Ljava/lang/Throwable;)Lscala/concurrent/Future;
  #210 = MethodType         #201          //  (Ljava/lang/Throwable;)Lscala/concurrent/Future;
  #211 = InvokeDynamic      #3:#159       // #3:apply:()Lscala/Function1;
  #212 = NameAndType        #63:#49       // recoverWithFailed:Lscala/Function1;
  #213 = Fieldref           #2.#212       // scala/concurrent/Future$.recoverWithFailed:Lscala/Function1;
  #214 = Utf8               (Ljava/lang/Object;Ljava/lang/Object;)Ljava/lang/Object;
  #215 = MethodType         #214          //  (Ljava/lang/Object;Ljava/lang/Object;)Ljava/lang/Object;
  #216 = Utf8               $anonfun$_zipWithTuple2$1
  #217 = Utf8               (Ljava/lang/Object;Ljava/lang/Object;)Lscala/Tuple2;
  #218 = NameAndType        #216:#217     // $anonfun$_zipWithTuple2$1:(Ljava/lang/Object;Ljava/lang/Object;)Lscala/Tuple2;
  #219 = Methodref          #2.#218       // scala/concurrent/Future$.$anonfun$_zipWithTuple2$1:(Ljava/lang/Object;Ljava/lang/Object;)Lscala/Tuple2;
  #220 = MethodHandle       6:#219        // REF_invokeStatic scala/concurrent/Future$.$anonfun$_zipWithTuple2$1:(Ljava/lang/Object;Ljava/lang/Object;)Lscala/Tuple2;
  #221 = MethodType         #217          //  (Ljava/lang/Object;Ljava/lang/Object;)Lscala/Tuple2;
  #222 = Utf8               ()Lscala/Function2;
  #223 = NameAndType        #157:#222     // apply:()Lscala/Function2;
  #224 = InvokeDynamic      #4:#223       // #4:apply:()Lscala/Function2;
  #225 = NameAndType        #65:#66       // _zipWithTuple2:Lscala/Function2;
  #226 = Fieldref           #2.#225       // scala/concurrent/Future$._zipWithTuple2:Lscala/Function2;
  #227 = Utf8               $anonfun$_addToBuilderFun$1
  #228 = Utf8               (Lscala/collection/mutable/Builder;Ljava/lang/Object;)Lscala/collection/mutable/Builder;
  #229 = NameAndType        #227:#228     // $anonfun$_addToBuilderFun$1:(Lscala/collection/mutable/Builder;Ljava/lang/Object;)Lscala/collection/mutable/Builder;
  #230 = Methodref          #2.#229       // scala/concurrent/Future$.$anonfun$_addToBuilderFun$1:(Lscala/collection/mutable/Builder;Ljava/lang/Object;)Lscala/collection/mutable/Builder;
  #231 = MethodHandle       6:#230        // REF_invokeStatic scala/concurrent/Future$.$anonfun$_addToBuilderFun$1:(Lscala/collection/mutable/Builder;Ljava/lang/Object;)Lscala/collection/mutable/Builder;
  #232 = MethodType         #228          //  (Lscala/collection/mutable/Builder;Ljava/lang/Object;)Lscala/collection/mutable/Builder;
  #233 = InvokeDynamic      #5:#223       // #5:apply:()Lscala/Function2;
  #234 = NameAndType        #68:#66       // _addToBuilderFun:Lscala/Function2;
  #235 = Fieldref           #2.#234       // scala/concurrent/Future$._addToBuilderFun:Lscala/Function2;
  #236 = Utf8               scala/util/Success
  #237 = Class              #236          // scala/util/Success
  #238 = Utf8               UNIT
  #239 = Utf8               Lscala/runtime/BoxedUnit;
  #240 = NameAndType        #238:#239     // UNIT:Lscala/runtime/BoxedUnit;
  #241 = Fieldref           #129.#240     // scala/runtime/BoxedUnit.UNIT:Lscala/runtime/BoxedUnit;
  #242 = Utf8               (Ljava/lang/Object;)V
  #243 = NameAndType        #74:#242      // "<init>":(Ljava/lang/Object;)V
  #244 = Methodref          #237.#243     // scala/util/Success."<init>":(Ljava/lang/Object;)V
  #245 = NameAndType        #70:#58       // unit:Lscala/concurrent/Future;
  #246 = Fieldref           #2.#245       // scala/concurrent/Future$.unit:Lscala/concurrent/Future;
  #247 = Utf8               $minus$greater$extension_$this
  #248 = Utf8               Ljava/lang/Object;
  #249 = Utf8               $minus$greater$extension_y
  #250 = Utf8               apply_this
  #251 = Utf8               Lscala/collection/immutable/Map$;
  #252 = Utf8               apply_elems
  #253 = Utf8               Lscala/collection/immutable/Seq;
  #254 = Utf8               scala/collection/immutable/ArraySeq
  #255 = Class              #254          // scala/collection/immutable/ArraySeq
  #256 = Utf8               ()Lscala/collection/immutable/Map;
  #257 = Utf8               ()Lscala/collection/immutable/Map<Ljava/lang/Class<*>;Ljava/lang/Class<*>;>;
  #258 = Utf8               this
  #259 = Utf8               id
  #260 = Utf8               <T:Ljava/lang/Object;>()Lscala/Function1<TT;TT;>;
  #261 = Utf8               ()Lscala/Function1<Ljava/lang/Object;Lscala/runtime/Nothing$;>;
  #262 = Utf8               ()Lscala/util/Failure;
  #263 = Utf8               ()Lscala/util/Failure<Lscala/runtime/Nothing$;>;
  #264 = Utf8               ()Lscala/concurrent/Future;
  #265 = Utf8               ()Lscala/concurrent/Future<Lscala/runtime/Nothing$;>;
  #266 = Utf8               failedFun
  #267 = Utf8               <T:Ljava/lang/Object;>()Lscala/Function1<Lscala/util/Try<TT;>;Lscala/util/Try<Ljava/lang/Throwable;>;>;
  #268 = Utf8               ()Lscala/Function1<Ljava/lang/Throwable;Lscala/concurrent/Future<Lscala/runtime/Nothing$;>;>;
  #269 = Utf8               zipWithTuple2Fun
  #270 = Utf8               <T:Ljava/lang/Object;U:Ljava/lang/Object;>()Lscala/Function2<TT;TU;Lscala/Tuple2<TT;TU;>;>;
  #271 = Utf8               addToBuilderFun
  #272 = Utf8               <A:Ljava/lang/Object;M:Ljava/lang/Object;>()Lscala/Function2<Lscala/collection/mutable/Builder<TA;TM;>;TA;Lscala/collection/mutable/Builder<TA;TM;>;>;
  #273 = Utf8               ()Lscala/concurrent/Future<Lscala/runtime/BoxedUnit;>;
  #274 = Utf8               <T:Ljava/lang/Object;>(Ljava/lang/Throwable;)Lscala/concurrent/Future<TT;>;
  #275 = Utf8               exception
  #276 = Utf8               scala/concurrent/Promise$
  #277 = Class              #276          // scala/concurrent/Promise$
  #278 = Utf8               Lscala/concurrent/Promise$;
  #279 = NameAndType        #43:#278      // MODULE$:Lscala/concurrent/Promise$;
  #280 = Fieldref           #277.#279     // scala/concurrent/Promise$.MODULE$:Lscala/concurrent/Promise$;
  #281 = Utf8               (Ljava/lang/Throwable;)Lscala/concurrent/Promise;
  #282 = NameAndType        #200:#281     // failed:(Ljava/lang/Throwable;)Lscala/concurrent/Promise;
  #283 = Methodref          #277.#282     // scala/concurrent/Promise$.failed:(Ljava/lang/Throwable;)Lscala/concurrent/Promise;
  #284 = Utf8               scala/concurrent/Promise
  #285 = Class              #284          // scala/concurrent/Promise
  #286 = Utf8               future
  #287 = NameAndType        #286:#264     // future:()Lscala/concurrent/Future;
  #288 = InterfaceMethodref #285.#287     // scala/concurrent/Promise.future:()Lscala/concurrent/Future;
  #289 = Utf8               Ljava/lang/Throwable;
  #290 = Utf8               successful
  #291 = Utf8               (Ljava/lang/Object;)Lscala/concurrent/Future;
  #292 = Utf8               <T:Ljava/lang/Object;>(TT;)Lscala/concurrent/Future<TT;>;
  #293 = Utf8               result
  #294 = Utf8               (Ljava/lang/Object;)Lscala/concurrent/Promise;
  #295 = NameAndType        #290:#294     // successful:(Ljava/lang/Object;)Lscala/concurrent/Promise;
  #296 = Methodref          #277.#295     // scala/concurrent/Promise$.successful:(Ljava/lang/Object;)Lscala/concurrent/Promise;
  #297 = Utf8               <T:Ljava/lang/Object;>(Lscala/util/Try<TT;>;)Lscala/concurrent/Future<TT;>;
  #298 = Utf8               (Lscala/util/Try;)V
  #299 = NameAndType        #74:#298      // "<init>":(Lscala/util/Try;)V
  #300 = Methodref          #39.#299      // scala/concurrent/impl/Promise$DefaultPromise."<init>":(Lscala/util/Try;)V
  #301 = Utf8               Lscala/util/Try;
  #302 = Utf8               (Lscala/Function0;Lscala/concurrent/ExecutionContext;)Lscala/concurrent/Future;
  #303 = Utf8               <T:Ljava/lang/Object;>(Lscala/Function0<TT;>;Lscala/concurrent/ExecutionContext;)Lscala/concurrent/Future<TT;>;
  #304 = Utf8               body
  #305 = Utf8               executor
  #306 = NameAndType        #70:#264      // unit:()Lscala/concurrent/Future;
  #307 = Methodref          #2.#306       // scala/concurrent/Future$.unit:()Lscala/concurrent/Future;
  #308 = Utf8               $anonfun$apply$1
  #309 = Utf8               (Lscala/Function0;Lscala/runtime/BoxedUnit;)Ljava/lang/Object;
  #310 = NameAndType        #308:#309     // $anonfun$apply$1:(Lscala/Function0;Lscala/runtime/BoxedUnit;)Ljava/lang/Object;
  #311 = Methodref          #2.#310       // scala/concurrent/Future$.$anonfun$apply$1:(Lscala/Function0;Lscala/runtime/BoxedUnit;)Ljava/lang/Object;
  #312 = MethodHandle       6:#311        // REF_invokeStatic scala/concurrent/Future$.$anonfun$apply$1:(Lscala/Function0;Lscala/runtime/BoxedUnit;)Ljava/lang/Object;
  #313 = Utf8               (Lscala/runtime/BoxedUnit;)Ljava/lang/Object;
  #314 = MethodType         #313          //  (Lscala/runtime/BoxedUnit;)Ljava/lang/Object;
  #315 = Utf8               (Lscala/Function0;)Lscala/Function1;
  #316 = NameAndType        #157:#315     // apply:(Lscala/Function0;)Lscala/Function1;
  #317 = InvokeDynamic      #6:#316       // #6:apply:(Lscala/Function0;)Lscala/Function1;
  #318 = Utf8               map
  #319 = Utf8               (Lscala/Function1;Lscala/concurrent/ExecutionContext;)Lscala/concurrent/Future;
  #320 = NameAndType        #318:#319     // map:(Lscala/Function1;Lscala/concurrent/ExecutionContext;)Lscala/concurrent/Future;
  #321 = InterfaceMethodref #36.#320      // scala/concurrent/Future.map:(Lscala/Function1;Lscala/concurrent/ExecutionContext;)Lscala/concurrent/Future;
  #322 = Utf8               Lscala/Function0;
  #323 = Utf8               Lscala/concurrent/ExecutionContext;
  #324 = Utf8               delegate
  #325 = Utf8               <T:Ljava/lang/Object;>(Lscala/Function0<Lscala/concurrent/Future<TT;>;>;Lscala/concurrent/ExecutionContext;)Lscala/concurrent/Future<TT;>;
  #326 = Utf8               $anonfun$delegate$1
  #327 = Utf8               (Lscala/Function0;Lscala/runtime/BoxedUnit;)Lscala/concurrent/Future;
  #328 = NameAndType        #326:#327     // $anonfun$delegate$1:(Lscala/Function0;Lscala/runtime/BoxedUnit;)Lscala/concurrent/Future;
  #329 = Methodref          #2.#328       // scala/concurrent/Future$.$anonfun$delegate$1:(Lscala/Function0;Lscala/runtime/BoxedUnit;)Lscala/concurrent/Future;
  #330 = MethodHandle       6:#329        // REF_invokeStatic scala/concurrent/Future$.$anonfun$delegate$1:(Lscala/Function0;Lscala/runtime/BoxedUnit;)Lscala/concurrent/Future;
  #331 = Utf8               (Lscala/runtime/BoxedUnit;)Lscala/concurrent/Future;
  #332 = MethodType         #331          //  (Lscala/runtime/BoxedUnit;)Lscala/concurrent/Future;
  #333 = InvokeDynamic      #7:#316       // #7:apply:(Lscala/Function0;)Lscala/Function1;
  #334 = Utf8               flatMap
  #335 = NameAndType        #334:#319     // flatMap:(Lscala/Function1;Lscala/concurrent/ExecutionContext;)Lscala/concurrent/Future;
  #336 = InterfaceMethodref #36.#335      // scala/concurrent/Future.flatMap:(Lscala/Function1;Lscala/concurrent/ExecutionContext;)Lscala/concurrent/Future;
  #337 = Utf8               sequence
  #338 = Utf8               (Lscala/collection/IterableOnce;Lscala/collection/BuildFrom;Lscala/concurrent/ExecutionContext;)Lscala/concurrent/Future;
  #339 = Utf8               <A:Ljava/lang/Object;CC::Lscala/collection/IterableOnce<Ljava/lang/Object;>;To:Ljava/lang/Object;>(TCC;Lscala/collection/BuildFrom<TCC;TA;TTo;>;Lscala/concurrent/ExecutionContext;)Lscala/concurrent/Future<TTo;>;
  #340 = Utf8               in
  #341 = Utf8               bf
  #342 = Utf8               scala/collection/IterableOnce
  #343 = Class              #342          // scala/collection/IterableOnce
  #344 = Utf8               iterator
  #345 = Utf8               ()Lscala/collection/Iterator;
  #346 = NameAndType        #344:#345     // iterator:()Lscala/collection/Iterator;
  #347 = InterfaceMethodref #343.#346     // scala/collection/IterableOnce.iterator:()Lscala/collection/Iterator;
  #348 = Utf8               scala/collection/BuildFrom
  #349 = Class              #348          // scala/collection/BuildFrom
  #350 = Utf8               newBuilder
  #351 = Utf8               (Ljava/lang/Object;)Lscala/collection/mutable/Builder;
  #352 = NameAndType        #350:#351     // newBuilder:(Ljava/lang/Object;)Lscala/collection/mutable/Builder;
  #353 = InterfaceMethodref #349.#352     // scala/collection/BuildFrom.newBuilder:(Ljava/lang/Object;)Lscala/collection/mutable/Builder;
  #354 = NameAndType        #290:#291     // successful:(Ljava/lang/Object;)Lscala/concurrent/Future;
  #355 = Methodref          #2.#354       // scala/concurrent/Future$.successful:(Ljava/lang/Object;)Lscala/concurrent/Future;
  #356 = Utf8               $anonfun$sequence$1
  #357 = Utf8               (Lscala/concurrent/ExecutionContext;Lscala/concurrent/Future;Lscala/concurrent/Future;)Lscala/concurrent/Future;
  #358 = NameAndType        #356:#357     // $anonfun$sequence$1:(Lscala/concurrent/ExecutionContext;Lscala/concurrent/Future;Lscala/concurrent/Future;)Lscala/concurrent/Future;
  #359 = Methodref          #2.#358       // scala/concurrent/Future$.$anonfun$sequence$1:(Lscala/concurrent/ExecutionContext;Lscala/concurrent/Future;Lscala/concurrent/Future;)Lscala/concurrent/Future;
  #360 = MethodHandle       6:#359        // REF_invokeStatic scala/concurrent/Future$.$anonfun$sequence$1:(Lscala/concurrent/ExecutionContext;Lscala/concurrent/Future;Lscala/concurrent/Future;)Lscala/concurrent/Future;
  #361 = Utf8               (Lscala/concurrent/Future;Lscala/concurrent/Future;)Lscala/concurrent/Future;
  #362 = MethodType         #361          //  (Lscala/concurrent/Future;Lscala/concurrent/Future;)Lscala/concurrent/Future;
  #363 = Utf8               (Lscala/concurrent/ExecutionContext;)Lscala/Function2;
  #364 = NameAndType        #157:#363     // apply:(Lscala/concurrent/ExecutionContext;)Lscala/Function2;
  #365 = InvokeDynamic      #8:#364       // #8:apply:(Lscala/concurrent/ExecutionContext;)Lscala/Function2;
  #366 = Utf8               scala/collection/Iterator
  #367 = Class              #366          // scala/collection/Iterator
  #368 = Utf8               foldLeft
  #369 = Utf8               (Ljava/lang/Object;Lscala/Function2;)Ljava/lang/Object;
  #370 = NameAndType        #368:#369     // foldLeft:(Ljava/lang/Object;Lscala/Function2;)Ljava/lang/Object;
  #371 = InterfaceMethodref #367.#370     // scala/collection/Iterator.foldLeft:(Ljava/lang/Object;Lscala/Function2;)Ljava/lang/Object;
  #372 = Utf8               $anonfun$sequence$2
  #373 = Utf8               (Lscala/collection/mutable/Builder;)Ljava/lang/Object;
  #374 = NameAndType        #372:#373     // $anonfun$sequence$2:(Lscala/collection/mutable/Builder;)Ljava/lang/Object;
  #375 = Methodref          #2.#374       // scala/concurrent/Future$.$anonfun$sequence$2:(Lscala/collection/mutable/Builder;)Ljava/lang/Object;
  #376 = MethodHandle       6:#375        // REF_invokeStatic scala/concurrent/Future$.$anonfun$sequence$2:(Lscala/collection/mutable/Builder;)Ljava/lang/Object;
  #377 = MethodType         #373          //  (Lscala/collection/mutable/Builder;)Ljava/lang/Object;
  #378 = InvokeDynamic      #9:#159       // #9:apply:()Lscala/Function1;
  #379 = Utf8               scala/concurrent/BatchingExecutor
  #380 = Class              #379          // scala/concurrent/BatchingExecutor
  #381 = Utf8               Lscala/concurrent/ExecutionContext$parasitic$;
  #382 = NameAndType        #43:#381      // MODULE$:Lscala/concurrent/ExecutionContext$parasitic$;
  #383 = Fieldref           #19.#382      // scala/concurrent/ExecutionContext$parasitic$.MODULE$:Lscala/concurrent/ExecutionContext$parasitic$;
  #384 = Utf8               Lscala/collection/IterableOnce;
  #385 = Utf8               Lscala/collection/BuildFrom;
  #386 = Utf8               scala/Function1
  #387 = Class              #386          // scala/Function1
  #388 = Utf8               firstCompletedOf
  #389 = Utf8               (Lscala/collection/IterableOnce;Lscala/concurrent/ExecutionContext;)Lscala/concurrent/Future;
  #390 = Utf8               <T:Ljava/lang/Object;>(Lscala/collection/IterableOnce<Lscala/concurrent/Future<TT;>;>;Lscala/concurrent/ExecutionContext;)Lscala/concurrent/Future<TT;>;
  #391 = Utf8               futures
  #392 = Utf8               hasNext
  #393 = Utf8               ()Z
  #394 = NameAndType        #392:#393     // hasNext:()Z
  #395 = InterfaceMethodref #367.#394     // scala/collection/Iterator.hasNext:()Z
  #396 = Utf8               Lscala/concurrent/Future$never$;
  #397 = NameAndType        #43:#396      // MODULE$:Lscala/concurrent/Future$never$;
  #398 = Fieldref           #34.#397      // scala/concurrent/Future$never$.MODULE$:Lscala/concurrent/Future$never$;
  #399 = Methodref          #39.#75       // scala/concurrent/impl/Promise$DefaultPromise."<init>":()V
  #400 = Utf8               (Lscala/concurrent/Promise;)V
  #401 = NameAndType        #74:#400      // "<init>":(Lscala/concurrent/Promise;)V
  #402 = Methodref          #32.#401      // scala/concurrent/Future$$anon$5."<init>":(Lscala/concurrent/Promise;)V
  #403 = Utf8               java/util/concurrent/atomic/AtomicReference
  #404 = Class              #403          // java/util/concurrent/atomic/AtomicReference
  #405 = Utf8               get
  #406 = Utf8               ()Ljava/lang/Object;
  #407 = NameAndType        #405:#406     // get:()Ljava/lang/Object;
  #408 = Methodref          #404.#407     // java/util/concurrent/atomic/AtomicReference.get:()Ljava/lang/Object;
  #409 = Utf8               next
  #410 = NameAndType        #409:#406     // next:()Ljava/lang/Object;
  #411 = InterfaceMethodref #367.#410     // scala/collection/Iterator.next:()Ljava/lang/Object;
  #412 = Utf8               onComplete
  #413 = Utf8               (Lscala/Function1;Lscala/concurrent/ExecutionContext;)V
  #414 = NameAndType        #412:#413     // onComplete:(Lscala/Function1;Lscala/concurrent/ExecutionContext;)V
  #415 = InterfaceMethodref #36.#414      // scala/concurrent/Future.onComplete:(Lscala/Function1;Lscala/concurrent/ExecutionContext;)V
  #416 = Utf8               p
  #417 = Utf8               Lscala/concurrent/Promise;
  #418 = Utf8               firstCompleteHandler
  #419 = Utf8               Ljava/util/concurrent/atomic/AtomicReference;
  #420 = Utf8               i
  #421 = Utf8               Lscala/collection/Iterator;
  #422 = Utf8               find
  #423 = Utf8               (Lscala/collection/immutable/Iterable;Lscala/Function1;Lscala/concurrent/ExecutionContext;)Lscala/concurrent/Future;
  #424 = Utf8               <T:Ljava/lang/Object;>(Lscala/collection/immutable/Iterable<Lscala/concurrent/Future<TT;>;>;Lscala/Function1<TT;Ljava/lang/Object;>;Lscala/concurrent/ExecutionContext;)Lscala/concurrent/Future<Lscala/Option<TT;>;>;
  #425 = Utf8               scala/collection/immutable/Iterable
  #426 = Class              #425          // scala/collection/immutable/Iterable
  #427 = InterfaceMethodref #426.#346     // scala/collection/immutable/Iterable.iterator:()Lscala/collection/Iterator;
  #428 = Utf8               scala/None$
  #429 = Class              #428          // scala/None$
  #430 = Utf8               Lscala/None$;
  #431 = NameAndType        #43:#430      // MODULE$:Lscala/None$;
  #432 = Fieldref           #429.#431     // scala/None$.MODULE$:Lscala/None$;
  #433 = Utf8               $anonfun$find$1
  #434 = Utf8               (Lscala/concurrent/Future$;Lscala/Function1;Lscala/collection/Iterator;Lscala/concurrent/ExecutionContext;Lscala/util/Try;)Lscala/concurrent/Future;
  #435 = NameAndType        #433:#434     // $anonfun$find$1:(Lscala/concurrent/Future$;Lscala/Function1;Lscala/collection/Iterator;Lscala/concurrent/ExecutionContext;Lscala/util/Try;)Lscala/concurrent/Future;
  #436 = Methodref          #2.#435       // scala/concurrent/Future$.$anonfun$find$1:(Lscala/concurrent/Future$;Lscala/Function1;Lscala/collection/Iterator;Lscala/concurrent/ExecutionContext;Lscala/util/Try;)Lscala/concurrent/Future;
  #437 = MethodHandle       6:#436        // REF_invokeStatic scala/concurrent/Future$.$anonfun$find$1:(Lscala/concurrent/Future$;Lscala/Function1;Lscala/collection/Iterator;Lscala/concurrent/ExecutionContext;Lscala/util/Try;)Lscala/concurrent/Future;
  #438 = MethodType         #185          //  (Lscala/util/Try;)Lscala/concurrent/Future;
  #439 = Utf8               (Lscala/concurrent/Future$;Lscala/Function1;Lscala/collection/Iterator;Lscala/concurrent/ExecutionContext;)Lscala/Function1;
  #440 = NameAndType        #157:#439     // apply:(Lscala/concurrent/Future$;Lscala/Function1;Lscala/collection/Iterator;Lscala/concurrent/ExecutionContext;)Lscala/Function1;
  #441 = InvokeDynamic      #10:#440      // #10:apply:(Lscala/concurrent/Future$;Lscala/Function1;Lscala/collection/Iterator;Lscala/concurrent/ExecutionContext;)Lscala/Function1;
  #442 = Utf8               transformWith
  #443 = NameAndType        #442:#319     // transformWith:(Lscala/Function1;Lscala/concurrent/ExecutionContext;)Lscala/concurrent/Future;
  #444 = InterfaceMethodref #36.#443      // scala/concurrent/Future.transformWith:(Lscala/Function1;Lscala/concurrent/ExecutionContext;)Lscala/concurrent/Future;
  #445 = Utf8               Lscala/collection/immutable/Iterable;
  #446 = Utf8               searchNext$1_i
  #447 = Utf8               (Lscala/collection/immutable/Iterable;Ljava/lang/Object;Lscala/Function2;Lscala/concurrent/ExecutionContext;)Lscala/concurrent/Future;
  #448 = Utf8               <T:Ljava/lang/Object;R:Ljava/lang/Object;>(Lscala/collection/immutable/Iterable<Lscala/concurrent/Future<TT;>;>;TR;Lscala/Function2<TR;TT;TR;>;Lscala/concurrent/ExecutionContext;)Lscala/concurrent/Future<TR;>;
  #449 = Utf8               zero
  #450 = Utf8               op
  #451 = Utf8               $anonfun$foldNext$1
  #452 = Utf8               (Lscala/collection/Iterator;Lscala/Function2;Ljava/lang/Object;Lscala/concurrent/ExecutionContext;Ljava/lang/Object;)Lscala/concurrent/Future;
  #453 = NameAndType        #451:#452     // $anonfun$foldNext$1:(Lscala/collection/Iterator;Lscala/Function2;Ljava/lang/Object;Lscala/concurrent/ExecutionContext;Ljava/lang/Object;)Lscala/concurrent/Future;
  #454 = Methodref          #2.#453       // scala/concurrent/Future$.$anonfun$foldNext$1:(Lscala/collection/Iterator;Lscala/Function2;Ljava/lang/Object;Lscala/concurrent/ExecutionContext;Ljava/lang/Object;)Lscala/concurrent/Future;
  #455 = MethodHandle       6:#454        // REF_invokeStatic scala/concurrent/Future$.$anonfun$foldNext$1:(Lscala/collection/Iterator;Lscala/Function2;Ljava/lang/Object;Lscala/concurrent/ExecutionContext;Ljava/lang/Object;)Lscala/concurrent/Future;
  #456 = MethodType         #291          //  (Ljava/lang/Object;)Lscala/concurrent/Future;
  #457 = Utf8               (Lscala/collection/Iterator;Lscala/Function2;Ljava/lang/Object;Lscala/concurrent/ExecutionContext;)Lscala/Function1;
  #458 = NameAndType        #157:#457     // apply:(Lscala/collection/Iterator;Lscala/Function2;Ljava/lang/Object;Lscala/concurrent/ExecutionContext;)Lscala/Function1;
  #459 = InvokeDynamic      #11:#458      // #11:apply:(Lscala/collection/Iterator;Lscala/Function2;Ljava/lang/Object;Lscala/concurrent/ExecutionContext;)Lscala/Function1;
  #460 = Utf8               foldNext_i
  #461 = Utf8               foldNext
  #462 = Utf8               (Lscala/collection/Iterator;Ljava/lang/Object;Lscala/Function2;Lscala/concurrent/ExecutionContext;)Lscala/concurrent/Future;
  #463 = Utf8               <T:Ljava/lang/Object;R:Ljava/lang/Object;>(Lscala/collection/Iterator<Lscala/concurrent/Future<TT;>;>;TR;Lscala/Function2<TR;TT;TR;>;Lscala/concurrent/ExecutionContext;)Lscala/concurrent/Future<TR;>;
  #464 = Utf8               prevValue
  #465 = Utf8               fold
  #466 = Utf8               (Lscala/collection/IterableOnce;Ljava/lang/Object;Lscala/Function2;Lscala/concurrent/ExecutionContext;)Lscala/concurrent/Future;
  #467 = Utf8               <T:Ljava/lang/Object;R:Ljava/lang/Object;>(Lscala/collection/IterableOnce<Lscala/concurrent/Future<TT;>;>;TR;Lscala/Function2<TR;TT;TR;>;Lscala/concurrent/ExecutionContext;)Lscala/concurrent/Future<TR;>;
  #468 = Utf8               scala/collection/IterableOnceExtensionMethods$
  #469 = Class              #468          // scala/collection/IterableOnceExtensionMethods$
  #470 = Utf8               Lscala/collection/IterableOnceExtensionMethods$;
  #471 = NameAndType        #43:#470      // MODULE$:Lscala/collection/IterableOnceExtensionMethods$;
  #472 = Fieldref           #469.#471     // scala/collection/IterableOnceExtensionMethods$.MODULE$:Lscala/collection/IterableOnceExtensionMethods$;
  #473 = Utf8               scala/collection/IterableOnce$
  #474 = Class              #473          // scala/collection/IterableOnce$
  #475 = Utf8               Lscala/collection/IterableOnce$;
  #476 = NameAndType        #43:#475      // MODULE$:Lscala/collection/IterableOnce$;
  #477 = Fieldref           #474.#476     // scala/collection/IterableOnce$.MODULE$:Lscala/collection/IterableOnce$;
  #478 = Utf8               isEmpty$extension
  #479 = Utf8               (Lscala/collection/IterableOnce;)Z
  #480 = NameAndType        #478:#479     // isEmpty$extension:(Lscala/collection/IterableOnce;)Z
  #481 = Methodref          #469.#480     // scala/collection/IterableOnceExtensionMethods$.isEmpty$extension:(Lscala/collection/IterableOnce;)Z
  #482 = Utf8               scala/collection/IterableFactory$
  #483 = Class              #482          // scala/collection/IterableFactory$
  #484 = Utf8               Lscala/collection/IterableFactory$;
  #485 = NameAndType        #43:#484      // MODULE$:Lscala/collection/IterableFactory$;
  #486 = Fieldref           #483.#485     // scala/collection/IterableFactory$.MODULE$:Lscala/collection/IterableFactory$;
  #487 = Utf8               scala/collection/mutable/ArrayBuffer$
  #488 = Class              #487          // scala/collection/mutable/ArrayBuffer$
  #489 = Utf8               Lscala/collection/mutable/ArrayBuffer$;
  #490 = NameAndType        #43:#489      // MODULE$:Lscala/collection/mutable/ArrayBuffer$;
  #491 = Fieldref           #488.#490     // scala/collection/mutable/ArrayBuffer$.MODULE$:Lscala/collection/mutable/ArrayBuffer$;
  #492 = Utf8               (Lscala/collection/IterableFactory;)V
  #493 = NameAndType        #74:#492      // "<init>":(Lscala/collection/IterableFactory;)V
  #494 = Methodref          #17.#493      // scala/collection/IterableFactory$$anon$1."<init>":(Lscala/collection/IterableFactory;)V
  #495 = NameAndType        #337:#338     // sequence:(Lscala/collection/IterableOnce;Lscala/collection/BuildFrom;Lscala/concurrent/ExecutionContext;)Lscala/concurrent/Future;
  #496 = Methodref          #2.#495       // scala/concurrent/Future$.sequence:(Lscala/collection/IterableOnce;Lscala/collection/BuildFrom;Lscala/concurrent/ExecutionContext;)Lscala/concurrent/Future;
  #497 = Utf8               $anonfun$fold$1
  #498 = Utf8               (Ljava/lang/Object;Lscala/Function2;Lscala/collection/mutable/ArrayBuffer;)Ljava/lang/Object;
  #499 = NameAndType        #497:#498     // $anonfun$fold$1:(Ljava/lang/Object;Lscala/Function2;Lscala/collection/mutable/ArrayBuffer;)Ljava/lang/Object;
  #500 = Methodref          #2.#499       // scala/concurrent/Future$.$anonfun$fold$1:(Ljava/lang/Object;Lscala/Function2;Lscala/collection/mutable/ArrayBuffer;)Ljava/lang/Object;
  #501 = MethodHandle       6:#500        // REF_invokeStatic scala/concurrent/Future$.$anonfun$fold$1:(Ljava/lang/Object;Lscala/Function2;Lscala/collection/mutable/ArrayBuffer;)Ljava/lang/Object;
  #502 = Utf8               (Lscala/collection/mutable/ArrayBuffer;)Ljava/lang/Object;
  #503 = MethodType         #502          //  (Lscala/collection/mutable/ArrayBuffer;)Ljava/lang/Object;
  #504 = Utf8               (Ljava/lang/Object;Lscala/Function2;)Lscala/Function1;
  #505 = NameAndType        #157:#504     // apply:(Ljava/lang/Object;Lscala/Function2;)Lscala/Function1;
  #506 = InvokeDynamic      #12:#505      // #12:apply:(Ljava/lang/Object;Lscala/Function2;)Lscala/Function1;
  #507 = Utf8               toBuildFrom_factory
  #508 = Utf8               Lscala/collection/IterableFactory;
  #509 = Utf8               reduce
  #510 = Utf8               (Lscala/collection/IterableOnce;Lscala/Function2;Lscala/concurrent/ExecutionContext;)Lscala/concurrent/Future;
  #511 = Utf8               <T:Ljava/lang/Object;R:Ljava/lang/Object;>(Lscala/collection/IterableOnce<Lscala/concurrent/Future<TT;>;>;Lscala/Function2<TR;TT;TR;>;Lscala/concurrent/ExecutionContext;)Lscala/concurrent/Future<TR;>;
  #512 = Utf8               java/util/NoSuchElementException
  #513 = Class              #512          // java/util/NoSuchElementException
  #514 = Utf8               reduce attempted on empty collection
  #515 = String             #514          // reduce attempted on empty collection
  #516 = Utf8               (Ljava/lang/String;)V
  #517 = NameAndType        #74:#516      // "<init>":(Ljava/lang/String;)V
  #518 = Methodref          #513.#517     // java/util/NoSuchElementException."<init>":(Ljava/lang/String;)V
  #519 = Utf8               $anonfun$reduce$1
  #520 = Utf8               (Lscala/Function2;Lscala/collection/mutable/ArrayBuffer;)Ljava/lang/Object;
  #521 = NameAndType        #519:#520     // $anonfun$reduce$1:(Lscala/Function2;Lscala/collection/mutable/ArrayBuffer;)Ljava/lang/Object;
  #522 = Methodref          #2.#521       // scala/concurrent/Future$.$anonfun$reduce$1:(Lscala/Function2;Lscala/collection/mutable/ArrayBuffer;)Ljava/lang/Object;
  #523 = MethodHandle       6:#522        // REF_invokeStatic scala/concurrent/Future$.$anonfun$reduce$1:(Lscala/Function2;Lscala/collection/mutable/ArrayBuffer;)Ljava/lang/Object;
  #524 = Utf8               (Lscala/Function2;)Lscala/Function1;
  #525 = NameAndType        #157:#524     // apply:(Lscala/Function2;)Lscala/Function1;
  #526 = InvokeDynamic      #13:#525      // #13:apply:(Lscala/Function2;)Lscala/Function1;
  #527 = Utf8               reduceLeft
  #528 = Utf8               (Lscala/collection/immutable/Iterable;Lscala/Function2;Lscala/concurrent/ExecutionContext;)Lscala/concurrent/Future;
  #529 = Utf8               <T:Ljava/lang/Object;R:Ljava/lang/Object;>(Lscala/collection/immutable/Iterable<Lscala/concurrent/Future<TT;>;>;Lscala/Function2<TR;TT;TR;>;Lscala/concurrent/ExecutionContext;)Lscala/concurrent/Future<TR;>;
  #530 = Utf8               reduceLeft attempted on empty collection
  #531 = String             #530          // reduceLeft attempted on empty collection
  #532 = Utf8               $anonfun$reduceLeft$1
  #533 = Utf8               (Lscala/collection/Iterator;Lscala/Function2;Lscala/concurrent/ExecutionContext;Ljava/lang/Object;)Lscala/concurrent/Future;
  #534 = NameAndType        #532:#533     // $anonfun$reduceLeft$1:(Lscala/collection/Iterator;Lscala/Function2;Lscala/concurrent/ExecutionContext;Ljava/lang/Object;)Lscala/concurrent/Future;
  #535 = Methodref          #2.#534       // scala/concurrent/Future$.$anonfun$reduceLeft$1:(Lscala/collection/Iterator;Lscala/Function2;Lscala/concurrent/ExecutionContext;Ljava/lang/Object;)Lscala/concurrent/Future;
  #536 = MethodHandle       6:#535        // REF_invokeStatic scala/concurrent/Future$.$anonfun$reduceLeft$1:(Lscala/collection/Iterator;Lscala/Function2;Lscala/concurrent/ExecutionContext;Ljava/lang/Object;)Lscala/concurrent/Future;
  #537 = Utf8               (Lscala/collection/Iterator;Lscala/Function2;Lscala/concurrent/ExecutionContext;)Lscala/Function1;
  #538 = NameAndType        #157:#537     // apply:(Lscala/collection/Iterator;Lscala/Function2;Lscala/concurrent/ExecutionContext;)Lscala/Function1;
  #539 = InvokeDynamic      #14:#538      // #14:apply:(Lscala/collection/Iterator;Lscala/Function2;Lscala/concurrent/ExecutionContext;)Lscala/Function1;
  #540 = Utf8               traverse
  #541 = Utf8               (Lscala/collection/IterableOnce;Lscala/Function1;Lscala/collection/BuildFrom;Lscala/concurrent/ExecutionContext;)Lscala/concurrent/Future;
  #542 = Utf8               <A:Ljava/lang/Object;B:Ljava/lang/Object;M::Lscala/collection/IterableOnce<Ljava/lang/Object;>;>(TM;Lscala/Function1<TA;Lscala/concurrent/Future<TB;>;>;Lscala/collection/BuildFrom<TM;TB;TM;>;Lscala/concurrent/ExecutionContext;)Lscala/concurrent/Future<TM;>;
  #543 = Utf8               fn
  #544 = Utf8               $anonfun$traverse$1
  #545 = Utf8               (Lscala/Function1;Lscala/concurrent/ExecutionContext;Lscala/concurrent/Future;Ljava/lang/Object;)Lscala/concurrent/Future;
  #546 = NameAndType        #544:#545     // $anonfun$traverse$1:(Lscala/Function1;Lscala/concurrent/ExecutionContext;Lscala/concurrent/Future;Ljava/lang/Object;)Lscala/concurrent/Future;
  #547 = Methodref          #2.#546       // scala/concurrent/Future$.$anonfun$traverse$1:(Lscala/Function1;Lscala/concurrent/ExecutionContext;Lscala/concurrent/Future;Ljava/lang/Object;)Lscala/concurrent/Future;
  #548 = MethodHandle       6:#547        // REF_invokeStatic scala/concurrent/Future$.$anonfun$traverse$1:(Lscala/Function1;Lscala/concurrent/ExecutionContext;Lscala/concurrent/Future;Ljava/lang/Object;)Lscala/concurrent/Future;
  #549 = Utf8               (Lscala/concurrent/Future;Ljava/lang/Object;)Lscala/concurrent/Future;
  #550 = MethodType         #549          //  (Lscala/concurrent/Future;Ljava/lang/Object;)Lscala/concurrent/Future;
  #551 = Utf8               (Lscala/Function1;Lscala/concurrent/ExecutionContext;)Lscala/Function2;
  #552 = NameAndType        #157:#551     // apply:(Lscala/Function1;Lscala/concurrent/ExecutionContext;)Lscala/Function2;
  #553 = InvokeDynamic      #15:#552      // #15:apply:(Lscala/Function1;Lscala/concurrent/ExecutionContext;)Lscala/Function2;
  #554 = Utf8               $anonfun$traverse$2
  #555 = Utf8               (Lscala/collection/mutable/Builder;)Lscala/collection/IterableOnce;
  #556 = NameAndType        #554:#555     // $anonfun$traverse$2:(Lscala/collection/mutable/Builder;)Lscala/collection/IterableOnce;
  #557 = Methodref          #2.#556       // scala/concurrent/Future$.$anonfun$traverse$2:(Lscala/collection/mutable/Builder;)Lscala/collection/IterableOnce;
  #558 = MethodHandle       6:#557        // REF_invokeStatic scala/concurrent/Future$.$anonfun$traverse$2:(Lscala/collection/mutable/Builder;)Lscala/collection/IterableOnce;
  #559 = MethodType         #555          //  (Lscala/collection/mutable/Builder;)Lscala/collection/IterableOnce;
  #560 = InvokeDynamic      #16:#159      // #16:apply:()Lscala/Function1;
  #561 = Utf8               x
  #562 = Utf8               identity
  #563 = NameAndType        #562:#143     // identity:(Ljava/lang/Object;)Ljava/lang/Object;
  #564 = Methodref          #80.#563      // scala/Predef$.identity:(Ljava/lang/Object;)Ljava/lang/Object;
  #565 = Utf8               t
  #566 = Methodref          #24.#243      // scala/concurrent/Future$$anon$1."<init>":(Ljava/lang/Object;)V
  #567 = Utf8               v
  #568 = Utf8               ()Ljava/lang/Throwable;
  #569 = NameAndType        #275:#568     // exception:()Ljava/lang/Throwable;
  #570 = Methodref          #174.#569     // scala/util/Failure.exception:()Ljava/lang/Throwable;
  #571 = NameAndType        #62:#264      // recoverWithFailedMarker:()Lscala/concurrent/Future;
  #572 = Methodref          #2.#571       // scala/concurrent/Future$.recoverWithFailedMarker:()Lscala/concurrent/Future;
  #573 = Utf8               _1
  #574 = Utf8               _2
  #575 = Utf8               b
  #576 = Utf8               e
  #577 = Utf8               scala/collection/mutable/Builder
  #578 = Class              #577          // scala/collection/mutable/Builder
  #579 = Utf8               $plus$eq
  #580 = Utf8               (Ljava/lang/Object;)Lscala/collection/mutable/Growable;
  #581 = NameAndType        #579:#580     // $plus$eq:(Ljava/lang/Object;)Lscala/collection/mutable/Growable;
  #582 = InterfaceMethodref #578.#581     // scala/collection/mutable/Builder.$plus$eq:(Ljava/lang/Object;)Lscala/collection/mutable/Growable;
  #583 = Utf8               Lscala/collection/mutable/Builder;
  #584 = Utf8               body$1
  #585 = Utf8               x$4
  #586 = Utf8               scala/Function0
  #587 = Class              #586          // scala/Function0
  #588 = NameAndType        #157:#406     // apply:()Ljava/lang/Object;
  #589 = InterfaceMethodref #587.#588     // scala/Function0.apply:()Ljava/lang/Object;
  #590 = Utf8               body$2
  #591 = Utf8               x$5
  #592 = Utf8               executor$3
  #593 = Utf8               fr
  #594 = Utf8               fa
  #595 = NameAndType        #271:#222     // addToBuilderFun:()Lscala/Function2;
  #596 = Methodref          #2.#595       // scala/concurrent/Future$.addToBuilderFun:()Lscala/Function2;
  #597 = Utf8               zipWith
  #598 = Utf8               (Lscala/concurrent/Future;Lscala/Function2;Lscala/concurrent/ExecutionContext;)Lscala/concurrent/Future;
  #599 = NameAndType        #597:#598     // zipWith:(Lscala/concurrent/Future;Lscala/Function2;Lscala/concurrent/ExecutionContext;)Lscala/concurrent/Future;
  #600 = InterfaceMethodref #36.#599      // scala/concurrent/Future.zipWith:(Lscala/concurrent/Future;Lscala/Function2;Lscala/concurrent/ExecutionContext;)Lscala/concurrent/Future;
  #601 = Utf8               x$6
  #602 = NameAndType        #293:#406     // result:()Ljava/lang/Object;
  #603 = InterfaceMethodref #578.#602     // scala/collection/mutable/Builder.result:()Ljava/lang/Object;
  #604 = Utf8               $this
  #605 = Utf8               p$3
  #606 = Utf8               i$1
  #607 = Utf8               executor$4
  #608 = Utf8               x0$1
  #609 = Utf8               value
  #610 = NameAndType        #609:#406     // value:()Ljava/lang/Object;
  #611 = Methodref          #237.#610     // scala/util/Success.value:()Ljava/lang/Object;
  #612 = NameAndType        #157:#143     // apply:(Ljava/lang/Object;)Ljava/lang/Object;
  #613 = InterfaceMethodref #387.#612     // scala/Function1.apply:(Ljava/lang/Object;)Ljava/lang/Object;
  #614 = Utf8               scala/runtime/BoxesRunTime
  #615 = Class              #614          // scala/runtime/BoxesRunTime
  #616 = Utf8               unboxToBoolean
  #617 = Utf8               (Ljava/lang/Object;)Z
  #618 = NameAndType        #616:#617     // unboxToBoolean:(Ljava/lang/Object;)Z
  #619 = Methodref          #615.#618     // scala/runtime/BoxesRunTime.unboxToBoolean:(Ljava/lang/Object;)Z
  #620 = Utf8               scala/Some
  #621 = Class              #620          // scala/Some
  #622 = Methodref          #621.#243     // scala/Some."<init>":(Ljava/lang/Object;)V
  #623 = Utf8               r
  #624 = Utf8               searchNext$1
  #625 = Utf8               (Lscala/collection/Iterator;Lscala/Function1;Lscala/concurrent/ExecutionContext;)Lscala/concurrent/Future;
  #626 = Utf8               i$2
  #627 = Utf8               op$1
  #628 = Utf8               prevValue$1
  #629 = Utf8               executor$5
  #630 = Utf8               scala/Function2
  #631 = Class              #630          // scala/Function2
  #632 = NameAndType        #157:#214     // apply:(Ljava/lang/Object;Ljava/lang/Object;)Ljava/lang/Object;
  #633 = InterfaceMethodref #631.#632     // scala/Function2.apply:(Ljava/lang/Object;Ljava/lang/Object;)Ljava/lang/Object;
  #634 = Utf8               foldNext_this
  #635 = Utf8               foldNext_prevValue
  #636 = Utf8               zero$1
  #637 = Utf8               op$2
  #638 = Utf8               x$7
  #639 = Utf8               scala/collection/mutable/ArrayBuffer
  #640 = Class              #639          // scala/collection/mutable/ArrayBuffer
  #641 = Methodref          #640.#370     // scala/collection/mutable/ArrayBuffer.foldLeft:(Ljava/lang/Object;Lscala/Function2;)Ljava/lang/Object;
  #642 = Utf8               Lscala/collection/mutable/ArrayBuffer;
  #643 = Utf8               op$3
  #644 = Utf8               x$8
  #645 = Utf8               (Lscala/Function2;)Ljava/lang/Object;
  #646 = NameAndType        #527:#645     // reduceLeft:(Lscala/Function2;)Ljava/lang/Object;
  #647 = Methodref          #640.#646     // scala/collection/mutable/ArrayBuffer.reduceLeft:(Lscala/Function2;)Ljava/lang/Object;
  #648 = Utf8               i$3
  #649 = Utf8               op$4
  #650 = Utf8               executor$6
  #651 = NameAndType        #461:#462     // foldNext:(Lscala/collection/Iterator;Ljava/lang/Object;Lscala/Function2;Lscala/concurrent/ExecutionContext;)Lscala/concurrent/Future;
  #652 = Methodref          #2.#651       // scala/concurrent/Future$.foldNext:(Lscala/collection/Iterator;Ljava/lang/Object;Lscala/Function2;Lscala/concurrent/ExecutionContext;)Lscala/concurrent/Future;
  #653 = Utf8               fn$1
  #654 = Utf8               executor$7
  #655 = Utf8               a
  #656 = Utf8               x$9
  #657 = Methodref          #4.#75        // java/lang/Object."<init>":()V
  #658 = Utf8               $deserializeLambda$
  #659 = Utf8               (Ljava/lang/invoke/SerializedLambda;)Ljava/lang/Object;
  #660 = Utf8               scala/runtime/LambdaDeserialize
  #661 = Class              #660          // scala/runtime/LambdaDeserialize
  #662 = Utf8               bootstrap
  #663 = Utf8               (Ljava/lang/invoke/MethodHandles$Lookup;Ljava/lang/String;Ljava/lang/invoke/MethodType;[Ljava/lang/invoke/MethodHandle;)Ljava/lang/invoke/CallSite;
  #664 = NameAndType        #662:#663     // bootstrap:(Ljava/lang/invoke/MethodHandles$Lookup;Ljava/lang/String;Ljava/lang/invoke/MethodType;[Ljava/lang/invoke/MethodHandle;)Ljava/lang/invoke/CallSite;
  #665 = Methodref          #661.#664     // scala/runtime/LambdaDeserialize.bootstrap:(Ljava/lang/invoke/MethodHandles$Lookup;Ljava/lang/String;Ljava/lang/invoke/MethodType;[Ljava/lang/invoke/MethodHandle;)Ljava/lang/invoke/CallSite;
  #666 = MethodHandle       6:#665        // REF_invokeStatic scala/runtime/LambdaDeserialize.bootstrap:(Ljava/lang/invoke/MethodHandles$Lookup;Ljava/lang/String;Ljava/lang/invoke/MethodType;[Ljava/lang/invoke/MethodHandle;)Ljava/lang/invoke/CallSite;
  #667 = Utf8               lambdaDeserialize
  #668 = NameAndType        #667:#659     // lambdaDeserialize:(Ljava/lang/invoke/SerializedLambda;)Ljava/lang/Object;
  #669 = InvokeDynamic      #17:#668      // #17:lambdaDeserialize:(Ljava/lang/invoke/SerializedLambda;)Ljava/lang/Object;
  #670 = Utf8               Signature
  #671 = Utf8               Code
  #672 = Utf8               StackMapTable
  #673 = Utf8               LineNumberTable
  #674 = Utf8               LocalVariableTable
  #675 = Utf8               MethodParameters
  #676 = Utf8               Deprecated
  #677 = Utf8               InnerClasses
  #678 = Utf8               SourceFile
  #679 = Utf8               BootstrapMethods
  #680 = Utf8               ScalaInlineInfo
  #681 = Utf8               Scala
{
  public static final scala.concurrent.Future$ MODULE$;
    descriptor: Lscala/concurrent/Future$;
    flags: (0x0019) ACC_PUBLIC, ACC_STATIC, ACC_FINAL

  private static final scala.collection.immutable.Map<java.lang.Class<?>, java.lang.Class<?>> toBoxed;
    descriptor: Lscala/collection/immutable/Map;
    flags: (0x001a) ACC_PRIVATE, ACC_STATIC, ACC_FINAL
    Signature: #47                          // Lscala/collection/immutable/Map<Ljava/lang/Class<*>;Ljava/lang/Class<*>;>;

  private static final scala.Function1<java.lang.Object, java.lang.Object> _cachedId;
    descriptor: Lscala/Function1;
    flags: (0x001a) ACC_PRIVATE, ACC_STATIC, ACC_FINAL
    Signature: #50                          // Lscala/Function1<Ljava/lang/Object;Ljava/lang/Object;>;

  private static final scala.Function1<java.lang.Object, scala.runtime.Nothing$> collectFailed;
    descriptor: Lscala/Function1;
    flags: (0x001a) ACC_PRIVATE, ACC_STATIC, ACC_FINAL
    Signature: #52                          // Lscala/Function1<Ljava/lang/Object;Lscala/runtime/Nothing$;>;

  private static final scala.util.Failure<scala.runtime.Nothing$> filterFailure;
    descriptor: Lscala/util/Failure;
    flags: (0x001a) ACC_PRIVATE, ACC_STATIC, ACC_FINAL
    Signature: #55                          // Lscala/util/Failure<Lscala/runtime/Nothing$;>;

  private static final scala.util.Failure<scala.runtime.Nothing$> failedFailure;
    descriptor: Lscala/util/Failure;
    flags: (0x001a) ACC_PRIVATE, ACC_STATIC, ACC_FINAL
    Signature: #55                          // Lscala/util/Failure<Lscala/runtime/Nothing$;>;

  private static final scala.concurrent.Future<scala.runtime.Nothing$> failedFailureFuture;
    descriptor: Lscala/concurrent/Future;
    flags: (0x001a) ACC_PRIVATE, ACC_STATIC, ACC_FINAL
    Signature: #59                          // Lscala/concurrent/Future<Lscala/runtime/Nothing$;>;

  private static final scala.Function1<scala.util.Try<java.lang.Object>, scala.util.Try<java.lang.Throwable>> _failedFun;
    descriptor: Lscala/Function1;
    flags: (0x001a) ACC_PRIVATE, ACC_STATIC, ACC_FINAL
    Signature: #61                          // Lscala/Function1<Lscala/util/Try<Ljava/lang/Object;>;Lscala/util/Try<Ljava/lang/Throwable;>;>;

  private static final scala.concurrent.Future<scala.runtime.Nothing$> recoverWithFailedMarker;
    descriptor: Lscala/concurrent/Future;
    flags: (0x001a) ACC_PRIVATE, ACC_STATIC, ACC_FINAL
    Signature: #59                          // Lscala/concurrent/Future<Lscala/runtime/Nothing$;>;

  private static final scala.Function1<java.lang.Throwable, scala.concurrent.Future<scala.runtime.Nothing$>> recoverWithFailed;
    descriptor: Lscala/Function1;
    flags: (0x001a) ACC_PRIVATE, ACC_STATIC, ACC_FINAL
    Signature: #64                          // Lscala/Function1<Ljava/lang/Throwable;Lscala/concurrent/Future<Lscala/runtime/Nothing$;>;>;

  private static final scala.Function2<java.lang.Object, java.lang.Object, scala.Tuple2<java.lang.Object, java.lang.Object>> _zipWithTuple2;
    descriptor: Lscala/Function2;
    flags: (0x001a) ACC_PRIVATE, ACC_STATIC, ACC_FINAL
    Signature: #67                          // Lscala/Function2<Ljava/lang/Object;Ljava/lang/Object;Lscala/Tuple2<Ljava/lang/Object;Ljava/lang/Object;>;>;

  private static final scala.Function2<scala.collection.mutable.Builder<java.lang.Object, scala.runtime.Nothing$>, java.lang.Object, scala.collection.mutable.Builder<java.lang.Object, scala.runtime.Nothing$>> _addToBuilderFun;
    descriptor: Lscala/Function2;
    flags: (0x001a) ACC_PRIVATE, ACC_STATIC, ACC_FINAL
    Signature: #69                          // Lscala/Function2<Lscala/collection/mutable/Builder<Ljava/lang/Object;Lscala/runtime/Nothing$;>;Ljava/lang/Object;Lscala/collection/mutable/Builder<Ljava/lang/Object;Lscala/runtime/Nothing$;>;>;

  private static final scala.concurrent.Future<scala.runtime.BoxedUnit> unit;
    descriptor: Lscala/concurrent/Future;
    flags: (0x001a) ACC_PRIVATE, ACC_STATIC, ACC_FINAL
    Signature: #71                          // Lscala/concurrent/Future<Lscala/runtime/BoxedUnit;>;

  public static {};
    descriptor: ()V
    flags: (0x0009) ACC_PUBLIC, ACC_STATIC
    Code:
      stack=9, locals=20, args_size=0
         0: new           #2                  // class scala/concurrent/Future$
         3: dup
         4: invokespecial #76                 // Method "<init>":()V
         7: putstatic     #78                 // Field MODULE$:Lscala/concurrent/Future$;
        10: getstatic     #83                 // Field scala/Predef$.MODULE$:Lscala/Predef$;
        13: invokevirtual #87                 // Method scala/Predef$.Map:()Lscala/collection/immutable/Map$;
        16: getstatic     #92                 // Field scala/runtime/ScalaRunTime$.MODULE$:Lscala/runtime/ScalaRunTime$;
        19: bipush        9
        21: anewarray     #94                 // class scala/Tuple2
        24: dup
        25: iconst_0
        26: getstatic     #97                 // Field scala/Predef$ArrowAssoc$.MODULE$:Lscala/Predef$ArrowAssoc$;
        29: pop
        30: getstatic     #103                // Field java/lang/Boolean.TYPE:Ljava/lang/Class;
        33: ldc           #99                 // class java/lang/Boolean
        35: astore_1
        36: astore_0
        37: new           #94                 // class scala/Tuple2
        40: dup
        41: aload_0
        42: aload_1
        43: invokespecial #106                // Method scala/Tuple2."<init>":(Ljava/lang/Object;Ljava/lang/Object;)V
        46: aconst_null
        47: astore_0
        48: aconst_null
        49: astore_1
        50: aastore
        51: dup
        52: iconst_1
        53: getstatic     #97                 // Field scala/Predef$ArrowAssoc$.MODULE$:Lscala/Predef$ArrowAssoc$;
        56: pop
        57: getstatic     #109                // Field java/lang/Byte.TYPE:Ljava/lang/Class;
        60: ldc           #108                // class java/lang/Byte
        62: astore_3
        63: astore_2
        64: new           #94                 // class scala/Tuple2
        67: dup
        68: aload_2
        69: aload_3
        70: invokespecial #106                // Method scala/Tuple2."<init>":(Ljava/lang/Object;Ljava/lang/Object;)V
        73: aconst_null
        74: astore_2
        75: aconst_null
        76: astore_3
        77: aastore
        78: dup
        79: iconst_2
        80: getstatic     #97                 // Field scala/Predef$ArrowAssoc$.MODULE$:Lscala/Predef$ArrowAssoc$;
        83: pop
        84: getstatic     #112                // Field java/lang/Character.TYPE:Ljava/lang/Class;
        87: ldc           #111                // class java/lang/Character
        89: astore        5
        91: astore        4
        93: new           #94                 // class scala/Tuple2
        96: dup
        97: aload         4
        99: aload         5
       101: invokespecial #106                // Method scala/Tuple2."<init>":(Ljava/lang/Object;Ljava/lang/Object;)V
       104: aconst_null
       105: astore        4
       107: aconst_null
       108: astore        5
       110: aastore
       111: dup
       112: iconst_3
       113: getstatic     #97                 // Field scala/Predef$ArrowAssoc$.MODULE$:Lscala/Predef$ArrowAssoc$;
       116: pop
       117: getstatic     #115                // Field java/lang/Short.TYPE:Ljava/lang/Class;
       120: ldc           #114                // class java/lang/Short
       122: astore        7
       124: astore        6
       126: new           #94                 // class scala/Tuple2
       129: dup
       130: aload         6
       132: aload         7
       134: invokespecial #106                // Method scala/Tuple2."<init>":(Ljava/lang/Object;Ljava/lang/Object;)V
       137: aconst_null
       138: astore        6
       140: aconst_null
       141: astore        7
       143: aastore
       144: dup
       145: iconst_4
       146: getstatic     #97                 // Field scala/Predef$ArrowAssoc$.MODULE$:Lscala/Predef$ArrowAssoc$;
       149: pop
       150: getstatic     #118                // Field java/lang/Integer.TYPE:Ljava/lang/Class;
       153: ldc           #117                // class java/lang/Integer
       155: astore        9
       157: astore        8
       159: new           #94                 // class scala/Tuple2
       162: dup
       163: aload         8
       165: aload         9
       167: invokespecial #106                // Method scala/Tuple2."<init>":(Ljava/lang/Object;Ljava/lang/Object;)V
       170: aconst_null
       171: astore        8
       173: aconst_null
       174: astore        9
       176: aastore
       177: dup
       178: iconst_5
       179: getstatic     #97                 // Field scala/Predef$ArrowAssoc$.MODULE$:Lscala/Predef$ArrowAssoc$;
       182: pop
       183: getstatic     #121                // Field java/lang/Long.TYPE:Ljava/lang/Class;
       186: ldc           #120                // class java/lang/Long
       188: astore        11
       190: astore        10
       192: new           #94                 // class scala/Tuple2
       195: dup
       196: aload         10
       198: aload         11
       200: invokespecial #106                // Method scala/Tuple2."<init>":(Ljava/lang/Object;Ljava/lang/Object;)V
       203: aconst_null
       204: astore        10
       206: aconst_null
       207: astore        11
       209: aastore
       210: dup
       211: bipush        6
       213: getstatic     #97                 // Field scala/Predef$ArrowAssoc$.MODULE$:Lscala/Predef$ArrowAssoc$;
       216: pop
       217: getstatic     #124                // Field java/lang/Float.TYPE:Ljava/lang/Class;
       220: ldc           #123                // class java/lang/Float
       222: astore        13
       224: astore        12
       226: new           #94                 // class scala/Tuple2
       229: dup
       230: aload         12
       232: aload         13
       234: invokespecial #106                // Method scala/Tuple2."<init>":(Ljava/lang/Object;Ljava/lang/Object;)V
       237: aconst_null
       238: astore        12
       240: aconst_null
       241: astore        13
       243: aastore
       244: dup
       245: bipush        7
       247: getstatic     #97                 // Field scala/Predef$ArrowAssoc$.MODULE$:Lscala/Predef$ArrowAssoc$;
       250: pop
       251: getstatic     #127                // Field java/lang/Double.TYPE:Ljava/lang/Class;
       254: ldc           #126                // class java/lang/Double
       256: astore        15
       258: astore        14
       260: new           #94                 // class scala/Tuple2
       263: dup
       264: aload         14
       266: aload         15
       268: invokespecial #106                // Method scala/Tuple2."<init>":(Ljava/lang/Object;Ljava/lang/Object;)V
       271: aconst_null
       272: astore        14
       274: aconst_null
       275: astore        15
       277: aastore
       278: dup
       279: bipush        8
       281: getstatic     #97                 // Field scala/Predef$ArrowAssoc$.MODULE$:Lscala/Predef$ArrowAssoc$;
       284: pop
       285: getstatic     #130                // Field scala/runtime/BoxedUnit.TYPE:Ljava/lang/Class;
       288: ldc           #129                // class scala/runtime/BoxedUnit
       290: astore        17
       292: astore        16
       294: new           #94                 // class scala/Tuple2
       297: dup
       298: aload         16
       300: aload         17
       302: invokespecial #106                // Method scala/Tuple2."<init>":(Ljava/lang/Object;Ljava/lang/Object;)V
       305: aconst_null
       306: astore        16
       308: aconst_null
       309: astore        17
       311: aastore
       312: invokevirtual #134                // Method scala/runtime/ScalaRunTime$.wrapRefArray:([Ljava/lang/Object;)Lscala/collection/immutable/ArraySeq;
       315: astore        19
       317: astore        18
       319: aload         18
       321: ifnonnull     326
       324: aconst_null
       325: athrow
       326: aload         18
       328: aload         19
       330: invokevirtual #140                // Method scala/collection/immutable/Map$.from:(Lscala/collection/IterableOnce;)Lscala/collection/immutable/Map;
       333: aconst_null
       334: astore        18
       336: aconst_null
       337: astore        19
       339: putstatic     #142                // Field toBoxed:Lscala/collection/immutable/Map;
       342: invokedynamic #160,  0            // InvokeDynamic #0:apply:()Lscala/Function1;
       347: putstatic     #162                // Field _cachedId:Lscala/Function1;
       350: invokedynamic #170,  0            // InvokeDynamic #1:apply:()Lscala/Function1;
       355: putstatic     #172                // Field collectFailed:Lscala/Function1;
       358: new           #174                // class scala/util/Failure
       361: dup
       362: new           #26                 // class scala/concurrent/Future$$anon$2
       365: dup
       366: invokespecial #175                // Method scala/concurrent/Future$$anon$2."<init>":()V
       369: invokespecial #178                // Method scala/util/Failure."<init>":(Ljava/lang/Throwable;)V
       372: putstatic     #180                // Field filterFailure:Lscala/util/Failure;
       375: new           #174                // class scala/util/Failure
       378: dup
       379: new           #28                 // class scala/concurrent/Future$$anon$3
       382: dup
       383: invokespecial #181                // Method scala/concurrent/Future$$anon$3."<init>":()V
       386: invokespecial #178                // Method scala/util/Failure."<init>":(Ljava/lang/Throwable;)V
       389: putstatic     #183                // Field failedFailure:Lscala/util/Failure;
       392: getstatic     #78                 // Field MODULE$:Lscala/concurrent/Future$;
       395: getstatic     #183                // Field failedFailure:Lscala/util/Failure;
       398: invokevirtual #187                // Method fromTry:(Lscala/util/Try;)Lscala/concurrent/Future;
       401: putstatic     #189                // Field failedFailureFuture:Lscala/concurrent/Future;
       404: invokedynamic #196,  0            // InvokeDynamic #2:apply:()Lscala/Function1;
       409: putstatic     #198                // Field _failedFun:Lscala/Function1;
       412: getstatic     #78                 // Field MODULE$:Lscala/concurrent/Future$;
       415: new           #30                 // class scala/concurrent/Future$$anon$4
       418: dup
       419: invokespecial #199                // Method scala/concurrent/Future$$anon$4."<init>":()V
       422: invokevirtual #203                // Method failed:(Ljava/lang/Throwable;)Lscala/concurrent/Future;
       425: putstatic     #205                // Field recoverWithFailedMarker:Lscala/concurrent/Future;
       428: invokedynamic #211,  0            // InvokeDynamic #3:apply:()Lscala/Function1;
       433: putstatic     #213                // Field recoverWithFailed:Lscala/Function1;
       436: invokedynamic #224,  0            // InvokeDynamic #4:apply:()Lscala/Function2;
       441: putstatic     #226                // Field _zipWithTuple2:Lscala/Function2;
       444: invokedynamic #233,  0            // InvokeDynamic #5:apply:()Lscala/Function2;
       449: putstatic     #235                // Field _addToBuilderFun:Lscala/Function2;
       452: getstatic     #78                 // Field MODULE$:Lscala/concurrent/Future$;
       455: new           #237                // class scala/util/Success
       458: dup
       459: getstatic     #241                // Field scala/runtime/BoxedUnit.UNIT:Lscala/runtime/BoxedUnit;
       462: invokespecial #244                // Method scala/util/Success."<init>":(Ljava/lang/Object;)V
       465: invokevirtual #187                // Method fromTry:(Lscala/util/Try;)Lscala/concurrent/Future;
       468: putstatic     #246                // Field unit:Lscala/concurrent/Future;
       471: return
      StackMapTable: number_of_entries = 1
        frame_type = 255 /* full_frame */
          offset_delta = 326
          locals = [ null, null, null, null, null, null, null, null, null, null, null, null, null, null, null, null, null, null, class scala/collection/immutable/Map$, class scala/collection/immutable/ArraySeq ]
          stack = []
      LineNumberTable:
        line 520: 0
        line 526: 10
        line 527: 30
        line 528: 57
        line 529: 84
        line 530: 117
        line 531: 150
        line 532: 183
        line 533: 217
        line 534: 251
        line 535: 285
        line 526: 339
        line 538: 342
        line 543: 350
        line 542: 355
        line 546: 358
        line 545: 372
        line 549: 375
        line 548: 389
        line 552: 392
        line 551: 401
        line 555: 404
        line 554: 409
        line 560: 412
        line 559: 425
        line 562: 428
        line 564: 436
        line 567: 444
        line 634: 452
        line 520: 471
      LocalVariableTable:
        Start  Length  Slot  Name   Signature
           37       9     0 $minus$greater$extension_$this   Ljava/lang/Object;
           37       9     1 $minus$greater$extension_y   Ljava/lang/Object;
           64       9     2 $minus$greater$extension_$this   Ljava/lang/Object;
           64       9     3 $minus$greater$extension_y   Ljava/lang/Object;
           93      11     4 $minus$greater$extension_$this   Ljava/lang/Object;
           93      11     5 $minus$greater$extension_y   Ljava/lang/Object;
          126      11     6 $minus$greater$extension_$this   Ljava/lang/Object;
          126      11     7 $minus$greater$extension_y   Ljava/lang/Object;
          159      11     8 $minus$greater$extension_$this   Ljava/lang/Object;
          159      11     9 $minus$greater$extension_y   Ljava/lang/Object;
          192      11    10 $minus$greater$extension_$this   Ljava/lang/Object;
          192      11    11 $minus$greater$extension_y   Ljava/lang/Object;
          226      11    12 $minus$greater$extension_$this   Ljava/lang/Object;
          226      11    13 $minus$greater$extension_y   Ljava/lang/Object;
          260      11    14 $minus$greater$extension_$this   Ljava/lang/Object;
          260      11    15 $minus$greater$extension_y   Ljava/lang/Object;
          294      11    16 $minus$greater$extension_$this   Ljava/lang/Object;
          294      11    17 $minus$greater$extension_y   Ljava/lang/Object;
          319      14    18 apply_this   Lscala/collection/immutable/Map$;
          319      14    19 apply_elems   Lscala/collection/immutable/Seq;

  public final scala.collection.immutable.Map<java.lang.Class<?>, java.lang.Class<?>> toBoxed();
    descriptor: ()Lscala/collection/immutable/Map;
    flags: (0x0011) ACC_PUBLIC, ACC_FINAL
    Code:
      stack=1, locals=1, args_size=1
         0: getstatic     #142                // Field toBoxed:Lscala/collection/immutable/Map;
         3: areturn
      LineNumberTable:
        line 526: 0
      LocalVariableTable:
        Start  Length  Slot  Name   Signature
            0       4     0  this   Lscala/concurrent/Future$;
    Signature: #257                         // ()Lscala/collection/immutable/Map<Ljava/lang/Class<*>;Ljava/lang/Class<*>;>;

  public final <T extends java.lang.Object> scala.Function1<T, T> id();
    descriptor: ()Lscala/Function1;
    flags: (0x0011) ACC_PUBLIC, ACC_FINAL
    Code:
      stack=1, locals=1, args_size=1
         0: getstatic     #162                // Field _cachedId:Lscala/Function1;
         3: areturn
      LineNumberTable:
        line 540: 0
      LocalVariableTable:
        Start  Length  Slot  Name   Signature
            0       4     0  this   Lscala/concurrent/Future$;
    Signature: #260                         // <T:Ljava/lang/Object;>()Lscala/Function1<TT;TT;>;

  public final scala.Function1<java.lang.Object, scala.runtime.Nothing$> collectFailed();
    descriptor: ()Lscala/Function1;
    flags: (0x0011) ACC_PUBLIC, ACC_FINAL
    Code:
      stack=1, locals=1, args_size=1
         0: getstatic     #172                // Field collectFailed:Lscala/Function1;
         3: areturn
      LineNumberTable:
        line 542: 0
      LocalVariableTable:
        Start  Length  Slot  Name   Signature
            0       4     0  this   Lscala/concurrent/Future$;
    Signature: #261                         // ()Lscala/Function1<Ljava/lang/Object;Lscala/runtime/Nothing$;>;

  public final scala.util.Failure<scala.runtime.Nothing$> filterFailure();
    descriptor: ()Lscala/util/Failure;
    flags: (0x0011) ACC_PUBLIC, ACC_FINAL
    Code:
      stack=1, locals=1, args_size=1
         0: getstatic     #180                // Field filterFailure:Lscala/util/Failure;
         3: areturn
      LineNumberTable:
        line 545: 0
      LocalVariableTable:
        Start  Length  Slot  Name   Signature
            0       4     0  this   Lscala/concurrent/Future$;
    Signature: #263                         // ()Lscala/util/Failure<Lscala/runtime/Nothing$;>;

  public final scala.concurrent.Future<scala.runtime.Nothing$> failedFailureFuture();
    descriptor: ()Lscala/concurrent/Future;
    flags: (0x0011) ACC_PUBLIC, ACC_FINAL
    Code:
      stack=1, locals=1, args_size=1
         0: getstatic     #189                // Field failedFailureFuture:Lscala/concurrent/Future;
         3: areturn
      LineNumberTable:
        line 551: 0
      LocalVariableTable:
        Start  Length  Slot  Name   Signature
            0       4     0  this   Lscala/concurrent/Future$;
    Signature: #265                         // ()Lscala/concurrent/Future<Lscala/runtime/Nothing$;>;

  public final <T extends java.lang.Object> scala.Function1<scala.util.Try<T>, scala.util.Try<java.lang.Throwable>> failedFun();
    descriptor: ()Lscala/Function1;
    flags: (0x0011) ACC_PUBLIC, ACC_FINAL
    Code:
      stack=1, locals=1, args_size=1
         0: getstatic     #198                // Field _failedFun:Lscala/Function1;
         3: areturn
      LineNumberTable:
        line 557: 0
      LocalVariableTable:
        Start  Length  Slot  Name   Signature
            0       4     0  this   Lscala/concurrent/Future$;
    Signature: #267                         // <T:Ljava/lang/Object;>()Lscala/Function1<Lscala/util/Try<TT;>;Lscala/util/Try<Ljava/lang/Throwable;>;>;

  public final scala.concurrent.Future<scala.runtime.Nothing$> recoverWithFailedMarker();
    descriptor: ()Lscala/concurrent/Future;
    flags: (0x0011) ACC_PUBLIC, ACC_FINAL
    Code:
      stack=1, locals=1, args_size=1
         0: getstatic     #205                // Field recoverWithFailedMarker:Lscala/concurrent/Future;
         3: areturn
      LineNumberTable:
        line 559: 0
      LocalVariableTable:
        Start  Length  Slot  Name   Signature
            0       4     0  this   Lscala/concurrent/Future$;
    Signature: #265                         // ()Lscala/concurrent/Future<Lscala/runtime/Nothing$;>;

  public final scala.Function1<java.lang.Throwable, scala.concurrent.Future<scala.runtime.Nothing$>> recoverWithFailed();
    descriptor: ()Lscala/Function1;
    flags: (0x0011) ACC_PUBLIC, ACC_FINAL
    Code:
      stack=1, locals=1, args_size=1
         0: getstatic     #213                // Field recoverWithFailed:Lscala/Function1;
         3: areturn
      LineNumberTable:
        line 562: 0
      LocalVariableTable:
        Start  Length  Slot  Name   Signature
            0       4     0  this   Lscala/concurrent/Future$;
    Signature: #268                         // ()Lscala/Function1<Ljava/lang/Throwable;Lscala/concurrent/Future<Lscala/runtime/Nothing$;>;>;

  public final <T extends java.lang.Object, U extends java.lang.Object> scala.Function2<T, U, scala.Tuple2<T, U>> zipWithTuple2Fun();
    descriptor: ()Lscala/Function2;
    flags: (0x0011) ACC_PUBLIC, ACC_FINAL
    Code:
      stack=1, locals=1, args_size=1
         0: getstatic     #226                // Field _zipWithTuple2:Lscala/Function2;
         3: areturn
      LineNumberTable:
        line 565: 0
      LocalVariableTable:
        Start  Length  Slot  Name   Signature
            0       4     0  this   Lscala/concurrent/Future$;
    Signature: #270                         // <T:Ljava/lang/Object;U:Ljava/lang/Object;>()Lscala/Function2<TT;TU;Lscala/Tuple2<TT;TU;>;>;

  public final <A extends java.lang.Object, M extends java.lang.Object> scala.Function2<scala.collection.mutable.Builder<A, M>, A, scala.collection.mutable.Builder<A, M>> addToBuilderFun();
    descriptor: ()Lscala/Function2;
    flags: (0x0011) ACC_PUBLIC, ACC_FINAL
    Code:
      stack=1, locals=1, args_size=1
         0: getstatic     #235                // Field _addToBuilderFun:Lscala/Function2;
         3: areturn
      LineNumberTable:
        line 568: 0
      LocalVariableTable:
        Start  Length  Slot  Name   Signature
            0       4     0  this   Lscala/concurrent/Future$;
    Signature: #272                         // <A:Ljava/lang/Object;M:Ljava/lang/Object;>()Lscala/Function2<Lscala/collection/mutable/Builder<TA;TM;>;TA;Lscala/collection/mutable/Builder<TA;TM;>;>;

  public final scala.concurrent.Future<scala.runtime.BoxedUnit> unit();
    descriptor: ()Lscala/concurrent/Future;
    flags: (0x0011) ACC_PUBLIC, ACC_FINAL
    Code:
      stack=1, locals=1, args_size=1
         0: getstatic     #246                // Field unit:Lscala/concurrent/Future;
         3: areturn
      LineNumberTable:
        line 634: 0
      LocalVariableTable:
        Start  Length  Slot  Name   Signature
            0       4     0  this   Lscala/concurrent/Future$;
    Signature: #273                         // ()Lscala/concurrent/Future<Lscala/runtime/BoxedUnit;>;

  public final <T extends java.lang.Object> scala.concurrent.Future<T> failed(java.lang.Throwable);
    descriptor: (Ljava/lang/Throwable;)Lscala/concurrent/Future;
    flags: (0x0011) ACC_PUBLIC, ACC_FINAL
    Code:
      stack=2, locals=2, args_size=2
         0: getstatic     #280                // Field scala/concurrent/Promise$.MODULE$:Lscala/concurrent/Promise$;
         3: aload_1
         4: invokevirtual #283                // Method scala/concurrent/Promise$.failed:(Ljava/lang/Throwable;)Lscala/concurrent/Promise;
         7: invokeinterface #288,  1          // InterfaceMethod scala/concurrent/Promise.future:()Lscala/concurrent/Future;
        12: areturn
      LineNumberTable:
        line 642: 0
      LocalVariableTable:
        Start  Length  Slot  Name   Signature
            0      13     0  this   Lscala/concurrent/Future$;
            0      13     1 exception   Ljava/lang/Throwable;
    Signature: #274                         // <T:Ljava/lang/Object;>(Ljava/lang/Throwable;)Lscala/concurrent/Future<TT;>;
    MethodParameters:
      Name                           Flags
      exception                      final

  public final <T extends java.lang.Object> scala.concurrent.Future<T> successful(T);
    descriptor: (Ljava/lang/Object;)Lscala/concurrent/Future;
    flags: (0x0011) ACC_PUBLIC, ACC_FINAL
    Code:
      stack=2, locals=2, args_size=2
         0: getstatic     #280                // Field scala/concurrent/Promise$.MODULE$:Lscala/concurrent/Promise$;
         3: aload_1
         4: invokevirtual #296                // Method scala/concurrent/Promise$.successful:(Ljava/lang/Object;)Lscala/concurrent/Promise;
         7: invokeinterface #288,  1          // InterfaceMethod scala/concurrent/Promise.future:()Lscala/concurrent/Future;
        12: areturn
      LineNumberTable:
        line 650: 0
      LocalVariableTable:
        Start  Length  Slot  Name   Signature
            0      13     0  this   Lscala/concurrent/Future$;
            0      13     1 result   Ljava/lang/Object;
    Signature: #292                         // <T:Ljava/lang/Object;>(TT;)Lscala/concurrent/Future<TT;>;
    MethodParameters:
      Name                           Flags
      result                         final

  public final <T extends java.lang.Object> scala.concurrent.Future<T> fromTry(scala.util.Try<T>);
    descriptor: (Lscala/util/Try;)Lscala/concurrent/Future;
    flags: (0x0011) ACC_PUBLIC, ACC_FINAL
    Code:
      stack=3, locals=2, args_size=2
         0: getstatic     #280                // Field scala/concurrent/Promise$.MODULE$:Lscala/concurrent/Promise$;
         3: pop
         4: new           #39                 // class scala/concurrent/impl/Promise$DefaultPromise
         7: dup
         8: aload_1
         9: invokespecial #300                // Method scala/concurrent/impl/Promise$DefaultPromise."<init>":(Lscala/util/Try;)V
        12: areturn
      LineNumberTable:
        line 658: 0
      LocalVariableTable:
        Start  Length  Slot  Name   Signature
            0      13     0  this   Lscala/concurrent/Future$;
            0      13     1 result   Lscala/util/Try;
    Signature: #297                         // <T:Ljava/lang/Object;>(Lscala/util/Try<TT;>;)Lscala/concurrent/Future<TT;>;
    MethodParameters:
      Name                           Flags
      result                         final

  public final <T extends java.lang.Object> scala.concurrent.Future<T> apply(scala.Function0<T>, scala.concurrent.ExecutionContext);
    descriptor: (Lscala/Function0;Lscala/concurrent/ExecutionContext;)Lscala/concurrent/Future;
    flags: (0x0011) ACC_PUBLIC, ACC_FINAL
    Code:
      stack=3, locals=3, args_size=3
         0: aload_0
         1: invokevirtual #307                // Method unit:()Lscala/concurrent/Future;
         4: aload_1
         5: invokedynamic #317,  0            // InvokeDynamic #6:apply:(Lscala/Function0;)Lscala/Function1;
        10: aload_2
        11: invokeinterface #321,  3          // InterfaceMethod scala/concurrent/Future.map:(Lscala/Function1;Lscala/concurrent/ExecutionContext;)Lscala/concurrent/Future;
        16: areturn
      LineNumberTable:
        line 678: 0
      LocalVariableTable:
        Start  Length  Slot  Name   Signature
            0      17     0  this   Lscala/concurrent/Future$;
            0      17     1  body   Lscala/Function0;
            0      17     2 executor   Lscala/concurrent/ExecutionContext;
    Signature: #303                         // <T:Ljava/lang/Object;>(Lscala/Function0<TT;>;Lscala/concurrent/ExecutionContext;)Lscala/concurrent/Future<TT;>;
    MethodParameters:
      Name                           Flags
      body                           final
      executor                       final

  public final <T extends java.lang.Object> scala.concurrent.Future<T> delegate(scala.Function0<scala.concurrent.Future<T>>, scala.concurrent.ExecutionContext);
    descriptor: (Lscala/Function0;Lscala/concurrent/ExecutionContext;)Lscala/concurrent/Future;
    flags: (0x0011) ACC_PUBLIC, ACC_FINAL
    Code:
      stack=3, locals=3, args_size=3
         0: aload_0
         1: invokevirtual #307                // Method unit:()Lscala/concurrent/Future;
         4: aload_1
         5: invokedynamic #333,  0            // InvokeDynamic #7:apply:(Lscala/Function0;)Lscala/Function1;
        10: aload_2
        11: invokeinterface #336,  3          // InterfaceMethod scala/concurrent/Future.flatMap:(Lscala/Function1;Lscala/concurrent/ExecutionContext;)Lscala/concurrent/Future;
        16: areturn
      LineNumberTable:
        line 698: 0
      LocalVariableTable:
        Start  Length  Slot  Name   Signature
            0      17     0  this   Lscala/concurrent/Future$;
            0      17     1  body   Lscala/Function0;
            0      17     2 executor   Lscala/concurrent/ExecutionContext;
    Signature: #325                         // <T:Ljava/lang/Object;>(Lscala/Function0<Lscala/concurrent/Future<TT;>;>;Lscala/concurrent/ExecutionContext;)Lscala/concurrent/Future<TT;>;
    MethodParameters:
      Name                           Flags
      body                           final
      executor                       final

  public final <A extends java.lang.Object, CC extends scala.collection.IterableOnce<java.lang.Object>, To extends java.lang.Object> scala.concurrent.Future<To> sequence(CC, scala.collection.BuildFrom<CC, A, To>, scala.concurrent.ExecutionContext);
    descriptor: (Lscala/collection/IterableOnce;Lscala/collection/BuildFrom;Lscala/concurrent/ExecutionContext;)Lscala/concurrent/Future;
    flags: (0x0011) ACC_PUBLIC, ACC_FINAL
    Code:
      stack=4, locals=4, args_size=4
         0: aload_1
         1: invokeinterface #347,  1          // InterfaceMethod scala/collection/IterableOnce.iterator:()Lscala/collection/Iterator;
         6: aload_0
         7: aload_2
         8: aload_1
         9: invokeinterface #353,  2          // InterfaceMethod scala/collection/BuildFrom.newBuilder:(Ljava/lang/Object;)Lscala/collection/mutable/Builder;
        14: invokevirtual #355                // Method successful:(Ljava/lang/Object;)Lscala/concurrent/Future;
        17: aload_3
        18: invokedynamic #365,  0            // InvokeDynamic #8:apply:(Lscala/concurrent/ExecutionContext;)Lscala/Function2;
        23: invokeinterface #371,  3          // InterfaceMethod scala/collection/Iterator.foldLeft:(Ljava/lang/Object;Lscala/Function2;)Ljava/lang/Object;
        28: checkcast     #36                 // class scala/concurrent/Future
        31: invokedynamic #378,  0            // InvokeDynamic #9:apply:()Lscala/Function1;
        36: aload_3
        37: instanceof    #380                // class scala/concurrent/BatchingExecutor
        40: ifeq          47
        43: aload_3
        44: goto          50
        47: getstatic     #383                // Field scala/concurrent/ExecutionContext$parasitic$.MODULE$:Lscala/concurrent/ExecutionContext$parasitic$;
        50: invokeinterface #321,  3          // InterfaceMethod scala/concurrent/Future.map:(Lscala/Function1;Lscala/concurrent/ExecutionContext;)Lscala/concurrent/Future;
        55: areturn
      StackMapTable: number_of_entries = 2
        frame_type = 255 /* full_frame */
          offset_delta = 47
          locals = [ class scala/concurrent/Future$, class scala/collection/IterableOnce, class scala/collection/BuildFrom, class scala/concurrent/ExecutionContext ]
          stack = [ class scala/concurrent/Future, class scala/Function1 ]
        frame_type = 255 /* full_frame */
          offset_delta = 2
          locals = [ class scala/concurrent/Future$, class scala/collection/IterableOnce, class scala/collection/BuildFrom, class scala/concurrent/ExecutionContext ]
          stack = [ class scala/concurrent/Future, class scala/Function1, class scala/concurrent/ExecutionContext ]
      LineNumberTable:
        line 710: 0
        line 711: 17
        line 712: 31
      LocalVariableTable:
        Start  Length  Slot  Name   Signature
            0      56     0  this   Lscala/concurrent/Future$;
            0      56     1    in   Lscala/collection/IterableOnce;
            0      56     2    bf   Lscala/collection/BuildFrom;
            0      56     3 executor   Lscala/concurrent/ExecutionContext;
    Signature: #339                         // <A:Ljava/lang/Object;CC::Lscala/collection/IterableOnce<Ljava/lang/Object;>;To:Ljava/lang/Object;>(TCC;Lscala/collection/BuildFrom<TCC;TA;TTo;>;Lscala/concurrent/ExecutionContext;)Lscala/concurrent/Future<TTo;>;
    MethodParameters:
      Name                           Flags
      in                             final
      bf                             final
      executor                       final

  public final <T extends java.lang.Object> scala.concurrent.Future<T> firstCompletedOf(scala.collection.IterableOnce<scala.concurrent.Future<T>>, scala.concurrent.ExecutionContext);
    descriptor: (Lscala/collection/IterableOnce;Lscala/concurrent/ExecutionContext;)Lscala/concurrent/Future;
    flags: (0x0011) ACC_PUBLIC, ACC_FINAL
    Code:
      stack=3, locals=7, args_size=3
         0: aload_1
         1: invokeinterface #347,  1          // InterfaceMethod scala/collection/IterableOnce.iterator:()Lscala/collection/Iterator;
         6: astore_3
         7: aload_3
         8: invokeinterface #395,  1          // InterfaceMethod scala/collection/Iterator.hasNext:()Z
        13: ifne          20
        16: getstatic     #398                // Field scala/concurrent/Future$never$.MODULE$:Lscala/concurrent/Future$never$;
        19: areturn
        20: getstatic     #280                // Field scala/concurrent/Promise$.MODULE$:Lscala/concurrent/Promise$;
        23: pop
        24: new           #39                 // class scala/concurrent/impl/Promise$DefaultPromise
        27: dup
        28: invokespecial #399                // Method scala/concurrent/impl/Promise$DefaultPromise."<init>":()V
        31: astore        6
        33: aload         6
        35: aconst_null
        36: astore        6
        38: astore        4
        40: new           #32                 // class scala/concurrent/Future$$anon$5
        43: dup
        44: aload         4
        46: invokespecial #402                // Method scala/concurrent/Future$$anon$5."<init>":(Lscala/concurrent/Promise;)V
        49: astore        5
        51: aload_3
        52: invokeinterface #395,  1          // InterfaceMethod scala/collection/Iterator.hasNext:()Z
        57: ifeq          88
        60: aload         5
        62: invokevirtual #408                // Method java/util/concurrent/atomic/AtomicReference.get:()Ljava/lang/Object;
        65: ifnull        88
        68: aload_3
        69: invokeinterface #411,  1          // InterfaceMethod scala/collection/Iterator.next:()Ljava/lang/Object;
        74: checkcast     #36                 // class scala/concurrent/Future
        77: aload         5
        79: aload_2
        80: invokeinterface #415,  3          // InterfaceMethod scala/concurrent/Future.onComplete:(Lscala/Function1;Lscala/concurrent/ExecutionContext;)V
        85: goto          51
        88: aload         4
        90: areturn
      StackMapTable: number_of_entries = 3
        frame_type = 252 /* append */
          offset_delta = 20
          locals = [ class scala/collection/Iterator ]
        frame_type = 254 /* append */
          offset_delta = 30
          locals = [ class scala/concurrent/impl/Promise$DefaultPromise, class scala/concurrent/Future$$anon$5, null ]
        frame_type = 36 /* same */
      LineNumberTable:
        line 722: 0
        line 723: 7
        line 725: 20
        line 726: 40
        line 733: 51
        line 734: 68
        line 735: 88
      LocalVariableTable:
        Start  Length  Slot  Name   Signature
           40      50     4     p   Lscala/concurrent/Promise;
           51      39     5 firstCompleteHandler   Ljava/util/concurrent/atomic/AtomicReference;
            7      83     3     i   Lscala/collection/Iterator;
            0      91     0  this   Lscala/concurrent/Future$;
            0      91     1 futures   Lscala/collection/IterableOnce;
            0      91     2 executor   Lscala/concurrent/ExecutionContext;
    Signature: #390                         // <T:Ljava/lang/Object;>(Lscala/collection/IterableOnce<Lscala/concurrent/Future<TT;>;>;Lscala/concurrent/ExecutionContext;)Lscala/concurrent/Future<TT;>;
    MethodParameters:
      Name                           Flags
      futures                        final
      executor                       final

  public final <T extends java.lang.Object> scala.concurrent.Future<scala.Option<T>> find(scala.collection.immutable.Iterable<scala.concurrent.Future<T>>, scala.Function1<T, java.lang.Object>, scala.concurrent.ExecutionContext);
    descriptor: (Lscala/collection/immutable/Iterable;Lscala/Function1;Lscala/concurrent/ExecutionContext;)Lscala/concurrent/Future;
    flags: (0x0011) ACC_PUBLIC, ACC_FINAL
    Code:
      stack=5, locals=5, args_size=4
         0: aload_1
         1: invokeinterface #427,  1          // InterfaceMethod scala/collection/immutable/Iterable.iterator:()Lscala/collection/Iterator;
         6: astore        4
         8: aload         4
        10: invokeinterface #395,  1          // InterfaceMethod scala/collection/Iterator.hasNext:()Z
        15: ifne          26
        18: aload_0
        19: getstatic     #432                // Field scala/None$.MODULE$:Lscala/None$;
        22: invokevirtual #355                // Method successful:(Ljava/lang/Object;)Lscala/concurrent/Future;
        25: areturn
        26: aload         4
        28: invokeinterface #411,  1          // InterfaceMethod scala/collection/Iterator.next:()Ljava/lang/Object;
        33: checkcast     #36                 // class scala/concurrent/Future
        36: aload_0
        37: aload_2
        38: aload         4
        40: aload_3
        41: invokedynamic #441,  0            // InvokeDynamic #10:apply:(Lscala/concurrent/Future$;Lscala/Function1;Lscala/collection/Iterator;Lscala/concurrent/ExecutionContext;)Lscala/Function1;
        46: aload_3
        47: invokeinterface #444,  3          // InterfaceMethod scala/concurrent/Future.transformWith:(Lscala/Function1;Lscala/concurrent/ExecutionContext;)Lscala/concurrent/Future;
        52: areturn
      StackMapTable: number_of_entries = 1
        frame_type = 252 /* append */
          offset_delta = 26
          locals = [ class scala/collection/Iterator ]
      LineNumberTable:
        line 755: 0
        line 749: 8
        line 750: 26
        line 755: 52
      LocalVariableTable:
        Start  Length  Slot  Name   Signature
            0      53     0  this   Lscala/concurrent/Future$;
            0      53     1 futures   Lscala/collection/immutable/Iterable;
            0      53     2     p   Lscala/Function1;
            0      53     3 executor   Lscala/concurrent/ExecutionContext;
            8      44     4 searchNext$1_i   Lscala/collection/Iterator;
    Signature: #424                         // <T:Ljava/lang/Object;>(Lscala/collection/immutable/Iterable<Lscala/concurrent/Future<TT;>;>;Lscala/Function1<TT;Ljava/lang/Object;>;Lscala/concurrent/ExecutionContext;)Lscala/concurrent/Future<Lscala/Option<TT;>;>;
    MethodParameters:
      Name                           Flags
      futures                        final
      p                              final
      executor                       final

  public final <T extends java.lang.Object, R extends java.lang.Object> scala.concurrent.Future<R> foldLeft(scala.collection.immutable.Iterable<scala.concurrent.Future<T>>, R, scala.Function2<R, T, R>, scala.concurrent.ExecutionContext);
    descriptor: (Lscala/collection/immutable/Iterable;Ljava/lang/Object;Lscala/Function2;Lscala/concurrent/ExecutionContext;)Lscala/concurrent/Future;
    flags: (0x0011) ACC_PUBLIC, ACC_FINAL
    Code:
      stack=5, locals=6, args_size=5
         0: aload_1
         1: invokeinterface #427,  1          // InterfaceMethod scala/collection/immutable/Iterable.iterator:()Lscala/collection/Iterator;
         6: astore        5
         8: aload         5
        10: invokeinterface #395,  1          // InterfaceMethod scala/collection/Iterator.hasNext:()Z
        15: ifne          24
        18: aload_0
        19: aload_2
        20: invokevirtual #355                // Method successful:(Ljava/lang/Object;)Lscala/concurrent/Future;
        23: areturn
        24: aload         5
        26: invokeinterface #411,  1          // InterfaceMethod scala/collection/Iterator.next:()Ljava/lang/Object;
        31: checkcast     #36                 // class scala/concurrent/Future
        34: aload         5
        36: aload_3
        37: aload_2
        38: aload         4
        40: invokedynamic #459,  0            // InvokeDynamic #11:apply:(Lscala/collection/Iterator;Lscala/Function2;Ljava/lang/Object;Lscala/concurrent/ExecutionContext;)Lscala/Function1;
        45: aload         4
        47: invokeinterface #336,  3          // InterfaceMethod scala/concurrent/Future.flatMap:(Lscala/Function1;Lscala/concurrent/ExecutionContext;)Lscala/concurrent/Future;
        52: areturn
      StackMapTable: number_of_entries = 1
        frame_type = 252 /* append */
          offset_delta = 24
          locals = [ class scala/collection/Iterator ]
      LineNumberTable:
        line 777: 0
        line 780: 8
        line 781: 24
        line 777: 52
      LocalVariableTable:
        Start  Length  Slot  Name   Signature
            0      53     0  this   Lscala/concurrent/Future$;
            0      53     1 futures   Lscala/collection/immutable/Iterable;
            0      53     2  zero   Ljava/lang/Object;
            0      53     3    op   Lscala/Function2;
            0      53     4 executor   Lscala/concurrent/ExecutionContext;
            8      44     5 foldNext_i   Lscala/collection/Iterator;
    Signature: #448                         // <T:Ljava/lang/Object;R:Ljava/lang/Object;>(Lscala/collection/immutable/Iterable<Lscala/concurrent/Future<TT;>;>;TR;Lscala/Function2<TR;TT;TR;>;Lscala/concurrent/ExecutionContext;)Lscala/concurrent/Future<TR;>;
    MethodParameters:
      Name                           Flags
      futures                        final
      zero                           final
      op                             final
      executor                       final

  private final <T extends java.lang.Object, R extends java.lang.Object> scala.concurrent.Future<R> foldNext(scala.collection.Iterator<scala.concurrent.Future<T>>, R, scala.Function2<R, T, R>, scala.concurrent.ExecutionContext);
    descriptor: (Lscala/collection/Iterator;Ljava/lang/Object;Lscala/Function2;Lscala/concurrent/ExecutionContext;)Lscala/concurrent/Future;
    flags: (0x0012) ACC_PRIVATE, ACC_FINAL
    Code:
      stack=5, locals=5, args_size=5
         0: aload_1
         1: invokeinterface #395,  1          // InterfaceMethod scala/collection/Iterator.hasNext:()Z
         6: ifne          15
         9: aload_0
        10: aload_2
        11: invokevirtual #355                // Method successful:(Ljava/lang/Object;)Lscala/concurrent/Future;
        14: areturn
        15: aload_1
        16: invokeinterface #411,  1          // InterfaceMethod scala/collection/Iterator.next:()Ljava/lang/Object;
        21: checkcast     #36                 // class scala/concurrent/Future
        24: aload_1
        25: aload_3
        26: aload_2
        27: aload         4
        29: invokedynamic #459,  0            // InvokeDynamic #11:apply:(Lscala/collection/Iterator;Lscala/Function2;Ljava/lang/Object;Lscala/concurrent/ExecutionContext;)Lscala/Function1;
        34: aload         4
        36: invokeinterface #336,  3          // InterfaceMethod scala/concurrent/Future.flatMap:(Lscala/Function1;Lscala/concurrent/ExecutionContext;)Lscala/concurrent/Future;
        41: areturn
      StackMapTable: number_of_entries = 1
        frame_type = 15 /* same */
      LineNumberTable:
        line 780: 0
        line 781: 15
      LocalVariableTable:
        Start  Length  Slot  Name   Signature
            0      42     0  this   Lscala/concurrent/Future$;
            0      42     1     i   Lscala/collection/Iterator;
            0      42     2 prevValue   Ljava/lang/Object;
            0      42     3    op   Lscala/Function2;
            0      42     4 executor   Lscala/concurrent/ExecutionContext;
    Signature: #463                         // <T:Ljava/lang/Object;R:Ljava/lang/Object;>(Lscala/collection/Iterator<Lscala/concurrent/Future<TT;>;>;TR;Lscala/Function2<TR;TT;TR;>;Lscala/concurrent/ExecutionContext;)Lscala/concurrent/Future<TR;>;
    MethodParameters:
      Name                           Flags
      i                              final
      prevValue                      final
      op                             final
      executor                       final

  public <T extends java.lang.Object, R extends java.lang.Object> scala.concurrent.Future<R> fold(scala.collection.IterableOnce<scala.concurrent.Future<T>>, R, scala.Function2<R, T, R>, scala.concurrent.ExecutionContext);
    descriptor: (Lscala/collection/IterableOnce;Ljava/lang/Object;Lscala/Function2;Lscala/concurrent/ExecutionContext;)Lscala/concurrent/Future;
    flags: (0x0001) ACC_PUBLIC
    Code:
      stack=5, locals=6, args_size=5
         0: getstatic     #472                // Field scala/collection/IterableOnceExtensionMethods$.MODULE$:Lscala/collection/IterableOnceExtensionMethods$;
         3: getstatic     #477                // Field scala/collection/IterableOnce$.MODULE$:Lscala/collection/IterableOnce$;
         6: pop
         7: aload_1
         8: invokevirtual #481                // Method scala/collection/IterableOnceExtensionMethods$.isEmpty$extension:(Lscala/collection/IterableOnce;)Z
        11: ifeq          20
        14: aload_0
        15: aload_2
        16: invokevirtual #355                // Method successful:(Ljava/lang/Object;)Lscala/concurrent/Future;
        19: areturn
        20: aload_0
        21: aload_1
        22: getstatic     #486                // Field scala/collection/IterableFactory$.MODULE$:Lscala/collection/IterableFactory$;
        25: pop
        26: getstatic     #491                // Field scala/collection/mutable/ArrayBuffer$.MODULE$:Lscala/collection/mutable/ArrayBuffer$;
        29: astore        5
        31: new           #17                 // class scala/collection/IterableFactory$$anon$1
        34: dup
        35: aload         5
        37: invokespecial #494                // Method scala/collection/IterableFactory$$anon$1."<init>":(Lscala/collection/IterableFactory;)V
        40: aconst_null
        41: astore        5
        43: aload         4
        45: invokevirtual #496                // Method sequence:(Lscala/collection/IterableOnce;Lscala/collection/BuildFrom;Lscala/concurrent/ExecutionContext;)Lscala/concurrent/Future;
        48: aload_2
        49: aload_3
        50: invokedynamic #506,  0            // InvokeDynamic #12:apply:(Ljava/lang/Object;Lscala/Function2;)Lscala/Function1;
        55: aload         4
        57: invokeinterface #321,  3          // InterfaceMethod scala/concurrent/Future.map:(Lscala/Function1;Lscala/concurrent/ExecutionContext;)Lscala/concurrent/Future;
        62: areturn
      StackMapTable: number_of_entries = 1
        frame_type = 20 /* same */
      LineNumberTable:
        line 803: 0
        line 804: 20
      LocalVariableTable:
        Start  Length  Slot  Name   Signature
            0      63     0  this   Lscala/concurrent/Future$;
            0      63     1 futures   Lscala/collection/IterableOnce;
            0      63     2  zero   Ljava/lang/Object;
            0      63     3    op   Lscala/Function2;
            0      63     4 executor   Lscala/concurrent/ExecutionContext;
           31       9     5 toBuildFrom_factory   Lscala/collection/IterableFactory;
    Signature: #467                         // <T:Ljava/lang/Object;R:Ljava/lang/Object;>(Lscala/collection/IterableOnce<Lscala/concurrent/Future<TT;>;>;TR;Lscala/Function2<TR;TT;TR;>;Lscala/concurrent/ExecutionContext;)Lscala/concurrent/Future<TR;>;
    Deprecated: true
    MethodParameters:
      Name                           Flags
      futures                        final
      zero                           final
      op                             final
      executor                       final

  public final <T extends java.lang.Object, R extends java.lang.Object> scala.concurrent.Future<R> reduce(scala.collection.IterableOnce<scala.concurrent.Future<T>>, scala.Function2<R, T, R>, scala.concurrent.ExecutionContext);
    descriptor: (Lscala/collection/IterableOnce;Lscala/Function2;Lscala/concurrent/ExecutionContext;)Lscala/concurrent/Future;
    flags: (0x0011) ACC_PUBLIC, ACC_FINAL
    Code:
      stack=5, locals=5, args_size=4
         0: getstatic     #472                // Field scala/collection/IterableOnceExtensionMethods$.MODULE$:Lscala/collection/IterableOnceExtensionMethods$;
         3: getstatic     #477                // Field scala/collection/IterableOnce$.MODULE$:Lscala/collection/IterableOnce$;
         6: pop
         7: aload_1
         8: invokevirtual #481                // Method scala/collection/IterableOnceExtensionMethods$.isEmpty$extension:(Lscala/collection/IterableOnce;)Z
        11: ifeq          29
        14: aload_0
        15: new           #513                // class java/util/NoSuchElementException
        18: dup
        19: ldc_w         #515                // String reduce attempted on empty collection
        22: invokespecial #518                // Method java/util/NoSuchElementException."<init>":(Ljava/lang/String;)V
        25: invokevirtual #203                // Method failed:(Ljava/lang/Throwable;)Lscala/concurrent/Future;
        28: areturn
        29: aload_0
        30: aload_1
        31: getstatic     #486                // Field scala/collection/IterableFactory$.MODULE$:Lscala/collection/IterableFactory$;
        34: pop
        35: getstatic     #491                // Field scala/collection/mutable/ArrayBuffer$.MODULE$:Lscala/collection/mutable/ArrayBuffer$;
        38: astore        4
        40: new           #17                 // class scala/collection/IterableFactory$$anon$1
        43: dup
        44: aload         4
        46: invokespecial #494                // Method scala/collection/IterableFactory$$anon$1."<init>":(Lscala/collection/IterableFactory;)V
        49: aconst_null
        50: astore        4
        52: aload_3
        53: invokevirtual #496                // Method sequence:(Lscala/collection/IterableOnce;Lscala/collection/BuildFrom;Lscala/concurrent/ExecutionContext;)Lscala/concurrent/Future;
        56: aload_2
        57: invokedynamic #526,  0            // InvokeDynamic #13:apply:(Lscala/Function2;)Lscala/Function1;
        62: aload_3
        63: invokeinterface #321,  3          // InterfaceMethod scala/concurrent/Future.map:(Lscala/Function1;Lscala/concurrent/ExecutionContext;)Lscala/concurrent/Future;
        68: areturn
      StackMapTable: number_of_entries = 1
        frame_type = 29 /* same */
      LineNumberTable:
        line 822: 0
        line 823: 29
      LocalVariableTable:
        Start  Length  Slot  Name   Signature
            0      69     0  this   Lscala/concurrent/Future$;
            0      69     1 futures   Lscala/collection/IterableOnce;
            0      69     2    op   Lscala/Function2;
            0      69     3 executor   Lscala/concurrent/ExecutionContext;
           40       9     4 toBuildFrom_factory   Lscala/collection/IterableFactory;
    Signature: #511                         // <T:Ljava/lang/Object;R:Ljava/lang/Object;>(Lscala/collection/IterableOnce<Lscala/concurrent/Future<TT;>;>;Lscala/Function2<TR;TT;TR;>;Lscala/concurrent/ExecutionContext;)Lscala/concurrent/Future<TR;>;
    Deprecated: true
    MethodParameters:
      Name                           Flags
      futures                        final
      op                             final
      executor                       final

  public final <T extends java.lang.Object, R extends java.lang.Object> scala.concurrent.Future<R> reduceLeft(scala.collection.immutable.Iterable<scala.concurrent.Future<T>>, scala.Function2<R, T, R>, scala.concurrent.ExecutionContext);
    descriptor: (Lscala/collection/immutable/Iterable;Lscala/Function2;Lscala/concurrent/ExecutionContext;)Lscala/concurrent/Future;
    flags: (0x0011) ACC_PUBLIC, ACC_FINAL
    Code:
      stack=4, locals=5, args_size=4
         0: aload_1
         1: invokeinterface #427,  1          // InterfaceMethod scala/collection/immutable/Iterable.iterator:()Lscala/collection/Iterator;
         6: astore        4
         8: aload         4
        10: invokeinterface #395,  1          // InterfaceMethod scala/collection/Iterator.hasNext:()Z
        15: ifne          33
        18: aload_0
        19: new           #513                // class java/util/NoSuchElementException
        22: dup
        23: ldc_w         #531                // String reduceLeft attempted on empty collection
        26: invokespecial #518                // Method java/util/NoSuchElementException."<init>":(Ljava/lang/String;)V
        29: invokevirtual #203                // Method failed:(Ljava/lang/Throwable;)Lscala/concurrent/Future;
        32: areturn
        33: aload         4
        35: invokeinterface #411,  1          // InterfaceMethod scala/collection/Iterator.next:()Ljava/lang/Object;
        40: checkcast     #36                 // class scala/concurrent/Future
        43: aload         4
        45: aload_2
        46: aload_3
        47: invokedynamic #539,  0            // InvokeDynamic #14:apply:(Lscala/collection/Iterator;Lscala/Function2;Lscala/concurrent/ExecutionContext;)Lscala/Function1;
        52: aload_3
        53: invokeinterface #336,  3          // InterfaceMethod scala/concurrent/Future.flatMap:(Lscala/Function1;Lscala/concurrent/ExecutionContext;)Lscala/concurrent/Future;
        58: areturn
      StackMapTable: number_of_entries = 1
        frame_type = 252 /* append */
          offset_delta = 33
          locals = [ class scala/collection/Iterator ]
      LineNumberTable:
        line 839: 0
        line 840: 8
        line 841: 33
      LocalVariableTable:
        Start  Length  Slot  Name   Signature
            8      50     4     i   Lscala/collection/Iterator;
            0      59     0  this   Lscala/concurrent/Future$;
            0      59     1 futures   Lscala/collection/immutable/Iterable;
            0      59     2    op   Lscala/Function2;
            0      59     3 executor   Lscala/concurrent/ExecutionContext;
    Signature: #529                         // <T:Ljava/lang/Object;R:Ljava/lang/Object;>(Lscala/collection/immutable/Iterable<Lscala/concurrent/Future<TT;>;>;Lscala/Function2<TR;TT;TR;>;Lscala/concurrent/ExecutionContext;)Lscala/concurrent/Future<TR;>;
    MethodParameters:
      Name                           Flags
      futures                        final
      op                             final
      executor                       final

  public final <A extends java.lang.Object, B extends java.lang.Object, M extends scala.collection.IterableOnce<java.lang.Object>> scala.concurrent.Future<M> traverse(M, scala.Function1<A, scala.concurrent.Future<B>>, scala.collection.BuildFrom<M, B, M>, scala.concurrent.ExecutionContext);
    descriptor: (Lscala/collection/IterableOnce;Lscala/Function1;Lscala/collection/BuildFrom;Lscala/concurrent/ExecutionContext;)Lscala/concurrent/Future;
    flags: (0x0011) ACC_PUBLIC, ACC_FINAL
    Code:
      stack=4, locals=5, args_size=5
         0: aload_1
         1: invokeinterface #347,  1          // InterfaceMethod scala/collection/IterableOnce.iterator:()Lscala/collection/Iterator;
         6: aload_0
         7: aload_3
         8: aload_1
         9: invokeinterface #353,  2          // InterfaceMethod scala/collection/BuildFrom.newBuilder:(Ljava/lang/Object;)Lscala/collection/mutable/Builder;
        14: invokevirtual #355                // Method successful:(Ljava/lang/Object;)Lscala/concurrent/Future;
        17: aload_2
        18: aload         4
        20: invokedynamic #553,  0            // InvokeDynamic #15:apply:(Lscala/Function1;Lscala/concurrent/ExecutionContext;)Lscala/Function2;
        25: invokeinterface #371,  3          // InterfaceMethod scala/collection/Iterator.foldLeft:(Ljava/lang/Object;Lscala/Function2;)Ljava/lang/Object;
        30: checkcast     #36                 // class scala/concurrent/Future
        33: invokedynamic #560,  0            // InvokeDynamic #16:apply:()Lscala/Function1;
        38: aload         4
        40: instanceof    #380                // class scala/concurrent/BatchingExecutor
        43: ifeq          51
        46: aload         4
        48: goto          54
        51: getstatic     #383                // Field scala/concurrent/ExecutionContext$parasitic$.MODULE$:Lscala/concurrent/ExecutionContext$parasitic$;
        54: invokeinterface #321,  3          // InterfaceMethod scala/concurrent/Future.map:(Lscala/Function1;Lscala/concurrent/ExecutionContext;)Lscala/concurrent/Future;
        59: areturn
      StackMapTable: number_of_entries = 2
        frame_type = 255 /* full_frame */
          offset_delta = 51
          locals = [ class scala/concurrent/Future$, class scala/collection/IterableOnce, class scala/Function1, class scala/collection/BuildFrom, class scala/concurrent/ExecutionContext ]
          stack = [ class scala/concurrent/Future, class scala/Function1 ]
        frame_type = 255 /* full_frame */
          offset_delta = 2
          locals = [ class scala/concurrent/Future$, class scala/collection/IterableOnce, class scala/Function1, class scala/collection/BuildFrom, class scala/concurrent/ExecutionContext ]
          stack = [ class scala/concurrent/Future, class scala/Function1, class scala/concurrent/ExecutionContext ]
      LineNumberTable:
        line 860: 0
        line 861: 17
        line 862: 33
      LocalVariableTable:
        Start  Length  Slot  Name   Signature
            0      60     0  this   Lscala/concurrent/Future$;
            0      60     1    in   Lscala/collection/IterableOnce;
            0      60     2    fn   Lscala/Function1;
            0      60     3    bf   Lscala/collection/BuildFrom;
            0      60     4 executor   Lscala/concurrent/ExecutionContext;
    Signature: #542                         // <A:Ljava/lang/Object;B:Ljava/lang/Object;M::Lscala/collection/IterableOnce<Ljava/lang/Object;>;>(TM;Lscala/Function1<TA;Lscala/concurrent/Future<TB;>;>;Lscala/collection/BuildFrom<TM;TB;TM;>;Lscala/concurrent/ExecutionContext;)Lscala/concurrent/Future<TM;>;
    MethodParameters:
      Name                           Flags
      in                             final
      fn                             final
      bf                             final
      executor                       final

  public static final java.lang.Object $anonfun$_cachedId$1(java.lang.Object);
    descriptor: (Ljava/lang/Object;)Ljava/lang/Object;
    flags: (0x1019) ACC_PUBLIC, ACC_STATIC, ACC_FINAL, ACC_SYNTHETIC
    Code:
      stack=2, locals=1, args_size=1
         0: getstatic     #83                 // Field scala/Predef$.MODULE$:Lscala/Predef$;
         3: aload_0
         4: invokevirtual #564                // Method scala/Predef$.identity:(Ljava/lang/Object;)Ljava/lang/Object;
         7: areturn
      LineNumberTable:
        line 538: 0
      LocalVariableTable:
        Start  Length  Slot  Name   Signature
            0       8     0     x   Ljava/lang/Object;
    MethodParameters:
      Name                           Flags
      x                              final

  public static final scala.runtime.Nothing$ $anonfun$collectFailed$1(java.lang.Object);
    descriptor: (Ljava/lang/Object;)Lscala/runtime/Nothing$;
    flags: (0x1019) ACC_PUBLIC, ACC_STATIC, ACC_FINAL, ACC_SYNTHETIC
    Code:
      stack=3, locals=1, args_size=1
         0: new           #24                 // class scala/concurrent/Future$$anon$1
         3: dup
         4: aload_0
         5: invokespecial #566                // Method scala/concurrent/Future$$anon$1."<init>":(Ljava/lang/Object;)V
         8: athrow
      LineNumberTable:
        line 543: 0
      LocalVariableTable:
        Start  Length  Slot  Name   Signature
            0       9     0     t   Ljava/lang/Object;
    MethodParameters:
      Name                           Flags
      t                              final

  public static final scala.util.Try $anonfun$_failedFun$1(scala.util.Try);
    descriptor: (Lscala/util/Try;)Lscala/util/Try;
    flags: (0x1019) ACC_PUBLIC, ACC_STATIC, ACC_FINAL, ACC_SYNTHETIC
    Code:
      stack=3, locals=1, args_size=1
         0: aload_0
         1: instanceof    #174                // class scala/util/Failure
         4: ifeq          22
         7: new           #237                // class scala/util/Success
        10: dup
        11: aload_0
        12: checkcast     #174                // class scala/util/Failure
        15: invokevirtual #570                // Method scala/util/Failure.exception:()Ljava/lang/Throwable;
        18: invokespecial #244                // Method scala/util/Success."<init>":(Ljava/lang/Object;)V
        21: areturn
        22: getstatic     #183                // Field failedFailure:Lscala/util/Failure;
        25: areturn
      StackMapTable: number_of_entries = 1
        frame_type = 22 /* same */
      LineNumberTable:
        line 555: 0
      LocalVariableTable:
        Start  Length  Slot  Name   Signature
            0      26     0     v   Lscala/util/Try;
    MethodParameters:
      Name                           Flags
      v                              final

  public static final scala.concurrent.Future $anonfun$recoverWithFailed$1(java.lang.Throwable);
    descriptor: (Ljava/lang/Throwable;)Lscala/concurrent/Future;
    flags: (0x1019) ACC_PUBLIC, ACC_STATIC, ACC_FINAL, ACC_SYNTHETIC
    Code:
      stack=1, locals=1, args_size=1
         0: getstatic     #78                 // Field MODULE$:Lscala/concurrent/Future$;
         3: invokevirtual #572                // Method recoverWithFailedMarker:()Lscala/concurrent/Future;
         6: areturn
      LineNumberTable:
        line 562: 0
      LocalVariableTable:
        Start  Length  Slot  Name   Signature
            0       7     0     t   Ljava/lang/Throwable;
    MethodParameters:
      Name                           Flags
      t                              final

  public static final scala.Tuple2 $anonfun$_zipWithTuple2$1(java.lang.Object, java.lang.Object);
    descriptor: (Ljava/lang/Object;Ljava/lang/Object;)Lscala/Tuple2;
    flags: (0x1019) ACC_PUBLIC, ACC_STATIC, ACC_FINAL, ACC_SYNTHETIC
    Code:
      stack=4, locals=2, args_size=2
         0: new           #94                 // class scala/Tuple2
         3: dup
         4: aload_0
         5: aload_1
         6: invokespecial #106                // Method scala/Tuple2."<init>":(Ljava/lang/Object;Ljava/lang/Object;)V
         9: areturn
      LineNumberTable:
        line 564: 0
      LocalVariableTable:
        Start  Length  Slot  Name   Signature
            0      10     0    _1   Ljava/lang/Object;
            0      10     1    _2   Ljava/lang/Object;
    MethodParameters:
      Name                           Flags
      _1                             final
      _2                             final

  public static final scala.collection.mutable.Builder $anonfun$_addToBuilderFun$1(scala.collection.mutable.Builder, java.lang.Object);
    descriptor: (Lscala/collection/mutable/Builder;Ljava/lang/Object;)Lscala/collection/mutable/Builder;
    flags: (0x1019) ACC_PUBLIC, ACC_STATIC, ACC_FINAL, ACC_SYNTHETIC
    Code:
      stack=2, locals=2, args_size=2
         0: aload_0
         1: aload_1
         2: invokeinterface #582,  2          // InterfaceMethod scala/collection/mutable/Builder.$plus$eq:(Ljava/lang/Object;)Lscala/collection/mutable/Growable;
         7: checkcast     #578                // class scala/collection/mutable/Builder
        10: areturn
      LineNumberTable:
        line 567: 0
      LocalVariableTable:
        Start  Length  Slot  Name   Signature
            0      11     0     b   Lscala/collection/mutable/Builder;
            0      11     1     e   Ljava/lang/Object;
    MethodParameters:
      Name                           Flags
      b                              final
      e                              final

  public static final java.lang.Object $anonfun$apply$1(scala.Function0, scala.runtime.BoxedUnit);
    descriptor: (Lscala/Function0;Lscala/runtime/BoxedUnit;)Ljava/lang/Object;
    flags: (0x1019) ACC_PUBLIC, ACC_STATIC, ACC_FINAL, ACC_SYNTHETIC
    Code:
      stack=1, locals=2, args_size=2
         0: aload_0
         1: invokeinterface #589,  1          // InterfaceMethod scala/Function0.apply:()Ljava/lang/Object;
         6: areturn
      LineNumberTable:
        line 678: 0
      LocalVariableTable:
        Start  Length  Slot  Name   Signature
            0       7     0 body$1   Lscala/Function0;
            0       7     1   x$4   Lscala/runtime/BoxedUnit;
    MethodParameters:
      Name                           Flags
      body$1                         final
      x$4                            final

  public static final scala.concurrent.Future $anonfun$delegate$1(scala.Function0, scala.runtime.BoxedUnit);
    descriptor: (Lscala/Function0;Lscala/runtime/BoxedUnit;)Lscala/concurrent/Future;
    flags: (0x1019) ACC_PUBLIC, ACC_STATIC, ACC_FINAL, ACC_SYNTHETIC
    Code:
      stack=1, locals=2, args_size=2
         0: aload_0
         1: invokeinterface #589,  1          // InterfaceMethod scala/Function0.apply:()Ljava/lang/Object;
         6: checkcast     #36                 // class scala/concurrent/Future
         9: areturn
      LineNumberTable:
        line 698: 0
      LocalVariableTable:
        Start  Length  Slot  Name   Signature
            0      10     0 body$2   Lscala/Function0;
            0      10     1   x$5   Lscala/runtime/BoxedUnit;
    MethodParameters:
      Name                           Flags
      body$2                         final
      x$5                            final

  public static final scala.concurrent.Future $anonfun$sequence$1(scala.concurrent.ExecutionContext, scala.concurrent.Future, scala.concurrent.Future);
    descriptor: (Lscala/concurrent/ExecutionContext;Lscala/concurrent/Future;Lscala/concurrent/Future;)Lscala/concurrent/Future;
    flags: (0x1019) ACC_PUBLIC, ACC_STATIC, ACC_FINAL, ACC_SYNTHETIC
    Code:
      stack=4, locals=3, args_size=3
         0: aload_1
         1: aload_2
         2: getstatic     #78                 // Field MODULE$:Lscala/concurrent/Future$;
         5: invokevirtual #596                // Method addToBuilderFun:()Lscala/Function2;
         8: aload_0
         9: invokeinterface #600,  4          // InterfaceMethod scala/concurrent/Future.zipWith:(Lscala/concurrent/Future;Lscala/Function2;Lscala/concurrent/ExecutionContext;)Lscala/concurrent/Future;
        14: areturn
      LineNumberTable:
        line 711: 0
      LocalVariableTable:
        Start  Length  Slot  Name   Signature
            0      15     0 executor$3   Lscala/concurrent/ExecutionContext;
            0      15     1    fr   Lscala/concurrent/Future;
            0      15     2    fa   Lscala/concurrent/Future;
    MethodParameters:
      Name                           Flags
      executor$3                     final
      fr                             final
      fa                             final

  public static final java.lang.Object $anonfun$sequence$2(scala.collection.mutable.Builder);
    descriptor: (Lscala/collection/mutable/Builder;)Ljava/lang/Object;
    flags: (0x1019) ACC_PUBLIC, ACC_STATIC, ACC_FINAL, ACC_SYNTHETIC
    Code:
      stack=1, locals=1, args_size=1
         0: aload_0
         1: invokeinterface #603,  1          // InterfaceMethod scala/collection/mutable/Builder.result:()Ljava/lang/Object;
         6: areturn
      LineNumberTable:
        line 712: 0
      LocalVariableTable:
        Start  Length  Slot  Name   Signature
            0       7     0   x$6   Lscala/collection/mutable/Builder;
    MethodParameters:
      Name                           Flags
      x$6                            final

  public static final scala.concurrent.Future $anonfun$find$1(scala.concurrent.Future$, scala.Function1, scala.collection.Iterator, scala.concurrent.ExecutionContext, scala.util.Try);
    descriptor: (Lscala/concurrent/Future$;Lscala/Function1;Lscala/collection/Iterator;Lscala/concurrent/ExecutionContext;Lscala/util/Try;)Lscala/concurrent/Future;
    flags: (0x1019) ACC_PUBLIC, ACC_STATIC, ACC_FINAL, ACC_SYNTHETIC
    Code:
      stack=5, locals=7, args_size=5
         0: aload         4
         2: instanceof    #237                // class scala/util/Success
         5: ifeq          52
         8: aload         4
        10: checkcast     #237                // class scala/util/Success
        13: invokevirtual #611                // Method scala/util/Success.value:()Ljava/lang/Object;
        16: astore        6
        18: aload_1
        19: aload         6
        21: invokeinterface #613,  2          // InterfaceMethod scala/Function1.apply:(Ljava/lang/Object;)Ljava/lang/Object;
        26: invokestatic  #619                // Method scala/runtime/BoxesRunTime.unboxToBoolean:(Ljava/lang/Object;)Z
        29: ifeq          52
        32: getstatic     #78                 // Field MODULE$:Lscala/concurrent/Future$;
        35: new           #621                // class scala/Some
        38: dup
        39: aload         6
        41: invokespecial #622                // Method scala/Some."<init>":(Ljava/lang/Object;)V
        44: invokevirtual #355                // Method successful:(Ljava/lang/Object;)Lscala/concurrent/Future;
        47: astore        5
        49: goto          97
        52: aload_2
        53: invokeinterface #395,  1          // InterfaceMethod scala/collection/Iterator.hasNext:()Z
        58: ifne          71
        61: aload_0
        62: getstatic     #432                // Field scala/None$.MODULE$:Lscala/None$;
        65: invokevirtual #355                // Method successful:(Ljava/lang/Object;)Lscala/concurrent/Future;
        68: goto          95
        71: aload_2
        72: invokeinterface #411,  1          // InterfaceMethod scala/collection/Iterator.next:()Ljava/lang/Object;
        77: checkcast     #36                 // class scala/concurrent/Future
        80: aload_0
        81: aload_1
        82: aload_2
        83: aload_3
        84: invokedynamic #441,  0            // InvokeDynamic #10:apply:(Lscala/concurrent/Future$;Lscala/Function1;Lscala/collection/Iterator;Lscala/concurrent/ExecutionContext;)Lscala/Function1;
        89: aload_3
        90: invokeinterface #444,  3          // InterfaceMethod scala/concurrent/Future.transformWith:(Lscala/Function1;Lscala/concurrent/ExecutionContext;)Lscala/concurrent/Future;
        95: astore        5
        97: aload         5
        99: areturn
      StackMapTable: number_of_entries = 4
        frame_type = 52 /* same */
        frame_type = 18 /* same */
        frame_type = 87 /* same_locals_1_stack_item */
          stack = [ class scala/concurrent/Future ]
        frame_type = 252 /* append */
          offset_delta = 1
          locals = [ class scala/concurrent/Future ]
      LineNumberTable:
        line 751: 0
        line 749: 52
        line 750: 71
        line 752: 95
        line 750: 97
      LocalVariableTable:
        Start  Length  Slot  Name   Signature
           18      34     6     r   Ljava/lang/Object;
            0     100     0 $this   Lscala/concurrent/Future$;
            0     100     1   p$3   Lscala/Function1;
            0     100     2   i$1   Lscala/collection/Iterator;
            0     100     3 executor$4   Lscala/concurrent/ExecutionContext;
            0     100     4  x0$1   Lscala/util/Try;
    MethodParameters:
      Name                           Flags
      $this                          final synthetic
      p$3                            final
      i$1                            final
      executor$4                     final
      x0$1                           final

  private final scala.concurrent.Future searchNext$1(scala.collection.Iterator, scala.Function1, scala.concurrent.ExecutionContext);
    descriptor: (Lscala/collection/Iterator;Lscala/Function1;Lscala/concurrent/ExecutionContext;)Lscala/concurrent/Future;
    flags: (0x0012) ACC_PRIVATE, ACC_FINAL
    Code:
      stack=5, locals=4, args_size=4
         0: aload_1
         1: invokeinterface #395,  1          // InterfaceMethod scala/collection/Iterator.hasNext:()Z
         6: ifne          17
         9: aload_0
        10: getstatic     #432                // Field scala/None$.MODULE$:Lscala/None$;
        13: invokevirtual #355                // Method successful:(Ljava/lang/Object;)Lscala/concurrent/Future;
        16: areturn
        17: aload_1
        18: invokeinterface #411,  1          // InterfaceMethod scala/collection/Iterator.next:()Ljava/lang/Object;
        23: checkcast     #36                 // class scala/concurrent/Future
        26: aload_0
        27: aload_2
        28: aload_1
        29: aload_3
        30: invokedynamic #441,  0            // InvokeDynamic #10:apply:(Lscala/concurrent/Future$;Lscala/Function1;Lscala/collection/Iterator;Lscala/concurrent/ExecutionContext;)Lscala/Function1;
        35: aload_3
        36: invokeinterface #444,  3          // InterfaceMethod scala/concurrent/Future.transformWith:(Lscala/Function1;Lscala/concurrent/ExecutionContext;)Lscala/concurrent/Future;
        41: areturn
      StackMapTable: number_of_entries = 1
        frame_type = 17 /* same */
      LineNumberTable:
        line 749: 0
        line 750: 17
      LocalVariableTable:
        Start  Length  Slot  Name   Signature
            0      42     0  this   Lscala/concurrent/Future$;
            0      42     1     i   Lscala/collection/Iterator;
            0      42     2   p$3   Lscala/Function1;
            0      42     3 executor$4   Lscala/concurrent/ExecutionContext;
    MethodParameters:
      Name                           Flags
      i                              final
      p$3                            final
      executor$4                     final

  public static final scala.concurrent.Future $anonfun$foldNext$1(scala.collection.Iterator, scala.Function2, java.lang.Object, scala.concurrent.ExecutionContext, java.lang.Object);
    descriptor: (Lscala/collection/Iterator;Lscala/Function2;Ljava/lang/Object;Lscala/concurrent/ExecutionContext;Ljava/lang/Object;)Lscala/concurrent/Future;
    flags: (0x1019) ACC_PUBLIC, ACC_STATIC, ACC_FINAL, ACC_SYNTHETIC
    Code:
      stack=5, locals=7, args_size=5
         0: getstatic     #78                 // Field MODULE$:Lscala/concurrent/Future$;
         3: aload_1
         4: aload_2
         5: aload         4
         7: invokeinterface #633,  3          // InterfaceMethod scala/Function2.apply:(Ljava/lang/Object;Ljava/lang/Object;)Ljava/lang/Object;
        12: astore        6
        14: astore        5
        16: aload_0
        17: invokeinterface #395,  1          // InterfaceMethod scala/collection/Iterator.hasNext:()Z
        22: ifne          33
        25: aload         5
        27: aload         6
        29: invokevirtual #355                // Method successful:(Ljava/lang/Object;)Lscala/concurrent/Future;
        32: areturn
        33: aload_0
        34: invokeinterface #411,  1          // InterfaceMethod scala/collection/Iterator.next:()Ljava/lang/Object;
        39: checkcast     #36                 // class scala/concurrent/Future
        42: aload_0
        43: aload_1
        44: aload         6
        46: aload_3
        47: invokedynamic #459,  0            // InvokeDynamic #11:apply:(Lscala/collection/Iterator;Lscala/Function2;Ljava/lang/Object;Lscala/concurrent/ExecutionContext;)Lscala/Function1;
        52: aload_3
        53: invokeinterface #336,  3          // InterfaceMethod scala/concurrent/Future.flatMap:(Lscala/Function1;Lscala/concurrent/ExecutionContext;)Lscala/concurrent/Future;
        58: areturn
      StackMapTable: number_of_entries = 1
        frame_type = 253 /* append */
          offset_delta = 33
          locals = [ class scala/concurrent/Future$, class java/lang/Object ]
      LineNumberTable:
        line 781: 0
        line 780: 16
        line 781: 33
        line 781: 58
      LocalVariableTable:
        Start  Length  Slot  Name   Signature
            0      59     0   i$2   Lscala/collection/Iterator;
            0      59     1  op$1   Lscala/Function2;
            0      59     2 prevValue$1   Ljava/lang/Object;
            0      59     3 executor$5   Lscala/concurrent/ExecutionContext;
            0      59     4 value   Ljava/lang/Object;
           16      42     5 foldNext_this   Lscala/concurrent/Future$;
           16      42     6 foldNext_prevValue   Ljava/lang/Object;
    MethodParameters:
      Name                           Flags
      i$2                            final
      op$1                           final
      prevValue$1                    final
      executor$5                     final
      value                          final

  public static final java.lang.Object $anonfun$fold$1(java.lang.Object, scala.Function2, scala.collection.mutable.ArrayBuffer);
    descriptor: (Ljava/lang/Object;Lscala/Function2;Lscala/collection/mutable/ArrayBuffer;)Ljava/lang/Object;
    flags: (0x1019) ACC_PUBLIC, ACC_STATIC, ACC_FINAL, ACC_SYNTHETIC
    Code:
      stack=3, locals=3, args_size=3
         0: aload_2
         1: aload_0
         2: aload_1
         3: invokevirtual #641                // Method scala/collection/mutable/ArrayBuffer.foldLeft:(Ljava/lang/Object;Lscala/Function2;)Ljava/lang/Object;
         6: areturn
      LineNumberTable:
        line 804: 0
      LocalVariableTable:
        Start  Length  Slot  Name   Signature
            0       7     0 zero$1   Ljava/lang/Object;
            0       7     1  op$2   Lscala/Function2;
            0       7     2   x$7   Lscala/collection/mutable/ArrayBuffer;
    MethodParameters:
      Name                           Flags
      zero$1                         final
      op$2                           final
      x$7                            final

  public static final java.lang.Object $anonfun$reduce$1(scala.Function2, scala.collection.mutable.ArrayBuffer);
    descriptor: (Lscala/Function2;Lscala/collection/mutable/ArrayBuffer;)Ljava/lang/Object;
    flags: (0x1019) ACC_PUBLIC, ACC_STATIC, ACC_FINAL, ACC_SYNTHETIC
    Code:
      stack=2, locals=2, args_size=2
         0: aload_1
         1: aload_0
         2: invokevirtual #647                // Method scala/collection/mutable/ArrayBuffer.reduceLeft:(Lscala/Function2;)Ljava/lang/Object;
         5: areturn
      LineNumberTable:
        line 823: 0
      LocalVariableTable:
        Start  Length  Slot  Name   Signature
            0       6     0  op$3   Lscala/Function2;
            0       6     1   x$8   Lscala/collection/mutable/ArrayBuffer;
    MethodParameters:
      Name                           Flags
      op$3                           final
      x$8                            final

  public static final scala.concurrent.Future $anonfun$reduceLeft$1(scala.collection.Iterator, scala.Function2, scala.concurrent.ExecutionContext, java.lang.Object);
    descriptor: (Lscala/collection/Iterator;Lscala/Function2;Lscala/concurrent/ExecutionContext;Ljava/lang/Object;)Lscala/concurrent/Future;
    flags: (0x1019) ACC_PUBLIC, ACC_STATIC, ACC_FINAL, ACC_SYNTHETIC
    Code:
      stack=5, locals=4, args_size=4
         0: getstatic     #78                 // Field MODULE$:Lscala/concurrent/Future$;
         3: aload_0
         4: aload_3
         5: aload_1
         6: aload_2
         7: invokespecial #652                // Method foldNext:(Lscala/collection/Iterator;Ljava/lang/Object;Lscala/Function2;Lscala/concurrent/ExecutionContext;)Lscala/concurrent/Future;
        10: areturn
      LineNumberTable:
        line 841: 0
      LocalVariableTable:
        Start  Length  Slot  Name   Signature
            0      11     0   i$3   Lscala/collection/Iterator;
            0      11     1  op$4   Lscala/Function2;
            0      11     2 executor$6   Lscala/concurrent/ExecutionContext;
            0      11     3     v   Ljava/lang/Object;
    MethodParameters:
      Name                           Flags
      i$3                            final
      op$4                           final
      executor$6                     final
      v                              final

  public static final scala.concurrent.Future $anonfun$traverse$1(scala.Function1, scala.concurrent.ExecutionContext, scala.concurrent.Future, java.lang.Object);
    descriptor: (Lscala/Function1;Lscala/concurrent/ExecutionContext;Lscala/concurrent/Future;Ljava/lang/Object;)Lscala/concurrent/Future;
    flags: (0x1019) ACC_PUBLIC, ACC_STATIC, ACC_FINAL, ACC_SYNTHETIC
    Code:
      stack=4, locals=4, args_size=4
         0: aload_2
         1: aload_0
         2: aload_3
         3: invokeinterface #613,  2          // InterfaceMethod scala/Function1.apply:(Ljava/lang/Object;)Ljava/lang/Object;
         8: checkcast     #36                 // class scala/concurrent/Future
        11: getstatic     #78                 // Field MODULE$:Lscala/concurrent/Future$;
        14: invokevirtual #596                // Method addToBuilderFun:()Lscala/Function2;
        17: aload_1
        18: invokeinterface #600,  4          // InterfaceMethod scala/concurrent/Future.zipWith:(Lscala/concurrent/Future;Lscala/Function2;Lscala/concurrent/ExecutionContext;)Lscala/concurrent/Future;
        23: areturn
      LineNumberTable:
        line 861: 0
      LocalVariableTable:
        Start  Length  Slot  Name   Signature
            0      24     0  fn$1   Lscala/Function1;
            0      24     1 executor$7   Lscala/concurrent/ExecutionContext;
            0      24     2    fr   Lscala/concurrent/Future;
            0      24     3     a   Ljava/lang/Object;
    MethodParameters:
      Name                           Flags
      fn$1                           final
      executor$7                     final
      fr                             final
      a                              final

  public static final scala.collection.IterableOnce $anonfun$traverse$2(scala.collection.mutable.Builder);
    descriptor: (Lscala/collection/mutable/Builder;)Lscala/collection/IterableOnce;
    flags: (0x1019) ACC_PUBLIC, ACC_STATIC, ACC_FINAL, ACC_SYNTHETIC
    Code:
      stack=1, locals=1, args_size=1
         0: aload_0
         1: invokeinterface #603,  1          // InterfaceMethod scala/collection/mutable/Builder.result:()Ljava/lang/Object;
         6: checkcast     #343                // class scala/collection/IterableOnce
         9: areturn
      LineNumberTable:
        line 862: 0
      LocalVariableTable:
        Start  Length  Slot  Name   Signature
            0      10     0   x$9   Lscala/collection/mutable/Builder;
    MethodParameters:
      Name                           Flags
      x$9                            final

  private scala.concurrent.Future$();
    descriptor: ()V
    flags: (0x0002) ACC_PRIVATE
    Code:
      stack=1, locals=1, args_size=1
         0: aload_0
         1: invokespecial #657                // Method java/lang/Object."<init>":()V
         4: return
      LineNumberTable:
        line 520: 0
      LocalVariableTable:
        Start  Length  Slot  Name   Signature
            0       5     0  this   Lscala/concurrent/Future$;

  private static java.lang.Object $deserializeLambda$(java.lang.invoke.SerializedLambda);
    descriptor: (Ljava/lang/invoke/SerializedLambda;)Ljava/lang/Object;
    flags: (0x100a) ACC_PRIVATE, ACC_STATIC, ACC_SYNTHETIC
    Code:
      stack=1, locals=1, args_size=1
         0: aload_0
         1: invokedynamic #669,  0            // InvokeDynamic #17:lambdaDeserialize:(Ljava/lang/invoke/SerializedLambda;)Ljava/lang/Object;
         6: areturn
}
InnerClasses:
  public static final #10= #7 of #9;      // Lookup=class java/lang/invoke/MethodHandles$Lookup of class java/lang/invoke/MethodHandles
  public static #15= #12 of #14;          // ArrowAssoc$=class scala/Predef$ArrowAssoc$ of class scala/Predef
  public final #17;                       // class scala/collection/IterableFactory$$anon$1
  public static #22= #19 of #21;          // parasitic$=class scala/concurrent/ExecutionContext$parasitic$ of class scala/concurrent/ExecutionContext
  public final #24;                       // class scala/concurrent/Future$$anon$1
  public final #26;                       // class scala/concurrent/Future$$anon$2
  public final #28;                       // class scala/concurrent/Future$$anon$3
  public final #30;                       // class scala/concurrent/Future$$anon$4
  public final #32;                       // class scala/concurrent/Future$$anon$5
  public static #37= #34 of #36;          // never$=class scala/concurrent/Future$never$ of class scala/concurrent/Future
  public static #42= #39 of #41;          // DefaultPromise=class scala/concurrent/impl/Promise$DefaultPromise of class scala/concurrent/impl/Promise
SourceFile: "Future.scala"
BootstrapMethods:
  0: #156 REF_invokeStatic java/lang/invoke/LambdaMetafactory.altMetafactory:(Ljava/lang/invoke/MethodHandles$Lookup;Ljava/lang/String;Ljava/lang/invoke/MethodType;[Ljava/lang/Object;)Ljava/lang/invoke/CallSite;
    Method arguments:
      #144 (Ljava/lang/Object;)Ljava/lang/Object;
      #148 REF_invokeStatic scala/concurrent/Future$.$anonfun$_cachedId$1:(Ljava/lang/Object;)Ljava/lang/Object;
      #144 (Ljava/lang/Object;)Ljava/lang/Object;
      #149 1
  1: #156 REF_invokeStatic java/lang/invoke/LambdaMetafactory.altMetafactory:(Ljava/lang/invoke/MethodHandles$Lookup;Ljava/lang/String;Ljava/lang/invoke/MethodType;[Ljava/lang/Object;)Ljava/lang/invoke/CallSite;
    Method arguments:
      #144 (Ljava/lang/Object;)Ljava/lang/Object;
      #167 REF_invokeStatic scala/concurrent/Future$.$anonfun$collectFailed$1:(Ljava/lang/Object;)Lscala/runtime/Nothing$;
      #168 (Ljava/lang/Object;)Lscala/runtime/Nothing$;
      #169 5
      #149 1
      #168 (Ljava/lang/Object;)Lscala/runtime/Nothing$;
  2: #156 REF_invokeStatic java/lang/invoke/LambdaMetafactory.altMetafactory:(Ljava/lang/invoke/MethodHandles$Lookup;Ljava/lang/String;Ljava/lang/invoke/MethodType;[Ljava/lang/Object;)Ljava/lang/invoke/CallSite;
    Method arguments:
      #144 (Ljava/lang/Object;)Ljava/lang/Object;
      #194 REF_invokeStatic scala/concurrent/Future$.$anonfun$_failedFun$1:(Lscala/util/Try;)Lscala/util/Try;
      #195 (Lscala/util/Try;)Lscala/util/Try;
      #169 5
      #149 1
      #195 (Lscala/util/Try;)Lscala/util/Try;
  3: #156 REF_invokeStatic java/lang/invoke/LambdaMetafactory.altMetafactory:(Ljava/lang/invoke/MethodHandles$Lookup;Ljava/lang/String;Ljava/lang/invoke/MethodType;[Ljava/lang/Object;)Ljava/lang/invoke/CallSite;
    Method arguments:
      #144 (Ljava/lang/Object;)Ljava/lang/Object;
      #209 REF_invokeStatic scala/concurrent/Future$.$anonfun$recoverWithFailed$1:(Ljava/lang/Throwable;)Lscala/concurrent/Future;
      #210 (Ljava/lang/Throwable;)Lscala/concurrent/Future;
      #169 5
      #149 1
      #210 (Ljava/lang/Throwable;)Lscala/concurrent/Future;
  4: #156 REF_invokeStatic java/lang/invoke/LambdaMetafactory.altMetafactory:(Ljava/lang/invoke/MethodHandles$Lookup;Ljava/lang/String;Ljava/lang/invoke/MethodType;[Ljava/lang/Object;)Ljava/lang/invoke/CallSite;
    Method arguments:
      #215 (Ljava/lang/Object;Ljava/lang/Object;)Ljava/lang/Object;
      #220 REF_invokeStatic scala/concurrent/Future$.$anonfun$_zipWithTuple2$1:(Ljava/lang/Object;Ljava/lang/Object;)Lscala/Tuple2;
      #221 (Ljava/lang/Object;Ljava/lang/Object;)Lscala/Tuple2;
      #169 5
      #149 1
      #221 (Ljava/lang/Object;Ljava/lang/Object;)Lscala/Tuple2;
  5: #156 REF_invokeStatic java/lang/invoke/LambdaMetafactory.altMetafactory:(Ljava/lang/invoke/MethodHandles$Lookup;Ljava/lang/String;Ljava/lang/invoke/MethodType;[Ljava/lang/Object;)Ljava/lang/invoke/CallSite;
    Method arguments:
      #215 (Ljava/lang/Object;Ljava/lang/Object;)Ljava/lang/Object;
      #231 REF_invokeStatic scala/concurrent/Future$.$anonfun$_addToBuilderFun$1:(Lscala/collection/mutable/Builder;Ljava/lang/Object;)Lscala/collection/mutable/Builder;
      #232 (Lscala/collection/mutable/Builder;Ljava/lang/Object;)Lscala/collection/mutable/Builder;
      #169 5
      #149 1
      #232 (Lscala/collection/mutable/Builder;Ljava/lang/Object;)Lscala/collection/mutable/Builder;
  6: #156 REF_invokeStatic java/lang/invoke/LambdaMetafactory.altMetafactory:(Ljava/lang/invoke/MethodHandles$Lookup;Ljava/lang/String;Ljava/lang/invoke/MethodType;[Ljava/lang/Object;)Ljava/lang/invoke/CallSite;
    Method arguments:
      #144 (Ljava/lang/Object;)Ljava/lang/Object;
      #312 REF_invokeStatic scala/concurrent/Future$.$anonfun$apply$1:(Lscala/Function0;Lscala/runtime/BoxedUnit;)Ljava/lang/Object;
      #314 (Lscala/runtime/BoxedUnit;)Ljava/lang/Object;
      #169 5
      #149 1
      #314 (Lscala/runtime/BoxedUnit;)Ljava/lang/Object;
  7: #156 REF_invokeStatic java/lang/invoke/LambdaMetafactory.altMetafactory:(Ljava/lang/invoke/MethodHandles$Lookup;Ljava/lang/String;Ljava/lang/invoke/MethodType;[Ljava/lang/Object;)Ljava/lang/invoke/CallSite;
    Method arguments:
      #144 (Ljava/lang/Object;)Ljava/lang/Object;
      #330 REF_invokeStatic scala/concurrent/Future$.$anonfun$delegate$1:(Lscala/Function0;Lscala/runtime/BoxedUnit;)Lscala/concurrent/Future;
      #332 (Lscala/runtime/BoxedUnit;)Lscala/concurrent/Future;
      #169 5
      #149 1
      #332 (Lscala/runtime/BoxedUnit;)Lscala/concurrent/Future;
  8: #156 REF_invokeStatic java/lang/invoke/LambdaMetafactory.altMetafactory:(Ljava/lang/invoke/MethodHandles$Lookup;Ljava/lang/String;Ljava/lang/invoke/MethodType;[Ljava/lang/Object;)Ljava/lang/invoke/CallSite;
    Method arguments:
      #215 (Ljava/lang/Object;Ljava/lang/Object;)Ljava/lang/Object;
      #360 REF_invokeStatic scala/concurrent/Future$.$anonfun$sequence$1:(Lscala/concurrent/ExecutionContext;Lscala/concurrent/Future;Lscala/concurrent/Future;)Lscala/concurrent/Future;
      #362 (Lscala/concurrent/Future;Lscala/concurrent/Future;)Lscala/concurrent/Future;
      #169 5
      #149 1
      #362 (Lscala/concurrent/Future;Lscala/concurrent/Future;)Lscala/concurrent/Future;
  9: #156 REF_invokeStatic java/lang/invoke/LambdaMetafactory.altMetafactory:(Ljava/lang/invoke/MethodHandles$Lookup;Ljava/lang/String;Ljava/lang/invoke/MethodType;[Ljava/lang/Object;)Ljava/lang/invoke/CallSite;
    Method arguments:
      #144 (Ljava/lang/Object;)Ljava/lang/Object;
      #376 REF_invokeStatic scala/concurrent/Future$.$anonfun$sequence$2:(Lscala/collection/mutable/Builder;)Ljava/lang/Object;
      #377 (Lscala/collection/mutable/Builder;)Ljava/lang/Object;
      #169 5
      #149 1
      #377 (Lscala/collection/mutable/Builder;)Ljava/lang/Object;
  10: #156 REF_invokeStatic java/lang/invoke/LambdaMetafactory.altMetafactory:(Ljava/lang/invoke/MethodHandles$Lookup;Ljava/lang/String;Ljava/lang/invoke/MethodType;[Ljava/lang/Object;)Ljava/lang/invoke/CallSite;
    Method arguments:
      #144 (Ljava/lang/Object;)Ljava/lang/Object;
      #437 REF_invokeStatic scala/concurrent/Future$.$anonfun$find$1:(Lscala/concurrent/Future$;Lscala/Function1;Lscala/collection/Iterator;Lscala/concurrent/ExecutionContext;Lscala/util/Try;)Lscala/concurrent/Future;
      #438 (Lscala/util/Try;)Lscala/concurrent/Future;
      #169 5
      #149 1
      #438 (Lscala/util/Try;)Lscala/concurrent/Future;
  11: #156 REF_invokeStatic java/lang/invoke/LambdaMetafactory.altMetafactory:(Ljava/lang/invoke/MethodHandles$Lookup;Ljava/lang/String;Ljava/lang/invoke/MethodType;[Ljava/lang/Object;)Ljava/lang/invoke/CallSite;
    Method arguments:
      #144 (Ljava/lang/Object;)Ljava/lang/Object;
      #455 REF_invokeStatic scala/concurrent/Future$.$anonfun$foldNext$1:(Lscala/collection/Iterator;Lscala/Function2;Ljava/lang/Object;Lscala/concurrent/ExecutionContext;Ljava/lang/Object;)Lscala/concurrent/Future;
      #456 (Ljava/lang/Object;)Lscala/concurrent/Future;
      #169 5
      #149 1
      #456 (Ljava/lang/Object;)Lscala/concurrent/Future;
  12: #156 REF_invokeStatic java/lang/invoke/LambdaMetafactory.altMetafactory:(Ljava/lang/invoke/MethodHandles$Lookup;Ljava/lang/String;Ljava/lang/invoke/MethodType;[Ljava/lang/Object;)Ljava/lang/invoke/CallSite;
    Method arguments:
      #144 (Ljava/lang/Object;)Ljava/lang/Object;
      #501 REF_invokeStatic scala/concurrent/Future$.$anonfun$fold$1:(Ljava/lang/Object;Lscala/Function2;Lscala/collection/mutable/ArrayBuffer;)Ljava/lang/Object;
      #503 (Lscala/collection/mutable/ArrayBuffer;)Ljava/lang/Object;
      #169 5
      #149 1
      #503 (Lscala/collection/mutable/ArrayBuffer;)Ljava/lang/Object;
  13: #156 REF_invokeStatic java/lang/invoke/LambdaMetafactory.altMetafactory:(Ljava/lang/invoke/MethodHandles$Lookup;Ljava/lang/String;Ljava/lang/invoke/MethodType;[Ljava/lang/Object;)Ljava/lang/invoke/CallSite;
    Method arguments:
      #144 (Ljava/lang/Object;)Ljava/lang/Object;
      #523 REF_invokeStatic scala/concurrent/Future$.$anonfun$reduce$1:(Lscala/Function2;Lscala/collection/mutable/ArrayBuffer;)Ljava/lang/Object;
      #503 (Lscala/collection/mutable/ArrayBuffer;)Ljava/lang/Object;
      #169 5
      #149 1
      #503 (Lscala/collection/mutable/ArrayBuffer;)Ljava/lang/Object;
  14: #156 REF_invokeStatic java/lang/invoke/LambdaMetafactory.altMetafactory:(Ljava/lang/invoke/MethodHandles$Lookup;Ljava/lang/String;Ljava/lang/invoke/MethodType;[Ljava/lang/Object;)Ljava/lang/invoke/CallSite;
    Method arguments:
      #144 (Ljava/lang/Object;)Ljava/lang/Object;
      #536 REF_invokeStatic scala/concurrent/Future$.$anonfun$reduceLeft$1:(Lscala/collection/Iterator;Lscala/Function2;Lscala/concurrent/ExecutionContext;Ljava/lang/Object;)Lscala/concurrent/Future;
      #456 (Ljava/lang/Object;)Lscala/concurrent/Future;
      #169 5
      #149 1
      #456 (Ljava/lang/Object;)Lscala/concurrent/Future;
  15: #156 REF_invokeStatic java/lang/invoke/LambdaMetafactory.altMetafactory:(Ljava/lang/invoke/MethodHandles$Lookup;Ljava/lang/String;Ljava/lang/invoke/MethodType;[Ljava/lang/Object;)Ljava/lang/invoke/CallSite;
    Method arguments:
      #215 (Ljava/lang/Object;Ljava/lang/Object;)Ljava/lang/Object;
      #548 REF_invokeStatic scala/concurrent/Future$.$anonfun$traverse$1:(Lscala/Function1;Lscala/concurrent/ExecutionContext;Lscala/concurrent/Future;Ljava/lang/Object;)Lscala/concurrent/Future;
      #550 (Lscala/concurrent/Future;Ljava/lang/Object;)Lscala/concurrent/Future;
      #169 5
      #149 1
      #550 (Lscala/concurrent/Future;Ljava/lang/Object;)Lscala/concurrent/Future;
  16: #156 REF_invokeStatic java/lang/invoke/LambdaMetafactory.altMetafactory:(Ljava/lang/invoke/MethodHandles$Lookup;Ljava/lang/String;Ljava/lang/invoke/MethodType;[Ljava/lang/Object;)Ljava/lang/invoke/CallSite;
    Method arguments:
      #144 (Ljava/lang/Object;)Ljava/lang/Object;
      #558 REF_invokeStatic scala/concurrent/Future$.$anonfun$traverse$2:(Lscala/collection/mutable/Builder;)Lscala/collection/IterableOnce;
      #559 (Lscala/collection/mutable/Builder;)Lscala/collection/IterableOnce;
      #169 5
      #149 1
      #559 (Lscala/collection/mutable/Builder;)Lscala/collection/IterableOnce;
  17: #666 REF_invokeStatic scala/runtime/LambdaDeserialize.bootstrap:(Ljava/lang/invoke/MethodHandles$Lookup;Ljava/lang/String;Ljava/lang/invoke/MethodType;[Ljava/lang/invoke/MethodHandle;)Ljava/lang/invoke/CallSite;
    Method arguments:
      #231 REF_invokeStatic scala/concurrent/Future$.$anonfun$_addToBuilderFun$1:(Lscala/collection/mutable/Builder;Ljava/lang/Object;)Lscala/collection/mutable/Builder;
      #148 REF_invokeStatic scala/concurrent/Future$.$anonfun$_cachedId$1:(Ljava/lang/Object;)Ljava/lang/Object;
      #194 REF_invokeStatic scala/concurrent/Future$.$anonfun$_failedFun$1:(Lscala/util/Try;)Lscala/util/Try;
      #220 REF_invokeStatic scala/concurrent/Future$.$anonfun$_zipWithTuple2$1:(Ljava/lang/Object;Ljava/lang/Object;)Lscala/Tuple2;
      #312 REF_invokeStatic scala/concurrent/Future$.$anonfun$apply$1:(Lscala/Function0;Lscala/runtime/BoxedUnit;)Ljava/lang/Object;
      #167 REF_invokeStatic scala/concurrent/Future$.$anonfun$collectFailed$1:(Ljava/lang/Object;)Lscala/runtime/Nothing$;
      #330 REF_invokeStatic scala/concurrent/Future$.$anonfun$delegate$1:(Lscala/Function0;Lscala/runtime/BoxedUnit;)Lscala/concurrent/Future;
      #437 REF_invokeStatic scala/concurrent/Future$.$anonfun$find$1:(Lscala/concurrent/Future$;Lscala/Function1;Lscala/collection/Iterator;Lscala/concurrent/ExecutionContext;Lscala/util/Try;)Lscala/concurrent/Future;
      #501 REF_invokeStatic scala/concurrent/Future$.$anonfun$fold$1:(Ljava/lang/Object;Lscala/Function2;Lscala/collection/mutable/ArrayBuffer;)Ljava/lang/Object;
      #455 REF_invokeStatic scala/concurrent/Future$.$anonfun$foldNext$1:(Lscala/collection/Iterator;Lscala/Function2;Ljava/lang/Object;Lscala/concurrent/ExecutionContext;Ljava/lang/Object;)Lscala/concurrent/Future;
      #209 REF_invokeStatic scala/concurrent/Future$.$anonfun$recoverWithFailed$1:(Ljava/lang/Throwable;)Lscala/concurrent/Future;
      #523 REF_invokeStatic scala/concurrent/Future$.$anonfun$reduce$1:(Lscala/Function2;Lscala/collection/mutable/ArrayBuffer;)Ljava/lang/Object;
      #536 REF_invokeStatic scala/concurrent/Future$.$anonfun$reduceLeft$1:(Lscala/collection/Iterator;Lscala/Function2;Lscala/concurrent/ExecutionContext;Ljava/lang/Object;)Lscala/concurrent/Future;
      #360 REF_invokeStatic scala/concurrent/Future$.$anonfun$sequence$1:(Lscala/concurrent/ExecutionContext;Lscala/concurrent/Future;Lscala/concurrent/Future;)Lscala/concurrent/Future;
      #376 REF_invokeStatic scala/concurrent/Future$.$anonfun$sequence$2:(Lscala/collection/mutable/Builder;)Ljava/lang/Object;
      #548 REF_invokeStatic scala/concurrent/Future$.$anonfun$traverse$1:(Lscala/Function1;Lscala/concurrent/ExecutionContext;Lscala/concurrent/Future;Ljava/lang/Object;)Lscala/concurrent/Future;
      #558 REF_invokeStatic scala/concurrent/Future$.$anonfun$traverse$2:(Lscala/collection/mutable/Builder;)Lscala/collection/IterableOnce;
  ScalaInlineInfo: length = 0xE0 (unknown attribute)
   01 01 00 2C 00 E3 00 E4 01 00 91 00 8F 01 00 BE
   00 BF 01 00 D8 00 D9 01 01 34 01 35 01 00 A3 00
   A4 01 01 46 01 47 01 01 B1 01 B2 01 01 F1 01 F2
   01 01 C3 01 C4 01 00 CE 00 C9 01 02 07 02 08 01
   02 14 02 15 01 01 64 01 65 01 01 74 01 75 01 02
   20 02 21 01 02 2A 02 2B 01 00 4A 00 49 01 01 0F
   00 DE 01 00 9D 01 2E 01 00 33 00 9E 01 01 44 01
   2E 01 00 C8 00 C9 01 00 39 01 08 01 01 0A 00 9E
   01 00 35 01 06 01 01 A6 01 A7 01 01 84 01 85 01
   01 D1 01 D2 01 01 70 01 BF 01 01 CD 01 CE 01 00
   B8 00 B9 01 01 03 00 9E 01 00 3F 00 9E 01 00 3E
   01 08 01 01 FD 01 FE 01 02 0F 02 10 01 02 70 02
   71 01 01 51 01 52 01 01 22 01 23 01 00 2D 01 00
   01 02 1C 02 1D 01 00 46 01 08 01 01 0D 00 DE 01

  Scala: length = 0x0 (unknown attribute)

