Classfile /Users/mw/Projects/slang-braindump/.jar/jar8/assemble/slang-braindump/assemble/content/scala/concurrent/Promise.class
  Last modified May 29, 2022; size 7431 bytes
  SHA-256 checksum 8007ce403e91079ec98df437dfad795e7e197faf4bd0a76b401e874c500c4ca4
  Compiled from "Promise.scala"
public interface scala.concurrent.Promise<T extends java.lang.Object>
  minor version: 0
  major version: 52
  flags: (0x0601) ACC_PUBLIC, ACC_INTERFACE, ACC_ABSTRACT
  this_class: #2                          // scala/concurrent/Promise
  super_class: #5                         // java/lang/Object
  interfaces: 0, fields: 0, methods: 25, attributes: 7
Constant pool:
    #1 = Utf8               scala/concurrent/Promise
    #2 = Class              #1            // scala/concurrent/Promise
    #3 = Utf8               <T:Ljava/lang/Object;>Ljava/lang/Object;
    #4 = Utf8               java/lang/Object
    #5 = Class              #4            // java/lang/Object
    #6 = Utf8               Promise.scala
    #7 = Utf8               Lscala/reflect/ScalaSignature;
    #8 = Utf8               bytes
    #9 = Utf8               \u0006\u0005\u0005-baB\n\u0015!\u0003\r\t!\u0007\u0005\u0006?\u0001!\t\u0001\t\u0005\u0006I\u00011\t!\n\u0005\u0006k\u00011\tA\u000e\u0005\u0006u\u0001!\ta\u000f\u0005\u0006\u000b\u00021\tA\u0012\u0005\u0006\u0011\u0002!\t!\u0013\u0005\u0006\u0019\u0002!)!\u0014\u0005\u00063\u0002!\tA\u0017\u0005\u0006;\u0002!\tA\u0018\u0005\u0006A\u0002!\t!\u0019\u0005\u0006a\u0002!\t!]\u0004\u0006gRA\t\u0001\u001e\u0004\u0006\'QA\t!\u001e\u0005\u0006m6!\ta\u001e\u0005\u0006q6!)!\u001f\u0005\u0006}6!)a \u0005\b\u0003\u001biAQAA\b\u0011\u001d\tY\"\u0004C\u0003\u0003;\u0011q\u0001\u0015:p[&\u001cXM\u0003\u0002\u0016-\u0005Q1m\u001c8dkJ\u0014XM\u001c;\u000b\u0003]\tQa]2bY\u0006\u001c\u0001!\u0006\u0002\u001bYM\u0011\u0001a\u0007\t\u00039ui\u0011AF\u0005\u0003=Y\u0011a!\u00118z%\u00164\u0017A\u0002\u0013j]&$H\u0005F\u0001\"!\ta\"%\u0003\u0002$-\t!QK\\5u\u0003\u00191W\u000f^;sKV\ta\u0005E\u0002(Q)j\u0011\u0001F\u0005\u0003SQ\u0011aAR;ukJ,\u0007CA\u0016-\u0019\u0001!Q!\f\u0001C\u00029\u0012\u0011\u0001V\t\u0003_I\u0002\"\u0001\b\u0019\n\u0005E2\"a\u0002(pi\"Lgn\u001a\t\u00039MJ!\u0001\u000e\f\u0003\u0007\u0005s\u00170A\u0006jg\u000e{W\u000e\u001d7fi\u0016$W#A\u001c\u0011\u0005qA\u0014BA\u001d\u0017\u0005\u001d\u0011un\u001c7fC:\f\u0001bY8na2,G/\u001a\u000b\u0003yuj\u0011\u0001\u0001\u0005\u0006}\u0011\u0001\raP\u0001\u0007e\u0016\u001cX\u000f\u001c;\u0011\u0007\u0001\u001b%&D\u0001B\u0015\t\u0011e#\u0001\u0003vi&d\u0017B\u0001#B\u0005\r!&/_\u0001\fiJL8i\\7qY\u0016$X\r\u0006\u00028\u000f\")a(\u0002a\u0001\u007f\u0005a1m\\7qY\u0016$XmV5uQR\u0011AH\u0013\u0005\u0006\u0017\u001a\u0001\rAJ\u0001\u0006_RDWM]\u0001\u0010iJL8i\\7qY\u0016$XmV5uQR\u0011AH\u0014\u0005\u0006\u0017\u001e\u0001\rA\n\u0015\u0007\u000fA\u001bFKV,\u0011\u0005q\t\u0016B\u0001*\u0017\u0005)!W\r\u001d:fG\u0006$X\rZ\u0001\b[\u0016\u001c8/Y4fC\u0005)\u0016!U*j]\u000e,\u0007\u0005\u001e5jg\u0002jW\r\u001e5pI\u0002J7\u000fI:f[\u0006tG/[2bY2L\b%Z9vSZ\fG.\u001a8uAQ|\u0007\u0005Y2p[BdW\r^3XSRD\u0007\r\f\u0011vg\u0016\u0004C\u000f[1uA%t7\u000f^3bI:\nQa]5oG\u0016\f\u0013\u0001W\u0001\u0007e9\n4G\f\u0019\u0002\u000fM,8mY3tgR\u0011Ah\u0017\u0005\u00069\"\u0001\rAK\u0001\u0006m\u0006dW/Z\u0001\u000biJL8+^2dKN\u001cHCA\u001c`\u0011\u0015a\u0016\u00021\u0001+\u0003\u001d1\u0017-\u001b7ve\u0016$\"\u0001\u00102\t\u000b\rT\u0001\u0019\u00013\u0002\u000b\r\fWo]3\u0011\u0005\u0015lgB\u00014l\u001d\t9\'.D\u0001i\u0015\tI\u0007$\u0001\u0004=e>|GOP\u0005\u0002/%\u0011ANF\u0001\ba\u0006\u001c7.Y4f\u0013\tqwNA\u0005UQJ|w/\u00192mK*\u0011ANF\u0001\u000biJLh)Y5mkJ,GCA\u001cs\u0011\u0015\u00197\u00021\u0001e\u0003\u001d\u0001&o\\7jg\u0016\u0004\"aJ\u0007\u0014\u00055Y\u0012A\u0002\u001fj]&$h\bF\u0001u\u0003\u0015\t\u0007\u000f\u001d7z+\tQX\u0010F\u0001|!\r9\u0003\u0001 \t\u0003Wu$Q!L\bC\u00029\naAZ1jY\u0016$W\u0003BA\u0001\u0003\u000f!B!a\u0001\u0002\nA!q\u0005AA\u0003!\rY\u0013q\u0001\u0003\u0006[A\u0011\rA\f\u0005\u0007\u0003\u0017\u0001\u0002\u0019\u00013\u0002\u0013\u0015D8-\u001a9uS>t\u0017AC:vG\u000e,7o\u001d4vYV!\u0011\u0011CA\f)\u0011\t\u0019\"!\u0007\u0011\t\u001d\u0002\u0011Q\u0003\t\u0004W\u0005]A!B\u0017\u0012\u0005\u0004q\u0003B\u0002 \u0012\u0001\u0004\t)\"A\u0004ge>lGK]=\u0016\t\u0005}\u0011Q\u0005\u000b\u0005\u0003C\t9\u0003\u0005\u0003(\u0001\u0005\r\u0002cA\u0016\u0002&\u0011)QF\u0005b\u0001]!1aH\u0005a\u0001\u0003S\u0001B\u0001Q\"\u0002$\u0001
   #10 = Utf8               java/lang/invoke/MethodHandles$Lookup
   #11 = Class              #10           // java/lang/invoke/MethodHandles$Lookup
   #12 = Utf8               java/lang/invoke/MethodHandles
   #13 = Class              #12           // java/lang/invoke/MethodHandles
   #14 = Utf8               Lookup
   #15 = Utf8               scala/concurrent/ExecutionContext$parasitic$
   #16 = Class              #15           // scala/concurrent/ExecutionContext$parasitic$
   #17 = Utf8               scala/concurrent/ExecutionContext
   #18 = Class              #17           // scala/concurrent/ExecutionContext
   #19 = Utf8               parasitic$
   #20 = Utf8               scala/concurrent/impl/Promise$DefaultPromise
   #21 = Class              #20           // scala/concurrent/impl/Promise$DefaultPromise
   #22 = Utf8               scala/concurrent/impl/Promise
   #23 = Class              #22           // scala/concurrent/impl/Promise
   #24 = Utf8               DefaultPromise
   #25 = Utf8               fromTry
   #26 = Utf8               (Lscala/util/Try;)Lscala/concurrent/Promise;
   #27 = Utf8               <T:Ljava/lang/Object;>(Lscala/util/Try<TT;>;)Lscala/concurrent/Promise<TT;>;
   #28 = Utf8               result
   #29 = Utf8               scala/concurrent/Promise$
   #30 = Class              #29           // scala/concurrent/Promise$
   #31 = Utf8               MODULE$
   #32 = Utf8               Lscala/concurrent/Promise$;
   #33 = NameAndType        #31:#32       // MODULE$:Lscala/concurrent/Promise$;
   #34 = Fieldref           #30.#33       // scala/concurrent/Promise$.MODULE$:Lscala/concurrent/Promise$;
   #35 = Utf8               <init>
   #36 = Utf8               (Lscala/util/Try;)V
   #37 = NameAndType        #35:#36       // "<init>":(Lscala/util/Try;)V
   #38 = Methodref          #21.#37       // scala/concurrent/impl/Promise$DefaultPromise."<init>":(Lscala/util/Try;)V
   #39 = Utf8               Lscala/util/Try;
   #40 = Utf8               successful
   #41 = Utf8               (Ljava/lang/Object;)Lscala/concurrent/Promise;
   #42 = Utf8               <T:Ljava/lang/Object;>(TT;)Lscala/concurrent/Promise<TT;>;
   #43 = NameAndType        #40:#41       // successful:(Ljava/lang/Object;)Lscala/concurrent/Promise;
   #44 = Methodref          #30.#43       // scala/concurrent/Promise$.successful:(Ljava/lang/Object;)Lscala/concurrent/Promise;
   #45 = Utf8               Ljava/lang/Object;
   #46 = Utf8               failed
   #47 = Utf8               (Ljava/lang/Throwable;)Lscala/concurrent/Promise;
   #48 = Utf8               <T:Ljava/lang/Object;>(Ljava/lang/Throwable;)Lscala/concurrent/Promise<TT;>;
   #49 = Utf8               exception
   #50 = NameAndType        #46:#47       // failed:(Ljava/lang/Throwable;)Lscala/concurrent/Promise;
   #51 = Methodref          #30.#50       // scala/concurrent/Promise$.failed:(Ljava/lang/Throwable;)Lscala/concurrent/Promise;
   #52 = Utf8               Ljava/lang/Throwable;
   #53 = Utf8               apply
   #54 = Utf8               ()Lscala/concurrent/Promise;
   #55 = Utf8               <T:Ljava/lang/Object;>()Lscala/concurrent/Promise<TT;>;
   #56 = Utf8               ()V
   #57 = NameAndType        #35:#56       // "<init>":()V
   #58 = Methodref          #21.#57       // scala/concurrent/impl/Promise$DefaultPromise."<init>":()V
   #59 = Utf8               future
   #60 = Utf8               ()Lscala/concurrent/Future;
   #61 = Utf8               ()Lscala/concurrent/Future<TT;>;
   #62 = Utf8               isCompleted
   #63 = Utf8               ()Z
   #64 = Utf8               complete$
   #65 = Utf8               (Lscala/concurrent/Promise;Lscala/util/Try;)Lscala/concurrent/Promise;
   #66 = Utf8               $this
   #67 = Utf8               complete
   #68 = NameAndType        #67:#26       // complete:(Lscala/util/Try;)Lscala/concurrent/Promise;
   #69 = InterfaceMethodref #2.#68        // scala/concurrent/Promise.complete:(Lscala/util/Try;)Lscala/concurrent/Promise;
   #70 = Utf8               Lscala/concurrent/Promise;
   #71 = Utf8               (Lscala/util/Try<TT;>;)Lscala/concurrent/Promise<TT;>;
   #72 = Utf8               tryComplete
   #73 = Utf8               (Lscala/util/Try;)Z
   #74 = NameAndType        #72:#73       // tryComplete:(Lscala/util/Try;)Z
   #75 = InterfaceMethodref #2.#74        // scala/concurrent/Promise.tryComplete:(Lscala/util/Try;)Z
   #76 = Utf8               java/lang/IllegalStateException
   #77 = Class              #76           // java/lang/IllegalStateException
   #78 = Utf8               Promise already completed.
   #79 = String             #78           // Promise already completed.
   #80 = Utf8               (Ljava/lang/String;)V
   #81 = NameAndType        #35:#80       // "<init>":(Ljava/lang/String;)V
   #82 = Methodref          #77.#81       // java/lang/IllegalStateException."<init>":(Ljava/lang/String;)V
   #83 = Utf8               this
   #84 = Utf8               (Lscala/util/Try<TT;>;)Z
   #85 = Utf8               completeWith$
   #86 = Utf8               (Lscala/concurrent/Promise;Lscala/concurrent/Future;)Lscala/concurrent/Promise;
   #87 = Utf8               other
   #88 = Utf8               completeWith
   #89 = Utf8               (Lscala/concurrent/Future;)Lscala/concurrent/Promise;
   #90 = NameAndType        #88:#89       // completeWith:(Lscala/concurrent/Future;)Lscala/concurrent/Promise;
   #91 = InterfaceMethodref #2.#90        // scala/concurrent/Promise.completeWith:(Lscala/concurrent/Future;)Lscala/concurrent/Promise;
   #92 = Utf8               Lscala/concurrent/Future;
   #93 = Utf8               (Lscala/concurrent/Future<TT;>;)Lscala/concurrent/Promise<TT;>;
   #94 = NameAndType        #59:#60       // future:()Lscala/concurrent/Future;
   #95 = InterfaceMethodref #2.#94        // scala/concurrent/Promise.future:()Lscala/concurrent/Future;
   #96 = Utf8               (Ljava/lang/Object;)Ljava/lang/Object;
   #97 = MethodType         #96           //  (Ljava/lang/Object;)Ljava/lang/Object;
   #98 = Utf8               $anonfun$completeWith$1$adapted
   #99 = Utf8               (Lscala/concurrent/Promise;Lscala/util/Try;)Ljava/lang/Object;
  #100 = NameAndType        #98:#99       // $anonfun$completeWith$1$adapted:(Lscala/concurrent/Promise;Lscala/util/Try;)Ljava/lang/Object;
  #101 = InterfaceMethodref #2.#100       // scala/concurrent/Promise.$anonfun$completeWith$1$adapted:(Lscala/concurrent/Promise;Lscala/util/Try;)Ljava/lang/Object;
  #102 = MethodHandle       6:#101        // REF_invokeStatic scala/concurrent/Promise.$anonfun$completeWith$1$adapted:(Lscala/concurrent/Promise;Lscala/util/Try;)Ljava/lang/Object;
  #103 = Utf8               (Lscala/util/Try;)Ljava/lang/Object;
  #104 = MethodType         #103          //  (Lscala/util/Try;)Ljava/lang/Object;
  #105 = Integer            5
  #106 = Integer            1
  #107 = Utf8               java/lang/invoke/LambdaMetafactory
  #108 = Class              #107          // java/lang/invoke/LambdaMetafactory
  #109 = Utf8               altMetafactory
  #110 = Utf8               (Ljava/lang/invoke/MethodHandles$Lookup;Ljava/lang/String;Ljava/lang/invoke/MethodType;[Ljava/lang/Object;)Ljava/lang/invoke/CallSite;
  #111 = NameAndType        #109:#110     // altMetafactory:(Ljava/lang/invoke/MethodHandles$Lookup;Ljava/lang/String;Ljava/lang/invoke/MethodType;[Ljava/lang/Object;)Ljava/lang/invoke/CallSite;
  #112 = Methodref          #108.#111     // java/lang/invoke/LambdaMetafactory.altMetafactory:(Ljava/lang/invoke/MethodHandles$Lookup;Ljava/lang/String;Ljava/lang/invoke/MethodType;[Ljava/lang/Object;)Ljava/lang/invoke/CallSite;
  #113 = MethodHandle       6:#112        // REF_invokeStatic java/lang/invoke/LambdaMetafactory.altMetafactory:(Ljava/lang/invoke/MethodHandles$Lookup;Ljava/lang/String;Ljava/lang/invoke/MethodType;[Ljava/lang/Object;)Ljava/lang/invoke/CallSite;
  #114 = Utf8               (Lscala/concurrent/Promise;)Lscala/Function1;
  #115 = NameAndType        #53:#114      // apply:(Lscala/concurrent/Promise;)Lscala/Function1;
  #116 = InvokeDynamic      #0:#115       // #0:apply:(Lscala/concurrent/Promise;)Lscala/Function1;
  #117 = Utf8               Lscala/concurrent/ExecutionContext$parasitic$;
  #118 = NameAndType        #31:#117      // MODULE$:Lscala/concurrent/ExecutionContext$parasitic$;
  #119 = Fieldref           #16.#118      // scala/concurrent/ExecutionContext$parasitic$.MODULE$:Lscala/concurrent/ExecutionContext$parasitic$;
  #120 = Utf8               scala/concurrent/Future
  #121 = Class              #120          // scala/concurrent/Future
  #122 = Utf8               onComplete
  #123 = Utf8               (Lscala/Function1;Lscala/concurrent/ExecutionContext;)V
  #124 = NameAndType        #122:#123     // onComplete:(Lscala/Function1;Lscala/concurrent/ExecutionContext;)V
  #125 = InterfaceMethodref #121.#124     // scala/concurrent/Future.onComplete:(Lscala/Function1;Lscala/concurrent/ExecutionContext;)V
  #126 = Utf8               tryCompleteWith$
  #127 = Utf8               tryCompleteWith
  #128 = NameAndType        #127:#89      // tryCompleteWith:(Lscala/concurrent/Future;)Lscala/concurrent/Promise;
  #129 = InterfaceMethodref #2.#128       // scala/concurrent/Promise.tryCompleteWith:(Lscala/concurrent/Future;)Lscala/concurrent/Promise;
  #130 = Utf8               success$
  #131 = Utf8               (Lscala/concurrent/Promise;Ljava/lang/Object;)Lscala/concurrent/Promise;
  #132 = Utf8               value
  #133 = Utf8               success
  #134 = NameAndType        #133:#41      // success:(Ljava/lang/Object;)Lscala/concurrent/Promise;
  #135 = InterfaceMethodref #2.#134       // scala/concurrent/Promise.success:(Ljava/lang/Object;)Lscala/concurrent/Promise;
  #136 = Utf8               (TT;)Lscala/concurrent/Promise<TT;>;
  #137 = Utf8               scala/util/Success
  #138 = Class              #137          // scala/util/Success
  #139 = Utf8               (Ljava/lang/Object;)V
  #140 = NameAndType        #35:#139      // "<init>":(Ljava/lang/Object;)V
  #141 = Methodref          #138.#140     // scala/util/Success."<init>":(Ljava/lang/Object;)V
  #142 = Utf8               trySuccess$
  #143 = Utf8               (Lscala/concurrent/Promise;Ljava/lang/Object;)Z
  #144 = Utf8               trySuccess
  #145 = Utf8               (Ljava/lang/Object;)Z
  #146 = NameAndType        #144:#145     // trySuccess:(Ljava/lang/Object;)Z
  #147 = InterfaceMethodref #2.#146       // scala/concurrent/Promise.trySuccess:(Ljava/lang/Object;)Z
  #148 = Utf8               (TT;)Z
  #149 = Utf8               failure$
  #150 = Utf8               (Lscala/concurrent/Promise;Ljava/lang/Throwable;)Lscala/concurrent/Promise;
  #151 = Utf8               cause
  #152 = Utf8               failure
  #153 = NameAndType        #152:#47      // failure:(Ljava/lang/Throwable;)Lscala/concurrent/Promise;
  #154 = InterfaceMethodref #2.#153       // scala/concurrent/Promise.failure:(Ljava/lang/Throwable;)Lscala/concurrent/Promise;
  #155 = Utf8               (Ljava/lang/Throwable;)Lscala/concurrent/Promise<TT;>;
  #156 = Utf8               scala/util/Failure
  #157 = Class              #156          // scala/util/Failure
  #158 = Utf8               (Ljava/lang/Throwable;)V
  #159 = NameAndType        #35:#158      // "<init>":(Ljava/lang/Throwable;)V
  #160 = Methodref          #157.#159     // scala/util/Failure."<init>":(Ljava/lang/Throwable;)V
  #161 = Utf8               tryFailure$
  #162 = Utf8               (Lscala/concurrent/Promise;Ljava/lang/Throwable;)Z
  #163 = Utf8               tryFailure
  #164 = Utf8               (Ljava/lang/Throwable;)Z
  #165 = NameAndType        #163:#164     // tryFailure:(Ljava/lang/Throwable;)Z
  #166 = InterfaceMethodref #2.#165       // scala/concurrent/Promise.tryFailure:(Ljava/lang/Throwable;)Z
  #167 = Utf8               $anonfun$completeWith$1
  #168 = Utf8               (Lscala/concurrent/Promise;Lscala/util/Try;)Z
  #169 = Utf8               x$1
  #170 = Utf8               $init$
  #171 = Utf8               (Lscala/concurrent/Promise;)V
  #172 = NameAndType        #167:#168     // $anonfun$completeWith$1:(Lscala/concurrent/Promise;Lscala/util/Try;)Z
  #173 = InterfaceMethodref #2.#172       // scala/concurrent/Promise.$anonfun$completeWith$1:(Lscala/concurrent/Promise;Lscala/util/Try;)Z
  #174 = Utf8               scala/runtime/BoxesRunTime
  #175 = Class              #174          // scala/runtime/BoxesRunTime
  #176 = Utf8               boxToBoolean
  #177 = Utf8               (Z)Ljava/lang/Boolean;
  #178 = NameAndType        #176:#177     // boxToBoolean:(Z)Ljava/lang/Boolean;
  #179 = Methodref          #175.#178     // scala/runtime/BoxesRunTime.boxToBoolean:(Z)Ljava/lang/Boolean;
  #180 = Utf8               $deserializeLambda$
  #181 = Utf8               (Ljava/lang/invoke/SerializedLambda;)Ljava/lang/Object;
  #182 = Utf8               scala/runtime/LambdaDeserialize
  #183 = Class              #182          // scala/runtime/LambdaDeserialize
  #184 = Utf8               bootstrap
  #185 = Utf8               (Ljava/lang/invoke/MethodHandles$Lookup;Ljava/lang/String;Ljava/lang/invoke/MethodType;[Ljava/lang/invoke/MethodHandle;)Ljava/lang/invoke/CallSite;
  #186 = NameAndType        #184:#185     // bootstrap:(Ljava/lang/invoke/MethodHandles$Lookup;Ljava/lang/String;Ljava/lang/invoke/MethodType;[Ljava/lang/invoke/MethodHandle;)Ljava/lang/invoke/CallSite;
  #187 = Methodref          #183.#186     // scala/runtime/LambdaDeserialize.bootstrap:(Ljava/lang/invoke/MethodHandles$Lookup;Ljava/lang/String;Ljava/lang/invoke/MethodType;[Ljava/lang/invoke/MethodHandle;)Ljava/lang/invoke/CallSite;
  #188 = MethodHandle       6:#187        // REF_invokeStatic scala/runtime/LambdaDeserialize.bootstrap:(Ljava/lang/invoke/MethodHandles$Lookup;Ljava/lang/String;Ljava/lang/invoke/MethodType;[Ljava/lang/invoke/MethodHandle;)Ljava/lang/invoke/CallSite;
  #189 = Utf8               lambdaDeserialize
  #190 = NameAndType        #189:#181     // lambdaDeserialize:(Ljava/lang/invoke/SerializedLambda;)Ljava/lang/Object;
  #191 = InvokeDynamic      #1:#190       // #1:lambdaDeserialize:(Ljava/lang/invoke/SerializedLambda;)Ljava/lang/Object;
  #192 = Utf8               Code
  #193 = Utf8               LineNumberTable
  #194 = Utf8               LocalVariableTable
  #195 = Utf8               Signature
  #196 = Utf8               MethodParameters
  #197 = Utf8               StackMapTable
  #198 = Utf8               Deprecated
  #199 = Utf8               InnerClasses
  #200 = Utf8               SourceFile
  #201 = Utf8               RuntimeVisibleAnnotations
  #202 = Utf8               BootstrapMethods
  #203 = Utf8               ScalaInlineInfo
  #204 = Utf8               ScalaSig
{
  public static <T extends java.lang.Object> scala.concurrent.Promise<T> fromTry(scala.util.Try<T>);
    descriptor: (Lscala/util/Try;)Lscala/concurrent/Promise;
    flags: (0x0009) ACC_PUBLIC, ACC_STATIC
    Code:
      stack=3, locals=1, args_size=1
         0: getstatic     #34                 // Field scala/concurrent/Promise$.MODULE$:Lscala/concurrent/Promise$;
         3: pop
         4: new           #21                 // class scala/concurrent/impl/Promise$DefaultPromise
         7: dup
         8: aload_0
         9: invokespecial #38                 // Method scala/concurrent/impl/Promise$DefaultPromise."<init>":(Lscala/util/Try;)V
        12: areturn
      LineNumberTable:
        line 147: 4
      LocalVariableTable:
        Start  Length  Slot  Name   Signature
            0      13     0 result   Lscala/util/Try;
    Signature: #27                          // <T:Ljava/lang/Object;>(Lscala/util/Try<TT;>;)Lscala/concurrent/Promise<TT;>;
    MethodParameters:
      Name                           Flags
      result                         final

  public static <T extends java.lang.Object> scala.concurrent.Promise<T> successful(T);
    descriptor: (Ljava/lang/Object;)Lscala/concurrent/Promise;
    flags: (0x0009) ACC_PUBLIC, ACC_STATIC
    Code:
      stack=2, locals=1, args_size=1
         0: getstatic     #34                 // Field scala/concurrent/Promise$.MODULE$:Lscala/concurrent/Promise$;
         3: aload_0
         4: invokevirtual #44                 // Method scala/concurrent/Promise$.successful:(Ljava/lang/Object;)Lscala/concurrent/Promise;
         7: areturn
      LocalVariableTable:
        Start  Length  Slot  Name   Signature
            0       8     0 result   Ljava/lang/Object;
    Signature: #42                          // <T:Ljava/lang/Object;>(TT;)Lscala/concurrent/Promise<TT;>;
    MethodParameters:
      Name                           Flags
      result                         final

  public static <T extends java.lang.Object> scala.concurrent.Promise<T> failed(java.lang.Throwable);
    descriptor: (Ljava/lang/Throwable;)Lscala/concurrent/Promise;
    flags: (0x0009) ACC_PUBLIC, ACC_STATIC
    Code:
      stack=2, locals=1, args_size=1
         0: getstatic     #34                 // Field scala/concurrent/Promise$.MODULE$:Lscala/concurrent/Promise$;
         3: aload_0
         4: invokevirtual #51                 // Method scala/concurrent/Promise$.failed:(Ljava/lang/Throwable;)Lscala/concurrent/Promise;
         7: areturn
      LocalVariableTable:
        Start  Length  Slot  Name   Signature
            0       8     0 exception   Ljava/lang/Throwable;
    Signature: #48                          // <T:Ljava/lang/Object;>(Ljava/lang/Throwable;)Lscala/concurrent/Promise<TT;>;
    MethodParameters:
      Name                           Flags
      exception                      final

  public static <T extends java.lang.Object> scala.concurrent.Promise<T> apply();
    descriptor: ()Lscala/concurrent/Promise;
    flags: (0x0009) ACC_PUBLIC, ACC_STATIC
    Code:
      stack=2, locals=0, args_size=0
         0: getstatic     #34                 // Field scala/concurrent/Promise$.MODULE$:Lscala/concurrent/Promise$;
         3: pop
         4: new           #21                 // class scala/concurrent/impl/Promise$DefaultPromise
         7: dup
         8: invokespecial #58                 // Method scala/concurrent/impl/Promise$DefaultPromise."<init>":()V
        11: areturn
      LineNumberTable:
        line 126: 4
    Signature: #55                          // <T:Ljava/lang/Object;>()Lscala/concurrent/Promise<TT;>;

  public abstract scala.concurrent.Future<T> future();
    descriptor: ()Lscala/concurrent/Future;
    flags: (0x0401) ACC_PUBLIC, ACC_ABSTRACT
    Signature: #61                          // ()Lscala/concurrent/Future<TT;>;

  public abstract boolean isCompleted();
    descriptor: ()Z
    flags: (0x0401) ACC_PUBLIC, ACC_ABSTRACT

  public static scala.concurrent.Promise complete$(scala.concurrent.Promise, scala.util.Try);
    descriptor: (Lscala/concurrent/Promise;Lscala/util/Try;)Lscala/concurrent/Promise;
    flags: (0x1009) ACC_PUBLIC, ACC_STATIC, ACC_SYNTHETIC
    Code:
      stack=2, locals=2, args_size=2
         0: aload_0
         1: aload_1
         2: invokespecial #69                 // InterfaceMethod complete:(Lscala/util/Try;)Lscala/concurrent/Promise;
         5: areturn
      LineNumberTable:
        line 56: 0
      LocalVariableTable:
        Start  Length  Slot  Name   Signature
            0       6     0 $this   Lscala/concurrent/Promise;
            0       6     1 result   Lscala/util/Try;
    MethodParameters:
      Name                           Flags
      $this                          final synthetic
      result                         final

  public default scala.concurrent.Promise<T> complete(scala.util.Try<T>);
    descriptor: (Lscala/util/Try;)Lscala/concurrent/Promise;
    flags: (0x0001) ACC_PUBLIC
    Code:
      stack=3, locals=2, args_size=2
         0: aload_0
         1: aload_1
         2: invokeinterface #75,  2           // InterfaceMethod tryComplete:(Lscala/util/Try;)Z
         7: ifeq          12
        10: aload_0
        11: areturn
        12: new           #77                 // class java/lang/IllegalStateException
        15: dup
        16: ldc           #79                 // String Promise already completed.
        18: invokespecial #82                 // Method java/lang/IllegalStateException."<init>":(Ljava/lang/String;)V
        21: athrow
      StackMapTable: number_of_entries = 1
        frame_type = 12 /* same */
      LineNumberTable:
        line 57: 0
      LocalVariableTable:
        Start  Length  Slot  Name   Signature
            0      22     0  this   Lscala/concurrent/Promise;
            0      22     1 result   Lscala/util/Try;
    Signature: #71                          // (Lscala/util/Try<TT;>;)Lscala/concurrent/Promise<TT;>;
    MethodParameters:
      Name                           Flags
      result                         final

  public abstract boolean tryComplete(scala.util.Try<T>);
    descriptor: (Lscala/util/Try;)Z
    flags: (0x0401) ACC_PUBLIC, ACC_ABSTRACT
    Signature: #84                          // (Lscala/util/Try<TT;>;)Z
    MethodParameters:
      Name                           Flags
      result                         final

  public static scala.concurrent.Promise completeWith$(scala.concurrent.Promise, scala.concurrent.Future);
    descriptor: (Lscala/concurrent/Promise;Lscala/concurrent/Future;)Lscala/concurrent/Promise;
    flags: (0x1009) ACC_PUBLIC, ACC_STATIC, ACC_SYNTHETIC
    Code:
      stack=2, locals=2, args_size=2
         0: aload_0
         1: aload_1
         2: invokespecial #91                 // InterfaceMethod completeWith:(Lscala/concurrent/Future;)Lscala/concurrent/Promise;
         5: areturn
      LineNumberTable:
        line 71: 0
      LocalVariableTable:
        Start  Length  Slot  Name   Signature
            0       6     0 $this   Lscala/concurrent/Promise;
            0       6     1 other   Lscala/concurrent/Future;
    MethodParameters:
      Name                           Flags
      $this                          final synthetic
      other                          final

  public default scala.concurrent.Promise<T> completeWith(scala.concurrent.Future<T>);
    descriptor: (Lscala/concurrent/Future;)Lscala/concurrent/Promise;
    flags: (0x0001) ACC_PUBLIC
    Code:
      stack=3, locals=2, args_size=2
         0: aload_1
         1: aload_0
         2: invokeinterface #95,  1           // InterfaceMethod future:()Lscala/concurrent/Future;
         7: if_acmpeq     25
        10: aload_1
        11: aload_0
        12: invokedynamic #116,  0            // InvokeDynamic #0:apply:(Lscala/concurrent/Promise;)Lscala/Function1;
        17: getstatic     #119                // Field scala/concurrent/ExecutionContext$parasitic$.MODULE$:Lscala/concurrent/ExecutionContext$parasitic$;
        20: invokeinterface #125,  3          // InterfaceMethod scala/concurrent/Future.onComplete:(Lscala/Function1;Lscala/concurrent/ExecutionContext;)V
        25: aload_0
        26: areturn
      StackMapTable: number_of_entries = 1
        frame_type = 25 /* same */
      LineNumberTable:
        line 72: 0
        line 73: 10
        line 75: 25
      LocalVariableTable:
        Start  Length  Slot  Name   Signature
            0      27     0  this   Lscala/concurrent/Promise;
            0      27     1 other   Lscala/concurrent/Future;
    Signature: #93                          // (Lscala/concurrent/Future<TT;>;)Lscala/concurrent/Promise<TT;>;
    MethodParameters:
      Name                           Flags
      other                          final

  public static scala.concurrent.Promise tryCompleteWith$(scala.concurrent.Promise, scala.concurrent.Future);
    descriptor: (Lscala/concurrent/Promise;Lscala/concurrent/Future;)Lscala/concurrent/Promise;
    flags: (0x1009) ACC_PUBLIC, ACC_STATIC, ACC_SYNTHETIC
    Code:
      stack=2, locals=2, args_size=2
         0: aload_0
         1: aload_1
         2: invokespecial #129                // InterfaceMethod tryCompleteWith:(Lscala/concurrent/Future;)Lscala/concurrent/Promise;
         5: areturn
      LineNumberTable:
        line 83: 0
      LocalVariableTable:
        Start  Length  Slot  Name   Signature
            0       6     0 $this   Lscala/concurrent/Promise;
            0       6     1 other   Lscala/concurrent/Future;
    MethodParameters:
      Name                           Flags
      $this                          final synthetic
      other                          final

  public default scala.concurrent.Promise<T> tryCompleteWith(scala.concurrent.Future<T>);
    descriptor: (Lscala/concurrent/Future;)Lscala/concurrent/Promise;
    flags: (0x0001) ACC_PUBLIC
    Code:
      stack=2, locals=2, args_size=2
         0: aload_0
         1: aload_1
         2: invokeinterface #91,  2           // InterfaceMethod completeWith:(Lscala/concurrent/Future;)Lscala/concurrent/Promise;
         7: areturn
      LineNumberTable:
        line 83: 0
      LocalVariableTable:
        Start  Length  Slot  Name   Signature
            0       8     0  this   Lscala/concurrent/Promise;
            0       8     1 other   Lscala/concurrent/Future;
    Signature: #93                          // (Lscala/concurrent/Future<TT;>;)Lscala/concurrent/Promise<TT;>;
    Deprecated: true
    MethodParameters:
      Name                           Flags
      other                          final

  public static scala.concurrent.Promise success$(scala.concurrent.Promise, java.lang.Object);
    descriptor: (Lscala/concurrent/Promise;Ljava/lang/Object;)Lscala/concurrent/Promise;
    flags: (0x1009) ACC_PUBLIC, ACC_STATIC, ACC_SYNTHETIC
    Code:
      stack=2, locals=2, args_size=2
         0: aload_0
         1: aload_1
         2: invokespecial #135                // InterfaceMethod success:(Ljava/lang/Object;)Lscala/concurrent/Promise;
         5: areturn
      LineNumberTable:
        line 91: 0
      LocalVariableTable:
        Start  Length  Slot  Name   Signature
            0       6     0 $this   Lscala/concurrent/Promise;
            0       6     1 value   Ljava/lang/Object;
    MethodParameters:
      Name                           Flags
      $this                          final synthetic
      value                          final

  public default scala.concurrent.Promise<T> success(T);
    descriptor: (Ljava/lang/Object;)Lscala/concurrent/Promise;
    flags: (0x0001) ACC_PUBLIC
    Code:
      stack=4, locals=2, args_size=2
         0: aload_0
         1: new           #138                // class scala/util/Success
         4: dup
         5: aload_1
         6: invokespecial #141                // Method scala/util/Success."<init>":(Ljava/lang/Object;)V
         9: invokeinterface #69,  2           // InterfaceMethod complete:(Lscala/util/Try;)Lscala/concurrent/Promise;
        14: areturn
      LineNumberTable:
        line 91: 0
      LocalVariableTable:
        Start  Length  Slot  Name   Signature
            0      15     0  this   Lscala/concurrent/Promise;
            0      15     1 value   Ljava/lang/Object;
    Signature: #136                         // (TT;)Lscala/concurrent/Promise<TT;>;
    MethodParameters:
      Name                           Flags
      value                          final

  public static boolean trySuccess$(scala.concurrent.Promise, java.lang.Object);
    descriptor: (Lscala/concurrent/Promise;Ljava/lang/Object;)Z
    flags: (0x1009) ACC_PUBLIC, ACC_STATIC, ACC_SYNTHETIC
    Code:
      stack=2, locals=2, args_size=2
         0: aload_0
         1: aload_1
         2: invokespecial #147                // InterfaceMethod trySuccess:(Ljava/lang/Object;)Z
         5: ireturn
      LineNumberTable:
        line 99: 0
      LocalVariableTable:
        Start  Length  Slot  Name   Signature
            0       6     0 $this   Lscala/concurrent/Promise;
            0       6     1 value   Ljava/lang/Object;
    MethodParameters:
      Name                           Flags
      $this                          final synthetic
      value                          final

  public default boolean trySuccess(T);
    descriptor: (Ljava/lang/Object;)Z
    flags: (0x0001) ACC_PUBLIC
    Code:
      stack=4, locals=2, args_size=2
         0: aload_0
         1: new           #138                // class scala/util/Success
         4: dup
         5: aload_1
         6: invokespecial #141                // Method scala/util/Success."<init>":(Ljava/lang/Object;)V
         9: invokeinterface #75,  2           // InterfaceMethod tryComplete:(Lscala/util/Try;)Z
        14: ireturn
      LineNumberTable:
        line 99: 0
      LocalVariableTable:
        Start  Length  Slot  Name   Signature
            0      15     0  this   Lscala/concurrent/Promise;
            0      15     1 value   Ljava/lang/Object;
    Signature: #148                         // (TT;)Z
    MethodParameters:
      Name                           Flags
      value                          final

  public static scala.concurrent.Promise failure$(scala.concurrent.Promise, java.lang.Throwable);
    descriptor: (Lscala/concurrent/Promise;Ljava/lang/Throwable;)Lscala/concurrent/Promise;
    flags: (0x1009) ACC_PUBLIC, ACC_STATIC, ACC_SYNTHETIC
    Code:
      stack=2, locals=2, args_size=2
         0: aload_0
         1: aload_1
         2: invokespecial #154                // InterfaceMethod failure:(Ljava/lang/Throwable;)Lscala/concurrent/Promise;
         5: areturn
      LineNumberTable:
        line 109: 0
      LocalVariableTable:
        Start  Length  Slot  Name   Signature
            0       6     0 $this   Lscala/concurrent/Promise;
            0       6     1 cause   Ljava/lang/Throwable;
    MethodParameters:
      Name                           Flags
      $this                          final synthetic
      cause                          final

  public default scala.concurrent.Promise<T> failure(java.lang.Throwable);
    descriptor: (Ljava/lang/Throwable;)Lscala/concurrent/Promise;
    flags: (0x0001) ACC_PUBLIC
    Code:
      stack=4, locals=2, args_size=2
         0: aload_0
         1: new           #157                // class scala/util/Failure
         4: dup
         5: aload_1
         6: invokespecial #160                // Method scala/util/Failure."<init>":(Ljava/lang/Throwable;)V
         9: invokeinterface #69,  2           // InterfaceMethod complete:(Lscala/util/Try;)Lscala/concurrent/Promise;
        14: areturn
      LineNumberTable:
        line 109: 0
      LocalVariableTable:
        Start  Length  Slot  Name   Signature
            0      15     0  this   Lscala/concurrent/Promise;
            0      15     1 cause   Ljava/lang/Throwable;
    Signature: #155                         // (Ljava/lang/Throwable;)Lscala/concurrent/Promise<TT;>;
    MethodParameters:
      Name                           Flags
      cause                          final

  public static boolean tryFailure$(scala.concurrent.Promise, java.lang.Throwable);
    descriptor: (Lscala/concurrent/Promise;Ljava/lang/Throwable;)Z
    flags: (0x1009) ACC_PUBLIC, ACC_STATIC, ACC_SYNTHETIC
    Code:
      stack=2, locals=2, args_size=2
         0: aload_0
         1: aload_1
         2: invokespecial #166                // InterfaceMethod tryFailure:(Ljava/lang/Throwable;)Z
         5: ireturn
      LineNumberTable:
        line 117: 0
      LocalVariableTable:
        Start  Length  Slot  Name   Signature
            0       6     0 $this   Lscala/concurrent/Promise;
            0       6     1 cause   Ljava/lang/Throwable;
    MethodParameters:
      Name                           Flags
      $this                          final synthetic
      cause                          final

  public default boolean tryFailure(java.lang.Throwable);
    descriptor: (Ljava/lang/Throwable;)Z
    flags: (0x0001) ACC_PUBLIC
    Code:
      stack=4, locals=2, args_size=2
         0: aload_0
         1: new           #157                // class scala/util/Failure
         4: dup
         5: aload_1
         6: invokespecial #160                // Method scala/util/Failure."<init>":(Ljava/lang/Throwable;)V
         9: invokeinterface #75,  2           // InterfaceMethod tryComplete:(Lscala/util/Try;)Z
        14: ireturn
      LineNumberTable:
        line 117: 0
      LocalVariableTable:
        Start  Length  Slot  Name   Signature
            0      15     0  this   Lscala/concurrent/Promise;
            0      15     1 cause   Ljava/lang/Throwable;
    MethodParameters:
      Name                           Flags
      cause                          final

  public static boolean $anonfun$completeWith$1(scala.concurrent.Promise, scala.util.Try);
    descriptor: (Lscala/concurrent/Promise;Lscala/util/Try;)Z
    flags: (0x1009) ACC_PUBLIC, ACC_STATIC, ACC_SYNTHETIC
    Code:
      stack=2, locals=2, args_size=2
         0: aload_0
         1: aload_1
         2: invokeinterface #75,  2           // InterfaceMethod tryComplete:(Lscala/util/Try;)Z
         7: ireturn
      LineNumberTable:
        line 73: 0
      LocalVariableTable:
        Start  Length  Slot  Name   Signature
            0       8     0 $this   Lscala/concurrent/Promise;
            0       8     1   x$1   Lscala/util/Try;
    MethodParameters:
      Name                           Flags
      $this                          final synthetic
      x$1                            final

  public static void $init$(scala.concurrent.Promise);
    descriptor: (Lscala/concurrent/Promise;)V
    flags: (0x0009) ACC_PUBLIC, ACC_STATIC
    Code:
      stack=0, locals=1, args_size=1
         0: return
      LineNumberTable:
        line 36: 0
      LocalVariableTable:
        Start  Length  Slot  Name   Signature
            0       1     0 $this   Lscala/concurrent/Promise;
    MethodParameters:
      Name                           Flags
      $this                          final synthetic

  public static java.lang.Object $anonfun$completeWith$1$adapted(scala.concurrent.Promise, scala.util.Try);
    descriptor: (Lscala/concurrent/Promise;Lscala/util/Try;)Ljava/lang/Object;
    flags: (0x1009) ACC_PUBLIC, ACC_STATIC, ACC_SYNTHETIC
    Code:
      stack=2, locals=2, args_size=2
         0: aload_0
         1: aload_1
         2: invokestatic  #173                // InterfaceMethod $anonfun$completeWith$1:(Lscala/concurrent/Promise;Lscala/util/Try;)Z
         5: invokestatic  #179                // Method scala/runtime/BoxesRunTime.boxToBoolean:(Z)Ljava/lang/Boolean;
         8: areturn
      LineNumberTable:
        line 73: 0
      LocalVariableTable:
        Start  Length  Slot  Name   Signature
            0       9     0 $this   Lscala/concurrent/Promise;
            0       9     1   x$1   Lscala/util/Try;
    MethodParameters:
      Name                           Flags
      $this                          final
      x$1                            final

  private static java.lang.Object $deserializeLambda$(java.lang.invoke.SerializedLambda);
    descriptor: (Ljava/lang/invoke/SerializedLambda;)Ljava/lang/Object;
    flags: (0x100a) ACC_PRIVATE, ACC_STATIC, ACC_SYNTHETIC
    Code:
      stack=1, locals=1, args_size=1
         0: aload_0
         1: invokedynamic #191,  0            // InvokeDynamic #1:lambdaDeserialize:(Ljava/lang/invoke/SerializedLambda;)Ljava/lang/Object;
         6: areturn
}
InnerClasses:
  public static final #14= #11 of #13;    // Lookup=class java/lang/invoke/MethodHandles$Lookup of class java/lang/invoke/MethodHandles
  public static #19= #16 of #18;          // parasitic$=class scala/concurrent/ExecutionContext$parasitic$ of class scala/concurrent/ExecutionContext
  public static #24= #21 of #23;          // DefaultPromise=class scala/concurrent/impl/Promise$DefaultPromise of class scala/concurrent/impl/Promise
Signature: #3                           // <T:Ljava/lang/Object;>Ljava/lang/Object;
SourceFile: "Promise.scala"
RuntimeVisibleAnnotations:
  0: #7(#8=s#9)
    scala.reflect.ScalaSignature(
      bytes="\u0006\u0005\u0005-baB\n\u0015!\u0003\r\t!\u0007\u0005\u0006?\u0001!\t\u0001\t\u0005\u0006I\u00011\t!\n\u0005\u0006k\u00011\tA\u000e\u0005\u0006u\u0001!\ta\u000f\u0005\u0006\u000b\u00021\tA\u0012\u0005\u0006\u0011\u0002!\t!\u0013\u0005\u0006\u0019\u0002!)!\u0014\u0005\u00063\u0002!\tA\u0017\u0005\u0006;\u0002!\tA\u0018\u0005\u0006A\u0002!\t!\u0019\u0005\u0006a\u0002!\t!]\u0004\u0006gRA\t\u0001\u001e\u0004\u0006\'QA\t!\u001e\u0005\u0006m6!\ta\u001e\u0005\u0006q6!)!\u001f\u0005\u0006}6!)a \u0005\b\u0003\u001biAQAA\b\u0011\u001d\tY\"\u0004C\u0003\u0003;\u0011q\u0001\u0015:p[&\u001cXM\u0003\u0002\u0016-\u0005Q1m\u001c8dkJ\u0014XM\u001c;\u000b\u0003]\tQa]2bY\u0006\u001c\u0001!\u0006\u0002\u001bYM\u0011\u0001a\u0007\t\u00039ui\u0011AF\u0005\u0003=Y\u0011a!\u00118z%\u00164\u0017A\u0002\u0013j]&$H\u0005F\u0001\"!\ta\"%\u0003\u0002$-\t!QK\\5u\u0003\u00191W\u000f^;sKV\ta\u0005E\u0002(Q)j\u0011\u0001F\u0005\u0003SQ\u0011aAR;ukJ,\u0007CA\u0016-\u0019\u0001!Q!\f\u0001C\u00029\u0012\u0011\u0001V\t\u0003_I\u0002\"\u0001\b\u0019\n\u0005E2\"a\u0002(pi\"Lgn\u001a\t\u00039MJ!\u0001\u000e\f\u0003\u0007\u0005s\u00170A\u0006jg\u000e{W\u000e\u001d7fi\u0016$W#A\u001c\u0011\u0005qA\u0014BA\u001d\u0017\u0005\u001d\u0011un\u001c7fC:\f\u0001bY8na2,G/\u001a\u000b\u0003yuj\u0011\u0001\u0001\u0005\u0006}\u0011\u0001\raP\u0001\u0007e\u0016\u001cX\u000f\u001c;\u0011\u0007\u0001\u001b%&D\u0001B\u0015\t\u0011e#\u0001\u0003vi&d\u0017B\u0001#B\u0005\r!&/_\u0001\fiJL8i\\7qY\u0016$X\r\u0006\u00028\u000f\")a(\u0002a\u0001\u007f\u0005a1m\\7qY\u0016$XmV5uQR\u0011AH\u0013\u0005\u0006\u0017\u001a\u0001\rAJ\u0001\u0006_RDWM]\u0001\u0010iJL8i\\7qY\u0016$XmV5uQR\u0011AH\u0014\u0005\u0006\u0017\u001e\u0001\rA\n\u0015\u0007\u000fA\u001bFKV,\u0011\u0005q\t\u0016B\u0001*\u0017\u0005)!W\r\u001d:fG\u0006$X\rZ\u0001\b[\u0016\u001c8/Y4fC\u0005)\u0016!U*j]\u000e,\u0007\u0005\u001e5jg\u0002jW\r\u001e5pI\u0002J7\u000fI:f[\u0006tG/[2bY2L\b%Z9vSZ\fG.\u001a8uAQ|\u0007\u0005Y2p[BdW\r^3XSRD\u0007\r\f\u0011vg\u0016\u0004C\u000f[1uA%t7\u000f^3bI:\nQa]5oG\u0016\f\u0013\u0001W\u0001\u0007e9\n4G\f\u0019\u0002\u000fM,8mY3tgR\u0011Ah\u0017\u0005\u00069\"\u0001\rAK\u0001\u0006m\u0006dW/Z\u0001\u000biJL8+^2dKN\u001cHCA\u001c`\u0011\u0015a\u0016\u00021\u0001+\u0003\u001d1\u0017-\u001b7ve\u0016$\"\u0001\u00102\t\u000b\rT\u0001\u0019\u00013\u0002\u000b\r\fWo]3\u0011\u0005\u0015lgB\u00014l\u001d\t9\'.D\u0001i\u0015\tI\u0007$\u0001\u0004=e>|GOP\u0005\u0002/%\u0011ANF\u0001\ba\u0006\u001c7.Y4f\u0013\tqwNA\u0005UQJ|w/\u00192mK*\u0011ANF\u0001\u000biJLh)Y5mkJ,GCA\u001cs\u0011\u0015\u00197\u00021\u0001e\u0003\u001d\u0001&o\\7jg\u0016\u0004\"aJ\u0007\u0014\u00055Y\u0012A\u0002\u001fj]&$h\bF\u0001u\u0003\u0015\t\u0007\u000f\u001d7z+\tQX\u0010F\u0001|!\r9\u0003\u0001 \t\u0003Wu$Q!L\bC\u00029\naAZ1jY\u0016$W\u0003BA\u0001\u0003\u000f!B!a\u0001\u0002\nA!q\u0005AA\u0003!\rY\u0013q\u0001\u0003\u0006[A\u0011\rA\f\u0005\u0007\u0003\u0017\u0001\u0002\u0019\u00013\u0002\u0013\u0015D8-\u001a9uS>t\u0017AC:vG\u000e,7o\u001d4vYV!\u0011\u0011CA\f)\u0011\t\u0019\"!\u0007\u0011\t\u001d\u0002\u0011Q\u0003\t\u0004W\u0005]A!B\u0017\u0012\u0005\u0004q\u0003B\u0002 \u0012\u0001\u0004\t)\"A\u0004ge>lGK]=\u0016\t\u0005}\u0011Q\u0005\u000b\u0005\u0003C\t9\u0003\u0005\u0003(\u0001\u0005\r\u0002cA\u0016\u0002&\u0011)QF\u0005b\u0001]!1aH\u0005a\u0001\u0003S\u0001B\u0001Q\"\u0002$\u0001"
    )
BootstrapMethods:
  0: #113 REF_invokeStatic java/lang/invoke/LambdaMetafactory.altMetafactory:(Ljava/lang/invoke/MethodHandles$Lookup;Ljava/lang/String;Ljava/lang/invoke/MethodType;[Ljava/lang/Object;)Ljava/lang/invoke/CallSite;
    Method arguments:
      #97 (Ljava/lang/Object;)Ljava/lang/Object;
      #102 REF_invokeStatic scala/concurrent/Promise.$anonfun$completeWith$1$adapted:(Lscala/concurrent/Promise;Lscala/util/Try;)Ljava/lang/Object;
      #104 (Lscala/util/Try;)Ljava/lang/Object;
      #105 5
      #106 1
      #104 (Lscala/util/Try;)Ljava/lang/Object;
  1: #188 REF_invokeStatic scala/runtime/LambdaDeserialize.bootstrap:(Ljava/lang/invoke/MethodHandles$Lookup;Ljava/lang/String;Ljava/lang/invoke/MethodType;[Ljava/lang/invoke/MethodHandle;)Ljava/lang/invoke/CallSite;
    Method arguments:
      #102 REF_invokeStatic scala/concurrent/Promise.$anonfun$completeWith$1$adapted:(Lscala/concurrent/Promise;Lscala/util/Try;)Ljava/lang/Object;
  ScalaInlineInfo: length = 0x68 (unknown attribute)
   01 00 00 14 00 A7 00 A8 01 00 62 00 63 01 00 AA
   00 AB 01 00 43 00 1A 00 00 40 00 41 01 00 58 00
   59 00 00 55 00 56 01 00 98 00 2F 00 00 95 00 96
   01 00 3B 00 3C 00 00 3E 00 3F 00 00 85 00 29 00
   00 82 00 83 01 00 48 00 49 00 00 7F 00 59 01 00
   7E 00 56 01 00 A3 00 A4 00 00 A1 00 A2 01 00 90
   00 91 00 00 8E 00 8F 01
  ScalaSig: length = 0x3 (unknown attribute)
   05 02 00
