Classfile /Users/mw/Projects/slang-braindump/.jar/jar8/assemble/slang-braindump/assemble/content/geny/Readable.class
  Last modified May 29, 2022; size 4926 bytes
  SHA-256 checksum 4d898c4b2124887bc4cced3785438258614f657c80c9b0ca3b1167e98a5fcd4d
  Compiled from "Writable.scala"
public interface geny.Readable extends geny.Writable
  minor version: 0
  major version: 52
  flags: (0x0601) ACC_PUBLIC, ACC_INTERFACE, ACC_ABSTRACT
  this_class: #2                          // geny/Readable
  super_class: #4                         // java/lang/Object
  interfaces: 1, fields: 0, methods: 11, attributes: 6
Constant pool:
    #1 = Utf8               geny/Readable
    #2 = Class              #1            // geny/Readable
    #3 = Utf8               java/lang/Object
    #4 = Class              #3            // java/lang/Object
    #5 = Utf8               geny/Writable
    #6 = Class              #5            // geny/Writable
    #7 = Utf8               Writable.scala
    #8 = Utf8               Lscala/reflect/ScalaSignature;
    #9 = Utf8               bytes
   #10 = Utf8               \u0006\u0005\u00055ea\u0002\u0012$!\u0003\r\tA\n\u0005\u0006c\u0001!\tA\r\u0005\u0006m\u00011\ta\u000e\u0005\u0006#\u0002!\tAU\u0004\u00061\u000eB\t!\u0017\u0004\u0006E\rB\tA\u0017\u0005\u00067\u0016!\t\u0001\u0018\u0004\u0005;\u0016\ta\f\u0003\u0005a\u000f\t\u0005\t\u0015!\u0003b\u0011\u0015Yv\u0001\"\u0001m\u0011\u00151t\u0001\"\u0001q\u0011\u00151x\u0001\"\u0011x\u0011\u001d\t\ta\u0002C!\u0003\u0007A\u0011\"!\u0004\u0006\u0003\u0003%\u0019!a\u0004\u0007\r\u0005MQ!AA\u000b\u0011)\t9B\u0004B\u0001B\u0003%\u0011\u0011\u0004\u0005\u00077:!\t!!\n\t\rYrA\u0011AA\u0016\u0011\u00151h\u0002\"\u0011x\u0011\u001d\t\tA\u0004C!\u0003\u0007A\u0011\"a\u000e\u0006\u0003\u0003%\u0019!!\u000f\u0007\r\u0005uR!AA \u0011)\t\t%\u0006B\u0001B\u0003%\u00111\t\u0005\u00077V!\t!a\u0014\t\rY*B\u0011AA+\u0011\u00151X\u0003\"\u0011x\u0011\u001d\t\t!\u0006C!\u0003\u0007A\u0011\"!\u0019\u0006\u0003\u0003%\u0019!a\u0019\u0007\r\u0005\u001dT!AA5\u0011%\tY\u0007\bB\u0001B\u0003%\u0011\n\u0003\u0004\\9\u0011\u0005\u0011Q\u000e\u0005\u0007mq!\t!a\u001d\t\rYdB\u0011IA@\u0011%\t9)BA\u0001\n\u0007\tII\u0001\u0005SK\u0006$\u0017M\u00197f\u0015\u0005!\u0013\u0001B4f]f\u001c\u0001aE\u0002\u0001O5\u0002\"\u0001K\u0016\u000e\u0003%R\u0011AK\u0001\u0006g\u000e\fG.Y\u0005\u0003Y%\u0012a!\u00118z%\u00164\u0007C\u0001\u00180\u001b\u0005\u0019\u0013B\u0001\u0019$\u0005!9&/\u001b;bE2,\u0017A\u0002\u0013j]&$H\u0005F\u00014!\tAC\'\u0003\u00026S\t!QK\\5u\u0003A\u0011X-\u00193CsR,7\u000f\u00165s_V<\u0007.\u0006\u00029wQ\u0011\u0011\b\u0012\t\u0003umb\u0001\u0001B\u0003=\u0005\t\u0007QHA\u0001U#\tq\u0014\t\u0005\u0002)\u007f%\u0011\u0001)\u000b\u0002\b\u001d>$\b.\u001b8h!\tA#)\u0003\u0002DS\t\u0019\u0011I\\=\t\u000b\u0015\u0013\u0001\u0019\u0001$\u0002\u0003\u0019\u0004B\u0001K$Js%\u0011\u0001*\u000b\u0002\n\rVt7\r^5p]F\u0002\"AS(\u000e\u0003-S!\u0001T\'\u0002\u0005%|\'\"\u0001(\u0002\t)\fg/Y\u0005\u0003!.\u00131\"\u00138qkR\u001cFO]3b[\u0006aqO]5uK\nKH/Z:U_R\u00111g\u0015\u0005\u0006)\u000e\u0001\r!V\u0001\u0004_V$\bC\u0001&W\u0013\t96J\u0001\u0007PkR\u0004X\u000f^*ue\u0016\fW.\u0001\u0005SK\u0006$\u0017M\u00197f!\tqSa\u0005\u0002\u0006O\u00051A(\u001b8jiz\"\u0012!\u0017\u0002\u000f\'R\u0014\u0018N\\4SK\u0006$\u0017M\u00197f\'\r9qe\u0018\t\u0003]\u0001\t\u0011a\u001d\t\u0003E&t!aY4\u0011\u0005\u0011LS\"A3\u000b\u0005\u0019,\u0013A\u0002\u001fs_>$h(\u0003\u0002iS\u00051\u0001K]3eK\u001aL!A[6\u0003\rM#(/\u001b8h\u0015\tA\u0017\u0006\u0006\u0002n_B\u0011anB\u0007\u0002\u000b!)\u0001-\u0003a\u0001CV\u0011\u0011o\u001d\u000b\u0003eR\u0004\"AO:\u0005\u000bqR!\u0019A\u001f\t\u000b\u0015S\u0001\u0019A;\u0011\t!:\u0015J]\u0001\u0010QR$\boQ8oi\u0016tG\u000fV=qKV\t\u0001\u0010E\u0002)snL!A_\u0015\u0003\tM{W.\u001a\t\u0003y~l\u0011! \u0006\u0003}6\u000bA\u0001\\1oO&\u0011!.`\u0001\u000eG>tG/\u001a8u\u0019\u0016tw\r\u001e5\u0016\u0005\u0005\u0015\u0001\u0003\u0002\u0015z\u0003\u000f\u00012\u0001KA\u0005\u0013\r\tY!\u000b\u0002\u0005\u0019>tw-\u0001\bTiJLgn\u001a*fC\u0012\f\'\r\\3\u0015\u00075\f\t\u0002C\u0003a\u001b\u0001\u0007\u0011MA\tCsR,\u0017I\u001d:bsJ+\u0017\rZ1cY\u0016\u001c2AD\u0014`\u0003\u0005\t\u0007#\u0002\u0015\u0002\u001c\u0005}\u0011bAA\u000fS\t)\u0011I\u001d:bsB\u0019\u0001&!\t\n\u0007\u0005\r\u0012F\u0001\u0003CsR,G\u0003BA\u0014\u0003S\u0001\"A\u001c\b\t\u000f\u0005]\u0001\u00031\u0001\u0002\u001aU!\u0011QFA\u0019)\u0011\ty#a\r\u0011\u0007i\n\t\u0004B\u0003=#\t\u0007Q\b\u0003\u0004F#\u0001\u0007\u0011Q\u0007\t\u0006Q\u001dK\u0015qF\u0001\u0012\u0005f$X-\u0011:sCf\u0014V-\u00193bE2,G\u0003BA\u0014\u0003wAq!a\u0006\u0015\u0001\u0004\tIB\u0001\nCsR,\')\u001e4gKJ\u0014V-\u00193bE2,7cA\u000b(?\u00061!-\u001e4gKJ\u0004B!!\u0012\u0002L5\u0011\u0011q\t\u0006\u0004\u0003\u0013j\u0015a\u00018j_&!\u0011QJA$\u0005)\u0011\u0015\u0010^3Ck\u001a4WM\u001d\u000b\u0005\u0003#\n\u0019\u0006\u0005\u0002o+!9\u0011\u0011I\fA\u0002\u0005\rS\u0003BA,\u00037\"B!!\u0017\u0002^A\u0019!(a\u0017\u0005\u000bqB\"\u0019A\u001f\t\r\u0015C\u0002\u0019AA0!\u0015As)SA-\u0003I\u0011\u0015\u0010^3Ck\u001a4WM\u001d*fC\u0012\f\'\r\\3\u0015\t\u0005E\u0013Q\r\u0005\b\u0003\u0003Z\u0002\u0019AA\"\u0005MIe\u000e];u\'R\u0014X-Y7SK\u0006$\u0017M\u00197f\'\rareX\u0001\u0002SR!\u0011qNA9!\tqG\u0004\u0003\u0004\u0002ly\u0001\r!S\u000b\u0005\u0003k\nI\b\u0006\u0003\u0002x\u0005m\u0004c\u0001\u001e\u0002z\u0011)Ah\bb\u0001{!1Qi\ba\u0001\u0003{\u0002R\u0001K$J\u0003o*\"!!!\u0011\t!\n\u0019)Y\u0005\u0004\u0003\u000bK#AB(qi&|g.A\nJ]B,Ho\u0015;sK\u0006l\'+Z1eC\ndW\r\u0006\u0003\u0002p\u0005-\u0005BBA6C\u0001\u0007\u0011\n
   #11 = Utf8               geny/Readable$ByteArrayReadable
   #12 = Class              #11           // geny/Readable$ByteArrayReadable
   #13 = Utf8               ByteArrayReadable
   #14 = Utf8               geny/Readable$ByteBufferReadable
   #15 = Class              #14           // geny/Readable$ByteBufferReadable
   #16 = Utf8               ByteBufferReadable
   #17 = Utf8               geny/Readable$InputStreamReadable
   #18 = Class              #17           // geny/Readable$InputStreamReadable
   #19 = Utf8               InputStreamReadable
   #20 = Utf8               geny/Readable$StringReadable
   #21 = Class              #20           // geny/Readable$StringReadable
   #22 = Utf8               StringReadable
   #23 = Utf8               java/lang/invoke/MethodHandles$Lookup
   #24 = Class              #23           // java/lang/invoke/MethodHandles$Lookup
   #25 = Utf8               java/lang/invoke/MethodHandles
   #26 = Class              #25           // java/lang/invoke/MethodHandles
   #27 = Utf8               Lookup
   #28 = Utf8               (Ljava/io/InputStream;)Lgeny/Readable$InputStreamReadable;
   #29 = Utf8               i
   #30 = Utf8               geny/Readable$
   #31 = Class              #30           // geny/Readable$
   #32 = Utf8               MODULE$
   #33 = Utf8               Lgeny/Readable$;
   #34 = NameAndType        #32:#33       // MODULE$:Lgeny/Readable$;
   #35 = Fieldref           #31.#34       // geny/Readable$.MODULE$:Lgeny/Readable$;
   #36 = NameAndType        #19:#28       // InputStreamReadable:(Ljava/io/InputStream;)Lgeny/Readable$InputStreamReadable;
   #37 = Methodref          #31.#36       // geny/Readable$.InputStreamReadable:(Ljava/io/InputStream;)Lgeny/Readable$InputStreamReadable;
   #38 = Utf8               (Ljava/nio/ByteBuffer;)Lgeny/Readable$ByteBufferReadable;
   #39 = Utf8               buffer
   #40 = NameAndType        #16:#38       // ByteBufferReadable:(Ljava/nio/ByteBuffer;)Lgeny/Readable$ByteBufferReadable;
   #41 = Methodref          #31.#40       // geny/Readable$.ByteBufferReadable:(Ljava/nio/ByteBuffer;)Lgeny/Readable$ByteBufferReadable;
   #42 = Utf8               ([B)Lgeny/Readable$ByteArrayReadable;
   #43 = Utf8               a
   #44 = NameAndType        #13:#42       // ByteArrayReadable:([B)Lgeny/Readable$ByteArrayReadable;
   #45 = Methodref          #31.#44       // geny/Readable$.ByteArrayReadable:([B)Lgeny/Readable$ByteArrayReadable;
   #46 = Utf8               (Ljava/lang/String;)Lgeny/Readable$StringReadable;
   #47 = Utf8               s
   #48 = NameAndType        #22:#46       // StringReadable:(Ljava/lang/String;)Lgeny/Readable$StringReadable;
   #49 = Methodref          #31.#48       // geny/Readable$.StringReadable:(Ljava/lang/String;)Lgeny/Readable$StringReadable;
   #50 = Utf8               readBytesThrough
   #51 = Utf8               (Lscala/Function1;)Ljava/lang/Object;
   #52 = Utf8               <T:Ljava/lang/Object;>(Lscala/Function1<Ljava/io/InputStream;TT;>;)TT;
   #53 = Utf8               f
   #54 = Utf8               writeBytesTo$
   #55 = Utf8               (Lgeny/Readable;Ljava/io/OutputStream;)V
   #56 = Utf8               $this
   #57 = Utf8               out
   #58 = Utf8               writeBytesTo
   #59 = Utf8               (Ljava/io/OutputStream;)V
   #60 = NameAndType        #58:#59       // writeBytesTo:(Ljava/io/OutputStream;)V
   #61 = InterfaceMethodref #2.#60        // geny/Readable.writeBytesTo:(Ljava/io/OutputStream;)V
   #62 = Utf8               Lgeny/Readable;
   #63 = Utf8               Ljava/io/OutputStream;
   #64 = Utf8               (Ljava/lang/Object;)Ljava/lang/Object;
   #65 = MethodType         #64           //  (Ljava/lang/Object;)Ljava/lang/Object;
   #66 = Utf8               $anonfun$writeBytesTo$2$adapted
   #67 = Utf8               (Ljava/io/OutputStream;Ljava/io/InputStream;)Ljava/lang/Object;
   #68 = NameAndType        #66:#67       // $anonfun$writeBytesTo$2$adapted:(Ljava/io/OutputStream;Ljava/io/InputStream;)Ljava/lang/Object;
   #69 = InterfaceMethodref #2.#68        // geny/Readable.$anonfun$writeBytesTo$2$adapted:(Ljava/io/OutputStream;Ljava/io/InputStream;)Ljava/lang/Object;
   #70 = MethodHandle       6:#69         // REF_invokeStatic geny/Readable.$anonfun$writeBytesTo$2$adapted:(Ljava/io/OutputStream;Ljava/io/InputStream;)Ljava/lang/Object;
   #71 = Utf8               (Ljava/io/InputStream;)Ljava/lang/Object;
   #72 = MethodType         #71           //  (Ljava/io/InputStream;)Ljava/lang/Object;
   #73 = Integer            5
   #74 = Integer            1
   #75 = Utf8               java/lang/invoke/LambdaMetafactory
   #76 = Class              #75           // java/lang/invoke/LambdaMetafactory
   #77 = Utf8               altMetafactory
   #78 = Utf8               (Ljava/lang/invoke/MethodHandles$Lookup;Ljava/lang/String;Ljava/lang/invoke/MethodType;[Ljava/lang/Object;)Ljava/lang/invoke/CallSite;
   #79 = NameAndType        #77:#78       // altMetafactory:(Ljava/lang/invoke/MethodHandles$Lookup;Ljava/lang/String;Ljava/lang/invoke/MethodType;[Ljava/lang/Object;)Ljava/lang/invoke/CallSite;
   #80 = Methodref          #76.#79       // java/lang/invoke/LambdaMetafactory.altMetafactory:(Ljava/lang/invoke/MethodHandles$Lookup;Ljava/lang/String;Ljava/lang/invoke/MethodType;[Ljava/lang/Object;)Ljava/lang/invoke/CallSite;
   #81 = MethodHandle       6:#80         // REF_invokeStatic java/lang/invoke/LambdaMetafactory.altMetafactory:(Ljava/lang/invoke/MethodHandles$Lookup;Ljava/lang/String;Ljava/lang/invoke/MethodType;[Ljava/lang/Object;)Ljava/lang/invoke/CallSite;
   #82 = Utf8               apply
   #83 = Utf8               (Ljava/io/OutputStream;)Lscala/Function1;
   #84 = NameAndType        #82:#83       // apply:(Ljava/io/OutputStream;)Lscala/Function1;
   #85 = InvokeDynamic      #0:#84        // #0:apply:(Ljava/io/OutputStream;)Lscala/Function1;
   #86 = NameAndType        #50:#51       // readBytesThrough:(Lscala/Function1;)Ljava/lang/Object;
   #87 = InterfaceMethodref #2.#86        // geny/Readable.readBytesThrough:(Lscala/Function1;)Ljava/lang/Object;
   #88 = Utf8               this
   #89 = Utf8               $anonfun$writeBytesTo$2
   #90 = Utf8               (Ljava/io/OutputStream;Ljava/io/InputStream;)V
   #91 = Utf8               out$2
   #92 = Utf8               x$1
   #93 = Utf8               geny/Internal$
   #94 = Class              #93           // geny/Internal$
   #95 = Utf8               Lgeny/Internal$;
   #96 = NameAndType        #32:#95       // MODULE$:Lgeny/Internal$;
   #97 = Fieldref           #94.#96       // geny/Internal$.MODULE$:Lgeny/Internal$;
   #98 = Utf8               transfer$default$3
   #99 = Utf8               ()I
  #100 = NameAndType        #98:#99       // transfer$default$3:()I
  #101 = Methodref          #94.#100      // geny/Internal$.transfer$default$3:()I
  #102 = Utf8               transfer$default$4
  #103 = NameAndType        #102:#99      // transfer$default$4:()I
  #104 = Methodref          #94.#103      // geny/Internal$.transfer$default$4:()I
  #105 = Utf8               transfer$default$5
  #106 = NameAndType        #105:#99      // transfer$default$5:()I
  #107 = Methodref          #94.#106      // geny/Internal$.transfer$default$5:()I
  #108 = Utf8               transfer
  #109 = Utf8               (Ljava/io/InputStream;Ljava/io/OutputStream;III)V
  #110 = NameAndType        #108:#109     // transfer:(Ljava/io/InputStream;Ljava/io/OutputStream;III)V
  #111 = Methodref          #94.#110      // geny/Internal$.transfer:(Ljava/io/InputStream;Ljava/io/OutputStream;III)V
  #112 = Utf8               Ljava/io/InputStream;
  #113 = Utf8               $init$
  #114 = Utf8               (Lgeny/Readable;)V
  #115 = NameAndType        #89:#90       // $anonfun$writeBytesTo$2:(Ljava/io/OutputStream;Ljava/io/InputStream;)V
  #116 = InterfaceMethodref #2.#115       // geny/Readable.$anonfun$writeBytesTo$2:(Ljava/io/OutputStream;Ljava/io/InputStream;)V
  #117 = Utf8               scala/runtime/BoxedUnit
  #118 = Class              #117          // scala/runtime/BoxedUnit
  #119 = Utf8               UNIT
  #120 = Utf8               Lscala/runtime/BoxedUnit;
  #121 = NameAndType        #119:#120     // UNIT:Lscala/runtime/BoxedUnit;
  #122 = Fieldref           #118.#121     // scala/runtime/BoxedUnit.UNIT:Lscala/runtime/BoxedUnit;
  #123 = Utf8               $deserializeLambda$
  #124 = Utf8               (Ljava/lang/invoke/SerializedLambda;)Ljava/lang/Object;
  #125 = Utf8               scala/runtime/LambdaDeserialize
  #126 = Class              #125          // scala/runtime/LambdaDeserialize
  #127 = Utf8               bootstrap
  #128 = Utf8               (Ljava/lang/invoke/MethodHandles$Lookup;Ljava/lang/String;Ljava/lang/invoke/MethodType;[Ljava/lang/invoke/MethodHandle;)Ljava/lang/invoke/CallSite;
  #129 = NameAndType        #127:#128     // bootstrap:(Ljava/lang/invoke/MethodHandles$Lookup;Ljava/lang/String;Ljava/lang/invoke/MethodType;[Ljava/lang/invoke/MethodHandle;)Ljava/lang/invoke/CallSite;
  #130 = Methodref          #126.#129     // scala/runtime/LambdaDeserialize.bootstrap:(Ljava/lang/invoke/MethodHandles$Lookup;Ljava/lang/String;Ljava/lang/invoke/MethodType;[Ljava/lang/invoke/MethodHandle;)Ljava/lang/invoke/CallSite;
  #131 = MethodHandle       6:#130        // REF_invokeStatic scala/runtime/LambdaDeserialize.bootstrap:(Ljava/lang/invoke/MethodHandles$Lookup;Ljava/lang/String;Ljava/lang/invoke/MethodType;[Ljava/lang/invoke/MethodHandle;)Ljava/lang/invoke/CallSite;
  #132 = Utf8               lambdaDeserialize
  #133 = NameAndType        #132:#124     // lambdaDeserialize:(Ljava/lang/invoke/SerializedLambda;)Ljava/lang/Object;
  #134 = InvokeDynamic      #1:#133       // #1:lambdaDeserialize:(Ljava/lang/invoke/SerializedLambda;)Ljava/lang/Object;
  #135 = Utf8               Code
  #136 = Utf8               MethodParameters
  #137 = Utf8               Signature
  #138 = Utf8               LineNumberTable
  #139 = Utf8               LocalVariableTable
  #140 = Utf8               InnerClasses
  #141 = Utf8               SourceFile
  #142 = Utf8               RuntimeVisibleAnnotations
  #143 = Utf8               BootstrapMethods
  #144 = Utf8               ScalaInlineInfo
  #145 = Utf8               ScalaSig
{
  public static geny.Readable$InputStreamReadable InputStreamReadable(java.io.InputStream);
    descriptor: (Ljava/io/InputStream;)Lgeny/Readable$InputStreamReadable;
    flags: (0x0009) ACC_PUBLIC, ACC_STATIC
    Code:
      stack=2, locals=1, args_size=1
         0: getstatic     #35                 // Field geny/Readable$.MODULE$:Lgeny/Readable$;
         3: aload_0
         4: invokevirtual #37                 // Method geny/Readable$.InputStreamReadable:(Ljava/io/InputStream;)Lgeny/Readable$InputStreamReadable;
         7: areturn
    MethodParameters:
      Name                           Flags
      i                              final

  public static geny.Readable$ByteBufferReadable ByteBufferReadable(java.nio.ByteBuffer);
    descriptor: (Ljava/nio/ByteBuffer;)Lgeny/Readable$ByteBufferReadable;
    flags: (0x0009) ACC_PUBLIC, ACC_STATIC
    Code:
      stack=2, locals=1, args_size=1
         0: getstatic     #35                 // Field geny/Readable$.MODULE$:Lgeny/Readable$;
         3: aload_0
         4: invokevirtual #41                 // Method geny/Readable$.ByteBufferReadable:(Ljava/nio/ByteBuffer;)Lgeny/Readable$ByteBufferReadable;
         7: areturn
    MethodParameters:
      Name                           Flags
      buffer                         final

  public static geny.Readable$ByteArrayReadable ByteArrayReadable(byte[]);
    descriptor: ([B)Lgeny/Readable$ByteArrayReadable;
    flags: (0x0009) ACC_PUBLIC, ACC_STATIC
    Code:
      stack=2, locals=1, args_size=1
         0: getstatic     #35                 // Field geny/Readable$.MODULE$:Lgeny/Readable$;
         3: aload_0
         4: invokevirtual #45                 // Method geny/Readable$.ByteArrayReadable:([B)Lgeny/Readable$ByteArrayReadable;
         7: areturn
    MethodParameters:
      Name                           Flags
      a                              final

  public static geny.Readable$StringReadable StringReadable(java.lang.String);
    descriptor: (Ljava/lang/String;)Lgeny/Readable$StringReadable;
    flags: (0x0009) ACC_PUBLIC, ACC_STATIC
    Code:
      stack=2, locals=1, args_size=1
         0: getstatic     #35                 // Field geny/Readable$.MODULE$:Lgeny/Readable$;
         3: aload_0
         4: invokevirtual #49                 // Method geny/Readable$.StringReadable:(Ljava/lang/String;)Lgeny/Readable$StringReadable;
         7: areturn
    MethodParameters:
      Name                           Flags
      s                              final

  public abstract <T extends java.lang.Object> T readBytesThrough(scala.Function1<java.io.InputStream, T>);
    descriptor: (Lscala/Function1;)Ljava/lang/Object;
    flags: (0x0401) ACC_PUBLIC, ACC_ABSTRACT
    Signature: #52                          // <T:Ljava/lang/Object;>(Lscala/Function1<Ljava/io/InputStream;TT;>;)TT;
    MethodParameters:
      Name                           Flags
      f                              final

  public static void writeBytesTo$(geny.Readable, java.io.OutputStream);
    descriptor: (Lgeny/Readable;Ljava/io/OutputStream;)V
    flags: (0x1009) ACC_PUBLIC, ACC_STATIC, ACC_SYNTHETIC
    Code:
      stack=2, locals=2, args_size=2
         0: aload_0
         1: aload_1
         2: invokespecial #61                 // InterfaceMethod writeBytesTo:(Ljava/io/OutputStream;)V
         5: return
      LineNumberTable:
        line 93: 0
      LocalVariableTable:
        Start  Length  Slot  Name   Signature
            0       6     0 $this   Lgeny/Readable;
            0       6     1   out   Ljava/io/OutputStream;
    MethodParameters:
      Name                           Flags
      $this                          final synthetic
      out                            final

  public default void writeBytesTo(java.io.OutputStream);
    descriptor: (Ljava/io/OutputStream;)V
    flags: (0x0001) ACC_PUBLIC
    Code:
      stack=2, locals=2, args_size=2
         0: aload_0
         1: aload_1
         2: invokedynamic #85,  0             // InvokeDynamic #0:apply:(Ljava/io/OutputStream;)Lscala/Function1;
         7: invokeinterface #87,  2           // InterfaceMethod readBytesThrough:(Lscala/Function1;)Ljava/lang/Object;
        12: pop
        13: return
      LineNumberTable:
        line 93: 0
      LocalVariableTable:
        Start  Length  Slot  Name   Signature
            0      14     0  this   Lgeny/Readable;
            0      14     1   out   Ljava/io/OutputStream;
    MethodParameters:
      Name                           Flags
      out                            final

  public static void $anonfun$writeBytesTo$2(java.io.OutputStream, java.io.InputStream);
    descriptor: (Ljava/io/OutputStream;Ljava/io/InputStream;)V
    flags: (0x1009) ACC_PUBLIC, ACC_STATIC, ACC_SYNTHETIC
    Code:
      stack=6, locals=2, args_size=2
         0: getstatic     #97                 // Field geny/Internal$.MODULE$:Lgeny/Internal$;
         3: aload_1
         4: aload_0
         5: getstatic     #97                 // Field geny/Internal$.MODULE$:Lgeny/Internal$;
         8: invokevirtual #101                // Method geny/Internal$.transfer$default$3:()I
        11: getstatic     #97                 // Field geny/Internal$.MODULE$:Lgeny/Internal$;
        14: invokevirtual #104                // Method geny/Internal$.transfer$default$4:()I
        17: getstatic     #97                 // Field geny/Internal$.MODULE$:Lgeny/Internal$;
        20: invokevirtual #107                // Method geny/Internal$.transfer$default$5:()I
        23: invokevirtual #111                // Method geny/Internal$.transfer:(Ljava/io/InputStream;Ljava/io/OutputStream;III)V
        26: return
      LineNumberTable:
        line 93: 0
      LocalVariableTable:
        Start  Length  Slot  Name   Signature
            0      27     0 out$2   Ljava/io/OutputStream;
            0      27     1   x$1   Ljava/io/InputStream;
    MethodParameters:
      Name                           Flags
      out$2                          final
      x$1                            final

  public static void $init$(geny.Readable);
    descriptor: (Lgeny/Readable;)V
    flags: (0x0009) ACC_PUBLIC, ACC_STATIC
    Code:
      stack=0, locals=1, args_size=1
         0: return
      LineNumberTable:
        line 91: 0
      LocalVariableTable:
        Start  Length  Slot  Name   Signature
            0       1     0 $this   Lgeny/Readable;
    MethodParameters:
      Name                           Flags
      $this                          final synthetic

  public static java.lang.Object $anonfun$writeBytesTo$2$adapted(java.io.OutputStream, java.io.InputStream);
    descriptor: (Ljava/io/OutputStream;Ljava/io/InputStream;)Ljava/lang/Object;
    flags: (0x1009) ACC_PUBLIC, ACC_STATIC, ACC_SYNTHETIC
    Code:
      stack=2, locals=2, args_size=2
         0: aload_0
         1: aload_1
         2: invokestatic  #116                // InterfaceMethod $anonfun$writeBytesTo$2:(Ljava/io/OutputStream;Ljava/io/InputStream;)V
         5: getstatic     #122                // Field scala/runtime/BoxedUnit.UNIT:Lscala/runtime/BoxedUnit;
         8: areturn
      LineNumberTable:
        line 93: 0
      LocalVariableTable:
        Start  Length  Slot  Name   Signature
            0       9     0 out$2   Ljava/io/OutputStream;
            0       9     1   x$1   Ljava/io/InputStream;
    MethodParameters:
      Name                           Flags
      out$2                          final
      x$1                            final

  private static java.lang.Object $deserializeLambda$(java.lang.invoke.SerializedLambda);
    descriptor: (Ljava/lang/invoke/SerializedLambda;)Ljava/lang/Object;
    flags: (0x100a) ACC_PRIVATE, ACC_STATIC, ACC_SYNTHETIC
    Code:
      stack=1, locals=1, args_size=1
         0: aload_0
         1: invokedynamic #134,  0            // InvokeDynamic #1:lambdaDeserialize:(Ljava/lang/invoke/SerializedLambda;)Ljava/lang/Object;
         6: areturn
}
InnerClasses:
  public static #13= #12 of #2;           // ByteArrayReadable=class geny/Readable$ByteArrayReadable of class geny/Readable
  public static #16= #15 of #2;           // ByteBufferReadable=class geny/Readable$ByteBufferReadable of class geny/Readable
  public static #19= #18 of #2;           // InputStreamReadable=class geny/Readable$InputStreamReadable of class geny/Readable
  public static #22= #21 of #2;           // StringReadable=class geny/Readable$StringReadable of class geny/Readable
  public static final #27= #24 of #26;    // Lookup=class java/lang/invoke/MethodHandles$Lookup of class java/lang/invoke/MethodHandles
SourceFile: "Writable.scala"
RuntimeVisibleAnnotations:
  0: #8(#9=s#10)
    scala.reflect.ScalaSignature(
      bytes="\u0006\u0005\u00055ea\u0002\u0012$!\u0003\r\tA\n\u0005\u0006c\u0001!\tA\r\u0005\u0006m\u00011\ta\u000e\u0005\u0006#\u0002!\tAU\u0004\u00061\u000eB\t!\u0017\u0004\u0006E\rB\tA\u0017\u0005\u00067\u0016!\t\u0001\u0018\u0004\u0005;\u0016\ta\f\u0003\u0005a\u000f\t\u0005\t\u0015!\u0003b\u0011\u0015Yv\u0001\"\u0001m\u0011\u00151t\u0001\"\u0001q\u0011\u00151x\u0001\"\u0011x\u0011\u001d\t\ta\u0002C!\u0003\u0007A\u0011\"!\u0004\u0006\u0003\u0003%\u0019!a\u0004\u0007\r\u0005MQ!AA\u000b\u0011)\t9B\u0004B\u0001B\u0003%\u0011\u0011\u0004\u0005\u00077:!\t!!\n\t\rYrA\u0011AA\u0016\u0011\u00151h\u0002\"\u0011x\u0011\u001d\t\tA\u0004C!\u0003\u0007A\u0011\"a\u000e\u0006\u0003\u0003%\u0019!!\u000f\u0007\r\u0005uR!AA \u0011)\t\t%\u0006B\u0001B\u0003%\u00111\t\u0005\u00077V!\t!a\u0014\t\rY*B\u0011AA+\u0011\u00151X\u0003\"\u0011x\u0011\u001d\t\t!\u0006C!\u0003\u0007A\u0011\"!\u0019\u0006\u0003\u0003%\u0019!a\u0019\u0007\r\u0005\u001dT!AA5\u0011%\tY\u0007\bB\u0001B\u0003%\u0011\n\u0003\u0004\\9\u0011\u0005\u0011Q\u000e\u0005\u0007mq!\t!a\u001d\t\rYdB\u0011IA@\u0011%\t9)BA\u0001\n\u0007\tII\u0001\u0005SK\u0006$\u0017M\u00197f\u0015\u0005!\u0013\u0001B4f]f\u001c\u0001aE\u0002\u0001O5\u0002\"\u0001K\u0016\u000e\u0003%R\u0011AK\u0001\u0006g\u000e\fG.Y\u0005\u0003Y%\u0012a!\u00118z%\u00164\u0007C\u0001\u00180\u001b\u0005\u0019\u0013B\u0001\u0019$\u0005!9&/\u001b;bE2,\u0017A\u0002\u0013j]&$H\u0005F\u00014!\tAC\'\u0003\u00026S\t!QK\\5u\u0003A\u0011X-\u00193CsR,7\u000f\u00165s_V<\u0007.\u0006\u00029wQ\u0011\u0011\b\u0012\t\u0003umb\u0001\u0001B\u0003=\u0005\t\u0007QHA\u0001U#\tq\u0014\t\u0005\u0002)\u007f%\u0011\u0001)\u000b\u0002\b\u001d>$\b.\u001b8h!\tA#)\u0003\u0002DS\t\u0019\u0011I\\=\t\u000b\u0015\u0013\u0001\u0019\u0001$\u0002\u0003\u0019\u0004B\u0001K$Js%\u0011\u0001*\u000b\u0002\n\rVt7\r^5p]F\u0002\"AS(\u000e\u0003-S!\u0001T\'\u0002\u0005%|\'\"\u0001(\u0002\t)\fg/Y\u0005\u0003!.\u00131\"\u00138qkR\u001cFO]3b[\u0006aqO]5uK\nKH/Z:U_R\u00111g\u0015\u0005\u0006)\u000e\u0001\r!V\u0001\u0004_V$\bC\u0001&W\u0013\t96J\u0001\u0007PkR\u0004X\u000f^*ue\u0016\fW.\u0001\u0005SK\u0006$\u0017M\u00197f!\tqSa\u0005\u0002\u0006O\u00051A(\u001b8jiz\"\u0012!\u0017\u0002\u000f\'R\u0014\u0018N\\4SK\u0006$\u0017M\u00197f\'\r9qe\u0018\t\u0003]\u0001\t\u0011a\u001d\t\u0003E&t!aY4\u0011\u0005\u0011LS\"A3\u000b\u0005\u0019,\u0013A\u0002\u001fs_>$h(\u0003\u0002iS\u00051\u0001K]3eK\u001aL!A[6\u0003\rM#(/\u001b8h\u0015\tA\u0017\u0006\u0006\u0002n_B\u0011anB\u0007\u0002\u000b!)\u0001-\u0003a\u0001CV\u0011\u0011o\u001d\u000b\u0003eR\u0004\"AO:\u0005\u000bqR!\u0019A\u001f\t\u000b\u0015S\u0001\u0019A;\u0011\t!:\u0015J]\u0001\u0010QR$\boQ8oi\u0016tG\u000fV=qKV\t\u0001\u0010E\u0002)snL!A_\u0015\u0003\tM{W.\u001a\t\u0003y~l\u0011! \u0006\u0003}6\u000bA\u0001\\1oO&\u0011!.`\u0001\u000eG>tG/\u001a8u\u0019\u0016tw\r\u001e5\u0016\u0005\u0005\u0015\u0001\u0003\u0002\u0015z\u0003\u000f\u00012\u0001KA\u0005\u0013\r\tY!\u000b\u0002\u0005\u0019>tw-\u0001\bTiJLgn\u001a*fC\u0012\f\'\r\\3\u0015\u00075\f\t\u0002C\u0003a\u001b\u0001\u0007\u0011MA\tCsR,\u0017I\u001d:bsJ+\u0017\rZ1cY\u0016\u001c2AD\u0014`\u0003\u0005\t\u0007#\u0002\u0015\u0002\u001c\u0005}\u0011bAA\u000fS\t)\u0011I\u001d:bsB\u0019\u0001&!\t\n\u0007\u0005\r\u0012F\u0001\u0003CsR,G\u0003BA\u0014\u0003S\u0001\"A\u001c\b\t\u000f\u0005]\u0001\u00031\u0001\u0002\u001aU!\u0011QFA\u0019)\u0011\ty#a\r\u0011\u0007i\n\t\u0004B\u0003=#\t\u0007Q\b\u0003\u0004F#\u0001\u0007\u0011Q\u0007\t\u0006Q\u001dK\u0015qF\u0001\u0012\u0005f$X-\u0011:sCf\u0014V-\u00193bE2,G\u0003BA\u0014\u0003wAq!a\u0006\u0015\u0001\u0004\tIB\u0001\nCsR,\')\u001e4gKJ\u0014V-\u00193bE2,7cA\u000b(?\u00061!-\u001e4gKJ\u0004B!!\u0012\u0002L5\u0011\u0011q\t\u0006\u0004\u0003\u0013j\u0015a\u00018j_&!\u0011QJA$\u0005)\u0011\u0015\u0010^3Ck\u001a4WM\u001d\u000b\u0005\u0003#\n\u0019\u0006\u0005\u0002o+!9\u0011\u0011I\fA\u0002\u0005\rS\u0003BA,\u00037\"B!!\u0017\u0002^A\u0019!(a\u0017\u0005\u000bqB\"\u0019A\u001f\t\r\u0015C\u0002\u0019AA0!\u0015As)SA-\u0003I\u0011\u0015\u0010^3Ck\u001a4WM\u001d*fC\u0012\f\'\r\\3\u0015\t\u0005E\u0013Q\r\u0005\b\u0003\u0003Z\u0002\u0019AA\"\u0005MIe\u000e];u\'R\u0014X-Y7SK\u0006$\u0017M\u00197f\'\rareX\u0001\u0002SR!\u0011qNA9!\tqG\u0004\u0003\u0004\u0002ly\u0001\r!S\u000b\u0005\u0003k\nI\b\u0006\u0003\u0002x\u0005m\u0004c\u0001\u001e\u0002z\u0011)Ah\bb\u0001{!1Qi\ba\u0001\u0003{\u0002R\u0001K$J\u0003o*\"!!!\u0011\t!\n\u0019)Y\u0005\u0004\u0003\u000bK#AB(qi&|g.A\nJ]B,Ho\u0015;sK\u0006l\'+Z1eC\ndW\r\u0006\u0003\u0002p\u0005-\u0005BBA6C\u0001\u0007\u0011\n"
    )
BootstrapMethods:
  0: #81 REF_invokeStatic java/lang/invoke/LambdaMetafactory.altMetafactory:(Ljava/lang/invoke/MethodHandles$Lookup;Ljava/lang/String;Ljava/lang/invoke/MethodType;[Ljava/lang/Object;)Ljava/lang/invoke/CallSite;
    Method arguments:
      #65 (Ljava/lang/Object;)Ljava/lang/Object;
      #70 REF_invokeStatic geny/Readable.$anonfun$writeBytesTo$2$adapted:(Ljava/io/OutputStream;Ljava/io/InputStream;)Ljava/lang/Object;
      #72 (Ljava/io/InputStream;)Ljava/lang/Object;
      #73 5
      #74 1
      #72 (Ljava/io/InputStream;)Ljava/lang/Object;
  1: #131 REF_invokeStatic scala/runtime/LambdaDeserialize.bootstrap:(Ljava/lang/invoke/MethodHandles$Lookup;Ljava/lang/String;Ljava/lang/invoke/MethodType;[Ljava/lang/invoke/MethodHandle;)Ljava/lang/invoke/CallSite;
    Method arguments:
      #70 REF_invokeStatic geny/Readable.$anonfun$writeBytesTo$2$adapted:(Ljava/io/OutputStream;Ljava/io/InputStream;)Ljava/lang/Object;
  ScalaInlineInfo: length = 0x22 (unknown attribute)
   01 00 00 06 00 59 00 5A 01 00 42 00 43 01 00 71
   00 72 01 00 32 00 33 00 00 3A 00 3B 00 00 36 00
   37 01
  ScalaSig: length = 0x3 (unknown attribute)
   05 02 00
