Classfile /Users/mw/Projects/slang-braindump/.jar/jar8/assemble/slang-braindump/assemble/content/geny/Readable$ByteBufferReadable$$anon$1.class
  Last modified May 29, 2022; size 1395 bytes
  SHA-256 checksum 1463ff247af95c5225e6bb7171f9966a6ab8729e6ffd21b3cfbdab3e645e1e37
  Compiled from "Writable.scala"
public final class geny.Readable$ByteBufferReadable$$anon$1 extends java.io.InputStream
  minor version: 0
  major version: 52
  flags: (0x0031) ACC_PUBLIC, ACC_FINAL, ACC_SUPER
  this_class: #2                          // geny/Readable$ByteBufferReadable$$anon$1
  super_class: #4                         // java/io/InputStream
  interfaces: 0, fields: 1, methods: 3, attributes: 5
Constant pool:
   #1 = Utf8               geny/Readable$ByteBufferReadable$$anon$1
   #2 = Class              #1             // geny/Readable$ByteBufferReadable$$anon$1
   #3 = Utf8               java/io/InputStream
   #4 = Class              #3             // java/io/InputStream
   #5 = Utf8               Writable.scala
   #6 = Utf8               geny/Readable$ByteBufferReadable
   #7 = Class              #6             // geny/Readable$ByteBufferReadable
   #8 = Utf8               readBytesThrough
   #9 = Utf8               (Lscala/Function1;)Ljava/lang/Object;
  #10 = NameAndType        #8:#9          // readBytesThrough:(Lscala/Function1;)Ljava/lang/Object;
  #11 = Utf8               geny/Readable
  #12 = Class              #11            // geny/Readable
  #13 = Utf8               ByteBufferReadable
  #14 = Utf8               bb$1
  #15 = Utf8               Ljava/nio/ByteBuffer;
  #16 = Utf8               read
  #17 = Utf8               ()I
  #18 = NameAndType        #14:#15        // bb$1:Ljava/nio/ByteBuffer;
  #19 = Fieldref           #2.#18         // geny/Readable$ByteBufferReadable$$anon$1.bb$1:Ljava/nio/ByteBuffer;
  #20 = Utf8               java/nio/ByteBuffer
  #21 = Class              #20            // java/nio/ByteBuffer
  #22 = Utf8               hasRemaining
  #23 = Utf8               ()Z
  #24 = NameAndType        #22:#23        // hasRemaining:()Z
  #25 = Methodref          #21.#24        // java/nio/ByteBuffer.hasRemaining:()Z
  #26 = Utf8               get
  #27 = Utf8               ()B
  #28 = NameAndType        #26:#27        // get:()B
  #29 = Methodref          #21.#28        // java/nio/ByteBuffer.get:()B
  #30 = Utf8               this
  #31 = Utf8               Lgeny/Readable$ByteBufferReadable$$anon$1;
  #32 = Utf8               ([BII)I
  #33 = Utf8               bytes
  #34 = Utf8               off
  #35 = Utf8               len
  #36 = Utf8               scala/math/package$
  #37 = Class              #36            // scala/math/package$
  #38 = Utf8               MODULE$
  #39 = Utf8               Lscala/math/package$;
  #40 = NameAndType        #38:#39        // MODULE$:Lscala/math/package$;
  #41 = Fieldref           #37.#40        // scala/math/package$.MODULE$:Lscala/math/package$;
  #42 = Utf8               remaining
  #43 = NameAndType        #42:#17        // remaining:()I
  #44 = Methodref          #21.#43        // java/nio/ByteBuffer.remaining:()I
  #45 = Utf8               min
  #46 = Utf8               (II)I
  #47 = NameAndType        #45:#46        // min:(II)I
  #48 = Methodref          #37.#47        // scala/math/package$.min:(II)I
  #49 = Utf8               ([BII)Ljava/nio/ByteBuffer;
  #50 = NameAndType        #26:#49        // get:([BII)Ljava/nio/ByteBuffer;
  #51 = Methodref          #21.#50        // java/nio/ByteBuffer.get:([BII)Ljava/nio/ByteBuffer;
  #52 = Utf8               l
  #53 = Utf8               I
  #54 = Utf8               [B
  #55 = Utf8               <init>
  #56 = Utf8               (Lgeny/Readable$ByteBufferReadable;Ljava/nio/ByteBuffer;)V
  #57 = Utf8               $outer
  #58 = Utf8               ()V
  #59 = NameAndType        #55:#58        // "<init>":()V
  #60 = Methodref          #4.#59         // java/io/InputStream."<init>":()V
  #61 = Utf8               Lgeny/Readable$ByteBufferReadable;
  #62 = Utf8               Code
  #63 = Utf8               StackMapTable
  #64 = Utf8               LineNumberTable
  #65 = Utf8               LocalVariableTable
  #66 = Utf8               MethodParameters
  #67 = Utf8               InnerClasses
  #68 = Utf8               EnclosingMethod
  #69 = Utf8               SourceFile
  #70 = Utf8               ScalaInlineInfo
  #71 = Utf8               Scala
{
  private final java.nio.ByteBuffer bb$1;
    descriptor: Ljava/nio/ByteBuffer;
    flags: (0x0012) ACC_PRIVATE, ACC_FINAL

  public int read();
    descriptor: ()I
    flags: (0x0001) ACC_PUBLIC
    Code:
      stack=2, locals=1, args_size=1
         0: aload_0
         1: getfield      #19                 // Field bb$1:Ljava/nio/ByteBuffer;
         4: invokevirtual #25                 // Method java/nio/ByteBuffer.hasRemaining:()Z
         7: ifne          14
        10: iconst_m1
        11: goto          25
        14: aload_0
        15: getfield      #19                 // Field bb$1:Ljava/nio/ByteBuffer;
        18: invokevirtual #29                 // Method java/nio/ByteBuffer.get:()B
        21: sipush        255
        24: iand
        25: ireturn
      StackMapTable: number_of_entries = 2
        frame_type = 14 /* same */
        frame_type = 74 /* same_locals_1_stack_item */
          stack = [ int ]
      LineNumberTable:
        line 115: 0
        line 116: 10
        line 118: 14
      LocalVariableTable:
        Start  Length  Slot  Name   Signature
            0      26     0  this   Lgeny/Readable$ByteBufferReadable$$anon$1;

  public int read(byte[], int, int);
    descriptor: ([BII)I
    flags: (0x0001) ACC_PUBLIC
    Code:
      stack=4, locals=5, args_size=4
         0: aload_0
         1: getfield      #19                 // Field bb$1:Ljava/nio/ByteBuffer;
         4: invokevirtual #25                 // Method java/nio/ByteBuffer.hasRemaining:()Z
         7: ifne          14
        10: iconst_m1
        11: goto          44
        14: getstatic     #41                 // Field scala/math/package$.MODULE$:Lscala/math/package$;
        17: iload_3
        18: aload_0
        19: getfield      #19                 // Field bb$1:Ljava/nio/ByteBuffer;
        22: invokevirtual #44                 // Method java/nio/ByteBuffer.remaining:()I
        25: invokevirtual #48                 // Method scala/math/package$.min:(II)I
        28: istore        4
        30: aload_0
        31: getfield      #19                 // Field bb$1:Ljava/nio/ByteBuffer;
        34: aload_1
        35: iload_2
        36: iload         4
        38: invokevirtual #51                 // Method java/nio/ByteBuffer.get:([BII)Ljava/nio/ByteBuffer;
        41: pop
        42: iload         4
        44: ireturn
      StackMapTable: number_of_entries = 2
        frame_type = 14 /* same */
        frame_type = 93 /* same_locals_1_stack_item */
          stack = [ int ]
      LineNumberTable:
        line 120: 0
        line 121: 10
        line 123: 14
        line 124: 30
        line 125: 42
      LocalVariableTable:
        Start  Length  Slot  Name   Signature
           30      14     4     l   I
            0      45     0  this   Lgeny/Readable$ByteBufferReadable$$anon$1;
            0      45     1 bytes   [B
            0      45     2   off   I
            0      45     3   len   I
    MethodParameters:
      Name                           Flags
      bytes                          final
      off                            final
      len                            final

  public geny.Readable$ByteBufferReadable$$anon$1(geny.Readable$ByteBufferReadable, java.nio.ByteBuffer);
    descriptor: (Lgeny/Readable$ByteBufferReadable;Ljava/nio/ByteBuffer;)V
    flags: (0x0001) ACC_PUBLIC
    Code:
      stack=2, locals=3, args_size=3
         0: aload_0
         1: aload_2
         2: putfield      #19                 // Field bb$1:Ljava/nio/ByteBuffer;
         5: aload_0
         6: invokespecial #60                 // Method java/io/InputStream."<init>":()V
         9: return
      LineNumberTable:
        line 112: 0
        line 114: 5
      LocalVariableTable:
        Start  Length  Slot  Name   Signature
            0      10     0  this   Lgeny/Readable$ByteBufferReadable$$anon$1;
            0      10     1 $outer   Lgeny/Readable$ByteBufferReadable;
            0      10     2  bb$1   Ljava/nio/ByteBuffer;
    MethodParameters:
      Name                           Flags
      $outer                         final synthetic
      bb$1                           final
}
InnerClasses:
  public static #13= #7 of #12;           // ByteBufferReadable=class geny/Readable$ByteBufferReadable of class geny/Readable
  public final #2;                        // class geny/Readable$ByteBufferReadable$$anon$1
EnclosingMethod: #7.#10                 // geny.Readable$ByteBufferReadable.readBytesThrough
SourceFile: "Writable.scala"
  ScalaInlineInfo: length = 0x13 (unknown attribute)
   01 01 00 03 00 37 00 38 01 00 10 00 11 01 00 10
   00 20 01
  Scala: length = 0x0 (unknown attribute)

