Classfile /Users/mw/Projects/slang-braindump/.jar/jar8/assemble/slang-braindump/assemble/content/geny/Writable$.class
  Last modified May 29, 2022; size 1749 bytes
  SHA-256 checksum c2d82f4749f406355351b6dd98033dce708e7ee6498902e422d6eb29c72b59bc
  Compiled from "Writable.scala"
public final class geny.Writable$ implements geny.LowPriWritable
  minor version: 0
  major version: 52
  flags: (0x0031) ACC_PUBLIC, ACC_FINAL, ACC_SUPER
  this_class: #2                          // geny/Writable$
  super_class: #4                         // java/lang/Object
  interfaces: 1, fields: 1, methods: 6, attributes: 4
Constant pool:
   #1 = Utf8               geny/Writable$
   #2 = Class              #1             // geny/Writable$
   #3 = Utf8               java/lang/Object
   #4 = Class              #3             // java/lang/Object
   #5 = Utf8               geny/LowPriWritable
   #6 = Class              #5             // geny/LowPriWritable
   #7 = Utf8               Writable.scala
   #8 = Utf8               geny/Writable$ByteArrayWritable
   #9 = Class              #8             // geny/Writable$ByteArrayWritable
  #10 = Utf8               geny/Writable
  #11 = Class              #10            // geny/Writable
  #12 = Utf8               ByteArrayWritable
  #13 = Utf8               geny/Writable$ByteBufferWritable
  #14 = Class              #13            // geny/Writable$ByteBufferWritable
  #15 = Utf8               ByteBufferWritable
  #16 = Utf8               geny/Writable$StringWritable
  #17 = Class              #16            // geny/Writable$StringWritable
  #18 = Utf8               StringWritable
  #19 = Utf8               MODULE$
  #20 = Utf8               Lgeny/Writable$;
  #21 = Utf8               <clinit>
  #22 = Utf8               ()V
  #23 = Utf8               <init>
  #24 = NameAndType        #23:#22        // "<init>":()V
  #25 = Methodref          #2.#24         // geny/Writable$."<init>":()V
  #26 = NameAndType        #19:#20        // MODULE$:Lgeny/Writable$;
  #27 = Fieldref           #2.#26         // geny/Writable$.MODULE$:Lgeny/Writable$;
  #28 = Utf8               $init$
  #29 = Utf8               (Lgeny/LowPriWritable;)V
  #30 = NameAndType        #28:#29        // $init$:(Lgeny/LowPriWritable;)V
  #31 = InterfaceMethodref #6.#30         // geny/LowPriWritable.$init$:(Lgeny/LowPriWritable;)V
  #32 = Utf8               readableWritable
  #33 = Utf8               (Ljava/lang/Object;Lscala/Function1;)Lgeny/Writable;
  #34 = Utf8               <T:Ljava/lang/Object;>(TT;Lscala/Function1<TT;Lgeny/Readable;>;)Lgeny/Writable;
  #35 = Utf8               t
  #36 = Utf8               f
  #37 = Utf8               readableWritable$
  #38 = Utf8               (Lgeny/LowPriWritable;Ljava/lang/Object;Lscala/Function1;)Lgeny/Writable;
  #39 = NameAndType        #37:#38        // readableWritable$:(Lgeny/LowPriWritable;Ljava/lang/Object;Lscala/Function1;)Lgeny/Writable;
  #40 = InterfaceMethodref #6.#39         // geny/LowPriWritable.readableWritable$:(Lgeny/LowPriWritable;Ljava/lang/Object;Lscala/Function1;)Lgeny/Writable;
  #41 = Utf8               this
  #42 = Utf8               Ljava/lang/Object;
  #43 = Utf8               Lscala/Function1;
  #44 = Utf8               (Ljava/lang/String;)Lgeny/Writable$StringWritable;
  #45 = Utf8               s
  #46 = Utf8               (Ljava/lang/String;)V
  #47 = NameAndType        #23:#46        // "<init>":(Ljava/lang/String;)V
  #48 = Methodref          #17.#47        // geny/Writable$StringWritable."<init>":(Ljava/lang/String;)V
  #49 = Utf8               Ljava/lang/String;
  #50 = Utf8               ([B)Lgeny/Writable$ByteArrayWritable;
  #51 = Utf8               a
  #52 = Utf8               ([B)V
  #53 = NameAndType        #23:#52        // "<init>":([B)V
  #54 = Methodref          #9.#53         // geny/Writable$ByteArrayWritable."<init>":([B)V
  #55 = Utf8               [B
  #56 = Utf8               (Ljava/nio/ByteBuffer;)Lgeny/Writable$ByteBufferWritable;
  #57 = Utf8               buffer
  #58 = Utf8               (Ljava/nio/ByteBuffer;)V
  #59 = NameAndType        #23:#58        // "<init>":(Ljava/nio/ByteBuffer;)V
  #60 = Methodref          #14.#59        // geny/Writable$ByteBufferWritable."<init>":(Ljava/nio/ByteBuffer;)V
  #61 = Utf8               Ljava/nio/ByteBuffer;
  #62 = Methodref          #4.#24         // java/lang/Object."<init>":()V
  #63 = Utf8               Code
  #64 = Utf8               LineNumberTable
  #65 = Utf8               LocalVariableTable
  #66 = Utf8               Signature
  #67 = Utf8               MethodParameters
  #68 = Utf8               InnerClasses
  #69 = Utf8               SourceFile
  #70 = Utf8               ScalaInlineInfo
  #71 = Utf8               Scala
{
  public static final geny.Writable$ MODULE$;
    descriptor: Lgeny/Writable$;
    flags: (0x0019) ACC_PUBLIC, ACC_STATIC, ACC_FINAL

  public static {};
    descriptor: ()V
    flags: (0x0009) ACC_PUBLIC, ACC_STATIC
    Code:
      stack=2, locals=0, args_size=0
         0: new           #2                  // class geny/Writable$
         3: dup
         4: invokespecial #25                 // Method "<init>":()V
         7: putstatic     #27                 // Field MODULE$:Lgeny/Writable$;
        10: getstatic     #27                 // Field MODULE$:Lgeny/Writable$;
        13: invokestatic  #31                 // InterfaceMethod geny/LowPriWritable.$init$:(Lgeny/LowPriWritable;)V
        16: return
      LineNumberTable:
        line 30: 0

  public <T extends java.lang.Object> geny.Writable readableWritable(T, scala.Function1<T, geny.Readable>);
    descriptor: (Ljava/lang/Object;Lscala/Function1;)Lgeny/Writable;
    flags: (0x0001) ACC_PUBLIC
    Code:
      stack=3, locals=3, args_size=3
         0: aload_0
         1: aload_1
         2: aload_2
         3: invokestatic  #40                 // InterfaceMethod geny/LowPriWritable.readableWritable$:(Lgeny/LowPriWritable;Ljava/lang/Object;Lscala/Function1;)Lgeny/Writable;
         6: areturn
      LineNumberTable:
        line 30: 0
      LocalVariableTable:
        Start  Length  Slot  Name   Signature
            0       7     0  this   Lgeny/Writable$;
            0       7     1     t   Ljava/lang/Object;
            0       7     2     f   Lscala/Function1;
    Signature: #34                          // <T:Ljava/lang/Object;>(TT;Lscala/Function1<TT;Lgeny/Readable;>;)Lgeny/Writable;
    MethodParameters:
      Name                           Flags
      t                              final
      f                              final

  public geny.Writable$StringWritable StringWritable(java.lang.String);
    descriptor: (Ljava/lang/String;)Lgeny/Writable$StringWritable;
    flags: (0x0001) ACC_PUBLIC
    Code:
      stack=3, locals=2, args_size=2
         0: new           #17                 // class geny/Writable$StringWritable
         3: dup
         4: aload_1
         5: invokespecial #48                 // Method geny/Writable$StringWritable."<init>":(Ljava/lang/String;)V
         8: areturn
      LineNumberTable:
        line 31: 0
      LocalVariableTable:
        Start  Length  Slot  Name   Signature
            0       9     0  this   Lgeny/Writable$;
            0       9     1     s   Ljava/lang/String;
    MethodParameters:
      Name                           Flags
      s                              final

  public geny.Writable$ByteArrayWritable ByteArrayWritable(byte[]);
    descriptor: ([B)Lgeny/Writable$ByteArrayWritable;
    flags: (0x0001) ACC_PUBLIC
    Code:
      stack=3, locals=2, args_size=2
         0: new           #9                  // class geny/Writable$ByteArrayWritable
         3: dup
         4: aload_1
         5: invokespecial #54                 // Method geny/Writable$ByteArrayWritable."<init>":([B)V
         8: areturn
      LineNumberTable:
        line 40: 0
      LocalVariableTable:
        Start  Length  Slot  Name   Signature
            0       9     0  this   Lgeny/Writable$;
            0       9     1     a   [B
    MethodParameters:
      Name                           Flags
      a                              final

  public geny.Writable$ByteBufferWritable ByteBufferWritable(java.nio.ByteBuffer);
    descriptor: (Ljava/nio/ByteBuffer;)Lgeny/Writable$ByteBufferWritable;
    flags: (0x0001) ACC_PUBLIC
    Code:
      stack=3, locals=2, args_size=2
         0: new           #14                 // class geny/Writable$ByteBufferWritable
         3: dup
         4: aload_1
         5: invokespecial #60                 // Method geny/Writable$ByteBufferWritable."<init>":(Ljava/nio/ByteBuffer;)V
         8: areturn
      LineNumberTable:
        line 46: 0
      LocalVariableTable:
        Start  Length  Slot  Name   Signature
            0       9     0  this   Lgeny/Writable$;
            0       9     1 buffer   Ljava/nio/ByteBuffer;
    MethodParameters:
      Name                           Flags
      buffer                         final

  private geny.Writable$();
    descriptor: ()V
    flags: (0x0002) ACC_PRIVATE
    Code:
      stack=1, locals=1, args_size=1
         0: aload_0
         1: invokespecial #62                 // Method java/lang/Object."<init>":()V
         4: return
      LineNumberTable:
        line 30: 0
      LocalVariableTable:
        Start  Length  Slot  Name   Signature
            0       5     0  this   Lgeny/Writable$;
}
InnerClasses:
  public static #12= #9 of #11;           // ByteArrayWritable=class geny/Writable$ByteArrayWritable of class geny/Writable
  public static #15= #14 of #11;          // ByteBufferWritable=class geny/Writable$ByteBufferWritable of class geny/Writable
  public static #18= #17 of #11;          // StringWritable=class geny/Writable$StringWritable of class geny/Writable
SourceFile: "Writable.scala"
  ScalaInlineInfo: length = 0x1D (unknown attribute)
   01 01 00 05 00 17 00 16 01 00 0C 00 32 01 00 0F
   00 38 01 00 12 00 2C 01 00 20 00 21 01
  Scala: length = 0x0 (unknown attribute)

