Classfile /Users/mw/Projects/slang-braindump/.jar/jar11/assemble/slang-braindump/assemble/content/org/sireum/Asm_Ext$.class
  Last modified May 29, 2022; size 5929 bytes
  SHA-256 checksum f2fcbe96615ff429a955d799cce6f219603bb304c3aa0577f867d4445547b314
  Compiled from "Asm_Ext.scala"
public final class org.sireum.Asm_Ext$
  minor version: 0
  major version: 52
  flags: (0x0031) ACC_PUBLIC, ACC_FINAL, ACC_SUPER
  this_class: #2                          // org/sireum/Asm_Ext$
  super_class: #4                         // java/lang/Object
  interfaces: 0, fields: 2, methods: 13, attributes: 5
Constant pool:
    #1 = Utf8               org/sireum/Asm_Ext$
    #2 = Class              #1            // org/sireum/Asm_Ext$
    #3 = Utf8               java/lang/Object
    #4 = Class              #3            // java/lang/Object
    #5 = Utf8               Asm_Ext.scala
    #6 = Utf8               java/lang/invoke/MethodHandles$Lookup
    #7 = Class              #6            // java/lang/invoke/MethodHandles$Lookup
    #8 = Utf8               java/lang/invoke/MethodHandles
    #9 = Class              #8            // java/lang/invoke/MethodHandles
   #10 = Utf8               Lookup
   #11 = Utf8               org/sireum/Asm_Ext$NativeUtil$
   #12 = Class              #11           // org/sireum/Asm_Ext$NativeUtil$
   #13 = Utf8               org/sireum/Asm_Ext
   #14 = Class              #13           // org/sireum/Asm_Ext
   #15 = Utf8               NativeUtil$
   #16 = Utf8               org/sireum/Asm_Ext$NativeUtil$CVisitor
   #17 = Class              #16           // org/sireum/Asm_Ext$NativeUtil$CVisitor
   #18 = Utf8               CVisitor
   #19 = Utf8               org/sireum/Asm_Ext$ReleaseFence$
   #20 = Class              #19           // org/sireum/Asm_Ext$ReleaseFence$
   #21 = Utf8               ReleaseFence$
   #22 = Utf8               org/sireum/Asm_Ext$ReleaseFence$CVisitor
   #23 = Class              #22           // org/sireum/Asm_Ext$ReleaseFence$CVisitor
   #24 = Utf8               org/sireum/Asm_Ext$SecurityManager$
   #25 = Class              #24           // org/sireum/Asm_Ext$SecurityManager$
   #26 = Utf8               SecurityManager$
   #27 = Utf8               org/sireum/Asm_Ext$SecurityManager$CVisitor
   #28 = Class              #27           // org/sireum/Asm_Ext$SecurityManager$CVisitor
   #29 = Utf8               org/sireum/Os$Path
   #30 = Class              #29           // org/sireum/Os$Path
   #31 = Utf8               org/sireum/Os
   #32 = Class              #31           // org/sireum/Os
   #33 = Utf8               Path
   #34 = Utf8               MODULE$
   #35 = Utf8               Lorg/sireum/Asm_Ext$;
   #36 = Utf8               api
   #37 = Utf8               I
   #38 = Utf8               <clinit>
   #39 = Utf8               ()V
   #40 = Utf8               <init>
   #41 = NameAndType        #40:#39       // "<init>":()V
   #42 = Methodref          #2.#41        // org/sireum/Asm_Ext$."<init>":()V
   #43 = NameAndType        #34:#35       // MODULE$:Lorg/sireum/Asm_Ext$;
   #44 = Fieldref           #2.#43        // org/sireum/Asm_Ext$.MODULE$:Lorg/sireum/Asm_Ext$;
   #45 = Integer            589824
   #46 = NameAndType        #36:#37       // api:I
   #47 = Fieldref           #2.#46        // org/sireum/Asm_Ext$.api:I
   #48 = Utf8               ()I
   #49 = Utf8               this
   #50 = Utf8               eraseNonNative
   #51 = Utf8               (Lorg/sireum/Os$Path;)V
   #52 = Utf8               path
   #53 = Utf8               org/sireum/B$
   #54 = Class              #53           // org/sireum/B$
   #55 = Utf8               Lorg/sireum/B$;
   #56 = NameAndType        #34:#55       // MODULE$:Lorg/sireum/B$;
   #57 = Fieldref           #54.#56       // org/sireum/B$.MODULE$:Lorg/sireum/B$;
   #58 = Utf8               isDir
   #59 = Utf8               ()Z
   #60 = NameAndType        #58:#59       // isDir:()Z
   #61 = InterfaceMethodref #30.#60       // org/sireum/Os$Path.isDir:()Z
   #62 = Utf8               $4B
   #63 = Utf8               (Z)Z
   #64 = NameAndType        #62:#63       // $4B:(Z)Z
   #65 = Methodref          #54.#64       // org/sireum/B$.$4B:(Z)Z
   #66 = Utf8               value
   #67 = Utf8               ()Ljava/lang/String;
   #68 = NameAndType        #66:#67       // value:()Ljava/lang/String;
   #69 = InterfaceMethodref #30.#68       // org/sireum/Os$Path.value:()Ljava/lang/String;
   #70 = Utf8               java/lang/String
   #71 = Class              #70           // java/lang/String
   #72 = Utf8               java/nio/file/Paths
   #73 = Class              #72           // java/nio/file/Paths
   #74 = Utf8               get
   #75 = Utf8               (Ljava/lang/String;[Ljava/lang/String;)Ljava/nio/file/Path;
   #76 = NameAndType        #74:#75       // get:(Ljava/lang/String;[Ljava/lang/String;)Ljava/nio/file/Path;
   #77 = Methodref          #73.#76       // java/nio/file/Paths.get:(Ljava/lang/String;[Ljava/lang/String;)Ljava/nio/file/Path;
   #78 = Utf8               process$1
   #79 = Utf8               (Ljava/nio/file/Path;)V
   #80 = NameAndType        #78:#79       // process$1:(Ljava/nio/file/Path;)V
   #81 = Methodref          #2.#80        // org/sireum/Asm_Ext$.process$1:(Ljava/nio/file/Path;)V
   #82 = Utf8               java/nio/file/FileSystems
   #83 = Class              #82           // java/nio/file/FileSystems
   #84 = Utf8               newFileSystem
   #85 = Utf8               (Ljava/nio/file/Path;Ljava/lang/ClassLoader;)Ljava/nio/file/FileSystem;
   #86 = NameAndType        #84:#85       // newFileSystem:(Ljava/nio/file/Path;Ljava/lang/ClassLoader;)Ljava/nio/file/FileSystem;
   #87 = Methodref          #83.#86       // java/nio/file/FileSystems.newFileSystem:(Ljava/nio/file/Path;Ljava/lang/ClassLoader;)Ljava/nio/file/FileSystem;
   #88 = Utf8               java/nio/file/FileSystem
   #89 = Class              #88           // java/nio/file/FileSystem
   #90 = Utf8               getRootDirectories
   #91 = Utf8               ()Ljava/lang/Iterable;
   #92 = NameAndType        #90:#91       // getRootDirectories:()Ljava/lang/Iterable;
   #93 = Methodref          #89.#92       // java/nio/file/FileSystem.getRootDirectories:()Ljava/lang/Iterable;
   #94 = Utf8               (Ljava/lang/Object;)V
   #95 = MethodType         #94           //  (Ljava/lang/Object;)V
   #96 = Utf8               $anonfun$eraseNonNative$2
   #97 = NameAndType        #96:#79       // $anonfun$eraseNonNative$2:(Ljava/nio/file/Path;)V
   #98 = Methodref          #2.#97        // org/sireum/Asm_Ext$.$anonfun$eraseNonNative$2:(Ljava/nio/file/Path;)V
   #99 = MethodHandle       6:#98         // REF_invokeStatic org/sireum/Asm_Ext$.$anonfun$eraseNonNative$2:(Ljava/nio/file/Path;)V
  #100 = MethodType         #79           //  (Ljava/nio/file/Path;)V
  #101 = Integer            4
  #102 = Integer            1
  #103 = Utf8               java/lang/invoke/LambdaMetafactory
  #104 = Class              #103          // java/lang/invoke/LambdaMetafactory
  #105 = Utf8               altMetafactory
  #106 = Utf8               (Ljava/lang/invoke/MethodHandles$Lookup;Ljava/lang/String;Ljava/lang/invoke/MethodType;[Ljava/lang/Object;)Ljava/lang/invoke/CallSite;
  #107 = NameAndType        #105:#106     // altMetafactory:(Ljava/lang/invoke/MethodHandles$Lookup;Ljava/lang/String;Ljava/lang/invoke/MethodType;[Ljava/lang/Object;)Ljava/lang/invoke/CallSite;
  #108 = Methodref          #104.#107     // java/lang/invoke/LambdaMetafactory.altMetafactory:(Ljava/lang/invoke/MethodHandles$Lookup;Ljava/lang/String;Ljava/lang/invoke/MethodType;[Ljava/lang/Object;)Ljava/lang/invoke/CallSite;
  #109 = MethodHandle       6:#108        // REF_invokeStatic java/lang/invoke/LambdaMetafactory.altMetafactory:(Ljava/lang/invoke/MethodHandles$Lookup;Ljava/lang/String;Ljava/lang/invoke/MethodType;[Ljava/lang/Object;)Ljava/lang/invoke/CallSite;
  #110 = Utf8               accept
  #111 = Utf8               ()Ljava/util/function/Consumer;
  #112 = NameAndType        #110:#111     // accept:()Ljava/util/function/Consumer;
  #113 = InvokeDynamic      #0:#112       // #0:accept:()Ljava/util/function/Consumer;
  #114 = Utf8               java/lang/Iterable
  #115 = Class              #114          // java/lang/Iterable
  #116 = Utf8               forEach
  #117 = Utf8               (Ljava/util/function/Consumer;)V
  #118 = NameAndType        #116:#117     // forEach:(Ljava/util/function/Consumer;)V
  #119 = InterfaceMethodref #115.#118     // java/lang/Iterable.forEach:(Ljava/util/function/Consumer;)V
  #120 = Utf8               close
  #121 = NameAndType        #120:#39      // close:()V
  #122 = Methodref          #89.#121      // java/nio/file/FileSystem.close:()V
  #123 = Utf8               fs
  #124 = Utf8               Ljava/nio/file/FileSystem;
  #125 = Utf8               Lorg/sireum/Os$Path;
  #126 = Utf8               rewriteReleaseFence
  #127 = Utf8               org/sireum/String$
  #128 = Class              #127          // org/sireum/String$
  #129 = Utf8               Lorg/sireum/String$;
  #130 = NameAndType        #34:#129      // MODULE$:Lorg/sireum/String$;
  #131 = Fieldref           #128.#130     // org/sireum/String$.MODULE$:Lorg/sireum/String$;
  #132 = Utf8               scala
  #133 = String             #132          // scala
  #134 = Utf8               apply
  #135 = Utf8               (Ljava/lang/String;)Ljava/lang/String;
  #136 = NameAndType        #134:#135     // apply:(Ljava/lang/String;)Ljava/lang/String;
  #137 = Methodref          #128.#136     // org/sireum/String$.apply:(Ljava/lang/String;)Ljava/lang/String;
  #138 = Utf8               $div
  #139 = Utf8               (Ljava/lang/String;)Lorg/sireum/Os$Path;
  #140 = NameAndType        #138:#139     // $div:(Ljava/lang/String;)Lorg/sireum/Os$Path;
  #141 = InterfaceMethodref #30.#140      // org/sireum/Os$Path.$div:(Ljava/lang/String;)Lorg/sireum/Os$Path;
  #142 = Utf8               collection
  #143 = String             #142          // collection
  #144 = Utf8               immutable
  #145 = String             #144          // immutable
  #146 = Utf8               VM.class
  #147 = String             #146          // VM.class
  #148 = Utf8               process$2
  #149 = NameAndType        #148:#79      // process$2:(Ljava/nio/file/Path;)V
  #150 = Methodref          #2.#149       // org/sireum/Asm_Ext$.process$2:(Ljava/nio/file/Path;)V
  #151 = Utf8               runtime
  #152 = String             #151          // runtime
  #153 = Utf8               Statics.class
  #154 = String             #153          // Statics.class
  #155 = Utf8               /scala/collection/immutable/VM.class
  #156 = String             #155          // /scala/collection/immutable/VM.class
  #157 = Utf8               getPath
  #158 = NameAndType        #157:#75      // getPath:(Ljava/lang/String;[Ljava/lang/String;)Ljava/nio/file/Path;
  #159 = Methodref          #89.#158      // java/nio/file/FileSystem.getPath:(Ljava/lang/String;[Ljava/lang/String;)Ljava/nio/file/Path;
  #160 = Utf8               /scala/runtime/Statics.class
  #161 = String             #160          // /scala/runtime/Statics.class
  #162 = Utf8               rewriteSetSecurityManager
  #163 = Utf8               process$3
  #164 = NameAndType        #163:#79      // process$3:(Ljava/nio/file/Path;)V
  #165 = Methodref          #2.#164       // org/sireum/Asm_Ext$.process$3:(Ljava/nio/file/Path;)V
  #166 = Utf8               $anonfun$rewriteSetSecurityManager$2
  #167 = NameAndType        #166:#79      // $anonfun$rewriteSetSecurityManager$2:(Ljava/nio/file/Path;)V
  #168 = Methodref          #2.#167       // org/sireum/Asm_Ext$.$anonfun$rewriteSetSecurityManager$2:(Ljava/nio/file/Path;)V
  #169 = MethodHandle       6:#168        // REF_invokeStatic org/sireum/Asm_Ext$.$anonfun$rewriteSetSecurityManager$2:(Ljava/nio/file/Path;)V
  #170 = InvokeDynamic      #1:#112       // #1:accept:()Ljava/util/function/Consumer;
  #171 = Utf8               $anonfun$eraseNonNative$1
  #172 = Utf8               p
  #173 = Utf8               Ljava/nio/file/Path;
  #174 = Utf8               java/nio/file/LinkOption
  #175 = Class              #174          // java/nio/file/LinkOption
  #176 = Utf8               java/nio/file/Files
  #177 = Class              #176          // java/nio/file/Files
  #178 = Utf8               exists
  #179 = Utf8               (Ljava/nio/file/Path;[Ljava/nio/file/LinkOption;)Z
  #180 = NameAndType        #178:#179     // exists:(Ljava/nio/file/Path;[Ljava/nio/file/LinkOption;)Z
  #181 = Methodref          #177.#180     // java/nio/file/Files.exists:(Ljava/nio/file/Path;[Ljava/nio/file/LinkOption;)Z
  #182 = Utf8               isDirectory
  #183 = NameAndType        #182:#179     // isDirectory:(Ljava/nio/file/Path;[Ljava/nio/file/LinkOption;)Z
  #184 = Methodref          #177.#183     // java/nio/file/Files.isDirectory:(Ljava/nio/file/Path;[Ljava/nio/file/LinkOption;)Z
  #185 = Utf8               list
  #186 = Utf8               (Ljava/nio/file/Path;)Ljava/util/stream/Stream;
  #187 = NameAndType        #185:#186     // list:(Ljava/nio/file/Path;)Ljava/util/stream/Stream;
  #188 = Methodref          #177.#187     // java/nio/file/Files.list:(Ljava/nio/file/Path;)Ljava/util/stream/Stream;
  #189 = NameAndType        #171:#79      // $anonfun$eraseNonNative$1:(Ljava/nio/file/Path;)V
  #190 = Methodref          #2.#189       // org/sireum/Asm_Ext$.$anonfun$eraseNonNative$1:(Ljava/nio/file/Path;)V
  #191 = MethodHandle       6:#190        // REF_invokeStatic org/sireum/Asm_Ext$.$anonfun$eraseNonNative$1:(Ljava/nio/file/Path;)V
  #192 = InvokeDynamic      #2:#112       // #2:accept:()Ljava/util/function/Consumer;
  #193 = Utf8               java/util/stream/Stream
  #194 = Class              #193          // java/util/stream/Stream
  #195 = InterfaceMethodref #194.#118     // java/util/stream/Stream.forEach:(Ljava/util/function/Consumer;)V
  #196 = Utf8               java/nio/file/Path
  #197 = Class              #196          // java/nio/file/Path
  #198 = Utf8               toUri
  #199 = Utf8               ()Ljava/net/URI;
  #200 = NameAndType        #198:#199     // toUri:()Ljava/net/URI;
  #201 = InterfaceMethodref #197.#200     // java/nio/file/Path.toUri:()Ljava/net/URI;
  #202 = Utf8               java/net/URI
  #203 = Class              #202          // java/net/URI
  #204 = Utf8               toASCIIString
  #205 = NameAndType        #204:#67      // toASCIIString:()Ljava/lang/String;
  #206 = Methodref          #203.#205     // java/net/URI.toASCIIString:()Ljava/lang/String;
  #207 = Utf8               .class
  #208 = String             #207          // .class
  #209 = Utf8               endsWith
  #210 = Utf8               (Ljava/lang/String;)Z
  #211 = NameAndType        #209:#210     // endsWith:(Ljava/lang/String;)Z
  #212 = Methodref          #71.#211      // java/lang/String.endsWith:(Ljava/lang/String;)Z
  #213 = Utf8               java/nio/file/OpenOption
  #214 = Class              #213          // java/nio/file/OpenOption
  #215 = Utf8               newInputStream
  #216 = Utf8               (Ljava/nio/file/Path;[Ljava/nio/file/OpenOption;)Ljava/io/InputStream;
  #217 = NameAndType        #215:#216     // newInputStream:(Ljava/nio/file/Path;[Ljava/nio/file/OpenOption;)Ljava/io/InputStream;
  #218 = Methodref          #177.#217     // java/nio/file/Files.newInputStream:(Ljava/nio/file/Path;[Ljava/nio/file/OpenOption;)Ljava/io/InputStream;
  #219 = Utf8               org/objectweb/asm/ClassReader
  #220 = Class              #219          // org/objectweb/asm/ClassReader
  #221 = Utf8               (Ljava/io/InputStream;)V
  #222 = NameAndType        #40:#221      // "<init>":(Ljava/io/InputStream;)V
  #223 = Methodref          #220.#222     // org/objectweb/asm/ClassReader."<init>":(Ljava/io/InputStream;)V
  #224 = Utf8               org/objectweb/asm/ClassWriter
  #225 = Class              #224          // org/objectweb/asm/ClassWriter
  #226 = Utf8               (I)V
  #227 = NameAndType        #40:#226      // "<init>":(I)V
  #228 = Methodref          #225.#227     // org/objectweb/asm/ClassWriter."<init>":(I)V
  #229 = Utf8               (Lorg/objectweb/asm/ClassWriter;)V
  #230 = NameAndType        #40:#229      // "<init>":(Lorg/objectweb/asm/ClassWriter;)V
  #231 = Methodref          #17.#230      // org/sireum/Asm_Ext$NativeUtil$CVisitor."<init>":(Lorg/objectweb/asm/ClassWriter;)V
  #232 = Utf8               (Lorg/objectweb/asm/ClassVisitor;I)V
  #233 = NameAndType        #110:#232     // accept:(Lorg/objectweb/asm/ClassVisitor;I)V
  #234 = Methodref          #220.#233     // org/objectweb/asm/ClassReader.accept:(Lorg/objectweb/asm/ClassVisitor;I)V
  #235 = Utf8               java/io/InputStream
  #236 = Class              #235          // java/io/InputStream
  #237 = Methodref          #236.#121     // java/io/InputStream.close:()V
  #238 = Utf8               toByteArray
  #239 = Utf8               ()[B
  #240 = NameAndType        #238:#239     // toByteArray:()[B
  #241 = Methodref          #225.#240     // org/objectweb/asm/ClassWriter.toByteArray:()[B
  #242 = Utf8               write
  #243 = Utf8               (Ljava/nio/file/Path;[B[Ljava/nio/file/OpenOption;)Ljava/nio/file/Path;
  #244 = NameAndType        #242:#243     // write:(Ljava/nio/file/Path;[B[Ljava/nio/file/OpenOption;)Ljava/nio/file/Path;
  #245 = Methodref          #177.#244     // java/nio/file/Files.write:(Ljava/nio/file/Path;[B[Ljava/nio/file/OpenOption;)Ljava/nio/file/Path;
  #246 = Utf8               is
  #247 = Utf8               Ljava/io/InputStream;
  #248 = Utf8               cr
  #249 = Utf8               Lorg/objectweb/asm/ClassReader;
  #250 = Utf8               cw
  #251 = Utf8               Lorg/objectweb/asm/ClassWriter;
  #252 = Utf8               cv
  #253 = Utf8               Lorg/sireum/Asm_Ext$NativeUtil$CVisitor;
  #254 = Methodref          #23.#230      // org/sireum/Asm_Ext$ReleaseFence$CVisitor."<init>":(Lorg/objectweb/asm/ClassWriter;)V
  #255 = Utf8               Lorg/sireum/Asm_Ext$ReleaseFence$CVisitor;
  #256 = Utf8               $anonfun$rewriteSetSecurityManager$1
  #257 = NameAndType        #256:#79      // $anonfun$rewriteSetSecurityManager$1:(Ljava/nio/file/Path;)V
  #258 = Methodref          #2.#257       // org/sireum/Asm_Ext$.$anonfun$rewriteSetSecurityManager$1:(Ljava/nio/file/Path;)V
  #259 = MethodHandle       6:#258        // REF_invokeStatic org/sireum/Asm_Ext$.$anonfun$rewriteSetSecurityManager$1:(Ljava/nio/file/Path;)V
  #260 = InvokeDynamic      #3:#112       // #3:accept:()Ljava/util/function/Consumer;
  #261 = Methodref          #28.#230      // org/sireum/Asm_Ext$SecurityManager$CVisitor."<init>":(Lorg/objectweb/asm/ClassWriter;)V
  #262 = Utf8               Lorg/sireum/Asm_Ext$SecurityManager$CVisitor;
  #263 = Methodref          #4.#41        // java/lang/Object."<init>":()V
  #264 = Utf8               Code
  #265 = Utf8               LineNumberTable
  #266 = Utf8               LocalVariableTable
  #267 = Utf8               StackMapTable
  #268 = Utf8               MethodParameters
  #269 = Utf8               InnerClasses
  #270 = Utf8               SourceFile
  #271 = Utf8               BootstrapMethods
  #272 = Utf8               ScalaInlineInfo
  #273 = Utf8               Scala
{
  public static final org.sireum.Asm_Ext$ MODULE$;
    descriptor: Lorg/sireum/Asm_Ext$;
    flags: (0x0019) ACC_PUBLIC, ACC_STATIC, ACC_FINAL

  private static final int api;
    descriptor: I
    flags: (0x001a) ACC_PRIVATE, ACC_STATIC, ACC_FINAL

  public static {};
    descriptor: ()V
    flags: (0x0009) ACC_PUBLIC, ACC_STATIC
    Code:
      stack=2, locals=0, args_size=0
         0: new           #2                  // class org/sireum/Asm_Ext$
         3: dup
         4: invokespecial #42                 // Method "<init>":()V
         7: putstatic     #44                 // Field MODULE$:Lorg/sireum/Asm_Ext$;
        10: ldc           #45                 // int 589824
        12: putstatic     #47                 // Field api:I
        15: return
      LineNumberTable:
        line 33: 0
        line 34: 10
        line 33: 15

  public int api();
    descriptor: ()I
    flags: (0x0001) ACC_PUBLIC
    Code:
      stack=1, locals=1, args_size=1
         0: getstatic     #47                 // Field api:I
         3: ireturn
      LineNumberTable:
        line 34: 0
      LocalVariableTable:
        Start  Length  Slot  Name   Signature
            0       4     0  this   Lorg/sireum/Asm_Ext$;

  public void eraseNonNative(org.sireum.Os$Path);
    descriptor: (Lorg/sireum/Os$Path;)V
    flags: (0x0001) ACC_PUBLIC
    Code:
      stack=2, locals=3, args_size=2
         0: getstatic     #57                 // Field org/sireum/B$.MODULE$:Lorg/sireum/B$;
         3: aload_1
         4: invokeinterface #61,  1           // InterfaceMethod org/sireum/Os$Path.isDir:()Z
         9: invokevirtual #65                 // Method org/sireum/B$.$4B:(Z)Z
        12: ifeq          34
        15: aload_1
        16: invokeinterface #69,  1           // InterfaceMethod org/sireum/Os$Path.value:()Ljava/lang/String;
        21: iconst_0
        22: anewarray     #71                 // class java/lang/String
        25: invokestatic  #77                 // Method java/nio/file/Paths.get:(Ljava/lang/String;[Ljava/lang/String;)Ljava/nio/file/Path;
        28: invokestatic  #81                 // Method process$1:(Ljava/nio/file/Path;)V
        31: goto          70
        34: aload_1
        35: invokeinterface #69,  1           // InterfaceMethod org/sireum/Os$Path.value:()Ljava/lang/String;
        40: iconst_0
        41: anewarray     #71                 // class java/lang/String
        44: invokestatic  #77                 // Method java/nio/file/Paths.get:(Ljava/lang/String;[Ljava/lang/String;)Ljava/nio/file/Path;
        47: aconst_null
        48: invokestatic  #87                 // Method java/nio/file/FileSystems.newFileSystem:(Ljava/nio/file/Path;Ljava/lang/ClassLoader;)Ljava/nio/file/FileSystem;
        51: astore_2
        52: aload_2
        53: invokevirtual #93                 // Method java/nio/file/FileSystem.getRootDirectories:()Ljava/lang/Iterable;
        56: invokedynamic #113,  0            // InvokeDynamic #0:accept:()Ljava/util/function/Consumer;
        61: invokeinterface #119,  2          // InterfaceMethod java/lang/Iterable.forEach:(Ljava/util/function/Consumer;)V
        66: aload_2
        67: invokevirtual #122                // Method java/nio/file/FileSystem.close:()V
        70: return
      StackMapTable: number_of_entries = 2
        frame_type = 34 /* same */
        frame_type = 35 /* same */
      LineNumberTable:
        line 55: 0
        line 56: 15
        line 58: 34
        line 59: 52
        line 60: 66
      LocalVariableTable:
        Start  Length  Slot  Name   Signature
           52      18     2    fs   Ljava/nio/file/FileSystem;
            0      71     0  this   Lorg/sireum/Asm_Ext$;
            0      71     1  path   Lorg/sireum/Os$Path;
    MethodParameters:
      Name                           Flags
      path                           final

  public void rewriteReleaseFence(org.sireum.Os$Path);
    descriptor: (Lorg/sireum/Os$Path;)V
    flags: (0x0001) ACC_PUBLIC
    Code:
      stack=3, locals=3, args_size=2
         0: getstatic     #57                 // Field org/sireum/B$.MODULE$:Lorg/sireum/B$;
         3: aload_1
         4: invokeinterface #61,  1           // InterfaceMethod org/sireum/Os$Path.isDir:()Z
         9: invokevirtual #65                 // Method org/sireum/B$.$4B:(Z)Z
        12: ifeq          141
        15: aload_1
        16: getstatic     #131                // Field org/sireum/String$.MODULE$:Lorg/sireum/String$;
        19: ldc           #133                // String scala
        21: invokevirtual #137                // Method org/sireum/String$.apply:(Ljava/lang/String;)Ljava/lang/String;
        24: invokeinterface #141,  2          // InterfaceMethod org/sireum/Os$Path.$div:(Ljava/lang/String;)Lorg/sireum/Os$Path;
        29: getstatic     #131                // Field org/sireum/String$.MODULE$:Lorg/sireum/String$;
        32: ldc           #143                // String collection
        34: invokevirtual #137                // Method org/sireum/String$.apply:(Ljava/lang/String;)Ljava/lang/String;
        37: invokeinterface #141,  2          // InterfaceMethod org/sireum/Os$Path.$div:(Ljava/lang/String;)Lorg/sireum/Os$Path;
        42: getstatic     #131                // Field org/sireum/String$.MODULE$:Lorg/sireum/String$;
        45: ldc           #145                // String immutable
        47: invokevirtual #137                // Method org/sireum/String$.apply:(Ljava/lang/String;)Ljava/lang/String;
        50: invokeinterface #141,  2          // InterfaceMethod org/sireum/Os$Path.$div:(Ljava/lang/String;)Lorg/sireum/Os$Path;
        55: getstatic     #131                // Field org/sireum/String$.MODULE$:Lorg/sireum/String$;
        58: ldc           #147                // String VM.class
        60: invokevirtual #137                // Method org/sireum/String$.apply:(Ljava/lang/String;)Ljava/lang/String;
        63: invokeinterface #141,  2          // InterfaceMethod org/sireum/Os$Path.$div:(Ljava/lang/String;)Lorg/sireum/Os$Path;
        68: invokeinterface #69,  1           // InterfaceMethod org/sireum/Os$Path.value:()Ljava/lang/String;
        73: iconst_0
        74: anewarray     #71                 // class java/lang/String
        77: invokestatic  #77                 // Method java/nio/file/Paths.get:(Ljava/lang/String;[Ljava/lang/String;)Ljava/nio/file/Path;
        80: invokestatic  #150                // Method process$2:(Ljava/nio/file/Path;)V
        83: aload_1
        84: getstatic     #131                // Field org/sireum/String$.MODULE$:Lorg/sireum/String$;
        87: ldc           #133                // String scala
        89: invokevirtual #137                // Method org/sireum/String$.apply:(Ljava/lang/String;)Ljava/lang/String;
        92: invokeinterface #141,  2          // InterfaceMethod org/sireum/Os$Path.$div:(Ljava/lang/String;)Lorg/sireum/Os$Path;
        97: getstatic     #131                // Field org/sireum/String$.MODULE$:Lorg/sireum/String$;
       100: ldc           #152                // String runtime
       102: invokevirtual #137                // Method org/sireum/String$.apply:(Ljava/lang/String;)Ljava/lang/String;
       105: invokeinterface #141,  2          // InterfaceMethod org/sireum/Os$Path.$div:(Ljava/lang/String;)Lorg/sireum/Os$Path;
       110: getstatic     #131                // Field org/sireum/String$.MODULE$:Lorg/sireum/String$;
       113: ldc           #154                // String Statics.class
       115: invokevirtual #137                // Method org/sireum/String$.apply:(Ljava/lang/String;)Ljava/lang/String;
       118: invokeinterface #141,  2          // InterfaceMethod org/sireum/Os$Path.$div:(Ljava/lang/String;)Lorg/sireum/Os$Path;
       123: invokeinterface #69,  1           // InterfaceMethod org/sireum/Os$Path.value:()Ljava/lang/String;
       128: iconst_0
       129: anewarray     #71                 // class java/lang/String
       132: invokestatic  #77                 // Method java/nio/file/Paths.get:(Ljava/lang/String;[Ljava/lang/String;)Ljava/nio/file/Path;
       135: invokestatic  #150                // Method process$2:(Ljava/nio/file/Path;)V
       138: goto          189
       141: aload_1
       142: invokeinterface #69,  1           // InterfaceMethod org/sireum/Os$Path.value:()Ljava/lang/String;
       147: iconst_0
       148: anewarray     #71                 // class java/lang/String
       151: invokestatic  #77                 // Method java/nio/file/Paths.get:(Ljava/lang/String;[Ljava/lang/String;)Ljava/nio/file/Path;
       154: aconst_null
       155: invokestatic  #87                 // Method java/nio/file/FileSystems.newFileSystem:(Ljava/nio/file/Path;Ljava/lang/ClassLoader;)Ljava/nio/file/FileSystem;
       158: astore_2
       159: aload_2
       160: ldc           #156                // String /scala/collection/immutable/VM.class
       162: iconst_0
       163: anewarray     #71                 // class java/lang/String
       166: invokevirtual #159                // Method java/nio/file/FileSystem.getPath:(Ljava/lang/String;[Ljava/lang/String;)Ljava/nio/file/Path;
       169: invokestatic  #150                // Method process$2:(Ljava/nio/file/Path;)V
       172: aload_2
       173: ldc           #161                // String /scala/runtime/Statics.class
       175: iconst_0
       176: anewarray     #71                 // class java/lang/String
       179: invokevirtual #159                // Method java/nio/file/FileSystem.getPath:(Ljava/lang/String;[Ljava/lang/String;)Ljava/nio/file/Path;
       182: invokestatic  #150                // Method process$2:(Ljava/nio/file/Path;)V
       185: aload_2
       186: invokevirtual #122                // Method java/nio/file/FileSystem.close:()V
       189: return
      StackMapTable: number_of_entries = 2
        frame_type = 251 /* same_frame_extended */
          offset_delta = 141
        frame_type = 47 /* same */
      LineNumberTable:
        line 79: 0
        line 80: 15
        line 81: 83
        line 83: 141
        line 84: 159
        line 85: 172
        line 86: 185
      LocalVariableTable:
        Start  Length  Slot  Name   Signature
          159      30     2    fs   Ljava/nio/file/FileSystem;
            0     190     0  this   Lorg/sireum/Asm_Ext$;
            0     190     1  path   Lorg/sireum/Os$Path;
    MethodParameters:
      Name                           Flags
      path                           final

  public void rewriteSetSecurityManager(org.sireum.Os$Path);
    descriptor: (Lorg/sireum/Os$Path;)V
    flags: (0x0001) ACC_PUBLIC
    Code:
      stack=2, locals=3, args_size=2
         0: getstatic     #57                 // Field org/sireum/B$.MODULE$:Lorg/sireum/B$;
         3: aload_1
         4: invokeinterface #61,  1           // InterfaceMethod org/sireum/Os$Path.isDir:()Z
         9: invokevirtual #65                 // Method org/sireum/B$.$4B:(Z)Z
        12: ifeq          34
        15: aload_1
        16: invokeinterface #69,  1           // InterfaceMethod org/sireum/Os$Path.value:()Ljava/lang/String;
        21: iconst_0
        22: anewarray     #71                 // class java/lang/String
        25: invokestatic  #77                 // Method java/nio/file/Paths.get:(Ljava/lang/String;[Ljava/lang/String;)Ljava/nio/file/Path;
        28: invokestatic  #165                // Method process$3:(Ljava/nio/file/Path;)V
        31: goto          70
        34: aload_1
        35: invokeinterface #69,  1           // InterfaceMethod org/sireum/Os$Path.value:()Ljava/lang/String;
        40: iconst_0
        41: anewarray     #71                 // class java/lang/String
        44: invokestatic  #77                 // Method java/nio/file/Paths.get:(Ljava/lang/String;[Ljava/lang/String;)Ljava/nio/file/Path;
        47: aconst_null
        48: invokestatic  #87                 // Method java/nio/file/FileSystems.newFileSystem:(Ljava/nio/file/Path;Ljava/lang/ClassLoader;)Ljava/nio/file/FileSystem;
        51: astore_2
        52: aload_2
        53: invokevirtual #93                 // Method java/nio/file/FileSystem.getRootDirectories:()Ljava/lang/Iterable;
        56: invokedynamic #170,  0            // InvokeDynamic #1:accept:()Ljava/util/function/Consumer;
        61: invokeinterface #119,  2          // InterfaceMethod java/lang/Iterable.forEach:(Ljava/util/function/Consumer;)V
        66: aload_2
        67: invokevirtual #122                // Method java/nio/file/FileSystem.close:()V
        70: return
      StackMapTable: number_of_entries = 2
        frame_type = 34 /* same */
        frame_type = 35 /* same */
      LineNumberTable:
        line 110: 0
        line 111: 15
        line 113: 34
        line 114: 52
        line 115: 66
      LocalVariableTable:
        Start  Length  Slot  Name   Signature
           52      18     2    fs   Ljava/nio/file/FileSystem;
            0      71     0  this   Lorg/sireum/Asm_Ext$;
            0      71     1  path   Lorg/sireum/Os$Path;
    MethodParameters:
      Name                           Flags
      path                           final

  public static final void $anonfun$eraseNonNative$1(java.nio.file.Path);
    descriptor: (Ljava/nio/file/Path;)V
    flags: (0x1019) ACC_PUBLIC, ACC_STATIC, ACC_FINAL, ACC_SYNTHETIC
    Code:
      stack=1, locals=1, args_size=1
         0: aload_0
         1: invokestatic  #81                 // Method process$1:(Ljava/nio/file/Path;)V
         4: return
      LineNumberTable:
        line 43: 0
      LocalVariableTable:
        Start  Length  Slot  Name   Signature
            0       5     0     p   Ljava/nio/file/Path;
    MethodParameters:
      Name                           Flags
      p                              final

  private static final void process$1(java.nio.file.Path);
    descriptor: (Ljava/nio/file/Path;)V
    flags: (0x001a) ACC_PRIVATE, ACC_STATIC, ACC_FINAL
    Code:
      stack=3, locals=5, args_size=1
         0: aload_0
         1: iconst_0
         2: anewarray     #175                // class java/nio/file/LinkOption
         5: invokestatic  #181                // Method java/nio/file/Files.exists:(Ljava/nio/file/Path;[Ljava/nio/file/LinkOption;)Z
         8: ifne          12
        11: return
        12: aload_0
        13: iconst_0
        14: anewarray     #175                // class java/nio/file/LinkOption
        17: invokestatic  #184                // Method java/nio/file/Files.isDirectory:(Ljava/nio/file/Path;[Ljava/nio/file/LinkOption;)Z
        20: ifeq          40
        23: aload_0
        24: invokestatic  #188                // Method java/nio/file/Files.list:(Ljava/nio/file/Path;)Ljava/util/stream/Stream;
        27: invokedynamic #192,  0            // InvokeDynamic #2:accept:()Ljava/util/function/Consumer;
        32: invokeinterface #195,  2          // InterfaceMethod java/util/stream/Stream.forEach:(Ljava/util/function/Consumer;)V
        37: goto          121
        40: aload_0
        41: invokeinterface #201,  1          // InterfaceMethod java/nio/file/Path.toUri:()Ljava/net/URI;
        46: invokevirtual #206                // Method java/net/URI.toASCIIString:()Ljava/lang/String;
        49: ldc           #208                // String .class
        51: invokevirtual #212                // Method java/lang/String.endsWith:(Ljava/lang/String;)Z
        54: ifeq          121
        57: aload_0
        58: iconst_0
        59: anewarray     #214                // class java/nio/file/OpenOption
        62: invokestatic  #218                // Method java/nio/file/Files.newInputStream:(Ljava/nio/file/Path;[Ljava/nio/file/OpenOption;)Ljava/io/InputStream;
        65: astore_1
        66: new           #220                // class org/objectweb/asm/ClassReader
        69: dup
        70: aload_1
        71: invokespecial #223                // Method org/objectweb/asm/ClassReader."<init>":(Ljava/io/InputStream;)V
        74: astore_2
        75: new           #225                // class org/objectweb/asm/ClassWriter
        78: dup
        79: iconst_0
        80: invokespecial #228                // Method org/objectweb/asm/ClassWriter."<init>":(I)V
        83: astore_3
        84: new           #17                 // class org/sireum/Asm_Ext$NativeUtil$CVisitor
        87: dup
        88: aload_3
        89: invokespecial #231                // Method org/sireum/Asm_Ext$NativeUtil$CVisitor."<init>":(Lorg/objectweb/asm/ClassWriter;)V
        92: astore        4
        94: aload_2
        95: aload         4
        97: iconst_0
        98: invokevirtual #234                // Method org/objectweb/asm/ClassReader.accept:(Lorg/objectweb/asm/ClassVisitor;I)V
       101: aload_1
       102: invokevirtual #237                // Method java/io/InputStream.close:()V
       105: aload_0
       106: aload_3
       107: invokevirtual #241                // Method org/objectweb/asm/ClassWriter.toByteArray:()[B
       110: iconst_0
       111: anewarray     #214                // class java/nio/file/OpenOption
       114: invokestatic  #245                // Method java/nio/file/Files.write:(Ljava/nio/file/Path;[B[Ljava/nio/file/OpenOption;)Ljava/nio/file/Path;
       117: pop
       118: goto          121
       121: return
      StackMapTable: number_of_entries = 3
        frame_type = 12 /* same */
        frame_type = 27 /* same */
        frame_type = 251 /* same_frame_extended */
          offset_delta = 80
      LineNumberTable:
        line 39: 0
        line 40: 11
        line 42: 12
        line 43: 23
        line 44: 40
        line 45: 57
        line 46: 66
        line 47: 75
        line 48: 84
        line 49: 94
        line 50: 101
        line 51: 105
        line 44: 121
      LocalVariableTable:
        Start  Length  Slot  Name   Signature
           66      52     1    is   Ljava/io/InputStream;
           75      43     2    cr   Lorg/objectweb/asm/ClassReader;
           84      34     3    cw   Lorg/objectweb/asm/ClassWriter;
           94      24     4    cv   Lorg/sireum/Asm_Ext$NativeUtil$CVisitor;
            0     122     0     p   Ljava/nio/file/Path;
    MethodParameters:
      Name                           Flags
      p                              final

  public static final void $anonfun$eraseNonNative$2(java.nio.file.Path);
    descriptor: (Ljava/nio/file/Path;)V
    flags: (0x1019) ACC_PUBLIC, ACC_STATIC, ACC_FINAL, ACC_SYNTHETIC
    Code:
      stack=1, locals=1, args_size=1
         0: aload_0
         1: invokestatic  #81                 // Method process$1:(Ljava/nio/file/Path;)V
         4: return
      LineNumberTable:
        line 59: 0
      LocalVariableTable:
        Start  Length  Slot  Name   Signature
            0       5     0     p   Ljava/nio/file/Path;
    MethodParameters:
      Name                           Flags
      p                              final

  private static final void process$2(java.nio.file.Path);
    descriptor: (Ljava/nio/file/Path;)V
    flags: (0x001a) ACC_PRIVATE, ACC_STATIC, ACC_FINAL
    Code:
      stack=3, locals=5, args_size=1
         0: aload_0
         1: iconst_0
         2: anewarray     #175                // class java/nio/file/LinkOption
         5: invokestatic  #181                // Method java/nio/file/Files.exists:(Ljava/nio/file/Path;[Ljava/nio/file/LinkOption;)Z
         8: ifne          12
        11: return
        12: aload_0
        13: iconst_0
        14: anewarray     #214                // class java/nio/file/OpenOption
        17: invokestatic  #218                // Method java/nio/file/Files.newInputStream:(Ljava/nio/file/Path;[Ljava/nio/file/OpenOption;)Ljava/io/InputStream;
        20: astore_1
        21: new           #220                // class org/objectweb/asm/ClassReader
        24: dup
        25: aload_1
        26: invokespecial #223                // Method org/objectweb/asm/ClassReader."<init>":(Ljava/io/InputStream;)V
        29: astore_2
        30: new           #225                // class org/objectweb/asm/ClassWriter
        33: dup
        34: iconst_3
        35: invokespecial #228                // Method org/objectweb/asm/ClassWriter."<init>":(I)V
        38: astore_3
        39: new           #23                 // class org/sireum/Asm_Ext$ReleaseFence$CVisitor
        42: dup
        43: aload_3
        44: invokespecial #254                // Method org/sireum/Asm_Ext$ReleaseFence$CVisitor."<init>":(Lorg/objectweb/asm/ClassWriter;)V
        47: astore        4
        49: aload_2
        50: aload         4
        52: iconst_4
        53: invokevirtual #234                // Method org/objectweb/asm/ClassReader.accept:(Lorg/objectweb/asm/ClassVisitor;I)V
        56: aload_1
        57: invokevirtual #237                // Method java/io/InputStream.close:()V
        60: aload_0
        61: aload_3
        62: invokevirtual #241                // Method org/objectweb/asm/ClassWriter.toByteArray:()[B
        65: iconst_0
        66: anewarray     #214                // class java/nio/file/OpenOption
        69: invokestatic  #245                // Method java/nio/file/Files.write:(Ljava/nio/file/Path;[B[Ljava/nio/file/OpenOption;)Ljava/nio/file/Path;
        72: pop
        73: return
      StackMapTable: number_of_entries = 1
        frame_type = 12 /* same */
      LineNumberTable:
        line 67: 0
        line 68: 11
        line 70: 12
        line 71: 21
        line 72: 30
        line 73: 39
        line 74: 49
        line 75: 56
        line 76: 60
      LocalVariableTable:
        Start  Length  Slot  Name   Signature
           21      52     1    is   Ljava/io/InputStream;
           30      43     2    cr   Lorg/objectweb/asm/ClassReader;
           39      34     3    cw   Lorg/objectweb/asm/ClassWriter;
           49      24     4    cv   Lorg/sireum/Asm_Ext$ReleaseFence$CVisitor;
            0      74     0     p   Ljava/nio/file/Path;
    MethodParameters:
      Name                           Flags
      p                              final

  public static final void $anonfun$rewriteSetSecurityManager$1(java.nio.file.Path);
    descriptor: (Ljava/nio/file/Path;)V
    flags: (0x1019) ACC_PUBLIC, ACC_STATIC, ACC_FINAL, ACC_SYNTHETIC
    Code:
      stack=1, locals=1, args_size=1
         0: aload_0
         1: invokestatic  #165                // Method process$3:(Ljava/nio/file/Path;)V
         4: return
      LineNumberTable:
        line 98: 0
      LocalVariableTable:
        Start  Length  Slot  Name   Signature
            0       5     0     p   Ljava/nio/file/Path;
    MethodParameters:
      Name                           Flags
      p                              final

  private static final void process$3(java.nio.file.Path);
    descriptor: (Ljava/nio/file/Path;)V
    flags: (0x001a) ACC_PRIVATE, ACC_STATIC, ACC_FINAL
    Code:
      stack=3, locals=5, args_size=1
         0: aload_0
         1: iconst_0
         2: anewarray     #175                // class java/nio/file/LinkOption
         5: invokestatic  #181                // Method java/nio/file/Files.exists:(Ljava/nio/file/Path;[Ljava/nio/file/LinkOption;)Z
         8: ifne          12
        11: return
        12: aload_0
        13: iconst_0
        14: anewarray     #175                // class java/nio/file/LinkOption
        17: invokestatic  #184                // Method java/nio/file/Files.isDirectory:(Ljava/nio/file/Path;[Ljava/nio/file/LinkOption;)Z
        20: ifeq          40
        23: aload_0
        24: invokestatic  #188                // Method java/nio/file/Files.list:(Ljava/nio/file/Path;)Ljava/util/stream/Stream;
        27: invokedynamic #260,  0            // InvokeDynamic #3:accept:()Ljava/util/function/Consumer;
        32: invokeinterface #195,  2          // InterfaceMethod java/util/stream/Stream.forEach:(Ljava/util/function/Consumer;)V
        37: goto          121
        40: aload_0
        41: invokeinterface #201,  1          // InterfaceMethod java/nio/file/Path.toUri:()Ljava/net/URI;
        46: invokevirtual #206                // Method java/net/URI.toASCIIString:()Ljava/lang/String;
        49: ldc           #208                // String .class
        51: invokevirtual #212                // Method java/lang/String.endsWith:(Ljava/lang/String;)Z
        54: ifeq          121
        57: aload_0
        58: iconst_0
        59: anewarray     #214                // class java/nio/file/OpenOption
        62: invokestatic  #218                // Method java/nio/file/Files.newInputStream:(Ljava/nio/file/Path;[Ljava/nio/file/OpenOption;)Ljava/io/InputStream;
        65: astore_1
        66: new           #220                // class org/objectweb/asm/ClassReader
        69: dup
        70: aload_1
        71: invokespecial #223                // Method org/objectweb/asm/ClassReader."<init>":(Ljava/io/InputStream;)V
        74: astore_2
        75: new           #225                // class org/objectweb/asm/ClassWriter
        78: dup
        79: iconst_0
        80: invokespecial #228                // Method org/objectweb/asm/ClassWriter."<init>":(I)V
        83: astore_3
        84: new           #28                 // class org/sireum/Asm_Ext$SecurityManager$CVisitor
        87: dup
        88: aload_3
        89: invokespecial #261                // Method org/sireum/Asm_Ext$SecurityManager$CVisitor."<init>":(Lorg/objectweb/asm/ClassWriter;)V
        92: astore        4
        94: aload_2
        95: aload         4
        97: iconst_0
        98: invokevirtual #234                // Method org/objectweb/asm/ClassReader.accept:(Lorg/objectweb/asm/ClassVisitor;I)V
       101: aload_1
       102: invokevirtual #237                // Method java/io/InputStream.close:()V
       105: aload_0
       106: aload_3
       107: invokevirtual #241                // Method org/objectweb/asm/ClassWriter.toByteArray:()[B
       110: iconst_0
       111: anewarray     #214                // class java/nio/file/OpenOption
       114: invokestatic  #245                // Method java/nio/file/Files.write:(Ljava/nio/file/Path;[B[Ljava/nio/file/OpenOption;)Ljava/nio/file/Path;
       117: pop
       118: goto          121
       121: return
      StackMapTable: number_of_entries = 3
        frame_type = 12 /* same */
        frame_type = 27 /* same */
        frame_type = 251 /* same_frame_extended */
          offset_delta = 80
      LineNumberTable:
        line 94: 0
        line 95: 11
        line 97: 12
        line 98: 23
        line 99: 40
        line 100: 57
        line 101: 66
        line 102: 75
        line 103: 84
        line 104: 94
        line 105: 101
        line 106: 105
        line 99: 121
      LocalVariableTable:
        Start  Length  Slot  Name   Signature
           66      52     1    is   Ljava/io/InputStream;
           75      43     2    cr   Lorg/objectweb/asm/ClassReader;
           84      34     3    cw   Lorg/objectweb/asm/ClassWriter;
           94      24     4    cv   Lorg/sireum/Asm_Ext$SecurityManager$CVisitor;
            0     122     0     p   Ljava/nio/file/Path;
    MethodParameters:
      Name                           Flags
      p                              final

  public static final void $anonfun$rewriteSetSecurityManager$2(java.nio.file.Path);
    descriptor: (Ljava/nio/file/Path;)V
    flags: (0x1019) ACC_PUBLIC, ACC_STATIC, ACC_FINAL, ACC_SYNTHETIC
    Code:
      stack=1, locals=1, args_size=1
         0: aload_0
         1: invokestatic  #165                // Method process$3:(Ljava/nio/file/Path;)V
         4: return
      LineNumberTable:
        line 114: 0
      LocalVariableTable:
        Start  Length  Slot  Name   Signature
            0       5     0     p   Ljava/nio/file/Path;
    MethodParameters:
      Name                           Flags
      p                              final

  private org.sireum.Asm_Ext$();
    descriptor: ()V
    flags: (0x0002) ACC_PRIVATE
    Code:
      stack=1, locals=1, args_size=1
         0: aload_0
         1: invokespecial #263                // Method java/lang/Object."<init>":()V
         4: return
      LineNumberTable:
        line 33: 0
      LocalVariableTable:
        Start  Length  Slot  Name   Signature
            0       5     0  this   Lorg/sireum/Asm_Ext$;
}
InnerClasses:
  public static final #10= #7 of #9;      // Lookup=class java/lang/invoke/MethodHandles$Lookup of class java/lang/invoke/MethodHandles
  public static #15= #12 of #14;          // NativeUtil$=class org/sireum/Asm_Ext$NativeUtil$ of class org/sireum/Asm_Ext
  public static #18= #17 of #12;          // CVisitor=class org/sireum/Asm_Ext$NativeUtil$CVisitor of class org/sireum/Asm_Ext$NativeUtil$
  public static #21= #20 of #14;          // ReleaseFence$=class org/sireum/Asm_Ext$ReleaseFence$ of class org/sireum/Asm_Ext
  public static #18= #23 of #20;          // CVisitor=class org/sireum/Asm_Ext$ReleaseFence$CVisitor of class org/sireum/Asm_Ext$ReleaseFence$
  public static #26= #25 of #14;          // SecurityManager$=class org/sireum/Asm_Ext$SecurityManager$ of class org/sireum/Asm_Ext
  public static #18= #28 of #25;          // CVisitor=class org/sireum/Asm_Ext$SecurityManager$CVisitor of class org/sireum/Asm_Ext$SecurityManager$
  public static #33= #30 of #32;          // Path=class org/sireum/Os$Path of class org/sireum/Os
SourceFile: "Asm_Ext.scala"
BootstrapMethods:
  0: #109 REF_invokeStatic java/lang/invoke/LambdaMetafactory.altMetafactory:(Ljava/lang/invoke/MethodHandles$Lookup;Ljava/lang/String;Ljava/lang/invoke/MethodType;[Ljava/lang/Object;)Ljava/lang/invoke/CallSite;
    Method arguments:
      #95 (Ljava/lang/Object;)V
      #99 REF_invokeStatic org/sireum/Asm_Ext$.$anonfun$eraseNonNative$2:(Ljava/nio/file/Path;)V
      #100 (Ljava/nio/file/Path;)V
      #101 4
      #102 1
      #100 (Ljava/nio/file/Path;)V
  1: #109 REF_invokeStatic java/lang/invoke/LambdaMetafactory.altMetafactory:(Ljava/lang/invoke/MethodHandles$Lookup;Ljava/lang/String;Ljava/lang/invoke/MethodType;[Ljava/lang/Object;)Ljava/lang/invoke/CallSite;
    Method arguments:
      #95 (Ljava/lang/Object;)V
      #169 REF_invokeStatic org/sireum/Asm_Ext$.$anonfun$rewriteSetSecurityManager$2:(Ljava/nio/file/Path;)V
      #100 (Ljava/nio/file/Path;)V
      #101 4
      #102 1
      #100 (Ljava/nio/file/Path;)V
  2: #109 REF_invokeStatic java/lang/invoke/LambdaMetafactory.altMetafactory:(Ljava/lang/invoke/MethodHandles$Lookup;Ljava/lang/String;Ljava/lang/invoke/MethodType;[Ljava/lang/Object;)Ljava/lang/invoke/CallSite;
    Method arguments:
      #95 (Ljava/lang/Object;)V
      #191 REF_invokeStatic org/sireum/Asm_Ext$.$anonfun$eraseNonNative$1:(Ljava/nio/file/Path;)V
      #100 (Ljava/nio/file/Path;)V
      #101 4
      #102 1
      #100 (Ljava/nio/file/Path;)V
  3: #109 REF_invokeStatic java/lang/invoke/LambdaMetafactory.altMetafactory:(Ljava/lang/invoke/MethodHandles$Lookup;Ljava/lang/String;Ljava/lang/invoke/MethodType;[Ljava/lang/Object;)Ljava/lang/invoke/CallSite;
    Method arguments:
      #95 (Ljava/lang/Object;)V
      #259 REF_invokeStatic org/sireum/Asm_Ext$.$anonfun$rewriteSetSecurityManager$1:(Ljava/nio/file/Path;)V
      #100 (Ljava/nio/file/Path;)V
      #101 4
      #102 1
      #100 (Ljava/nio/file/Path;)V
  ScalaInlineInfo: length = 0x40 (unknown attribute)
   01 01 00 0C 00 AB 00 4F 01 00 60 00 4F 01 01 00
   00 4F 01 00 A6 00 4F 01 00 28 00 27 01 00 24 00
   30 01 00 32 00 33 01 00 4E 00 4F 01 00 94 00 4F
   01 00 A3 00 4F 01 00 7E 00 33 01 00 A2 00 33 01

  Scala: length = 0x0 (unknown attribute)

