Classfile /Users/mw/Projects/slang-braindump/.jar/jar11/assemble/slang-braindump/assemble/content/org/sireum/B$.class
  Last modified May 29, 2022; size 5655 bytes
  SHA-256 checksum e586dc92b17c89853fb600c2aabb85d7f3abfac4a468b2978345a9e804ca661f
  Compiled from "B.scala"
public final class org.sireum.B$
  minor version: 0
  major version: 52
  flags: (0x0031) ACC_PUBLIC, ACC_FINAL, ACC_SUPER
  this_class: #2                          // org/sireum/B$
  super_class: #4                         // java/lang/Object
  interfaces: 0, fields: 3, methods: 29, attributes: 5
Constant pool:
    #1 = Utf8               org/sireum/B$
    #2 = Class              #1            // org/sireum/B$
    #3 = Utf8               java/lang/Object
    #4 = Class              #3            // java/lang/Object
    #5 = Utf8               B.scala
    #6 = Utf8               java/lang/invoke/MethodHandles$Lookup
    #7 = Class              #6            // java/lang/invoke/MethodHandles$Lookup
    #8 = Utf8               java/lang/invoke/MethodHandles
    #9 = Class              #8            // java/lang/invoke/MethodHandles
   #10 = Utf8               Lookup
   #11 = Utf8               org/sireum/B$Boxer$
   #12 = Class              #11           // org/sireum/B$Boxer$
   #13 = Utf8               org/sireum/B
   #14 = Class              #13           // org/sireum/B
   #15 = Utf8               Boxer$
   #16 = Utf8               MODULE$
   #17 = Utf8               Lorg/sireum/B$;
   #18 = Utf8               T
   #19 = Utf8               Z
   #20 = Utf8               F
   #21 = Utf8               <clinit>
   #22 = Utf8               ()V
   #23 = Utf8               <init>
   #24 = NameAndType        #23:#22       // "<init>":()V
   #25 = Methodref          #2.#24        // org/sireum/B$."<init>":()V
   #26 = NameAndType        #16:#17       // MODULE$:Lorg/sireum/B$;
   #27 = Fieldref           #2.#26        // org/sireum/B$.MODULE$:Lorg/sireum/B$;
   #28 = NameAndType        #18:#19       // T:Z
   #29 = Fieldref           #2.#28        // org/sireum/B$.T:Z
   #30 = NameAndType        #20:#19       // F:Z
   #31 = Fieldref           #2.#30        // org/sireum/B$.F:Z
   #32 = Utf8               ()Z
   #33 = Utf8               this
   #34 = Utf8               random
   #35 = Utf8               java/util/Random
   #36 = Class              #35           // java/util/Random
   #37 = Methodref          #36.#24       // java/util/Random."<init>":()V
   #38 = Utf8               nextBoolean
   #39 = NameAndType        #38:#32       // nextBoolean:()Z
   #40 = Methodref          #36.#39       // java/util/Random.nextBoolean:()Z
   #41 = Utf8               apply
   #42 = Utf8               (Z)Z
   #43 = NameAndType        #41:#42       // apply:(Z)Z
   #44 = Methodref          #2.#43        // org/sireum/B$.apply:(Z)Z
   #45 = Utf8               unapply
   #46 = Utf8               (Z)Lscala/Option;
   #47 = Utf8               (Z)Lscala/Option<Ljava/lang/Object;>;
   #48 = Utf8               b
   #49 = Utf8               scala/Some
   #50 = Class              #49           // scala/Some
   #51 = Utf8               scala/runtime/BoxesRunTime
   #52 = Class              #51           // scala/runtime/BoxesRunTime
   #53 = Utf8               boxToBoolean
   #54 = Utf8               (Z)Ljava/lang/Boolean;
   #55 = NameAndType        #53:#54       // boxToBoolean:(Z)Ljava/lang/Boolean;
   #56 = Methodref          #52.#55       // scala/runtime/BoxesRunTime.boxToBoolean:(Z)Ljava/lang/Boolean;
   #57 = Utf8               (Ljava/lang/Object;)V
   #58 = NameAndType        #23:#57       // "<init>":(Ljava/lang/Object;)V
   #59 = Methodref          #50.#58       // scala/Some."<init>":(Ljava/lang/Object;)V
   #60 = NameAndType        #18:#32       // T:()Z
   #61 = Methodref          #2.#60        // org/sireum/B$.T:()Z
   #62 = NameAndType        #20:#32       // F:()Z
   #63 = Methodref          #2.#62        // org/sireum/B$.F:()Z
   #64 = Utf8               $4B
   #65 = Utf8               $amp$extension
   #66 = Utf8               (ZZ)Z
   #67 = Utf8               $this
   #68 = Utf8               other
   #69 = Utf8               $bar$extension
   #70 = Utf8               $bar$up$extension
   #71 = Utf8               $amp$amp$extension
   #72 = Utf8               (ZLscala/Function0;)Z
   #73 = Utf8               (ZLscala/Function0<Lorg/sireum/B;>;)Z
   #74 = Utf8               scala/Function0
   #75 = Class              #74           // scala/Function0
   #76 = Utf8               ()Ljava/lang/Object;
   #77 = NameAndType        #41:#76       // apply:()Ljava/lang/Object;
   #78 = InterfaceMethodref #75.#77       // scala/Function0.apply:()Ljava/lang/Object;
   #79 = Utf8               value
   #80 = NameAndType        #79:#32       // value:()Z
   #81 = Methodref          #14.#80       // org/sireum/B.value:()Z
   #82 = Utf8               Lscala/Function0;
   #83 = Utf8               $bar$bar$extension
   #84 = Utf8               $minus$greater$colon$extension
   #85 = Utf8               $minus$minus$greater$colon$extension
   #86 = Utf8               imply_$colon$extension
   #87 = NameAndType        #84:#66       // $minus$greater$colon$extension:(ZZ)Z
   #88 = Methodref          #2.#87        // org/sireum/B$.$minus$greater$colon$extension:(ZZ)Z
   #89 = Utf8               simply_$colon$extension
   #90 = MethodType         #76           //  ()Ljava/lang/Object;
   #91 = Utf8               $anonfun$simply_$colon$extension$1$adapted
   #92 = Utf8               (Z)Ljava/lang/Object;
   #93 = NameAndType        #91:#92       // $anonfun$simply_$colon$extension$1$adapted:(Z)Ljava/lang/Object;
   #94 = Methodref          #2.#93        // org/sireum/B$.$anonfun$simply_$colon$extension$1$adapted:(Z)Ljava/lang/Object;
   #95 = MethodHandle       6:#94         // REF_invokeStatic org/sireum/B$.$anonfun$simply_$colon$extension$1$adapted:(Z)Ljava/lang/Object;
   #96 = Integer            1
   #97 = Utf8               java/lang/invoke/LambdaMetafactory
   #98 = Class              #97           // java/lang/invoke/LambdaMetafactory
   #99 = Utf8               altMetafactory
  #100 = Utf8               (Ljava/lang/invoke/MethodHandles$Lookup;Ljava/lang/String;Ljava/lang/invoke/MethodType;[Ljava/lang/Object;)Ljava/lang/invoke/CallSite;
  #101 = NameAndType        #99:#100      // altMetafactory:(Ljava/lang/invoke/MethodHandles$Lookup;Ljava/lang/String;Ljava/lang/invoke/MethodType;[Ljava/lang/Object;)Ljava/lang/invoke/CallSite;
  #102 = Methodref          #98.#101      // java/lang/invoke/LambdaMetafactory.altMetafactory:(Ljava/lang/invoke/MethodHandles$Lookup;Ljava/lang/String;Ljava/lang/invoke/MethodType;[Ljava/lang/Object;)Ljava/lang/invoke/CallSite;
  #103 = MethodHandle       6:#102        // REF_invokeStatic java/lang/invoke/LambdaMetafactory.altMetafactory:(Ljava/lang/invoke/MethodHandles$Lookup;Ljava/lang/String;Ljava/lang/invoke/MethodType;[Ljava/lang/Object;)Ljava/lang/invoke/CallSite;
  #104 = Utf8               (Z)Lscala/Function0;
  #105 = NameAndType        #41:#104      // apply:(Z)Lscala/Function0;
  #106 = InvokeDynamic      #0:#105       // #0:apply:(Z)Lscala/Function0;
  #107 = NameAndType        #85:#72       // $minus$minus$greater$colon$extension:(ZLscala/Function0;)Z
  #108 = Methodref          #2.#107       // org/sireum/B$.$minus$minus$greater$colon$extension:(ZLscala/Function0;)Z
  #109 = Utf8               unary_$bang$extension
  #110 = Utf8               unary_$tilde$extension
  #111 = Utf8               $eq$eq$eq$extension
  #112 = Utf8               $eq$bang$eq$extension
  #113 = Utf8               string$extension
  #114 = Utf8               (Z)Ljava/lang/String;
  #115 = Utf8               org/sireum/String$
  #116 = Class              #115          // org/sireum/String$
  #117 = Utf8               Lorg/sireum/String$;
  #118 = NameAndType        #16:#117      // MODULE$:Lorg/sireum/String$;
  #119 = Fieldref           #116.#118     // org/sireum/String$.MODULE$:Lorg/sireum/String$;
  #120 = Utf8               toString$extension
  #121 = NameAndType        #120:#114     // toString$extension:(Z)Ljava/lang/String;
  #122 = Methodref          #2.#121       // org/sireum/B$.toString$extension:(Z)Ljava/lang/String;
  #123 = Utf8               (Ljava/lang/String;)Ljava/lang/String;
  #124 = NameAndType        #41:#123      // apply:(Ljava/lang/String;)Ljava/lang/String;
  #125 = Methodref          #116.#124     // org/sireum/String$.apply:(Ljava/lang/String;)Ljava/lang/String;
  #126 = Utf8               java/lang/Boolean
  #127 = Class              #126          // java/lang/Boolean
  #128 = Utf8               toString
  #129 = NameAndType        #128:#114     // toString:(Z)Ljava/lang/String;
  #130 = Methodref          #127.#129     // java/lang/Boolean.toString:(Z)Ljava/lang/String;
  #131 = Utf8               boxer$extension
  #132 = Utf8               (Z)Lorg/sireum/$internal/Boxer;
  #133 = Utf8               Lorg/sireum/B$Boxer$;
  #134 = NameAndType        #16:#133      // MODULE$:Lorg/sireum/B$Boxer$;
  #135 = Fieldref           #12.#134      // org/sireum/B$Boxer$.MODULE$:Lorg/sireum/B$Boxer$;
  #136 = Utf8               hashCode$extension
  #137 = Utf8               (Z)I
  #138 = Utf8               hashCode
  #139 = NameAndType        #138:#137     // hashCode:(Z)I
  #140 = Methodref          #127.#139     // java/lang/Boolean.hashCode:(Z)I
  #141 = Utf8               equals$extension
  #142 = Utf8               (ZLjava/lang/Object;)Z
  #143 = Utf8               x$1
  #144 = Utf8               Ljava/lang/Object;
  #145 = Utf8               $anonfun$simply_$colon$extension$1
  #146 = Utf8               $this$1
  #147 = Methodref          #4.#24        // java/lang/Object."<init>":()V
  #148 = NameAndType        #145:#42      // $anonfun$simply_$colon$extension$1:(Z)Z
  #149 = Methodref          #2.#148       // org/sireum/B$.$anonfun$simply_$colon$extension$1:(Z)Z
  #150 = Utf8               (Z)V
  #151 = NameAndType        #23:#150      // "<init>":(Z)V
  #152 = Methodref          #14.#151      // org/sireum/B."<init>":(Z)V
  #153 = Utf8               $deserializeLambda$
  #154 = Utf8               (Ljava/lang/invoke/SerializedLambda;)Ljava/lang/Object;
  #155 = Utf8               scala/runtime/LambdaDeserialize
  #156 = Class              #155          // scala/runtime/LambdaDeserialize
  #157 = Utf8               bootstrap
  #158 = Utf8               (Ljava/lang/invoke/MethodHandles$Lookup;Ljava/lang/String;Ljava/lang/invoke/MethodType;[Ljava/lang/invoke/MethodHandle;)Ljava/lang/invoke/CallSite;
  #159 = NameAndType        #157:#158     // bootstrap:(Ljava/lang/invoke/MethodHandles$Lookup;Ljava/lang/String;Ljava/lang/invoke/MethodType;[Ljava/lang/invoke/MethodHandle;)Ljava/lang/invoke/CallSite;
  #160 = Methodref          #156.#159     // scala/runtime/LambdaDeserialize.bootstrap:(Ljava/lang/invoke/MethodHandles$Lookup;Ljava/lang/String;Ljava/lang/invoke/MethodType;[Ljava/lang/invoke/MethodHandle;)Ljava/lang/invoke/CallSite;
  #161 = MethodHandle       6:#160        // REF_invokeStatic scala/runtime/LambdaDeserialize.bootstrap:(Ljava/lang/invoke/MethodHandles$Lookup;Ljava/lang/String;Ljava/lang/invoke/MethodType;[Ljava/lang/invoke/MethodHandle;)Ljava/lang/invoke/CallSite;
  #162 = Utf8               lambdaDeserialize
  #163 = NameAndType        #162:#154     // lambdaDeserialize:(Ljava/lang/invoke/SerializedLambda;)Ljava/lang/Object;
  #164 = InvokeDynamic      #1:#163       // #1:lambdaDeserialize:(Ljava/lang/invoke/SerializedLambda;)Ljava/lang/Object;
  #165 = Utf8               Code
  #166 = Utf8               LineNumberTable
  #167 = Utf8               LocalVariableTable
  #168 = Utf8               Signature
  #169 = Utf8               MethodParameters
  #170 = Utf8               StackMapTable
  #171 = Utf8               InnerClasses
  #172 = Utf8               SourceFile
  #173 = Utf8               BootstrapMethods
  #174 = Utf8               ScalaInlineInfo
  #175 = Utf8               Scala
{
  public static final org.sireum.B$ MODULE$;
    descriptor: Lorg/sireum/B$;
    flags: (0x0019) ACC_PUBLIC, ACC_STATIC, ACC_FINAL

  private static final boolean T;
    descriptor: Z
    flags: (0x001a) ACC_PRIVATE, ACC_STATIC, ACC_FINAL

  private static final boolean F;
    descriptor: Z
    flags: (0x001a) ACC_PRIVATE, ACC_STATIC, ACC_FINAL

  public static {};
    descriptor: ()V
    flags: (0x0009) ACC_PUBLIC, ACC_STATIC
    Code:
      stack=2, locals=0, args_size=0
         0: new           #2                  // class org/sireum/B$
         3: dup
         4: invokespecial #25                 // Method "<init>":()V
         7: putstatic     #27                 // Field MODULE$:Lorg/sireum/B$;
        10: iconst_1
        11: putstatic     #29                 // Field T:Z
        14: iconst_0
        15: putstatic     #31                 // Field F:Z
        18: return
      LineNumberTable:
        line 30: 0
        line 145: 10
        line 146: 14
        line 30: 18

  public boolean T();
    descriptor: ()Z
    flags: (0x0001) ACC_PUBLIC
    Code:
      stack=1, locals=1, args_size=1
         0: getstatic     #29                 // Field T:Z
         3: ireturn
      LineNumberTable:
        line 145: 0
      LocalVariableTable:
        Start  Length  Slot  Name   Signature
            0       4     0  this   Lorg/sireum/B$;

  public boolean F();
    descriptor: ()Z
    flags: (0x0001) ACC_PUBLIC
    Code:
      stack=1, locals=1, args_size=1
         0: getstatic     #31                 // Field F:Z
         3: ireturn
      LineNumberTable:
        line 146: 0
      LocalVariableTable:
        Start  Length  Slot  Name   Signature
            0       4     0  this   Lorg/sireum/B$;

  public boolean random();
    descriptor: ()Z
    flags: (0x0001) ACC_PUBLIC
    Code:
      stack=3, locals=1, args_size=1
         0: aload_0
         1: new           #36                 // class java/util/Random
         4: dup
         5: invokespecial #37                 // Method java/util/Random."<init>":()V
         8: invokevirtual #40                 // Method java/util/Random.nextBoolean:()Z
        11: invokevirtual #44                 // Method apply:(Z)Z
        14: ireturn
      LineNumberTable:
        line 148: 0
      LocalVariableTable:
        Start  Length  Slot  Name   Signature
            0      15     0  this   Lorg/sireum/B$;

  public scala.Option<java.lang.Object> unapply(boolean);
    descriptor: (Z)Lscala/Option;
    flags: (0x0001) ACC_PUBLIC
    Code:
      stack=3, locals=2, args_size=2
         0: new           #50                 // class scala/Some
         3: dup
         4: iload_1
         5: invokestatic  #56                 // Method scala/runtime/BoxesRunTime.boxToBoolean:(Z)Ljava/lang/Boolean;
         8: invokespecial #59                 // Method scala/Some."<init>":(Ljava/lang/Object;)V
        11: areturn
      LineNumberTable:
        line 150: 0
      LocalVariableTable:
        Start  Length  Slot  Name   Signature
            0      12     0  this   Lorg/sireum/B$;
            0      12     1     b   Z
    Signature: #47                          // (Z)Lscala/Option<Ljava/lang/Object;>;
    MethodParameters:
      Name                           Flags
      b                              final

  public boolean apply(boolean);
    descriptor: (Z)Z
    flags: (0x0001) ACC_PUBLIC
    Code:
      stack=1, locals=2, args_size=2
         0: iload_1
         1: ifeq          11
         4: aload_0
         5: invokevirtual #61                 // Method T:()Z
         8: goto          15
        11: aload_0
        12: invokevirtual #63                 // Method F:()Z
        15: ireturn
      StackMapTable: number_of_entries = 2
        frame_type = 11 /* same */
        frame_type = 67 /* same_locals_1_stack_item */
          stack = [ int ]
      LineNumberTable:
        line 154: 0
      LocalVariableTable:
        Start  Length  Slot  Name   Signature
            0      16     0  this   Lorg/sireum/B$;
            0      16     1     b   Z
    MethodParameters:
      Name                           Flags
      b                              final

  public boolean $4B(boolean);
    descriptor: (Z)Z
    flags: (0x0001) ACC_PUBLIC
    Code:
      stack=1, locals=2, args_size=2
         0: iload_1
         1: ireturn
      LineNumberTable:
        line 156: 0
      LocalVariableTable:
        Start  Length  Slot  Name   Signature
            0       2     0  this   Lorg/sireum/B$;
            0       2     1     b   Z
    MethodParameters:
      Name                           Flags
      b                              final

  public final boolean $amp$extension(boolean, boolean);
    descriptor: (ZZ)Z
    flags: (0x0011) ACC_PUBLIC, ACC_FINAL
    Code:
      stack=3, locals=3, args_size=3
         0: aload_0
         1: iload_1
         2: iload_2
         3: iand
         4: invokevirtual #44                 // Method apply:(Z)Z
         7: ireturn
      LineNumberTable:
        line 162: 0
      LocalVariableTable:
        Start  Length  Slot  Name   Signature
            0       8     0  this   Lorg/sireum/B$;
            0       8     1 $this   Z
            0       8     2 other   Z
    MethodParameters:
      Name                           Flags
      $this                          final
      other                          final

  public final boolean $bar$extension(boolean, boolean);
    descriptor: (ZZ)Z
    flags: (0x0011) ACC_PUBLIC, ACC_FINAL
    Code:
      stack=3, locals=3, args_size=3
         0: aload_0
         1: iload_1
         2: iload_2
         3: ior
         4: invokevirtual #44                 // Method apply:(Z)Z
         7: ireturn
      LineNumberTable:
        line 164: 0
      LocalVariableTable:
        Start  Length  Slot  Name   Signature
            0       8     0  this   Lorg/sireum/B$;
            0       8     1 $this   Z
            0       8     2 other   Z
    MethodParameters:
      Name                           Flags
      $this                          final
      other                          final

  public final boolean $bar$up$extension(boolean, boolean);
    descriptor: (ZZ)Z
    flags: (0x0011) ACC_PUBLIC, ACC_FINAL
    Code:
      stack=3, locals=3, args_size=3
         0: aload_0
         1: iload_1
         2: iload_2
         3: ixor
         4: invokevirtual #44                 // Method apply:(Z)Z
         7: ireturn
      LineNumberTable:
        line 166: 0
      LocalVariableTable:
        Start  Length  Slot  Name   Signature
            0       8     0  this   Lorg/sireum/B$;
            0       8     1 $this   Z
            0       8     2 other   Z
    MethodParameters:
      Name                           Flags
      $this                          final
      other                          final

  public final boolean $amp$amp$extension(boolean, scala.Function0<org.sireum.B>);
    descriptor: (ZLscala/Function0;)Z
    flags: (0x0011) ACC_PUBLIC, ACC_FINAL
    Code:
      stack=2, locals=3, args_size=3
         0: aload_0
         1: iload_1
         2: ifeq          24
         5: aload_2
         6: invokeinterface #78,  1           // InterfaceMethod scala/Function0.apply:()Ljava/lang/Object;
        11: checkcast     #14                 // class org/sireum/B
        14: invokevirtual #81                 // Method org/sireum/B.value:()Z
        17: ifeq          24
        20: iconst_1
        21: goto          25
        24: iconst_0
        25: invokevirtual #44                 // Method apply:(Z)Z
        28: ireturn
      StackMapTable: number_of_entries = 2
        frame_type = 88 /* same_locals_1_stack_item */
          stack = [ class org/sireum/B$ ]
        frame_type = 255 /* full_frame */
          offset_delta = 0
          locals = [ class org/sireum/B$, int, class scala/Function0 ]
          stack = [ class org/sireum/B$, int ]
      LineNumberTable:
        line 168: 0
      LocalVariableTable:
        Start  Length  Slot  Name   Signature
            0      29     0  this   Lorg/sireum/B$;
            0      29     1 $this   Z
            0      29     2 other   Lscala/Function0;
    Signature: #73                          // (ZLscala/Function0<Lorg/sireum/B;>;)Z
    MethodParameters:
      Name                           Flags
      $this                          final
      other                          final

  public final boolean $bar$bar$extension(boolean, scala.Function0<org.sireum.B>);
    descriptor: (ZLscala/Function0;)Z
    flags: (0x0011) ACC_PUBLIC, ACC_FINAL
    Code:
      stack=2, locals=3, args_size=3
         0: aload_0
         1: iload_1
         2: ifne          20
         5: aload_2
         6: invokeinterface #78,  1           // InterfaceMethod scala/Function0.apply:()Ljava/lang/Object;
        11: checkcast     #14                 // class org/sireum/B
        14: invokevirtual #81                 // Method org/sireum/B.value:()Z
        17: ifeq          24
        20: iconst_1
        21: goto          25
        24: iconst_0
        25: invokevirtual #44                 // Method apply:(Z)Z
        28: ireturn
      StackMapTable: number_of_entries = 3
        frame_type = 84 /* same_locals_1_stack_item */
          stack = [ class org/sireum/B$ ]
        frame_type = 67 /* same_locals_1_stack_item */
          stack = [ class org/sireum/B$ ]
        frame_type = 255 /* full_frame */
          offset_delta = 0
          locals = [ class org/sireum/B$, int, class scala/Function0 ]
          stack = [ class org/sireum/B$, int ]
      LineNumberTable:
        line 170: 0
      LocalVariableTable:
        Start  Length  Slot  Name   Signature
            0      29     0  this   Lorg/sireum/B$;
            0      29     1 $this   Z
            0      29     2 other   Lscala/Function0;
    Signature: #73                          // (ZLscala/Function0<Lorg/sireum/B;>;)Z
    MethodParameters:
      Name                           Flags
      $this                          final
      other                          final

  public final boolean $minus$greater$colon$extension(boolean, boolean);
    descriptor: (ZZ)Z
    flags: (0x0011) ACC_PUBLIC, ACC_FINAL
    Code:
      stack=3, locals=3, args_size=3
         0: aload_0
         1: iload_2
         2: ifne          9
         5: iconst_1
         6: goto          10
         9: iconst_0
        10: iload_1
        11: ior
        12: invokevirtual #44                 // Method apply:(Z)Z
        15: ireturn
      StackMapTable: number_of_entries = 2
        frame_type = 73 /* same_locals_1_stack_item */
          stack = [ class org/sireum/B$ ]
        frame_type = 255 /* full_frame */
          offset_delta = 0
          locals = [ class org/sireum/B$, int, int ]
          stack = [ class org/sireum/B$, int ]
      LineNumberTable:
        line 172: 0
      LocalVariableTable:
        Start  Length  Slot  Name   Signature
            0      16     0  this   Lorg/sireum/B$;
            0      16     1 $this   Z
            0      16     2 other   Z
    MethodParameters:
      Name                           Flags
      $this                          final
      other                          final

  public final boolean $minus$minus$greater$colon$extension(boolean, scala.Function0<org.sireum.B>);
    descriptor: (ZLscala/Function0;)Z
    flags: (0x0011) ACC_PUBLIC, ACC_FINAL
    Code:
      stack=2, locals=3, args_size=3
         0: aload_0
         1: aload_2
         2: invokeinterface #78,  1           // InterfaceMethod scala/Function0.apply:()Ljava/lang/Object;
         7: checkcast     #14                 // class org/sireum/B
        10: invokevirtual #81                 // Method org/sireum/B.value:()Z
        13: ifeq          20
        16: iload_1
        17: ifeq          24
        20: iconst_1
        21: goto          25
        24: iconst_0
        25: invokevirtual #44                 // Method apply:(Z)Z
        28: ireturn
      StackMapTable: number_of_entries = 3
        frame_type = 84 /* same_locals_1_stack_item */
          stack = [ class org/sireum/B$ ]
        frame_type = 67 /* same_locals_1_stack_item */
          stack = [ class org/sireum/B$ ]
        frame_type = 255 /* full_frame */
          offset_delta = 0
          locals = [ class org/sireum/B$, int, class scala/Function0 ]
          stack = [ class org/sireum/B$, int ]
      LineNumberTable:
        line 174: 0
      LocalVariableTable:
        Start  Length  Slot  Name   Signature
            0      29     0  this   Lorg/sireum/B$;
            0      29     1 $this   Z
            0      29     2 other   Lscala/Function0;
    Signature: #73                          // (ZLscala/Function0<Lorg/sireum/B;>;)Z
    MethodParameters:
      Name                           Flags
      $this                          final
      other                          final

  public final boolean imply_$colon$extension(boolean, boolean);
    descriptor: (ZZ)Z
    flags: (0x0011) ACC_PUBLIC, ACC_FINAL
    Code:
      stack=3, locals=4, args_size=3
         0: iload_1
         1: istore_3
         2: aload_0
         3: iload_2
         4: iload_3
         5: invokevirtual #88                 // Method $minus$greater$colon$extension:(ZZ)Z
         8: ireturn
      LineNumberTable:
        line 176: 0
      LocalVariableTable:
        Start  Length  Slot  Name   Signature
            0       9     0  this   Lorg/sireum/B$;
            0       9     1 $this   Z
            0       9     2 other   Z
    MethodParameters:
      Name                           Flags
      $this                          final
      other                          final

  public final boolean simply_$colon$extension(boolean, scala.Function0<org.sireum.B>);
    descriptor: (ZLscala/Function0;)Z
    flags: (0x0011) ACC_PUBLIC, ACC_FINAL
    Code:
      stack=3, locals=3, args_size=3
         0: aload_0
         1: aload_2
         2: invokeinterface #78,  1           // InterfaceMethod scala/Function0.apply:()Ljava/lang/Object;
         7: checkcast     #14                 // class org/sireum/B
        10: invokevirtual #81                 // Method org/sireum/B.value:()Z
        13: iload_1
        14: invokedynamic #106,  0            // InvokeDynamic #0:apply:(Z)Lscala/Function0;
        19: invokevirtual #108                // Method $minus$minus$greater$colon$extension:(ZLscala/Function0;)Z
        22: ireturn
      LineNumberTable:
        line 178: 1
      LocalVariableTable:
        Start  Length  Slot  Name   Signature
            0      23     0  this   Lorg/sireum/B$;
            0      23     1 $this   Z
            0      23     2 other   Lscala/Function0;
    Signature: #73                          // (ZLscala/Function0<Lorg/sireum/B;>;)Z
    MethodParameters:
      Name                           Flags
      $this                          final
      other                          final

  public final boolean unary_$bang$extension(boolean);
    descriptor: (Z)Z
    flags: (0x0011) ACC_PUBLIC, ACC_FINAL
    Code:
      stack=2, locals=2, args_size=2
         0: aload_0
         1: iload_1
         2: ifne          9
         5: iconst_1
         6: goto          10
         9: iconst_0
        10: invokevirtual #44                 // Method apply:(Z)Z
        13: ireturn
      StackMapTable: number_of_entries = 2
        frame_type = 73 /* same_locals_1_stack_item */
          stack = [ class org/sireum/B$ ]
        frame_type = 255 /* full_frame */
          offset_delta = 0
          locals = [ class org/sireum/B$, int ]
          stack = [ class org/sireum/B$, int ]
      LineNumberTable:
        line 180: 0
      LocalVariableTable:
        Start  Length  Slot  Name   Signature
            0      14     0  this   Lorg/sireum/B$;
            0      14     1 $this   Z
    MethodParameters:
      Name                           Flags
      $this                          final

  public final boolean unary_$tilde$extension(boolean);
    descriptor: (Z)Z
    flags: (0x0011) ACC_PUBLIC, ACC_FINAL
    Code:
      stack=2, locals=2, args_size=2
         0: aload_0
         1: iload_1
         2: ifne          9
         5: iconst_1
         6: goto          10
         9: iconst_0
        10: invokevirtual #44                 // Method apply:(Z)Z
        13: ireturn
      StackMapTable: number_of_entries = 2
        frame_type = 73 /* same_locals_1_stack_item */
          stack = [ class org/sireum/B$ ]
        frame_type = 255 /* full_frame */
          offset_delta = 0
          locals = [ class org/sireum/B$, int ]
          stack = [ class org/sireum/B$, int ]
      LineNumberTable:
        line 182: 0
      LocalVariableTable:
        Start  Length  Slot  Name   Signature
            0      14     0  this   Lorg/sireum/B$;
            0      14     1 $this   Z
    MethodParameters:
      Name                           Flags
      $this                          final

  public final boolean $eq$eq$eq$extension(boolean, boolean);
    descriptor: (ZZ)Z
    flags: (0x0011) ACC_PUBLIC, ACC_FINAL
    Code:
      stack=3, locals=3, args_size=3
         0: aload_0
         1: iload_1
         2: iload_2
         3: if_icmpne     10
         6: iconst_1
         7: goto          11
        10: iconst_0
        11: invokevirtual #44                 // Method apply:(Z)Z
        14: ireturn
      StackMapTable: number_of_entries = 2
        frame_type = 74 /* same_locals_1_stack_item */
          stack = [ class org/sireum/B$ ]
        frame_type = 255 /* full_frame */
          offset_delta = 0
          locals = [ class org/sireum/B$, int, int ]
          stack = [ class org/sireum/B$, int ]
      LineNumberTable:
        line 184: 0
      LocalVariableTable:
        Start  Length  Slot  Name   Signature
            0      15     0  this   Lorg/sireum/B$;
            0      15     1 $this   Z
            0      15     2 other   Z
    MethodParameters:
      Name                           Flags
      $this                          final
      other                          final

  public final boolean $eq$bang$eq$extension(boolean, boolean);
    descriptor: (ZZ)Z
    flags: (0x0011) ACC_PUBLIC, ACC_FINAL
    Code:
      stack=3, locals=3, args_size=3
         0: aload_0
         1: iload_1
         2: iload_2
         3: if_icmpeq     10
         6: iconst_1
         7: goto          11
        10: iconst_0
        11: invokevirtual #44                 // Method apply:(Z)Z
        14: ireturn
      StackMapTable: number_of_entries = 2
        frame_type = 74 /* same_locals_1_stack_item */
          stack = [ class org/sireum/B$ ]
        frame_type = 255 /* full_frame */
          offset_delta = 0
          locals = [ class org/sireum/B$, int, int ]
          stack = [ class org/sireum/B$, int ]
      LineNumberTable:
        line 186: 0
      LocalVariableTable:
        Start  Length  Slot  Name   Signature
            0      15     0  this   Lorg/sireum/B$;
            0      15     1 $this   Z
            0      15     2 other   Z
    MethodParameters:
      Name                           Flags
      $this                          final
      other                          final

  public final java.lang.String string$extension(boolean);
    descriptor: (Z)Ljava/lang/String;
    flags: (0x0011) ACC_PUBLIC, ACC_FINAL
    Code:
      stack=3, locals=2, args_size=2
         0: getstatic     #119                // Field org/sireum/String$.MODULE$:Lorg/sireum/String$;
         3: aload_0
         4: iload_1
         5: invokevirtual #122                // Method toString$extension:(Z)Ljava/lang/String;
         8: invokevirtual #125                // Method org/sireum/String$.apply:(Ljava/lang/String;)Ljava/lang/String;
        11: areturn
      LineNumberTable:
        line 188: 0
      LocalVariableTable:
        Start  Length  Slot  Name   Signature
            0      12     0  this   Lorg/sireum/B$;
            0      12     1 $this   Z
    MethodParameters:
      Name                           Flags
      $this                          final

  public final java.lang.String toString$extension(boolean);
    descriptor: (Z)Ljava/lang/String;
    flags: (0x0011) ACC_PUBLIC, ACC_FINAL
    Code:
      stack=1, locals=2, args_size=2
         0: iload_1
         1: invokestatic  #130                // Method java/lang/Boolean.toString:(Z)Ljava/lang/String;
         4: areturn
      LineNumberTable:
        line 190: 0
      LocalVariableTable:
        Start  Length  Slot  Name   Signature
            0       5     0  this   Lorg/sireum/B$;
            0       5     1 $this   Z
    MethodParameters:
      Name                           Flags
      $this                          final

  public final org.sireum.$internal.Boxer boxer$extension(boolean);
    descriptor: (Z)Lorg/sireum/$internal/Boxer;
    flags: (0x0011) ACC_PUBLIC, ACC_FINAL
    Code:
      stack=1, locals=2, args_size=2
         0: getstatic     #135                // Field org/sireum/B$Boxer$.MODULE$:Lorg/sireum/B$Boxer$;
         3: areturn
      LineNumberTable:
        line 192: 0
      LocalVariableTable:
        Start  Length  Slot  Name   Signature
            0       4     0  this   Lorg/sireum/B$;
            0       4     1 $this   Z
    MethodParameters:
      Name                           Flags
      $this                          final

  public final int hashCode$extension(boolean);
    descriptor: (Z)I
    flags: (0x0011) ACC_PUBLIC, ACC_FINAL
    Code:
      stack=1, locals=2, args_size=2
         0: iload_1
         1: invokestatic  #140                // Method java/lang/Boolean.hashCode:(Z)I
         4: ireturn
      LineNumberTable:
        line 160: 0
      LocalVariableTable:
        Start  Length  Slot  Name   Signature
            0       5     0  this   Lorg/sireum/B$;
            0       5     1 $this   Z
    MethodParameters:
      Name                           Flags
      $this                          final

  public final boolean equals$extension(boolean, java.lang.Object);
    descriptor: (ZLjava/lang/Object;)Z
    flags: (0x0011) ACC_PUBLIC, ACC_FINAL
    Code:
      stack=2, locals=6, args_size=3
         0: aload_2
         1: astore        4
         3: aload         4
         5: instanceof    #14                 // class org/sireum/B
         8: ifeq          16
        11: iconst_1
        12: istore_3
        13: goto          24
        16: goto          19
        19: iconst_0
        20: istore_3
        21: goto          24
        24: iload_3
        25: ifeq          55
        28: aload_2
        29: checkcast     #14                 // class org/sireum/B
        32: invokevirtual #81                 // Method org/sireum/B.value:()Z
        35: istore        5
        37: iload_1
        38: iload         5
        40: if_icmpne     47
        43: iconst_1
        44: goto          48
        47: iconst_0
        48: ifeq          55
        51: iconst_1
        52: goto          56
        55: iconst_0
        56: ireturn
      StackMapTable: number_of_entries = 7
        frame_type = 253 /* append */
          offset_delta = 16
          locals = [ top, class java/lang/Object ]
        frame_type = 2 /* same */
        frame_type = 255 /* full_frame */
          offset_delta = 4
          locals = [ class org/sireum/B$, int, class java/lang/Object, int, class java/lang/Object ]
          stack = []
        frame_type = 252 /* append */
          offset_delta = 22
          locals = [ int ]
        frame_type = 64 /* same_locals_1_stack_item */
          stack = [ int ]
        frame_type = 250 /* chop */
          offset_delta = 6
        frame_type = 64 /* same_locals_1_stack_item */
          stack = [ int ]
      LineNumberTable:
        line 160: 0
      LocalVariableTable:
        Start  Length  Slot  Name   Signature
            0      57     0  this   Lorg/sireum/B$;
            0      57     1 $this   Z
            0      57     2   x$1   Ljava/lang/Object;
    MethodParameters:
      Name                           Flags
      $this                          final
      x$1                            final

  public static final boolean $anonfun$simply_$colon$extension$1(boolean);
    descriptor: (Z)Z
    flags: (0x1019) ACC_PUBLIC, ACC_STATIC, ACC_FINAL, ACC_SYNTHETIC
    Code:
      stack=1, locals=1, args_size=1
         0: iload_0
         1: ireturn
      LocalVariableTable:
        Start  Length  Slot  Name   Signature
            0       2     0 $this$1   Z
    MethodParameters:
      Name                           Flags
      $this$1                        final

  private org.sireum.B$();
    descriptor: ()V
    flags: (0x0002) ACC_PRIVATE
    Code:
      stack=1, locals=1, args_size=1
         0: aload_0
         1: invokespecial #147                // Method java/lang/Object."<init>":()V
         4: return
      LineNumberTable:
        line 30: 0
      LocalVariableTable:
        Start  Length  Slot  Name   Signature
            0       5     0  this   Lorg/sireum/B$;

  public static final java.lang.Object $anonfun$simply_$colon$extension$1$adapted(boolean);
    descriptor: (Z)Ljava/lang/Object;
    flags: (0x1019) ACC_PUBLIC, ACC_STATIC, ACC_FINAL, ACC_SYNTHETIC
    Code:
      stack=3, locals=1, args_size=1
         0: new           #14                 // class org/sireum/B
         3: dup
         4: iload_0
         5: invokestatic  #149                // Method $anonfun$simply_$colon$extension$1:(Z)Z
         8: invokespecial #152                // Method org/sireum/B."<init>":(Z)V
        11: areturn
      LocalVariableTable:
        Start  Length  Slot  Name   Signature
            0      12     0 $this$1   Z
    MethodParameters:
      Name                           Flags
      $this$1                        final

  private static java.lang.Object $deserializeLambda$(java.lang.invoke.SerializedLambda);
    descriptor: (Ljava/lang/invoke/SerializedLambda;)Ljava/lang/Object;
    flags: (0x100a) ACC_PRIVATE, ACC_STATIC, ACC_SYNTHETIC
    Code:
      stack=1, locals=1, args_size=1
         0: aload_0
         1: invokedynamic #164,  0            // InvokeDynamic #1:lambdaDeserialize:(Ljava/lang/invoke/SerializedLambda;)Ljava/lang/Object;
         6: areturn
}
InnerClasses:
  public static final #10= #7 of #9;      // Lookup=class java/lang/invoke/MethodHandles$Lookup of class java/lang/invoke/MethodHandles
  public static #15= #12 of #14;          // Boxer$=class org/sireum/B$Boxer$ of class org/sireum/B
SourceFile: "B.scala"
BootstrapMethods:
  0: #103 REF_invokeStatic java/lang/invoke/LambdaMetafactory.altMetafactory:(Ljava/lang/invoke/MethodHandles$Lookup;Ljava/lang/String;Ljava/lang/invoke/MethodType;[Ljava/lang/Object;)Ljava/lang/invoke/CallSite;
    Method arguments:
      #90 ()Ljava/lang/Object;
      #95 REF_invokeStatic org/sireum/B$.$anonfun$simply_$colon$extension$1$adapted:(Z)Ljava/lang/Object;
      #90 ()Ljava/lang/Object;
      #96 1
  1: #161 REF_invokeStatic scala/runtime/LambdaDeserialize.bootstrap:(Ljava/lang/invoke/MethodHandles$Lookup;Ljava/lang/String;Ljava/lang/invoke/MethodType;[Ljava/lang/invoke/MethodHandle;)Ljava/lang/invoke/CallSite;
    Method arguments:
      #95 REF_invokeStatic org/sireum/B$.$anonfun$simply_$colon$extension$1$adapted:(Z)Ljava/lang/Object;
  ScalaInlineInfo: length = 0x8B (unknown attribute)
   01 01 00 1B 00 40 00 2A 05 00 47 00 48 05 00 41
   00 42 05 00 91 00 2A 01 00 5B 00 5C 01 00 53 00
   48 05 00 45 00 42 05 00 46 00 42 05 00 70 00 42
   05 00 6F 00 42 05 00 54 00 42 05 00 55 00 48 05
   00 17 00 16 01 00 14 00 20 01 00 12 00 20 01 00
   29 00 2A 05 00 83 00 84 05 00 8D 00 8E 01 00 88
   00 89 01 00 56 00 42 05 00 22 00 20 01 00 59 00
   48 05 00 71 00 72 05 00 78 00 72 05 00 2D 00 2E
   01 00 6D 00 2A 05 00 6E 00 2A 05
  Scala: length = 0x0 (unknown attribute)

