Classfile /Users/mw/Projects/slang-braindump/.jar/jar11/assemble/slang-braindump/assemble/content/org/sireum/C$.class
  Last modified May 29, 2022; size 4850 bytes
  SHA-256 checksum 2b3a59e24bcc4d95badadc9c2878ef78d36c3d209e5701ffe0f57544ccdaa75c
  Compiled from "C.scala"
public final class org.sireum.C$
  minor version: 0
  major version: 52
  flags: (0x0031) ACC_PUBLIC, ACC_FINAL, ACC_SUPER
  this_class: #2                          // org/sireum/C$
  super_class: #4                         // java/lang/Object
  interfaces: 0, fields: 1, methods: 28, attributes: 4
Constant pool:
    #1 = Utf8               org/sireum/C$
    #2 = Class              #1            // org/sireum/C$
    #3 = Utf8               java/lang/Object
    #4 = Class              #3            // java/lang/Object
    #5 = Utf8               C.scala
    #6 = Utf8               org/sireum/C$Boxer$
    #7 = Class              #6            // org/sireum/C$Boxer$
    #8 = Utf8               org/sireum/C
    #9 = Class              #8            // org/sireum/C
   #10 = Utf8               Boxer$
   #11 = Utf8               MODULE$
   #12 = Utf8               Lorg/sireum/C$;
   #13 = Utf8               <clinit>
   #14 = Utf8               ()V
   #15 = Utf8               <init>
   #16 = NameAndType        #15:#14       // "<init>":()V
   #17 = Methodref          #2.#16        // org/sireum/C$."<init>":()V
   #18 = NameAndType        #11:#12       // MODULE$:Lorg/sireum/C$;
   #19 = Fieldref           #2.#18        // org/sireum/C$.MODULE$:Lorg/sireum/C$;
   #20 = Utf8               random
   #21 = Utf8               ()I
   #22 = Utf8               java/util/Random
   #23 = Class              #22           // java/util/Random
   #24 = Methodref          #23.#16       // java/util/Random."<init>":()V
   #25 = Utf8               nextInt
   #26 = NameAndType        #25:#21       // nextInt:()I
   #27 = Methodref          #23.#26       // java/util/Random.nextInt:()I
   #28 = Utf8               apply
   #29 = Utf8               (I)I
   #30 = NameAndType        #28:#29       // apply:(I)I
   #31 = Methodref          #2.#30        // org/sireum/C$.apply:(I)I
   #32 = Utf8               r
   #33 = Utf8               Ljava/util/Random;
   #34 = Utf8               this
   #35 = Utf8               unapply
   #36 = Utf8               (I)Lscala/Some;
   #37 = Utf8               (I)Lscala/Some<Ljava/lang/Object;>;
   #38 = Utf8               c
   #39 = Utf8               scala/Some
   #40 = Class              #39           // scala/Some
   #41 = Utf8               scala/runtime/BoxesRunTime
   #42 = Class              #41           // scala/runtime/BoxesRunTime
   #43 = Utf8               boxToInteger
   #44 = Utf8               (I)Ljava/lang/Integer;
   #45 = NameAndType        #43:#44       // boxToInteger:(I)Ljava/lang/Integer;
   #46 = Methodref          #42.#45       // scala/runtime/BoxesRunTime.boxToInteger:(I)Ljava/lang/Integer;
   #47 = Utf8               (Ljava/lang/Object;)V
   #48 = NameAndType        #15:#47       // "<init>":(Ljava/lang/Object;)V
   #49 = Methodref          #40.#48       // scala/Some."<init>":(Ljava/lang/Object;)V
   #50 = Utf8               I
   #51 = Utf8               (C)I
   #52 = Utf8               C
   #53 = Utf8               native$extension
   #54 = Utf8               (I)C
   #55 = Utf8               $this
   #56 = Utf8               unary_$tilde$extension
   #57 = Utf8               $plus$extension
   #58 = Utf8               (II)I
   #59 = Utf8               other
   #60 = Utf8               $minus$extension
   #61 = Utf8               $less$extension
   #62 = Utf8               (II)Z
   #63 = Utf8               org/sireum/B$
   #64 = Class              #63           // org/sireum/B$
   #65 = Utf8               Lorg/sireum/B$;
   #66 = NameAndType        #11:#65       // MODULE$:Lorg/sireum/B$;
   #67 = Fieldref           #64.#66       // org/sireum/B$.MODULE$:Lorg/sireum/B$;
   #68 = Utf8               (Z)Z
   #69 = NameAndType        #28:#68       // apply:(Z)Z
   #70 = Methodref          #64.#69       // org/sireum/B$.apply:(Z)Z
   #71 = Utf8               $less$eq$extension
   #72 = Utf8               $greater$extension
   #73 = Utf8               $greater$eq$extension
   #74 = Utf8               $eq$eq$eq$extension
   #75 = Utf8               $eq$bang$eq$extension
   #76 = Utf8               $greater$greater$greater$extension
   #77 = Utf8               $greater$greater$extension
   #78 = Utf8               $less$less$extension
   #79 = Utf8               $amp$extension
   #80 = Utf8               $bar$extension
   #81 = Utf8               $bar$up$extension
   #82 = Utf8               string$extension
   #83 = Utf8               (I)Ljava/lang/String;
   #84 = Utf8               org/sireum/String$
   #85 = Class              #84           // org/sireum/String$
   #86 = Utf8               Lorg/sireum/String$;
   #87 = NameAndType        #11:#86       // MODULE$:Lorg/sireum/String$;
   #88 = Fieldref           #85.#87       // org/sireum/String$.MODULE$:Lorg/sireum/String$;
   #89 = Utf8               toString$extension
   #90 = NameAndType        #89:#83       // toString$extension:(I)Ljava/lang/String;
   #91 = Methodref          #2.#90        // org/sireum/C$.toString$extension:(I)Ljava/lang/String;
   #92 = Utf8               (Ljava/lang/String;)Ljava/lang/String;
   #93 = NameAndType        #28:#92       // apply:(Ljava/lang/String;)Ljava/lang/String;
   #94 = Methodref          #85.#93       // org/sireum/String$.apply:(Ljava/lang/String;)Ljava/lang/String;
   #95 = Utf8               java/lang/String
   #96 = Class              #95           // java/lang/String
   #97 = Utf8               ([III)V
   #98 = NameAndType        #15:#97       // "<init>":([III)V
   #99 = Methodref          #96.#98       // java/lang/String."<init>":([III)V
  #100 = Utf8               isWhitespace$extension
  #101 = Utf8               (I)Z
  #102 = Utf8               scala/runtime/RichChar$
  #103 = Class              #102          // scala/runtime/RichChar$
  #104 = Utf8               Lscala/runtime/RichChar$;
  #105 = NameAndType        #11:#104      // MODULE$:Lscala/runtime/RichChar$;
  #106 = Fieldref           #103.#105     // scala/runtime/RichChar$.MODULE$:Lscala/runtime/RichChar$;
  #107 = Utf8               scala/Predef$
  #108 = Class              #107          // scala/Predef$
  #109 = Utf8               Lscala/Predef$;
  #110 = NameAndType        #11:#109      // MODULE$:Lscala/Predef$;
  #111 = Fieldref           #108.#110     // scala/Predef$.MODULE$:Lscala/Predef$;
  #112 = Utf8               charWrapper
  #113 = Utf8               (C)C
  #114 = NameAndType        #112:#113     // charWrapper:(C)C
  #115 = Methodref          #108.#114     // scala/Predef$.charWrapper:(C)C
  #116 = Utf8               (C)Z
  #117 = NameAndType        #100:#116     // isWhitespace$extension:(C)Z
  #118 = Methodref          #103.#117     // scala/runtime/RichChar$.isWhitespace$extension:(C)Z
  #119 = Utf8               boxer$extension
  #120 = Utf8               (I)Lorg/sireum/$internal/Boxer;
  #121 = Utf8               Lorg/sireum/C$Boxer$;
  #122 = NameAndType        #11:#121      // MODULE$:Lorg/sireum/C$Boxer$;
  #123 = Fieldref           #7.#122       // org/sireum/C$Boxer$.MODULE$:Lorg/sireum/C$Boxer$;
  #124 = Utf8               hashCode$extension
  #125 = Utf8               java/lang/Integer
  #126 = Class              #125          // java/lang/Integer
  #127 = Utf8               hashCode
  #128 = NameAndType        #127:#29      // hashCode:(I)I
  #129 = Methodref          #126.#128     // java/lang/Integer.hashCode:(I)I
  #130 = Utf8               equals$extension
  #131 = Utf8               (ILjava/lang/Object;)Z
  #132 = Utf8               x$1
  #133 = Utf8               value
  #134 = NameAndType        #133:#21      // value:()I
  #135 = Methodref          #9.#134       // org/sireum/C.value:()I
  #136 = Utf8               Ljava/lang/Object;
  #137 = Methodref          #4.#16        // java/lang/Object."<init>":()V
  #138 = Utf8               Code
  #139 = Utf8               LineNumberTable
  #140 = Utf8               LocalVariableTable
  #141 = Utf8               Signature
  #142 = Utf8               MethodParameters
  #143 = Utf8               StackMapTable
  #144 = Utf8               InnerClasses
  #145 = Utf8               SourceFile
  #146 = Utf8               ScalaInlineInfo
  #147 = Utf8               Scala
{
  public static final org.sireum.C$ MODULE$;
    descriptor: Lorg/sireum/C$;
    flags: (0x0019) ACC_PUBLIC, ACC_STATIC, ACC_FINAL

  public static {};
    descriptor: ()V
    flags: (0x0009) ACC_PUBLIC, ACC_STATIC
    Code:
      stack=2, locals=0, args_size=0
         0: new           #2                  // class org/sireum/C$
         3: dup
         4: invokespecial #17                 // Method "<init>":()V
         7: putstatic     #19                 // Field MODULE$:Lorg/sireum/C$;
        10: return
      LineNumberTable:
        line 29: 0

  public int random();
    descriptor: ()I
    flags: (0x0001) ACC_PUBLIC
    Code:
      stack=2, locals=2, args_size=1
         0: new           #23                 // class java/util/Random
         3: dup
         4: invokespecial #24                 // Method java/util/Random."<init>":()V
         7: astore_1
         8: aload_0
         9: aload_1
        10: invokevirtual #27                 // Method java/util/Random.nextInt:()I
        13: i2c
        14: invokevirtual #31                 // Method apply:(I)I
        17: ireturn
      LineNumberTable:
        line 55: 0
        line 56: 8
      LocalVariableTable:
        Start  Length  Slot  Name   Signature
            8       9     1     r   Ljava/util/Random;
            0      18     0  this   Lorg/sireum/C$;

  public scala.Some<java.lang.Object> unapply(int);
    descriptor: (I)Lscala/Some;
    flags: (0x0001) ACC_PUBLIC
    Code:
      stack=3, locals=2, args_size=2
         0: new           #40                 // class scala/Some
         3: dup
         4: iload_1
         5: invokestatic  #46                 // Method scala/runtime/BoxesRunTime.boxToInteger:(I)Ljava/lang/Integer;
         8: invokespecial #49                 // Method scala/Some."<init>":(Ljava/lang/Object;)V
        11: areturn
      LineNumberTable:
        line 59: 0
      LocalVariableTable:
        Start  Length  Slot  Name   Signature
            0      12     0  this   Lorg/sireum/C$;
            0      12     1     c   I
    Signature: #37                          // (I)Lscala/Some<Ljava/lang/Object;>;
    MethodParameters:
      Name                           Flags
      c                              final

  public int apply(int);
    descriptor: (I)I
    flags: (0x0001) ACC_PUBLIC
    Code:
      stack=1, locals=2, args_size=2
         0: iload_1
         1: ireturn
      LineNumberTable:
        line 63: 0
      LocalVariableTable:
        Start  Length  Slot  Name   Signature
            0       2     0  this   Lorg/sireum/C$;
            0       2     1     c   I
    MethodParameters:
      Name                           Flags
      c                              final

  public int apply(char);
    descriptor: (C)I
    flags: (0x0001) ACC_PUBLIC
    Code:
      stack=1, locals=2, args_size=2
         0: iload_1
         1: ireturn
      LineNumberTable:
        line 66: 0
      LocalVariableTable:
        Start  Length  Slot  Name   Signature
            0       2     0  this   Lorg/sireum/C$;
            0       2     1     c   C
    MethodParameters:
      Name                           Flags
      c                              final

  public final char native$extension(int);
    descriptor: (I)C
    flags: (0x0011) ACC_PUBLIC, ACC_FINAL
    Code:
      stack=1, locals=2, args_size=2
         0: iload_1
         1: i2c
         2: ireturn
      LineNumberTable:
        line 73: 0
      LocalVariableTable:
        Start  Length  Slot  Name   Signature
            0       3     0  this   Lorg/sireum/C$;
            0       3     1 $this   I
    MethodParameters:
      Name                           Flags
      $this                          final

  public final int unary_$tilde$extension(int);
    descriptor: (I)I
    flags: (0x0011) ACC_PUBLIC, ACC_FINAL
    Code:
      stack=3, locals=2, args_size=2
         0: aload_0
         1: iload_1
         2: iconst_m1
         3: ixor
         4: invokevirtual #31                 // Method apply:(I)I
         7: ireturn
      LineNumberTable:
        line 75: 0
      LocalVariableTable:
        Start  Length  Slot  Name   Signature
            0       8     0  this   Lorg/sireum/C$;
            0       8     1 $this   I
    MethodParameters:
      Name                           Flags
      $this                          final

  public final int $plus$extension(int, int);
    descriptor: (II)I
    flags: (0x0011) ACC_PUBLIC, ACC_FINAL
    Code:
      stack=3, locals=3, args_size=3
         0: aload_0
         1: iload_1
         2: iload_2
         3: iadd
         4: invokevirtual #31                 // Method apply:(I)I
         7: ireturn
      LineNumberTable:
        line 77: 0
      LocalVariableTable:
        Start  Length  Slot  Name   Signature
            0       8     0  this   Lorg/sireum/C$;
            0       8     1 $this   I
            0       8     2 other   I
    MethodParameters:
      Name                           Flags
      $this                          final
      other                          final

  public final int $minus$extension(int, int);
    descriptor: (II)I
    flags: (0x0011) ACC_PUBLIC, ACC_FINAL
    Code:
      stack=3, locals=3, args_size=3
         0: aload_0
         1: iload_1
         2: iload_2
         3: isub
         4: invokevirtual #31                 // Method apply:(I)I
         7: ireturn
      LineNumberTable:
        line 79: 0
      LocalVariableTable:
        Start  Length  Slot  Name   Signature
            0       8     0  this   Lorg/sireum/C$;
            0       8     1 $this   I
            0       8     2 other   I
    MethodParameters:
      Name                           Flags
      $this                          final
      other                          final

  public final boolean $less$extension(int, int);
    descriptor: (II)Z
    flags: (0x0011) ACC_PUBLIC, ACC_FINAL
    Code:
      stack=3, locals=3, args_size=3
         0: getstatic     #67                 // Field org/sireum/B$.MODULE$:Lorg/sireum/B$;
         3: iload_1
         4: iload_2
         5: if_icmpge     12
         8: iconst_1
         9: goto          13
        12: iconst_0
        13: invokevirtual #70                 // Method org/sireum/B$.apply:(Z)Z
        16: ireturn
      StackMapTable: number_of_entries = 2
        frame_type = 76 /* same_locals_1_stack_item */
          stack = [ class org/sireum/B$ ]
        frame_type = 255 /* full_frame */
          offset_delta = 0
          locals = [ class org/sireum/C$, int, int ]
          stack = [ class org/sireum/B$, int ]
      LineNumberTable:
        line 81: 0
      LocalVariableTable:
        Start  Length  Slot  Name   Signature
            0      17     0  this   Lorg/sireum/C$;
            0      17     1 $this   I
            0      17     2 other   I
    MethodParameters:
      Name                           Flags
      $this                          final
      other                          final

  public final boolean $less$eq$extension(int, int);
    descriptor: (II)Z
    flags: (0x0011) ACC_PUBLIC, ACC_FINAL
    Code:
      stack=3, locals=3, args_size=3
         0: getstatic     #67                 // Field org/sireum/B$.MODULE$:Lorg/sireum/B$;
         3: iload_1
         4: iload_2
         5: if_icmpgt     12
         8: iconst_1
         9: goto          13
        12: iconst_0
        13: invokevirtual #70                 // Method org/sireum/B$.apply:(Z)Z
        16: ireturn
      StackMapTable: number_of_entries = 2
        frame_type = 76 /* same_locals_1_stack_item */
          stack = [ class org/sireum/B$ ]
        frame_type = 255 /* full_frame */
          offset_delta = 0
          locals = [ class org/sireum/C$, int, int ]
          stack = [ class org/sireum/B$, int ]
      LineNumberTable:
        line 83: 0
      LocalVariableTable:
        Start  Length  Slot  Name   Signature
            0      17     0  this   Lorg/sireum/C$;
            0      17     1 $this   I
            0      17     2 other   I
    MethodParameters:
      Name                           Flags
      $this                          final
      other                          final

  public final boolean $greater$extension(int, int);
    descriptor: (II)Z
    flags: (0x0011) ACC_PUBLIC, ACC_FINAL
    Code:
      stack=3, locals=3, args_size=3
         0: getstatic     #67                 // Field org/sireum/B$.MODULE$:Lorg/sireum/B$;
         3: iload_1
         4: iload_2
         5: if_icmple     12
         8: iconst_1
         9: goto          13
        12: iconst_0
        13: invokevirtual #70                 // Method org/sireum/B$.apply:(Z)Z
        16: ireturn
      StackMapTable: number_of_entries = 2
        frame_type = 76 /* same_locals_1_stack_item */
          stack = [ class org/sireum/B$ ]
        frame_type = 255 /* full_frame */
          offset_delta = 0
          locals = [ class org/sireum/C$, int, int ]
          stack = [ class org/sireum/B$, int ]
      LineNumberTable:
        line 85: 0
      LocalVariableTable:
        Start  Length  Slot  Name   Signature
            0      17     0  this   Lorg/sireum/C$;
            0      17     1 $this   I
            0      17     2 other   I
    MethodParameters:
      Name                           Flags
      $this                          final
      other                          final

  public final boolean $greater$eq$extension(int, int);
    descriptor: (II)Z
    flags: (0x0011) ACC_PUBLIC, ACC_FINAL
    Code:
      stack=3, locals=3, args_size=3
         0: getstatic     #67                 // Field org/sireum/B$.MODULE$:Lorg/sireum/B$;
         3: iload_1
         4: iload_2
         5: if_icmplt     12
         8: iconst_1
         9: goto          13
        12: iconst_0
        13: invokevirtual #70                 // Method org/sireum/B$.apply:(Z)Z
        16: ireturn
      StackMapTable: number_of_entries = 2
        frame_type = 76 /* same_locals_1_stack_item */
          stack = [ class org/sireum/B$ ]
        frame_type = 255 /* full_frame */
          offset_delta = 0
          locals = [ class org/sireum/C$, int, int ]
          stack = [ class org/sireum/B$, int ]
      LineNumberTable:
        line 87: 0
      LocalVariableTable:
        Start  Length  Slot  Name   Signature
            0      17     0  this   Lorg/sireum/C$;
            0      17     1 $this   I
            0      17     2 other   I
    MethodParameters:
      Name                           Flags
      $this                          final
      other                          final

  public final boolean $eq$eq$eq$extension(int, int);
    descriptor: (II)Z
    flags: (0x0011) ACC_PUBLIC, ACC_FINAL
    Code:
      stack=3, locals=3, args_size=3
         0: getstatic     #67                 // Field org/sireum/B$.MODULE$:Lorg/sireum/B$;
         3: iload_1
         4: iload_2
         5: if_icmpne     12
         8: iconst_1
         9: goto          13
        12: iconst_0
        13: invokevirtual #70                 // Method org/sireum/B$.apply:(Z)Z
        16: ireturn
      StackMapTable: number_of_entries = 2
        frame_type = 76 /* same_locals_1_stack_item */
          stack = [ class org/sireum/B$ ]
        frame_type = 255 /* full_frame */
          offset_delta = 0
          locals = [ class org/sireum/C$, int, int ]
          stack = [ class org/sireum/B$, int ]
      LineNumberTable:
        line 89: 0
      LocalVariableTable:
        Start  Length  Slot  Name   Signature
            0      17     0  this   Lorg/sireum/C$;
            0      17     1 $this   I
            0      17     2 other   I
    MethodParameters:
      Name                           Flags
      $this                          final
      other                          final

  public final boolean $eq$bang$eq$extension(int, int);
    descriptor: (II)Z
    flags: (0x0011) ACC_PUBLIC, ACC_FINAL
    Code:
      stack=3, locals=3, args_size=3
         0: getstatic     #67                 // Field org/sireum/B$.MODULE$:Lorg/sireum/B$;
         3: iload_1
         4: iload_2
         5: if_icmpeq     12
         8: iconst_1
         9: goto          13
        12: iconst_0
        13: invokevirtual #70                 // Method org/sireum/B$.apply:(Z)Z
        16: ireturn
      StackMapTable: number_of_entries = 2
        frame_type = 76 /* same_locals_1_stack_item */
          stack = [ class org/sireum/B$ ]
        frame_type = 255 /* full_frame */
          offset_delta = 0
          locals = [ class org/sireum/C$, int, int ]
          stack = [ class org/sireum/B$, int ]
      LineNumberTable:
        line 91: 0
      LocalVariableTable:
        Start  Length  Slot  Name   Signature
            0      17     0  this   Lorg/sireum/C$;
            0      17     1 $this   I
            0      17     2 other   I
    MethodParameters:
      Name                           Flags
      $this                          final
      other                          final

  public final int $greater$greater$greater$extension(int, int);
    descriptor: (II)I
    flags: (0x0011) ACC_PUBLIC, ACC_FINAL
    Code:
      stack=3, locals=3, args_size=3
         0: aload_0
         1: iload_1
         2: iload_2
         3: iushr
         4: invokevirtual #31                 // Method apply:(I)I
         7: ireturn
      LineNumberTable:
        line 93: 0
      LocalVariableTable:
        Start  Length  Slot  Name   Signature
            0       8     0  this   Lorg/sireum/C$;
            0       8     1 $this   I
            0       8     2 other   I
    MethodParameters:
      Name                           Flags
      $this                          final
      other                          final

  public final int $greater$greater$extension(int, int);
    descriptor: (II)I
    flags: (0x0011) ACC_PUBLIC, ACC_FINAL
    Code:
      stack=3, locals=3, args_size=3
         0: aload_0
         1: iload_1
         2: iload_2
         3: iushr
         4: invokevirtual #31                 // Method apply:(I)I
         7: ireturn
      LineNumberTable:
        line 95: 0
      LocalVariableTable:
        Start  Length  Slot  Name   Signature
            0       8     0  this   Lorg/sireum/C$;
            0       8     1 $this   I
            0       8     2 other   I
    MethodParameters:
      Name                           Flags
      $this                          final
      other                          final

  public final int $less$less$extension(int, int);
    descriptor: (II)I
    flags: (0x0011) ACC_PUBLIC, ACC_FINAL
    Code:
      stack=3, locals=3, args_size=3
         0: aload_0
         1: iload_1
         2: iload_2
         3: ishl
         4: invokevirtual #31                 // Method apply:(I)I
         7: ireturn
      LineNumberTable:
        line 97: 0
      LocalVariableTable:
        Start  Length  Slot  Name   Signature
            0       8     0  this   Lorg/sireum/C$;
            0       8     1 $this   I
            0       8     2 other   I
    MethodParameters:
      Name                           Flags
      $this                          final
      other                          final

  public final int $amp$extension(int, int);
    descriptor: (II)I
    flags: (0x0011) ACC_PUBLIC, ACC_FINAL
    Code:
      stack=3, locals=3, args_size=3
         0: aload_0
         1: iload_1
         2: iload_2
         3: iand
         4: invokevirtual #31                 // Method apply:(I)I
         7: ireturn
      LineNumberTable:
        line 99: 0
      LocalVariableTable:
        Start  Length  Slot  Name   Signature
            0       8     0  this   Lorg/sireum/C$;
            0       8     1 $this   I
            0       8     2 other   I
    MethodParameters:
      Name                           Flags
      $this                          final
      other                          final

  public final int $bar$extension(int, int);
    descriptor: (II)I
    flags: (0x0011) ACC_PUBLIC, ACC_FINAL
    Code:
      stack=3, locals=3, args_size=3
         0: aload_0
         1: iload_1
         2: iload_2
         3: ior
         4: invokevirtual #31                 // Method apply:(I)I
         7: ireturn
      LineNumberTable:
        line 101: 0
      LocalVariableTable:
        Start  Length  Slot  Name   Signature
            0       8     0  this   Lorg/sireum/C$;
            0       8     1 $this   I
            0       8     2 other   I
    MethodParameters:
      Name                           Flags
      $this                          final
      other                          final

  public final int $bar$up$extension(int, int);
    descriptor: (II)I
    flags: (0x0011) ACC_PUBLIC, ACC_FINAL
    Code:
      stack=3, locals=3, args_size=3
         0: aload_0
         1: iload_1
         2: iload_2
         3: ixor
         4: invokevirtual #31                 // Method apply:(I)I
         7: ireturn
      LineNumberTable:
        line 103: 0
      LocalVariableTable:
        Start  Length  Slot  Name   Signature
            0       8     0  this   Lorg/sireum/C$;
            0       8     1 $this   I
            0       8     2 other   I
    MethodParameters:
      Name                           Flags
      $this                          final
      other                          final

  public final java.lang.String string$extension(int);
    descriptor: (I)Ljava/lang/String;
    flags: (0x0011) ACC_PUBLIC, ACC_FINAL
    Code:
      stack=3, locals=2, args_size=2
         0: getstatic     #88                 // Field org/sireum/String$.MODULE$:Lorg/sireum/String$;
         3: aload_0
         4: iload_1
         5: invokevirtual #91                 // Method toString$extension:(I)Ljava/lang/String;
         8: invokevirtual #94                 // Method org/sireum/String$.apply:(Ljava/lang/String;)Ljava/lang/String;
        11: areturn
      LineNumberTable:
        line 105: 0
      LocalVariableTable:
        Start  Length  Slot  Name   Signature
            0      12     0  this   Lorg/sireum/C$;
            0      12     1 $this   I
    MethodParameters:
      Name                           Flags
      $this                          final

  public final java.lang.String toString$extension(int);
    descriptor: (I)Ljava/lang/String;
    flags: (0x0011) ACC_PUBLIC, ACC_FINAL
    Code:
      stack=6, locals=2, args_size=2
         0: new           #96                 // class java/lang/String
         3: dup
         4: iconst_1
         5: newarray       int
         7: dup
         8: iconst_0
         9: iload_1
        10: iastore
        11: iconst_0
        12: iconst_1
        13: invokespecial #99                 // Method java/lang/String."<init>":([III)V
        16: areturn
      LineNumberTable:
        line 107: 0
      LocalVariableTable:
        Start  Length  Slot  Name   Signature
            0      17     0  this   Lorg/sireum/C$;
            0      17     1 $this   I
    MethodParameters:
      Name                           Flags
      $this                          final

  public final boolean isWhitespace$extension(int);
    descriptor: (I)Z
    flags: (0x0011) ACC_PUBLIC, ACC_FINAL
    Code:
      stack=4, locals=2, args_size=2
         0: getstatic     #67                 // Field org/sireum/B$.MODULE$:Lorg/sireum/B$;
         3: getstatic     #106                // Field scala/runtime/RichChar$.MODULE$:Lscala/runtime/RichChar$;
         6: getstatic     #111                // Field scala/Predef$.MODULE$:Lscala/Predef$;
         9: iload_1
        10: i2c
        11: invokevirtual #115                // Method scala/Predef$.charWrapper:(C)C
        14: invokevirtual #118                // Method scala/runtime/RichChar$.isWhitespace$extension:(C)Z
        17: invokevirtual #70                 // Method org/sireum/B$.apply:(Z)Z
        20: ireturn
      LineNumberTable:
        line 109: 0
      LocalVariableTable:
        Start  Length  Slot  Name   Signature
            0      21     0  this   Lorg/sireum/C$;
            0      21     1 $this   I
    MethodParameters:
      Name                           Flags
      $this                          final

  public final org.sireum.$internal.Boxer boxer$extension(int);
    descriptor: (I)Lorg/sireum/$internal/Boxer;
    flags: (0x0011) ACC_PUBLIC, ACC_FINAL
    Code:
      stack=1, locals=2, args_size=2
         0: getstatic     #123                // Field org/sireum/C$Boxer$.MODULE$:Lorg/sireum/C$Boxer$;
         3: areturn
      LineNumberTable:
        line 111: 0
      LocalVariableTable:
        Start  Length  Slot  Name   Signature
            0       4     0  this   Lorg/sireum/C$;
            0       4     1 $this   I
    MethodParameters:
      Name                           Flags
      $this                          final

  public final int hashCode$extension(int);
    descriptor: (I)I
    flags: (0x0011) ACC_PUBLIC, ACC_FINAL
    Code:
      stack=1, locals=2, args_size=2
         0: iload_1
         1: invokestatic  #129                // Method java/lang/Integer.hashCode:(I)I
         4: ireturn
      LineNumberTable:
        line 71: 0
      LocalVariableTable:
        Start  Length  Slot  Name   Signature
            0       5     0  this   Lorg/sireum/C$;
            0       5     1 $this   I
    MethodParameters:
      Name                           Flags
      $this                          final

  public final boolean equals$extension(int, java.lang.Object);
    descriptor: (ILjava/lang/Object;)Z
    flags: (0x0011) ACC_PUBLIC, ACC_FINAL
    Code:
      stack=2, locals=6, args_size=3
         0: aload_2
         1: astore        4
         3: aload         4
         5: instanceof    #9                  // class org/sireum/C
         8: ifeq          16
        11: iconst_1
        12: istore_3
        13: goto          24
        16: goto          19
        19: iconst_0
        20: istore_3
        21: goto          24
        24: iload_3
        25: ifeq          55
        28: aload_2
        29: checkcast     #9                  // class org/sireum/C
        32: invokevirtual #135                // Method org/sireum/C.value:()I
        35: istore        5
        37: iload_1
        38: iload         5
        40: if_icmpne     47
        43: iconst_1
        44: goto          48
        47: iconst_0
        48: ifeq          55
        51: iconst_1
        52: goto          56
        55: iconst_0
        56: ireturn
      StackMapTable: number_of_entries = 7
        frame_type = 253 /* append */
          offset_delta = 16
          locals = [ top, class java/lang/Object ]
        frame_type = 2 /* same */
        frame_type = 255 /* full_frame */
          offset_delta = 4
          locals = [ class org/sireum/C$, int, class java/lang/Object, int, class java/lang/Object ]
          stack = []
        frame_type = 252 /* append */
          offset_delta = 22
          locals = [ int ]
        frame_type = 64 /* same_locals_1_stack_item */
          stack = [ int ]
        frame_type = 250 /* chop */
          offset_delta = 6
        frame_type = 64 /* same_locals_1_stack_item */
          stack = [ int ]
      LineNumberTable:
        line 71: 0
      LocalVariableTable:
        Start  Length  Slot  Name   Signature
            0      57     0  this   Lorg/sireum/C$;
            0      57     1 $this   I
            0      57     2   x$1   Ljava/lang/Object;
    MethodParameters:
      Name                           Flags
      $this                          final
      x$1                            final

  private org.sireum.C$();
    descriptor: ()V
    flags: (0x0002) ACC_PRIVATE
    Code:
      stack=1, locals=1, args_size=1
         0: aload_0
         1: invokespecial #137                // Method java/lang/Object."<init>":()V
         4: return
      LineNumberTable:
        line 29: 0
      LocalVariableTable:
        Start  Length  Slot  Name   Signature
            0       5     0  this   Lorg/sireum/C$;
}
InnerClasses:
  public static #10= #7 of #9;            // Boxer$=class org/sireum/C$Boxer$ of class org/sireum/C
SourceFile: "C.scala"
  ScalaInlineInfo: length = 0x8B (unknown attribute)
   01 01 00 1B 00 4F 00 3A 05 00 50 00 3A 05 00 51
   00 3A 05 00 4B 00 3E 05 00 4A 00 3E 05 00 49 00
   3E 05 00 48 00 3E 05 00 4D 00 3A 05 00 4C 00 3A
   05 00 47 00 3E 05 00 3D 00 3E 05 00 4E 00 3A 05
   00 3C 00 3A 05 00 39 00 3A 05 00 0F 00 0E 01 00
   1C 00 33 05 00 1C 00 1D 05 00 77 00 78 01 00 82
   00 83 01 00 7C 00 1D 01 00 64 00 65 05 00 35 00
   36 05 00 14 00 15 01 00 52 00 53 05 00 59 00 53
   05 00 23 00 24 01 00 38 00 1D 05
  Scala: length = 0x0 (unknown attribute)

