Classfile /Users/mw/Projects/slang-braindump/.jar/jar11/assemble/slang-braindump/assemble/content/org/sireum/ContractUtil.class
  Last modified May 29, 2022; size 2721 bytes
  SHA-256 checksum cbbcc3f319164c980d13dd8522b044260e9ea224a7de68850dc239eed2659660
  Compiled from "ContractUtil.scala"
public final class org.sireum.ContractUtil
  minor version: 0
  major version: 52
  flags: (0x0031) ACC_PUBLIC, ACC_FINAL, ACC_SUPER
  this_class: #2                          // org/sireum/ContractUtil
  super_class: #4                         // java/lang/Object
  interfaces: 0, fields: 0, methods: 8, attributes: 3
Constant pool:
   #1 = Utf8               org/sireum/ContractUtil
   #2 = Class              #1             // org/sireum/ContractUtil
   #3 = Utf8               java/lang/Object
   #4 = Class              #3             // java/lang/Object
   #5 = Utf8               ContractUtil.scala
   #6 = Utf8               Lscala/reflect/ScalaSignature;
   #7 = Utf8               bytes
   #8 = Utf8               \u0006\u0005\u0005}q!B\u0006\r\u0011\u0003\tb!B\n\r\u0011\u0003!\u0002\"B\u000e\u0002\t\u0003a\u0002\"B\u000f\u0002\t\u0003q\u0002\"\u0002\u0016\u0002\t\u0003Y\u0003\"B\u0018\u0002\t\u0003\u0001\u0004\"B\'\u0002\t\u0003q\u0005\"\u0002/\u0002\t\u0003i\u0006\"\u00026\u0002\t\u0003Y\u0007\"B<\u0002\t\u0003A\bbBA\u0005\u0003\u0011\u0005\u00111B\u0001\r\u0007>tGO]1diV#\u0018\u000e\u001c\u0006\u0003\u001b9\taa]5sKVl\'\"A\b\u0002\u0007=\u0014xm\u0001\u0001\u0011\u0005I\tQ\"\u0001\u0007\u0003\u0019\r{g\u000e\u001e:bGR,F/\u001b7\u0014\u0005\u0005)\u0002C\u0001\f\u001a\u001b\u00059\"\"\u0001\r\u0002\u000bM\u001c\u0017\r\\1\n\u0005i9\"AB!osJ+g-\u0001\u0004=S:LGO\u0010\u000b\u0002#\u00051Qn\u001c3Q_N$2a\b\u0012%!\t\u0011\u0002%\u0003\u0002\"\u0019\t\t!\fC\u0003$\u0007\u0001\u0007q$A\u0001o\u0011\u0015)3\u00011\u0001 \u0003\u0005i\u0007FA\u0002(!\t\u0011\u0002&\u0003\u0002*\u0019\tQ1\u000f\u001e:jGR\u0004XO]3\u0002\r5|GMT3h)\ryB&\f\u0005\u0006G\u0011\u0001\ra\b\u0005\u0006K\u0011\u0001\ra\b\u0015\u0003\t\u001d\nQ\"[:FcV\fG.\u0012=dKB$XcA\u0019=\rR!!\'\u000e%K!\t\u00112\'\u0003\u00025\u0019\t\t!\tC\u00037\u000b\u0001\u0007q\'\u0001\u0002tcA!!\u0003\u000f\u001eF\u0013\tIDB\u0001\u0002J\'B\u00111\b\u0010\u0007\u0001\t\u0015iTA1\u0001?\u0005\u0005I\u0015CA C!\t1\u0002)\u0003\u0002B/\t9aj\u001c;iS:<\u0007C\u0001\fD\u0013\t!uCA\u0002B]f\u0004\"a\u000f$\u0005\u000b\u001d+!\u0019\u0001 \u0003\u0003QCQ!S\u0003A\u0002]\n!a\u001d\u001a\t\u000b-+\u0001\u0019\u0001\u001e\u0002\u0003%D#!B\u0014\u0002\u001d%\u001cX)];bY\u0016C8-\u001a9ueU\u0019qjU+\u0015\u000bI\u0002fkV-\t\u000bY2\u0001\u0019A)\u0011\tIA$\u000b\u0016\t\u0003wM#Q!\u0010\u0004C\u0002y\u0002\"aO+\u0005\u000b\u001d3!\u0019\u0001 \t\u000b%3\u0001\u0019A)\t\u000ba3\u0001\u0019\u0001*\u0002\u0005%\f\u0004\"\u0002.\u0007\u0001\u0004\u0011\u0016AA53Q\t1q%A\u0007ng\u0016\u000bX/\u00197Fq\u000e,\u0007\u000f^\u000b\u0004=\u00124G\u0003\u0002\u001a`O\"DQAN\u0004A\u0002\u0001\u0004BAE1dK&\u0011!\r\u0004\u0002\u0003\u001bN\u0003\"a\u000f3\u0005\u000bu:!\u0019\u0001 \u0011\u0005m2G!B$\b\u0005\u0004q\u0004\"B%\b\u0001\u0004\u0001\u0007\"B&\b\u0001\u0004\u0019\u0007FA\u0004(\u00039i7/R9vC2,\u0005pY3qiJ*2\u0001\u001c9s)\u0015\u0011Tn\u001d;v\u0011\u00151\u0004\u00021\u0001o!\u0011\u0011\u0012m\\9\u0011\u0005m\u0002H!B\u001f\t\u0005\u0004q\u0004CA\u001es\t\u00159\u0005B1\u0001?\u0011\u0015I\u0005\u00021\u0001o\u0011\u0015A\u0006\u00021\u0001p\u0011\u0015Q\u0006\u00021\u0001pQ\tAq%A\u0004jg\u0006cG.S*\u0016\tet\u0018\u0011\u0001\u000b\u0005ei\f\u0019\u0001C\u0003|\u0013\u0001\u0007A0A\u0001t!\u0011\u0011\u0002(`@\u0011\u0005mrH!B\u001f\n\u0005\u0004q\u0004cA\u001e\u0002\u0002\u0011)q)\u0003b\u0001}!1\u0011QA\u0005A\u0002}\f\u0011!\u001a\u0015\u0003\u0013\u001d\nq![:BY2l5+\u0006\u0004\u0002\u000e\u0005U\u0011\u0011\u0004\u000b\u0006e\u0005=\u00111\u0004\u0005\u0007w*\u0001\r!!\u0005\u0011\rI\t\u00171CA\f!\rY\u0014Q\u0003\u0003\u0006{)\u0011\rA\u0010\t\u0004w\u0005eA!B$\u000b\u0005\u0004q\u0004bBA\u0003\u0015\u0001\u0007\u0011q\u0003\u0015\u0003\u0015\u001d\u0002
   #9 = Utf8               isAllMS
  #10 = Utf8               (Lorg/sireum/MS;Ljava/lang/Object;)Z
  #11 = Utf8               s
  #12 = Utf8               e
  #13 = Utf8               org/sireum/ContractUtil$
  #14 = Class              #13            // org/sireum/ContractUtil$
  #15 = Utf8               MODULE$
  #16 = Utf8               Lorg/sireum/ContractUtil$;
  #17 = NameAndType        #15:#16        // MODULE$:Lorg/sireum/ContractUtil$;
  #18 = Fieldref           #14.#17        // org/sireum/ContractUtil$.MODULE$:Lorg/sireum/ContractUtil$;
  #19 = NameAndType        #9:#10         // isAllMS:(Lorg/sireum/MS;Ljava/lang/Object;)Z
  #20 = Methodref          #14.#19        // org/sireum/ContractUtil$.isAllMS:(Lorg/sireum/MS;Ljava/lang/Object;)Z
  #21 = Utf8               Lorg/sireum/MS;
  #22 = Utf8               Ljava/lang/Object;
  #23 = Utf8               isAllIS
  #24 = Utf8               (Lorg/sireum/IS;Ljava/lang/Object;)Z
  #25 = NameAndType        #23:#24        // isAllIS:(Lorg/sireum/IS;Ljava/lang/Object;)Z
  #26 = Methodref          #14.#25        // org/sireum/ContractUtil$.isAllIS:(Lorg/sireum/IS;Ljava/lang/Object;)Z
  #27 = Utf8               Lorg/sireum/IS;
  #28 = Utf8               msEqualExcept2
  #29 = Utf8               (Lorg/sireum/MS;Lorg/sireum/MS;Ljava/lang/Object;Ljava/lang/Object;)Z
  #30 = Utf8               s1
  #31 = Utf8               s2
  #32 = Utf8               i1
  #33 = Utf8               i2
  #34 = NameAndType        #28:#29        // msEqualExcept2:(Lorg/sireum/MS;Lorg/sireum/MS;Ljava/lang/Object;Ljava/lang/Object;)Z
  #35 = Methodref          #14.#34        // org/sireum/ContractUtil$.msEqualExcept2:(Lorg/sireum/MS;Lorg/sireum/MS;Ljava/lang/Object;Ljava/lang/Object;)Z
  #36 = Utf8               msEqualExcept
  #37 = Utf8               (Lorg/sireum/MS;Lorg/sireum/MS;Ljava/lang/Object;)Z
  #38 = Utf8               i
  #39 = NameAndType        #36:#37        // msEqualExcept:(Lorg/sireum/MS;Lorg/sireum/MS;Ljava/lang/Object;)Z
  #40 = Methodref          #14.#39        // org/sireum/ContractUtil$.msEqualExcept:(Lorg/sireum/MS;Lorg/sireum/MS;Ljava/lang/Object;)Z
  #41 = Utf8               isEqualExcept2
  #42 = Utf8               (Lorg/sireum/IS;Lorg/sireum/IS;Ljava/lang/Object;Ljava/lang/Object;)Z
  #43 = NameAndType        #41:#42        // isEqualExcept2:(Lorg/sireum/IS;Lorg/sireum/IS;Ljava/lang/Object;Ljava/lang/Object;)Z
  #44 = Methodref          #14.#43        // org/sireum/ContractUtil$.isEqualExcept2:(Lorg/sireum/IS;Lorg/sireum/IS;Ljava/lang/Object;Ljava/lang/Object;)Z
  #45 = Utf8               isEqualExcept
  #46 = Utf8               (Lorg/sireum/IS;Lorg/sireum/IS;Ljava/lang/Object;)Z
  #47 = NameAndType        #45:#46        // isEqualExcept:(Lorg/sireum/IS;Lorg/sireum/IS;Ljava/lang/Object;)Z
  #48 = Methodref          #14.#47        // org/sireum/ContractUtil$.isEqualExcept:(Lorg/sireum/IS;Lorg/sireum/IS;Ljava/lang/Object;)Z
  #49 = Utf8               modNeg
  #50 = Utf8               (Lorg/sireum/Z;Lorg/sireum/Z;)Lorg/sireum/Z;
  #51 = Utf8               n
  #52 = Utf8               m
  #53 = NameAndType        #49:#50        // modNeg:(Lorg/sireum/Z;Lorg/sireum/Z;)Lorg/sireum/Z;
  #54 = Methodref          #14.#53        // org/sireum/ContractUtil$.modNeg:(Lorg/sireum/Z;Lorg/sireum/Z;)Lorg/sireum/Z;
  #55 = Utf8               Lorg/sireum/Z;
  #56 = Utf8               modPos
  #57 = NameAndType        #56:#50        // modPos:(Lorg/sireum/Z;Lorg/sireum/Z;)Lorg/sireum/Z;
  #58 = Methodref          #14.#57        // org/sireum/ContractUtil$.modPos:(Lorg/sireum/Z;Lorg/sireum/Z;)Lorg/sireum/Z;
  #59 = Utf8               Code
  #60 = Utf8               LocalVariableTable
  #61 = Utf8               MethodParameters
  #62 = Utf8               SourceFile
  #63 = Utf8               RuntimeVisibleAnnotations
  #64 = Utf8               ScalaSig
{
  public static boolean isAllMS(org.sireum.MS, java.lang.Object);
    descriptor: (Lorg/sireum/MS;Ljava/lang/Object;)Z
    flags: (0x0009) ACC_PUBLIC, ACC_STATIC
    Code:
      stack=3, locals=2, args_size=2
         0: getstatic     #18                 // Field org/sireum/ContractUtil$.MODULE$:Lorg/sireum/ContractUtil$;
         3: aload_0
         4: aload_1
         5: invokevirtual #20                 // Method org/sireum/ContractUtil$.isAllMS:(Lorg/sireum/MS;Ljava/lang/Object;)Z
         8: ireturn
      LocalVariableTable:
        Start  Length  Slot  Name   Signature
            0       9     0     s   Lorg/sireum/MS;
            0       9     1     e   Ljava/lang/Object;
    MethodParameters:
      Name                           Flags
      s                              final
      e                              final

  public static boolean isAllIS(org.sireum.IS, java.lang.Object);
    descriptor: (Lorg/sireum/IS;Ljava/lang/Object;)Z
    flags: (0x0009) ACC_PUBLIC, ACC_STATIC
    Code:
      stack=3, locals=2, args_size=2
         0: getstatic     #18                 // Field org/sireum/ContractUtil$.MODULE$:Lorg/sireum/ContractUtil$;
         3: aload_0
         4: aload_1
         5: invokevirtual #26                 // Method org/sireum/ContractUtil$.isAllIS:(Lorg/sireum/IS;Ljava/lang/Object;)Z
         8: ireturn
      LocalVariableTable:
        Start  Length  Slot  Name   Signature
            0       9     0     s   Lorg/sireum/IS;
            0       9     1     e   Ljava/lang/Object;
    MethodParameters:
      Name                           Flags
      s                              final
      e                              final

  public static boolean msEqualExcept2(org.sireum.MS, org.sireum.MS, java.lang.Object, java.lang.Object);
    descriptor: (Lorg/sireum/MS;Lorg/sireum/MS;Ljava/lang/Object;Ljava/lang/Object;)Z
    flags: (0x0009) ACC_PUBLIC, ACC_STATIC
    Code:
      stack=5, locals=4, args_size=4
         0: getstatic     #18                 // Field org/sireum/ContractUtil$.MODULE$:Lorg/sireum/ContractUtil$;
         3: aload_0
         4: aload_1
         5: aload_2
         6: aload_3
         7: invokevirtual #35                 // Method org/sireum/ContractUtil$.msEqualExcept2:(Lorg/sireum/MS;Lorg/sireum/MS;Ljava/lang/Object;Ljava/lang/Object;)Z
        10: ireturn
      LocalVariableTable:
        Start  Length  Slot  Name   Signature
            0      11     0    s1   Lorg/sireum/MS;
            0      11     1    s2   Lorg/sireum/MS;
            0      11     2    i1   Ljava/lang/Object;
            0      11     3    i2   Ljava/lang/Object;
    MethodParameters:
      Name                           Flags
      s1                             final
      s2                             final
      i1                             final
      i2                             final

  public static boolean msEqualExcept(org.sireum.MS, org.sireum.MS, java.lang.Object);
    descriptor: (Lorg/sireum/MS;Lorg/sireum/MS;Ljava/lang/Object;)Z
    flags: (0x0009) ACC_PUBLIC, ACC_STATIC
    Code:
      stack=4, locals=3, args_size=3
         0: getstatic     #18                 // Field org/sireum/ContractUtil$.MODULE$:Lorg/sireum/ContractUtil$;
         3: aload_0
         4: aload_1
         5: aload_2
         6: invokevirtual #40                 // Method org/sireum/ContractUtil$.msEqualExcept:(Lorg/sireum/MS;Lorg/sireum/MS;Ljava/lang/Object;)Z
         9: ireturn
      LocalVariableTable:
        Start  Length  Slot  Name   Signature
            0      10     0    s1   Lorg/sireum/MS;
            0      10     1    s2   Lorg/sireum/MS;
            0      10     2     i   Ljava/lang/Object;
    MethodParameters:
      Name                           Flags
      s1                             final
      s2                             final
      i                              final

  public static boolean isEqualExcept2(org.sireum.IS, org.sireum.IS, java.lang.Object, java.lang.Object);
    descriptor: (Lorg/sireum/IS;Lorg/sireum/IS;Ljava/lang/Object;Ljava/lang/Object;)Z
    flags: (0x0009) ACC_PUBLIC, ACC_STATIC
    Code:
      stack=5, locals=4, args_size=4
         0: getstatic     #18                 // Field org/sireum/ContractUtil$.MODULE$:Lorg/sireum/ContractUtil$;
         3: aload_0
         4: aload_1
         5: aload_2
         6: aload_3
         7: invokevirtual #44                 // Method org/sireum/ContractUtil$.isEqualExcept2:(Lorg/sireum/IS;Lorg/sireum/IS;Ljava/lang/Object;Ljava/lang/Object;)Z
        10: ireturn
      LocalVariableTable:
        Start  Length  Slot  Name   Signature
            0      11     0    s1   Lorg/sireum/IS;
            0      11     1    s2   Lorg/sireum/IS;
            0      11     2    i1   Ljava/lang/Object;
            0      11     3    i2   Ljava/lang/Object;
    MethodParameters:
      Name                           Flags
      s1                             final
      s2                             final
      i1                             final
      i2                             final

  public static boolean isEqualExcept(org.sireum.IS, org.sireum.IS, java.lang.Object);
    descriptor: (Lorg/sireum/IS;Lorg/sireum/IS;Ljava/lang/Object;)Z
    flags: (0x0009) ACC_PUBLIC, ACC_STATIC
    Code:
      stack=4, locals=3, args_size=3
         0: getstatic     #18                 // Field org/sireum/ContractUtil$.MODULE$:Lorg/sireum/ContractUtil$;
         3: aload_0
         4: aload_1
         5: aload_2
         6: invokevirtual #48                 // Method org/sireum/ContractUtil$.isEqualExcept:(Lorg/sireum/IS;Lorg/sireum/IS;Ljava/lang/Object;)Z
         9: ireturn
      LocalVariableTable:
        Start  Length  Slot  Name   Signature
            0      10     0    s1   Lorg/sireum/IS;
            0      10     1    s2   Lorg/sireum/IS;
            0      10     2     i   Ljava/lang/Object;
    MethodParameters:
      Name                           Flags
      s1                             final
      s2                             final
      i                              final

  public static org.sireum.Z modNeg(org.sireum.Z, org.sireum.Z);
    descriptor: (Lorg/sireum/Z;Lorg/sireum/Z;)Lorg/sireum/Z;
    flags: (0x0009) ACC_PUBLIC, ACC_STATIC
    Code:
      stack=3, locals=2, args_size=2
         0: getstatic     #18                 // Field org/sireum/ContractUtil$.MODULE$:Lorg/sireum/ContractUtil$;
         3: aload_0
         4: aload_1
         5: invokevirtual #54                 // Method org/sireum/ContractUtil$.modNeg:(Lorg/sireum/Z;Lorg/sireum/Z;)Lorg/sireum/Z;
         8: areturn
      LocalVariableTable:
        Start  Length  Slot  Name   Signature
            0       9     0     n   Lorg/sireum/Z;
            0       9     1     m   Lorg/sireum/Z;
    MethodParameters:
      Name                           Flags
      n                              final
      m                              final

  public static org.sireum.Z modPos(org.sireum.Z, org.sireum.Z);
    descriptor: (Lorg/sireum/Z;Lorg/sireum/Z;)Lorg/sireum/Z;
    flags: (0x0009) ACC_PUBLIC, ACC_STATIC
    Code:
      stack=3, locals=2, args_size=2
         0: getstatic     #18                 // Field org/sireum/ContractUtil$.MODULE$:Lorg/sireum/ContractUtil$;
         3: aload_0
         4: aload_1
         5: invokevirtual #58                 // Method org/sireum/ContractUtil$.modPos:(Lorg/sireum/Z;Lorg/sireum/Z;)Lorg/sireum/Z;
         8: areturn
      LocalVariableTable:
        Start  Length  Slot  Name   Signature
            0       9     0     n   Lorg/sireum/Z;
            0       9     1     m   Lorg/sireum/Z;
    MethodParameters:
      Name                           Flags
      n                              final
      m                              final
}
SourceFile: "ContractUtil.scala"
RuntimeVisibleAnnotations:
  0: #6(#7=s#8)
    scala.reflect.ScalaSignature(
      bytes="\u0006\u0005\u0005}q!B\u0006\r\u0011\u0003\tb!B\n\r\u0011\u0003!\u0002\"B\u000e\u0002\t\u0003a\u0002\"B\u000f\u0002\t\u0003q\u0002\"\u0002\u0016\u0002\t\u0003Y\u0003\"B\u0018\u0002\t\u0003\u0001\u0004\"B\'\u0002\t\u0003q\u0005\"\u0002/\u0002\t\u0003i\u0006\"\u00026\u0002\t\u0003Y\u0007\"B<\u0002\t\u0003A\bbBA\u0005\u0003\u0011\u0005\u00111B\u0001\r\u0007>tGO]1diV#\u0018\u000e\u001c\u0006\u0003\u001b9\taa]5sKVl\'\"A\b\u0002\u0007=\u0014xm\u0001\u0001\u0011\u0005I\tQ\"\u0001\u0007\u0003\u0019\r{g\u000e\u001e:bGR,F/\u001b7\u0014\u0005\u0005)\u0002C\u0001\f\u001a\u001b\u00059\"\"\u0001\r\u0002\u000bM\u001c\u0017\r\\1\n\u0005i9\"AB!osJ+g-\u0001\u0004=S:LGO\u0010\u000b\u0002#\u00051Qn\u001c3Q_N$2a\b\u0012%!\t\u0011\u0002%\u0003\u0002\"\u0019\t\t!\fC\u0003$\u0007\u0001\u0007q$A\u0001o\u0011\u0015)3\u00011\u0001 \u0003\u0005i\u0007FA\u0002(!\t\u0011\u0002&\u0003\u0002*\u0019\tQ1\u000f\u001e:jGR\u0004XO]3\u0002\r5|GMT3h)\ryB&\f\u0005\u0006G\u0011\u0001\ra\b\u0005\u0006K\u0011\u0001\ra\b\u0015\u0003\t\u001d\nQ\"[:FcV\fG.\u0012=dKB$XcA\u0019=\rR!!\'\u000e%K!\t\u00112\'\u0003\u00025\u0019\t\t!\tC\u00037\u000b\u0001\u0007q\'\u0001\u0002tcA!!\u0003\u000f\u001eF\u0013\tIDB\u0001\u0002J\'B\u00111\b\u0010\u0007\u0001\t\u0015iTA1\u0001?\u0005\u0005I\u0015CA C!\t1\u0002)\u0003\u0002B/\t9aj\u001c;iS:<\u0007C\u0001\fD\u0013\t!uCA\u0002B]f\u0004\"a\u000f$\u0005\u000b\u001d+!\u0019\u0001 \u0003\u0003QCQ!S\u0003A\u0002]\n!a\u001d\u001a\t\u000b-+\u0001\u0019\u0001\u001e\u0002\u0003%D#!B\u0014\u0002\u001d%\u001cX)];bY\u0016C8-\u001a9ueU\u0019qjU+\u0015\u000bI\u0002fkV-\t\u000bY2\u0001\u0019A)\u0011\tIA$\u000b\u0016\t\u0003wM#Q!\u0010\u0004C\u0002y\u0002\"aO+\u0005\u000b\u001d3!\u0019\u0001 \t\u000b%3\u0001\u0019A)\t\u000ba3\u0001\u0019\u0001*\u0002\u0005%\f\u0004\"\u0002.\u0007\u0001\u0004\u0011\u0016AA53Q\t1q%A\u0007ng\u0016\u000bX/\u00197Fq\u000e,\u0007\u000f^\u000b\u0004=\u00124G\u0003\u0002\u001a`O\"DQAN\u0004A\u0002\u0001\u0004BAE1dK&\u0011!\r\u0004\u0002\u0003\u001bN\u0003\"a\u000f3\u0005\u000bu:!\u0019\u0001 \u0011\u0005m2G!B$\b\u0005\u0004q\u0004\"B%\b\u0001\u0004\u0001\u0007\"B&\b\u0001\u0004\u0019\u0007FA\u0004(\u00039i7/R9vC2,\u0005pY3qiJ*2\u0001\u001c9s)\u0015\u0011Tn\u001d;v\u0011\u00151\u0004\u00021\u0001o!\u0011\u0011\u0012m\\9\u0011\u0005m\u0002H!B\u001f\t\u0005\u0004q\u0004CA\u001es\t\u00159\u0005B1\u0001?\u0011\u0015I\u0005\u00021\u0001o\u0011\u0015A\u0006\u00021\u0001p\u0011\u0015Q\u0006\u00021\u0001pQ\tAq%A\u0004jg\u0006cG.S*\u0016\tet\u0018\u0011\u0001\u000b\u0005ei\f\u0019\u0001C\u0003|\u0013\u0001\u0007A0A\u0001t!\u0011\u0011\u0002(`@\u0011\u0005mrH!B\u001f\n\u0005\u0004q\u0004cA\u001e\u0002\u0002\u0011)q)\u0003b\u0001}!1\u0011QA\u0005A\u0002}\f\u0011!\u001a\u0015\u0003\u0013\u001d\nq![:BY2l5+\u0006\u0004\u0002\u000e\u0005U\u0011\u0011\u0004\u000b\u0006e\u0005=\u00111\u0004\u0005\u0007w*\u0001\r!!\u0005\u0011\rI\t\u00171CA\f!\rY\u0014Q\u0003\u0003\u0006{)\u0011\rA\u0010\t\u0004w\u0005eA!B$\u000b\u0005\u0004q\u0004bBA\u0003\u0015\u0001\u0007\u0011q\u0003\u0015\u0003\u0015\u001d\u0002"
    )
  ScalaSig: length = 0x3 (unknown attribute)
   05 02 00
