Classfile /Users/mw/Projects/slang-braindump/.jar/jar11/assemble/slang-braindump/assemble/content/org/sireum/contract$Spec$.class
  Last modified May 29, 2022; size 531 bytes
  SHA-256 checksum 2d3d8b3e590790376149a44e6024fd1283ed14717e594dce08864a7e7f326575
  Compiled from "contract.scala"
public class org.sireum.contract$Spec$
  minor version: 0
  major version: 52
  flags: (0x0021) ACC_PUBLIC, ACC_SUPER
  this_class: #2                          // org/sireum/contract$Spec$
  super_class: #4                         // java/lang/Object
  interfaces: 0, fields: 0, methods: 1, attributes: 4
Constant pool:
   #1 = Utf8               org/sireum/contract$Spec$
   #2 = Class              #1             // org/sireum/contract$Spec$
   #3 = Utf8               java/lang/Object
   #4 = Class              #3             // java/lang/Object
   #5 = Utf8               contract.scala
   #6 = Utf8               org/sireum/contract
   #7 = Class              #6             // org/sireum/contract
   #8 = Utf8               Spec$
   #9 = Utf8               <init>
  #10 = Utf8               (Lorg/sireum/contract;)V
  #11 = Utf8               $outer
  #12 = Utf8               ()V
  #13 = NameAndType        #9:#12         // "<init>":()V
  #14 = Methodref          #4.#13         // java/lang/Object."<init>":()V
  #15 = Utf8               this
  #16 = Utf8               Lorg/sireum/contract$Spec$;
  #17 = Utf8               Lorg/sireum/contract;
  #18 = Utf8               Code
  #19 = Utf8               LineNumberTable
  #20 = Utf8               LocalVariableTable
  #21 = Utf8               MethodParameters
  #22 = Utf8               InnerClasses
  #23 = Utf8               SourceFile
  #24 = Utf8               ScalaInlineInfo
  #25 = Utf8               apply
  #26 = Utf8               (Lscala/Function0;)V
  #27 = Utf8               Scala
{
  public org.sireum.contract$Spec$(org.sireum.contract);
    descriptor: (Lorg/sireum/contract;)V
    flags: (0x0001) ACC_PUBLIC
    Code:
      stack=1, locals=2, args_size=2
         0: aload_0
         1: invokespecial #14                 // Method java/lang/Object."<init>":()V
         4: return
      LineNumberTable:
        line 34: 0
      LocalVariableTable:
        Start  Length  Slot  Name   Signature
            0       5     0  this   Lorg/sireum/contract$Spec$;
            0       5     1 $outer   Lorg/sireum/contract;
    MethodParameters:
      Name                           Flags
      $outer                         final synthetic
}
InnerClasses:
  public #8= #2 of #7;                    // Spec$=class org/sireum/contract$Spec$ of class org/sireum/contract
SourceFile: "contract.scala"
  ScalaInlineInfo: length = 0xE (unknown attribute)
   01 01 00 02 00 09 00 0A 01 00 19 00 1A 01
  Scala: length = 0x0 (unknown attribute)

