Classfile /Users/mw/Projects/slang-braindump/.jar/jar11/assemble/slang-braindump/assemble/content/org/sireum/contract$Contract$.class
  Last modified May 29, 2022; size 5074 bytes
  SHA-256 checksum 87901f19c6e327496d934284edd7133749b9edcca9d9d5ff1e874304d0ce50c6
  Compiled from "contract.scala"
public class org.sireum.contract$Contract$
  minor version: 0
  major version: 52
  flags: (0x0021) ACC_PUBLIC, ACC_SUPER
  this_class: #2                          // org/sireum/contract$Contract$
  super_class: #4                         // java/lang/Object
  interfaces: 0, fields: 2, methods: 5, attributes: 4
Constant pool:
    #1 = Utf8               org/sireum/contract$Contract$
    #2 = Class              #1            // org/sireum/contract$Contract$
    #3 = Utf8               java/lang/Object
    #4 = Class              #3            // java/lang/Object
    #5 = Utf8               contract.scala
    #6 = Utf8               org/sireum/contract
    #7 = Class              #6            // org/sireum/contract
    #8 = Utf8               Contract$
    #9 = Utf8               org/sireum/contract$Contract$Assert
   #10 = Class              #9            // org/sireum/contract$Contract$Assert
   #11 = Utf8               Assert
   #12 = Utf8               org/sireum/contract$Contract$Assume
   #13 = Class              #12           // org/sireum/contract$Contract$Assume
   #14 = Utf8               Assume
   #15 = Utf8               org/sireum/contract$Contract$Case
   #16 = Class              #15           // org/sireum/contract$Contract$Case
   #17 = Utf8               Case
   #18 = Utf8               org/sireum/contract$Contract$DataRefinement
   #19 = Class              #18           // org/sireum/contract$Contract$DataRefinement
   #20 = Utf8               DataRefinement
   #21 = Utf8               org/sireum/contract$Contract$Ensures
   #22 = Class              #21           // org/sireum/contract$Contract$Ensures
   #23 = Utf8               Ensures
   #24 = Utf8               org/sireum/contract$Contract$Fact
   #25 = Class              #24           // org/sireum/contract$Contract$Fact
   #26 = Utf8               Fact
   #27 = Utf8               org/sireum/contract$Contract$Invariant
   #28 = Class              #27           // org/sireum/contract$Contract$Invariant
   #29 = Utf8               Invariant
   #30 = Utf8               org/sireum/contract$Contract$Justification
   #31 = Class              #30           // org/sireum/contract$Contract$Justification
   #32 = Utf8               Justification
   #33 = Utf8               org/sireum/contract$Contract$Lemma
   #34 = Class              #33           // org/sireum/contract$Contract$Lemma
   #35 = Utf8               Lemma
   #36 = Utf8               org/sireum/contract$Contract$Let
   #37 = Class              #36           // org/sireum/contract$Contract$Let
   #38 = Utf8               Let
   #39 = Utf8               org/sireum/contract$Contract$MaxIt
   #40 = Class              #39           // org/sireum/contract$Contract$MaxIt
   #41 = Utf8               MaxIt
   #42 = Utf8               org/sireum/contract$Contract$Modifies
   #43 = Class              #42           // org/sireum/contract$Contract$Modifies
   #44 = Utf8               Modifies
   #45 = Utf8               org/sireum/contract$Contract$Only$
   #46 = Class              #45           // org/sireum/contract$Contract$Only$
   #47 = Utf8               Only$
   #48 = Utf8               org/sireum/contract$Contract$Proof
   #49 = Class              #48           // org/sireum/contract$Contract$Proof
   #50 = Utf8               Proof
   #51 = Utf8               org/sireum/contract$Contract$ProofStep
   #52 = Class              #51           // org/sireum/contract$Contract$ProofStep
   #53 = Utf8               ProofStep
   #54 = Utf8               org/sireum/contract$Contract$Reads
   #55 = Class              #54           // org/sireum/contract$Contract$Reads
   #56 = Utf8               Reads
   #57 = Utf8               org/sireum/contract$Contract$Requires
   #58 = Class              #57           // org/sireum/contract$Contract$Requires
   #59 = Utf8               Requires
   #60 = Utf8               org/sireum/contract$Contract$Sequent
   #61 = Class              #60           // org/sireum/contract$Contract$Sequent
   #62 = Utf8               Sequent
   #63 = Utf8               org/sireum/contract$Contract$SequentBuilder
   #64 = Class              #63           // org/sireum/contract$Contract$SequentBuilder
   #65 = Utf8               SequentBuilder
   #66 = Utf8               org/sireum/contract$Contract$State
   #67 = Class              #66           // org/sireum/contract$Contract$State
   #68 = Utf8               State
   #69 = Utf8               org/sireum/contract$Contract$StateCont
   #70 = Class              #69           // org/sireum/contract$Contract$StateCont
   #71 = Utf8               StateCont
   #72 = Utf8               org/sireum/contract$Contract$StatePost
   #73 = Class              #72           // org/sireum/contract$Contract$StatePost
   #74 = Utf8               StatePost
   #75 = Utf8               org/sireum/contract$Contract$StepBuilder
   #76 = Class              #75           // org/sireum/contract$Contract$StepBuilder
   #77 = Utf8               StepBuilder
   #78 = Utf8               org/sireum/contract$Contract$StepBuilder2
   #79 = Class              #78           // org/sireum/contract$Contract$StepBuilder2
   #80 = Utf8               StepBuilder2
   #81 = Utf8               org/sireum/contract$Contract$StepBuilder3
   #82 = Class              #81           // org/sireum/contract$Contract$StepBuilder3
   #83 = Utf8               StepBuilder3
   #84 = Utf8               org/sireum/contract$Contract$StepBuilder3$
   #85 = Class              #84           // org/sireum/contract$Contract$StepBuilder3$
   #86 = Utf8               StepBuilder3$
   #87 = Utf8               org/sireum/contract$Contract$SubProof
   #88 = Class              #87           // org/sireum/contract$Contract$SubProof
   #89 = Utf8               SubProof
   #90 = Utf8               org/sireum/contract$Contract$Theorem
   #91 = Class              #90           // org/sireum/contract$Contract$Theorem
   #92 = Utf8               Theorem
   #93 = Utf8               Only$module
   #94 = Utf8               Lorg/sireum/contract$Contract$Only$;
   #95 = Utf8               StepBuilder3$module
   #96 = Utf8               Lorg/sireum/contract$Contract$StepBuilder3$;
   #97 = Utf8               Only
   #98 = Utf8               ()Lorg/sireum/contract$Contract$Only$;
   #99 = NameAndType        #93:#94       // Only$module:Lorg/sireum/contract$Contract$Only$;
  #100 = Fieldref           #2.#99        // org/sireum/contract$Contract$.Only$module:Lorg/sireum/contract$Contract$Only$;
  #101 = Utf8               Only$lzycompute$1
  #102 = Utf8               ()V
  #103 = NameAndType        #101:#102     // Only$lzycompute$1:()V
  #104 = Methodref          #2.#103       // org/sireum/contract$Contract$.Only$lzycompute$1:()V
  #105 = Utf8               this
  #106 = Utf8               Lorg/sireum/contract$Contract$;
  #107 = Utf8               ()Lorg/sireum/contract$Contract$StepBuilder3$;
  #108 = NameAndType        #95:#96       // StepBuilder3$module:Lorg/sireum/contract$Contract$StepBuilder3$;
  #109 = Fieldref           #2.#108       // org/sireum/contract$Contract$.StepBuilder3$module:Lorg/sireum/contract$Contract$StepBuilder3$;
  #110 = Utf8               StepBuilder3$lzycompute$1
  #111 = NameAndType        #110:#102     // StepBuilder3$lzycompute$1:()V
  #112 = Methodref          #2.#111       // org/sireum/contract$Contract$.StepBuilder3$lzycompute$1:()V
  #113 = Utf8               <init>
  #114 = Utf8               (Lorg/sireum/contract$Contract$;)V
  #115 = NameAndType        #113:#114     // "<init>":(Lorg/sireum/contract$Contract$;)V
  #116 = Methodref          #46.#115      // org/sireum/contract$Contract$Only$."<init>":(Lorg/sireum/contract$Contract$;)V
  #117 = Utf8               java/lang/Throwable
  #118 = Class              #117          // java/lang/Throwable
  #119 = Methodref          #85.#115      // org/sireum/contract$Contract$StepBuilder3$."<init>":(Lorg/sireum/contract$Contract$;)V
  #120 = Utf8               (Lorg/sireum/contract;)V
  #121 = Utf8               $outer
  #122 = NameAndType        #113:#102     // "<init>":()V
  #123 = Methodref          #4.#122       // java/lang/Object."<init>":()V
  #124 = Utf8               Lorg/sireum/contract;
  #125 = Utf8               Code
  #126 = Utf8               StackMapTable
  #127 = Utf8               LineNumberTable
  #128 = Utf8               LocalVariableTable
  #129 = Utf8               MethodParameters
  #130 = Utf8               InnerClasses
  #131 = Utf8               SourceFile
  #132 = Utf8               ScalaInlineInfo
  #133 = Utf8               Havoc
  #134 = Utf8               (Ljava/lang/Object;Lscala/collection/immutable/Seq;)V
  #135 = Utf8               apply
  #136 = Utf8               (Ljava/lang/String;)V
  #137 = Utf8               (Lorg/sireum/contract$Contract$Case;Lscala/collection/immutable/Seq;)V
  #138 = Utf8               (Lorg/sireum/contract$Contract$DataRefinement;)V
  #139 = Utf8               (Lorg/sireum/contract$Contract$Ensures;)V
  #140 = Utf8               (Lorg/sireum/contract$Contract$Modifies;)V
  #141 = Utf8               (Lorg/sireum/contract$Contract$Modifies;Lorg/sireum/contract$Contract$Case;Lscala/collection/immutable/Seq;)V
  #142 = Utf8               (Lorg/sireum/contract$Contract$Modifies;Lorg/sireum/contract$Contract$Ensures;)V
  #143 = Utf8               (Lorg/sireum/contract$Contract$Reads;)V
  #144 = Utf8               (Lorg/sireum/contract$Contract$Reads;Lorg/sireum/contract$Contract$Case;Lscala/collection/immutable/Seq;)V
  #145 = Utf8               (Lorg/sireum/contract$Contract$Reads;Lorg/sireum/contract$Contract$Ensures;)V
  #146 = Utf8               (Lorg/sireum/contract$Contract$Reads;Lorg/sireum/contract$Contract$Modifies;)V
  #147 = Utf8               (Lorg/sireum/contract$Contract$Reads;Lorg/sireum/contract$Contract$Modifies;Lorg/sireum/contract$Contract$Case;Lscala/collection/immutable/Seq;)V
  #148 = Utf8               (Lorg/sireum/contract$Contract$Reads;Lorg/sireum/contract$Contract$Modifies;Lorg/sireum/contract$Contract$Ensures;)V
  #149 = Utf8               (Lorg/sireum/contract$Contract$Reads;Lorg/sireum/contract$Contract$Requires;)V
  #150 = Utf8               (Lorg/sireum/contract$Contract$Reads;Lorg/sireum/contract$Contract$Requires;Lorg/sireum/contract$Contract$Ensures;)V
  #151 = Utf8               (Lorg/sireum/contract$Contract$Reads;Lorg/sireum/contract$Contract$Requires;Lorg/sireum/contract$Contract$Modifies;)V
  #152 = Utf8               (Lorg/sireum/contract$Contract$Reads;Lorg/sireum/contract$Contract$Requires;Lorg/sireum/contract$Contract$Modifies;Lorg/sireum/contract$Contract$Ensures;)V
  #153 = Utf8               (Lorg/sireum/contract$Contract$Requires;)V
  #154 = Utf8               (Lorg/sireum/contract$Contract$Requires;Lorg/sireum/contract$Contract$Ensures;)V
  #155 = Utf8               (Lorg/sireum/contract$Contract$Requires;Lorg/sireum/contract$Contract$Modifies;)V
  #156 = Utf8               (Lorg/sireum/contract$Contract$Requires;Lorg/sireum/contract$Contract$Modifies;Lorg/sireum/contract$Contract$Ensures;)V
  #157 = Utf8               Scala
{
  private volatile org.sireum.contract$Contract$Only$ Only$module;
    descriptor: Lorg/sireum/contract$Contract$Only$;
    flags: (0x0042) ACC_PRIVATE, ACC_VOLATILE

  private volatile org.sireum.contract$Contract$StepBuilder3$ StepBuilder3$module;
    descriptor: Lorg/sireum/contract$Contract$StepBuilder3$;
    flags: (0x0042) ACC_PRIVATE, ACC_VOLATILE

  public org.sireum.contract$Contract$Only$ Only();
    descriptor: ()Lorg/sireum/contract$Contract$Only$;
    flags: (0x0001) ACC_PUBLIC
    Code:
      stack=1, locals=1, args_size=1
         0: aload_0
         1: getfield      #100                // Field Only$module:Lorg/sireum/contract$Contract$Only$;
         4: ifnonnull     11
         7: aload_0
         8: invokespecial #104                // Method Only$lzycompute$1:()V
        11: aload_0
        12: getfield      #100                // Field Only$module:Lorg/sireum/contract$Contract$Only$;
        15: areturn
      StackMapTable: number_of_entries = 1
        frame_type = 11 /* same */
      LineNumberTable:
        line 84: 0
      LocalVariableTable:
        Start  Length  Slot  Name   Signature
            0      16     0  this   Lorg/sireum/contract$Contract$;

  public org.sireum.contract$Contract$StepBuilder3$ StepBuilder3();
    descriptor: ()Lorg/sireum/contract$Contract$StepBuilder3$;
    flags: (0x0001) ACC_PUBLIC
    Code:
      stack=1, locals=1, args_size=1
         0: aload_0
         1: getfield      #109                // Field StepBuilder3$module:Lorg/sireum/contract$Contract$StepBuilder3$;
         4: ifnonnull     11
         7: aload_0
         8: invokespecial #112                // Method StepBuilder3$lzycompute$1:()V
        11: aload_0
        12: getfield      #109                // Field StepBuilder3$module:Lorg/sireum/contract$Contract$StepBuilder3$;
        15: areturn
      StackMapTable: number_of_entries = 1
        frame_type = 11 /* same */
      LineNumberTable:
        line 216: 0
      LocalVariableTable:
        Start  Length  Slot  Name   Signature
            0      16     0  this   Lorg/sireum/contract$Contract$;

  private final void Only$lzycompute$1();
    descriptor: ()V
    flags: (0x0012) ACC_PRIVATE, ACC_FINAL
    Code:
      stack=4, locals=2, args_size=1
         0: aload_0
         1: dup
         2: astore_1
         3: monitorenter
         4: aload_0
         5: getfield      #100                // Field Only$module:Lorg/sireum/contract$Contract$Only$;
         8: ifnonnull     23
        11: aload_0
        12: new           #46                 // class org/sireum/contract$Contract$Only$
        15: dup
        16: aload_0
        17: invokespecial #116                // Method org/sireum/contract$Contract$Only$."<init>":(Lorg/sireum/contract$Contract$;)V
        20: putfield      #100                // Field Only$module:Lorg/sireum/contract$Contract$Only$;
        23: aload_1
        24: monitorexit
        25: goto          31
        28: aload_1
        29: monitorexit
        30: athrow
        31: return
      Exception table:
         from    to  target type
             4    23    28   any
      StackMapTable: number_of_entries = 3
        frame_type = 252 /* append */
          offset_delta = 23
          locals = [ class org/sireum/contract$Contract$ ]
        frame_type = 68 /* same_locals_1_stack_item */
          stack = [ class java/lang/Throwable ]
        frame_type = 2 /* same */
      LineNumberTable:
        line 84: 0
      LocalVariableTable:
        Start  Length  Slot  Name   Signature
            0      32     0  this   Lorg/sireum/contract$Contract$;

  private final void StepBuilder3$lzycompute$1();
    descriptor: ()V
    flags: (0x0012) ACC_PRIVATE, ACC_FINAL
    Code:
      stack=4, locals=2, args_size=1
         0: aload_0
         1: dup
         2: astore_1
         3: monitorenter
         4: aload_0
         5: getfield      #109                // Field StepBuilder3$module:Lorg/sireum/contract$Contract$StepBuilder3$;
         8: ifnonnull     23
        11: aload_0
        12: new           #85                 // class org/sireum/contract$Contract$StepBuilder3$
        15: dup
        16: aload_0
        17: invokespecial #119                // Method org/sireum/contract$Contract$StepBuilder3$."<init>":(Lorg/sireum/contract$Contract$;)V
        20: putfield      #109                // Field StepBuilder3$module:Lorg/sireum/contract$Contract$StepBuilder3$;
        23: aload_1
        24: monitorexit
        25: goto          31
        28: aload_1
        29: monitorexit
        30: athrow
        31: return
      Exception table:
         from    to  target type
             4    23    28   any
      StackMapTable: number_of_entries = 3
        frame_type = 252 /* append */
          offset_delta = 23
          locals = [ class org/sireum/contract$Contract$ ]
        frame_type = 68 /* same_locals_1_stack_item */
          stack = [ class java/lang/Throwable ]
        frame_type = 2 /* same */
      LineNumberTable:
        line 216: 0
      LocalVariableTable:
        Start  Length  Slot  Name   Signature
            0      32     0  this   Lorg/sireum/contract$Contract$;

  public org.sireum.contract$Contract$(org.sireum.contract);
    descriptor: (Lorg/sireum/contract;)V
    flags: (0x0001) ACC_PUBLIC
    Code:
      stack=1, locals=2, args_size=2
         0: aload_0
         1: invokespecial #123                // Method java/lang/Object."<init>":()V
         4: return
      LineNumberTable:
        line 38: 0
      LocalVariableTable:
        Start  Length  Slot  Name   Signature
            0       5     0  this   Lorg/sireum/contract$Contract$;
            0       5     1 $outer   Lorg/sireum/contract;
    MethodParameters:
      Name                           Flags
      $outer                         final synthetic
}
InnerClasses:
  public #8= #2 of #7;                    // Contract$=class org/sireum/contract$Contract$ of class org/sireum/contract
  public #11= #10 of #2;                  // Assert=class org/sireum/contract$Contract$Assert of class org/sireum/contract$Contract$
  public #14= #13 of #2;                  // Assume=class org/sireum/contract$Contract$Assume of class org/sireum/contract$Contract$
  public #17= #16 of #2;                  // Case=class org/sireum/contract$Contract$Case of class org/sireum/contract$Contract$
  public #20= #19 of #2;                  // DataRefinement=class org/sireum/contract$Contract$DataRefinement of class org/sireum/contract$Contract$
  public #23= #22 of #2;                  // Ensures=class org/sireum/contract$Contract$Ensures of class org/sireum/contract$Contract$
  public #26= #25 of #2;                  // Fact=class org/sireum/contract$Contract$Fact of class org/sireum/contract$Contract$
  public #29= #28 of #2;                  // Invariant=class org/sireum/contract$Contract$Invariant of class org/sireum/contract$Contract$
  public #32= #31 of #2;                  // Justification=class org/sireum/contract$Contract$Justification of class org/sireum/contract$Contract$
  public #35= #34 of #2;                  // Lemma=class org/sireum/contract$Contract$Lemma of class org/sireum/contract$Contract$
  public #38= #37 of #2;                  // Let=class org/sireum/contract$Contract$Let of class org/sireum/contract$Contract$
  public #41= #40 of #2;                  // MaxIt=class org/sireum/contract$Contract$MaxIt of class org/sireum/contract$Contract$
  public #44= #43 of #2;                  // Modifies=class org/sireum/contract$Contract$Modifies of class org/sireum/contract$Contract$
  public #47= #46 of #2;                  // Only$=class org/sireum/contract$Contract$Only$ of class org/sireum/contract$Contract$
  public #50= #49 of #2;                  // Proof=class org/sireum/contract$Contract$Proof of class org/sireum/contract$Contract$
  public #53= #52 of #2;                  // ProofStep=class org/sireum/contract$Contract$ProofStep of class org/sireum/contract$Contract$
  public #56= #55 of #2;                  // Reads=class org/sireum/contract$Contract$Reads of class org/sireum/contract$Contract$
  public #59= #58 of #2;                  // Requires=class org/sireum/contract$Contract$Requires of class org/sireum/contract$Contract$
  public #62= #61 of #2;                  // Sequent=class org/sireum/contract$Contract$Sequent of class org/sireum/contract$Contract$
  public #65= #64 of #2;                  // SequentBuilder=class org/sireum/contract$Contract$SequentBuilder of class org/sireum/contract$Contract$
  public #68= #67 of #2;                  // State=class org/sireum/contract$Contract$State of class org/sireum/contract$Contract$
  public #71= #70 of #2;                  // StateCont=class org/sireum/contract$Contract$StateCont of class org/sireum/contract$Contract$
  public #74= #73 of #2;                  // StatePost=class org/sireum/contract$Contract$StatePost of class org/sireum/contract$Contract$
  public #77= #76 of #2;                  // StepBuilder=class org/sireum/contract$Contract$StepBuilder of class org/sireum/contract$Contract$
  public #80= #79 of #2;                  // StepBuilder2=class org/sireum/contract$Contract$StepBuilder2 of class org/sireum/contract$Contract$
  public #83= #82 of #2;                  // StepBuilder3=class org/sireum/contract$Contract$StepBuilder3 of class org/sireum/contract$Contract$
  public #86= #85 of #2;                  // StepBuilder3$=class org/sireum/contract$Contract$StepBuilder3$ of class org/sireum/contract$Contract$
  public #89= #88 of #2;                  // SubProof=class org/sireum/contract$Contract$SubProof of class org/sireum/contract$Contract$
  public #92= #91 of #2;                  // Theorem=class org/sireum/contract$Contract$Theorem of class org/sireum/contract$Contract$
SourceFile: "contract.scala"
  ScalaInlineInfo: length = 0x8B (unknown attribute)
   01 01 00 1B 00 71 00 78 01 00 85 00 86 01 00 61
   00 62 01 00 65 00 66 01 00 53 00 6B 01 00 6E 00
   66 01 00 87 00 88 01 00 87 00 89 01 00 87 00 8A
   01 00 87 00 8B 01 00 87 00 8C 01 00 87 00 8D 01
   00 87 00 8E 01 00 87 00 8F 01 00 87 00 90 01 00
   87 00 91 01 00 87 00 92 01 00 87 00 93 01 00 87
   00 94 01 00 87 00 95 01 00 87 00 96 01 00 87 00
   97 01 00 87 00 98 01 00 87 00 99 01 00 87 00 9A
   01 00 87 00 9B 01 00 87 00 9C 01
  Scala: length = 0x0 (unknown attribute)

