Classfile /Users/mw/Projects/slang-braindump/.jar/jar11/assemble/slang-braindump/assemble/content/org/sireum/contract$Contract$Only$.class
  Last modified May 29, 2022; size 7524 bytes
  SHA-256 checksum 987e59013ecc02d60a4b63b98580699faa0fbf6e766f53d6fd6146a412948d56
  Compiled from "contract.scala"
public class org.sireum.contract$Contract$Only$
  minor version: 0
  major version: 52
  flags: (0x0021) ACC_PUBLIC, ACC_SUPER
  this_class: #2                          // org/sireum/contract$Contract$Only$
  super_class: #4                         // java/lang/Object
  interfaces: 0, fields: 0, methods: 19, attributes: 4
Constant pool:
    #1 = Utf8               org/sireum/contract$Contract$Only$
    #2 = Class              #1            // org/sireum/contract$Contract$Only$
    #3 = Utf8               java/lang/Object
    #4 = Class              #3            // java/lang/Object
    #5 = Utf8               contract.scala
    #6 = Utf8               org/sireum/contract$Contract$
    #7 = Class              #6            // org/sireum/contract$Contract$
    #8 = Utf8               org/sireum/contract
    #9 = Class              #8            // org/sireum/contract
   #10 = Utf8               Contract$
   #11 = Utf8               org/sireum/contract$Contract$Case
   #12 = Class              #11           // org/sireum/contract$Contract$Case
   #13 = Utf8               Case
   #14 = Utf8               org/sireum/contract$Contract$Ensures
   #15 = Class              #14           // org/sireum/contract$Contract$Ensures
   #16 = Utf8               Ensures
   #17 = Utf8               org/sireum/contract$Contract$Modifies
   #18 = Class              #17           // org/sireum/contract$Contract$Modifies
   #19 = Utf8               Modifies
   #20 = Utf8               Only$
   #21 = Utf8               org/sireum/contract$Contract$Reads
   #22 = Class              #21           // org/sireum/contract$Contract$Reads
   #23 = Utf8               Reads
   #24 = Utf8               org/sireum/contract$Contract$Requires
   #25 = Class              #24           // org/sireum/contract$Contract$Requires
   #26 = Utf8               Requires
   #27 = Utf8               apply
   #28 = Utf8               (Lorg/sireum/contract$Contract$Reads;)Ljava/lang/Object;
   #29 = Utf8               <T:Ljava/lang/Object;>(Lorg/sireum/contract$Contract$Reads;)TT;
   #30 = Utf8               reads
   #31 = Utf8               scala/Predef$
   #32 = Class              #31           // scala/Predef$
   #33 = Utf8               MODULE$
   #34 = Utf8               Lscala/Predef$;
   #35 = NameAndType        #33:#34       // MODULE$:Lscala/Predef$;
   #36 = Fieldref           #32.#35       // scala/Predef$.MODULE$:Lscala/Predef$;
   #37 = Utf8               $qmark$qmark$qmark
   #38 = Utf8               ()Lscala/runtime/Nothing$;
   #39 = NameAndType        #37:#38       // $qmark$qmark$qmark:()Lscala/runtime/Nothing$;
   #40 = Methodref          #32.#39       // scala/Predef$.$qmark$qmark$qmark:()Lscala/runtime/Nothing$;
   #41 = Utf8               this
   #42 = Utf8               Lorg/sireum/contract$Contract$Only$;
   #43 = Utf8               Lorg/sireum/contract$Contract$Reads;
   #44 = Utf8               (Lorg/sireum/contract$Contract$Requires;)Ljava/lang/Object;
   #45 = Utf8               <T:Ljava/lang/Object;>(Lorg/sireum/contract$Contract$Requires;)TT;
   #46 = Utf8               requires
   #47 = Utf8               Lorg/sireum/contract$Contract$Requires;
   #48 = Utf8               (Lorg/sireum/contract$Contract$Modifies;)Ljava/lang/Object;
   #49 = Utf8               <T:Ljava/lang/Object;>(Lorg/sireum/contract$Contract$Modifies;)TT;
   #50 = Utf8               modifies
   #51 = Utf8               Lorg/sireum/contract$Contract$Modifies;
   #52 = Utf8               (Lorg/sireum/contract$Contract$Ensures;)Ljava/lang/Object;
   #53 = Utf8               <T:Ljava/lang/Object;>(Lorg/sireum/contract$Contract$Ensures;)TT;
   #54 = Utf8               ensures
   #55 = Utf8               Lorg/sireum/contract$Contract$Ensures;
   #56 = Utf8               (Lorg/sireum/contract$Contract$Reads;Lorg/sireum/contract$Contract$Requires;)Ljava/lang/Object;
   #57 = Utf8               <T:Ljava/lang/Object;>(Lorg/sireum/contract$Contract$Reads;Lorg/sireum/contract$Contract$Requires;)TT;
   #58 = Utf8               (Lorg/sireum/contract$Contract$Reads;Lorg/sireum/contract$Contract$Modifies;)Ljava/lang/Object;
   #59 = Utf8               <T:Ljava/lang/Object;>(Lorg/sireum/contract$Contract$Reads;Lorg/sireum/contract$Contract$Modifies;)TT;
   #60 = Utf8               (Lorg/sireum/contract$Contract$Reads;Lorg/sireum/contract$Contract$Ensures;)Ljava/lang/Object;
   #61 = Utf8               <T:Ljava/lang/Object;>(Lorg/sireum/contract$Contract$Reads;Lorg/sireum/contract$Contract$Ensures;)TT;
   #62 = Utf8               (Lorg/sireum/contract$Contract$Requires;Lorg/sireum/contract$Contract$Modifies;)Ljava/lang/Object;
   #63 = Utf8               <T:Ljava/lang/Object;>(Lorg/sireum/contract$Contract$Requires;Lorg/sireum/contract$Contract$Modifies;)TT;
   #64 = Utf8               (Lorg/sireum/contract$Contract$Requires;Lorg/sireum/contract$Contract$Ensures;)Ljava/lang/Object;
   #65 = Utf8               <T:Ljava/lang/Object;>(Lorg/sireum/contract$Contract$Requires;Lorg/sireum/contract$Contract$Ensures;)TT;
   #66 = Utf8               (Lorg/sireum/contract$Contract$Modifies;Lorg/sireum/contract$Contract$Ensures;)Ljava/lang/Object;
   #67 = Utf8               <T:Ljava/lang/Object;>(Lorg/sireum/contract$Contract$Modifies;Lorg/sireum/contract$Contract$Ensures;)TT;
   #68 = Utf8               (Lorg/sireum/contract$Contract$Reads;Lorg/sireum/contract$Contract$Requires;Lorg/sireum/contract$Contract$Modifies;)Ljava/lang/Object;
   #69 = Utf8               <T:Ljava/lang/Object;>(Lorg/sireum/contract$Contract$Reads;Lorg/sireum/contract$Contract$Requires;Lorg/sireum/contract$Contract$Modifies;)TT;
   #70 = Utf8               (Lorg/sireum/contract$Contract$Reads;Lorg/sireum/contract$Contract$Modifies;Lorg/sireum/contract$Contract$Ensures;)Ljava/lang/Object;
   #71 = Utf8               <T:Ljava/lang/Object;>(Lorg/sireum/contract$Contract$Reads;Lorg/sireum/contract$Contract$Modifies;Lorg/sireum/contract$Contract$Ensures;)TT;
   #72 = Utf8               (Lorg/sireum/contract$Contract$Requires;Lorg/sireum/contract$Contract$Modifies;Lorg/sireum/contract$Contract$Ensures;)Ljava/lang/Object;
   #73 = Utf8               <T:Ljava/lang/Object;>(Lorg/sireum/contract$Contract$Requires;Lorg/sireum/contract$Contract$Modifies;Lorg/sireum/contract$Contract$Ensures;)TT;
   #74 = Utf8               (Lorg/sireum/contract$Contract$Reads;Lorg/sireum/contract$Contract$Requires;Lorg/sireum/contract$Contract$Modifies;Lorg/sireum/contract$Contract$Ensures;)Ljava/lang/Object;
   #75 = Utf8               <T:Ljava/lang/Object;>(Lorg/sireum/contract$Contract$Reads;Lorg/sireum/contract$Contract$Requires;Lorg/sireum/contract$Contract$Modifies;Lorg/sireum/contract$Contract$Ensures;)TT;
   #76 = Utf8               (Lorg/sireum/contract$Contract$Case;Lscala/collection/immutable/Seq;)Ljava/lang/Object;
   #77 = Utf8               <T:Ljava/lang/Object;>(Lorg/sireum/contract$Contract$Case;Lscala/collection/immutable/Seq<Lorg/sireum/contract$Contract$Case;>;)TT;
   #78 = Utf8               case0
   #79 = Utf8               cases
   #80 = Utf8               Lorg/sireum/contract$Contract$Case;
   #81 = Utf8               Lscala/collection/immutable/Seq;
   #82 = Utf8               (Lorg/sireum/contract$Contract$Reads;Lorg/sireum/contract$Contract$Case;Lscala/collection/immutable/Seq;)Ljava/lang/Object;
   #83 = Utf8               <T:Ljava/lang/Object;>(Lorg/sireum/contract$Contract$Reads;Lorg/sireum/contract$Contract$Case;Lscala/collection/immutable/Seq<Lorg/sireum/contract$Contract$Case;>;)TT;
   #84 = Utf8               (Lorg/sireum/contract$Contract$Modifies;Lorg/sireum/contract$Contract$Case;Lscala/collection/immutable/Seq;)Ljava/lang/Object;
   #85 = Utf8               <T:Ljava/lang/Object;>(Lorg/sireum/contract$Contract$Modifies;Lorg/sireum/contract$Contract$Case;Lscala/collection/immutable/Seq<Lorg/sireum/contract$Contract$Case;>;)TT;
   #86 = Utf8               (Lorg/sireum/contract$Contract$Reads;Lorg/sireum/contract$Contract$Modifies;Lorg/sireum/contract$Contract$Case;Lscala/collection/immutable/Seq;)Ljava/lang/Object;
   #87 = Utf8               <T:Ljava/lang/Object;>(Lorg/sireum/contract$Contract$Reads;Lorg/sireum/contract$Contract$Modifies;Lorg/sireum/contract$Contract$Case;Lscala/collection/immutable/Seq<Lorg/sireum/contract$Contract$Case;>;)TT;
   #88 = Utf8               <init>
   #89 = Utf8               (Lorg/sireum/contract$Contract$;)V
   #90 = Utf8               $outer
   #91 = Utf8               ()V
   #92 = NameAndType        #88:#91       // "<init>":()V
   #93 = Methodref          #4.#92        // java/lang/Object."<init>":()V
   #94 = Utf8               Lorg/sireum/contract$Contract$;
   #95 = Utf8               Code
   #96 = Utf8               LineNumberTable
   #97 = Utf8               LocalVariableTable
   #98 = Utf8               Signature
   #99 = Utf8               MethodParameters
  #100 = Utf8               InnerClasses
  #101 = Utf8               SourceFile
  #102 = Utf8               ScalaInlineInfo
  #103 = Utf8               Scala
{
  public <T extends java.lang.Object> T apply(org.sireum.contract$Contract$Reads);
    descriptor: (Lorg/sireum/contract$Contract$Reads;)Ljava/lang/Object;
    flags: (0x0001) ACC_PUBLIC
    Code:
      stack=1, locals=2, args_size=2
         0: getstatic     #36                 // Field scala/Predef$.MODULE$:Lscala/Predef$;
         3: invokevirtual #40                 // Method scala/Predef$.$qmark$qmark$qmark:()Lscala/runtime/Nothing$;
         6: athrow
      LineNumberTable:
        line 86: 0
      LocalVariableTable:
        Start  Length  Slot  Name   Signature
            0       7     0  this   Lorg/sireum/contract$Contract$Only$;
            0       7     1 reads   Lorg/sireum/contract$Contract$Reads;
    Signature: #29                          // <T:Ljava/lang/Object;>(Lorg/sireum/contract$Contract$Reads;)TT;
    MethodParameters:
      Name                           Flags
      reads                          final

  public <T extends java.lang.Object> T apply(org.sireum.contract$Contract$Requires);
    descriptor: (Lorg/sireum/contract$Contract$Requires;)Ljava/lang/Object;
    flags: (0x0001) ACC_PUBLIC
    Code:
      stack=1, locals=2, args_size=2
         0: getstatic     #36                 // Field scala/Predef$.MODULE$:Lscala/Predef$;
         3: invokevirtual #40                 // Method scala/Predef$.$qmark$qmark$qmark:()Lscala/runtime/Nothing$;
         6: athrow
      LineNumberTable:
        line 88: 0
      LocalVariableTable:
        Start  Length  Slot  Name   Signature
            0       7     0  this   Lorg/sireum/contract$Contract$Only$;
            0       7     1 requires   Lorg/sireum/contract$Contract$Requires;
    Signature: #45                          // <T:Ljava/lang/Object;>(Lorg/sireum/contract$Contract$Requires;)TT;
    MethodParameters:
      Name                           Flags
      requires                       final

  public <T extends java.lang.Object> T apply(org.sireum.contract$Contract$Modifies);
    descriptor: (Lorg/sireum/contract$Contract$Modifies;)Ljava/lang/Object;
    flags: (0x0001) ACC_PUBLIC
    Code:
      stack=1, locals=2, args_size=2
         0: getstatic     #36                 // Field scala/Predef$.MODULE$:Lscala/Predef$;
         3: invokevirtual #40                 // Method scala/Predef$.$qmark$qmark$qmark:()Lscala/runtime/Nothing$;
         6: athrow
      LineNumberTable:
        line 90: 0
      LocalVariableTable:
        Start  Length  Slot  Name   Signature
            0       7     0  this   Lorg/sireum/contract$Contract$Only$;
            0       7     1 modifies   Lorg/sireum/contract$Contract$Modifies;
    Signature: #49                          // <T:Ljava/lang/Object;>(Lorg/sireum/contract$Contract$Modifies;)TT;
    MethodParameters:
      Name                           Flags
      modifies                       final

  public <T extends java.lang.Object> T apply(org.sireum.contract$Contract$Ensures);
    descriptor: (Lorg/sireum/contract$Contract$Ensures;)Ljava/lang/Object;
    flags: (0x0001) ACC_PUBLIC
    Code:
      stack=1, locals=2, args_size=2
         0: getstatic     #36                 // Field scala/Predef$.MODULE$:Lscala/Predef$;
         3: invokevirtual #40                 // Method scala/Predef$.$qmark$qmark$qmark:()Lscala/runtime/Nothing$;
         6: athrow
      LineNumberTable:
        line 92: 0
      LocalVariableTable:
        Start  Length  Slot  Name   Signature
            0       7     0  this   Lorg/sireum/contract$Contract$Only$;
            0       7     1 ensures   Lorg/sireum/contract$Contract$Ensures;
    Signature: #53                          // <T:Ljava/lang/Object;>(Lorg/sireum/contract$Contract$Ensures;)TT;
    MethodParameters:
      Name                           Flags
      ensures                        final

  public <T extends java.lang.Object> T apply(org.sireum.contract$Contract$Reads, org.sireum.contract$Contract$Requires);
    descriptor: (Lorg/sireum/contract$Contract$Reads;Lorg/sireum/contract$Contract$Requires;)Ljava/lang/Object;
    flags: (0x0001) ACC_PUBLIC
    Code:
      stack=1, locals=3, args_size=3
         0: getstatic     #36                 // Field scala/Predef$.MODULE$:Lscala/Predef$;
         3: invokevirtual #40                 // Method scala/Predef$.$qmark$qmark$qmark:()Lscala/runtime/Nothing$;
         6: athrow
      LineNumberTable:
        line 94: 0
      LocalVariableTable:
        Start  Length  Slot  Name   Signature
            0       7     0  this   Lorg/sireum/contract$Contract$Only$;
            0       7     1 reads   Lorg/sireum/contract$Contract$Reads;
            0       7     2 requires   Lorg/sireum/contract$Contract$Requires;
    Signature: #57                          // <T:Ljava/lang/Object;>(Lorg/sireum/contract$Contract$Reads;Lorg/sireum/contract$Contract$Requires;)TT;
    MethodParameters:
      Name                           Flags
      reads                          final
      requires                       final

  public <T extends java.lang.Object> T apply(org.sireum.contract$Contract$Reads, org.sireum.contract$Contract$Modifies);
    descriptor: (Lorg/sireum/contract$Contract$Reads;Lorg/sireum/contract$Contract$Modifies;)Ljava/lang/Object;
    flags: (0x0001) ACC_PUBLIC
    Code:
      stack=1, locals=3, args_size=3
         0: getstatic     #36                 // Field scala/Predef$.MODULE$:Lscala/Predef$;
         3: invokevirtual #40                 // Method scala/Predef$.$qmark$qmark$qmark:()Lscala/runtime/Nothing$;
         6: athrow
      LineNumberTable:
        line 96: 0
      LocalVariableTable:
        Start  Length  Slot  Name   Signature
            0       7     0  this   Lorg/sireum/contract$Contract$Only$;
            0       7     1 reads   Lorg/sireum/contract$Contract$Reads;
            0       7     2 modifies   Lorg/sireum/contract$Contract$Modifies;
    Signature: #59                          // <T:Ljava/lang/Object;>(Lorg/sireum/contract$Contract$Reads;Lorg/sireum/contract$Contract$Modifies;)TT;
    MethodParameters:
      Name                           Flags
      reads                          final
      modifies                       final

  public <T extends java.lang.Object> T apply(org.sireum.contract$Contract$Reads, org.sireum.contract$Contract$Ensures);
    descriptor: (Lorg/sireum/contract$Contract$Reads;Lorg/sireum/contract$Contract$Ensures;)Ljava/lang/Object;
    flags: (0x0001) ACC_PUBLIC
    Code:
      stack=1, locals=3, args_size=3
         0: getstatic     #36                 // Field scala/Predef$.MODULE$:Lscala/Predef$;
         3: invokevirtual #40                 // Method scala/Predef$.$qmark$qmark$qmark:()Lscala/runtime/Nothing$;
         6: athrow
      LineNumberTable:
        line 98: 0
      LocalVariableTable:
        Start  Length  Slot  Name   Signature
            0       7     0  this   Lorg/sireum/contract$Contract$Only$;
            0       7     1 reads   Lorg/sireum/contract$Contract$Reads;
            0       7     2 ensures   Lorg/sireum/contract$Contract$Ensures;
    Signature: #61                          // <T:Ljava/lang/Object;>(Lorg/sireum/contract$Contract$Reads;Lorg/sireum/contract$Contract$Ensures;)TT;
    MethodParameters:
      Name                           Flags
      reads                          final
      ensures                        final

  public <T extends java.lang.Object> T apply(org.sireum.contract$Contract$Requires, org.sireum.contract$Contract$Modifies);
    descriptor: (Lorg/sireum/contract$Contract$Requires;Lorg/sireum/contract$Contract$Modifies;)Ljava/lang/Object;
    flags: (0x0001) ACC_PUBLIC
    Code:
      stack=1, locals=3, args_size=3
         0: getstatic     #36                 // Field scala/Predef$.MODULE$:Lscala/Predef$;
         3: invokevirtual #40                 // Method scala/Predef$.$qmark$qmark$qmark:()Lscala/runtime/Nothing$;
         6: athrow
      LineNumberTable:
        line 100: 0
      LocalVariableTable:
        Start  Length  Slot  Name   Signature
            0       7     0  this   Lorg/sireum/contract$Contract$Only$;
            0       7     1 requires   Lorg/sireum/contract$Contract$Requires;
            0       7     2 modifies   Lorg/sireum/contract$Contract$Modifies;
    Signature: #63                          // <T:Ljava/lang/Object;>(Lorg/sireum/contract$Contract$Requires;Lorg/sireum/contract$Contract$Modifies;)TT;
    MethodParameters:
      Name                           Flags
      requires                       final
      modifies                       final

  public <T extends java.lang.Object> T apply(org.sireum.contract$Contract$Requires, org.sireum.contract$Contract$Ensures);
    descriptor: (Lorg/sireum/contract$Contract$Requires;Lorg/sireum/contract$Contract$Ensures;)Ljava/lang/Object;
    flags: (0x0001) ACC_PUBLIC
    Code:
      stack=1, locals=3, args_size=3
         0: getstatic     #36                 // Field scala/Predef$.MODULE$:Lscala/Predef$;
         3: invokevirtual #40                 // Method scala/Predef$.$qmark$qmark$qmark:()Lscala/runtime/Nothing$;
         6: athrow
      LineNumberTable:
        line 102: 0
      LocalVariableTable:
        Start  Length  Slot  Name   Signature
            0       7     0  this   Lorg/sireum/contract$Contract$Only$;
            0       7     1 requires   Lorg/sireum/contract$Contract$Requires;
            0       7     2 ensures   Lorg/sireum/contract$Contract$Ensures;
    Signature: #65                          // <T:Ljava/lang/Object;>(Lorg/sireum/contract$Contract$Requires;Lorg/sireum/contract$Contract$Ensures;)TT;
    MethodParameters:
      Name                           Flags
      requires                       final
      ensures                        final

  public <T extends java.lang.Object> T apply(org.sireum.contract$Contract$Modifies, org.sireum.contract$Contract$Ensures);
    descriptor: (Lorg/sireum/contract$Contract$Modifies;Lorg/sireum/contract$Contract$Ensures;)Ljava/lang/Object;
    flags: (0x0001) ACC_PUBLIC
    Code:
      stack=1, locals=3, args_size=3
         0: getstatic     #36                 // Field scala/Predef$.MODULE$:Lscala/Predef$;
         3: invokevirtual #40                 // Method scala/Predef$.$qmark$qmark$qmark:()Lscala/runtime/Nothing$;
         6: athrow
      LineNumberTable:
        line 104: 0
      LocalVariableTable:
        Start  Length  Slot  Name   Signature
            0       7     0  this   Lorg/sireum/contract$Contract$Only$;
            0       7     1 modifies   Lorg/sireum/contract$Contract$Modifies;
            0       7     2 ensures   Lorg/sireum/contract$Contract$Ensures;
    Signature: #67                          // <T:Ljava/lang/Object;>(Lorg/sireum/contract$Contract$Modifies;Lorg/sireum/contract$Contract$Ensures;)TT;
    MethodParameters:
      Name                           Flags
      modifies                       final
      ensures                        final

  public <T extends java.lang.Object> T apply(org.sireum.contract$Contract$Reads, org.sireum.contract$Contract$Requires, org.sireum.contract$Contract$Modifies);
    descriptor: (Lorg/sireum/contract$Contract$Reads;Lorg/sireum/contract$Contract$Requires;Lorg/sireum/contract$Contract$Modifies;)Ljava/lang/Object;
    flags: (0x0001) ACC_PUBLIC
    Code:
      stack=1, locals=4, args_size=4
         0: getstatic     #36                 // Field scala/Predef$.MODULE$:Lscala/Predef$;
         3: invokevirtual #40                 // Method scala/Predef$.$qmark$qmark$qmark:()Lscala/runtime/Nothing$;
         6: athrow
      LineNumberTable:
        line 106: 0
      LocalVariableTable:
        Start  Length  Slot  Name   Signature
            0       7     0  this   Lorg/sireum/contract$Contract$Only$;
            0       7     1 reads   Lorg/sireum/contract$Contract$Reads;
            0       7     2 requires   Lorg/sireum/contract$Contract$Requires;
            0       7     3 modifies   Lorg/sireum/contract$Contract$Modifies;
    Signature: #69                          // <T:Ljava/lang/Object;>(Lorg/sireum/contract$Contract$Reads;Lorg/sireum/contract$Contract$Requires;Lorg/sireum/contract$Contract$Modifies;)TT;
    MethodParameters:
      Name                           Flags
      reads                          final
      requires                       final
      modifies                       final

  public <T extends java.lang.Object> T apply(org.sireum.contract$Contract$Reads, org.sireum.contract$Contract$Modifies, org.sireum.contract$Contract$Ensures);
    descriptor: (Lorg/sireum/contract$Contract$Reads;Lorg/sireum/contract$Contract$Modifies;Lorg/sireum/contract$Contract$Ensures;)Ljava/lang/Object;
    flags: (0x0001) ACC_PUBLIC
    Code:
      stack=1, locals=4, args_size=4
         0: getstatic     #36                 // Field scala/Predef$.MODULE$:Lscala/Predef$;
         3: invokevirtual #40                 // Method scala/Predef$.$qmark$qmark$qmark:()Lscala/runtime/Nothing$;
         6: athrow
      LineNumberTable:
        line 108: 0
      LocalVariableTable:
        Start  Length  Slot  Name   Signature
            0       7     0  this   Lorg/sireum/contract$Contract$Only$;
            0       7     1 reads   Lorg/sireum/contract$Contract$Reads;
            0       7     2 modifies   Lorg/sireum/contract$Contract$Modifies;
            0       7     3 ensures   Lorg/sireum/contract$Contract$Ensures;
    Signature: #71                          // <T:Ljava/lang/Object;>(Lorg/sireum/contract$Contract$Reads;Lorg/sireum/contract$Contract$Modifies;Lorg/sireum/contract$Contract$Ensures;)TT;
    MethodParameters:
      Name                           Flags
      reads                          final
      modifies                       final
      ensures                        final

  public <T extends java.lang.Object> T apply(org.sireum.contract$Contract$Requires, org.sireum.contract$Contract$Modifies, org.sireum.contract$Contract$Ensures);
    descriptor: (Lorg/sireum/contract$Contract$Requires;Lorg/sireum/contract$Contract$Modifies;Lorg/sireum/contract$Contract$Ensures;)Ljava/lang/Object;
    flags: (0x0001) ACC_PUBLIC
    Code:
      stack=1, locals=4, args_size=4
         0: getstatic     #36                 // Field scala/Predef$.MODULE$:Lscala/Predef$;
         3: invokevirtual #40                 // Method scala/Predef$.$qmark$qmark$qmark:()Lscala/runtime/Nothing$;
         6: athrow
      LineNumberTable:
        line 110: 0
      LocalVariableTable:
        Start  Length  Slot  Name   Signature
            0       7     0  this   Lorg/sireum/contract$Contract$Only$;
            0       7     1 requires   Lorg/sireum/contract$Contract$Requires;
            0       7     2 modifies   Lorg/sireum/contract$Contract$Modifies;
            0       7     3 ensures   Lorg/sireum/contract$Contract$Ensures;
    Signature: #73                          // <T:Ljava/lang/Object;>(Lorg/sireum/contract$Contract$Requires;Lorg/sireum/contract$Contract$Modifies;Lorg/sireum/contract$Contract$Ensures;)TT;
    MethodParameters:
      Name                           Flags
      requires                       final
      modifies                       final
      ensures                        final

  public <T extends java.lang.Object> T apply(org.sireum.contract$Contract$Reads, org.sireum.contract$Contract$Requires, org.sireum.contract$Contract$Modifies, org.sireum.contract$Contract$Ensures);
    descriptor: (Lorg/sireum/contract$Contract$Reads;Lorg/sireum/contract$Contract$Requires;Lorg/sireum/contract$Contract$Modifies;Lorg/sireum/contract$Contract$Ensures;)Ljava/lang/Object;
    flags: (0x0001) ACC_PUBLIC
    Code:
      stack=1, locals=5, args_size=5
         0: getstatic     #36                 // Field scala/Predef$.MODULE$:Lscala/Predef$;
         3: invokevirtual #40                 // Method scala/Predef$.$qmark$qmark$qmark:()Lscala/runtime/Nothing$;
         6: athrow
      LineNumberTable:
        line 112: 0
      LocalVariableTable:
        Start  Length  Slot  Name   Signature
            0       7     0  this   Lorg/sireum/contract$Contract$Only$;
            0       7     1 reads   Lorg/sireum/contract$Contract$Reads;
            0       7     2 requires   Lorg/sireum/contract$Contract$Requires;
            0       7     3 modifies   Lorg/sireum/contract$Contract$Modifies;
            0       7     4 ensures   Lorg/sireum/contract$Contract$Ensures;
    Signature: #75                          // <T:Ljava/lang/Object;>(Lorg/sireum/contract$Contract$Reads;Lorg/sireum/contract$Contract$Requires;Lorg/sireum/contract$Contract$Modifies;Lorg/sireum/contract$Contract$Ensures;)TT;
    MethodParameters:
      Name                           Flags
      reads                          final
      requires                       final
      modifies                       final
      ensures                        final

  public <T extends java.lang.Object> T apply(org.sireum.contract$Contract$Case, scala.collection.immutable.Seq<org.sireum.contract$Contract$Case>);
    descriptor: (Lorg/sireum/contract$Contract$Case;Lscala/collection/immutable/Seq;)Ljava/lang/Object;
    flags: (0x0001) ACC_PUBLIC
    Code:
      stack=1, locals=3, args_size=3
         0: getstatic     #36                 // Field scala/Predef$.MODULE$:Lscala/Predef$;
         3: invokevirtual #40                 // Method scala/Predef$.$qmark$qmark$qmark:()Lscala/runtime/Nothing$;
         6: athrow
      LineNumberTable:
        line 114: 0
      LocalVariableTable:
        Start  Length  Slot  Name   Signature
            0       7     0  this   Lorg/sireum/contract$Contract$Only$;
            0       7     1 case0   Lorg/sireum/contract$Contract$Case;
            0       7     2 cases   Lscala/collection/immutable/Seq;
    Signature: #77                          // <T:Ljava/lang/Object;>(Lorg/sireum/contract$Contract$Case;Lscala/collection/immutable/Seq<Lorg/sireum/contract$Contract$Case;>;)TT;
    MethodParameters:
      Name                           Flags
      case0                          final
      cases                          final

  public <T extends java.lang.Object> T apply(org.sireum.contract$Contract$Reads, org.sireum.contract$Contract$Case, scala.collection.immutable.Seq<org.sireum.contract$Contract$Case>);
    descriptor: (Lorg/sireum/contract$Contract$Reads;Lorg/sireum/contract$Contract$Case;Lscala/collection/immutable/Seq;)Ljava/lang/Object;
    flags: (0x0001) ACC_PUBLIC
    Code:
      stack=1, locals=4, args_size=4
         0: getstatic     #36                 // Field scala/Predef$.MODULE$:Lscala/Predef$;
         3: invokevirtual #40                 // Method scala/Predef$.$qmark$qmark$qmark:()Lscala/runtime/Nothing$;
         6: athrow
      LineNumberTable:
        line 116: 0
      LocalVariableTable:
        Start  Length  Slot  Name   Signature
            0       7     0  this   Lorg/sireum/contract$Contract$Only$;
            0       7     1 reads   Lorg/sireum/contract$Contract$Reads;
            0       7     2 case0   Lorg/sireum/contract$Contract$Case;
            0       7     3 cases   Lscala/collection/immutable/Seq;
    Signature: #83                          // <T:Ljava/lang/Object;>(Lorg/sireum/contract$Contract$Reads;Lorg/sireum/contract$Contract$Case;Lscala/collection/immutable/Seq<Lorg/sireum/contract$Contract$Case;>;)TT;
    MethodParameters:
      Name                           Flags
      reads                          final
      case0                          final
      cases                          final

  public <T extends java.lang.Object> T apply(org.sireum.contract$Contract$Modifies, org.sireum.contract$Contract$Case, scala.collection.immutable.Seq<org.sireum.contract$Contract$Case>);
    descriptor: (Lorg/sireum/contract$Contract$Modifies;Lorg/sireum/contract$Contract$Case;Lscala/collection/immutable/Seq;)Ljava/lang/Object;
    flags: (0x0001) ACC_PUBLIC
    Code:
      stack=1, locals=4, args_size=4
         0: getstatic     #36                 // Field scala/Predef$.MODULE$:Lscala/Predef$;
         3: invokevirtual #40                 // Method scala/Predef$.$qmark$qmark$qmark:()Lscala/runtime/Nothing$;
         6: athrow
      LineNumberTable:
        line 118: 0
      LocalVariableTable:
        Start  Length  Slot  Name   Signature
            0       7     0  this   Lorg/sireum/contract$Contract$Only$;
            0       7     1 modifies   Lorg/sireum/contract$Contract$Modifies;
            0       7     2 case0   Lorg/sireum/contract$Contract$Case;
            0       7     3 cases   Lscala/collection/immutable/Seq;
    Signature: #85                          // <T:Ljava/lang/Object;>(Lorg/sireum/contract$Contract$Modifies;Lorg/sireum/contract$Contract$Case;Lscala/collection/immutable/Seq<Lorg/sireum/contract$Contract$Case;>;)TT;
    MethodParameters:
      Name                           Flags
      modifies                       final
      case0                          final
      cases                          final

  public <T extends java.lang.Object> T apply(org.sireum.contract$Contract$Reads, org.sireum.contract$Contract$Modifies, org.sireum.contract$Contract$Case, scala.collection.immutable.Seq<org.sireum.contract$Contract$Case>);
    descriptor: (Lorg/sireum/contract$Contract$Reads;Lorg/sireum/contract$Contract$Modifies;Lorg/sireum/contract$Contract$Case;Lscala/collection/immutable/Seq;)Ljava/lang/Object;
    flags: (0x0001) ACC_PUBLIC
    Code:
      stack=1, locals=5, args_size=5
         0: getstatic     #36                 // Field scala/Predef$.MODULE$:Lscala/Predef$;
         3: invokevirtual #40                 // Method scala/Predef$.$qmark$qmark$qmark:()Lscala/runtime/Nothing$;
         6: athrow
      LineNumberTable:
        line 120: 0
      LocalVariableTable:
        Start  Length  Slot  Name   Signature
            0       7     0  this   Lorg/sireum/contract$Contract$Only$;
            0       7     1 reads   Lorg/sireum/contract$Contract$Reads;
            0       7     2 modifies   Lorg/sireum/contract$Contract$Modifies;
            0       7     3 case0   Lorg/sireum/contract$Contract$Case;
            0       7     4 cases   Lscala/collection/immutable/Seq;
    Signature: #87                          // <T:Ljava/lang/Object;>(Lorg/sireum/contract$Contract$Reads;Lorg/sireum/contract$Contract$Modifies;Lorg/sireum/contract$Contract$Case;Lscala/collection/immutable/Seq<Lorg/sireum/contract$Contract$Case;>;)TT;
    MethodParameters:
      Name                           Flags
      reads                          final
      modifies                       final
      case0                          final
      cases                          final

  public org.sireum.contract$Contract$Only$(org.sireum.contract$Contract$);
    descriptor: (Lorg/sireum/contract$Contract$;)V
    flags: (0x0001) ACC_PUBLIC
    Code:
      stack=1, locals=2, args_size=2
         0: aload_0
         1: invokespecial #93                 // Method java/lang/Object."<init>":()V
         4: return
      LineNumberTable:
        line 84: 0
      LocalVariableTable:
        Start  Length  Slot  Name   Signature
            0       5     0  this   Lorg/sireum/contract$Contract$Only$;
            0       5     1 $outer   Lorg/sireum/contract$Contract$;
    MethodParameters:
      Name                           Flags
      $outer                         final synthetic
}
InnerClasses:
  public #10= #7 of #9;                   // Contract$=class org/sireum/contract$Contract$ of class org/sireum/contract
  public #13= #12 of #7;                  // Case=class org/sireum/contract$Contract$Case of class org/sireum/contract$Contract$
  public #16= #15 of #7;                  // Ensures=class org/sireum/contract$Contract$Ensures of class org/sireum/contract$Contract$
  public #19= #18 of #7;                  // Modifies=class org/sireum/contract$Contract$Modifies of class org/sireum/contract$Contract$
  public #20= #2 of #7;                   // Only$=class org/sireum/contract$Contract$Only$ of class org/sireum/contract$Contract$
  public #23= #22 of #7;                  // Reads=class org/sireum/contract$Contract$Reads of class org/sireum/contract$Contract$
  public #26= #25 of #7;                  // Requires=class org/sireum/contract$Contract$Requires of class org/sireum/contract$Contract$
SourceFile: "contract.scala"
  ScalaInlineInfo: length = 0x63 (unknown attribute)
   01 01 00 13 00 58 00 59 01 00 1B 00 4C 01 00 1B
   00 34 01 00 1B 00 30 01 00 1B 00 54 01 00 1B 00
   42 01 00 1B 00 1C 01 00 1B 00 52 01 00 1B 00 3C
   01 00 1B 00 3A 01 00 1B 00 56 01 00 1B 00 46 01
   00 1B 00 38 01 00 1B 00 44 01 00 1B 00 4A 01 00
   1B 00 2C 01 00 1B 00 40 01 00 1B 00 3E 01 00 1B
   00 48 01
  Scala: length = 0x0 (unknown attribute)

