Classfile /Users/mw/Projects/slang-braindump/.jar/jar11/assemble/slang-braindump/assemble/content/org/sireum/contract$Contract$StepBuilder3$.class
  Last modified May 29, 2022; size 1176 bytes
  SHA-256 checksum b57699315c46af250bef8f7b74f1db05972f0b81e94cb08ba6f53e4a64155d28
  Compiled from "contract.scala"
public class org.sireum.contract$Contract$StepBuilder3$
  minor version: 0
  major version: 52
  flags: (0x0021) ACC_PUBLIC, ACC_SUPER
  this_class: #2                          // org/sireum/contract$Contract$StepBuilder3$
  super_class: #4                         // java/lang/Object
  interfaces: 0, fields: 0, methods: 2, attributes: 4
Constant pool:
   #1 = Utf8               org/sireum/contract$Contract$StepBuilder3$
   #2 = Class              #1             // org/sireum/contract$Contract$StepBuilder3$
   #3 = Utf8               java/lang/Object
   #4 = Class              #3             // java/lang/Object
   #5 = Utf8               contract.scala
   #6 = Utf8               org/sireum/contract$Contract$
   #7 = Class              #6             // org/sireum/contract$Contract$
   #8 = Utf8               org/sireum/contract
   #9 = Class              #8             // org/sireum/contract
  #10 = Utf8               Contract$
  #11 = Utf8               org/sireum/contract$Contract$ProofStep
  #12 = Class              #11            // org/sireum/contract$Contract$ProofStep
  #13 = Utf8               ProofStep
  #14 = Utf8               org/sireum/contract$Contract$StepBuilder3
  #15 = Class              #14            // org/sireum/contract$Contract$StepBuilder3
  #16 = Utf8               StepBuilder3
  #17 = Utf8               StepBuilder3$
  #18 = Utf8               toProofStep
  #19 = Utf8               (Lorg/sireum/contract$Contract$StepBuilder3;)Lorg/sireum/contract$Contract$ProofStep;
  #20 = Utf8               o
  #21 = Utf8               scala/collection/immutable/Nil$
  #22 = Class              #21            // scala/collection/immutable/Nil$
  #23 = Utf8               MODULE$
  #24 = Utf8               Lscala/collection/immutable/Nil$;
  #25 = NameAndType        #23:#24        // MODULE$:Lscala/collection/immutable/Nil$;
  #26 = Fieldref           #22.#25        // scala/collection/immutable/Nil$.MODULE$:Lscala/collection/immutable/Nil$;
  #27 = Utf8               and
  #28 = Utf8               (Lscala/collection/immutable/Seq;)Lorg/sireum/contract$Contract$ProofStep;
  #29 = NameAndType        #27:#28        // and:(Lscala/collection/immutable/Seq;)Lorg/sireum/contract$Contract$ProofStep;
  #30 = InterfaceMethodref #15.#29        // org/sireum/contract$Contract$StepBuilder3.and:(Lscala/collection/immutable/Seq;)Lorg/sireum/contract$Contract$ProofStep;
  #31 = Utf8               this
  #32 = Utf8               Lorg/sireum/contract$Contract$StepBuilder3$;
  #33 = Utf8               Lorg/sireum/contract$Contract$StepBuilder3;
  #34 = Utf8               <init>
  #35 = Utf8               (Lorg/sireum/contract$Contract$;)V
  #36 = Utf8               $outer
  #37 = Utf8               ()V
  #38 = NameAndType        #34:#37        // "<init>":()V
  #39 = Methodref          #4.#38         // java/lang/Object."<init>":()V
  #40 = Utf8               Lorg/sireum/contract$Contract$;
  #41 = Utf8               Code
  #42 = Utf8               LineNumberTable
  #43 = Utf8               LocalVariableTable
  #44 = Utf8               MethodParameters
  #45 = Utf8               InnerClasses
  #46 = Utf8               SourceFile
  #47 = Utf8               ScalaInlineInfo
  #48 = Utf8               Scala
{
  public org.sireum.contract$Contract$ProofStep toProofStep(org.sireum.contract$Contract$StepBuilder3);
    descriptor: (Lorg/sireum/contract$Contract$StepBuilder3;)Lorg/sireum/contract$Contract$ProofStep;
    flags: (0x0001) ACC_PUBLIC
    Code:
      stack=2, locals=2, args_size=2
         0: aload_1
         1: getstatic     #26                 // Field scala/collection/immutable/Nil$.MODULE$:Lscala/collection/immutable/Nil$;
         4: invokeinterface #30,  2           // InterfaceMethod org/sireum/contract$Contract$StepBuilder3.and:(Lscala/collection/immutable/Seq;)Lorg/sireum/contract$Contract$ProofStep;
         9: areturn
      LineNumberTable:
        line 218: 0
      LocalVariableTable:
        Start  Length  Slot  Name   Signature
            0      10     0  this   Lorg/sireum/contract$Contract$StepBuilder3$;
            0      10     1     o   Lorg/sireum/contract$Contract$StepBuilder3;
    MethodParameters:
      Name                           Flags
      o                              final

  public org.sireum.contract$Contract$StepBuilder3$(org.sireum.contract$Contract$);
    descriptor: (Lorg/sireum/contract$Contract$;)V
    flags: (0x0001) ACC_PUBLIC
    Code:
      stack=1, locals=2, args_size=2
         0: aload_0
         1: invokespecial #39                 // Method java/lang/Object."<init>":()V
         4: return
      LineNumberTable:
        line 216: 0
      LocalVariableTable:
        Start  Length  Slot  Name   Signature
            0       5     0  this   Lorg/sireum/contract$Contract$StepBuilder3$;
            0       5     1 $outer   Lorg/sireum/contract$Contract$;
    MethodParameters:
      Name                           Flags
      $outer                         final synthetic
}
InnerClasses:
  public #10= #7 of #9;                   // Contract$=class org/sireum/contract$Contract$ of class org/sireum/contract
  public #13= #12 of #7;                  // ProofStep=class org/sireum/contract$Contract$ProofStep of class org/sireum/contract$Contract$
  public #16= #15 of #7;                  // StepBuilder3=class org/sireum/contract$Contract$StepBuilder3 of class org/sireum/contract$Contract$
  public #17= #2 of #7;                   // StepBuilder3$=class org/sireum/contract$Contract$StepBuilder3$ of class org/sireum/contract$Contract$
SourceFile: "contract.scala"
  ScalaInlineInfo: length = 0xE (unknown attribute)
   01 01 00 02 00 22 00 23 01 00 12 00 13 01
  Scala: length = 0x0 (unknown attribute)

