Classfile /Users/mw/Projects/slang-braindump/.jar/jar11/assemble/slang-braindump/assemble/content/org/sireum/Coursier_Ext.class
  Last modified May 29, 2022; size 4555 bytes
  SHA-256 checksum 2988f16269cfb5429d15bee8f82c03a3abdc3b67b3ac657547f779c0e877bacf
  Compiled from "Coursier_Ext.scala"
public final class org.sireum.Coursier_Ext
  minor version: 0
  major version: 52
  flags: (0x0031) ACC_PUBLIC, ACC_FINAL, ACC_SUPER
  this_class: #2                          // org/sireum/Coursier_Ext
  super_class: #4                         // java/lang/Object
  interfaces: 0, fields: 0, methods: 17, attributes: 4
Constant pool:
    #1 = Utf8               org/sireum/Coursier_Ext
    #2 = Class              #1            // org/sireum/Coursier_Ext
    #3 = Utf8               java/lang/Object
    #4 = Class              #3            // java/lang/Object
    #5 = Utf8               Coursier_Ext.scala
    #6 = Utf8               Lscala/reflect/ScalaSignature;
    #7 = Utf8               bytes
    #8 = Utf8               \u0006\u0005\u0005=s!\u0002\u000e\u001c\u0011\u0003\u0001c!\u0002\u0012\u001c\u0011\u0003\u0019\u0003\"\u0002\u0016\u0002\t\u0003Y\u0003b\u0002\u0017\u0002\u0005\u0004%\t!\f\u0005\u0007y\u0005\u0001\u000b\u0011\u0002\u0018\t\u000fu\n!\u0019!C\u0001[!1a(\u0001Q\u0001\n9BqaP\u0001A\u0002\u0013\u0005\u0001\tC\u0004E\u0003\u0001\u0007I\u0011A#\t\r-\u000b\u0001\u0015)\u0003B\u0011\u001da\u0015\u00011A\u0005\u00025Cq\u0001W\u0001A\u0002\u0013\u0005\u0011\f\u0003\u0004\\\u0003\u0001\u0006KA\u0014\u0005\b9\u0006\u0001\r\u0011\"\u0001^\u0011\u001d9\u0017\u00011A\u0005\u0002!DaA[\u0001!B\u0013q\u0006bB6\u0002\u0005\u0004%\t\u0001\u001c\u0005\u0007]\u0006\u0001\u000b\u0011B7\t\u000b=\fA\u0011\u00019\t\u000by\fA\u0011A@\t\u000f\u0005\u0015\u0011\u0001\"\u0001\u0002\b!9\u0011QB\u0001\u0005\u0002\u0005=\u0001bBA\u000b\u0003\u0011\u0005\u0011q\u0003\u0005\b\u00037\tA\u0011AA\u000f\u0011\u001d\tI#\u0001C\u0001\u0003WAq!a\u0011\u0002\t\u0003\t)%\u0001\u0007D_V\u00148/[3s?\u0016CHO\u0003\u0002\u001d;\u000511/\u001b:fk6T\u0011AH\u0001\u0004_J<7\u0001\u0001\t\u0003C\u0005i\u0011a\u0007\u0002\r\u0007>,(o]5fe~+\u0005\u0010^\n\u0003\u0003\u0011\u0002\"!\n\u0015\u000e\u0003\u0019R\u0011aJ\u0001\u0006g\u000e\fG.Y\u0005\u0003S\u0019\u0012a!\u00118z%\u00164\u0017A\u0002\u001fj]&$h\bF\u0001!\u00039awnY1m\u001b\u00064XM\u001c*fa>,\u0012A\f\t\u0003_er!\u0001\r\u001c\u000f\u0005E\"T\"\u0001\u001a\u000b\u0005Mz\u0012A\u0002\u001fs_>$h(C\u00016\u0003!\u0019w.\u001e:tS\u0016\u0014\u0018BA\u001c9\u0003\u001d\u0001\u0018mY6bO\u0016T\u0011!N\u0005\u0003um\u0012!BU3q_NLGo\u001c:z\u0015\t9\u0004(A\bm_\u000e\fG.T1wK:\u0014V\r]8!\u0003M\u0019xN\\1usB,\'+\u001a7fCN,\'+\u001a9p\u0003Q\u0019xN\\1usB,\'+\u001a7fCN,\'+\u001a9pA\u0005a1oY1mCZ+\'o]5p]V\t\u0011\t\u0005\u0002\"\u0005&\u00111i\u0007\u0002\u0007\'R\u0014\u0018N\\4\u0002!M\u001c\u0017\r\\1WKJ\u001c\u0018n\u001c8`I\u0015\fHC\u0001$J!\t)s)\u0003\u0002IM\t!QK\\5u\u0011\u001dQ\u0005\"!AA\u0002\u0005\u000b1\u0001\u001f\u00132\u00035\u00198-\u00197b-\u0016\u00148/[8oA\u0005A1-Y2iK>\u0003H/F\u0001O!\r\ts*U\u0005\u0003!n\u0011aa\u00149uS>t\u0007C\u0001*V\u001d\t\t3+\u0003\u0002U7\u0005\u0011qj]\u0005\u0003-^\u0013A\u0001U1uQ*\u0011AkG\u0001\rG\u0006\u001c\u0007.Z(qi~#S-\u001d\u000b\u0003\rjCqAS\u0006\u0002\u0002\u0003\u0007a*A\u0005dC\u000eDWm\u00149uA\u0005iQ.\u0019<f]J+\u0007o\\+sYN,\u0012A\u0018\t\u0004?\u0006\feBA\u0011a\u0013\t94$\u0003\u0002cG\n\u0019\u0011j\u0015.\n\u0005\u0011,\'\u0001\u0004)bG.\fw-\u001a+sC&$(B\u00014\u001c\u0003%!\u0013N\u001c;fe:\fG.A\tnCZ,gNU3q_V\u0013Hn]0%KF$\"AR5\t\u000f)s\u0011\u0011!a\u0001=\u0006qQ.\u0019<f]J+\u0007o\\+sYN\u0004\u0013\u0001\u0004:fa>\u001c\u0018\u000e^8sS\u0016\u001cX#A7\u0011\u0007}\u000bg&A\u0007sKB|7/\u001b;pe&,7\u000fI\u0001\u0007i>$U\r]:\u0015\u0005Ed\bc\u0001:ws:\u00111/\u001e\b\u0003cQL\u0011aJ\u0005\u0003o\u0019J!a\u001e=\u0003\u0007M+\u0017O\u0003\u00028MA\u0011qF_\u0005\u0003wn\u0012!\u0002R3qK:$WM\\2z\u0011\u0015i(\u00031\u0001_\u0003\u0011!W\r]:\u0002\u001fM,GoU2bY\u00064VM]:j_:$2ARA\u0001\u0011\u0019\t\u0019a\u0005a\u0001\u0003\u00069a/\u001a:tS>t\u0017\u0001C:fi\u000e\u000b7\r[3\u0015\u0007\u0019\u000bI\u0001\u0003\u0004\u0002\fQ\u0001\rAT\u0001\ba\u0006$\bn\u00149u\u0003Q\tG\rZ\'bm\u0016t\'+\u001a9pg&$xN]5fgR\u0019a)!\u0005\t\r\u0005MQ\u00031\u0001_\u0003\u0011)(\u000f\\:\u0002)M,G/T1wK:\u0014V\r]8tSR|\'/[3t)\r1\u0015\u0011\u0004\u0005\u0007\u0003\'1\u0002\u0019\u00010\u0002\u000b\u0019,Go\u00195\u0015\t\u0005}\u0011q\u0005\t\u0005?\u0006\f\t\u0003E\u0002\"\u0003GI1!!\n\u001c\u0005A\u0019u.\u001e:tS\u0016\u0014h)\u001b7f\u0013:4w\u000eC\u0003~/\u0001\u0007a,\u0001\tgKR\u001c\u0007n\u00117bgNLg-[3sgR1\u0011qDA\u0017\u0003_AQ! \rA\u0002yCq!!\r\u0019\u0001\u0004\t\u0019$A\u0002dYN\u0004BaX1\u00026A!\u0011qGA\u001f\u001d\r\t\u0013\u0011H\u0005\u0004\u0003wY\u0012AE\"pkJ\u001c\u0018.\u001a:DY\u0006\u001c8/\u001b4jKJLA!a\u0010\u0002B\t!A+\u001f9f\u0015\r\tYdG\u0001\u001aSN\u0014VO\u001c;j[\u0016\u0004VO\u00197jg\",G\rT8dC2d\u0017\u0010\u0006\u0003\u0002H\u00055\u0003cA\u0011\u0002J%\u0019\u00111J\u000e\u0003\u0003\tCa!a\u0001\u001a\u0001\u0004\t\u0005
    #9 = Utf8               org/sireum/CoursierClassifier$Type
   #10 = Class              #9            // org/sireum/CoursierClassifier$Type
   #11 = Utf8               org/sireum/CoursierClassifier
   #12 = Class              #11           // org/sireum/CoursierClassifier
   #13 = Utf8               Type
   #14 = Utf8               org/sireum/Os$Path
   #15 = Class              #14           // org/sireum/Os$Path
   #16 = Utf8               org/sireum/Os
   #17 = Class              #16           // org/sireum/Os
   #18 = Utf8               Path
   #19 = Utf8               isRuntimePublishedLocally
   #20 = Utf8               (Ljava/lang/String;)Z
   #21 = Utf8               version
   #22 = Utf8               org/sireum/Coursier_Ext$
   #23 = Class              #22           // org/sireum/Coursier_Ext$
   #24 = Utf8               MODULE$
   #25 = Utf8               Lorg/sireum/Coursier_Ext$;
   #26 = NameAndType        #24:#25       // MODULE$:Lorg/sireum/Coursier_Ext$;
   #27 = Fieldref           #23.#26       // org/sireum/Coursier_Ext$.MODULE$:Lorg/sireum/Coursier_Ext$;
   #28 = NameAndType        #19:#20       // isRuntimePublishedLocally:(Ljava/lang/String;)Z
   #29 = Methodref          #23.#28       // org/sireum/Coursier_Ext$.isRuntimePublishedLocally:(Ljava/lang/String;)Z
   #30 = Utf8               Ljava/lang/String;
   #31 = Utf8               fetchClassifiers
   #32 = Utf8               (Lorg/sireum/IS;Lorg/sireum/IS;)Lorg/sireum/IS;
   #33 = Utf8               (Lorg/sireum/IS<Lorg/sireum/Z;Lorg/sireum/String;>;Lorg/sireum/IS<Lorg/sireum/Z;Lorg/sireum/CoursierClassifier$Type;>;)Lorg/sireum/IS<Lorg/sireum/Z;Lorg/sireum/CoursierFileInfo;>;
   #34 = Utf8               deps
   #35 = Utf8               cls
   #36 = NameAndType        #31:#32       // fetchClassifiers:(Lorg/sireum/IS;Lorg/sireum/IS;)Lorg/sireum/IS;
   #37 = Methodref          #23.#36       // org/sireum/Coursier_Ext$.fetchClassifiers:(Lorg/sireum/IS;Lorg/sireum/IS;)Lorg/sireum/IS;
   #38 = Utf8               Lorg/sireum/IS;
   #39 = Utf8               fetch
   #40 = Utf8               (Lorg/sireum/IS;)Lorg/sireum/IS;
   #41 = Utf8               (Lorg/sireum/IS<Lorg/sireum/Z;Lorg/sireum/String;>;)Lorg/sireum/IS<Lorg/sireum/Z;Lorg/sireum/CoursierFileInfo;>;
   #42 = NameAndType        #39:#40       // fetch:(Lorg/sireum/IS;)Lorg/sireum/IS;
   #43 = Methodref          #23.#42       // org/sireum/Coursier_Ext$.fetch:(Lorg/sireum/IS;)Lorg/sireum/IS;
   #44 = Utf8               setMavenRepositories
   #45 = Utf8               (Lorg/sireum/IS;)V
   #46 = Utf8               (Lorg/sireum/IS<Lorg/sireum/Z;Lorg/sireum/String;>;)V
   #47 = Utf8               urls
   #48 = NameAndType        #44:#45       // setMavenRepositories:(Lorg/sireum/IS;)V
   #49 = Methodref          #23.#48       // org/sireum/Coursier_Ext$.setMavenRepositories:(Lorg/sireum/IS;)V
   #50 = Utf8               addMavenRepositories
   #51 = NameAndType        #50:#45       // addMavenRepositories:(Lorg/sireum/IS;)V
   #52 = Methodref          #23.#51       // org/sireum/Coursier_Ext$.addMavenRepositories:(Lorg/sireum/IS;)V
   #53 = Utf8               setCache
   #54 = Utf8               (Lorg/sireum/Option;)V
   #55 = Utf8               (Lorg/sireum/Option<Lorg/sireum/Os$Path;>;)V
   #56 = Utf8               pathOpt
   #57 = NameAndType        #53:#54       // setCache:(Lorg/sireum/Option;)V
   #58 = Methodref          #23.#57       // org/sireum/Coursier_Ext$.setCache:(Lorg/sireum/Option;)V
   #59 = Utf8               Lorg/sireum/Option;
   #60 = Utf8               setScalaVersion
   #61 = Utf8               (Ljava/lang/String;)V
   #62 = NameAndType        #60:#61       // setScalaVersion:(Ljava/lang/String;)V
   #63 = Methodref          #23.#62       // org/sireum/Coursier_Ext$.setScalaVersion:(Ljava/lang/String;)V
   #64 = Utf8               toDeps
   #65 = Utf8               (Lorg/sireum/IS;)Lscala/collection/immutable/Seq;
   #66 = Utf8               (Lorg/sireum/IS<Lorg/sireum/Z;Lorg/sireum/String;>;)Lscala/collection/immutable/Seq<Lcoursier/core/Dependency;>;
   #67 = NameAndType        #64:#65       // toDeps:(Lorg/sireum/IS;)Lscala/collection/immutable/Seq;
   #68 = Methodref          #23.#67       // org/sireum/Coursier_Ext$.toDeps:(Lorg/sireum/IS;)Lscala/collection/immutable/Seq;
   #69 = Utf8               repositories
   #70 = Utf8               ()Lorg/sireum/IS;
   #71 = Utf8               ()Lorg/sireum/IS<Lorg/sireum/Z;Lcoursier/core/Repository;>;
   #72 = NameAndType        #69:#70       // repositories:()Lorg/sireum/IS;
   #73 = Methodref          #23.#72       // org/sireum/Coursier_Ext$.repositories:()Lorg/sireum/IS;
   #74 = Utf8               mavenRepoUrls_$eq
   #75 = Utf8               x$1
   #76 = NameAndType        #74:#45       // mavenRepoUrls_$eq:(Lorg/sireum/IS;)V
   #77 = Methodref          #23.#76       // org/sireum/Coursier_Ext$.mavenRepoUrls_$eq:(Lorg/sireum/IS;)V
   #78 = Utf8               mavenRepoUrls
   #79 = Utf8               ()Lorg/sireum/IS<Lorg/sireum/Z;Lorg/sireum/String;>;
   #80 = NameAndType        #78:#70       // mavenRepoUrls:()Lorg/sireum/IS;
   #81 = Methodref          #23.#80       // org/sireum/Coursier_Ext$.mavenRepoUrls:()Lorg/sireum/IS;
   #82 = Utf8               cacheOpt_$eq
   #83 = NameAndType        #82:#54       // cacheOpt_$eq:(Lorg/sireum/Option;)V
   #84 = Methodref          #23.#83       // org/sireum/Coursier_Ext$.cacheOpt_$eq:(Lorg/sireum/Option;)V
   #85 = Utf8               cacheOpt
   #86 = Utf8               ()Lorg/sireum/Option;
   #87 = Utf8               ()Lorg/sireum/Option<Lorg/sireum/Os$Path;>;
   #88 = NameAndType        #85:#86       // cacheOpt:()Lorg/sireum/Option;
   #89 = Methodref          #23.#88       // org/sireum/Coursier_Ext$.cacheOpt:()Lorg/sireum/Option;
   #90 = Utf8               scalaVersion_$eq
   #91 = NameAndType        #90:#61       // scalaVersion_$eq:(Ljava/lang/String;)V
   #92 = Methodref          #23.#91       // org/sireum/Coursier_Ext$.scalaVersion_$eq:(Ljava/lang/String;)V
   #93 = Utf8               scalaVersion
   #94 = Utf8               ()Ljava/lang/String;
   #95 = NameAndType        #93:#94       // scalaVersion:()Ljava/lang/String;
   #96 = Methodref          #23.#95       // org/sireum/Coursier_Ext$.scalaVersion:()Ljava/lang/String;
   #97 = Utf8               sonatypeReleaseRepo
   #98 = Utf8               ()Lcoursier/core/Repository;
   #99 = NameAndType        #97:#98       // sonatypeReleaseRepo:()Lcoursier/core/Repository;
  #100 = Methodref          #23.#99       // org/sireum/Coursier_Ext$.sonatypeReleaseRepo:()Lcoursier/core/Repository;
  #101 = Utf8               localMavenRepo
  #102 = NameAndType        #101:#98      // localMavenRepo:()Lcoursier/core/Repository;
  #103 = Methodref          #23.#102      // org/sireum/Coursier_Ext$.localMavenRepo:()Lcoursier/core/Repository;
  #104 = Utf8               Code
  #105 = Utf8               LocalVariableTable
  #106 = Utf8               MethodParameters
  #107 = Utf8               Signature
  #108 = Utf8               InnerClasses
  #109 = Utf8               SourceFile
  #110 = Utf8               RuntimeVisibleAnnotations
  #111 = Utf8               ScalaSig
{
  public static boolean isRuntimePublishedLocally(java.lang.String);
    descriptor: (Ljava/lang/String;)Z
    flags: (0x0009) ACC_PUBLIC, ACC_STATIC
    Code:
      stack=2, locals=1, args_size=1
         0: getstatic     #27                 // Field org/sireum/Coursier_Ext$.MODULE$:Lorg/sireum/Coursier_Ext$;
         3: aload_0
         4: invokevirtual #29                 // Method org/sireum/Coursier_Ext$.isRuntimePublishedLocally:(Ljava/lang/String;)Z
         7: ireturn
      LocalVariableTable:
        Start  Length  Slot  Name   Signature
            0       8     0 version   Ljava/lang/String;
    MethodParameters:
      Name                           Flags
      version                        final

  public static org.sireum.IS<org.sireum.Z, org.sireum.CoursierFileInfo> fetchClassifiers(org.sireum.IS<org.sireum.Z, org.sireum.String>, org.sireum.IS<org.sireum.Z, org.sireum.CoursierClassifier$Type>);
    descriptor: (Lorg/sireum/IS;Lorg/sireum/IS;)Lorg/sireum/IS;
    flags: (0x0009) ACC_PUBLIC, ACC_STATIC
    Code:
      stack=3, locals=2, args_size=2
         0: getstatic     #27                 // Field org/sireum/Coursier_Ext$.MODULE$:Lorg/sireum/Coursier_Ext$;
         3: aload_0
         4: aload_1
         5: invokevirtual #37                 // Method org/sireum/Coursier_Ext$.fetchClassifiers:(Lorg/sireum/IS;Lorg/sireum/IS;)Lorg/sireum/IS;
         8: areturn
      LocalVariableTable:
        Start  Length  Slot  Name   Signature
            0       9     0  deps   Lorg/sireum/IS;
            0       9     1   cls   Lorg/sireum/IS;
    Signature: #33                          // (Lorg/sireum/IS<Lorg/sireum/Z;Lorg/sireum/String;>;Lorg/sireum/IS<Lorg/sireum/Z;Lorg/sireum/CoursierClassifier$Type;>;)Lorg/sireum/IS<Lorg/sireum/Z;Lorg/sireum/CoursierFileInfo;>;
    MethodParameters:
      Name                           Flags
      deps                           final
      cls                            final

  public static org.sireum.IS<org.sireum.Z, org.sireum.CoursierFileInfo> fetch(org.sireum.IS<org.sireum.Z, org.sireum.String>);
    descriptor: (Lorg/sireum/IS;)Lorg/sireum/IS;
    flags: (0x0009) ACC_PUBLIC, ACC_STATIC
    Code:
      stack=2, locals=1, args_size=1
         0: getstatic     #27                 // Field org/sireum/Coursier_Ext$.MODULE$:Lorg/sireum/Coursier_Ext$;
         3: aload_0
         4: invokevirtual #43                 // Method org/sireum/Coursier_Ext$.fetch:(Lorg/sireum/IS;)Lorg/sireum/IS;
         7: areturn
      LocalVariableTable:
        Start  Length  Slot  Name   Signature
            0       8     0  deps   Lorg/sireum/IS;
    Signature: #41                          // (Lorg/sireum/IS<Lorg/sireum/Z;Lorg/sireum/String;>;)Lorg/sireum/IS<Lorg/sireum/Z;Lorg/sireum/CoursierFileInfo;>;
    MethodParameters:
      Name                           Flags
      deps                           final

  public static void setMavenRepositories(org.sireum.IS<org.sireum.Z, org.sireum.String>);
    descriptor: (Lorg/sireum/IS;)V
    flags: (0x0009) ACC_PUBLIC, ACC_STATIC
    Code:
      stack=2, locals=1, args_size=1
         0: getstatic     #27                 // Field org/sireum/Coursier_Ext$.MODULE$:Lorg/sireum/Coursier_Ext$;
         3: aload_0
         4: invokevirtual #49                 // Method org/sireum/Coursier_Ext$.setMavenRepositories:(Lorg/sireum/IS;)V
         7: return
      LocalVariableTable:
        Start  Length  Slot  Name   Signature
            0       8     0  urls   Lorg/sireum/IS;
    Signature: #46                          // (Lorg/sireum/IS<Lorg/sireum/Z;Lorg/sireum/String;>;)V
    MethodParameters:
      Name                           Flags
      urls                           final

  public static void addMavenRepositories(org.sireum.IS<org.sireum.Z, org.sireum.String>);
    descriptor: (Lorg/sireum/IS;)V
    flags: (0x0009) ACC_PUBLIC, ACC_STATIC
    Code:
      stack=2, locals=1, args_size=1
         0: getstatic     #27                 // Field org/sireum/Coursier_Ext$.MODULE$:Lorg/sireum/Coursier_Ext$;
         3: aload_0
         4: invokevirtual #52                 // Method org/sireum/Coursier_Ext$.addMavenRepositories:(Lorg/sireum/IS;)V
         7: return
      LocalVariableTable:
        Start  Length  Slot  Name   Signature
            0       8     0  urls   Lorg/sireum/IS;
    Signature: #46                          // (Lorg/sireum/IS<Lorg/sireum/Z;Lorg/sireum/String;>;)V
    MethodParameters:
      Name                           Flags
      urls                           final

  public static void setCache(org.sireum.Option<org.sireum.Os$Path>);
    descriptor: (Lorg/sireum/Option;)V
    flags: (0x0009) ACC_PUBLIC, ACC_STATIC
    Code:
      stack=2, locals=1, args_size=1
         0: getstatic     #27                 // Field org/sireum/Coursier_Ext$.MODULE$:Lorg/sireum/Coursier_Ext$;
         3: aload_0
         4: invokevirtual #58                 // Method org/sireum/Coursier_Ext$.setCache:(Lorg/sireum/Option;)V
         7: return
      LocalVariableTable:
        Start  Length  Slot  Name   Signature
            0       8     0 pathOpt   Lorg/sireum/Option;
    Signature: #55                          // (Lorg/sireum/Option<Lorg/sireum/Os$Path;>;)V
    MethodParameters:
      Name                           Flags
      pathOpt                        final

  public static void setScalaVersion(java.lang.String);
    descriptor: (Ljava/lang/String;)V
    flags: (0x0009) ACC_PUBLIC, ACC_STATIC
    Code:
      stack=2, locals=1, args_size=1
         0: getstatic     #27                 // Field org/sireum/Coursier_Ext$.MODULE$:Lorg/sireum/Coursier_Ext$;
         3: aload_0
         4: invokevirtual #63                 // Method org/sireum/Coursier_Ext$.setScalaVersion:(Ljava/lang/String;)V
         7: return
      LocalVariableTable:
        Start  Length  Slot  Name   Signature
            0       8     0 version   Ljava/lang/String;
    MethodParameters:
      Name                           Flags
      version                        final

  public static scala.collection.immutable.Seq<coursier.core.Dependency> toDeps(org.sireum.IS<org.sireum.Z, org.sireum.String>);
    descriptor: (Lorg/sireum/IS;)Lscala/collection/immutable/Seq;
    flags: (0x0009) ACC_PUBLIC, ACC_STATIC
    Code:
      stack=2, locals=1, args_size=1
         0: getstatic     #27                 // Field org/sireum/Coursier_Ext$.MODULE$:Lorg/sireum/Coursier_Ext$;
         3: aload_0
         4: invokevirtual #68                 // Method org/sireum/Coursier_Ext$.toDeps:(Lorg/sireum/IS;)Lscala/collection/immutable/Seq;
         7: areturn
      LocalVariableTable:
        Start  Length  Slot  Name   Signature
            0       8     0  deps   Lorg/sireum/IS;
    Signature: #66                          // (Lorg/sireum/IS<Lorg/sireum/Z;Lorg/sireum/String;>;)Lscala/collection/immutable/Seq<Lcoursier/core/Dependency;>;
    MethodParameters:
      Name                           Flags
      deps                           final

  public static org.sireum.IS<org.sireum.Z, coursier.core.Repository> repositories();
    descriptor: ()Lorg/sireum/IS;
    flags: (0x0009) ACC_PUBLIC, ACC_STATIC
    Code:
      stack=1, locals=0, args_size=0
         0: getstatic     #27                 // Field org/sireum/Coursier_Ext$.MODULE$:Lorg/sireum/Coursier_Ext$;
         3: invokevirtual #73                 // Method org/sireum/Coursier_Ext$.repositories:()Lorg/sireum/IS;
         6: areturn
    Signature: #71                          // ()Lorg/sireum/IS<Lorg/sireum/Z;Lcoursier/core/Repository;>;

  public static void mavenRepoUrls_$eq(org.sireum.IS<org.sireum.Z, org.sireum.String>);
    descriptor: (Lorg/sireum/IS;)V
    flags: (0x0009) ACC_PUBLIC, ACC_STATIC
    Code:
      stack=2, locals=1, args_size=1
         0: getstatic     #27                 // Field org/sireum/Coursier_Ext$.MODULE$:Lorg/sireum/Coursier_Ext$;
         3: aload_0
         4: invokevirtual #77                 // Method org/sireum/Coursier_Ext$.mavenRepoUrls_$eq:(Lorg/sireum/IS;)V
         7: return
      LocalVariableTable:
        Start  Length  Slot  Name   Signature
            0       8     0   x$1   Lorg/sireum/IS;
    Signature: #46                          // (Lorg/sireum/IS<Lorg/sireum/Z;Lorg/sireum/String;>;)V
    MethodParameters:
      Name                           Flags
      x$1                            final

  public static org.sireum.IS<org.sireum.Z, org.sireum.String> mavenRepoUrls();
    descriptor: ()Lorg/sireum/IS;
    flags: (0x0009) ACC_PUBLIC, ACC_STATIC
    Code:
      stack=1, locals=0, args_size=0
         0: getstatic     #27                 // Field org/sireum/Coursier_Ext$.MODULE$:Lorg/sireum/Coursier_Ext$;
         3: invokevirtual #81                 // Method org/sireum/Coursier_Ext$.mavenRepoUrls:()Lorg/sireum/IS;
         6: areturn
    Signature: #79                          // ()Lorg/sireum/IS<Lorg/sireum/Z;Lorg/sireum/String;>;

  public static void cacheOpt_$eq(org.sireum.Option<org.sireum.Os$Path>);
    descriptor: (Lorg/sireum/Option;)V
    flags: (0x0009) ACC_PUBLIC, ACC_STATIC
    Code:
      stack=2, locals=1, args_size=1
         0: getstatic     #27                 // Field org/sireum/Coursier_Ext$.MODULE$:Lorg/sireum/Coursier_Ext$;
         3: aload_0
         4: invokevirtual #84                 // Method org/sireum/Coursier_Ext$.cacheOpt_$eq:(Lorg/sireum/Option;)V
         7: return
      LocalVariableTable:
        Start  Length  Slot  Name   Signature
            0       8     0   x$1   Lorg/sireum/Option;
    Signature: #55                          // (Lorg/sireum/Option<Lorg/sireum/Os$Path;>;)V
    MethodParameters:
      Name                           Flags
      x$1                            final

  public static org.sireum.Option<org.sireum.Os$Path> cacheOpt();
    descriptor: ()Lorg/sireum/Option;
    flags: (0x0009) ACC_PUBLIC, ACC_STATIC
    Code:
      stack=1, locals=0, args_size=0
         0: getstatic     #27                 // Field org/sireum/Coursier_Ext$.MODULE$:Lorg/sireum/Coursier_Ext$;
         3: invokevirtual #89                 // Method org/sireum/Coursier_Ext$.cacheOpt:()Lorg/sireum/Option;
         6: areturn
    Signature: #87                          // ()Lorg/sireum/Option<Lorg/sireum/Os$Path;>;

  public static void scalaVersion_$eq(java.lang.String);
    descriptor: (Ljava/lang/String;)V
    flags: (0x0009) ACC_PUBLIC, ACC_STATIC
    Code:
      stack=2, locals=1, args_size=1
         0: getstatic     #27                 // Field org/sireum/Coursier_Ext$.MODULE$:Lorg/sireum/Coursier_Ext$;
         3: aload_0
         4: invokevirtual #92                 // Method org/sireum/Coursier_Ext$.scalaVersion_$eq:(Ljava/lang/String;)V
         7: return
      LocalVariableTable:
        Start  Length  Slot  Name   Signature
            0       8     0   x$1   Ljava/lang/String;
    MethodParameters:
      Name                           Flags
      x$1                            final

  public static java.lang.String scalaVersion();
    descriptor: ()Ljava/lang/String;
    flags: (0x0009) ACC_PUBLIC, ACC_STATIC
    Code:
      stack=1, locals=0, args_size=0
         0: getstatic     #27                 // Field org/sireum/Coursier_Ext$.MODULE$:Lorg/sireum/Coursier_Ext$;
         3: invokevirtual #96                 // Method org/sireum/Coursier_Ext$.scalaVersion:()Ljava/lang/String;
         6: areturn

  public static coursier.core.Repository sonatypeReleaseRepo();
    descriptor: ()Lcoursier/core/Repository;
    flags: (0x0009) ACC_PUBLIC, ACC_STATIC
    Code:
      stack=1, locals=0, args_size=0
         0: getstatic     #27                 // Field org/sireum/Coursier_Ext$.MODULE$:Lorg/sireum/Coursier_Ext$;
         3: invokevirtual #100                // Method org/sireum/Coursier_Ext$.sonatypeReleaseRepo:()Lcoursier/core/Repository;
         6: areturn

  public static coursier.core.Repository localMavenRepo();
    descriptor: ()Lcoursier/core/Repository;
    flags: (0x0009) ACC_PUBLIC, ACC_STATIC
    Code:
      stack=1, locals=0, args_size=0
         0: getstatic     #27                 // Field org/sireum/Coursier_Ext$.MODULE$:Lorg/sireum/Coursier_Ext$;
         3: invokevirtual #103                // Method org/sireum/Coursier_Ext$.localMavenRepo:()Lcoursier/core/Repository;
         6: areturn
}
InnerClasses:
  public static #13= #10 of #12;          // Type=class org/sireum/CoursierClassifier$Type of class org/sireum/CoursierClassifier
  public static #18= #15 of #17;          // Path=class org/sireum/Os$Path of class org/sireum/Os
SourceFile: "Coursier_Ext.scala"
RuntimeVisibleAnnotations:
  0: #6(#7=s#8)
    scala.reflect.ScalaSignature(
      bytes="\u0006\u0005\u0005=s!\u0002\u000e\u001c\u0011\u0003\u0001c!\u0002\u0012\u001c\u0011\u0003\u0019\u0003\"\u0002\u0016\u0002\t\u0003Y\u0003b\u0002\u0017\u0002\u0005\u0004%\t!\f\u0005\u0007y\u0005\u0001\u000b\u0011\u0002\u0018\t\u000fu\n!\u0019!C\u0001[!1a(\u0001Q\u0001\n9BqaP\u0001A\u0002\u0013\u0005\u0001\tC\u0004E\u0003\u0001\u0007I\u0011A#\t\r-\u000b\u0001\u0015)\u0003B\u0011\u001da\u0015\u00011A\u0005\u00025Cq\u0001W\u0001A\u0002\u0013\u0005\u0011\f\u0003\u0004\\\u0003\u0001\u0006KA\u0014\u0005\b9\u0006\u0001\r\u0011\"\u0001^\u0011\u001d9\u0017\u00011A\u0005\u0002!DaA[\u0001!B\u0013q\u0006bB6\u0002\u0005\u0004%\t\u0001\u001c\u0005\u0007]\u0006\u0001\u000b\u0011B7\t\u000b=\fA\u0011\u00019\t\u000by\fA\u0011A@\t\u000f\u0005\u0015\u0011\u0001\"\u0001\u0002\b!9\u0011QB\u0001\u0005\u0002\u0005=\u0001bBA\u000b\u0003\u0011\u0005\u0011q\u0003\u0005\b\u00037\tA\u0011AA\u000f\u0011\u001d\tI#\u0001C\u0001\u0003WAq!a\u0011\u0002\t\u0003\t)%\u0001\u0007D_V\u00148/[3s?\u0016CHO\u0003\u0002\u001d;\u000511/\u001b:fk6T\u0011AH\u0001\u0004_J<7\u0001\u0001\t\u0003C\u0005i\u0011a\u0007\u0002\r\u0007>,(o]5fe~+\u0005\u0010^\n\u0003\u0003\u0011\u0002\"!\n\u0015\u000e\u0003\u0019R\u0011aJ\u0001\u0006g\u000e\fG.Y\u0005\u0003S\u0019\u0012a!\u00118z%\u00164\u0017A\u0002\u001fj]&$h\bF\u0001!\u00039awnY1m\u001b\u00064XM\u001c*fa>,\u0012A\f\t\u0003_er!\u0001\r\u001c\u000f\u0005E\"T\"\u0001\u001a\u000b\u0005Mz\u0012A\u0002\u001fs_>$h(C\u00016\u0003!\u0019w.\u001e:tS\u0016\u0014\u0018BA\u001c9\u0003\u001d\u0001\u0018mY6bO\u0016T\u0011!N\u0005\u0003um\u0012!BU3q_NLGo\u001c:z\u0015\t9\u0004(A\bm_\u000e\fG.T1wK:\u0014V\r]8!\u0003M\u0019xN\\1usB,\'+\u001a7fCN,\'+\u001a9p\u0003Q\u0019xN\\1usB,\'+\u001a7fCN,\'+\u001a9pA\u0005a1oY1mCZ+\'o]5p]V\t\u0011\t\u0005\u0002\"\u0005&\u00111i\u0007\u0002\u0007\'R\u0014\u0018N\\4\u0002!M\u001c\u0017\r\\1WKJ\u001c\u0018n\u001c8`I\u0015\fHC\u0001$J!\t)s)\u0003\u0002IM\t!QK\\5u\u0011\u001dQ\u0005\"!AA\u0002\u0005\u000b1\u0001\u001f\u00132\u00035\u00198-\u00197b-\u0016\u00148/[8oA\u0005A1-Y2iK>\u0003H/F\u0001O!\r\ts*U\u0005\u0003!n\u0011aa\u00149uS>t\u0007C\u0001*V\u001d\t\t3+\u0003\u0002U7\u0005\u0011qj]\u0005\u0003-^\u0013A\u0001U1uQ*\u0011AkG\u0001\rG\u0006\u001c\u0007.Z(qi~#S-\u001d\u000b\u0003\rjCqAS\u0006\u0002\u0002\u0003\u0007a*A\u0005dC\u000eDWm\u00149uA\u0005iQ.\u0019<f]J+\u0007o\\+sYN,\u0012A\u0018\t\u0004?\u0006\feBA\u0011a\u0013\t94$\u0003\u0002cG\n\u0019\u0011j\u0015.\n\u0005\u0011,\'\u0001\u0004)bG.\fw-\u001a+sC&$(B\u00014\u001c\u0003%!\u0013N\u001c;fe:\fG.A\tnCZ,gNU3q_V\u0013Hn]0%KF$\"AR5\t\u000f)s\u0011\u0011!a\u0001=\u0006qQ.\u0019<f]J+\u0007o\\+sYN\u0004\u0013\u0001\u0004:fa>\u001c\u0018\u000e^8sS\u0016\u001cX#A7\u0011\u0007}\u000bg&A\u0007sKB|7/\u001b;pe&,7\u000fI\u0001\u0007i>$U\r]:\u0015\u0005Ed\bc\u0001:ws:\u00111/\u001e\b\u0003cQL\u0011aJ\u0005\u0003o\u0019J!a\u001e=\u0003\u0007M+\u0017O\u0003\u00028MA\u0011qF_\u0005\u0003wn\u0012!\u0002R3qK:$WM\\2z\u0011\u0015i(\u00031\u0001_\u0003\u0011!W\r]:\u0002\u001fM,GoU2bY\u00064VM]:j_:$2ARA\u0001\u0011\u0019\t\u0019a\u0005a\u0001\u0003\u00069a/\u001a:tS>t\u0017\u0001C:fi\u000e\u000b7\r[3\u0015\u0007\u0019\u000bI\u0001\u0003\u0004\u0002\fQ\u0001\rAT\u0001\ba\u0006$\bn\u00149u\u0003Q\tG\rZ\'bm\u0016t\'+\u001a9pg&$xN]5fgR\u0019a)!\u0005\t\r\u0005MQ\u00031\u0001_\u0003\u0011)(\u000f\\:\u0002)M,G/T1wK:\u0014V\r]8tSR|\'/[3t)\r1\u0015\u0011\u0004\u0005\u0007\u0003\'1\u0002\u0019\u00010\u0002\u000b\u0019,Go\u00195\u0015\t\u0005}\u0011q\u0005\t\u0005?\u0006\f\t\u0003E\u0002\"\u0003GI1!!\n\u001c\u0005A\u0019u.\u001e:tS\u0016\u0014h)\u001b7f\u0013:4w\u000eC\u0003~/\u0001\u0007a,\u0001\tgKR\u001c\u0007n\u00117bgNLg-[3sgR1\u0011qDA\u0017\u0003_AQ! \rA\u0002yCq!!\r\u0019\u0001\u0004\t\u0019$A\u0002dYN\u0004BaX1\u00026A!\u0011qGA\u001f\u001d\r\t\u0013\u0011H\u0005\u0004\u0003wY\u0012AE\"pkJ\u001c\u0018.\u001a:DY\u0006\u001c8/\u001b4jKJLA!a\u0010\u0002B\t!A+\u001f9f\u0015\r\tYdG\u0001\u001aSN\u0014VO\u001c;j[\u0016\u0004VO\u00197jg\",G\rT8dC2d\u0017\u0010\u0006\u0003\u0002H\u00055\u0003cA\u0011\u0002J%\u0019\u00111J\u000e\u0003\u0003\tCa!a\u0001\u001a\u0001\u0004\t\u0005"
    )
  ScalaSig: length = 0x3 (unknown attribute)
   05 02 00
