Classfile /Users/mw/Projects/slang-braindump/.jar/jar11/assemble/slang-braindump/assemble/content/org/sireum/Coursier.class
  Last modified May 29, 2022; size 3180 bytes
  SHA-256 checksum c234e73335be24c8b45f3d1f95ffbdb64879f3a2e23fe041ea73d1ede9f07ea8
  Compiled from "Coursier.scala"
public final class org.sireum.Coursier
  minor version: 0
  major version: 52
  flags: (0x0031) ACC_PUBLIC, ACC_FINAL, ACC_SUPER
  this_class: #2                          // org/sireum/Coursier
  super_class: #4                         // java/lang/Object
  interfaces: 0, fields: 0, methods: 10, attributes: 4
Constant pool:
   #1 = Utf8               org/sireum/Coursier
   #2 = Class              #1             // org/sireum/Coursier
   #3 = Utf8               java/lang/Object
   #4 = Class              #3             // java/lang/Object
   #5 = Utf8               Coursier.scala
   #6 = Utf8               Lscala/reflect/ScalaSignature;
   #7 = Utf8               bytes
   #8 = Utf8               \u0006\u0005a<Q!\u0004\b\t\u0002M1Q!\u0006\b\t\u0002YAQ!H\u0001\u0005\u0002yAQaH\u0001\u0005\u0002\u0001BQaK\u0001\u0005\u00021BQ\u0001M\u0001\u0005\u0002EBQaN\u0001\u0005\u0002aBQaO\u0001\u0005\u0002qBQ!S\u0001\u0005\u0002)CQ\u0001T\u0001\u0005\u00025CQAT\u0001\u0005\u0002=CQAV\u0001\u0005\u0002]CQaY\u0001\u0005\u0002\u0011\f\u0001bQ8veNLWM\u001d\u0006\u0003\u001fA\taa]5sKVl\'\"A\t\u0002\u0007=\u0014xm\u0001\u0001\u0011\u0005Q\tQ\"\u0001\b\u0003\u0011\r{WO]:jKJ\u001c\"!A\f\u0011\u0005aYR\"A\r\u000b\u0003i\tQa]2bY\u0006L!\u0001H\r\u0003\r\u0005s\u0017PU3g\u0003\u0019a\u0014N\\5u}Q\t1#\u0001\u0005dC\u000eDWm\u00149u+\u0005\t\u0003c\u0001\u000b#I%\u00111E\u0004\u0002\u0007\u001fB$\u0018n\u001c8\u0011\u0005\u0015BcB\u0001\u000b\'\u0013\t9c\"\u0001\u0002Pg&\u0011\u0011F\u000b\u0002\u0005!\u0006$\bN\u0003\u0002(\u001d\u0005a1oY1mCZ+\'o]5p]V\tQ\u0006\u0005\u0002\u0015]%\u0011qF\u0004\u0002\u0007\'R\u0014\u0018N\\4\u0002\u001fM,GoU2bY\u00064VM]:j_:$\"AM\u001b\u0011\u0005a\u0019\u0014B\u0001\u001b\u001a\u0005\u0011)f.\u001b;\t\u000bY*\u0001\u0019A\u0017\u0002\u000fY,\'o]5p]\u0006A1/\u001a;DC\u000eDW\r\u0006\u00023s!)!H\u0002a\u0001C\u00059\u0001/\u0019;i\u001fB$\u0018\u0001F1eI6\u000bg/\u001a8SKB|7/\u001b;pe&,7\u000f\u0006\u00023{!)ah\u0002a\u0001\u007f\u0005!QO\u001d7t!\r\u00015)\f\b\u0003)\u0005K!A\u0011\b\u0002\u000fA\f7m[1hK&\u0011A)\u0012\u0002\u0004\u0013NS\u0016B\u0001$H\u00051\u0001\u0016mY6bO\u0016$&/Y5u\u0015\tAe\"A\u0005%S:$XM\u001d8bY\u0006!2/\u001a;NCZ,gNU3q_NLGo\u001c:jKN$\"AM&\t\u000byB\u0001\u0019A \u0002\u001b5\fg/\u001a8SKB|WK\u001d7t+\u0005y\u0014!\u00024fi\u000eDGC\u0001)U!\r\u00015)\u0015\t\u0003)IK!a\u0015\b\u0003!\r{WO]:jKJ4\u0015\u000e\\3J]\u001a|\u0007\"B+\u000b\u0001\u0004y\u0014\u0001\u00023faN\f\u0001CZ3uG\"\u001cE.Y:tS\u001aLWM]:\u0015\u0007AC\u0016\fC\u0003V\u0017\u0001\u0007q\bC\u0003[\u0017\u0001\u00071,A\u0002dYN\u00042\u0001Q\"]!\ti\u0006M\u0004\u0002\u0015=&\u0011qLD\u0001\u0013\u0007>,(o]5fe\u000ec\u0017m]:jM&,\'/\u0003\u0002bE\n!A+\u001f9f\u0015\tyf\"A\rjgJ+h\u000e^5nKB+(\r\\5tQ\u0016$Gj\\2bY2LHCA3i!\t!b-\u0003\u0002h\u001d\t\t!\tC\u00037\u0019\u0001\u0007Q\u0006K\u0002\u0002U6\u0004\"\u0001F6\n\u00051t!aA3yiF*1%\f8s_&\u0011q\u000e]\u0001\u001cI1,7o]5oSR$sM]3bi\u0016\u0014H\u0005Z3gCVdG\u000fJ\u0019\u000b\u0005Et\u0011aA3yiF*1e\u001d;vc:\u0011A\u0003^\u0005\u0003c:\tDA\t\u000b\u000fm\n11/\u001b:fk6D3\u0001\u00016n\u0001
   #9 = Utf8               org/sireum/CoursierClassifier$Type
  #10 = Class              #9             // org/sireum/CoursierClassifier$Type
  #11 = Utf8               org/sireum/CoursierClassifier
  #12 = Class              #11            // org/sireum/CoursierClassifier
  #13 = Utf8               Type
  #14 = Utf8               org/sireum/Os$Path
  #15 = Class              #14            // org/sireum/Os$Path
  #16 = Utf8               org/sireum/Os
  #17 = Class              #16            // org/sireum/Os
  #18 = Utf8               Path
  #19 = Utf8               isRuntimePublishedLocally
  #20 = Utf8               (Ljava/lang/String;)Z
  #21 = Utf8               version
  #22 = Utf8               org/sireum/Coursier$
  #23 = Class              #22            // org/sireum/Coursier$
  #24 = Utf8               MODULE$
  #25 = Utf8               Lorg/sireum/Coursier$;
  #26 = NameAndType        #24:#25        // MODULE$:Lorg/sireum/Coursier$;
  #27 = Fieldref           #23.#26        // org/sireum/Coursier$.MODULE$:Lorg/sireum/Coursier$;
  #28 = NameAndType        #19:#20        // isRuntimePublishedLocally:(Ljava/lang/String;)Z
  #29 = Methodref          #23.#28        // org/sireum/Coursier$.isRuntimePublishedLocally:(Ljava/lang/String;)Z
  #30 = Utf8               Ljava/lang/String;
  #31 = Utf8               fetchClassifiers
  #32 = Utf8               (Lorg/sireum/IS;Lorg/sireum/IS;)Lorg/sireum/IS;
  #33 = Utf8               (Lorg/sireum/IS<Lorg/sireum/Z;Lorg/sireum/String;>;Lorg/sireum/IS<Lorg/sireum/Z;Lorg/sireum/CoursierClassifier$Type;>;)Lorg/sireum/IS<Lorg/sireum/Z;Lorg/sireum/CoursierFileInfo;>;
  #34 = Utf8               deps
  #35 = Utf8               cls
  #36 = NameAndType        #31:#32        // fetchClassifiers:(Lorg/sireum/IS;Lorg/sireum/IS;)Lorg/sireum/IS;
  #37 = Methodref          #23.#36        // org/sireum/Coursier$.fetchClassifiers:(Lorg/sireum/IS;Lorg/sireum/IS;)Lorg/sireum/IS;
  #38 = Utf8               Lorg/sireum/IS;
  #39 = Utf8               fetch
  #40 = Utf8               (Lorg/sireum/IS;)Lorg/sireum/IS;
  #41 = Utf8               (Lorg/sireum/IS<Lorg/sireum/Z;Lorg/sireum/String;>;)Lorg/sireum/IS<Lorg/sireum/Z;Lorg/sireum/CoursierFileInfo;>;
  #42 = NameAndType        #39:#40        // fetch:(Lorg/sireum/IS;)Lorg/sireum/IS;
  #43 = Methodref          #23.#42        // org/sireum/Coursier$.fetch:(Lorg/sireum/IS;)Lorg/sireum/IS;
  #44 = Utf8               mavenRepoUrls
  #45 = Utf8               ()Lorg/sireum/IS;
  #46 = Utf8               ()Lorg/sireum/IS<Lorg/sireum/Z;Lorg/sireum/String;>;
  #47 = NameAndType        #44:#45        // mavenRepoUrls:()Lorg/sireum/IS;
  #48 = Methodref          #23.#47        // org/sireum/Coursier$.mavenRepoUrls:()Lorg/sireum/IS;
  #49 = Utf8               setMavenRepositories
  #50 = Utf8               (Lorg/sireum/IS;)V
  #51 = Utf8               (Lorg/sireum/IS<Lorg/sireum/Z;Lorg/sireum/String;>;)V
  #52 = Utf8               urls
  #53 = NameAndType        #49:#50        // setMavenRepositories:(Lorg/sireum/IS;)V
  #54 = Methodref          #23.#53        // org/sireum/Coursier$.setMavenRepositories:(Lorg/sireum/IS;)V
  #55 = Utf8               addMavenRepositories
  #56 = NameAndType        #55:#50        // addMavenRepositories:(Lorg/sireum/IS;)V
  #57 = Methodref          #23.#56        // org/sireum/Coursier$.addMavenRepositories:(Lorg/sireum/IS;)V
  #58 = Utf8               setCache
  #59 = Utf8               (Lorg/sireum/Option;)V
  #60 = Utf8               (Lorg/sireum/Option<Lorg/sireum/Os$Path;>;)V
  #61 = Utf8               pathOpt
  #62 = NameAndType        #58:#59        // setCache:(Lorg/sireum/Option;)V
  #63 = Methodref          #23.#62        // org/sireum/Coursier$.setCache:(Lorg/sireum/Option;)V
  #64 = Utf8               Lorg/sireum/Option;
  #65 = Utf8               setScalaVersion
  #66 = Utf8               (Ljava/lang/String;)V
  #67 = NameAndType        #65:#66        // setScalaVersion:(Ljava/lang/String;)V
  #68 = Methodref          #23.#67        // org/sireum/Coursier$.setScalaVersion:(Ljava/lang/String;)V
  #69 = Utf8               scalaVersion
  #70 = Utf8               ()Ljava/lang/String;
  #71 = NameAndType        #69:#70        // scalaVersion:()Ljava/lang/String;
  #72 = Methodref          #23.#71        // org/sireum/Coursier$.scalaVersion:()Ljava/lang/String;
  #73 = Utf8               cacheOpt
  #74 = Utf8               ()Lorg/sireum/Option;
  #75 = Utf8               ()Lorg/sireum/Option<Lorg/sireum/Os$Path;>;
  #76 = NameAndType        #73:#74        // cacheOpt:()Lorg/sireum/Option;
  #77 = Methodref          #23.#76        // org/sireum/Coursier$.cacheOpt:()Lorg/sireum/Option;
  #78 = Utf8               Code
  #79 = Utf8               LocalVariableTable
  #80 = Utf8               MethodParameters
  #81 = Utf8               Signature
  #82 = Utf8               InnerClasses
  #83 = Utf8               SourceFile
  #84 = Utf8               RuntimeVisibleAnnotations
  #85 = Utf8               ScalaSig
{
  public static boolean isRuntimePublishedLocally(java.lang.String);
    descriptor: (Ljava/lang/String;)Z
    flags: (0x0009) ACC_PUBLIC, ACC_STATIC
    Code:
      stack=2, locals=1, args_size=1
         0: getstatic     #27                 // Field org/sireum/Coursier$.MODULE$:Lorg/sireum/Coursier$;
         3: aload_0
         4: invokevirtual #29                 // Method org/sireum/Coursier$.isRuntimePublishedLocally:(Ljava/lang/String;)Z
         7: ireturn
      LocalVariableTable:
        Start  Length  Slot  Name   Signature
            0       8     0 version   Ljava/lang/String;
    MethodParameters:
      Name                           Flags
      version                        final

  public static org.sireum.IS<org.sireum.Z, org.sireum.CoursierFileInfo> fetchClassifiers(org.sireum.IS<org.sireum.Z, org.sireum.String>, org.sireum.IS<org.sireum.Z, org.sireum.CoursierClassifier$Type>);
    descriptor: (Lorg/sireum/IS;Lorg/sireum/IS;)Lorg/sireum/IS;
    flags: (0x0009) ACC_PUBLIC, ACC_STATIC
    Code:
      stack=3, locals=2, args_size=2
         0: getstatic     #27                 // Field org/sireum/Coursier$.MODULE$:Lorg/sireum/Coursier$;
         3: aload_0
         4: aload_1
         5: invokevirtual #37                 // Method org/sireum/Coursier$.fetchClassifiers:(Lorg/sireum/IS;Lorg/sireum/IS;)Lorg/sireum/IS;
         8: areturn
      LocalVariableTable:
        Start  Length  Slot  Name   Signature
            0       9     0  deps   Lorg/sireum/IS;
            0       9     1   cls   Lorg/sireum/IS;
    Signature: #33                          // (Lorg/sireum/IS<Lorg/sireum/Z;Lorg/sireum/String;>;Lorg/sireum/IS<Lorg/sireum/Z;Lorg/sireum/CoursierClassifier$Type;>;)Lorg/sireum/IS<Lorg/sireum/Z;Lorg/sireum/CoursierFileInfo;>;
    MethodParameters:
      Name                           Flags
      deps                           final
      cls                            final

  public static org.sireum.IS<org.sireum.Z, org.sireum.CoursierFileInfo> fetch(org.sireum.IS<org.sireum.Z, org.sireum.String>);
    descriptor: (Lorg/sireum/IS;)Lorg/sireum/IS;
    flags: (0x0009) ACC_PUBLIC, ACC_STATIC
    Code:
      stack=2, locals=1, args_size=1
         0: getstatic     #27                 // Field org/sireum/Coursier$.MODULE$:Lorg/sireum/Coursier$;
         3: aload_0
         4: invokevirtual #43                 // Method org/sireum/Coursier$.fetch:(Lorg/sireum/IS;)Lorg/sireum/IS;
         7: areturn
      LocalVariableTable:
        Start  Length  Slot  Name   Signature
            0       8     0  deps   Lorg/sireum/IS;
    Signature: #41                          // (Lorg/sireum/IS<Lorg/sireum/Z;Lorg/sireum/String;>;)Lorg/sireum/IS<Lorg/sireum/Z;Lorg/sireum/CoursierFileInfo;>;
    MethodParameters:
      Name                           Flags
      deps                           final

  public static org.sireum.IS<org.sireum.Z, org.sireum.String> mavenRepoUrls();
    descriptor: ()Lorg/sireum/IS;
    flags: (0x0009) ACC_PUBLIC, ACC_STATIC
    Code:
      stack=1, locals=0, args_size=0
         0: getstatic     #27                 // Field org/sireum/Coursier$.MODULE$:Lorg/sireum/Coursier$;
         3: invokevirtual #48                 // Method org/sireum/Coursier$.mavenRepoUrls:()Lorg/sireum/IS;
         6: areturn
    Signature: #46                          // ()Lorg/sireum/IS<Lorg/sireum/Z;Lorg/sireum/String;>;

  public static void setMavenRepositories(org.sireum.IS<org.sireum.Z, org.sireum.String>);
    descriptor: (Lorg/sireum/IS;)V
    flags: (0x0009) ACC_PUBLIC, ACC_STATIC
    Code:
      stack=2, locals=1, args_size=1
         0: getstatic     #27                 // Field org/sireum/Coursier$.MODULE$:Lorg/sireum/Coursier$;
         3: aload_0
         4: invokevirtual #54                 // Method org/sireum/Coursier$.setMavenRepositories:(Lorg/sireum/IS;)V
         7: return
      LocalVariableTable:
        Start  Length  Slot  Name   Signature
            0       8     0  urls   Lorg/sireum/IS;
    Signature: #51                          // (Lorg/sireum/IS<Lorg/sireum/Z;Lorg/sireum/String;>;)V
    MethodParameters:
      Name                           Flags
      urls                           final

  public static void addMavenRepositories(org.sireum.IS<org.sireum.Z, org.sireum.String>);
    descriptor: (Lorg/sireum/IS;)V
    flags: (0x0009) ACC_PUBLIC, ACC_STATIC
    Code:
      stack=2, locals=1, args_size=1
         0: getstatic     #27                 // Field org/sireum/Coursier$.MODULE$:Lorg/sireum/Coursier$;
         3: aload_0
         4: invokevirtual #57                 // Method org/sireum/Coursier$.addMavenRepositories:(Lorg/sireum/IS;)V
         7: return
      LocalVariableTable:
        Start  Length  Slot  Name   Signature
            0       8     0  urls   Lorg/sireum/IS;
    Signature: #51                          // (Lorg/sireum/IS<Lorg/sireum/Z;Lorg/sireum/String;>;)V
    MethodParameters:
      Name                           Flags
      urls                           final

  public static void setCache(org.sireum.Option<org.sireum.Os$Path>);
    descriptor: (Lorg/sireum/Option;)V
    flags: (0x0009) ACC_PUBLIC, ACC_STATIC
    Code:
      stack=2, locals=1, args_size=1
         0: getstatic     #27                 // Field org/sireum/Coursier$.MODULE$:Lorg/sireum/Coursier$;
         3: aload_0
         4: invokevirtual #63                 // Method org/sireum/Coursier$.setCache:(Lorg/sireum/Option;)V
         7: return
      LocalVariableTable:
        Start  Length  Slot  Name   Signature
            0       8     0 pathOpt   Lorg/sireum/Option;
    Signature: #60                          // (Lorg/sireum/Option<Lorg/sireum/Os$Path;>;)V
    MethodParameters:
      Name                           Flags
      pathOpt                        final

  public static void setScalaVersion(java.lang.String);
    descriptor: (Ljava/lang/String;)V
    flags: (0x0009) ACC_PUBLIC, ACC_STATIC
    Code:
      stack=2, locals=1, args_size=1
         0: getstatic     #27                 // Field org/sireum/Coursier$.MODULE$:Lorg/sireum/Coursier$;
         3: aload_0
         4: invokevirtual #68                 // Method org/sireum/Coursier$.setScalaVersion:(Ljava/lang/String;)V
         7: return
      LocalVariableTable:
        Start  Length  Slot  Name   Signature
            0       8     0 version   Ljava/lang/String;
    MethodParameters:
      Name                           Flags
      version                        final

  public static java.lang.String scalaVersion();
    descriptor: ()Ljava/lang/String;
    flags: (0x0009) ACC_PUBLIC, ACC_STATIC
    Code:
      stack=1, locals=0, args_size=0
         0: getstatic     #27                 // Field org/sireum/Coursier$.MODULE$:Lorg/sireum/Coursier$;
         3: invokevirtual #72                 // Method org/sireum/Coursier$.scalaVersion:()Ljava/lang/String;
         6: areturn

  public static org.sireum.Option<org.sireum.Os$Path> cacheOpt();
    descriptor: ()Lorg/sireum/Option;
    flags: (0x0009) ACC_PUBLIC, ACC_STATIC
    Code:
      stack=1, locals=0, args_size=0
         0: getstatic     #27                 // Field org/sireum/Coursier$.MODULE$:Lorg/sireum/Coursier$;
         3: invokevirtual #77                 // Method org/sireum/Coursier$.cacheOpt:()Lorg/sireum/Option;
         6: areturn
    Signature: #75                          // ()Lorg/sireum/Option<Lorg/sireum/Os$Path;>;
}
InnerClasses:
  public static #13= #10 of #12;          // Type=class org/sireum/CoursierClassifier$Type of class org/sireum/CoursierClassifier
  public static #18= #15 of #17;          // Path=class org/sireum/Os$Path of class org/sireum/Os
SourceFile: "Coursier.scala"
RuntimeVisibleAnnotations:
  0: #6(#7=s#8)
    scala.reflect.ScalaSignature(
      bytes="\u0006\u0005a<Q!\u0004\b\t\u0002M1Q!\u0006\b\t\u0002YAQ!H\u0001\u0005\u0002yAQaH\u0001\u0005\u0002\u0001BQaK\u0001\u0005\u00021BQ\u0001M\u0001\u0005\u0002EBQaN\u0001\u0005\u0002aBQaO\u0001\u0005\u0002qBQ!S\u0001\u0005\u0002)CQ\u0001T\u0001\u0005\u00025CQAT\u0001\u0005\u0002=CQAV\u0001\u0005\u0002]CQaY\u0001\u0005\u0002\u0011\f\u0001bQ8veNLWM\u001d\u0006\u0003\u001fA\taa]5sKVl\'\"A\t\u0002\u0007=\u0014xm\u0001\u0001\u0011\u0005Q\tQ\"\u0001\b\u0003\u0011\r{WO]:jKJ\u001c\"!A\f\u0011\u0005aYR\"A\r\u000b\u0003i\tQa]2bY\u0006L!\u0001H\r\u0003\r\u0005s\u0017PU3g\u0003\u0019a\u0014N\\5u}Q\t1#\u0001\u0005dC\u000eDWm\u00149u+\u0005\t\u0003c\u0001\u000b#I%\u00111E\u0004\u0002\u0007\u001fB$\u0018n\u001c8\u0011\u0005\u0015BcB\u0001\u000b\'\u0013\t9c\"\u0001\u0002Pg&\u0011\u0011F\u000b\u0002\u0005!\u0006$\bN\u0003\u0002(\u001d\u0005a1oY1mCZ+\'o]5p]V\tQ\u0006\u0005\u0002\u0015]%\u0011qF\u0004\u0002\u0007\'R\u0014\u0018N\\4\u0002\u001fM,GoU2bY\u00064VM]:j_:$\"AM\u001b\u0011\u0005a\u0019\u0014B\u0001\u001b\u001a\u0005\u0011)f.\u001b;\t\u000bY*\u0001\u0019A\u0017\u0002\u000fY,\'o]5p]\u0006A1/\u001a;DC\u000eDW\r\u0006\u00023s!)!H\u0002a\u0001C\u00059\u0001/\u0019;i\u001fB$\u0018\u0001F1eI6\u000bg/\u001a8SKB|7/\u001b;pe&,7\u000f\u0006\u00023{!)ah\u0002a\u0001\u007f\u0005!QO\u001d7t!\r\u00015)\f\b\u0003)\u0005K!A\u0011\b\u0002\u000fA\f7m[1hK&\u0011A)\u0012\u0002\u0004\u0013NS\u0016B\u0001$H\u00051\u0001\u0016mY6bO\u0016$&/Y5u\u0015\tAe\"A\u0005%S:$XM\u001d8bY\u0006!2/\u001a;NCZ,gNU3q_NLGo\u001c:jKN$\"AM&\t\u000byB\u0001\u0019A \u0002\u001b5\fg/\u001a8SKB|WK\u001d7t+\u0005y\u0014!\u00024fi\u000eDGC\u0001)U!\r\u00015)\u0015\t\u0003)IK!a\u0015\b\u0003!\r{WO]:jKJ4\u0015\u000e\\3J]\u001a|\u0007\"B+\u000b\u0001\u0004y\u0014\u0001\u00023faN\f\u0001CZ3uG\"\u001cE.Y:tS\u001aLWM]:\u0015\u0007AC\u0016\fC\u0003V\u0017\u0001\u0007q\bC\u0003[\u0017\u0001\u00071,A\u0002dYN\u00042\u0001Q\"]!\ti\u0006M\u0004\u0002\u0015=&\u0011qLD\u0001\u0013\u0007>,(o]5fe\u000ec\u0017m]:jM&,\'/\u0003\u0002bE\n!A+\u001f9f\u0015\tyf\"A\rjgJ+h\u000e^5nKB+(\r\\5tQ\u0016$Gj\\2bY2LHCA3i!\t!b-\u0003\u0002h\u001d\t\t!\tC\u00037\u0019\u0001\u0007Q\u0006K\u0002\u0002U6\u0004\"\u0001F6\n\u00051t!aA3yiF*1%\f8s_&\u0011q\u000e]\u0001\u001cI1,7o]5oSR$sM]3bi\u0016\u0014H\u0005Z3gCVdG\u000fJ\u0019\u000b\u0005Et\u0011aA3yiF*1e\u001d;vc:\u0011A\u0003^\u0005\u0003c:\tDA\t\u000b\u000fm\n11/\u001b:fk6D3\u0001\u00016n\u0001"
    )
  ScalaSig: length = 0x3 (unknown attribute)
   05 02 00
