Classfile /Users/mw/Projects/slang-braindump/.jar/jar11/assemble/slang-braindump/assemble/content/org/sireum/Either$Left$.class
  Last modified May 29, 2022; size 1187 bytes
  SHA-256 checksum 9cc044c21531a2a43c057014232e0d4b6c2ee3181d3e6e77b256452de626da60
  Compiled from "Either.scala"
public class org.sireum.Either$Left$
  minor version: 0
  major version: 52
  flags: (0x0021) ACC_PUBLIC, ACC_SUPER
  this_class: #2                          // org/sireum/Either$Left$
  super_class: #4                         // java/lang/Object
  interfaces: 0, fields: 1, methods: 4, attributes: 4
Constant pool:
   #1 = Utf8               org/sireum/Either$Left$
   #2 = Class              #1             // org/sireum/Either$Left$
   #3 = Utf8               java/lang/Object
   #4 = Class              #3             // java/lang/Object
   #5 = Utf8               Either.scala
   #6 = Utf8               org/sireum/Either$Left
   #7 = Class              #6             // org/sireum/Either$Left
   #8 = Utf8               org/sireum/Either
   #9 = Class              #8             // org/sireum/Either
  #10 = Utf8               Left
  #11 = Utf8               Left$
  #12 = Utf8               MODULE$
  #13 = Utf8               Lorg/sireum/Either$Left$;
  #14 = Utf8               <clinit>
  #15 = Utf8               ()V
  #16 = Utf8               <init>
  #17 = NameAndType        #16:#15        // "<init>":()V
  #18 = Methodref          #2.#17         // org/sireum/Either$Left$."<init>":()V
  #19 = NameAndType        #12:#13        // MODULE$:Lorg/sireum/Either$Left$;
  #20 = Fieldref           #2.#19         // org/sireum/Either$Left$.MODULE$:Lorg/sireum/Either$Left$;
  #21 = Utf8               apply
  #22 = Utf8               (Ljava/lang/Object;)Lorg/sireum/Either$Left;
  #23 = Utf8               <L:Ljava/lang/Object;R:Ljava/lang/Object;>(TL;)Lorg/sireum/Either$Left<TL;TR;>;
  #24 = Utf8               value
  #25 = Utf8               (Ljava/lang/Object;)V
  #26 = NameAndType        #16:#25        // "<init>":(Ljava/lang/Object;)V
  #27 = Methodref          #7.#26         // org/sireum/Either$Left."<init>":(Ljava/lang/Object;)V
  #28 = Utf8               this
  #29 = Utf8               Ljava/lang/Object;
  #30 = Utf8               unapply
  #31 = Utf8               (Lorg/sireum/Either$Left;)Lscala/Some;
  #32 = Utf8               <L:Ljava/lang/Object;R:Ljava/lang/Object;>(Lorg/sireum/Either$Left<TL;TR;>;)Lscala/Some<TL;>;
  #33 = Utf8               o
  #34 = Utf8               scala/Some
  #35 = Class              #34            // scala/Some
  #36 = Utf8               ()Ljava/lang/Object;
  #37 = NameAndType        #24:#36        // value:()Ljava/lang/Object;
  #38 = Methodref          #7.#37         // org/sireum/Either$Left.value:()Ljava/lang/Object;
  #39 = Methodref          #35.#26        // scala/Some."<init>":(Ljava/lang/Object;)V
  #40 = Utf8               Lorg/sireum/Either$Left;
  #41 = Methodref          #4.#17         // java/lang/Object."<init>":()V
  #42 = Utf8               Code
  #43 = Utf8               LineNumberTable
  #44 = Utf8               LocalVariableTable
  #45 = Utf8               Signature
  #46 = Utf8               MethodParameters
  #47 = Utf8               InnerClasses
  #48 = Utf8               SourceFile
  #49 = Utf8               ScalaInlineInfo
  #50 = Utf8               Scala
{
  public static final org.sireum.Either$Left$ MODULE$;
    descriptor: Lorg/sireum/Either$Left$;
    flags: (0x0019) ACC_PUBLIC, ACC_STATIC, ACC_FINAL

  public static {};
    descriptor: ()V
    flags: (0x0009) ACC_PUBLIC, ACC_STATIC
    Code:
      stack=2, locals=0, args_size=0
         0: new           #2                  // class org/sireum/Either$Left$
         3: dup
         4: invokespecial #18                 // Method "<init>":()V
         7: putstatic     #20                 // Field MODULE$:Lorg/sireum/Either$Left$;
        10: return
      LineNumberTable:
        line 74: 0

  public <L extends java.lang.Object, R extends java.lang.Object> org.sireum.Either$Left<L, R> apply(L);
    descriptor: (Ljava/lang/Object;)Lorg/sireum/Either$Left;
    flags: (0x0001) ACC_PUBLIC
    Code:
      stack=3, locals=2, args_size=2
         0: new           #7                  // class org/sireum/Either$Left
         3: dup
         4: aload_1
         5: invokespecial #27                 // Method org/sireum/Either$Left."<init>":(Ljava/lang/Object;)V
         8: areturn
      LineNumberTable:
        line 74: 0
      LocalVariableTable:
        Start  Length  Slot  Name   Signature
            0       9     0  this   Lorg/sireum/Either$Left$;
            0       9     1 value   Ljava/lang/Object;
    Signature: #23                          // <L:Ljava/lang/Object;R:Ljava/lang/Object;>(TL;)Lorg/sireum/Either$Left<TL;TR;>;
    MethodParameters:
      Name                           Flags
      value                          final

  public <L extends java.lang.Object, R extends java.lang.Object> scala.Some<L> unapply(org.sireum.Either$Left<L, R>);
    descriptor: (Lorg/sireum/Either$Left;)Lscala/Some;
    flags: (0x0001) ACC_PUBLIC
    Code:
      stack=3, locals=2, args_size=2
         0: new           #35                 // class scala/Some
         3: dup
         4: aload_1
         5: invokevirtual #38                 // Method org/sireum/Either$Left.value:()Ljava/lang/Object;
         8: invokespecial #39                 // Method scala/Some."<init>":(Ljava/lang/Object;)V
        11: areturn
      LineNumberTable:
        line 74: 0
      LocalVariableTable:
        Start  Length  Slot  Name   Signature
            0      12     0  this   Lorg/sireum/Either$Left$;
            0      12     1     o   Lorg/sireum/Either$Left;
    Signature: #32                          // <L:Ljava/lang/Object;R:Ljava/lang/Object;>(Lorg/sireum/Either$Left<TL;TR;>;)Lscala/Some<TL;>;
    MethodParameters:
      Name                           Flags
      o                              final

  public org.sireum.Either$Left$();
    descriptor: ()V
    flags: (0x0001) ACC_PUBLIC
    Code:
      stack=1, locals=1, args_size=1
         0: aload_0
         1: invokespecial #41                 // Method java/lang/Object."<init>":()V
         4: return
      LineNumberTable:
        line 74: 0
      LocalVariableTable:
        Start  Length  Slot  Name   Signature
            0       5     0  this   Lorg/sireum/Either$Left$;
}
InnerClasses:
  public static final #10= #7 of #9;      // Left=class org/sireum/Either$Left of class org/sireum/Either
  public static #11= #2 of #9;            // Left$=class org/sireum/Either$Left$ of class org/sireum/Either
SourceFile: "Either.scala"
  ScalaInlineInfo: length = 0x13 (unknown attribute)
   01 01 00 03 00 10 00 0F 01 00 15 00 16 01 00 1E
   00 1F 01
  Scala: length = 0x0 (unknown attribute)

