Classfile /Users/mw/Projects/slang-braindump/.jar/jar11/assemble/slang-braindump/assemble/content/org/sireum/F64$Boxer$.class
  Last modified May 29, 2022; size 4405 bytes
  SHA-256 checksum adfd03e40e5ddf722a5def0b1f071bca6f4f88f56516701a2585b368ca1c6be6
  Compiled from "FloatingPoint.scala"
public class org.sireum.F64$Boxer$ implements org.sireum.$internal.Boxer
  minor version: 0
  major version: 52
  flags: (0x0021) ACC_PUBLIC, ACC_SUPER
  this_class: #2                          // org/sireum/F64$Boxer$
  super_class: #4                         // java/lang/Object
  interfaces: 1, fields: 1, methods: 16, attributes: 4
Constant pool:
    #1 = Utf8               org/sireum/F64$Boxer$
    #2 = Class              #1            // org/sireum/F64$Boxer$
    #3 = Utf8               java/lang/Object
    #4 = Class              #3            // java/lang/Object
    #5 = Utf8               org/sireum/$internal/Boxer
    #6 = Class              #5            // org/sireum/$internal/Boxer
    #7 = Utf8               FloatingPoint.scala
    #8 = Utf8               org/sireum/F64
    #9 = Class              #8            // org/sireum/F64
   #10 = Utf8               Boxer$
   #11 = Utf8               MODULE$
   #12 = Utf8               Lorg/sireum/F64$Boxer$;
   #13 = Utf8               <clinit>
   #14 = Utf8               ()V
   #15 = Utf8               <init>
   #16 = NameAndType        #15:#14       // "<init>":()V
   #17 = Methodref          #2.#16        // org/sireum/F64$Boxer$."<init>":()V
   #18 = NameAndType        #11:#12       // MODULE$:Lorg/sireum/F64$Boxer$;
   #19 = Fieldref           #2.#18        // org/sireum/F64$Boxer$.MODULE$:Lorg/sireum/F64$Boxer$;
   #20 = Utf8               $init$
   #21 = Utf8               (Lorg/sireum/$internal/Boxer;)V
   #22 = NameAndType        #20:#21       // $init$:(Lorg/sireum/$internal/Boxer;)V
   #23 = InterfaceMethodref #6.#22        // org/sireum/$internal/Boxer.$init$:(Lorg/sireum/$internal/Boxer;)V
   #24 = Utf8               size
   #25 = Utf8               (Ljava/lang/Object;)Lorg/sireum/Z;
   #26 = Utf8               a
   #27 = Utf8               size$
   #28 = Utf8               (Lorg/sireum/$internal/Boxer;Ljava/lang/Object;)Lorg/sireum/Z;
   #29 = NameAndType        #27:#28       // size$:(Lorg/sireum/$internal/Boxer;Ljava/lang/Object;)Lorg/sireum/Z;
   #30 = InterfaceMethodref #6.#29        // org/sireum/$internal/Boxer.size$:(Lorg/sireum/$internal/Boxer;Ljava/lang/Object;)Lorg/sireum/Z;
   #31 = Utf8               this
   #32 = Utf8               Ljava/lang/Object;
   #33 = Utf8               copy
   #34 = Utf8               (Ljava/lang/Object;Lorg/sireum/Z;Ljava/lang/Object;Lorg/sireum/Z;Lorg/sireum/Z;)V
   #35 = Utf8               src
   #36 = Utf8               srcPos
   #37 = Utf8               dest
   #38 = Utf8               destPos
   #39 = Utf8               length
   #40 = Utf8               copy$
   #41 = Utf8               (Lorg/sireum/$internal/Boxer;Ljava/lang/Object;Lorg/sireum/Z;Ljava/lang/Object;Lorg/sireum/Z;Lorg/sireum/Z;)V
   #42 = NameAndType        #40:#41       // copy$:(Lorg/sireum/$internal/Boxer;Ljava/lang/Object;Lorg/sireum/Z;Ljava/lang/Object;Lorg/sireum/Z;Lorg/sireum/Z;)V
   #43 = InterfaceMethodref #6.#42        // org/sireum/$internal/Boxer.copy$:(Lorg/sireum/$internal/Boxer;Ljava/lang/Object;Lorg/sireum/Z;Ljava/lang/Object;Lorg/sireum/Z;Lorg/sireum/Z;)V
   #44 = Utf8               Lorg/sireum/Z;
   #45 = Utf8               clone
   #46 = Utf8               (Ljava/lang/Object;Lorg/sireum/Z;Lorg/sireum/Z;Lorg/sireum/Z;)Ljava/lang/Object;
   #47 = Utf8               newLength
   #48 = Utf8               offset
   #49 = Utf8               clone$
   #50 = Utf8               (Lorg/sireum/$internal/Boxer;Ljava/lang/Object;Lorg/sireum/Z;Lorg/sireum/Z;Lorg/sireum/Z;)Ljava/lang/Object;
   #51 = NameAndType        #49:#50       // clone$:(Lorg/sireum/$internal/Boxer;Ljava/lang/Object;Lorg/sireum/Z;Lorg/sireum/Z;Lorg/sireum/Z;)Ljava/lang/Object;
   #52 = InterfaceMethodref #6.#51        // org/sireum/$internal/Boxer.clone$:(Lorg/sireum/$internal/Boxer;Ljava/lang/Object;Lorg/sireum/Z;Lorg/sireum/Z;Lorg/sireum/Z;)Ljava/lang/Object;
   #53 = Utf8               cloneMut
   #54 = Utf8               cloneMut$
   #55 = NameAndType        #54:#50       // cloneMut$:(Lorg/sireum/$internal/Boxer;Ljava/lang/Object;Lorg/sireum/Z;Lorg/sireum/Z;Lorg/sireum/Z;)Ljava/lang/Object;
   #56 = InterfaceMethodref #6.#55        // org/sireum/$internal/Boxer.cloneMut$:(Lorg/sireum/$internal/Boxer;Ljava/lang/Object;Lorg/sireum/Z;Lorg/sireum/Z;Lorg/sireum/Z;)Ljava/lang/Object;
   #57 = Utf8               toString
   #58 = Utf8               (Ljava/lang/Object;Lorg/sireum/Z;)Ljava/lang/String;
   #59 = Utf8               toString$
   #60 = Utf8               (Lorg/sireum/$internal/Boxer;Ljava/lang/Object;Lorg/sireum/Z;)Ljava/lang/String;
   #61 = NameAndType        #59:#60       // toString$:(Lorg/sireum/$internal/Boxer;Ljava/lang/Object;Lorg/sireum/Z;)Ljava/lang/String;
   #62 = InterfaceMethodref #6.#61        // org/sireum/$internal/Boxer.toString$:(Lorg/sireum/$internal/Boxer;Ljava/lang/Object;Lorg/sireum/Z;)Ljava/lang/String;
   #63 = Utf8               toInt
   #64 = Utf8               (Lorg/sireum/Z;)I
   #65 = Utf8               n
   #66 = Utf8               toInt$
   #67 = Utf8               (Lorg/sireum/$internal/Boxer;Lorg/sireum/Z;)I
   #68 = NameAndType        #66:#67       // toInt$:(Lorg/sireum/$internal/Boxer;Lorg/sireum/Z;)I
   #69 = InterfaceMethodref #6.#68        // org/sireum/$internal/Boxer.toInt$:(Lorg/sireum/$internal/Boxer;Lorg/sireum/Z;)I
   #70 = Utf8               toLong
   #71 = Utf8               (Lorg/sireum/Z;)J
   #72 = Utf8               toLong$
   #73 = Utf8               (Lorg/sireum/$internal/Boxer;Lorg/sireum/Z;)J
   #74 = NameAndType        #72:#73       // toLong$:(Lorg/sireum/$internal/Boxer;Lorg/sireum/Z;)J
   #75 = InterfaceMethodref #6.#74        // org/sireum/$internal/Boxer.toLong$:(Lorg/sireum/$internal/Boxer;Lorg/sireum/Z;)J
   #76 = Utf8               box
   #77 = Utf8               (Ljava/lang/Object;)Ljava/lang/Object;
   #78 = Utf8               <T:Ljava/lang/Object;>(Ljava/lang/Object;)TT;
   #79 = Utf8               o
   #80 = Utf8               java/lang/Double
   #81 = Class              #80           // java/lang/Double
   #82 = Utf8               scala/runtime/BoxesRunTime
   #83 = Class              #82           // scala/runtime/BoxesRunTime
   #84 = Utf8               unboxToDouble
   #85 = Utf8               (Ljava/lang/Object;)D
   #86 = NameAndType        #84:#85       // unboxToDouble:(Ljava/lang/Object;)D
   #87 = Methodref          #83.#86       // scala/runtime/BoxesRunTime.unboxToDouble:(Ljava/lang/Object;)D
   #88 = Utf8               org/sireum/F64$
   #89 = Class              #88           // org/sireum/F64$
   #90 = Utf8               Lorg/sireum/F64$;
   #91 = NameAndType        #11:#90       // MODULE$:Lorg/sireum/F64$;
   #92 = Fieldref           #89.#91       // org/sireum/F64$.MODULE$:Lorg/sireum/F64$;
   #93 = Utf8               apply
   #94 = Utf8               (D)D
   #95 = NameAndType        #93:#94       // apply:(D)D
   #96 = Methodref          #89.#95       // org/sireum/F64$.apply:(D)D
   #97 = Utf8               (D)V
   #98 = NameAndType        #15:#97       // "<init>":(D)V
   #99 = Methodref          #9.#98        // org/sireum/F64."<init>":(D)V
  #100 = Utf8               scala/MatchError
  #101 = Class              #100          // scala/MatchError
  #102 = Utf8               (Ljava/lang/Object;)V
  #103 = NameAndType        #15:#102      // "<init>":(Ljava/lang/Object;)V
  #104 = Methodref          #101.#103     // scala/MatchError."<init>":(Ljava/lang/Object;)V
  #105 = Utf8               unbox
  #106 = Utf8               value
  #107 = Utf8               ()D
  #108 = NameAndType        #106:#107     // value:()D
  #109 = Methodref          #9.#108       // org/sireum/F64.value:()D
  #110 = Utf8               copyMut
  #111 = NameAndType        #33:#34       // copy:(Ljava/lang/Object;Lorg/sireum/Z;Ljava/lang/Object;Lorg/sireum/Z;Lorg/sireum/Z;)V
  #112 = Methodref          #2.#111       // org/sireum/F64$Boxer$.copy:(Ljava/lang/Object;Lorg/sireum/Z;Ljava/lang/Object;Lorg/sireum/Z;Lorg/sireum/Z;)V
  #113 = Utf8               create
  #114 = Utf8               (Lorg/sireum/Z;)Ljava/lang/Object;
  #115 = NameAndType        #63:#64       // toInt:(Lorg/sireum/Z;)I
  #116 = Methodref          #2.#115       // org/sireum/F64$Boxer$.toInt:(Lorg/sireum/Z;)I
  #117 = Utf8               lookup
  #118 = Utf8               (Ljava/lang/Object;Lorg/sireum/Z;)Ljava/lang/Object;
  #119 = Utf8               <T:Ljava/lang/Object;>(Ljava/lang/Object;Lorg/sireum/Z;)TT;
  #120 = Utf8               i
  #121 = Utf8               [D
  #122 = Class              #121          // "[D"
  #123 = Utf8               boxToDouble
  #124 = Utf8               (D)Ljava/lang/Double;
  #125 = NameAndType        #123:#124     // boxToDouble:(D)Ljava/lang/Double;
  #126 = Methodref          #83.#125      // scala/runtime/BoxesRunTime.boxToDouble:(D)Ljava/lang/Double;
  #127 = NameAndType        #76:#77       // box:(Ljava/lang/Object;)Ljava/lang/Object;
  #128 = Methodref          #2.#127       // org/sireum/F64$Boxer$.box:(Ljava/lang/Object;)Ljava/lang/Object;
  #129 = Utf8               org/sireum/Z
  #130 = Class              #129          // org/sireum/Z
  #131 = Utf8               store
  #132 = Utf8               (Ljava/lang/Object;Lorg/sireum/Z;Ljava/lang/Object;)V
  #133 = Utf8               v
  #134 = NameAndType        #105:#85      // unbox:(Ljava/lang/Object;)D
  #135 = Methodref          #2.#134       // org/sireum/F64$Boxer$.unbox:(Ljava/lang/Object;)D
  #136 = Utf8               scala/runtime/BoxedUnit
  #137 = Class              #136          // scala/runtime/BoxedUnit
  #138 = Utf8               UNIT
  #139 = Utf8               Lscala/runtime/BoxedUnit;
  #140 = NameAndType        #138:#139     // UNIT:Lscala/runtime/BoxedUnit;
  #141 = Fieldref           #137.#140     // scala/runtime/BoxedUnit.UNIT:Lscala/runtime/BoxedUnit;
  #142 = Methodref          #4.#16        // java/lang/Object."<init>":()V
  #143 = Utf8               Code
  #144 = Utf8               LineNumberTable
  #145 = Utf8               LocalVariableTable
  #146 = Utf8               MethodParameters
  #147 = Utf8               StackMapTable
  #148 = Utf8               Signature
  #149 = Utf8               InnerClasses
  #150 = Utf8               SourceFile
  #151 = Utf8               ScalaInlineInfo
  #152 = Utf8               Scala
{
  public static final org.sireum.F64$Boxer$ MODULE$;
    descriptor: Lorg/sireum/F64$Boxer$;
    flags: (0x0019) ACC_PUBLIC, ACC_STATIC, ACC_FINAL

  public static {};
    descriptor: ()V
    flags: (0x0009) ACC_PUBLIC, ACC_STATIC
    Code:
      stack=2, locals=0, args_size=0
         0: new           #2                  // class org/sireum/F64$Boxer$
         3: dup
         4: invokespecial #17                 // Method "<init>":()V
         7: putstatic     #19                 // Field MODULE$:Lorg/sireum/F64$Boxer$;
        10: getstatic     #19                 // Field MODULE$:Lorg/sireum/F64$Boxer$;
        13: invokestatic  #23                 // InterfaceMethod org/sireum/$internal/Boxer.$init$:(Lorg/sireum/$internal/Boxer;)V
        16: return
      LineNumberTable:
        line 127: 0

  public org.sireum.Z size(java.lang.Object);
    descriptor: (Ljava/lang/Object;)Lorg/sireum/Z;
    flags: (0x0001) ACC_PUBLIC
    Code:
      stack=2, locals=2, args_size=2
         0: aload_0
         1: aload_1
         2: invokestatic  #30                 // InterfaceMethod org/sireum/$internal/Boxer.size$:(Lorg/sireum/$internal/Boxer;Ljava/lang/Object;)Lorg/sireum/Z;
         5: areturn
      LineNumberTable:
        line 127: 0
      LocalVariableTable:
        Start  Length  Slot  Name   Signature
            0       6     0  this   Lorg/sireum/F64$Boxer$;
            0       6     1     a   Ljava/lang/Object;
    MethodParameters:
      Name                           Flags
      a                              final

  public void copy(java.lang.Object, org.sireum.Z, java.lang.Object, org.sireum.Z, org.sireum.Z);
    descriptor: (Ljava/lang/Object;Lorg/sireum/Z;Ljava/lang/Object;Lorg/sireum/Z;Lorg/sireum/Z;)V
    flags: (0x0001) ACC_PUBLIC
    Code:
      stack=6, locals=6, args_size=6
         0: aload_0
         1: aload_1
         2: aload_2
         3: aload_3
         4: aload         4
         6: aload         5
         8: invokestatic  #43                 // InterfaceMethod org/sireum/$internal/Boxer.copy$:(Lorg/sireum/$internal/Boxer;Ljava/lang/Object;Lorg/sireum/Z;Ljava/lang/Object;Lorg/sireum/Z;Lorg/sireum/Z;)V
        11: return
      LineNumberTable:
        line 127: 0
      LocalVariableTable:
        Start  Length  Slot  Name   Signature
            0      12     0  this   Lorg/sireum/F64$Boxer$;
            0      12     1   src   Ljava/lang/Object;
            0      12     2 srcPos   Lorg/sireum/Z;
            0      12     3  dest   Ljava/lang/Object;
            0      12     4 destPos   Lorg/sireum/Z;
            0      12     5 length   Lorg/sireum/Z;
    MethodParameters:
      Name                           Flags
      src                            final
      srcPos                         final
      dest                           final
      destPos                        final
      length                         final

  public java.lang.Object clone(java.lang.Object, org.sireum.Z, org.sireum.Z, org.sireum.Z);
    descriptor: (Ljava/lang/Object;Lorg/sireum/Z;Lorg/sireum/Z;Lorg/sireum/Z;)Ljava/lang/Object;
    flags: (0x0001) ACC_PUBLIC
    Code:
      stack=5, locals=5, args_size=5
         0: aload_0
         1: aload_1
         2: aload_2
         3: aload_3
         4: aload         4
         6: invokestatic  #52                 // InterfaceMethod org/sireum/$internal/Boxer.clone$:(Lorg/sireum/$internal/Boxer;Ljava/lang/Object;Lorg/sireum/Z;Lorg/sireum/Z;Lorg/sireum/Z;)Ljava/lang/Object;
         9: areturn
      LineNumberTable:
        line 127: 0
      LocalVariableTable:
        Start  Length  Slot  Name   Signature
            0      10     0  this   Lorg/sireum/F64$Boxer$;
            0      10     1     a   Ljava/lang/Object;
            0      10     2 length   Lorg/sireum/Z;
            0      10     3 newLength   Lorg/sireum/Z;
            0      10     4 offset   Lorg/sireum/Z;
    MethodParameters:
      Name                           Flags
      a                              final
      length                         final
      newLength                      final
      offset                         final

  public java.lang.Object cloneMut(java.lang.Object, org.sireum.Z, org.sireum.Z, org.sireum.Z);
    descriptor: (Ljava/lang/Object;Lorg/sireum/Z;Lorg/sireum/Z;Lorg/sireum/Z;)Ljava/lang/Object;
    flags: (0x0001) ACC_PUBLIC
    Code:
      stack=5, locals=5, args_size=5
         0: aload_0
         1: aload_1
         2: aload_2
         3: aload_3
         4: aload         4
         6: invokestatic  #56                 // InterfaceMethod org/sireum/$internal/Boxer.cloneMut$:(Lorg/sireum/$internal/Boxer;Ljava/lang/Object;Lorg/sireum/Z;Lorg/sireum/Z;Lorg/sireum/Z;)Ljava/lang/Object;
         9: areturn
      LineNumberTable:
        line 127: 0
      LocalVariableTable:
        Start  Length  Slot  Name   Signature
            0      10     0  this   Lorg/sireum/F64$Boxer$;
            0      10     1     a   Ljava/lang/Object;
            0      10     2 length   Lorg/sireum/Z;
            0      10     3 newLength   Lorg/sireum/Z;
            0      10     4 offset   Lorg/sireum/Z;
    MethodParameters:
      Name                           Flags
      a                              final
      length                         final
      newLength                      final
      offset                         final

  public java.lang.String toString(java.lang.Object, org.sireum.Z);
    descriptor: (Ljava/lang/Object;Lorg/sireum/Z;)Ljava/lang/String;
    flags: (0x0001) ACC_PUBLIC
    Code:
      stack=3, locals=3, args_size=3
         0: aload_0
         1: aload_1
         2: aload_2
         3: invokestatic  #62                 // InterfaceMethod org/sireum/$internal/Boxer.toString$:(Lorg/sireum/$internal/Boxer;Ljava/lang/Object;Lorg/sireum/Z;)Ljava/lang/String;
         6: areturn
      LineNumberTable:
        line 127: 0
      LocalVariableTable:
        Start  Length  Slot  Name   Signature
            0       7     0  this   Lorg/sireum/F64$Boxer$;
            0       7     1     a   Ljava/lang/Object;
            0       7     2 length   Lorg/sireum/Z;
    MethodParameters:
      Name                           Flags
      a                              final
      length                         final

  public int toInt(org.sireum.Z);
    descriptor: (Lorg/sireum/Z;)I
    flags: (0x0001) ACC_PUBLIC
    Code:
      stack=2, locals=2, args_size=2
         0: aload_0
         1: aload_1
         2: invokestatic  #69                 // InterfaceMethod org/sireum/$internal/Boxer.toInt$:(Lorg/sireum/$internal/Boxer;Lorg/sireum/Z;)I
         5: ireturn
      LineNumberTable:
        line 127: 0
      LocalVariableTable:
        Start  Length  Slot  Name   Signature
            0       6     0  this   Lorg/sireum/F64$Boxer$;
            0       6     1     n   Lorg/sireum/Z;
    MethodParameters:
      Name                           Flags
      n                              final

  public long toLong(org.sireum.Z);
    descriptor: (Lorg/sireum/Z;)J
    flags: (0x0001) ACC_PUBLIC
    Code:
      stack=2, locals=2, args_size=2
         0: aload_0
         1: aload_1
         2: invokestatic  #75                 // InterfaceMethod org/sireum/$internal/Boxer.toLong$:(Lorg/sireum/$internal/Boxer;Lorg/sireum/Z;)J
         5: lreturn
      LineNumberTable:
        line 127: 0
      LocalVariableTable:
        Start  Length  Slot  Name   Signature
            0       6     0  this   Lorg/sireum/F64$Boxer$;
            0       6     1     n   Lorg/sireum/Z;
    MethodParameters:
      Name                           Flags
      n                              final

  public <T extends java.lang.Object> T box(java.lang.Object);
    descriptor: (Ljava/lang/Object;)Ljava/lang/Object;
    flags: (0x0001) ACC_PUBLIC
    Code:
      stack=5, locals=6, args_size=2
         0: aload_1
         1: astore_3
         2: aload_3
         3: instanceof    #81                 // class java/lang/Double
         6: ifeq          34
         9: aload_3
        10: invokestatic  #87                 // Method scala/runtime/BoxesRunTime.unboxToDouble:(Ljava/lang/Object;)D
        13: dstore        4
        15: new           #9                  // class org/sireum/F64
        18: dup
        19: getstatic     #92                 // Field org/sireum/F64$.MODULE$:Lorg/sireum/F64$;
        22: dload         4
        24: invokevirtual #96                 // Method org/sireum/F64$.apply:(D)D
        27: invokespecial #99                 // Method org/sireum/F64."<init>":(D)V
        30: astore_2
        31: goto          46
        34: goto          37
        37: new           #101                // class scala/MatchError
        40: dup
        41: aload_3
        42: invokespecial #104                // Method scala/MatchError."<init>":(Ljava/lang/Object;)V
        45: athrow
        46: aload_2
        47: areturn
      StackMapTable: number_of_entries = 3
        frame_type = 253 /* append */
          offset_delta = 34
          locals = [ top, class java/lang/Object ]
        frame_type = 2 /* same */
        frame_type = 255 /* full_frame */
          offset_delta = 8
          locals = [ class org/sireum/F64$Boxer$, class java/lang/Object, class org/sireum/F64, class java/lang/Object, double ]
          stack = []
      LineNumberTable:
        line 128: 0
        line 129: 2
        line 128: 37
      LocalVariableTable:
        Start  Length  Slot  Name   Signature
            0      48     0  this   Lorg/sireum/F64$Boxer$;
            0      48     1     o   Ljava/lang/Object;
    Signature: #78                          // <T:Ljava/lang/Object;>(Ljava/lang/Object;)TT;
    MethodParameters:
      Name                           Flags
      o                              final

  public double unbox(java.lang.Object);
    descriptor: (Ljava/lang/Object;)D
    flags: (0x0001) ACC_PUBLIC
    Code:
      stack=3, locals=7, args_size=2
         0: aload_1
         1: astore        4
         3: aload         4
         5: instanceof    #9                  // class org/sireum/F64
         8: ifeq          27
        11: aload         4
        13: checkcast     #9                  // class org/sireum/F64
        16: invokevirtual #109                // Method org/sireum/F64.value:()D
        19: dstore        5
        21: dload         5
        23: dstore_2
        24: goto          40
        27: goto          30
        30: new           #101                // class scala/MatchError
        33: dup
        34: aload         4
        36: invokespecial #104                // Method scala/MatchError."<init>":(Ljava/lang/Object;)V
        39: athrow
        40: dload_2
        41: dreturn
      StackMapTable: number_of_entries = 3
        frame_type = 254 /* append */
          offset_delta = 27
          locals = [ top, top, class java/lang/Object ]
        frame_type = 2 /* same */
        frame_type = 255 /* full_frame */
          offset_delta = 9
          locals = [ class org/sireum/F64$Boxer$, class java/lang/Object, double, class java/lang/Object, double ]
          stack = []
      LineNumberTable:
        line 132: 0
        line 133: 3
        line 132: 30
      LocalVariableTable:
        Start  Length  Slot  Name   Signature
            0      42     0  this   Lorg/sireum/F64$Boxer$;
            0      42     1     o   Ljava/lang/Object;
    MethodParameters:
      Name                           Flags
      o                              final

  public void copyMut(java.lang.Object, org.sireum.Z, java.lang.Object, org.sireum.Z, org.sireum.Z);
    descriptor: (Ljava/lang/Object;Lorg/sireum/Z;Ljava/lang/Object;Lorg/sireum/Z;Lorg/sireum/Z;)V
    flags: (0x0001) ACC_PUBLIC
    Code:
      stack=6, locals=6, args_size=6
         0: aload_0
         1: aload_1
         2: aload_2
         3: aload_3
         4: aload         4
         6: aload         5
         8: invokevirtual #112                // Method copy:(Ljava/lang/Object;Lorg/sireum/Z;Ljava/lang/Object;Lorg/sireum/Z;Lorg/sireum/Z;)V
        11: return
      LineNumberTable:
        line 137: 0
      LocalVariableTable:
        Start  Length  Slot  Name   Signature
            0      12     0  this   Lorg/sireum/F64$Boxer$;
            0      12     1   src   Ljava/lang/Object;
            0      12     2 srcPos   Lorg/sireum/Z;
            0      12     3  dest   Ljava/lang/Object;
            0      12     4 destPos   Lorg/sireum/Z;
            0      12     5 length   Lorg/sireum/Z;
    MethodParameters:
      Name                           Flags
      src                            final
      srcPos                         final
      dest                           final
      destPos                        final
      length                         final

  public java.lang.Object create(org.sireum.Z);
    descriptor: (Lorg/sireum/Z;)Ljava/lang/Object;
    flags: (0x0001) ACC_PUBLIC
    Code:
      stack=2, locals=2, args_size=2
         0: aload_0
         1: aload_1
         2: invokevirtual #116                // Method toInt:(Lorg/sireum/Z;)I
         5: newarray       double
         7: areturn
      LineNumberTable:
        line 139: 0
      LocalVariableTable:
        Start  Length  Slot  Name   Signature
            0       8     0  this   Lorg/sireum/F64$Boxer$;
            0       8     1 length   Lorg/sireum/Z;
    MethodParameters:
      Name                           Flags
      length                         final

  public <T extends java.lang.Object> T lookup(java.lang.Object, org.sireum.Z);
    descriptor: (Ljava/lang/Object;Lorg/sireum/Z;)Ljava/lang/Object;
    flags: (0x0001) ACC_PUBLIC
    Code:
      stack=4, locals=6, args_size=3
         0: aload_1
         1: astore        4
         3: aload         4
         5: instanceof    #122                // class "[D"
         8: ifeq          37
        11: aload         4
        13: checkcast     #122                // class "[D"
        16: astore        5
        18: aload_0
        19: aload         5
        21: aload_0
        22: aload_2
        23: invokevirtual #116                // Method toInt:(Lorg/sireum/Z;)I
        26: daload
        27: invokestatic  #126                // Method scala/runtime/BoxesRunTime.boxToDouble:(D)Ljava/lang/Double;
        30: invokevirtual #128                // Method box:(Ljava/lang/Object;)Ljava/lang/Object;
        33: astore_3
        34: goto          50
        37: goto          40
        40: new           #101                // class scala/MatchError
        43: dup
        44: aload         4
        46: invokespecial #104                // Method scala/MatchError."<init>":(Ljava/lang/Object;)V
        49: athrow
        50: aload_3
        51: areturn
      StackMapTable: number_of_entries = 3
        frame_type = 253 /* append */
          offset_delta = 37
          locals = [ top, class java/lang/Object ]
        frame_type = 2 /* same */
        frame_type = 255 /* full_frame */
          offset_delta = 9
          locals = [ class org/sireum/F64$Boxer$, class java/lang/Object, class org/sireum/Z, class java/lang/Object, class java/lang/Object, class "[D" ]
          stack = []
      LineNumberTable:
        line 141: 0
        line 142: 3
        line 141: 40
      LocalVariableTable:
        Start  Length  Slot  Name   Signature
            0      52     0  this   Lorg/sireum/F64$Boxer$;
            0      52     1     a   Ljava/lang/Object;
            0      52     2     i   Lorg/sireum/Z;
    Signature: #119                         // <T:Ljava/lang/Object;>(Ljava/lang/Object;Lorg/sireum/Z;)TT;
    MethodParameters:
      Name                           Flags
      a                              final
      i                              final

  public void store(java.lang.Object, org.sireum.Z, java.lang.Object);
    descriptor: (Ljava/lang/Object;Lorg/sireum/Z;Ljava/lang/Object;)V
    flags: (0x0001) ACC_PUBLIC
    Code:
      stack=4, locals=7, args_size=4
         0: aload_1
         1: astore        5
         3: aload         5
         5: instanceof    #122                // class "[D"
         8: ifeq          39
        11: aload         5
        13: checkcast     #122                // class "[D"
        16: astore        6
        18: aload         6
        20: aload_0
        21: aload_2
        22: invokevirtual #116                // Method toInt:(Lorg/sireum/Z;)I
        25: aload_0
        26: aload_3
        27: invokevirtual #135                // Method unbox:(Ljava/lang/Object;)D
        30: dastore
        31: getstatic     #141                // Field scala/runtime/BoxedUnit.UNIT:Lscala/runtime/BoxedUnit;
        34: astore        4
        36: goto          52
        39: goto          42
        42: new           #101                // class scala/MatchError
        45: dup
        46: aload         5
        48: invokespecial #104                // Method scala/MatchError."<init>":(Ljava/lang/Object;)V
        51: athrow
        52: return
      StackMapTable: number_of_entries = 3
        frame_type = 253 /* append */
          offset_delta = 39
          locals = [ top, class java/lang/Object ]
        frame_type = 2 /* same */
        frame_type = 255 /* full_frame */
          offset_delta = 9
          locals = [ class org/sireum/F64$Boxer$, class java/lang/Object, class org/sireum/Z, class java/lang/Object, class scala/runtime/BoxedUnit, class java/lang/Object, class "[D" ]
          stack = []
      LineNumberTable:
        line 145: 0
        line 146: 3
        line 145: 42
      LocalVariableTable:
        Start  Length  Slot  Name   Signature
            0      53     0  this   Lorg/sireum/F64$Boxer$;
            0      53     1     a   Ljava/lang/Object;
            0      53     2     i   Lorg/sireum/Z;
            0      53     3     v   Ljava/lang/Object;
    MethodParameters:
      Name                           Flags
      a                              final
      i                              final
      v                              final

  public java.lang.Object unbox(java.lang.Object);
    descriptor: (Ljava/lang/Object;)Ljava/lang/Object;
    flags: (0x1041) ACC_PUBLIC, ACC_BRIDGE, ACC_SYNTHETIC
    Code:
      stack=2, locals=2, args_size=2
         0: aload_0
         1: aload_1
         2: invokevirtual #135                // Method unbox:(Ljava/lang/Object;)D
         5: invokestatic  #126                // Method scala/runtime/BoxesRunTime.boxToDouble:(D)Ljava/lang/Double;
         8: areturn
      LineNumberTable:
        line 127: 0
      LocalVariableTable:
        Start  Length  Slot  Name   Signature
            0       9     0  this   Lorg/sireum/F64$Boxer$;
            0       9     1     o   Ljava/lang/Object;
    MethodParameters:
      Name                           Flags
      o                              final

  public org.sireum.F64$Boxer$();
    descriptor: ()V
    flags: (0x0001) ACC_PUBLIC
    Code:
      stack=1, locals=1, args_size=1
         0: aload_0
         1: invokespecial #142                // Method java/lang/Object."<init>":()V
         4: return
      LineNumberTable:
        line 127: 0
      LocalVariableTable:
        Start  Length  Slot  Name   Signature
            0       5     0  this   Lorg/sireum/F64$Boxer$;
}
InnerClasses:
  public static #10= #2 of #9;            // Boxer$=class org/sireum/F64$Boxer$ of class org/sireum/F64
SourceFile: "FloatingPoint.scala"
  ScalaInlineInfo: length = 0x4F (unknown attribute)
   01 01 00 0F 00 0F 00 0E 01 00 4C 00 4D 01 00 2D
   00 2E 01 00 35 00 2E 01 00 21 00 22 01 00 6E 00
   22 01 00 71 00 72 01 00 75 00 76 01 00 18 00 19
   01 00 83 00 84 01 00 3F 00 40 01 00 46 00 47 01
   00 39 00 3A 01 00 69 00 55 01 00 69 00 4D 01
  Scala: length = 0x0 (unknown attribute)

