Classfile /Users/mw/Projects/slang-braindump/.jar/jar11/assemble/slang-braindump/assemble/content/org/sireum/GitHub$Ext$.class
  Last modified May 29, 2022; size 1470 bytes
  SHA-256 checksum b38a1ccaafa7dac28937709be3b5a5836b379b104da86935c63a484bacd2a920
  Compiled from "GitHub.scala"
public class org.sireum.GitHub$Ext$
  minor version: 0
  major version: 52
  flags: (0x0021) ACC_PUBLIC, ACC_SUPER
  this_class: #2                          // org/sireum/GitHub$Ext$
  super_class: #4                         // java/lang/Object
  interfaces: 0, fields: 1, methods: 5, attributes: 4
Constant pool:
   #1 = Utf8               org/sireum/GitHub$Ext$
   #2 = Class              #1             // org/sireum/GitHub$Ext$
   #3 = Utf8               java/lang/Object
   #4 = Class              #3             // java/lang/Object
   #5 = Utf8               GitHub.scala
   #6 = Utf8               org/sireum/GitHub$Asset
   #7 = Class              #6             // org/sireum/GitHub$Asset
   #8 = Utf8               org/sireum/GitHub
   #9 = Class              #8             // org/sireum/GitHub
  #10 = Utf8               Asset
  #11 = Utf8               Ext$
  #12 = Utf8               org/sireum/GitHub$Release
  #13 = Class              #12            // org/sireum/GitHub$Release
  #14 = Utf8               Release
  #15 = Utf8               org/sireum/GitHub$Repository
  #16 = Class              #15            // org/sireum/GitHub$Repository
  #17 = Utf8               Repository
  #18 = Utf8               MODULE$
  #19 = Utf8               Lorg/sireum/GitHub$Ext$;
  #20 = Utf8               <clinit>
  #21 = Utf8               ()V
  #22 = Utf8               <init>
  #23 = NameAndType        #22:#21        // "<init>":()V
  #24 = Methodref          #2.#23         // org/sireum/GitHub$Ext$."<init>":()V
  #25 = NameAndType        #18:#19        // MODULE$:Lorg/sireum/GitHub$Ext$;
  #26 = Fieldref           #2.#25         // org/sireum/GitHub$Ext$.MODULE$:Lorg/sireum/GitHub$Ext$;
  #27 = Utf8               latestRelease
  #28 = Utf8               (Lorg/sireum/GitHub$Repository;)Lorg/sireum/GitHub$Release;
  #29 = Utf8               repo
  #30 = Utf8               org/sireum/GitHub_Ext$
  #31 = Class              #30            // org/sireum/GitHub_Ext$
  #32 = Utf8               Lorg/sireum/GitHub_Ext$;
  #33 = NameAndType        #18:#32        // MODULE$:Lorg/sireum/GitHub_Ext$;
  #34 = Fieldref           #31.#33        // org/sireum/GitHub_Ext$.MODULE$:Lorg/sireum/GitHub_Ext$;
  #35 = NameAndType        #27:#28        // latestRelease:(Lorg/sireum/GitHub$Repository;)Lorg/sireum/GitHub$Release;
  #36 = Methodref          #31.#35        // org/sireum/GitHub_Ext$.latestRelease:(Lorg/sireum/GitHub$Repository;)Lorg/sireum/GitHub$Release;
  #37 = Utf8               this
  #38 = Utf8               Lorg/sireum/GitHub$Repository;
  #39 = Utf8               releases
  #40 = Utf8               (Lorg/sireum/GitHub$Repository;)Lorg/sireum/Jen;
  #41 = Utf8               (Lorg/sireum/GitHub$Repository;)Lorg/sireum/Jen<Lorg/sireum/GitHub$Release;>;
  #42 = NameAndType        #39:#40        // releases:(Lorg/sireum/GitHub$Repository;)Lorg/sireum/Jen;
  #43 = Methodref          #31.#42        // org/sireum/GitHub_Ext$.releases:(Lorg/sireum/GitHub$Repository;)Lorg/sireum/Jen;
  #44 = Utf8               assets
  #45 = Utf8               (Lorg/sireum/GitHub$Release;)Lorg/sireum/Jen;
  #46 = Utf8               (Lorg/sireum/GitHub$Release;)Lorg/sireum/Jen<Lorg/sireum/GitHub$Asset;>;
  #47 = Utf8               release
  #48 = NameAndType        #44:#45        // assets:(Lorg/sireum/GitHub$Release;)Lorg/sireum/Jen;
  #49 = Methodref          #31.#48        // org/sireum/GitHub_Ext$.assets:(Lorg/sireum/GitHub$Release;)Lorg/sireum/Jen;
  #50 = Utf8               Lorg/sireum/GitHub$Release;
  #51 = Methodref          #4.#23         // java/lang/Object."<init>":()V
  #52 = Utf8               Code
  #53 = Utf8               LineNumberTable
  #54 = Utf8               LocalVariableTable
  #55 = Utf8               MethodParameters
  #56 = Utf8               Signature
  #57 = Utf8               InnerClasses
  #58 = Utf8               SourceFile
  #59 = Utf8               ScalaInlineInfo
  #60 = Utf8               Scala
{
  public static final org.sireum.GitHub$Ext$ MODULE$;
    descriptor: Lorg/sireum/GitHub$Ext$;
    flags: (0x0019) ACC_PUBLIC, ACC_STATIC, ACC_FINAL

  public static {};
    descriptor: ()V
    flags: (0x0009) ACC_PUBLIC, ACC_STATIC
    Code:
      stack=2, locals=0, args_size=0
         0: new           #2                  // class org/sireum/GitHub$Ext$
         3: dup
         4: invokespecial #24                 // Method "<init>":()V
         7: putstatic     #26                 // Field MODULE$:Lorg/sireum/GitHub$Ext$;
        10: return
      LineNumberTable:
        line 73: 0

  public org.sireum.GitHub$Release latestRelease(org.sireum.GitHub$Repository);
    descriptor: (Lorg/sireum/GitHub$Repository;)Lorg/sireum/GitHub$Release;
    flags: (0x0001) ACC_PUBLIC
    Code:
      stack=2, locals=2, args_size=2
         0: getstatic     #34                 // Field org/sireum/GitHub_Ext$.MODULE$:Lorg/sireum/GitHub_Ext$;
         3: aload_1
         4: invokevirtual #36                 // Method org/sireum/GitHub_Ext$.latestRelease:(Lorg/sireum/GitHub$Repository;)Lorg/sireum/GitHub$Release;
         7: areturn
      LineNumberTable:
        line 75: 0
      LocalVariableTable:
        Start  Length  Slot  Name   Signature
            0       8     0  this   Lorg/sireum/GitHub$Ext$;
            0       8     1  repo   Lorg/sireum/GitHub$Repository;
    MethodParameters:
      Name                           Flags
      repo                           final

  public org.sireum.Jen<org.sireum.GitHub$Release> releases(org.sireum.GitHub$Repository);
    descriptor: (Lorg/sireum/GitHub$Repository;)Lorg/sireum/Jen;
    flags: (0x0001) ACC_PUBLIC
    Code:
      stack=2, locals=2, args_size=2
         0: getstatic     #34                 // Field org/sireum/GitHub_Ext$.MODULE$:Lorg/sireum/GitHub_Ext$;
         3: aload_1
         4: invokevirtual #43                 // Method org/sireum/GitHub_Ext$.releases:(Lorg/sireum/GitHub$Repository;)Lorg/sireum/Jen;
         7: areturn
      LineNumberTable:
        line 77: 0
      LocalVariableTable:
        Start  Length  Slot  Name   Signature
            0       8     0  this   Lorg/sireum/GitHub$Ext$;
            0       8     1  repo   Lorg/sireum/GitHub$Repository;
    Signature: #41                          // (Lorg/sireum/GitHub$Repository;)Lorg/sireum/Jen<Lorg/sireum/GitHub$Release;>;
    MethodParameters:
      Name                           Flags
      repo                           final

  public org.sireum.Jen<org.sireum.GitHub$Asset> assets(org.sireum.GitHub$Release);
    descriptor: (Lorg/sireum/GitHub$Release;)Lorg/sireum/Jen;
    flags: (0x0001) ACC_PUBLIC
    Code:
      stack=2, locals=2, args_size=2
         0: getstatic     #34                 // Field org/sireum/GitHub_Ext$.MODULE$:Lorg/sireum/GitHub_Ext$;
         3: aload_1
         4: invokevirtual #49                 // Method org/sireum/GitHub_Ext$.assets:(Lorg/sireum/GitHub$Release;)Lorg/sireum/Jen;
         7: areturn
      LineNumberTable:
        line 79: 0
      LocalVariableTable:
        Start  Length  Slot  Name   Signature
            0       8     0  this   Lorg/sireum/GitHub$Ext$;
            0       8     1 release   Lorg/sireum/GitHub$Release;
    Signature: #46                          // (Lorg/sireum/GitHub$Release;)Lorg/sireum/Jen<Lorg/sireum/GitHub$Asset;>;
    MethodParameters:
      Name                           Flags
      release                        final

  public org.sireum.GitHub$Ext$();
    descriptor: ()V
    flags: (0x0001) ACC_PUBLIC
    Code:
      stack=1, locals=1, args_size=1
         0: aload_0
         1: invokespecial #51                 // Method java/lang/Object."<init>":()V
         4: return
      LineNumberTable:
        line 73: 0
      LocalVariableTable:
        Start  Length  Slot  Name   Signature
            0       5     0  this   Lorg/sireum/GitHub$Ext$;
}
InnerClasses:
  public static final #10= #7 of #9;      // Asset=class org/sireum/GitHub$Asset of class org/sireum/GitHub
  public static #11= #2 of #9;            // Ext$=class org/sireum/GitHub$Ext$ of class org/sireum/GitHub
  public static final #14= #13 of #9;     // Release=class org/sireum/GitHub$Release of class org/sireum/GitHub
  public static final #17= #16 of #9;     // Repository=class org/sireum/GitHub$Repository of class org/sireum/GitHub
SourceFile: "GitHub.scala"
  ScalaInlineInfo: length = 0x18 (unknown attribute)
   01 01 00 04 00 16 00 15 01 00 2C 00 2D 01 00 1B
   00 1C 01 00 27 00 28 01
  Scala: length = 0x0 (unknown attribute)

