Classfile /Users/mw/Projects/slang-braindump/.jar/jar11/assemble/slang-braindump/assemble/content/org/sireum/IS.class
  Last modified May 29, 2022; size 28632 bytes
  SHA-256 checksum 57393280e96bf1884b6a30fc2eb231a14dcd07d616023d71b6d829759c3cd303
  Compiled from "IS.scala"
public final class org.sireum.IS<I extends java.lang.Object, V extends java.lang.Object> extends java.lang.Object implements org.sireum.Immutable, org.sireum.$internal.ISMarker, java.lang.Iterable<V>
  minor version: 0
  major version: 52
  flags: (0x0031) ACC_PUBLIC, ACC_FINAL, ACC_SUPER
  this_class: #2                          // org/sireum/IS
  super_class: #5                         // java/lang/Object
  interfaces: 3, fields: 6, methods: 80, attributes: 7
Constant pool:
    #1 = Utf8               org/sireum/IS
    #2 = Class              #1            // org/sireum/IS
    #3 = Utf8               <I:Ljava/lang/Object;V:Ljava/lang/Object;>Ljava/lang/Object;Lorg/sireum/Immutable;Lorg/sireum/$internal/ISMarker;Ljava/lang/Iterable<TV;>;
    #4 = Utf8               java/lang/Object
    #5 = Class              #4            // java/lang/Object
    #6 = Utf8               org/sireum/Immutable
    #7 = Class              #6            // org/sireum/Immutable
    #8 = Utf8               org/sireum/$internal/ISMarker
    #9 = Class              #8            // org/sireum/$internal/ISMarker
   #10 = Utf8               java/lang/Iterable
   #11 = Class              #10           // java/lang/Iterable
   #12 = Utf8               IS.scala
   #13 = Utf8               Lscala/reflect/ScalaSignature;
   #14 = Utf8               bytes
   #15 = Utf8               \u0006\u0005\r=r!\u0002\u001d:\u0011\u0003qd!\u0002!:\u0011\u0003\t\u0005\"\u0002%\u0002\t\u0003Ie\u0001\u0002&\u0002\u0001-C\u0001\"T\u0002\u0003\u0002\u0003\u0006IA\u0014\u0005\u000b\u0003k\u001b!\u0011!Q\u0001\n\tm\u0004B\u0002%\u0004\t\u0003\u0011i\bC\u0004\u0002r\r!\tAa\"\t\u000f\u0005%5\u0001\"\u0001\u0003\u0016\"9\u0011qT\u0002\u0005\u0002\t\u0005\u0006bBAb\u0007\u0011\u0005!q\u0016\u0005\b\u0005k\u000bA\u0011\u0001B\\\u0011\u001d\u0011y!\u0001C\u0001\u0005\u000fDqAa8\u0002\t\u0003\u0011\t\u000fC\u0004\u0003\u0010\u0005!\tAa?\t\u000f\rM\u0011\u0001\"\u0001\u0004\u0016\u0019!\u0001)\u000f\u0002P\u0011!i\u0007C!b\u0001\n\u0003q\u0007\u0002C;\u0011\u0005\u0003\u0005\u000b\u0011B8\t\u0011Y\u0004\"Q1A\u0005\u0002]D\u0001\u0002\u001f\t\u0003\u0002\u0003\u0006IA\u0011\u0005\tsB\u0011)\u0019!C\u0001u\"Aa\u0010\u0005B\u0001B\u0003%1\u0010C\u0005\u0000!\t\u0015\r\u0011\"\u0001\u0002\u0002!Q\u0011\u0011\u0002\t\u0003\u0002\u0003\u0006I!a\u0001\t\r!\u0003B\u0011AA\u0006\u0011\u0019\t9\u0002\u0005C\u0001u\"9\u0011\u0011\u0004\t\u0005\u0002\u0005m\u0001bBA\u0012!\u0011\u0005\u00111\u0004\u0005\b\u0003K\u0001B\u0011AA\u0014\u0011\u001d\ti\u0003\u0005C\u0001\u0003_Aq!!\u000e\u0011\t\u0003\t9\u0004C\u0004\u0002<A!\t!!\u0010\t\u000f\u00055\u0003\u0003\"\u0001\u0002P!9\u00111\f\t\u0005\u0002\u0005u\u0003bBA1!\u0011\u0005\u00111\r\u0005\b\u0003O\u0002B\u0011AA5\u0011\u001d\t\t\b\u0005C\u0001\u0003gBq!!#\u0011\t\u0003\tY\tC\u0004\u0002 B!\t!!)\t\u000f\u0005=\u0006\u0003\"\u0001\u00022\"9\u00111\u0019\t\u0005\u0002\u0005\u0015\u0007bBAh!\u0011\u0005\u0011\u0011\u001b\u0005\u0007\u0003?\u0004B\u0011\u0001>\t\u000f\u0005\u0005\b\u0003\"\u0001\u0002d\"9\u0011Q\u001d\t\u0005\u0002\u0005\r\bbBAt!\u0011\u0005\u0011\u0011\u001e\u0005\b\u0003c\u0004B\u0011AAz\u0011\u001d\u0011)\u0001\u0005C\u0001\u0005\u000fAqAa\u0004\u0011\t\u0003\u0011\t\u0002C\u0004\u0003\u0010A!\tAa\u0006\t\u000f\t%\u0002\u0003\"\u0001\u0003,!Q!1\t\t\t\u0006\u0004%\tE!\u0012\t\u000f\t5\u0003\u0003\"\u0011\u0003P!9!\u0011\f\t\u0005\u0002\tm\u0003b\u0002B2!\u0011\u0005#QM\u0001\u0003\u0013NS!AO\u001e\u0002\rML\'/Z;n\u0015\u0005a\u0014aA8sO\u000e\u0001\u0001CA \u0002\u001b\u0005I$AA%T\'\t\t!\t\u0005\u0002D\r6\tAIC\u0001F\u0003\u0015\u00198-\u00197b\u0013\t9EI\u0001\u0004B]f\u0014VMZ\u0001\u0007y%t\u0017\u000e\u001e \u0015\u0003y\u0012!bV5uQ\u001aKG\u000e^3s+\u0015a%Q\u000fB=\'\t\u0019!)\u0001\u0002jgB1q\b\u0005B:\u0005o*2\u0001U:e\'\u0015\u0001\")\u0015+[!\ty$+\u0003\u0002Ts\tI\u0011*\\7vi\u0006\u0014G.\u001a\t\u0003+bk\u0011A\u0016\u0006\u0003/f\n\u0011\u0002J5oi\u0016\u0014h.\u00197\n\u0005e3&\u0001C%T\u001b\u0006\u00148.\u001a:\u0011\u0007m\u0003\'-D\u0001]\u0015\tif,\u0001\u0003mC:<\'\"A0\u0002\t)\fg/Y\u0005\u0003Cr\u0013\u0001\"\u0013;fe\u0006\u0014G.\u001a\t\u0003G\u0012d\u0001\u0001B\u0003f!\t\u0007aMA\u0001W#\t9\'\u000e\u0005\u0002DQ&\u0011\u0011\u000e\u0012\u0002\b\u001d>$\b.\u001b8h!\t\u00195.\u0003\u0002m\t\n\u0019\u0011I\\=\u0002\u0013\r|W\u000e]1oS>tW#A8\u0011\u0007}\u0002(/\u0003\u0002rs\tYAEW\"p[B\fg.[8o!\t\u00197\u000fB\u0003u!\t\u0007aMA\u0001J\u0003)\u0019w.\u001c9b]&|g\u000eI\u0001\u0005I\u0006$\u0018-F\u0001C\u0003\u0015!\u0017\r^1!\u0003\u0019aWM\\4uQV\t1\u0010\u0005\u0002@y&\u0011Q0\u000f\u0002\u00025\u00069A.\u001a8hi\"\u0004\u0013!\u00022pq\u0016\u0014XCAA\u0002!\r)\u0016QA\u0005\u0004\u0003\u000f1&!\u0002\"pq\u0016\u0014\u0018A\u00022pq\u0016\u0014\b\u0005\u0006\u0006\u0002\u000e\u0005=\u0011\u0011CA\n\u0003+\u0001Ba\u0010\tsE\")Q.\u0007a\u0001_\")a/\u0007a\u0001\u0005\")\u00110\u0007a\u0001w\"1q0\u0007a\u0001\u0003\u0007\tA\u0001[1tQ\u00069\u0011n]#naRLXCAA\u000f!\ry\u0014qD\u0005\u0004\u0003CI$!\u0001\"\u0002\u00119|g.R7qif\f\u0011\"[:J]\n{WO\u001c3\u0015\t\u0005u\u0011\u0011\u0006\u0005\u0007\u0003Wi\u0002\u0019\u0001:\u0002\u0003%\f1\u0002J2pY>tG\u0005\u001d7vgR!\u0011QBA\u0019\u0011\u0019\t\u0019D\ba\u0001E\u0006\tQ-A\u0006%a2,8\u000fJ2pY>tG\u0003BA\u0007\u0003sAa!a\r \u0001\u0004\u0011\u0017A\u0003\u0013qYV\u001cH\u0005\u001d7vgV!\u0011qHA%)\u0011\ti!!\u0011\t\u000f\u0005\r\u0003\u00051\u0001\u0002F\u0005)q\u000e\u001e5feB)q\bEA$EB\u00191-!\u0013\u0005\r\u0005-\u0003E1\u0001g\u0005\tI%\'\u0001\u0007%[&tWo\u001d\u0013nS:,8/\u0006\u0003\u0002R\u0005eC\u0003BA\u0007\u0003\'Bq!a\u0011\"\u0001\u0004\t)\u0006E\u0003@!\u0005]#\rE\u0002d\u00033\"a!a\u0013\"\u0005\u00041\u0017A\u0002\u0013nS:,8\u000f\u0006\u0003\u0002\u000e\u0005}\u0003BBA\u001aE\u0001\u0007!-A\u0002bij#2AYA3\u0011\u0019\tYc\ta\u0001w\u00069\u0011N\u001c3jG\u0016\u001cXCAA6!\u0011y\u0014Q\u000e:\n\u0007\u0005=\u0014H\u0001\u0004[%\u0006tw-Z\u0001\u0004[\u0006\u0004X\u0003BA;\u0003w\"B!a\u001e\u0002\u0000A)q\b\u0005:\u0002zA\u00191-a\u001f\u0005\r\u0005uTE1\u0001g\u0005\t1&\u0007C\u0004\u0002\u0002\u0016\u0002\r!a!\u0002\u0003\u0019\u0004baQACE\u0006e\u0014bAAD\t\nIa)\u001e8di&|g.M\u0001\bM>\u0014X-Y2i+\u0011\ti)a\'\u0015\t\u0005=\u0015Q\u0013\t\u0004\u0007\u0006E\u0015bAAJ\t\n!QK\\5u\u0011\u001d\t\tI\na\u0001\u0003/\u0003baQACE\u0006e\u0005cA2\u0002\u001c\u00121\u0011Q\u0014\u0014C\u0002\u0019\u0014\u0011!V\u0001\bM2\fG/T1q+\u0011\t\u0019+!+\u0015\t\u0005\u0015\u00161\u0016\t\u0006\u007fA\u0011\u0018q\u0015\t\u0004G\u0006%FABA?O\t\u0007a\rC\u0004\u0002\u0002\u001e\u0002\r!!,\u0011\r\r\u000b)IYAS\u0003\u00191\u0017\u000e\u001c;feR!\u0011QBAZ\u0011\u001d\t)\f\u000ba\u0001\u0003o\u000b\u0011\u0001\u001d\t\u0007\u0007\u0006\u0015%-!/+\t\u0005u\u00111X\u0016\u0003\u0003{\u00032aPA`\u0013\r\t\t-\u000f\u0002\u0005aV\u0014X-\u0001\u0006xSRDg)\u001b7uKJ$B!a2\u0002LB)\u0011\u0011Z\u0002sE:\u0011q\b\u0001\u0005\b\u0003kK\u0003\u0019AAg!\u0019\u0019\u0015Q\u00112\u0002\u001e\u0005A\u0011\u000e^3sCR|\'\u000f\u0006\u0002\u0002TB)\u0011Q[AnE6\u0011\u0011q\u001b\u0006\u0004\u00033t\u0016\u0001B;uS2LA!!8\u0002X\nA\u0011\n^3sCR|\'/\u0001\u0003tSj,\u0017A\u00034jeN$\u0018J\u001c3fqV\t!/A\u0005mCN$\u0018J\u001c3fq\u0006!Ao\\\'T+\t\tY\u000fE\u0003@\u0003[\u0014(-C\u0002\u0002pf\u0012!!T*\u0002\u000bQ|\u0017j\u0015.\u0016\u0005\u0005U\b#BA|\u0003{\u0014gbA \u0002z&\u0019\u00111`\u001d\u0002\u000fA\f7m[1hK&!\u0011q B\u0001\u0005\rI5KW\u0005\u0004\u0005\u00071&\u0001\u0004)bG.\fw-\u001a+sC&$\u0018!\u0002;p\u001bNSVC\u0001B\u0005!\u0015\t9Pa\u0003c\u0013\u0011\u0011iA!\u0001\u0003\u00075\u001b&,A\u0003baBd\u0017\u0010F\u0002c\u0005\'AaA!\u00062\u0001\u0004\u0011\u0018!B5oI\u0016DH\u0003BA\u0007\u00053AqAa\u00073\u0001\u0004\u0011i\"\u0001\u0003be\u001e\u001c\b#B\"\u0003 \t\r\u0012b\u0001B\u0011\t\nQAH]3qK\u0006$X\r\u001a \u0011\u000b\r\u0013)C\u001d2\n\u0007\t\u001dBI\u0001\u0004UkBdWMM\u0001\tK2,W.\u001a8ugV\u0011!Q\u0006\t\u0006\u0005_\u0011iD\u0019\b\u0005\u0005c\u0011YD\u0004\u0003\u00034\teRB\u0001B\u001b\u0015\r\u00119$P\u0001\u0007yI|w\u000e\u001e \n\u0003\u0015K1!a?E\u0013\u0011\u0011yD!\u0011\u0003\u0007M+\u0017OC\u0002\u0002|\u0012\u000b\u0001\u0002[1tQ\u000e{G-Z\u000b\u0003\u0005\u000f\u00022a\u0011B%\u0013\r\u0011Y\u0005\u0012\u0002\u0004\u0013:$\u0018AB3rk\u0006d7\u000f\u0006\u0003\u0003R\t]\u0003cA\"\u0003T%\u0019!Q\u000b#\u0003\u000f\t{w\u000e\\3b]\"1\u00111I\u001bA\u0002)\faa\u001d;sS:<WC\u0001B/!\ry$qL\u0005\u0004\u0005CJ$AB*ue&tw-\u0001\u0005u_N#(/\u001b8h)\t\u00119\u0007\u0005\u0003\u0003j\t=dbA\"\u0003l%\u0019!Q\u000e#\u0002\rA\u0013X\rZ3g\u0013\u0011\u0011\tG!\u001d\u000b\u0007\t5D\tE\u0002d\u0005k\"Q\u0001^\u0002C\u0002\u0019\u00042a\u0019B=\t\u0015)7A1\u0001g!\u001d\u0019\u0015Q\u0011B<\u0003;!bAa \u0003\u0004\n\u0015\u0005c\u0002BA\u0007\tM$qO\u0007\u0002\u0003!)QJ\u0002a\u0001\u001d\"9\u0011Q\u0017\u0004A\u0002\tmT\u0003\u0002BE\u0005\u001f#BAa#\u0003\u0012B1q\b\u0005B:\u0005\u001b\u00032a\u0019BH\t\u0019\tih\u0002b\u0001M\"9\u0011\u0011Q\u0004A\u0002\tM\u0005cB\"\u0002\u0006\n]$QR\u000b\u0005\u0005/\u0013y\n\u0006\u0003\u0002\u0010\ne\u0005bBAA\u0011\u0001\u0007!1\u0014\t\b\u0007\u0006\u0015%q\u000fBO!\r\u0019\'q\u0014\u0003\u0007\u0003;C!\u0019\u00014\u0016\t\t\r&\u0011\u0016\u000b\u0005\u0005K\u0013Y\u000b\u0005\u0004@!\tM$q\u0015\t\u0004G\n%FABA?\u0013\t\u0007a\rC\u0004\u0002\u0002&\u0001\rA!,\u0011\u000f\r\u000b)Ia\u001e\u0003&R!!q\u0010BY\u0011\u001d\u0011\u0019L\u0003a\u0001\u0005w\n!\u0001\u001d\u001a\u0002\u0013\rDWmY6TSj,W\u0003\u0002B]\u0005\u0007$BAa/\u0003FR!\u0011q\u0012B_\u0011\u0019i7\u0002q\u0001\u0003@B!q\b\u001dBa!\r\u0019\'1\u0019\u0003\u0006i.\u0011\rA\u001a\u0005\u0007\u0003?\\\u0001\u0019A>\u0016\r\t%\'\u0011\u001bBk)\u0011\u0011YMa7\u0015\t\t5\'q\u001b\t\u0007\u007fA\u0011yMa5\u0011\u0007\r\u0014\t\u000eB\u0003u\u0019\t\u0007a\rE\u0002d\u0005+$Q!\u001a\u0007C\u0002\u0019Da!\u001c\u0007A\u0004\te\u0007\u0003B q\u0005\u001fDqAa\u0007\r\u0001\u0004\u0011i\u000eE\u0003D\u0005?\u0011\u0019.\u0001\u0004de\u0016\fG/Z\u000b\u0007\u0005G\u0014YOa<\u0015\r\t\u0015(Q\u001fB|)\u0011\u00119O!=\u0011\r}\u0002\"\u0011\u001eBw!\r\u0019\'1\u001e\u0003\u0006i6\u0011\rA\u001a\t\u0004G\n=H!B3\u000e\u0005\u00041\u0007BB7\u000e\u0001\b\u0011\u0019\u0010\u0005\u0003@a\n%\bBBAp\u001b\u0001\u00071\u0010C\u0004\u0003z6\u0001\rA!<\u0002\u000f\u0011,g-Y;miV1!Q`B\u0002\u0007\u000f!\"Ba@\u0004\n\r51qBB\t!\u0019y\u0004c!\u0001\u0004\u0006A\u00191ma\u0001\u0005\u000bQt!\u0019\u00014\u0011\u0007\r\u001c9\u0001B\u0003f\u001d\t\u0007a\r\u0003\u0004n\u001d\u0001\u000711\u0002\t\u0005\u007fA\u001c\t\u0001C\u0003w\u001d\u0001\u0007!\tC\u0003z\u001d\u0001\u00071\u0010\u0003\u0004\u0000\u001d\u0001\u0007\u00111A\u0001\u000bk:\f\u0007\u000f\u001d7z\'\u0016\fXCBB\f\u0007[\u0019\u0019\u0003\u0006\u0003\u0004\u001a\r\u0015\u0002#B\"\u0004\u001c\r}\u0011bAB\u000f\t\n1q\n\u001d;j_:\u0004bAa\f\u0003>\r\u0005\u0002cA2\u0004$\u0011)Qm\u0004b\u0001M\"91qE\bA\u0002\r%\u0012!A8\u0011\r}\u000221FB\u0011!\r\u00197Q\u0006\u0003\u0006i>\u0011\rA\u001a
   #16 = Utf8               java/lang/invoke/MethodHandles$Lookup
   #17 = Class              #16           // java/lang/invoke/MethodHandles$Lookup
   #18 = Utf8               java/lang/invoke/MethodHandles
   #19 = Class              #18           // java/lang/invoke/MethodHandles
   #20 = Utf8               Lookup
   #21 = Utf8               org/sireum/$internal/PackageTrait$ISZ$
   #22 = Class              #21           // org/sireum/$internal/PackageTrait$ISZ$
   #23 = Utf8               org/sireum/$internal/PackageTrait
   #24 = Class              #23           // org/sireum/$internal/PackageTrait
   #25 = Utf8               ISZ$
   #26 = Utf8               org/sireum/$internal/PackageTrait$MSZ$
   #27 = Class              #26           // org/sireum/$internal/PackageTrait$MSZ$
   #28 = Utf8               MSZ$
   #29 = Utf8               org/sireum/IS$$anon$1
   #30 = Class              #29           // org/sireum/IS$$anon$1
   #31 = Utf8               org/sireum/IS$$anon$2
   #32 = Class              #31           // org/sireum/IS$$anon$2
   #33 = Utf8               org/sireum/IS$WithFilter
   #34 = Class              #33           // org/sireum/IS$WithFilter
   #35 = Utf8               WithFilter
   #36 = Utf8               org/sireum/Z$MP$
   #37 = Class              #36           // org/sireum/Z$MP$
   #38 = Utf8               org/sireum/Z
   #39 = Class              #38           // org/sireum/Z
   #40 = Utf8               MP$
   #41 = Utf8               org/sireum/ZRange$CondIncDec
   #42 = Class              #41           // org/sireum/ZRange$CondIncDec
   #43 = Utf8               org/sireum/ZRange
   #44 = Class              #43           // org/sireum/ZRange
   #45 = Utf8               CondIncDec
   #46 = Utf8               org/sireum/package$$Int2Z$
   #47 = Class              #46           // org/sireum/package$$Int2Z$
   #48 = Utf8               org/sireum/package
   #49 = Class              #48           // org/sireum/package
   #50 = Utf8               $Int2Z$
   #51 = Utf8               hashCode
   #52 = Utf8               I
   #53 = Utf8               companion
   #54 = Utf8               Lorg/sireum/$ZCompanion;
   #55 = Utf8               Lorg/sireum/$ZCompanion<TI;>;
   #56 = Utf8               data
   #57 = Utf8               Ljava/lang/Object;
   #58 = Utf8               length
   #59 = Utf8               Lorg/sireum/Z;
   #60 = Utf8               boxer
   #61 = Utf8               Lorg/sireum/$internal/Boxer;
   #62 = Utf8               bitmap$0
   #63 = Utf8               Z
   #64 = Utf8               unapplySeq
   #65 = Utf8               (Lorg/sireum/IS;)Lscala/Option;
   #66 = Utf8               <I:Ljava/lang/Object;V:Ljava/lang/Object;>(Lorg/sireum/IS<TI;TV;>;)Lscala/Option<Lscala/collection/immutable/Seq<TV;>;>;
   #67 = Utf8               o
   #68 = Utf8               org/sireum/IS$
   #69 = Class              #68           // org/sireum/IS$
   #70 = Utf8               MODULE$
   #71 = Utf8               Lorg/sireum/IS$;
   #72 = NameAndType        #70:#71       // MODULE$:Lorg/sireum/IS$;
   #73 = Fieldref           #69.#72       // org/sireum/IS$.MODULE$:Lorg/sireum/IS$;
   #74 = NameAndType        #64:#65       // unapplySeq:(Lorg/sireum/IS;)Lscala/Option;
   #75 = Methodref          #69.#74       // org/sireum/IS$.unapplySeq:(Lorg/sireum/IS;)Lscala/Option;
   #76 = Utf8               Lorg/sireum/IS;
   #77 = Utf8               create
   #78 = Utf8               (Lorg/sireum/Z;Ljava/lang/Object;Lorg/sireum/$ZCompanion;)Lorg/sireum/IS;
   #79 = Utf8               <I:Ljava/lang/Object;V:Ljava/lang/Object;>(Lorg/sireum/Z;TV;Lorg/sireum/$ZCompanion<TI;>;)Lorg/sireum/IS<TI;TV;>;
   #80 = Utf8               size
   #81 = Utf8               default
   #82 = NameAndType        #77:#78       // create:(Lorg/sireum/Z;Ljava/lang/Object;Lorg/sireum/$ZCompanion;)Lorg/sireum/IS;
   #83 = Methodref          #69.#82       // org/sireum/IS$.create:(Lorg/sireum/Z;Ljava/lang/Object;Lorg/sireum/$ZCompanion;)Lorg/sireum/IS;
   #84 = Utf8               checkSize
   #85 = Utf8               (Lorg/sireum/Z;Lorg/sireum/$ZCompanion;)V
   #86 = Utf8               <I:Ljava/lang/Object;>(Lorg/sireum/Z;Lorg/sireum/$ZCompanion<TI;>;)V
   #87 = NameAndType        #84:#85       // checkSize:(Lorg/sireum/Z;Lorg/sireum/$ZCompanion;)V
   #88 = Methodref          #69.#87       // org/sireum/IS$.checkSize:(Lorg/sireum/Z;Lorg/sireum/$ZCompanion;)V
   #89 = Utf8               forEach
   #90 = Utf8               (Ljava/util/function/Consumer;)V
   #91 = Utf8               (Ljava/util/function/Consumer<-TV;>;)V
   #92 = Utf8               x$1
   #93 = NameAndType        #89:#90       // forEach:(Ljava/util/function/Consumer;)V
   #94 = InterfaceMethodref #11.#93       // java/lang/Iterable.forEach:(Ljava/util/function/Consumer;)V
   #95 = Utf8               this
   #96 = Utf8               Ljava/util/function/Consumer;
   #97 = Utf8               spliterator
   #98 = Utf8               ()Ljava/util/Spliterator;
   #99 = Utf8               ()Ljava/util/Spliterator<TV;>;
  #100 = NameAndType        #97:#98       // spliterator:()Ljava/util/Spliterator;
  #101 = InterfaceMethodref #11.#100      // java/lang/Iterable.spliterator:()Ljava/util/Spliterator;
  #102 = Utf8               $cannotMixImmutableAndMutable
  #103 = Utf8               ()Lscala/runtime/Nothing$;
  #104 = Utf8               $cannotMixImmutableAndMutable$
  #105 = Utf8               (Lorg/sireum/Immutable;)Lscala/runtime/Nothing$;
  #106 = NameAndType        #104:#105     // $cannotMixImmutableAndMutable$:(Lorg/sireum/Immutable;)Lscala/runtime/Nothing$;
  #107 = InterfaceMethodref #7.#106       // org/sireum/Immutable.$cannotMixImmutableAndMutable$:(Lorg/sireum/Immutable;)Lscala/runtime/Nothing$;
  #108 = Utf8               $hasEquals
  #109 = Utf8               ()Z
  #110 = Utf8               $hasEquals$
  #111 = Utf8               (Lorg/sireum/Immutable;)Z
  #112 = NameAndType        #110:#111     // $hasEquals$:(Lorg/sireum/Immutable;)Z
  #113 = InterfaceMethodref #7.#112       // org/sireum/Immutable.$hasEquals$:(Lorg/sireum/Immutable;)Z
  #114 = Utf8               $hasString
  #115 = Utf8               $hasString$
  #116 = NameAndType        #115:#111     // $hasString$:(Lorg/sireum/Immutable;)Z
  #117 = InterfaceMethodref #7.#116       // org/sireum/Immutable.$hasString$:(Lorg/sireum/Immutable;)Z
  #118 = Utf8               $clone
  #119 = Utf8               ()Lorg/sireum/$internal/ImmutableMarker;
  #120 = Utf8               org/sireum/$internal/ImmutableMarker
  #121 = Class              #120          // org/sireum/$internal/ImmutableMarker
  #122 = Utf8               $clone$
  #123 = Utf8               (Lorg/sireum/$internal/ImmutableMarker;)Lorg/sireum/$internal/ImmutableMarker;
  #124 = NameAndType        #122:#123     // $clone$:(Lorg/sireum/$internal/ImmutableMarker;)Lorg/sireum/$internal/ImmutableMarker;
  #125 = InterfaceMethodref #121.#124     // org/sireum/$internal/ImmutableMarker.$clone$:(Lorg/sireum/$internal/ImmutableMarker;)Lorg/sireum/$internal/ImmutableMarker;
  #126 = Utf8               ()Lorg/sireum/$ZCompanion;
  #127 = Utf8               ()Lorg/sireum/$ZCompanion<TI;>;
  #128 = NameAndType        #53:#54       // companion:Lorg/sireum/$ZCompanion;
  #129 = Fieldref           #2.#128       // org/sireum/IS.companion:Lorg/sireum/$ZCompanion;
  #130 = Utf8               ()Ljava/lang/Object;
  #131 = NameAndType        #56:#57       // data:Ljava/lang/Object;
  #132 = Fieldref           #2.#131       // org/sireum/IS.data:Ljava/lang/Object;
  #133 = Utf8               ()Lorg/sireum/Z;
  #134 = NameAndType        #58:#59       // length:Lorg/sireum/Z;
  #135 = Fieldref           #2.#134       // org/sireum/IS.length:Lorg/sireum/Z;
  #136 = Utf8               ()Lorg/sireum/$internal/Boxer;
  #137 = NameAndType        #60:#61       // boxer:Lorg/sireum/$internal/Boxer;
  #138 = Fieldref           #2.#137       // org/sireum/IS.boxer:Lorg/sireum/$internal/Boxer;
  #139 = Utf8               hash
  #140 = Utf8               org/sireum/Z$
  #141 = Class              #140          // org/sireum/Z$
  #142 = Utf8               Lorg/sireum/Z$;
  #143 = NameAndType        #70:#142      // MODULE$:Lorg/sireum/Z$;
  #144 = Fieldref           #141.#143     // org/sireum/Z$.MODULE$:Lorg/sireum/Z$;
  #145 = Utf8               ()I
  #146 = NameAndType        #51:#145      // hashCode:()I
  #147 = Methodref          #2.#146       // org/sireum/IS.hashCode:()I
  #148 = Utf8               apply
  #149 = Utf8               (I)Lorg/sireum/Z;
  #150 = NameAndType        #148:#149     // apply:(I)Lorg/sireum/Z;
  #151 = Methodref          #141.#150     // org/sireum/Z$.apply:(I)Lorg/sireum/Z;
  #152 = Utf8               isEmpty
  #153 = Utf8               org/sireum/B$
  #154 = Class              #153          // org/sireum/B$
  #155 = Utf8               Lorg/sireum/B$;
  #156 = NameAndType        #70:#155      // MODULE$:Lorg/sireum/B$;
  #157 = Fieldref           #154.#156     // org/sireum/B$.MODULE$:Lorg/sireum/B$;
  #158 = NameAndType        #58:#133      // length:()Lorg/sireum/Z;
  #159 = Methodref          #2.#158       // org/sireum/IS.length:()Lorg/sireum/Z;
  #160 = Utf8               Lorg/sireum/Z$MP$;
  #161 = NameAndType        #70:#160      // MODULE$:Lorg/sireum/Z$MP$;
  #162 = Fieldref           #37.#161      // org/sireum/Z$MP$.MODULE$:Lorg/sireum/Z$MP$;
  #163 = Utf8               zero
  #164 = NameAndType        #163:#133     // zero:()Lorg/sireum/Z;
  #165 = Methodref          #37.#164      // org/sireum/Z$MP$.zero:()Lorg/sireum/Z;
  #166 = Utf8               equals
  #167 = Utf8               (Ljava/lang/Object;)Z
  #168 = NameAndType        #166:#167     // equals:(Ljava/lang/Object;)Z
  #169 = Methodref          #5.#168       // java/lang/Object.equals:(Ljava/lang/Object;)Z
  #170 = Utf8               (Z)Z
  #171 = NameAndType        #148:#170     // apply:(Z)Z
  #172 = Methodref          #154.#171     // org/sireum/B$.apply:(Z)Z
  #173 = Utf8               nonEmpty
  #174 = Utf8               isInBound
  #175 = Utf8               (TI;)Z
  #176 = Utf8               i
  #177 = Utf8               org/sireum/ZLike
  #178 = Class              #177          // org/sireum/ZLike
  #179 = Utf8               toMP
  #180 = NameAndType        #179:#133     // toMP:()Lorg/sireum/Z;
  #181 = InterfaceMethodref #178.#180     // org/sireum/ZLike.toMP:()Lorg/sireum/Z;
  #182 = Utf8               Lorg/sireum/package$$Int2Z$;
  #183 = NameAndType        #70:#182      // MODULE$:Lorg/sireum/package$$Int2Z$;
  #184 = Fieldref           #47.#183      // org/sireum/package$$Int2Z$.MODULE$:Lorg/sireum/package$$Int2Z$;
  #185 = Utf8               org/sireum/package$
  #186 = Class              #185          // org/sireum/package$
  #187 = Utf8               Lorg/sireum/package$;
  #188 = NameAndType        #70:#187      // MODULE$:Lorg/sireum/package$;
  #189 = Fieldref           #186.#188     // org/sireum/package$.MODULE$:Lorg/sireum/package$;
  #190 = Utf8               $Int2Z
  #191 = Utf8               (I)I
  #192 = NameAndType        #190:#191     // $Int2Z:(I)I
  #193 = Methodref          #186.#192     // org/sireum/package$.$Int2Z:(I)I
  #194 = Utf8               $less$eq$extension
  #195 = Utf8               (ILorg/sireum/Z;)Z
  #196 = NameAndType        #194:#195     // $less$eq$extension:(ILorg/sireum/Z;)Z
  #197 = Methodref          #47.#196      // org/sireum/package$$Int2Z$.$less$eq$extension:(ILorg/sireum/Z;)Z
  #198 = MethodType         #130          //  ()Ljava/lang/Object;
  #199 = Utf8               $anonfun$isInBound$1$adapted
  #200 = Utf8               (Lorg/sireum/IS;Lorg/sireum/Z;)Ljava/lang/Object;
  #201 = NameAndType        #199:#200     // $anonfun$isInBound$1$adapted:(Lorg/sireum/IS;Lorg/sireum/Z;)Ljava/lang/Object;
  #202 = Methodref          #2.#201       // org/sireum/IS.$anonfun$isInBound$1$adapted:(Lorg/sireum/IS;Lorg/sireum/Z;)Ljava/lang/Object;
  #203 = MethodHandle       6:#202        // REF_invokeStatic org/sireum/IS.$anonfun$isInBound$1$adapted:(Lorg/sireum/IS;Lorg/sireum/Z;)Ljava/lang/Object;
  #204 = Integer            1
  #205 = Utf8               java/lang/invoke/LambdaMetafactory
  #206 = Class              #205          // java/lang/invoke/LambdaMetafactory
  #207 = Utf8               altMetafactory
  #208 = Utf8               (Ljava/lang/invoke/MethodHandles$Lookup;Ljava/lang/String;Ljava/lang/invoke/MethodType;[Ljava/lang/Object;)Ljava/lang/invoke/CallSite;
  #209 = NameAndType        #207:#208     // altMetafactory:(Ljava/lang/invoke/MethodHandles$Lookup;Ljava/lang/String;Ljava/lang/invoke/MethodType;[Ljava/lang/Object;)Ljava/lang/invoke/CallSite;
  #210 = Methodref          #206.#209     // java/lang/invoke/LambdaMetafactory.altMetafactory:(Ljava/lang/invoke/MethodHandles$Lookup;Ljava/lang/String;Ljava/lang/invoke/MethodType;[Ljava/lang/Object;)Ljava/lang/invoke/CallSite;
  #211 = MethodHandle       6:#210        // REF_invokeStatic java/lang/invoke/LambdaMetafactory.altMetafactory:(Ljava/lang/invoke/MethodHandles$Lookup;Ljava/lang/String;Ljava/lang/invoke/MethodType;[Ljava/lang/Object;)Ljava/lang/invoke/CallSite;
  #212 = Utf8               (Lorg/sireum/IS;Lorg/sireum/Z;)Lscala/Function0;
  #213 = NameAndType        #148:#212     // apply:(Lorg/sireum/IS;Lorg/sireum/Z;)Lscala/Function0;
  #214 = InvokeDynamic      #0:#213       // #0:apply:(Lorg/sireum/IS;Lorg/sireum/Z;)Lscala/Function0;
  #215 = Utf8               $amp$amp$extension
  #216 = Utf8               (ZLscala/Function0;)Z
  #217 = NameAndType        #215:#216     // $amp$amp$extension:(ZLscala/Function0;)Z
  #218 = Methodref          #154.#217     // org/sireum/B$.$amp$amp$extension:(ZLscala/Function0;)Z
  #219 = Utf8               iMP
  #220 = Utf8               $colon$plus
  #221 = Utf8               (Ljava/lang/Object;)Lorg/sireum/IS;
  #222 = Utf8               (TV;)Lorg/sireum/IS<TI;TV;>;
  #223 = Utf8               e
  #224 = NameAndType        #152:#109     // isEmpty:()Z
  #225 = Methodref          #2.#224       // org/sireum/IS.isEmpty:()Z
  #226 = Utf8               $4B
  #227 = NameAndType        #226:#170     // $4B:(Z)Z
  #228 = Methodref          #154.#227     // org/sireum/B$.$4B:(Z)Z
  #229 = Utf8               scala/runtime/ScalaRunTime$
  #230 = Class              #229          // scala/runtime/ScalaRunTime$
  #231 = Utf8               Lscala/runtime/ScalaRunTime$;
  #232 = NameAndType        #70:#231      // MODULE$:Lscala/runtime/ScalaRunTime$;
  #233 = Fieldref           #230.#232     // scala/runtime/ScalaRunTime$.MODULE$:Lscala/runtime/ScalaRunTime$;
  #234 = Utf8               genericWrapArray
  #235 = Utf8               (Ljava/lang/Object;)Lscala/collection/immutable/ArraySeq;
  #236 = NameAndType        #234:#235     // genericWrapArray:(Ljava/lang/Object;)Lscala/collection/immutable/ArraySeq;
  #237 = Methodref          #230.#236     // scala/runtime/ScalaRunTime$.genericWrapArray:(Ljava/lang/Object;)Lscala/collection/immutable/ArraySeq;
  #238 = NameAndType        #53:#126      // companion:()Lorg/sireum/$ZCompanion;
  #239 = Methodref          #2.#238       // org/sireum/IS.companion:()Lorg/sireum/$ZCompanion;
  #240 = Utf8               (Lscala/collection/immutable/Seq;Lorg/sireum/$ZCompanion;)Lorg/sireum/IS;
  #241 = NameAndType        #148:#240     // apply:(Lscala/collection/immutable/Seq;Lorg/sireum/$ZCompanion;)Lorg/sireum/IS;
  #242 = Methodref          #69.#241      // org/sireum/IS$.apply:(Lscala/collection/immutable/Seq;Lorg/sireum/$ZCompanion;)Lorg/sireum/IS;
  #243 = Utf8               increase
  #244 = NameAndType        #243:#133     // increase:()Lorg/sireum/Z;
  #245 = InterfaceMethodref #39.#244      // org/sireum/Z.increase:()Lorg/sireum/Z;
  #246 = Utf8               $ZCompanion
  #247 = NameAndType        #246:#126     // $ZCompanion:()Lorg/sireum/$ZCompanion;
  #248 = Methodref          #186.#247     // org/sireum/package$.$ZCompanion:()Lorg/sireum/$ZCompanion;
  #249 = NameAndType        #60:#136      // boxer:()Lorg/sireum/$internal/Boxer;
  #250 = Methodref          #2.#249       // org/sireum/IS.boxer:()Lorg/sireum/$internal/Boxer;
  #251 = NameAndType        #56:#130      // data:()Ljava/lang/Object;
  #252 = Methodref          #2.#251       // org/sireum/IS.data:()Ljava/lang/Object;
  #253 = Utf8               org/sireum/$internal/Boxer
  #254 = Class              #253          // org/sireum/$internal/Boxer
  #255 = Utf8               clone
  #256 = Utf8               (Ljava/lang/Object;Lorg/sireum/Z;Lorg/sireum/Z;Lorg/sireum/Z;)Ljava/lang/Object;
  #257 = NameAndType        #255:#256     // clone:(Ljava/lang/Object;Lorg/sireum/Z;Lorg/sireum/Z;Lorg/sireum/Z;)Ljava/lang/Object;
  #258 = InterfaceMethodref #254.#257     // org/sireum/$internal/Boxer.clone:(Ljava/lang/Object;Lorg/sireum/Z;Lorg/sireum/Z;Lorg/sireum/Z;)Ljava/lang/Object;
  #259 = Utf8               store
  #260 = Utf8               (Ljava/lang/Object;Lorg/sireum/Z;Ljava/lang/Object;)V
  #261 = NameAndType        #259:#260     // store:(Ljava/lang/Object;Lorg/sireum/Z;Ljava/lang/Object;)V
  #262 = InterfaceMethodref #254.#261     // org/sireum/$internal/Boxer.store:(Ljava/lang/Object;Lorg/sireum/Z;Ljava/lang/Object;)V
  #263 = Utf8               (Lorg/sireum/$ZCompanion;Ljava/lang/Object;Lorg/sireum/Z;Lorg/sireum/$internal/Boxer;)Lorg/sireum/IS;
  #264 = NameAndType        #148:#263     // apply:(Lorg/sireum/$ZCompanion;Ljava/lang/Object;Lorg/sireum/Z;Lorg/sireum/$internal/Boxer;)Lorg/sireum/IS;
  #265 = Methodref          #69.#264      // org/sireum/IS$.apply:(Lorg/sireum/$ZCompanion;Ljava/lang/Object;Lorg/sireum/Z;Lorg/sireum/$internal/Boxer;)Lorg/sireum/IS;
  #266 = Utf8               newLength
  #267 = Utf8               a
  #268 = Utf8               $plus$colon
  #269 = Utf8               one
  #270 = NameAndType        #269:#133     // one:()Lorg/sireum/Z;
  #271 = Methodref          #37.#270      // org/sireum/Z$MP$.one:()Lorg/sireum/Z;
  #272 = Utf8               $plus$plus
  #273 = Utf8               (Lorg/sireum/IS;)Lorg/sireum/IS;
  #274 = Utf8               <I2:Ljava/lang/Object;>(Lorg/sireum/IS<TI2;TV;>;)Lorg/sireum/IS<TI;TV;>;
  #275 = Utf8               other
  #276 = Utf8               $plus
  #277 = Utf8               (Lorg/sireum/Z;)Lorg/sireum/Z;
  #278 = NameAndType        #276:#277     // $plus:(Lorg/sireum/Z;)Lorg/sireum/Z;
  #279 = InterfaceMethodref #39.#278      // org/sireum/Z.$plus:(Lorg/sireum/Z;)Lorg/sireum/Z;
  #280 = Utf8               $less
  #281 = Utf8               (Lorg/sireum/Z;)Z
  #282 = NameAndType        #280:#281     // $less:(Lorg/sireum/Z;)Z
  #283 = InterfaceMethodref #39.#282      // org/sireum/Z.$less:(Lorg/sireum/Z;)Z
  #284 = Utf8               lookup
  #285 = Utf8               (Ljava/lang/Object;Lorg/sireum/Z;)Ljava/lang/Object;
  #286 = NameAndType        #284:#285     // lookup:(Ljava/lang/Object;Lorg/sireum/Z;)Ljava/lang/Object;
  #287 = InterfaceMethodref #254.#286     // org/sireum/$internal/Boxer.lookup:(Ljava/lang/Object;Lorg/sireum/Z;)Ljava/lang/Object;
  #288 = Utf8               bxr
  #289 = Utf8               j
  #290 = Utf8               $minus$minus
  #291 = Utf8               $anonfun$$minus$minus$1$adapted
  #292 = Utf8               (Lorg/sireum/IS;)Ljava/lang/Object;
  #293 = NameAndType        #291:#292     // $anonfun$$minus$minus$1$adapted:(Lorg/sireum/IS;)Ljava/lang/Object;
  #294 = Methodref          #2.#293       // org/sireum/IS.$anonfun$$minus$minus$1$adapted:(Lorg/sireum/IS;)Ljava/lang/Object;
  #295 = MethodHandle       6:#294        // REF_invokeStatic org/sireum/IS.$anonfun$$minus$minus$1$adapted:(Lorg/sireum/IS;)Ljava/lang/Object;
  #296 = Utf8               (Lorg/sireum/IS;)Lscala/Function0;
  #297 = NameAndType        #148:#296     // apply:(Lorg/sireum/IS;)Lscala/Function0;
  #298 = InvokeDynamic      #1:#297       // #1:apply:(Lorg/sireum/IS;)Lscala/Function0;
  #299 = Utf8               $bar$bar$extension
  #300 = NameAndType        #299:#216     // $bar$bar$extension:(ZLscala/Function0;)Z
  #301 = Methodref          #154.#300     // org/sireum/B$.$bar$bar$extension:(ZLscala/Function0;)Z
  #302 = Utf8               elements
  #303 = Utf8               ()Lscala/collection/immutable/Seq;
  #304 = NameAndType        #302:#303     // elements:()Lscala/collection/immutable/Seq;
  #305 = Methodref          #2.#304       // org/sireum/IS.elements:()Lscala/collection/immutable/Seq;
  #306 = Utf8               (Ljava/lang/Object;)Ljava/lang/Object;
  #307 = MethodType         #306          //  (Ljava/lang/Object;)Ljava/lang/Object;
  #308 = Utf8               $anonfun$$minus$minus$2$adapted
  #309 = Utf8               (Lscala/collection/immutable/Seq;Ljava/lang/Object;)Ljava/lang/Object;
  #310 = NameAndType        #308:#309     // $anonfun$$minus$minus$2$adapted:(Lscala/collection/immutable/Seq;Ljava/lang/Object;)Ljava/lang/Object;
  #311 = Methodref          #2.#310       // org/sireum/IS.$anonfun$$minus$minus$2$adapted:(Lscala/collection/immutable/Seq;Ljava/lang/Object;)Ljava/lang/Object;
  #312 = MethodHandle       6:#311        // REF_invokeStatic org/sireum/IS.$anonfun$$minus$minus$2$adapted:(Lscala/collection/immutable/Seq;Ljava/lang/Object;)Ljava/lang/Object;
  #313 = Utf8               (Lscala/collection/immutable/Seq;)Lscala/Function1;
  #314 = NameAndType        #148:#313     // apply:(Lscala/collection/immutable/Seq;)Lscala/Function1;
  #315 = InvokeDynamic      #2:#314       // #2:apply:(Lscala/collection/immutable/Seq;)Lscala/Function1;
  #316 = Utf8               scala/collection/immutable/Seq
  #317 = Class              #316          // scala/collection/immutable/Seq
  #318 = Utf8               withFilter
  #319 = Utf8               (Lscala/Function1;)Lscala/collection/WithFilter;
  #320 = NameAndType        #318:#319     // withFilter:(Lscala/Function1;)Lscala/collection/WithFilter;
  #321 = InterfaceMethodref #317.#320     // scala/collection/immutable/Seq.withFilter:(Lscala/Function1;)Lscala/collection/WithFilter;
  #322 = Utf8               scala/runtime/ObjectRef
  #323 = Class              #322          // scala/runtime/ObjectRef
  #324 = Utf8               (Ljava/lang/Object;)Lscala/runtime/ObjectRef;
  #325 = NameAndType        #77:#324      // create:(Ljava/lang/Object;)Lscala/runtime/ObjectRef;
  #326 = Methodref          #323.#325     // scala/runtime/ObjectRef.create:(Ljava/lang/Object;)Lscala/runtime/ObjectRef;
  #327 = Utf8               tail
  #328 = NameAndType        #327:#130     // tail:()Ljava/lang/Object;
  #329 = InterfaceMethodref #317.#328     // scala/collection/immutable/Seq.tail:()Ljava/lang/Object;
  #330 = Utf8               scala/collection/IterableOnceOps
  #331 = Class              #330          // scala/collection/IterableOnceOps
  #332 = Utf8               $anonfun$$minus$minus$3$adapted
  #333 = Utf8               (Lscala/runtime/ObjectRef;Ljava/lang/Object;)Ljava/lang/Object;
  #334 = NameAndType        #332:#333     // $anonfun$$minus$minus$3$adapted:(Lscala/runtime/ObjectRef;Ljava/lang/Object;)Ljava/lang/Object;
  #335 = Methodref          #2.#334       // org/sireum/IS.$anonfun$$minus$minus$3$adapted:(Lscala/runtime/ObjectRef;Ljava/lang/Object;)Ljava/lang/Object;
  #336 = MethodHandle       6:#335        // REF_invokeStatic org/sireum/IS.$anonfun$$minus$minus$3$adapted:(Lscala/runtime/ObjectRef;Ljava/lang/Object;)Ljava/lang/Object;
  #337 = Utf8               (Lscala/runtime/ObjectRef;)Lscala/Function1;
  #338 = NameAndType        #148:#337     // apply:(Lscala/runtime/ObjectRef;)Lscala/Function1;
  #339 = InvokeDynamic      #3:#338       // #3:apply:(Lscala/runtime/ObjectRef;)Lscala/Function1;
  #340 = Utf8               foreach
  #341 = Utf8               (Lscala/Function1;)V
  #342 = NameAndType        #340:#341     // foreach:(Lscala/Function1;)V
  #343 = InterfaceMethodref #331.#342     // scala/collection/IterableOnceOps.foreach:(Lscala/Function1;)V
  #344 = Utf8               elem
  #345 = NameAndType        #344:#57      // elem:Ljava/lang/Object;
  #346 = Fieldref           #323.#345     // scala/runtime/ObjectRef.elem:Ljava/lang/Object;
  #347 = Utf8               scala/collection/WithFilter
  #348 = Class              #347          // scala/collection/WithFilter
  #349 = Utf8               $anonfun$$minus$minus$5
  #350 = NameAndType        #349:#306     // $anonfun$$minus$minus$5:(Ljava/lang/Object;)Ljava/lang/Object;
  #351 = Methodref          #2.#350       // org/sireum/IS.$anonfun$$minus$minus$5:(Ljava/lang/Object;)Ljava/lang/Object;
  #352 = MethodHandle       6:#351        // REF_invokeStatic org/sireum/IS.$anonfun$$minus$minus$5:(Ljava/lang/Object;)Ljava/lang/Object;
  #353 = Utf8               ()Lscala/Function1;
  #354 = NameAndType        #148:#353     // apply:()Lscala/Function1;
  #355 = InvokeDynamic      #4:#354       // #4:apply:()Lscala/Function1;
  #356 = Utf8               map
  #357 = Utf8               (Lscala/Function1;)Ljava/lang/Object;
  #358 = NameAndType        #356:#357     // map:(Lscala/Function1;)Ljava/lang/Object;
  #359 = Methodref          #348.#358     // scala/collection/WithFilter.map:(Lscala/Function1;)Ljava/lang/Object;
  #360 = NameAndType        #80:#145      // size:()I
  #361 = InterfaceMethodref #317.#360     // scala/collection/immutable/Seq.size:()I
  #362 = Methodref          #37.#150      // org/sireum/Z$MP$.apply:(I)Lorg/sireum/Z;
  #363 = Utf8               (Lorg/sireum/Z;)Ljava/lang/Object;
  #364 = NameAndType        #77:#363      // create:(Lorg/sireum/Z;)Ljava/lang/Object;
  #365 = InterfaceMethodref #254.#364     // org/sireum/$internal/Boxer.create:(Lorg/sireum/Z;)Ljava/lang/Object;
  #366 = Utf8               $anonfun$$minus$minus$6$adapted
  #367 = Utf8               (Lorg/sireum/IS;Ljava/lang/Object;Lscala/runtime/ObjectRef;Ljava/lang/Object;)Ljava/lang/Object;
  #368 = NameAndType        #366:#367     // $anonfun$$minus$minus$6$adapted:(Lorg/sireum/IS;Ljava/lang/Object;Lscala/runtime/ObjectRef;Ljava/lang/Object;)Ljava/lang/Object;
  #369 = Methodref          #2.#368       // org/sireum/IS.$anonfun$$minus$minus$6$adapted:(Lorg/sireum/IS;Ljava/lang/Object;Lscala/runtime/ObjectRef;Ljava/lang/Object;)Ljava/lang/Object;
  #370 = MethodHandle       6:#369        // REF_invokeStatic org/sireum/IS.$anonfun$$minus$minus$6$adapted:(Lorg/sireum/IS;Ljava/lang/Object;Lscala/runtime/ObjectRef;Ljava/lang/Object;)Ljava/lang/Object;
  #371 = Utf8               (Lorg/sireum/IS;Ljava/lang/Object;Lscala/runtime/ObjectRef;)Lscala/Function1;
  #372 = NameAndType        #148:#371     // apply:(Lorg/sireum/IS;Ljava/lang/Object;Lscala/runtime/ObjectRef;)Lscala/Function1;
  #373 = InvokeDynamic      #5:#372       // #5:apply:(Lorg/sireum/IS;Ljava/lang/Object;Lscala/runtime/ObjectRef;)Lscala/Function1;
  #374 = InterfaceMethodref #317.#342     // scala/collection/immutable/Seq.foreach:(Lscala/Function1;)V
  #375 = Utf8               otherElements
  #376 = Utf8               Lscala/collection/immutable/Seq;
  #377 = Utf8               sm
  #378 = Utf8               Lscala/runtime/ObjectRef;
  #379 = Utf8               s
  #380 = Utf8               $minus
  #381 = Utf8               $anonfun$$minus$1$adapted
  #382 = Utf8               (Ljava/lang/Object;Ljava/lang/Object;)Ljava/lang/Object;
  #383 = NameAndType        #381:#382     // $anonfun$$minus$1$adapted:(Ljava/lang/Object;Ljava/lang/Object;)Ljava/lang/Object;
  #384 = Methodref          #2.#383       // org/sireum/IS.$anonfun$$minus$1$adapted:(Ljava/lang/Object;Ljava/lang/Object;)Ljava/lang/Object;
  #385 = MethodHandle       6:#384        // REF_invokeStatic org/sireum/IS.$anonfun$$minus$1$adapted:(Ljava/lang/Object;Ljava/lang/Object;)Ljava/lang/Object;
  #386 = Utf8               (Ljava/lang/Object;)Lscala/Function1;
  #387 = NameAndType        #148:#386     // apply:(Ljava/lang/Object;)Lscala/Function1;
  #388 = InvokeDynamic      #6:#387       // #6:apply:(Ljava/lang/Object;)Lscala/Function1;
  #389 = Utf8               filter
  #390 = Utf8               (Lscala/Function1;)Lorg/sireum/IS;
  #391 = NameAndType        #389:#390     // filter:(Lscala/Function1;)Lorg/sireum/IS;
  #392 = Methodref          #2.#391       // org/sireum/IS.filter:(Lscala/Function1;)Lorg/sireum/IS;
  #393 = Utf8               atZ
  #394 = Utf8               (Lorg/sireum/Z;)TV;
  #395 = Utf8               scala/Predef$
  #396 = Class              #395          // scala/Predef$
  #397 = Utf8               Lscala/Predef$;
  #398 = NameAndType        #70:#397      // MODULE$:Lscala/Predef$;
  #399 = Fieldref           #396.#398     // scala/Predef$.MODULE$:Lscala/Predef$;
  #400 = Utf8               $less$eq
  #401 = NameAndType        #400:#281     // $less$eq:(Lorg/sireum/Z;)Z
  #402 = InterfaceMethodref #39.#401      // org/sireum/Z.$less$eq:(Lorg/sireum/Z;)Z
  #403 = Utf8               $anonfun$atZ$1$adapted
  #404 = NameAndType        #403:#200     // $anonfun$atZ$1$adapted:(Lorg/sireum/IS;Lorg/sireum/Z;)Ljava/lang/Object;
  #405 = Methodref          #2.#404       // org/sireum/IS.$anonfun$atZ$1$adapted:(Lorg/sireum/IS;Lorg/sireum/Z;)Ljava/lang/Object;
  #406 = MethodHandle       6:#405        // REF_invokeStatic org/sireum/IS.$anonfun$atZ$1$adapted:(Lorg/sireum/IS;Lorg/sireum/Z;)Ljava/lang/Object;
  #407 = InvokeDynamic      #7:#213       // #7:apply:(Lorg/sireum/IS;Lorg/sireum/Z;)Lscala/Function0;
  #408 = Utf8               $anonfun$atZ$2
  #409 = Utf8               (Lorg/sireum/Z;)Ljava/lang/String;
  #410 = NameAndType        #408:#409     // $anonfun$atZ$2:(Lorg/sireum/Z;)Ljava/lang/String;
  #411 = Methodref          #2.#410       // org/sireum/IS.$anonfun$atZ$2:(Lorg/sireum/Z;)Ljava/lang/String;
  #412 = MethodHandle       6:#411        // REF_invokeStatic org/sireum/IS.$anonfun$atZ$2:(Lorg/sireum/Z;)Ljava/lang/String;
  #413 = Utf8               ()Ljava/lang/String;
  #414 = MethodType         #413          //  ()Ljava/lang/String;
  #415 = Integer            5
  #416 = Utf8               (Lorg/sireum/Z;)Lscala/Function0;
  #417 = NameAndType        #148:#416     // apply:(Lorg/sireum/Z;)Lscala/Function0;
  #418 = InvokeDynamic      #8:#417       // #8:apply:(Lorg/sireum/Z;)Lscala/Function0;
  #419 = Utf8               assert
  #420 = Utf8               (ZLscala/Function0;)V
  #421 = NameAndType        #419:#420     // assert:(ZLscala/Function0;)V
  #422 = Methodref          #396.#421     // scala/Predef$.assert:(ZLscala/Function0;)V
  #423 = Utf8               indices
  #424 = Utf8               ()Lorg/sireum/ZRange;
  #425 = Utf8               ()Lorg/sireum/ZRange<TI;>;
  #426 = Utf8               org/sireum/$ZCompanion
  #427 = Class              #426          // org/sireum/$ZCompanion
  #428 = Utf8               Index
  #429 = NameAndType        #428:#130     // Index:()Ljava/lang/Object;
  #430 = InterfaceMethodref #427.#429     // org/sireum/$ZCompanion.Index:()Ljava/lang/Object;
  #431 = Utf8               ()Lorg/sireum/ZLike;
  #432 = NameAndType        #243:#431     // increase:()Lorg/sireum/ZLike;
  #433 = InterfaceMethodref #178.#432     // org/sireum/ZLike.increase:()Lorg/sireum/ZLike;
  #434 = Utf8               T
  #435 = NameAndType        #434:#109     // T:()Z
  #436 = Methodref          #186.#435     // org/sireum/package$.T:()Z
  #437 = Utf8               decrease
  #438 = NameAndType        #437:#431     // decrease:()Lorg/sireum/ZLike;
  #439 = InterfaceMethodref #178.#438     // org/sireum/ZLike.decrease:()Lorg/sireum/ZLike;
  #440 = Utf8               <init>
  #441 = Utf8               (Lorg/sireum/IS;)V
  #442 = NameAndType        #440:#441     // "<init>":(Lorg/sireum/IS;)V
  #443 = Methodref          #30.#442      // org/sireum/IS$$anon$1."<init>":(Lorg/sireum/IS;)V
  #444 = Utf8               (ZLjava/lang/Object;Ljava/lang/Object;Lorg/sireum/Z;Lorg/sireum/ZRange$CondIncDec;)V
  #445 = NameAndType        #440:#444     // "<init>":(ZLjava/lang/Object;Ljava/lang/Object;Lorg/sireum/Z;Lorg/sireum/ZRange$CondIncDec;)V
  #446 = Methodref          #44.#445      // org/sireum/ZRange."<init>":(ZLjava/lang/Object;Ljava/lang/Object;Lorg/sireum/Z;Lorg/sireum/ZRange$CondIncDec;)V
  #447 = Utf8               Lorg/sireum/ZLike;
  #448 = Utf8               <V2:Ljava/lang/Object;>(Lscala/Function1<TV;TV2;>;)Lorg/sireum/IS<TI;TV2;>;
  #449 = Utf8               f
  #450 = Utf8               scala/Array$
  #451 = Class              #450          // scala/Array$
  #452 = Utf8               Lscala/Array$;
  #453 = NameAndType        #70:#452      // MODULE$:Lscala/Array$;
  #454 = Fieldref           #451.#453     // scala/Array$.MODULE$:Lscala/Array$;
  #455 = Utf8               scala/collection/immutable/Nil$
  #456 = Class              #455          // scala/collection/immutable/Nil$
  #457 = Utf8               Lscala/collection/immutable/Nil$;
  #458 = NameAndType        #70:#457      // MODULE$:Lscala/collection/immutable/Nil$;
  #459 = Fieldref           #456.#458     // scala/collection/immutable/Nil$.MODULE$:Lscala/collection/immutable/Nil$;
  #460 = Utf8               scala/reflect/ClassTag$
  #461 = Class              #460          // scala/reflect/ClassTag$
  #462 = Utf8               Lscala/reflect/ClassTag$;
  #463 = NameAndType        #70:#462      // MODULE$:Lscala/reflect/ClassTag$;
  #464 = Fieldref           #461.#463     // scala/reflect/ClassTag$.MODULE$:Lscala/reflect/ClassTag$;
  #465 = Utf8               Nothing
  #466 = Utf8               ()Lscala/reflect/ClassTag;
  #467 = NameAndType        #465:#466     // Nothing:()Lscala/reflect/ClassTag;
  #468 = Methodref          #461.#467     // scala/reflect/ClassTag$.Nothing:()Lscala/reflect/ClassTag;
  #469 = Utf8               (Lscala/collection/immutable/Seq;Lscala/reflect/ClassTag;)Ljava/lang/Object;
  #470 = NameAndType        #148:#469     // apply:(Lscala/collection/immutable/Seq;Lscala/reflect/ClassTag;)Ljava/lang/Object;
  #471 = Methodref          #451.#470     // scala/Array$.apply:(Lscala/collection/immutable/Seq;Lscala/reflect/ClassTag;)Ljava/lang/Object;
  #472 = Utf8               scala/Function1
  #473 = Class              #472          // scala/Function1
  #474 = NameAndType        #148:#306     // apply:(Ljava/lang/Object;)Ljava/lang/Object;
  #475 = InterfaceMethodref #473.#474     // scala/Function1.apply:(Ljava/lang/Object;)Ljava/lang/Object;
  #476 = Utf8               org/sireum/$internal/Boxer$
  #477 = Class              #476          // org/sireum/$internal/Boxer$
  #478 = Utf8               Lorg/sireum/$internal/Boxer$;
  #479 = NameAndType        #70:#478      // MODULE$:Lorg/sireum/$internal/Boxer$;
  #480 = Fieldref           #477.#479     // org/sireum/$internal/Boxer$.MODULE$:Lorg/sireum/$internal/Boxer$;
  #481 = Utf8               (Ljava/lang/Object;)Lorg/sireum/$internal/Boxer;
  #482 = NameAndType        #60:#481      // boxer:(Ljava/lang/Object;)Lorg/sireum/$internal/Boxer;
  #483 = Methodref          #477.#482     // org/sireum/$internal/Boxer$.boxer:(Ljava/lang/Object;)Lorg/sireum/$internal/Boxer;
  #484 = Utf8               org/sireum/$internal/IdentityBoxer$
  #485 = Class              #484          // org/sireum/$internal/IdentityBoxer$
  #486 = Utf8               Lorg/sireum/$internal/IdentityBoxer$;
  #487 = NameAndType        #70:#486      // MODULE$:Lorg/sireum/$internal/IdentityBoxer$;
  #488 = Fieldref           #485.#487     // org/sireum/$internal/IdentityBoxer$.MODULE$:Lorg/sireum/$internal/IdentityBoxer$;
  #489 = Utf8               v2
  #490 = Utf8               boxer2
  #491 = Utf8               Lscala/Function1;
  #492 = Utf8               <U:Ljava/lang/Object;>(Lscala/Function1<TV;TU;>;)V
  #493 = Utf8               flatMap
  #494 = Utf8               <V2:Ljava/lang/Object;>(Lscala/Function1<TV;Lorg/sireum/IS<TI;TV2;>;>;)Lorg/sireum/IS<TI;TV2;>;
  #495 = Utf8               head
  #496 = NameAndType        #495:#130     // head:()Ljava/lang/Object;
  #497 = InterfaceMethodref #317.#496     // scala/collection/immutable/Seq.head:()Ljava/lang/Object;
  #498 = Utf8               $anonfun$flatMap$3$adapted
  #499 = Utf8               (Lscala/runtime/ObjectRef;Lscala/Function1;Ljava/lang/Object;)Ljava/lang/Object;
  #500 = NameAndType        #498:#499     // $anonfun$flatMap$3$adapted:(Lscala/runtime/ObjectRef;Lscala/Function1;Ljava/lang/Object;)Ljava/lang/Object;
  #501 = Methodref          #2.#500       // org/sireum/IS.$anonfun$flatMap$3$adapted:(Lscala/runtime/ObjectRef;Lscala/Function1;Ljava/lang/Object;)Ljava/lang/Object;
  #502 = MethodHandle       6:#501        // REF_invokeStatic org/sireum/IS.$anonfun$flatMap$3$adapted:(Lscala/runtime/ObjectRef;Lscala/Function1;Ljava/lang/Object;)Ljava/lang/Object;
  #503 = Utf8               (Lscala/runtime/ObjectRef;Lscala/Function1;)Lscala/Function1;
  #504 = NameAndType        #148:#503     // apply:(Lscala/runtime/ObjectRef;Lscala/Function1;)Lscala/Function1;
  #505 = InvokeDynamic      #9:#504       // #9:apply:(Lscala/runtime/ObjectRef;Lscala/Function1;)Lscala/Function1;
  #506 = Utf8               es
  #507 = Utf8               r
  #508 = Utf8               (Lscala/Function1<TV;Lorg/sireum/B;>;)Lorg/sireum/IS<TI;TV;>;
  #509 = Utf8               p
  #510 = Utf8               org/sireum/B
  #511 = Class              #510          // org/sireum/B
  #512 = Utf8               value
  #513 = NameAndType        #512:#109     // value:()Z
  #514 = Methodref          #511.#513     // org/sireum/B.value:()Z
  #515 = Utf8               (Lscala/Function1;)Lorg/sireum/IS$WithFilter;
  #516 = Utf8               (Lscala/Function1<TV;Lorg/sireum/B;>;)Lorg/sireum/IS$WithFilter<TI;TV;>;
  #517 = Utf8               (Lorg/sireum/IS;Lscala/Function1;)V
  #518 = NameAndType        #440:#517     // "<init>":(Lorg/sireum/IS;Lscala/Function1;)V
  #519 = Methodref          #34.#518      // org/sireum/IS$WithFilter."<init>":(Lorg/sireum/IS;Lscala/Function1;)V
  #520 = Utf8               iterator
  #521 = Utf8               ()Ljava/util/Iterator;
  #522 = Utf8               ()Ljava/util/Iterator<TV;>;
  #523 = Methodref          #32.#442      // org/sireum/IS$$anon$2."<init>":(Lorg/sireum/IS;)V
  #524 = Utf8               firstIndex
  #525 = Utf8               ()TI;
  #526 = NameAndType        #173:#109     // nonEmpty:()Z
  #527 = Methodref          #2.#526       // org/sireum/IS.nonEmpty:()Z
  #528 = Utf8               $anonfun$firstIndex$1
  #529 = NameAndType        #528:#413     // $anonfun$firstIndex$1:()Ljava/lang/String;
  #530 = Methodref          #2.#529       // org/sireum/IS.$anonfun$firstIndex$1:()Ljava/lang/String;
  #531 = MethodHandle       6:#530        // REF_invokeStatic org/sireum/IS.$anonfun$firstIndex$1:()Ljava/lang/String;
  #532 = Utf8               ()Lscala/Function0;
  #533 = NameAndType        #148:#532     // apply:()Lscala/Function0;
  #534 = InvokeDynamic      #10:#533      // #10:apply:()Lscala/Function0;
  #535 = Utf8               isZeroIndex
  #536 = NameAndType        #535:#109     // isZeroIndex:()Z
  #537 = InterfaceMethodref #427.#536     // org/sireum/$ZCompanion.isZeroIndex:()Z
  #538 = NameAndType        #148:#363     // apply:(Lorg/sireum/Z;)Ljava/lang/Object;
  #539 = InterfaceMethodref #427.#538     // org/sireum/$ZCompanion.apply:(Lorg/sireum/Z;)Ljava/lang/Object;
  #540 = Utf8               Min
  #541 = NameAndType        #540:#130     // Min:()Ljava/lang/Object;
  #542 = InterfaceMethodref #427.#541     // org/sireum/$ZCompanion.Min:()Ljava/lang/Object;
  #543 = Utf8               lastIndex
  #544 = Utf8               $anonfun$lastIndex$1
  #545 = NameAndType        #544:#413     // $anonfun$lastIndex$1:()Ljava/lang/String;
  #546 = Methodref          #2.#545       // org/sireum/IS.$anonfun$lastIndex$1:()Ljava/lang/String;
  #547 = MethodHandle       6:#546        // REF_invokeStatic org/sireum/IS.$anonfun$lastIndex$1:()Ljava/lang/String;
  #548 = InvokeDynamic      #11:#533      // #11:apply:()Lscala/Function0;
  #549 = Utf8               until$extension
  #550 = Utf8               (ILorg/sireum/Z;)Lorg/sireum/ZRange;
  #551 = NameAndType        #549:#550     // until$extension:(ILorg/sireum/Z;)Lorg/sireum/ZRange;
  #552 = Methodref          #47.#551      // org/sireum/package$$Int2Z$.until$extension:(ILorg/sireum/Z;)Lorg/sireum/ZRange;
  #553 = Utf8               $anonfun$lastIndex$2$adapted
  #554 = Utf8               (Lscala/runtime/ObjectRef;Lorg/sireum/Z;)Ljava/lang/Object;
  #555 = NameAndType        #553:#554     // $anonfun$lastIndex$2$adapted:(Lscala/runtime/ObjectRef;Lorg/sireum/Z;)Ljava/lang/Object;
  #556 = Methodref          #2.#555       // org/sireum/IS.$anonfun$lastIndex$2$adapted:(Lscala/runtime/ObjectRef;Lorg/sireum/Z;)Ljava/lang/Object;
  #557 = MethodHandle       6:#556        // REF_invokeStatic org/sireum/IS.$anonfun$lastIndex$2$adapted:(Lscala/runtime/ObjectRef;Lorg/sireum/Z;)Ljava/lang/Object;
  #558 = MethodType         #363          //  (Lorg/sireum/Z;)Ljava/lang/Object;
  #559 = InvokeDynamic      #12:#338      // #12:apply:(Lscala/runtime/ObjectRef;)Lscala/Function1;
  #560 = Methodref          #44.#342      // org/sireum/ZRange.foreach:(Lscala/Function1;)V
  #561 = Utf8               toMS
  #562 = Utf8               ()Lorg/sireum/MS;
  #563 = Utf8               ()Lorg/sireum/MS<TI;TV;>;
  #564 = Utf8               org/sireum/MS
  #565 = Class              #564          // org/sireum/MS
  #566 = Utf8               (Lorg/sireum/$ZCompanion;Ljava/lang/Object;Lorg/sireum/Z;Lorg/sireum/$internal/Boxer;)V
  #567 = NameAndType        #440:#566     // "<init>":(Lorg/sireum/$ZCompanion;Ljava/lang/Object;Lorg/sireum/Z;Lorg/sireum/$internal/Boxer;)V
  #568 = Methodref          #565.#567     // org/sireum/MS."<init>":(Lorg/sireum/$ZCompanion;Ljava/lang/Object;Lorg/sireum/Z;Lorg/sireum/$internal/Boxer;)V
  #569 = Utf8               toISZ
  #570 = Utf8               ()Lorg/sireum/IS;
  #571 = Utf8               ()Lorg/sireum/IS<Lorg/sireum/Z;TV;>;
  #572 = Utf8               ISZ
  #573 = Utf8               ()Lorg/sireum/$internal/PackageTrait$ISZ$;
  #574 = NameAndType        #572:#573     // ISZ:()Lorg/sireum/$internal/PackageTrait$ISZ$;
  #575 = Methodref          #186.#574     // org/sireum/package$.ISZ:()Lorg/sireum/$internal/PackageTrait$ISZ$;
  #576 = Utf8               (Lscala/collection/immutable/Seq;)Lorg/sireum/IS;
  #577 = NameAndType        #148:#576     // apply:(Lscala/collection/immutable/Seq;)Lorg/sireum/IS;
  #578 = Methodref          #22.#577      // org/sireum/$internal/PackageTrait$ISZ$.apply:(Lscala/collection/immutable/Seq;)Lorg/sireum/IS;
  #579 = Utf8               toMSZ
  #580 = Utf8               ()Lorg/sireum/MS<Lorg/sireum/Z;TV;>;
  #581 = Utf8               MSZ
  #582 = Utf8               ()Lorg/sireum/$internal/PackageTrait$MSZ$;
  #583 = NameAndType        #581:#582     // MSZ:()Lorg/sireum/$internal/PackageTrait$MSZ$;
  #584 = Methodref          #186.#583     // org/sireum/package$.MSZ:()Lorg/sireum/$internal/PackageTrait$MSZ$;
  #585 = Utf8               (Lscala/collection/immutable/Seq;)Lorg/sireum/MS;
  #586 = NameAndType        #148:#585     // apply:(Lscala/collection/immutable/Seq;)Lorg/sireum/MS;
  #587 = Methodref          #27.#586      // org/sireum/$internal/PackageTrait$MSZ$.apply:(Lscala/collection/immutable/Seq;)Lorg/sireum/MS;
  #588 = Utf8               (TI;)TV;
  #589 = Utf8               index
  #590 = Utf8               toIndex
  #591 = NameAndType        #590:#133     // toIndex:()Lorg/sireum/Z;
  #592 = InterfaceMethodref #178.#591     // org/sireum/ZLike.toIndex:()Lorg/sireum/Z;
  #593 = NameAndType        #393:#363     // atZ:(Lorg/sireum/Z;)Ljava/lang/Object;
  #594 = Methodref          #2.#593       // org/sireum/IS.atZ:(Lorg/sireum/Z;)Ljava/lang/Object;
  #595 = Utf8               (Lscala/collection/immutable/Seq<Lscala/Tuple2<TI;TV;>;>;)Lorg/sireum/IS<TI;TV;>;
  #596 = Utf8               args
  #597 = InterfaceMethodref #317.#224     // scala/collection/immutable/Seq.isEmpty:()Z
  #598 = Utf8               $anonfun$apply$2$adapted
  #599 = Utf8               (Lscala/Tuple2;)Ljava/lang/Object;
  #600 = NameAndType        #598:#599     // $anonfun$apply$2$adapted:(Lscala/Tuple2;)Ljava/lang/Object;
  #601 = Methodref          #2.#600       // org/sireum/IS.$anonfun$apply$2$adapted:(Lscala/Tuple2;)Ljava/lang/Object;
  #602 = MethodHandle       6:#601        // REF_invokeStatic org/sireum/IS.$anonfun$apply$2$adapted:(Lscala/Tuple2;)Ljava/lang/Object;
  #603 = MethodType         #599          //  (Lscala/Tuple2;)Ljava/lang/Object;
  #604 = InvokeDynamic      #13:#354      // #13:apply:()Lscala/Function1;
  #605 = Utf8               $anonfun$apply$3$adapted
  #606 = Utf8               (Lorg/sireum/IS;Ljava/lang/Object;Lscala/Tuple2;)Ljava/lang/Object;
  #607 = NameAndType        #605:#606     // $anonfun$apply$3$adapted:(Lorg/sireum/IS;Ljava/lang/Object;Lscala/Tuple2;)Ljava/lang/Object;
  #608 = Methodref          #2.#607       // org/sireum/IS.$anonfun$apply$3$adapted:(Lorg/sireum/IS;Ljava/lang/Object;Lscala/Tuple2;)Ljava/lang/Object;
  #609 = MethodHandle       6:#608        // REF_invokeStatic org/sireum/IS.$anonfun$apply$3$adapted:(Lorg/sireum/IS;Ljava/lang/Object;Lscala/Tuple2;)Ljava/lang/Object;
  #610 = Utf8               (Lorg/sireum/IS;Ljava/lang/Object;)Lscala/Function1;
  #611 = NameAndType        #148:#610     // apply:(Lorg/sireum/IS;Ljava/lang/Object;)Lscala/Function1;
  #612 = InvokeDynamic      #14:#611      // #14:apply:(Lorg/sireum/IS;Ljava/lang/Object;)Lscala/Function1;
  #613 = Methodref          #348.#342     // scala/collection/WithFilter.foreach:(Lscala/Function1;)V
  #614 = Utf8               ()Lscala/collection/immutable/Seq<TV;>;
  #615 = Utf8               toInt
  #616 = NameAndType        #615:#145     // toInt:()I
  #617 = InterfaceMethodref #39.#616      // org/sireum/Z.toInt:()I
  #618 = Utf8               scala/collection/ArrayOps$
  #619 = Class              #618          // scala/collection/ArrayOps$
  #620 = Utf8               Lscala/collection/ArrayOps$;
  #621 = NameAndType        #70:#620      // MODULE$:Lscala/collection/ArrayOps$;
  #622 = Fieldref           #619.#621     // scala/collection/ArrayOps$.MODULE$:Lscala/collection/ArrayOps$;
  #623 = Utf8               genericArrayOps
  #624 = NameAndType        #623:#306     // genericArrayOps:(Ljava/lang/Object;)Ljava/lang/Object;
  #625 = Methodref          #396.#624     // scala/Predef$.genericArrayOps:(Ljava/lang/Object;)Ljava/lang/Object;
  #626 = Utf8               toSeq$extension
  #627 = Utf8               (Ljava/lang/Object;)Lscala/collection/immutable/Seq;
  #628 = NameAndType        #626:#627     // toSeq$extension:(Ljava/lang/Object;)Lscala/collection/immutable/Seq;
  #629 = Methodref          #619.#628     // scala/collection/ArrayOps$.toSeq$extension:(Ljava/lang/Object;)Lscala/collection/immutable/Seq;
  #630 = Utf8               [Ljava/lang/Object;
  #631 = Class              #630          // "[Ljava/lang/Object;"
  #632 = Utf8               hashCode$lzycompute
  #633 = NameAndType        #62:#63       // bitmap$0:Z
  #634 = Fieldref           #2.#633       // org/sireum/IS.bitmap$0:Z
  #635 = Utf8               scala/Tuple2
  #636 = Class              #635          // scala/Tuple2
  #637 = Utf8               (Ljava/lang/Object;Ljava/lang/Object;)V
  #638 = NameAndType        #440:#637     // "<init>":(Ljava/lang/Object;Ljava/lang/Object;)V
  #639 = Methodref          #636.#638     // scala/Tuple2."<init>":(Ljava/lang/Object;Ljava/lang/Object;)V
  #640 = Methodref          #636.#146     // scala/Tuple2.hashCode:()I
  #641 = NameAndType        #51:#52       // hashCode:I
  #642 = Fieldref           #2.#641       // org/sireum/IS.hashCode:I
  #643 = Utf8               java/lang/Throwable
  #644 = Class              #643          // java/lang/Throwable
  #645 = NameAndType        #632:#145     // hashCode$lzycompute:()I
  #646 = Methodref          #2.#645       // org/sireum/IS.hashCode$lzycompute:()I
  #647 = Utf8               scala/runtime/NonLocalReturnControl
  #648 = Class              #647          // scala/runtime/NonLocalReturnControl
  #649 = Utf8               ()V
  #650 = NameAndType        #440:#649     // "<init>":()V
  #651 = Methodref          #5.#650       // java/lang/Object."<init>":()V
  #652 = Utf8               until
  #653 = Utf8               (Lorg/sireum/ZLike;)Lorg/sireum/ZRange;
  #654 = NameAndType        #652:#653     // until:(Lorg/sireum/ZLike;)Lorg/sireum/ZRange;
  #655 = InterfaceMethodref #39.#654      // org/sireum/Z.until:(Lorg/sireum/ZLike;)Lorg/sireum/ZRange;
  #656 = Utf8               $anonfun$equals$1$adapted
  #657 = Utf8               (Lorg/sireum/$internal/Boxer;Ljava/lang/Object;Lorg/sireum/$internal/Boxer;Ljava/lang/Object;Ljava/lang/Object;Lorg/sireum/Z;)Ljava/lang/Object;
  #658 = NameAndType        #656:#657     // $anonfun$equals$1$adapted:(Lorg/sireum/$internal/Boxer;Ljava/lang/Object;Lorg/sireum/$internal/Boxer;Ljava/lang/Object;Ljava/lang/Object;Lorg/sireum/Z;)Ljava/lang/Object;
  #659 = Methodref          #2.#658       // org/sireum/IS.$anonfun$equals$1$adapted:(Lorg/sireum/$internal/Boxer;Ljava/lang/Object;Lorg/sireum/$internal/Boxer;Ljava/lang/Object;Ljava/lang/Object;Lorg/sireum/Z;)Ljava/lang/Object;
  #660 = MethodHandle       6:#659        // REF_invokeStatic org/sireum/IS.$anonfun$equals$1$adapted:(Lorg/sireum/$internal/Boxer;Ljava/lang/Object;Lorg/sireum/$internal/Boxer;Ljava/lang/Object;Ljava/lang/Object;Lorg/sireum/Z;)Ljava/lang/Object;
  #661 = Utf8               (Lorg/sireum/$internal/Boxer;Ljava/lang/Object;Lorg/sireum/$internal/Boxer;Ljava/lang/Object;Ljava/lang/Object;)Lscala/Function1;
  #662 = NameAndType        #148:#661     // apply:(Lorg/sireum/$internal/Boxer;Ljava/lang/Object;Lorg/sireum/$internal/Boxer;Ljava/lang/Object;Ljava/lang/Object;)Lscala/Function1;
  #663 = InvokeDynamic      #15:#662      // #15:apply:(Lorg/sireum/$internal/Boxer;Ljava/lang/Object;Lorg/sireum/$internal/Boxer;Ljava/lang/Object;Ljava/lang/Object;)Lscala/Function1;
  #664 = Utf8               key
  #665 = NameAndType        #664:#130     // key:()Ljava/lang/Object;
  #666 = Methodref          #648.#665     // scala/runtime/NonLocalReturnControl.key:()Ljava/lang/Object;
  #667 = Utf8               value$mcZ$sp
  #668 = NameAndType        #667:#109     // value$mcZ$sp:()Z
  #669 = Methodref          #648.#668     // scala/runtime/NonLocalReturnControl.value$mcZ$sp:()Z
  #670 = Utf8               b1
  #671 = Utf8               b2
  #672 = Utf8               data1
  #673 = Utf8               data2
  #674 = Utf8               ex
  #675 = Utf8               Lscala/runtime/NonLocalReturnControl;
  #676 = Utf8               string
  #677 = Utf8               org/sireum/String$
  #678 = Class              #677          // org/sireum/String$
  #679 = Utf8               Lorg/sireum/String$;
  #680 = NameAndType        #70:#679      // MODULE$:Lorg/sireum/String$;
  #681 = Fieldref           #678.#680     // org/sireum/String$.MODULE$:Lorg/sireum/String$;
  #682 = Utf8               toString
  #683 = NameAndType        #682:#413     // toString:()Ljava/lang/String;
  #684 = Methodref          #2.#683       // org/sireum/IS.toString:()Ljava/lang/String;
  #685 = Utf8               (Ljava/lang/String;)Ljava/lang/String;
  #686 = NameAndType        #148:#685     // apply:(Ljava/lang/String;)Ljava/lang/String;
  #687 = Methodref          #678.#686     // org/sireum/String$.apply:(Ljava/lang/String;)Ljava/lang/String;
  #688 = Utf8               (Ljava/lang/Object;Lorg/sireum/Z;)Ljava/lang/String;
  #689 = NameAndType        #682:#688     // toString:(Ljava/lang/Object;Lorg/sireum/Z;)Ljava/lang/String;
  #690 = InterfaceMethodref #254.#689     // org/sireum/$internal/Boxer.toString:(Ljava/lang/Object;Lorg/sireum/Z;)Ljava/lang/String;
  #691 = NameAndType        #118:#119     // $clone:()Lorg/sireum/$internal/ImmutableMarker;
  #692 = Methodref          #2.#691       // org/sireum/IS.$clone:()Lorg/sireum/$internal/ImmutableMarker;
  #693 = Utf8               $anonfun$isInBound$1
  #694 = Utf8               (Lorg/sireum/IS;Lorg/sireum/Z;)Z
  #695 = Utf8               $this
  #696 = Utf8               iMP$1
  #697 = Utf8               $anonfun$$minus$minus$1
  #698 = Utf8               (Lorg/sireum/IS;)Z
  #699 = Utf8               other$1
  #700 = Utf8               $anonfun$$minus$minus$2
  #701 = Utf8               (Lscala/collection/immutable/Seq;Ljava/lang/Object;)Z
  #702 = Utf8               otherElements$1
  #703 = Utf8               scala/runtime/BoxesRunTime
  #704 = Class              #703          // scala/runtime/BoxesRunTime
  #705 = Utf8               (Ljava/lang/Object;Ljava/lang/Object;)Z
  #706 = NameAndType        #166:#705     // equals:(Ljava/lang/Object;Ljava/lang/Object;)Z
  #707 = Methodref          #704.#706     // scala/runtime/BoxesRunTime.equals:(Ljava/lang/Object;Ljava/lang/Object;)Z
  #708 = Utf8               $anonfun$$minus$minus$4
  #709 = Utf8               e$1
  #710 = Utf8               x$2
  #711 = Utf8               $anonfun$$minus$minus$3
  #712 = Utf8               (Lscala/runtime/ObjectRef;Ljava/lang/Object;)V
  #713 = Utf8               sm$1
  #714 = Utf8               $anonfun$$minus$minus$4$adapted
  #715 = NameAndType        #714:#382     // $anonfun$$minus$minus$4$adapted:(Ljava/lang/Object;Ljava/lang/Object;)Ljava/lang/Object;
  #716 = Methodref          #2.#715       // org/sireum/IS.$anonfun$$minus$minus$4$adapted:(Ljava/lang/Object;Ljava/lang/Object;)Ljava/lang/Object;
  #717 = MethodHandle       6:#716        // REF_invokeStatic org/sireum/IS.$anonfun$$minus$minus$4$adapted:(Ljava/lang/Object;Ljava/lang/Object;)Ljava/lang/Object;
  #718 = InvokeDynamic      #16:#387      // #16:apply:(Ljava/lang/Object;)Lscala/Function1;
  #719 = Methodref          #348.#320     // scala/collection/WithFilter.withFilter:(Lscala/Function1;)Lscala/collection/WithFilter;
  #720 = Utf8               x
  #721 = Utf8               identity
  #722 = NameAndType        #721:#306     // identity:(Ljava/lang/Object;)Ljava/lang/Object;
  #723 = Methodref          #396.#722     // scala/Predef$.identity:(Ljava/lang/Object;)Ljava/lang/Object;
  #724 = Utf8               $anonfun$$minus$minus$6
  #725 = Utf8               (Lorg/sireum/IS;Ljava/lang/Object;Lscala/runtime/ObjectRef;Ljava/lang/Object;)V
  #726 = Utf8               a$2
  #727 = Utf8               i$2
  #728 = Utf8               $anonfun$$minus$1
  #729 = Utf8               e$2
  #730 = Utf8               x$3
  #731 = Utf8               $anonfun$atZ$1
  #732 = Utf8               i$3
  #733 = Utf8               java/lang/StringBuilder
  #734 = Class              #733          // java/lang/StringBuilder
  #735 = Integer            24
  #736 = Utf8               (I)V
  #737 = NameAndType        #440:#736     // "<init>":(I)V
  #738 = Methodref          #734.#737     // java/lang/StringBuilder."<init>":(I)V
  #739 = Utf8               Indexing out of bounds:
  #740 = String             #739          // Indexing out of bounds:
  #741 = Utf8               append
  #742 = Utf8               (Ljava/lang/String;)Ljava/lang/StringBuilder;
  #743 = NameAndType        #741:#742     // append:(Ljava/lang/String;)Ljava/lang/StringBuilder;
  #744 = Methodref          #734.#743     // java/lang/StringBuilder.append:(Ljava/lang/String;)Ljava/lang/StringBuilder;
  #745 = Utf8               (Ljava/lang/Object;)Ljava/lang/StringBuilder;
  #746 = NameAndType        #741:#745     // append:(Ljava/lang/Object;)Ljava/lang/StringBuilder;
  #747 = Methodref          #734.#746     // java/lang/StringBuilder.append:(Ljava/lang/Object;)Ljava/lang/StringBuilder;
  #748 = Methodref          #734.#683     // java/lang/StringBuilder.toString:()Ljava/lang/String;
  #749 = Utf8               $anonfun$flatMap$3
  #750 = Utf8               (Lscala/runtime/ObjectRef;Lscala/Function1;Ljava/lang/Object;)V
  #751 = Utf8               r$2
  #752 = Utf8               f$2
  #753 = NameAndType        #272:#273     // $plus$plus:(Lorg/sireum/IS;)Lorg/sireum/IS;
  #754 = Methodref          #2.#753       // org/sireum/IS.$plus$plus:(Lorg/sireum/IS;)Lorg/sireum/IS;
  #755 = Utf8               firstIndex can only be used on non-empty IS
  #756 = String             #755          // firstIndex can only be used on non-empty IS
  #757 = Utf8               lastIndex can only be used on non-empty IS
  #758 = String             #757          // lastIndex can only be used on non-empty IS
  #759 = Utf8               $anonfun$lastIndex$2
  #760 = Utf8               (Lscala/runtime/ObjectRef;Lorg/sireum/Z;)V
  #761 = Utf8               r$3
  #762 = Utf8               x$4
  #763 = Utf8               scala/runtime/BoxedUnit
  #764 = Class              #763          // scala/runtime/BoxedUnit
  #765 = Utf8               UNIT
  #766 = Utf8               Lscala/runtime/BoxedUnit;
  #767 = NameAndType        #765:#766     // UNIT:Lscala/runtime/BoxedUnit;
  #768 = Fieldref           #764.#767     // scala/runtime/BoxedUnit.UNIT:Lscala/runtime/BoxedUnit;
  #769 = Utf8               $anonfun$apply$2
  #770 = Utf8               (Lscala/Tuple2;)Z
  #771 = Utf8               check$ifrefutable$1
  #772 = Utf8               Lscala/Tuple2;
  #773 = Utf8               $anonfun$apply$4
  #774 = Utf8               i$4
  #775 = Utf8               $anonfun$apply$5
  #776 = Utf8               (Ljava/lang/Object;)Ljava/lang/String;
  #777 = Utf8               index$1
  #778 = Utf8               $anonfun$apply$3
  #779 = Utf8               (Lorg/sireum/IS;Ljava/lang/Object;Lscala/Tuple2;)V
  #780 = Utf8               a$3
  #781 = Utf8               x$5
  #782 = Utf8               _1
  #783 = NameAndType        #782:#130     // _1:()Ljava/lang/Object;
  #784 = Methodref          #636.#783     // scala/Tuple2._1:()Ljava/lang/Object;
  #785 = Utf8               _2
  #786 = NameAndType        #785:#130     // _2:()Ljava/lang/Object;
  #787 = Methodref          #636.#786     // scala/Tuple2._2:()Ljava/lang/Object;
  #788 = Utf8               $anonfun$apply$4$adapted
  #789 = NameAndType        #788:#200     // $anonfun$apply$4$adapted:(Lorg/sireum/IS;Lorg/sireum/Z;)Ljava/lang/Object;
  #790 = Methodref          #2.#789       // org/sireum/IS.$anonfun$apply$4$adapted:(Lorg/sireum/IS;Lorg/sireum/Z;)Ljava/lang/Object;
  #791 = MethodHandle       6:#790        // REF_invokeStatic org/sireum/IS.$anonfun$apply$4$adapted:(Lorg/sireum/IS;Lorg/sireum/Z;)Ljava/lang/Object;
  #792 = InvokeDynamic      #17:#213      // #17:apply:(Lorg/sireum/IS;Lorg/sireum/Z;)Lscala/Function0;
  #793 = NameAndType        #775:#776     // $anonfun$apply$5:(Ljava/lang/Object;)Ljava/lang/String;
  #794 = Methodref          #2.#793       // org/sireum/IS.$anonfun$apply$5:(Ljava/lang/Object;)Ljava/lang/String;
  #795 = MethodHandle       6:#794        // REF_invokeStatic org/sireum/IS.$anonfun$apply$5:(Ljava/lang/Object;)Ljava/lang/String;
  #796 = Utf8               (Ljava/lang/Object;)Lscala/Function0;
  #797 = NameAndType        #148:#796     // apply:(Ljava/lang/Object;)Lscala/Function0;
  #798 = InvokeDynamic      #18:#797      // #18:apply:(Ljava/lang/Object;)Lscala/Function0;
  #799 = Utf8               scala/MatchError
  #800 = Class              #799          // scala/MatchError
  #801 = Utf8               (Ljava/lang/Object;)V
  #802 = NameAndType        #440:#801     // "<init>":(Ljava/lang/Object;)V
  #803 = Methodref          #800.#802     // scala/MatchError."<init>":(Ljava/lang/Object;)V
  #804 = Utf8               v
  #805 = Utf8               $anonfun$equals$1
  #806 = Utf8               (Lorg/sireum/$internal/Boxer;Ljava/lang/Object;Lorg/sireum/$internal/Boxer;Ljava/lang/Object;Ljava/lang/Object;Lorg/sireum/Z;)V
  #807 = Utf8               b1$1
  #808 = Utf8               data1$1
  #809 = Utf8               b2$1
  #810 = Utf8               data2$1
  #811 = Utf8               nonLocalReturnKey1$1
  #812 = InterfaceMethodref #39.#180      // org/sireum/Z.toMP:()Lorg/sireum/Z;
  #813 = Utf8               scala/runtime/NonLocalReturnControl$mcZ$sp
  #814 = Class              #813          // scala/runtime/NonLocalReturnControl$mcZ$sp
  #815 = Utf8               (Ljava/lang/Object;Z)V
  #816 = NameAndType        #440:#815     // "<init>":(Ljava/lang/Object;Z)V
  #817 = Methodref          #814.#816     // scala/runtime/NonLocalReturnControl$mcZ$sp."<init>":(Ljava/lang/Object;Z)V
  #818 = Utf8               (Lorg/sireum/$ZCompanion<TI;>;Ljava/lang/Object;Lorg/sireum/Z;Lorg/sireum/$internal/Boxer;)V
  #819 = Utf8               $init$
  #820 = Utf8               (Lorg/sireum/$internal/ImmutableMarker;)V
  #821 = NameAndType        #819:#820     // $init$:(Lorg/sireum/$internal/ImmutableMarker;)V
  #822 = InterfaceMethodref #121.#821     // org/sireum/$internal/ImmutableMarker.$init$:(Lorg/sireum/$internal/ImmutableMarker;)V
  #823 = Utf8               (Lorg/sireum/Immutable;)V
  #824 = NameAndType        #819:#823     // $init$:(Lorg/sireum/Immutable;)V
  #825 = InterfaceMethodref #7.#824       // org/sireum/Immutable.$init$:(Lorg/sireum/Immutable;)V
  #826 = NameAndType        #693:#694     // $anonfun$isInBound$1:(Lorg/sireum/IS;Lorg/sireum/Z;)Z
  #827 = Methodref          #2.#826       // org/sireum/IS.$anonfun$isInBound$1:(Lorg/sireum/IS;Lorg/sireum/Z;)Z
  #828 = Utf8               (Z)V
  #829 = NameAndType        #440:#828     // "<init>":(Z)V
  #830 = Methodref          #511.#829     // org/sireum/B."<init>":(Z)V
  #831 = NameAndType        #697:#698     // $anonfun$$minus$minus$1:(Lorg/sireum/IS;)Z
  #832 = Methodref          #2.#831       // org/sireum/IS.$anonfun$$minus$minus$1:(Lorg/sireum/IS;)Z
  #833 = NameAndType        #700:#701     // $anonfun$$minus$minus$2:(Lscala/collection/immutable/Seq;Ljava/lang/Object;)Z
  #834 = Methodref          #2.#833       // org/sireum/IS.$anonfun$$minus$minus$2:(Lscala/collection/immutable/Seq;Ljava/lang/Object;)Z
  #835 = Utf8               boxToBoolean
  #836 = Utf8               (Z)Ljava/lang/Boolean;
  #837 = NameAndType        #835:#836     // boxToBoolean:(Z)Ljava/lang/Boolean;
  #838 = Methodref          #704.#837     // scala/runtime/BoxesRunTime.boxToBoolean:(Z)Ljava/lang/Boolean;
  #839 = NameAndType        #711:#712     // $anonfun$$minus$minus$3:(Lscala/runtime/ObjectRef;Ljava/lang/Object;)V
  #840 = Methodref          #2.#839       // org/sireum/IS.$anonfun$$minus$minus$3:(Lscala/runtime/ObjectRef;Ljava/lang/Object;)V
  #841 = NameAndType        #724:#725     // $anonfun$$minus$minus$6:(Lorg/sireum/IS;Ljava/lang/Object;Lscala/runtime/ObjectRef;Ljava/lang/Object;)V
  #842 = Methodref          #2.#841       // org/sireum/IS.$anonfun$$minus$minus$6:(Lorg/sireum/IS;Ljava/lang/Object;Lscala/runtime/ObjectRef;Ljava/lang/Object;)V
  #843 = NameAndType        #728:#705     // $anonfun$$minus$1:(Ljava/lang/Object;Ljava/lang/Object;)Z
  #844 = Methodref          #2.#843       // org/sireum/IS.$anonfun$$minus$1:(Ljava/lang/Object;Ljava/lang/Object;)Z
  #845 = NameAndType        #731:#694     // $anonfun$atZ$1:(Lorg/sireum/IS;Lorg/sireum/Z;)Z
  #846 = Methodref          #2.#845       // org/sireum/IS.$anonfun$atZ$1:(Lorg/sireum/IS;Lorg/sireum/Z;)Z
  #847 = NameAndType        #749:#750     // $anonfun$flatMap$3:(Lscala/runtime/ObjectRef;Lscala/Function1;Ljava/lang/Object;)V
  #848 = Methodref          #2.#847       // org/sireum/IS.$anonfun$flatMap$3:(Lscala/runtime/ObjectRef;Lscala/Function1;Ljava/lang/Object;)V
  #849 = NameAndType        #759:#760     // $anonfun$lastIndex$2:(Lscala/runtime/ObjectRef;Lorg/sireum/Z;)V
  #850 = Methodref          #2.#849       // org/sireum/IS.$anonfun$lastIndex$2:(Lscala/runtime/ObjectRef;Lorg/sireum/Z;)V
  #851 = NameAndType        #769:#770     // $anonfun$apply$2:(Lscala/Tuple2;)Z
  #852 = Methodref          #2.#851       // org/sireum/IS.$anonfun$apply$2:(Lscala/Tuple2;)Z
  #853 = NameAndType        #778:#779     // $anonfun$apply$3:(Lorg/sireum/IS;Ljava/lang/Object;Lscala/Tuple2;)V
  #854 = Methodref          #2.#853       // org/sireum/IS.$anonfun$apply$3:(Lorg/sireum/IS;Ljava/lang/Object;Lscala/Tuple2;)V
  #855 = NameAndType        #805:#806     // $anonfun$equals$1:(Lorg/sireum/$internal/Boxer;Ljava/lang/Object;Lorg/sireum/$internal/Boxer;Ljava/lang/Object;Ljava/lang/Object;Lorg/sireum/Z;)V
  #856 = Methodref          #2.#855       // org/sireum/IS.$anonfun$equals$1:(Lorg/sireum/$internal/Boxer;Ljava/lang/Object;Lorg/sireum/$internal/Boxer;Ljava/lang/Object;Ljava/lang/Object;Lorg/sireum/Z;)V
  #857 = NameAndType        #708:#705     // $anonfun$$minus$minus$4:(Ljava/lang/Object;Ljava/lang/Object;)Z
  #858 = Methodref          #2.#857       // org/sireum/IS.$anonfun$$minus$minus$4:(Ljava/lang/Object;Ljava/lang/Object;)Z
  #859 = NameAndType        #773:#694     // $anonfun$apply$4:(Lorg/sireum/IS;Lorg/sireum/Z;)Z
  #860 = Methodref          #2.#859       // org/sireum/IS.$anonfun$apply$4:(Lorg/sireum/IS;Lorg/sireum/Z;)Z
  #861 = Utf8               $deserializeLambda$
  #862 = Utf8               (Ljava/lang/invoke/SerializedLambda;)Ljava/lang/Object;
  #863 = Utf8               scala/runtime/LambdaDeserialize
  #864 = Class              #863          // scala/runtime/LambdaDeserialize
  #865 = Utf8               bootstrap
  #866 = Utf8               (Ljava/lang/invoke/MethodHandles$Lookup;Ljava/lang/String;Ljava/lang/invoke/MethodType;[Ljava/lang/invoke/MethodHandle;)Ljava/lang/invoke/CallSite;
  #867 = NameAndType        #865:#866     // bootstrap:(Ljava/lang/invoke/MethodHandles$Lookup;Ljava/lang/String;Ljava/lang/invoke/MethodType;[Ljava/lang/invoke/MethodHandle;)Ljava/lang/invoke/CallSite;
  #868 = Methodref          #864.#867     // scala/runtime/LambdaDeserialize.bootstrap:(Ljava/lang/invoke/MethodHandles$Lookup;Ljava/lang/String;Ljava/lang/invoke/MethodType;[Ljava/lang/invoke/MethodHandle;)Ljava/lang/invoke/CallSite;
  #869 = MethodHandle       6:#868        // REF_invokeStatic scala/runtime/LambdaDeserialize.bootstrap:(Ljava/lang/invoke/MethodHandles$Lookup;Ljava/lang/String;Ljava/lang/invoke/MethodType;[Ljava/lang/invoke/MethodHandle;)Ljava/lang/invoke/CallSite;
  #870 = Utf8               lambdaDeserialize
  #871 = NameAndType        #870:#862     // lambdaDeserialize:(Ljava/lang/invoke/SerializedLambda;)Ljava/lang/Object;
  #872 = InvokeDynamic      #19:#871      // #19:lambdaDeserialize:(Ljava/lang/invoke/SerializedLambda;)Ljava/lang/Object;
  #873 = Utf8               Signature
  #874 = Utf8               Code
  #875 = Utf8               LocalVariableTable
  #876 = Utf8               MethodParameters
  #877 = Utf8               LineNumberTable
  #878 = Utf8               StackMapTable
  #879 = Utf8               InnerClasses
  #880 = Utf8               SourceFile
  #881 = Utf8               RuntimeVisibleAnnotations
  #882 = Utf8               BootstrapMethods
  #883 = Utf8               ScalaInlineInfo
  #884 = Utf8               ScalaSig
{
  private int hashCode;
    descriptor: I
    flags: (0x0002) ACC_PRIVATE

  private final org.sireum.$ZCompanion<I> companion;
    descriptor: Lorg/sireum/$ZCompanion;
    flags: (0x0012) ACC_PRIVATE, ACC_FINAL
    Signature: #55                          // Lorg/sireum/$ZCompanion<TI;>;

  private final java.lang.Object data;
    descriptor: Ljava/lang/Object;
    flags: (0x0012) ACC_PRIVATE, ACC_FINAL

  private final org.sireum.Z length;
    descriptor: Lorg/sireum/Z;
    flags: (0x0012) ACC_PRIVATE, ACC_FINAL

  private final org.sireum.$internal.Boxer boxer;
    descriptor: Lorg/sireum/$internal/Boxer;
    flags: (0x0012) ACC_PRIVATE, ACC_FINAL

  private volatile boolean bitmap$0;
    descriptor: Z
    flags: (0x0042) ACC_PRIVATE, ACC_VOLATILE

  public static <I extends java.lang.Object, V extends java.lang.Object> scala.Option<scala.collection.immutable.Seq<V>> unapplySeq(org.sireum.IS<I, V>);
    descriptor: (Lorg/sireum/IS;)Lscala/Option;
    flags: (0x0009) ACC_PUBLIC, ACC_STATIC
    Code:
      stack=2, locals=1, args_size=1
         0: getstatic     #73                 // Field org/sireum/IS$.MODULE$:Lorg/sireum/IS$;
         3: aload_0
         4: invokevirtual #75                 // Method org/sireum/IS$.unapplySeq:(Lorg/sireum/IS;)Lscala/Option;
         7: areturn
      LocalVariableTable:
        Start  Length  Slot  Name   Signature
            0       8     0     o   Lorg/sireum/IS;
    Signature: #66                          // <I:Ljava/lang/Object;V:Ljava/lang/Object;>(Lorg/sireum/IS<TI;TV;>;)Lscala/Option<Lscala/collection/immutable/Seq<TV;>;>;
    MethodParameters:
      Name                           Flags
      o                              final

  public static <I extends java.lang.Object, V extends java.lang.Object> org.sireum.IS<I, V> create(org.sireum.Z, V, org.sireum.$ZCompanion<I>);
    descriptor: (Lorg/sireum/Z;Ljava/lang/Object;Lorg/sireum/$ZCompanion;)Lorg/sireum/IS;
    flags: (0x0009) ACC_PUBLIC, ACC_STATIC
    Code:
      stack=4, locals=3, args_size=3
         0: getstatic     #73                 // Field org/sireum/IS$.MODULE$:Lorg/sireum/IS$;
         3: aload_0
         4: aload_1
         5: aload_2
         6: invokevirtual #83                 // Method org/sireum/IS$.create:(Lorg/sireum/Z;Ljava/lang/Object;Lorg/sireum/$ZCompanion;)Lorg/sireum/IS;
         9: areturn
      LocalVariableTable:
        Start  Length  Slot  Name   Signature
            0      10     0  size   Lorg/sireum/Z;
            0      10     1 default   Ljava/lang/Object;
            0      10     2 companion   Lorg/sireum/$ZCompanion;
    Signature: #79                          // <I:Ljava/lang/Object;V:Ljava/lang/Object;>(Lorg/sireum/Z;TV;Lorg/sireum/$ZCompanion<TI;>;)Lorg/sireum/IS<TI;TV;>;
    MethodParameters:
      Name                           Flags
      size                           final
      default                        final
      companion                      final

  public static <I extends java.lang.Object> void checkSize(org.sireum.Z, org.sireum.$ZCompanion<I>);
    descriptor: (Lorg/sireum/Z;Lorg/sireum/$ZCompanion;)V
    flags: (0x0009) ACC_PUBLIC, ACC_STATIC
    Code:
      stack=3, locals=2, args_size=2
         0: getstatic     #73                 // Field org/sireum/IS$.MODULE$:Lorg/sireum/IS$;
         3: aload_0
         4: aload_1
         5: invokevirtual #88                 // Method org/sireum/IS$.checkSize:(Lorg/sireum/Z;Lorg/sireum/$ZCompanion;)V
         8: return
      LocalVariableTable:
        Start  Length  Slot  Name   Signature
            0       9     0  size   Lorg/sireum/Z;
            0       9     1 companion   Lorg/sireum/$ZCompanion;
    Signature: #86                          // <I:Ljava/lang/Object;>(Lorg/sireum/Z;Lorg/sireum/$ZCompanion<TI;>;)V
    MethodParameters:
      Name                           Flags
      size                           final
      companion                      final

  public void forEach(java.util.function.Consumer<? super V>);
    descriptor: (Ljava/util/function/Consumer;)V
    flags: (0x0001) ACC_PUBLIC
    Code:
      stack=2, locals=2, args_size=2
         0: aload_0
         1: aload_1
         2: invokespecial #94                 // InterfaceMethod java/lang/Iterable.forEach:(Ljava/util/function/Consumer;)V
         5: return
      LineNumberTable:
        line 123: 0
      LocalVariableTable:
        Start  Length  Slot  Name   Signature
            0       6     0  this   Lorg/sireum/IS;
            0       6     1   x$1   Ljava/util/function/Consumer;
    Signature: #91                          // (Ljava/util/function/Consumer<-TV;>;)V
    MethodParameters:
      Name                           Flags
      x$1                            final

  public java.util.Spliterator<V> spliterator();
    descriptor: ()Ljava/util/Spliterator;
    flags: (0x0001) ACC_PUBLIC
    Code:
      stack=1, locals=1, args_size=1
         0: aload_0
         1: invokespecial #101                // InterfaceMethod java/lang/Iterable.spliterator:()Ljava/util/Spliterator;
         4: areturn
      LineNumberTable:
        line 123: 0
      LocalVariableTable:
        Start  Length  Slot  Name   Signature
            0       5     0  this   Lorg/sireum/IS;
    Signature: #99                          // ()Ljava/util/Spliterator<TV;>;

  public final scala.runtime.Nothing$ $cannotMixImmutableAndMutable();
    descriptor: ()Lscala/runtime/Nothing$;
    flags: (0x0011) ACC_PUBLIC, ACC_FINAL
    Code:
      stack=1, locals=1, args_size=1
         0: aload_0
         1: invokestatic  #107                // InterfaceMethod org/sireum/Immutable.$cannotMixImmutableAndMutable$:(Lorg/sireum/Immutable;)Lscala/runtime/Nothing$;
         4: areturn
      LineNumberTable:
        line 123: 0
      LocalVariableTable:
        Start  Length  Slot  Name   Signature
            0       5     0  this   Lorg/sireum/IS;

  public boolean $hasEquals();
    descriptor: ()Z
    flags: (0x0001) ACC_PUBLIC
    Code:
      stack=1, locals=1, args_size=1
         0: aload_0
         1: invokestatic  #113                // InterfaceMethod org/sireum/Immutable.$hasEquals$:(Lorg/sireum/Immutable;)Z
         4: ireturn
      LineNumberTable:
        line 123: 0
      LocalVariableTable:
        Start  Length  Slot  Name   Signature
            0       5     0  this   Lorg/sireum/IS;

  public boolean $hasString();
    descriptor: ()Z
    flags: (0x0001) ACC_PUBLIC
    Code:
      stack=1, locals=1, args_size=1
         0: aload_0
         1: invokestatic  #117                // InterfaceMethod org/sireum/Immutable.$hasString$:(Lorg/sireum/Immutable;)Z
         4: ireturn
      LineNumberTable:
        line 123: 0
      LocalVariableTable:
        Start  Length  Slot  Name   Signature
            0       5     0  this   Lorg/sireum/IS;

  public org.sireum.$internal.ImmutableMarker $clone();
    descriptor: ()Lorg/sireum/$internal/ImmutableMarker;
    flags: (0x0001) ACC_PUBLIC
    Code:
      stack=1, locals=1, args_size=1
         0: aload_0
         1: invokestatic  #125                // InterfaceMethod org/sireum/$internal/ImmutableMarker.$clone$:(Lorg/sireum/$internal/ImmutableMarker;)Lorg/sireum/$internal/ImmutableMarker;
         4: areturn
      LineNumberTable:
        line 123: 0
      LocalVariableTable:
        Start  Length  Slot  Name   Signature
            0       5     0  this   Lorg/sireum/IS;

  public org.sireum.$ZCompanion<I> companion();
    descriptor: ()Lorg/sireum/$ZCompanion;
    flags: (0x0001) ACC_PUBLIC
    Code:
      stack=1, locals=1, args_size=1
         0: aload_0
         1: getfield      #129                // Field companion:Lorg/sireum/$ZCompanion;
         4: areturn
      LineNumberTable:
        line 123: 0
      LocalVariableTable:
        Start  Length  Slot  Name   Signature
            0       5     0  this   Lorg/sireum/IS;
    Signature: #127                         // ()Lorg/sireum/$ZCompanion<TI;>;

  public java.lang.Object data();
    descriptor: ()Ljava/lang/Object;
    flags: (0x0001) ACC_PUBLIC
    Code:
      stack=1, locals=1, args_size=1
         0: aload_0
         1: getfield      #132                // Field data:Ljava/lang/Object;
         4: areturn
      LineNumberTable:
        line 123: 0
      LocalVariableTable:
        Start  Length  Slot  Name   Signature
            0       5     0  this   Lorg/sireum/IS;

  public org.sireum.Z length();
    descriptor: ()Lorg/sireum/Z;
    flags: (0x0001) ACC_PUBLIC
    Code:
      stack=1, locals=1, args_size=1
         0: aload_0
         1: getfield      #135                // Field length:Lorg/sireum/Z;
         4: areturn
      LineNumberTable:
        line 123: 0
      LocalVariableTable:
        Start  Length  Slot  Name   Signature
            0       5     0  this   Lorg/sireum/IS;

  public org.sireum.$internal.Boxer boxer();
    descriptor: ()Lorg/sireum/$internal/Boxer;
    flags: (0x0001) ACC_PUBLIC
    Code:
      stack=1, locals=1, args_size=1
         0: aload_0
         1: getfield      #138                // Field boxer:Lorg/sireum/$internal/Boxer;
         4: areturn
      LineNumberTable:
        line 123: 0
      LocalVariableTable:
        Start  Length  Slot  Name   Signature
            0       5     0  this   Lorg/sireum/IS;

  public org.sireum.Z hash();
    descriptor: ()Lorg/sireum/Z;
    flags: (0x0001) ACC_PUBLIC
    Code:
      stack=2, locals=1, args_size=1
         0: getstatic     #144                // Field org/sireum/Z$.MODULE$:Lorg/sireum/Z$;
         3: aload_0
         4: invokevirtual #147                // Method hashCode:()I
         7: invokevirtual #151                // Method org/sireum/Z$.apply:(I)Lorg/sireum/Z;
        10: areturn
      LineNumberTable:
        line 126: 0
      LocalVariableTable:
        Start  Length  Slot  Name   Signature
            0      11     0  this   Lorg/sireum/IS;

  public boolean isEmpty();
    descriptor: ()Z
    flags: (0x0001) ACC_PUBLIC
    Code:
      stack=3, locals=2, args_size=1
         0: getstatic     #157                // Field org/sireum/B$.MODULE$:Lorg/sireum/B$;
         3: aload_0
         4: invokevirtual #159                // Method length:()Lorg/sireum/Z;
         7: getstatic     #162                // Field org/sireum/Z$MP$.MODULE$:Lorg/sireum/Z$MP$;
        10: invokevirtual #165                // Method org/sireum/Z$MP$.zero:()Lorg/sireum/Z;
        13: astore_1
        14: dup
        15: ifnonnull     26
        18: pop
        19: aload_1
        20: ifnull        33
        23: goto          37
        26: aload_1
        27: invokevirtual #169                // Method java/lang/Object.equals:(Ljava/lang/Object;)Z
        30: ifeq          37
        33: iconst_1
        34: goto          38
        37: iconst_0
        38: invokevirtual #172                // Method org/sireum/B$.apply:(Z)Z
        41: ireturn
      StackMapTable: number_of_entries = 4
        frame_type = 255 /* full_frame */
          offset_delta = 26
          locals = [ class org/sireum/IS, class org/sireum/Z ]
          stack = [ class org/sireum/B$, class org/sireum/Z ]
        frame_type = 70 /* same_locals_1_stack_item */
          stack = [ class org/sireum/B$ ]
        frame_type = 67 /* same_locals_1_stack_item */
          stack = [ class org/sireum/B$ ]
        frame_type = 255 /* full_frame */
          offset_delta = 0
          locals = [ class org/sireum/IS, class org/sireum/Z ]
          stack = [ class org/sireum/B$, int ]
      LineNumberTable:
        line 128: 0
      LocalVariableTable:
        Start  Length  Slot  Name   Signature
            0      42     0  this   Lorg/sireum/IS;

  public boolean nonEmpty();
    descriptor: ()Z
    flags: (0x0001) ACC_PUBLIC
    Code:
      stack=3, locals=2, args_size=1
         0: getstatic     #157                // Field org/sireum/B$.MODULE$:Lorg/sireum/B$;
         3: aload_0
         4: invokevirtual #159                // Method length:()Lorg/sireum/Z;
         7: getstatic     #162                // Field org/sireum/Z$MP$.MODULE$:Lorg/sireum/Z$MP$;
        10: invokevirtual #165                // Method org/sireum/Z$MP$.zero:()Lorg/sireum/Z;
        13: astore_1
        14: dup
        15: ifnonnull     26
        18: pop
        19: aload_1
        20: ifnull        37
        23: goto          33
        26: aload_1
        27: invokevirtual #169                // Method java/lang/Object.equals:(Ljava/lang/Object;)Z
        30: ifne          37
        33: iconst_1
        34: goto          38
        37: iconst_0
        38: invokevirtual #172                // Method org/sireum/B$.apply:(Z)Z
        41: ireturn
      StackMapTable: number_of_entries = 4
        frame_type = 255 /* full_frame */
          offset_delta = 26
          locals = [ class org/sireum/IS, class org/sireum/Z ]
          stack = [ class org/sireum/B$, class org/sireum/Z ]
        frame_type = 70 /* same_locals_1_stack_item */
          stack = [ class org/sireum/B$ ]
        frame_type = 67 /* same_locals_1_stack_item */
          stack = [ class org/sireum/B$ ]
        frame_type = 255 /* full_frame */
          offset_delta = 0
          locals = [ class org/sireum/IS, class org/sireum/Z ]
          stack = [ class org/sireum/B$, int ]
      LineNumberTable:
        line 130: 0
      LocalVariableTable:
        Start  Length  Slot  Name   Signature
            0      42     0  this   Lorg/sireum/IS;

  public boolean isInBound(I);
    descriptor: (Ljava/lang/Object;)Z
    flags: (0x0001) ACC_PUBLIC
    Code:
      stack=4, locals=3, args_size=2
         0: aload_1
         1: checkcast     #178                // class org/sireum/ZLike
         4: invokeinterface #181,  1          // InterfaceMethod org/sireum/ZLike.toMP:()Lorg/sireum/Z;
         9: astore_2
        10: getstatic     #157                // Field org/sireum/B$.MODULE$:Lorg/sireum/B$;
        13: getstatic     #184                // Field org/sireum/package$$Int2Z$.MODULE$:Lorg/sireum/package$$Int2Z$;
        16: getstatic     #189                // Field org/sireum/package$.MODULE$:Lorg/sireum/package$;
        19: iconst_0
        20: invokevirtual #193                // Method org/sireum/package$.$Int2Z:(I)I
        23: aload_2
        24: invokevirtual #197                // Method org/sireum/package$$Int2Z$.$less$eq$extension:(ILorg/sireum/Z;)Z
        27: aload_0
        28: aload_2
        29: invokedynamic #214,  0            // InvokeDynamic #0:apply:(Lorg/sireum/IS;Lorg/sireum/Z;)Lscala/Function0;
        34: invokevirtual #218                // Method org/sireum/B$.$amp$amp$extension:(ZLscala/Function0;)Z
        37: ireturn
      LineNumberTable:
        line 133: 0
        line 134: 16
      LocalVariableTable:
        Start  Length  Slot  Name   Signature
           10      27     2   iMP   Lorg/sireum/Z;
            0      38     0  this   Lorg/sireum/IS;
            0      38     1     i   Ljava/lang/Object;
    Signature: #175                         // (TI;)Z
    MethodParameters:
      Name                           Flags
      i                              final

  public org.sireum.IS<I, V> $colon$plus(V);
    descriptor: (Ljava/lang/Object;)Lorg/sireum/IS;
    flags: (0x0001) ACC_PUBLIC
    Code:
      stack=6, locals=4, args_size=2
         0: getstatic     #157                // Field org/sireum/B$.MODULE$:Lorg/sireum/B$;
         3: aload_0
         4: invokevirtual #225                // Method isEmpty:()Z
         7: invokevirtual #228                // Method org/sireum/B$.$4B:(Z)Z
        10: ifeq          40
        13: getstatic     #73                 // Field org/sireum/IS$.MODULE$:Lorg/sireum/IS$;
        16: getstatic     #233                // Field scala/runtime/ScalaRunTime$.MODULE$:Lscala/runtime/ScalaRunTime$;
        19: iconst_1
        20: anewarray     #5                  // class java/lang/Object
        23: dup
        24: iconst_0
        25: aload_1
        26: aastore
        27: invokevirtual #237                // Method scala/runtime/ScalaRunTime$.genericWrapArray:(Ljava/lang/Object;)Lscala/collection/immutable/ArraySeq;
        30: aload_0
        31: invokevirtual #239                // Method companion:()Lorg/sireum/$ZCompanion;
        34: invokevirtual #242                // Method org/sireum/IS$.apply:(Lscala/collection/immutable/Seq;Lorg/sireum/$ZCompanion;)Lorg/sireum/IS;
        37: goto          119
        40: aload_0
        41: invokevirtual #159                // Method length:()Lorg/sireum/Z;
        44: invokeinterface #245,  1          // InterfaceMethod org/sireum/Z.increase:()Lorg/sireum/Z;
        49: astore_2
        50: getstatic     #73                 // Field org/sireum/IS$.MODULE$:Lorg/sireum/IS$;
        53: aload_2
        54: getstatic     #189                // Field org/sireum/package$.MODULE$:Lorg/sireum/package$;
        57: invokevirtual #248                // Method org/sireum/package$.$ZCompanion:()Lorg/sireum/$ZCompanion;
        60: invokevirtual #88                 // Method org/sireum/IS$.checkSize:(Lorg/sireum/Z;Lorg/sireum/$ZCompanion;)V
        63: aload_0
        64: invokevirtual #250                // Method boxer:()Lorg/sireum/$internal/Boxer;
        67: aload_0
        68: invokevirtual #252                // Method data:()Ljava/lang/Object;
        71: aload_0
        72: invokevirtual #159                // Method length:()Lorg/sireum/Z;
        75: aload_2
        76: getstatic     #162                // Field org/sireum/Z$MP$.MODULE$:Lorg/sireum/Z$MP$;
        79: invokevirtual #165                // Method org/sireum/Z$MP$.zero:()Lorg/sireum/Z;
        82: invokeinterface #258,  5          // InterfaceMethod org/sireum/$internal/Boxer.clone:(Ljava/lang/Object;Lorg/sireum/Z;Lorg/sireum/Z;Lorg/sireum/Z;)Ljava/lang/Object;
        87: astore_3
        88: aload_0
        89: invokevirtual #250                // Method boxer:()Lorg/sireum/$internal/Boxer;
        92: aload_3
        93: aload_0
        94: invokevirtual #159                // Method length:()Lorg/sireum/Z;
        97: aload_1
        98: invokeinterface #262,  4          // InterfaceMethod org/sireum/$internal/Boxer.store:(Ljava/lang/Object;Lorg/sireum/Z;Ljava/lang/Object;)V
       103: getstatic     #73                 // Field org/sireum/IS$.MODULE$:Lorg/sireum/IS$;
       106: aload_0
       107: invokevirtual #239                // Method companion:()Lorg/sireum/$ZCompanion;
       110: aload_3
       111: aload_2
       112: aload_0
       113: invokevirtual #250                // Method boxer:()Lorg/sireum/$internal/Boxer;
       116: invokevirtual #265                // Method org/sireum/IS$.apply:(Lorg/sireum/$ZCompanion;Ljava/lang/Object;Lorg/sireum/Z;Lorg/sireum/$internal/Boxer;)Lorg/sireum/IS;
       119: areturn
      StackMapTable: number_of_entries = 2
        frame_type = 40 /* same */
        frame_type = 247 /* same_locals_1_stack_item_frame_extended */
          offset_delta = 78
          stack = [ class org/sireum/IS ]
      LineNumberTable:
        line 138: 0
        line 140: 40
        line 141: 50
        line 142: 63
        line 143: 88
        line 144: 103
      LocalVariableTable:
        Start  Length  Slot  Name   Signature
           50      69     2 newLength   Lorg/sireum/Z;
           88      31     3     a   Ljava/lang/Object;
            0     120     0  this   Lorg/sireum/IS;
            0     120     1     e   Ljava/lang/Object;
    Signature: #222                         // (TV;)Lorg/sireum/IS<TI;TV;>;
    MethodParameters:
      Name                           Flags
      e                              final

  public org.sireum.IS<I, V> $plus$colon(V);
    descriptor: (Ljava/lang/Object;)Lorg/sireum/IS;
    flags: (0x0001) ACC_PUBLIC
    Code:
      stack=6, locals=4, args_size=2
         0: getstatic     #157                // Field org/sireum/B$.MODULE$:Lorg/sireum/B$;
         3: aload_0
         4: invokevirtual #225                // Method isEmpty:()Z
         7: invokevirtual #228                // Method org/sireum/B$.$4B:(Z)Z
        10: ifeq          40
        13: getstatic     #73                 // Field org/sireum/IS$.MODULE$:Lorg/sireum/IS$;
        16: getstatic     #233                // Field scala/runtime/ScalaRunTime$.MODULE$:Lscala/runtime/ScalaRunTime$;
        19: iconst_1
        20: anewarray     #5                  // class java/lang/Object
        23: dup
        24: iconst_0
        25: aload_1
        26: aastore
        27: invokevirtual #237                // Method scala/runtime/ScalaRunTime$.genericWrapArray:(Ljava/lang/Object;)Lscala/collection/immutable/ArraySeq;
        30: aload_0
        31: invokevirtual #239                // Method companion:()Lorg/sireum/$ZCompanion;
        34: invokevirtual #242                // Method org/sireum/IS$.apply:(Lscala/collection/immutable/Seq;Lorg/sireum/$ZCompanion;)Lorg/sireum/IS;
        37: goto          121
        40: aload_0
        41: invokevirtual #159                // Method length:()Lorg/sireum/Z;
        44: invokeinterface #245,  1          // InterfaceMethod org/sireum/Z.increase:()Lorg/sireum/Z;
        49: astore_2
        50: getstatic     #73                 // Field org/sireum/IS$.MODULE$:Lorg/sireum/IS$;
        53: aload_2
        54: getstatic     #189                // Field org/sireum/package$.MODULE$:Lorg/sireum/package$;
        57: invokevirtual #248                // Method org/sireum/package$.$ZCompanion:()Lorg/sireum/$ZCompanion;
        60: invokevirtual #88                 // Method org/sireum/IS$.checkSize:(Lorg/sireum/Z;Lorg/sireum/$ZCompanion;)V
        63: aload_0
        64: invokevirtual #250                // Method boxer:()Lorg/sireum/$internal/Boxer;
        67: aload_0
        68: invokevirtual #252                // Method data:()Ljava/lang/Object;
        71: aload_0
        72: invokevirtual #159                // Method length:()Lorg/sireum/Z;
        75: aload_2
        76: getstatic     #162                // Field org/sireum/Z$MP$.MODULE$:Lorg/sireum/Z$MP$;
        79: invokevirtual #271                // Method org/sireum/Z$MP$.one:()Lorg/sireum/Z;
        82: invokeinterface #258,  5          // InterfaceMethod org/sireum/$internal/Boxer.clone:(Ljava/lang/Object;Lorg/sireum/Z;Lorg/sireum/Z;Lorg/sireum/Z;)Ljava/lang/Object;
        87: astore_3
        88: aload_0
        89: invokevirtual #250                // Method boxer:()Lorg/sireum/$internal/Boxer;
        92: aload_3
        93: getstatic     #162                // Field org/sireum/Z$MP$.MODULE$:Lorg/sireum/Z$MP$;
        96: invokevirtual #165                // Method org/sireum/Z$MP$.zero:()Lorg/sireum/Z;
        99: aload_1
       100: invokeinterface #262,  4          // InterfaceMethod org/sireum/$internal/Boxer.store:(Ljava/lang/Object;Lorg/sireum/Z;Ljava/lang/Object;)V
       105: getstatic     #73                 // Field org/sireum/IS$.MODULE$:Lorg/sireum/IS$;
       108: aload_0
       109: invokevirtual #239                // Method companion:()Lorg/sireum/$ZCompanion;
       112: aload_3
       113: aload_2
       114: aload_0
       115: invokevirtual #250                // Method boxer:()Lorg/sireum/$internal/Boxer;
       118: invokevirtual #265                // Method org/sireum/IS$.apply:(Lorg/sireum/$ZCompanion;Ljava/lang/Object;Lorg/sireum/Z;Lorg/sireum/$internal/Boxer;)Lorg/sireum/IS;
       121: areturn
      StackMapTable: number_of_entries = 2
        frame_type = 40 /* same */
        frame_type = 247 /* same_locals_1_stack_item_frame_extended */
          offset_delta = 80
          stack = [ class org/sireum/IS ]
      LineNumberTable:
        line 148: 0
        line 150: 40
        line 151: 50
        line 152: 63
        line 153: 88
        line 154: 105
      LocalVariableTable:
        Start  Length  Slot  Name   Signature
           50      71     2 newLength   Lorg/sireum/Z;
           88      33     3     a   Ljava/lang/Object;
            0     122     0  this   Lorg/sireum/IS;
            0     122     1     e   Ljava/lang/Object;
    Signature: #222                         // (TV;)Lorg/sireum/IS<TI;TV;>;
    MethodParameters:
      Name                           Flags
      e                              final

  public <I2 extends java.lang.Object> org.sireum.IS<I, V> $plus$plus(org.sireum.IS<I2, V>);
    descriptor: (Lorg/sireum/IS;)Lorg/sireum/IS;
    flags: (0x0001) ACC_PUBLIC
    Code:
      stack=6, locals=8, args_size=2
         0: getstatic     #157                // Field org/sireum/B$.MODULE$:Lorg/sireum/B$;
         3: aload_0
         4: invokevirtual #225                // Method isEmpty:()Z
         7: invokevirtual #228                // Method org/sireum/B$.$4B:(Z)Z
        10: ifeq          20
        13: aload_1
        14: invokevirtual #250                // Method boxer:()Lorg/sireum/$internal/Boxer;
        17: goto          24
        20: aload_0
        21: invokevirtual #250                // Method boxer:()Lorg/sireum/$internal/Boxer;
        24: astore_2
        25: aload_1
        26: invokevirtual #159                // Method length:()Lorg/sireum/Z;
        29: getstatic     #162                // Field org/sireum/Z$MP$.MODULE$:Lorg/sireum/Z$MP$;
        32: invokevirtual #165                // Method org/sireum/Z$MP$.zero:()Lorg/sireum/Z;
        35: astore_3
        36: dup
        37: ifnonnull     48
        40: pop
        41: aload_3
        42: ifnull        55
        45: goto          57
        48: aload_3
        49: invokevirtual #169                // Method java/lang/Object.equals:(Ljava/lang/Object;)Z
        52: ifeq          57
        55: aload_0
        56: areturn
        57: aload_0
        58: invokevirtual #159                // Method length:()Lorg/sireum/Z;
        61: aload_1
        62: invokevirtual #159                // Method length:()Lorg/sireum/Z;
        65: invokeinterface #279,  2          // InterfaceMethod org/sireum/Z.$plus:(Lorg/sireum/Z;)Lorg/sireum/Z;
        70: astore        4
        72: getstatic     #73                 // Field org/sireum/IS$.MODULE$:Lorg/sireum/IS$;
        75: aload         4
        77: getstatic     #189                // Field org/sireum/package$.MODULE$:Lorg/sireum/package$;
        80: invokevirtual #248                // Method org/sireum/package$.$ZCompanion:()Lorg/sireum/$ZCompanion;
        83: invokevirtual #88                 // Method org/sireum/IS$.checkSize:(Lorg/sireum/Z;Lorg/sireum/$ZCompanion;)V
        86: aload_2
        87: aload_0
        88: invokevirtual #252                // Method data:()Ljava/lang/Object;
        91: aload_0
        92: invokevirtual #159                // Method length:()Lorg/sireum/Z;
        95: aload         4
        97: getstatic     #162                // Field org/sireum/Z$MP$.MODULE$:Lorg/sireum/Z$MP$;
       100: invokevirtual #165                // Method org/sireum/Z$MP$.zero:()Lorg/sireum/Z;
       103: invokeinterface #258,  5          // InterfaceMethod org/sireum/$internal/Boxer.clone:(Ljava/lang/Object;Lorg/sireum/Z;Lorg/sireum/Z;Lorg/sireum/Z;)Ljava/lang/Object;
       108: astore        5
       110: aload_0
       111: invokevirtual #159                // Method length:()Lorg/sireum/Z;
       114: astore        6
       116: getstatic     #162                // Field org/sireum/Z$MP$.MODULE$:Lorg/sireum/Z$MP$;
       119: invokevirtual #165                // Method org/sireum/Z$MP$.zero:()Lorg/sireum/Z;
       122: astore        7
       124: getstatic     #157                // Field org/sireum/B$.MODULE$:Lorg/sireum/B$;
       127: aload         6
       129: aload         4
       131: invokeinterface #283,  2          // InterfaceMethod org/sireum/Z.$less:(Lorg/sireum/Z;)Z
       136: invokevirtual #228                // Method org/sireum/B$.$4B:(Z)Z
       139: ifeq          188
       142: aload_2
       143: aload         5
       145: aload         6
       147: aload_1
       148: invokevirtual #250                // Method boxer:()Lorg/sireum/$internal/Boxer;
       151: aload_1
       152: invokevirtual #252                // Method data:()Ljava/lang/Object;
       155: aload         7
       157: invokeinterface #287,  3          // InterfaceMethod org/sireum/$internal/Boxer.lookup:(Ljava/lang/Object;Lorg/sireum/Z;)Ljava/lang/Object;
       162: invokeinterface #262,  4          // InterfaceMethod org/sireum/$internal/Boxer.store:(Ljava/lang/Object;Lorg/sireum/Z;Ljava/lang/Object;)V
       167: aload         6
       169: invokeinterface #245,  1          // InterfaceMethod org/sireum/Z.increase:()Lorg/sireum/Z;
       174: astore        6
       176: aload         7
       178: invokeinterface #245,  1          // InterfaceMethod org/sireum/Z.increase:()Lorg/sireum/Z;
       183: astore        7
       185: goto          124
       188: getstatic     #73                 // Field org/sireum/IS$.MODULE$:Lorg/sireum/IS$;
       191: aload_0
       192: invokevirtual #239                // Method companion:()Lorg/sireum/$ZCompanion;
       195: aload         5
       197: aload         4
       199: aload_2
       200: invokevirtual #265                // Method org/sireum/IS$.apply:(Lorg/sireum/$ZCompanion;Ljava/lang/Object;Lorg/sireum/Z;Lorg/sireum/$internal/Boxer;)Lorg/sireum/IS;
       203: areturn
      StackMapTable: number_of_entries = 7
        frame_type = 20 /* same */
        frame_type = 67 /* same_locals_1_stack_item */
          stack = [ class org/sireum/$internal/Boxer ]
        frame_type = 255 /* full_frame */
          offset_delta = 23
          locals = [ class org/sireum/IS, class org/sireum/IS, class org/sireum/$internal/Boxer, class org/sireum/Z ]
          stack = [ class org/sireum/Z ]
        frame_type = 6 /* same */
        frame_type = 1 /* same */
        frame_type = 255 /* full_frame */
          offset_delta = 66
          locals = [ class org/sireum/IS, class org/sireum/IS, class org/sireum/$internal/Boxer, class org/sireum/Z, class org/sireum/Z, class java/lang/Object, class org/sireum/Z, class org/sireum/Z ]
          stack = []
        frame_type = 63 /* same */
      LineNumberTable:
        line 158: 0
        line 159: 25
        line 160: 57
        line 161: 72
        line 162: 86
        line 163: 110
        line 164: 116
        line 165: 124
        line 166: 142
        line 167: 167
        line 168: 176
        line 165: 185
        line 170: 188
      LocalVariableTable:
        Start  Length  Slot  Name   Signature
           25     178     2   bxr   Lorg/sireum/$internal/Boxer;
           72     131     4 newLength   Lorg/sireum/Z;
          110      93     5     a   Ljava/lang/Object;
          116      87     6     i   Lorg/sireum/Z;
          124      79     7     j   Lorg/sireum/Z;
            0     204     0  this   Lorg/sireum/IS;
            0     204     1 other   Lorg/sireum/IS;
    Signature: #274                         // <I2:Ljava/lang/Object;>(Lorg/sireum/IS<TI2;TV;>;)Lorg/sireum/IS<TI;TV;>;
    MethodParameters:
      Name                           Flags
      other                          final

  public <I2 extends java.lang.Object> org.sireum.IS<I, V> $minus$minus(org.sireum.IS<I2, V>);
    descriptor: (Lorg/sireum/IS;)Lorg/sireum/IS;
    flags: (0x0001) ACC_PUBLIC
    Code:
      stack=5, locals=8, args_size=2
         0: getstatic     #157                // Field org/sireum/B$.MODULE$:Lorg/sireum/B$;
         3: getstatic     #157                // Field org/sireum/B$.MODULE$:Lorg/sireum/B$;
         6: aload_0
         7: invokevirtual #225                // Method isEmpty:()Z
        10: aload_1
        11: invokedynamic #298,  0            // InvokeDynamic #1:apply:(Lorg/sireum/IS;)Lscala/Function0;
        16: invokevirtual #301                // Method org/sireum/B$.$bar$bar$extension:(ZLscala/Function0;)Z
        19: invokevirtual #228                // Method org/sireum/B$.$4B:(Z)Z
        22: ifeq          29
        25: aload_0
        26: goto          170
        29: aload_1
        30: invokevirtual #305                // Method elements:()Lscala/collection/immutable/Seq;
        33: astore_2
        34: aload_0
        35: invokevirtual #305                // Method elements:()Lscala/collection/immutable/Seq;
        38: aload_2
        39: invokedynamic #315,  0            // InvokeDynamic #2:apply:(Lscala/collection/immutable/Seq;)Lscala/Function1;
        44: invokeinterface #321,  2          // InterfaceMethod scala/collection/immutable/Seq.withFilter:(Lscala/Function1;)Lscala/collection/WithFilter;
        49: invokestatic  #326                // Method scala/runtime/ObjectRef.create:(Ljava/lang/Object;)Lscala/runtime/ObjectRef;
        52: astore_3
        53: aload_1
        54: invokevirtual #305                // Method elements:()Lscala/collection/immutable/Seq;
        57: invokeinterface #329,  1          // InterfaceMethod scala/collection/immutable/Seq.tail:()Ljava/lang/Object;
        62: checkcast     #331                // class scala/collection/IterableOnceOps
        65: aload_3
        66: invokedynamic #339,  0            // InvokeDynamic #3:apply:(Lscala/runtime/ObjectRef;)Lscala/Function1;
        71: invokeinterface #343,  2          // InterfaceMethod scala/collection/IterableOnceOps.foreach:(Lscala/Function1;)V
        76: aload_3
        77: getfield      #346                // Field scala/runtime/ObjectRef.elem:Ljava/lang/Object;
        80: checkcast     #348                // class scala/collection/WithFilter
        83: invokedynamic #355,  0            // InvokeDynamic #4:apply:()Lscala/Function1;
        88: invokevirtual #359                // Method scala/collection/WithFilter.map:(Lscala/Function1;)Ljava/lang/Object;
        91: checkcast     #317                // class scala/collection/immutable/Seq
        94: astore        4
        96: getstatic     #162                // Field org/sireum/Z$MP$.MODULE$:Lorg/sireum/Z$MP$;
        99: aload         4
       101: invokeinterface #361,  1          // InterfaceMethod scala/collection/immutable/Seq.size:()I
       106: invokevirtual #362                // Method org/sireum/Z$MP$.apply:(I)Lorg/sireum/Z;
       109: astore        5
       111: aload_0
       112: invokevirtual #250                // Method boxer:()Lorg/sireum/$internal/Boxer;
       115: aload         5
       117: invokeinterface #365,  2          // InterfaceMethod org/sireum/$internal/Boxer.create:(Lorg/sireum/Z;)Ljava/lang/Object;
       122: astore        6
       124: getstatic     #162                // Field org/sireum/Z$MP$.MODULE$:Lorg/sireum/Z$MP$;
       127: invokevirtual #165                // Method org/sireum/Z$MP$.zero:()Lorg/sireum/Z;
       130: invokestatic  #326                // Method scala/runtime/ObjectRef.create:(Ljava/lang/Object;)Lscala/runtime/ObjectRef;
       133: astore        7
       135: aload         4
       137: aload_0
       138: aload         6
       140: aload         7
       142: invokedynamic #373,  0            // InvokeDynamic #5:apply:(Lorg/sireum/IS;Ljava/lang/Object;Lscala/runtime/ObjectRef;)Lscala/Function1;
       147: invokeinterface #374,  2          // InterfaceMethod scala/collection/immutable/Seq.foreach:(Lscala/Function1;)V
       152: getstatic     #73                 // Field org/sireum/IS$.MODULE$:Lorg/sireum/IS$;
       155: aload_0
       156: invokevirtual #239                // Method companion:()Lorg/sireum/$ZCompanion;
       159: aload         6
       161: aload         5
       163: aload_0
       164: invokevirtual #250                // Method boxer:()Lorg/sireum/$internal/Boxer;
       167: invokevirtual #265                // Method org/sireum/IS$.apply:(Lorg/sireum/$ZCompanion;Ljava/lang/Object;Lorg/sireum/Z;Lorg/sireum/$internal/Boxer;)Lorg/sireum/IS;
       170: areturn
      StackMapTable: number_of_entries = 2
        frame_type = 29 /* same */
        frame_type = 247 /* same_locals_1_stack_item_frame_extended */
          offset_delta = 140
          stack = [ class org/sireum/IS ]
      LineNumberTable:
        line 174: 0
        line 176: 29
        line 177: 34
        line 178: 53
        line 181: 76
        line 182: 96
        line 183: 111
        line 184: 124
        line 185: 135
        line 189: 152
      LocalVariableTable:
        Start  Length  Slot  Name   Signature
           34     136     2 otherElements   Lscala/collection/immutable/Seq;
           53     117     3    sm   Lscala/runtime/ObjectRef;
           96      74     4     s   Lscala/collection/immutable/Seq;
          111      59     5 newLength   Lorg/sireum/Z;
          124      46     6     a   Ljava/lang/Object;
          135      35     7     i   Lscala/runtime/ObjectRef;
            0     171     0  this   Lorg/sireum/IS;
            0     171     1 other   Lorg/sireum/IS;
    Signature: #274                         // <I2:Ljava/lang/Object;>(Lorg/sireum/IS<TI2;TV;>;)Lorg/sireum/IS<TI;TV;>;
    MethodParameters:
      Name                           Flags
      other                          final

  public org.sireum.IS<I, V> $minus(V);
    descriptor: (Ljava/lang/Object;)Lorg/sireum/IS;
    flags: (0x0001) ACC_PUBLIC
    Code:
      stack=2, locals=2, args_size=2
         0: getstatic     #157                // Field org/sireum/B$.MODULE$:Lorg/sireum/B$;
         3: aload_0
         4: invokevirtual #225                // Method isEmpty:()Z
         7: invokevirtual #228                // Method org/sireum/B$.$4B:(Z)Z
        10: ifeq          17
        13: aload_0
        14: goto          27
        17: aload_0
        18: aload_1
        19: invokedynamic #388,  0            // InvokeDynamic #6:apply:(Ljava/lang/Object;)Lscala/Function1;
        24: invokevirtual #392                // Method filter:(Lscala/Function1;)Lorg/sireum/IS;
        27: areturn
      StackMapTable: number_of_entries = 2
        frame_type = 17 /* same */
        frame_type = 73 /* same_locals_1_stack_item */
          stack = [ class org/sireum/IS ]
      LineNumberTable:
        line 193: 0
      LocalVariableTable:
        Start  Length  Slot  Name   Signature
            0      28     0  this   Lorg/sireum/IS;
            0      28     1     e   Ljava/lang/Object;
    Signature: #222                         // (TV;)Lorg/sireum/IS<TI;TV;>;
    MethodParameters:
      Name                           Flags
      e                              final

  public V atZ(org.sireum.Z);
    descriptor: (Lorg/sireum/Z;)Ljava/lang/Object;
    flags: (0x0001) ACC_PUBLIC
    Code:
      stack=6, locals=2, args_size=2
         0: getstatic     #399                // Field scala/Predef$.MODULE$:Lscala/Predef$;
         3: getstatic     #157                // Field org/sireum/B$.MODULE$:Lorg/sireum/B$;
         6: getstatic     #157                // Field org/sireum/B$.MODULE$:Lorg/sireum/B$;
         9: getstatic     #162                // Field org/sireum/Z$MP$.MODULE$:Lorg/sireum/Z$MP$;
        12: invokevirtual #165                // Method org/sireum/Z$MP$.zero:()Lorg/sireum/Z;
        15: aload_1
        16: invokeinterface #402,  2          // InterfaceMethod org/sireum/Z.$less$eq:(Lorg/sireum/Z;)Z
        21: aload_0
        22: aload_1
        23: invokedynamic #407,  0            // InvokeDynamic #7:apply:(Lorg/sireum/IS;Lorg/sireum/Z;)Lscala/Function0;
        28: invokevirtual #218                // Method org/sireum/B$.$amp$amp$extension:(ZLscala/Function0;)Z
        31: invokevirtual #228                // Method org/sireum/B$.$4B:(Z)Z
        34: aload_1
        35: invokedynamic #418,  0            // InvokeDynamic #8:apply:(Lorg/sireum/Z;)Lscala/Function0;
        40: invokevirtual #422                // Method scala/Predef$.assert:(ZLscala/Function0;)V
        43: aload_0
        44: invokevirtual #250                // Method boxer:()Lorg/sireum/$internal/Boxer;
        47: aload_0
        48: invokevirtual #252                // Method data:()Ljava/lang/Object;
        51: aload_1
        52: invokeinterface #287,  3          // InterfaceMethod org/sireum/$internal/Boxer.lookup:(Ljava/lang/Object;Lorg/sireum/Z;)Ljava/lang/Object;
        57: areturn
      LineNumberTable:
        line 197: 0
        line 198: 43
      LocalVariableTable:
        Start  Length  Slot  Name   Signature
            0      58     0  this   Lorg/sireum/IS;
            0      58     1     i   Lorg/sireum/Z;
    Signature: #394                         // (Lorg/sireum/Z;)TV;
    MethodParameters:
      Name                           Flags
      i                              final

  public org.sireum.ZRange<I> indices();
    descriptor: ()Lorg/sireum/ZRange;
    flags: (0x0001) ACC_PUBLIC
    Code:
      stack=9, locals=3, args_size=1
         0: aload_0
         1: invokevirtual #239                // Method companion:()Lorg/sireum/$ZCompanion;
         4: invokeinterface #430,  1          // InterfaceMethod org/sireum/$ZCompanion.Index:()Ljava/lang/Object;
         9: checkcast     #178                // class org/sireum/ZLike
        12: astore_1
        13: getstatic     #162                // Field org/sireum/Z$MP$.MODULE$:Lorg/sireum/Z$MP$;
        16: invokevirtual #165                // Method org/sireum/Z$MP$.zero:()Lorg/sireum/Z;
        19: astore_2
        20: getstatic     #157                // Field org/sireum/B$.MODULE$:Lorg/sireum/B$;
        23: aload_2
        24: aload_0
        25: invokevirtual #159                // Method length:()Lorg/sireum/Z;
        28: invokeinterface #283,  2          // InterfaceMethod org/sireum/Z.$less:(Lorg/sireum/Z;)Z
        33: invokevirtual #228                // Method org/sireum/B$.$4B:(Z)Z
        36: ifeq          56
        39: aload_2
        40: invokeinterface #245,  1          // InterfaceMethod org/sireum/Z.increase:()Lorg/sireum/Z;
        45: astore_2
        46: aload_1
        47: invokeinterface #433,  1          // InterfaceMethod org/sireum/ZLike.increase:()Lorg/sireum/ZLike;
        52: astore_1
        53: goto          20
        56: new           #44                 // class org/sireum/ZRange
        59: dup
        60: getstatic     #189                // Field org/sireum/package$.MODULE$:Lorg/sireum/package$;
        63: invokevirtual #436                // Method org/sireum/package$.T:()Z
        66: aload_0
        67: invokevirtual #239                // Method companion:()Lorg/sireum/$ZCompanion;
        70: invokeinterface #430,  1          // InterfaceMethod org/sireum/$ZCompanion.Index:()Ljava/lang/Object;
        75: aload_1
        76: invokeinterface #439,  1          // InterfaceMethod org/sireum/ZLike.decrease:()Lorg/sireum/ZLike;
        81: getstatic     #144                // Field org/sireum/Z$.MODULE$:Lorg/sireum/Z$;
        84: iconst_1
        85: invokevirtual #151                // Method org/sireum/Z$.apply:(I)Lorg/sireum/Z;
        88: new           #30                 // class org/sireum/IS$$anon$1
        91: dup
        92: aconst_null
        93: invokespecial #443                // Method org/sireum/IS$$anon$1."<init>":(Lorg/sireum/IS;)V
        96: invokespecial #446                // Method org/sireum/ZRange."<init>":(ZLjava/lang/Object;Ljava/lang/Object;Lorg/sireum/Z;Lorg/sireum/ZRange$CondIncDec;)V
        99: areturn
      StackMapTable: number_of_entries = 2
        frame_type = 253 /* append */
          offset_delta = 20
          locals = [ class org/sireum/ZLike, class org/sireum/Z ]
        frame_type = 35 /* same */
      LineNumberTable:
        line 202: 0
        line 203: 13
        line 204: 20
        line 205: 39
        line 206: 46
        line 204: 53
        line 208: 56
        line 209: 60
        line 210: 66
        line 211: 75
        line 212: 81
        line 213: 88
      LocalVariableTable:
        Start  Length  Slot  Name   Signature
           13      86     1     j   Lorg/sireum/ZLike;
           20      79     2     i   Lorg/sireum/Z;
            0     100     0  this   Lorg/sireum/IS;
    Signature: #425                         // ()Lorg/sireum/ZRange<TI;>;

  public <V2 extends java.lang.Object> org.sireum.IS<I, V2> map(scala.Function1<V, V2>);
    descriptor: (Lscala/Function1;)Lorg/sireum/IS;
    flags: (0x0001) ACC_PUBLIC
    Code:
      stack=5, locals=6, args_size=2
         0: getstatic     #157                // Field org/sireum/B$.MODULE$:Lorg/sireum/B$;
         3: aload_0
         4: invokevirtual #225                // Method isEmpty:()Z
         7: invokevirtual #228                // Method org/sireum/B$.$4B:(Z)Z
        10: ifeq          17
        13: aload_0
        14: goto          162
        17: getstatic     #454                // Field scala/Array$.MODULE$:Lscala/Array$;
        20: getstatic     #459                // Field scala/collection/immutable/Nil$.MODULE$:Lscala/collection/immutable/Nil$;
        23: getstatic     #464                // Field scala/reflect/ClassTag$.MODULE$:Lscala/reflect/ClassTag$;
        26: invokevirtual #468                // Method scala/reflect/ClassTag$.Nothing:()Lscala/reflect/ClassTag;
        29: invokevirtual #471                // Method scala/Array$.apply:(Lscala/collection/immutable/Seq;Lscala/reflect/ClassTag;)Ljava/lang/Object;
        32: astore_2
        33: aconst_null
        34: astore_3
        35: getstatic     #162                // Field org/sireum/Z$MP$.MODULE$:Lorg/sireum/Z$MP$;
        38: invokevirtual #165                // Method org/sireum/Z$MP$.zero:()Lorg/sireum/Z;
        41: astore        4
        43: getstatic     #157                // Field org/sireum/B$.MODULE$:Lorg/sireum/B$;
        46: aload         4
        48: aload_0
        49: invokevirtual #159                // Method length:()Lorg/sireum/Z;
        52: invokeinterface #283,  2          // InterfaceMethod org/sireum/Z.$less:(Lorg/sireum/Z;)Z
        57: invokevirtual #228                // Method org/sireum/B$.$4B:(Z)Z
        60: ifeq          136
        63: aload_1
        64: aload_0
        65: invokevirtual #250                // Method boxer:()Lorg/sireum/$internal/Boxer;
        68: aload_0
        69: invokevirtual #252                // Method data:()Ljava/lang/Object;
        72: aload         4
        74: invokeinterface #287,  3          // InterfaceMethod org/sireum/$internal/Boxer.lookup:(Ljava/lang/Object;Lorg/sireum/Z;)Ljava/lang/Object;
        79: invokeinterface #475,  2          // InterfaceMethod scala/Function1.apply:(Ljava/lang/Object;)Ljava/lang/Object;
        84: astore        5
        86: aload_3
        87: ifnonnull     113
        90: getstatic     #480                // Field org/sireum/$internal/Boxer$.MODULE$:Lorg/sireum/$internal/Boxer$;
        93: aload         5
        95: invokevirtual #483                // Method org/sireum/$internal/Boxer$.boxer:(Ljava/lang/Object;)Lorg/sireum/$internal/Boxer;
        98: astore_3
        99: aload_3
       100: aload_0
       101: invokevirtual #159                // Method length:()Lorg/sireum/Z;
       104: invokeinterface #365,  2          // InterfaceMethod org/sireum/$internal/Boxer.create:(Lorg/sireum/Z;)Ljava/lang/Object;
       109: astore_2
       110: goto          113
       113: aload_3
       114: aload_2
       115: aload         4
       117: aload         5
       119: invokeinterface #262,  4          // InterfaceMethod org/sireum/$internal/Boxer.store:(Ljava/lang/Object;Lorg/sireum/Z;Ljava/lang/Object;)V
       124: aload         4
       126: invokeinterface #245,  1          // InterfaceMethod org/sireum/Z.increase:()Lorg/sireum/Z;
       131: astore        4
       133: goto          43
       136: getstatic     #73                 // Field org/sireum/IS$.MODULE$:Lorg/sireum/IS$;
       139: aload_0
       140: invokevirtual #239                // Method companion:()Lorg/sireum/$ZCompanion;
       143: aload_2
       144: aload_0
       145: invokevirtual #159                // Method length:()Lorg/sireum/Z;
       148: aload_3
       149: ifnonnull     158
       152: getstatic     #488                // Field org/sireum/$internal/IdentityBoxer$.MODULE$:Lorg/sireum/$internal/IdentityBoxer$;
       155: goto          159
       158: aload_3
       159: invokevirtual #265                // Method org/sireum/IS$.apply:(Lorg/sireum/$ZCompanion;Ljava/lang/Object;Lorg/sireum/Z;Lorg/sireum/$internal/Boxer;)Lorg/sireum/IS;
       162: areturn
      StackMapTable: number_of_entries = 7
        frame_type = 17 /* same */
        frame_type = 254 /* append */
          offset_delta = 25
          locals = [ class java/lang/Object, class org/sireum/$internal/Boxer, class org/sireum/Z ]
        frame_type = 252 /* append */
          offset_delta = 69
          locals = [ class java/lang/Object ]
        frame_type = 250 /* chop */
          offset_delta = 22
        frame_type = 255 /* full_frame */
          offset_delta = 21
          locals = [ class org/sireum/IS, class scala/Function1, class java/lang/Object, class org/sireum/$internal/Boxer, class org/sireum/Z ]
          stack = [ class org/sireum/IS$, class org/sireum/$ZCompanion, class java/lang/Object, class org/sireum/Z ]
        frame_type = 255 /* full_frame */
          offset_delta = 0
          locals = [ class org/sireum/IS, class scala/Function1, class java/lang/Object, class org/sireum/$internal/Boxer, class org/sireum/Z ]
          stack = [ class org/sireum/IS$, class org/sireum/$ZCompanion, class java/lang/Object, class org/sireum/Z, class org/sireum/$internal/Boxer ]
        frame_type = 255 /* full_frame */
          offset_delta = 2
          locals = [ class org/sireum/IS, class scala/Function1 ]
          stack = [ class org/sireum/IS ]
      LineNumberTable:
        line 222: 0
        line 224: 17
        line 225: 33
        line 226: 35
        line 227: 43
        line 228: 63
        line 229: 86
        line 230: 90
        line 231: 99
        line 233: 113
        line 234: 124
        line 227: 133
        line 236: 136
      LocalVariableTable:
        Start  Length  Slot  Name   Signature
           86      47     5    v2   Ljava/lang/Object;
           33     129     2     a   Ljava/lang/Object;
           35     127     3 boxer2   Lorg/sireum/$internal/Boxer;
           43     119     4     i   Lorg/sireum/Z;
            0     163     0  this   Lorg/sireum/IS;
            0     163     1     f   Lscala/Function1;
    Signature: #448                         // <V2:Ljava/lang/Object;>(Lscala/Function1<TV;TV2;>;)Lorg/sireum/IS<TI;TV2;>;
    MethodParameters:
      Name                           Flags
      f                              final

  public <U extends java.lang.Object> void foreach(scala.Function1<V, U>);
    descriptor: (Lscala/Function1;)V
    flags: (0x0001) ACC_PUBLIC
    Code:
      stack=4, locals=3, args_size=2
         0: getstatic     #162                // Field org/sireum/Z$MP$.MODULE$:Lorg/sireum/Z$MP$;
         3: invokevirtual #165                // Method org/sireum/Z$MP$.zero:()Lorg/sireum/Z;
         6: astore_2
         7: getstatic     #157                // Field org/sireum/B$.MODULE$:Lorg/sireum/B$;
        10: aload_2
        11: aload_0
        12: invokevirtual #159                // Method length:()Lorg/sireum/Z;
        15: invokeinterface #283,  2          // InterfaceMethod org/sireum/Z.$less:(Lorg/sireum/Z;)Z
        20: invokevirtual #228                // Method org/sireum/B$.$4B:(Z)Z
        23: ifeq          57
        26: aload_1
        27: aload_0
        28: invokevirtual #250                // Method boxer:()Lorg/sireum/$internal/Boxer;
        31: aload_0
        32: invokevirtual #252                // Method data:()Ljava/lang/Object;
        35: aload_2
        36: invokeinterface #287,  3          // InterfaceMethod org/sireum/$internal/Boxer.lookup:(Ljava/lang/Object;Lorg/sireum/Z;)Ljava/lang/Object;
        41: invokeinterface #475,  2          // InterfaceMethod scala/Function1.apply:(Ljava/lang/Object;)Ljava/lang/Object;
        46: pop
        47: aload_2
        48: invokeinterface #245,  1          // InterfaceMethod org/sireum/Z.increase:()Lorg/sireum/Z;
        53: astore_2
        54: goto          7
        57: return
      StackMapTable: number_of_entries = 2
        frame_type = 252 /* append */
          offset_delta = 7
          locals = [ class org/sireum/Z ]
        frame_type = 49 /* same */
      LineNumberTable:
        line 240: 0
        line 241: 7
        line 242: 26
        line 243: 47
        line 241: 54
      LocalVariableTable:
        Start  Length  Slot  Name   Signature
            7      50     2     i   Lorg/sireum/Z;
            0      58     0  this   Lorg/sireum/IS;
            0      58     1     f   Lscala/Function1;
    Signature: #492                         // <U:Ljava/lang/Object;>(Lscala/Function1<TV;TU;>;)V
    MethodParameters:
      Name                           Flags
      f                              final

  public <V2 extends java.lang.Object> org.sireum.IS<I, V2> flatMap(scala.Function1<V, org.sireum.IS<I, V2>>);
    descriptor: (Lscala/Function1;)Lorg/sireum/IS;
    flags: (0x0001) ACC_PUBLIC
    Code:
      stack=3, locals=4, args_size=2
         0: getstatic     #157                // Field org/sireum/B$.MODULE$:Lorg/sireum/B$;
         3: aload_0
         4: invokevirtual #225                // Method isEmpty:()Z
         7: invokevirtual #228                // Method org/sireum/B$.$4B:(Z)Z
        10: ifeq          17
        13: aload_0
        14: goto          69
        17: aload_0
        18: invokevirtual #305                // Method elements:()Lscala/collection/immutable/Seq;
        21: astore_2
        22: aload_1
        23: aload_2
        24: invokeinterface #497,  1          // InterfaceMethod scala/collection/immutable/Seq.head:()Ljava/lang/Object;
        29: invokeinterface #475,  2          // InterfaceMethod scala/Function1.apply:(Ljava/lang/Object;)Ljava/lang/Object;
        34: checkcast     #2                  // class org/sireum/IS
        37: invokestatic  #326                // Method scala/runtime/ObjectRef.create:(Ljava/lang/Object;)Lscala/runtime/ObjectRef;
        40: astore_3
        41: aload_2
        42: invokeinterface #329,  1          // InterfaceMethod scala/collection/immutable/Seq.tail:()Ljava/lang/Object;
        47: checkcast     #331                // class scala/collection/IterableOnceOps
        50: aload_3
        51: aload_1
        52: invokedynamic #505,  0            // InvokeDynamic #9:apply:(Lscala/runtime/ObjectRef;Lscala/Function1;)Lscala/Function1;
        57: invokeinterface #343,  2          // InterfaceMethod scala/collection/IterableOnceOps.foreach:(Lscala/Function1;)V
        62: aload_3
        63: getfield      #346                // Field scala/runtime/ObjectRef.elem:Ljava/lang/Object;
        66: checkcast     #2                  // class org/sireum/IS
        69: areturn
      StackMapTable: number_of_entries = 2
        frame_type = 17 /* same */
        frame_type = 115 /* same_locals_1_stack_item */
          stack = [ class org/sireum/IS ]
      LineNumberTable:
        line 248: 0
        line 250: 17
        line 251: 22
        line 252: 41
        line 255: 62
      LocalVariableTable:
        Start  Length  Slot  Name   Signature
           22      47     2    es   Lscala/collection/immutable/Seq;
           41      28     3     r   Lscala/runtime/ObjectRef;
            0      70     0  this   Lorg/sireum/IS;
            0      70     1     f   Lscala/Function1;
    Signature: #494                         // <V2:Ljava/lang/Object;>(Lscala/Function1<TV;Lorg/sireum/IS<TI;TV2;>;>;)Lorg/sireum/IS<TI;TV2;>;
    MethodParameters:
      Name                           Flags
      f                              final

  public org.sireum.IS<I, V> filter(scala.Function1<V, org.sireum.B>);
    descriptor: (Lscala/Function1;)Lorg/sireum/IS;
    flags: (0x0001) ACC_PUBLIC
    Code:
      stack=5, locals=6, args_size=2
         0: getstatic     #157                // Field org/sireum/B$.MODULE$:Lorg/sireum/B$;
         3: aload_0
         4: invokevirtual #225                // Method isEmpty:()Z
         7: invokevirtual #228                // Method org/sireum/B$.$4B:(Z)Z
        10: ifeq          17
        13: aload_0
        14: goto          157
        17: aload_0
        18: invokevirtual #250                // Method boxer:()Lorg/sireum/$internal/Boxer;
        21: aload_0
        22: invokevirtual #159                // Method length:()Lorg/sireum/Z;
        25: invokeinterface #365,  2          // InterfaceMethod org/sireum/$internal/Boxer.create:(Lorg/sireum/Z;)Ljava/lang/Object;
        30: astore_2
        31: getstatic     #162                // Field org/sireum/Z$MP$.MODULE$:Lorg/sireum/Z$MP$;
        34: invokevirtual #165                // Method org/sireum/Z$MP$.zero:()Lorg/sireum/Z;
        37: astore_3
        38: getstatic     #162                // Field org/sireum/Z$MP$.MODULE$:Lorg/sireum/Z$MP$;
        41: invokevirtual #165                // Method org/sireum/Z$MP$.zero:()Lorg/sireum/Z;
        44: astore        4
        46: getstatic     #157                // Field org/sireum/B$.MODULE$:Lorg/sireum/B$;
        49: aload_3
        50: aload_0
        51: invokevirtual #159                // Method length:()Lorg/sireum/Z;
        54: invokeinterface #283,  2          // InterfaceMethod org/sireum/Z.$less:(Lorg/sireum/Z;)Z
        59: invokevirtual #228                // Method org/sireum/B$.$4B:(Z)Z
        62: ifeq          140
        65: aload_0
        66: invokevirtual #250                // Method boxer:()Lorg/sireum/$internal/Boxer;
        69: aload_0
        70: invokevirtual #252                // Method data:()Ljava/lang/Object;
        73: aload_3
        74: invokeinterface #287,  3          // InterfaceMethod org/sireum/$internal/Boxer.lookup:(Ljava/lang/Object;Lorg/sireum/Z;)Ljava/lang/Object;
        79: astore        5
        81: getstatic     #157                // Field org/sireum/B$.MODULE$:Lorg/sireum/B$;
        84: aload_1
        85: aload         5
        87: invokeinterface #475,  2          // InterfaceMethod scala/Function1.apply:(Ljava/lang/Object;)Ljava/lang/Object;
        92: checkcast     #511                // class org/sireum/B
        95: invokevirtual #514                // Method org/sireum/B.value:()Z
        98: invokevirtual #228                // Method org/sireum/B$.$4B:(Z)Z
       101: ifeq          130
       104: aload_0
       105: invokevirtual #250                // Method boxer:()Lorg/sireum/$internal/Boxer;
       108: aload_2
       109: aload         4
       111: aload         5
       113: invokeinterface #262,  4          // InterfaceMethod org/sireum/$internal/Boxer.store:(Ljava/lang/Object;Lorg/sireum/Z;Ljava/lang/Object;)V
       118: aload         4
       120: invokeinterface #245,  1          // InterfaceMethod org/sireum/Z.increase:()Lorg/sireum/Z;
       125: astore        4
       127: goto          130
       130: aload_3
       131: invokeinterface #245,  1          // InterfaceMethod org/sireum/Z.increase:()Lorg/sireum/Z;
       136: astore_3
       137: goto          46
       140: getstatic     #73                 // Field org/sireum/IS$.MODULE$:Lorg/sireum/IS$;
       143: aload_0
       144: invokevirtual #239                // Method companion:()Lorg/sireum/$ZCompanion;
       147: aload_2
       148: aload         4
       150: aload_0
       151: invokevirtual #250                // Method boxer:()Lorg/sireum/$internal/Boxer;
       154: invokevirtual #265                // Method org/sireum/IS$.apply:(Lorg/sireum/$ZCompanion;Ljava/lang/Object;Lorg/sireum/Z;Lorg/sireum/$internal/Boxer;)Lorg/sireum/IS;
       157: areturn
      StackMapTable: number_of_entries = 5
        frame_type = 17 /* same */
        frame_type = 254 /* append */
          offset_delta = 28
          locals = [ class java/lang/Object, class org/sireum/Z, class org/sireum/Z ]
        frame_type = 252 /* append */
          offset_delta = 83
          locals = [ class java/lang/Object ]
        frame_type = 250 /* chop */
          offset_delta = 9
        frame_type = 255 /* full_frame */
          offset_delta = 16
          locals = [ class org/sireum/IS, class scala/Function1 ]
          stack = [ class org/sireum/IS ]
      LineNumberTable:
        line 259: 0
        line 261: 17
        line 262: 31
        line 263: 38
        line 264: 46
        line 265: 65
        line 266: 81
        line 267: 104
        line 268: 118
        line 270: 130
        line 264: 137
        line 272: 140
      LocalVariableTable:
        Start  Length  Slot  Name   Signature
           81      56     5    v2   Ljava/lang/Object;
           31     126     2     a   Ljava/lang/Object;
           38     119     3     i   Lorg/sireum/Z;
           46     111     4     j   Lorg/sireum/Z;
            0     158     0  this   Lorg/sireum/IS;
            0     158     1     p   Lscala/Function1;
    Signature: #508                         // (Lscala/Function1<TV;Lorg/sireum/B;>;)Lorg/sireum/IS<TI;TV;>;
    MethodParameters:
      Name                           Flags
      p                              final

  public org.sireum.IS$WithFilter<I, V> withFilter(scala.Function1<V, org.sireum.B>);
    descriptor: (Lscala/Function1;)Lorg/sireum/IS$WithFilter;
    flags: (0x0001) ACC_PUBLIC
    Code:
      stack=4, locals=2, args_size=2
         0: new           #34                 // class org/sireum/IS$WithFilter
         3: dup
         4: aload_0
         5: aload_1
         6: invokespecial #519                // Method org/sireum/IS$WithFilter."<init>":(Lorg/sireum/IS;Lscala/Function1;)V
         9: areturn
      LineNumberTable:
        line 275: 0
      LocalVariableTable:
        Start  Length  Slot  Name   Signature
            0      10     0  this   Lorg/sireum/IS;
            0      10     1     p   Lscala/Function1;
    Signature: #516                         // (Lscala/Function1<TV;Lorg/sireum/B;>;)Lorg/sireum/IS$WithFilter<TI;TV;>;
    MethodParameters:
      Name                           Flags
      p                              final

  public java.util.Iterator<V> iterator();
    descriptor: ()Ljava/util/Iterator;
    flags: (0x0001) ACC_PUBLIC
    Code:
      stack=3, locals=1, args_size=1
         0: new           #32                 // class org/sireum/IS$$anon$2
         3: dup
         4: aload_0
         5: invokespecial #523                // Method org/sireum/IS$$anon$2."<init>":(Lorg/sireum/IS;)V
         8: areturn
      LineNumberTable:
        line 277: 0
      LocalVariableTable:
        Start  Length  Slot  Name   Signature
            0       9     0  this   Lorg/sireum/IS;
    Signature: #522                         // ()Ljava/util/Iterator<TV;>;

  public org.sireum.Z size();
    descriptor: ()Lorg/sireum/Z;
    flags: (0x0001) ACC_PUBLIC
    Code:
      stack=1, locals=1, args_size=1
         0: aload_0
         1: invokevirtual #159                // Method length:()Lorg/sireum/Z;
         4: areturn
      LineNumberTable:
        line 290: 0
      LocalVariableTable:
        Start  Length  Slot  Name   Signature
            0       5     0  this   Lorg/sireum/IS;

  public I firstIndex();
    descriptor: ()Ljava/lang/Object;
    flags: (0x0001) ACC_PUBLIC
    Code:
      stack=3, locals=1, args_size=1
         0: getstatic     #399                // Field scala/Predef$.MODULE$:Lscala/Predef$;
         3: getstatic     #157                // Field org/sireum/B$.MODULE$:Lorg/sireum/B$;
         6: aload_0
         7: invokevirtual #527                // Method nonEmpty:()Z
        10: invokevirtual #228                // Method org/sireum/B$.$4B:(Z)Z
        13: invokedynamic #534,  0            // InvokeDynamic #10:apply:()Lscala/Function0;
        18: invokevirtual #422                // Method scala/Predef$.assert:(ZLscala/Function0;)V
        21: aload_0
        22: invokevirtual #239                // Method companion:()Lorg/sireum/$ZCompanion;
        25: invokeinterface #537,  1          // InterfaceMethod org/sireum/$ZCompanion.isZeroIndex:()Z
        30: ifeq          52
        33: aload_0
        34: invokevirtual #239                // Method companion:()Lorg/sireum/$ZCompanion;
        37: getstatic     #144                // Field org/sireum/Z$.MODULE$:Lorg/sireum/Z$;
        40: iconst_0
        41: invokevirtual #151                // Method org/sireum/Z$.apply:(I)Lorg/sireum/Z;
        44: invokeinterface #539,  2          // InterfaceMethod org/sireum/$ZCompanion.apply:(Lorg/sireum/Z;)Ljava/lang/Object;
        49: goto          61
        52: aload_0
        53: invokevirtual #239                // Method companion:()Lorg/sireum/$ZCompanion;
        56: invokeinterface #542,  1          // InterfaceMethod org/sireum/$ZCompanion.Min:()Ljava/lang/Object;
        61: areturn
      StackMapTable: number_of_entries = 2
        frame_type = 52 /* same */
        frame_type = 72 /* same_locals_1_stack_item */
          stack = [ class java/lang/Object ]
      LineNumberTable:
        line 293: 0
        line 294: 21
      LocalVariableTable:
        Start  Length  Slot  Name   Signature
            0      62     0  this   Lorg/sireum/IS;
    Signature: #525                         // ()TI;

  public I lastIndex();
    descriptor: ()Ljava/lang/Object;
    flags: (0x0001) ACC_PUBLIC
    Code:
      stack=3, locals=2, args_size=1
         0: getstatic     #399                // Field scala/Predef$.MODULE$:Lscala/Predef$;
         3: getstatic     #157                // Field org/sireum/B$.MODULE$:Lorg/sireum/B$;
         6: aload_0
         7: invokevirtual #527                // Method nonEmpty:()Z
        10: invokevirtual #228                // Method org/sireum/B$.$4B:(Z)Z
        13: invokedynamic #548,  0            // InvokeDynamic #11:apply:()Lscala/Function0;
        18: invokevirtual #422                // Method scala/Predef$.assert:(ZLscala/Function0;)V
        21: aload_0
        22: invokevirtual #239                // Method companion:()Lorg/sireum/$ZCompanion;
        25: invokeinterface #537,  1          // InterfaceMethod org/sireum/$ZCompanion.isZeroIndex:()Z
        30: ifeq          49
        33: aload_0
        34: invokevirtual #239                // Method companion:()Lorg/sireum/$ZCompanion;
        37: aload_0
        38: invokevirtual #159                // Method length:()Lorg/sireum/Z;
        41: invokeinterface #539,  2          // InterfaceMethod org/sireum/$ZCompanion.apply:(Lorg/sireum/Z;)Ljava/lang/Object;
        46: goto          93
        49: aload_0
        50: invokevirtual #239                // Method companion:()Lorg/sireum/$ZCompanion;
        53: invokeinterface #542,  1          // InterfaceMethod org/sireum/$ZCompanion.Min:()Ljava/lang/Object;
        58: invokestatic  #326                // Method scala/runtime/ObjectRef.create:(Ljava/lang/Object;)Lscala/runtime/ObjectRef;
        61: astore_1
        62: getstatic     #184                // Field org/sireum/package$$Int2Z$.MODULE$:Lorg/sireum/package$$Int2Z$;
        65: getstatic     #189                // Field org/sireum/package$.MODULE$:Lorg/sireum/package$;
        68: iconst_0
        69: invokevirtual #193                // Method org/sireum/package$.$Int2Z:(I)I
        72: aload_0
        73: invokevirtual #159                // Method length:()Lorg/sireum/Z;
        76: invokevirtual #552                // Method org/sireum/package$$Int2Z$.until$extension:(ILorg/sireum/Z;)Lorg/sireum/ZRange;
        79: aload_1
        80: invokedynamic #559,  0            // InvokeDynamic #12:apply:(Lscala/runtime/ObjectRef;)Lscala/Function1;
        85: invokevirtual #560                // Method org/sireum/ZRange.foreach:(Lscala/Function1;)V
        88: aload_1
        89: getfield      #346                // Field scala/runtime/ObjectRef.elem:Ljava/lang/Object;
        92: areturn
        93: areturn
      StackMapTable: number_of_entries = 2
        frame_type = 49 /* same */
        frame_type = 107 /* same_locals_1_stack_item */
          stack = [ class java/lang/Object ]
      LineNumberTable:
        line 298: 0
        line 299: 21
        line 300: 49
        line 301: 62
        line 304: 88
      LocalVariableTable:
        Start  Length  Slot  Name   Signature
           62      31     1     r   Lscala/runtime/ObjectRef;
            0      94     0  this   Lorg/sireum/IS;
    Signature: #525                         // ()TI;

  public org.sireum.MS<I, V> toMS();
    descriptor: ()Lorg/sireum/MS;
    flags: (0x0001) ACC_PUBLIC
    Code:
      stack=8, locals=1, args_size=1
         0: new           #565                // class org/sireum/MS
         3: dup
         4: aload_0
         5: invokevirtual #239                // Method companion:()Lorg/sireum/$ZCompanion;
         8: aload_0
         9: invokevirtual #250                // Method boxer:()Lorg/sireum/$internal/Boxer;
        12: aload_0
        13: invokevirtual #252                // Method data:()Ljava/lang/Object;
        16: aload_0
        17: invokevirtual #159                // Method length:()Lorg/sireum/Z;
        20: aload_0
        21: invokevirtual #159                // Method length:()Lorg/sireum/Z;
        24: getstatic     #162                // Field org/sireum/Z$MP$.MODULE$:Lorg/sireum/Z$MP$;
        27: invokevirtual #165                // Method org/sireum/Z$MP$.zero:()Lorg/sireum/Z;
        30: invokeinterface #258,  5          // InterfaceMethod org/sireum/$internal/Boxer.clone:(Ljava/lang/Object;Lorg/sireum/Z;Lorg/sireum/Z;Lorg/sireum/Z;)Ljava/lang/Object;
        35: aload_0
        36: invokevirtual #159                // Method length:()Lorg/sireum/Z;
        39: aload_0
        40: invokevirtual #250                // Method boxer:()Lorg/sireum/$internal/Boxer;
        43: invokespecial #568                // Method org/sireum/MS."<init>":(Lorg/sireum/$ZCompanion;Ljava/lang/Object;Lorg/sireum/Z;Lorg/sireum/$internal/Boxer;)V
        46: areturn
      LineNumberTable:
        line 309: 0
      LocalVariableTable:
        Start  Length  Slot  Name   Signature
            0      47     0  this   Lorg/sireum/IS;
    Signature: #563                         // ()Lorg/sireum/MS<TI;TV;>;

  public org.sireum.IS<org.sireum.Z, V> toISZ();
    descriptor: ()Lorg/sireum/IS;
    flags: (0x0001) ACC_PUBLIC
    Code:
      stack=2, locals=1, args_size=1
         0: getstatic     #189                // Field org/sireum/package$.MODULE$:Lorg/sireum/package$;
         3: invokevirtual #575                // Method org/sireum/package$.ISZ:()Lorg/sireum/$internal/PackageTrait$ISZ$;
         6: aload_0
         7: invokevirtual #305                // Method elements:()Lscala/collection/immutable/Seq;
        10: invokevirtual #578                // Method org/sireum/$internal/PackageTrait$ISZ$.apply:(Lscala/collection/immutable/Seq;)Lorg/sireum/IS;
        13: areturn
      LineNumberTable:
        line 312: 0
      LocalVariableTable:
        Start  Length  Slot  Name   Signature
            0      14     0  this   Lorg/sireum/IS;
    Signature: #571                         // ()Lorg/sireum/IS<Lorg/sireum/Z;TV;>;

  public org.sireum.MS<org.sireum.Z, V> toMSZ();
    descriptor: ()Lorg/sireum/MS;
    flags: (0x0001) ACC_PUBLIC
    Code:
      stack=2, locals=1, args_size=1
         0: getstatic     #189                // Field org/sireum/package$.MODULE$:Lorg/sireum/package$;
         3: invokevirtual #584                // Method org/sireum/package$.MSZ:()Lorg/sireum/$internal/PackageTrait$MSZ$;
         6: aload_0
         7: invokevirtual #305                // Method elements:()Lscala/collection/immutable/Seq;
        10: invokevirtual #587                // Method org/sireum/$internal/PackageTrait$MSZ$.apply:(Lscala/collection/immutable/Seq;)Lorg/sireum/MS;
        13: areturn
      LineNumberTable:
        line 314: 0
      LocalVariableTable:
        Start  Length  Slot  Name   Signature
            0      14     0  this   Lorg/sireum/IS;
    Signature: #580                         // ()Lorg/sireum/MS<Lorg/sireum/Z;TV;>;

  public V apply(I);
    descriptor: (Ljava/lang/Object;)Ljava/lang/Object;
    flags: (0x0001) ACC_PUBLIC
    Code:
      stack=2, locals=2, args_size=2
         0: aload_0
         1: aload_1
         2: checkcast     #178                // class org/sireum/ZLike
         5: invokeinterface #592,  1          // InterfaceMethod org/sireum/ZLike.toIndex:()Lorg/sireum/Z;
        10: invokevirtual #594                // Method atZ:(Lorg/sireum/Z;)Ljava/lang/Object;
        13: areturn
      LineNumberTable:
        line 316: 0
      LocalVariableTable:
        Start  Length  Slot  Name   Signature
            0      14     0  this   Lorg/sireum/IS;
            0      14     1 index   Ljava/lang/Object;
    Signature: #588                         // (TI;)TV;
    MethodParameters:
      Name                           Flags
      index                          final

  public org.sireum.IS<I, V> apply(scala.collection.immutable.Seq<scala.Tuple2<I, V>>);
    descriptor: (Lscala/collection/immutable/Seq;)Lorg/sireum/IS;
    flags: (0x0001) ACC_PUBLIC
    Code:
      stack=5, locals=3, args_size=2
         0: aload_1
         1: invokeinterface #597,  1          // InterfaceMethod scala/collection/immutable/Seq.isEmpty:()Z
         6: ifeq          13
         9: aload_0
        10: goto          81
        13: aload_0
        14: invokevirtual #250                // Method boxer:()Lorg/sireum/$internal/Boxer;
        17: aload_0
        18: invokevirtual #252                // Method data:()Ljava/lang/Object;
        21: aload_0
        22: invokevirtual #159                // Method length:()Lorg/sireum/Z;
        25: aload_0
        26: invokevirtual #159                // Method length:()Lorg/sireum/Z;
        29: getstatic     #162                // Field org/sireum/Z$MP$.MODULE$:Lorg/sireum/Z$MP$;
        32: invokevirtual #165                // Method org/sireum/Z$MP$.zero:()Lorg/sireum/Z;
        35: invokeinterface #258,  5          // InterfaceMethod org/sireum/$internal/Boxer.clone:(Ljava/lang/Object;Lorg/sireum/Z;Lorg/sireum/Z;Lorg/sireum/Z;)Ljava/lang/Object;
        40: astore_2
        41: aload_1
        42: invokedynamic #604,  0            // InvokeDynamic #13:apply:()Lscala/Function1;
        47: invokeinterface #321,  2          // InterfaceMethod scala/collection/immutable/Seq.withFilter:(Lscala/Function1;)Lscala/collection/WithFilter;
        52: aload_0
        53: aload_2
        54: invokedynamic #612,  0            // InvokeDynamic #14:apply:(Lorg/sireum/IS;Ljava/lang/Object;)Lscala/Function1;
        59: invokevirtual #613                // Method scala/collection/WithFilter.foreach:(Lscala/Function1;)V
        62: getstatic     #73                 // Field org/sireum/IS$.MODULE$:Lorg/sireum/IS$;
        65: aload_0
        66: invokevirtual #239                // Method companion:()Lorg/sireum/$ZCompanion;
        69: aload_2
        70: aload_0
        71: invokevirtual #159                // Method length:()Lorg/sireum/Z;
        74: aload_0
        75: invokevirtual #250                // Method boxer:()Lorg/sireum/$internal/Boxer;
        78: invokevirtual #265                // Method org/sireum/IS$.apply:(Lorg/sireum/$ZCompanion;Ljava/lang/Object;Lorg/sireum/Z;Lorg/sireum/$internal/Boxer;)Lorg/sireum/IS;
        81: areturn
      StackMapTable: number_of_entries = 2
        frame_type = 13 /* same */
        frame_type = 247 /* same_locals_1_stack_item_frame_extended */
          offset_delta = 67
          stack = [ class org/sireum/IS ]
      LineNumberTable:
        line 319: 0
        line 321: 13
        line 322: 41
        line 327: 62
      LocalVariableTable:
        Start  Length  Slot  Name   Signature
           41      40     2     a   Ljava/lang/Object;
            0      82     0  this   Lorg/sireum/IS;
            0      82     1  args   Lscala/collection/immutable/Seq;
    Signature: #595                         // (Lscala/collection/immutable/Seq<Lscala/Tuple2<TI;TV;>;>;)Lorg/sireum/IS<TI;TV;>;
    MethodParameters:
      Name                           Flags
      args                           final

  public scala.collection.immutable.Seq<V> elements();
    descriptor: ()Lscala/collection/immutable/Seq;
    flags: (0x0001) ACC_PUBLIC
    Code:
      stack=5, locals=3, args_size=1
         0: aload_0
         1: invokevirtual #159                // Method length:()Lorg/sireum/Z;
         4: invokeinterface #617,  1          // InterfaceMethod org/sireum/Z.toInt:()I
         9: anewarray     #5                  // class java/lang/Object
        12: astore_1
        13: getstatic     #162                // Field org/sireum/Z$MP$.MODULE$:Lorg/sireum/Z$MP$;
        16: invokevirtual #165                // Method org/sireum/Z$MP$.zero:()Lorg/sireum/Z;
        19: astore_2
        20: getstatic     #157                // Field org/sireum/B$.MODULE$:Lorg/sireum/B$;
        23: aload_2
        24: aload_0
        25: invokevirtual #159                // Method length:()Lorg/sireum/Z;
        28: invokeinterface #283,  2          // InterfaceMethod org/sireum/Z.$less:(Lorg/sireum/Z;)Z
        33: invokevirtual #228                // Method org/sireum/B$.$4B:(Z)Z
        36: ifeq          71
        39: aload_1
        40: aload_2
        41: invokeinterface #617,  1          // InterfaceMethod org/sireum/Z.toInt:()I
        46: aload_0
        47: invokevirtual #250                // Method boxer:()Lorg/sireum/$internal/Boxer;
        50: aload_0
        51: invokevirtual #252                // Method data:()Ljava/lang/Object;
        54: aload_2
        55: invokeinterface #287,  3          // InterfaceMethod org/sireum/$internal/Boxer.lookup:(Ljava/lang/Object;Lorg/sireum/Z;)Ljava/lang/Object;
        60: aastore
        61: aload_2
        62: invokeinterface #245,  1          // InterfaceMethod org/sireum/Z.increase:()Lorg/sireum/Z;
        67: astore_2
        68: goto          20
        71: getstatic     #622                // Field scala/collection/ArrayOps$.MODULE$:Lscala/collection/ArrayOps$;
        74: getstatic     #399                // Field scala/Predef$.MODULE$:Lscala/Predef$;
        77: aload_1
        78: invokevirtual #625                // Method scala/Predef$.genericArrayOps:(Ljava/lang/Object;)Ljava/lang/Object;
        81: invokevirtual #629                // Method scala/collection/ArrayOps$.toSeq$extension:(Ljava/lang/Object;)Lscala/collection/immutable/Seq;
        84: areturn
      StackMapTable: number_of_entries = 2
        frame_type = 253 /* append */
          offset_delta = 20
          locals = [ class "[Ljava/lang/Object;", class org/sireum/Z ]
        frame_type = 50 /* same */
      LineNumberTable:
        line 331: 0
        line 332: 13
        line 333: 20
        line 334: 39
        line 335: 61
        line 333: 68
        line 337: 71
      LocalVariableTable:
        Start  Length  Slot  Name   Signature
           13      71     1     r   [Ljava/lang/Object;
           20      64     2     i   Lorg/sireum/Z;
            0      85     0  this   Lorg/sireum/IS;
    Signature: #614                         // ()Lscala/collection/immutable/Seq<TV;>;

  private int hashCode$lzycompute();
    descriptor: ()I
    flags: (0x0002) ACC_PRIVATE
    Code:
      stack=5, locals=2, args_size=1
         0: aload_0
         1: dup
         2: astore_1
         3: monitorenter
         4: aload_0
         5: getfield      #634                // Field bitmap$0:Z
         8: ifne          38
        11: aload_0
        12: new           #636                // class scala/Tuple2
        15: dup
        16: aload_0
        17: invokevirtual #239                // Method companion:()Lorg/sireum/$ZCompanion;
        20: aload_0
        21: invokevirtual #305                // Method elements:()Lscala/collection/immutable/Seq;
        24: invokespecial #639                // Method scala/Tuple2."<init>":(Ljava/lang/Object;Ljava/lang/Object;)V
        27: invokevirtual #640                // Method scala/Tuple2.hashCode:()I
        30: putfield      #642                // Field hashCode:I
        33: aload_0
        34: iconst_1
        35: putfield      #634                // Field bitmap$0:Z
        38: aload_1
        39: monitorexit
        40: goto          46
        43: aload_1
        44: monitorexit
        45: athrow
        46: aload_0
        47: getfield      #642                // Field hashCode:I
        50: ireturn
      Exception table:
         from    to  target type
             4    38    43   any
      StackMapTable: number_of_entries = 3
        frame_type = 252 /* append */
          offset_delta = 38
          locals = [ class org/sireum/IS ]
        frame_type = 68 /* same_locals_1_stack_item */
          stack = [ class java/lang/Throwable ]
        frame_type = 2 /* same */
      LineNumberTable:
        line 340: 0
      LocalVariableTable:
        Start  Length  Slot  Name   Signature
            0      51     0  this   Lorg/sireum/IS;

  public int hashCode();
    descriptor: ()I
    flags: (0x0001) ACC_PUBLIC
    Code:
      stack=1, locals=1, args_size=1
         0: aload_0
         1: getfield      #634                // Field bitmap$0:Z
         4: ifne          14
         7: aload_0
         8: invokespecial #646                // Method hashCode$lzycompute:()I
        11: goto          18
        14: aload_0
        15: getfield      #642                // Field hashCode:I
        18: ireturn
      StackMapTable: number_of_entries = 2
        frame_type = 14 /* same */
        frame_type = 67 /* same_locals_1_stack_item */
          stack = [ int ]
      LineNumberTable:
        line 340: 0
      LocalVariableTable:
        Start  Length  Slot  Name   Signature
            0      19     0  this   Lorg/sireum/IS;

  public boolean equals(java.lang.Object);
    descriptor: (Ljava/lang/Object;)Z
    flags: (0x0001) ACC_PUBLIC
    Code:
      stack=6, locals=12, args_size=2
         0: new           #5                  // class java/lang/Object
         3: dup
         4: invokespecial #651                // Method java/lang/Object."<init>":()V
         7: astore_3
         8: aload_0
         9: aload_1
        10: if_acmpne     17
        13: iconst_1
        14: goto          169
        17: aload_1
        18: astore        4
        20: aload         4
        22: instanceof    #2                  // class org/sireum/IS
        25: ifeq          160
        28: aload         4
        30: checkcast     #2                  // class org/sireum/IS
        33: astore        5
        35: aload_0
        36: invokevirtual #239                // Method companion:()Lorg/sireum/$ZCompanion;
        39: aload         5
        41: invokevirtual #239                // Method companion:()Lorg/sireum/$ZCompanion;
        44: if_acmpeq     49
        47: iconst_0
        48: ireturn
        49: aload_0
        50: invokevirtual #159                // Method length:()Lorg/sireum/Z;
        53: aload         5
        55: invokevirtual #159                // Method length:()Lorg/sireum/Z;
        58: astore        6
        60: dup
        61: ifnonnull     73
        64: pop
        65: aload         6
        67: ifnull        83
        70: goto          81
        73: aload         6
        75: invokevirtual #169                // Method java/lang/Object.equals:(Ljava/lang/Object;)Z
        78: ifne          83
        81: iconst_0
        82: ireturn
        83: aload_0
        84: invokevirtual #252                // Method data:()Ljava/lang/Object;
        87: aload         5
        89: invokevirtual #252                // Method data:()Ljava/lang/Object;
        92: if_acmpne     97
        95: iconst_1
        96: ireturn
        97: aload_0
        98: invokevirtual #250                // Method boxer:()Lorg/sireum/$internal/Boxer;
       101: astore        7
       103: aload         5
       105: invokevirtual #250                // Method boxer:()Lorg/sireum/$internal/Boxer;
       108: astore        8
       110: aload_0
       111: invokevirtual #252                // Method data:()Ljava/lang/Object;
       114: astore        9
       116: aload         5
       118: invokevirtual #252                // Method data:()Ljava/lang/Object;
       121: astore        10
       123: getstatic     #162                // Field org/sireum/Z$MP$.MODULE$:Lorg/sireum/Z$MP$;
       126: invokevirtual #165                // Method org/sireum/Z$MP$.zero:()Lorg/sireum/Z;
       129: aload_0
       130: invokevirtual #159                // Method length:()Lorg/sireum/Z;
       133: invokeinterface #655,  2          // InterfaceMethod org/sireum/Z.until:(Lorg/sireum/ZLike;)Lorg/sireum/ZRange;
       138: aload         7
       140: aload         9
       142: aload         8
       144: aload         10
       146: aload_3
       147: invokedynamic #663,  0            // InvokeDynamic #15:apply:(Lorg/sireum/$internal/Boxer;Ljava/lang/Object;Lorg/sireum/$internal/Boxer;Ljava/lang/Object;Ljava/lang/Object;)Lscala/Function1;
       152: invokevirtual #560                // Method org/sireum/ZRange.foreach:(Lscala/Function1;)V
       155: iconst_1
       156: istore_2
       157: goto          168
       160: goto          163
       163: iconst_0
       164: istore_2
       165: goto          168
       168: iload_2
       169: goto          197
       172: astore        11
       174: aload         11
       176: invokevirtual #666                // Method scala/runtime/NonLocalReturnControl.key:()Ljava/lang/Object;
       179: aload_3
       180: if_acmpne     191
       183: aload         11
       185: invokevirtual #669                // Method scala/runtime/NonLocalReturnControl.value$mcZ$sp:()Z
       188: goto          194
       191: aload         11
       193: athrow
       194: goto          197
       197: ireturn
      Exception table:
         from    to  target type
             8   169   172   Class scala/runtime/NonLocalReturnControl
      StackMapTable: number_of_entries = 14
        frame_type = 253 /* append */
          offset_delta = 17
          locals = [ top, class java/lang/Object ]
        frame_type = 253 /* append */
          offset_delta = 31
          locals = [ class java/lang/Object, class org/sireum/IS ]
        frame_type = 255 /* full_frame */
          offset_delta = 23
          locals = [ class org/sireum/IS, class java/lang/Object, top, class java/lang/Object, class java/lang/Object, class org/sireum/IS, class org/sireum/Z ]
          stack = [ class org/sireum/Z ]
        frame_type = 7 /* same */
        frame_type = 1 /* same */
        frame_type = 13 /* same */
        frame_type = 249 /* chop */
          offset_delta = 62
        frame_type = 2 /* same */
        frame_type = 255 /* full_frame */
          offset_delta = 4
          locals = [ class org/sireum/IS, class java/lang/Object, int, class java/lang/Object, class java/lang/Object ]
          stack = []
        frame_type = 255 /* full_frame */
          offset_delta = 0
          locals = [ class org/sireum/IS, class java/lang/Object, top, class java/lang/Object ]
          stack = [ int ]
        frame_type = 66 /* same_locals_1_stack_item */
          stack = [ class scala/runtime/NonLocalReturnControl ]
        frame_type = 255 /* full_frame */
          offset_delta = 18
          locals = [ class org/sireum/IS, class java/lang/Object, top, class java/lang/Object, top, top, top, top, top, top, top, class scala/runtime/NonLocalReturnControl ]
          stack = []
        frame_type = 66 /* same_locals_1_stack_item */
          stack = [ int ]
        frame_type = 255 /* full_frame */
          offset_delta = 2
          locals = [ class org/sireum/IS, class java/lang/Object, top, class java/lang/Object ]
          stack = [ int ]
      LineNumberTable:
        line 342: 0
        line 343: 8
        line 345: 17
        line 346: 20
        line 347: 35
        line 348: 49
        line 349: 83
        line 350: 97
        line 351: 103
        line 352: 110
        line 353: 116
        line 354: 123
        line 358: 155
        line 346: 160
        line 359: 163
        line 345: 168
        line 343: 174
      LocalVariableTable:
        Start  Length  Slot  Name   Signature
          103      53     7    b1   Lorg/sireum/$internal/Boxer;
          110      46     8    b2   Lorg/sireum/$internal/Boxer;
          116      40     9 data1   Ljava/lang/Object;
          123      33    10 data2   Ljava/lang/Object;
          172      22    11    ex   Lscala/runtime/NonLocalReturnControl;
            0     198     0  this   Lorg/sireum/IS;
            0     198     1 other   Ljava/lang/Object;
    MethodParameters:
      Name                           Flags
      other                          final

  public java.lang.String string();
    descriptor: ()Ljava/lang/String;
    flags: (0x0001) ACC_PUBLIC
    Code:
      stack=2, locals=1, args_size=1
         0: getstatic     #681                // Field org/sireum/String$.MODULE$:Lorg/sireum/String$;
         3: aload_0
         4: invokevirtual #684                // Method toString:()Ljava/lang/String;
         7: invokevirtual #687                // Method org/sireum/String$.apply:(Ljava/lang/String;)Ljava/lang/String;
        10: areturn
      LineNumberTable:
        line 362: 0
      LocalVariableTable:
        Start  Length  Slot  Name   Signature
            0      11     0  this   Lorg/sireum/IS;

  public java.lang.String toString();
    descriptor: ()Ljava/lang/String;
    flags: (0x0001) ACC_PUBLIC
    Code:
      stack=3, locals=1, args_size=1
         0: aload_0
         1: invokevirtual #250                // Method boxer:()Lorg/sireum/$internal/Boxer;
         4: aload_0
         5: invokevirtual #252                // Method data:()Ljava/lang/Object;
         8: aload_0
         9: invokevirtual #159                // Method length:()Lorg/sireum/Z;
        12: invokeinterface #690,  3          // InterfaceMethod org/sireum/$internal/Boxer.toString:(Ljava/lang/Object;Lorg/sireum/Z;)Ljava/lang/String;
        17: areturn
      LineNumberTable:
        line 364: 0
      LocalVariableTable:
        Start  Length  Slot  Name   Signature
            0      18     0  this   Lorg/sireum/IS;

  public java.lang.Object $clone();
    descriptor: ()Ljava/lang/Object;
    flags: (0x1041) ACC_PUBLIC, ACC_BRIDGE, ACC_SYNTHETIC
    Code:
      stack=1, locals=1, args_size=1
         0: aload_0
         1: invokevirtual #692                // Method $clone:()Lorg/sireum/$internal/ImmutableMarker;
         4: areturn
      LineNumberTable:
        line 123: 0
      LocalVariableTable:
        Start  Length  Slot  Name   Signature
            0       5     0  this   Lorg/sireum/IS;

  public static final boolean $anonfun$isInBound$1(org.sireum.IS, org.sireum.Z);
    descriptor: (Lorg/sireum/IS;Lorg/sireum/Z;)Z
    flags: (0x1019) ACC_PUBLIC, ACC_STATIC, ACC_FINAL, ACC_SYNTHETIC
    Code:
      stack=2, locals=2, args_size=2
         0: aload_1
         1: aload_0
         2: invokevirtual #159                // Method length:()Lorg/sireum/Z;
         5: invokeinterface #283,  2          // InterfaceMethod org/sireum/Z.$less:(Lorg/sireum/Z;)Z
        10: ireturn
      LineNumberTable:
        line 134: 0
      LocalVariableTable:
        Start  Length  Slot  Name   Signature
            0      11     0 $this   Lorg/sireum/IS;
            0      11     1 iMP$1   Lorg/sireum/Z;
    MethodParameters:
      Name                           Flags
      $this                          final synthetic
      iMP$1                          final

  public static final boolean $anonfun$$minus$minus$1(org.sireum.IS);
    descriptor: (Lorg/sireum/IS;)Z
    flags: (0x1019) ACC_PUBLIC, ACC_STATIC, ACC_FINAL, ACC_SYNTHETIC
    Code:
      stack=3, locals=2, args_size=1
         0: getstatic     #157                // Field org/sireum/B$.MODULE$:Lorg/sireum/B$;
         3: aload_0
         4: invokevirtual #159                // Method length:()Lorg/sireum/Z;
         7: getstatic     #162                // Field org/sireum/Z$MP$.MODULE$:Lorg/sireum/Z$MP$;
        10: invokevirtual #165                // Method org/sireum/Z$MP$.zero:()Lorg/sireum/Z;
        13: astore_1
        14: dup
        15: ifnonnull     26
        18: pop
        19: aload_1
        20: ifnull        33
        23: goto          37
        26: aload_1
        27: invokevirtual #169                // Method java/lang/Object.equals:(Ljava/lang/Object;)Z
        30: ifeq          37
        33: iconst_1
        34: goto          38
        37: iconst_0
        38: invokevirtual #172                // Method org/sireum/B$.apply:(Z)Z
        41: ireturn
      StackMapTable: number_of_entries = 4
        frame_type = 255 /* full_frame */
          offset_delta = 26
          locals = [ class org/sireum/IS, class org/sireum/Z ]
          stack = [ class org/sireum/B$, class org/sireum/Z ]
        frame_type = 70 /* same_locals_1_stack_item */
          stack = [ class org/sireum/B$ ]
        frame_type = 67 /* same_locals_1_stack_item */
          stack = [ class org/sireum/B$ ]
        frame_type = 255 /* full_frame */
          offset_delta = 0
          locals = [ class org/sireum/IS, class org/sireum/Z ]
          stack = [ class org/sireum/B$, int ]
      LineNumberTable:
        line 174: 0
      LocalVariableTable:
        Start  Length  Slot  Name   Signature
            0      42     0 other$1   Lorg/sireum/IS;
    MethodParameters:
      Name                           Flags
      other$1                        final

  public static final boolean $anonfun$$minus$minus$2(scala.collection.immutable.Seq, java.lang.Object);
    descriptor: (Lscala/collection/immutable/Seq;Ljava/lang/Object;)Z
    flags: (0x1019) ACC_PUBLIC, ACC_STATIC, ACC_FINAL, ACC_SYNTHETIC
    Code:
      stack=2, locals=2, args_size=2
         0: aload_1
         1: aload_0
         2: invokeinterface #497,  1          // InterfaceMethod scala/collection/immutable/Seq.head:()Ljava/lang/Object;
         7: invokestatic  #707                // Method scala/runtime/BoxesRunTime.equals:(Ljava/lang/Object;Ljava/lang/Object;)Z
        10: ifne          17
        13: iconst_1
        14: goto          18
        17: iconst_0
        18: ireturn
      StackMapTable: number_of_entries = 2
        frame_type = 17 /* same */
        frame_type = 64 /* same_locals_1_stack_item */
          stack = [ int ]
      LineNumberTable:
        line 177: 0
      LocalVariableTable:
        Start  Length  Slot  Name   Signature
            0      19     0 otherElements$1   Lscala/collection/immutable/Seq;
            0      19     1   x$1   Ljava/lang/Object;
    MethodParameters:
      Name                           Flags
      otherElements$1                final
      x$1                            final

  public static final boolean $anonfun$$minus$minus$4(java.lang.Object, java.lang.Object);
    descriptor: (Ljava/lang/Object;Ljava/lang/Object;)Z
    flags: (0x1019) ACC_PUBLIC, ACC_STATIC, ACC_FINAL, ACC_SYNTHETIC
    Code:
      stack=2, locals=2, args_size=2
         0: aload_1
         1: aload_0
         2: invokestatic  #707                // Method scala/runtime/BoxesRunTime.equals:(Ljava/lang/Object;Ljava/lang/Object;)Z
         5: ifne          12
         8: iconst_1
         9: goto          13
        12: iconst_0
        13: ireturn
      StackMapTable: number_of_entries = 2
        frame_type = 12 /* same */
        frame_type = 64 /* same_locals_1_stack_item */
          stack = [ int ]
      LineNumberTable:
        line 179: 0
      LocalVariableTable:
        Start  Length  Slot  Name   Signature
            0      14     0   e$1   Ljava/lang/Object;
            0      14     1   x$2   Ljava/lang/Object;
    MethodParameters:
      Name                           Flags
      e$1                            final
      x$2                            final

  public static final void $anonfun$$minus$minus$3(scala.runtime.ObjectRef, java.lang.Object);
    descriptor: (Lscala/runtime/ObjectRef;Ljava/lang/Object;)V
    flags: (0x1019) ACC_PUBLIC, ACC_STATIC, ACC_FINAL, ACC_SYNTHETIC
    Code:
      stack=3, locals=2, args_size=2
         0: aload_0
         1: aload_0
         2: getfield      #346                // Field scala/runtime/ObjectRef.elem:Ljava/lang/Object;
         5: checkcast     #348                // class scala/collection/WithFilter
         8: aload_1
         9: invokedynamic #718,  0            // InvokeDynamic #16:apply:(Ljava/lang/Object;)Lscala/Function1;
        14: invokevirtual #719                // Method scala/collection/WithFilter.withFilter:(Lscala/Function1;)Lscala/collection/WithFilter;
        17: putfield      #346                // Field scala/runtime/ObjectRef.elem:Ljava/lang/Object;
        20: return
      LineNumberTable:
        line 179: 0
      LocalVariableTable:
        Start  Length  Slot  Name   Signature
            0      21     0  sm$1   Lscala/runtime/ObjectRef;
            0      21     1     e   Ljava/lang/Object;
    MethodParameters:
      Name                           Flags
      sm$1                           final
      e                              final

  public static final java.lang.Object $anonfun$$minus$minus$5(java.lang.Object);
    descriptor: (Ljava/lang/Object;)Ljava/lang/Object;
    flags: (0x1019) ACC_PUBLIC, ACC_STATIC, ACC_FINAL, ACC_SYNTHETIC
    Code:
      stack=2, locals=1, args_size=1
         0: getstatic     #399                // Field scala/Predef$.MODULE$:Lscala/Predef$;
         3: aload_0
         4: invokevirtual #723                // Method scala/Predef$.identity:(Ljava/lang/Object;)Ljava/lang/Object;
         7: areturn
      LineNumberTable:
        line 181: 0
      LocalVariableTable:
        Start  Length  Slot  Name   Signature
            0       8     0     x   Ljava/lang/Object;
    MethodParameters:
      Name                           Flags
      x                              final

  public static final void $anonfun$$minus$minus$6(org.sireum.IS, java.lang.Object, scala.runtime.ObjectRef, java.lang.Object);
    descriptor: (Lorg/sireum/IS;Ljava/lang/Object;Lscala/runtime/ObjectRef;Ljava/lang/Object;)V
    flags: (0x1019) ACC_PUBLIC, ACC_STATIC, ACC_FINAL, ACC_SYNTHETIC
    Code:
      stack=4, locals=4, args_size=4
         0: aload_0
         1: invokevirtual #250                // Method boxer:()Lorg/sireum/$internal/Boxer;
         4: aload_1
         5: aload_2
         6: getfield      #346                // Field scala/runtime/ObjectRef.elem:Ljava/lang/Object;
         9: checkcast     #39                 // class org/sireum/Z
        12: aload_3
        13: invokeinterface #262,  4          // InterfaceMethod org/sireum/$internal/Boxer.store:(Ljava/lang/Object;Lorg/sireum/Z;Ljava/lang/Object;)V
        18: aload_2
        19: aload_2
        20: getfield      #346                // Field scala/runtime/ObjectRef.elem:Ljava/lang/Object;
        23: checkcast     #39                 // class org/sireum/Z
        26: invokeinterface #245,  1          // InterfaceMethod org/sireum/Z.increase:()Lorg/sireum/Z;
        31: putfield      #346                // Field scala/runtime/ObjectRef.elem:Ljava/lang/Object;
        34: return
      LineNumberTable:
        line 186: 0
        line 187: 18
      LocalVariableTable:
        Start  Length  Slot  Name   Signature
            0      35     0 $this   Lorg/sireum/IS;
            0      35     1   a$2   Ljava/lang/Object;
            0      35     2   i$2   Lscala/runtime/ObjectRef;
            0      35     3     e   Ljava/lang/Object;
    MethodParameters:
      Name                           Flags
      $this                          final synthetic
      a$2                            final
      i$2                            final
      e                              final

  public static final boolean $anonfun$$minus$1(java.lang.Object, java.lang.Object);
    descriptor: (Ljava/lang/Object;Ljava/lang/Object;)Z
    flags: (0x1019) ACC_PUBLIC, ACC_STATIC, ACC_FINAL, ACC_SYNTHETIC
    Code:
      stack=3, locals=2, args_size=2
         0: getstatic     #157                // Field org/sireum/B$.MODULE$:Lorg/sireum/B$;
         3: aload_1
         4: aload_0
         5: invokestatic  #707                // Method scala/runtime/BoxesRunTime.equals:(Ljava/lang/Object;Ljava/lang/Object;)Z
         8: ifne          15
        11: iconst_1
        12: goto          16
        15: iconst_0
        16: invokevirtual #172                // Method org/sireum/B$.apply:(Z)Z
        19: ireturn
      StackMapTable: number_of_entries = 2
        frame_type = 79 /* same_locals_1_stack_item */
          stack = [ class org/sireum/B$ ]
        frame_type = 255 /* full_frame */
          offset_delta = 0
          locals = [ class java/lang/Object, class java/lang/Object ]
          stack = [ class org/sireum/B$, int ]
      LineNumberTable:
        line 193: 0
      LocalVariableTable:
        Start  Length  Slot  Name   Signature
            0      20     0   e$2   Ljava/lang/Object;
            0      20     1   x$3   Ljava/lang/Object;
    MethodParameters:
      Name                           Flags
      e$2                            final
      x$3                            final

  public static final boolean $anonfun$atZ$1(org.sireum.IS, org.sireum.Z);
    descriptor: (Lorg/sireum/IS;Lorg/sireum/Z;)Z
    flags: (0x1019) ACC_PUBLIC, ACC_STATIC, ACC_FINAL, ACC_SYNTHETIC
    Code:
      stack=2, locals=2, args_size=2
         0: aload_1
         1: aload_0
         2: invokevirtual #159                // Method length:()Lorg/sireum/Z;
         5: invokeinterface #283,  2          // InterfaceMethod org/sireum/Z.$less:(Lorg/sireum/Z;)Z
        10: ireturn
      LineNumberTable:
        line 197: 0
      LocalVariableTable:
        Start  Length  Slot  Name   Signature
            0      11     0 $this   Lorg/sireum/IS;
            0      11     1   i$3   Lorg/sireum/Z;
    MethodParameters:
      Name                           Flags
      $this                          final synthetic
      i$3                            final

  public static final java.lang.String $anonfun$atZ$2(org.sireum.Z);
    descriptor: (Lorg/sireum/Z;)Ljava/lang/String;
    flags: (0x1019) ACC_PUBLIC, ACC_STATIC, ACC_FINAL, ACC_SYNTHETIC
    Code:
      stack=3, locals=1, args_size=1
         0: new           #734                // class java/lang/StringBuilder
         3: dup
         4: ldc_w         #735                // int 24
         7: invokespecial #738                // Method java/lang/StringBuilder."<init>":(I)V
        10: ldc_w         #740                // String Indexing out of bounds:
        13: invokevirtual #744                // Method java/lang/StringBuilder.append:(Ljava/lang/String;)Ljava/lang/StringBuilder;
        16: aload_0
        17: invokevirtual #747                // Method java/lang/StringBuilder.append:(Ljava/lang/Object;)Ljava/lang/StringBuilder;
        20: invokevirtual #748                // Method java/lang/StringBuilder.toString:()Ljava/lang/String;
        23: areturn
      LineNumberTable:
        line 197: 0
      LocalVariableTable:
        Start  Length  Slot  Name   Signature
            0      24     0   i$3   Lorg/sireum/Z;
    MethodParameters:
      Name                           Flags
      i$3                            final

  public static final void $anonfun$flatMap$3(scala.runtime.ObjectRef, scala.Function1, java.lang.Object);
    descriptor: (Lscala/runtime/ObjectRef;Lscala/Function1;Ljava/lang/Object;)V
    flags: (0x1019) ACC_PUBLIC, ACC_STATIC, ACC_FINAL, ACC_SYNTHETIC
    Code:
      stack=4, locals=3, args_size=3
         0: aload_0
         1: aload_0
         2: getfield      #346                // Field scala/runtime/ObjectRef.elem:Ljava/lang/Object;
         5: checkcast     #2                  // class org/sireum/IS
         8: aload_1
         9: aload_2
        10: invokeinterface #475,  2          // InterfaceMethod scala/Function1.apply:(Ljava/lang/Object;)Ljava/lang/Object;
        15: checkcast     #2                  // class org/sireum/IS
        18: invokevirtual #754                // Method $plus$plus:(Lorg/sireum/IS;)Lorg/sireum/IS;
        21: putfield      #346                // Field scala/runtime/ObjectRef.elem:Ljava/lang/Object;
        24: return
      LineNumberTable:
        line 253: 0
      LocalVariableTable:
        Start  Length  Slot  Name   Signature
            0      25     0   r$2   Lscala/runtime/ObjectRef;
            0      25     1   f$2   Lscala/Function1;
            0      25     2     e   Ljava/lang/Object;
    MethodParameters:
      Name                           Flags
      r$2                            final
      f$2                            final
      e                              final

  public static final java.lang.String $anonfun$firstIndex$1();
    descriptor: ()Ljava/lang/String;
    flags: (0x1019) ACC_PUBLIC, ACC_STATIC, ACC_FINAL, ACC_SYNTHETIC
    Code:
      stack=1, locals=0, args_size=0
         0: ldc_w         #756                // String firstIndex can only be used on non-empty IS
         3: areturn
      LineNumberTable:
        line 293: 0

  public static final java.lang.String $anonfun$lastIndex$1();
    descriptor: ()Ljava/lang/String;
    flags: (0x1019) ACC_PUBLIC, ACC_STATIC, ACC_FINAL, ACC_SYNTHETIC
    Code:
      stack=1, locals=0, args_size=0
         0: ldc_w         #758                // String lastIndex can only be used on non-empty IS
         3: areturn
      LineNumberTable:
        line 298: 0

  public static final void $anonfun$lastIndex$2(scala.runtime.ObjectRef, org.sireum.Z);
    descriptor: (Lscala/runtime/ObjectRef;Lorg/sireum/Z;)V
    flags: (0x1019) ACC_PUBLIC, ACC_STATIC, ACC_FINAL, ACC_SYNTHETIC
    Code:
      stack=2, locals=4, args_size=2
         0: aload_1
         1: astore_3
         2: aload_0
         3: aload_0
         4: getfield      #346                // Field scala/runtime/ObjectRef.elem:Ljava/lang/Object;
         7: checkcast     #178                // class org/sireum/ZLike
        10: invokeinterface #433,  1          // InterfaceMethod org/sireum/ZLike.increase:()Lorg/sireum/ZLike;
        15: putfield      #346                // Field scala/runtime/ObjectRef.elem:Ljava/lang/Object;
        18: getstatic     #768                // Field scala/runtime/BoxedUnit.UNIT:Lscala/runtime/BoxedUnit;
        21: astore_2
        22: goto          25
        25: return
      StackMapTable: number_of_entries = 1
        frame_type = 253 /* append */
          offset_delta = 25
          locals = [ class scala/runtime/BoxedUnit, class org/sireum/Z ]
      LineNumberTable:
        line 301: 0
        line 302: 2
        line 301: 25
      LocalVariableTable:
        Start  Length  Slot  Name   Signature
            0      26     0   r$3   Lscala/runtime/ObjectRef;
            0      26     1   x$4   Lorg/sireum/Z;
    MethodParameters:
      Name                           Flags
      r$3                            final
      x$4                            final

  public static final boolean $anonfun$apply$2(scala.Tuple2);
    descriptor: (Lscala/Tuple2;)Z
    flags: (0x1019) ACC_PUBLIC, ACC_STATIC, ACC_FINAL, ACC_SYNTHETIC
    Code:
      stack=1, locals=3, args_size=1
         0: aload_0
         1: astore_2
         2: aload_2
         3: ifnull        11
         6: iconst_1
         7: istore_1
         8: goto          19
        11: goto          14
        14: iconst_0
        15: istore_1
        16: goto          19
        19: iload_1
        20: ireturn
      StackMapTable: number_of_entries = 3
        frame_type = 253 /* append */
          offset_delta = 11
          locals = [ top, class scala/Tuple2 ]
        frame_type = 2 /* same */
        frame_type = 255 /* full_frame */
          offset_delta = 4
          locals = [ class scala/Tuple2, int, class scala/Tuple2 ]
          stack = []
      LineNumberTable:
        line 322: 0
      LocalVariableTable:
        Start  Length  Slot  Name   Signature
            0      21     0 check$ifrefutable$1   Lscala/Tuple2;
    MethodParameters:
      Name                           Flags
      check$ifrefutable$1            final

  public static final boolean $anonfun$apply$4(org.sireum.IS, org.sireum.Z);
    descriptor: (Lorg/sireum/IS;Lorg/sireum/Z;)Z
    flags: (0x1019) ACC_PUBLIC, ACC_STATIC, ACC_FINAL, ACC_SYNTHETIC
    Code:
      stack=2, locals=2, args_size=2
         0: aload_1
         1: aload_0
         2: invokevirtual #159                // Method length:()Lorg/sireum/Z;
         5: invokeinterface #283,  2          // InterfaceMethod org/sireum/Z.$less:(Lorg/sireum/Z;)Z
        10: ireturn
      LineNumberTable:
        line 324: 0
      LocalVariableTable:
        Start  Length  Slot  Name   Signature
            0      11     0 $this   Lorg/sireum/IS;
            0      11     1   i$4   Lorg/sireum/Z;
    MethodParameters:
      Name                           Flags
      $this                          final synthetic
      i$4                            final

  public static final java.lang.String $anonfun$apply$5(java.lang.Object);
    descriptor: (Ljava/lang/Object;)Ljava/lang/String;
    flags: (0x1019) ACC_PUBLIC, ACC_STATIC, ACC_FINAL, ACC_SYNTHETIC
    Code:
      stack=3, locals=1, args_size=1
         0: new           #734                // class java/lang/StringBuilder
         3: dup
         4: ldc_w         #735                // int 24
         7: invokespecial #738                // Method java/lang/StringBuilder."<init>":(I)V
        10: ldc_w         #740                // String Indexing out of bounds:
        13: invokevirtual #744                // Method java/lang/StringBuilder.append:(Ljava/lang/String;)Ljava/lang/StringBuilder;
        16: aload_0
        17: invokevirtual #747                // Method java/lang/StringBuilder.append:(Ljava/lang/Object;)Ljava/lang/StringBuilder;
        20: invokevirtual #748                // Method java/lang/StringBuilder.toString:()Ljava/lang/String;
        23: areturn
      LineNumberTable:
        line 324: 0
      LocalVariableTable:
        Start  Length  Slot  Name   Signature
            0      24     0 index$1   Ljava/lang/Object;
    MethodParameters:
      Name                           Flags
      index$1                        final

  public static final void $anonfun$apply$3(org.sireum.IS, java.lang.Object, scala.Tuple2);
    descriptor: (Lorg/sireum/IS;Ljava/lang/Object;Lscala/Tuple2;)V
    flags: (0x1019) ACC_PUBLIC, ACC_STATIC, ACC_FINAL, ACC_SYNTHETIC
    Code:
      stack=6, locals=8, args_size=3
         0: aload_2
         1: astore        4
         3: aload         4
         5: ifnull        101
         8: aload         4
        10: invokevirtual #784                // Method scala/Tuple2._1:()Ljava/lang/Object;
        13: astore        5
        15: aload         4
        17: invokevirtual #787                // Method scala/Tuple2._2:()Ljava/lang/Object;
        20: astore        6
        22: aload         5
        24: checkcast     #178                // class org/sireum/ZLike
        27: invokeinterface #592,  1          // InterfaceMethod org/sireum/ZLike.toIndex:()Lorg/sireum/Z;
        32: astore        7
        34: getstatic     #399                // Field scala/Predef$.MODULE$:Lscala/Predef$;
        37: getstatic     #157                // Field org/sireum/B$.MODULE$:Lorg/sireum/B$;
        40: getstatic     #157                // Field org/sireum/B$.MODULE$:Lorg/sireum/B$;
        43: getstatic     #162                // Field org/sireum/Z$MP$.MODULE$:Lorg/sireum/Z$MP$;
        46: invokevirtual #165                // Method org/sireum/Z$MP$.zero:()Lorg/sireum/Z;
        49: aload         7
        51: invokeinterface #402,  2          // InterfaceMethod org/sireum/Z.$less$eq:(Lorg/sireum/Z;)Z
        56: aload_0
        57: aload         7
        59: invokedynamic #792,  0            // InvokeDynamic #17:apply:(Lorg/sireum/IS;Lorg/sireum/Z;)Lscala/Function0;
        64: invokevirtual #218                // Method org/sireum/B$.$amp$amp$extension:(ZLscala/Function0;)Z
        67: invokevirtual #228                // Method org/sireum/B$.$4B:(Z)Z
        70: aload         5
        72: invokedynamic #798,  0            // InvokeDynamic #18:apply:(Ljava/lang/Object;)Lscala/Function0;
        77: invokevirtual #422                // Method scala/Predef$.assert:(ZLscala/Function0;)V
        80: aload_0
        81: invokevirtual #250                // Method boxer:()Lorg/sireum/$internal/Boxer;
        84: aload_1
        85: aload         7
        87: aload         6
        89: invokeinterface #262,  4          // InterfaceMethod org/sireum/$internal/Boxer.store:(Ljava/lang/Object;Lorg/sireum/Z;Ljava/lang/Object;)V
        94: getstatic     #768                // Field scala/runtime/BoxedUnit.UNIT:Lscala/runtime/BoxedUnit;
        97: astore_3
        98: goto          114
       101: goto          104
       104: new           #800                // class scala/MatchError
       107: dup
       108: aload         4
       110: invokespecial #803                // Method scala/MatchError."<init>":(Ljava/lang/Object;)V
       113: athrow
       114: return
      StackMapTable: number_of_entries = 3
        frame_type = 253 /* append */
          offset_delta = 101
          locals = [ top, class scala/Tuple2 ]
        frame_type = 2 /* same */
        frame_type = 255 /* full_frame */
          offset_delta = 9
          locals = [ class org/sireum/IS, class java/lang/Object, class scala/Tuple2, class scala/runtime/BoxedUnit, class scala/Tuple2, class java/lang/Object, class java/lang/Object, class org/sireum/Z ]
          stack = []
      LineNumberTable:
        line 322: 0
        line 323: 22
        line 324: 34
        line 325: 80
        line 322: 101
      LocalVariableTable:
        Start  Length  Slot  Name   Signature
           34      63     7     i   Lorg/sireum/Z;
           15      86     5 index   Ljava/lang/Object;
           22      79     6     v   Ljava/lang/Object;
            0     115     0 $this   Lorg/sireum/IS;
            0     115     1   a$3   Ljava/lang/Object;
            0     115     2   x$5   Lscala/Tuple2;
    MethodParameters:
      Name                           Flags
      $this                          final synthetic
      a$3                            final
      x$5                            final

  public static final void $anonfun$equals$1(org.sireum.$internal.Boxer, java.lang.Object, org.sireum.$internal.Boxer, java.lang.Object, java.lang.Object, org.sireum.Z);
    descriptor: (Lorg/sireum/$internal/Boxer;Ljava/lang/Object;Lorg/sireum/$internal/Boxer;Ljava/lang/Object;Ljava/lang/Object;Lorg/sireum/Z;)V
    flags: (0x1019) ACC_PUBLIC, ACC_STATIC, ACC_FINAL, ACC_SYNTHETIC
    Code:
      stack=4, locals=7, args_size=6
         0: aload         5
         2: invokeinterface #812,  1          // InterfaceMethod org/sireum/Z.toMP:()Lorg/sireum/Z;
         7: astore        6
         9: aload_0
        10: aload_1
        11: aload         6
        13: invokeinterface #287,  3          // InterfaceMethod org/sireum/$internal/Boxer.lookup:(Ljava/lang/Object;Lorg/sireum/Z;)Ljava/lang/Object;
        18: aload_2
        19: aload_3
        20: aload         6
        22: invokeinterface #287,  3          // InterfaceMethod org/sireum/$internal/Boxer.lookup:(Ljava/lang/Object;Lorg/sireum/Z;)Ljava/lang/Object;
        27: invokestatic  #707                // Method scala/runtime/BoxesRunTime.equals:(Ljava/lang/Object;Ljava/lang/Object;)Z
        30: ifne          44
        33: new           #814                // class scala/runtime/NonLocalReturnControl$mcZ$sp
        36: dup
        37: aload         4
        39: iconst_0
        40: invokespecial #817                // Method scala/runtime/NonLocalReturnControl$mcZ$sp."<init>":(Ljava/lang/Object;Z)V
        43: athrow
        44: return
      StackMapTable: number_of_entries = 1
        frame_type = 252 /* append */
          offset_delta = 44
          locals = [ class org/sireum/Z ]
      LineNumberTable:
        line 355: 0
        line 356: 9
      LocalVariableTable:
        Start  Length  Slot  Name   Signature
            9      35     6   iMP   Lorg/sireum/Z;
            0      45     0  b1$1   Lorg/sireum/$internal/Boxer;
            0      45     1 data1$1   Ljava/lang/Object;
            0      45     2  b2$1   Lorg/sireum/$internal/Boxer;
            0      45     3 data2$1   Ljava/lang/Object;
            0      45     4 nonLocalReturnKey1$1   Ljava/lang/Object;
            0      45     5     i   Lorg/sireum/Z;
    MethodParameters:
      Name                           Flags
      b1$1                           final
      data1$1                        final
      b2$1                           final
      data2$1                        final
      nonLocalReturnKey1$1           final
      i                              final

  public org.sireum.IS(org.sireum.$ZCompanion<I>, java.lang.Object, org.sireum.Z, org.sireum.$internal.Boxer);
    descriptor: (Lorg/sireum/$ZCompanion;Ljava/lang/Object;Lorg/sireum/Z;Lorg/sireum/$internal/Boxer;)V
    flags: (0x0001) ACC_PUBLIC
    Code:
      stack=2, locals=5, args_size=5
         0: aload_0
         1: aload_1
         2: putfield      #129                // Field companion:Lorg/sireum/$ZCompanion;
         5: aload_0
         6: aload_2
         7: putfield      #132                // Field data:Ljava/lang/Object;
        10: aload_0
        11: aload_3
        12: putfield      #135                // Field length:Lorg/sireum/Z;
        15: aload_0
        16: aload         4
        18: putfield      #138                // Field boxer:Lorg/sireum/$internal/Boxer;
        21: aload_0
        22: invokespecial #651                // Method java/lang/Object."<init>":()V
        25: aload_0
        26: invokestatic  #822                // InterfaceMethod org/sireum/$internal/ImmutableMarker.$init$:(Lorg/sireum/$internal/ImmutableMarker;)V
        29: aload_0
        30: invokestatic  #825                // InterfaceMethod org/sireum/Immutable.$init$:(Lorg/sireum/Immutable;)V
        33: return
      LineNumberTable:
        line 123: 0
        line 124: 21
        line 123: 33
      LocalVariableTable:
        Start  Length  Slot  Name   Signature
            0      34     0  this   Lorg/sireum/IS;
            0      34     1 companion   Lorg/sireum/$ZCompanion;
            0      34     2  data   Ljava/lang/Object;
            0      34     3 length   Lorg/sireum/Z;
            0      34     4 boxer   Lorg/sireum/$internal/Boxer;
    Signature: #818                         // (Lorg/sireum/$ZCompanion<TI;>;Ljava/lang/Object;Lorg/sireum/Z;Lorg/sireum/$internal/Boxer;)V
    MethodParameters:
      Name                           Flags
      companion                      final
      data                           final
      length                         final
      boxer                          final

  public static final java.lang.Object $anonfun$isInBound$1$adapted(org.sireum.IS, org.sireum.Z);
    descriptor: (Lorg/sireum/IS;Lorg/sireum/Z;)Ljava/lang/Object;
    flags: (0x1019) ACC_PUBLIC, ACC_STATIC, ACC_FINAL, ACC_SYNTHETIC
    Code:
      stack=4, locals=2, args_size=2
         0: new           #511                // class org/sireum/B
         3: dup
         4: aload_0
         5: aload_1
         6: invokestatic  #827                // Method $anonfun$isInBound$1:(Lorg/sireum/IS;Lorg/sireum/Z;)Z
         9: invokespecial #830                // Method org/sireum/B."<init>":(Z)V
        12: areturn
      LineNumberTable:
        line 134: 0
      LocalVariableTable:
        Start  Length  Slot  Name   Signature
            0      13     0 $this   Lorg/sireum/IS;
            0      13     1 iMP$1   Lorg/sireum/Z;
    MethodParameters:
      Name                           Flags
      $this                          final
      iMP$1                          final

  public static final java.lang.Object $anonfun$$minus$minus$1$adapted(org.sireum.IS);
    descriptor: (Lorg/sireum/IS;)Ljava/lang/Object;
    flags: (0x1019) ACC_PUBLIC, ACC_STATIC, ACC_FINAL, ACC_SYNTHETIC
    Code:
      stack=3, locals=1, args_size=1
         0: new           #511                // class org/sireum/B
         3: dup
         4: aload_0
         5: invokestatic  #832                // Method $anonfun$$minus$minus$1:(Lorg/sireum/IS;)Z
         8: invokespecial #830                // Method org/sireum/B."<init>":(Z)V
        11: areturn
      LineNumberTable:
        line 174: 0
      LocalVariableTable:
        Start  Length  Slot  Name   Signature
            0      12     0 other$1   Lorg/sireum/IS;
    MethodParameters:
      Name                           Flags
      other$1                        final

  public static final java.lang.Object $anonfun$$minus$minus$2$adapted(scala.collection.immutable.Seq, java.lang.Object);
    descriptor: (Lscala/collection/immutable/Seq;Ljava/lang/Object;)Ljava/lang/Object;
    flags: (0x1019) ACC_PUBLIC, ACC_STATIC, ACC_FINAL, ACC_SYNTHETIC
    Code:
      stack=2, locals=2, args_size=2
         0: aload_0
         1: aload_1
         2: invokestatic  #834                // Method $anonfun$$minus$minus$2:(Lscala/collection/immutable/Seq;Ljava/lang/Object;)Z
         5: invokestatic  #838                // Method scala/runtime/BoxesRunTime.boxToBoolean:(Z)Ljava/lang/Boolean;
         8: areturn
      LineNumberTable:
        line 177: 0
      LocalVariableTable:
        Start  Length  Slot  Name   Signature
            0       9     0 otherElements$1   Lscala/collection/immutable/Seq;
            0       9     1   x$1   Ljava/lang/Object;
    MethodParameters:
      Name                           Flags
      otherElements$1                final
      x$1                            final

  public static final java.lang.Object $anonfun$$minus$minus$3$adapted(scala.runtime.ObjectRef, java.lang.Object);
    descriptor: (Lscala/runtime/ObjectRef;Ljava/lang/Object;)Ljava/lang/Object;
    flags: (0x1019) ACC_PUBLIC, ACC_STATIC, ACC_FINAL, ACC_SYNTHETIC
    Code:
      stack=2, locals=2, args_size=2
         0: aload_0
         1: aload_1
         2: invokestatic  #840                // Method $anonfun$$minus$minus$3:(Lscala/runtime/ObjectRef;Ljava/lang/Object;)V
         5: getstatic     #768                // Field scala/runtime/BoxedUnit.UNIT:Lscala/runtime/BoxedUnit;
         8: areturn
      LineNumberTable:
        line 178: 0
      LocalVariableTable:
        Start  Length  Slot  Name   Signature
            0       9     0  sm$1   Lscala/runtime/ObjectRef;
            0       9     1     e   Ljava/lang/Object;
    MethodParameters:
      Name                           Flags
      sm$1                           final
      e                              final

  public static final java.lang.Object $anonfun$$minus$minus$6$adapted(org.sireum.IS, java.lang.Object, scala.runtime.ObjectRef, java.lang.Object);
    descriptor: (Lorg/sireum/IS;Ljava/lang/Object;Lscala/runtime/ObjectRef;Ljava/lang/Object;)Ljava/lang/Object;
    flags: (0x1019) ACC_PUBLIC, ACC_STATIC, ACC_FINAL, ACC_SYNTHETIC
    Code:
      stack=4, locals=4, args_size=4
         0: aload_0
         1: aload_1
         2: aload_2
         3: aload_3
         4: invokestatic  #842                // Method $anonfun$$minus$minus$6:(Lorg/sireum/IS;Ljava/lang/Object;Lscala/runtime/ObjectRef;Ljava/lang/Object;)V
         7: getstatic     #768                // Field scala/runtime/BoxedUnit.UNIT:Lscala/runtime/BoxedUnit;
        10: areturn
      LineNumberTable:
        line 185: 0
      LocalVariableTable:
        Start  Length  Slot  Name   Signature
            0      11     0 $this   Lorg/sireum/IS;
            0      11     1   a$2   Ljava/lang/Object;
            0      11     2   i$2   Lscala/runtime/ObjectRef;
            0      11     3     e   Ljava/lang/Object;
    MethodParameters:
      Name                           Flags
      $this                          final
      a$2                            final
      i$2                            final
      e                              final

  public static final java.lang.Object $anonfun$$minus$1$adapted(java.lang.Object, java.lang.Object);
    descriptor: (Ljava/lang/Object;Ljava/lang/Object;)Ljava/lang/Object;
    flags: (0x1019) ACC_PUBLIC, ACC_STATIC, ACC_FINAL, ACC_SYNTHETIC
    Code:
      stack=4, locals=2, args_size=2
         0: new           #511                // class org/sireum/B
         3: dup
         4: aload_0
         5: aload_1
         6: invokestatic  #844                // Method $anonfun$$minus$1:(Ljava/lang/Object;Ljava/lang/Object;)Z
         9: invokespecial #830                // Method org/sireum/B."<init>":(Z)V
        12: areturn
      LineNumberTable:
        line 193: 0
      LocalVariableTable:
        Start  Length  Slot  Name   Signature
            0      13     0   e$2   Ljava/lang/Object;
            0      13     1   x$3   Ljava/lang/Object;
    MethodParameters:
      Name                           Flags
      e$2                            final
      x$3                            final

  public static final java.lang.Object $anonfun$atZ$1$adapted(org.sireum.IS, org.sireum.Z);
    descriptor: (Lorg/sireum/IS;Lorg/sireum/Z;)Ljava/lang/Object;
    flags: (0x1019) ACC_PUBLIC, ACC_STATIC, ACC_FINAL, ACC_SYNTHETIC
    Code:
      stack=4, locals=2, args_size=2
         0: new           #511                // class org/sireum/B
         3: dup
         4: aload_0
         5: aload_1
         6: invokestatic  #846                // Method $anonfun$atZ$1:(Lorg/sireum/IS;Lorg/sireum/Z;)Z
         9: invokespecial #830                // Method org/sireum/B."<init>":(Z)V
        12: areturn
      LineNumberTable:
        line 197: 0
      LocalVariableTable:
        Start  Length  Slot  Name   Signature
            0      13     0 $this   Lorg/sireum/IS;
            0      13     1   i$3   Lorg/sireum/Z;
    MethodParameters:
      Name                           Flags
      $this                          final
      i$3                            final

  public static final java.lang.Object $anonfun$flatMap$3$adapted(scala.runtime.ObjectRef, scala.Function1, java.lang.Object);
    descriptor: (Lscala/runtime/ObjectRef;Lscala/Function1;Ljava/lang/Object;)Ljava/lang/Object;
    flags: (0x1019) ACC_PUBLIC, ACC_STATIC, ACC_FINAL, ACC_SYNTHETIC
    Code:
      stack=3, locals=3, args_size=3
         0: aload_0
         1: aload_1
         2: aload_2
         3: invokestatic  #848                // Method $anonfun$flatMap$3:(Lscala/runtime/ObjectRef;Lscala/Function1;Ljava/lang/Object;)V
         6: getstatic     #768                // Field scala/runtime/BoxedUnit.UNIT:Lscala/runtime/BoxedUnit;
         9: areturn
      LineNumberTable:
        line 252: 0
      LocalVariableTable:
        Start  Length  Slot  Name   Signature
            0      10     0   r$2   Lscala/runtime/ObjectRef;
            0      10     1   f$2   Lscala/Function1;
            0      10     2     e   Ljava/lang/Object;
    MethodParameters:
      Name                           Flags
      r$2                            final
      f$2                            final
      e                              final

  public static final java.lang.Object $anonfun$lastIndex$2$adapted(scala.runtime.ObjectRef, org.sireum.Z);
    descriptor: (Lscala/runtime/ObjectRef;Lorg/sireum/Z;)Ljava/lang/Object;
    flags: (0x1019) ACC_PUBLIC, ACC_STATIC, ACC_FINAL, ACC_SYNTHETIC
    Code:
      stack=2, locals=2, args_size=2
         0: aload_0
         1: aload_1
         2: invokestatic  #850                // Method $anonfun$lastIndex$2:(Lscala/runtime/ObjectRef;Lorg/sireum/Z;)V
         5: getstatic     #768                // Field scala/runtime/BoxedUnit.UNIT:Lscala/runtime/BoxedUnit;
         8: areturn
      LineNumberTable:
        line 301: 0
      LocalVariableTable:
        Start  Length  Slot  Name   Signature
            0       9     0   r$3   Lscala/runtime/ObjectRef;
            0       9     1   x$4   Lorg/sireum/Z;
    MethodParameters:
      Name                           Flags
      r$3                            final
      x$4                            final

  public static final java.lang.Object $anonfun$apply$2$adapted(scala.Tuple2);
    descriptor: (Lscala/Tuple2;)Ljava/lang/Object;
    flags: (0x1019) ACC_PUBLIC, ACC_STATIC, ACC_FINAL, ACC_SYNTHETIC
    Code:
      stack=1, locals=1, args_size=1
         0: aload_0
         1: invokestatic  #852                // Method $anonfun$apply$2:(Lscala/Tuple2;)Z
         4: invokestatic  #838                // Method scala/runtime/BoxesRunTime.boxToBoolean:(Z)Ljava/lang/Boolean;
         7: areturn
      LineNumberTable:
        line 322: 0
      LocalVariableTable:
        Start  Length  Slot  Name   Signature
            0       8     0 check$ifrefutable$1   Lscala/Tuple2;
    MethodParameters:
      Name                           Flags
      check$ifrefutable$1            final

  public static final java.lang.Object $anonfun$apply$3$adapted(org.sireum.IS, java.lang.Object, scala.Tuple2);
    descriptor: (Lorg/sireum/IS;Ljava/lang/Object;Lscala/Tuple2;)Ljava/lang/Object;
    flags: (0x1019) ACC_PUBLIC, ACC_STATIC, ACC_FINAL, ACC_SYNTHETIC
    Code:
      stack=3, locals=3, args_size=3
         0: aload_0
         1: aload_1
         2: aload_2
         3: invokestatic  #854                // Method $anonfun$apply$3:(Lorg/sireum/IS;Ljava/lang/Object;Lscala/Tuple2;)V
         6: getstatic     #768                // Field scala/runtime/BoxedUnit.UNIT:Lscala/runtime/BoxedUnit;
         9: areturn
      LineNumberTable:
        line 322: 0
      LocalVariableTable:
        Start  Length  Slot  Name   Signature
            0      10     0 $this   Lorg/sireum/IS;
            0      10     1   a$3   Ljava/lang/Object;
            0      10     2   x$5   Lscala/Tuple2;
    MethodParameters:
      Name                           Flags
      $this                          final
      a$3                            final
      x$5                            final

  public static final java.lang.Object $anonfun$equals$1$adapted(org.sireum.$internal.Boxer, java.lang.Object, org.sireum.$internal.Boxer, java.lang.Object, java.lang.Object, org.sireum.Z);
    descriptor: (Lorg/sireum/$internal/Boxer;Ljava/lang/Object;Lorg/sireum/$internal/Boxer;Ljava/lang/Object;Ljava/lang/Object;Lorg/sireum/Z;)Ljava/lang/Object;
    flags: (0x1019) ACC_PUBLIC, ACC_STATIC, ACC_FINAL, ACC_SYNTHETIC
    Code:
      stack=6, locals=6, args_size=6
         0: aload_0
         1: aload_1
         2: aload_2
         3: aload_3
         4: aload         4
         6: aload         5
         8: invokestatic  #856                // Method $anonfun$equals$1:(Lorg/sireum/$internal/Boxer;Ljava/lang/Object;Lorg/sireum/$internal/Boxer;Ljava/lang/Object;Ljava/lang/Object;Lorg/sireum/Z;)V
        11: getstatic     #768                // Field scala/runtime/BoxedUnit.UNIT:Lscala/runtime/BoxedUnit;
        14: areturn
      LineNumberTable:
        line 354: 0
      LocalVariableTable:
        Start  Length  Slot  Name   Signature
            0      15     0  b1$1   Lorg/sireum/$internal/Boxer;
            0      15     1 data1$1   Ljava/lang/Object;
            0      15     2  b2$1   Lorg/sireum/$internal/Boxer;
            0      15     3 data2$1   Ljava/lang/Object;
            0      15     4 nonLocalReturnKey1$1   Ljava/lang/Object;
            0      15     5     i   Lorg/sireum/Z;
    MethodParameters:
      Name                           Flags
      b1$1                           final
      data1$1                        final
      b2$1                           final
      data2$1                        final
      nonLocalReturnKey1$1           final
      i                              final

  public static final java.lang.Object $anonfun$$minus$minus$4$adapted(java.lang.Object, java.lang.Object);
    descriptor: (Ljava/lang/Object;Ljava/lang/Object;)Ljava/lang/Object;
    flags: (0x1019) ACC_PUBLIC, ACC_STATIC, ACC_FINAL, ACC_SYNTHETIC
    Code:
      stack=2, locals=2, args_size=2
         0: aload_0
         1: aload_1
         2: invokestatic  #858                // Method $anonfun$$minus$minus$4:(Ljava/lang/Object;Ljava/lang/Object;)Z
         5: invokestatic  #838                // Method scala/runtime/BoxesRunTime.boxToBoolean:(Z)Ljava/lang/Boolean;
         8: areturn
      LineNumberTable:
        line 179: 0
      LocalVariableTable:
        Start  Length  Slot  Name   Signature
            0       9     0   e$1   Ljava/lang/Object;
            0       9     1   x$2   Ljava/lang/Object;
    MethodParameters:
      Name                           Flags
      e$1                            final
      x$2                            final

  public static final java.lang.Object $anonfun$apply$4$adapted(org.sireum.IS, org.sireum.Z);
    descriptor: (Lorg/sireum/IS;Lorg/sireum/Z;)Ljava/lang/Object;
    flags: (0x1019) ACC_PUBLIC, ACC_STATIC, ACC_FINAL, ACC_SYNTHETIC
    Code:
      stack=4, locals=2, args_size=2
         0: new           #511                // class org/sireum/B
         3: dup
         4: aload_0
         5: aload_1
         6: invokestatic  #860                // Method $anonfun$apply$4:(Lorg/sireum/IS;Lorg/sireum/Z;)Z
         9: invokespecial #830                // Method org/sireum/B."<init>":(Z)V
        12: areturn
      LineNumberTable:
        line 324: 0
      LocalVariableTable:
        Start  Length  Slot  Name   Signature
            0      13     0 $this   Lorg/sireum/IS;
            0      13     1   i$4   Lorg/sireum/Z;
    MethodParameters:
      Name                           Flags
      $this                          final
      i$4                            final

  private static java.lang.Object $deserializeLambda$(java.lang.invoke.SerializedLambda);
    descriptor: (Ljava/lang/invoke/SerializedLambda;)Ljava/lang/Object;
    flags: (0x100a) ACC_PRIVATE, ACC_STATIC, ACC_SYNTHETIC
    Code:
      stack=1, locals=1, args_size=1
         0: aload_0
         1: invokedynamic #872,  0            // InvokeDynamic #19:lambdaDeserialize:(Ljava/lang/invoke/SerializedLambda;)Ljava/lang/Object;
         6: areturn
}
InnerClasses:
  public static final #20= #17 of #19;    // Lookup=class java/lang/invoke/MethodHandles$Lookup of class java/lang/invoke/MethodHandles
  public #25= #22 of #24;                 // ISZ$=class org/sireum/$internal/PackageTrait$ISZ$ of class org/sireum/$internal/PackageTrait
  public #28= #27 of #24;                 // MSZ$=class org/sireum/$internal/PackageTrait$MSZ$ of class org/sireum/$internal/PackageTrait
  public final #30;                       // class org/sireum/IS$$anon$1
  public final #32;                       // class org/sireum/IS$$anon$2
  public static #35= #34 of #2;           // WithFilter=class org/sireum/IS$WithFilter of class org/sireum/IS
  public static #40= #37 of #39;          // MP$=class org/sireum/Z$MP$ of class org/sireum/Z
  public static #45= #42 of #44;          // CondIncDec=class org/sireum/ZRange$CondIncDec of class org/sireum/ZRange
  public static #50= #47 of #49;          // $Int2Z$=class org/sireum/package$$Int2Z$ of class org/sireum/package
Signature: #3                           // <I:Ljava/lang/Object;V:Ljava/lang/Object;>Ljava/lang/Object;Lorg/sireum/Immutable;Lorg/sireum/$internal/ISMarker;Ljava/lang/Iterable<TV;>;
SourceFile: "IS.scala"
RuntimeVisibleAnnotations:
  0: #13(#14=s#15)
    scala.reflect.ScalaSignature(
      bytes="\u0006\u0005\r=r!\u0002\u001d:\u0011\u0003qd!\u0002!:\u0011\u0003\t\u0005\"\u0002%\u0002\t\u0003Ie\u0001\u0002&\u0002\u0001-C\u0001\"T\u0002\u0003\u0002\u0003\u0006IA\u0014\u0005\u000b\u0003k\u001b!\u0011!Q\u0001\n\tm\u0004B\u0002%\u0004\t\u0003\u0011i\bC\u0004\u0002r\r!\tAa\"\t\u000f\u0005%5\u0001\"\u0001\u0003\u0016\"9\u0011qT\u0002\u0005\u0002\t\u0005\u0006bBAb\u0007\u0011\u0005!q\u0016\u0005\b\u0005k\u000bA\u0011\u0001B\\\u0011\u001d\u0011y!\u0001C\u0001\u0005\u000fDqAa8\u0002\t\u0003\u0011\t\u000fC\u0004\u0003\u0010\u0005!\tAa?\t\u000f\rM\u0011\u0001\"\u0001\u0004\u0016\u0019!\u0001)\u000f\u0002P\u0011!i\u0007C!b\u0001\n\u0003q\u0007\u0002C;\u0011\u0005\u0003\u0005\u000b\u0011B8\t\u0011Y\u0004\"Q1A\u0005\u0002]D\u0001\u0002\u001f\t\u0003\u0002\u0003\u0006IA\u0011\u0005\tsB\u0011)\u0019!C\u0001u\"Aa\u0010\u0005B\u0001B\u0003%1\u0010C\u0005\u0000!\t\u0015\r\u0011\"\u0001\u0002\u0002!Q\u0011\u0011\u0002\t\u0003\u0002\u0003\u0006I!a\u0001\t\r!\u0003B\u0011AA\u0006\u0011\u0019\t9\u0002\u0005C\u0001u\"9\u0011\u0011\u0004\t\u0005\u0002\u0005m\u0001bBA\u0012!\u0011\u0005\u00111\u0004\u0005\b\u0003K\u0001B\u0011AA\u0014\u0011\u001d\ti\u0003\u0005C\u0001\u0003_Aq!!\u000e\u0011\t\u0003\t9\u0004C\u0004\u0002<A!\t!!\u0010\t\u000f\u00055\u0003\u0003\"\u0001\u0002P!9\u00111\f\t\u0005\u0002\u0005u\u0003bBA1!\u0011\u0005\u00111\r\u0005\b\u0003O\u0002B\u0011AA5\u0011\u001d\t\t\b\u0005C\u0001\u0003gBq!!#\u0011\t\u0003\tY\tC\u0004\u0002 B!\t!!)\t\u000f\u0005=\u0006\u0003\"\u0001\u00022\"9\u00111\u0019\t\u0005\u0002\u0005\u0015\u0007bBAh!\u0011\u0005\u0011\u0011\u001b\u0005\u0007\u0003?\u0004B\u0011\u0001>\t\u000f\u0005\u0005\b\u0003\"\u0001\u0002d\"9\u0011Q\u001d\t\u0005\u0002\u0005\r\bbBAt!\u0011\u0005\u0011\u0011\u001e\u0005\b\u0003c\u0004B\u0011AAz\u0011\u001d\u0011)\u0001\u0005C\u0001\u0005\u000fAqAa\u0004\u0011\t\u0003\u0011\t\u0002C\u0004\u0003\u0010A!\tAa\u0006\t\u000f\t%\u0002\u0003\"\u0001\u0003,!Q!1\t\t\t\u0006\u0004%\tE!\u0012\t\u000f\t5\u0003\u0003\"\u0011\u0003P!9!\u0011\f\t\u0005\u0002\tm\u0003b\u0002B2!\u0011\u0005#QM\u0001\u0003\u0013NS!AO\u001e\u0002\rML\'/Z;n\u0015\u0005a\u0014aA8sO\u000e\u0001\u0001CA \u0002\u001b\u0005I$AA%T\'\t\t!\t\u0005\u0002D\r6\tAIC\u0001F\u0003\u0015\u00198-\u00197b\u0013\t9EI\u0001\u0004B]f\u0014VMZ\u0001\u0007y%t\u0017\u000e\u001e \u0015\u0003y\u0012!bV5uQ\u001aKG\u000e^3s+\u0015a%Q\u000fB=\'\t\u0019!)\u0001\u0002jgB1q\b\u0005B:\u0005o*2\u0001U:e\'\u0015\u0001\")\u0015+[!\ty$+\u0003\u0002Ts\tI\u0011*\\7vi\u0006\u0014G.\u001a\t\u0003+bk\u0011A\u0016\u0006\u0003/f\n\u0011\u0002J5oi\u0016\u0014h.\u00197\n\u0005e3&\u0001C%T\u001b\u0006\u00148.\u001a:\u0011\u0007m\u0003\'-D\u0001]\u0015\tif,\u0001\u0003mC:<\'\"A0\u0002\t)\fg/Y\u0005\u0003Cr\u0013\u0001\"\u0013;fe\u0006\u0014G.\u001a\t\u0003G\u0012d\u0001\u0001B\u0003f!\t\u0007aMA\u0001W#\t9\'\u000e\u0005\u0002DQ&\u0011\u0011\u000e\u0012\u0002\b\u001d>$\b.\u001b8h!\t\u00195.\u0003\u0002m\t\n\u0019\u0011I\\=\u0002\u0013\r|W\u000e]1oS>tW#A8\u0011\u0007}\u0002(/\u0003\u0002rs\tYAEW\"p[B\fg.[8o!\t\u00197\u000fB\u0003u!\t\u0007aMA\u0001J\u0003)\u0019w.\u001c9b]&|g\u000eI\u0001\u0005I\u0006$\u0018-F\u0001C\u0003\u0015!\u0017\r^1!\u0003\u0019aWM\\4uQV\t1\u0010\u0005\u0002@y&\u0011Q0\u000f\u0002\u00025\u00069A.\u001a8hi\"\u0004\u0013!\u00022pq\u0016\u0014XCAA\u0002!\r)\u0016QA\u0005\u0004\u0003\u000f1&!\u0002\"pq\u0016\u0014\u0018A\u00022pq\u0016\u0014\b\u0005\u0006\u0006\u0002\u000e\u0005=\u0011\u0011CA\n\u0003+\u0001Ba\u0010\tsE\")Q.\u0007a\u0001_\")a/\u0007a\u0001\u0005\")\u00110\u0007a\u0001w\"1q0\u0007a\u0001\u0003\u0007\tA\u0001[1tQ\u00069\u0011n]#naRLXCAA\u000f!\ry\u0014qD\u0005\u0004\u0003CI$!\u0001\"\u0002\u00119|g.R7qif\f\u0011\"[:J]\n{WO\u001c3\u0015\t\u0005u\u0011\u0011\u0006\u0005\u0007\u0003Wi\u0002\u0019\u0001:\u0002\u0003%\f1\u0002J2pY>tG\u0005\u001d7vgR!\u0011QBA\u0019\u0011\u0019\t\u0019D\ba\u0001E\u0006\tQ-A\u0006%a2,8\u000fJ2pY>tG\u0003BA\u0007\u0003sAa!a\r \u0001\u0004\u0011\u0017A\u0003\u0013qYV\u001cH\u0005\u001d7vgV!\u0011qHA%)\u0011\ti!!\u0011\t\u000f\u0005\r\u0003\u00051\u0001\u0002F\u0005)q\u000e\u001e5feB)q\bEA$EB\u00191-!\u0013\u0005\r\u0005-\u0003E1\u0001g\u0005\tI%\'\u0001\u0007%[&tWo\u001d\u0013nS:,8/\u0006\u0003\u0002R\u0005eC\u0003BA\u0007\u0003\'Bq!a\u0011\"\u0001\u0004\t)\u0006E\u0003@!\u0005]#\rE\u0002d\u00033\"a!a\u0013\"\u0005\u00041\u0017A\u0002\u0013nS:,8\u000f\u0006\u0003\u0002\u000e\u0005}\u0003BBA\u001aE\u0001\u0007!-A\u0002bij#2AYA3\u0011\u0019\tYc\ta\u0001w\u00069\u0011N\u001c3jG\u0016\u001cXCAA6!\u0011y\u0014Q\u000e:\n\u0007\u0005=\u0014H\u0001\u0004[%\u0006tw-Z\u0001\u0004[\u0006\u0004X\u0003BA;\u0003w\"B!a\u001e\u0002\u0000A)q\b\u0005:\u0002zA\u00191-a\u001f\u0005\r\u0005uTE1\u0001g\u0005\t1&\u0007C\u0004\u0002\u0002\u0016\u0002\r!a!\u0002\u0003\u0019\u0004baQACE\u0006e\u0014bAAD\t\nIa)\u001e8di&|g.M\u0001\bM>\u0014X-Y2i+\u0011\ti)a\'\u0015\t\u0005=\u0015Q\u0013\t\u0004\u0007\u0006E\u0015bAAJ\t\n!QK\\5u\u0011\u001d\t\tI\na\u0001\u0003/\u0003baQACE\u0006e\u0005cA2\u0002\u001c\u00121\u0011Q\u0014\u0014C\u0002\u0019\u0014\u0011!V\u0001\bM2\fG/T1q+\u0011\t\u0019+!+\u0015\t\u0005\u0015\u00161\u0016\t\u0006\u007fA\u0011\u0018q\u0015\t\u0004G\u0006%FABA?O\t\u0007a\rC\u0004\u0002\u0002\u001e\u0002\r!!,\u0011\r\r\u000b)IYAS\u0003\u00191\u0017\u000e\u001c;feR!\u0011QBAZ\u0011\u001d\t)\f\u000ba\u0001\u0003o\u000b\u0011\u0001\u001d\t\u0007\u0007\u0006\u0015%-!/+\t\u0005u\u00111X\u0016\u0003\u0003{\u00032aPA`\u0013\r\t\t-\u000f\u0002\u0005aV\u0014X-\u0001\u0006xSRDg)\u001b7uKJ$B!a2\u0002LB)\u0011\u0011Z\u0002sE:\u0011q\b\u0001\u0005\b\u0003kK\u0003\u0019AAg!\u0019\u0019\u0015Q\u00112\u0002\u001e\u0005A\u0011\u000e^3sCR|\'\u000f\u0006\u0002\u0002TB)\u0011Q[AnE6\u0011\u0011q\u001b\u0006\u0004\u00033t\u0016\u0001B;uS2LA!!8\u0002X\nA\u0011\n^3sCR|\'/\u0001\u0003tSj,\u0017A\u00034jeN$\u0018J\u001c3fqV\t!/A\u0005mCN$\u0018J\u001c3fq\u0006!Ao\\\'T+\t\tY\u000fE\u0003@\u0003[\u0014(-C\u0002\u0002pf\u0012!!T*\u0002\u000bQ|\u0017j\u0015.\u0016\u0005\u0005U\b#BA|\u0003{\u0014gbA \u0002z&\u0019\u00111`\u001d\u0002\u000fA\f7m[1hK&!\u0011q B\u0001\u0005\rI5KW\u0005\u0004\u0005\u00071&\u0001\u0004)bG.\fw-\u001a+sC&$\u0018!\u0002;p\u001bNSVC\u0001B\u0005!\u0015\t9Pa\u0003c\u0013\u0011\u0011iA!\u0001\u0003\u00075\u001b&,A\u0003baBd\u0017\u0010F\u0002c\u0005\'AaA!\u00062\u0001\u0004\u0011\u0018!B5oI\u0016DH\u0003BA\u0007\u00053AqAa\u00073\u0001\u0004\u0011i\"\u0001\u0003be\u001e\u001c\b#B\"\u0003 \t\r\u0012b\u0001B\u0011\t\nQAH]3qK\u0006$X\r\u001a \u0011\u000b\r\u0013)C\u001d2\n\u0007\t\u001dBI\u0001\u0004UkBdWMM\u0001\tK2,W.\u001a8ugV\u0011!Q\u0006\t\u0006\u0005_\u0011iD\u0019\b\u0005\u0005c\u0011YD\u0004\u0003\u00034\teRB\u0001B\u001b\u0015\r\u00119$P\u0001\u0007yI|w\u000e\u001e \n\u0003\u0015K1!a?E\u0013\u0011\u0011yD!\u0011\u0003\u0007M+\u0017OC\u0002\u0002|\u0012\u000b\u0001\u0002[1tQ\u000e{G-Z\u000b\u0003\u0005\u000f\u00022a\u0011B%\u0013\r\u0011Y\u0005\u0012\u0002\u0004\u0013:$\u0018AB3rk\u0006d7\u000f\u0006\u0003\u0003R\t]\u0003cA\"\u0003T%\u0019!Q\u000b#\u0003\u000f\t{w\u000e\\3b]\"1\u00111I\u001bA\u0002)\faa\u001d;sS:<WC\u0001B/!\ry$qL\u0005\u0004\u0005CJ$AB*ue&tw-\u0001\u0005u_N#(/\u001b8h)\t\u00119\u0007\u0005\u0003\u0003j\t=dbA\"\u0003l%\u0019!Q\u000e#\u0002\rA\u0013X\rZ3g\u0013\u0011\u0011\tG!\u001d\u000b\u0007\t5D\tE\u0002d\u0005k\"Q\u0001^\u0002C\u0002\u0019\u00042a\u0019B=\t\u0015)7A1\u0001g!\u001d\u0019\u0015Q\u0011B<\u0003;!bAa \u0003\u0004\n\u0015\u0005c\u0002BA\u0007\tM$qO\u0007\u0002\u0003!)QJ\u0002a\u0001\u001d\"9\u0011Q\u0017\u0004A\u0002\tmT\u0003\u0002BE\u0005\u001f#BAa#\u0003\u0012B1q\b\u0005B:\u0005\u001b\u00032a\u0019BH\t\u0019\tih\u0002b\u0001M\"9\u0011\u0011Q\u0004A\u0002\tM\u0005cB\"\u0002\u0006\n]$QR\u000b\u0005\u0005/\u0013y\n\u0006\u0003\u0002\u0010\ne\u0005bBAA\u0011\u0001\u0007!1\u0014\t\b\u0007\u0006\u0015%q\u000fBO!\r\u0019\'q\u0014\u0003\u0007\u0003;C!\u0019\u00014\u0016\t\t\r&\u0011\u0016\u000b\u0005\u0005K\u0013Y\u000b\u0005\u0004@!\tM$q\u0015\t\u0004G\n%FABA?\u0013\t\u0007a\rC\u0004\u0002\u0002&\u0001\rA!,\u0011\u000f\r\u000b)Ia\u001e\u0003&R!!q\u0010BY\u0011\u001d\u0011\u0019L\u0003a\u0001\u0005w\n!\u0001\u001d\u001a\u0002\u0013\rDWmY6TSj,W\u0003\u0002B]\u0005\u0007$BAa/\u0003FR!\u0011q\u0012B_\u0011\u0019i7\u0002q\u0001\u0003@B!q\b\u001dBa!\r\u0019\'1\u0019\u0003\u0006i.\u0011\rA\u001a\u0005\u0007\u0003?\\\u0001\u0019A>\u0016\r\t%\'\u0011\u001bBk)\u0011\u0011YMa7\u0015\t\t5\'q\u001b\t\u0007\u007fA\u0011yMa5\u0011\u0007\r\u0014\t\u000eB\u0003u\u0019\t\u0007a\rE\u0002d\u0005+$Q!\u001a\u0007C\u0002\u0019Da!\u001c\u0007A\u0004\te\u0007\u0003B q\u0005\u001fDqAa\u0007\r\u0001\u0004\u0011i\u000eE\u0003D\u0005?\u0011\u0019.\u0001\u0004de\u0016\fG/Z\u000b\u0007\u0005G\u0014YOa<\u0015\r\t\u0015(Q\u001fB|)\u0011\u00119O!=\u0011\r}\u0002\"\u0011\u001eBw!\r\u0019\'1\u001e\u0003\u0006i6\u0011\rA\u001a\t\u0004G\n=H!B3\u000e\u0005\u00041\u0007BB7\u000e\u0001\b\u0011\u0019\u0010\u0005\u0003@a\n%\bBBAp\u001b\u0001\u00071\u0010C\u0004\u0003z6\u0001\rA!<\u0002\u000f\u0011,g-Y;miV1!Q`B\u0002\u0007\u000f!\"Ba@\u0004\n\r51qBB\t!\u0019y\u0004c!\u0001\u0004\u0006A\u00191ma\u0001\u0005\u000bQt!\u0019\u00014\u0011\u0007\r\u001c9\u0001B\u0003f\u001d\t\u0007a\r\u0003\u0004n\u001d\u0001\u000711\u0002\t\u0005\u007fA\u001c\t\u0001C\u0003w\u001d\u0001\u0007!\tC\u0003z\u001d\u0001\u00071\u0010\u0003\u0004\u0000\u001d\u0001\u0007\u00111A\u0001\u000bk:\f\u0007\u000f\u001d7z\'\u0016\fXCBB\f\u0007[\u0019\u0019\u0003\u0006\u0003\u0004\u001a\r\u0015\u0002#B\"\u0004\u001c\r}\u0011bAB\u000f\t\n1q\n\u001d;j_:\u0004bAa\f\u0003>\r\u0005\u0002cA2\u0004$\u0011)Qm\u0004b\u0001M\"91qE\bA\u0002\r%\u0012!A8\u0011\r}\u000221FB\u0011!\r\u00197Q\u0006\u0003\u0006i>\u0011\rA\u001a"
    )
BootstrapMethods:
  0: #211 REF_invokeStatic java/lang/invoke/LambdaMetafactory.altMetafactory:(Ljava/lang/invoke/MethodHandles$Lookup;Ljava/lang/String;Ljava/lang/invoke/MethodType;[Ljava/lang/Object;)Ljava/lang/invoke/CallSite;
    Method arguments:
      #198 ()Ljava/lang/Object;
      #203 REF_invokeStatic org/sireum/IS.$anonfun$isInBound$1$adapted:(Lorg/sireum/IS;Lorg/sireum/Z;)Ljava/lang/Object;
      #198 ()Ljava/lang/Object;
      #204 1
  1: #211 REF_invokeStatic java/lang/invoke/LambdaMetafactory.altMetafactory:(Ljava/lang/invoke/MethodHandles$Lookup;Ljava/lang/String;Ljava/lang/invoke/MethodType;[Ljava/lang/Object;)Ljava/lang/invoke/CallSite;
    Method arguments:
      #198 ()Ljava/lang/Object;
      #295 REF_invokeStatic org/sireum/IS.$anonfun$$minus$minus$1$adapted:(Lorg/sireum/IS;)Ljava/lang/Object;
      #198 ()Ljava/lang/Object;
      #204 1
  2: #211 REF_invokeStatic java/lang/invoke/LambdaMetafactory.altMetafactory:(Ljava/lang/invoke/MethodHandles$Lookup;Ljava/lang/String;Ljava/lang/invoke/MethodType;[Ljava/lang/Object;)Ljava/lang/invoke/CallSite;
    Method arguments:
      #307 (Ljava/lang/Object;)Ljava/lang/Object;
      #312 REF_invokeStatic org/sireum/IS.$anonfun$$minus$minus$2$adapted:(Lscala/collection/immutable/Seq;Ljava/lang/Object;)Ljava/lang/Object;
      #307 (Ljava/lang/Object;)Ljava/lang/Object;
      #204 1
  3: #211 REF_invokeStatic java/lang/invoke/LambdaMetafactory.altMetafactory:(Ljava/lang/invoke/MethodHandles$Lookup;Ljava/lang/String;Ljava/lang/invoke/MethodType;[Ljava/lang/Object;)Ljava/lang/invoke/CallSite;
    Method arguments:
      #307 (Ljava/lang/Object;)Ljava/lang/Object;
      #336 REF_invokeStatic org/sireum/IS.$anonfun$$minus$minus$3$adapted:(Lscala/runtime/ObjectRef;Ljava/lang/Object;)Ljava/lang/Object;
      #307 (Ljava/lang/Object;)Ljava/lang/Object;
      #204 1
  4: #211 REF_invokeStatic java/lang/invoke/LambdaMetafactory.altMetafactory:(Ljava/lang/invoke/MethodHandles$Lookup;Ljava/lang/String;Ljava/lang/invoke/MethodType;[Ljava/lang/Object;)Ljava/lang/invoke/CallSite;
    Method arguments:
      #307 (Ljava/lang/Object;)Ljava/lang/Object;
      #352 REF_invokeStatic org/sireum/IS.$anonfun$$minus$minus$5:(Ljava/lang/Object;)Ljava/lang/Object;
      #307 (Ljava/lang/Object;)Ljava/lang/Object;
      #204 1
  5: #211 REF_invokeStatic java/lang/invoke/LambdaMetafactory.altMetafactory:(Ljava/lang/invoke/MethodHandles$Lookup;Ljava/lang/String;Ljava/lang/invoke/MethodType;[Ljava/lang/Object;)Ljava/lang/invoke/CallSite;
    Method arguments:
      #307 (Ljava/lang/Object;)Ljava/lang/Object;
      #370 REF_invokeStatic org/sireum/IS.$anonfun$$minus$minus$6$adapted:(Lorg/sireum/IS;Ljava/lang/Object;Lscala/runtime/ObjectRef;Ljava/lang/Object;)Ljava/lang/Object;
      #307 (Ljava/lang/Object;)Ljava/lang/Object;
      #204 1
  6: #211 REF_invokeStatic java/lang/invoke/LambdaMetafactory.altMetafactory:(Ljava/lang/invoke/MethodHandles$Lookup;Ljava/lang/String;Ljava/lang/invoke/MethodType;[Ljava/lang/Object;)Ljava/lang/invoke/CallSite;
    Method arguments:
      #307 (Ljava/lang/Object;)Ljava/lang/Object;
      #385 REF_invokeStatic org/sireum/IS.$anonfun$$minus$1$adapted:(Ljava/lang/Object;Ljava/lang/Object;)Ljava/lang/Object;
      #307 (Ljava/lang/Object;)Ljava/lang/Object;
      #204 1
  7: #211 REF_invokeStatic java/lang/invoke/LambdaMetafactory.altMetafactory:(Ljava/lang/invoke/MethodHandles$Lookup;Ljava/lang/String;Ljava/lang/invoke/MethodType;[Ljava/lang/Object;)Ljava/lang/invoke/CallSite;
    Method arguments:
      #198 ()Ljava/lang/Object;
      #406 REF_invokeStatic org/sireum/IS.$anonfun$atZ$1$adapted:(Lorg/sireum/IS;Lorg/sireum/Z;)Ljava/lang/Object;
      #198 ()Ljava/lang/Object;
      #204 1
  8: #211 REF_invokeStatic java/lang/invoke/LambdaMetafactory.altMetafactory:(Ljava/lang/invoke/MethodHandles$Lookup;Ljava/lang/String;Ljava/lang/invoke/MethodType;[Ljava/lang/Object;)Ljava/lang/invoke/CallSite;
    Method arguments:
      #198 ()Ljava/lang/Object;
      #412 REF_invokeStatic org/sireum/IS.$anonfun$atZ$2:(Lorg/sireum/Z;)Ljava/lang/String;
      #414 ()Ljava/lang/String;
      #415 5
      #204 1
      #414 ()Ljava/lang/String;
  9: #211 REF_invokeStatic java/lang/invoke/LambdaMetafactory.altMetafactory:(Ljava/lang/invoke/MethodHandles$Lookup;Ljava/lang/String;Ljava/lang/invoke/MethodType;[Ljava/lang/Object;)Ljava/lang/invoke/CallSite;
    Method arguments:
      #307 (Ljava/lang/Object;)Ljava/lang/Object;
      #502 REF_invokeStatic org/sireum/IS.$anonfun$flatMap$3$adapted:(Lscala/runtime/ObjectRef;Lscala/Function1;Ljava/lang/Object;)Ljava/lang/Object;
      #307 (Ljava/lang/Object;)Ljava/lang/Object;
      #204 1
  10: #211 REF_invokeStatic java/lang/invoke/LambdaMetafactory.altMetafactory:(Ljava/lang/invoke/MethodHandles$Lookup;Ljava/lang/String;Ljava/lang/invoke/MethodType;[Ljava/lang/Object;)Ljava/lang/invoke/CallSite;
    Method arguments:
      #198 ()Ljava/lang/Object;
      #531 REF_invokeStatic org/sireum/IS.$anonfun$firstIndex$1:()Ljava/lang/String;
      #414 ()Ljava/lang/String;
      #415 5
      #204 1
      #414 ()Ljava/lang/String;
  11: #211 REF_invokeStatic java/lang/invoke/LambdaMetafactory.altMetafactory:(Ljava/lang/invoke/MethodHandles$Lookup;Ljava/lang/String;Ljava/lang/invoke/MethodType;[Ljava/lang/Object;)Ljava/lang/invoke/CallSite;
    Method arguments:
      #198 ()Ljava/lang/Object;
      #547 REF_invokeStatic org/sireum/IS.$anonfun$lastIndex$1:()Ljava/lang/String;
      #414 ()Ljava/lang/String;
      #415 5
      #204 1
      #414 ()Ljava/lang/String;
  12: #211 REF_invokeStatic java/lang/invoke/LambdaMetafactory.altMetafactory:(Ljava/lang/invoke/MethodHandles$Lookup;Ljava/lang/String;Ljava/lang/invoke/MethodType;[Ljava/lang/Object;)Ljava/lang/invoke/CallSite;
    Method arguments:
      #307 (Ljava/lang/Object;)Ljava/lang/Object;
      #557 REF_invokeStatic org/sireum/IS.$anonfun$lastIndex$2$adapted:(Lscala/runtime/ObjectRef;Lorg/sireum/Z;)Ljava/lang/Object;
      #558 (Lorg/sireum/Z;)Ljava/lang/Object;
      #415 5
      #204 1
      #558 (Lorg/sireum/Z;)Ljava/lang/Object;
  13: #211 REF_invokeStatic java/lang/invoke/LambdaMetafactory.altMetafactory:(Ljava/lang/invoke/MethodHandles$Lookup;Ljava/lang/String;Ljava/lang/invoke/MethodType;[Ljava/lang/Object;)Ljava/lang/invoke/CallSite;
    Method arguments:
      #307 (Ljava/lang/Object;)Ljava/lang/Object;
      #602 REF_invokeStatic org/sireum/IS.$anonfun$apply$2$adapted:(Lscala/Tuple2;)Ljava/lang/Object;
      #603 (Lscala/Tuple2;)Ljava/lang/Object;
      #415 5
      #204 1
      #603 (Lscala/Tuple2;)Ljava/lang/Object;
  14: #211 REF_invokeStatic java/lang/invoke/LambdaMetafactory.altMetafactory:(Ljava/lang/invoke/MethodHandles$Lookup;Ljava/lang/String;Ljava/lang/invoke/MethodType;[Ljava/lang/Object;)Ljava/lang/invoke/CallSite;
    Method arguments:
      #307 (Ljava/lang/Object;)Ljava/lang/Object;
      #609 REF_invokeStatic org/sireum/IS.$anonfun$apply$3$adapted:(Lorg/sireum/IS;Ljava/lang/Object;Lscala/Tuple2;)Ljava/lang/Object;
      #603 (Lscala/Tuple2;)Ljava/lang/Object;
      #415 5
      #204 1
      #603 (Lscala/Tuple2;)Ljava/lang/Object;
  15: #211 REF_invokeStatic java/lang/invoke/LambdaMetafactory.altMetafactory:(Ljava/lang/invoke/MethodHandles$Lookup;Ljava/lang/String;Ljava/lang/invoke/MethodType;[Ljava/lang/Object;)Ljava/lang/invoke/CallSite;
    Method arguments:
      #307 (Ljava/lang/Object;)Ljava/lang/Object;
      #660 REF_invokeStatic org/sireum/IS.$anonfun$equals$1$adapted:(Lorg/sireum/$internal/Boxer;Ljava/lang/Object;Lorg/sireum/$internal/Boxer;Ljava/lang/Object;Ljava/lang/Object;Lorg/sireum/Z;)Ljava/lang/Object;
      #558 (Lorg/sireum/Z;)Ljava/lang/Object;
      #415 5
      #204 1
      #558 (Lorg/sireum/Z;)Ljava/lang/Object;
  16: #211 REF_invokeStatic java/lang/invoke/LambdaMetafactory.altMetafactory:(Ljava/lang/invoke/MethodHandles$Lookup;Ljava/lang/String;Ljava/lang/invoke/MethodType;[Ljava/lang/Object;)Ljava/lang/invoke/CallSite;
    Method arguments:
      #307 (Ljava/lang/Object;)Ljava/lang/Object;
      #717 REF_invokeStatic org/sireum/IS.$anonfun$$minus$minus$4$adapted:(Ljava/lang/Object;Ljava/lang/Object;)Ljava/lang/Object;
      #307 (Ljava/lang/Object;)Ljava/lang/Object;
      #204 1
  17: #211 REF_invokeStatic java/lang/invoke/LambdaMetafactory.altMetafactory:(Ljava/lang/invoke/MethodHandles$Lookup;Ljava/lang/String;Ljava/lang/invoke/MethodType;[Ljava/lang/Object;)Ljava/lang/invoke/CallSite;
    Method arguments:
      #198 ()Ljava/lang/Object;
      #791 REF_invokeStatic org/sireum/IS.$anonfun$apply$4$adapted:(Lorg/sireum/IS;Lorg/sireum/Z;)Ljava/lang/Object;
      #198 ()Ljava/lang/Object;
      #204 1
  18: #211 REF_invokeStatic java/lang/invoke/LambdaMetafactory.altMetafactory:(Ljava/lang/invoke/MethodHandles$Lookup;Ljava/lang/String;Ljava/lang/invoke/MethodType;[Ljava/lang/Object;)Ljava/lang/invoke/CallSite;
    Method arguments:
      #198 ()Ljava/lang/Object;
      #795 REF_invokeStatic org/sireum/IS.$anonfun$apply$5:(Ljava/lang/Object;)Ljava/lang/String;
      #414 ()Ljava/lang/String;
      #415 5
      #204 1
      #414 ()Ljava/lang/String;
  19: #869 REF_invokeStatic scala/runtime/LambdaDeserialize.bootstrap:(Ljava/lang/invoke/MethodHandles$Lookup;Ljava/lang/String;Ljava/lang/invoke/MethodType;[Ljava/lang/invoke/MethodHandle;)Ljava/lang/invoke/CallSite;
    Method arguments:
      #385 REF_invokeStatic org/sireum/IS.$anonfun$$minus$1$adapted:(Ljava/lang/Object;Ljava/lang/Object;)Ljava/lang/Object;
      #295 REF_invokeStatic org/sireum/IS.$anonfun$$minus$minus$1$adapted:(Lorg/sireum/IS;)Ljava/lang/Object;
      #312 REF_invokeStatic org/sireum/IS.$anonfun$$minus$minus$2$adapted:(Lscala/collection/immutable/Seq;Ljava/lang/Object;)Ljava/lang/Object;
      #336 REF_invokeStatic org/sireum/IS.$anonfun$$minus$minus$3$adapted:(Lscala/runtime/ObjectRef;Ljava/lang/Object;)Ljava/lang/Object;
      #717 REF_invokeStatic org/sireum/IS.$anonfun$$minus$minus$4$adapted:(Ljava/lang/Object;Ljava/lang/Object;)Ljava/lang/Object;
      #352 REF_invokeStatic org/sireum/IS.$anonfun$$minus$minus$5:(Ljava/lang/Object;)Ljava/lang/Object;
      #370 REF_invokeStatic org/sireum/IS.$anonfun$$minus$minus$6$adapted:(Lorg/sireum/IS;Ljava/lang/Object;Lscala/runtime/ObjectRef;Ljava/lang/Object;)Ljava/lang/Object;
      #602 REF_invokeStatic org/sireum/IS.$anonfun$apply$2$adapted:(Lscala/Tuple2;)Ljava/lang/Object;
      #609 REF_invokeStatic org/sireum/IS.$anonfun$apply$3$adapted:(Lorg/sireum/IS;Ljava/lang/Object;Lscala/Tuple2;)Ljava/lang/Object;
      #791 REF_invokeStatic org/sireum/IS.$anonfun$apply$4$adapted:(Lorg/sireum/IS;Lorg/sireum/Z;)Ljava/lang/Object;
      #795 REF_invokeStatic org/sireum/IS.$anonfun$apply$5:(Ljava/lang/Object;)Ljava/lang/String;
      #406 REF_invokeStatic org/sireum/IS.$anonfun$atZ$1$adapted:(Lorg/sireum/IS;Lorg/sireum/Z;)Ljava/lang/Object;
      #412 REF_invokeStatic org/sireum/IS.$anonfun$atZ$2:(Lorg/sireum/Z;)Ljava/lang/String;
      #660 REF_invokeStatic org/sireum/IS.$anonfun$equals$1$adapted:(Lorg/sireum/$internal/Boxer;Ljava/lang/Object;Lorg/sireum/$internal/Boxer;Ljava/lang/Object;Ljava/lang/Object;Lorg/sireum/Z;)Ljava/lang/Object;
      #531 REF_invokeStatic org/sireum/IS.$anonfun$firstIndex$1:()Ljava/lang/String;
      #502 REF_invokeStatic org/sireum/IS.$anonfun$flatMap$3$adapted:(Lscala/runtime/ObjectRef;Lscala/Function1;Ljava/lang/Object;)Ljava/lang/Object;
      #203 REF_invokeStatic org/sireum/IS.$anonfun$isInBound$1$adapted:(Lorg/sireum/IS;Lorg/sireum/Z;)Ljava/lang/Object;
      #547 REF_invokeStatic org/sireum/IS.$anonfun$lastIndex$1:()Ljava/lang/String;
      #557 REF_invokeStatic org/sireum/IS.$anonfun$lastIndex$2$adapted:(Lscala/runtime/ObjectRef;Lorg/sireum/Z;)Ljava/lang/Object;
  ScalaInlineInfo: length = 0x180 (unknown attribute)
   01 01 00 4C 02 D8 02 C1 01 01 7D 01 7E 01 02 B9
   02 BA 01 01 23 01 24 01 02 BC 02 BD 01 01 34 01
   35 01 02 C7 02 C8 01 01 4C 01 4D 01 02 C4 02 C1
   01 02 CA 01 7E 01 01 5D 01 32 01 02 D4 02 D5 01
   01 6E 01 6F 01 03 01 03 02 01 02 56 02 57 01 03
   0A 03 0B 01 02 5D 02 5E 01 03 05 02 B6 01 03 14
   00 C8 01 03 07 03 08 01 02 DB 02 B6 01 01 93 00
   C8 01 01 98 01 99 01 03 25 03 26 01 02 90 02 91
   01 02 10 01 9D 01 02 ED 02 EE 01 01 F2 01 F3 01
   02 B5 02 B6 01 00 C7 00 C8 01 02 20 01 9D 01 02
   F7 02 F8 01 02 29 02 2A 01 00 66 00 67 01 00 76
   00 82 01 00 76 00 77 01 00 DC 00 DD 01 00 6C 00
   6D 01 00 72 00 6D 01 01 7C 00 DD 01 01 22 01 11
   01 01 0C 00 DD 01 01 10 01 11 01 01 B8 02 36 01
   00 94 01 32 01 00 94 02 40 01 01 89 01 6B 01 00
   3C 00 88 01 00 35 00 7E 01 00 38 00 82 01 01 2E
   01 2F 01 00 A6 00 A7 01 01 85 01 86 01 02 0C 00
   82 01 01 ED 01 86 01 00 59 00 5A 01 01 54 01 55
   01 00 8B 00 85 01 00 33 00 91 01 02 78 00 91 01
   01 A7 01 A8 01 00 98 00 6D 01 00 AE 00 A7 01 02
   08 02 09 01 02 1F 00 82 01 00 3A 00 85 01 01 64
   01 86 01 00 AD 00 6D 01 00 50 00 85 01 00 61 00
   62 01 02 A4 01 9D 01 02 39 02 3A 01 02 31 02 32
   01 02 43 02 32 01 02 AA 01 9D 01 01 3E 02 03 01

  ScalaSig: length = 0x3 (unknown attribute)
   05 02 00
