Classfile /Users/mw/Projects/slang-braindump/.jar/jar11/assemble/slang-braindump/assemble/content/org/sireum/Jen$Internal$.class
  Last modified May 29, 2022; size 1992 bytes
  SHA-256 checksum a9a6600c638a14dfe6e79dbcf851f411cf0d4532cfd1fb1184c1f884762d2c34
  Compiled from "Jen.scala"
public class org.sireum.Jen$Internal$
  minor version: 0
  major version: 52
  flags: (0x0021) ACC_PUBLIC, ACC_SUPER
  this_class: #2                          // org/sireum/Jen$Internal$
  super_class: #4                         // java/lang/Object
  interfaces: 0, fields: 1, methods: 2, attributes: 4
Constant pool:
    #1 = Utf8               org/sireum/Jen$Internal$
    #2 = Class              #1            // org/sireum/Jen$Internal$
    #3 = Utf8               java/lang/Object
    #4 = Class              #3            // java/lang/Object
    #5 = Utf8               Jen.scala
    #6 = Utf8               org/sireum/Jen
    #7 = Class              #6            // org/sireum/Jen
    #8 = Utf8               Internal$
    #9 = Utf8               org/sireum/Jen$Internal$Concat
   #10 = Class              #9            // org/sireum/Jen$Internal$Concat
   #11 = Utf8               Concat
   #12 = Utf8               org/sireum/Jen$Internal$Concat$
   #13 = Class              #12           // org/sireum/Jen$Internal$Concat$
   #14 = Utf8               Concat$
   #15 = Utf8               org/sireum/Jen$Internal$DropWhile
   #16 = Class              #15           // org/sireum/Jen$Internal$DropWhile
   #17 = Utf8               DropWhile
   #18 = Utf8               org/sireum/Jen$Internal$DropWhile$
   #19 = Class              #18           // org/sireum/Jen$Internal$DropWhile$
   #20 = Utf8               DropWhile$
   #21 = Utf8               org/sireum/Jen$Internal$Filtered
   #22 = Class              #21           // org/sireum/Jen$Internal$Filtered
   #23 = Utf8               Filtered
   #24 = Utf8               org/sireum/Jen$Internal$Filtered$
   #25 = Class              #24           // org/sireum/Jen$Internal$Filtered$
   #26 = Utf8               Filtered$
   #27 = Utf8               org/sireum/Jen$Internal$FlatMapped
   #28 = Class              #27           // org/sireum/Jen$Internal$FlatMapped
   #29 = Utf8               FlatMapped
   #30 = Utf8               org/sireum/Jen$Internal$FlatMapped$
   #31 = Class              #30           // org/sireum/Jen$Internal$FlatMapped$
   #32 = Utf8               FlatMapped$
   #33 = Utf8               org/sireum/Jen$Internal$HashMapImpl
   #34 = Class              #33           // org/sireum/Jen$Internal$HashMapImpl
   #35 = Utf8               HashMapImpl
   #36 = Utf8               org/sireum/Jen$Internal$HashMapImpl$
   #37 = Class              #36           // org/sireum/Jen$Internal$HashMapImpl$
   #38 = Utf8               HashMapImpl$
   #39 = Utf8               org/sireum/Jen$Internal$ISImpl
   #40 = Class              #39           // org/sireum/Jen$Internal$ISImpl
   #41 = Utf8               ISImpl
   #42 = Utf8               org/sireum/Jen$Internal$ISImpl$
   #43 = Class              #42           // org/sireum/Jen$Internal$ISImpl$
   #44 = Utf8               ISImpl$
   #45 = Utf8               org/sireum/Jen$Internal$MapImpl
   #46 = Class              #45           // org/sireum/Jen$Internal$MapImpl
   #47 = Utf8               MapImpl
   #48 = Utf8               org/sireum/Jen$Internal$MapImpl$
   #49 = Class              #48           // org/sireum/Jen$Internal$MapImpl$
   #50 = Utf8               MapImpl$
   #51 = Utf8               org/sireum/Jen$Internal$Mapped
   #52 = Class              #51           // org/sireum/Jen$Internal$Mapped
   #53 = Utf8               Mapped
   #54 = Utf8               org/sireum/Jen$Internal$Mapped$
   #55 = Class              #54           // org/sireum/Jen$Internal$Mapped$
   #56 = Utf8               Mapped$
   #57 = Utf8               org/sireum/Jen$Internal$Product
   #58 = Class              #57           // org/sireum/Jen$Internal$Product
   #59 = Utf8               Product
   #60 = Utf8               org/sireum/Jen$Internal$Product$
   #61 = Class              #60           // org/sireum/Jen$Internal$Product$
   #62 = Utf8               Product$
   #63 = Utf8               org/sireum/Jen$Internal$Sliced
   #64 = Class              #63           // org/sireum/Jen$Internal$Sliced
   #65 = Utf8               Sliced
   #66 = Utf8               org/sireum/Jen$Internal$Sliced$
   #67 = Class              #66           // org/sireum/Jen$Internal$Sliced$
   #68 = Utf8               Sliced$
   #69 = Utf8               org/sireum/Jen$Internal$TakeWhile
   #70 = Class              #69           // org/sireum/Jen$Internal$TakeWhile
   #71 = Utf8               TakeWhile
   #72 = Utf8               org/sireum/Jen$Internal$TakeWhile$
   #73 = Class              #72           // org/sireum/Jen$Internal$TakeWhile$
   #74 = Utf8               TakeWhile$
   #75 = Utf8               org/sireum/Jen$Internal$ZipWithIndexed
   #76 = Class              #75           // org/sireum/Jen$Internal$ZipWithIndexed
   #77 = Utf8               ZipWithIndexed
   #78 = Utf8               org/sireum/Jen$Internal$ZipWithIndexed$
   #79 = Class              #78           // org/sireum/Jen$Internal$ZipWithIndexed$
   #80 = Utf8               ZipWithIndexed$
   #81 = Utf8               org/sireum/Jen$Internal$Zipped
   #82 = Class              #81           // org/sireum/Jen$Internal$Zipped
   #83 = Utf8               Zipped
   #84 = Utf8               org/sireum/Jen$Internal$Zipped$
   #85 = Class              #84           // org/sireum/Jen$Internal$Zipped$
   #86 = Utf8               Zipped$
   #87 = Utf8               MODULE$
   #88 = Utf8               Lorg/sireum/Jen$Internal$;
   #89 = Utf8               <clinit>
   #90 = Utf8               ()V
   #91 = Utf8               <init>
   #92 = NameAndType        #91:#90       // "<init>":()V
   #93 = Methodref          #2.#92        // org/sireum/Jen$Internal$."<init>":()V
   #94 = NameAndType        #87:#88       // MODULE$:Lorg/sireum/Jen$Internal$;
   #95 = Fieldref           #2.#94        // org/sireum/Jen$Internal$.MODULE$:Lorg/sireum/Jen$Internal$;
   #96 = Methodref          #4.#92        // java/lang/Object."<init>":()V
   #97 = Utf8               this
   #98 = Utf8               Code
   #99 = Utf8               LineNumberTable
  #100 = Utf8               LocalVariableTable
  #101 = Utf8               InnerClasses
  #102 = Utf8               SourceFile
  #103 = Utf8               ScalaInlineInfo
  #104 = Utf8               Scala
{
  public static final org.sireum.Jen$Internal$ MODULE$;
    descriptor: Lorg/sireum/Jen$Internal$;
    flags: (0x0019) ACC_PUBLIC, ACC_STATIC, ACC_FINAL

  public static {};
    descriptor: ()V
    flags: (0x0009) ACC_PUBLIC, ACC_STATIC
    Code:
      stack=2, locals=0, args_size=0
         0: new           #2                  // class org/sireum/Jen$Internal$
         3: dup
         4: invokespecial #93                 // Method "<init>":()V
         7: putstatic     #95                 // Field MODULE$:Lorg/sireum/Jen$Internal$;
        10: return
      LineNumberTable:
        line 245: 0

  public org.sireum.Jen$Internal$();
    descriptor: ()V
    flags: (0x0001) ACC_PUBLIC
    Code:
      stack=1, locals=1, args_size=1
         0: aload_0
         1: invokespecial #96                 // Method java/lang/Object."<init>":()V
         4: return
      LineNumberTable:
        line 245: 0
      LocalVariableTable:
        Start  Length  Slot  Name   Signature
            0       5     0  this   Lorg/sireum/Jen$Internal$;
}
InnerClasses:
  public static #8= #2 of #7;             // Internal$=class org/sireum/Jen$Internal$ of class org/sireum/Jen
  public static final #11= #10 of #2;     // Concat=class org/sireum/Jen$Internal$Concat of class org/sireum/Jen$Internal$
  public static #14= #13 of #2;           // Concat$=class org/sireum/Jen$Internal$Concat$ of class org/sireum/Jen$Internal$
  public static final #17= #16 of #2;     // DropWhile=class org/sireum/Jen$Internal$DropWhile of class org/sireum/Jen$Internal$
  public static #20= #19 of #2;           // DropWhile$=class org/sireum/Jen$Internal$DropWhile$ of class org/sireum/Jen$Internal$
  public static final #23= #22 of #2;     // Filtered=class org/sireum/Jen$Internal$Filtered of class org/sireum/Jen$Internal$
  public static #26= #25 of #2;           // Filtered$=class org/sireum/Jen$Internal$Filtered$ of class org/sireum/Jen$Internal$
  public static final #29= #28 of #2;     // FlatMapped=class org/sireum/Jen$Internal$FlatMapped of class org/sireum/Jen$Internal$
  public static #32= #31 of #2;           // FlatMapped$=class org/sireum/Jen$Internal$FlatMapped$ of class org/sireum/Jen$Internal$
  public static final #35= #34 of #2;     // HashMapImpl=class org/sireum/Jen$Internal$HashMapImpl of class org/sireum/Jen$Internal$
  public static #38= #37 of #2;           // HashMapImpl$=class org/sireum/Jen$Internal$HashMapImpl$ of class org/sireum/Jen$Internal$
  public static final #41= #40 of #2;     // ISImpl=class org/sireum/Jen$Internal$ISImpl of class org/sireum/Jen$Internal$
  public static #44= #43 of #2;           // ISImpl$=class org/sireum/Jen$Internal$ISImpl$ of class org/sireum/Jen$Internal$
  public static final #47= #46 of #2;     // MapImpl=class org/sireum/Jen$Internal$MapImpl of class org/sireum/Jen$Internal$
  public static #50= #49 of #2;           // MapImpl$=class org/sireum/Jen$Internal$MapImpl$ of class org/sireum/Jen$Internal$
  public static final #53= #52 of #2;     // Mapped=class org/sireum/Jen$Internal$Mapped of class org/sireum/Jen$Internal$
  public static #56= #55 of #2;           // Mapped$=class org/sireum/Jen$Internal$Mapped$ of class org/sireum/Jen$Internal$
  public static final #59= #58 of #2;     // Product=class org/sireum/Jen$Internal$Product of class org/sireum/Jen$Internal$
  public static #62= #61 of #2;           // Product$=class org/sireum/Jen$Internal$Product$ of class org/sireum/Jen$Internal$
  public static final #65= #64 of #2;     // Sliced=class org/sireum/Jen$Internal$Sliced of class org/sireum/Jen$Internal$
  public static #68= #67 of #2;           // Sliced$=class org/sireum/Jen$Internal$Sliced$ of class org/sireum/Jen$Internal$
  public static final #71= #70 of #2;     // TakeWhile=class org/sireum/Jen$Internal$TakeWhile of class org/sireum/Jen$Internal$
  public static #74= #73 of #2;           // TakeWhile$=class org/sireum/Jen$Internal$TakeWhile$ of class org/sireum/Jen$Internal$
  public static final #77= #76 of #2;     // ZipWithIndexed=class org/sireum/Jen$Internal$ZipWithIndexed of class org/sireum/Jen$Internal$
  public static #80= #79 of #2;           // ZipWithIndexed$=class org/sireum/Jen$Internal$ZipWithIndexed$ of class org/sireum/Jen$Internal$
  public static final #83= #82 of #2;     // Zipped=class org/sireum/Jen$Internal$Zipped of class org/sireum/Jen$Internal$
  public static #86= #85 of #2;           // Zipped$=class org/sireum/Jen$Internal$Zipped$ of class org/sireum/Jen$Internal$
SourceFile: "Jen.scala"
  ScalaInlineInfo: length = 0x9 (unknown attribute)
   01 01 00 01 00 5B 00 5A 01
  Scala: length = 0x0 (unknown attribute)

