Classfile /Users/mw/Projects/slang-braindump/.jar/jar11/assemble/slang-braindump/assemble/content/org/sireum/Json$Parser$.class
  Last modified May 29, 2022; size 2410 bytes
  SHA-256 checksum 52a6af996c66f8e037061ba9a7df826a5f0e8362d4247045dd458d9aeb07ab21
  Compiled from "Json.scala"
public class org.sireum.Json$Parser$
  minor version: 0
  major version: 52
  flags: (0x0021) ACC_PUBLIC, ACC_SUPER
  this_class: #2                          // org/sireum/Json$Parser$
  super_class: #4                         // java/lang/Object
  interfaces: 0, fields: 1, methods: 5, attributes: 4
Constant pool:
    #1 = Utf8               org/sireum/Json$Parser$
    #2 = Class              #1            // org/sireum/Json$Parser$
    #3 = Utf8               java/lang/Object
    #4 = Class              #3            // java/lang/Object
    #5 = Utf8               Json.scala
    #6 = Utf8               org/sireum/Json$ErrorMsg
    #7 = Class              #6            // org/sireum/Json$ErrorMsg
    #8 = Utf8               org/sireum/Json
    #9 = Class              #8            // org/sireum/Json
   #10 = Utf8               ErrorMsg
   #11 = Utf8               org/sireum/Json$Parser
   #12 = Class              #11           // org/sireum/Json$Parser
   #13 = Utf8               Parser
   #14 = Utf8               Parser$
   #15 = Utf8               MODULE$
   #16 = Utf8               Lorg/sireum/Json$Parser$;
   #17 = Utf8               <clinit>
   #18 = Utf8               ()V
   #19 = Utf8               <init>
   #20 = NameAndType        #19:#18       // "<init>":()V
   #21 = Methodref          #2.#20        // org/sireum/Json$Parser$."<init>":()V
   #22 = NameAndType        #15:#16       // MODULE$:Lorg/sireum/Json$Parser$;
   #23 = Fieldref           #2.#22        // org/sireum/Json$Parser$.MODULE$:Lorg/sireum/Json$Parser$;
   #24 = Utf8               create
   #25 = Utf8               (Ljava/lang/String;)Lorg/sireum/Json$Parser;
   #26 = Utf8               input
   #27 = Utf8               org/sireum/helper$
   #28 = Class              #27           // org/sireum/helper$
   #29 = Utf8               Lorg/sireum/helper$;
   #30 = NameAndType        #15:#29       // MODULE$:Lorg/sireum/helper$;
   #31 = Fieldref           #28.#30       // org/sireum/helper$.MODULE$:Lorg/sireum/helper$;
   #32 = Utf8               org/sireum/conversions/String$
   #33 = Class              #32           // org/sireum/conversions/String$
   #34 = Utf8               Lorg/sireum/conversions/String$;
   #35 = NameAndType        #15:#34       // MODULE$:Lorg/sireum/conversions/String$;
   #36 = Fieldref           #33.#35       // org/sireum/conversions/String$.MODULE$:Lorg/sireum/conversions/String$;
   #37 = Utf8               toCis
   #38 = Utf8               (Ljava/lang/String;)Lorg/sireum/IS;
   #39 = NameAndType        #37:#38       // toCis:(Ljava/lang/String;)Lorg/sireum/IS;
   #40 = Methodref          #33.#39       // org/sireum/conversions/String$.toCis:(Ljava/lang/String;)Lorg/sireum/IS;
   #41 = Utf8               org/sireum/Z$
   #42 = Class              #41           // org/sireum/Z$
   #43 = Utf8               Lorg/sireum/Z$;
   #44 = NameAndType        #15:#43       // MODULE$:Lorg/sireum/Z$;
   #45 = Fieldref           #42.#44       // org/sireum/Z$.MODULE$:Lorg/sireum/Z$;
   #46 = Utf8               apply
   #47 = Utf8               (I)Lorg/sireum/Z;
   #48 = NameAndType        #46:#47       // apply:(I)Lorg/sireum/Z;
   #49 = Methodref          #42.#48       // org/sireum/Z$.apply:(I)Lorg/sireum/Z;
   #50 = Utf8               org/sireum/None$
   #51 = Class              #50           // org/sireum/None$
   #52 = Utf8               Lorg/sireum/None$;
   #53 = NameAndType        #15:#52       // MODULE$:Lorg/sireum/None$;
   #54 = Fieldref           #51.#53       // org/sireum/None$.MODULE$:Lorg/sireum/None$;
   #55 = Utf8               ()Lorg/sireum/None;
   #56 = NameAndType        #46:#55       // apply:()Lorg/sireum/None;
   #57 = Methodref          #51.#56       // org/sireum/None$.apply:()Lorg/sireum/None;
   #58 = Utf8               (Lorg/sireum/IS;Lorg/sireum/Z;Lorg/sireum/Option;)Lorg/sireum/Json$Parser;
   #59 = NameAndType        #46:#58       // apply:(Lorg/sireum/IS;Lorg/sireum/Z;Lorg/sireum/Option;)Lorg/sireum/Json$Parser;
   #60 = Methodref          #2.#59        // org/sireum/Json$Parser$.apply:(Lorg/sireum/IS;Lorg/sireum/Z;Lorg/sireum/Option;)Lorg/sireum/Json$Parser;
   #61 = Utf8               retMut
   #62 = Utf8               (Lorg/sireum/$internal/MutableMarker;)Ljava/lang/Object;
   #63 = NameAndType        #61:#62       // retMut:(Lorg/sireum/$internal/MutableMarker;)Ljava/lang/Object;
   #64 = Methodref          #28.#63       // org/sireum/helper$.retMut:(Lorg/sireum/$internal/MutableMarker;)Ljava/lang/Object;
   #65 = Utf8               this
   #66 = Utf8               Ljava/lang/String;
   #67 = Utf8               (Lorg/sireum/IS<Lorg/sireum/Z;Lorg/sireum/C;>;Lorg/sireum/Z;Lorg/sireum/Option<Lorg/sireum/Json$ErrorMsg;>;)Lorg/sireum/Json$Parser;
   #68 = Utf8               offset
   #69 = Utf8               errorOpt
   #70 = Utf8               (Lorg/sireum/IS;Lorg/sireum/Z;Lorg/sireum/Option;)V
   #71 = NameAndType        #19:#70       // "<init>":(Lorg/sireum/IS;Lorg/sireum/Z;Lorg/sireum/Option;)V
   #72 = Methodref          #12.#71       // org/sireum/Json$Parser."<init>":(Lorg/sireum/IS;Lorg/sireum/Z;Lorg/sireum/Option;)V
   #73 = Utf8               Lorg/sireum/IS;
   #74 = Utf8               Lorg/sireum/Z;
   #75 = Utf8               Lorg/sireum/Option;
   #76 = Utf8               unapply
   #77 = Utf8               (Lorg/sireum/Json$Parser;)Lscala/Some;
   #78 = Utf8               (Lorg/sireum/Json$Parser;)Lscala/Some<Lscala/Tuple3<Lorg/sireum/IS<Lorg/sireum/Z;Lorg/sireum/C;>;Lorg/sireum/Z;Lorg/sireum/Option<Lorg/sireum/Json$ErrorMsg;>;>;>;
   #79 = Utf8               o
   #80 = Utf8               scala/Some
   #81 = Class              #80           // scala/Some
   #82 = Utf8               scala/Tuple3
   #83 = Class              #82           // scala/Tuple3
   #84 = Utf8               ()Lorg/sireum/IS;
   #85 = NameAndType        #26:#84       // input:()Lorg/sireum/IS;
   #86 = Methodref          #12.#85       // org/sireum/Json$Parser.input:()Lorg/sireum/IS;
   #87 = Utf8               clone
   #88 = Utf8               (Ljava/lang/Object;)Ljava/lang/Object;
   #89 = NameAndType        #87:#88       // clone:(Ljava/lang/Object;)Ljava/lang/Object;
   #90 = Methodref          #28.#89       // org/sireum/helper$.clone:(Ljava/lang/Object;)Ljava/lang/Object;
   #91 = Utf8               ()Lorg/sireum/Z;
   #92 = NameAndType        #68:#91       // offset:()Lorg/sireum/Z;
   #93 = Methodref          #12.#92       // org/sireum/Json$Parser.offset:()Lorg/sireum/Z;
   #94 = Utf8               ()Lorg/sireum/Option;
   #95 = NameAndType        #69:#94       // errorOpt:()Lorg/sireum/Option;
   #96 = Methodref          #12.#95       // org/sireum/Json$Parser.errorOpt:()Lorg/sireum/Option;
   #97 = Utf8               (Ljava/lang/Object;Ljava/lang/Object;Ljava/lang/Object;)V
   #98 = NameAndType        #19:#97       // "<init>":(Ljava/lang/Object;Ljava/lang/Object;Ljava/lang/Object;)V
   #99 = Methodref          #83.#98       // scala/Tuple3."<init>":(Ljava/lang/Object;Ljava/lang/Object;Ljava/lang/Object;)V
  #100 = Utf8               (Ljava/lang/Object;)V
  #101 = NameAndType        #19:#100      // "<init>":(Ljava/lang/Object;)V
  #102 = Methodref          #81.#101      // scala/Some."<init>":(Ljava/lang/Object;)V
  #103 = Utf8               Lorg/sireum/Json$Parser;
  #104 = Methodref          #4.#20        // java/lang/Object."<init>":()V
  #105 = Utf8               Code
  #106 = Utf8               LineNumberTable
  #107 = Utf8               LocalVariableTable
  #108 = Utf8               MethodParameters
  #109 = Utf8               Signature
  #110 = Utf8               InnerClasses
  #111 = Utf8               SourceFile
  #112 = Utf8               ScalaInlineInfo
  #113 = Utf8               Scala
{
  public static final org.sireum.Json$Parser$ MODULE$;
    descriptor: Lorg/sireum/Json$Parser$;
    flags: (0x0019) ACC_PUBLIC, ACC_STATIC, ACC_FINAL

  public static {};
    descriptor: ()V
    flags: (0x0009) ACC_PUBLIC, ACC_STATIC
    Code:
      stack=2, locals=0, args_size=0
         0: new           #2                  // class org/sireum/Json$Parser$
         3: dup
         4: invokespecial #21                 // Method "<init>":()V
         7: putstatic     #23                 // Field MODULE$:Lorg/sireum/Json$Parser$;
        10: return
      LineNumberTable:
        line 651: 0

  public org.sireum.Json$Parser create(java.lang.String);
    descriptor: (Ljava/lang/String;)Lorg/sireum/Json$Parser;
    flags: (0x0001) ACC_PUBLIC
    Code:
      stack=5, locals=2, args_size=2
         0: getstatic     #31                 // Field org/sireum/helper$.MODULE$:Lorg/sireum/helper$;
         3: aload_0
         4: getstatic     #36                 // Field org/sireum/conversions/String$.MODULE$:Lorg/sireum/conversions/String$;
         7: aload_1
         8: invokevirtual #40                 // Method org/sireum/conversions/String$.toCis:(Ljava/lang/String;)Lorg/sireum/IS;
        11: getstatic     #45                 // Field org/sireum/Z$.MODULE$:Lorg/sireum/Z$;
        14: iconst_0
        15: invokevirtual #49                 // Method org/sireum/Z$.apply:(I)Lorg/sireum/Z;
        18: getstatic     #54                 // Field org/sireum/None$.MODULE$:Lorg/sireum/None$;
        21: invokevirtual #57                 // Method org/sireum/None$.apply:()Lorg/sireum/None;
        24: invokevirtual #60                 // Method apply:(Lorg/sireum/IS;Lorg/sireum/Z;Lorg/sireum/Option;)Lorg/sireum/Json$Parser;
        27: invokevirtual #64                 // Method org/sireum/helper$.retMut:(Lorg/sireum/$internal/MutableMarker;)Ljava/lang/Object;
        30: checkcast     #12                 // class org/sireum/Json$Parser
        33: areturn
      LineNumberTable:
        line 654: 0
      LocalVariableTable:
        Start  Length  Slot  Name   Signature
            0      34     0  this   Lorg/sireum/Json$Parser$;
            0      34     1 input   Ljava/lang/String;
    MethodParameters:
      Name                           Flags
      input                          final

  public org.sireum.Json$Parser apply(org.sireum.IS<org.sireum.Z, org.sireum.C>, org.sireum.Z, org.sireum.Option<org.sireum.Json$ErrorMsg>);
    descriptor: (Lorg/sireum/IS;Lorg/sireum/Z;Lorg/sireum/Option;)Lorg/sireum/Json$Parser;
    flags: (0x0001) ACC_PUBLIC
    Code:
      stack=5, locals=4, args_size=4
         0: new           #12                 // class org/sireum/Json$Parser
         3: dup
         4: aload_1
         5: aload_2
         6: aload_3
         7: invokespecial #72                 // Method org/sireum/Json$Parser."<init>":(Lorg/sireum/IS;Lorg/sireum/Z;Lorg/sireum/Option;)V
        10: areturn
      LineNumberTable:
        line 651: 0
      LocalVariableTable:
        Start  Length  Slot  Name   Signature
            0      11     0  this   Lorg/sireum/Json$Parser$;
            0      11     1 input   Lorg/sireum/IS;
            0      11     2 offset   Lorg/sireum/Z;
            0      11     3 errorOpt   Lorg/sireum/Option;
    Signature: #67                          // (Lorg/sireum/IS<Lorg/sireum/Z;Lorg/sireum/C;>;Lorg/sireum/Z;Lorg/sireum/Option<Lorg/sireum/Json$ErrorMsg;>;)Lorg/sireum/Json$Parser;
    MethodParameters:
      Name                           Flags
      input                          final
      offset                         final
      errorOpt                       final

  public scala.Some<scala.Tuple3<org.sireum.IS<org.sireum.Z, org.sireum.C>, org.sireum.Z, org.sireum.Option<org.sireum.Json$ErrorMsg>>> unapply(org.sireum.Json$Parser);
    descriptor: (Lorg/sireum/Json$Parser;)Lscala/Some;
    flags: (0x0001) ACC_PUBLIC
    Code:
      stack=8, locals=2, args_size=2
         0: new           #81                 // class scala/Some
         3: dup
         4: new           #83                 // class scala/Tuple3
         7: dup
         8: getstatic     #31                 // Field org/sireum/helper$.MODULE$:Lorg/sireum/helper$;
        11: aload_1
        12: invokevirtual #86                 // Method org/sireum/Json$Parser.input:()Lorg/sireum/IS;
        15: invokevirtual #90                 // Method org/sireum/helper$.clone:(Ljava/lang/Object;)Ljava/lang/Object;
        18: getstatic     #31                 // Field org/sireum/helper$.MODULE$:Lorg/sireum/helper$;
        21: aload_1
        22: invokevirtual #93                 // Method org/sireum/Json$Parser.offset:()Lorg/sireum/Z;
        25: invokevirtual #90                 // Method org/sireum/helper$.clone:(Ljava/lang/Object;)Ljava/lang/Object;
        28: getstatic     #31                 // Field org/sireum/helper$.MODULE$:Lorg/sireum/helper$;
        31: aload_1
        32: invokevirtual #96                 // Method org/sireum/Json$Parser.errorOpt:()Lorg/sireum/Option;
        35: invokevirtual #90                 // Method org/sireum/helper$.clone:(Ljava/lang/Object;)Ljava/lang/Object;
        38: invokespecial #99                 // Method scala/Tuple3."<init>":(Ljava/lang/Object;Ljava/lang/Object;Ljava/lang/Object;)V
        41: invokespecial #102                // Method scala/Some."<init>":(Ljava/lang/Object;)V
        44: areturn
      LineNumberTable:
        line 651: 0
      LocalVariableTable:
        Start  Length  Slot  Name   Signature
            0      45     0  this   Lorg/sireum/Json$Parser$;
            0      45     1     o   Lorg/sireum/Json$Parser;
    Signature: #78                          // (Lorg/sireum/Json$Parser;)Lscala/Some<Lscala/Tuple3<Lorg/sireum/IS<Lorg/sireum/Z;Lorg/sireum/C;>;Lorg/sireum/Z;Lorg/sireum/Option<Lorg/sireum/Json$ErrorMsg;>;>;>;
    MethodParameters:
      Name                           Flags
      o                              final

  public org.sireum.Json$Parser$();
    descriptor: ()V
    flags: (0x0001) ACC_PUBLIC
    Code:
      stack=1, locals=1, args_size=1
         0: aload_0
         1: invokespecial #104                // Method java/lang/Object."<init>":()V
         4: return
      LineNumberTable:
        line 651: 0
      LocalVariableTable:
        Start  Length  Slot  Name   Signature
            0       5     0  this   Lorg/sireum/Json$Parser$;
}
InnerClasses:
  public static final #10= #7 of #9;      // ErrorMsg=class org/sireum/Json$ErrorMsg of class org/sireum/Json
  public static final #13= #12 of #9;     // Parser=class org/sireum/Json$Parser of class org/sireum/Json
  public static #14= #2 of #9;            // Parser$=class org/sireum/Json$Parser$ of class org/sireum/Json
SourceFile: "Json.scala"
  ScalaInlineInfo: length = 0x18 (unknown attribute)
   01 01 00 04 00 13 00 12 01 00 2E 00 3A 01 00 18
   00 19 01 00 4C 00 4D 01
  Scala: length = 0x0 (unknown attribute)

