Classfile /Users/mw/Projects/slang-braindump/.jar/jar11/assemble/slang-braindump/assemble/content/org/sireum/just.class
  Last modified May 29, 2022; size 1099 bytes
  SHA-256 checksum 13535cde55cd12d41fde1558d52e5090596d8c6930cff5fd2371031522247170
  Compiled from "Annotations.scala"
public class org.sireum.just extends scala.annotation.Annotation implements scala.annotation.StaticAnnotation
  minor version: 0
  major version: 52
  flags: (0x0021) ACC_PUBLIC, ACC_SUPER
  this_class: #2                          // org/sireum/just
  super_class: #4                         // scala/annotation/Annotation
  interfaces: 1, fields: 0, methods: 2, attributes: 4
Constant pool:
   #1 = Utf8               org/sireum/just
   #2 = Class              #1             // org/sireum/just
   #3 = Utf8               scala/annotation/Annotation
   #4 = Class              #3             // scala/annotation/Annotation
   #5 = Utf8               scala/annotation/StaticAnnotation
   #6 = Class              #5             // scala/annotation/StaticAnnotation
   #7 = Utf8               Annotations.scala
   #8 = Utf8               Lscala/reflect/ScalaSignature;
   #9 = Utf8               bytes
  #10 = Utf8               \u0006\u0005Q2Aa\u0002\u0005\u0001\u001b!A\u0011\u0004\u0001B\u0001B\u0003%!\u0004C\u0003\u001f\u0001\u0011\u0005qdB\u0004#\u0011\u0005\u0005\t\u0012A\u0012\u0007\u000f\u001dA\u0011\u0011!E\u0001I!)a\u0004\u0002C\u0001S!9!\u0006BI\u0001\n\u0003Y#\u0001\u00026vgRT!!\u0003\u0006\u0002\rML\'/Z;n\u0015\u0005Y\u0011aA8sO\u000e\u00011c\u0001\u0001\u000f-A\u0011q\u0002F\u0007\u0002!)\u0011\u0011CE\u0001\u000bC:tw\u000e^1uS>t\'\"A\n\u0002\u000bM\u001c\u0017\r\\1\n\u0005U\u0001\"AC!o]>$\u0018\r^5p]B\u0011qbF\u0005\u00031A\u0011\u0001c\u0015;bi&\u001c\u0017I\u001c8pi\u0006$\u0018n\u001c8\u0002\t9\fW.\u001a\t\u00037qi\u0011\u0001C\u0005\u0003;!\u0011aa\u0015;sS:<\u0017A\u0002\u001fj]&$h\b\u0006\u0002!CA\u00111\u0004\u0001\u0005\b3\t\u0001\n\u00111\u0001\u001b\u0003\u0011QWo\u001d;\u0011\u0005m!1C\u0001\u0003&!\t1s%D\u0001\u0013\u0013\tA#C\u0001\u0004B]f\u0014VM\u001a\u000b\u0002G\u0005YB\u0005\\3tg&t\u0017\u000e\u001e\u0013he\u0016\fG/\u001a:%I\u00164\u0017-\u001e7uIE*\u0012\u0001\f\u0016\u000355Z\u0013A\f\t\u0003_Ij\u0011\u0001\r\u0006\u0003cA\t\u0011\"\u001e8dQ\u0016\u001c7.\u001a3\n\u0005M\u0002$!E;oG\",7m[3e-\u0006\u0014\u0018.\u00198dK\u0002
  #11 = Utf8               $lessinit$greater$default$1
  #12 = Utf8               ()Ljava/lang/String;
  #13 = Utf8               org/sireum/just$
  #14 = Class              #13            // org/sireum/just$
  #15 = Utf8               MODULE$
  #16 = Utf8               Lorg/sireum/just$;
  #17 = NameAndType        #15:#16        // MODULE$:Lorg/sireum/just$;
  #18 = Fieldref           #14.#17        // org/sireum/just$.MODULE$:Lorg/sireum/just$;
  #19 = NameAndType        #11:#12        // $lessinit$greater$default$1:()Ljava/lang/String;
  #20 = Methodref          #14.#19        // org/sireum/just$.$lessinit$greater$default$1:()Ljava/lang/String;
  #21 = Utf8               <init>
  #22 = Utf8               (Ljava/lang/String;)V
  #23 = Utf8               name
  #24 = Utf8               ()V
  #25 = NameAndType        #21:#24        // "<init>":()V
  #26 = Methodref          #4.#25         // scala/annotation/Annotation."<init>":()V
  #27 = Utf8               this
  #28 = Utf8               Lorg/sireum/just;
  #29 = Utf8               Ljava/lang/String;
  #30 = Utf8               Code
  #31 = Utf8               LineNumberTable
  #32 = Utf8               LocalVariableTable
  #33 = Utf8               MethodParameters
  #34 = Utf8               SourceFile
  #35 = Utf8               RuntimeVisibleAnnotations
  #36 = Utf8               ScalaInlineInfo
  #37 = Utf8               ScalaSig
{
  public static java.lang.String $lessinit$greater$default$1();
    descriptor: ()Ljava/lang/String;
    flags: (0x0009) ACC_PUBLIC, ACC_STATIC
    Code:
      stack=1, locals=0, args_size=0
         0: getstatic     #18                 // Field org/sireum/just$.MODULE$:Lorg/sireum/just$;
         3: invokevirtual #20                 // Method org/sireum/just$.$lessinit$greater$default$1:()Ljava/lang/String;
         6: areturn

  public org.sireum.just(java.lang.String);
    descriptor: (Ljava/lang/String;)V
    flags: (0x0001) ACC_PUBLIC
    Code:
      stack=1, locals=2, args_size=2
         0: aload_0
         1: invokespecial #26                 // Method scala/annotation/Annotation."<init>":()V
         4: return
      LineNumberTable:
        line 36: 0
      LocalVariableTable:
        Start  Length  Slot  Name   Signature
            0       5     0  this   Lorg/sireum/just;
            0       5     1  name   Ljava/lang/String;
    MethodParameters:
      Name                           Flags
      name                           final
}
SourceFile: "Annotations.scala"
RuntimeVisibleAnnotations:
  0: #8(#9=s#10)
    scala.reflect.ScalaSignature(
      bytes="\u0006\u0005Q2Aa\u0002\u0005\u0001\u001b!A\u0011\u0004\u0001B\u0001B\u0003%!\u0004C\u0003\u001f\u0001\u0011\u0005qdB\u0004#\u0011\u0005\u0005\t\u0012A\u0012\u0007\u000f\u001dA\u0011\u0011!E\u0001I!)a\u0004\u0002C\u0001S!9!\u0006BI\u0001\n\u0003Y#\u0001\u00026vgRT!!\u0003\u0006\u0002\rML\'/Z;n\u0015\u0005Y\u0011aA8sO\u000e\u00011c\u0001\u0001\u000f-A\u0011q\u0002F\u0007\u0002!)\u0011\u0011CE\u0001\u000bC:tw\u000e^1uS>t\'\"A\n\u0002\u000bM\u001c\u0017\r\\1\n\u0005U\u0001\"AC!o]>$\u0018\r^5p]B\u0011qbF\u0005\u00031A\u0011\u0001c\u0015;bi&\u001c\u0017I\u001c8pi\u0006$\u0018n\u001c8\u0002\t9\fW.\u001a\t\u00037qi\u0011\u0001C\u0005\u0003;!\u0011aa\u0015;sS:<\u0017A\u0002\u001fj]&$h\b\u0006\u0002!CA\u00111\u0004\u0001\u0005\b3\t\u0001\n\u00111\u0001\u001b\u0003\u0011QWo\u001d;\u0011\u0005m!1C\u0001\u0003&!\t1s%D\u0001\u0013\u0013\tA#C\u0001\u0004B]f\u0014VM\u001a\u000b\u0002G\u0005YB\u0005\\3tg&t\u0017\u000e\u001e\u0013he\u0016\fG/\u001a:%I\u00164\u0017-\u001e7uIE*\u0012\u0001\f\u0016\u000355Z\u0013A\f\t\u0003_Ij\u0011\u0001\r\u0006\u0003cA\t\u0011\"\u001e8dQ\u0016\u001c7.\u001a3\n\u0005M\u0002$!E;oG\",7m[3e-\u0006\u0014\u0018.\u00198dK\u0002"
    )
  ScalaInlineInfo: length = 0x9 (unknown attribute)
   01 00 00 01 00 15 00 16 00
  ScalaSig: length = 0x3 (unknown attribute)
   05 02 00
