Classfile /Users/mw/Projects/slang-braindump/.jar/jar11/assemble/slang-braindump/assemble/content/org/sireum/MBox10.class
  Last modified May 29, 2022; size 17838 bytes
  SHA-256 checksum 9b975d9f552f3350452a58b9b2eb4ed816239ecfbf0d0f1e382e1877cf84134b
  Compiled from "MBox.scala"
public final class org.sireum.MBox10<T1 extends java.lang.Object, T2 extends java.lang.Object, T3 extends java.lang.Object, T4 extends java.lang.Object, T5 extends java.lang.Object, T6 extends java.lang.Object, T7 extends java.lang.Object, T8 extends java.lang.Object, T9 extends java.lang.Object, T10 extends java.lang.Object> extends java.lang.Object implements org.sireum.RecordSig
  minor version: 0
  major version: 52
  flags: (0x0031) ACC_PUBLIC, ACC_FINAL, ACC_SUPER
  this_class: #2                          // org/sireum/MBox10
  super_class: #5                         // java/lang/Object
  interfaces: 1, fields: 11, methods: 70, attributes: 5
Constant pool:
    #1 = Utf8               org/sireum/MBox10
    #2 = Class              #1            // org/sireum/MBox10
    #3 = Utf8               <T1:Ljava/lang/Object;T2:Ljava/lang/Object;T3:Ljava/lang/Object;T4:Ljava/lang/Object;T5:Ljava/lang/Object;T6:Ljava/lang/Object;T7:Ljava/lang/Object;T8:Ljava/lang/Object;T9:Ljava/lang/Object;T10:Ljava/lang/Object;>Ljava/lang/Object;Lorg/sireum/RecordSig;
    #4 = Utf8               java/lang/Object
    #5 = Class              #4            // java/lang/Object
    #6 = Utf8               org/sireum/RecordSig
    #7 = Class              #6            // org/sireum/RecordSig
    #8 = Utf8               MBox.scala
    #9 = Utf8               Lscala/reflect/ScalaSignature;
   #10 = Utf8               bytes
   #11 = Utf8               \u0006\u0005\r\u0005t!\u0002+V\u0011\u0003Qf!\u0002/V\u0011\u0003i\u0006\"\u00023\u0002\t\u0003)\u0007\"\u00024\u0002\t\u00039\u0007bBB\u0012\u0003\u0011\u00051Q\u0005\u0004\u00059V\u0013!\u000e\u0003\u0005p\u000b\t\u0005\t\u0015!\u0003q\u0011!YXA!A!\u0002\u0013a\b\"C@\u0006\u0005\u0003\u0005\u000b\u0011BA\u0001\u0011)\t9!\u0002B\u0001B\u0003%\u0011\u0011\u0002\u0005\u000b\u0003\u001f)!\u0011!Q\u0001\n\u0005E\u0001BCA\f\u000b\t\u0005\t\u0015!\u0003\u0002\u001a!Q\u0011qD\u0003\u0003\u0002\u0003\u0006I!!\t\t\u0015\u0005\u001dRA!A!\u0002\u0013\tI\u0003\u0003\u0006\u00020\u0015\u0011\t\u0011)A\u0005\u0003cA!\"a\u000e\u0006\u0005\u0003\u0005\u000b\u0011BA\u001d\u0011\u0019!W\u0001\"\u0001\u0002@!9\u0011qK\u0003!B\u0013\u0001\bbBA-\u000b\u0011\u0005\u00111\f\u0005\b\u0003;*A\u0011AA.\u0011\u001d\ty&\u0002C\u0001\u0003CBq!a\u001a\u0006\t\u0003\tI\u0007C\u0004\u0002n\u0015\u0001\u000b\u0015\u0002?\t\u000f\u0005=T\u0001\"\u0001\u0002r!9\u00111O\u0003\u0005\u0002\u0005E\u0004bBA;\u000b\u0011\u0005\u0011q\u000f\u0005\b\u0003w*A\u0011AA?\u0011!\t\t)\u0002Q!\n\u0005\u0005\u0001bBAB\u000b\u0011\u0005\u0011Q\u0011\u0005\b\u0003\u000f+A\u0011AAC\u0011\u001d\tI)\u0002C\u0001\u0003\u0017Cq!a$\u0006\t\u0003\t\t\n\u0003\u0005\u0002\u0016\u0016\u0001\u000b\u0015BA\u0005\u0011\u001d\t9*\u0002C\u0001\u00033Cq!a\'\u0006\t\u0003\tI\nC\u0004\u0002\u001e\u0016!\t!a(\t\u000f\u0005\rV\u0001\"\u0001\u0002&\"A\u0011\u0011V\u0003!B\u0013\t\t\u0002C\u0004\u0002,\u0016!\t!!,\t\u000f\u0005=V\u0001\"\u0001\u0002.\"9\u0011\u0011W\u0003\u0005\u0002\u0005M\u0006bBA\\\u000b\u0011\u0005\u0011\u0011\u0018\u0005\t\u0003{+\u0001\u0015)\u0003\u0002\u001a!9\u0011qX\u0003\u0005\u0002\u0005\u0005\u0007bBAb\u000b\u0011\u0005\u0011\u0011\u0019\u0005\b\u0003\u000b,A\u0011AAd\u0011\u001d\tY-\u0002C\u0001\u0003\u001bD\u0001\"!5\u0006A\u0003&\u0011\u0011\u0005\u0005\b\u0003\',A\u0011AAk\u0011\u001d\t9.\u0002C\u0001\u0003+Dq!!7\u0006\t\u0003\tY\u000eC\u0004\u0002`\u0016!\t!!9\t\u0011\u0005\u0015X\u0001)Q\u0005\u0003SAq!a:\u0006\t\u0003\tI\u000fC\u0004\u0002l\u0016!\t!!;\t\u000f\u00055X\u0001\"\u0001\u0002p\"9\u00111_\u0003\u0005\u0002\u0005U\b\u0002CA}\u000b\u0001\u0006K!!\r\t\u000f\u0005mX\u0001\"\u0001\u0002~\"9\u0011q`\u0003\u0005\u0002\u0005u\bb\u0002B\u0001\u000b\u0011\u0005!1\u0001\u0005\b\u0005\u000f)A\u0011\u0001B\u0005\u0011!\u0011i!\u0002Q!\n\u0005e\u0002b\u0002B\b\u000b\u0011\u0005!\u0011\u0003\u0005\b\u0005\')A\u0011\u0001B\t\u0011\u001d\u0011)\"\u0002C\u0001\u0005/AqAa\u0007\u0006\t\u0003\u0011i\u0002C\u0004\u0003\"\u0015!\tEa\t\t\u000f\tUR\u0001\"\u0011\u00038!9!QH\u0003\u0005B\t}\u0002b\u0002B$\u000b\u0011\u0005#\u0011\n\u0005\u0007M\u0016!\tA!\u0016\t\u0013\t-T!%A\u0005\u0002\t5\u0004\"\u0003BB\u000bE\u0005I\u0011\u0001BC\u0011%\u0011I)BI\u0001\n\u0003\u0011Y\tC\u0005\u0003\u0010\u0016\t\n\u0011\"\u0001\u0003\u0012\"I!QS\u0003\u0012\u0002\u0013\u0005!q\u0013\u0005\n\u00057+\u0011\u0013!C\u0001\u0005;C\u0011B!)\u0006#\u0003%\tAa)\t\u0013\t\u001dV!%A\u0005\u0002\t%\u0006\"\u0003BW\u000bE\u0005I\u0011\u0001BX\u0011%\u0011\u0019,BI\u0001\n\u0003\u0011)\fC\u0004\u0003:\u0016!\tEa/\t\u000f\tmW\u0001\"\u0011\u0003^\u00061QJQ8ycAR!AV,\u0002\rML\'/Z;n\u0015\u0005A\u0016aA8sO\u000e\u0001\u0001CA.\u0002\u001b\u0005)&AB\'C_b\f\u0004g\u0005\u0002\u0002=B\u0011qLY\u0007\u0002A*\t\u0011-A\u0003tG\u0006d\u0017-\u0003\u0002dA\n1\u0011I\\=SK\u001a\fa\u0001P5oSRtD#\u0001.\u0002\u000b\u0005\u0004\b\u000f\\=\u0016+!\u0014IO!<\u0003r\nU(\u0011 B\u007f\u0007\u0003\u0019)a!\u0003\u0004\u000eQ)\u0012na\u0004\u0004\u0012\rM1QCB\f\u00073\u0019Yb!\b\u0004 \r\u0005\u0002CF.\u0006\u0005O\u0014YOa<\u0003t\n](1 B\u0000\u0007\u0007\u00199aa\u0003\u0016\'-\u0014X0a\u0001\u0002\f\u0005M\u00111DA\u0012\u0003W\t\u0019$a\u000f\u0014\u0007\u0015qF\u000e\u0005\u0002\\[&\u0011a.\u0016\u0002\n%\u0016\u001cwN\u001d3TS\u001e\f\u0001bX0wC2,X-\r\t\u0003cJd\u0001\u0001B\u0003t\u000b\t\u0007AO\u0001\u0002UcE\u0011Q\u000f\u001f\t\u0003?ZL!a\u001e1\u0003\u000f9{G\u000f[5oOB\u0011q,_\u0005\u0003u\u0002\u00141!\u00118z\u0003!yvL^1mk\u0016\u0014\u0004CA9~\t\u0015qXA1\u0001u\u0005\t!&\'\u0001\u0005`?Z\fG.^34!\r\t\u00181\u0001\u0003\u0007\u0003\u000b)!\u0019\u0001;\u0003\u0005Q\u001b\u0014\u0001C0`m\u0006dW/\u001a\u001b\u0011\u0007E\fY\u0001\u0002\u0004\u0002\u000e\u0015\u0011\r\u0001\u001e\u0002\u0003)R\n\u0001bX0wC2,X-\u000e\t\u0004c\u0006MAABA\u000b\u000b\t\u0007AO\u0001\u0002Uk\u0005Aql\u0018<bYV,g\u0007E\u0002r\u00037!a!!\b\u0006\u0005\u0004!(A\u0001+7\u0003!yvL^1mk\u0016<\u0004cA9\u0002$\u00111\u0011QE\u0003C\u0002Q\u0014!\u0001V\u001c\u0002\u0011}{f/\u00197vKb\u00022!]A\u0016\t\u0019\ti#\u0002b\u0001i\n\u0011A\u000bO\u0001\t?~3\u0018\r\\;fsA\u0019\u0011/a\r\u0005\r\u0005URA1\u0001u\u0005\t!\u0016(A\u0005`?Z\fG.^32aA\u0019\u0011/a\u000f\u0005\r\u0005uRA1\u0001u\u0005\r!\u0016\u0007\r\u000b\u0017\u0003\u0003\n\u0019%!\u0012\u0002H\u0005%\u00131JA\'\u0003\u001f\n\t&a\u0015\u0002VA!2,\u00029}\u0003\u0003\tI!!\u0005\u0002\u001a\u0005\u0005\u0012\u0011FA\u0019\u0003sAQa\u001c\tA\u0002ADQa\u001f\tA\u0002qDaa \tA\u0002\u0005\u0005\u0001bBA\u0004!\u0001\u0007\u0011\u0011\u0002\u0005\b\u0003\u001f\u0001\u0002\u0019AA\t\u0011\u001d\t9\u0002\u0005a\u0001\u00033Aq!a\b\u0011\u0001\u0004\t\t\u0003C\u0004\u0002(A\u0001\r!!\u000b\t\u000f\u0005=\u0002\u00031\u0001\u00022!9\u0011q\u0007\tA\u0002\u0005e\u0012aB0wC2,X-M\u0001\u0007m\u0006dW/Z\u0019\u0016\u0003A\f\u0011bZ3u-\u0006dW/Z\u0019\u0002\u0015Y\fG.^32?\u0012*\u0017\u000f\u0006\u0003\u0002d\u0005\u0015T\"A\u0003\t\r\u0005eC\u00031\u0001q\u0003%\u0019X\r\u001e,bYV,\u0017\u0007\u0006\u0003\u0002d\u0005-\u0004BBA-+\u0001\u0007\u0001/A\u0004`m\u0006dW/\u001a\u001a\u0002\rY\fG.^33+\u0005a\u0018!C4fiZ\u000bG.^33\u0003)1\u0018\r\\;fe}#S-\u001d\u000b\u0005\u0003G\nI\b\u0003\u0004\u0002pe\u0001\r\u0001`\u0001\ng\u0016$h+\u00197vKJ\"B!a\u0019\u0002\u0000!1\u0011q\u000e\u000eA\u0002q\fqa\u0018<bYV,7\'\u0001\u0004wC2,XmM\u000b\u0003\u0003\u0003\t\u0011bZ3u-\u0006dW/Z\u001a\u0002\u0015Y\fG.^34?\u0012*\u0017\u000f\u0006\u0003\u0002d\u00055\u0005bBAB=\u0001\u0007\u0011\u0011A\u0001\ng\u0016$h+\u00197vKN\"B!a\u0019\u0002\u0014\"9\u00111Q\u0010A\u0002\u0005\u0005\u0011aB0wC2,X\rN\u0001\u0007m\u0006dW/\u001a\u001b\u0016\u0005\u0005%\u0011!C4fiZ\u000bG.^35\u0003)1\u0018\r\\;fi}#S-\u001d\u000b\u0005\u0003G\n\t\u000bC\u0004\u0002\u0018\u000e\u0002\r!!\u0003\u0002\u0013M,GOV1mk\u0016$D\u0003BA2\u0003OCq!a&%\u0001\u0004\tI!A\u0004`m\u0006dW/Z\u001b\u0002\rY\fG.^36+\t\t\t\"A\u0005hKR4\u0016\r\\;fk\u0005Qa/\u00197vKVzF%Z9\u0015\t\u0005\r\u0014Q\u0017\u0005\b\u0003WC\u0003\u0019AA\t\u0003%\u0019X\r\u001e,bYV,W\u0007\u0006\u0003\u0002d\u0005m\u0006bBAVS\u0001\u0007\u0011\u0011C\u0001\b?Z\fG.^37\u0003\u00191\u0018\r\\;fmU\u0011\u0011\u0011D\u0001\nO\u0016$h+\u00197vKZ\n!B^1mk\u00164t\fJ3r)\u0011\t\u0019\'!3\t\u000f\u0005}V\u00061\u0001\u0002\u001a\u0005I1/\u001a;WC2,XM\u000e\u000b\u0005\u0003G\ny\rC\u0004\u0002@:\u0002\r!!\u0007\u0002\u000f}3\u0018\r\\;fo\u00051a/\u00197vK^*\"!!\t\u0002\u0013\u001d,GOV1mk\u0016<\u0014A\u0003<bYV,wg\u0018\u0013fcR!\u00111MAo\u0011\u001d\t\u0019N\ra\u0001\u0003C\t\u0011b]3u-\u0006dW/Z\u001c\u0015\t\u0005\r\u00141\u001d\u0005\b\u0003\'\u001c\u0004\u0019AA\u0011\u0003\u001dyf/\u00197vKb\naA^1mk\u0016DTCAA\u0015\u0003%9W\r\u001e,bYV,\u0007(\u0001\u0006wC2,X\rO0%KF$B!a\u0019\u0002r\"9\u0011q]\u001cA\u0002\u0005%\u0012!C:fiZ\u000bG.^39)\u0011\t\u0019\'a>\t\u000f\u0005\u001d\b\b1\u0001\u0002*\u00059qL^1mk\u0016L\u0014A\u0002<bYV,\u0017(\u0006\u0002\u00022\u0005Iq-\u001a;WC2,X-O\u0001\u000bm\u0006dW/Z\u001d`I\u0015\fH\u0003BA2\u0005\u000bAq!a?=\u0001\u0004\t\t$A\u0005tKR4\u0016\r\\;fsQ!\u00111\rB\u0006\u0011\u001d\tY0\u0010a\u0001\u0003c\t\u0001b\u0018<bYV,\u0017\u0007M\u0001\bm\u0006dW/Z\u00191+\t\tI$\u0001\u0006hKR4\u0016\r\\;fcA\n1B^1mk\u0016\f\u0004g\u0018\u0013fcR!\u00111\rB\r\u0011\u001d\u0011y!\u0011a\u0001\u0003s\t!b]3u-\u0006dW/Z\u00191)\u0011\t\u0019Ga\b\t\u000f\t=!\t1\u0001\u0002:\u0005AAo\\*ue&tw\r\u0006\u0002\u0003&A!!q\u0005B\u0019\u001b\t\u0011IC\u0003\u0003\u0003,\t5\u0012\u0001\u00027b]\u001eT!Aa\f\u0002\t)\fg/Y\u0005\u0005\u0005g\u0011IC\u0001\u0004TiJLgnZ\u0001\u0007gR\u0014\u0018N\\4\u0016\u0005\te\u0002cA.\u0003<%\u0019!1G+\u0002\u0011!\f7\u000f[\"pI\u0016$\"A!\u0011\u0011\u0007}\u0013\u0019%C\u0002\u0003F\u0001\u00141!\u00138u\u0003\u0019)\u0017/^1mgR!!1\nB)!\ry&QJ\u0005\u0004\u0005\u001f\u0002\'a\u0002\"p_2,\u0017M\u001c\u0005\u0007\u0005\'2\u0005\u0019\u0001=\u0002\u0003=$b#!\u0011\u0003X\te#1\fB/\u0005?\u0012\tGa\u0019\u0003f\t\u001d$\u0011\u000e\u0005\t\u00033:\u0005\u0013!a\u0001a\"A\u0011qN$\u0011\u0002\u0003\u0007A\u0010C\u0005\u0002\u0004\u001e\u0003\n\u00111\u0001\u0002\u0002!I\u0011qS$\u0011\u0002\u0003\u0007\u0011\u0011\u0002\u0005\n\u0003W;\u0005\u0013!a\u0001\u0003#A\u0011\"a0H!\u0003\u0005\r!!\u0007\t\u0013\u0005Mw\t%AA\u0002\u0005\u0005\u0002\"CAt\u000fB\u0005\t\u0019AA\u0015\u0011%\tYp\u0012I\u0001\u0002\u0004\t\t\u0004C\u0005\u0003\u0010\u001d\u0003\n\u00111\u0001\u0002:\u0005y\u0011\r\u001d9ms\u0012\"WMZ1vYR$\u0013\'\u0006\u0002\u0003p)\u001a\u0001O!\u001d,\u0005\tM\u0004\u0003\u0002B;\u0005\u007fj!Aa\u001e\u000b\t\te$1P\u0001\nk:\u001c\u0007.Z2lK\u0012T1A! a\u0003)\tgN\\8uCRLwN\\\u0005\u0005\u0005\u0003\u00139HA\tv]\u000eDWmY6fIZ\u000b\'/[1oG\u0016\fq\"\u00199qYf$C-\u001a4bk2$HEM\u000b\u0003\u0005\u000fS3\u0001 B9\u0003=\t\u0007\u000f\u001d7zI\u0011,g-Y;mi\u0012\u001aTC\u0001BGU\u0011\t\tA!\u001d\u0002\u001f\u0005\u0004\b\u000f\\=%I\u00164\u0017-\u001e7uIQ*\"Aa%+\t\u0005%!\u0011O\u0001\u0010CB\u0004H.\u001f\u0013eK\u001a\fW\u000f\u001c;%kU\u0011!\u0011\u0014\u0016\u0005\u0003#\u0011\t(A\bbaBd\u0017\u0010\n3fM\u0006,H\u000e\u001e\u00137+\t\u0011yJ\u000b\u0003\u0002\u001a\tE\u0014aD1qa2LH\u0005Z3gCVdG\u000fJ\u001c\u0016\u0005\t\u0015&\u0006BA\u0011\u0005c\nq\"\u00199qYf$C-\u001a4bk2$H\u0005O\u000b\u0003\u0005WSC!!\u000b\u0003r\u0005y\u0011\r\u001d9ms\u0012\"WMZ1vYR$\u0013(\u0006\u0002\u00032*\"\u0011\u0011\u0007B9\u0003A\t\u0007\u000f\u001d7zI\u0011,g-Y;mi\u0012\n\u0004\'\u0006\u0002\u00038*\"\u0011\u0011\bB9\u0003!!3m\u001c8uK:$XC\u0001B_!\u0019\u0011yLa4\u0003V:!!\u0011\u0019Bf\u001d\u0011\u0011\u0019M!3\u000e\u0005\t\u0015\'b\u0001Bd3\u00061AH]8pizJ\u0011!Y\u0005\u0004\u0005\u001b\u0004\u0017a\u00029bG.\fw-Z\u0005\u0005\u0005#\u0014\u0019NA\u0002TKFT1A!4a!\u0019y&q\u001bB\u0013q&\u0019!\u0011\u001c1\u0003\rQ+\b\u000f\\33\u0003\u0019!3\r\\8oKV\u0011\u0011\u0011\t\u0015\u0004\u000b\t\u0005\bcA.\u0003d&\u0019!Q]+\u0003\rI,7m\u001c:e!\r\t(\u0011\u001e\u0003\u0006g\u000e\u0011\r\u0001\u001e\t\u0004c\n5H!\u0002@\u0004\u0005\u0004!\bcA9\u0003r\u00121\u0011QA\u0002C\u0002Q\u00042!\u001dB{\t\u0019\tia\u0001b\u0001iB\u0019\u0011O!?\u0005\r\u0005U1A1\u0001u!\r\t(Q \u0003\u0007\u0003;\u0019!\u0019\u0001;\u0011\u0007E\u001c\t\u0001\u0002\u0004\u0002&\r\u0011\r\u0001\u001e\t\u0004c\u000e\u0015AABA\u0017\u0007\t\u0007A\u000fE\u0002r\u0007\u0013!a!!\u000e\u0004\u0005\u0004!\bcA9\u0004\u000e\u00111\u0011QH\u0002C\u0002QDq!!\u0017\u0004\u0001\u0004\u00119\u000fC\u0004\u0002p\r\u0001\rAa;\t\u000f\u0005\r5\u00011\u0001\u0003p\"9\u0011qS\u0002A\u0002\tM\bbBAV\u0007\u0001\u0007!q\u001f\u0005\b\u0003\u007f\u001b\u0001\u0019\u0001B~\u0011\u001d\t\u0019n\u0001a\u0001\u0005\u007fDq!a:\u0004\u0001\u0004\u0019\u0019\u0001C\u0004\u0002|\u000e\u0001\raa\u0002\t\u000f\t=1\u00011\u0001\u0004\f\u00059QO\\1qa2LXCFB\u0014\u0007o\u0019Yda\u0010\u0004D\r\u001d31JB(\u0007\'\u001a9fa\u0017\u0015\t\r%2Q\f\t\u0006?\u000e-2qF\u0005\u0004\u0007[\u0001\'\u0001B*p[\u0016\u0004rcXB\u0019\u0007k\u0019Id!\u0010\u0004B\r\u00153\u0011JB\'\u0007#\u001a)f!\u0017\n\u0007\rM\u0002MA\u0004UkBdW-\r\u0019\u0011\u0007E\u001c9\u0004B\u0003t\t\t\u0007A\u000fE\u0002r\u0007w!QA \u0003C\u0002Q\u00042!]B \t\u0019\t)\u0001\u0002b\u0001iB\u0019\u0011oa\u0011\u0005\r\u00055AA1\u0001u!\r\t8q\t\u0003\u0007\u0003+!!\u0019\u0001;\u0011\u0007E\u001cY\u0005\u0002\u0004\u0002\u001e\u0011\u0011\r\u0001\u001e\t\u0004c\u000e=CABA\u0013\t\t\u0007A\u000fE\u0002r\u0007\'\"a!!\f\u0005\u0005\u0004!\bcA9\u0004X\u00111\u0011Q\u0007\u0003C\u0002Q\u00042!]B.\t\u0019\ti\u0004\u0002b\u0001i\"9!1\u000b\u0003A\u0002\r}\u0003CF.\u0006\u0007k\u0019Id!\u0010\u0004B\r\u00153\u0011JB\'\u0007#\u001a)f!\u0017
   #12 = Utf8               _value1
   #13 = Utf8               Ljava/lang/Object;
   #14 = Utf8               TT1;
   #15 = Utf8               _value2
   #16 = Utf8               TT2;
   #17 = Utf8               _value3
   #18 = Utf8               TT3;
   #19 = Utf8               _value4
   #20 = Utf8               TT4;
   #21 = Utf8               _value5
   #22 = Utf8               TT5;
   #23 = Utf8               _value6
   #24 = Utf8               TT6;
   #25 = Utf8               _value7
   #26 = Utf8               TT7;
   #27 = Utf8               _value8
   #28 = Utf8               TT8;
   #29 = Utf8               _value9
   #30 = Utf8               TT9;
   #31 = Utf8               _value10
   #32 = Utf8               TT10;
   #33 = Utf8               org$sireum$RecordSig$$$isOwned
   #34 = Utf8               Z
   #35 = Utf8               unapply
   #36 = Utf8               (Lorg/sireum/MBox10;)Lscala/Some;
   #37 = Utf8               <T1:Ljava/lang/Object;T2:Ljava/lang/Object;T3:Ljava/lang/Object;T4:Ljava/lang/Object;T5:Ljava/lang/Object;T6:Ljava/lang/Object;T7:Ljava/lang/Object;T8:Ljava/lang/Object;T9:Ljava/lang/Object;T10:Ljava/lang/Object;>(Lorg/sireum/MBox10<TT1;TT2;TT3;TT4;TT5;TT6;TT7;TT8;TT9;TT10;>;)Lscala/Some<Lscala/Tuple10<TT1;TT2;TT3;TT4;TT5;TT6;TT7;TT8;TT9;TT10;>;>;
   #38 = Utf8               o
   #39 = Utf8               org/sireum/MBox10$
   #40 = Class              #39           // org/sireum/MBox10$
   #41 = Utf8               MODULE$
   #42 = Utf8               Lorg/sireum/MBox10$;
   #43 = NameAndType        #41:#42       // MODULE$:Lorg/sireum/MBox10$;
   #44 = Fieldref           #40.#43       // org/sireum/MBox10$.MODULE$:Lorg/sireum/MBox10$;
   #45 = NameAndType        #35:#36       // unapply:(Lorg/sireum/MBox10;)Lscala/Some;
   #46 = Methodref          #40.#45       // org/sireum/MBox10$.unapply:(Lorg/sireum/MBox10;)Lscala/Some;
   #47 = Utf8               Lorg/sireum/MBox10;
   #48 = Utf8               $owned
   #49 = Utf8               ()Z
   #50 = Utf8               $owned$
   #51 = Utf8               (Lorg/sireum/RecordSig;)Z
   #52 = NameAndType        #50:#51       // $owned$:(Lorg/sireum/RecordSig;)Z
   #53 = InterfaceMethodref #7.#52        // org/sireum/RecordSig.$owned$:(Lorg/sireum/RecordSig;)Z
   #54 = Utf8               this
   #55 = Utf8               $owned_$eq
   #56 = Utf8               (Z)Lorg/sireum/RecordSig;
   #57 = Utf8               b
   #58 = Utf8               $owned_$eq$
   #59 = Utf8               (Lorg/sireum/RecordSig;Z)Lorg/sireum/RecordSig;
   #60 = NameAndType        #58:#59       // $owned_$eq$:(Lorg/sireum/RecordSig;Z)Lorg/sireum/RecordSig;
   #61 = InterfaceMethodref #7.#60        // org/sireum/RecordSig.$owned_$eq$:(Lorg/sireum/RecordSig;Z)Lorg/sireum/RecordSig;
   #62 = Utf8               hash
   #63 = Utf8               ()Lorg/sireum/Z;
   #64 = Utf8               hash$
   #65 = Utf8               (Lorg/sireum/RecordSig;)Lorg/sireum/Z;
   #66 = NameAndType        #64:#65       // hash$:(Lorg/sireum/RecordSig;)Lorg/sireum/Z;
   #67 = InterfaceMethodref #7.#66        // org/sireum/RecordSig.hash$:(Lorg/sireum/RecordSig;)Lorg/sireum/Z;
   #68 = Utf8               $cannotMixImmutableAndMutable
   #69 = Utf8               ()Lscala/runtime/Nothing$;
   #70 = Utf8               org/sireum/Mutable
   #71 = Class              #70           // org/sireum/Mutable
   #72 = Utf8               $cannotMixImmutableAndMutable$
   #73 = Utf8               (Lorg/sireum/Mutable;)Lscala/runtime/Nothing$;
   #74 = NameAndType        #72:#73       // $cannotMixImmutableAndMutable$:(Lorg/sireum/Mutable;)Lscala/runtime/Nothing$;
   #75 = InterfaceMethodref #71.#74       // org/sireum/Mutable.$cannotMixImmutableAndMutable$:(Lorg/sireum/Mutable;)Lscala/runtime/Nothing$;
   #76 = Utf8               $hasEquals
   #77 = Utf8               $hasEquals$
   #78 = Utf8               (Lorg/sireum/Mutable;)Z
   #79 = NameAndType        #77:#78       // $hasEquals$:(Lorg/sireum/Mutable;)Z
   #80 = InterfaceMethodref #71.#79       // org/sireum/Mutable.$hasEquals$:(Lorg/sireum/Mutable;)Z
   #81 = Utf8               $hasString
   #82 = Utf8               $hasString$
   #83 = NameAndType        #82:#78       // $hasString$:(Lorg/sireum/Mutable;)Z
   #84 = InterfaceMethodref #71.#83       // org/sireum/Mutable.$hasString$:(Lorg/sireum/Mutable;)Z
   #85 = NameAndType        #33:#34       // org$sireum$RecordSig$$$isOwned:Z
   #86 = Fieldref           #2.#85        // org/sireum/MBox10.org$sireum$RecordSig$$$isOwned:Z
   #87 = Utf8               org$sireum$RecordSig$$$isOwned_$eq
   #88 = Utf8               (Z)V
   #89 = Utf8               x$1
   #90 = Utf8               value1
   #91 = Utf8               ()Ljava/lang/Object;
   #92 = Utf8               ()TT1;
   #93 = NameAndType        #12:#13       // _value1:Ljava/lang/Object;
   #94 = Fieldref           #2.#93        // org/sireum/MBox10._value1:Ljava/lang/Object;
   #95 = Utf8               getValue1
   #96 = Utf8               value1_$eq
   #97 = Utf8               (Ljava/lang/Object;)Lorg/sireum/MBox10;
   #98 = Utf8               (TT1;)Lorg/sireum/MBox10<TT1;TT2;TT3;TT4;TT5;TT6;TT7;TT8;TT9;TT10;>;
   #99 = Utf8               setValue1
  #100 = Utf8               value2
  #101 = Utf8               ()TT2;
  #102 = NameAndType        #15:#13       // _value2:Ljava/lang/Object;
  #103 = Fieldref           #2.#102       // org/sireum/MBox10._value2:Ljava/lang/Object;
  #104 = Utf8               getValue2
  #105 = Utf8               value2_$eq
  #106 = Utf8               (TT2;)Lorg/sireum/MBox10<TT1;TT2;TT3;TT4;TT5;TT6;TT7;TT8;TT9;TT10;>;
  #107 = Utf8               setValue2
  #108 = Utf8               value3
  #109 = Utf8               ()TT3;
  #110 = NameAndType        #17:#13       // _value3:Ljava/lang/Object;
  #111 = Fieldref           #2.#110       // org/sireum/MBox10._value3:Ljava/lang/Object;
  #112 = Utf8               getValue3
  #113 = Utf8               value3_$eq
  #114 = Utf8               (TT3;)Lorg/sireum/MBox10<TT1;TT2;TT3;TT4;TT5;TT6;TT7;TT8;TT9;TT10;>;
  #115 = Utf8               setValue3
  #116 = Utf8               value4
  #117 = Utf8               ()TT4;
  #118 = NameAndType        #19:#13       // _value4:Ljava/lang/Object;
  #119 = Fieldref           #2.#118       // org/sireum/MBox10._value4:Ljava/lang/Object;
  #120 = Utf8               getValue4
  #121 = Utf8               value4_$eq
  #122 = Utf8               (TT4;)Lorg/sireum/MBox10<TT1;TT2;TT3;TT4;TT5;TT6;TT7;TT8;TT9;TT10;>;
  #123 = Utf8               setValue4
  #124 = Utf8               value5
  #125 = Utf8               ()TT5;
  #126 = NameAndType        #21:#13       // _value5:Ljava/lang/Object;
  #127 = Fieldref           #2.#126       // org/sireum/MBox10._value5:Ljava/lang/Object;
  #128 = Utf8               getValue5
  #129 = Utf8               value5_$eq
  #130 = Utf8               (TT5;)Lorg/sireum/MBox10<TT1;TT2;TT3;TT4;TT5;TT6;TT7;TT8;TT9;TT10;>;
  #131 = Utf8               setValue5
  #132 = Utf8               value6
  #133 = Utf8               ()TT6;
  #134 = NameAndType        #23:#13       // _value6:Ljava/lang/Object;
  #135 = Fieldref           #2.#134       // org/sireum/MBox10._value6:Ljava/lang/Object;
  #136 = Utf8               getValue6
  #137 = Utf8               value6_$eq
  #138 = Utf8               (TT6;)Lorg/sireum/MBox10<TT1;TT2;TT3;TT4;TT5;TT6;TT7;TT8;TT9;TT10;>;
  #139 = Utf8               setValue6
  #140 = Utf8               value7
  #141 = Utf8               ()TT7;
  #142 = NameAndType        #25:#13       // _value7:Ljava/lang/Object;
  #143 = Fieldref           #2.#142       // org/sireum/MBox10._value7:Ljava/lang/Object;
  #144 = Utf8               getValue7
  #145 = Utf8               value7_$eq
  #146 = Utf8               (TT7;)Lorg/sireum/MBox10<TT1;TT2;TT3;TT4;TT5;TT6;TT7;TT8;TT9;TT10;>;
  #147 = Utf8               setValue7
  #148 = Utf8               value8
  #149 = Utf8               ()TT8;
  #150 = NameAndType        #27:#13       // _value8:Ljava/lang/Object;
  #151 = Fieldref           #2.#150       // org/sireum/MBox10._value8:Ljava/lang/Object;
  #152 = Utf8               getValue8
  #153 = Utf8               value8_$eq
  #154 = Utf8               (TT8;)Lorg/sireum/MBox10<TT1;TT2;TT3;TT4;TT5;TT6;TT7;TT8;TT9;TT10;>;
  #155 = Utf8               setValue8
  #156 = Utf8               value9
  #157 = Utf8               ()TT9;
  #158 = NameAndType        #29:#13       // _value9:Ljava/lang/Object;
  #159 = Fieldref           #2.#158       // org/sireum/MBox10._value9:Ljava/lang/Object;
  #160 = Utf8               getValue9
  #161 = Utf8               value9_$eq
  #162 = Utf8               (TT9;)Lorg/sireum/MBox10<TT1;TT2;TT3;TT4;TT5;TT6;TT7;TT8;TT9;TT10;>;
  #163 = Utf8               setValue9
  #164 = Utf8               value10
  #165 = Utf8               ()TT10;
  #166 = NameAndType        #31:#13       // _value10:Ljava/lang/Object;
  #167 = Fieldref           #2.#166       // org/sireum/MBox10._value10:Ljava/lang/Object;
  #168 = Utf8               getValue10
  #169 = Utf8               value10_$eq
  #170 = Utf8               (TT10;)Lorg/sireum/MBox10<TT1;TT2;TT3;TT4;TT5;TT6;TT7;TT8;TT9;TT10;>;
  #171 = Utf8               setValue10
  #172 = Utf8               toString
  #173 = Utf8               ()Ljava/lang/String;
  #174 = NameAndType        #81:#49       // $hasString:()Z
  #175 = Methodref          #2.#174       // org/sireum/MBox10.$hasString:()Z
  #176 = Utf8               string$
  #177 = Utf8               (Lorg/sireum/RecordSig;)Ljava/lang/String;
  #178 = NameAndType        #176:#177     // string$:(Lorg/sireum/RecordSig;)Ljava/lang/String;
  #179 = InterfaceMethodref #7.#178       // org/sireum/RecordSig.string$:(Lorg/sireum/RecordSig;)Ljava/lang/String;
  #180 = Utf8               java/lang/StringBuilder
  #181 = Class              #180          // java/lang/StringBuilder
  #182 = Utf8               <init>
  #183 = Utf8               ()V
  #184 = NameAndType        #182:#183     // "<init>":()V
  #185 = Methodref          #181.#184     // java/lang/StringBuilder."<init>":()V
  #186 = Utf8               MBox10
  #187 = String             #186          // MBox10
  #188 = Utf8               append
  #189 = Utf8               (Ljava/lang/String;)Ljava/lang/StringBuilder;
  #190 = NameAndType        #188:#189     // append:(Ljava/lang/String;)Ljava/lang/StringBuilder;
  #191 = Methodref          #181.#190     // java/lang/StringBuilder.append:(Ljava/lang/String;)Ljava/lang/StringBuilder;
  #192 = Utf8               (C)Ljava/lang/StringBuilder;
  #193 = NameAndType        #188:#192     // append:(C)Ljava/lang/StringBuilder;
  #194 = Methodref          #181.#193     // java/lang/StringBuilder.append:(C)Ljava/lang/StringBuilder;
  #195 = Utf8               org/sireum/String$
  #196 = Class              #195          // org/sireum/String$
  #197 = Utf8               Lorg/sireum/String$;
  #198 = NameAndType        #41:#197      // MODULE$:Lorg/sireum/String$;
  #199 = Fieldref           #196.#198     // org/sireum/String$.MODULE$:Lorg/sireum/String$;
  #200 = NameAndType        #90:#91       // value1:()Ljava/lang/Object;
  #201 = Methodref          #2.#200       // org/sireum/MBox10.value1:()Ljava/lang/Object;
  #202 = Utf8               escape
  #203 = Utf8               (Ljava/lang/Object;)Ljava/lang/String;
  #204 = NameAndType        #202:#203     // escape:(Ljava/lang/Object;)Ljava/lang/String;
  #205 = Methodref          #196.#204     // org/sireum/String$.escape:(Ljava/lang/Object;)Ljava/lang/String;
  #206 = Utf8               ,
  #207 = String             #206          // ,
  #208 = NameAndType        #100:#91      // value2:()Ljava/lang/Object;
  #209 = Methodref          #2.#208       // org/sireum/MBox10.value2:()Ljava/lang/Object;
  #210 = NameAndType        #108:#91      // value3:()Ljava/lang/Object;
  #211 = Methodref          #2.#210       // org/sireum/MBox10.value3:()Ljava/lang/Object;
  #212 = NameAndType        #116:#91      // value4:()Ljava/lang/Object;
  #213 = Methodref          #2.#212       // org/sireum/MBox10.value4:()Ljava/lang/Object;
  #214 = NameAndType        #124:#91      // value5:()Ljava/lang/Object;
  #215 = Methodref          #2.#214       // org/sireum/MBox10.value5:()Ljava/lang/Object;
  #216 = NameAndType        #132:#91      // value6:()Ljava/lang/Object;
  #217 = Methodref          #2.#216       // org/sireum/MBox10.value6:()Ljava/lang/Object;
  #218 = NameAndType        #140:#91      // value7:()Ljava/lang/Object;
  #219 = Methodref          #2.#218       // org/sireum/MBox10.value7:()Ljava/lang/Object;
  #220 = NameAndType        #148:#91      // value8:()Ljava/lang/Object;
  #221 = Methodref          #2.#220       // org/sireum/MBox10.value8:()Ljava/lang/Object;
  #222 = NameAndType        #156:#91      // value9:()Ljava/lang/Object;
  #223 = Methodref          #2.#222       // org/sireum/MBox10.value9:()Ljava/lang/Object;
  #224 = NameAndType        #164:#91      // value10:()Ljava/lang/Object;
  #225 = Methodref          #2.#224       // org/sireum/MBox10.value10:()Ljava/lang/Object;
  #226 = NameAndType        #172:#173     // toString:()Ljava/lang/String;
  #227 = Methodref          #181.#226     // java/lang/StringBuilder.toString:()Ljava/lang/String;
  #228 = Utf8               sb
  #229 = Utf8               Ljava/lang/StringBuilder;
  #230 = Utf8               java/lang/String
  #231 = Class              #230          // java/lang/String
  #232 = Utf8               string
  #233 = Methodref          #2.#226       // org/sireum/MBox10.toString:()Ljava/lang/String;
  #234 = Utf8               apply
  #235 = Utf8               (Ljava/lang/String;)Ljava/lang/String;
  #236 = NameAndType        #234:#235     // apply:(Ljava/lang/String;)Ljava/lang/String;
  #237 = Methodref          #196.#236     // org/sireum/String$.apply:(Ljava/lang/String;)Ljava/lang/String;
  #238 = Utf8               hashCode
  #239 = Utf8               ()I
  #240 = NameAndType        #76:#49       // $hasEquals:()Z
  #241 = Methodref          #2.#240       // org/sireum/MBox10.$hasEquals:()Z
  #242 = NameAndType        #238:#239     // hashCode:()I
  #243 = Methodref          #5.#242       // java/lang/Object.hashCode:()I
  #244 = Utf8               scala/package$
  #245 = Class              #244          // scala/package$
  #246 = Utf8               Lscala/package$;
  #247 = NameAndType        #41:#246      // MODULE$:Lscala/package$;
  #248 = Fieldref           #245.#247     // scala/package$.MODULE$:Lscala/package$;
  #249 = Utf8               Seq
  #250 = Utf8               ()Lscala/collection/immutable/Seq$;
  #251 = NameAndType        #249:#250     // Seq:()Lscala/collection/immutable/Seq$;
  #252 = Methodref          #245.#251     // scala/package$.Seq:()Lscala/collection/immutable/Seq$;
  #253 = Utf8               scala/runtime/ScalaRunTime$
  #254 = Class              #253          // scala/runtime/ScalaRunTime$
  #255 = Utf8               Lscala/runtime/ScalaRunTime$;
  #256 = NameAndType        #41:#255      // MODULE$:Lscala/runtime/ScalaRunTime$;
  #257 = Fieldref           #254.#256     // scala/runtime/ScalaRunTime$.MODULE$:Lscala/runtime/ScalaRunTime$;
  #258 = Utf8               getClass
  #259 = Utf8               ()Ljava/lang/Class;
  #260 = NameAndType        #258:#259     // getClass:()Ljava/lang/Class;
  #261 = Methodref          #2.#260       // org/sireum/MBox10.getClass:()Ljava/lang/Class;
  #262 = Utf8               java/lang/Class
  #263 = Class              #262          // java/lang/Class
  #264 = Utf8               getName
  #265 = NameAndType        #264:#173     // getName:()Ljava/lang/String;
  #266 = Methodref          #263.#265     // java/lang/Class.getName:()Ljava/lang/String;
  #267 = Utf8               genericWrapArray
  #268 = Utf8               (Ljava/lang/Object;)Lscala/collection/immutable/ArraySeq;
  #269 = NameAndType        #267:#268     // genericWrapArray:(Ljava/lang/Object;)Lscala/collection/immutable/ArraySeq;
  #270 = Methodref          #254.#269     // scala/runtime/ScalaRunTime$.genericWrapArray:(Ljava/lang/Object;)Lscala/collection/immutable/ArraySeq;
  #271 = Utf8               scala/collection/immutable/Seq$
  #272 = Class              #271          // scala/collection/immutable/Seq$
  #273 = Utf8               (Lscala/collection/immutable/Seq;)Lscala/collection/SeqOps;
  #274 = NameAndType        #234:#273     // apply:(Lscala/collection/immutable/Seq;)Lscala/collection/SeqOps;
  #275 = Methodref          #272.#274     // scala/collection/immutable/Seq$.apply:(Lscala/collection/immutable/Seq;)Lscala/collection/SeqOps;
  #276 = Utf8               scala/collection/Seq
  #277 = Class              #276          // scala/collection/Seq
  #278 = InterfaceMethodref #277.#242     // scala/collection/Seq.hashCode:()I
  #279 = Utf8               equals
  #280 = Utf8               (Ljava/lang/Object;)Z
  #281 = NameAndType        #279:#280     // equals:(Ljava/lang/Object;)Z
  #282 = Methodref          #5.#281       // java/lang/Object.equals:(Ljava/lang/Object;)Z
  #283 = Methodref          #2.#242       // org/sireum/MBox10.hashCode:()I
  #284 = Utf8               scala/runtime/BoxesRunTime
  #285 = Class              #284          // scala/runtime/BoxesRunTime
  #286 = Utf8               (Ljava/lang/Object;Ljava/lang/Object;)Z
  #287 = NameAndType        #279:#286     // equals:(Ljava/lang/Object;Ljava/lang/Object;)Z
  #288 = Methodref          #285.#287     // scala/runtime/BoxesRunTime.equals:(Ljava/lang/Object;Ljava/lang/Object;)Z
  #289 = Utf8               (Ljava/lang/Object;Ljava/lang/Object;Ljava/lang/Object;Ljava/lang/Object;Ljava/lang/Object;Ljava/lang/Object;Ljava/lang/Object;Ljava/lang/Object;Ljava/lang/Object;Ljava/lang/Object;)Lorg/sireum/MBox10;
  #290 = Utf8               (TT1;TT2;TT3;TT4;TT5;TT6;TT7;TT8;TT9;TT10;)Lorg/sireum/MBox10<TT1;TT2;TT3;TT4;TT5;TT6;TT7;TT8;TT9;TT10;>;
  #291 = Utf8               (Ljava/lang/Object;Ljava/lang/Object;Ljava/lang/Object;Ljava/lang/Object;Ljava/lang/Object;Ljava/lang/Object;Ljava/lang/Object;Ljava/lang/Object;Ljava/lang/Object;Ljava/lang/Object;)V
  #292 = NameAndType        #182:#291     // "<init>":(Ljava/lang/Object;Ljava/lang/Object;Ljava/lang/Object;Ljava/lang/Object;Ljava/lang/Object;Ljava/lang/Object;Ljava/lang/Object;Ljava/lang/Object;Ljava/lang/Object;Ljava/lang/Object;)V
  #293 = Methodref          #2.#292       // org/sireum/MBox10."<init>":(Ljava/lang/Object;Ljava/lang/Object;Ljava/lang/Object;Ljava/lang/Object;Ljava/lang/Object;Ljava/lang/Object;Ljava/lang/Object;Ljava/lang/Object;Ljava/lang/Object;Ljava/lang/Object;)V
  #294 = Utf8               apply$default$1
  #295 = Utf8               apply$default$2
  #296 = Utf8               apply$default$3
  #297 = Utf8               apply$default$4
  #298 = Utf8               apply$default$5
  #299 = Utf8               apply$default$6
  #300 = Utf8               apply$default$7
  #301 = Utf8               apply$default$8
  #302 = Utf8               apply$default$9
  #303 = Utf8               apply$default$10
  #304 = Utf8               $content
  #305 = Utf8               ()Lscala/collection/immutable/Seq;
  #306 = Utf8               ()Lscala/collection/immutable/Seq<Lscala/Tuple2<Ljava/lang/String;Ljava/lang/Object;>;>;
  #307 = Utf8               scala/Tuple2
  #308 = Class              #307          // scala/Tuple2
  #309 = Utf8               type
  #310 = String             #309          // type
  #311 = Utf8               List
  #312 = Utf8               ()Lscala/collection/immutable/List$;
  #313 = NameAndType        #311:#312     // List:()Lscala/collection/immutable/List$;
  #314 = Methodref          #245.#313     // scala/package$.List:()Lscala/collection/immutable/List$;
  #315 = Utf8               org
  #316 = String             #315          // org
  #317 = Utf8               sireum
  #318 = String             #317          // sireum
  #319 = Utf8               [Ljava/lang/Object;
  #320 = Class              #319          // "[Ljava/lang/Object;"
  #321 = Utf8               wrapRefArray
  #322 = Utf8               ([Ljava/lang/Object;)Lscala/collection/immutable/ArraySeq;
  #323 = NameAndType        #321:#322     // wrapRefArray:([Ljava/lang/Object;)Lscala/collection/immutable/ArraySeq;
  #324 = Methodref          #254.#323     // scala/runtime/ScalaRunTime$.wrapRefArray:([Ljava/lang/Object;)Lscala/collection/immutable/ArraySeq;
  #325 = Utf8               scala/collection/immutable/List$
  #326 = Class              #325          // scala/collection/immutable/List$
  #327 = Utf8               (Lscala/collection/immutable/Seq;)Ljava/lang/Object;
  #328 = NameAndType        #234:#327     // apply:(Lscala/collection/immutable/Seq;)Ljava/lang/Object;
  #329 = Methodref          #326.#328     // scala/collection/immutable/List$.apply:(Lscala/collection/immutable/Seq;)Ljava/lang/Object;
  #330 = Utf8               (Ljava/lang/Object;Ljava/lang/Object;)V
  #331 = NameAndType        #182:#330     // "<init>":(Ljava/lang/Object;Ljava/lang/Object;)V
  #332 = Methodref          #308.#331     // scala/Tuple2."<init>":(Ljava/lang/Object;Ljava/lang/Object;)V
  #333 = String             #90           // value1
  #334 = String             #100          // value2
  #335 = String             #108          // value3
  #336 = String             #116          // value4
  #337 = String             #124          // value5
  #338 = String             #132          // value6
  #339 = String             #140          // value7
  #340 = String             #148          // value8
  #341 = String             #156          // value9
  #342 = String             #164          // value10
  #343 = Utf8               scala/collection/immutable/Seq
  #344 = Class              #343          // scala/collection/immutable/Seq
  #345 = Utf8               $clone
  #346 = Utf8               ()Lorg/sireum/MBox10;
  #347 = Utf8               ()Lorg/sireum/MBox10<TT1;TT2;TT3;TT4;TT5;TT6;TT7;TT8;TT9;TT10;>;
  #348 = Utf8               org/sireum/helper$
  #349 = Class              #348          // org/sireum/helper$
  #350 = Utf8               Lorg/sireum/helper$;
  #351 = NameAndType        #41:#350      // MODULE$:Lorg/sireum/helper$;
  #352 = Fieldref           #349.#351     // org/sireum/helper$.MODULE$:Lorg/sireum/helper$;
  #353 = Utf8               cloneAssign
  #354 = Utf8               (Ljava/lang/Object;)Ljava/lang/Object;
  #355 = NameAndType        #353:#354     // cloneAssign:(Ljava/lang/Object;)Ljava/lang/Object;
  #356 = Methodref          #349.#355     // org/sireum/helper$.cloneAssign:(Ljava/lang/Object;)Ljava/lang/Object;
  #357 = Utf8               r
  #358 = Utf8               (Z)Lorg/sireum/$internal/MutableMarker;
  #359 = NameAndType        #55:#56       // $owned_$eq:(Z)Lorg/sireum/RecordSig;
  #360 = Methodref          #2.#359       // org/sireum/MBox10.$owned_$eq:(Z)Lorg/sireum/RecordSig;
  #361 = NameAndType        #345:#346     // $clone:()Lorg/sireum/MBox10;
  #362 = Methodref          #2.#361       // org/sireum/MBox10.$clone:()Lorg/sireum/MBox10;
  #363 = Utf8               ()Lorg/sireum/$internal/MutableMarker;
  #364 = Utf8               (TT1;TT2;TT3;TT4;TT5;TT6;TT7;TT8;TT9;TT10;)V
  #365 = Utf8               __value1
  #366 = Utf8               __value2
  #367 = Utf8               __value3
  #368 = Utf8               __value4
  #369 = Utf8               __value5
  #370 = Utf8               __value6
  #371 = Utf8               __value7
  #372 = Utf8               __value8
  #373 = Utf8               __value9
  #374 = Utf8               __value10
  #375 = Methodref          #5.#184       // java/lang/Object."<init>":()V
  #376 = Utf8               $init$
  #377 = Utf8               (Lorg/sireum/Mutable;)V
  #378 = NameAndType        #376:#377     // $init$:(Lorg/sireum/Mutable;)V
  #379 = InterfaceMethodref #71.#378      // org/sireum/Mutable.$init$:(Lorg/sireum/Mutable;)V
  #380 = Utf8               (Lorg/sireum/RecordSig;)V
  #381 = NameAndType        #376:#380     // $init$:(Lorg/sireum/RecordSig;)V
  #382 = InterfaceMethodref #7.#381       // org/sireum/RecordSig.$init$:(Lorg/sireum/RecordSig;)V
  #383 = Utf8               Signature
  #384 = Utf8               Code
  #385 = Utf8               LocalVariableTable
  #386 = Utf8               MethodParameters
  #387 = Utf8               LineNumberTable
  #388 = Utf8               StackMapTable
  #389 = Utf8               SourceFile
  #390 = Utf8               RuntimeVisibleAnnotations
  #391 = Utf8               ScalaInlineInfo
  #392 = Utf8               ScalaSig
{
  private T1 _value1;
    descriptor: Ljava/lang/Object;
    flags: (0x0002) ACC_PRIVATE
    Signature: #14                          // TT1;

  private T2 _value2;
    descriptor: Ljava/lang/Object;
    flags: (0x0002) ACC_PRIVATE
    Signature: #16                          // TT2;

  private T3 _value3;
    descriptor: Ljava/lang/Object;
    flags: (0x0002) ACC_PRIVATE
    Signature: #18                          // TT3;

  private T4 _value4;
    descriptor: Ljava/lang/Object;
    flags: (0x0002) ACC_PRIVATE
    Signature: #20                          // TT4;

  private T5 _value5;
    descriptor: Ljava/lang/Object;
    flags: (0x0002) ACC_PRIVATE
    Signature: #22                          // TT5;

  private T6 _value6;
    descriptor: Ljava/lang/Object;
    flags: (0x0002) ACC_PRIVATE
    Signature: #24                          // TT6;

  private T7 _value7;
    descriptor: Ljava/lang/Object;
    flags: (0x0002) ACC_PRIVATE
    Signature: #26                          // TT7;

  private T8 _value8;
    descriptor: Ljava/lang/Object;
    flags: (0x0002) ACC_PRIVATE
    Signature: #28                          // TT8;

  private T9 _value9;
    descriptor: Ljava/lang/Object;
    flags: (0x0002) ACC_PRIVATE
    Signature: #30                          // TT9;

  private T10 _value10;
    descriptor: Ljava/lang/Object;
    flags: (0x0002) ACC_PRIVATE
    Signature: #32                          // TT10;

  private boolean org$sireum$RecordSig$$$isOwned;
    descriptor: Z
    flags: (0x0002) ACC_PRIVATE

  public static <T1 extends java.lang.Object, T2 extends java.lang.Object, T3 extends java.lang.Object, T4 extends java.lang.Object, T5 extends java.lang.Object, T6 extends java.lang.Object, T7 extends java.lang.Object, T8 extends java.lang.Object, T9 extends java.lang.Object, T10 extends java.lang.Object> scala.Some<scala.Tuple10<T1, T2, T3, T4, T5, T6, T7, T8, T9, T10>> unapply(org.sireum.MBox10<T1, T2, T3, T4, T5, T6, T7, T8, T9, T10>);
    descriptor: (Lorg/sireum/MBox10;)Lscala/Some;
    flags: (0x0009) ACC_PUBLIC, ACC_STATIC
    Code:
      stack=2, locals=1, args_size=1
         0: getstatic     #44                 // Field org/sireum/MBox10$.MODULE$:Lorg/sireum/MBox10$;
         3: aload_0
         4: invokevirtual #46                 // Method org/sireum/MBox10$.unapply:(Lorg/sireum/MBox10;)Lscala/Some;
         7: areturn
      LocalVariableTable:
        Start  Length  Slot  Name   Signature
            0       8     0     o   Lorg/sireum/MBox10;
    Signature: #37                          // <T1:Ljava/lang/Object;T2:Ljava/lang/Object;T3:Ljava/lang/Object;T4:Ljava/lang/Object;T5:Ljava/lang/Object;T6:Ljava/lang/Object;T7:Ljava/lang/Object;T8:Ljava/lang/Object;T9:Ljava/lang/Object;T10:Ljava/lang/Object;>(Lorg/sireum/MBox10<TT1;TT2;TT3;TT4;TT5;TT6;TT7;TT8;TT9;TT10;>;)Lscala/Some<Lscala/Tuple10<TT1;TT2;TT3;TT4;TT5;TT6;TT7;TT8;TT9;TT10;>;>;
    MethodParameters:
      Name                           Flags
      o                              final

  public final boolean $owned();
    descriptor: ()Z
    flags: (0x0011) ACC_PUBLIC, ACC_FINAL
    Code:
      stack=1, locals=1, args_size=1
         0: aload_0
         1: invokestatic  #53                 // InterfaceMethod org/sireum/RecordSig.$owned$:(Lorg/sireum/RecordSig;)Z
         4: ireturn
      LineNumberTable:
        line 47: 0
      LocalVariableTable:
        Start  Length  Slot  Name   Signature
            0       5     0  this   Lorg/sireum/MBox10;

  public final org.sireum.RecordSig $owned_$eq(boolean);
    descriptor: (Z)Lorg/sireum/RecordSig;
    flags: (0x0011) ACC_PUBLIC, ACC_FINAL
    Code:
      stack=2, locals=2, args_size=2
         0: aload_0
         1: iload_1
         2: invokestatic  #61                 // InterfaceMethod org/sireum/RecordSig.$owned_$eq$:(Lorg/sireum/RecordSig;Z)Lorg/sireum/RecordSig;
         5: areturn
      LineNumberTable:
        line 47: 0
      LocalVariableTable:
        Start  Length  Slot  Name   Signature
            0       6     0  this   Lorg/sireum/MBox10;
            0       6     1     b   Z
    MethodParameters:
      Name                           Flags
      b                              final

  public org.sireum.Z hash();
    descriptor: ()Lorg/sireum/Z;
    flags: (0x0001) ACC_PUBLIC
    Code:
      stack=1, locals=1, args_size=1
         0: aload_0
         1: invokestatic  #67                 // InterfaceMethod org/sireum/RecordSig.hash$:(Lorg/sireum/RecordSig;)Lorg/sireum/Z;
         4: areturn
      LineNumberTable:
        line 47: 0
      LocalVariableTable:
        Start  Length  Slot  Name   Signature
            0       5     0  this   Lorg/sireum/MBox10;

  public final scala.runtime.Nothing$ $cannotMixImmutableAndMutable();
    descriptor: ()Lscala/runtime/Nothing$;
    flags: (0x0011) ACC_PUBLIC, ACC_FINAL
    Code:
      stack=1, locals=1, args_size=1
         0: aload_0
         1: invokestatic  #75                 // InterfaceMethod org/sireum/Mutable.$cannotMixImmutableAndMutable$:(Lorg/sireum/Mutable;)Lscala/runtime/Nothing$;
         4: areturn
      LineNumberTable:
        line 47: 0
      LocalVariableTable:
        Start  Length  Slot  Name   Signature
            0       5     0  this   Lorg/sireum/MBox10;

  public boolean $hasEquals();
    descriptor: ()Z
    flags: (0x0001) ACC_PUBLIC
    Code:
      stack=1, locals=1, args_size=1
         0: aload_0
         1: invokestatic  #80                 // InterfaceMethod org/sireum/Mutable.$hasEquals$:(Lorg/sireum/Mutable;)Z
         4: ireturn
      LineNumberTable:
        line 47: 0
      LocalVariableTable:
        Start  Length  Slot  Name   Signature
            0       5     0  this   Lorg/sireum/MBox10;

  public boolean $hasString();
    descriptor: ()Z
    flags: (0x0001) ACC_PUBLIC
    Code:
      stack=1, locals=1, args_size=1
         0: aload_0
         1: invokestatic  #84                 // InterfaceMethod org/sireum/Mutable.$hasString$:(Lorg/sireum/Mutable;)Z
         4: ireturn
      LineNumberTable:
        line 47: 0
      LocalVariableTable:
        Start  Length  Slot  Name   Signature
            0       5     0  this   Lorg/sireum/MBox10;

  public boolean org$sireum$RecordSig$$$isOwned();
    descriptor: ()Z
    flags: (0x0001) ACC_PUBLIC
    Code:
      stack=1, locals=1, args_size=1
         0: aload_0
         1: getfield      #86                 // Field org$sireum$RecordSig$$$isOwned:Z
         4: ireturn
      LineNumberTable:
        line 47: 0
      LocalVariableTable:
        Start  Length  Slot  Name   Signature
            0       5     0  this   Lorg/sireum/MBox10;

  public void org$sireum$RecordSig$$$isOwned_$eq(boolean);
    descriptor: (Z)V
    flags: (0x0001) ACC_PUBLIC
    Code:
      stack=2, locals=2, args_size=2
         0: aload_0
         1: iload_1
         2: putfield      #86                 // Field org$sireum$RecordSig$$$isOwned:Z
         5: return
      LineNumberTable:
        line 47: 0
      LocalVariableTable:
        Start  Length  Slot  Name   Signature
            0       6     0  this   Lorg/sireum/MBox10;
            0       6     1   x$1   Z
    MethodParameters:
      Name                           Flags
      x$1                            final

  public T1 value1();
    descriptor: ()Ljava/lang/Object;
    flags: (0x0001) ACC_PUBLIC
    Code:
      stack=1, locals=1, args_size=1
         0: aload_0
         1: getfield      #94                 // Field _value1:Ljava/lang/Object;
         4: areturn
      LineNumberTable:
        line 47: 0
      LocalVariableTable:
        Start  Length  Slot  Name   Signature
            0       5     0  this   Lorg/sireum/MBox10;
    Signature: #92                          // ()TT1;

  public T1 getValue1();
    descriptor: ()Ljava/lang/Object;
    flags: (0x0001) ACC_PUBLIC
    Code:
      stack=1, locals=1, args_size=1
         0: aload_0
         1: getfield      #94                 // Field _value1:Ljava/lang/Object;
         4: areturn
      LineNumberTable:
        line 47: 0
      LocalVariableTable:
        Start  Length  Slot  Name   Signature
            0       5     0  this   Lorg/sireum/MBox10;
    Signature: #92                          // ()TT1;

  public org.sireum.MBox10<T1, T2, T3, T4, T5, T6, T7, T8, T9, T10> value1_$eq(T1);
    descriptor: (Ljava/lang/Object;)Lorg/sireum/MBox10;
    flags: (0x0001) ACC_PUBLIC
    Code:
      stack=2, locals=2, args_size=2
         0: aload_0
         1: aload_1
         2: putfield      #94                 // Field _value1:Ljava/lang/Object;
         5: aload_0
         6: areturn
      LineNumberTable:
        line 47: 0
      LocalVariableTable:
        Start  Length  Slot  Name   Signature
            0       7     0  this   Lorg/sireum/MBox10;
            0       7     1 value1   Ljava/lang/Object;
    Signature: #98                          // (TT1;)Lorg/sireum/MBox10<TT1;TT2;TT3;TT4;TT5;TT6;TT7;TT8;TT9;TT10;>;
    MethodParameters:
      Name                           Flags
      value1                         final

  public org.sireum.MBox10<T1, T2, T3, T4, T5, T6, T7, T8, T9, T10> setValue1(T1);
    descriptor: (Ljava/lang/Object;)Lorg/sireum/MBox10;
    flags: (0x0001) ACC_PUBLIC
    Code:
      stack=2, locals=2, args_size=2
         0: aload_0
         1: aload_1
         2: putfield      #94                 // Field _value1:Ljava/lang/Object;
         5: aload_0
         6: areturn
      LineNumberTable:
        line 47: 0
      LocalVariableTable:
        Start  Length  Slot  Name   Signature
            0       7     0  this   Lorg/sireum/MBox10;
            0       7     1 value1   Ljava/lang/Object;
    Signature: #98                          // (TT1;)Lorg/sireum/MBox10<TT1;TT2;TT3;TT4;TT5;TT6;TT7;TT8;TT9;TT10;>;
    MethodParameters:
      Name                           Flags
      value1                         final

  public T2 value2();
    descriptor: ()Ljava/lang/Object;
    flags: (0x0001) ACC_PUBLIC
    Code:
      stack=1, locals=1, args_size=1
         0: aload_0
         1: getfield      #103                // Field _value2:Ljava/lang/Object;
         4: areturn
      LineNumberTable:
        line 47: 0
      LocalVariableTable:
        Start  Length  Slot  Name   Signature
            0       5     0  this   Lorg/sireum/MBox10;
    Signature: #101                         // ()TT2;

  public T2 getValue2();
    descriptor: ()Ljava/lang/Object;
    flags: (0x0001) ACC_PUBLIC
    Code:
      stack=1, locals=1, args_size=1
         0: aload_0
         1: getfield      #103                // Field _value2:Ljava/lang/Object;
         4: areturn
      LineNumberTable:
        line 47: 0
      LocalVariableTable:
        Start  Length  Slot  Name   Signature
            0       5     0  this   Lorg/sireum/MBox10;
    Signature: #101                         // ()TT2;

  public org.sireum.MBox10<T1, T2, T3, T4, T5, T6, T7, T8, T9, T10> value2_$eq(T2);
    descriptor: (Ljava/lang/Object;)Lorg/sireum/MBox10;
    flags: (0x0001) ACC_PUBLIC
    Code:
      stack=2, locals=2, args_size=2
         0: aload_0
         1: aload_1
         2: putfield      #103                // Field _value2:Ljava/lang/Object;
         5: aload_0
         6: areturn
      LineNumberTable:
        line 47: 0
      LocalVariableTable:
        Start  Length  Slot  Name   Signature
            0       7     0  this   Lorg/sireum/MBox10;
            0       7     1 value2   Ljava/lang/Object;
    Signature: #106                         // (TT2;)Lorg/sireum/MBox10<TT1;TT2;TT3;TT4;TT5;TT6;TT7;TT8;TT9;TT10;>;
    MethodParameters:
      Name                           Flags
      value2                         final

  public org.sireum.MBox10<T1, T2, T3, T4, T5, T6, T7, T8, T9, T10> setValue2(T2);
    descriptor: (Ljava/lang/Object;)Lorg/sireum/MBox10;
    flags: (0x0001) ACC_PUBLIC
    Code:
      stack=2, locals=2, args_size=2
         0: aload_0
         1: aload_1
         2: putfield      #103                // Field _value2:Ljava/lang/Object;
         5: aload_0
         6: areturn
      LineNumberTable:
        line 47: 0
      LocalVariableTable:
        Start  Length  Slot  Name   Signature
            0       7     0  this   Lorg/sireum/MBox10;
            0       7     1 value2   Ljava/lang/Object;
    Signature: #106                         // (TT2;)Lorg/sireum/MBox10<TT1;TT2;TT3;TT4;TT5;TT6;TT7;TT8;TT9;TT10;>;
    MethodParameters:
      Name                           Flags
      value2                         final

  public T3 value3();
    descriptor: ()Ljava/lang/Object;
    flags: (0x0001) ACC_PUBLIC
    Code:
      stack=1, locals=1, args_size=1
         0: aload_0
         1: getfield      #111                // Field _value3:Ljava/lang/Object;
         4: areturn
      LineNumberTable:
        line 47: 0
      LocalVariableTable:
        Start  Length  Slot  Name   Signature
            0       5     0  this   Lorg/sireum/MBox10;
    Signature: #109                         // ()TT3;

  public T3 getValue3();
    descriptor: ()Ljava/lang/Object;
    flags: (0x0001) ACC_PUBLIC
    Code:
      stack=1, locals=1, args_size=1
         0: aload_0
         1: getfield      #111                // Field _value3:Ljava/lang/Object;
         4: areturn
      LineNumberTable:
        line 47: 0
      LocalVariableTable:
        Start  Length  Slot  Name   Signature
            0       5     0  this   Lorg/sireum/MBox10;
    Signature: #109                         // ()TT3;

  public org.sireum.MBox10<T1, T2, T3, T4, T5, T6, T7, T8, T9, T10> value3_$eq(T3);
    descriptor: (Ljava/lang/Object;)Lorg/sireum/MBox10;
    flags: (0x0001) ACC_PUBLIC
    Code:
      stack=2, locals=2, args_size=2
         0: aload_0
         1: aload_1
         2: putfield      #111                // Field _value3:Ljava/lang/Object;
         5: aload_0
         6: areturn
      LineNumberTable:
        line 47: 0
      LocalVariableTable:
        Start  Length  Slot  Name   Signature
            0       7     0  this   Lorg/sireum/MBox10;
            0       7     1 value3   Ljava/lang/Object;
    Signature: #114                         // (TT3;)Lorg/sireum/MBox10<TT1;TT2;TT3;TT4;TT5;TT6;TT7;TT8;TT9;TT10;>;
    MethodParameters:
      Name                           Flags
      value3                         final

  public org.sireum.MBox10<T1, T2, T3, T4, T5, T6, T7, T8, T9, T10> setValue3(T3);
    descriptor: (Ljava/lang/Object;)Lorg/sireum/MBox10;
    flags: (0x0001) ACC_PUBLIC
    Code:
      stack=2, locals=2, args_size=2
         0: aload_0
         1: aload_1
         2: putfield      #111                // Field _value3:Ljava/lang/Object;
         5: aload_0
         6: areturn
      LineNumberTable:
        line 47: 0
      LocalVariableTable:
        Start  Length  Slot  Name   Signature
            0       7     0  this   Lorg/sireum/MBox10;
            0       7     1 value3   Ljava/lang/Object;
    Signature: #114                         // (TT3;)Lorg/sireum/MBox10<TT1;TT2;TT3;TT4;TT5;TT6;TT7;TT8;TT9;TT10;>;
    MethodParameters:
      Name                           Flags
      value3                         final

  public T4 value4();
    descriptor: ()Ljava/lang/Object;
    flags: (0x0001) ACC_PUBLIC
    Code:
      stack=1, locals=1, args_size=1
         0: aload_0
         1: getfield      #119                // Field _value4:Ljava/lang/Object;
         4: areturn
      LineNumberTable:
        line 47: 0
      LocalVariableTable:
        Start  Length  Slot  Name   Signature
            0       5     0  this   Lorg/sireum/MBox10;
    Signature: #117                         // ()TT4;

  public T4 getValue4();
    descriptor: ()Ljava/lang/Object;
    flags: (0x0001) ACC_PUBLIC
    Code:
      stack=1, locals=1, args_size=1
         0: aload_0
         1: getfield      #119                // Field _value4:Ljava/lang/Object;
         4: areturn
      LineNumberTable:
        line 47: 0
      LocalVariableTable:
        Start  Length  Slot  Name   Signature
            0       5     0  this   Lorg/sireum/MBox10;
    Signature: #117                         // ()TT4;

  public org.sireum.MBox10<T1, T2, T3, T4, T5, T6, T7, T8, T9, T10> value4_$eq(T4);
    descriptor: (Ljava/lang/Object;)Lorg/sireum/MBox10;
    flags: (0x0001) ACC_PUBLIC
    Code:
      stack=2, locals=2, args_size=2
         0: aload_0
         1: aload_1
         2: putfield      #119                // Field _value4:Ljava/lang/Object;
         5: aload_0
         6: areturn
      LineNumberTable:
        line 47: 0
      LocalVariableTable:
        Start  Length  Slot  Name   Signature
            0       7     0  this   Lorg/sireum/MBox10;
            0       7     1 value4   Ljava/lang/Object;
    Signature: #122                         // (TT4;)Lorg/sireum/MBox10<TT1;TT2;TT3;TT4;TT5;TT6;TT7;TT8;TT9;TT10;>;
    MethodParameters:
      Name                           Flags
      value4                         final

  public org.sireum.MBox10<T1, T2, T3, T4, T5, T6, T7, T8, T9, T10> setValue4(T4);
    descriptor: (Ljava/lang/Object;)Lorg/sireum/MBox10;
    flags: (0x0001) ACC_PUBLIC
    Code:
      stack=2, locals=2, args_size=2
         0: aload_0
         1: aload_1
         2: putfield      #119                // Field _value4:Ljava/lang/Object;
         5: aload_0
         6: areturn
      LineNumberTable:
        line 47: 0
      LocalVariableTable:
        Start  Length  Slot  Name   Signature
            0       7     0  this   Lorg/sireum/MBox10;
            0       7     1 value4   Ljava/lang/Object;
    Signature: #122                         // (TT4;)Lorg/sireum/MBox10<TT1;TT2;TT3;TT4;TT5;TT6;TT7;TT8;TT9;TT10;>;
    MethodParameters:
      Name                           Flags
      value4                         final

  public T5 value5();
    descriptor: ()Ljava/lang/Object;
    flags: (0x0001) ACC_PUBLIC
    Code:
      stack=1, locals=1, args_size=1
         0: aload_0
         1: getfield      #127                // Field _value5:Ljava/lang/Object;
         4: areturn
      LineNumberTable:
        line 47: 0
      LocalVariableTable:
        Start  Length  Slot  Name   Signature
            0       5     0  this   Lorg/sireum/MBox10;
    Signature: #125                         // ()TT5;

  public T5 getValue5();
    descriptor: ()Ljava/lang/Object;
    flags: (0x0001) ACC_PUBLIC
    Code:
      stack=1, locals=1, args_size=1
         0: aload_0
         1: getfield      #127                // Field _value5:Ljava/lang/Object;
         4: areturn
      LineNumberTable:
        line 47: 0
      LocalVariableTable:
        Start  Length  Slot  Name   Signature
            0       5     0  this   Lorg/sireum/MBox10;
    Signature: #125                         // ()TT5;

  public org.sireum.MBox10<T1, T2, T3, T4, T5, T6, T7, T8, T9, T10> value5_$eq(T5);
    descriptor: (Ljava/lang/Object;)Lorg/sireum/MBox10;
    flags: (0x0001) ACC_PUBLIC
    Code:
      stack=2, locals=2, args_size=2
         0: aload_0
         1: aload_1
         2: putfield      #127                // Field _value5:Ljava/lang/Object;
         5: aload_0
         6: areturn
      LineNumberTable:
        line 47: 0
      LocalVariableTable:
        Start  Length  Slot  Name   Signature
            0       7     0  this   Lorg/sireum/MBox10;
            0       7     1 value5   Ljava/lang/Object;
    Signature: #130                         // (TT5;)Lorg/sireum/MBox10<TT1;TT2;TT3;TT4;TT5;TT6;TT7;TT8;TT9;TT10;>;
    MethodParameters:
      Name                           Flags
      value5                         final

  public org.sireum.MBox10<T1, T2, T3, T4, T5, T6, T7, T8, T9, T10> setValue5(T5);
    descriptor: (Ljava/lang/Object;)Lorg/sireum/MBox10;
    flags: (0x0001) ACC_PUBLIC
    Code:
      stack=2, locals=2, args_size=2
         0: aload_0
         1: aload_1
         2: putfield      #127                // Field _value5:Ljava/lang/Object;
         5: aload_0
         6: areturn
      LineNumberTable:
        line 47: 0
      LocalVariableTable:
        Start  Length  Slot  Name   Signature
            0       7     0  this   Lorg/sireum/MBox10;
            0       7     1 value5   Ljava/lang/Object;
    Signature: #130                         // (TT5;)Lorg/sireum/MBox10<TT1;TT2;TT3;TT4;TT5;TT6;TT7;TT8;TT9;TT10;>;
    MethodParameters:
      Name                           Flags
      value5                         final

  public T6 value6();
    descriptor: ()Ljava/lang/Object;
    flags: (0x0001) ACC_PUBLIC
    Code:
      stack=1, locals=1, args_size=1
         0: aload_0
         1: getfield      #135                // Field _value6:Ljava/lang/Object;
         4: areturn
      LineNumberTable:
        line 47: 0
      LocalVariableTable:
        Start  Length  Slot  Name   Signature
            0       5     0  this   Lorg/sireum/MBox10;
    Signature: #133                         // ()TT6;

  public T6 getValue6();
    descriptor: ()Ljava/lang/Object;
    flags: (0x0001) ACC_PUBLIC
    Code:
      stack=1, locals=1, args_size=1
         0: aload_0
         1: getfield      #135                // Field _value6:Ljava/lang/Object;
         4: areturn
      LineNumberTable:
        line 47: 0
      LocalVariableTable:
        Start  Length  Slot  Name   Signature
            0       5     0  this   Lorg/sireum/MBox10;
    Signature: #133                         // ()TT6;

  public org.sireum.MBox10<T1, T2, T3, T4, T5, T6, T7, T8, T9, T10> value6_$eq(T6);
    descriptor: (Ljava/lang/Object;)Lorg/sireum/MBox10;
    flags: (0x0001) ACC_PUBLIC
    Code:
      stack=2, locals=2, args_size=2
         0: aload_0
         1: aload_1
         2: putfield      #135                // Field _value6:Ljava/lang/Object;
         5: aload_0
         6: areturn
      LineNumberTable:
        line 47: 0
      LocalVariableTable:
        Start  Length  Slot  Name   Signature
            0       7     0  this   Lorg/sireum/MBox10;
            0       7     1 value6   Ljava/lang/Object;
    Signature: #138                         // (TT6;)Lorg/sireum/MBox10<TT1;TT2;TT3;TT4;TT5;TT6;TT7;TT8;TT9;TT10;>;
    MethodParameters:
      Name                           Flags
      value6                         final

  public org.sireum.MBox10<T1, T2, T3, T4, T5, T6, T7, T8, T9, T10> setValue6(T6);
    descriptor: (Ljava/lang/Object;)Lorg/sireum/MBox10;
    flags: (0x0001) ACC_PUBLIC
    Code:
      stack=2, locals=2, args_size=2
         0: aload_0
         1: aload_1
         2: putfield      #135                // Field _value6:Ljava/lang/Object;
         5: aload_0
         6: areturn
      LineNumberTable:
        line 47: 0
      LocalVariableTable:
        Start  Length  Slot  Name   Signature
            0       7     0  this   Lorg/sireum/MBox10;
            0       7     1 value6   Ljava/lang/Object;
    Signature: #138                         // (TT6;)Lorg/sireum/MBox10<TT1;TT2;TT3;TT4;TT5;TT6;TT7;TT8;TT9;TT10;>;
    MethodParameters:
      Name                           Flags
      value6                         final

  public T7 value7();
    descriptor: ()Ljava/lang/Object;
    flags: (0x0001) ACC_PUBLIC
    Code:
      stack=1, locals=1, args_size=1
         0: aload_0
         1: getfield      #143                // Field _value7:Ljava/lang/Object;
         4: areturn
      LineNumberTable:
        line 47: 0
      LocalVariableTable:
        Start  Length  Slot  Name   Signature
            0       5     0  this   Lorg/sireum/MBox10;
    Signature: #141                         // ()TT7;

  public T7 getValue7();
    descriptor: ()Ljava/lang/Object;
    flags: (0x0001) ACC_PUBLIC
    Code:
      stack=1, locals=1, args_size=1
         0: aload_0
         1: getfield      #143                // Field _value7:Ljava/lang/Object;
         4: areturn
      LineNumberTable:
        line 47: 0
      LocalVariableTable:
        Start  Length  Slot  Name   Signature
            0       5     0  this   Lorg/sireum/MBox10;
    Signature: #141                         // ()TT7;

  public org.sireum.MBox10<T1, T2, T3, T4, T5, T6, T7, T8, T9, T10> value7_$eq(T7);
    descriptor: (Ljava/lang/Object;)Lorg/sireum/MBox10;
    flags: (0x0001) ACC_PUBLIC
    Code:
      stack=2, locals=2, args_size=2
         0: aload_0
         1: aload_1
         2: putfield      #143                // Field _value7:Ljava/lang/Object;
         5: aload_0
         6: areturn
      LineNumberTable:
        line 47: 0
      LocalVariableTable:
        Start  Length  Slot  Name   Signature
            0       7     0  this   Lorg/sireum/MBox10;
            0       7     1 value7   Ljava/lang/Object;
    Signature: #146                         // (TT7;)Lorg/sireum/MBox10<TT1;TT2;TT3;TT4;TT5;TT6;TT7;TT8;TT9;TT10;>;
    MethodParameters:
      Name                           Flags
      value7                         final

  public org.sireum.MBox10<T1, T2, T3, T4, T5, T6, T7, T8, T9, T10> setValue7(T7);
    descriptor: (Ljava/lang/Object;)Lorg/sireum/MBox10;
    flags: (0x0001) ACC_PUBLIC
    Code:
      stack=2, locals=2, args_size=2
         0: aload_0
         1: aload_1
         2: putfield      #143                // Field _value7:Ljava/lang/Object;
         5: aload_0
         6: areturn
      LineNumberTable:
        line 47: 0
      LocalVariableTable:
        Start  Length  Slot  Name   Signature
            0       7     0  this   Lorg/sireum/MBox10;
            0       7     1 value7   Ljava/lang/Object;
    Signature: #146                         // (TT7;)Lorg/sireum/MBox10<TT1;TT2;TT3;TT4;TT5;TT6;TT7;TT8;TT9;TT10;>;
    MethodParameters:
      Name                           Flags
      value7                         final

  public T8 value8();
    descriptor: ()Ljava/lang/Object;
    flags: (0x0001) ACC_PUBLIC
    Code:
      stack=1, locals=1, args_size=1
         0: aload_0
         1: getfield      #151                // Field _value8:Ljava/lang/Object;
         4: areturn
      LineNumberTable:
        line 47: 0
      LocalVariableTable:
        Start  Length  Slot  Name   Signature
            0       5     0  this   Lorg/sireum/MBox10;
    Signature: #149                         // ()TT8;

  public T8 getValue8();
    descriptor: ()Ljava/lang/Object;
    flags: (0x0001) ACC_PUBLIC
    Code:
      stack=1, locals=1, args_size=1
         0: aload_0
         1: getfield      #151                // Field _value8:Ljava/lang/Object;
         4: areturn
      LineNumberTable:
        line 47: 0
      LocalVariableTable:
        Start  Length  Slot  Name   Signature
            0       5     0  this   Lorg/sireum/MBox10;
    Signature: #149                         // ()TT8;

  public org.sireum.MBox10<T1, T2, T3, T4, T5, T6, T7, T8, T9, T10> value8_$eq(T8);
    descriptor: (Ljava/lang/Object;)Lorg/sireum/MBox10;
    flags: (0x0001) ACC_PUBLIC
    Code:
      stack=2, locals=2, args_size=2
         0: aload_0
         1: aload_1
         2: putfield      #151                // Field _value8:Ljava/lang/Object;
         5: aload_0
         6: areturn
      LineNumberTable:
        line 47: 0
      LocalVariableTable:
        Start  Length  Slot  Name   Signature
            0       7     0  this   Lorg/sireum/MBox10;
            0       7     1 value8   Ljava/lang/Object;
    Signature: #154                         // (TT8;)Lorg/sireum/MBox10<TT1;TT2;TT3;TT4;TT5;TT6;TT7;TT8;TT9;TT10;>;
    MethodParameters:
      Name                           Flags
      value8                         final

  public org.sireum.MBox10<T1, T2, T3, T4, T5, T6, T7, T8, T9, T10> setValue8(T8);
    descriptor: (Ljava/lang/Object;)Lorg/sireum/MBox10;
    flags: (0x0001) ACC_PUBLIC
    Code:
      stack=2, locals=2, args_size=2
         0: aload_0
         1: aload_1
         2: putfield      #151                // Field _value8:Ljava/lang/Object;
         5: aload_0
         6: areturn
      LineNumberTable:
        line 47: 0
      LocalVariableTable:
        Start  Length  Slot  Name   Signature
            0       7     0  this   Lorg/sireum/MBox10;
            0       7     1 value8   Ljava/lang/Object;
    Signature: #154                         // (TT8;)Lorg/sireum/MBox10<TT1;TT2;TT3;TT4;TT5;TT6;TT7;TT8;TT9;TT10;>;
    MethodParameters:
      Name                           Flags
      value8                         final

  public T9 value9();
    descriptor: ()Ljava/lang/Object;
    flags: (0x0001) ACC_PUBLIC
    Code:
      stack=1, locals=1, args_size=1
         0: aload_0
         1: getfield      #159                // Field _value9:Ljava/lang/Object;
         4: areturn
      LineNumberTable:
        line 47: 0
      LocalVariableTable:
        Start  Length  Slot  Name   Signature
            0       5     0  this   Lorg/sireum/MBox10;
    Signature: #157                         // ()TT9;

  public T9 getValue9();
    descriptor: ()Ljava/lang/Object;
    flags: (0x0001) ACC_PUBLIC
    Code:
      stack=1, locals=1, args_size=1
         0: aload_0
         1: getfield      #159                // Field _value9:Ljava/lang/Object;
         4: areturn
      LineNumberTable:
        line 47: 0
      LocalVariableTable:
        Start  Length  Slot  Name   Signature
            0       5     0  this   Lorg/sireum/MBox10;
    Signature: #157                         // ()TT9;

  public org.sireum.MBox10<T1, T2, T3, T4, T5, T6, T7, T8, T9, T10> value9_$eq(T9);
    descriptor: (Ljava/lang/Object;)Lorg/sireum/MBox10;
    flags: (0x0001) ACC_PUBLIC
    Code:
      stack=2, locals=2, args_size=2
         0: aload_0
         1: aload_1
         2: putfield      #159                // Field _value9:Ljava/lang/Object;
         5: aload_0
         6: areturn
      LineNumberTable:
        line 47: 0
      LocalVariableTable:
        Start  Length  Slot  Name   Signature
            0       7     0  this   Lorg/sireum/MBox10;
            0       7     1 value9   Ljava/lang/Object;
    Signature: #162                         // (TT9;)Lorg/sireum/MBox10<TT1;TT2;TT3;TT4;TT5;TT6;TT7;TT8;TT9;TT10;>;
    MethodParameters:
      Name                           Flags
      value9                         final

  public org.sireum.MBox10<T1, T2, T3, T4, T5, T6, T7, T8, T9, T10> setValue9(T9);
    descriptor: (Ljava/lang/Object;)Lorg/sireum/MBox10;
    flags: (0x0001) ACC_PUBLIC
    Code:
      stack=2, locals=2, args_size=2
         0: aload_0
         1: aload_1
         2: putfield      #159                // Field _value9:Ljava/lang/Object;
         5: aload_0
         6: areturn
      LineNumberTable:
        line 47: 0
      LocalVariableTable:
        Start  Length  Slot  Name   Signature
            0       7     0  this   Lorg/sireum/MBox10;
            0       7     1 value9   Ljava/lang/Object;
    Signature: #162                         // (TT9;)Lorg/sireum/MBox10<TT1;TT2;TT3;TT4;TT5;TT6;TT7;TT8;TT9;TT10;>;
    MethodParameters:
      Name                           Flags
      value9                         final

  public T10 value10();
    descriptor: ()Ljava/lang/Object;
    flags: (0x0001) ACC_PUBLIC
    Code:
      stack=1, locals=1, args_size=1
         0: aload_0
         1: getfield      #167                // Field _value10:Ljava/lang/Object;
         4: areturn
      LineNumberTable:
        line 47: 0
      LocalVariableTable:
        Start  Length  Slot  Name   Signature
            0       5     0  this   Lorg/sireum/MBox10;
    Signature: #165                         // ()TT10;

  public T10 getValue10();
    descriptor: ()Ljava/lang/Object;
    flags: (0x0001) ACC_PUBLIC
    Code:
      stack=1, locals=1, args_size=1
         0: aload_0
         1: getfield      #167                // Field _value10:Ljava/lang/Object;
         4: areturn
      LineNumberTable:
        line 47: 0
      LocalVariableTable:
        Start  Length  Slot  Name   Signature
            0       5     0  this   Lorg/sireum/MBox10;
    Signature: #165                         // ()TT10;

  public org.sireum.MBox10<T1, T2, T3, T4, T5, T6, T7, T8, T9, T10> value10_$eq(T10);
    descriptor: (Ljava/lang/Object;)Lorg/sireum/MBox10;
    flags: (0x0001) ACC_PUBLIC
    Code:
      stack=2, locals=2, args_size=2
         0: aload_0
         1: aload_1
         2: putfield      #167                // Field _value10:Ljava/lang/Object;
         5: aload_0
         6: areturn
      LineNumberTable:
        line 47: 0
      LocalVariableTable:
        Start  Length  Slot  Name   Signature
            0       7     0  this   Lorg/sireum/MBox10;
            0       7     1 value10   Ljava/lang/Object;
    Signature: #170                         // (TT10;)Lorg/sireum/MBox10<TT1;TT2;TT3;TT4;TT5;TT6;TT7;TT8;TT9;TT10;>;
    MethodParameters:
      Name                           Flags
      value10                        final

  public org.sireum.MBox10<T1, T2, T3, T4, T5, T6, T7, T8, T9, T10> setValue10(T10);
    descriptor: (Ljava/lang/Object;)Lorg/sireum/MBox10;
    flags: (0x0001) ACC_PUBLIC
    Code:
      stack=2, locals=2, args_size=2
         0: aload_0
         1: aload_1
         2: putfield      #167                // Field _value10:Ljava/lang/Object;
         5: aload_0
         6: areturn
      LineNumberTable:
        line 47: 0
      LocalVariableTable:
        Start  Length  Slot  Name   Signature
            0       7     0  this   Lorg/sireum/MBox10;
            0       7     1 value10   Ljava/lang/Object;
    Signature: #170                         // (TT10;)Lorg/sireum/MBox10<TT1;TT2;TT3;TT4;TT5;TT6;TT7;TT8;TT9;TT10;>;
    MethodParameters:
      Name                           Flags
      value10                        final

  public java.lang.String toString();
    descriptor: ()Ljava/lang/String;
    flags: (0x0001) ACC_PUBLIC
    Code:
      stack=3, locals=2, args_size=1
         0: aload_0
         1: invokevirtual #175                // Method $hasString:()Z
         4: ifeq          14
         7: aload_0
         8: invokestatic  #179                // InterfaceMethod org/sireum/RecordSig.string$:(Lorg/sireum/RecordSig;)Ljava/lang/String;
        11: goto          260
        14: new           #181                // class java/lang/StringBuilder
        17: dup
        18: invokespecial #185                // Method java/lang/StringBuilder."<init>":()V
        21: astore_1
        22: aload_1
        23: ldc           #187                // String MBox10
        25: invokevirtual #191                // Method java/lang/StringBuilder.append:(Ljava/lang/String;)Ljava/lang/StringBuilder;
        28: pop
        29: aload_1
        30: bipush        40
        32: invokevirtual #194                // Method java/lang/StringBuilder.append:(C)Ljava/lang/StringBuilder;
        35: pop
        36: aload_1
        37: getstatic     #199                // Field org/sireum/String$.MODULE$:Lorg/sireum/String$;
        40: aload_0
        41: invokevirtual #201                // Method value1:()Ljava/lang/Object;
        44: invokevirtual #205                // Method org/sireum/String$.escape:(Ljava/lang/Object;)Ljava/lang/String;
        47: invokevirtual #191                // Method java/lang/StringBuilder.append:(Ljava/lang/String;)Ljava/lang/StringBuilder;
        50: pop
        51: aload_1
        52: ldc           #207                // String ,
        54: invokevirtual #191                // Method java/lang/StringBuilder.append:(Ljava/lang/String;)Ljava/lang/StringBuilder;
        57: pop
        58: aload_1
        59: getstatic     #199                // Field org/sireum/String$.MODULE$:Lorg/sireum/String$;
        62: aload_0
        63: invokevirtual #209                // Method value2:()Ljava/lang/Object;
        66: invokevirtual #205                // Method org/sireum/String$.escape:(Ljava/lang/Object;)Ljava/lang/String;
        69: invokevirtual #191                // Method java/lang/StringBuilder.append:(Ljava/lang/String;)Ljava/lang/StringBuilder;
        72: pop
        73: aload_1
        74: ldc           #207                // String ,
        76: invokevirtual #191                // Method java/lang/StringBuilder.append:(Ljava/lang/String;)Ljava/lang/StringBuilder;
        79: pop
        80: aload_1
        81: getstatic     #199                // Field org/sireum/String$.MODULE$:Lorg/sireum/String$;
        84: aload_0
        85: invokevirtual #211                // Method value3:()Ljava/lang/Object;
        88: invokevirtual #205                // Method org/sireum/String$.escape:(Ljava/lang/Object;)Ljava/lang/String;
        91: invokevirtual #191                // Method java/lang/StringBuilder.append:(Ljava/lang/String;)Ljava/lang/StringBuilder;
        94: pop
        95: aload_1
        96: ldc           #207                // String ,
        98: invokevirtual #191                // Method java/lang/StringBuilder.append:(Ljava/lang/String;)Ljava/lang/StringBuilder;
       101: pop
       102: aload_1
       103: getstatic     #199                // Field org/sireum/String$.MODULE$:Lorg/sireum/String$;
       106: aload_0
       107: invokevirtual #213                // Method value4:()Ljava/lang/Object;
       110: invokevirtual #205                // Method org/sireum/String$.escape:(Ljava/lang/Object;)Ljava/lang/String;
       113: invokevirtual #191                // Method java/lang/StringBuilder.append:(Ljava/lang/String;)Ljava/lang/StringBuilder;
       116: pop
       117: aload_1
       118: ldc           #207                // String ,
       120: invokevirtual #191                // Method java/lang/StringBuilder.append:(Ljava/lang/String;)Ljava/lang/StringBuilder;
       123: pop
       124: aload_1
       125: getstatic     #199                // Field org/sireum/String$.MODULE$:Lorg/sireum/String$;
       128: aload_0
       129: invokevirtual #215                // Method value5:()Ljava/lang/Object;
       132: invokevirtual #205                // Method org/sireum/String$.escape:(Ljava/lang/Object;)Ljava/lang/String;
       135: invokevirtual #191                // Method java/lang/StringBuilder.append:(Ljava/lang/String;)Ljava/lang/StringBuilder;
       138: pop
       139: aload_1
       140: ldc           #207                // String ,
       142: invokevirtual #191                // Method java/lang/StringBuilder.append:(Ljava/lang/String;)Ljava/lang/StringBuilder;
       145: pop
       146: aload_1
       147: getstatic     #199                // Field org/sireum/String$.MODULE$:Lorg/sireum/String$;
       150: aload_0
       151: invokevirtual #217                // Method value6:()Ljava/lang/Object;
       154: invokevirtual #205                // Method org/sireum/String$.escape:(Ljava/lang/Object;)Ljava/lang/String;
       157: invokevirtual #191                // Method java/lang/StringBuilder.append:(Ljava/lang/String;)Ljava/lang/StringBuilder;
       160: pop
       161: aload_1
       162: ldc           #207                // String ,
       164: invokevirtual #191                // Method java/lang/StringBuilder.append:(Ljava/lang/String;)Ljava/lang/StringBuilder;
       167: pop
       168: aload_1
       169: getstatic     #199                // Field org/sireum/String$.MODULE$:Lorg/sireum/String$;
       172: aload_0
       173: invokevirtual #219                // Method value7:()Ljava/lang/Object;
       176: invokevirtual #205                // Method org/sireum/String$.escape:(Ljava/lang/Object;)Ljava/lang/String;
       179: invokevirtual #191                // Method java/lang/StringBuilder.append:(Ljava/lang/String;)Ljava/lang/StringBuilder;
       182: pop
       183: aload_1
       184: ldc           #207                // String ,
       186: invokevirtual #191                // Method java/lang/StringBuilder.append:(Ljava/lang/String;)Ljava/lang/StringBuilder;
       189: pop
       190: aload_1
       191: getstatic     #199                // Field org/sireum/String$.MODULE$:Lorg/sireum/String$;
       194: aload_0
       195: invokevirtual #221                // Method value8:()Ljava/lang/Object;
       198: invokevirtual #205                // Method org/sireum/String$.escape:(Ljava/lang/Object;)Ljava/lang/String;
       201: invokevirtual #191                // Method java/lang/StringBuilder.append:(Ljava/lang/String;)Ljava/lang/StringBuilder;
       204: pop
       205: aload_1
       206: ldc           #207                // String ,
       208: invokevirtual #191                // Method java/lang/StringBuilder.append:(Ljava/lang/String;)Ljava/lang/StringBuilder;
       211: pop
       212: aload_1
       213: getstatic     #199                // Field org/sireum/String$.MODULE$:Lorg/sireum/String$;
       216: aload_0
       217: invokevirtual #223                // Method value9:()Ljava/lang/Object;
       220: invokevirtual #205                // Method org/sireum/String$.escape:(Ljava/lang/Object;)Ljava/lang/String;
       223: invokevirtual #191                // Method java/lang/StringBuilder.append:(Ljava/lang/String;)Ljava/lang/StringBuilder;
       226: pop
       227: aload_1
       228: ldc           #207                // String ,
       230: invokevirtual #191                // Method java/lang/StringBuilder.append:(Ljava/lang/String;)Ljava/lang/StringBuilder;
       233: pop
       234: aload_1
       235: getstatic     #199                // Field org/sireum/String$.MODULE$:Lorg/sireum/String$;
       238: aload_0
       239: invokevirtual #225                // Method value10:()Ljava/lang/Object;
       242: invokevirtual #205                // Method org/sireum/String$.escape:(Ljava/lang/Object;)Ljava/lang/String;
       245: invokevirtual #191                // Method java/lang/StringBuilder.append:(Ljava/lang/String;)Ljava/lang/StringBuilder;
       248: pop
       249: aload_1
       250: bipush        41
       252: invokevirtual #194                // Method java/lang/StringBuilder.append:(C)Ljava/lang/StringBuilder;
       255: pop
       256: aload_1
       257: invokevirtual #227                // Method java/lang/StringBuilder.toString:()Ljava/lang/String;
       260: areturn
      StackMapTable: number_of_entries = 2
        frame_type = 14 /* same */
        frame_type = 247 /* same_locals_1_stack_item_frame_extended */
          offset_delta = 245
          stack = [ class java/lang/String ]
      LineNumberTable:
        line 47: 0
      LocalVariableTable:
        Start  Length  Slot  Name   Signature
           22     238     1    sb   Ljava/lang/StringBuilder;
            0     261     0  this   Lorg/sireum/MBox10;

  public java.lang.String string();
    descriptor: ()Ljava/lang/String;
    flags: (0x0001) ACC_PUBLIC
    Code:
      stack=2, locals=1, args_size=1
         0: aload_0
         1: invokevirtual #175                // Method $hasString:()Z
         4: ifeq          14
         7: aload_0
         8: invokestatic  #179                // InterfaceMethod org/sireum/RecordSig.string$:(Lorg/sireum/RecordSig;)Ljava/lang/String;
        11: goto          24
        14: getstatic     #199                // Field org/sireum/String$.MODULE$:Lorg/sireum/String$;
        17: aload_0
        18: invokevirtual #233                // Method toString:()Ljava/lang/String;
        21: invokevirtual #237                // Method org/sireum/String$.apply:(Ljava/lang/String;)Ljava/lang/String;
        24: areturn
      StackMapTable: number_of_entries = 2
        frame_type = 14 /* same */
        frame_type = 73 /* same_locals_1_stack_item */
          stack = [ class java/lang/String ]
      LineNumberTable:
        line 47: 0
      LocalVariableTable:
        Start  Length  Slot  Name   Signature
            0      25     0  this   Lorg/sireum/MBox10;

  public int hashCode();
    descriptor: ()I
    flags: (0x0001) ACC_PUBLIC
    Code:
      stack=6, locals=1, args_size=1
         0: aload_0
         1: invokevirtual #241                // Method $hasEquals:()Z
         4: ifeq          14
         7: aload_0
         8: invokespecial #243                // Method java/lang/Object.hashCode:()I
        11: goto          127
        14: getstatic     #248                // Field scala/package$.MODULE$:Lscala/package$;
        17: invokevirtual #252                // Method scala/package$.Seq:()Lscala/collection/immutable/Seq$;
        20: getstatic     #257                // Field scala/runtime/ScalaRunTime$.MODULE$:Lscala/runtime/ScalaRunTime$;
        23: bipush        11
        25: anewarray     #5                  // class java/lang/Object
        28: dup
        29: iconst_0
        30: aload_0
        31: invokevirtual #261                // Method getClass:()Ljava/lang/Class;
        34: invokevirtual #266                // Method java/lang/Class.getName:()Ljava/lang/String;
        37: aastore
        38: dup
        39: iconst_1
        40: aload_0
        41: invokevirtual #201                // Method value1:()Ljava/lang/Object;
        44: aastore
        45: dup
        46: iconst_2
        47: aload_0
        48: invokevirtual #209                // Method value2:()Ljava/lang/Object;
        51: aastore
        52: dup
        53: iconst_3
        54: aload_0
        55: invokevirtual #211                // Method value3:()Ljava/lang/Object;
        58: aastore
        59: dup
        60: iconst_4
        61: aload_0
        62: invokevirtual #213                // Method value4:()Ljava/lang/Object;
        65: aastore
        66: dup
        67: iconst_5
        68: aload_0
        69: invokevirtual #215                // Method value5:()Ljava/lang/Object;
        72: aastore
        73: dup
        74: bipush        6
        76: aload_0
        77: invokevirtual #217                // Method value6:()Ljava/lang/Object;
        80: aastore
        81: dup
        82: bipush        7
        84: aload_0
        85: invokevirtual #219                // Method value7:()Ljava/lang/Object;
        88: aastore
        89: dup
        90: bipush        8
        92: aload_0
        93: invokevirtual #221                // Method value8:()Ljava/lang/Object;
        96: aastore
        97: dup
        98: bipush        9
       100: aload_0
       101: invokevirtual #223                // Method value9:()Ljava/lang/Object;
       104: aastore
       105: dup
       106: bipush        10
       108: aload_0
       109: invokevirtual #225                // Method value10:()Ljava/lang/Object;
       112: aastore
       113: invokevirtual #270                // Method scala/runtime/ScalaRunTime$.genericWrapArray:(Ljava/lang/Object;)Lscala/collection/immutable/ArraySeq;
       116: invokevirtual #275                // Method scala/collection/immutable/Seq$.apply:(Lscala/collection/immutable/Seq;)Lscala/collection/SeqOps;
       119: checkcast     #277                // class scala/collection/Seq
       122: invokeinterface #278,  1          // InterfaceMethod scala/collection/Seq.hashCode:()I
       127: ireturn
      StackMapTable: number_of_entries = 2
        frame_type = 14 /* same */
        frame_type = 247 /* same_locals_1_stack_item_frame_extended */
          offset_delta = 112
          stack = [ int ]
      LineNumberTable:
        line 47: 0
      LocalVariableTable:
        Start  Length  Slot  Name   Signature
            0     128     0  this   Lorg/sireum/MBox10;

  public boolean equals(java.lang.Object);
    descriptor: (Ljava/lang/Object;)Z
    flags: (0x0001) ACC_PUBLIC
    Code:
      stack=2, locals=5, args_size=2
         0: aload_0
         1: invokevirtual #241                // Method $hasEquals:()Z
         4: ifeq          15
         7: aload_0
         8: aload_1
         9: invokespecial #282                // Method java/lang/Object.equals:(Ljava/lang/Object;)Z
        12: goto          223
        15: aload_0
        16: aload_1
        17: if_acmpne     24
        20: iconst_1
        21: goto          223
        24: aload_1
        25: astore_3
        26: aload_3
        27: instanceof    #2                  // class org/sireum/MBox10
        30: ifeq          214
        33: aload_3
        34: checkcast     #2                  // class org/sireum/MBox10
        37: astore        4
        39: aload_0
        40: invokevirtual #283                // Method hashCode:()I
        43: aload         4
        45: invokevirtual #283                // Method hashCode:()I
        48: if_icmpeq     55
        51: iconst_0
        52: goto          210
        55: aload_0
        56: invokevirtual #201                // Method value1:()Ljava/lang/Object;
        59: aload         4
        61: invokevirtual #201                // Method value1:()Ljava/lang/Object;
        64: invokestatic  #288                // Method scala/runtime/BoxesRunTime.equals:(Ljava/lang/Object;Ljava/lang/Object;)Z
        67: ifeq          209
        70: aload_0
        71: invokevirtual #209                // Method value2:()Ljava/lang/Object;
        74: aload         4
        76: invokevirtual #209                // Method value2:()Ljava/lang/Object;
        79: invokestatic  #288                // Method scala/runtime/BoxesRunTime.equals:(Ljava/lang/Object;Ljava/lang/Object;)Z
        82: ifeq          209
        85: aload_0
        86: invokevirtual #211                // Method value3:()Ljava/lang/Object;
        89: aload         4
        91: invokevirtual #211                // Method value3:()Ljava/lang/Object;
        94: invokestatic  #288                // Method scala/runtime/BoxesRunTime.equals:(Ljava/lang/Object;Ljava/lang/Object;)Z
        97: ifeq          209
       100: aload_0
       101: invokevirtual #213                // Method value4:()Ljava/lang/Object;
       104: aload         4
       106: invokevirtual #213                // Method value4:()Ljava/lang/Object;
       109: invokestatic  #288                // Method scala/runtime/BoxesRunTime.equals:(Ljava/lang/Object;Ljava/lang/Object;)Z
       112: ifeq          209
       115: aload_0
       116: invokevirtual #215                // Method value5:()Ljava/lang/Object;
       119: aload         4
       121: invokevirtual #215                // Method value5:()Ljava/lang/Object;
       124: invokestatic  #288                // Method scala/runtime/BoxesRunTime.equals:(Ljava/lang/Object;Ljava/lang/Object;)Z
       127: ifeq          209
       130: aload_0
       131: invokevirtual #217                // Method value6:()Ljava/lang/Object;
       134: aload         4
       136: invokevirtual #217                // Method value6:()Ljava/lang/Object;
       139: invokestatic  #288                // Method scala/runtime/BoxesRunTime.equals:(Ljava/lang/Object;Ljava/lang/Object;)Z
       142: ifeq          209
       145: aload_0
       146: invokevirtual #219                // Method value7:()Ljava/lang/Object;
       149: aload         4
       151: invokevirtual #219                // Method value7:()Ljava/lang/Object;
       154: invokestatic  #288                // Method scala/runtime/BoxesRunTime.equals:(Ljava/lang/Object;Ljava/lang/Object;)Z
       157: ifeq          209
       160: aload_0
       161: invokevirtual #221                // Method value8:()Ljava/lang/Object;
       164: aload         4
       166: invokevirtual #221                // Method value8:()Ljava/lang/Object;
       169: invokestatic  #288                // Method scala/runtime/BoxesRunTime.equals:(Ljava/lang/Object;Ljava/lang/Object;)Z
       172: ifeq          209
       175: aload_0
       176: invokevirtual #223                // Method value9:()Ljava/lang/Object;
       179: aload         4
       181: invokevirtual #223                // Method value9:()Ljava/lang/Object;
       184: invokestatic  #288                // Method scala/runtime/BoxesRunTime.equals:(Ljava/lang/Object;Ljava/lang/Object;)Z
       187: ifeq          209
       190: aload_0
       191: invokevirtual #225                // Method value10:()Ljava/lang/Object;
       194: aload         4
       196: invokevirtual #225                // Method value10:()Ljava/lang/Object;
       199: invokestatic  #288                // Method scala/runtime/BoxesRunTime.equals:(Ljava/lang/Object;Ljava/lang/Object;)Z
       202: ifeq          209
       205: iconst_1
       206: goto          210
       209: iconst_0
       210: istore_2
       211: goto          222
       214: goto          217
       217: iconst_0
       218: istore_2
       219: goto          222
       222: iload_2
       223: ireturn
      StackMapTable: number_of_entries = 9
        frame_type = 15 /* same */
        frame_type = 8 /* same */
        frame_type = 254 /* append */
          offset_delta = 30
          locals = [ top, class java/lang/Object, class org/sireum/MBox10 ]
        frame_type = 251 /* same_frame_extended */
          offset_delta = 153
        frame_type = 64 /* same_locals_1_stack_item */
          stack = [ int ]
        frame_type = 250 /* chop */
          offset_delta = 3
        frame_type = 2 /* same */
        frame_type = 255 /* full_frame */
          offset_delta = 4
          locals = [ class org/sireum/MBox10, class java/lang/Object, int, class java/lang/Object ]
          stack = []
        frame_type = 255 /* full_frame */
          offset_delta = 0
          locals = [ class org/sireum/MBox10, class java/lang/Object ]
          stack = [ int ]
      LineNumberTable:
        line 47: 0
      LocalVariableTable:
        Start  Length  Slot  Name   Signature
            0     224     0  this   Lorg/sireum/MBox10;
            0     224     1     o   Ljava/lang/Object;
    MethodParameters:
      Name                           Flags
      o                              final

  public org.sireum.MBox10<T1, T2, T3, T4, T5, T6, T7, T8, T9, T10> apply(T1, T2, T3, T4, T5, T6, T7, T8, T9, T10);
    descriptor: (Ljava/lang/Object;Ljava/lang/Object;Ljava/lang/Object;Ljava/lang/Object;Ljava/lang/Object;Ljava/lang/Object;Ljava/lang/Object;Ljava/lang/Object;Ljava/lang/Object;Ljava/lang/Object;)Lorg/sireum/MBox10;
    flags: (0x0001) ACC_PUBLIC
    Code:
      stack=12, locals=11, args_size=11
         0: new           #2                  // class org/sireum/MBox10
         3: dup
         4: aload_1
         5: aload_2
         6: aload_3
         7: aload         4
         9: aload         5
        11: aload         6
        13: aload         7
        15: aload         8
        17: aload         9
        19: aload         10
        21: invokespecial #293                // Method "<init>":(Ljava/lang/Object;Ljava/lang/Object;Ljava/lang/Object;Ljava/lang/Object;Ljava/lang/Object;Ljava/lang/Object;Ljava/lang/Object;Ljava/lang/Object;Ljava/lang/Object;Ljava/lang/Object;)V
        24: areturn
      LineNumberTable:
        line 47: 0
      LocalVariableTable:
        Start  Length  Slot  Name   Signature
            0      25     0  this   Lorg/sireum/MBox10;
            0      25     1 value1   Ljava/lang/Object;
            0      25     2 value2   Ljava/lang/Object;
            0      25     3 value3   Ljava/lang/Object;
            0      25     4 value4   Ljava/lang/Object;
            0      25     5 value5   Ljava/lang/Object;
            0      25     6 value6   Ljava/lang/Object;
            0      25     7 value7   Ljava/lang/Object;
            0      25     8 value8   Ljava/lang/Object;
            0      25     9 value9   Ljava/lang/Object;
            0      25    10 value10   Ljava/lang/Object;
    Signature: #290                         // (TT1;TT2;TT3;TT4;TT5;TT6;TT7;TT8;TT9;TT10;)Lorg/sireum/MBox10<TT1;TT2;TT3;TT4;TT5;TT6;TT7;TT8;TT9;TT10;>;
    MethodParameters:
      Name                           Flags
      value1                         final
      value2                         final
      value3                         final
      value4                         final
      value5                         final
      value6                         final
      value7                         final
      value8                         final
      value9                         final
      value10                        final

  public T1 apply$default$1();
    descriptor: ()Ljava/lang/Object;
    flags: (0x0001) ACC_PUBLIC
    Code:
      stack=1, locals=1, args_size=1
         0: aload_0
         1: invokevirtual #201                // Method value1:()Ljava/lang/Object;
         4: areturn
      LineNumberTable:
        line 47: 0
      LocalVariableTable:
        Start  Length  Slot  Name   Signature
            0       5     0  this   Lorg/sireum/MBox10;
    Signature: #92                          // ()TT1;

  public T2 apply$default$2();
    descriptor: ()Ljava/lang/Object;
    flags: (0x0001) ACC_PUBLIC
    Code:
      stack=1, locals=1, args_size=1
         0: aload_0
         1: invokevirtual #209                // Method value2:()Ljava/lang/Object;
         4: areturn
      LineNumberTable:
        line 47: 0
      LocalVariableTable:
        Start  Length  Slot  Name   Signature
            0       5     0  this   Lorg/sireum/MBox10;
    Signature: #101                         // ()TT2;

  public T3 apply$default$3();
    descriptor: ()Ljava/lang/Object;
    flags: (0x0001) ACC_PUBLIC
    Code:
      stack=1, locals=1, args_size=1
         0: aload_0
         1: invokevirtual #211                // Method value3:()Ljava/lang/Object;
         4: areturn
      LineNumberTable:
        line 47: 0
      LocalVariableTable:
        Start  Length  Slot  Name   Signature
            0       5     0  this   Lorg/sireum/MBox10;
    Signature: #109                         // ()TT3;

  public T4 apply$default$4();
    descriptor: ()Ljava/lang/Object;
    flags: (0x0001) ACC_PUBLIC
    Code:
      stack=1, locals=1, args_size=1
         0: aload_0
         1: invokevirtual #213                // Method value4:()Ljava/lang/Object;
         4: areturn
      LineNumberTable:
        line 47: 0
      LocalVariableTable:
        Start  Length  Slot  Name   Signature
            0       5     0  this   Lorg/sireum/MBox10;
    Signature: #117                         // ()TT4;

  public T5 apply$default$5();
    descriptor: ()Ljava/lang/Object;
    flags: (0x0001) ACC_PUBLIC
    Code:
      stack=1, locals=1, args_size=1
         0: aload_0
         1: invokevirtual #215                // Method value5:()Ljava/lang/Object;
         4: areturn
      LineNumberTable:
        line 47: 0
      LocalVariableTable:
        Start  Length  Slot  Name   Signature
            0       5     0  this   Lorg/sireum/MBox10;
    Signature: #125                         // ()TT5;

  public T6 apply$default$6();
    descriptor: ()Ljava/lang/Object;
    flags: (0x0001) ACC_PUBLIC
    Code:
      stack=1, locals=1, args_size=1
         0: aload_0
         1: invokevirtual #217                // Method value6:()Ljava/lang/Object;
         4: areturn
      LineNumberTable:
        line 47: 0
      LocalVariableTable:
        Start  Length  Slot  Name   Signature
            0       5     0  this   Lorg/sireum/MBox10;
    Signature: #133                         // ()TT6;

  public T7 apply$default$7();
    descriptor: ()Ljava/lang/Object;
    flags: (0x0001) ACC_PUBLIC
    Code:
      stack=1, locals=1, args_size=1
         0: aload_0
         1: invokevirtual #219                // Method value7:()Ljava/lang/Object;
         4: areturn
      LineNumberTable:
        line 47: 0
      LocalVariableTable:
        Start  Length  Slot  Name   Signature
            0       5     0  this   Lorg/sireum/MBox10;
    Signature: #141                         // ()TT7;

  public T8 apply$default$8();
    descriptor: ()Ljava/lang/Object;
    flags: (0x0001) ACC_PUBLIC
    Code:
      stack=1, locals=1, args_size=1
         0: aload_0
         1: invokevirtual #221                // Method value8:()Ljava/lang/Object;
         4: areturn
      LineNumberTable:
        line 47: 0
      LocalVariableTable:
        Start  Length  Slot  Name   Signature
            0       5     0  this   Lorg/sireum/MBox10;
    Signature: #149                         // ()TT8;

  public T9 apply$default$9();
    descriptor: ()Ljava/lang/Object;
    flags: (0x0001) ACC_PUBLIC
    Code:
      stack=1, locals=1, args_size=1
         0: aload_0
         1: invokevirtual #223                // Method value9:()Ljava/lang/Object;
         4: areturn
      LineNumberTable:
        line 47: 0
      LocalVariableTable:
        Start  Length  Slot  Name   Signature
            0       5     0  this   Lorg/sireum/MBox10;
    Signature: #157                         // ()TT9;

  public T10 apply$default$10();
    descriptor: ()Ljava/lang/Object;
    flags: (0x0001) ACC_PUBLIC
    Code:
      stack=1, locals=1, args_size=1
         0: aload_0
         1: invokevirtual #225                // Method value10:()Ljava/lang/Object;
         4: areturn
      LineNumberTable:
        line 47: 0
      LocalVariableTable:
        Start  Length  Slot  Name   Signature
            0       5     0  this   Lorg/sireum/MBox10;
    Signature: #165                         // ()TT10;

  public scala.collection.immutable.Seq<scala.Tuple2<java.lang.String, java.lang.Object>> $content();
    descriptor: ()Lscala/collection/immutable/Seq;
    flags: (0x0001) ACC_PUBLIC
    Code:
      stack=14, locals=1, args_size=1
         0: getstatic     #248                // Field scala/package$.MODULE$:Lscala/package$;
         3: invokevirtual #252                // Method scala/package$.Seq:()Lscala/collection/immutable/Seq$;
         6: getstatic     #257                // Field scala/runtime/ScalaRunTime$.MODULE$:Lscala/runtime/ScalaRunTime$;
         9: bipush        11
        11: anewarray     #308                // class scala/Tuple2
        14: dup
        15: iconst_0
        16: new           #308                // class scala/Tuple2
        19: dup
        20: ldc_w         #310                // String type
        23: getstatic     #248                // Field scala/package$.MODULE$:Lscala/package$;
        26: invokevirtual #314                // Method scala/package$.List:()Lscala/collection/immutable/List$;
        29: getstatic     #257                // Field scala/runtime/ScalaRunTime$.MODULE$:Lscala/runtime/ScalaRunTime$;
        32: iconst_3
        33: anewarray     #231                // class java/lang/String
        36: dup
        37: iconst_0
        38: ldc_w         #316                // String org
        41: aastore
        42: dup
        43: iconst_1
        44: ldc_w         #318                // String sireum
        47: aastore
        48: dup
        49: iconst_2
        50: ldc           #187                // String MBox10
        52: aastore
        53: checkcast     #320                // class "[Ljava/lang/Object;"
        56: invokevirtual #324                // Method scala/runtime/ScalaRunTime$.wrapRefArray:([Ljava/lang/Object;)Lscala/collection/immutable/ArraySeq;
        59: invokevirtual #329                // Method scala/collection/immutable/List$.apply:(Lscala/collection/immutable/Seq;)Ljava/lang/Object;
        62: invokespecial #332                // Method scala/Tuple2."<init>":(Ljava/lang/Object;Ljava/lang/Object;)V
        65: aastore
        66: dup
        67: iconst_1
        68: new           #308                // class scala/Tuple2
        71: dup
        72: ldc_w         #333                // String value1
        75: aload_0
        76: invokevirtual #201                // Method value1:()Ljava/lang/Object;
        79: invokespecial #332                // Method scala/Tuple2."<init>":(Ljava/lang/Object;Ljava/lang/Object;)V
        82: aastore
        83: dup
        84: iconst_2
        85: new           #308                // class scala/Tuple2
        88: dup
        89: ldc_w         #334                // String value2
        92: aload_0
        93: invokevirtual #209                // Method value2:()Ljava/lang/Object;
        96: invokespecial #332                // Method scala/Tuple2."<init>":(Ljava/lang/Object;Ljava/lang/Object;)V
        99: aastore
       100: dup
       101: iconst_3
       102: new           #308                // class scala/Tuple2
       105: dup
       106: ldc_w         #335                // String value3
       109: aload_0
       110: invokevirtual #211                // Method value3:()Ljava/lang/Object;
       113: invokespecial #332                // Method scala/Tuple2."<init>":(Ljava/lang/Object;Ljava/lang/Object;)V
       116: aastore
       117: dup
       118: iconst_4
       119: new           #308                // class scala/Tuple2
       122: dup
       123: ldc_w         #336                // String value4
       126: aload_0
       127: invokevirtual #213                // Method value4:()Ljava/lang/Object;
       130: invokespecial #332                // Method scala/Tuple2."<init>":(Ljava/lang/Object;Ljava/lang/Object;)V
       133: aastore
       134: dup
       135: iconst_5
       136: new           #308                // class scala/Tuple2
       139: dup
       140: ldc_w         #337                // String value5
       143: aload_0
       144: invokevirtual #215                // Method value5:()Ljava/lang/Object;
       147: invokespecial #332                // Method scala/Tuple2."<init>":(Ljava/lang/Object;Ljava/lang/Object;)V
       150: aastore
       151: dup
       152: bipush        6
       154: new           #308                // class scala/Tuple2
       157: dup
       158: ldc_w         #338                // String value6
       161: aload_0
       162: invokevirtual #217                // Method value6:()Ljava/lang/Object;
       165: invokespecial #332                // Method scala/Tuple2."<init>":(Ljava/lang/Object;Ljava/lang/Object;)V
       168: aastore
       169: dup
       170: bipush        7
       172: new           #308                // class scala/Tuple2
       175: dup
       176: ldc_w         #339                // String value7
       179: aload_0
       180: invokevirtual #219                // Method value7:()Ljava/lang/Object;
       183: invokespecial #332                // Method scala/Tuple2."<init>":(Ljava/lang/Object;Ljava/lang/Object;)V
       186: aastore
       187: dup
       188: bipush        8
       190: new           #308                // class scala/Tuple2
       193: dup
       194: ldc_w         #340                // String value8
       197: aload_0
       198: invokevirtual #221                // Method value8:()Ljava/lang/Object;
       201: invokespecial #332                // Method scala/Tuple2."<init>":(Ljava/lang/Object;Ljava/lang/Object;)V
       204: aastore
       205: dup
       206: bipush        9
       208: new           #308                // class scala/Tuple2
       211: dup
       212: ldc_w         #341                // String value9
       215: aload_0
       216: invokevirtual #223                // Method value9:()Ljava/lang/Object;
       219: invokespecial #332                // Method scala/Tuple2."<init>":(Ljava/lang/Object;Ljava/lang/Object;)V
       222: aastore
       223: dup
       224: bipush        10
       226: new           #308                // class scala/Tuple2
       229: dup
       230: ldc_w         #342                // String value10
       233: aload_0
       234: invokevirtual #225                // Method value10:()Ljava/lang/Object;
       237: invokespecial #332                // Method scala/Tuple2."<init>":(Ljava/lang/Object;Ljava/lang/Object;)V
       240: aastore
       241: checkcast     #320                // class "[Ljava/lang/Object;"
       244: invokevirtual #324                // Method scala/runtime/ScalaRunTime$.wrapRefArray:([Ljava/lang/Object;)Lscala/collection/immutable/ArraySeq;
       247: invokevirtual #275                // Method scala/collection/immutable/Seq$.apply:(Lscala/collection/immutable/Seq;)Lscala/collection/SeqOps;
       250: checkcast     #344                // class scala/collection/immutable/Seq
       253: areturn
      LineNumberTable:
        line 47: 0
      LocalVariableTable:
        Start  Length  Slot  Name   Signature
            0     254     0  this   Lorg/sireum/MBox10;
    Signature: #306                         // ()Lscala/collection/immutable/Seq<Lscala/Tuple2<Ljava/lang/String;Ljava/lang/Object;>;>;

  public org.sireum.MBox10<T1, T2, T3, T4, T5, T6, T7, T8, T9, T10> $clone();
    descriptor: ()Lorg/sireum/MBox10;
    flags: (0x0001) ACC_PUBLIC
    Code:
      stack=13, locals=2, args_size=1
         0: new           #2                  // class org/sireum/MBox10
         3: dup
         4: getstatic     #352                // Field org/sireum/helper$.MODULE$:Lorg/sireum/helper$;
         7: aload_0
         8: invokevirtual #201                // Method value1:()Ljava/lang/Object;
        11: invokevirtual #356                // Method org/sireum/helper$.cloneAssign:(Ljava/lang/Object;)Ljava/lang/Object;
        14: getstatic     #352                // Field org/sireum/helper$.MODULE$:Lorg/sireum/helper$;
        17: aload_0
        18: invokevirtual #209                // Method value2:()Ljava/lang/Object;
        21: invokevirtual #356                // Method org/sireum/helper$.cloneAssign:(Ljava/lang/Object;)Ljava/lang/Object;
        24: getstatic     #352                // Field org/sireum/helper$.MODULE$:Lorg/sireum/helper$;
        27: aload_0
        28: invokevirtual #211                // Method value3:()Ljava/lang/Object;
        31: invokevirtual #356                // Method org/sireum/helper$.cloneAssign:(Ljava/lang/Object;)Ljava/lang/Object;
        34: getstatic     #352                // Field org/sireum/helper$.MODULE$:Lorg/sireum/helper$;
        37: aload_0
        38: invokevirtual #213                // Method value4:()Ljava/lang/Object;
        41: invokevirtual #356                // Method org/sireum/helper$.cloneAssign:(Ljava/lang/Object;)Ljava/lang/Object;
        44: getstatic     #352                // Field org/sireum/helper$.MODULE$:Lorg/sireum/helper$;
        47: aload_0
        48: invokevirtual #215                // Method value5:()Ljava/lang/Object;
        51: invokevirtual #356                // Method org/sireum/helper$.cloneAssign:(Ljava/lang/Object;)Ljava/lang/Object;
        54: getstatic     #352                // Field org/sireum/helper$.MODULE$:Lorg/sireum/helper$;
        57: aload_0
        58: invokevirtual #217                // Method value6:()Ljava/lang/Object;
        61: invokevirtual #356                // Method org/sireum/helper$.cloneAssign:(Ljava/lang/Object;)Ljava/lang/Object;
        64: getstatic     #352                // Field org/sireum/helper$.MODULE$:Lorg/sireum/helper$;
        67: aload_0
        68: invokevirtual #219                // Method value7:()Ljava/lang/Object;
        71: invokevirtual #356                // Method org/sireum/helper$.cloneAssign:(Ljava/lang/Object;)Ljava/lang/Object;
        74: getstatic     #352                // Field org/sireum/helper$.MODULE$:Lorg/sireum/helper$;
        77: aload_0
        78: invokevirtual #221                // Method value8:()Ljava/lang/Object;
        81: invokevirtual #356                // Method org/sireum/helper$.cloneAssign:(Ljava/lang/Object;)Ljava/lang/Object;
        84: getstatic     #352                // Field org/sireum/helper$.MODULE$:Lorg/sireum/helper$;
        87: aload_0
        88: invokevirtual #223                // Method value9:()Ljava/lang/Object;
        91: invokevirtual #356                // Method org/sireum/helper$.cloneAssign:(Ljava/lang/Object;)Ljava/lang/Object;
        94: getstatic     #352                // Field org/sireum/helper$.MODULE$:Lorg/sireum/helper$;
        97: aload_0
        98: invokevirtual #225                // Method value10:()Ljava/lang/Object;
       101: invokevirtual #356                // Method org/sireum/helper$.cloneAssign:(Ljava/lang/Object;)Ljava/lang/Object;
       104: invokespecial #293                // Method "<init>":(Ljava/lang/Object;Ljava/lang/Object;Ljava/lang/Object;Ljava/lang/Object;Ljava/lang/Object;Ljava/lang/Object;Ljava/lang/Object;Ljava/lang/Object;Ljava/lang/Object;Ljava/lang/Object;)V
       107: astore_1
       108: aload_1
       109: areturn
      LineNumberTable:
        line 47: 0
      LocalVariableTable:
        Start  Length  Slot  Name   Signature
          108       1     1     r   Lorg/sireum/MBox10;
            0     110     0  this   Lorg/sireum/MBox10;
    Signature: #347                         // ()Lorg/sireum/MBox10<TT1;TT2;TT3;TT4;TT5;TT6;TT7;TT8;TT9;TT10;>;

  public final org.sireum.$internal.MutableMarker $owned_$eq(boolean);
    descriptor: (Z)Lorg/sireum/$internal/MutableMarker;
    flags: (0x1051) ACC_PUBLIC, ACC_FINAL, ACC_BRIDGE, ACC_SYNTHETIC
    Code:
      stack=2, locals=2, args_size=2
         0: aload_0
         1: iload_1
         2: invokevirtual #360                // Method $owned_$eq:(Z)Lorg/sireum/RecordSig;
         5: areturn
      LineNumberTable:
        line 47: 0
      LocalVariableTable:
        Start  Length  Slot  Name   Signature
            0       6     0  this   Lorg/sireum/MBox10;
            0       6     1     b   Z
    MethodParameters:
      Name                           Flags
      b                              final

  public java.lang.Object $clone();
    descriptor: ()Ljava/lang/Object;
    flags: (0x1041) ACC_PUBLIC, ACC_BRIDGE, ACC_SYNTHETIC
    Code:
      stack=1, locals=1, args_size=1
         0: aload_0
         1: invokevirtual #362                // Method $clone:()Lorg/sireum/MBox10;
         4: areturn
      LineNumberTable:
        line 47: 0
      LocalVariableTable:
        Start  Length  Slot  Name   Signature
            0       5     0  this   Lorg/sireum/MBox10;

  public org.sireum.$internal.MutableMarker $clone();
    descriptor: ()Lorg/sireum/$internal/MutableMarker;
    flags: (0x1041) ACC_PUBLIC, ACC_BRIDGE, ACC_SYNTHETIC
    Code:
      stack=1, locals=1, args_size=1
         0: aload_0
         1: invokevirtual #362                // Method $clone:()Lorg/sireum/MBox10;
         4: areturn
      LineNumberTable:
        line 47: 0
      LocalVariableTable:
        Start  Length  Slot  Name   Signature
            0       5     0  this   Lorg/sireum/MBox10;

  public org.sireum.MBox10(T1, T2, T3, T4, T5, T6, T7, T8, T9, T10);
    descriptor: (Ljava/lang/Object;Ljava/lang/Object;Ljava/lang/Object;Ljava/lang/Object;Ljava/lang/Object;Ljava/lang/Object;Ljava/lang/Object;Ljava/lang/Object;Ljava/lang/Object;Ljava/lang/Object;)V
    flags: (0x0001) ACC_PUBLIC
    Code:
      stack=2, locals=11, args_size=11
         0: aload_0
         1: invokespecial #375                // Method java/lang/Object."<init>":()V
         4: aload_0
         5: invokestatic  #379                // InterfaceMethod org/sireum/Mutable.$init$:(Lorg/sireum/Mutable;)V
         8: aload_0
         9: invokestatic  #382                // InterfaceMethod org/sireum/RecordSig.$init$:(Lorg/sireum/RecordSig;)V
        12: aload_0
        13: aload_1
        14: putfield      #94                 // Field _value1:Ljava/lang/Object;
        17: aload_0
        18: aload_2
        19: putfield      #103                // Field _value2:Ljava/lang/Object;
        22: aload_0
        23: aload_3
        24: putfield      #111                // Field _value3:Ljava/lang/Object;
        27: aload_0
        28: aload         4
        30: putfield      #119                // Field _value4:Ljava/lang/Object;
        33: aload_0
        34: aload         5
        36: putfield      #127                // Field _value5:Ljava/lang/Object;
        39: aload_0
        40: aload         6
        42: putfield      #135                // Field _value6:Ljava/lang/Object;
        45: aload_0
        46: aload         7
        48: putfield      #143                // Field _value7:Ljava/lang/Object;
        51: aload_0
        52: aload         8
        54: putfield      #151                // Field _value8:Ljava/lang/Object;
        57: aload_0
        58: aload         9
        60: putfield      #159                // Field _value9:Ljava/lang/Object;
        63: aload_0
        64: aload         10
        66: putfield      #167                // Field _value10:Ljava/lang/Object;
        69: return
      LineNumberTable:
        line 47: 0
      LocalVariableTable:
        Start  Length  Slot  Name   Signature
            0      70     0  this   Lorg/sireum/MBox10;
            0      70     1 __value1   Ljava/lang/Object;
            0      70     2 __value2   Ljava/lang/Object;
            0      70     3 __value3   Ljava/lang/Object;
            0      70     4 __value4   Ljava/lang/Object;
            0      70     5 __value5   Ljava/lang/Object;
            0      70     6 __value6   Ljava/lang/Object;
            0      70     7 __value7   Ljava/lang/Object;
            0      70     8 __value8   Ljava/lang/Object;
            0      70     9 __value9   Ljava/lang/Object;
            0      70    10 __value10   Ljava/lang/Object;
    Signature: #364                         // (TT1;TT2;TT3;TT4;TT5;TT6;TT7;TT8;TT9;TT10;)V
    MethodParameters:
      Name                           Flags
      __value1                       final
      __value2                       final
      __value3                       final
      __value4                       final
      __value5                       final
      __value6                       final
      __value7                       final
      __value8                       final
      __value9                       final
      __value10                      final
}
Signature: #3                           // <T1:Ljava/lang/Object;T2:Ljava/lang/Object;T3:Ljava/lang/Object;T4:Ljava/lang/Object;T5:Ljava/lang/Object;T6:Ljava/lang/Object;T7:Ljava/lang/Object;T8:Ljava/lang/Object;T9:Ljava/lang/Object;T10:Ljava/lang/Object;>Ljava/lang/Object;Lorg/sireum/RecordSig;
SourceFile: "MBox.scala"
RuntimeVisibleAnnotations:
  0: #9(#10=s#11)
    scala.reflect.ScalaSignature(
      bytes="\u0006\u0005\r\u0005t!\u0002+V\u0011\u0003Qf!\u0002/V\u0011\u0003i\u0006\"\u00023\u0002\t\u0003)\u0007\"\u00024\u0002\t\u00039\u0007bBB\u0012\u0003\u0011\u00051Q\u0005\u0004\u00059V\u0013!\u000e\u0003\u0005p\u000b\t\u0005\t\u0015!\u0003q\u0011!YXA!A!\u0002\u0013a\b\"C@\u0006\u0005\u0003\u0005\u000b\u0011BA\u0001\u0011)\t9!\u0002B\u0001B\u0003%\u0011\u0011\u0002\u0005\u000b\u0003\u001f)!\u0011!Q\u0001\n\u0005E\u0001BCA\f\u000b\t\u0005\t\u0015!\u0003\u0002\u001a!Q\u0011qD\u0003\u0003\u0002\u0003\u0006I!!\t\t\u0015\u0005\u001dRA!A!\u0002\u0013\tI\u0003\u0003\u0006\u00020\u0015\u0011\t\u0011)A\u0005\u0003cA!\"a\u000e\u0006\u0005\u0003\u0005\u000b\u0011BA\u001d\u0011\u0019!W\u0001\"\u0001\u0002@!9\u0011qK\u0003!B\u0013\u0001\bbBA-\u000b\u0011\u0005\u00111\f\u0005\b\u0003;*A\u0011AA.\u0011\u001d\ty&\u0002C\u0001\u0003CBq!a\u001a\u0006\t\u0003\tI\u0007C\u0004\u0002n\u0015\u0001\u000b\u0015\u0002?\t\u000f\u0005=T\u0001\"\u0001\u0002r!9\u00111O\u0003\u0005\u0002\u0005E\u0004bBA;\u000b\u0011\u0005\u0011q\u000f\u0005\b\u0003w*A\u0011AA?\u0011!\t\t)\u0002Q!\n\u0005\u0005\u0001bBAB\u000b\u0011\u0005\u0011Q\u0011\u0005\b\u0003\u000f+A\u0011AAC\u0011\u001d\tI)\u0002C\u0001\u0003\u0017Cq!a$\u0006\t\u0003\t\t\n\u0003\u0005\u0002\u0016\u0016\u0001\u000b\u0015BA\u0005\u0011\u001d\t9*\u0002C\u0001\u00033Cq!a\'\u0006\t\u0003\tI\nC\u0004\u0002\u001e\u0016!\t!a(\t\u000f\u0005\rV\u0001\"\u0001\u0002&\"A\u0011\u0011V\u0003!B\u0013\t\t\u0002C\u0004\u0002,\u0016!\t!!,\t\u000f\u0005=V\u0001\"\u0001\u0002.\"9\u0011\u0011W\u0003\u0005\u0002\u0005M\u0006bBA\\\u000b\u0011\u0005\u0011\u0011\u0018\u0005\t\u0003{+\u0001\u0015)\u0003\u0002\u001a!9\u0011qX\u0003\u0005\u0002\u0005\u0005\u0007bBAb\u000b\u0011\u0005\u0011\u0011\u0019\u0005\b\u0003\u000b,A\u0011AAd\u0011\u001d\tY-\u0002C\u0001\u0003\u001bD\u0001\"!5\u0006A\u0003&\u0011\u0011\u0005\u0005\b\u0003\',A\u0011AAk\u0011\u001d\t9.\u0002C\u0001\u0003+Dq!!7\u0006\t\u0003\tY\u000eC\u0004\u0002`\u0016!\t!!9\t\u0011\u0005\u0015X\u0001)Q\u0005\u0003SAq!a:\u0006\t\u0003\tI\u000fC\u0004\u0002l\u0016!\t!!;\t\u000f\u00055X\u0001\"\u0001\u0002p\"9\u00111_\u0003\u0005\u0002\u0005U\b\u0002CA}\u000b\u0001\u0006K!!\r\t\u000f\u0005mX\u0001\"\u0001\u0002~\"9\u0011q`\u0003\u0005\u0002\u0005u\bb\u0002B\u0001\u000b\u0011\u0005!1\u0001\u0005\b\u0005\u000f)A\u0011\u0001B\u0005\u0011!\u0011i!\u0002Q!\n\u0005e\u0002b\u0002B\b\u000b\u0011\u0005!\u0011\u0003\u0005\b\u0005\')A\u0011\u0001B\t\u0011\u001d\u0011)\"\u0002C\u0001\u0005/AqAa\u0007\u0006\t\u0003\u0011i\u0002C\u0004\u0003\"\u0015!\tEa\t\t\u000f\tUR\u0001\"\u0011\u00038!9!QH\u0003\u0005B\t}\u0002b\u0002B$\u000b\u0011\u0005#\u0011\n\u0005\u0007M\u0016!\tA!\u0016\t\u0013\t-T!%A\u0005\u0002\t5\u0004\"\u0003BB\u000bE\u0005I\u0011\u0001BC\u0011%\u0011I)BI\u0001\n\u0003\u0011Y\tC\u0005\u0003\u0010\u0016\t\n\u0011\"\u0001\u0003\u0012\"I!QS\u0003\u0012\u0002\u0013\u0005!q\u0013\u0005\n\u00057+\u0011\u0013!C\u0001\u0005;C\u0011B!)\u0006#\u0003%\tAa)\t\u0013\t\u001dV!%A\u0005\u0002\t%\u0006\"\u0003BW\u000bE\u0005I\u0011\u0001BX\u0011%\u0011\u0019,BI\u0001\n\u0003\u0011)\fC\u0004\u0003:\u0016!\tEa/\t\u000f\tmW\u0001\"\u0011\u0003^\u00061QJQ8ycAR!AV,\u0002\rML\'/Z;n\u0015\u0005A\u0016aA8sO\u000e\u0001\u0001CA.\u0002\u001b\u0005)&AB\'C_b\f\u0004g\u0005\u0002\u0002=B\u0011qLY\u0007\u0002A*\t\u0011-A\u0003tG\u0006d\u0017-\u0003\u0002dA\n1\u0011I\\=SK\u001a\fa\u0001P5oSRtD#\u0001.\u0002\u000b\u0005\u0004\b\u000f\\=\u0016+!\u0014IO!<\u0003r\nU(\u0011 B\u007f\u0007\u0003\u0019)a!\u0003\u0004\u000eQ)\u0012na\u0004\u0004\u0012\rM1QCB\f\u00073\u0019Yb!\b\u0004 \r\u0005\u0002CF.\u0006\u0005O\u0014YOa<\u0003t\n](1 B\u0000\u0007\u0007\u00199aa\u0003\u0016\'-\u0014X0a\u0001\u0002\f\u0005M\u00111DA\u0012\u0003W\t\u0019$a\u000f\u0014\u0007\u0015qF\u000e\u0005\u0002\\[&\u0011a.\u0016\u0002\n%\u0016\u001cwN\u001d3TS\u001e\f\u0001bX0wC2,X-\r\t\u0003cJd\u0001\u0001B\u0003t\u000b\t\u0007AO\u0001\u0002UcE\u0011Q\u000f\u001f\t\u0003?ZL!a\u001e1\u0003\u000f9{G\u000f[5oOB\u0011q,_\u0005\u0003u\u0002\u00141!\u00118z\u0003!yvL^1mk\u0016\u0014\u0004CA9~\t\u0015qXA1\u0001u\u0005\t!&\'\u0001\u0005`?Z\fG.^34!\r\t\u00181\u0001\u0003\u0007\u0003\u000b)!\u0019\u0001;\u0003\u0005Q\u001b\u0014\u0001C0`m\u0006dW/\u001a\u001b\u0011\u0007E\fY\u0001\u0002\u0004\u0002\u000e\u0015\u0011\r\u0001\u001e\u0002\u0003)R\n\u0001bX0wC2,X-\u000e\t\u0004c\u0006MAABA\u000b\u000b\t\u0007AO\u0001\u0002Uk\u0005Aql\u0018<bYV,g\u0007E\u0002r\u00037!a!!\b\u0006\u0005\u0004!(A\u0001+7\u0003!yvL^1mk\u0016<\u0004cA9\u0002$\u00111\u0011QE\u0003C\u0002Q\u0014!\u0001V\u001c\u0002\u0011}{f/\u00197vKb\u00022!]A\u0016\t\u0019\ti#\u0002b\u0001i\n\u0011A\u000bO\u0001\t?~3\u0018\r\\;fsA\u0019\u0011/a\r\u0005\r\u0005URA1\u0001u\u0005\t!\u0016(A\u0005`?Z\fG.^32aA\u0019\u0011/a\u000f\u0005\r\u0005uRA1\u0001u\u0005\r!\u0016\u0007\r\u000b\u0017\u0003\u0003\n\u0019%!\u0012\u0002H\u0005%\u00131JA\'\u0003\u001f\n\t&a\u0015\u0002VA!2,\u00029}\u0003\u0003\tI!!\u0005\u0002\u001a\u0005\u0005\u0012\u0011FA\u0019\u0003sAQa\u001c\tA\u0002ADQa\u001f\tA\u0002qDaa \tA\u0002\u0005\u0005\u0001bBA\u0004!\u0001\u0007\u0011\u0011\u0002\u0005\b\u0003\u001f\u0001\u0002\u0019AA\t\u0011\u001d\t9\u0002\u0005a\u0001\u00033Aq!a\b\u0011\u0001\u0004\t\t\u0003C\u0004\u0002(A\u0001\r!!\u000b\t\u000f\u0005=\u0002\u00031\u0001\u00022!9\u0011q\u0007\tA\u0002\u0005e\u0012aB0wC2,X-M\u0001\u0007m\u0006dW/Z\u0019\u0016\u0003A\f\u0011bZ3u-\u0006dW/Z\u0019\u0002\u0015Y\fG.^32?\u0012*\u0017\u000f\u0006\u0003\u0002d\u0005\u0015T\"A\u0003\t\r\u0005eC\u00031\u0001q\u0003%\u0019X\r\u001e,bYV,\u0017\u0007\u0006\u0003\u0002d\u0005-\u0004BBA-+\u0001\u0007\u0001/A\u0004`m\u0006dW/\u001a\u001a\u0002\rY\fG.^33+\u0005a\u0018!C4fiZ\u000bG.^33\u0003)1\u0018\r\\;fe}#S-\u001d\u000b\u0005\u0003G\nI\b\u0003\u0004\u0002pe\u0001\r\u0001`\u0001\ng\u0016$h+\u00197vKJ\"B!a\u0019\u0002\u0000!1\u0011q\u000e\u000eA\u0002q\fqa\u0018<bYV,7\'\u0001\u0004wC2,XmM\u000b\u0003\u0003\u0003\t\u0011bZ3u-\u0006dW/Z\u001a\u0002\u0015Y\fG.^34?\u0012*\u0017\u000f\u0006\u0003\u0002d\u00055\u0005bBAB=\u0001\u0007\u0011\u0011A\u0001\ng\u0016$h+\u00197vKN\"B!a\u0019\u0002\u0014\"9\u00111Q\u0010A\u0002\u0005\u0005\u0011aB0wC2,X\rN\u0001\u0007m\u0006dW/\u001a\u001b\u0016\u0005\u0005%\u0011!C4fiZ\u000bG.^35\u0003)1\u0018\r\\;fi}#S-\u001d\u000b\u0005\u0003G\n\t\u000bC\u0004\u0002\u0018\u000e\u0002\r!!\u0003\u0002\u0013M,GOV1mk\u0016$D\u0003BA2\u0003OCq!a&%\u0001\u0004\tI!A\u0004`m\u0006dW/Z\u001b\u0002\rY\fG.^36+\t\t\t\"A\u0005hKR4\u0016\r\\;fk\u0005Qa/\u00197vKVzF%Z9\u0015\t\u0005\r\u0014Q\u0017\u0005\b\u0003WC\u0003\u0019AA\t\u0003%\u0019X\r\u001e,bYV,W\u0007\u0006\u0003\u0002d\u0005m\u0006bBAVS\u0001\u0007\u0011\u0011C\u0001\b?Z\fG.^37\u0003\u00191\u0018\r\\;fmU\u0011\u0011\u0011D\u0001\nO\u0016$h+\u00197vKZ\n!B^1mk\u00164t\fJ3r)\u0011\t\u0019\'!3\t\u000f\u0005}V\u00061\u0001\u0002\u001a\u0005I1/\u001a;WC2,XM\u000e\u000b\u0005\u0003G\ny\rC\u0004\u0002@:\u0002\r!!\u0007\u0002\u000f}3\u0018\r\\;fo\u00051a/\u00197vK^*\"!!\t\u0002\u0013\u001d,GOV1mk\u0016<\u0014A\u0003<bYV,wg\u0018\u0013fcR!\u00111MAo\u0011\u001d\t\u0019N\ra\u0001\u0003C\t\u0011b]3u-\u0006dW/Z\u001c\u0015\t\u0005\r\u00141\u001d\u0005\b\u0003\'\u001c\u0004\u0019AA\u0011\u0003\u001dyf/\u00197vKb\naA^1mk\u0016DTCAA\u0015\u0003%9W\r\u001e,bYV,\u0007(\u0001\u0006wC2,X\rO0%KF$B!a\u0019\u0002r\"9\u0011q]\u001cA\u0002\u0005%\u0012!C:fiZ\u000bG.^39)\u0011\t\u0019\'a>\t\u000f\u0005\u001d\b\b1\u0001\u0002*\u00059qL^1mk\u0016L\u0014A\u0002<bYV,\u0017(\u0006\u0002\u00022\u0005Iq-\u001a;WC2,X-O\u0001\u000bm\u0006dW/Z\u001d`I\u0015\fH\u0003BA2\u0005\u000bAq!a?=\u0001\u0004\t\t$A\u0005tKR4\u0016\r\\;fsQ!\u00111\rB\u0006\u0011\u001d\tY0\u0010a\u0001\u0003c\t\u0001b\u0018<bYV,\u0017\u0007M\u0001\bm\u0006dW/Z\u00191+\t\tI$\u0001\u0006hKR4\u0016\r\\;fcA\n1B^1mk\u0016\f\u0004g\u0018\u0013fcR!\u00111\rB\r\u0011\u001d\u0011y!\u0011a\u0001\u0003s\t!b]3u-\u0006dW/Z\u00191)\u0011\t\u0019Ga\b\t\u000f\t=!\t1\u0001\u0002:\u0005AAo\\*ue&tw\r\u0006\u0002\u0003&A!!q\u0005B\u0019\u001b\t\u0011IC\u0003\u0003\u0003,\t5\u0012\u0001\u00027b]\u001eT!Aa\f\u0002\t)\fg/Y\u0005\u0005\u0005g\u0011IC\u0001\u0004TiJLgnZ\u0001\u0007gR\u0014\u0018N\\4\u0016\u0005\te\u0002cA.\u0003<%\u0019!1G+\u0002\u0011!\f7\u000f[\"pI\u0016$\"A!\u0011\u0011\u0007}\u0013\u0019%C\u0002\u0003F\u0001\u00141!\u00138u\u0003\u0019)\u0017/^1mgR!!1\nB)!\ry&QJ\u0005\u0004\u0005\u001f\u0002\'a\u0002\"p_2,\u0017M\u001c\u0005\u0007\u0005\'2\u0005\u0019\u0001=\u0002\u0003=$b#!\u0011\u0003X\te#1\fB/\u0005?\u0012\tGa\u0019\u0003f\t\u001d$\u0011\u000e\u0005\t\u00033:\u0005\u0013!a\u0001a\"A\u0011qN$\u0011\u0002\u0003\u0007A\u0010C\u0005\u0002\u0004\u001e\u0003\n\u00111\u0001\u0002\u0002!I\u0011qS$\u0011\u0002\u0003\u0007\u0011\u0011\u0002\u0005\n\u0003W;\u0005\u0013!a\u0001\u0003#A\u0011\"a0H!\u0003\u0005\r!!\u0007\t\u0013\u0005Mw\t%AA\u0002\u0005\u0005\u0002\"CAt\u000fB\u0005\t\u0019AA\u0015\u0011%\tYp\u0012I\u0001\u0002\u0004\t\t\u0004C\u0005\u0003\u0010\u001d\u0003\n\u00111\u0001\u0002:\u0005y\u0011\r\u001d9ms\u0012\"WMZ1vYR$\u0013\'\u0006\u0002\u0003p)\u001a\u0001O!\u001d,\u0005\tM\u0004\u0003\u0002B;\u0005\u007fj!Aa\u001e\u000b\t\te$1P\u0001\nk:\u001c\u0007.Z2lK\u0012T1A! a\u0003)\tgN\\8uCRLwN\\\u0005\u0005\u0005\u0003\u00139HA\tv]\u000eDWmY6fIZ\u000b\'/[1oG\u0016\fq\"\u00199qYf$C-\u001a4bk2$HEM\u000b\u0003\u0005\u000fS3\u0001 B9\u0003=\t\u0007\u000f\u001d7zI\u0011,g-Y;mi\u0012\u001aTC\u0001BGU\u0011\t\tA!\u001d\u0002\u001f\u0005\u0004\b\u000f\\=%I\u00164\u0017-\u001e7uIQ*\"Aa%+\t\u0005%!\u0011O\u0001\u0010CB\u0004H.\u001f\u0013eK\u001a\fW\u000f\u001c;%kU\u0011!\u0011\u0014\u0016\u0005\u0003#\u0011\t(A\bbaBd\u0017\u0010\n3fM\u0006,H\u000e\u001e\u00137+\t\u0011yJ\u000b\u0003\u0002\u001a\tE\u0014aD1qa2LH\u0005Z3gCVdG\u000fJ\u001c\u0016\u0005\t\u0015&\u0006BA\u0011\u0005c\nq\"\u00199qYf$C-\u001a4bk2$H\u0005O\u000b\u0003\u0005WSC!!\u000b\u0003r\u0005y\u0011\r\u001d9ms\u0012\"WMZ1vYR$\u0013(\u0006\u0002\u00032*\"\u0011\u0011\u0007B9\u0003A\t\u0007\u000f\u001d7zI\u0011,g-Y;mi\u0012\n\u0004\'\u0006\u0002\u00038*\"\u0011\u0011\bB9\u0003!!3m\u001c8uK:$XC\u0001B_!\u0019\u0011yLa4\u0003V:!!\u0011\u0019Bf\u001d\u0011\u0011\u0019M!3\u000e\u0005\t\u0015\'b\u0001Bd3\u00061AH]8pizJ\u0011!Y\u0005\u0004\u0005\u001b\u0004\u0017a\u00029bG.\fw-Z\u0005\u0005\u0005#\u0014\u0019NA\u0002TKFT1A!4a!\u0019y&q\u001bB\u0013q&\u0019!\u0011\u001c1\u0003\rQ+\b\u000f\\33\u0003\u0019!3\r\\8oKV\u0011\u0011\u0011\t\u0015\u0004\u000b\t\u0005\bcA.\u0003d&\u0019!Q]+\u0003\rI,7m\u001c:e!\r\t(\u0011\u001e\u0003\u0006g\u000e\u0011\r\u0001\u001e\t\u0004c\n5H!\u0002@\u0004\u0005\u0004!\bcA9\u0003r\u00121\u0011QA\u0002C\u0002Q\u00042!\u001dB{\t\u0019\tia\u0001b\u0001iB\u0019\u0011O!?\u0005\r\u0005U1A1\u0001u!\r\t(Q \u0003\u0007\u0003;\u0019!\u0019\u0001;\u0011\u0007E\u001c\t\u0001\u0002\u0004\u0002&\r\u0011\r\u0001\u001e\t\u0004c\u000e\u0015AABA\u0017\u0007\t\u0007A\u000fE\u0002r\u0007\u0013!a!!\u000e\u0004\u0005\u0004!\bcA9\u0004\u000e\u00111\u0011QH\u0002C\u0002QDq!!\u0017\u0004\u0001\u0004\u00119\u000fC\u0004\u0002p\r\u0001\rAa;\t\u000f\u0005\r5\u00011\u0001\u0003p\"9\u0011qS\u0002A\u0002\tM\bbBAV\u0007\u0001\u0007!q\u001f\u0005\b\u0003\u007f\u001b\u0001\u0019\u0001B~\u0011\u001d\t\u0019n\u0001a\u0001\u0005\u007fDq!a:\u0004\u0001\u0004\u0019\u0019\u0001C\u0004\u0002|\u000e\u0001\raa\u0002\t\u000f\t=1\u00011\u0001\u0004\f\u00059QO\\1qa2LXCFB\u0014\u0007o\u0019Yda\u0010\u0004D\r\u001d31JB(\u0007\'\u001a9fa\u0017\u0015\t\r%2Q\f\t\u0006?\u000e-2qF\u0005\u0004\u0007[\u0001\'\u0001B*p[\u0016\u0004rcXB\u0019\u0007k\u0019Id!\u0010\u0004B\r\u00153\u0011JB\'\u0007#\u001a)f!\u0017\n\u0007\rM\u0002MA\u0004UkBdW-\r\u0019\u0011\u0007E\u001c9\u0004B\u0003t\t\t\u0007A\u000fE\u0002r\u0007w!QA \u0003C\u0002Q\u00042!]B \t\u0019\t)\u0001\u0002b\u0001iB\u0019\u0011oa\u0011\u0005\r\u00055AA1\u0001u!\r\t8q\t\u0003\u0007\u0003+!!\u0019\u0001;\u0011\u0007E\u001cY\u0005\u0002\u0004\u0002\u001e\u0011\u0011\r\u0001\u001e\t\u0004c\u000e=CABA\u0013\t\t\u0007A\u000fE\u0002r\u0007\'\"a!!\f\u0005\u0005\u0004!\bcA9\u0004X\u00111\u0011Q\u0007\u0003C\u0002Q\u00042!]B.\t\u0019\ti\u0004\u0002b\u0001i\"9!1\u000b\u0003A\u0002\r}\u0003CF.\u0006\u0007k\u0019Id!\u0010\u0004B\r\u00153\u0011JB\'\u0007#\u001a)f!\u0017"
    )
  ScalaInlineInfo: length = 0x15D (unknown attribute)
   01 01 00 45 00 44 00 45 01 01 59 00 5B 01 01 59
   01 6B 01 01 59 01 5A 01 01 30 01 31 01 00 4C 00
   31 01 00 51 00 31 01 00 30 00 31 01 00 37 01 66
   01 00 37 00 38 01 00 B6 01 23 01 00 EA 01 21 01
   01 26 00 5B 01 01 2F 00 5B 01 01 27 00 5B 01 01
   28 00 5B 01 01 29 00 5B 01 01 2A 00 5B 01 01 2B
   00 5B 01 01 2C 00 5B 01 01 2D 00 5B 01 01 2E 00
   5B 01 01 17 01 18 01 00 5F 00 5B 01 00 A8 00 5B
   01 00 68 00 5B 01 00 70 00 5B 01 00 78 00 5B 01
   00 80 00 5B 01 00 88 00 5B 01 00 90 00 5B 01 00
   98 00 5B 01 00 A0 00 5B 01 00 3E 00 3F 01 00 EE
   00 EF 01 00 21 00 31 01 00 57 00 58 01 00 63 00
   61 01 00 AB 00 61 01 00 6B 00 61 01 00 73 00 61
   01 00 7B 00 61 01 00 83 00 61 01 00 8B 00 61 01
   00 93 00 61 01 00 9B 00 61 01 00 A3 00 61 01 00
   E8 00 AD 01 00 AC 00 AD 01 00 5A 00 5B 01 00 A4
   00 5B 01 00 A9 00 61 01 00 60 00 61 01 00 64 00
   5B 01 00 69 00 61 01 00 6C 00 5B 01 00 71 00 61
   01 00 74 00 5B 01 00 79 00 61 01 00 7C 00 5B 01
   00 81 00 61 01 00 84 00 5B 01 00 89 00 61 01 00
   8C 00 5B 01 00 91 00 61 01 00 94 00 5B 01 00 99
   00 61 01 00 9C 00 5B 01 00 A1 00 61 01
  ScalaSig: length = 0x3 (unknown attribute)
   05 02 00
