Classfile /Users/mw/Projects/slang-braindump/.jar/jar11/assemble/slang-braindump/assemble/content/org/sireum/MessagePack$Kind$EXTENSION$.class
  Last modified May 29, 2022; size 5439 bytes
  SHA-256 checksum 4e156b7cccc800d219e7773a51b1d9234e0b1c05ddf1b6208862c3413828a4b7
  Compiled from "MessagePack.scala"
public final class org.sireum.MessagePack$Kind$EXTENSION$ implements org.sireum.MessagePack$Kind$Type,scala.Product,java.io.Serializable
  minor version: 0
  major version: 52
  flags: (0x0031) ACC_PUBLIC, ACC_FINAL, ACC_SUPER
  this_class: #2                          // org/sireum/MessagePack$Kind$EXTENSION$
  super_class: #4                         // java/lang/Object
  interfaces: 3, fields: 1, methods: 29, attributes: 4
Constant pool:
    #1 = Utf8               org/sireum/MessagePack$Kind$EXTENSION$
    #2 = Class              #1            // org/sireum/MessagePack$Kind$EXTENSION$
    #3 = Utf8               java/lang/Object
    #4 = Class              #3            // java/lang/Object
    #5 = Utf8               org/sireum/MessagePack$Kind$Type
    #6 = Class              #5            // org/sireum/MessagePack$Kind$Type
    #7 = Utf8               scala/Product
    #8 = Class              #7            // scala/Product
    #9 = Utf8               java/io/Serializable
   #10 = Class              #9            // java/io/Serializable
   #11 = Utf8               MessagePack.scala
   #12 = Utf8               org/sireum/MessagePack$Kind$
   #13 = Class              #12           // org/sireum/MessagePack$Kind$
   #14 = Utf8               org/sireum/MessagePack
   #15 = Class              #14           // org/sireum/MessagePack
   #16 = Utf8               Kind$
   #17 = Utf8               EXTENSION$
   #18 = Utf8               Type
   #19 = Utf8               MODULE$
   #20 = Utf8               Lorg/sireum/MessagePack$Kind$EXTENSION$;
   #21 = Utf8               <clinit>
   #22 = Utf8               ()V
   #23 = Utf8               <init>
   #24 = NameAndType        #23:#22       // "<init>":()V
   #25 = Methodref          #2.#24        // org/sireum/MessagePack$Kind$EXTENSION$."<init>":()V
   #26 = NameAndType        #19:#20       // MODULE$:Lorg/sireum/MessagePack$Kind$EXTENSION$;
   #27 = Fieldref           #2.#26        // org/sireum/MessagePack$Kind$EXTENSION$.MODULE$:Lorg/sireum/MessagePack$Kind$EXTENSION$;
   #28 = Utf8               org/sireum/$internal/ImmutableMarker
   #29 = Class              #28           // org/sireum/$internal/ImmutableMarker
   #30 = Utf8               $init$
   #31 = Utf8               (Lorg/sireum/$internal/ImmutableMarker;)V
   #32 = NameAndType        #30:#31       // $init$:(Lorg/sireum/$internal/ImmutableMarker;)V
   #33 = InterfaceMethodref #29.#32       // org/sireum/$internal/ImmutableMarker.$init$:(Lorg/sireum/$internal/ImmutableMarker;)V
   #34 = Utf8               org/sireum/Immutable
   #35 = Class              #34           // org/sireum/Immutable
   #36 = Utf8               (Lorg/sireum/Immutable;)V
   #37 = NameAndType        #30:#36       // $init$:(Lorg/sireum/Immutable;)V
   #38 = InterfaceMethodref #35.#37       // org/sireum/Immutable.$init$:(Lorg/sireum/Immutable;)V
   #39 = Utf8               scala/math/Ordered
   #40 = Class              #39           // scala/math/Ordered
   #41 = Utf8               (Lscala/math/Ordered;)V
   #42 = NameAndType        #30:#41       // $init$:(Lscala/math/Ordered;)V
   #43 = InterfaceMethodref #40.#42       // scala/math/Ordered.$init$:(Lscala/math/Ordered;)V
   #44 = Utf8               (Lorg/sireum/MessagePack$Kind$Type;)V
   #45 = NameAndType        #30:#44       // $init$:(Lorg/sireum/MessagePack$Kind$Type;)V
   #46 = InterfaceMethodref #6.#45        // org/sireum/MessagePack$Kind$Type.$init$:(Lorg/sireum/MessagePack$Kind$Type;)V
   #47 = Utf8               (Lscala/Product;)V
   #48 = NameAndType        #30:#47       // $init$:(Lscala/Product;)V
   #49 = InterfaceMethodref #8.#48        // scala/Product.$init$:(Lscala/Product;)V
   #50 = Utf8               productElementName
   #51 = Utf8               (I)Ljava/lang/String;
   #52 = Utf8               n
   #53 = Utf8               productElementName$
   #54 = Utf8               (Lscala/Product;I)Ljava/lang/String;
   #55 = NameAndType        #53:#54       // productElementName$:(Lscala/Product;I)Ljava/lang/String;
   #56 = InterfaceMethodref #8.#55        // scala/Product.productElementName$:(Lscala/Product;I)Ljava/lang/String;
   #57 = Utf8               this
   #58 = Utf8               I
   #59 = Utf8               productElementNames
   #60 = Utf8               ()Lscala/collection/Iterator;
   #61 = Utf8               ()Lscala/collection/Iterator<Ljava/lang/String;>;
   #62 = Utf8               productElementNames$
   #63 = Utf8               (Lscala/Product;)Lscala/collection/Iterator;
   #64 = NameAndType        #62:#63       // productElementNames$:(Lscala/Product;)Lscala/collection/Iterator;
   #65 = InterfaceMethodref #8.#64        // scala/Product.productElementNames$:(Lscala/Product;)Lscala/collection/Iterator;
   #66 = Utf8               hash
   #67 = Utf8               ()Lorg/sireum/Z;
   #68 = Utf8               hash$
   #69 = Utf8               (Lorg/sireum/MessagePack$Kind$Type;)Lorg/sireum/Z;
   #70 = NameAndType        #68:#69       // hash$:(Lorg/sireum/MessagePack$Kind$Type;)Lorg/sireum/Z;
   #71 = InterfaceMethodref #6.#70        // org/sireum/MessagePack$Kind$Type.hash$:(Lorg/sireum/MessagePack$Kind$Type;)Lorg/sireum/Z;
   #72 = Utf8               isEqual
   #73 = Utf8               (Lorg/sireum/MessagePack$Kind$Type;)Z
   #74 = Utf8               other
   #75 = Utf8               isEqual$
   #76 = Utf8               (Lorg/sireum/MessagePack$Kind$Type;Lorg/sireum/MessagePack$Kind$Type;)Z
   #77 = NameAndType        #75:#76       // isEqual$:(Lorg/sireum/MessagePack$Kind$Type;Lorg/sireum/MessagePack$Kind$Type;)Z
   #78 = InterfaceMethodref #6.#77        // org/sireum/MessagePack$Kind$Type.isEqual$:(Lorg/sireum/MessagePack$Kind$Type;Lorg/sireum/MessagePack$Kind$Type;)Z
   #79 = Utf8               Lorg/sireum/MessagePack$Kind$Type;
   #80 = Utf8               compare
   #81 = Utf8               (Lorg/sireum/MessagePack$Kind$Type;)I
   #82 = Utf8               that
   #83 = Utf8               compare$
   #84 = Utf8               (Lorg/sireum/MessagePack$Kind$Type;Lorg/sireum/MessagePack$Kind$Type;)I
   #85 = NameAndType        #83:#84       // compare$:(Lorg/sireum/MessagePack$Kind$Type;Lorg/sireum/MessagePack$Kind$Type;)I
   #86 = InterfaceMethodref #6.#85        // org/sireum/MessagePack$Kind$Type.compare$:(Lorg/sireum/MessagePack$Kind$Type;Lorg/sireum/MessagePack$Kind$Type;)I
   #87 = Utf8               string
   #88 = Utf8               ()Ljava/lang/String;
   #89 = Utf8               string$
   #90 = Utf8               (Lorg/sireum/MessagePack$Kind$Type;)Ljava/lang/String;
   #91 = NameAndType        #89:#90       // string$:(Lorg/sireum/MessagePack$Kind$Type;)Ljava/lang/String;
   #92 = InterfaceMethodref #6.#91        // org/sireum/MessagePack$Kind$Type.string$:(Lorg/sireum/MessagePack$Kind$Type;)Ljava/lang/String;
   #93 = Utf8               $less
   #94 = Utf8               (Ljava/lang/Object;)Z
   #95 = Utf8               $less$
   #96 = Utf8               (Lscala/math/Ordered;Ljava/lang/Object;)Z
   #97 = NameAndType        #95:#96       // $less$:(Lscala/math/Ordered;Ljava/lang/Object;)Z
   #98 = InterfaceMethodref #40.#97       // scala/math/Ordered.$less$:(Lscala/math/Ordered;Ljava/lang/Object;)Z
   #99 = Utf8               Ljava/lang/Object;
  #100 = Utf8               $greater
  #101 = Utf8               $greater$
  #102 = NameAndType        #101:#96      // $greater$:(Lscala/math/Ordered;Ljava/lang/Object;)Z
  #103 = InterfaceMethodref #40.#102      // scala/math/Ordered.$greater$:(Lscala/math/Ordered;Ljava/lang/Object;)Z
  #104 = Utf8               $less$eq
  #105 = Utf8               $less$eq$
  #106 = NameAndType        #105:#96      // $less$eq$:(Lscala/math/Ordered;Ljava/lang/Object;)Z
  #107 = InterfaceMethodref #40.#106      // scala/math/Ordered.$less$eq$:(Lscala/math/Ordered;Ljava/lang/Object;)Z
  #108 = Utf8               $greater$eq
  #109 = Utf8               $greater$eq$
  #110 = NameAndType        #109:#96      // $greater$eq$:(Lscala/math/Ordered;Ljava/lang/Object;)Z
  #111 = InterfaceMethodref #40.#110      // scala/math/Ordered.$greater$eq$:(Lscala/math/Ordered;Ljava/lang/Object;)Z
  #112 = Utf8               compareTo
  #113 = Utf8               (Ljava/lang/Object;)I
  #114 = Utf8               compareTo$
  #115 = Utf8               (Lscala/math/Ordered;Ljava/lang/Object;)I
  #116 = NameAndType        #114:#115     // compareTo$:(Lscala/math/Ordered;Ljava/lang/Object;)I
  #117 = InterfaceMethodref #40.#116      // scala/math/Ordered.compareTo$:(Lscala/math/Ordered;Ljava/lang/Object;)I
  #118 = Utf8               $cannotMixImmutableAndMutable
  #119 = Utf8               ()Lscala/runtime/Nothing$;
  #120 = Utf8               $cannotMixImmutableAndMutable$
  #121 = Utf8               (Lorg/sireum/Immutable;)Lscala/runtime/Nothing$;
  #122 = NameAndType        #120:#121     // $cannotMixImmutableAndMutable$:(Lorg/sireum/Immutable;)Lscala/runtime/Nothing$;
  #123 = InterfaceMethodref #35.#122      // org/sireum/Immutable.$cannotMixImmutableAndMutable$:(Lorg/sireum/Immutable;)Lscala/runtime/Nothing$;
  #124 = Utf8               $hasEquals
  #125 = Utf8               ()Z
  #126 = Utf8               $hasEquals$
  #127 = Utf8               (Lorg/sireum/Immutable;)Z
  #128 = NameAndType        #126:#127     // $hasEquals$:(Lorg/sireum/Immutable;)Z
  #129 = InterfaceMethodref #35.#128      // org/sireum/Immutable.$hasEquals$:(Lorg/sireum/Immutable;)Z
  #130 = Utf8               $hasString
  #131 = Utf8               $hasString$
  #132 = NameAndType        #131:#127     // $hasString$:(Lorg/sireum/Immutable;)Z
  #133 = InterfaceMethodref #35.#132      // org/sireum/Immutable.$hasString$:(Lorg/sireum/Immutable;)Z
  #134 = Utf8               $clone
  #135 = Utf8               ()Lorg/sireum/$internal/ImmutableMarker;
  #136 = Utf8               $clone$
  #137 = Utf8               (Lorg/sireum/$internal/ImmutableMarker;)Lorg/sireum/$internal/ImmutableMarker;
  #138 = NameAndType        #136:#137     // $clone$:(Lorg/sireum/$internal/ImmutableMarker;)Lorg/sireum/$internal/ImmutableMarker;
  #139 = InterfaceMethodref #29.#138      // org/sireum/$internal/ImmutableMarker.$clone$:(Lorg/sireum/$internal/ImmutableMarker;)Lorg/sireum/$internal/ImmutableMarker;
  #140 = Utf8               ordinal
  #141 = Utf8               org/sireum/Z$
  #142 = Class              #141          // org/sireum/Z$
  #143 = Utf8               Lorg/sireum/Z$;
  #144 = NameAndType        #19:#143      // MODULE$:Lorg/sireum/Z$;
  #145 = Fieldref           #142.#144     // org/sireum/Z$.MODULE$:Lorg/sireum/Z$;
  #146 = Utf8               apply
  #147 = Utf8               (I)Lorg/sireum/Z;
  #148 = NameAndType        #146:#147     // apply:(I)Lorg/sireum/Z;
  #149 = Methodref          #142.#148     // org/sireum/Z$.apply:(I)Lorg/sireum/Z;
  #150 = Utf8               name
  #151 = Utf8               org/sireum/String$
  #152 = Class              #151          // org/sireum/String$
  #153 = Utf8               Lorg/sireum/String$;
  #154 = NameAndType        #19:#153      // MODULE$:Lorg/sireum/String$;
  #155 = Fieldref           #152.#154     // org/sireum/String$.MODULE$:Lorg/sireum/String$;
  #156 = Utf8               EXTENSION
  #157 = String             #156          // EXTENSION
  #158 = Utf8               (Ljava/lang/String;)Ljava/lang/String;
  #159 = NameAndType        #146:#158     // apply:(Ljava/lang/String;)Ljava/lang/String;
  #160 = Methodref          #152.#159     // org/sireum/String$.apply:(Ljava/lang/String;)Ljava/lang/String;
  #161 = Utf8               productPrefix
  #162 = Utf8               productArity
  #163 = Utf8               ()I
  #164 = Utf8               productElement
  #165 = Utf8               (I)Ljava/lang/Object;
  #166 = Utf8               x$1
  #167 = Utf8               scala/runtime/Statics
  #168 = Class              #167          // scala/runtime/Statics
  #169 = Utf8               ioobe
  #170 = NameAndType        #169:#165     // ioobe:(I)Ljava/lang/Object;
  #171 = Methodref          #168.#170     // scala/runtime/Statics.ioobe:(I)Ljava/lang/Object;
  #172 = Utf8               productIterator
  #173 = Utf8               ()Lscala/collection/Iterator<Ljava/lang/Object;>;
  #174 = Utf8               scala/runtime/ScalaRunTime$
  #175 = Class              #174          // scala/runtime/ScalaRunTime$
  #176 = Utf8               Lscala/runtime/ScalaRunTime$;
  #177 = NameAndType        #19:#176      // MODULE$:Lscala/runtime/ScalaRunTime$;
  #178 = Fieldref           #175.#177     // scala/runtime/ScalaRunTime$.MODULE$:Lscala/runtime/ScalaRunTime$;
  #179 = Utf8               typedProductIterator
  #180 = NameAndType        #179:#63      // typedProductIterator:(Lscala/Product;)Lscala/collection/Iterator;
  #181 = Methodref          #175.#180     // scala/runtime/ScalaRunTime$.typedProductIterator:(Lscala/Product;)Lscala/collection/Iterator;
  #182 = Utf8               canEqual
  #183 = Utf8               hashCode
  #184 = Integer            -2120930273
  #185 = Utf8               toString
  #186 = Utf8               writeReplace
  #187 = Utf8               ()Ljava/lang/Object;
  #188 = Utf8               scala/runtime/ModuleSerializationProxy
  #189 = Class              #188          // scala/runtime/ModuleSerializationProxy
  #190 = Utf8               (Ljava/lang/Class;)V
  #191 = NameAndType        #23:#190      // "<init>":(Ljava/lang/Class;)V
  #192 = Methodref          #189.#191     // scala/runtime/ModuleSerializationProxy."<init>":(Ljava/lang/Class;)V
  #193 = NameAndType        #134:#135     // $clone:()Lorg/sireum/$internal/ImmutableMarker;
  #194 = Methodref          #2.#193       // org/sireum/MessagePack$Kind$EXTENSION$.$clone:()Lorg/sireum/$internal/ImmutableMarker;
  #195 = NameAndType        #80:#81       // compare:(Lorg/sireum/MessagePack$Kind$Type;)I
  #196 = Methodref          #2.#195       // org/sireum/MessagePack$Kind$EXTENSION$.compare:(Lorg/sireum/MessagePack$Kind$Type;)I
  #197 = Methodref          #4.#24        // java/lang/Object."<init>":()V
  #198 = Utf8               Code
  #199 = Utf8               LineNumberTable
  #200 = Utf8               LocalVariableTable
  #201 = Utf8               MethodParameters
  #202 = Utf8               Signature
  #203 = Utf8               StackMapTable
  #204 = Utf8               InnerClasses
  #205 = Utf8               SourceFile
  #206 = Utf8               ScalaInlineInfo
  #207 = Utf8               Scala
{
  public static final org.sireum.MessagePack$Kind$EXTENSION$ MODULE$;
    descriptor: Lorg/sireum/MessagePack$Kind$EXTENSION$;
    flags: (0x0019) ACC_PUBLIC, ACC_STATIC, ACC_FINAL

  public static {};
    descriptor: ()V
    flags: (0x0009) ACC_PUBLIC, ACC_STATIC
    Code:
      stack=2, locals=0, args_size=0
         0: new           #2                  // class org/sireum/MessagePack$Kind$EXTENSION$
         3: dup
         4: invokespecial #25                 // Method "<init>":()V
         7: putstatic     #27                 // Field MODULE$:Lorg/sireum/MessagePack$Kind$EXTENSION$;
        10: getstatic     #27                 // Field MODULE$:Lorg/sireum/MessagePack$Kind$EXTENSION$;
        13: invokestatic  #33                 // InterfaceMethod org/sireum/$internal/ImmutableMarker.$init$:(Lorg/sireum/$internal/ImmutableMarker;)V
        16: getstatic     #27                 // Field MODULE$:Lorg/sireum/MessagePack$Kind$EXTENSION$;
        19: invokestatic  #38                 // InterfaceMethod org/sireum/Immutable.$init$:(Lorg/sireum/Immutable;)V
        22: getstatic     #27                 // Field MODULE$:Lorg/sireum/MessagePack$Kind$EXTENSION$;
        25: invokestatic  #43                 // InterfaceMethod scala/math/Ordered.$init$:(Lscala/math/Ordered;)V
        28: getstatic     #27                 // Field MODULE$:Lorg/sireum/MessagePack$Kind$EXTENSION$;
        31: invokestatic  #46                 // InterfaceMethod org/sireum/MessagePack$Kind$Type.$init$:(Lorg/sireum/MessagePack$Kind$Type;)V
        34: getstatic     #27                 // Field MODULE$:Lorg/sireum/MessagePack$Kind$EXTENSION$;
        37: invokestatic  #49                 // InterfaceMethod scala/Product.$init$:(Lscala/Product;)V
        40: return
      LineNumberTable:
        line 39: 0

  public java.lang.String productElementName(int);
    descriptor: (I)Ljava/lang/String;
    flags: (0x0001) ACC_PUBLIC
    Code:
      stack=2, locals=2, args_size=2
         0: aload_0
         1: iload_1
         2: invokestatic  #56                 // InterfaceMethod scala/Product.productElementName$:(Lscala/Product;I)Ljava/lang/String;
         5: areturn
      LineNumberTable:
        line 39: 0
      LocalVariableTable:
        Start  Length  Slot  Name   Signature
            0       6     0  this   Lorg/sireum/MessagePack$Kind$EXTENSION$;
            0       6     1     n   I
    MethodParameters:
      Name                           Flags
      n                              final

  public scala.collection.Iterator<java.lang.String> productElementNames();
    descriptor: ()Lscala/collection/Iterator;
    flags: (0x0001) ACC_PUBLIC
    Code:
      stack=1, locals=1, args_size=1
         0: aload_0
         1: invokestatic  #65                 // InterfaceMethod scala/Product.productElementNames$:(Lscala/Product;)Lscala/collection/Iterator;
         4: areturn
      LineNumberTable:
        line 39: 0
      LocalVariableTable:
        Start  Length  Slot  Name   Signature
            0       5     0  this   Lorg/sireum/MessagePack$Kind$EXTENSION$;
    Signature: #61                          // ()Lscala/collection/Iterator<Ljava/lang/String;>;

  public final org.sireum.Z hash();
    descriptor: ()Lorg/sireum/Z;
    flags: (0x0011) ACC_PUBLIC, ACC_FINAL
    Code:
      stack=1, locals=1, args_size=1
         0: aload_0
         1: invokestatic  #71                 // InterfaceMethod org/sireum/MessagePack$Kind$Type.hash$:(Lorg/sireum/MessagePack$Kind$Type;)Lorg/sireum/Z;
         4: areturn
      LineNumberTable:
        line 39: 0
      LocalVariableTable:
        Start  Length  Slot  Name   Signature
            0       5     0  this   Lorg/sireum/MessagePack$Kind$EXTENSION$;

  public final boolean isEqual(org.sireum.MessagePack$Kind$Type);
    descriptor: (Lorg/sireum/MessagePack$Kind$Type;)Z
    flags: (0x0011) ACC_PUBLIC, ACC_FINAL
    Code:
      stack=2, locals=2, args_size=2
         0: aload_0
         1: aload_1
         2: invokestatic  #78                 // InterfaceMethod org/sireum/MessagePack$Kind$Type.isEqual$:(Lorg/sireum/MessagePack$Kind$Type;Lorg/sireum/MessagePack$Kind$Type;)Z
         5: ireturn
      LineNumberTable:
        line 39: 0
      LocalVariableTable:
        Start  Length  Slot  Name   Signature
            0       6     0  this   Lorg/sireum/MessagePack$Kind$EXTENSION$;
            0       6     1 other   Lorg/sireum/MessagePack$Kind$Type;
    MethodParameters:
      Name                           Flags
      other                          final

  public final int compare(org.sireum.MessagePack$Kind$Type);
    descriptor: (Lorg/sireum/MessagePack$Kind$Type;)I
    flags: (0x0011) ACC_PUBLIC, ACC_FINAL
    Code:
      stack=2, locals=2, args_size=2
         0: aload_0
         1: aload_1
         2: invokestatic  #86                 // InterfaceMethod org/sireum/MessagePack$Kind$Type.compare$:(Lorg/sireum/MessagePack$Kind$Type;Lorg/sireum/MessagePack$Kind$Type;)I
         5: ireturn
      LineNumberTable:
        line 39: 0
      LocalVariableTable:
        Start  Length  Slot  Name   Signature
            0       6     0  this   Lorg/sireum/MessagePack$Kind$EXTENSION$;
            0       6     1  that   Lorg/sireum/MessagePack$Kind$Type;
    MethodParameters:
      Name                           Flags
      that                           final

  public final java.lang.String string();
    descriptor: ()Ljava/lang/String;
    flags: (0x0011) ACC_PUBLIC, ACC_FINAL
    Code:
      stack=1, locals=1, args_size=1
         0: aload_0
         1: invokestatic  #92                 // InterfaceMethod org/sireum/MessagePack$Kind$Type.string$:(Lorg/sireum/MessagePack$Kind$Type;)Ljava/lang/String;
         4: areturn
      LineNumberTable:
        line 39: 0
      LocalVariableTable:
        Start  Length  Slot  Name   Signature
            0       5     0  this   Lorg/sireum/MessagePack$Kind$EXTENSION$;

  public boolean $less(java.lang.Object);
    descriptor: (Ljava/lang/Object;)Z
    flags: (0x0001) ACC_PUBLIC
    Code:
      stack=2, locals=2, args_size=2
         0: aload_0
         1: aload_1
         2: invokestatic  #98                 // InterfaceMethod scala/math/Ordered.$less$:(Lscala/math/Ordered;Ljava/lang/Object;)Z
         5: ireturn
      LineNumberTable:
        line 39: 0
      LocalVariableTable:
        Start  Length  Slot  Name   Signature
            0       6     0  this   Lorg/sireum/MessagePack$Kind$EXTENSION$;
            0       6     1  that   Ljava/lang/Object;
    MethodParameters:
      Name                           Flags
      that                           final

  public boolean $greater(java.lang.Object);
    descriptor: (Ljava/lang/Object;)Z
    flags: (0x0001) ACC_PUBLIC
    Code:
      stack=2, locals=2, args_size=2
         0: aload_0
         1: aload_1
         2: invokestatic  #103                // InterfaceMethod scala/math/Ordered.$greater$:(Lscala/math/Ordered;Ljava/lang/Object;)Z
         5: ireturn
      LineNumberTable:
        line 39: 0
      LocalVariableTable:
        Start  Length  Slot  Name   Signature
            0       6     0  this   Lorg/sireum/MessagePack$Kind$EXTENSION$;
            0       6     1  that   Ljava/lang/Object;
    MethodParameters:
      Name                           Flags
      that                           final

  public boolean $less$eq(java.lang.Object);
    descriptor: (Ljava/lang/Object;)Z
    flags: (0x0001) ACC_PUBLIC
    Code:
      stack=2, locals=2, args_size=2
         0: aload_0
         1: aload_1
         2: invokestatic  #107                // InterfaceMethod scala/math/Ordered.$less$eq$:(Lscala/math/Ordered;Ljava/lang/Object;)Z
         5: ireturn
      LineNumberTable:
        line 39: 0
      LocalVariableTable:
        Start  Length  Slot  Name   Signature
            0       6     0  this   Lorg/sireum/MessagePack$Kind$EXTENSION$;
            0       6     1  that   Ljava/lang/Object;
    MethodParameters:
      Name                           Flags
      that                           final

  public boolean $greater$eq(java.lang.Object);
    descriptor: (Ljava/lang/Object;)Z
    flags: (0x0001) ACC_PUBLIC
    Code:
      stack=2, locals=2, args_size=2
         0: aload_0
         1: aload_1
         2: invokestatic  #111                // InterfaceMethod scala/math/Ordered.$greater$eq$:(Lscala/math/Ordered;Ljava/lang/Object;)Z
         5: ireturn
      LineNumberTable:
        line 39: 0
      LocalVariableTable:
        Start  Length  Slot  Name   Signature
            0       6     0  this   Lorg/sireum/MessagePack$Kind$EXTENSION$;
            0       6     1  that   Ljava/lang/Object;
    MethodParameters:
      Name                           Flags
      that                           final

  public int compareTo(java.lang.Object);
    descriptor: (Ljava/lang/Object;)I
    flags: (0x0001) ACC_PUBLIC
    Code:
      stack=2, locals=2, args_size=2
         0: aload_0
         1: aload_1
         2: invokestatic  #117                // InterfaceMethod scala/math/Ordered.compareTo$:(Lscala/math/Ordered;Ljava/lang/Object;)I
         5: ireturn
      LineNumberTable:
        line 39: 0
      LocalVariableTable:
        Start  Length  Slot  Name   Signature
            0       6     0  this   Lorg/sireum/MessagePack$Kind$EXTENSION$;
            0       6     1  that   Ljava/lang/Object;
    MethodParameters:
      Name                           Flags
      that                           final

  public final scala.runtime.Nothing$ $cannotMixImmutableAndMutable();
    descriptor: ()Lscala/runtime/Nothing$;
    flags: (0x0011) ACC_PUBLIC, ACC_FINAL
    Code:
      stack=1, locals=1, args_size=1
         0: aload_0
         1: invokestatic  #123                // InterfaceMethod org/sireum/Immutable.$cannotMixImmutableAndMutable$:(Lorg/sireum/Immutable;)Lscala/runtime/Nothing$;
         4: areturn
      LineNumberTable:
        line 39: 0
      LocalVariableTable:
        Start  Length  Slot  Name   Signature
            0       5     0  this   Lorg/sireum/MessagePack$Kind$EXTENSION$;

  public boolean $hasEquals();
    descriptor: ()Z
    flags: (0x0001) ACC_PUBLIC
    Code:
      stack=1, locals=1, args_size=1
         0: aload_0
         1: invokestatic  #129                // InterfaceMethod org/sireum/Immutable.$hasEquals$:(Lorg/sireum/Immutable;)Z
         4: ireturn
      LineNumberTable:
        line 39: 0
      LocalVariableTable:
        Start  Length  Slot  Name   Signature
            0       5     0  this   Lorg/sireum/MessagePack$Kind$EXTENSION$;

  public boolean $hasString();
    descriptor: ()Z
    flags: (0x0001) ACC_PUBLIC
    Code:
      stack=1, locals=1, args_size=1
         0: aload_0
         1: invokestatic  #133                // InterfaceMethod org/sireum/Immutable.$hasString$:(Lorg/sireum/Immutable;)Z
         4: ireturn
      LineNumberTable:
        line 39: 0
      LocalVariableTable:
        Start  Length  Slot  Name   Signature
            0       5     0  this   Lorg/sireum/MessagePack$Kind$EXTENSION$;

  public org.sireum.$internal.ImmutableMarker $clone();
    descriptor: ()Lorg/sireum/$internal/ImmutableMarker;
    flags: (0x0001) ACC_PUBLIC
    Code:
      stack=1, locals=1, args_size=1
         0: aload_0
         1: invokestatic  #139                // InterfaceMethod org/sireum/$internal/ImmutableMarker.$clone$:(Lorg/sireum/$internal/ImmutableMarker;)Lorg/sireum/$internal/ImmutableMarker;
         4: areturn
      LineNumberTable:
        line 39: 0
      LocalVariableTable:
        Start  Length  Slot  Name   Signature
            0       5     0  this   Lorg/sireum/MessagePack$Kind$EXTENSION$;

  public org.sireum.Z ordinal();
    descriptor: ()Lorg/sireum/Z;
    flags: (0x0001) ACC_PUBLIC
    Code:
      stack=2, locals=1, args_size=1
         0: getstatic     #145                // Field org/sireum/Z$.MODULE$:Lorg/sireum/Z$;
         3: bipush        8
         5: invokevirtual #149                // Method org/sireum/Z$.apply:(I)Lorg/sireum/Z;
         8: areturn
      LineNumberTable:
        line 39: 0
      LocalVariableTable:
        Start  Length  Slot  Name   Signature
            0       9     0  this   Lorg/sireum/MessagePack$Kind$EXTENSION$;

  public java.lang.String name();
    descriptor: ()Ljava/lang/String;
    flags: (0x0001) ACC_PUBLIC
    Code:
      stack=2, locals=1, args_size=1
         0: getstatic     #155                // Field org/sireum/String$.MODULE$:Lorg/sireum/String$;
         3: ldc           #157                // String EXTENSION
         5: invokevirtual #160                // Method org/sireum/String$.apply:(Ljava/lang/String;)Ljava/lang/String;
         8: areturn
      LineNumberTable:
        line 39: 0
      LocalVariableTable:
        Start  Length  Slot  Name   Signature
            0       9     0  this   Lorg/sireum/MessagePack$Kind$EXTENSION$;

  public java.lang.String productPrefix();
    descriptor: ()Ljava/lang/String;
    flags: (0x0001) ACC_PUBLIC
    Code:
      stack=1, locals=1, args_size=1
         0: ldc           #157                // String EXTENSION
         2: areturn
      LineNumberTable:
        line 39: 0
      LocalVariableTable:
        Start  Length  Slot  Name   Signature
            0       3     0  this   Lorg/sireum/MessagePack$Kind$EXTENSION$;

  public int productArity();
    descriptor: ()I
    flags: (0x0001) ACC_PUBLIC
    Code:
      stack=1, locals=1, args_size=1
         0: iconst_0
         1: ireturn
      LineNumberTable:
        line 39: 0
      LocalVariableTable:
        Start  Length  Slot  Name   Signature
            0       2     0  this   Lorg/sireum/MessagePack$Kind$EXTENSION$;

  public java.lang.Object productElement(int);
    descriptor: (I)Ljava/lang/Object;
    flags: (0x0001) ACC_PUBLIC
    Code:
      stack=1, locals=4, args_size=2
         0: iload_1
         1: istore_3
         2: iload_1
         3: invokestatic  #171                // Method scala/runtime/Statics.ioobe:(I)Ljava/lang/Object;
         6: astore_2
         7: goto          10
        10: aload_2
        11: areturn
      StackMapTable: number_of_entries = 1
        frame_type = 253 /* append */
          offset_delta = 10
          locals = [ class java/lang/Object, int ]
      LineNumberTable:
        line 39: 0
      LocalVariableTable:
        Start  Length  Slot  Name   Signature
            0      12     0  this   Lorg/sireum/MessagePack$Kind$EXTENSION$;
            0      12     1   x$1   I
    MethodParameters:
      Name                           Flags
      x$1                            final

  public scala.collection.Iterator<java.lang.Object> productIterator();
    descriptor: ()Lscala/collection/Iterator;
    flags: (0x0001) ACC_PUBLIC
    Code:
      stack=2, locals=1, args_size=1
         0: getstatic     #178                // Field scala/runtime/ScalaRunTime$.MODULE$:Lscala/runtime/ScalaRunTime$;
         3: aload_0
         4: invokevirtual #181                // Method scala/runtime/ScalaRunTime$.typedProductIterator:(Lscala/Product;)Lscala/collection/Iterator;
         7: areturn
      LineNumberTable:
        line 39: 0
      LocalVariableTable:
        Start  Length  Slot  Name   Signature
            0       8     0  this   Lorg/sireum/MessagePack$Kind$EXTENSION$;
    Signature: #173                         // ()Lscala/collection/Iterator<Ljava/lang/Object;>;

  public boolean canEqual(java.lang.Object);
    descriptor: (Ljava/lang/Object;)Z
    flags: (0x0001) ACC_PUBLIC
    Code:
      stack=1, locals=2, args_size=2
         0: aload_1
         1: instanceof    #2                  // class org/sireum/MessagePack$Kind$EXTENSION$
         4: ireturn
      LineNumberTable:
        line 39: 0
      LocalVariableTable:
        Start  Length  Slot  Name   Signature
            0       5     0  this   Lorg/sireum/MessagePack$Kind$EXTENSION$;
            0       5     1   x$1   Ljava/lang/Object;
    MethodParameters:
      Name                           Flags
      x$1                            final

  public int hashCode();
    descriptor: ()I
    flags: (0x0001) ACC_PUBLIC
    Code:
      stack=1, locals=1, args_size=1
         0: ldc           #184                // int -2120930273
         2: ireturn
      LineNumberTable:
        line 39: 0
      LocalVariableTable:
        Start  Length  Slot  Name   Signature
            0       3     0  this   Lorg/sireum/MessagePack$Kind$EXTENSION$;

  public java.lang.String toString();
    descriptor: ()Ljava/lang/String;
    flags: (0x0001) ACC_PUBLIC
    Code:
      stack=1, locals=1, args_size=1
         0: ldc           #157                // String EXTENSION
         2: areturn
      LineNumberTable:
        line 39: 0
      LocalVariableTable:
        Start  Length  Slot  Name   Signature
            0       3     0  this   Lorg/sireum/MessagePack$Kind$EXTENSION$;

  private java.lang.Object writeReplace();
    descriptor: ()Ljava/lang/Object;
    flags: (0x0002) ACC_PRIVATE
    Code:
      stack=3, locals=1, args_size=1
         0: new           #189                // class scala/runtime/ModuleSerializationProxy
         3: dup
         4: ldc           #2                  // class org/sireum/MessagePack$Kind$EXTENSION$
         6: invokespecial #192                // Method scala/runtime/ModuleSerializationProxy."<init>":(Ljava/lang/Class;)V
         9: areturn
      LineNumberTable:
        line 39: 0
      LocalVariableTable:
        Start  Length  Slot  Name   Signature
            0      10     0  this   Lorg/sireum/MessagePack$Kind$EXTENSION$;

  public java.lang.Object $clone();
    descriptor: ()Ljava/lang/Object;
    flags: (0x1041) ACC_PUBLIC, ACC_BRIDGE, ACC_SYNTHETIC
    Code:
      stack=1, locals=1, args_size=1
         0: aload_0
         1: invokevirtual #194                // Method $clone:()Lorg/sireum/$internal/ImmutableMarker;
         4: areturn
      LineNumberTable:
        line 39: 0
      LocalVariableTable:
        Start  Length  Slot  Name   Signature
            0       5     0  this   Lorg/sireum/MessagePack$Kind$EXTENSION$;

  public final int compare(java.lang.Object);
    descriptor: (Ljava/lang/Object;)I
    flags: (0x1051) ACC_PUBLIC, ACC_FINAL, ACC_BRIDGE, ACC_SYNTHETIC
    Code:
      stack=2, locals=2, args_size=2
         0: aload_0
         1: aload_1
         2: checkcast     #6                  // class org/sireum/MessagePack$Kind$Type
         5: invokevirtual #196                // Method compare:(Lorg/sireum/MessagePack$Kind$Type;)I
         8: ireturn
      LineNumberTable:
        line 39: 0
      LocalVariableTable:
        Start  Length  Slot  Name   Signature
            0       9     0  this   Lorg/sireum/MessagePack$Kind$EXTENSION$;
            0       9     1  that   Ljava/lang/Object;
    MethodParameters:
      Name                           Flags
      that                           final

  public org.sireum.MessagePack$Kind$EXTENSION$();
    descriptor: ()V
    flags: (0x0001) ACC_PUBLIC
    Code:
      stack=1, locals=1, args_size=1
         0: aload_0
         1: invokespecial #197                // Method java/lang/Object."<init>":()V
         4: return
      LineNumberTable:
        line 39: 0
      LocalVariableTable:
        Start  Length  Slot  Name   Signature
            0       5     0  this   Lorg/sireum/MessagePack$Kind$EXTENSION$;
}
InnerClasses:
  public static #16= #13 of #15;          // Kind$=class org/sireum/MessagePack$Kind$ of class org/sireum/MessagePack
  public static final #17= #2 of #13;     // EXTENSION$=class org/sireum/MessagePack$Kind$EXTENSION$ of class org/sireum/MessagePack$Kind$
  public static #18= #6 of #13;           // Type=class org/sireum/MessagePack$Kind$Type of class org/sireum/MessagePack$Kind$
SourceFile: "MessagePack.scala"
  ScalaInlineInfo: length = 0x90 (unknown attribute)
   01 01 00 1C 00 76 00 77 01 00 86 00 BB 01 00 86
   00 87 01 00 64 00 5E 01 00 6C 00 5E 01 00 7C 00
   7D 01 00 82 00 7D 01 00 5D 00 5E 01 00 68 00 5E
   01 00 17 00 16 01 00 B6 00 5E 01 00 50 00 71 01
   00 50 00 51 01 00 70 00 71 01 00 42 00 43 01 00
   B7 00 A3 01 00 48 00 49 01 00 96 00 58 01 00 8C
   00 43 01 00 A2 00 A3 01 00 A4 00 A5 01 00 32 00
   33 01 00 3B 00 3C 01 00 AC 00 3C 01 00 A1 00 58
   01 00 57 00 58 01 00 B9 00 58 01 00 BA 00 BB 01

  Scala: length = 0x0 (unknown attribute)

