Classfile /Users/mw/Projects/slang-braindump/.jar/jar11/assemble/slang-braindump/assemble/content/org/sireum/MNone$.class
  Last modified May 29, 2022; size 878 bytes
  SHA-256 checksum 0c36bb0ea57476dd8ab3f1b233c585a6d9ebf0aa83c764898ae345b1d9c3ce5c
  Compiled from "MOption.scala"
public final class org.sireum.MNone$
  minor version: 0
  major version: 52
  flags: (0x0031) ACC_PUBLIC, ACC_FINAL, ACC_SUPER
  this_class: #2                          // org/sireum/MNone$
  super_class: #4                         // java/lang/Object
  interfaces: 0, fields: 2, methods: 4, attributes: 3
Constant pool:
   #1 = Utf8               org/sireum/MNone$
   #2 = Class              #1             // org/sireum/MNone$
   #3 = Utf8               java/lang/Object
   #4 = Class              #3             // java/lang/Object
   #5 = Utf8               MOption.scala
   #6 = Utf8               MODULE$
   #7 = Utf8               Lorg/sireum/MNone$;
   #8 = Utf8               $v
   #9 = Utf8               Ljava/lang/Object;
  #10 = Utf8               <clinit>
  #11 = Utf8               ()V
  #12 = Utf8               <init>
  #13 = NameAndType        #12:#11        // "<init>":()V
  #14 = Methodref          #2.#13         // org/sireum/MNone$."<init>":()V
  #15 = NameAndType        #6:#7          // MODULE$:Lorg/sireum/MNone$;
  #16 = Fieldref           #2.#15         // org/sireum/MNone$.MODULE$:Lorg/sireum/MNone$;
  #17 = Utf8               org/sireum/MNone
  #18 = Class              #17            // org/sireum/MNone
  #19 = Methodref          #18.#13        // org/sireum/MNone."<init>":()V
  #20 = NameAndType        #8:#9          // $v:Ljava/lang/Object;
  #21 = Fieldref           #2.#20         // org/sireum/MNone$.$v:Ljava/lang/Object;
  #22 = Utf8               apply
  #23 = Utf8               ()Lorg/sireum/MNone;
  #24 = Utf8               <T:Ljava/lang/Object;>()Lorg/sireum/MNone<TT;>;
  #25 = Utf8               this
  #26 = Utf8               unapply
  #27 = Utf8               (Lorg/sireum/MNone;)Z
  #28 = Utf8               <T:Ljava/lang/Object;>(Lorg/sireum/MNone<TT;>;)Z
  #29 = Utf8               o
  #30 = Utf8               Lorg/sireum/MNone;
  #31 = Methodref          #4.#13         // java/lang/Object."<init>":()V
  #32 = Utf8               Code
  #33 = Utf8               LineNumberTable
  #34 = Utf8               LocalVariableTable
  #35 = Utf8               Signature
  #36 = Utf8               MethodParameters
  #37 = Utf8               SourceFile
  #38 = Utf8               ScalaInlineInfo
  #39 = Utf8               Scala
{
  public static final org.sireum.MNone$ MODULE$;
    descriptor: Lorg/sireum/MNone$;
    flags: (0x0019) ACC_PUBLIC, ACC_STATIC, ACC_FINAL

  private static final java.lang.Object $v;
    descriptor: Ljava/lang/Object;
    flags: (0x001a) ACC_PRIVATE, ACC_STATIC, ACC_FINAL

  public static {};
    descriptor: ()V
    flags: (0x0009) ACC_PUBLIC, ACC_STATIC
    Code:
      stack=2, locals=0, args_size=0
         0: new           #2                  // class org/sireum/MNone$
         3: dup
         4: invokespecial #14                 // Method "<init>":()V
         7: putstatic     #16                 // Field MODULE$:Lorg/sireum/MNone$;
        10: new           #18                 // class org/sireum/MNone
        13: dup
        14: invokespecial #19                 // Method org/sireum/MNone."<init>":()V
        17: putstatic     #21                 // Field $v:Ljava/lang/Object;
        20: return
      LineNumberTable:
        line 146: 0

  public <T extends java.lang.Object> org.sireum.MNone<T> apply();
    descriptor: ()Lorg/sireum/MNone;
    flags: (0x0001) ACC_PUBLIC
    Code:
      stack=1, locals=1, args_size=1
         0: getstatic     #21                 // Field $v:Ljava/lang/Object;
         3: checkcast     #18                 // class org/sireum/MNone
         6: areturn
      LineNumberTable:
        line 146: 0
      LocalVariableTable:
        Start  Length  Slot  Name   Signature
            0       7     0  this   Lorg/sireum/MNone$;
    Signature: #24                          // <T:Ljava/lang/Object;>()Lorg/sireum/MNone<TT;>;

  public <T extends java.lang.Object> boolean unapply(org.sireum.MNone<T>);
    descriptor: (Lorg/sireum/MNone;)Z
    flags: (0x0001) ACC_PUBLIC
    Code:
      stack=1, locals=2, args_size=2
         0: iconst_1
         1: ireturn
      LineNumberTable:
        line 146: 0
      LocalVariableTable:
        Start  Length  Slot  Name   Signature
            0       2     0  this   Lorg/sireum/MNone$;
            0       2     1     o   Lorg/sireum/MNone;
    Signature: #28                          // <T:Ljava/lang/Object;>(Lorg/sireum/MNone<TT;>;)Z
    MethodParameters:
      Name                           Flags
      o                              final

  private org.sireum.MNone$();
    descriptor: ()V
    flags: (0x0002) ACC_PRIVATE
    Code:
      stack=1, locals=1, args_size=1
         0: aload_0
         1: invokespecial #31                 // Method java/lang/Object."<init>":()V
         4: return
      LineNumberTable:
        line 146: 0
      LocalVariableTable:
        Start  Length  Slot  Name   Signature
            0       5     0  this   Lorg/sireum/MNone$;
}
SourceFile: "MOption.scala"
  ScalaInlineInfo: length = 0x13 (unknown attribute)
   01 01 00 03 00 0C 00 0B 01 00 16 00 17 01 00 1A
   00 1B 01
  Scala: length = 0x0 (unknown attribute)

