Classfile /Users/mw/Projects/slang-braindump/.jar/jar11/assemble/slang-braindump/assemble/content/org/sireum/Os$Path$WriteMode$Type.class
  Last modified May 29, 2022; size 2494 bytes
  SHA-256 checksum 4b7506c8c1ecb2a79e59a363b0c2f4b1cc47d0e57671aaeacb1abc538af83312
  Compiled from "Os.scala"
public interface org.sireum.Os$Path$WriteMode$Type extends org.sireum.Immutable, scala.math.Ordered<org.sireum.Os$Path$WriteMode$Type>
  minor version: 0
  major version: 52
  flags: (0x0601) ACC_PUBLIC, ACC_INTERFACE, ACC_ABSTRACT
  this_class: #2                          // org/sireum/Os$Path$WriteMode$Type
  super_class: #5                         // java/lang/Object
  interfaces: 2, fields: 0, methods: 11, attributes: 5
Constant pool:
    #1 = Utf8               org/sireum/Os$Path$WriteMode$Type
    #2 = Class              #1            // org/sireum/Os$Path$WriteMode$Type
    #3 = Utf8               Ljava/lang/Object;Lorg/sireum/Immutable;Lscala/math/Ordered<Lorg/sireum/Os$Path$WriteMode$Type;>;
    #4 = Utf8               java/lang/Object
    #5 = Class              #4            // java/lang/Object
    #6 = Utf8               org/sireum/Immutable
    #7 = Class              #6            // org/sireum/Immutable
    #8 = Utf8               scala/math/Ordered
    #9 = Class              #8            // scala/math/Ordered
   #10 = Utf8               Os.scala
   #11 = Utf8               org/sireum/Os$Path$
   #12 = Class              #11           // org/sireum/Os$Path$
   #13 = Utf8               org/sireum/Os
   #14 = Class              #13           // org/sireum/Os
   #15 = Utf8               Path$
   #16 = Utf8               org/sireum/Os$Path$WriteMode$
   #17 = Class              #16           // org/sireum/Os$Path$WriteMode$
   #18 = Utf8               WriteMode$
   #19 = Utf8               Type
   #20 = Utf8               ordinal
   #21 = Utf8               ()Lorg/sireum/Z;
   #22 = Utf8               name
   #23 = Utf8               ()Ljava/lang/String;
   #24 = Utf8               hash$
   #25 = Utf8               (Lorg/sireum/Os$Path$WriteMode$Type;)Lorg/sireum/Z;
   #26 = Utf8               $this
   #27 = Utf8               hash
   #28 = NameAndType        #27:#21       // hash:()Lorg/sireum/Z;
   #29 = InterfaceMethodref #2.#28        // org/sireum/Os$Path$WriteMode$Type.hash:()Lorg/sireum/Z;
   #30 = Utf8               Lorg/sireum/Os$Path$WriteMode$Type;
   #31 = Utf8               org/sireum/Z$
   #32 = Class              #31           // org/sireum/Z$
   #33 = Utf8               MODULE$
   #34 = Utf8               Lorg/sireum/Z$;
   #35 = NameAndType        #33:#34       // MODULE$:Lorg/sireum/Z$;
   #36 = Fieldref           #32.#35       // org/sireum/Z$.MODULE$:Lorg/sireum/Z$;
   #37 = Utf8               hashCode
   #38 = Utf8               ()I
   #39 = NameAndType        #37:#38       // hashCode:()I
   #40 = Methodref          #5.#39        // java/lang/Object.hashCode:()I
   #41 = Utf8               apply
   #42 = Utf8               (I)Lorg/sireum/Z;
   #43 = NameAndType        #41:#42       // apply:(I)Lorg/sireum/Z;
   #44 = Methodref          #32.#43       // org/sireum/Z$.apply:(I)Lorg/sireum/Z;
   #45 = Utf8               this
   #46 = Utf8               isEqual$
   #47 = Utf8               (Lorg/sireum/Os$Path$WriteMode$Type;Lorg/sireum/Os$Path$WriteMode$Type;)Z
   #48 = Utf8               other
   #49 = Utf8               isEqual
   #50 = Utf8               (Lorg/sireum/Os$Path$WriteMode$Type;)Z
   #51 = NameAndType        #49:#50       // isEqual:(Lorg/sireum/Os$Path$WriteMode$Type;)Z
   #52 = InterfaceMethodref #2.#51        // org/sireum/Os$Path$WriteMode$Type.isEqual:(Lorg/sireum/Os$Path$WriteMode$Type;)Z
   #53 = Utf8               org/sireum/B$
   #54 = Class              #53           // org/sireum/B$
   #55 = Utf8               Lorg/sireum/B$;
   #56 = NameAndType        #33:#55       // MODULE$:Lorg/sireum/B$;
   #57 = Fieldref           #54.#56       // org/sireum/B$.MODULE$:Lorg/sireum/B$;
   #58 = Utf8               equals
   #59 = Utf8               (Ljava/lang/Object;)Z
   #60 = NameAndType        #58:#59       // equals:(Ljava/lang/Object;)Z
   #61 = Methodref          #5.#60        // java/lang/Object.equals:(Ljava/lang/Object;)Z
   #62 = Utf8               (Z)Z
   #63 = NameAndType        #41:#62       // apply:(Z)Z
   #64 = Methodref          #54.#63       // org/sireum/B$.apply:(Z)Z
   #65 = Utf8               compare$
   #66 = Utf8               (Lorg/sireum/Os$Path$WriteMode$Type;Lorg/sireum/Os$Path$WriteMode$Type;)I
   #67 = Utf8               that
   #68 = Utf8               compare
   #69 = Utf8               (Lorg/sireum/Os$Path$WriteMode$Type;)I
   #70 = NameAndType        #68:#69       // compare:(Lorg/sireum/Os$Path$WriteMode$Type;)I
   #71 = InterfaceMethodref #2.#70        // org/sireum/Os$Path$WriteMode$Type.compare:(Lorg/sireum/Os$Path$WriteMode$Type;)I
   #72 = NameAndType        #20:#21       // ordinal:()Lorg/sireum/Z;
   #73 = InterfaceMethodref #2.#72        // org/sireum/Os$Path$WriteMode$Type.ordinal:()Lorg/sireum/Z;
   #74 = Utf8               org/sireum/Z
   #75 = Class              #74           // org/sireum/Z
   #76 = Utf8               compareTo
   #77 = Utf8               (Lorg/sireum/ZLike;)I
   #78 = NameAndType        #76:#77       // compareTo:(Lorg/sireum/ZLike;)I
   #79 = InterfaceMethodref #75.#78       // org/sireum/Z.compareTo:(Lorg/sireum/ZLike;)I
   #80 = Utf8               string$
   #81 = Utf8               (Lorg/sireum/Os$Path$WriteMode$Type;)Ljava/lang/String;
   #82 = Utf8               string
   #83 = NameAndType        #82:#23       // string:()Ljava/lang/String;
   #84 = InterfaceMethodref #2.#83        // org/sireum/Os$Path$WriteMode$Type.string:()Ljava/lang/String;
   #85 = Utf8               org/sireum/String$
   #86 = Class              #85           // org/sireum/String$
   #87 = Utf8               Lorg/sireum/String$;
   #88 = NameAndType        #33:#87       // MODULE$:Lorg/sireum/String$;
   #89 = Fieldref           #86.#88       // org/sireum/String$.MODULE$:Lorg/sireum/String$;
   #90 = Utf8               toString
   #91 = NameAndType        #90:#23       // toString:()Ljava/lang/String;
   #92 = Methodref          #5.#91        // java/lang/Object.toString:()Ljava/lang/String;
   #93 = Utf8               (Ljava/lang/String;)Ljava/lang/String;
   #94 = NameAndType        #41:#93       // apply:(Ljava/lang/String;)Ljava/lang/String;
   #95 = Methodref          #86.#94       // org/sireum/String$.apply:(Ljava/lang/String;)Ljava/lang/String;
   #96 = Utf8               $init$
   #97 = Utf8               (Lorg/sireum/Os$Path$WriteMode$Type;)V
   #98 = Utf8               Code
   #99 = Utf8               LineNumberTable
  #100 = Utf8               LocalVariableTable
  #101 = Utf8               MethodParameters
  #102 = Utf8               StackMapTable
  #103 = Utf8               InnerClasses
  #104 = Utf8               Signature
  #105 = Utf8               SourceFile
  #106 = Utf8               ScalaInlineInfo
  #107 = Utf8               Scala
{
  public abstract org.sireum.Z ordinal();
    descriptor: ()Lorg/sireum/Z;
    flags: (0x0401) ACC_PUBLIC, ACC_ABSTRACT

  public abstract java.lang.String name();
    descriptor: ()Ljava/lang/String;
    flags: (0x0401) ACC_PUBLIC, ACC_ABSTRACT

  public static org.sireum.Z hash$(org.sireum.Os$Path$WriteMode$Type);
    descriptor: (Lorg/sireum/Os$Path$WriteMode$Type;)Lorg/sireum/Z;
    flags: (0x1009) ACC_PUBLIC, ACC_STATIC, ACC_SYNTHETIC
    Code:
      stack=1, locals=1, args_size=1
         0: aload_0
         1: invokespecial #29                 // InterfaceMethod hash:()Lorg/sireum/Z;
         4: areturn
      LineNumberTable:
        line 166: 0
      LocalVariableTable:
        Start  Length  Slot  Name   Signature
            0       5     0 $this   Lorg/sireum/Os$Path$WriteMode$Type;
    MethodParameters:
      Name                           Flags
      $this                          final synthetic

  public default org.sireum.Z hash();
    descriptor: ()Lorg/sireum/Z;
    flags: (0x0001) ACC_PUBLIC
    Code:
      stack=2, locals=1, args_size=1
         0: getstatic     #36                 // Field org/sireum/Z$.MODULE$:Lorg/sireum/Z$;
         3: aload_0
         4: invokevirtual #40                 // Method java/lang/Object.hashCode:()I
         7: invokevirtual #44                 // Method org/sireum/Z$.apply:(I)Lorg/sireum/Z;
        10: areturn
      LineNumberTable:
        line 166: 0
      LocalVariableTable:
        Start  Length  Slot  Name   Signature
            0      11     0  this   Lorg/sireum/Os$Path$WriteMode$Type;

  public static boolean isEqual$(org.sireum.Os$Path$WriteMode$Type, org.sireum.Os$Path$WriteMode$Type);
    descriptor: (Lorg/sireum/Os$Path$WriteMode$Type;Lorg/sireum/Os$Path$WriteMode$Type;)Z
    flags: (0x1009) ACC_PUBLIC, ACC_STATIC, ACC_SYNTHETIC
    Code:
      stack=2, locals=2, args_size=2
         0: aload_0
         1: aload_1
         2: invokespecial #52                 // InterfaceMethod isEqual:(Lorg/sireum/Os$Path$WriteMode$Type;)Z
         5: ireturn
      LineNumberTable:
        line 166: 0
      LocalVariableTable:
        Start  Length  Slot  Name   Signature
            0       6     0 $this   Lorg/sireum/Os$Path$WriteMode$Type;
            0       6     1 other   Lorg/sireum/Os$Path$WriteMode$Type;
    MethodParameters:
      Name                           Flags
      $this                          final synthetic
      other                          final

  public default boolean isEqual(org.sireum.Os$Path$WriteMode$Type);
    descriptor: (Lorg/sireum/Os$Path$WriteMode$Type;)Z
    flags: (0x0001) ACC_PUBLIC
    Code:
      stack=3, locals=3, args_size=2
         0: getstatic     #57                 // Field org/sireum/B$.MODULE$:Lorg/sireum/B$;
         3: aload_0
         4: aload_1
         5: astore_2
         6: dup
         7: ifnonnull     18
        10: pop
        11: aload_2
        12: ifnull        25
        15: goto          29
        18: aload_2
        19: invokevirtual #61                 // Method java/lang/Object.equals:(Ljava/lang/Object;)Z
        22: ifeq          29
        25: iconst_1
        26: goto          30
        29: iconst_0
        30: invokevirtual #64                 // Method org/sireum/B$.apply:(Z)Z
        33: ireturn
      StackMapTable: number_of_entries = 4
        frame_type = 255 /* full_frame */
          offset_delta = 18
          locals = [ class org/sireum/Os$Path$WriteMode$Type, class org/sireum/Os$Path$WriteMode$Type, class org/sireum/Os$Path$WriteMode$Type ]
          stack = [ class org/sireum/B$, class org/sireum/Os$Path$WriteMode$Type ]
        frame_type = 70 /* same_locals_1_stack_item */
          stack = [ class org/sireum/B$ ]
        frame_type = 67 /* same_locals_1_stack_item */
          stack = [ class org/sireum/B$ ]
        frame_type = 255 /* full_frame */
          offset_delta = 0
          locals = [ class org/sireum/Os$Path$WriteMode$Type, class org/sireum/Os$Path$WriteMode$Type, class org/sireum/Os$Path$WriteMode$Type ]
          stack = [ class org/sireum/B$, int ]
      LineNumberTable:
        line 166: 0
      LocalVariableTable:
        Start  Length  Slot  Name   Signature
            0      34     0  this   Lorg/sireum/Os$Path$WriteMode$Type;
            0      34     1 other   Lorg/sireum/Os$Path$WriteMode$Type;
    MethodParameters:
      Name                           Flags
      other                          final

  public static int compare$(org.sireum.Os$Path$WriteMode$Type, org.sireum.Os$Path$WriteMode$Type);
    descriptor: (Lorg/sireum/Os$Path$WriteMode$Type;Lorg/sireum/Os$Path$WriteMode$Type;)I
    flags: (0x1009) ACC_PUBLIC, ACC_STATIC, ACC_SYNTHETIC
    Code:
      stack=2, locals=2, args_size=2
         0: aload_0
         1: aload_1
         2: invokespecial #71                 // InterfaceMethod compare:(Lorg/sireum/Os$Path$WriteMode$Type;)I
         5: ireturn
      LineNumberTable:
        line 166: 0
      LocalVariableTable:
        Start  Length  Slot  Name   Signature
            0       6     0 $this   Lorg/sireum/Os$Path$WriteMode$Type;
            0       6     1  that   Lorg/sireum/Os$Path$WriteMode$Type;
    MethodParameters:
      Name                           Flags
      $this                          final synthetic
      that                           final

  public default int compare(org.sireum.Os$Path$WriteMode$Type);
    descriptor: (Lorg/sireum/Os$Path$WriteMode$Type;)I
    flags: (0x0001) ACC_PUBLIC
    Code:
      stack=2, locals=2, args_size=2
         0: aload_0
         1: invokeinterface #73,  1           // InterfaceMethod ordinal:()Lorg/sireum/Z;
         6: aload_1
         7: invokeinterface #73,  1           // InterfaceMethod ordinal:()Lorg/sireum/Z;
        12: invokeinterface #79,  2           // InterfaceMethod org/sireum/Z.compareTo:(Lorg/sireum/ZLike;)I
        17: ireturn
      LineNumberTable:
        line 166: 0
      LocalVariableTable:
        Start  Length  Slot  Name   Signature
            0      18     0  this   Lorg/sireum/Os$Path$WriteMode$Type;
            0      18     1  that   Lorg/sireum/Os$Path$WriteMode$Type;
    MethodParameters:
      Name                           Flags
      that                           final

  public static java.lang.String string$(org.sireum.Os$Path$WriteMode$Type);
    descriptor: (Lorg/sireum/Os$Path$WriteMode$Type;)Ljava/lang/String;
    flags: (0x1009) ACC_PUBLIC, ACC_STATIC, ACC_SYNTHETIC
    Code:
      stack=1, locals=1, args_size=1
         0: aload_0
         1: invokespecial #84                 // InterfaceMethod string:()Ljava/lang/String;
         4: areturn
      LineNumberTable:
        line 166: 0
      LocalVariableTable:
        Start  Length  Slot  Name   Signature
            0       5     0 $this   Lorg/sireum/Os$Path$WriteMode$Type;
    MethodParameters:
      Name                           Flags
      $this                          final synthetic

  public default java.lang.String string();
    descriptor: ()Ljava/lang/String;
    flags: (0x0001) ACC_PUBLIC
    Code:
      stack=2, locals=1, args_size=1
         0: getstatic     #89                 // Field org/sireum/String$.MODULE$:Lorg/sireum/String$;
         3: aload_0
         4: invokevirtual #92                 // Method java/lang/Object.toString:()Ljava/lang/String;
         7: invokevirtual #95                 // Method org/sireum/String$.apply:(Ljava/lang/String;)Ljava/lang/String;
        10: areturn
      LineNumberTable:
        line 166: 0
      LocalVariableTable:
        Start  Length  Slot  Name   Signature
            0      11     0  this   Lorg/sireum/Os$Path$WriteMode$Type;

  public static void $init$(org.sireum.Os$Path$WriteMode$Type);
    descriptor: (Lorg/sireum/Os$Path$WriteMode$Type;)V
    flags: (0x0009) ACC_PUBLIC, ACC_STATIC
    Code:
      stack=0, locals=1, args_size=1
         0: return
      LineNumberTable:
        line 166: 0
      LocalVariableTable:
        Start  Length  Slot  Name   Signature
            0       1     0 $this   Lorg/sireum/Os$Path$WriteMode$Type;
    MethodParameters:
      Name                           Flags
      $this                          final synthetic
}
InnerClasses:
  public static #15= #12 of #14;          // Path$=class org/sireum/Os$Path$ of class org/sireum/Os
  public static #18= #17 of #12;          // WriteMode$=class org/sireum/Os$Path$WriteMode$ of class org/sireum/Os$Path$
  public static #19= #2 of #17;           // Type=class org/sireum/Os$Path$WriteMode$Type of class org/sireum/Os$Path$WriteMode$
Signature: #3                           // Ljava/lang/Object;Lorg/sireum/Immutable;Lscala/math/Ordered<Lorg/sireum/Os$Path$WriteMode$Type;>;
SourceFile: "Os.scala"
  ScalaInlineInfo: length = 0x3B (unknown attribute)
   01 00 00 0B 00 60 00 61 01 00 44 00 45 01 00 41
   00 42 01 00 1B 00 15 01 00 18 00 19 01 00 31 00
   32 01 00 2E 00 2F 01 00 16 00 17 00 00 14 00 15
   00 00 52 00 17 01 00 50 00 51 01
  Scala: length = 0x0 (unknown attribute)

