Classfile /Users/mw/Projects/slang-braindump/.jar/jar11/assemble/slang-braindump/assemble/content/org/sireum/package$Any2HashString$.class
  Last modified May 29, 2022; size 1712 bytes
  SHA-256 checksum fa9e0ac3f88c0a52bc6073b483040849a3abcfc8a4d8fce3231ec93ac27a6316
  Compiled from "package.scala"
public class org.sireum.package$Any2HashString$
  minor version: 0
  major version: 52
  flags: (0x0021) ACC_PUBLIC, ACC_SUPER
  this_class: #2                          // org/sireum/package$Any2HashString$
  super_class: #4                         // java/lang/Object
  interfaces: 0, fields: 1, methods: 6, attributes: 4
Constant pool:
   #1 = Utf8               org/sireum/package$Any2HashString$
   #2 = Class              #1             // org/sireum/package$Any2HashString$
   #3 = Utf8               java/lang/Object
   #4 = Class              #3             // java/lang/Object
   #5 = Utf8               package.scala
   #6 = Utf8               org/sireum/package$Any2HashString
   #7 = Class              #6             // org/sireum/package$Any2HashString
   #8 = Utf8               org/sireum/package
   #9 = Class              #8             // org/sireum/package
  #10 = Utf8               Any2HashString
  #11 = Utf8               Any2HashString$
  #12 = Utf8               MODULE$
  #13 = Utf8               Lorg/sireum/package$Any2HashString$;
  #14 = Utf8               <clinit>
  #15 = Utf8               ()V
  #16 = Utf8               <init>
  #17 = NameAndType        #16:#15        // "<init>":()V
  #18 = Methodref          #2.#17         // org/sireum/package$Any2HashString$."<init>":()V
  #19 = NameAndType        #12:#13        // MODULE$:Lorg/sireum/package$Any2HashString$;
  #20 = Fieldref           #2.#19         // org/sireum/package$Any2HashString$.MODULE$:Lorg/sireum/package$Any2HashString$;
  #21 = Utf8               hash$extension
  #22 = Utf8               (Ljava/lang/Object;)Lorg/sireum/Z;
  #23 = Utf8               $this
  #24 = Utf8               org/sireum/Z$
  #25 = Class              #24            // org/sireum/Z$
  #26 = Utf8               Lorg/sireum/Z$;
  #27 = NameAndType        #12:#26        // MODULE$:Lorg/sireum/Z$;
  #28 = Fieldref           #25.#27        // org/sireum/Z$.MODULE$:Lorg/sireum/Z$;
  #29 = Utf8               hashCode
  #30 = Utf8               ()I
  #31 = NameAndType        #29:#30        // hashCode:()I
  #32 = Methodref          #4.#31         // java/lang/Object.hashCode:()I
  #33 = Utf8               apply
  #34 = Utf8               (I)Lorg/sireum/Z;
  #35 = NameAndType        #33:#34        // apply:(I)Lorg/sireum/Z;
  #36 = Methodref          #25.#35        // org/sireum/Z$.apply:(I)Lorg/sireum/Z;
  #37 = Utf8               this
  #38 = Utf8               Ljava/lang/Object;
  #39 = Utf8               string$extension
  #40 = Utf8               (Ljava/lang/Object;)Ljava/lang/String;
  #41 = Utf8               org/sireum/String$
  #42 = Class              #41            // org/sireum/String$
  #43 = Utf8               Lorg/sireum/String$;
  #44 = NameAndType        #12:#43        // MODULE$:Lorg/sireum/String$;
  #45 = Fieldref           #42.#44        // org/sireum/String$.MODULE$:Lorg/sireum/String$;
  #46 = Utf8               toString
  #47 = Utf8               ()Ljava/lang/String;
  #48 = NameAndType        #46:#47        // toString:()Ljava/lang/String;
  #49 = Methodref          #4.#48         // java/lang/Object.toString:()Ljava/lang/String;
  #50 = Utf8               (Ljava/lang/String;)Ljava/lang/String;
  #51 = NameAndType        #33:#50        // apply:(Ljava/lang/String;)Ljava/lang/String;
  #52 = Methodref          #42.#51        // org/sireum/String$.apply:(Ljava/lang/String;)Ljava/lang/String;
  #53 = Utf8               hashCode$extension
  #54 = Utf8               (Ljava/lang/Object;)I
  #55 = Utf8               equals$extension
  #56 = Utf8               (Ljava/lang/Object;Ljava/lang/Object;)Z
  #57 = Utf8               x$1
  #58 = Utf8               _o
  #59 = Utf8               ()Ljava/lang/Object;
  #60 = NameAndType        #58:#59        // _o:()Ljava/lang/Object;
  #61 = Methodref          #7.#60         // org/sireum/package$Any2HashString._o:()Ljava/lang/Object;
  #62 = Utf8               scala/runtime/BoxesRunTime
  #63 = Class              #62            // scala/runtime/BoxesRunTime
  #64 = Utf8               equals
  #65 = NameAndType        #64:#56        // equals:(Ljava/lang/Object;Ljava/lang/Object;)Z
  #66 = Methodref          #63.#65        // scala/runtime/BoxesRunTime.equals:(Ljava/lang/Object;Ljava/lang/Object;)Z
  #67 = Methodref          #4.#17         // java/lang/Object."<init>":()V
  #68 = Utf8               Code
  #69 = Utf8               LineNumberTable
  #70 = Utf8               LocalVariableTable
  #71 = Utf8               MethodParameters
  #72 = Utf8               StackMapTable
  #73 = Utf8               InnerClasses
  #74 = Utf8               SourceFile
  #75 = Utf8               ScalaInlineInfo
  #76 = Utf8               Scala
{
  public static final org.sireum.package$Any2HashString$ MODULE$;
    descriptor: Lorg/sireum/package$Any2HashString$;
    flags: (0x0019) ACC_PUBLIC, ACC_STATIC, ACC_FINAL

  public static {};
    descriptor: ()V
    flags: (0x0009) ACC_PUBLIC, ACC_STATIC
    Code:
      stack=2, locals=0, args_size=0
         0: new           #2                  // class org/sireum/package$Any2HashString$
         3: dup
         4: invokespecial #18                 // Method "<init>":()V
         7: putstatic     #20                 // Field MODULE$:Lorg/sireum/package$Any2HashString$;
        10: return
      LineNumberTable:
        line 122: 0

  public final org.sireum.Z hash$extension(java.lang.Object);
    descriptor: (Ljava/lang/Object;)Lorg/sireum/Z;
    flags: (0x0011) ACC_PUBLIC, ACC_FINAL
    Code:
      stack=2, locals=2, args_size=2
         0: getstatic     #28                 // Field org/sireum/Z$.MODULE$:Lorg/sireum/Z$;
         3: aload_1
         4: invokevirtual #32                 // Method java/lang/Object.hashCode:()I
         7: invokevirtual #36                 // Method org/sireum/Z$.apply:(I)Lorg/sireum/Z;
        10: areturn
      LineNumberTable:
        line 123: 0
      LocalVariableTable:
        Start  Length  Slot  Name   Signature
            0      11     0  this   Lorg/sireum/package$Any2HashString$;
            0      11     1 $this   Ljava/lang/Object;
    MethodParameters:
      Name                           Flags
      $this                          final

  public final java.lang.String string$extension(java.lang.Object);
    descriptor: (Ljava/lang/Object;)Ljava/lang/String;
    flags: (0x0011) ACC_PUBLIC, ACC_FINAL
    Code:
      stack=2, locals=2, args_size=2
         0: getstatic     #45                 // Field org/sireum/String$.MODULE$:Lorg/sireum/String$;
         3: aload_1
         4: invokevirtual #49                 // Method java/lang/Object.toString:()Ljava/lang/String;
         7: invokevirtual #52                 // Method org/sireum/String$.apply:(Ljava/lang/String;)Ljava/lang/String;
        10: areturn
      LineNumberTable:
        line 124: 0
      LocalVariableTable:
        Start  Length  Slot  Name   Signature
            0      11     0  this   Lorg/sireum/package$Any2HashString$;
            0      11     1 $this   Ljava/lang/Object;
    MethodParameters:
      Name                           Flags
      $this                          final

  public final int hashCode$extension(java.lang.Object);
    descriptor: (Ljava/lang/Object;)I
    flags: (0x0011) ACC_PUBLIC, ACC_FINAL
    Code:
      stack=1, locals=2, args_size=2
         0: aload_1
         1: invokevirtual #32                 // Method java/lang/Object.hashCode:()I
         4: ireturn
      LineNumberTable:
        line 122: 0
      LocalVariableTable:
        Start  Length  Slot  Name   Signature
            0       5     0  this   Lorg/sireum/package$Any2HashString$;
            0       5     1 $this   Ljava/lang/Object;
    MethodParameters:
      Name                           Flags
      $this                          final

  public final boolean equals$extension(java.lang.Object, java.lang.Object);
    descriptor: (Ljava/lang/Object;Ljava/lang/Object;)Z
    flags: (0x0011) ACC_PUBLIC, ACC_FINAL
    Code:
      stack=2, locals=6, args_size=3
         0: aload_2
         1: astore        4
         3: aload         4
         5: instanceof    #7                  // class org/sireum/package$Any2HashString
         8: ifeq          16
        11: iconst_1
        12: istore_3
        13: goto          24
        16: goto          19
        19: iconst_0
        20: istore_3
        21: goto          24
        24: iload_3
        25: ifeq          66
        28: aload_2
        29: ifnonnull     36
        32: aconst_null
        33: goto          43
        36: aload_2
        37: checkcast     #7                  // class org/sireum/package$Any2HashString
        40: invokevirtual #61                 // Method org/sireum/package$Any2HashString._o:()Ljava/lang/Object;
        43: astore        5
        45: aload_1
        46: aload         5
        48: invokestatic  #66                 // Method scala/runtime/BoxesRunTime.equals:(Ljava/lang/Object;Ljava/lang/Object;)Z
        51: ifeq          58
        54: iconst_1
        55: goto          59
        58: iconst_0
        59: ifeq          66
        62: iconst_1
        63: goto          67
        66: iconst_0
        67: ireturn
      StackMapTable: number_of_entries = 9
        frame_type = 253 /* append */
          offset_delta = 16
          locals = [ top, class java/lang/Object ]
        frame_type = 2 /* same */
        frame_type = 255 /* full_frame */
          offset_delta = 4
          locals = [ class org/sireum/package$Any2HashString$, class java/lang/Object, class java/lang/Object, int, class java/lang/Object ]
          stack = []
        frame_type = 11 /* same */
        frame_type = 70 /* same_locals_1_stack_item */
          stack = [ class java/lang/Object ]
        frame_type = 252 /* append */
          offset_delta = 14
          locals = [ class java/lang/Object ]
        frame_type = 64 /* same_locals_1_stack_item */
          stack = [ int ]
        frame_type = 250 /* chop */
          offset_delta = 6
        frame_type = 64 /* same_locals_1_stack_item */
          stack = [ int ]
      LineNumberTable:
        line 122: 0
      LocalVariableTable:
        Start  Length  Slot  Name   Signature
            0      68     0  this   Lorg/sireum/package$Any2HashString$;
            0      68     1 $this   Ljava/lang/Object;
            0      68     2   x$1   Ljava/lang/Object;
    MethodParameters:
      Name                           Flags
      $this                          final
      x$1                            final

  public org.sireum.package$Any2HashString$();
    descriptor: ()V
    flags: (0x0001) ACC_PUBLIC
    Code:
      stack=1, locals=1, args_size=1
         0: aload_0
         1: invokespecial #67                 // Method java/lang/Object."<init>":()V
         4: return
      LineNumberTable:
        line 122: 0
      LocalVariableTable:
        Start  Length  Slot  Name   Signature
            0       5     0  this   Lorg/sireum/package$Any2HashString$;
}
InnerClasses:
  public static final #10= #7 of #9;      // Any2HashString=class org/sireum/package$Any2HashString of class org/sireum/package
  public static #11= #2 of #9;            // Any2HashString$=class org/sireum/package$Any2HashString$ of class org/sireum/package
SourceFile: "package.scala"
  ScalaInlineInfo: length = 0x1D (unknown attribute)
   01 01 00 05 00 10 00 0F 01 00 37 00 38 01 00 15
   00 16 01 00 35 00 36 01 00 27 00 28 01
  Scala: length = 0x0 (unknown attribute)

